{
  "type": "Feature",
  "properties": {
    "iso:country":"CA",
    "sg:address":"1607 Pembina Hwy",
    "sg:city":"Winnipeg",
    "sg:classifiers":[
        {
            "category":"Restaurant",
            "type":"Food & Drink"
        }
    ],
    "sg:phone":"+1 204 453 5241",
    "sg:postcode":"R3T 3Y6",
    "sg:province":"MB",
    "wof:name":"Szechuan Restaurant",
    "wof:placetype":"venue"
},
  "geometry": {"coordinates":[-97.15143585209999,49.8315658569],"type":"Point"}
}