{
  "type": "Feature",
  "properties": {
    "addr:full":"22 Hadera Pl Keswick ON L4P 3N6",
    "addr:housenumber":"22",
    "addr:postcode":"l4p 3n6",
    "addr:street":"Hadera Pl",
    "iso:country":"CA",
    "sg:address":"22 Hadera Pl",
    "sg:city":"Keswick",
    "sg:classifiers":[
        {
            "category":"Professional",
            "subcategory":"Computer Services",
            "type":"Services"
        }
    ],
    "sg:phone":"+1 905 476 1065",
    "sg:postcode":"L4P 3N6",
    "sg:province":"ON",
    "sg:tags":[
        "consultant"
    ],
    "wof:name":"Siroky Group",
    "wof:placetype":"venue"
},
  "geometry": {"coordinates":[-79.461349,44.244854],"type":"Point"}
}