{
  "type": "Feature",
  "properties": {
    "addr:full":"1099 Lansdowne Dr Coquitlam BC V3B 4T7",
    "addr:housenumber":"1099",
    "addr:postcode":"v3b 4t7",
    "addr:street":"Lansdowne Dr",
    "iso:country":"CA",
    "sg:address":"1099 Lansdowne Dr",
    "sg:city":"Coquitlam",
    "sg:classifiers":[
        {
            "category":"Retail",
            "subcategory":"Auto Repair",
            "type":"Services"
        }
    ],
    "sg:phone":"+1 604 461 8888",
    "sg:postcode":"V3B 4T7",
    "sg:province":"BC",
    "sg:tags":[
        "wheel",
        "alignment",
        "axle"
    ],
    "wof:name":"Circuit Frame & Suspension Ltd",
    "wof:placetype":"venue"
},
  "geometry": {"coordinates":[-122.80824279799999,49.2769546509],"type":"Point"}
}