{
  "type": "Feature",
  "properties": {
    "addr:full":"Thunder Bay ON P7B 6R9",
    "addr:postcode":"p7b 6r9",
    "iso:country":"CA",
    "sg:city":"Thunder Bay",
    "sg:classifiers":[
        {
            "category":"Freight",
            "type":"Transportation"
        }
    ],
    "sg:phone":"+1 807 344 3330",
    "sg:postcode":"P7B 6R9",
    "sg:province":"ON",
    "sg:tags":[
        "trucking"
    ],
    "wof:name":"Freight Managers",
    "wof:placetype":"venue"
},
  "geometry": {"coordinates":[-89.239693,48.406685],"type":"Point"}
}