{
  "type": "Feature",
  "properties": {
    "addr:full":"PO Box 939 Blackfalds AB T0M 0J0",
    "addr:housenumber":"po",
    "addr:postcode":"t0m 0j0",
    "addr:street":"Box 939",
    "iso:country":"CA",
    "sg:address":"PO Box 939",
    "sg:city":"Blackfalds",
    "sg:classifiers":[
        {
            "category":"Professional",
            "subcategory":"Business Services",
            "type":"Services"
        }
    ],
    "sg:phone":"+1 403 885 5149",
    "sg:postcode":"T0M 0J0",
    "sg:province":"AB",
    "sg:tags":[
        "auctioneer"
    ],
    "wof:name":"Montgomery Auction Svc Ltd",
    "wof:placetype":"venue"
},
  "geometry": {"coordinates":[-113.79022999999999,52.38015],"type":"Point"}
}