{
  "type": "Feature",
  "properties": {
    "addr:full":"Dorval QC H9S 2A6",
    "addr:postcode":"h9s 2a6",
    "iso:country":"CA",
    "sg:city":"Dorval",
    "sg:classifiers":[
        {
            "category":"Building & Trades",
            "subcategory":"Plumbing",
            "type":"Services"
        }
    ],
    "sg:phone":"+1 514 631 3361",
    "sg:postcode":"H9S 2A6",
    "sg:province":"QC",
    "sg:tags":[
        "contractor"
    ],
    "wof:name":"J Beliveau Plomberie & Chauf",
    "wof:placetype":"venue"
},
  "geometry": {"coordinates":[-73.77886199949999,45.4455871582],"type":"Point"}
}