{
  "type": "Feature",
  "properties": {
    "addr:full":"159 York St Ottawa ON K1N 5T4",
    "addr:housenumber":"159",
    "addr:postcode":"k1n 5t4",
    "addr:street":"York St",
    "iso:country":"CA",
    "sg:address":"159 York St",
    "sg:city":"Ottawa",
    "sg:classifiers":[
        {
            "category":"Shopping",
            "subcategory":"Clothing, Apparel, & Fashions",
            "type":"Retail Goods"
        }
    ],
    "sg:phone":"+1 613 241 8354",
    "sg:postcode":"K1N 5T4",
    "sg:province":"ON",
    "sg:tags":[
        "item",
        "boutique"
    ],
    "wof:name":"Aurajan Boutique",
    "wof:placetype":"venue"
},
  "geometry": {"coordinates":[-75.689682,45.429813],"type":"Point"}
}