{
  "type": "Feature",
  "properties": {
    "addr:full":"203 Camden Rd Napanee ON K7R 1E4",
    "addr:housenumber":"203",
    "addr:postcode":"k7r 1e4",
    "addr:street":"Camden Rd",
    "iso:country":"CA",
    "sg:address":"203 Camden Rd",
    "sg:city":"Napanee",
    "sg:classifiers":[
        {
            "category":"Building & Trades",
            "subcategory":"Electrical",
            "type":"Services"
        }
    ],
    "sg:phone":"+1 613 354 5462",
    "sg:postcode":"K7R 1E4",
    "sg:province":"ON",
    "sg:tags":[
        "electric",
        "contractor"
    ],
    "wof:name":"Keyworth Electric",
    "wof:placetype":"venue"
},
  "geometry": {"coordinates":[-76.9468765259,44.2534828186],"type":"Point"}
}