{
  "type": "Feature",
  "properties": {
    "iso:country":"CA",
    "sg:address":"100 Center St SW",
    "sg:city":"Longview",
    "sg:classifiers":[
        {
            "category":"Education",
            "subcategory":"School",
            "type":"Public Place"
        }
    ],
    "sg:phone":"+1 403 558 2480",
    "sg:postcode":"T0L 1H0",
    "sg:province":"AB",
    "wof:name":"Chief Jacob Bearspaw School",
    "wof:placetype":"venue"
},
  "geometry": {"coordinates":[-114.23097229,50.5312156677],"type":"Point"}
}