{
  "type": "Feature",
  "properties": {
    "addr:full":"321 S Copper St Greenwood BC V0H 1J0",
    "addr:housenumber":"321",
    "addr:postcode":"v0h 1j0",
    "addr:street":"S Copper St",
    "iso:country":"CA",
    "sg:address":"321 S Copper St",
    "sg:city":"Greenwood",
    "sg:classifiers":[
        {
            "category":"Bars & Pubs",
            "type":"Food & Drink"
        }
    ],
    "sg:phone":"+1 250 445 6623",
    "sg:postcode":"V0H 1J0",
    "sg:province":"BC",
    "wof:name":"Greenwood Inn Hotel",
    "wof:placetype":"venue"
},
  "geometry": {"coordinates":[-118.67672,49.09655],"type":"Point"}
}