{
  "type": "Feature",
  "properties": {
    "addr:full":"6033 Promontory Rd Chilliwack BC V2R 4M4",
    "addr:housenumber":"6033",
    "addr:postcode":"v2r 4m4",
    "addr:street":"Promontory Rd",
    "iso:country":"CA",
    "sg:address":"6033 Promontory Rd",
    "sg:city":"Chilliwack",
    "sg:classifiers":[
        {
            "category":"Personal",
            "type":"Services"
        }
    ],
    "sg:phone":"+1 604 824 9177",
    "sg:postcode":"V2R 4M4",
    "sg:province":"BC",
    "sg:tags":[
        "control",
        "weight"
    ],
    "wof:name":"Herbalife",
    "wof:placetype":"venue"
},
  "geometry": {"coordinates":[-121.94280999999999,49.111126],"type":"Point"}
}