{
  "type": "Feature",
  "properties": {
    "addr:full":"182 Rebecca St Hamilton ON L8R 1C1",
    "addr:housenumber":"182",
    "addr:postcode":"l8r 1c1",
    "addr:street":"Rebecca St",
    "iso:country":"CA",
    "sg:address":"182 Rebecca St",
    "sg:city":"Hamilton",
    "sg:classifiers":[
        {
            "category":"Social Services",
            "type":"Services"
        }
    ],
    "sg:phone":"+1 905 521 0090",
    "sg:postcode":"L8R 1C1",
    "sg:province":"ON",
    "sg:tags":[
        "organization",
        "association",
        "welfare"
    ],
    "wof:name":"Canadian Mental Health Assn",
    "wof:placetype":"venue"
},
  "geometry": {"coordinates":[-79.86140441889999,43.2561836243],"type":"Point"}
}