{
  "type": "Feature",
  "properties": {
    "iso:country":"CA",
    "sg:address":"775 Wharncliffe Rd S",
    "sg:city":"London",
    "sg:classifiers":[
        {
            "category":"Shopping",
            "type":"Retail Goods"
        }
    ],
    "sg:phone":"+1 519 681 0249",
    "sg:postcode":"N6J 2N8",
    "sg:province":"ON",
    "sg:tags":[
        "spa",
        "hot",
        "tub"
    ],
    "wof:name":"Beachcomber Hot Tubs London",
    "wof:placetype":"venue"
},
  "geometry": {"coordinates":[-81.257721,42.944324],"type":"Point"}
}