{
  "type": "Feature",
  "properties": {
    "addr:full":"1117 Grant St Victoria BC V8T 1B8",
    "addr:housenumber":"1117",
    "addr:postcode":"v8t 1b8",
    "addr:street":"Grant St",
    "iso:country":"CA",
    "sg:address":"1117 Grant St",
    "sg:city":"Victoria",
    "sg:classifiers":[
        {
            "category":"Manufacturing",
            "subcategory":"Paper Products",
            "type":"Manufacturing & Wholesale Goods"
        }
    ],
    "sg:phone":"+1 250 385 5117",
    "sg:postcode":"V8T 1B8",
    "sg:province":"BC",
    "sg:tags":[
        "label"
    ],
    "wof:name":"Lenar Group",
    "wof:placetype":"venue"
},
  "geometry": {"coordinates":[-123.352341,48.428871],"type":"Point"}
}