{
  "type": "Feature",
  "properties": {
    "iso:country":"CA",
    "sg:address":"7031 Rue Jarry E",
    "sg:city":"Anjou",
    "sg:classifiers":[
        {
            "category":"Restaurant",
            "type":"Food & Drink"
        }
    ],
    "sg:phone":"+1 514 353 3801",
    "sg:postcode":"H1J 1G3",
    "sg:province":"QC",
    "wof:name":"Restaurant Pazzesco",
    "wof:placetype":"venue"
},
  "geometry": {"coordinates":[-73.5769119263,45.6005363464],"type":"Point"}
}