{
  "type": "Feature",
  "properties": {
    "addr:full":"Saint-Stanislas-DE-Champlain QC G0X 3E0",
    "addr:postcode":"g0x 3e0",
    "iso:country":"CA",
    "sg:city":"Saint-Stanislas-DE-Champlain",
    "sg:classifiers":[
        {
            "category":"Government",
            "subcategory":"Office",
            "type":"Public Place"
        }
    ],
    "sg:phone":"+1 418 328 9916",
    "sg:postcode":"G0X 3E0",
    "sg:province":"QC",
    "sg:tags":[
        "village"
    ],
    "wof:name":"St-Stanislas Salle Municipale",
    "wof:placetype":"venue"
},
  "geometry": {"coordinates":[-72.385254,46.610016],"type":"Point"}
}