{
  "type": "Feature",
  "properties": {
    "addr:full":"623 Center St Ottawa ON K1K 2N8",
    "addr:housenumber":"623",
    "addr:postcode":"k1k 2n8",
    "addr:street":"Center St",
    "iso:country":"CA",
    "sg:address":"623 Center St",
    "sg:city":"Ottawa",
    "sg:classifiers":[
        {
            "category":"Restaurant",
            "type":"Food & Drink"
        }
    ],
    "sg:phone":"+1 613 744 3300",
    "sg:postcode":"K1K 2N8",
    "sg:province":"ON",
    "sg:tags":[
        "pizza"
    ],
    "wof:name":"Centre Pizza",
    "wof:placetype":"venue"
},
  "geometry": {"coordinates":[-75.642754,45.44154],"type":"Point"}
}