{
  "type": "Feature",
  "properties": {
    "addr:full":"400 Pfeffer Ave Elbow SK S0H 1J0",
    "addr:housenumber":"400",
    "addr:postcode":"s0h 1j0",
    "addr:street":"Pfeffer Ave Elbow",
    "iso:country":"CA",
    "sg:address":"400 Pfeffer Ave",
    "sg:city":"Elbow",
    "sg:classifiers":[
        {
            "category":"Shopping",
            "subcategory":"Musical Instruments",
            "type":"Retail Goods"
        }
    ],
    "sg:phone":"+1 306 854 2333",
    "sg:postcode":"S0H 1J0",
    "sg:province":"SK",
    "wof:name":"Concert Master Piano Acces",
    "wof:placetype":"venue"
},
  "geometry": {"coordinates":[-106.59440600000001,51.121407],"type":"Point"}
}