{
  "type": "Feature",
  "properties": {
    "addr:full":"PO Box 724 Dawson YT Y0B 1G0",
    "addr:housenumber":"po",
    "addr:postcode":"y0b 1g0",
    "addr:street":"Box 724",
    "iso:country":"CA",
    "sg:address":"PO Box 724",
    "sg:city":"Dawson",
    "sg:classifiers":[
        {
            "category":"Manufacturing",
            "subcategory":"Metals",
            "type":"Manufacturing & Wholesale Goods"
        }
    ],
    "sg:phone":"+1 867 993 5600",
    "sg:postcode":"Y0B 1G0",
    "sg:province":"YT",
    "sg:tags":[
        "refiner",
        "smelter"
    ],
    "wof:name":"Technic Canada Inc",
    "wof:placetype":"venue"
},
  "geometry": {"coordinates":[-139.434326172,64.0633010864],"type":"Point"}
}