{
  "type": "Feature",
  "properties": {
    "addr:full":"1917 Lonsdale Ave North Vancouver BC V7M 2K3",
    "addr:housenumber":"1917",
    "addr:postcode":"v7m 2k3",
    "addr:street":"Lonsdale Ave",
    "iso:country":"CA",
    "sg:address":"1917 Lonsdale Ave",
    "sg:city":"North Vancouver",
    "sg:classifiers":[
        {
            "category":"Shopping",
            "subcategory":"Florist",
            "type":"Retail Goods"
        }
    ],
    "sg:phone":"+1 604 985 7197",
    "sg:postcode":"V7M 2K3",
    "sg:province":"BC",
    "wof:name":"Precious Things Flower Shop",
    "wof:placetype":"venue"
},
  "geometry": {"coordinates":[-123.07240299999999,49.326466],"type":"Point"}
}