{
  "type": "Feature",
  "properties": {
    "iso:country":"CA",
    "sg:address":"2045 20th Ave E",
    "sg:city":"Owen Sound",
    "sg:classifiers":[
        {
            "category":"Home & Garden",
            "subcategory":"Garden Supply",
            "type":"Retail Goods"
        }
    ],
    "sg:phone":"+1 519 371 8974",
    "sg:postcode":"N4K 5N3",
    "sg:province":"ON",
    "sg:tags":[
        "sprinkler"
    ],
    "wof:name":"Arc Irrigation",
    "wof:placetype":"venue"
},
  "geometry": {"coordinates":[-80.89873504640001,44.5838623047],"type":"Point"}
}