{
  "type": "Feature",
  "properties": {
    "addr:full":"Trois-Rivieres-Ouest QC G8Z 4A8",
    "addr:postcode":"g8z 4a8",
    "iso:country":"CA",
    "sg:city":"Trois-Rivieres-Ouest",
    "sg:classifiers":[
        {
            "category":"Health Services",
            "subcategory":"Doctor",
            "type":"Services"
        }
    ],
    "sg:phone":"+1 819 371 2221",
    "sg:postcode":"G8Z 4A8",
    "sg:province":"QC",
    "sg:tags":[
        "dentist"
    ],
    "wof:name":"Centre Dentaire Michel Laroche",
    "wof:placetype":"venue"
},
  "geometry": {"coordinates":[-72.5909042358,46.3342514038],"type":"Point"}
}