{
  "type": "Feature",
  "properties": {
    "addr:full":"Montreal QC H1T 3Y8",
    "addr:postcode":"h1t 3y8",
    "iso:country":"CA",
    "sg:city":"Montreal",
    "sg:classifiers":[
        {
            "category":"Health Services",
            "subcategory":"Doctor",
            "type":"Services"
        }
    ],
    "sg:phone":"+1 514 374 5950",
    "sg:postcode":"H1T 3Y8",
    "sg:province":"QC",
    "sg:tags":[
        "dentist"
    ],
    "wof:name":"Belanger, Chantale DDS",
    "wof:placetype":"venue"
},
  "geometry": {"coordinates":[-73.576286,45.566246],"type":"Point"}
}