{
  "type": "Feature",
  "properties": {
    "addr:full":"2623 Granville St Vancouver BC V6H 3H2",
    "addr:housenumber":"2623",
    "addr:postcode":"v6h 3h2",
    "addr:street":"Granville St",
    "iso:country":"CA",
    "sg:address":"2623 Granville St",
    "sg:city":"Vancouver",
    "sg:classifiers":[
        {
            "category":"Home & Garden",
            "subcategory":"Furniture",
            "type":"Retail Goods"
        }
    ],
    "sg:phone":"+1 604 734 2623",
    "sg:postcode":"V6H 3H2",
    "sg:province":"BC",
    "sg:tags":[
        "bedding",
        "bed"
    ],
    "wof:name":"Duxiana",
    "wof:placetype":"venue"
},
  "geometry": {"coordinates":[-123.138824,49.262402],"type":"Point"}
}