{
  "type": "Feature",
  "properties": {
    "iso:country":"CA",
    "sg:address":"1360 Oxford St W",
    "sg:city":"London",
    "sg:classifiers":[
        {
            "category":"Education",
            "subcategory":"School",
            "type":"Public Place"
        }
    ],
    "sg:phone":"+1 519 641 1223",
    "sg:postcode":"N6H 1W2",
    "sg:province":"ON",
    "wof:name":"St Thomas Aquinas",
    "wof:placetype":"venue"
},
  "geometry": {"coordinates":[-81.334854126,42.9714202881],"type":"Point"}
}