{
  "type": "Feature",
  "properties": {
    "addr:full":"6921 Fallon Dr Lucan ON N0M 2J0",
    "addr:housenumber":"6921",
    "addr:postcode":"n0m 2j0",
    "addr:street":"Fallon Dr",
    "iso:country":"CA",
    "sg:address":"6921 Fallon Dr",
    "sg:city":"Lucan",
    "sg:classifiers":[
        {
            "category":"Retail",
            "subcategory":"Auto Repair",
            "type":"Services"
        }
    ],
    "sg:phone":"+1 519 227 0500",
    "sg:postcode":"N0M 2J0",
    "sg:province":"ON",
    "sg:tags":[
        "wrecker"
    ],
    "wof:name":"K & K Towing & Auto Svc",
    "wof:placetype":"venue"
},
  "geometry": {"coordinates":[-81.3757858276,43.2058105469],"type":"Point"}
}