{
  "type": "Feature",
  "properties": {
    "addr:full":"845 Rue Jean-Marchand Levis QC G6V 9G4",
    "addr:housenumber":"845",
    "addr:postcode":"g6v 9g4",
    "addr:street":"Rue Jean-Marchand",
    "iso:country":"CA",
    "sg:address":"845 Rue Jean-Marchand",
    "sg:city":"Levis",
    "sg:classifiers":[
        {
            "category":"Food & Beverages",
            "subcategory":"Bakery",
            "type":"Retail Goods"
        }
    ],
    "sg:phone":"+1 418 837 3611",
    "sg:postcode":"G6V 9G4",
    "sg:province":"QC",
    "sg:tags":[
        "baker"
    ],
    "wof:name":"Multi Marquis",
    "wof:placetype":"venue"
},
  "geometry": {"coordinates":[-71.129501,46.818413],"type":"Point"}
}