{
  "type": "Feature",
  "properties": {
    "addr:full":"7577 Keele St # 102 Concord ON L4K 4X3",
    "addr:housenumber":"7577",
    "addr:postcode":"l4k 4x3",
    "addr:street":"Keele St # 102",
    "iso:country":"CA",
    "sg:address":"7577 Keele St # 102",
    "sg:city":"Concord",
    "sg:classifiers":[
        {
            "category":"Wholesale",
            "subcategory":"Drugs",
            "type":"Manufacturing & Wholesale Goods"
        }
    ],
    "sg:phone":"+1 905 669 9889",
    "sg:postcode":"L4K 4X3",
    "sg:province":"ON",
    "sg:tags":[
        "pharmaceutical",
        "product"
    ],
    "wof:name":"Alliance Retail Management Grp",
    "wof:placetype":"venue"
},
  "geometry": {"coordinates":[-79.498322,43.796513],"type":"Point"}
}