{
  "type": "Feature",
  "properties": {
    "addr:full":"151 Dundas St E Paris ON N3L 3H4",
    "addr:housenumber":"151",
    "addr:postcode":"n3l 3h4",
    "addr:street":"Dundas St E",
    "iso:country":"CA",
    "sg:address":"151 Dundas St E",
    "sg:city":"Paris",
    "sg:classifiers":[
        {
            "category":"Food & Beverages",
            "subcategory":"Bakery",
            "type":"Retail Goods"
        }
    ],
    "sg:phone":"+1 519 442 1430",
    "sg:postcode":"N3L 3H4",
    "sg:province":"ON",
    "sg:tags":[
        "doughnut"
    ],
    "wof:name":"Tim Hortons",
    "wof:placetype":"venue"
},
  "geometry": {"coordinates":[-80.365295,43.191208],"type":"Point"}
}