{
  "type": "Feature",
  "properties": {
    "addr:full":"6265 Rue Saint-Denis Montreal QC H2S 2R8",
    "addr:housenumber":"6265",
    "addr:postcode":"h2s 2r8",
    "addr:street":"Rue Saint-Denis",
    "iso:country":"CA",
    "sg:address":"6265 Rue Saint-Denis",
    "sg:city":"Montreal",
    "sg:classifiers":[
        {
            "category":"Health Services",
            "subcategory":"Doctor",
            "type":"Services"
        }
    ],
    "sg:phone":"+1 514 270 1523",
    "sg:postcode":"H2S 2R8",
    "sg:province":"QC",
    "sg:tags":[
        "dentist"
    ],
    "wof:name":"Schwartz, Joel S DDS",
    "wof:placetype":"venue"
},
  "geometry": {"coordinates":[-73.6026306152,45.53307724],"type":"Point"}
}