{
  "type": "Feature",
  "properties": {
    "addr:full":"37 Hall St Lunenburg NS B0J 2C0",
    "addr:housenumber":"37",
    "addr:postcode":"b0j 2c0",
    "addr:street":"Hall St",
    "iso:country":"CA",
    "sg:address":"37 Hall St",
    "sg:city":"Lunenburg",
    "sg:classifiers":[
        {
            "category":"Manufacturing",
            "subcategory":"Printing",
            "type":"Manufacturing & Wholesale Goods"
        }
    ],
    "sg:phone":"+1 902 634 8316",
    "sg:postcode":"B0J 2C0",
    "sg:province":"NS",
    "sg:tags":[
        "multimedia"
    ],
    "wof:name":"H B Studios Multi Media Ltd",
    "wof:placetype":"venue"
},
  "geometry": {"coordinates":[-64.3243179321,44.3751411438],"type":"Point"}
}