{
  "type": "Feature",
  "properties": {
    "addr:full":"8567 Ch Dalton Mont-Royal QC H4T 1V5",
    "addr:housenumber":"ch",
    "addr:postcode":"8567;h4t 1v5",
    "addr:street":"Dalton",
    "iso:country":"CA",
    "sg:address":"8567 Ch Dalton",
    "sg:city":"Mont-Royal",
    "sg:classifiers":[
        {
            "category":"Wholesale",
            "subcategory":"Durable Goods & Equipment",
            "type":"Manufacturing & Wholesale Goods"
        }
    ],
    "sg:phone":"+1 514 344 3525",
    "sg:postcode":"H4T 1V5",
    "sg:province":"QC",
    "sg:tags":[
        "laboratory",
        "supply"
    ],
    "wof:name":"Vwr International",
    "wof:placetype":"venue"
},
  "geometry": {"coordinates":[-73.682159,45.487717],"type":"Point"}
}