{
  "type": "Feature",
  "properties": {
    "addr:full":"Smooth Rock Falls ON P0L 2B0",
    "addr:postcode":"p0l 2b0",
    "iso:country":"CA",
    "sg:city":"Smooth Rock Falls",
    "sg:classifiers":[
        {
            "category":"Autos & Motor Vehicles",
            "subcategory":"Fuel & Gas Station",
            "type":"Retail Goods"
        }
    ],
    "sg:phone":"+1 705 338 2121",
    "sg:postcode":"P0L 2B0",
    "sg:province":"ON",
    "sg:tags":[
        "oil"
    ],
    "wof:name":"Formula 21 Gasoline",
    "wof:placetype":"venue"
},
  "geometry": {"coordinates":[-81.62990600000001,49.27705],"type":"Point"}
}