{
  "type": "Feature",
  "properties": {
    "addr:full":"5010 46 St Stettler AB T0C 2L2",
    "addr:housenumber":"5010",
    "addr:postcode":"t0c 2l2",
    "addr:street":"46 St",
    "iso:country":"CA",
    "sg:address":"5010 46 St",
    "sg:city":"Stettler",
    "sg:classifiers":[
        {
            "category":"Home & Garden",
            "subcategory":"Carpets & Floor Coverings",
            "type":"Retail Goods"
        }
    ],
    "sg:phone":"+1 403 742 2909",
    "sg:postcode":"T0C 2L2",
    "sg:province":"AB",
    "sg:tags":[
        "material"
    ],
    "wof:name":"Nicoll Flooring Ltd",
    "wof:placetype":"venue"
},
  "geometry": {"coordinates":[-112.69956999999999,52.327114],"type":"Point"}
}