{
  "type": "Feature",
  "properties": {
    "addr:full":"1110 Kamato Rd Mississauga ON L4W 2P3",
    "addr:housenumber":"1110",
    "addr:postcode":"l4w 2p3",
    "addr:street":"Kamato Rd",
    "iso:country":"CA",
    "sg:address":"1110 Kamato Rd",
    "sg:city":"Mississauga",
    "sg:classifiers":[
        {
            "category":"Freight",
            "type":"Transportation"
        }
    ],
    "sg:phone":"+1 905 238 2600",
    "sg:postcode":"L4W 2P3",
    "sg:province":"ON",
    "wof:name":"Tradespan",
    "wof:placetype":"venue"
},
  "geometry": {"coordinates":[-79.64112900000001,43.641113],"type":"Point"}
}