{
  "type": "Feature",
  "properties": {
    "addr:full":"105 Mcleod Ave W Melfort SK S0E 1A0",
    "addr:housenumber":"105",
    "addr:postcode":"s0e 1a0",
    "addr:street":"Mcleod Ave W Melfort",
    "iso:country":"CA",
    "sg:address":"105 Mcleod Ave W",
    "sg:city":"Melfort",
    "sg:classifiers":[
        {
            "category":"Sports & Exercise",
            "subcategory":"Bowling",
            "type":"Entertainment"
        }
    ],
    "sg:phone":"+1 306 752 2608",
    "sg:postcode":"S0E 1A0",
    "sg:province":"SK",
    "sg:tags":[
        "center"
    ],
    "wof:name":"Melfort Bowl",
    "wof:placetype":"venue"
},
  "geometry": {"coordinates":[-104.619446,52.86375],"type":"Point"}
}