{
  "type": "Feature",
  "properties": {
    "addr:full":"107 Chandos Ave Toronto ON M6H 2E7",
    "addr:housenumber":"107",
    "addr:postcode":"m6h 2e7",
    "addr:street":"Chandos Ave",
    "iso:country":"CA",
    "sg:address":"107 Chandos Ave",
    "sg:city":"Toronto",
    "sg:classifiers":[
        {
            "category":"Professional",
            "subcategory":"Art Services",
            "type":"Services"
        }
    ],
    "sg:phone":"+1 416 534 0110",
    "sg:postcode":"M6H 2E7",
    "sg:province":"ON",
    "sg:tags":[
        "graphic",
        "printer",
        "designer"
    ],
    "wof:name":"Market Graphics",
    "wof:placetype":"venue"
},
  "geometry": {"coordinates":[-79.443619,43.670383],"type":"Point"}
}