{
  "type": "Feature",
  "properties": {
    "addr:full":"52 King St N Waterloo ON N2J 2W8",
    "addr:housenumber":"52",
    "addr:postcode":"n2j 2w8",
    "addr:street":"King St N",
    "iso:country":"CA",
    "sg:address":"52 King St N",
    "sg:city":"Waterloo",
    "sg:classifiers":[
        {
            "category":"Personal",
            "subcategory":"Beauty Salon",
            "type":"Services"
        }
    ],
    "sg:phone":"+1 519 886 3990",
    "sg:postcode":"N2J 2W8",
    "sg:province":"ON",
    "wof:name":"Capri Hair Styles Ltd",
    "wof:placetype":"venue"
},
  "geometry": {"coordinates":[-80.5225906372,43.4666824341],"type":"Point"}
}