{
  "type": "Feature",
  "properties": {
    "addr:full":"4036 Gairloch Rd Westville NS B0K 2A0",
    "addr:housenumber":"4036",
    "addr:postcode":"b0k 2a0",
    "addr:street":"Gairloch Rd",
    "iso:country":"CA",
    "sg:address":"4036 Gairloch Rd",
    "sg:city":"Westville",
    "sg:classifiers":[
        {
            "category":"Autos & Motor Vehicles",
            "subcategory":"Fuel & Gas Station",
            "type":"Retail Goods"
        }
    ],
    "sg:phone":"+1 902 396 4479",
    "sg:postcode":"B0K 2A0",
    "sg:province":"NS",
    "sg:tags":[
        "oil"
    ],
    "wof:name":"Union Centre One Step",
    "wof:placetype":"venue"
},
  "geometry": {"coordinates":[-62.709908,45.56176],"type":"Point"}
}