{
  "type": "Feature",
  "properties": {
    "iso:country":"CA",
    "sg:address":"330 Rue Aime-Vincent",
    "sg:city":"Vaudreuil-Dorion",
    "sg:classifiers":[
        {
            "category":"Wholesale",
            "subcategory":"Durable Goods & Equipment",
            "type":"Manufacturing & Wholesale Goods"
        }
    ],
    "sg:phone":"+1 450 424 4040",
    "sg:postcode":"J7V 5V5",
    "sg:province":"QC",
    "sg:tags":[
        "laboratory",
        "dental",
        "supply"
    ],
    "wof:name":"Systemes DE Mobilier Triangle",
    "wof:placetype":"venue"
},
  "geometry": {"coordinates":[-74.04890441889999,45.4052085876],"type":"Point"}
}