{
  "type": "Feature",
  "properties": {
    "addr:full":"485 6th Ave Hanover ON N4N 2G5",
    "addr:housenumber":"485",
    "addr:postcode":"n4n 2g5",
    "addr:street":"6Th Ave",
    "iso:country":"CA",
    "sg:address":"485 6th Ave",
    "sg:city":"Hanover",
    "sg:classifiers":[
        {
            "category":"Building & Trades",
            "subcategory":"Construction",
            "type":"Services"
        }
    ],
    "sg:phone":"+1 519 364 3609",
    "sg:postcode":"N4N 2G5",
    "sg:province":"ON",
    "sg:tags":[
        "general",
        "contractor"
    ],
    "wof:name":"Landmark Builders Ltd",
    "wof:placetype":"venue"
},
  "geometry": {"coordinates":[-81.0323638916,44.1523132324],"type":"Point"}
}