{
  "type": "Feature",
  "properties": {
    "addr:full":"Mississauga ON L5C 4E6",
    "addr:postcode":"l5c 4e6",
    "iso:country":"CA",
    "sg:city":"Mississauga",
    "sg:classifiers":[
        {
            "category":"Retail",
            "subcategory":"Laundry & Dry Cleaning",
            "type":"Services"
        }
    ],
    "sg:phone":"+1 905 848 4287",
    "sg:postcode":"L5C 4E6",
    "sg:province":"ON",
    "sg:tags":[
        "cleaners"
    ],
    "wof:name":"One Hour Martinizing Dryclnrs",
    "wof:placetype":"venue"
},
  "geometry": {"coordinates":[-79.6631698608,43.5690078735],"type":"Point"}
}