{
  "type": "Feature",
  "properties": {
    "addr:full":"18 Ottawa W Havelock ON K0L 1Z0",
    "addr:housenumber":"18",
    "addr:postcode":"k0l 1z0",
    "addr:street":"Ottawa W",
    "iso:country":"CA",
    "sg:address":"18 Ottawa W",
    "sg:city":"Havelock",
    "sg:classifiers":[
        {
            "category":"Travel",
            "subcategory":"Hotels & Motels",
            "type":"Entertainment"
        }
    ],
    "sg:phone":"+1 705 778 1092",
    "sg:postcode":"K0L 1Z0",
    "sg:province":"ON",
    "wof:name":"Havelock Belmont Methuen",
    "wof:placetype":"venue"
},
  "geometry": {"coordinates":[-77.888023,44.433285],"type":"Point"}
}