{
  "type": "Feature",
  "properties": {
    "addr:full":"58 Van Order Dr Kingston ON K7M 1B7",
    "addr:housenumber":"58",
    "addr:postcode":"k7m 1b7",
    "addr:street":"Van Order Dr",
    "iso:country":"CA",
    "sg:address":"58 Van Order Dr",
    "sg:city":"Kingston",
    "sg:classifiers":[
        {
            "category":"Building & Trades",
            "subcategory":"Electrical",
            "type":"Services"
        }
    ],
    "sg:phone":"+1 613 546 4779",
    "sg:postcode":"K7M 1B7",
    "sg:province":"ON",
    "sg:tags":[
        "electric",
        "contractor"
    ],
    "wof:name":"Carlo DE Longhi Electric Ltd",
    "wof:placetype":"venue"
},
  "geometry": {"coordinates":[-76.51778411870001,44.2352790833],"type":"Point"}
}