{
  "type": "Feature",
  "properties": {
    "iso:country":"CA",
    "sg:city":"Hull",
    "sg:classifiers":[
        {
            "category":"Restaurant",
            "type":"Food & Drink"
        }
    ],
    "sg:phone":"+1 819 771 6170",
    "sg:postcode":"J8X 3G8",
    "sg:province":"QC",
    "wof:name":"L'Argoat",
    "wof:placetype":"venue"
},
  "geometry": {"coordinates":[-75.7165145874,45.4268760681],"type":"Point"}
}