{
  "type": "Feature",
  "properties": {
    "iso:country":"CA",
    "sg:address":"1496 Delkatla St",
    "sg:city":"Masset",
    "sg:classifiers":[
        {
            "category":"Travel",
            "subcategory":"Hotels & Motels",
            "type":"Entertainment"
        }
    ],
    "sg:phone":"+1 250 626 3322",
    "sg:postcode":"V0T 1M0",
    "sg:province":"BC",
    "sg:tags":[
        "breakfast",
        "accommodation",
        "bed"
    ],
    "wof:name":"Naden Lodge Inc",
    "wof:placetype":"venue"
},
  "geometry": {"coordinates":[-132.139572144,54.0120773315],"type":"Point"}
}