{
  "type": "Feature",
  "properties": {
    "iso:country":"CA",
    "sg:address":"800 Av Du Mont-Royal E",
    "sg:city":"Montreal",
    "sg:classifiers":[
        {
            "category":"Shopping",
            "subcategory":"Stationery & Office Supplies",
            "type":"Retail Goods"
        }
    ],
    "sg:phone":"+1 514 524 3081",
    "sg:postcode":"H2J 1X1",
    "sg:province":"QC",
    "wof:name":"Papeterie Le Plateau",
    "wof:placetype":"venue"
},
  "geometry": {"coordinates":[-73.5811920166,45.5257377625],"type":"Point"}
}