{
  "type": "Feature",
  "properties": {
    "iso:country":"CA",
    "sg:city":"West Vancouver",
    "sg:classifiers":[
        {
            "category":"Health Services",
            "subcategory":"Doctor",
            "type":"Services"
        }
    ],
    "sg:phone":"+1 604 926 1112",
    "sg:postcode":"V7T 1B8",
    "sg:province":"BC",
    "sg:tags":[
        "physician",
        "surgeon"
    ],
    "wof:name":"Paragas, Pedro G MD",
    "wof:placetype":"venue"
},
  "geometry": {"coordinates":[-123.156417847,49.3283920288],"type":"Point"}
}