{
  "type": "Feature",
  "properties": {
    "addr:full":"5212 50 St Whitecourt AB T7S 1P6",
    "addr:housenumber":"5212",
    "addr:postcode":"t7s 1p6",
    "addr:street":"50 St",
    "iso:country":"CA",
    "sg:address":"5212 50 St",
    "sg:city":"Whitecourt",
    "sg:classifiers":[
        {
            "category":"Organizations",
            "subcategory":"Professional Association",
            "type":"Services"
        }
    ],
    "sg:phone":"+1 780 778 4950",
    "sg:postcode":"T7S 1P6",
    "sg:province":"AB",
    "sg:tags":[
        "club"
    ],
    "wof:name":"Whitecourt Seniors Circle",
    "wof:placetype":"venue"
},
  "geometry": {"coordinates":[-115.68480682400001,54.1429176331],"type":"Point"}
}