{
  "type": "Feature",
  "properties": {
    "addr:full":"PO Box 1720 Morrin AB T0J 2B0",
    "addr:housenumber":"po",
    "addr:postcode":"t0j 2b0",
    "addr:street":"Box 1720 Morrin",
    "iso:country":"CA",
    "sg:address":"PO Box 1720",
    "sg:city":"Morrin",
    "sg:classifiers":[
        {
            "category":"Organizations",
            "subcategory":"Religious Organization",
            "type":"Services"
        }
    ],
    "sg:phone":"+1 403 772 2154",
    "sg:postcode":"T0J 2B0",
    "sg:province":"AB",
    "sg:tags":[
        "church"
    ],
    "wof:name":"Starland Hutterite Church",
    "wof:placetype":"venue"
},
  "geometry": {"coordinates":[-112.756355286,51.64894104],"type":"Point"}
}