{
  "type": "Feature",
  "properties": {
    "iso:country":"CA",
    "sg:address":"515 Goderich St",
    "sg:city":"Port Elgin",
    "sg:classifiers":[
        {
            "category":"Social Services",
            "type":"Services"
        }
    ],
    "sg:phone":"+1 519 389 3942",
    "sg:postcode":"N0H 2C4",
    "sg:province":"ON",
    "sg:tags":[
        "organization",
        "welfare"
    ],
    "wof:name":"Salvation Army Family & Comm",
    "wof:placetype":"venue"
},
  "geometry": {"coordinates":[-81.3906326294,44.4337158203],"type":"Point"}
}