{
  "type": "Feature",
  "properties": {
    "addr:full":"Saskatoon SK S7K 5E4",
    "addr:postcode":"s7k 5e4",
    "iso:country":"CA",
    "sg:city":"Saskatoon",
    "sg:classifiers":[
        {
            "category":"Insurance",
            "subcategory":"Insurance Agent",
            "type":"Services"
        }
    ],
    "sg:phone":"+1 306 931 1999",
    "sg:postcode":"S7K 5E4",
    "sg:province":"SK",
    "sg:tags":[
        "adjuster"
    ],
    "wof:name":"Crawfords Adjusters Canada Inc",
    "wof:placetype":"venue"
},
  "geometry": {"coordinates":[-106.635513,52.168015],"type":"Point"}
}