{
  "type": "Feature",
  "properties": {
    "addr:full":"8 Rue DE L'Eglise N Lorrainville QC J0Z 2R0",
    "addr:housenumber":"8",
    "addr:postcode":"j0z 2r0",
    "addr:street":"Rue De L'Eglise N",
    "iso:country":"CA",
    "sg:address":"8 Rue DE L'Eglise N",
    "sg:city":"Lorrainville",
    "sg:classifiers":[
        {
            "category":"Organizations",
            "subcategory":"Religious Organization",
            "type":"Services"
        }
    ],
    "sg:phone":"+1 819 625 2104",
    "sg:postcode":"J0Z 2R0",
    "sg:province":"QC",
    "sg:tags":[
        "church"
    ],
    "wof:name":"Presbyteres DE Notre-Dame",
    "wof:placetype":"venue"
},
  "geometry": {"coordinates":[-79.352127,47.35387],"type":"Point"}
}