{
  "type": "Feature",
  "properties": {
    "addr:full":"904 Hwy 414 Biggar SK S0K 0M0",
    "addr:housenumber":"904",
    "addr:postcode":"s0k 0m0",
    "addr:street":"Hwy 414",
    "iso:country":"CA",
    "sg:address":"904 Hwy 414",
    "sg:city":"Biggar",
    "sg:classifiers":[
        {
            "category":"Autos & Motor Vehicles",
            "subcategory":"Fuel & Gas Station",
            "type":"Retail Goods"
        }
    ],
    "sg:phone":"+1 306 948 3600",
    "sg:postcode":"S0K 0M0",
    "sg:province":"SK",
    "sg:tags":[
        "oil"
    ],
    "wof:name":"Esso 414 Ltd",
    "wof:placetype":"venue"
},
  "geometry": {"coordinates":[-107.98204,52.06049],"type":"Point"}
}