{
  "type": "Feature",
  "properties": {
    "addr:full":"Thunder Bay ON P7C 5V5",
    "addr:postcode":"p7c 5v5",
    "iso:country":"CA",
    "sg:city":"Thunder Bay",
    "sg:classifiers":[
        {
            "category":"Building & Trades",
            "subcategory":"Construction",
            "type":"Services"
        }
    ],
    "sg:phone":"+1 807 476 7005",
    "sg:postcode":"P7C 5V5",
    "sg:province":"ON",
    "sg:tags":[
        "dry wall",
        "contractor"
    ],
    "wof:name":"Wagenaar Dry Wall",
    "wof:placetype":"venue"
},
  "geometry": {"coordinates":[-89.245476,48.381699],"type":"Point"}
}