{
  "type": "Feature",
  "properties": {
    "addr:full":"1792 Liverpool Rd # 2 Pickering ON L1V 4G6",
    "addr:housenumber":"1792",
    "addr:postcode":"l1v 4g6",
    "addr:street":"Liverpool Rd # 2",
    "iso:country":"CA",
    "sg:address":"1792 Liverpool Rd # 2",
    "sg:city":"Pickering",
    "sg:classifiers":[
        {
            "category":"Health Services",
            "subcategory":"Doctor",
            "type":"Services"
        }
    ],
    "sg:phone":"+1 905 420 8990",
    "sg:postcode":"L1V 4G6",
    "sg:province":"ON",
    "sg:tags":[
        "dentist"
    ],
    "wof:name":"Pickering Market Dental Office",
    "wof:placetype":"venue"
},
  "geometry": {"coordinates":[-79.0896682739,43.8331642151],"type":"Point"}
}