{
  "type": "Feature",
  "properties": {
    "addr:full":"211 Kensington Pl Orangeville ON L9W 4G4",
    "addr:housenumber":"211",
    "addr:postcode":"l9w 4g4",
    "addr:street":"Kensington Pl",
    "iso:country":"CA",
    "sg:address":"211 Kensington Pl",
    "sg:city":"Orangeville",
    "sg:classifiers":[
        {
            "category":"Building & Trades",
            "subcategory":"Electrical",
            "type":"Services"
        }
    ],
    "sg:phone":"+1 519 942 4488",
    "sg:postcode":"L9W 4G4",
    "sg:province":"ON",
    "sg:tags":[
        "telephone"
    ],
    "wof:name":"Cadcom Communications",
    "wof:placetype":"venue"
},
  "geometry": {"coordinates":[-80.11312103269999,43.9228172302],"type":"Point"}
}