{
  "type": "Feature",
  "properties": {
    "iso:country":"CA",
    "sg:city":"Scarborough",
    "sg:classifiers":[
        {
            "category":"Education",
            "subcategory":"Special Training",
            "type":"Public Place"
        }
    ],
    "sg:phone":"+1 416 497 4633",
    "sg:postcode":"M1W 3Y3",
    "sg:province":"ON",
    "sg:tags":[
        "tutoring"
    ],
    "wof:name":"Rainbow Learning Ctr",
    "wof:placetype":"venue"
},
  "geometry": {"coordinates":[-79.335105896,43.8018188477],"type":"Point"}
}