{
  "type": "Feature",
  "properties": {
    "addr:full":"2183 Rue Des Roses Carignan QC J3L 5E1",
    "addr:housenumber":"2183",
    "addr:postcode":"j3l 5e1",
    "addr:street":"Rue Des Roses",
    "iso:country":"CA",
    "sg:address":"2183 Rue Des Roses",
    "sg:city":"Carignan",
    "sg:classifiers":[
        {
            "category":"Health Services",
            "subcategory":"Medical Lab",
            "type":"Services"
        }
    ],
    "sg:phone":"+1 450 676 6767",
    "sg:postcode":"J3L 5E1",
    "sg:province":"QC",
    "wof:name":"Beaudoin, Christian",
    "wof:placetype":"venue"
},
  "geometry": {"coordinates":[-73.2831192017,45.4695320129],"type":"Point"}
}