{
  "type": "Feature",
  "properties": {
    "addr:full":"Bedford NS B4A 2X9",
    "addr:postcode":"b4a 2x9",
    "iso:country":"CA",
    "sg:city":"Bedford",
    "sg:classifiers":[
        {
            "category":"Personal",
            "type":"Services"
        }
    ],
    "sg:phone":"+1 902 835 5386",
    "sg:postcode":"B4A 2X9",
    "sg:province":"NS",
    "sg:tags":[
        "hair",
        "removing",
        "electrolysis"
    ],
    "wof:name":"Bedford Electrolysis",
    "wof:placetype":"venue"
},
  "geometry": {"coordinates":[-63.6548042297,44.7364006042],"type":"Point"}
}