{
  "type": "Feature",
  "properties": {
    "addr:full":"4351 London Line Wyoming ON N0N 1T0",
    "addr:housenumber":"4351",
    "addr:postcode":"n0n 1t0",
    "addr:street":"London Line",
    "iso:country":"CA",
    "sg:address":"4351 London Line",
    "sg:city":"Wyoming",
    "sg:classifiers":[
        {
            "category":"Autos & Motor Vehicles",
            "subcategory":"Recreational Vehicle Sales",
            "type":"Retail Goods"
        }
    ],
    "sg:phone":"+1 519 845 0060",
    "sg:postcode":"N0N 1T0",
    "sg:province":"ON",
    "wof:name":"W Bill Trailer Sales",
    "wof:placetype":"venue"
},
  "geometry": {"coordinates":[-82.1299133301,42.9797668457],"type":"Point"}
}