{
  "type": "Feature",
  "properties": {
    "addr:full":"1780 Rue Fleury E Montreal QC H2C 1T4",
    "addr:housenumber":"1780",
    "addr:postcode":"h2c 1t4",
    "addr:street":"Rue Fleury E",
    "iso:country":"CA",
    "sg:address":"1780 Rue Fleury E",
    "sg:city":"Montreal",
    "sg:classifiers":[
        {
            "category":"Shopping",
            "subcategory":"Department Store",
            "type":"Retail Goods"
        }
    ],
    "sg:phone":"+1 514 384 8862",
    "sg:postcode":"H2C 1T4",
    "sg:province":"QC",
    "sg:tags":[
        "shop"
    ],
    "wof:name":"Dollar Depot Inc",
    "wof:placetype":"venue"
},
  "geometry": {"coordinates":[-73.653465271,45.5677490234],"type":"Point"}
}