{
  "type": "Feature",
  "properties": {
    "addr:full":"821 Notre-Dame St-Barnabe-Nord QC G0X 2K0",
    "addr:housenumber":"821",
    "addr:postcode":"g0x 2k0",
    "addr:street":"Notre-Dame St-Barnabe-Nord",
    "iso:country":"CA",
    "sg:address":"821 Notre-Dame",
    "sg:city":"St-Barnabe-Nord",
    "sg:classifiers":[
        {
            "category":"Building & Trades",
            "subcategory":"Plumbing",
            "type":"Services"
        }
    ],
    "sg:phone":"+1 819 264 5623",
    "sg:postcode":"G0X 2K0",
    "sg:province":"QC",
    "sg:tags":[
        "contractor"
    ],
    "wof:name":"Plomberie Lamco Inc",
    "wof:placetype":"venue"
},
  "geometry": {"coordinates":[-72.8800201416,46.393901825],"type":"Point"}
}