{
  "type": "Feature",
  "properties": {
    "iso:country":"CA",
    "sg:address":"1281 Old Thorold Stone Rd",
    "sg:city":"Thorold",
    "sg:classifiers":[
        {
            "category":"Freight",
            "type":"Transportation"
        }
    ],
    "sg:phone":"+1 905 227 1261",
    "sg:postcode":"L2V 3Y7",
    "sg:province":"ON",
    "sg:tags":[
        "warehouse",
        "self",
        "storage"
    ],
    "wof:name":"Niagara District Warehouse",
    "wof:placetype":"venue"
},
  "geometry": {"coordinates":[-79.18980407710001,43.117477417],"type":"Point"}
}