{
  "type": "Feature",
  "properties": {
    "addr:full":"167 Rue Saint-Alphonse Drummondville QC J2B 6M1",
    "addr:housenumber":"167",
    "addr:postcode":"j2b 6m1",
    "addr:street":"Rue Saint-Alphonse",
    "iso:country":"CA",
    "sg:address":"167 Rue Saint-Alphonse",
    "sg:city":"Drummondville",
    "sg:classifiers":[
        {
            "category":"Shopping",
            "subcategory":"Clothing, Apparel, & Fashions",
            "type":"Retail Goods"
        }
    ],
    "sg:phone":"+1 819 472 2318",
    "sg:postcode":"J2B 6M1",
    "sg:province":"QC",
    "sg:tags":[
        "theatrical",
        "costume"
    ],
    "wof:name":"Costumes Decor",
    "wof:placetype":"venue"
},
  "geometry": {"coordinates":[-72.494263,45.873699],"type":"Point"}
}