{
  "type": "Feature",
  "properties": {
    "addr:full":"7515 158 Ave NW Edmonton AB T5Z 2W4",
    "addr:housenumber":"7515",
    "addr:postcode":"t5z 2w4",
    "addr:street":"158 Ave Nw",
    "iso:country":"CA",
    "sg:address":"7515 158 Ave NW",
    "sg:city":"Edmonton",
    "sg:classifiers":[
        {
            "category":"Professional",
            "subcategory":"Business Services",
            "type":"Services"
        }
    ],
    "sg:phone":"+1 780 940 3969",
    "sg:postcode":"T5Z 2W4",
    "sg:province":"AB",
    "sg:tags":[
        "appraiser"
    ],
    "wof:name":"Tandem Appraisals",
    "wof:placetype":"venue"
},
  "geometry": {"coordinates":[-113.457191467,53.6192512512],"type":"Point"}
}