{
  "type": "Feature",
  "properties": {
    "iso:country":"CA",
    "sg:address":"9509 117 Ave",
    "sg:city":"Grande Prairie",
    "sg:classifiers":[
        {
            "category":"Retail",
            "subcategory":"Repair Shop",
            "type":"Services"
        }
    ],
    "sg:phone":"+1 780 532 1801",
    "sg:postcode":"T8V 4R2",
    "sg:province":"AB",
    "sg:tags":[
        "repairing",
        "piano",
        "refinishing"
    ],
    "wof:name":"Noteworthy Piano Ctr",
    "wof:placetype":"venue"
},
  "geometry": {"coordinates":[-118.78047180199999,55.1859054565],"type":"Point"}
}