{
  "type": "Feature",
  "properties": {
    "addr:full":"714 Mcintyre St W North Bay ON P1B 2Z9",
    "addr:housenumber":"714",
    "addr:postcode":"p1b 2z9",
    "addr:street":"Mcintyre St W",
    "iso:country":"CA",
    "sg:address":"714 Mcintyre St W",
    "sg:city":"North Bay",
    "sg:classifiers":[
        {
            "category":"Social Services",
            "type":"Services"
        }
    ],
    "sg:phone":"+1 705 474 7441",
    "sg:postcode":"P1B 2Z9",
    "sg:province":"ON",
    "sg:tags":[
        "counselor",
        "marriage",
        "family"
    ],
    "wof:name":"Paul Smith Counselling Svc",
    "wof:placetype":"venue"
},
  "geometry": {"coordinates":[-79.47077899999999,46.317848],"type":"Point"}
}