{
  "type": "Feature",
  "properties": {
    "iso:country":"CA",
    "sg:address":"1235 Main St N",
    "sg:city":"Moose Jaw",
    "sg:classifiers":[
        {
            "category":"Shopping",
            "subcategory":"Department Store",
            "type":"Retail Goods"
        }
    ],
    "sg:phone":"+1 306 692 7851",
    "sg:postcode":"S6H 6M3",
    "sg:province":"SK",
    "wof:name":"Sears Canada Inc",
    "wof:placetype":"venue"
},
  "geometry": {"coordinates":[-105.53441599999999,50.404331],"type":"Point"}
}