{
  "type": "Feature",
  "properties": {
    "addr:full":"7130 Rue Saint-Denis Montreal QC H2S 2S4",
    "addr:housenumber":"7130",
    "addr:postcode":"h2s 2s4",
    "addr:street":"Rue Saint-Denis",
    "iso:country":"CA",
    "sg:address":"7130 Rue Saint-Denis",
    "sg:city":"Montreal",
    "sg:classifiers":[
        {
            "category":"Food & Beverages",
            "subcategory":"Groceries & Convenience Stores",
            "type":"Retail Goods"
        }
    ],
    "sg:phone":"+1 514 271 4469",
    "sg:postcode":"H2S 2S4",
    "sg:province":"QC",
    "sg:tags":[
        "grocer"
    ],
    "wof:name":"Marche Thai-Hour",
    "wof:placetype":"venue"
},
  "geometry": {"coordinates":[-73.61483764650001,45.5382843018],"type":"Point"}
}