{
  "type": "Feature",
  "properties": {
    "addr:full":"16814 104 Ave Surrey BC V4N 4L8",
    "addr:housenumber":"16814",
    "addr:postcode":"v4n 4l8",
    "addr:street":"104 Ave",
    "iso:country":"CA",
    "sg:address":"16814 104 Ave",
    "sg:city":"Surrey",
    "sg:classifiers":[
        {
            "category":"Food & Beverages",
            "subcategory":"Groceries & Convenience Stores",
            "type":"Retail Goods"
        }
    ],
    "sg:phone":"+1 604 583 4545",
    "sg:postcode":"V4N 4L8",
    "sg:province":"BC",
    "sg:tags":[
        "grocer"
    ],
    "wof:name":"Fraser Glen Market",
    "wof:placetype":"venue"
},
  "geometry": {"coordinates":[-122.755554199,49.1914787292],"type":"Point"}
}