{
  "type": "Feature",
  "properties": {
    "addr:full":"1303 Av Greene # 100 Westmount QC H3Z 2A7",
    "addr:housenumber":"1303",
    "addr:postcode":"h3z 2a7",
    "addr:street":"Av Greene # 100",
    "iso:country":"CA",
    "sg:address":"1303 Av Greene # 100",
    "sg:city":"Westmount",
    "sg:classifiers":[
        {
            "category":"Professional",
            "subcategory":"Research",
            "type":"Services"
        }
    ],
    "sg:phone":"+1 514 937 8786",
    "sg:postcode":"H3Z 2A7",
    "sg:province":"QC",
    "sg:tags":[
        "market",
        "analysis"
    ],
    "wof:name":"126201 Canada Inc",
    "wof:placetype":"venue"
},
  "geometry": {"coordinates":[-73.589714,45.487137],"type":"Point"}
}