{
  "type": "Feature",
  "properties": {
    "addr:full":"280 King St Fredericton NB E3B 1E2",
    "addr:housenumber":"280",
    "addr:postcode":"e3b 1e2",
    "addr:street":"King St",
    "iso:country":"CA",
    "sg:address":"280 King St",
    "sg:city":"Fredericton",
    "sg:classifiers":[
        {
            "category":"Restaurant",
            "type":"Food & Drink"
        }
    ],
    "sg:phone":"+1 506 458 1212",
    "sg:postcode":"E3B 1E2",
    "sg:province":"NB",
    "wof:name":"Mc Ginnis Landing",
    "wof:placetype":"venue"
},
  "geometry": {"coordinates":[-66.646812,45.963116],"type":"Point"}
}