{
  "type": "Feature",
  "properties": {
    "addr:full":"1965 Sumas Way Abbotsford BC V2S 4L5",
    "addr:housenumber":"1965",
    "addr:postcode":"v2s 4l5",
    "addr:street":"Sumas Way",
    "iso:country":"CA",
    "sg:address":"1965 Sumas Way",
    "sg:city":"Abbotsford",
    "sg:classifiers":[
        {
            "category":"Restaurant",
            "type":"Food & Drink"
        }
    ],
    "sg:phone":"+1 604 853 1911",
    "sg:postcode":"V2S 4L5",
    "sg:province":"BC",
    "wof:name":"Smitty's Family Restaurant",
    "wof:placetype":"venue"
},
  "geometry": {"coordinates":[-122.268112,49.036957],"type":"Point"}
}