{
  "type": "Feature",
  "properties": {
    "addr:full":"4400 55th Ave Camrose AB T4V 1X8",
    "addr:housenumber":"4400",
    "addr:postcode":"t4v 1x8",
    "addr:street":"55Th Ave",
    "iso:country":"CA",
    "sg:address":"4400 55th Ave",
    "sg:city":"Camrose",
    "sg:classifiers":[
        {
            "category":"Building & Trades",
            "subcategory":"Equipment Rental",
            "type":"Services"
        }
    ],
    "sg:phone":"+1 780 672 1810",
    "sg:postcode":"T4V 1X8",
    "sg:province":"AB",
    "sg:tags":[
        "aircraft",
        "leasing",
        "charter",
        "school"
    ],
    "wof:name":"Camrose Flight Ctr",
    "wof:placetype":"venue"
},
  "geometry": {"coordinates":[-112.815307617,53.0320663452],"type":"Point"}
}