{
  "type": "Feature",
  "properties": {
    "addr:full":"12185 Boul Laurentien Montreal QC H4K 1N4",
    "addr:housenumber":"12185",
    "addr:postcode":"h4k 1n4",
    "addr:street":"Boul Laurentien",
    "iso:country":"CA",
    "sg:address":"12185 Boul Laurentien",
    "sg:city":"Montreal",
    "sg:classifiers":[
        {
            "category":"Retail",
            "subcategory":"Auto Repair",
            "type":"Services"
        }
    ],
    "sg:phone":"+1 514 331 3003",
    "sg:postcode":"H4K 1N4",
    "sg:province":"QC",
    "sg:tags":[
        "muffler",
        "exhaust",
        "system"
    ],
    "wof:name":"Silencieux Gms",
    "wof:placetype":"venue"
},
  "geometry": {"coordinates":[-73.72007000000001,45.528053],"type":"Point"}
}