{
  "type": "Feature",
  "properties": {
    "addr:full":"Truro NS B2N 2R9",
    "addr:postcode":"b2n 2r9",
    "iso:country":"CA",
    "sg:city":"Truro",
    "sg:classifiers":[
        {
            "category":"Professional",
            "subcategory":"Engineering",
            "type":"Services"
        }
    ],
    "sg:phone":"+1 902 897 0982",
    "sg:postcode":"B2N 2R9",
    "sg:province":"NS",
    "sg:tags":[
        "engineer"
    ],
    "wof:name":"Reinforced Earth CO Ltd",
    "wof:placetype":"venue"
},
  "geometry": {"coordinates":[-63.2890396118,45.3660202026],"type":"Point"}
}