{
  "type": "Feature",
  "properties": {
    "addr:full":"683 Rue Principale St Leonard NB E7E 2J4",
    "addr:housenumber":"683",
    "addr:postcode":"e7e 2j4",
    "addr:street":"Rue Principale St",
    "iso:country":"CA",
    "sg:address":"683 Rue Principale",
    "sg:city":"St Leonard",
    "sg:classifiers":[
        {
            "category":"Banks & Credit Unions",
            "subcategory":"Bank",
            "type":"Services"
        }
    ],
    "sg:phone":"+1 506 423 6386",
    "sg:postcode":"E7E 2J4",
    "sg:province":"NB",
    "wof:name":"Caisse Populaire DE St Leonard",
    "wof:placetype":"venue"
},
  "geometry": {"coordinates":[-67.92527,47.164993],"type":"Point"}
}