{
  "type": "Feature",
  "properties": {
    "addr:full":"8707 Main St Osoyoos BC V0H 1V0",
    "addr:housenumber":"8707",
    "addr:postcode":"v0h 1v0",
    "addr:street":"Main St",
    "iso:country":"CA",
    "sg:address":"8707 Main St",
    "sg:city":"Osoyoos",
    "sg:classifiers":[
        {
            "category":"Government",
            "subcategory":"Office",
            "type":"Public Place"
        }
    ],
    "sg:phone":"+1 250 495 6515",
    "sg:postcode":"V0H 1V0",
    "sg:province":"BC",
    "sg:tags":[
        "village"
    ],
    "wof:name":"Osoyoos Town Ofc",
    "wof:placetype":"venue"
},
  "geometry": {"coordinates":[-119.468208,49.032578],"type":"Point"}
}