{
  "type": "Feature",
  "properties": {
    "addr:full":"2190 143 Rte Hatley QC J0B 4B0",
    "addr:housenumber":"2190",
    "addr:postcode":"j0b 4b0",
    "addr:street":"143 Rte",
    "iso:country":"CA",
    "sg:address":"2190 143 Rte",
    "sg:city":"Hatley",
    "sg:classifiers":[
        {
            "category":"Shopping",
            "subcategory":"Used Merchandise",
            "type":"Retail Goods"
        }
    ],
    "sg:phone":"+1 819 838 1419",
    "sg:postcode":"J0B 4B0",
    "sg:province":"QC",
    "sg:tags":[
        "antique"
    ],
    "wof:name":"Raveau-Marcil Antiquites",
    "wof:placetype":"venue"
},
  "geometry": {"coordinates":[-71.98941000000001,45.182217],"type":"Point"}
}