{
  "type": "Feature",
  "properties": {
    "addr:full":"122 Broadway St Tillsonburg ON N4G 3P8",
    "addr:housenumber":"122",
    "addr:postcode":"n4g 3p8",
    "addr:street":"Broadway St",
    "iso:country":"CA",
    "sg:address":"122 Broadway St",
    "sg:city":"Tillsonburg",
    "sg:classifiers":[
        {
            "category":"Personal",
            "subcategory":"Beauty Salon",
            "type":"Services"
        }
    ],
    "sg:phone":"+1 519 842 3702",
    "sg:postcode":"N4G 3P8",
    "sg:province":"ON",
    "wof:name":"Escapes",
    "wof:placetype":"venue"
},
  "geometry": {"coordinates":[-80.727394,42.860394],"type":"Point"}
}