{
  "type": "Feature",
  "properties": {
    "iso:country":"CA",
    "sg:city":"Burnaby",
    "sg:classifiers":[
        {
            "category":"Building & Trades",
            "subcategory":"Electrical",
            "type":"Services"
        }
    ],
    "sg:phone":"+1 604 451 8708",
    "sg:postcode":"V5J 4R2",
    "sg:province":"BC",
    "sg:tags":[
        "electric",
        "contractor"
    ],
    "wof:name":"Advanco Electric Ltd",
    "wof:placetype":"venue"
},
  "geometry": {"coordinates":[-122.981796265,49.221534729],"type":"Point"}
}