{
  "type": "Feature",
  "properties": {
    "addr:full":"Richmond BC V6X 4B3",
    "addr:postcode":"v6x 4b3",
    "iso:country":"CA",
    "sg:city":"Richmond",
    "sg:classifiers":[
        {
            "category":"Restaurant",
            "type":"Food & Drink"
        }
    ],
    "sg:phone":"+1 604 232 0242",
    "sg:postcode":"V6X 4B3",
    "sg:province":"BC",
    "wof:name":"Tea Hut Cafe",
    "wof:placetype":"venue"
},
  "geometry": {"coordinates":[-123.127845764,49.1781044006],"type":"Point"}
}