{
  "type": "Feature",
  "properties": {
    "addr:full":"288 Dundas St E Waterdown ON L0R 2H0",
    "addr:housenumber":"288",
    "addr:postcode":"l0r 2h0",
    "addr:street":"Dundas St E",
    "iso:country":"CA",
    "sg:address":"288 Dundas St E",
    "sg:city":"Waterdown",
    "sg:classifiers":[
        {
            "category":"Health Services",
            "subcategory":"Doctor",
            "type":"Services"
        }
    ],
    "sg:phone":"+1 905 689 8677",
    "sg:postcode":"L0R 2H0",
    "sg:province":"ON",
    "sg:tags":[
        "physician",
        "surgeon"
    ],
    "wof:name":"Faught, Jim MD",
    "wof:placetype":"venue"
},
  "geometry": {"coordinates":[-79.894402,43.331856],"type":"Point"}
}