{
  "type": "Feature",
  "properties": {
    "iso:country":"CA",
    "sg:address":"7975 Yonge St",
    "sg:city":"Innisfil",
    "sg:classifiers":[
        {
            "category":"Personal",
            "subcategory":"Beauty Salon",
            "type":"Services"
        }
    ],
    "sg:phone":"+1 705 436 4020",
    "sg:postcode":"L9S 1L2",
    "sg:province":"ON",
    "wof:name":"Suzette's",
    "wof:placetype":"venue"
},
  "geometry": {"coordinates":[-79.622719,44.336941],"type":"Point"}
}