{
  "type": "Feature",
  "properties": {
    "addr:full":"608 25 Ave NE Calgary AB T2E 1Y5",
    "addr:postcode":"t2e 1y5",
    "addr:street":"608 25 Ave Ne",
    "iso:country":"CA",
    "sg:address":"608 25 Ave NE",
    "sg:city":"Calgary",
    "sg:classifiers":[
        {
            "category":"Professional",
            "subcategory":"Art Services",
            "type":"Services"
        }
    ],
    "sg:phone":"+1 403 276 6335",
    "sg:postcode":"T2E 1Y5",
    "sg:province":"AB",
    "sg:tags":[
        "graphic",
        "designer"
    ],
    "wof:name":"Eleventh Hour Images",
    "wof:placetype":"venue"
},
  "geometry": {"coordinates":[-114.050316,51.075321],"type":"Point"}
}