{
  "type": "Feature",
  "properties": {
    "addr:full":"45 Wright Ave Dartmouth NS B3B 1G9",
    "addr:housenumber":"45",
    "addr:postcode":"b3b 1g9",
    "addr:street":"Wright Ave",
    "iso:country":"CA",
    "sg:address":"45 Wright Ave",
    "sg:city":"Dartmouth",
    "sg:classifiers":[
        {
            "category":"Home & Garden",
            "subcategory":"Building Materials",
            "type":"Retail Goods"
        }
    ],
    "sg:phone":"+1 902 468 5446",
    "sg:postcode":"B3B 1G9",
    "sg:province":"NS",
    "sg:tags":[
        "insulation"
    ],
    "wof:name":"Mgi Insulations Eastern Ltd",
    "wof:placetype":"venue"
},
  "geometry": {"coordinates":[-63.6015586853,44.7007102966],"type":"Point"}
}