{
  "type": "Feature",
  "properties": {
    "addr:full":"5840 Oak St Vancouver BC V6M 2V9",
    "addr:housenumber":"5840",
    "addr:postcode":"v6m 2v9",
    "addr:street":"Oak St",
    "iso:country":"CA",
    "sg:address":"5840 Oak St",
    "sg:city":"Vancouver",
    "sg:classifiers":[
        {
            "category":"Organizations",
            "subcategory":"Religious Organization",
            "type":"Services"
        }
    ],
    "sg:phone":"+1 604 266 6281",
    "sg:postcode":"V6M 2V9",
    "sg:province":"BC",
    "sg:tags":[
        "church"
    ],
    "wof:name":"Unity of Vancouver",
    "wof:placetype":"venue"
},
  "geometry": {"coordinates":[-123.127883911,49.2326698303],"type":"Point"}
}