{
  "type": "Feature",
  "properties": {
    "addr:full":"6805 Boul Decarie Montreal QC H3W 3E4",
    "addr:housenumber":"6805",
    "addr:postcode":"h3w 3e4",
    "addr:street":"Boul Decarie",
    "iso:country":"CA",
    "sg:address":"6805 Boul Decarie",
    "sg:city":"Montreal",
    "sg:classifiers":[
        {
            "category":"Wholesale",
            "subcategory":"Office Equipment",
            "type":"Manufacturing & Wholesale Goods"
        }
    ],
    "sg:phone":"+1 514 738 8474",
    "sg:postcode":"H3W 3E4",
    "sg:province":"QC",
    "sg:tags":[
        "control",
        "production",
        "chalkboard",
        "system"
    ],
    "wof:name":"National Coaching Skills Inc",
    "wof:placetype":"venue"
},
  "geometry": {"coordinates":[-73.6476821899,45.4922103882],"type":"Point"}
}