{
  "type": "Feature",
  "properties": {
    "addr:full":"221 Sunnidale St Stayner ON L0M 1S0",
    "addr:housenumber":"221",
    "addr:postcode":"l0m 1s0",
    "addr:street":"Sunnidale St",
    "iso:country":"CA",
    "sg:address":"221 Sunnidale St",
    "sg:city":"Stayner",
    "sg:classifiers":[
        {
            "category":"Building & Trades",
            "subcategory":"Electrical",
            "type":"Services"
        }
    ],
    "sg:phone":"+1 705 428 3439",
    "sg:postcode":"L0M 1S0",
    "sg:province":"ON",
    "sg:tags":[
        "electric",
        "contractor"
    ],
    "wof:name":"Lorne Bunn Electric",
    "wof:placetype":"venue"
},
  "geometry": {"coordinates":[-80.076065,44.419498],"type":"Point"}
}