{
  "type": "Feature",
  "properties": {
    "addr:full":"515 Mount Pleasant Rd Toronto ON M4S 2M4",
    "addr:housenumber":"515",
    "addr:postcode":"m4s 2m4",
    "addr:street":"Mount Pleasant Rd",
    "iso:country":"CA",
    "sg:address":"515 Mount Pleasant Rd",
    "sg:city":"Toronto",
    "sg:classifiers":[
        {
            "category":"Shopping",
            "subcategory":"Used Merchandise",
            "type":"Retail Goods"
        }
    ],
    "sg:phone":"+1 416 488 6687",
    "sg:postcode":"M4S 2M4",
    "sg:province":"ON",
    "sg:tags":[
        "shop",
        "second",
        "consignment",
        "store",
        "hand"
    ],
    "wof:name":"Rotations",
    "wof:placetype":"venue"
},
  "geometry": {"coordinates":[-79.387398,43.701946],"type":"Point"}
}