{
  "type": "Feature",
  "properties": {
    "addr:full":"1500 Sixth Line # 9 Oakville ON L6H 2P2",
    "addr:housenumber":"1500",
    "addr:postcode":"l6h 2p2",
    "addr:street":"Sixth Line # 9",
    "iso:country":"CA",
    "sg:address":"1500 Sixth Line # 9",
    "sg:city":"Oakville",
    "sg:classifiers":[
        {
            "category":"Health Services",
            "subcategory":"Doctor",
            "type":"Services"
        }
    ],
    "sg:phone":"+1 905 815 0775",
    "sg:postcode":"L6H 2P2",
    "sg:province":"ON",
    "sg:tags":[
        "dentist"
    ],
    "wof:name":"North Oak Dental Office",
    "wof:placetype":"venue"
},
  "geometry": {"coordinates":[-79.7096710205,43.465007782],"type":"Point"}
}