{
  "type": "Feature",
  "properties": {
    "iso:country":"CA",
    "sg:address":"109 York St # B",
    "sg:city":"Cornwall",
    "sg:classifiers":[
        {
            "category":"Social Services",
            "type":"Services"
        }
    ],
    "sg:phone":"+1 613 938 2000",
    "sg:postcode":"K6J 3Y9",
    "sg:province":"ON",
    "sg:tags":[
        "organization",
        "welfare"
    ],
    "wof:name":"Partir D'Un Bon Pas Pour Un",
    "wof:placetype":"venue"
},
  "geometry": {"coordinates":[-74.73197937010001,45.0159454346],"type":"Point"}
}