{
  "type": "Feature",
  "properties": {
    "addr:full":"Montreal QC H3A 3M8",
    "addr:postcode":"h3a 3m8",
    "iso:country":"CA",
    "sg:city":"Montreal",
    "sg:classifiers":[
        {
            "category":"Government",
            "subcategory":"Office",
            "type":"Public Place"
        }
    ],
    "sg:phone":"+1 514 287 1669",
    "sg:postcode":"H3A 3M8",
    "sg:province":"QC",
    "sg:tags":[
        "commission",
        "trade"
    ],
    "wof:name":"Banque DE Commerce Exterieur",
    "wof:placetype":"venue"
},
  "geometry": {"coordinates":[-73.57151,45.502453],"type":"Point"}
}