{
  "type": "Feature",
  "properties": {
    "addr:full":"27 Island Pond Dr Kippens NL A2N 3N9",
    "addr:housenumber":"27",
    "addr:postcode":"a2n 3n9",
    "addr:street":"Island Pond Dr",
    "iso:country":"CA",
    "sg:address":"27 Island Pond Dr",
    "sg:city":"Kippens",
    "sg:classifiers":[
        {
            "category":"Building & Trades",
            "subcategory":"Landscaping Services",
            "type":"Services"
        }
    ],
    "sg:phone":"+1 709 643 2721",
    "sg:postcode":"A2N 3N9",
    "sg:province":"NL",
    "sg:tags":[
        "lawn",
        "maintenance",
        "grounds"
    ],
    "wof:name":"Lawn Specialists",
    "wof:placetype":"venue"
},
  "geometry": {"coordinates":[-58.6222801208,48.5486602783],"type":"Point"}
}