{
  "type": "Feature",
  "properties": {
    "addr:full":"106 Fleetwood Rd Lindsay ON K9V 6C6",
    "addr:housenumber":"106",
    "addr:postcode":"k9v 6c6",
    "addr:street":"Fleetwood Rd",
    "iso:country":"CA",
    "sg:address":"106 Fleetwood Rd",
    "sg:city":"Lindsay",
    "sg:classifiers":[
        {
            "category":"Wholesale",
            "subcategory":"Hardware",
            "type":"Manufacturing & Wholesale Goods"
        }
    ],
    "sg:phone":"+1 705 324 1772",
    "sg:postcode":"K9V 6C6",
    "sg:province":"ON",
    "sg:tags":[
        "fastener"
    ],
    "wof:name":"Brafasco",
    "wof:placetype":"venue"
},
  "geometry": {"coordinates":[-78.73009500000001,44.373085],"type":"Point"}
}