{
  "type": "Feature",
  "properties": {
    "addr:full":"4811 Delta St Delta BC V4K 2T7",
    "addr:housenumber":"4811",
    "addr:postcode":"v4k 2t7",
    "addr:street":"Delta St",
    "iso:country":"CA",
    "sg:address":"4811 Delta St",
    "sg:city":"Delta",
    "sg:classifiers":[
        {
            "category":"Food & Beverages",
            "subcategory":"Specialty",
            "type":"Retail Goods"
        }
    ],
    "sg:phone":"+1 604 940 2266",
    "sg:postcode":"V4K 2T7",
    "sg:province":"BC",
    "sg:tags":[
        "tea",
        "coffee"
    ],
    "wof:name":"Beanies Coffee Bar",
    "wof:placetype":"venue"
},
  "geometry": {"coordinates":[-123.08535000000001,49.090347],"type":"Point"}
}