{
  "type": "Feature",
  "properties": {
    "addr:full":"55 Victoria St E Kensington PE C0B 1M0",
    "addr:housenumber":"55",
    "addr:postcode":"c0b 1m0",
    "addr:street":"Victoria St E",
    "iso:country":"CA",
    "sg:address":"55 Victoria St E",
    "sg:city":"Kensington",
    "sg:classifiers":[
        {
            "category":"Government",
            "subcategory":"Office",
            "type":"Public Place"
        }
    ],
    "sg:phone":"+1 902 836 3781",
    "sg:postcode":"C0B 1M0",
    "sg:province":"PE",
    "sg:tags":[
        "village"
    ],
    "wof:name":"Kensington Town Office",
    "wof:placetype":"venue"
},
  "geometry": {"coordinates":[-63.6368484497,46.436882019],"type":"Point"}
}