{
  "type": "Feature",
  "properties": {
    "iso:country":"CA",
    "sg:address":"15 Ch Du Cap-Aux-Corbeaux S",
    "sg:city":"Baie-Saint-Paul",
    "sg:classifiers":[
        {
            "category":"Wholesale",
            "subcategory":"Chemicals & Plastics",
            "type":"Manufacturing & Wholesale Goods"
        }
    ],
    "sg:phone":"+1 418 435 5407",
    "sg:postcode":"G3Z 1A9",
    "sg:province":"QC",
    "sg:tags":[
        "cleaning",
        "compound"
    ],
    "wof:name":"Produits Sani-Pro Enr",
    "wof:placetype":"venue"
},
  "geometry": {"coordinates":[-70.45272827150001,47.4285774231],"type":"Point"}
}