{
  "type": "Feature",
  "properties": {
    "addr:full":"2246 Eglinton Ave W York ON M6E 2L3",
    "addr:housenumber":"2246",
    "addr:postcode":"m6e 2l3",
    "addr:street":"Eglinton Ave W",
    "iso:country":"CA",
    "sg:address":"2246 Eglinton Ave W",
    "sg:city":"York",
    "sg:classifiers":[
        {
            "category":"Communications",
            "subcategory":"Film & Video Production",
            "type":"Services"
        }
    ],
    "sg:phone":"+1 416 782 3126",
    "sg:postcode":"M6E 2L3",
    "sg:province":"ON",
    "sg:tags":[
        "taping"
    ],
    "wof:name":"Big City Productions",
    "wof:placetype":"venue"
},
  "geometry": {"coordinates":[-79.4625701904,43.6930847168],"type":"Point"}
}