{
  "type": "Feature",
  "properties": {
    "addr:full":"Victoria BC V8T 5K6",
    "addr:postcode":"v8t 5k6",
    "iso:country":"CA",
    "sg:city":"Victoria",
    "sg:classifiers":[
        {
            "category":"Autos & Motor Vehicles",
            "subcategory":"Boat Sales",
            "type":"Retail Goods"
        }
    ],
    "sg:phone":"+1 250 380 4668",
    "sg:postcode":"V8T 5K6",
    "sg:province":"BC",
    "sg:tags":[
        "dealer",
        "canoe"
    ],
    "wof:name":"Gorge Kayaking Ctr",
    "wof:placetype":"venue"
},
  "geometry": {"coordinates":[-123.379105,48.439396],"type":"Point"}
}