{
  "type": "Feature",
  "properties": {
    "iso:country":"CA",
    "sg:address":"6257 Airport Rd",
    "sg:city":"Mississauga",
    "sg:classifiers":[
        {
            "category":"Travel",
            "subcategory":"Hotels & Motels",
            "type":"Entertainment"
        }
    ],
    "sg:phone":"+1 905 678 1400",
    "sg:postcode":"L4V 1E4",
    "sg:province":"ON",
    "wof:name":"Days Hotel & Conference Ctr",
    "wof:placetype":"venue"
},
  "geometry": {"coordinates":[-79.62339,43.690147],"type":"Point"}
}