{
  "type": "Feature",
  "properties": {
    "addr:full":"1500 23 St Didsbury AB T0M 0W0",
    "addr:housenumber":"1500",
    "addr:postcode":"t0m 0w0",
    "addr:street":"23 St",
    "iso:country":"CA",
    "sg:address":"1500 23 St",
    "sg:city":"Didsbury",
    "sg:classifiers":[
        {
            "category":"Organizations",
            "subcategory":"Religious Organization",
            "type":"Services"
        }
    ],
    "sg:phone":"+1 403 335 3161",
    "sg:postcode":"T0M 0W0",
    "sg:province":"AB",
    "sg:tags":[
        "church"
    ],
    "wof:name":"Redeemer Lutheran Church",
    "wof:placetype":"venue"
},
  "geometry": {"coordinates":[-114.143501,51.656933],"type":"Point"}
}