{
  "type": "Feature",
  "properties": {
    "iso:country":"CA",
    "sg:address":"6524 Henderson Hwy",
    "sg:city":"Winnipeg",
    "sg:classifiers":[
        {
            "category":"Manufacturing",
            "subcategory":"Tools & Machinery",
            "type":"Manufacturing & Wholesale Goods"
        }
    ],
    "sg:phone":"+1 204 757 9176",
    "sg:postcode":"R3C 2E7",
    "sg:province":"MB",
    "sg:tags":[
        "farm",
        "equipment"
    ],
    "wof:name":"J J Riverside Mfg Ltd",
    "wof:placetype":"venue"
},
  "geometry": {"coordinates":[-97.068619,49.95985],"type":"Point"}
}