{
  "type": "Feature",
  "properties": {
    "addr:full":"281 Tupper St Hawkesbury ON K6A 3T6",
    "addr:housenumber":"281",
    "addr:postcode":"k6a 3t6",
    "addr:street":"Tupper St",
    "iso:country":"CA",
    "sg:address":"281 Tupper St",
    "sg:city":"Hawkesbury",
    "sg:classifiers":[
        {
            "category":"Autos & Motor Vehicles",
            "subcategory":"Automobile Sales",
            "type":"Retail Goods"
        }
    ],
    "sg:phone":"+1 613 632 8816",
    "sg:postcode":"K6A 3T6",
    "sg:province":"ON",
    "sg:tags":[
        "car",
        "dealer"
    ],
    "wof:name":"Rendez Vous Nissan",
    "wof:placetype":"venue"
},
  "geometry": {"coordinates":[-74.58326700000001,45.605976],"type":"Point"}
}