{
  "type": "Feature",
  "properties": {
    "addr:full":"565 Rue Saint-Andre Laval QC H7G 3A2",
    "addr:housenumber":"565",
    "addr:postcode":"qc h7g 3a2",
    "addr:street":"Rue Saint-Andre",
    "iso:country":"CA",
    "sg:address":"565 Rue Saint-Andre",
    "sg:city":"Laval",
    "sg:classifiers":[
        {
            "category":"Wholesale",
            "subcategory":"Office Equipment",
            "type":"Manufacturing & Wholesale Goods"
        }
    ],
    "sg:phone":"+1 450 669 3140",
    "sg:postcode":"H7G 3A2",
    "sg:province":"QC",
    "sg:tags":[
        "vault",
        "safe"
    ],
    "wof:name":"Coffre-Fort Laurentien",
    "wof:placetype":"venue"
},
  "geometry": {"coordinates":[-73.691444,45.572521],"type":"Point"}
}