{
  "type": "Feature",
  "properties": {
    "addr:full":"14823 108 Ave Surrey BC V3R 1W2",
    "addr:housenumber":"14823",
    "addr:postcode":"v3r 1w2",
    "addr:street":"108 Ave",
    "iso:country":"CA",
    "sg:address":"14823 108 Ave",
    "sg:city":"Surrey",
    "sg:classifiers":[
        {
            "category":"Insurance",
            "subcategory":"Insurance Agent",
            "type":"Services"
        }
    ],
    "sg:phone":"+1 604 581 4466",
    "sg:postcode":"V3R 1W2",
    "sg:province":"BC",
    "wof:name":"Riverside Insurance Ltd",
    "wof:placetype":"venue"
},
  "geometry": {"coordinates":[-122.81173706,49.1988792419],"type":"Point"}
}