{
  "type": "Feature",
  "properties": {
    "iso:country":"CA",
    "sg:city":"Moberly Lake",
    "sg:classifiers":[
        {
            "category":"Food & Beverages",
            "subcategory":"Groceries & Convenience Stores",
            "type":"Retail Goods"
        }
    ],
    "sg:phone":"+1 250 788 3007",
    "sg:postcode":"V0C 1X0",
    "sg:province":"BC",
    "sg:tags":[
        "grocer"
    ],
    "wof:name":"Crowfeather's Store",
    "wof:placetype":"venue"
},
  "geometry": {"coordinates":[-121.72489166299999,55.8353881836],"type":"Point"}
}