{
  "type": "Feature",
  "properties": {
    "addr:full":"Park St W Kamsack SK S0A 1S0",
    "addr:postcode":"s0a 1s0",
    "addr:street":"Park St W Kamsack",
    "iso:country":"CA",
    "sg:address":"Park St W",
    "sg:city":"Kamsack",
    "sg:classifiers":[
        {
            "category":"Building & Trades",
            "subcategory":"Construction",
            "type":"Services"
        }
    ],
    "sg:phone":"+1 306 542 2256",
    "sg:postcode":"S0A 1S0",
    "sg:province":"SK",
    "sg:tags":[
        "excavating",
        "contractor",
        "general"
    ],
    "wof:name":"Walker's Backhoe",
    "wof:placetype":"venue"
},
  "geometry": {"coordinates":[-101.896721,51.568016],"type":"Point"}
}