{
  "type": "Feature",
  "properties": {
    "addr:full":"33 Industrial Dr Campbellford ON K0L 1L0",
    "addr:housenumber":"33",
    "addr:postcode":"k0l 1l0",
    "addr:street":"Industrial Dr",
    "iso:country":"CA",
    "sg:address":"33 Industrial Dr",
    "sg:city":"Campbellford",
    "sg:classifiers":[
        {
            "category":"Professional",
            "subcategory":"Business Services",
            "type":"Services"
        }
    ],
    "sg:phone":"+1 705 653 3533",
    "sg:postcode":"K0L 1L0",
    "sg:province":"ON",
    "sg:tags":[
        "auctioneer"
    ],
    "wof:name":"Williams Auction & Appraisal",
    "wof:placetype":"venue"
},
  "geometry": {"coordinates":[-77.80249000000001,44.288116],"type":"Point"}
}