{
  "type": "Feature",
  "properties": {
    "addr:full":"23 Buchanan Crt London ON N5Z 4P9",
    "addr:housenumber":"23",
    "addr:postcode":"n5z 4p9",
    "addr:street":"Buchanan Crt",
    "iso:country":"CA",
    "sg:address":"23 Buchanan Crt",
    "sg:city":"London",
    "sg:classifiers":[
        {
            "category":"Home & Garden",
            "subcategory":"Building Materials",
            "type":"Retail Goods"
        }
    ],
    "sg:phone":"+1 519 681 7012",
    "sg:postcode":"N5Z 4P9",
    "sg:province":"ON",
    "sg:tags":[
        "windows"
    ],
    "wof:name":"Kml Windows Inc",
    "wof:placetype":"venue"
},
  "geometry": {"coordinates":[-81.189781,42.936214],"type":"Point"}
}