{
  "type": "Feature",
  "properties": {
    "addr:full":"16334 Fairview Dr Avonmore ON K0C 1C0",
    "addr:housenumber":"16334",
    "addr:postcode":"k0c 1c0",
    "addr:street":"Fairview Dr",
    "iso:country":"CA",
    "sg:address":"16334 Fairview Dr",
    "sg:city":"Avonmore",
    "sg:classifiers":[
        {
            "category":"Restaurant",
            "type":"Food & Drink"
        }
    ],
    "sg:phone":"+1 613 346 0174",
    "sg:postcode":"K0C 1C0",
    "sg:province":"ON",
    "sg:tags":[
        "banquet",
        "rooms"
    ],
    "wof:name":"Avonmore Community Ctr",
    "wof:placetype":"venue"
},
  "geometry": {"coordinates":[-74.96863555909999,45.1713409424],"type":"Point"}
}