{
  "type": "Feature",
  "properties": {
    "addr:full":"3025 Rue Saint-Ambroise Montreal QC H4C 2C2",
    "addr:housenumber":"3025",
    "addr:postcode":"h4c 2c2",
    "addr:street":"Rue Saint-Ambroise",
    "iso:country":"CA",
    "sg:address":"3025 Rue Saint-Ambroise",
    "sg:city":"Montreal",
    "sg:classifiers":[
        {
            "category":"Food & Beverages",
            "subcategory":"Bakery",
            "type":"Retail Goods"
        }
    ],
    "sg:phone":"+1 514 932 0328",
    "sg:postcode":"H4C 2C2",
    "sg:province":"QC",
    "sg:tags":[
        "baker"
    ],
    "wof:name":"Boulangerie Premiere Moisson",
    "wof:placetype":"venue"
},
  "geometry": {"coordinates":[-73.575836,45.479218],"type":"Point"}
}