{
  "type": "Feature",
  "properties": {
    "iso:country":"CA",
    "sg:address":"6945 Av Christophe-Colomb",
    "sg:city":"Montreal",
    "sg:classifiers":[
        {
            "category":"Education",
            "subcategory":"School",
            "type":"Public Place"
        }
    ],
    "sg:phone":"+1 514 272 1786",
    "sg:postcode":"H2S 2H3",
    "sg:province":"QC",
    "sg:tags":[
        "academic",
        "instruction",
        "special",
        "dancing"
    ],
    "wof:name":"Ecole DE Ballet Classique",
    "wof:placetype":"venue"
},
  "geometry": {"coordinates":[-73.6079483032,45.540851593],"type":"Point"}
}