{
  "type": "Feature",
  "properties": {
    "addr:full":"427 Rue DE LA Riviere Cowansville QC J2K 1N4",
    "addr:housenumber":"427",
    "addr:postcode":"j2k 1n4",
    "addr:street":"Rue De La Riviere",
    "iso:country":"CA",
    "sg:address":"427 Rue DE LA Riviere",
    "sg:city":"Cowansville",
    "sg:classifiers":[
        {
            "category":"Restaurant",
            "type":"Food & Drink"
        }
    ],
    "sg:phone":"+1 450 266 2066",
    "sg:postcode":"J2K 1N4",
    "sg:province":"QC",
    "wof:name":"Subway Sandwiches & Salads",
    "wof:placetype":"venue"
},
  "geometry": {"coordinates":[-72.769096,45.21032],"type":"Point"}
}