{
  "type": "Feature",
  "properties": {
    "addr:full":"RR 1 STN Main Grande Prairie AB T8V 2Z8",
    "addr:postcode":"t8v 2z8",
    "addr:street":"Rr 1 Stn Main",
    "iso:country":"CA",
    "sg:address":"RR 1 STN Main",
    "sg:city":"Grande Prairie",
    "sg:classifiers":[
        {
            "category":"Wholesale",
            "subcategory":"Machinery & Supplies",
            "type":"Manufacturing & Wholesale Goods"
        }
    ],
    "sg:phone":"+1 780 532 1652",
    "sg:postcode":"T8V 2Z8",
    "sg:province":"AB",
    "sg:tags":[
        "engine"
    ],
    "wof:name":"West Country Products Grande",
    "wof:placetype":"venue"
},
  "geometry": {"coordinates":[-118.794891357,55.1711616516],"type":"Point"}
}