{
  "type": "Feature",
  "properties": {
    "addr:full":"London ON N6L 1G9",
    "addr:postcode":"n6l 1g9",
    "iso:country":"CA",
    "sg:city":"London",
    "sg:classifiers":[
        {
            "category":"Professional",
            "subcategory":"Business Services",
            "type":"Services"
        }
    ],
    "sg:phone":"+1 519 652 6566",
    "sg:postcode":"N6L 1G9",
    "sg:province":"ON",
    "sg:tags":[
        "salvage",
        "surplus",
        "merchandise",
        "liquidator"
    ],
    "wof:name":"City Centre Liquidations",
    "wof:placetype":"venue"
},
  "geometry": {"coordinates":[-81.2665939331,42.9206390381],"type":"Point"}
}