{
  "type": "Feature",
  "properties": {
    "addr:full":"250 Bunting Rd St Catharines ON L2M 3Y1",
    "addr:housenumber":"250",
    "addr:postcode":"l2m 3y1",
    "addr:street":"Bunting Rd",
    "iso:country":"CA",
    "sg:address":"250 Bunting Rd",
    "sg:city":"St Catharines",
    "sg:classifiers":[
        {
            "category":"Manufacturing",
            "subcategory":"Apparel",
            "type":"Manufacturing & Wholesale Goods"
        }
    ],
    "sg:phone":"+1 905 688 6100",
    "sg:postcode":"L2M 3Y1",
    "sg:province":"ON",
    "sg:tags":[
        "clothing"
    ],
    "wof:name":"Calhoun Sportswear",
    "wof:placetype":"venue"
},
  "geometry": {"coordinates":[-79.209885,43.173992],"type":"Point"}
}