{
  "type": "Feature",
  "properties": {
    "addr:full":"106 Rue Saint-Eustache Saint-Eustache QC J7R 2K9",
    "addr:housenumber":"106",
    "addr:postcode":"j7r 2k9",
    "addr:street":"Rue Saint-Eustache",
    "iso:country":"CA",
    "sg:address":"106 Rue Saint-Eustache",
    "sg:city":"Saint-Eustache",
    "sg:classifiers":[
        {
            "category":"Restaurant",
            "type":"Food & Drink"
        }
    ],
    "sg:phone":"+1 450 472 1414",
    "sg:postcode":"J7R 2K9",
    "sg:province":"QC",
    "wof:name":"Restaurant Chateau Lafitte",
    "wof:placetype":"venue"
},
  "geometry": {"coordinates":[-73.8923568726,45.5585441589],"type":"Point"}
}