{
  "type": "Feature",
  "properties": {
    "addr:full":"68 Glendale Dr Tillsonburg ON N4G 1J7",
    "addr:housenumber":"68",
    "addr:postcode":"n4g 1j7",
    "addr:street":"Glendale Dr",
    "iso:country":"CA",
    "sg:address":"68 Glendale Dr",
    "sg:city":"Tillsonburg",
    "sg:classifiers":[
        {
            "category":"Personal",
            "subcategory":"Beauty Salon",
            "type":"Services"
        }
    ],
    "sg:phone":"+1 519 842 6623",
    "sg:postcode":"N4G 1J7",
    "sg:province":"ON",
    "wof:name":"Viola's Hair Fashions",
    "wof:placetype":"venue"
},
  "geometry": {"coordinates":[-80.74516300000001,42.869259],"type":"Point"}
}