{
  "type": "Feature",
  "properties": {
    "iso:country":"CA",
    "sg:address":"12325 Mount Lawn Rd NW",
    "sg:city":"Edmonton",
    "sg:classifiers":[
        {
            "category":"Wholesale",
            "subcategory":"Meat",
            "type":"Manufacturing & Wholesale Goods"
        }
    ],
    "sg:phone":"+1 780 471 3030",
    "sg:postcode":"T5B 4J3",
    "sg:province":"AB",
    "wof:name":"Hurley's Meat Distributors Ltd",
    "wof:placetype":"venue"
},
  "geometry": {"coordinates":[-113.451538086,53.578830719],"type":"Point"}
}