{
  "type": "Feature",
  "properties": {
    "addr:full":"2902 St. Johns St Port Moody BC V3H 2C3",
    "addr:housenumber":"2902",
    "addr:postcode":"v3h 2c3",
    "addr:street":"St. Johns St",
    "iso:country":"CA",
    "sg:address":"2902 St. Johns St",
    "sg:city":"Port Moody",
    "sg:classifiers":[
        {
            "category":"Retail",
            "subcategory":"Auto Repair",
            "type":"Services"
        }
    ],
    "sg:phone":"+1 604 461 4040",
    "sg:postcode":"V3H 2C3",
    "sg:province":"BC",
    "sg:tags":[
        "body",
        "automobile",
        "painting"
    ],
    "wof:name":"First Class Auto Body Ltd",
    "wof:placetype":"venue"
},
  "geometry": {"coordinates":[-122.847595215,49.276802063],"type":"Point"}
}