{
  "type": "Feature",
  "properties": {
    "addr:full":"29 Turnbull Rd Ajax ON L1S 2X3",
    "addr:housenumber":"29",
    "addr:postcode":"l1s 2x3",
    "addr:street":"Turnbull Rd",
    "iso:country":"CA",
    "sg:address":"29 Turnbull Rd",
    "sg:city":"Ajax",
    "sg:classifiers":[
        {
            "category":"Building & Trades",
            "subcategory":"Construction",
            "type":"Services"
        }
    ],
    "sg:phone":"+1 905 683 2729",
    "sg:postcode":"L1S 2X3",
    "sg:province":"ON",
    "sg:tags":[
        "home",
        "improvement"
    ],
    "wof:name":"Ajax Home Renovations",
    "wof:placetype":"venue"
},
  "geometry": {"coordinates":[-79.0072097778,43.8381347656],"type":"Point"}
}