{
  "type": "Feature",
  "properties": {
    "addr:full":"206 4 Ave Stirling AB T0K 2E0",
    "addr:housenumber":"206",
    "addr:postcode":"t0k 2e0",
    "addr:street":"4 Ave",
    "iso:country":"CA",
    "sg:address":"206 4 Ave",
    "sg:city":"Stirling",
    "sg:classifiers":[
        {
            "category":"Organizations",
            "subcategory":"Non-profit Organization",
            "type":"Services"
        }
    ],
    "sg:phone":"+1 403 756 3057",
    "sg:postcode":"T0K 2E0",
    "sg:province":"AB",
    "sg:tags":[
        "disability"
    ],
    "wof:name":"Sterling Handicapped Program",
    "wof:placetype":"venue"
},
  "geometry": {"coordinates":[-112.520355225,49.5020942688],"type":"Point"}
}