{
  "type": "Feature",
  "properties": {
    "addr:full":"2855 Wentworth Rd Courtenay BC V9N 6B7",
    "addr:housenumber":"2855",
    "addr:postcode":"v9n 6b7",
    "addr:street":"Wentworth Rd",
    "iso:country":"CA",
    "sg:address":"2855 Wentworth Rd",
    "sg:city":"Courtenay",
    "sg:classifiers":[
        {
            "category":"Home & Garden",
            "subcategory":"Garden Supply",
            "type":"Retail Goods"
        }
    ],
    "sg:phone":"+1 250 334 3024",
    "sg:postcode":"V9N 6B7",
    "sg:province":"BC",
    "sg:tags":[
        "nurseryman",
        "center"
    ],
    "wof:name":"Art Knapp's Plantland",
    "wof:placetype":"venue"
},
  "geometry": {"coordinates":[-124.993141174,49.6867218018],"type":"Point"}
}