{
  "type": "Feature",
  "properties": {
    "addr:full":"355 Heritage Dr SE Calgary AB T2H 1M8",
    "addr:housenumber":"355",
    "addr:postcode":"t2h 1m8",
    "addr:street":"Heritage Dr Se",
    "iso:country":"CA",
    "sg:address":"355 Heritage Dr SE",
    "sg:city":"Calgary",
    "sg:classifiers":[
        {
            "category":"Real Estate",
            "subcategory":"Real Estate Agent",
            "type":"Services"
        }
    ],
    "sg:phone":"+1 403 255 2550",
    "sg:postcode":"T2H 1M8",
    "sg:province":"AB",
    "wof:name":"S J Williams & Assoc Ltd",
    "wof:placetype":"venue"
},
  "geometry": {"coordinates":[-114.061645508,50.9794273376],"type":"Point"}
}