{
  "type": "Feature",
  "properties": {
    "addr:full":"22 Cherrywood Dr Nepean ON K2H 6G7",
    "addr:housenumber":"22",
    "addr:postcode":"k2h 6g7",
    "addr:street":"Cherrywood Dr",
    "iso:country":"CA",
    "sg:address":"22 Cherrywood Dr",
    "sg:city":"Nepean",
    "sg:classifiers":[
        {
            "category":"Organizations",
            "subcategory":"Religious Organization",
            "type":"Services"
        }
    ],
    "sg:phone":"+1 613 828 0814",
    "sg:postcode":"K2H 6G7",
    "sg:province":"ON",
    "sg:tags":[
        "church"
    ],
    "wof:name":"Christian Science Church",
    "wof:placetype":"venue"
},
  "geometry": {"coordinates":[-75.81514,45.317799],"type":"Point"}
}