{
  "type": "Feature",
  "properties": {
    "addr:full":"226 Industrial Pky N Aurora ON L4G 4C3",
    "addr:housenumber":"226",
    "addr:postcode":"l4g 4c3",
    "addr:street":"Industrial Pky N",
    "iso:country":"CA",
    "sg:address":"226 Industrial Pky N",
    "sg:city":"Aurora",
    "sg:classifiers":[
        {
            "category":"Wholesale",
            "subcategory":"Machinery & Supplies",
            "type":"Manufacturing & Wholesale Goods"
        }
    ],
    "sg:phone":"+1 905 841 6633",
    "sg:postcode":"L4G 4C3",
    "sg:province":"ON",
    "sg:tags":[
        "equipment",
        "foundry"
    ],
    "wof:name":"Canadian Thermix Inc",
    "wof:placetype":"venue"
},
  "geometry": {"coordinates":[-79.462799,44.013721],"type":"Point"}
}