{
  "type": "Feature",
  "properties": {
    "iso:country":"CA",
    "sg:address":"480 Hespeler Rd",
    "sg:city":"Cambridge",
    "sg:classifiers":[
        {
            "category":"Cinema",
            "subcategory":"Movie Rental",
            "type":"Entertainment"
        }
    ],
    "sg:phone":"+1 519 740 7750",
    "sg:postcode":"N1R 7R9",
    "sg:province":"ON",
    "sg:tags":[
        "leasing",
        "video",
        "disc",
        "tape"
    ],
    "wof:name":"Blockbuster Video",
    "wof:placetype":"venue"
},
  "geometry": {"coordinates":[-80.3252487183,43.3983764648],"type":"Point"}
}