{
  "type": "Feature",
  "properties": {
    "iso:country":"CA",
    "sg:city":"Sainte-Foy",
    "sg:classifiers":[
        {
            "category":"Professional",
            "subcategory":"Computer Services",
            "type":"Services"
        }
    ],
    "sg:phone":"+1 418 658 4003",
    "sg:postcode":"G1V 4K5",
    "sg:province":"QC",
    "sg:tags":[
        "information",
        "system",
        "consultant"
    ],
    "wof:name":"Groupe Agi Inc",
    "wof:placetype":"venue"
},
  "geometry": {"coordinates":[-71.284073,46.769676],"type":"Point"}
}