{
  "type": "Feature",
  "properties": {
    "addr:full":"Southampton ON N0H 2L0",
    "addr:postcode":"n0h 2l0",
    "iso:country":"CA",
    "sg:city":"Southampton",
    "sg:classifiers":[
        {
            "category":"Professional",
            "subcategory":"Accounting & Tax Preparation",
            "type":"Services"
        }
    ],
    "sg:phone":"+1 519 797 5379",
    "sg:postcode":"N0H 2L0",
    "sg:province":"ON",
    "sg:tags":[
        "bookkeeping",
        "return",
        "filing",
        "general"
    ],
    "wof:name":"Bookkeeper",
    "wof:placetype":"venue"
},
  "geometry": {"coordinates":[-81.372589,44.497326],"type":"Point"}
}