{
  "type": "Feature",
  "properties": {
    "addr:full":"2 W Front St Stirling ON K0K 3E0",
    "addr:housenumber":"2",
    "addr:postcode":"k0k 3e0",
    "addr:street":"W Front St",
    "iso:country":"CA",
    "sg:address":"2 W Front St",
    "sg:city":"Stirling",
    "sg:classifiers":[
        {
            "category":"Restaurant",
            "type":"Food & Drink"
        }
    ],
    "sg:phone":"+1 613 395 5111",
    "sg:postcode":"K0K 3E0",
    "sg:province":"ON",
    "wof:name":"Jimmy's Spec Pizza Fish & Chip",
    "wof:placetype":"venue"
},
  "geometry": {"coordinates":[-77.54755400000001,44.296158],"type":"Point"}
}