{
  "type": "Feature",
  "properties": {
    "addr:full":"12336 45 St NW Edmonton AB T5W 5C1",
    "addr:housenumber":"12336",
    "addr:postcode":"t5w 5c1",
    "addr:street":"45 St Nw",
    "iso:country":"CA",
    "sg:address":"12336 45 St NW",
    "sg:city":"Edmonton",
    "sg:classifiers":[
        {
            "category":"Building & Trades",
            "subcategory":"Plumbing",
            "type":"Services"
        }
    ],
    "sg:phone":"+1 780 479 1795",
    "sg:postcode":"T5W 5C1",
    "sg:province":"AB",
    "sg:tags":[
        "contractor"
    ],
    "wof:name":"Horizon Plumbing Svc",
    "wof:placetype":"venue"
},
  "geometry": {"coordinates":[-113.41089630099999,53.579410553],"type":"Point"}
}