{
  "type": "Feature",
  "properties": {
    "addr:full":"Saskatoon SK S7H 5M3",
    "addr:postcode":"s7h 5m3",
    "iso:country":"CA",
    "sg:city":"Saskatoon",
    "sg:classifiers":[
        {
            "category":"Wholesale",
            "subcategory":"Hardware",
            "type":"Manufacturing & Wholesale Goods"
        }
    ],
    "sg:phone":"+1 306 374 3343",
    "sg:postcode":"S7H 5M3",
    "sg:province":"SK",
    "sg:tags":[
        "housewares"
    ],
    "wof:name":"Cutting Edge Cutlery CO",
    "wof:placetype":"venue"
},
  "geometry": {"coordinates":[-106.60267639200001,52.1144218445],"type":"Point"}
}