{
  "type": "Feature",
  "properties": {
    "addr:full":"Etobicoke ON M9A 3T7",
    "addr:postcode":"m9a 3t7",
    "iso:country":"CA",
    "sg:city":"Etobicoke",
    "sg:classifiers":[
        {
            "category":"Food & Beverages",
            "subcategory":"Groceries & Convenience Stores",
            "type":"Retail Goods"
        }
    ],
    "sg:phone":"+1 416 231 9515",
    "sg:postcode":"M9A 3T7",
    "sg:province":"ON",
    "wof:name":"Humbertown Convenience",
    "wof:placetype":"venue"
},
  "geometry": {"coordinates":[-79.52010300000001,43.662872],"type":"Point"}
}