{
  "type": "Feature",
  "properties": {
    "iso:country":"CA",
    "sg:address":"4725 Rte Marie-Victorin",
    "sg:city":"Contrecoeur",
    "sg:classifiers":[
        {
            "category":"Cinema",
            "subcategory":"Movie Rental",
            "type":"Entertainment"
        }
    ],
    "sg:phone":"+1 450 587 8440",
    "sg:postcode":"J0L 1C0",
    "sg:province":"QC",
    "sg:tags":[
        "leasing",
        "video",
        "disc",
        "tape"
    ],
    "wof:name":"Club Videotheque Enr",
    "wof:placetype":"venue"
},
  "geometry": {"coordinates":[-73.24206542970001,45.8545951843],"type":"Point"}
}