{
  "type": "Feature",
  "properties": {
    "addr:full":"1977 Kennedy Rd Scarborough ON M1P 2M1",
    "addr:housenumber":"1977",
    "addr:postcode":"m1p 2m1",
    "addr:street":"Kennedy Rd",
    "iso:country":"CA",
    "sg:address":"1977 Kennedy Rd",
    "sg:city":"Scarborough",
    "sg:classifiers":[
        {
            "category":"Autos & Motor Vehicles",
            "subcategory":"Fuel & Gas Station",
            "type":"Retail Goods"
        }
    ],
    "sg:phone":"+1 416 298 0017",
    "sg:postcode":"M1P 2M1",
    "sg:province":"ON",
    "sg:tags":[
        "oil"
    ],
    "wof:name":"Sunoco",
    "wof:placetype":"venue"
},
  "geometry": {"coordinates":[-79.2822265625,43.7697753906],"type":"Point"}
}