{
  "type": "Feature",
  "properties": {
    "addr:full":"516 Victoria Ave E Thunder Bay ON P7C 1A7",
    "addr:housenumber":"516",
    "addr:postcode":"p7c 1a7",
    "addr:street":"Victoria Ave E",
    "iso:country":"CA",
    "sg:address":"516 Victoria Ave E",
    "sg:city":"Thunder Bay",
    "sg:classifiers":[
        {
            "category":"Shopping",
            "subcategory":"Shoes",
            "type":"Retail Goods"
        }
    ],
    "sg:phone":"+1 807 623 1740",
    "sg:postcode":"P7C 1A7",
    "sg:province":"ON",
    "sg:tags":[
        "sporting"
    ],
    "wof:name":"Take A Hike",
    "wof:placetype":"venue"
},
  "geometry": {"coordinates":[-89.245689,48.383926],"type":"Point"}
}