{
  "type": "Feature",
  "properties": {
    "addr:full":"374 Rue Principale Saint-Jacques NB E7B 1X7",
    "addr:housenumber":"374",
    "addr:postcode":"e7b 1x7",
    "addr:street":"Rue Principale",
    "iso:country":"CA",
    "sg:address":"374 Rue Principale",
    "sg:city":"Saint-Jacques",
    "sg:classifiers":[
        {
            "category":"Restaurant",
            "type":"Food & Drink"
        }
    ],
    "sg:phone":"+1 506 735 4072",
    "sg:postcode":"E7B 1X7",
    "sg:province":"NB",
    "wof:name":"Jose's Pizza",
    "wof:placetype":"venue"
},
  "geometry": {"coordinates":[-68.37744903559999,47.4183998108],"type":"Point"}
}