{
  "type": "Feature",
  "properties": {
    "iso:country":"CA",
    "sg:city":"Winnipeg",
    "sg:classifiers":[
        {
            "category":"Shopping",
            "subcategory":"Computers & Home Electronics",
            "type":"Retail Goods"
        }
    ],
    "sg:phone":"+1 204 632 4966",
    "sg:postcode":"R2R 1T9",
    "sg:province":"MB",
    "sg:tags":[
        "band",
        "parts",
        "truck",
        "equipment"
    ],
    "wof:name":"18 Wheeler Truck Accessories",
    "wof:placetype":"venue"
},
  "geometry": {"coordinates":[-97.2180557251,49.9345817566],"type":"Point"}
}