{
  "type": "Feature",
  "properties": {
    "iso:country":"CA",
    "sg:address":"410 Rue Boulianne",
    "sg:city":"Dolbeau-Mistassini",
    "sg:classifiers":[
        {
            "category":"Retail",
            "subcategory":"Repair Shop",
            "type":"Services"
        }
    ],
    "sg:phone":"+1 418 276 6668",
    "sg:postcode":"G8L 6B4",
    "sg:province":"QC",
    "sg:tags":[
        "machinery"
    ],
    "wof:name":"Garage Germain Paquet",
    "wof:placetype":"venue"
},
  "geometry": {"coordinates":[-72.1828384399,48.8811759949],"type":"Point"}
}