{
  "type": "Feature",
  "properties": {
    "addr:full":"4303 20 Ave NW Edmonton AB T6L 5Y4",
    "addr:housenumber":"4303",
    "addr:postcode":"t6l 5y4",
    "addr:street":"20 Ave Nw",
    "iso:country":"CA",
    "sg:address":"4303 20 Ave NW",
    "sg:city":"Edmonton",
    "sg:classifiers":[
        {
            "category":"Organizations",
            "subcategory":"Religious Organization",
            "type":"Services"
        }
    ],
    "sg:phone":"+1 780 450 1738",
    "sg:postcode":"T6L 5Y4",
    "sg:province":"AB",
    "sg:tags":[
        "church"
    ],
    "wof:name":"Church of Jesus Christ-Lds",
    "wof:placetype":"venue"
},
  "geometry": {"coordinates":[-113.408241,53.451794],"type":"Point"}
}