{
  "type": "Feature",
  "properties": {
    "addr:full":"9819 97 Ave Grande Prairie AB T8V 0M9",
    "addr:housenumber":"9819",
    "addr:postcode":"t8v 0m9",
    "addr:street":"97 Ave",
    "iso:country":"CA",
    "sg:address":"9819 97 Ave",
    "sg:city":"Grande Prairie",
    "sg:classifiers":[
        {
            "category":"Taxi",
            "type":"Transportation"
        }
    ],
    "sg:phone":"+1 780 539 3366",
    "sg:postcode":"T8V 0M9",
    "sg:province":"AB",
    "sg:tags":[
        "taxicab"
    ],
    "wof:name":"Yellow Cab",
    "wof:placetype":"venue"
},
  "geometry": {"coordinates":[-118.789260864,55.1678390503],"type":"Point"}
}