{
  "type": "Feature",
  "properties": {
    "iso:country":"CA",
    "sg:address":"1308 Rue Du Concorde",
    "sg:city":"Fleurimont",
    "sg:classifiers":[
        {
            "category":"Personal",
            "subcategory":"Beauty Salon",
            "type":"Services"
        }
    ],
    "sg:phone":"+1 819 820 2863",
    "sg:postcode":"J1E 1C3",
    "sg:province":"QC",
    "wof:name":"Salon DE Coiffure Yakim",
    "wof:placetype":"venue"
},
  "geometry": {"coordinates":[-71.89312,45.425926],"type":"Point"}
}