{
  "type": "Feature",
  "properties": {
    "addr:full":"5920 Prince of Wales Dr North Gower ON K0A 2T0",
    "addr:housenumber":"5920",
    "addr:postcode":"k0a 2t0",
    "addr:street":"Prince Of Wales Dr",
    "iso:country":"CA",
    "sg:address":"5920 Prince of Wales Dr",
    "sg:city":"North Gower",
    "sg:classifiers":[
        {
            "category":"Recreation",
            "type":"Entertainment"
        }
    ],
    "sg:phone":"+1 613 489 2066",
    "sg:postcode":"K0A 2T0",
    "sg:province":"ON",
    "sg:tags":[
        "golf",
        "banquet",
        "rooms"
    ],
    "wof:name":"Manderley Golf & Country Club",
    "wof:placetype":"venue"
},
  "geometry": {"coordinates":[-75.70983099999999,45.153542],"type":"Point"}
}