{
  "type": "Feature",
  "properties": {
    "iso:country":"CA",
    "sg:address":"1167 173 Rte S",
    "sg:city":"Saint-Joseph-DE-Beauce",
    "sg:classifiers":[
        {
            "category":"Retail",
            "subcategory":"Veterinary Services",
            "type":"Services"
        }
    ],
    "sg:phone":"+1 418 397 4934",
    "sg:postcode":"G0S 2V0",
    "sg:province":"QC",
    "sg:tags":[
        "veterinarian"
    ],
    "wof:name":"Clinique Veterinaire St-Joseph",
    "wof:placetype":"venue"
},
  "geometry": {"coordinates":[-70.87535095210001,46.3120574951],"type":"Point"}
}