{
  "type": "Feature",
  "properties": {
    "addr:full":"Conception Bay South NL A1W 3A6",
    "addr:postcode":"a1w 3a6",
    "iso:country":"CA",
    "sg:city":"Conception Bay South",
    "sg:classifiers":[
        {
            "category":"Professional",
            "subcategory":"Employment Agencies",
            "type":"Services"
        }
    ],
    "sg:phone":"+1 709 834 8723",
    "sg:postcode":"A1W 3A6",
    "sg:province":"NL",
    "sg:tags":[
        "co",
        "fraternal"
    ],
    "wof:name":"Employment Service",
    "wof:placetype":"venue"
},
  "geometry": {"coordinates":[-52.956005,47.51881],"type":"Point"}
}