{
  "type": "Feature",
  "properties": {
    "iso:country":"CA",
    "sg:address":"274 Commercial St",
    "sg:city":"North Sydney",
    "sg:classifiers":[
        {
            "category":"Personal",
            "subcategory":"Beauty Salon",
            "type":"Services"
        }
    ],
    "sg:phone":"+1 902 794 3554",
    "sg:postcode":"B2A 1B8",
    "sg:province":"NS",
    "wof:name":"Curl Up & Dye",
    "wof:placetype":"venue"
},
  "geometry": {"coordinates":[-60.248867,46.209053],"type":"Point"}
}