{
  "type": "Feature",
  "properties": {
    "iso:country":"CA",
    "sg:address":"740 Rue Du Conseil",
    "sg:city":"Sherbrooke",
    "sg:classifiers":[
        {
            "category":"Wholesale",
            "subcategory":"Meat",
            "type":"Manufacturing & Wholesale Goods"
        }
    ],
    "sg:phone":"+1 819 569 7688",
    "sg:postcode":"J1G 1K9",
    "sg:province":"QC",
    "sg:tags":[
        "butchering"
    ],
    "wof:name":"Boucherie Guertin Nova",
    "wof:placetype":"venue"
},
  "geometry": {"coordinates":[-71.8728637695,45.4035072327],"type":"Point"}
}