{
  "type": "Feature",
  "properties": {
    "addr:full":"585 Sackville Dr Lower Sackville NS B4C 2S4",
    "addr:housenumber":"585",
    "addr:postcode":"b4c 2s4",
    "addr:street":"Sackville Dr",
    "iso:country":"CA",
    "sg:address":"585 Sackville Dr",
    "sg:city":"Lower Sackville",
    "sg:classifiers":[
        {
            "category":"Home & Garden",
            "subcategory":"Household Appliances",
            "type":"Retail Goods"
        }
    ],
    "sg:phone":"+1 902 865 9997",
    "sg:postcode":"B4C 2S4",
    "sg:province":"NS",
    "sg:tags":[
        "mail",
        "catalog",
        "shopping",
        "order"
    ],
    "wof:name":"Sears Canada Inc",
    "wof:placetype":"venue"
},
  "geometry": {"coordinates":[-63.6850967407,44.7681617737],"type":"Point"}
}