{
  "type": "Feature",
  "properties": {
    "addr:full":"18 Wynford Dr # 405 North York ON M3C 3S2",
    "addr:housenumber":"18;405",
    "addr:postcode":"m3c 3s2",
    "addr:street":"Wynford Dr #",
    "iso:country":"CA",
    "sg:address":"18 Wynford Dr # 405",
    "sg:city":"North York",
    "sg:classifiers":[
        {
            "category":"Manufacturing",
            "subcategory":"Printing",
            "type":"Manufacturing & Wholesale Goods"
        }
    ],
    "sg:phone":"+1 416 368 4993",
    "sg:postcode":"M3C 3S2",
    "sg:province":"ON",
    "sg:tags":[
        "multimedia"
    ],
    "wof:name":"Deltech Communications Group",
    "wof:placetype":"venue"
},
  "geometry": {"coordinates":[-79.33697509770001,43.7235908508],"type":"Point"}
}