{
  "type": "Feature",
  "properties": {
    "addr:full":"123 Government Rd N Stoughton SK S0G 4T0",
    "addr:housenumber":"123",
    "addr:postcode":"s0g 4t0",
    "addr:street":"Government Rd N",
    "iso:country":"CA",
    "sg:address":"123 Government Rd N",
    "sg:city":"Stoughton",
    "sg:classifiers":[
        {
            "category":"Health Services",
            "subcategory":"Nursing And Care Facility",
            "type":"Services"
        }
    ],
    "sg:phone":"+1 306 457 2552",
    "sg:postcode":"S0G 4T0",
    "sg:province":"SK",
    "sg:tags":[
        "home",
        "convalescent"
    ],
    "wof:name":"Newhope Pioneer Lodge",
    "wof:placetype":"venue"
},
  "geometry": {"coordinates":[-103.02253,49.67664],"type":"Point"}
}