{
  "type": "Feature",
  "properties": {
    "addr:full":"181 St George St Lindsay ON K9V 6H5",
    "addr:housenumber":"181",
    "addr:postcode":"k9v 6h5",
    "addr:street":"St George St",
    "iso:country":"CA",
    "sg:address":"181 St George St",
    "sg:city":"Lindsay",
    "sg:classifiers":[
        {
            "category":"Manufacturing",
            "subcategory":"Tools & Machinery",
            "type":"Manufacturing & Wholesale Goods"
        }
    ],
    "sg:phone":"+1 705 324 4303",
    "sg:postcode":"K9V 6H5",
    "sg:province":"ON",
    "sg:tags":[
        "machine",
        "shop"
    ],
    "wof:name":"Falcon Tool & Mould",
    "wof:placetype":"venue"
},
  "geometry": {"coordinates":[-78.7292938232,44.3727149963],"type":"Point"}
}