{
  "type": "Feature",
  "properties": {
    "addr:full":"70 Market St #400 Brantford ON N3T 2Z7",
    "addr:housenumber":"70",
    "addr:postcode":"n3t 2z7",
    "addr:street":"Market St # 400",
    "iso:country":"CA",
    "sg:address":"70 Market St #400",
    "sg:city":"Brantford",
    "sg:classifiers":[
        {
            "category":"Professional",
            "subcategory":"Lawyer & Legal Services",
            "type":"Services"
        }
    ],
    "sg:phone":"+1 519 759 0900",
    "sg:postcode":"N3T 2Z7",
    "sg:province":"ON",
    "sg:tags":[
        "attorney"
    ],
    "wof:name":"Reeves, Douglas O",
    "wof:placetype":"venue"
},
  "geometry": {"coordinates":[-80.26387,43.140461],"type":"Point"}
}