{
  "type": "Feature",
  "properties": {
    "addr:full":"6620 Rue Abrams Saint-Laurent QC H4S 1Y1",
    "addr:housenumber":"6620",
    "addr:postcode":"h4s 1y1",
    "addr:street":"Rue Abrams",
    "iso:country":"CA",
    "sg:address":"6620 Rue Abrams",
    "sg:city":"Saint-Laurent",
    "sg:classifiers":[
        {
            "category":"Professional",
            "subcategory":"Business Services",
            "type":"Services"
        }
    ],
    "sg:phone":"+1 514 332 6696",
    "sg:postcode":"H4S 1Y1",
    "sg:province":"QC",
    "sg:tags":[
        "packaging"
    ],
    "wof:name":"Transpack Inc",
    "wof:placetype":"venue"
},
  "geometry": {"coordinates":[-73.7561416626,45.4886054993],"type":"Point"}
}