{
  "type": "Feature",
  "properties": {
    "addr:full":"1900 Hyde Park Rd #4A London ON N6H 5L9",
    "addr:housenumber":"1900",
    "addr:postcode":"n6h 5l9",
    "addr:street":"Hyde Park Rd # 4A",
    "iso:country":"CA",
    "sg:address":"1900 Hyde Park Rd #4A",
    "sg:city":"London",
    "sg:classifiers":[
        {
            "category":"Retail",
            "subcategory":"Animal Services",
            "type":"Services"
        }
    ],
    "sg:phone":"+1 519 870 1402",
    "sg:postcode":"N6H 5L9",
    "sg:province":"ON",
    "sg:tags":[
        "pet",
        "training"
    ],
    "wof:name":"Sure Victor",
    "wof:placetype":"venue"
},
  "geometry": {"coordinates":[-81.3360214233,43.0062217712],"type":"Point"}
}