{
  "type": "Feature",
  "properties": {
    "addr:full":"866 Saskatchewan Cres E Saskatoon SK S7N 0L4",
    "addr:housenumber":"866",
    "addr:postcode":"s7n 0l4",
    "addr:street":"Saskatchewan Cres E",
    "iso:country":"CA",
    "sg:address":"866 Saskatchewan Cres E",
    "sg:city":"Saskatoon",
    "sg:classifiers":[
        {
            "category":"Organizations",
            "subcategory":"Religious Organization",
            "type":"Services"
        }
    ],
    "sg:phone":"+1 306 653 0138",
    "sg:postcode":"S7N 0L4",
    "sg:province":"SK",
    "sg:tags":[
        "church"
    ],
    "wof:name":"Bishop's Chancery Eparchy Sask",
    "wof:placetype":"venue"
},
  "geometry": {"coordinates":[-106.651352,52.126232],"type":"Point"}
}