{
  "type": "Feature",
  "properties": {
    "addr:full":"Bashaw AB T0B 0H0",
    "addr:postcode":"t0b 0h0",
    "iso:country":"CA",
    "sg:city":"Bashaw",
    "sg:classifiers":[
        {
            "category":"Wholesale",
            "subcategory":"Petroleum",
            "type":"Manufacturing & Wholesale Goods"
        }
    ],
    "sg:phone":"+1 780 372 3865",
    "sg:postcode":"T0B 0H0",
    "sg:province":"AB",
    "sg:tags":[
        "bulk",
        "oil",
        "gasoline"
    ],
    "wof:name":"Ufa",
    "wof:placetype":"venue"
},
  "geometry": {"coordinates":[-112.976486206,52.5800209045],"type":"Point"}
}