{
  "type": "Feature",
  "properties": {
    "addr:full":"22755 Hwy 7 E Maberly ON K0H 2B0",
    "addr:housenumber":"22755",
    "addr:postcode":"k0h 2b0",
    "addr:street":"Hwy 7 E Maberly",
    "iso:country":"CA",
    "sg:address":"22755 Hwy 7 E",
    "sg:city":"Maberly",
    "sg:classifiers":[
        {
            "category":"Restaurant",
            "type":"Food & Drink"
        }
    ],
    "sg:phone":"+1 613 268 2224",
    "sg:postcode":"K0H 2B0",
    "sg:province":"ON",
    "wof:name":"Silver Seven Quality Food",
    "wof:placetype":"venue"
},
  "geometry": {"coordinates":[-76.577164,44.829021],"type":"Point"}
}