{
  "type": "Feature",
  "properties": {
    "iso:country":"CA",
    "sg:city":"Mississauga",
    "sg:classifiers":[
        {
            "category":"Personal",
            "subcategory":"Beauty Salon",
            "type":"Services"
        }
    ],
    "sg:phone":"+1 905 826 8622",
    "sg:postcode":"L5M 2P4",
    "sg:province":"ON",
    "wof:name":"Winchester Place Men's Hrstylg",
    "wof:placetype":"venue"
},
  "geometry": {"coordinates":[-79.5979690552,43.5455169678],"type":"Point"}
}