{
  "type": "Feature",
  "properties": {
    "addr:full":"2 Dundas St W Napanee ON K7R 1Z4",
    "addr:housenumber":"2",
    "addr:postcode":"k7r 1z4",
    "addr:street":"Dundas St W",
    "iso:country":"CA",
    "sg:address":"2 Dundas St W",
    "sg:city":"Napanee",
    "sg:classifiers":[
        {
            "category":"Restaurant",
            "type":"Food & Drink"
        }
    ],
    "sg:phone":"+1 613 354 4243",
    "sg:postcode":"K7R 1Z4",
    "sg:province":"ON",
    "wof:name":"Superior Restaurant",
    "wof:placetype":"venue"
},
  "geometry": {"coordinates":[-76.950569,44.247139],"type":"Point"}
}