{
  "type": "Feature",
  "properties": {
    "iso:country":"CA",
    "sg:address":"30 Norwood Cres",
    "sg:city":"Regina",
    "sg:classifiers":[
        {
            "category":"Professional",
            "subcategory":"Computer Services",
            "type":"Services"
        }
    ],
    "sg:phone":"+1 306 924 0716",
    "sg:postcode":"S4R 0A1",
    "sg:province":"SK",
    "sg:tags":[
        "consultant"
    ],
    "wof:name":"Dns Innovative Systems",
    "wof:placetype":"venue"
},
  "geometry": {"coordinates":[-104.614479,50.49263],"type":"Point"}
}