{
  "type": "Feature",
  "properties": {
    "addr:full":"2 Windfield Cres Kanata ON K2M 2B6",
    "addr:housenumber":"2",
    "addr:postcode":"k2m 2b6",
    "addr:street":"Windfield Cres",
    "iso:country":"CA",
    "sg:address":"2 Windfield Cres",
    "sg:city":"Kanata",
    "sg:classifiers":[
        {
            "category":"Building & Trades",
            "subcategory":"Construction",
            "type":"Services"
        }
    ],
    "sg:phone":"+1 613 599 7610",
    "sg:postcode":"K2M 2B6",
    "sg:province":"ON",
    "sg:tags":[
        "general",
        "contractor"
    ],
    "wof:name":"Klinger Homes",
    "wof:placetype":"venue"
},
  "geometry": {"coordinates":[-75.8500747681,45.2906761169],"type":"Point"}
}