{
  "type": "Feature",
  "properties": {
    "addr:full":"115 Rue Principale Ham-Nord QC G0P 1A0",
    "addr:housenumber":"115",
    "addr:postcode":"g0p 1a0",
    "addr:street":"Rue Principale",
    "iso:country":"CA",
    "sg:address":"115 Rue Principale",
    "sg:city":"Ham-Nord",
    "sg:classifiers":[
        {
            "category":"Manufacturing",
            "subcategory":"Lumber",
            "type":"Manufacturing & Wholesale Goods"
        }
    ],
    "sg:phone":"+1 819 344 2232",
    "sg:postcode":"G0P 1A0",
    "sg:province":"QC",
    "sg:tags":[
        "forester"
    ],
    "wof:name":"Amenagement Forestier Coop",
    "wof:placetype":"venue"
},
  "geometry": {"coordinates":[-71.6408004761,45.9002571106],"type":"Point"}
}