{
  "type": "Feature",
  "properties": {
    "iso:country":"CA",
    "sg:address":"622 Rue DE Hull",
    "sg:city":"Lasalle",
    "sg:classifiers":[
        {
            "category":"Wholesale",
            "subcategory":"Electrical",
            "type":"Manufacturing & Wholesale Goods"
        }
    ],
    "sg:phone":"+1 514 367 1764",
    "sg:postcode":"H8R 1V9",
    "sg:province":"QC",
    "sg:tags":[
        "transmission",
        "equipment",
        "power"
    ],
    "wof:name":"Renold Canada Ltd",
    "wof:placetype":"venue"
},
  "geometry": {"coordinates":[-73.641647,45.435326],"type":"Point"}
}