{
  "type": "Feature",
  "properties": {
    "addr:full":"1999 Wellington Ave Winnipeg MB R3H 1H5",
    "addr:housenumber":"1999",
    "addr:postcode":"r3h 1h5",
    "addr:street":"Wellington Ave",
    "iso:country":"CA",
    "sg:address":"1999 Wellington Ave",
    "sg:city":"Winnipeg",
    "sg:classifiers":[
        {
            "category":"Travel",
            "subcategory":"Hotels & Motels",
            "type":"Entertainment"
        }
    ],
    "sg:phone":"+1 204 775 5222",
    "sg:postcode":"R3H 1H5",
    "sg:province":"MB",
    "wof:name":"Four Points Sheraton Winnipeg",
    "wof:placetype":"venue"
},
  "geometry": {"coordinates":[-97.22566223139999,49.9040641785],"type":"Point"}
}