{
  "type": "Feature",
  "properties": {
    "addr:full":"120 Massey Dr North Bay ON P1A 4K9",
    "addr:housenumber":"120",
    "addr:postcode":"p1a 4k9",
    "addr:street":"Massey Dr",
    "iso:country":"CA",
    "sg:address":"120 Massey Dr",
    "sg:city":"North Bay",
    "sg:classifiers":[
        {
            "category":"Organizations",
            "subcategory":"Professional Association",
            "type":"Services"
        }
    ],
    "sg:phone":"+1 705 497 1773",
    "sg:postcode":"P1A 4K9",
    "sg:province":"ON",
    "sg:tags":[
        "housing"
    ],
    "wof:name":"Native People of Nipissing",
    "wof:placetype":"venue"
},
  "geometry": {"coordinates":[-79.43438,46.273533],"type":"Point"}
}