{
  "type": "Feature",
  "properties": {
    "iso:country":"CA",
    "sg:address":"180 Kenneth Ave",
    "sg:city":"Kitchener",
    "sg:classifiers":[
        {
            "category":"Building & Trades",
            "subcategory":"Cleaning & Sanitation",
            "type":"Services"
        }
    ],
    "sg:phone":"+1 519 894 2224",
    "sg:postcode":"N2A 1W2",
    "sg:province":"ON",
    "sg:tags":[
        "house"
    ],
    "wof:name":"Cleanland",
    "wof:placetype":"venue"
},
  "geometry": {"coordinates":[-80.448692,43.441399],"type":"Point"}
}