{
  "type": "Feature",
  "properties": {
    "addr:full":"2209 48 Ave Vernon BC V1T 3P9",
    "addr:housenumber":"2209",
    "addr:postcode":"v1t 3p9",
    "addr:street":"48 Ave",
    "iso:country":"CA",
    "sg:address":"2209 48 Ave",
    "sg:city":"Vernon",
    "sg:classifiers":[
        {
            "category":"Home & Garden",
            "subcategory":"Building Materials",
            "type":"Retail Goods"
        }
    ],
    "sg:phone":"+1 250 545 4355",
    "sg:postcode":"V1T 3P9",
    "sg:province":"BC",
    "sg:tags":[
        "glass",
        "window",
        "plate"
    ],
    "wof:name":"Sun Valley Glass",
    "wof:placetype":"venue"
},
  "geometry": {"coordinates":[-119.26096344,50.2821083069],"type":"Point"}
}