{
  "type": "Feature",
  "properties": {
    "addr:full":"1416 Front St Hearst ON P0L 1N0",
    "addr:housenumber":"1416",
    "addr:postcode":"p0l 1n0",
    "addr:street":"Front St",
    "iso:country":"CA",
    "sg:address":"1416 Front St",
    "sg:city":"Hearst",
    "sg:classifiers":[
        {
            "category":"Freight",
            "type":"Transportation"
        }
    ],
    "sg:phone":"+1 705 362 4675",
    "sg:postcode":"P0L 1N0",
    "sg:province":"ON",
    "sg:tags":[
        "warehouse",
        "storage"
    ],
    "wof:name":"Warehouse Gagne Entrepots",
    "wof:placetype":"venue"
},
  "geometry": {"coordinates":[-83.678802,49.69101],"type":"Point"}
}