{
  "type": "Feature",
  "properties": {
    "iso:country":"CA",
    "sg:address":"1509 Rue DE L'Eglise",
    "sg:city":"Saint-Jean-Chrysostome",
    "sg:classifiers":[
        {
            "category":"Wholesale",
            "subcategory":"Scrap",
            "type":"Manufacturing & Wholesale Goods"
        }
    ],
    "sg:phone":"+1 418 832 7621",
    "sg:postcode":"G6Z 2L1",
    "sg:province":"QC",
    "sg:tags":[
        "metal",
        "iron"
    ],
    "wof:name":"Nittolo Metal 2000 Inc",
    "wof:placetype":"venue"
},
  "geometry": {"coordinates":[-71.1913909912,46.7214393616],"type":"Point"}
}