{
  "type": "Feature",
  "properties": {
    "addr:full":"877 Ch D'Entrelacs Entrelacs QC J0T 2E0",
    "addr:housenumber":"877",
    "addr:postcode":"j0t 2e0",
    "addr:street":"Ch D'Entrelacs",
    "iso:country":"CA",
    "sg:address":"877 Ch D'Entrelacs",
    "sg:city":"Entrelacs",
    "sg:classifiers":[
        {
            "category":"Manufacturing",
            "subcategory":"Lumber",
            "type":"Manufacturing & Wholesale Goods"
        }
    ],
    "sg:phone":"+1 450 228 2253",
    "sg:postcode":"J0T 2E0",
    "sg:province":"QC",
    "sg:tags":[
        "syrup",
        "maple",
        "sugar"
    ],
    "wof:name":"Erabliere Aux 2 Pierrots Senc",
    "wof:placetype":"venue"
},
  "geometry": {"coordinates":[-74.07656860349999,46.0558853149],"type":"Point"}
}