{
  "type": "Feature",
  "properties": {
    "addr:full":"Gatineau QC J8R 3N9",
    "addr:postcode":"j8r 3n9",
    "iso:country":"CA",
    "sg:city":"Gatineau",
    "sg:classifiers":[
        {
            "category":"Building & Trades",
            "subcategory":"Construction",
            "type":"Services"
        }
    ],
    "sg:phone":"+1 819 663 4764",
    "sg:postcode":"J8R 3N9",
    "sg:province":"QC",
    "wof:name":"Batiments Kalad'Art Inc",
    "wof:placetype":"venue"
},
  "geometry": {"coordinates":[-75.592896,45.512592],"type":"Point"}
}