{
  "type": "Feature",
  "properties": {
    "addr:full":"5591 Delta Rd Sechelt BC V0N 3A3",
    "addr:housenumber":"5591",
    "addr:postcode":"v0n 3a3",
    "addr:street":"Delta Rd",
    "iso:country":"CA",
    "sg:address":"5591 Delta Rd",
    "sg:city":"Sechelt",
    "sg:classifiers":[
        {
            "category":"Restaurant",
            "type":"Food & Drink"
        }
    ],
    "sg:phone":"+1 604 885 3847",
    "sg:postcode":"V0N 3A3",
    "sg:province":"BC",
    "wof:name":"Blue Heron Inn",
    "wof:placetype":"venue"
},
  "geometry": {"coordinates":[-123.751846,49.486515],"type":"Point"}
}