{
  "type": "Feature",
  "properties": {
    "addr:full":"Gold Bridge BC V0K 1P0",
    "addr:postcode":"v0k 1p0",
    "iso:country":"CA",
    "sg:city":"Gold Bridge",
    "sg:classifiers":[
        {
            "category":"Travel",
            "subcategory":"Hotels & Motels",
            "type":"Entertainment"
        }
    ],
    "sg:phone":"+1 250 238 2221",
    "sg:postcode":"V0K 1P0",
    "sg:province":"BC",
    "sg:tags":[
        "resort"
    ],
    "wof:name":"Tyax Mountain Lake Resort",
    "wof:placetype":"venue"
},
  "geometry": {"coordinates":[-122.84909820599999,50.851360321],"type":"Point"}
}