{
  "type": "Feature",
  "properties": {
    "addr:full":"Bethany ON L0A 1A0",
    "addr:postcode":"l0a 1a0",
    "iso:country":"CA",
    "sg:city":"Bethany",
    "sg:classifiers":[
        {
            "category":"Freight",
            "type":"Transportation"
        }
    ],
    "sg:phone":"+1 705 277 9318",
    "sg:postcode":"L0A 1A0",
    "sg:province":"ON",
    "sg:tags":[
        "trucking"
    ],
    "wof:name":"Tenbrooks Transportation",
    "wof:placetype":"venue"
},
  "geometry": {"coordinates":[-78.566734,44.182865],"type":"Point"}
}