{
  "type": "Feature",
  "properties": {
    "addr:full":"9275 Boul Langelier Saint-Leonard QC H1P 2Z9",
    "addr:housenumber":"9275",
    "addr:postcode":"h1p 2z9",
    "addr:street":"Boul Langelier",
    "iso:country":"CA",
    "sg:address":"9275 Boul Langelier",
    "sg:city":"Saint-Leonard",
    "sg:classifiers":[
        {
            "category":"Home & Garden",
            "subcategory":"Building Materials",
            "type":"Retail Goods"
        }
    ],
    "sg:phone":"+1 514 326 6800",
    "sg:postcode":"H1P 2Z9",
    "sg:province":"QC",
    "sg:tags":[
        "lumber"
    ],
    "wof:name":"Matco Ravary Inc",
    "wof:placetype":"venue"
},
  "geometry": {"coordinates":[-73.60385100000001,45.605579],"type":"Point"}
}