{
  "type": "Feature",
  "properties": {
    "addr:full":"Sainte-Marcelline-DE-Kildare QC J0K 2Y0",
    "addr:postcode":"j0k 2y0",
    "iso:country":"CA",
    "sg:city":"Sainte-Marcelline-DE-Kildare",
    "sg:classifiers":[
        {
            "category":"Government",
            "subcategory":"Office",
            "type":"Public Place"
        }
    ],
    "sg:phone":"+1 450 883 2241",
    "sg:postcode":"J0K 2Y0",
    "sg:province":"QC",
    "sg:tags":[
        "village"
    ],
    "wof:name":"Ste-Marcelline DE Kildare",
    "wof:placetype":"venue"
},
  "geometry": {"coordinates":[-73.599754,46.120747],"type":"Point"}
}