{
  "type": "Feature",
  "properties": {
    "iso:country":"CA",
    "sg:address":"4421 2 Ave",
    "sg:city":"Edson",
    "sg:classifiers":[
        {
            "category":"Wholesale",
            "subcategory":"Machinery & Supplies",
            "type":"Manufacturing & Wholesale Goods"
        }
    ],
    "sg:phone":"+1 780 723 3378",
    "sg:postcode":"T7E 1C1",
    "sg:province":"AB",
    "sg:tags":[
        "equipment",
        "industrial"
    ],
    "wof:name":"Acklands-Grainger",
    "wof:placetype":"venue"
},
  "geometry": {"coordinates":[-116.416931152,53.5852813721],"type":"Point"}
}