{
  "type": "Feature",
  "properties": {
    "addr:full":"Saint-Ulric QC G0J 3H0",
    "addr:postcode":"g0j 3h0",
    "iso:country":"CA",
    "sg:city":"Saint-Ulric",
    "sg:classifiers":[
        {
            "category":"Banks & Credit Unions",
            "subcategory":"Bank",
            "type":"Services"
        }
    ],
    "sg:phone":"+1 418 737 4391",
    "sg:postcode":"G0J 3H0",
    "sg:province":"QC",
    "wof:name":"Caisses Desjardins",
    "wof:placetype":"venue"
},
  "geometry": {"coordinates":[-67.70445251460001,48.7865447998],"type":"Point"}
}