{
  "type": "Feature",
  "properties": {
    "addr:full":"Calgary AB T2R 1J8",
    "addr:postcode":"t2r 1j8",
    "iso:country":"CA",
    "sg:city":"Calgary",
    "sg:classifiers":[
        {
            "category":"Professional",
            "subcategory":"Art Services",
            "type":"Services"
        }
    ],
    "sg:phone":"+1 403 269 8228",
    "sg:postcode":"T2R 1J8",
    "sg:province":"AB",
    "sg:tags":[
        "photographer"
    ],
    "wof:name":"Tarin Resource Svc Ltd",
    "wof:placetype":"venue"
},
  "geometry": {"coordinates":[-114.07434845,51.0428237915],"type":"Point"}
}