{
  "type": "Feature",
  "properties": {
    "addr:full":"1316 Portage Ave Winnipeg MB R3G 0V2",
    "addr:housenumber":"1316",
    "addr:postcode":"r3g 0v2",
    "addr:street":"Portage Ave",
    "iso:country":"CA",
    "sg:address":"1316 Portage Ave",
    "sg:city":"Winnipeg",
    "sg:classifiers":[
        {
            "category":"Shopping",
            "subcategory":"Florist",
            "type":"Retail Goods"
        }
    ],
    "sg:phone":"+1 204 774 1424",
    "sg:postcode":"R3G 0V2",
    "sg:province":"MB",
    "wof:name":"Tulip Flowers & Gifts",
    "wof:placetype":"venue"
},
  "geometry": {"coordinates":[-97.188934,49.882431],"type":"Point"}
}