{
  "type": "Feature",
  "properties": {
    "addr:full":"2100 Lawrence Ave E Scarborough ON M1R 2Z7",
    "addr:housenumber":"2100",
    "addr:postcode":"m1r 2z7",
    "addr:street":"Lawrence Ave E",
    "iso:country":"CA",
    "sg:address":"2100 Lawrence Ave E",
    "sg:city":"Scarborough",
    "sg:classifiers":[
        {
            "category":"Retail",
            "subcategory":"Auto Rental",
            "type":"Services"
        }
    ],
    "sg:phone":"+1 416 285 5310",
    "sg:postcode":"M1R 2Z7",
    "sg:province":"ON",
    "sg:tags":[
        "renting",
        "automobile"
    ],
    "wof:name":"Thrifty Car Rental",
    "wof:placetype":"venue"
},
  "geometry": {"coordinates":[-79.29150390620001,43.7461738586],"type":"Point"}
}