{
  "type": "Feature",
  "properties": {
    "addr:full":"Langley BC V3A 4Y1",
    "addr:postcode":"v3a 4y1",
    "iso:country":"CA",
    "sg:city":"Langley",
    "sg:classifiers":[
        {
            "category":"Utilities",
            "subcategory":"Mobile Phone",
            "type":"Services"
        }
    ],
    "sg:phone":"+1 604 534 0018",
    "sg:postcode":"V3A 4Y1",
    "sg:province":"BC",
    "sg:tags":[
        "telephone",
        "cellular"
    ],
    "wof:name":"Pacific Coast Com",
    "wof:placetype":"venue"
},
  "geometry": {"coordinates":[-122.672234,49.113083],"type":"Point"}
}