{
  "type": "Feature",
  "properties": {
    "addr:full":"PO Box 48 STN Main Navan ON K4B 1J3",
    "addr:housenumber":"po box 48 stn",
    "addr:postcode":"k4b 1j3",
    "addr:street":"Main",
    "iso:country":"CA",
    "sg:address":"PO Box 48 STN Main",
    "sg:city":"Navan",
    "sg:classifiers":[
        {
            "category":"Food & Beverages",
            "subcategory":"Specialty",
            "type":"Retail Goods"
        }
    ],
    "sg:phone":"+1 613 834 8046",
    "sg:postcode":"K4B 1J3",
    "sg:province":"ON",
    "sg:tags":[
        "water",
        "bulk",
        "company"
    ],
    "wof:name":"H Harper Enterprises",
    "wof:placetype":"venue"
},
  "geometry": {"coordinates":[-75.4264907837,45.4204597473],"type":"Point"}
}