{
  "type": "Feature",
  "properties": {
    "addr:full":"475 Archer Dr Kirkland Lake ON P2N 3M6",
    "addr:housenumber":"475",
    "addr:postcode":"p2n 3m6",
    "addr:street":"Archer Dr",
    "iso:country":"CA",
    "sg:address":"475 Archer Dr",
    "sg:city":"Kirkland Lake",
    "sg:classifiers":[
        {
            "category":"Wholesale",
            "subcategory":"Electrical",
            "type":"Manufacturing & Wholesale Goods"
        }
    ],
    "sg:phone":"+1 705 568 6355",
    "sg:postcode":"P2N 3M6",
    "sg:province":"ON",
    "sg:tags":[
        "equipment",
        "electric",
        "motor"
    ],
    "wof:name":"Siemens in Canada",
    "wof:placetype":"venue"
},
  "geometry": {"coordinates":[-80.061508,48.142448],"type":"Point"}
}