{
  "type": "Feature",
  "properties": {
    "addr:full":"450 Erb St W Waterloo ON N2T 1H4",
    "addr:housenumber":"450",
    "addr:postcode":"n2t 1h4",
    "addr:street":"Erb St W",
    "iso:country":"CA",
    "sg:address":"450 Erb St W",
    "sg:city":"Waterloo",
    "sg:classifiers":[
        {
            "category":"Health Services",
            "subcategory":"Doctor",
            "type":"Services"
        }
    ],
    "sg:phone":"+1 519 886 0330",
    "sg:postcode":"N2T 1H4",
    "sg:province":"ON",
    "sg:tags":[
        "dentist"
    ],
    "wof:name":"Carere, Vincent P DDS",
    "wof:placetype":"venue"
},
  "geometry": {"coordinates":[-80.5554199219,43.4519462585],"type":"Point"}
}