{
  "type": "Feature",
  "properties": {
    "addr:full":"408 7th Ave S Virden MB R0M 2C0",
    "addr:housenumber":"408",
    "addr:postcode":"r0m 2c0",
    "addr:street":"7Th Ave S Virden",
    "iso:country":"CA",
    "sg:address":"408 7th Ave S",
    "sg:city":"Virden",
    "sg:classifiers":[
        {
            "category":"Shopping",
            "subcategory":"Clothing, Apparel, & Fashions",
            "type":"Retail Goods"
        }
    ],
    "sg:phone":"+1 204 748 1996",
    "sg:postcode":"R0M 2C0",
    "sg:province":"MB",
    "sg:tags":[
        "furnishing"
    ],
    "wof:name":"Randy's Mens Wear Ltd",
    "wof:placetype":"venue"
},
  "geometry": {"coordinates":[-100.932258606,49.851348877],"type":"Point"}
}