{
  "type": "Feature",
  "properties": {
    "addr:full":"50 Bloor St W # 13 Toronto ON M4W 3L8",
    "addr:housenumber":"50",
    "addr:postcode":"m4w 3l8",
    "addr:street":"Bloor St W # 13",
    "iso:country":"CA",
    "sg:address":"50 Bloor St W # 13",
    "sg:city":"Toronto",
    "sg:classifiers":[
        {
            "category":"Manufacturing",
            "subcategory":"Tools & Machinery",
            "type":"Manufacturing & Wholesale Goods"
        }
    ],
    "sg:phone":"+1 416 968 2627",
    "sg:postcode":"M4W 3L8",
    "sg:province":"ON",
    "sg:tags":[
        "binoculars",
        "magnifying",
        "glasses"
    ],
    "wof:name":"Science City Inc",
    "wof:placetype":"venue"
},
  "geometry": {"coordinates":[-79.389145,43.669868],"type":"Point"}
}