{
  "type": "Feature",
  "properties": {
    "iso:country":"CA",
    "sg:address":"7 Fleetside Rd",
    "sg:city":"Conception Bay South",
    "sg:classifiers":[
        {
            "category":"Building & Trades",
            "subcategory":"Construction",
            "type":"Services"
        }
    ],
    "sg:phone":"+1 709 834 5351",
    "sg:postcode":"A1X 7V6",
    "sg:province":"NL",
    "sg:tags":[
        "general",
        "contractor"
    ],
    "wof:name":"O'Toole Brian General Contract",
    "wof:placetype":"venue"
},
  "geometry": {"coordinates":[-52.9780235291,47.5000495911],"type":"Point"}
}