{
  "type": "Feature",
  "properties": {
    "iso:country":"CA",
    "sg:city":"Saint-Jean-Sur-Richelieu",
    "sg:classifiers":[
        {
            "category":"Shopping",
            "subcategory":"Computers & Home Electronics",
            "type":"Retail Goods"
        }
    ],
    "sg:phone":"+1 450 347 0115",
    "sg:postcode":"J3B 2M7",
    "sg:province":"QC",
    "sg:tags":[
        "equipment",
        "dealer"
    ],
    "wof:name":"J & M Electronique Enr",
    "wof:placetype":"venue"
},
  "geometry": {"coordinates":[-73.278908,45.306095],"type":"Point"}
}