{
  "type": "Feature",
  "properties": {
    "addr:full":"17 Government Rd W Kirkland Lake ON P2N 2E3",
    "addr:housenumber":"17",
    "addr:postcode":"p2n 2e3",
    "addr:street":"Rd W",
    "iso:country":"CA",
    "sg:address":"17 Government Rd W",
    "sg:city":"Kirkland Lake",
    "sg:classifiers":[
        {
            "category":"Shopping",
            "subcategory":"Jewelry",
            "type":"Retail Goods"
        }
    ],
    "sg:phone":"+1 705 567 4151",
    "sg:postcode":"P2N 2E3",
    "sg:province":"ON",
    "sg:tags":[
        "jeweler"
    ],
    "wof:name":"Jewel Box",
    "wof:placetype":"venue"
},
  "geometry": {"coordinates":[-80.034515,48.15028],"type":"Point"}
}