{
  "type": "Feature",
  "properties": {
    "addr:full":"Brampton ON L6W 4P9",
    "addr:postcode":"l6w 4p9",
    "iso:country":"CA",
    "sg:city":"Brampton",
    "sg:classifiers":[
        {
            "category":"Manufacturing",
            "subcategory":"Signs",
            "type":"Manufacturing & Wholesale Goods"
        }
    ],
    "sg:phone":"+1 905 450 3460",
    "sg:postcode":"L6W 4P9",
    "sg:province":"ON",
    "wof:name":"1 Hour Signs",
    "wof:placetype":"venue"
},
  "geometry": {"coordinates":[-79.714958,43.67873],"type":"Point"}
}