{
  "type": "Feature",
  "properties": {
    "addr:full":"99 Skinner Ave Longlac ON P0T 2A0",
    "addr:housenumber":"99",
    "addr:postcode":"p0t 2a0",
    "addr:street":"Skinner Ave",
    "iso:country":"CA",
    "sg:address":"99 Skinner Ave",
    "sg:city":"Longlac",
    "sg:classifiers":[
        {
            "category":"Health Services",
            "subcategory":"Doctor",
            "type":"Services"
        }
    ],
    "sg:phone":"+1 807 876 2271",
    "sg:postcode":"P0T 2A0",
    "sg:province":"ON",
    "sg:tags":[
        "clinic",
        "holistic",
        "practitioner"
    ],
    "wof:name":"Nor West Community Ctr Longlac",
    "wof:placetype":"venue"
},
  "geometry": {"coordinates":[-86.52722199999999,49.779064],"type":"Point"}
}