{
  "type": "Feature",
  "properties": {
    "addr:full":"Delta BC V3M 6Y9",
    "addr:postcode":"v3m 6y9",
    "iso:country":"CA",
    "sg:city":"Delta",
    "sg:classifiers":[
        {
            "category":"Wholesale",
            "subcategory":"Machinery & Supplies",
            "type":"Manufacturing & Wholesale Goods"
        }
    ],
    "sg:phone":"+1 604 517 1777",
    "sg:postcode":"V3M 6Y9",
    "sg:province":"BC",
    "sg:tags":[
        "bearing"
    ],
    "wof:name":"Ntn Bearing Corp of Canada",
    "wof:placetype":"venue"
},
  "geometry": {"coordinates":[-122.964134,49.161526],"type":"Point"}
}