{
  "type": "Feature",
  "properties": {
    "addr:full":"4879 Kingsway Burnaby BC V5H 4T6",
    "addr:housenumber":"4879",
    "addr:postcode":"v5h 4t6",
    "addr:street":"Kingsway",
    "iso:country":"CA",
    "sg:address":"4879 Kingsway",
    "sg:city":"Burnaby",
    "sg:classifiers":[
        {
            "category":"Health Services",
            "subcategory":"Doctor",
            "type":"Services"
        }
    ],
    "sg:phone":"+1 604 433 3341",
    "sg:postcode":"V5H 4T6",
    "sg:province":"BC",
    "sg:tags":[
        "physician",
        "clinic",
        "surgeon"
    ],
    "wof:name":"Metrohealth Clinic",
    "wof:placetype":"venue"
},
  "geometry": {"coordinates":[-122.994636536,49.227016449],"type":"Point"}
}