{
  "type": "Feature",
  "properties": {
    "addr:full":"1515 Matheson Blvd E #210 Mississauga ON L4W 2P5",
    "addr:housenumber":"1515",
    "addr:postcode":"l4w 2p5",
    "addr:street":"Matheson Blvd E # 210",
    "iso:country":"CA",
    "sg:address":"1515 Matheson Blvd E #210",
    "sg:city":"Mississauga",
    "sg:classifiers":[
        {
            "category":"Wholesale",
            "subcategory":"Electrical",
            "type":"Manufacturing & Wholesale Goods"
        }
    ],
    "sg:phone":"+1 905 238 6848",
    "sg:postcode":"L4W 2P5",
    "sg:province":"ON",
    "sg:tags":[
        "equipment",
        "testing",
        "electronic"
    ],
    "wof:name":"Rcc Electronics Ltd",
    "wof:placetype":"venue"
},
  "geometry": {"coordinates":[-79.6295928955,43.6432266235],"type":"Point"}
}