{
  "type": "Feature",
  "properties": {
    "addr:full":"10 Japonica Rd Scarborough ON M1R 4R7",
    "addr:housenumber":"10",
    "addr:postcode":"m1r 4r7",
    "addr:street":"Japonica Rd",
    "iso:country":"CA",
    "sg:address":"10 Japonica Rd",
    "sg:city":"Scarborough",
    "sg:classifiers":[
        {
            "category":"Social Services",
            "subcategory":"Child Care",
            "type":"Services"
        }
    ],
    "sg:phone":"+1 416 446 7398",
    "sg:postcode":"M1R 4R7",
    "sg:province":"ON",
    "wof:name":"Ace After Four Program",
    "wof:placetype":"venue"
},
  "geometry": {"coordinates":[-79.30780799999999,43.761784],"type":"Point"}
}