{
  "type": "Feature",
  "properties": {
    "addr:full":"PO Box 5007 STN Main Devon AB T9G 1X8",
    "addr:housenumber":"po",
    "addr:postcode":"5007;t9g 1x8",
    "addr:street":"Box;Stn Main",
    "iso:country":"CA",
    "sg:address":"PO Box 5007 STN Main",
    "sg:city":"Devon",
    "sg:classifiers":[
        {
            "category":"Wholesale",
            "subcategory":"Durable Goods & Equipment",
            "type":"Manufacturing & Wholesale Goods"
        }
    ],
    "sg:phone":"+1 780 987 3212",
    "sg:postcode":"T9G 1X8",
    "sg:province":"AB",
    "sg:tags":[
        "environmental",
        "product"
    ],
    "wof:name":"Safety & Loss Control Ltd",
    "wof:placetype":"venue"
},
  "geometry": {"coordinates":[-113.730164,53.363655],"type":"Point"}
}