{
  "type": "Feature",
  "properties": {
    "iso:country":"CA",
    "sg:city":"Oakville",
    "sg:classifiers":[
        {
            "category":"Personal",
            "type":"Services"
        }
    ],
    "sg:phone":"+1 905 845 8100",
    "sg:postcode":"L6J 1J4",
    "sg:province":"ON",
    "sg:tags":[
        "school",
        "electrolysis",
        "beauty"
    ],
    "wof:name":"Mauria Clinic of Electrolysis",
    "wof:placetype":"venue"
},
  "geometry": {"coordinates":[-79.6655426025,43.4484786987],"type":"Point"}
}