{
  "type": "Feature",
  "properties": {
    "addr:full":"12419 Stony Plain Rd NW Edmonton AB T5N 3N3",
    "addr:housenumber":"12419",
    "addr:postcode":"t5n 3n3",
    "addr:street":"Stony Plain Rd Nw",
    "iso:country":"CA",
    "sg:address":"12419 Stony Plain Rd NW",
    "sg:city":"Edmonton",
    "sg:classifiers":[
        {
            "category":"Manufacturing",
            "subcategory":"Jewelry",
            "type":"Manufacturing & Wholesale Goods"
        }
    ],
    "sg:phone":"+1 780 482 1347",
    "sg:postcode":"T5N 3N3",
    "sg:province":"AB",
    "wof:name":"Wayne Mac Kenzie Dsgnr Gldsmth",
    "wof:placetype":"venue"
},
  "geometry": {"coordinates":[-113.53639200000001,53.546818],"type":"Point"}
}