{
  "type": "Feature",
  "properties": {
    "addr:full":"782 Lasalle Blvd Sudbury ON P3A 4V4",
    "addr:housenumber":"782",
    "addr:postcode":"p3a 4v4",
    "addr:street":"Lasalle Blvd",
    "iso:country":"CA",
    "sg:address":"782 Lasalle Blvd",
    "sg:city":"Sudbury",
    "sg:classifiers":[
        {
            "category":"Government",
            "subcategory":"Office",
            "type":"Public Place"
        }
    ],
    "sg:phone":"+1 705 566 0315",
    "sg:postcode":"P3A 4V4",
    "sg:province":"ON",
    "wof:name":"Ontario Permis DE Conduire",
    "wof:placetype":"venue"
},
  "geometry": {"coordinates":[-80.965309,46.522259],"type":"Point"}
}