{
  "type": "Feature",
  "properties": {
    "addr:full":"Creston NL A0E 1K0",
    "addr:postcode":"a0e 1k0",
    "iso:country":"CA",
    "sg:city":"Creston",
    "sg:classifiers":[
        {
            "category":"Shopping",
            "subcategory":"Books",
            "type":"Retail Goods"
        }
    ],
    "sg:phone":"+1 709 279 2154",
    "sg:postcode":"A0E 1K0",
    "sg:province":"NL",
    "sg:tags":[
        "dealer"
    ],
    "wof:name":"Jul-Kris",
    "wof:placetype":"venue"
},
  "geometry": {"coordinates":[-55.2041358948,47.1423988342],"type":"Point"}
}