{
  "type": "Feature",
  "properties": {
    "addr:full":"328 Rue Pine Rosemere QC J7A 1T8",
    "addr:housenumber":"328",
    "addr:postcode":"j7a 1t8",
    "addr:street":"Rue Pine Rosemere",
    "iso:country":"CA",
    "sg:address":"328 Rue Pine",
    "sg:city":"Rosemere",
    "sg:classifiers":[
        {
            "category":"Organizations",
            "subcategory":"Religious Organization",
            "type":"Services"
        }
    ],
    "sg:phone":"+1 450 621 6466",
    "sg:postcode":"J7A 1T8",
    "sg:province":"QC",
    "sg:tags":[
        "church"
    ],
    "wof:name":"St James Anglican Church",
    "wof:placetype":"venue"
},
  "geometry": {"coordinates":[-73.7964706421,45.6380081177],"type":"Point"}
}