{
  "type": "Feature",
  "properties": {
    "addr:full":"3724 Av Des Eglises Charny QC G6X 1X4",
    "addr:housenumber":"3724",
    "addr:postcode":"g6x 1x4",
    "addr:street":"Av Des Eglises",
    "iso:country":"CA",
    "sg:address":"3724 Av Des Eglises",
    "sg:city":"Charny",
    "sg:classifiers":[
        {
            "category":"Organizations",
            "subcategory":"Professional Association",
            "type":"Services"
        }
    ],
    "sg:phone":"+1 418 832 4567",
    "sg:postcode":"G6X 1X4",
    "sg:province":"QC",
    "wof:name":"Syndicat Soutien Scolaire Des",
    "wof:placetype":"venue"
},
  "geometry": {"coordinates":[-71.26676177980001,46.7198104858],"type":"Point"}
}