{
  "type": "Feature",
  "properties": {
    "addr:full":"1379 Av Dollard Lasalle QC H8N 1T3",
    "addr:housenumber":"1379",
    "addr:postcode":"h8n 1t3",
    "addr:street":"Av Dollard",
    "iso:country":"CA",
    "sg:address":"1379 Av Dollard",
    "sg:city":"Lasalle",
    "sg:classifiers":[
        {
            "category":"Personal",
            "subcategory":"Beauty Salon",
            "type":"Services"
        }
    ],
    "sg:phone":"+1 514 363 6462",
    "sg:postcode":"H8N 1T3",
    "sg:province":"QC",
    "wof:name":"Salon Dollard Coiffure",
    "wof:placetype":"venue"
},
  "geometry": {"coordinates":[-73.626457,45.426697],"type":"Point"}
}