{
  "type": "Feature",
  "properties": {
    "addr:full":"Toronto ON M4P 1J5",
    "addr:postcode":"m4p 1j5",
    "iso:country":"CA",
    "sg:city":"Toronto",
    "sg:classifiers":[
        {
            "category":"Travel",
            "subcategory":"Campground",
            "type":"Entertainment"
        }
    ],
    "sg:phone":"+1 416 924 7433",
    "sg:postcode":"M4P 1J5",
    "sg:province":"ON",
    "sg:tags":[
        "camp"
    ],
    "wof:name":"Camp Tamakwa",
    "wof:placetype":"venue"
},
  "geometry": {"coordinates":[-79.39250183110001,43.7078514099],"type":"Point"}
}