{
  "type": "Feature",
  "properties": {
    "addr:full":"374 Richmond St London ON N6A 3C7",
    "addr:housenumber":"374",
    "addr:postcode":"n6a 3c7",
    "addr:street":"Richmond St",
    "iso:country":"CA",
    "sg:address":"374 Richmond St",
    "sg:city":"London",
    "sg:classifiers":[
        {
            "category":"Restaurant",
            "type":"Food & Drink"
        }
    ],
    "sg:phone":"+1 519 850 5678",
    "sg:postcode":"N6A 3C7",
    "sg:province":"ON",
    "wof:name":"Curry Garden Restaurant",
    "wof:placetype":"venue"
},
  "geometry": {"coordinates":[-81.249016,42.982792],"type":"Point"}
}