{
  "type": "Feature",
  "properties": {
    "iso:country":"CA",
    "sg:address":"374 Richmond St",
    "sg:city":"London",
    "sg:classifiers":[
        {
            "category":"Restaurant",
            "type":"Food & Drink"
        }
    ],
    "sg:phone":"+1 519 850 5678",
    "sg:postcode":"N6A 3C7",
    "sg:province":"ON",
    "wof:name":"Curry Garden Restaurant",
    "wof:placetype":"venue"
},
  "geometry": {"coordinates":[-81.249016,42.982792],"type":"Point"}
}