{
  "type": "Feature",
  "properties": {
    "iso:country":"CA",
    "sg:address":"17th Ave & 18th St",
    "sg:city":"Nanton",
    "sg:classifiers":[
        {
            "category":"Government",
            "subcategory":"Office",
            "type":"Public Place"
        }
    ],
    "sg:phone":"+1 403 646 2902",
    "sg:postcode":"T0L 1R0",
    "sg:province":"AB",
    "sg:tags":[
        "village"
    ],
    "wof:name":"Nanton Sewage Plant",
    "wof:placetype":"venue"
},
  "geometry": {"coordinates":[-113.77384948700001,50.3498191833],"type":"Point"}
}