{
  "type": "Feature",
  "properties": {
    "iso:country":"CA",
    "sg:address":"Columbus Dr",
    "sg:city":"Carbonear",
    "sg:classifiers":[
        {
            "category":"Food & Beverages",
            "subcategory":"Fruits & Vegetables",
            "type":"Retail Goods"
        }
    ],
    "sg:phone":"+1 709 596 5682",
    "sg:postcode":"A1Y 1B1",
    "sg:province":"NL",
    "sg:tags":[
        "produce"
    ],
    "wof:name":"P & P Food Mart Ltd",
    "wof:placetype":"venue"
},
  "geometry": {"coordinates":[-53.246257782,47.7270278931],"type":"Point"}
}