{
  "type": "Feature",
  "properties": {
    "iso:country":"CA",
    "sg:address":"45 Rue D'Anvers",
    "sg:city":"Saint-Augustin-DE-Desmaures",
    "sg:classifiers":[
        {
            "category":"Autos & Motor Vehicles",
            "subcategory":"Automobile Sales",
            "type":"Retail Goods"
        }
    ],
    "sg:phone":"+1 418 878 2010",
    "sg:postcode":"G3A 1S5",
    "sg:province":"QC",
    "sg:tags":[
        "body",
        "car"
    ],
    "wof:name":"Atelier DE Carrosserie",
    "wof:placetype":"venue"
},
  "geometry": {"coordinates":[-71.434677124,46.7532958984],"type":"Point"}
}