{
  "type": "Feature",
  "properties": {
    "addr:full":"22338 Lougheed Hwy Maple Ridge BC V2X 2T4",
    "addr:housenumber":"22338",
    "addr:postcode":"v2x 2t4",
    "addr:street":"Lougheed Hwy",
    "iso:country":"CA",
    "sg:address":"22338 Lougheed Hwy",
    "sg:city":"Maple Ridge",
    "sg:classifiers":[
        {
            "category":"Shopping",
            "subcategory":"Bicycles & Sporting Goods",
            "type":"Retail Goods"
        }
    ],
    "sg:phone":"+1 604 463 4412",
    "sg:postcode":"V2X 2T4",
    "sg:province":"BC",
    "wof:name":"E & D Sports Shop",
    "wof:placetype":"venue"
},
  "geometry": {"coordinates":[-122.603325,49.216732],"type":"Point"}
}