{
  "type": "Feature",
  "properties": {
    "addr:full":"359 Av Sainte-Croix Saint-Laurent QC H4N 2L3",
    "addr:postcode":"h4n 2l3",
    "addr:street":"359 Av Sainte-Croix",
    "iso:country":"CA",
    "sg:address":"359 Av Sainte-Croix",
    "sg:city":"Saint-Laurent",
    "sg:classifiers":[
        {
            "category":"Banks & Credit Unions",
            "subcategory":"Bank",
            "type":"Services"
        }
    ],
    "sg:phone":"+1 514 747 4000",
    "sg:postcode":"H4N 2L3",
    "sg:province":"QC",
    "sg:tags":[
        "loan",
        "real estate"
    ],
    "wof:name":"Mayco Financial Corp",
    "wof:placetype":"venue"
},
  "geometry": {"coordinates":[-73.668297,45.509716],"type":"Point"}
}