{
  "type": "Feature",
  "properties": {
    "addr:full":"956 Lucas Ave Victoria BC V8X 4H5",
    "addr:housenumber":"956",
    "addr:postcode":"v8x 4h5",
    "addr:street":"Lucas Ave",
    "iso:country":"CA",
    "sg:address":"956 Lucas Ave",
    "sg:city":"Victoria",
    "sg:classifiers":[
        {
            "category":"Professional",
            "subcategory":"Management & Consulting",
            "type":"Services"
        }
    ],
    "sg:phone":"+1 250 479 2775",
    "sg:postcode":"V8X 4H5",
    "sg:province":"BC",
    "sg:tags":[
        "consultant",
        "educational"
    ],
    "wof:name":"Keta Consulting Inc",
    "wof:placetype":"venue"
},
  "geometry": {"coordinates":[-123.36451700000001,48.428314],"type":"Point"}
}