{
  "type": "Feature",
  "properties": {
    "addr:full":"700 Rue Des Seigneurs Montreal QC H3J 2S5",
    "addr:housenumber":"700",
    "addr:postcode":"h3j 2s5",
    "addr:street":"Rue Des Seigneurs",
    "iso:country":"CA",
    "sg:address":"700 Rue Des Seigneurs",
    "sg:city":"Montreal",
    "sg:classifiers":[
        {
            "category":"Professional",
            "subcategory":"Computer Services",
            "type":"Services"
        }
    ],
    "sg:phone":"+1 514 333 3386",
    "sg:postcode":"H3J 2S5",
    "sg:province":"QC",
    "sg:tags":[
        "consultant"
    ],
    "wof:name":"Solutions Micro-Plus Data-Lan",
    "wof:placetype":"venue"
},
  "geometry": {"coordinates":[-73.572029,45.489037],"type":"Point"}
}