{
  "type": "Feature",
  "properties": {
    "addr:full":"530 Rue DE LA Station Saint-Leonard-D'Aston QC J0C 1M0",
    "addr:housenumber":"530",
    "addr:postcode":"j0c 1m0",
    "addr:street":"Rue De La Station Saint-Leonard-D'Aston",
    "iso:country":"CA",
    "sg:address":"530 Rue DE LA Station",
    "sg:city":"Saint-Leonard-D'Aston",
    "sg:classifiers":[
        {
            "category":"Retail",
            "subcategory":"Funeral Services",
            "type":"Services"
        }
    ],
    "sg:phone":"+1 819 399 3381",
    "sg:postcode":"J0C 1M0",
    "sg:province":"QC",
    "sg:tags":[
        "director"
    ],
    "wof:name":"Lauziere & Vachon",
    "wof:placetype":"venue"
},
  "geometry": {"coordinates":[-71.749961853,46.4133224487],"type":"Point"}
}