{
  "type": "Feature",
  "properties": {
    "addr:full":"590 Av George-V #1 Lachine QC H8S 2R7",
    "addr:postcode":"h8s 2r7",
    "addr:street":"590 Av George-V # 1",
    "iso:country":"CA",
    "sg:address":"590 Av George-V #1",
    "sg:city":"Lachine",
    "sg:classifiers":[
        {
            "category":"Freight",
            "type":"Transportation"
        }
    ],
    "sg:phone":"+1 514 637 2333",
    "sg:postcode":"H8S 2R7",
    "sg:province":"QC",
    "sg:tags":[
        "mover",
        "trucking"
    ],
    "wof:name":"Lipari Demenagement & Ent Ltee",
    "wof:placetype":"venue"
},
  "geometry": {"coordinates":[-73.6632843018,45.4398956299],"type":"Point"}
}