{
  "type": "Feature",
  "properties": {
    "addr:full":"513 Main St Montague PE C0A 1R0",
    "addr:housenumber":"513",
    "addr:postcode":"c0a 1r0",
    "addr:street":"Main St",
    "iso:country":"CA",
    "sg:address":"513 Main St",
    "sg:city":"Montague",
    "sg:classifiers":[
        {
            "category":"Organizations",
            "subcategory":"Religious Organization",
            "type":"Services"
        }
    ],
    "sg:phone":"+1 902 838 4189",
    "sg:postcode":"C0A 1R0",
    "sg:province":"PE",
    "sg:tags":[
        "church"
    ],
    "wof:name":"Church of Christ",
    "wof:placetype":"venue"
},
  "geometry": {"coordinates":[-62.651466,46.17099],"type":"Point"}
}