{
  "type": "Feature",
  "properties": {
    "addr:full":"2315 Peardonville Rd Abbotsford BC V2T 6J7",
    "addr:housenumber":"2315",
    "addr:postcode":"v2t 6j7",
    "addr:street":"Peardonville Rd",
    "iso:country":"CA",
    "sg:address":"2315 Peardonville Rd",
    "sg:city":"Abbotsford",
    "sg:classifiers":[
        {
            "category":"Building & Trades",
            "subcategory":"Electrical",
            "type":"Services"
        }
    ],
    "sg:phone":"+1 604 864 2666",
    "sg:postcode":"V2T 6J7",
    "sg:province":"BC",
    "sg:tags":[
        "pole",
        "line",
        "electric",
        "contractor"
    ],
    "wof:name":"Galbraith Power Line Contr Ltd",
    "wof:placetype":"venue"
},
  "geometry": {"coordinates":[-122.37663999999999,49.040722],"type":"Point"}
}