{
  "type": "Feature",
  "properties": {
    "iso:country":"CA",
    "sg:address":"53 Boul Brunswick",
    "sg:city":"Dollard-Des-Ormeaux",
    "sg:classifiers":[
        {
            "category":"Restaurant",
            "type":"Food & Drink"
        }
    ],
    "sg:phone":"+1 514 684 1321",
    "sg:postcode":"H9B 1P7",
    "sg:province":"QC",
    "wof:name":"Restaurant LA Serentata",
    "wof:placetype":"venue"
},
  "geometry": {"coordinates":[-73.795372,45.4837],"type":"Point"}
}