{
  "type": "Feature",
  "properties": {
    "addr:full":"1033 Rue Faessler Beloeil QC J3G 5W2",
    "addr:housenumber":"1033",
    "addr:postcode":"j3g 5w2",
    "addr:street":"Rue Faessler",
    "iso:country":"CA",
    "sg:address":"1033 Rue Faessler",
    "sg:city":"Beloeil",
    "sg:classifiers":[
        {
            "category":"Health Services",
            "subcategory":"Doctor",
            "type":"Services"
        }
    ],
    "sg:phone":"+1 450 464 4670",
    "sg:postcode":"J3G 5W2",
    "sg:province":"QC",
    "sg:tags":[
        "clinic"
    ],
    "wof:name":"Richard Perreault Denturist",
    "wof:placetype":"venue"
},
  "geometry": {"coordinates":[-73.22350299999999,45.567108],"type":"Point"}
}