{
  "type": "Feature",
  "properties": {
    "addr:full":"6061 Young St # C3 Halifax NS B3K 2A3",
    "addr:housenumber":"6061",
    "addr:postcode":"b3k 2a3",
    "addr:street":"Young St # C3",
    "iso:country":"CA",
    "sg:address":"6061 Young St # C3",
    "sg:city":"Halifax",
    "sg:classifiers":[
        {
            "category":"Social Services",
            "subcategory":"Job Training",
            "type":"Services"
        }
    ],
    "sg:phone":"+1 902 423 4244",
    "sg:postcode":"B3K 2A3",
    "sg:province":"NS",
    "sg:tags":[
        "orthopedic",
        "appliance",
        "rehabilitation"
    ],
    "wof:name":"Curwin Health & Sport",
    "wof:placetype":"venue"
},
  "geometry": {"coordinates":[-63.6031990051,44.6591491699],"type":"Point"}
}