{
  "type": "Feature",
  "properties": {
    "iso:country":"CA",
    "sg:address":"4621 61 Ave",
    "sg:city":"Leduc",
    "sg:classifiers":[
        {
            "category":"Home & Garden",
            "subcategory":"Building Materials",
            "type":"Retail Goods"
        }
    ],
    "sg:phone":"+1 780 986 6244",
    "sg:postcode":"T9E 7A4",
    "sg:province":"AB",
    "wof:name":"Schneider's Building Supls Inc",
    "wof:placetype":"venue"
},
  "geometry": {"coordinates":[-113.54755401600001,53.2742729187],"type":"Point"}
}