{
  "type": "Feature",
  "properties": {
    "iso:country":"CA",
    "sg:address":"150 Rue Racine E",
    "sg:city":"Chicoutimi",
    "sg:classifiers":[
        {
            "category":"Building & Trades",
            "subcategory":"Cleaning & Sanitation",
            "type":"Services"
        }
    ],
    "sg:phone":"+1 418 543 2412",
    "sg:postcode":"G7H 6V4",
    "sg:province":"QC",
    "sg:tags":[
        "janitor"
    ],
    "wof:name":"Services Sanitaires Du Fjord",
    "wof:placetype":"venue"
},
  "geometry": {"coordinates":[-71.06391143800001,48.4276428223],"type":"Point"}
}