{
  "type": "Feature",
  "properties": {
    "addr:full":"Port Hawkesbury NS B9A 2S4",
    "addr:postcode":"b9a 2s4",
    "iso:country":"CA",
    "sg:city":"Port Hawkesbury",
    "sg:classifiers":[
        {
            "category":"Personal",
            "subcategory":"Barber",
            "type":"Services"
        }
    ],
    "sg:phone":"+1 902 625 1500",
    "sg:postcode":"B9A 2S4",
    "sg:province":"NS",
    "wof:name":"Sandi's Barber Shop",
    "wof:placetype":"venue"
},
  "geometry": {"coordinates":[-61.34893,45.613724],"type":"Point"}
}