{
  "type": "Feature",
  "properties": {
    "addr:full":"107 4E Boulevard Terrasse-Vaudreuil QC J7V 5M6",
    "addr:housenumber":"107",
    "addr:postcode":"j7v 5m6",
    "addr:street":"4E Boulevard",
    "iso:country":"CA",
    "sg:address":"107 4E Boulevard",
    "sg:city":"Terrasse-Vaudreuil",
    "sg:classifiers":[
        {
            "category":"Autos & Motor Vehicles",
            "subcategory":"Automobile Sales",
            "type":"Retail Goods"
        }
    ],
    "sg:phone":"+1 514 453 8976",
    "sg:postcode":"J7V 5M6",
    "sg:province":"QC",
    "sg:tags":[
        "parts",
        "snowmobile",
        "accessory"
    ],
    "wof:name":"Entreprises Lucien Goyette Inc",
    "wof:placetype":"venue"
},
  "geometry": {"coordinates":[-73.99037199999999,45.388748],"type":"Point"}
}