{
  "type": "Feature",
  "properties": {
    "iso:country":"CA",
    "sg:address":"130 Rue Marie-DE-L'Incarnation",
    "sg:city":"Quebec",
    "sg:classifiers":[
        {
            "category":"Retail",
            "subcategory":"Auto Repair",
            "type":"Services"
        }
    ],
    "sg:phone":"+1 418 687 0327",
    "sg:postcode":"G1N 3G2",
    "sg:province":"QC",
    "sg:tags":[
        "repairing",
        "automobile"
    ],
    "wof:name":"Station Service Marc & Michel",
    "wof:placetype":"venue"
},
  "geometry": {"coordinates":[-71.4194717407,46.858581543],"type":"Point"}
}