{
  "type": "Feature",
  "properties": {
    "addr:full":"Winnipeg MB R2C 2Z2",
    "addr:postcode":"r2c 2z2",
    "iso:country":"CA",
    "sg:city":"Winnipeg",
    "sg:classifiers":[
        {
            "category":"Building & Trades",
            "subcategory":"Plumbing",
            "type":"Services"
        }
    ],
    "sg:phone":"+1 204 222 2990",
    "sg:postcode":"R2C 2Z2",
    "sg:province":"MB",
    "sg:tags":[
        "heating",
        "contractor"
    ],
    "wof:name":"Jpb Enterprises",
    "wof:placetype":"venue"
},
  "geometry": {"coordinates":[-97.12990600000001,49.910282],"type":"Point"}
}