{
  "type": "Feature",
  "properties": {
    "addr:full":"1805 Trim Rd Orleans ON K4A 3P6",
    "addr:housenumber":"1805",
    "addr:postcode":"k4a 3p6",
    "addr:street":"Trim Rd",
    "iso:country":"CA",
    "sg:address":"1805 Trim Rd",
    "sg:city":"Orleans",
    "sg:classifiers":[
        {
            "category":"Wholesale",
            "subcategory":"Machinery & Supplies",
            "type":"Manufacturing & Wholesale Goods"
        }
    ],
    "sg:phone":"+1 613 830 4308",
    "sg:postcode":"K4A 3P6",
    "sg:province":"ON",
    "sg:tags":[
        "sprinkler"
    ],
    "wof:name":"Escape Fire Protection Ltd",
    "wof:placetype":"venue"
},
  "geometry": {"coordinates":[-75.45974731450001,45.4754753113],"type":"Point"}
}