{
  "type": "Feature",
  "properties": {
    "addr:full":"379 132 Rte RR 1 Chandler QC G0C 1K0",
    "addr:housenumber":"132",
    "addr:postcode":"g0c 1k0",
    "addr:street":"Rte Rr 1",
    "iso:country":"CA",
    "sg:address":"379 132 Rte RR 1",
    "sg:city":"Chandler",
    "sg:classifiers":[
        {
            "category":"Home & Garden",
            "subcategory":"Hardware",
            "type":"Retail Goods"
        }
    ],
    "sg:phone":"+1 418 689 2681",
    "sg:postcode":"G0C 1K0",
    "sg:province":"QC",
    "sg:tags":[
        "building",
        "material"
    ],
    "wof:name":"Maurice Goupil Ltee",
    "wof:placetype":"venue"
},
  "geometry": {"coordinates":[-64.71080000000001,48.342243],"type":"Point"}
}