{
  "type": "Feature",
  "properties": {
    "iso:country":"CA",
    "sg:address":"21 Rue Maple",
    "sg:city":"Sainte-Anne-DE-Bellevue",
    "sg:classifiers":[
        {
            "category":"Education",
            "subcategory":"School",
            "type":"Public Place"
        }
    ],
    "sg:phone":"+1 514 457 5422",
    "sg:postcode":"H9X 2E5",
    "sg:province":"QC",
    "wof:name":"Commission Scolaire Kativik",
    "wof:placetype":"venue"
},
  "geometry": {"coordinates":[-73.945007,45.406479],"type":"Point"}
}