{
  "type": "Feature",
  "properties": {
    "addr:full":"460 Rue Joseph-Gagne S LA Baie QC G7B 3P6",
    "addr:housenumber":"460",
    "addr:postcode":"g7b 3p6",
    "addr:street":"Rue Joseph-Gagne S La Baie",
    "iso:country":"CA",
    "sg:address":"460 Rue Joseph-Gagne S",
    "sg:city":"LA Baie",
    "sg:classifiers":[
        {
            "category":"Building & Trades",
            "subcategory":"Cleaning & Sanitation",
            "type":"Services"
        }
    ],
    "sg:phone":"+1 418 544 6871",
    "sg:postcode":"G7B 3P6",
    "sg:province":"QC",
    "sg:tags":[
        "filter",
        "maintenance"
    ],
    "wof:name":"Filtre Saglac Inc",
    "wof:placetype":"venue"
},
  "geometry": {"coordinates":[-70.899406,48.328552],"type":"Point"}
}