{
  "type": "Feature",
  "properties": {
    "iso:country":"CA",
    "sg:address":"294 Wellington St",
    "sg:city":"St Thomas",
    "sg:classifiers":[
        {
            "category":"Shopping",
            "subcategory":"Discount & Variety Stores",
            "type":"Retail Goods"
        }
    ],
    "sg:phone":"+1 519 637 2926",
    "sg:postcode":"N5R 2S9",
    "sg:province":"ON",
    "wof:name":"St Thomas Variety",
    "wof:placetype":"venue"
},
  "geometry": {"coordinates":[-81.1773147583,42.7748718262],"type":"Point"}
}