{
  "type": "Feature",
  "properties": {
    "addr:full":"10649 97 St NW Edmonton AB T5H 2L7",
    "addr:housenumber":"10649",
    "addr:postcode":"t5h 2l7",
    "addr:street":"97 St Nw",
    "iso:country":"CA",
    "sg:address":"10649 97 St NW",
    "sg:city":"Edmonton",
    "sg:classifiers":[
        {
            "category":"Food & Beverages",
            "subcategory":"Bakery",
            "type":"Retail Goods"
        }
    ],
    "sg:phone":"+1 780 429 3838",
    "sg:postcode":"T5H 2L7",
    "sg:province":"AB",
    "sg:tags":[
        "baker"
    ],
    "wof:name":"Hong Kong Bakery & Restaurant",
    "wof:placetype":"venue"
},
  "geometry": {"coordinates":[-113.488991,53.551235],"type":"Point"}
}