{
  "type": "Feature",
  "properties": {
    "addr:full":"136 Queen St Longlac ON P0T 2A0",
    "addr:housenumber":"136",
    "addr:postcode":"p0t 2a0",
    "addr:street":"Queen St",
    "iso:country":"CA",
    "sg:address":"136 Queen St",
    "sg:city":"Longlac",
    "sg:classifiers":[
        {
            "category":"Autos & Motor Vehicles",
            "subcategory":"Fuel & Gas Station",
            "type":"Retail Goods"
        }
    ],
    "sg:phone":"+1 807 876 2303",
    "sg:postcode":"P0T 2A0",
    "sg:province":"ON",
    "sg:tags":[
        "repairing",
        "automobile",
        "oil"
    ],
    "wof:name":"Longlac Auto Ctr",
    "wof:placetype":"venue"
},
  "geometry": {"coordinates":[-86.53620100000001,49.782318],"type":"Point"}
}