{
  "type": "Feature",
  "properties": {
    "addr:full":"3154 Delta Ave Victoria BC V8Z 1A7",
    "addr:housenumber":"3154",
    "addr:postcode":"v8z 1a7",
    "addr:street":"Delta Ave",
    "iso:country":"CA",
    "sg:address":"3154 Delta Ave",
    "sg:city":"Victoria",
    "sg:classifiers":[
        {
            "category":"Manufacturing",
            "subcategory":"Apparel",
            "type":"Manufacturing & Wholesale Goods"
        }
    ],
    "sg:phone":"+1 250 388 6261",
    "sg:postcode":"V8Z 1A7",
    "sg:province":"BC",
    "sg:tags":[
        "clothing"
    ],
    "wof:name":"Hall & CO Big Horn Mfg",
    "wof:placetype":"venue"
},
  "geometry": {"coordinates":[-123.375298,48.446003],"type":"Point"}
}