{
  "type": "Feature",
  "properties": {
    "addr:full":"251 Hwy 16 W Burns Lake BC V0J 1E0",
    "addr:housenumber":"251",
    "addr:postcode":"v0j 1e0",
    "addr:street":"Hwy 16 W Burns",
    "iso:country":"CA",
    "sg:address":"251 Hwy 16 W",
    "sg:city":"Burns Lake",
    "sg:classifiers":[
        {
            "category":"Insurance",
            "subcategory":"Insurance Agent",
            "type":"Services"
        }
    ],
    "sg:phone":"+1 250 692 3161",
    "sg:postcode":"V0J 1E0",
    "sg:province":"BC",
    "wof:name":"Village Insurance Svc Ltd",
    "wof:placetype":"venue"
},
  "geometry": {"coordinates":[-125.758682251,54.2265930176],"type":"Point"}
}