{
  "type": "Feature",
  "properties": {
    "addr:full":"290 Ch Yamaska Saint-Germain-DE-Grantham QC J0C 1K0",
    "addr:housenumber":"290",
    "addr:postcode":"j0c 1k0",
    "addr:street":"Ch Yamaska",
    "iso:country":"CA",
    "sg:address":"290 Ch Yamaska",
    "sg:city":"Saint-Germain-DE-Grantham",
    "sg:classifiers":[
        {
            "category":"Autos & Motor Vehicles",
            "subcategory":"Automobile Sales",
            "type":"Retail Goods"
        }
    ],
    "sg:phone":"+1 819 395 5242",
    "sg:postcode":"J0C 1K0",
    "sg:province":"QC",
    "sg:tags":[
        "car",
        "dealer"
    ],
    "wof:name":"R P Auto Enr",
    "wof:placetype":"venue"
},
  "geometry": {"coordinates":[-72.567474,45.846661],"type":"Point"}
}