{
  "type": "Feature",
  "properties": {
    "addr:full":"Prince George BC V2N 2S9",
    "addr:postcode":"v2n 2s9",
    "iso:country":"CA",
    "sg:city":"Prince George",
    "sg:classifiers":[
        {
            "category":"Shopping",
            "subcategory":"Tobacco",
            "type":"Retail Goods"
        }
    ],
    "sg:phone":"+1 250 562 7874",
    "sg:postcode":"V2N 2S9",
    "sg:province":"BC",
    "sg:tags":[
        "cigarette",
        "cigar",
        "dealer"
    ],
    "wof:name":"Shefield & Sons Tobacconists",
    "wof:placetype":"venue"
},
  "geometry": {"coordinates":[-122.779839,53.899452],"type":"Point"}
}