{
  "type": "Feature",
  "properties": {
    "iso:country":"CA",
    "sg:address":"107 Main St",
    "sg:city":"Yarmouth",
    "sg:classifiers":[
        {
            "category":"Food & Beverages",
            "subcategory":"Groceries & Convenience Stores",
            "type":"Retail Goods"
        }
    ],
    "sg:phone":"+1 902 742 8894",
    "sg:postcode":"B5A 1B6",
    "sg:province":"NS",
    "sg:tags":[
        "grocer"
    ],
    "wof:name":"Yarmouth Food Master",
    "wof:placetype":"venue"
},
  "geometry": {"coordinates":[-66.1227111816,43.824180603],"type":"Point"}
}