{
  "type": "Feature",
  "properties": {
    "addr:full":"98 Rte 132 N Saint-Godefroi QC G0C 3C0",
    "addr:housenumber":"98",
    "addr:postcode":"g0c 3c0",
    "addr:street":"Rte 132 N",
    "iso:country":"CA",
    "sg:address":"98 Rte 132 N",
    "sg:city":"Saint-Godefroi",
    "sg:classifiers":[
        {
            "category":"Organizations",
            "subcategory":"Religious Organization",
            "type":"Services"
        }
    ],
    "sg:phone":"+1 418 752 3927",
    "sg:postcode":"G0C 3C0",
    "sg:province":"QC",
    "sg:tags":[
        "church"
    ],
    "wof:name":"St-Godefroi Eglises",
    "wof:placetype":"venue"
},
  "geometry": {"coordinates":[-65.1100769043,48.0776252747],"type":"Point"}
}