{
  "type": "Feature",
  "properties": {
    "addr:full":"1162 Boul DE LA Rive-Sud Saint-Romuald QC G6W 5M6",
    "addr:housenumber":"1162",
    "addr:postcode":"g6w 5m6",
    "addr:street":"Boul De La Rive-Sud",
    "iso:country":"CA",
    "sg:address":"1162 Boul DE LA Rive-Sud",
    "sg:city":"Saint-Romuald",
    "sg:classifiers":[
        {
            "category":"Organizations",
            "subcategory":"Religious Organization",
            "type":"Services"
        }
    ],
    "sg:phone":"+1 418 834 4169",
    "sg:postcode":"G6W 5M6",
    "sg:province":"QC",
    "sg:tags":[
        "church"
    ],
    "wof:name":"Temoins DE Jehovah",
    "wof:placetype":"venue"
},
  "geometry": {"coordinates":[-71.265586853,46.733707428],"type":"Point"}
}