{
  "type": "Feature",
  "properties": {
    "addr:full":"Carberry MB R0K 0H0",
    "addr:postcode":"r0k 0h0",
    "iso:country":"CA",
    "sg:city":"Carberry",
    "sg:classifiers":[
        {
            "category":"Wholesale",
            "subcategory":"Farm Supplies",
            "type":"Manufacturing & Wholesale Goods"
        }
    ],
    "sg:phone":"+1 204 834 3114",
    "sg:postcode":"R0K 0H0",
    "sg:province":"MB",
    "sg:tags":[
        "fertilizer",
        "product",
        "protection",
        "crop"
    ],
    "wof:name":"Cargill Limited",
    "wof:placetype":"venue"
},
  "geometry": {"coordinates":[-99.357849,49.871185],"type":"Point"}
}