{
  "type": "Feature",
  "properties": {
    "addr:full":"10116 Centennial Dr Fort Mcmurray AB T9H 1Y4",
    "addr:housenumber":"10116",
    "addr:postcode":"t9h 1y4",
    "addr:street":"Centennial Dr",
    "iso:country":"CA",
    "sg:address":"10116 Centennial Dr",
    "sg:city":"Fort Mcmurray",
    "sg:classifiers":[
        {
            "category":"Retail",
            "subcategory":"Veterinary Services",
            "type":"Services"
        }
    ],
    "sg:phone":"+1 780 743 4044",
    "sg:postcode":"T9H 1Y4",
    "sg:province":"AB",
    "sg:tags":[
        "veterinarian"
    ],
    "wof:name":"Fort Mc Murray Animal Hospital",
    "wof:placetype":"venue"
},
  "geometry": {"coordinates":[-111.35102081300001,56.7173500061],"type":"Point"}
}