{
  "type": "Feature",
  "properties": {
    "addr:full":"3624 Parkview St Penticton BC V2A 6H1",
    "addr:housenumber":"3624",
    "addr:postcode":"v2a 6h1",
    "addr:street":"Parkview St",
    "iso:country":"CA",
    "sg:address":"3624 Parkview St",
    "sg:city":"Penticton",
    "sg:classifiers":[
        {
            "category":"Travel",
            "subcategory":"Hotels & Motels",
            "type":"Entertainment"
        }
    ],
    "sg:phone":"+1 250 492 8318",
    "sg:postcode":"V2A 6H1",
    "sg:province":"BC",
    "wof:name":"Beachside Motel",
    "wof:placetype":"venue"
},
  "geometry": {"coordinates":[-119.586555,49.455128],"type":"Point"}
}