{
  "type": "Feature",
  "properties": {
    "addr:full":"7245 Rue Alexandra Montreal QC H2R 2Y9",
    "addr:housenumber":"7245",
    "addr:postcode":"h2r 2y9",
    "addr:street":"Rue Alexandra",
    "iso:country":"CA",
    "sg:address":"7245 Rue Alexandra",
    "sg:city":"Montreal",
    "sg:classifiers":[
        {
            "category":"Wholesale",
            "subcategory":"Apparel",
            "type":"Manufacturing & Wholesale Goods"
        }
    ],
    "sg:phone":"+1 514 271 5456",
    "sg:postcode":"H2R 2Y9",
    "sg:province":"QC",
    "sg:tags":[
        "hosiery"
    ],
    "wof:name":"Bonneperie Central",
    "wof:placetype":"venue"
},
  "geometry": {"coordinates":[-73.6210632324,45.5329284668],"type":"Point"}
}