{
  "type": "Feature",
  "properties": {
    "addr:full":"2700 Montague St Regina SK S4S 0J9",
    "addr:housenumber":"2700",
    "addr:postcode":"s4s 0j9",
    "addr:street":"Montague St",
    "iso:country":"CA",
    "sg:address":"2700 Montague St",
    "sg:city":"Regina",
    "sg:classifiers":[
        {
            "category":"Personal",
            "subcategory":"Barber",
            "type":"Services"
        }
    ],
    "sg:phone":"+1 306 584 7822",
    "sg:postcode":"S4S 0J9",
    "sg:province":"SK",
    "wof:name":"Ivan's Barber Shop",
    "wof:placetype":"venue"
},
  "geometry": {"coordinates":[-104.63060760499999,50.4360656738],"type":"Point"}
}