{
  "type": "Feature",
  "properties": {
    "addr:full":"33660 South Fraser Way Abbotsford BC V2S 2B9",
    "addr:housenumber":"33660",
    "addr:postcode":"v2s 2b9",
    "addr:street":"South Fraser Way",
    "iso:country":"CA",
    "sg:address":"33660 South Fraser Way",
    "sg:city":"Abbotsford",
    "sg:classifiers":[
        {
            "category":"Education",
            "subcategory":"Library",
            "type":"Public Place"
        }
    ],
    "sg:phone":"+1 604 853 1753",
    "sg:postcode":"V2S 2B9",
    "sg:province":"BC",
    "wof:name":"Msa Centennial Library",
    "wof:placetype":"venue"
},
  "geometry": {"coordinates":[-122.29233600000001,49.048489],"type":"Point"}
}