{
  "type": "Feature",
  "properties": {
    "addr:full":"710 Dairy Rd Kamloops BC V2B 8N5",
    "addr:housenumber":"710",
    "addr:postcode":"bc v2b 8n5",
    "addr:street":"Dairy Rd",
    "iso:country":"CA",
    "sg:address":"710 Dairy Rd",
    "sg:city":"Kamloops",
    "sg:classifiers":[
        {
            "category":"Food & Beverages",
            "subcategory":"Specialty",
            "type":"Retail Goods"
        }
    ],
    "sg:phone":"+1 250 579 9617",
    "sg:postcode":"V2B 8N5",
    "sg:province":"BC",
    "sg:tags":[
        "organic",
        "health",
        "diet"
    ],
    "wof:name":"Thistle Farm",
    "wof:placetype":"venue"
},
  "geometry": {"coordinates":[-120.315117,50.817276],"type":"Point"}
}