{
  "type": "Feature",
  "properties": {
    "addr:full":"6215 48 St SE Calgary AB T2C 3J7",
    "addr:housenumber":"6215",
    "addr:postcode":"t2c 3j7",
    "addr:street":"48 St Se",
    "iso:country":"CA",
    "sg:address":"6215 48 St SE",
    "sg:city":"Calgary",
    "sg:classifiers":[
        {
            "category":"Retail",
            "subcategory":"Auto Rental",
            "type":"Services"
        }
    ],
    "sg:phone":"+1 403 236 7161",
    "sg:postcode":"T2C 3J7",
    "sg:province":"AB",
    "sg:tags":[
        "renting",
        "truck",
        "leasing"
    ],
    "wof:name":"Penske Truck Leasing Canada",
    "wof:placetype":"venue"
},
  "geometry": {"coordinates":[-113.96446228000001,50.9987449646],"type":"Point"}
}