{
  "type": "Feature",
  "properties": {
    "addr:full":"11133 184 St NW Edmonton AB T5S 2L6",
    "addr:housenumber":"11133",
    "addr:postcode":"t5s 2l6",
    "addr:street":"184 St Nw",
    "iso:country":"CA",
    "sg:address":"11133 184 St NW",
    "sg:city":"Edmonton",
    "sg:classifiers":[
        {
            "category":"Shopping",
            "type":"Retail Goods"
        }
    ],
    "sg:phone":"+1 780 453 3364",
    "sg:postcode":"T5S 2L6",
    "sg:province":"AB",
    "sg:tags":[
        "picture",
        "frame"
    ],
    "wof:name":"Frameguild",
    "wof:placetype":"venue"
},
  "geometry": {"coordinates":[-113.63938899999999,53.560284],"type":"Point"}
}