{
  "type": "Feature",
  "properties": {
    "addr:full":"737 Ferguson St #B Tracadie-Sheila NB E1X 1C6",
    "addr:housenumber":"737",
    "addr:postcode":"e1x 1c6",
    "addr:street":"Ferguson St # B Tracadie-Sheila",
    "iso:country":"CA",
    "sg:address":"737 Ferguson St #B",
    "sg:city":"Tracadie-Sheila",
    "sg:classifiers":[
        {
            "category":"Insurance",
            "subcategory":"Insurance Agent",
            "type":"Services"
        }
    ],
    "sg:phone":"+1 506 395 3575",
    "sg:postcode":"E1X 1C6",
    "sg:province":"NB",
    "wof:name":"Assurances Lg Trask",
    "wof:placetype":"venue"
},
  "geometry": {"coordinates":[-64.91059112550001,47.5213088989],"type":"Point"}
}