{
  "type": "Feature",
  "properties": {
    "iso:country":"CA",
    "sg:city":"Grande Prairie",
    "sg:classifiers":[
        {
            "category":"Insurance",
            "subcategory":"Insurance Agent",
            "type":"Services"
        }
    ],
    "sg:phone":"+1 780 532 2991",
    "sg:postcode":"T8V 1R6",
    "sg:province":"AB",
    "wof:name":"Price, J Lindsay",
    "wof:placetype":"venue"
},
  "geometry": {"coordinates":[-118.79454040500001,55.1792297363],"type":"Point"}
}