{
  "type": "Feature",
  "properties": {
    "addr:full":"Exeter ON N0M 1S3",
    "addr:postcode":"n0m 1s3",
    "iso:country":"CA",
    "sg:city":"Exeter",
    "sg:classifiers":[
        {
            "category":"Autos & Motor Vehicles",
            "subcategory":"Automobile Sales",
            "type":"Retail Goods"
        }
    ],
    "sg:phone":"+1 519 235 3698",
    "sg:postcode":"N0M 1S3",
    "sg:province":"ON",
    "sg:tags":[
        "car",
        "dealer"
    ],
    "wof:name":"Bdm Motor Car Inc",
    "wof:placetype":"venue"
},
  "geometry": {"coordinates":[-81.48612213129999,43.3615951538],"type":"Point"}
}