{
  "type": "Feature",
  "properties": {
    "iso:country":"CA",
    "sg:address":"38 Thornway Ave",
    "sg:city":"Thornhill",
    "sg:classifiers":[
        {
            "category":"Wholesale",
            "subcategory":"Machinery & Supplies",
            "type":"Manufacturing & Wholesale Goods"
        }
    ],
    "sg:phone":"+1 905 761 1394",
    "sg:postcode":"L4J 7R8",
    "sg:province":"ON",
    "sg:tags":[
        "machine",
        "sewing"
    ],
    "wof:name":"Able Sewing Machines",
    "wof:placetype":"venue"
},
  "geometry": {"coordinates":[-79.46156311039999,43.8079719543],"type":"Point"}
}