{
  "type": "Feature",
  "properties": {
    "addr:full":"1481 28E Av Pointe-Aux-Trembles QC H1A 4S2",
    "addr:housenumber":"1481",
    "addr:postcode":"h1a 4s2",
    "addr:street":"28E Av Pointe-Aux-Trembles",
    "iso:country":"CA",
    "sg:address":"1481 28E Av",
    "sg:city":"Pointe-Aux-Trembles",
    "sg:classifiers":[
        {
            "category":"Building & Trades",
            "subcategory":"Electrical",
            "type":"Services"
        }
    ],
    "sg:phone":"+1 514 644 0677",
    "sg:postcode":"H1A 4S2",
    "sg:province":"QC",
    "sg:tags":[
        "electric",
        "contractor"
    ],
    "wof:name":"Richard Bond Electrique Inc",
    "wof:placetype":"venue"
},
  "geometry": {"coordinates":[-73.501625,45.654125],"type":"Point"}
}