{
  "type": "Feature",
  "properties": {
    "addr:full":"Salaberry-DE-Valleyfield QC J6T 4R1",
    "addr:postcode":"j6t 4r1",
    "iso:country":"CA",
    "sg:city":"Salaberry-DE-Valleyfield",
    "sg:classifiers":[
        {
            "category":"Banks & Credit Unions",
            "subcategory":"Investment Brokerage",
            "type":"Services"
        }
    ],
    "sg:phone":"+1 450 373 5030",
    "sg:postcode":"J6T 4R1",
    "sg:province":"QC",
    "sg:tags":[
        "advisory",
        "financial"
    ],
    "wof:name":"Groupe Investors",
    "wof:placetype":"venue"
},
  "geometry": {"coordinates":[-74.129486,45.254852],"type":"Point"}
}