{
  "type": "Feature",
  "properties": {
    "addr:full":"222 Esplanade E North Vancouver BC V7L 1A3",
    "addr:housenumber":"222",
    "addr:postcode":"v7l 1a3",
    "addr:street":"Esplanade E",
    "iso:country":"CA",
    "sg:address":"222 Esplanade E",
    "sg:city":"North Vancouver",
    "sg:classifiers":[
        {
            "category":"Retail",
            "subcategory":"Auto Repair",
            "type":"Services"
        }
    ],
    "sg:phone":"+1 604 990 5267",
    "sg:postcode":"V7L 1A3",
    "sg:province":"BC",
    "sg:tags":[
        "repairing",
        "automobile"
    ],
    "wof:name":"Marlatt Motor Works",
    "wof:placetype":"venue"
},
  "geometry": {"coordinates":[-123.07533264200001,49.3095016479],"type":"Point"}
}