{
  "type": "Feature",
  "properties": {
    "iso:country":"CA",
    "sg:address":"209 Harding Blvd W",
    "sg:city":"Richmond Hill",
    "sg:classifiers":[
        {
            "category":"Professional",
            "subcategory":"Accounting & Tax Preparation",
            "type":"Services"
        }
    ],
    "sg:phone":"+1 905 883 1508",
    "sg:postcode":"L4C 8X6",
    "sg:province":"ON",
    "sg:tags":[
        "accountant"
    ],
    "wof:name":"Veltheer, Robert M CA",
    "wof:placetype":"venue"
},
  "geometry": {"coordinates":[-79.4468536377,43.8671112061],"type":"Point"}
}