{
  "type": "Feature",
  "properties": {
    "addr:full":"50 Inverlochy Blvd Thornhill ON L3T 4T6",
    "addr:housenumber":"50",
    "addr:postcode":"l3t 4t6",
    "addr:street":"Inverlochy Blvd",
    "iso:country":"CA",
    "sg:address":"50 Inverlochy Blvd",
    "sg:city":"Thornhill",
    "sg:classifiers":[
        {
            "category":"Real Estate",
            "subcategory":"Real Estate Operator",
            "type":"Services"
        }
    ],
    "sg:phone":"+1 905 881 3368",
    "sg:postcode":"L3T 4T6",
    "sg:province":"ON",
    "sg:tags":[
        "condominium"
    ],
    "wof:name":"York Condo 300",
    "wof:placetype":"venue"
},
  "geometry": {"coordinates":[-79.423523,43.821228],"type":"Point"}
}