{
  "type": "Feature",
  "properties": {
    "iso:country":"CA",
    "sg:address":"11451 Rue Sainte-Catherine E",
    "sg:city":"Montreal-Est",
    "sg:classifiers":[
        {
            "category":"Organizations",
            "subcategory":"Labor Organization",
            "type":"Services"
        }
    ],
    "sg:phone":"+1 514 645 5445",
    "sg:postcode":"H1B 5W7",
    "sg:province":"QC",
    "wof:name":"Scep Local 7Q",
    "wof:placetype":"venue"
},
  "geometry": {"coordinates":[-73.506271,45.633884],"type":"Point"}
}