{
  "type": "Feature",
  "properties": {
    "addr:full":"Toronto ON M6S 1M5",
    "addr:postcode":"m6s 1m5",
    "iso:country":"CA",
    "sg:city":"Toronto",
    "sg:classifiers":[
        {
            "category":"Shopping",
            "subcategory":"Bicycles & Sporting Goods",
            "type":"Retail Goods"
        }
    ],
    "sg:phone":"+1 416 762 9119",
    "sg:postcode":"M6S 1M5",
    "sg:province":"ON",
    "wof:name":"Wheels of Bloor",
    "wof:placetype":"venue"
},
  "geometry": {"coordinates":[-79.47184,43.651985],"type":"Point"}
}