{
  "type": "Feature",
  "properties": {
    "iso:country":"CA",
    "sg:address":"7825 103 St",
    "sg:city":"Grande Prairie",
    "sg:classifiers":[
        {
            "category":"Building & Trades",
            "subcategory":"Electrical",
            "type":"Services"
        }
    ],
    "sg:phone":"+1 780 538 4344",
    "sg:postcode":"T8W 1Y5",
    "sg:province":"AB",
    "sg:tags":[
        "electric",
        "contractor"
    ],
    "wof:name":"Northwest Electric Ltd",
    "wof:placetype":"venue"
},
  "geometry": {"coordinates":[-118.806793,55.151405],"type":"Point"}
}