{
  "type": "Feature",
  "properties": {
    "addr:full":"94 Kenhar Dr North York ON M9L 1N2",
    "addr:housenumber":"94",
    "addr:postcode":"m9l 1n2",
    "addr:street":"Kenhar Dr",
    "iso:country":"CA",
    "sg:address":"94 Kenhar Dr",
    "sg:city":"North York",
    "sg:classifiers":[
        {
            "category":"Manufacturing",
            "subcategory":"Apparel",
            "type":"Manufacturing & Wholesale Goods"
        }
    ],
    "sg:phone":"+1 416 749 3336",
    "sg:postcode":"M9L 1N2",
    "sg:province":"ON",
    "sg:tags":[
        "clothing"
    ],
    "wof:name":"Allure Leather Fashions",
    "wof:placetype":"venue"
},
  "geometry": {"coordinates":[-79.54582977290001,43.7615623474],"type":"Point"}
}