{
  "type": "Feature",
  "properties": {
    "iso:country":"CA",
    "sg:address":"4225 107 St NW",
    "sg:city":"Edmonton",
    "sg:classifiers":[
        {
            "category":"Health Services",
            "subcategory":"Nursing And Care Facility",
            "type":"Services"
        }
    ],
    "sg:phone":"+1 780 431 3600",
    "sg:postcode":"T6J 2P1",
    "sg:province":"AB",
    "sg:tags":[
        "home",
        "convalescent"
    ],
    "wof:name":"Southgate Care Ctr",
    "wof:placetype":"venue"
},
  "geometry": {"coordinates":[-113.507621765,53.4799003601],"type":"Point"}
}