{
  "type": "Feature",
  "properties": {
    "addr:full":"1276 Av Dollard Lasalle QC H8N 2P2",
    "addr:housenumber":"1276",
    "addr:postcode":"h8n 2p2",
    "addr:street":"Av Dollard",
    "iso:country":"CA",
    "sg:address":"1276 Av Dollard",
    "sg:city":"Lasalle",
    "sg:classifiers":[
        {
            "category":"Food & Beverages",
            "subcategory":"Bakery",
            "type":"Retail Goods"
        }
    ],
    "sg:phone":"+1 514 363 8776",
    "sg:postcode":"H8N 2P2",
    "sg:province":"QC",
    "sg:tags":[
        "baker"
    ],
    "wof:name":"Pains & Delices Luigi",
    "wof:placetype":"venue"
},
  "geometry": {"coordinates":[-73.625519,45.425915],"type":"Point"}
}