{
  "type": "Feature",
  "properties": {
    "iso:country":"CA",
    "sg:city":"Abbotsford",
    "sg:classifiers":[
        {
            "category":"Restaurant",
            "type":"Food & Drink"
        }
    ],
    "sg:phone":"+1 604 626 0330",
    "sg:postcode":"V4X 2M9",
    "sg:province":"BC",
    "wof:name":"Hana Sushi",
    "wof:placetype":"venue"
},
  "geometry": {"coordinates":[-122.381034851,49.061794281],"type":"Point"}
}