{
  "type": "Feature",
  "properties": {
    "addr:full":"Nanticoke ON N0A 1L0",
    "addr:postcode":"n0a 1l0",
    "addr:street":"Nanticoke",
    "iso:country":"CA",
    "sg:city":"Nanticoke",
    "sg:classifiers":[
        {
            "category":"Manufacturing",
            "subcategory":"Metals",
            "type":"Manufacturing & Wholesale Goods"
        }
    ],
    "sg:phone":"+1 905 776 2008",
    "sg:postcode":"N0A 1L0",
    "sg:province":"ON",
    "sg:tags":[
        "general",
        "contractor"
    ],
    "wof:name":"J & M Contractors",
    "wof:placetype":"venue"
},
  "geometry": {"coordinates":[-80.07197600000001,42.810741],"type":"Point"}
}