{
  "type": "Feature",
  "properties": {
    "addr:full":"South Shore Rd Pointe-Au-Baril-Station ON P0G 1K0",
    "addr:postcode":"p0g 1k0",
    "addr:street":"South Shore Rd",
    "iso:country":"CA",
    "sg:address":"South Shore Rd",
    "sg:city":"Pointe-Au-Baril-Station",
    "sg:classifiers":[
        {
            "category":"Recreation",
            "type":"Entertainment"
        }
    ],
    "sg:phone":"+1 705 366 2515",
    "sg:postcode":"P0G 1K0",
    "sg:province":"ON",
    "sg:tags":[
        "government",
        "hall",
        "auditorium"
    ],
    "wof:name":"Point Au Baril Community Ctr",
    "wof:placetype":"venue"
},
  "geometry": {"coordinates":[-80.37716674799999,45.6002883911],"type":"Point"}
}