{
  "type": "Feature",
  "properties": {
    "addr:full":"Main St Lunaire-Griquet NL A0K 2X0",
    "addr:postcode":"a0k 2x0",
    "addr:street":"Main St",
    "iso:country":"CA",
    "sg:address":"Main",
    "sg:city":"St Lunaire-Griquet",
    "sg:classifiers":[
        {
            "category":"Professional",
            "type":"Services"
        }
    ],
    "sg:phone":"+1 709 623 2371",
    "sg:postcode":"A0K 2X0",
    "sg:province":"NL",
    "sg:tags":[
        "sculptor"
    ],
    "wof:name":"Stage Head Carvings Ltd",
    "wof:placetype":"venue"
},
  "geometry": {"coordinates":[-55.4839439392,51.5050582886],"type":"Point"}
}