{
  "type": "Feature",
  "properties": {
    "addr:full":"2 Complex Desjardins Montreal QC H5B 1E9",
    "addr:housenumber":"2",
    "addr:postcode":"h5b 1e9",
    "addr:street":"Complex Desjardins",
    "iso:country":"CA",
    "sg:address":"2 Complex Desjardins",
    "sg:city":"Montreal",
    "sg:classifiers":[
        {
            "category":"Shopping",
            "subcategory":"Clothing, Apparel, & Fashions",
            "type":"Retail Goods"
        }
    ],
    "sg:phone":"+1 514 845 1468",
    "sg:postcode":"H5B 1E9",
    "sg:province":"QC",
    "sg:tags":[
        "item",
        "boutique"
    ],
    "wof:name":"Au Coton",
    "wof:placetype":"venue"
},
  "geometry": {"coordinates":[-73.565994,45.507198],"type":"Point"}
}