{
  "type": "Feature",
  "properties": {
    "addr:full":"111 Smithe St Vancouver BC V6B 4Z8",
    "addr:housenumber":"111",
    "addr:postcode":"bc v6b 4z8",
    "addr:street":"Smithe St",
    "iso:country":"CA",
    "sg:address":"111 Smithe St",
    "sg:city":"Vancouver",
    "sg:classifiers":[
        {
            "category":"Professional",
            "subcategory":"Lawyer & Legal Services",
            "type":"Services"
        }
    ],
    "sg:phone":"+1 604 648 2901",
    "sg:postcode":"V6B 4Z8",
    "sg:province":"BC",
    "sg:tags":[
        "attorney"
    ],
    "wof:name":"Tevlin, Murray",
    "wof:placetype":"venue"
},
  "geometry": {"coordinates":[-123.11555481000001,49.2767486572],"type":"Point"}
}