{
  "type": "Feature",
  "properties": {
    "addr:full":"Edmonton AB T6J 6L7",
    "addr:postcode":"t6j 6l7",
    "iso:country":"CA",
    "sg:city":"Edmonton",
    "sg:classifiers":[
        {
            "category":"Retail",
            "subcategory":"Laundry & Dry Cleaning",
            "type":"Services"
        }
    ],
    "sg:phone":"+1 780 436 5672",
    "sg:postcode":"T6J 6L7",
    "sg:province":"AB",
    "sg:tags":[
        "cleaners"
    ],
    "wof:name":"Valtone Cleaners",
    "wof:placetype":"venue"
},
  "geometry": {"coordinates":[-113.503906,53.47905],"type":"Point"}
}