{
  "type": "Feature",
  "properties": {
    "addr:full":"4133 Dundas St W Etobicoke ON M8X 1X2",
    "addr:housenumber":"4133",
    "addr:postcode":"m8x 1x2",
    "addr:street":"Dundas St W",
    "iso:country":"CA",
    "sg:address":"4133 Dundas St W",
    "sg:city":"Etobicoke",
    "sg:classifiers":[
        {
            "category":"Home & Garden",
            "subcategory":"Carpets & Floor Coverings",
            "type":"Retail Goods"
        }
    ],
    "sg:phone":"+1 416 233 2281",
    "sg:postcode":"M8X 1X2",
    "sg:province":"ON",
    "sg:tags":[
        "dealer",
        "rug"
    ],
    "wof:name":"Kingsway Carpet & Blinds",
    "wof:placetype":"venue"
},
  "geometry": {"coordinates":[-79.50751495359999,43.6616287231],"type":"Point"}
}