{
  "type": "Feature",
  "properties": {
    "iso:country":"CA",
    "sg:address":"1395 Abbeywood Dr # 15",
    "sg:city":"Oakville",
    "sg:classifiers":[
        {
            "category":"Personal",
            "subcategory":"Beauty Salon",
            "type":"Services"
        }
    ],
    "sg:phone":"+1 905 847 5823",
    "sg:postcode":"L6M 3B2",
    "sg:province":"ON",
    "sg:tags":[
        "day"
    ],
    "wof:name":"Abbeywood Spa",
    "wof:placetype":"venue"
},
  "geometry": {"coordinates":[-79.7259750366,43.4310188293],"type":"Point"}
}