{
  "type": "Feature",
  "properties": {
    "iso:country":"CA",
    "sg:address":"PO Box 44 STN Main",
    "sg:city":"Lindsay",
    "sg:classifiers":[
        {
            "category":"Building & Trades",
            "subcategory":"Pest Control",
            "type":"Services"
        }
    ],
    "sg:phone":"+1 705 878 9060",
    "sg:postcode":"K9V 4R8",
    "sg:province":"ON",
    "sg:tags":[
        "society",
        "humane"
    ],
    "wof:name":"Northern Pest Management",
    "wof:placetype":"venue"
},
  "geometry": {"coordinates":[-78.74006652830001,44.3542861938],"type":"Point"}
}