{
  "type": "Feature",
  "properties": {
    "iso:country":"CA",
    "sg:address":"800 Av Desaulniers",
    "sg:city":"Saint-Hyacinthe",
    "sg:classifiers":[
        {
            "category":"Organizations",
            "subcategory":"Religious Organization",
            "type":"Services"
        }
    ],
    "sg:phone":"+1 450 773 4233",
    "sg:postcode":"J2S 8P5",
    "sg:province":"QC",
    "sg:tags":[
        "school"
    ],
    "wof:name":"Couvent Du Precieux Sang",
    "wof:placetype":"venue"
},
  "geometry": {"coordinates":[-72.9551696777,45.6211662292],"type":"Point"}
}