{
  "type": "Feature",
  "properties": {
    "addr:full":"4268 Stewart Rd Chilliwack BC V2R 5G2",
    "addr:housenumber":"4268",
    "addr:postcode":"v2r 5g2",
    "addr:street":"Stewart Rd",
    "iso:country":"CA",
    "sg:address":"4268 Stewart Rd",
    "sg:city":"Chilliwack",
    "sg:classifiers":[
        {
            "category":"Education",
            "subcategory":"School",
            "type":"Public Place"
        }
    ],
    "sg:phone":"+1 604 823 6814",
    "sg:postcode":"V2R 5G2",
    "sg:province":"BC",
    "wof:name":"John Calvin School",
    "wof:placetype":"venue"
},
  "geometry": {"coordinates":[-122.06745147700001,49.0789031982],"type":"Point"}
}