{
  "type": "Feature",
  "properties": {
    "iso:country":"CA",
    "sg:city":"Calgary",
    "sg:classifiers":[
        {
            "category":"Building & Trades",
            "subcategory":"Construction",
            "type":"Services"
        }
    ],
    "sg:phone":"+1 403 256 5123",
    "sg:postcode":"T2X 1J6",
    "sg:province":"AB",
    "sg:tags":[
        "designer"
    ],
    "wof:name":"Evans 2 Design Group",
    "wof:placetype":"venue"
},
  "geometry": {"coordinates":[-114.06387329099999,50.9103355408],"type":"Point"}
}