{
  "type": "Feature",
  "properties": {
    "addr:full":"Vancouver BC V6B 2W6",
    "addr:postcode":"v6b 2w6",
    "iso:country":"CA",
    "sg:city":"Vancouver",
    "sg:classifiers":[
        {
            "category":"Building & Trades",
            "subcategory":"Construction",
            "type":"Services"
        }
    ],
    "sg:phone":"+1 604 602 7700",
    "sg:postcode":"V6B 2W6",
    "sg:province":"BC",
    "sg:tags":[
        "general",
        "contractor"
    ],
    "wof:name":"Amacon Group",
    "wof:placetype":"venue"
},
  "geometry": {"coordinates":[-123.118889,49.278332],"type":"Point"}
}