{
  "type": "Feature",
  "properties": {
    "addr:full":"7A Ralston Ave Dartmouth NS B3B 1H5",
    "addr:housenumber":"7a",
    "addr:postcode":"b3b 1h5",
    "addr:street":"Ralston Ave",
    "iso:country":"CA",
    "sg:address":"7A Ralston Ave",
    "sg:city":"Dartmouth",
    "sg:classifiers":[
        {
            "category":"Utilities",
            "subcategory":"Refuse",
            "type":"Services"
        }
    ],
    "sg:phone":"+1 902 466 7501",
    "sg:postcode":"B3B 1H5",
    "sg:province":"NS",
    "sg:tags":[
        "garbage",
        "collection",
        "trucking"
    ],
    "wof:name":"Ed DE Wolfe Trucking Ltd",
    "wof:placetype":"venue"
},
  "geometry": {"coordinates":[-63.6068153381,44.7011680603],"type":"Point"}
}