{
  "type": "Feature",
  "properties": {
    "addr:full":"1554 Marine Dr West Vancouver BC V7V 1H8",
    "addr:housenumber":"1554",
    "addr:postcode":"v7v 1h8",
    "addr:street":"Marine Dr",
    "iso:country":"CA",
    "sg:address":"1554 Marine Dr",
    "sg:city":"West Vancouver",
    "sg:classifiers":[
        {
            "category":"Manufacturing",
            "subcategory":"Metals",
            "type":"Manufacturing & Wholesale Goods"
        }
    ],
    "sg:phone":"+1 604 922 3156",
    "sg:postcode":"V7V 1H8",
    "sg:province":"BC",
    "sg:tags":[
        "brass",
        "furniture"
    ],
    "wof:name":"Brassicles",
    "wof:placetype":"venue"
},
  "geometry": {"coordinates":[-123.157958984,49.3283424377],"type":"Point"}
}