{
  "type": "Feature",
  "properties": {
    "iso:country":"CA",
    "sg:address":"700 St Peter Ave",
    "sg:city":"Bathurst",
    "sg:classifiers":[
        {
            "category":"Shopping",
            "subcategory":"Optical Goods",
            "type":"Retail Goods"
        }
    ],
    "sg:phone":"+1 506 545 6077",
    "sg:postcode":"E2A 2Y7",
    "sg:province":"NB",
    "sg:tags":[
        "optician"
    ],
    "wof:name":"Optique Heritage Optical",
    "wof:placetype":"venue"
},
  "geometry": {"coordinates":[-65.66826629640001,47.6317100525],"type":"Point"}
}