{
  "type": "Feature",
  "properties": {
    "addr:full":"Delta BC V4G 1C5",
    "addr:postcode":"v4g 1c5",
    "iso:country":"CA",
    "sg:city":"Delta",
    "sg:classifiers":[
        {
            "category":"Wholesale",
            "subcategory":"Home Furnishings",
            "type":"Manufacturing & Wholesale Goods"
        }
    ],
    "sg:phone":"+1 604 940 9652",
    "sg:postcode":"V4G 1C5",
    "sg:province":"BC",
    "sg:tags":[
        "housewares"
    ],
    "wof:name":"Mulder & CO Marketing Inc",
    "wof:placetype":"venue"
},
  "geometry": {"coordinates":[-123.018333,49.131199],"type":"Point"}
}