{
  "type": "Feature",
  "properties": {
    "addr:full":"5248 Morris St Halifax NS B3J 1B4",
    "addr:housenumber":"5248",
    "addr:postcode":"ns b3j 1b4",
    "addr:street":"Morris St",
    "iso:country":"CA",
    "sg:address":"5248 Morris St",
    "sg:city":"Halifax",
    "sg:classifiers":[
        {
            "category":"Professional",
            "subcategory":"Employment Agencies",
            "type":"Services"
        }
    ],
    "sg:phone":"+1 902 491 7600",
    "sg:postcode":"B3J 1B4",
    "sg:province":"NS",
    "sg:tags":[
        "consultant",
        "search",
        "executive",
        "opportunity"
    ],
    "wof:name":"Talentworks Inc",
    "wof:placetype":"venue"
},
  "geometry": {"coordinates":[-63.5724182129,44.6412963867],"type":"Point"}
}