{
  "type": "Feature",
  "properties": {
    "addr:full":"1790 Rue Villeneuve Saint-Emile QC G3E 1N6",
    "addr:housenumber":"1790",
    "addr:postcode":"g3e 1n6",
    "addr:street":"Rue Villeneuve Saint-Emile",
    "iso:country":"CA",
    "sg:address":"1790 Rue Villeneuve",
    "sg:city":"Saint-Emile",
    "sg:phone":"+1 418 842 3281",
    "sg:postcode":"G3E 1N6",
    "sg:province":"QC",
    "sg:tags":[
        "tank",
        "station",
        "installation",
        "equipment"
    ],
    "wof:name":"Constructions Jm Robitaille",
    "wof:placetype":"venue"
},
  "geometry": {"coordinates":[-71.33908099999999,46.87215],"type":"Point"}
}