{
  "type": "Feature",
  "properties": {
    "iso:country":"CA",
    "sg:address":"172 Victoria St N",
    "sg:city":"Kitchener",
    "sg:classifiers":[
        {
            "category":"Retail",
            "subcategory":"Auto Repair",
            "type":"Services"
        }
    ],
    "sg:phone":"+1 519 741 1536",
    "sg:postcode":"N2H 5C6",
    "sg:province":"ON",
    "sg:tags":[
        "repairing",
        "automobile"
    ],
    "wof:name":"C & S Automotive",
    "wof:placetype":"venue"
},
  "geometry": {"coordinates":[-80.4905700684,43.4560470581],"type":"Point"}
}