{
  "type": "Feature",
  "properties": {
    "addr:full":"778 Confederation St Sarnia ON N7T 2E3",
    "addr:housenumber":"778",
    "addr:postcode":"n7t 2e3",
    "addr:street":"Confederation St",
    "iso:country":"CA",
    "sg:address":"778 Confederation St",
    "sg:city":"Sarnia",
    "sg:classifiers":[
        {
            "category":"Retail",
            "subcategory":"Auto Repair",
            "type":"Services"
        }
    ],
    "sg:phone":"+1 519 344 9979",
    "sg:postcode":"N7T 2E3",
    "sg:province":"ON",
    "sg:tags":[
        "body",
        "automobile",
        "painting"
    ],
    "wof:name":"Ontario Auto Body",
    "wof:placetype":"venue"
},
  "geometry": {"coordinates":[-82.382721,42.960876],"type":"Point"}
}