{
  "type": "Feature",
  "properties": {
    "addr:full":"14831 28 Ave Surrey BC V4P 1P3",
    "addr:housenumber":"14831",
    "addr:postcode":"v4p 1p3",
    "addr:street":"28 Ave",
    "iso:country":"CA",
    "sg:address":"14831 28 Ave",
    "sg:city":"Surrey",
    "sg:classifiers":[
        {
            "category":"Retail",
            "subcategory":"Funeral Services",
            "type":"Services"
        }
    ],
    "sg:phone":"+1 604 536 6522",
    "sg:postcode":"V4P 1P3",
    "sg:province":"BC",
    "sg:tags":[
        "director",
        "crematory"
    ],
    "wof:name":"Victory Memorial Park Funeral",
    "wof:placetype":"venue"
},
  "geometry": {"coordinates":[-122.811210632,49.0531349182],"type":"Point"}
}