{
  "type": "Feature",
  "properties": {
    "iso:country":"CA",
    "sg:city":"Gibsons",
    "sg:classifiers":[
        {
            "category":"Personal",
            "subcategory":"Beauty Salon",
            "type":"Services"
        }
    ],
    "sg:phone":"+1 604 886 6860",
    "sg:postcode":"V0N 1V9",
    "sg:province":"BC",
    "wof:name":"Q T's Hair Design",
    "wof:placetype":"venue"
},
  "geometry": {"coordinates":[-123.507484436,49.4070625305],"type":"Point"}
}