{
  "type": "Feature",
  "properties": {
    "iso:country":"CA",
    "sg:address":"645 Mcmurray Rd",
    "sg:city":"Waterloo",
    "sg:classifiers":[
        {
            "category":"Wholesale",
            "subcategory":"Auto Parts",
            "type":"Manufacturing & Wholesale Goods"
        }
    ],
    "sg:phone":"+1 519 885 4420",
    "sg:postcode":"N2V 2B7",
    "sg:province":"ON",
    "sg:tags":[
        "tire"
    ],
    "wof:name":"Conestoga Tire & Rim",
    "wof:placetype":"venue"
},
  "geometry": {"coordinates":[-80.5295257568,43.5095291138],"type":"Point"}
}