{
  "type": "Feature",
  "properties": {
    "addr:full":"20439 Douglas Cres Langley BC V3A 4B6",
    "addr:housenumber":"20439",
    "addr:postcode":"v3a 4b6",
    "addr:street":"Douglas Cres",
    "iso:country":"CA",
    "sg:address":"20439 Douglas Cres",
    "sg:city":"Langley",
    "sg:classifiers":[
        {
            "category":"Organizations",
            "subcategory":"Non-profit Organization",
            "type":"Services"
        }
    ],
    "sg:phone":"+1 604 534 1195",
    "sg:postcode":"V3A 4B6",
    "sg:province":"BC",
    "sg:tags":[
        "alternative",
        "abortion",
        "association"
    ],
    "wof:name":"Langley Pro Life Society",
    "wof:placetype":"venue"
},
  "geometry": {"coordinates":[-122.65553300000001,49.103603],"type":"Point"}
}