{
  "type": "Feature",
  "properties": {
    "addr:full":"1018 Smart Rd Cloyne ON K0H 1K0",
    "addr:housenumber":"1018",
    "addr:postcode":"k0h 1k0",
    "addr:street":"Smart Rd",
    "iso:country":"CA",
    "sg:address":"1018 Smart Rd",
    "sg:city":"Cloyne",
    "sg:classifiers":[
        {
            "category":"Autos & Motor Vehicles",
            "subcategory":"Boat Sales",
            "type":"Retail Goods"
        }
    ],
    "sg:phone":"+1 613 336 2222",
    "sg:postcode":"K0H 1K0",
    "sg:province":"ON",
    "sg:tags":[
        "marina",
        "dealer"
    ],
    "wof:name":"Smart's Marina",
    "wof:placetype":"venue"
},
  "geometry": {"coordinates":[-77.1869888306,44.8220901489],"type":"Point"}
}