{
  "type": "Feature",
  "properties": {
    "addr:full":"100 Alexis-Nihon Blvd, Suite 770 Montreal  H4M 2P3",
    "addr:housenumber":"100",
    "addr:postcode":"h4m 2p3",
    "addr:street":"Alexis-Nihon Blvd Suite 770",
    "iso:country":"CA",
    "sg:address":"100 Alexis-Nihon Blvd, Suite 770",
    "sg:city":"Montreal",
    "sg:classifiers":[
        {
            "category":"Professional",
            "subcategory":"Computer Services",
            "type":"Services"
        }
    ],
    "sg:postcode":" H4M 2P3",
    "sg:website":"http://www.trellia.com",
    "wof:name":"Trellia Networks",
    "wof:placetype":"venue"
},
  "geometry": {"coordinates":[-73.6763827,45.4961978],"type":"Point"}
}