{
  "type": "Feature",
  "properties": {
    "iso:country":"CA",
    "sg:address":"3204 LA Grande-Allee",
    "sg:city":"Saint-Hubert",
    "sg:classifiers":[
        {
            "category":"Professional",
            "subcategory":"Business Services",
            "type":"Services"
        }
    ],
    "sg:phone":"+1 450 462 2440",
    "sg:postcode":"J4T 2S5",
    "sg:province":"QC",
    "sg:tags":[
        "consultant",
        "relation",
        "labor"
    ],
    "wof:name":"Vezina Labelle & Assoc Inc",
    "wof:placetype":"venue"
},
  "geometry": {"coordinates":[-73.478225708,45.497833252],"type":"Point"}
}