{
  "type": "Feature",
  "properties": {
    "addr:full":"78 Coolspring Cres Nepean ON K2E 7M8",
    "addr:housenumber":"78",
    "addr:postcode":"k2e 7m8",
    "addr:street":"Coolspring Cres",
    "iso:country":"CA",
    "sg:address":"78 Coolspring Cres",
    "sg:city":"Nepean",
    "sg:classifiers":[
        {
            "category":"Professional",
            "subcategory":"Business Services",
            "type":"Services"
        }
    ],
    "sg:phone":"+1 613 228 8824",
    "sg:postcode":"K2E 7M8",
    "sg:province":"ON",
    "sg:tags":[
        "drafting"
    ],
    "wof:name":"Rainbow Drafting Consultants",
    "wof:placetype":"venue"
},
  "geometry": {"coordinates":[-75.71272277830001,45.3489341736],"type":"Point"}
}