{
  "type": "Feature",
  "properties": {
    "iso:country":"CA",
    "sg:address":"1121 Boul Taschereau",
    "sg:city":"LA Prairie",
    "sg:classifiers":[
        {
            "category":"Retail",
            "subcategory":"Auto Repair",
            "type":"Services"
        }
    ],
    "sg:phone":"+1 450 444 2565",
    "sg:postcode":"J5R 1W9",
    "sg:province":"QC",
    "sg:tags":[
        "repairing",
        "automobile"
    ],
    "wof:name":"Mecanique Bellavance Inc",
    "wof:placetype":"venue"
},
  "geometry": {"coordinates":[-73.4986343384,45.4043769836],"type":"Point"}
}