{
  "type": "Feature",
  "properties": {
    "addr:full":"2536 Rue Lapierre Lasalle QC H8N 2W9",
    "addr:housenumber":"2536",
    "addr:postcode":"h8n 2w9",
    "addr:street":"Rue Lapierre",
    "iso:country":"CA",
    "sg:address":"2536 Rue Lapierre",
    "sg:city":"Lasalle",
    "sg:classifiers":[
        {
            "category":"Organizations",
            "subcategory":"Professional Association",
            "type":"Services"
        }
    ],
    "sg:phone":"+1 514 363 1238",
    "sg:postcode":"H8N 2W9",
    "sg:province":"QC",
    "wof:name":"Assn Des Transporteurs",
    "wof:placetype":"venue"
},
  "geometry": {"coordinates":[-73.62989,45.44276],"type":"Point"}
}