{
  "type": "Feature",
  "properties": {
    "addr:full":"1570 7th Ave W Vancouver BC V6J 5M1",
    "addr:housenumber":"1570",
    "addr:postcode":"v6j 5m1",
    "addr:street":"7Th Ave W",
    "iso:country":"CA",
    "sg:address":"1570 7th Ave W",
    "sg:city":"Vancouver",
    "sg:classifiers":[
        {
            "category":"Health Services",
            "subcategory":"Nursing And Care Facility",
            "type":"Services"
        }
    ],
    "sg:phone":"+1 604 738 8380",
    "sg:postcode":"V6J 5M1",
    "sg:province":"BC",
    "sg:tags":[
        "home",
        "retirement",
        "community"
    ],
    "wof:name":"Terraces on 7th",
    "wof:placetype":"venue"
},
  "geometry": {"coordinates":[-123.14016700000001,49.265255],"type":"Point"}
}