{
  "type": "Feature",
  "properties": {
    "addr:full":"3451 Cambie St Vancouver BC V5Z 2W7",
    "addr:housenumber":"3451",
    "addr:postcode":"v5z 2w7",
    "addr:street":"Cambie St",
    "iso:country":"CA",
    "sg:address":"3451 Cambie St",
    "sg:city":"Vancouver",
    "sg:classifiers":[
        {
            "category":"Cinema",
            "subcategory":"Movie Rental",
            "type":"Entertainment"
        }
    ],
    "sg:phone":"+1 604 873 6958",
    "sg:postcode":"V5Z 2W7",
    "sg:province":"BC",
    "sg:tags":[
        "leasing",
        "video",
        "disc",
        "tape"
    ],
    "wof:name":"Black Dog Video",
    "wof:placetype":"venue"
},
  "geometry": {"coordinates":[-123.115371704,49.2545471191],"type":"Point"}
}