{
  "type": "Feature",
  "properties": {
    "addr:full":"2554 Av Sainte-Anne Saint-Hyacinthe QC J2S 5J3",
    "addr:housenumber":"2554",
    "addr:postcode":"j2s 5j3",
    "addr:street":"Av Sainte-Anne",
    "iso:country":"CA",
    "sg:address":"2554 Av Sainte-Anne",
    "sg:city":"Saint-Hyacinthe",
    "sg:classifiers":[
        {
            "category":"Recreation",
            "type":"Entertainment"
        }
    ],
    "sg:phone":"+1 450 773 0735",
    "sg:postcode":"J2S 5J3",
    "sg:province":"QC",
    "sg:tags":[
        "tackle",
        "trip",
        "hunting",
        "fishing"
    ],
    "wof:name":"L M Sports Enr",
    "wof:placetype":"venue"
},
  "geometry": {"coordinates":[-72.957481,45.632092],"type":"Point"}
}