{
  "type": "Feature",
  "properties": {
    "addr:full":"228 Danforth Ave Toronto ON M4K 1N4",
    "addr:housenumber":"228",
    "addr:postcode":"m4k 1n4",
    "addr:street":"Danforth Ave",
    "iso:country":"CA",
    "sg:address":"228 Danforth Ave",
    "sg:city":"Toronto",
    "sg:classifiers":[
        {
            "category":"Shopping",
            "subcategory":"Optical Goods",
            "type":"Retail Goods"
        }
    ],
    "sg:phone":"+1 416 463 8717",
    "sg:postcode":"M4K 1N4",
    "sg:province":"ON",
    "sg:tags":[
        "optician"
    ],
    "wof:name":"Modern Optical",
    "wof:placetype":"venue"
},
  "geometry": {"coordinates":[-79.355492,43.676975],"type":"Point"}
}