{
  "type": "Feature",
  "properties": {
    "addr:full":"1635 Bayview Ave East York ON M4G 3B5",
    "addr:housenumber":"1635",
    "addr:postcode":"m4g 3b5",
    "addr:street":"Bayview Ave",
    "iso:country":"CA",
    "sg:address":"1635 Bayview Ave",
    "sg:city":"East York",
    "sg:classifiers":[
        {
            "category":"Shopping",
            "subcategory":"Used Merchandise",
            "type":"Retail Goods"
        }
    ],
    "sg:phone":"+1 416 488 8080",
    "sg:postcode":"M4G 3B5",
    "sg:province":"ON",
    "sg:tags":[
        "clocks"
    ],
    "wof:name":"A Pagnello's Antique Clock Svc",
    "wof:placetype":"venue"
},
  "geometry": {"coordinates":[-79.375343,43.706734],"type":"Point"}
}