{
  "type": "Feature",
  "properties": {
    "iso:country":"CA",
    "sg:address":"198 Fir St",
    "sg:city":"Sherwood Park",
    "sg:classifiers":[
        {
            "category":"Building & Trades",
            "subcategory":"Plumbing",
            "type":"Services"
        }
    ],
    "sg:phone":"+1 780 467 7680",
    "sg:postcode":"T8A 2A2",
    "sg:province":"AB",
    "sg:tags":[
        "contractor"
    ],
    "wof:name":"Wes Fuller Plumbing & Heating",
    "wof:placetype":"venue"
},
  "geometry": {"coordinates":[-113.311882019,53.5165023804],"type":"Point"}
}