{
  "type": "Feature",
  "properties": {
    "addr:full":"1417 Rue Dezery Montreal QC H1W 2R2",
    "addr:housenumber":"1417",
    "addr:postcode":"h1w 2r2",
    "addr:street":"Rue Dezery",
    "iso:country":"CA",
    "sg:address":"1417 Rue Dezery",
    "sg:city":"Montreal",
    "sg:classifiers":[
        {
            "category":"Freight",
            "type":"Transportation"
        }
    ],
    "sg:phone":"+1 514 521 0775",
    "sg:postcode":"H1W 2R2",
    "sg:province":"QC",
    "sg:tags":[
        "delivery"
    ],
    "wof:name":"Courrier Plus",
    "wof:placetype":"venue"
},
  "geometry": {"coordinates":[-73.541481,45.53944],"type":"Point"}
}