{
  "type": "Feature",
  "properties": {
    "addr:full":"1600 Gamble Pl Winnipeg MB R3T 3L7",
    "addr:housenumber":"1600",
    "addr:postcode":"r3t 3l7",
    "addr:street":"Gamble Pl",
    "iso:country":"CA",
    "sg:address":"1600 Gamble Pl",
    "sg:city":"Winnipeg",
    "sg:classifiers":[
        {
            "category":"Manufacturing",
            "subcategory":"Tools & Machinery",
            "type":"Manufacturing & Wholesale Goods"
        }
    ],
    "sg:phone":"+1 204 284 1330",
    "sg:postcode":"R3T 3L7",
    "sg:province":"MB",
    "sg:tags":[
        "concrete",
        "contractor"
    ],
    "wof:name":"Hertz Equipment Rentals",
    "wof:placetype":"venue"
},
  "geometry": {"coordinates":[-97.17631530760001,49.8328132629],"type":"Point"}
}