{
  "type": "Feature",
  "properties": {
    "addr:full":"Dugald MB R0E 0K0",
    "addr:postcode":"r0e 0k0",
    "iso:country":"CA",
    "sg:city":"Dugald",
    "sg:classifiers":[
        {
            "category":"Recreation",
            "type":"Entertainment"
        }
    ],
    "sg:phone":"+1 204 853 7729",
    "sg:postcode":"R0E 0K0",
    "sg:province":"MB",
    "sg:tags":[
        "club",
        "curling"
    ],
    "wof:name":"Springfield Curling Club",
    "wof:placetype":"venue"
},
  "geometry": {"coordinates":[-96.840118,49.885906],"type":"Point"}
}