{
  "type": "Feature",
  "properties": {
    "addr:full":"Edmonton AB T5C 0A3",
    "addr:postcode":"t5c 0a3",
    "iso:country":"CA",
    "sg:city":"Edmonton",
    "sg:classifiers":[
        {
            "category":"Health Services",
            "subcategory":"Doctor",
            "type":"Services"
        }
    ],
    "sg:phone":"+1 780 478 2787",
    "sg:postcode":"T5C 0A3",
    "sg:province":"AB",
    "sg:tags":[
        "dentist"
    ],
    "wof:name":"Lee, Grace DDS",
    "wof:placetype":"venue"
},
  "geometry": {"coordinates":[-113.44310760499999,53.5853614807],"type":"Point"}
}