{
  "type": "Feature",
  "properties": {
    "iso:country":"CA",
    "sg:address":"837 Rue Clemenceau",
    "sg:city":"Beauport",
    "sg:classifiers":[
        {
            "category":"Restaurant",
            "type":"Food & Drink"
        }
    ],
    "sg:phone":"+1 418 663 9000",
    "sg:postcode":"G1C 2K6",
    "sg:province":"QC",
    "wof:name":"Cage Aux Sports",
    "wof:placetype":"venue"
},
  "geometry": {"coordinates":[-71.20192,46.871082],"type":"Point"}
}