{
  "type": "Feature",
  "properties": {
    "addr:full":"279 Torii St Woodbridge ON L4L 5L3",
    "addr:housenumber":"279",
    "addr:postcode":"l4l 5l3",
    "addr:street":"Torii St",
    "iso:country":"CA",
    "sg:address":"279 Torii St",
    "sg:city":"Woodbridge",
    "sg:classifiers":[
        {
            "category":"Building & Trades",
            "subcategory":"Construction",
            "type":"Services"
        }
    ],
    "sg:phone":"+1 905 851 7996",
    "sg:postcode":"L4L 5L3",
    "sg:province":"ON",
    "sg:tags":[
        "general",
        "contractor"
    ],
    "wof:name":"Sergco General Contracting Inc",
    "wof:placetype":"venue"
},
  "geometry": {"coordinates":[-79.573402,43.787724],"type":"Point"}
}