{
  "type": "Feature",
  "properties": {
    "addr:full":"1335 2nd Ave E Owen Sound ON N4K 2J5",
    "addr:housenumber":"1335",
    "addr:postcode":"n4k 2j5",
    "addr:street":"2Nd Ave E",
    "iso:country":"CA",
    "sg:address":"1335 2nd Ave E",
    "sg:city":"Owen Sound",
    "sg:classifiers":[
        {
            "category":"Retail",
            "subcategory":"Auto Repair",
            "type":"Services"
        }
    ],
    "sg:phone":"+1 519 376 9666",
    "sg:postcode":"N4K 2J5",
    "sg:province":"ON",
    "sg:tags":[
        "muffler",
        "exhaust",
        "system"
    ],
    "wof:name":"Discount Muffler",
    "wof:placetype":"venue"
},
  "geometry": {"coordinates":[-80.9387893677,44.5742607117],"type":"Point"}
}