{
  "type": "Feature",
  "properties": {
    "addr:full":"1770 Manotick Station Rd Greely ON K4P 1K4",
    "addr:housenumber":"1770",
    "addr:postcode":"k4p 1k4",
    "addr:street":"Manotick Station Rd",
    "iso:country":"CA",
    "sg:address":"1770 Manotick Station Rd",
    "sg:city":"Greely",
    "sg:classifiers":[
        {
            "category":"Manufacturing",
            "subcategory":"Glass & Minerals",
            "type":"Manufacturing & Wholesale Goods"
        }
    ],
    "sg:phone":"+1 613 821 7953",
    "sg:postcode":"K4P 1K4",
    "sg:province":"ON",
    "sg:tags":[
        "concrete",
        "brick",
        "product",
        "block"
    ],
    "wof:name":"K & B Concrete Lawn Ornaments",
    "wof:placetype":"venue"
},
  "geometry": {"coordinates":[-75.60553,45.224422],"type":"Point"}
}