{
  "type": "Feature",
  "properties": {
    "addr:full":"Ottawa ON K1K 4P3",
    "addr:postcode":"k1k 4p3",
    "iso:country":"CA",
    "sg:city":"Ottawa",
    "sg:classifiers":[
        {
            "category":"Real Estate",
            "subcategory":"Real Estate Agent",
            "type":"Services"
        }
    ],
    "sg:phone":"+1 613 745 8553",
    "sg:postcode":"K1K 4P3",
    "sg:province":"ON",
    "sg:tags":[
        "cooperative"
    ],
    "wof:name":"Cooperative Desloges",
    "wof:placetype":"venue"
},
  "geometry": {"coordinates":[-75.62953899999999,45.446423],"type":"Point"}
}