{
  "type": "Feature",
  "properties": {
    "addr:full":"Nepean ON K2H 8T3",
    "addr:postcode":"k2h 8t3",
    "iso:country":"CA",
    "sg:city":"Nepean",
    "sg:classifiers":[
        {
            "category":"Professional",
            "subcategory":"Accounting & Tax Preparation",
            "type":"Services"
        }
    ],
    "sg:phone":"+1 613 726 2021",
    "sg:postcode":"K2H 8T3",
    "sg:province":"ON",
    "sg:tags":[
        "bookkeeping",
        "general"
    ],
    "wof:name":"Kidwai, M A",
    "wof:placetype":"venue"
},
  "geometry": {"coordinates":[-75.7847747803,45.3322944641],"type":"Point"}
}