{
  "type": "Feature",
  "properties": {
    "addr:full":"600 Eighth St New Westminster BC V3M 3S2",
    "addr:housenumber":"600",
    "addr:postcode":"v3m 3s2",
    "addr:street":"Eighth St",
    "iso:country":"CA",
    "sg:address":"600 Eighth St",
    "sg:city":"New Westminster",
    "sg:classifiers":[
        {
            "category":"Recreation",
            "type":"Entertainment"
        }
    ],
    "sg:phone":"+1 604 527 4567",
    "sg:postcode":"V3M 3S2",
    "sg:province":"BC",
    "sg:tags":[
        "provincial",
        "parks",
        "government"
    ],
    "wof:name":"New Westminster Parks & Rec",
    "wof:placetype":"venue"
},
  "geometry": {"coordinates":[-122.924133,49.211189],"type":"Point"}
}