{
  "type": "Feature",
  "properties": {
    "addr:full":"Antigonish NS B2G 2C3",
    "addr:postcode":"b2g 2c3",
    "iso:country":"CA",
    "sg:city":"Antigonish",
    "sg:classifiers":[
        {
            "category":"Personal",
            "subcategory":"Beauty Salon",
            "type":"Services"
        }
    ],
    "sg:phone":"+1 902 863 2288",
    "sg:postcode":"B2G 2C3",
    "sg:province":"NS",
    "wof:name":"Total Hair Care",
    "wof:placetype":"venue"
},
  "geometry": {"coordinates":[-61.993176,45.622383],"type":"Point"}
}