{
  "type": "Feature",
  "properties": {
    "iso:country":"CA",
    "sg:address":"112 Regent Ave E # L1",
    "sg:city":"Winnipeg",
    "sg:classifiers":[
        {
            "category":"Personal",
            "type":"Services"
        }
    ],
    "sg:phone":"+1 204 777 6222",
    "sg:postcode":"R2C 0C1",
    "sg:province":"MB",
    "sg:tags":[
        "therapist",
        "massage"
    ],
    "wof:name":"Aruba Massage Therapy Clinic",
    "wof:placetype":"venue"
},
  "geometry": {"coordinates":[-97.0021286011,49.894859314],"type":"Point"}
}