{
  "type": "Feature",
  "properties": {
    "addr:full":"301 21st Ave E Vancouver BC V5V 1R2",
    "addr:housenumber":"301",
    "addr:postcode":"v5v 1r2",
    "addr:street":"21St Ave E",
    "iso:country":"CA",
    "sg:address":"301 21st Ave E",
    "sg:city":"Vancouver",
    "sg:classifiers":[
        {
            "category":"Building & Trades",
            "subcategory":"Plumbing",
            "type":"Services"
        }
    ],
    "sg:phone":"+1 604 731 4090",
    "sg:postcode":"V5V 1R2",
    "sg:province":"BC",
    "sg:tags":[
        "contractor"
    ],
    "wof:name":"Rockfield Plumbing Svc",
    "wof:placetype":"venue"
},
  "geometry": {"coordinates":[-123.09828899999999,49.252148],"type":"Point"}
}