{
  "type": "Feature",
  "properties": {
    "iso:country":"CA",
    "sg:address":"3 Bardsley Pl",
    "sg:city":"Winnipeg",
    "sg:classifiers":[
        {
            "category":"Wholesale",
            "subcategory":"Farm Supplies",
            "type":"Manufacturing & Wholesale Goods"
        }
    ],
    "sg:phone":"+1 204 987 1700",
    "sg:postcode":"R3P 2B8",
    "sg:province":"MB",
    "sg:tags":[
        "grain",
        "broker"
    ],
    "wof:name":"Morrow Grain CO Ltd",
    "wof:placetype":"venue"
},
  "geometry": {"coordinates":[-97.2273406982,49.8530845642],"type":"Point"}
}