{
  "type": "Feature",
  "properties": {
    "iso:country":"CA",
    "sg:address":"4149 Ch Notre-Dame",
    "sg:city":"Saint-Augustin-DE-Desmaures",
    "sg:classifiers":[
        {
            "category":"Building & Trades",
            "subcategory":"Construction",
            "type":"Services"
        }
    ],
    "sg:phone":"+1 418 875 2891",
    "sg:postcode":"G3A 1W8",
    "sg:province":"QC",
    "sg:tags":[
        "general",
        "contractor"
    ],
    "wof:name":"Fondations Rm",
    "wof:placetype":"venue"
},
  "geometry": {"coordinates":[-71.477013,46.784084],"type":"Point"}
}