{
  "type": "Feature",
  "properties": {
    "addr:full":"67 Carroll St Miramichi NB E1V 6R1",
    "addr:housenumber":"67",
    "addr:postcode":"e1v 6r1",
    "addr:street":"Carroll St",
    "iso:country":"CA",
    "sg:address":"67 Carroll St",
    "sg:city":"Miramichi",
    "sg:classifiers":[
        {
            "category":"Shopping",
            "subcategory":"Clothing, Apparel, & Fashions",
            "type":"Retail Goods"
        }
    ],
    "sg:phone":"+1 506 773 3113",
    "sg:postcode":"E1V 6R1",
    "sg:province":"NB",
    "sg:tags":[
        "shop",
        "bridal",
        "fabric"
    ],
    "wof:name":"Material World",
    "wof:placetype":"venue"
},
  "geometry": {"coordinates":[-65.50473,47.025829],"type":"Point"}
}