{
  "type": "Feature",
  "properties": {
    "addr:full":"58 Northumberland St Toronto ON M6H 1R3",
    "addr:housenumber":"58",
    "addr:postcode":"m6h 1r3",
    "addr:street":"Northumberland St",
    "iso:country":"CA",
    "sg:address":"58 Northumberland St",
    "sg:city":"Toronto",
    "sg:classifiers":[
        {
            "category":"Wholesale",
            "subcategory":"Scrap",
            "type":"Manufacturing & Wholesale Goods"
        }
    ],
    "sg:phone":"+1 416 652 6968",
    "sg:postcode":"M6H 1R3",
    "sg:province":"ON",
    "sg:tags":[
        "recycling",
        "center"
    ],
    "wof:name":"Blue Box Recycling Inc",
    "wof:placetype":"venue"
},
  "geometry": {"coordinates":[-79.429962,43.662308],"type":"Point"}
}