{
  "type": "Feature",
  "properties": {
    "addr:full":"Murray River PE C0A 1W0",
    "addr:postcode":"c0a 1w0",
    "iso:country":"CA",
    "sg:city":"Murray River",
    "sg:classifiers":[
        {
            "category":"Organizations",
            "subcategory":"Professional Association",
            "type":"Services"
        }
    ],
    "sg:phone":"+1 902 964 2152",
    "sg:postcode":"C0A 1W0",
    "sg:province":"PE",
    "wof:name":"Hunter River Lions Club",
    "wof:placetype":"venue"
},
  "geometry": {"coordinates":[-62.6125679016,46.0151405334],"type":"Point"}
}