{
  "type": "Feature",
  "properties": {
    "addr:full":"323 Rue Joseph-Gagne S LA Baie QC G7B 3P6",
    "addr:housenumber":"323",
    "addr:postcode":"g7b 3p6",
    "addr:street":"Rue Joseph-Gagne S La Baie",
    "iso:country":"CA",
    "sg:address":"323 Rue Joseph-Gagne S",
    "sg:city":"LA Baie",
    "sg:classifiers":[
        {
            "category":"Home & Garden",
            "subcategory":"Furniture",
            "type":"Retail Goods"
        }
    ],
    "sg:phone":"+1 418 544 0704",
    "sg:postcode":"G7B 3P6",
    "sg:province":"QC",
    "sg:tags":[
        "equipment",
        "kitchen",
        "cabinet"
    ],
    "wof:name":"Cuisines Option Plus Inc",
    "wof:placetype":"venue"
},
  "geometry": {"coordinates":[-70.899597,48.327335],"type":"Point"}
}