{
  "type": "Feature",
  "properties": {
    "iso:country":"CA",
    "sg:address":"323 Rue Joseph-Gagne S",
    "sg:city":"LA Baie",
    "sg:classifiers":[
        {
            "category":"Home & Garden",
            "subcategory":"Furniture",
            "type":"Retail Goods"
        }
    ],
    "sg:phone":"+1 418 544 0704",
    "sg:postcode":"G7B 3P6",
    "sg:province":"QC",
    "sg:tags":[
        "equipment",
        "kitchen",
        "cabinet"
    ],
    "wof:name":"Cuisines Option Plus Inc",
    "wof:placetype":"venue"
},
  "geometry": {"coordinates":[-70.899597,48.327335],"type":"Point"}
}