{
  "type": "Feature",
  "properties": {
    "addr:full":"1151 Roselawn Ave York ON M6B 1C5",
    "addr:housenumber":"1151",
    "addr:postcode":"m6b 1c5",
    "addr:street":"Roselawn Ave",
    "iso:country":"CA",
    "sg:address":"1151 Roselawn Ave",
    "sg:city":"York",
    "sg:classifiers":[
        {
            "category":"Retail",
            "subcategory":"Auto Repair",
            "type":"Services"
        }
    ],
    "sg:phone":"+1 416 783 2126",
    "sg:postcode":"M6B 1C5",
    "sg:province":"ON",
    "sg:tags":[
        "repairing",
        "automobile"
    ],
    "wof:name":"Peter's Volkswagen Svc",
    "wof:placetype":"venue"
},
  "geometry": {"coordinates":[-79.4526748657,43.6995353699],"type":"Point"}
}