{
  "type": "Feature",
  "properties": {
    "iso:country":"CA",
    "sg:address":"137 Bowes Rd",
    "sg:city":"Concord",
    "sg:classifiers":[
        {
            "category":"Real Estate",
            "subcategory":"Developer",
            "type":"Services"
        }
    ],
    "sg:phone":"+1 905 738 7010",
    "sg:postcode":"L4K 1H3",
    "sg:province":"ON",
    "wof:name":"Zancor Homes",
    "wof:placetype":"venue"
},
  "geometry": {"coordinates":[-79.4918060303,43.805644989],"type":"Point"}
}