{
  "type": "Feature",
  "properties": {
    "iso:country":"CA",
    "sg:address":"221 Boul Sir-Wilfrid-Laurier",
    "sg:city":"Saint-Basile-Le-Grand",
    "sg:classifiers":[
        {
            "category":"Autos & Motor Vehicles",
            "subcategory":"Automobile Sales",
            "type":"Retail Goods"
        }
    ],
    "sg:phone":"+1 450 653 2485",
    "sg:postcode":"J3N 1M2",
    "sg:province":"QC",
    "sg:tags":[
        "car",
        "dealer"
    ],
    "wof:name":"St Bruno Nissan Inc",
    "wof:placetype":"venue"
},
  "geometry": {"coordinates":[-73.29340362550001,45.5277252197],"type":"Point"}
}