{
  "type": "Feature",
  "properties": {
    "addr:full":"686 Rue Saint-Jude N Canton-DE-Granby QC J2G 8C9",
    "addr:housenumber":"686",
    "addr:postcode":"j2g 8c9",
    "addr:street":"Rue Saint-Jude N",
    "iso:country":"CA",
    "sg:address":"686 Rue Saint-Jude N",
    "sg:city":"Canton-DE-Granby",
    "sg:classifiers":[
        {
            "category":"Wholesale",
            "subcategory":"Meat",
            "type":"Manufacturing & Wholesale Goods"
        }
    ],
    "sg:phone":"+1 450 378 2415",
    "sg:postcode":"J2G 8C9",
    "sg:province":"QC",
    "sg:tags":[
        "packer"
    ],
    "wof:name":"Abattoir Lamarche",
    "wof:placetype":"venue"
},
  "geometry": {"coordinates":[-72.7217712402,45.3979949951],"type":"Point"}
}