{
  "type": "Feature",
  "properties": {
    "addr:full":"1915 Carron Dr Bathurst NB E2A 5Z7",
    "addr:housenumber":"1915",
    "addr:postcode":"e2a 5z7",
    "addr:street":"Carron Dr",
    "iso:country":"CA",
    "sg:address":"1915 Carron Dr",
    "sg:city":"Bathurst",
    "sg:classifiers":[
        {
            "category":"Building & Trades",
            "subcategory":"Landscaping Services",
            "type":"Services"
        }
    ],
    "sg:phone":"+1 506 548 3008",
    "sg:postcode":"E2A 5Z7",
    "sg:province":"NB",
    "sg:tags":[
        "landscape",
        "contractor"
    ],
    "wof:name":"Eastside Nursery",
    "wof:placetype":"venue"
},
  "geometry": {"coordinates":[-65.609657,47.634766],"type":"Point"}
}