{
  "type": "Feature",
  "properties": {
    "addr:full":"1292 Barton St E Hamilton ON L8H 2W1",
    "addr:housenumber":"1292",
    "addr:postcode":"l8h 2w1",
    "addr:street":"Barton St E",
    "iso:country":"CA",
    "sg:address":"1292 Barton St E",
    "sg:city":"Hamilton",
    "sg:classifiers":[
        {
            "category":"Travel",
            "subcategory":"Travel Agent",
            "type":"Entertainment"
        }
    ],
    "sg:phone":"+1 905 545 5900",
    "sg:postcode":"L8H 2W1",
    "sg:province":"ON",
    "sg:tags":[
        "agency",
        "bureau"
    ],
    "wof:name":"All Season Travel",
    "wof:placetype":"venue"
},
  "geometry": {"coordinates":[-79.8076019287,43.2493743896],"type":"Point"}
}