{
  "type": "Feature",
  "properties": {
    "addr:full":"160 Main St E Dresden ON N0P 1M0",
    "addr:housenumber":"160",
    "addr:postcode":"n0p 1m0",
    "addr:street":"Main St E",
    "iso:country":"CA",
    "sg:address":"160 Main St E",
    "sg:city":"Dresden",
    "sg:classifiers":[
        {
            "category":"Insurance",
            "subcategory":"Insurance Agent",
            "type":"Services"
        }
    ],
    "sg:phone":"+1 519 683 1743",
    "sg:postcode":"N0P 1M0",
    "sg:province":"ON",
    "wof:name":"Shillington Insurance",
    "wof:placetype":"venue"
},
  "geometry": {"coordinates":[-82.17920700000001,42.590263],"type":"Point"}
}