{
  "type": "Feature",
  "properties": {
    "iso:country":"CA",
    "sg:address":"1310 Rue Begin",
    "sg:city":"Saint-Laurent",
    "sg:classifiers":[
        {
            "category":"Shopping",
            "subcategory":"Computers & Home Electronics",
            "type":"Retail Goods"
        }
    ],
    "sg:phone":"+1 514 336 6875",
    "sg:postcode":"H4R 1X1",
    "sg:province":"QC",
    "sg:tags":[
        "equipment",
        "dealer"
    ],
    "wof:name":"Netmicro Technologies",
    "wof:placetype":"venue"
},
  "geometry": {"coordinates":[-73.7132568359,45.4940795898],"type":"Point"}
}