{
  "type": "Feature",
  "properties": {
    "iso:country":"CA",
    "sg:city":"Calgary",
    "sg:classifiers":[
        {
            "category":"Professional",
            "subcategory":"Business Services",
            "type":"Services"
        }
    ],
    "sg:phone":"+1 403 692 0692",
    "sg:postcode":"T2H 2K6",
    "sg:province":"AB",
    "sg:tags":[
        "information",
        "referral"
    ],
    "wof:name":"Dsis Data Base Storage Ltd",
    "wof:placetype":"venue"
},
  "geometry": {"coordinates":[-114.07189178500001,50.9912185669],"type":"Point"}
}