{
  "type": "Feature",
  "properties": {
    "addr:full":"610 3 Ave S Lethbridge AB T1J 0H5",
    "addr:housenumber":"610",
    "addr:postcode":"t1j 0h5",
    "addr:street":"3 Ave S",
    "iso:country":"CA",
    "sg:address":"610 3 Ave S",
    "sg:city":"Lethbridge",
    "sg:classifiers":[
        {
            "category":"Restaurant",
            "type":"Food & Drink"
        }
    ],
    "sg:phone":"+1 403 327 3552",
    "sg:postcode":"T1J 0H5",
    "sg:province":"AB",
    "wof:name":"Shanghai Chop Suey",
    "wof:placetype":"venue"
},
  "geometry": {"coordinates":[-112.838387,49.695728],"type":"Point"}
}