{
  "type": "Feature",
  "properties": {
    "iso:country":"CA",
    "sg:address":"22 Mockingbird Dr",
    "sg:city":"Elmira",
    "sg:classifiers":[
        {
            "category":"Social Services",
            "subcategory":"Child Care",
            "type":"Services"
        }
    ],
    "sg:phone":"+1 519 669 2609",
    "sg:postcode":"N3B 1H4",
    "sg:province":"ON",
    "wof:name":"Elmira Community Nursery Schl",
    "wof:placetype":"venue"
},
  "geometry": {"coordinates":[-80.571388,43.587124],"type":"Point"}
}