{
  "type": "Feature",
  "properties": {
    "addr:full":"1773 Water St Miramichi NB E1N 1B2",
    "addr:housenumber":"1773",
    "addr:postcode":"e1n 1b2",
    "addr:street":"Water St",
    "iso:country":"CA",
    "sg:address":"1773 Water St",
    "sg:city":"Miramichi",
    "sg:classifiers":[
        {
            "category":"Insurance",
            "subcategory":"Insurance Agent",
            "type":"Services"
        }
    ],
    "sg:phone":"+1 506 773 4489",
    "sg:postcode":"E1N 1B2",
    "sg:province":"NB",
    "wof:name":"Henry Wilson Insurance Ltd",
    "wof:placetype":"venue"
},
  "geometry": {"coordinates":[-65.4698181152,47.0305366516],"type":"Point"}
}