{
  "type": "Feature",
  "properties": {
    "addr:full":"4415 76 Ave NW Edmonton AB T6B 0A3",
    "addr:housenumber":"4415",
    "addr:postcode":"t6b 0a3",
    "addr:street":"76 Ave Nw",
    "iso:country":"CA",
    "sg:address":"4415 76 Ave NW",
    "sg:city":"Edmonton",
    "sg:classifiers":[
        {
            "category":"Wholesale",
            "subcategory":"Scrap",
            "type":"Manufacturing & Wholesale Goods"
        }
    ],
    "sg:phone":"+1 780 465 4730",
    "sg:postcode":"T6B 0A3",
    "sg:province":"AB",
    "sg:tags":[
        "automobile",
        "crushing",
        "parts",
        "supply"
    ],
    "wof:name":"Allwest Auto Parts",
    "wof:placetype":"venue"
},
  "geometry": {"coordinates":[-113.40931701700001,53.5122718811],"type":"Point"}
}