{
  "type": "Feature",
  "properties": {
    "addr:full":"PO Box 181 STN A Prince George BC V2L 4S1",
    "addr:housenumber":"po",
    "addr:postcode":"v2l 4s1",
    "addr:street":"Box 181 Stn A",
    "iso:country":"CA",
    "sg:address":"PO Box 181 STN A",
    "sg:city":"Prince George",
    "sg:classifiers":[
        {
            "category":"Wholesale",
            "subcategory":"Machinery & Supplies",
            "type":"Manufacturing & Wholesale Goods"
        }
    ],
    "sg:phone":"+1 250 613 8853",
    "sg:postcode":"V2L 4S1",
    "sg:province":"BC",
    "sg:tags":[
        "crane",
        "parts"
    ],
    "wof:name":"R & R Hoist Repair Ltd",
    "wof:placetype":"venue"
},
  "geometry": {"coordinates":[-122.74508667000001,53.9123497009],"type":"Point"}
}