{
  "type": "Feature",
  "properties": {
    "addr:full":"6984 Kingsway Burnaby BC V5E 1E6",
    "addr:housenumber":"6984",
    "addr:postcode":"v5e 1e6",
    "addr:street":"Kingsway",
    "iso:country":"CA",
    "sg:address":"6984 Kingsway",
    "sg:city":"Burnaby",
    "sg:classifiers":[
        {
            "category":"Autos & Motor Vehicles",
            "subcategory":"Automobile Sales",
            "type":"Retail Goods"
        }
    ],
    "sg:phone":"+1 604 525 4667",
    "sg:postcode":"V5E 1E6",
    "sg:province":"BC",
    "sg:tags":[
        "car",
        "dealer"
    ],
    "wof:name":"Middlegate Honda",
    "wof:placetype":"venue"
},
  "geometry": {"coordinates":[-122.959648,49.218315],"type":"Point"}
}