{
  "type": "Feature",
  "properties": {
    "addr:full":"245 Mcdermot Ave Winnipeg MB R3B 0S6",
    "addr:housenumber":"245",
    "addr:postcode":"r3b 0s6",
    "addr:street":"Mcdermot Ave",
    "iso:country":"CA",
    "sg:address":"245 Mcdermot Ave",
    "sg:city":"Winnipeg",
    "sg:classifiers":[
        {
            "category":"Recreation",
            "type":"Entertainment"
        }
    ],
    "sg:phone":"+1 204 957 7666",
    "sg:postcode":"R3B 0S6",
    "sg:province":"MB",
    "sg:tags":[
        "boxing",
        "instruction"
    ],
    "wof:name":"Pan am Boxing & Athletic Club",
    "wof:placetype":"venue"
},
  "geometry": {"coordinates":[-97.1409454346,49.8973274231],"type":"Point"}
}