{
  "type": "Feature",
  "properties": {
    "addr:full":"584 Rue Commerciale O RR 1 Chandler QC G0C 1K0",
    "addr:housenumber":"584",
    "addr:postcode":"g0c 1k0",
    "addr:street":"Rue Commerciale;Rr 1",
    "iso:country":"CA",
    "sg:address":"584 Rue Commerciale O RR 1",
    "sg:city":"Chandler",
    "sg:classifiers":[
        {
            "category":"Personal",
            "subcategory":"Beauty Salon",
            "type":"Services"
        }
    ],
    "sg:phone":"+1 418 689 2293",
    "sg:postcode":"G0C 1K0",
    "sg:province":"QC",
    "wof:name":"Salon Sylvie",
    "wof:placetype":"venue"
},
  "geometry": {"coordinates":[-64.68017578120001,48.3490104675],"type":"Point"}
}