{
  "type": "Feature",
  "properties": {
    "iso:country":"CA",
    "sg:address":"14 Wellington St E",
    "sg:city":"Aurora",
    "sg:classifiers":[
        {
            "category":"Food & Beverages",
            "subcategory":"Groceries & Convenience Stores",
            "type":"Retail Goods"
        }
    ],
    "sg:phone":"+1 905 841 9296",
    "sg:postcode":"L4G 1H5",
    "sg:province":"ON",
    "wof:name":"Mac's Convenience Stores Ltd",
    "wof:placetype":"venue"
},
  "geometry": {"coordinates":[-79.466927,43.999924],"type":"Point"}
}