{
  "type": "Feature",
  "properties": {
    "addr:full":"5 Henry St Brockville ON K6V 6M4",
    "addr:housenumber":"5",
    "addr:postcode":"k6v 6m4",
    "addr:street":"Henry St",
    "iso:country":"CA",
    "sg:address":"5 Henry St",
    "sg:city":"Brockville",
    "sg:classifiers":[
        {
            "category":"Museum",
            "type":"Entertainment"
        }
    ],
    "sg:phone":"+1 613 342 4397",
    "sg:postcode":"K6V 6M4",
    "sg:province":"ON",
    "sg:tags":[
        "government"
    ],
    "wof:name":"Brockville Museum",
    "wof:placetype":"venue"
},
  "geometry": {"coordinates":[-75.686752,44.586369],"type":"Point"}
}