{
  "type": "Feature",
  "properties": {
    "addr:full":"North York ON M2R 1Y1",
    "addr:postcode":"m2r 1y1",
    "iso:country":"CA",
    "sg:city":"North York",
    "sg:classifiers":[
        {
            "category":"Cinema",
            "subcategory":"Movie Rental",
            "type":"Entertainment"
        }
    ],
    "sg:phone":"+1 416 225 9663",
    "sg:postcode":"M2R 1Y1",
    "sg:province":"ON",
    "sg:tags":[
        "leasing",
        "video",
        "disc",
        "tape"
    ],
    "wof:name":"Plaza Video 2",
    "wof:placetype":"venue"
},
  "geometry": {"coordinates":[-79.44286346440001,43.7741088867],"type":"Point"}
}