{
  "type": "Feature",
  "properties": {
    "addr:full":"Ste-Marguerite-DE-Dorchester QC G0S 2X0",
    "addr:postcode":"g0s 2x0",
    "iso:country":"CA",
    "sg:city":"Ste-Marguerite-DE-Dorchester",
    "sg:classifiers":[
        {
            "category":"Restaurant",
            "type":"Food & Drink"
        }
    ],
    "sg:phone":"+1 418 935 7030",
    "sg:postcode":"G0S 2X0",
    "sg:province":"QC",
    "wof:name":"Restaurant LA Marguerite Enr",
    "wof:placetype":"venue"
},
  "geometry": {"coordinates":[-70.938683,46.511299],"type":"Point"}
}