{
  "type": "Feature",
  "properties": {
    "addr:full":"210 3rd Ave Assiniboia SK S0H 0B0",
    "addr:housenumber":"210",
    "addr:postcode":"s0h 0b0",
    "addr:street":"3Rd Ave",
    "iso:country":"CA",
    "sg:address":"210 3rd Ave",
    "sg:city":"Assiniboia",
    "sg:classifiers":[
        {
            "category":"Organizations",
            "subcategory":"Professional Association",
            "type":"Services"
        }
    ],
    "sg:phone":"+1 306 642 4200",
    "sg:postcode":"S0H 0B0",
    "sg:province":"SK",
    "sg:tags":[
        "club"
    ],
    "wof:name":"Assiniboia Canadian Legion",
    "wof:placetype":"venue"
},
  "geometry": {"coordinates":[-105.991226,49.631744],"type":"Point"}
}