{
  "type": "Feature",
  "properties": {
    "addr:full":"Vancouver BC V7X 1L3",
    "addr:postcode":"v7x 1l3",
    "iso:country":"CA",
    "sg:city":"Vancouver",
    "sg:classifiers":[
        {
            "category":"Professional",
            "subcategory":"Lawyer & Legal Services",
            "type":"Services"
        }
    ],
    "sg:phone":"+1 604 631 3300",
    "sg:postcode":"V7X 1L3",
    "sg:province":"BC",
    "sg:tags":[
        "attorney"
    ],
    "wof:name":"Lysyk, Joanne R",
    "wof:placetype":"venue"
},
  "geometry": {"coordinates":[-123.119308472,49.2857131958],"type":"Point"}
}