{
  "type": "Feature",
  "properties": {
    "addr:full":"103 Main St S Eston SK S0L 1A0",
    "addr:housenumber":"103",
    "addr:postcode":"s0l 1a0",
    "addr:street":"Main St S Eston",
    "iso:country":"CA",
    "sg:address":"103 Main St S",
    "sg:city":"Eston",
    "sg:classifiers":[
        {
            "category":"Banks & Credit Unions",
            "subcategory":"Bank",
            "type":"Services"
        }
    ],
    "sg:phone":"+1 306 962 3634",
    "sg:postcode":"S0L 1A0",
    "sg:province":"SK",
    "wof:name":"Prairie Centre Credit Union",
    "wof:placetype":"venue"
},
  "geometry": {"coordinates":[-108.753151,51.153767],"type":"Point"}
}