{
  "type": "Feature",
  "properties": {
    "addr:full":"9960 Ch DE LA Cote-DE-Liesse Lachine QC H8T 1A1",
    "addr:postcode":"9960;h8t 1a1",
    "addr:street":"Ch De La Cote-De-Liesse",
    "iso:country":"CA",
    "sg:address":"9960 Ch DE LA Cote-DE-Liesse",
    "sg:city":"Lachine",
    "sg:classifiers":[
        {
            "category":"Wholesale",
            "subcategory":"Drugs",
            "type":"Manufacturing & Wholesale Goods"
        }
    ],
    "sg:phone":"+1 514 636 7660",
    "sg:postcode":"H8T 1A1",
    "sg:province":"QC",
    "sg:tags":[
        "importer"
    ],
    "wof:name":"Masdel Group Inc",
    "wof:placetype":"venue"
},
  "geometry": {"coordinates":[-73.7148971558,45.4678077698],"type":"Point"}
}