{
  "type": "Feature",
  "properties": {
    "addr:full":"20 Rue Saint-Joseph S Alma QC G8B 3E4",
    "addr:housenumber":"20",
    "addr:postcode":"g8b 3e4",
    "addr:street":"Rue Saint-Joseph S",
    "iso:country":"CA",
    "sg:address":"20 Rue Saint-Joseph S",
    "sg:city":"Alma",
    "sg:classifiers":[
        {
            "category":"Organizations",
            "subcategory":"Labor Organization",
            "type":"Services"
        }
    ],
    "sg:phone":"+1 418 662 1081",
    "sg:postcode":"G8B 3E4",
    "sg:province":"QC",
    "wof:name":"Syndicat Des Salaries-Caisses",
    "wof:placetype":"venue"
},
  "geometry": {"coordinates":[-71.6519393921,48.5514221191],"type":"Point"}
}