{
  "type": "Feature",
  "properties": {
    "iso:country":"CA",
    "sg:address":"34 Champlain St",
    "sg:city":"North Bay",
    "sg:classifiers":[
        {
            "category":"Shopping",
            "subcategory":"Computers & Home Electronics",
            "type":"Retail Goods"
        }
    ],
    "sg:phone":"+1 705 472 3111",
    "sg:postcode":"P1B 7M4",
    "sg:province":"ON",
    "sg:tags":[
        "television",
        "radio"
    ],
    "wof:name":"Electronic Playground",
    "wof:placetype":"venue"
},
  "geometry": {"coordinates":[-79.4712142944,46.3332176208],"type":"Point"}
}