{
  "type": "Feature",
  "properties": {
    "addr:full":"46222 Orangehill Rd Gorrie ON N0G 1X0",
    "addr:postcode":"46222;n0g 1x0",
    "addr:street":"Orangehill Rd",
    "iso:country":"CA",
    "sg:address":"46222 Orangehill Rd",
    "sg:city":"Gorrie",
    "sg:classifiers":[
        {
            "category":"Building & Trades",
            "subcategory":"Construction",
            "type":"Services"
        }
    ],
    "sg:phone":"+1 519 335 6696",
    "sg:postcode":"N0G 1X0",
    "sg:province":"ON",
    "sg:tags":[
        "general",
        "contractor"
    ],
    "wof:name":"Triple F Construction",
    "wof:placetype":"venue"
},
  "geometry": {"coordinates":[-81.10972599999999,43.872761],"type":"Point"}
}