{
  "type": "Feature",
  "properties": {
    "addr:full":"Brampton ON L6T 5H9",
    "addr:postcode":"l6t 5h9",
    "iso:country":"CA",
    "sg:city":"Brampton",
    "sg:classifiers":[
        {
            "category":"Restaurant",
            "type":"Food & Drink"
        }
    ],
    "sg:phone":"+1 905 793 3476",
    "sg:postcode":"L6T 5H9",
    "sg:province":"ON",
    "wof:name":"Speranza Ristorante",
    "wof:placetype":"venue"
},
  "geometry": {"coordinates":[-79.67813110349999,43.7501487732],"type":"Point"}
}