{
  "type": "Feature",
  "properties": {
    "iso:country":"CA",
    "sg:address":"1417 Rue Amherst",
    "sg:city":"Montreal",
    "sg:classifiers":[
        {
            "category":"Food & Beverages",
            "subcategory":"Specialty",
            "type":"Retail Goods"
        }
    ],
    "sg:phone":"+1 514 527 2970",
    "sg:postcode":"H2L 3L2",
    "sg:province":"QC",
    "sg:tags":[
        "sporting"
    ],
    "wof:name":"Boutique Fitness Shop",
    "wof:placetype":"venue"
},
  "geometry": {"coordinates":[-73.557289,45.517742],"type":"Point"}
}