{
  "type": "Feature",
  "properties": {
    "addr:full":"Mont-Saint-Hilaire QC J3H 5V3",
    "addr:postcode":"j3h 5v3",
    "iso:country":"CA",
    "sg:city":"Mont-Saint-Hilaire",
    "sg:classifiers":[
        {
            "category":"Education",
            "subcategory":"School",
            "type":"Public Place"
        }
    ],
    "sg:phone":"+1 450 464 2886",
    "sg:postcode":"J3H 5V3",
    "sg:province":"QC",
    "sg:tags":[
        "instruction",
        "driving"
    ],
    "wof:name":"Ecole DE Conduite St-Amour",
    "wof:placetype":"venue"
},
  "geometry": {"coordinates":[-73.18483000000001,45.564388],"type":"Point"}
}