{
  "type": "Feature",
  "properties": {
    "addr:full":"111 Larch St Sudbury ON P3E 4T5",
    "addr:housenumber":"111",
    "addr:postcode":"p3e 4t5",
    "addr:street":"Larch St",
    "iso:country":"CA",
    "sg:address":"111 Larch St",
    "sg:city":"Sudbury",
    "sg:classifiers":[
        {
            "category":"Personal",
            "subcategory":"Barber",
            "type":"Services"
        }
    ],
    "sg:phone":"+1 705 674 9503",
    "sg:postcode":"P3E 4T5",
    "sg:province":"ON",
    "wof:name":"Nickel Range Barber Shop",
    "wof:placetype":"venue"
},
  "geometry": {"coordinates":[-80.992554,46.491165],"type":"Point"}
}