{
  "type": "Feature",
  "properties": {
    "addr:full":"Alberton PE C0B 1B0",
    "addr:postcode":"c0b 1b0",
    "iso:country":"CA",
    "sg:city":"Alberton",
    "sg:classifiers":[
        {
            "category":"Building & Trades",
            "subcategory":"Construction",
            "type":"Services"
        }
    ],
    "sg:phone":"+1 902 853 2559",
    "sg:postcode":"C0B 1B0",
    "sg:province":"PE",
    "sg:tags":[
        "excavating",
        "contractor"
    ],
    "wof:name":"O'Meara's Heavy Equipment Ltd",
    "wof:placetype":"venue"
},
  "geometry": {"coordinates":[-64.072594,46.816017],"type":"Point"}
}