{
  "type": "Feature",
  "properties": {
    "addr:full":"1506 9 Ave S Lethbridge AB T1J 1V8",
    "addr:housenumber":"1506",
    "addr:postcode":"t1j 1v8",
    "addr:street":"9 Ave S",
    "iso:country":"CA",
    "sg:address":"1506 9 Ave S",
    "sg:city":"Lethbridge",
    "sg:classifiers":[
        {
            "category":"Shopping",
            "subcategory":"Pharmacy",
            "type":"Retail Goods"
        }
    ],
    "sg:phone":"+1 403 328 5512",
    "sg:postcode":"T1J 1V8",
    "sg:province":"AB",
    "wof:name":"Stubbs Pharmacy",
    "wof:placetype":"venue"
},
  "geometry": {"coordinates":[-112.82070899999999,49.686455],"type":"Point"}
}