{
  "type": "Feature",
  "properties": {
    "addr:full":"275 Saunders Rd Barrie ON L4N 9A3",
    "addr:housenumber":"275",
    "addr:postcode":"l4n 9a3",
    "addr:street":"Saunders Rd",
    "iso:country":"CA",
    "sg:address":"275 Saunders Rd",
    "sg:city":"Barrie",
    "sg:classifiers":[
        {
            "category":"Home & Garden",
            "subcategory":"Building Materials",
            "type":"Retail Goods"
        }
    ],
    "sg:phone":"+1 705 734 3600",
    "sg:postcode":"L4N 9A3",
    "sg:province":"ON",
    "sg:tags":[
        "mixed",
        "concrete"
    ],
    "wof:name":"Lafarge Canada Inc",
    "wof:placetype":"venue"
},
  "geometry": {"coordinates":[-79.66790008540001,44.3342475891],"type":"Point"}
}