{
  "type": "Feature",
  "properties": {
    "iso:country":"CA",
    "sg:address":"9825 158 St NW",
    "sg:city":"Edmonton",
    "sg:classifiers":[
        {
            "category":"Organizations",
            "subcategory":"Religious Organization",
            "type":"Services"
        }
    ],
    "sg:phone":"+1 780 483 6476",
    "sg:postcode":"T5P 2X4",
    "sg:province":"AB",
    "sg:tags":[
        "school",
        "church"
    ],
    "wof:name":"Meadowlark Christian School",
    "wof:placetype":"venue"
},
  "geometry": {"coordinates":[-113.593589783,53.536567688],"type":"Point"}
}