{
  "type": "Feature",
  "properties": {
    "addr:full":"12863 52 St NW Edmonton AB T5A 3P8",
    "addr:housenumber":"12863",
    "addr:postcode":"t5a 3p8",
    "addr:street":"52 St Nw",
    "iso:country":"CA",
    "sg:address":"12863 52 St NW",
    "sg:city":"Edmonton",
    "sg:classifiers":[
        {
            "category":"Retail",
            "subcategory":"Car Wash",
            "type":"Services"
        }
    ],
    "sg:phone":"+1 780 476 4766",
    "sg:postcode":"T5A 3P8",
    "sg:province":"AB",
    "sg:tags":[
        "automobile",
        "truck",
        "detail",
        "accessory"
    ],
    "wof:name":"Brima Services Inc",
    "wof:placetype":"venue"
},
  "geometry": {"coordinates":[-113.421227,53.586979],"type":"Point"}
}