{
  "type": "Feature",
  "properties": {
    "iso:country":"CA",
    "sg:address":"288 Mary St",
    "sg:city":"Orillia",
    "sg:classifiers":[
        {
            "category":"Wholesale",
            "subcategory":"Non-durable Goods",
            "type":"Manufacturing & Wholesale Goods"
        }
    ],
    "sg:phone":"+1 705 325 7919",
    "sg:postcode":"L3V 3E7",
    "sg:province":"ON",
    "wof:name":"Chapman & Robins Photographic",
    "wof:placetype":"venue"
},
  "geometry": {"coordinates":[-79.431930542,44.6045036316],"type":"Point"}
}