{
  "type": "Feature",
  "properties": {
    "addr:full":"30 Rue Des Grands-Lacs Saint-Augustin-DE-Desmaures QC G3A 2E6",
    "addr:housenumber":"30",
    "addr:postcode":"g3a 2e6",
    "addr:street":"Rue Des Grands-Lacs",
    "iso:country":"CA",
    "sg:address":"30 Rue Des Grands-Lacs",
    "sg:city":"Saint-Augustin-DE-Desmaures",
    "sg:classifiers":[
        {
            "category":"Manufacturing",
            "subcategory":"Apparel",
            "type":"Manufacturing & Wholesale Goods"
        }
    ],
    "sg:phone":"+1 418 878 4135",
    "sg:postcode":"G3A 2E6",
    "sg:province":"QC",
    "sg:tags":[
        "clothing"
    ],
    "wof:name":"Louis Garneau Sports Inc",
    "wof:placetype":"venue"
},
  "geometry": {"coordinates":[-71.4450378418,46.7481193542],"type":"Point"}
}