{
  "type": "Feature",
  "properties": {
    "addr:full":"4533 Notre Dame Ave Hanmer ON P3P 1X5",
    "addr:housenumber":"4533",
    "addr:postcode":"p3p 1x5",
    "addr:street":"Notre Dame Ave",
    "iso:country":"CA",
    "sg:address":"4533 Notre Dame Ave",
    "sg:city":"Hanmer",
    "sg:classifiers":[
        {
            "category":"Restaurant",
            "type":"Food & Drink"
        }
    ],
    "sg:phone":"+1 705 969 2397",
    "sg:postcode":"P3P 1X5",
    "sg:province":"ON",
    "sg:tags":[
        "sandwich"
    ],
    "wof:name":"Suzanne's Sub Shop",
    "wof:placetype":"venue"
},
  "geometry": {"coordinates":[-80.944984436,46.6521987915],"type":"Point"}
}