{
  "type": "Feature",
  "properties": {
    "addr:full":"182 King St Stratford ON N5A 4S1",
    "addr:housenumber":"182",
    "addr:postcode":"n5a 4s1",
    "addr:street":"King St",
    "iso:country":"CA",
    "sg:address":"182 King St",
    "sg:city":"Stratford",
    "sg:classifiers":[
        {
            "category":"Manufacturing",
            "subcategory":"Tools & Machinery",
            "type":"Manufacturing & Wholesale Goods"
        }
    ],
    "sg:phone":"+1 519 273 6921",
    "sg:postcode":"N5A 4S1",
    "sg:province":"ON",
    "sg:tags":[
        "machine",
        "shop"
    ],
    "wof:name":"Integrated Mechanical Svc",
    "wof:placetype":"venue"
},
  "geometry": {"coordinates":[-80.96686553959999,43.3683128357],"type":"Point"}
}