{
  "type": "Feature",
  "properties": {
    "addr:full":"Daysland AB T0B 1A0",
    "addr:postcode":"t0b 1a0",
    "iso:country":"CA",
    "sg:city":"Daysland",
    "sg:classifiers":[
        {
            "category":"Mining & Drilling",
            "type":"Manufacturing & Wholesale Goods"
        }
    ],
    "sg:phone":"+1 780 374 2145",
    "sg:postcode":"T0B 1A0",
    "sg:province":"AB",
    "sg:tags":[
        "field",
        "oil"
    ],
    "wof:name":"Rangeland Oil & Gasfield Svc",
    "wof:placetype":"venue"
},
  "geometry": {"coordinates":[-112.261589,52.8633],"type":"Point"}
}