{
  "type": "Feature",
  "properties": {
    "addr:full":"4540 26 Ave SW Calgary AB T3E 0R1",
    "addr:housenumber":"4540",
    "addr:postcode":"t3e 0r1",
    "addr:street":"26 Ave Sw",
    "iso:country":"CA",
    "sg:address":"4540 26 Ave SW",
    "sg:city":"Calgary",
    "sg:classifiers":[
        {
            "category":"Education",
            "subcategory":"School",
            "type":"Public Place"
        }
    ],
    "sg:phone":"+1 403 249 0437",
    "sg:postcode":"T3E 0R1",
    "sg:province":"AB",
    "wof:name":"St Thomas Aquinas Elem School",
    "wof:placetype":"venue"
},
  "geometry": {"coordinates":[-114.151596,51.030609],"type":"Point"}
}