{
  "type": "Feature",
  "properties": {
    "addr:full":"15 Commercial St Milton ON L9T 2H6",
    "addr:housenumber":"15",
    "addr:postcode":"l9t 2h6",
    "addr:street":"Commercial St",
    "iso:country":"CA",
    "sg:address":"15 Commercial St",
    "sg:city":"Milton",
    "sg:classifiers":[
        {
            "category":"Retail",
            "subcategory":"Car Wash",
            "type":"Services"
        }
    ],
    "sg:phone":"+1 905 875 4573",
    "sg:postcode":"L9T 2H6",
    "sg:province":"ON",
    "sg:tags":[
        "polishing",
        "washing"
    ],
    "wof:name":"Main Street Wash Works Inc",
    "wof:placetype":"venue"
},
  "geometry": {"coordinates":[-79.881226,43.514214],"type":"Point"}
}