{
  "type": "Feature",
  "properties": {
    "iso:country":"CA",
    "sg:address":"1471 Rue Sainte-Catherine E",
    "sg:city":"Montreal",
    "sg:classifiers":[
        {
            "category":"Social Services",
            "type":"Services"
        }
    ],
    "sg:phone":"+1 514 522 7156",
    "sg:postcode":"H2L 2H9",
    "sg:province":"QC",
    "sg:tags":[
        "organization",
        "welfare"
    ],
    "wof:name":"Cafe Chretien Centre-Sud",
    "wof:placetype":"venue"
},
  "geometry": {"coordinates":[-73.55407,45.520817],"type":"Point"}
}