{
  "type": "Feature",
  "properties": {
    "addr:full":"5695 176 St Surrey BC V3S 4C5",
    "addr:housenumber":"5695",
    "addr:postcode":"v3s 4c5",
    "addr:street":"176 St",
    "iso:country":"CA",
    "sg:address":"5695 176 St",
    "sg:city":"Surrey",
    "sg:classifiers":[
        {
            "category":"Restaurant",
            "type":"Food & Drink"
        }
    ],
    "sg:phone":"+1 604 576 6512",
    "sg:postcode":"V3S 4C5",
    "sg:province":"BC",
    "wof:name":"Ken's Cafe",
    "wof:placetype":"venue"
},
  "geometry": {"coordinates":[-122.734909,49.10397],"type":"Point"}
}