{
  "type": "Feature",
  "properties": {
    "addr:full":"254 Ritson Rd S Oshawa ON L1H 5J1",
    "addr:housenumber":"254",
    "addr:postcode":"l1h 5j1",
    "addr:street":"Ritson Rd",
    "iso:country":"CA",
    "sg:address":"254 Ritson Rd S",
    "sg:city":"Oshawa",
    "sg:classifiers":[
        {
            "category":"Building & Trades",
            "subcategory":"Construction",
            "type":"Services"
        }
    ],
    "sg:phone":"+1 905 432 1366",
    "sg:postcode":"L1H 5J1",
    "sg:province":"ON",
    "sg:tags":[
        "excavating",
        "breaking",
        "contractor",
        "concrete",
        "cutting",
        "sawing"
    ],
    "wof:name":"Merrill Barnes Excavating",
    "wof:placetype":"venue"
},
  "geometry": {"coordinates":[-78.850899,43.89315],"type":"Point"}
}