{
  "type": "Feature",
  "properties": {
    "addr:full":"1 Rue Georges Pierreville QC J0G 1J0",
    "addr:housenumber":"1",
    "addr:postcode":"j0g 1j0",
    "addr:street":"Rue Georges",
    "iso:country":"CA",
    "sg:address":"1 Rue Georges",
    "sg:city":"Pierreville",
    "sg:classifiers":[
        {
            "category":"Travel",
            "subcategory":"Hotels & Motels",
            "type":"Entertainment"
        }
    ],
    "sg:phone":"+1 450 568 2140",
    "sg:postcode":"J0G 1J0",
    "sg:province":"QC",
    "wof:name":"Hotel Traversy",
    "wof:placetype":"venue"
},
  "geometry": {"coordinates":[-72.811707,46.070831],"type":"Point"}
}