{
  "type": "Feature",
  "properties": {
    "iso:country":"CA",
    "sg:address":"2815 12 St NE",
    "sg:city":"Calgary",
    "sg:classifiers":[
        {
            "category":"Manufacturing",
            "subcategory":"Printing",
            "type":"Manufacturing & Wholesale Goods"
        }
    ],
    "sg:phone":"+1 403 250 9022",
    "sg:postcode":"T2E 7J2",
    "sg:province":"AB",
    "sg:tags":[
        "printer"
    ],
    "wof:name":"Style-Craft Printing Ltd",
    "wof:placetype":"venue"
},
  "geometry": {"coordinates":[-114.02560424799999,51.0772781372],"type":"Point"}
}