{
  "type": "Feature",
  "properties": {
    "addr:full":"26985 116 Ave Maple Ridge BC V2W 1N1",
    "addr:housenumber":"26985",
    "addr:postcode":"v2w 1n1",
    "addr:street":"116 Ave",
    "iso:country":"CA",
    "sg:address":"26985 116 Ave",
    "sg:city":"Maple Ridge",
    "sg:classifiers":[
        {
            "category":"Professional",
            "subcategory":"Computer Services",
            "type":"Services"
        }
    ],
    "sg:phone":"+1 604 462 1105",
    "sg:postcode":"V2W 1N1",
    "sg:province":"BC",
    "sg:tags":[
        "consultant"
    ],
    "wof:name":"Afcom Computer Svc",
    "wof:placetype":"venue"
},
  "geometry": {"coordinates":[-122.473312378,49.21301651],"type":"Point"}
}