{
  "type": "Feature",
  "properties": {
    "addr:full":"168 St Andrew St W Fergus ON N1M 1N5",
    "addr:housenumber":"168",
    "addr:postcode":"n1m 1n5",
    "addr:street":"St Andrew St W",
    "iso:country":"CA",
    "sg:address":"168 St Andrew St W",
    "sg:city":"Fergus",
    "sg:classifiers":[
        {
            "category":"Personal",
            "subcategory":"Beauty Salon",
            "type":"Services"
        }
    ],
    "sg:phone":"+1 519 843 4103",
    "sg:postcode":"N1M 1N5",
    "sg:province":"ON",
    "sg:tags":[
        "manicuring"
    ],
    "wof:name":"Professional Nail",
    "wof:placetype":"venue"
},
  "geometry": {"coordinates":[-80.3782501221,43.7051010132],"type":"Point"}
}