{
  "type": "Feature",
  "properties": {
    "iso:country":"CA",
    "sg:address":"10333 34 Ave NW",
    "sg:city":"Edmonton",
    "sg:classifiers":[
        {
            "category":"Restaurant",
            "type":"Food & Drink"
        }
    ],
    "sg:phone":"+1 780 430 0606",
    "sg:postcode":"T6J 6V1",
    "sg:province":"AB",
    "wof:name":"Chili's Texas Grill",
    "wof:placetype":"venue"
},
  "geometry": {"coordinates":[-113.49432373,53.4675483704],"type":"Point"}
}