{
  "type": "Feature",
  "properties": {
    "addr:full":"154 Main St E North Bay ON P1B 1A8",
    "addr:housenumber":"154",
    "addr:postcode":"p1b 1a8",
    "addr:street":"Main St E",
    "iso:country":"CA",
    "sg:address":"154 Main St E",
    "sg:city":"North Bay",
    "sg:classifiers":[
        {
            "category":"Banks & Credit Unions",
            "subcategory":"Investment Brokerage",
            "type":"Services"
        }
    ],
    "sg:phone":"+1 705 494 9850",
    "sg:postcode":"P1B 1A8",
    "sg:province":"ON",
    "wof:name":"Bmo Nesbitt Burns",
    "wof:placetype":"venue"
},
  "geometry": {"coordinates":[-79.4632492065,46.3097496033],"type":"Point"}
}