{
  "type": "Feature",
  "properties": {
    "addr:full":"80 Keewatin St Winnipeg MB R3E 3C5",
    "addr:housenumber":"80",
    "addr:postcode":"r3e 3c5",
    "addr:street":"Keewatin St",
    "iso:country":"CA",
    "sg:address":"80 Keewatin St",
    "sg:city":"Winnipeg",
    "sg:classifiers":[
        {
            "category":"Autos & Motor Vehicles",
            "subcategory":"Fuel & Gas Station",
            "type":"Retail Goods"
        }
    ],
    "sg:phone":"+1 204 694 5018",
    "sg:postcode":"R3E 3C5",
    "sg:province":"MB",
    "sg:tags":[
        "oil"
    ],
    "wof:name":"Mohawk Keewatin",
    "wof:placetype":"venue"
},
  "geometry": {"coordinates":[-97.195396,49.920212],"type":"Point"}
}