{
  "type": "Feature",
  "properties": {
    "addr:full":"Windsor ON N9A 6V2",
    "addr:postcode":"n9a 6v2",
    "iso:country":"CA",
    "sg:city":"Windsor",
    "sg:classifiers":[
        {
            "category":"Government",
            "subcategory":"Office",
            "type":"Public Place"
        }
    ],
    "sg:phone":"+1 519 255 6555",
    "sg:postcode":"N9A 6V2",
    "sg:province":"ON",
    "sg:tags":[
        "village"
    ],
    "wof:name":"Provincial Offences Office",
    "wof:placetype":"venue"
},
  "geometry": {"coordinates":[-83.037476,42.318295],"type":"Point"}
}