{
  "type": "Feature",
  "properties": {
    "addr:full":"18177 County Rd 2 Cornwall ON K6H 5R5",
    "addr:housenumber":"18177",
    "addr:postcode":"k6h 5r5",
    "addr:street":"County Rd 2",
    "iso:country":"CA",
    "sg:address":"18177 County Rd 2",
    "sg:city":"Cornwall",
    "sg:classifiers":[
        {
            "category":"Travel",
            "subcategory":"Hotels & Motels",
            "type":"Entertainment"
        }
    ],
    "sg:phone":"+1 613 931 2508",
    "sg:postcode":"K6H 5R5",
    "sg:province":"ON",
    "sg:tags":[
        "breakfast",
        "accommodation",
        "bed"
    ],
    "wof:name":"Lighthouse Landing B & B",
    "wof:placetype":"venue"
},
  "geometry": {"coordinates":[-74.73569488530001,45.0284347534],"type":"Point"}
}