{
  "type": "Feature",
  "properties": {
    "addr:full":"Banff AB T1L 1B9",
    "addr:postcode":"t1l 1b9",
    "iso:country":"CA",
    "sg:city":"Banff",
    "sg:classifiers":[
        {
            "category":"Manufacturing",
            "subcategory":"Printing",
            "type":"Manufacturing & Wholesale Goods"
        }
    ],
    "sg:phone":"+1 403 762 4477",
    "sg:postcode":"T1L 1B9",
    "sg:province":"AB",
    "sg:tags":[
        "printer"
    ],
    "wof:name":"Unicom Graphics of Banff",
    "wof:placetype":"venue"
},
  "geometry": {"coordinates":[-115.572624206,51.1768226624],"type":"Point"}
}