{
  "type": "Feature",
  "properties": {
    "addr:full":"450 Rue Dugas Laval QC H7X 3T6",
    "addr:housenumber":"450",
    "addr:postcode":"h7x 3t6",
    "addr:street":"Rue Dugas",
    "iso:country":"CA",
    "sg:address":"450 Rue Dugas",
    "sg:city":"Laval",
    "sg:classifiers":[
        {
            "category":"Local Transit",
            "type":"Transportation"
        }
    ],
    "sg:phone":"+1 514 727 4222",
    "sg:postcode":"H7X 3T6",
    "sg:province":"QC",
    "sg:tags":[
        "limousine"
    ],
    "wof:name":"Limousine Marano",
    "wof:placetype":"venue"
},
  "geometry": {"coordinates":[-73.8014831543,45.5328521729],"type":"Point"}
}