{
  "type": "Feature",
  "properties": {
    "addr:full":"2050 Boul Dagenais O Laval QC H7L 5W2",
    "addr:housenumber":"2050",
    "addr:postcode":"h7l 5w2",
    "addr:street":"Boul Dagenais O",
    "iso:country":"CA",
    "sg:address":"2050 Boul Dagenais O",
    "sg:city":"Laval",
    "sg:classifiers":[
        {
            "category":"Manufacturing",
            "subcategory":"Metals",
            "type":"Manufacturing & Wholesale Goods"
        }
    ],
    "sg:phone":"+1 450 622 8775",
    "sg:postcode":"H7L 5W2",
    "sg:province":"QC",
    "sg:tags":[
        "valve"
    ],
    "wof:name":"Orbe Canada Inc",
    "wof:placetype":"venue"
},
  "geometry": {"coordinates":[-73.76592254640001,45.5880889893],"type":"Point"}
}