{
  "type": "Feature",
  "properties": {
    "addr:full":"3207 Ch Sainte-Foy Sainte-Foy QC G1X 1R3",
    "addr:housenumber":"3207",
    "addr:postcode":"g1x 1r3",
    "addr:street":"Ch Sainte-Foy",
    "iso:country":"CA",
    "sg:address":"3207 Ch Sainte-Foy",
    "sg:city":"Sainte-Foy",
    "sg:classifiers":[
        {
            "category":"Shopping",
            "subcategory":"Pharmacy",
            "type":"Retail Goods"
        }
    ],
    "sg:phone":"+1 418 651 3230",
    "sg:postcode":"G1X 1R3",
    "sg:province":"QC",
    "wof:name":"Delage & Simpson Inc",
    "wof:placetype":"venue"
},
  "geometry": {"coordinates":[-71.291763,46.769211],"type":"Point"}
}