{
  "type": "Feature",
  "properties": {
    "addr:full":"Calgary AB T2H 1J4",
    "addr:postcode":"t2h 1j4",
    "iso:country":"CA",
    "sg:city":"Calgary",
    "sg:classifiers":[
        {
            "category":"Retail",
            "subcategory":"Auto Repair",
            "type":"Services"
        }
    ],
    "sg:phone":"+1 403 255 7818",
    "sg:postcode":"T2H 1J4",
    "sg:province":"AB",
    "sg:tags":[
        "body",
        "automobile",
        "painting"
    ],
    "wof:name":"K & L Auto Body Ltd",
    "wof:placetype":"venue"
},
  "geometry": {"coordinates":[-114.059799,50.996281],"type":"Point"}
}