{
  "type": "Feature",
  "properties": {
    "addr:full":"102 Main St Watrous SK S0K 4T0",
    "addr:housenumber":"102",
    "addr:postcode":"s0k 4t0",
    "addr:street":"Main St",
    "iso:country":"CA",
    "sg:address":"102 Main St",
    "sg:city":"Watrous",
    "sg:classifiers":[
        {
            "category":"Travel",
            "subcategory":"Hotels & Motels",
            "type":"Entertainment"
        }
    ],
    "sg:phone":"+1 306 946 3315",
    "sg:postcode":"S0K 4T0",
    "sg:province":"SK",
    "wof:name":"Manitou Hotel",
    "wof:placetype":"venue"
},
  "geometry": {"coordinates":[-105.46871899999999,51.672066],"type":"Point"}
}