{
  "type": "Feature",
  "properties": {
    "addr:full":"Valleyview AB T0H 3N0",
    "addr:postcode":"t0h 3n0",
    "iso:country":"CA",
    "sg:city":"Valleyview",
    "sg:classifiers":[
        {
            "category":"Manufacturing",
            "subcategory":"Lumber",
            "type":"Manufacturing & Wholesale Goods"
        }
    ],
    "sg:phone":"+1 780 524 5022",
    "sg:postcode":"T0H 3N0",
    "sg:province":"AB",
    "sg:tags":[
        "company",
        "logging"
    ],
    "wof:name":"Big D Contracting Ltd",
    "wof:placetype":"venue"
},
  "geometry": {"coordinates":[-117.272797,55.068619],"type":"Point"}
}