{
  "type": "Feature",
  "properties": {
    "iso:country":"CA",
    "sg:city":"Montreal",
    "sg:classifiers":[
        {
            "category":"Professional",
            "subcategory":"Testing Lab",
            "type":"Services"
        }
    ],
    "sg:phone":"+1 514 284 6085",
    "sg:postcode":"H2Y 1L5",
    "sg:province":"QC",
    "sg:tags":[
        "inspection",
        "infrared"
    ],
    "wof:name":"Groupe Conseil Gie Inc",
    "wof:placetype":"venue"
},
  "geometry": {"coordinates":[-73.556831,45.50565],"type":"Point"}
}