{
  "type": "Feature",
  "properties": {
    "iso:country":"CA",
    "sg:address":"54 Wilson St W",
    "sg:city":"Ancaster",
    "sg:classifiers":[
        {
            "category":"Personal",
            "subcategory":"Beauty Salon",
            "type":"Services"
        }
    ],
    "sg:phone":"+1 905 648 0896",
    "sg:postcode":"L9G 3T8",
    "sg:province":"ON",
    "wof:name":"Haircrafters",
    "wof:placetype":"venue"
},
  "geometry": {"coordinates":[-79.9893112183,43.2163238525],"type":"Point"}
}