{
  "type": "Feature",
  "properties": {
    "addr:full":"104 Rue Saint-Germain O Rimouski QC G5L 4B5",
    "addr:housenumber":"104",
    "addr:postcode":"g5l 4b5",
    "addr:street":"Rue Saint-Germain O",
    "iso:country":"CA",
    "sg:address":"104 Rue Saint-Germain O",
    "sg:city":"Rimouski",
    "sg:classifiers":[
        {
            "category":"Shopping",
            "subcategory":"Clothing, Apparel, & Fashions",
            "type":"Retail Goods"
        }
    ],
    "sg:phone":"+1 418 722 9495",
    "sg:postcode":"G5L 4B5",
    "sg:province":"QC",
    "sg:tags":[
        "leather"
    ],
    "wof:name":"Tendance",
    "wof:placetype":"venue"
},
  "geometry": {"coordinates":[-68.52369689939999,48.4530487061],"type":"Point"}
}