{
  "type": "Feature",
  "properties": {
    "addr:full":"716 Railway Ave Rosthern SK S0K 3R0",
    "addr:housenumber":"716",
    "addr:postcode":"s0k 3r0",
    "addr:street":"Railway Ave",
    "iso:country":"CA",
    "sg:address":"716 Railway Ave",
    "sg:city":"Rosthern",
    "sg:classifiers":[
        {
            "category":"Health Services",
            "subcategory":"Optometrist",
            "type":"Services"
        }
    ],
    "sg:phone":"+1 306 232 5483",
    "sg:postcode":"S0K 3R0",
    "sg:province":"SK",
    "wof:name":"Krueger, James A OD",
    "wof:placetype":"venue"
},
  "geometry": {"coordinates":[-106.331695557,52.6577529907],"type":"Point"}
}