{
  "type": "Feature",
  "properties": {
    "addr:full":"Oka QC J0N 1E0",
    "addr:postcode":"j0n 1e0",
    "iso:country":"CA",
    "sg:city":"Oka",
    "sg:classifiers":[
        {
            "category":"Personal",
            "subcategory":"Beauty Salon",
            "type":"Services"
        }
    ],
    "sg:phone":"+1 450 479 6138",
    "sg:postcode":"J0N 1E0",
    "sg:province":"QC",
    "wof:name":"Chan Coiffure Elle & Lui",
    "wof:placetype":"venue"
},
  "geometry": {"coordinates":[-74.084045,45.4627],"type":"Point"}
}