{
  "type": "Feature",
  "properties": {
    "addr:full":"32 Rt 13 Crapaud PE C0A 1J0",
    "addr:housenumber":"32",
    "addr:postcode":"c0a 1j0",
    "addr:street":"Rt 13",
    "iso:country":"CA",
    "sg:address":"32 Rt 13",
    "sg:city":"Crapaud",
    "sg:classifiers":[
        {
            "category":"Retail",
            "subcategory":"Funeral Services",
            "type":"Services"
        }
    ],
    "sg:phone":"+1 902 658 2992",
    "sg:postcode":"C0A 1J0",
    "sg:province":"PE",
    "sg:tags":[
        "director"
    ],
    "wof:name":"Dawson's Funeral Home",
    "wof:placetype":"venue"
},
  "geometry": {"coordinates":[-63.500244,46.239925],"type":"Point"}
}