{
  "type": "Feature",
  "properties": {
    "addr:full":"1231 Weston Rd York ON M6M 4P7",
    "addr:housenumber":"1231",
    "addr:postcode":"m6m 4p7",
    "addr:street":"Weston Rd",
    "iso:country":"CA",
    "sg:address":"1231 Weston Rd",
    "sg:city":"York",
    "sg:classifiers":[
        {
            "category":"Professional",
            "subcategory":"Business Services",
            "type":"Services"
        }
    ],
    "sg:phone":"+1 416 243 0401",
    "sg:postcode":"M6M 4P7",
    "sg:province":"ON",
    "sg:tags":[
        "auctioneer"
    ],
    "wof:name":"A & A Auctioneers",
    "wof:placetype":"venue"
},
  "geometry": {"coordinates":[-79.49276,43.688313],"type":"Point"}
}