{
  "type": "Feature",
  "properties": {
    "addr:full":"32 Grand Ave S Cambridge ON N1S 2L6",
    "addr:housenumber":"32",
    "addr:postcode":"n1s 2l6",
    "addr:street":"Grand Ave S",
    "iso:country":"CA",
    "sg:address":"32 Grand Ave S",
    "sg:city":"Cambridge",
    "sg:classifiers":[
        {
            "category":"Banks & Credit Unions",
            "subcategory":"Investment Brokerage",
            "type":"Services"
        }
    ],
    "sg:phone":"+1 519 622 7526",
    "sg:postcode":"N1S 2L6",
    "sg:province":"ON",
    "sg:tags":[
        "consultant",
        "planning",
        "financial"
    ],
    "wof:name":"Reid & Assoc Financial Svc Inc",
    "wof:placetype":"venue"
},
  "geometry": {"coordinates":[-80.317673,43.357071],"type":"Point"}
}