{
  "type": "Feature",
  "properties": {
    "addr:full":"PO Box 5459 STN Main Drayton Valley AB T7A 1R5",
    "addr:housenumber":"po",
    "addr:postcode":"5459;t7a 1r5",
    "addr:street":"Box;Stn Main",
    "iso:country":"CA",
    "sg:address":"PO Box 5459 STN Main",
    "sg:city":"Drayton Valley",
    "sg:classifiers":[
        {
            "category":"Manufacturing",
            "subcategory":"Lumber",
            "type":"Manufacturing & Wholesale Goods"
        }
    ],
    "sg:phone":"+1 780 542 1737",
    "sg:postcode":"T7A 1R5",
    "sg:province":"AB",
    "sg:tags":[
        "company",
        "logging"
    ],
    "wof:name":"Lance's Logging Ltd",
    "wof:placetype":"venue"
},
  "geometry": {"coordinates":[-114.98689299999999,53.227997],"type":"Point"}
}