{
  "type": "Feature",
  "properties": {
    "iso:country":"CA",
    "sg:address":"2881 Major Mackenzie Dr E",
    "sg:city":"Markham",
    "sg:classifiers":[
        {
            "category":"Autos & Motor Vehicles",
            "subcategory":"Fuel & Gas Station",
            "type":"Retail Goods"
        }
    ],
    "sg:phone":"+1 905 887 2763",
    "sg:postcode":"L6C 1Z5",
    "sg:province":"ON",
    "sg:tags":[
        "oil"
    ],
    "wof:name":"Shell Canada Products Ltd",
    "wof:placetype":"venue"
},
  "geometry": {"coordinates":[-79.3709182739,43.8850364685],"type":"Point"}
}