{
  "type": "Feature",
  "properties": {
    "addr:full":"5045 Orbitor Dr Mississauga ON L4W 4Y4",
    "addr:housenumber":"5045",
    "addr:postcode":"l4w 4y4",
    "addr:street":"Orbitor Dr",
    "iso:country":"CA",
    "sg:address":"5045 Orbitor Dr",
    "sg:city":"Mississauga",
    "sg:classifiers":[
        {
            "category":"Travel",
            "subcategory":"Travel Agent",
            "type":"Entertainment"
        }
    ],
    "sg:phone":"+1 905 361 2022",
    "sg:postcode":"L4W 4Y4",
    "sg:province":"ON",
    "sg:tags":[
        "agency",
        "bureau"
    ],
    "wof:name":"Flightline",
    "wof:placetype":"venue"
},
  "geometry": {"coordinates":[-79.599197,43.656467],"type":"Point"}
}