{
  "type": "Feature",
  "properties": {
    "addr:full":"43 Silver Aspen Cres Kitchener ON N2N 1H5",
    "addr:housenumber":"43",
    "addr:postcode":"n2n 1h5",
    "addr:street":"Silver Aspen Cres",
    "iso:country":"CA",
    "sg:address":"43 Silver Aspen Cres",
    "sg:city":"Kitchener",
    "sg:classifiers":[
        {
            "category":"Professional",
            "subcategory":"Engineering",
            "type":"Services"
        }
    ],
    "sg:phone":"+1 519 579 2608",
    "sg:postcode":"N2N 1H5",
    "sg:province":"ON",
    "sg:tags":[
        "sound",
        "level",
        "consultant",
        "testing",
        "hearing",
        "acoustical"
    ],
    "wof:name":"William E Ford & Assoc",
    "wof:placetype":"venue"
},
  "geometry": {"coordinates":[-80.5263519287,43.4227371216],"type":"Point"}
}