{
  "type": "Feature",
  "properties": {
    "addr:full":"Montreal QC H2T 1S6",
    "addr:postcode":"h2t 1s6",
    "iso:country":"CA",
    "sg:city":"Montreal",
    "sg:classifiers":[
        {
            "category":"Organizations",
            "subcategory":"Professional Association",
            "type":"Services"
        }
    ],
    "sg:phone":"+1 514 667 5540",
    "sg:postcode":"H2T 1S6",
    "sg:province":"QC",
    "wof:name":"Odysees Du Livre",
    "wof:placetype":"venue"
},
  "geometry": {"coordinates":[-73.598457,45.525791],"type":"Point"}
}