{
  "type": "Feature",
  "properties": {
    "addr:full":"2 Corliss St Gloucester ON K1J 6W5",
    "addr:housenumber":"2",
    "addr:postcode":"k1j 6w5",
    "addr:street":"Corliss St",
    "iso:country":"CA",
    "sg:address":"2 Corliss St",
    "sg:city":"Gloucester",
    "sg:classifiers":[
        {
            "category":"Real Estate",
            "subcategory":"Real Estate Agent",
            "type":"Services"
        }
    ],
    "sg:phone":"+1 613 749 2765",
    "sg:postcode":"K1J 6W5",
    "sg:province":"ON",
    "sg:tags":[
        "management"
    ],
    "wof:name":"George D Eadie & Assoc Ltd",
    "wof:placetype":"venue"
},
  "geometry": {"coordinates":[-75.60890999999999,45.439163],"type":"Point"}
}