{
  "type": "Feature",
  "properties": {
    "addr:full":"962 Upper James St Hamilton ON L9C 3A5",
    "addr:housenumber":"962",
    "addr:postcode":"l9c 3a5",
    "addr:street":"Upper James St",
    "iso:country":"CA",
    "sg:address":"962 Upper James St",
    "sg:city":"Hamilton",
    "sg:classifiers":[
        {
            "category":"Retail",
            "subcategory":"Veterinary Services",
            "type":"Services"
        }
    ],
    "sg:phone":"+1 905 389 2286",
    "sg:postcode":"L9C 3A5",
    "sg:province":"ON",
    "sg:tags":[
        "veterinarian"
    ],
    "wof:name":"Mohawk Animal Clinic",
    "wof:placetype":"venue"
},
  "geometry": {"coordinates":[-79.88386535639999,43.224029541],"type":"Point"}
}