{
  "type": "Feature",
  "properties": {
    "addr:full":"Valleyview AB T0H 3N0",
    "addr:postcode":"t0h 3n0",
    "iso:country":"CA",
    "sg:city":"Valleyview",
    "sg:classifiers":[
        {
            "category":"Mining & Drilling",
            "type":"Manufacturing & Wholesale Goods"
        }
    ],
    "sg:phone":"+1 780 524 2651",
    "sg:postcode":"T0H 3N0",
    "sg:province":"AB",
    "sg:tags":[
        "field",
        "oil",
        "transportation"
    ],
    "wof:name":"Maedae Oilfield Svc Ltd",
    "wof:placetype":"venue"
},
  "geometry": {"coordinates":[-117.271774292,55.0686416626],"type":"Point"}
}