{
  "type": "Feature",
  "properties": {
    "addr:full":"164 Boul Du Portage-Des-Mousse Port-Cartier QC G5B 1E3",
    "addr:housenumber":"164",
    "addr:postcode":"g5b 1e3",
    "addr:street":"Boul Du Portage-Des-Mousse",
    "iso:country":"CA",
    "sg:address":"164 Boul Du Portage-Des-Mousse",
    "sg:city":"Port-Cartier",
    "sg:classifiers":[
        {
            "category":"Manufacturing",
            "subcategory":"Metals",
            "type":"Manufacturing & Wholesale Goods"
        }
    ],
    "sg:phone":"+1 418 766 6806",
    "sg:postcode":"G5B 1E3",
    "sg:province":"QC",
    "sg:tags":[
        "tool"
    ],
    "wof:name":"Equipements Industriels Jr",
    "wof:placetype":"venue"
},
  "geometry": {"coordinates":[-66.830933,50.033791],"type":"Point"}
}