{
  "type": "Feature",
  "properties": {
    "addr:full":"346 Eglinton Ave W Toronto ON M5N 1A2",
    "addr:housenumber":"346",
    "addr:postcode":"m5n 1a2",
    "addr:street":"Eglinton Ave W",
    "iso:country":"CA",
    "sg:address":"346 Eglinton Ave W",
    "sg:city":"Toronto",
    "sg:classifiers":[
        {
            "category":"Shopping",
            "subcategory":"Tobacco",
            "type":"Retail Goods"
        }
    ],
    "sg:phone":"+1 416 484 1114",
    "sg:postcode":"M5N 1A2",
    "sg:province":"ON",
    "sg:tags":[
        "cigarette",
        "cigar",
        "dealer"
    ],
    "wof:name":"Fairfax & Carruthers Tobacco",
    "wof:placetype":"venue"
},
  "geometry": {"coordinates":[-79.408996582,43.7046356201],"type":"Point"}
}