{
  "type": "Feature",
  "properties": {
    "addr:full":"18 Tache St Fisher Branch MB R0C 0Z0",
    "addr:housenumber":"18",
    "addr:postcode":"r0c 0z0",
    "addr:street":"Tache St",
    "iso:country":"CA",
    "sg:address":"18 Tache St",
    "sg:city":"Fisher Branch",
    "sg:classifiers":[
        {
            "category":"Shopping",
            "subcategory":"Discount & Variety Stores",
            "type":"Retail Goods"
        }
    ],
    "sg:phone":"+1 204 372 8793",
    "sg:postcode":"R0C 0Z0",
    "sg:province":"MB",
    "sg:tags":[
        "shop",
        "gift"
    ],
    "wof:name":"Mr Greenbucks Dollar Store",
    "wof:placetype":"venue"
},
  "geometry": {"coordinates":[-97.618454,51.082603],"type":"Point"}
}