{
  "type": "Feature",
  "properties": {
    "addr:full":"1505 Arlington Ave Saskatoon SK S7H 2Y3",
    "addr:housenumber":"1505",
    "addr:postcode":"s7h 2y3",
    "addr:street":"Arlington Ave",
    "iso:country":"CA",
    "sg:address":"1505 Arlington Ave",
    "sg:city":"Saskatoon",
    "sg:classifiers":[
        {
            "category":"Building & Trades",
            "subcategory":"Cleaning & Sanitation",
            "type":"Services"
        }
    ],
    "sg:phone":"+1 306 955 4151",
    "sg:postcode":"S7H 2Y3",
    "sg:province":"SK",
    "sg:tags":[
        "janitor"
    ],
    "wof:name":"Saskachimo Cleaners Ltd",
    "wof:placetype":"venue"
},
  "geometry": {"coordinates":[-106.608643,52.110416],"type":"Point"}
}