{
  "type": "Feature",
  "properties": {
    "addr:full":"537 Goderich St Port Elgin ON N0H 2C4",
    "addr:housenumber":"537",
    "addr:postcode":"n0h 2c4",
    "addr:street":"Goderich St",
    "iso:country":"CA",
    "sg:address":"537 Goderich St",
    "sg:city":"Port Elgin",
    "sg:classifiers":[
        {
            "category":"Cinema",
            "subcategory":"Movie Rental",
            "type":"Entertainment"
        }
    ],
    "sg:phone":"+1 519 389 4211",
    "sg:postcode":"N0H 2C4",
    "sg:province":"ON",
    "sg:tags":[
        "leasing",
        "video",
        "disc",
        "tape"
    ],
    "wof:name":"B J's Video",
    "wof:placetype":"venue"
},
  "geometry": {"coordinates":[-81.39016700000001,44.434326],"type":"Point"}
}