{
  "type": "Feature",
  "properties": {
    "addr:full":"2280 St Laurent Blvd #103 Ottawa ON K1G 4K1",
    "addr:housenumber":"2280",
    "addr:postcode":"k1g 4k1",
    "addr:street":"St Laurent Blvd # 103",
    "iso:country":"CA",
    "sg:address":"2280 St Laurent Blvd #103",
    "sg:city":"Ottawa",
    "sg:classifiers":[
        {
            "category":"Professional",
            "type":"Services"
        }
    ],
    "sg:phone":"+1 613 526 1969",
    "sg:postcode":"K1G 4K1",
    "sg:province":"ON",
    "sg:tags":[
        "computer",
        "establishment",
        "software"
    ],
    "wof:name":"Winfund Software Corp",
    "wof:placetype":"venue"
},
  "geometry": {"coordinates":[-75.616264,45.386314],"type":"Point"}
}