{
  "type": "Feature",
  "properties": {
    "addr:full":"8620 91 St NW Edmonton AB T6C 3N2",
    "addr:housenumber":"8620",
    "addr:postcode":"t6c 3n2",
    "addr:street":"91 St Nw",
    "iso:country":"CA",
    "sg:address":"8620 91 St NW",
    "sg:city":"Edmonton",
    "sg:classifiers":[
        {
            "category":"Education",
            "subcategory":"School",
            "type":"Public Place"
        }
    ],
    "sg:phone":"+1 780 466 2891",
    "sg:postcode":"T6C 3N2",
    "sg:province":"AB",
    "wof:name":"Rutherford Elementary School",
    "wof:placetype":"venue"
},
  "geometry": {"coordinates":[-113.467659,53.522224],"type":"Point"}
}