{
  "type": "Feature",
  "properties": {
    "addr:full":"233 Rte Langevin Saint-Odilon QC G0S 3A0",
    "addr:housenumber":"233",
    "addr:postcode":"g0s 3a0",
    "addr:street":"Rte Langevin",
    "iso:country":"CA",
    "sg:address":"233 Rte Langevin",
    "sg:city":"Saint-Odilon",
    "sg:classifiers":[
        {
            "category":"Personal",
            "subcategory":"Beauty Salon",
            "type":"Services"
        }
    ],
    "sg:phone":"+1 418 464 4038",
    "sg:postcode":"G0S 3A0",
    "sg:province":"QC",
    "wof:name":"Salon Nicole Cloutier",
    "wof:placetype":"venue"
},
  "geometry": {"coordinates":[-70.674057,46.356369],"type":"Point"}
}