{
  "type": "Feature",
  "properties": {
    "addr:full":"Montreal-Nord QC H1G 6L2",
    "addr:postcode":"h1g 6l2",
    "iso:country":"CA",
    "sg:city":"Montreal-Nord",
    "sg:classifiers":[
        {
            "category":"Food & Beverages",
            "subcategory":"Groceries & Convenience Stores",
            "type":"Retail Goods"
        }
    ],
    "sg:phone":"+1 514 326 4740",
    "sg:postcode":"H1G 6L2",
    "sg:province":"QC",
    "wof:name":"Depanneur Les Tours Gouin",
    "wof:placetype":"venue"
},
  "geometry": {"coordinates":[-73.6217803955,45.6275978088],"type":"Point"}
}