{
  "type": "Feature",
  "properties": {
    "addr:full":"162 Boul Des Bois-Francs N Victoriaville QC G6P 9C3",
    "addr:housenumber":"162",
    "addr:postcode":"g6p 9c3",
    "addr:street":"Boul Des Bois-Francs N",
    "iso:country":"CA",
    "sg:address":"162 Boul Des Bois-Francs N",
    "sg:city":"Victoriaville",
    "sg:classifiers":[
        {
            "category":"Health Services",
            "subcategory":"Doctor",
            "type":"Services"
        }
    ],
    "sg:phone":"+1 819 758 1200",
    "sg:postcode":"G6P 9C3",
    "sg:province":"QC",
    "sg:tags":[
        "clinic",
        "chiropractor"
    ],
    "wof:name":"Centre Chiropratique Place",
    "wof:placetype":"venue"
},
  "geometry": {"coordinates":[-71.9561920166,46.0613899231],"type":"Point"}
}