{
  "type": "Feature",
  "properties": {
    "addr:full":"2418 22 Ave SE Medicine Hat AB T1B 1B6",
    "addr:housenumber":"2418",
    "addr:postcode":"t1b 1b6",
    "addr:street":"22 Ave Se",
    "iso:country":"CA",
    "sg:address":"2418 22 Ave SE",
    "sg:city":"Medicine Hat",
    "sg:classifiers":[
        {
            "category":"Building & Trades",
            "subcategory":"Construction",
            "type":"Services"
        }
    ],
    "sg:phone":"+1 403 529 9042",
    "sg:postcode":"T1B 1B6",
    "sg:province":"AB",
    "sg:tags":[
        "repairing",
        "remodeling",
        "contractor"
    ],
    "wof:name":"E B Finishing",
    "wof:placetype":"venue"
},
  "geometry": {"coordinates":[-110.64979599999999,50.01609],"type":"Point"}
}