{
  "type": "Feature",
  "properties": {
    "iso:country":"CA",
    "sg:address":"44 Canary Reed Crt",
    "sg:city":"Barrie",
    "sg:classifiers":[
        {
            "category":"Education",
            "subcategory":"Special Training",
            "type":"Public Place"
        }
    ],
    "sg:phone":"+1 705 726 6633",
    "sg:postcode":"L4N 8S1",
    "sg:province":"ON",
    "sg:tags":[
        "instruction",
        "music"
    ],
    "wof:name":"Accent Piano School",
    "wof:placetype":"venue"
},
  "geometry": {"coordinates":[-79.721481,44.334438],"type":"Point"}
}