{
  "type": "Feature",
  "properties": {
    "addr:full":"Etobicoke ON M9V 5H1",
    "addr:postcode":"m9v 5h1",
    "iso:country":"CA",
    "sg:city":"Etobicoke",
    "sg:classifiers":[
        {
            "category":"Wholesale",
            "subcategory":"Machinery & Supplies",
            "type":"Manufacturing & Wholesale Goods"
        }
    ],
    "sg:phone":"+1 416 745 2250",
    "sg:postcode":"M9V 5H1",
    "sg:province":"ON",
    "sg:tags":[
        "truck"
    ],
    "wof:name":"Royal Lift Trucks Ltd",
    "wof:placetype":"venue"
},
  "geometry": {"coordinates":[-79.56667299999999,43.643398],"type":"Point"}
}