{
  "type": "Feature",
  "properties": {
    "addr:full":"Sainte-Anne-DE-Madawaska NB E7E 1A2",
    "addr:postcode":"e7e 1a2",
    "iso:country":"CA",
    "sg:city":"Sainte-Anne-DE-Madawaska",
    "sg:classifiers":[
        {
            "category":"Autos & Motor Vehicles",
            "subcategory":"Fuel & Gas Station",
            "type":"Retail Goods"
        }
    ],
    "sg:phone":"+1 506 445 2462",
    "sg:postcode":"E7E 1A2",
    "sg:province":"NB",
    "sg:tags":[
        "oil"
    ],
    "wof:name":"Ringuette Esso",
    "wof:placetype":"venue"
},
  "geometry": {"coordinates":[-68.153702,47.634754],"type":"Point"}
}