{
  "type": "Feature",
  "properties": {
    "addr:full":"234 Brookhurst Cres Saskatoon SK S7V 1C5",
    "addr:housenumber":"234",
    "addr:postcode":"s7v 1c5",
    "addr:street":"Brookhurst Cres",
    "iso:country":"CA",
    "sg:address":"234 Brookhurst Cres",
    "sg:city":"Saskatoon",
    "sg:classifiers":[
        {
            "category":"Professional",
            "subcategory":"Engineering",
            "type":"Services"
        }
    ],
    "sg:phone":"+1 306 374 1889",
    "sg:postcode":"S7V 1C5",
    "sg:province":"SK",
    "sg:tags":[
        "engineer"
    ],
    "wof:name":"Mickleborough Consulting Ltd",
    "wof:placetype":"venue"
},
  "geometry": {"coordinates":[-106.565636,52.10825],"type":"Point"}
}