{
  "type": "Feature",
  "properties": {
    "addr:full":"1901 Bank St Ottawa ON K1V 8A1",
    "addr:housenumber":"1901",
    "addr:postcode":"k1v 8a1",
    "addr:street":"Bank St",
    "iso:country":"CA",
    "sg:address":"1901 Bank St",
    "sg:city":"Ottawa",
    "sg:classifiers":[
        {
            "category":"Shopping",
            "subcategory":"Computers & Home Electronics",
            "type":"Retail Goods"
        }
    ],
    "sg:phone":"+1 613 828 0550",
    "sg:postcode":"K1V 8A1",
    "sg:province":"ON",
    "sg:tags":[
        "television",
        "radio"
    ],
    "wof:name":"Unik Electronics",
    "wof:placetype":"venue"
},
  "geometry": {"coordinates":[-75.66235399999999,45.368736],"type":"Point"}
}