{
  "type": "Feature",
  "properties": {
    "addr:full":"1981 Dundas St W Mississauga ON L5K 1R2",
    "addr:housenumber":"1981",
    "addr:postcode":"l5k 1r2",
    "addr:street":"Dundas St W",
    "iso:country":"CA",
    "sg:address":"1981 Dundas St W",
    "sg:city":"Mississauga",
    "sg:classifiers":[
        {
            "category":"Retail",
            "subcategory":"Funeral Services",
            "type":"Services"
        }
    ],
    "sg:phone":"+1 905 828 8000",
    "sg:postcode":"L5K 1R2",
    "sg:province":"ON",
    "sg:tags":[
        "director"
    ],
    "wof:name":"Neweduk Funeral Home",
    "wof:placetype":"venue"
},
  "geometry": {"coordinates":[-79.6643829346,43.5387153625],"type":"Point"}
}