{
  "type": "Feature",
  "properties": {
    "addr:full":"Vancouver BC V6C 1T1",
    "addr:postcode":"v6c 1t1",
    "iso:country":"CA",
    "sg:city":"Vancouver",
    "sg:classifiers":[
        {
            "category":"Professional",
            "subcategory":"Accounting & Tax Preparation",
            "type":"Services"
        }
    ],
    "sg:phone":"+1 604 681 4334",
    "sg:postcode":"V6C 1T1",
    "sg:province":"BC",
    "sg:tags":[
        "accountant"
    ],
    "wof:name":"Jamal Jamal & CO",
    "wof:placetype":"venue"
},
  "geometry": {"coordinates":[-123.11444899999999,49.285042],"type":"Point"}
}