{
  "type": "Feature",
  "properties": {
    "addr:full":"790 Rue Principale Clair NB E7A 2H6",
    "addr:housenumber":"790",
    "addr:postcode":"e7a 2h6",
    "addr:street":"Rue Principale",
    "iso:country":"CA",
    "sg:address":"790 Rue Principale",
    "sg:city":"Clair",
    "sg:classifiers":[
        {
            "category":"Government",
            "subcategory":"Office",
            "type":"Public Place"
        }
    ],
    "sg:phone":"+1 506 992 2124",
    "sg:postcode":"E7A 2H6",
    "sg:province":"NB",
    "wof:name":"Canada Douanes",
    "wof:placetype":"venue"
},
  "geometry": {"coordinates":[-68.6050643921,47.2510871887],"type":"Point"}
}