{
  "type": "Feature",
  "properties": {
    "addr:full":"2533 Danforth Ave Toronto ON M4C 1L1",
    "addr:housenumber":"2533",
    "addr:postcode":"m4c 1l1",
    "addr:street":"Danforth Ave",
    "iso:country":"CA",
    "sg:address":"2533 Danforth Ave",
    "sg:city":"Toronto",
    "sg:classifiers":[
        {
            "category":"Health Services",
            "subcategory":"Doctor",
            "type":"Services"
        }
    ],
    "sg:phone":"+1 416 698 5521",
    "sg:postcode":"M4C 1L1",
    "sg:province":"ON",
    "sg:tags":[
        "physician",
        "surgeon"
    ],
    "wof:name":"Shiffman, Norman MD",
    "wof:placetype":"venue"
},
  "geometry": {"coordinates":[-79.302155,43.68792],"type":"Point"}
}