{
  "type": "Feature",
  "properties": {
    "addr:full":"2235 Rue Leclaire Montreal QC H1V 3A3",
    "addr:housenumber":"2235",
    "addr:postcode":"h1v 3a3",
    "addr:street":"Rue Leclaire",
    "iso:country":"CA",
    "sg:address":"2235 Rue Leclaire",
    "sg:city":"Montreal",
    "sg:classifiers":[
        {
            "category":"Shopping",
            "subcategory":"Bicycles & Sporting Goods",
            "type":"Retail Goods"
        }
    ],
    "sg:phone":"+1 514 649 9097",
    "sg:postcode":"H1V 3A3",
    "sg:province":"QC",
    "sg:tags":[
        "equipment",
        "exercise"
    ],
    "wof:name":"Pro-Gym St Hubert",
    "wof:placetype":"venue"
},
  "geometry": {"coordinates":[-73.539787,45.558197],"type":"Point"}
}