{
  "type": "Feature",
  "properties": {
    "addr:full":"633391 Hwy 10 N Orangeville ON L9W 2Z1",
    "addr:housenumber":"633391",
    "addr:postcode":"l9w 2z1",
    "addr:street":"Hwy 10 N",
    "iso:country":"CA",
    "sg:address":"633391 Hwy 10 N",
    "sg:city":"Orangeville",
    "sg:classifiers":[
        {
            "category":"Retail",
            "subcategory":"Veterinary Services",
            "type":"Services"
        }
    ],
    "sg:phone":"+1 519 941 6383",
    "sg:postcode":"L9W 2Z1",
    "sg:province":"ON",
    "sg:tags":[
        "veterinarian"
    ],
    "wof:name":"Mono Veterinary Clinic",
    "wof:placetype":"venue"
},
  "geometry": {"coordinates":[-80.0727844238,43.9168701172],"type":"Point"}
}