{
  "type": "Feature",
  "properties": {
    "addr:full":"265 Yorkland Blvd #402 North York ON M2J 1S5",
    "addr:housenumber":"265",
    "addr:postcode":"m2j 1s5",
    "addr:street":"Yorkland Blvd # 402",
    "iso:country":"CA",
    "sg:address":"265 Yorkland Blvd #402",
    "sg:city":"North York",
    "sg:classifiers":[
        {
            "category":"Professional",
            "type":"Services"
        }
    ],
    "sg:phone":"+1 416 494 7311",
    "sg:postcode":"M2J 1S5",
    "sg:province":"ON",
    "sg:tags":[
        "accountant",
        "establishment"
    ],
    "wof:name":"Chan Dykopf & King",
    "wof:placetype":"venue"
},
  "geometry": {"coordinates":[-79.33566999999999,43.773155],"type":"Point"}
}