{
  "type": "Feature",
  "properties": {
    "iso:country":"CA",
    "sg:address":"926 Mccullough Dr",
    "sg:city":"Whitby",
    "sg:classifiers":[
        {
            "category":"Retail",
            "subcategory":"Repair Shop",
            "type":"Services"
        }
    ],
    "sg:phone":"+1 905 666 1852",
    "sg:postcode":"L1N 1C6",
    "sg:province":"ON",
    "sg:tags":[
        "upholsterer"
    ],
    "wof:name":"Brooks Upholstery",
    "wof:placetype":"venue"
},
  "geometry": {"coordinates":[-78.946892,43.867908],"type":"Point"}
}