{
  "type": "Feature",
  "properties": {
    "addr:full":"345 Bloor St E # 6 Toronto ON M4W 3J6",
    "addr:housenumber":"345",
    "addr:postcode":"m4w 3j6",
    "addr:street":"Bloor St E # 6",
    "iso:country":"CA",
    "sg:address":"345 Bloor St E # 6",
    "sg:city":"Toronto",
    "sg:classifiers":[
        {
            "category":"Restaurant",
            "type":"Food & Drink"
        }
    ],
    "sg:phone":"+1 416 925 6908",
    "sg:postcode":"M4W 3J6",
    "sg:province":"ON",
    "sg:tags":[
        "caterer"
    ],
    "wof:name":"Meallenium Food Svc",
    "wof:placetype":"venue"
},
  "geometry": {"coordinates":[-79.379097,43.67186],"type":"Point"}
}