{
  "type": "Feature",
  "properties": {
    "addr:full":"95 Rue Merry N Magog QC J1X 2E7",
    "addr:housenumber":"95",
    "addr:postcode":"j1x 2e7",
    "addr:street":"Rue Merry N",
    "iso:country":"CA",
    "sg:address":"95 Rue Merry N",
    "sg:city":"Magog",
    "sg:classifiers":[
        {
            "category":"Social Services",
            "subcategory":"Child Care",
            "type":"Services"
        }
    ],
    "sg:phone":"+1 819 843 5349",
    "sg:postcode":"J1X 2E7",
    "sg:province":"QC",
    "wof:name":"Centre DE LA Petite Enfance",
    "wof:placetype":"venue"
},
  "geometry": {"coordinates":[-72.1556091309,45.2678604126],"type":"Point"}
}