{
  "type": "Feature",
  "properties": {
    "addr:full":"Burnaby BC V5C 6C1",
    "addr:postcode":"v5c 6c1",
    "iso:country":"CA",
    "sg:city":"Burnaby",
    "sg:classifiers":[
        {
            "category":"Health Services",
            "subcategory":"Health Practitioner",
            "type":"Services"
        }
    ],
    "sg:phone":"+1 604 294 3911",
    "sg:postcode":"V5C 6C1",
    "sg:province":"BC",
    "sg:tags":[
        "physiotherapist"
    ],
    "wof:name":"Burnaby Heights Physiotherapy",
    "wof:placetype":"venue"
},
  "geometry": {"coordinates":[-123.01693725600001,49.2809371948],"type":"Point"}
}