{
  "type": "Feature",
  "properties": {
    "addr:full":"2 Main St W Grimsby ON L3M 1R4",
    "addr:housenumber":"2",
    "addr:postcode":"l3m 1r4",
    "addr:street":"Main St W",
    "iso:country":"CA",
    "sg:address":"2 Main St W",
    "sg:city":"Grimsby",
    "sg:classifiers":[
        {
            "category":"Food & Beverages",
            "subcategory":"Specialty",
            "type":"Retail Goods"
        }
    ],
    "sg:phone":"+1 905 945 9391",
    "sg:postcode":"L3M 1R4",
    "sg:province":"ON",
    "sg:tags":[
        "health",
        "diet"
    ],
    "wof:name":"Good Earth Shop",
    "wof:placetype":"venue"
},
  "geometry": {"coordinates":[-79.5607910156,43.1932868958],"type":"Point"}
}