{
  "type": "Feature",
  "properties": {
    "iso:country":"CA",
    "sg:city":"Vulcan",
    "sg:classifiers":[
        {
            "category":"Retail",
            "subcategory":"Auto Repair",
            "type":"Services"
        }
    ],
    "sg:phone":"+1 403 485 6671",
    "sg:postcode":"T0L 2B0",
    "sg:province":"AB",
    "sg:tags":[
        "repairing",
        "automobile"
    ],
    "wof:name":"Corner Store & Garage",
    "wof:placetype":"venue"
},
  "geometry": {"coordinates":[-113.258178711,50.3973388672],"type":"Point"}
}