{
  "type": "Feature",
  "properties": {
    "addr:full":"1875 17 St SE Medicine Hat AB T1A 2B3",
    "addr:housenumber":"1875",
    "addr:postcode":"t1a 2b3",
    "addr:street":"17 St Se",
    "iso:country":"CA",
    "sg:address":"1875 17 St SE",
    "sg:city":"Medicine Hat",
    "sg:classifiers":[
        {
            "category":"Health Services",
            "subcategory":"Clinic",
            "type":"Services"
        }
    ],
    "sg:phone":"+1 403 526 3868",
    "sg:postcode":"T1A 2B3",
    "sg:province":"AB",
    "sg:tags":[
        "home"
    ],
    "wof:name":"Quality Care CO",
    "wof:placetype":"venue"
},
  "geometry": {"coordinates":[-110.656608581,50.0230064392],"type":"Point"}
}