{
  "type": "Feature",
  "properties": {
    "addr:full":"241 Grassy Rd Omemee ON K0L 2W0",
    "addr:housenumber":"241",
    "addr:postcode":"k0l 2w0",
    "addr:street":"Grassy Rd",
    "iso:country":"CA",
    "sg:address":"241 Grassy Rd",
    "sg:city":"Omemee",
    "sg:classifiers":[
        {
            "category":"Building & Trades",
            "subcategory":"Construction",
            "type":"Services"
        }
    ],
    "sg:phone":"+1 705 799 1803",
    "sg:postcode":"K0L 2W0",
    "sg:province":"ON",
    "sg:tags":[
        "contractor"
    ],
    "wof:name":"Mc Coll Construction",
    "wof:placetype":"venue"
},
  "geometry": {"coordinates":[-78.526138,44.320881],"type":"Point"}
}