{
  "type": "Feature",
  "properties": {
    "addr:full":"2685 Rue Dessaulles Saint-Hyacinthe QC J2S 2V4",
    "addr:housenumber":"2685",
    "addr:postcode":"j2s 2v4",
    "addr:street":"Rue Dessaulles",
    "iso:country":"CA",
    "sg:address":"2685 Rue Dessaulles",
    "sg:city":"Saint-Hyacinthe",
    "sg:classifiers":[
        {
            "category":"Retail",
            "subcategory":"Laundry & Dry Cleaning",
            "type":"Services"
        }
    ],
    "sg:phone":"+1 450 774 4337",
    "sg:postcode":"J2S 2V4",
    "sg:province":"QC",
    "sg:tags":[
        "cleaners"
    ],
    "wof:name":"Nettoyeurs Chatel Inc",
    "wof:placetype":"venue"
},
  "geometry": {"coordinates":[-72.95700100000001,45.621475],"type":"Point"}
}