{
  "type": "Feature",
  "properties": {
    "addr:full":"Dugald MB R0E 0K0",
    "addr:postcode":"r0e 0k0",
    "iso:country":"CA",
    "sg:city":"Dugald",
    "sg:classifiers":[
        {
            "category":"Wholesale",
            "subcategory":"Construction Materials",
            "type":"Manufacturing & Wholesale Goods"
        }
    ],
    "sg:phone":"+1 204 444 3667",
    "sg:postcode":"R0E 0K0",
    "sg:province":"MB",
    "sg:tags":[
        "sand",
        "gravel"
    ],
    "wof:name":"Ross Sand & Gravel",
    "wof:placetype":"venue"
},
  "geometry": {"coordinates":[-96.840118,49.885906],"type":"Point"}
}