{
  "type": "Feature",
  "properties": {
    "iso:country":"CA",
    "sg:address":"755 Lake Bonavista Dr SE #81078",
    "sg:city":"Calgary",
    "sg:classifiers":[
        {
            "category":"Professional",
            "subcategory":"Computer Services",
            "type":"Services"
        }
    ],
    "sg:phone":"+1 403 225 2123",
    "sg:postcode":"T2J 0N3",
    "sg:province":"AB",
    "sg:tags":[
        "website",
        "design",
        "internet"
    ],
    "wof:name":"Web World",
    "wof:placetype":"venue"
},
  "geometry": {"coordinates":[-114.048141,50.943687],"type":"Point"}
}