{
  "type": "Feature",
  "properties": {
    "addr:full":"North York ON M3J 2C4",
    "addr:postcode":"m3j 2c4",
    "iso:country":"CA",
    "sg:city":"North York",
    "sg:classifiers":[
        {
            "category":"Professional",
            "subcategory":"Management & Consulting",
            "type":"Services"
        }
    ],
    "sg:phone":"+1 416 661 4460",
    "sg:postcode":"M3J 2C4",
    "sg:province":"ON",
    "sg:tags":[
        "party",
        "planning"
    ],
    "wof:name":"Encore Food With Elegance",
    "wof:placetype":"venue"
},
  "geometry": {"coordinates":[-79.472191,43.781433],"type":"Point"}
}