{
  "type": "Feature",
  "properties": {
    "iso:country":"CA",
    "sg:address":"PO Box 100",
    "sg:city":"Change Islands",
    "sg:classifiers":[
        {
            "category":"Health Services",
            "subcategory":"Clinic",
            "type":"Services"
        }
    ],
    "sg:phone":"+1 709 621 6161",
    "sg:postcode":"A0G 1R0",
    "sg:province":"NL",
    "sg:tags":[
        "home"
    ],
    "wof:name":"Health & Community Svc-Central",
    "wof:placetype":"venue"
},
  "geometry": {"coordinates":[-54.4072761536,49.6714401245],"type":"Point"}
}