{
  "type": "Feature",
  "properties": {
    "addr:full":"7075 Ordan Dr Mississauga ON L5T 1K6",
    "addr:housenumber":"7075",
    "addr:postcode":"l5t 1k6",
    "addr:street":"Ordan Dr",
    "iso:country":"CA",
    "sg:address":"7075 Ordan Dr",
    "sg:city":"Mississauga",
    "sg:classifiers":[
        {
            "category":"Freight",
            "type":"Transportation"
        }
    ],
    "sg:phone":"+1 905 677 7371",
    "sg:postcode":"L5T 1K6",
    "sg:province":"ON",
    "sg:tags":[
        "broker",
        "customs"
    ],
    "wof:name":"Fedex Trade Networks Transport",
    "wof:placetype":"venue"
},
  "geometry": {"coordinates":[-79.666443,43.657936],"type":"Point"}
}