{
  "type": "Feature",
  "properties": {
    "iso:country":"CA",
    "sg:address":"170 Beaver Bend Cres",
    "sg:city":"Etobicoke",
    "sg:classifiers":[
        {
            "category":"Wholesale",
            "subcategory":"Machinery & Supplies",
            "type":"Manufacturing & Wholesale Goods"
        }
    ],
    "sg:phone":"+1 416 621 0123",
    "sg:postcode":"M9B 5S1",
    "sg:province":"ON",
    "sg:tags":[
        "equipment",
        "printing"
    ],
    "wof:name":"Pactek International Inc",
    "wof:placetype":"venue"
},
  "geometry": {"coordinates":[-79.572098,43.669121],"type":"Point"}
}