{
  "type": "Feature",
  "properties": {
    "addr:full":"Pointe-Claire QC H9R 5N8",
    "addr:postcode":"h9r 5n8",
    "iso:country":"CA",
    "sg:city":"Pointe-Claire",
    "sg:classifiers":[
        {
            "category":"Utilities",
            "subcategory":"Mobile Phone",
            "type":"Services"
        }
    ],
    "sg:phone":"+1 514 426 9999",
    "sg:postcode":"H9R 5N8",
    "sg:province":"QC",
    "sg:tags":[
        "telephone",
        "cellular"
    ],
    "wof:name":"Cell Tel",
    "wof:placetype":"venue"
},
  "geometry": {"coordinates":[-73.83055899999999,45.468571],"type":"Point"}
}