{
  "type": "Feature",
  "properties": {
    "addr:full":"534 Old Wilton Rd Odessa ON K0H 2H0",
    "addr:housenumber":"534",
    "addr:postcode":"k0h 2h0",
    "addr:street":"Old Wilton Rd",
    "iso:country":"CA",
    "sg:address":"534 Old Wilton Rd",
    "sg:city":"Odessa",
    "sg:classifiers":[
        {
            "category":"Retail",
            "subcategory":"Animal Services",
            "type":"Services"
        }
    ],
    "sg:phone":"+1 613 386 3728",
    "sg:postcode":"K0H 2H0",
    "sg:province":"ON",
    "sg:tags":[
        "pet",
        "boarding",
        "sitting"
    ],
    "wof:name":"Zarko Kennels Regd",
    "wof:placetype":"venue"
},
  "geometry": {"coordinates":[-76.72328186039999,44.2778205872],"type":"Point"}
}