{
  "type": "Feature",
  "properties": {
    "addr:full":"33 Av Pie-X Victoriaville QC G6P 4R8",
    "addr:postcode":"g6p 4r8",
    "addr:street":"33 Av Pie-X",
    "iso:country":"CA",
    "sg:address":"33 Av Pie-X",
    "sg:city":"Victoriaville",
    "sg:classifiers":[
        {
            "category":"Recreation",
            "type":"Entertainment"
        }
    ],
    "sg:phone":"+1 819 758 6414",
    "sg:postcode":"G6P 4R8",
    "sg:province":"QC",
    "sg:tags":[
        "provincial",
        "parks"
    ],
    "wof:name":"Parc Lineaire Bois-Franc Inc",
    "wof:placetype":"venue"
},
  "geometry": {"coordinates":[-71.96090700000001,46.046421],"type":"Point"}
}