{
  "type": "Feature",
  "properties": {
    "addr:full":"6620 Kitimat Rd Mississauga ON L5N 2B8",
    "addr:postcode":"6620;l5n 2b8",
    "addr:street":"Kitimat Rd",
    "iso:country":"CA",
    "sg:address":"6620 Kitimat Rd",
    "sg:city":"Mississauga",
    "sg:classifiers":[
        {
            "category":"Shopping",
            "subcategory":"Bicycles & Sporting Goods",
            "type":"Retail Goods"
        }
    ],
    "sg:phone":"+1 905 826 5250",
    "sg:postcode":"L5N 2B8",
    "sg:province":"ON",
    "sg:tags":[
        "equipment",
        "curling",
        "supply"
    ],
    "wof:name":"Goldline Curling Pro Shop",
    "wof:placetype":"venue"
},
  "geometry": {"coordinates":[-79.735474,43.602543],"type":"Point"}
}