{
  "type": "Feature",
  "properties": {
    "addr:full":"7701 Rue Mcvey Montreal QC H1L 6M2",
    "addr:housenumber":"7701",
    "addr:postcode":"h1l 6m2",
    "addr:street":"Rue Mcvey",
    "iso:country":"CA",
    "sg:address":"7701 Rue Mcvey",
    "sg:city":"Montreal",
    "sg:classifiers":[
        {
            "category":"Wholesale",
            "subcategory":"Sporting Goods",
            "type":"Manufacturing & Wholesale Goods"
        }
    ],
    "sg:phone":"+1 514 355 5579",
    "sg:postcode":"H1L 6M2",
    "sg:province":"QC",
    "sg:tags":[
        "equipment",
        "golf",
        "supply"
    ],
    "wof:name":"Golf Associates",
    "wof:placetype":"venue"
},
  "geometry": {"coordinates":[-73.5210342407,45.5896377563],"type":"Point"}
}