{
  "type": "Feature",
  "properties": {
    "addr:full":"30 Rue Racine E Chicoutimi QC G7H 1P5",
    "addr:housenumber":"30",
    "addr:postcode":"g7h 1p5",
    "addr:street":"Rue Racine E",
    "iso:country":"CA",
    "sg:address":"30 Rue Racine E",
    "sg:city":"Chicoutimi",
    "sg:classifiers":[
        {
            "category":"Professional",
            "subcategory":"Lawyer & Legal Services",
            "type":"Services"
        }
    ],
    "sg:phone":"+1 418 549 7182",
    "sg:postcode":"G7H 1P5",
    "sg:province":"QC",
    "sg:tags":[
        "attorney"
    ],
    "wof:name":"Gaudreault Saucier Simard",
    "wof:placetype":"venue"
},
  "geometry": {"coordinates":[-71.067581,48.427849],"type":"Point"}
}