{
  "type": "Feature",
  "properties": {
    "addr:full":"5862 Boul Saint-Michel Montreal QC H1Y 2E4",
    "addr:housenumber":"5862",
    "addr:postcode":"h1y 2e4",
    "addr:street":"Boul Saint-Michel",
    "iso:country":"CA",
    "sg:address":"5862 Boul Saint-Michel",
    "sg:city":"Montreal",
    "sg:classifiers":[
        {
            "category":"Manufacturing",
            "subcategory":"Printing",
            "type":"Manufacturing & Wholesale Goods"
        }
    ],
    "sg:phone":"+1 514 729 3335",
    "sg:postcode":"H1Y 2E4",
    "sg:province":"QC",
    "sg:tags":[
        "imprinting"
    ],
    "wof:name":"Communicateurs Ethniques",
    "wof:placetype":"venue"
},
  "geometry": {"coordinates":[-73.579735,45.552795],"type":"Point"}
}