{
  "type": "Feature",
  "properties": {
    "iso:country":"CA",
    "sg:address":"3565 Kingsway",
    "sg:city":"Vancouver",
    "sg:classifiers":[
        {
            "category":"Utilities",
            "subcategory":"Mobile Phone",
            "type":"Services"
        }
    ],
    "sg:phone":"+1 604 439 8888",
    "sg:postcode":"V5R 5L9",
    "sg:province":"BC",
    "sg:tags":[
        "telephone",
        "cellular"
    ],
    "wof:name":"Unipage",
    "wof:placetype":"venue"
},
  "geometry": {"coordinates":[-123.02735900899999,49.2322616577],"type":"Point"}
}