{
  "type": "Feature",
  "properties": {
    "addr:full":"977 Wagonwood Pl Victoria BC V8X 4M1",
    "addr:housenumber":"977",
    "addr:postcode":"v8x 4m1",
    "addr:street":"Wagonwood Pl",
    "iso:country":"CA",
    "sg:address":"977 Wagonwood Pl",
    "sg:city":"Victoria",
    "sg:classifiers":[
        {
            "category":"Professional",
            "subcategory":"Lawyer & Legal Services",
            "type":"Services"
        }
    ],
    "sg:phone":"+1 250 658 0318",
    "sg:postcode":"V8X 4M1",
    "sg:province":"BC",
    "sg:tags":[
        "naturalization",
        "immigration"
    ],
    "wof:name":"Asian Rim Intl Public Relation",
    "wof:placetype":"venue"
},
  "geometry": {"coordinates":[-123.36451700000001,48.428314],"type":"Point"}
}