{
  "type": "Feature",
  "properties": {
    "addr:full":"44 Great Northern Rd Sault Ste Marie ON P6B 4Y5",
    "addr:housenumber":"44",
    "addr:postcode":"p6b 4y5",
    "addr:street":"Great Northern Rd",
    "iso:country":"CA",
    "sg:address":"44 Great Northern Rd",
    "sg:city":"Sault Ste Marie",
    "sg:classifiers":[
        {
            "category":"Shopping",
            "subcategory":"Books",
            "type":"Retail Goods"
        }
    ],
    "sg:phone":"+1 705 949 5467",
    "sg:postcode":"P6B 4Y5",
    "sg:province":"ON",
    "sg:tags":[
        "dealer"
    ],
    "wof:name":"Coles",
    "wof:placetype":"venue"
},
  "geometry": {"coordinates":[-84.31927490229999,46.5247497559],"type":"Point"}
}