{
  "type": "Feature",
  "properties": {
    "addr:full":"566 Rue Principale Petit-Rocher NB E8J 1R2",
    "addr:housenumber":"566",
    "addr:postcode":"e8j 1r2",
    "addr:street":"Rue Principale",
    "iso:country":"CA",
    "sg:address":"566 Rue Principale",
    "sg:city":"Petit-Rocher",
    "sg:classifiers":[
        {
            "category":"Banks & Credit Unions",
            "subcategory":"Bank",
            "type":"Services"
        }
    ],
    "sg:phone":"+1 506 783 4241",
    "sg:postcode":"E8J 1R2",
    "sg:province":"NB",
    "wof:name":"Caisse Populaire DE Petit",
    "wof:placetype":"venue"
},
  "geometry": {"coordinates":[-65.71895599370001,47.7842636108],"type":"Point"}
}