{
  "type": "Feature",
  "properties": {
    "addr:full":"28 Willett St Halifax NS B3N 3B2",
    "addr:housenumber":"28",
    "addr:postcode":"b3n 3b2",
    "addr:street":"Willett St",
    "iso:country":"CA",
    "sg:address":"28 Willett St",
    "sg:city":"Halifax",
    "sg:classifiers":[
        {
            "category":"Organizations",
            "subcategory":"Religious Organization",
            "type":"Services"
        }
    ],
    "sg:phone":"+1 902 443 4700",
    "sg:postcode":"B3N 3B2",
    "sg:province":"NS",
    "sg:tags":[
        "church"
    ],
    "wof:name":"Alive Christian Church",
    "wof:placetype":"venue"
},
  "geometry": {"coordinates":[-63.644192,44.650787],"type":"Point"}
}