{
  "type": "Feature",
  "properties": {
    "addr:full":"3775 Boul Lite Laval QC H7E 1A3",
    "addr:housenumber":"3775",
    "addr:postcode":"h7e 1a3",
    "addr:street":"Boul Lite",
    "iso:country":"CA",
    "sg:address":"3775 Boul Lite",
    "sg:city":"Laval",
    "sg:classifiers":[
        {
            "category":"Home & Garden",
            "subcategory":"Building Materials",
            "type":"Retail Goods"
        }
    ],
    "sg:phone":"+1 450 664 1434",
    "sg:postcode":"H7E 1A3",
    "sg:province":"QC",
    "wof:name":"Edouard Beauchesne Inc",
    "wof:placetype":"venue"
},
  "geometry": {"coordinates":[-73.668907,45.611061],"type":"Point"}
}