{
  "type": "Feature",
  "properties": {
    "iso:country":"CA",
    "sg:address":"13 Industrial Dr",
    "sg:city":"Elmira",
    "sg:classifiers":[
        {
            "category":"Retail",
            "subcategory":"Laundry & Dry Cleaning",
            "type":"Services"
        }
    ],
    "sg:phone":"+1 519 669 2033",
    "sg:postcode":"N3B 2S1",
    "sg:province":"ON",
    "sg:tags":[
        "cleaners",
        "rug",
        "carpet"
    ],
    "wof:name":"Kleensweep Carpet Care",
    "wof:placetype":"venue"
},
  "geometry": {"coordinates":[-80.56090500000001,43.590012],"type":"Point"}
}