{
  "type": "Feature",
  "properties": {
    "addr:full":"336 James St Wallaceburg ON N8A 2N5",
    "addr:housenumber":"336",
    "addr:postcode":"n8a 2n5",
    "addr:street":"James St",
    "iso:country":"CA",
    "sg:address":"336 James St",
    "sg:city":"Wallaceburg",
    "sg:classifiers":[
        {
            "category":"Social Services",
            "type":"Services"
        }
    ],
    "sg:phone":"+1 519 627 3813",
    "sg:postcode":"N8A 2N5",
    "sg:province":"ON",
    "sg:tags":[
        "organization",
        "welfare"
    ],
    "wof:name":"St Vincent DE Paul Store",
    "wof:placetype":"venue"
},
  "geometry": {"coordinates":[-82.383194,42.594612],"type":"Point"}
}