{
  "type": "Feature",
  "properties": {
    "addr:full":"2159 Av Notre-Dame Sainte-Foy QC G2E 3E8",
    "addr:housenumber":"2159",
    "addr:postcode":"g2e 3e8",
    "addr:street":"Av Notre-Dame",
    "iso:country":"CA",
    "sg:address":"2159 Av Notre-Dame",
    "sg:city":"Sainte-Foy",
    "sg:classifiers":[
        {
            "category":"Bars & Pubs",
            "type":"Food & Drink"
        }
    ],
    "sg:phone":"+1 418 872 4731",
    "sg:postcode":"G2E 3E8",
    "sg:province":"QC",
    "sg:tags":[
        "lounge",
        "cocktail"
    ],
    "wof:name":"Bulls Bistro",
    "wof:placetype":"venue"
},
  "geometry": {"coordinates":[-71.3736877441,46.8155975342],"type":"Point"}
}