{
  "type": "Feature",
  "properties": {
    "iso:country":"CA",
    "sg:address":"1931 Island Hwy",
    "sg:city":"Campbell River",
    "sg:classifiers":[
        {
            "category":"Wholesale",
            "subcategory":"Hardware",
            "type":"Manufacturing & Wholesale Goods"
        }
    ],
    "sg:phone":"+1 250 286 1060",
    "sg:postcode":"V9W 2G3",
    "sg:province":"BC",
    "sg:tags":[
        "tool"
    ],
    "wof:name":"House of Tools",
    "wof:placetype":"venue"
},
  "geometry": {"coordinates":[-125.27141571,50.0327072144],"type":"Point"}
}