{
  "type": "Feature",
  "properties": {
    "addr:full":"Aurora ON L4G 3M7",
    "addr:postcode":"l4g 3m7",
    "iso:country":"CA",
    "sg:city":"Aurora",
    "sg:classifiers":[
        {
            "category":"Health Services",
            "subcategory":"Chiropractor",
            "type":"Services"
        }
    ],
    "sg:phone":"+1 905 727 1817",
    "sg:postcode":"L4G 3M7",
    "sg:province":"ON",
    "wof:name":"Moore Chiropractic Group",
    "wof:placetype":"venue"
},
  "geometry": {"coordinates":[-79.462097,43.987064],"type":"Point"}
}