{
  "type": "Feature",
  "properties": {
    "addr:full":"250 Mtee Du Moulin Vercheres QC J0L 2R0",
    "addr:housenumber":"250",
    "addr:postcode":"j0l 2r0",
    "addr:street":"Mtee Du Moulin",
    "iso:country":"CA",
    "sg:address":"250 Mtee Du Moulin",
    "sg:city":"Vercheres",
    "sg:classifiers":[
        {
            "category":"Shopping",
            "subcategory":"Bicycles & Sporting Goods",
            "type":"Retail Goods"
        }
    ],
    "sg:phone":"+1 450 583 5600",
    "sg:postcode":"J0L 2R0",
    "sg:province":"QC",
    "wof:name":"Boutique DE Golf Daniel",
    "wof:placetype":"venue"
},
  "geometry": {"coordinates":[-73.357552,45.775921],"type":"Point"}
}