{
  "type": "Feature",
  "properties": {
    "addr:full":"1126 Cranbrook St N Cranbrook BC V1C 3S5",
    "addr:housenumber":"1126",
    "addr:postcode":"v1c 3s5",
    "addr:street":"Cranbrook St N",
    "iso:country":"CA",
    "sg:address":"1126 Cranbrook St N",
    "sg:city":"Cranbrook",
    "sg:classifiers":[
        {
            "category":"Autos & Motor Vehicles",
            "subcategory":"Automobile Sales",
            "type":"Retail Goods"
        }
    ],
    "sg:phone":"+1 250 426 6645",
    "sg:postcode":"V1C 3S5",
    "sg:province":"BC",
    "sg:tags":[
        "car",
        "dealer"
    ],
    "wof:name":"Millennium Ford Sales Ltd",
    "wof:placetype":"venue"
},
  "geometry": {"coordinates":[-115.756942749,49.5215415955],"type":"Point"}
}