{
  "type": "Feature",
  "properties": {
    "addr:full":"329 James St Shawville QC J0X 2Y0",
    "addr:housenumber":"329",
    "addr:postcode":"j0x 2y0",
    "addr:street":"James St",
    "iso:country":"CA",
    "sg:address":"329 James St",
    "sg:city":"Shawville",
    "sg:classifiers":[
        {
            "category":"Organizations",
            "subcategory":"Religious Organization",
            "type":"Services"
        }
    ],
    "sg:phone":"+1 819 647 2693",
    "sg:postcode":"J0X 2Y0",
    "sg:province":"QC",
    "sg:tags":[
        "church"
    ],
    "wof:name":"Wesleyan Church",
    "wof:placetype":"venue"
},
  "geometry": {"coordinates":[-76.490784,45.602764],"type":"Point"}
}