{
  "type": "Feature",
  "properties": {
    "addr:full":"117 Tycos Dr North York ON M6B 1W3",
    "addr:housenumber":"117",
    "addr:postcode":"m6b 1w3",
    "addr:street":"Tycos Dr",
    "iso:country":"CA",
    "sg:address":"117 Tycos Dr",
    "sg:city":"North York",
    "sg:classifiers":[
        {
            "category":"Wholesale",
            "subcategory":"Machinery & Supplies",
            "type":"Manufacturing & Wholesale Goods"
        }
    ],
    "sg:phone":"+1 416 789 7646",
    "sg:postcode":"M6B 1W3",
    "sg:province":"ON",
    "sg:tags":[
        "fan",
        "commercial"
    ],
    "wof:name":"Willow Manufacturing CO Ltd",
    "wof:placetype":"venue"
},
  "geometry": {"coordinates":[-79.45910600000001,43.704231],"type":"Point"}
}