{
  "type": "Feature",
  "properties": {
    "addr:full":"6482 Boul Sainte-Anne L'Ange Gardien QC G0A 2K0",
    "addr:housenumber":"6482",
    "addr:postcode":"g0a 2k0",
    "addr:street":"Boul Sainte-Anne",
    "iso:country":"CA",
    "sg:address":"6482 Boul Sainte-Anne",
    "sg:city":"L'Ange Gardien",
    "sg:classifiers":[
        {
            "category":"Autos & Motor Vehicles",
            "subcategory":"Recreational Vehicle Sales",
            "type":"Retail Goods"
        }
    ],
    "sg:phone":"+1 418 822 3737",
    "sg:postcode":"G0A 2K0",
    "sg:province":"QC",
    "wof:name":"Roulottes Desjardins Inc",
    "wof:placetype":"venue"
},
  "geometry": {"coordinates":[-72.93802599999999,45.35746],"type":"Point"}
}