{
  "type": "Feature",
  "properties": {
    "addr:full":"111 Erie Ave Brantford ON N3S 2G3",
    "addr:housenumber":"111",
    "addr:postcode":"n3s 2g3",
    "addr:street":"Erie Ave",
    "iso:country":"CA",
    "sg:address":"111 Erie Ave",
    "sg:city":"Brantford",
    "sg:classifiers":[
        {
            "category":"Health Services",
            "subcategory":"Health Practitioner",
            "type":"Services"
        }
    ],
    "sg:phone":"+1 519 770 3498",
    "sg:postcode":"N3S 2G3",
    "sg:province":"ON",
    "sg:tags":[
        "therapist",
        "massage",
        "physical"
    ],
    "wof:name":"Forever Changing Healthcare",
    "wof:placetype":"venue"
},
  "geometry": {"coordinates":[-80.258591,43.130428],"type":"Point"}
}