{
  "type": "Feature",
  "properties": {
    "addr:full":"3901 Boul Henri-Bourassa O Saint-Laurent QC H4L 1A1",
    "addr:housenumber":"3901",
    "addr:postcode":"h4l 1a1",
    "addr:street":"Boul Henri-Bourassa O",
    "iso:country":"CA",
    "sg:address":"3901 Boul Henri-Bourassa O",
    "sg:city":"Saint-Laurent",
    "sg:classifiers":[
        {
            "category":"Organizations",
            "subcategory":"Religious Organization",
            "type":"Services"
        }
    ],
    "sg:phone":"+1 514 336 2117",
    "sg:postcode":"H4L 1A1",
    "sg:province":"QC",
    "sg:tags":[
        "church"
    ],
    "wof:name":"Grace Gospal Hall",
    "wof:placetype":"venue"
},
  "geometry": {"coordinates":[-73.6952972412,45.5277442932],"type":"Point"}
}