{
  "type": "Feature",
  "properties": {
    "addr:full":"113 Cree Rd Sherwood Park AB T8A 3X9",
    "addr:housenumber":"113",
    "addr:postcode":"t8a 3x9",
    "addr:street":"Cree Rd",
    "iso:country":"CA",
    "sg:address":"113 Cree Rd",
    "sg:city":"Sherwood Park",
    "sg:classifiers":[
        {
            "category":"Retail",
            "subcategory":"Auto Repair",
            "type":"Services"
        }
    ],
    "sg:phone":"+1 780 467 7795",
    "sg:postcode":"T8A 3X9",
    "sg:province":"AB",
    "sg:tags":[
        "wrecker"
    ],
    "wof:name":"Double L Towing",
    "wof:placetype":"venue"
},
  "geometry": {"coordinates":[-113.32893371599999,53.5369911194],"type":"Point"}
}