{
  "type": "Feature",
  "properties": {
    "addr:full":"Lac-Etchemin QC G0R 1S0",
    "addr:postcode":"g0r 1s0",
    "iso:country":"CA",
    "sg:city":"Lac-Etchemin",
    "sg:classifiers":[
        {
            "category":"Building & Trades",
            "subcategory":"Electrical",
            "type":"Services"
        }
    ],
    "sg:phone":"+1 418 625 2742",
    "sg:postcode":"G0R 1S0",
    "sg:province":"QC",
    "sg:tags":[
        "electric",
        "contractor"
    ],
    "wof:name":"9028-7046 Quebec Inc",
    "wof:placetype":"venue"
},
  "geometry": {"coordinates":[-70.514595,46.399471],"type":"Point"}
}