{
  "type": "Feature",
  "properties": {
    "addr:full":"730 Yonge St Toronto ON M4Y 2B7",
    "addr:housenumber":"730",
    "addr:postcode":"m4y 2b7",
    "addr:street":"Yonge St",
    "iso:country":"CA",
    "sg:address":"730 Yonge St",
    "sg:city":"Toronto",
    "sg:classifiers":[
        {
            "category":"Professional",
            "subcategory":"Lawyer & Legal Services",
            "type":"Services"
        }
    ],
    "sg:phone":"+1 416 924 6220",
    "sg:postcode":"M4Y 2B7",
    "sg:province":"ON",
    "sg:tags":[
        "attorney"
    ],
    "wof:name":"Hackett, Bryan D",
    "wof:placetype":"venue"
},
  "geometry": {"coordinates":[-79.3862457275,43.6687927246],"type":"Point"}
}