{
  "type": "Feature",
  "properties": {
    "addr:full":"410 1st Ave Pine River MB R0L 1M0",
    "addr:housenumber":"410",
    "addr:postcode":"r0l 1m0",
    "addr:street":"1St Ave",
    "iso:country":"CA",
    "sg:address":"410 1st Ave",
    "sg:city":"Pine River",
    "sg:classifiers":[
        {
            "category":"Food & Beverages",
            "subcategory":"Liquor & Beverages",
            "type":"Retail Goods"
        }
    ],
    "sg:phone":"+1 204 263 2108",
    "sg:postcode":"R0L 1M0",
    "sg:province":"MB",
    "sg:tags":[
        "store"
    ],
    "wof:name":"Semeniuk Lucky Dollar",
    "wof:placetype":"venue"
},
  "geometry": {"coordinates":[-100.530914307,51.7842597961],"type":"Point"}
}