{
  "type": "Feature",
  "properties": {
    "addr:full":"140 Main St Lewisporte NL A0G 3A0",
    "addr:housenumber":"140",
    "addr:postcode":"a0g 3a0",
    "addr:street":"Main St",
    "iso:country":"CA",
    "sg:address":"140 Main St",
    "sg:city":"Lewisporte",
    "sg:classifiers":[
        {
            "category":"Bars & Pubs",
            "type":"Food & Drink"
        }
    ],
    "sg:phone":"+1 709 535 3427",
    "sg:postcode":"A0G 3A0",
    "sg:province":"NL",
    "sg:tags":[
        "lounge",
        "cocktail"
    ],
    "wof:name":"Blue Finn Lounge",
    "wof:placetype":"venue"
},
  "geometry": {"coordinates":[-55.0599365234,49.2417984009],"type":"Point"}
}