{
  "type": "Feature",
  "properties": {
    "addr:full":"1052 Northside Dr Minto NB E4B 3H7",
    "addr:housenumber":"1052",
    "addr:postcode":"e4b 3h7",
    "addr:street":"Northside Dr",
    "iso:country":"CA",
    "sg:address":"1052 Northside Dr",
    "sg:city":"Minto",
    "sg:classifiers":[
        {
            "category":"Social Services",
            "subcategory":"Child Care",
            "type":"Services"
        }
    ],
    "sg:phone":"+1 506 327 4551",
    "sg:postcode":"E4B 3H7",
    "sg:province":"NB",
    "wof:name":"Early World of Learning Day",
    "wof:placetype":"venue"
},
  "geometry": {"coordinates":[-66.06006622309999,46.1100997925],"type":"Point"}
}