{
  "type": "Feature",
  "properties": {
    "addr:full":"Powell River BC V8A 5K9",
    "addr:postcode":"v8a 5k9",
    "iso:country":"CA",
    "sg:city":"Powell River",
    "sg:classifiers":[
        {
            "category":"Food & Beverages",
            "subcategory":"Liquor & Beverages",
            "type":"Retail Goods"
        }
    ],
    "sg:phone":"+1 604 485 6311",
    "sg:postcode":"V8A 5K9",
    "sg:province":"BC",
    "sg:tags":[
        "store"
    ],
    "wof:name":"Liquor Store-Government",
    "wof:placetype":"venue"
},
  "geometry": {"coordinates":[-124.51841,49.846344],"type":"Point"}
}