{
  "type": "Feature",
  "properties": {
    "addr:full":"1231 Peoples Rd Sault Ste Marie ON P6C 3W7",
    "addr:housenumber":"1231",
    "addr:postcode":"p6c 3w7",
    "addr:street":"Peoples Rd",
    "iso:country":"CA",
    "sg:address":"1231 Peoples Rd",
    "sg:city":"Sault Ste Marie",
    "sg:classifiers":[
        {
            "category":"Building & Trades",
            "subcategory":"Plumbing",
            "type":"Services"
        }
    ],
    "sg:phone":"+1 705 759 5148",
    "sg:postcode":"P6C 3W7",
    "sg:province":"ON",
    "sg:tags":[
        "mechanical",
        "contractor"
    ],
    "wof:name":"Superior Industrial Svc",
    "wof:placetype":"venue"
},
  "geometry": {"coordinates":[-84.35159299999999,46.553635],"type":"Point"}
}