{
  "type": "Feature",
  "properties": {
    "addr:full":"1279 Loudoun Rd Winnipeg MB R3S 1A3",
    "addr:housenumber":"1279",
    "addr:postcode":"r3s 1a3",
    "addr:street":"Loudoun Rd",
    "iso:country":"CA",
    "sg:address":"1279 Loudoun Rd",
    "sg:city":"Winnipeg",
    "sg:classifiers":[
        {
            "category":"Building & Trades",
            "subcategory":"Construction",
            "type":"Services"
        }
    ],
    "sg:phone":"+1 204 895 9594",
    "sg:postcode":"R3S 1A3",
    "sg:province":"MB",
    "sg:tags":[
        "boring",
        "drilling",
        "contractor"
    ],
    "wof:name":"Cambrian Blasting CO Ltd",
    "wof:placetype":"venue"
},
  "geometry": {"coordinates":[-97.25556182859999,49.8394088745],"type":"Point"}
}