{
  "type": "Feature",
  "properties": {
    "iso:country":"CA",
    "sg:address":"1279 Loudoun Rd",
    "sg:city":"Winnipeg",
    "sg:classifiers":[
        {
            "category":"Building & Trades",
            "subcategory":"Construction",
            "type":"Services"
        }
    ],
    "sg:phone":"+1 204 895 9594",
    "sg:postcode":"R3S 1A3",
    "sg:province":"MB",
    "sg:tags":[
        "boring",
        "drilling",
        "contractor"
    ],
    "wof:name":"Cambrian Blasting CO Ltd",
    "wof:placetype":"venue"
},
  "geometry": {"coordinates":[-97.25556182859999,49.8394088745],"type":"Point"}
}