{
  "type": "Feature",
  "properties": {
    "addr:full":"216 39 Ave NE Calgary AB T2E 2M5",
    "addr:postcode":"t2e 2m5",
    "addr:street":"216 39 Ave Ne",
    "iso:country":"CA",
    "sg:address":"216 39 Ave NE",
    "sg:city":"Calgary",
    "sg:classifiers":[
        {
            "category":"Building & Trades",
            "subcategory":"Electrical",
            "type":"Services"
        }
    ],
    "sg:phone":"+1 403 250 8888",
    "sg:postcode":"T2E 2M5",
    "sg:province":"AB",
    "sg:tags":[
        "communications",
        "contractor"
    ],
    "wof:name":"W P Telectronics Ltd",
    "wof:placetype":"venue"
},
  "geometry": {"coordinates":[-114.059265137,51.087890625],"type":"Point"}
}