{
  "type": "Feature",
  "properties": {
    "addr:full":"Montreal QC H2E 2H4",
    "addr:postcode":"h2e 2h4",
    "iso:country":"CA",
    "sg:city":"Montreal",
    "sg:classifiers":[
        {
            "category":"Professional",
            "subcategory":"Accounting & Tax Preparation",
            "type":"Services"
        }
    ],
    "sg:phone":"+1 514 374 0137",
    "sg:postcode":"H2E 2H4",
    "sg:province":"QC",
    "sg:tags":[
        "accountant"
    ],
    "wof:name":"J B Colas & Assoc",
    "wof:placetype":"venue"
},
  "geometry": {"coordinates":[-73.6147155762,45.5515022278],"type":"Point"}
}