{
  "type": "Feature",
  "properties": {
    "addr:full":"PO Box 115 Rainier AB T0J 2M0",
    "addr:housenumber":"po;115",
    "addr:postcode":"t0j 2m0",
    "addr:street":"Box",
    "iso:country":"CA",
    "sg:address":"PO Box 115",
    "sg:city":"Rainier",
    "sg:classifiers":[
        {
            "category":"Retail",
            "subcategory":"Repair Shop",
            "type":"Services"
        }
    ],
    "sg:phone":"+1 403 362 2165",
    "sg:postcode":"T0J 2M0",
    "sg:province":"AB",
    "sg:tags":[
        "upholsterer"
    ],
    "wof:name":"Bob's Upholstery",
    "wof:placetype":"venue"
},
  "geometry": {"coordinates":[-112.030059815,50.367931366],"type":"Point"}
}