{
  "type": "Feature",
  "properties": {
    "addr:full":"6988 St Clair Rd E Pointe Aux Roches ON N0R 1N0",
    "addr:housenumber":"6988",
    "addr:postcode":"n0r 1n0",
    "addr:street":"St Clair Rd E Pointe Aux Roches",
    "iso:country":"CA",
    "sg:address":"6988 St Clair Rd E",
    "sg:city":"Pointe Aux Roches",
    "sg:classifiers":[
        {
            "category":"Recreation",
            "subcategory":"Marina",
            "type":"Entertainment"
        }
    ],
    "sg:phone":"+1 519 798 5757",
    "sg:postcode":"N0R 1N0",
    "sg:province":"ON",
    "wof:name":"Stoney Point Marina",
    "wof:placetype":"venue"
},
  "geometry": {"coordinates":[-82.547844,42.313957],"type":"Point"}
}