{
  "type": "Feature",
  "properties": {
    "addr:full":"Victoria BC V8V 3H7",
    "addr:postcode":"v8v 3h7",
    "iso:country":"CA",
    "sg:city":"Victoria",
    "sg:classifiers":[
        {
            "category":"Real Estate",
            "subcategory":"Real Estate Operator",
            "type":"Services"
        }
    ],
    "sg:phone":"+1 250 361 0924",
    "sg:postcode":"V8V 3H7",
    "sg:province":"BC",
    "sg:tags":[
        "apartment"
    ],
    "wof:name":"Rockmeare Manor",
    "wof:placetype":"venue"
},
  "geometry": {"coordinates":[-123.352745056,48.4219284058],"type":"Point"}
}