{
  "type": "Feature",
  "properties": {
    "addr:full":"82 Summerhill Ave Toronto ON M4T 1A8",
    "addr:housenumber":"82",
    "addr:postcode":"m4t 1a8",
    "addr:street":"Summerhill Ave",
    "iso:country":"CA",
    "sg:address":"82 Summerhill Ave",
    "sg:city":"Toronto",
    "sg:classifiers":[
        {
            "category":"Travel",
            "subcategory":"Travel Agent",
            "type":"Entertainment"
        }
    ],
    "sg:phone":"+1 416 972 9820",
    "sg:postcode":"M4T 1A8",
    "sg:province":"ON",
    "sg:tags":[
        "agency",
        "bureau"
    ],
    "wof:name":"Worldwide Travel Management",
    "wof:placetype":"venue"
},
  "geometry": {"coordinates":[-79.38911400000001,43.68383],"type":"Point"}
}