{
  "type": "Feature",
  "properties": {
    "addr:full":"20 Cudmore Cres The Pas MB R9A 1L1",
    "addr:housenumber":"20",
    "addr:postcode":"r9a 1l1",
    "addr:street":"Cudmore Cres",
    "iso:country":"CA",
    "sg:address":"20 Cudmore Cres",
    "sg:city":"The Pas",
    "sg:classifiers":[
        {
            "category":"Shopping",
            "type":"Retail Goods"
        }
    ],
    "sg:phone":"+1 204 623 3790",
    "sg:postcode":"R9A 1L1",
    "sg:province":"MB",
    "sg:tags":[
        "picture",
        "frame"
    ],
    "wof:name":"Framed Expressions",
    "wof:placetype":"venue"
},
  "geometry": {"coordinates":[-101.23967,53.816151],"type":"Point"}
}