{
  "type": "Feature",
  "properties": {
    "addr:full":"28 Sandiford Dr Stouffville ON L4A 7X5",
    "addr:housenumber":"28",
    "addr:postcode":"l4a 7x5",
    "addr:street":"Sandiford Dr",
    "iso:country":"CA",
    "sg:address":"28 Sandiford Dr",
    "sg:city":"Stouffville",
    "sg:classifiers":[
        {
            "category":"Personal",
            "subcategory":"Beauty Salon",
            "type":"Services"
        }
    ],
    "sg:phone":"+1 905 640 8655",
    "sg:postcode":"L4A 7X5",
    "sg:province":"ON",
    "wof:name":"Salon 2000",
    "wof:placetype":"venue"
},
  "geometry": {"coordinates":[-79.27022599999999,43.965416],"type":"Point"}
}