{
  "type": "Feature",
  "properties": {
    "addr:full":"Mackenzie BC V0J 2C0",
    "addr:postcode":"v0j 2c0",
    "iso:country":"CA",
    "sg:city":"Mackenzie",
    "sg:classifiers":[
        {
            "category":"Retail",
            "subcategory":"Laundry & Dry Cleaning",
            "type":"Services"
        }
    ],
    "sg:phone":"+1 250 997 4712",
    "sg:postcode":"V0J 2C0",
    "sg:province":"BC",
    "sg:tags":[
        "cleaners"
    ],
    "wof:name":"Mac Kenzie Drycleaning",
    "wof:placetype":"venue"
},
  "geometry": {"coordinates":[-123.094680786,55.3351173401],"type":"Point"}
}