{
  "type": "Feature",
  "properties": {
    "addr:full":"3687 Arbutus St Vancouver BC V6J 3Z7",
    "addr:housenumber":"3687",
    "addr:postcode":"v6j 3z7",
    "addr:street":"Arbutus St",
    "iso:country":"CA",
    "sg:address":"3687 Arbutus St",
    "sg:city":"Vancouver",
    "sg:classifiers":[
        {
            "category":"Building & Trades",
            "subcategory":"Plumbing",
            "type":"Services"
        }
    ],
    "sg:phone":"+1 604 738 2923",
    "sg:postcode":"V6J 3Z7",
    "sg:province":"BC",
    "sg:tags":[
        "contractor"
    ],
    "wof:name":"A Alfa W Plumbing & Heating",
    "wof:placetype":"venue"
},
  "geometry": {"coordinates":[-123.15321400000001,49.253677],"type":"Point"}
}