{
  "type": "Feature",
  "properties": {
    "addr:full":"41 East Main St Welland ON L3B 3W4",
    "addr:housenumber":"41",
    "addr:postcode":"l3b 3w4",
    "addr:street":"East Main St",
    "iso:country":"CA",
    "sg:address":"41 East Main St",
    "sg:city":"Welland",
    "sg:classifiers":[
        {
            "category":"Banks & Credit Unions",
            "subcategory":"Bank",
            "type":"Services"
        }
    ],
    "sg:phone":"+1 905 735 7910",
    "sg:postcode":"L3B 3W4",
    "sg:province":"ON",
    "wof:name":"Royal Bank Financial Group",
    "wof:placetype":"venue"
},
  "geometry": {"coordinates":[-79.249504,42.991737],"type":"Point"}
}