{
  "type": "Feature",
  "properties": {
    "addr:full":"9280 No. 2 Rd Richmond BC V7E 2C8",
    "addr:postcode":"9280;v7e 2c8",
    "addr:street":"2 Rd",
    "iso:country":"CA",
    "sg:address":"9280 No. 2 Rd",
    "sg:city":"Richmond",
    "sg:classifiers":[
        {
            "category":"Organizations",
            "subcategory":"Religious Organization",
            "type":"Services"
        }
    ],
    "sg:phone":"+1 604 277 2326",
    "sg:postcode":"V7E 2C8",
    "sg:province":"BC",
    "sg:tags":[
        "church"
    ],
    "wof:name":"Christian Reformed Churches",
    "wof:placetype":"venue"
},
  "geometry": {"coordinates":[-123.158691,49.145691],"type":"Point"}
}