{
  "type": "Feature",
  "properties": {
    "addr:full":"RR 4 STN Main Pembroke ON K8A 6W5",
    "addr:postcode":"k8a 6w5",
    "addr:street":"Rr 4 Stn Main",
    "iso:country":"CA",
    "sg:address":"RR 4 STN Main",
    "sg:city":"Pembroke",
    "sg:classifiers":[
        {
            "category":"Recreation",
            "type":"Entertainment"
        }
    ],
    "sg:phone":"+1 613 735 6457",
    "sg:postcode":"K8A 6W5",
    "sg:province":"ON",
    "sg:tags":[
        "club",
        "hall",
        "auditorium"
    ],
    "wof:name":"Timberline Snow Mobile Club",
    "wof:placetype":"venue"
},
  "geometry": {"coordinates":[-77.112213,45.826481],"type":"Point"}
}