{
  "type": "Feature",
  "properties": {
    "addr:full":"Embrun ON K0A 1W1",
    "addr:postcode":"k0a 1w1",
    "iso:country":"CA",
    "sg:city":"Embrun",
    "sg:classifiers":[
        {
            "category":"Building & Trades",
            "subcategory":"Plumbing",
            "type":"Services"
        }
    ],
    "sg:phone":"+1 613 746 0516",
    "sg:postcode":"K0A 1W1",
    "sg:province":"ON",
    "sg:tags":[
        "conditioning",
        "air",
        "system",
        "contractor"
    ],
    "wof:name":"Castor Heating & Cooling Ltd",
    "wof:placetype":"venue"
},
  "geometry": {"coordinates":[-75.30864699999999,45.268204],"type":"Point"}
}