{
  "type": "Feature",
  "properties": {
    "addr:full":"9181 Main St # 214 Chilliwack BC V2P 4M9",
    "addr:housenumber":"9181",
    "addr:postcode":"v2p 4m9",
    "addr:street":"Main St # 214",
    "iso:country":"CA",
    "sg:address":"9181 Main St # 214",
    "sg:city":"Chilliwack",
    "sg:classifiers":[
        {
            "category":"Health Services",
            "subcategory":"Doctor",
            "type":"Services"
        }
    ],
    "sg:phone":"+1 604 795 0084",
    "sg:postcode":"V2P 4M9",
    "sg:province":"BC",
    "sg:tags":[
        "physician",
        "surgeon"
    ],
    "wof:name":"Ryan, Clive MD",
    "wof:placetype":"venue"
},
  "geometry": {"coordinates":[-121.95697784399999,49.1691093445],"type":"Point"}
}