{
  "type": "Feature",
  "properties": {
    "iso:country":"CA",
    "sg:city":"Toronto",
    "sg:classifiers":[
        {
            "category":"Health Services",
            "subcategory":"Doctor",
            "type":"Services"
        }
    ],
    "sg:phone":"+1 416 925 2408",
    "sg:postcode":"M5S 1X2",
    "sg:province":"ON",
    "sg:tags":[
        "dentist"
    ],
    "wof:name":"Yoon, Choong Tae DDS",
    "wof:placetype":"venue"
},
  "geometry": {"coordinates":[-79.405487,43.666389],"type":"Point"}
}