{
  "type": "Feature",
  "properties": {
    "addr:full":"36 Meteor Dr Etobicoke ON M9W 1A4",
    "addr:housenumber":"36",
    "addr:postcode":"m9w 1a4",
    "addr:street":"Meteor Dr",
    "iso:country":"CA",
    "sg:address":"36 Meteor Dr",
    "sg:city":"Etobicoke",
    "sg:classifiers":[
        {
            "category":"Professional",
            "subcategory":"Research",
            "type":"Services"
        }
    ],
    "sg:phone":"+1 416 674 9500",
    "sg:postcode":"M9W 1A4",
    "sg:province":"ON",
    "sg:tags":[
        "development",
        "laboratory"
    ],
    "wof:name":"Umedik Inc",
    "wof:placetype":"venue"
},
  "geometry": {"coordinates":[-79.5912857056,43.6813240051],"type":"Point"}
}