{
  "type": "Feature",
  "properties": {
    "iso:country":"CA",
    "sg:city":"Fairview",
    "sg:classifiers":[
        {
            "category":"Personal",
            "subcategory":"Beauty Salon",
            "type":"Services"
        }
    ],
    "sg:phone":"+1 780 835 5880",
    "sg:postcode":"T0H 1L0",
    "sg:province":"AB",
    "wof:name":"Roots Hair Design",
    "wof:placetype":"venue"
},
  "geometry": {"coordinates":[-118.384170532,56.0657958984],"type":"Point"}
}