{
  "type": "Feature",
  "properties": {
    "addr:full":"9750 74 Ave NW Edmonton AB T6E 1E8",
    "addr:housenumber":"9750",
    "addr:postcode":"t6e 1e8",
    "addr:street":"74 Ave Nw",
    "iso:country":"CA",
    "sg:address":"9750 74 Ave NW",
    "sg:city":"Edmonton",
    "sg:classifiers":[
        {
            "category":"Education",
            "subcategory":"School",
            "type":"Public Place"
        }
    ],
    "sg:phone":"+1 780 433 1553",
    "sg:postcode":"T6E 1E8",
    "sg:province":"AB",
    "wof:name":"Ritchie Junior High School",
    "wof:placetype":"venue"
},
  "geometry": {"coordinates":[-113.48284099999999,53.510429],"type":"Point"}
}