{
  "type": "Feature",
  "properties": {
    "addr:full":"46 Princess St Saint John NB E2L 1K2",
    "addr:housenumber":"46",
    "addr:postcode":"e2l 1k2",
    "addr:street":"Princess St",
    "iso:country":"CA",
    "sg:address":"46 Princess St",
    "sg:city":"Saint John",
    "sg:classifiers":[
        {
            "category":"Bars & Pubs",
            "type":"Food & Drink"
        }
    ],
    "sg:phone":"+1 506 634 7135",
    "sg:postcode":"E2L 1K2",
    "sg:province":"NB",
    "wof:name":"O'Leary's",
    "wof:placetype":"venue"
},
  "geometry": {"coordinates":[-66.0610961914,45.2713088989],"type":"Point"}
}