{
  "type": "Feature",
  "properties": {
    "addr:full":"1186 Bank St Ottawa ON K1S 3X9",
    "addr:housenumber":"1186",
    "addr:postcode":"k1s 3x9",
    "addr:street":"Bank St",
    "iso:country":"CA",
    "sg:address":"1186 Bank St",
    "sg:city":"Ottawa",
    "sg:classifiers":[
        {
            "category":"Bars & Pubs",
            "type":"Food & Drink"
        }
    ],
    "sg:phone":"+1 613 730 2434",
    "sg:postcode":"K1S 3X9",
    "sg:province":"ON",
    "wof:name":"Patty's Pub",
    "wof:placetype":"venue"
},
  "geometry": {"coordinates":[-75.681709,45.391953],"type":"Point"}
}