{
  "type": "Feature",
  "properties": {
    "addr:full":"NW 17-11-12E Whitemouth MB R0E 2G0",
    "addr:postcode":"17-11-12e;r0e 2g0",
    "addr:street":"Nw",
    "iso:country":"CA",
    "sg:address":"NW 17-11-12E",
    "sg:city":"Whitemouth",
    "sg:classifiers":[
        {
            "category":"Building & Trades",
            "subcategory":"Construction",
            "type":"Services"
        }
    ],
    "sg:phone":"+1 204 348 2722",
    "sg:postcode":"R0E 2G0",
    "sg:province":"MB",
    "sg:tags":[
        "woodworker"
    ],
    "wof:name":"Elma Custom Woodworks",
    "wof:placetype":"venue"
},
  "geometry": {"coordinates":[-95.9650268555,49.9411659241],"type":"Point"}
}