{
  "type": "Feature",
  "properties": {
    "addr:full":"55 Duncan St Winnipeg MB R3B 0Y5",
    "addr:housenumber":"55",
    "addr:postcode":"r3b 0y5",
    "addr:street":"Duncan St",
    "iso:country":"CA",
    "sg:address":"55 Duncan St",
    "sg:city":"Winnipeg",
    "sg:classifiers":[
        {
            "category":"Organizations",
            "subcategory":"Professional Association",
            "type":"Services"
        }
    ],
    "sg:phone":"+1 204 943 1162",
    "sg:postcode":"R3B 0Y5",
    "sg:province":"MB",
    "sg:tags":[
        "club"
    ],
    "wof:name":"Sportsplex",
    "wof:placetype":"venue"
},
  "geometry": {"coordinates":[-97.13091300000001,49.900948],"type":"Point"}
}