{
  "type": "Feature",
  "properties": {
    "addr:full":"517 Powell Rd Whitby ON L1N 2H5",
    "addr:housenumber":"517",
    "addr:postcode":"l1n 2h5",
    "addr:street":"Powell Rd",
    "iso:country":"CA",
    "sg:address":"517 Powell Rd",
    "sg:city":"Whitby",
    "sg:classifiers":[
        {
            "category":"Health Services",
            "subcategory":"Medical Lab",
            "type":"Services"
        }
    ],
    "sg:phone":"+1 905 725 4652",
    "sg:postcode":"L1N 2H5",
    "sg:province":"ON",
    "sg:tags":[
        "laboratory"
    ],
    "wof:name":"Mc O Dental Technology Svc",
    "wof:placetype":"venue"
},
  "geometry": {"coordinates":[-78.8960266113,43.8808784485],"type":"Point"}
}