{
  "type": "Feature",
  "properties": {
    "addr:full":"RR 2 Pickardville AB T0G 1W0",
    "addr:postcode":"t0g 1w0",
    "addr:street":"Rr 2",
    "iso:country":"CA",
    "sg:address":"RR 2",
    "sg:city":"Pickardville",
    "sg:classifiers":[
        {
            "category":"Freight",
            "type":"Transportation"
        }
    ],
    "sg:phone":"+1 780 349 5730",
    "sg:postcode":"T0G 1W0",
    "sg:province":"AB",
    "sg:tags":[
        "trucking"
    ],
    "wof:name":"Hay Exchange",
    "wof:placetype":"venue"
},
  "geometry": {"coordinates":[-113.880043,54.052536],"type":"Point"}
}