{
  "type": "Feature",
  "properties": {
    "iso:country":"CA",
    "sg:address":"39 King George Rd",
    "sg:city":"Brantford",
    "sg:classifiers":[
        {
            "category":"Real Estate",
            "subcategory":"Real Estate Agent",
            "type":"Services"
        }
    ],
    "sg:phone":"+1 519 759 5494",
    "sg:postcode":"N3R 5K2",
    "sg:province":"ON",
    "wof:name":"Re/Max Twin City Realty Inc",
    "wof:placetype":"venue"
},
  "geometry": {"coordinates":[-80.2745056152,43.1640090942],"type":"Point"}
}