{
  "type": "Feature",
  "properties": {
    "iso:country":"CA",
    "sg:address":"152 Bancroft St",
    "sg:city":"Hamilton",
    "sg:classifiers":[
        {
            "category":"Manufacturing",
            "subcategory":"Motor Vehicles & Parts",
            "type":"Manufacturing & Wholesale Goods"
        }
    ],
    "sg:phone":"+1 905 560 3523",
    "sg:postcode":"L8E 2W6",
    "sg:province":"ON",
    "sg:tags":[
        "automobile"
    ],
    "wof:name":"G G Motor Ctr Ltd",
    "wof:placetype":"venue"
},
  "geometry": {"coordinates":[-79.76141357420001,43.241733551],"type":"Point"}
}