{
  "type": "Feature",
  "properties": {
    "addr:full":"1485 Rue Tardif Brossard QC J4W 2M4",
    "addr:housenumber":"1485",
    "addr:postcode":"j4w 2m4",
    "addr:street":"Rue Tardif",
    "iso:country":"CA",
    "sg:address":"1485 Rue Tardif",
    "sg:city":"Brossard",
    "sg:classifiers":[
        {
            "category":"Wholesale",
            "subcategory":"Durable Goods & Equipment",
            "type":"Manufacturing & Wholesale Goods"
        }
    ],
    "sg:phone":"+1 450 923 3434",
    "sg:postcode":"J4W 2M4",
    "sg:province":"QC",
    "sg:tags":[
        "exporter"
    ],
    "wof:name":"Agro-Haribec Inc",
    "wof:placetype":"venue"
},
  "geometry": {"coordinates":[-73.480225,45.457535],"type":"Point"}
}