{
  "type": "Feature",
  "properties": {
    "addr:full":"134 Rue Degrace Shippagan NB E8S 1H5",
    "addr:housenumber":"134",
    "addr:postcode":"e8s 1h5",
    "addr:street":"Rue Degrace Shippagan",
    "iso:country":"CA",
    "sg:address":"134 Rue Degrace",
    "sg:city":"Shippagan",
    "sg:classifiers":[
        {
            "category":"Personal",
            "subcategory":"Barber",
            "type":"Services"
        }
    ],
    "sg:phone":"+1 506 336 2724",
    "sg:postcode":"E8S 1H5",
    "sg:province":"NB",
    "wof:name":"Salon Barbier Claire",
    "wof:placetype":"venue"
},
  "geometry": {"coordinates":[-64.71272277830001,47.7457427979],"type":"Point"}
}