{
  "type": "Feature",
  "properties": {
    "addr:full":"354 Princess Ave London ON N6B 2A8",
    "addr:housenumber":"354",
    "addr:postcode":"n6b 2a8",
    "addr:street":"Princess Ave",
    "iso:country":"CA",
    "sg:address":"354 Princess Ave",
    "sg:city":"London",
    "sg:classifiers":[
        {
            "category":"Professional",
            "subcategory":"Computer Services",
            "type":"Services"
        }
    ],
    "sg:phone":"+1 519 434 9936",
    "sg:postcode":"N6B 2A8",
    "sg:province":"ON",
    "wof:name":"Gordon Ruth & CO Ltd",
    "wof:placetype":"venue"
},
  "geometry": {"coordinates":[-81.24417099999999,42.989925],"type":"Point"}
}