{
  "type": "Feature",
  "properties": {
    "addr:full":"14 Victoria Thedford ON N0M 2N0",
    "addr:housenumber":"14",
    "addr:postcode":"n0m 2n0",
    "addr:street":"Victoria Thedford",
    "iso:country":"CA",
    "sg:address":"14 Victoria",
    "sg:city":"Thedford",
    "sg:classifiers":[
        {
            "category":"Health Services",
            "subcategory":"Nursing And Care Facility",
            "type":"Services"
        }
    ],
    "sg:phone":"+1 519 296 5715",
    "sg:postcode":"N0M 2N0",
    "sg:province":"ON",
    "sg:tags":[
        "home",
        "retirement",
        "community"
    ],
    "wof:name":"Country Manor Retirement Fclty",
    "wof:placetype":"venue"
},
  "geometry": {"coordinates":[-81.853088,43.162815],"type":"Point"}
}