{
  "type": "Feature",
  "properties": {
    "addr:full":"35 Brook St Port Perry ON L9L 1B5",
    "addr:housenumber":"35",
    "addr:postcode":"l9l 1b5",
    "addr:street":"Brook St",
    "iso:country":"CA",
    "sg:address":"35 Brook St",
    "sg:city":"Port Perry",
    "sg:classifiers":[
        {
            "category":"Retail",
            "subcategory":"Auto Repair",
            "type":"Services"
        }
    ],
    "sg:phone":"+1 905 985 8486",
    "sg:postcode":"L9L 1B5",
    "sg:province":"ON",
    "sg:tags":[
        "truck"
    ],
    "wof:name":"Jerry's Truck Svc",
    "wof:placetype":"venue"
},
  "geometry": {"coordinates":[-78.981651,44.079979],"type":"Point"}
}