{
  "type": "Feature",
  "properties": {
    "iso:country":"CA",
    "sg:address":"558 Queenston Rd",
    "sg:city":"Hamilton",
    "sg:classifiers":[
        {
            "category":"Autos & Motor Vehicles",
            "subcategory":"Auto Supplies",
            "type":"Retail Goods"
        }
    ],
    "sg:phone":"+1 905 560 9033",
    "sg:postcode":"L8K 1K2",
    "sg:province":"ON",
    "sg:tags":[
        "tire"
    ],
    "wof:name":"Active Green & Ross Tire Ctr",
    "wof:placetype":"venue"
},
  "geometry": {"coordinates":[-79.7777099609,43.2307662964],"type":"Point"}
}