{
  "type": "Feature",
  "properties": {
    "iso:country":"CA",
    "sg:address":"83 Gibson Rd",
    "sg:city":"North Bay",
    "sg:classifiers":[
        {
            "category":"Retail",
            "subcategory":"Auto Repair",
            "type":"Services"
        }
    ],
    "sg:phone":"+1 705 495 2689",
    "sg:postcode":"P1B 8Z4",
    "sg:province":"ON",
    "sg:tags":[
        "body",
        "automobile",
        "painting"
    ],
    "wof:name":"City Centre Collision Inc",
    "wof:placetype":"venue"
},
  "geometry": {"coordinates":[-79.404427,46.268337],"type":"Point"}
}