{
  "type": "Feature",
  "properties": {
    "addr:full":"3560 Lobsinger Line St Clements ON N0B 2M0",
    "addr:housenumber":"3560",
    "addr:postcode":"n0b 2m0",
    "addr:street":"Lobsinger Line St Clements",
    "iso:country":"CA",
    "sg:address":"3560 Lobsinger Line",
    "sg:city":"St Clements",
    "sg:classifiers":[
        {
            "category":"Building & Trades",
            "subcategory":"Landscaping Services",
            "type":"Services"
        }
    ],
    "sg:phone":"+1 519 699 5043",
    "sg:postcode":"N0B 2M0",
    "sg:province":"ON",
    "sg:tags":[
        "landscape",
        "contractor"
    ],
    "wof:name":"J & J Craftsmen",
    "wof:placetype":"venue"
},
  "geometry": {"coordinates":[-80.651093,43.522865],"type":"Point"}
}