{
  "type": "Feature",
  "properties": {
    "addr:full":"2984 Rue Sainte-Emilie Jonquiere QC G7S 4M3",
    "addr:housenumber":"2984",
    "addr:postcode":"g7s 4m3",
    "addr:street":"Rue Sainte-Emilie",
    "iso:country":"CA",
    "sg:address":"2984 Rue Sainte-Emilie",
    "sg:city":"Jonquiere",
    "sg:classifiers":[
        {
            "category":"Food & Beverages",
            "subcategory":"Groceries & Convenience Stores",
            "type":"Retail Goods"
        }
    ],
    "sg:phone":"+1 418 548 3092",
    "sg:postcode":"G7S 4M3",
    "sg:province":"QC",
    "sg:tags":[
        "grocer"
    ],
    "wof:name":"Depanneur Gino Enr",
    "wof:placetype":"venue"
},
  "geometry": {"coordinates":[-71.19203186039999,48.4152030945],"type":"Point"}
}