{
  "type": "Feature",
  "properties": {
    "iso:country":"CA",
    "sg:address":"70 James St",
    "sg:city":"St Catharines",
    "sg:classifiers":[
        {
            "category":"Food & Beverages",
            "subcategory":"Bakery",
            "type":"Retail Goods"
        }
    ],
    "sg:phone":"+1 905 687 9996",
    "sg:postcode":"L2R 5C1",
    "sg:province":"ON",
    "sg:tags":[
        "tea",
        "coffee",
        "doughnut"
    ],
    "wof:name":"Tim Hortons",
    "wof:placetype":"venue"
},
  "geometry": {"coordinates":[-79.245667,43.159225],"type":"Point"}
}