{
  "type": "Feature",
  "properties": {
    "addr:full":"29 Ferguson St Picton ON K0K 2T0",
    "addr:housenumber":"29",
    "addr:postcode":"k0k 2t0",
    "addr:street":"Ferguson St",
    "iso:country":"CA",
    "sg:address":"29 Ferguson St",
    "sg:city":"Picton",
    "sg:classifiers":[
        {
            "category":"Organizations",
            "subcategory":"Religious Organization",
            "type":"Services"
        }
    ],
    "sg:phone":"+1 613 476 7347",
    "sg:postcode":"K0K 2T0",
    "sg:province":"ON",
    "wof:name":"Gospel Crusade of Canada",
    "wof:placetype":"venue"
},
  "geometry": {"coordinates":[-77.145447,44.00388],"type":"Point"}
}