{
  "type": "Feature",
  "properties": {
    "addr:full":"114 Main St S Carman MB R0G 0J0",
    "addr:housenumber":"114",
    "addr:postcode":"r0g 0j0",
    "addr:street":"Main St S",
    "iso:country":"CA",
    "sg:address":"114 Main St S",
    "sg:city":"Carman",
    "sg:classifiers":[
        {
            "category":"Professional",
            "subcategory":"Accounting & Tax Preparation",
            "type":"Services"
        }
    ],
    "sg:phone":"+1 204 745 2430",
    "sg:postcode":"R0G 0J0",
    "sg:province":"MB",
    "sg:tags":[
        "accountant"
    ],
    "wof:name":"Gislason Targownik Peters",
    "wof:placetype":"venue"
},
  "geometry": {"coordinates":[-98.001762,49.505135],"type":"Point"}
}