{
  "type": "Feature",
  "properties": {
    "addr:full":"Whitecourt AB T7S 1P5",
    "addr:postcode":"t7s 1p5",
    "iso:country":"CA",
    "sg:city":"Whitecourt",
    "sg:classifiers":[
        {
            "category":"Utilities",
            "subcategory":"Natural Gas",
            "type":"Services"
        }
    ],
    "sg:phone":"+1 780 648 2172",
    "sg:postcode":"T7S 1P5",
    "sg:province":"AB",
    "sg:tags":[
        "company"
    ],
    "wof:name":"Three Rivers Gas CO-OP Ltd",
    "wof:placetype":"venue"
},
  "geometry": {"coordinates":[-115.68718,54.138279],"type":"Point"}
}