{
  "type": "Feature",
  "properties": {
    "iso:country":"CA",
    "sg:city":"North Vancouver",
    "sg:classifiers":[
        {
            "category":"Manufacturing",
            "subcategory":"Lumber",
            "type":"Manufacturing & Wholesale Goods"
        }
    ],
    "sg:phone":"+1 604 986 8346",
    "sg:postcode":"V7M 3G3",
    "sg:province":"BC",
    "sg:tags":[
        "forester"
    ],
    "wof:name":"B A Blackwell & Assoc Ltd",
    "wof:placetype":"venue"
},
  "geometry": {"coordinates":[-123.092811584,49.3144874573],"type":"Point"}
}