{
  "type": "Feature",
  "properties": {
    "addr:full":"121 John St Hawkesbury ON K6A 1Y1",
    "addr:housenumber":"121",
    "addr:postcode":"k6a 1y1",
    "addr:street":"John St",
    "iso:country":"CA",
    "sg:address":"121 John St",
    "sg:city":"Hawkesbury",
    "sg:classifiers":[
        {
            "category":"Autos & Motor Vehicles",
            "subcategory":"Fuel & Gas Station",
            "type":"Retail Goods"
        }
    ],
    "sg:phone":"+1 613 632 7621",
    "sg:postcode":"K6A 1Y1",
    "sg:province":"ON",
    "sg:tags":[
        "oil"
    ],
    "wof:name":"Garage Marcel Wilson Inc",
    "wof:placetype":"venue"
},
  "geometry": {"coordinates":[-74.6044845581,45.61120224],"type":"Point"}
}