{
  "type": "Feature",
  "properties": {
    "addr:full":"495 Woodward Ave Hamilton ON L8H 6N6",
    "addr:housenumber":"495",
    "addr:postcode":"l8h 6n6",
    "addr:street":"Woodward Ave",
    "iso:country":"CA",
    "sg:address":"495 Woodward Ave",
    "sg:city":"Hamilton",
    "sg:classifiers":[
        {
            "category":"Freight",
            "type":"Transportation"
        }
    ],
    "sg:phone":"+1 905 547 9696",
    "sg:postcode":"L8H 6N6",
    "sg:province":"ON",
    "sg:tags":[
        "mover"
    ],
    "wof:name":"Family Movers",
    "wof:placetype":"venue"
},
  "geometry": {"coordinates":[-79.7776107788,43.2461547852],"type":"Point"}
}