{
  "type": "Feature",
  "properties": {
    "iso:country":"CA",
    "sg:city":"Saint-Rosaire",
    "sg:classifiers":[
        {
            "category":"Insurance",
            "subcategory":"Insurance Agent",
            "type":"Services"
        }
    ],
    "sg:phone":"+1 819 752 9689",
    "sg:postcode":"G0Z 1K0",
    "sg:province":"QC",
    "wof:name":"Assurances Denis Boucher",
    "wof:placetype":"venue"
},
  "geometry": {"coordinates":[-71.985496521,46.1783332825],"type":"Point"}
}