{
  "type": "Feature",
  "properties": {
    "addr:full":"2823 Broadway W Vancouver BC V6K 2G6",
    "addr:housenumber":"2823",
    "addr:postcode":"v6k 2g6",
    "addr:street":"Broadway W",
    "iso:country":"CA",
    "sg:address":"2823 Broadway W",
    "sg:city":"Vancouver",
    "sg:classifiers":[
        {
            "category":"Restaurant",
            "type":"Food & Drink"
        }
    ],
    "sg:phone":"+1 604 733 1561",
    "sg:postcode":"V6K 2G6",
    "sg:province":"BC",
    "wof:name":"Fresh Slice Pizza",
    "wof:placetype":"venue"
},
  "geometry": {"coordinates":[-123.168762,49.264198],"type":"Point"}
}