{
  "type": "Feature",
  "properties": {
    "iso:country":"CA",
    "sg:address":"208 Strickland St",
    "sg:city":"Whitehorse",
    "sg:classifiers":[
        {
            "category":"Mining & Drilling",
            "type":"Manufacturing & Wholesale Goods"
        }
    ],
    "sg:phone":"+1 867 668 6660",
    "sg:postcode":"Y1A 2J8",
    "sg:province":"YT",
    "sg:tags":[
        "field",
        "oil",
        "trucking"
    ],
    "wof:name":"Swanberg Brothers Trucking Ltd",
    "wof:placetype":"venue"
},
  "geometry": {"coordinates":[-135.055069,60.722843],"type":"Point"}
}