{
  "type": "Feature",
  "properties": {
    "addr:full":"Tavistock ON N0B 2R0",
    "addr:postcode":"n0b 2r0",
    "iso:country":"CA",
    "sg:city":"Tavistock",
    "sg:classifiers":[
        {
            "category":"Building & Trades",
            "subcategory":"Construction",
            "type":"Services"
        }
    ],
    "sg:phone":"+1 519 655 2157",
    "sg:postcode":"N0B 2R0",
    "sg:province":"ON",
    "sg:tags":[
        "excavating",
        "contractor"
    ],
    "wof:name":"Raedon Excavating Ltd",
    "wof:placetype":"venue"
},
  "geometry": {"coordinates":[-80.83644099999999,43.32732],"type":"Point"}
}