{
  "type": "Feature",
  "properties": {
    "addr:full":"Gatineau QC J8T 6M7",
    "addr:postcode":"j8t 6m7",
    "iso:country":"CA",
    "sg:city":"Gatineau",
    "sg:classifiers":[
        {
            "category":"Professional",
            "subcategory":"Lawyer & Legal Services",
            "type":"Services"
        }
    ],
    "sg:phone":"+1 819 246 2400",
    "sg:postcode":"J8T 6M7",
    "sg:province":"QC",
    "sg:tags":[
        "attorney"
    ],
    "wof:name":"Lewis & Assoc",
    "wof:placetype":"venue"
},
  "geometry": {"coordinates":[-75.70124800000001,45.481232],"type":"Point"}
}