{
  "type": "Feature",
  "properties": {
    "addr:full":"559 Birch Rd North Saanich BC V8L 5S2",
    "addr:housenumber":"559",
    "addr:postcode":"v8l 5s2",
    "addr:street":"Birch Rd",
    "iso:country":"CA",
    "sg:address":"559 Birch Rd",
    "sg:city":"North Saanich",
    "sg:classifiers":[
        {
            "category":"Building & Trades",
            "subcategory":"Construction",
            "type":"Services"
        }
    ],
    "sg:phone":"+1 250 656 4336",
    "sg:postcode":"V8L 5S2",
    "sg:province":"BC",
    "sg:tags":[
        "control",
        "corrosion"
    ],
    "wof:name":"Northwest Electro-Guard Ltd",
    "wof:placetype":"venue"
},
  "geometry": {"coordinates":[-123.475013733,48.6776657104],"type":"Point"}
}