{
  "type": "Feature",
  "properties": {
    "iso:country":"CA",
    "sg:address":"155 Front St",
    "sg:city":"Sturgeon Falls",
    "sg:classifiers":[
        {
            "category":"Travel",
            "subcategory":"Hotels & Motels",
            "type":"Entertainment"
        }
    ],
    "sg:phone":"+1 705 753 1300",
    "sg:postcode":"P2B 2H7",
    "sg:province":"ON",
    "wof:name":"Champlain Motel",
    "wof:placetype":"venue"
},
  "geometry": {"coordinates":[-79.9211883545,46.3661270142],"type":"Point"}
}