{
  "type": "Feature",
  "properties": {
    "addr:full":"126 Bobcaygeon Minden ON K0M 2K0",
    "addr:housenumber":"126",
    "addr:postcode":"k0m 2k0",
    "addr:street":"Bobcaygeon",
    "iso:country":"CA",
    "sg:address":"126 Bobcaygeon",
    "sg:city":"Minden",
    "sg:classifiers":[
        {
            "category":"Government",
            "subcategory":"Office",
            "type":"Public Place"
        }
    ],
    "sg:phone":"+1 705 286 3559",
    "sg:postcode":"K0M 2K0",
    "sg:province":"ON",
    "wof:name":"Ontario Driver & Vehicle Agnts",
    "wof:placetype":"venue"
},
  "geometry": {"coordinates":[-78.72566999999999,44.926094],"type":"Point"}
}