{
  "type": "Feature",
  "properties": {
    "addr:full":"9125 Boul Grande-Allee Brossard QC J4Z 3H8",
    "addr:housenumber":"9125",
    "addr:postcode":"j4z 3h8",
    "addr:street":"Boul Grande-Allee",
    "iso:country":"CA",
    "sg:address":"9125 Boul Grande-Allee",
    "sg:city":"Brossard",
    "sg:classifiers":[
        {
            "category":"Wholesale",
            "subcategory":"Farm Supplies",
            "type":"Manufacturing & Wholesale Goods"
        }
    ],
    "sg:phone":"+1 450 443 4019",
    "sg:postcode":"J4Z 3H8",
    "sg:province":"QC",
    "sg:tags":[
        "livestock"
    ],
    "wof:name":"Entreprises Max Fried Inc",
    "wof:placetype":"venue"
},
  "geometry": {"coordinates":[-73.393242,45.441452],"type":"Point"}
}