{
  "type": "Feature",
  "properties": {
    "addr:full":"Brooks AB T1R 0M9",
    "addr:postcode":"t1r 0m9",
    "iso:country":"CA",
    "sg:city":"Brooks",
    "sg:classifiers":[
        {
            "category":"Communications",
            "subcategory":"Film & Video Production",
            "type":"Services"
        }
    ],
    "sg:phone":"+1 403 362 5034",
    "sg:postcode":"T1R 0M9",
    "sg:province":"AB",
    "sg:tags":[
        "taping"
    ],
    "wof:name":"Allpro Video Productions",
    "wof:placetype":"venue"
},
  "geometry": {"coordinates":[-111.891373,50.574894],"type":"Point"}
}