{
  "type": "Feature",
  "properties": {
    "addr:full":"157 Grand Ave W Chatham ON N7L 1B9",
    "addr:housenumber":"157",
    "addr:postcode":"n7l 1b9",
    "addr:street":"Grand Ave W",
    "iso:country":"CA",
    "sg:address":"157 Grand Ave W",
    "sg:city":"Chatham",
    "sg:classifiers":[
        {
            "category":"Health Services",
            "subcategory":"Doctor",
            "type":"Services"
        }
    ],
    "sg:phone":"+1 519 354 8173",
    "sg:postcode":"N7L 1B9",
    "sg:province":"ON",
    "sg:tags":[
        "physician",
        "surgeon"
    ],
    "wof:name":"Harnarine, Carleton MD",
    "wof:placetype":"venue"
},
  "geometry": {"coordinates":[-82.196236,42.404556],"type":"Point"}
}