{
  "type": "Feature",
  "properties": {
    "addr:full":"Cap-Sante QC G0A 1L0",
    "addr:postcode":"g0a 1l0",
    "iso:country":"CA",
    "sg:city":"Cap-Sante",
    "sg:classifiers":[
        {
            "category":"Recreation",
            "type":"Entertainment"
        }
    ],
    "sg:phone":"+1 418 285 0366",
    "sg:postcode":"G0A 1L0",
    "sg:province":"QC",
    "sg:tags":[
        "center"
    ],
    "wof:name":"Centre LA Rencontre",
    "wof:placetype":"venue"
},
  "geometry": {"coordinates":[-71.770988,46.670048],"type":"Point"}
}