{
  "type": "Feature",
  "properties": {
    "addr:full":"Abbotsford BC V2T 6H4",
    "addr:postcode":"v2t 6h4",
    "iso:country":"CA",
    "sg:city":"Abbotsford",
    "sg:classifiers":[
        {
            "category":"Farming",
            "subcategory":"Nursery",
            "type":"Manufacturing & Wholesale Goods"
        }
    ],
    "sg:phone":"+1 604 852 9302",
    "sg:postcode":"V2T 6H4",
    "sg:province":"BC",
    "sg:tags":[
        "greenhouse"
    ],
    "wof:name":"Cedar Build Hobby Greenhouses",
    "wof:placetype":"venue"
},
  "geometry": {"coordinates":[-122.377967834,49.05078125],"type":"Point"}
}