{
  "type": "Feature",
  "properties": {
    "addr:full":"751 1st Ave E Owen Sound ON N4K 2C6",
    "addr:housenumber":"751",
    "addr:postcode":"n4k 2c6",
    "addr:street":"1St Ave E",
    "iso:country":"CA",
    "sg:address":"751 1st Ave E",
    "sg:city":"Owen Sound",
    "sg:classifiers":[
        {
            "category":"Home & Garden",
            "subcategory":"Carpets & Floor Coverings",
            "type":"Retail Goods"
        }
    ],
    "sg:phone":"+1 519 376 1764",
    "sg:postcode":"N4K 2C6",
    "sg:province":"ON",
    "sg:tags":[
        "dealer",
        "rug"
    ],
    "wof:name":"Wardell's Carpets",
    "wof:placetype":"venue"
},
  "geometry": {"coordinates":[-80.9429016113,44.5626564026],"type":"Point"}
}