{
  "type": "Feature",
  "properties": {
    "addr:full":"444 Dufferin St Toronto ON M6K 2A3",
    "addr:housenumber":"444",
    "addr:postcode":"m6k 2a3",
    "addr:street":"Dufferin St",
    "iso:country":"CA",
    "sg:address":"444 Dufferin St",
    "sg:city":"Toronto",
    "sg:classifiers":[
        {
            "category":"Building & Trades",
            "subcategory":"Construction",
            "type":"Services"
        }
    ],
    "sg:phone":"+1 416 539 8150",
    "sg:postcode":"M6K 2A3",
    "sg:province":"ON",
    "sg:tags":[
        "maker",
        "cabinet"
    ],
    "wof:name":"Bob Kelly Design",
    "wof:placetype":"venue"
},
  "geometry": {"coordinates":[-79.429596,43.644505],"type":"Point"}
}