{
  "type": "Feature",
  "properties": {
    "addr:full":"Calgary AB T2B 3B5",
    "addr:postcode":"t2b 3b5",
    "iso:country":"CA",
    "sg:city":"Calgary",
    "sg:classifiers":[
        {
            "category":"Autos & Motor Vehicles",
            "subcategory":"Fuel & Gas Station",
            "type":"Retail Goods"
        }
    ],
    "sg:phone":"+1 403 248 9100",
    "sg:postcode":"T2B 3B5",
    "sg:province":"AB",
    "sg:tags":[
        "plaza",
        "truck",
        "stops"
    ],
    "wof:name":"Royal Truck Lube Ltd",
    "wof:placetype":"venue"
},
  "geometry": {"coordinates":[-114.002075195,51.0102882385],"type":"Point"}
}