{
  "type": "Feature",
  "properties": {
    "addr:full":"191 Dalton Ave Kingston ON K7K 6C2",
    "addr:housenumber":"191",
    "addr:postcode":"k7k 6c2",
    "addr:street":"Dalton Ave",
    "iso:country":"CA",
    "sg:address":"191 Dalton Ave",
    "sg:city":"Kingston",
    "sg:classifiers":[
        {
            "category":"Wholesale",
            "subcategory":"Machinery & Supplies",
            "type":"Manufacturing & Wholesale Goods"
        }
    ],
    "sg:phone":"+1 613 546 9393",
    "sg:postcode":"K7K 6C2",
    "sg:province":"ON",
    "sg:tags":[
        "roofing",
        "material"
    ],
    "wof:name":"Roofmart Limited",
    "wof:placetype":"venue"
},
  "geometry": {"coordinates":[-76.50611114500001,44.267288208],"type":"Point"}
}