{
  "type": "Feature",
  "properties": {
    "iso:country":"CA",
    "sg:address":"3862 Boul Saint-Charles",
    "sg:city":"Kirkland",
    "sg:classifiers":[
        {
            "category":"Food & Beverages",
            "subcategory":"Bakery",
            "type":"Retail Goods"
        }
    ],
    "sg:phone":"+1 514 693 9059",
    "sg:postcode":"H9H 3C3",
    "sg:province":"QC",
    "sg:tags":[
        "doughnut"
    ],
    "wof:name":"Tim Hortons",
    "wof:placetype":"venue"
},
  "geometry": {"coordinates":[-73.865791,45.459572],"type":"Point"}
}