{
  "type": "Feature",
  "properties": {
    "addr:full":"Surrey BC V3W 3N5",
    "addr:postcode":"v3w 3n5",
    "iso:country":"CA",
    "sg:city":"Surrey",
    "sg:classifiers":[
        {
            "category":"Personal",
            "subcategory":"Beauty Salon",
            "type":"Services"
        }
    ],
    "sg:phone":"+1 604 572 7749",
    "sg:postcode":"V3W 3N5",
    "sg:province":"BC",
    "wof:name":"Kelly's Hair Beauty Salon",
    "wof:placetype":"venue"
},
  "geometry": {"coordinates":[-122.890167236,49.1586761475],"type":"Point"}
}