{
  "type": "Feature",
  "properties": {
    "addr:full":"5214 44 St Rocky Mountain House AB T4T 1B4",
    "addr:housenumber":"5214",
    "addr:postcode":"t4t 1b4",
    "addr:street":"44 St",
    "iso:country":"CA",
    "sg:address":"5214 44 St",
    "sg:city":"Rocky Mountain House",
    "sg:classifiers":[
        {
            "category":"Retail",
            "subcategory":"Veterinary Services",
            "type":"Services"
        }
    ],
    "sg:phone":"+1 403 845 5353",
    "sg:postcode":"T4T 1B4",
    "sg:province":"AB",
    "sg:tags":[
        "veterinarian"
    ],
    "wof:name":"Clearwater Vet Clinic",
    "wof:placetype":"venue"
},
  "geometry": {"coordinates":[-114.908508,52.378334],"type":"Point"}
}