{
  "type": "Feature",
  "properties": {
    "addr:full":"3400 14th Ave Markham ON L3R 0H7",
    "addr:housenumber":"3400",
    "addr:postcode":"l3r 0h7",
    "addr:street":"14Th Ave",
    "iso:country":"CA",
    "sg:address":"3400 14th Ave",
    "sg:city":"Markham",
    "sg:classifiers":[
        {
            "category":"Professional",
            "type":"Services"
        }
    ],
    "sg:phone":"+1 905 940 8093",
    "sg:postcode":"L3R 0H7",
    "sg:province":"ON",
    "sg:tags":[
        "instrument",
        "establishment",
        "musical"
    ],
    "wof:name":"Impact Electronic Svc",
    "wof:placetype":"venue"
},
  "geometry": {"coordinates":[-79.3406219482,43.8347702026],"type":"Point"}
}