{
  "type": "Feature",
  "properties": {
    "addr:full":"Mississauga ON L5T 2K2",
    "addr:postcode":"l5t 2k2",
    "iso:country":"CA",
    "sg:city":"Mississauga",
    "sg:classifiers":[
        {
            "category":"Professional",
            "subcategory":"Business Services",
            "type":"Services"
        }
    ],
    "sg:phone":"+1 905 564 2611",
    "sg:postcode":"L5T 2K2",
    "sg:province":"ON",
    "sg:tags":[
        "painter",
        "sign"
    ],
    "wof:name":"Turbo Images Inc",
    "wof:placetype":"venue"
},
  "geometry": {"coordinates":[-79.662132,43.666485],"type":"Point"}
}