{
  "type": "Feature",
  "properties": {
    "addr:full":"Burlington ON L7R 4B6",
    "addr:postcode":"l7r 4b6",
    "iso:country":"CA",
    "sg:city":"Burlington",
    "sg:classifiers":[
        {
            "category":"Social Services",
            "type":"Services"
        }
    ],
    "sg:phone":"+1 905 637 5256",
    "sg:postcode":"L7R 4B6",
    "sg:province":"ON",
    "sg:tags":[
        "counselor",
        "marriage",
        "family"
    ],
    "wof:name":"DE Forest, Connie",
    "wof:placetype":"venue"
},
  "geometry": {"coordinates":[-79.7995834351,43.3267288208],"type":"Point"}
}