{
  "type": "Feature",
  "properties": {
    "addr:full":"333 Worthington St E North Bay ON P1B 1H2",
    "addr:housenumber":"333",
    "addr:postcode":"p1b 1h2",
    "addr:street":"Worthington St E",
    "iso:country":"CA",
    "sg:address":"333 Worthington St E",
    "sg:city":"North Bay",
    "sg:classifiers":[
        {
            "category":"Building & Trades",
            "subcategory":"Construction",
            "type":"Services"
        }
    ],
    "sg:phone":"+1 705 474 9650",
    "sg:postcode":"P1B 1H2",
    "sg:province":"ON",
    "sg:tags":[
        "masonry",
        "contractor"
    ],
    "wof:name":"Artan Contracting",
    "wof:placetype":"venue"
},
  "geometry": {"coordinates":[-79.4591827393,46.3080635071],"type":"Point"}
}