{
  "type": "Feature",
  "properties": {
    "addr:full":"1704 Bow Valley Trail Canmore AB T1W 1N5",
    "addr:housenumber":"1704",
    "addr:postcode":"t1w 1n5",
    "addr:street":"Bow Valley Trail",
    "iso:country":"CA",
    "sg:address":"1704 Bow Valley Trail",
    "sg:city":"Canmore",
    "sg:classifiers":[
        {
            "category":"Restaurant",
            "type":"Food & Drink"
        }
    ],
    "sg:phone":"+1 403 678 3300",
    "sg:postcode":"T1W 1N5",
    "sg:province":"AB",
    "wof:name":"Boston Pizza",
    "wof:placetype":"venue"
},
  "geometry": {"coordinates":[-115.35791,51.097336],"type":"Point"}
}