{
  "type": "Feature",
  "properties": {
    "addr:full":"7290 Rue Honore-Vaillancourt Montreal QC H1E 2S2",
    "addr:housenumber":"7290",
    "addr:postcode":"h1e 2s2",
    "addr:street":"Rue Honore-Vaillancourt",
    "iso:country":"CA",
    "sg:address":"7290 Rue Honore-Vaillancourt",
    "sg:city":"Montreal",
    "sg:classifiers":[
        {
            "category":"Wholesale",
            "subcategory":"Motor Vehicles",
            "type":"Manufacturing & Wholesale Goods"
        }
    ],
    "sg:phone":"+1 514 881 2223",
    "sg:postcode":"H1E 2S2",
    "sg:province":"QC",
    "sg:tags":[
        "body",
        "equipment",
        "truck"
    ],
    "wof:name":"A-1 Franc Metal Canada",
    "wof:placetype":"venue"
},
  "geometry": {"coordinates":[-73.598534,45.620907],"type":"Point"}
}