{
  "type": "Feature",
  "properties": {
    "addr:full":"Woodbridge ON L4L 5X8",
    "addr:postcode":"l4l 5x8",
    "iso:country":"CA",
    "sg:city":"Woodbridge",
    "sg:classifiers":[
        {
            "category":"Shopping",
            "subcategory":"Discount & Variety Stores",
            "type":"Retail Goods"
        }
    ],
    "sg:phone":"+1 905 850 2774",
    "sg:postcode":"L4L 5X8",
    "sg:province":"ON",
    "wof:name":"Vicky Convenience",
    "wof:placetype":"venue"
},
  "geometry": {"coordinates":[-79.5663757324,43.7844467163],"type":"Point"}
}