{
  "type": "Feature",
  "properties": {
    "addr:full":"Abbotsford BC V2T 3S5",
    "addr:postcode":"v2t 3s5",
    "iso:country":"CA",
    "sg:city":"Abbotsford",
    "sg:classifiers":[
        {
            "category":"Health Services",
            "subcategory":"Doctor",
            "type":"Services"
        }
    ],
    "sg:phone":"+1 604 853 2125",
    "sg:postcode":"V2T 3S5",
    "sg:province":"BC",
    "sg:tags":[
        "physician",
        "surgeon"
    ],
    "wof:name":"Cedar Park Medical Clinic",
    "wof:placetype":"venue"
},
  "geometry": {"coordinates":[-122.33509063699999,49.0495223999],"type":"Point"}
}