{
  "type": "Feature",
  "properties": {
    "addr:full":"SE 19 22 15W Ste Rose Du Lac MB R0L 1S0",
    "addr:housenumber":"19 22 15w ste",
    "addr:postcode":"r0l 1s0",
    "addr:street":"Se;Rose Du Lac",
    "iso:country":"CA",
    "sg:address":"SE 19 22 15W",
    "sg:city":"Ste Rose Du Lac",
    "sg:classifiers":[
        {
            "category":"Building & Trades",
            "subcategory":"Construction",
            "type":"Services"
        }
    ],
    "sg:phone":"+1 204 447 2219",
    "sg:postcode":"R0L 1S0",
    "sg:province":"MB",
    "sg:tags":[
        "excavating",
        "contractor"
    ],
    "wof:name":"Henry Haun Construction",
    "wof:placetype":"venue"
},
  "geometry": {"coordinates":[-99.5232009888,51.0591850281],"type":"Point"}
}