{
  "type": "Feature",
  "properties": {
    "addr:full":"201 Howey St Red Lake ON P0V 2M0",
    "addr:housenumber":"201",
    "addr:postcode":"p0v 2m0",
    "addr:street":"Howey St",
    "iso:country":"CA",
    "sg:address":"201 Howey St",
    "sg:city":"Red Lake",
    "sg:classifiers":[
        {
            "category":"Social Services",
            "type":"Services"
        }
    ],
    "sg:phone":"+1 807 727 2165",
    "sg:postcode":"P0V 2M0",
    "sg:province":"ON",
    "sg:tags":[
        "organization",
        "welfare"
    ],
    "wof:name":"Family Futures",
    "wof:placetype":"venue"
},
  "geometry": {"coordinates":[-93.8263626099,51.0192146301],"type":"Point"}
}