{
  "type": "Feature",
  "properties": {
    "addr:full":"8017 Hornby Rd Hornby ON L0P 1E0",
    "addr:housenumber":"8017",
    "addr:postcode":"l0p 1e0",
    "addr:street":"Hornby Rd",
    "iso:country":"CA",
    "sg:address":"8017 Hornby Rd",
    "sg:city":"Hornby",
    "sg:classifiers":[
        {
            "category":"Food & Beverages",
            "subcategory":"Groceries & Convenience Stores",
            "type":"Retail Goods"
        }
    ],
    "sg:phone":"+1 905 878 4589",
    "sg:postcode":"L0P 1E0",
    "sg:province":"ON",
    "wof:name":"K & B Gas Bar",
    "wof:placetype":"venue"
},
  "geometry": {"coordinates":[-79.842339,43.569374],"type":"Point"}
}