{
  "type": "Feature",
  "properties": {
    "iso:country":"CA",
    "sg:city":"Etobicoke",
    "sg:classifiers":[
        {
            "category":"Shopping",
            "subcategory":"Computers & Home Electronics",
            "type":"Retail Goods"
        }
    ],
    "sg:phone":"+1 416 249 7171",
    "sg:postcode":"M9P 2M5",
    "sg:province":"ON",
    "sg:tags":[
        "equipment",
        "dealer"
    ],
    "wof:name":"Supertect Computers",
    "wof:placetype":"venue"
},
  "geometry": {"coordinates":[-79.544029,43.697617],"type":"Point"}
}