{
  "type": "Feature",
  "properties": {
    "addr:full":"4 Ettrick Cres Nepean ON K2J 1G1",
    "addr:housenumber":"4",
    "addr:postcode":"k2j 1g1",
    "addr:street":"Ettrick Cres",
    "iso:country":"CA",
    "sg:address":"4 Ettrick Cres",
    "sg:city":"Nepean",
    "sg:classifiers":[
        {
            "category":"Retail",
            "subcategory":"Laundry & Dry Cleaning",
            "type":"Services"
        }
    ],
    "sg:phone":"+1 613 880 9063",
    "sg:postcode":"K2J 1G1",
    "sg:province":"ON",
    "sg:tags":[
        "cleaners",
        "rug",
        "carpet"
    ],
    "wof:name":"Barrhaven Carpet Cleaning",
    "wof:placetype":"venue"
},
  "geometry": {"coordinates":[-75.76409099999999,45.282585],"type":"Point"}
}