{
  "type": "Feature",
  "properties": {
    "iso:country":"CA",
    "sg:address":"3844 Boul Lasalle",
    "sg:city":"Verdun",
    "sg:classifiers":[
        {
            "category":"Health Services",
            "subcategory":"Podiatrist",
            "type":"Services"
        }
    ],
    "sg:phone":"+1 514 769 4250",
    "sg:postcode":"H4G 1Z9",
    "sg:province":"QC",
    "wof:name":"Deschenes, Richard M P DPM",
    "wof:placetype":"venue"
},
  "geometry": {"coordinates":[-73.565254,45.465511],"type":"Point"}
}