{
  "type": "Feature",
  "properties": {
    "addr:full":"200 1st Ave Carberry MB R0K 0H0",
    "addr:housenumber":"200",
    "addr:postcode":"r0k 0h0",
    "addr:street":"1St Ave",
    "iso:country":"CA",
    "sg:address":"200 1st Ave",
    "sg:city":"Carberry",
    "sg:classifiers":[
        {
            "category":"Freight",
            "type":"Transportation"
        }
    ],
    "sg:phone":"+1 204 834 2242",
    "sg:postcode":"R0K 0H0",
    "sg:province":"MB",
    "sg:tags":[
        "courier"
    ],
    "wof:name":"Greyhound Canada",
    "wof:placetype":"venue"
},
  "geometry": {"coordinates":[-99.37368011469999,49.8714866638],"type":"Point"}
}