{
  "type": "Feature",
  "properties": {
    "addr:full":"Lethbridge AB T1J 4C9",
    "addr:postcode":"t1j 4c9",
    "iso:country":"CA",
    "sg:city":"Lethbridge",
    "sg:classifiers":[
        {
            "category":"Shopping",
            "subcategory":"Clothing, Apparel, & Fashions",
            "type":"Retail Goods"
        }
    ],
    "sg:phone":"+1 403 329 6272",
    "sg:postcode":"T1J 4C9",
    "sg:province":"AB",
    "wof:name":"Tan Jay",
    "wof:placetype":"venue"
},
  "geometry": {"coordinates":[-112.844368,49.693977],"type":"Point"}
}