{
  "type": "Feature",
  "properties": {
    "addr:full":"311 Ross St NE Salmon Arm BC V1E 4N3",
    "addr:housenumber":"311",
    "addr:postcode":"v1e 4n3",
    "addr:street":"Ross St Ne",
    "iso:country":"CA",
    "sg:address":"311 Ross St NE",
    "sg:city":"Salmon Arm",
    "sg:classifiers":[
        {
            "category":"Shopping",
            "subcategory":"Bicycles & Sporting Goods",
            "type":"Retail Goods"
        }
    ],
    "sg:phone":"+1 250 832 9811",
    "sg:postcode":"V1E 4N3",
    "sg:province":"BC",
    "wof:name":"Ridetech Enterprises",
    "wof:placetype":"venue"
},
  "geometry": {"coordinates":[-119.281433105,50.7018585205],"type":"Point"}
}