{
  "type": "Feature",
  "properties": {
    "addr:full":"650 Dufferin Ave Winnipeg MB R2W 2Z2",
    "addr:housenumber":"650",
    "addr:postcode":"r2w 2z2",
    "addr:street":"Dufferin Ave",
    "iso:country":"CA",
    "sg:address":"650 Dufferin Ave",
    "sg:city":"Winnipeg",
    "sg:classifiers":[
        {
            "category":"Manufacturing",
            "subcategory":"Textiles",
            "type":"Manufacturing & Wholesale Goods"
        }
    ],
    "sg:phone":"+1 204 582 2360",
    "sg:postcode":"R2W 2Z2",
    "sg:province":"MB",
    "sg:tags":[
        "printer"
    ],
    "wof:name":"Mercury Press",
    "wof:placetype":"venue"
},
  "geometry": {"coordinates":[-97.15218353269999,49.9144630432],"type":"Point"}
}