{
  "type": "Feature",
  "properties": {
    "iso:country":"CA",
    "sg:address":"600 Rue Commerciale",
    "sg:city":"Notre-Dame-Du-Lac",
    "sg:classifiers":[
        {
            "category":"Shopping",
            "subcategory":"Crafts & Fabrics",
            "type":"Retail Goods"
        }
    ],
    "sg:phone":"+1 418 899 6823",
    "sg:postcode":"G0L 1X0",
    "sg:province":"QC",
    "sg:tags":[
        "shop"
    ],
    "wof:name":"Boutique LA Releve",
    "wof:placetype":"venue"
},
  "geometry": {"coordinates":[-68.7980499268,47.6136283875],"type":"Point"}
}