{
  "type": "Feature",
  "properties": {
    "addr:full":"1651 Rang DE LA Riviere N Sainte-Elisabeth QC J0K 2J0",
    "addr:housenumber":"1651",
    "addr:postcode":"j0k 2j0",
    "addr:street":"Rang De La Riviere N Sainte-Elisabeth",
    "iso:country":"CA",
    "sg:address":"1651 Rang DE LA Riviere N",
    "sg:city":"Sainte-Elisabeth",
    "sg:classifiers":[
        {
            "category":"Wholesale",
            "subcategory":"Farm Supplies",
            "type":"Manufacturing & Wholesale Goods"
        }
    ],
    "sg:phone":"+1 450 752 0976",
    "sg:postcode":"J0K 2J0",
    "sg:province":"QC",
    "sg:tags":[
        "livestock"
    ],
    "wof:name":"Aubuchon, Dominic",
    "wof:placetype":"venue"
},
  "geometry": {"coordinates":[-73.316833,46.09885],"type":"Point"}
}