{
  "type": "Feature",
  "properties": {
    "addr:full":"379 Parkview Rd Yorkton SK S3N 2L4",
    "addr:housenumber":"379",
    "addr:postcode":"s3n 2l4",
    "addr:street":"Parkview Rd",
    "iso:country":"CA",
    "sg:address":"379 Parkview Rd",
    "sg:city":"Yorkton",
    "sg:classifiers":[
        {
            "category":"Health Services",
            "subcategory":"Doctor",
            "type":"Services"
        }
    ],
    "sg:phone":"+1 306 782 2444",
    "sg:postcode":"S3N 2L4",
    "sg:province":"SK",
    "sg:tags":[
        "physician",
        "surgeon"
    ],
    "wof:name":"Yorkton Medical Clinic",
    "wof:placetype":"venue"
},
  "geometry": {"coordinates":[-102.48790700000001,51.200935],"type":"Point"}
}