{
  "type": "Feature",
  "properties": {
    "addr:full":"8131 Yonge St Thornhill ON L3T 2C6",
    "addr:housenumber":"8131",
    "addr:postcode":"l3t 2c6",
    "addr:street":"Yonge St",
    "iso:country":"CA",
    "sg:address":"8131 Yonge St",
    "sg:city":"Thornhill",
    "sg:classifiers":[
        {
            "category":"Professional",
            "subcategory":"Business Services",
            "type":"Services"
        }
    ],
    "sg:phone":"+1 905 764 6643",
    "sg:postcode":"L3T 2C6",
    "sg:province":"ON",
    "sg:tags":[
        "paralegal"
    ],
    "wof:name":"J B Claims Management Svc",
    "wof:placetype":"venue"
},
  "geometry": {"coordinates":[-79.426514,43.825802],"type":"Point"}
}