{
  "type": "Feature",
  "properties": {
    "addr:full":"Red Deer AB T4N 6V4",
    "addr:postcode":"t4n 6v4",
    "iso:country":"CA",
    "sg:city":"Red Deer",
    "sg:classifiers":[
        {
            "category":"Shopping",
            "subcategory":"Gifts & Souvenirs",
            "type":"Retail Goods"
        }
    ],
    "sg:phone":"+1 403 346 3550",
    "sg:postcode":"T4N 6V4",
    "sg:province":"AB",
    "sg:tags":[
        "cards",
        "greeting"
    ],
    "wof:name":"Okie Cards & Confectionery",
    "wof:placetype":"venue"
},
  "geometry": {"coordinates":[-113.812904358,52.269821167],"type":"Point"}
}