{
  "type": "Feature",
  "properties": {
    "addr:full":"1200 Englishman River Rd Errington BC V0R 1V0",
    "addr:housenumber":"1200",
    "addr:postcode":"v0r 1v0",
    "addr:street":"Englishman River Rd",
    "iso:country":"CA",
    "sg:address":"1200 Englishman River Rd",
    "sg:city":"Errington",
    "sg:classifiers":[
        {
            "category":"Building & Trades",
            "subcategory":"Landscaping Services",
            "type":"Services"
        }
    ],
    "sg:phone":"+1 250 248 9147",
    "sg:postcode":"V0R 1V0",
    "sg:province":"BC",
    "sg:tags":[
        "lawn",
        "contractor",
        "landscape",
        "maintenance",
        "grounds"
    ],
    "wof:name":"Beautiful Gardens Ltd",
    "wof:placetype":"venue"
},
  "geometry": {"coordinates":[-124.376091,49.289455],"type":"Point"}
}