{
  "type": "Feature",
  "properties": {
    "addr:full":"263 Champlain Lake Rd Mattawa ON P0H 1V0",
    "addr:housenumber":"263",
    "addr:postcode":"p0h 1v0",
    "addr:street":"Champlain Lake Rd",
    "iso:country":"CA",
    "sg:address":"263 Champlain Lake Rd",
    "sg:city":"Mattawa",
    "sg:classifiers":[
        {
            "category":"Building & Trades",
            "subcategory":"Plumbing",
            "type":"Services"
        }
    ],
    "sg:phone":"+1 705 744 5153",
    "sg:postcode":"P0H 1V0",
    "sg:province":"ON",
    "sg:tags":[
        "contractor"
    ],
    "wof:name":"Mattawa Plumbing & Heating",
    "wof:placetype":"venue"
},
  "geometry": {"coordinates":[-78.6990280151,46.3162612915],"type":"Point"}
}