{
  "type": "Feature",
  "properties": {
    "addr:full":"1210 Fewster Dr Mississauga ON L4W 1A1",
    "addr:housenumber":"1210",
    "addr:postcode":"l4w 1a1",
    "addr:street":"Fewster Dr",
    "iso:country":"CA",
    "sg:address":"1210 Fewster Dr",
    "sg:city":"Mississauga",
    "sg:classifiers":[
        {
            "category":"Autos & Motor Vehicles",
            "subcategory":"Auto Supplies",
            "type":"Retail Goods"
        }
    ],
    "sg:phone":"+1 905 625 6006",
    "sg:postcode":"L4W 1A1",
    "sg:province":"ON",
    "sg:tags":[
        "tire"
    ],
    "wof:name":"Abc New & Used Tires",
    "wof:placetype":"venue"
},
  "geometry": {"coordinates":[-79.619682,43.628586],"type":"Point"}
}