{
  "type": "Feature",
  "properties": {
    "addr:full":"44 Cumberland Dr Dartmouth NS B2V 2C7",
    "addr:housenumber":"44",
    "addr:postcode":"b2v 2c7",
    "addr:street":"Cumberland Dr",
    "iso:country":"CA",
    "sg:address":"44 Cumberland Dr",
    "sg:city":"Dartmouth",
    "sg:classifiers":[
        {
            "category":"Organizations",
            "subcategory":"Religious Organization",
            "type":"Services"
        }
    ],
    "sg:phone":"+1 902 462 2102",
    "sg:postcode":"B2V 2C7",
    "sg:province":"NS",
    "sg:tags":[
        "church"
    ],
    "wof:name":"Church of Jesus Christ-Lds",
    "wof:placetype":"venue"
},
  "geometry": {"coordinates":[-63.4896659851,44.6699485779],"type":"Point"}
}