{
  "type": "Feature",
  "properties": {
    "addr:full":"40 Rue Berube Gatineau QC J8P 6T3",
    "addr:housenumber":"40",
    "addr:postcode":"j8p 6t3",
    "addr:street":"Rue Berube",
    "iso:country":"CA",
    "sg:address":"40 Rue Berube",
    "sg:city":"Gatineau",
    "sg:classifiers":[
        {
            "category":"Building & Trades",
            "subcategory":"Construction",
            "type":"Services"
        }
    ],
    "sg:phone":"+1 819 663 7191",
    "sg:postcode":"J8P 6T3",
    "sg:province":"QC",
    "sg:tags":[
        "repairing",
        "home",
        "improvement",
        "remodeling",
        "contractor"
    ],
    "wof:name":"Service Design Enr",
    "wof:placetype":"venue"
},
  "geometry": {"coordinates":[-75.59629099999999,45.494774],"type":"Point"}
}