{
  "type": "Feature",
  "properties": {
    "addr:full":"39 West St Goderich ON N7A 2K5",
    "addr:housenumber":"39",
    "addr:postcode":"n7a 2k5",
    "addr:street":"West St",
    "iso:country":"CA",
    "sg:address":"39 West St",
    "sg:city":"Goderich",
    "sg:classifiers":[
        {
            "category":"Organizations",
            "subcategory":"Community Association",
            "type":"Services"
        }
    ],
    "sg:phone":"+1 519 524 8561",
    "sg:postcode":"N7A 2K5",
    "sg:province":"ON",
    "sg:tags":[
        "club"
    ],
    "wof:name":"Menesetung Canoe Club",
    "wof:placetype":"venue"
},
  "geometry": {"coordinates":[-81.71277618409999,43.7429428101],"type":"Point"}
}