{
  "type": "Feature",
  "properties": {
    "addr:full":"1082 Thimbleberry Cir Oshawa ON L1K 2H2",
    "addr:housenumber":"1082",
    "addr:postcode":"l1k 2h2",
    "addr:street":"Thimbleberry Cir",
    "iso:country":"CA",
    "sg:address":"1082 Thimbleberry Cir",
    "sg:city":"Oshawa",
    "sg:classifiers":[
        {
            "category":"Education",
            "subcategory":"Special Training",
            "type":"Public Place"
        }
    ],
    "sg:phone":"+1 905 404 0111",
    "sg:postcode":"L1K 2H2",
    "sg:province":"ON",
    "sg:tags":[
        "instruction",
        "driving"
    ],
    "wof:name":"Old Timer's Truck Driving Schl",
    "wof:placetype":"venue"
},
  "geometry": {"coordinates":[-78.829903,43.91526],"type":"Point"}
}