{
  "type": "Feature",
  "properties": {
    "iso:country":"CA",
    "sg:address":"4403 52nd Ave",
    "sg:city":"Provost",
    "sg:classifiers":[
        {
            "category":"Education",
            "subcategory":"School",
            "type":"Public Place"
        }
    ],
    "sg:phone":"+1 780 753 6838",
    "sg:postcode":"T0B 3S0",
    "sg:province":"AB",
    "wof:name":"St Thomas Aquinas School",
    "wof:placetype":"venue"
},
  "geometry": {"coordinates":[-110.257904053,52.3542060852],"type":"Point"}
}