{
  "type": "Feature",
  "properties": {
    "iso:country":"CA",
    "sg:address":"280 Wilson St",
    "sg:city":"Sault Ste Marie",
    "sg:classifiers":[
        {
            "category":"Retail",
            "subcategory":"Auto Repair",
            "type":"Services"
        }
    ],
    "sg:phone":"+1 705 256 5898",
    "sg:postcode":"P6B 2K5",
    "sg:province":"ON",
    "sg:tags":[
        "repairing",
        "automobile"
    ],
    "wof:name":"Gail Joy Investments",
    "wof:placetype":"venue"
},
  "geometry": {"coordinates":[-84.33122253419999,46.5179290771],"type":"Point"}
}