{
  "type": "Feature",
  "properties": {
    "addr:full":"Victoria BC V9A 3S2",
    "addr:postcode":"v9a 3s2",
    "iso:country":"CA",
    "sg:city":"Victoria",
    "sg:classifiers":[
        {
            "category":"Manufacturing",
            "subcategory":"Tools & Machinery",
            "type":"Manufacturing & Wholesale Goods"
        }
    ],
    "sg:phone":"+1 250 385 9738",
    "sg:postcode":"V9A 3S2",
    "sg:province":"BC",
    "sg:tags":[
        "machine",
        "shop",
        "welding"
    ],
    "wof:name":"United Engineering Ltd",
    "wof:placetype":"venue"
},
  "geometry": {"coordinates":[-123.376296997,48.4307785034],"type":"Point"}
}