{
  "type": "Feature",
  "properties": {
    "iso:country":"CA",
    "sg:address":"166 Main St",
    "sg:city":"Unionville",
    "sg:classifiers":[
        {
            "category":"Restaurant",
            "type":"Food & Drink"
        }
    ],
    "sg:phone":"+1 905 305 0503",
    "sg:postcode":"L3R 2G9",
    "sg:province":"ON",
    "wof:name":"Blacksmith's Bistro",
    "wof:placetype":"venue"
},
  "geometry": {"coordinates":[-79.312134,43.866947],"type":"Point"}
}