{
  "type": "Feature",
  "properties": {
    "iso:country":"CA",
    "sg:city":"Toronto",
    "sg:classifiers":[
        {
            "category":"Professional",
            "type":"Services"
        }
    ],
    "sg:phone":"+1 416 955 8630",
    "sg:postcode":"M5H 2G4",
    "sg:province":"ON",
    "sg:tags":[
        "consultant",
        "mining",
        "geological"
    ],
    "wof:name":"Dale M Hendrick Assoc",
    "wof:placetype":"venue"
},
  "geometry": {"coordinates":[-79.3838348389,43.6504745483],"type":"Point"}
}