{
  "type": "Feature",
  "properties": {
    "addr:full":"75 Erie St S # 101 Leamington ON N8H 3B2",
    "addr:housenumber":"75",
    "addr:postcode":"n8h 3b2",
    "addr:street":"Erie St S # 101",
    "iso:country":"CA",
    "sg:address":"75 Erie St S # 101",
    "sg:city":"Leamington",
    "sg:classifiers":[
        {
            "category":"Insurance",
            "subcategory":"Insurance Agent",
            "type":"Services"
        }
    ],
    "sg:phone":"+1 519 326 4462",
    "sg:postcode":"N8H 3B2",
    "sg:province":"ON",
    "wof:name":"Clarica Life Insurance CO",
    "wof:placetype":"venue"
},
  "geometry": {"coordinates":[-82.60013600000001,42.050743],"type":"Point"}
}