{
  "type": "Feature",
  "properties": {
    "iso:country":"CA",
    "sg:address":"652 Rue Sigouin",
    "sg:city":"Gatineau",
    "sg:classifiers":[
        {
            "category":"Real Estate",
            "subcategory":"Real Estate Agent",
            "type":"Services"
        }
    ],
    "sg:phone":"+1 819 663 9965",
    "sg:postcode":"J8P 5H8",
    "sg:province":"QC",
    "wof:name":"Tremblay Pierre",
    "wof:placetype":"venue"
},
  "geometry": {"coordinates":[-75.6501235962,45.4990692139],"type":"Point"}
}