{
  "type": "Feature",
  "properties": {
    "addr:full":"1475 Wheatland Trail Strathmore AB T1P 1K1",
    "addr:housenumber":"1475",
    "addr:postcode":"t1p 1k1",
    "addr:street":"Wheatland Trail",
    "iso:country":"CA",
    "sg:address":"1475 Wheatland Trail",
    "sg:city":"Strathmore",
    "sg:classifiers":[
        {
            "category":"Professional",
            "subcategory":"Management & Consulting",
            "type":"Services"
        }
    ],
    "sg:phone":"+1 403 934 2211",
    "sg:postcode":"T1P 1K1",
    "sg:province":"AB",
    "sg:tags":[
        "agricultural",
        "consultant"
    ],
    "wof:name":"Lundman Agri-Svc Inc",
    "wof:placetype":"venue"
},
  "geometry": {"coordinates":[-113.400299,51.039371],"type":"Point"}
}