{
  "type": "Feature",
  "properties": {
    "addr:full":"951 Boul Hamel E Chibougamau QC G8P 2Z3",
    "addr:housenumber":"951",
    "addr:postcode":"g8p 2z3",
    "addr:street":"Boul Hamel E",
    "iso:country":"CA",
    "sg:address":"951 Boul Hamel E",
    "sg:city":"Chibougamau",
    "sg:classifiers":[
        {
            "category":"Government",
            "subcategory":"Office",
            "type":"Public Place"
        }
    ],
    "sg:phone":"+1 418 748 7701",
    "sg:postcode":"G8P 2Z3",
    "sg:province":"QC",
    "wof:name":"Quebec Amenagement & Expltn",
    "wof:placetype":"venue"
},
  "geometry": {"coordinates":[-74.38445299999999,49.905659],"type":"Point"}
}