{
  "type": "Feature",
  "properties": {
    "iso:country":"CA",
    "sg:city":"Scarborough",
    "sg:classifiers":[
        {
            "category":"Personal",
            "subcategory":"Beauty Salon",
            "type":"Services"
        }
    ],
    "sg:phone":"+1 416 299 8998",
    "sg:postcode":"M1S 2C1",
    "sg:province":"ON",
    "wof:name":"Winky Salon",
    "wof:placetype":"venue"
},
  "geometry": {"coordinates":[-79.2761764526,43.7865715027],"type":"Point"}
}