{
  "type": "Feature",
  "properties": {
    "addr:full":"116 Prospect Ave Kirkland Lake ON P2N 2X1",
    "addr:housenumber":"116",
    "addr:postcode":"p2n 2x1",
    "addr:street":"Prospect Ave",
    "iso:country":"CA",
    "sg:address":"116 Prospect Ave",
    "sg:city":"Kirkland Lake",
    "sg:classifiers":[
        {
            "category":"Retail",
            "subcategory":"Auto Repair",
            "type":"Services"
        }
    ],
    "sg:phone":"+1 705 567 7400",
    "sg:postcode":"P2N 2X1",
    "sg:province":"ON",
    "sg:tags":[
        "repairing",
        "automobile"
    ],
    "wof:name":"On the Road Again",
    "wof:placetype":"venue"
},
  "geometry": {"coordinates":[-80.0298538208,48.1428985596],"type":"Point"}
}