{
  "type": "Feature",
  "properties": {
    "addr:full":"1371 Robin Lane Sarnia ON N7V 3E6",
    "addr:housenumber":"1371",
    "addr:postcode":"n7v 3e6",
    "addr:street":"Robin Lane",
    "iso:country":"CA",
    "sg:address":"1371 Robin Lane",
    "sg:city":"Sarnia",
    "sg:classifiers":[
        {
            "category":"Shopping",
            "type":"Retail Goods"
        }
    ],
    "sg:phone":"+1 519 332 4800",
    "sg:postcode":"N7V 3E6",
    "sg:province":"ON",
    "sg:tags":[
        "wedding",
        "supply"
    ],
    "wof:name":"Bluewater Weddings Marriage Sv",
    "wof:placetype":"venue"
},
  "geometry": {"coordinates":[-82.3941421509,43.005405426],"type":"Point"}
}