{
  "type": "Feature",
  "properties": {
    "iso:country":"CA",
    "sg:address":"1591 Eastern Dr",
    "sg:city":"Port Coquitlam",
    "sg:classifiers":[
        {
            "category":"Professional",
            "subcategory":"Employment Agencies",
            "type":"Services"
        }
    ],
    "sg:phone":"+1 604 464 4300",
    "sg:postcode":"V3C 2S9",
    "sg:province":"BC",
    "sg:tags":[
        "opportunity"
    ],
    "wof:name":"Jollibee Nannies",
    "wof:placetype":"venue"
},
  "geometry": {"coordinates":[-122.775688171,49.2440605164],"type":"Point"}
}