{
  "type": "Feature",
  "properties": {
    "addr:full":"1409 Summit St SW Calgary AB T3C 2L8",
    "addr:housenumber":"1409",
    "addr:postcode":"t3c 2l8",
    "addr:street":"Summit St Sw",
    "iso:country":"CA",
    "sg:address":"1409 Summit St SW",
    "sg:city":"Calgary",
    "sg:classifiers":[
        {
            "category":"Real Estate",
            "subcategory":"Architect",
            "type":"Services"
        }
    ],
    "sg:phone":"+1 403 261 3962",
    "sg:postcode":"T3C 2L8",
    "sg:province":"AB",
    "wof:name":"Moffat Architecture & Eng",
    "wof:placetype":"venue"
},
  "geometry": {"coordinates":[-114.11116800000001,51.040531],"type":"Point"}
}