{
  "type": "Feature",
  "properties": {
    "addr:full":"340 Welton St Sydney NS B1P 5S4",
    "addr:housenumber":"340",
    "addr:postcode":"b1p 5s4",
    "addr:street":"Welton St",
    "iso:country":"CA",
    "sg:address":"340 Welton St",
    "sg:city":"Sydney",
    "sg:classifiers":[
        {
            "category":"Wholesale",
            "subcategory":"Tobacco Products",
            "type":"Manufacturing & Wholesale Goods"
        }
    ],
    "sg:phone":"+1 902 539 1099",
    "sg:postcode":"B1P 5S4",
    "sg:province":"NS",
    "sg:tags":[
        "cigarette",
        "cigar",
        "dealer"
    ],
    "wof:name":"Atlantic Cash & Carry",
    "wof:placetype":"venue"
},
  "geometry": {"coordinates":[-60.162197,46.144199],"type":"Point"}
}