{
  "type": "Feature",
  "properties": {
    "iso:country":"CA",
    "sg:address":"24 Kelvin Pl SW",
    "sg:city":"Calgary",
    "sg:classifiers":[
        {
            "category":"Building & Trades",
            "subcategory":"Construction",
            "type":"Services"
        }
    ],
    "sg:phone":"+1 403 252 8322",
    "sg:postcode":"T2V 2K8",
    "sg:province":"AB",
    "sg:tags":[
        "general",
        "contractor"
    ],
    "wof:name":"Oscar Fech Construction Ltd",
    "wof:placetype":"venue"
},
  "geometry": {"coordinates":[-114.079567,50.981438],"type":"Point"}
}