{
  "type": "Feature",
  "properties": {
    "addr:full":"Sainte-Cecile-DE-Milton QC J0E 2C0",
    "addr:postcode":"j0e 2c0",
    "iso:country":"CA",
    "sg:city":"Sainte-Cecile-DE-Milton",
    "sg:classifiers":[
        {
            "category":"Wholesale",
            "subcategory":"Auto Parts",
            "type":"Manufacturing & Wholesale Goods"
        }
    ],
    "sg:phone":"+1 450 372 8449",
    "sg:postcode":"J0E 2C0",
    "sg:province":"QC",
    "sg:tags":[
        "automobile",
        "rebuilt",
        "supply"
    ],
    "wof:name":"Pieces D'Auto Lf Inc",
    "wof:placetype":"venue"
},
  "geometry": {"coordinates":[-72.759262085,45.4801483154],"type":"Point"}
}