{
  "type": "Feature",
  "properties": {
    "iso:country":"CA",
    "sg:city":"Saint-Hubert",
    "sg:classifiers":[
        {
            "category":"Shopping",
            "subcategory":"Shoes",
            "type":"Retail Goods"
        }
    ],
    "sg:phone":"+1 450 926 1548",
    "sg:postcode":"J3Y 6J8",
    "sg:province":"QC",
    "wof:name":"Chaussures Polo",
    "wof:placetype":"venue"
},
  "geometry": {"coordinates":[-73.425148,45.501904],"type":"Point"}
}