{
  "type": "Feature",
  "properties": {
    "addr:full":"535 Louisa St Ayton ON N0G 1C0",
    "addr:housenumber":"535",
    "addr:postcode":"n0g 1c0",
    "addr:street":"Louisa St",
    "iso:country":"CA",
    "sg:address":"535 Louisa St",
    "sg:city":"Ayton",
    "sg:classifiers":[
        {
            "category":"Food & Beverages",
            "subcategory":"Groceries & Convenience Stores",
            "type":"Retail Goods"
        }
    ],
    "sg:phone":"+1 519 665 7828",
    "sg:postcode":"N0G 1C0",
    "sg:province":"ON",
    "wof:name":"Granny's General Store",
    "wof:placetype":"venue"
},
  "geometry": {"coordinates":[-80.926682,44.052856],"type":"Point"}
}