{
  "type": "Feature",
  "properties": {
    "iso:country":"CA",
    "sg:address":"334 Av Principale",
    "sg:city":"Degelis",
    "sg:classifiers":[
        {
            "category":"Wholesale",
            "subcategory":"Machinery & Supplies",
            "type":"Manufacturing & Wholesale Goods"
        }
    ],
    "sg:phone":"+1 418 853 2941",
    "sg:postcode":"G5T 1M4",
    "sg:province":"QC",
    "sg:tags":[
        "forestry",
        "timber"
    ],
    "wof:name":"Equipements Sigma Inc",
    "wof:placetype":"venue"
},
  "geometry": {"coordinates":[-68.6494674683,47.5480155945],"type":"Point"}
}