{
  "type": "Feature",
  "properties": {
    "addr:full":"251 Rue Sainte-Anne Chicoutimi QC G7J 2M2",
    "addr:housenumber":"251",
    "addr:postcode":"g7j 2m2",
    "addr:street":"Rue Sainte-Anne",
    "iso:country":"CA",
    "sg:address":"251 Rue Sainte-Anne",
    "sg:city":"Chicoutimi",
    "sg:classifiers":[
        {
            "category":"Autos & Motor Vehicles",
            "subcategory":"Auto Supplies",
            "type":"Retail Goods"
        }
    ],
    "sg:phone":"+1 418 543 7788",
    "sg:postcode":"G7J 2M2",
    "sg:province":"QC",
    "sg:tags":[
        "automobile",
        "parts"
    ],
    "wof:name":"Uap Napa Pieces D'Auto",
    "wof:placetype":"venue"
},
  "geometry": {"coordinates":[-71.068153,48.428841],"type":"Point"}
}