{
  "type": "Feature",
  "properties": {
    "iso:country":"CA",
    "sg:address":"5631 Old Hwy 2",
    "sg:city":"Shannonville",
    "sg:classifiers":[
        {
            "category":"Organizations",
            "subcategory":"Professional Association",
            "type":"Services"
        }
    ],
    "sg:phone":"+1 613 969 2215",
    "sg:postcode":"K0K 3A0",
    "sg:province":"ON",
    "sg:tags":[
        "native"
    ],
    "wof:name":"Red Cedars Shelter Traditional",
    "wof:placetype":"venue"
},
  "geometry": {"coordinates":[-77.2316665649,44.1972389221],"type":"Point"}
}