{
  "type": "Feature",
  "properties": {
    "addr:full":"71 Conley Dr Westville NS B0K 2A0",
    "addr:housenumber":"71",
    "addr:postcode":"b0k 2a0",
    "addr:street":"Conley Dr",
    "iso:country":"CA",
    "sg:address":"71 Conley Dr",
    "sg:city":"Westville",
    "sg:classifiers":[
        {
            "category":"Manufacturing",
            "subcategory":"Motor Vehicles & Parts",
            "type":"Manufacturing & Wholesale Goods"
        }
    ],
    "sg:phone":"+1 902 396 4171",
    "sg:postcode":"B0K 2A0",
    "sg:province":"NS",
    "sg:tags":[
        "repairing",
        "automobile",
        "drive"
    ],
    "wof:name":"Radco Enterprises Ltd",
    "wof:placetype":"venue"
},
  "geometry": {"coordinates":[-62.709908,45.56176],"type":"Point"}
}