{
  "type": "Feature",
  "properties": {
    "addr:full":"10425 1E Av Saint-Georges QC G5Y 6X8",
    "addr:housenumber":"10425",
    "addr:postcode":"g5y 6x8",
    "addr:street":"1E Av",
    "iso:country":"CA",
    "sg:address":"10425 1E Av",
    "sg:city":"Saint-Georges",
    "sg:classifiers":[
        {
            "category":"Shopping",
            "type":"Retail Goods"
        }
    ],
    "sg:phone":"+1 418 227 6697",
    "sg:postcode":"G5Y 6X8",
    "sg:province":"QC",
    "sg:tags":[
        "picture",
        "frame"
    ],
    "wof:name":"Ateliers DE LA Magie-Couleurs",
    "wof:placetype":"venue"
},
  "geometry": {"coordinates":[-70.67115,46.123348],"type":"Point"}
}