{
  "type": "Feature",
  "properties": {
    "addr:full":"5655 Av Du Parc Montreal QC H2V 4H2",
    "addr:housenumber":"5655",
    "addr:postcode":"h2v 4h2",
    "addr:street":"Av Du Parc",
    "iso:country":"CA",
    "sg:address":"5655 Av Du Parc",
    "sg:city":"Montreal",
    "sg:classifiers":[
        {
            "category":"Health Services",
            "subcategory":"Doctor",
            "type":"Services"
        }
    ],
    "sg:phone":"+1 514 270 2121",
    "sg:postcode":"H2V 4H2",
    "sg:province":"QC",
    "sg:tags":[
        "physician",
        "clinic",
        "surgeon"
    ],
    "wof:name":"Medico Centre Du Parc",
    "wof:placetype":"venue"
},
  "geometry": {"coordinates":[-73.6037979126,45.5230712891],"type":"Point"}
}