{
  "type": "Feature",
  "properties": {
    "addr:full":"24001 Fern Cres Maple Ridge BC V4R 2R7",
    "addr:housenumber":"24001",
    "addr:postcode":"bc v4r 2r7",
    "addr:street":"Fern Cres",
    "iso:country":"CA",
    "sg:address":"24001 Fern Cres",
    "sg:city":"Maple Ridge",
    "sg:classifiers":[
        {
            "category":"Building & Trades",
            "subcategory":"Plumbing",
            "type":"Services"
        }
    ],
    "sg:phone":"+1 604 826 8441",
    "sg:postcode":"V4R 2R7",
    "sg:province":"BC",
    "sg:tags":[
        "contractor"
    ],
    "wof:name":"Willco Plumbing & Heating",
    "wof:placetype":"venue"
},
  "geometry": {"coordinates":[-122.556968689,49.2335510254],"type":"Point"}
}