{
  "type": "Feature",
  "properties": {
    "addr:full":"2410 Nanaimo St Vancouver BC V5N 5E4",
    "addr:housenumber":"2410",
    "addr:postcode":"v5n 5e4",
    "addr:street":"Nanaimo St",
    "iso:country":"CA",
    "sg:address":"2410 Nanaimo St",
    "sg:city":"Vancouver",
    "sg:classifiers":[
        {
            "category":"Insurance",
            "subcategory":"Insurance Agent",
            "type":"Services"
        }
    ],
    "sg:phone":"+1 604 251 3571",
    "sg:postcode":"V5N 5E4",
    "sg:province":"BC",
    "wof:name":"Adams-Broadway Insurance Svc",
    "wof:placetype":"venue"
},
  "geometry": {"coordinates":[-123.05647999999999,49.262856],"type":"Point"}
}