{
  "type": "Feature",
  "properties": {
    "iso:country":"CA",
    "sg:address":"298 Rue Queen",
    "sg:city":"Lennoxville",
    "sg:classifiers":[
        {
            "category":"Wholesale",
            "subcategory":"Auto Parts",
            "type":"Manufacturing & Wholesale Goods"
        }
    ],
    "sg:phone":"+1 819 346 9939",
    "sg:postcode":"J1M 1K6",
    "sg:province":"QC",
    "sg:tags":[
        "repairing",
        "automobile"
    ],
    "wof:name":"Centre DE L'Auto Prevost",
    "wof:placetype":"venue"
},
  "geometry": {"coordinates":[-71.86437988279999,45.3770675659],"type":"Point"}
}