{
  "type": "Feature",
  "properties": {
    "iso:country":"CA",
    "sg:city":"Rimouski",
    "sg:classifiers":[
        {
            "category":"Shopping",
            "subcategory":"Clothing, Apparel, & Fashions",
            "type":"Retail Goods"
        }
    ],
    "sg:phone":"+1 418 722 8689",
    "sg:postcode":"G5L 3H8",
    "sg:province":"QC",
    "sg:tags":[
        "item",
        "boutique"
    ],
    "wof:name":"Boutique Revue Inc",
    "wof:placetype":"venue"
},
  "geometry": {"coordinates":[-68.52424621580001,48.4528198242],"type":"Point"}
}