{
  "type": "Feature",
  "properties": {
    "addr:full":"180 Rue Des Grands Espaces Mcwatters QC J9X 5B7",
    "addr:housenumber":"180",
    "addr:postcode":"j9x 5b7",
    "addr:street":"Rue Des Grands Espaces",
    "iso:country":"CA",
    "sg:address":"180 Rue Des Grands Espaces",
    "sg:city":"Mcwatters",
    "sg:classifiers":[
        {
            "category":"Wholesale",
            "subcategory":"Groceries",
            "type":"Manufacturing & Wholesale Goods"
        }
    ],
    "sg:phone":"+1 819 797 0708",
    "sg:postcode":"J9X 5B7",
    "sg:province":"QC",
    "sg:tags":[
        "food",
        "broker"
    ],
    "wof:name":"Rejean Turgeon Inc",
    "wof:placetype":"venue"
},
  "geometry": {"coordinates":[-78.9568099976,48.2150268555],"type":"Point"}
}