{
  "type": "Feature",
  "properties": {
    "iso:country":"CA",
    "sg:address":"805 King St N",
    "sg:city":"Waterloo",
    "sg:classifiers":[
        {
            "category":"Shopping",
            "subcategory":"Used Merchandise",
            "type":"Retail Goods"
        }
    ],
    "sg:phone":"+1 519 725 2644",
    "sg:postcode":"N2J 4G8",
    "sg:province":"ON",
    "sg:tags":[
        "antique"
    ],
    "wof:name":"Waterloo County Antique",
    "wof:placetype":"venue"
},
  "geometry": {"coordinates":[-80.54219818120001,43.5094604492],"type":"Point"}
}