{
  "type": "Feature",
  "properties": {
    "addr:full":"5568 Ch DE L'Aeroport Valcourt QC J0E 2L0",
    "addr:postcode":"5568;j0e 2l0",
    "addr:street":"Ch De L'Aeroport",
    "iso:country":"CA",
    "sg:address":"5568 Ch DE L'Aeroport",
    "sg:city":"Valcourt",
    "sg:classifiers":[
        {
            "category":"Building & Trades",
            "subcategory":"Construction",
            "type":"Services"
        }
    ],
    "sg:phone":"+1 450 532 2341",
    "sg:postcode":"J0E 2L0",
    "sg:province":"QC",
    "sg:tags":[
        "excavating",
        "contractor"
    ],
    "wof:name":"Leon Bombardier Inc",
    "wof:placetype":"venue"
},
  "geometry": {"coordinates":[-72.3921508789,45.027431488],"type":"Point"}
}