{
  "type": "Feature",
  "properties": {
    "iso:country":"CA",
    "sg:address":"3711 Main St W",
    "sg:city":"Stevensville",
    "sg:classifiers":[
        {
            "category":"Building & Trades",
            "subcategory":"Plumbing",
            "type":"Services"
        }
    ],
    "sg:phone":"+1 905 382 3133",
    "sg:postcode":"L0S 1S0",
    "sg:province":"ON",
    "sg:tags":[
        "conditioning",
        "contractor",
        "system",
        "air"
    ],
    "wof:name":"J W Furness Plumbing & Heating",
    "wof:placetype":"venue"
},
  "geometry": {"coordinates":[-79.0551376343,42.944480896],"type":"Point"}
}