{
  "type": "Feature",
  "properties": {
    "addr:full":"3120 Dougall Ave Windsor ON N9E 1S7",
    "addr:housenumber":"3120",
    "addr:postcode":"n9e 1s7",
    "addr:street":"Dougall Ave",
    "iso:country":"CA",
    "sg:address":"3120 Dougall Ave",
    "sg:city":"Windsor",
    "sg:classifiers":[
        {
            "category":"Restaurant",
            "type":"Food & Drink"
        }
    ],
    "sg:phone":"+1 519 966 1402",
    "sg:postcode":"N9E 1S7",
    "sg:province":"ON",
    "wof:name":"Mc Donald's",
    "wof:placetype":"venue"
},
  "geometry": {"coordinates":[-83.01181,42.270012],"type":"Point"}
}