{
  "type": "Feature",
  "properties": {
    "addr:full":"149 Yeomans St Belleville ON K8P 3Y1",
    "addr:housenumber":"149",
    "addr:postcode":"k8p 3y1",
    "addr:street":"Yeomans St",
    "iso:country":"CA",
    "sg:address":"149 Yeomans St",
    "sg:city":"Belleville",
    "sg:classifiers":[
        {
            "category":"Building & Trades",
            "subcategory":"Construction",
            "type":"Services"
        }
    ],
    "sg:phone":"+1 613 962 2936",
    "sg:postcode":"K8P 3Y1",
    "sg:province":"ON",
    "sg:tags":[
        "painter"
    ],
    "wof:name":"G & Son Painting & Decorating",
    "wof:placetype":"venue"
},
  "geometry": {"coordinates":[-77.3991851807,44.1679840088],"type":"Point"}
}