{
  "type": "Feature",
  "properties": {
    "iso:country":"CA",
    "sg:address":"46 Orangewood Blvd",
    "sg:city":"Chatham",
    "sg:classifiers":[
        {
            "category":"Organizations",
            "subcategory":"Religious Organization",
            "type":"Services"
        }
    ],
    "sg:phone":"+1 519 354 8353",
    "sg:postcode":"N7L 5H1",
    "sg:province":"ON",
    "sg:tags":[
        "church"
    ],
    "wof:name":"Salvation Army",
    "wof:placetype":"venue"
},
  "geometry": {"coordinates":[-82.2113952637,42.4158287048],"type":"Point"}
}