{
  "type": "Feature",
  "properties": {
    "iso:country":"CA",
    "sg:address":"1321 Rue Roberval",
    "sg:city":"Saint-Bruno",
    "sg:classifiers":[
        {
            "category":"Shopping",
            "subcategory":"Clothing, Apparel, & Fashions",
            "type":"Retail Goods"
        }
    ],
    "sg:phone":"+1 450 653 0354",
    "sg:postcode":"J3V 5J1",
    "sg:province":"QC",
    "wof:name":"Mode Le Grenier Inc",
    "wof:placetype":"venue"
},
  "geometry": {"coordinates":[-71.67552185060001,48.4717712402],"type":"Point"}
}