{
  "type": "Feature",
  "properties": {
    "addr:full":"3103 6 Ave N Lethbridge AB T1H 5B9",
    "addr:housenumber":"3103",
    "addr:postcode":"t1h 5b9",
    "addr:street":"6 Ave N",
    "iso:country":"CA",
    "sg:address":"3103 6 Ave N",
    "sg:city":"Lethbridge",
    "sg:classifiers":[
        {
            "category":"Home & Garden",
            "subcategory":"Building Materials",
            "type":"Retail Goods"
        }
    ],
    "sg:phone":"+1 403 327 8506",
    "sg:postcode":"T1H 5B9",
    "sg:province":"AB",
    "sg:tags":[
        "plywood",
        "veneer"
    ],
    "wof:name":"Windsor Plywood",
    "wof:placetype":"venue"
},
  "geometry": {"coordinates":[-112.79632599999999,49.708504],"type":"Point"}
}