{
  "type": "Feature",
  "properties": {
    "iso:country":"CA",
    "sg:address":"5300 Yonge St",
    "sg:city":"North York",
    "sg:classifiers":[
        {
            "category":"Wholesale",
            "subcategory":"Home Furnishings",
            "type":"Manufacturing & Wholesale Goods"
        }
    ],
    "sg:phone":"+1 416 224 9489",
    "sg:postcode":"M2N 5R2",
    "sg:province":"ON",
    "sg:tags":[
        "venetian",
        "blind"
    ],
    "wof:name":"Designer Shade & Interiors",
    "wof:placetype":"venue"
},
  "geometry": {"coordinates":[-79.413895,43.772541],"type":"Point"}
}