{
  "type": "Feature",
  "properties": {
    "addr:full":"Chibougamau QC G8P 1N3",
    "addr:postcode":"g8p 1n3",
    "iso:country":"CA",
    "sg:city":"Chibougamau",
    "sg:classifiers":[
        {
            "category":"Cinema",
            "subcategory":"Movie Rental",
            "type":"Entertainment"
        }
    ],
    "sg:phone":"+1 418 748 3892",
    "sg:postcode":"G8P 1N3",
    "sg:province":"QC",
    "sg:tags":[
        "leasing",
        "video",
        "disc",
        "tape"
    ],
    "wof:name":"Video Club 317",
    "wof:placetype":"venue"
},
  "geometry": {"coordinates":[-74.355125,49.913792],"type":"Point"}
}