{
  "type": "Feature",
  "properties": {
    "iso:country":"CA",
    "sg:address":"107 172 Rte E",
    "sg:city":"St-Nazaire-Du-Lac-St-Jean",
    "sg:classifiers":[
        {
            "category":"Farming",
            "subcategory":"Farm",
            "type":"Manufacturing & Wholesale Goods"
        }
    ],
    "sg:phone":"+1 418 662 2479",
    "sg:postcode":"G0W 2V0",
    "sg:province":"QC",
    "wof:name":"Ferme LA Terre Promise",
    "wof:placetype":"venue"
},
  "geometry": {"coordinates":[-71.4889297485,48.5756187439],"type":"Point"}
}