{
  "type": "Feature",
  "properties": {
    "addr:full":"3578 Ch Du Souvenir Laval QC H7V 1X2",
    "addr:housenumber":"3578",
    "addr:postcode":"h7v 1x2",
    "addr:street":"Ch Du Souvenir",
    "iso:country":"CA",
    "sg:address":"3578 Ch Du Souvenir",
    "sg:city":"Laval",
    "sg:classifiers":[
        {
            "category":"Home & Garden",
            "subcategory":"Building Materials",
            "type":"Retail Goods"
        }
    ],
    "sg:phone":"+1 450 682 8928",
    "sg:postcode":"H7V 1X2",
    "sg:province":"QC",
    "sg:tags":[
        "windows"
    ],
    "wof:name":"Traitement Des Fentres-Laval",
    "wof:placetype":"venue"
},
  "geometry": {"coordinates":[-73.7491607666,45.5507202148],"type":"Point"}
}