{
  "type": "Feature",
  "properties": {
    "addr:full":"52 Albert St W Alliston ON L9R 1H2",
    "addr:housenumber":"52",
    "addr:postcode":"l9r 1h2",
    "addr:street":"Albert St W Alliston",
    "iso:country":"CA",
    "sg:address":"52 Albert St W",
    "sg:city":"Alliston",
    "sg:classifiers":[
        {
            "category":"Organizations",
            "subcategory":"Community Association",
            "type":"Services"
        }
    ],
    "sg:phone":"+1 705 435 7731",
    "sg:postcode":"L9R 1H2",
    "sg:province":"ON",
    "sg:tags":[
        "club"
    ],
    "wof:name":"Alliston Curling Club Inc",
    "wof:placetype":"venue"
},
  "geometry": {"coordinates":[-79.87022399999999,44.150433],"type":"Point"}
}