{
  "type": "Feature",
  "properties": {
    "addr:full":"21 Manitou Dr Kitchener ON N2C 1K9",
    "addr:housenumber":"21",
    "addr:postcode":"n2c 1k9",
    "addr:street":"Manitou Dr",
    "iso:country":"CA",
    "sg:address":"21 Manitou Dr",
    "sg:city":"Kitchener",
    "sg:classifiers":[
        {
            "category":"Wholesale",
            "subcategory":"Auto Parts",
            "type":"Manufacturing & Wholesale Goods"
        }
    ],
    "sg:phone":"+1 519 894 1450",
    "sg:postcode":"N2C 1K9",
    "sg:province":"ON",
    "sg:tags":[
        "automobile",
        "wrecking"
    ],
    "wof:name":"Parkway Auto Recyclers",
    "wof:placetype":"venue"
},
  "geometry": {"coordinates":[-80.45207977290001,43.4172897339],"type":"Point"}
}