{
  "type": "Feature",
  "properties": {
    "addr:full":"80 Rue DE Bresoles Montreal QC H2Y 1V5",
    "addr:housenumber":"80",
    "addr:postcode":"h2y 1v5",
    "addr:street":"Rue De Bresoles",
    "iso:country":"CA",
    "sg:address":"80 Rue DE Bresoles",
    "sg:city":"Montreal",
    "sg:classifiers":[
        {
            "category":"Professional",
            "subcategory":"Computer Services",
            "type":"Services"
        }
    ],
    "sg:phone":"+1 514 282 6699",
    "sg:postcode":"H2Y 1V5",
    "sg:province":"QC",
    "sg:tags":[
        "information",
        "system",
        "consultant"
    ],
    "wof:name":"Mac 911",
    "wof:placetype":"venue"
},
  "geometry": {"coordinates":[-73.5554656982,45.5048561096],"type":"Point"}
}