{
  "type": "Feature",
  "properties": {
    "iso:country":"CA",
    "sg:address":"240 Marilyn Ave",
    "sg:city":"Napanee",
    "sg:classifiers":[
        {
            "category":"Education",
            "subcategory":"School",
            "type":"Public Place"
        }
    ],
    "sg:phone":"+1 613 354 9500",
    "sg:postcode":"K7R 2L4",
    "sg:province":"ON",
    "wof:name":"J J O'Neill Catholic School",
    "wof:placetype":"venue"
},
  "geometry": {"coordinates":[-76.96421051030001,44.2475814819],"type":"Point"}
}