{
  "type": "Feature",
  "properties": {
    "iso:country":"CA",
    "sg:address":"50 Mill St N",
    "sg:city":"Newcastle",
    "sg:classifiers":[
        {
            "category":"Wholesale",
            "subcategory":"Drugs",
            "type":"Manufacturing & Wholesale Goods"
        }
    ],
    "sg:phone":"+1 905 987 7224",
    "sg:postcode":"L1B 1L4",
    "sg:province":"ON",
    "sg:tags":[
        "pharmaceutical",
        "product"
    ],
    "wof:name":"Logan Pharmaceuticals",
    "wof:placetype":"venue"
},
  "geometry": {"coordinates":[-78.58940887449999,43.9182434082],"type":"Point"}
}