{
  "type": "Feature",
  "properties": {
    "addr:full":"2092 Rue Du Pere-Lalemant Jonquiere QC G7X 6H3",
    "addr:housenumber":"2092",
    "addr:postcode":"g7x 6h3",
    "addr:street":"Rue Du Pere-Lalemant",
    "iso:country":"CA",
    "sg:address":"2092 Rue Du Pere-Lalemant",
    "sg:city":"Jonquiere",
    "sg:classifiers":[
        {
            "category":"Retail",
            "subcategory":"Auto Repair",
            "type":"Services"
        }
    ],
    "sg:phone":"+1 418 542 2408",
    "sg:postcode":"G7X 6H3",
    "sg:province":"QC",
    "sg:tags":[
        "repairing",
        "automobile"
    ],
    "wof:name":"Garage Gerard Tremblay Fils",
    "wof:placetype":"venue"
},
  "geometry": {"coordinates":[-71.2519836426,48.4191474915],"type":"Point"}
}