{
  "type": "Feature",
  "properties": {
    "addr:full":"407 Mcdermot Ave Winnipeg MB R3A 0A8",
    "addr:housenumber":"407",
    "addr:postcode":"r3a 0a8",
    "addr:street":"Mcdermot Ave",
    "iso:country":"CA",
    "sg:address":"407 Mcdermot Ave",
    "sg:city":"Winnipeg",
    "sg:classifiers":[
        {
            "category":"Manufacturing",
            "subcategory":"Printing",
            "type":"Manufacturing & Wholesale Goods"
        }
    ],
    "sg:phone":"+1 204 949 0363",
    "sg:postcode":"R3A 0A8",
    "sg:province":"MB",
    "sg:tags":[
        "screen"
    ],
    "wof:name":"Screentech Printers",
    "wof:placetype":"venue"
},
  "geometry": {"coordinates":[-97.147026,49.899357],"type":"Point"}
}