{
  "type": "Feature",
  "properties": {
    "addr:full":"9688 Leslie St # 1 Richmond Hill ON L4B 4C4",
    "addr:housenumber":"9688",
    "addr:postcode":"l4b 4c4",
    "addr:street":"Leslie St # 1",
    "iso:country":"CA",
    "sg:address":"9688 Leslie St # 1",
    "sg:city":"Richmond Hill",
    "sg:classifiers":[
        {
            "category":"Professional",
            "subcategory":"Computer Services",
            "type":"Services"
        }
    ],
    "sg:phone":"+1 905 508 3400",
    "sg:postcode":"L4B 4C4",
    "sg:province":"ON",
    "sg:tags":[
        "consultant"
    ],
    "wof:name":"Advanced System Patronage Inc",
    "wof:placetype":"venue"
},
  "geometry": {"coordinates":[-79.3897476196,43.8730278015],"type":"Point"}
}