{
  "type": "Feature",
  "properties": {
    "addr:full":"9910 97 Ave Peace River AB T8S 1H6",
    "addr:housenumber":"9910",
    "addr:postcode":"t8s 1h6",
    "addr:street":"97 Ave",
    "iso:country":"CA",
    "sg:address":"9910 97 Ave",
    "sg:city":"Peace River",
    "sg:classifiers":[
        {
            "category":"Professional",
            "subcategory":"Lawyer & Legal Services",
            "type":"Services"
        }
    ],
    "sg:phone":"+1 780 624 1122",
    "sg:postcode":"T8S 1H6",
    "sg:province":"AB",
    "sg:tags":[
        "attorney"
    ],
    "wof:name":"Murphy, Amy K",
    "wof:placetype":"venue"
},
  "geometry": {"coordinates":[-117.29196167000001,56.2365379333],"type":"Point"}
}