{
  "type": "Feature",
  "properties": {
    "addr:full":"16700 Bayview Ave Newmarket ON L3X 1W1",
    "addr:housenumber":"16700",
    "addr:postcode":"l3x 1w1",
    "addr:street":"Bayview Ave",
    "iso:country":"CA",
    "sg:address":"16700 Bayview Ave",
    "sg:city":"Newmarket",
    "sg:classifiers":[
        {
            "category":"Organizations",
            "subcategory":"Religious Organization",
            "type":"Services"
        }
    ],
    "sg:phone":"+1 905 853 6567",
    "sg:postcode":"L3X 1W1",
    "sg:province":"ON",
    "sg:tags":[
        "church"
    ],
    "wof:name":"Saint Timothy Church",
    "wof:placetype":"venue"
},
  "geometry": {"coordinates":[-79.451927,44.040298],"type":"Point"}
}