{
  "type": "Feature",
  "properties": {
    "addr:full":"Charlottetown PE C1A 8T5",
    "addr:postcode":"c1a 8t5",
    "iso:country":"CA",
    "sg:city":"Charlottetown",
    "sg:classifiers":[
        {
            "category":"Health Services",
            "subcategory":"Doctor",
            "type":"Services"
        }
    ],
    "sg:phone":"+1 902 894 2027",
    "sg:postcode":"C1A 8T5",
    "sg:province":"PE",
    "sg:tags":[
        "physician",
        "surgeon"
    ],
    "wof:name":"Dryer, Dagney MD",
    "wof:placetype":"venue"
},
  "geometry": {"coordinates":[-63.1473121643,46.2322540283],"type":"Point"}
}