{
  "type": "Feature",
  "properties": {
    "iso:country":"CA",
    "sg:address":"11 Ordnance St",
    "sg:city":"Toronto",
    "sg:classifiers":[
        {
            "category":"Government",
            "subcategory":"Fire Station",
            "type":"Public Place"
        }
    ],
    "sg:phone":"+1 ",
    "sg:postcode":"M6K 1A1",
    "sg:province":"ON",
    "sg:tags":[
        "department"
    ],
    "wof:name":"Toronto Fire Apparatus",
    "wof:placetype":"venue"
},
  "geometry": {"coordinates":[-79.4095077515,43.6391220093],"type":"Point"}
}