{
  "type": "Feature",
  "properties": {
    "addr:full":"North Vancouver BC V7L 2N3",
    "addr:postcode":"v7l 2n3",
    "iso:country":"CA",
    "sg:city":"North Vancouver",
    "sg:classifiers":[
        {
            "category":"Food & Beverages",
            "subcategory":"Meat & Fish",
            "type":"Retail Goods"
        }
    ],
    "sg:phone":"+1 604 985 2412",
    "sg:postcode":"V7L 2N3",
    "sg:province":"BC",
    "wof:name":"North Shore Quality Meats",
    "wof:placetype":"venue"
},
  "geometry": {"coordinates":[-123.071136475,49.3211746216],"type":"Point"}
}