{
  "type": "Feature",
  "properties": {
    "addr:full":"1800 4th St SW Calgary AB T2S 2S4",
    "addr:housenumber":"1800",
    "addr:postcode":"t2s 2s4",
    "addr:street":"4Th St Sw",
    "iso:country":"CA",
    "sg:address":"1800 4th St SW",
    "sg:city":"Calgary",
    "sg:classifiers":[
        {
            "category":"Personal",
            "subcategory":"Beauty Salon",
            "type":"Services"
        }
    ],
    "sg:phone":"+1 403 234 0697",
    "sg:postcode":"T2S 2S4",
    "sg:province":"AB",
    "wof:name":"Shampers of London Hair Design",
    "wof:placetype":"venue"
},
  "geometry": {"coordinates":[-114.071411133,51.0368652344],"type":"Point"}
}