{
  "type": "Feature",
  "properties": {
    "addr:full":"Timmins ON P4N 2K3",
    "addr:postcode":"p4n 2k3",
    "iso:country":"CA",
    "sg:city":"Timmins",
    "sg:classifiers":[
        {
            "category":"Health Services",
            "subcategory":"Chiropractor",
            "type":"Services"
        }
    ],
    "sg:phone":"+1 705 267 5856",
    "sg:postcode":"P4N 2K3",
    "sg:province":"ON",
    "wof:name":"Russell, D K DC",
    "wof:placetype":"venue"
},
  "geometry": {"coordinates":[-81.3284988403,48.4736404419],"type":"Point"}
}