{
  "type": "Feature",
  "properties": {
    "addr:full":"5 Rue Saint-Charles L'Ile-Bizard QC H9C 1L4",
    "addr:housenumber":"5",
    "addr:postcode":"h9c 1l4",
    "addr:street":"Rue Saint-Charles",
    "iso:country":"CA",
    "sg:address":"5 Rue Saint-Charles",
    "sg:city":"L'Ile-Bizard",
    "sg:classifiers":[
        {
            "category":"Retail",
            "subcategory":"Auto Repair",
            "type":"Services"
        }
    ],
    "sg:phone":"+1 514 620 9252",
    "sg:postcode":"H9C 1L4",
    "sg:province":"QC",
    "sg:tags":[
        "transmission"
    ],
    "wof:name":"Autopital Enrg",
    "wof:placetype":"venue"
},
  "geometry": {"coordinates":[-73.8790359497,45.4895210266],"type":"Point"}
}