{
  "type": "Feature",
  "properties": {
    "addr:full":"Victoria BC V8R 1C9",
    "addr:postcode":"v8r 1c9",
    "iso:country":"CA",
    "sg:city":"Victoria",
    "sg:classifiers":[
        {
            "category":"Restaurant",
            "type":"Food & Drink"
        }
    ],
    "sg:phone":"+1 250 595 3021",
    "sg:postcode":"V8R 1C9",
    "sg:province":"BC",
    "wof:name":"Mee Wah Restaurant Ltd",
    "wof:placetype":"venue"
},
  "geometry": {"coordinates":[-123.32415,48.426594],"type":"Point"}
}