{
  "type": "Feature",
  "properties": {
    "addr:full":"751 Marine Dr North Vancouver BC V7M 1H4",
    "addr:housenumber":"751",
    "addr:postcode":"v7m 1h4",
    "addr:street":"Marine Dr",
    "iso:country":"CA",
    "sg:address":"751 Marine Dr",
    "sg:city":"North Vancouver",
    "sg:classifiers":[
        {
            "category":"Retail",
            "subcategory":"Auto Rental",
            "type":"Services"
        }
    ],
    "sg:phone":"+1 604 988 5878",
    "sg:postcode":"V7M 1H4",
    "sg:province":"BC",
    "sg:tags":[
        "renting",
        "automobile"
    ],
    "wof:name":"Enterprise Rent-A-Car",
    "wof:placetype":"venue"
},
  "geometry": {"coordinates":[-123.094261,49.320896],"type":"Point"}
}