{
  "type": "Feature",
  "properties": {
    "addr:full":"38 Helmcken Rd Victoria BC V8Z 5G7",
    "addr:housenumber":"38",
    "addr:postcode":"v8z 5g7",
    "addr:street":"Helmcken Rd",
    "iso:country":"CA",
    "sg:address":"38 Helmcken Rd",
    "sg:city":"Victoria",
    "sg:classifiers":[
        {
            "category":"Food & Beverages",
            "subcategory":"Groceries & Convenience Stores",
            "type":"Retail Goods"
        }
    ],
    "sg:phone":"+1 250 479 1818",
    "sg:postcode":"V8Z 5G7",
    "sg:province":"BC",
    "sg:tags":[
        "florist"
    ],
    "wof:name":"Helmcken Market",
    "wof:placetype":"venue"
},
  "geometry": {"coordinates":[-123.36451700000001,48.428314],"type":"Point"}
}