{
  "type": "Feature",
  "properties": {
    "addr:full":"1870 Rue Davidson Montreal QC H1W 2Y6",
    "addr:housenumber":"1870",
    "addr:postcode":"h1w 2y6",
    "addr:street":"Rue Davidson",
    "iso:country":"CA",
    "sg:address":"1870 Rue Davidson",
    "sg:city":"Montreal",
    "sg:classifiers":[
        {
            "category":"Recreation",
            "type":"Entertainment"
        }
    ],
    "sg:phone":"+1 514 872 2105",
    "sg:postcode":"H1W 2Y6",
    "sg:province":"QC",
    "sg:tags":[
        "pool",
        "swimming"
    ],
    "wof:name":"Piscines Hochelaga",
    "wof:placetype":"venue"
},
  "geometry": {"coordinates":[-73.5457229614,45.5427856445],"type":"Point"}
}