{
  "type": "Feature",
  "properties": {
    "addr:full":"Edmonton AB T5G 3C8",
    "addr:postcode":"t5g 3c8",
    "iso:country":"CA",
    "sg:city":"Edmonton",
    "sg:classifiers":[
        {
            "category":"Health Services",
            "subcategory":"Doctor",
            "type":"Services"
        }
    ],
    "sg:phone":"+1 780 428 6944",
    "sg:postcode":"T5G 3C8",
    "sg:province":"AB",
    "sg:tags":[
        "physician",
        "surgeon"
    ],
    "wof:name":"Wong, Jean MD",
    "wof:placetype":"venue"
},
  "geometry": {"coordinates":[-113.503082275,53.5583457947],"type":"Point"}
}