{
  "type": "Feature",
  "properties": {
    "addr:full":"158 Cooperage Cres Richmond Hill ON L4C 9K8",
    "addr:housenumber":"158",
    "addr:postcode":"l4c 9k8",
    "addr:street":"Cooperage Cres",
    "iso:country":"CA",
    "sg:address":"158 Cooperage Cres",
    "sg:city":"Richmond Hill",
    "sg:classifiers":[
        {
            "category":"Professional",
            "subcategory":"Art Services",
            "type":"Services"
        }
    ],
    "sg:phone":"+1 905 883 0111",
    "sg:postcode":"L4C 9K8",
    "sg:province":"ON",
    "sg:tags":[
        "graphic",
        "designer"
    ],
    "wof:name":"Alive Design Inc",
    "wof:placetype":"venue"
},
  "geometry": {"coordinates":[-79.4514465332,43.8896598816],"type":"Point"}
}