{
  "type": "Feature",
  "properties": {
    "addr:full":"3043 Boul Saint-Jean-Baptiste Chicoutimi QC G7H 7T1",
    "addr:housenumber":"3043",
    "addr:postcode":"g7h 7t1",
    "addr:street":"Boul Saint-Jean-Baptiste",
    "iso:country":"CA",
    "sg:address":"3043 Boul Saint-Jean-Baptiste",
    "sg:city":"Chicoutimi",
    "sg:classifiers":[
        {
            "category":"Food & Beverages",
            "subcategory":"Groceries & Convenience Stores",
            "type":"Retail Goods"
        }
    ],
    "sg:phone":"+1 418 549 2367",
    "sg:postcode":"G7H 7T1",
    "sg:province":"QC",
    "sg:tags":[
        "grocer"
    ],
    "wof:name":"Epicerie A Lavoie Ltee",
    "wof:placetype":"venue"
},
  "geometry": {"coordinates":[-70.978553772,48.3892822266],"type":"Point"}
}