{
  "type": "Feature",
  "properties": {
    "addr:full":"644 Du College Saint-Theophile QC G0M 2A0",
    "addr:housenumber":"644",
    "addr:postcode":"g0m 2a0",
    "addr:street":"Du College Saint-Theophile",
    "iso:country":"CA",
    "sg:address":"644 Du College",
    "sg:city":"Saint-Theophile",
    "sg:classifiers":[
        {
            "category":"Government",
            "subcategory":"Office",
            "type":"Public Place"
        }
    ],
    "sg:phone":"+1 418 597 3998",
    "sg:postcode":"G0M 2A0",
    "sg:province":"QC",
    "sg:tags":[
        "village"
    ],
    "wof:name":"Municipalite DE St-Theophile",
    "wof:placetype":"venue"
},
  "geometry": {"coordinates":[-70.484573,45.936161],"type":"Point"}
}