{
  "type": "Feature",
  "properties": {
    "addr:full":"1550 Huron Church Rd Windsor ON N9C 3Z3",
    "addr:housenumber":"1550",
    "addr:postcode":"n9c 3z3",
    "addr:street":"Huron Church Rd",
    "iso:country":"CA",
    "sg:address":"1550 Huron Church Rd",
    "sg:city":"Windsor",
    "sg:classifiers":[
        {
            "category":"Shopping",
            "subcategory":"Pharmacy",
            "type":"Retail Goods"
        }
    ],
    "sg:phone":"+1 519 254 1106",
    "sg:postcode":"N9C 3Z3",
    "sg:province":"ON",
    "wof:name":"Zellers Pharmacy",
    "wof:placetype":"venue"
},
  "geometry": {"coordinates":[-83.0583648682,42.2884750366],"type":"Point"}
}