{
  "type": "Feature",
  "properties": {
    "addr:full":"Manitou Rd Manitouwadge ON P0T 2C0",
    "addr:postcode":"p0t 2c0",
    "addr:street":"Manitou Rd",
    "iso:country":"CA",
    "sg:address":"Manitou Rd",
    "sg:city":"Manitouwadge",
    "sg:phone":"+1 807 826 4904",
    "sg:postcode":"P0T 2C0",
    "sg:province":"ON",
    "sg:tags":[
        "oil"
    ],
    "wof:name":"Manitouwadge Fuels Ltd",
    "wof:placetype":"venue"
},
  "geometry": {"coordinates":[-85.843361,49.117805],"type":"Point"}
}