{
  "type": "Feature",
  "properties": {
    "iso:country":"CA",
    "sg:address":"1980 Dundas St",
    "sg:city":"London",
    "sg:classifiers":[
        {
            "category":"Restaurant",
            "type":"Food & Drink"
        }
    ],
    "sg:phone":"+1 519 455 1339",
    "sg:postcode":"N5V 1P5",
    "sg:province":"ON",
    "sg:tags":[
        "parlor",
        "ice",
        "cream"
    ],
    "wof:name":"Dairy Queen",
    "wof:placetype":"venue"
},
  "geometry": {"coordinates":[-81.17189,43.005993],"type":"Point"}
}