{
  "type": "Feature",
  "properties": {
    "iso:country":"CA",
    "sg:address":"1297 Rue Des Erables",
    "sg:city":"Saint-Lambert-DE-Lauzon",
    "sg:classifiers":[
        {
            "category":"Health Services",
            "subcategory":"Nursing And Care Facility",
            "type":"Services"
        }
    ],
    "sg:phone":"+1 418 889 0950",
    "sg:postcode":"G0S 2W0",
    "sg:province":"QC",
    "sg:tags":[
        "home",
        "retirement",
        "community"
    ],
    "wof:name":"Petit Domicile St-Lambert",
    "wof:placetype":"venue"
},
  "geometry": {"coordinates":[-71.2102279663,46.5855522156],"type":"Point"}
}