{
  "type": "Feature",
  "properties": {
    "iso:country":"CA",
    "sg:city":"Windsor",
    "sg:classifiers":[
        {
            "category":"Banks & Credit Unions",
            "subcategory":"Investment Brokerage",
            "type":"Services"
        }
    ],
    "sg:phone":"+1 519 974 6688",
    "sg:postcode":"N8W 5K8",
    "sg:province":"ON",
    "sg:tags":[
        "insurance"
    ],
    "wof:name":"Seguin & Assoc Financial Svc",
    "wof:placetype":"venue"
},
  "geometry": {"coordinates":[-82.9699020386,42.2820167542],"type":"Point"}
}