{
  "type": "Feature",
  "properties": {
    "addr:full":"380 Dundas St E Oakville ON L6H 6Z9",
    "addr:housenumber":"380",
    "addr:postcode":"l6h 6z9",
    "addr:street":"Dundas St E",
    "iso:country":"CA",
    "sg:address":"380 Dundas St E",
    "sg:city":"Oakville",
    "sg:classifiers":[
        {
            "category":"Restaurant",
            "type":"Food & Drink"
        }
    ],
    "sg:phone":"+1 905 257 9644",
    "sg:postcode":"L6H 6Z9",
    "sg:province":"ON",
    "wof:name":"Roxy's",
    "wof:placetype":"venue"
},
  "geometry": {"coordinates":[-79.717583,43.489483],"type":"Point"}
}