{
  "type": "Feature",
  "properties": {
    "addr:full":"Lambton QC G0M 1H0",
    "addr:postcode":"g0m 1h0",
    "iso:country":"CA",
    "sg:city":"Lambton",
    "sg:classifiers":[
        {
            "category":"Building & Trades",
            "subcategory":"Construction",
            "type":"Services"
        }
    ],
    "sg:phone":"+1 819 832 3883",
    "sg:postcode":"G0M 1H0",
    "sg:province":"QC",
    "sg:tags":[
        "product",
        "paving",
        "asphalt",
        "contractor"
    ],
    "wof:name":"Pavages St-Francois Inc",
    "wof:placetype":"venue"
},
  "geometry": {"coordinates":[-71.1122131348,45.8481864929],"type":"Point"}
}