{
  "type": "Feature",
  "properties": {
    "addr:full":"610 Grierson Ave Winnipeg MB R3T 2S1",
    "addr:housenumber":"610",
    "addr:postcode":"r3t 2s1",
    "addr:street":"Grierson Ave",
    "iso:country":"CA",
    "sg:address":"610 Grierson Ave",
    "sg:city":"Winnipeg",
    "sg:classifiers":[
        {
            "category":"Arts & Performance",
            "subcategory":"Theater",
            "type":"Entertainment"
        }
    ],
    "sg:phone":"+1 204 261 7277",
    "sg:postcode":"R3T 2S1",
    "sg:province":"MB",
    "sg:tags":[
        "instruction",
        "music"
    ],
    "wof:name":"Bohdanna's Sounds of Music Std",
    "wof:placetype":"venue"
},
  "geometry": {"coordinates":[-97.13455963129999,49.8037948608],"type":"Point"}
}