{
  "type": "Feature",
  "properties": {
    "addr:full":"363 Collishaw St Moncton NB E1C 9R2",
    "addr:housenumber":"363",
    "addr:postcode":"e1c 9r2",
    "addr:street":"Collishaw St",
    "iso:country":"CA",
    "sg:address":"363 Collishaw St",
    "sg:city":"Moncton",
    "sg:classifiers":[
        {
            "category":"Banks & Credit Unions",
            "subcategory":"Bank",
            "type":"Services"
        }
    ],
    "sg:phone":"+1 506 863 0111",
    "sg:postcode":"E1C 9R2",
    "sg:province":"NB",
    "sg:tags":[
        "loan"
    ],
    "wof:name":"Bronswick Loan Acceptance",
    "wof:placetype":"venue"
},
  "geometry": {"coordinates":[-64.813316,46.097172],"type":"Point"}
}