{
  "type": "Feature",
  "properties": {
    "iso:country":"CA",
    "sg:address":"80 Rue Saint-Thomas",
    "sg:city":"Louiseville",
    "sg:classifiers":[
        {
            "category":"Personal",
            "subcategory":"Beauty Salon",
            "type":"Services"
        }
    ],
    "sg:phone":"+1 819 228 5540",
    "sg:postcode":"J5V 2A4",
    "sg:province":"QC",
    "wof:name":"Salon DE Coiffure L'Excellence",
    "wof:placetype":"venue"
},
  "geometry": {"coordinates":[-72.94296264650001,46.2545852661],"type":"Point"}
}