{
  "type": "Feature",
  "properties": {
    "iso:country":"CA",
    "sg:address":"484 Water St",
    "sg:city":"Newmarket",
    "sg:classifiers":[
        {
            "category":"Organizations",
            "subcategory":"Religious Organization",
            "type":"Services"
        }
    ],
    "sg:phone":"+1 905 895 5512",
    "sg:postcode":"L3Y 1M5",
    "sg:province":"ON",
    "sg:tags":[
        "church"
    ],
    "wof:name":"St Andrews Presbyterian Church",
    "wof:placetype":"venue"
},
  "geometry": {"coordinates":[-79.456444,44.051292],"type":"Point"}
}