{
  "type": "Feature",
  "properties": {
    "addr:full":"307 Rang Lepage Sainte-Anne-Des-Plaines QC J0N 1H0",
    "addr:housenumber":"307",
    "addr:postcode":"j0n 1h0",
    "addr:street":"Rang Lepage",
    "iso:country":"CA",
    "sg:address":"307 Rang Lepage",
    "sg:city":"Sainte-Anne-Des-Plaines",
    "sg:classifiers":[
        {
            "category":"Wholesale",
            "subcategory":"Hardware",
            "type":"Manufacturing & Wholesale Goods"
        }
    ],
    "sg:phone":"+1 450 478 5127",
    "sg:postcode":"J0N 1H0",
    "sg:province":"QC",
    "sg:tags":[
        "refrigerating"
    ],
    "wof:name":"Refrigeration Technique Plus",
    "wof:placetype":"venue"
},
  "geometry": {"coordinates":[-73.8033218384,45.7300720215],"type":"Point"}
}