{
  "type": "Feature",
  "properties": {
    "addr:full":"Lloydminster AB T9V 1N5",
    "addr:postcode":"t9v 1n5",
    "iso:country":"CA",
    "sg:city":"Lloydminster",
    "sg:classifiers":[
        {
            "category":"Building & Trades",
            "subcategory":"Construction",
            "type":"Services"
        }
    ],
    "sg:phone":"+1 780 875 8775",
    "sg:postcode":"T9V 1N5",
    "sg:province":"AB",
    "sg:tags":[
        "general",
        "contractor"
    ],
    "wof:name":"Square One Builders 1998 Ltd",
    "wof:placetype":"venue"
},
  "geometry": {"coordinates":[-110.01567077599999,53.2657814026],"type":"Point"}
}