{
  "type": "Feature",
  "properties": {
    "addr:full":"60 Copernicus Dr Sault Ste Marie ON P6A 6H2",
    "addr:housenumber":"60",
    "addr:postcode":"p6a 6h2",
    "addr:street":"Copernicus Dr",
    "iso:country":"CA",
    "sg:address":"60 Copernicus Dr",
    "sg:city":"Sault Ste Marie",
    "sg:classifiers":[
        {
            "category":"Building & Trades",
            "subcategory":"Construction",
            "type":"Services"
        }
    ],
    "sg:phone":"+1 705 946 7718",
    "sg:postcode":"P6A 6H2",
    "sg:province":"ON",
    "sg:tags":[
        "roofing",
        "contractor"
    ],
    "wof:name":"Dynamic Roofing",
    "wof:placetype":"venue"
},
  "geometry": {"coordinates":[-84.256371,46.512207],"type":"Point"}
}