{
  "type": "Feature",
  "properties": {
    "iso:country":"CA",
    "sg:city":"Pickering",
    "sg:classifiers":[
        {
            "category":"Professional",
            "subcategory":"Business Services",
            "type":"Services"
        }
    ],
    "sg:phone":"+1 905 426 7411",
    "sg:postcode":"L1W 3V4",
    "sg:province":"ON",
    "sg:tags":[
        "water",
        "treatment"
    ],
    "wof:name":"Aquarian Pure Water CO",
    "wof:placetype":"venue"
},
  "geometry": {"coordinates":[-79.0562667847,43.8264656067],"type":"Point"}
}