{
  "type": "Feature",
  "properties": {
    "addr:full":"1460 Sutherland Ave Kelowna BC V1Y 5Y5",
    "addr:housenumber":"1460",
    "addr:postcode":"v1y 5y5",
    "addr:street":"Sutherland Ave",
    "iso:country":"CA",
    "sg:address":"1460 Sutherland Ave",
    "sg:city":"Kelowna",
    "sg:classifiers":[
        {
            "category":"Social Services",
            "subcategory":"Adult Care",
            "type":"Services"
        }
    ],
    "sg:phone":"+1 250 860 2117",
    "sg:postcode":"V1Y 5Y5",
    "sg:province":"BC",
    "sg:tags":[
        "community",
        "facility"
    ],
    "wof:name":"Joseph Benjamin Residence",
    "wof:placetype":"venue"
},
  "geometry": {"coordinates":[-119.467094421,49.8803939819],"type":"Point"}
}