{
  "type": "Feature",
  "properties": {
    "addr:full":"Saint-Simeon-DE-Bonaventure QC G0C 3A0",
    "addr:postcode":"g0c 3a0",
    "iso:country":"CA",
    "sg:city":"Saint-Simeon-DE-Bonaventure",
    "sg:classifiers":[
        {
            "category":"Government",
            "subcategory":"Office",
            "type":"Public Place"
        }
    ],
    "sg:phone":"+1 418 534 3962",
    "sg:postcode":"G0C 3A0",
    "sg:province":"QC",
    "sg:tags":[
        "village"
    ],
    "wof:name":"St-Simeon Centre Multi-Recreat",
    "wof:placetype":"venue"
},
  "geometry": {"coordinates":[-65.5713806152,48.0707092285],"type":"Point"}
}