{
  "type": "Feature",
  "properties": {
    "addr:full":"408 Victoria St Nelson BC V1L 4K5",
    "addr:housenumber":"408",
    "addr:postcode":"bc v1l 4k5",
    "addr:street":"Victoria St",
    "iso:country":"CA",
    "sg:address":"408 Victoria St",
    "sg:city":"Nelson",
    "sg:classifiers":[
        {
            "category":"Travel",
            "subcategory":"Hotels & Motels",
            "type":"Entertainment"
        }
    ],
    "sg:phone":"+1 250 352 3226",
    "sg:postcode":"V1L 4K5",
    "sg:province":"BC",
    "sg:tags":[
        "breakfast",
        "accommodation",
        "bed"
    ],
    "wof:name":"Inn the Garden Bed & Breakfast",
    "wof:placetype":"venue"
},
  "geometry": {"coordinates":[-117.294342,49.490681],"type":"Point"}
}