{
  "type": "Feature",
  "properties": {
    "iso:country":"CA",
    "sg:city":"Chateauguay",
    "sg:classifiers":[
        {
            "category":"Insurance",
            "subcategory":"Insurance Agent",
            "type":"Services"
        }
    ],
    "sg:phone":"+1 450 699 6224",
    "sg:postcode":"J6K 3B4",
    "sg:province":"QC",
    "wof:name":"Assurances Ernest Lapointe",
    "wof:placetype":"venue"
},
  "geometry": {"coordinates":[-73.718773,45.354164],"type":"Point"}
}