{
  "type": "Feature",
  "properties": {
    "addr:full":"Pickle Lake ON P0V 3A0",
    "addr:postcode":"p0v 3a0",
    "iso:country":"CA",
    "sg:city":"Pickle Lake",
    "sg:classifiers":[
        {
            "category":"Government",
            "subcategory":"Office",
            "type":"Public Place"
        }
    ],
    "sg:phone":"+1 807 928 2870",
    "sg:postcode":"P0V 3A0",
    "sg:province":"ON",
    "wof:name":"Asin Contracting Ltd",
    "wof:placetype":"venue"
},
  "geometry": {"coordinates":[-90.1605377197,51.4813728333],"type":"Point"}
}