{
  "type": "Feature",
  "properties": {
    "addr:full":"236 Rue Champlain Saint-Jean-Sur-Richelieu QC J3B 6V8",
    "addr:housenumber":"236",
    "addr:postcode":"j3b 6v8",
    "addr:street":"Rue Champlain",
    "iso:country":"CA",
    "sg:address":"236 Rue Champlain",
    "sg:city":"Saint-Jean-Sur-Richelieu",
    "sg:classifiers":[
        {
            "category":"Restaurant",
            "type":"Food & Drink"
        }
    ],
    "sg:phone":"+1 450 346 0811",
    "sg:postcode":"J3B 6V8",
    "sg:province":"QC",
    "wof:name":"Restaurant Chez Noeser",
    "wof:placetype":"venue"
},
  "geometry": {"coordinates":[-73.25229644780001,45.3073043823],"type":"Point"}
}