{
  "type": "Feature",
  "properties": {
    "iso:country":"CA",
    "sg:address":"275 Lower Bench Rd",
    "sg:city":"Penticton",
    "sg:classifiers":[
        {
            "category":"Professional",
            "subcategory":"Management & Consulting",
            "type":"Services"
        }
    ],
    "sg:phone":"+1 250 492 5106",
    "sg:postcode":"V2A 1B2",
    "sg:province":"BC",
    "sg:tags":[
        "consultant",
        "business"
    ],
    "wof:name":"Graham Punnett & Assoc Ltd",
    "wof:placetype":"venue"
},
  "geometry": {"coordinates":[-119.576698303,49.5083694458],"type":"Point"}
}