{
  "type": "Feature",
  "properties": {
    "addr:full":"7575 Kilrea Cres Burnaby BC V5A 3N8",
    "addr:housenumber":"7575",
    "addr:postcode":"v5a 3n8",
    "addr:street":"Kilrea Cres",
    "iso:country":"CA",
    "sg:address":"7575 Kilrea Cres",
    "sg:city":"Burnaby",
    "sg:classifiers":[
        {
            "category":"Real Estate",
            "subcategory":"Surveying",
            "type":"Services"
        }
    ],
    "sg:phone":"+1 604 327 6275",
    "sg:postcode":"V5A 3N8",
    "sg:province":"BC",
    "sg:tags":[
        "surveyor"
    ],
    "wof:name":"Benchmark Surveys",
    "wof:placetype":"venue"
},
  "geometry": {"coordinates":[-122.943237,49.259315],"type":"Point"}
}