{
  "type": "Feature",
  "properties": {
    "iso:country":"CA",
    "sg:city":"Kingston",
    "sg:classifiers":[
        {
            "category":"Wholesale",
            "subcategory":"Auto Parts",
            "type":"Manufacturing & Wholesale Goods"
        }
    ],
    "sg:phone":"+1 613 384 7110",
    "sg:postcode":"K7M 4X2",
    "sg:province":"ON",
    "sg:tags":[
        "automobile",
        "supply"
    ],
    "wof:name":"Fisher Auto Parts & Equipment",
    "wof:placetype":"venue"
},
  "geometry": {"coordinates":[-76.541008,44.23843],"type":"Point"}
}