{
  "type": "Feature",
  "properties": {
    "addr:full":"437 Av Grosvenor Westmount QC H3Y 2S5",
    "addr:housenumber":"437",
    "addr:postcode":"h3y 2s5",
    "addr:street":"Av Grosvenor",
    "iso:country":"CA",
    "sg:address":"437 Av Grosvenor",
    "sg:city":"Westmount",
    "sg:classifiers":[
        {
            "category":"Wholesale",
            "subcategory":"Durable Goods & Equipment",
            "type":"Manufacturing & Wholesale Goods"
        }
    ],
    "sg:phone":"+1 514 932 5313",
    "sg:postcode":"H3Y 2S5",
    "sg:province":"QC",
    "sg:tags":[
        "importer"
    ],
    "wof:name":"Entreprises Turquand Inc",
    "wof:placetype":"venue"
},
  "geometry": {"coordinates":[-73.60391199999999,45.480328],"type":"Point"}
}