{
  "type": "Feature",
  "properties": {
    "iso:country":"CA",
    "sg:address":"1225 Wonderland Rd N",
    "sg:city":"London",
    "sg:classifiers":[
        {
            "category":"Restaurant",
            "type":"Food & Drink"
        }
    ],
    "sg:phone":"+1 519 473 4567",
    "sg:postcode":"N6G 2V9",
    "sg:province":"ON",
    "wof:name":"Subway Sandwiches & Salads",
    "wof:placetype":"venue"
},
  "geometry": {"coordinates":[-81.303558,43.005066],"type":"Point"}
}