{
  "type": "Feature",
  "properties": {
    "iso:country":"CA",
    "sg:address":"375 Hartman Rd",
    "sg:city":"Kelowna",
    "sg:classifiers":[
        {
            "category":"Social Services",
            "subcategory":"Child Care",
            "type":"Services"
        }
    ],
    "sg:phone":"+1 250 765 4191",
    "sg:postcode":"V1X 2M9",
    "sg:province":"BC",
    "sg:tags":[
        "youth",
        "organization",
        "recreation",
        "center"
    ],
    "wof:name":"Kelowna Family Ymca-Ywca",
    "wof:placetype":"venue"
},
  "geometry": {"coordinates":[-119.381042,49.899796],"type":"Point"}
}