{
  "type": "Feature",
  "properties": {
    "addr:full":"2069 Lawrence Ave E Scarborough ON M1R 2Z4",
    "addr:housenumber":"2069",
    "addr:postcode":"m1r 2z4",
    "addr:street":"Lawrence Ave E",
    "iso:country":"CA",
    "sg:address":"2069 Lawrence Ave E",
    "sg:city":"Scarborough",
    "sg:classifiers":[
        {
            "category":"Food & Beverages",
            "subcategory":"Groceries & Convenience Stores",
            "type":"Retail Goods"
        }
    ],
    "sg:phone":"+1 416 288 9330",
    "sg:postcode":"M1R 2Z4",
    "sg:province":"ON",
    "sg:tags":[
        "grocer"
    ],
    "wof:name":"Uncle Seth Tropical Foods",
    "wof:placetype":"venue"
},
  "geometry": {"coordinates":[-79.29327392579999,43.7455482483],"type":"Point"}
}