{
  "type": "Feature",
  "properties": {
    "addr:full":"135 Av Frank-Robinson Aylmer QC J9H 4A8",
    "addr:postcode":"j9h 4a8",
    "addr:street":"135 Av Frank-Robinson",
    "iso:country":"CA",
    "sg:address":"135 Av Frank-Robinson",
    "sg:city":"Aylmer",
    "sg:classifiers":[
        {
            "category":"Insurance",
            "subcategory":"Insurance Agent",
            "type":"Services"
        }
    ],
    "sg:phone":"+1 819 684 0555",
    "sg:postcode":"J9H 4A8",
    "sg:province":"QC",
    "wof:name":"E M Milne Courtiers D'Assrnce",
    "wof:placetype":"venue"
},
  "geometry": {"coordinates":[-75.8409957886,45.3940925598],"type":"Point"}
}