{
  "type": "Feature",
  "properties": {
    "addr:full":"144 John St Shelburne NS B0T 1W0",
    "addr:housenumber":"144",
    "addr:postcode":"b0t 1w0",
    "addr:street":"John St",
    "iso:country":"CA",
    "sg:address":"144 John St",
    "sg:city":"Shelburne",
    "sg:classifiers":[
        {
            "category":"Arena",
            "subcategory":"Sports Club",
            "type":"Entertainment"
        }
    ],
    "sg:phone":"+1 902 875 2977",
    "sg:postcode":"B0T 1W0",
    "sg:province":"NS",
    "sg:tags":[
        "athletic",
        "fields",
        "stadium"
    ],
    "wof:name":"Shelburne County Arena",
    "wof:placetype":"venue"
},
  "geometry": {"coordinates":[-65.31564299999999,43.765659],"type":"Point"}
}