{
  "type": "Feature",
  "properties": {
    "addr:full":"18265 74 Ave NW Edmonton AB T5T 2G6",
    "addr:housenumber":"18265",
    "addr:postcode":"t5t 2g6",
    "addr:street":"74 Ave Nw",
    "iso:country":"CA",
    "sg:address":"18265 74 Ave NW",
    "sg:city":"Edmonton",
    "sg:classifiers":[
        {
            "category":"Building & Trades",
            "subcategory":"Cleaning & Sanitation",
            "type":"Services"
        }
    ],
    "sg:phone":"+1 780 489 1361",
    "sg:postcode":"T5T 2G6",
    "sg:province":"AB",
    "sg:tags":[
        "janitor"
    ],
    "wof:name":"Meticulous Cleaners",
    "wof:placetype":"venue"
},
  "geometry": {"coordinates":[-113.637077331,53.5074882507],"type":"Point"}
}