{
  "type": "Feature",
  "properties": {
    "addr:full":"197 Hill St Corunna ON N0N 1G0",
    "addr:housenumber":"197",
    "addr:postcode":"n0n 1g0",
    "addr:street":"Hill St",
    "iso:country":"CA",
    "sg:address":"197 Hill St",
    "sg:city":"Corunna",
    "sg:classifiers":[
        {
            "category":"Retail",
            "subcategory":"Veterinary Services",
            "type":"Services"
        }
    ],
    "sg:phone":"+1 519 862 4244",
    "sg:postcode":"N0N 1G0",
    "sg:province":"ON",
    "sg:tags":[
        "veterinarian"
    ],
    "wof:name":"Corunna Veterinary Svc",
    "wof:placetype":"venue"
},
  "geometry": {"coordinates":[-82.4520645142,42.8884124756],"type":"Point"}
}