{
  "type": "Feature",
  "properties": {
    "addr:full":"1208 Rue Bishop Montreal QC H3G 2E3",
    "addr:housenumber":"1208",
    "addr:postcode":"h3g 2e3",
    "addr:street":"Rue Bishop",
    "iso:country":"CA",
    "sg:address":"1208 Rue Bishop",
    "sg:city":"Montreal",
    "sg:classifiers":[
        {
            "category":"Personal",
            "subcategory":"Beauty Salon",
            "type":"Services"
        }
    ],
    "sg:phone":"+1 514 879 9247",
    "sg:postcode":"H3G 2E3",
    "sg:province":"QC",
    "wof:name":"Coiffure Desinvolte Inc",
    "wof:placetype":"venue"
},
  "geometry": {"coordinates":[-73.57517199999999,45.49585],"type":"Point"}
}