{
  "type": "Feature",
  "properties": {
    "iso:country":"CA",
    "sg:address":"1208 Rue Bishop",
    "sg:city":"Montreal",
    "sg:classifiers":[
        {
            "category":"Personal",
            "subcategory":"Beauty Salon",
            "type":"Services"
        }
    ],
    "sg:phone":"+1 514 879 9247",
    "sg:postcode":"H3G 2E3",
    "sg:province":"QC",
    "wof:name":"Coiffure Desinvolte Inc",
    "wof:placetype":"venue"
},
  "geometry": {"coordinates":[-73.575172,45.49585],"type":"Point"}
}