{
  "type": "Feature",
  "properties": {
    "addr:full":"362 Esther St Pembroke ON K8A 6X9",
    "addr:housenumber":"362",
    "addr:postcode":"k8a 6x9",
    "addr:street":"Esther St",
    "iso:country":"CA",
    "sg:address":"362 Esther St",
    "sg:city":"Pembroke",
    "sg:classifiers":[
        {
            "category":"Health Services",
            "subcategory":"Doctor",
            "type":"Services"
        }
    ],
    "sg:phone":"+1 613 732 9916",
    "sg:postcode":"K8A 6X9",
    "sg:province":"ON",
    "sg:tags":[
        "physician",
        "surgeon"
    ],
    "wof:name":"A Y Eng & Assoc",
    "wof:placetype":"venue"
},
  "geometry": {"coordinates":[-77.1032943726,45.8250617981],"type":"Point"}
}