{
  "type": "Feature",
  "properties": {
    "addr:full":"9210 Boul Maurice-Duplessis Montreal QC H1E 1M7",
    "addr:housenumber":"9210",
    "addr:postcode":"h1e 1m7",
    "addr:street":"Boul Maurice-Duplessis",
    "iso:country":"CA",
    "sg:address":"9210 Boul Maurice-Duplessis",
    "sg:city":"Montreal",
    "sg:classifiers":[
        {
            "category":"Manufacturing",
            "subcategory":"Metals",
            "type":"Manufacturing & Wholesale Goods"
        }
    ],
    "sg:phone":"+1 514 881 8503",
    "sg:postcode":"H1E 1M7",
    "sg:province":"QC",
    "sg:tags":[
        "cap",
        "bottle",
        "seal"
    ],
    "wof:name":"Brentacork Inc",
    "wof:placetype":"venue"
},
  "geometry": {"coordinates":[-73.568748,45.646797],"type":"Point"}
}