{
  "type": "Feature",
  "properties": {
    "iso:country":"CA",
    "sg:address":"2339 Melin's Rd",
    "sg:city":"Lively",
    "sg:classifiers":[
        {
            "category":"Freight",
            "type":"Transportation"
        }
    ],
    "sg:phone":"+1 705 692 3078",
    "sg:postcode":"P3Y 1H9",
    "sg:province":"ON",
    "sg:tags":[
        "trucking"
    ],
    "wof:name":"John Rintala Trucking",
    "wof:placetype":"venue"
},
  "geometry": {"coordinates":[-81.1337814331,46.4261016846],"type":"Point"}
}