{
  "type": "Feature",
  "properties": {
    "addr:full":"Thornhill ON L3T 5W4",
    "addr:postcode":"l3t 5w4",
    "iso:country":"CA",
    "sg:city":"Thornhill",
    "sg:classifiers":[
        {
            "category":"Health Services",
            "subcategory":"Doctor",
            "type":"Services"
        }
    ],
    "sg:phone":"+1 905 731 1555",
    "sg:postcode":"L3T 5W4",
    "sg:province":"ON",
    "sg:tags":[
        "dentist"
    ],
    "wof:name":"Rubenstein, Jeffrey DDS",
    "wof:placetype":"venue"
},
  "geometry": {"coordinates":[-79.3972625732,43.819480896],"type":"Point"}
}