{
  "type": "Feature",
  "properties": {
    "addr:full":"Barrie ON L4M 4Z8",
    "addr:postcode":"l4m 4z8",
    "iso:country":"CA",
    "sg:city":"Barrie",
    "sg:classifiers":[
        {
            "category":"Shopping",
            "subcategory":"Jewelry",
            "type":"Retail Goods"
        }
    ],
    "sg:phone":"+1 705 722 0032",
    "sg:postcode":"L4M 4Z8",
    "sg:province":"ON",
    "sg:tags":[
        "jeweler"
    ],
    "wof:name":"Peoples Jewellers",
    "wof:placetype":"venue"
},
  "geometry": {"coordinates":[-79.7113571167,44.4139251709],"type":"Point"}
}