{
  "type": "Feature",
  "properties": {
    "addr:full":"136 Broadway St Tillsonburg ON N4G 3P8",
    "addr:housenumber":"136",
    "addr:postcode":"n4g 3p8",
    "addr:street":"Broadway St",
    "iso:country":"CA",
    "sg:address":"136 Broadway St",
    "sg:city":"Tillsonburg",
    "sg:classifiers":[
        {
            "category":"Restaurant",
            "type":"Food & Drink"
        }
    ],
    "sg:phone":"+1 519 688 1126",
    "sg:postcode":"N4G 3P8",
    "sg:province":"ON",
    "wof:name":"Town Cafe Restaurant",
    "wof:placetype":"venue"
},
  "geometry": {"coordinates":[-80.72761535639999,42.8606529236],"type":"Point"}
}