{
  "type": "Feature",
  "properties": {
    "addr:full":"5011 51 St Innisfree AB T0B 2G0",
    "addr:housenumber":"5011",
    "addr:postcode":"t0b 2g0",
    "addr:street":"51 St",
    "iso:country":"CA",
    "sg:address":"5011 51 St",
    "sg:city":"Innisfree",
    "sg:classifiers":[
        {
            "category":"Food & Beverages",
            "subcategory":"Groceries & Convenience Stores",
            "type":"Retail Goods"
        }
    ],
    "sg:phone":"+1 780 592 3802",
    "sg:postcode":"T0B 2G0",
    "sg:province":"AB",
    "sg:tags":[
        "grocer"
    ],
    "wof:name":"Corner Foods",
    "wof:placetype":"venue"
},
  "geometry": {"coordinates":[-111.528221,53.38282],"type":"Point"}
}