{
  "type": "Feature",
  "properties": {
    "addr:full":"3788 North Fraser Way Burnaby BC V5J 5G1",
    "addr:housenumber":"3788",
    "addr:postcode":"v5j 5g1",
    "addr:street":"North Fraser Way",
    "iso:country":"CA",
    "sg:address":"3788 North Fraser Way",
    "sg:city":"Burnaby",
    "sg:classifiers":[
        {
            "category":"Manufacturing",
            "subcategory":"Apparel",
            "type":"Manufacturing & Wholesale Goods"
        }
    ],
    "sg:phone":"+1 604 451 9799",
    "sg:postcode":"V5J 5G1",
    "sg:province":"BC",
    "wof:name":"Oceanic Sportswear Ltd",
    "wof:placetype":"venue"
},
  "geometry": {"coordinates":[-123.019134522,49.2013893127],"type":"Point"}
}