{
  "type": "Feature",
  "properties": {
    "addr:full":"1505 Centre St NW Calgary AB T2E 2S1",
    "addr:housenumber":"1505",
    "addr:postcode":"t2e 2s1",
    "addr:street":"Centre St Nw",
    "iso:country":"CA",
    "sg:address":"1505 Centre St NW",
    "sg:city":"Calgary",
    "sg:classifiers":[
        {
            "category":"Retail",
            "subcategory":"Auto Repair",
            "type":"Services"
        }
    ],
    "sg:phone":"+1 403 276 7676",
    "sg:postcode":"T2E 2S1",
    "sg:province":"AB",
    "sg:tags":[
        "repairing",
        "automobile"
    ],
    "wof:name":"Speedy Auto Svc",
    "wof:placetype":"venue"
},
  "geometry": {"coordinates":[-114.063850403,51.0654411316],"type":"Point"}
}