{
  "type": "Feature",
  "properties": {
    "addr:full":"437 Boul Dr Albiny-Paquette Mont-Laurier QC J9L 1K7",
    "addr:housenumber":"437",
    "addr:postcode":"j9l 1k7",
    "addr:street":"Boul Dr Albiny-Paquette",
    "iso:country":"CA",
    "sg:address":"437 Boul Dr Albiny-Paquette",
    "sg:city":"Mont-Laurier",
    "sg:classifiers":[
        {
            "category":"Restaurant",
            "type":"Food & Drink"
        }
    ],
    "sg:phone":"+1 819 623 4339",
    "sg:postcode":"J9L 1K7",
    "sg:province":"QC",
    "wof:name":"Restaurant LA Lanterne",
    "wof:placetype":"venue"
},
  "geometry": {"coordinates":[-75.49917600000001,46.549557],"type":"Point"}
}