{
  "type": "Feature",
  "properties": {
    "addr:full":"405 Brooks Ave Denzil SK S0L 0S0",
    "addr:housenumber":"405",
    "addr:postcode":"s0l 0s0",
    "addr:street":"Brooks Ave",
    "iso:country":"CA",
    "sg:address":"405 Brooks Ave",
    "sg:city":"Denzil",
    "sg:classifiers":[
        {
            "category":"Government",
            "subcategory":"Office",
            "type":"Public Place"
        }
    ],
    "sg:phone":"+1 306 358 2118",
    "sg:postcode":"S0L 0S0",
    "sg:province":"SK",
    "sg:tags":[
        "municipality"
    ],
    "wof:name":"Village of Denzil",
    "wof:placetype":"venue"
},
  "geometry": {"coordinates":[-109.646522522,52.2255439758],"type":"Point"}
}