{
  "type": "Feature",
  "properties": {
    "iso:country":"CA",
    "sg:address":"2510 Cavendish Dr",
    "sg:city":"Burlington",
    "sg:classifiers":[
        {
            "category":"Education",
            "subcategory":"School",
            "type":"Public Place"
        }
    ],
    "sg:phone":"+1 905 335 0679",
    "sg:postcode":"L7P 4K5",
    "sg:province":"ON",
    "wof:name":"B T Lindley Elementary Schools",
    "wof:placetype":"venue"
},
  "geometry": {"coordinates":[-79.83954620359999,43.3711013794],"type":"Point"}
}