{
  "type": "Feature",
  "properties": {
    "addr:full":"1250 St. George Blvd Moncton NB E1E 3S1",
    "addr:housenumber":"1250",
    "addr:postcode":"e1e 3s1",
    "addr:street":"St. George Blvd",
    "iso:country":"CA",
    "sg:address":"1250 St. George Blvd",
    "sg:city":"Moncton",
    "sg:classifiers":[
        {
            "category":"Restaurant",
            "type":"Food & Drink"
        }
    ],
    "sg:phone":"+1 506 858 3601",
    "sg:postcode":"E1E 3S1",
    "sg:province":"NB",
    "sg:tags":[
        "caterer"
    ],
    "wof:name":"Right Choice Catering",
    "wof:placetype":"venue"
},
  "geometry": {"coordinates":[-64.8343734741,46.0801239014],"type":"Point"}
}