{
  "type": "Feature",
  "properties": {
    "addr:full":"719 Krosno Blvd Pickering ON L1W 1G4",
    "addr:housenumber":"719",
    "addr:postcode":"l1w 1g4",
    "addr:street":"Krosno Blvd",
    "iso:country":"CA",
    "sg:address":"719 Krosno Blvd",
    "sg:city":"Pickering",
    "sg:classifiers":[
        {
            "category":"Restaurant",
            "type":"Food & Drink"
        }
    ],
    "sg:phone":"+1 905 831 9684",
    "sg:postcode":"L1W 1G4",
    "sg:province":"ON",
    "wof:name":"Liverpool Fish & Chips",
    "wof:placetype":"venue"
},
  "geometry": {"coordinates":[-79.08312225340001,43.8218345642],"type":"Point"}
}