{
  "type": "Feature",
  "properties": {
    "addr:full":"774 Ochakwin Cres Prince George BC V2M 5P3",
    "addr:housenumber":"774",
    "addr:postcode":"v2m 5p3",
    "addr:street":"Ochakwin Cres",
    "iso:country":"CA",
    "sg:address":"774 Ochakwin Cres",
    "sg:city":"Prince George",
    "sg:classifiers":[
        {
            "category":"Wholesale",
            "subcategory":"Medical Equipment & Supplies",
            "type":"Manufacturing & Wholesale Goods"
        }
    ],
    "sg:phone":"+1 250 614 1516",
    "sg:postcode":"V2M 5P3",
    "sg:province":"BC",
    "sg:tags":[
        "alarm",
        "security",
        "system"
    ],
    "wof:name":"Medic Aid Response Systems",
    "wof:placetype":"venue"
},
  "geometry": {"coordinates":[-122.815422,53.918243],"type":"Point"}
}