{
  "type": "Feature",
  "properties": {
    "addr:full":"Halifax NS B3J 3L7",
    "addr:postcode":"ns b3j 3l7",
    "iso:country":"CA",
    "sg:city":"Halifax",
    "sg:classifiers":[
        {
            "category":"Shopping",
            "subcategory":"Jewelry",
            "type":"Retail Goods"
        }
    ],
    "sg:phone":"+1 902 423 5998",
    "sg:postcode":"B3J 3L7",
    "sg:province":"NS",
    "sg:tags":[
        "watch"
    ],
    "wof:name":"Watch Repair Ctr",
    "wof:placetype":"venue"
},
  "geometry": {"coordinates":[-63.5752296448,44.649974823],"type":"Point"}
}