{
  "type": "Feature",
  "properties": {
    "iso:country":"CA",
    "sg:address":"173 Limestone Cres",
    "sg:city":"North York",
    "sg:classifiers":[
        {
            "category":"Retail",
            "subcategory":"Auto Repair",
            "type":"Services"
        }
    ],
    "sg:phone":"+1 416 663 9945",
    "sg:postcode":"M3J 2R1",
    "sg:province":"ON",
    "sg:tags":[
        "body",
        "automobile",
        "painting"
    ],
    "wof:name":"Guycan Auto Body",
    "wof:placetype":"venue"
},
  "geometry": {"coordinates":[-79.48751068120001,43.780216217],"type":"Point"}
}