{
  "type": "Feature",
  "properties": {
    "addr:full":"411 Av Sirois Rimouski QC G5L 8B2",
    "addr:postcode":"g5l 8b2",
    "addr:street":"411 Av Sirois",
    "iso:country":"CA",
    "sg:address":"411 Av Sirois",
    "sg:city":"Rimouski",
    "sg:classifiers":[
        {
            "category":"Food & Beverages",
            "subcategory":"Specialty",
            "type":"Retail Goods"
        }
    ],
    "sg:phone":"+1 418 724 6713",
    "sg:postcode":"G5L 8B2",
    "sg:province":"QC",
    "sg:tags":[
        "water",
        "bulk",
        "company"
    ],
    "wof:name":"Boutique D'Eau",
    "wof:placetype":"venue"
},
  "geometry": {"coordinates":[-68.52299499510001,48.435256958],"type":"Point"}
}