{
  "type": "Feature",
  "properties": {
    "addr:full":"115 Collier St Barrie ON L4M 1H2",
    "addr:housenumber":"115",
    "addr:postcode":"l4m 1h2",
    "addr:street":"Collier St",
    "iso:country":"CA",
    "sg:address":"115 Collier St",
    "sg:city":"Barrie",
    "sg:classifiers":[
        {
            "category":"Shopping",
            "subcategory":"Hobbies, Toys, & Games",
            "type":"Retail Goods"
        }
    ],
    "sg:phone":"+1 705 722 9838",
    "sg:postcode":"L4M 1H2",
    "sg:province":"ON",
    "sg:tags":[
        "supply"
    ],
    "wof:name":"John Huxley Casino Equipment",
    "wof:placetype":"venue"
},
  "geometry": {"coordinates":[-79.68343400000001,44.390324],"type":"Point"}
}