{
  "type": "Feature",
  "properties": {
    "addr:full":"1500 Don Mills Rd North York ON M3B 3K4",
    "addr:housenumber":"1500",
    "addr:postcode":"m3b 3k4",
    "addr:street":"Don Mills Rd",
    "iso:country":"CA",
    "sg:address":"1500 Don Mills Rd",
    "sg:city":"North York",
    "sg:classifiers":[
        {
            "category":"Manufacturing",
            "subcategory":"Tobacco Products",
            "type":"Manufacturing & Wholesale Goods"
        }
    ],
    "sg:phone":"+1 416 449 5525",
    "sg:postcode":"M3B 3K4",
    "sg:province":"ON",
    "sg:tags":[
        "cigarette",
        "cigar"
    ],
    "wof:name":"Rothmans Benson & Hedges Inc",
    "wof:placetype":"venue"
},
  "geometry": {"coordinates":[-79.34716,43.75531],"type":"Point"}
}