{
  "type": "Feature",
  "properties": {
    "addr:full":"1517 Princess Ave Brandon MB R7A 0R7",
    "addr:housenumber":"1517",
    "addr:postcode":"r7a 0r7",
    "addr:street":"Princess Ave",
    "iso:country":"CA",
    "sg:address":"1517 Princess Ave",
    "sg:city":"Brandon",
    "sg:classifiers":[
        {
            "category":"Retail",
            "subcategory":"Auto Repair",
            "type":"Services"
        }
    ],
    "sg:phone":"+1 204 727 3630",
    "sg:postcode":"R7A 0R7",
    "sg:province":"MB",
    "sg:tags":[
        "body",
        "automobile",
        "painting"
    ],
    "wof:name":"Central Auto Body Shop Brandon",
    "wof:placetype":"venue"
},
  "geometry": {"coordinates":[-99.95858764650001,49.8471374512],"type":"Point"}
}