{
  "type": "Feature",
  "properties": {
    "addr:full":"Vancouver BC V5T 4L6",
    "addr:postcode":"v5t 4l6",
    "iso:country":"CA",
    "sg:city":"Vancouver",
    "sg:classifiers":[
        {
            "category":"Health Services",
            "subcategory":"Medical Lab",
            "type":"Services"
        }
    ],
    "sg:phone":"+1 604 877 1148",
    "sg:postcode":"V5T 4L6",
    "sg:province":"BC",
    "sg:tags":[
        "laboratory"
    ],
    "wof:name":"Vogue Dental Studio",
    "wof:placetype":"venue"
},
  "geometry": {"coordinates":[-123.103149414,49.263507843],"type":"Point"}
}