{
  "type": "Feature",
  "properties": {
    "iso:country":"CA",
    "sg:city":"Mont-Saint-Hilaire",
    "sg:classifiers":[
        {
            "category":"Personal",
            "subcategory":"Beauty Salon",
            "type":"Services"
        }
    ],
    "sg:phone":"+1 450 464 0903",
    "sg:postcode":"J3H 3N7",
    "sg:province":"QC",
    "wof:name":"Salon En Tete Coiffures Enr",
    "wof:placetype":"venue"
},
  "geometry": {"coordinates":[-73.188683,45.562263],"type":"Point"}
}