{
  "type": "Feature",
  "properties": {
    "addr:full":"31 Osborne St Winnipeg MB R3L 1Y1",
    "addr:housenumber":"31",
    "addr:postcode":"r3l 1y1",
    "addr:street":"Osborne St",
    "iso:country":"CA",
    "sg:address":"31 Osborne St",
    "sg:city":"Winnipeg",
    "sg:classifiers":[
        {
            "category":"Autos & Motor Vehicles",
            "subcategory":"Fuel & Gas Station",
            "type":"Retail Goods"
        }
    ],
    "sg:phone":"+1 204 475 6148",
    "sg:postcode":"R3L 1Y1",
    "sg:province":"MB",
    "sg:tags":[
        "grocer",
        "oil"
    ],
    "wof:name":"Shell Food Store",
    "wof:placetype":"venue"
},
  "geometry": {"coordinates":[-97.147598,49.880394],"type":"Point"}
}