{
  "type": "Feature",
  "properties": {
    "addr:full":"3104 Rue Dandurand Montreal QC H1Y 1V1",
    "addr:housenumber":"3104",
    "addr:postcode":"h1y 1v1",
    "addr:street":"Rue Dandurand",
    "iso:country":"CA",
    "sg:address":"3104 Rue Dandurand",
    "sg:city":"Montreal",
    "sg:classifiers":[
        {
            "category":"Health Services",
            "subcategory":"Health Practitioner",
            "type":"Services"
        }
    ],
    "sg:phone":"+1 514 592 7797",
    "sg:postcode":"H1Y 1V1",
    "sg:province":"QC",
    "sg:tags":[
        "psychologist"
    ],
    "wof:name":"Racicot, Michel",
    "wof:placetype":"venue"
},
  "geometry": {"coordinates":[-73.577133,45.550224],"type":"Point"}
}