{
  "type": "Feature",
  "properties": {
    "addr:full":"1001 Ottawa St S Kitchener ON N2E 2X5",
    "addr:housenumber":"1001",
    "addr:postcode":"n2e 2x5",
    "addr:street":"Ottawa St S",
    "iso:country":"CA",
    "sg:address":"1001 Ottawa St S",
    "sg:city":"Kitchener",
    "sg:classifiers":[
        {
            "category":"Retail",
            "subcategory":"Funeral Services",
            "type":"Services"
        }
    ],
    "sg:phone":"+1 519 743 8900",
    "sg:postcode":"N2E 2X5",
    "sg:province":"ON",
    "sg:tags":[
        "director"
    ],
    "wof:name":"Westmount Funeral Chapel",
    "wof:placetype":"venue"
},
  "geometry": {"coordinates":[-80.49894714360001,43.4207496643],"type":"Point"}
}