{
  "type": "Feature",
  "properties": {
    "addr:full":"237 King St W Oshawa ON L1J 2J7",
    "addr:housenumber":"237",
    "addr:postcode":"l1j 2j7",
    "addr:street":"King St W",
    "iso:country":"CA",
    "sg:address":"237 King St W",
    "sg:city":"Oshawa",
    "sg:classifiers":[
        {
            "category":"Cinema",
            "subcategory":"Movie Rental",
            "type":"Entertainment"
        }
    ],
    "sg:phone":"+1 905 721 2298",
    "sg:postcode":"L1J 2J7",
    "sg:province":"ON",
    "sg:tags":[
        "leasing",
        "video",
        "disc",
        "tape"
    ],
    "wof:name":"Blockbuster Video",
    "wof:placetype":"venue"
},
  "geometry": {"coordinates":[-78.872139,43.895531],"type":"Point"}
}