{
  "type": "Feature",
  "properties": {
    "addr:full":"981 Queenston Rd Stoney Creek ON L8G 1B8",
    "addr:housenumber":"981",
    "addr:postcode":"l8g 1b8",
    "addr:street":"Queenston Rd",
    "iso:country":"CA",
    "sg:address":"981 Queenston Rd",
    "sg:city":"Stoney Creek",
    "sg:classifiers":[
        {
            "category":"Restaurant",
            "type":"Food & Drink"
        }
    ],
    "sg:phone":"+1 905 662 4224",
    "sg:postcode":"L8G 1B8",
    "sg:province":"ON",
    "sg:tags":[
        "parlor",
        "ice",
        "cream"
    ],
    "wof:name":"Dairy Queen",
    "wof:placetype":"venue"
},
  "geometry": {"coordinates":[-79.7502670288,43.2249755859],"type":"Point"}
}