{
  "type": "Feature",
  "properties": {
    "addr:full":"1280 Rue DE LA Digue Havre-Saint-Pierre QC G0G 1P0",
    "addr:housenumber":"1280",
    "addr:postcode":"g0g 1p0",
    "addr:street":"Rue De La Digue",
    "iso:country":"CA",
    "sg:address":"1280 Rue DE LA Digue",
    "sg:city":"Havre-Saint-Pierre",
    "sg:classifiers":[
        {
            "category":"Food & Beverages",
            "subcategory":"Groceries & Convenience Stores",
            "type":"Retail Goods"
        }
    ],
    "sg:phone":"+1 418 538 2010",
    "sg:postcode":"G0G 1P0",
    "sg:province":"QC",
    "sg:tags":[
        "grocer"
    ],
    "wof:name":"Marche Vigneault Ltee",
    "wof:placetype":"venue"
},
  "geometry": {"coordinates":[-63.5945205688,50.2447090149],"type":"Point"}
}