{
  "type": "Feature",
  "properties": {
    "addr:full":"521 Almey Ave Winnipeg MB R3W 1P7",
    "addr:housenumber":"521",
    "addr:postcode":"r3w 1p7",
    "addr:street":"Almey Ave",
    "iso:country":"CA",
    "sg:address":"521 Almey Ave",
    "sg:city":"Winnipeg",
    "sg:classifiers":[
        {
            "category":"Building & Trades",
            "subcategory":"Plumbing",
            "type":"Services"
        }
    ],
    "sg:phone":"+1 204 663 6072",
    "sg:postcode":"R3W 1P7",
    "sg:province":"MB",
    "sg:tags":[
        "contractor"
    ],
    "wof:name":"Elite Plumbing & Heating",
    "wof:placetype":"venue"
},
  "geometry": {"coordinates":[-97.05437499999999,49.901768],"type":"Point"}
}