{
  "type": "Feature",
  "properties": {
    "iso:country":"CA",
    "sg:city":"Scarborough",
    "sg:classifiers":[
        {
            "category":"Real Estate",
            "subcategory":"Real Estate Agent",
            "type":"Services"
        }
    ],
    "sg:phone":"+1 416 754 2575",
    "sg:postcode":"M1P 3H1",
    "sg:province":"ON",
    "sg:tags":[
        "management"
    ],
    "wof:name":"Luiza Investments Ltd",
    "wof:placetype":"venue"
},
  "geometry": {"coordinates":[-79.2621078491,43.772064209],"type":"Point"}
}