{
  "type": "Feature",
  "properties": {
    "addr:full":"1060 Av Antoine-Panet Alma QC G8B 7P8",
    "addr:housenumber":"1060",
    "addr:postcode":"g8b 7p8",
    "addr:street":"Av Antoine-Panet",
    "iso:country":"CA",
    "sg:address":"1060 Av Antoine-Panet",
    "sg:city":"Alma",
    "sg:classifiers":[
        {
            "category":"Professional",
            "subcategory":"Accounting & Tax Preparation",
            "type":"Services"
        }
    ],
    "sg:phone":"+1 418 668 2998",
    "sg:postcode":"G8B 7P8",
    "sg:province":"QC",
    "sg:tags":[
        "consultant",
        "accountant",
        "management",
        "business"
    ],
    "wof:name":"Societe Gesmark Inc",
    "wof:placetype":"venue"
},
  "geometry": {"coordinates":[-71.66629,48.537994],"type":"Point"}
}