{
  "type": "Feature",
  "properties": {
    "addr:full":"812 Queen St E Toronto ON M4M 1H7",
    "addr:housenumber":"812",
    "addr:postcode":"m4m 1h7",
    "addr:street":"Queen St E",
    "iso:country":"CA",
    "sg:address":"812 Queen St E",
    "sg:city":"Toronto",
    "sg:classifiers":[
        {
            "category":"Food & Beverages",
            "subcategory":"Bakery",
            "type":"Retail Goods"
        }
    ],
    "sg:phone":"+1 416 406 1250",
    "sg:postcode":"M4M 1H7",
    "sg:province":"ON",
    "sg:tags":[
        "baker"
    ],
    "wof:name":"Bonjour Brioche Bakery Cafe",
    "wof:placetype":"venue"
},
  "geometry": {"coordinates":[-79.34618399999999,43.659737],"type":"Point"}
}