{
  "type": "Feature",
  "properties": {
    "addr:full":"Dog Lake Rd Thunder Bay ON P7B 5E5",
    "addr:postcode":"p7b 5e5",
    "addr:street":"Dog Lake Rd",
    "iso:country":"CA",
    "sg:address":"Dog Lake Rd",
    "sg:city":"Thunder Bay",
    "sg:classifiers":[
        {
            "category":"Travel",
            "subcategory":"Hotels & Motels",
            "type":"Entertainment"
        }
    ],
    "sg:phone":"+1 807 933 4407",
    "sg:postcode":"P7B 5E5",
    "sg:province":"ON",
    "sg:tags":[
        "resort"
    ],
    "wof:name":"Dog Lake Resort",
    "wof:placetype":"venue"
},
  "geometry": {"coordinates":[-89.326988,48.504055],"type":"Point"}
}