{
  "type": "Feature",
  "properties": {
    "addr:full":"7505 134A St Surrey BC V3W 7B3",
    "addr:housenumber":"7505",
    "addr:postcode":"v3w 7b3",
    "addr:street":"134A St",
    "iso:country":"CA",
    "sg:address":"7505 134A St",
    "sg:city":"Surrey",
    "sg:classifiers":[
        {
            "category":"Building & Trades",
            "subcategory":"Construction",
            "type":"Services"
        }
    ],
    "sg:phone":"+1 604 594 0422",
    "sg:postcode":"V3W 7B3",
    "sg:province":"BC",
    "sg:tags":[
        "elevator"
    ],
    "wof:name":"Garaventa Limited",
    "wof:placetype":"venue"
},
  "geometry": {"coordinates":[-122.830215,49.105179],"type":"Point"}
}