{
  "type": "Feature",
  "properties": {
    "iso:country":"CA",
    "sg:address":"364 Eagles Glenn Blvd",
    "sg:city":"Hunter River",
    "sg:classifiers":[
        {
            "category":"Sports & Exercise",
            "subcategory":"Golf",
            "type":"Entertainment"
        }
    ],
    "sg:phone":"+1 902 963 3600",
    "sg:postcode":"C0A 1N0",
    "sg:province":"PE",
    "sg:tags":[
        "course"
    ],
    "wof:name":"Eagles Glenn Golf Resort",
    "wof:placetype":"venue"
},
  "geometry": {"coordinates":[-63.3431472778,46.3517608643],"type":"Point"}
}