{
  "type": "Feature",
  "properties": {
    "addr:full":"1547 Beach Dr Port Mcneill BC V0N 2R0",
    "addr:housenumber":"1547",
    "addr:postcode":"v0n 2r0",
    "addr:street":"Beach Dr",
    "iso:country":"CA",
    "sg:address":"1547 Beach Dr",
    "sg:city":"Port Mcneill",
    "sg:classifiers":[
        {
            "category":"Restaurant",
            "type":"Food & Drink"
        }
    ],
    "sg:phone":"+1 250 956 4113",
    "sg:postcode":"V0N 2R0",
    "sg:province":"BC",
    "wof:name":"Sportsman's Steak & Pizza Hse",
    "wof:placetype":"venue"
},
  "geometry": {"coordinates":[-127.08596,50.590931],"type":"Point"}
}