{
  "type": "Feature",
  "properties": {
    "addr:full":"3904 1 St NE Calgary AB T2E 3E3",
    "addr:housenumber":"3904 1",
    "addr:postcode":"t2e 3e3",
    "addr:street":"St Ne",
    "iso:country":"CA",
    "sg:address":"3904 1 St NE",
    "sg:city":"Calgary",
    "sg:classifiers":[
        {
            "category":"Building & Trades",
            "subcategory":"Construction",
            "type":"Services"
        }
    ],
    "sg:phone":"+1 403 230 0688",
    "sg:postcode":"T2E 3E3",
    "sg:province":"AB",
    "sg:tags":[
        "painter",
        "furniture"
    ],
    "wof:name":"Jme Designing To Finishing",
    "wof:placetype":"venue"
},
  "geometry": {"coordinates":[-114.05970764200001,51.0872917175],"type":"Point"}
}