{
  "type": "Feature",
  "properties": {
    "iso:country":"CA",
    "sg:address":"95 Queensway W",
    "sg:city":"Simcoe",
    "sg:classifiers":[
        {
            "category":"Wholesale",
            "subcategory":"Groceries",
            "type":"Manufacturing & Wholesale Goods"
        }
    ],
    "sg:phone":"+1 519 426 9393",
    "sg:postcode":"N3Y 2M8",
    "sg:province":"ON",
    "sg:tags":[
        "grocer"
    ],
    "wof:name":"Hbr Ginseng Ltd",
    "wof:placetype":"venue"
},
  "geometry": {"coordinates":[-80.3112335205,42.8455810547],"type":"Point"}
}