{
  "type": "Feature",
  "properties": {
    "addr:full":"252 Rue DE Courcelle Montreal QC H4C 3B7",
    "addr:housenumber":"252",
    "addr:postcode":"h4c 3b7",
    "addr:street":"Rue De Courcelle",
    "iso:country":"CA",
    "sg:address":"252 Rue DE Courcelle",
    "sg:city":"Montreal",
    "sg:classifiers":[
        {
            "category":"Food & Beverages",
            "subcategory":"Groceries & Convenience Stores",
            "type":"Retail Goods"
        }
    ],
    "sg:phone":"+1 514 932 2829",
    "sg:postcode":"H4C 3B7",
    "sg:province":"QC",
    "sg:tags":[
        "grocer"
    ],
    "wof:name":"Depanneur Super A",
    "wof:placetype":"venue"
},
  "geometry": {"coordinates":[-73.58763885499999,45.4720497131],"type":"Point"}
}