{
  "type": "Feature",
  "properties": {
    "addr:full":"138 Heward Ave Toronto ON M4M 2T7",
    "addr:housenumber":"138",
    "addr:postcode":"m4m 2t7",
    "addr:street":"Heward Ave",
    "iso:country":"CA",
    "sg:address":"138 Heward Ave",
    "sg:city":"Toronto",
    "sg:classifiers":[
        {
            "category":"Social Services",
            "type":"Services"
        }
    ],
    "sg:phone":"+1 416 469 1070",
    "sg:postcode":"M4M 2T7",
    "sg:province":"ON",
    "sg:tags":[
        "home",
        "senior",
        "health",
        "citizen"
    ],
    "wof:name":"Heritage Home Healthcare Inc",
    "wof:placetype":"venue"
},
  "geometry": {"coordinates":[-79.3382034302,43.6591873169],"type":"Point"}
}