{
  "type": "Feature",
  "properties": {
    "addr:full":"436 Rte Begin Saint-Anselme QC G0R 2N0",
    "addr:housenumber":"436",
    "addr:postcode":"g0r 2n0",
    "addr:street":"Rte Begin",
    "iso:country":"CA",
    "sg:address":"436 Rte Begin",
    "sg:city":"Saint-Anselme",
    "sg:classifiers":[
        {
            "category":"Recreation",
            "subcategory":"Arcade",
            "type":"Entertainment"
        }
    ],
    "sg:phone":"+1 418 885 9191",
    "sg:postcode":"G0R 2N0",
    "sg:province":"QC",
    "sg:tags":[
        "amusement",
        "devices"
    ],
    "wof:name":"Ben Amusements Inc",
    "wof:placetype":"venue"
},
  "geometry": {"coordinates":[-70.992065,46.642612],"type":"Point"}
}