{
  "type": "Feature",
  "properties": {
    "iso:country":"CA",
    "sg:city":"Verner",
    "sg:classifiers":[
        {
            "category":"Home & Garden",
            "subcategory":"Building Materials",
            "type":"Retail Goods"
        }
    ],
    "sg:phone":"+1 705 594 9444",
    "sg:postcode":"P0H 2M0",
    "sg:province":"ON",
    "sg:tags":[
        "door"
    ],
    "wof:name":"Larry's Siding & Welding",
    "wof:placetype":"venue"
},
  "geometry": {"coordinates":[-80.13060760499999,46.4122314453],"type":"Point"}
}