{
  "type": "Feature",
  "properties": {
    "addr:full":"Brighton ON K0K 1H0",
    "addr:postcode":"k0k 1h0",
    "iso:country":"CA",
    "sg:city":"Brighton",
    "sg:classifiers":[
        {
            "category":"Retail",
            "subcategory":"Auto Repair",
            "type":"Services"
        }
    ],
    "sg:phone":"+1 613 475 1212",
    "sg:postcode":"K0K 1H0",
    "sg:province":"ON",
    "sg:tags":[
        "body",
        "automobile",
        "painting"
    ],
    "wof:name":"Salem Auto Body",
    "wof:placetype":"venue"
},
  "geometry": {"coordinates":[-77.673637,44.058975],"type":"Point"}
}