{
  "type": "Feature",
  "properties": {
    "addr:full":"1669 Courtice Rd Courtice ON L1E 2M9",
    "addr:housenumber":"1669",
    "addr:postcode":"l1e 2m9",
    "addr:street":"Courtice Rd",
    "iso:country":"CA",
    "sg:address":"1669 Courtice Rd",
    "sg:city":"Courtice",
    "sg:classifiers":[
        {
            "category":"Organizations",
            "subcategory":"Religious Organization",
            "type":"Services"
        }
    ],
    "sg:phone":"+1 905 436 2058",
    "sg:postcode":"L1E 2M9",
    "sg:province":"ON",
    "sg:tags":[
        "church"
    ],
    "wof:name":"Ebenezer United Church",
    "wof:placetype":"venue"
},
  "geometry": {"coordinates":[-78.768951,43.891499],"type":"Point"}
}