{
  "type": "Feature",
  "properties": {
    "addr:full":"Mississauga ON L4W 5G6",
    "addr:postcode":"l4w 5g6",
    "iso:country":"CA",
    "sg:city":"Mississauga",
    "sg:classifiers":[
        {
            "category":"Health Services",
            "subcategory":"Medical Lab",
            "type":"Services"
        }
    ],
    "sg:phone":"+1 905 206 1300",
    "sg:postcode":"L4W 5G6",
    "sg:province":"ON",
    "sg:tags":[
        "x"
    ],
    "wof:name":"Ugofan Diagnostic Inc",
    "wof:placetype":"venue"
},
  "geometry": {"coordinates":[-79.6140823364,43.6328887939],"type":"Point"}
}