{
  "type": "Feature",
  "properties": {
    "addr:full":"305 Bell Blvd Belleville ON K8P 5H3",
    "addr:housenumber":"305",
    "addr:postcode":"k8p 5h3",
    "addr:street":"Bell Blvd",
    "iso:country":"CA",
    "sg:address":"305 Bell Blvd",
    "sg:city":"Belleville",
    "sg:classifiers":[
        {
            "category":"Travel",
            "subcategory":"Travel Agent",
            "type":"Entertainment"
        }
    ],
    "sg:phone":"+1 613 966 7000",
    "sg:postcode":"K8P 5H3",
    "sg:province":"ON",
    "sg:tags":[
        "agency",
        "bureau"
    ],
    "wof:name":"Franklin Coach & Tours Ltd",
    "wof:placetype":"venue"
},
  "geometry": {"coordinates":[-77.411987,44.18446],"type":"Point"}
}