{
  "type": "Feature",
  "properties": {
    "addr:full":"Vancouver BC V6B 2S2",
    "addr:postcode":"v6b 2s2",
    "iso:country":"CA",
    "sg:city":"Vancouver",
    "sg:classifiers":[
        {
            "category":"Real Estate",
            "subcategory":"Real Estate Agent",
            "type":"Services"
        }
    ],
    "sg:phone":"+1 604 681 3999",
    "sg:postcode":"V6B 2S2",
    "sg:province":"BC",
    "wof:name":"Yamato Development Canada Inc",
    "wof:placetype":"venue"
},
  "geometry": {"coordinates":[-123.121376,49.275566],"type":"Point"}
}