{
  "type": "Feature",
  "properties": {
    "addr:full":"100 5th Conc E Waterdown ON L0R 2H1",
    "addr:housenumber":"100",
    "addr:postcode":"l0r 2h1",
    "addr:street":"5Th Conc E",
    "iso:country":"CA",
    "sg:address":"100 5th Conc E",
    "sg:city":"Waterdown",
    "sg:classifiers":[
        {
            "category":"Wholesale",
            "subcategory":"Petroleum",
            "type":"Manufacturing & Wholesale Goods"
        }
    ],
    "sg:phone":"+1 905 689 6652",
    "sg:postcode":"L0R 2H1",
    "sg:province":"ON",
    "sg:tags":[
        "pipe",
        "line",
        "company"
    ],
    "wof:name":"Imperial Oil Ltd",
    "wof:placetype":"venue"
},
  "geometry": {"coordinates":[-79.934479,43.337955],"type":"Point"}
}