{
  "type": "Feature",
  "properties": {
    "iso:country":"CA",
    "sg:address":"24 Simms Dr",
    "sg:city":"Ajax",
    "sg:classifiers":[
        {
            "category":"Retail",
            "subcategory":"Car Wash",
            "type":"Services"
        }
    ],
    "sg:phone":"+1 905 426 2772",
    "sg:postcode":"L1T 3J5",
    "sg:province":"ON",
    "sg:tags":[
        "polishing",
        "washing"
    ],
    "wof:name":"Shand Mobile Wash",
    "wof:placetype":"venue"
},
  "geometry": {"coordinates":[-79.049896,43.862709],"type":"Point"}
}