{
  "type": "Feature",
  "properties": {
    "iso:country":"CA",
    "sg:address":"4145 Rue Courchesne",
    "sg:city":"Laval",
    "sg:classifiers":[
        {
            "category":"Professional",
            "subcategory":"Computer Services",
            "type":"Services"
        }
    ],
    "sg:phone":"+1 450 687 7625",
    "sg:postcode":"H7T 1W3",
    "sg:province":"QC",
    "sg:tags":[
        "information",
        "system",
        "consultant"
    ],
    "wof:name":"Llh Consultants Inc",
    "wof:placetype":"venue"
},
  "geometry": {"coordinates":[-73.77378082280001,45.557636261],"type":"Point"}
}