{
  "type": "Feature",
  "properties": {
    "iso:country":"CA",
    "sg:address":"34 Rue Principale",
    "sg:city":"Stanstead",
    "sg:classifiers":[
        {
            "category":"Banks & Credit Unions",
            "subcategory":"Bank",
            "type":"Services"
        }
    ],
    "sg:phone":"+1 819 876 2441",
    "sg:postcode":"J0B 3E5",
    "sg:province":"QC",
    "wof:name":"Cibc",
    "wof:placetype":"venue"
},
  "geometry": {"coordinates":[-72.14320373539999,45.0080757141],"type":"Point"}
}