{
  "type": "Feature",
  "properties": {
    "iso:country":"CA",
    "sg:address":"Main St",
    "sg:city":"Channel-Port-Aux-Basques",
    "sg:classifiers":[
        {
            "category":"Taxi",
            "type":"Transportation"
        }
    ],
    "sg:phone":"+1 709 695 3333",
    "sg:postcode":"A0M 1C0",
    "sg:province":"NL",
    "sg:tags":[
        "taxicab"
    ],
    "wof:name":"Gateway Cabs",
    "wof:placetype":"venue"
},
  "geometry": {"coordinates":[-59.142372,47.573521],"type":"Point"}
}