{
  "type": "Feature",
  "properties": {
    "iso:country":"CA",
    "sg:address":"284 265 Rte S",
    "sg:city":"Villeroy",
    "sg:classifiers":[
        {
            "category":"Building & Trades",
            "subcategory":"Construction",
            "type":"Services"
        }
    ],
    "sg:phone":"+1 819 385 4379",
    "sg:postcode":"G0S 3K0",
    "sg:province":"QC",
    "sg:tags":[
        "excavating",
        "contractor"
    ],
    "wof:name":"Laliberte, Bertrand",
    "wof:placetype":"venue"
},
  "geometry": {"coordinates":[-71.86005401609999,46.3756217957],"type":"Point"}
}