{
  "type": "Feature",
  "properties": {
    "iso:country":"CA",
    "sg:address":"9 Rue Des Besants",
    "sg:city":"Blainville",
    "sg:classifiers":[
        {
            "category":"Building & Trades",
            "subcategory":"Construction",
            "type":"Services"
        }
    ],
    "sg:phone":"+1 450 434 0664",
    "sg:postcode":"J7C 5B4",
    "sg:province":"QC",
    "sg:tags":[
        "repairing",
        "remodeling",
        "contractor"
    ],
    "wof:name":"Constructions Yvan Caron Inc",
    "wof:placetype":"venue"
},
  "geometry": {"coordinates":[-73.8969039917,45.7059631348],"type":"Point"}
}