{
  "type": "Feature",
  "properties": {
    "iso:country":"CA",
    "sg:address":"370 Brunel Rd",
    "sg:city":"Mississauga",
    "sg:classifiers":[
        {
            "category":"Manufacturing",
            "subcategory":"Printing",
            "type":"Manufacturing & Wholesale Goods"
        }
    ],
    "sg:phone":"+1 905 890 2553",
    "sg:postcode":"L4Z 2C2",
    "sg:province":"ON",
    "sg:tags":[
        "printer"
    ],
    "wof:name":"Somerset Graphics CO Ltd",
    "wof:placetype":"venue"
},
  "geometry": {"coordinates":[-79.667427,43.630871],"type":"Point"}
}