{
  "type": "Feature",
  "properties": {
    "addr:full":"4285 Glendinning Dr Campbell River BC V9W 6G5",
    "addr:housenumber":"4285",
    "addr:postcode":"v9w 6g5",
    "addr:street":"Glendinning Dr",
    "iso:country":"CA",
    "sg:address":"4285 Glendinning Dr",
    "sg:city":"Campbell River",
    "sg:classifiers":[
        {
            "category":"Building & Trades",
            "subcategory":"Construction",
            "type":"Services"
        }
    ],
    "sg:phone":"+1 250 287 8290",
    "sg:postcode":"V9W 6G5",
    "sg:province":"BC",
    "sg:tags":[
        "repairing",
        "remodeling",
        "contractor"
    ],
    "wof:name":"Town & Country Railings",
    "wof:placetype":"venue"
},
  "geometry": {"coordinates":[-125.274384,50.064613],"type":"Point"}
}