{
  "type": "Feature",
  "properties": {
    "addr:full":"8801 110A St Grande Prairie AB T8V 5L5",
    "addr:housenumber":"8801",
    "addr:postcode":"t8v 5l5",
    "addr:street":"110A St",
    "iso:country":"CA",
    "sg:address":"8801 110A St",
    "sg:city":"Grande Prairie",
    "sg:classifiers":[
        {
            "category":"Manufacturing",
            "subcategory":"Tools & Machinery",
            "type":"Manufacturing & Wholesale Goods"
        }
    ],
    "sg:phone":"+1 780 539 7557",
    "sg:postcode":"T8V 5L5",
    "sg:province":"AB",
    "sg:tags":[
        "machine",
        "shop"
    ],
    "wof:name":"Mid Western Machine Works Inc",
    "wof:placetype":"venue"
},
  "geometry": {"coordinates":[-118.828819,55.160469],"type":"Point"}
}