{
  "type": "Feature",
  "properties": {
    "addr:full":"4115 Brisebois Dr NW Calgary AB T2L 2E8",
    "addr:postcode":"4115;t2l 2e8",
    "addr:street":"Brisebois Dr Nw",
    "iso:country":"CA",
    "sg:address":"4115 Brisebois Dr NW",
    "sg:city":"Calgary",
    "sg:classifiers":[
        {
            "category":"Professional",
            "subcategory":"Computer Services",
            "type":"Services"
        }
    ],
    "sg:phone":"+1 403 284 4082",
    "sg:postcode":"T2L 2E8",
    "sg:province":"AB",
    "sg:tags":[
        "consultant"
    ],
    "wof:name":"Octavian Micro Development Inc",
    "wof:placetype":"venue"
},
  "geometry": {"coordinates":[-114.133202,51.089962],"type":"Point"}
}