{
  "type": "Feature",
  "properties": {
    "addr:full":"20 Hawkside Rd NW Calgary AB T3G 3K9",
    "addr:housenumber":"20",
    "addr:postcode":"t3g 3k9",
    "addr:street":"Hawkside Rd Nw",
    "iso:country":"CA",
    "sg:address":"20 Hawkside Rd NW",
    "sg:city":"Calgary",
    "sg:classifiers":[
        {
            "category":"Organizations",
            "subcategory":"Professional Association",
            "type":"Services"
        }
    ],
    "sg:phone":"+1 403 241 1975",
    "sg:postcode":"T3G 3K9",
    "sg:province":"AB",
    "wof:name":"Uplands Recreation Ctr",
    "wof:placetype":"venue"
},
  "geometry": {"coordinates":[-114.18296814,51.1274795532],"type":"Point"}
}