{
  "type": "Feature",
  "properties": {
    "addr:full":"290 Allee Des Ursulines Rimouski QC G5L 2Z9",
    "addr:housenumber":"290",
    "addr:postcode":"g5l 2z9",
    "addr:street":"Allee Des Ursulines",
    "iso:country":"CA",
    "sg:address":"290 Allee Des Ursulines",
    "sg:city":"Rimouski",
    "sg:classifiers":[
        {
            "category":"Social Services",
            "subcategory":"Child Care",
            "type":"Services"
        }
    ],
    "sg:phone":"+1 418 722 4644",
    "sg:postcode":"G5L 2Z9",
    "sg:province":"QC",
    "wof:name":"Univers Des Copains",
    "wof:placetype":"venue"
},
  "geometry": {"coordinates":[-68.513824,48.453724],"type":"Point"}
}