{
  "type": "Feature",
  "properties": {
    "addr:full":"32 Queen St Bridgetown NS B0S 1C0",
    "addr:housenumber":"32",
    "addr:postcode":"b0s 1c0",
    "addr:street":"Queen St",
    "iso:country":"CA",
    "sg:address":"32 Queen St",
    "sg:city":"Bridgetown",
    "sg:classifiers":[
        {
            "category":"Home & Garden",
            "subcategory":"Building Materials",
            "type":"Retail Goods"
        }
    ],
    "sg:phone":"+1 902 665 4449",
    "sg:postcode":"B0S 1C0",
    "sg:province":"NS",
    "wof:name":"Frasers Pro Home Ctr",
    "wof:placetype":"venue"
},
  "geometry": {"coordinates":[-65.291336,44.84021],"type":"Point"}
}