{
  "type": "Feature",
  "properties": {
    "addr:full":"Saskatoon SK S7L 6R4",
    "addr:postcode":"s7l 6r4",
    "iso:country":"CA",
    "sg:city":"Saskatoon",
    "sg:classifiers":[
        {
            "category":"Food & Beverages",
            "subcategory":"Bakery",
            "type":"Retail Goods"
        }
    ],
    "sg:phone":"+1 306 384 6607",
    "sg:postcode":"S7L 6R4",
    "sg:province":"SK",
    "sg:tags":[
        "baker"
    ],
    "wof:name":"Mc Gavin's Bread Basket",
    "wof:placetype":"venue"
},
  "geometry": {"coordinates":[-106.727577209,52.1314964294],"type":"Point"}
}