{
  "type": "Feature",
  "properties": {
    "addr:full":"80 Ward St Toronto ON M6H 4A6",
    "addr:housenumber":"80",
    "addr:postcode":"m6h 4a6",
    "addr:street":"Ward St",
    "iso:country":"CA",
    "sg:address":"80 Ward St",
    "sg:city":"Toronto",
    "sg:classifiers":[
        {
            "category":"Home & Garden",
            "subcategory":"Furniture",
            "type":"Retail Goods"
        }
    ],
    "sg:phone":"+1 416 531 0681",
    "sg:postcode":"M6H 4A6",
    "sg:province":"ON",
    "sg:tags":[
        "builder",
        "custom"
    ],
    "wof:name":"Gibson Greenwood Inc",
    "wof:placetype":"venue"
},
  "geometry": {"coordinates":[-79.446808,43.66394],"type":"Point"}
}