{
  "type": "Feature",
  "properties": {
    "iso:country":"CA",
    "sg:address":"325 First Ave",
    "sg:city":"Strathmore",
    "sg:classifiers":[
        {
            "category":"Organizations",
            "subcategory":"Religious Organization",
            "type":"Services"
        }
    ],
    "sg:phone":"+1 403 934 3543",
    "sg:postcode":"T1P 1B3",
    "sg:province":"AB",
    "sg:tags":[
        "church"
    ],
    "wof:name":"Strathmore Alliance Church",
    "wof:placetype":"venue"
},
  "geometry": {"coordinates":[-113.39917755099999,51.0428924561],"type":"Point"}
}