{
  "type": "Feature",
  "properties": {
    "addr:full":"Tofield AB T0B 4J0",
    "addr:postcode":"t0b 4j0",
    "iso:country":"CA",
    "sg:city":"Tofield",
    "sg:classifiers":[
        {
            "category":"Autos & Motor Vehicles",
            "subcategory":"Auto Supplies",
            "type":"Retail Goods"
        }
    ],
    "sg:phone":"+1 780 662 3334",
    "sg:postcode":"T0B 4J0",
    "sg:province":"AB",
    "sg:tags":[
        "tire"
    ],
    "wof:name":"Kal Tire-Tofield",
    "wof:placetype":"venue"
},
  "geometry": {"coordinates":[-112.66881561300001,53.3696212769],"type":"Point"}
}