{
  "type": "Feature",
  "properties": {
    "addr:full":"2060 Av Francis-Hughes Laval QC H7S 1N4",
    "addr:housenumber":"2060",
    "addr:postcode":"h7s 1n4",
    "addr:street":"Av Francis-Hughes",
    "iso:country":"CA",
    "sg:address":"2060 Av Francis-Hughes",
    "sg:city":"Laval",
    "sg:classifiers":[
        {
            "category":"Manufacturing",
            "subcategory":"Tools & Machinery",
            "type":"Manufacturing & Wholesale Goods"
        }
    ],
    "sg:phone":"+1 450 667 1426",
    "sg:postcode":"H7S 1N4",
    "sg:province":"QC",
    "sg:tags":[
        "machine",
        "shop"
    ],
    "wof:name":"Atelier D'Usinage Speedway Inc",
    "wof:placetype":"venue"
},
  "geometry": {"coordinates":[-73.722115,45.57925],"type":"Point"}
}