{
  "type": "Feature",
  "properties": {
    "addr:full":"800 Rosser Ave #A1 Brandon MB R7A 6N5",
    "addr:housenumber":"800",
    "addr:postcode":"r7a 6n5",
    "addr:street":"Rosser Ave # A1",
    "iso:country":"CA",
    "sg:address":"800 Rosser Ave #A1",
    "sg:city":"Brandon",
    "sg:classifiers":[
        {
            "category":"Personal",
            "subcategory":"Beauty Salon",
            "type":"Services"
        }
    ],
    "sg:phone":"+1 204 727 0921",
    "sg:postcode":"R7A 6N5",
    "sg:province":"MB",
    "sg:tags":[
        "manicuring"
    ],
    "wof:name":"Gio Vannae Nail Design",
    "wof:placetype":"venue"
},
  "geometry": {"coordinates":[-99.94886779789999,49.8483581543],"type":"Point"}
}