{
  "type": "Feature",
  "properties": {
    "iso:country":"CA",
    "sg:city":"Port Coquitlam",
    "sg:classifiers":[
        {
            "category":"Real Estate",
            "subcategory":"Developer",
            "type":"Services"
        }
    ],
    "sg:phone":"+1 604 945 8860",
    "sg:postcode":"V3C 4T7",
    "sg:province":"BC",
    "sg:tags":[
        "company",
        "land"
    ],
    "wof:name":"Kenrae Enterprises Ltd",
    "wof:placetype":"venue"
},
  "geometry": {"coordinates":[-122.783424377,49.2677764893],"type":"Point"}
}