{
  "type": "Feature",
  "properties": {
    "addr:full":"609 Hanlan Rd Woodbridge ON L4L 4R8",
    "addr:housenumber":"609",
    "addr:postcode":"l4l 4r8",
    "addr:street":"Hanlan Rd",
    "iso:country":"CA",
    "sg:address":"609 Hanlan Rd",
    "sg:city":"Woodbridge",
    "sg:classifiers":[
        {
            "category":"Professional",
            "type":"Services"
        }
    ],
    "sg:phone":"+1 905 264 3585",
    "sg:postcode":"L4L 4R8",
    "sg:province":"ON",
    "sg:tags":[
        "establishment",
        "label"
    ],
    "wof:name":"Label Depot",
    "wof:placetype":"venue"
},
  "geometry": {"coordinates":[-79.5481338501,43.7722473145],"type":"Point"}
}