{
  "type": "Feature",
  "properties": {
    "addr:full":"234 Av Saint-Laurent Louiseville QC J5V 1J9",
    "addr:postcode":"j5v 1j9",
    "addr:street":"234 Av Saint-Laurent",
    "iso:country":"CA",
    "sg:address":"234 Av Saint-Laurent",
    "sg:city":"Louiseville",
    "sg:classifiers":[
        {
            "category":"Restaurant",
            "type":"Food & Drink"
        }
    ],
    "sg:phone":"+1 819 228 2930",
    "sg:postcode":"J5V 1J9",
    "sg:province":"QC",
    "wof:name":"Restaurant Au Casso",
    "wof:placetype":"venue"
},
  "geometry": {"coordinates":[-72.94471,46.255939],"type":"Point"}
}