{
  "type": "Feature",
  "properties": {
    "addr:full":"SE 25-15-25W Decker MB R0M 0K0",
    "addr:housenumber":"25-15-25w",
    "addr:postcode":"r0m 0k0",
    "addr:street":"Se",
    "iso:country":"CA",
    "sg:address":"SE 25-15-25W",
    "sg:city":"Decker",
    "sg:classifiers":[
        {
            "category":"Manufacturing",
            "subcategory":"Metals",
            "type":"Manufacturing & Wholesale Goods"
        }
    ],
    "sg:phone":"+1 204 764 2861",
    "sg:postcode":"R0M 0K0",
    "sg:province":"MB",
    "sg:tags":[
        "equipment",
        "heating",
        "system"
    ],
    "wof:name":"Decker Manufacturing Ltd",
    "wof:placetype":"venue"
},
  "geometry": {"coordinates":[-100.77037799999999,50.269955],"type":"Point"}
}