{
  "type": "Feature",
  "properties": {
    "iso:country":"CA",
    "sg:address":"20 DE L'Hotel-DE-Ville Prom",
    "sg:city":"Amqui",
    "sg:classifiers":[
        {
            "category":"Government",
            "subcategory":"Fire Station",
            "type":"Public Place"
        }
    ],
    "sg:phone":"+1 418 629 4242",
    "sg:postcode":"G5J 1A1",
    "sg:province":"QC",
    "sg:tags":[
        "department"
    ],
    "wof:name":"Amqui Administration Ofc",
    "wof:placetype":"venue"
},
  "geometry": {"coordinates":[-67.4258728027,48.464679718],"type":"Point"}
}