{
  "type": "Feature",
  "properties": {
    "addr:full":"84 Moira St E Belleville ON K8P 2S4",
    "addr:housenumber":"84",
    "addr:postcode":"k8p 2s4",
    "addr:street":"Moira St E",
    "iso:country":"CA",
    "sg:address":"84 Moira St E",
    "sg:city":"Belleville",
    "sg:classifiers":[
        {
            "category":"Wholesale",
            "subcategory":"Office Equipment",
            "type":"Manufacturing & Wholesale Goods"
        }
    ],
    "sg:phone":"+1 613 962 1820",
    "sg:postcode":"K8P 2S4",
    "sg:province":"ON",
    "sg:tags":[
        "accounting",
        "bookkeeping",
        "system",
        "general"
    ],
    "wof:name":"Mobile Bookkeeping Svc",
    "wof:placetype":"venue"
},
  "geometry": {"coordinates":[-77.38371276860001,44.1733703613],"type":"Point"}
}