{
  "type": "Feature",
  "properties": {
    "addr:full":"10825 142 St NW Edmonton AB T5N 3Y7",
    "addr:housenumber":"10825",
    "addr:postcode":"t5n 3y7",
    "addr:street":"142 St Nw",
    "iso:country":"CA",
    "sg:address":"10825 142 St NW",
    "sg:city":"Edmonton",
    "sg:classifiers":[
        {
            "category":"Education",
            "subcategory":"School",
            "type":"Public Place"
        }
    ],
    "sg:phone":"+1 780 454 5310",
    "sg:postcode":"T5N 3Y7",
    "sg:province":"AB",
    "wof:name":"Elves Special Needs Society",
    "wof:placetype":"venue"
},
  "geometry": {"coordinates":[-113.56559799999999,53.553223],"type":"Point"}
}