{
  "type": "Feature",
  "properties": {
    "iso:country":"CA",
    "sg:address":"3454 Bathurst St",
    "sg:city":"North York",
    "sg:classifiers":[
        {
            "category":"Food & Beverages",
            "subcategory":"Dairy",
            "type":"Retail Goods"
        }
    ],
    "sg:phone":"+1 416 787 8879",
    "sg:postcode":"M6A 2C4",
    "sg:province":"ON",
    "sg:tags":[
        "delicatessen"
    ],
    "wof:name":"Yossis Fine Foods",
    "wof:placetype":"venue"
},
  "geometry": {"coordinates":[-79.43185424799999,43.72813797],"type":"Point"}
}