{
  "type": "Feature",
  "properties": {
    "addr:full":"82 Boul Saint-Michel Dolbeau-Mistassini QC G8L 5J5",
    "addr:housenumber":"82",
    "addr:postcode":"g8l 5j5",
    "addr:street":"Boul Saint-Michel",
    "iso:country":"CA",
    "sg:address":"82 Boul Saint-Michel",
    "sg:city":"Dolbeau-Mistassini",
    "sg:classifiers":[
        {
            "category":"Local Transit",
            "type":"Transportation"
        }
    ],
    "sg:phone":"+1 418 276 3575",
    "sg:postcode":"G8L 5J5",
    "sg:province":"QC",
    "sg:tags":[
        "bus",
        "line"
    ],
    "wof:name":"Autobus Gerard Besson Inc",
    "wof:placetype":"venue"
},
  "geometry": {"coordinates":[-72.20684799999999,48.896095],"type":"Point"}
}