{
  "type": "Feature",
  "properties": {
    "iso:country":"CA",
    "sg:address":"1618 Rue Julien",
    "sg:city":"Rock Forest",
    "sg:classifiers":[
        {
            "category":"Arts & Performance",
            "subcategory":"Theater",
            "type":"Entertainment"
        }
    ],
    "sg:phone":"+1 819 821 4221",
    "sg:postcode":"J1N 3V1",
    "sg:province":"QC",
    "sg:tags":[
        "mobile",
        "discotheque"
    ],
    "wof:name":"Discoplus Enr",
    "wof:placetype":"venue"
},
  "geometry": {"coordinates":[-71.995377,45.371265],"type":"Point"}
}