{
  "type": "Feature",
  "properties": {
    "addr:full":"213 Rue Du College Lambton QC G0M 1H0",
    "addr:housenumber":"213",
    "addr:postcode":"g0m 1h0",
    "addr:street":"Rue Du College",
    "iso:country":"CA",
    "sg:address":"213 Rue Du College",
    "sg:city":"Lambton",
    "sg:classifiers":[
        {
            "category":"Real Estate",
            "subcategory":"Surveying",
            "type":"Services"
        }
    ],
    "sg:phone":"+1 418 486 7696",
    "sg:postcode":"G0M 1H0",
    "sg:province":"QC",
    "sg:tags":[
        "surveyor"
    ],
    "wof:name":"Perreault, Michel",
    "wof:placetype":"venue"
},
  "geometry": {"coordinates":[-71.09111,45.839699],"type":"Point"}
}