{
  "type": "Feature",
  "properties": {
    "addr:full":"210 Ossington Ave Toronto ON M6J 2Z9",
    "addr:housenumber":"210",
    "addr:postcode":"m6j 2z9",
    "addr:street":"Ossington Ave",
    "iso:country":"CA",
    "sg:address":"210 Ossington Ave",
    "sg:city":"Toronto",
    "sg:classifiers":[
        {
            "category":"Cinema",
            "subcategory":"Movie Rental",
            "type":"Entertainment"
        }
    ],
    "sg:phone":"+1 416 536 1311",
    "sg:postcode":"M6J 2Z9",
    "sg:province":"ON",
    "sg:tags":[
        "leasing",
        "video",
        "disc",
        "tape"
    ],
    "wof:name":"Hanh Phuc Video",
    "wof:placetype":"venue"
},
  "geometry": {"coordinates":[-79.42063899999999,43.648899],"type":"Point"}
}