{
  "type": "Feature",
  "properties": {
    "addr:full":"1085 Lauzon Rd Windsor ON N8S 3M8",
    "addr:housenumber":"1085",
    "addr:postcode":"n8s 3m8",
    "addr:street":"Lauzon Rd",
    "iso:country":"CA",
    "sg:address":"1085 Lauzon Rd",
    "sg:city":"Windsor",
    "sg:classifiers":[
        {
            "category":"Shopping",
            "type":"Retail Goods"
        }
    ],
    "sg:phone":"+1 519 944 7813",
    "sg:postcode":"N8S 3M8",
    "sg:province":"ON",
    "sg:tags":[
        "pet",
        "food",
        "supply"
    ],
    "wof:name":"Pet Valu Discount Pet Foods",
    "wof:placetype":"venue"
},
  "geometry": {"coordinates":[-82.940483,42.327656],"type":"Point"}
}