{
  "type": "Feature",
  "properties": {
    "addr:full":"528 15E Av Saint-Zacharie QC G0M 2C0",
    "addr:housenumber":"528",
    "addr:postcode":"g0m 2c0",
    "addr:street":"15E Av Saint-Zacharie",
    "iso:country":"CA",
    "sg:address":"528 15E Av",
    "sg:city":"Saint-Zacharie",
    "sg:classifiers":[
        {
            "category":"Health Services",
            "subcategory":"Doctor",
            "type":"Services"
        }
    ],
    "sg:phone":"+1 418 593 5511",
    "sg:postcode":"G0M 2C0",
    "sg:province":"QC",
    "sg:tags":[
        "clinic"
    ],
    "wof:name":"Clinique Medicale St-Zacharie",
    "wof:placetype":"venue"
},
  "geometry": {"coordinates":[-70.363029,46.126438],"type":"Point"}
}