{
  "type": "Feature",
  "properties": {
    "addr:full":"2075 Ch DE Sainte-Catherine Rock Forest QC J1N 1E7",
    "addr:housenumber":"2075",
    "addr:postcode":"j1n 1e7",
    "addr:street":"Ch De Sainte-Catherine",
    "iso:country":"CA",
    "sg:address":"2075 Ch DE Sainte-Catherine",
    "sg:city":"Rock Forest",
    "sg:classifiers":[
        {
            "category":"Organizations",
            "subcategory":"Religious Organization",
            "type":"Services"
        }
    ],
    "sg:phone":"+1 819 562 4676",
    "sg:postcode":"J1N 1E7",
    "sg:province":"QC",
    "wof:name":"Missionnaires Des Marinnhill",
    "wof:placetype":"venue"
},
  "geometry": {"coordinates":[-71.934181,45.36871],"type":"Point"}
}