{
  "type": "Feature",
  "properties": {
    "addr:full":"Rte 389 N 24E Kms Baie-Comeau QC G4Z 2G8",
    "addr:housenumber":"24e",
    "addr:postcode":"g4z 2g8",
    "addr:street":"Rte 389 N;Kms",
    "iso:country":"CA",
    "sg:address":"Rte 389 N 24E Kms",
    "sg:city":"Baie-Comeau",
    "sg:classifiers":[
        {
            "category":"Travel",
            "subcategory":"Campground",
            "type":"Entertainment"
        }
    ],
    "sg:phone":"+1 418 296 2810",
    "sg:postcode":"G4Z 2G8",
    "sg:province":"QC",
    "wof:name":"Camping Manic 2",
    "wof:placetype":"venue"
},
  "geometry": {"coordinates":[-68.24215700000001,49.247063],"type":"Point"}
}