{
  "type": "Feature",
  "properties": {
    "addr:full":"2855 Rue Sabourin Saint-Laurent QC H4S 1M9",
    "addr:housenumber":"2855",
    "addr:postcode":"h4s 1m9",
    "addr:street":"Rue Sabourin",
    "iso:country":"CA",
    "sg:address":"2855 Rue Sabourin",
    "sg:city":"Saint-Laurent",
    "sg:classifiers":[
        {
            "category":"Manufacturing",
            "subcategory":"Metals",
            "type":"Manufacturing & Wholesale Goods"
        }
    ],
    "sg:phone":"+1 514 331 3730",
    "sg:postcode":"H4S 1M9",
    "sg:province":"QC",
    "sg:tags":[
        "steel"
    ],
    "wof:name":"Nash Industries Ltd",
    "wof:placetype":"venue"
},
  "geometry": {"coordinates":[-73.749138,45.492893],"type":"Point"}
}