{
  "type": "Feature",
  "properties": {
    "addr:full":"208 Vesta Dr Toronto ON M5P 2Z9",
    "addr:housenumber":"208",
    "addr:postcode":"m5p 2z9",
    "addr:street":"Vesta Dr",
    "iso:country":"CA",
    "sg:address":"208 Vesta Dr",
    "sg:city":"Toronto",
    "sg:classifiers":[
        {
            "category":"Banks & Credit Unions",
            "subcategory":"Investment Brokerage",
            "type":"Services"
        }
    ],
    "sg:phone":"+1 416 407 8395",
    "sg:postcode":"M5P 2Z9",
    "sg:province":"ON",
    "sg:tags":[
        "consultant",
        "planning",
        "financial"
    ],
    "wof:name":"Churchill Financial Svc Inc",
    "wof:placetype":"venue"
},
  "geometry": {"coordinates":[-79.418098,43.695335],"type":"Point"}
}