{
  "type": "Feature",
  "properties": {
    "iso:country":"CA",
    "sg:address":"5600 Elbow Dr SW",
    "sg:city":"Calgary",
    "sg:classifiers":[
        {
            "category":"Health Services",
            "subcategory":"Doctor",
            "type":"Services"
        }
    ],
    "sg:phone":"+1 403 264 3831",
    "sg:postcode":"T2V 1H8",
    "sg:province":"AB",
    "sg:tags":[
        "dentist"
    ],
    "wof:name":"Elbow Drive Dental Ctr",
    "wof:placetype":"venue"
},
  "geometry": {"coordinates":[-114.08118399999999,51.004131],"type":"Point"}
}