{
  "type": "Feature",
  "properties": {
    "addr:full":"2065 Boul Des Laurentides Laval QC H7M 4M2",
    "addr:housenumber":"2065",
    "addr:postcode":"h7m 4m2",
    "addr:street":"Boul Des Laurentides",
    "iso:country":"CA",
    "sg:address":"2065 Boul Des Laurentides",
    "sg:city":"Laval",
    "sg:classifiers":[
        {
            "category":"Shopping",
            "subcategory":"Pharmacy",
            "type":"Retail Goods"
        }
    ],
    "sg:phone":"+1 450 663 0672",
    "sg:postcode":"H7M 4M2",
    "sg:province":"QC",
    "wof:name":"Jean Coutu",
    "wof:placetype":"venue"
},
  "geometry": {"coordinates":[-73.7327804565,45.6072654724],"type":"Point"}
}