{
  "type": "Feature",
  "properties": {
    "addr:full":"7475 Vedder Rd Chilliwack BC V2R 4E7",
    "addr:housenumber":"7475",
    "addr:postcode":"v2r 4e7",
    "addr:street":"Vedder Rd",
    "iso:country":"CA",
    "sg:address":"7475 Vedder Rd",
    "sg:city":"Chilliwack",
    "sg:classifiers":[
        {
            "category":"Autos & Motor Vehicles",
            "subcategory":"Recreational Vehicle Sales",
            "type":"Retail Goods"
        }
    ],
    "sg:phone":"+1 604 858 4988",
    "sg:postcode":"V2R 4E7",
    "sg:province":"BC",
    "wof:name":"Pacific Coast Van & Rv Ltd",
    "wof:placetype":"venue"
},
  "geometry": {"coordinates":[-121.96013600000001,49.141201],"type":"Point"}
}