{
  "type": "Feature",
  "properties": {
    "addr:full":"321 Main St N Moose Jaw SK S6H 0W2",
    "addr:housenumber":"321",
    "addr:postcode":"s6h 0w2",
    "addr:street":"Main St N",
    "iso:country":"CA",
    "sg:address":"321 Main St N",
    "sg:city":"Moose Jaw",
    "sg:classifiers":[
        {
            "category":"Shopping",
            "type":"Retail Goods"
        }
    ],
    "sg:phone":"+1 306 694 0880",
    "sg:postcode":"S6H 0W2",
    "sg:province":"SK",
    "sg:tags":[
        "cosmetic",
        "perfume"
    ],
    "wof:name":"Merle Norman & More",
    "wof:placetype":"venue"
},
  "geometry": {"coordinates":[-105.53440856900001,50.3928146362],"type":"Point"}
}