{
  "type": "Feature",
  "properties": {
    "addr:full":"2683 Rue Ontario E Montreal QC H2K 1X1",
    "addr:housenumber":"2683",
    "addr:postcode":"h2k 1x1",
    "addr:street":"Rue Ontario E",
    "iso:country":"CA",
    "sg:address":"2683 Rue Ontario E",
    "sg:city":"Montreal",
    "sg:classifiers":[
        {
            "category":"Bars & Pubs",
            "type":"Food & Drink"
        }
    ],
    "sg:phone":"+1 514 526 9166",
    "sg:postcode":"H2K 1X1",
    "sg:province":"QC",
    "sg:tags":[
        "club",
        "night"
    ],
    "wof:name":"Bar Sexe Mania",
    "wof:placetype":"venue"
},
  "geometry": {"coordinates":[-73.551643,45.534603],"type":"Point"}
}