{
  "type": "Feature",
  "properties": {
    "addr:full":"Waterford ON N0E 1Y0",
    "addr:postcode":"n0e 1y0",
    "iso:country":"CA",
    "sg:city":"Waterford",
    "sg:classifiers":[
        {
            "category":"Freight",
            "type":"Transportation"
        }
    ],
    "sg:phone":"+1 519 443 7431",
    "sg:postcode":"N0E 1Y0",
    "sg:province":"ON",
    "sg:tags":[
        "trucking"
    ],
    "wof:name":"Keruda Traffic Svc Inc",
    "wof:placetype":"venue"
},
  "geometry": {"coordinates":[-80.287940979,42.9252090454],"type":"Point"}
}