{
  "type": "Feature",
  "properties": {
    "iso:country":"CA",
    "sg:city":"Burnaby",
    "sg:classifiers":[
        {
            "category":"Health Services",
            "subcategory":"Doctor",
            "type":"Services"
        }
    ],
    "sg:phone":"+1 604 420 1777",
    "sg:postcode":"V3J 7T8",
    "sg:province":"BC",
    "sg:tags":[
        "physician",
        "surgeon"
    ],
    "wof:name":"Jemima J Wasswa-Kintu Inc",
    "wof:placetype":"venue"
},
  "geometry": {"coordinates":[-122.893104553,49.2521858215],"type":"Point"}
}