{
  "type": "Feature",
  "properties": {
    "addr:full":"101 2nd St E Meadow Lake SK S9X 1G4",
    "addr:housenumber":"101",
    "addr:postcode":"s9x 1g4",
    "addr:street":"2Nd St E;Lake",
    "iso:country":"CA",
    "sg:address":"101 2nd St E",
    "sg:city":"Meadow Lake",
    "sg:classifiers":[
        {
            "category":"Retail",
            "subcategory":"Laundry & Dry Cleaning",
            "type":"Services"
        }
    ],
    "sg:phone":"+1 306 236 3463",
    "sg:postcode":"S9X 1G4",
    "sg:province":"SK",
    "wof:name":"D J's Laundromat",
    "wof:placetype":"venue"
},
  "geometry": {"coordinates":[-108.430206,54.125664],"type":"Point"}
}