{
  "type": "Feature",
  "properties": {
    "addr:full":"1428 Shediac Rd Moncton NB E1A 7A7",
    "addr:housenumber":"1428",
    "addr:postcode":"e1a 7a7",
    "addr:street":"Shediac Rd",
    "iso:country":"CA",
    "sg:address":"1428 Shediac Rd",
    "sg:city":"Moncton",
    "sg:classifiers":[
        {
            "category":"Health Services",
            "subcategory":"Doctor",
            "type":"Services"
        }
    ],
    "sg:phone":"+1 506 855 6030",
    "sg:postcode":"E1A 7A7",
    "sg:province":"NB",
    "sg:tags":[
        "clinic"
    ],
    "wof:name":"Harrisville Pain Clinic",
    "wof:placetype":"venue"
},
  "geometry": {"coordinates":[-64.705322,46.124039],"type":"Point"}
}