{
  "type": "Feature",
  "properties": {
    "iso:country":"CA",
    "sg:address":"31 Clothier St E",
    "sg:city":"Kemptville",
    "sg:classifiers":[
        {
            "category":"Retail",
            "subcategory":"Auto Repair",
            "type":"Services"
        }
    ],
    "sg:phone":"+1 613 258 4456",
    "sg:postcode":"K0G 1J0",
    "sg:province":"ON",
    "sg:tags":[
        "repairing",
        "automobile",
        "tire"
    ],
    "wof:name":"416 Tire Svc",
    "wof:placetype":"venue"
},
  "geometry": {"coordinates":[-75.6471862793,45.0170288086],"type":"Point"}
}