{
  "type": "Feature",
  "properties": {
    "addr:full":"PO Box 371 STN Main Fergus ON N1M 3E2",
    "addr:housenumber":"po",
    "addr:postcode":"n1m 3e2",
    "addr:street":"Box 371 Stn Main",
    "iso:country":"CA",
    "sg:address":"PO Box 371 STN Main",
    "sg:city":"Fergus",
    "sg:classifiers":[
        {
            "category":"Retail",
            "subcategory":"Repair Shop",
            "type":"Services"
        }
    ],
    "sg:phone":"+1 519 843 3697",
    "sg:postcode":"N1M 3E2",
    "sg:province":"ON",
    "sg:tags":[
        "gas",
        "appliance"
    ],
    "wof:name":"Allpro Gas Svc",
    "wof:placetype":"venue"
},
  "geometry": {"coordinates":[-80.37814331049999,43.7054443359],"type":"Point"}
}