{
  "type": "Feature",
  "properties": {
    "addr:full":"517 Blue Mountain St #301 Coquitlam BC V3J 4P8",
    "addr:housenumber":"517",
    "addr:postcode":"v3j 4p8",
    "addr:street":"Blue Mountain St # 301",
    "iso:country":"CA",
    "sg:address":"517 Blue Mountain St #301",
    "sg:city":"Coquitlam",
    "sg:classifiers":[
        {
            "category":"Real Estate",
            "subcategory":"Real Estate Operator",
            "type":"Services"
        }
    ],
    "sg:phone":"+1 604 931 4014",
    "sg:postcode":"V3J 4P8",
    "sg:province":"BC",
    "sg:tags":[
        "apartment"
    ],
    "wof:name":"Blue Mountain Apartment",
    "wof:placetype":"venue"
},
  "geometry": {"coordinates":[-122.868843079,49.250087738],"type":"Point"}
}