{
  "type": "Feature",
  "properties": {
    "addr:full":"1 Chukuni Dr Ear Falls ON P0V 1T0",
    "addr:housenumber":"1",
    "addr:postcode":"p0v 1t0",
    "addr:street":"Chukuni Dr",
    "iso:country":"CA",
    "sg:address":"1 Chukuni Dr",
    "sg:city":"Ear Falls",
    "sg:classifiers":[
        {
            "category":"Building & Trades",
            "subcategory":"Electrical",
            "type":"Services"
        }
    ],
    "sg:phone":"+1 807 222 3245",
    "sg:postcode":"P0V 1T0",
    "sg:province":"ON",
    "sg:tags":[
        "electric",
        "contractor"
    ],
    "wof:name":"Kennedy Electric",
    "wof:placetype":"venue"
},
  "geometry": {"coordinates":[-93.22996521,50.6362190247],"type":"Point"}
}