{
  "type": "Feature",
  "properties": {
    "addr:full":"Farm Assiniboia SK S0H 0B0",
    "addr:postcode":"s0h 0b0",
    "iso:country":"CA",
    "sg:address":"Farm",
    "sg:city":"Assiniboia",
    "sg:classifiers":[
        {
            "category":"Building & Trades",
            "subcategory":"Construction",
            "type":"Services"
        }
    ],
    "sg:phone":"+1 306 642 4061",
    "sg:postcode":"S0H 0B0",
    "sg:province":"SK",
    "sg:tags":[
        "excavating",
        "contractor"
    ],
    "wof:name":"Stevenson's Dirt Moving",
    "wof:placetype":"venue"
},
  "geometry": {"coordinates":[-105.993118,49.632839],"type":"Point"}
}