{
  "type": "Feature",
  "properties": {
    "addr:full":"8328 Rue Saint-Denis Montreal QC H2P 2G8",
    "addr:housenumber":"8328",
    "addr:postcode":"h2p 2g8",
    "addr:street":"Rue Saint-Denis",
    "iso:country":"CA",
    "sg:address":"8328 Rue Saint-Denis",
    "sg:city":"Montreal",
    "sg:classifiers":[
        {
            "category":"Professional",
            "subcategory":"Lawyer & Legal Services",
            "type":"Services"
        }
    ],
    "sg:phone":"+1 514 385 9409",
    "sg:postcode":"H2P 2G8",
    "sg:province":"QC",
    "sg:tags":[
        "attorney"
    ],
    "wof:name":"Cloutier, Yves",
    "wof:placetype":"venue"
},
  "geometry": {"coordinates":[-73.63305699999999,45.543568],"type":"Point"}
}