{
  "type": "Feature",
  "properties": {
    "iso:country":"CA",
    "sg:address":"1115 Rue Saint-Amour",
    "sg:city":"Saint-Laurent",
    "sg:classifiers":[
        {
            "category":"Freight",
            "type":"Transportation"
        }
    ],
    "sg:phone":"+1 514 956 8800",
    "sg:postcode":"H4S 1T4",
    "sg:province":"QC",
    "sg:tags":[
        "trucking"
    ],
    "wof:name":"Argus Transport Canada Inc",
    "wof:placetype":"venue"
},
  "geometry": {"coordinates":[-73.728058,45.487949],"type":"Point"}
}