{
  "type": "Feature",
  "properties": {
    "addr:full":"Coquitlam BC V3B 2P5",
    "addr:postcode":"v3b 2p5",
    "iso:country":"CA",
    "sg:city":"Coquitlam",
    "sg:classifiers":[
        {
            "category":"Education",
            "subcategory":"Dance Studio",
            "type":"Public Place"
        }
    ],
    "sg:phone":"+1 604 464 6487",
    "sg:postcode":"V3B 2P5",
    "sg:province":"BC",
    "sg:tags":[
        "instruction",
        "dancing"
    ],
    "wof:name":"Footloose Dance Productions",
    "wof:placetype":"venue"
},
  "geometry": {"coordinates":[-122.800163269,49.2825698853],"type":"Point"}
}