{
  "type": "Feature",
  "properties": {
    "addr:full":"2500 Rue DE L'Eglise Val-David QC J0T 2N0",
    "addr:housenumber":"2500",
    "addr:postcode":"j0t 2n0",
    "addr:street":"Rue De L'Eglise",
    "iso:country":"CA",
    "sg:address":"2500 Rue DE L'Eglise",
    "sg:city":"Val-David",
    "sg:classifiers":[
        {
            "category":"Food & Beverages",
            "subcategory":"Groceries & Convenience Stores",
            "type":"Retail Goods"
        }
    ],
    "sg:phone":"+1 819 322 2030",
    "sg:postcode":"J0T 2N0",
    "sg:province":"QC",
    "sg:tags":[
        "grocer"
    ],
    "wof:name":"L Dufresne & Fils Ltee",
    "wof:placetype":"venue"
},
  "geometry": {"coordinates":[-74.47188568120001,46.1305656433],"type":"Point"}
}