{
  "type": "Feature",
  "properties": {
    "addr:full":"5620 94A St NW Edmonton AB T6E 3E4",
    "addr:housenumber":"5620",
    "addr:postcode":"t6e 3e4",
    "addr:street":"94A St Nw",
    "iso:country":"CA",
    "sg:address":"5620 94A St NW",
    "sg:city":"Edmonton",
    "sg:classifiers":[
        {
            "category":"Manufacturing",
            "subcategory":"Tools & Machinery",
            "type":"Manufacturing & Wholesale Goods"
        }
    ],
    "sg:phone":"+1 780 468 1311",
    "sg:postcode":"T6E 3E4",
    "sg:province":"AB",
    "sg:tags":[
        "machine",
        "shop"
    ],
    "wof:name":"Alberta Production Machining",
    "wof:placetype":"venue"
},
  "geometry": {"coordinates":[-113.47214508099999,53.4921379089],"type":"Point"}
}