{
  "type": "Feature",
  "properties": {
    "addr:full":"1127 Chemong Rd Peterborough ON K9H 7R8",
    "addr:housenumber":"1127",
    "addr:postcode":"k9h 7r8",
    "addr:street":"Chemong Rd",
    "iso:country":"CA",
    "sg:address":"1127 Chemong Rd",
    "sg:city":"Peterborough",
    "sg:classifiers":[
        {
            "category":"Autos & Motor Vehicles",
            "subcategory":"Fuel & Gas Station",
            "type":"Retail Goods"
        }
    ],
    "sg:phone":"+1 705 876 0992",
    "sg:postcode":"K9H 7R8",
    "sg:province":"ON",
    "sg:tags":[
        "oil"
    ],
    "wof:name":"Esso",
    "wof:placetype":"venue"
},
  "geometry": {"coordinates":[-78.33970600000001,44.327297],"type":"Point"}
}