{
  "type": "Feature",
  "properties": {
    "iso:country":"CA",
    "sg:address":"806 Chemong Rd",
    "sg:city":"Peterborough",
    "sg:classifiers":[
        {
            "category":"Banks & Credit Unions",
            "subcategory":"Bank",
            "type":"Services"
        }
    ],
    "sg:phone":"+1 705 743 0545",
    "sg:postcode":"K9H 5Z6",
    "sg:province":"ON",
    "wof:name":"Royal Bank Financial Group",
    "wof:placetype":"venue"
},
  "geometry": {"coordinates":[-78.329536,44.317192],"type":"Point"}
}