{
  "type": "Feature",
  "properties": {
    "iso:country":"CA",
    "sg:address":"1 Boland Dr",
    "sg:city":"Erin",
    "sg:classifiers":[
        {
            "category":"Arena",
            "subcategory":"Sports Club",
            "type":"Entertainment"
        }
    ],
    "sg:phone":"+1 519 833 2114",
    "sg:postcode":"N0B 1T0",
    "sg:province":"ON",
    "sg:tags":[
        "government",
        "athletic",
        "fields",
        "rooms",
        "stadium",
        "banquet"
    ],
    "wof:name":"Erin Community Ctr & Arena",
    "wof:placetype":"venue"
},
  "geometry": {"coordinates":[-80.0674362183,43.7775535583],"type":"Point"}
}