{
  "type": "Feature",
  "properties": {
    "addr:full":"1680 Sismet Rd Mississauga ON L4W 1R4",
    "addr:housenumber":"1680",
    "addr:postcode":"l4w 1r4",
    "addr:street":"Sismet Rd",
    "iso:country":"CA",
    "sg:address":"1680 Sismet Rd",
    "sg:city":"Mississauga",
    "sg:classifiers":[
        {
            "category":"Home & Garden",
            "subcategory":"Building Materials",
            "type":"Retail Goods"
        }
    ],
    "sg:phone":"+1 905 602 5887",
    "sg:postcode":"L4W 1R4",
    "sg:province":"ON",
    "sg:tags":[
        "windows",
        "door"
    ],
    "wof:name":"Just Aluminum & Glass Inc",
    "wof:placetype":"venue"
},
  "geometry": {"coordinates":[-79.6216812134,43.6451873779],"type":"Point"}
}