{
  "type": "Feature",
  "properties": {
    "addr:full":"376 Browns Line Etobicoke ON M8W 3T7",
    "addr:housenumber":"376",
    "addr:postcode":"m8w 3t7",
    "addr:street":"Browns Line",
    "iso:country":"CA",
    "sg:address":"376 Browns Line",
    "sg:city":"Etobicoke",
    "sg:classifiers":[
        {
            "category":"Restaurant",
            "type":"Food & Drink"
        }
    ],
    "sg:phone":"+1 416 255 4414",
    "sg:postcode":"M8W 3T7",
    "sg:province":"ON",
    "sg:tags":[
        "cafe"
    ],
    "wof:name":"Cafe Sport Bar Europe",
    "wof:placetype":"venue"
},
  "geometry": {"coordinates":[-79.544899,43.600555],"type":"Point"}
}