{
  "type": "Feature",
  "properties": {
    "iso:country":"CA",
    "sg:address":"1225 Wonderland Rd N",
    "sg:city":"London",
    "sg:classifiers":[
        {
            "category":"Food & Beverages",
            "subcategory":"Specialty",
            "type":"Retail Goods"
        }
    ],
    "sg:phone":"+1 519 473 0443",
    "sg:postcode":"N6G 2V9",
    "sg:province":"ON",
    "sg:tags":[
        "health",
        "diet"
    ],
    "wof:name":"S & H Health Foods",
    "wof:placetype":"venue"
},
  "geometry": {"coordinates":[-81.303558,43.005066],"type":"Point"}
}