{
  "type": "Feature",
  "properties": {
    "addr:full":"2077 Av Methot Plessisville QC G6L 2Y4",
    "addr:housenumber":"2077",
    "addr:postcode":"g6l 2y4",
    "addr:street":"Av Methot",
    "iso:country":"CA",
    "sg:address":"2077 Av Methot",
    "sg:city":"Plessisville",
    "sg:classifiers":[
        {
            "category":"Manufacturing",
            "subcategory":"Metals",
            "type":"Manufacturing & Wholesale Goods"
        }
    ],
    "sg:phone":"+1 819 362 8668",
    "sg:postcode":"G6L 2Y4",
    "sg:province":"QC",
    "sg:tags":[
        "hardware"
    ],
    "wof:name":"Estampillage Paul Piche Inc",
    "wof:placetype":"venue"
},
  "geometry": {"coordinates":[-71.772156,46.229439],"type":"Point"}
}