{
  "type": "Feature",
  "properties": {
    "addr:full":"525 Rue Saint-Edouard Saint-Jerome QC J7Z 4T7",
    "addr:housenumber":"525",
    "addr:postcode":"j7z 4t7",
    "addr:street":"Rue Saint-Edouard Saint-Jerome",
    "iso:country":"CA",
    "sg:address":"525 Rue Saint-Edouard",
    "sg:city":"Saint-Jerome",
    "sg:classifiers":[
        {
            "category":"Food & Beverages",
            "subcategory":"Groceries & Convenience Stores",
            "type":"Retail Goods"
        }
    ],
    "sg:phone":"+1 450 438 8938",
    "sg:postcode":"J7Z 4T7",
    "sg:province":"QC",
    "wof:name":"Depanneur Felicity",
    "wof:placetype":"venue"
},
  "geometry": {"coordinates":[-73.999252,45.782364],"type":"Point"}
}