{
  "type": "Feature",
  "properties": {
    "iso:country":"CA",
    "sg:city":"Woodbridge",
    "sg:classifiers":[
        {
            "category":"Autos & Motor Vehicles",
            "subcategory":"Boat Sales",
            "type":"Retail Goods"
        }
    ],
    "sg:phone":"+1 905 851 3903",
    "sg:postcode":"L4L 1T7",
    "sg:province":"ON",
    "sg:tags":[
        "dealer"
    ],
    "wof:name":"Leisure Marine Warehouse",
    "wof:placetype":"venue"
},
  "geometry": {"coordinates":[-79.614555,43.774593],"type":"Point"}
}