{
  "type": "Feature",
  "properties": {
    "addr:full":"9500 No. 4 Rd Richmond BC V7A 2Y9",
    "addr:postcode":"9500;v7a 2y9",
    "addr:street":"4 Rd",
    "iso:country":"CA",
    "sg:address":"9500 No. 4 Rd",
    "sg:city":"Richmond",
    "sg:classifiers":[
        {
            "category":"Education",
            "subcategory":"School",
            "type":"Public Place"
        }
    ],
    "sg:phone":"+1 604 668 6575",
    "sg:postcode":"V7A 2Y9",
    "sg:province":"BC",
    "wof:name":"Mc Nair Secondary School",
    "wof:placetype":"venue"
},
  "geometry": {"coordinates":[-123.11391449,49.1428756714],"type":"Point"}
}