{
  "type": "Feature",
  "properties": {
    "addr:full":"101 Bridge St Carleton Place ON K7C 2V4",
    "addr:housenumber":"101",
    "addr:postcode":"k7c 2v4",
    "addr:street":"Bridge St",
    "iso:country":"CA",
    "sg:address":"101 Bridge St",
    "sg:city":"Carleton Place",
    "sg:classifiers":[
        {
            "category":"Restaurant",
            "type":"Food & Drink"
        }
    ],
    "sg:phone":"+1 613 257 1234",
    "sg:postcode":"K7C 2V4",
    "sg:province":"ON",
    "wof:name":"Olympia Restaurant Dining Room",
    "wof:placetype":"venue"
},
  "geometry": {"coordinates":[-76.14471399999999,45.138996],"type":"Point"}
}