{
  "type": "Feature",
  "properties": {
    "addr:full":"2230 Boul Saint-Paul Chicoutimi QC G7K 1E6",
    "addr:housenumber":"2230",
    "addr:postcode":"g7k 1e6",
    "addr:street":"Boul Saint-Paul",
    "iso:country":"CA",
    "sg:address":"2230 Boul Saint-Paul",
    "sg:city":"Chicoutimi",
    "sg:classifiers":[
        {
            "category":"Food & Beverages",
            "subcategory":"Groceries & Convenience Stores",
            "type":"Retail Goods"
        }
    ],
    "sg:phone":"+1 418 549 3345",
    "sg:postcode":"G7K 1E6",
    "sg:province":"QC",
    "wof:name":"Accommodation 2230 Enr",
    "wof:placetype":"venue"
},
  "geometry": {"coordinates":[-71.1131820679,48.3898887634],"type":"Point"}
}