{
  "type": "Feature",
  "properties": {
    "addr:full":"4540 No. 3 Rd Richmond BC V6X 2C2",
    "addr:postcode":"4540;v6x 2c2",
    "addr:street":"3 Rd",
    "iso:country":"CA",
    "sg:address":"4540 No. 3 Rd",
    "sg:city":"Richmond",
    "sg:classifiers":[
        {
            "category":"Real Estate",
            "subcategory":"Real Estate Operator",
            "type":"Services"
        }
    ],
    "sg:phone":"+1 604 207 2818",
    "sg:postcode":"V6X 2C2",
    "sg:province":"BC",
    "sg:tags":[
        "mall",
        "shopping",
        "center"
    ],
    "wof:name":"Empire Centre",
    "wof:placetype":"venue"
},
  "geometry": {"coordinates":[-123.136253357,49.1809577942],"type":"Point"}
}