{
  "type": "Feature",
  "properties": {
    "addr:full":"Vancouver BC V6G 2M9",
    "addr:postcode":"v6g 2m9",
    "iso:country":"CA",
    "sg:city":"Vancouver",
    "sg:classifiers":[
        {
            "category":"Restaurant",
            "type":"Food & Drink"
        }
    ],
    "sg:phone":"+1 604 688 8856",
    "sg:postcode":"V6G 2M9",
    "sg:province":"BC",
    "wof:name":"Won More Szechuan Cuisine",
    "wof:placetype":"venue"
},
  "geometry": {"coordinates":[-123.14147199999999,49.287312],"type":"Point"}
}