{
  "type": "Feature",
  "properties": {
    "addr:full":"210 Humber Ave Labrador City NL A2V 2W8",
    "addr:housenumber":"210",
    "addr:postcode":"a2v 2w8",
    "addr:street":"Humber Ave",
    "iso:country":"CA",
    "sg:address":"210 Humber Ave",
    "sg:city":"Labrador City",
    "sg:classifiers":[
        {
            "category":"Recreation",
            "type":"Entertainment"
        }
    ],
    "sg:phone":"+1 709 944 2888",
    "sg:postcode":"A2V 2W8",
    "sg:province":"NL",
    "sg:tags":[
        "lounge",
        "parlor",
        "billiard",
        "cocktail"
    ],
    "wof:name":"Mc Nally's Billards Inc",
    "wof:placetype":"venue"
},
  "geometry": {"coordinates":[-66.90961456300001,52.9431610107],"type":"Point"}
}