{
  "type": "Feature",
  "properties": {
    "addr:full":"8374 Longwoods Rd London ON N6P 1L5",
    "addr:housenumber":"8374",
    "addr:postcode":"n6p 1l5",
    "addr:street":"Longwoods Rd",
    "iso:country":"CA",
    "sg:address":"8374 Longwoods Rd",
    "sg:city":"London",
    "sg:classifiers":[
        {
            "category":"Building & Trades",
            "subcategory":"Construction",
            "type":"Services"
        }
    ],
    "sg:phone":"+1 519 652 2820",
    "sg:postcode":"N6P 1L5",
    "sg:province":"ON",
    "sg:tags":[
        "home",
        "improvement"
    ],
    "wof:name":"Lormac",
    "wof:placetype":"venue"
},
  "geometry": {"coordinates":[-81.33467899999999,42.910938],"type":"Point"}
}