{
  "type": "Feature",
  "properties": {
    "addr:full":"Edmonton AB T5L 4S6",
    "addr:postcode":"t5l 4s6",
    "iso:country":"CA",
    "sg:city":"Edmonton",
    "sg:classifiers":[
        {
            "category":"Shopping",
            "subcategory":"Books",
            "type":"Retail Goods"
        }
    ],
    "sg:phone":"+1 780 455 4467",
    "sg:postcode":"T5L 4S6",
    "sg:province":"AB",
    "sg:tags":[
        "dealer"
    ],
    "wof:name":"Blessings Christian Marketplc",
    "wof:placetype":"venue"
},
  "geometry": {"coordinates":[-113.568016,53.570183],"type":"Point"}
}