{
  "type": "Feature",
  "properties": {
    "addr:full":"23287 Mckay Ave Maple Ridge BC V2W 1B9",
    "addr:housenumber":"23287",
    "addr:postcode":"v2w 1b9",
    "addr:street":"Mckay Ave",
    "iso:country":"CA",
    "sg:address":"23287 Mckay Ave",
    "sg:city":"Maple Ridge",
    "sg:classifiers":[
        {
            "category":"Retail",
            "subcategory":"Auto Repair",
            "type":"Services"
        }
    ],
    "sg:phone":"+1 604 467 6611",
    "sg:postcode":"V2W 1B9",
    "sg:province":"BC",
    "sg:tags":[
        "wrecker"
    ],
    "wof:name":"Maple Ridge Towing Ltd",
    "wof:placetype":"venue"
},
  "geometry": {"coordinates":[-122.57402,49.191662],"type":"Point"}
}