{
  "type": "Feature",
  "properties": {
    "addr:full":"525 West St S Orillia ON L3V 5H2",
    "addr:housenumber":"525",
    "addr:postcode":"l3v 5h2",
    "addr:street":"West St S",
    "iso:country":"CA",
    "sg:address":"525 West St S",
    "sg:city":"Orillia",
    "sg:classifiers":[
        {
            "category":"Banks & Credit Unions",
            "subcategory":"Financial Services",
            "type":"Services"
        }
    ],
    "sg:phone":"+1 705 327 2797",
    "sg:postcode":"L3V 5H2",
    "sg:province":"ON",
    "sg:tags":[
        "bankruptcy",
        "trustee"
    ],
    "wof:name":"Paddon & Yorke Inc",
    "wof:placetype":"venue"
},
  "geometry": {"coordinates":[-79.409294,44.595501],"type":"Point"}
}