{
  "type": "Feature",
  "properties": {
    "iso:country":"CA",
    "sg:address":"2400 Rue DE L'Industrie",
    "sg:city":"Trois-Rivieres-Ouest",
    "sg:classifiers":[
        {
            "category":"Wholesale",
            "subcategory":"Electrical",
            "type":"Manufacturing & Wholesale Goods"
        }
    ],
    "sg:phone":"+1 819 691 3188",
    "sg:postcode":"G8Z 4R5",
    "sg:province":"QC",
    "sg:tags":[
        "equipment",
        "electric",
        "supply"
    ],
    "wof:name":"Nedco Quebec",
    "wof:placetype":"venue"
},
  "geometry": {"coordinates":[-72.58802,46.336578],"type":"Point"}
}