{
  "type": "Feature",
  "properties": {
    "addr:full":"455 Queen St W Sault Ste Marie ON P6A 1A7",
    "addr:housenumber":"455",
    "addr:postcode":"p6a 1a7",
    "addr:street":"Queen St W",
    "iso:country":"CA",
    "sg:address":"455 Queen St W",
    "sg:city":"Sault Ste Marie",
    "sg:classifiers":[
        {
            "category":"Recreation",
            "type":"Entertainment"
        }
    ],
    "sg:phone":"+1 705 253 0889",
    "sg:postcode":"P6A 1A7",
    "sg:province":"ON",
    "sg:tags":[
        "hall",
        "auditorium"
    ],
    "wof:name":"Verdi Hall",
    "wof:placetype":"venue"
},
  "geometry": {"coordinates":[-84.351479,46.518684],"type":"Point"}
}