{
  "type": "Feature",
  "properties": {
    "addr:full":"601 9th St Brandon MB R7A 4B3",
    "addr:housenumber":"601",
    "addr:postcode":"r7a 4b3",
    "addr:street":"9Th St",
    "iso:country":"CA",
    "sg:address":"601 9th St",
    "sg:city":"Brandon",
    "sg:classifiers":[
        {
            "category":"Retail",
            "subcategory":"Auto Repair",
            "type":"Services"
        }
    ],
    "sg:phone":"+1 204 727 0020",
    "sg:postcode":"R7A 4B3",
    "sg:province":"MB",
    "sg:tags":[
        "repairing",
        "automobile",
        "muffler",
        "system",
        "exhaust"
    ],
    "wof:name":"Minute Muffler & Brake",
    "wof:placetype":"venue"
},
  "geometry": {"coordinates":[-99.94986,49.840473],"type":"Point"}
}