{
  "type": "Feature",
  "properties": {
    "iso:country":"CA",
    "sg:address":"2856 Princess St RR 3",
    "sg:city":"Kingston",
    "sg:classifiers":[
        {
            "category":"Retail",
            "subcategory":"Auto Repair",
            "type":"Services"
        }
    ],
    "sg:phone":"+1 613 389 5981",
    "sg:postcode":"K7L 4V2",
    "sg:province":"ON",
    "sg:tags":[
        "repairing",
        "automobile"
    ],
    "wof:name":"George's Automotive Svc",
    "wof:placetype":"venue"
},
  "geometry": {"coordinates":[-76.586678,44.2603],"type":"Point"}
}