{
  "type": "Feature",
  "properties": {
    "addr:full":"2856 Princess St RR 3 Kingston ON K7L 4V2",
    "addr:housenumber":"2856",
    "addr:postcode":"k7l 4v2",
    "addr:street":"Princess St Rr 3",
    "iso:country":"CA",
    "sg:address":"2856 Princess St RR 3",
    "sg:city":"Kingston",
    "sg:classifiers":[
        {
            "category":"Retail",
            "subcategory":"Auto Repair",
            "type":"Services"
        }
    ],
    "sg:phone":"+1 613 389 5981",
    "sg:postcode":"K7L 4V2",
    "sg:province":"ON",
    "sg:tags":[
        "repairing",
        "automobile"
    ],
    "wof:name":"George's Automotive Svc",
    "wof:placetype":"venue"
},
  "geometry": {"coordinates":[-76.58667800000001,44.2603],"type":"Point"}
}