{
  "type": "Feature",
  "properties": {
    "addr:full":"315 Rue Vachon Cap-DE-LA-Madeleine QC G8T 8P6",
    "addr:housenumber":"315",
    "addr:postcode":"g8t 8p6",
    "addr:street":"Rue Vachon",
    "iso:country":"CA",
    "sg:address":"315 Rue Vachon",
    "sg:city":"Cap-DE-LA-Madeleine",
    "sg:classifiers":[
        {
            "category":"Professional",
            "subcategory":"Research",
            "type":"Services"
        }
    ],
    "sg:phone":"+1 819 371 1949",
    "sg:postcode":"G8T 8P6",
    "sg:province":"QC",
    "sg:tags":[
        "environmental",
        "ecological"
    ],
    "wof:name":"Biolab",
    "wof:placetype":"venue"
},
  "geometry": {"coordinates":[-72.552032,46.37352],"type":"Point"}
}