{
  "type": "Feature",
  "properties": {
    "addr:full":"12214 128 St NW Edmonton AB T5L 1C5",
    "addr:housenumber":"12214",
    "addr:postcode":"t5l 1c5",
    "addr:street":"128 St Nw",
    "iso:country":"CA",
    "sg:address":"12214 128 St NW",
    "sg:city":"Edmonton",
    "sg:classifiers":[
        {
            "category":"Social Services",
            "subcategory":"Child Care",
            "type":"Services"
        }
    ],
    "sg:phone":"+1 780 452 0587",
    "sg:postcode":"T5L 1C5",
    "sg:province":"AB",
    "wof:name":"First Choice Daycare",
    "wof:placetype":"venue"
},
  "geometry": {"coordinates":[-113.543091,53.577019],"type":"Point"}
}