{
  "type": "Feature",
  "properties": {
    "addr:full":"Montreal QC H2N 2J3",
    "addr:postcode":"h2n 2j3",
    "iso:country":"CA",
    "sg:city":"Montreal",
    "sg:classifiers":[
        {
            "category":"Wholesale",
            "subcategory":"Durable Goods & Equipment",
            "type":"Manufacturing & Wholesale Goods"
        }
    ],
    "sg:phone":"+1 514 387 7520",
    "sg:postcode":"H2N 2J3",
    "sg:province":"QC",
    "sg:tags":[
        "importer"
    ],
    "wof:name":"Cinquieme Republique",
    "wof:placetype":"venue"
},
  "geometry": {"coordinates":[-73.648865,45.548431],"type":"Point"}
}