{
  "type": "Feature",
  "properties": {
    "addr:full":"4912 Cordova Bay Rd Victoria BC V8Y 2J5",
    "addr:housenumber":"4912",
    "addr:postcode":"v8y 2j5",
    "addr:street":"Cordova Bay Rd",
    "iso:country":"CA",
    "sg:address":"4912 Cordova Bay Rd",
    "sg:city":"Victoria",
    "sg:classifiers":[
        {
            "category":"Banks & Credit Unions",
            "subcategory":"Investment Brokerage",
            "type":"Services"
        }
    ],
    "sg:phone":"+1 250 658 3892",
    "sg:postcode":"V8Y 2J5",
    "sg:province":"BC",
    "sg:tags":[
        "consultant",
        "planning",
        "financial"
    ],
    "wof:name":"Mc Dougall Financial Svc",
    "wof:placetype":"venue"
},
  "geometry": {"coordinates":[-123.364517212,48.428314209],"type":"Point"}
}