{
  "type": "Feature",
  "properties": {
    "addr:full":"117 Pth 20 N Camperville MB R0L 0J0",
    "addr:housenumber":"117",
    "addr:postcode":"r0l 0j0",
    "addr:street":"Pth 20 N",
    "iso:country":"CA",
    "sg:address":"117 Pth 20 N",
    "sg:city":"Camperville",
    "sg:classifiers":[
        {
            "category":"Autos & Motor Vehicles",
            "subcategory":"Fuel & Gas Station",
            "type":"Retail Goods"
        }
    ],
    "sg:phone":"+1 204 524 2464",
    "sg:postcode":"R0L 0J0",
    "sg:province":"MB",
    "sg:tags":[
        "oil"
    ],
    "wof:name":"Stan's Gas Bar",
    "wof:placetype":"venue"
},
  "geometry": {"coordinates":[-100.145203,51.98592],"type":"Point"}
}