{
  "type": "Feature",
  "properties": {
    "addr:full":"Edmonton AB T5N 1N7",
    "addr:postcode":"t5n 1n7",
    "iso:country":"CA",
    "sg:city":"Edmonton",
    "sg:classifiers":[
        {
            "category":"Professional",
            "subcategory":"Accounting & Tax Preparation",
            "type":"Services"
        }
    ],
    "sg:phone":"+1 780 448 0121",
    "sg:postcode":"T5N 1N7",
    "sg:province":"AB",
    "sg:tags":[
        "accountant"
    ],
    "wof:name":"Mormyluk Accounting Ltd",
    "wof:placetype":"venue"
},
  "geometry": {"coordinates":[-113.53434,53.546955],"type":"Point"}
}