{
  "type": "Feature",
  "properties": {
    "addr:full":"Fort St John BC V1J 6M7",
    "addr:postcode":"v1j 6m7",
    "iso:country":"CA",
    "sg:city":"Fort St John",
    "sg:classifiers":[
        {
            "category":"Government",
            "subcategory":"Office",
            "type":"Public Place"
        }
    ],
    "sg:phone":"+1 250 787 3412",
    "sg:postcode":"V1J 6M7",
    "sg:province":"BC",
    "wof:name":"British Columbia Crown Land",
    "wof:placetype":"venue"
},
  "geometry": {"coordinates":[-120.847862244,56.255115509],"type":"Point"}
}