{
  "type": "Feature",
  "properties": {
    "iso:country":"CA",
    "sg:city":"Brossard",
    "sg:classifiers":[
        {
            "category":"Insurance",
            "subcategory":"Insurance Agent",
            "type":"Services"
        }
    ],
    "sg:phone":"+1 450 672 1758",
    "sg:postcode":"J4W 2Z7",
    "sg:province":"QC",
    "wof:name":"Services Financiers Sfl",
    "wof:placetype":"venue"
},
  "geometry": {"coordinates":[-73.4748840332,45.4736289978],"type":"Point"}
}