{
  "type": "Feature",
  "properties": {
    "addr:full":"3128 Angus St Regina SK S4S 1P4",
    "addr:housenumber":"3128",
    "addr:postcode":"s4s 1p4",
    "addr:street":"Angus St",
    "iso:country":"CA",
    "sg:address":"3128 Angus St",
    "sg:city":"Regina",
    "sg:classifiers":[
        {
            "category":"Wholesale",
            "subcategory":"Electrical",
            "type":"Manufacturing & Wholesale Goods"
        }
    ],
    "sg:phone":"+1 306 584 0220",
    "sg:postcode":"S4S 1P4",
    "sg:province":"SK",
    "sg:tags":[
        "alarm",
        "burglar",
        "system"
    ],
    "wof:name":"Alarmforce Saskatchewan Inc",
    "wof:placetype":"venue"
},
  "geometry": {"coordinates":[-104.619766,50.429485],"type":"Point"}
}