{
  "type": "Feature",
  "properties": {
    "addr:full":"1766 Wilton Grove Rd London ON N6N 1M8",
    "addr:housenumber":"1766",
    "addr:postcode":"n6n 1m8",
    "addr:street":"Wilton Grove Rd",
    "iso:country":"CA",
    "sg:address":"1766 Wilton Grove Rd",
    "sg:city":"London",
    "sg:classifiers":[
        {
            "category":"Retail",
            "subcategory":"Animal Services",
            "type":"Services"
        }
    ],
    "sg:phone":"+1 519 644 1771",
    "sg:postcode":"N6N 1M8",
    "sg:province":"ON",
    "sg:tags":[
        "pet",
        "boarding",
        "grooming",
        "washing",
        "sitting"
    ],
    "wof:name":"Country Paws Boarding",
    "wof:placetype":"venue"
},
  "geometry": {"coordinates":[-81.153419,42.931763],"type":"Point"}
}