{
  "type": "Feature",
  "properties": {
    "addr:full":"2188 Rue Melisande Laval QC H7A 3W1",
    "addr:housenumber":"2188",
    "addr:postcode":"h7a 3w1",
    "addr:street":"Rue Melisande",
    "iso:country":"CA",
    "sg:address":"2188 Rue Melisande",
    "sg:city":"Laval",
    "sg:classifiers":[
        {
            "category":"Wholesale",
            "subcategory":"Non-durable Goods",
            "type":"Manufacturing & Wholesale Goods"
        }
    ],
    "sg:phone":"+1 450 665 1569",
    "sg:postcode":"H7A 3W1",
    "sg:province":"QC",
    "sg:tags":[
        "interior"
    ],
    "wof:name":"Draperies Marcelle Enr",
    "wof:placetype":"venue"
},
  "geometry": {"coordinates":[-73.58814239500001,45.6750907898],"type":"Point"}
}