{
  "type": "Feature",
  "properties": {
    "addr:full":"Winnipeg MB R2C 4J2",
    "addr:postcode":"r2c 4j2",
    "iso:country":"CA",
    "sg:city":"Winnipeg",
    "sg:classifiers":[
        {
            "category":"Shopping",
            "subcategory":"Gifts & Souvenirs",
            "type":"Retail Goods"
        }
    ],
    "sg:phone":"+1 204 661 9365",
    "sg:postcode":"R2C 4J2",
    "sg:province":"MB",
    "sg:tags":[
        "shop"
    ],
    "wof:name":"Spencer Gifts Canada Inc",
    "wof:placetype":"venue"
},
  "geometry": {"coordinates":[-97.0619888306,49.8973731995],"type":"Point"}
}