{
  "type": "Feature",
  "properties": {
    "addr:full":"747 Appleby Line Burlington ON L7L 2Y6",
    "addr:housenumber":"747",
    "addr:postcode":"l7l 2y6",
    "addr:street":"Appleby Line",
    "iso:country":"CA",
    "sg:address":"747 Appleby Line",
    "sg:city":"Burlington",
    "sg:classifiers":[
        {
            "category":"Manufacturing",
            "subcategory":"Paper Products",
            "type":"Manufacturing & Wholesale Goods"
        }
    ],
    "sg:phone":"+1 905 634 5525",
    "sg:postcode":"L7L 2Y6",
    "sg:province":"ON",
    "sg:tags":[
        "corrugated",
        "solid",
        "fiber",
        "box"
    ],
    "wof:name":"Smurfit Mbi",
    "wof:placetype":"venue"
},
  "geometry": {"coordinates":[-79.763397,43.374676],"type":"Point"}
}