{
  "type": "Feature",
  "properties": {
    "addr:full":"6697 Bank St Verona ON K0H 2W0",
    "addr:housenumber":"6697",
    "addr:postcode":"k0h 2w0",
    "addr:street":"Bank St",
    "iso:country":"CA",
    "sg:address":"6697 Bank St",
    "sg:city":"Verona",
    "sg:classifiers":[
        {
            "category":"Real Estate",
            "subcategory":"Real Estate Agent",
            "type":"Services"
        }
    ],
    "sg:phone":"+1 613 374 2222",
    "sg:postcode":"K0H 2W0",
    "sg:province":"ON",
    "wof:name":"Royal Le Page Gale Real Estate",
    "wof:placetype":"venue"
},
  "geometry": {"coordinates":[-76.696472168,44.4861297607],"type":"Point"}
}