{
  "type": "Feature",
  "properties": {
    "addr:full":"Delta BC V4C 2K4",
    "addr:postcode":"v4c 2k4",
    "iso:country":"CA",
    "sg:city":"Delta",
    "sg:classifiers":[
        {
            "category":"Restaurant",
            "type":"Food & Drink"
        }
    ],
    "sg:phone":"+1 604 594 5511",
    "sg:postcode":"V4C 2K4",
    "sg:province":"BC",
    "wof:name":"Apollo Pizza Ltd",
    "wof:placetype":"venue"
},
  "geometry": {"coordinates":[-122.91368900000001,49.156212],"type":"Point"}
}