{
  "type": "Feature",
  "properties": {
    "addr:full":"63 5th St Englehart ON P0J 1H0",
    "addr:housenumber":"63",
    "addr:postcode":"p0j 1h0",
    "addr:street":"5Th St",
    "iso:country":"CA",
    "sg:address":"63 5th St",
    "sg:city":"Englehart",
    "sg:classifiers":[
        {
            "category":"Shopping",
            "subcategory":"Pharmacy",
            "type":"Retail Goods"
        }
    ],
    "sg:phone":"+1 705 544 8054",
    "sg:postcode":"P0J 1H0",
    "sg:province":"ON",
    "wof:name":"Pharmx Rexall Drug Store",
    "wof:placetype":"venue"
},
  "geometry": {"coordinates":[-79.87869999999999,47.825352],"type":"Point"}
}