{
  "type": "Feature",
  "properties": {
    "addr:full":"Mayo YT Y0B 1M0",
    "addr:postcode":"y0b 1m0",
    "iso:country":"CA",
    "sg:city":"Mayo",
    "sg:classifiers":[
        {
            "category":"Education",
            "subcategory":"School",
            "type":"Public Place"
        }
    ],
    "sg:phone":"+1 867 996 2275",
    "sg:postcode":"Y0B 1M0",
    "sg:province":"YT",
    "wof:name":"J V Clark School",
    "wof:placetype":"venue"
},
  "geometry": {"coordinates":[-135.93185424800001,63.6166038513],"type":"Point"}
}