{
  "type": "Feature",
  "properties": {
    "addr:full":"Winnipeg MB R3C 0S6",
    "addr:postcode":"r3c 0s6",
    "iso:country":"CA",
    "sg:city":"Winnipeg",
    "sg:classifiers":[
        {
            "category":"Banks & Credit Unions",
            "subcategory":"Financial Services",
            "type":"Services"
        }
    ],
    "sg:phone":"+1 204 925 6400",
    "sg:postcode":"R3C 0S6",
    "sg:province":"MB",
    "sg:tags":[
        "bankruptcy",
        "trustee"
    ],
    "wof:name":"L C Taylor & CO Trustee",
    "wof:placetype":"venue"
},
  "geometry": {"coordinates":[-97.1402587891,49.8874435425],"type":"Point"}
}