{
  "type": "Feature",
  "properties": {
    "addr:full":"400 Boul Saint-Martin O # 405A Laval QC H7M 3Y8",
    "addr:housenumber":"400",
    "addr:postcode":"h7m 3y8",
    "addr:street":"Boul Saint-Martin O # 405A",
    "iso:country":"CA",
    "sg:address":"400 Boul Saint-Martin O # 405A",
    "sg:city":"Laval",
    "sg:classifiers":[
        {
            "category":"Health Services",
            "subcategory":"Doctor",
            "type":"Services"
        }
    ],
    "sg:phone":"+1 450 669 3100",
    "sg:postcode":"H7M 3Y8",
    "sg:province":"QC",
    "sg:tags":[
        "dentist"
    ],
    "wof:name":"Centre Dentaire Dr Vu",
    "wof:placetype":"venue"
},
  "geometry": {"coordinates":[-73.7105789185,45.5777435303],"type":"Point"}
}