{
  "type": "Feature",
  "properties": {
    "iso:country":"CA",
    "sg:address":"1338 Clarkson Rd",
    "sg:city":"Mississauga",
    "sg:classifiers":[
        {
            "category":"Education",
            "subcategory":"School",
            "type":"Public Place"
        }
    ],
    "sg:phone":"+1 905 855 2321",
    "sg:postcode":"L5J 2W5",
    "sg:province":"ON",
    "wof:name":"White Oaks Montessori School",
    "wof:placetype":"venue"
},
  "geometry": {"coordinates":[-79.6332244873,43.5239982605],"type":"Point"}
}