{
  "type": "Feature",
  "properties": {
    "addr:full":"2001 Sherwood Dr Sherwood Park AB T8A 3J4",
    "addr:housenumber":"2001",
    "addr:postcode":"t8a 3j4",
    "addr:street":"Sherwood Dr",
    "iso:country":"CA",
    "sg:address":"2001 Sherwood Dr",
    "sg:city":"Sherwood Park",
    "sg:classifiers":[
        {
            "category":"Government",
            "subcategory":"Office",
            "type":"Public Place"
        }
    ],
    "sg:phone":"+1 780 464 8245",
    "sg:postcode":"T8A 3J4",
    "sg:province":"AB",
    "sg:tags":[
        "party",
        "planning"
    ],
    "wof:name":"Strathcona County Recreation",
    "wof:placetype":"venue"
},
  "geometry": {"coordinates":[-113.29637146,53.5253715515],"type":"Point"}
}