{
  "type": "Feature",
  "properties": {
    "iso:country":"CA",
    "sg:address":"850 Waverley St",
    "sg:city":"Winnipeg",
    "sg:classifiers":[
        {
            "category":"Retail",
            "subcategory":"Car Wash",
            "type":"Services"
        }
    ],
    "sg:phone":"+1 204 775 9700",
    "sg:postcode":"R3T 5Z7",
    "sg:province":"MB",
    "sg:tags":[
        "polishing",
        "washing"
    ],
    "wof:name":"Chamois the Full Svc Car Wash",
    "wof:placetype":"venue"
},
  "geometry": {"coordinates":[-97.1790313721,49.8475532532],"type":"Point"}
}