{
  "type": "Feature",
  "properties": {
    "addr:full":"78 Chancery Pt Sherwood Park AB T8H 1Z4",
    "addr:housenumber":"78",
    "addr:postcode":"t8h 1z4",
    "addr:street":"Chancery Pt",
    "iso:country":"CA",
    "sg:address":"78 Chancery Pt",
    "sg:city":"Sherwood Park",
    "sg:classifiers":[
        {
            "category":"Building & Trades",
            "subcategory":"Construction",
            "type":"Services"
        }
    ],
    "sg:phone":"+1 780 913 0013",
    "sg:postcode":"T8H 1Z4",
    "sg:province":"AB",
    "sg:tags":[
        "home",
        "builder",
        "railing"
    ],
    "wof:name":"Tri-Gem Developments Ltd",
    "wof:placetype":"venue"
},
  "geometry": {"coordinates":[-113.293564,53.549194],"type":"Point"}
}