{
  "type": "Feature",
  "properties": {
    "addr:full":"1 Av Cartier Pointe-Claire QC H9S 4R3",
    "addr:postcode":"h9s 4r3",
    "addr:street":"Av Cartier",
    "iso:country":"CA",
    "sg:address":"1 Av Cartier",
    "sg:city":"Pointe-Claire",
    "sg:classifiers":[
        {
            "category":"Recreation",
            "type":"Entertainment"
        }
    ],
    "sg:phone":"+1 514 695 2441",
    "sg:postcode":"H9S 4R3",
    "sg:province":"QC",
    "sg:tags":[
        "boating",
        "instruction"
    ],
    "wof:name":"Pointe Claire Yacht Club",
    "wof:placetype":"venue"
},
  "geometry": {"coordinates":[-73.821091,45.428001],"type":"Point"}
}