{
  "type": "Feature",
  "properties": {
    "iso:country":"CA",
    "sg:address":"185 Rue Des Censitaires",
    "sg:city":"Varennes",
    "sg:classifiers":[
        {
            "category":"Wholesale",
            "subcategory":"Metals & Minerals",
            "type":"Manufacturing & Wholesale Goods"
        }
    ],
    "sg:phone":"+1 450 929 1222",
    "sg:postcode":"J3X 2C4",
    "sg:province":"QC",
    "sg:tags":[
        "building",
        "material",
        "specialty"
    ],
    "wof:name":"Systemes Metalliques Dewar",
    "wof:placetype":"venue"
},
  "geometry": {"coordinates":[-73.42918396,45.6607437134],"type":"Point"}
}