{
  "type": "Feature",
  "properties": {
    "iso:country":"CA",
    "sg:city":"Red Deer",
    "sg:classifiers":[
        {
            "category":"Health Services",
            "subcategory":"Doctor",
            "type":"Services"
        }
    ],
    "sg:phone":"+1 403 342 6615",
    "sg:postcode":"T4N 6V7",
    "sg:province":"AB",
    "sg:tags":[
        "physician",
        "surgeon"
    ],
    "wof:name":"Hjertaas, Richard MD",
    "wof:placetype":"venue"
},
  "geometry": {"coordinates":[-113.816383362,52.260559082],"type":"Point"}
}