{
  "type": "Feature",
  "properties": {
    "addr:full":"5104 51 St Berwyn AB T0H 0E0",
    "addr:housenumber":"5104",
    "addr:postcode":"t0h 0e0",
    "addr:street":"51 St",
    "iso:country":"CA",
    "sg:address":"5104 51 St",
    "sg:city":"Berwyn",
    "sg:classifiers":[
        {
            "category":"Home & Garden",
            "subcategory":"Hardware",
            "type":"Retail Goods"
        }
    ],
    "sg:phone":"+1 780 338 3768",
    "sg:postcode":"T0H 0E0",
    "sg:province":"AB",
    "wof:name":"Kinley's of Berwyn Hardware",
    "wof:placetype":"venue"
},
  "geometry": {"coordinates":[-117.736488342,56.1464233398],"type":"Point"}
}