{
  "type": "Feature",
  "properties": {
    "addr:full":"292 Trafalgar Rd Pembroke ON K8A 5A8",
    "addr:housenumber":"292",
    "addr:postcode":"k8a 5a8",
    "addr:street":"Trafalgar Rd",
    "iso:country":"CA",
    "sg:address":"292 Trafalgar Rd",
    "sg:city":"Pembroke",
    "sg:classifiers":[
        {
            "category":"Home & Garden",
            "subcategory":"Carpets & Floor Coverings",
            "type":"Retail Goods"
        }
    ],
    "sg:phone":"+1 613 735 8190",
    "sg:postcode":"K8A 5A8",
    "sg:province":"ON",
    "sg:tags":[
        "material",
        "dealer",
        "rug"
    ],
    "wof:name":"Michael St Jean Flooring Svc",
    "wof:placetype":"venue"
},
  "geometry": {"coordinates":[-77.13061500000001,45.823463],"type":"Point"}
}