{
  "type": "Feature",
  "properties": {
    "addr:full":"7 Rue Valliere Quebec QC G1K 6S9",
    "addr:housenumber":"7",
    "addr:postcode":"g1k 6s9",
    "addr:street":"Rue Valliere",
    "iso:country":"CA",
    "sg:address":"7 Rue Valliere",
    "sg:city":"Quebec",
    "sg:classifiers":[
        {
            "category":"Organizations",
            "subcategory":"Labor Organization",
            "type":"Services"
        }
    ],
    "sg:phone":"+1 418 692 0022",
    "sg:postcode":"G1K 6S9",
    "sg:province":"QC",
    "wof:name":"Spgq",
    "wof:placetype":"venue"
},
  "geometry": {"coordinates":[-71.214935,46.815514],"type":"Point"}
}