{
  "type": "Feature",
  "properties": {
    "addr:full":"1101 Boundary Rd # 1 Oshawa ON L1J 8P8",
    "addr:housenumber":"1101",
    "addr:postcode":"l1j 8p8",
    "addr:street":"Boundary Rd # 1",
    "iso:country":"CA",
    "sg:address":"1101 Boundary Rd # 1",
    "sg:city":"Oshawa",
    "sg:classifiers":[
        {
            "category":"Real Estate",
            "subcategory":"Surveying",
            "type":"Services"
        }
    ],
    "sg:phone":"+1 905 725 4795",
    "sg:postcode":"L1J 8P8",
    "sg:province":"ON",
    "sg:tags":[
        "surveyor"
    ],
    "wof:name":"Donevan Fleischmann Petrich",
    "wof:placetype":"venue"
},
  "geometry": {"coordinates":[-78.885338,43.861366],"type":"Point"}
}