{
  "type": "Feature",
  "properties": {
    "iso:country":"CA",
    "sg:address":"18 Front St E",
    "sg:city":"Strathroy",
    "sg:classifiers":[
        {
            "category":"Professional",
            "subcategory":"Lawyer & Legal Services",
            "type":"Services"
        }
    ],
    "sg:phone":"+1 519 245 0342",
    "sg:postcode":"N7G 1Y4",
    "sg:province":"ON",
    "sg:tags":[
        "attorney"
    ],
    "wof:name":"Quinlan & Somerville",
    "wof:placetype":"venue"
},
  "geometry": {"coordinates":[-81.62329864500001,42.9588356018],"type":"Point"}
}