{
  "type": "Feature",
  "properties": {
    "addr:full":"3670 Rue Chenier Mirabel QC J7N 2N1",
    "addr:housenumber":"3670",
    "addr:postcode":"j7n 2n1",
    "addr:street":"Rue Chenier",
    "iso:country":"CA",
    "sg:address":"3670 Rue Chenier",
    "sg:city":"Mirabel",
    "sg:classifiers":[
        {
            "category":"Wholesale",
            "subcategory":"Farm Supplies",
            "type":"Manufacturing & Wholesale Goods"
        }
    ],
    "sg:phone":"+1 450 432 9747",
    "sg:postcode":"J7N 2N1",
    "sg:province":"QC",
    "sg:tags":[
        "fertilizer",
        "cooperative"
    ],
    "wof:name":"Cooperative Agricole Profid'Or",
    "wof:placetype":"venue"
},
  "geometry": {"coordinates":[-74.091843,45.565292],"type":"Point"}
}