{
  "type": "Feature",
  "properties": {
    "addr:full":"Montreal QC H2W 1Z5",
    "addr:postcode":"h2w 1z5",
    "iso:country":"CA",
    "sg:city":"Montreal",
    "sg:classifiers":[
        {
            "category":"Wholesale",
            "subcategory":"Furniture",
            "type":"Manufacturing & Wholesale Goods"
        }
    ],
    "sg:phone":"+1 514 287 9038",
    "sg:postcode":"H2W 1Z5",
    "sg:province":"QC",
    "wof:name":"Dismo International",
    "wof:placetype":"venue"
},
  "geometry": {"coordinates":[-73.5851135254,45.5193939209],"type":"Point"}
}