{
  "type": "Feature",
  "properties": {
    "addr:full":"2170 Boul Lapiniere Brossard QC J4W 1M2",
    "addr:housenumber":"2170",
    "addr:postcode":"j4w 1m2",
    "addr:street":"Boul Lapiniere",
    "iso:country":"CA",
    "sg:address":"2170 Boul Lapiniere",
    "sg:city":"Brossard",
    "sg:classifiers":[
        {
            "category":"Professional",
            "subcategory":"Accounting & Tax Preparation",
            "type":"Services"
        }
    ],
    "sg:phone":"+1 450 676 0666",
    "sg:postcode":"J4W 1M2",
    "sg:province":"QC",
    "sg:tags":[
        "accountant"
    ],
    "wof:name":"Brassard & Assoc",
    "wof:placetype":"venue"
},
  "geometry": {"coordinates":[-73.4709701538,45.4743652344],"type":"Point"}
}