{
  "type": "Feature",
  "properties": {
    "addr:full":"2707 Mill Woods Rd NW Edmonton AB T6K 4A6",
    "addr:housenumber":"2707",
    "addr:postcode":"t6k 4a6",
    "addr:street":"Mill Woods Rd Nw",
    "iso:country":"CA",
    "sg:address":"2707 Mill Woods Rd NW",
    "sg:city":"Edmonton",
    "sg:classifiers":[
        {
            "category":"Education",
            "subcategory":"School",
            "type":"Public Place"
        }
    ],
    "sg:phone":"+1 780 462 3322",
    "sg:postcode":"T6K 4A6",
    "sg:province":"AB",
    "wof:name":"J Percy Page Composite High",
    "wof:placetype":"venue"
},
  "geometry": {"coordinates":[-113.447838,53.457764],"type":"Point"}
}