{
  "type": "Feature",
  "properties": {
    "addr:full":"440 Rue Sainte-Helene Longueuil QC J4K 3R2",
    "addr:housenumber":"440",
    "addr:postcode":"j4k 3r2",
    "addr:street":"Rue Sainte-Helene",
    "iso:country":"CA",
    "sg:address":"440 Rue Sainte-Helene",
    "sg:city":"Longueuil",
    "sg:classifiers":[
        {
            "category":"Autos & Motor Vehicles",
            "subcategory":"Auto Supplies",
            "type":"Retail Goods"
        }
    ],
    "sg:phone":"+1 514 861 2761",
    "sg:postcode":"J4K 3R2",
    "sg:province":"QC",
    "sg:tags":[
        "automobile",
        "alarm"
    ],
    "wof:name":"Sherlock Marquage Antivol Inc",
    "wof:placetype":"venue"
},
  "geometry": {"coordinates":[-73.51252746580001,45.5220527649],"type":"Point"}
}