{
  "type": "Feature",
  "properties": {
    "addr:full":"65 Woolwich St S Breslau ON N0B 1M0",
    "addr:housenumber":"65",
    "addr:postcode":"n0b 1m0",
    "addr:street":"Woolwich St S",
    "iso:country":"CA",
    "sg:address":"65 Woolwich St S",
    "sg:city":"Breslau",
    "sg:classifiers":[
        {
            "category":"Shopping",
            "subcategory":"Jewelry",
            "type":"Retail Goods"
        }
    ],
    "sg:phone":"+1 519 648 3062",
    "sg:postcode":"N0B 1M0",
    "sg:province":"ON",
    "sg:tags":[
        "photographer"
    ],
    "wof:name":"Jackalyn's Photography",
    "wof:placetype":"venue"
},
  "geometry": {"coordinates":[-80.4150543213,43.4797668457],"type":"Point"}
}