{
  "type": "Feature",
  "properties": {
    "addr:full":"9330 Boul Du Centre-Hospitalie Charny QC G6X 1L6",
    "addr:housenumber":"9330",
    "addr:postcode":"g6x 1l6",
    "addr:street":"Boul Du Centre-Hospitalie",
    "iso:country":"CA",
    "sg:address":"9330 Boul Du Centre-Hospitalie",
    "sg:city":"Charny",
    "sg:classifiers":[
        {
            "category":"Health Services",
            "subcategory":"Hospital",
            "type":"Services"
        }
    ],
    "sg:phone":"+1 418 380 8993",
    "sg:postcode":"G6X 1L6",
    "sg:province":"QC",
    "wof:name":"Centre DE Sante Paul-Gilbert",
    "wof:placetype":"venue"
},
  "geometry": {"coordinates":[-71.258072,46.724541],"type":"Point"}
}