{
  "type": "Feature",
  "properties": {
    "addr:full":"59 First Ave S Williams Lake BC V2G 1H4",
    "addr:housenumber":"59",
    "addr:postcode":"v2g 1h4",
    "addr:street":"First Ave S Williams",
    "iso:country":"CA",
    "sg:address":"59 First Ave S",
    "sg:city":"Williams Lake",
    "sg:classifiers":[
        {
            "category":"Building & Trades",
            "subcategory":"Construction",
            "type":"Services"
        }
    ],
    "sg:phone":"+1 250 398 7535",
    "sg:postcode":"V2G 1H4",
    "sg:province":"BC",
    "sg:tags":[
        "contractor"
    ],
    "wof:name":"Dene Development Corp",
    "wof:placetype":"venue"
},
  "geometry": {"coordinates":[-122.14572099999999,52.127815],"type":"Point"}
}