{
  "type": "Feature",
  "properties": {
    "addr:full":"513 Rundleville Pl NE Calgary AB T1Y 2T5",
    "addr:housenumber":"513",
    "addr:postcode":"t1y 2t5",
    "addr:street":"Rundleville Pl Ne",
    "iso:country":"CA",
    "sg:address":"513 Rundleville Pl NE",
    "sg:city":"Calgary",
    "sg:classifiers":[
        {
            "category":"Building & Trades",
            "subcategory":"Construction",
            "type":"Services"
        }
    ],
    "sg:phone":"+1 403 280 6122",
    "sg:postcode":"T1Y 2T5",
    "sg:province":"AB",
    "sg:tags":[
        "ceiling",
        "painter"
    ],
    "wof:name":"P & D Painting & Decorating",
    "wof:placetype":"venue"
},
  "geometry": {"coordinates":[-113.973099,51.073837],"type":"Point"}
}