{
  "type": "Feature",
  "properties": {
    "addr:full":"1436 Prairie Ave Port Coquitlam BC V3B 5M8",
    "addr:housenumber":"1436",
    "addr:postcode":"v3b 5m8",
    "addr:street":"Prairie Ave",
    "iso:country":"CA",
    "sg:address":"1436 Prairie Ave",
    "sg:city":"Port Coquitlam",
    "sg:classifiers":[
        {
            "category":"Food & Beverages",
            "subcategory":"Liquor & Beverages",
            "type":"Retail Goods"
        }
    ],
    "sg:phone":"+1 604 941 3111",
    "sg:postcode":"V3B 5M8",
    "sg:province":"BC",
    "sg:tags":[
        "store"
    ],
    "wof:name":"Liquor Stores-Government",
    "wof:placetype":"venue"
},
  "geometry": {"coordinates":[-122.75395202599999,49.2710609436],"type":"Point"}
}