{
  "type": "Feature",
  "properties": {
    "addr:full":"236 Main St Antigonish NS B2G 2C2",
    "addr:housenumber":"236",
    "addr:postcode":"b2g 2c2",
    "addr:street":"Main St",
    "iso:country":"CA",
    "sg:address":"236 Main St",
    "sg:city":"Antigonish",
    "sg:classifiers":[
        {
            "category":"Banks & Credit Unions",
            "subcategory":"Bank",
            "type":"Services"
        }
    ],
    "sg:phone":"+1 902 863 4411",
    "sg:postcode":"B2G 2C2",
    "sg:province":"NS",
    "wof:name":"Royal Bank Financial Group",
    "wof:placetype":"venue"
},
  "geometry": {"coordinates":[-61.990215,45.622631],"type":"Point"}
}