{
  "type": "Feature",
  "properties": {
    "addr:full":"580 Powell St Vancouver BC V6A 1G9",
    "addr:housenumber":"580",
    "addr:postcode":"v6a 1g9",
    "addr:street":"Powell St",
    "iso:country":"CA",
    "sg:address":"580 Powell St",
    "sg:city":"Vancouver",
    "sg:classifiers":[
        {
            "category":"Restaurant",
            "type":"Food & Drink"
        }
    ],
    "sg:phone":"+1 604 251 5570",
    "sg:postcode":"V6A 1G9",
    "sg:province":"BC",
    "sg:tags":[
        "shop",
        "coffee"
    ],
    "wof:name":"Eastside Coffee Bar",
    "wof:placetype":"venue"
},
  "geometry": {"coordinates":[-123.091812,49.282944],"type":"Point"}
}