{
  "type": "Feature",
  "properties": {
    "addr:full":"Cambridge ON N1R 8G6",
    "addr:postcode":"n1r 8g6",
    "iso:country":"CA",
    "sg:city":"Cambridge",
    "sg:classifiers":[
        {
            "category":"Autos & Motor Vehicles",
            "subcategory":"Motorcycle Sales",
            "type":"Retail Goods"
        }
    ],
    "sg:phone":"+1 519 740 1993",
    "sg:postcode":"N1R 8G6",
    "sg:province":"ON",
    "sg:tags":[
        "scooter"
    ],
    "wof:name":"Cambridge Custom Cycle",
    "wof:placetype":"venue"
},
  "geometry": {"coordinates":[-80.29220599999999,43.365444],"type":"Point"}
}