{
  "type": "Feature",
  "properties": {
    "addr:full":"1140 8 St SE Calgary AB T2G 2Z7",
    "addr:housenumber":"1140 8",
    "addr:postcode":"t2g 2z7",
    "addr:street":"St Se",
    "iso:country":"CA",
    "sg:address":"1140 8 St SE",
    "sg:city":"Calgary",
    "sg:classifiers":[
        {
            "category":"Organizations",
            "subcategory":"Professional Association",
            "type":"Services"
        }
    ],
    "sg:phone":"+1 403 263 2277",
    "sg:postcode":"T2G 2Z7",
    "sg:province":"AB",
    "wof:name":"Ramsay Welcome Ctr Assn",
    "wof:placetype":"venue"
},
  "geometry": {"coordinates":[-114.041382,51.03915],"type":"Point"}
}