{
  "type": "Feature",
  "properties": {
    "iso:country":"CA",
    "sg:address":"3035 Tutor Dr",
    "sg:city":"Regina",
    "sg:classifiers":[
        {
            "category":"Building & Trades",
            "subcategory":"Equipment Rental",
            "type":"Services"
        }
    ],
    "sg:phone":"+1 306 359 0957",
    "sg:postcode":"S4W 1B5",
    "sg:province":"SK",
    "sg:tags":[
        "aircraft",
        "leasing",
        "charter"
    ],
    "wof:name":"Westwind Aviation Inc",
    "wof:placetype":"venue"
},
  "geometry": {"coordinates":[-104.6512146,50.433719635],"type":"Point"}
}