{
  "type": "Feature",
  "properties": {
    "addr:full":"LA Macaza QC J0T 1R0",
    "addr:postcode":"j0t 1r0",
    "iso:country":"CA",
    "sg:city":"LA Macaza",
    "sg:classifiers":[
        {
            "category":"Professional",
            "subcategory":"Art Services",
            "type":"Services"
        }
    ],
    "sg:phone":"+1 819 275 2445",
    "sg:postcode":"J0T 1R0",
    "sg:province":"QC",
    "sg:tags":[
        "aircraft",
        "school"
    ],
    "wof:name":"Aero Loisirs Inc",
    "wof:placetype":"venue"
},
  "geometry": {"coordinates":[-74.7459487915,46.2807693481],"type":"Point"}
}