{
  "type": "Feature",
  "properties": {
    "addr:full":"Fort Macleod AB T0L 0Z0",
    "addr:postcode":"t0l 0z0",
    "addr:street":"Fort",
    "iso:country":"CA",
    "sg:city":"Fort Macleod",
    "sg:classifiers":[
        {
            "category":"Insurance",
            "subcategory":"Insurance Agent",
            "type":"Services"
        }
    ],
    "sg:phone":"+1 403 553 3717",
    "sg:postcode":"T0L 0Z0",
    "sg:province":"AB",
    "wof:name":"Fort Macleod Agencies Ltd",
    "wof:placetype":"venue"
},
  "geometry": {"coordinates":[-113.395584106,49.7260742188],"type":"Point"}
}