{
  "type": "Feature",
  "properties": {
    "addr:full":"1451 Marine Dr # 115 West Vancouver BC V7T 1B8",
    "addr:housenumber":"1451",
    "addr:postcode":"v7t 1b8",
    "addr:street":"Marine Dr # 115",
    "iso:country":"CA",
    "sg:address":"1451 Marine Dr # 115",
    "sg:city":"West Vancouver",
    "sg:classifiers":[
        {
            "category":"Professional",
            "subcategory":"Engineering",
            "type":"Services"
        }
    ],
    "sg:phone":"+1 604 925 2552",
    "sg:postcode":"V7T 1B8",
    "sg:province":"BC",
    "sg:tags":[
        "engineer"
    ],
    "wof:name":"Smith & CO Consulting Engrs",
    "wof:placetype":"venue"
},
  "geometry": {"coordinates":[-123.15553300000001,49.328251],"type":"Point"}
}