{
  "type": "Feature",
  "properties": {
    "addr:full":"8 Earl St Tobermory ON N0H 2R0",
    "addr:housenumber":"8",
    "addr:postcode":"n0h 2r0",
    "addr:street":"Earl St",
    "iso:country":"CA",
    "sg:address":"8 Earl St",
    "sg:city":"Tobermory",
    "sg:classifiers":[
        {
            "category":"Travel",
            "subcategory":"Hotels & Motels",
            "type":"Entertainment"
        }
    ],
    "sg:phone":"+1 519 596 2220",
    "sg:postcode":"N0H 2R0",
    "sg:province":"ON",
    "wof:name":"Grandview Motel & Dining Room",
    "wof:placetype":"venue"
},
  "geometry": {"coordinates":[-81.65966033940001,45.2586021423],"type":"Point"}
}