{
  "type": "Feature",
  "properties": {
    "addr:full":"Victoria BC V8T 5C3",
    "addr:postcode":"v8t 5c3",
    "iso:country":"CA",
    "sg:city":"Victoria",
    "sg:classifiers":[
        {
            "category":"Insurance",
            "subcategory":"Insurance Agent",
            "type":"Services"
        }
    ],
    "sg:phone":"+1 250 388 7577",
    "sg:postcode":"V8T 5C3",
    "sg:province":"BC",
    "wof:name":"Aon Reed Stenhouse Inc",
    "wof:placetype":"venue"
},
  "geometry": {"coordinates":[-123.364364624,48.4303398132],"type":"Point"}
}