{
  "type": "Feature",
  "properties": {
    "iso:country":"CA",
    "sg:address":"1110 Lynn Valley Rd",
    "sg:city":"North Vancouver",
    "sg:classifiers":[
        {
            "category":"Government",
            "subcategory":"Fire Station",
            "type":"Public Place"
        }
    ],
    "sg:phone":"+1 604 980 7575",
    "sg:postcode":"V7J 1Z9",
    "sg:province":"BC",
    "sg:tags":[
        "department"
    ],
    "wof:name":"N Vancouver Dist Fire Dept",
    "wof:placetype":"venue"
},
  "geometry": {"coordinates":[-123.043556213,49.3344306946],"type":"Point"}
}