{
  "type": "Feature",
  "properties": {
    "addr:full":"3426 Glenwood Ave Windsor ON N9E 2Y5",
    "addr:housenumber":"3426",
    "addr:postcode":"n9e 2y5",
    "addr:street":"Glenwood Ave",
    "iso:country":"CA",
    "sg:address":"3426 Glenwood Ave",
    "sg:city":"Windsor",
    "sg:classifiers":[
        {
            "category":"Shopping",
            "type":"Retail Goods"
        }
    ],
    "sg:phone":"+1 519 969 5921",
    "sg:postcode":"N9E 2Y5",
    "sg:province":"ON",
    "sg:tags":[
        "cosmetic",
        "perfume"
    ],
    "wof:name":"Mary Kay Cosmetics",
    "wof:placetype":"venue"
},
  "geometry": {"coordinates":[-83.02564239500001,42.2590255737],"type":"Point"}
}