{
  "type": "Feature",
  "properties": {
    "addr:full":"4905 Hotel Lake Rd Garden Bay BC V0N 1S0",
    "addr:housenumber":"4905",
    "addr:postcode":"v0n 1s0",
    "addr:street":"Hotel Lake Rd",
    "iso:country":"CA",
    "sg:address":"4905 Hotel Lake Rd",
    "sg:city":"Garden Bay",
    "sg:classifiers":[
        {
            "category":"Travel",
            "subcategory":"Travel Agent",
            "type":"Entertainment"
        }
    ],
    "sg:phone":"+1 604 883 9842",
    "sg:postcode":"V0N 1S0",
    "sg:province":"BC",
    "sg:tags":[
        "bureau",
        "agency",
        "tours"
    ],
    "wof:name":"Pacific Motorcycle Adventure",
    "wof:placetype":"venue"
},
  "geometry": {"coordinates":[-123.97172500000001,49.638954],"type":"Point"}
}