{
  "type": "Feature",
  "properties": {
    "addr:full":"Toronto ON M5H 1J9",
    "addr:postcode":"m5h 1j9",
    "iso:country":"CA",
    "sg:city":"Toronto",
    "sg:classifiers":[
        {
            "category":"Insurance",
            "subcategory":"Insurance Agent",
            "type":"Services"
        }
    ],
    "sg:phone":"+1 416 408 0272",
    "sg:postcode":"M5H 1J9",
    "sg:province":"ON",
    "wof:name":"Swiss Reinsurance CO",
    "wof:placetype":"venue"
},
  "geometry": {"coordinates":[-79.38372039790001,43.6479721069],"type":"Point"}
}