{
  "type": "Feature",
  "properties": {
    "addr:full":"5680 Navoo Rd Watford ON N0M 2S0",
    "addr:postcode":"5680;n0m 2s0",
    "addr:street":"Navoo Rd",
    "iso:country":"CA",
    "sg:address":"5680 Navoo Rd",
    "sg:city":"Watford",
    "sg:classifiers":[
        {
            "category":"Wholesale",
            "subcategory":"Farm Supplies",
            "type":"Manufacturing & Wholesale Goods"
        }
    ],
    "sg:phone":"+1 519 849 5575",
    "sg:postcode":"N0M 2S0",
    "sg:province":"ON",
    "sg:tags":[
        "livestock"
    ],
    "wof:name":"Moffatt Sales Yard",
    "wof:placetype":"venue"
},
  "geometry": {"coordinates":[-81.879593,42.97089],"type":"Point"}
}