{
  "type": "Feature",
  "properties": {
    "addr:full":"1150 Rue DE Louvain O Montreal QC H4N 1G5",
    "addr:housenumber":"1150",
    "addr:postcode":"h4n 1g5",
    "addr:street":"Rue De Louvain O",
    "iso:country":"CA",
    "sg:address":"1150 Rue DE Louvain O",
    "sg:city":"Montreal",
    "sg:classifiers":[
        {
            "category":"Professional",
            "subcategory":"Lawyer & Legal Services",
            "type":"Services"
        }
    ],
    "sg:phone":"+1 514 747 0690",
    "sg:postcode":"H4N 1G5",
    "sg:province":"QC",
    "sg:tags":[
        "attorney"
    ],
    "wof:name":"Chahwan & Nahabedian",
    "wof:placetype":"venue"
},
  "geometry": {"coordinates":[-73.64576721189999,45.5585784912],"type":"Point"}
}