{
  "type": "Feature",
  "properties": {
    "addr:full":"Redwing Industrial Dr Prince Albert SK S6V 5R3",
    "addr:postcode":"s6v 5r3",
    "addr:street":"Redwing Industrial Dr",
    "iso:country":"CA",
    "sg:address":"Redwing Industrial Dr",
    "sg:city":"Prince Albert",
    "sg:classifiers":[
        {
            "category":"Wholesale",
            "subcategory":"Auto Parts",
            "type":"Manufacturing & Wholesale Goods"
        }
    ],
    "sg:phone":"+1 306 764 2724",
    "sg:postcode":"S6V 5R3",
    "sg:province":"SK",
    "sg:tags":[
        "automobile",
        "wrecking"
    ],
    "wof:name":"Five Mile Auto Wreckers Inc",
    "wof:placetype":"venue"
},
  "geometry": {"coordinates":[-105.751716614,53.2175483704],"type":"Point"}
}