{
  "type": "Feature",
  "properties": {
    "addr:full":"753 Rue Principale Cowansville QC J2K 1J8",
    "addr:housenumber":"753",
    "addr:postcode":"j2k 1j8",
    "addr:street":"Rue Principale",
    "iso:country":"CA",
    "sg:address":"753 Rue Principale",
    "sg:city":"Cowansville",
    "sg:classifiers":[
        {
            "category":"Health Services",
            "subcategory":"Doctor",
            "type":"Services"
        }
    ],
    "sg:phone":"+1 450 266 2429",
    "sg:postcode":"J2K 1J8",
    "sg:province":"QC",
    "sg:tags":[
        "clinic",
        "dentist"
    ],
    "wof:name":"Clinique Dentaire D Caille",
    "wof:placetype":"venue"
},
  "geometry": {"coordinates":[-72.723526001,45.2091445923],"type":"Point"}
}