{
  "type": "Feature",
  "properties": {
    "addr:full":"1132 Fennell Ave E Hamilton ON L8T 1S5",
    "addr:housenumber":"1132",
    "addr:postcode":"l8t 1s5",
    "addr:street":"Fennell Ave E",
    "iso:country":"CA",
    "sg:address":"1132 Fennell Ave E",
    "sg:city":"Hamilton",
    "sg:classifiers":[
        {
            "category":"Personal",
            "subcategory":"Beauty Salon",
            "type":"Services"
        }
    ],
    "sg:phone":"+1 905 388 1811",
    "sg:postcode":"L8T 1S5",
    "sg:province":"ON",
    "wof:name":"Nick's Hair Design",
    "wof:placetype":"venue"
},
  "geometry": {"coordinates":[-79.828796,43.225266],"type":"Point"}
}