{
  "type": "Feature",
  "properties": {
    "addr:full":"955 Av DE Bourgogne # 110 Sainte-Foy QC G1X 3E5",
    "addr:postcode":"g1x 3e5",
    "addr:street":"955 Av De Bourgogne # 110",
    "iso:country":"CA",
    "sg:address":"955 Av DE Bourgogne # 110",
    "sg:city":"Sainte-Foy",
    "sg:classifiers":[
        {
            "category":"Real Estate",
            "subcategory":"Real Estate Operator",
            "type":"Services"
        }
    ],
    "sg:phone":"+1 418 658 5447",
    "sg:postcode":"G1X 3E5",
    "sg:province":"QC",
    "sg:tags":[
        "apartment"
    ],
    "wof:name":"Nadeau & Freres Ltee",
    "wof:placetype":"venue"
},
  "geometry": {"coordinates":[-71.3120727539,46.7671585083],"type":"Point"}
}