{
  "type": "Feature",
  "properties": {
    "addr:full":"769 Downie St Stratford ON N5A 1Y8",
    "addr:housenumber":"769",
    "addr:postcode":"n5a 1y8",
    "addr:street":"Downie St",
    "iso:country":"CA",
    "sg:address":"769 Downie St",
    "sg:city":"Stratford",
    "sg:classifiers":[
        {
            "category":"Social Services",
            "type":"Services"
        }
    ],
    "sg:phone":"+1 519 273 4021",
    "sg:postcode":"N5A 1Y8",
    "sg:province":"ON",
    "sg:tags":[
        "housing",
        "assistance"
    ],
    "wof:name":"Vineyard Village",
    "wof:placetype":"venue"
},
  "geometry": {"coordinates":[-80.973389,43.355095],"type":"Point"}
}