{
  "type": "Feature",
  "properties": {
    "iso:country":"CA",
    "sg:city":"Raymond",
    "sg:classifiers":[
        {
            "category":"Recreation",
            "type":"Entertainment"
        }
    ],
    "sg:phone":"+1 403 752 4781",
    "sg:postcode":"T0K 2S0",
    "sg:province":"AB",
    "sg:tags":[
        "skating",
        "rink",
        "government"
    ],
    "wof:name":"Raymond Ice Arena",
    "wof:placetype":"venue"
},
  "geometry": {"coordinates":[-112.663887024,49.4655189514],"type":"Point"}
}