{
  "type": "Feature",
  "properties": {
    "addr:full":"289 King St Winnipeg MB R3B 1J8",
    "addr:housenumber":"289",
    "addr:postcode":"r3b 1j8",
    "addr:street":"King St",
    "iso:country":"CA",
    "sg:address":"289 King St",
    "sg:city":"Winnipeg",
    "sg:classifiers":[
        {
            "category":"Home & Garden",
            "subcategory":"Furniture",
            "type":"Retail Goods"
        }
    ],
    "sg:phone":"+1 204 943 6180",
    "sg:postcode":"R3B 1J8",
    "sg:province":"MB",
    "sg:tags":[
        "equipment",
        "kitchen",
        "cabinet"
    ],
    "wof:name":"Factory Kitchens Direct",
    "wof:placetype":"venue"
},
  "geometry": {"coordinates":[-97.136589,49.903637],"type":"Point"}
}