{
  "type": "Feature",
  "properties": {
    "addr:full":"295 King St Midland ON L4R 3M5",
    "addr:housenumber":"295",
    "addr:postcode":"l4r 3m5",
    "addr:street":"King St",
    "iso:country":"CA",
    "sg:address":"295 King St",
    "sg:city":"Midland",
    "sg:classifiers":[
        {
            "category":"Personal",
            "type":"Services"
        }
    ],
    "sg:phone":"+1 705 526 0791",
    "sg:postcode":"L4R 3M5",
    "sg:province":"ON",
    "sg:tags":[
        "credit",
        "debt",
        "counseling"
    ],
    "wof:name":"A Farber & Partners Inc",
    "wof:placetype":"venue"
},
  "geometry": {"coordinates":[-79.8848190308,44.74949646],"type":"Point"}
}