{
  "type": "Feature",
  "properties": {
    "addr:full":"Val-D'Or QC J9P 1C7",
    "addr:postcode":"j9p 1c7",
    "iso:country":"CA",
    "sg:city":"Val-D'Or",
    "sg:classifiers":[
        {
            "category":"Building & Trades",
            "subcategory":"Plumbing",
            "type":"Services"
        }
    ],
    "sg:phone":"+1 819 824 3095",
    "sg:postcode":"J9P 1C7",
    "sg:province":"QC",
    "sg:tags":[
        "excavating",
        "tank",
        "septic",
        "contractor"
    ],
    "wof:name":"Excavation Gerald Barbin Inc",
    "wof:placetype":"venue"
},
  "geometry": {"coordinates":[-71.0033187866,45.3835067749],"type":"Point"}
}