{
  "type": "Feature",
  "properties": {
    "addr:full":"1008 105 Ave Dawson Creek BC V1G 2L4",
    "addr:housenumber":"1008",
    "addr:postcode":"v1g 2l4",
    "addr:street":"105 Ave",
    "iso:country":"CA",
    "sg:address":"1008 105 Ave",
    "sg:city":"Dawson Creek",
    "sg:classifiers":[
        {
            "category":"Health Services",
            "subcategory":"Chiropractor",
            "type":"Services"
        }
    ],
    "sg:phone":"+1 250 782 9360",
    "sg:postcode":"V1G 2L4",
    "sg:province":"BC",
    "wof:name":"Irwin, David G DC",
    "wof:placetype":"venue"
},
  "geometry": {"coordinates":[-120.231079102,55.7561416626],"type":"Point"}
}