{
  "type": "Feature",
  "properties": {
    "addr:full":"Leduc AB T9E 6P1",
    "addr:postcode":"t9e 6p1",
    "iso:country":"CA",
    "sg:city":"Leduc",
    "sg:classifiers":[
        {
            "category":"Shopping",
            "subcategory":"Department Store",
            "type":"Retail Goods"
        }
    ],
    "sg:phone":"+1 780 986 6403",
    "sg:postcode":"T9E 6P1",
    "sg:province":"AB",
    "wof:name":"Saan Stores Ltd",
    "wof:placetype":"venue"
},
  "geometry": {"coordinates":[-113.548935,53.276108],"type":"Point"}
}