{
  "type": "Feature",
  "properties": {
    "iso:country":"CA",
    "sg:address":"1009 Princess Ave",
    "sg:city":"Brandon",
    "sg:classifiers":[
        {
            "category":"Organizations",
            "subcategory":"Political Organization",
            "type":"Services"
        }
    ],
    "sg:phone":"+1 204 727 8734",
    "sg:postcode":"R7A 0P7",
    "sg:province":"MB",
    "wof:name":"Caldwell, Drew",
    "wof:placetype":"venue"
},
  "geometry": {"coordinates":[-99.95166778559999,49.8470458984],"type":"Point"}
}