{
  "type": "Feature",
  "properties": {
    "addr:full":"375 10E Av Lachine QC H8S 3E4",
    "addr:housenumber":"375",
    "addr:postcode":"h8s 3e4",
    "addr:street":"10E Av",
    "iso:country":"CA",
    "sg:address":"375 10E Av",
    "sg:city":"Lachine",
    "sg:classifiers":[
        {
            "category":"Building & Trades",
            "subcategory":"Construction",
            "type":"Services"
        }
    ],
    "sg:phone":"+1 514 634 6650",
    "sg:postcode":"H8S 3E4",
    "sg:province":"QC",
    "sg:tags":[
        "resurfacing",
        "laying",
        "refinishing",
        "floor"
    ],
    "wof:name":"M A Lemonde Enrg",
    "wof:placetype":"venue"
},
  "geometry": {"coordinates":[-73.6727676392,45.4365730286],"type":"Point"}
}