{
  "type": "Feature",
  "properties": {
    "addr:full":"111 Whitburn Cres North York ON M3M 2S6",
    "addr:housenumber":"111",
    "addr:postcode":"m3m 2s6",
    "addr:street":"Whitburn Cres",
    "iso:country":"CA",
    "sg:address":"111 Whitburn Cres",
    "sg:city":"North York",
    "sg:classifiers":[
        {
            "category":"Building & Trades",
            "subcategory":"Construction",
            "type":"Services"
        }
    ],
    "sg:phone":"+1 416 457 1439",
    "sg:postcode":"M3M 2S6",
    "sg:province":"ON",
    "sg:tags":[
        "home",
        "improvement"
    ],
    "wof:name":"Arca Contracting",
    "wof:placetype":"venue"
},
  "geometry": {"coordinates":[-79.490936,43.737995],"type":"Point"}
}