{
  "type": "Feature",
  "properties": {
    "iso:country":"CA",
    "sg:city":"Sainte-Madeleine",
    "sg:classifiers":[
        {
            "category":"Manufacturing",
            "subcategory":"Building Materials",
            "type":"Manufacturing & Wholesale Goods"
        }
    ],
    "sg:phone":"+1 450 795 6970",
    "sg:postcode":"J0H 1S0",
    "sg:province":"QC",
    "wof:name":"Boiseries Mg Inc",
    "wof:placetype":"venue"
},
  "geometry": {"coordinates":[-73.090599,45.594505],"type":"Point"}
}