{
  "type": "Feature",
  "properties": {
    "addr:full":"Toronto ON M6R 3A9",
    "addr:postcode":"m6r 3a9",
    "iso:country":"CA",
    "sg:city":"Toronto",
    "sg:classifiers":[
        {
            "category":"Health Services",
            "subcategory":"Doctor",
            "type":"Services"
        }
    ],
    "sg:phone":"+1 416 533 3314",
    "sg:postcode":"M6R 3A9",
    "sg:province":"ON",
    "sg:tags":[
        "physician",
        "surgeon"
    ],
    "wof:name":"Tsatsaronis, Eleftheria MD",
    "wof:placetype":"venue"
},
  "geometry": {"coordinates":[-79.451736,43.654331],"type":"Point"}
}