{
  "type": "Feature",
  "properties": {
    "addr:full":"85 Granton Ave Nepean ON K2G 1X2",
    "addr:housenumber":"85",
    "addr:postcode":"k2g 1x2",
    "addr:street":"Granton Ave",
    "iso:country":"CA",
    "sg:address":"85 Granton Ave",
    "sg:city":"Nepean",
    "sg:classifiers":[
        {
            "category":"Building & Trades",
            "subcategory":"Cleaning & Sanitation",
            "type":"Services"
        }
    ],
    "sg:phone":"+1 613 224 6929",
    "sg:postcode":"K2G 1X2",
    "sg:province":"ON",
    "sg:tags":[
        "janitor"
    ],
    "wof:name":"Zorba Building Cleaners Inc",
    "wof:placetype":"venue"
},
  "geometry": {"coordinates":[-75.747772,45.357239],"type":"Point"}
}