{
  "type": "Feature",
  "properties": {
    "addr:full":"Sainte-Christine QC J0H 1H0",
    "addr:postcode":"j0h 1h0",
    "iso:country":"CA",
    "sg:city":"Sainte-Christine",
    "sg:classifiers":[
        {
            "category":"Organizations",
            "subcategory":"Religious Organization",
            "type":"Services"
        }
    ],
    "sg:phone":"+1 819 858 2922",
    "sg:postcode":"J0H 1H0",
    "sg:province":"QC",
    "sg:tags":[
        "church"
    ],
    "wof:name":"Presbytere Ste-Christine",
    "wof:placetype":"venue"
},
  "geometry": {"coordinates":[-72.428116,45.615311],"type":"Point"}
}