{
  "type": "Feature",
  "properties": {
    "iso:country":"CA",
    "sg:address":"600 1E Av",
    "sg:city":"Quebec",
    "sg:classifiers":[
        {
            "category":"Autos & Motor Vehicles",
            "subcategory":"Automobile Sales",
            "type":"Retail Goods"
        }
    ],
    "sg:phone":"+1 418 660 1515",
    "sg:postcode":"G1L 3K1",
    "sg:province":"QC",
    "sg:tags":[
        "car",
        "dealer"
    ],
    "wof:name":"Automobiles Plaza Jp Blouin",
    "wof:placetype":"venue"
},
  "geometry": {"coordinates":[-71.230331,46.822769],"type":"Point"}
}