{
  "type": "Feature",
  "properties": {
    "addr:full":"5805 56 St Taber AB T1G 1L1",
    "addr:housenumber":"5805",
    "addr:postcode":"t1g 1l1",
    "addr:street":"56 St",
    "iso:country":"CA",
    "sg:address":"5805 56 St",
    "sg:city":"Taber",
    "sg:classifiers":[
        {
            "category":"Mining & Drilling",
            "type":"Manufacturing & Wholesale Goods"
        }
    ],
    "sg:phone":"+1 403 223 4215",
    "sg:postcode":"T1G 1L1",
    "sg:province":"AB",
    "sg:tags":[
        "field",
        "oil"
    ],
    "wof:name":"Roc Oilfield Construction",
    "wof:placetype":"venue"
},
  "geometry": {"coordinates":[-112.139633,49.794559],"type":"Point"}
}