{
  "type": "Feature",
  "properties": {
    "addr:full":"PO Box 7500 STN Main Edson AB T7E 1V6",
    "addr:housenumber":"po",
    "addr:postcode":"7500;t7e 1v6",
    "addr:street":"Box;Stn Main",
    "iso:country":"CA",
    "sg:address":"PO Box 7500 STN Main",
    "sg:city":"Edson",
    "sg:classifiers":[
        {
            "category":"Building & Trades",
            "subcategory":"Construction",
            "type":"Services"
        }
    ],
    "sg:phone":"+1 780 723 3016",
    "sg:postcode":"T7E 1V6",
    "sg:province":"AB",
    "sg:tags":[
        "general",
        "contractor"
    ],
    "wof:name":"Sandon Industries Ltd",
    "wof:placetype":"venue"
},
  "geometry": {"coordinates":[-116.43409699999999,53.58213],"type":"Point"}
}