{
  "type": "Feature",
  "properties": {
    "addr:full":"263 101 Rte S Duhamel-Ouest QC J9V 2E4",
    "addr:housenumber":"101",
    "addr:postcode":"j9v 2e4",
    "addr:street":"Rte S",
    "iso:country":"CA",
    "sg:address":"263 101 Rte S",
    "sg:city":"Duhamel-Ouest",
    "sg:classifiers":[
        {
            "category":"Food & Beverages",
            "subcategory":"Groceries & Convenience Stores",
            "type":"Retail Goods"
        }
    ],
    "sg:phone":"+1 819 622 1627",
    "sg:postcode":"J9V 2E4",
    "sg:province":"QC",
    "sg:tags":[
        "grocer"
    ],
    "wof:name":"Depanneur Vieux Fort Enr",
    "wof:placetype":"venue"
},
  "geometry": {"coordinates":[-79.412758,47.337421],"type":"Point"}
}