{
  "type": "Feature",
  "properties": {
    "addr:full":"953 7E Rang Saint-Dominique QC J0H 1L0",
    "addr:housenumber":"953",
    "addr:postcode":"j0h 1l0",
    "addr:street":"7E Rang Saint-Dominique",
    "iso:country":"CA",
    "sg:address":"953 7E Rang",
    "sg:city":"Saint-Dominique",
    "sg:classifiers":[
        {
            "category":"Home & Garden",
            "subcategory":"Building Materials",
            "type":"Retail Goods"
        }
    ],
    "sg:phone":"+1 450 773 6682",
    "sg:postcode":"J0H 1L0",
    "sg:province":"QC",
    "sg:tags":[
        "mixed",
        "concrete"
    ],
    "wof:name":"Beton Mobile Dalpe Enr",
    "wof:placetype":"venue"
},
  "geometry": {"coordinates":[-72.837593,45.593925],"type":"Point"}
}