{
  "type": "Feature",
  "properties": {
    "addr:full":"500 Victoria Terr Fergus ON N1M 2G5",
    "addr:housenumber":"500",
    "addr:postcode":"n1m 2g5",
    "addr:street":"Victoria Terr",
    "iso:country":"CA",
    "sg:address":"500 Victoria Terr",
    "sg:city":"Fergus",
    "sg:classifiers":[
        {
            "category":"Education",
            "subcategory":"School",
            "type":"Public Place"
        }
    ],
    "sg:phone":"+1 519 843 2720",
    "sg:postcode":"N1M 2G5",
    "sg:province":"ON",
    "wof:name":"Victoria Terrace Public School",
    "wof:placetype":"venue"
},
  "geometry": {"coordinates":[-80.37822,43.710651],"type":"Point"}
}