{
  "type": "Feature",
  "properties": {
    "addr:full":"113 Boul Saint-Joseph Chateauguay QC J6K 3J6",
    "addr:housenumber":"113",
    "addr:postcode":"j6k 3j6",
    "addr:street":"Boul Saint-Joseph",
    "iso:country":"CA",
    "sg:address":"113 Boul Saint-Joseph",
    "sg:city":"Chateauguay",
    "sg:classifiers":[
        {
            "category":"Personal",
            "subcategory":"Beauty Salon",
            "type":"Services"
        }
    ],
    "sg:phone":"+1 450 691 2112",
    "sg:postcode":"J6K 3J6",
    "sg:province":"QC",
    "wof:name":"Salon Melanie",
    "wof:placetype":"venue"
},
  "geometry": {"coordinates":[-73.7317276001,45.3509750366],"type":"Point"}
}