{
  "type": "Feature",
  "properties": {
    "iso:country":"CA",
    "sg:address":"980 Kimberly Ave",
    "sg:city":"Winnipeg",
    "sg:classifiers":[
        {
            "category":"Arts & Performance",
            "subcategory":"Theater",
            "type":"Entertainment"
        }
    ],
    "sg:phone":"+1 204 663 1000",
    "sg:postcode":"R2K 3S9",
    "sg:province":"MB",
    "sg:tags":[
        "bureau"
    ],
    "wof:name":"Clowns Magicians & More",
    "wof:placetype":"venue"
},
  "geometry": {"coordinates":[-97.0693283081,49.9159164429],"type":"Point"}
}