{
  "type": "Feature",
  "properties": {
    "addr:full":"Calgary AB T3E 0C2",
    "addr:postcode":"t3e 0c2",
    "iso:country":"CA",
    "sg:city":"Calgary",
    "sg:classifiers":[
        {
            "category":"Restaurant",
            "type":"Food & Drink"
        }
    ],
    "sg:phone":"+1 403 246 8764",
    "sg:postcode":"T3E 0C2",
    "sg:province":"AB",
    "wof:name":"Mr Sub",
    "wof:placetype":"venue"
},
  "geometry": {"coordinates":[-114.14135,51.037949],"type":"Point"}
}