{
  "type": "Feature",
  "properties": {
    "iso:country":"CA",
    "sg:address":"162 Av Du Sacre-Coeur",
    "sg:city":"Quebec",
    "sg:classifiers":[
        {
            "category":"Home & Garden",
            "subcategory":"Home Furnishings",
            "type":"Retail Goods"
        }
    ],
    "sg:phone":"+1 418 522 5693",
    "sg:postcode":"G1N 2W2",
    "sg:province":"QC",
    "sg:tags":[
        "lighting",
        "fixture"
    ],
    "wof:name":"Eclairages Solaires Fgc Inc",
    "wof:placetype":"venue"
},
  "geometry": {"coordinates":[-71.2443389893,46.81092453],"type":"Point"}
}