{
  "type": "Feature",
  "properties": {
    "addr:full":"555 Rexdale Blvd Etobicoke ON M9W 7G3",
    "addr:housenumber":"555",
    "addr:postcode":"m9w 7g3",
    "addr:street":"Rexdale Blvd",
    "iso:country":"CA",
    "sg:address":"555 Rexdale Blvd",
    "sg:city":"Etobicoke",
    "sg:classifiers":[
        {
            "category":"Retail",
            "subcategory":"Animal Services",
            "type":"Services"
        }
    ],
    "sg:phone":"+1 416 674 7300",
    "sg:postcode":"M9W 7G3",
    "sg:province":"ON",
    "sg:tags":[
        "horse",
        "training"
    ],
    "wof:name":"Fairile, Scott",
    "wof:placetype":"venue"
},
  "geometry": {"coordinates":[-79.6031951904,43.7189025879],"type":"Point"}
}