{
  "type": "Feature",
  "properties": {
    "addr:full":"113 2nd Ave E Kindersley SK S0L 1S0",
    "addr:housenumber":"113",
    "addr:postcode":"s0l 1s0",
    "addr:street":"2Nd Ave E Kindersley",
    "iso:country":"CA",
    "sg:address":"113 2nd Ave E",
    "sg:city":"Kindersley",
    "sg:classifiers":[
        {
            "category":"Organizations",
            "subcategory":"Professional Association",
            "type":"Services"
        }
    ],
    "sg:phone":"+1 306 463 4702",
    "sg:postcode":"S0L 1S0",
    "sg:province":"SK",
    "sg:tags":[
        "club"
    ],
    "wof:name":"Mental Health Assn",
    "wof:placetype":"venue"
},
  "geometry": {"coordinates":[-109.15175600000001,51.468971],"type":"Point"}
}