{
  "type": "Feature",
  "properties": {
    "addr:full":"44 Rue Principale S Richmond QC J0B 2H0",
    "addr:housenumber":"44",
    "addr:postcode":"j0b 2h0",
    "addr:street":"Rue Principale S",
    "iso:country":"CA",
    "sg:address":"44 Rue Principale S",
    "sg:city":"Richmond",
    "sg:classifiers":[
        {
            "category":"Restaurant",
            "type":"Food & Drink"
        }
    ],
    "sg:phone":"+1 819 826 3432",
    "sg:postcode":"J0B 2H0",
    "sg:province":"QC",
    "wof:name":"Repas Minute Richmond Inc",
    "wof:placetype":"venue"
},
  "geometry": {"coordinates":[-72.142059,45.658054],"type":"Point"}
}