{
  "type": "Feature",
  "properties": {
    "addr:full":"27 Front St W Hastings ON K0L 1Y0",
    "addr:housenumber":"27",
    "addr:postcode":"k0l 1y0",
    "addr:street":"Front St W",
    "iso:country":"CA",
    "sg:address":"27 Front St W",
    "sg:city":"Hastings",
    "sg:classifiers":[
        {
            "category":"Restaurant",
            "type":"Food & Drink"
        }
    ],
    "sg:phone":"+1 705 696 3301",
    "sg:postcode":"K0L 1Y0",
    "sg:province":"ON",
    "wof:name":"Sheila's Restaurant & Take Out",
    "wof:placetype":"venue"
},
  "geometry": {"coordinates":[-77.958,44.308968],"type":"Point"}
}