{
  "type": "Feature",
  "properties": {
    "iso:country":"CA",
    "sg:city":"Surrey",
    "sg:classifiers":[
        {
            "category":"Shopping",
            "type":"Retail Goods"
        }
    ],
    "sg:phone":"+1 604 597 4784",
    "sg:postcode":"V3W 3E9",
    "sg:province":"BC",
    "sg:tags":[
        "orthopedic",
        "appliance"
    ],
    "wof:name":"Valley Orthocare Ltd",
    "wof:placetype":"venue"
},
  "geometry": {"coordinates":[-122.87747192400001,49.1519508362],"type":"Point"}
}