{
  "type": "Feature",
  "properties": {
    "addr:full":"Powell River BC V8A 2C3",
    "addr:postcode":"v8a 2c3",
    "iso:country":"CA",
    "sg:city":"Powell River",
    "sg:classifiers":[
        {
            "category":"Personal",
            "subcategory":"Barber",
            "type":"Services"
        }
    ],
    "sg:phone":"+1 604 485 6133",
    "sg:postcode":"V8A 2C3",
    "sg:province":"BC",
    "wof:name":"Joyce Avenue Barbers",
    "wof:placetype":"venue"
},
  "geometry": {"coordinates":[-124.519341,49.846165],"type":"Point"}
}