{
  "type": "Feature",
  "properties": {
    "addr:full":"3550 Rue Ontario E Montreal QC H1W 1R5",
    "addr:housenumber":"3550",
    "addr:postcode":"h1w 1r5",
    "addr:street":"Rue Ontario E",
    "iso:country":"CA",
    "sg:address":"3550 Rue Ontario E",
    "sg:city":"Montreal",
    "sg:classifiers":[
        {
            "category":"Restaurant",
            "type":"Food & Drink"
        }
    ],
    "sg:phone":"+1 514 525 0817",
    "sg:postcode":"H1W 1R5",
    "sg:province":"QC",
    "sg:tags":[
        "delicatessen"
    ],
    "wof:name":"Charcuterie Du Village",
    "wof:placetype":"venue"
},
  "geometry": {"coordinates":[-73.54490699999999,45.544636],"type":"Point"}
}