{
  "type": "Feature",
  "properties": {
    "addr:full":"333 N Rivermede Rd Concord ON L4K 3N7",
    "addr:housenumber":"333",
    "addr:postcode":"l4k 3n7",
    "addr:street":"N Rivermede Rd",
    "iso:country":"CA",
    "sg:address":"333 N Rivermede Rd",
    "sg:city":"Concord",
    "sg:classifiers":[
        {
            "category":"Wholesale",
            "subcategory":"Toys & Hobbies",
            "type":"Manufacturing & Wholesale Goods"
        }
    ],
    "sg:phone":"+1 905 738 8888",
    "sg:postcode":"L4K 3N7",
    "sg:province":"ON",
    "wof:name":"Encore Sales Ltd",
    "wof:placetype":"venue"
},
  "geometry": {"coordinates":[-79.48292499999999,43.814045],"type":"Point"}
}