{
  "type": "Feature",
  "properties": {
    "iso:country":"CA",
    "sg:city":"Fort Frances",
    "sg:classifiers":[
        {
            "category":"Health Services",
            "subcategory":"Chiropractor",
            "type":"Services"
        }
    ],
    "sg:phone":"+1 807 274 2545",
    "sg:postcode":"P9A 2T1",
    "sg:province":"ON",
    "wof:name":"Fort Frances Chiropractic Ctr",
    "wof:placetype":"venue"
},
  "geometry": {"coordinates":[-93.39111328120001,48.6100006104],"type":"Point"}
}