{
  "type": "Feature",
  "properties": {
    "addr:full":"5815 Morrison St Niagara Falls ON L2E 2E8",
    "addr:housenumber":"5815",
    "addr:postcode":"l2e 2e8",
    "addr:street":"Morrison St",
    "iso:country":"CA",
    "sg:address":"5815 Morrison St",
    "sg:city":"Niagara Falls",
    "sg:classifiers":[
        {
            "category":"Government",
            "subcategory":"Fire Station",
            "type":"Public Place"
        }
    ],
    "sg:phone":"+1 905 356 1321",
    "sg:postcode":"L2E 2E8",
    "sg:province":"ON",
    "sg:tags":[
        "department"
    ],
    "wof:name":"Niagara Falls Fire Dept",
    "wof:placetype":"venue"
},
  "geometry": {"coordinates":[-79.09156,43.10453],"type":"Point"}
}