{
  "type": "Feature",
  "properties": {
    "addr:full":"9164 Yellowhead Trail NW Edmonton AB T5B 1G2",
    "addr:housenumber":"9164",
    "addr:postcode":"t5b 1g2",
    "addr:street":"Yellowhead Trail Nw",
    "iso:country":"CA",
    "sg:address":"9164 Yellowhead Trail NW",
    "sg:city":"Edmonton",
    "sg:classifiers":[
        {
            "category":"Retail",
            "subcategory":"Auto Repair",
            "type":"Services"
        }
    ],
    "sg:phone":"+1 780 496 9497",
    "sg:postcode":"T5B 1G2",
    "sg:province":"AB",
    "sg:tags":[
        "repairing",
        "automobile"
    ],
    "wof:name":"Strictly Avs",
    "wof:placetype":"venue"
},
  "geometry": {"coordinates":[-113.481994629,53.581615448],"type":"Point"}
}