{
  "type": "Feature",
  "properties": {
    "iso:country":"CA",
    "sg:address":"5812 149 Ave NW",
    "sg:city":"Edmonton",
    "sg:classifiers":[
        {
            "category":"Organizations",
            "subcategory":"Religious Organization",
            "type":"Services"
        }
    ],
    "sg:phone":"+1 780 478 1553",
    "sg:postcode":"T5A 3A7",
    "sg:province":"AB",
    "sg:tags":[
        "church"
    ],
    "wof:name":"Steele Heights Baptist Church",
    "wof:placetype":"venue"
},
  "geometry": {"coordinates":[-113.430770874,53.6114883423],"type":"Point"}
}