{
  "type": "Feature",
  "properties": {
    "addr:full":"851 Pembina Ave Winkler MB R6W 2N5",
    "addr:housenumber":"851",
    "addr:postcode":"r6w 2n5",
    "addr:street":"Pembina Ave",
    "iso:country":"CA",
    "sg:address":"851 Pembina Ave",
    "sg:city":"Winkler",
    "sg:classifiers":[
        {
            "category":"Social Services",
            "subcategory":"Child Care",
            "type":"Services"
        }
    ],
    "sg:phone":"+1 204 325 9103",
    "sg:postcode":"R6W 2N5",
    "sg:province":"MB",
    "wof:name":"Winkler Day Care Ctr",
    "wof:placetype":"venue"
},
  "geometry": {"coordinates":[-97.94412199999999,49.177841],"type":"Point"}
}