{
  "type": "Feature",
  "properties": {
    "addr:full":"669 Av Du Parc Valcourt QC J0E 2L0",
    "addr:postcode":"j0e 2l0",
    "addr:street":"669 Av Du Parc",
    "iso:country":"CA",
    "sg:address":"669 Av Du Parc",
    "sg:city":"Valcourt",
    "sg:classifiers":[
        {
            "category":"Personal",
            "subcategory":"Barber",
            "type":"Services"
        }
    ],
    "sg:phone":"+1 450 532 3458",
    "sg:postcode":"J0E 2L0",
    "sg:province":"QC",
    "wof:name":"Salon Lorraine",
    "wof:placetype":"venue"
},
  "geometry": {"coordinates":[-72.30889892579999,45.4925384521],"type":"Point"}
}