{
  "type": "Feature",
  "properties": {
    "addr:full":"7225 Woodbine Ave Markham ON L3R 1A3",
    "addr:housenumber":"7225",
    "addr:postcode":"l3r 1a3",
    "addr:street":"Woodbine Ave",
    "iso:country":"CA",
    "sg:address":"7225 Woodbine Ave",
    "sg:city":"Markham",
    "sg:classifiers":[
        {
            "category":"Freight",
            "type":"Transportation"
        }
    ],
    "sg:phone":"+1 905 479 6245",
    "sg:postcode":"L3R 1A3",
    "sg:province":"ON",
    "sg:tags":[
        "courier"
    ],
    "wof:name":"On the Wings of the Dove",
    "wof:placetype":"venue"
},
  "geometry": {"coordinates":[-79.34981500000001,43.819111],"type":"Point"}
}