{
  "type": "Feature",
  "properties": {
    "addr:full":"7640 Winston St Burnaby BC V5A 2H4",
    "addr:housenumber":"7640",
    "addr:postcode":"v5a 2h4",
    "addr:street":"Winston St",
    "iso:country":"CA",
    "sg:address":"7640 Winston St",
    "sg:city":"Burnaby",
    "sg:classifiers":[
        {
            "category":"Wholesale",
            "subcategory":"Hardware",
            "type":"Manufacturing & Wholesale Goods"
        }
    ],
    "sg:phone":"+1 604 420 7100",
    "sg:postcode":"V5A 2H4",
    "sg:province":"BC",
    "sg:tags":[
        "equipment",
        "caster",
        "material",
        "handling",
        "glide"
    ],
    "wof:name":"Caster Solutions",
    "wof:placetype":"venue"
},
  "geometry": {"coordinates":[-122.940872,49.2481],"type":"Point"}
}