{
  "type": "Feature",
  "properties": {
    "addr:full":"5671 Montevideo Rd Mississauga ON L5N 2M5",
    "addr:housenumber":"5671",
    "addr:postcode":"l5n 2m5",
    "addr:street":"Montevideo Rd",
    "iso:country":"CA",
    "sg:address":"5671 Montevideo Rd",
    "sg:city":"Mississauga",
    "sg:classifiers":[
        {
            "category":"Building & Trades",
            "subcategory":"Electrical",
            "type":"Services"
        }
    ],
    "sg:phone":"+1 905 826 1079",
    "sg:postcode":"L5N 2M5",
    "sg:province":"ON",
    "sg:tags":[
        "electric",
        "contractor"
    ],
    "wof:name":"Mascan Electric Ltd",
    "wof:placetype":"venue"
},
  "geometry": {"coordinates":[-79.7535934448,43.5775222778],"type":"Point"}
}