{
  "type": "Feature",
  "properties": {
    "addr:full":"Toronto ON M4Y 2G9",
    "addr:postcode":"m4y 2g9",
    "iso:country":"CA",
    "sg:city":"Toronto",
    "sg:classifiers":[
        {
            "category":"Building & Trades",
            "subcategory":"Cleaning & Sanitation",
            "type":"Services"
        }
    ],
    "sg:phone":"+1 416 964 3757",
    "sg:postcode":"M4Y 2G9",
    "sg:province":"ON",
    "sg:tags":[
        "fireplace",
        "chimney"
    ],
    "wof:name":"Great Lakes Building Svc Ltd",
    "wof:placetype":"venue"
},
  "geometry": {"coordinates":[-79.376976,43.663479],"type":"Point"}
}