{
  "type": "Feature",
  "properties": {
    "iso:country":"CA",
    "sg:address":"1175 Rue Saint-Adelard",
    "sg:city":"Drummondville",
    "sg:classifiers":[
        {
            "category":"Manufacturing",
            "subcategory":"Toys & Sporting Goods",
            "type":"Manufacturing & Wholesale Goods"
        }
    ],
    "sg:phone":"+1 819 477 3143",
    "sg:postcode":"J2B 7P3",
    "sg:province":"QC",
    "sg:tags":[
        "tackle",
        "fishing"
    ],
    "wof:name":"Mouches Neptune Flies Inc",
    "wof:placetype":"venue"
},
  "geometry": {"coordinates":[-72.47319030760001,45.8661766052],"type":"Point"}
}