{
  "type": "Feature",
  "properties": {
    "addr:full":"13350 Comber Way Surrey BC V3W 5V9",
    "addr:housenumber":"13350",
    "addr:postcode":"v3w 5v9",
    "addr:street":"Comber Way",
    "iso:country":"CA",
    "sg:address":"13350 Comber Way",
    "sg:city":"Surrey",
    "sg:classifiers":[
        {
            "category":"Home & Garden",
            "subcategory":"Furniture",
            "type":"Retail Goods"
        }
    ],
    "sg:phone":"+1 604 594 1112",
    "sg:postcode":"V3W 5V9",
    "sg:province":"BC",
    "sg:tags":[
        "mattress"
    ],
    "wof:name":"Restwell Mattress CO Ltd",
    "wof:placetype":"venue"
},
  "geometry": {"coordinates":[-122.85307312,49.1359367371],"type":"Point"}
}