{
  "type": "Feature",
  "properties": {
    "iso:country":"CA",
    "sg:address":"18 Golden Gate Crt",
    "sg:city":"Scarborough",
    "sg:classifiers":[
        {
            "category":"Manufacturing",
            "subcategory":"Tools & Machinery",
            "type":"Manufacturing & Wholesale Goods"
        }
    ],
    "sg:phone":"+1 416 293 8229",
    "sg:postcode":"M1P 3A5",
    "sg:province":"ON",
    "sg:tags":[
        "casting",
        "die",
        "mold",
        "nonferrous"
    ],
    "wof:name":"J & K Die Casting Ltd",
    "wof:placetype":"venue"
},
  "geometry": {"coordinates":[-79.264503479,43.7714958191],"type":"Point"}
}