{
  "type": "Feature",
  "properties": {
    "addr:full":"1769 Chiefswood Rd Ohsweken ON N0A 1M0",
    "addr:housenumber":"1769",
    "addr:postcode":"n0a 1m0",
    "addr:street":"Chiefswood Rd",
    "iso:country":"CA",
    "sg:address":"1769 Chiefswood Rd",
    "sg:city":"Ohsweken",
    "sg:classifiers":[
        {
            "category":"Food & Beverages",
            "subcategory":"Specialty",
            "type":"Retail Goods"
        }
    ],
    "sg:phone":"+1 519 445 0782",
    "sg:postcode":"N0A 1M0",
    "sg:province":"ON",
    "sg:tags":[
        "instruction",
        "health",
        "association",
        "diet",
        "care"
    ],
    "wof:name":"Health Promotion Nutrition Pro",
    "wof:placetype":"venue"
},
  "geometry": {"coordinates":[-80.1152191162,43.0733375549],"type":"Point"}
}