{
  "type": "Feature",
  "properties": {
    "addr:full":"8425 Rue Saint-Denis Montreal QC H2P 2G9",
    "addr:housenumber":"8425",
    "addr:postcode":"h2p 2g9",
    "addr:street":"Rue Saint-Denis",
    "iso:country":"CA",
    "sg:address":"8425 Rue Saint-Denis",
    "sg:city":"Montreal",
    "sg:classifiers":[
        {
            "category":"Personal",
            "subcategory":"Beauty Salon",
            "type":"Services"
        }
    ],
    "sg:phone":"+1 514 389 6703",
    "sg:postcode":"H2P 2G9",
    "sg:province":"QC",
    "wof:name":"Tuniki",
    "wof:placetype":"venue"
},
  "geometry": {"coordinates":[-73.634064,45.544159],"type":"Point"}
}