{
  "type": "Feature",
  "properties": {
    "addr:full":"3841 Canada Way Burnaby BC V5G 1G6",
    "addr:housenumber":"3841",
    "addr:postcode":"v5g 1g6",
    "addr:street":"Canada Way",
    "iso:country":"CA",
    "sg:address":"3841 Canada Way",
    "sg:city":"Burnaby",
    "sg:classifiers":[
        {
            "category":"Personal",
            "subcategory":"Barber",
            "type":"Services"
        }
    ],
    "sg:phone":"+1 604 437 5410",
    "sg:postcode":"V5G 1G6",
    "sg:province":"BC",
    "wof:name":"Canada Way Barber Shop",
    "wof:placetype":"venue"
},
  "geometry": {"coordinates":[-123.0187,49.254936],"type":"Point"}
}