{
  "type": "Feature",
  "properties": {
    "addr:full":"13 Rue Principale Saint-Esprit QC J0K 2L0",
    "addr:housenumber":"13",
    "addr:postcode":"j0k 2l0",
    "addr:street":"Rue Principale",
    "iso:country":"CA",
    "sg:address":"13 Rue Principale",
    "sg:city":"Saint-Esprit",
    "sg:classifiers":[
        {
            "category":"Wholesale",
            "subcategory":"Farm Supplies",
            "type":"Manufacturing & Wholesale Goods"
        }
    ],
    "sg:phone":"+1 450 839 2581",
    "sg:postcode":"J0K 2L0",
    "sg:province":"QC",
    "sg:tags":[
        "feed"
    ],
    "wof:name":"Meunerie Marcel Bouchard",
    "wof:placetype":"venue"
},
  "geometry": {"coordinates":[-73.666222,45.897564],"type":"Point"}
}