{
  "type": "Feature",
  "properties": {
    "addr:full":"133 Head St S # 5 Strathroy ON N7G 2L1",
    "addr:housenumber":"133",
    "addr:postcode":"n7g 2l1",
    "addr:street":"Head St S # 5",
    "iso:country":"CA",
    "sg:address":"133 Head St S # 5",
    "sg:city":"Strathroy",
    "sg:classifiers":[
        {
            "category":"Retail",
            "subcategory":"Car Wash",
            "type":"Services"
        }
    ],
    "sg:phone":"+1 519 245 2588",
    "sg:postcode":"N7G 2L1",
    "sg:province":"ON",
    "sg:tags":[
        "polishing",
        "washing"
    ],
    "wof:name":"Kevin's Car Care",
    "wof:placetype":"venue"
},
  "geometry": {"coordinates":[-81.616196,42.955956],"type":"Point"}
}