{
  "type": "Feature",
  "properties": {
    "addr:full":"556 Oster Lane Concord ON L4K 2C1",
    "addr:housenumber":"556",
    "addr:postcode":"l4k 2c1",
    "addr:street":"Oster Lane",
    "iso:country":"CA",
    "sg:address":"556 Oster Lane",
    "sg:city":"Concord",
    "sg:classifiers":[
        {
            "category":"Building & Trades",
            "subcategory":"Construction",
            "type":"Services"
        }
    ],
    "sg:phone":"+1 905 738 0004",
    "sg:postcode":"L4K 2C1",
    "sg:province":"ON",
    "sg:tags":[
        "general",
        "contractor"
    ],
    "wof:name":"Naples Construction Ltd",
    "wof:placetype":"venue"
},
  "geometry": {"coordinates":[-79.49387400000001,43.806831],"type":"Point"}
}