{
  "type": "Feature",
  "properties": {
    "iso:country":"CA",
    "sg:address":"556 Oster Lane",
    "sg:city":"Concord",
    "sg:classifiers":[
        {
            "category":"Building & Trades",
            "subcategory":"Construction",
            "type":"Services"
        }
    ],
    "sg:phone":"+1 905 738 0004",
    "sg:postcode":"L4K 2C1",
    "sg:province":"ON",
    "sg:tags":[
        "general",
        "contractor"
    ],
    "wof:name":"Naples Construction Ltd",
    "wof:placetype":"venue"
},
  "geometry": {"coordinates":[-79.493874,43.806831],"type":"Point"}
}