{
  "type": "Feature",
  "properties": {
    "addr:full":"219 Lambton St Kincardine ON N2Z 2Y1",
    "addr:housenumber":"219",
    "addr:postcode":"n2z 2y1",
    "addr:street":"Lambton St",
    "iso:country":"CA",
    "sg:address":"219 Lambton St",
    "sg:city":"Kincardine",
    "sg:classifiers":[
        {
            "category":"Recreation",
            "type":"Entertainment"
        }
    ],
    "sg:phone":"+1 519 396 2372",
    "sg:postcode":"N2Z 2Y1",
    "sg:province":"ON",
    "sg:tags":[
        "hall",
        "auditorium"
    ],
    "wof:name":"Royal Canadian Legion",
    "wof:placetype":"venue"
},
  "geometry": {"coordinates":[-81.63726,44.178761],"type":"Point"}
}