{
  "type": "Feature",
  "properties": {
    "addr:full":"1495 Rue Sainte-Catherine E Montreal QC H2L 2H9",
    "addr:housenumber":"1495",
    "addr:postcode":"h2l 2h9",
    "addr:street":"Rue Sainte-Catherine E",
    "iso:country":"CA",
    "sg:address":"1495 Rue Sainte-Catherine E",
    "sg:city":"Montreal",
    "sg:classifiers":[
        {
            "category":"Restaurant",
            "type":"Food & Drink"
        }
    ],
    "sg:phone":"+1 514 596 3933",
    "sg:postcode":"H2L 2H9",
    "sg:province":"QC",
    "wof:name":"Kilo Restaurant",
    "wof:placetype":"venue"
},
  "geometry": {"coordinates":[-73.55381800000001,45.521137],"type":"Point"}
}