{
  "type": "Feature",
  "properties": {
    "addr:full":"171 Ave Abitibi Malartic QC J0Y 1Z0",
    "addr:housenumber":"171",
    "addr:postcode":"j0y 1z0",
    "addr:street":"Ave Abitibi",
    "iso:country":"CA",
    "sg:address":"171 Ave Abitibi",
    "sg:city":"Malartic",
    "sg:classifiers":[
        {
            "category":"Personal",
            "subcategory":"Beauty Salon",
            "type":"Services"
        }
    ],
    "sg:phone":"+1 819 757 4160",
    "sg:postcode":"J0Y 1Z0",
    "sg:province":"QC",
    "wof:name":"Salon Jeannette Enr",
    "wof:placetype":"venue"
},
  "geometry": {"coordinates":[-78.12730407710001,48.1352996826],"type":"Point"}
}