{
  "type": "Feature",
  "properties": {
    "addr:full":"272 3rd St Mattice ON P0L 1T0",
    "addr:housenumber":"272",
    "addr:postcode":"p0l 1t0",
    "addr:street":"3Rd St",
    "iso:country":"CA",
    "sg:address":"272 3rd St",
    "sg:city":"Mattice",
    "sg:classifiers":[
        {
            "category":"Arena",
            "subcategory":"Sports Club",
            "type":"Entertainment"
        }
    ],
    "sg:phone":"+1 705 364 4551",
    "sg:postcode":"P0L 1T0",
    "sg:province":"ON",
    "sg:tags":[
        "athletic",
        "fields",
        "stadium",
        "government"
    ],
    "wof:name":"Mattice Complex Sportif",
    "wof:placetype":"venue"
},
  "geometry": {"coordinates":[-83.26303900000001,49.608562],"type":"Point"}
}