{
  "type": "Feature",
  "properties": {
    "iso:country":"CA",
    "sg:address":"370 Queen St S",
    "sg:city":"Bolton",
    "sg:classifiers":[
        {
            "category":"Shopping",
            "subcategory":"Bicycles & Sporting Goods",
            "type":"Retail Goods"
        }
    ],
    "sg:phone":"+1 905 857 2797",
    "sg:postcode":"L7E 4Z7",
    "sg:province":"ON",
    "sg:tags":[
        "snowboard"
    ],
    "wof:name":"King Sports",
    "wof:placetype":"venue"
},
  "geometry": {"coordinates":[-79.728515625,43.8724746704],"type":"Point"}
}