{
  "type": "Feature",
  "properties": {
    "addr:full":"277 Rue Du Bocage Rosemere QC J7A 3Z7",
    "addr:housenumber":"277",
    "addr:postcode":"j7a 3z7",
    "addr:street":"Rue Du Bocage",
    "iso:country":"CA",
    "sg:address":"277 Rue Du Bocage",
    "sg:city":"Rosemere",
    "sg:classifiers":[
        {
            "category":"Professional",
            "subcategory":"Management & Consulting",
            "type":"Services"
        }
    ],
    "sg:phone":"+1 450 430 7228",
    "sg:postcode":"J7A 3Z7",
    "sg:province":"QC",
    "sg:tags":[
        "consultant",
        "business"
    ],
    "wof:name":"Gestion Sur Mesure Inc",
    "wof:placetype":"venue"
},
  "geometry": {"coordinates":[-73.80991363530001,45.625202179],"type":"Point"}
}