{
  "type": "Feature",
  "properties": {
    "addr:full":"Leduc AB T9E 6V4",
    "addr:postcode":"t9e 6v4",
    "iso:country":"CA",
    "sg:city":"Leduc",
    "sg:classifiers":[
        {
            "category":"Insurance",
            "subcategory":"Insurance Agent",
            "type":"Services"
        }
    ],
    "sg:phone":"+1 780 980 9803",
    "sg:postcode":"T9E 6V4",
    "sg:province":"AB",
    "wof:name":"Shaw Insurance Ltd",
    "wof:placetype":"venue"
},
  "geometry": {"coordinates":[-113.41719055199999,53.3525848389],"type":"Point"}
}