{
  "type": "Feature",
  "properties": {
    "iso:country":"CA",
    "sg:address":"148 Waterloo St",
    "sg:city":"Woodstock",
    "sg:classifiers":[
        {
            "category":"Home & Garden",
            "subcategory":"Building Materials",
            "type":"Retail Goods"
        }
    ],
    "sg:phone":"+1 519 539 8479",
    "sg:postcode":"N4S 2T4",
    "sg:province":"ON",
    "sg:tags":[
        "door"
    ],
    "wof:name":"Woodstock Overhead Doors",
    "wof:placetype":"venue"
},
  "geometry": {"coordinates":[-80.7659454346,43.1234664917],"type":"Point"}
}