{
  "type": "Feature",
  "properties": {
    "addr:full":"North York ON M2J 1T5",
    "addr:postcode":"m2j 1t5",
    "iso:country":"CA",
    "sg:city":"North York",
    "sg:classifiers":[
        {
            "category":"Professional",
            "subcategory":"Accounting & Tax Preparation",
            "type":"Services"
        }
    ],
    "sg:phone":"+1 416 498 5995",
    "sg:postcode":"M2J 1T5",
    "sg:province":"ON",
    "sg:tags":[
        "accountant"
    ],
    "wof:name":"C A Svc Ltd",
    "wof:placetype":"venue"
},
  "geometry": {"coordinates":[-79.325676,43.773602],"type":"Point"}
}