{
  "type": "Feature",
  "properties": {
    "addr:full":"6534 Boul Des Mille-Iles Laval QC H7B 1B6",
    "addr:housenumber":"6534",
    "addr:postcode":"h7b 1b6",
    "addr:street":"Boul Des Mille-Iles",
    "iso:country":"CA",
    "sg:address":"6534 Boul Des Mille-Iles",
    "sg:city":"Laval",
    "sg:classifiers":[
        {
            "category":"Building & Trades",
            "subcategory":"Construction",
            "type":"Services"
        }
    ],
    "sg:phone":"+1 450 666 6394",
    "sg:postcode":"H7B 1B6",
    "sg:province":"QC",
    "sg:tags":[
        "excavating",
        "contractor"
    ],
    "wof:name":"Luc Meunier Excavation Ltee",
    "wof:placetype":"venue"
},
  "geometry": {"coordinates":[-73.63009599999999,45.688095],"type":"Point"}
}