{
  "type": "Feature",
  "properties": {
    "addr:full":"Main St Boyle AB T0A 0M0",
    "addr:postcode":"t0a 0m0",
    "addr:street":"Main St",
    "iso:country":"CA",
    "sg:address":"Main St",
    "sg:city":"Boyle",
    "sg:classifiers":[
        {
            "category":"Social Services",
            "type":"Services"
        }
    ],
    "sg:phone":"+1 780 689 3741",
    "sg:postcode":"T0A 0M0",
    "sg:province":"AB",
    "sg:tags":[
        "organization",
        "welfare"
    ],
    "wof:name":"Family & Community Support Svc",
    "wof:placetype":"venue"
},
  "geometry": {"coordinates":[-112.804474,54.587303],"type":"Point"}
}