{
  "type": "Feature",
  "properties": {
    "addr:full":"2595 Barnet Hwy Coquitlam BC V3E 1K9",
    "addr:housenumber":"2595",
    "addr:postcode":"v3e 1k9",
    "addr:street":"Barnet Hwy",
    "iso:country":"CA",
    "sg:address":"2595 Barnet Hwy",
    "sg:city":"Coquitlam",
    "sg:classifiers":[
        {
            "category":"Autos & Motor Vehicles",
            "subcategory":"Automobile Sales",
            "type":"Retail Goods"
        }
    ],
    "sg:phone":"+1 604 464 3941",
    "sg:postcode":"V3E 1K9",
    "sg:province":"BC",
    "sg:tags":[
        "car",
        "dealer"
    ],
    "wof:name":"Eagle Ridge Pontiac Buick Gmc",
    "wof:placetype":"venue"
},
  "geometry": {"coordinates":[-122.816902161,49.2779884338],"type":"Point"}
}