{
  "type": "Feature",
  "properties": {
    "iso:country":"CA",
    "sg:address":"2356 Gottingen St",
    "sg:city":"Halifax",
    "sg:classifiers":[
        {
            "category":"Personal",
            "subcategory":"Barber",
            "type":"Services"
        }
    ],
    "sg:phone":"+1 902 422 0810",
    "sg:postcode":"B3K 3B9",
    "sg:province":"NS",
    "wof:name":"Up Close Barbershop",
    "wof:placetype":"venue"
},
  "geometry": {"coordinates":[-63.5875205994,44.6546897888],"type":"Point"}
}