{
  "type": "Feature",
  "properties": {
    "addr:full":"9 Maitland St Port Hope ON L1A 4H6",
    "addr:housenumber":"9",
    "addr:postcode":"l1a 4h6",
    "addr:street":"Maitland St",
    "iso:country":"CA",
    "sg:address":"9 Maitland St",
    "sg:city":"Port Hope",
    "sg:classifiers":[
        {
            "category":"Retail",
            "subcategory":"Auto Repair",
            "type":"Services"
        }
    ],
    "sg:phone":"+1 905 885 7063",
    "sg:postcode":"L1A 4H6",
    "sg:province":"ON",
    "sg:tags":[
        "repairing",
        "automobile"
    ],
    "wof:name":"Dayman Automotive",
    "wof:placetype":"venue"
},
  "geometry": {"coordinates":[-78.2941207886,43.9523582458],"type":"Point"}
}