{
  "type": "Feature",
  "properties": {
    "addr:full":"32 Charing Rd Nepean ON K2G 0Z5",
    "addr:housenumber":"32",
    "addr:postcode":"k2g 0z5",
    "addr:street":"Charing Rd",
    "iso:country":"CA",
    "sg:address":"32 Charing Rd",
    "sg:city":"Nepean",
    "sg:classifiers":[
        {
            "category":"Professional",
            "subcategory":"Management & Consulting",
            "type":"Services"
        }
    ],
    "sg:phone":"+1 613 727 1448",
    "sg:postcode":"K2G 0Z5",
    "sg:province":"ON",
    "sg:tags":[
        "consultant",
        "business"
    ],
    "wof:name":"R D Chuchryk & Assoc",
    "wof:placetype":"venue"
},
  "geometry": {"coordinates":[-75.76514400000001,45.331104],"type":"Point"}
}