{
  "type": "Feature",
  "properties": {
    "addr:full":"575 Main St Montague PE C0A 1R0",
    "addr:housenumber":"575",
    "addr:postcode":"c0a 1r0",
    "addr:street":"Main St",
    "iso:country":"CA",
    "sg:address":"575 Main St",
    "sg:city":"Montague",
    "sg:classifiers":[
        {
            "category":"Autos & Motor Vehicles",
            "subcategory":"Fuel & Gas Station",
            "type":"Retail Goods"
        }
    ],
    "sg:phone":"+1 902 838 2103",
    "sg:postcode":"C0A 1R0",
    "sg:province":"PE",
    "sg:tags":[
        "convenience",
        "oil",
        "store"
    ],
    "wof:name":"Montague Esso Convenience",
    "wof:placetype":"venue"
},
  "geometry": {"coordinates":[-62.645699,46.163395],"type":"Point"}
}