{
  "type": "Feature",
  "properties": {
    "addr:full":"802 Boul Decarie Saint-Laurent QC H4L 3L9",
    "addr:housenumber":"802",
    "addr:postcode":"h4l 3l9",
    "addr:street":"Boul Decarie",
    "iso:country":"CA",
    "sg:address":"802 Boul Decarie",
    "sg:city":"Saint-Laurent",
    "sg:classifiers":[
        {
            "category":"Shopping",
            "subcategory":"Pharmacy",
            "type":"Retail Goods"
        }
    ],
    "sg:phone":"+1 514 747 3521",
    "sg:postcode":"H4L 3L9",
    "sg:province":"QC",
    "wof:name":"Jean Coutu",
    "wof:placetype":"venue"
},
  "geometry": {"coordinates":[-73.6787643433,45.5114936829],"type":"Point"}
}