{
  "type": "Feature",
  "properties": {
    "addr:full":"426 Gough Rd Kapuskasing ON P5N 2X7",
    "addr:housenumber":"426",
    "addr:postcode":"p5n 2x7",
    "addr:street":"Gough Rd",
    "iso:country":"CA",
    "sg:address":"426 Gough Rd",
    "sg:city":"Kapuskasing",
    "sg:classifiers":[
        {
            "category":"Building & Trades",
            "subcategory":"Construction",
            "type":"Services"
        }
    ],
    "sg:phone":"+1 705 335 2490",
    "sg:postcode":"P5N 2X7",
    "sg:province":"ON",
    "sg:tags":[
        "excavating",
        "contractor",
        "general"
    ],
    "wof:name":"Maurice Lebrun Contracting",
    "wof:placetype":"venue"
},
  "geometry": {"coordinates":[-82.361267,49.391682],"type":"Point"}
}