{
  "type": "Feature",
  "properties": {
    "addr:full":"40 Bethridge Rd Etobicoke ON M9W 1N1",
    "addr:housenumber":"40",
    "addr:postcode":"m9w 1n1",
    "addr:street":"Bethridge Rd",
    "iso:country":"CA",
    "sg:address":"40 Bethridge Rd",
    "sg:city":"Etobicoke",
    "sg:classifiers":[
        {
            "category":"Manufacturing",
            "subcategory":"Tools & Machinery",
            "type":"Manufacturing & Wholesale Goods"
        }
    ],
    "sg:phone":"+1 416 636 0861",
    "sg:postcode":"M9W 1N1",
    "sg:province":"ON",
    "sg:tags":[
        "disposal",
        "garbage",
        "equipment"
    ],
    "wof:name":"Metro Compactor Svc",
    "wof:placetype":"venue"
},
  "geometry": {"coordinates":[-79.57010699999999,43.70858],"type":"Point"}
}