{
  "type": "Feature",
  "properties": {
    "addr:full":"11408 Palfrey Dr Coldstream BC V1B 2B1",
    "addr:housenumber":"11408",
    "addr:postcode":"bc v1b 2b1",
    "addr:street":"Palfrey Dr",
    "iso:country":"CA",
    "sg:address":"11408 Palfrey Dr",
    "sg:city":"Coldstream",
    "sg:classifiers":[
        {
            "category":"Personal",
            "type":"Services"
        }
    ],
    "sg:phone":"+1 250 260 3848",
    "sg:postcode":"V1B 2B1",
    "sg:province":"BC",
    "sg:tags":[
        "therapist",
        "massage"
    ],
    "wof:name":"Kalamalka Therapeutic Massage",
    "wof:placetype":"venue"
},
  "geometry": {"coordinates":[-119.25051116900001,50.2166557312],"type":"Point"}
}