{
  "type": "Feature",
  "properties": {
    "addr:full":"220 Rue Lajoie S Joliette QC J6E 5L2",
    "addr:housenumber":"220",
    "addr:postcode":"j6e 5l2",
    "addr:street":"Rue Lajoie S",
    "iso:country":"CA",
    "sg:address":"220 Rue Lajoie S",
    "sg:city":"Joliette",
    "sg:classifiers":[
        {
            "category":"Social Services",
            "type":"Services"
        }
    ],
    "sg:phone":"+1 450 759 6848",
    "sg:postcode":"J6E 5L2",
    "sg:province":"QC",
    "sg:tags":[
        "info",
        "drug",
        "abuse",
        "treatment",
        "welfare",
        "organization",
        "addiction"
    ],
    "wof:name":"Unite Point DE Depart Inc",
    "wof:placetype":"venue"
},
  "geometry": {"coordinates":[-73.4382553101,46.022102356],"type":"Point"}
}