{
  "type": "Feature",
  "properties": {
    "addr:full":"150 Inkster Garden Dr Winnipeg MB R2R 2R8",
    "addr:housenumber":"150",
    "addr:postcode":"r2r 2r8",
    "addr:street":"Inkster Garden Dr",
    "iso:country":"CA",
    "sg:address":"150 Inkster Garden Dr",
    "sg:city":"Winnipeg",
    "sg:classifiers":[
        {
            "category":"Education",
            "subcategory":"School",
            "type":"Public Place"
        }
    ],
    "sg:phone":"+1 204 694 6755",
    "sg:postcode":"R2R 2R8",
    "sg:province":"MB",
    "wof:name":"Meadows West School",
    "wof:placetype":"venue"
},
  "geometry": {"coordinates":[-97.198257,49.949474],"type":"Point"}
}