{
  "type": "Feature",
  "properties": {
    "addr:full":"17653 112 St NW Edmonton AB T5X 5Z2",
    "addr:housenumber":"17653",
    "addr:postcode":"t5x 5z2",
    "addr:street":"112 St Nw",
    "iso:country":"CA",
    "sg:address":"17653 112 St NW",
    "sg:city":"Edmonton",
    "sg:classifiers":[
        {
            "category":"Organizations",
            "subcategory":"Religious Organization",
            "type":"Services"
        }
    ],
    "sg:phone":"+1 780 456 5399",
    "sg:postcode":"T5X 5Z2",
    "sg:province":"AB",
    "sg:tags":[
        "church"
    ],
    "wof:name":"St Charles Roman Catholic Chr",
    "wof:placetype":"venue"
},
  "geometry": {"coordinates":[-113.51637268099999,53.6405296326],"type":"Point"}
}