{
  "type": "Feature",
  "properties": {
    "addr:full":"Highway 11 & 71 W Emo ON P0W 1E0",
    "addr:postcode":"p0w 1e0",
    "addr:street":"Highway 11 & 71 W Emo",
    "iso:country":"CA",
    "sg:address":"Highway 11 & 71 W",
    "sg:city":"Emo",
    "sg:classifiers":[
        {
            "category":"Home & Garden",
            "subcategory":"Garden Supply",
            "type":"Retail Goods"
        }
    ],
    "sg:phone":"+1 807 482 2833",
    "sg:postcode":"P0W 1E0",
    "sg:province":"ON",
    "sg:tags":[
        "farm",
        "equipment",
        "lawn"
    ],
    "wof:name":"DE Gagne Equipment",
    "wof:placetype":"venue"
},
  "geometry": {"coordinates":[-93.838852,48.632538],"type":"Point"}
}