{
  "type": "Feature",
  "properties": {
    "addr:full":"4891 Manning Rd Maidstone ON N0R 1K0",
    "addr:housenumber":"4891",
    "addr:postcode":"n0r 1k0",
    "addr:street":"Manning Rd",
    "iso:country":"CA",
    "sg:address":"4891 Manning Rd",
    "sg:city":"Maidstone",
    "sg:classifiers":[
        {
            "category":"Retail",
            "subcategory":"Auto Repair",
            "type":"Services"
        }
    ],
    "sg:phone":"+1 519 979 5421",
    "sg:postcode":"N0R 1K0",
    "sg:province":"ON",
    "sg:tags":[
        "wrecker"
    ],
    "wof:name":"Cts Coxon's",
    "wof:placetype":"venue"
},
  "geometry": {"coordinates":[-82.8748168945,42.2194099426],"type":"Point"}
}