{
  "type": "Feature",
  "properties": {
    "addr:full":"2200 Rue Du Moulin Quebec QC G2B 2C1",
    "addr:housenumber":"2200",
    "addr:postcode":"g2b 2c1",
    "addr:street":"Rue Du Moulin",
    "iso:country":"CA",
    "sg:address":"2200 Rue Du Moulin",
    "sg:city":"Quebec",
    "sg:classifiers":[
        {
            "category":"Personal",
            "subcategory":"Beauty Salon",
            "type":"Services"
        }
    ],
    "sg:phone":"+1 418 843 8046",
    "sg:postcode":"G2B 2C1",
    "sg:province":"QC",
    "wof:name":"Salon Jackie Enr",
    "wof:placetype":"venue"
},
  "geometry": {"coordinates":[-71.331474,46.852119],"type":"Point"}
}