{
  "type": "Feature",
  "properties": {
    "iso:country":"CA",
    "sg:city":"Milton",
    "sg:classifiers":[
        {
            "category":"Professional",
            "subcategory":"Accounting & Tax Preparation",
            "type":"Services"
        }
    ],
    "sg:phone":"+1 905 878 2168",
    "sg:postcode":"L9T 1N7",
    "sg:province":"ON",
    "sg:tags":[
        "return",
        "filing"
    ],
    "wof:name":"Professional Computer Solution",
    "wof:placetype":"venue"
},
  "geometry": {"coordinates":[-79.8836517334,43.5128936768],"type":"Point"}
}