{
  "type": "Feature",
  "properties": {
    "addr:full":"4360 Rue Circle Pierrefonds QC H9H 2G9",
    "addr:housenumber":"4360",
    "addr:postcode":"h9h 2g9",
    "addr:street":"Rue Circle",
    "iso:country":"CA",
    "sg:address":"4360 Rue Circle",
    "sg:city":"Pierrefonds",
    "sg:classifiers":[
        {
            "category":"Professional",
            "subcategory":"Computer Services",
            "type":"Services"
        }
    ],
    "sg:phone":"+1 514 696 1234",
    "sg:postcode":"H9H 2G9",
    "sg:province":"QC",
    "sg:tags":[
        "information",
        "system",
        "consultant"
    ],
    "wof:name":"Elisoft",
    "wof:placetype":"venue"
},
  "geometry": {"coordinates":[-73.85437,45.478447],"type":"Point"}
}