{
  "type": "Feature",
  "properties": {
    "addr:full":"36660 83rd St Oliver BC V0H 1T0",
    "addr:housenumber":"36660",
    "addr:postcode":"bc v0h 1t0",
    "addr:street":"83Rd St",
    "iso:country":"CA",
    "sg:address":"36660 83rd St",
    "sg:city":"Oliver",
    "sg:classifiers":[
        {
            "category":"Shopping",
            "type":"Retail Goods"
        }
    ],
    "sg:phone":"+1 250 498 6595",
    "sg:postcode":"V0H 1T0",
    "sg:province":"BC",
    "sg:tags":[
        "plumbing",
        "water",
        "contractor"
    ],
    "wof:name":"Watchel Plumbing & Heating Ltd",
    "wof:placetype":"venue"
},
  "geometry": {"coordinates":[-119.544250488,49.189540863],"type":"Point"}
}