{
  "type": "Feature",
  "properties": {
    "addr:full":"528 Av Lariviere Rouyn-Noranda QC J9X 4J2",
    "addr:postcode":"j9x 4j2",
    "addr:street":"528 Av Lariviere",
    "iso:country":"CA",
    "sg:address":"528 Av Lariviere",
    "sg:city":"Rouyn-Noranda",
    "sg:classifiers":[
        {
            "category":"Manufacturing",
            "subcategory":"Printing",
            "type":"Manufacturing & Wholesale Goods"
        }
    ],
    "sg:phone":"+1 819 762 7628",
    "sg:postcode":"J9X 4J2",
    "sg:province":"QC",
    "sg:tags":[
        "screen"
    ],
    "wof:name":"Pro-Image",
    "wof:placetype":"venue"
},
  "geometry": {"coordinates":[-79.0130996704,48.2281951904],"type":"Point"}
}