{
  "type": "Feature",
  "properties": {
    "iso:country":"CA",
    "sg:address":"19 Holiday Dr",
    "sg:city":"Brantford",
    "sg:classifiers":[
        {
            "category":"Travel",
            "subcategory":"Hotels & Motels",
            "type":"Entertainment"
        }
    ],
    "sg:phone":"+1 519 753 8651",
    "sg:postcode":"N3R 7J4",
    "sg:province":"ON",
    "wof:name":"Best Western Brant Park Inn",
    "wof:placetype":"venue"
},
  "geometry": {"coordinates":[-80.241737,43.162998],"type":"Point"}
}