{
  "type": "Feature",
  "properties": {
    "addr:full":"327 Bronte St S Milton ON L9T 4A4",
    "addr:housenumber":"327",
    "addr:postcode":"l9t 4a4",
    "addr:street":"Bronte St S",
    "iso:country":"CA",
    "sg:address":"327 Bronte St S",
    "sg:city":"Milton",
    "sg:classifiers":[
        {
            "category":"Health Services",
            "subcategory":"Optometrist",
            "type":"Services"
        }
    ],
    "sg:phone":"+1 905 876 4649",
    "sg:postcode":"L9T 4A4",
    "sg:province":"ON",
    "wof:name":"Jany, Susan E OD",
    "wof:placetype":"venue"
},
  "geometry": {"coordinates":[-79.87912,43.502018],"type":"Point"}
}