{
  "type": "Feature",
  "properties": {
    "addr:full":"309 19 St NW Calgary AB T2N 2J2",
    "addr:housenumber":"19",
    "addr:postcode":"t2n 2j2",
    "addr:street":"309;St Nw",
    "iso:country":"CA",
    "sg:address":"309 19 St NW",
    "sg:city":"Calgary",
    "sg:classifiers":[
        {
            "category":"Retail",
            "subcategory":"Laundry & Dry Cleaning",
            "type":"Services"
        }
    ],
    "sg:phone":"+1 403 283 4123",
    "sg:postcode":"T2N 2J2",
    "sg:province":"AB",
    "sg:tags":[
        "cleaners"
    ],
    "wof:name":"Hi Neighbour Cleaners Ltd",
    "wof:placetype":"venue"
},
  "geometry": {"coordinates":[-114.105712891,51.0546455383],"type":"Point"}
}