{
  "type": "Feature",
  "properties": {
    "addr:full":"821 Rue Vercheres Longueuil QC J4K 2Y8",
    "addr:housenumber":"821",
    "addr:postcode":"j4k 2y8",
    "addr:street":"Rue Vercheres",
    "iso:country":"CA",
    "sg:address":"821 Rue Vercheres",
    "sg:city":"Longueuil",
    "sg:classifiers":[
        {
            "category":"Manufacturing",
            "subcategory":"Tools & Machinery",
            "type":"Manufacturing & Wholesale Goods"
        }
    ],
    "sg:phone":"+1 450 670 5860",
    "sg:postcode":"J4K 2Y8",
    "sg:province":"QC",
    "sg:tags":[
        "machine",
        "shop"
    ],
    "wof:name":"Atelier D'Usinage Lc Enrg",
    "wof:placetype":"venue"
},
  "geometry": {"coordinates":[-73.5108413696,45.5171012878],"type":"Point"}
}