{
  "type": "Feature",
  "properties": {
    "addr:full":"197 Leila Ave Winnipeg MB R2V 1L5",
    "addr:housenumber":"197",
    "addr:postcode":"r2v 1l5",
    "addr:street":"Leila Ave",
    "iso:country":"CA",
    "sg:address":"197 Leila Ave",
    "sg:city":"Winnipeg",
    "sg:classifiers":[
        {
            "category":"Shopping",
            "type":"Retail Goods"
        }
    ],
    "sg:phone":"+1 204 338 2083",
    "sg:postcode":"R2V 1L5",
    "sg:province":"MB",
    "sg:tags":[
        "trophy",
        "medal",
        "award"
    ],
    "wof:name":"First West Awards",
    "wof:placetype":"venue"
},
  "geometry": {"coordinates":[-97.11279296879999,49.9422531128],"type":"Point"}
}