{
  "type": "Feature",
  "properties": {
    "addr:full":"2393 Finch Ave W North York ON M9M 2W8",
    "addr:housenumber":"2393",
    "addr:postcode":"m9m 2w8",
    "addr:street":"Finch Ave W",
    "iso:country":"CA",
    "sg:address":"2393 Finch Ave W",
    "sg:city":"North York",
    "sg:classifiers":[
        {
            "category":"Banks & Credit Unions",
            "subcategory":"Bank",
            "type":"Services"
        }
    ],
    "sg:phone":"+1 416 744 6911",
    "sg:postcode":"M9M 2W8",
    "sg:province":"ON",
    "sg:tags":[
        "cashing",
        "check"
    ],
    "wof:name":"Cash Money Cheque Cashing",
    "wof:placetype":"venue"
},
  "geometry": {"coordinates":[-79.545967,43.751171],"type":"Point"}
}