{
  "type": "Feature",
  "properties": {
    "addr:full":"828 Dewdney Ave Regina SK S4N 0G7",
    "addr:housenumber":"828",
    "addr:postcode":"s4n 0g7",
    "addr:street":"Dewdney Ave",
    "iso:country":"CA",
    "sg:address":"828 Dewdney Ave",
    "sg:city":"Regina",
    "sg:classifiers":[
        {
            "category":"Retail",
            "subcategory":"Auto Repair",
            "type":"Services"
        }
    ],
    "sg:phone":"+1 306 347 0440",
    "sg:postcode":"S4N 0G7",
    "sg:province":"SK",
    "sg:tags":[
        "repairing",
        "automobile"
    ],
    "wof:name":"Cardinal Automotive",
    "wof:placetype":"venue"
},
  "geometry": {"coordinates":[-104.592933655,50.455280304],"type":"Point"}
}