{
  "type": "Feature",
  "properties": {
    "addr:full":"10413 79 Ave NW Edmonton AB T6E 1R7",
    "addr:housenumber":"10413",
    "addr:postcode":"t6e 1r7",
    "addr:street":"79 Ave Nw",
    "iso:country":"CA",
    "sg:address":"10413 79 Ave NW",
    "sg:city":"Edmonton",
    "sg:classifiers":[
        {
            "category":"Retail",
            "subcategory":"Auto Repair",
            "type":"Services"
        }
    ],
    "sg:phone":"+1 780 432 0182",
    "sg:postcode":"T6E 1R7",
    "sg:province":"AB",
    "sg:tags":[
        "repairing",
        "automobile"
    ],
    "wof:name":"A P Transmission Ltd",
    "wof:placetype":"venue"
},
  "geometry": {"coordinates":[-113.49826049799999,53.5149421692],"type":"Point"}
}