{
  "type": "Feature",
  "properties": {
    "addr:full":"5772 Cowrie St Sechelt BC V0N 3A0",
    "addr:housenumber":"5772",
    "addr:postcode":"v0n 3a0",
    "addr:street":"Cowrie St",
    "iso:country":"CA",
    "sg:address":"5772 Cowrie St",
    "sg:city":"Sechelt",
    "sg:classifiers":[
        {
            "category":"Real Estate",
            "subcategory":"Real Estate Agent",
            "type":"Services"
        }
    ],
    "sg:phone":"+1 604 885 5017",
    "sg:postcode":"V0N 3A0",
    "sg:province":"BC",
    "sg:tags":[
        "notary"
    ],
    "wof:name":"Parker, Tracy D",
    "wof:placetype":"venue"
},
  "geometry": {"coordinates":[-123.76120758099999,49.4725456238],"type":"Point"}
}