{
  "type": "Feature",
  "properties": {
    "addr:full":"1926 Cummings Rd Courtenay BC V9N 9G6",
    "addr:housenumber":"1926",
    "addr:postcode":"v9n 9g6",
    "addr:street":"Cummings Rd",
    "iso:country":"CA",
    "sg:address":"1926 Cummings Rd",
    "sg:city":"Courtenay",
    "sg:classifiers":[
        {
            "category":"Health Services",
            "subcategory":"Nursing And Care Facility",
            "type":"Services"
        }
    ],
    "sg:phone":"+1 250 897 0075",
    "sg:postcode":"V9N 9G6",
    "sg:province":"BC",
    "sg:tags":[
        "home",
        "convalescent"
    ],
    "wof:name":"Cummings Home",
    "wof:placetype":"venue"
},
  "geometry": {"coordinates":[-124.99314099999999,49.686722],"type":"Point"}
}