{
  "type": "Feature",
  "properties": {
    "addr:full":"8573 132 St Surrey BC V3W 4N8",
    "addr:housenumber":"8573",
    "addr:postcode":"v3w 4n8",
    "addr:street":"132 St",
    "iso:country":"CA",
    "sg:address":"8573 132 St",
    "sg:city":"Surrey",
    "sg:classifiers":[
        {
            "category":"Home & Garden",
            "subcategory":"Carpets & Floor Coverings",
            "type":"Retail Goods"
        }
    ],
    "sg:phone":"+1 604 590 3394",
    "sg:postcode":"V3W 4N8",
    "sg:province":"BC",
    "sg:tags":[
        "dealer",
        "rug"
    ],
    "wof:name":"Supreme Flooring Ltd",
    "wof:placetype":"venue"
},
  "geometry": {"coordinates":[-122.85700199999999,49.158775],"type":"Point"}
}