{
  "type": "Feature",
  "properties": {
    "iso:country":"CA",
    "sg:city":"Barrie",
    "sg:classifiers":[
        {
            "category":"Professional",
            "subcategory":"Credit Reporting & Collection",
            "type":"Services"
        }
    ],
    "sg:phone":"+1 705 734 1400",
    "sg:postcode":"L4M 6H1",
    "sg:province":"ON",
    "sg:tags":[
        "agency"
    ],
    "wof:name":"Central Credit Control",
    "wof:placetype":"venue"
},
  "geometry": {"coordinates":[-79.683921814,44.3894729614],"type":"Point"}
}