{
  "type": "Feature",
  "properties": {
    "addr:full":"4805 Rue Des Ardennes Montreal-Nord QC H1H 1N6",
    "addr:housenumber":"4805",
    "addr:postcode":"h1h 1n6",
    "addr:street":"Rue Des Ardennes",
    "iso:country":"CA",
    "sg:address":"4805 Rue Des Ardennes",
    "sg:city":"Montreal-Nord",
    "sg:classifiers":[
        {
            "category":"Personal",
            "subcategory":"Beauty Salon",
            "type":"Services"
        }
    ],
    "sg:phone":"+1 514 323 6974",
    "sg:postcode":"H1H 1N6",
    "sg:province":"QC",
    "wof:name":"Salon Miracle Enr",
    "wof:placetype":"venue"
},
  "geometry": {"coordinates":[-73.6361618042,45.6019325256],"type":"Point"}
}