{
  "type": "Feature",
  "properties": {
    "addr:full":"2405 Marine Dr West Vancouver BC V7V 1L3",
    "addr:housenumber":"2405",
    "addr:postcode":"v7v 1l3",
    "addr:street":"Marine Dr",
    "iso:country":"CA",
    "sg:address":"2405 Marine Dr",
    "sg:city":"West Vancouver",
    "sg:classifiers":[
        {
            "category":"Travel",
            "subcategory":"Travel Agent",
            "type":"Entertainment"
        }
    ],
    "sg:phone":"+1 604 922 9344",
    "sg:postcode":"V7V 1L3",
    "sg:province":"BC",
    "sg:tags":[
        "agency",
        "bureau"
    ],
    "wof:name":"Travel Time Intl",
    "wof:placetype":"venue"
},
  "geometry": {"coordinates":[-123.17955000000001,49.334396],"type":"Point"}
}