{
  "type": "Feature",
  "properties": {
    "addr:full":"209 Broughdale Ave London ON N6A 2K8",
    "addr:housenumber":"209",
    "addr:postcode":"n6a 2k8",
    "addr:street":"Broughdale Ave",
    "iso:country":"CA",
    "sg:address":"209 Broughdale Ave",
    "sg:city":"London",
    "sg:classifiers":[
        {
            "category":"Health Services",
            "subcategory":"Doctor",
            "type":"Services"
        }
    ],
    "sg:phone":"+1 519 439 2211",
    "sg:postcode":"N6A 2K8",
    "sg:province":"ON",
    "sg:tags":[
        "physician",
        "surgeon"
    ],
    "wof:name":"Shaheed, W A MD",
    "wof:placetype":"venue"
},
  "geometry": {"coordinates":[-81.25992599999999,43.007973],"type":"Point"}
}