{
  "type": "Feature",
  "properties": {
    "addr:full":"55 Ch Langlois-Tougas Pike River QC J0J 1P0",
    "addr:housenumber":"55",
    "addr:postcode":"j0j 1p0",
    "addr:street":"Ch Langlois-Tougas",
    "iso:country":"CA",
    "sg:address":"55 Ch Langlois-Tougas",
    "sg:city":"Pike River",
    "sg:classifiers":[
        {
            "category":"Autos & Motor Vehicles",
            "subcategory":"Boat Sales",
            "type":"Retail Goods"
        }
    ],
    "sg:phone":"+1 450 248 4318",
    "sg:postcode":"J0J 1P0",
    "sg:province":"QC",
    "sg:tags":[
        "dealer"
    ],
    "wof:name":"Daniel Marina Langlois Inc",
    "wof:placetype":"venue"
},
  "geometry": {"coordinates":[-73.0684051514,45.1209335327],"type":"Point"}
}