{
  "type": "Feature",
  "properties": {
    "addr:full":"Sutton West ON L0E 1R0",
    "addr:postcode":"l0e 1r0",
    "iso:country":"CA",
    "sg:city":"Sutton West",
    "sg:classifiers":[
        {
            "category":"Building & Trades",
            "subcategory":"Construction",
            "type":"Services"
        }
    ],
    "sg:phone":"+1 905 722 8868",
    "sg:postcode":"L0E 1R0",
    "sg:province":"ON",
    "sg:tags":[
        "general",
        "contractor"
    ],
    "wof:name":"Gtk Renovations",
    "wof:placetype":"venue"
},
  "geometry": {"coordinates":[-79.355057,44.306957],"type":"Point"}
}