{
  "type": "Feature",
  "properties": {
    "addr:full":"Hwy 49 Preeceville SK S0A 3B0",
    "addr:postcode":"s0a 3b0",
    "addr:street":"Hwy 49",
    "iso:country":"CA",
    "sg:address":"Hwy 49",
    "sg:city":"Preeceville",
    "sg:classifiers":[
        {
            "category":"Restaurant",
            "type":"Food & Drink"
        }
    ],
    "sg:phone":"+1 306 547 3333",
    "sg:postcode":"S0A 3B0",
    "sg:province":"SK",
    "wof:name":"Chris' Place",
    "wof:placetype":"venue"
},
  "geometry": {"coordinates":[-102.666878,51.954235],"type":"Point"}
}