{
  "type": "Feature",
  "properties": {
    "iso:country":"CA",
    "sg:city":"Milton",
    "sg:classifiers":[
        {
            "category":"Retail",
            "subcategory":"Repair Shop",
            "type":"Services"
        }
    ],
    "sg:phone":"+1 905 878 7111",
    "sg:postcode":"L9T 5A9",
    "sg:province":"ON",
    "sg:tags":[
        "welding"
    ],
    "wof:name":"High Arc Welding",
    "wof:placetype":"venue"
},
  "geometry": {"coordinates":[-79.870895,43.524708],"type":"Point"}
}