{
  "type": "Feature",
  "properties": {
    "addr:full":"1285 Av Des Gouverneurs Sillery QC G1T 2G4",
    "addr:housenumber":"1285",
    "addr:postcode":"g1t 2g4",
    "addr:street":"Av Des Gouverneurs",
    "iso:country":"CA",
    "sg:address":"1285 Av Des Gouverneurs",
    "sg:city":"Sillery",
    "sg:classifiers":[
        {
            "category":"Real Estate",
            "subcategory":"Real Estate Agent",
            "type":"Services"
        }
    ],
    "sg:phone":"+1 418 527 5113",
    "sg:postcode":"G1T 2G4",
    "sg:province":"QC",
    "wof:name":"Royal Trust",
    "wof:placetype":"venue"
},
  "geometry": {"coordinates":[-71.2619552612,46.7761230469],"type":"Point"}
}