{
  "type": "Feature",
  "properties": {
    "iso:country":"CA",
    "sg:address":"269 Windmill Rd",
    "sg:city":"Dartmouth",
    "sg:classifiers":[
        {
            "category":"Food & Beverages",
            "subcategory":"Groceries & Convenience Stores",
            "type":"Retail Goods"
        }
    ],
    "sg:phone":"+1 902 461 9220",
    "sg:postcode":"B3A 1G5",
    "sg:province":"NS",
    "sg:tags":[
        "grocer"
    ],
    "wof:name":"One Stop Shop",
    "wof:placetype":"venue"
},
  "geometry": {"coordinates":[-63.5903625488,44.6746368408],"type":"Point"}
}