{
  "type": "Feature",
  "properties": {
    "addr:full":"Saint-Jean-Sur-Richelieu QC J3B 5K9",
    "addr:postcode":"j3b 5k9",
    "iso:country":"CA",
    "sg:city":"Saint-Jean-Sur-Richelieu",
    "sg:classifiers":[
        {
            "category":"Health Services",
            "subcategory":"Doctor",
            "type":"Services"
        }
    ],
    "sg:phone":"+1 450 349 0145",
    "sg:postcode":"J3B 5K9",
    "sg:province":"QC",
    "sg:tags":[
        "dentist"
    ],
    "wof:name":"Clinique Dentaire",
    "wof:placetype":"venue"
},
  "geometry": {"coordinates":[-73.26519012449999,45.3100738525],"type":"Point"}
}