{
  "type": "Feature",
  "properties": {
    "addr:full":"North York ON M3N 2V6",
    "addr:postcode":"m3n 2v6",
    "iso:country":"CA",
    "sg:city":"North York",
    "sg:classifiers":[
        {
            "category":"Shopping",
            "subcategory":"Pharmacy",
            "type":"Retail Goods"
        }
    ],
    "sg:phone":"+1 416 746 2044",
    "sg:postcode":"M3N 2V6",
    "sg:province":"ON",
    "wof:name":"Westview Pharmacists & Chemist",
    "wof:placetype":"venue"
},
  "geometry": {"coordinates":[-79.525398,43.755466],"type":"Point"}
}