{
  "type": "Feature",
  "properties": {
    "addr:full":"Brampton ON L6W 3P8",
    "addr:postcode":"l6w 3p8",
    "iso:country":"CA",
    "sg:city":"Brampton",
    "sg:classifiers":[
        {
            "category":"Health Services",
            "subcategory":"Doctor",
            "type":"Services"
        }
    ],
    "sg:phone":"+1 905 453 8081",
    "sg:postcode":"L6W 3P8",
    "sg:province":"ON",
    "sg:tags":[
        "dentist"
    ],
    "wof:name":"New Breath",
    "wof:placetype":"venue"
},
  "geometry": {"coordinates":[-79.75386,43.691452],"type":"Point"}
}