{
  "type": "Feature",
  "properties": {
    "iso:country":"CA",
    "sg:address":"11000 Av Mackay",
    "sg:city":"Montreal-Nord",
    "sg:classifiers":[
        {
            "category":"Building & Trades",
            "subcategory":"Plumbing",
            "type":"Services"
        }
    ],
    "sg:phone":"+1 514 325 1000",
    "sg:postcode":"H1H 5G2",
    "sg:province":"QC",
    "sg:tags":[
        "heating",
        "contractor"
    ],
    "wof:name":"Dominair Inc",
    "wof:placetype":"venue"
},
  "geometry": {"coordinates":[-73.651581,45.586094],"type":"Point"}
}