{
  "type": "Feature",
  "properties": {
    "iso:country":"CA",
    "sg:address":"1105 Queen St E",
    "sg:city":"Brampton",
    "sg:classifiers":[
        {
            "category":"Social Services",
            "type":"Services"
        }
    ],
    "sg:phone":"+1 905 457 3611",
    "sg:postcode":"L6T 4E2",
    "sg:province":"ON",
    "sg:tags":[
        "organization",
        "welfare"
    ],
    "wof:name":"St Leonard's House",
    "wof:placetype":"venue"
},
  "geometry": {"coordinates":[-79.734062,43.709061],"type":"Point"}
}