{
  "type": "Feature",
  "properties": {
    "addr:full":"1105 Queen St E Brampton ON L6T 4E2",
    "addr:housenumber":"1105",
    "addr:postcode":"l6t 4e2",
    "addr:street":"Queen St E",
    "iso:country":"CA",
    "sg:address":"1105 Queen St E",
    "sg:city":"Brampton",
    "sg:classifiers":[
        {
            "category":"Social Services",
            "type":"Services"
        }
    ],
    "sg:phone":"+1 905 457 3611",
    "sg:postcode":"L6T 4E2",
    "sg:province":"ON",
    "sg:tags":[
        "organization",
        "welfare"
    ],
    "wof:name":"St Leonard's House",
    "wof:placetype":"venue"
},
  "geometry": {"coordinates":[-79.73406199999999,43.709061],"type":"Point"}
}