{
  "type": "Feature",
  "properties": {
    "addr:full":"7554 Yonge St Thornhill ON L4J 1V8",
    "addr:housenumber":"7554",
    "addr:postcode":"l4j 1v8",
    "addr:street":"Yonge St",
    "iso:country":"CA",
    "sg:address":"7554 Yonge St",
    "sg:city":"Thornhill",
    "sg:classifiers":[
        {
            "category":"Education",
            "subcategory":"School",
            "type":"Public Place"
        }
    ],
    "sg:phone":"+1 905 889 1566",
    "sg:postcode":"L4J 1V8",
    "sg:province":"ON",
    "wof:name":"Thornhill Public School",
    "wof:placetype":"venue"
},
  "geometry": {"coordinates":[-79.4233093262,43.8108825684],"type":"Point"}
}