{
  "type": "Feature",
  "properties": {
    "addr:full":"8480 Boul Saint-Laurent Montreal QC H2P 2M6",
    "addr:housenumber":"8480",
    "addr:postcode":"h2p 2m6",
    "addr:street":"Boul Saint-Laurent",
    "iso:country":"CA",
    "sg:address":"8480 Boul Saint-Laurent",
    "sg:city":"Montreal",
    "sg:classifiers":[
        {
            "category":"Manufacturing",
            "subcategory":"Food",
            "type":"Manufacturing & Wholesale Goods"
        }
    ],
    "sg:phone":"+1 514 381 5631",
    "sg:postcode":"H2P 2M6",
    "sg:province":"QC",
    "sg:tags":[
        "natural"
    ],
    "wof:name":"Rosell Institute Inc",
    "wof:placetype":"venue"
},
  "geometry": {"coordinates":[-73.63709299999999,45.54039],"type":"Point"}
}