{
  "type": "Feature",
  "properties": {
    "iso:country":"CA",
    "sg:address":"206 Main St",
    "sg:city":"Ailsa Craig",
    "sg:classifiers":[
        {
            "category":"Building & Trades",
            "subcategory":"Plumbing",
            "type":"Services"
        }
    ],
    "sg:phone":"+1 519 293 3239",
    "sg:postcode":"N0M 1A0",
    "sg:province":"ON",
    "sg:tags":[
        "heating",
        "contractor"
    ],
    "wof:name":"Robert Park Plumbing & Heating",
    "wof:placetype":"venue"
},
  "geometry": {"coordinates":[-81.53044128419999,43.1466445923],"type":"Point"}
}