{
  "type": "Feature",
  "properties": {
    "addr:full":"280 King St Spruce Grove AB T7X 3A2",
    "addr:housenumber":"280",
    "addr:postcode":"t7x 3a2",
    "addr:street":"King St",
    "iso:country":"CA",
    "sg:address":"280 King St",
    "sg:city":"Spruce Grove",
    "sg:classifiers":[
        {
            "category":"Food & Beverages",
            "subcategory":"Specialty",
            "type":"Retail Goods"
        }
    ],
    "sg:phone":"+1 780 962 1313",
    "sg:postcode":"T7X 3A2",
    "sg:province":"AB",
    "sg:tags":[
        "health",
        "diet"
    ],
    "wof:name":"Health 4U",
    "wof:placetype":"venue"
},
  "geometry": {"coordinates":[-113.90031399999999,53.543839],"type":"Point"}
}