{
  "type": "Feature",
  "properties": {
    "iso:country":"CA",
    "sg:address":"208 Newport Dr",
    "sg:city":"Port Moody",
    "sg:classifiers":[
        {
            "category":"Personal",
            "subcategory":"Beauty Salon",
            "type":"Services"
        }
    ],
    "sg:phone":"+1 604 461 5278",
    "sg:postcode":"V3H 5B9",
    "sg:province":"BC",
    "wof:name":"Kast Hair & Esthetics Studio",
    "wof:placetype":"venue"
},
  "geometry": {"coordinates":[-122.82711792000001,49.2823524475],"type":"Point"}
}