{
  "type": "Feature",
  "properties": {
    "addr:full":"167 Main St W Shelburne ON L0N 1S0",
    "addr:housenumber":"167",
    "addr:postcode":"l0n 1s0",
    "addr:street":"Main St W",
    "iso:country":"CA",
    "sg:address":"167 Main St W",
    "sg:city":"Shelburne",
    "sg:classifiers":[
        {
            "category":"Manufacturing",
            "subcategory":"Printing",
            "type":"Manufacturing & Wholesale Goods"
        }
    ],
    "sg:phone":"+1 519 925 2832",
    "sg:postcode":"L0N 1S0",
    "sg:province":"ON",
    "sg:tags":[
        "newspaper"
    ],
    "wof:name":"Shelburne Free Press",
    "wof:placetype":"venue"
},
  "geometry": {"coordinates":[-80.20648199999999,44.07777],"type":"Point"}
}