{
  "type": "Feature",
  "properties": {
    "addr:full":"2633 Montrose Ave Abbotsford BC V2S 3T5",
    "addr:housenumber":"2633",
    "addr:postcode":"v2s 3t5",
    "addr:street":"Montrose Ave",
    "iso:country":"CA",
    "sg:address":"2633 Montrose Ave",
    "sg:city":"Abbotsford",
    "sg:classifiers":[
        {
            "category":"Personal",
            "subcategory":"Barber",
            "type":"Services"
        }
    ],
    "sg:phone":"+1 604 853 4941",
    "sg:postcode":"V2S 3T5",
    "sg:province":"BC",
    "wof:name":"Jakes Hairstyling",
    "wof:placetype":"venue"
},
  "geometry": {"coordinates":[-122.290481567,49.049785614],"type":"Point"}
}