{
  "type": "Feature",
  "properties": {
    "addr:full":"285 12th St Hanover ON N4N 1V4",
    "addr:housenumber":"285",
    "addr:postcode":"n4n 1v4",
    "addr:street":"12Th St",
    "iso:country":"CA",
    "sg:address":"285 12th St",
    "sg:city":"Hanover",
    "sg:classifiers":[
        {
            "category":"Health Services",
            "subcategory":"Chiropractor",
            "type":"Services"
        }
    ],
    "sg:phone":"+1 519 364 3020",
    "sg:postcode":"N4N 1V4",
    "sg:province":"ON",
    "wof:name":"Kucan Chiropractic Office",
    "wof:placetype":"venue"
},
  "geometry": {"coordinates":[-81.02943399999999,44.153419],"type":"Point"}
}