{
  "type": "Feature",
  "properties": {
    "addr:full":"663 3rd St W North Vancouver BC V7M 1H1",
    "addr:housenumber":"663",
    "addr:postcode":"v7m 1h1",
    "addr:street":"3Rd St W",
    "iso:country":"CA",
    "sg:address":"663 3rd St W",
    "sg:city":"North Vancouver",
    "sg:classifiers":[
        {
            "category":"Building & Trades",
            "subcategory":"Plumbing",
            "type":"Services"
        }
    ],
    "sg:phone":"+1 604 988 3922",
    "sg:postcode":"V7M 1H1",
    "sg:province":"BC",
    "sg:tags":[
        "heating",
        "contractor"
    ],
    "wof:name":"Nova Heating & Sheet Metal Ltd",
    "wof:placetype":"venue"
},
  "geometry": {"coordinates":[-123.09095000000001,49.319557],"type":"Point"}
}