{
  "type": "Feature",
  "properties": {
    "addr:full":"472 Eighth Ave E New Westminster BC V3L 4L2",
    "addr:housenumber":"472",
    "addr:postcode":"v3l 4l2",
    "addr:street":"Eighth Ave E",
    "iso:country":"CA",
    "sg:address":"472 Eighth Ave E",
    "sg:city":"New Westminster",
    "sg:classifiers":[
        {
            "category":"Organizations",
            "subcategory":"Religious Organization",
            "type":"Services"
        }
    ],
    "sg:phone":"+1 604 526 7351",
    "sg:postcode":"V3L 4L2",
    "sg:province":"BC",
    "sg:tags":[
        "church"
    ],
    "wof:name":"Sts Cyril & Methodius Slovak",
    "wof:placetype":"venue"
},
  "geometry": {"coordinates":[-122.89447,49.231579],"type":"Point"}
}