{
  "type": "Feature",
  "properties": {
    "addr:full":"253 Industrial Park Rd Colborne ON K0K 1S0",
    "addr:housenumber":"253",
    "addr:postcode":"k0k 1s0",
    "addr:street":"Industrial Park Rd",
    "iso:country":"CA",
    "sg:address":"253 Industrial Park Rd",
    "sg:city":"Colborne",
    "sg:classifiers":[
        {
            "category":"Wholesale",
            "subcategory":"Metals & Minerals",
            "type":"Manufacturing & Wholesale Goods"
        }
    ],
    "sg:phone":"+1 905 355 1494",
    "sg:postcode":"K0K 1S0",
    "sg:province":"ON",
    "sg:tags":[
        "steel",
        "warehouse"
    ],
    "wof:name":"Upper Canada Steel",
    "wof:placetype":"venue"
},
  "geometry": {"coordinates":[-77.8959579468,44.0218696594],"type":"Point"}
}