{
  "type": "Feature",
  "properties": {
    "addr:full":"1444 Cornwall Rd Oakville ON L6J 7W5",
    "addr:housenumber":"1444",
    "addr:postcode":"l6j 7w5",
    "addr:street":"Cornwall Rd",
    "iso:country":"CA",
    "sg:address":"1444 Cornwall Rd",
    "sg:city":"Oakville",
    "sg:classifiers":[
        {
            "category":"Manufacturing",
            "subcategory":"Electronics",
            "type":"Manufacturing & Wholesale Goods"
        }
    ],
    "sg:phone":"+1 905 842 1234",
    "sg:postcode":"L6J 7W5",
    "sg:province":"ON",
    "sg:tags":[
        "equipment",
        "electronic",
        "supply"
    ],
    "wof:name":"Laytec Design & Consulting Inc",
    "wof:placetype":"venue"
},
  "geometry": {"coordinates":[-79.661575,43.475876],"type":"Point"}
}