{
  "type": "Feature",
  "properties": {
    "addr:full":"105 2nd Ave W Kindersley SK S0L 1S0",
    "addr:housenumber":"105",
    "addr:postcode":"s0l 1s0",
    "addr:street":"2Nd Ave W Kindersley",
    "iso:country":"CA",
    "sg:address":"105 2nd Ave W",
    "sg:city":"Kindersley",
    "sg:classifiers":[
        {
            "category":"Wholesale",
            "subcategory":"Machinery & Supplies",
            "type":"Manufacturing & Wholesale Goods"
        }
    ],
    "sg:phone":"+1 306 463 2100",
    "sg:postcode":"S0L 1S0",
    "sg:province":"SK",
    "sg:tags":[
        "agricultural",
        "implement"
    ],
    "wof:name":"Wyman Farm & Industrial Supply",
    "wof:placetype":"venue"
},
  "geometry": {"coordinates":[-109.157348633,51.4658660889],"type":"Point"}
}