{
  "type": "Feature",
  "properties": {
    "addr:full":"84 Gablewood Cres London ON N6G 2Z9",
    "addr:housenumber":"84",
    "addr:postcode":"n6g 2z9",
    "addr:street":"Gablewood Cres",
    "iso:country":"CA",
    "sg:address":"84 Gablewood Cres",
    "sg:city":"London",
    "sg:classifiers":[
        {
            "category":"Social Services",
            "type":"Services"
        }
    ],
    "sg:phone":"+1 519 473 5182",
    "sg:postcode":"N6G 2Z9",
    "sg:province":"ON",
    "sg:tags":[
        "counselor",
        "marriage",
        "family"
    ],
    "wof:name":"Lesperance, Michael",
    "wof:placetype":"venue"
},
  "geometry": {"coordinates":[-81.316757,43.00901],"type":"Point"}
}