{
  "type": "Feature",
  "properties": {
    "addr:full":"292 Speedvale Ave W Guelph ON N1H 1C4",
    "addr:housenumber":"292",
    "addr:postcode":"n1h 1c4",
    "addr:street":"Speedvale Ave W",
    "iso:country":"CA",
    "sg:address":"292 Speedvale Ave W",
    "sg:city":"Guelph",
    "sg:classifiers":[
        {
            "category":"Freight",
            "type":"Transportation"
        }
    ],
    "sg:phone":"+1 519 821 7888",
    "sg:postcode":"N1H 1C4",
    "sg:province":"ON",
    "sg:tags":[
        "mover"
    ],
    "wof:name":"Hummel's Moving",
    "wof:placetype":"venue"
},
  "geometry": {"coordinates":[-80.285805,43.545479],"type":"Point"}
}