{
  "type": "Feature",
  "properties": {
    "addr:full":"23 Main St Lions Head ON N0H 1W0",
    "addr:housenumber":"23",
    "addr:postcode":"n0h 1w0",
    "addr:street":"Main St",
    "iso:country":"CA",
    "sg:address":"23 Main St",
    "sg:city":"Lions Head",
    "sg:classifiers":[
        {
            "category":"Building & Trades",
            "subcategory":"Cleaning & Sanitation",
            "type":"Services"
        }
    ],
    "sg:phone":"+1 519 793 3456",
    "sg:postcode":"N0H 1W0",
    "sg:province":"ON",
    "sg:tags":[
        "janitor"
    ],
    "wof:name":"Catley, Bob",
    "wof:placetype":"venue"
},
  "geometry": {"coordinates":[-81.251465,44.981758],"type":"Point"}
}