{
  "type": "Feature",
  "properties": {
    "addr:full":"3316 Portage Ave Winnipeg MB R3K 0Z1",
    "addr:housenumber":"3316",
    "addr:postcode":"r3k 0z1",
    "addr:street":"Portage Ave",
    "iso:country":"CA",
    "sg:address":"3316 Portage Ave",
    "sg:city":"Winnipeg",
    "sg:classifiers":[
        {
            "category":"Autos & Motor Vehicles",
            "subcategory":"Fuel & Gas Station",
            "type":"Retail Goods"
        }
    ],
    "sg:phone":"+1 204 897 3339",
    "sg:postcode":"R3K 0Z1",
    "sg:province":"MB",
    "sg:tags":[
        "oil"
    ],
    "wof:name":"Westwood Gas Bar",
    "wof:placetype":"venue"
},
  "geometry": {"coordinates":[-97.295975,49.881989],"type":"Point"}
}