{
  "type": "Feature",
  "properties": {
    "addr:full":"9921 Old Homestead Rd Pefferlaw ON L0E 1N0",
    "addr:housenumber":"9921",
    "addr:postcode":"l0e 1n0",
    "addr:street":"Old Homestead Rd",
    "iso:country":"CA",
    "sg:address":"9921 Old Homestead Rd",
    "sg:city":"Pefferlaw",
    "sg:classifiers":[
        {
            "category":"Professional",
            "subcategory":"Art Services",
            "type":"Services"
        }
    ],
    "sg:phone":"+1 705 437 4600",
    "sg:postcode":"L0E 1N0",
    "sg:province":"ON",
    "sg:tags":[
        "graphic",
        "designer"
    ],
    "wof:name":"Gtr Printing",
    "wof:placetype":"venue"
},
  "geometry": {"coordinates":[-79.20826721189999,44.3054428101],"type":"Point"}
}