{
  "type": "Feature",
  "properties": {
    "addr:full":"9425 58 Ave NW Edmonton AB T6E 0B8",
    "addr:housenumber":"9425",
    "addr:postcode":"t6e 0b8",
    "addr:street":"58 Ave Nw",
    "iso:country":"CA",
    "sg:address":"9425 58 Ave NW",
    "sg:city":"Edmonton",
    "sg:classifiers":[
        {
            "category":"Wholesale",
            "subcategory":"Machinery & Supplies",
            "type":"Manufacturing & Wholesale Goods"
        }
    ],
    "sg:phone":"+1 780 434 3362",
    "sg:postcode":"T6E 0B8",
    "sg:province":"AB",
    "sg:tags":[
        "equipment",
        "welding"
    ],
    "wof:name":"Western Studwelding Supply",
    "wof:placetype":"venue"
},
  "geometry": {"coordinates":[-113.47266399999999,53.493683],"type":"Point"}
}