{
  "type": "Feature",
  "properties": {
    "addr:full":"Fox Creek AB T0H 1P0",
    "addr:postcode":"t0h 1p0",
    "iso:country":"CA",
    "sg:city":"Fox Creek",
    "sg:classifiers":[
        {
            "category":"Shopping",
            "subcategory":"Hobbies, Toys, & Games",
            "type":"Retail Goods"
        }
    ],
    "sg:phone":"+1 780 622 2206",
    "sg:postcode":"T0H 1P0",
    "sg:province":"AB",
    "sg:tags":[
        "model",
        "supply"
    ],
    "wof:name":"Scribblings",
    "wof:placetype":"venue"
},
  "geometry": {"coordinates":[-116.801452637,54.3936576843],"type":"Point"}
}