{
  "type": "Feature",
  "properties": {
    "addr:full":"3522 Rue Masson Montreal QC H1X 1R9",
    "addr:housenumber":"3522",
    "addr:postcode":"h1x 1r9",
    "addr:street":"Rue Masson",
    "iso:country":"CA",
    "sg:address":"3522 Rue Masson",
    "sg:city":"Montreal",
    "sg:classifiers":[
        {
            "category":"Restaurant",
            "type":"Food & Drink"
        }
    ],
    "sg:phone":"+1 514 593 5508",
    "sg:postcode":"H1X 1R9",
    "sg:province":"QC",
    "wof:name":"Restaurant LA Porte DE Masson",
    "wof:placetype":"venue"
},
  "geometry": {"coordinates":[-73.5715332031,45.5534248352],"type":"Point"}
}