{
  "type": "Feature",
  "properties": {
    "addr:full":"1475 Av Bennett Montreal QC H1V 2S5",
    "addr:housenumber":"1475",
    "addr:postcode":"h1v 2s5",
    "addr:street":"Av Bennett",
    "iso:country":"CA",
    "sg:address":"1475 Av Bennett",
    "sg:city":"Montreal",
    "sg:classifiers":[
        {
            "category":"Social Services",
            "type":"Services"
        }
    ],
    "sg:phone":"+1 514 251 2081",
    "sg:postcode":"H1V 2S5",
    "sg:province":"QC",
    "sg:tags":[
        "organization",
        "welfare"
    ],
    "wof:name":"Cap St Barnabe Inc",
    "wof:placetype":"venue"
},
  "geometry": {"coordinates":[-73.5329284668,45.5533180237],"type":"Point"}
}