{
  "type": "Feature",
  "properties": {
    "addr:full":"1835 Renfrew St Vancouver BC V5M 3J1",
    "addr:housenumber":"1835",
    "addr:postcode":"v5m 3j1",
    "addr:street":"Renfrew St",
    "iso:country":"CA",
    "sg:address":"1835 Renfrew St",
    "sg:city":"Vancouver",
    "sg:classifiers":[
        {
            "category":"Cinema",
            "subcategory":"Movie Rental",
            "type":"Entertainment"
        }
    ],
    "sg:phone":"+1 604 251 3744",
    "sg:postcode":"V5M 3J1",
    "sg:province":"BC",
    "sg:tags":[
        "leasing",
        "video",
        "disc",
        "tape"
    ],
    "wof:name":"Blockbuster Video",
    "wof:placetype":"venue"
},
  "geometry": {"coordinates":[-123.04441799999999,49.268177],"type":"Point"}
}