{
  "type": "Feature",
  "properties": {
    "addr:full":"Prince Albert SK S6V 6Z6",
    "addr:postcode":"s6v 6z6",
    "iso:country":"CA",
    "sg:city":"Prince Albert",
    "sg:classifiers":[
        {
            "category":"Health Services",
            "subcategory":"Doctor",
            "type":"Services"
        }
    ],
    "sg:phone":"+1 306 763 2681",
    "sg:postcode":"S6V 6Z6",
    "sg:province":"SK",
    "sg:tags":[
        "physician",
        "surgeon"
    ],
    "wof:name":"Holton, P MD",
    "wof:placetype":"venue"
},
  "geometry": {"coordinates":[-105.737823486,53.1874351501],"type":"Point"}
}