{
  "type": "Feature",
  "properties": {
    "addr:full":"1209 18 Ave Coaldale AB T1M 1M2",
    "addr:housenumber":"1209",
    "addr:postcode":"t1m 1m2",
    "addr:street":"18 Ave",
    "iso:country":"CA",
    "sg:address":"1209 18 Ave",
    "sg:city":"Coaldale",
    "sg:classifiers":[
        {
            "category":"Manufacturing",
            "subcategory":"Metals",
            "type":"Manufacturing & Wholesale Goods"
        }
    ],
    "sg:phone":"+1 403 345 3973",
    "sg:postcode":"T1M 1M2",
    "sg:province":"AB",
    "sg:tags":[
        "welding"
    ],
    "wof:name":"Coaldale Iron Products Ltd",
    "wof:placetype":"venue"
},
  "geometry": {"coordinates":[-112.610145569,49.7313117981],"type":"Point"}
}