{
  "type": "Feature",
  "properties": {
    "addr:full":"293 1st Ave Kamloops BC V2C 3J3",
    "addr:housenumber":"293",
    "addr:postcode":"bc v2c 3j3",
    "addr:street":"1St Ave",
    "iso:country":"CA",
    "sg:address":"293 1st Ave",
    "sg:city":"Kamloops",
    "sg:classifiers":[
        {
            "category":"Professional",
            "subcategory":"Engineering",
            "type":"Services"
        }
    ],
    "sg:phone":"+1 250 374 2200",
    "sg:postcode":"V2C 3J3",
    "sg:province":"BC",
    "sg:tags":[
        "engineer"
    ],
    "wof:name":"Civic Engineering Svc Ltd",
    "wof:placetype":"venue"
},
  "geometry": {"coordinates":[-120.33880600000001,50.675529],"type":"Point"}
}