{
  "type": "Feature",
  "properties": {
    "iso:country":"CA",
    "sg:address":"293 1st Ave",
    "sg:city":"Kamloops",
    "sg:classifiers":[
        {
            "category":"Professional",
            "subcategory":"Engineering",
            "type":"Services"
        }
    ],
    "sg:phone":"+1 250 374 2200",
    "sg:postcode":"V2C 3J3",
    "sg:province":"BC",
    "sg:tags":[
        "engineer"
    ],
    "wof:name":"Civic Engineering Svc Ltd",
    "wof:placetype":"venue"
},
  "geometry": {"coordinates":[-120.338806,50.675529],"type":"Point"}
}