{
  "type": "Feature",
  "properties": {
    "iso:country":"CA",
    "sg:address":"592 Justus Dr",
    "sg:city":"Kingston",
    "sg:classifiers":[
        {
            "category":"Building & Trades",
            "subcategory":"Construction",
            "type":"Services"
        }
    ],
    "sg:phone":"+1 613 389 4250",
    "sg:postcode":"K7M 4H4",
    "sg:province":"ON",
    "sg:tags":[
        "general",
        "contractor"
    ],
    "wof:name":"Emmons & Mitchell Constr Ltd",
    "wof:placetype":"venue"
},
  "geometry": {"coordinates":[-76.57206,44.244068],"type":"Point"}
}