{
  "type": "Feature",
  "properties": {
    "addr:full":"124 Muskrat St Banff AB T1L 1C4",
    "addr:housenumber":"124",
    "addr:postcode":"t1l 1c4",
    "addr:street":"Muskrat St",
    "iso:country":"CA",
    "sg:address":"124 Muskrat St",
    "sg:city":"Banff",
    "sg:classifiers":[
        {
            "category":"Shopping",
            "subcategory":"Bicycles & Sporting Goods",
            "type":"Retail Goods"
        }
    ],
    "sg:phone":"+1 403 760 7668",
    "sg:postcode":"T1L 1C4",
    "sg:province":"AB",
    "sg:tags":[
        "fishing",
        "guide"
    ],
    "wof:name":"Upper Bow Fly Fishing CO",
    "wof:placetype":"venue"
},
  "geometry": {"coordinates":[-115.567741394,51.1748886108],"type":"Point"}
}