{
  "type": "Feature",
  "properties": {
    "iso:country":"CA",
    "sg:city":"Barrie",
    "sg:classifiers":[
        {
            "category":"Autos & Motor Vehicles",
            "subcategory":"Auto Supplies",
            "type":"Retail Goods"
        }
    ],
    "sg:phone":"+1 705 737 0905",
    "sg:postcode":"L4N 1R8",
    "sg:province":"ON",
    "sg:tags":[
        "automobile",
        "stereo",
        "radio"
    ],
    "wof:name":"Retech",
    "wof:placetype":"venue"
},
  "geometry": {"coordinates":[-79.692429,44.389965],"type":"Point"}
}