{
  "type": "Feature",
  "properties": {
    "addr:full":"58 Oakwood Ave N Mississauga ON L5G 3L8",
    "addr:housenumber":"58",
    "addr:postcode":"l5g 3l8",
    "addr:street":"Oakwood Ave N",
    "iso:country":"CA",
    "sg:address":"58 Oakwood Ave N",
    "sg:city":"Mississauga",
    "sg:classifiers":[
        {
            "category":"Professional",
            "subcategory":"Accounting & Tax Preparation",
            "type":"Services"
        }
    ],
    "sg:phone":"+1 905 274 9425",
    "sg:postcode":"L5G 3L8",
    "sg:province":"ON",
    "sg:tags":[
        "accountant"
    ],
    "wof:name":"Total Accounting",
    "wof:placetype":"venue"
},
  "geometry": {"coordinates":[-79.58093261720001,43.5598678589],"type":"Point"}
}