{
  "type": "Feature",
  "properties": {
    "addr:full":"10 Wildhaven Cres Maple ON L6A 2G9",
    "addr:housenumber":"10",
    "addr:postcode":"l6a 2g9",
    "addr:street":"Wildhaven Cres",
    "iso:country":"CA",
    "sg:address":"10 Wildhaven Cres",
    "sg:city":"Maple",
    "sg:classifiers":[
        {
            "category":"Professional",
            "subcategory":"Engineering",
            "type":"Services"
        }
    ],
    "sg:phone":"+1 905 303 7220",
    "sg:postcode":"L6A 2G9",
    "sg:province":"ON",
    "sg:tags":[
        "engineer"
    ],
    "wof:name":"Dynamic Designs & Engineering",
    "wof:placetype":"venue"
},
  "geometry": {"coordinates":[-79.520882,43.860493],"type":"Point"}
}