{
  "type": "Feature",
  "properties": {
    "addr:full":"Bldg 29 Berens River MB R0B 0A0",
    "addr:postcode":"r0b 0a0",
    "addr:street":"Berens River",
    "iso:country":"CA",
    "sg:address":"Bldg 29",
    "sg:city":"Berens River",
    "sg:classifiers":[
        {
            "category":"Food & Beverages",
            "subcategory":"Groceries & Convenience Stores",
            "type":"Retail Goods"
        }
    ],
    "sg:phone":"+1 204 382 2341",
    "sg:postcode":"R0B 0A0",
    "sg:province":"MB",
    "sg:tags":[
        "grocer"
    ],
    "wof:name":"Alix Enterprises Ltd",
    "wof:placetype":"venue"
},
  "geometry": {"coordinates":[-100.23764038100001,50.0292854309],"type":"Point"}
}