{
  "type": "Feature",
  "properties": {
    "addr:full":"Vancouver BC V6C 2V6",
    "addr:postcode":"v6c 2v6",
    "iso:country":"CA",
    "sg:city":"Vancouver",
    "sg:classifiers":[
        {
            "category":"Professional",
            "subcategory":"Management & Consulting",
            "type":"Services"
        }
    ],
    "sg:phone":"+1 604 689 3833",
    "sg:postcode":"V6C 2V6",
    "sg:province":"BC",
    "sg:tags":[
        "consultant",
        "business"
    ],
    "wof:name":"Pannell Kerr Forster",
    "wof:placetype":"venue"
},
  "geometry": {"coordinates":[-123.11592102,49.2853050232],"type":"Point"}
}