{
  "type": "Feature",
  "properties": {
    "addr:full":"901 1st Ave N Saskatoon SK S7K 1Y4",
    "addr:housenumber":"901",
    "addr:postcode":"s7k 1y4",
    "addr:street":"1St Ave N",
    "iso:country":"CA",
    "sg:address":"901 1st Ave N",
    "sg:city":"Saskatoon",
    "sg:classifiers":[
        {
            "category":"Manufacturing",
            "subcategory":"Tools & Machinery",
            "type":"Manufacturing & Wholesale Goods"
        }
    ],
    "sg:phone":"+1 306 955 2272",
    "sg:postcode":"S7K 1Y4",
    "sg:province":"SK",
    "sg:tags":[
        "equipment",
        "motel",
        "hotel"
    ],
    "wof:name":"Capa Hospitality Solutions Inc",
    "wof:placetype":"venue"
},
  "geometry": {"coordinates":[-106.659622,52.141239],"type":"Point"}
}