{
  "type": "Feature",
  "properties": {
    "addr:full":"5619 Route 105 Mill Cove NB E4C 3E5",
    "addr:housenumber":"5619",
    "addr:postcode":"e4c 3e5",
    "addr:street":"Route 105",
    "iso:country":"CA",
    "sg:address":"5619 Route 105",
    "sg:city":"Mill Cove",
    "sg:classifiers":[
        {
            "category":"Travel",
            "subcategory":"Campground",
            "type":"Entertainment"
        }
    ],
    "sg:phone":"+1 506 488 2244",
    "sg:postcode":"E4C 3E5",
    "sg:province":"NB",
    "sg:tags":[
        "camp",
        "fishing"
    ],
    "wof:name":"Black Bear Lodge",
    "wof:placetype":"venue"
},
  "geometry": {"coordinates":[-66.013947,45.87579],"type":"Point"}
}