{
  "type": "Feature",
  "properties": {
    "addr:full":"99 Rue DE L'Eveche E Rimouski QC G5L 1X7",
    "addr:housenumber":"99",
    "addr:postcode":"g5l 1x7",
    "addr:street":"Rue De L'Eveche E",
    "iso:country":"CA",
    "sg:address":"99 Rue DE L'Eveche E",
    "sg:city":"Rimouski",
    "sg:classifiers":[
        {
            "category":"Retail",
            "subcategory":"Animal Services",
            "type":"Services"
        }
    ],
    "sg:phone":"+1 418 722 8683",
    "sg:postcode":"G5L 1X7",
    "sg:province":"QC",
    "sg:tags":[
        "pet",
        "grooming",
        "washing"
    ],
    "wof:name":"Salon Pitou-Poil Inc",
    "wof:placetype":"venue"
},
  "geometry": {"coordinates":[-68.5217056274,48.4502677917],"type":"Point"}
}