{
  "type": "Feature",
  "properties": {
    "iso:country":"CA",
    "sg:address":"4408 28 St",
    "sg:city":"Vernon",
    "sg:classifiers":[
        {
            "category":"Shopping",
            "subcategory":"Computers & Home Electronics",
            "type":"Retail Goods"
        }
    ],
    "sg:phone":"+1 250 542 1362",
    "sg:postcode":"V1T 7P5",
    "sg:province":"BC",
    "sg:tags":[
        "equipment",
        "dealer"
    ],
    "wof:name":"Vernon Stationery",
    "wof:placetype":"venue"
},
  "geometry": {"coordinates":[-119.268669128,50.2763671875],"type":"Point"}
}