{
  "type": "Feature",
  "properties": {
    "addr:full":"405 Hall Ave E Renfrew ON K7V 2S6",
    "addr:housenumber":"405",
    "addr:postcode":"k7v 2s6",
    "addr:street":"Hall Ave E",
    "iso:country":"CA",
    "sg:address":"405 Hall Ave E",
    "sg:city":"Renfrew",
    "sg:classifiers":[
        {
            "category":"Health Services",
            "subcategory":"Health Practitioner",
            "type":"Services"
        }
    ],
    "sg:phone":"+1 613 432 9088",
    "sg:postcode":"K7V 2S6",
    "sg:province":"ON",
    "sg:tags":[
        "physiotherapist"
    ],
    "wof:name":"Ottawa Valley Physiotherapy",
    "wof:placetype":"venue"
},
  "geometry": {"coordinates":[-76.67237854,45.4742698669],"type":"Point"}
}