{
  "type": "Feature",
  "properties": {
    "addr:full":"Calgary AB T2P 4A3",
    "addr:postcode":"t2p 4a3",
    "iso:country":"CA",
    "sg:city":"Calgary",
    "sg:classifiers":[
        {
            "category":"Professional",
            "subcategory":"Lawyer & Legal Services",
            "type":"Services"
        }
    ],
    "sg:phone":"+1 403 267 8400",
    "sg:postcode":"T2P 4A3",
    "sg:province":"AB",
    "sg:tags":[
        "attorney"
    ],
    "wof:name":"Hunt, Ray",
    "wof:placetype":"venue"
},
  "geometry": {"coordinates":[-114.078941345,51.0477561951],"type":"Point"}
}