{
  "type": "Feature",
  "properties": {
    "addr:full":"6 Hyde Park Dr Georgetown ON L7G 2B6",
    "addr:housenumber":"6",
    "addr:postcode":"l7g 2b6",
    "addr:street":"Hyde Park Dr",
    "iso:country":"CA",
    "sg:address":"6 Hyde Park Dr",
    "sg:city":"Georgetown",
    "sg:classifiers":[
        {
            "category":"Education",
            "subcategory":"School",
            "type":"Public Place"
        }
    ],
    "sg:phone":"+1 905 877 9301",
    "sg:postcode":"L7G 2B6",
    "sg:province":"ON",
    "wof:name":"Park School",
    "wof:placetype":"venue"
},
  "geometry": {"coordinates":[-79.930397,43.644119],"type":"Point"}
}