{
  "type": "Feature",
  "properties": {
    "addr:full":"134 50th Ave W Claresholm AB T0L 0T0",
    "addr:housenumber":"134",
    "addr:postcode":"t0l 0t0",
    "addr:street":"50Th Ave W Claresholm",
    "iso:country":"CA",
    "sg:address":"134 50th Ave W",
    "sg:city":"Claresholm",
    "sg:classifiers":[
        {
            "category":"Banks & Credit Unions",
            "subcategory":"Bank",
            "type":"Services"
        }
    ],
    "sg:phone":"+1 403 625 4401",
    "sg:postcode":"T0L 0T0",
    "sg:province":"AB",
    "wof:name":"Mac Leod Savings & Cu Ltd",
    "wof:placetype":"venue"
},
  "geometry": {"coordinates":[-113.583099365,50.0262718201],"type":"Point"}
}