{
  "type": "Feature",
  "properties": {
    "addr:full":"8078 Rue Drolet Montreal QC H2R 2C9",
    "addr:housenumber":"8078",
    "addr:postcode":"h2r 2c9",
    "addr:street":"Rue Drolet",
    "iso:country":"CA",
    "sg:address":"8078 Rue Drolet",
    "sg:city":"Montreal",
    "sg:classifiers":[
        {
            "category":"Organizations",
            "subcategory":"Membership Organization",
            "type":"Services"
        }
    ],
    "sg:phone":"+1 514 383 9108",
    "sg:postcode":"H2R 2C9",
    "sg:province":"QC",
    "wof:name":"Maison Des Grands-Parents",
    "wof:placetype":"venue"
},
  "geometry": {"coordinates":[-73.6290893555,45.5416488647],"type":"Point"}
}