{
  "type": "Feature",
  "properties": {
    "addr:full":"1117 Finch Ave W North York ON M3J 2P7",
    "addr:housenumber":"1117",
    "addr:postcode":"m3j 2p7",
    "addr:street":"Finch Ave W",
    "iso:country":"CA",
    "sg:address":"1117 Finch Ave W",
    "sg:city":"North York",
    "sg:classifiers":[
        {
            "category":"Government",
            "subcategory":"Office",
            "type":"Public Place"
        }
    ],
    "sg:phone":"+1 416 397 9450",
    "sg:postcode":"M3J 2P7",
    "sg:province":"ON",
    "sg:tags":[
        "village"
    ],
    "wof:name":"Toronto Social Assistance Ofc",
    "wof:placetype":"venue"
},
  "geometry": {"coordinates":[-79.47444900000001,43.767033],"type":"Point"}
}