{
  "type": "Feature",
  "properties": {
    "addr:full":"206 Chestnut St E Whitby ON L1N 2Y2",
    "addr:housenumber":"206",
    "addr:postcode":"l1n 2y2",
    "addr:street":"Chestnut St E",
    "iso:country":"CA",
    "sg:address":"206 Chestnut St E",
    "sg:city":"Whitby",
    "sg:classifiers":[
        {
            "category":"Personal",
            "subcategory":"Beauty Salon",
            "type":"Services"
        }
    ],
    "sg:phone":"+1 905 430 0514",
    "sg:postcode":"L1N 2Y2",
    "sg:province":"ON",
    "sg:tags":[
        "manicuring"
    ],
    "wof:name":"Carol M Complete Spa",
    "wof:placetype":"venue"
},
  "geometry": {"coordinates":[-78.9426727295,43.8858718872],"type":"Point"}
}