{
  "type": "Feature",
  "properties": {
    "iso:country":"CA",
    "sg:address":"306 2E Av",
    "sg:city":"Iberville",
    "sg:classifiers":[
        {
            "category":"Wholesale",
            "subcategory":"Hardware",
            "type":"Manufacturing & Wholesale Goods"
        }
    ],
    "sg:phone":"+1 450 346 3139",
    "sg:postcode":"J2X 2B6",
    "sg:province":"QC",
    "sg:tags":[
        "system",
        "equipment",
        "heating",
        "electric",
        "contractor"
    ],
    "wof:name":"Entreprises D & C Electriques",
    "wof:placetype":"venue"
},
  "geometry": {"coordinates":[-73.23565673829999,45.3043251038],"type":"Point"}
}