{
  "type": "Feature",
  "properties": {
    "addr:full":"Vancouver BC V6B 6A8",
    "addr:postcode":"v6b 6a8",
    "iso:country":"CA",
    "sg:city":"Vancouver",
    "sg:classifiers":[
        {
            "category":"Travel",
            "subcategory":"Travel Agent",
            "type":"Entertainment"
        }
    ],
    "sg:phone":"+1 604 899 8845",
    "sg:postcode":"V6B 6A8",
    "sg:province":"BC",
    "sg:tags":[
        "cruise"
    ],
    "wof:name":"International Cruise & Travel",
    "wof:placetype":"venue"
},
  "geometry": {"coordinates":[-123.12487,49.274075],"type":"Point"}
}