{
  "type": "Feature",
  "properties": {
    "iso:country":"CA",
    "sg:city":"Sainte-Foy",
    "sg:classifiers":[
        {
            "category":"Wholesale",
            "subcategory":"Medical Equipment & Supplies",
            "type":"Manufacturing & Wholesale Goods"
        }
    ],
    "sg:phone":"+1 418 657 7788",
    "sg:postcode":"G1W 2K7",
    "sg:province":"QC",
    "sg:tags":[
        "physician",
        "surgeon",
        "dental"
    ],
    "wof:name":"Dufort & Lavigne Ltee",
    "wof:placetype":"venue"
},
  "geometry": {"coordinates":[-71.309013,46.767857],"type":"Point"}
}