{
  "type": "Feature",
  "properties": {
    "addr:full":"1602 Rue Fleury E Montreal QC H2C 1S8",
    "addr:housenumber":"1602",
    "addr:postcode":"h2c 1s8",
    "addr:street":"Rue Fleury E",
    "iso:country":"CA",
    "sg:address":"1602 Rue Fleury E",
    "sg:city":"Montreal",
    "sg:classifiers":[
        {
            "category":"Food & Beverages",
            "subcategory":"Specialty",
            "type":"Retail Goods"
        }
    ],
    "sg:phone":"+1 514 384 6660",
    "sg:postcode":"H2C 1S8",
    "sg:province":"QC",
    "wof:name":"Tournesol Aliments Naturels",
    "wof:placetype":"venue"
},
  "geometry": {"coordinates":[-73.65551000000001,45.563988],"type":"Point"}
}