{
  "type": "Feature",
  "properties": {
    "iso:country":"CA",
    "sg:address":"169 Rue Merizzi",
    "sg:city":"Saint-Laurent",
    "sg:classifiers":[
        {
            "category":"Food & Beverages",
            "subcategory":"Candy",
            "type":"Retail Goods"
        }
    ],
    "sg:phone":"+1 514 733 0500",
    "sg:postcode":"H4T 1Y3",
    "sg:province":"QC",
    "sg:tags":[
        "confectionery"
    ],
    "wof:name":"Importation Napa Inc",
    "wof:placetype":"venue"
},
  "geometry": {"coordinates":[-73.695778,45.479561],"type":"Point"}
}