{
  "type": "Feature",
  "properties": {
    "addr:full":"1025 Cook St Victoria BC V8V 3Z7",
    "addr:housenumber":"1025",
    "addr:postcode":"v8v 3z7",
    "addr:street":"Cook St",
    "iso:country":"CA",
    "sg:address":"1025 Cook St",
    "sg:city":"Victoria",
    "sg:classifiers":[
        {
            "category":"Shopping",
            "subcategory":"Florist",
            "type":"Retail Goods"
        }
    ],
    "sg:phone":"+1 250 384 2251",
    "sg:postcode":"V8V 3Z7",
    "sg:province":"BC",
    "wof:name":"Flowers First",
    "wof:placetype":"venue"
},
  "geometry": {"coordinates":[-123.354156,48.423012],"type":"Point"}
}