{
  "type": "Feature",
  "properties": {
    "addr:full":"345 Scott St St Catharines ON L2N 1J7",
    "addr:housenumber":"345",
    "addr:postcode":"l2n 1j7",
    "addr:street":"Scott St",
    "iso:country":"CA",
    "sg:address":"345 Scott St",
    "sg:city":"St Catharines",
    "sg:classifiers":[
        {
            "category":"Retail",
            "subcategory":"Car Wash",
            "type":"Services"
        }
    ],
    "sg:phone":"+1 905 934 5215",
    "sg:postcode":"L2N 1J7",
    "sg:province":"ON",
    "sg:tags":[
        "polishing",
        "washing"
    ],
    "wof:name":"Flynn's Wash Ctr",
    "wof:placetype":"venue"
},
  "geometry": {"coordinates":[-79.2313156128,43.1882629395],"type":"Point"}
}