{
  "type": "Feature",
  "properties": {
    "addr:full":"12709 Imperial Rd Springfield ON N0L 2J0",
    "addr:housenumber":"12709",
    "addr:postcode":"n0l 2j0",
    "addr:street":"Imperial Rd",
    "iso:country":"CA",
    "sg:address":"12709 Imperial Rd",
    "sg:city":"Springfield",
    "sg:classifiers":[
        {
            "category":"Building & Trades",
            "subcategory":"Construction",
            "type":"Services"
        }
    ],
    "sg:phone":"+1 519 765 4445",
    "sg:postcode":"N0L 2J0",
    "sg:province":"ON",
    "sg:tags":[
        "drainage",
        "contractor"
    ],
    "wof:name":"Van Gorp Drainage & Excavating",
    "wof:placetype":"venue"
},
  "geometry": {"coordinates":[-80.98342132569999,42.8327713013],"type":"Point"}
}