{
  "type": "Feature",
  "properties": {
    "addr:full":"363 Rue Mgr Desmarais Upton QC J0H 2E0",
    "addr:housenumber":"363",
    "addr:postcode":"j0h 2e0",
    "addr:street":"Rue Mgr Desmarais",
    "iso:country":"CA",
    "sg:address":"363 Rue Mgr Desmarais",
    "sg:city":"Upton",
    "sg:classifiers":[
        {
            "category":"Organizations",
            "subcategory":"Religious Organization",
            "type":"Services"
        }
    ],
    "sg:phone":"+1 450 549 4533",
    "sg:postcode":"J0H 2E0",
    "sg:province":"QC",
    "sg:tags":[
        "church"
    ],
    "wof:name":"Presbytere D'Upton",
    "wof:placetype":"venue"
},
  "geometry": {"coordinates":[-72.692429,45.651669],"type":"Point"}
}