{
  "type": "Feature",
  "properties": {
    "addr:full":"4963 Thornwood Pl Burnaby BC V5G 3Z3",
    "addr:housenumber":"4963",
    "addr:postcode":"v5g 3z3",
    "addr:street":"Thornwood Pl",
    "iso:country":"CA",
    "sg:address":"4963 Thornwood Pl",
    "sg:city":"Burnaby",
    "sg:classifiers":[
        {
            "category":"Real Estate",
            "subcategory":"Developer",
            "type":"Services"
        }
    ],
    "sg:phone":"+1 604 438 9409",
    "sg:postcode":"V5G 3Z3",
    "sg:province":"BC",
    "sg:tags":[
        "company",
        "land"
    ],
    "wof:name":"Mainline Group",
    "wof:placetype":"venue"
},
  "geometry": {"coordinates":[-122.99505600000001,49.24461],"type":"Point"}
}