{
  "type": "Feature",
  "properties": {
    "addr:full":"108 Queen St Fredericton NB E3B 1A5",
    "addr:housenumber":"108",
    "addr:postcode":"e3b 1a5",
    "addr:street":"Queen St",
    "iso:country":"CA",
    "sg:address":"108 Queen St",
    "sg:city":"Fredericton",
    "sg:classifiers":[
        {
            "category":"Real Estate",
            "subcategory":"Real Estate Operator",
            "type":"Services"
        }
    ],
    "sg:phone":"+1 506 459 7000",
    "sg:postcode":"E3B 1A5",
    "sg:province":"NB",
    "sg:tags":[
        "apartment"
    ],
    "wof:name":"Wulastook Industries Ltd",
    "wof:placetype":"venue"
},
  "geometry": {"coordinates":[-66.6493759155,45.9649238586],"type":"Point"}
}