{
  "type": "Feature",
  "properties": {
    "addr:full":"1846 Pass Creek Rd Castlegar BC V1N 4S6",
    "addr:housenumber":"1846",
    "addr:postcode":"v1n 4s6",
    "addr:street":"Pass Creek Rd",
    "iso:country":"CA",
    "sg:address":"1846 Pass Creek Rd",
    "sg:city":"Castlegar",
    "sg:classifiers":[
        {
            "category":"Building & Trades",
            "subcategory":"Plumbing",
            "type":"Services"
        }
    ],
    "sg:phone":"+1 250 365 0178",
    "sg:postcode":"V1N 4S6",
    "sg:province":"BC",
    "sg:tags":[
        "contractor"
    ],
    "wof:name":"L & M Plumbing & Heating",
    "wof:placetype":"venue"
},
  "geometry": {"coordinates":[-117.65418243400001,49.2962532043],"type":"Point"}
}