{
  "type": "Feature",
  "properties": {
    "addr:full":"Victoria BC V8V 3K8",
    "addr:postcode":"v8v 3k8",
    "iso:country":"CA",
    "sg:city":"Victoria",
    "sg:classifiers":[
        {
            "category":"Real Estate",
            "subcategory":"Architect",
            "type":"Services"
        }
    ],
    "sg:phone":"+1 250 382 3823",
    "sg:postcode":"V8V 3K8",
    "sg:province":"BC",
    "wof:name":"Keay & Assoc Architecture Ltd",
    "wof:placetype":"venue"
},
  "geometry": {"coordinates":[-123.352783,48.423386],"type":"Point"}
}