{
  "type": "Feature",
  "properties": {
    "addr:full":"1125 3E Av Val-D'Or QC J9P 1T7",
    "addr:housenumber":"1125",
    "addr:postcode":"j9p 1t7",
    "addr:street":"3E Av Val-D'Or",
    "iso:country":"CA",
    "sg:address":"1125 3E Av",
    "sg:city":"Val-D'Or",
    "sg:classifiers":[
        {
            "category":"Building & Trades",
            "subcategory":"Electrical",
            "type":"Services"
        }
    ],
    "sg:phone":"+1 819 825 0328",
    "sg:postcode":"J9P 1T7",
    "sg:province":"QC",
    "sg:tags":[
        "electric",
        "contractor"
    ],
    "wof:name":"Norbell Electrique Inc",
    "wof:placetype":"venue"
},
  "geometry": {"coordinates":[-68.42929100000001,53.890121],"type":"Point"}
}