{
  "type": "Feature",
  "properties": {
    "addr:full":"1477 Drouillard Rd Windsor ON N8Y 2R8",
    "addr:housenumber":"1477",
    "addr:postcode":"n8y 2r8",
    "addr:street":"Drouillard Rd",
    "iso:country":"CA",
    "sg:address":"1477 Drouillard Rd",
    "sg:city":"Windsor",
    "sg:classifiers":[
        {
            "category":"Wholesale",
            "subcategory":"Electrical",
            "type":"Manufacturing & Wholesale Goods"
        }
    ],
    "sg:phone":"+1 519 945 3478",
    "sg:postcode":"N8Y 2R8",
    "sg:province":"ON",
    "sg:tags":[
        "control",
        "equipment",
        "heating",
        "system"
    ],
    "wof:name":"Wholesale Service & Repair Ctr",
    "wof:placetype":"venue"
},
  "geometry": {"coordinates":[-82.99472799999999,42.312805],"type":"Point"}
}