{
  "type": "Feature",
  "properties": {
    "addr:full":"50925 Riverview Dr Chilliwack BC V4Z 1B7",
    "addr:housenumber":"50925",
    "addr:postcode":"v4z 1b7",
    "addr:street":"Riverview Dr",
    "iso:country":"CA",
    "sg:address":"50925 Riverview Dr",
    "sg:city":"Chilliwack",
    "sg:classifiers":[
        {
            "category":"Retail",
            "subcategory":"Auto Repair",
            "type":"Services"
        }
    ],
    "sg:phone":"+1 604 858 2494",
    "sg:postcode":"V4Z 1B7",
    "sg:province":"BC",
    "sg:tags":[
        "trailer"
    ],
    "wof:name":"Slesse Mobile Rv Svc",
    "wof:placetype":"venue"
},
  "geometry": {"coordinates":[-121.9515,49.156319],"type":"Point"}
}