{
  "type": "Feature",
  "properties": {
    "addr:full":"Langley BC V3A 9J8",
    "addr:postcode":"v3a 9j8",
    "iso:country":"CA",
    "sg:city":"Langley",
    "sg:classifiers":[
        {
            "category":"Shopping",
            "subcategory":"Shoes",
            "type":"Retail Goods"
        }
    ],
    "sg:phone":"+1 604 539 9992",
    "sg:postcode":"V3A 9J8",
    "sg:province":"BC",
    "wof:name":"Shoe CO",
    "wof:placetype":"venue"
},
  "geometry": {"coordinates":[-122.664985657,49.1132125854],"type":"Point"}
}