{
  "type": "Feature",
  "properties": {
    "addr:full":"45 Rue Racine O Chicoutimi QC G7J 1E3",
    "addr:housenumber":"45",
    "addr:postcode":"g7j 1e3",
    "addr:street":"Rue Racine O",
    "iso:country":"CA",
    "sg:address":"45 Rue Racine O",
    "sg:city":"Chicoutimi",
    "sg:classifiers":[
        {
            "category":"Retail",
            "subcategory":"Laundry & Dry Cleaning",
            "type":"Services"
        }
    ],
    "sg:phone":"+1 418 543 4822",
    "sg:postcode":"G7J 1E3",
    "sg:province":"QC",
    "sg:tags":[
        "cleaners"
    ],
    "wof:name":"Nettoyeur Deschenes Ltee",
    "wof:placetype":"venue"
},
  "geometry": {"coordinates":[-71.067276001,48.4280967712],"type":"Point"}
}