{
  "type": "Feature",
  "properties": {
    "addr:full":"Mont-Royal QC H3P 3C8",
    "addr:postcode":"h3p 3c8",
    "iso:country":"CA",
    "sg:city":"Mont-Royal",
    "sg:classifiers":[
        {
            "category":"Travel",
            "subcategory":"Travel Agent",
            "type":"Entertainment"
        }
    ],
    "sg:phone":"+1 514 342 4880",
    "sg:postcode":"H3P 3C8",
    "sg:province":"QC",
    "sg:tags":[
        "agency",
        "bureau"
    ],
    "wof:name":"Agence DE Voyage Canora Inc",
    "wof:placetype":"venue"
},
  "geometry": {"coordinates":[-73.639999,45.516953],"type":"Point"}
}