{
  "type": "Feature",
  "properties": {
    "addr:full":"1649 Barrington St # 400 Halifax NS B3J 1Z9",
    "addr:housenumber":"1649",
    "addr:postcode":"ns b3j 1z9",
    "addr:street":"Barrington St # 400",
    "iso:country":"CA",
    "sg:address":"1649 Barrington St # 400",
    "sg:city":"Halifax",
    "sg:classifiers":[
        {
            "category":"Social Services",
            "type":"Services"
        }
    ],
    "sg:phone":"+1 902 422 3711",
    "sg:postcode":"B3J 1Z9",
    "sg:province":"NS",
    "sg:tags":[
        "counselor",
        "marriage",
        "family"
    ],
    "wof:name":"Loomis, Connor G",
    "wof:placetype":"venue"
},
  "geometry": {"coordinates":[-63.5736198425,44.6467895508],"type":"Point"}
}