{
  "type": "Feature",
  "properties": {
    "addr:full":"1820 Rue Laval Longueuil QC J4K 5A2",
    "addr:housenumber":"1820",
    "addr:postcode":"j4k 5a2",
    "addr:street":"Rue Laval",
    "iso:country":"CA",
    "sg:address":"1820 Rue Laval",
    "sg:city":"Longueuil",
    "sg:classifiers":[
        {
            "category":"Retail",
            "subcategory":"Auto Repair",
            "type":"Services"
        }
    ],
    "sg:phone":"+1 450 677 8798",
    "sg:postcode":"J4K 5A2",
    "sg:province":"QC",
    "sg:tags":[
        "wrecker"
    ],
    "wof:name":"Remorquage Denis Tremblay",
    "wof:placetype":"venue"
},
  "geometry": {"coordinates":[-73.49494199999999,45.511456],"type":"Point"}
}