{
  "type": "Feature",
  "properties": {
    "addr:full":"Pickering ON L1W 3V2",
    "addr:postcode":"l1w 3v2",
    "iso:country":"CA",
    "sg:city":"Pickering",
    "sg:classifiers":[
        {
            "category":"Manufacturing",
            "subcategory":"Printing",
            "type":"Manufacturing & Wholesale Goods"
        }
    ],
    "sg:phone":"+1 905 831 5028",
    "sg:postcode":"L1W 3V2",
    "sg:province":"ON",
    "sg:tags":[
        "printer"
    ],
    "wof:name":"North Alliance Press Ltd",
    "wof:placetype":"venue"
},
  "geometry": {"coordinates":[-79.0751495361,43.8318061829],"type":"Point"}
}