{
  "type": "Feature",
  "properties": {
    "iso:country":"CA",
    "sg:address":"Main St",
    "sg:city":"Bonne Bay",
    "sg:classifiers":[
        {
            "category":"Travel",
            "subcategory":"Hotels & Motels",
            "type":"Entertainment"
        }
    ],
    "sg:phone":"+1 709 453 2515",
    "sg:postcode":"A0K 1P0",
    "sg:province":"NL",
    "wof:name":"Woody Point Motel",
    "wof:placetype":"venue"
},
  "geometry": {"coordinates":[-57.9161186218,49.5032196045],"type":"Point"}
}