{
  "type": "Feature",
  "properties": {
    "iso:country":"CA",
    "sg:address":"778 Rue Principale",
    "sg:city":"Saint-Albert",
    "sg:classifiers":[
        {
            "category":"Restaurant",
            "type":"Food & Drink"
        }
    ],
    "sg:phone":"+1 819 353 1655",
    "sg:postcode":"J0A 1E0",
    "sg:province":"QC",
    "wof:name":"Restaurant L'Odysee",
    "wof:placetype":"venue"
},
  "geometry": {"coordinates":[-72.0712509155,46.0121078491],"type":"Point"}
}