{
  "type": "Feature",
  "properties": {
    "iso:country":"CA",
    "sg:address":"101 Dundas St W",
    "sg:city":"Whitby",
    "sg:classifiers":[
        {
            "category":"Professional",
            "subcategory":"Business Services",
            "type":"Services"
        }
    ],
    "sg:phone":"+1 905 666 5271",
    "sg:postcode":"L1N 2M2",
    "sg:province":"ON",
    "sg:tags":[
        "telemarketing"
    ],
    "wof:name":"Marketing Resource Group",
    "wof:placetype":"venue"
},
  "geometry": {"coordinates":[-78.942329,43.879768],"type":"Point"}
}