{
  "type": "Feature",
  "properties": {
    "addr:full":"112 Industrial Court A Sault Ste Marie ON P6B 5W6",
    "addr:housenumber":"112",
    "addr:postcode":"p6b 5w6",
    "addr:street":"Industrial Court A",
    "iso:country":"CA",
    "sg:address":"112 Industrial Court A",
    "sg:city":"Sault Ste Marie",
    "sg:classifiers":[
        {
            "category":"Building & Trades",
            "subcategory":"Construction",
            "type":"Services"
        }
    ],
    "sg:phone":"+1 705 254 2400",
    "sg:postcode":"P6B 5W6",
    "sg:province":"ON",
    "sg:tags":[
        "contractor",
        "general"
    ],
    "wof:name":"F Coccimiglio Ents Ltd",
    "wof:placetype":"venue"
},
  "geometry": {"coordinates":[-84.326126,46.548779],"type":"Point"}
}