{
  "type": "Feature",
  "properties": {
    "addr:full":"1103 Bank St Ottawa ON K1S 3X4",
    "addr:housenumber":"1103",
    "addr:postcode":"k1s 3x4",
    "addr:street":"Bank St",
    "iso:country":"CA",
    "sg:address":"1103 Bank St",
    "sg:city":"Ottawa",
    "sg:classifiers":[
        {
            "category":"Shopping",
            "subcategory":"Bicycles & Sporting Goods",
            "type":"Retail Goods"
        }
    ],
    "sg:phone":"+1 613 821 1401",
    "sg:postcode":"K1S 3X4",
    "sg:province":"ON",
    "sg:tags":[
        "bait",
        "fishing"
    ],
    "wof:name":"Alves Worms Wholesale",
    "wof:placetype":"venue"
},
  "geometry": {"coordinates":[-75.6830062866,45.3939476013],"type":"Point"}
}