{
  "type": "Feature",
  "properties": {
    "iso:country":"CA",
    "sg:address":"233 Rue Queen",
    "sg:city":"Lennoxville",
    "sg:classifiers":[
        {
            "category":"Shopping",
            "type":"Retail Goods"
        }
    ],
    "sg:phone":"+1 819 565 8188",
    "sg:postcode":"J1M 1K5",
    "sg:province":"QC",
    "sg:tags":[
        "coin",
        "dealer",
        "supply"
    ],
    "wof:name":"Coin Center",
    "wof:placetype":"venue"
},
  "geometry": {"coordinates":[-71.8597106934,45.3724708557],"type":"Point"}
}