{
  "type": "Feature",
  "properties": {
    "addr:full":"1501 Rue DE L'Industrie Saint-Mathieu-DE-Beloeil QC J3G 4S5",
    "addr:housenumber":"1501",
    "addr:postcode":"j3g 4s5",
    "addr:street":"Rue De L'Industrie",
    "iso:country":"CA",
    "sg:address":"1501 Rue DE L'Industrie",
    "sg:city":"Saint-Mathieu-DE-Beloeil",
    "sg:classifiers":[
        {
            "category":"Shopping",
            "type":"Retail Goods"
        }
    ],
    "sg:phone":"+1 450 446 1215",
    "sg:postcode":"J3G 4S5",
    "sg:province":"QC",
    "sg:tags":[
        "miscellaneous",
        "store"
    ],
    "wof:name":"Monsieur Cabanon",
    "wof:placetype":"venue"
},
  "geometry": {"coordinates":[-73.19450399999999,45.595997],"type":"Point"}
}