{
  "type": "Feature",
  "properties": {
    "addr:full":"1726 Rue Notre-Dame O Montreal QC H3J 1M3",
    "addr:housenumber":"1726",
    "addr:postcode":"h3j 1m3",
    "addr:street":"Rue Notre-Dame O",
    "iso:country":"CA",
    "sg:address":"1726 Rue Notre-Dame O",
    "sg:city":"Montreal",
    "sg:classifiers":[
        {
            "category":"Shopping",
            "subcategory":"Used Merchandise",
            "type":"Retail Goods"
        }
    ],
    "sg:phone":"+1 514 937 7040",
    "sg:postcode":"H3J 1M3",
    "sg:province":"QC",
    "sg:tags":[
        "antique"
    ],
    "wof:name":"Antiquites Landry",
    "wof:placetype":"venue"
},
  "geometry": {"coordinates":[-73.547684,45.518745],"type":"Point"}
}