{
  "type": "Feature",
  "properties": {
    "addr:full":"260 Flamingo Rd Thornhill ON L4J 8N3",
    "addr:housenumber":"260",
    "addr:postcode":"l4j 8n3",
    "addr:street":"Flamingo Rd",
    "iso:country":"CA",
    "sg:address":"260 Flamingo Rd",
    "sg:city":"Thornhill",
    "sg:classifiers":[
        {
            "category":"Arts & Performance",
            "subcategory":"Theater",
            "type":"Entertainment"
        }
    ],
    "sg:phone":"+1 905 881 1378",
    "sg:postcode":"L4J 8N3",
    "sg:province":"ON",
    "sg:tags":[
        "music"
    ],
    "wof:name":"Joe Star Band",
    "wof:placetype":"venue"
},
  "geometry": {"coordinates":[-79.44654800000001,43.824211],"type":"Point"}
}