{
  "type": "Feature",
  "properties": {
    "iso:country":"CA",
    "sg:address":"818 Railway Ave",
    "sg:city":"Rosthern",
    "sg:classifiers":[
        {
            "category":"Food & Beverages",
            "subcategory":"Liquor & Beverages",
            "type":"Retail Goods"
        }
    ],
    "sg:phone":"+1 306 232 6266",
    "sg:postcode":"S0K 3R0",
    "sg:province":"SK",
    "sg:tags":[
        "store"
    ],
    "wof:name":"Liquor Stores",
    "wof:placetype":"venue"
},
  "geometry": {"coordinates":[-106.331695557,52.6577529907],"type":"Point"}
}