{
  "type": "Feature",
  "properties": {
    "addr:full":"221 Commercial St Nanaimo BC V9R 5G8",
    "addr:housenumber":"221",
    "addr:postcode":"v9r 5g8",
    "addr:street":"Commercial St",
    "iso:country":"CA",
    "sg:address":"221 Commercial St",
    "sg:city":"Nanaimo",
    "sg:classifiers":[
        {
            "category":"Restaurant",
            "type":"Food & Drink"
        }
    ],
    "sg:phone":"+1 250 754 5022",
    "sg:postcode":"V9R 5G8",
    "sg:province":"BC",
    "wof:name":"Modern Cafe",
    "wof:placetype":"venue"
},
  "geometry": {"coordinates":[-123.937202,49.166626],"type":"Point"}
}