{
  "type": "Feature",
  "properties": {
    "addr:full":"166 Rue Saint-Amable # A Montreal QC H2Y 1E8",
    "addr:housenumber":"166",
    "addr:postcode":"h2y 1e8",
    "addr:street":"Rue Saint-Amable # A",
    "iso:country":"CA",
    "sg:address":"166 Rue Saint-Amable # A",
    "sg:city":"Montreal",
    "sg:classifiers":[
        {
            "category":"Manufacturing",
            "subcategory":"Jewelry",
            "type":"Manufacturing & Wholesale Goods"
        }
    ],
    "sg:phone":"+1 514 875 5831",
    "sg:postcode":"H2Y 1E8",
    "sg:province":"QC",
    "sg:tags":[
        "craft"
    ],
    "wof:name":"Jules Perrier Artisan Inc",
    "wof:placetype":"venue"
},
  "geometry": {"coordinates":[-73.55280303959999,45.5073890686],"type":"Point"}
}