{
  "type": "Feature",
  "properties": {
    "addr:full":"3508 St. Georges Ave North Vancouver BC V7N 1V9",
    "addr:housenumber":"3508",
    "addr:postcode":"v7n 1v9",
    "addr:street":"St. Georges Ave",
    "iso:country":"CA",
    "sg:address":"3508 St. Georges Ave",
    "sg:city":"North Vancouver",
    "sg:classifiers":[
        {
            "category":"Professional",
            "subcategory":"Business Services",
            "type":"Services"
        }
    ],
    "sg:phone":"+1 604 681 2108",
    "sg:postcode":"V7N 1V9",
    "sg:province":"BC",
    "sg:tags":[
        "building",
        "inspection"
    ],
    "wof:name":"National Home Reviews",
    "wof:placetype":"venue"
},
  "geometry": {"coordinates":[-123.06842804,49.3416252136],"type":"Point"}
}