{
  "type": "Feature",
  "properties": {
    "addr:full":"7053 Glacier St Powell River BC V8A 5J7",
    "addr:housenumber":"7053",
    "addr:postcode":"v8a 5j7",
    "addr:street":"Glacier St",
    "iso:country":"CA",
    "sg:address":"7053 Glacier St",
    "sg:city":"Powell River",
    "sg:classifiers":[
        {
            "category":"Organizations",
            "subcategory":"Non-profit Organization",
            "type":"Services"
        }
    ],
    "sg:phone":"+1 604 485 5432",
    "sg:postcode":"V8A 5J7",
    "sg:province":"BC",
    "sg:tags":[
        "alternative",
        "abortion"
    ],
    "wof:name":"Pro-Life Society",
    "wof:placetype":"venue"
},
  "geometry": {"coordinates":[-124.5182724,49.8317604065],"type":"Point"}
}