{
  "type": "Feature",
  "properties": {
    "addr:full":"939 Boul Dr Albiny-Paquette # 27 Mont-Laurier QC J9L 3J1",
    "addr:housenumber":"939;# 27",
    "addr:postcode":"j9l 3j1",
    "addr:street":"Boul Dr Albiny-Paquette",
    "iso:country":"CA",
    "sg:address":"939 Boul Dr Albiny-Paquette # 27",
    "sg:city":"Mont-Laurier",
    "sg:classifiers":[
        {
            "category":"Shopping",
            "subcategory":"Clothing, Apparel, & Fashions",
            "type":"Retail Goods"
        }
    ],
    "sg:phone":"+1 819 623 7759",
    "sg:postcode":"J9L 3J1",
    "sg:province":"QC",
    "sg:tags":[
        "lingerie"
    ],
    "wof:name":"Lingerie Finesse",
    "wof:placetype":"venue"
},
  "geometry": {"coordinates":[-75.4869384766,46.5511207581],"type":"Point"}
}