{
  "type": "Feature",
  "properties": {
    "addr:full":"Leclercville QC G0S 2K0",
    "addr:postcode":"g0s 2k0",
    "iso:country":"CA",
    "sg:city":"Leclercville",
    "sg:classifiers":[
        {
            "category":"Wholesale",
            "subcategory":"Auto Parts",
            "type":"Manufacturing & Wholesale Goods"
        }
    ],
    "sg:phone":"+1 819 292 2501",
    "sg:postcode":"G0S 2K0",
    "sg:province":"QC",
    "sg:tags":[
        "automobile",
        "rebuilt"
    ],
    "wof:name":"Duval, Denis",
    "wof:placetype":"venue"
},
  "geometry": {"coordinates":[-72.003021,46.56842],"type":"Point"}
}