{
  "type": "Feature",
  "properties": {
    "addr:full":"110 Disraeli St Winnipeg MB R2W 3J5",
    "addr:housenumber":"110",
    "addr:postcode":"r2w 3j5",
    "addr:street":"Disraeli St",
    "iso:country":"CA",
    "sg:address":"110 Disraeli St",
    "sg:city":"Winnipeg",
    "sg:classifiers":[
        {
            "category":"Organizations",
            "subcategory":"Religious Organization",
            "type":"Services"
        }
    ],
    "sg:phone":"+1 204 956 0325",
    "sg:postcode":"R2W 3J5",
    "sg:province":"MB",
    "sg:tags":[
        "church"
    ],
    "wof:name":"St Michael's Orthodox Church",
    "wof:placetype":"venue"
},
  "geometry": {"coordinates":[-97.124786,49.906242],"type":"Point"}
}