{
  "type": "Feature",
  "properties": {
    "addr:full":"Valcourt QC J0E 2L0",
    "addr:postcode":"j0e 2l0",
    "iso:country":"CA",
    "sg:city":"Valcourt",
    "sg:classifiers":[
        {
            "category":"Autos & Motor Vehicles",
            "subcategory":"Motorcycle Sales",
            "type":"Retail Goods"
        }
    ],
    "sg:phone":"+1 450 532 4509",
    "sg:postcode":"J0E 2L0",
    "sg:province":"QC",
    "sg:tags":[
        "scooter"
    ],
    "wof:name":"Motocyclette Sajy Enr",
    "wof:placetype":"venue"
},
  "geometry": {"coordinates":[-72.3136978149,45.4863204956],"type":"Point"}
}