{
  "type": "Feature",
  "properties": {
    "iso:country":"CA",
    "sg:address":"2300 Boul Pere-Lelievre",
    "sg:city":"Quebec",
    "sg:classifiers":[
        {
            "category":"Food & Beverages",
            "subcategory":"Groceries & Convenience Stores",
            "type":"Retail Goods"
        }
    ],
    "sg:phone":"+1 418 682 4197",
    "sg:postcode":"G1P 2X5",
    "sg:province":"QC",
    "sg:tags":[
        "grocer"
    ],
    "wof:name":"CO-OP Iga",
    "wof:placetype":"venue"
},
  "geometry": {"coordinates":[-71.298218,46.811783],"type":"Point"}
}