{
  "type": "Feature",
  "properties": {
    "addr:full":"1570 King St E Hamilton ON L8K 1T2",
    "addr:housenumber":"1570",
    "addr:postcode":"l8k 1t2",
    "addr:street":"King St E",
    "iso:country":"CA",
    "sg:address":"1570 King St E",
    "sg:city":"Hamilton",
    "sg:classifiers":[
        {
            "category":"Real Estate",
            "subcategory":"Real Estate Agent",
            "type":"Services"
        }
    ],
    "sg:phone":"+1 905 547 3849",
    "sg:postcode":"L8K 1T2",
    "sg:province":"ON",
    "sg:tags":[
        "management"
    ],
    "wof:name":"Professional Property Mgmt",
    "wof:placetype":"venue"
},
  "geometry": {"coordinates":[-79.81869500000001,43.236015],"type":"Point"}
}