{
  "type": "Feature",
  "properties": {
    "addr:full":"Parksville BC V9P 2G9",
    "addr:postcode":"v9p 2g9",
    "iso:country":"CA",
    "sg:city":"Parksville",
    "sg:classifiers":[
        {
            "category":"Personal",
            "subcategory":"Beauty Salon",
            "type":"Services"
        }
    ],
    "sg:phone":"+1 250 248 6332",
    "sg:postcode":"V9P 2G9",
    "sg:province":"BC",
    "wof:name":"Short Cuts",
    "wof:placetype":"venue"
},
  "geometry": {"coordinates":[-124.315444946,49.3212547302],"type":"Point"}
}