{
  "type": "Feature",
  "properties": {
    "addr:full":"SE 34 20 28 W Russell MB R0J 1W0",
    "addr:housenumber":"34 20 28",
    "addr:postcode":"r0j 1w0",
    "addr:street":"Se;W Russell",
    "iso:country":"CA",
    "sg:address":"SE 34 20 28 W",
    "sg:city":"Russell",
    "sg:classifiers":[
        {
            "category":"Travel",
            "subcategory":"Hotels & Motels",
            "type":"Entertainment"
        }
    ],
    "sg:phone":"+1 204 773 3335",
    "sg:postcode":"R0J 1W0",
    "sg:province":"MB",
    "sg:tags":[
        "farm",
        "resort",
        "equipment"
    ],
    "wof:name":"Keating's",
    "wof:placetype":"venue"
},
  "geometry": {"coordinates":[-101.288269,50.773129],"type":"Point"}
}