{
  "type": "Feature",
  "properties": {
    "iso:country":"CA",
    "sg:address":"585 116 Rte",
    "sg:city":"Saint-Nicolas",
    "sg:classifiers":[
        {
            "category":"Personal",
            "subcategory":"Shoe Repair & Shine",
            "type":"Services"
        }
    ],
    "sg:phone":"+1 418 831 7407",
    "sg:postcode":"G7A 2P6",
    "sg:province":"QC",
    "sg:tags":[
        "repairing",
        "boot"
    ],
    "wof:name":"Boutique Du Cordonnier",
    "wof:placetype":"venue"
},
  "geometry": {"coordinates":[-71.28875732420001,46.7101516724],"type":"Point"}
}