{
  "type": "Feature",
  "properties": {
    "iso:country":"CA",
    "sg:address":"17922 107 Ave NW",
    "sg:city":"Edmonton",
    "sg:classifiers":[
        {
            "category":"Building & Trades",
            "subcategory":"Construction",
            "type":"Services"
        }
    ],
    "sg:phone":"+1 780 484 2777",
    "sg:postcode":"T5S 1J1",
    "sg:province":"AB",
    "sg:tags":[
        "contractor",
        "dry wall",
        "general"
    ],
    "wof:name":"Imperial Drywall Contrg Ltd",
    "wof:placetype":"venue"
},
  "geometry": {"coordinates":[-113.629127502,53.5534858704],"type":"Point"}
}