{
  "type": "Feature",
  "properties": {
    "addr:full":"1920 Ch Gascon Terrebonne QC J6X 2E4",
    "addr:postcode":"1920;j6x 2e4",
    "addr:street":"Ch Gascon",
    "iso:country":"CA",
    "sg:address":"1920 Ch Gascon",
    "sg:city":"Terrebonne",
    "sg:classifiers":[
        {
            "category":"Restaurant",
            "type":"Food & Drink"
        }
    ],
    "sg:phone":"+1 450 961 4444",
    "sg:postcode":"J6X 2E4",
    "sg:province":"QC",
    "wof:name":"Pizza Bravo Express",
    "wof:placetype":"venue"
},
  "geometry": {"coordinates":[-73.658241,45.719238],"type":"Point"}
}