{
  "type": "Feature",
  "properties": {
    "addr:full":"2049 Laval Aut W #200 Laval QC H7L 3W3",
    "addr:housenumber":"2049",
    "addr:postcode":"h7l 3w3",
    "addr:street":"W # 200",
    "iso:country":"CA",
    "sg:address":"2049 Laval Aut W #200",
    "sg:city":"Laval",
    "sg:classifiers":[
        {
            "category":"Manufacturing",
            "subcategory":"Chemicals & Compounds",
            "type":"Manufacturing & Wholesale Goods"
        }
    ],
    "sg:phone":"+1 450 978 6644",
    "sg:postcode":"H7L 3W3",
    "sg:province":"QC",
    "sg:tags":[
        "cleaning"
    ],
    "wof:name":"Ecolab Limited",
    "wof:placetype":"venue"
},
  "geometry": {"coordinates":[-73.744637,45.551567],"type":"Point"}
}