{
  "type": "Feature",
  "properties": {
    "addr:full":"North York ON M3C 3M9",
    "addr:postcode":"m3c 3m9",
    "iso:country":"CA",
    "sg:city":"North York",
    "sg:classifiers":[
        {
            "category":"Health Services",
            "subcategory":"Optometrist",
            "type":"Services"
        }
    ],
    "sg:phone":"+1 416 447 4611",
    "sg:postcode":"M3C 3M9",
    "sg:province":"ON",
    "wof:name":"Don Mills Optometri Clinic",
    "wof:placetype":"venue"
},
  "geometry": {"coordinates":[-79.343735,43.731918],"type":"Point"}
}