{
  "type": "Feature",
  "properties": {
    "addr:full":"Vancouver BC V6J 5B3",
    "addr:postcode":"v6j 5b3",
    "iso:country":"CA",
    "sg:city":"Vancouver",
    "sg:classifiers":[
        {
            "category":"Real Estate",
            "subcategory":"Developer",
            "type":"Services"
        }
    ],
    "sg:phone":"+1 604 734 8443",
    "sg:postcode":"V6J 5B3",
    "sg:province":"BC",
    "sg:tags":[
        "company",
        "land"
    ],
    "wof:name":"Pennyfarthing Development Corp",
    "wof:placetype":"venue"
},
  "geometry": {"coordinates":[-123.140404,49.273174],"type":"Point"}
}