{
  "type": "Feature",
  "properties": {
    "addr:full":"4434 10th Ave W Vancouver BC V6R 2H9",
    "addr:housenumber":"4434",
    "addr:postcode":"v6r 2h9",
    "addr:street":"10Th Ave W",
    "iso:country":"CA",
    "sg:address":"4434 10th Ave W",
    "sg:city":"Vancouver",
    "sg:classifiers":[
        {
            "category":"Restaurant",
            "type":"Food & Drink"
        }
    ],
    "sg:phone":"+1 604 221 7839",
    "sg:postcode":"V6R 2H9",
    "sg:province":"BC",
    "wof:name":"Burgoo Bistro",
    "wof:placetype":"venue"
},
  "geometry": {"coordinates":[-123.20724487299999,49.2636680603],"type":"Point"}
}