{
  "type": "Feature",
  "properties": {
    "addr:full":"Saint-Stanislas-DE-Champlain QC G0X 3E0",
    "addr:postcode":"g0x 3e0",
    "iso:country":"CA",
    "sg:city":"Saint-Stanislas-DE-Champlain",
    "sg:classifiers":[
        {
            "category":"Health Services",
            "subcategory":"Optometrist",
            "type":"Services"
        }
    ],
    "sg:phone":"+1 418 328 8417",
    "sg:postcode":"G0X 3E0",
    "sg:province":"QC",
    "wof:name":"Lynch, Nicole",
    "wof:placetype":"venue"
},
  "geometry": {"coordinates":[-72.385201,46.611389],"type":"Point"}
}