{
  "type": "Feature",
  "properties": {
    "addr:full":"Westbank BC V4T 1Y9",
    "addr:postcode":"v4t 1y9",
    "iso:country":"CA",
    "sg:city":"Westbank",
    "sg:classifiers":[
        {
            "category":"Shopping",
            "subcategory":"Bicycles & Sporting Goods",
            "type":"Retail Goods"
        }
    ],
    "sg:phone":"+1 250 768 7520",
    "sg:postcode":"V4T 1Y9",
    "sg:province":"BC",
    "wof:name":"Replay Sports Exchange",
    "wof:placetype":"venue"
},
  "geometry": {"coordinates":[-119.627045,49.829678],"type":"Point"}
}