{
  "type": "Feature",
  "properties": {
    "addr:full":"81 Balsam St Snow Lake MB R0B 1M0",
    "addr:housenumber":"81",
    "addr:postcode":"r0b 1m0",
    "addr:street":"Balsam St",
    "iso:country":"CA",
    "sg:address":"81 Balsam St",
    "sg:city":"Snow Lake",
    "sg:classifiers":[
        {
            "category":"Banks & Credit Unions",
            "subcategory":"Bank",
            "type":"Services"
        }
    ],
    "sg:phone":"+1 204 358 7711",
    "sg:postcode":"R0B 1M0",
    "sg:province":"MB",
    "wof:name":"Royal Bank Financial Group",
    "wof:placetype":"venue"
},
  "geometry": {"coordinates":[-100.015022,54.874523],"type":"Point"}
}