{
  "type": "Feature",
  "properties": {
    "iso:country":"CA",
    "sg:address":"241 Oak St E",
    "sg:city":"Leamington",
    "sg:classifiers":[
        {
            "category":"Home & Garden",
            "subcategory":"Building Materials",
            "type":"Retail Goods"
        }
    ],
    "sg:phone":"+1 519 326 4474",
    "sg:postcode":"N8H 4W8",
    "sg:province":"ON",
    "wof:name":"Home Building Ctr",
    "wof:placetype":"venue"
},
  "geometry": {"coordinates":[-82.58735656739999,42.0462226868],"type":"Point"}
}