{
  "type": "Feature",
  "properties": {
    "iso:country":"CA",
    "sg:address":"129 Aberdeen Rd",
    "sg:city":"Bridgewater",
    "sg:classifiers":[
        {
            "category":"Government",
            "subcategory":"Office",
            "type":"Public Place"
        }
    ],
    "sg:phone":"+1 902 354 2933",
    "sg:postcode":"B4V 2S7",
    "sg:province":"NS",
    "sg:tags":[
        "village"
    ],
    "wof:name":"South Shore Housing Auth",
    "wof:placetype":"venue"
},
  "geometry": {"coordinates":[-64.516456604,44.3836631775],"type":"Point"}
}