{
  "type": "Feature",
  "properties": {
    "addr:full":"Grand Falls-Windsor NL A2A 2T5",
    "addr:postcode":"a2a 2t5",
    "iso:country":"CA",
    "sg:city":"Grand Falls-Windsor",
    "sg:classifiers":[
        {
            "category":"Government",
            "subcategory":"Office",
            "type":"Public Place"
        }
    ],
    "sg:phone":"+1 709 292 5171",
    "sg:postcode":"A2A 2T5",
    "sg:province":"NL",
    "wof:name":"Canada Licensing Clerk",
    "wof:placetype":"venue"
},
  "geometry": {"coordinates":[-55.6477050781,48.9476356506],"type":"Point"}
}