{
  "type": "Feature",
  "properties": {
    "addr:full":"237 241 Rte Saint-Joachim-DE-Shefford QC J0E 2G0",
    "addr:housenumber":"241",
    "addr:postcode":"j0e 2g0",
    "addr:street":"Rte Saint-Joachim-De-Shefford",
    "iso:country":"CA",
    "sg:address":"237 241 Rte",
    "sg:city":"Saint-Joachim-DE-Shefford",
    "sg:classifiers":[
        {
            "category":"Building & Trades",
            "subcategory":"Plumbing",
            "type":"Services"
        }
    ],
    "sg:phone":"+1 450 539 0057",
    "sg:postcode":"J0E 2G0",
    "sg:province":"QC",
    "sg:tags":[
        "ventilating",
        "conditioning",
        "contractor",
        "system",
        "air"
    ],
    "wof:name":"Ventilation Synergie",
    "wof:placetype":"venue"
},
  "geometry": {"coordinates":[-72.47402954099999,45.3321380615],"type":"Point"}
}