{
  "type": "Feature",
  "properties": {
    "addr:full":"RR 1 Italy Cross NS B0J 1V0",
    "addr:postcode":"b0j 1v0",
    "addr:street":"Rr 1",
    "iso:country":"CA",
    "sg:address":"RR 1",
    "sg:city":"Italy Cross",
    "sg:classifiers":[
        {
            "category":"Organizations",
            "subcategory":"Religious Organization",
            "type":"Services"
        }
    ],
    "sg:phone":"+1 902 943 0183",
    "sg:postcode":"B0J 1V0",
    "sg:province":"NS",
    "sg:tags":[
        "church"
    ],
    "wof:name":"Calvary Lutheran Church",
    "wof:placetype":"venue"
},
  "geometry": {"coordinates":[-64.5493774414,44.2610435486],"type":"Point"}
}