{
  "type": "Feature",
  "properties": {
    "addr:full":"Hwy 83 S Roblin MB R0L 1P0",
    "addr:postcode":"r0l 1p0",
    "addr:street":"Hwy 83 S Roblin",
    "iso:country":"CA",
    "sg:address":"Hwy 83 S",
    "sg:city":"Roblin",
    "sg:classifiers":[
        {
            "category":"Government",
            "subcategory":"Office",
            "type":"Public Place"
        }
    ],
    "sg:phone":"+1 204 937 2181",
    "sg:postcode":"R0L 1P0",
    "sg:province":"MB",
    "wof:name":"Manitoba National Resources",
    "wof:placetype":"venue"
},
  "geometry": {"coordinates":[-101.352081,51.227055],"type":"Point"}
}