{
  "type": "Feature",
  "properties": {
    "addr:full":"6673 Rte 225 Kinkora PE C0B 1N0",
    "addr:housenumber":"6673",
    "addr:postcode":"c0b 1n0",
    "addr:street":"Rte 225",
    "iso:country":"CA",
    "sg:address":"6673 Rte 225",
    "sg:city":"Kinkora",
    "sg:classifiers":[
        {
            "category":"Wholesale",
            "subcategory":"Farm Supplies",
            "type":"Manufacturing & Wholesale Goods"
        }
    ],
    "sg:phone":"+1 902 887 2115",
    "sg:postcode":"C0B 1N0",
    "sg:province":"PE",
    "sg:tags":[
        "fertilizer"
    ],
    "wof:name":"Mc Cain Fertilizers Ltd",
    "wof:placetype":"venue"
},
  "geometry": {"coordinates":[-63.602737,46.32275],"type":"Point"}
}