{
  "type": "Feature",
  "properties": {
    "addr:full":"154 Field Settlement Rd Carlingford NB E7H 2A4",
    "addr:housenumber":"154",
    "addr:postcode":"e7h 2a4",
    "addr:street":"Field Settlement Rd",
    "iso:country":"CA",
    "sg:address":"154 Field Settlement Rd",
    "sg:city":"Carlingford",
    "sg:classifiers":[
        {
            "category":"Retail",
            "subcategory":"Auto Repair",
            "type":"Services"
        }
    ],
    "sg:phone":"+1 506 273 6172",
    "sg:postcode":"E7H 2A4",
    "sg:province":"NB",
    "sg:tags":[
        "repairing",
        "automobile"
    ],
    "wof:name":"Clarke's Auto Repair",
    "wof:placetype":"venue"
},
  "geometry": {"coordinates":[-67.74639892579999,46.7476997375],"type":"Point"}
}