{
  "type": "Feature",
  "properties": {
    "addr:full":"North York ON M9L 1W6",
    "addr:postcode":"m9l 1w6",
    "iso:country":"CA",
    "sg:city":"North York",
    "sg:classifiers":[
        {
            "category":"Wholesale",
            "subcategory":"Construction Materials",
            "type":"Manufacturing & Wholesale Goods"
        }
    ],
    "sg:phone":"+1 416 740 1999",
    "sg:postcode":"M9L 1W6",
    "sg:province":"ON",
    "sg:tags":[
        "equipment",
        "caulking"
    ],
    "wof:name":"Jamac Sales",
    "wof:placetype":"venue"
},
  "geometry": {"coordinates":[-79.54555499999999,43.7668],"type":"Point"}
}