{
  "type": "Feature",
  "properties": {
    "addr:full":"12326 Boul Gouin O Pierrefonds QC H8Z 1W2",
    "addr:housenumber":"12326",
    "addr:postcode":"h8z 1w2",
    "addr:street":"Boul Gouin O",
    "iso:country":"CA",
    "sg:address":"12326 Boul Gouin O",
    "sg:city":"Pierrefonds",
    "sg:classifiers":[
        {
            "category":"Organizations",
            "subcategory":"Religious Organization",
            "type":"Services"
        }
    ],
    "sg:phone":"+1 514 685 3149",
    "sg:postcode":"H8Z 1W2",
    "sg:province":"QC",
    "sg:tags":[
        "church"
    ],
    "wof:name":"Temoins DE Jehovah",
    "wof:placetype":"venue"
},
  "geometry": {"coordinates":[-73.83046,45.505993],"type":"Point"}
}