{
  "type": "Feature",
  "properties": {
    "addr:full":"Thunder Bay ON P7B 5Z6",
    "addr:postcode":"p7b 5z6",
    "iso:country":"CA",
    "sg:city":"Thunder Bay",
    "sg:classifiers":[
        {
            "category":"Real Estate",
            "subcategory":"Developer",
            "type":"Services"
        }
    ],
    "sg:phone":"+1 807 344 1004",
    "sg:postcode":"P7B 5Z6",
    "sg:province":"ON",
    "sg:tags":[
        "cemetery"
    ],
    "wof:name":"Sunset Memorial Gardens",
    "wof:placetype":"venue"
},
  "geometry": {"coordinates":[-89.254257,48.410797],"type":"Point"}
}