{
  "type": "Feature",
  "properties": {
    "iso:country":"CA",
    "sg:address":"3330 Wells Ave",
    "sg:city":"Saskatoon",
    "sg:classifiers":[
        {
            "category":"Building & Trades",
            "subcategory":"Construction",
            "type":"Services"
        }
    ],
    "sg:phone":"+1 306 242 5909",
    "sg:postcode":"S7K 5W7",
    "sg:province":"SK",
    "sg:tags":[
        "roofing",
        "contractor"
    ],
    "wof:name":"Flynn Canada Ltd",
    "wof:placetype":"venue"
},
  "geometry": {"coordinates":[-106.64838409399999,52.1846580505],"type":"Point"}
}