{
  "type": "Feature",
  "properties": {
    "addr:full":"2350 Rue Des Ormeaux Montreal QC H1L 4X3",
    "addr:housenumber":"2350",
    "addr:postcode":"h1l 4x3",
    "addr:street":"Rue Des Ormeaux",
    "iso:country":"CA",
    "sg:address":"2350 Rue Des Ormeaux",
    "sg:city":"Montreal",
    "sg:classifiers":[
        {
            "category":"Shopping",
            "type":"Retail Goods"
        }
    ],
    "sg:phone":"+1 514 351 0032",
    "sg:postcode":"H1L 4X3",
    "sg:province":"QC",
    "sg:tags":[
        "pet",
        "shop"
    ],
    "wof:name":"Boutique Pour Animaux Y Lewis",
    "wof:placetype":"venue"
},
  "geometry": {"coordinates":[-73.5188903809,45.6010894775],"type":"Point"}
}