{
  "type": "Feature",
  "properties": {
    "iso:country":"CA",
    "sg:address":"2350 Rue Des Ormeaux",
    "sg:city":"Montreal",
    "sg:classifiers":[
        {
            "category":"Shopping",
            "type":"Retail Goods"
        }
    ],
    "sg:phone":"+1 514 351 0032",
    "sg:postcode":"H1L 4X3",
    "sg:province":"QC",
    "sg:tags":[
        "pet",
        "shop"
    ],
    "wof:name":"Boutique Pour Animaux Y Lewis",
    "wof:placetype":"venue"
},
  "geometry": {"coordinates":[-73.5188903809,45.6010894775],"type":"Point"}
}