{
  "type": "Feature",
  "properties": {
    "iso:country":"CA",
    "sg:city":"Plantagenet",
    "sg:classifiers":[
        {
            "category":"Building & Trades",
            "subcategory":"Construction",
            "type":"Services"
        }
    ],
    "sg:phone":"+1 613 673 4017",
    "sg:postcode":"K0B 1L0",
    "sg:province":"ON",
    "sg:tags":[
        "designer",
        "dealer",
        "pool",
        "swimming"
    ],
    "wof:name":"Mci Pools",
    "wof:placetype":"venue"
},
  "geometry": {"coordinates":[-74.99816894529999,45.5352592468],"type":"Point"}
}