{
  "type": "Feature",
  "properties": {
    "iso:country":"CA",
    "sg:address":"47 Rue Principale S",
    "sg:city":"Saint-Jean-DE-Dieu",
    "sg:classifiers":[
        {
            "category":"Local Transit",
            "type":"Transportation"
        }
    ],
    "sg:phone":"+1 418 963 2917",
    "sg:postcode":"G0L 3M0",
    "sg:province":"QC",
    "sg:tags":[
        "bus",
        "line"
    ],
    "wof:name":"Gervais Rouleau Inc",
    "wof:placetype":"venue"
},
  "geometry": {"coordinates":[-69.04615020750001,48.0059585571],"type":"Point"}
}