{
  "type": "Feature",
  "properties": {
    "addr:full":"1120 11th Ave Regina SK S4P 0G3",
    "addr:housenumber":"1120",
    "addr:postcode":"s4p 0g3",
    "addr:street":"11Th Ave",
    "iso:country":"CA",
    "sg:address":"1120 11th Ave",
    "sg:city":"Regina",
    "sg:classifiers":[
        {
            "category":"Shopping",
            "subcategory":"Used Merchandise",
            "type":"Retail Goods"
        }
    ],
    "sg:phone":"+1 306 352 2274",
    "sg:postcode":"S4P 0G3",
    "sg:province":"SK",
    "sg:tags":[
        "pawnbroker"
    ],
    "wof:name":"Capital Pawn & Gun Ltd",
    "wof:placetype":"venue"
},
  "geometry": {"coordinates":[-104.596649,50.450569],"type":"Point"}
}