{
  "type": "Feature",
  "properties": {
    "addr:full":"Vancouver BC V6J 1G1",
    "addr:postcode":"v6j 1g1",
    "iso:country":"CA",
    "sg:city":"Vancouver",
    "sg:classifiers":[
        {
            "category":"Personal",
            "subcategory":"Beauty Salon",
            "type":"Services"
        }
    ],
    "sg:phone":"+1 604 733 3712",
    "sg:postcode":"V6J 1G1",
    "sg:province":"BC",
    "wof:name":"Sonny Off Broadway Hair Design",
    "wof:placetype":"venue"
},
  "geometry": {"coordinates":[-123.141739,49.270527],"type":"Point"}
}