{
  "type": "Feature",
  "properties": {
    "iso:country":"CA",
    "sg:city":"Killarney",
    "sg:classifiers":[
        {
            "category":"Travel",
            "subcategory":"Campground",
            "type":"Entertainment"
        }
    ],
    "sg:phone":"+1 705 287 2089",
    "sg:postcode":"P0M 2A0",
    "sg:province":"ON",
    "sg:tags":[
        "camp"
    ],
    "wof:name":"Mahzenazing River Lodge",
    "wof:placetype":"venue"
},
  "geometry": {"coordinates":[-81.5101470947,45.9735984802],"type":"Point"}
}