{
  "type": "Feature",
  "properties": {
    "addr:full":"151 King St S Alliston ON L9R 1B2",
    "addr:housenumber":"151",
    "addr:postcode":"l9r 1b2",
    "addr:street":"King St S Alliston",
    "iso:country":"CA",
    "sg:address":"151 King St S",
    "sg:city":"Alliston",
    "sg:classifiers":[
        {
            "category":"Home & Garden",
            "subcategory":"Household Appliances",
            "type":"Retail Goods"
        }
    ],
    "sg:phone":"+1 705 435 7457",
    "sg:postcode":"L9R 1B2",
    "sg:province":"ON",
    "sg:tags":[
        "cleaners",
        "carpet",
        "rug",
        "vacuum"
    ],
    "wof:name":"Crown Carpet Care",
    "wof:placetype":"venue"
},
  "geometry": {"coordinates":[-79.876701,44.144562],"type":"Point"}
}