{
  "type": "Feature",
  "properties": {
    "iso:country":"CA",
    "sg:address":"181 Saunders Rd",
    "sg:city":"Barrie",
    "sg:classifiers":[
        {
            "category":"Manufacturing",
            "subcategory":"Tools & Machinery",
            "type":"Manufacturing & Wholesale Goods"
        }
    ],
    "sg:phone":"+1 705 722 0800",
    "sg:postcode":"L4N 9A3",
    "sg:province":"ON",
    "sg:tags":[
        "die",
        "maker"
    ],
    "wof:name":"Beta Tech Inc",
    "wof:placetype":"venue"
},
  "geometry": {"coordinates":[-79.67497299999999,44.332626],"type":"Point"}
}