{
  "type": "Feature",
  "properties": {
    "addr:full":"125 Water St Gananoque ON K7G 3E3",
    "addr:housenumber":"125",
    "addr:postcode":"k7g 3e3",
    "addr:street":"Water St",
    "iso:country":"CA",
    "sg:address":"125 Water St",
    "sg:city":"Gananoque",
    "sg:classifiers":[
        {
            "category":"Retail",
            "subcategory":"Laundry & Dry Cleaning",
            "type":"Services"
        }
    ],
    "sg:phone":"+1 613 382 3665",
    "sg:postcode":"K7G 3E3",
    "sg:province":"ON",
    "sg:tags":[
        "cleaners"
    ],
    "wof:name":"West Town Coin Laundry",
    "wof:placetype":"venue"
},
  "geometry": {"coordinates":[-76.1596832275,44.3252906799],"type":"Point"}
}