{
  "type": "Feature",
  "properties": {
    "addr:full":"Thorold ON L2V 4Y6",
    "addr:postcode":"l2v 4y6",
    "iso:country":"CA",
    "sg:city":"Thorold",
    "sg:classifiers":[
        {
            "category":"Professional",
            "subcategory":"Computer Services",
            "type":"Services"
        }
    ],
    "sg:phone":"+1 905 984 8388",
    "sg:postcode":"L2V 4Y6",
    "sg:province":"ON",
    "sg:tags":[
        "website",
        "design",
        "internet"
    ],
    "wof:name":"Computan",
    "wof:placetype":"venue"
},
  "geometry": {"coordinates":[-79.243134,43.112328],"type":"Point"}
}