{
  "type": "Feature",
  "properties": {
    "addr:full":"59 King St E Bowmanville ON L1C 1N4",
    "addr:housenumber":"59",
    "addr:postcode":"l1c 1n4",
    "addr:street":"King St",
    "iso:country":"CA",
    "sg:address":"59 King St E",
    "sg:city":"Bowmanville",
    "sg:classifiers":[
        {
            "category":"Restaurant",
            "type":"Food & Drink"
        }
    ],
    "sg:phone":"+1 905 623 1222",
    "sg:postcode":"L1C 1N4",
    "sg:province":"ON",
    "wof:name":"Sunrise Restaurant",
    "wof:placetype":"venue"
},
  "geometry": {"coordinates":[-78.687325,43.911606],"type":"Point"}
}