{
  "type": "Feature",
  "properties": {
    "addr:full":"Calgary AB T2E 6L1",
    "addr:postcode":"t2e 6l1",
    "iso:country":"CA",
    "sg:city":"Calgary",
    "sg:classifiers":[
        {
            "category":"Building & Trades",
            "subcategory":"Construction",
            "type":"Services"
        }
    ],
    "sg:phone":"+1 403 291 4837",
    "sg:postcode":"T2E 6L1",
    "sg:province":"AB",
    "sg:tags":[
        "dry wall",
        "contractor"
    ],
    "wof:name":"Kds Supply Ltd",
    "wof:placetype":"venue"
},
  "geometry": {"coordinates":[-114.029731751,51.0888633728],"type":"Point"}
}