{
  "type": "Feature",
  "properties": {
    "addr:full":"617 Windmill Rd Dartmouth NS B3B 1B6",
    "addr:housenumber":"617",
    "addr:postcode":"b3b 1b6",
    "addr:street":"Windmill Rd",
    "iso:country":"CA",
    "sg:address":"617 Windmill Rd",
    "sg:city":"Dartmouth",
    "sg:classifiers":[
        {
            "category":"Manufacturing",
            "subcategory":"Metals",
            "type":"Manufacturing & Wholesale Goods"
        }
    ],
    "sg:phone":"+1 902 481 0239",
    "sg:postcode":"B3B 1B6",
    "sg:province":"NS",
    "sg:tags":[
        "field",
        "oil",
        "equipment"
    ],
    "wof:name":"K & D United Safety Svc Ltd",
    "wof:placetype":"venue"
},
  "geometry": {"coordinates":[-63.6028442383,44.6967124939],"type":"Point"}
}