{
  "type": "Feature",
  "properties": {
    "addr:full":"1101 Connecticut Dr Stephenville NL A2N 2Y9",
    "addr:housenumber":"1101",
    "addr:postcode":"a2n 2y9",
    "addr:street":"Connecticut Dr",
    "iso:country":"CA",
    "sg:address":"1101 Connecticut Dr",
    "sg:city":"Stephenville",
    "sg:classifiers":[
        {
            "category":"Wholesale",
            "subcategory":"Scrap",
            "type":"Manufacturing & Wholesale Goods"
        }
    ],
    "sg:phone":"+1 709 643 5546",
    "sg:postcode":"A2N 2Y9",
    "sg:province":"NL",
    "sg:tags":[
        "metal",
        "iron"
    ],
    "wof:name":"K & J Metals",
    "wof:placetype":"venue"
},
  "geometry": {"coordinates":[-58.554382,48.557083],"type":"Point"}
}