{
  "type": "Feature",
  "properties": {
    "addr:full":"96 Pinnacle St S Belleville ON K8N 5P5",
    "addr:housenumber":"96",
    "addr:postcode":"k8n 5p5",
    "addr:street":"Pinnacle St S",
    "iso:country":"CA",
    "sg:address":"96 Pinnacle St S",
    "sg:city":"Belleville",
    "sg:classifiers":[
        {
            "category":"Personal",
            "subcategory":"Beauty Salon",
            "type":"Services"
        }
    ],
    "sg:phone":"+1 613 967 2887",
    "sg:postcode":"K8N 5P5",
    "sg:province":"ON",
    "wof:name":"Studio Dk Hair Design",
    "wof:placetype":"venue"
},
  "geometry": {"coordinates":[-77.38093600000001,44.160091],"type":"Point"}
}