{
  "type": "Feature",
  "properties": {
    "addr:full":"1033 Black Rd Sault Ste Marie ON P6A 6J8",
    "addr:housenumber":"1033",
    "addr:postcode":"p6a 6j8",
    "addr:street":"Black Rd",
    "iso:country":"CA",
    "sg:address":"1033 Black Rd",
    "sg:city":"Sault Ste Marie",
    "sg:classifiers":[
        {
            "category":"Home & Garden",
            "subcategory":"Furniture",
            "type":"Retail Goods"
        }
    ],
    "sg:phone":"+1 705 946 2975",
    "sg:postcode":"P6A 6J8",
    "sg:province":"ON",
    "sg:tags":[
        "downspouts",
        "gutter"
    ],
    "wof:name":"Seamless Eavestrough Ltd",
    "wof:placetype":"venue"
},
  "geometry": {"coordinates":[-84.2882843018,46.5506401062],"type":"Point"}
}