{
  "type": "Feature",
  "properties": {
    "addr:full":"Lloydminster AB T9V 2C9",
    "addr:postcode":"t9v 2c9",
    "iso:country":"CA",
    "sg:city":"Lloydminster",
    "sg:classifiers":[
        {
            "category":"Utilities",
            "subcategory":"Mobile Phone",
            "type":"Services"
        }
    ],
    "sg:phone":"+1 780 875 1818",
    "sg:postcode":"T9V 2C9",
    "sg:province":"AB",
    "sg:tags":[
        "telephone",
        "cellular"
    ],
    "wof:name":"Northwind Radio Ltd",
    "wof:placetype":"venue"
},
  "geometry": {"coordinates":[-110.005661,53.301205],"type":"Point"}
}