{
  "type": "Feature",
  "properties": {
    "addr:full":"6321 Aut Transcanadienne Pointe-Claire QC H9R 5A5",
    "addr:postcode":"6321;h9r 5a5",
    "addr:street":"Transcanadienne",
    "iso:country":"CA",
    "sg:address":"6321 Aut Transcanadienne",
    "sg:city":"Pointe-Claire",
    "sg:classifiers":[
        {
            "category":"Restaurant",
            "type":"Food & Drink"
        }
    ],
    "sg:phone":"+1 514 694 4915",
    "sg:postcode":"H9R 5A5",
    "sg:province":"QC",
    "wof:name":"Cage Aux Sports",
    "wof:placetype":"venue"
},
  "geometry": {"coordinates":[-73.838219,45.457832],"type":"Point"}
}