{
  "type": "Feature",
  "properties": {
    "iso:country":"CA",
    "sg:city":"Brampton",
    "sg:classifiers":[
        {
            "category":"Professional",
            "subcategory":"Business Services",
            "type":"Services"
        }
    ],
    "sg:phone":"+1 905 799 1694",
    "sg:postcode":"L6T 5H1",
    "sg:province":"ON",
    "sg:tags":[
        "liquidator"
    ],
    "wof:name":"Superior Liquidation",
    "wof:placetype":"venue"
},
  "geometry": {"coordinates":[-79.68728637700001,43.7200508118],"type":"Point"}
}