{
  "type": "Feature",
  "properties": {
    "iso:country":"CA",
    "sg:address":"2023 Boul Saint-Laurent",
    "sg:city":"Montreal",
    "sg:classifiers":[
        {
            "category":"Manufacturing",
            "subcategory":"Metals",
            "type":"Manufacturing & Wholesale Goods"
        }
    ],
    "sg:phone":"+1 514 849 4238",
    "sg:postcode":"H2X 2T3",
    "sg:province":"QC",
    "sg:tags":[
        "tool"
    ],
    "wof:name":"Price Plus Inc",
    "wof:placetype":"venue"
},
  "geometry": {"coordinates":[-73.567078,45.511593],"type":"Point"}
}