{
  "type": "Feature",
  "properties": {
    "addr:full":"995 Peter Robertson Blvd Brampton ON L6R 2E9",
    "addr:housenumber":"995",
    "addr:postcode":"l6r 2e9",
    "addr:street":"Peter Robertson Blvd",
    "iso:country":"CA",
    "sg:address":"995 Peter Robertson Blvd",
    "sg:city":"Brampton",
    "sg:classifiers":[
        {
            "category":"Government",
            "subcategory":"Office",
            "type":"Public Place"
        }
    ],
    "sg:phone":"+1 905 789 6111",
    "sg:postcode":"L6R 2E9",
    "sg:province":"ON",
    "sg:tags":[
        "village"
    ],
    "wof:name":"Brampton Wellness Ctr",
    "wof:placetype":"venue"
},
  "geometry": {"coordinates":[-79.7430343628,43.7500801086],"type":"Point"}
}