{
  "type": "Feature",
  "properties": {
    "iso:country":"CA",
    "sg:city":"Bracebridge",
    "sg:classifiers":[
        {
            "category":"Sports & Exercise",
            "subcategory":"Golf",
            "type":"Entertainment"
        }
    ],
    "sg:phone":"+1 705 646 1060",
    "sg:postcode":"P1L 1W8",
    "sg:province":"ON",
    "sg:tags":[
        "course"
    ],
    "wof:name":"Muskoka Highlands Golf Course",
    "wof:placetype":"venue"
},
  "geometry": {"coordinates":[-79.37260437010001,45.0850067139],"type":"Point"}
}