{
  "type": "Feature",
  "properties": {
    "addr:full":"Surrey BC V3W 4M8",
    "addr:postcode":"v3w 4m8",
    "iso:country":"CA",
    "sg:city":"Surrey",
    "sg:classifiers":[
        {
            "category":"Manufacturing",
            "subcategory":"Metals",
            "type":"Manufacturing & Wholesale Goods"
        }
    ],
    "sg:phone":"+1 604 596 7001",
    "sg:postcode":"V3W 4M8",
    "sg:province":"BC",
    "sg:tags":[
        "steel"
    ],
    "wof:name":"Canneth Industries Ltd",
    "wof:placetype":"venue"
},
  "geometry": {"coordinates":[-122.85700199999999,49.144951],"type":"Point"}
}