{
  "type": "Feature",
  "properties": {
    "addr:full":"3495 Lawrence Ave E # Cb018F Scarborough ON M1H 1B3",
    "addr:housenumber":"3495",
    "addr:postcode":"m1h 1b3",
    "addr:street":"Lawrence Ave E # Cb018F",
    "iso:country":"CA",
    "sg:address":"3495 Lawrence Ave E # Cb018F",
    "sg:city":"Scarborough",
    "sg:classifiers":[
        {
            "category":"Restaurant",
            "type":"Food & Drink"
        }
    ],
    "sg:phone":"+1 416 438 6447",
    "sg:postcode":"M1H 1B3",
    "sg:province":"ON",
    "wof:name":"Asian Gourmet",
    "wof:placetype":"venue"
},
  "geometry": {"coordinates":[-79.228767,43.758938],"type":"Point"}
}