{
  "type": "Feature",
  "properties": {
    "addr:full":"415 Queen St W Toronto ON M5V 2A5",
    "addr:housenumber":"415",
    "addr:postcode":"m5v 2a5",
    "addr:street":"Queen St W",
    "iso:country":"CA",
    "sg:address":"415 Queen St W",
    "sg:city":"Toronto",
    "sg:classifiers":[
        {
            "category":"Shopping",
            "subcategory":"Musical Instruments",
            "type":"Retail Goods"
        }
    ],
    "sg:phone":"+1 416 593 8888",
    "sg:postcode":"M5V 2A5",
    "sg:province":"ON",
    "wof:name":"Steve's Music Store",
    "wof:placetype":"venue"
},
  "geometry": {"coordinates":[-79.395111,43.648865],"type":"Point"}
}