{
  "type": "Feature",
  "properties": {
    "addr:full":"770 Av Ogilvy Montreal QC H3N 1N7",
    "addr:postcode":"h3n 1n7",
    "addr:street":"770 Av Ogilvy",
    "iso:country":"CA",
    "sg:address":"770 Av Ogilvy",
    "sg:city":"Montreal",
    "sg:classifiers":[
        {
            "category":"Cinema",
            "subcategory":"Movie Rental",
            "type":"Entertainment"
        }
    ],
    "sg:phone":"+1 514 277 8631",
    "sg:postcode":"H3N 1N7",
    "sg:province":"QC",
    "sg:tags":[
        "leasing",
        "video",
        "disc",
        "tape"
    ],
    "wof:name":"My Choice Videocentre",
    "wof:placetype":"venue"
},
  "geometry": {"coordinates":[-73.6262054443,45.5271034241],"type":"Point"}
}