{
  "type": "Feature",
  "properties": {
    "iso:country":"CA",
    "sg:address":"157 Metcalf St",
    "sg:city":"Saint John",
    "sg:classifiers":[
        {
            "category":"Food & Beverages",
            "subcategory":"Groceries & Convenience Stores",
            "type":"Retail Goods"
        }
    ],
    "sg:phone":"+1 506 635 5855",
    "sg:postcode":"E2K 1K2",
    "sg:province":"NB",
    "wof:name":"Smart Choice Variety",
    "wof:placetype":"venue"
},
  "geometry": {"coordinates":[-66.081657,45.276234],"type":"Point"}
}