{
  "type": "Feature",
  "properties": {
    "addr:full":"Hwy 5 E Humboldt SK S0K 2A0",
    "addr:postcode":"s0k 2a0",
    "addr:street":"Hwy 5 E",
    "iso:country":"CA",
    "sg:address":"Hwy 5 E",
    "sg:city":"Humboldt",
    "sg:classifiers":[
        {
            "category":"Home & Garden",
            "subcategory":"Building Materials",
            "type":"Retail Goods"
        }
    ],
    "sg:phone":"+1 306 682 4340",
    "sg:postcode":"S0K 2A0",
    "sg:province":"SK",
    "sg:tags":[
        "mixed",
        "concrete"
    ],
    "wof:name":"Brockman Redi-Mix",
    "wof:placetype":"venue"
},
  "geometry": {"coordinates":[-105.092545,52.201939],"type":"Point"}
}