{
  "type": "Feature",
  "properties": {
    "addr:full":"Saint John NB E2K 1J5",
    "addr:postcode":"e2k 1j5",
    "iso:country":"CA",
    "sg:city":"Saint John",
    "sg:classifiers":[
        {
            "category":"Real Estate",
            "subcategory":"Real Estate Agent",
            "type":"Services"
        }
    ],
    "sg:phone":"+1 506 657 1212",
    "sg:postcode":"E2K 1J5",
    "sg:province":"NB",
    "wof:name":"Prudential Summit Real Estate",
    "wof:placetype":"venue"
},
  "geometry": {"coordinates":[-66.07335662840001,45.2753829956],"type":"Point"}
}