{
  "type": "Feature",
  "properties": {
    "addr:full":"2606 Pandosy St Kelowna BC V1Y 1V6",
    "addr:housenumber":"2606",
    "addr:postcode":"v1y 1v6",
    "addr:street":"Pandosy St",
    "iso:country":"CA",
    "sg:address":"2606 Pandosy St",
    "sg:city":"Kelowna",
    "sg:classifiers":[
        {
            "category":"Health Services",
            "subcategory":"Doctor",
            "type":"Services"
        }
    ],
    "sg:phone":"+1 250 762 9211",
    "sg:postcode":"V1Y 1V6",
    "sg:province":"BC",
    "sg:tags":[
        "physician",
        "surgeon"
    ],
    "wof:name":"Pistawka, Kevin J MD",
    "wof:placetype":"venue"
},
  "geometry": {"coordinates":[-119.491394,49.867168],"type":"Point"}
}