{
  "type": "Feature",
  "properties": {
    "addr:full":"Richmond BC V7C 1V2",
    "addr:postcode":"v7c 1v2",
    "iso:country":"CA",
    "sg:city":"Richmond",
    "sg:classifiers":[
        {
            "category":"Personal",
            "subcategory":"Shoe Repair & Shine",
            "type":"Services"
        }
    ],
    "sg:phone":"+1 604 272 0119",
    "sg:postcode":"V7C 1V2",
    "sg:province":"BC",
    "sg:tags":[
        "repairing",
        "boot"
    ],
    "wof:name":"Alex's Shoe Repair",
    "wof:placetype":"venue"
},
  "geometry": {"coordinates":[-123.181442,49.149719],"type":"Point"}
}