{
  "type": "Feature",
  "properties": {
    "addr:full":"300 Rue Barkoff # 196 Cap-DE-LA-Madeleine QC G8T 2A3",
    "addr:housenumber":"300",
    "addr:postcode":"g8t 2a3",
    "addr:street":"Rue Barkoff # 196 Cap-De-La-Madeleine",
    "iso:country":"CA",
    "sg:address":"300 Rue Barkoff # 196",
    "sg:city":"Cap-DE-LA-Madeleine",
    "sg:classifiers":[
        {
            "category":"Shopping",
            "subcategory":"Pharmacy",
            "type":"Retail Goods"
        }
    ],
    "sg:phone":"+1 819 378 4829",
    "sg:postcode":"G8T 2A3",
    "sg:province":"QC",
    "wof:name":"Jean Coutu",
    "wof:placetype":"venue"
},
  "geometry": {"coordinates":[-72.5581436157,46.3718528748],"type":"Point"}
}