{
  "type": "Feature",
  "properties": {
    "iso:country":"CA",
    "sg:city":"Scarborough",
    "sg:classifiers":[
        {
            "category":"Building & Trades",
            "subcategory":"Equipment Rental",
            "type":"Services"
        }
    ],
    "sg:phone":"+1 416 292 4771",
    "sg:postcode":"M1V 2T3",
    "sg:province":"ON",
    "sg:tags":[
        "leasing"
    ],
    "wof:name":"Mayo & Assoc",
    "wof:placetype":"venue"
},
  "geometry": {"coordinates":[-79.248314,43.819656],"type":"Point"}
}