{
  "type": "Feature",
  "properties": {
    "addr:full":"51 Augusta St Hamilton ON L8N 1P8",
    "addr:postcode":"l8n 1p8",
    "addr:street":"51 Augusta St",
    "iso:country":"CA",
    "sg:address":"51 Augusta St",
    "sg:city":"Hamilton",
    "sg:classifiers":[
        {
            "category":"Personal",
            "subcategory":"Beauty Salon",
            "type":"Services"
        }
    ],
    "sg:phone":"+1 905 529 7586",
    "sg:postcode":"L8N 1P8",
    "sg:province":"ON",
    "wof:name":"Carmen Hair Group",
    "wof:placetype":"venue"
},
  "geometry": {"coordinates":[-79.869141,43.251846],"type":"Point"}
}