{
  "type": "Feature",
  "properties": {
    "addr:full":"294 Windmill Rd Dartmouth NS B3A 1H1",
    "addr:housenumber":"294",
    "addr:postcode":"b3a 1h1",
    "addr:street":"Windmill Rd",
    "iso:country":"CA",
    "sg:address":"294 Windmill Rd",
    "sg:city":"Dartmouth",
    "sg:classifiers":[
        {
            "category":"Retail",
            "subcategory":"Car Wash",
            "type":"Services"
        }
    ],
    "sg:phone":"+1 902 466 3577",
    "sg:postcode":"B3A 1H1",
    "sg:province":"NS",
    "sg:tags":[
        "polishing",
        "automobile",
        "washing",
        "detail"
    ],
    "wof:name":"Al-N-Moe Auto Shine",
    "wof:placetype":"venue"
},
  "geometry": {"coordinates":[-63.591084,44.676857],"type":"Point"}
}