{
  "type": "Feature",
  "properties": {
    "iso:country":"CA",
    "sg:address":"1607 Idylwyld Dr N",
    "sg:city":"Saskatoon",
    "sg:classifiers":[
        {
            "category":"Restaurant",
            "type":"Food & Drink"
        }
    ],
    "sg:phone":"+1 306 955 9378",
    "sg:postcode":"S7L 1B2",
    "sg:province":"SK",
    "wof:name":"A & W Family Restaurant",
    "wof:placetype":"venue"
},
  "geometry": {"coordinates":[-106.670524597,52.1503067017],"type":"Point"}
}