{
  "type": "Feature",
  "properties": {
    "addr:full":"80 Rue Principale Sainte-Claire QC G0R 2V0",
    "addr:housenumber":"80",
    "addr:postcode":"g0r 2v0",
    "addr:street":"Rue Principale",
    "iso:country":"CA",
    "sg:address":"80 Rue Principale",
    "sg:city":"Sainte-Claire",
    "sg:classifiers":[
        {
            "category":"Wholesale",
            "subcategory":"Machinery & Supplies",
            "type":"Manufacturing & Wholesale Goods"
        }
    ],
    "sg:phone":"+1 418 883 3364",
    "sg:postcode":"G0R 2V0",
    "sg:province":"QC",
    "sg:tags":[
        "equipment",
        "dairy"
    ],
    "wof:name":"Equipement Denis Chabot Inc",
    "wof:placetype":"venue"
},
  "geometry": {"coordinates":[-70.8716506958,46.5987815857],"type":"Point"}
}