{
  "type": "Feature",
  "properties": {
    "addr:full":"425 58 Ave SE Calgary AB T2H 0P5",
    "addr:housenumber":"425",
    "addr:postcode":"t2h 0p5",
    "addr:street":"58 Ave Se",
    "iso:country":"CA",
    "sg:address":"425 58 Ave SE",
    "sg:city":"Calgary",
    "sg:classifiers":[
        {
            "category":"Retail",
            "subcategory":"Auto Repair",
            "type":"Services"
        }
    ],
    "sg:phone":"+1 403 253 7863",
    "sg:postcode":"T2H 0P5",
    "sg:province":"AB",
    "sg:tags":[
        "repairing",
        "automobile"
    ],
    "wof:name":"Cetus Automotive Repair Ctr",
    "wof:placetype":"venue"
},
  "geometry": {"coordinates":[-114.056129,51.001202],"type":"Point"}
}