{
  "type": "Feature",
  "properties": {
    "addr:full":"1805 8E Rue Saint-Prosper-DE-Dorchester QC G0M 1Y0",
    "addr:housenumber":"1805",
    "addr:postcode":"g0m 1y0",
    "addr:street":"8E Rue Saint-Prosper-De-Dorchester",
    "iso:country":"CA",
    "sg:address":"1805 8E Rue",
    "sg:city":"Saint-Prosper-DE-Dorchester",
    "sg:classifiers":[
        {
            "category":"Shopping",
            "subcategory":"Bicycles & Sporting Goods",
            "type":"Retail Goods"
        }
    ],
    "sg:phone":"+1 418 594 5117",
    "sg:postcode":"G0M 1Y0",
    "sg:province":"QC",
    "wof:name":"Rodrigue Sports Inc",
    "wof:placetype":"venue"
},
  "geometry": {"coordinates":[-70.49774932859999,46.2215538025],"type":"Point"}
}