{
  "type": "Feature",
  "properties": {
    "iso:country":"CA",
    "sg:address":"209 Zina St",
    "sg:city":"Orangeville",
    "sg:classifiers":[
        {
            "category":"Professional",
            "subcategory":"Management & Consulting",
            "type":"Services"
        }
    ],
    "sg:phone":"+1 519 941 3250",
    "sg:postcode":"L9W 1E9",
    "sg:province":"ON",
    "sg:tags":[
        "consultant",
        "business"
    ],
    "wof:name":"Harold Doan & Assoc Ltd",
    "wof:placetype":"venue"
},
  "geometry": {"coordinates":[-80.1098327637,43.9177322388],"type":"Point"}
}