{
  "type": "Feature",
  "properties": {
    "addr:full":"71 Rue Principale Chateauguay QC J6K 1G1",
    "addr:housenumber":"71",
    "addr:postcode":"j6k 1g1",
    "addr:street":"Rue Principale",
    "iso:country":"CA",
    "sg:address":"71 Rue Principale",
    "sg:city":"Chateauguay",
    "sg:classifiers":[
        {
            "category":"Organizations",
            "subcategory":"Professional Association",
            "type":"Services"
        }
    ],
    "sg:phone":"+1 450 692 9805",
    "sg:postcode":"J6K 1G1",
    "sg:province":"QC",
    "wof:name":"Re-Nou-Vie",
    "wof:placetype":"venue"
},
  "geometry": {"coordinates":[-73.750938,45.359524],"type":"Point"}
}