{
  "type": "Feature",
  "properties": {
    "addr:full":"213 1st Ave W Clandonald AB T0B 0X0",
    "addr:housenumber":"213",
    "addr:postcode":"t0b 0x0",
    "addr:street":"1St Ave W",
    "iso:country":"CA",
    "sg:address":"213 1st Ave W",
    "sg:city":"Clandonald",
    "sg:classifiers":[
        {
            "category":"Education",
            "subcategory":"School",
            "type":"Public Place"
        }
    ],
    "sg:phone":"+1 780 853 2122",
    "sg:postcode":"T0B 0X0",
    "sg:province":"AB",
    "wof:name":"Clandonald School",
    "wof:placetype":"venue"
},
  "geometry": {"coordinates":[-110.731171,53.569775],"type":"Point"}
}