{
  "type": "Feature",
  "properties": {
    "addr:full":"Surrey BC V3W 3V6",
    "addr:postcode":"v3w 3v6",
    "iso:country":"CA",
    "sg:city":"Surrey",
    "sg:classifiers":[
        {
            "category":"Home & Garden",
            "subcategory":"Furniture",
            "type":"Retail Goods"
        }
    ],
    "sg:phone":"+1 604 502 9552",
    "sg:postcode":"V3W 3V6",
    "sg:province":"BC",
    "sg:tags":[
        "top",
        "counter"
    ],
    "wof:name":"Porterhill Countertops",
    "wof:placetype":"venue"
},
  "geometry": {"coordinates":[-122.882041931,49.1583328247],"type":"Point"}
}