{
  "type": "Feature",
  "properties": {
    "iso:country":"CA",
    "sg:address":"940 Gateway St",
    "sg:city":"Burlington",
    "sg:classifiers":[
        {
            "category":"Wholesale",
            "subcategory":"Electrical",
            "type":"Manufacturing & Wholesale Goods"
        }
    ],
    "sg:phone":"+1 905 632 6894",
    "sg:postcode":"L7L 5K7",
    "sg:province":"ON",
    "sg:tags":[
        "equipment",
        "electronic",
        "supply"
    ],
    "wof:name":"White Radio Ltd",
    "wof:placetype":"venue"
},
  "geometry": {"coordinates":[-79.758209,43.388935],"type":"Point"}
}