{
  "type": "Feature",
  "properties": {
    "addr:full":"940 Gateway St Burlington ON L7L 5K7",
    "addr:housenumber":"940",
    "addr:postcode":"l7l 5k7",
    "addr:street":"Gateway St",
    "iso:country":"CA",
    "sg:address":"940 Gateway St",
    "sg:city":"Burlington",
    "sg:classifiers":[
        {
            "category":"Wholesale",
            "subcategory":"Electrical",
            "type":"Manufacturing & Wholesale Goods"
        }
    ],
    "sg:phone":"+1 905 632 6894",
    "sg:postcode":"L7L 5K7",
    "sg:province":"ON",
    "sg:tags":[
        "equipment",
        "electronic",
        "supply"
    ],
    "wof:name":"White Radio Ltd",
    "wof:placetype":"venue"
},
  "geometry": {"coordinates":[-79.75820899999999,43.388935],"type":"Point"}
}