{
  "type": "Feature",
  "properties": {
    "addr:full":"2428 Bloor St W Toronto ON M6S 1P9",
    "addr:housenumber":"2428",
    "addr:postcode":"m6s 1p9",
    "addr:street":"Bloor St W",
    "iso:country":"CA",
    "sg:address":"2428 Bloor St W",
    "sg:city":"Toronto",
    "sg:classifiers":[
        {
            "category":"Food & Beverages",
            "subcategory":"Groceries & Convenience Stores",
            "type":"Retail Goods"
        }
    ],
    "sg:phone":"+1 416 767 5032",
    "sg:postcode":"M6S 1P9",
    "sg:province":"ON",
    "wof:name":"Mini Mart Convenience",
    "wof:placetype":"venue"
},
  "geometry": {"coordinates":[-79.48397827150001,43.6495742798],"type":"Point"}
}