{
  "type": "Feature",
  "properties": {
    "iso:country":"CA",
    "sg:address":"28 William St S",
    "sg:city":"Chatham",
    "sg:classifiers":[
        {
            "category":"Restaurant",
            "type":"Food & Drink"
        }
    ],
    "sg:phone":"+1 519 360 1932",
    "sg:postcode":"N7M 4S1",
    "sg:province":"ON",
    "wof:name":"William Street Cafe",
    "wof:placetype":"venue"
},
  "geometry": {"coordinates":[-82.1813049316,42.4043617249],"type":"Point"}
}