{
  "type": "Feature",
  "properties": {
    "addr:full":"2111 1E Av Quebec QC G1L 3M6",
    "addr:housenumber":"2111",
    "addr:postcode":"g1l 3m6",
    "addr:street":"1E Av",
    "iso:country":"CA",
    "sg:address":"2111 1E Av",
    "sg:city":"Quebec",
    "sg:classifiers":[
        {
            "category":"Restaurant",
            "type":"Food & Drink"
        }
    ],
    "sg:phone":"+1 418 529 1558",
    "sg:postcode":"G1L 3M6",
    "sg:province":"QC",
    "wof:name":"Taxi Station",
    "wof:placetype":"venue"
},
  "geometry": {"coordinates":[-71.2397766113,46.831905365],"type":"Point"}
}