{
  "type": "Feature",
  "properties": {
    "addr:full":"13408 Stony Plain Rd NW Edmonton AB T5N 3P5",
    "addr:housenumber":"13408",
    "addr:postcode":"t5n 3p5",
    "addr:street":"Stony Plain Rd Nw",
    "iso:country":"CA",
    "sg:address":"13408 Stony Plain Rd NW",
    "sg:city":"Edmonton",
    "sg:classifiers":[
        {
            "category":"Restaurant",
            "type":"Food & Drink"
        }
    ],
    "sg:phone":"+1 780 454 4300",
    "sg:postcode":"T5N 3P5",
    "sg:province":"AB",
    "wof:name":"Vi's For Pies",
    "wof:placetype":"venue"
},
  "geometry": {"coordinates":[-113.553367615,53.5456733704],"type":"Point"}
}