{
  "type": "Feature",
  "properties": {
    "addr:full":"Newmarket ON L3Y 6Z2",
    "addr:postcode":"l3y 6z2",
    "iso:country":"CA",
    "sg:city":"Newmarket",
    "sg:classifiers":[
        {
            "category":"Autos & Motor Vehicles",
            "subcategory":"Auto Supplies",
            "type":"Retail Goods"
        }
    ],
    "sg:phone":"+1 905 954 0717",
    "sg:postcode":"L3Y 6Z2",
    "sg:province":"ON",
    "sg:tags":[
        "automobile",
        "parts"
    ],
    "wof:name":"Carquest Auto Parts",
    "wof:placetype":"venue"
},
  "geometry": {"coordinates":[-79.45470400000001,44.039837],"type":"Point"}
}