{
  "type": "Feature",
  "properties": {
    "addr:full":"2480 Hastings St E Vancouver BC V5K 1Z1",
    "addr:housenumber":"2480",
    "addr:postcode":"v5k 1z1",
    "addr:street":"Hastings St E",
    "iso:country":"CA",
    "sg:address":"2480 Hastings St E",
    "sg:city":"Vancouver",
    "sg:classifiers":[
        {
            "category":"Shopping",
            "subcategory":"Stationery & Office Supplies",
            "type":"Retail Goods"
        }
    ],
    "sg:phone":"+1 604 254 0449",
    "sg:postcode":"V5K 1Z1",
    "sg:province":"BC",
    "sg:tags":[
        "post"
    ],
    "wof:name":"Tomson's Copy & Stationery Ltd",
    "wof:placetype":"venue"
},
  "geometry": {"coordinates":[-123.055031,49.280983],"type":"Point"}
}