{
  "type": "Feature",
  "properties": {
    "iso:country":"CA",
    "sg:city":"Peterborough",
    "sg:classifiers":[
        {
            "category":"Health Services",
            "subcategory":"Hospital",
            "type":"Services"
        }
    ],
    "sg:phone":"+1 705 742 3803",
    "sg:postcode":"K9H 7L7",
    "sg:province":"ON",
    "sg:tags":[
        "mental"
    ],
    "wof:name":"Kinark Child & Family Svc",
    "wof:placetype":"venue"
},
  "geometry": {"coordinates":[-78.30503845210001,44.306854248],"type":"Point"}
}