{
  "type": "Feature",
  "properties": {
    "iso:country":"CA",
    "sg:address":"1947 Main St",
    "sg:city":"Moncton",
    "sg:classifiers":[
        {
            "category":"Autos & Motor Vehicles",
            "subcategory":"Automobile Sales",
            "type":"Retail Goods"
        }
    ],
    "sg:phone":"+1 506 384 2886",
    "sg:postcode":"E1E 1H9",
    "sg:province":"NB",
    "sg:tags":[
        "car",
        "dealer"
    ],
    "wof:name":"Car Store",
    "wof:placetype":"venue"
},
  "geometry": {"coordinates":[-64.8052520752,46.0754890442],"type":"Point"}
}