{
  "type": "Feature",
  "properties": {
    "addr:full":"108 Broadway E Vancouver BC V5T 1V9",
    "addr:housenumber":"108",
    "addr:postcode":"v5t 1v9",
    "addr:street":"Broadway E",
    "iso:country":"CA",
    "sg:address":"108 Broadway E",
    "sg:city":"Vancouver",
    "sg:classifiers":[
        {
            "category":"Manufacturing",
            "subcategory":"Furniture",
            "type":"Manufacturing & Wholesale Goods"
        }
    ],
    "sg:phone":"+1 604 872 7009",
    "sg:postcode":"V5T 1V9",
    "sg:province":"BC",
    "sg:tags":[
        "mattress"
    ],
    "wof:name":"Parker's Mattress Factory",
    "wof:placetype":"venue"
},
  "geometry": {"coordinates":[-123.102630615,49.2628250122],"type":"Point"}
}