{
  "type": "Feature",
  "properties": {
    "addr:full":"1000 Edward St Prescott ON K0E 1T0",
    "addr:housenumber":"1000",
    "addr:postcode":"k0e 1t0",
    "addr:street":"Edward St",
    "iso:country":"CA",
    "sg:address":"1000 Edward St",
    "sg:city":"Prescott",
    "sg:classifiers":[
        {
            "category":"Education",
            "subcategory":"School",
            "type":"Public Place"
        }
    ],
    "sg:phone":"+1 613 925 2855",
    "sg:postcode":"K0E 1T0",
    "sg:province":"ON",
    "wof:name":"South Grenville Dist High Schl",
    "wof:placetype":"venue"
},
  "geometry": {"coordinates":[-75.5211486816,44.7183265686],"type":"Point"}
}