{
  "type": "Feature",
  "properties": {
    "addr:full":"99 River St W Prince Albert SK S6V 2Y9",
    "addr:housenumber":"99",
    "addr:postcode":"s6v 2y9",
    "addr:street":"River St",
    "iso:country":"CA",
    "sg:address":"99 River St W",
    "sg:city":"Prince Albert",
    "sg:classifiers":[
        {
            "category":"Food & Beverages",
            "subcategory":"Liquor & Beverages",
            "type":"Retail Goods"
        }
    ],
    "sg:phone":"+1 306 764 5240",
    "sg:postcode":"S6V 2Y9",
    "sg:province":"SK",
    "sg:tags":[
        "beer",
        "ale"
    ],
    "wof:name":"Georgie's Beer & Wine Store",
    "wof:placetype":"venue"
},
  "geometry": {"coordinates":[-105.75679,53.204372],"type":"Point"}
}