{
  "type": "Feature",
  "properties": {
    "addr:full":"PO Box 130 Sandy Cove NL A0K 5C0",
    "addr:housenumber":"po",
    "addr:postcode":"a0k 5c0",
    "addr:street":"Box 130",
    "iso:country":"CA",
    "sg:address":"PO Box 130",
    "sg:city":"Sandy Cove",
    "sg:classifiers":[
        {
            "category":"Wholesale",
            "subcategory":"Groceries",
            "type":"Manufacturing & Wholesale Goods"
        }
    ],
    "sg:phone":"+1 709 456 2211",
    "sg:postcode":"A0K 5C0",
    "sg:province":"NL",
    "sg:tags":[
        "grocer"
    ],
    "wof:name":"Strait's Wholesale",
    "wof:placetype":"venue"
},
  "geometry": {"coordinates":[-53.736256,48.640583],"type":"Point"}
}