{
  "type": "Feature",
  "properties": {
    "addr:full":"Toronto ON M4E 1E2",
    "addr:postcode":"m4e 1e2",
    "iso:country":"CA",
    "sg:city":"Toronto",
    "sg:classifiers":[
        {
            "category":"Manufacturing",
            "subcategory":"Printing",
            "type":"Manufacturing & Wholesale Goods"
        }
    ],
    "sg:phone":"+1 416 694 3348",
    "sg:postcode":"M4E 1E2",
    "sg:province":"ON",
    "sg:tags":[
        "publisher"
    ],
    "wof:name":"Ecw Press",
    "wof:placetype":"venue"
},
  "geometry": {"coordinates":[-79.294685,43.671299],"type":"Point"}
}