{
  "type": "Feature",
  "properties": {
    "addr:full":"739 Main St Hampton NB E5N 6E2",
    "addr:housenumber":"739",
    "addr:postcode":"e5n 6e2",
    "addr:street":"Main St",
    "iso:country":"CA",
    "sg:address":"739 Main St",
    "sg:city":"Hampton",
    "sg:classifiers":[
        {
            "category":"Home & Garden",
            "subcategory":"Household Appliances",
            "type":"Retail Goods"
        }
    ],
    "sg:phone":"+1 506 832 5571",
    "sg:postcode":"E5N 6E2",
    "sg:province":"NB",
    "wof:name":"Floyd's Store Ltd",
    "wof:placetype":"venue"
},
  "geometry": {"coordinates":[-65.831604,45.529816],"type":"Point"}
}