{
  "type": "Feature",
  "properties": {
    "addr:full":"Stanstead QC J0B 3E0",
    "addr:postcode":"j0b 3e0",
    "iso:country":"CA",
    "sg:city":"Stanstead",
    "sg:classifiers":[
        {
            "category":"Retail",
            "subcategory":"Auto Repair",
            "type":"Services"
        }
    ],
    "sg:phone":"+1 819 876 1594",
    "sg:postcode":"J0B 3E0",
    "sg:province":"QC",
    "sg:tags":[
        "equipment",
        "parts",
        "truck"
    ],
    "wof:name":"90169335 Quebec Inc",
    "wof:placetype":"venue"
},
  "geometry": {"coordinates":[-72.105667,45.020287],"type":"Point"}
}