{
  "type": "Feature",
  "properties": {
    "addr:full":"306 Erb St W Waterloo ON N2L 1W3",
    "addr:housenumber":"306",
    "addr:postcode":"n2l 1w3",
    "addr:street":"Erb St W",
    "iso:country":"CA",
    "sg:address":"306 Erb St W",
    "sg:city":"Waterloo",
    "sg:classifiers":[
        {
            "category":"Organizations",
            "subcategory":"Religious Organization",
            "type":"Services"
        }
    ],
    "sg:phone":"+1 519 886 6530",
    "sg:postcode":"N2L 1W3",
    "sg:province":"ON",
    "sg:tags":[
        "church"
    ],
    "wof:name":"First Baptist Church",
    "wof:placetype":"venue"
},
  "geometry": {"coordinates":[-80.54271697999999,43.4564094543],"type":"Point"}
}