{
  "type": "Feature",
  "properties": {
    "addr:full":"3835 24E Rue Laval QC H7R 2L8",
    "addr:housenumber":"3835",
    "addr:postcode":"h7r 2l8",
    "addr:street":"24E Rue",
    "iso:country":"CA",
    "sg:address":"3835 24E Rue",
    "sg:city":"Laval",
    "sg:classifiers":[
        {
            "category":"Personal",
            "subcategory":"Shoe Repair & Shine",
            "type":"Services"
        }
    ],
    "sg:phone":"+1 450 627 4441",
    "sg:postcode":"H7R 2L8",
    "sg:province":"QC",
    "sg:tags":[
        "repairing",
        "boot"
    ],
    "wof:name":"Cordonnerie Bolduc",
    "wof:placetype":"venue"
},
  "geometry": {"coordinates":[-73.871979,45.550961],"type":"Point"}
}