{
  "type": "Feature",
  "properties": {
    "iso:country":"CA",
    "sg:address":"6405 Windsor St",
    "sg:city":"Vancouver",
    "sg:classifiers":[
        {
            "category":"Building & Trades",
            "subcategory":"Plumbing",
            "type":"Services"
        }
    ],
    "sg:phone":"+1 604 327 8798",
    "sg:postcode":"V5W 3J4",
    "sg:province":"BC",
    "sg:tags":[
        "heating",
        "contractor"
    ],
    "wof:name":"Helma Home Heating Ltd",
    "wof:placetype":"venue"
},
  "geometry": {"coordinates":[-123.08541870099999,49.2263755798],"type":"Point"}
}