{
  "type": "Feature",
  "properties": {
    "addr:full":"515 William St Cambridge ON N3H 3W6",
    "addr:housenumber":"515",
    "addr:postcode":"n3h 3w6",
    "addr:street":"William St",
    "iso:country":"CA",
    "sg:address":"515 William St",
    "sg:city":"Cambridge",
    "sg:classifiers":[
        {
            "category":"Recreation",
            "type":"Entertainment"
        }
    ],
    "sg:phone":"+1 519 653 7646",
    "sg:postcode":"N3H 3W6",
    "sg:province":"ON",
    "sg:tags":[
        "pool",
        "swimming"
    ],
    "wof:name":"Ed Newland Swimming Pool",
    "wof:placetype":"venue"
},
  "geometry": {"coordinates":[-80.35881000000001,43.398842],"type":"Point"}
}