{
  "type": "Feature",
  "properties": {
    "addr:full":"970 Boul Martel Saint-Honore-DE-Chicoutimi QC G0V 1L0",
    "addr:housenumber":"970",
    "addr:postcode":"g0v 1l0",
    "addr:street":"Boul Martel Saint-Honore-De-Chicoutimi",
    "iso:country":"CA",
    "sg:address":"970 Boul Martel",
    "sg:city":"Saint-Honore-DE-Chicoutimi",
    "sg:classifiers":[
        {
            "category":"Freight",
            "type":"Transportation"
        }
    ],
    "sg:phone":"+1 418 673 4472",
    "sg:postcode":"G0V 1L0",
    "sg:province":"QC",
    "sg:tags":[
        "excavating",
        "contractor",
        "trucking"
    ],
    "wof:name":"L M Villeneuve Excavation Inc",
    "wof:placetype":"venue"
},
  "geometry": {"coordinates":[-71.06139400000001,48.428944],"type":"Point"}
}