{
  "type": "Feature",
  "properties": {
    "addr:full":"1011 Av DE Bourlamaque Quebec QC G1R 2P3",
    "addr:housenumber":"1011",
    "addr:postcode":"g1r 2p3",
    "addr:street":"Av De Bourlamaque",
    "iso:country":"CA",
    "sg:address":"1011 Av DE Bourlamaque",
    "sg:city":"Quebec",
    "sg:classifiers":[
        {
            "category":"Food & Beverages",
            "subcategory":"Groceries & Convenience Stores",
            "type":"Retail Goods"
        }
    ],
    "sg:phone":"+1 418 529 1255",
    "sg:postcode":"G1R 2P3",
    "sg:province":"QC",
    "wof:name":"Depan-Escompte Couche-Tard",
    "wof:placetype":"venue"
},
  "geometry": {"coordinates":[-71.22801200000001,46.803181],"type":"Point"}
}