{
  "type": "Feature",
  "properties": {
    "iso:country":"CA",
    "sg:address":"1011 Av DE Bourlamaque",
    "sg:city":"Quebec",
    "sg:classifiers":[
        {
            "category":"Food & Beverages",
            "subcategory":"Groceries & Convenience Stores",
            "type":"Retail Goods"
        }
    ],
    "sg:phone":"+1 418 529 1255",
    "sg:postcode":"G1R 2P3",
    "sg:province":"QC",
    "wof:name":"Depan-Escompte Couche-Tard",
    "wof:placetype":"venue"
},
  "geometry": {"coordinates":[-71.228012,46.803181],"type":"Point"}
}