{
  "type": "Feature",
  "properties": {
    "iso:country":"CA",
    "sg:address":"124 Rue Principale",
    "sg:city":"Saint-Andre-Du-Lac-Saint-Jean",
    "sg:classifiers":[
        {
            "category":"Food & Beverages",
            "subcategory":"Groceries & Convenience Stores",
            "type":"Retail Goods"
        }
    ],
    "sg:phone":"+1 418 349 8065",
    "sg:postcode":"G0W 2K0",
    "sg:province":"QC",
    "wof:name":"Accommodation St-Andre Petro-T",
    "wof:placetype":"venue"
},
  "geometry": {"coordinates":[-70.889702,46.92123],"type":"Point"}
}