{
  "type": "Feature",
  "properties": {
    "addr:full":"6985 1E Av Charlesbourg QC G1H 2X1",
    "addr:housenumber":"6985",
    "addr:postcode":"g1h 2x1",
    "addr:street":"1E Av",
    "iso:country":"CA",
    "sg:address":"6985 1E Av",
    "sg:city":"Charlesbourg",
    "sg:classifiers":[
        {
            "category":"Health Services",
            "subcategory":"Health Practitioner",
            "type":"Services"
        }
    ],
    "sg:phone":"+1 418 802 5129",
    "sg:postcode":"G1H 2X1",
    "sg:province":"QC",
    "sg:tags":[
        "psychologist"
    ],
    "wof:name":"St-Pierre, Lyne",
    "wof:placetype":"venue"
},
  "geometry": {"coordinates":[-71.26340500000001,46.85611],"type":"Point"}
}