{
  "type": "Feature",
  "properties": {
    "addr:full":"Vancouver BC V6P 3S8",
    "addr:postcode":"v6p 3s8",
    "iso:country":"CA",
    "sg:city":"Vancouver",
    "sg:classifiers":[
        {
            "category":"Shopping",
            "subcategory":"Musical Instruments",
            "type":"Retail Goods"
        }
    ],
    "sg:phone":"+1 604 325 0582",
    "sg:postcode":"V6P 3S8",
    "sg:province":"BC",
    "sg:tags":[
        "violin"
    ],
    "wof:name":"Fan's String World",
    "wof:placetype":"venue"
},
  "geometry": {"coordinates":[-123.123519898,49.2065315247],"type":"Point"}
}