{
  "type": "Feature",
  "properties": {
    "addr:full":"10704 113 St #103 Fairview AB T0H 1L0",
    "addr:housenumber":"10704",
    "addr:postcode":"t0h 1l0",
    "addr:street":"113 St # 103",
    "iso:country":"CA",
    "sg:address":"10704 113 St #103",
    "sg:city":"Fairview",
    "sg:classifiers":[
        {
            "category":"Travel",
            "subcategory":"Hotels & Motels",
            "type":"Entertainment"
        }
    ],
    "sg:phone":"+1 780 835 2466",
    "sg:postcode":"T0H 1L0",
    "sg:province":"AB",
    "wof:name":"Hillview Inn",
    "wof:placetype":"venue"
},
  "geometry": {"coordinates":[-118.392242,56.071686],"type":"Point"}
}