{
  "type": "Feature",
  "properties": {
    "addr:full":"Scarborough ON M1E 4V2",
    "addr:postcode":"m1e 4v2",
    "iso:country":"CA",
    "sg:city":"Scarborough",
    "sg:classifiers":[
        {
            "category":"Health Services",
            "subcategory":"Doctor",
            "type":"Services"
        }
    ],
    "sg:phone":"+1 416 269 5088",
    "sg:postcode":"M1E 4V2",
    "sg:province":"ON",
    "sg:tags":[
        "physician",
        "surgeon"
    ],
    "wof:name":"Livingston Medical Ctr",
    "wof:placetype":"venue"
},
  "geometry": {"coordinates":[-79.19982899999999,43.747231],"type":"Point"}
}