{
  "type": "Feature",
  "properties": {
    "addr:full":"12125 149 St NW Edmonton AB T5L 2J2",
    "addr:housenumber":"12125",
    "addr:postcode":"t5l 2j2",
    "addr:street":"149 St Nw",
    "iso:country":"CA",
    "sg:address":"12125 149 St NW",
    "sg:city":"Edmonton",
    "sg:classifiers":[
        {
            "category":"Home & Garden",
            "subcategory":"Building Materials",
            "type":"Retail Goods"
        }
    ],
    "sg:phone":"+1 780 452 8201",
    "sg:postcode":"T5L 2J2",
    "sg:province":"AB",
    "sg:tags":[
        "paint"
    ],
    "wof:name":"Walls Alive",
    "wof:placetype":"venue"
},
  "geometry": {"coordinates":[-113.577782,53.573318],"type":"Point"}
}