{
  "type": "Feature",
  "properties": {
    "addr:full":"6555 Rue DE Normanville Montreal QC H2S 2B8",
    "addr:housenumber":"6555",
    "addr:postcode":"h2s 2b8",
    "addr:street":"Rue De Normanville",
    "iso:country":"CA",
    "sg:address":"6555 Rue DE Normanville",
    "sg:city":"Montreal",
    "sg:classifiers":[
        {
            "category":"Education",
            "subcategory":"School",
            "type":"Public Place"
        }
    ],
    "sg:phone":"+1 514 596 4940",
    "sg:postcode":"H2S 2B8",
    "sg:province":"QC",
    "wof:name":"Ecole St-Ambroise",
    "wof:placetype":"venue"
},
  "geometry": {"coordinates":[-73.6011886597,45.5398788452],"type":"Point"}
}