{
  "type": "Feature",
  "properties": {
    "addr:full":"440 England Ave Courtenay BC V9N 2N1",
    "addr:housenumber":"440",
    "addr:postcode":"v9n 2n1",
    "addr:street":"England Ave",
    "iso:country":"CA",
    "sg:address":"440 England Ave",
    "sg:city":"Courtenay",
    "sg:classifiers":[
        {
            "category":"Retail",
            "subcategory":"Funeral Services",
            "type":"Services"
        }
    ],
    "sg:phone":"+1 250 334 4464",
    "sg:postcode":"V9N 2N1",
    "sg:province":"BC",
    "sg:tags":[
        "director"
    ],
    "wof:name":"Piercy's Funeral Home Ltd",
    "wof:placetype":"venue"
},
  "geometry": {"coordinates":[-125.00050400000001,49.691124],"type":"Point"}
}