{
  "type": "Feature",
  "properties": {
    "addr:full":"Calgary AB T2R 0G5",
    "addr:postcode":"t2r 0g5",
    "iso:country":"CA",
    "sg:city":"Calgary",
    "sg:classifiers":[
        {
            "category":"Sports & Exercise",
            "subcategory":"Gym",
            "type":"Entertainment"
        }
    ],
    "sg:phone":"+1 403 244 7405",
    "sg:postcode":"T2R 0G5",
    "sg:province":"AB",
    "sg:tags":[
        "club",
        "health",
        "studio",
        "gymnasium"
    ],
    "wof:name":"Innovative Fitness",
    "wof:placetype":"venue"
},
  "geometry": {"coordinates":[-114.086845,51.0429],"type":"Point"}
}