{
  "type": "Feature",
  "properties": {
    "addr:full":"471 High St W Moose Jaw SK S6H 1T2",
    "addr:housenumber":"471",
    "addr:postcode":"s6h 1t2",
    "addr:street":"High St W",
    "iso:country":"CA",
    "sg:address":"471 High St W",
    "sg:city":"Moose Jaw",
    "sg:classifiers":[
        {
            "category":"Home & Garden",
            "subcategory":"Building Materials",
            "type":"Retail Goods"
        }
    ],
    "sg:phone":"+1 306 693 4811",
    "sg:postcode":"S6H 1T2",
    "sg:province":"SK",
    "sg:tags":[
        "glass",
        "window",
        "plate"
    ],
    "wof:name":"Crystal Glass Canada Ltd",
    "wof:placetype":"venue"
},
  "geometry": {"coordinates":[-105.546257,50.391338],"type":"Point"}
}