{
  "type": "Feature",
  "properties": {
    "addr:full":"17620 100 Ave NW Edmonton AB T5S 1S9",
    "addr:housenumber":"17620",
    "addr:postcode":"t5s 1s9",
    "addr:street":"100 Ave Nw",
    "iso:country":"CA",
    "sg:address":"17620 100 Ave NW",
    "sg:city":"Edmonton",
    "sg:classifiers":[
        {
            "category":"Restaurant",
            "type":"Food & Drink"
        }
    ],
    "sg:phone":"+1 780 489 2699",
    "sg:postcode":"T5S 1S9",
    "sg:province":"AB",
    "wof:name":"Albert's Family Restaurant",
    "wof:placetype":"venue"
},
  "geometry": {"coordinates":[-113.623664856,53.5384521484],"type":"Point"}
}