{
  "type": "Feature",
  "properties": {
    "addr:full":"547 Rue Principale Lachute QC J8H 1Y6",
    "addr:housenumber":"547",
    "addr:postcode":"j8h 1y6",
    "addr:street":"Rue Principale",
    "iso:country":"CA",
    "sg:address":"547 Rue Principale",
    "sg:city":"Lachute",
    "sg:classifiers":[
        {
            "category":"Health Services",
            "subcategory":"Optometrist",
            "type":"Services"
        }
    ],
    "sg:phone":"+1 450 562 5281",
    "sg:postcode":"J8H 1Y6",
    "sg:province":"QC",
    "wof:name":"Clinique Optometrie Iris",
    "wof:placetype":"venue"
},
  "geometry": {"coordinates":[-74.333527,45.657314],"type":"Point"}
}