{
  "type": "Feature",
  "properties": {
    "addr:full":"2038 Sheppard Ave E North York ON M2J 5B3",
    "addr:housenumber":"2038",
    "addr:postcode":"m2j 5b3",
    "addr:street":"Sheppard Ave E",
    "iso:country":"CA",
    "sg:address":"2038 Sheppard Ave E",
    "sg:city":"North York",
    "sg:classifiers":[
        {
            "category":"Restaurant",
            "type":"Food & Drink"
        }
    ],
    "sg:phone":"+1 416 495 1208",
    "sg:postcode":"M2J 5B3",
    "sg:province":"ON",
    "wof:name":"Sashimi House",
    "wof:placetype":"venue"
},
  "geometry": {"coordinates":[-79.330383,43.775139],"type":"Point"}
}