{
  "type": "Feature",
  "properties": {
    "addr:full":"9913 99th St Sexsmith AB T0H 3C0",
    "addr:housenumber":"9913",
    "addr:postcode":"t0h 3c0",
    "addr:street":"99Th St",
    "iso:country":"CA",
    "sg:address":"9913 99th St",
    "sg:city":"Sexsmith",
    "sg:classifiers":[
        {
            "category":"Recreation",
            "type":"Entertainment"
        }
    ],
    "sg:phone":"+1 780 568 3633",
    "sg:postcode":"T0H 3C0",
    "sg:province":"AB",
    "sg:tags":[
        "club",
        "curling"
    ],
    "wof:name":"Sexsmith Curling Club",
    "wof:placetype":"venue"
},
  "geometry": {"coordinates":[-118.781723,55.348667],"type":"Point"}
}