{
  "type": "Feature",
  "properties": {
    "addr:full":"30 Greenfield Ave North York ON M2N 6N3",
    "addr:housenumber":"30",
    "addr:postcode":"m2n 6n3",
    "addr:street":"Greenfield Ave",
    "iso:country":"CA",
    "sg:address":"30 Greenfield Ave",
    "sg:city":"North York",
    "sg:classifiers":[
        {
            "category":"Real Estate",
            "subcategory":"Real Estate Agent",
            "type":"Services"
        }
    ],
    "sg:phone":"+1 416 229 4040",
    "sg:postcode":"M2N 6N3",
    "sg:province":"ON",
    "sg:tags":[
        "management"
    ],
    "wof:name":"Mtcc 877",
    "wof:placetype":"venue"
},
  "geometry": {"coordinates":[-79.410522,43.763649],"type":"Point"}
}