{
  "type": "Feature",
  "properties": {
    "addr:full":"2615 Place Chasse Montreal QC H1Y 2C3",
    "addr:housenumber":"2615",
    "addr:postcode":"h1y 2c3",
    "addr:street":"Place Chasse",
    "iso:country":"CA",
    "sg:address":"2615 Place Chasse",
    "sg:city":"Montreal",
    "sg:classifiers":[
        {
            "category":"Manufacturing",
            "subcategory":"Food",
            "type":"Manufacturing & Wholesale Goods"
        }
    ],
    "sg:phone":"+1 514 522 3187",
    "sg:postcode":"H1Y 2C3",
    "sg:province":"QC",
    "sg:tags":[
        "natural",
        "vitamin"
    ],
    "wof:name":"Laboratoire Lalco Inc",
    "wof:placetype":"venue"
},
  "geometry": {"coordinates":[-73.5706253052,45.5433120728],"type":"Point"}
}