{
  "type": "Feature",
  "properties": {
    "addr:full":"175 Elm St Toronto ON M5T 2Z8",
    "addr:housenumber":"175",
    "addr:postcode":"m5t 2z8",
    "addr:street":"Elm St",
    "iso:country":"CA",
    "sg:address":"175 Elm St",
    "sg:city":"Toronto",
    "sg:classifiers":[
        {
            "category":"Real Estate",
            "subcategory":"Real Estate Agent",
            "type":"Services"
        }
    ],
    "sg:phone":"+1 416 598 3884",
    "sg:postcode":"M5T 2Z8",
    "sg:province":"ON",
    "sg:tags":[
        "cooperative"
    ],
    "wof:name":"Charles Hastings Housing",
    "wof:placetype":"venue"
},
  "geometry": {"coordinates":[-79.39054899999999,43.656033],"type":"Point"}
}