{
  "type": "Feature",
  "properties": {
    "addr:full":"51 Grand River St N Paris ON N3L 2M3",
    "addr:housenumber":"51",
    "addr:postcode":"n3l 2m3",
    "addr:street":"Grand;St N",
    "iso:country":"CA",
    "sg:address":"51 Grand River St N",
    "sg:city":"Paris",
    "sg:classifiers":[
        {
            "category":"Wholesale",
            "subcategory":"Machinery & Supplies",
            "type":"Manufacturing & Wholesale Goods"
        }
    ],
    "sg:phone":"+1 519 442 6562",
    "sg:postcode":"N3L 2M3",
    "sg:province":"ON",
    "sg:tags":[
        "baker"
    ],
    "wof:name":"General Store",
    "wof:placetype":"venue"
},
  "geometry": {"coordinates":[-80.38371276860001,43.193195343],"type":"Point"}
}