{
  "type": "Feature",
  "properties": {
    "addr:full":"375 Smythe St Fredericton NB E3B 3E3",
    "addr:housenumber":"375",
    "addr:postcode":"e3b 3e3",
    "addr:street":"Smythe St",
    "iso:country":"CA",
    "sg:address":"375 Smythe St",
    "sg:city":"Fredericton",
    "sg:classifiers":[
        {
            "category":"Restaurant",
            "type":"Food & Drink"
        }
    ],
    "sg:phone":"+1 506 462 9952",
    "sg:postcode":"E3B 3E3",
    "sg:province":"NB",
    "wof:name":"Tim Hortons",
    "wof:placetype":"venue"
},
  "geometry": {"coordinates":[-66.6547546387,45.9606399536],"type":"Point"}
}