{
  "type": "Feature",
  "properties": {
    "iso:country":"CA",
    "sg:address":"36207 Beyer Rd",
    "sg:city":"Mission",
    "sg:classifiers":[
        {
            "category":"Building & Trades",
            "subcategory":"Construction",
            "type":"Services"
        }
    ],
    "sg:phone":"+1 604 826 3079",
    "sg:postcode":"V2V 7G7",
    "sg:province":"BC",
    "sg:tags":[
        "excavating",
        "contractor"
    ],
    "wof:name":"Anderson Excavating",
    "wof:placetype":"venue"
},
  "geometry": {"coordinates":[-122.282806397,49.1599960327],"type":"Point"}
}