{
  "type": "Feature",
  "properties": {
    "addr:full":"1710 Avenue Rd North York ON M5M 3Y6",
    "addr:housenumber":"1710",
    "addr:postcode":"m5m 3y6",
    "addr:street":"Avenue Rd",
    "iso:country":"CA",
    "sg:address":"1710 Avenue Rd",
    "sg:city":"North York",
    "sg:classifiers":[
        {
            "category":"Shopping",
            "type":"Retail Goods"
        }
    ],
    "sg:phone":"+1 416 789 0419",
    "sg:postcode":"M5M 3Y6",
    "sg:province":"ON",
    "sg:tags":[
        "art",
        "gallery",
        "dealer"
    ],
    "wof:name":"Art Avenue",
    "wof:placetype":"venue"
},
  "geometry": {"coordinates":[-79.41812896730001,43.7280387878],"type":"Point"}
}