{
  "type": "Feature",
  "properties": {
    "addr:full":"847 Central St Centreville NB E7K 2E8",
    "addr:housenumber":"847",
    "addr:postcode":"e7k 2e8",
    "addr:street":"Central St",
    "iso:country":"CA",
    "sg:address":"847 Central St",
    "sg:city":"Centreville",
    "sg:classifiers":[
        {
            "category":"Building & Trades",
            "subcategory":"Plumbing",
            "type":"Services"
        }
    ],
    "sg:phone":"+1 506 276 4551",
    "sg:postcode":"E7K 2E8",
    "sg:province":"NB",
    "sg:tags":[
        "sheet",
        "work",
        "metal",
        "contractor"
    ],
    "wof:name":"Metalfab Limited",
    "wof:placetype":"venue"
},
  "geometry": {"coordinates":[-67.711243,46.430885],"type":"Point"}
}