{
  "type": "Feature",
  "properties": {
    "addr:full":"155 12E Rue Ferme-Neuve QC J0W 1C0",
    "addr:housenumber":"155",
    "addr:postcode":"j0w 1c0",
    "addr:street":"12E Rue",
    "iso:country":"CA",
    "sg:address":"155 12E Rue",
    "sg:city":"Ferme-Neuve",
    "sg:classifiers":[
        {
            "category":"Banks & Credit Unions",
            "subcategory":"Bank",
            "type":"Services"
        }
    ],
    "sg:phone":"+1 819 587 3123",
    "sg:postcode":"J0W 1C0",
    "sg:province":"QC",
    "wof:name":"Caisse Desjardins Ferme-Neuve",
    "wof:placetype":"venue"
},
  "geometry": {"coordinates":[-75.44910430909999,46.6989555359],"type":"Point"}
}