{
  "type": "Feature",
  "properties": {
    "addr:full":"Lantz NS B2S 1Z2",
    "addr:postcode":"b2s 1z2",
    "iso:country":"CA",
    "sg:city":"Lantz",
    "sg:classifiers":[
        {
            "category":"Shopping",
            "type":"Retail Goods"
        }
    ],
    "sg:phone":"+1 902 883 1744",
    "sg:postcode":"B2S 1Z2",
    "sg:province":"NS",
    "sg:tags":[
        "trophy",
        "medal",
        "award"
    ],
    "wof:name":"Alico Trophies",
    "wof:placetype":"venue"
},
  "geometry": {"coordinates":[-63.484577,44.985802],"type":"Point"}
}