{
  "type": "Feature",
  "properties": {
    "addr:full":"5972 2E Av Montreal QC H1Y 2Y9",
    "addr:housenumber":"5972",
    "addr:postcode":"h1y 2y9",
    "addr:street":"2E Av",
    "iso:country":"CA",
    "sg:address":"5972 2E Av",
    "sg:city":"Montreal",
    "sg:classifiers":[
        {
            "category":"Wholesale",
            "subcategory":"Home Furnishings",
            "type":"Manufacturing & Wholesale Goods"
        }
    ],
    "sg:phone":"+1 514 722 4673",
    "sg:postcode":"H1Y 2Y9",
    "sg:province":"QC",
    "sg:tags":[
        "lamp"
    ],
    "wof:name":"Lampes Sicotte Lamps Ltee",
    "wof:placetype":"venue"
},
  "geometry": {"coordinates":[-73.5851135254,45.5487174988],"type":"Point"}
}