{
  "type": "Feature",
  "properties": {
    "addr:full":"1255 5 Ave S Lethbridge AB T1J 0V6",
    "addr:housenumber":"1255",
    "addr:postcode":"t1j 0v6",
    "addr:street":"5 Ave S",
    "iso:country":"CA",
    "sg:address":"1255 5 Ave S",
    "sg:city":"Lethbridge",
    "sg:classifiers":[
        {
            "category":"Health Services",
            "subcategory":"Clinic",
            "type":"Services"
        }
    ],
    "sg:phone":"+1 403 328 6631",
    "sg:postcode":"T1J 0V6",
    "sg:province":"AB",
    "wof:name":"Edith Cavell Care Ctr",
    "wof:placetype":"venue"
},
  "geometry": {"coordinates":[-112.82635500000001,49.693516],"type":"Point"}
}