{
  "type": "Feature",
  "properties": {
    "addr:full":"Edmonton AB T5T 1Y7",
    "addr:postcode":"t5t 1y7",
    "iso:country":"CA",
    "sg:city":"Edmonton",
    "sg:classifiers":[
        {
            "category":"Shopping",
            "subcategory":"Clothing, Apparel, & Fashions",
            "type":"Retail Goods"
        }
    ],
    "sg:phone":"+1 780 483 5938",
    "sg:postcode":"T5T 1Y7",
    "sg:province":"AB",
    "sg:tags":[
        "tailor"
    ],
    "wof:name":"Bonjours",
    "wof:placetype":"venue"
},
  "geometry": {"coordinates":[-113.63759613000001,53.51720047],"type":"Point"}
}