{
  "type": "Feature",
  "properties": {
    "addr:full":"4032 Glenview Cres North Vancouver BC V7R 3G4",
    "addr:housenumber":"4032",
    "addr:postcode":"v7r 3g4",
    "addr:street":"Glenview Cres",
    "iso:country":"CA",
    "sg:address":"4032 Glenview Cres",
    "sg:city":"North Vancouver",
    "sg:classifiers":[
        {
            "category":"Professional",
            "subcategory":"Business Services",
            "type":"Services"
        }
    ],
    "sg:phone":"+1 604 988 3029",
    "sg:postcode":"V7R 3G4",
    "sg:province":"BC",
    "sg:tags":[
        "diver"
    ],
    "wof:name":"Industrial Marine Divers",
    "wof:placetype":"venue"
},
  "geometry": {"coordinates":[-123.090446,49.345699],"type":"Point"}
}