{
  "type": "Feature",
  "properties": {
    "addr:full":"23 Railway Ave S Norquay SK S0A 2V0",
    "addr:housenumber":"23",
    "addr:postcode":"s0a 2v0",
    "addr:street":"Railway Ave S Norquay",
    "iso:country":"CA",
    "sg:address":"23 Railway Ave S",
    "sg:city":"Norquay",
    "sg:classifiers":[
        {
            "category":"Travel",
            "subcategory":"Hotels & Motels",
            "type":"Entertainment"
        }
    ],
    "sg:phone":"+1 306 594 2228",
    "sg:postcode":"S0A 2V0",
    "sg:province":"SK",
    "wof:name":"Norquay Hotel",
    "wof:placetype":"venue"
},
  "geometry": {"coordinates":[-102.087616,51.881996],"type":"Point"}
}