{
  "type": "Feature",
  "properties": {
    "addr:full":"Stoney Creek ON L8E 5S7",
    "addr:postcode":"l8e 5s7",
    "iso:country":"CA",
    "sg:city":"Stoney Creek",
    "sg:classifiers":[
        {
            "category":"Manufacturing",
            "subcategory":"Tools & Machinery",
            "type":"Manufacturing & Wholesale Goods"
        }
    ],
    "sg:phone":"+1 905 643 3474",
    "sg:postcode":"L8E 5S7",
    "sg:province":"ON",
    "sg:tags":[
        "transmission",
        "power"
    ],
    "wof:name":"Hyatt Industries Ltd",
    "wof:placetype":"venue"
},
  "geometry": {"coordinates":[-79.692131,43.228352],"type":"Point"}
}