{
  "type": "Feature",
  "properties": {
    "addr:full":"733 Fairweather Rd Vernon BC V1T 8T9",
    "addr:housenumber":"733",
    "addr:postcode":"v1t 8t9",
    "addr:street":"Fairweather Rd",
    "iso:country":"CA",
    "sg:address":"733 Fairweather Rd",
    "sg:city":"Vernon",
    "sg:classifiers":[
        {
            "category":"Wholesale",
            "subcategory":"Construction Materials",
            "type":"Manufacturing & Wholesale Goods"
        }
    ],
    "sg:phone":"+1 250 545 7566",
    "sg:postcode":"V1T 8T9",
    "sg:province":"BC",
    "sg:tags":[
        "lumber"
    ],
    "wof:name":"Vernon Forest",
    "wof:placetype":"venue"
},
  "geometry": {"coordinates":[-119.261223,50.247478],"type":"Point"}
}