{
  "type": "Feature",
  "properties": {
    "addr:full":"15 Barrett Cres Ajax ON L1T 2C8",
    "addr:housenumber":"15",
    "addr:postcode":"l1t 2c8",
    "addr:street":"Barrett Cres",
    "iso:country":"CA",
    "sg:address":"15 Barrett Cres",
    "sg:city":"Ajax",
    "sg:classifiers":[
        {
            "category":"Arts & Performance",
            "subcategory":"Theater",
            "type":"Entertainment"
        }
    ],
    "sg:phone":"+1 905 428 9756",
    "sg:postcode":"L1T 2C8",
    "sg:province":"ON",
    "sg:tags":[
        "talent",
        "agency",
        "casting"
    ],
    "wof:name":"Class Act Entertainment",
    "wof:placetype":"venue"
},
  "geometry": {"coordinates":[-79.04632599999999,43.867805],"type":"Point"}
}