{
  "type": "Feature",
  "properties": {
    "iso:country":"CA",
    "sg:city":"Williamstown",
    "sg:classifiers":[
        {
            "category":"Retail",
            "subcategory":"Veterinary Services",
            "type":"Services"
        }
    ],
    "sg:phone":"+1 613 347 3930",
    "sg:postcode":"K0C 2J0",
    "sg:province":"ON",
    "sg:tags":[
        "veterinarian"
    ],
    "wof:name":"Williamstown Veterinary Svc",
    "wof:placetype":"venue"
},
  "geometry": {"coordinates":[-74.578742981,45.1465415955],"type":"Point"}
}