{
  "type": "Feature",
  "properties": {
    "iso:country":"CA",
    "sg:city":"Newmarket",
    "sg:classifiers":[
        {
            "category":"Personal",
            "subcategory":"Beauty Salon",
            "type":"Services"
        }
    ],
    "sg:phone":"+1 905 836 5290",
    "sg:postcode":"L3Y 4Z1",
    "sg:province":"ON",
    "wof:name":"Gable & Garbo",
    "wof:placetype":"venue"
},
  "geometry": {"coordinates":[-79.481071,44.057091],"type":"Point"}
}