{
  "type": "Feature",
  "properties": {
    "addr:full":"300 Lakeshore Dr North Bay ON P1A 3V2",
    "addr:housenumber":"300",
    "addr:postcode":"p1a 3v2",
    "addr:street":"Lakeshore Dr",
    "iso:country":"CA",
    "sg:address":"300 Lakeshore Dr",
    "sg:city":"North Bay",
    "sg:classifiers":[
        {
            "category":"Shopping",
            "subcategory":"Department Store",
            "type":"Retail Goods"
        }
    ],
    "sg:phone":"+1 705 474 8196",
    "sg:postcode":"P1A 3V2",
    "sg:province":"ON",
    "sg:tags":[
        "shop"
    ],
    "wof:name":"Dollarama",
    "wof:placetype":"venue"
},
  "geometry": {"coordinates":[-79.448784,46.282852],"type":"Point"}
}