{
  "type": "Feature",
  "properties": {
    "addr:full":"Nanaimo BC V9R 6B9",
    "addr:postcode":"v9r 6b9",
    "iso:country":"CA",
    "sg:city":"Nanaimo",
    "sg:classifiers":[
        {
            "category":"Shopping",
            "subcategory":"Pharmacy",
            "type":"Retail Goods"
        }
    ],
    "sg:phone":"+1 250 753 6401",
    "sg:postcode":"V9R 6B9",
    "sg:province":"BC",
    "wof:name":"Central Drugs",
    "wof:placetype":"venue"
},
  "geometry": {"coordinates":[-123.895103455,49.0946159363],"type":"Point"}
}