{
  "type": "Feature",
  "properties": {
    "addr:full":"1919 Riverside Dr #306 Ottawa ON K1H 1A2",
    "addr:housenumber":"1919",
    "addr:postcode":"k1h 1a2",
    "addr:street":"Riverside Dr # 306",
    "iso:country":"CA",
    "sg:address":"1919 Riverside Dr #306",
    "sg:city":"Ottawa",
    "sg:classifiers":[
        {
            "category":"Health Services",
            "subcategory":"Doctor",
            "type":"Services"
        }
    ],
    "sg:phone":"+1 613 731 3015",
    "sg:postcode":"K1H 1A2",
    "sg:province":"ON",
    "sg:tags":[
        "physician",
        "surgeon"
    ],
    "wof:name":"Taylor, J Robert MD",
    "wof:placetype":"venue"
},
  "geometry": {"coordinates":[-75.669838,45.397057],"type":"Point"}
}