{
  "type": "Feature",
  "properties": {
    "addr:full":"Cap-Sante QC G0A 1L0",
    "addr:postcode":"g0a 1l0",
    "iso:country":"CA",
    "sg:city":"Cap-Sante",
    "sg:classifiers":[
        {
            "category":"Retail",
            "subcategory":"Auto Repair",
            "type":"Services"
        }
    ],
    "sg:phone":"+1 418 285 2147",
    "sg:postcode":"G0A 1L0",
    "sg:province":"QC",
    "sg:tags":[
        "repairing",
        "automobile"
    ],
    "wof:name":"Mecanique Mobile Yvan Germain",
    "wof:placetype":"venue"
},
  "geometry": {"coordinates":[-71.7733917236,46.7211761475],"type":"Point"}
}