{
  "type": "Feature",
  "properties": {
    "addr:full":"253 Rue DE Fontenelle Boucherville QC J4B 7T7",
    "addr:housenumber":"253",
    "addr:postcode":"j4b 7t7",
    "addr:street":"Rue De Fontenelle",
    "iso:country":"CA",
    "sg:address":"253 Rue DE Fontenelle",
    "sg:city":"Boucherville",
    "sg:classifiers":[
        {
            "category":"Professional",
            "subcategory":"Accounting & Tax Preparation",
            "type":"Services"
        }
    ],
    "sg:phone":"+1 450 641 0130",
    "sg:postcode":"J4B 7T7",
    "sg:province":"QC",
    "sg:tags":[
        "accountant"
    ],
    "wof:name":"Shedleur, Serge",
    "wof:placetype":"venue"
},
  "geometry": {"coordinates":[-73.4320526123,45.5735626221],"type":"Point"}
}