{
  "type": "Feature",
  "properties": {
    "addr:full":"465 Addis Ave West St Paul MB R2V 4R9",
    "addr:housenumber":"465",
    "addr:postcode":"r2v 4r9",
    "addr:street":"Addis Ave",
    "iso:country":"CA",
    "sg:address":"465 Addis Ave",
    "sg:city":"West St Paul",
    "sg:classifiers":[
        {
            "category":"Shopping",
            "type":"Retail Goods"
        }
    ],
    "sg:phone":"+1 204 334 1206",
    "sg:postcode":"R2V 4R9",
    "sg:province":"MB",
    "sg:tags":[
        "orthopedic",
        "appliance"
    ],
    "wof:name":"Lifeart Prosthetics",
    "wof:placetype":"venue"
},
  "geometry": {"coordinates":[-97.08112335209999,49.9683952332],"type":"Point"}
}