{
  "type": "Feature",
  "properties": {
    "addr:full":"Nanoose Bay BC V9P 9J9",
    "addr:postcode":"v9p 9j9",
    "iso:country":"CA",
    "sg:city":"Nanoose Bay",
    "sg:classifiers":[
        {
            "category":"Cinema",
            "subcategory":"Movie Rental",
            "type":"Entertainment"
        }
    ],
    "sg:phone":"+1 250 468 5226",
    "sg:postcode":"V9P 9J9",
    "sg:province":"BC",
    "sg:tags":[
        "leasing",
        "video",
        "disc",
        "tape"
    ],
    "wof:name":"Red Gap Video",
    "wof:placetype":"venue"
},
  "geometry": {"coordinates":[-124.194496,49.272243],"type":"Point"}
}