{
  "type": "Feature",
  "properties": {
    "addr:full":"1020 Rue Saint-Denis Montreal QC H2X 3J2",
    "addr:housenumber":"1020",
    "addr:postcode":"h2x 3j2",
    "addr:street":"Rue Saint-Denis",
    "iso:country":"CA",
    "sg:address":"1020 Rue Saint-Denis",
    "sg:city":"Montreal",
    "sg:classifiers":[
        {
            "category":"Professional",
            "subcategory":"Lawyer & Legal Services",
            "type":"Services"
        }
    ],
    "sg:phone":"+1 514 842 6900",
    "sg:postcode":"H2X 3J2",
    "sg:province":"QC",
    "sg:tags":[
        "attorney"
    ],
    "wof:name":"Mac Donald, Ronnie",
    "wof:placetype":"venue"
},
  "geometry": {"coordinates":[-73.556389,45.511707],"type":"Point"}
}