{
  "type": "Feature",
  "properties": {
    "addr:full":"6041 E Porpoise Bay Rd Sechelt BC V0N 3A0",
    "addr:housenumber":"6041",
    "addr:postcode":"v0n 3a0",
    "addr:street":"E Porpoise Bay Rd",
    "iso:country":"CA",
    "sg:address":"6041 E Porpoise Bay Rd",
    "sg:city":"Sechelt",
    "sg:classifiers":[
        {
            "category":"Bus Charters",
            "type":"Transportation"
        }
    ],
    "sg:phone":"+1 604 885 2513",
    "sg:postcode":"V0N 3A0",
    "sg:province":"BC",
    "sg:tags":[
        "rental"
    ],
    "wof:name":"Sechelt School Bus Svc Ltd",
    "wof:placetype":"venue"
},
  "geometry": {"coordinates":[-123.753410339,49.4801597595],"type":"Point"}
}