{
  "type": "Feature",
  "properties": {
    "addr:full":"Merritt BC V1K 1B8",
    "addr:postcode":"v1k 1b8",
    "iso:country":"CA",
    "sg:city":"Merritt",
    "sg:classifiers":[
        {
            "category":"Retail",
            "subcategory":"Auto Repair",
            "type":"Services"
        }
    ],
    "sg:phone":"+1 250 378 2346",
    "sg:postcode":"V1K 1B8",
    "sg:province":"BC",
    "sg:tags":[
        "repairing",
        "automobile"
    ],
    "wof:name":"T & T Automotive",
    "wof:placetype":"venue"
},
  "geometry": {"coordinates":[-120.773376,50.107773],"type":"Point"}
}