{
  "type": "Feature",
  "properties": {
    "addr:full":"Rouyn-Noranda QC J9X 5A3",
    "addr:postcode":"j9x 5a3",
    "iso:country":"CA",
    "sg:city":"Rouyn-Noranda",
    "sg:classifiers":[
        {
            "category":"Freight",
            "type":"Transportation"
        }
    ],
    "sg:phone":"+1 819 762 2131",
    "sg:postcode":"J9X 5A3",
    "sg:province":"QC",
    "sg:tags":[
        "trucking"
    ],
    "wof:name":"Northwest Transport",
    "wof:placetype":"venue"
},
  "geometry": {"coordinates":[-79.0406341553,48.2971458435],"type":"Point"}
}