{
  "type": "Feature",
  "properties": {
    "addr:full":"340 Transport Rd Springfield MB R2C 2Z2",
    "addr:housenumber":"340",
    "addr:postcode":"r2c 2z2",
    "addr:street":"Transport Rd",
    "iso:country":"CA",
    "sg:address":"340 Transport Rd",
    "sg:city":"Springfield",
    "sg:classifiers":[
        {
            "category":"Building & Trades",
            "subcategory":"Plumbing",
            "type":"Services"
        }
    ],
    "sg:phone":"+1 204 222 0723",
    "sg:postcode":"R2C 2Z2",
    "sg:province":"MB",
    "sg:tags":[
        "contractor"
    ],
    "wof:name":"S S Plumbing & Heating CO Ltd",
    "wof:placetype":"venue"
},
  "geometry": {"coordinates":[-96.974953,49.916512],"type":"Point"}
}