{
  "type": "Feature",
  "properties": {
    "addr:full":"425 West St N # 6A Orillia ON L3V 7R2",
    "addr:housenumber":"425",
    "addr:postcode":"l3v 7r2",
    "addr:street":"West St N # 6A",
    "iso:country":"CA",
    "sg:address":"425 West St N # 6A",
    "sg:city":"Orillia",
    "sg:classifiers":[
        {
            "category":"Manufacturing",
            "subcategory":"Printing",
            "type":"Manufacturing & Wholesale Goods"
        }
    ],
    "sg:phone":"+1 705 327 0128",
    "sg:postcode":"L3V 7R2",
    "sg:province":"ON",
    "sg:tags":[
        "multimedia"
    ],
    "wof:name":"Electronic Lifestyles Inc",
    "wof:placetype":"venue"
},
  "geometry": {"coordinates":[-79.4319992065,44.622882843],"type":"Point"}
}