{
  "type": "Feature",
  "properties": {
    "addr:full":"612 13 St N Lethbridge AB T1H 2S8",
    "addr:housenumber":"13",
    "addr:postcode":"t1h 2s8",
    "addr:street":"612;St N",
    "iso:country":"CA",
    "sg:address":"612 13 St N",
    "sg:city":"Lethbridge",
    "sg:classifiers":[
        {
            "category":"Shopping",
            "subcategory":"Bicycles & Sporting Goods",
            "type":"Retail Goods"
        }
    ],
    "sg:phone":"+1 403 327 7777",
    "sg:postcode":"T1H 2S8",
    "sg:province":"AB",
    "wof:name":"Players Bench",
    "wof:placetype":"venue"
},
  "geometry": {"coordinates":[-112.82426452599999,49.707950592],"type":"Point"}
}