{
  "type": "Feature",
  "properties": {
    "iso:country":"CA",
    "sg:address":"2463 Hamilton Rd",
    "sg:city":"Dorchester",
    "sg:classifiers":[
        {
            "category":"Organizations",
            "subcategory":"Professional Association",
            "type":"Services"
        }
    ],
    "sg:phone":"+1 519 268 7103",
    "sg:postcode":"N0L 1G5",
    "sg:province":"ON",
    "wof:name":"Masonic Temple",
    "wof:placetype":"venue"
},
  "geometry": {"coordinates":[-81.108711,42.974445],"type":"Point"}
}