{
  "type": "Feature",
  "properties": {
    "addr:full":"2463 Hamilton Rd Dorchester ON N0L 1G5",
    "addr:housenumber":"2463",
    "addr:postcode":"n0l 1g5",
    "addr:street":"Hamilton Rd",
    "iso:country":"CA",
    "sg:address":"2463 Hamilton Rd",
    "sg:city":"Dorchester",
    "sg:classifiers":[
        {
            "category":"Organizations",
            "subcategory":"Professional Association",
            "type":"Services"
        }
    ],
    "sg:phone":"+1 519 268 7103",
    "sg:postcode":"N0L 1G5",
    "sg:province":"ON",
    "wof:name":"Masonic Temple",
    "wof:placetype":"venue"
},
  "geometry": {"coordinates":[-81.108711,42.974445],"type":"Point"}
}