{
  "type": "Feature",
  "properties": {
    "addr:full":"1050 Paramount Dr Stoney Creek ON L8J 1P8",
    "addr:housenumber":"1050",
    "addr:postcode":"l8j 1p8",
    "addr:street":"Paramount Dr",
    "iso:country":"CA",
    "sg:address":"1050 Paramount Dr",
    "sg:city":"Stoney Creek",
    "sg:classifiers":[
        {
            "category":"Shopping",
            "subcategory":"Catalog Store",
            "type":"Retail Goods"
        }
    ],
    "sg:phone":"+1 905 573 3773",
    "sg:postcode":"L8J 1P8",
    "sg:province":"ON",
    "sg:tags":[
        "mail",
        "order",
        "internet"
    ],
    "wof:name":"Sears Canada Inc",
    "wof:placetype":"venue"
},
  "geometry": {"coordinates":[-79.7942352295,43.1995658875],"type":"Point"}
}