{
  "type": "Feature",
  "properties": {
    "addr:full":"409 Main St Selkirk MB R1A 1V2",
    "addr:housenumber":"409",
    "addr:postcode":"r1a 1v2",
    "addr:street":"Main St",
    "iso:country":"CA",
    "sg:address":"409 Main St",
    "sg:city":"Selkirk",
    "sg:classifiers":[
        {
            "category":"Shopping",
            "subcategory":"Clothing, Apparel, & Fashions",
            "type":"Retail Goods"
        }
    ],
    "sg:phone":"+1 204 482 5988",
    "sg:postcode":"R1A 1V2",
    "sg:province":"MB",
    "wof:name":"Packer's Ladies Wear",
    "wof:placetype":"venue"
},
  "geometry": {"coordinates":[-96.872559,50.145191],"type":"Point"}
}