{
  "type": "Feature",
  "properties": {
    "addr:full":"15618 Niagara Parkway Rd Niagara on the Lake ON L0S 1J0",
    "addr:housenumber":"15618",
    "addr:postcode":"l0s 1j0",
    "addr:street":"Niagara Parkway Rd;On",
    "iso:country":"CA",
    "sg:address":"15618 Niagara Parkway Rd",
    "sg:city":"Niagara on the Lake",
    "sg:classifiers":[
        {
            "category":"Travel",
            "subcategory":"Hotels & Motels",
            "type":"Entertainment"
        }
    ],
    "sg:phone":"+1 905 468 0997",
    "sg:postcode":"L0S 1J0",
    "sg:province":"ON",
    "sg:tags":[
        "breakfast",
        "accommodation",
        "bed"
    ],
    "wof:name":"Grand Victorian Bed & Brkfst",
    "wof:placetype":"venue"
},
  "geometry": {"coordinates":[-79.05987500000001,43.217976],"type":"Point"}
}