{
  "type": "Feature",
  "properties": {
    "addr:full":"1412 Rue Sauve O Montreal QC H4N 1C5",
    "addr:housenumber":"1412",
    "addr:postcode":"h4n 1c5",
    "addr:street":"Rue Sauve O",
    "iso:country":"CA",
    "sg:address":"1412 Rue Sauve O",
    "sg:city":"Montreal",
    "sg:classifiers":[
        {
            "category":"Personal",
            "subcategory":"Beauty Salon",
            "type":"Services"
        }
    ],
    "sg:phone":"+1 514 334 8787",
    "sg:postcode":"H4N 1C5",
    "sg:province":"QC",
    "wof:name":"Boutique & Salon Le Carillon",
    "wof:placetype":"venue"
},
  "geometry": {"coordinates":[-73.66540500000001,45.535202],"type":"Point"}
}