{
  "type": "Feature",
  "properties": {
    "iso:country":"CA",
    "sg:address":"6393 Rue Saint-Hubert",
    "sg:city":"Montreal",
    "sg:classifiers":[
        {
            "category":"Manufacturing",
            "subcategory":"Printing",
            "type":"Manufacturing & Wholesale Goods"
        }
    ],
    "sg:phone":"+1 514 277 6508",
    "sg:postcode":"H2S 2L9",
    "sg:province":"QC",
    "sg:tags":[
        "printer"
    ],
    "wof:name":"Imprimerie Lemieux Inc",
    "wof:placetype":"venue"
},
  "geometry": {"coordinates":[-73.601707,45.535713],"type":"Point"}
}