{
  "type": "Feature",
  "properties": {
    "addr:full":"2707 58 Ave SE Calgary AB T2C 0B4",
    "addr:housenumber":"2707",
    "addr:postcode":"t2c 0b4",
    "addr:street":"58 Ave Se",
    "iso:country":"CA",
    "sg:address":"2707 58 Ave SE",
    "sg:city":"Calgary",
    "sg:classifiers":[
        {
            "category":"Manufacturing",
            "subcategory":"Tools & Machinery",
            "type":"Manufacturing & Wholesale Goods"
        }
    ],
    "sg:phone":"+1 403 236 4464",
    "sg:postcode":"T2C 0B4",
    "sg:province":"AB",
    "sg:tags":[
        "equipment",
        "system",
        "automation"
    ],
    "wof:name":"Cam Tech Industries",
    "wof:placetype":"venue"
},
  "geometry": {"coordinates":[-113.99722300000001,51.002728],"type":"Point"}
}