{
  "type": "Feature",
  "properties": {
    "addr:full":"10807 Boul Pie-Ix Montreal-Nord QC H1H 4A9",
    "addr:housenumber":"10807",
    "addr:postcode":"h1h 4a9",
    "addr:street":"Boul Pie-Ix",
    "iso:country":"CA",
    "sg:address":"10807 Boul Pie-Ix",
    "sg:city":"Montreal-Nord",
    "sg:classifiers":[
        {
            "category":"Home & Garden",
            "subcategory":"Household Appliances",
            "type":"Retail Goods"
        }
    ],
    "sg:phone":"+1 514 327 2276",
    "sg:postcode":"H1H 4A9",
    "sg:province":"QC",
    "sg:tags":[
        "machine",
        "sewing"
    ],
    "wof:name":"Centre DE Couture Mtl-N Enr",
    "wof:placetype":"venue"
},
  "geometry": {"coordinates":[-73.636680603,45.5906066895],"type":"Point"}
}