{
  "type": "Feature",
  "properties": {
    "addr:full":"8 Rue Gaetan Victoriaville QC G6P 8G6",
    "addr:housenumber":"8",
    "addr:postcode":"g6p 8g6",
    "addr:street":"Rue Gaetan",
    "iso:country":"CA",
    "sg:address":"8 Rue Gaetan",
    "sg:city":"Victoriaville",
    "sg:classifiers":[
        {
            "category":"Health Services",
            "subcategory":"Health Practitioner",
            "type":"Services"
        }
    ],
    "sg:phone":"+1 819 795 3651",
    "sg:postcode":"G6P 8G6",
    "sg:province":"QC",
    "sg:tags":[
        "acupuncture"
    ],
    "wof:name":"Robert, Christine",
    "wof:placetype":"venue"
},
  "geometry": {"coordinates":[-72.003845,46.049091],"type":"Point"}
}