{
  "type": "Feature",
  "properties": {
    "addr:full":"39 Hawkridge Ave Markham ON L3P 1V8",
    "addr:housenumber":"39",
    "addr:postcode":"l3p 1v8",
    "addr:street":"Hawkridge Ave",
    "iso:country":"CA",
    "sg:address":"39 Hawkridge Ave",
    "sg:city":"Markham",
    "sg:classifiers":[
        {
            "category":"Personal",
            "subcategory":"Beauty Salon",
            "type":"Services"
        }
    ],
    "sg:phone":"+1 905 472 2409",
    "sg:postcode":"L3P 1V8",
    "sg:province":"ON",
    "sg:tags":[
        "manicuring"
    ],
    "wof:name":"Nail Salon",
    "wof:placetype":"venue"
},
  "geometry": {"coordinates":[-79.264267,43.875389],"type":"Point"}
}