{
  "type": "Feature",
  "properties": {
    "iso:country":"CA",
    "sg:address":"39 Petworth Rd",
    "sg:city":"Brampton",
    "sg:classifiers":[
        {
            "category":"Professional",
            "subcategory":"Art Services",
            "type":"Services"
        }
    ],
    "sg:phone":"+1 905 846 5635",
    "sg:postcode":"L6Z 4C7",
    "sg:province":"ON",
    "sg:tags":[
        "graphic",
        "designer"
    ],
    "wof:name":"Tvm Graphics",
    "wof:placetype":"venue"
},
  "geometry": {"coordinates":[-79.80573272709999,43.724822998],"type":"Point"}
}