{
  "type": "Feature",
  "properties": {
    "addr:full":"Barrie ON L4N 7R8",
    "addr:postcode":"l4n 7r8",
    "iso:country":"CA",
    "sg:city":"Barrie",
    "sg:classifiers":[
        {
            "category":"Professional",
            "subcategory":"Engineering",
            "type":"Services"
        }
    ],
    "sg:phone":"+1 705 734 2973",
    "sg:postcode":"L4N 7R8",
    "sg:province":"ON",
    "sg:tags":[
        "engineer"
    ],
    "wof:name":"Highway Construction Inspctn",
    "wof:placetype":"venue"
},
  "geometry": {"coordinates":[-79.708473,44.370388],"type":"Point"}
}