{
  "type": "Feature",
  "properties": {
    "addr:full":"2082 Rte 1 Auburn NS B0P 1A0",
    "addr:housenumber":"2082",
    "addr:postcode":"b0p 1a0",
    "addr:street":"Rte 1",
    "iso:country":"CA",
    "sg:address":"2082 Rte 1",
    "sg:city":"Auburn",
    "sg:classifiers":[
        {
            "category":"Food & Beverages",
            "subcategory":"Groceries & Convenience Stores",
            "type":"Retail Goods"
        }
    ],
    "sg:phone":"+1 902 847 9878",
    "sg:postcode":"B0P 1A0",
    "sg:province":"NS",
    "sg:tags":[
        "grocer"
    ],
    "wof:name":"Burt's Grocery",
    "wof:placetype":"venue"
},
  "geometry": {"coordinates":[-64.859329,45.015984],"type":"Point"}
}