{
  "type": "Feature",
  "properties": {
    "addr:full":"3745 Gordon Dr Kelowna BC V1W 4M8",
    "addr:housenumber":"3745",
    "addr:postcode":"v1w 4m8",
    "addr:street":"Gordon Dr",
    "iso:country":"CA",
    "sg:address":"3745 Gordon Dr",
    "sg:city":"Kelowna",
    "sg:classifiers":[
        {
            "category":"Recreation",
            "type":"Entertainment"
        }
    ],
    "sg:phone":"+1 250 762 6370",
    "sg:postcode":"V1W 4M8",
    "sg:province":"BC",
    "sg:tags":[
        "riding",
        "academy"
    ],
    "wof:name":"Kelowna Riding Club",
    "wof:placetype":"venue"
},
  "geometry": {"coordinates":[-119.47846199999999,49.847755],"type":"Point"}
}