{
  "type": "Feature",
  "properties": {
    "addr:full":"RR 2 STN Main Leduc AB T9E 2X2",
    "addr:postcode":"t9e 2x2",
    "addr:street":"Rr 2 Stn Main",
    "iso:country":"CA",
    "sg:address":"RR 2 STN Main",
    "sg:city":"Leduc",
    "sg:classifiers":[
        {
            "category":"Building & Trades",
            "subcategory":"Construction",
            "type":"Services"
        }
    ],
    "sg:phone":"+1 780 986 2327",
    "sg:postcode":"T9E 2X2",
    "sg:province":"AB",
    "sg:tags":[
        "water",
        "well",
        "drilling"
    ],
    "wof:name":"Papley Drilling",
    "wof:placetype":"venue"
},
  "geometry": {"coordinates":[-113.548568726,53.2593765259],"type":"Point"}
}