{
  "type": "Feature",
  "properties": {
    "addr:full":"3495 Lawrence Ave E Scarborough ON M1H 1B3",
    "addr:housenumber":"3495",
    "addr:postcode":"m1h 1b3",
    "addr:street":"Lawrence Ave E",
    "iso:country":"CA",
    "sg:address":"3495 Lawrence Ave E",
    "sg:city":"Scarborough",
    "sg:classifiers":[
        {
            "category":"Restaurant",
            "type":"Food & Drink"
        }
    ],
    "sg:phone":"+1 416 431 5816",
    "sg:postcode":"M1H 1B3",
    "sg:province":"ON",
    "wof:name":"Burger King",
    "wof:placetype":"venue"
},
  "geometry": {"coordinates":[-79.22876739500001,43.7589378357],"type":"Point"}
}