{
  "type": "Feature",
  "properties": {
    "addr:full":"18067 92 Ave Surrey BC V4N 3Y4",
    "addr:housenumber":"18067",
    "addr:postcode":"v4n 3y4",
    "addr:street":"92 Ave",
    "iso:country":"CA",
    "sg:address":"18067 92 Ave",
    "sg:city":"Surrey",
    "sg:classifiers":[
        {
            "category":"Building & Trades",
            "subcategory":"Construction",
            "type":"Services"
        }
    ],
    "sg:phone":"+1 604 888 4488",
    "sg:postcode":"V4N 3Y4",
    "sg:province":"BC",
    "sg:tags":[
        "siding",
        "contractor"
    ],
    "wof:name":"Ajax Building Products Inc",
    "wof:placetype":"venue"
},
  "geometry": {"coordinates":[-122.722587585,49.170211792],"type":"Point"}
}