{
  "type": "Feature",
  "properties": {
    "addr:full":"113 Main St Rouleau SK S0G 4H0",
    "addr:housenumber":"113",
    "addr:postcode":"s0g 4h0",
    "addr:street":"Main St",
    "iso:country":"CA",
    "sg:address":"113 Main St",
    "sg:city":"Rouleau",
    "sg:classifiers":[
        {
            "category":"Government",
            "subcategory":"Office",
            "type":"Public Place"
        }
    ],
    "sg:phone":"+1 306 776 2479",
    "sg:postcode":"S0G 4H0",
    "sg:province":"SK",
    "sg:tags":[
        "village",
        "center",
        "bowling"
    ],
    "wof:name":"Rouleau Bowling Ctr",
    "wof:placetype":"venue"
},
  "geometry": {"coordinates":[-104.907234192,50.1885795593],"type":"Point"}
}