{
  "type": "Feature",
  "properties": {
    "addr:full":"Thurso QC J0X 3B0",
    "addr:postcode":"j0x 3b0",
    "iso:country":"CA",
    "sg:city":"Thurso",
    "sg:classifiers":[
        {
            "category":"Shopping",
            "subcategory":"Catalog Store",
            "type":"Retail Goods"
        }
    ],
    "sg:phone":"+1 819 985 2281",
    "sg:postcode":"J0X 3B0",
    "sg:province":"QC",
    "sg:tags":[
        "mail",
        "order",
        "internet"
    ],
    "wof:name":"Sears Canada Inc",
    "wof:placetype":"venue"
},
  "geometry": {"coordinates":[-75.2438278198,45.5986976624],"type":"Point"}
}