{
  "type": "Feature",
  "properties": {
    "addr:full":"192 Commerical St Berwick NS B0P 1E0",
    "addr:housenumber":"192",
    "addr:postcode":"b0p 1e0",
    "addr:street":"Commerical St",
    "iso:country":"CA",
    "sg:address":"192 Commerical St",
    "sg:city":"Berwick",
    "sg:classifiers":[
        {
            "category":"Shopping",
            "type":"Retail Goods"
        }
    ],
    "sg:phone":"+1 902 538 9900",
    "sg:postcode":"B0P 1E0",
    "sg:province":"NS",
    "sg:tags":[
        "monument"
    ],
    "wof:name":"Heritage Memorials Ltd",
    "wof:placetype":"venue"
},
  "geometry": {"coordinates":[-64.737724,45.049816],"type":"Point"}
}