{
  "type": "Feature",
  "properties": {
    "iso:country":"CA",
    "sg:city":"Laval",
    "sg:classifiers":[
        {
            "category":"Social Services",
            "subcategory":"Job Training",
            "type":"Services"
        }
    ],
    "sg:phone":"+1 450 664 0711",
    "sg:postcode":"H7E 2B8",
    "sg:province":"QC",
    "sg:tags":[
        "employment"
    ],
    "wof:name":"Association Midi-Quarante Inc",
    "wof:placetype":"venue"
},
  "geometry": {"coordinates":[-73.6677474976,45.5925521851],"type":"Point"}
}