{
  "type": "Feature",
  "properties": {
    "addr:full":"2827 Yonge St Toronto ON M4N 2J4",
    "addr:housenumber":"2827",
    "addr:postcode":"m4n 2j4",
    "addr:street":"Yonge St",
    "iso:country":"CA",
    "sg:address":"2827 Yonge St",
    "sg:city":"Toronto",
    "sg:classifiers":[
        {
            "category":"Building & Trades",
            "subcategory":"Landscaping Services",
            "type":"Services"
        }
    ],
    "sg:phone":"+1 416 481 6429",
    "sg:postcode":"M4N 2J4",
    "sg:province":"ON",
    "sg:tags":[
        "center",
        "garden",
        "landscape",
        "contractor"
    ],
    "wof:name":"Sheridan Nurseries Ltd",
    "wof:placetype":"venue"
},
  "geometry": {"coordinates":[-79.40082550050001,43.7192611694],"type":"Point"}
}