{
  "type": "Feature",
  "properties": {
    "addr:full":"5400 16E Av Shawinigan QC G9N 4T3",
    "addr:housenumber":"5400",
    "addr:postcode":"g9n 4t3",
    "addr:street":"16E Av",
    "iso:country":"CA",
    "sg:address":"5400 16E Av",
    "sg:city":"Shawinigan",
    "sg:classifiers":[
        {
            "category":"Organizations",
            "subcategory":"Religious Organization",
            "type":"Services"
        }
    ],
    "sg:phone":"+1 819 539 8295",
    "sg:postcode":"G9N 4T3",
    "sg:province":"QC",
    "sg:tags":[
        "house",
        "retreat"
    ],
    "wof:name":"Residences Des Chesnes",
    "wof:placetype":"venue"
},
  "geometry": {"coordinates":[-72.728386,46.570831],"type":"Point"}
}