{
  "type": "Feature",
  "properties": {
    "addr:full":"174 Edgebrook Close NW Calgary AB T3A 4W7",
    "addr:housenumber":"174",
    "addr:postcode":"t3a 4w7",
    "addr:street":"Edgebrook Close Nw",
    "iso:country":"CA",
    "sg:address":"174 Edgebrook Close NW",
    "sg:city":"Calgary",
    "sg:classifiers":[
        {
            "category":"Shopping",
            "subcategory":"Computers & Home Electronics",
            "type":"Retail Goods"
        }
    ],
    "sg:phone":"+1 403 263 5803",
    "sg:postcode":"T3A 4W7",
    "sg:province":"AB",
    "sg:tags":[
        "software"
    ],
    "wof:name":"Rockwave Technology",
    "wof:placetype":"venue"
},
  "geometry": {"coordinates":[-114.131790161,51.1315460205],"type":"Point"}
}