{
  "type": "Feature",
  "properties": {
    "addr:full":"Barrhead AB T7N 1N3",
    "addr:postcode":"t7n 1n3",
    "iso:country":"CA",
    "sg:city":"Barrhead",
    "sg:classifiers":[
        {
            "category":"Building & Trades",
            "subcategory":"Construction",
            "type":"Services"
        }
    ],
    "sg:phone":"+1 780 674 3921",
    "sg:postcode":"T7N 1N3",
    "sg:province":"AB",
    "sg:tags":[
        "water",
        "well",
        "drilling"
    ],
    "wof:name":"Vern Mahar Drilling Ltd",
    "wof:placetype":"venue"
},
  "geometry": {"coordinates":[-114.406006,54.120991],"type":"Point"}
}