{
  "type": "Feature",
  "properties": {
    "iso:country":"CA",
    "sg:address":"300 Boul Churchill",
    "sg:city":"Greenfield Park",
    "sg:classifiers":[
        {
            "category":"Social Services",
            "type":"Services"
        }
    ],
    "sg:phone":"+1 450 672 6461",
    "sg:postcode":"J4V 2N2",
    "sg:province":"QC",
    "sg:tags":[
        "organization",
        "welfare"
    ],
    "wof:name":"Apres-Coup",
    "wof:placetype":"venue"
},
  "geometry": {"coordinates":[-73.483276,45.494598],"type":"Point"}
}