{
  "type": "Feature",
  "properties": {
    "iso:country":"CA",
    "sg:address":"241 Queen St E",
    "sg:city":"Brampton",
    "sg:classifiers":[
        {
            "category":"Retail",
            "subcategory":"Auto Rental",
            "type":"Services"
        }
    ],
    "sg:phone":"+1 905 452 8818",
    "sg:postcode":"L6W 2B5",
    "sg:province":"ON",
    "sg:tags":[
        "renting",
        "automobile",
        "leasing"
    ],
    "wof:name":"John Logan National Leasing",
    "wof:placetype":"venue"
},
  "geometry": {"coordinates":[-79.74690246580001,43.6977119446],"type":"Point"}
}