{
  "type": "Feature",
  "properties": {
    "addr:full":"584 Rue Rene-Verrier Drummondville QC J2C 7Z7",
    "addr:housenumber":"584",
    "addr:postcode":"j2c 7z7",
    "addr:street":"Rue Rene-Verrier",
    "iso:country":"CA",
    "sg:address":"584 Rue Rene-Verrier",
    "sg:city":"Drummondville",
    "sg:classifiers":[
        {
            "category":"Retail",
            "subcategory":"Auto Repair",
            "type":"Services"
        }
    ],
    "sg:phone":"+1 819 477 1361",
    "sg:postcode":"J2C 7Z7",
    "sg:province":"QC",
    "sg:tags":[
        "body",
        "automobile",
        "painting"
    ],
    "wof:name":"Pro Du Pare-Brise",
    "wof:placetype":"venue"
},
  "geometry": {"coordinates":[-72.512726,45.904037],"type":"Point"}
}