{
  "type": "Feature",
  "properties": {
    "addr:full":"234 17th St Hanover ON N4N 2A8",
    "addr:housenumber":"234",
    "addr:postcode":"n4n 2a8",
    "addr:street":"17Th St",
    "iso:country":"CA",
    "sg:address":"234 17th St",
    "sg:city":"Hanover",
    "sg:classifiers":[
        {
            "category":"Building & Trades",
            "subcategory":"Landscaping Services",
            "type":"Services"
        }
    ],
    "sg:phone":"+1 519 364 0972",
    "sg:postcode":"N4N 2A8",
    "sg:province":"ON",
    "sg:tags":[
        "lawn",
        "contractor",
        "landscape",
        "maintenance",
        "grounds"
    ],
    "wof:name":"Hanover Lawn Maintenance",
    "wof:placetype":"venue"
},
  "geometry": {"coordinates":[-81.032005,44.160019],"type":"Point"}
}