{
  "type": "Feature",
  "properties": {
    "addr:full":"64 Rue Pinsonneault #A Saint-Constant QC J5A 1B5",
    "addr:housenumber":"64",
    "addr:postcode":"j5a 1b5",
    "addr:street":"Rue Pinsonneault # A",
    "iso:country":"CA",
    "sg:address":"64 Rue Pinsonneault #A",
    "sg:city":"Saint-Constant",
    "sg:classifiers":[
        {
            "category":"Building & Trades",
            "subcategory":"Electrical",
            "type":"Services"
        }
    ],
    "sg:phone":"+1 450 632 4161",
    "sg:postcode":"J5A 1B5",
    "sg:province":"QC",
    "sg:tags":[
        "electric",
        "contractor"
    ],
    "wof:name":"Entreprises D'Elec C Bedard",
    "wof:placetype":"venue"
},
  "geometry": {"coordinates":[-73.5600204468,45.3796653748],"type":"Point"}
}