{
  "type": "Feature",
  "properties": {
    "iso:country":"CA",
    "sg:address":"90 Sparks St",
    "sg:city":"Ottawa",
    "sg:classifiers":[
        {
            "category":"Travel",
            "subcategory":"Travel Agent",
            "type":"Entertainment"
        }
    ],
    "sg:phone":"+1 613 237 9200",
    "sg:postcode":"K1P 5B4",
    "sg:province":"ON",
    "sg:tags":[
        "agency",
        "bureau"
    ],
    "wof:name":"Algonquin Travel",
    "wof:placetype":"venue"
},
  "geometry": {"coordinates":[-75.6970901489,45.4228515625],"type":"Point"}
}