{
  "type": "Feature",
  "properties": {
    "iso:country":"CA",
    "sg:address":"644 Rue Deslauriers",
    "sg:city":"Saint-Laurent",
    "sg:classifiers":[
        {
            "category":"Wholesale",
            "subcategory":"Fruits & Vegetables",
            "type":"Manufacturing & Wholesale Goods"
        }
    ],
    "sg:phone":"+1 514 745 3679",
    "sg:postcode":"H4N 1W5",
    "sg:province":"QC",
    "wof:name":"Potager Laurentien",
    "wof:placetype":"venue"
},
  "geometry": {"coordinates":[-73.666161,45.525192],"type":"Point"}
}