{
  "type": "Feature",
  "properties": {
    "addr:full":"11875 Av Ethier Montreal-Nord QC H1H 3H5",
    "addr:housenumber":"11875",
    "addr:postcode":"h1h 3h5",
    "addr:street":"Av Ethier",
    "iso:country":"CA",
    "sg:address":"11875 Av Ethier",
    "sg:city":"Montreal-Nord",
    "sg:classifiers":[
        {
            "category":"Wholesale",
            "subcategory":"Vending Machines",
            "type":"Manufacturing & Wholesale Goods"
        }
    ],
    "sg:phone":"+1 514 322 1040",
    "sg:postcode":"H1H 3H5",
    "sg:province":"QC",
    "wof:name":"Automates Prebec Ltee",
    "wof:placetype":"venue"
},
  "geometry": {"coordinates":[-73.639038,45.60355],"type":"Point"}
}