{
  "type": "Feature",
  "properties": {
    "addr:full":"3532 Commercial St Vancouver BC V5N 4E9",
    "addr:housenumber":"3532",
    "addr:postcode":"v5n 4e9",
    "addr:street":"Commercial St",
    "iso:country":"CA",
    "sg:address":"3532 Commercial St",
    "sg:city":"Vancouver",
    "sg:classifiers":[
        {
            "category":"Restaurant",
            "type":"Food & Drink"
        }
    ],
    "sg:phone":"+1 604 876 7647",
    "sg:postcode":"V5N 4E9",
    "sg:province":"BC",
    "wof:name":"Casa Verde Restaurant",
    "wof:placetype":"venue"
},
  "geometry": {"coordinates":[-123.067703247,49.253074646],"type":"Point"}
}