{
  "type": "Feature",
  "properties": {
    "addr:full":"204 6th Ave NW Nakusp BC V0G 1R0",
    "addr:housenumber":"204",
    "addr:postcode":"v0g 1r0",
    "addr:street":"6Th Ave Nw",
    "iso:country":"CA",
    "sg:address":"204 6th Ave NW",
    "sg:city":"Nakusp",
    "sg:classifiers":[
        {
            "category":"Government",
            "subcategory":"Office",
            "type":"Public Place"
        }
    ],
    "sg:phone":"+1 250 265 4865",
    "sg:postcode":"V0G 1R0",
    "sg:province":"BC",
    "wof:name":"British Columbia Child Family",
    "wof:placetype":"venue"
},
  "geometry": {"coordinates":[-117.804993,50.241497],"type":"Point"}
}