{
  "type": "Feature",
  "properties": {
    "addr:full":"2974 Marine Dr West Vancouver BC V7V 1M2",
    "addr:housenumber":"2974",
    "addr:postcode":"v7v 1m2",
    "addr:street":"Marine Dr",
    "iso:country":"CA",
    "sg:address":"2974 Marine Dr",
    "sg:city":"West Vancouver",
    "sg:classifiers":[
        {
            "category":"Freight",
            "type":"Transportation"
        }
    ],
    "sg:phone":"+1 604 251 7867",
    "sg:postcode":"V7V 1M2",
    "sg:province":"BC",
    "sg:tags":[
        "commercial",
        "storage"
    ],
    "wof:name":"Storkit Storage",
    "wof:placetype":"venue"
},
  "geometry": {"coordinates":[-123.19826500000001,49.338814],"type":"Point"}
}