{
  "type": "Feature",
  "properties": {
    "iso:country":"CA",
    "sg:address":"30 Carden St",
    "sg:city":"Guelph",
    "sg:classifiers":[
        {
            "category":"Shopping",
            "type":"Retail Goods"
        }
    ],
    "sg:phone":"+1 519 836 5873",
    "sg:postcode":"N1H 3A2",
    "sg:province":"ON",
    "sg:tags":[
        "picture",
        "frame",
        "art",
        "gallery",
        "dealer"
    ],
    "wof:name":"Framing & Art Ctr",
    "wof:placetype":"venue"
},
  "geometry": {"coordinates":[-80.248764,43.543976],"type":"Point"}
}