{
  "type": "Feature",
  "properties": {
    "addr:full":"30 Carden St Guelph ON N1H 3A2",
    "addr:housenumber":"30",
    "addr:postcode":"n1h 3a2",
    "addr:street":"Carden St",
    "iso:country":"CA",
    "sg:address":"30 Carden St",
    "sg:city":"Guelph",
    "sg:classifiers":[
        {
            "category":"Shopping",
            "type":"Retail Goods"
        }
    ],
    "sg:phone":"+1 519 836 5873",
    "sg:postcode":"N1H 3A2",
    "sg:province":"ON",
    "sg:tags":[
        "picture",
        "frame",
        "art",
        "gallery",
        "dealer"
    ],
    "wof:name":"Framing & Art Ctr",
    "wof:placetype":"venue"
},
  "geometry": {"coordinates":[-80.24876399999999,43.543976],"type":"Point"}
}