{
  "type": "Feature",
  "properties": {
    "addr:full":"541 Portage Ave Winnipeg MB R3B 2G1",
    "addr:housenumber":"541",
    "addr:postcode":"r3b 2g1",
    "addr:street":"Portage Ave",
    "iso:country":"CA",
    "sg:address":"541 Portage Ave",
    "sg:city":"Winnipeg",
    "sg:classifiers":[
        {
            "category":"Communications",
            "subcategory":"Radio Station",
            "type":"Services"
        }
    ],
    "sg:phone":"+1 204 788 3222",
    "sg:postcode":"R3B 2G1",
    "sg:province":"MB",
    "sg:tags":[
        "company",
        "broadcasting"
    ],
    "wof:name":"Canadian Broadcasting Corp",
    "wof:placetype":"venue"
},
  "geometry": {"coordinates":[-97.1541442871,49.8898658752],"type":"Point"}
}