{
  "type": "Feature",
  "properties": {
    "addr:full":"432 2nd Ave N Vauxhall AB T0K 2K0",
    "addr:housenumber":"432",
    "addr:postcode":"t0k 2k0",
    "addr:street":"2Nd Ave N",
    "iso:country":"CA",
    "sg:address":"432 2nd Ave N",
    "sg:city":"Vauxhall",
    "sg:classifiers":[
        {
            "category":"Professional",
            "subcategory":"Lawyer & Legal Services",
            "type":"Services"
        }
    ],
    "sg:phone":"+1 403 654 4211",
    "sg:postcode":"T0K 2K0",
    "sg:province":"AB",
    "sg:tags":[
        "attorney"
    ],
    "wof:name":"Baldry Sugden Law Office",
    "wof:placetype":"venue"
},
  "geometry": {"coordinates":[-112.104103088,50.0683784485],"type":"Point"}
}