{
  "type": "Feature",
  "properties": {
    "addr:full":"Wolfe Island ON K0H 2Y0",
    "addr:postcode":"k0h 2y0",
    "iso:country":"CA",
    "sg:city":"Wolfe Island",
    "sg:classifiers":[
        {
            "category":"Freight",
            "type":"Transportation"
        }
    ],
    "sg:phone":"+1 613 385 2923",
    "sg:postcode":"K0H 2Y0",
    "sg:province":"ON",
    "sg:tags":[
        "carriage"
    ],
    "wof:name":"White's Ride's",
    "wof:placetype":"venue"
},
  "geometry": {"coordinates":[-76.4560699463,44.1892204285],"type":"Point"}
}