{
  "type": "Feature",
  "properties": {
    "addr:full":"Marysville BC V1A 3H5",
    "addr:postcode":"v1a 3h5",
    "iso:country":"CA",
    "sg:city":"Marysville",
    "sg:classifiers":[
        {
            "category":"Social Services",
            "subcategory":"Child Care",
            "type":"Services"
        }
    ],
    "sg:phone":"+1 250 427 4945",
    "sg:postcode":"V1A 3H5",
    "sg:province":"BC",
    "wof:name":"Sonya's Quality Childcare Ctr",
    "wof:placetype":"venue"
},
  "geometry": {"coordinates":[-115.956459045,49.6363945007],"type":"Point"}
}