{
  "type": "Feature",
  "properties": {
    "addr:full":"67 Memorial Ave Orillia ON L3V 5W9",
    "addr:housenumber":"67",
    "addr:postcode":"l3v 5w9",
    "addr:street":"Memorial Ave",
    "iso:country":"CA",
    "sg:address":"67 Memorial Ave",
    "sg:city":"Orillia",
    "sg:classifiers":[
        {
            "category":"Restaurant",
            "type":"Food & Drink"
        }
    ],
    "sg:phone":"+1 705 325 0034",
    "sg:postcode":"L3V 5W9",
    "sg:province":"ON",
    "sg:tags":[
        "parlor",
        "ice",
        "cream"
    ],
    "wof:name":"Dairy Queen",
    "wof:placetype":"venue"
},
  "geometry": {"coordinates":[-79.4260635376,44.6022758484],"type":"Point"}
}