{
  "type": "Feature",
  "properties": {
    "addr:full":"Mississauga ON L5L 5S9",
    "addr:postcode":"l5l 5s9",
    "iso:country":"CA",
    "sg:city":"Mississauga",
    "sg:classifiers":[
        {
            "category":"Manufacturing",
            "subcategory":"Furniture",
            "type":"Manufacturing & Wholesale Goods"
        }
    ],
    "sg:phone":"+1 905 607 3658",
    "sg:postcode":"L5L 5S9",
    "sg:province":"ON",
    "wof:name":"Lovat Furniture Inc",
    "wof:placetype":"venue"
},
  "geometry": {"coordinates":[-79.71635437010001,43.5301971436],"type":"Point"}
}