{
  "type": "Feature",
  "properties": {
    "addr:full":"2116 Boul DE Boucherville Saint-Bruno QC J3V 5X9",
    "addr:housenumber":"2116",
    "addr:postcode":"j3v 5x9",
    "addr:street":"Boul De Boucherville",
    "iso:country":"CA",
    "sg:address":"2116 Boul DE Boucherville",
    "sg:city":"Saint-Bruno",
    "sg:classifiers":[
        {
            "category":"Health Services",
            "subcategory":"Chiropractor",
            "type":"Services"
        }
    ],
    "sg:phone":"+1 450 441 2023",
    "sg:postcode":"J3V 5X9",
    "sg:province":"QC",
    "wof:name":"Lefebvre, Stephane DC",
    "wof:placetype":"venue"
},
  "geometry": {"coordinates":[-71.675522,48.471771],"type":"Point"}
}