{
  "type": "Feature",
  "properties": {
    "addr:full":"3036 Rue Saint-Laurent Levis QC G6V 3W5",
    "addr:housenumber":"3036",
    "addr:postcode":"g6v 3w5",
    "addr:street":"Rue Saint-Laurent",
    "iso:country":"CA",
    "sg:address":"3036 Rue Saint-Laurent",
    "sg:city":"Levis",
    "sg:classifiers":[
        {
            "category":"Professional",
            "subcategory":"Research",
            "type":"Services"
        }
    ],
    "sg:phone":"+1 418 839 5868",
    "sg:postcode":"G6V 3W5",
    "sg:province":"QC",
    "sg:tags":[
        "environmental",
        "ecological"
    ],
    "wof:name":"Bureau D'Ecologie Appliquee",
    "wof:placetype":"venue"
},
  "geometry": {"coordinates":[-71.2167510986,46.7682952881],"type":"Point"}
}