{
  "type": "Feature",
  "properties": {
    "iso:country":"CA",
    "sg:city":"Piapot",
    "sg:classifiers":[
        {
            "category":"Farming",
            "subcategory":"Farm & Veterinary Services",
            "type":"Manufacturing & Wholesale Goods"
        }
    ],
    "sg:phone":"+1 306 558 4452",
    "sg:postcode":"S0N 1Y0",
    "sg:province":"SK",
    "sg:tags":[
        "seed",
        "grain",
        "cleaning"
    ],
    "wof:name":"Jensen Seed Cleaning Plant",
    "wof:placetype":"venue"
},
  "geometry": {"coordinates":[-109.12716674799999,49.9896316528],"type":"Point"}
}