{
  "type": "Feature",
  "properties": {
    "addr:full":"James River Rd Antigonish NS B2G 2K8",
    "addr:postcode":"b2g 2k8",
    "addr:street":"James River Rd",
    "iso:country":"CA",
    "sg:address":"James River Rd",
    "sg:city":"Antigonish",
    "sg:classifiers":[
        {
            "category":"Autos & Motor Vehicles",
            "subcategory":"Automobile Sales",
            "type":"Retail Goods"
        }
    ],
    "sg:phone":"+1 902 863 6620",
    "sg:postcode":"B2G 2K8",
    "sg:province":"NS",
    "sg:tags":[
        "car",
        "dealer"
    ],
    "wof:name":"Willie G's",
    "wof:placetype":"venue"
},
  "geometry": {"coordinates":[-61.99427,45.622189],"type":"Point"}
}