{
  "type": "Feature",
  "properties": {
    "addr:full":"4385 57 St Delta BC V4K 3C8",
    "addr:housenumber":"4385",
    "addr:postcode":"v4k 3c8",
    "addr:street":"57 St",
    "iso:country":"CA",
    "sg:address":"4385 57 St",
    "sg:city":"Delta",
    "sg:classifiers":[
        {
            "category":"Building & Trades",
            "subcategory":"Construction",
            "type":"Services"
        }
    ],
    "sg:phone":"+1 604 946 3004",
    "sg:postcode":"V4K 3C8",
    "sg:province":"BC",
    "sg:tags":[
        "downspouts",
        "gutter"
    ],
    "wof:name":"Busy Bee Gutter",
    "wof:placetype":"venue"
},
  "geometry": {"coordinates":[-123.065612793,49.0839195251],"type":"Point"}
}