{
  "type": "Feature",
  "properties": {
    "iso:country":"CA",
    "sg:address":"152 Main St",
    "sg:city":"Lafleche",
    "sg:classifiers":[
        {
            "category":"Wholesale",
            "subcategory":"Machinery & Supplies",
            "type":"Manufacturing & Wholesale Goods"
        }
    ],
    "sg:phone":"+1 306 472 5440",
    "sg:postcode":"S0H 2K0",
    "sg:province":"SK",
    "sg:tags":[
        "agricultural",
        "implement"
    ],
    "wof:name":"Superior Farm Equipment",
    "wof:placetype":"venue"
},
  "geometry": {"coordinates":[-106.57157135,49.6989746094],"type":"Point"}
}