{
  "type": "Feature",
  "properties": {
    "iso:country":"CA",
    "sg:city":"Oakville",
    "sg:classifiers":[
        {
            "category":"Health Services",
            "subcategory":"Doctor",
            "type":"Services"
        }
    ],
    "sg:phone":"+1 905 842 0972",
    "sg:postcode":"L6J 1X8",
    "sg:province":"ON",
    "sg:tags":[
        "physician",
        "surgeon"
    ],
    "wof:name":"Belovic, Brian MD",
    "wof:placetype":"venue"
},
  "geometry": {"coordinates":[-79.6709976196,43.4522628784],"type":"Point"}
}