{
  "type": "Feature",
  "properties": {
    "addr:full":"439 4E Rue Laval QC H7N 2B3",
    "addr:housenumber":"439",
    "addr:postcode":"h7n 2b3",
    "addr:street":"4E Rue",
    "iso:country":"CA",
    "sg:address":"439 4E Rue",
    "sg:city":"Laval",
    "sg:classifiers":[
        {
            "category":"Retail",
            "subcategory":"Auto Repair",
            "type":"Services"
        }
    ],
    "sg:phone":"+1 514 917 2540",
    "sg:postcode":"H7N 2B3",
    "sg:province":"QC",
    "sg:tags":[
        "body",
        "automobile",
        "painting"
    ],
    "wof:name":"Ricardo Casciaro Auto Repaint",
    "wof:placetype":"venue"
},
  "geometry": {"coordinates":[-73.717956543,45.5488967896],"type":"Point"}
}