{
  "type": "Feature",
  "properties": {
    "iso:country":"CA",
    "sg:address":"Junction Hwy 9 & 41",
    "sg:city":"Oyen",
    "sg:classifiers":[
        {
            "category":"Autos & Motor Vehicles",
            "subcategory":"Fuel & Gas Station",
            "type":"Retail Goods"
        }
    ],
    "sg:phone":"+1 403 664 3633",
    "sg:postcode":"T0J 2J0",
    "sg:province":"AB",
    "sg:tags":[
        "oil"
    ],
    "wof:name":"Oyen CO-OP",
    "wof:placetype":"venue"
},
  "geometry": {"coordinates":[-110.470832825,51.3501701355],"type":"Point"}
}