{
  "type": "Feature",
  "properties": {
    "addr:full":"Scarborough ON M1P 3B2",
    "addr:postcode":"m1p 3b2",
    "iso:country":"CA",
    "sg:city":"Scarborough",
    "sg:classifiers":[
        {
            "category":"Building & Trades",
            "subcategory":"Construction",
            "type":"Services"
        }
    ],
    "sg:phone":"+1 416 285 7835",
    "sg:postcode":"M1P 3B2",
    "sg:province":"ON",
    "sg:tags":[
        "elevator"
    ],
    "wof:name":"Demtra Elevator Interiors Ltd",
    "wof:placetype":"venue"
},
  "geometry": {"coordinates":[-79.269241333,43.7560501099],"type":"Point"}
}