{
  "type": "Feature",
  "properties": {
    "addr:full":"14111 127 St NW Edmonton AB T6V 1E7",
    "addr:housenumber":"14111",
    "addr:postcode":"t6v 1e7",
    "addr:street":"127 St Nw",
    "iso:country":"CA",
    "sg:address":"14111 127 St NW",
    "sg:city":"Edmonton",
    "sg:classifiers":[
        {
            "category":"Retail",
            "subcategory":"Auto Repair",
            "type":"Services"
        }
    ],
    "sg:phone":"+1 780 472 8473",
    "sg:postcode":"T6V 1E7",
    "sg:province":"AB",
    "sg:tags":[
        "repairing",
        "automobile"
    ],
    "wof:name":"Tire Warehouse",
    "wof:placetype":"venue"
},
  "geometry": {"coordinates":[-113.54095459,53.6032333374],"type":"Point"}
}