{
  "type": "Feature",
  "properties": {
    "iso:country":"CA",
    "sg:address":"40 Rte Des Erables",
    "sg:city":"Caplan",
    "sg:classifiers":[
        {
            "category":"Real Estate",
            "subcategory":"Real Estate Agent",
            "type":"Services"
        }
    ],
    "sg:phone":"+1 418 388 2860",
    "sg:postcode":"G0C 1H0",
    "sg:province":"QC",
    "sg:tags":[
        "paint",
        "cooperative"
    ],
    "wof:name":"Cooperative Agricole Baie",
    "wof:placetype":"venue"
},
  "geometry": {"coordinates":[-65.67961883540001,48.107925415],"type":"Point"}
}