{
  "type": "Feature",
  "properties": {
    "addr:full":"1324 Sayward Rd Sayward BC V0P 1R0",
    "addr:housenumber":"1324",
    "addr:postcode":"v0p 1r0",
    "addr:street":"Sayward Rd",
    "iso:country":"CA",
    "sg:address":"1324 Sayward Rd",
    "sg:city":"Sayward",
    "sg:classifiers":[
        {
            "category":"Shopping",
            "subcategory":"Used Merchandise",
            "type":"Retail Goods"
        }
    ],
    "sg:phone":"+1 250 282 3363",
    "sg:postcode":"V0P 1R0",
    "sg:province":"BC",
    "sg:tags":[
        "antique"
    ],
    "wof:name":"Treasured Moments Antiques",
    "wof:placetype":"venue"
},
  "geometry": {"coordinates":[-125.943496704,50.3692321777],"type":"Point"}
}