{
  "type": "Feature",
  "properties": {
    "iso:country":"CA",
    "sg:city":"Joliette",
    "sg:classifiers":[
        {
            "category":"Manufacturing",
            "subcategory":"Signs",
            "type":"Manufacturing & Wholesale Goods"
        }
    ],
    "sg:phone":"+1 450 759 0955",
    "sg:postcode":"J6E 2S6",
    "sg:province":"QC",
    "wof:name":"Amtech Design Enr",
    "wof:placetype":"venue"
},
  "geometry": {"coordinates":[-73.4411773682,46.0298309326],"type":"Point"}
}