{
  "type": "Feature",
  "properties": {
    "addr:full":"Williams Lake BC V2G 2G8",
    "addr:postcode":"bc v2g 2g8",
    "iso:country":"CA",
    "sg:city":"Williams Lake",
    "sg:classifiers":[
        {
            "category":"Health Services",
            "subcategory":"Doctor",
            "type":"Services"
        }
    ],
    "sg:phone":"+1 250 398 8280",
    "sg:postcode":"V2G 2G8",
    "sg:province":"BC",
    "sg:tags":[
        "physician",
        "surgeon"
    ],
    "wof:name":"Specialist Physicians",
    "wof:placetype":"venue"
},
  "geometry": {"coordinates":[-122.142051697,52.1374053955],"type":"Point"}
}