{
  "type": "Feature",
  "properties": {
    "addr:full":"Elk Point AB T0A 1A0",
    "addr:postcode":"t0a 1a0",
    "iso:country":"CA",
    "sg:city":"Elk Point",
    "sg:classifiers":[
        {
            "category":"Restaurant",
            "type":"Food & Drink"
        }
    ],
    "sg:phone":"+1 780 724 4373",
    "sg:postcode":"T0A 1A0",
    "sg:province":"AB",
    "sg:tags":[
        "grocer"
    ],
    "wof:name":"Tags Elk Point",
    "wof:placetype":"venue"
},
  "geometry": {"coordinates":[-110.89654541,53.8959922791],"type":"Point"}
}