{
  "type": "Feature",
  "properties": {
    "addr:full":"PO Box 1101 High Level AB T0H 1Z0",
    "addr:housenumber":"po",
    "addr:postcode":"t0h 1z0",
    "addr:street":"Box 1101",
    "iso:country":"CA",
    "sg:address":"PO Box 1101",
    "sg:city":"High Level",
    "sg:classifiers":[
        {
            "category":"Freight",
            "type":"Transportation"
        }
    ],
    "sg:phone":"+1 780 926 3247",
    "sg:postcode":"T0H 1Z0",
    "sg:province":"AB",
    "sg:tags":[
        "field",
        "oil"
    ],
    "wof:name":"Pigeon Transport Ltd",
    "wof:placetype":"venue"
},
  "geometry": {"coordinates":[-117.126091,58.51672],"type":"Point"}
}