{
  "type": "Feature",
  "properties": {
    "iso:country":"CA",
    "sg:address":"4509 54th Ave",
    "sg:city":"Bon Accord",
    "sg:classifiers":[
        {
            "category":"Recreation",
            "type":"Entertainment"
        }
    ],
    "sg:phone":"+1 780 921 3233",
    "sg:postcode":"T0A 0K0",
    "sg:province":"AB",
    "sg:tags":[
        "hall",
        "auditorium"
    ],
    "wof:name":"Lilian Schick School Community",
    "wof:placetype":"venue"
},
  "geometry": {"coordinates":[-113.40573883099999,53.8400497437],"type":"Point"}
}