{
  "type": "Feature",
  "properties": {
    "addr:full":"4333 Colonel Talbot Rd London ON N6P 1P9",
    "addr:housenumber":"4333",
    "addr:postcode":"n6p 1p9",
    "addr:street":"Colonel Talbot Rd",
    "iso:country":"CA",
    "sg:address":"4333 Colonel Talbot Rd",
    "sg:city":"London",
    "sg:classifiers":[
        {
            "category":"Home & Garden",
            "subcategory":"Carpets & Floor Coverings",
            "type":"Retail Goods"
        }
    ],
    "sg:phone":"+1 519 652 0140",
    "sg:postcode":"N6P 1P9",
    "sg:province":"ON",
    "sg:tags":[
        "rug"
    ],
    "wof:name":"Floorsource",
    "wof:placetype":"venue"
},
  "geometry": {"coordinates":[-81.29978199999999,42.908573],"type":"Point"}
}