{
  "type": "Feature",
  "properties": {
    "addr:full":"640 Park Ave Beausejour MB R0E 0C0",
    "addr:housenumber":"640",
    "addr:postcode":"r0e 0c0",
    "addr:street":"Park Ave",
    "iso:country":"CA",
    "sg:address":"640 Park Ave",
    "sg:city":"Beausejour",
    "sg:classifiers":[
        {
            "category":"Personal",
            "subcategory":"Beauty Salon",
            "type":"Services"
        }
    ],
    "sg:phone":"+1 204 268 1088",
    "sg:postcode":"R0E 0C0",
    "sg:province":"MB",
    "wof:name":"Hairfax",
    "wof:placetype":"venue"
},
  "geometry": {"coordinates":[-96.51348900000001,50.061653],"type":"Point"}
}