{
  "type": "Feature",
  "properties": {
    "addr:full":"2240 Boul Industriel Chambly QC J3L 4V2",
    "addr:housenumber":"2240",
    "addr:postcode":"j3l 4v2",
    "addr:street":"Boul Industriel",
    "iso:country":"CA",
    "sg:address":"2240 Boul Industriel",
    "sg:city":"Chambly",
    "sg:classifiers":[
        {
            "category":"Building & Trades",
            "subcategory":"Equipment Rental",
            "type":"Services"
        }
    ],
    "sg:phone":"+1 514 726 6585",
    "sg:postcode":"J3L 4V2",
    "sg:province":"QC",
    "sg:tags":[
        "crane"
    ],
    "wof:name":"A 1 Mobile Rive-Sud",
    "wof:placetype":"venue"
},
  "geometry": {"coordinates":[-73.27508544920001,45.4330024719],"type":"Point"}
}