{
  "type": "Feature",
  "properties": {
    "iso:country":"CA",
    "sg:address":"6508 31 Ave NW",
    "sg:city":"Edmonton",
    "sg:classifiers":[
        {
            "category":"Organizations",
            "subcategory":"Religious Organization",
            "type":"Services"
        }
    ],
    "sg:phone":"+1 780 463 1527",
    "sg:postcode":"T6L 6P7",
    "sg:province":"AB",
    "sg:tags":[
        "church"
    ],
    "wof:name":"South Edmonton Alliance Church",
    "wof:placetype":"venue"
},
  "geometry": {"coordinates":[-113.433502197,53.4623908997],"type":"Point"}
}