{
  "type": "Feature",
  "properties": {
    "iso:country":"CA",
    "sg:address":"112 2nd St",
    "sg:city":"Oakville",
    "sg:classifiers":[
        {
            "category":"Personal",
            "subcategory":"Beauty Salon",
            "type":"Services"
        }
    ],
    "sg:phone":"+1 204 267 2254",
    "sg:postcode":"R0H 0Y0",
    "sg:province":"MB",
    "wof:name":"Hay's Hair Design",
    "wof:placetype":"venue"
},
  "geometry": {"coordinates":[-98.0039520264,49.9297599792],"type":"Point"}
}