{
  "type": "Feature",
  "properties": {
    "addr:full":"77416 Bluewater Hwy Bayfield ON N0M 1G0",
    "addr:housenumber":"77416",
    "addr:postcode":"n0m 1g0",
    "addr:street":"Bluewater Hwy",
    "iso:country":"CA",
    "sg:address":"77416 Bluewater Hwy",
    "sg:city":"Bayfield",
    "sg:classifiers":[
        {
            "category":"Sports & Exercise",
            "subcategory":"Golf",
            "type":"Entertainment"
        }
    ],
    "sg:phone":"+1 519 482 7197",
    "sg:postcode":"N0M 1G0",
    "sg:province":"ON",
    "sg:tags":[
        "course"
    ],
    "wof:name":"Bluewater Golf Course & Camp",
    "wof:placetype":"venue"
},
  "geometry": {"coordinates":[-81.70536800000001,43.575699],"type":"Point"}
}