{
  "type": "Feature",
  "properties": {
    "addr:full":"25 Hibbins Ave Ajax ON L1T 4C4",
    "addr:housenumber":"25",
    "addr:postcode":"l1t 4c4",
    "addr:street":"Hibbins Ave",
    "iso:country":"CA",
    "sg:address":"25 Hibbins Ave",
    "sg:city":"Ajax",
    "sg:classifiers":[
        {
            "category":"Insurance",
            "subcategory":"Insurance Agent",
            "type":"Services"
        }
    ],
    "sg:phone":"+1 905 619 9544",
    "sg:postcode":"L1T 4C4",
    "sg:province":"ON",
    "wof:name":"Chappell & Stone Insurance",
    "wof:placetype":"venue"
},
  "geometry": {"coordinates":[-79.06384300000001,43.862511],"type":"Point"}
}