{
  "type": "Feature",
  "properties": {
    "addr:full":"1170 Carling Ave Ottawa ON K1Z 7K6",
    "addr:housenumber":"1170",
    "addr:postcode":"k1z 7k6",
    "addr:street":"Carling Ave",
    "iso:country":"CA",
    "sg:address":"1170 Carling Ave",
    "sg:city":"Ottawa",
    "sg:classifiers":[
        {
            "category":"Restaurant",
            "type":"Food & Drink"
        }
    ],
    "sg:phone":"+1 613 722 1490",
    "sg:postcode":"K1Z 7K6",
    "sg:province":"ON",
    "wof:name":"New Dubrovnik Restaurant",
    "wof:placetype":"venue"
},
  "geometry": {"coordinates":[-75.7293930054,45.3879776001],"type":"Point"}
}