{
  "type": "Feature",
  "properties": {
    "iso:country":"CA",
    "sg:address":"25 Boul LA Fayette # 100",
    "sg:city":"Longueuil",
    "sg:classifiers":[
        {
            "category":"Social Services",
            "type":"Services"
        }
    ],
    "sg:phone":"+1 450 679 0140",
    "sg:postcode":"J4K 5C7",
    "sg:province":"QC",
    "sg:tags":[
        "organization",
        "welfare"
    ],
    "wof:name":"Centres Jeunesse DE Monteregie",
    "wof:placetype":"venue"
},
  "geometry": {"coordinates":[-73.523659,45.523308],"type":"Point"}
}