{
  "type": "Feature",
  "properties": {
    "addr:full":"10067 100 Ave Fort St John BC V1J 1Y7",
    "addr:housenumber":"10067",
    "addr:postcode":"v1j 1y7",
    "addr:street":"100 Ave",
    "iso:country":"CA",
    "sg:address":"10067 100 Ave",
    "sg:city":"Fort St John",
    "sg:classifiers":[
        {
            "category":"Insurance",
            "subcategory":"Insurance Agent",
            "type":"Services"
        }
    ],
    "sg:phone":"+1 250 785 7566",
    "sg:postcode":"V1J 1Y7",
    "sg:province":"BC",
    "sg:tags":[
        "consultant",
        "planning",
        "financial"
    ],
    "wof:name":"Money Concepts",
    "wof:placetype":"venue"
},
  "geometry": {"coordinates":[-120.84876300000001,56.24622],"type":"Point"}
}