{
  "type": "Feature",
  "properties": {
    "addr:full":"322 18E Av Deux-Montagnes QC J7R 4B6",
    "addr:housenumber":"322",
    "addr:postcode":"j7r 4b6",
    "addr:street":"18E Av",
    "iso:country":"CA",
    "sg:address":"322 18E Av",
    "sg:city":"Deux-Montagnes",
    "sg:classifiers":[
        {
            "category":"Building & Trades",
            "subcategory":"Electrical",
            "type":"Services"
        }
    ],
    "sg:phone":"+1 450 473 7706",
    "sg:postcode":"J7R 4B6",
    "sg:province":"QC",
    "sg:tags":[
        "electric",
        "contractor"
    ],
    "wof:name":"Dorion Electrique 2005 Inc",
    "wof:placetype":"venue"
},
  "geometry": {"coordinates":[-73.9052429199,45.5395431519],"type":"Point"}
}