{
  "type": "Feature",
  "properties": {
    "addr:full":"680 Lake George Rd South Ohio NS B0W 3E0",
    "addr:housenumber":"680",
    "addr:postcode":"b0w 3e0",
    "addr:street":"Lake George Rd",
    "iso:country":"CA",
    "sg:address":"680 Lake George Rd",
    "sg:city":"South Ohio",
    "sg:classifiers":[
        {
            "category":"Building & Trades",
            "subcategory":"Construction",
            "type":"Services"
        }
    ],
    "sg:phone":"+1 902 742 4809",
    "sg:postcode":"B0W 3E0",
    "sg:province":"NS",
    "sg:tags":[
        "contractor",
        "general"
    ],
    "wof:name":"Stanwood Builders",
    "wof:placetype":"venue"
},
  "geometry": {"coordinates":[-66.0597915649,43.929901123],"type":"Point"}
}