{
  "type": "Feature",
  "properties": {
    "addr:full":"5485 Av Victoria Montreal QC H3W 2P9",
    "addr:housenumber":"5485",
    "addr:postcode":"h3w 2p9",
    "addr:street":"Av Victoria",
    "iso:country":"CA",
    "sg:address":"5485 Av Victoria",
    "sg:city":"Montreal",
    "sg:classifiers":[
        {
            "category":"Restaurant",
            "type":"Food & Drink"
        }
    ],
    "sg:phone":"+1 514 738 6610",
    "sg:postcode":"H3W 2P9",
    "sg:province":"QC",
    "wof:name":"Restaurant Hoai Hiong",
    "wof:placetype":"venue"
},
  "geometry": {"coordinates":[-73.63102722169999,45.4915962219],"type":"Point"}
}