{
  "type": "Feature",
  "properties": {
    "addr:full":"101 Rue Saint-Pierre Matane QC G4W 2B6",
    "addr:housenumber":"101",
    "addr:postcode":"g4w 2b6",
    "addr:street":"Rue Saint-Pierre",
    "iso:country":"CA",
    "sg:address":"101 Rue Saint-Pierre",
    "sg:city":"Matane",
    "sg:classifiers":[
        {
            "category":"Restaurant",
            "type":"Food & Drink"
        }
    ],
    "sg:phone":"+1 418 562 3646",
    "sg:postcode":"G4W 2B6",
    "sg:province":"QC",
    "sg:tags":[
        "pizza"
    ],
    "wof:name":"Pizzeria Italia Restaurant",
    "wof:placetype":"venue"
},
  "geometry": {"coordinates":[-67.52973175050001,48.8466835022],"type":"Point"}
}