{
  "type": "Feature",
  "properties": {
    "addr:full":"Teulon MB R0C 3B0",
    "addr:postcode":"r0c 3b0",
    "iso:country":"CA",
    "sg:city":"Teulon",
    "sg:classifiers":[
        {
            "category":"Manufacturing",
            "subcategory":"Tools & Machinery",
            "type":"Manufacturing & Wholesale Goods"
        }
    ],
    "sg:phone":"+1 204 886 2466",
    "sg:postcode":"R0C 3B0",
    "sg:province":"MB",
    "sg:tags":[
        "machine",
        "shop"
    ],
    "wof:name":"Precise Machine Technologies",
    "wof:placetype":"venue"
},
  "geometry": {"coordinates":[-97.263092,50.385746],"type":"Point"}
}