{
  "type": "Feature",
  "properties": {
    "iso:country":"CA",
    "sg:address":"969 Rue Vercheres",
    "sg:city":"Longueuil",
    "sg:classifiers":[
        {
            "category":"Autos & Motor Vehicles",
            "subcategory":"Motorcycle Sales",
            "type":"Retail Goods"
        }
    ],
    "sg:phone":"+1 450 651 2146",
    "sg:postcode":"J4K 2Y8",
    "sg:province":"QC",
    "sg:tags":[
        "scooter"
    ],
    "wof:name":"S P Moto Enr",
    "wof:placetype":"venue"
},
  "geometry": {"coordinates":[-73.5079574585,45.516166687],"type":"Point"}
}