{
  "type": "Feature",
  "properties": {
    "addr:full":"319 Rue Franquet Sainte-Foy QC G1P 4R4",
    "addr:housenumber":"319",
    "addr:postcode":"g1p 4r4",
    "addr:street":"Rue Franquet",
    "iso:country":"CA",
    "sg:address":"319 Rue Franquet",
    "sg:city":"Sainte-Foy",
    "sg:classifiers":[
        {
            "category":"Manufacturing",
            "subcategory":"Lumber",
            "type":"Manufacturing & Wholesale Goods"
        }
    ],
    "sg:phone":"+1 418 659 2647",
    "sg:postcode":"G1P 4R4",
    "sg:province":"QC",
    "sg:tags":[
        "forester"
    ],
    "wof:name":"Forintek Canada Corp",
    "wof:placetype":"venue"
},
  "geometry": {"coordinates":[-71.31321699999999,46.794147],"type":"Point"}
}