{
  "type": "Feature",
  "properties": {
    "addr:full":"9509 41 Ave NW Edmonton AB T6E 5X7",
    "addr:housenumber":"9509",
    "addr:postcode":"t6e 5x7",
    "addr:street":"41 Ave Nw",
    "iso:country":"CA",
    "sg:address":"9509 41 Ave NW",
    "sg:city":"Edmonton",
    "sg:classifiers":[
        {
            "category":"Wholesale",
            "subcategory":"Machinery & Supplies",
            "type":"Manufacturing & Wholesale Goods"
        }
    ],
    "sg:phone":"+1 780 436 7730",
    "sg:postcode":"T6E 5X7",
    "sg:province":"AB",
    "sg:tags":[
        "equipment",
        "oil",
        "well"
    ],
    "wof:name":"Carreau Oilfield Specialties",
    "wof:placetype":"venue"
},
  "geometry": {"coordinates":[-113.47586099999999,53.476246],"type":"Point"}
}