{
  "type": "Feature",
  "properties": {
    "iso:country":"CA",
    "sg:address":"9509 41 Ave NW",
    "sg:city":"Edmonton",
    "sg:classifiers":[
        {
            "category":"Wholesale",
            "subcategory":"Machinery & Supplies",
            "type":"Manufacturing & Wholesale Goods"
        }
    ],
    "sg:phone":"+1 780 436 7730",
    "sg:postcode":"T6E 5X7",
    "sg:province":"AB",
    "sg:tags":[
        "equipment",
        "oil",
        "well"
    ],
    "wof:name":"Carreau Oilfield Specialties",
    "wof:placetype":"venue"
},
  "geometry": {"coordinates":[-113.475861,53.476246],"type":"Point"}
}