{
  "type": "Feature",
  "properties": {
    "addr:full":"1261 Ch Des Anglais Lachenaie QC J6X 4G4",
    "addr:housenumber":"1261",
    "addr:postcode":"j6x 4g4",
    "addr:street":"Ch Des Anglais",
    "iso:country":"CA",
    "sg:address":"1261 Ch Des Anglais",
    "sg:city":"Lachenaie",
    "sg:classifiers":[
        {
            "category":"Building & Trades",
            "subcategory":"Construction",
            "type":"Services"
        }
    ],
    "sg:phone":"+1 450 492 1881",
    "sg:postcode":"J6X 4G4",
    "sg:province":"QC",
    "sg:tags":[
        "designer",
        "dealer",
        "pool",
        "swimming"
    ],
    "wof:name":"Service DE Piscines Rive-Nord",
    "wof:placetype":"venue"
},
  "geometry": {"coordinates":[-73.65698999999999,45.719543],"type":"Point"}
}