{
  "type": "Feature",
  "properties": {
    "addr:full":"2353 Rue Girouard O Saint-Hyacinthe QC J2S 3A9",
    "addr:housenumber":"2353",
    "addr:postcode":"j2s 3a9",
    "addr:street":"Rue Girouard O",
    "iso:country":"CA",
    "sg:address":"2353 Rue Girouard O",
    "sg:city":"Saint-Hyacinthe",
    "sg:classifiers":[
        {
            "category":"Insurance",
            "subcategory":"Insurance Agent",
            "type":"Services"
        }
    ],
    "sg:phone":"+1 450 773 2753",
    "sg:postcode":"J2S 3A9",
    "sg:province":"QC",
    "wof:name":"Assurance-Vie Raynald Therrien",
    "wof:placetype":"venue"
},
  "geometry": {"coordinates":[-72.9511566162,45.6218452454],"type":"Point"}
}