{
  "type": "Feature",
  "properties": {
    "iso:country":"CA",
    "sg:address":"7A Rte 138 E",
    "sg:city":"Forestville",
    "sg:classifiers":[
        {
            "category":"Home & Garden",
            "subcategory":"Furniture",
            "type":"Retail Goods"
        }
    ],
    "sg:phone":"+1 418 587 2268",
    "sg:postcode":"G0T 1E0",
    "sg:province":"QC",
    "sg:tags":[
        "appliance"
    ],
    "wof:name":"Gagnon Freres",
    "wof:placetype":"venue"
},
  "geometry": {"coordinates":[-69.08734893800001,48.7406845093],"type":"Point"}
}