{
  "type": "Feature",
  "properties": {
    "addr:full":"115 Rue DE LA Fabrique Dijon QC G0R 1L0",
    "addr:housenumber":"115",
    "addr:postcode":"g0r 1l0",
    "addr:street":"Rue De La Fabrique",
    "iso:country":"CA",
    "sg:address":"115 Rue DE LA Fabrique",
    "sg:city":"Dijon",
    "sg:classifiers":[
        {
            "category":"Education",
            "subcategory":"Library",
            "type":"Public Place"
        }
    ],
    "sg:phone":"+1 418 636 2776",
    "sg:postcode":"G0R 1L0",
    "sg:province":"QC",
    "wof:name":"St-Luc Bibliotheque",
    "wof:placetype":"venue"
},
  "geometry": {"coordinates":[-70.482185,46.50853],"type":"Point"}
}