{
  "type": "Feature",
  "properties": {
    "iso:country":"CA",
    "sg:city":"New Westminster",
    "sg:classifiers":[
        {
            "category":"Health Services",
            "subcategory":"Doctor",
            "type":"Services"
        }
    ],
    "sg:phone":"+1 604 521 8522",
    "sg:postcode":"V3L 3C2",
    "sg:province":"BC",
    "sg:tags":[
        "physician",
        "surgeon"
    ],
    "wof:name":"John Cp Yap Inc",
    "wof:placetype":"venue"
},
  "geometry": {"coordinates":[-122.920891,49.213367],"type":"Point"}
}