{
  "type": "Feature",
  "properties": {
    "addr:full":"225 138 Rte Saint-Augustin-DE-Desmaures QC G3A 1W7",
    "addr:housenumber":"225 138",
    "addr:postcode":"g3a 1w7",
    "addr:street":"Rte Saint-Augustin-De-Desmaures",
    "iso:country":"CA",
    "sg:address":"225 138 Rte",
    "sg:city":"Saint-Augustin-DE-Desmaures",
    "sg:classifiers":[
        {
            "category":"Restaurant",
            "type":"Food & Drink"
        }
    ],
    "sg:phone":"+1 418 878 2663",
    "sg:postcode":"G3A 1W7",
    "sg:province":"QC",
    "wof:name":"Casse-Croute Chez Micheline",
    "wof:placetype":"venue"
},
  "geometry": {"coordinates":[-71.384727,46.749176],"type":"Point"}
}