{
  "type": "Feature",
  "properties": {
    "addr:full":"Concord ON L4K 3X8",
    "addr:postcode":"l4k 3x8",
    "iso:country":"CA",
    "sg:city":"Concord",
    "sg:classifiers":[
        {
            "category":"Building & Trades",
            "subcategory":"Cleaning & Sanitation",
            "type":"Services"
        }
    ],
    "sg:phone":"+1 905 660 5630",
    "sg:postcode":"L4K 3X8",
    "sg:province":"ON",
    "sg:tags":[
        "property",
        "maintenance"
    ],
    "wof:name":"Moreau Property Svc",
    "wof:placetype":"venue"
},
  "geometry": {"coordinates":[-79.531158,43.801422],"type":"Point"}
}