{
  "type": "Feature",
  "properties": {
    "addr:full":"2093 Hwy 124 Dunchurch ON P0A 1G0",
    "addr:housenumber":"2093",
    "addr:postcode":"p0a 1g0",
    "addr:street":"Hwy 124",
    "iso:country":"CA",
    "sg:address":"2093 Hwy 124",
    "sg:city":"Dunchurch",
    "sg:classifiers":[
        {
            "category":"Travel",
            "subcategory":"Hotels & Motels",
            "type":"Entertainment"
        }
    ],
    "sg:phone":"+1 705 389 3322",
    "sg:postcode":"P0A 1G0",
    "sg:province":"ON",
    "sg:tags":[
        "resort"
    ],
    "wof:name":"Duck Rock Resort",
    "wof:placetype":"venue"
},
  "geometry": {"coordinates":[-79.8489,45.650181],"type":"Point"}
}