{
  "type": "Feature",
  "properties": {
    "addr:full":"109 Bassett Blvd Whitby ON L1N 7W9",
    "addr:housenumber":"109",
    "addr:postcode":"l1n 7w9",
    "addr:street":"Bassett Blvd",
    "iso:country":"CA",
    "sg:address":"109 Bassett Blvd",
    "sg:city":"Whitby",
    "sg:classifiers":[
        {
            "category":"Retail",
            "subcategory":"Repair Shop",
            "type":"Services"
        }
    ],
    "sg:phone":"+1 905 666 4063",
    "sg:postcode":"L1N 7W9",
    "sg:province":"ON",
    "sg:tags":[
        "lock",
        "locksmith"
    ],
    "wof:name":"Kenton Lock & Security",
    "wof:placetype":"venue"
},
  "geometry": {"coordinates":[-78.93473052980001,43.899471283],"type":"Point"}
}