{
  "type": "Feature",
  "properties": {
    "addr:full":"Lock 34 Fenelon Falls ON K0M 1N0",
    "addr:postcode":"k0m 1n0",
    "iso:country":"CA",
    "sg:address":"Lock 34",
    "sg:city":"Fenelon Falls",
    "sg:classifiers":[
        {
            "category":"Government",
            "subcategory":"Office",
            "type":"Public Place"
        }
    ],
    "sg:phone":"+1 705 887 3001",
    "sg:postcode":"K0M 1N0",
    "sg:province":"ON",
    "sg:tags":[
        "provincial",
        "parks"
    ],
    "wof:name":"Canadian Parks Svc",
    "wof:placetype":"venue"
},
  "geometry": {"coordinates":[-78.73584700000001,44.537579],"type":"Point"}
}