{
  "type": "Feature",
  "properties": {
    "iso:country":"CA",
    "sg:address":"932 Norway Rd",
    "sg:city":"Canora",
    "sg:classifiers":[
        {
            "category":"Shopping",
            "subcategory":"Discount & Variety Stores",
            "type":"Retail Goods"
        }
    ],
    "sg:phone":"+1 306 563 2084",
    "sg:postcode":"S0A 0L0",
    "sg:province":"SK",
    "sg:tags":[
        "novelty"
    ],
    "wof:name":"Canora Bargain Store",
    "wof:placetype":"venue"
},
  "geometry": {"coordinates":[-102.432434,51.635456],"type":"Point"}
}