{
  "type": "Feature",
  "properties": {
    "addr:full":"6722 Snow Goose Lanes Mississauga ON L5N 5J1",
    "addr:housenumber":"6722",
    "addr:postcode":"l5n 5j1",
    "addr:street":"Snow Goose Lanes",
    "iso:country":"CA",
    "sg:address":"6722 Snow Goose Lanes",
    "sg:city":"Mississauga",
    "sg:classifiers":[
        {
            "category":"Professional",
            "subcategory":"Management & Consulting",
            "type":"Services"
        }
    ],
    "sg:phone":"+1 905 824 3104",
    "sg:postcode":"L5N 5J1",
    "sg:province":"ON",
    "sg:tags":[
        "consultant",
        "business"
    ],
    "wof:name":"My Leadership Corp",
    "wof:placetype":"venue"
},
  "geometry": {"coordinates":[-79.7707290649,43.5751647949],"type":"Point"}
}