{
  "type": "Feature",
  "properties": {
    "addr:full":"Mississauga ON L4Z 3K8",
    "addr:postcode":"l4z 3k8",
    "iso:country":"CA",
    "sg:city":"Mississauga",
    "sg:classifiers":[
        {
            "category":"Restaurant",
            "type":"Food & Drink"
        }
    ],
    "sg:phone":"+1 905 502 8583",
    "sg:postcode":"L4Z 3K8",
    "sg:province":"ON",
    "wof:name":"Bombay Chopsticks",
    "wof:placetype":"venue"
},
  "geometry": {"coordinates":[-79.662361,43.615292],"type":"Point"}
}