{
  "type": "Feature",
  "properties": {
    "addr:full":"4579 Chatterton Way Victoria BC V8X 4Y7",
    "addr:housenumber":"4579",
    "addr:postcode":"v8x 4y7",
    "addr:street":"Chatterton Way",
    "iso:country":"CA",
    "sg:address":"4579 Chatterton Way",
    "sg:city":"Victoria",
    "sg:classifiers":[
        {
            "category":"Social Services",
            "type":"Services"
        }
    ],
    "sg:phone":"+1 250 658 3270",
    "sg:postcode":"V8X 4Y7",
    "sg:province":"BC",
    "sg:tags":[
        "care",
        "center",
        "day"
    ],
    "wof:name":"Veterans Health Ctr",
    "wof:placetype":"venue"
},
  "geometry": {"coordinates":[-123.36451700000001,48.428314],"type":"Point"}
}