{
  "type": "Feature",
  "properties": {
    "addr:full":"Huberdeau QC J0T 1G0",
    "addr:postcode":"j0t 1g0",
    "iso:country":"CA",
    "sg:city":"Huberdeau",
    "sg:classifiers":[
        {
            "category":"Utilities",
            "subcategory":"Fuel Oil & Lpg",
            "type":"Services"
        }
    ],
    "sg:phone":"+1 819 687 8331",
    "sg:postcode":"J0T 1G0",
    "sg:province":"QC",
    "wof:name":"Provost, Steve",
    "wof:placetype":"venue"
},
  "geometry": {"coordinates":[-74.62797500000001,45.978897],"type":"Point"}
}