{
  "type": "Feature",
  "properties": {
    "addr:full":"122 Main St E Listowel ON N4W 2B6",
    "addr:housenumber":"122",
    "addr:postcode":"n4w 2b6",
    "addr:street":"Main St E",
    "iso:country":"CA",
    "sg:address":"122 Main St E",
    "sg:city":"Listowel",
    "sg:classifiers":[
        {
            "category":"Home & Garden",
            "subcategory":"Carpets & Floor Coverings",
            "type":"Retail Goods"
        }
    ],
    "sg:phone":"+1 519 291 4440",
    "sg:postcode":"N4W 2B6",
    "sg:province":"ON",
    "sg:tags":[
        "interior",
        "consultant",
        "material",
        "design",
        "decorator"
    ],
    "wof:name":"Tenpas Decor Ctr Ltd",
    "wof:placetype":"venue"
},
  "geometry": {"coordinates":[-80.95277404789999,43.7312507629],"type":"Point"}
}