{
  "type": "Feature",
  "properties": {
    "iso:country":"CA",
    "sg:address":"1233 Monashee Crt",
    "sg:city":"Kamloops",
    "sg:classifiers":[
        {
            "category":"Health Services",
            "subcategory":"Health Practitioner",
            "type":"Services"
        }
    ],
    "sg:phone":"+1 250 318 3257",
    "sg:postcode":"V2C 6B4",
    "sg:province":"BC",
    "sg:tags":[
        "acupuncture"
    ],
    "wof:name":"Interior Acupuncture Ctr",
    "wof:placetype":"venue"
},
  "geometry": {"coordinates":[-120.341430664,50.6660766602],"type":"Point"}
}