{
  "type": "Feature",
  "properties": {
    "addr:full":"420 Balmoral Dr Brampton ON L6T 1V9",
    "addr:housenumber":"420",
    "addr:postcode":"l6t 1v9",
    "addr:street":"Balmoral Dr",
    "iso:country":"CA",
    "sg:address":"420 Balmoral Dr",
    "sg:city":"Brampton",
    "sg:classifiers":[
        {
            "category":"Organizations",
            "subcategory":"Religious Organization",
            "type":"Services"
        }
    ],
    "sg:phone":"+1 905 792 3269",
    "sg:postcode":"L6T 1V9",
    "sg:province":"ON",
    "sg:tags":[
        "church"
    ],
    "wof:name":"Emmanuel United Church",
    "wof:placetype":"venue"
},
  "geometry": {"coordinates":[-79.708382,43.713295],"type":"Point"}
}