{
  "type": "Feature",
  "properties": {
    "iso:country":"CA",
    "sg:address":"9100 Sunset Rd",
    "sg:city":"Vernon",
    "sg:classifiers":[
        {
            "category":"Building & Trades",
            "subcategory":"Construction",
            "type":"Services"
        }
    ],
    "sg:phone":"+1 250 542 8337",
    "sg:postcode":"V1H 1K4",
    "sg:province":"BC",
    "sg:tags":[
        "contractor",
        "general"
    ],
    "wof:name":"Precision Construction",
    "wof:placetype":"venue"
},
  "geometry": {"coordinates":[-119.387550354,50.2129402161],"type":"Point"}
}