{
  "type": "Feature",
  "properties": {
    "addr:full":"244 Victoria St Toronto ON M5B 1V8",
    "addr:housenumber":"244",
    "addr:postcode":"m5b 1v8",
    "addr:street":"Victoria St",
    "iso:country":"CA",
    "sg:address":"244 Victoria St",
    "sg:city":"Toronto",
    "sg:classifiers":[
        {
            "category":"Arts & Performance",
            "subcategory":"Theater",
            "type":"Entertainment"
        }
    ],
    "sg:phone":"+1 416 872 1212",
    "sg:postcode":"M5B 1V8",
    "sg:province":"ON",
    "wof:name":"Canon Theatre",
    "wof:placetype":"venue"
},
  "geometry": {"coordinates":[-79.37924957280001,43.6550483704],"type":"Point"}
}