{
  "type": "Feature",
  "properties": {
    "iso:country":"CA",
    "sg:address":"43 Wicks Dr",
    "sg:city":"Ajax",
    "sg:classifiers":[
        {
            "category":"Professional",
            "type":"Services"
        }
    ],
    "sg:phone":"+1 905 686 2180",
    "sg:postcode":"L1Z 1C5",
    "sg:province":"ON",
    "sg:tags":[
        "food",
        "establishment",
        "product",
        "health"
    ],
    "wof:name":"Natural Home Health Products",
    "wof:placetype":"venue"
},
  "geometry": {"coordinates":[-79.0097198486,43.8622436523],"type":"Point"}
}