{
  "type": "Feature",
  "properties": {
    "iso:country":"CA",
    "sg:city":"Montreal",
    "sg:classifiers":[
        {
            "category":"Professional",
            "subcategory":"Accounting & Tax Preparation",
            "type":"Services"
        }
    ],
    "sg:phone":"+1 514 489 0075",
    "sg:postcode":"H4A 1S9",
    "sg:province":"QC",
    "sg:tags":[
        "accountant"
    ],
    "wof:name":"Fischer Roche",
    "wof:placetype":"venue"
},
  "geometry": {"coordinates":[-73.55423,45.566135],"type":"Point"}
}