{
  "type": "Feature",
  "properties": {
    "addr:full":"North York ON M3B 3H9",
    "addr:postcode":"m3b 3h9",
    "iso:country":"CA",
    "sg:city":"North York",
    "sg:classifiers":[
        {
            "category":"Professional",
            "subcategory":"Management & Consulting",
            "type":"Services"
        }
    ],
    "sg:phone":"+1 416 686 4434",
    "sg:postcode":"M3B 3H9",
    "sg:province":"ON",
    "sg:tags":[
        "construction"
    ],
    "wof:name":"Dpi Construction Mgmt",
    "wof:placetype":"venue"
},
  "geometry": {"coordinates":[-79.350098,43.76128],"type":"Point"}
}