{
  "type": "Feature",
  "properties": {
    "addr:full":"3632 Hart Hwy Prince George BC V2K 2Z3",
    "addr:housenumber":"3632",
    "addr:postcode":"v2k 2z3",
    "addr:street":"Hart Hwy",
    "iso:country":"CA",
    "sg:address":"3632 Hart Hwy",
    "sg:city":"Prince George",
    "sg:classifiers":[
        {
            "category":"Freight",
            "type":"Transportation"
        }
    ],
    "sg:phone":"+1 250 962 5600",
    "sg:postcode":"V2K 2Z3",
    "sg:province":"BC",
    "sg:tags":[
        "commercial",
        "storage"
    ],
    "wof:name":"A-1 Self Storage",
    "wof:placetype":"venue"
},
  "geometry": {"coordinates":[-122.78647599999999,53.989578],"type":"Point"}
}