{
  "type": "Feature",
  "properties": {
    "iso:country":"CA",
    "sg:city":"Princeton",
    "sg:classifiers":[
        {
            "category":"Recreation",
            "type":"Entertainment"
        }
    ],
    "sg:phone":"+1 250 295 6535",
    "sg:postcode":"V0X 1W0",
    "sg:province":"BC",
    "sg:tags":[
        "government",
        "swimming"
    ],
    "wof:name":"Princeton Centennial Pool",
    "wof:placetype":"venue"
},
  "geometry": {"coordinates":[-120.505897522,49.4586753845],"type":"Point"}
}