{
  "type": "Feature",
  "properties": {
    "addr:full":"3111 Coldstream Ave Vernon BC V1T 1X8",
    "addr:housenumber":"3111",
    "addr:postcode":"v1t 1x8",
    "addr:street":"Coldstream Ave",
    "iso:country":"CA",
    "sg:address":"3111 Coldstream Ave",
    "sg:city":"Vernon",
    "sg:classifiers":[
        {
            "category":"Cinema",
            "subcategory":"Movie Rental",
            "type":"Entertainment"
        }
    ],
    "sg:phone":"+1 250 542 5127",
    "sg:postcode":"V1T 1X8",
    "sg:province":"BC",
    "sg:tags":[
        "leasing",
        "video",
        "disc",
        "tape"
    ],
    "wof:name":"Libra Video & Love Boutique",
    "wof:placetype":"venue"
},
  "geometry": {"coordinates":[-119.27298,50.262398],"type":"Point"}
}