{
  "type": "Feature",
  "properties": {
    "addr:full":"2275 Elgin Ave Port Coquitlam BC V3C 2B3",
    "addr:housenumber":"2275",
    "addr:postcode":"v3c 2b3",
    "addr:street":"Elgin Ave",
    "iso:country":"CA",
    "sg:address":"2275 Elgin Ave",
    "sg:city":"Port Coquitlam",
    "sg:classifiers":[
        {
            "category":"Shopping",
            "subcategory":"Used Merchandise",
            "type":"Retail Goods"
        }
    ],
    "sg:phone":"+1 604 942 0505",
    "sg:postcode":"V3C 2B3",
    "sg:province":"BC",
    "sg:tags":[
        "shop",
        "thrift"
    ],
    "wof:name":"Salvation Army",
    "wof:placetype":"venue"
},
  "geometry": {"coordinates":[-122.779418945,49.2633895874],"type":"Point"}
}