{
  "type": "Feature",
  "properties": {
    "addr:full":"Queenston ON L0S 1L0",
    "addr:postcode":"l0s 1l0",
    "iso:country":"CA",
    "sg:city":"Queenston",
    "sg:classifiers":[
        {
            "category":"Freight",
            "type":"Transportation"
        }
    ],
    "sg:phone":"+1 905 262 4214",
    "sg:postcode":"L0S 1L0",
    "sg:province":"ON",
    "sg:tags":[
        "broker",
        "customs"
    ],
    "wof:name":"Livingston International Inc",
    "wof:placetype":"venue"
},
  "geometry": {"coordinates":[-79.17398799999999,43.164246],"type":"Point"}
}