{
  "type": "Feature",
  "properties": {
    "iso:country":"CA",
    "sg:address":"762 Crescent Ave",
    "sg:city":"Picture Butte",
    "sg:classifiers":[
        {
            "category":"Organizations",
            "subcategory":"Religious Organization",
            "type":"Services"
        }
    ],
    "sg:phone":"+1 403 732 4433",
    "sg:postcode":"T0K 1V0",
    "sg:province":"AB",
    "sg:tags":[
        "church"
    ],
    "wof:name":"St Catherine's Rc Church",
    "wof:placetype":"venue"
},
  "geometry": {"coordinates":[-112.787643,49.875397],"type":"Point"}
}