{
  "type": "Feature",
  "properties": {
    "addr:full":"238 Rue Dupernay Boucherville QC J4B 1G6",
    "addr:housenumber":"238",
    "addr:postcode":"j4b 1g6",
    "addr:street":"Rue Dupernay",
    "iso:country":"CA",
    "sg:address":"238 Rue Dupernay",
    "sg:city":"Boucherville",
    "sg:classifiers":[
        {
            "category":"Social Services",
            "subcategory":"Child Care",
            "type":"Services"
        }
    ],
    "sg:phone":"+1 450 655 1357",
    "sg:postcode":"J4B 1G6",
    "sg:province":"QC",
    "wof:name":"Cpe Ses Amis",
    "wof:placetype":"venue"
},
  "geometry": {"coordinates":[-73.448921,45.584976],"type":"Point"}
}