{
  "type": "Feature",
  "properties": {
    "addr:full":"3035 Rue Jarry E Montreal QC H1Z 2C2",
    "addr:housenumber":"3035",
    "addr:postcode":"h1z 2c2",
    "addr:street":"Rue Jarry E",
    "iso:country":"CA",
    "sg:address":"3035 Rue Jarry E",
    "sg:city":"Montreal",
    "sg:classifiers":[
        {
            "category":"Freight",
            "type":"Transportation"
        }
    ],
    "sg:phone":"+1 514 593 8555",
    "sg:postcode":"H1Z 2C2",
    "sg:province":"QC",
    "sg:tags":[
        "trucking"
    ],
    "wof:name":"Col Sel Transit Inc",
    "wof:placetype":"venue"
},
  "geometry": {"coordinates":[-73.61149597169999,45.5619010925],"type":"Point"}
}