{
  "type": "Feature",
  "properties": {
    "addr:full":"725 Ottawa St S Kitchener ON N2E 3H5",
    "addr:housenumber":"725",
    "addr:postcode":"n2e 3h5",
    "addr:street":"Ottawa St S",
    "iso:country":"CA",
    "sg:address":"725 Ottawa St S",
    "sg:city":"Kitchener",
    "sg:classifiers":[
        {
            "category":"Cinema",
            "subcategory":"Movie Rental",
            "type":"Entertainment"
        }
    ],
    "sg:phone":"+1 519 570 2559",
    "sg:postcode":"N2E 3H5",
    "sg:province":"ON",
    "sg:tags":[
        "leasing",
        "video",
        "disc",
        "tape"
    ],
    "wof:name":"Videoscene",
    "wof:placetype":"venue"
},
  "geometry": {"coordinates":[-80.483749,43.425041],"type":"Point"}
}