{
  "type": "Feature",
  "properties": {
    "addr:full":"362 Carmody St Pembroke ON K8A 4G2",
    "addr:housenumber":"362",
    "addr:postcode":"k8a 4g2",
    "addr:street":"Carmody St",
    "iso:country":"CA",
    "sg:address":"362 Carmody St",
    "sg:city":"Pembroke",
    "sg:classifiers":[
        {
            "category":"Education",
            "subcategory":"School",
            "type":"Public Place"
        }
    ],
    "sg:phone":"+1 613 735 5496",
    "sg:postcode":"K8A 4G2",
    "sg:province":"ON",
    "wof:name":"Bishop Smith Catholic High",
    "wof:placetype":"venue"
},
  "geometry": {"coordinates":[-77.1192245483,45.8178749084],"type":"Point"}
}