{
  "type": "Feature",
  "properties": {
    "iso:country":"CA",
    "sg:city":"Windsor",
    "sg:classifiers":[
        {
            "category":"Wholesale",
            "subcategory":"Machinery & Supplies",
            "type":"Manufacturing & Wholesale Goods"
        }
    ],
    "sg:phone":"+1 519 972 1253",
    "sg:postcode":"N9A 6J3",
    "sg:province":"ON",
    "sg:tags":[
        "equipment",
        "hydraulic"
    ],
    "wof:name":"Essex County Hydraulics Inc",
    "wof:placetype":"venue"
},
  "geometry": {"coordinates":[-82.9659500122,42.263710022],"type":"Point"}
}