{
  "type": "Feature",
  "properties": {
    "addr:full":"658 Leitches Creek Rd Leitches Creek NS B2A 3Z7",
    "addr:housenumber":"658",
    "addr:postcode":"b2a 3z7",
    "addr:street":"Leitches Creek Rd",
    "iso:country":"CA",
    "sg:address":"658 Leitches Creek Rd",
    "sg:city":"Leitches Creek",
    "sg:classifiers":[
        {
            "category":"Retail",
            "subcategory":"Repair Shop",
            "type":"Services"
        }
    ],
    "sg:phone":"+1 902 794 2642",
    "sg:postcode":"B2A 3Z7",
    "sg:province":"NS",
    "sg:tags":[
        "repairing",
        "equipment",
        "electric"
    ],
    "wof:name":"Bartlett's Industrial Rewindng",
    "wof:placetype":"venue"
},
  "geometry": {"coordinates":[-60.359867,46.147259],"type":"Point"}
}