{
  "type": "Feature",
  "properties": {
    "iso:country":"CA",
    "sg:address":"36 Pine Ave W",
    "sg:city":"Brooks",
    "sg:classifiers":[
        {
            "category":"Building & Trades",
            "subcategory":"Electrical",
            "type":"Services"
        }
    ],
    "sg:phone":"+1 403 362 8656",
    "sg:postcode":"T1R 0A1",
    "sg:province":"AB",
    "sg:tags":[
        "electric",
        "contractor"
    ],
    "wof:name":"Boulton Electric",
    "wof:placetype":"venue"
},
  "geometry": {"coordinates":[-111.907158,50.56263],"type":"Point"}
}