{
  "type": "Feature",
  "properties": {
    "addr:full":"250 2 St E Drumheller AB T0J 0Y4",
    "addr:housenumber":"250 2",
    "addr:postcode":"t0j 0y4",
    "addr:street":"St E",
    "iso:country":"CA",
    "sg:address":"250 2 St E",
    "sg:city":"Drumheller",
    "sg:classifiers":[
        {
            "category":"Social Services",
            "subcategory":"Adult Care",
            "type":"Services"
        }
    ],
    "sg:phone":"+1 403 823 6354",
    "sg:postcode":"T0J 0Y4",
    "sg:province":"AB",
    "sg:tags":[
        "senior",
        "housing",
        "citizen"
    ],
    "wof:name":"Maple Ridge Manors",
    "wof:placetype":"venue"
},
  "geometry": {"coordinates":[-112.704620361,51.4646530151],"type":"Point"}
}