{
  "type": "Feature",
  "properties": {
    "addr:full":"159 1E Rue S St-Nazaire-Du-Lac-St-Jean QC G0W 2V0",
    "addr:housenumber":"159",
    "addr:postcode":"g0w 2v0",
    "addr:street":"1E Rue S St-Nazaire-Du-Lac-St-Jean",
    "iso:country":"CA",
    "sg:address":"159 1E Rue S",
    "sg:city":"St-Nazaire-Du-Lac-St-Jean",
    "sg:classifiers":[
        {
            "category":"Organizations",
            "subcategory":"Religious Organization",
            "type":"Services"
        }
    ],
    "sg:phone":"+1 418 662 5525",
    "sg:postcode":"G0W 2V0",
    "sg:province":"QC",
    "sg:tags":[
        "home",
        "retirement",
        "community",
        "retreat",
        "house"
    ],
    "wof:name":"Oasis Des Batisseurs",
    "wof:placetype":"venue"
},
  "geometry": {"coordinates":[-71.486931,48.575367],"type":"Point"}
}