{
  "type": "Feature",
  "properties": {
    "addr:full":"8 Pond St Charlottetown PE C1A 2P2",
    "addr:housenumber":"8",
    "addr:postcode":"c1a 2p2",
    "addr:street":"Pond St",
    "iso:country":"CA",
    "sg:address":"8 Pond St",
    "sg:city":"Charlottetown",
    "sg:classifiers":[
        {
            "category":"Social Services",
            "subcategory":"Child Care",
            "type":"Services"
        }
    ],
    "sg:phone":"+1 902 892 4352",
    "sg:postcode":"C1A 2P2",
    "sg:province":"PE",
    "wof:name":"Kiddies Kollege Korner",
    "wof:placetype":"venue"
},
  "geometry": {"coordinates":[-63.1379737854,46.2408752441],"type":"Point"}
}