{
  "type": "Feature",
  "properties": {
    "addr:full":"Langley BC V3A 4C4",
    "addr:postcode":"v3a 4c4",
    "iso:country":"CA",
    "sg:city":"Langley",
    "sg:classifiers":[
        {
            "category":"Restaurant",
            "type":"Food & Drink"
        }
    ],
    "sg:phone":"+1 604 533 4131",
    "sg:postcode":"V3A 4C4",
    "sg:province":"BC",
    "wof:name":"Okinawa Garden",
    "wof:placetype":"venue"
},
  "geometry": {"coordinates":[-122.65004,49.106045],"type":"Point"}
}