{
  "type": "Feature",
  "properties": {
    "addr:full":"Edmonton AB T5K 0Z4",
    "addr:postcode":"t5k 0z4",
    "iso:country":"CA",
    "sg:city":"Edmonton",
    "sg:classifiers":[
        {
            "category":"Real Estate",
            "subcategory":"Real Estate Operator",
            "type":"Services"
        }
    ],
    "sg:phone":"+1 780 424 6612",
    "sg:postcode":"T5K 0Z4",
    "sg:province":"AB",
    "sg:tags":[
        "apartment"
    ],
    "wof:name":"Dunedin House Apartments",
    "wof:placetype":"venue"
},
  "geometry": {"coordinates":[-113.499481,53.53754],"type":"Point"}
}