{
  "type": "Feature",
  "properties": {
    "addr:full":"155 E 6th Ave Regina SK S4N 5A6",
    "addr:housenumber":"155",
    "addr:postcode":"s4n 5a6",
    "addr:street":"E 6Th Ave",
    "iso:country":"CA",
    "sg:address":"155 E 6th Ave",
    "sg:city":"Regina",
    "sg:classifiers":[
        {
            "category":"Wholesale",
            "subcategory":"Construction Materials",
            "type":"Manufacturing & Wholesale Goods"
        }
    ],
    "sg:phone":"+1 306 352 7377",
    "sg:postcode":"S4N 5A6",
    "sg:province":"SK",
    "sg:tags":[
        "building",
        "roofing"
    ],
    "wof:name":"Wayne Building Products Ltd",
    "wof:placetype":"venue"
},
  "geometry": {"coordinates":[-104.581276,50.459694],"type":"Point"}
}