{
  "type": "Feature",
  "properties": {
    "addr:full":"801 Wheeler St Whitehorse YT Y1A 2P8",
    "addr:housenumber":"801",
    "addr:postcode":"y1a 2p8",
    "addr:street":"Wheeler St",
    "iso:country":"CA",
    "sg:address":"801 Wheeler St",
    "sg:city":"Whitehorse",
    "sg:classifiers":[
        {
            "category":"Organizations",
            "subcategory":"Religious Organization",
            "type":"Services"
        }
    ],
    "sg:phone":"+1 867 668 2003",
    "sg:postcode":"Y1A 2P8",
    "sg:province":"YT",
    "sg:tags":[
        "church"
    ],
    "wof:name":"Grace Community Church",
    "wof:placetype":"venue"
},
  "geometry": {"coordinates":[-135.06820678700001,60.7227134705],"type":"Point"}
}