{
  "type": "Feature",
  "properties": {
    "addr:full":"Sawchuk St Mundare AB T0B 3H0",
    "addr:postcode":"t0b 3h0",
    "addr:street":"Sawchuk St",
    "iso:country":"CA",
    "sg:address":"Sawchuk St",
    "sg:city":"Mundare",
    "sg:classifiers":[
        {
            "category":"Health Services",
            "subcategory":"Hospital",
            "type":"Services"
        }
    ],
    "sg:phone":"+1 780 764 3730",
    "sg:postcode":"T0B 3H0",
    "sg:province":"AB",
    "wof:name":"Mary Immaculate Hospital",
    "wof:placetype":"venue"
},
  "geometry": {"coordinates":[-112.336472,53.595341],"type":"Point"}
}