{
  "type": "Feature",
  "properties": {
    "addr:full":"Pointe-Claire QC H9S 4L4",
    "addr:postcode":"h9s 4l4",
    "iso:country":"CA",
    "sg:city":"Pointe-Claire",
    "sg:classifiers":[
        {
            "category":"Shopping",
            "subcategory":"Clothing, Apparel, & Fashions",
            "type":"Retail Goods"
        }
    ],
    "sg:phone":"+1 514 697 8264",
    "sg:postcode":"H9S 4L4",
    "sg:province":"QC",
    "wof:name":"Boutique Looking Glass",
    "wof:placetype":"venue"
},
  "geometry": {"coordinates":[-73.82620199999999,45.429012],"type":"Point"}
}