{
  "type": "Feature",
  "properties": {
    "iso:country":"CA",
    "sg:address":"195 Rue Principale",
    "sg:city":"Les Coteaux",
    "sg:classifiers":[
        {
            "category":"Education",
            "subcategory":"Library",
            "type":"Public Place"
        }
    ],
    "sg:phone":"+1 450 267 1414",
    "sg:postcode":"J7X 1A1",
    "sg:province":"QC",
    "wof:name":"Bibliotheque Les Coteaux",
    "wof:placetype":"venue"
},
  "geometry": {"coordinates":[-74.2090301514,45.2568016052],"type":"Point"}
}