{
  "type": "Feature",
  "properties": {
    "iso:country":"CA",
    "sg:address":"96 Harbord St",
    "sg:city":"Toronto",
    "sg:classifiers":[
        {
            "category":"Restaurant",
            "type":"Food & Drink"
        }
    ],
    "sg:phone":"+1 416 964 6414",
    "sg:postcode":"M5S 1G6",
    "sg:province":"ON",
    "sg:tags":[
        "cafe"
    ],
    "wof:name":"Tik Talk Cafe",
    "wof:placetype":"venue"
},
  "geometry": {"coordinates":[-79.403259,43.662895],"type":"Point"}
}