{
  "type": "Feature",
  "properties": {
    "addr:full":"373 Cedarvale Ave East York ON M4C 4K7",
    "addr:housenumber":"373",
    "addr:postcode":"m4c 4k7",
    "addr:street":"Cedarvale Ave",
    "iso:country":"CA",
    "sg:address":"373 Cedarvale Ave",
    "sg:city":"East York",
    "sg:classifiers":[
        {
            "category":"Social Services",
            "type":"Services"
        }
    ],
    "sg:phone":"+1 416 396 2842",
    "sg:postcode":"M4C 4K7",
    "sg:province":"ON",
    "sg:tags":[
        "senior",
        "government",
        "citizen"
    ],
    "wof:name":"East York Stan Wadlow Snr Ctr",
    "wof:placetype":"venue"
},
  "geometry": {"coordinates":[-79.31568908689999,43.6973876953],"type":"Point"}
}