{
  "type": "Feature",
  "properties": {
    "addr:full":"149 Rue Champlain Saint-Jean-Sur-Richelieu QC J3B 6V5",
    "addr:housenumber":"149",
    "addr:postcode":"j3b 6v5",
    "addr:street":"Rue Champlain",
    "iso:country":"CA",
    "sg:address":"149 Rue Champlain",
    "sg:city":"Saint-Jean-Sur-Richelieu",
    "sg:classifiers":[
        {
            "category":"Restaurant",
            "type":"Food & Drink"
        }
    ],
    "sg:phone":"+1 450 542 5031",
    "sg:postcode":"J3B 6V5",
    "sg:province":"QC",
    "sg:tags":[
        "cafe"
    ],
    "wof:name":"Cafe Chretien",
    "wof:placetype":"venue"
},
  "geometry": {"coordinates":[-73.251892,45.304783],"type":"Point"}
}