{
  "type": "Feature",
  "properties": {
    "addr:full":"555 Davenport Rd Waterloo ON N2L 6L2",
    "addr:housenumber":"555",
    "addr:postcode":"n2l 6l2",
    "addr:street":"Davenport Rd",
    "iso:country":"CA",
    "sg:address":"555 Davenport Rd",
    "sg:city":"Waterloo",
    "sg:classifiers":[
        {
            "category":"Food & Beverages",
            "subcategory":"Liquor & Beverages",
            "type":"Retail Goods"
        }
    ],
    "sg:phone":"+1 519 883 0887",
    "sg:postcode":"N2L 6L2",
    "sg:province":"ON",
    "sg:tags":[
        "wine"
    ],
    "wof:name":"Wine Rack",
    "wof:placetype":"venue"
},
  "geometry": {"coordinates":[-80.524895,43.49884],"type":"Point"}
}