{
  "type": "Feature",
  "properties": {
    "addr:full":"565 Rue Leclerc Repentigny QC J6A 8C1",
    "addr:housenumber":"565",
    "addr:postcode":"j6a 8c1",
    "addr:street":"Rue Leclerc",
    "iso:country":"CA",
    "sg:address":"565 Rue Leclerc",
    "sg:city":"Repentigny",
    "sg:classifiers":[
        {
            "category":"Manufacturing",
            "subcategory":"Printing",
            "type":"Manufacturing & Wholesale Goods"
        }
    ],
    "sg:phone":"+1 450 585 3967",
    "sg:postcode":"J6A 8C1",
    "sg:province":"QC",
    "sg:tags":[
        "printer"
    ],
    "wof:name":"Imprimerie Rivest Inc",
    "wof:placetype":"venue"
},
  "geometry": {"coordinates":[-73.4476394653,45.7507247925],"type":"Point"}
}