{
  "type": "Feature",
  "properties": {
    "addr:full":"1656Y Y.M.C.A. Rd Gibsons BC V0N 1V6",
    "addr:postcode":"v0n 1v6",
    "addr:street":"Y.M.C.A. Rd",
    "iso:country":"CA",
    "sg:address":"1656Y Y.M.C.A. Rd",
    "sg:city":"Gibsons",
    "sg:classifiers":[
        {
            "category":"Banks & Credit Unions",
            "subcategory":"Bank",
            "type":"Services"
        }
    ],
    "sg:phone":"+1 604 886 6543",
    "sg:postcode":"V0N 1V6",
    "sg:province":"BC",
    "sg:tags":[
        "loan",
        "real estate"
    ],
    "wof:name":"B C Investors Mortgage Exch",
    "wof:placetype":"venue"
},
  "geometry": {"coordinates":[-123.503440857,49.4034538269],"type":"Point"}
}