{
  "type": "Feature",
  "properties": {
    "addr:full":"3240 Ch D'Oka Sainte-Marthe-Sur-Le-Lac QC J0N 1P0",
    "addr:postcode":"3240;j0n 1p0",
    "addr:street":"Ch D'Oka",
    "iso:country":"CA",
    "sg:address":"3240 Ch D'Oka",
    "sg:city":"Sainte-Marthe-Sur-Le-Lac",
    "sg:classifiers":[
        {
            "category":"Personal",
            "type":"Services"
        }
    ],
    "sg:phone":"+1 450 472 6265",
    "sg:postcode":"J0N 1P0",
    "sg:province":"QC",
    "sg:tags":[
        "baby",
        "child",
        "sitter",
        "care"
    ],
    "wof:name":"Garderie Coeur D'Enfant",
    "wof:placetype":"venue"
},
  "geometry": {"coordinates":[-73.99458312989999,45.5016860962],"type":"Point"}
}