{
  "type": "Feature",
  "properties": {
    "addr:full":"10439 69 Ave NW Edmonton AB T6H 2C4",
    "addr:housenumber":"10439",
    "addr:postcode":"t6h 2c4",
    "addr:street":"69 Ave Nw",
    "iso:country":"CA",
    "sg:address":"10439 69 Ave NW",
    "sg:city":"Edmonton",
    "sg:classifiers":[
        {
            "category":"Health Services",
            "subcategory":"Health Practitioner",
            "type":"Services"
        }
    ],
    "sg:phone":"+1 780 437 2792",
    "sg:postcode":"T6H 2C4",
    "sg:province":"AB",
    "sg:tags":[
        "psychologist"
    ],
    "wof:name":"Adas Psych & Counselling Svc",
    "wof:placetype":"venue"
},
  "geometry": {"coordinates":[-113.498856,53.505203],"type":"Point"}
}