{
  "type": "Feature",
  "properties": {
    "addr:full":"26 Kincaid St Brockville ON K6V 4Z9",
    "addr:housenumber":"26",
    "addr:postcode":"k6v 4z9",
    "addr:street":"Kincaid St",
    "iso:country":"CA",
    "sg:address":"26 Kincaid St",
    "sg:city":"Brockville",
    "sg:classifiers":[
        {
            "category":"Shopping",
            "type":"Retail Goods"
        }
    ],
    "sg:phone":"+1 613 345 5949",
    "sg:postcode":"K6V 4Z9",
    "sg:province":"ON",
    "sg:tags":[
        "video",
        "disc",
        "tape",
        "miscellaneous",
        "store"
    ],
    "wof:name":"Sensual Adult Gifts",
    "wof:placetype":"venue"
},
  "geometry": {"coordinates":[-75.686966,44.587296],"type":"Point"}
}