{
  "type": "Feature",
  "properties": {
    "addr:full":"Toronto ON M5J 2P1",
    "addr:postcode":"m5j 2p1",
    "iso:country":"CA",
    "sg:city":"Toronto",
    "sg:classifiers":[
        {
            "category":"Professional",
            "subcategory":"Employment Agencies",
            "type":"Services"
        }
    ],
    "sg:phone":"+1 416 368 1058",
    "sg:postcode":"M5J 2P1",
    "sg:province":"ON",
    "sg:tags":[
        "opportunity"
    ],
    "wof:name":"Kelly Professional Svc",
    "wof:placetype":"venue"
},
  "geometry": {"coordinates":[-79.383682251,43.6457481384],"type":"Point"}
}