{
  "type": "Feature",
  "properties": {
    "addr:full":"3750 St Clair Ave E Scarborough ON M1M 1T9",
    "addr:housenumber":"3750",
    "addr:postcode":"m1m 1t9",
    "addr:street":"St Clair Ave E",
    "iso:country":"CA",
    "sg:address":"3750 St Clair Ave E",
    "sg:city":"Scarborough",
    "sg:classifiers":[
        {
            "category":"Food & Beverages",
            "subcategory":"Bakery",
            "type":"Retail Goods"
        }
    ],
    "sg:phone":"+1 416 261 5070",
    "sg:postcode":"M1M 1T9",
    "sg:province":"ON",
    "sg:tags":[
        "baker"
    ],
    "wof:name":"Fresh Buns & Bread",
    "wof:placetype":"venue"
},
  "geometry": {"coordinates":[-79.2425003052,43.7207717896],"type":"Point"}
}