{
  "type": "Feature",
  "properties": {
    "addr:full":"10655 Rue Clark Montreal QC H3L 2S6",
    "addr:housenumber":"10655",
    "addr:postcode":"h3l 2s6",
    "addr:street":"Rue Clark",
    "iso:country":"CA",
    "sg:address":"10655 Rue Clark",
    "sg:city":"Montreal",
    "sg:classifiers":[
        {
            "category":"Professional",
            "subcategory":"Accounting & Tax Preparation",
            "type":"Services"
        }
    ],
    "sg:phone":"+1 514 333 8592",
    "sg:postcode":"H3L 2S6",
    "sg:province":"QC",
    "sg:tags":[
        "publisher",
        "accountant"
    ],
    "wof:name":"Tango Editions Publications",
    "wof:placetype":"venue"
},
  "geometry": {"coordinates":[-73.67040299999999,45.549267],"type":"Point"}
}