{
  "type": "Feature",
  "properties": {
    "iso:country":"CA",
    "sg:address":"13704 170 St NW",
    "sg:city":"Edmonton",
    "sg:classifiers":[
        {
            "category":"Building & Trades",
            "subcategory":"Landscaping Services",
            "type":"Services"
        }
    ],
    "sg:phone":"+1 780 414 1476",
    "sg:postcode":"T5V 1T2",
    "sg:province":"AB",
    "sg:tags":[
        "center",
        "garden",
        "landscape",
        "contractor"
    ],
    "wof:name":"Best Landscaping Depot Ltd",
    "wof:placetype":"venue"
},
  "geometry": {"coordinates":[-113.615364075,53.5997314453],"type":"Point"}
}