{
  "type": "Feature",
  "properties": {
    "iso:country":"CA",
    "sg:address":"260 Ch Des Patriotes N",
    "sg:city":"Mont-Saint-Hilaire",
    "sg:classifiers":[
        {
            "category":"Organizations",
            "subcategory":"Professional Association",
            "type":"Services"
        }
    ],
    "sg:phone":"+1 450 464 4343",
    "sg:postcode":"J3H 3H4",
    "sg:province":"QC",
    "wof:name":"Scouts Guides Msh",
    "wof:placetype":"venue"
},
  "geometry": {"coordinates":[-73.1947479248,45.570526123],"type":"Point"}
}