{
  "type": "Feature",
  "properties": {
    "addr:full":"Victoria BC V8X 1K7",
    "addr:postcode":"v8x 1k7",
    "iso:country":"CA",
    "sg:city":"Victoria",
    "sg:classifiers":[
        {
            "category":"Personal",
            "subcategory":"Beauty Salon",
            "type":"Services"
        }
    ],
    "sg:phone":"+1 250 479 8815",
    "sg:postcode":"V8X 1K7",
    "sg:province":"BC",
    "wof:name":"Sue's Family Hair Salon",
    "wof:placetype":"venue"
},
  "geometry": {"coordinates":[-123.35891700000001,48.428104],"type":"Point"}
}