{
  "type": "Feature",
  "properties": {
    "iso:country":"CA",
    "sg:address":"2857 St Clair Ave E",
    "sg:city":"East York",
    "sg:classifiers":[
        {
            "category":"Building & Trades",
            "subcategory":"Cleaning & Sanitation",
            "type":"Services"
        }
    ],
    "sg:phone":"+1 416 751 7034",
    "sg:postcode":"M4B 1N4",
    "sg:province":"ON",
    "sg:tags":[
        "janitor"
    ],
    "wof:name":"Caretakers Cleaning Svc Inc",
    "wof:placetype":"venue"
},
  "geometry": {"coordinates":[-79.30373400000001,43.707275],"type":"Point"}
}