{
  "type": "Feature",
  "properties": {
    "addr:full":"2269 Lake Shore Blvd W Etobicoke ON M8V 3X6",
    "addr:housenumber":"2269",
    "addr:postcode":"m8v 3x6",
    "addr:street":"Lake Shore Blvd W",
    "iso:country":"CA",
    "sg:address":"2269 Lake Shore Blvd W",
    "sg:city":"Etobicoke",
    "sg:classifiers":[
        {
            "category":"Professional",
            "subcategory":"Computer Services",
            "type":"Services"
        }
    ],
    "sg:phone":"+1 416 503 9995",
    "sg:postcode":"M8V 3X6",
    "sg:province":"ON",
    "sg:tags":[
        "consultant"
    ],
    "wof:name":"R D Webb & Assoc",
    "wof:placetype":"venue"
},
  "geometry": {"coordinates":[-79.484261,43.620018],"type":"Point"}
}