{
  "type": "Feature",
  "properties": {
    "addr:full":"1457 York St Regina SK S4T 4P8",
    "addr:housenumber":"1457",
    "addr:postcode":"s4t 4p8",
    "addr:street":"York St",
    "iso:country":"CA",
    "sg:address":"1457 York St",
    "sg:city":"Regina",
    "sg:classifiers":[
        {
            "category":"Building & Trades",
            "subcategory":"Construction",
            "type":"Services"
        }
    ],
    "sg:phone":"+1 306 543 9609",
    "sg:postcode":"S4T 4P8",
    "sg:province":"SK",
    "sg:tags":[
        "general",
        "contractor"
    ],
    "wof:name":"Sudimel Construction Ltd",
    "wof:placetype":"venue"
},
  "geometry": {"coordinates":[-104.645073,50.455906],"type":"Point"}
}