{
  "type": "Feature",
  "properties": {
    "addr:full":"148 Boul Cure-Labelle Sainte-Rose QC H7L 2Z7",
    "addr:housenumber":"148",
    "addr:postcode":"h7l 2z7",
    "addr:street":"Boul Cure-Labelle",
    "iso:country":"CA",
    "sg:address":"148 Boul Cure-Labelle",
    "sg:city":"Sainte-Rose",
    "sg:classifiers":[
        {
            "category":"Retail",
            "subcategory":"Auto Repair",
            "type":"Services"
        }
    ],
    "sg:phone":"+1 450 622 4666",
    "sg:postcode":"H7L 2Z7",
    "sg:province":"QC",
    "sg:tags":[
        "repairing",
        "automobile"
    ],
    "wof:name":"Automobiles Metz Inc",
    "wof:placetype":"venue"
},
  "geometry": {"coordinates":[-73.79113769529999,45.6079673767],"type":"Point"}
}