{
  "type": "Feature",
  "properties": {
    "iso:country":"CA",
    "sg:address":"108 Rue Michaud",
    "sg:city":"Chicoutimi",
    "sg:classifiers":[
        {
            "category":"Retail",
            "subcategory":"Auto Repair",
            "type":"Services"
        }
    ],
    "sg:phone":"+1 418 543 5121",
    "sg:postcode":"G7G 2V2",
    "sg:province":"QC",
    "sg:tags":[
        "repairing",
        "automobile"
    ],
    "wof:name":"Garage Body Mecanique",
    "wof:placetype":"venue"
},
  "geometry": {"coordinates":[-71.0608673096,48.4367828369],"type":"Point"}
}