{
  "type": "Feature",
  "properties": {
    "addr:full":"3179 Rue Adam Montreal QC H1W 1X5",
    "addr:housenumber":"3179",
    "addr:postcode":"h1w 1x5",
    "addr:street":"Rue Adam",
    "iso:country":"CA",
    "sg:address":"3179 Rue Adam",
    "sg:city":"Montreal",
    "sg:classifiers":[
        {
            "category":"Retail",
            "subcategory":"Auto Repair",
            "type":"Services"
        }
    ],
    "sg:phone":"+1 514 522 7525",
    "sg:postcode":"H1W 1X5",
    "sg:province":"QC",
    "sg:tags":[
        "repairing",
        "automobile"
    ],
    "wof:name":"Garage Gauthier",
    "wof:placetype":"venue"
},
  "geometry": {"coordinates":[-73.5438156128,45.5395545959],"type":"Point"}
}