{
  "type": "Feature",
  "properties": {
    "addr:full":"1025 Pacific Ave Winnipeg MB R3E 1G5",
    "addr:housenumber":"1025",
    "addr:postcode":"r3e 1g5",
    "addr:street":"Pacific Ave",
    "iso:country":"CA",
    "sg:address":"1025 Pacific Ave",
    "sg:city":"Winnipeg",
    "sg:classifiers":[
        {
            "category":"Building & Trades",
            "subcategory":"Construction",
            "type":"Services"
        }
    ],
    "sg:phone":"+1 204 772 0808",
    "sg:postcode":"R3E 1G5",
    "sg:province":"MB",
    "sg:tags":[
        "woodworker"
    ],
    "wof:name":"Leslie Woodworking",
    "wof:placetype":"venue"
},
  "geometry": {"coordinates":[-97.168465,49.911346],"type":"Point"}
}