{
  "type": "Feature",
  "properties": {
    "addr:full":"1419 Ch Gascon Terrebonne QC J6X 4L9",
    "addr:housenumber":"1419",
    "addr:postcode":"j6x 4l9",
    "addr:street":"Ch Gascon",
    "iso:country":"CA",
    "sg:address":"1419 Ch Gascon",
    "sg:city":"Terrebonne",
    "sg:classifiers":[
        {
            "category":"Restaurant",
            "type":"Food & Drink"
        }
    ],
    "sg:phone":"+1 514 910 4713",
    "sg:postcode":"J6X 4L9",
    "sg:province":"QC",
    "sg:tags":[
        "parlor",
        "ice",
        "cream"
    ],
    "wof:name":"Cremerie LA Meuniere",
    "wof:placetype":"venue"
},
  "geometry": {"coordinates":[-73.6520690918,45.7101097107],"type":"Point"}
}