{
  "type": "Feature",
  "properties": {
    "addr:full":"896 Ash St Campbell River BC V9W 1G2",
    "addr:housenumber":"896",
    "addr:postcode":"v9w 1g2",
    "addr:street":"Ash St",
    "iso:country":"CA",
    "sg:address":"896 Ash St",
    "sg:city":"Campbell River",
    "sg:classifiers":[
        {
            "category":"Professional",
            "subcategory":"Research",
            "type":"Services"
        }
    ],
    "sg:phone":"+1 250 923 9116",
    "sg:postcode":"V9W 1G2",
    "sg:province":"BC",
    "sg:tags":[
        "environmental",
        "ecological"
    ],
    "wof:name":"Superior Info Resources Ltd",
    "wof:placetype":"venue"
},
  "geometry": {"coordinates":[-125.230407715,49.9903793335],"type":"Point"}
}