{
  "type": "Feature",
  "properties": {
    "addr:full":"7200 Boul Saint-Laurent Montreal QC H2R 2X9",
    "addr:housenumber":"7200",
    "addr:postcode":"h2r 2x9",
    "addr:street":"Boul Saint-Laurent",
    "iso:country":"CA",
    "sg:address":"7200 Boul Saint-Laurent",
    "sg:city":"Montreal",
    "sg:classifiers":[
        {
            "category":"Retail",
            "subcategory":"Auto Rental",
            "type":"Services"
        }
    ],
    "sg:phone":"+1 514 277 3737",
    "sg:postcode":"H2R 2X9",
    "sg:province":"QC",
    "sg:tags":[
        "renting",
        "automobile"
    ],
    "wof:name":"Auto Location Pelletier",
    "wof:placetype":"venue"
},
  "geometry": {"coordinates":[-73.618607,45.53463],"type":"Point"}
}