{
  "type": "Feature",
  "properties": {
    "addr:full":"224 Bonnechere St Eganville ON K0J 1T0",
    "addr:housenumber":"224",
    "addr:postcode":"k0j 1t0",
    "addr:street":"Bonnechere St",
    "iso:country":"CA",
    "sg:address":"224 Bonnechere St",
    "sg:city":"Eganville",
    "sg:classifiers":[
        {
            "category":"Autos & Motor Vehicles",
            "subcategory":"Auto Supplies",
            "type":"Retail Goods"
        }
    ],
    "sg:phone":"+1 613 628 2242",
    "sg:postcode":"K0J 1T0",
    "sg:province":"ON",
    "sg:tags":[
        "automobile",
        "parts"
    ],
    "wof:name":"Auto Parts Extra",
    "wof:placetype":"venue"
},
  "geometry": {"coordinates":[-77.1052322388,45.5436325073],"type":"Point"}
}