{
  "type": "Feature",
  "properties": {
    "addr:full":"6009 Quinpool Rd #1000 Halifax NS B3K 5J7",
    "addr:housenumber":"6009",
    "addr:postcode":"b3k 5j7",
    "addr:street":"Quinpool Rd # 1000",
    "iso:country":"CA",
    "sg:address":"6009 Quinpool Rd #1000",
    "sg:city":"Halifax",
    "sg:classifiers":[
        {
            "category":"Real Estate",
            "subcategory":"Real Estate Agent",
            "type":"Services"
        }
    ],
    "sg:phone":"+1 902 423 1080",
    "sg:postcode":"B3K 5J7",
    "sg:province":"NS",
    "sg:tags":[
        "management"
    ],
    "wof:name":"Scotia Learning Ctr",
    "wof:placetype":"venue"
},
  "geometry": {"coordinates":[-63.5907897949,44.6473655701],"type":"Point"}
}