{
  "type": "Feature",
  "properties": {
    "addr:full":"1222 9 Ave S Lethbridge AB T1J 1V4",
    "addr:housenumber":"1222",
    "addr:postcode":"t1j 1v4",
    "addr:street":"9 Ave S",
    "iso:country":"CA",
    "sg:address":"1222 9 Ave S",
    "sg:city":"Lethbridge",
    "sg:classifiers":[
        {
            "category":"Education",
            "subcategory":"School",
            "type":"Public Place"
        }
    ],
    "sg:phone":"+1 403 327 5818",
    "sg:postcode":"T1J 1V4",
    "sg:province":"AB",
    "wof:name":"Fleetwood Bawden School",
    "wof:placetype":"venue"
},
  "geometry": {"coordinates":[-112.827026,49.68626],"type":"Point"}
}