{
  "type": "Feature",
  "properties": {
    "addr:full":"Rossland BC V0G 1Y0",
    "addr:postcode":"v0g 1y0",
    "iso:country":"CA",
    "sg:city":"Rossland",
    "sg:classifiers":[
        {
            "category":"Professional",
            "subcategory":"Art Services",
            "type":"Services"
        }
    ],
    "sg:phone":"+1 250 362 3394",
    "sg:postcode":"V0G 1Y0",
    "sg:province":"BC",
    "sg:tags":[
        "graphic",
        "designer"
    ],
    "wof:name":"Hlf Images",
    "wof:placetype":"venue"
},
  "geometry": {"coordinates":[-117.799362,49.076931],"type":"Point"}
}