{
  "type": "Feature",
  "properties": {
    "iso:country":"CA",
    "sg:address":"270 North Service Rd W",
    "sg:city":"Oakville",
    "sg:classifiers":[
        {
            "category":"Restaurant",
            "type":"Food & Drink"
        }
    ],
    "sg:phone":"+1 905 338 0602",
    "sg:postcode":"L6M 2R8",
    "sg:province":"ON",
    "wof:name":"Caz's Fish & Chip Shoppe",
    "wof:placetype":"venue"
},
  "geometry": {"coordinates":[-79.70665,43.446812],"type":"Point"}
}