{
  "type": "Feature",
  "properties": {
    "addr:full":"3165 King George Hwy Surrey BC V4P 1B8",
    "addr:housenumber":"3165",
    "addr:postcode":"v4p 1b8",
    "addr:street":"King George Hwy",
    "iso:country":"CA",
    "sg:address":"3165 King George Hwy",
    "sg:city":"Surrey",
    "sg:classifiers":[
        {
            "category":"Home & Garden",
            "subcategory":"Building Materials",
            "type":"Retail Goods"
        }
    ],
    "sg:phone":"+1 604 535 9888",
    "sg:postcode":"V4P 1B8",
    "sg:province":"BC",
    "wof:name":"Rona Revy Home Ctr",
    "wof:placetype":"venue"
},
  "geometry": {"coordinates":[-122.810844421,49.0593147278],"type":"Point"}
}