{
  "type": "Feature",
  "properties": {
    "addr:full":"Red Deer AB T4N 4C9",
    "addr:postcode":"t4n 4c9",
    "iso:country":"CA",
    "sg:city":"Red Deer",
    "sg:classifiers":[
        {
            "category":"Personal",
            "type":"Services"
        }
    ],
    "sg:phone":"+1 403 343 0909",
    "sg:postcode":"T4N 4C9",
    "sg:province":"AB",
    "sg:tags":[
        "therapist",
        "massage"
    ],
    "wof:name":"Pines Plaza Muscle Therapy",
    "wof:placetype":"venue"
},
  "geometry": {"coordinates":[-113.81326294,52.291721344],"type":"Point"}
}