{
  "type": "Feature",
  "properties": {
    "addr:full":"1014 Bloor St W Toronto ON M6H 1M2",
    "addr:housenumber":"1014",
    "addr:postcode":"m6h 1m2",
    "addr:street":"Bloor St W",
    "iso:country":"CA",
    "sg:address":"1014 Bloor St W",
    "sg:city":"Toronto",
    "sg:classifiers":[
        {
            "category":"Food & Beverages",
            "subcategory":"Bakery",
            "type":"Retail Goods"
        }
    ],
    "sg:phone":"+1 416 536 1522",
    "sg:postcode":"M6H 1M2",
    "sg:province":"ON",
    "sg:tags":[
        "baker"
    ],
    "wof:name":"Courense Bakery Ltd",
    "wof:placetype":"venue"
},
  "geometry": {"coordinates":[-79.430908,43.660931],"type":"Point"}
}