{
  "type": "Feature",
  "properties": {
    "addr:full":"2685 Rue King O Sherbrooke QC J1L 1C1",
    "addr:housenumber":"2685",
    "addr:postcode":"j1l 1c1",
    "addr:street":"Rue King O",
    "iso:country":"CA",
    "sg:address":"2685 Rue King O",
    "sg:city":"Sherbrooke",
    "sg:classifiers":[
        {
            "category":"Professional",
            "subcategory":"Advertising",
            "type":"Services"
        }
    ],
    "sg:phone":"+1 819 823 0850",
    "sg:postcode":"J1L 1C1",
    "sg:province":"QC",
    "sg:tags":[
        "publicity"
    ],
    "wof:name":"Lemieux Bedard Communications",
    "wof:placetype":"venue"
},
  "geometry": {"coordinates":[-71.93871300000001,45.398369],"type":"Point"}
}