{
  "type": "Feature",
  "properties": {
    "addr:full":"1087 St Mary's Rd Winnipeg MB R2M 3T2",
    "addr:housenumber":"1087",
    "addr:postcode":"r2m 3t2",
    "addr:street":"St Mary'S Rd",
    "iso:country":"CA",
    "sg:address":"1087 St Mary's Rd",
    "sg:city":"Winnipeg",
    "sg:classifiers":[
        {
            "category":"Shopping",
            "subcategory":"Pharmacy",
            "type":"Retail Goods"
        }
    ],
    "sg:phone":"+1 204 255 2988",
    "sg:postcode":"R2M 3T2",
    "sg:province":"MB",
    "wof:name":"Dakota Pharmacy",
    "wof:placetype":"venue"
},
  "geometry": {"coordinates":[-97.112442,49.836483],"type":"Point"}
}