{
  "type": "Feature",
  "properties": {
    "addr:full":"North York ON M2N 6N4",
    "addr:postcode":"m2n 6n4",
    "iso:country":"CA",
    "sg:city":"North York",
    "sg:classifiers":[
        {
            "category":"Restaurant",
            "type":"Food & Drink"
        }
    ],
    "sg:phone":"+1 416 225 5545",
    "sg:postcode":"M2N 6N4",
    "sg:province":"ON",
    "wof:name":"Mr Submarine",
    "wof:placetype":"venue"
},
  "geometry": {"coordinates":[-79.4097442627,43.7564544678],"type":"Point"}
}