{
  "type": "Feature",
  "properties": {
    "addr:full":"NW 18-53-04 W5 Fallis AB T0E 0V0",
    "addr:postcode":"18-53-04 w5 fallis;t0e 0v0",
    "addr:street":"Nw",
    "iso:country":"CA",
    "sg:address":"NW 18-53-04 W5",
    "sg:city":"Fallis",
    "sg:classifiers":[
        {
            "category":"Autos & Motor Vehicles",
            "subcategory":"Automobile Sales",
            "type":"Retail Goods"
        }
    ],
    "sg:phone":"+1 780 892 2382",
    "sg:postcode":"T0E 0V0",
    "sg:province":"AB",
    "sg:tags":[
        "car",
        "dealer"
    ],
    "wof:name":"Wally's Garage",
    "wof:placetype":"venue"
},
  "geometry": {"coordinates":[-114.639823914,53.5751342773],"type":"Point"}
}