{
  "type": "Feature",
  "properties": {
    "addr:full":"Fortune NL A0E 1P0",
    "addr:postcode":"a0e 1p0",
    "iso:country":"CA",
    "sg:city":"Fortune",
    "sg:classifiers":[
        {
            "category":"Professional",
            "subcategory":"Employment Agencies",
            "type":"Services"
        }
    ],
    "sg:phone":"+1 709 832 2090",
    "sg:postcode":"A0E 1P0",
    "sg:province":"NL",
    "sg:tags":[
        "opportunity"
    ],
    "wof:name":"Bridges Employment Corp",
    "wof:placetype":"venue"
},
  "geometry": {"coordinates":[-55.8259544373,47.0741348267],"type":"Point"}
}