{
  "type": "Feature",
  "properties": {
    "addr:full":"253 Boul St-Pierre E Caraquet NB E1W 1B3",
    "addr:housenumber":"253",
    "addr:postcode":"e1w 1b3",
    "addr:street":"Boul St-Pierre E Caraquet",
    "iso:country":"CA",
    "sg:address":"253 Boul St-Pierre E",
    "sg:city":"Caraquet",
    "sg:classifiers":[
        {
            "category":"Health Services",
            "subcategory":"Nursing And Care Facility",
            "type":"Services"
        }
    ],
    "sg:phone":"+1 506 726 2744",
    "sg:postcode":"E1W 1B3",
    "sg:province":"NB",
    "sg:tags":[
        "home",
        "convalescent",
        "residential"
    ],
    "wof:name":"Villa Beausejour",
    "wof:placetype":"venue"
},
  "geometry": {"coordinates":[-64.90263400000001,47.796799],"type":"Point"}
}