{
  "type": "Feature",
  "properties": {
    "addr:full":"7 Hazelglen Ave North York ON M2R 1R6",
    "addr:housenumber":"7",
    "addr:postcode":"m2r 1r6",
    "addr:street":"Hazelglen Ave",
    "iso:country":"CA",
    "sg:address":"7 Hazelglen Ave",
    "sg:city":"North York",
    "sg:classifiers":[
        {
            "category":"Building & Trades",
            "subcategory":"Electrical",
            "type":"Services"
        }
    ],
    "sg:phone":"+1 416 225 0157",
    "sg:postcode":"M2R 1R6",
    "sg:province":"ON",
    "sg:tags":[
        "electric",
        "contractor"
    ],
    "wof:name":"Ken Moore Electrical Contr",
    "wof:placetype":"venue"
},
  "geometry": {"coordinates":[-79.429543,43.770245],"type":"Point"}
}