{
  "type": "Feature",
  "properties": {
    "addr:full":"180 Market Ave Winnipeg MB R3B 0P7",
    "addr:housenumber":"180",
    "addr:postcode":"r3b 0p7",
    "addr:street":"Market Ave",
    "iso:country":"CA",
    "sg:address":"180 Market Ave",
    "sg:city":"Winnipeg",
    "sg:classifiers":[
        {
            "category":"Recreation",
            "type":"Entertainment"
        }
    ],
    "sg:phone":"+1 204 989 2880",
    "sg:postcode":"R3B 0P7",
    "sg:province":"MB",
    "sg:tags":[
        "hall",
        "auditorium"
    ],
    "wof:name":"Pantages Playhouse Theatre",
    "wof:placetype":"venue"
},
  "geometry": {"coordinates":[-97.137711,49.898987],"type":"Point"}
}