{
  "type": "Feature",
  "properties": {
    "addr:full":"260 Industrial Road F Cranbrook BC V1C 6N8",
    "addr:housenumber":"260",
    "addr:postcode":"v1c 6n8",
    "addr:street":"Industrial Road F",
    "iso:country":"CA",
    "sg:address":"260 Industrial Road F",
    "sg:city":"Cranbrook",
    "sg:classifiers":[
        {
            "category":"Building & Trades",
            "subcategory":"Construction",
            "type":"Services"
        }
    ],
    "sg:phone":"+1 250 489 4214",
    "sg:postcode":"V1C 6N8",
    "sg:province":"BC",
    "sg:tags":[
        "equipment",
        "station"
    ],
    "wof:name":"Kootenay Valley Petroleum Svc",
    "wof:placetype":"venue"
},
  "geometry": {"coordinates":[-115.75799600000001,49.534466],"type":"Point"}
}