{
  "type": "Feature",
  "properties": {
    "addr:full":"750 Av Ogilvy Montreal QC H3N 1N7",
    "addr:housenumber":"750",
    "addr:postcode":"h3n 1n7",
    "addr:street":"Av Ogilvy",
    "iso:country":"CA",
    "sg:address":"750 Av Ogilvy",
    "sg:city":"Montreal",
    "sg:classifiers":[
        {
            "category":"Retail",
            "subcategory":"Laundry & Dry Cleaning",
            "type":"Services"
        }
    ],
    "sg:phone":"+1 514 272 1823",
    "sg:postcode":"H3N 1N7",
    "sg:province":"QC",
    "sg:tags":[
        "cleaners"
    ],
    "wof:name":"Nettoyeur Plissimo Inc",
    "wof:placetype":"venue"
},
  "geometry": {"coordinates":[-73.626205,45.527313],"type":"Point"}
}