{
  "type": "Feature",
  "properties": {
    "iso:country":"CA",
    "sg:city":"Calgary",
    "sg:classifiers":[
        {
            "category":"Personal",
            "subcategory":"Beauty Salon",
            "type":"Services"
        }
    ],
    "sg:phone":"+1 403 239 2334",
    "sg:postcode":"T3G 3T2",
    "sg:province":"AB",
    "wof:name":"Image Hair & Esthetics-Day Spa",
    "wof:placetype":"venue"
},
  "geometry": {"coordinates":[-114.197608948,51.1270446777],"type":"Point"}
}