{
  "type": "Feature",
  "properties": {
    "addr:full":"573 King St E Oshawa ON L1H 1G3",
    "addr:housenumber":"573",
    "addr:postcode":"l1h 1g3",
    "addr:street":"King St E",
    "iso:country":"CA",
    "sg:address":"573 King St E",
    "sg:city":"Oshawa",
    "sg:classifiers":[
        {
            "category":"Shopping",
            "subcategory":"Pharmacy",
            "type":"Retail Goods"
        }
    ],
    "sg:phone":"+1 905 725 3594",
    "sg:postcode":"L1H 1G3",
    "sg:province":"ON",
    "wof:name":"Eastview Pharmacy Inc",
    "wof:placetype":"venue"
},
  "geometry": {"coordinates":[-78.84251403810001,43.9023361206],"type":"Point"}
}