{
  "type": "Feature",
  "properties": {
    "addr:full":"Edmonton AB T6J 1E8",
    "addr:postcode":"t6j 1e8",
    "iso:country":"CA",
    "sg:city":"Edmonton",
    "sg:classifiers":[
        {
            "category":"Personal",
            "subcategory":"Beauty Salon",
            "type":"Services"
        }
    ],
    "sg:phone":"+1 780 434 1344",
    "sg:postcode":"T6J 1E8",
    "sg:province":"AB",
    "wof:name":"Harry Ainlay Beauty Culture",
    "wof:placetype":"venue"
},
  "geometry": {"coordinates":[-113.516845703,53.4777145386],"type":"Point"}
}