{
  "type": "Feature",
  "properties": {
    "addr:full":"950 Ch Hemming Saint-Charles-DE-Drummond QC J2B 7T5",
    "addr:housenumber":"950",
    "addr:postcode":"j2b 7t5",
    "addr:street":"Ch Hemming",
    "iso:country":"CA",
    "sg:address":"950 Ch Hemming",
    "sg:city":"Saint-Charles-DE-Drummond",
    "sg:classifiers":[
        {
            "category":"Restaurant",
            "type":"Food & Drink"
        }
    ],
    "sg:phone":"+1 819 474 1917",
    "sg:postcode":"J2B 7T5",
    "sg:province":"QC",
    "sg:tags":[
        "caterer"
    ],
    "wof:name":"Buffet Leo Arel",
    "wof:placetype":"venue"
},
  "geometry": {"coordinates":[-72.4587860107,45.8672370911],"type":"Point"}
}