{
  "type": "Feature",
  "properties": {
    "addr:full":"527 Boul Tache E Montmagny QC G5V 4G7",
    "addr:housenumber":"527",
    "addr:postcode":"g5v 4g7",
    "addr:street":"Boul Tache E",
    "iso:country":"CA",
    "sg:address":"527 Boul Tache E",
    "sg:city":"Montmagny",
    "sg:classifiers":[
        {
            "category":"Building & Trades",
            "subcategory":"Electrical",
            "type":"Services"
        }
    ],
    "sg:phone":"+1 418 248 1058",
    "sg:postcode":"G5V 4G7",
    "sg:province":"QC",
    "sg:tags":[
        "electric",
        "contractor"
    ],
    "wof:name":"Simon Blanchet Inc",
    "wof:placetype":"venue"
},
  "geometry": {"coordinates":[-70.52093499999999,46.99324],"type":"Point"}
}