{
  "type": "Feature",
  "properties": {
    "addr:full":"5203 50 St Rocky Mountain House AB T4T 1G7",
    "addr:housenumber":"5203",
    "addr:postcode":"t4t 1g7",
    "addr:street":"50 St",
    "iso:country":"CA",
    "sg:address":"5203 50 St",
    "sg:city":"Rocky Mountain House",
    "sg:classifiers":[
        {
            "category":"Health Services",
            "subcategory":"Medical Lab",
            "type":"Services"
        }
    ],
    "sg:phone":"+1 403 845 6660",
    "sg:postcode":"T4T 1G7",
    "sg:province":"AB",
    "wof:name":"Rocky Mountain Denture Clinic",
    "wof:placetype":"venue"
},
  "geometry": {"coordinates":[-114.919067383,52.377948761],"type":"Point"}
}