{
  "type": "Feature",
  "properties": {
    "addr:full":"9655 49 Ave NW Edmonton AB T6E 5Z5",
    "addr:housenumber":"9655",
    "addr:postcode":"t6e 5z5",
    "addr:street":"49 Ave Nw",
    "iso:country":"CA",
    "sg:address":"9655 49 Ave NW",
    "sg:city":"Edmonton",
    "sg:classifiers":[
        {
            "category":"Wholesale",
            "subcategory":"Machinery & Supplies",
            "type":"Manufacturing & Wholesale Goods"
        }
    ],
    "sg:phone":"+1 780 438 6110",
    "sg:postcode":"T6E 5Z5",
    "sg:province":"AB",
    "sg:tags":[
        "carpet",
        "janitor",
        "cleaning",
        "rug"
    ],
    "wof:name":"Fibreclean Supplies Ltd",
    "wof:placetype":"venue"
},
  "geometry": {"coordinates":[-113.47839399999999,53.486103],"type":"Point"}
}