{
  "type": "Feature",
  "properties": {
    "addr:full":"720 Spadina Ave # 402 Toronto ON M5S 2T9",
    "addr:housenumber":"720",
    "addr:postcode":"m5s 2t9",
    "addr:street":"Spadina Ave # 402",
    "iso:country":"CA",
    "sg:address":"720 Spadina Ave # 402",
    "sg:city":"Toronto",
    "sg:classifiers":[
        {
            "category":"Organizations",
            "subcategory":"Membership Organization",
            "type":"Services"
        }
    ],
    "sg:phone":"+1 416 964 0619",
    "sg:postcode":"M5S 2T9",
    "sg:province":"ON",
    "sg:tags":[
        "physician",
        "surgeon"
    ],
    "wof:name":"Doctors Without Borders",
    "wof:placetype":"venue"
},
  "geometry": {"coordinates":[-79.40329,43.665295],"type":"Point"}
}