{
  "type": "Feature",
  "properties": {
    "iso:country":"CA",
    "sg:address":"220 Livingstone Ave N",
    "sg:city":"Listowel",
    "sg:classifiers":[
        {
            "category":"Organizations",
            "subcategory":"Religious Organization",
            "type":"Services"
        }
    ],
    "sg:phone":"+1 519 291 4690",
    "sg:postcode":"N4W 1P9",
    "sg:province":"ON",
    "sg:tags":[
        "church"
    ],
    "wof:name":"Knox Presbyterian Church",
    "wof:placetype":"venue"
},
  "geometry": {"coordinates":[-80.9544906616,43.7336540222],"type":"Point"}
}