{
  "type": "Feature",
  "properties": {
    "addr:full":"Port Moody BC V3H 2C1",
    "addr:postcode":"v3h 2c1",
    "iso:country":"CA",
    "sg:city":"Port Moody",
    "sg:classifiers":[
        {
            "category":"Restaurant",
            "type":"Food & Drink"
        }
    ],
    "sg:phone":"+1 604 469 2444",
    "sg:postcode":"V3H 2C1",
    "sg:province":"BC",
    "wof:name":"Rozzini's Restaurant & Cafe",
    "wof:placetype":"venue"
},
  "geometry": {"coordinates":[-122.84972399999999,49.276794],"type":"Point"}
}