{
  "type": "Feature",
  "properties": {
    "iso:country":"CA",
    "sg:address":"1075 Ceremonial Dr # 2",
    "sg:city":"Mississauga",
    "sg:classifiers":[
        {
            "category":"Restaurant",
            "type":"Food & Drink"
        }
    ],
    "sg:phone":"+1 905 755 9711",
    "sg:postcode":"L5R 2Z4",
    "sg:province":"ON",
    "wof:name":"Mississauga Pizza Depot",
    "wof:placetype":"venue"
},
  "geometry": {"coordinates":[-79.6780090332,43.6070327759],"type":"Point"}
}