{
  "type": "Feature",
  "properties": {
    "addr:full":"132 Sheppard Ave W North York ON M2N 1M5",
    "addr:housenumber":"132",
    "addr:postcode":"m2n 1m5",
    "addr:street":"Sheppard Ave W",
    "iso:country":"CA",
    "sg:address":"132 Sheppard Ave W",
    "sg:city":"North York",
    "sg:classifiers":[
        {
            "category":"Shopping",
            "subcategory":"Gifts & Souvenirs",
            "type":"Retail Goods"
        }
    ],
    "sg:phone":"+1 416 250 6020",
    "sg:postcode":"M2N 1M5",
    "sg:province":"ON",
    "sg:tags":[
        "basket",
        "shop",
        "parcel"
    ],
    "wof:name":"Wrappers",
    "wof:placetype":"venue"
},
  "geometry": {"coordinates":[-79.41774700000001,43.760132],"type":"Point"}
}