{
  "type": "Feature",
  "properties": {
    "addr:full":"1259 Rue Guy Montreal QC H3H 2K5",
    "addr:housenumber":"1259",
    "addr:postcode":"h3h 2k5",
    "addr:street":"Rue Guy",
    "iso:country":"CA",
    "sg:address":"1259 Rue Guy",
    "sg:city":"Montreal",
    "sg:classifiers":[
        {
            "category":"Sports & Exercise",
            "subcategory":"Gym",
            "type":"Entertainment"
        }
    ],
    "sg:phone":"+1 514 939 6061",
    "sg:postcode":"H3H 2K5",
    "sg:province":"QC",
    "sg:tags":[
        "club",
        "health",
        "studio",
        "gymnasium"
    ],
    "wof:name":"Perfmax",
    "wof:placetype":"venue"
},
  "geometry": {"coordinates":[-73.5768280029,45.4948043823],"type":"Point"}
}