{
  "type": "Feature",
  "properties": {
    "addr:full":"3302 Broadway St Avonmore ON K0C 1C0",
    "addr:housenumber":"3302",
    "addr:postcode":"k0c 1c0",
    "addr:street":"Broadway St",
    "iso:country":"CA",
    "sg:address":"3302 Broadway St",
    "sg:city":"Avonmore",
    "sg:classifiers":[
        {
            "category":"Building & Trades",
            "subcategory":"Construction",
            "type":"Services"
        }
    ],
    "sg:phone":"+1 613 346 5594",
    "sg:postcode":"K0C 1C0",
    "sg:province":"ON",
    "sg:tags":[
        "general",
        "contractor"
    ],
    "wof:name":"Dale Coleman Construction Ltd",
    "wof:placetype":"venue"
},
  "geometry": {"coordinates":[-74.966072,45.172108],"type":"Point"}
}