{
  "type": "Feature",
  "properties": {
    "addr:full":"423 Yonge St Toronto ON M5B 1T2",
    "addr:housenumber":"423",
    "addr:postcode":"m5b 1t2",
    "addr:street":"Yonge St",
    "iso:country":"CA",
    "sg:address":"423 Yonge St",
    "sg:city":"Toronto",
    "sg:classifiers":[
        {
            "category":"Social Services",
            "type":"Services"
        }
    ],
    "sg:phone":"+1 416 340 7222",
    "sg:postcode":"M5B 1T2",
    "sg:province":"ON",
    "sg:tags":[
        "senior",
        "citizen"
    ],
    "wof:name":"College View Supportive Hsng",
    "wof:placetype":"venue"
},
  "geometry": {"coordinates":[-79.382401,43.660221],"type":"Point"}
}