{
  "type": "Feature",
  "properties": {
    "addr:full":"13 Rue Beauchemin Victoriaville QC G6P 2E3",
    "addr:housenumber":"13",
    "addr:postcode":"g6p 2e3",
    "addr:street":"Rue Beauchemin",
    "iso:country":"CA",
    "sg:address":"13 Rue Beauchemin",
    "sg:city":"Victoriaville",
    "sg:classifiers":[
        {
            "category":"Restaurant",
            "type":"Food & Drink"
        }
    ],
    "sg:phone":"+1 819 758 8040",
    "sg:postcode":"G6P 2E3",
    "sg:province":"QC",
    "sg:tags":[
        "caterer",
        "rooms",
        "banquet"
    ],
    "wof:name":"Mechoui Mobile Premier Choix",
    "wof:placetype":"venue"
},
  "geometry": {"coordinates":[-71.98634300000001,46.051907],"type":"Point"}
}