{
  "type": "Feature",
  "properties": {
    "addr:full":"1360 Bedford Hwy Bedford NS B4A 1E2",
    "addr:housenumber":"1360",
    "addr:postcode":"b4a 1e2",
    "addr:street":"Bedford Hwy",
    "iso:country":"CA",
    "sg:address":"1360 Bedford Hwy",
    "sg:city":"Bedford",
    "sg:classifiers":[
        {
            "category":"Home & Garden",
            "subcategory":"Furniture",
            "type":"Retail Goods"
        }
    ],
    "sg:phone":"+1 902 835 5314",
    "sg:postcode":"B4A 1E2",
    "sg:province":"NS",
    "sg:tags":[
        "shop",
        "gift"
    ],
    "wof:name":"Cricket on the Hearth Intrs",
    "wof:placetype":"venue"
},
  "geometry": {"coordinates":[-63.664597,44.728226],"type":"Point"}
}