{
  "type": "Feature",
  "properties": {
    "addr:full":"58 Promenade Ave Nepean ON K2E 5X8",
    "addr:housenumber":"58",
    "addr:postcode":"k2e 5x8",
    "addr:street":"Promenade Ave",
    "iso:country":"CA",
    "sg:address":"58 Promenade Ave",
    "sg:city":"Nepean",
    "sg:classifiers":[
        {
            "category":"Food & Beverages",
            "subcategory":"Specialty",
            "type":"Retail Goods"
        }
    ],
    "sg:phone":"+1 613 727 5484",
    "sg:postcode":"K2E 5X8",
    "sg:province":"ON",
    "sg:tags":[
        "health",
        "diet"
    ],
    "wof:name":"Forever Living Products",
    "wof:placetype":"venue"
},
  "geometry": {"coordinates":[-75.703766,45.327972],"type":"Point"}
}