{
  "type": "Feature",
  "properties": {
    "addr:full":"7178 Horne St Mission BC V2V 3X8",
    "addr:housenumber":"7178",
    "addr:postcode":"v2v 3x8",
    "addr:street":"Horne St",
    "iso:country":"CA",
    "sg:address":"7178 Horne St",
    "sg:city":"Mission",
    "sg:classifiers":[
        {
            "category":"Shopping",
            "subcategory":"Department Store",
            "type":"Retail Goods"
        }
    ],
    "sg:phone":"+1 604 820 8115",
    "sg:postcode":"V2V 3X8",
    "sg:province":"BC",
    "sg:tags":[
        "shop"
    ],
    "wof:name":"Liquidation World Inc",
    "wof:placetype":"venue"
},
  "geometry": {"coordinates":[-122.300697,49.132301],"type":"Point"}
}