{
  "type": "Feature",
  "properties": {
    "iso:country":"CA",
    "sg:address":"20 Mutchmore St W",
    "sg:city":"Providence Bay",
    "sg:classifiers":[
        {
            "category":"Home & Garden",
            "subcategory":"Hardware",
            "type":"Retail Goods"
        }
    ],
    "sg:phone":"+1 705 377 5341",
    "sg:postcode":"P0P 1T0",
    "sg:province":"ON",
    "wof:name":"Home Hardware Building Ctr",
    "wof:placetype":"venue"
},
  "geometry": {"coordinates":[-82.26438903810001,45.6640815735],"type":"Point"}
}