{
  "type": "Feature",
  "properties": {
    "addr:full":"1015 Central Ave Saskatoon SK S7N 4J2",
    "addr:housenumber":"1015",
    "addr:postcode":"s7n 4j2",
    "addr:street":"Central Ave",
    "iso:country":"CA",
    "sg:address":"1015 Central Ave",
    "sg:city":"Saskatoon",
    "sg:classifiers":[
        {
            "category":"Recreation",
            "type":"Entertainment"
        }
    ],
    "sg:phone":"+1 306 374 7665",
    "sg:postcode":"S7N 4J2",
    "sg:province":"SK",
    "sg:tags":[
        "parlor",
        "billiard"
    ],
    "wof:name":"Modern Billiards",
    "wof:placetype":"venue"
},
  "geometry": {"coordinates":[-106.598724,52.138878],"type":"Point"}
}