{
  "type": "Feature",
  "properties": {
    "addr:full":"15060 108 Ave Surrey BC V3R 1W4",
    "addr:housenumber":"15060",
    "addr:postcode":"v3r 1w4",
    "addr:street":"108 Ave",
    "iso:country":"CA",
    "sg:address":"15060 108 Ave",
    "sg:city":"Surrey",
    "sg:classifiers":[
        {
            "category":"Personal",
            "subcategory":"Beauty Salon",
            "type":"Services"
        }
    ],
    "sg:phone":"+1 604 584 3687",
    "sg:postcode":"V3R 1W4",
    "sg:province":"BC",
    "sg:tags":[
        "hair",
        "replacement"
    ],
    "wof:name":"Gents Hair Systems",
    "wof:placetype":"venue"
},
  "geometry": {"coordinates":[-122.80527499999999,49.198643],"type":"Point"}
}