{
  "type": "Feature",
  "properties": {
    "iso:country":"CA",
    "sg:address":"439 Av Notre-Dame",
    "sg:city":"Saint-Lambert",
    "sg:classifiers":[
        {
            "category":"Professional",
            "subcategory":"Lawyer & Legal Services",
            "type":"Services"
        }
    ],
    "sg:phone":"+1 450 466 3630",
    "sg:postcode":"J4P 2K5",
    "sg:province":"QC",
    "sg:tags":[
        "attorney"
    ],
    "wof:name":"Racicot, Jean-Felix",
    "wof:placetype":"venue"
},
  "geometry": {"coordinates":[-73.511513,45.502377],"type":"Point"}
}