{
  "type": "Feature",
  "properties": {
    "addr:full":"376 Champlain St Dieppe NB E1A 1P3",
    "addr:housenumber":"376",
    "addr:postcode":"e1a 1p3",
    "addr:street":"Champlain St",
    "iso:country":"CA",
    "sg:address":"376 Champlain St",
    "sg:city":"Dieppe",
    "sg:classifiers":[
        {
            "category":"Building & Trades",
            "subcategory":"Cleaning & Sanitation",
            "type":"Services"
        }
    ],
    "sg:phone":"+1 506 858 5085",
    "sg:postcode":"E1A 1P3",
    "sg:province":"NB",
    "sg:tags":[
        "janitor"
    ],
    "wof:name":"Sprucegrove Building Cleaners",
    "wof:placetype":"venue"
},
  "geometry": {"coordinates":[-64.74050099999999,46.096947],"type":"Point"}
}