{
  "type": "Feature",
  "properties": {
    "addr:full":"39 Hyland Cres Whitehorse YT Y1A 4P6",
    "addr:housenumber":"39",
    "addr:postcode":"y1a 4p6",
    "addr:street":"Hyland Cres",
    "iso:country":"CA",
    "sg:address":"39 Hyland Cres",
    "sg:city":"Whitehorse",
    "sg:classifiers":[
        {
            "category":"Shopping",
            "subcategory":"Gifts & Souvenirs",
            "type":"Retail Goods"
        }
    ],
    "sg:phone":"+1 867 668 3683",
    "sg:postcode":"Y1A 4P6",
    "sg:province":"YT",
    "sg:tags":[
        "party",
        "ice",
        "supply"
    ],
    "wof:name":"Igloo Ice Sales",
    "wof:placetype":"venue"
},
  "geometry": {"coordinates":[-135.01393127399999,60.7017173767],"type":"Point"}
}