{
  "type": "Feature",
  "properties": {
    "addr:full":"151 Wood Valley Rise SW Calgary AB T2W 5S9",
    "addr:housenumber":"151",
    "addr:postcode":"t2w 5s9",
    "addr:street":"Wood Valley Rise Sw",
    "iso:country":"CA",
    "sg:address":"151 Wood Valley Rise SW",
    "sg:city":"Calgary",
    "sg:classifiers":[
        {
            "category":"Personal",
            "type":"Services"
        }
    ],
    "sg:phone":"+1 403 710 0011",
    "sg:postcode":"T2W 5S9",
    "sg:province":"AB",
    "sg:tags":[
        "house",
        "sitter",
        "real estate",
        "inspection"
    ],
    "wof:name":"Ahs Absentee Homeowner Svc",
    "wof:placetype":"venue"
},
  "geometry": {"coordinates":[-114.13781,50.936916],"type":"Point"}
}