{
  "type": "Feature",
  "properties": {
    "addr:full":"21 Main St Unionville ON L3R 2E5",
    "addr:housenumber":"21",
    "addr:postcode":"l3r 2e5",
    "addr:street":"Main St",
    "iso:country":"CA",
    "sg:address":"21 Main St",
    "sg:city":"Unionville",
    "sg:classifiers":[
        {
            "category":"Autos & Motor Vehicles",
            "subcategory":"Automobile Sales",
            "type":"Retail Goods"
        }
    ],
    "sg:phone":"+1 905 764 9330",
    "sg:postcode":"L3R 2E5",
    "sg:province":"ON",
    "sg:tags":[
        "car",
        "dealer"
    ],
    "wof:name":"Markville Ford Lincoln Ltd",
    "wof:placetype":"venue"
},
  "geometry": {"coordinates":[-79.2954483032,43.8277549744],"type":"Point"}
}