{
  "type": "Feature",
  "properties": {
    "addr:full":"75 Blackfriars St London ON N6H 1K8",
    "addr:housenumber":"75",
    "addr:postcode":"n6h 1k8",
    "addr:street":"Blackfriars St",
    "iso:country":"CA",
    "sg:address":"75 Blackfriars St",
    "sg:city":"London",
    "sg:classifiers":[
        {
            "category":"Organizations",
            "subcategory":"Religious Organization",
            "type":"Services"
        }
    ],
    "sg:phone":"+1 519 679 9770",
    "sg:postcode":"N6H 1K8",
    "sg:province":"ON",
    "sg:tags":[
        "church"
    ],
    "wof:name":"Empress United Church",
    "wof:placetype":"venue"
},
  "geometry": {"coordinates":[-81.26216100000001,42.989464],"type":"Point"}
}