{
  "type": "Feature",
  "properties": {
    "addr:full":"2320 Rue Fullum Montreal QC H2K 3P2",
    "addr:housenumber":"2320",
    "addr:postcode":"h2k 3p2",
    "addr:street":"Rue Fullum",
    "iso:country":"CA",
    "sg:address":"2320 Rue Fullum",
    "sg:city":"Montreal",
    "sg:classifiers":[
        {
            "category":"Food & Beverages",
            "subcategory":"Groceries & Convenience Stores",
            "type":"Retail Goods"
        }
    ],
    "sg:phone":"+1 514 527 1612",
    "sg:postcode":"H2K 3P2",
    "sg:province":"QC",
    "sg:tags":[
        "grocer"
    ],
    "wof:name":"Depanneur Majestic",
    "wof:placetype":"venue"
},
  "geometry": {"coordinates":[-73.55940246580001,45.5322647095],"type":"Point"}
}