{
  "type": "Feature",
  "properties": {
    "addr:full":"291 Dixon Blvd Newmarket ON L3Y 4V5",
    "addr:housenumber":"291",
    "addr:postcode":"l3y 4v5",
    "addr:street":"Dixon Blvd",
    "iso:country":"CA",
    "sg:address":"291 Dixon Blvd",
    "sg:city":"Newmarket",
    "sg:classifiers":[
        {
            "category":"Professional",
            "subcategory":"Art Services",
            "type":"Services"
        }
    ],
    "sg:phone":"+1 905 715 7188",
    "sg:postcode":"L3Y 4V5",
    "sg:province":"ON",
    "sg:tags":[
        "graphic",
        "designer"
    ],
    "wof:name":"Stoney Lake Marketing",
    "wof:placetype":"venue"
},
  "geometry": {"coordinates":[-79.476234436,44.0456924438],"type":"Point"}
}