{
  "type": "Feature",
  "properties": {
    "iso:country":"CA",
    "sg:address":"5822 Boul Talbot",
    "sg:city":"Laterriere",
    "sg:classifiers":[
        {
            "category":"Autos & Motor Vehicles",
            "subcategory":"Fuel & Gas Station",
            "type":"Retail Goods"
        }
    ],
    "sg:phone":"+1 418 678 2541",
    "sg:postcode":"G7N 1W1",
    "sg:province":"QC",
    "sg:tags":[
        "oil"
    ],
    "wof:name":"Petroles Rl Inc",
    "wof:placetype":"venue"
},
  "geometry": {"coordinates":[-71.1340255737,48.3168678284],"type":"Point"}
}