{
  "type": "Feature",
  "properties": {
    "iso:country":"CA",
    "sg:address":"1409 Tecumseh Rd E",
    "sg:city":"Windsor",
    "sg:classifiers":[
        {
            "category":"Retail",
            "subcategory":"Laundry & Dry Cleaning",
            "type":"Services"
        }
    ],
    "sg:phone":"+1 519 256 3426",
    "sg:postcode":"N8W 1C2",
    "sg:province":"ON",
    "sg:tags":[
        "cleaners"
    ],
    "wof:name":"Ixl Cleaners Ltd",
    "wof:placetype":"venue"
},
  "geometry": {"coordinates":[-83.0044937134,42.3002700806],"type":"Point"}
}