{
  "type": "Feature",
  "properties": {
    "addr:full":"Etobicoke ON M8X 2W8",
    "addr:postcode":"m8x 2w8",
    "iso:country":"CA",
    "sg:city":"Etobicoke",
    "sg:classifiers":[
        {
            "category":"Food & Beverages",
            "subcategory":"Specialty",
            "type":"Retail Goods"
        }
    ],
    "sg:phone":"+1 416 233 8786",
    "sg:postcode":"M8X 2W8",
    "sg:province":"ON",
    "sg:tags":[
        "health",
        "diet"
    ],
    "wof:name":"Whole Health",
    "wof:placetype":"venue"
},
  "geometry": {"coordinates":[-79.52216339109999,43.6450500488],"type":"Point"}
}