{
  "type": "Feature",
  "properties": {
    "addr:full":"Keg River AB T0H 2G0",
    "addr:postcode":"t0h 2g0",
    "iso:country":"CA",
    "sg:city":"Keg River",
    "sg:classifiers":[
        {
            "category":"Health Services",
            "subcategory":"Doctor",
            "type":"Services"
        }
    ],
    "sg:phone":"+1 780 981 2556",
    "sg:postcode":"T0H 2G0",
    "sg:province":"AB",
    "sg:tags":[
        "clinic"
    ],
    "wof:name":"Keg River Health Clinic",
    "wof:placetype":"venue"
},
  "geometry": {"coordinates":[-117.89949799999999,57.788273],"type":"Point"}
}