{
  "type": "Feature",
  "properties": {
    "addr:full":"7205 71 St NW Edmonton AB T6B 2Z9",
    "addr:housenumber":"7205",
    "addr:postcode":"t6b 2z9",
    "addr:street":"71 St Nw",
    "iso:country":"CA",
    "sg:address":"7205 71 St NW",
    "sg:city":"Edmonton",
    "sg:classifiers":[
        {
            "category":"Wholesale",
            "subcategory":"Furniture",
            "type":"Manufacturing & Wholesale Goods"
        }
    ],
    "sg:phone":"+1 780 413 9638",
    "sg:postcode":"T6B 2Z9",
    "sg:province":"AB",
    "wof:name":"Office Marketplace Ltd",
    "wof:placetype":"venue"
},
  "geometry": {"coordinates":[-113.435326,53.508324],"type":"Point"}
}