{
  "type": "Feature",
  "properties": {
    "addr:full":"329 Montee Industrielle-Et-Com Rimouski QC G5M 1A7",
    "addr:housenumber":"329",
    "addr:postcode":"g5m 1a7",
    "addr:street":"Montee Industrielle-Et-Com",
    "iso:country":"CA",
    "sg:address":"329 Montee Industrielle-Et-Com",
    "sg:city":"Rimouski",
    "sg:classifiers":[
        {
            "category":"Building & Trades",
            "subcategory":"Plumbing",
            "type":"Services"
        }
    ],
    "sg:phone":"+1 418 724 4436",
    "sg:postcode":"G5M 1A7",
    "sg:province":"QC",
    "sg:tags":[
        "contractor"
    ],
    "wof:name":"Plomberie DE L'Est Inc",
    "wof:placetype":"venue"
},
  "geometry": {"coordinates":[-68.500816,48.460163],"type":"Point"}
}