{
  "type": "Feature",
  "properties": {
    "addr:full":"693 Boul Renault Beauceville QC G5X 1L9",
    "addr:housenumber":"693",
    "addr:postcode":"g5x 1l9",
    "addr:street":"Boul Renault",
    "iso:country":"CA",
    "sg:address":"693 Boul Renault",
    "sg:city":"Beauceville",
    "sg:classifiers":[
        {
            "category":"Manufacturing",
            "subcategory":"Leather Goods",
            "type":"Manufacturing & Wholesale Goods"
        }
    ],
    "sg:phone":"+1 418 774 6201",
    "sg:postcode":"G5X 1L9",
    "sg:province":"QC",
    "wof:name":"Cuiroma Enr",
    "wof:placetype":"venue"
},
  "geometry": {"coordinates":[-70.76649500000001,46.200665],"type":"Point"}
}