{
  "type": "Feature",
  "properties": {
    "addr:full":"1075 Wallace Ave N Listowel ON N4W 1M6",
    "addr:housenumber":"1075",
    "addr:postcode":"n4w 1m6",
    "addr:street":"Wallace Ave N",
    "iso:country":"CA",
    "sg:address":"1075 Wallace Ave N",
    "sg:city":"Listowel",
    "sg:classifiers":[
        {
            "category":"Wholesale",
            "subcategory":"Hardware",
            "type":"Manufacturing & Wholesale Goods"
        }
    ],
    "sg:phone":"+1 519 291 2280",
    "sg:postcode":"N4W 1M6",
    "sg:province":"ON",
    "sg:tags":[
        "tool"
    ],
    "wof:name":"Global Tools & Equipment",
    "wof:placetype":"venue"
},
  "geometry": {"coordinates":[-80.945679,43.741291],"type":"Point"}
}