{
  "type": "Feature",
  "properties": {
    "addr:full":"3711 Rue Notre-Dame O Montreal QC H4C 1P8",
    "addr:housenumber":"3711",
    "addr:postcode":"h4c 1p8",
    "addr:street":"Rue Notre-Dame O",
    "iso:country":"CA",
    "sg:address":"3711 Rue Notre-Dame O",
    "sg:city":"Montreal",
    "sg:classifiers":[
        {
            "category":"Shopping",
            "subcategory":"Pharmacy",
            "type":"Retail Goods"
        }
    ],
    "sg:phone":"+1 514 935 8813",
    "sg:postcode":"H4C 1P8",
    "sg:province":"QC",
    "wof:name":"Jean Coutu",
    "wof:placetype":"venue"
},
  "geometry": {"coordinates":[-73.5359802246,45.5433883667],"type":"Point"}
}