{
  "type": "Feature",
  "properties": {
    "iso:country":"CA",
    "sg:address":"89 Rue Morane",
    "sg:city":"Laval",
    "sg:classifiers":[
        {
            "category":"Building & Trades",
            "subcategory":"Equipment Rental",
            "type":"Services"
        }
    ],
    "sg:phone":"+1 450 975 1300",
    "sg:postcode":"H7M 1R5",
    "sg:province":"QC",
    "sg:tags":[
        "crane"
    ],
    "wof:name":"Jmf Grues & Palans Inc",
    "wof:placetype":"venue"
},
  "geometry": {"coordinates":[-73.71286773680001,45.5921859741],"type":"Point"}
}