{
  "type": "Feature",
  "properties": {
    "addr:full":"9851 Av Lausanne Montreal-Nord QC H1H 5A6",
    "addr:housenumber":"9851",
    "addr:postcode":"h1h 5a6",
    "addr:street":"Av Lausanne",
    "iso:country":"CA",
    "sg:address":"9851 Av Lausanne",
    "sg:city":"Montreal-Nord",
    "sg:classifiers":[
        {
            "category":"Manufacturing",
            "subcategory":"Tools & Machinery",
            "type":"Manufacturing & Wholesale Goods"
        }
    ],
    "sg:phone":"+1 514 325 4659",
    "sg:postcode":"H1H 5A6",
    "sg:province":"QC",
    "sg:tags":[
        "machine",
        "shop"
    ],
    "wof:name":"Metric Industries MI Inc",
    "wof:placetype":"venue"
},
  "geometry": {"coordinates":[-73.637154,45.577099],"type":"Point"}
}