{
  "type": "Feature",
  "properties": {
    "addr:full":"169 Rue Jalbert O Thetford Mines QC G6G 7W1",
    "addr:housenumber":"169",
    "addr:postcode":"g6g 7w1",
    "addr:street":"Rue Jalbert O",
    "iso:country":"CA",
    "sg:address":"169 Rue Jalbert O",
    "sg:city":"Thetford Mines",
    "sg:classifiers":[
        {
            "category":"Home & Garden",
            "subcategory":"Household Appliances",
            "type":"Retail Goods"
        }
    ],
    "sg:phone":"+1 418 338 0442",
    "sg:postcode":"G6G 7W1",
    "sg:province":"QC",
    "wof:name":"Richard Service",
    "wof:placetype":"venue"
},
  "geometry": {"coordinates":[-71.311722,46.098686],"type":"Point"}
}