{
  "type": "Feature",
  "properties": {
    "addr:full":"Coquitlam BC V3K 6V2",
    "addr:postcode":"v3k 6v2",
    "iso:country":"CA",
    "sg:city":"Coquitlam",
    "sg:classifiers":[
        {
            "category":"Shopping",
            "subcategory":"Stationery & Office Supplies",
            "type":"Retail Goods"
        }
    ],
    "sg:phone":"+1 604 525 5247",
    "sg:postcode":"V3K 6V2",
    "sg:province":"BC",
    "sg:tags":[
        "protection",
        "check",
        "mach"
    ],
    "wof:name":"F & E Cheque Protectors",
    "wof:placetype":"venue"
},
  "geometry": {"coordinates":[-122.83386993400001,49.2240257263],"type":"Point"}
}