{
  "type": "Feature",
  "properties": {
    "addr:full":"1700 Inkster Blvd Winnipeg MB R2X 2T1",
    "addr:housenumber":"1700",
    "addr:postcode":"r2x 2t1",
    "addr:street":"Inkster Blvd",
    "iso:country":"CA",
    "sg:address":"1700 Inkster Blvd",
    "sg:city":"Winnipeg",
    "sg:classifiers":[
        {
            "category":"Government",
            "subcategory":"Office",
            "type":"Public Place"
        }
    ],
    "sg:phone":"+1 204 983 4492",
    "sg:postcode":"R2X 2T1",
    "sg:province":"MB",
    "wof:name":"Canada National Archives",
    "wof:placetype":"venue"
},
  "geometry": {"coordinates":[-97.186317,49.945721],"type":"Point"}
}