{
  "type": "Feature",
  "properties": {
    "iso:country":"CA",
    "sg:address":"388 Broadway W",
    "sg:city":"Vancouver",
    "sg:classifiers":[
        {
            "category":"Home & Garden",
            "subcategory":"Furniture",
            "type":"Retail Goods"
        }
    ],
    "sg:phone":"+1 604 879 7398",
    "sg:postcode":"V5Y 1R2",
    "sg:province":"BC",
    "sg:tags":[
        "mattress",
        "futon"
    ],
    "wof:name":"Majestic Futon & Frame CO",
    "wof:placetype":"venue"
},
  "geometry": {"coordinates":[-123.112564087,49.2630462646],"type":"Point"}
}