{
  "type": "Feature",
  "properties": {
    "addr:full":"388 Browns Line #A Etobicoke ON M8W 3T8",
    "addr:housenumber":"388",
    "addr:postcode":"m8w 3t8",
    "addr:street":"Browns Line # A",
    "iso:country":"CA",
    "sg:address":"388 Browns Line #A",
    "sg:city":"Etobicoke",
    "sg:classifiers":[
        {
            "category":"Professional",
            "subcategory":"Lawyer & Legal Services",
            "type":"Services"
        }
    ],
    "sg:phone":"+1 416 251 3331",
    "sg:postcode":"M8W 3T8",
    "sg:province":"ON",
    "sg:tags":[
        "attorney"
    ],
    "wof:name":"Trainer, Wayne",
    "wof:placetype":"venue"
},
  "geometry": {"coordinates":[-79.545029,43.600929],"type":"Point"}
}