{
  "type": "Feature",
  "properties": {
    "addr:full":"2159 Rue Saint-Louis Saint-Laurent QC H4M 1P1",
    "addr:housenumber":"2159",
    "addr:postcode":"h4m 1p1",
    "addr:street":"Rue Saint-Louis",
    "iso:country":"CA",
    "sg:address":"2159 Rue Saint-Louis",
    "sg:city":"Saint-Laurent",
    "sg:classifiers":[
        {
            "category":"Wholesale",
            "subcategory":"Meat",
            "type":"Manufacturing & Wholesale Goods"
        }
    ],
    "sg:phone":"+1 514 747 6531",
    "sg:postcode":"H4M 1P1",
    "sg:province":"QC",
    "sg:tags":[
        "butchering"
    ],
    "wof:name":"Glatt's Kosher Self Svc Ltd",
    "wof:placetype":"venue"
},
  "geometry": {"coordinates":[-73.681602,45.501148],"type":"Point"}
}