{
  "type": "Feature",
  "properties": {
    "addr:full":"Dijon QC G0R 1L0",
    "addr:postcode":"g0r 1l0",
    "iso:country":"CA",
    "sg:city":"Dijon",
    "sg:classifiers":[
        {
            "category":"Personal",
            "subcategory":"Beauty Salon",
            "type":"Services"
        }
    ],
    "sg:phone":"+1 418 636 2855",
    "sg:postcode":"G0R 1L0",
    "sg:province":"QC",
    "wof:name":"Salon Carmen Enrg",
    "wof:placetype":"venue"
},
  "geometry": {"coordinates":[-70.48337554930001,46.5102043152],"type":"Point"}
}