{
  "type": "Feature",
  "properties": {
    "addr:full":"34214 97 St Oliver BC V0H 1T0",
    "addr:housenumber":"34214",
    "addr:postcode":"bc v0h 1t0",
    "addr:street":"97 St",
    "iso:country":"CA",
    "sg:address":"34214 97 St",
    "sg:city":"Oliver",
    "sg:classifiers":[
        {
            "category":"Travel",
            "subcategory":"Hotels & Motels",
            "type":"Entertainment"
        }
    ],
    "sg:phone":"+1 250 498 0363",
    "sg:postcode":"V0H 1T0",
    "sg:province":"BC",
    "sg:tags":[
        "breakfast",
        "accommodation",
        "bed"
    ],
    "wof:name":"Villa Sonora Bed & Brkfst",
    "wof:placetype":"venue"
},
  "geometry": {"coordinates":[-119.554085,49.17498],"type":"Point"}
}