{
  "type": "Feature",
  "properties": {
    "addr:full":"808 9th Ave W Nipawin SK S0E 1E0",
    "addr:housenumber":"808",
    "addr:postcode":"s0e 1e0",
    "addr:street":"9Th Ave W Nipawin",
    "iso:country":"CA",
    "sg:address":"808 9th Ave W",
    "sg:city":"Nipawin",
    "sg:classifiers":[
        {
            "category":"Restaurant",
            "type":"Food & Drink"
        }
    ],
    "sg:phone":"+1 306 862 4499",
    "sg:postcode":"S0E 1E0",
    "sg:province":"SK",
    "wof:name":"A & W Family Restaurant",
    "wof:placetype":"venue"
},
  "geometry": {"coordinates":[-104.02628300000001,53.356743],"type":"Point"}
}