{
  "type": "Feature",
  "properties": {
    "iso:country":"CA",
    "sg:address":"7098 Rama Rd",
    "sg:city":"Longford Mills",
    "sg:classifiers":[
        {
            "category":"Travel",
            "subcategory":"Campground",
            "type":"Entertainment"
        }
    ],
    "sg:phone":"+1 705 689 5572",
    "sg:postcode":"L0K 1L0",
    "sg:province":"ON",
    "sg:tags":[
        "camp"
    ],
    "wof:name":"Ontario Educational Leadership",
    "wof:placetype":"venue"
},
  "geometry": {"coordinates":[-79.34963999999999,44.675449],"type":"Point"}
}