{
  "type": "Feature",
  "properties": {
    "addr:full":"15 Rue Costigan Edmundston NB E3V 1W7",
    "addr:housenumber":"15",
    "addr:postcode":"e3v 1w7",
    "addr:street":"Rue Costigan",
    "iso:country":"CA",
    "sg:address":"15 Rue Costigan",
    "sg:city":"Edmundston",
    "sg:classifiers":[
        {
            "category":"Manufacturing",
            "subcategory":"Printing",
            "type":"Manufacturing & Wholesale Goods"
        }
    ],
    "sg:phone":"+1 506 739 7769",
    "sg:postcode":"E3V 1W7",
    "sg:province":"NB",
    "sg:tags":[
        "printer"
    ],
    "wof:name":"Imprimerie Excel Inc",
    "wof:placetype":"venue"
},
  "geometry": {"coordinates":[-68.326622,47.364559],"type":"Point"}
}