{
  "type": "Feature",
  "properties": {
    "iso:country":"CA",
    "sg:address":"5775 Av Andover",
    "sg:city":"Mont-Royal",
    "sg:classifiers":[
        {
            "category":"Wholesale",
            "subcategory":"Hardware",
            "type":"Manufacturing & Wholesale Goods"
        }
    ],
    "sg:phone":"+1 514 341 6921",
    "sg:postcode":"H4T 1H6",
    "sg:province":"QC",
    "wof:name":"Brands International Inc",
    "wof:placetype":"venue"
},
  "geometry": {"coordinates":[-73.677467,45.488499],"type":"Point"}
}