{
  "type": "Feature",
  "properties": {
    "addr:full":"PO Box 28098 Rpo East Kelowna Kelowna BC V1W 4A6",
    "addr:housenumber":"po box",
    "addr:postcode":"28098;v1w 4a6",
    "iso:country":"CA",
    "sg:address":"PO Box 28098 Rpo East Kelowna",
    "sg:city":"Kelowna",
    "sg:classifiers":[
        {
            "category":"Professional",
            "subcategory":"Management & Consulting",
            "type":"Services"
        }
    ],
    "sg:phone":"+1 250 717 1898",
    "sg:postcode":"V1W 4A6",
    "sg:province":"BC",
    "sg:tags":[
        "agricultural",
        "consultant"
    ],
    "wof:name":"Crop Health Advising",
    "wof:placetype":"venue"
},
  "geometry": {"coordinates":[-119.49659699999999,49.886814],"type":"Point"}
}