{
  "type": "Feature",
  "properties": {
    "addr:full":"40 Hyslop St Chatham ON N7M 4X1",
    "addr:housenumber":"40",
    "addr:postcode":"n7m 4x1",
    "addr:street":"Hyslop St",
    "iso:country":"CA",
    "sg:address":"40 Hyslop St",
    "sg:city":"Chatham",
    "sg:classifiers":[
        {
            "category":"Retail",
            "subcategory":"Auto Repair",
            "type":"Services"
        }
    ],
    "sg:phone":"+1 519 351 8181",
    "sg:postcode":"N7M 4X1",
    "sg:province":"ON",
    "sg:tags":[
        "repairing",
        "automobile"
    ],
    "wof:name":"Dave's Fix It Shop",
    "wof:placetype":"venue"
},
  "geometry": {"coordinates":[-82.16935700000001,42.403755],"type":"Point"}
}