{
  "type": "Feature",
  "properties": {
    "addr:full":"979 Fennell Ave E Hamilton ON L8T 1R1",
    "addr:housenumber":"979",
    "addr:postcode":"l8t 1r1",
    "addr:street":"Fennell Ave E",
    "iso:country":"CA",
    "sg:address":"979 Fennell Ave E",
    "sg:city":"Hamilton",
    "sg:classifiers":[
        {
            "category":"Shopping",
            "subcategory":"Clothing, Apparel, & Fashions",
            "type":"Retail Goods"
        }
    ],
    "sg:phone":"+1 905 383 4722",
    "sg:postcode":"L8T 1R1",
    "sg:province":"ON",
    "wof:name":"Reitmans",
    "wof:placetype":"venue"
},
  "geometry": {"coordinates":[-79.837547,43.227768],"type":"Point"}
}