{
  "type": "Feature",
  "properties": {
    "iso:country":"CA",
    "sg:city":"North York",
    "sg:classifiers":[
        {
            "category":"Professional",
            "subcategory":"Credit Reporting & Collection",
            "type":"Services"
        }
    ],
    "sg:phone":"+1 416 739 6500",
    "sg:postcode":"M3J 3H7",
    "sg:province":"ON",
    "sg:tags":[
        "agency"
    ],
    "wof:name":"Shellco Credit Systems Ltd",
    "wof:placetype":"venue"
},
  "geometry": {"coordinates":[-79.4763717651,43.7668800354],"type":"Point"}
}