{
  "type": "Feature",
  "properties": {
    "addr:full":"2170 Parkcrest Ave Kamloops BC V2B 4Y1",
    "addr:housenumber":"2170",
    "addr:postcode":"bc v2b 4y1",
    "addr:street":"Parkcrest Ave",
    "iso:country":"CA",
    "sg:address":"2170 Parkcrest Ave",
    "sg:city":"Kamloops",
    "sg:classifiers":[
        {
            "category":"Education",
            "subcategory":"School",
            "type":"Public Place"
        }
    ],
    "sg:phone":"+1 250 554 2368",
    "sg:postcode":"V2B 4Y1",
    "sg:province":"BC",
    "wof:name":"Parkcrest Elementary School",
    "wof:placetype":"venue"
},
  "geometry": {"coordinates":[-120.406548,50.708031],"type":"Point"}
}