{
  "type": "Feature",
  "properties": {
    "addr:full":"1200 Pembroke St W Pembroke ON K8A 7T1",
    "addr:housenumber":"1200",
    "addr:postcode":"k8a 7t1",
    "addr:street":"Pembroke St W",
    "iso:country":"CA",
    "sg:address":"1200 Pembroke St W",
    "sg:city":"Pembroke",
    "sg:classifiers":[
        {
            "category":"Shopping",
            "subcategory":"Discount & Variety Stores",
            "type":"Retail Goods"
        }
    ],
    "sg:phone":"+1 613 732 8251",
    "sg:postcode":"K8A 7T1",
    "sg:province":"ON",
    "wof:name":"Kim's Korner",
    "wof:placetype":"venue"
},
  "geometry": {"coordinates":[-77.145729,45.832096],"type":"Point"}
}