{
  "type": "Feature",
  "properties": {
    "addr:full":"1209 Rue Gilford Montreal QC H2J 1R1",
    "addr:housenumber":"1209",
    "addr:postcode":"h2j 1r1",
    "addr:street":"Rue Gilford",
    "iso:country":"CA",
    "sg:address":"1209 Rue Gilford",
    "sg:city":"Montreal",
    "sg:classifiers":[
        {
            "category":"Shopping",
            "type":"Retail Goods"
        }
    ],
    "sg:phone":"+1 514 527 0481",
    "sg:postcode":"H2J 1R1",
    "sg:province":"QC",
    "sg:tags":[
        "picture",
        "frame"
    ],
    "wof:name":"Encadrement Savoie Inc",
    "wof:placetype":"venue"
},
  "geometry": {"coordinates":[-73.5820236206,45.5305480957],"type":"Point"}
}