{
  "type": "Feature",
  "properties": {
    "addr:full":"10 Dundas St W Belleville ON K8P 1A1",
    "addr:housenumber":"10",
    "addr:postcode":"k8p 1a1",
    "addr:street":"Dundas St W",
    "iso:country":"CA",
    "sg:address":"10 Dundas St W",
    "sg:city":"Belleville",
    "sg:classifiers":[
        {
            "category":"Real Estate",
            "subcategory":"Architect",
            "type":"Services"
        }
    ],
    "sg:phone":"+1 613 962 9995",
    "sg:postcode":"K8P 1A1",
    "sg:province":"ON",
    "wof:name":"W R White Architect Ltd",
    "wof:placetype":"venue"
},
  "geometry": {"coordinates":[-77.386009,44.160343],"type":"Point"}
}