{
  "type": "Feature",
  "properties": {
    "addr:full":"Montreal QC H3G 2S1",
    "addr:postcode":"h3g 2s1",
    "iso:country":"CA",
    "sg:city":"Montreal",
    "sg:classifiers":[
        {
            "category":"Travel",
            "subcategory":"Travel Agent",
            "type":"Entertainment"
        }
    ],
    "sg:phone":"+1 514 861 5111",
    "sg:postcode":"H3G 2S1",
    "sg:province":"QC",
    "sg:tags":[
        "agency",
        "bureau"
    ],
    "wof:name":"Agence DE Voyages Caa Travel",
    "wof:placetype":"venue"
},
  "geometry": {"coordinates":[-73.5728607178,45.4978294373],"type":"Point"}
}