{
  "type": "Feature",
  "properties": {
    "addr:full":"12 Rue Gamble E Rouyn-Noranda QC J9X 3B7",
    "addr:housenumber":"12",
    "addr:postcode":"j9x 3b7",
    "addr:street":"Rue Gamble E",
    "iso:country":"CA",
    "sg:address":"12 Rue Gamble E",
    "sg:city":"Rouyn-Noranda",
    "sg:classifiers":[
        {
            "category":"Health Services",
            "subcategory":"Doctor",
            "type":"Services"
        }
    ],
    "sg:phone":"+1 819 764 9441",
    "sg:postcode":"J9X 3B7",
    "sg:province":"QC",
    "sg:tags":[
        "clinic"
    ],
    "wof:name":"Clinique Medicale Du Cuivre",
    "wof:placetype":"venue"
},
  "geometry": {"coordinates":[-79.019661,48.239796],"type":"Point"}
}