{
  "type": "Feature",
  "properties": {
    "addr:full":"Scarborough ON M1V 5A2",
    "addr:postcode":"m1v 5a2",
    "iso:country":"CA",
    "sg:city":"Scarborough",
    "sg:classifiers":[
        {
            "category":"Wholesale",
            "subcategory":"Office Equipment",
            "type":"Manufacturing & Wholesale Goods"
        }
    ],
    "sg:phone":"+1 416 293 1977",
    "sg:postcode":"M1V 5A2",
    "sg:province":"ON",
    "sg:tags":[
        "machine",
        "duplicating",
        "copying"
    ],
    "wof:name":"Office Machines Sales Rental",
    "wof:placetype":"venue"
},
  "geometry": {"coordinates":[-79.292175293,43.806804657],"type":"Point"}
}