{
  "type": "Feature",
  "properties": {
    "addr:full":"3895 Lawrence Ave E Scarborough ON M1G 3T3",
    "addr:housenumber":"3895",
    "addr:postcode":"m1g 3t3",
    "addr:street":"Lawrence Ave E",
    "iso:country":"CA",
    "sg:address":"3895 Lawrence Ave E",
    "sg:city":"Scarborough",
    "sg:classifiers":[
        {
            "category":"Social Services",
            "subcategory":"Child Care",
            "type":"Services"
        }
    ],
    "sg:phone":"+1 416 431 3898",
    "sg:postcode":"M1G 3T3",
    "sg:province":"ON",
    "wof:name":"Future Stars Child Care",
    "wof:placetype":"venue"
},
  "geometry": {"coordinates":[-79.2060699463,43.7638206482],"type":"Point"}
}