{
  "type": "Feature",
  "properties": {
    "addr:full":"160 Hastings St E Vancouver BC V6A 1N4",
    "addr:housenumber":"160",
    "addr:postcode":"v6a 1n4",
    "addr:street":"Hastings St E",
    "iso:country":"CA",
    "sg:address":"160 Hastings St E",
    "sg:city":"Vancouver",
    "sg:classifiers":[
        {
            "category":"Travel",
            "subcategory":"Hotels & Motels",
            "type":"Entertainment"
        }
    ],
    "sg:phone":"+1 604 684 4924",
    "sg:postcode":"V6A 1N4",
    "sg:province":"BC",
    "wof:name":"Regent Hotel",
    "wof:placetype":"venue"
},
  "geometry": {"coordinates":[-123.100739,49.281227],"type":"Point"}
}