{
  "type": "Feature",
  "properties": {
    "addr:full":"1664 Jane St York ON M9N 2S1",
    "addr:housenumber":"1664",
    "addr:postcode":"m9n 2s1",
    "addr:street":"Jane St",
    "iso:country":"CA",
    "sg:address":"1664 Jane St",
    "sg:city":"York",
    "sg:classifiers":[
        {
            "category":"Wholesale",
            "subcategory":"Groceries",
            "type":"Manufacturing & Wholesale Goods"
        }
    ],
    "sg:phone":"+1 416 249 4022",
    "sg:postcode":"M9N 2S1",
    "sg:province":"ON",
    "sg:tags":[
        "pasta"
    ],
    "wof:name":"Continental Noodles CO",
    "wof:placetype":"venue"
},
  "geometry": {"coordinates":[-79.5037155151,43.7019767761],"type":"Point"}
}