{
  "type": "Feature",
  "properties": {
    "addr:full":"681 Boul Saint-Laurent E Louiseville QC J5V 1J1",
    "addr:housenumber":"681",
    "addr:postcode":"j5v 1j1",
    "addr:street":"Boul Saint-Laurent E",
    "iso:country":"CA",
    "sg:address":"681 Boul Saint-Laurent E",
    "sg:city":"Louiseville",
    "sg:classifiers":[
        {
            "category":"Home & Garden",
            "subcategory":"Household Appliances",
            "type":"Retail Goods"
        }
    ],
    "sg:phone":"+1 819 228 0395",
    "sg:postcode":"J5V 1J1",
    "sg:province":"QC",
    "wof:name":"Lemay Electro-Menagers",
    "wof:placetype":"venue"
},
  "geometry": {"coordinates":[-72.917168,46.258224],"type":"Point"}
}