{
  "type": "Feature",
  "properties": {
    "addr:full":"5319 Av Clarendon Laval QC H7W 4Z5",
    "addr:housenumber":"5319",
    "addr:postcode":"h7w 4z5",
    "addr:street":"Av Clarendon",
    "iso:country":"CA",
    "sg:address":"5319 Av Clarendon",
    "sg:city":"Laval",
    "sg:classifiers":[
        {
            "category":"Building & Trades",
            "subcategory":"Electrical",
            "type":"Services"
        }
    ],
    "sg:phone":"+1 450 681 5084",
    "sg:postcode":"H7W 4Z5",
    "sg:province":"QC",
    "sg:tags":[
        "electric",
        "contractor"
    ],
    "wof:name":"Entreprises D'Electricite Inc",
    "wof:placetype":"venue"
},
  "geometry": {"coordinates":[-73.77774047849999,45.5310516357],"type":"Point"}
}