{
  "type": "Feature",
  "properties": {
    "addr:full":"855 College St Toronto ON M6H 1A1",
    "addr:housenumber":"855",
    "addr:postcode":"m6h 1a1",
    "addr:street":"College St",
    "iso:country":"CA",
    "sg:address":"855 College St",
    "sg:city":"Toronto",
    "sg:classifiers":[
        {
            "category":"Building & Trades",
            "subcategory":"Cleaning & Sanitation",
            "type":"Services"
        }
    ],
    "sg:phone":"+1 416 534 5611",
    "sg:postcode":"M6H 1A1",
    "sg:province":"ON",
    "sg:tags":[
        "removal",
        "snow",
        "landscape",
        "contractor"
    ],
    "wof:name":"Global Snow Plowing",
    "wof:placetype":"venue"
},
  "geometry": {"coordinates":[-79.423401,43.654106],"type":"Point"}
}