{
  "type": "Feature",
  "properties": {
    "addr:full":"7155 Rte Transcanadienne Saint-Laurent QC H4T 1A2",
    "addr:housenumber":"7155",
    "addr:postcode":"h4t 1a2",
    "addr:street":"Rte Transcanadienne",
    "iso:country":"CA",
    "sg:address":"7155 Rte Transcanadienne",
    "sg:city":"Saint-Laurent",
    "sg:classifiers":[
        {
            "category":"Travel",
            "subcategory":"Campground",
            "type":"Entertainment"
        }
    ],
    "sg:phone":"+1 514 595 1300",
    "sg:postcode":"H4T 1A2",
    "sg:province":"QC",
    "sg:tags":[
        "game",
        "adventure",
        "activity"
    ],
    "wof:name":"Paintball T2",
    "wof:placetype":"venue"
},
  "geometry": {"coordinates":[-73.702796936,45.4913024902],"type":"Point"}
}