{
  "type": "Feature",
  "properties": {
    "addr:full":"Lethbridge AB T1K 2S2",
    "addr:postcode":"t1k 2s2",
    "iso:country":"CA",
    "sg:city":"Lethbridge",
    "sg:classifiers":[
        {
            "category":"Food & Beverages",
            "subcategory":"Specialty",
            "type":"Retail Goods"
        }
    ],
    "sg:phone":"+1 403 327 4994",
    "sg:postcode":"T1K 2S2",
    "sg:province":"AB",
    "sg:tags":[
        "health",
        "diet"
    ],
    "wof:name":"Oliver Health Foods Ltd",
    "wof:placetype":"venue"
},
  "geometry": {"coordinates":[-112.79939299999999,49.672192],"type":"Point"}
}