{
  "type": "Feature",
  "properties": {
    "addr:full":"5131 Longwoods Rd Appin ON N0L 1A0",
    "addr:housenumber":"5131",
    "addr:postcode":"n0l 1a0",
    "addr:street":"Longwoods Rd",
    "iso:country":"CA",
    "sg:address":"5131 Longwoods Rd",
    "sg:city":"Appin",
    "sg:classifiers":[
        {
            "category":"Food & Beverages",
            "subcategory":"Groceries & Convenience Stores",
            "type":"Retail Goods"
        }
    ],
    "sg:phone":"+1 519 289 5445",
    "sg:postcode":"N0L 1A0",
    "sg:province":"ON",
    "sg:tags":[
        "grocer"
    ],
    "wof:name":"Muscutt's Country Store",
    "wof:placetype":"venue"
},
  "geometry": {"coordinates":[-81.650047,42.795712],"type":"Point"}
}