{
  "type": "Feature",
  "properties": {
    "addr:full":"Oakville ON L6J 1J5",
    "addr:postcode":"l6j 1j5",
    "iso:country":"CA",
    "sg:city":"Oakville",
    "sg:classifiers":[
        {
            "category":"Social Services",
            "type":"Services"
        }
    ],
    "sg:phone":"+1 905 842 1332",
    "sg:postcode":"L6J 1J5",
    "sg:province":"ON",
    "sg:tags":[
        "counselor",
        "marriage",
        "family"
    ],
    "wof:name":"Centre For Personal Growth",
    "wof:placetype":"venue"
},
  "geometry": {"coordinates":[-79.6652755737,43.4487419128],"type":"Point"}
}