{
  "type": "Feature",
  "properties": {
    "iso:country":"CA",
    "sg:address":"2200 South Rd",
    "sg:city":"Gabriola",
    "sg:classifiers":[
        {
            "category":"Recreation",
            "type":"Entertainment"
        }
    ],
    "sg:phone":"+1 250 247 9292",
    "sg:postcode":"V0R 1X7",
    "sg:province":"BC",
    "sg:tags":[
        "hall",
        "auditorium"
    ],
    "wof:name":"Gabriola Island Community Hall",
    "wof:placetype":"venue"
},
  "geometry": {"coordinates":[-123.753684998,49.1337280273],"type":"Point"}
}