{
  "type": "Feature",
  "properties": {
    "addr:full":"136 O'Connor St Ottawa ON K2P 2G7",
    "addr:housenumber":"136",
    "addr:postcode":"k2p 2g7",
    "addr:street":"O'Connor St",
    "iso:country":"CA",
    "sg:address":"136 O'Connor St",
    "sg:city":"Ottawa",
    "sg:classifiers":[
        {
            "category":"Shopping",
            "subcategory":"Stationery & Office Supplies",
            "type":"Retail Goods"
        }
    ],
    "sg:phone":"+1 613 236 6698",
    "sg:postcode":"K2P 2G7",
    "sg:province":"ON",
    "wof:name":"Art Woods Office Supplies Inc",
    "wof:placetype":"venue"
},
  "geometry": {"coordinates":[-75.698898,45.421761],"type":"Point"}
}