{
  "type": "Feature",
  "properties": {
    "iso:country":"CA",
    "sg:city":"Comox",
    "sg:classifiers":[
        {
            "category":"Banks & Credit Unions",
            "subcategory":"Investment Brokerage",
            "type":"Services"
        }
    ],
    "sg:phone":"+1 250 339 0529",
    "sg:postcode":"V9M 3M7",
    "sg:province":"BC",
    "wof:name":"Edward Jones",
    "wof:placetype":"venue"
},
  "geometry": {"coordinates":[-124.928749084,49.6743469238],"type":"Point"}
}