{
  "type": "Feature",
  "properties": {
    "addr:full":"Toronto ON M4N 3N1",
    "addr:postcode":"m4n 3n1",
    "iso:country":"CA",
    "sg:city":"Toronto",
    "sg:classifiers":[
        {
            "category":"Social Services",
            "type":"Services"
        }
    ],
    "sg:phone":"+1 416 487 3613",
    "sg:postcode":"M4N 3N1",
    "sg:province":"ON",
    "sg:tags":[
        "counselor",
        "marriage",
        "family"
    ],
    "wof:name":"Institute of Family Living",
    "wof:placetype":"venue"
},
  "geometry": {"coordinates":[-79.40245819090001,43.7254180908],"type":"Point"}
}