{
  "type": "Feature",
  "properties": {
    "addr:full":"1330 Exmouth St Sarnia ON N7S 3X9",
    "addr:housenumber":"1330",
    "addr:postcode":"n7s 3x9",
    "addr:street":"Exmouth St",
    "iso:country":"CA",
    "sg:address":"1330 Exmouth St",
    "sg:city":"Sarnia",
    "sg:classifiers":[
        {
            "category":"Food & Beverages",
            "subcategory":"Liquor & Beverages",
            "type":"Retail Goods"
        }
    ],
    "sg:phone":"+1 519 542 6836",
    "sg:postcode":"N7S 3X9",
    "sg:province":"ON",
    "sg:tags":[
        "store"
    ],
    "wof:name":"Liquor Control Board of Ont",
    "wof:placetype":"venue"
},
  "geometry": {"coordinates":[-82.356026,42.984638],"type":"Point"}
}