{
  "type": "Feature",
  "properties": {
    "addr:full":"5671 Ch Saint-Francois Saint-Laurent QC H4S 1W6",
    "addr:housenumber":"5671",
    "addr:postcode":"h4s 1w6",
    "addr:street":"Ch Saint-Francois",
    "iso:country":"CA",
    "sg:address":"5671 Ch Saint-Francois",
    "sg:city":"Saint-Laurent",
    "sg:classifiers":[
        {
            "category":"Wholesale",
            "subcategory":"Construction Materials",
            "type":"Manufacturing & Wholesale Goods"
        }
    ],
    "sg:phone":"+1 514 863 8055",
    "sg:postcode":"H4S 1W6",
    "sg:province":"QC",
    "sg:tags":[
        "frame",
        "industrial",
        "door"
    ],
    "wof:name":"Projet DE Portes Cr Enrg",
    "wof:placetype":"venue"
},
  "geometry": {"coordinates":[-73.7375335693,45.4877891541],"type":"Point"}
}