{
  "type": "Feature",
  "properties": {
    "addr:full":"10 Rue DE LA Montagne Sainte-Claire QC G0R 2V0",
    "addr:housenumber":"10",
    "addr:postcode":"g0r 2v0",
    "addr:street":"Rue De La Montagne",
    "iso:country":"CA",
    "sg:address":"10 Rue DE LA Montagne",
    "sg:city":"Sainte-Claire",
    "sg:classifiers":[
        {
            "category":"Bars & Pubs",
            "type":"Food & Drink"
        }
    ],
    "sg:phone":"+1 418 883 2222",
    "sg:postcode":"G0R 2V0",
    "sg:province":"QC",
    "wof:name":"Bar 203",
    "wof:placetype":"venue"
},
  "geometry": {"coordinates":[-70.85237100000001,46.600094],"type":"Point"}
}