{
  "type": "Feature",
  "properties": {
    "addr:full":"20395 Lougheed Hwy # 57 Maple Ridge BC V2X 2P9",
    "addr:housenumber":"20395",
    "addr:postcode":"v2x 2p9",
    "addr:street":"Lougheed Hwy # 57",
    "iso:country":"CA",
    "sg:address":"20395 Lougheed Hwy # 57",
    "sg:city":"Maple Ridge",
    "sg:classifiers":[
        {
            "category":"Retail",
            "subcategory":"Laundry & Dry Cleaning",
            "type":"Services"
        }
    ],
    "sg:phone":"+1 604 460 0334",
    "sg:postcode":"V2X 2P9",
    "sg:province":"BC",
    "sg:tags":[
        "cleaners"
    ],
    "wof:name":"NU-Crescent Cleaners",
    "wof:placetype":"venue"
},
  "geometry": {"coordinates":[-122.65646362299999,49.2191505432],"type":"Point"}
}