{
  "type": "Feature",
  "properties": {
    "iso:country":"CA",
    "sg:address":"2100 Av DE Marlowe",
    "sg:city":"Montreal",
    "sg:classifiers":[
        {
            "category":"Health Services",
            "subcategory":"Health Practitioner",
            "type":"Services"
        }
    ],
    "sg:phone":"+1 514 481 1000",
    "sg:postcode":"H4A 3L5",
    "sg:province":"QC",
    "sg:tags":[
        "homeopath"
    ],
    "wof:name":"Abadian Ramtin",
    "wof:placetype":"venue"
},
  "geometry": {"coordinates":[-73.60623168950001,45.4744720459],"type":"Point"}
}