{
  "type": "Feature",
  "properties": {
    "iso:country":"CA",
    "sg:address":"14 Rue Des Emeraudes",
    "sg:city":"Levis",
    "sg:classifiers":[
        {
            "category":"Autos & Motor Vehicles",
            "subcategory":"Auto Supplies",
            "type":"Retail Goods"
        }
    ],
    "sg:phone":"+1 418 837 2467",
    "sg:postcode":"G6W 6Y6",
    "sg:province":"QC",
    "sg:tags":[
        "tire"
    ],
    "wof:name":"Centre Du Pneu St-David Inc",
    "wof:placetype":"venue"
},
  "geometry": {"coordinates":[-71.1983718872,46.7715187073],"type":"Point"}
}