{
  "type": "Feature",
  "properties": {
    "iso:country":"CA",
    "sg:address":"333 Ontario St",
    "sg:city":"St Catharines",
    "sg:classifiers":[
        {
            "category":"Restaurant",
            "type":"Food & Drink"
        }
    ],
    "sg:phone":"+1 905 688 3363",
    "sg:postcode":"L2R 5L3",
    "sg:province":"ON",
    "wof:name":"Tim Hortons",
    "wof:placetype":"venue"
},
  "geometry": {"coordinates":[-79.264854,43.170612],"type":"Point"}
}