{
  "type": "Feature",
  "properties": {
    "iso:country":"CA",
    "sg:address":"1020 Topsail Rd",
    "sg:city":"Mount Pearl",
    "sg:classifiers":[
        {
            "category":"Food & Beverages",
            "subcategory":"Groceries & Convenience Stores",
            "type":"Retail Goods"
        }
    ],
    "sg:phone":"+1 709 364 1811",
    "sg:postcode":"A1N 5E5",
    "sg:province":"NL",
    "wof:name":"Needs Pearlview",
    "wof:placetype":"venue"
},
  "geometry": {"coordinates":[-52.8085021973,47.5250549316],"type":"Point"}
}