{
  "type": "Feature",
  "properties": {
    "addr:full":"387 Av Lariviere Rouyn-Noranda QC J9X 4H7",
    "addr:housenumber":"387",
    "addr:postcode":"j9x 4h7",
    "addr:street":"Av Lariviere",
    "iso:country":"CA",
    "sg:address":"387 Av Lariviere",
    "sg:city":"Rouyn-Noranda",
    "sg:classifiers":[
        {
            "category":"Home & Garden",
            "subcategory":"Garden Supply",
            "type":"Retail Goods"
        }
    ],
    "sg:phone":"+1 819 762 4414",
    "sg:postcode":"J9X 4H7",
    "sg:province":"QC",
    "sg:tags":[
        "engine",
        "lawn",
        "mower"
    ],
    "wof:name":"Atelier Serge Vachon",
    "wof:placetype":"venue"
},
  "geometry": {"coordinates":[-79.014465,48.232056],"type":"Point"}
}