{
  "type": "Feature",
  "properties": {
    "addr:full":"85 Rue Victoria Edmundston NB E3V 2H4",
    "addr:housenumber":"85",
    "addr:postcode":"e3v 2h4",
    "addr:street":"Rue Victoria",
    "iso:country":"CA",
    "sg:address":"85 Rue Victoria",
    "sg:city":"Edmundston",
    "sg:classifiers":[
        {
            "category":"Social Services",
            "type":"Services"
        }
    ],
    "sg:phone":"+1 506 735 6313",
    "sg:postcode":"E3V 2H4",
    "sg:province":"NB",
    "sg:tags":[
        "organization",
        "welfare"
    ],
    "wof:name":"Atelier Rado Inc",
    "wof:placetype":"venue"
},
  "geometry": {"coordinates":[-68.32218899999999,47.365879],"type":"Point"}
}