{
  "type": "Feature",
  "properties": {
    "addr:full":"296 Oliver St Williams Lake BC V2G 1M1",
    "addr:housenumber":"296",
    "addr:postcode":"v2g 1m1",
    "addr:street":"Oliver St",
    "iso:country":"CA",
    "sg:address":"296 Oliver St",
    "sg:city":"Williams Lake",
    "sg:classifiers":[
        {
            "category":"Shopping",
            "subcategory":"Computers & Home Electronics",
            "type":"Retail Goods"
        }
    ],
    "sg:phone":"+1 250 392 6550",
    "sg:postcode":"V2G 1M1",
    "sg:province":"BC",
    "sg:tags":[
        "high",
        "fidelity",
        "stereophonic"
    ],
    "wof:name":"Stereo Plus",
    "wof:placetype":"venue"
},
  "geometry": {"coordinates":[-122.14258599999999,52.128998],"type":"Point"}
}