{
  "type": "Feature",
  "properties": {
    "addr:full":"5853 Boul Des Rossignols Laval QC H7L 4Z2",
    "addr:housenumber":"5853",
    "addr:postcode":"h7l 4z2",
    "addr:street":"Boul Des Rossignols",
    "iso:country":"CA",
    "sg:address":"5853 Boul Des Rossignols",
    "sg:city":"Laval",
    "sg:classifiers":[
        {
            "category":"Building & Trades",
            "subcategory":"Electrical",
            "type":"Services"
        }
    ],
    "sg:phone":"+1 450 625 1373",
    "sg:postcode":"H7L 4Z2",
    "sg:province":"QC",
    "sg:tags":[
        "electric",
        "contractor"
    ],
    "wof:name":"E D Electrique Inc",
    "wof:placetype":"venue"
},
  "geometry": {"coordinates":[-73.77171300000001,45.590664],"type":"Point"}
}