{
  "type": "Feature",
  "properties": {
    "addr:full":"247 Bridgeland Ave North York ON M6A 1Y7",
    "addr:housenumber":"247",
    "addr:postcode":"m6a 1y7",
    "addr:street":"Bridgeland Ave",
    "iso:country":"CA",
    "sg:address":"247 Bridgeland Ave",
    "sg:city":"North York",
    "sg:classifiers":[
        {
            "category":"Shopping",
            "subcategory":"Clothing, Apparel, & Fashions",
            "type":"Retail Goods"
        }
    ],
    "sg:phone":"+1 416 784 1537",
    "sg:postcode":"M6A 1Y7",
    "sg:province":"ON",
    "sg:tags":[
        "furnishing"
    ],
    "wof:name":"Suit Club",
    "wof:placetype":"venue"
},
  "geometry": {"coordinates":[-79.46790300000001,43.724419],"type":"Point"}
}