{
  "type": "Feature",
  "properties": {
    "addr:full":"30 Ropewalk Lane St. John's NL A1E 5T2",
    "addr:housenumber":"30",
    "addr:postcode":"a1e 5t2",
    "addr:street":"Ropewalk Lane",
    "iso:country":"CA",
    "sg:address":"30 Ropewalk Lane",
    "sg:city":"St. John's",
    "sg:classifiers":[
        {
            "category":"Shopping",
            "type":"Retail Goods"
        }
    ],
    "sg:phone":"+1 709 738 2787",
    "sg:postcode":"A1E 5T2",
    "sg:province":"NL",
    "sg:tags":[
        "art",
        "gallery",
        "dealer"
    ],
    "wof:name":"Art Emporium",
    "wof:placetype":"venue"
},
  "geometry": {"coordinates":[-52.735123,47.555325],"type":"Point"}
}