{
  "type": "Feature",
  "properties": {
    "addr:full":"1893 Av Du Mont-Royal E Montreal QC H2H 1J3",
    "addr:housenumber":"1893",
    "addr:postcode":"h2h 1j3",
    "addr:street":"Av Du Mont-Royal E",
    "iso:country":"CA",
    "sg:address":"1893 Av Du Mont-Royal E",
    "sg:city":"Montreal",
    "sg:classifiers":[
        {
            "category":"Shopping",
            "subcategory":"Florist",
            "type":"Retail Goods"
        }
    ],
    "sg:phone":"+1 514 522 6555",
    "sg:postcode":"H2H 1J3",
    "sg:province":"QC",
    "wof:name":"DE Feuilles En Fleurs",
    "wof:placetype":"venue"
},
  "geometry": {"coordinates":[-73.573868,45.533886],"type":"Point"}
}