{
  "type": "Feature",
  "properties": {
    "addr:full":"12 1E Av Vllge Saint-Albert QC J0A 1E0",
    "addr:housenumber":"12",
    "addr:postcode":"j0a 1e0",
    "addr:street":"1E Av Vllge",
    "iso:country":"CA",
    "sg:address":"12 1E Av Vllge",
    "sg:city":"Saint-Albert",
    "sg:classifiers":[
        {
            "category":"Social Services",
            "subcategory":"Child Care",
            "type":"Services"
        }
    ],
    "sg:phone":"+1 819 353 1262",
    "sg:postcode":"J0A 1E0",
    "sg:province":"QC",
    "wof:name":"Garderie Les Petits Charmeurs",
    "wof:placetype":"venue"
},
  "geometry": {"coordinates":[-72.094666,46.012985],"type":"Point"}
}