{
  "type": "Feature",
  "properties": {
    "addr:full":"533 Pefferlaw Rd Pefferlaw ON L0E 1N0",
    "addr:housenumber":"533",
    "addr:postcode":"l0e 1n0",
    "addr:street":"Pefferlaw Rd",
    "iso:country":"CA",
    "sg:address":"533 Pefferlaw Rd",
    "sg:city":"Pefferlaw",
    "sg:classifiers":[
        {
            "category":"Building & Trades",
            "subcategory":"Construction",
            "type":"Services"
        }
    ],
    "sg:phone":"+1 705 437 3983",
    "sg:postcode":"L0E 1N0",
    "sg:province":"ON",
    "sg:tags":[
        "pole",
        "line",
        "contractor"
    ],
    "wof:name":"Utility Surplus & Sales",
    "wof:placetype":"venue"
},
  "geometry": {"coordinates":[-79.2163314819,44.3252258301],"type":"Point"}
}