{
  "type": "Feature",
  "properties": {
    "addr:full":"Toronto ON M5R 2N4",
    "addr:postcode":"m5r 2n4",
    "iso:country":"CA",
    "sg:city":"Toronto",
    "sg:classifiers":[
        {
            "category":"Health Services",
            "subcategory":"Doctor",
            "type":"Services"
        }
    ],
    "sg:phone":"+1 416 921 5471",
    "sg:postcode":"M5R 2N4",
    "sg:province":"ON",
    "sg:tags":[
        "dentist"
    ],
    "wof:name":"Marquis, S F DDS",
    "wof:placetype":"venue"
},
  "geometry": {"coordinates":[-79.4007797241,43.6693916321],"type":"Point"}
}