{
  "type": "Feature",
  "properties": {
    "addr:full":"Ottawa ON K1Y 3B2",
    "addr:postcode":"k1y 3b2",
    "iso:country":"CA",
    "sg:city":"Ottawa",
    "sg:classifiers":[
        {
            "category":"Banks & Credit Unions",
            "subcategory":"Investment Brokerage",
            "type":"Services"
        }
    ],
    "sg:phone":"+1 613 722 1854",
    "sg:postcode":"K1Y 3B2",
    "sg:province":"ON",
    "sg:tags":[
        "advisory",
        "financial"
    ],
    "wof:name":"Armstrong & Quaile Assoc Inc",
    "wof:placetype":"venue"
},
  "geometry": {"coordinates":[-75.736435,45.398659],"type":"Point"}
}