{
  "type": "Feature",
  "properties": {
    "addr:full":"37 Yarmouth St Guelph ON N1H 4G2",
    "addr:housenumber":"37",
    "addr:postcode":"n1h 4g2",
    "addr:street":"Yarmouth St",
    "iso:country":"CA",
    "sg:address":"37 Yarmouth St",
    "sg:city":"Guelph",
    "sg:classifiers":[
        {
            "category":"Restaurant",
            "type":"Food & Drink"
        }
    ],
    "sg:phone":"+1 519 822 4465",
    "sg:postcode":"N1H 4G2",
    "sg:province":"ON",
    "wof:name":"Other Brother's Restaurant",
    "wof:placetype":"venue"
},
  "geometry": {"coordinates":[-80.252281189,43.5465736389],"type":"Point"}
}