{
  "type": "Feature",
  "properties": {
    "iso:country":"CA",
    "sg:city":"Montreal",
    "sg:classifiers":[
        {
            "category":"Recreation",
            "subcategory":"Arcade",
            "type":"Entertainment"
        }
    ],
    "sg:phone":"+1 514 858 7222",
    "sg:postcode":"H2N 1N4",
    "sg:province":"QC",
    "sg:tags":[
        "casino"
    ],
    "wof:name":"Au Lucky Charm Casino Prdctn",
    "wof:placetype":"venue"
},
  "geometry": {"coordinates":[-73.651611,45.544445],"type":"Point"}
}