{
  "type": "Feature",
  "properties": {
    "addr:full":"755 Vanalman Ave #18 Victoria BC V8Z 3B8",
    "addr:housenumber":"755;18",
    "addr:postcode":"v8z 3b8",
    "addr:street":"Vanalman Ave #",
    "iso:country":"CA",
    "sg:address":"755 Vanalman Ave #18",
    "sg:city":"Victoria",
    "sg:classifiers":[
        {
            "category":"Retail",
            "subcategory":"Laundry & Dry Cleaning",
            "type":"Services"
        }
    ],
    "sg:phone":"+1 250 708 0091",
    "sg:postcode":"V8Z 3B8",
    "sg:province":"BC",
    "sg:tags":[
        "cleaners",
        "rug",
        "carpet"
    ],
    "wof:name":"Aquamist Carpet Care Ltd",
    "wof:placetype":"venue"
},
  "geometry": {"coordinates":[-123.364517212,48.428314209],"type":"Point"}
}