{
  "type": "Feature",
  "properties": {
    "addr:full":"805 Dovercourt Rd Toronto ON M6H 2X4",
    "addr:housenumber":"805",
    "addr:postcode":"m6h 2x4",
    "addr:street":"Dovercourt Rd",
    "iso:country":"CA",
    "sg:address":"805 Dovercourt Rd",
    "sg:city":"Toronto",
    "sg:classifiers":[
        {
            "category":"Arts & Performance",
            "subcategory":"Theater",
            "type":"Entertainment"
        }
    ],
    "sg:phone":"+1 416 516 4025",
    "sg:postcode":"M6H 2X4",
    "sg:province":"ON",
    "sg:tags":[
        "bureau"
    ],
    "wof:name":"Corpus Dance Projects",
    "wof:placetype":"venue"
},
  "geometry": {"coordinates":[-79.4297027588,43.6628341675],"type":"Point"}
}