{
  "type": "Feature",
  "properties": {
    "iso:country":"CA",
    "sg:address":"100 Boul LA Fayette",
    "sg:city":"Longueuil",
    "sg:classifiers":[
        {
            "category":"Health Services",
            "subcategory":"Nursing And Care Facility",
            "type":"Services"
        }
    ],
    "sg:phone":"+1 450 674 8111",
    "sg:postcode":"J4K 5H6",
    "sg:province":"QC",
    "sg:tags":[
        "home",
        "retirement",
        "community"
    ],
    "wof:name":"Habitats Lafayette",
    "wof:placetype":"venue"
},
  "geometry": {"coordinates":[-73.520233,45.520844],"type":"Point"}
}