{
  "type": "Feature",
  "properties": {
    "addr:full":"376 Rue Jacques-Bedard Lac-Saint-Charles QC G3G 1P7",
    "addr:housenumber":"376",
    "addr:postcode":"g3g 1p7",
    "addr:street":"Rue Jacques-Bedard Lac-Saint-Charles",
    "iso:country":"CA",
    "sg:address":"376 Rue Jacques-Bedard",
    "sg:city":"Lac-Saint-Charles",
    "sg:classifiers":[
        {
            "category":"Retail",
            "subcategory":"Auto Repair",
            "type":"Services"
        }
    ],
    "sg:phone":"+1 418 841 4010",
    "sg:postcode":"G3G 1P7",
    "sg:province":"QC",
    "sg:tags":[
        "body",
        "automobile",
        "painting"
    ],
    "wof:name":"Ben Le Carrossier Enr",
    "wof:placetype":"venue"
},
  "geometry": {"coordinates":[-71.36382293699999,46.9044036865],"type":"Point"}
}