{
  "type": "Feature",
  "properties": {
    "addr:full":"438 Main St S Alexandria ON K0C 1A0",
    "addr:housenumber":"438",
    "addr:postcode":"k0c 1a0",
    "addr:street":"Main St S",
    "iso:country":"CA",
    "sg:address":"438 Main St S",
    "sg:city":"Alexandria",
    "sg:classifiers":[
        {
            "category":"Freight",
            "type":"Transportation"
        }
    ],
    "sg:phone":"+1 613 525 1150",
    "sg:postcode":"K0C 1A0",
    "sg:province":"ON",
    "sg:tags":[
        "trucking"
    ],
    "wof:name":"Rcmr Transport Inc",
    "wof:placetype":"venue"
},
  "geometry": {"coordinates":[-74.64385223390001,45.3195915222],"type":"Point"}
}