{
  "type": "Feature",
  "properties": {
    "iso:country":"CA",
    "sg:city":"Aylesford",
    "sg:classifiers":[
        {
            "category":"Social Services",
            "type":"Services"
        }
    ],
    "sg:phone":"+1 902 847 0927",
    "sg:postcode":"B0P 1C0",
    "sg:province":"NS",
    "sg:tags":[
        "youth",
        "organization",
        "center"
    ],
    "wof:name":"Duke of Edinburgh's Awards",
    "wof:placetype":"venue"
},
  "geometry": {"coordinates":[-64.8375244141,45.0277938843],"type":"Point"}
}