{
  "type": "Feature",
  "properties": {
    "addr:full":"Winnipeg MB R2C 5C6",
    "addr:postcode":"r2c 5c6",
    "iso:country":"CA",
    "sg:city":"Winnipeg",
    "sg:classifiers":[
        {
            "category":"Restaurant",
            "type":"Food & Drink"
        }
    ],
    "sg:phone":"+1 204 654 3345",
    "sg:postcode":"R2C 5C6",
    "sg:province":"MB",
    "wof:name":"Moxie's Restaurant",
    "wof:placetype":"venue"
},
  "geometry": {"coordinates":[-97.0698013306,49.8987312317],"type":"Point"}
}