{
  "type": "Feature",
  "properties": {
    "addr:full":"Red Point Rd Hwy Souris PE C0A 2B0",
    "addr:postcode":"c0a 2b0",
    "addr:street":"Red Point Rd Hwy",
    "iso:country":"CA",
    "sg:address":"Red Point Rd Hwy",
    "sg:city":"Souris",
    "sg:classifiers":[
        {
            "category":"Wholesale",
            "subcategory":"Auto Parts",
            "type":"Manufacturing & Wholesale Goods"
        }
    ],
    "sg:phone":"+1 902 357 2890",
    "sg:postcode":"C0A 2B0",
    "sg:province":"PE",
    "sg:tags":[
        "transmission",
        "automobile",
        "rebuilt"
    ],
    "wof:name":"Deagle's Transmission Svc Ctr",
    "wof:placetype":"venue"
},
  "geometry": {"coordinates":[-62.2530326843,46.3544883728],"type":"Point"}
}