{
  "type": "Feature",
  "properties": {
    "addr:full":"Sherrington QC J0L 2N0",
    "addr:postcode":"j0l 2n0",
    "iso:country":"CA",
    "sg:city":"Sherrington",
    "sg:classifiers":[
        {
            "category":"Food & Beverages",
            "subcategory":"Groceries & Convenience Stores",
            "type":"Retail Goods"
        }
    ],
    "sg:phone":"+1 450 454 6931",
    "sg:postcode":"J0L 2N0",
    "sg:province":"QC",
    "sg:tags":[
        "grocer"
    ],
    "wof:name":"Marche Oka-Zou",
    "wof:placetype":"venue"
},
  "geometry": {"coordinates":[-73.524467,45.167332],"type":"Point"}
}