{
  "type": "Feature",
  "properties": {
    "addr:full":"2220A Boul Industriel Chambly QC J3L 4V2",
    "addr:housenumber":"2220a",
    "addr:postcode":"j3l 4v2",
    "addr:street":"Boul Industriel",
    "iso:country":"CA",
    "sg:address":"2220A Boul Industriel",
    "sg:city":"Chambly",
    "sg:classifiers":[
        {
            "category":"Building & Trades",
            "subcategory":"Construction",
            "type":"Services"
        }
    ],
    "sg:phone":"+1 450 447 3925",
    "sg:postcode":"J3L 4V2",
    "sg:province":"QC",
    "sg:tags":[
        "steel",
        "crane",
        "erectors"
    ],
    "wof:name":"Erecteur International Ltee",
    "wof:placetype":"venue"
},
  "geometry": {"coordinates":[-73.27507,45.433056],"type":"Point"}
}