{
  "type": "Feature",
  "properties": {
    "iso:country":"CA",
    "sg:address":"5070 Dundas St W",
    "sg:city":"Etobicoke",
    "sg:classifiers":[
        {
            "category":"Food & Beverages",
            "subcategory":"Bakery",
            "type":"Retail Goods"
        }
    ],
    "sg:phone":"+1 416 233 9063",
    "sg:postcode":"M9A 1B9",
    "sg:province":"ON",
    "sg:tags":[
        "baker"
    ],
    "wof:name":"Joe's Pastizzi Plus",
    "wof:placetype":"venue"
},
  "geometry": {"coordinates":[-79.5318984985,43.6455230713],"type":"Point"}
}