{
  "type": "Feature",
  "properties": {
    "addr:full":"Fleurimont QC J1E 3V4",
    "addr:postcode":"j1e 3v4",
    "iso:country":"CA",
    "sg:city":"Fleurimont",
    "sg:classifiers":[
        {
            "category":"Building & Trades",
            "subcategory":"Construction",
            "type":"Services"
        }
    ],
    "sg:phone":"+1 819 564 1712",
    "sg:postcode":"J1E 3V4",
    "sg:province":"QC",
    "sg:tags":[
        "tile",
        "concrete",
        "contractor"
    ],
    "wof:name":"Fana Terrazzo Tuile Marbre",
    "wof:placetype":"venue"
},
  "geometry": {"coordinates":[-71.870018,45.426384],"type":"Point"}
}