{
  "type": "Feature",
  "properties": {
    "addr:full":"1273 London Rd Sarnia ON N7S 1P3",
    "addr:housenumber":"1273",
    "addr:postcode":"n7s 1p3",
    "addr:street":"London Rd",
    "iso:country":"CA",
    "sg:address":"1273 London Rd",
    "sg:city":"Sarnia",
    "sg:classifiers":[
        {
            "category":"Recreation",
            "type":"Entertainment"
        }
    ],
    "sg:phone":"+1 519 344 5135",
    "sg:postcode":"N7S 1P3",
    "sg:province":"ON",
    "sg:tags":[
        "bingo",
        "game"
    ],
    "wof:name":"Harvey's Bingo Hall",
    "wof:placetype":"venue"
},
  "geometry": {"coordinates":[-82.359177,42.97963],"type":"Point"}
}