{
  "type": "Feature",
  "properties": {
    "addr:full":"22 Rue Notre-Dame N Ville-Marie QC J9V 1W8",
    "addr:housenumber":"22",
    "addr:postcode":"j9v 1w8",
    "addr:street":"Rue Notre-Dame N",
    "iso:country":"CA",
    "sg:address":"22 Rue Notre-Dame N",
    "sg:city":"Ville-Marie",
    "sg:classifiers":[
        {
            "category":"Government",
            "subcategory":"Fire Station",
            "type":"Public Place"
        }
    ],
    "sg:phone":"+1 ",
    "sg:postcode":"J9V 1W8",
    "sg:province":"QC",
    "sg:tags":[
        "department"
    ],
    "wof:name":"Ville Marie Feu-Appels",
    "wof:placetype":"venue"
},
  "geometry": {"coordinates":[-79.444824,47.333],"type":"Point"}
}