{
  "type": "Feature",
  "properties": {
    "addr:full":"114 Rankin Rd Churchbridge SK S0A 0M0",
    "addr:housenumber":"114",
    "addr:postcode":"s0a 0m0",
    "addr:street":"Rankin Rd",
    "iso:country":"CA",
    "sg:address":"114 Rankin Rd",
    "sg:city":"Churchbridge",
    "sg:classifiers":[
        {
            "category":"Education",
            "subcategory":"Library",
            "type":"Public Place"
        }
    ],
    "sg:phone":"+1 306 896 2322",
    "sg:postcode":"S0A 0M0",
    "sg:province":"SK",
    "wof:name":"Churchbridge Library",
    "wof:placetype":"venue"
},
  "geometry": {"coordinates":[-101.89769699999999,50.897385],"type":"Point"}
}