{
  "type": "Feature",
  "properties": {
    "addr:full":"4781 47 Ave Delta BC V4K 1P7",
    "addr:housenumber":"4781",
    "addr:postcode":"v4k 1p7",
    "addr:street":"47 Ave",
    "iso:country":"CA",
    "sg:address":"4781 47 Ave",
    "sg:city":"Delta",
    "sg:classifiers":[
        {
            "category":"Building & Trades",
            "subcategory":"Construction",
            "type":"Services"
        }
    ],
    "sg:phone":"+1 604 946 7213",
    "sg:postcode":"V4K 1P7",
    "sg:province":"BC",
    "sg:tags":[
        "concrete",
        "contractor"
    ],
    "wof:name":"Permanent Cement Finishing Ltd",
    "wof:placetype":"venue"
},
  "geometry": {"coordinates":[-123.090965,49.088596],"type":"Point"}
}