{
  "type": "Feature",
  "properties": {
    "addr:full":"Charlie Lake BC V0C 1H0",
    "addr:postcode":"bc v0c 1h0",
    "iso:country":"CA",
    "sg:city":"Charlie Lake",
    "sg:classifiers":[
        {
            "category":"Education",
            "subcategory":"Dance Studio",
            "type":"Public Place"
        }
    ],
    "sg:phone":"+1 250 787 5458",
    "sg:postcode":"V0C 1H0",
    "sg:province":"BC",
    "sg:tags":[
        "instruction",
        "dancing"
    ],
    "wof:name":"Jennifer Lindsay School-Dance",
    "wof:placetype":"venue"
},
  "geometry": {"coordinates":[-120.964912,56.280636],"type":"Point"}
}