{
  "type": "Feature",
  "properties": {
    "addr:full":"4 Toronto St N Uxbridge ON L9P 1E6",
    "addr:housenumber":"4",
    "addr:postcode":"l9p 1e6",
    "addr:street":"Toronto St N",
    "iso:country":"CA",
    "sg:address":"4 Toronto St N",
    "sg:city":"Uxbridge",
    "sg:classifiers":[
        {
            "category":"Restaurant",
            "type":"Food & Drink"
        }
    ],
    "sg:phone":"+1 905 852 5050",
    "sg:postcode":"L9P 1E6",
    "sg:province":"ON",
    "wof:name":"Texas Burger & Doughnut Shop",
    "wof:placetype":"venue"
},
  "geometry": {"coordinates":[-79.1227722168,44.1093635559],"type":"Point"}
}