{
  "type": "Feature",
  "properties": {
    "addr:full":"2 Corey St Bloomfield ON K0K 1G0",
    "addr:housenumber":"2",
    "addr:postcode":"k0k 1g0",
    "addr:street":"Corey St",
    "iso:country":"CA",
    "sg:address":"2 Corey St",
    "sg:city":"Bloomfield",
    "sg:classifiers":[
        {
            "category":"Organizations",
            "subcategory":"Religious Organization",
            "type":"Services"
        }
    ],
    "sg:phone":"+1 613 393 2234",
    "sg:postcode":"K0K 1G0",
    "sg:province":"ON",
    "sg:tags":[
        "church"
    ],
    "wof:name":"Emmanuel Baptist Church",
    "wof:placetype":"venue"
},
  "geometry": {"coordinates":[-77.22710418699999,43.9879112244],"type":"Point"}
}