{
  "type": "Feature",
  "properties": {
    "iso:country":"CA",
    "sg:address":"706 Rue Principale",
    "sg:city":"Petit-Rocher",
    "sg:classifiers":[
        {
            "category":"Organizations",
            "subcategory":"Professional Association",
            "type":"Services"
        }
    ],
    "sg:phone":"+1 506 783 2846",
    "sg:postcode":"E8J 1V1",
    "sg:province":"NB",
    "wof:name":"Legion Royale Canadienne",
    "wof:placetype":"venue"
},
  "geometry": {"coordinates":[-65.71553,47.773029],"type":"Point"}
}