{
  "type": "Feature",
  "properties": {
    "addr:full":"761 Rue Villeray Montreal QC H2R 1J2",
    "addr:housenumber":"761",
    "addr:postcode":"h2r 1j2",
    "addr:street":"Rue Villeray",
    "iso:country":"CA",
    "sg:address":"761 Rue Villeray",
    "sg:city":"Montreal",
    "sg:classifiers":[
        {
            "category":"Retail",
            "subcategory":"Laundry & Dry Cleaning",
            "type":"Services"
        }
    ],
    "sg:phone":"+1 514 721 9375",
    "sg:postcode":"H2R 1J2",
    "sg:province":"QC",
    "wof:name":"Buanderie Bronzage Entre-2",
    "wof:placetype":"venue"
},
  "geometry": {"coordinates":[-73.621368,45.54409],"type":"Point"}
}