{
  "type": "Feature",
  "properties": {
    "addr:full":"11824 Boul Langelier Montreal-Nord QC H1G 3M3",
    "addr:housenumber":"11824",
    "addr:postcode":"h1g 3m3",
    "addr:street":"Boul Langelier",
    "iso:country":"CA",
    "sg:address":"11824 Boul Langelier",
    "sg:city":"Montreal-Nord",
    "sg:classifiers":[
        {
            "category":"Food & Beverages",
            "subcategory":"Groceries & Convenience Stores",
            "type":"Retail Goods"
        }
    ],
    "sg:phone":"+1 514 852 1237",
    "sg:postcode":"H1G 3M3",
    "sg:province":"QC",
    "sg:tags":[
        "grocer"
    ],
    "wof:name":"Marche Salomon",
    "wof:placetype":"venue"
},
  "geometry": {"coordinates":[-73.6148300171,45.6168212891],"type":"Point"}
}