{
  "type": "Feature",
  "properties": {
    "addr:full":"3073 North Service Rd Burlington ON L7N 3G1",
    "addr:housenumber":"3073",
    "addr:postcode":"l7n 3g1",
    "addr:street":"North Service Rd",
    "iso:country":"CA",
    "sg:address":"3073 North Service Rd",
    "sg:city":"Burlington",
    "sg:classifiers":[
        {
            "category":"Wholesale",
            "subcategory":"Machinery & Supplies",
            "type":"Manufacturing & Wholesale Goods"
        }
    ],
    "sg:phone":"+1 905 335 4020",
    "sg:postcode":"L7N 3G1",
    "sg:province":"ON",
    "sg:tags":[
        "equipment",
        "industrial"
    ],
    "wof:name":"R W Hamilton Ltd",
    "wof:placetype":"venue"
},
  "geometry": {"coordinates":[-79.80104799999999,43.355537],"type":"Point"}
}