{
  "type": "Feature",
  "properties": {
    "iso:country":"CA",
    "sg:address":"817 Boul Vachon S",
    "sg:city":"Sainte-Marie",
    "sg:classifiers":[
        {
            "category":"Shopping",
            "subcategory":"Clothing, Apparel, & Fashions",
            "type":"Retail Goods"
        }
    ],
    "sg:phone":"+1 418 387 4106",
    "sg:postcode":"G6E 1Y4",
    "sg:province":"QC",
    "sg:tags":[
        "infant",
        "wear"
    ],
    "wof:name":"Friperie Enfantine",
    "wof:placetype":"venue"
},
  "geometry": {"coordinates":[-71.0097503662,46.4318466187],"type":"Point"}
}