{
  "type": "Feature",
  "properties": {
    "addr:full":"Richmond BC V6Y 2B6",
    "addr:postcode":"v6y 2b6",
    "iso:country":"CA",
    "sg:city":"Richmond",
    "sg:classifiers":[
        {
            "category":"Shopping",
            "subcategory":"Jewelry",
            "type":"Retail Goods"
        }
    ],
    "sg:phone":"+1 604 278 7524",
    "sg:postcode":"V6Y 2B6",
    "sg:province":"BC",
    "sg:tags":[
        "jeweler"
    ],
    "wof:name":"Peoples Jewellers",
    "wof:placetype":"venue"
},
  "geometry": {"coordinates":[-123.136657715,49.1663742065],"type":"Point"}
}