{
  "type": "Feature",
  "properties": {
    "iso:country":"CA",
    "sg:address":"88 Valleyview Cres",
    "sg:city":"Bradford",
    "sg:classifiers":[
        {
            "category":"Wholesale",
            "subcategory":"Groceries",
            "type":"Manufacturing & Wholesale Goods"
        }
    ],
    "sg:phone":"+1 905 775 5452",
    "sg:postcode":"L3Z 1S7",
    "sg:province":"ON",
    "sg:tags":[
        "food",
        "product",
        "spice"
    ],
    "wof:name":"Watkins Products",
    "wof:placetype":"venue"
},
  "geometry": {"coordinates":[-79.568756,44.110962],"type":"Point"}
}