{
  "type": "Feature",
  "properties": {
    "addr:full":"7861 Hoskins St Delta BC V4G 1M4",
    "addr:housenumber":"7861",
    "addr:postcode":"v4g 1m4",
    "addr:street":"Hoskins St",
    "iso:country":"CA",
    "sg:address":"7861 Hoskins St",
    "sg:city":"Delta",
    "sg:classifiers":[
        {
            "category":"Manufacturing",
            "subcategory":"Paper Products",
            "type":"Manufacturing & Wholesale Goods"
        }
    ],
    "sg:phone":"+1 604 940 8704",
    "sg:postcode":"V4G 1M4",
    "sg:province":"BC",
    "sg:tags":[
        "core",
        "tube"
    ],
    "wof:name":"Nova Pak Paper Products Inc",
    "wof:placetype":"venue"
},
  "geometry": {"coordinates":[-122.999168,49.144459],"type":"Point"}
}