{
  "type": "Feature",
  "properties": {
    "addr:full":"618 Railway Ave Glenboro MB R0K 0X0",
    "addr:housenumber":"618",
    "addr:postcode":"r0k 0x0",
    "addr:street":"Railway Ave",
    "iso:country":"CA",
    "sg:address":"618 Railway Ave",
    "sg:city":"Glenboro",
    "sg:classifiers":[
        {
            "category":"Government",
            "subcategory":"Office",
            "type":"Public Place"
        }
    ],
    "sg:phone":"+1 204 827 2252",
    "sg:postcode":"R0K 0X0",
    "sg:province":"MB",
    "sg:tags":[
        "village"
    ],
    "wof:name":"South Cypress Municipality",
    "wof:placetype":"venue"
},
  "geometry": {"coordinates":[-99.28044128419999,49.55493927],"type":"Point"}
}