{
  "type": "Feature",
  "properties": {
    "addr:full":"Saint-Felicien QC G8K 2X3",
    "addr:postcode":"g8k 2x3",
    "iso:country":"CA",
    "sg:city":"Saint-Felicien",
    "sg:classifiers":[
        {
            "category":"Health Services",
            "subcategory":"Doctor",
            "type":"Services"
        }
    ],
    "sg:phone":"+1 418 679 5755",
    "sg:postcode":"G8K 2X3",
    "sg:province":"QC",
    "sg:tags":[
        "clinic",
        "dentist"
    ],
    "wof:name":"Clinique Dentaire Lebel Serge",
    "wof:placetype":"venue"
},
  "geometry": {"coordinates":[-72.459137,48.654221],"type":"Point"}
}