{
  "type": "Feature",
  "properties": {
    "addr:full":"33525 Seventh Ave Mission BC V2V 2E8",
    "addr:housenumber":"33525",
    "addr:postcode":"v2v 2e8",
    "addr:street":"Seventh Ave",
    "iso:country":"CA",
    "sg:address":"33525 Seventh Ave",
    "sg:city":"Mission",
    "sg:classifiers":[
        {
            "category":"Health Services",
            "subcategory":"Doctor",
            "type":"Services"
        }
    ],
    "sg:phone":"+1 604 826 5112",
    "sg:postcode":"V2V 2E8",
    "sg:province":"BC",
    "sg:tags":[
        "physician",
        "surgeon"
    ],
    "wof:name":"Edelson, A S MD",
    "wof:placetype":"venue"
},
  "geometry": {"coordinates":[-122.296401977,49.1398925781],"type":"Point"}
}