{
  "type": "Feature",
  "properties": {
    "addr:full":"13840 Mayfield Pl Richmond BC V6V 2E4",
    "addr:housenumber":"13840",
    "addr:postcode":"v6v 2e4",
    "addr:street":"Mayfield Pl",
    "iso:country":"CA",
    "sg:address":"13840 Mayfield Pl",
    "sg:city":"Richmond",
    "sg:classifiers":[
        {
            "category":"Professional",
            "type":"Services"
        }
    ],
    "sg:phone":"+1 604 273 8684",
    "sg:postcode":"V6V 2E4",
    "sg:province":"BC",
    "sg:tags":[
        "grocer",
        "establishment"
    ],
    "wof:name":"Canterbury Coffee Corp",
    "wof:placetype":"venue"
},
  "geometry": {"coordinates":[-123.070518494,49.1815567017],"type":"Point"}
}