{
  "type": "Feature",
  "properties": {
    "addr:full":"Calgary AB T2E 6Z3",
    "addr:postcode":"t2e 6z3",
    "iso:country":"CA",
    "sg:city":"Calgary",
    "sg:classifiers":[
        {
            "category":"Personal",
            "subcategory":"Beauty Salon",
            "type":"Services"
        }
    ],
    "sg:phone":"+1 403 219 3232",
    "sg:postcode":"T2E 6Z3",
    "sg:province":"AB",
    "wof:name":"Kathy's Hair Boutique Ltd",
    "wof:placetype":"venue"
},
  "geometry": {"coordinates":[-114.006797791,51.081287384],"type":"Point"}
}