{
  "type": "Feature",
  "properties": {
    "addr:full":"Woodbridge ON L4L 6A9",
    "addr:postcode":"l4l 6a9",
    "iso:country":"CA",
    "sg:city":"Woodbridge",
    "sg:classifiers":[
        {
            "category":"Building & Trades",
            "subcategory":"Construction",
            "type":"Services"
        }
    ],
    "sg:phone":"+1 905 850 3857",
    "sg:postcode":"L4L 6A9",
    "sg:province":"ON",
    "sg:tags":[
        "painter"
    ],
    "wof:name":"Archie's Decor Painting",
    "wof:placetype":"venue"
},
  "geometry": {"coordinates":[-79.5531845093,43.7870674133],"type":"Point"}
}