{
  "type": "Feature",
  "properties": {
    "addr:full":"Hamilton ON L9A 4Y6",
    "addr:postcode":"l9a 4y6",
    "iso:country":"CA",
    "sg:city":"Hamilton",
    "sg:classifiers":[
        {
            "category":"Health Services",
            "subcategory":"Doctor",
            "type":"Services"
        }
    ],
    "sg:phone":"+1 905 318 5888",
    "sg:postcode":"L9A 4Y6",
    "sg:province":"ON",
    "sg:tags":[
        "dentist"
    ],
    "wof:name":"Harper, David DDS",
    "wof:placetype":"venue"
},
  "geometry": {"coordinates":[-79.86311340330001,43.219871521],"type":"Point"}
}