{
  "type": "Feature",
  "properties": {
    "iso:country":"CA",
    "sg:address":"750 Lansdowne St W",
    "sg:city":"Peterborough",
    "sg:classifiers":[
        {
            "category":"Restaurant",
            "type":"Food & Drink"
        }
    ],
    "sg:phone":"+1 705 748 2020",
    "sg:postcode":"K9J 1Z3",
    "sg:province":"ON",
    "wof:name":"Burger King",
    "wof:placetype":"venue"
},
  "geometry": {"coordinates":[-78.335068,44.284641],"type":"Point"}
}