{
  "type": "Feature",
  "properties": {
    "addr:full":"5342 Hamilton Rd Dorchester ON N0L 1G6",
    "addr:housenumber":"5342",
    "addr:postcode":"n0l 1g6",
    "addr:street":"Hamilton Rd",
    "iso:country":"CA",
    "sg:address":"5342 Hamilton Rd",
    "sg:city":"Dorchester",
    "sg:classifiers":[
        {
            "category":"Sports & Exercise",
            "subcategory":"Golf",
            "type":"Entertainment"
        }
    ],
    "sg:phone":"+1 519 268 0031",
    "sg:postcode":"N0L 1G6",
    "sg:province":"ON",
    "sg:tags":[
        "instruction"
    ],
    "wof:name":"Dorchester Golf Ctr",
    "wof:placetype":"venue"
},
  "geometry": {"coordinates":[-81.015305,42.979328],"type":"Point"}
}