{
  "type": "Feature",
  "properties": {
    "addr:full":"545 Ouellette Ave Windsor ON N9A 4J3",
    "addr:housenumber":"545",
    "addr:postcode":"n9a 4j3",
    "addr:street":"Ouellette Ave",
    "iso:country":"CA",
    "sg:address":"545 Ouellette Ave",
    "sg:city":"Windsor",
    "sg:classifiers":[
        {
            "category":"Organizations",
            "subcategory":"Membership Organization",
            "type":"Services"
        }
    ],
    "sg:phone":"+1 519 977 6141",
    "sg:postcode":"N9A 4J3",
    "sg:province":"ON",
    "wof:name":"Epilepsy Windsor & Essex Cnty",
    "wof:placetype":"venue"
},
  "geometry": {"coordinates":[-83.03723100000001,42.314453],"type":"Point"}
}