{
  "type": "Feature",
  "properties": {
    "addr:full":"1850 Wilson Ave North York ON M9M 1A1",
    "addr:housenumber":"1850",
    "addr:postcode":"m9m 1a1",
    "addr:street":"Wilson Ave",
    "iso:country":"CA",
    "sg:address":"1850 Wilson Ave",
    "sg:city":"North York",
    "sg:classifiers":[
        {
            "category":"Manufacturing",
            "subcategory":"Tools & Machinery",
            "type":"Manufacturing & Wholesale Goods"
        }
    ],
    "sg:phone":"+1 416 741 7336",
    "sg:postcode":"M9M 1A1",
    "sg:province":"ON",
    "sg:tags":[
        "equipment",
        "electric"
    ],
    "wof:name":"H B Etlin CO Ltd",
    "wof:placetype":"venue"
},
  "geometry": {"coordinates":[-79.5228347778,43.7178993225],"type":"Point"}
}