{
  "type": "Feature",
  "properties": {
    "addr:full":"North York ON M9L 1X9",
    "addr:postcode":"m9l 1x9",
    "iso:country":"CA",
    "sg:city":"North York",
    "sg:classifiers":[
        {
            "category":"Retail",
            "subcategory":"Auto Repair",
            "type":"Services"
        }
    ],
    "sg:phone":"+1 416 745 2075",
    "sg:postcode":"M9L 1X9",
    "sg:province":"ON",
    "sg:tags":[
        "repairing",
        "automobile"
    ],
    "wof:name":"Pro Power Auto Svc",
    "wof:placetype":"venue"
},
  "geometry": {"coordinates":[-79.55489300000001,43.757957],"type":"Point"}
}