{
  "type": "Feature",
  "properties": {
    "addr:full":"593 Sheppard Ave E North York ON M2K 1B4",
    "addr:housenumber":"593",
    "addr:postcode":"m2k 1b4",
    "addr:street":"Sheppard Ave E",
    "iso:country":"CA",
    "sg:address":"593 Sheppard Ave E",
    "sg:city":"North York",
    "sg:classifiers":[
        {
            "category":"Retail",
            "subcategory":"Repair Shop",
            "type":"Services"
        }
    ],
    "sg:phone":"+1 416 733 7770",
    "sg:postcode":"M2K 1B4",
    "sg:province":"ON",
    "sg:tags":[
        "lock",
        "locksmith"
    ],
    "wof:name":"Abba High Security Locksmiths",
    "wof:placetype":"venue"
},
  "geometry": {"coordinates":[-79.38449900000001,43.767456],"type":"Point"}
}