{
  "type": "Feature",
  "properties": {
    "iso:country":"CA",
    "sg:address":"593 Sheppard Ave E",
    "sg:city":"North York",
    "sg:classifiers":[
        {
            "category":"Retail",
            "subcategory":"Repair Shop",
            "type":"Services"
        }
    ],
    "sg:phone":"+1 416 733 7770",
    "sg:postcode":"M2K 1B4",
    "sg:province":"ON",
    "sg:tags":[
        "lock",
        "locksmith"
    ],
    "wof:name":"Abba High Security Locksmiths",
    "wof:placetype":"venue"
},
  "geometry": {"coordinates":[-79.384499,43.767456],"type":"Point"}
}