{
  "type": "Feature",
  "properties": {
    "iso:country":"CA",
    "sg:address":"10th St",
    "sg:city":"Hearst",
    "sg:classifiers":[
        {
            "category":"Railroad",
            "type":"Transportation"
        }
    ],
    "sg:phone":"+1 705 362 4041",
    "sg:postcode":"P0L 1N0",
    "sg:province":"ON",
    "wof:name":"Algoma Central Railway",
    "wof:placetype":"venue"
},
  "geometry": {"coordinates":[-83.6675872803,49.6886749268],"type":"Point"}
}