{
  "type": "Feature",
  "properties": {
    "addr:full":"158 Macnab St N Hamilton ON L8R 2M3",
    "addr:housenumber":"158",
    "addr:postcode":"l8r 2m3",
    "addr:street":"Macnab St N",
    "iso:country":"CA",
    "sg:address":"158 Macnab St N",
    "sg:city":"Hamilton",
    "sg:classifiers":[
        {
            "category":"Wholesale",
            "subcategory":"Machinery & Supplies",
            "type":"Manufacturing & Wholesale Goods"
        }
    ],
    "sg:phone":"+1 905 527 2406",
    "sg:postcode":"L8R 2M3",
    "sg:province":"ON",
    "sg:tags":[
        "sprinkler"
    ],
    "wof:name":"Central P & H Fire Protection",
    "wof:placetype":"venue"
},
  "geometry": {"coordinates":[-79.868324,43.261929],"type":"Point"}
}