{
  "type": "Feature",
  "properties": {
    "addr:full":"1547 Venables St Vancouver BC V5L 2G8",
    "addr:housenumber":"1547",
    "addr:postcode":"v5l 2g8",
    "addr:street":"Venables St",
    "iso:country":"CA",
    "sg:address":"1547 Venables St",
    "sg:city":"Vancouver",
    "sg:classifiers":[
        {
            "category":"Manufacturing",
            "subcategory":"Furniture",
            "type":"Manufacturing & Wholesale Goods"
        }
    ],
    "sg:phone":"+1 604 253 7802",
    "sg:postcode":"V5L 2G8",
    "sg:province":"BC",
    "sg:tags":[
        "food",
        "equipment",
        "facility"
    ],
    "wof:name":"Canow Food Equipment",
    "wof:placetype":"venue"
},
  "geometry": {"coordinates":[-123.07325,49.27681],"type":"Point"}
}