{
  "type": "Feature",
  "properties": {
    "addr:full":"9162 Yellowhead Trail NW Edmonton AB T5B 1G2",
    "addr:housenumber":"9162",
    "addr:postcode":"t5b 1g2",
    "addr:street":"Yellowhead Trail Nw",
    "iso:country":"CA",
    "sg:address":"9162 Yellowhead Trail NW",
    "sg:city":"Edmonton",
    "sg:classifiers":[
        {
            "category":"Freight",
            "type":"Transportation"
        }
    ],
    "sg:phone":"+1 780 413 6207",
    "sg:postcode":"T5B 1G2",
    "sg:province":"AB",
    "sg:tags":[
        "trucking"
    ],
    "wof:name":"K & W Michalyk",
    "wof:placetype":"venue"
},
  "geometry": {"coordinates":[-113.481972,53.581615],"type":"Point"}
}