{
  "type": "Feature",
  "properties": {
    "addr:full":"230 2 Ave Vauxhall AB T0K 2K0",
    "addr:housenumber":"230",
    "addr:postcode":"t0k 2k0",
    "addr:street":"2 Ave",
    "iso:country":"CA",
    "sg:address":"230 2 Ave",
    "sg:city":"Vauxhall",
    "sg:classifiers":[
        {
            "category":"Organizations",
            "subcategory":"Religious Organization",
            "type":"Services"
        }
    ],
    "sg:phone":"+1 403 654 2032",
    "sg:postcode":"T0K 2K0",
    "sg:province":"AB",
    "sg:tags":[
        "church"
    ],
    "wof:name":"Christian Reformed Church",
    "wof:placetype":"venue"
},
  "geometry": {"coordinates":[-112.10020400000001,50.068378],"type":"Point"}
}