{
  "type": "Feature",
  "properties": {
    "addr:full":"Kitchener ON N2M 2K5",
    "addr:postcode":"n2m 2k5",
    "iso:country":"CA",
    "sg:city":"Kitchener",
    "sg:classifiers":[
        {
            "category":"Restaurant",
            "type":"Food & Drink"
        }
    ],
    "sg:phone":"+1 519 578 4441",
    "sg:postcode":"N2M 2K5",
    "sg:province":"ON",
    "sg:tags":[
        "out",
        "pizza"
    ],
    "wof:name":"Mario's Two For One Pizza",
    "wof:placetype":"venue"
},
  "geometry": {"coordinates":[-80.5238037109,43.4463615417],"type":"Point"}
}