{
  "type": "Feature",
  "properties": {
    "addr:full":"3796 Champlain St Bourget ON K0A 1E0",
    "addr:housenumber":"3796",
    "addr:postcode":"k0a 1e0",
    "addr:street":"Champlain St",
    "iso:country":"CA",
    "sg:address":"3796 Champlain St",
    "sg:city":"Bourget",
    "sg:classifiers":[
        {
            "category":"Cinema",
            "subcategory":"Movie Rental",
            "type":"Entertainment"
        }
    ],
    "sg:phone":"+1 613 487 3990",
    "sg:postcode":"K0A 1E0",
    "sg:province":"ON",
    "sg:tags":[
        "leasing",
        "video",
        "disc",
        "tape"
    ],
    "wof:name":"Flicks & Flavours",
    "wof:placetype":"venue"
},
  "geometry": {"coordinates":[-75.158356,45.435127],"type":"Point"}
}