{
  "type": "Feature",
  "properties": {
    "addr:full":"11518 71 Ave NW Edmonton AB T6G 0A7",
    "addr:housenumber":"11518",
    "addr:postcode":"t6g 0a7",
    "addr:street":"71 Ave Nw",
    "iso:country":"CA",
    "sg:address":"11518 71 Ave NW",
    "sg:city":"Edmonton",
    "sg:classifiers":[
        {
            "category":"Professional",
            "type":"Services"
        }
    ],
    "sg:phone":"+1 780 430 0461",
    "sg:postcode":"T6G 0A7",
    "sg:province":"AB",
    "sg:tags":[
        "home",
        "planning",
        "plan",
        "house"
    ],
    "wof:name":"Timber Line Graphics",
    "wof:placetype":"venue"
},
  "geometry": {"coordinates":[-113.528381348,53.5076675415],"type":"Point"}
}