{
  "type": "Feature",
  "properties": {
    "addr:full":"133 Greely Rd Fort Mcmurray AB T9H 3Y7",
    "addr:housenumber":"133",
    "addr:postcode":"t9h 3y7",
    "addr:street":"Greely Rd",
    "iso:country":"CA",
    "sg:address":"133 Greely Rd",
    "sg:city":"Fort Mcmurray",
    "sg:classifiers":[
        {
            "category":"Professional",
            "subcategory":"Business Services",
            "type":"Services"
        }
    ],
    "sg:phone":"+1 780 743 5804",
    "sg:postcode":"T9H 3Y7",
    "sg:province":"AB",
    "sg:tags":[
        "liquidator",
        "auctioneer"
    ],
    "wof:name":"All-Rite Auctions Ltd",
    "wof:placetype":"venue"
},
  "geometry": {"coordinates":[-111.338516,56.674725],"type":"Point"}
}