{
  "type": "Feature",
  "properties": {
    "iso:country":"CA",
    "sg:address":"215 Parkside Dr E",
    "sg:city":"Waterdown",
    "sg:classifiers":[
        {
            "category":"Education",
            "subcategory":"School",
            "type":"Public Place"
        }
    ],
    "sg:phone":"+1 905 689 6692",
    "sg:postcode":"L0R 2H1",
    "sg:province":"ON",
    "wof:name":"Waterdown District High School",
    "wof:placetype":"venue"
},
  "geometry": {"coordinates":[-79.9102859497,43.3330154419],"type":"Point"}
}