{
  "type": "Feature",
  "properties": {
    "addr:full":"215 Parkside Dr E Waterdown ON L0R 2H1",
    "addr:housenumber":"215",
    "addr:postcode":"l0r 2h1",
    "addr:street":"Parkside Dr E",
    "iso:country":"CA",
    "sg:address":"215 Parkside Dr E",
    "sg:city":"Waterdown",
    "sg:classifiers":[
        {
            "category":"Education",
            "subcategory":"School",
            "type":"Public Place"
        }
    ],
    "sg:phone":"+1 905 689 6692",
    "sg:postcode":"L0R 2H1",
    "sg:province":"ON",
    "wof:name":"Waterdown District High School",
    "wof:placetype":"venue"
},
  "geometry": {"coordinates":[-79.9102859497,43.3330154419],"type":"Point"}
}