{
  "type": "Feature",
  "properties": {
    "addr:full":"Calgary AB T2N 1X7",
    "addr:postcode":"t2n 1x7",
    "iso:country":"CA",
    "sg:city":"Calgary",
    "sg:classifiers":[
        {
            "category":"Professional",
            "subcategory":"Accounting & Tax Preparation",
            "type":"Services"
        }
    ],
    "sg:phone":"+1 403 283 4242",
    "sg:postcode":"T2N 1X7",
    "sg:province":"AB",
    "sg:tags":[
        "accountant"
    ],
    "wof:name":"Owen Mayer Kirzinger",
    "wof:placetype":"venue"
},
  "geometry": {"coordinates":[-114.09017900000001,51.051937],"type":"Point"}
}