{
  "type": "Feature",
  "properties": {
    "addr:full":"Foster QC J0E 1R0",
    "addr:postcode":"j0e 1r0",
    "iso:country":"CA",
    "sg:city":"Foster",
    "sg:classifiers":[
        {
            "category":"Wholesale",
            "subcategory":"Construction Materials",
            "type":"Manufacturing & Wholesale Goods"
        }
    ],
    "sg:phone":"+1 450 539 2646",
    "sg:postcode":"J0E 1R0",
    "sg:province":"QC",
    "sg:tags":[
        "sand",
        "gravel",
        "excavating",
        "contractor"
    ],
    "wof:name":"Allard & Allard Constr Inc",
    "wof:placetype":"venue"
},
  "geometry": {"coordinates":[-72.5006561279,45.3074531555],"type":"Point"}
}