{
  "type": "Feature",
  "properties": {
    "addr:full":"955 139 Rte Saint-Theodore-D'Acton QC J0H 1Z0",
    "addr:housenumber":"139",
    "addr:postcode":"j0h 1z0",
    "addr:street":"Rte Saint-Theodore-D'Acton",
    "iso:country":"CA",
    "sg:address":"955 139 Rte",
    "sg:city":"Saint-Theodore-D'Acton",
    "sg:classifiers":[
        {
            "category":"Building & Trades",
            "subcategory":"Construction",
            "type":"Services"
        }
    ],
    "sg:phone":"+1 450 546 3940",
    "sg:postcode":"J0H 1Z0",
    "sg:province":"QC",
    "sg:tags":[
        "maker",
        "cabinet"
    ],
    "wof:name":"Ebenisterie Guy Le Blanc Enr",
    "wof:placetype":"venue"
},
  "geometry": {"coordinates":[-72.522751,45.621269],"type":"Point"}
}