{
  "type": "Feature",
  "properties": {
    "addr:full":"7 Cow Bay Rd Prince Rupert BC V8J 1A4",
    "addr:housenumber":"7",
    "addr:postcode":"v8j 1a4",
    "addr:street":"Cow Bay Rd",
    "iso:country":"CA",
    "sg:address":"7 Cow Bay Rd",
    "sg:city":"Prince Rupert",
    "sg:classifiers":[
        {
            "category":"Food & Beverages",
            "subcategory":"Meat & Fish",
            "type":"Retail Goods"
        }
    ],
    "sg:phone":"+1 250 624 6090",
    "sg:postcode":"V8J 1A4",
    "sg:province":"BC",
    "sg:tags":[
        "seafood"
    ],
    "wof:name":"Dolly's Fish Market",
    "wof:placetype":"venue"
},
  "geometry": {"coordinates":[-130.31762699999999,54.31741],"type":"Point"}
}