{
  "type": "Feature",
  "properties": {
    "addr:full":"131 Main St Parkhill ON N0M 2K0",
    "addr:housenumber":"131",
    "addr:postcode":"n0m 2k0",
    "addr:street":"Main St",
    "iso:country":"CA",
    "sg:address":"131 Main St",
    "sg:city":"Parkhill",
    "sg:classifiers":[
        {
            "category":"Health Services",
            "subcategory":"Hospital",
            "type":"Services"
        }
    ],
    "sg:phone":"+1 519 294 6932",
    "sg:postcode":"N0M 2K0",
    "sg:province":"ON",
    "sg:tags":[
        "mental"
    ],
    "wof:name":"Parkhill Residential Home",
    "wof:placetype":"venue"
},
  "geometry": {"coordinates":[-81.68398999999999,43.162891],"type":"Point"}
}