{
  "type": "Feature",
  "properties": {
    "addr:full":"1315 Rue St Edouard Saint-Jude QC J0H 1P0",
    "addr:housenumber":"1315",
    "addr:postcode":"j0h 1p0",
    "addr:street":"Rue St Edouard Saint-Jude",
    "iso:country":"CA",
    "sg:address":"1315 Rue St Edouard",
    "sg:city":"Saint-Jude",
    "sg:classifiers":[
        {
            "category":"Retail",
            "subcategory":"Auto Repair",
            "type":"Services"
        }
    ],
    "sg:phone":"+1 450 792 2131",
    "sg:postcode":"J0H 1P0",
    "sg:province":"QC",
    "sg:tags":[
        "repairing",
        "automobile"
    ],
    "wof:name":"Garage Remy Lapierre",
    "wof:placetype":"venue"
},
  "geometry": {"coordinates":[-72.99198150629999,45.7768211365],"type":"Point"}
}