{
  "type": "Feature",
  "properties": {
    "addr:full":"1101 Elm St White Rock BC V4B 3R9",
    "addr:housenumber":"1101",
    "addr:postcode":"v4b 3r9",
    "addr:street":"Elm St",
    "iso:country":"CA",
    "sg:address":"1101 Elm St",
    "sg:city":"White Rock",
    "sg:classifiers":[
        {
            "category":"Restaurant",
            "type":"Food & Drink"
        }
    ],
    "sg:phone":"+1 604 531 3600",
    "sg:postcode":"V4B 3R9",
    "sg:province":"BC",
    "wof:name":"Troll's Restaurants",
    "wof:placetype":"venue"
},
  "geometry": {"coordinates":[-122.810699,49.022854],"type":"Point"}
}