{
  "type": "Feature",
  "properties": {
    "addr:full":"7797 Edmonds St Burnaby BC V3N 1B9",
    "addr:housenumber":"7797",
    "addr:postcode":"v3n 1b9",
    "addr:street":"Edmonds St",
    "iso:country":"CA",
    "sg:address":"7797 Edmonds St",
    "sg:city":"Burnaby",
    "sg:classifiers":[
        {
            "category":"Retail",
            "subcategory":"Auto Repair",
            "type":"Services"
        }
    ],
    "sg:phone":"+1 604 540 0304",
    "sg:postcode":"V3N 1B9",
    "sg:province":"BC",
    "sg:tags":[
        "muffler",
        "exhaust",
        "system"
    ],
    "wof:name":"Action Muffler Radiator & Brks",
    "wof:placetype":"venue"
},
  "geometry": {"coordinates":[-122.939194,49.22525],"type":"Point"}
}