{
  "type": "Feature",
  "properties": {
    "addr:full":"5012 50th Ave Pouce Coupe BC V0C 2C0",
    "addr:housenumber":"5012",
    "addr:postcode":"bc v0c 2c0",
    "addr:street":"50Th Ave",
    "iso:country":"CA",
    "sg:address":"5012 50th Ave",
    "sg:city":"Pouce Coupe",
    "sg:classifiers":[
        {
            "category":"Food & Beverages",
            "subcategory":"Groceries & Convenience Stores",
            "type":"Retail Goods"
        }
    ],
    "sg:phone":"+1 250 786 5352",
    "sg:postcode":"V0C 2C0",
    "sg:province":"BC",
    "sg:tags":[
        "grocer"
    ],
    "wof:name":"Hillcrest General Store",
    "wof:placetype":"venue"
},
  "geometry": {"coordinates":[-120.133461,55.716061],"type":"Point"}
}