{
  "type": "Feature",
  "properties": {
    "addr:full":"Vancouver BC V6A 2T4",
    "addr:postcode":"v6a 2t4",
    "iso:country":"CA",
    "sg:city":"Vancouver",
    "sg:classifiers":[
        {
            "category":"Recreation",
            "type":"Entertainment"
        }
    ],
    "sg:phone":"+1 604 662 7556",
    "sg:postcode":"V6A 2T4",
    "sg:province":"BC",
    "sg:tags":[
        "astrologer"
    ],
    "wof:name":"Union Lau Palmistry & Geomancy",
    "wof:placetype":"venue"
},
  "geometry": {"coordinates":[-123.09947200000001,49.281067],"type":"Point"}
}