{
  "type": "Feature",
  "properties": {
    "addr:full":"6808 Ogden Rd SE Calgary AB T2C 1B4",
    "addr:housenumber":"6808",
    "addr:postcode":"t2c 1b4",
    "addr:street":"Ogden Rd Se",
    "iso:country":"CA",
    "sg:address":"6808 Ogden Rd SE",
    "sg:city":"Calgary",
    "sg:classifiers":[
        {
            "category":"Shopping",
            "subcategory":"Hobbies, Toys, & Games",
            "type":"Retail Goods"
        }
    ],
    "sg:phone":"+1 403 236 5098",
    "sg:postcode":"T2C 1B4",
    "sg:province":"AB",
    "sg:tags":[
        "model",
        "supply"
    ],
    "wof:name":"Action Hobby Canada Ltd",
    "wof:placetype":"venue"
},
  "geometry": {"coordinates":[-114.001335,50.990456],"type":"Point"}
}