{
  "type": "Feature",
  "properties": {
    "addr:full":"240 Adelaide St W Toronto ON M5H 1W7",
    "addr:housenumber":"240",
    "addr:postcode":"m5h 1w7",
    "addr:street":"Adelaide St W",
    "iso:country":"CA",
    "sg:address":"240 Adelaide St W",
    "sg:city":"Toronto",
    "sg:classifiers":[
        {
            "category":"Restaurant",
            "type":"Food & Drink"
        }
    ],
    "sg:phone":"+1 416 599 9751",
    "sg:postcode":"M5H 1W7",
    "sg:province":"ON",
    "wof:name":"Crocodile Rock",
    "wof:placetype":"venue"
},
  "geometry": {"coordinates":[-79.3884735107,43.6483726501],"type":"Point"}
}