{
  "type": "Feature",
  "properties": {
    "addr:full":"581 Concession St Hamilton ON L8V 1B2",
    "addr:housenumber":"581",
    "addr:postcode":"l8v 1b2",
    "addr:street":"Concession St",
    "iso:country":"CA",
    "sg:address":"581 Concession St",
    "sg:city":"Hamilton",
    "sg:classifiers":[
        {
            "category":"Food & Beverages",
            "subcategory":"Groceries & Convenience Stores",
            "type":"Retail Goods"
        }
    ],
    "sg:phone":"+1 905 318 9366",
    "sg:postcode":"L8V 1B2",
    "sg:province":"ON",
    "sg:tags":[
        "grocer"
    ],
    "wof:name":"Sam's Food Mart",
    "wof:placetype":"venue"
},
  "geometry": {"coordinates":[-79.850723,43.240753],"type":"Point"}
}