{
  "type": "Feature",
  "properties": {
    "iso:country":"CA",
    "sg:city":"Toronto",
    "sg:classifiers":[
        {
            "category":"Personal",
            "subcategory":"Beauty Salon",
            "type":"Services"
        }
    ],
    "sg:phone":"+1 416 925 5150",
    "sg:postcode":"M4T 1Z2",
    "sg:province":"ON",
    "wof:name":"Heath Hair Studio",
    "wof:placetype":"venue"
},
  "geometry": {"coordinates":[-79.394234,43.688843],"type":"Point"}
}