{
  "type": "Feature",
  "properties": {
    "addr:full":"4215 Concession 7 Windsor ON N9A 6J3",
    "addr:housenumber":"4215",
    "addr:postcode":"n9a 6j3",
    "addr:street":"Concession 7",
    "iso:country":"CA",
    "sg:address":"4215 Concession 7",
    "sg:city":"Windsor",
    "sg:classifiers":[
        {
            "category":"Retail",
            "subcategory":"Auto Rental",
            "type":"Services"
        }
    ],
    "sg:phone":"+1 519 966 2782",
    "sg:postcode":"N9A 6J3",
    "sg:province":"ON",
    "sg:tags":[
        "renting",
        "automobile"
    ],
    "wof:name":"Avis Car",
    "wof:placetype":"venue"
},
  "geometry": {"coordinates":[-83.033913,42.317822],"type":"Point"}
}