{
  "type": "Feature",
  "properties": {
    "addr:full":"Brampton ON L6W 3V1",
    "addr:postcode":"l6w 3v1",
    "iso:country":"CA",
    "sg:city":"Brampton",
    "sg:classifiers":[
        {
            "category":"Building & Trades",
            "subcategory":"Construction",
            "type":"Services"
        }
    ],
    "sg:phone":"+1 905 450 7010",
    "sg:postcode":"L6W 3V1",
    "sg:province":"ON",
    "sg:tags":[
        "wheel",
        "chair",
        "lift",
        "ramp"
    ],
    "wof:name":"Concord Elevator Ltd",
    "wof:placetype":"venue"
},
  "geometry": {"coordinates":[-79.7158508301,43.6841049194],"type":"Point"}
}