{
  "type": "Feature",
  "properties": {
    "addr:full":"1627 1st Ave NE Weyburn SK S4H 3E7",
    "addr:housenumber":"1627",
    "addr:postcode":"s4h 3e7",
    "addr:street":"1St Ave Ne",
    "iso:country":"CA",
    "sg:address":"1627 1st Ave NE",
    "sg:city":"Weyburn",
    "sg:classifiers":[
        {
            "category":"Autos & Motor Vehicles",
            "subcategory":"Automobile Sales",
            "type":"Retail Goods"
        }
    ],
    "sg:phone":"+1 306 842 7333",
    "sg:postcode":"S4H 3E7",
    "sg:province":"SK",
    "sg:tags":[
        "car",
        "dealer"
    ],
    "wof:name":"Redcoat Plymouth Chrysler Ltd",
    "wof:placetype":"venue"
},
  "geometry": {"coordinates":[-103.83445,49.668987],"type":"Point"}
}