{
  "type": "Feature",
  "properties": {
    "addr:full":"2417 Valley Forest Way Oakville, Ontario Oakville, Ontario",
    "addr:housenumber":"2417",
    "addr:street":"Valley Forest Way",
    "iso:country":"CA",
    "sg:address":"2417 Valley Forest Way Oakville, Ontario",
    "sg:classifiers":[
        {
            "category":"Professional",
            "subcategory":"Computer Services",
            "type":"Services"
        }
    ],
    "sg:postcode":"Oakville, Ontario",
    "sg:tags":[
        "sms",
        "bluetooth",
        "mobile",
        "social",
        "mobuddy"
    ],
    "sg:website":"http://www.redriever.com",
    "wof:name":"Redriever",
    "wof:placetype":"venue"
},
  "geometry": {"coordinates":[-79.7441633,43.4608103],"type":"Point"}
}