{
  "type": "Feature",
  "properties": {
    "iso:country":"CA",
    "sg:address":"10209 134 Ave NW",
    "sg:city":"Edmonton",
    "sg:classifiers":[
        {
            "category":"Social Services",
            "subcategory":"Adult Care",
            "type":"Services"
        }
    ],
    "sg:phone":"+1 780 476 1470",
    "sg:postcode":"T5E 1J2",
    "sg:province":"AB",
    "sg:tags":[
        "senior",
        "housing",
        "citizen"
    ],
    "wof:name":"Mary A Finlay Manor",
    "wof:placetype":"venue"
},
  "geometry": {"coordinates":[-113.495903,53.594479],"type":"Point"}
}