{
  "type": "Feature",
  "properties": {
    "addr:full":"PO Box 779 Falher AB T0H 1M0",
    "addr:housenumber":"po",
    "addr:postcode":"t0h 1m0",
    "addr:street":"Box 779 Falher",
    "iso:country":"CA",
    "sg:address":"PO Box 779",
    "sg:city":"Falher",
    "sg:classifiers":[
        {
            "category":"Manufacturing",
            "subcategory":"Tools & Machinery",
            "type":"Manufacturing & Wholesale Goods"
        }
    ],
    "sg:phone":"+1 780 837 8083",
    "sg:postcode":"T0H 1M0",
    "sg:province":"AB",
    "sg:tags":[
        "machine",
        "shop"
    ],
    "wof:name":"Don's Country Machining",
    "wof:placetype":"venue"
},
  "geometry": {"coordinates":[-117.201897,55.741131],"type":"Point"}
}