{
  "type": "Feature",
  "properties": {
    "addr:full":"255 Fischer-Hallman Rd Kitchener ON N2M 4X8",
    "addr:housenumber":"255",
    "addr:postcode":"n2m 4x8",
    "addr:street":"Fischer-Hallman Rd",
    "iso:country":"CA",
    "sg:address":"255 Fischer-Hallman Rd",
    "sg:city":"Kitchener",
    "sg:classifiers":[
        {
            "category":"Education",
            "subcategory":"School",
            "type":"Public Place"
        }
    ],
    "sg:phone":"+1 519 744 6567",
    "sg:postcode":"N2M 4X8",
    "sg:province":"ON",
    "wof:name":"Forest Heights Collegiate Inst",
    "wof:placetype":"venue"
},
  "geometry": {"coordinates":[-80.521233,43.425362],"type":"Point"}
}