{
  "type": "Feature",
  "properties": {
    "addr:full":"145 Victoria Ave Chatham ON N7L 3A7",
    "addr:housenumber":"145",
    "addr:postcode":"n7l 3a7",
    "addr:street":"Victoria Ave",
    "iso:country":"CA",
    "sg:address":"145 Victoria Ave",
    "sg:city":"Chatham",
    "sg:classifiers":[
        {
            "category":"Organizations",
            "subcategory":"Religious Organization",
            "type":"Services"
        }
    ],
    "sg:phone":"+1 519 352 9370",
    "sg:postcode":"N7L 3A7",
    "sg:province":"ON",
    "sg:tags":[
        "church"
    ],
    "wof:name":"Blessed Sacrament Church",
    "wof:placetype":"venue"
},
  "geometry": {"coordinates":[-82.18988,42.41177],"type":"Point"}
}