{
  "type": "Feature",
  "properties": {
    "iso:country":"CA",
    "sg:address":"27 Rue Yvon",
    "sg:city":"Canton-DE-Granby",
    "sg:classifiers":[
        {
            "category":"Retail",
            "subcategory":"Auto Repair",
            "type":"Services"
        }
    ],
    "sg:phone":"+1 450 378 1275",
    "sg:postcode":"J2G 8C8",
    "sg:province":"QC",
    "sg:tags":[
        "repairing",
        "automobile",
        "parts",
        "radiator",
        "supply"
    ],
    "wof:name":"G M Radiateurs & Reservoirs",
    "wof:placetype":"venue"
},
  "geometry": {"coordinates":[-72.7217712402,45.3979949951],"type":"Point"}
}