{
  "type": "Feature",
  "properties": {
    "addr:full":"298 Rue Saint-Jean Quebec QC G1R 1P1",
    "addr:housenumber":"298",
    "addr:postcode":"g1r 1p1",
    "addr:street":"Rue Saint-Jean",
    "iso:country":"CA",
    "sg:address":"298 Rue Saint-Jean",
    "sg:city":"Quebec",
    "sg:classifiers":[
        {
            "category":"Restaurant",
            "type":"Food & Drink"
        }
    ],
    "sg:phone":"+1 418 647 3031",
    "sg:postcode":"G1R 1P1",
    "sg:province":"QC",
    "wof:name":"Cafe Au Bonnet D'Ane",
    "wof:placetype":"venue"
},
  "geometry": {"coordinates":[-71.22380099999999,46.808582],"type":"Point"}
}