{
  "type": "Feature",
  "properties": {
    "addr:full":"1015 Silver Springs Dr Baden ON N3A 3R6",
    "addr:housenumber":"1015",
    "addr:postcode":"n3a 3r6",
    "addr:street":"Silver Springs Dr",
    "iso:country":"CA",
    "sg:address":"1015 Silver Springs Dr",
    "sg:city":"Baden",
    "sg:classifiers":[
        {
            "category":"Professional",
            "subcategory":"Accounting & Tax Preparation",
            "type":"Services"
        }
    ],
    "sg:phone":"+1 519 634 5571",
    "sg:postcode":"N3A 3R6",
    "sg:province":"ON",
    "sg:tags":[
        "accountant"
    ],
    "wof:name":"Bender, Robert V CA",
    "wof:placetype":"venue"
},
  "geometry": {"coordinates":[-80.657928,43.395271],"type":"Point"}
}