{
  "type": "Feature",
  "properties": {
    "addr:full":"7840 Highway 97 Kelowna BC V4V 1T3",
    "addr:housenumber":"7840",
    "addr:postcode":"v4v 1t3",
    "addr:street":"Highway 97",
    "iso:country":"CA",
    "sg:address":"7840 Highway 97",
    "sg:city":"Kelowna",
    "sg:classifiers":[
        {
            "category":"Autos & Motor Vehicles",
            "subcategory":"Recreational Vehicle Sales",
            "type":"Retail Goods"
        }
    ],
    "sg:phone":"+1 250 766 3100",
    "sg:postcode":"V4V 1T3",
    "sg:province":"BC",
    "wof:name":"Country Rv Ctr Ltd",
    "wof:placetype":"venue"
},
  "geometry": {"coordinates":[-119.49659699999999,49.886814],"type":"Point"}
}