{
  "type": "Feature",
  "properties": {
    "addr:full":"69 Rue Fraser Riviere-Du-Loup QC G5R 1C5",
    "addr:housenumber":"69",
    "addr:postcode":"g5r 1c5",
    "addr:street":"Rue Fraser Riviere-Du-Loup",
    "iso:country":"CA",
    "sg:address":"69 Rue Fraser",
    "sg:city":"Riviere-Du-Loup",
    "sg:classifiers":[
        {
            "category":"Retail",
            "subcategory":"Auto Repair",
            "type":"Services"
        }
    ],
    "sg:phone":"+1 418 862 1960",
    "sg:postcode":"G5R 1C5",
    "sg:province":"QC",
    "sg:tags":[
        "repairing",
        "automobile"
    ],
    "wof:name":"Station DE Svc D Pelletier",
    "wof:placetype":"venue"
},
  "geometry": {"coordinates":[-69.540909,47.838902],"type":"Point"}
}