{
  "type": "Feature",
  "properties": {
    "addr:full":"7th Ave W Central Butte SK S0H 0T0",
    "addr:postcode":"s0h 0t0",
    "addr:street":"7Th Ave W Central",
    "iso:country":"CA",
    "sg:address":"7th Ave W",
    "sg:city":"Central Butte",
    "sg:classifiers":[
        {
            "category":"Organizations",
            "subcategory":"Religious Organization",
            "type":"Services"
        }
    ],
    "sg:phone":"+1 306 796 2261",
    "sg:postcode":"S0H 0T0",
    "sg:province":"SK",
    "sg:tags":[
        "church"
    ],
    "wof:name":"St Mary's Roman Catholic Chr",
    "wof:placetype":"venue"
},
  "geometry": {"coordinates":[-106.511512756,50.8009605408],"type":"Point"}
}