{
  "type": "Feature",
  "properties": {
    "addr:full":"2560 Mcintosh Rd Prescott ON K0E 1T0",
    "addr:housenumber":"2560",
    "addr:postcode":"k0e 1t0",
    "addr:street":"Mcintosh Rd",
    "iso:country":"CA",
    "sg:address":"2560 Mcintosh Rd",
    "sg:city":"Prescott",
    "sg:classifiers":[
        {
            "category":"Manufacturing",
            "subcategory":"Signs",
            "type":"Manufacturing & Wholesale Goods"
        }
    ],
    "sg:phone":"+1 613 925 2553",
    "sg:postcode":"K0E 1T0",
    "sg:province":"ON",
    "wof:name":"Visser Signs",
    "wof:placetype":"venue"
},
  "geometry": {"coordinates":[-75.5184173584,44.7094192505],"type":"Point"}
}