{
  "type": "Feature",
  "properties": {
    "addr:full":"Lake Cowichan BC V0R 2G0",
    "addr:postcode":"v0r 2g0",
    "iso:country":"CA",
    "sg:city":"Lake Cowichan",
    "sg:classifiers":[
        {
            "category":"Home & Garden",
            "subcategory":"Building Materials",
            "type":"Retail Goods"
        }
    ],
    "sg:phone":"+1 250 749 4575",
    "sg:postcode":"V0R 2G0",
    "sg:province":"BC",
    "sg:tags":[
        "mixed",
        "concrete"
    ],
    "wof:name":"Cowichan Lake Concrete Ltd",
    "wof:placetype":"venue"
},
  "geometry": {"coordinates":[-124.072921753,48.8243560791],"type":"Point"}
}