{
  "type": "Feature",
  "properties": {
    "iso:country":"CA",
    "sg:address":"1201 Huron St",
    "sg:city":"London",
    "sg:classifiers":[
        {
            "category":"Health Services",
            "subcategory":"Doctor",
            "type":"Services"
        }
    ],
    "sg:phone":"+1 519 659 7323",
    "sg:postcode":"N5Y 4K5",
    "sg:province":"ON",
    "sg:tags":[
        "dentist"
    ],
    "wof:name":"Agathos, Peter DDS",
    "wof:placetype":"venue"
},
  "geometry": {"coordinates":[-81.224007,43.017307],"type":"Point"}
}