{
  "type": "Feature",
  "properties": {
    "addr:full":"138 E Broadway Ave Regina SK S4N 0Z5",
    "addr:housenumber":"138",
    "addr:postcode":"s4n 0z5",
    "addr:street":"E Broadway Ave",
    "iso:country":"CA",
    "sg:address":"138 E Broadway Ave",
    "sg:city":"Regina",
    "sg:classifiers":[
        {
            "category":"Health Services",
            "subcategory":"Clinic",
            "type":"Services"
        }
    ],
    "sg:phone":"+1 306 347 3132",
    "sg:postcode":"S4N 0Z5",
    "sg:province":"SK",
    "sg:tags":[
        "personal",
        "home",
        "care"
    ],
    "wof:name":"Broadway Care Home",
    "wof:placetype":"venue"
},
  "geometry": {"coordinates":[-104.581329,50.437962],"type":"Point"}
}