{
  "type": "Feature",
  "properties": {
    "addr:full":"8 Lincoln St Capreol ON P0M 1H0",
    "addr:housenumber":"8",
    "addr:postcode":"p0m 1h0",
    "addr:street":"Lincoln St",
    "iso:country":"CA",
    "sg:address":"8 Lincoln St",
    "sg:city":"Capreol",
    "sg:classifiers":[
        {
            "category":"Education",
            "subcategory":"School",
            "type":"Public Place"
        }
    ],
    "sg:phone":"+1 705 858 3861",
    "sg:postcode":"P0M 1H0",
    "sg:province":"ON",
    "wof:name":"C R Judd Public School",
    "wof:placetype":"venue"
},
  "geometry": {"coordinates":[-80.921875,46.7124328613],"type":"Point"}
}