{
  "type": "Feature",
  "properties": {
    "addr:full":"10417 10 St Dawson Creek BC V1G 3T8",
    "addr:housenumber":"10417",
    "addr:postcode":"v1g 3t8",
    "addr:street":"10 St",
    "iso:country":"CA",
    "sg:address":"10417 10 St",
    "sg:city":"Dawson Creek",
    "sg:classifiers":[
        {
            "category":"Organizations",
            "subcategory":"Labor Organization",
            "type":"Services"
        }
    ],
    "sg:phone":"+1 250 719 0256",
    "sg:postcode":"V1G 3T8",
    "sg:province":"BC",
    "wof:name":"Communications Energy",
    "wof:placetype":"venue"
},
  "geometry": {"coordinates":[-120.230728149,55.7562828064],"type":"Point"}
}