{
  "type": "Feature",
  "properties": {
    "iso:country":"CA",
    "sg:address":"394 Rue Isabey",
    "sg:city":"Saint-Laurent",
    "sg:classifiers":[
        {
            "category":"Professional",
            "type":"Services"
        }
    ],
    "sg:phone":"+1 514 344 5111",
    "sg:postcode":"H4T 1V3",
    "sg:province":"QC",
    "sg:tags":[
        "establishment",
        "investment"
    ],
    "wof:name":"Tradefreedom Technologies Inc",
    "wof:placetype":"venue"
},
  "geometry": {"coordinates":[-73.685242,45.49287],"type":"Point"}
}