{
  "type": "Feature",
  "properties": {
    "iso:country":"CA",
    "sg:address":"1801 3E Av #40",
    "sg:city":"Val-D'Or",
    "sg:classifiers":[
        {
            "category":"Shopping",
            "subcategory":"Clothing, Apparel, & Fashions",
            "type":"Retail Goods"
        }
    ],
    "sg:phone":"+1 819 874 4466",
    "sg:postcode":"J9P 5K1",
    "sg:province":"QC",
    "sg:tags":[
        "lingerie"
    ],
    "wof:name":"Boutique Secrets Nocturnes",
    "wof:placetype":"venue"
},
  "geometry": {"coordinates":[-72.44482421879999,48.8869552612],"type":"Point"}
}