{
  "type": "Feature",
  "properties": {
    "addr:full":"Wendake QC G0A 4V0",
    "addr:postcode":"g0a 4v0",
    "iso:country":"CA",
    "sg:city":"Wendake",
    "sg:classifiers":[
        {
            "category":"Social Services",
            "type":"Services"
        }
    ],
    "sg:phone":"+1 418 842 1540",
    "sg:postcode":"G0A 4V0",
    "sg:province":"QC",
    "sg:tags":[
        "organization",
        "welfare"
    ],
    "wof:name":"Commission DE LA Sante",
    "wof:placetype":"venue"
},
  "geometry": {"coordinates":[-71.4270782471,46.8429489136],"type":"Point"}
}