{
  "type": "Feature",
  "properties": {
    "addr:full":"146 George St Arthur ON N0G 1A0",
    "addr:housenumber":"146",
    "addr:postcode":"n0g 1a0",
    "addr:street":"George St",
    "iso:country":"CA",
    "sg:address":"146 George St",
    "sg:city":"Arthur",
    "sg:classifiers":[
        {
            "category":"Social Services",
            "type":"Services"
        }
    ],
    "sg:phone":"+1 519 848 6487",
    "sg:postcode":"N0G 1A0",
    "sg:province":"ON",
    "sg:tags":[
        "organization",
        "welfare"
    ],
    "wof:name":"Community Resource Ctr",
    "wof:placetype":"venue"
},
  "geometry": {"coordinates":[-80.536827,43.831593],"type":"Point"}
}