{
  "type": "Feature",
  "properties": {
    "addr:full":"15610 95 Ave NW Edmonton AB T5P 0A4",
    "addr:housenumber":"15610",
    "addr:postcode":"t5p 0a4",
    "addr:street":"95 Ave Nw",
    "iso:country":"CA",
    "sg:address":"15610 95 Ave NW",
    "sg:city":"Edmonton",
    "sg:classifiers":[
        {
            "category":"Food & Beverages",
            "subcategory":"Liquor & Beverages",
            "type":"Retail Goods"
        }
    ],
    "sg:phone":"+1 780 944 1144",
    "sg:postcode":"T5P 0A4",
    "sg:province":"AB",
    "sg:tags":[
        "store"
    ],
    "wof:name":"Sandy Lane Liquor Store",
    "wof:placetype":"venue"
},
  "geometry": {"coordinates":[-113.590843201,53.5317649841],"type":"Point"}
}