{
  "type": "Feature",
  "properties": {
    "addr:full":"243 Lewisville Rd Moncton NB E1A 6T1",
    "addr:housenumber":"243",
    "addr:postcode":"e1a 6t1",
    "addr:street":"Lewisville Rd",
    "iso:country":"CA",
    "sg:address":"243 Lewisville Rd",
    "sg:city":"Moncton",
    "sg:classifiers":[
        {
            "category":"Social Services",
            "type":"Services"
        }
    ],
    "sg:phone":"+1 506 857 9121",
    "sg:postcode":"E1A 6T1",
    "sg:province":"NB",
    "sg:tags":[
        "organization",
        "welfare"
    ],
    "wof:name":"Christian Food Bank Ministries",
    "wof:placetype":"venue"
},
  "geometry": {"coordinates":[-64.766548,46.102448],"type":"Point"}
}