{
  "type": "Feature",
  "properties": {
    "addr:full":"400 Kinistino Ave Kinistino SK S0J 1H0",
    "addr:housenumber":"400",
    "addr:postcode":"s0j 1h0",
    "addr:street":"Kinistino Ave",
    "iso:country":"CA",
    "sg:address":"400 Kinistino Ave",
    "sg:city":"Kinistino",
    "sg:classifiers":[
        {
            "category":"Organizations",
            "subcategory":"Religious Organization",
            "type":"Services"
        }
    ],
    "sg:phone":"+1 306 864 2888",
    "sg:postcode":"S0J 1H0",
    "sg:province":"SK",
    "sg:tags":[
        "church"
    ],
    "wof:name":"Kinistino Zion Lutheran Church",
    "wof:placetype":"venue"
},
  "geometry": {"coordinates":[-105.034218,52.951115],"type":"Point"}
}