{
  "type": "Feature",
  "properties": {
    "iso:country":"CA",
    "sg:address":"7111 Maple St",
    "sg:city":"Vancouver",
    "sg:classifiers":[
        {
            "category":"Professional",
            "subcategory":"Management & Consulting",
            "type":"Services"
        }
    ],
    "sg:phone":"+1 604 263 5255",
    "sg:postcode":"V6P 5P5",
    "sg:province":"BC",
    "sg:tags":[
        "consultant",
        "educational"
    ],
    "wof:name":"Campbell Golinsky & Assocs Ltd",
    "wof:placetype":"venue"
},
  "geometry": {"coordinates":[-123.153060913,49.2214012146],"type":"Point"}
}