{
  "type": "Feature",
  "properties": {
    "addr:full":"195 Franklin Blvd Cambridge ON N1R 8H3",
    "addr:housenumber":"195",
    "addr:postcode":"n1r 8h3",
    "addr:street":"Franklin Blvd",
    "iso:country":"CA",
    "sg:address":"195 Franklin Blvd",
    "sg:city":"Cambridge",
    "sg:classifiers":[
        {
            "category":"Restaurant",
            "type":"Food & Drink"
        }
    ],
    "sg:phone":"+1 519 624 5402",
    "sg:postcode":"N1R 8H3",
    "sg:province":"ON",
    "wof:name":"Wall Street Cafe",
    "wof:placetype":"venue"
},
  "geometry": {"coordinates":[-80.287811,43.354107],"type":"Point"}
}