{
  "type": "Feature",
  "properties": {
    "addr:full":"645 Rue DE LA Place-Publique Laval QC H7X 1G1",
    "addr:housenumber":"645",
    "addr:postcode":"h7x 1g1",
    "addr:street":"Rue De La Place-Publique",
    "iso:country":"CA",
    "sg:address":"645 Rue DE LA Place-Publique",
    "sg:city":"Laval",
    "sg:classifiers":[
        {
            "category":"Health Services",
            "subcategory":"Doctor",
            "type":"Services"
        }
    ],
    "sg:phone":"+1 450 689 1144",
    "sg:postcode":"H7X 1G1",
    "sg:province":"QC",
    "sg:tags":[
        "clinic",
        "chiropractor"
    ],
    "wof:name":"Centre Chiropratique-Dorothee",
    "wof:placetype":"venue"
},
  "geometry": {"coordinates":[-73.82034299999999,45.528736],"type":"Point"}
}