{
  "type": "Feature",
  "properties": {
    "addr:full":"19 Cromer Ave Grand Falls-Windsor NL A2A 2K5",
    "addr:housenumber":"19",
    "addr:postcode":"a2a 2k5",
    "addr:street":"Cromer Ave",
    "iso:country":"CA",
    "sg:address":"19 Cromer Ave",
    "sg:city":"Grand Falls-Windsor",
    "sg:classifiers":[
        {
            "category":"Shopping",
            "type":"Retail Goods"
        }
    ],
    "sg:phone":"+1 709 489 7070",
    "sg:postcode":"A2A 2K5",
    "sg:province":"NL",
    "sg:tags":[
        "pet",
        "shop"
    ],
    "wof:name":"Pet City",
    "wof:placetype":"venue"
},
  "geometry": {"coordinates":[-55.65391922,48.9472084045],"type":"Point"}
}