{
  "type": "Feature",
  "properties": {
    "addr:full":"3385 Highway 11 S Callander ON P0H 1H0",
    "addr:housenumber":"3385",
    "addr:postcode":"p0h 1h0",
    "addr:street":"Highway 11 S",
    "iso:country":"CA",
    "sg:address":"3385 Highway 11 S",
    "sg:city":"Callander",
    "sg:classifiers":[
        {
            "category":"Building & Trades",
            "subcategory":"Construction",
            "type":"Services"
        }
    ],
    "sg:phone":"+1 705 752 3427",
    "sg:postcode":"P0H 1H0",
    "sg:province":"ON",
    "sg:tags":[
        "designer",
        "marine",
        "contractor"
    ],
    "wof:name":"Eves Marine Svc",
    "wof:placetype":"venue"
},
  "geometry": {"coordinates":[-79.362877,46.22316],"type":"Point"}
}