{
  "type": "Feature",
  "properties": {
    "addr:full":"723 Gillan Rd Renfrew ON K7V 3Z4",
    "addr:housenumber":"723",
    "addr:postcode":"k7v 3z4",
    "addr:street":"Gillan Rd",
    "iso:country":"CA",
    "sg:address":"723 Gillan Rd",
    "sg:city":"Renfrew",
    "sg:classifiers":[
        {
            "category":"Building & Trades",
            "subcategory":"Landscaping Services",
            "type":"Services"
        }
    ],
    "sg:phone":"+1 613 432 2239",
    "sg:postcode":"K7V 3Z4",
    "sg:province":"ON",
    "sg:tags":[
        "center",
        "garden",
        "landscape",
        "contractor"
    ],
    "wof:name":"Hultink Landscaping Ltd",
    "wof:placetype":"venue"
},
  "geometry": {"coordinates":[-76.6607055664,45.472492218],"type":"Point"}
}