{
  "type": "Feature",
  "properties": {
    "addr:full":"120 1st St E Meadow Lake SK S9X 1P8",
    "addr:housenumber":"120",
    "addr:postcode":"s9x 1p8",
    "addr:street":"1St St E;Lake",
    "iso:country":"CA",
    "sg:address":"120 1st St E",
    "sg:city":"Meadow Lake",
    "sg:classifiers":[
        {
            "category":"Government",
            "subcategory":"Office",
            "type":"Public Place"
        }
    ],
    "sg:phone":"+1 306 236 3622",
    "sg:postcode":"S9X 1P8",
    "sg:province":"SK",
    "sg:tags":[
        "municipality",
        "village"
    ],
    "wof:name":"Town of Meadow Lake",
    "wof:placetype":"venue"
},
  "geometry": {"coordinates":[-108.43167099999999,54.123714],"type":"Point"}
}