{
  "type": "Feature",
  "properties": {
    "addr:full":"Kingston ON K7K 5W2",
    "addr:postcode":"k7k 5w2",
    "iso:country":"CA",
    "sg:city":"Kingston",
    "sg:classifiers":[
        {
            "category":"Travel",
            "subcategory":"Hotels & Motels",
            "type":"Entertainment"
        }
    ],
    "sg:phone":"+1 613 546 3661",
    "sg:postcode":"K7K 5W2",
    "sg:province":"ON",
    "wof:name":"Days Inn Kingston",
    "wof:placetype":"venue"
},
  "geometry": {"coordinates":[-76.49865699999999,44.266121],"type":"Point"}
}