{
  "type": "Feature",
  "properties": {
    "addr:full":"2451 Rue Logan Montreal QC H2K 2B9",
    "addr:housenumber":"2451",
    "addr:postcode":"h2k 2b9",
    "addr:street":"Rue Logan",
    "iso:country":"CA",
    "sg:address":"2451 Rue Logan",
    "sg:city":"Montreal",
    "sg:classifiers":[
        {
            "category":"Personal",
            "subcategory":"Beauty Salon",
            "type":"Services"
        }
    ],
    "sg:phone":"+1 514 527 0474",
    "sg:postcode":"H2K 2B9",
    "sg:province":"QC",
    "wof:name":"Salon Jo-Jo",
    "wof:placetype":"venue"
},
  "geometry": {"coordinates":[-73.54950700000001,45.530224],"type":"Point"}
}