{
  "type": "Feature",
  "properties": {
    "addr:full":"200 Provincial Rd 244 S Notre Dame DE Lourdes MB R0G 1M0",
    "addr:housenumber":"200",
    "addr:postcode":"r0g 1m0",
    "addr:street":"Provincial Rd 244 S",
    "iso:country":"CA",
    "sg:address":"200 Provincial Rd 244 S",
    "sg:city":"Notre Dame DE Lourdes",
    "sg:classifiers":[
        {
            "category":"Retail",
            "subcategory":"Auto Repair",
            "type":"Services"
        }
    ],
    "sg:phone":"+1 204 248 2255",
    "sg:postcode":"R0G 1M0",
    "sg:province":"MB",
    "sg:tags":[
        "body",
        "automobile",
        "painting"
    ],
    "wof:name":"Gilles' Auto Body & Towing",
    "wof:placetype":"venue"
},
  "geometry": {"coordinates":[-98.547752,49.527905],"type":"Point"}
}