{
  "type": "Feature",
  "properties": {
    "addr:full":"Carleton Place ON K7C 3V7",
    "addr:postcode":"k7c 3v7",
    "iso:country":"CA",
    "sg:city":"Carleton Place",
    "sg:classifiers":[
        {
            "category":"Building & Trades",
            "subcategory":"Plumbing",
            "type":"Services"
        }
    ],
    "sg:phone":"+1 613 257 4628",
    "sg:postcode":"K7C 3V7",
    "sg:province":"ON",
    "sg:tags":[
        "contractor"
    ],
    "wof:name":"Purdy Plumbing & Heating Inc",
    "wof:placetype":"venue"
},
  "geometry": {"coordinates":[-76.146545,45.148617],"type":"Point"}
}