{
  "type": "Feature",
  "properties": {
    "iso:country":"CA",
    "sg:city":"Fort Chipewyan",
    "sg:classifiers":[
        {
            "category":"Autos & Motor Vehicles",
            "subcategory":"Fuel & Gas Station",
            "type":"Retail Goods"
        }
    ],
    "sg:phone":"+1 780 697 2000",
    "sg:postcode":"T0P 1B0",
    "sg:province":"AB",
    "sg:tags":[
        "oil"
    ],
    "wof:name":"Acg Fraser Gas",
    "wof:placetype":"venue"
},
  "geometry": {"coordinates":[-111.152847,58.713268],"type":"Point"}
}