{
  "type": "Feature",
  "properties": {
    "addr:full":"18 Poole Dr Herring Cove NS B3V 1H6",
    "addr:housenumber":"18",
    "addr:postcode":"b3v 1h6",
    "addr:street":"Poole Dr",
    "iso:country":"CA",
    "sg:address":"18 Poole Dr",
    "sg:city":"Herring Cove",
    "sg:classifiers":[
        {
            "category":"Building & Trades",
            "subcategory":"Construction",
            "type":"Services"
        }
    ],
    "sg:phone":"+1 902 477 3337",
    "sg:postcode":"B3V 1H6",
    "sg:province":"NS",
    "sg:tags":[
        "excavating",
        "contractor"
    ],
    "wof:name":"Poole's Backhoeing Svc",
    "wof:placetype":"venue"
},
  "geometry": {"coordinates":[-63.566383,44.564579],"type":"Point"}
}