{
  "type": "Feature",
  "properties": {
    "addr:full":"513 105th Ave Tisdale SK S0E 1T0",
    "addr:housenumber":"513",
    "addr:postcode":"s0e 1t0",
    "addr:street":"105Th Ave",
    "iso:country":"CA",
    "sg:address":"513 105th Ave",
    "sg:city":"Tisdale",
    "sg:classifiers":[
        {
            "category":"Education",
            "subcategory":"School",
            "type":"Public Place"
        }
    ],
    "sg:phone":"+1 306 873 4533",
    "sg:postcode":"S0E 1T0",
    "sg:province":"SK",
    "wof:name":"Tisdale Elementary School",
    "wof:placetype":"venue"
},
  "geometry": {"coordinates":[-104.051208496,52.8529815674],"type":"Point"}
}