{
  "type": "Feature",
  "properties": {
    "addr:full":"SW 27-9-19W Brandon MB R7A 6Y8",
    "addr:postcode":"r7a 6y8",
    "addr:street":"Sw 27-9-19W",
    "iso:country":"CA",
    "sg:address":"SW 27-9-19W",
    "sg:city":"Brandon",
    "sg:classifiers":[
        {
            "category":"Building & Trades",
            "subcategory":"Construction",
            "type":"Services"
        }
    ],
    "sg:phone":"+1 204 725 2294",
    "sg:postcode":"R7A 6Y8",
    "sg:province":"MB",
    "sg:tags":[
        "downspouts",
        "roofing",
        "gutter",
        "contractor"
    ],
    "wof:name":"Able Eavestroughing Ltd",
    "wof:placetype":"venue"
},
  "geometry": {"coordinates":[-99.9619522095,49.8476982117],"type":"Point"}
}