{
  "type": "Feature",
  "properties": {
    "iso:country":"CA",
    "sg:address":"1639 Burncoat Rd",
    "sg:city":"Noel",
    "sg:classifiers":[
        {
            "category":"Government",
            "subcategory":"Fire Station",
            "type":"Public Place"
        }
    ],
    "sg:phone":"+1 902 369 2088",
    "sg:postcode":"B0N 2C0",
    "sg:province":"NS",
    "sg:tags":[
        "department"
    ],
    "wof:name":"Noel & District Vol Fire Dept",
    "wof:placetype":"venue"
},
  "geometry": {"coordinates":[-63.7448883057,45.2958068848],"type":"Point"}
}