{
  "type": "Feature",
  "properties": {
    "addr:full":"10807 209 St NW Edmonton AB T5S 1Z7",
    "addr:housenumber":"10807",
    "addr:postcode":"t5s 1z7",
    "addr:street":"209 St Nw",
    "iso:country":"CA",
    "sg:address":"10807 209 St NW",
    "sg:city":"Edmonton",
    "sg:classifiers":[
        {
            "category":"Wholesale",
            "subcategory":"Machinery & Supplies",
            "type":"Manufacturing & Wholesale Goods"
        }
    ],
    "sg:phone":"+1 780 452 7021",
    "sg:postcode":"T5S 1Z7",
    "sg:province":"AB",
    "sg:tags":[
        "contractor"
    ],
    "wof:name":"Jade Equipment CO Ltd",
    "wof:placetype":"venue"
},
  "geometry": {"coordinates":[-113.67937469500001,53.5537948608],"type":"Point"}
}