{
  "type": "Feature",
  "properties": {
    "addr:full":"Winnipeg MB R3T 5K1",
    "addr:postcode":"r3t 5k1",
    "iso:country":"CA",
    "sg:city":"Winnipeg",
    "sg:classifiers":[
        {
            "category":"Real Estate",
            "subcategory":"Real Estate Operator",
            "type":"Services"
        }
    ],
    "sg:phone":"+1 204 269 0248",
    "sg:postcode":"R3T 5K1",
    "sg:province":"MB",
    "sg:tags":[
        "apartment"
    ],
    "wof:name":"Celebrity Place",
    "wof:placetype":"venue"
},
  "geometry": {"coordinates":[-97.155380249,49.8086090088],"type":"Point"}
}