{
  "type": "Feature",
  "properties": {
    "addr:full":"25 Charlton Ave E #307 Hamilton ON L8N 1Y2",
    "addr:housenumber":"25;307",
    "addr:postcode":"l8n 1y2",
    "addr:street":"Charlton Ave E #",
    "iso:country":"CA",
    "sg:address":"25 Charlton Ave E #307",
    "sg:city":"Hamilton",
    "sg:classifiers":[
        {
            "category":"Health Services",
            "subcategory":"Doctor",
            "type":"Services"
        }
    ],
    "sg:phone":"+1 905 522 1461",
    "sg:postcode":"L8N 1Y2",
    "sg:province":"ON",
    "sg:tags":[
        "physician",
        "surgeon"
    ],
    "wof:name":"Rastogi, Indra P MD",
    "wof:placetype":"venue"
},
  "geometry": {"coordinates":[-79.8711013794,43.2497062683],"type":"Point"}
}