{
  "type": "Feature",
  "properties": {
    "addr:full":"1505 1st Ave W Vancouver BC V6J 1E8",
    "addr:housenumber":"1505",
    "addr:postcode":"v6j 1e8",
    "addr:street":"1St Ave W",
    "iso:country":"CA",
    "sg:address":"1505 1st Ave W",
    "sg:city":"Vancouver",
    "sg:classifiers":[
        {
            "category":"Recreation",
            "subcategory":"Marina",
            "type":"Entertainment"
        }
    ],
    "sg:phone":"+1 604 733 3625",
    "sg:postcode":"V6J 1E8",
    "sg:province":"BC",
    "wof:name":"False Creek Harbour Authority",
    "wof:placetype":"venue"
},
  "geometry": {"coordinates":[-123.14011383099999,49.2714958191],"type":"Point"}
}