{
  "type": "Feature",
  "properties": {
    "addr:full":"3615 Mill Woods Road East NW Edmonton AB T6L 5X2",
    "addr:housenumber":"3615",
    "addr:postcode":"t6l 5x2",
    "addr:street":"Mill Woods Road East Nw",
    "iso:country":"CA",
    "sg:address":"3615 Mill Woods Road East NW",
    "sg:city":"Edmonton",
    "sg:classifiers":[
        {
            "category":"Education",
            "subcategory":"School",
            "type":"Public Place"
        }
    ],
    "sg:phone":"+1 780 461 0616",
    "sg:postcode":"T6L 5X2",
    "sg:province":"AB",
    "wof:name":"Minchau School",
    "wof:placetype":"venue"
},
  "geometry": {"coordinates":[-113.408828735,53.4674606323],"type":"Point"}
}