{
  "type": "Feature",
  "properties": {
    "addr:full":"201 Lonsdale Ave North Vancouver BC V7M 2E9",
    "addr:housenumber":"201",
    "addr:postcode":"v7m 2e9",
    "addr:street":"Lonsdale Ave",
    "iso:country":"CA",
    "sg:address":"201 Lonsdale Ave",
    "sg:city":"North Vancouver",
    "sg:classifiers":[
        {
            "category":"Shopping",
            "subcategory":"Bicycles & Sporting Goods",
            "type":"Retail Goods"
        }
    ],
    "sg:phone":"+1 604 990 4737",
    "sg:postcode":"V7M 2E9",
    "sg:province":"BC",
    "sg:tags":[
        "equipment",
        "skateboard"
    ],
    "wof:name":"Rds Skate Supply Ltd",
    "wof:placetype":"venue"
},
  "geometry": {"coordinates":[-123.07781219500001,49.3127975464],"type":"Point"}
}