{
  "type": "Feature",
  "properties": {
    "addr:full":"2696 Pembina Hwy Winnipeg MB R3T 2H7",
    "addr:housenumber":"2696",
    "addr:postcode":"r3t 2h7",
    "addr:street":"Pembina Hwy",
    "iso:country":"CA",
    "sg:address":"2696 Pembina Hwy",
    "sg:city":"Winnipeg",
    "sg:classifiers":[
        {
            "category":"Cinema",
            "subcategory":"Movie Rental",
            "type":"Entertainment"
        }
    ],
    "sg:phone":"+1 204 261 1047",
    "sg:postcode":"R3T 2H7",
    "sg:province":"MB",
    "sg:tags":[
        "video",
        "game",
        "tape",
        "leasing"
    ],
    "wof:name":"Blockbuster Video",
    "wof:placetype":"venue"
},
  "geometry": {"coordinates":[-97.1570892334,49.7947006226],"type":"Point"}
}