{
  "type": "Feature",
  "properties": {
    "addr:full":"17 Franklin St Norman Wells NT X0E 0V0",
    "addr:housenumber":"17",
    "addr:postcode":"x0e 0v0",
    "addr:street":"Franklin St",
    "iso:country":"CA",
    "sg:address":"17 Franklin St",
    "sg:city":"Norman Wells",
    "sg:classifiers":[
        {
            "category":"Food & Beverages",
            "subcategory":"Liquor & Beverages",
            "type":"Retail Goods"
        }
    ],
    "sg:phone":"+1 867 587 2476",
    "sg:postcode":"X0E 0V0",
    "sg:province":"NT",
    "sg:tags":[
        "store"
    ],
    "wof:name":"Norman Wells Liquor Agency Ltd",
    "wof:placetype":"venue"
},
  "geometry": {"coordinates":[-126.706687927,65.30633544920001],"type":"Point"}
}