{
  "type": "Feature",
  "properties": {
    "addr:full":"85 N Main St Deer Lake NL A8A 1X1",
    "addr:housenumber":"85",
    "addr:postcode":"a8a 1x1",
    "addr:street":"N Main St",
    "iso:country":"CA",
    "sg:address":"85 N Main St",
    "sg:city":"Deer Lake",
    "sg:classifiers":[
        {
            "category":"Shopping",
            "subcategory":"Catalog Store",
            "type":"Retail Goods"
        }
    ],
    "sg:phone":"+1 709 635 5131",
    "sg:postcode":"A8A 1X1",
    "sg:province":"NL",
    "sg:tags":[
        "mail",
        "order",
        "internet"
    ],
    "wof:name":"Sears Canada Inc",
    "wof:placetype":"venue"
},
  "geometry": {"coordinates":[-57.423664093,49.1753387451],"type":"Point"}
}