{
  "type": "Feature",
  "properties": {
    "addr:full":"421 Grand Ave Indian Head SK S0G 2K0",
    "addr:housenumber":"421",
    "addr:postcode":"s0g 2k0",
    "addr:street":"Grand Ave",
    "iso:country":"CA",
    "sg:address":"421 Grand Ave",
    "sg:city":"Indian Head",
    "sg:classifiers":[
        {
            "category":"Government",
            "subcategory":"Office",
            "type":"Public Place"
        }
    ],
    "sg:phone":"+1 306 695 3344",
    "sg:postcode":"S0G 2K0",
    "sg:province":"SK",
    "sg:tags":[
        "village"
    ],
    "wof:name":"Indian Head Town Office",
    "wof:placetype":"venue"
},
  "geometry": {"coordinates":[-103.667885,50.531864],"type":"Point"}
}