{
  "type": "Feature",
  "properties": {
    "addr:full":"620 Rue Notre Dame Saint-Ferdinand QC G0N 1N0",
    "addr:housenumber":"620",
    "addr:postcode":"g0n 1n0",
    "addr:street":"Rue Notre Dame",
    "iso:country":"CA",
    "sg:address":"620 Rue Notre Dame",
    "sg:city":"Saint-Ferdinand",
    "sg:classifiers":[
        {
            "category":"Education",
            "subcategory":"School",
            "type":"Public Place"
        }
    ],
    "sg:phone":"+1 418 428 3731",
    "sg:postcode":"G0N 1N0",
    "sg:province":"QC",
    "wof:name":"Notre-Dame Ecole",
    "wof:placetype":"venue"
},
  "geometry": {"coordinates":[-71.5725860596,46.1079101562],"type":"Point"}
}