{
  "type": "Feature",
  "properties": {
    "addr:full":"240 20th St W Prince Albert SK S6V 4G4",
    "addr:housenumber":"240",
    "addr:postcode":"s6v 4g4",
    "addr:street":"20Th St",
    "iso:country":"CA",
    "sg:address":"240 20th St W",
    "sg:city":"Prince Albert",
    "sg:classifiers":[
        {
            "category":"Building & Trades",
            "subcategory":"Construction",
            "type":"Services"
        }
    ],
    "sg:phone":"+1 306 922 0116",
    "sg:postcode":"S6V 4G4",
    "sg:province":"SK",
    "sg:tags":[
        "pavement",
        "marking"
    ],
    "wof:name":"Superior Sweeping & Line Pntng",
    "wof:placetype":"venue"
},
  "geometry": {"coordinates":[-105.76107,53.195065],"type":"Point"}
}