{
  "type": "Feature",
  "properties": {
    "iso:country":"CA",
    "sg:address":"214 Main St",
    "sg:city":"Kindersley",
    "sg:classifiers":[
        {
            "category":"Shopping",
            "subcategory":"Pharmacy",
            "type":"Retail Goods"
        }
    ],
    "sg:phone":"+1 306 463 2624",
    "sg:postcode":"S0L 1S0",
    "sg:province":"SK",
    "wof:name":"Kindersley & District CO-OP",
    "wof:placetype":"venue"
},
  "geometry": {"coordinates":[-109.161056519,51.4721603394],"type":"Point"}
}