{
  "type": "Feature",
  "properties": {
    "addr:full":"1832 169 Rte Metabetchouan-Lac-A-LA-Croix QC G8G 1B3",
    "addr:housenumber":"1832",
    "addr:postcode":"g8g 1b3",
    "addr:street":"169 Rte Metabetchouan-Lac-A-La-Croix",
    "iso:country":"CA",
    "sg:address":"1832 169 Rte",
    "sg:city":"Metabetchouan-Lac-A-LA-Croix",
    "sg:classifiers":[
        {
            "category":"Restaurant",
            "type":"Food & Drink"
        }
    ],
    "sg:phone":"+1 418 349 3760",
    "sg:postcode":"G8G 1B3",
    "sg:province":"QC",
    "wof:name":"Au Coin DE LA Patate",
    "wof:placetype":"venue"
},
  "geometry": {"coordinates":[-71.8765792847,48.4169006348],"type":"Point"}
}