{
  "type": "Feature",
  "properties": {
    "addr:full":"2221 Granville St Vancouver BC V6H 3G1",
    "addr:housenumber":"2221",
    "addr:postcode":"v6h 3g1",
    "addr:street":"Granville St",
    "iso:country":"CA",
    "sg:address":"2221 Granville St",
    "sg:city":"Vancouver",
    "sg:classifiers":[
        {
            "category":"Retail",
            "subcategory":"Laundry & Dry Cleaning",
            "type":"Services"
        }
    ],
    "sg:phone":"+1 604 733 5616",
    "sg:postcode":"V6H 3G1",
    "sg:province":"BC",
    "sg:tags":[
        "cleaners",
        "carpet",
        "dealer",
        "rug"
    ],
    "wof:name":"Ararat Oriental Rug CO Ltd",
    "wof:placetype":"venue"
},
  "geometry": {"coordinates":[-123.138695,49.265972],"type":"Point"}
}