{
  "type": "Feature",
  "properties": {
    "addr:full":"Duncan BC V9L 4X3",
    "addr:postcode":"v9l 4x3",
    "iso:country":"CA",
    "sg:city":"Duncan",
    "sg:classifiers":[
        {
            "category":"Shopping",
            "type":"Retail Goods"
        }
    ],
    "sg:phone":"+1 250 715 0200",
    "sg:postcode":"V9L 4X3",
    "sg:province":"BC",
    "sg:tags":[
        "equipment",
        "beer",
        "wine",
        "supply"
    ],
    "wof:name":"Wine Kitz",
    "wof:placetype":"venue"
},
  "geometry": {"coordinates":[-123.70738220200001,48.779094696],"type":"Point"}
}