{
  "type": "Feature",
  "properties": {
    "addr:full":"47 Ipswich Terr Kanata ON K2K 2R4",
    "addr:housenumber":"47",
    "addr:postcode":"k2k 2r4",
    "addr:street":"Terr",
    "iso:country":"CA",
    "sg:address":"47 Ipswich Terr",
    "sg:city":"Kanata",
    "sg:classifiers":[
        {
            "category":"Professional",
            "subcategory":"Management & Consulting",
            "type":"Services"
        }
    ],
    "sg:phone":"+1 613 591 3075",
    "sg:postcode":"K2K 2R4",
    "sg:province":"ON",
    "sg:tags":[
        "consultant",
        "business"
    ],
    "wof:name":"H W Dubois & Assoc",
    "wof:placetype":"venue"
},
  "geometry": {"coordinates":[-75.9353485107,45.3457794189],"type":"Point"}
}