{
  "type": "Feature",
  "properties": {
    "addr:full":"5204 50th St Viking AB T0B 4N0",
    "addr:housenumber":"5204",
    "addr:postcode":"t0b 4n0",
    "addr:street":"50Th St",
    "iso:country":"CA",
    "sg:address":"5204 50th St",
    "sg:city":"Viking",
    "sg:classifiers":[
        {
            "category":"Professional",
            "subcategory":"Printing & Photocopies",
            "type":"Services"
        }
    ],
    "sg:phone":"+1 780 336 2080",
    "sg:postcode":"T0B 4N0",
    "sg:province":"AB",
    "sg:tags":[
        "duplicating",
        "copying"
    ],
    "wof:name":"Troll Printing",
    "wof:placetype":"venue"
},
  "geometry": {"coordinates":[-111.777885,53.094597],"type":"Point"}
}