{
  "type": "Feature",
  "properties": {
    "addr:full":"Etobicoke ON M9V 5H1",
    "addr:postcode":"m9v 5h1",
    "iso:country":"CA",
    "sg:city":"Etobicoke",
    "sg:classifiers":[
        {
            "category":"Professional",
            "subcategory":"Accounting & Tax Preparation",
            "type":"Services"
        }
    ],
    "sg:phone":"+1 416 746 4440",
    "sg:postcode":"M9V 5H1",
    "sg:province":"ON",
    "sg:tags":[
        "accountant"
    ],
    "wof:name":"Vona, Leslie F CA",
    "wof:placetype":"venue"
},
  "geometry": {"coordinates":[-79.60916899999999,43.753708],"type":"Point"}
}