{
  "type": "Feature",
  "properties": {
    "iso:country":"CA",
    "sg:city":"Port Sydney",
    "sg:classifiers":[
        {
            "category":"Organizations",
            "subcategory":"Religious Organization",
            "type":"Services"
        }
    ],
    "sg:phone":"+1 705 385 1606",
    "sg:postcode":"P0B 1L0",
    "sg:province":"ON",
    "sg:tags":[
        "church"
    ],
    "wof:name":"Deer Lake Gospel Hall",
    "wof:placetype":"venue"
},
  "geometry": {"coordinates":[-79.2761764526,45.2136917114],"type":"Point"}
}