{
  "type": "Feature",
  "properties": {
    "addr:full":"3790 Alfred Ave Smithers BC V0J 2N0",
    "addr:housenumber":"3790",
    "addr:postcode":"v0j 2n0",
    "addr:street":"Alfred Ave",
    "iso:country":"CA",
    "sg:address":"3790 Alfred Ave",
    "sg:city":"Smithers",
    "sg:classifiers":[
        {
            "category":"Airline",
            "type":"Transportation"
        }
    ],
    "sg:phone":"+1 250 847 5613",
    "sg:postcode":"V0J 2N0",
    "sg:province":"BC",
    "sg:tags":[
        "company"
    ],
    "wof:name":"Central Mountain Air Ltd",
    "wof:placetype":"venue"
},
  "geometry": {"coordinates":[-127.174622,54.778851],"type":"Point"}
}