{
  "type": "Feature",
  "properties": {
    "addr:full":"PO Box 652 Two Hills AB T0B 4K0",
    "addr:housenumber":"po",
    "addr:postcode":"t0b 4k0",
    "addr:street":"Box 652",
    "iso:country":"CA",
    "sg:address":"PO Box 652",
    "sg:city":"Two Hills",
    "sg:classifiers":[
        {
            "category":"Recreation",
            "type":"Entertainment"
        }
    ],
    "sg:phone":"+1 780 657 2395",
    "sg:postcode":"T0B 4K0",
    "sg:province":"AB",
    "sg:tags":[
        "pool",
        "swimming"
    ],
    "wof:name":"Two Hills & District Swimming",
    "wof:placetype":"venue"
},
  "geometry": {"coordinates":[-111.74181400000001,53.715511],"type":"Point"}
}