{
  "type": "Feature",
  "properties": {
    "addr:full":"3219 Route 535 Cocagne NB E4R 3E4",
    "addr:housenumber":"3219",
    "addr:postcode":"e4r 3e4",
    "addr:street":"Route 535",
    "iso:country":"CA",
    "sg:address":"3219 Route 535",
    "sg:city":"Cocagne",
    "sg:classifiers":[
        {
            "category":"Food & Beverages",
            "subcategory":"Groceries & Convenience Stores",
            "type":"Retail Goods"
        }
    ],
    "sg:phone":"+1 506 576 8131",
    "sg:postcode":"E4R 3E4",
    "sg:province":"NB",
    "wof:name":"Depanneur Cormierville Cnvnc",
    "wof:placetype":"venue"
},
  "geometry": {"coordinates":[-64.61432600000001,46.333805],"type":"Point"}
}