{
  "type": "Feature",
  "properties": {
    "addr:full":"444 Ch Bradley Saint-Armand QC J0J 1T0",
    "addr:housenumber":"444",
    "addr:postcode":"j0j 1t0",
    "addr:street":"Ch Bradley",
    "iso:country":"CA",
    "sg:address":"444 Ch Bradley",
    "sg:city":"Saint-Armand",
    "sg:classifiers":[
        {
            "category":"Government",
            "subcategory":"Office",
            "type":"Public Place"
        }
    ],
    "sg:phone":"+1 450 248 2344",
    "sg:postcode":"J0J 1T0",
    "sg:province":"QC",
    "sg:tags":[
        "village"
    ],
    "wof:name":"St-Armand Ouest",
    "wof:placetype":"venue"
},
  "geometry": {"coordinates":[-73.042625,45.031803],"type":"Point"}
}