{
  "type": "Feature",
  "properties": {
    "addr:full":"590 Abilene Dr Mississauga ON L5T 2T4",
    "addr:housenumber":"590",
    "addr:postcode":"l5t 2t4",
    "addr:street":"Abilene Dr",
    "iso:country":"CA",
    "sg:address":"590 Abilene Dr",
    "sg:city":"Mississauga",
    "sg:classifiers":[
        {
            "category":"Manufacturing",
            "subcategory":"Rubber & Plastics",
            "type":"Manufacturing & Wholesale Goods"
        }
    ],
    "sg:phone":"+1 905 565 1055",
    "sg:postcode":"L5T 2T4",
    "sg:province":"ON",
    "wof:name":"Collins & Aikman Plastics Ltd",
    "wof:placetype":"venue"
},
  "geometry": {"coordinates":[-79.66864776609999,43.6398124695],"type":"Point"}
}