{
  "type": "Feature",
  "properties": {
    "addr:full":"2372 Finch Ave W North York ON M9M 2C7",
    "addr:housenumber":"2372",
    "addr:postcode":"m9m 2c7",
    "addr:street":"Finch Ave W",
    "iso:country":"CA",
    "sg:address":"2372 Finch Ave W",
    "sg:city":"North York",
    "sg:classifiers":[
        {
            "category":"Restaurant",
            "type":"Food & Drink"
        }
    ],
    "sg:phone":"+1 416 749 9087",
    "sg:postcode":"M9M 2C7",
    "sg:province":"ON",
    "wof:name":"Burger King",
    "wof:placetype":"venue"
},
  "geometry": {"coordinates":[-79.54583700000001,43.75148],"type":"Point"}
}