{
  "type": "Feature",
  "properties": {
    "addr:full":"310 Rte DE LA Montagne Notre-Dame-Du-Portage QC G0L 1Y0",
    "addr:housenumber":"310",
    "addr:postcode":"g0l 1y0",
    "addr:street":"Rte De La Montagne",
    "iso:country":"CA",
    "sg:address":"310 Rte DE LA Montagne",
    "sg:city":"Notre-Dame-Du-Portage",
    "sg:classifiers":[
        {
            "category":"Building & Trades",
            "subcategory":"Construction",
            "type":"Services"
        }
    ],
    "sg:phone":"+1 418 862 5552",
    "sg:postcode":"G0L 1Y0",
    "sg:province":"QC",
    "sg:tags":[
        "painter"
    ],
    "wof:name":"Decoration Peinture L Lapointe",
    "wof:placetype":"venue"
},
  "geometry": {"coordinates":[-69.592438,47.783455],"type":"Point"}
}