{
  "type": "Feature",
  "properties": {
    "addr:full":"121 Main St Kelliher SK S0A 1V0",
    "addr:housenumber":"121",
    "addr:postcode":"s0a 1v0",
    "addr:street":"Main St",
    "iso:country":"CA",
    "sg:address":"121 Main St",
    "sg:city":"Kelliher",
    "sg:classifiers":[
        {
            "category":"Restaurant",
            "type":"Food & Drink"
        }
    ],
    "sg:phone":"+1 306 675 4595",
    "sg:postcode":"S0A 1V0",
    "sg:province":"SK",
    "wof:name":"Emerald Restaurant",
    "wof:placetype":"venue"
},
  "geometry": {"coordinates":[-103.73799099999999,51.26207],"type":"Point"}
}