{
  "type": "Feature",
  "properties": {
    "addr:full":"715 Av Castelneau Saint-Hyacinthe QC J2S 6S5",
    "addr:housenumber":"715",
    "addr:postcode":"j2s 6s5",
    "addr:street":"Av Castelneau",
    "iso:country":"CA",
    "sg:address":"715 Av Castelneau",
    "sg:city":"Saint-Hyacinthe",
    "sg:classifiers":[
        {
            "category":"Shopping",
            "subcategory":"Bicycles & Sporting Goods",
            "type":"Retail Goods"
        }
    ],
    "sg:phone":"+1 450 778 3408",
    "sg:postcode":"J2S 6S5",
    "sg:province":"QC",
    "wof:name":"Centre DE Plongee Norsud",
    "wof:placetype":"venue"
},
  "geometry": {"coordinates":[-72.9719238281,45.6065597534],"type":"Point"}
}