{
  "type": "Feature",
  "properties": {
    "addr:full":"1009 Rue Fleury E Montreal QC H2C 1P8",
    "addr:housenumber":"1009",
    "addr:postcode":"h2c 1p8",
    "addr:street":"Rue Fleury E",
    "iso:country":"CA",
    "sg:address":"1009 Rue Fleury E",
    "sg:city":"Montreal",
    "sg:classifiers":[
        {
            "category":"Shopping",
            "subcategory":"Jewelry",
            "type":"Retail Goods"
        }
    ],
    "sg:phone":"+1 514 387 0668",
    "sg:postcode":"H2C 1P8",
    "sg:province":"QC",
    "sg:tags":[
        "jeweler"
    ],
    "wof:name":"Bijouterie Chayer",
    "wof:placetype":"venue"
},
  "geometry": {"coordinates":[-73.6594161987,45.5578804016],"type":"Point"}
}