{
  "type": "Feature",
  "properties": {
    "addr:full":"Stoney Creek ON L8E 4W3",
    "addr:postcode":"l8e 4w3",
    "iso:country":"CA",
    "sg:city":"Stoney Creek",
    "sg:classifiers":[
        {
            "category":"Manufacturing",
            "subcategory":"Printing",
            "type":"Manufacturing & Wholesale Goods"
        }
    ],
    "sg:phone":"+1 905 664 2933",
    "sg:postcode":"L8E 4W3",
    "sg:province":"ON",
    "sg:tags":[
        "printer"
    ],
    "wof:name":"Allegra Print & Imaging",
    "wof:placetype":"venue"
},
  "geometry": {"coordinates":[-79.7364807129,43.2316207886],"type":"Point"}
}