{
  "type": "Feature",
  "properties": {
    "addr:full":"755 Rue Des Seigneurs Montreal QC H3J 1Y2",
    "addr:housenumber":"755",
    "addr:postcode":"h3j 1y2",
    "addr:street":"Rue Des Seigneurs",
    "iso:country":"CA",
    "sg:address":"755 Rue Des Seigneurs",
    "sg:city":"Montreal",
    "sg:classifiers":[
        {
            "category":"Social Services",
            "type":"Services"
        }
    ],
    "sg:phone":"+1 514 931 8830",
    "sg:postcode":"H3J 1Y2",
    "sg:province":"QC",
    "sg:tags":[
        "organization",
        "welfare"
    ],
    "wof:name":"Gardemanger Pour Tous Inc",
    "wof:placetype":"venue"
},
  "geometry": {"coordinates":[-73.5730056763,45.4896659851],"type":"Point"}
}