{
  "type": "Feature",
  "properties": {
    "iso:country":"CA",
    "sg:city":"Alder Flats",
    "sg:classifiers":[
        {
            "category":"Building & Trades",
            "subcategory":"Construction",
            "type":"Services"
        }
    ],
    "sg:phone":"+1 780 388 3996",
    "sg:postcode":"T0C 0A0",
    "sg:province":"AB",
    "sg:tags":[
        "sand",
        "gravel",
        "general",
        "contractor"
    ],
    "wof:name":"RI-Dale Trucking Sand & Gravel",
    "wof:placetype":"venue"
},
  "geometry": {"coordinates":[-114.96631622300001,52.9313697815],"type":"Point"}
}