{
  "type": "Feature",
  "properties": {
    "iso:country":"CA",
    "sg:address":"885 Main St W",
    "sg:city":"Listowel",
    "sg:classifiers":[
        {
            "category":"Retail",
            "subcategory":"Auto Repair",
            "type":"Services"
        }
    ],
    "sg:phone":"+1 519 291 2555",
    "sg:postcode":"N4W 1B4",
    "sg:province":"ON",
    "sg:tags":[
        "repairing",
        "automobile"
    ],
    "wof:name":"Listowel Automotive Spec Svc",
    "wof:placetype":"venue"
},
  "geometry": {"coordinates":[-80.9641494751,43.7362327576],"type":"Point"}
}