{
  "type": "Feature",
  "properties": {
    "addr:full":"147 Union St Berwick NS B0P 1E0",
    "addr:housenumber":"147",
    "addr:postcode":"b0p 1e0",
    "addr:street":"Union St",
    "iso:country":"CA",
    "sg:address":"147 Union St",
    "sg:city":"Berwick",
    "sg:classifiers":[
        {
            "category":"Home & Garden",
            "subcategory":"Building Materials",
            "type":"Retail Goods"
        }
    ],
    "sg:phone":"+1 902 538 3126",
    "sg:postcode":"B0P 1E0",
    "sg:province":"NS",
    "wof:name":"Berwick Building Supplies Ltd",
    "wof:placetype":"venue"
},
  "geometry": {"coordinates":[-64.738129,45.042988],"type":"Point"}
}