{
  "type": "Feature",
  "properties": {
    "addr:full":"Richmond BC V6Y 2G5",
    "addr:postcode":"v6y 2g5",
    "iso:country":"CA",
    "sg:city":"Richmond",
    "sg:classifiers":[
        {
            "category":"Social Services",
            "type":"Services"
        }
    ],
    "sg:phone":"+1 604 279 5599",
    "sg:postcode":"V6Y 2G5",
    "sg:province":"BC",
    "sg:tags":[
        "organization",
        "welfare"
    ],
    "wof:name":"Touchstone Family Assn",
    "wof:placetype":"venue"
},
  "geometry": {"coordinates":[-123.13387299999999,49.16748],"type":"Point"}
}