{
  "type": "Feature",
  "properties": {
    "addr:full":"244 Elgin Rd Dorchester ON N0L 1G4",
    "addr:housenumber":"244",
    "addr:postcode":"n0l 1g4",
    "addr:street":"Elgin Rd",
    "iso:country":"CA",
    "sg:address":"244 Elgin Rd",
    "sg:city":"Dorchester",
    "sg:classifiers":[
        {
            "category":"Wholesale",
            "subcategory":"Plants",
            "type":"Manufacturing & Wholesale Goods"
        }
    ],
    "sg:phone":"+1 519 285 3243",
    "sg:postcode":"N0L 1G4",
    "sg:province":"ON",
    "sg:tags":[
        "florist"
    ],
    "wof:name":"Frank Van Dam Greenhouses Ltd",
    "wof:placetype":"venue"
},
  "geometry": {"coordinates":[-81.04883599999999,43.029499],"type":"Point"}
}