{
  "type": "Feature",
  "properties": {
    "addr:full":"4800 Av Papineau Montreal QC H2H 1V6",
    "addr:housenumber":"4800",
    "addr:postcode":"h2h 1v6",
    "addr:street":"Av Papineau",
    "iso:country":"CA",
    "sg:address":"4800 Av Papineau",
    "sg:city":"Montreal",
    "sg:classifiers":[
        {
            "category":"Food & Beverages",
            "subcategory":"Groceries & Convenience Stores",
            "type":"Retail Goods"
        }
    ],
    "sg:phone":"+1 514 526 8254",
    "sg:postcode":"H2H 1V6",
    "sg:province":"QC",
    "wof:name":"Depanneur Papineau",
    "wof:placetype":"venue"
},
  "geometry": {"coordinates":[-73.5782318115,45.5345077515],"type":"Point"}
}