{
  "type": "Feature",
  "properties": {
    "addr:full":"18 Walker Dr Charlottetown PE C1A 8S6",
    "addr:housenumber":"18",
    "addr:postcode":"c1a 8s6",
    "addr:street":"Walker Dr",
    "iso:country":"CA",
    "sg:address":"18 Walker Dr",
    "sg:city":"Charlottetown",
    "sg:classifiers":[
        {
            "category":"Taxi",
            "type":"Transportation"
        }
    ],
    "sg:phone":"+1 902 892 6561",
    "sg:postcode":"C1A 8S6",
    "sg:province":"PE",
    "sg:tags":[
        "taxicab"
    ],
    "wof:name":"Yellow Cab",
    "wof:placetype":"venue"
},
  "geometry": {"coordinates":[-63.114128,46.254776],"type":"Point"}
}