{
  "type": "Feature",
  "properties": {
    "addr:full":"2701 32 Ave NE Calgary AB T1Y 2G1",
    "addr:housenumber":"2701",
    "addr:postcode":"t1y 2g1",
    "addr:street":"32 Ave Ne",
    "iso:country":"CA",
    "sg:address":"2701 32 Ave NE",
    "sg:city":"Calgary",
    "sg:classifiers":[
        {
            "category":"Autos & Motor Vehicles",
            "subcategory":"Automobile Sales",
            "type":"Retail Goods"
        }
    ],
    "sg:phone":"+1 403 291 1578",
    "sg:postcode":"T1Y 2G1",
    "sg:province":"AB",
    "sg:tags":[
        "car",
        "parts",
        "supply"
    ],
    "wof:name":"Contemporary Motorsports",
    "wof:placetype":"venue"
},
  "geometry": {"coordinates":[-113.997879,51.081226],"type":"Point"}
}