{
  "type": "Feature",
  "properties": {
    "addr:full":"1250 Boul Charest O Quebec QC G1N 2E3",
    "addr:housenumber":"1250",
    "addr:postcode":"g1n 2e3",
    "addr:street":"Boul Charest O",
    "iso:country":"CA",
    "sg:address":"1250 Boul Charest O",
    "sg:city":"Quebec",
    "sg:classifiers":[
        {
            "category":"Autos & Motor Vehicles",
            "subcategory":"Fuel & Gas Station",
            "type":"Retail Goods"
        }
    ],
    "sg:phone":"+1 418 681 3325",
    "sg:postcode":"G1N 2E3",
    "sg:province":"QC",
    "sg:tags":[
        "oil"
    ],
    "wof:name":"Ultramar",
    "wof:placetype":"venue"
},
  "geometry": {"coordinates":[-71.255493,46.799854],"type":"Point"}
}