{
  "type": "Feature",
  "properties": {
    "addr:full":"1531 Michael St Ottawa ON K1B 3T3",
    "addr:housenumber":"1531",
    "addr:postcode":"k1b 3t3",
    "addr:street":"Michael St",
    "iso:country":"CA",
    "sg:address":"1531 Michael St",
    "sg:city":"Ottawa",
    "sg:classifiers":[
        {
            "category":"Retail",
            "subcategory":"Repair Shop",
            "type":"Services"
        }
    ],
    "sg:phone":"+1 613 724 0442",
    "sg:postcode":"K1B 3T3",
    "sg:province":"ON",
    "sg:tags":[
        "leather",
        "good"
    ],
    "wof:name":"Fibrenew Industries Ottawa",
    "wof:placetype":"venue"
},
  "geometry": {"coordinates":[-75.6265945435,45.4122505188],"type":"Point"}
}