{
  "type": "Feature",
  "properties": {
    "addr:full":"4831 48 St NW Calgary AB T3A 0S5",
    "addr:housenumber":"4831",
    "addr:postcode":"t3a 0s5",
    "addr:street":"48 St Nw",
    "iso:country":"CA",
    "sg:address":"4831 48 St NW",
    "sg:city":"Calgary",
    "sg:classifiers":[
        {
            "category":"Professional",
            "subcategory":"Advertising",
            "type":"Services"
        }
    ],
    "sg:phone":"+1 403 288 8828",
    "sg:postcode":"T3A 0S5",
    "sg:province":"AB",
    "sg:tags":[
        "counselor"
    ],
    "wof:name":"Western Canada Press",
    "wof:placetype":"venue"
},
  "geometry": {"coordinates":[-114.157524,51.095547],"type":"Point"}
}