{
  "type": "Feature",
  "properties": {
    "addr:full":"Isle-Aux-Coudres QC G0A 1X0",
    "addr:postcode":"g0a 1x0",
    "iso:country":"CA",
    "sg:city":"Isle-Aux-Coudres",
    "sg:classifiers":[
        {
            "category":"Building & Trades",
            "subcategory":"Electrical",
            "type":"Services"
        }
    ],
    "sg:phone":"+1 418 438 2122",
    "sg:postcode":"G0A 1X0",
    "sg:province":"QC",
    "sg:tags":[
        "electric",
        "contractor"
    ],
    "wof:name":"Entreprises D'Electricite",
    "wof:placetype":"venue"
},
  "geometry": {"coordinates":[-70.421173,47.398148],"type":"Point"}
}