{
  "type": "Feature",
  "properties": {
    "iso:country":"CA",
    "sg:address":"44 Princess St",
    "sg:city":"Kingston",
    "sg:classifiers":[
        {
            "category":"Food & Beverages",
            "subcategory":"Bakery",
            "type":"Retail Goods"
        }
    ],
    "sg:phone":"+1 613 531 4489",
    "sg:postcode":"K7L 1A4",
    "sg:province":"ON",
    "sg:tags":[
        "baker"
    ],
    "wof:name":"Pan Chancho Bakery",
    "wof:placetype":"venue"
},
  "geometry": {"coordinates":[-76.4804763794,44.2310943604],"type":"Point"}
}