{
  "type": "Feature",
  "properties": {
    "addr:full":"PO Box 20038 Rpo Downtown Edson AB T7E 1W4",
    "addr:housenumber":"po box",
    "addr:postcode":"20038;t7e 1w4",
    "addr:street":"Rpo",
    "iso:country":"CA",
    "sg:address":"PO Box 20038 Rpo Downtown",
    "sg:city":"Edson",
    "sg:classifiers":[
        {
            "category":"Mining & Drilling",
            "type":"Manufacturing & Wholesale Goods"
        }
    ],
    "sg:phone":"+1 780 712 1065",
    "sg:postcode":"T7E 1W4",
    "sg:province":"AB",
    "sg:tags":[
        "field",
        "oil"
    ],
    "wof:name":"Hi-Rock Contracting",
    "wof:placetype":"venue"
},
  "geometry": {"coordinates":[-116.43409729,53.5821304321],"type":"Point"}
}