{
  "type": "Feature",
  "properties": {
    "addr:full":"2275 Highway 20 # 17 Welland ON L3B 5N5",
    "addr:housenumber":"2275",
    "addr:postcode":"l3b 5n5",
    "addr:street":"Highway 20 # 17",
    "iso:country":"CA",
    "sg:address":"2275 Highway 20 # 17",
    "sg:city":"Welland",
    "sg:classifiers":[
        {
            "category":"Home & Garden",
            "subcategory":"Building Materials",
            "type":"Retail Goods"
        }
    ],
    "sg:phone":"+1 905 892 6697",
    "sg:postcode":"L3B 5N5",
    "sg:province":"ON",
    "sg:tags":[
        "door"
    ],
    "wof:name":"Fretworks International",
    "wof:placetype":"venue"
},
  "geometry": {"coordinates":[-79.239243,42.99345],"type":"Point"}
}