{
  "type": "Feature",
  "properties": {
    "addr:full":"6858 Veyaness Rd Saanichton BC V8M 2A8",
    "addr:housenumber":"6858",
    "addr:postcode":"v8m 2a8",
    "addr:street":"Veyaness Rd",
    "iso:country":"CA",
    "sg:address":"6858 Veyaness Rd",
    "sg:city":"Saanichton",
    "sg:classifiers":[
        {
            "category":"Autos & Motor Vehicles",
            "subcategory":"Auto Supplies",
            "type":"Retail Goods"
        }
    ],
    "sg:phone":"+1 250 812 1219",
    "sg:postcode":"V8M 2A8",
    "sg:province":"BC",
    "sg:tags":[
        "battery"
    ],
    "wof:name":"East Penn/Power Battery Sales",
    "wof:placetype":"venue"
},
  "geometry": {"coordinates":[-123.41689300500001,48.595199585],"type":"Point"}
}