{
  "type": "Feature",
  "properties": {
    "addr:full":"80 Old Kingston Rd Ajax ON L1T 2Z8",
    "addr:housenumber":"80",
    "addr:postcode":"l1t 2z8",
    "addr:street":"Old Kingston Rd",
    "iso:country":"CA",
    "sg:address":"80 Old Kingston Rd",
    "sg:city":"Ajax",
    "sg:classifiers":[
        {
            "category":"Personal",
            "subcategory":"Beauty Salon",
            "type":"Services"
        }
    ],
    "sg:phone":"+1 905 427 9367",
    "sg:postcode":"L1T 2Z8",
    "sg:province":"ON",
    "sg:tags":[
        "school"
    ],
    "wof:name":"Mistique Beauty Clinic & Spa",
    "wof:placetype":"venue"
},
  "geometry": {"coordinates":[-79.0589599609,43.8544578552],"type":"Point"}
}