{
  "type": "Feature",
  "properties": {
    "addr:full":"44 Church St E Brampton ON L6V 1G3",
    "addr:housenumber":"44",
    "addr:postcode":"l6v 1g3",
    "addr:street":"Church St E",
    "iso:country":"CA",
    "sg:address":"44 Church St E",
    "sg:city":"Brampton",
    "sg:classifiers":[
        {
            "category":"Organizations",
            "subcategory":"Religious Organization",
            "type":"Services"
        }
    ],
    "sg:phone":"+1 905 451 1723",
    "sg:postcode":"L6V 1G3",
    "sg:province":"ON",
    "sg:tags":[
        "church"
    ],
    "wof:name":"St Andrews Presbyterian Church",
    "wof:placetype":"venue"
},
  "geometry": {"coordinates":[-79.76078800000001,43.689899],"type":"Point"}
}