{
  "type": "Feature",
  "properties": {
    "addr:full":"Concord ON L4K 1X7",
    "addr:postcode":"l4k 1x7",
    "iso:country":"CA",
    "sg:city":"Concord",
    "sg:classifiers":[
        {
            "category":"Manufacturing",
            "subcategory":"Tools & Machinery",
            "type":"Manufacturing & Wholesale Goods"
        }
    ],
    "sg:phone":"+1 905 738 4252",
    "sg:postcode":"L4K 1X7",
    "sg:province":"ON",
    "sg:tags":[
        "alternator",
        "automobile",
        "electric"
    ],
    "wof:name":"Core Automotive Ltd",
    "wof:placetype":"venue"
},
  "geometry": {"coordinates":[-79.494179,43.79549],"type":"Point"}
}