{
  "type": "Feature",
  "properties": {
    "addr:full":"377 Vermilyea Rd Belleville ON K8N 4Z5",
    "addr:housenumber":"377",
    "addr:postcode":"k8n 4z5",
    "addr:street":"Vermilyea Rd",
    "iso:country":"CA",
    "sg:address":"377 Vermilyea Rd",
    "sg:city":"Belleville",
    "sg:classifiers":[
        {
            "category":"Retail",
            "subcategory":"Repair Shop",
            "type":"Services"
        }
    ],
    "sg:phone":"+1 613 968 7303",
    "sg:postcode":"K8N 4Z5",
    "sg:province":"ON",
    "sg:tags":[
        "engine"
    ],
    "wof:name":"Detlor's Sales & Svc",
    "wof:placetype":"venue"
},
  "geometry": {"coordinates":[-77.4248962402,44.2151603699],"type":"Point"}
}