{
  "type": "Feature",
  "properties": {
    "iso:country":"CA",
    "sg:address":"250 Rte DE L'Ermitage",
    "sg:city":"Lac-Bouchette",
    "sg:classifiers":[
        {
            "category":"Organizations",
            "subcategory":"Religious Organization",
            "type":"Services"
        }
    ],
    "sg:phone":"+1 418 348 6344",
    "sg:postcode":"G0W 1V0",
    "sg:province":"QC",
    "sg:tags":[
        "church"
    ],
    "wof:name":"Ermitage St-Antoine",
    "wof:placetype":"venue"
},
  "geometry": {"coordinates":[-72.2251281738,48.1680984497],"type":"Point"}
}