{
  "type": "Feature",
  "properties": {
    "addr:full":"103 Rue Dalhousie Quebec QC G1K 4B9",
    "addr:housenumber":"103",
    "addr:postcode":"g1k 4b9",
    "addr:street":"Rue Dalhousie",
    "iso:country":"CA",
    "sg:address":"103 Rue Dalhousie",
    "sg:city":"Quebec",
    "sg:classifiers":[
        {
            "category":"Communications",
            "subcategory":"Film & Video Production",
            "type":"Services"
        }
    ],
    "sg:phone":"+1 418 694 6165",
    "sg:postcode":"G1K 4B9",
    "sg:province":"QC",
    "sg:tags":[
        "motion",
        "picture",
        "casting"
    ],
    "wof:name":"Casting Cauffope Enr",
    "wof:placetype":"venue"
},
  "geometry": {"coordinates":[-71.202331543,46.8160896301],"type":"Point"}
}