{
  "type": "Feature",
  "properties": {
    "addr:full":"66 Rue Beausoleil Saint-Gabriel-DE-Brandon QC J0K 2N0",
    "addr:housenumber":"66",
    "addr:postcode":"j0k 2n0",
    "addr:street":"Rue Beausoleil",
    "iso:country":"CA",
    "sg:address":"66 Rue Beausoleil",
    "sg:city":"Saint-Gabriel-DE-Brandon",
    "sg:classifiers":[
        {
            "category":"Shopping",
            "subcategory":"Shoes",
            "type":"Retail Goods"
        }
    ],
    "sg:phone":"+1 450 835 2293",
    "sg:postcode":"J0K 2N0",
    "sg:province":"QC",
    "wof:name":"Magasin Maurice Enrg",
    "wof:placetype":"venue"
},
  "geometry": {"coordinates":[-73.3822021484,46.2927818298],"type":"Point"}
}