{
  "type": "Feature",
  "properties": {
    "addr:full":"42 Foundry Cres Markham ON L3P 6W4",
    "addr:housenumber":"42",
    "addr:postcode":"l3p 6w4",
    "addr:street":"Foundry Cres",
    "iso:country":"CA",
    "sg:address":"42 Foundry Cres",
    "sg:city":"Markham",
    "sg:classifiers":[
        {
            "category":"Building & Trades",
            "subcategory":"Plumbing",
            "type":"Services"
        }
    ],
    "sg:phone":"+1 905 472 2724",
    "sg:postcode":"L3P 6W4",
    "sg:province":"ON",
    "sg:tags":[
        "contractor"
    ],
    "wof:name":"Complete Plumbing Ltd",
    "wof:placetype":"venue"
},
  "geometry": {"coordinates":[-79.2658157349,43.8897247314],"type":"Point"}
}