{
  "type": "Feature",
  "properties": {
    "addr:full":"8094 Burnlake Dr Burnaby BC V5A 3X2",
    "addr:housenumber":"8094",
    "addr:postcode":"v5a 3x2",
    "addr:street":"Burnlake Dr",
    "iso:country":"CA",
    "sg:address":"8094 Burnlake Dr",
    "sg:city":"Burnaby",
    "sg:classifiers":[
        {
            "category":"Professional",
            "subcategory":"Engineering",
            "type":"Services"
        }
    ],
    "sg:phone":"+1 604 420 3310",
    "sg:postcode":"V5A 3X2",
    "sg:province":"BC",
    "sg:tags":[
        "engineer"
    ],
    "wof:name":"Scs Materials Engineers Ltd",
    "wof:placetype":"venue"
},
  "geometry": {"coordinates":[-122.929367,49.249023],"type":"Point"}
}