{
  "type": "Feature",
  "properties": {
    "addr:full":"2000 Jubilee Pky Campbell River BC V9H 1T5",
    "addr:housenumber":"2000",
    "addr:postcode":"v9h 1t5",
    "addr:street":"Jubilee Pky",
    "iso:country":"CA",
    "sg:address":"2000 Jubilee Pky",
    "sg:city":"Campbell River",
    "sg:classifiers":[
        {
            "category":"Airline",
            "type":"Transportation"
        }
    ],
    "sg:phone":"+1 250 926 6690",
    "sg:postcode":"V9H 1T5",
    "sg:province":"BC",
    "sg:tags":[
        "company"
    ],
    "wof:name":"Pacific Coastal Air",
    "wof:placetype":"venue"
},
  "geometry": {"coordinates":[-125.26889799999999,49.954353],"type":"Point"}
}