{
  "type": "Feature",
  "properties": {
    "iso:country":"CA",
    "sg:address":"8904 Boul Maurice-Duplessis",
    "sg:city":"Montreal",
    "sg:classifiers":[
        {
            "category":"Health Services",
            "subcategory":"Optometrist",
            "type":"Services"
        }
    ],
    "sg:phone":"+1 514 494 9933",
    "sg:postcode":"H1E 6X5",
    "sg:province":"QC",
    "wof:name":"Clinique D'Optometrie Rdp",
    "wof:placetype":"venue"
},
  "geometry": {"coordinates":[-73.57618,45.641323],"type":"Point"}
}