{
  "type": "Feature",
  "properties": {
    "addr:full":"8904 Boul Maurice-Duplessis Montreal QC H1E 6X5",
    "addr:housenumber":"8904",
    "addr:postcode":"h1e 6x5",
    "addr:street":"Boul Maurice-Duplessis",
    "iso:country":"CA",
    "sg:address":"8904 Boul Maurice-Duplessis",
    "sg:city":"Montreal",
    "sg:classifiers":[
        {
            "category":"Health Services",
            "subcategory":"Optometrist",
            "type":"Services"
        }
    ],
    "sg:phone":"+1 514 494 9933",
    "sg:postcode":"H1E 6X5",
    "sg:province":"QC",
    "wof:name":"Clinique D'Optometrie Rdp",
    "wof:placetype":"venue"
},
  "geometry": {"coordinates":[-73.57617999999999,45.641323],"type":"Point"}
}