{
  "type": "Feature",
  "properties": {
    "addr:full":"79 Route 216 Wotton QC J0A 1N0",
    "addr:housenumber":"79",
    "addr:postcode":"j0a 1n0",
    "addr:street":"Route 216",
    "iso:country":"CA",
    "sg:address":"79 Route 216",
    "sg:city":"Wotton",
    "sg:classifiers":[
        {
            "category":"Farming",
            "subcategory":"Farm & Veterinary Services",
            "type":"Manufacturing & Wholesale Goods"
        }
    ],
    "sg:phone":"+1 819 828 2593",
    "sg:postcode":"J0A 1N0",
    "sg:province":"QC",
    "sg:tags":[
        "insemination"
    ],
    "wof:name":"Cab DE Wooton",
    "wof:placetype":"venue"
},
  "geometry": {"coordinates":[-71.7778625488,45.7828292847],"type":"Point"}
}