{
  "type": "Feature",
  "properties": {
    "addr:full":"2889 Agricola St Halifax NS B3K 4E8",
    "addr:housenumber":"2889",
    "addr:postcode":"b3k 4e8",
    "addr:street":"Agricola St",
    "iso:country":"CA",
    "sg:address":"2889 Agricola St",
    "sg:city":"Halifax",
    "sg:classifiers":[
        {
            "category":"Building & Trades",
            "subcategory":"Plumbing",
            "type":"Services"
        }
    ],
    "sg:phone":"+1 902 477 0414",
    "sg:postcode":"B3K 4E8",
    "sg:province":"NS",
    "sg:tags":[
        "contractor"
    ],
    "wof:name":"Rollie's Plumbing & Heating",
    "wof:placetype":"venue"
},
  "geometry": {"coordinates":[-63.598961,44.659332],"type":"Point"}
}