{
  "type": "Feature",
  "properties": {
    "addr:full":"510 Lawrence Ave Kelowna BC V1Y 6L7",
    "addr:housenumber":"510",
    "addr:postcode":"v1y 6l7",
    "addr:street":"Lawrence Ave",
    "iso:country":"CA",
    "sg:address":"510 Lawrence Ave",
    "sg:city":"Kelowna",
    "sg:classifiers":[
        {
            "category":"Personal",
            "subcategory":"Beauty Salon",
            "type":"Services"
        }
    ],
    "sg:phone":"+1 250 861 4810",
    "sg:postcode":"V1Y 6L7",
    "sg:province":"BC",
    "wof:name":"Dressers Hair Salon",
    "wof:placetype":"venue"
},
  "geometry": {"coordinates":[-119.492851,49.885483],"type":"Point"}
}