{
  "type": "Feature",
  "properties": {
    "addr:full":"101 Boul Roland-Therrien Longueuil QC J4H 4B9",
    "addr:housenumber":"101",
    "addr:postcode":"j4h 4b9",
    "addr:street":"Boul Roland-Therrien",
    "iso:country":"CA",
    "sg:address":"101 Boul Roland-Therrien",
    "sg:city":"Longueuil",
    "sg:classifiers":[
        {
            "category":"Professional",
            "subcategory":"Lawyer & Legal Services",
            "type":"Services"
        }
    ],
    "sg:phone":"+1 450 679 0720",
    "sg:postcode":"J4H 4B9",
    "sg:province":"QC",
    "sg:tags":[
        "attorney"
    ],
    "wof:name":"Montgrain Mc Clure Gibeau",
    "wof:placetype":"venue"
},
  "geometry": {"coordinates":[-73.4965515137,45.5493011475],"type":"Point"}
}