{
  "type": "Feature",
  "properties": {
    "iso:country":"CA",
    "sg:address":"6235 Rue DE LA Villanelle",
    "sg:city":"Saint-Leonard",
    "sg:classifiers":[
        {
            "category":"Retail",
            "subcategory":"Repair Shop",
            "type":"Services"
        }
    ],
    "sg:phone":"+1 514 254 6563",
    "sg:postcode":"H1S 1W2",
    "sg:province":"QC",
    "sg:tags":[
        "appliance"
    ],
    "wof:name":"Reparations Vincenzo Floridia",
    "wof:placetype":"venue"
},
  "geometry": {"coordinates":[-73.57628631590001,45.5892410278],"type":"Point"}
}