{
  "type": "Feature",
  "properties": {
    "addr:full":"3 Softwood Dr Sault Ste Marie ON P6A 6R8",
    "addr:housenumber":"3",
    "addr:postcode":"p6a 6r8",
    "addr:street":"Softwood Dr",
    "iso:country":"CA",
    "sg:address":"3 Softwood Dr",
    "sg:city":"Sault Ste Marie",
    "sg:classifiers":[
        {
            "category":"Personal",
            "subcategory":"Beauty Salon",
            "type":"Services"
        }
    ],
    "sg:phone":"+1 705 945 0777",
    "sg:postcode":"P6A 6R8",
    "sg:province":"ON",
    "wof:name":"Kery's Kurls",
    "wof:placetype":"venue"
},
  "geometry": {"coordinates":[-84.250488,46.520191],"type":"Point"}
}