{
  "type": "Feature",
  "properties": {
    "addr:full":"116 Poplar Heights Dr Etobicoke ON M9A 4Z4",
    "addr:housenumber":"116",
    "addr:postcode":"m9a 4z4",
    "addr:street":"Poplar Heights Dr",
    "iso:country":"CA",
    "sg:address":"116 Poplar Heights Dr",
    "sg:city":"Etobicoke",
    "sg:classifiers":[
        {
            "category":"Real Estate",
            "subcategory":"Real Estate Agent",
            "type":"Services"
        }
    ],
    "sg:phone":"+1 416 244 1111",
    "sg:postcode":"M9A 4Z4",
    "sg:province":"ON",
    "wof:name":"Mandatory Real Estate Ltd",
    "wof:placetype":"venue"
},
  "geometry": {"coordinates":[-79.535622,43.67968],"type":"Point"}
}