{
  "type": "Feature",
  "properties": {
    "iso:country":"CA",
    "sg:city":"North York",
    "sg:classifiers":[
        {
            "category":"Building & Trades",
            "subcategory":"Equipment Rental",
            "type":"Services"
        }
    ],
    "sg:phone":"+1 416 499 6879",
    "sg:postcode":"M2J 4Y8",
    "sg:province":"ON",
    "sg:tags":[
        "leasing"
    ],
    "wof:name":"Equilease Corp",
    "wof:placetype":"venue"
},
  "geometry": {"coordinates":[-79.336235,43.772488],"type":"Point"}
}