{
  "type": "Feature",
  "properties": {
    "iso:country":"CA",
    "sg:address":"420 Ch Des Cormiers",
    "sg:city":"Saint-Gerard-Des-Laurentides",
    "sg:classifiers":[
        {
            "category":"Building & Trades",
            "subcategory":"Construction",
            "type":"Services"
        }
    ],
    "sg:phone":"+1 819 537 4422",
    "sg:postcode":"G9R 1A8",
    "sg:province":"QC",
    "sg:tags":[
        "repairing",
        "remodeling",
        "contractor"
    ],
    "wof:name":"Gouttieres Mauricienne Enr",
    "wof:placetype":"venue"
},
  "geometry": {"coordinates":[-73.75709533689999,45.8524208069],"type":"Point"}
}