{
  "type": "Feature",
  "properties": {
    "iso:country":"CA",
    "sg:address":"163 West Hastings Street Suite 207",
    "sg:city":"Vancouver",
    "sg:classifiers":[
        {
            "category":"Professional",
            "subcategory":"Computer Services",
            "type":"Services"
        }
    ],
    "sg:postcode":"V6B 1H5",
    "sg:tags":[
        "social-media",
        "marketing-tool",
        "contest-platform",
        "technology",
        "software",
        "api",
        "content-management"
    ],
    "sg:website":"http://www.strutta.com",
    "wof:name":"Strutta",
    "wof:placetype":"venue"
},
  "geometry": {"coordinates":[-123.110394,49.2846085],"type":"Point"}
}