{
  "type": "Feature",
  "properties": {
    "iso:country":"CA",
    "sg:city":"Scarborough",
    "sg:classifiers":[
        {
            "category":"Professional",
            "subcategory":"Printing & Photocopies",
            "type":"Services"
        }
    ],
    "sg:phone":"+1 416 298 6996",
    "sg:postcode":"M1P 3E3",
    "sg:province":"ON",
    "sg:tags":[
        "duplicating",
        "copying"
    ],
    "wof:name":"Xoxo Cyberprint Inc",
    "wof:placetype":"venue"
},
  "geometry": {"coordinates":[-79.27192687989999,43.7707939148],"type":"Point"}
}