{
  "type": "Feature",
  "properties": {
    "addr:full":"Bathurst NB E2A 1A9",
    "addr:postcode":"e2a 1a9",
    "iso:country":"CA",
    "sg:city":"Bathurst",
    "sg:classifiers":[
        {
            "category":"Health Services",
            "subcategory":"Health Practitioner",
            "type":"Services"
        }
    ],
    "sg:phone":"+1 506 546 2030",
    "sg:postcode":"E2A 1A9",
    "sg:province":"NB",
    "sg:tags":[
        "acupuncture",
        "therapist",
        "massage"
    ],
    "wof:name":"Clinique D'Acupuncture",
    "wof:placetype":"venue"
},
  "geometry": {"coordinates":[-65.6512298584,47.620513916],"type":"Point"}
}