{
  "type": "Feature",
  "properties": {
    "addr:full":"Scarborough ON M1N 4E3",
    "addr:postcode":"m1n 4e3",
    "iso:country":"CA",
    "sg:city":"Scarborough",
    "sg:classifiers":[
        {
            "category":"Restaurant",
            "type":"Food & Drink"
        }
    ],
    "sg:phone":"+1 416 699 5355",
    "sg:postcode":"M1N 4E3",
    "sg:province":"ON",
    "sg:tags":[
        "gourmet",
        "shop",
        "cafe"
    ],
    "wof:name":"Panda Bay Cafe",
    "wof:placetype":"venue"
},
  "geometry": {"coordinates":[-79.282646,43.680954],"type":"Point"}
}