{
  "type": "Feature",
  "properties": {
    "iso:country":"CA",
    "sg:address":"121 Ilsley Ave # K",
    "sg:city":"Dartmouth",
    "sg:classifiers":[
        {
            "category":"Wholesale",
            "subcategory":"Durable Goods & Equipment",
            "type":"Manufacturing & Wholesale Goods"
        }
    ],
    "sg:phone":"+1 902 468 6060",
    "sg:postcode":"B3B 1S4",
    "sg:province":"NS",
    "sg:tags":[
        "fire",
        "extinguisher",
        "protection"
    ],
    "wof:name":"Micmac Fire & Safety Ltd",
    "wof:placetype":"venue"
},
  "geometry": {"coordinates":[-63.58469,44.697479],"type":"Point"}
}