{
  "type": "Feature",
  "properties": {
    "addr:full":"Halifax NS B3J 3T2",
    "addr:postcode":"ns b3j 3t2",
    "iso:country":"CA",
    "sg:city":"Halifax",
    "sg:classifiers":[
        {
            "category":"Mining & Drilling",
            "type":"Manufacturing & Wholesale Goods"
        }
    ],
    "sg:phone":"+1 902 429 4511",
    "sg:postcode":"B3J 3T2",
    "sg:province":"NS",
    "sg:tags":[
        "development",
        "gas",
        "oil",
        "exploration"
    ],
    "wof:name":"Corridor Resources Inc",
    "wof:placetype":"venue"
},
  "geometry": {"coordinates":[-63.576092,44.64333],"type":"Point"}
}