{
  "type": "Feature",
  "properties": {
    "addr:full":"5 Fairview Mall Dr # 470 North York ON M2J 2Z1",
    "addr:housenumber":"5",
    "addr:postcode":"m2j 2z1",
    "addr:street":"Fairview Mall Dr # 470",
    "iso:country":"CA",
    "sg:address":"5 Fairview Mall Dr # 470",
    "sg:city":"North York",
    "sg:classifiers":[
        {
            "category":"Health Services",
            "subcategory":"Doctor",
            "type":"Services"
        }
    ],
    "sg:phone":"+1 416 499 2716",
    "sg:postcode":"M2J 2Z1",
    "sg:province":"ON",
    "sg:tags":[
        "physician",
        "surgeon"
    ],
    "wof:name":"Krajny, M J MD",
    "wof:placetype":"venue"
},
  "geometry": {"coordinates":[-79.3483200073,43.7790222168],"type":"Point"}
}