{
  "type": "Feature",
  "properties": {
    "addr:full":"4031 Line 13 N Warminster ON L0K 2G0",
    "addr:housenumber":"4031",
    "addr:postcode":"l0k 2g0",
    "addr:street":"Line 13 N",
    "iso:country":"CA",
    "sg:address":"4031 Line 13 N",
    "sg:city":"Warminster",
    "sg:classifiers":[
        {
            "category":"Education",
            "subcategory":"School",
            "type":"Public Place"
        }
    ],
    "sg:phone":"+1 705 325 6711",
    "sg:postcode":"L0K 2G0",
    "sg:province":"ON",
    "wof:name":"Warminster School",
    "wof:placetype":"venue"
},
  "geometry": {"coordinates":[-79.54528000000001,44.637646],"type":"Point"}
}