{
  "type": "Feature",
  "properties": {
    "addr:full":"Creston BC V0B 1G2",
    "addr:postcode":"bc v0b 1g2",
    "iso:country":"CA",
    "sg:city":"Creston",
    "sg:classifiers":[
        {
            "category":"Education",
            "subcategory":"School",
            "type":"Public Place"
        }
    ],
    "sg:phone":"+1 250 428 4428",
    "sg:postcode":"V0B 1G2",
    "sg:province":"BC",
    "wof:name":"Lower Kootenay Band School",
    "wof:placetype":"venue"
},
  "geometry": {"coordinates":[-116.523620605,49.0982208252],"type":"Point"}
}