{
  "type": "Feature",
  "properties": {
    "iso:country":"CA",
    "sg:address":"720 John St",
    "sg:city":"Mattawa",
    "sg:classifiers":[
        {
            "category":"Autos & Motor Vehicles",
            "subcategory":"Fuel & Gas Station",
            "type":"Retail Goods"
        }
    ],
    "sg:phone":"+1 705 744 0726",
    "sg:postcode":"P0H 1V0",
    "sg:province":"ON",
    "sg:tags":[
        "oil"
    ],
    "wof:name":"Mr Gas",
    "wof:placetype":"venue"
},
  "geometry": {"coordinates":[-78.7087402344,46.3106117249],"type":"Point"}
}