{
  "type": "Feature",
  "properties": {
    "addr:full":"1001 Heritage Rd Rockland ON K4K 1R2",
    "addr:housenumber":"1001",
    "addr:postcode":"k4k 1r2",
    "addr:street":"Heritage Rd",
    "iso:country":"CA",
    "sg:address":"1001 Heritage Rd",
    "sg:city":"Rockland",
    "sg:classifiers":[
        {
            "category":"Education",
            "subcategory":"School",
            "type":"Public Place"
        }
    ],
    "sg:phone":"+1 613 446 7215",
    "sg:postcode":"K4K 1R2",
    "sg:province":"ON",
    "wof:name":"St Patrick Catholic Elem Schl",
    "wof:placetype":"venue"
},
  "geometry": {"coordinates":[-75.298019,45.540173],"type":"Point"}
}