{
  "type": "Feature",
  "properties": {
    "addr:full":"104 Brookside Cres Kitchener ON N2N 1H1",
    "addr:housenumber":"104",
    "addr:postcode":"n2n 1h1",
    "addr:street":"Brookside Cres",
    "iso:country":"CA",
    "sg:address":"104 Brookside Cres",
    "sg:city":"Kitchener",
    "sg:classifiers":[
        {
            "category":"Building & Trades",
            "subcategory":"Construction",
            "type":"Services"
        }
    ],
    "sg:phone":"+1 519 744 2488",
    "sg:postcode":"N2N 1H1",
    "sg:province":"ON",
    "sg:tags":[
        "general",
        "contractor"
    ],
    "wof:name":"Peer Construction Inc",
    "wof:placetype":"venue"
},
  "geometry": {"coordinates":[-80.5271453857,43.4218826294],"type":"Point"}
}