{
  "type": "Feature",
  "properties": {
    "addr:full":"3 Route 133 Shediac Cape NB E4P 3C8",
    "addr:housenumber":"3",
    "addr:postcode":"e4p 3c8",
    "addr:street":"Route 133 Shediac",
    "iso:country":"CA",
    "sg:address":"3 Route 133",
    "sg:city":"Shediac Cape",
    "sg:classifiers":[
        {
            "category":"Retail",
            "subcategory":"Auto Repair",
            "type":"Services"
        }
    ],
    "sg:phone":"+1 506 532 3530",
    "sg:postcode":"E4P 3C8",
    "sg:province":"NB",
    "sg:tags":[
        "repairing",
        "automobile"
    ],
    "wof:name":"Waite's Garage Ltd",
    "wof:placetype":"venue"
},
  "geometry": {"coordinates":[-64.5666809082,46.2378463745],"type":"Point"}
}