{
  "type": "Feature",
  "properties": {
    "addr:full":"7020 Boul Henri-Bourassa E Anjou QC H1E 7K7",
    "addr:housenumber":"7020",
    "addr:postcode":"h1e 7k7",
    "addr:street":"Boul Henri-Bourassa E",
    "iso:country":"CA",
    "sg:address":"7020 Boul Henri-Bourassa E",
    "sg:city":"Anjou",
    "sg:classifiers":[
        {
            "category":"Autos & Motor Vehicles",
            "subcategory":"Automobile Sales",
            "type":"Retail Goods"
        }
    ],
    "sg:phone":"+1 514 329 7777",
    "sg:postcode":"H1E 7K7",
    "sg:province":"QC",
    "sg:tags":[
        "car",
        "dealer"
    ],
    "wof:name":"Hyundai Gabriel",
    "wof:placetype":"venue"
},
  "geometry": {"coordinates":[-73.60111999999999,45.612717],"type":"Point"}
}