{
  "type": "Feature",
  "properties": {
    "addr:full":"22 Leeming St Hamilton ON L8L 5T3",
    "addr:housenumber":"22",
    "addr:postcode":"l8l 5t3",
    "addr:street":"Leeming St",
    "iso:country":"CA",
    "sg:address":"22 Leeming St",
    "sg:city":"Hamilton",
    "sg:classifiers":[
        {
            "category":"Social Services",
            "subcategory":"Child Care",
            "type":"Services"
        }
    ],
    "sg:phone":"+1 905 526 8441",
    "sg:postcode":"L8L 5T3",
    "sg:province":"ON",
    "wof:name":"Hamilton & District Council",
    "wof:placetype":"venue"
},
  "geometry": {"coordinates":[-79.848122,43.256821],"type":"Point"}
}