{
  "type": "Feature",
  "properties": {
    "addr:full":"25 Ritson Rd N Oshawa ON L1G 5P4",
    "addr:housenumber":"25",
    "addr:postcode":"l1g 5p4",
    "addr:street":"Ritson Rd N",
    "iso:country":"CA",
    "sg:address":"25 Ritson Rd N",
    "sg:city":"Oshawa",
    "sg:classifiers":[
        {
            "category":"Home & Garden",
            "subcategory":"Home Furnishings",
            "type":"Retail Goods"
        }
    ],
    "sg:phone":"+1 905 571 7244",
    "sg:postcode":"L1G 5P4",
    "sg:province":"ON",
    "sg:tags":[
        "fireplace",
        "maker",
        "cabinet"
    ],
    "wof:name":"Fireside Corner Ltd",
    "wof:placetype":"venue"
},
  "geometry": {"coordinates":[-78.85391235349999,43.90051651],"type":"Point"}
}