{
  "type": "Feature",
  "properties": {
    "addr:full":"575 Ninth Concession Rd Westport ON K0G 1X0",
    "addr:housenumber":"575",
    "addr:postcode":"k0g 1x0",
    "addr:street":"Ninth Concession Rd",
    "iso:country":"CA",
    "sg:address":"575 Ninth Concession Rd",
    "sg:city":"Westport",
    "sg:classifiers":[
        {
            "category":"Building & Trades",
            "subcategory":"Electrical",
            "type":"Services"
        }
    ],
    "sg:phone":"+1 613 273 6456",
    "sg:postcode":"K0G 1X0",
    "sg:province":"ON",
    "sg:tags":[
        "electric",
        "contractor"
    ],
    "wof:name":"Greg Beck Electric Plumbing",
    "wof:placetype":"venue"
},
  "geometry": {"coordinates":[-76.397446,44.679676],"type":"Point"}
}