{
  "type": "Feature",
  "properties": {
    "addr:full":"North York ON M3B 2M3",
    "addr:postcode":"m3b 2m3",
    "iso:country":"CA",
    "sg:city":"North York",
    "sg:classifiers":[
        {
            "category":"Insurance",
            "subcategory":"Insurance Agent",
            "type":"Services"
        }
    ],
    "sg:phone":"+1 416 410 1888",
    "sg:postcode":"M3B 2M3",
    "sg:province":"ON",
    "wof:name":"Allstate Insurance CO",
    "wof:placetype":"venue"
},
  "geometry": {"coordinates":[-79.36028289790001,43.7551002502],"type":"Point"}
}