{
  "type": "Feature",
  "properties": {
    "addr:full":"212 Av Des Cerisiers Orford QC J1X 6W8",
    "addr:housenumber":"212",
    "addr:postcode":"j1x 6w8",
    "addr:street":"Av Des Cerisiers",
    "iso:country":"CA",
    "sg:address":"212 Av Des Cerisiers",
    "sg:city":"Orford",
    "sg:classifiers":[
        {
            "category":"Building & Trades",
            "subcategory":"Plumbing",
            "type":"Services"
        }
    ],
    "sg:phone":"+1 819 847 0723",
    "sg:postcode":"J1X 6W8",
    "sg:province":"QC",
    "sg:tags":[
        "conditioning",
        "air",
        "system",
        "contractor"
    ],
    "wof:name":"G N Climatisation Inc",
    "wof:placetype":"venue"
},
  "geometry": {"coordinates":[-72.171005249,45.3201446533],"type":"Point"}
}