{
  "type": "Feature",
  "properties": {
    "addr:full":"75 Hastings St N Bancroft ON K0L 1C0",
    "addr:housenumber":"75",
    "addr:postcode":"k0l 1c0",
    "addr:street":"Hastings St N",
    "iso:country":"CA",
    "sg:address":"75 Hastings St N",
    "sg:city":"Bancroft",
    "sg:classifiers":[
        {
            "category":"Food & Beverages",
            "subcategory":"Specialty",
            "type":"Retail Goods"
        }
    ],
    "sg:phone":"+1 613 332 2323",
    "sg:postcode":"K0L 1C0",
    "sg:province":"ON",
    "sg:tags":[
        "water",
        "bulk",
        "company"
    ],
    "wof:name":"Clear Water Shop",
    "wof:placetype":"venue"
},
  "geometry": {"coordinates":[-77.85436199999999,45.058708],"type":"Point"}
}