{
  "type": "Feature",
  "properties": {
    "addr:full":"Parksville BC V9P 2G5",
    "addr:postcode":"v9p 2g5",
    "iso:country":"CA",
    "sg:city":"Parksville",
    "sg:classifiers":[
        {
            "category":"Health Services",
            "subcategory":"Chiropractor",
            "type":"Services"
        }
    ],
    "sg:phone":"+1 250 248 6333",
    "sg:postcode":"V9P 2G5",
    "sg:province":"BC",
    "wof:name":"Smith, Larry DC",
    "wof:placetype":"venue"
},
  "geometry": {"coordinates":[-124.25528,49.299152],"type":"Point"}
}