{
  "type": "Feature",
  "properties": {
    "addr:full":"14515 121A Ave NW Edmonton AB T5L 2T2",
    "addr:housenumber":"14515",
    "addr:postcode":"t5l 2t2",
    "addr:street":"121A Ave Nw",
    "iso:country":"CA",
    "sg:address":"14515 121A Ave NW",
    "sg:city":"Edmonton",
    "sg:classifiers":[
        {
            "category":"Shopping",
            "subcategory":"Computers & Home Electronics",
            "type":"Retail Goods"
        }
    ],
    "sg:phone":"+1 780 944 4698",
    "sg:postcode":"T5L 2T2",
    "sg:province":"AB",
    "sg:tags":[
        "parts",
        "supply"
    ],
    "wof:name":"Great Northern Data Supplies",
    "wof:placetype":"venue"
},
  "geometry": {"coordinates":[-113.572044373,53.5733985901],"type":"Point"}
}