{
  "type": "Feature",
  "properties": {
    "iso:country":"CA",
    "sg:address":"25 Langstaff Rd E",
    "sg:city":"Thornhill",
    "sg:classifiers":[
        {
            "category":"Wholesale",
            "subcategory":"Construction Materials",
            "type":"Manufacturing & Wholesale Goods"
        }
    ],
    "sg:phone":"+1 905 886 5787",
    "sg:postcode":"L3T 3P7",
    "sg:province":"ON",
    "sg:tags":[
        "sand",
        "gravel",
        "stone"
    ],
    "wof:name":"Beaver Valley Stone Ltd",
    "wof:placetype":"venue"
},
  "geometry": {"coordinates":[-79.426902771,43.8337974548],"type":"Point"}
}