{
  "type": "Feature",
  "properties": {
    "addr:full":"51 Victoria St E Alliston ON L9R 1L5",
    "addr:housenumber":"51",
    "addr:postcode":"l9r 1l5",
    "addr:street":"Victoria St E Alliston",
    "iso:country":"CA",
    "sg:address":"51 Victoria St E",
    "sg:city":"Alliston",
    "sg:classifiers":[
        {
            "category":"Shopping",
            "type":"Retail Goods"
        }
    ],
    "sg:phone":"+1 705 435 7951",
    "sg:postcode":"L9R 1L5",
    "sg:province":"ON",
    "sg:tags":[
        "monument"
    ],
    "wof:name":"Alliston Monuments",
    "wof:placetype":"venue"
},
  "geometry": {"coordinates":[-79.8667755127,44.1543769836],"type":"Point"}
}