{
  "type": "Feature",
  "properties": {
    "addr:full":"499 Rue Calixa-Lavallee Joliette QC J6E 7E2",
    "addr:housenumber":"499",
    "addr:postcode":"j6e 7e2",
    "addr:street":"Rue Calixa-Lavallee",
    "iso:country":"CA",
    "sg:address":"499 Rue Calixa-Lavallee",
    "sg:city":"Joliette",
    "sg:classifiers":[
        {
            "category":"Professional",
            "subcategory":"Management & Consulting",
            "type":"Services"
        }
    ],
    "sg:phone":"+1 450 753 5153",
    "sg:postcode":"J6E 7E2",
    "sg:province":"QC",
    "sg:tags":[
        "agricultural",
        "consultant"
    ],
    "wof:name":"Groupe Conseil Agricole",
    "wof:placetype":"venue"
},
  "geometry": {"coordinates":[-73.425529,46.023922],"type":"Point"}
}