{
  "type": "Feature",
  "properties": {
    "addr:full":"208 Rue Saint-Jacques Ste-Marguerite-DE-Dorchester QC G0S 2X0",
    "addr:housenumber":"208",
    "addr:postcode":"g0s 2x0",
    "addr:street":"Rue Saint-Jacques Ste-Marguerite-De-Dorchester",
    "iso:country":"CA",
    "sg:address":"208 Rue Saint-Jacques",
    "sg:city":"Ste-Marguerite-DE-Dorchester",
    "sg:classifiers":[
        {
            "category":"Insurance",
            "subcategory":"Insurance Agent",
            "type":"Services"
        }
    ],
    "sg:phone":"+1 418 935 3875",
    "sg:postcode":"G0S 2X0",
    "sg:province":"QC",
    "wof:name":"Services Financiers Le Nord",
    "wof:placetype":"venue"
},
  "geometry": {"coordinates":[-70.9372634888,46.5103874207],"type":"Point"}
}