{
  "type": "Feature",
  "properties": {
    "addr:full":"1696 Danforth Ave Toronto ON M4C 1H8",
    "addr:housenumber":"1696",
    "addr:postcode":"m4c 1h8",
    "addr:street":"Danforth Ave",
    "iso:country":"CA",
    "sg:address":"1696 Danforth Ave",
    "sg:city":"Toronto",
    "sg:classifiers":[
        {
            "category":"Personal",
            "subcategory":"Barber",
            "type":"Services"
        }
    ],
    "sg:phone":"+1 416 406 5075",
    "sg:postcode":"M4C 1H8",
    "sg:province":"ON",
    "wof:name":"Sams Mens Hairstyling",
    "wof:placetype":"venue"
},
  "geometry": {"coordinates":[-79.3207397461,43.6840553284],"type":"Point"}
}