{
  "type": "Feature",
  "properties": {
    "addr:full":"70 Sandown Ave Scarborough ON M1N 3W3",
    "addr:housenumber":"70",
    "addr:postcode":"m1n 3w3",
    "addr:street":"Sandown Ave",
    "iso:country":"CA",
    "sg:address":"70 Sandown Ave",
    "sg:city":"Scarborough",
    "sg:classifiers":[
        {
            "category":"Building & Trades",
            "subcategory":"Construction",
            "type":"Services"
        }
    ],
    "sg:phone":"+1 416 266 9536",
    "sg:postcode":"M1N 3W3",
    "sg:province":"ON",
    "sg:tags":[
        "home",
        "contractor",
        "improvement"
    ],
    "wof:name":"Legge Industries Ltd",
    "wof:placetype":"venue"
},
  "geometry": {"coordinates":[-79.2525939941,43.7122612],"type":"Point"}
}