{
  "type": "Feature",
  "properties": {
    "iso:country":"CA",
    "sg:city":"Varennes",
    "sg:classifiers":[
        {
            "category":"Manufacturing",
            "subcategory":"Tools & Machinery",
            "type":"Manufacturing & Wholesale Goods"
        }
    ],
    "sg:phone":"+1 450 929 3434",
    "sg:postcode":"J3X 1P7",
    "sg:province":"QC",
    "sg:tags":[
        "machine",
        "shop"
    ],
    "wof:name":"Industries Danmare Inc",
    "wof:placetype":"venue"
},
  "geometry": {"coordinates":[-73.416222,45.652287],"type":"Point"}
}