{
  "type": "Feature",
  "properties": {
    "addr:full":"Calgary AB T2G 2G8",
    "addr:postcode":"t2g 2g8",
    "iso:country":"CA",
    "sg:city":"Calgary",
    "sg:classifiers":[
        {
            "category":"Shopping",
            "subcategory":"Computers & Home Electronics",
            "type":"Retail Goods"
        }
    ],
    "sg:phone":"+1 403 263 9238",
    "sg:postcode":"T2G 2G8",
    "sg:province":"AB",
    "sg:tags":[
        "software"
    ],
    "wof:name":"Investment Planet Corp",
    "wof:placetype":"venue"
},
  "geometry": {"coordinates":[-114.06026458700001,51.0461769104],"type":"Point"}
}