{
  "type": "Feature",
  "properties": {
    "addr:full":"3515 Av Du Parc Montreal QC H2X 2H8",
    "addr:housenumber":"3515",
    "addr:postcode":"h2x 2h8",
    "addr:street":"Av Du Parc",
    "iso:country":"CA",
    "sg:address":"3515 Av Du Parc",
    "sg:city":"Montreal",
    "sg:classifiers":[
        {
            "category":"Retail",
            "subcategory":"Laundry & Dry Cleaning",
            "type":"Services"
        }
    ],
    "sg:phone":"+1 514 284 6837",
    "sg:postcode":"H2X 2H8",
    "sg:province":"QC",
    "sg:tags":[
        "cleaners"
    ],
    "wof:name":"Nettoyeur St Marc II",
    "wof:placetype":"venue"
},
  "geometry": {"coordinates":[-73.574005,45.509804],"type":"Point"}
}