{
  "type": "Feature",
  "properties": {
    "iso:country":"CA",
    "sg:address":"482 Belmont Ave W",
    "sg:city":"Kitchener",
    "sg:classifiers":[
        {
            "category":"Manufacturing",
            "subcategory":"Metals",
            "type":"Manufacturing & Wholesale Goods"
        }
    ],
    "sg:phone":"+1 519 745 8414",
    "sg:postcode":"N2M 1N3",
    "sg:province":"ON",
    "sg:tags":[
        "rubber",
        "stamp",
        "plastic"
    ],
    "wof:name":"Warwick Marking Products Ltd",
    "wof:placetype":"venue"
},
  "geometry": {"coordinates":[-80.5136795044,43.4468345642],"type":"Point"}
}