{
  "type": "Feature",
  "properties": {
    "iso:country":"CA",
    "sg:address":"8 Rue Panet",
    "sg:city":"Salaberry-DE-Valleyfield",
    "sg:classifiers":[
        {
            "category":"Health Services",
            "subcategory":"Health Practitioner",
            "type":"Services"
        }
    ],
    "sg:phone":"+1 450 373 8626",
    "sg:postcode":"J6S 4H1",
    "sg:province":"QC",
    "wof:name":"Leclerc, Manon",
    "wof:placetype":"venue"
},
  "geometry": {"coordinates":[-74.115906,45.266373],"type":"Point"}
}