{
  "type": "Feature",
  "properties": {
    "addr:full":"Shippagan NB E8S 3E1",
    "addr:postcode":"e8s 3e1",
    "iso:country":"CA",
    "sg:city":"Shippagan",
    "sg:classifiers":[
        {
            "category":"Retail",
            "subcategory":"Auto Repair",
            "type":"Services"
        }
    ],
    "sg:phone":"+1 506 336 4281",
    "sg:postcode":"E8S 3E1",
    "sg:province":"NB",
    "sg:tags":[
        "body",
        "automobile",
        "painting"
    ],
    "wof:name":"Mallet Debosselage Ltee",
    "wof:placetype":"venue"
},
  "geometry": {"coordinates":[-64.711258,47.744629],"type":"Point"}
}