{
  "type": "Feature",
  "properties": {
    "addr:full":"Sainte-Foy QC G1V 4W2",
    "addr:postcode":"g1v 4w2",
    "iso:country":"CA",
    "sg:city":"Sainte-Foy",
    "sg:classifiers":[
        {
            "category":"Professional",
            "subcategory":"Computer Services",
            "type":"Services"
        }
    ],
    "sg:phone":"+1 418 681 0151",
    "sg:postcode":"G1V 4W2",
    "sg:province":"QC",
    "sg:tags":[
        "project",
        "information",
        "management",
        "system",
        "consultant"
    ],
    "wof:name":"Services Conseils Systematix",
    "wof:placetype":"venue"
},
  "geometry": {"coordinates":[-71.281059,46.771248],"type":"Point"}
}