{
  "type": "Feature",
  "properties": {
    "addr:full":"PO Box 4500 STN South Cro Edmonton AB T6E 6K2",
    "addr:housenumber":"po",
    "addr:postcode":"4500 stn;t6e 6k2",
    "addr:street":"Box;South",
    "iso:country":"CA",
    "sg:address":"PO Box 4500 STN South Cro",
    "sg:city":"Edmonton",
    "sg:classifiers":[
        {
            "category":"Organizations",
            "subcategory":"Professional Association",
            "type":"Services"
        }
    ],
    "sg:phone":"+1 780 407 2620",
    "sg:postcode":"T6E 6K2",
    "sg:province":"AB",
    "wof:name":"Action on Smoking & Health Sn",
    "wof:placetype":"venue"
},
  "geometry": {"coordinates":[-113.490371704,53.5462188721],"type":"Point"}
}