{
  "type": "Feature",
  "properties": {
    "addr:full":"170 Bruce St Sault Ste Marie ON P6A 2X9",
    "addr:housenumber":"170",
    "addr:postcode":"p6a 2x9",
    "addr:street":"Bruce St",
    "iso:country":"CA",
    "sg:address":"170 Bruce St",
    "sg:city":"Sault Ste Marie",
    "sg:classifiers":[
        {
            "category":"Professional",
            "subcategory":"Accounting & Tax Preparation",
            "type":"Services"
        }
    ],
    "sg:phone":"+1 705 946 3360",
    "sg:postcode":"P6A 2X9",
    "sg:province":"ON",
    "sg:tags":[
        "return",
        "filing"
    ],
    "wof:name":"Superior Tax Action Svc Ltd",
    "wof:placetype":"venue"
},
  "geometry": {"coordinates":[-84.33358,46.514996],"type":"Point"}
}