{
  "type": "Feature",
  "properties": {
    "addr:full":"Ladysmith BC V9G 1B7",
    "addr:postcode":"v9g 1b7",
    "iso:country":"CA",
    "sg:city":"Ladysmith",
    "sg:classifiers":[
        {
            "category":"Social Services",
            "type":"Services"
        }
    ],
    "sg:phone":"+1 250 245 3466",
    "sg:postcode":"V9G 1B7",
    "sg:province":"BC",
    "sg:tags":[
        "organization",
        "welfare"
    ],
    "wof:name":"Supported Child Care CO-Ordntr",
    "wof:placetype":"venue"
},
  "geometry": {"coordinates":[-123.816299,48.993874],"type":"Point"}
}