{
  "type": "Feature",
  "properties": {
    "addr:full":"17 Cambridge St Cambridge ON N1R 3R8",
    "addr:housenumber":"17",
    "addr:postcode":"n1r 3r8",
    "addr:street":"Cambridge St",
    "iso:country":"CA",
    "sg:address":"17 Cambridge St",
    "sg:city":"Cambridge",
    "sg:classifiers":[
        {
            "category":"Social Services",
            "type":"Services"
        }
    ],
    "sg:phone":"+1 519 622 3699",
    "sg:postcode":"N1R 3R8",
    "sg:province":"ON",
    "sg:tags":[
        "organization",
        "welfare"
    ],
    "wof:name":"Developmental Services Access",
    "wof:placetype":"venue"
},
  "geometry": {"coordinates":[-80.31249200000001,43.361343],"type":"Point"}
}