{
  "type": "Feature",
  "properties": {
    "addr:full":"Guelph ON N1H 6J3",
    "addr:postcode":"n1h 6j3",
    "iso:country":"CA",
    "sg:city":"Guelph",
    "sg:classifiers":[
        {
            "category":"Freight",
            "type":"Transportation"
        }
    ],
    "sg:phone":"+1 519 824 6827",
    "sg:postcode":"N1H 6J3",
    "sg:province":"ON",
    "sg:tags":[
        "commercial",
        "storage"
    ],
    "wof:name":"Clark's Mini Storage",
    "wof:placetype":"venue"
},
  "geometry": {"coordinates":[-80.2683105469,43.5177993774],"type":"Point"}
}