{
  "type": "Feature",
  "properties": {
    "addr:full":"404 Nelson St Kingston ON K7K 4N2",
    "addr:housenumber":"404",
    "addr:postcode":"k7k 4n2",
    "addr:street":"Nelson St",
    "iso:country":"CA",
    "sg:address":"404 Nelson St",
    "sg:city":"Kingston",
    "sg:classifiers":[
        {
            "category":"Food & Beverages",
            "subcategory":"Groceries & Convenience Stores",
            "type":"Retail Goods"
        }
    ],
    "sg:phone":"+1 613 542 5424",
    "sg:postcode":"K7K 4N2",
    "sg:province":"ON",
    "wof:name":"Mc Laughlin Foods",
    "wof:placetype":"venue"
},
  "geometry": {"coordinates":[-76.5027999878,44.243309021],"type":"Point"}
}