{
  "type": "Feature",
  "properties": {
    "addr:full":"4873 Boul Saint-Laurent Montreal QC H2T 1R6",
    "addr:housenumber":"4873",
    "addr:postcode":"h2t 1r6",
    "addr:street":"Boul Saint-Laurent",
    "iso:country":"CA",
    "sg:address":"4873 Boul Saint-Laurent",
    "sg:city":"Montreal",
    "sg:classifiers":[
        {
            "category":"Restaurant",
            "type":"Food & Drink"
        }
    ],
    "sg:phone":"+1 514 284 0122",
    "sg:postcode":"H2T 1R6",
    "sg:province":"QC",
    "sg:tags":[
        "cafe"
    ],
    "wof:name":"Casa Del Popolo",
    "wof:placetype":"venue"
},
  "geometry": {"coordinates":[-73.589989,45.521942],"type":"Point"}
}