{
  "type": "Feature",
  "properties": {
    "addr:full":"Kelowna BC V1X 2J8",
    "addr:postcode":"v1x 2j8",
    "iso:country":"CA",
    "sg:city":"Kelowna",
    "sg:classifiers":[
        {
            "category":"Wholesale",
            "subcategory":"Machinery & Supplies",
            "type":"Manufacturing & Wholesale Goods"
        }
    ],
    "sg:phone":"+1 250 491 7235",
    "sg:postcode":"V1X 2J8",
    "sg:province":"BC",
    "sg:tags":[
        "concrete",
        "form",
        "equipment"
    ],
    "wof:name":"Unicon Concrete Specialties",
    "wof:placetype":"venue"
},
  "geometry": {"coordinates":[-119.402901,49.895508],"type":"Point"}
}