{
  "type": "Feature",
  "properties": {
    "addr:full":"24308 Lower Springbank Rd Calgary AB T3Z 3K2",
    "addr:housenumber":"24308",
    "addr:postcode":"t3z 3k2",
    "addr:street":"Lower Springbank Rd",
    "iso:country":"CA",
    "sg:address":"24308 Lower Springbank Rd",
    "sg:city":"Calgary",
    "sg:classifiers":[
        {
            "category":"Farming",
            "subcategory":"Nursery",
            "type":"Manufacturing & Wholesale Goods"
        }
    ],
    "sg:phone":"+1 403 246 0611",
    "sg:postcode":"T3Z 3K2",
    "sg:province":"AB",
    "sg:tags":[
        "greenhouse"
    ],
    "wof:name":"Country Gardens & Nursery",
    "wof:placetype":"venue"
},
  "geometry": {"coordinates":[-114.23419199999999,51.028801],"type":"Point"}
}