{
  "type": "Feature",
  "properties": {
    "addr:full":"963 Rue Sigouin Sainte-Adele QC J8B 1S2",
    "addr:housenumber":"963",
    "addr:postcode":"j8b 1s2",
    "addr:street":"Rue Sigouin Sainte-Adele",
    "iso:country":"CA",
    "sg:address":"963 Rue Sigouin",
    "sg:city":"Sainte-Adele",
    "sg:classifiers":[
        {
            "category":"Building & Trades",
            "subcategory":"Construction",
            "type":"Services"
        }
    ],
    "sg:phone":"+1 450 229 4220",
    "sg:postcode":"J8B 1S2",
    "sg:province":"QC",
    "sg:tags":[
        "excavating",
        "contractor"
    ],
    "wof:name":"Excavation A Dube & Fils Inc",
    "wof:placetype":"venue"
},
  "geometry": {"coordinates":[-74.13162199999999,45.951889],"type":"Point"}
}