{
  "type": "Feature",
  "properties": {
    "addr:full":"799 Av Cartier Quebec QC G1R 2R8",
    "addr:postcode":"g1r 2r8",
    "addr:street":"799 Av Cartier",
    "iso:country":"CA",
    "sg:address":"799 Av Cartier",
    "sg:city":"Quebec",
    "sg:classifiers":[
        {
            "category":"Restaurant",
            "type":"Food & Drink"
        }
    ],
    "sg:phone":"+1 418 523 4011",
    "sg:postcode":"G1R 2R8",
    "sg:province":"QC",
    "sg:tags":[
        "cafe"
    ],
    "wof:name":"Quartiers DE Lune",
    "wof:placetype":"venue"
},
  "geometry": {"coordinates":[-71.2281417847,46.8056182861],"type":"Point"}
}