{
  "type": "Feature",
  "properties": {
    "addr:full":"4664 Yonge St North York ON M2N 5M1",
    "addr:housenumber":"4664",
    "addr:postcode":"m2n 5m1",
    "addr:street":"Yonge St",
    "iso:country":"CA",
    "sg:address":"4664 Yonge St",
    "sg:city":"North York",
    "sg:classifiers":[
        {
            "category":"Retail",
            "subcategory":"Laundry & Dry Cleaning",
            "type":"Services"
        }
    ],
    "sg:phone":"+1 416 733 1456",
    "sg:postcode":"M2N 5M1",
    "sg:province":"ON",
    "sg:tags":[
        "cleaners"
    ],
    "wof:name":"Felix Cleaners",
    "wof:placetype":"venue"
},
  "geometry": {"coordinates":[-79.410263,43.758011],"type":"Point"}
}