{
  "type": "Feature",
  "properties": {
    "addr:full":"York ON M6N 4Z9",
    "addr:postcode":"m6n 4z9",
    "iso:country":"CA",
    "sg:city":"York",
    "sg:classifiers":[
        {
            "category":"Shopping",
            "subcategory":"Shoes",
            "type":"Retail Goods"
        }
    ],
    "sg:phone":"+1 416 760 8336",
    "sg:postcode":"M6N 4Z9",
    "sg:province":"ON",
    "wof:name":"Shoe Barn",
    "wof:placetype":"venue"
},
  "geometry": {"coordinates":[-79.474396,43.679211],"type":"Point"}
}