{
  "type": "Feature",
  "properties": {
    "addr:full":"78 Neville St Dominion NS B1G 1P6",
    "addr:housenumber":"78",
    "addr:postcode":"b1g 1p6",
    "addr:street":"Neville St",
    "iso:country":"CA",
    "sg:address":"78 Neville St",
    "sg:city":"Dominion",
    "sg:classifiers":[
        {
            "category":"Social Services",
            "type":"Services"
        }
    ],
    "sg:phone":"+1 902 849 2651",
    "sg:postcode":"B1G 1P6",
    "sg:province":"NS",
    "sg:tags":[
        "organization",
        "welfare"
    ],
    "wof:name":"Royal Canadian Legion",
    "wof:placetype":"venue"
},
  "geometry": {"coordinates":[-60.010578,46.207279],"type":"Point"}
}