{
  "type": "Feature",
  "properties": {
    "addr:full":"2095 43rd Ave W Vancouver BC V6M 2C8",
    "addr:housenumber":"2095",
    "addr:postcode":"v6m 2c8",
    "addr:street":"43Rd Ave W",
    "iso:country":"CA",
    "sg:address":"2095 43rd Ave W",
    "sg:city":"Vancouver",
    "sg:classifiers":[
        {
            "category":"Organizations",
            "subcategory":"Religious Organization",
            "type":"Services"
        }
    ],
    "sg:phone":"+1 604 261 7515",
    "sg:postcode":"V6M 2C8",
    "sg:province":"BC",
    "sg:tags":[
        "church"
    ],
    "wof:name":"Fourth Ch of Christ Scientist",
    "wof:placetype":"venue"
},
  "geometry": {"coordinates":[-123.154556,49.2328],"type":"Point"}
}