{
  "type": "Feature",
  "properties": {
    "addr:full":"2987 Skaha Lake Rd Penticton BC V2A 6G3",
    "addr:housenumber":"2987",
    "addr:postcode":"v2a 6g3",
    "addr:street":"Skaha Lake Rd",
    "iso:country":"CA",
    "sg:address":"2987 Skaha Lake Rd",
    "sg:city":"Penticton",
    "sg:classifiers":[
        {
            "category":"Restaurant",
            "type":"Food & Drink"
        }
    ],
    "sg:phone":"+1 250 492 0496",
    "sg:postcode":"V2A 6G3",
    "sg:province":"BC",
    "wof:name":"Pantry Restaurant",
    "wof:placetype":"venue"
},
  "geometry": {"coordinates":[-119.588523865,49.4622840881],"type":"Point"}
}