{
  "type": "Feature",
  "properties": {
    "iso:country":"CA",
    "sg:city":"North York",
    "sg:classifiers":[
        {
            "category":"Retail",
            "subcategory":"Repair Shop",
            "type":"Services"
        }
    ],
    "sg:phone":"+1 416 661 1179",
    "sg:postcode":"M3J 2K3",
    "sg:province":"ON",
    "sg:tags":[
        "upholsterer"
    ],
    "wof:name":"Flair Custom Upholstery",
    "wof:placetype":"venue"
},
  "geometry": {"coordinates":[-79.4740142822,43.7717208862],"type":"Point"}
}