{
  "type": "Feature",
  "properties": {
    "addr:full":"5694 Highway 7 Markham ON L3P 1B4",
    "addr:housenumber":"5694",
    "addr:postcode":"l3p 1b4",
    "addr:street":"Highway 7",
    "iso:country":"CA",
    "sg:address":"5694 Highway 7",
    "sg:city":"Markham",
    "sg:classifiers":[
        {
            "category":"Recreation",
            "type":"Entertainment"
        }
    ],
    "sg:phone":"+1 905 471 5205",
    "sg:postcode":"L3P 1B4",
    "sg:province":"ON",
    "sg:tags":[
        "martial",
        "arts",
        "instruction"
    ],
    "wof:name":"Master Myung's Tae Kwon DO Acd",
    "wof:placetype":"venue"
},
  "geometry": {"coordinates":[-79.3399429321,43.8560333252],"type":"Point"}
}