{
  "type": "Feature",
  "properties": {
    "iso:country":"CA",
    "sg:address":"212 Main St",
    "sg:city":"Biggar",
    "sg:classifiers":[
        {
            "category":"Restaurant",
            "type":"Food & Drink"
        }
    ],
    "sg:phone":"+1 306 948 4800",
    "sg:postcode":"S0K 0M0",
    "sg:province":"SK",
    "wof:name":"Pizzeria Adria",
    "wof:placetype":"venue"
},
  "geometry": {"coordinates":[-107.98550415,52.0550537109],"type":"Point"}
}