{
  "type": "Feature",
  "properties": {
    "addr:full":"Toronto ON M5C 2A5",
    "addr:postcode":"m5c 2a5",
    "iso:country":"CA",
    "sg:city":"Toronto",
    "sg:classifiers":[
        {
            "category":"Restaurant",
            "type":"Food & Drink"
        }
    ],
    "sg:phone":"+1 416 360 0446",
    "sg:postcode":"M5C 2A5",
    "sg:province":"ON",
    "wof:name":"Green Peas",
    "wof:placetype":"venue"
},
  "geometry": {"coordinates":[-79.377571106,43.6512184143],"type":"Point"}
}