{
  "type": "Feature",
  "properties": {
    "addr:full":"4335 Boul Saint-Martin O Laval QC H7T 1C4",
    "addr:housenumber":"4335",
    "addr:postcode":"h7t 1c4",
    "addr:street":"Boul Saint-Martin O",
    "iso:country":"CA",
    "sg:address":"4335 Boul Saint-Martin O",
    "sg:city":"Laval",
    "sg:classifiers":[
        {
            "category":"Social Services",
            "subcategory":"Child Care",
            "type":"Services"
        }
    ],
    "sg:phone":"+1 450 681 0692",
    "sg:postcode":"H7T 1C4",
    "sg:province":"QC",
    "wof:name":"Centre DE LA Petite Enfance Le",
    "wof:placetype":"venue"
},
  "geometry": {"coordinates":[-73.76799800000001,45.548946],"type":"Point"}
}