{
  "type": "Feature",
  "properties": {
    "addr:full":"901 Fresno Pl Coquitlam BC V3J 6G5",
    "addr:housenumber":"901",
    "addr:postcode":"v3j 6g5",
    "addr:street":"Fresno Pl",
    "iso:country":"CA",
    "sg:address":"901 Fresno Pl",
    "sg:city":"Coquitlam",
    "sg:classifiers":[
        {
            "category":"Wholesale",
            "subcategory":"Machinery & Supplies",
            "type":"Manufacturing & Wholesale Goods"
        }
    ],
    "sg:phone":"+1 604 931 8824",
    "sg:postcode":"V3J 6G5",
    "sg:province":"BC",
    "sg:tags":[
        "sprinkler"
    ],
    "wof:name":"J L Munro Fire Protection",
    "wof:placetype":"venue"
},
  "geometry": {"coordinates":[-122.840958,49.268578],"type":"Point"}
}