{
  "type": "Feature",
  "properties": {
    "iso:country":"CA",
    "sg:address":"345 Watline Ave # B",
    "sg:city":"Mississauga",
    "sg:classifiers":[
        {
            "category":"Manufacturing",
            "subcategory":"Tools & Machinery",
            "type":"Manufacturing & Wholesale Goods"
        }
    ],
    "sg:phone":"+1 905 660 7359",
    "sg:postcode":"L4Z 1P3",
    "sg:province":"ON",
    "sg:tags":[
        "scale"
    ],
    "wof:name":"Saturn Scale Systems Inc",
    "wof:placetype":"venue"
},
  "geometry": {"coordinates":[-79.6642990112,43.6275291443],"type":"Point"}
}