{
  "type": "Feature",
  "properties": {
    "iso:country":"CA",
    "sg:address":"1820 Bank St",
    "sg:city":"Ottawa",
    "sg:classifiers":[
        {
            "category":"Retail",
            "subcategory":"Laundry & Dry Cleaning",
            "type":"Services"
        }
    ],
    "sg:phone":"+1 613 731 7392",
    "sg:postcode":"K1V 7Y6",
    "sg:province":"ON",
    "sg:tags":[
        "cleaners"
    ],
    "wof:name":"Laundry Land",
    "wof:placetype":"venue"
},
  "geometry": {"coordinates":[-75.6639709473,45.3714599609],"type":"Point"}
}