{
  "type": "Feature",
  "properties": {
    "addr:full":"RR 1 Salford ON N0J 1W0",
    "addr:postcode":"n0j 1w0",
    "addr:street":"Rr 1",
    "iso:country":"CA",
    "sg:address":"RR 1",
    "sg:city":"Salford",
    "sg:classifiers":[
        {
            "category":"Wholesale",
            "subcategory":"Scrap",
            "type":"Manufacturing & Wholesale Goods"
        }
    ],
    "sg:phone":"+1 519 424 9502",
    "sg:postcode":"N0J 1W0",
    "sg:province":"ON",
    "sg:tags":[
        "recycling",
        "center"
    ],
    "wof:name":"West End Lumber & Wood Prods",
    "wof:placetype":"venue"
},
  "geometry": {"coordinates":[-80.829735,42.999107],"type":"Point"}
}