{
  "type": "Feature",
  "properties": {
    "addr:full":"1970 Gottingen St Halifax NS B3J 3Y2",
    "addr:housenumber":"1970",
    "addr:postcode":"ns b3j 3y2",
    "addr:street":"Gottingen St",
    "iso:country":"CA",
    "sg:address":"1970 Gottingen St",
    "sg:city":"Halifax",
    "sg:classifiers":[
        {
            "category":"Recreation",
            "type":"Entertainment"
        }
    ],
    "sg:phone":"+1 902 490 7219",
    "sg:postcode":"B3J 3Y2",
    "sg:province":"NS",
    "sg:tags":[
        "pool",
        "swimming"
    ],
    "wof:name":"Centennial Pool",
    "wof:placetype":"venue"
},
  "geometry": {"coordinates":[-63.580719,44.649975],"type":"Point"}
}