{
  "type": "Feature",
  "properties": {
    "addr:full":"221 Glendale Ave St Catharines ON L2T 2K9",
    "addr:housenumber":"221",
    "addr:postcode":"l2t 2k9",
    "addr:street":"Glendale Ave",
    "iso:country":"CA",
    "sg:address":"221 Glendale Ave",
    "sg:city":"St Catharines",
    "sg:classifiers":[
        {
            "category":"Shopping",
            "subcategory":"Clothing, Apparel, & Fashions",
            "type":"Retail Goods"
        }
    ],
    "sg:phone":"+1 905 682 3131",
    "sg:postcode":"L2T 2K9",
    "sg:province":"ON",
    "sg:tags":[
        "sportswear"
    ],
    "wof:name":"Gap",
    "wof:placetype":"venue"
},
  "geometry": {"coordinates":[-79.2248306274,43.1331481934],"type":"Point"}
}