{
  "type": "Feature",
  "properties": {
    "addr:full":"PO Box 189 Princeton BC V0X 1W0",
    "addr:housenumber":"po",
    "addr:postcode":"v0x 1w0",
    "addr:street":"Box 189",
    "iso:country":"CA",
    "sg:address":"PO Box 189",
    "sg:city":"Princeton",
    "sg:classifiers":[
        {
            "category":"Manufacturing",
            "subcategory":"Printing",
            "type":"Manufacturing & Wholesale Goods"
        }
    ],
    "sg:phone":"+1 250 295 7755",
    "sg:postcode":"V0X 1W0",
    "sg:province":"BC",
    "sg:tags":[
        "publisher"
    ],
    "wof:name":"Growers Press Inc",
    "wof:placetype":"venue"
},
  "geometry": {"coordinates":[-120.505898,49.458675],"type":"Point"}
}