{
  "type": "Feature",
  "properties": {
    "iso:country":"CA",
    "sg:address":"Linton Rd",
    "sg:city":"Honey Harbour",
    "sg:classifiers":[
        {
            "category":"Travel",
            "subcategory":"Hotels & Motels",
            "type":"Entertainment"
        }
    ],
    "sg:phone":"+1 705 756 2245",
    "sg:postcode":"P0E 1E0",
    "sg:province":"ON",
    "sg:tags":[
        "cottage",
        "cabin"
    ],
    "wof:name":"Elm Cove Cottages",
    "wof:placetype":"venue"
},
  "geometry": {"coordinates":[-79.82056427000001,44.8676071167],"type":"Point"}
}