{
  "type": "Feature",
  "properties": {
    "addr:full":"Kanata ON K2L 3H1",
    "addr:postcode":"k2l 3h1",
    "iso:country":"CA",
    "sg:city":"Kanata",
    "sg:classifiers":[
        {
            "category":"Health Services",
            "subcategory":"Doctor",
            "type":"Services"
        }
    ],
    "sg:phone":"+1 613 271 6400",
    "sg:postcode":"K2L 3H1",
    "sg:province":"ON",
    "sg:tags":[
        "dentist"
    ],
    "wof:name":"Pariseau, Marielle DDS",
    "wof:placetype":"venue"
},
  "geometry": {"coordinates":[-75.89338684080001,45.3147735596],"type":"Point"}
}