{
  "type": "Feature",
  "properties": {
    "addr:full":"403 Queen St W Toronto ON M5V 2A5",
    "addr:housenumber":"403",
    "addr:postcode":"m5v 2a5",
    "addr:street":"Queen St W",
    "iso:country":"CA",
    "sg:address":"403 Queen St W",
    "sg:city":"Toronto",
    "sg:classifiers":[
        {
            "category":"Shopping",
            "subcategory":"Clothing, Apparel, & Fashions",
            "type":"Retail Goods"
        }
    ],
    "sg:phone":"+1 416 979 5633",
    "sg:postcode":"M5V 2A5",
    "sg:province":"ON",
    "wof:name":"Club Monaco",
    "wof:placetype":"venue"
},
  "geometry": {"coordinates":[-79.39474487299999,43.6489448547],"type":"Point"}
}