{
  "type": "Feature",
  "properties": {
    "addr:full":"68 Boul Leveille Saint-Eustache QC J7R 6V2",
    "addr:housenumber":"68",
    "addr:postcode":"j7r 6v2",
    "addr:street":"Boul Leveille",
    "iso:country":"CA",
    "sg:address":"68 Boul Leveille",
    "sg:city":"Saint-Eustache",
    "sg:classifiers":[
        {
            "category":"Retail",
            "subcategory":"Laundry & Dry Cleaning",
            "type":"Services"
        }
    ],
    "sg:phone":"+1 450 473 2049",
    "sg:postcode":"J7R 6V2",
    "sg:province":"QC",
    "sg:tags":[
        "cleaners"
    ],
    "wof:name":"Nettoyeur Michel Forget",
    "wof:placetype":"venue"
},
  "geometry": {"coordinates":[-73.92361450200001,45.5812149048],"type":"Point"}
}