{
  "type": "Feature",
  "properties": {
    "addr:full":"450 Sanatorium Rd Hamilton ON L9C 2B1",
    "addr:housenumber":"450",
    "addr:postcode":"l9c 2b1",
    "addr:street":"Sanatorium Rd",
    "iso:country":"CA",
    "sg:address":"450 Sanatorium Rd",
    "sg:city":"Hamilton",
    "sg:classifiers":[
        {
            "category":"Education",
            "subcategory":"School",
            "type":"Public Place"
        }
    ],
    "sg:phone":"+1 905 385 5369",
    "sg:postcode":"L9C 2B1",
    "sg:province":"ON",
    "wof:name":"Holbrook School",
    "wof:placetype":"venue"
},
  "geometry": {"coordinates":[-79.91404,43.236919],"type":"Point"}
}