{
  "type": "Feature",
  "properties": {
    "addr:full":"Picton ON K0K 2T0",
    "addr:postcode":"k0k 2t0",
    "iso:country":"CA",
    "sg:city":"Picton",
    "sg:classifiers":[
        {
            "category":"Recreation",
            "subcategory":"Marina",
            "type":"Entertainment"
        }
    ],
    "sg:phone":"+1 613 476 4649",
    "sg:postcode":"K0K 2T0",
    "sg:province":"ON",
    "sg:tags":[
        "polishing",
        "car",
        "washing",
        "repairing",
        "boat"
    ],
    "wof:name":"Annie's Pedal & Props",
    "wof:placetype":"venue"
},
  "geometry": {"coordinates":[-77.1753234863,43.9952278137],"type":"Point"}
}