{
  "type": "Feature",
  "properties": {
    "addr:full":"858 3E Rue Chibougamau QC G8P 1P9",
    "addr:housenumber":"858",
    "addr:postcode":"g8p 1p9",
    "addr:street":"3E Rue",
    "iso:country":"CA",
    "sg:address":"858 3E Rue",
    "sg:city":"Chibougamau",
    "sg:classifiers":[
        {
            "category":"Restaurant",
            "type":"Food & Drink"
        }
    ],
    "sg:phone":"+1 418 748 4800",
    "sg:postcode":"G8P 1P9",
    "sg:province":"QC",
    "wof:name":"Restaurant Chez Raymonde",
    "wof:placetype":"venue"
},
  "geometry": {"coordinates":[-74.37989,49.91346],"type":"Point"}
}