{
  "type": "Feature",
  "properties": {
    "addr:full":"13201 Rue Sherbrooke E Pointe-Aux-Trembles QC H1A 1C2",
    "addr:housenumber":"13201",
    "addr:postcode":"h1a 1c2",
    "addr:street":"Rue Sherbrooke E Pointe-Aux-Trembles",
    "iso:country":"CA",
    "sg:address":"13201 Rue Sherbrooke E",
    "sg:city":"Pointe-Aux-Trembles",
    "sg:classifiers":[
        {
            "category":"Shopping",
            "subcategory":"Clothing, Apparel, & Fashions",
            "type":"Retail Goods"
        }
    ],
    "sg:phone":"+1 514 642 5915",
    "sg:postcode":"H1A 1C2",
    "sg:province":"QC",
    "sg:tags":[
        "item",
        "boutique"
    ],
    "wof:name":"Laurier Vetements DE Modes Inc",
    "wof:placetype":"venue"
},
  "geometry": {"coordinates":[-73.508995,45.658577],"type":"Point"}
}