{
  "type": "Feature",
  "properties": {
    "addr:full":"Calgary AB T2P 3N3",
    "addr:postcode":"t2p 3n3",
    "iso:country":"CA",
    "sg:city":"Calgary",
    "sg:classifiers":[
        {
            "category":"Manufacturing",
            "subcategory":"Printing",
            "type":"Manufacturing & Wholesale Goods"
        }
    ],
    "sg:phone":"+1 403 261 5844",
    "sg:postcode":"T2P 3N3",
    "sg:province":"AB",
    "sg:tags":[
        "printer"
    ],
    "wof:name":"One-Forty Copiers Inc",
    "wof:placetype":"venue"
},
  "geometry": {"coordinates":[-114.06381225600001,51.0494537354],"type":"Point"}
}