{
  "type": "Feature",
  "properties": {
    "addr:full":"PO Box 130 Wolfe Island ON K0H 2Y0",
    "addr:housenumber":"po",
    "addr:postcode":"k0h 2y0",
    "addr:street":"Box 130 Wolfe",
    "iso:country":"CA",
    "sg:address":"PO Box 130",
    "sg:city":"Wolfe Island",
    "sg:classifiers":[
        {
            "category":"Government",
            "subcategory":"Office",
            "type":"Public Place"
        }
    ],
    "sg:phone":"+1 613 385 2300",
    "sg:postcode":"K0H 2Y0",
    "sg:province":"ON",
    "sg:tags":[
        "village"
    ],
    "wof:name":"Wolfe Island Garage",
    "wof:placetype":"venue"
},
  "geometry": {"coordinates":[-76.441689,44.19297],"type":"Point"}
}