{
  "type": "Feature",
  "properties": {
    "addr:full":"4912 51 Ave Bonnyville AB T9N 2H4",
    "addr:housenumber":"4912",
    "addr:postcode":"t9n 2h4",
    "addr:street":"51 Ave",
    "iso:country":"CA",
    "sg:address":"4912 51 Ave",
    "sg:city":"Bonnyville",
    "sg:classifiers":[
        {
            "category":"Retail",
            "subcategory":"Auto Repair",
            "type":"Services"
        }
    ],
    "sg:phone":"+1 780 826 2416",
    "sg:postcode":"T9N 2H4",
    "sg:province":"AB",
    "sg:tags":[
        "body",
        "automobile",
        "painting"
    ],
    "wof:name":"J D Collision Ltd",
    "wof:placetype":"venue"
},
  "geometry": {"coordinates":[-110.738274,54.26881],"type":"Point"}
}