{
  "type": "Feature",
  "properties": {
    "iso:country":"CA",
    "sg:city":"Burnaby",
    "sg:classifiers":[
        {
            "category":"Organizations",
            "subcategory":"Professional Association",
            "type":"Services"
        }
    ],
    "sg:phone":"+1 604 205 5058",
    "sg:postcode":"V5C 6P8",
    "sg:province":"BC",
    "wof:name":"Mechanical Industrial Relation",
    "wof:placetype":"venue"
},
  "geometry": {"coordinates":[-123.016693115,49.2641716003],"type":"Point"}
}