{
  "type": "Feature",
  "properties": {
    "addr:full":"2904 29 Ave Vernon BC V1T 1Y7",
    "addr:housenumber":"2904",
    "addr:postcode":"v1t 1y7",
    "addr:street":"29 Ave",
    "iso:country":"CA",
    "sg:address":"2904 29 Ave",
    "sg:city":"Vernon",
    "sg:classifiers":[
        {
            "category":"Government",
            "subcategory":"Office",
            "type":"Public Place"
        }
    ],
    "sg:phone":"+1 250 542 2329",
    "sg:postcode":"V1T 1Y7",
    "sg:province":"BC",
    "wof:name":"Vernon Irrigation District",
    "wof:placetype":"venue"
},
  "geometry": {"coordinates":[-119.269309998,50.2627868652],"type":"Point"}
}