{
  "type": "Feature",
  "properties": {
    "addr:full":"3192 Oak St Vancouver BC V6H 2L1",
    "addr:housenumber":"3192",
    "addr:postcode":"v6h 2l1",
    "addr:street":"Oak St",
    "iso:country":"CA",
    "sg:address":"3192 Oak St",
    "sg:city":"Vancouver",
    "sg:classifiers":[
        {
            "category":"Restaurant",
            "type":"Food & Drink"
        }
    ],
    "sg:phone":"+1 604 732 1915",
    "sg:postcode":"V6H 2L1",
    "sg:province":"BC",
    "wof:name":"Dutch Pannekoek House",
    "wof:placetype":"venue"
},
  "geometry": {"coordinates":[-123.12710571300001,49.2572441101],"type":"Point"}
}