{
  "type": "Feature",
  "properties": {
    "addr:full":"180 Winges Rd #5 Woodbridge ON L4L 6C5",
    "addr:housenumber":"180",
    "addr:postcode":"l4l 6c5",
    "addr:street":"Winges Rd # 5",
    "iso:country":"CA",
    "sg:address":"180 Winges Rd #5",
    "sg:city":"Woodbridge",
    "sg:classifiers":[
        {
            "category":"Personal",
            "subcategory":"Beauty Salon",
            "type":"Services"
        }
    ],
    "sg:phone":"+1 905 850 3654",
    "sg:postcode":"L4L 6C5",
    "sg:province":"ON",
    "wof:name":"Phases Hair Studio",
    "wof:placetype":"venue"
},
  "geometry": {"coordinates":[-79.5512008667,43.7874641418],"type":"Point"}
}