{
  "type": "Feature",
  "properties": {
    "addr:full":"580 Rue Hebert Mont-Laurier QC J9L 2X2",
    "addr:housenumber":"580",
    "addr:postcode":"j9l 2x2",
    "addr:street":"Rue Hebert",
    "iso:country":"CA",
    "sg:address":"580 Rue Hebert",
    "sg:city":"Mont-Laurier",
    "sg:classifiers":[
        {
            "category":"Home & Garden",
            "subcategory":"Furniture",
            "type":"Retail Goods"
        }
    ],
    "sg:phone":"+1 819 623 1115",
    "sg:postcode":"J9L 2X2",
    "sg:province":"QC",
    "wof:name":"Meubles Mont-Laurier Ltee",
    "wof:placetype":"venue"
},
  "geometry": {"coordinates":[-75.49192810060001,46.5548248291],"type":"Point"}
}