{
  "type": "Feature",
  "properties": {
    "addr:full":"8 Rue Saint-Marcellin Les Escoumins QC G0T 1K0",
    "addr:housenumber":"8",
    "addr:postcode":"g0t 1k0",
    "addr:street":"Rue Saint-Marcellin",
    "iso:country":"CA",
    "sg:address":"8 Rue Saint-Marcellin",
    "sg:city":"Les Escoumins",
    "sg:classifiers":[
        {
            "category":"Retail",
            "subcategory":"Auto Repair",
            "type":"Services"
        }
    ],
    "sg:phone":"+1 418 233 3223",
    "sg:postcode":"G0T 1K0",
    "sg:province":"QC",
    "sg:tags":[
        "repairing",
        "automobile"
    ],
    "wof:name":"Mecanique Haute Cote-Nord Enr",
    "wof:placetype":"venue"
},
  "geometry": {"coordinates":[-69.409554,48.332314],"type":"Point"}
}