{
  "type": "Feature",
  "properties": {
    "iso:country":"CA",
    "sg:address":"4785 5E Av E",
    "sg:city":"Charlesbourg",
    "sg:classifiers":[
        {
            "category":"Organizations",
            "subcategory":"Professional Association",
            "type":"Services"
        }
    ],
    "sg:phone":"+1 418 623 3801",
    "sg:postcode":"G1H 3R7",
    "sg:province":"QC",
    "wof:name":"Expansion Femme DE Quebec Inc",
    "wof:placetype":"venue"
},
  "geometry": {"coordinates":[-71.245781,46.848915],"type":"Point"}
}