{
  "type": "Feature",
  "properties": {
    "addr:full":"4785 5E Av E Charlesbourg QC G1H 3R7",
    "addr:housenumber":"4785",
    "addr:postcode":"g1h 3r7",
    "addr:street":"5E Av E",
    "iso:country":"CA",
    "sg:address":"4785 5E Av E",
    "sg:city":"Charlesbourg",
    "sg:classifiers":[
        {
            "category":"Organizations",
            "subcategory":"Professional Association",
            "type":"Services"
        }
    ],
    "sg:phone":"+1 418 623 3801",
    "sg:postcode":"G1H 3R7",
    "sg:province":"QC",
    "wof:name":"Expansion Femme DE Quebec Inc",
    "wof:placetype":"venue"
},
  "geometry": {"coordinates":[-71.24578099999999,46.848915],"type":"Point"}
}