{
  "type": "Feature",
  "properties": {
    "addr:full":"1500 Av Mcgill College Montreal QC H3A 3J5",
    "addr:housenumber":"1500",
    "addr:postcode":"h3a 3j5",
    "addr:street":"Av Mcgill College",
    "iso:country":"CA",
    "sg:address":"1500 Av Mcgill College",
    "sg:city":"Montreal",
    "sg:classifiers":[
        {
            "category":"Shopping",
            "subcategory":"Gifts & Souvenirs",
            "type":"Retail Goods"
        }
    ],
    "sg:phone":"+1 514 843 5235",
    "sg:postcode":"H3A 3J5",
    "sg:province":"QC",
    "sg:tags":[
        "shop"
    ],
    "wof:name":"Rouet Metiers D'Art Inc",
    "wof:placetype":"venue"
},
  "geometry": {"coordinates":[-73.571777,45.502033],"type":"Point"}
}