{
  "type": "Feature",
  "properties": {
    "addr:full":"Gaspe QC G4X 2A9",
    "addr:postcode":"g4x 2a9",
    "iso:country":"CA",
    "sg:city":"Gaspe",
    "sg:classifiers":[
        {
            "category":"Shopping",
            "subcategory":"Shoes",
            "type":"Retail Goods"
        }
    ],
    "sg:phone":"+1 418 368 5224",
    "sg:postcode":"G4X 2A9",
    "sg:province":"QC",
    "wof:name":"Magasin Aux Beaux Souliers Inc",
    "wof:placetype":"venue"
},
  "geometry": {"coordinates":[-64.4726867676,48.8238296509],"type":"Point"}
}