{
  "type": "Feature",
  "properties": {
    "addr:full":"Scarborough ON M1V 1E7",
    "addr:postcode":"m1v 1e7",
    "iso:country":"CA",
    "sg:city":"Scarborough",
    "sg:classifiers":[
        {
            "category":"Social Services",
            "subcategory":"Child Care",
            "type":"Services"
        }
    ],
    "sg:phone":"+1 416 754 8814",
    "sg:postcode":"M1V 1E7",
    "sg:province":"ON",
    "wof:name":"Heritage Home Childcare Svc",
    "wof:placetype":"venue"
},
  "geometry": {"coordinates":[-79.299744,43.807762],"type":"Point"}
}