{
  "type": "Feature",
  "properties": {
    "addr:full":"2160 Western Pky Vancouver BC V6T 1V6",
    "addr:housenumber":"2160",
    "addr:postcode":"v6t 1v6",
    "addr:street":"Western Pky",
    "iso:country":"CA",
    "sg:address":"2160 Western Pky",
    "sg:city":"Vancouver",
    "sg:classifiers":[
        {
            "category":"Utilities",
            "subcategory":"Mobile Phone",
            "type":"Services"
        }
    ],
    "sg:phone":"+1 604 221 5505",
    "sg:postcode":"V6T 1V6",
    "sg:province":"BC",
    "sg:tags":[
        "telephone",
        "cellular"
    ],
    "wof:name":"Nedco Cellular Sales & Svc",
    "wof:placetype":"venue"
},
  "geometry": {"coordinates":[-123.243408,49.266029],"type":"Point"}
}