{
  "type": "Feature",
  "properties": {
    "addr:full":"851 Browns Line Etobicoke ON M8W 3V7",
    "addr:housenumber":"851",
    "addr:postcode":"m8w 3v7",
    "addr:street":"Browns Line",
    "iso:country":"CA",
    "sg:address":"851 Browns Line",
    "sg:city":"Etobicoke",
    "sg:classifiers":[
        {
            "category":"Shopping",
            "subcategory":"Discount & Variety Stores",
            "type":"Retail Goods"
        }
    ],
    "sg:phone":"+1 416 251 6355",
    "sg:postcode":"M8W 3V7",
    "sg:province":"ON",
    "sg:tags":[
        "game",
        "video"
    ],
    "wof:name":"Video 99 & Smoke Shop",
    "wof:placetype":"venue"
},
  "geometry": {"coordinates":[-79.54806499999999,43.608768],"type":"Point"}
}