{
  "type": "Feature",
  "properties": {
    "addr:full":"Sherwood Park AB T8H 1S8",
    "addr:postcode":"t8h 1s8",
    "iso:country":"CA",
    "sg:city":"Sherwood Park",
    "sg:classifiers":[
        {
            "category":"Personal",
            "subcategory":"Barber",
            "type":"Services"
        }
    ],
    "sg:phone":"+1 780 467 4320",
    "sg:postcode":"T8H 1S8",
    "sg:province":"AB",
    "wof:name":"Thee Barber Shop",
    "wof:placetype":"venue"
},
  "geometry": {"coordinates":[-113.31735229500001,53.5414161682],"type":"Point"}
}