{
  "type": "Feature",
  "properties": {
    "addr:full":"Ajax ON L1S 7G5",
    "addr:postcode":"l1s 7g5",
    "iso:country":"CA",
    "sg:city":"Ajax",
    "sg:classifiers":[
        {
            "category":"Health Services",
            "subcategory":"Doctor",
            "type":"Services"
        }
    ],
    "sg:phone":"+1 905 426 8181",
    "sg:postcode":"L1S 7G5",
    "sg:province":"ON",
    "sg:tags":[
        "dentist"
    ],
    "wof:name":"A Westney Heights Dental Ctr",
    "wof:placetype":"venue"
},
  "geometry": {"coordinates":[-79.0399093628,43.8545265198],"type":"Point"}
}