{
  "type": "Feature",
  "properties": {
    "addr:full":"11 Todd Bay Regina SK S4X 1X5",
    "addr:housenumber":"11",
    "addr:postcode":"s4x 1x5",
    "addr:street":"Todd Bay",
    "iso:country":"CA",
    "sg:address":"11 Todd Bay",
    "sg:city":"Regina",
    "sg:classifiers":[
        {
            "category":"Building & Trades",
            "subcategory":"Cleaning & Sanitation",
            "type":"Services"
        }
    ],
    "sg:phone":"+1 306 775 1722",
    "sg:postcode":"S4X 1X5",
    "sg:province":"SK",
    "sg:tags":[
        "house"
    ],
    "wof:name":"Neat & Tidy Home Cleaning",
    "wof:placetype":"venue"
},
  "geometry": {"coordinates":[-104.66477203399999,50.4873085022],"type":"Point"}
}