{
  "type": "Feature",
  "properties": {
    "iso:country":"CA",
    "sg:address":"835 Marion St",
    "sg:city":"Winnipeg",
    "sg:classifiers":[
        {
            "category":"Building & Trades",
            "subcategory":"Cleaning & Sanitation",
            "type":"Services"
        }
    ],
    "sg:phone":"+1 204 231 3880",
    "sg:postcode":"R2J 0K6",
    "sg:province":"MB",
    "sg:tags":[
        "venetian",
        "blind"
    ],
    "wof:name":"Blind-Shiners",
    "wof:placetype":"venue"
},
  "geometry": {"coordinates":[-97.085281,49.882118],"type":"Point"}
}