{
  "type": "Feature",
  "properties": {
    "addr:full":"9017 109 St Fairview AB T0H 1L0",
    "addr:housenumber":"9017",
    "addr:postcode":"t0h 1l0",
    "addr:street":"109 St",
    "iso:country":"CA",
    "sg:address":"9017 109 St",
    "sg:city":"Fairview",
    "sg:classifiers":[
        {
            "category":"Freight",
            "type":"Transportation"
        }
    ],
    "sg:phone":"+1 780 835 3353",
    "sg:postcode":"T0H 1L0",
    "sg:province":"AB",
    "sg:tags":[
        "commercial",
        "storage"
    ],
    "wof:name":"Clema Mini Storage",
    "wof:placetype":"venue"
},
  "geometry": {"coordinates":[-118.38035600000001,56.055763],"type":"Point"}
}