{
  "type": "Feature",
  "properties": {
    "iso:country":"CA",
    "sg:address":"2195 45th Ave W",
    "sg:city":"Vancouver",
    "sg:classifiers":[
        {
            "category":"Organizations",
            "subcategory":"Religious Organization",
            "type":"Services"
        }
    ],
    "sg:phone":"+1 604 266 5377",
    "sg:postcode":"V6M 2J2",
    "sg:province":"BC",
    "sg:tags":[
        "church"
    ],
    "wof:name":"Ryerson United Church-Canada",
    "wof:placetype":"venue"
},
  "geometry": {"coordinates":[-123.158226013,49.2309837341],"type":"Point"}
}