{
  "type": "Feature",
  "properties": {
    "addr:full":"50 Rue Victoria Sorel-Tracy QC J3P 1Y6",
    "addr:housenumber":"50",
    "addr:postcode":"j3p 1y6",
    "addr:street":"Rue Victoria",
    "iso:country":"CA",
    "sg:address":"50 Rue Victoria",
    "sg:city":"Sorel-Tracy",
    "sg:classifiers":[
        {
            "category":"Food & Beverages",
            "subcategory":"Groceries & Convenience Stores",
            "type":"Retail Goods"
        }
    ],
    "sg:phone":"+1 450 743 5738",
    "sg:postcode":"J3P 1Y6",
    "sg:province":"QC",
    "sg:tags":[
        "grocer"
    ],
    "wof:name":"Provigo",
    "wof:placetype":"venue"
},
  "geometry": {"coordinates":[-73.112449646,46.038444519],"type":"Point"}
}