{
  "type": "Feature",
  "properties": {
    "addr:full":"223 King St E Hamilton ON L8N 1B6",
    "addr:housenumber":"223",
    "addr:postcode":"l8n 1b6",
    "addr:street":"King St E",
    "iso:country":"CA",
    "sg:address":"223 King St E",
    "sg:city":"Hamilton",
    "sg:classifiers":[
        {
            "category":"Shopping",
            "subcategory":"Used Merchandise",
            "type":"Retail Goods"
        }
    ],
    "sg:phone":"+1 905 308 8282",
    "sg:postcode":"L8N 1B6",
    "sg:province":"ON",
    "sg:tags":[
        "second",
        "store",
        "hand"
    ],
    "wof:name":"Out of the Past",
    "wof:placetype":"venue"
},
  "geometry": {"coordinates":[-79.86247299999999,43.254658],"type":"Point"}
}