{
  "type": "Feature",
  "properties": {
    "addr:full":"100 Queensway W Mississauga ON L5B 1B8",
    "addr:housenumber":"100",
    "addr:postcode":"l5b 1b8",
    "addr:street":"Queensway W",
    "iso:country":"CA",
    "sg:address":"100 Queensway W",
    "sg:city":"Mississauga",
    "sg:classifiers":[
        {
            "category":"Food & Beverages",
            "subcategory":"Groceries & Convenience Stores",
            "type":"Retail Goods"
        }
    ],
    "sg:phone":"+1 905 566 8524",
    "sg:postcode":"L5B 1B8",
    "sg:province":"ON",
    "sg:tags":[
        "grocer"
    ],
    "wof:name":"Hasty Market",
    "wof:placetype":"venue"
},
  "geometry": {"coordinates":[-79.61058,43.5714],"type":"Point"}
}