{
  "type": "Feature",
  "properties": {
    "iso:country":"CA",
    "sg:address":"8719 50 St NW",
    "sg:city":"Edmonton",
    "sg:classifiers":[
        {
            "category":"Organizations",
            "subcategory":"Professional Association",
            "type":"Services"
        }
    ],
    "sg:phone":"+1 780 448 5990",
    "sg:postcode":"T6B 1E7",
    "sg:province":"AB",
    "sg:tags":[
        "club"
    ],
    "wof:name":"Main Event Boxing Club",
    "wof:placetype":"venue"
},
  "geometry": {"coordinates":[-113.41791534399999,53.5199012756],"type":"Point"}
}