{
  "type": "Feature",
  "properties": {
    "iso:country":"CA",
    "sg:address":"1535 South Gateway Rd",
    "sg:city":"Mississauga",
    "sg:classifiers":[
        {
            "category":"Retail",
            "subcategory":"Funeral Services",
            "type":"Services"
        }
    ],
    "sg:phone":"+1 905 602 1580",
    "sg:postcode":"L4W 5J1",
    "sg:province":"ON",
    "sg:tags":[
        "director"
    ],
    "wof:name":"Simple Alternative",
    "wof:placetype":"venue"
},
  "geometry": {"coordinates":[-79.614655,43.632793],"type":"Point"}
}