{
  "type": "Feature",
  "properties": {
    "addr:full":"22 Brock St E Uxbridge ON L9P 1P1",
    "addr:housenumber":"22",
    "addr:postcode":"l9p 1p1",
    "addr:street":"Brock St E",
    "iso:country":"CA",
    "sg:address":"22 Brock St E",
    "sg:city":"Uxbridge",
    "sg:classifiers":[
        {
            "category":"Professional",
            "subcategory":"Lawyer & Legal Services",
            "type":"Services"
        }
    ],
    "sg:phone":"+1 905 852 3353",
    "sg:postcode":"L9P 1P1",
    "sg:province":"ON",
    "sg:tags":[
        "attorney"
    ],
    "wof:name":"Wilson Associates",
    "wof:placetype":"venue"
},
  "geometry": {"coordinates":[-79.119308,44.10947],"type":"Point"}
}