{
  "type": "Feature",
  "properties": {
    "addr:full":"565 Rue Lavoisier Repentigny QC J6A 7M8",
    "addr:housenumber":"565",
    "addr:postcode":"j6a 7m8",
    "addr:street":"Rue Lavoisier",
    "iso:country":"CA",
    "sg:address":"565 Rue Lavoisier",
    "sg:city":"Repentigny",
    "sg:classifiers":[
        {
            "category":"Retail",
            "subcategory":"Auto Repair",
            "type":"Services"
        }
    ],
    "sg:phone":"+1 450 654 6118",
    "sg:postcode":"J6A 7M8",
    "sg:province":"QC",
    "sg:tags":[
        "repairing",
        "automobile"
    ],
    "wof:name":"Belle Mecanique",
    "wof:placetype":"venue"
},
  "geometry": {"coordinates":[-73.450081,45.751839],"type":"Point"}
}