{
  "type": "Feature",
  "properties": {
    "addr:full":"11012 89 Ave Grande Prairie AB T8V 4W4",
    "addr:housenumber":"11012",
    "addr:postcode":"t8v 4w4",
    "addr:street":"89 Ave",
    "iso:country":"CA",
    "sg:address":"11012 89 Ave",
    "sg:city":"Grande Prairie",
    "sg:classifiers":[
        {
            "category":"Wholesale",
            "subcategory":"Machinery & Supplies",
            "type":"Manufacturing & Wholesale Goods"
        }
    ],
    "sg:phone":"+1 780 538 1608",
    "sg:postcode":"T8V 4W4",
    "sg:province":"AB",
    "sg:tags":[
        "engine"
    ],
    "wof:name":"Dan's Truck & Diesel Svc",
    "wof:placetype":"venue"
},
  "geometry": {"coordinates":[-118.827575684,55.1611251831],"type":"Point"}
}