{
  "type": "Feature",
  "properties": {
    "addr:full":"North York ON M2J 5B5",
    "addr:postcode":"m2j 5b5",
    "iso:country":"CA",
    "sg:city":"North York",
    "sg:classifiers":[
        {
            "category":"Manufacturing",
            "subcategory":"Food",
            "type":"Manufacturing & Wholesale Goods"
        }
    ],
    "sg:phone":"+1 416 493 8800",
    "sg:postcode":"M2J 5B5",
    "sg:province":"ON",
    "sg:tags":[
        "product",
        "broker",
        "manufacturer"
    ],
    "wof:name":"Peter Igel Food Products Inc",
    "wof:placetype":"venue"
},
  "geometry": {"coordinates":[-79.32957500000001,43.774757],"type":"Point"}
}