{
  "type": "Feature",
  "properties": {
    "addr:full":"5011 Highway 7 Markham ON L3R 1N1",
    "addr:housenumber":"5011",
    "addr:postcode":"l3r 1n1",
    "addr:street":"Highway 7",
    "iso:country":"CA",
    "sg:address":"5011 Highway 7",
    "sg:city":"Markham",
    "sg:classifiers":[
        {
            "category":"Health Services",
            "subcategory":"Doctor",
            "type":"Services"
        }
    ],
    "sg:phone":"+1 905 415 7700",
    "sg:postcode":"L3R 1N1",
    "sg:province":"ON",
    "sg:tags":[
        "dentist"
    ],
    "wof:name":"Dr Brown & Assoc",
    "wof:placetype":"venue"
},
  "geometry": {"coordinates":[-79.3399429321,43.8560333252],"type":"Point"}
}