{
  "type": "Feature",
  "properties": {
    "addr:full":"1515 Upper Ottawa St Hamilton ON L8W 3E2",
    "addr:housenumber":"1515",
    "addr:postcode":"l8w 3e2",
    "addr:street":"Upper Ottawa St",
    "iso:country":"CA",
    "sg:address":"1515 Upper Ottawa St",
    "sg:city":"Hamilton",
    "sg:classifiers":[
        {
            "category":"Food & Beverages",
            "subcategory":"Groceries & Convenience Stores",
            "type":"Retail Goods"
        }
    ],
    "sg:phone":"+1 905 385 4431",
    "sg:postcode":"L8W 3E2",
    "sg:province":"ON",
    "sg:tags":[
        "variety"
    ],
    "wof:name":"Maximum Variety & Convenience",
    "wof:placetype":"venue"
},
  "geometry": {"coordinates":[-79.84247589109999,43.1939315796],"type":"Point"}
}