{
  "type": "Feature",
  "properties": {
    "addr:full":"365 South Side Harbour Rd Antigonish NS B2G 2L4",
    "addr:housenumber":"365",
    "addr:postcode":"b2g 2l4",
    "addr:street":"South Side Harbour Rd",
    "iso:country":"CA",
    "sg:address":"365 South Side Harbour Rd",
    "sg:city":"Antigonish",
    "sg:classifiers":[
        {
            "category":"Shopping",
            "subcategory":"Crafts & Fabrics",
            "type":"Retail Goods"
        }
    ],
    "sg:phone":"+1 902 863 6801",
    "sg:postcode":"B2G 2L4",
    "sg:province":"NS",
    "sg:tags":[
        "shop"
    ],
    "wof:name":"Harbour Quilt CO",
    "wof:placetype":"venue"
},
  "geometry": {"coordinates":[-61.914589,45.605289],"type":"Point"}
}