{
  "type": "Feature",
  "properties": {
    "addr:full":"10621 Av Balzac Montreal-Nord QC H1H 3L8",
    "addr:postcode":"h1h 3l8",
    "addr:street":"Av Balzac",
    "iso:country":"CA",
    "sg:address":"10621 Av Balzac",
    "sg:city":"Montreal-Nord",
    "sg:classifiers":[
        {
            "category":"Wholesale",
            "subcategory":"Auto Parts",
            "type":"Manufacturing & Wholesale Goods"
        }
    ],
    "sg:phone":"+1 514 322 2450",
    "sg:postcode":"H1H 3L8",
    "sg:province":"QC",
    "sg:tags":[
        "garage",
        "equipment"
    ],
    "wof:name":"Cie Electronique M & M Ltee",
    "wof:placetype":"venue"
},
  "geometry": {"coordinates":[-73.62867,45.591721],"type":"Point"}
}