{
  "type": "Feature",
  "properties": {
    "addr:full":"North Bay ON P1B 2C8",
    "addr:postcode":"p1b 2c8",
    "iso:country":"CA",
    "sg:city":"North Bay",
    "sg:classifiers":[
        {
            "category":"Professional",
            "subcategory":"Lawyer & Legal Services",
            "type":"Services"
        }
    ],
    "sg:phone":"+1 705 474 3655",
    "sg:postcode":"P1B 2C8",
    "sg:province":"ON",
    "sg:tags":[
        "attorney"
    ],
    "wof:name":"D'Agostino & Assoc",
    "wof:placetype":"venue"
},
  "geometry": {"coordinates":[-79.46067810060001,46.3061561584],"type":"Point"}
}