{
  "type": "Feature",
  "properties": {
    "iso:country":"CA",
    "sg:address":"840 Carmichael Lane",
    "sg:city":"Hinton",
    "sg:classifiers":[
        {
            "category":"Restaurant",
            "type":"Food & Drink"
        }
    ],
    "sg:phone":"+1 780 865 5227",
    "sg:postcode":"T7V 1Y6",
    "sg:province":"AB",
    "wof:name":"Mc Donald's",
    "wof:placetype":"venue"
},
  "geometry": {"coordinates":[-117.623497009,53.3834724426],"type":"Point"}
}