{
  "type": "Feature",
  "properties": {
    "addr:full":"4906 51st St Elk Point AB T0A 1A0",
    "addr:housenumber":"4906",
    "addr:postcode":"t0a 1a0",
    "addr:street":"51St St",
    "iso:country":"CA",
    "sg:address":"4906 51st St",
    "sg:city":"Elk Point",
    "sg:classifiers":[
        {
            "category":"Recreation",
            "type":"Entertainment"
        }
    ],
    "sg:phone":"+1 780 724 3580",
    "sg:postcode":"T0A 1A0",
    "sg:province":"AB",
    "sg:tags":[
        "hall",
        "auditorium"
    ],
    "wof:name":"Elks Community Hall",
    "wof:placetype":"venue"
},
  "geometry": {"coordinates":[-110.902145,53.89695],"type":"Point"}
}