{
  "type": "Feature",
  "properties": {
    "addr:full":"3958 Rue DE LA Meuse Jonquiere QC G7X 3Y3",
    "addr:housenumber":"3958",
    "addr:postcode":"g7x 3y3",
    "addr:street":"Rue De La Meuse",
    "iso:country":"CA",
    "sg:address":"3958 Rue DE LA Meuse",
    "sg:city":"Jonquiere",
    "sg:classifiers":[
        {
            "category":"Social Services",
            "subcategory":"Child Care",
            "type":"Services"
        }
    ],
    "sg:phone":"+1 418 547 5894",
    "sg:postcode":"G7X 3Y3",
    "sg:province":"QC",
    "wof:name":"Garderie Jardiniere/Schtroumps",
    "wof:placetype":"venue"
},
  "geometry": {"coordinates":[-71.25695037840001,48.4032287598],"type":"Point"}
}