{
  "type": "Feature",
  "properties": {
    "addr:full":"30 George Anderson Dr North York ON M6M 2Y8",
    "addr:housenumber":"30",
    "addr:postcode":"m6m 2y8",
    "addr:street":"George Anderson Dr",
    "iso:country":"CA",
    "sg:address":"30 George Anderson Dr",
    "sg:city":"North York",
    "sg:classifiers":[
        {
            "category":"Education",
            "subcategory":"School",
            "type":"Public Place"
        }
    ],
    "sg:phone":"+1 416 395 5000",
    "sg:postcode":"M6M 2Y8",
    "sg:province":"ON",
    "wof:name":"George Anderson Public School",
    "wof:placetype":"venue"
},
  "geometry": {"coordinates":[-79.4795379639,43.704914093],"type":"Point"}
}