{
  "type": "Feature",
  "properties": {
    "addr:full":"28 Division St Bowmanville ON L1C 2Z3",
    "addr:housenumber":"28",
    "addr:postcode":"l1c 2z3",
    "addr:street":"Division St",
    "iso:country":"CA",
    "sg:address":"28 Division St",
    "sg:city":"Bowmanville",
    "sg:classifiers":[
        {
            "category":"Personal",
            "subcategory":"Beauty Salon",
            "type":"Services"
        }
    ],
    "sg:phone":"+1 905 623 1341",
    "sg:postcode":"L1C 2Z3",
    "sg:province":"ON",
    "wof:name":"Guys & Gals",
    "wof:placetype":"venue"
},
  "geometry": {"coordinates":[-78.687645,43.912174],"type":"Point"}
}