{
  "type": "Feature",
  "properties": {
    "addr:full":"1261 Av Maguire # 102 Sillery QC G1T 1Z2",
    "addr:housenumber":"1261",
    "addr:postcode":"g1t 1z2",
    "addr:street":"Av Maguire # 102",
    "iso:country":"CA",
    "sg:address":"1261 Av Maguire # 102",
    "sg:city":"Sillery",
    "sg:classifiers":[
        {
            "category":"Professional",
            "subcategory":"Business Services",
            "type":"Services"
        }
    ],
    "sg:phone":"+1 418 688 3463",
    "sg:postcode":"G1T 1Z2",
    "sg:province":"QC",
    "sg:tags":[
        "interior",
        "consultant",
        "design",
        "decorator"
    ],
    "wof:name":"Style Libre Maison & Objects",
    "wof:placetype":"venue"
},
  "geometry": {"coordinates":[-71.253258,46.782223],"type":"Point"}
}