{
  "type": "Feature",
  "properties": {
    "addr:full":"Warwick QC J0A 1M0",
    "addr:postcode":"j0a 1m0",
    "iso:country":"CA",
    "sg:city":"Warwick",
    "sg:classifiers":[
        {
            "category":"Personal",
            "subcategory":"Beauty Salon",
            "type":"Services"
        }
    ],
    "sg:phone":"+1 819 358 5960",
    "sg:postcode":"J0A 1M0",
    "sg:province":"QC",
    "wof:name":"Salon Coiffe-Plus",
    "wof:placetype":"venue"
},
  "geometry": {"coordinates":[-71.988663,45.943569],"type":"Point"}
}