{
  "type": "Feature",
  "properties": {
    "iso:country":"CA",
    "sg:city":"Gloucester",
    "sg:classifiers":[
        {
            "category":"Professional",
            "subcategory":"Accounting & Tax Preparation",
            "type":"Services"
        }
    ],
    "sg:phone":"+1 613 742 5681",
    "sg:postcode":"K1J 9J1",
    "sg:province":"ON",
    "sg:tags":[
        "accountant",
        "return",
        "filing"
    ],
    "wof:name":"Ethier Parenteau Accounting",
    "wof:placetype":"venue"
},
  "geometry": {"coordinates":[-75.58419,45.456493],"type":"Point"}
}