{
  "type": "Feature",
  "properties": {
    "iso:country":"CA",
    "sg:address":"5800 Explorer Dr",
    "sg:city":"Mississauga",
    "sg:classifiers":[
        {
            "category":"Shopping",
            "subcategory":"Computers & Home Electronics",
            "type":"Retail Goods"
        }
    ],
    "sg:phone":"+1 905 602 1700",
    "sg:postcode":"L4W 5K9",
    "sg:province":"ON",
    "sg:tags":[
        "software"
    ],
    "wof:name":"Mrs CO Ltd",
    "wof:placetype":"venue"
},
  "geometry": {"coordinates":[-79.615715,43.656929],"type":"Point"}
}