{
  "type": "Feature",
  "properties": {
    "addr:full":"7350 Rue Saint-Denis Montreal QC H2R 2E4",
    "addr:housenumber":"7350",
    "addr:postcode":"h2r 2e4",
    "addr:street":"Rue Saint-Denis",
    "iso:country":"CA",
    "sg:address":"7350 Rue Saint-Denis",
    "sg:city":"Montreal",
    "sg:classifiers":[
        {
            "category":"Personal",
            "subcategory":"Beauty Salon",
            "type":"Services"
        }
    ],
    "sg:phone":"+1 514 276 9467",
    "sg:postcode":"H2R 2E4",
    "sg:province":"QC",
    "wof:name":"Claude Duquette Haute Coiffure",
    "wof:placetype":"venue"
},
  "geometry": {"coordinates":[-73.617980957,45.5392074585],"type":"Point"}
}