{
  "type": "Feature",
  "properties": {
    "iso:country":"CA",
    "sg:address":"85 Rue Acres",
    "sg:city":"Kirkland",
    "sg:classifiers":[
        {
            "category":"Manufacturing",
            "subcategory":"Apparel",
            "type":"Manufacturing & Wholesale Goods"
        }
    ],
    "sg:phone":"+1 514 697 9307",
    "sg:postcode":"H9H 5B5",
    "sg:province":"QC",
    "sg:tags":[
        "textile",
        "broker",
        "manufacturer"
    ],
    "wof:name":"Intexco",
    "wof:placetype":"venue"
},
  "geometry": {"coordinates":[-73.84828186039999,45.4638633728],"type":"Point"}
}