{
  "type": "Feature",
  "properties": {
    "addr:full":"574 14E Ave LA Guadeloupe QC G0M 1G0",
    "addr:housenumber":"574",
    "addr:postcode":"g0m 1g0",
    "addr:street":"14E Ave",
    "iso:country":"CA",
    "sg:address":"574 14E Ave",
    "sg:city":"LA Guadeloupe",
    "sg:classifiers":[
        {
            "category":"Retail",
            "subcategory":"Auto Repair",
            "type":"Services"
        }
    ],
    "sg:phone":"+1 418 459 6290",
    "sg:postcode":"G0M 1G0",
    "sg:province":"QC",
    "sg:tags":[
        "repairing",
        "automobile"
    ],
    "wof:name":"Garage Bolduc Gaetan",
    "wof:placetype":"venue"
},
  "geometry": {"coordinates":[-70.93821,45.963013],"type":"Point"}
}