{
  "type": "Feature",
  "properties": {
    "addr:full":"50 Breadalbane St Hamilton ON L8R 3G1",
    "addr:housenumber":"50",
    "addr:postcode":"l8r 3g1",
    "addr:street":"Breadalbane St",
    "iso:country":"CA",
    "sg:address":"50 Breadalbane St",
    "sg:city":"Hamilton",
    "sg:classifiers":[
        {
            "category":"Organizations",
            "subcategory":"Religious Organization",
            "type":"Services"
        }
    ],
    "sg:phone":"+1 905 522 0342",
    "sg:postcode":"L8R 3G1",
    "sg:province":"ON",
    "sg:tags":[
        "church"
    ],
    "wof:name":"Hamilton Chinese Alliance Ch",
    "wof:placetype":"venue"
},
  "geometry": {"coordinates":[-79.888817,43.263836],"type":"Point"}
}