{
  "type": "Feature",
  "properties": {
    "addr:full":"7555 Montrose Rd Niagara Falls ON L2H 2E9",
    "addr:housenumber":"7555",
    "addr:postcode":"l2h 2e9",
    "addr:street":"Montrose Rd",
    "iso:country":"CA",
    "sg:address":"7555 Montrose Rd",
    "sg:city":"Niagara Falls",
    "sg:classifiers":[
        {
            "category":"Shopping",
            "subcategory":"Jewelry",
            "type":"Retail Goods"
        }
    ],
    "sg:phone":"+1 905 357 1140",
    "sg:postcode":"L2H 2E9",
    "sg:province":"ON",
    "sg:tags":[
        "jeweler"
    ],
    "wof:name":"Peoples Jewellers",
    "wof:placetype":"venue"
},
  "geometry": {"coordinates":[-79.12297058110001,43.0668144226],"type":"Point"}
}