{
  "type": "Feature",
  "properties": {
    "addr:full":"105 Rue Renaud Laurierville QC G0S 1P0",
    "addr:housenumber":"105",
    "addr:postcode":"g0s 1p0",
    "addr:street":"Rue Renaud",
    "iso:country":"CA",
    "sg:address":"105 Rue Renaud",
    "sg:city":"Laurierville",
    "sg:classifiers":[
        {
            "category":"Manufacturing",
            "subcategory":"Apparel",
            "type":"Manufacturing & Wholesale Goods"
        }
    ],
    "sg:phone":"+1 819 365 4282",
    "sg:postcode":"G0S 1P0",
    "sg:province":"QC",
    "sg:tags":[
        "sewing",
        "contractor"
    ],
    "wof:name":"Technofil Inc",
    "wof:placetype":"venue"
},
  "geometry": {"coordinates":[-71.65477799999999,46.300804],"type":"Point"}
}