{
  "type": "Feature",
  "properties": {
    "addr:full":"Quebec QC G1R 1R7",
    "addr:postcode":"g1r 1r7",
    "iso:country":"CA",
    "sg:city":"Quebec",
    "sg:classifiers":[
        {
            "category":"Organizations",
            "subcategory":"Professional Association",
            "type":"Services"
        }
    ],
    "sg:phone":"+1 418 694 1394",
    "sg:postcode":"G1R 1R7",
    "sg:province":"QC",
    "wof:name":"United Transportation Union",
    "wof:placetype":"venue"
},
  "geometry": {"coordinates":[-71.21235656739999,46.8130455017],"type":"Point"}
}