{
  "type": "Feature",
  "properties": {
    "addr:full":"216 Main St Eston SK S0L 1A0",
    "addr:housenumber":"216",
    "addr:postcode":"s0l 1a0",
    "addr:street":"Main St",
    "iso:country":"CA",
    "sg:address":"216 Main St",
    "sg:city":"Eston",
    "sg:classifiers":[
        {
            "category":"Food & Beverages",
            "subcategory":"Groceries & Convenience Stores",
            "type":"Retail Goods"
        }
    ],
    "sg:phone":"+1 306 962 3514",
    "sg:postcode":"S0L 1A0",
    "sg:province":"SK",
    "sg:tags":[
        "grocer"
    ],
    "wof:name":"Eston Locker",
    "wof:placetype":"venue"
},
  "geometry": {"coordinates":[-108.753227,51.152733],"type":"Point"}
}