{
  "type": "Feature",
  "properties": {
    "iso:country":"CA",
    "sg:address":"499 Place Beauchamp",
    "sg:city":"Le Gardeur",
    "sg:classifiers":[
        {
            "category":"Building & Trades",
            "subcategory":"Construction",
            "type":"Services"
        }
    ],
    "sg:phone":"+1 450 471 1466",
    "sg:postcode":"J5Z 1K2",
    "sg:province":"QC",
    "sg:tags":[
        "steam",
        "cleaning"
    ],
    "wof:name":"Service Gn Inc",
    "wof:placetype":"venue"
},
  "geometry": {"coordinates":[-73.472237,45.75732],"type":"Point"}
}