{
  "type": "Feature",
  "properties": {
    "addr:full":"499 Place Beauchamp Le Gardeur QC J5Z 1K2",
    "addr:housenumber":"499",
    "addr:postcode":"j5z 1k2",
    "addr:street":"Place Beauchamp;Gardeur",
    "iso:country":"CA",
    "sg:address":"499 Place Beauchamp",
    "sg:city":"Le Gardeur",
    "sg:classifiers":[
        {
            "category":"Building & Trades",
            "subcategory":"Construction",
            "type":"Services"
        }
    ],
    "sg:phone":"+1 450 471 1466",
    "sg:postcode":"J5Z 1K2",
    "sg:province":"QC",
    "sg:tags":[
        "steam",
        "cleaning"
    ],
    "wof:name":"Service Gn Inc",
    "wof:placetype":"venue"
},
  "geometry": {"coordinates":[-73.47223700000001,45.75732],"type":"Point"}
}