{
  "type": "Feature",
  "properties": {
    "addr:full":"221 Rexleigh Dr East York ON M4B 2N7",
    "addr:housenumber":"221",
    "addr:postcode":"m4b 2n7",
    "addr:street":"Rexleigh Dr",
    "iso:country":"CA",
    "sg:address":"221 Rexleigh Dr",
    "sg:city":"East York",
    "sg:classifiers":[
        {
            "category":"Personal",
            "subcategory":"Barber",
            "type":"Services"
        }
    ],
    "sg:phone":"+1 416 757 1679",
    "sg:postcode":"M4B 2N7",
    "sg:province":"ON",
    "wof:name":"Rexleigh Barber Shop",
    "wof:placetype":"venue"
},
  "geometry": {"coordinates":[-79.306679,43.706097],"type":"Point"}
}