{
  "type": "Feature",
  "properties": {
    "iso:country":"CA",
    "sg:address":"3099 Carp Rd",
    "sg:city":"Carp",
    "sg:classifiers":[
        {
            "category":"Professional",
            "subcategory":"Accounting & Tax Preparation",
            "type":"Services"
        }
    ],
    "sg:phone":"+1 613 839 7777",
    "sg:postcode":"K0A 1L0",
    "sg:province":"ON",
    "sg:tags":[
        "return",
        "filing"
    ],
    "wof:name":"Bradley & Assoc",
    "wof:placetype":"venue"
},
  "geometry": {"coordinates":[-76.0029144287,45.3179206848],"type":"Point"}
}