{
  "type": "Feature",
  "properties": {
    "addr:full":"102 Rivalda Rd North York ON M9M 2M8",
    "addr:housenumber":"102",
    "addr:postcode":"m9m 2m8",
    "addr:street":"Rivalda Rd",
    "iso:country":"CA",
    "sg:address":"102 Rivalda Rd",
    "sg:city":"North York",
    "sg:classifiers":[
        {
            "category":"Organizations",
            "subcategory":"Religious Organization",
            "type":"Services"
        }
    ],
    "sg:phone":"+1 416 741 4335",
    "sg:postcode":"M9M 2M8",
    "sg:province":"ON",
    "sg:tags":[
        "church"
    ],
    "wof:name":"Pranav Hindu Mandir",
    "wof:placetype":"venue"
},
  "geometry": {"coordinates":[-79.5359573364,43.7418746948],"type":"Point"}
}