{
  "type": "Feature",
  "properties": {
    "addr:full":"199 Bay St Toronto ON M5L 1E7",
    "addr:housenumber":"199",
    "addr:postcode":"m5l 1e7",
    "addr:street":"Bay St",
    "iso:country":"CA",
    "sg:address":"199 Bay St",
    "sg:city":"Toronto",
    "sg:classifiers":[
        {
            "category":"Shopping",
            "subcategory":"Pharmacy",
            "type":"Retail Goods"
        }
    ],
    "sg:phone":"+1 416 365 0972",
    "sg:postcode":"M5L 1E7",
    "sg:province":"ON",
    "sg:tags":[
        "cosmetic",
        "perfume"
    ],
    "wof:name":"Pharma Plus Drugmart",
    "wof:placetype":"venue"
},
  "geometry": {"coordinates":[-79.37964599999999,43.647636],"type":"Point"}
}