{
  "type": "Feature",
  "properties": {
    "addr:full":"110 Anne St S Barrie ON L4N 2E3",
    "addr:housenumber":"110",
    "addr:postcode":"l4n 2e3",
    "addr:street":"Anne St S",
    "iso:country":"CA",
    "sg:address":"110 Anne St S",
    "sg:city":"Barrie",
    "sg:classifiers":[
        {
            "category":"Recreation",
            "type":"Entertainment"
        }
    ],
    "sg:phone":"+1 705 725 6200",
    "sg:postcode":"L4N 2E3",
    "sg:province":"ON",
    "sg:tags":[
        "parlor",
        "billiard"
    ],
    "wof:name":"Masse Hall Inc",
    "wof:placetype":"venue"
},
  "geometry": {"coordinates":[-79.6993713379,44.375377655],"type":"Point"}
}