{
  "type": "Feature",
  "properties": {
    "addr:full":"100 Metropolitan Rd Scarborough ON M1R 5A2",
    "addr:housenumber":"100",
    "addr:postcode":"m1r 5a2",
    "addr:street":"Metropolitan Rd",
    "iso:country":"CA",
    "sg:address":"100 Metropolitan Rd",
    "sg:city":"Scarborough",
    "sg:classifiers":[
        {
            "category":"Wholesale",
            "subcategory":"Durable Goods & Equipment",
            "type":"Manufacturing & Wholesale Goods"
        }
    ],
    "sg:phone":"+1 416 396 2700",
    "sg:postcode":"M1R 5A2",
    "sg:province":"ON",
    "sg:tags":[
        "distribution",
        "center"
    ],
    "wof:name":"Zellers",
    "wof:placetype":"venue"
},
  "geometry": {"coordinates":[-79.298019,43.768261],"type":"Point"}
}