{
  "type": "Feature",
  "properties": {
    "addr:full":"23 Arthur St W Hwy 26 Thornbury ON N0H 2P0",
    "addr:housenumber":"23",
    "addr:postcode":"n0h 2p0",
    "addr:street":"Arthur St W Hwy 26",
    "iso:country":"CA",
    "sg:address":"23 Arthur St W Hwy 26",
    "sg:city":"Thornbury",
    "sg:classifiers":[
        {
            "category":"Personal",
            "subcategory":"Beauty Salon",
            "type":"Services"
        }
    ],
    "sg:phone":"+1 519 599 2460",
    "sg:postcode":"N0H 2P0",
    "sg:province":"ON",
    "wof:name":"Nail & Esthetics Boutique",
    "wof:placetype":"venue"
},
  "geometry": {"coordinates":[-80.45435333250001,44.5624351501],"type":"Point"}
}