{
  "type": "Feature",
  "properties": {
    "iso:country":"CA",
    "sg:address":"402 Main St",
    "sg:city":"Wolfville",
    "sg:classifiers":[
        {
            "category":"Restaurant",
            "type":"Food & Drink"
        }
    ],
    "sg:phone":"+1 902 542 0477",
    "sg:postcode":"B4P 1C9",
    "sg:province":"NS",
    "sg:tags":[
        "pizza"
    ],
    "wof:name":"Chris' Pizzeria",
    "wof:placetype":"venue"
},
  "geometry": {"coordinates":[-64.3728256226,45.0900688171],"type":"Point"}
}