{
  "type": "Feature",
  "properties": {
    "addr:full":"6707 Winston Churchill Blvd # 3 Mississauga ON L5N 3W2",
    "addr:housenumber":"6707",
    "addr:postcode":"l5n 3w2",
    "addr:street":"Winston Churchill Blvd # 3",
    "iso:country":"CA",
    "sg:address":"6707 Winston Churchill Blvd # 3",
    "sg:city":"Mississauga",
    "sg:classifiers":[
        {
            "category":"Retail",
            "subcategory":"Auto Repair",
            "type":"Services"
        }
    ],
    "sg:phone":"+1 905 821 8685",
    "sg:postcode":"L5N 3W2",
    "sg:province":"ON",
    "sg:tags":[
        "automobile",
        "lubrication"
    ],
    "wof:name":"Lube Master",
    "wof:placetype":"venue"
},
  "geometry": {"coordinates":[-79.762665,43.582413],"type":"Point"}
}