{
  "type": "Feature",
  "properties": {
    "addr:full":"Paspebiac QC G0C 2K0",
    "addr:postcode":"g0c 2k0",
    "iso:country":"CA",
    "sg:city":"Paspebiac",
    "sg:classifiers":[
        {
            "category":"Travel",
            "subcategory":"Hotels & Motels",
            "type":"Entertainment"
        }
    ],
    "sg:phone":"+1 418 752 9923",
    "sg:postcode":"G0C 2K0",
    "sg:province":"QC",
    "sg:tags":[
        "resort"
    ],
    "wof:name":"Centre DE Plein Air Les Mntcls",
    "wof:placetype":"venue"
},
  "geometry": {"coordinates":[-65.2492675781,48.028968811],"type":"Point"}
}