{
  "type": "Feature",
  "properties": {
    "addr:full":"1 Old Yellowhead Hwy Jasper AB T0E 1E0",
    "addr:housenumber":"1",
    "addr:postcode":"t0e 1e0",
    "addr:street":"Old Yellowhead Hwy",
    "iso:country":"CA",
    "sg:address":"1 Old Yellowhead Hwy",
    "sg:city":"Jasper",
    "sg:classifiers":[
        {
            "category":"Home & Garden",
            "subcategory":"Building Materials",
            "type":"Retail Goods"
        }
    ],
    "sg:phone":"+1 780 852 4491",
    "sg:postcode":"T0E 1E0",
    "sg:province":"AB",
    "wof:name":"Jasper Lumber & Hardware",
    "wof:placetype":"venue"
},
  "geometry": {"coordinates":[-118.393569946,52.882724762],"type":"Point"}
}