{
  "type": "Feature",
  "properties": {
    "addr:full":"Granby QC J2G 5B4",
    "addr:postcode":"j2g 5b4",
    "iso:country":"CA",
    "sg:city":"Granby",
    "sg:classifiers":[
        {
            "category":"Personal",
            "subcategory":"Beauty Salon",
            "type":"Services"
        }
    ],
    "sg:phone":"+1 450 378 4403",
    "sg:postcode":"J2G 5B4",
    "sg:province":"QC",
    "wof:name":"Salon Reflets Beaute II Enr",
    "wof:placetype":"venue"
},
  "geometry": {"coordinates":[-72.7263259888,45.4004516602],"type":"Point"}
}