{
  "type": "Feature",
  "properties": {
    "addr:full":"30 Eugene St North York ON M6B 3Z4",
    "addr:housenumber":"30",
    "addr:postcode":"m6b 3z4",
    "addr:street":"Eugene St",
    "iso:country":"CA",
    "sg:address":"30 Eugene St",
    "sg:city":"North York",
    "sg:classifiers":[
        {
            "category":"Retail",
            "subcategory":"Auto Repair",
            "type":"Services"
        }
    ],
    "sg:phone":"+1 416 789 1491",
    "sg:postcode":"M6B 3Z4",
    "sg:province":"ON",
    "sg:tags":[
        "repairing",
        "automobile"
    ],
    "wof:name":"Bruno Auto Repairs",
    "wof:placetype":"venue"
},
  "geometry": {"coordinates":[-79.4686203003,43.7086868286],"type":"Point"}
}