{
  "type": "Feature",
  "properties": {
    "addr:full":"335 Boul Sir-Wilfrid-Laurier Beloeil QC J3G 4H5",
    "addr:housenumber":"335",
    "addr:postcode":"j3g 4h5",
    "addr:street":"Boul Sir-Wilfrid-Laurier",
    "iso:country":"CA",
    "sg:address":"335 Boul Sir-Wilfrid-Laurier",
    "sg:city":"Beloeil",
    "sg:classifiers":[
        {
            "category":"Restaurant",
            "type":"Food & Drink"
        }
    ],
    "sg:phone":"+1 450 467 0118",
    "sg:postcode":"J3G 4H5",
    "sg:province":"QC",
    "wof:name":"Kfc",
    "wof:placetype":"venue"
},
  "geometry": {"coordinates":[-73.21128082280001,45.5559959412],"type":"Point"}
}