{
  "type": "Feature",
  "properties": {
    "addr:full":"3260 Av Francis-Hughes Laval QC H7L 5A7",
    "addr:housenumber":"3260",
    "addr:postcode":"h7l 5a7",
    "addr:street":"Av Francis-Hughes",
    "iso:country":"CA",
    "sg:address":"3260 Av Francis-Hughes",
    "sg:city":"Laval",
    "sg:classifiers":[
        {
            "category":"Manufacturing",
            "subcategory":"Tools & Machinery",
            "type":"Manufacturing & Wholesale Goods"
        }
    ],
    "sg:phone":"+1 450 663 5830",
    "sg:postcode":"H7L 5A7",
    "sg:province":"QC",
    "sg:tags":[
        "die",
        "maker"
    ],
    "wof:name":"Techno-Coupe Inc",
    "wof:placetype":"venue"
},
  "geometry": {"coordinates":[-73.7383346558,45.593547821],"type":"Point"}
}