{
  "type": "Feature",
  "properties": {
    "iso:country":"CA",
    "sg:city":"Campbellville",
    "sg:classifiers":[
        {
            "category":"Building & Trades",
            "subcategory":"Construction",
            "type":"Services"
        }
    ],
    "sg:phone":"+1 905 854 2521",
    "sg:postcode":"L0P 1B0",
    "sg:province":"ON",
    "sg:tags":[
        "siding",
        "contractor"
    ],
    "wof:name":"F D Siding & Eavestroughing",
    "wof:placetype":"venue"
},
  "geometry": {"coordinates":[-79.9729919434,43.4806785583],"type":"Point"}
}