{
  "type": "Feature",
  "properties": {
    "iso:country":"CA",
    "sg:address":"1352 Langlois Ave",
    "sg:city":"Windsor",
    "sg:classifiers":[
        {
            "category":"Social Services",
            "subcategory":"Child Care",
            "type":"Services"
        }
    ],
    "sg:phone":"+1 519 973 3070",
    "sg:postcode":"N8X 4L7",
    "sg:province":"ON",
    "wof:name":"Ursula Day Nursery",
    "wof:placetype":"venue"
},
  "geometry": {"coordinates":[-83.015045,42.307762],"type":"Point"}
}