{
  "type": "Feature",
  "properties": {
    "addr:full":"216 7 Ave SW Calgary AB T2P 0W6",
    "addr:housenumber":"216",
    "addr:postcode":"t2p 0w6",
    "addr:street":"7 Ave Sw",
    "iso:country":"CA",
    "sg:address":"216 7 Ave SW",
    "sg:city":"Calgary",
    "sg:classifiers":[
        {
            "category":"Restaurant",
            "type":"Food & Drink"
        }
    ],
    "sg:phone":"+1 403 269 8211",
    "sg:postcode":"T2P 0W6",
    "sg:province":"AB",
    "wof:name":"Thanh Truc Vietnamese Rstrnt",
    "wof:placetype":"venue"
},
  "geometry": {"coordinates":[-114.065971374,51.046672821],"type":"Point"}
}