{
  "type": "Feature",
  "properties": {
    "addr:full":"294 E 3rd St Vanderhoof BC V0J 3A0",
    "addr:housenumber":"294",
    "addr:postcode":"v0j 3a0",
    "addr:street":"E 3Rd St",
    "iso:country":"CA",
    "sg:address":"294 E 3rd St",
    "sg:city":"Vanderhoof",
    "sg:classifiers":[
        {
            "category":"Wholesale",
            "subcategory":"Scrap",
            "type":"Manufacturing & Wholesale Goods"
        }
    ],
    "sg:phone":"+1 250 567 4059",
    "sg:postcode":"V0J 3A0",
    "sg:province":"BC",
    "sg:tags":[
        "depot",
        "container",
        "can"
    ],
    "wof:name":"Nechako Valley Secondary Schl",
    "wof:placetype":"venue"
},
  "geometry": {"coordinates":[-124.012901,54.013977],"type":"Point"}
}