{
  "type": "Feature",
  "properties": {
    "iso:country":"CA",
    "sg:address":"54 4th Ave E",
    "sg:city":"Vancouver",
    "sg:classifiers":[
        {
            "category":"Manufacturing",
            "subcategory":"Apparel",
            "type":"Manufacturing & Wholesale Goods"
        }
    ],
    "sg:phone":"+1 604 872 6989",
    "sg:postcode":"V5T 1E8",
    "sg:province":"BC",
    "sg:tags":[
        "clothing"
    ],
    "wof:name":"Prominent Fashions Mfg Ltd",
    "wof:placetype":"venue"
},
  "geometry": {"coordinates":[-123.103721619,49.2672538757],"type":"Point"}
}