{
  "type": "Feature",
  "properties": {
    "addr:full":"2148 Rue DE LA Province Longueuil QC J4G 1R7",
    "addr:housenumber":"2148",
    "addr:postcode":"j4g 1r7",
    "addr:street":"Rue De La Province",
    "iso:country":"CA",
    "sg:address":"2148 Rue DE LA Province",
    "sg:city":"Longueuil",
    "sg:classifiers":[
        {
            "category":"Wholesale",
            "subcategory":"Electrical",
            "type":"Manufacturing & Wholesale Goods"
        }
    ],
    "sg:phone":"+1 450 463 4571",
    "sg:postcode":"J4G 1R7",
    "sg:province":"QC",
    "sg:tags":[
        "light",
        "tube",
        "bulb"
    ],
    "wof:name":"Eclair-Plus",
    "wof:placetype":"venue"
},
  "geometry": {"coordinates":[-73.471306,45.564835],"type":"Point"}
}