{
  "type": "Feature",
  "properties": {
    "iso:country":"CA",
    "sg:address":"3161 Edgemont Blvd",
    "sg:city":"North Vancouver",
    "sg:classifiers":[
        {
            "category":"Retail",
            "subcategory":"Photofinishing",
            "type":"Services"
        }
    ],
    "sg:phone":"+1 604 985 2311",
    "sg:postcode":"V7R 2N8",
    "sg:province":"BC",
    "sg:tags":[
        "photo",
        "finishing"
    ],
    "wof:name":"Village Photo",
    "wof:placetype":"venue"
},
  "geometry": {"coordinates":[-123.10303497300001,49.3381385803],"type":"Point"}
}