{
  "type": "Feature",
  "properties": {
    "addr:full":"Saint-Victor QC G0M 2B0",
    "addr:postcode":"g0m 2b0",
    "iso:country":"CA",
    "sg:city":"Saint-Victor",
    "sg:classifiers":[
        {
            "category":"Building & Trades",
            "subcategory":"Construction",
            "type":"Services"
        }
    ],
    "sg:phone":"+1 418 588 7285",
    "sg:postcode":"G0M 2B0",
    "sg:province":"QC",
    "sg:tags":[
        "general",
        "contractor"
    ],
    "wof:name":"Constructions Paul-Eugene",
    "wof:placetype":"venue"
},
  "geometry": {"coordinates":[-70.902687,46.14695],"type":"Point"}
}