{
  "type": "Feature",
  "properties": {
    "addr:full":"183 Pemberton Ave North Vancouver BC V7P 2R4",
    "addr:housenumber":"183",
    "addr:postcode":"v7p 2r4",
    "addr:street":"Pemberton Ave",
    "iso:country":"CA",
    "sg:address":"183 Pemberton Ave",
    "sg:city":"North Vancouver",
    "sg:classifiers":[
        {
            "category":"Retail",
            "subcategory":"Auto Repair",
            "type":"Services"
        }
    ],
    "sg:phone":"+1 604 985 7195",
    "sg:postcode":"V7P 2R4",
    "sg:province":"BC",
    "sg:tags":[
        "repairing",
        "automobile",
        "body"
    ],
    "wof:name":"Levett Auto Metal Ltd",
    "wof:placetype":"venue"
},
  "geometry": {"coordinates":[-123.10810089100001,49.3184242249],"type":"Point"}
}