{
  "type": "Feature",
  "properties": {
    "addr:full":"12 Wren Dr Cobden ON K0J 1K0",
    "addr:housenumber":"12",
    "addr:postcode":"k0j 1k0",
    "addr:street":"Wren Dr",
    "iso:country":"CA",
    "sg:address":"12 Wren Dr",
    "sg:city":"Cobden",
    "sg:classifiers":[
        {
            "category":"Health Services",
            "subcategory":"Nursing And Care Facility",
            "type":"Services"
        }
    ],
    "sg:phone":"+1 613 646 2109",
    "sg:postcode":"K0J 1K0",
    "sg:province":"ON",
    "sg:tags":[
        "home",
        "convalescent"
    ],
    "wof:name":"Caressant Care Cobden Nursing",
    "wof:placetype":"venue"
},
  "geometry": {"coordinates":[-76.88642900000001,45.627548],"type":"Point"}
}