{
  "type": "Feature",
  "properties": {
    "iso:country":"CA",
    "sg:city":"Montreal",
    "sg:classifiers":[
        {
            "category":"Shopping",
            "subcategory":"Stationery & Office Supplies",
            "type":"Retail Goods"
        }
    ],
    "sg:phone":"+1 514 282 9881",
    "sg:postcode":"H2Y 2P5",
    "sg:province":"QC",
    "wof:name":"404223 Canada Inc",
    "wof:placetype":"venue"
},
  "geometry": {"coordinates":[-73.5560531616,45.5020523071],"type":"Point"}
}