{
  "type": "Feature",
  "properties": {
    "addr:full":"PO Box 181 Buckhorn ON K0L 1J0",
    "addr:housenumber":"po",
    "addr:postcode":"k0l 1j0",
    "addr:street":"Box 181",
    "iso:country":"CA",
    "sg:address":"PO Box 181",
    "sg:city":"Buckhorn",
    "sg:classifiers":[
        {
            "category":"Building & Trades",
            "subcategory":"Construction",
            "type":"Services"
        }
    ],
    "sg:phone":"+1 705 657 8682",
    "sg:postcode":"K0L 1J0",
    "sg:province":"ON",
    "sg:tags":[
        "contractor"
    ],
    "wof:name":"B A Construction",
    "wof:placetype":"venue"
},
  "geometry": {"coordinates":[-78.351952,44.554256],"type":"Point"}
}