{
  "type": "Feature",
  "properties": {
    "iso:country":"CA",
    "sg:address":"240 Furnival Rd",
    "sg:city":"Rodney",
    "sg:classifiers":[
        {
            "category":"Restaurant",
            "type":"Food & Drink"
        }
    ],
    "sg:phone":"+1 519 785 3000",
    "sg:postcode":"N0L 2C0",
    "sg:province":"ON",
    "sg:tags":[
        "out"
    ],
    "wof:name":"Back Door Pizza",
    "wof:placetype":"venue"
},
  "geometry": {"coordinates":[-81.682762146,42.5676269531],"type":"Point"}
}