{
  "type": "Feature",
  "properties": {
    "addr:full":"299 Yorkland Blvd North York ON M2J 1S5",
    "addr:housenumber":"299",
    "addr:postcode":"m2j 1s5",
    "addr:street":"Yorkland Blvd",
    "iso:country":"CA",
    "sg:address":"299 Yorkland Blvd",
    "sg:city":"North York",
    "sg:classifiers":[
        {
            "category":"Retail",
            "subcategory":"Auto Repair",
            "type":"Services"
        }
    ],
    "sg:phone":"+1 416 756 4044",
    "sg:postcode":"M2J 1S5",
    "sg:province":"ON",
    "sg:tags":[
        "body",
        "automobile",
        "painting"
    ],
    "wof:name":"Summit Collision Carstar Ltd",
    "wof:placetype":"venue"
},
  "geometry": {"coordinates":[-79.33487700000001,43.773327],"type":"Point"}
}