{
  "type": "Feature",
  "properties": {
    "iso:country":"CA",
    "sg:address":"150 Churchill Blvd",
    "sg:city":"Sault Ste Marie",
    "sg:classifiers":[
        {
            "category":"Manufacturing",
            "subcategory":"Food",
            "type":"Manufacturing & Wholesale Goods"
        }
    ],
    "sg:phone":"+1 705 253 2161",
    "sg:postcode":"P6A 3Z9",
    "sg:province":"ON",
    "sg:tags":[
        "winery"
    ],
    "wof:name":"Wine Rack",
    "wof:placetype":"venue"
},
  "geometry": {"coordinates":[-84.29834747309999,46.5095863342],"type":"Point"}
}