{
  "type": "Feature",
  "properties": {
    "addr:full":"5896 County Rd 7 Guelph ON N1H 6J2",
    "addr:housenumber":"5896",
    "addr:postcode":"n1h 6j2",
    "addr:street":"County Rd 7",
    "iso:country":"CA",
    "sg:address":"5896 County Rd 7",
    "sg:city":"Guelph",
    "sg:classifiers":[
        {
            "category":"Building & Trades",
            "subcategory":"Plumbing",
            "type":"Services"
        }
    ],
    "sg:phone":"+1 519 763 8239",
    "sg:postcode":"N1H 6J2",
    "sg:province":"ON",
    "sg:tags":[
        "water",
        "well",
        "drilling",
        "contractor"
    ],
    "wof:name":"Hanlon Well Drilling Ltd",
    "wof:placetype":"venue"
},
  "geometry": {"coordinates":[-80.2478713989,43.5445632935],"type":"Point"}
}