{
  "type": "Feature",
  "properties": {
    "iso:country":"CA",
    "sg:city":"Winnipeg",
    "sg:classifiers":[
        {
            "category":"Real Estate",
            "subcategory":"Real Estate Agent",
            "type":"Services"
        }
    ],
    "sg:phone":"+1 204 284 1300",
    "sg:postcode":"R3M 3Y7",
    "sg:province":"MB",
    "sg:tags":[
        "management"
    ],
    "wof:name":"Remco Realty Inc",
    "wof:placetype":"venue"
},
  "geometry": {"coordinates":[-97.15352630620001,49.8562164307],"type":"Point"}
}