{
  "type": "Feature",
  "properties": {
    "addr:full":"Hines Creek AB T0H 2A0",
    "addr:postcode":"t0h 2a0",
    "iso:country":"CA",
    "sg:city":"Hines Creek",
    "sg:classifiers":[
        {
            "category":"Education",
            "subcategory":"School",
            "type":"Public Place"
        }
    ],
    "sg:phone":"+1 780 494 3510",
    "sg:postcode":"T0H 2A0",
    "sg:province":"AB",
    "wof:name":"Hines Creek High School",
    "wof:placetype":"venue"
},
  "geometry": {"coordinates":[-118.602264404,56.2473716736],"type":"Point"}
}