{
  "type": "Feature",
  "properties": {
    "addr:full":"156 16E Av O Venise-En-Quebec QC J0J 2K0",
    "addr:housenumber":"156",
    "addr:postcode":"j0j 2k0",
    "addr:street":"16E Av O Venise-En-Quebec",
    "iso:country":"CA",
    "sg:address":"156 16E Av O",
    "sg:city":"Venise-En-Quebec",
    "sg:classifiers":[
        {
            "category":"Autos & Motor Vehicles",
            "subcategory":"Fuel & Gas Station",
            "type":"Retail Goods"
        }
    ],
    "sg:phone":"+1 450 244 5383",
    "sg:postcode":"J0J 2K0",
    "sg:province":"QC",
    "sg:tags":[
        "oil"
    ],
    "wof:name":"Depanneur Venise",
    "wof:placetype":"venue"
},
  "geometry": {"coordinates":[-73.152046,45.086891],"type":"Point"}
}