{
  "type": "Feature",
  "properties": {
    "addr:full":"311 Av Saint-Laurent Louiseville QC J5V 1K2",
    "addr:housenumber":"311",
    "addr:postcode":"j5v 1k2",
    "addr:street":"Av Saint-Laurent",
    "iso:country":"CA",
    "sg:address":"311 Av Saint-Laurent",
    "sg:city":"Louiseville",
    "sg:classifiers":[
        {
            "category":"Retail",
            "subcategory":"Portrait Studio",
            "type":"Services"
        }
    ],
    "sg:phone":"+1 819 228 5892",
    "sg:postcode":"J5V 1K2",
    "sg:province":"QC",
    "sg:tags":[
        "photographer"
    ],
    "wof:name":"Jacques Beland Photos Enr",
    "wof:placetype":"venue"
},
  "geometry": {"coordinates":[-72.94617462159999,46.2555809021],"type":"Point"}
}