{
  "type": "Feature",
  "properties": {
    "addr:full":"117 Orchard Way Strathmore AB T1P 1R8",
    "addr:housenumber":"117",
    "addr:postcode":"t1p 1r8",
    "addr:street":"Orchard Way",
    "iso:country":"CA",
    "sg:address":"117 Orchard Way",
    "sg:city":"Strathmore",
    "sg:classifiers":[
        {
            "category":"Mining & Drilling",
            "type":"Manufacturing & Wholesale Goods"
        }
    ],
    "sg:phone":"+1 403 901 2210",
    "sg:postcode":"T1P 1R8",
    "sg:province":"AB",
    "sg:tags":[
        "oil",
        "gas",
        "producer"
    ],
    "wof:name":"Eog Resources Canada Inc",
    "wof:placetype":"venue"
},
  "geometry": {"coordinates":[-113.389977,51.032341],"type":"Point"}
}