{
  "type": "Feature",
  "properties": {
    "addr:full":"3660 Lake Shore Blvd W Etobicoke ON M8W 1P2",
    "addr:housenumber":"3660",
    "addr:postcode":"m8w 1p2",
    "addr:street":"Lake Shore Blvd W",
    "iso:country":"CA",
    "sg:address":"3660 Lake Shore Blvd W",
    "sg:city":"Etobicoke",
    "sg:classifiers":[
        {
            "category":"Professional",
            "type":"Services"
        }
    ],
    "sg:phone":"+1 416 201 0844",
    "sg:postcode":"M8W 1P2",
    "sg:province":"ON",
    "sg:tags":[
        "marketing",
        "program",
        "establishment"
    ],
    "wof:name":"Castrol Canada Inc",
    "wof:placetype":"venue"
},
  "geometry": {"coordinates":[-79.53685,43.59383],"type":"Point"}
}