{
  "type": "Feature",
  "properties": {
    "addr:full":"6315 Montevideo Rd Mississauga ON L5N 4G7",
    "addr:housenumber":"6315",
    "addr:postcode":"l5n 4g7",
    "addr:street":"Montevideo Rd",
    "iso:country":"CA",
    "sg:address":"6315 Montevideo Rd",
    "sg:city":"Mississauga",
    "sg:classifiers":[
        {
            "category":"Government",
            "subcategory":"Office",
            "type":"Public Place"
        }
    ],
    "sg:phone":"+1 905 821 7732",
    "sg:postcode":"L5N 4G7",
    "sg:province":"ON",
    "sg:tags":[
        "village"
    ],
    "wof:name":"Meadowvale Theatre",
    "wof:placetype":"venue"
},
  "geometry": {"coordinates":[-79.747551,43.585472],"type":"Point"}
}