{
  "type": "Feature",
  "properties": {
    "addr:full":"Janetville Rd Janetville ON L0B 1K0",
    "addr:postcode":"l0b 1k0",
    "addr:street":"Janetville Rd",
    "iso:country":"CA",
    "sg:address":"Janetville Rd",
    "sg:city":"Janetville",
    "sg:classifiers":[
        {
            "category":"Recreation",
            "type":"Entertainment"
        }
    ],
    "sg:phone":"+1 705 324 9604",
    "sg:postcode":"L0B 1K0",
    "sg:province":"ON",
    "sg:tags":[
        "government",
        "hall",
        "auditorium"
    ],
    "wof:name":"Janetville Community Ctr",
    "wof:placetype":"venue"
},
  "geometry": {"coordinates":[-78.72133636469999,44.2064704895],"type":"Point"}
}