{
  "type": "Feature",
  "properties": {
    "addr:full":"Calgary AB T2C 2X5",
    "addr:postcode":"t2c 2x5",
    "iso:country":"CA",
    "sg:city":"Calgary",
    "sg:classifiers":[
        {
            "category":"Social Services",
            "subcategory":"Child Care",
            "type":"Services"
        }
    ],
    "sg:phone":"+1 403 236 7908",
    "sg:postcode":"T2C 2X5",
    "sg:province":"AB",
    "wof:name":"Riverbend Day Care Ctr",
    "wof:placetype":"venue"
},
  "geometry": {"coordinates":[-114.012702942,50.9778556824],"type":"Point"}
}