{
  "type": "Feature",
  "properties": {
    "addr:full":"Courtenay BC V9N 8V7",
    "addr:postcode":"v9n 8v7",
    "iso:country":"CA",
    "sg:city":"Courtenay",
    "sg:classifiers":[
        {
            "category":"Health Services",
            "subcategory":"Health Practitioner",
            "type":"Services"
        }
    ],
    "sg:phone":"+1 250 338 8754",
    "sg:postcode":"V9N 8V7",
    "sg:province":"BC",
    "sg:tags":[
        "physiotherapist"
    ],
    "wof:name":"Courtenay Physiotherapy Clinic",
    "wof:placetype":"venue"
},
  "geometry": {"coordinates":[-124.99546814,49.686580658],"type":"Point"}
}