{
  "type": "Feature",
  "properties": {
    "addr:full":"8599 112 St Fort Saskatchewan AB T8L 3V3",
    "addr:housenumber":"8599",
    "addr:postcode":"t8l 3v3",
    "addr:street":"112 St",
    "iso:country":"CA",
    "sg:address":"8599 112 St",
    "sg:city":"Fort Saskatchewan",
    "sg:classifiers":[
        {
            "category":"Wholesale",
            "subcategory":"Machinery & Supplies",
            "type":"Manufacturing & Wholesale Goods"
        }
    ],
    "sg:phone":"+1 780 998 3249",
    "sg:postcode":"T8L 3V3",
    "sg:province":"AB",
    "sg:tags":[
        "farm",
        "equipment"
    ],
    "wof:name":"Deerland Farm Equipment Ltd",
    "wof:placetype":"venue"
},
  "geometry": {"coordinates":[-113.19001,53.706142],"type":"Point"}
}