{
  "type": "Feature",
  "properties": {
    "iso:country":"CA",
    "sg:address":"1665 Rue Poirier",
    "sg:city":"Saint-Laurent",
    "sg:classifiers":[
        {
            "category":"Personal",
            "subcategory":"Barber",
            "type":"Services"
        }
    ],
    "sg:phone":"+1 514 747 9242",
    "sg:postcode":"H4L 1J2",
    "sg:province":"QC",
    "wof:name":"Peter Salon Hair Stylist",
    "wof:placetype":"venue"
},
  "geometry": {"coordinates":[-73.69734191889999,45.5197639465],"type":"Point"}
}