{
  "type": "Feature",
  "properties": {
    "iso:country":"CA",
    "sg:city":"Montreal",
    "sg:classifiers":[
        {
            "category":"Shopping",
            "subcategory":"Clothing, Apparel, & Fashions",
            "type":"Retail Goods"
        }
    ],
    "sg:phone":"+1 514 321 0533",
    "sg:postcode":"H1Z 4H9",
    "sg:province":"QC",
    "sg:tags":[
        "furnishing"
    ],
    "wof:name":"Promodor",
    "wof:placetype":"venue"
},
  "geometry": {"coordinates":[-73.617287,45.577763],"type":"Point"}
}