{
  "type": "Feature",
  "properties": {
    "addr:full":"11307 Rue Notre-Dame E Montreal-Est QC H1B 2W4",
    "addr:housenumber":"11307",
    "addr:postcode":"h1b 2w4",
    "addr:street":"Rue Notre-Dame E Montreal-Est",
    "iso:country":"CA",
    "sg:address":"11307 Rue Notre-Dame E",
    "sg:city":"Montreal-Est",
    "sg:classifiers":[
        {
            "category":"Shopping",
            "subcategory":"Optical Goods",
            "type":"Retail Goods"
        }
    ],
    "sg:phone":"+1 514 645 8877",
    "sg:postcode":"H1B 2W4",
    "sg:province":"QC",
    "sg:tags":[
        "optometrist",
        "contact",
        "lense"
    ],
    "wof:name":"Optique Jm Picard Inc",
    "wof:placetype":"venue"
},
  "geometry": {"coordinates":[-73.4970169067,45.6306343079],"type":"Point"}
}