{
  "type": "Feature",
  "properties": {
    "addr:full":"Hwy 599 N Pickle Lake ON P0V 3A0",
    "addr:postcode":"p0v 3a0",
    "addr:street":"Hwy 599 N",
    "iso:country":"CA",
    "sg:address":"Hwy 599 N",
    "sg:city":"Pickle Lake",
    "sg:classifiers":[
        {
            "category":"Taxi",
            "type":"Transportation"
        }
    ],
    "sg:phone":"+1 807 928 2457",
    "sg:postcode":"P0V 3A0",
    "sg:province":"ON",
    "sg:tags":[
        "taxicab"
    ],
    "wof:name":"Tom's Taxi",
    "wof:placetype":"venue"
},
  "geometry": {"coordinates":[-90.1638641357,51.4621238708],"type":"Point"}
}