{
  "type": "Feature",
  "properties": {
    "addr:full":"450 Main St W North Bay ON P1B 2V2",
    "addr:housenumber":"450",
    "addr:postcode":"p1b 2v2",
    "addr:street":"Main St W",
    "iso:country":"CA",
    "sg:address":"450 Main St W",
    "sg:city":"North Bay",
    "sg:classifiers":[
        {
            "category":"Banks & Credit Unions",
            "subcategory":"Bank",
            "type":"Services"
        }
    ],
    "sg:phone":"+1 705 494 9911",
    "sg:postcode":"P1B 2V2",
    "sg:province":"ON",
    "sg:tags":[
        "financing",
        "loan",
        "real estate"
    ],
    "wof:name":"Mortgage Corp Financial Svc",
    "wof:placetype":"venue"
},
  "geometry": {"coordinates":[-79.467857,46.315033],"type":"Point"}
}