{
  "type": "Feature",
  "properties": {
    "addr:full":"Vancouver BC V6Z 2P3",
    "addr:postcode":"v6z 2p3",
    "iso:country":"CA",
    "sg:city":"Vancouver",
    "sg:classifiers":[
        {
            "category":"Professional",
            "subcategory":"Employment Agencies",
            "type":"Services"
        }
    ],
    "sg:phone":"+1 604 221 4080",
    "sg:postcode":"V6Z 2P3",
    "sg:province":"BC",
    "sg:tags":[
        "modeling"
    ],
    "wof:name":"Vmh Intl Model Group",
    "wof:placetype":"venue"
},
  "geometry": {"coordinates":[-123.12902069099999,49.2765922546],"type":"Point"}
}