{
  "type": "Feature",
  "properties": {
    "iso:country":"CA",
    "sg:address":"77 Mccaul St",
    "sg:city":"Toronto",
    "sg:classifiers":[
        {
            "category":"Personal",
            "subcategory":"Beauty Salon",
            "type":"Services"
        }
    ],
    "sg:phone":"+1 416 993 2184",
    "sg:postcode":"M5T 2W7",
    "sg:province":"ON",
    "wof:name":"Carolyn Mc Auley Hair",
    "wof:placetype":"venue"
},
  "geometry": {"coordinates":[-79.390625,43.6528434753],"type":"Point"}
}