{
  "type": "Feature",
  "properties": {
    "addr:full":"1213 Pearce Cres Victoria BC V8X 3S8",
    "addr:housenumber":"1213",
    "addr:postcode":"v8x 3s8",
    "addr:street":"Pearce Cres",
    "iso:country":"CA",
    "sg:address":"1213 Pearce Cres",
    "sg:city":"Victoria",
    "sg:classifiers":[
        {
            "category":"Professional",
            "subcategory":"Business Services",
            "type":"Services"
        }
    ],
    "sg:phone":"+1 250 479 1000",
    "sg:postcode":"V8X 3S8",
    "sg:province":"BC",
    "sg:tags":[
        "balloon",
        "decorating",
        "artist"
    ],
    "wof:name":"Helium To Go Victoria",
    "wof:placetype":"venue"
},
  "geometry": {"coordinates":[-123.364517212,48.428314209],"type":"Point"}
}