{
  "type": "Feature",
  "properties": {
    "addr:full":"799 Logan Ave Winnipeg MB R3E 3J9",
    "addr:housenumber":"799",
    "addr:postcode":"r3e 3j9",
    "addr:street":"Logan Ave",
    "iso:country":"CA",
    "sg:address":"799 Logan Ave",
    "sg:city":"Winnipeg",
    "sg:classifiers":[
        {
            "category":"Arena",
            "subcategory":"Sports Club",
            "type":"Entertainment"
        }
    ],
    "sg:phone":"+1 204 986 6989",
    "sg:postcode":"R3E 3J9",
    "sg:province":"MB",
    "sg:tags":[
        "athletic",
        "fields",
        "stadium"
    ],
    "wof:name":"Pioneer Arena",
    "wof:placetype":"venue"
},
  "geometry": {"coordinates":[-97.15773,49.909649],"type":"Point"}
}