{
  "type": "Feature",
  "properties": {
    "addr:full":"5770 Boul Taschereau Brossard QC J4W 1M6",
    "addr:housenumber":"5770",
    "addr:postcode":"j4w 1m6",
    "addr:street":"Boul Taschereau",
    "iso:country":"CA",
    "sg:address":"5770 Boul Taschereau",
    "sg:city":"Brossard",
    "sg:classifiers":[
        {
            "category":"Autos & Motor Vehicles",
            "subcategory":"Automobile Sales",
            "type":"Retail Goods"
        }
    ],
    "sg:phone":"+1 450 923 7777",
    "sg:postcode":"J4W 1M6",
    "sg:province":"QC",
    "sg:tags":[
        "car",
        "dealer"
    ],
    "wof:name":"Lexus Prestige",
    "wof:placetype":"venue"
},
  "geometry": {"coordinates":[-73.46558400000001,45.479225],"type":"Point"}
}