{
  "type": "Feature",
  "properties": {
    "addr:full":"Plantagenet ON K0B 1L0",
    "addr:postcode":"k0b 1l0",
    "iso:country":"CA",
    "sg:city":"Plantagenet",
    "sg:classifiers":[
        {
            "category":"Organizations",
            "subcategory":"Religious Organization",
            "type":"Services"
        }
    ],
    "sg:phone":"+1 613 673 4766",
    "sg:postcode":"K0B 1L0",
    "sg:province":"ON",
    "wof:name":"Centre DE L'Amour",
    "wof:placetype":"venue"
},
  "geometry": {"coordinates":[-75.059921,45.560383],"type":"Point"}
}