{
  "type": "Feature",
  "properties": {
    "iso:country":"CA",
    "sg:address":"365 North Front St # 13",
    "sg:city":"Belleville",
    "sg:classifiers":[
        {
            "category":"Restaurant",
            "type":"Food & Drink"
        }
    ],
    "sg:phone":"+1 613 967 7888",
    "sg:postcode":"K8P 5A5",
    "sg:province":"ON",
    "wof:name":"Buffet Garden",
    "wof:placetype":"venue"
},
  "geometry": {"coordinates":[-77.395859,44.187622],"type":"Point"}
}