{
  "type": "Feature",
  "properties": {
    "iso:country":"CA",
    "sg:address":"6774 75 St NW",
    "sg:city":"Edmonton",
    "sg:classifiers":[
        {
            "category":"Home & Garden",
            "subcategory":"Carpets & Floor Coverings",
            "type":"Retail Goods"
        }
    ],
    "sg:phone":"+1 780 448 2858",
    "sg:postcode":"T6E 6T9",
    "sg:province":"AB",
    "sg:tags":[
        "dealer",
        "rug"
    ],
    "wof:name":"Carpet Superstore",
    "wof:placetype":"venue"
},
  "geometry": {"coordinates":[-113.442863464,53.5049552917],"type":"Point"}
}