{
  "type": "Feature",
  "properties": {
    "addr:full":"1275 St. David St Victoria BC V8S 4Z1",
    "addr:housenumber":"1275",
    "addr:postcode":"v8s 4z1",
    "addr:street":"St. David St",
    "iso:country":"CA",
    "sg:address":"1275 St. David St",
    "sg:city":"Victoria",
    "sg:classifiers":[
        {
            "category":"Real Estate",
            "subcategory":"Real Estate Agent",
            "type":"Services"
        }
    ],
    "sg:phone":"+1 250 595 4021",
    "sg:postcode":"V8S 4Z1",
    "sg:province":"BC",
    "sg:tags":[
        "management"
    ],
    "wof:name":"Peel Property Svc",
    "wof:placetype":"venue"
},
  "geometry": {"coordinates":[-123.36451700000001,48.428314],"type":"Point"}
}