{
  "type": "Feature",
  "properties": {
    "addr:full":"Hwy 43 N Whitecourt AB T7S 1N9",
    "addr:postcode":"t7s 1n9",
    "addr:street":"Hwy 43 N",
    "iso:country":"CA",
    "sg:address":"Hwy 43 N",
    "sg:city":"Whitecourt",
    "sg:classifiers":[
        {
            "category":"Travel",
            "subcategory":"Hotels & Motels",
            "type":"Entertainment"
        }
    ],
    "sg:phone":"+1 780 778 3734",
    "sg:postcode":"T7S 1N9",
    "sg:province":"AB",
    "sg:tags":[
        "campground",
        "resort"
    ],
    "wof:name":"Sagitawah Rv Park",
    "wof:placetype":"venue"
},
  "geometry": {"coordinates":[-115.707954407,54.1393051147],"type":"Point"}
}