{
  "type": "Feature",
  "properties": {
    "addr:full":"195 Broadway St Woodstock NB E7M 1B8",
    "addr:housenumber":"195",
    "addr:postcode":"e7m 1b8",
    "addr:street":"Broadway St",
    "iso:country":"CA",
    "sg:address":"195 Broadway St",
    "sg:city":"Woodstock",
    "sg:classifiers":[
        {
            "category":"Food & Beverages",
            "subcategory":"Groceries & Convenience Stores",
            "type":"Retail Goods"
        }
    ],
    "sg:phone":"+1 506 328 3466",
    "sg:postcode":"E7M 1B8",
    "sg:province":"NB",
    "sg:tags":[
        "grocer"
    ],
    "wof:name":"Broadway Mainway",
    "wof:placetype":"venue"
},
  "geometry": {"coordinates":[-67.582581,46.142292],"type":"Point"}
}