{
  "type": "Feature",
  "properties": {
    "addr:full":"PO Box 66 Beiseker AB T0M 0G0",
    "addr:housenumber":"po box 66",
    "addr:postcode":"t0m 0g0",
    "iso:country":"CA",
    "sg:address":"PO Box 66",
    "sg:city":"Beiseker",
    "sg:classifiers":[
        {
            "category":"Building & Trades",
            "subcategory":"Plumbing",
            "type":"Services"
        }
    ],
    "sg:phone":"+1 403 947 2569",
    "sg:postcode":"T0M 0G0",
    "sg:province":"AB",
    "sg:tags":[
        "sheet",
        "work",
        "metal",
        "heating",
        "contractor"
    ],
    "wof:name":"Christianson Sheet Metal & Htg",
    "wof:placetype":"venue"
},
  "geometry": {"coordinates":[-113.522659,51.386929],"type":"Point"}
}