{
  "type": "Feature",
  "properties": {
    "addr:full":"Whitehorse YT Y1A 2B5",
    "addr:postcode":"y1a 2b5",
    "iso:country":"CA",
    "sg:city":"Whitehorse",
    "sg:classifiers":[
        {
            "category":"Government",
            "subcategory":"Office",
            "type":"Public Place"
        }
    ],
    "sg:phone":"+1 867 667 5102",
    "sg:postcode":"Y1A 2B5",
    "sg:province":"YT",
    "wof:name":"Canada Radio Licensing",
    "wof:placetype":"venue"
},
  "geometry": {"coordinates":[-135.05453491200001,60.7193641663],"type":"Point"}
}