{
  "type": "Feature",
  "properties": {
    "addr:full":"895 Av Godin Vanier QC G1M 2X5",
    "addr:postcode":"g1m 2x5",
    "addr:street":"895 Av Godin",
    "iso:country":"CA",
    "sg:address":"895 Av Godin",
    "sg:city":"Vanier",
    "sg:classifiers":[
        {
            "category":"Building & Trades",
            "subcategory":"Plumbing",
            "type":"Services"
        }
    ],
    "sg:phone":"+1 418 687 5410",
    "sg:postcode":"G1M 2X5",
    "sg:province":"QC",
    "sg:tags":[
        "conditioning",
        "air",
        "system",
        "contractor"
    ],
    "wof:name":"Labil Inc",
    "wof:placetype":"venue"
},
  "geometry": {"coordinates":[-71.280838,46.824066],"type":"Point"}
}