{
  "type": "Feature",
  "properties": {
    "addr:full":"1015 Westport Cres Mississauga ON L5T 1E8",
    "addr:housenumber":"1015",
    "addr:postcode":"l5t 1e8",
    "addr:street":"Westport Cres",
    "iso:country":"CA",
    "sg:address":"1015 Westport Cres",
    "sg:city":"Mississauga",
    "sg:classifiers":[
        {
            "category":"Manufacturing",
            "subcategory":"Tools & Machinery",
            "type":"Manufacturing & Wholesale Goods"
        }
    ],
    "sg:phone":"+1 905 564 0960",
    "sg:postcode":"L5T 1E8",
    "sg:province":"ON",
    "sg:tags":[
        "machine",
        "shop"
    ],
    "wof:name":"P W Vickery Ltd",
    "wof:placetype":"venue"
},
  "geometry": {"coordinates":[-79.65967559809999,43.6492614746],"type":"Point"}
}