{
  "type": "Feature",
  "properties": {
    "addr:full":"804 Boul Cure-Labelle Laval QC H7V 2V3",
    "addr:housenumber":"804",
    "addr:postcode":"h7v 2v3",
    "addr:street":"Boul Cure-Labelle",
    "iso:country":"CA",
    "sg:address":"804 Boul Cure-Labelle",
    "sg:city":"Laval",
    "sg:classifiers":[
        {
            "category":"Personal",
            "subcategory":"Tanning Parlor",
            "type":"Services"
        }
    ],
    "sg:phone":"+1 450 681 6666",
    "sg:postcode":"H7V 2V3",
    "sg:province":"QC",
    "sg:tags":[
        "salon"
    ],
    "wof:name":"Bronzes Les Bronzes Illimites",
    "wof:placetype":"venue"
},
  "geometry": {"coordinates":[-73.7474975586,45.5397872925],"type":"Point"}
}