{
  "type": "Feature",
  "properties": {
    "addr:full":"5002 55 Ave Bonnyville AB T9N 2K6",
    "addr:housenumber":"5002",
    "addr:postcode":"t9n 2k6",
    "addr:street":"55 Ave",
    "iso:country":"CA",
    "sg:address":"5002 55 Ave",
    "sg:city":"Bonnyville",
    "sg:classifiers":[
        {
            "category":"Building & Trades",
            "subcategory":"Construction",
            "type":"Services"
        }
    ],
    "sg:phone":"+1 780 826 4737",
    "sg:postcode":"T9N 2K6",
    "sg:province":"AB",
    "sg:tags":[
        "insulation",
        "heat",
        "contractor"
    ],
    "wof:name":"Albrico Services Ltd",
    "wof:placetype":"venue"
},
  "geometry": {"coordinates":[-110.74194300000001,54.273483],"type":"Point"}
}