{
  "type": "Feature",
  "properties": {
    "addr:full":"828 Rue Jean-Talon O Montreal QC H3N 1S4",
    "addr:housenumber":"828",
    "addr:postcode":"h3n 1s4",
    "addr:street":"Rue Jean-Talon O",
    "iso:country":"CA",
    "sg:address":"828 Rue Jean-Talon O",
    "sg:city":"Montreal",
    "sg:classifiers":[
        {
            "category":"Shopping",
            "subcategory":"Crafts & Fabrics",
            "type":"Retail Goods"
        }
    ],
    "sg:phone":"+1 514 276 1325",
    "sg:postcode":"H3N 1S4",
    "sg:province":"QC",
    "sg:tags":[
        "shop",
        "jeweler"
    ],
    "wof:name":"Sana Boutique",
    "wof:placetype":"venue"
},
  "geometry": {"coordinates":[-73.61293000000001,45.540817],"type":"Point"}
}