{
  "type": "Feature",
  "properties": {
    "addr:full":"689 St Mary's Rd Winnipeg MB R2M 3M8",
    "addr:housenumber":"689",
    "addr:postcode":"r2m 3m8",
    "addr:street":"St Mary'S Rd",
    "iso:country":"CA",
    "sg:address":"689 St Mary's Rd",
    "sg:city":"Winnipeg",
    "sg:classifiers":[
        {
            "category":"Manufacturing",
            "subcategory":"Glass & Minerals",
            "type":"Manufacturing & Wholesale Goods"
        }
    ],
    "sg:phone":"+1 204 253 1609",
    "sg:postcode":"R2M 3M8",
    "sg:province":"MB",
    "sg:tags":[
        "engraver"
    ],
    "wof:name":"Aida Crystal Engraving",
    "wof:placetype":"venue"
},
  "geometry": {"coordinates":[-97.112038,49.857632],"type":"Point"}
}