{
  "type": "Feature",
  "properties": {
    "addr:full":"Scarborough ON M1V 3X6",
    "addr:postcode":"m1v 3x6",
    "iso:country":"CA",
    "sg:city":"Scarborough",
    "sg:classifiers":[
        {
            "category":"Manufacturing",
            "subcategory":"Metals",
            "type":"Manufacturing & Wholesale Goods"
        }
    ],
    "sg:phone":"+1 416 754 3313",
    "sg:postcode":"M1V 3X6",
    "sg:province":"ON",
    "sg:tags":[
        "production",
        "grinding"
    ],
    "wof:name":"Aamax Precision Engineering",
    "wof:placetype":"venue"
},
  "geometry": {"coordinates":[-79.250595,43.82188],"type":"Point"}
}