{
  "type": "Feature",
  "properties": {
    "addr:full":"172 Milner Ave Scarborough ON M1S 3R3",
    "addr:housenumber":"172",
    "addr:postcode":"m1s 3r3",
    "addr:street":"Milner Ave",
    "iso:country":"CA",
    "sg:address":"172 Milner Ave",
    "sg:city":"Scarborough",
    "sg:classifiers":[
        {
            "category":"Manufacturing",
            "subcategory":"Textiles",
            "type":"Manufacturing & Wholesale Goods"
        }
    ],
    "sg:phone":"+1 416 321 1672",
    "sg:postcode":"M1S 3R3",
    "sg:province":"ON",
    "sg:tags":[
        "knitted",
        "fabric"
    ],
    "wof:name":"Koda Knitting Ltd",
    "wof:placetype":"venue"
},
  "geometry": {"coordinates":[-79.2442245483,43.7862548828],"type":"Point"}
}