{
  "type": "Feature",
  "properties": {
    "addr:full":"PO Box 299 Atlin BC V0W 1A0",
    "addr:housenumber":"po",
    "addr:postcode":"v0w 1a0",
    "addr:street":"Box 299",
    "iso:country":"CA",
    "sg:address":"PO Box 299",
    "sg:city":"Atlin",
    "sg:classifiers":[
        {
            "category":"Building & Trades",
            "subcategory":"Equipment Rental",
            "type":"Services"
        }
    ],
    "sg:phone":"+1 250 651 7716",
    "sg:postcode":"V0W 1A0",
    "sg:province":"BC",
    "sg:tags":[
        "aircraft",
        "leasing",
        "charter"
    ],
    "wof:name":"Osprey Air",
    "wof:placetype":"venue"
},
  "geometry": {"coordinates":[-133.70311000000001,59.575008],"type":"Point"}
}