{
  "type": "Feature",
  "properties": {
    "addr:full":"830 Campbell Ave Ottawa ON K2A 2C2",
    "addr:housenumber":"830",
    "addr:postcode":"k2a 2c2",
    "addr:street":"Campbell Ave",
    "iso:country":"CA",
    "sg:address":"830 Campbell Ave",
    "sg:city":"Ottawa",
    "sg:phone":"+1 613 820 0139",
    "sg:postcode":"K2A 2C2",
    "sg:province":"ON",
    "sg:tags":[
        "equipment",
        "supply"
    ],
    "wof:name":"Mcl Hospitality Ltd",
    "wof:placetype":"venue"
},
  "geometry": {"coordinates":[-75.750221,45.376785],"type":"Point"}
}