{
  "type": "Feature",
  "properties": {
    "addr:full":"1898 Boul Thimens Saint-Laurent QC H4R 2K2",
    "addr:housenumber":"1898",
    "addr:postcode":"h4r 2k2",
    "addr:street":"Boul Thimens",
    "iso:country":"CA",
    "sg:address":"1898 Boul Thimens",
    "sg:city":"Saint-Laurent",
    "sg:classifiers":[
        {
            "category":"Restaurant",
            "type":"Food & Drink"
        }
    ],
    "sg:phone":"+1 514 337 1999",
    "sg:postcode":"H4R 2K2",
    "sg:province":"QC",
    "wof:name":"Trattoria LA Villetta",
    "wof:placetype":"venue"
},
  "geometry": {"coordinates":[-73.693825,45.512123],"type":"Point"}
}