{
  "type": "Feature",
  "properties": {
    "iso:country":"CA",
    "sg:city":"Dryden",
    "sg:classifiers":[
        {
            "category":"Government",
            "subcategory":"Office",
            "type":"Public Place"
        }
    ],
    "sg:phone":"+1 807 223 2331",
    "sg:postcode":"P8N 1E6",
    "sg:province":"ON",
    "wof:name":"Canada Human Resource Ctr",
    "wof:placetype":"venue"
},
  "geometry": {"coordinates":[-92.8390655518,49.7821884155],"type":"Point"}
}