{
  "type": "Feature",
  "properties": {
    "addr:full":"2170 4th Ave Jordan Station ON L0R 1S0",
    "addr:housenumber":"2170",
    "addr:postcode":"l0r 1s0",
    "addr:street":"4Th Ave Jordan",
    "iso:country":"CA",
    "sg:address":"2170 4th Ave",
    "sg:city":"Jordan Station",
    "sg:classifiers":[
        {
            "category":"Manufacturing",
            "subcategory":"Food",
            "type":"Manufacturing & Wholesale Goods"
        }
    ],
    "sg:phone":"+1 905 562 0035",
    "sg:postcode":"L0R 1S0",
    "sg:province":"ON",
    "sg:tags":[
        "winery"
    ],
    "wof:name":"Creekside Estate Winery",
    "wof:placetype":"venue"
},
  "geometry": {"coordinates":[-79.349281311,43.1529884338],"type":"Point"}
}