{
  "type": "Feature",
  "properties": {
    "iso:country":"CA",
    "sg:city":"Delta",
    "sg:classifiers":[
        {
            "category":"Building & Trades",
            "subcategory":"Construction",
            "type":"Services"
        }
    ],
    "sg:phone":"+1 604 940 4244",
    "sg:postcode":"V4G 1H9",
    "sg:province":"BC",
    "sg:tags":[
        "general",
        "contractor"
    ],
    "wof:name":"Mar-Will Construction Ltd",
    "wof:placetype":"venue"
},
  "geometry": {"coordinates":[-123.025093079,49.1364555359],"type":"Point"}
}