{
  "type": "Feature",
  "properties": {
    "addr:full":"5330 Boul Decarie Montreal QC H3X 2J1",
    "addr:housenumber":"5330",
    "addr:postcode":"h3x 2j1",
    "addr:street":"Boul Decarie",
    "iso:country":"CA",
    "sg:address":"5330 Boul Decarie",
    "sg:city":"Montreal",
    "sg:classifiers":[
        {
            "category":"Autos & Motor Vehicles",
            "subcategory":"Fuel & Gas Station",
            "type":"Retail Goods"
        }
    ],
    "sg:phone":"+1 514 369 6164",
    "sg:postcode":"H3X 2J1",
    "sg:province":"QC",
    "sg:tags":[
        "oil"
    ],
    "wof:name":"Shell Canada Ltd",
    "wof:placetype":"venue"
},
  "geometry": {"coordinates":[-73.6332778931,45.4851036072],"type":"Point"}
}