{
  "type": "Feature",
  "properties": {
    "iso:country":"CA",
    "sg:address":"949 2nd Ave E",
    "sg:city":"Owen Sound",
    "sg:classifiers":[
        {
            "category":"Real Estate",
            "subcategory":"Real Estate Agent",
            "type":"Services"
        }
    ],
    "sg:phone":"+1 519 376 5818",
    "sg:postcode":"N4K 2H5",
    "sg:province":"ON",
    "wof:name":"B Gorbet & Sons Ltd",
    "wof:placetype":"venue"
},
  "geometry": {"coordinates":[-80.9428482056,44.5667762756],"type":"Point"}
}