{
  "type": "Feature",
  "properties": {
    "addr:full":"109 Vaughan Rd York ON M6C 2L9",
    "addr:housenumber":"109",
    "addr:postcode":"m6c 2l9",
    "addr:street":"Vaughan Rd",
    "iso:country":"CA",
    "sg:address":"109 Vaughan Rd",
    "sg:city":"York",
    "sg:classifiers":[
        {
            "category":"Manufacturing",
            "subcategory":"Jewelry",
            "type":"Manufacturing & Wholesale Goods"
        }
    ],
    "sg:phone":"+1 416 657 8654",
    "sg:postcode":"M6C 2L9",
    "sg:province":"ON",
    "sg:tags":[
        "jeweler"
    ],
    "wof:name":"Raven's Hoard Studio",
    "wof:placetype":"venue"
},
  "geometry": {"coordinates":[-79.42106628419999,43.6840667725],"type":"Point"}
}