{
  "type": "Feature",
  "properties": {
    "addr:full":"4 Place Du Commerce # 210 Verdun QC H3E 1J4",
    "addr:housenumber":"4",
    "addr:postcode":"h3e 1j4",
    "addr:street":"Place Du Commerce # 210",
    "iso:country":"CA",
    "sg:address":"4 Place Du Commerce # 210",
    "sg:city":"Verdun",
    "sg:classifiers":[
        {
            "category":"Insurance",
            "subcategory":"Insurance Agent",
            "type":"Services"
        }
    ],
    "sg:phone":"+1 514 769 4643",
    "sg:postcode":"H3E 1J4",
    "sg:province":"QC",
    "sg:tags":[
        "consultant"
    ],
    "wof:name":"M Bacal Insurance",
    "wof:placetype":"venue"
},
  "geometry": {"coordinates":[-73.571762085,45.4590187073],"type":"Point"}
}