{
  "type": "Feature",
  "properties": {
    "addr:full":"Dublin ON N0K 1E0",
    "addr:postcode":"n0k 1e0",
    "iso:country":"CA",
    "sg:city":"Dublin",
    "sg:classifiers":[
        {
            "category":"Organizations",
            "subcategory":"Professional Association",
            "type":"Services"
        }
    ],
    "sg:phone":"+1 519 345 2222",
    "sg:postcode":"N0K 1E0",
    "sg:province":"ON",
    "wof:name":"Dublin & District Athletic",
    "wof:placetype":"venue"
},
  "geometry": {"coordinates":[-81.28370700000001,43.505821],"type":"Point"}
}