{
  "type": "Feature",
  "properties": {
    "addr:full":"25 Jarvis St Cambridge ON N1R 1G7",
    "addr:housenumber":"25",
    "addr:postcode":"n1r 1g7",
    "addr:street":"Jarvis St",
    "iso:country":"CA",
    "sg:address":"25 Jarvis St",
    "sg:city":"Cambridge",
    "sg:classifiers":[
        {
            "category":"Building & Trades",
            "subcategory":"Electrical",
            "type":"Services"
        }
    ],
    "sg:phone":"+1 519 623 1934",
    "sg:postcode":"N1R 1G7",
    "sg:province":"ON",
    "sg:tags":[
        "electric",
        "contractor"
    ],
    "wof:name":"Jamieson Whetham Electric Inc",
    "wof:placetype":"venue"
},
  "geometry": {"coordinates":[-80.315437,43.372551],"type":"Point"}
}