{
  "type": "Feature",
  "properties": {
    "iso:country":"CA",
    "sg:city":"Lloydminster",
    "sg:classifiers":[
        {
            "category":"Wholesale",
            "subcategory":"Machinery & Supplies",
            "type":"Manufacturing & Wholesale Goods"
        }
    ],
    "sg:phone":"+1 780 875 8864",
    "sg:postcode":"T9V 2E6",
    "sg:province":"AB",
    "sg:tags":[
        "bearing"
    ],
    "wof:name":"Bearing & Transmission Ltd",
    "wof:placetype":"venue"
},
  "geometry": {"coordinates":[-110.010002136,53.3018112183],"type":"Point"}
}