{
  "type": "Feature",
  "properties": {
    "addr:full":"360 Booth St Ottawa ON K1R 7K4",
    "addr:housenumber":"360",
    "addr:postcode":"k1r 7k4",
    "addr:street":"Booth St",
    "iso:country":"CA",
    "sg:address":"360 Booth St",
    "sg:city":"Ottawa",
    "sg:classifiers":[
        {
            "category":"Travel",
            "subcategory":"Travel Agent",
            "type":"Entertainment"
        }
    ],
    "sg:phone":"+1 613 594 8832",
    "sg:postcode":"K1R 7K4",
    "sg:province":"ON",
    "sg:tags":[
        "agency",
        "bureau"
    ],
    "wof:name":"Cindy Travel Agency Ltd",
    "wof:placetype":"venue"
},
  "geometry": {"coordinates":[-75.709473,45.40733],"type":"Point"}
}