{
  "type": "Feature",
  "properties": {
    "addr:full":"2900 111 Rte E Amos QC J9T 3A1",
    "addr:housenumber":"2900",
    "addr:postcode":"j9t 3a1",
    "addr:street":"111 Rte E Amos",
    "iso:country":"CA",
    "sg:address":"2900 111 Rte E",
    "sg:city":"Amos",
    "sg:classifiers":[
        {
            "category":"Restaurant",
            "type":"Food & Drink"
        }
    ],
    "sg:phone":"+1 819 732 3121",
    "sg:postcode":"J9T 3A1",
    "sg:province":"QC",
    "wof:name":"Restaurant Pacini",
    "wof:placetype":"venue"
},
  "geometry": {"coordinates":[-78.1064834595,48.5637702942],"type":"Point"}
}