{
  "type": "Feature",
  "properties": {
    "addr:full":"1399 Ellsworth Lane Greely ON K4P 1N3",
    "addr:housenumber":"1399",
    "addr:postcode":"k4p 1n3",
    "addr:street":"Ellsworth Lane",
    "iso:country":"CA",
    "sg:address":"1399 Ellsworth Lane",
    "sg:city":"Greely",
    "sg:classifiers":[
        {
            "category":"Health Services",
            "subcategory":"Doctor",
            "type":"Services"
        }
    ],
    "sg:phone":"+1 613 821 3428",
    "sg:postcode":"K4P 1N3",
    "sg:province":"ON",
    "sg:tags":[
        "physician",
        "surgeon"
    ],
    "wof:name":"Greely Family Medical Ctr",
    "wof:placetype":"venue"
},
  "geometry": {"coordinates":[-75.560287,45.264259],"type":"Point"}
}