{
  "type": "Feature",
  "properties": {
    "addr:full":"Morris MB R0G 1K0",
    "addr:postcode":"r0g 1k0",
    "iso:country":"CA",
    "sg:city":"Morris",
    "sg:classifiers":[
        {
            "category":"Freight",
            "type":"Transportation"
        }
    ],
    "sg:phone":"+1 204 746 8702",
    "sg:postcode":"R0G 1K0",
    "sg:province":"MB",
    "sg:tags":[
        "trucking"
    ],
    "wof:name":"P K Friesen Trucking Ltd",
    "wof:placetype":"venue"
},
  "geometry": {"coordinates":[-97.36604309080001,49.3546867371],"type":"Point"}
}