{
  "type": "Feature",
  "properties": {
    "addr:full":"Burnaby BC V5C 3Z6",
    "addr:postcode":"v5c 3z6",
    "iso:country":"CA",
    "sg:city":"Burnaby",
    "sg:classifiers":[
        {
            "category":"Shopping",
            "subcategory":"Jewelry",
            "type":"Retail Goods"
        }
    ],
    "sg:phone":"+1 604 299 1552",
    "sg:postcode":"V5C 3Z6",
    "sg:province":"BC",
    "sg:tags":[
        "jeweler"
    ],
    "wof:name":"Lexia Jewellers Ltd",
    "wof:placetype":"venue"
},
  "geometry": {"coordinates":[-123.001693726,49.2666282654],"type":"Point"}
}