{
  "type": "Feature",
  "properties": {
    "iso:country":"CA",
    "sg:city":"St Catharines",
    "sg:classifiers":[
        {
            "category":"Social Services",
            "type":"Services"
        }
    ],
    "sg:phone":"+1 905 684 6918",
    "sg:postcode":"L2T 3B2",
    "sg:province":"ON",
    "sg:tags":[
        "organization",
        "welfare"
    ],
    "wof:name":"Bethesda Programs",
    "wof:placetype":"venue"
},
  "geometry": {"coordinates":[-79.2240524292,43.1327133179],"type":"Point"}
}