{
  "type": "Feature",
  "properties": {
    "addr:full":"3535 New St Burlington ON L7N 3W2",
    "addr:housenumber":"3535",
    "addr:postcode":"l7n 3w2",
    "addr:street":"New St",
    "iso:country":"CA",
    "sg:address":"3535 New St",
    "sg:city":"Burlington",
    "sg:classifiers":[
        {
            "category":"Banks & Credit Unions",
            "subcategory":"Bank",
            "type":"Services"
        }
    ],
    "sg:phone":"+1 905 637 2333",
    "sg:postcode":"L7N 3W2",
    "sg:province":"ON",
    "sg:tags":[
        "company",
        "trust",
        "investment"
    ],
    "wof:name":"Royal Trust",
    "wof:placetype":"venue"
},
  "geometry": {"coordinates":[-79.770332,43.35231],"type":"Point"}
}