{
  "type": "Feature",
  "properties": {
    "addr:full":"642 Government Ave Winnipeg MB R2K 1X2",
    "addr:housenumber":"642",
    "addr:postcode":"r2k 1x2",
    "addr:street":"Government Ave",
    "iso:country":"CA",
    "sg:address":"642 Government Ave",
    "sg:city":"Winnipeg",
    "sg:classifiers":[
        {
            "category":"Organizations",
            "subcategory":"Professional Association",
            "type":"Services"
        }
    ],
    "sg:phone":"+1 204 667 0406",
    "sg:postcode":"R2K 1X2",
    "sg:province":"MB",
    "wof:name":"St Andrew's Society-Winnipeg",
    "wof:placetype":"venue"
},
  "geometry": {"coordinates":[-97.08566999999999,49.915188],"type":"Point"}
}