{
  "type": "Feature",
  "properties": {
    "addr:full":"313 Horner Ave Etobicoke ON M8W 1Z5",
    "addr:housenumber":"313",
    "addr:postcode":"m8w 1z5",
    "addr:street":"Horner Ave",
    "iso:country":"CA",
    "sg:address":"313 Horner Ave",
    "sg:city":"Etobicoke",
    "sg:classifiers":[
        {
            "category":"Building & Trades",
            "subcategory":"Construction",
            "type":"Services"
        }
    ],
    "sg:phone":"+1 416 252 2226",
    "sg:postcode":"M8W 1Z5",
    "sg:province":"ON",
    "sg:tags":[
        "contractor"
    ],
    "wof:name":"Horner Development Ltd",
    "wof:placetype":"venue"
},
  "geometry": {"coordinates":[-79.52713799999999,43.605602],"type":"Point"}
}