{
  "type": "Feature",
  "properties": {
    "addr:full":"3645 Kingsway Vancouver BC V5R 5M1",
    "addr:housenumber":"3645",
    "addr:postcode":"v5r 5m1",
    "addr:street":"Kingsway",
    "iso:country":"CA",
    "sg:address":"3645 Kingsway",
    "sg:city":"Vancouver",
    "sg:classifiers":[
        {
            "category":"Shopping",
            "subcategory":"Bicycles & Sporting Goods",
            "type":"Retail Goods"
        }
    ],
    "sg:phone":"+1 604 431 5504",
    "sg:postcode":"V5R 5M1",
    "sg:province":"BC",
    "wof:name":"Soccer Cents",
    "wof:placetype":"venue"
},
  "geometry": {"coordinates":[-123.02497863799999,49.2323226929],"type":"Point"}
}