{
  "type": "Feature",
  "properties": {
    "addr:full":"2946 Eglinton Ave E Scarborough ON M1J 2E7",
    "addr:housenumber":"2946",
    "addr:postcode":"m1j 2e7",
    "addr:street":"Eglinton Ave E",
    "iso:country":"CA",
    "sg:address":"2946 Eglinton Ave E",
    "sg:city":"Scarborough",
    "sg:classifiers":[
        {
            "category":"Retail",
            "subcategory":"Auto Repair",
            "type":"Services"
        }
    ],
    "sg:phone":"+1 416 289 4248",
    "sg:postcode":"M1J 2E7",
    "sg:province":"ON",
    "sg:tags":[
        "repairing",
        "automobile"
    ],
    "wof:name":"City Auto Repair",
    "wof:placetype":"venue"
},
  "geometry": {"coordinates":[-79.234734,43.739826],"type":"Point"}
}