{
  "type": "Feature",
  "properties": {
    "iso:country":"CA",
    "sg:address":"116 Roseberry St",
    "sg:city":"Campbellton",
    "sg:classifiers":[
        {
            "category":"Banks & Credit Unions",
            "subcategory":"Bank",
            "type":"Services"
        }
    ],
    "sg:phone":"+1 506 753 7691",
    "sg:postcode":"E3N 2G9",
    "sg:province":"NB",
    "wof:name":"Banque Nationale Du Canada",
    "wof:placetype":"venue"
},
  "geometry": {"coordinates":[-66.6805114746,48.0037612915],"type":"Point"}
}