{
  "type": "Feature",
  "properties": {
    "addr:full":"394 Rothesay Ave Saint John NB E2J 2C4",
    "addr:housenumber":"394",
    "addr:postcode":"e2j 2c4",
    "addr:street":"Rothesay Ave",
    "iso:country":"CA",
    "sg:address":"394 Rothesay Ave",
    "sg:city":"Saint John",
    "sg:classifiers":[
        {
            "category":"Autos & Motor Vehicles",
            "subcategory":"Motorcycle Sales",
            "type":"Retail Goods"
        }
    ],
    "sg:phone":"+1 506 693 3000",
    "sg:postcode":"E2J 2C4",
    "sg:province":"NB",
    "sg:tags":[
        "scooter"
    ],
    "wof:name":"Sparky's Small Engine Repairs",
    "wof:placetype":"venue"
},
  "geometry": {"coordinates":[-66.036629,45.30064],"type":"Point"}
}