{
  "type": "Feature",
  "properties": {
    "iso:country":"CA",
    "sg:address":"552 Marsh Rd",
    "sg:city":"Thorburn",
    "sg:classifiers":[
        {
            "category":"Retail",
            "subcategory":"Repair Shop",
            "type":"Services"
        }
    ],
    "sg:phone":"+1 902 922 2844",
    "sg:postcode":"B0K 1W0",
    "sg:province":"NS",
    "sg:tags":[
        "appliance"
    ],
    "wof:name":"Pictou County Home Appliance",
    "wof:placetype":"venue"
},
  "geometry": {"coordinates":[-62.5550727844,45.5617980957],"type":"Point"}
}