{
  "type": "Feature",
  "properties": {
    "iso:country":"CA",
    "sg:address":"4479 Kingston Rd",
    "sg:city":"Scarborough",
    "sg:classifiers":[
        {
            "category":"Food & Beverages",
            "subcategory":"Bakery",
            "type":"Retail Goods"
        }
    ],
    "sg:phone":"+1 416 284 5163",
    "sg:postcode":"M1E 2N7",
    "sg:province":"ON",
    "sg:tags":[
        "tea",
        "coffee",
        "doughnut"
    ],
    "wof:name":"Tim Horton's",
    "wof:placetype":"venue"
},
  "geometry": {"coordinates":[-79.1873626709,43.7697753906],"type":"Point"}
}