{
  "type": "Feature",
  "properties": {
    "addr:full":"432 Country Squire Rd Waterloo ON N2J 4G8",
    "addr:housenumber":"432",
    "addr:postcode":"n2j 4g8",
    "addr:street":"Country Squire Rd",
    "iso:country":"CA",
    "sg:address":"432 Country Squire Rd",
    "sg:city":"Waterloo",
    "sg:classifiers":[
        {
            "category":"Professional",
            "subcategory":"Business Services",
            "type":"Services"
        }
    ],
    "sg:phone":"+1 519 886 5071",
    "sg:postcode":"N2J 4G8",
    "sg:province":"ON",
    "sg:tags":[
        "inspection"
    ],
    "wof:name":"Materials Research Institute",
    "wof:placetype":"venue"
},
  "geometry": {"coordinates":[-80.47998,43.523811],"type":"Point"}
}