{
  "type": "Feature",
  "properties": {
    "addr:full":"144 Thames St S Ingersoll ON N5C 2T4",
    "addr:housenumber":"144",
    "addr:postcode":"n5c 2t4",
    "addr:street":"Thames St S",
    "iso:country":"CA",
    "sg:address":"144 Thames St S",
    "sg:city":"Ingersoll",
    "sg:classifiers":[
        {
            "category":"Restaurant",
            "type":"Food & Drink"
        }
    ],
    "sg:phone":"+1 519 485 0111",
    "sg:postcode":"N5C 2T4",
    "sg:province":"ON",
    "wof:name":"Diana Family Restaurant",
    "wof:placetype":"venue"
},
  "geometry": {"coordinates":[-80.882828,43.038166],"type":"Point"}
}