{
  "type": "Feature",
  "properties": {
    "addr:full":"945 Gardiners Rd Kingston ON K7M 7H4",
    "addr:housenumber":"945",
    "addr:postcode":"k7m 7h4",
    "addr:street":"Gardiners Rd",
    "iso:country":"CA",
    "sg:address":"945 Gardiners Rd",
    "sg:city":"Kingston",
    "sg:classifiers":[
        {
            "category":"Shopping",
            "subcategory":"Optical Goods",
            "type":"Retail Goods"
        }
    ],
    "sg:phone":"+1 613 384 0743",
    "sg:postcode":"K7M 7H4",
    "sg:province":"ON",
    "sg:tags":[
        "laboratory"
    ],
    "wof:name":"Lenscrafters",
    "wof:placetype":"venue"
},
  "geometry": {"coordinates":[-76.5689163208,44.2562675476],"type":"Point"}
}