{
  "type": "Feature",
  "properties": {
    "iso:country":"CA",
    "sg:address":"2715 Bernard Rd",
    "sg:city":"Windsor",
    "sg:classifiers":[
        {
            "category":"Organizations",
            "subcategory":"Religious Organization",
            "type":"Services"
        }
    ],
    "sg:phone":"+1 519 974 9300",
    "sg:postcode":"N8W 4S5",
    "sg:province":"ON",
    "sg:tags":[
        "church"
    ],
    "wof:name":"Windsor Evangel Bible Church",
    "wof:placetype":"venue"
},
  "geometry": {"coordinates":[-82.96687316889999,42.2981071472],"type":"Point"}
}