{
  "type": "Feature",
  "properties": {
    "addr:full":"990 343 Rte Saint-Ambroise-DE-Kildare QC J0K 1C0",
    "addr:housenumber":"343",
    "addr:postcode":"j0k 1c0",
    "addr:street":"Rte Saint-Ambroise-De-Kildare",
    "iso:country":"CA",
    "sg:address":"990 343 Rte",
    "sg:city":"Saint-Ambroise-DE-Kildare",
    "sg:classifiers":[
        {
            "category":"Food & Beverages",
            "subcategory":"Groceries & Convenience Stores",
            "type":"Retail Goods"
        }
    ],
    "sg:phone":"+1 450 755 3949",
    "sg:postcode":"J0K 1C0",
    "sg:province":"QC",
    "wof:name":"Depanneur Rsv Enr",
    "wof:placetype":"venue"
},
  "geometry": {"coordinates":[-73.55163574220001,46.0781402588],"type":"Point"}
}