{
  "type": "Feature",
  "properties": {
    "addr:full":"124 Pleasant Dr Minto NB E4B 2S8",
    "addr:housenumber":"124",
    "addr:postcode":"e4b 2s8",
    "addr:street":"Pleasant Dr",
    "iso:country":"CA",
    "sg:address":"124 Pleasant Dr",
    "sg:city":"Minto",
    "sg:classifiers":[
        {
            "category":"Organizations",
            "subcategory":"Religious Organization",
            "type":"Services"
        }
    ],
    "sg:phone":"+1 506 327 6306",
    "sg:postcode":"E4B 2S8",
    "sg:province":"NB",
    "sg:tags":[
        "church"
    ],
    "wof:name":"United Baptist Church of Minto",
    "wof:placetype":"venue"
},
  "geometry": {"coordinates":[-66.07936100000001,46.064659],"type":"Point"}
}