{
  "type": "Feature",
  "properties": {
    "addr:full":"939 Prospect St Fredericton NB E3B 2T7",
    "addr:housenumber":"939",
    "addr:postcode":"e3b 2t7",
    "addr:street":"Prospect St",
    "iso:country":"CA",
    "sg:address":"939 Prospect St",
    "sg:city":"Fredericton",
    "sg:classifiers":[
        {
            "category":"Retail",
            "subcategory":"Self-service Laundry",
            "type":"Services"
        }
    ],
    "sg:phone":"+1 506 459 8018",
    "sg:postcode":"E3B 2T7",
    "sg:province":"NB",
    "wof:name":"Rainbow Car Wash",
    "wof:placetype":"venue"
},
  "geometry": {"coordinates":[-66.67248499999999,45.943855],"type":"Point"}
}