{
  "type": "Feature",
  "properties": {
    "iso:country":"CA",
    "sg:address":"4360 Bennett Rd",
    "sg:city":"Burlington",
    "sg:classifiers":[
        {
            "category":"Professional",
            "subcategory":"Computer Services",
            "type":"Services"
        }
    ],
    "sg:phone":"+1 905 631 9123",
    "sg:postcode":"L7L 1Y6",
    "sg:province":"ON",
    "sg:tags":[
        "consultant"
    ],
    "wof:name":"Straylight Digital Inc",
    "wof:placetype":"venue"
},
  "geometry": {"coordinates":[-79.763184,43.366573],"type":"Point"}
}