{
  "type": "Feature",
  "properties": {
    "iso:country":"CA",
    "sg:address":"201 Barclay Parade SW",
    "sg:city":"Calgary",
    "sg:classifiers":[
        {
            "category":"Bars & Pubs",
            "type":"Food & Drink"
        }
    ],
    "sg:phone":"+1 403 290 1500",
    "sg:postcode":"T2P 4R3",
    "sg:province":"AB",
    "wof:name":"Barley Mill Eatery & Pub",
    "wof:placetype":"venue"
},
  "geometry": {"coordinates":[-114.069480896,51.0527992249],"type":"Point"}
}