{
  "type": "Feature",
  "properties": {
    "iso:country":"CA",
    "sg:city":"Vancouver",
    "sg:classifiers":[
        {
            "category":"Professional",
            "subcategory":"Business Services",
            "type":"Services"
        }
    ],
    "sg:phone":"+1 604 736 2803",
    "sg:postcode":"V6J 1N3",
    "sg:province":"BC",
    "sg:tags":[
        "plant",
        "design",
        "maintenance"
    ],
    "wof:name":"Joy of Plants Inc",
    "wof:placetype":"venue"
},
  "geometry": {"coordinates":[-123.151809692,49.268283844],"type":"Point"}
}