{
  "type": "Feature",
  "properties": {
    "addr:full":"3834 Morosoff Rd Quesnel BC V2J 6S7",
    "addr:housenumber":"3834",
    "addr:postcode":"v2j 6s7",
    "addr:street":"Morosoff Rd",
    "iso:country":"CA",
    "sg:address":"3834 Morosoff Rd",
    "sg:city":"Quesnel",
    "sg:classifiers":[
        {
            "category":"Manufacturing",
            "subcategory":"Tools & Machinery",
            "type":"Manufacturing & Wholesale Goods"
        }
    ],
    "sg:phone":"+1 250 992 6583",
    "sg:postcode":"V2J 6S7",
    "sg:province":"BC",
    "sg:tags":[
        "machine",
        "shop"
    ],
    "wof:name":"Lebrun Repair Ltd",
    "wof:placetype":"venue"
},
  "geometry": {"coordinates":[-122.498245239,52.9781188965],"type":"Point"}
}