{
  "type": "Feature",
  "properties": {
    "iso:country":"CA",
    "sg:address":"2075 Boul Saint-Laurent",
    "sg:city":"Montreal",
    "sg:classifiers":[
        {
            "category":"Shopping",
            "subcategory":"Clothing, Apparel, & Fashions",
            "type":"Retail Goods"
        }
    ],
    "sg:phone":"+1 514 288 6444",
    "sg:postcode":"H2X 2T3",
    "sg:province":"QC",
    "sg:tags":[
        "item",
        "boutique"
    ],
    "wof:name":"Body-Con",
    "wof:placetype":"venue"
},
  "geometry": {"coordinates":[-73.567787,45.511925],"type":"Point"}
}