{
  "type": "Feature",
  "properties": {
    "addr:full":"Saint-Ferdinand QC G0N 1N0",
    "addr:postcode":"g0n 1n0",
    "iso:country":"CA",
    "sg:city":"Saint-Ferdinand",
    "sg:classifiers":[
        {
            "category":"Retail",
            "subcategory":"Auto Repair",
            "type":"Services"
        }
    ],
    "sg:phone":"+1 418 428 3428",
    "sg:postcode":"G0N 1N0",
    "sg:province":"QC",
    "sg:tags":[
        "body",
        "automobile",
        "painting"
    ],
    "wof:name":"Ami DE LA Carrosserie Inc",
    "wof:placetype":"venue"
},
  "geometry": {"coordinates":[-71.5881271362,46.1357955933],"type":"Point"}
}