{
  "type": "Feature",
  "properties": {
    "addr:full":"96 Rue Des Bordages Varennes QC J3X 2A7",
    "addr:housenumber":"96",
    "addr:postcode":"j3x 2a7",
    "addr:street":"Rue Des Bordages",
    "iso:country":"CA",
    "sg:address":"96 Rue Des Bordages",
    "sg:city":"Varennes",
    "sg:classifiers":[
        {
            "category":"Professional",
            "subcategory":"Business Services",
            "type":"Services"
        }
    ],
    "sg:phone":"+1 450 652 0918",
    "sg:postcode":"J3X 2A7",
    "sg:province":"QC",
    "sg:tags":[
        "convention",
        "meeting",
        "facility"
    ],
    "wof:name":"Pluri Congres Inc",
    "wof:placetype":"venue"
},
  "geometry": {"coordinates":[-73.435394,45.665749],"type":"Point"}
}