{
  "type": "Feature",
  "properties": {
    "iso:country":"CA",
    "sg:address":"1883 Rang 10-1",
    "sg:city":"Val-Paradis",
    "sg:classifiers":[
        {
            "category":"Food & Beverages",
            "subcategory":"Groceries & Convenience Stores",
            "type":"Retail Goods"
        }
    ],
    "sg:phone":"+1 819 941 2604",
    "sg:postcode":"J0Z 3S0",
    "sg:province":"QC",
    "sg:tags":[
        "grocer"
    ],
    "wof:name":"Epicerie Gmc",
    "wof:placetype":"venue"
},
  "geometry": {"coordinates":[-79.2961730957,49.1539764404],"type":"Point"}
}