{
  "type": "Feature",
  "properties": {
    "addr:full":"Whitby ON L1N 2C1",
    "addr:postcode":"l1n 2c1",
    "iso:country":"CA",
    "sg:city":"Whitby",
    "sg:classifiers":[
        {
            "category":"Retail",
            "subcategory":"Car Wash",
            "type":"Services"
        }
    ],
    "sg:phone":"+1 905 665 6753",
    "sg:postcode":"L1N 2C1",
    "sg:province":"ON",
    "sg:tags":[
        "polishing",
        "automobile",
        "rustproofing",
        "washing",
        "undercoating"
    ],
    "wof:name":"Krown Body Maintenance Program",
    "wof:placetype":"venue"
},
  "geometry": {"coordinates":[-78.9203796387,43.8796653748],"type":"Point"}
}