{
  "type": "Feature",
  "properties": {
    "addr:full":"Regina SK S4N 5X2",
    "addr:postcode":"s4n 5x2",
    "iso:country":"CA",
    "sg:city":"Regina",
    "sg:classifiers":[
        {
            "category":"Building & Trades",
            "subcategory":"Electrical",
            "type":"Services"
        }
    ],
    "sg:phone":"+1 306 721 6484",
    "sg:postcode":"S4N 5X2",
    "sg:province":"SK",
    "sg:tags":[
        "electric",
        "contractor"
    ],
    "wof:name":"Alliance Energy Ltd",
    "wof:placetype":"venue"
},
  "geometry": {"coordinates":[-104.56751251199999,50.4696159363],"type":"Point"}
}