{
  "type": "Feature",
  "properties": {
    "iso:country":"CA",
    "sg:address":"78 Admiral Rd",
    "sg:city":"Toronto",
    "sg:classifiers":[
        {
            "category":"Social Services",
            "type":"Services"
        }
    ],
    "sg:phone":"+1 416 921 0953",
    "sg:postcode":"M5R 2L6",
    "sg:province":"ON",
    "sg:tags":[
        "organization",
        "welfare"
    ],
    "wof:name":"Salvation Army Homestead",
    "wof:placetype":"venue"
},
  "geometry": {"coordinates":[-79.40130615229999,43.6734580994],"type":"Point"}
}