{
  "type": "Feature",
  "properties": {
    "addr:full":"7 Pinsent Dr Grand Falls-Windsor NL A2A 2S8",
    "addr:housenumber":"7",
    "addr:postcode":"a2a 2s8",
    "addr:street":"Pinsent Dr",
    "iso:country":"CA",
    "sg:address":"7 Pinsent Dr",
    "sg:city":"Grand Falls-Windsor",
    "sg:classifiers":[
        {
            "category":"Health Services",
            "subcategory":"Doctor",
            "type":"Services"
        }
    ],
    "sg:phone":"+1 709 489 3141",
    "sg:postcode":"A2A 2S8",
    "sg:province":"NL",
    "sg:tags":[
        "physician",
        "surgeon"
    ],
    "wof:name":"Cohen, Mike MD",
    "wof:placetype":"venue"
},
  "geometry": {"coordinates":[-55.653046,48.945778],"type":"Point"}
}