{
  "type": "Feature",
  "properties": {
    "iso:country":"CA",
    "sg:city":"Mississauga",
    "sg:classifiers":[
        {
            "category":"Wholesale",
            "subcategory":"Home Furnishings",
            "type":"Manufacturing & Wholesale Goods"
        }
    ],
    "sg:phone":"+1 905 671 0097",
    "sg:postcode":"L4V 1E8",
    "sg:province":"ON",
    "sg:tags":[
        "rug",
        "carpet"
    ],
    "wof:name":"Minster Interiors Inc",
    "wof:placetype":"venue"
},
  "geometry": {"coordinates":[-79.638062,43.700108],"type":"Point"}
}