{
  "type": "Feature",
  "properties": {
    "addr:full":"Quesnel BC V2J 3K2",
    "addr:postcode":"v2j 3k2",
    "iso:country":"CA",
    "sg:city":"Quesnel",
    "sg:classifiers":[
        {
            "category":"Shopping",
            "subcategory":"Optical Goods",
            "type":"Retail Goods"
        }
    ],
    "sg:phone":"+1 250 992 5240",
    "sg:postcode":"V2J 3K2",
    "sg:province":"BC",
    "sg:tags":[
        "sun",
        "goggles",
        "sunglasses",
        "optician"
    ],
    "wof:name":"Lensmasters 1 Hour Optical",
    "wof:placetype":"venue"
},
  "geometry": {"coordinates":[-122.50664500000001,52.973442],"type":"Point"}
}