{
  "type": "Feature",
  "properties": {
    "addr:full":"Saint-Frederic QC G0N 1P0",
    "addr:postcode":"g0n 1p0",
    "iso:country":"CA",
    "sg:city":"Saint-Frederic",
    "sg:classifiers":[
        {
            "category":"Recreation",
            "type":"Entertainment"
        }
    ],
    "sg:phone":"+1 418 426 2625",
    "sg:postcode":"G0N 1P0",
    "sg:province":"QC",
    "sg:tags":[
        "center"
    ],
    "wof:name":"Loisirs DE St-Frederic Inc",
    "wof:placetype":"venue"
},
  "geometry": {"coordinates":[-70.97086334230001,46.2971458435],"type":"Point"}
}