{
  "type": "Feature",
  "properties": {
    "addr:full":"Calgary AB T2R 0A5",
    "addr:postcode":"t2r 0a5",
    "iso:country":"CA",
    "sg:city":"Calgary",
    "sg:classifiers":[
        {
            "category":"Wholesale",
            "subcategory":"Machinery & Supplies",
            "type":"Manufacturing & Wholesale Goods"
        }
    ],
    "sg:phone":"+1 403 262 6679",
    "sg:postcode":"T2R 0A5",
    "sg:province":"AB",
    "sg:tags":[
        "field",
        "oil",
        "equipment"
    ],
    "wof:name":"Corlac Oilfield Leasing Ltd",
    "wof:placetype":"venue"
},
  "geometry": {"coordinates":[-114.068741,51.043324],"type":"Point"}
}