{
  "type": "Feature",
  "properties": {
    "addr:full":"Lac-Etchemin QC G0R 1S0",
    "addr:postcode":"g0r 1s0",
    "iso:country":"CA",
    "sg:city":"Lac-Etchemin",
    "sg:classifiers":[
        {
            "category":"Food & Beverages",
            "subcategory":"Groceries & Convenience Stores",
            "type":"Retail Goods"
        }
    ],
    "sg:phone":"+1 418 625 6833",
    "sg:postcode":"G0R 1S0",
    "sg:province":"QC",
    "wof:name":"Accommodation Quatre-Chemins",
    "wof:placetype":"venue"
},
  "geometry": {"coordinates":[-70.47407531739999,46.3933105469],"type":"Point"}
}