{
  "type": "Feature",
  "properties": {
    "iso:country":"CA",
    "sg:address":"871 Islington Ave",
    "sg:city":"Etobicoke",
    "sg:classifiers":[
        {
            "category":"Wholesale",
            "subcategory":"Jewelry",
            "type":"Manufacturing & Wholesale Goods"
        }
    ],
    "sg:phone":"+1 416 251 0606",
    "sg:postcode":"M8Z 4N9",
    "sg:province":"ON",
    "sg:tags":[
        "jeweler"
    ],
    "wof:name":"Yellowstone",
    "wof:placetype":"venue"
},
  "geometry": {"coordinates":[-79.51416778559999,43.6227912903],"type":"Point"}
}