{
  "type": "Feature",
  "properties": {
    "addr:full":"3 Rivers Dr Trenton ON K8V 1B3",
    "addr:housenumber":"3",
    "addr:postcode":"k8v 1b3",
    "addr:street":"Rivers Dr",
    "iso:country":"CA",
    "sg:address":"3 Rivers Dr",
    "sg:city":"Trenton",
    "sg:classifiers":[
        {
            "category":"Manufacturing",
            "subcategory":"Rubber & Plastics",
            "type":"Manufacturing & Wholesale Goods"
        }
    ],
    "sg:phone":"+1 613 394 2988",
    "sg:postcode":"K8V 1B3",
    "sg:province":"ON",
    "wof:name":"Quinte Plastics Ltd",
    "wof:placetype":"venue"
},
  "geometry": {"coordinates":[-77.5601196289,44.1115837097],"type":"Point"}
}