{
  "type": "Feature",
  "properties": {
    "addr:full":"5012 49th Ave Fort Nelson BC V0C 1R0",
    "addr:housenumber":"5012",
    "addr:postcode":"bc v0c 1r0",
    "addr:street":"49Th Ave",
    "iso:country":"CA",
    "sg:address":"5012 49th Ave",
    "sg:city":"Fort Nelson",
    "sg:classifiers":[
        {
            "category":"Organizations",
            "subcategory":"Non-profit Organization",
            "type":"Services"
        }
    ],
    "sg:phone":"+1 250 774 2993",
    "sg:postcode":"V0C 1R0",
    "sg:province":"BC",
    "sg:tags":[
        "info",
        "center",
        "drug",
        "abuse",
        "treatment",
        "addiction"
    ],
    "wof:name":"Fort Nelson Aboriginal Frndshp",
    "wof:placetype":"venue"
},
  "geometry": {"coordinates":[-122.701927185,58.8034133911],"type":"Point"}
}