{
  "type": "Feature",
  "properties": {
    "addr:full":"406 Mill St Blyth ON N0M 1H0",
    "addr:housenumber":"406",
    "addr:postcode":"n0m 1h0",
    "addr:street":"Mill St",
    "iso:country":"CA",
    "sg:address":"406 Mill St",
    "sg:city":"Blyth",
    "sg:classifiers":[
        {
            "category":"Personal",
            "subcategory":"Beauty Salon",
            "type":"Services"
        }
    ],
    "sg:phone":"+1 519 523 4793",
    "sg:postcode":"N0M 1H0",
    "sg:province":"ON",
    "sg:tags":[
        "day"
    ],
    "wof:name":"Spa Essentials",
    "wof:placetype":"venue"
},
  "geometry": {"coordinates":[-81.43142700200001,43.7371520996],"type":"Point"}
}