{
  "type": "Feature",
  "properties": {
    "iso:country":"CA",
    "sg:address":"169 Steeles Ave E",
    "sg:city":"North York",
    "sg:classifiers":[
        {
            "category":"Wholesale",
            "subcategory":"Durable Goods & Equipment",
            "type":"Manufacturing & Wholesale Goods"
        }
    ],
    "sg:phone":"+1 416 225 8010",
    "sg:postcode":"M2M 3Y5",
    "sg:province":"ON",
    "sg:tags":[
        "importer"
    ],
    "wof:name":"Alfakraft",
    "wof:placetype":"venue"
},
  "geometry": {"coordinates":[-79.4068069458,43.8007736206],"type":"Point"}
}