{
  "type": "Feature",
  "properties": {
    "addr:full":"281 Edward St Wingham ON N0G 2W0",
    "addr:housenumber":"281",
    "addr:postcode":"n0g 2w0",
    "addr:street":"Edward St",
    "iso:country":"CA",
    "sg:address":"281 Edward St",
    "sg:city":"Wingham",
    "sg:classifiers":[
        {
            "category":"Education",
            "subcategory":"Library",
            "type":"Public Place"
        }
    ],
    "sg:phone":"+1 519 357 3312",
    "sg:postcode":"N0G 2W0",
    "sg:province":"ON",
    "wof:name":"Wingham Public Library",
    "wof:placetype":"venue"
},
  "geometry": {"coordinates":[-81.313095,43.887627],"type":"Point"}
}