{
  "type": "Feature",
  "properties": {
    "addr:full":"Scarborough ON M1K 1N8",
    "addr:postcode":"m1k 1n8",
    "iso:country":"CA",
    "sg:city":"Scarborough",
    "sg:classifiers":[
        {
            "category":"Food & Beverages",
            "subcategory":"Bakery",
            "type":"Retail Goods"
        }
    ],
    "sg:phone":"+1 416 690 0372",
    "sg:postcode":"M1K 1N8",
    "sg:province":"ON",
    "sg:tags":[
        "baker"
    ],
    "wof:name":"Bread King Bakeries Ltd",
    "wof:placetype":"venue"
},
  "geometry": {"coordinates":[-79.268387,43.707249],"type":"Point"}
}