{
  "type": "Feature",
  "properties": {
    "addr:full":"8 Clarendon Ave Toronto ON M4V 1H9",
    "addr:housenumber":"8",
    "addr:postcode":"m4v 1h9",
    "addr:street":"Clarendon Ave",
    "iso:country":"CA",
    "sg:address":"8 Clarendon Ave",
    "sg:city":"Toronto",
    "sg:classifiers":[
        {
            "category":"Banks & Credit Unions",
            "subcategory":"Investment Brokerage",
            "type":"Services"
        }
    ],
    "sg:phone":"+1 416 922 1223",
    "sg:postcode":"M4V 1H9",
    "sg:province":"ON",
    "sg:tags":[
        "advisory",
        "financial"
    ],
    "wof:name":"Monetary Dynamics",
    "wof:placetype":"venue"
},
  "geometry": {"coordinates":[-79.4009170532,43.683380127],"type":"Point"}
}