{
  "type": "Feature",
  "properties": {
    "addr:full":"349 Rue Riverside Saint-Lambert QC J4P 1A8",
    "addr:housenumber":"349",
    "addr:postcode":"j4p 1a8",
    "addr:street":"Rue Riverside",
    "iso:country":"CA",
    "sg:address":"349 Rue Riverside",
    "sg:city":"Saint-Lambert",
    "sg:classifiers":[
        {
            "category":"Museum",
            "type":"Entertainment"
        }
    ],
    "sg:phone":"+1 450 923 6601",
    "sg:postcode":"J4P 1A8",
    "sg:province":"QC",
    "sg:tags":[
        "government",
        "village"
    ],
    "wof:name":"St Lambert Musee Marsil",
    "wof:placetype":"venue"
},
  "geometry": {"coordinates":[-73.5173873901,45.5045166016],"type":"Point"}
}