{
  "type": "Feature",
  "properties": {
    "addr:full":"380 County Blvd Thunder Bay ON P7A 7P5",
    "addr:housenumber":"380",
    "addr:postcode":"p7a 7p5",
    "addr:street":"County Blvd",
    "iso:country":"CA",
    "sg:address":"380 County Blvd",
    "sg:city":"Thunder Bay",
    "sg:classifiers":[
        {
            "category":"Government",
            "subcategory":"Police Station",
            "type":"Public Place"
        }
    ],
    "sg:phone":"+1 807 767 0300",
    "sg:postcode":"P7A 7P5",
    "sg:province":"ON",
    "sg:tags":[
        "department"
    ],
    "wof:name":"Thunder Bay Police Dept",
    "wof:placetype":"venue"
},
  "geometry": {"coordinates":[-89.2427825928,48.4581451416],"type":"Point"}
}