{
  "type": "Feature",
  "properties": {
    "addr:full":"1718 Vincent Massey Dr Cornwall ON K6H 5R6",
    "addr:housenumber":"1718",
    "addr:postcode":"k6h 5r6",
    "addr:street":"Vincent Massey Dr",
    "iso:country":"CA",
    "sg:address":"1718 Vincent Massey Dr",
    "sg:city":"Cornwall",
    "sg:classifiers":[
        {
            "category":"Restaurant",
            "type":"Food & Drink"
        }
    ],
    "sg:phone":"+1 613 933 2573",
    "sg:postcode":"K6H 5R6",
    "sg:province":"ON",
    "wof:name":"A & W Family Restaurant",
    "wof:placetype":"venue"
},
  "geometry": {"coordinates":[-74.7698516846,45.0312614441],"type":"Point"}
}