{
  "type": "Feature",
  "properties": {
    "iso:country":"CA",
    "sg:address":"85 Rue Chef Maurice Bastien",
    "sg:city":"Wendake",
    "sg:classifiers":[
        {
            "category":"Shopping",
            "subcategory":"Hobbies, Toys, & Games",
            "type":"Retail Goods"
        }
    ],
    "sg:phone":"+1 418 842 9395",
    "sg:postcode":"G0A 4V0",
    "sg:province":"QC",
    "sg:tags":[
        "craft"
    ],
    "wof:name":"Petit Huron Moc Enr",
    "wof:placetype":"venue"
},
  "geometry": {"coordinates":[-71.427078,46.842949],"type":"Point"}
}