{
  "type": "Feature",
  "properties": {
    "addr:full":"85 Rue Chef Maurice Bastien Wendake QC G0A 4V0",
    "addr:housenumber":"85",
    "addr:postcode":"g0a 4v0",
    "addr:street":"Rue Chef Maurice Bastien",
    "iso:country":"CA",
    "sg:address":"85 Rue Chef Maurice Bastien",
    "sg:city":"Wendake",
    "sg:classifiers":[
        {
            "category":"Shopping",
            "subcategory":"Hobbies, Toys, & Games",
            "type":"Retail Goods"
        }
    ],
    "sg:phone":"+1 418 842 9395",
    "sg:postcode":"G0A 4V0",
    "sg:province":"QC",
    "sg:tags":[
        "craft"
    ],
    "wof:name":"Petit Huron Moc Enr",
    "wof:placetype":"venue"
},
  "geometry": {"coordinates":[-71.42707799999999,46.842949],"type":"Point"}
}