{
  "type": "Feature",
  "properties": {
    "iso:country":"CA",
    "sg:city":"Regina",
    "sg:classifiers":[
        {
            "category":"Government",
            "subcategory":"Office",
            "type":"Public Place"
        }
    ],
    "sg:phone":"+1 306 787 5220",
    "sg:postcode":"S4R 3C3",
    "sg:province":"SK",
    "wof:name":"Canadian Food Inspection Agenc",
    "wof:placetype":"venue"
},
  "geometry": {"coordinates":[-104.617905,50.430397],"type":"Point"}
}