{
  "type": "Feature",
  "properties": {
    "addr:full":"Regina SK S4R 3C3",
    "addr:postcode":"s4r 3c3",
    "iso:country":"CA",
    "sg:city":"Regina",
    "sg:classifiers":[
        {
            "category":"Government",
            "subcategory":"Office",
            "type":"Public Place"
        }
    ],
    "sg:phone":"+1 306 787 5220",
    "sg:postcode":"S4R 3C3",
    "sg:province":"SK",
    "wof:name":"Canadian Food Inspection Agenc",
    "wof:placetype":"venue"
},
  "geometry": {"coordinates":[-104.61790499999999,50.430397],"type":"Point"}
}