{
  "type": "Feature",
  "properties": {
    "addr:full":"85 Queen St N Hamilton ON L8R 2V5",
    "addr:housenumber":"85",
    "addr:postcode":"l8r 2v5",
    "addr:street":"Queen St N",
    "iso:country":"CA",
    "sg:address":"85 Queen St N",
    "sg:city":"Hamilton",
    "sg:classifiers":[
        {
            "category":"Restaurant",
            "type":"Food & Drink"
        }
    ],
    "sg:phone":"+1 905 526 0889",
    "sg:postcode":"L8R 2V5",
    "sg:province":"ON",
    "wof:name":"Cho Sun oK Korean Bbq Rest",
    "wof:placetype":"venue"
},
  "geometry": {"coordinates":[-79.8776931763,43.2619361877],"type":"Point"}
}