{
  "type": "Feature",
  "properties": {
    "iso:country":"CA",
    "sg:address":"314 Green St",
    "sg:city":"Flin Flon",
    "sg:classifiers":[
        {
            "category":"Restaurant",
            "type":"Food & Drink"
        }
    ],
    "sg:phone":"+1 204 687 7517",
    "sg:postcode":"R8A 0H2",
    "sg:province":"MB",
    "sg:tags":[
        "grocer"
    ],
    "wof:name":"Arctic Beverages Ltd",
    "wof:placetype":"venue"
},
  "geometry": {"coordinates":[-101.850891113,54.7712898254],"type":"Point"}
}