{
  "type": "Feature",
  "properties": {
    "addr:full":"1771 County Road 5 Rd Frankford ON K0K 2C0",
    "addr:housenumber":"1771",
    "addr:postcode":"k0k 2c0",
    "addr:street":"County Road 5 Rd",
    "iso:country":"CA",
    "sg:address":"1771 County Road 5 Rd",
    "sg:city":"Frankford",
    "sg:classifiers":[
        {
            "category":"Building & Trades",
            "subcategory":"Electrical",
            "type":"Services"
        }
    ],
    "sg:phone":"+1 613 398 8860",
    "sg:postcode":"K0K 2C0",
    "sg:province":"ON",
    "sg:tags":[
        "electric",
        "contractor"
    ],
    "wof:name":"Stockdale Electric & Mech",
    "wof:placetype":"venue"
},
  "geometry": {"coordinates":[-77.596352,44.201118],"type":"Point"}
}