{
  "type": "Feature",
  "properties": {
    "iso:country":"CA",
    "sg:address":"3063 Lake Shore Blvd W",
    "sg:city":"Etobicoke",
    "sg:classifiers":[
        {
            "category":"Food & Beverages",
            "subcategory":"Groceries & Convenience Stores",
            "type":"Retail Goods"
        }
    ],
    "sg:phone":"+1 416 255 7357",
    "sg:postcode":"M8V 1K6",
    "sg:province":"ON",
    "wof:name":"Lakeshore Smoke & Variety",
    "wof:placetype":"venue"
},
  "geometry": {"coordinates":[-79.51016235349999,43.5995674133],"type":"Point"}
}