{
  "type": "Feature",
  "properties": {
    "addr:full":"2000 S Main St Westville NS B0K 2A0",
    "addr:housenumber":"2000",
    "addr:postcode":"b0k 2a0",
    "addr:street":"S Main St",
    "iso:country":"CA",
    "sg:address":"2000 S Main St",
    "sg:city":"Westville",
    "sg:classifiers":[
        {
            "category":"Retail",
            "subcategory":"Car Wash",
            "type":"Services"
        }
    ],
    "sg:phone":"+1 902 396 1272",
    "sg:postcode":"B0K 2A0",
    "sg:province":"NS",
    "sg:tags":[
        "polishing",
        "washing"
    ],
    "wof:name":"Mac Intosh Car Care Ctr",
    "wof:placetype":"venue"
},
  "geometry": {"coordinates":[-62.7191200256,45.5533256531],"type":"Point"}
}