{
  "type": "Feature",
  "properties": {
    "addr:full":"1134 Yonge St Toronto ON M4W 2L8",
    "addr:housenumber":"1134",
    "addr:postcode":"m4w 2l8",
    "addr:street":"Yonge St",
    "iso:country":"CA",
    "sg:address":"1134 Yonge St",
    "sg:city":"Toronto",
    "sg:classifiers":[
        {
            "category":"Wholesale",
            "subcategory":"Machinery & Supplies",
            "type":"Manufacturing & Wholesale Goods"
        }
    ],
    "sg:phone":"+1 416 929 6885",
    "sg:postcode":"M4W 2L8",
    "sg:province":"ON",
    "sg:tags":[
        "equipment",
        "barbecue",
        "kitchen",
        "accessory"
    ],
    "wof:name":"Word of Mouth Upscale Kitchen",
    "wof:placetype":"venue"
},
  "geometry": {"coordinates":[-79.390694,43.679394],"type":"Point"}
}