{
  "type": "Feature",
  "properties": {
    "addr:full":"435 Av Pie-X Saint-Christophe-D'Arthabaska QC G6P 6S1",
    "addr:housenumber":"435",
    "addr:postcode":"g6p 6s1",
    "addr:street":"Av Pie-X",
    "iso:country":"CA",
    "sg:address":"435 Av Pie-X",
    "sg:city":"Saint-Christophe-D'Arthabaska",
    "sg:classifiers":[
        {
            "category":"Freight",
            "type":"Transportation"
        }
    ],
    "sg:phone":"+1 819 357 2691",
    "sg:postcode":"G6P 6S1",
    "sg:province":"QC",
    "sg:tags":[
        "mover",
        "commercial"
    ],
    "wof:name":"Livraison Jo Pouliot Inc",
    "wof:placetype":"venue"
},
  "geometry": {"coordinates":[-71.9313659668,46.0294685364],"type":"Point"}
}