{
  "type": "Feature",
  "properties": {
    "addr:full":"2016 Queen St E Toronto ON M4L 1J3",
    "addr:housenumber":"2016",
    "addr:postcode":"m4l 1j3",
    "addr:street":"Queen St E",
    "iso:country":"CA",
    "sg:address":"2016 Queen St E",
    "sg:city":"Toronto",
    "sg:classifiers":[
        {
            "category":"Shopping",
            "subcategory":"Clothing, Apparel, & Fashions",
            "type":"Retail Goods"
        }
    ],
    "sg:phone":"+1 416 690 5533",
    "sg:postcode":"M4L 1J3",
    "sg:province":"ON",
    "wof:name":"Posh Boutique",
    "wof:placetype":"venue"
},
  "geometry": {"coordinates":[-79.299156,43.670361],"type":"Point"}
}