{
  "type": "Feature",
  "properties": {
    "addr:full":"644 Pine Ave Beausejour MB R0E 0C0",
    "addr:housenumber":"644",
    "addr:postcode":"r0e 0c0",
    "addr:street":"Pine Ave",
    "iso:country":"CA",
    "sg:address":"644 Pine Ave",
    "sg:city":"Beausejour",
    "sg:classifiers":[
        {
            "category":"Building & Trades",
            "subcategory":"Construction",
            "type":"Services"
        }
    ],
    "sg:phone":"+1 204 268 2687",
    "sg:postcode":"R0E 0C0",
    "sg:province":"MB",
    "sg:tags":[
        "painter"
    ],
    "wof:name":"Urbanski Painting",
    "wof:placetype":"venue"
},
  "geometry": {"coordinates":[-96.51462554930001,50.0671844482],"type":"Point"}
}