{
  "type": "Feature",
  "properties": {
    "iso:country":"CA",
    "sg:city":"Edmonton",
    "sg:classifiers":[
        {
            "category":"Professional",
            "subcategory":"Computer Services",
            "type":"Services"
        }
    ],
    "sg:phone":"+1 780 421 1878",
    "sg:postcode":"T5J 1V9",
    "sg:province":"AB",
    "sg:tags":[
        "consultant"
    ],
    "wof:name":"Technology North Corp",
    "wof:placetype":"venue"
},
  "geometry": {"coordinates":[-113.493118286,53.54114151],"type":"Point"}
}