{
  "type": "Feature",
  "properties": {
    "addr:full":"Bonnyville AB T9N 2B4",
    "addr:postcode":"t9n 2b4",
    "iso:country":"CA",
    "sg:city":"Bonnyville",
    "sg:classifiers":[
        {
            "category":"Personal",
            "subcategory":"Beauty Salon",
            "type":"Services"
        }
    ],
    "sg:phone":"+1 780 826 4566",
    "sg:postcode":"T9N 2B4",
    "sg:province":"AB",
    "wof:name":"Techniques Hair Salon",
    "wof:placetype":"venue"
},
  "geometry": {"coordinates":[-110.735207,54.267738],"type":"Point"}
}