{
  "type": "Feature",
  "properties": {
    "addr:full":"1201 Rue DE LA Montagne Montreal QC H3G 1Z2",
    "addr:housenumber":"1201",
    "addr:postcode":"h3g 1z2",
    "addr:street":"Rue De La Montagne",
    "iso:country":"CA",
    "sg:address":"1201 Rue DE LA Montagne",
    "sg:city":"Montreal",
    "sg:classifiers":[
        {
            "category":"Parking",
            "type":"Transportation"
        }
    ],
    "sg:phone":"+1 514 879 1079",
    "sg:postcode":"H3G 1Z2",
    "sg:province":"QC",
    "sg:tags":[
        "garage"
    ],
    "wof:name":"Stationnement Em",
    "wof:placetype":"venue"
},
  "geometry": {"coordinates":[-73.57359313960001,45.4973869324],"type":"Point"}
}