{
  "type": "Feature",
  "properties": {
    "addr:full":"320 Amherst Ave Viscount SK S0K 4M0",
    "addr:housenumber":"320",
    "addr:postcode":"s0k 4m0",
    "addr:street":"Amherst Ave",
    "iso:country":"CA",
    "sg:address":"320 Amherst Ave",
    "sg:city":"Viscount",
    "sg:classifiers":[
        {
            "category":"Food & Beverages",
            "subcategory":"Specialty",
            "type":"Retail Goods"
        }
    ],
    "sg:phone":"+1 306 944 4404",
    "sg:postcode":"S0K 4M0",
    "sg:province":"SK",
    "sg:tags":[
        "water",
        "cooler",
        "bulk",
        "fountain",
        "filter"
    ],
    "wof:name":"Mister Mist",
    "wof:placetype":"venue"
},
  "geometry": {"coordinates":[-105.640693665,51.9491539001],"type":"Point"}
}