{
  "type": "Feature",
  "properties": {
    "addr:full":"Havelock ON K0L 1Z0",
    "addr:postcode":"k0l 1z0",
    "iso:country":"CA",
    "sg:city":"Havelock",
    "sg:classifiers":[
        {
            "category":"Sports & Exercise",
            "subcategory":"Race Track",
            "type":"Entertainment"
        }
    ],
    "sg:phone":"+1 705 778 1304",
    "sg:postcode":"K0L 1Z0",
    "sg:province":"ON",
    "sg:tags":[
        "equipment",
        "supply"
    ],
    "wof:name":"Graham's Racing Silks Inc",
    "wof:placetype":"venue"
},
  "geometry": {"coordinates":[-77.886383,44.433201],"type":"Point"}
}