{
  "type": "Feature",
  "properties": {
    "addr:full":"100 Main St Springhill NS B0M 1X0",
    "addr:housenumber":"100",
    "addr:postcode":"b0m 1x0",
    "addr:street":"Main St",
    "iso:country":"CA",
    "sg:address":"100 Main St",
    "sg:city":"Springhill",
    "sg:classifiers":[
        {
            "category":"Wholesale",
            "subcategory":"Scrap",
            "type":"Manufacturing & Wholesale Goods"
        }
    ],
    "sg:phone":"+1 902 597 8000",
    "sg:postcode":"B0M 1X0",
    "sg:province":"NS",
    "sg:tags":[
        "recycling",
        "center"
    ],
    "wof:name":"Paint Recycling CO",
    "wof:placetype":"venue"
},
  "geometry": {"coordinates":[-64.055397,45.651104],"type":"Point"}
}