{
  "type": "Feature",
  "properties": {
    "addr:full":"240 Keefer St Vancouver BC V6A 1X5",
    "addr:housenumber":"240",
    "addr:postcode":"v6a 1x5",
    "addr:street":"Keefer St",
    "iso:country":"CA",
    "sg:address":"240 Keefer St",
    "sg:city":"Vancouver",
    "sg:classifiers":[
        {
            "category":"Health Services",
            "subcategory":"Clinic",
            "type":"Services"
        }
    ],
    "sg:phone":"+1 604 682 8872",
    "sg:postcode":"V6A 1X5",
    "sg:province":"BC",
    "sg:tags":[
        "herbalist"
    ],
    "wof:name":"Yue Hua Trading CO Ltd",
    "wof:placetype":"venue"
},
  "geometry": {"coordinates":[-123.098625183,49.2793159485],"type":"Point"}
}