{
  "type": "Feature",
  "properties": {
    "addr:full":"1375 Rue Graham-Bell Boucherville QC J4B 6A1",
    "addr:housenumber":"1375",
    "addr:postcode":"j4b 6a1",
    "addr:street":"Rue Graham-Bell",
    "iso:country":"CA",
    "sg:address":"1375 Rue Graham-Bell",
    "sg:city":"Boucherville",
    "sg:classifiers":[
        {
            "category":"Manufacturing",
            "subcategory":"Pet Food",
            "type":"Manufacturing & Wholesale Goods"
        }
    ],
    "sg:phone":"+1 450 655 3505",
    "sg:postcode":"J4B 6A1",
    "sg:province":"QC",
    "sg:tags":[
        "feed"
    ],
    "wof:name":"Farines Spb Meal Ltee",
    "wof:placetype":"venue"
},
  "geometry": {"coordinates":[-73.4324645996,45.562915802],"type":"Point"}
}