{
  "type": "Feature",
  "properties": {
    "addr:full":"347 Boul Desgagne Falardeau QC G0V 1C0",
    "addr:housenumber":"347",
    "addr:postcode":"g0v 1c0",
    "addr:street":"Boul Desgagne Falardeau",
    "iso:country":"CA",
    "sg:address":"347 Boul Desgagne",
    "sg:city":"Falardeau",
    "sg:classifiers":[
        {
            "category":"Restaurant",
            "type":"Food & Drink"
        }
    ],
    "sg:phone":"+1 418 673 3737",
    "sg:postcode":"G0V 1C0",
    "sg:province":"QC",
    "wof:name":"Cocotte",
    "wof:placetype":"venue"
},
  "geometry": {"coordinates":[-71.110336,48.620945],"type":"Point"}
}