{
  "type": "Feature",
  "properties": {
    "addr:full":"277 Willow St Truro NS B2N 5A3",
    "addr:housenumber":"277",
    "addr:postcode":"b2n 5a3",
    "addr:street":"Willow St",
    "iso:country":"CA",
    "sg:address":"277 Willow St",
    "sg:city":"Truro",
    "sg:classifiers":[
        {
            "category":"Travel",
            "subcategory":"Hotels & Motels",
            "type":"Entertainment"
        }
    ],
    "sg:phone":"+1 902 895 5325",
    "sg:postcode":"B2N 5A3",
    "sg:province":"NS",
    "wof:name":"Willow Bend Motel & Restaurant",
    "wof:placetype":"venue"
},
  "geometry": {"coordinates":[-63.293694,45.355812],"type":"Point"}
}