{
  "type": "Feature",
  "properties": {
    "addr:full":"529 17 Ave SW Calgary AB T2S 0A9",
    "addr:postcode":"t2s 0a9",
    "addr:street":"529 17 Ave Sw",
    "iso:country":"CA",
    "sg:address":"529 17 Ave SW",
    "sg:city":"Calgary",
    "sg:classifiers":[
        {
            "category":"Bars & Pubs",
            "type":"Food & Drink"
        }
    ],
    "sg:phone":"+1 403 228 7175",
    "sg:postcode":"T2S 0A9",
    "sg:province":"AB",
    "wof:name":"Sal's on 17th",
    "wof:placetype":"venue"
},
  "geometry": {"coordinates":[-114.072387695,51.037689209],"type":"Point"}
}