{
  "type": "Feature",
  "properties": {
    "addr:full":"15 King Lane Riley Brook NB E7G 1W5",
    "addr:housenumber":"15",
    "addr:postcode":"e7g 1w5",
    "addr:street":"King Lane",
    "iso:country":"CA",
    "sg:address":"15 King Lane",
    "sg:city":"Riley Brook",
    "sg:classifiers":[
        {
            "category":"Farming",
            "subcategory":"Fish & Marine Products",
            "type":"Manufacturing & Wholesale Goods"
        }
    ],
    "sg:phone":"+1 506 356 2354",
    "sg:postcode":"E7G 1W5",
    "sg:province":"NB",
    "sg:tags":[
        "wildlife",
        "camp",
        "fishing"
    ],
    "wof:name":"Tobique Valley Outfitters Ltd",
    "wof:placetype":"venue"
},
  "geometry": {"coordinates":[-67.215157,47.164459],"type":"Point"}
}