{
  "type": "Feature",
  "properties": {
    "addr:full":"52 Harwood Ave S Ajax ON L1S 2H6",
    "addr:housenumber":"52",
    "addr:postcode":"l1s 2h6",
    "addr:street":"Harwood Ave S",
    "iso:country":"CA",
    "sg:address":"52 Harwood Ave S",
    "sg:city":"Ajax",
    "sg:classifiers":[
        {
            "category":"Shopping",
            "subcategory":"Tobacco",
            "type":"Retail Goods"
        }
    ],
    "sg:phone":"+1 905 683 5930",
    "sg:postcode":"L1S 2H6",
    "sg:province":"ON",
    "sg:tags":[
        "cigarette",
        "cigar",
        "dealer"
    ],
    "wof:name":"Centre Smoke Shop",
    "wof:placetype":"venue"
},
  "geometry": {"coordinates":[-79.0216293335,43.8510322571],"type":"Point"}
}