{
  "type": "Feature",
  "properties": {
    "addr:full":"3190 Rue Sherbrooke E Montreal QC H1W 1B7",
    "addr:housenumber":"3190",
    "addr:postcode":"h1w 1b7",
    "addr:street":"Rue Sherbrooke E",
    "iso:country":"CA",
    "sg:address":"3190 Rue Sherbrooke E",
    "sg:city":"Montreal",
    "sg:classifiers":[
        {
            "category":"Professional",
            "subcategory":"Art Services",
            "type":"Services"
        }
    ],
    "sg:phone":"+1 514 273 9330",
    "sg:postcode":"H1W 1B7",
    "sg:province":"QC",
    "sg:tags":[
        "development",
        "package",
        "designing"
    ],
    "wof:name":"Gagnon Designer Enr",
    "wof:placetype":"venue"
},
  "geometry": {"coordinates":[-73.55697600000001,45.543709],"type":"Point"}
}