{
  "type": "Feature",
  "properties": {
    "addr:full":"38 Pete's Lane Pefferlaw ON L0E 1N0",
    "addr:housenumber":"38",
    "addr:postcode":"l0e 1n0",
    "addr:street":"Pete'S Lane",
    "iso:country":"CA",
    "sg:address":"38 Pete's Lane",
    "sg:city":"Pefferlaw",
    "sg:classifiers":[
        {
            "category":"Education",
            "subcategory":"Library",
            "type":"Public Place"
        }
    ],
    "sg:phone":"+1 705 437 1514",
    "sg:postcode":"L0E 1N0",
    "sg:province":"ON",
    "wof:name":"Pefferlaw Public Library",
    "wof:placetype":"venue"
},
  "geometry": {"coordinates":[-79.195595,44.308548],"type":"Point"}
}