{
  "type": "Feature",
  "properties": {
    "addr:full":"2810 Major Mackenzie Dr # 11 Maple ON L6A 3L2",
    "addr:housenumber":"2810",
    "addr:postcode":"l6a 3l2",
    "addr:street":"Major Mackenzie Dr # 11",
    "iso:country":"CA",
    "sg:address":"2810 Major Mackenzie Dr # 11",
    "sg:city":"Maple",
    "sg:classifiers":[
        {
            "category":"Food & Beverages",
            "subcategory":"Groceries & Convenience Stores",
            "type":"Retail Goods"
        }
    ],
    "sg:phone":"+1 905 832 9566",
    "sg:postcode":"L6A 3L2",
    "sg:province":"ON",
    "sg:tags":[
        "grocer"
    ],
    "wof:name":"Hasty Market",
    "wof:placetype":"venue"
},
  "geometry": {"coordinates":[-79.53276099999999,43.850861],"type":"Point"}
}