{
  "type": "Feature",
  "properties": {
    "addr:full":"2067 Ogilvie St S Prince George BC V2N 1X2",
    "addr:housenumber":"2067",
    "addr:postcode":"v2n 1x2",
    "addr:street":"Ogilvie St S",
    "iso:country":"CA",
    "sg:address":"2067 Ogilvie St S",
    "sg:city":"Prince George",
    "sg:classifiers":[
        {
            "category":"Home & Garden",
            "subcategory":"Hardware",
            "type":"Retail Goods"
        }
    ],
    "sg:phone":"+1 250 563 4930",
    "sg:postcode":"V2N 1X2",
    "sg:province":"BC",
    "sg:tags":[
        "door"
    ],
    "wof:name":"Accurate Door & Hardware CO",
    "wof:placetype":"venue"
},
  "geometry": {"coordinates":[-122.78945899999999,53.90498],"type":"Point"}
}