{
  "type": "Feature",
  "properties": {
    "addr:full":"689 Carpenter Bald Hill Rd Shannon NB E5T 3W7",
    "addr:housenumber":"689",
    "addr:postcode":"e5t 3w7",
    "addr:street":"Carpenter Bald Hill Rd",
    "iso:country":"CA",
    "sg:address":"689 Carpenter Bald Hill Rd",
    "sg:city":"Shannon",
    "sg:classifiers":[
        {
            "category":"Building & Trades",
            "subcategory":"Construction",
            "type":"Services"
        }
    ],
    "sg:phone":"+1 506 485 5923",
    "sg:postcode":"E5T 3W7",
    "sg:province":"NB",
    "sg:tags":[
        "concrete",
        "contractor"
    ],
    "wof:name":"Prestige Concrete Ltd",
    "wof:placetype":"venue"
},
  "geometry": {"coordinates":[-65.9889221191,45.7065010071],"type":"Point"}
}