{
  "type": "Feature",
  "properties": {
    "addr:full":"35 Pearl St E Kingsville ON N9Y 1K3",
    "addr:housenumber":"35",
    "addr:postcode":"n9y 1k3",
    "addr:street":"Pearl St E",
    "iso:country":"CA",
    "sg:address":"35 Pearl St E",
    "sg:city":"Kingsville",
    "sg:classifiers":[
        {
            "category":"Personal",
            "subcategory":"Beauty Salon",
            "type":"Services"
        }
    ],
    "sg:phone":"+1 519 733 5646",
    "sg:postcode":"N9Y 1K3",
    "sg:province":"ON",
    "wof:name":"Fiorella & CO",
    "wof:placetype":"venue"
},
  "geometry": {"coordinates":[-82.73825100000001,42.036926],"type":"Point"}
}