{
  "type": "Feature",
  "properties": {
    "addr:full":"Chambly QC J3L 1W7",
    "addr:postcode":"j3l 1w7",
    "iso:country":"CA",
    "sg:city":"Chambly",
    "sg:classifiers":[
        {
            "category":"Retail",
            "subcategory":"Animal Services",
            "type":"Services"
        }
    ],
    "sg:phone":"+1 450 658 3125",
    "sg:postcode":"J3L 1W7",
    "sg:province":"QC",
    "sg:tags":[
        "pet",
        "shop",
        "grooming",
        "washing"
    ],
    "wof:name":"Tropicazoo Chambly",
    "wof:placetype":"venue"
},
  "geometry": {"coordinates":[-73.28969600000001,45.44693],"type":"Point"}
}