{
  "type": "Feature",
  "properties": {
    "addr:full":"532 Rue Notre-Dame Saint-Francois-Du-Lac QC J0G 1M0",
    "addr:housenumber":"532",
    "addr:postcode":"j0g 1m0",
    "addr:street":"Rue Notre-Dame Saint-Francois-Du-Lac",
    "iso:country":"CA",
    "sg:address":"532 Rue Notre-Dame",
    "sg:city":"Saint-Francois-Du-Lac",
    "sg:classifiers":[
        {
            "category":"Building & Trades",
            "subcategory":"Construction",
            "type":"Services"
        }
    ],
    "sg:phone":"+1 450 568 0614",
    "sg:postcode":"J0G 1M0",
    "sg:province":"QC",
    "sg:tags":[
        "maker",
        "cabinet"
    ],
    "wof:name":"Ebenisterie Simon Pierre",
    "wof:placetype":"venue"
},
  "geometry": {"coordinates":[-72.81764221189999,46.063205719],"type":"Point"}
}