{
  "type": "Feature",
  "properties": {
    "addr:full":"Cambridge ON N1R 7P3",
    "addr:postcode":"n1r 7p3",
    "iso:country":"CA",
    "sg:city":"Cambridge",
    "sg:classifiers":[
        {
            "category":"Building & Trades",
            "subcategory":"Plumbing",
            "type":"Services"
        }
    ],
    "sg:phone":"+1 519 622 2772",
    "sg:postcode":"N1R 7P3",
    "sg:province":"ON",
    "sg:tags":[
        "air",
        "conditioning",
        "furnace",
        "system",
        "contractor"
    ],
    "wof:name":"Union Energy",
    "wof:placetype":"venue"
},
  "geometry": {"coordinates":[-80.32137299999999,43.400421],"type":"Point"}
}