{
  "type": "Feature",
  "properties": {
    "iso:country":"CA",
    "sg:address":"45 Outer Dr",
    "sg:city":"London",
    "sg:classifiers":[
        {
            "category":"Building & Trades",
            "subcategory":"Electrical",
            "type":"Services"
        }
    ],
    "sg:phone":"+1 519 652 5531",
    "sg:postcode":"N6P 1E3",
    "sg:province":"ON",
    "sg:tags":[
        "electric",
        "contractor"
    ],
    "wof:name":"Ray's Electric",
    "wof:placetype":"venue"
},
  "geometry": {"coordinates":[-81.2896575928,42.9021453857],"type":"Point"}
}