{
  "type": "Feature",
  "properties": {
    "iso:country":"CA",
    "sg:address":"279 Tranquille Rd",
    "sg:city":"Kamloops",
    "sg:classifiers":[
        {
            "category":"Home & Garden",
            "subcategory":"Home Furnishings",
            "type":"Retail Goods"
        }
    ],
    "sg:phone":"+1 250 376 2238",
    "sg:postcode":"V2B 3G2",
    "sg:province":"BC",
    "sg:tags":[
        "lighting",
        "fixture"
    ],
    "wof:name":"Light Your World",
    "wof:placetype":"venue"
},
  "geometry": {"coordinates":[-120.356987,50.687023],"type":"Point"}
}