{
  "type": "Feature",
  "properties": {
    "addr:full":"6470 28 Ave NW Edmonton AB T6L 6N3",
    "addr:housenumber":"6470",
    "addr:postcode":"t6l 6n3",
    "addr:street":"28 Ave Nw",
    "iso:country":"CA",
    "sg:address":"6470 28 Ave NW",
    "sg:city":"Edmonton",
    "sg:classifiers":[
        {
            "category":"Restaurant",
            "type":"Food & Drink"
        }
    ],
    "sg:phone":"+1 780 461 5174",
    "sg:postcode":"T6L 6N3",
    "sg:province":"AB",
    "wof:name":"Taco Bell",
    "wof:placetype":"venue"
},
  "geometry": {"coordinates":[-113.43218231199999,53.4584884644],"type":"Point"}
}