{
  "type": "Feature",
  "properties": {
    "addr:full":"1310 Centre St SE Calgary AB T2G 2E2",
    "addr:housenumber":"1310",
    "addr:postcode":"t2g 2e2",
    "addr:street":"Centre St Se",
    "iso:country":"CA",
    "sg:address":"1310 Centre St SE",
    "sg:city":"Calgary",
    "sg:classifiers":[
        {
            "category":"Manufacturing",
            "subcategory":"Printing",
            "type":"Manufacturing & Wholesale Goods"
        }
    ],
    "sg:phone":"+1 403 264 8880",
    "sg:postcode":"T2G 2E2",
    "sg:province":"AB",
    "sg:tags":[
        "printer"
    ],
    "wof:name":"Stop & Go Reproductions",
    "wof:placetype":"venue"
},
  "geometry": {"coordinates":[-114.063187,51.040283],"type":"Point"}
}