{
  "type": "Feature",
  "properties": {
    "addr:full":"Brockville ON K6V 6Z4",
    "addr:postcode":"k6v 6z4",
    "iso:country":"CA",
    "sg:city":"Brockville",
    "sg:classifiers":[
        {
            "category":"Professional",
            "subcategory":"Lawyer & Legal Services",
            "type":"Services"
        }
    ],
    "sg:phone":"+1 613 498 0944",
    "sg:postcode":"K6V 6Z4",
    "sg:province":"ON",
    "sg:tags":[
        "attorney"
    ],
    "wof:name":"Hammond Osborne",
    "wof:placetype":"venue"
},
  "geometry": {"coordinates":[-75.6824417114,44.5881652832],"type":"Point"}
}