{
  "type": "Feature",
  "properties": {
    "addr:full":"17010 90 Ave NW # 156 Edmonton AB T5T 1L6",
    "addr:housenumber":"17010",
    "addr:postcode":"t5t 1l6",
    "addr:street":"90 Ave Nw # 156",
    "iso:country":"CA",
    "sg:address":"17010 90 Ave NW # 156",
    "sg:city":"Edmonton",
    "sg:classifiers":[
        {
            "category":"Insurance",
            "subcategory":"Insurance Agent",
            "type":"Services"
        }
    ],
    "sg:phone":"+1 780 448 7137",
    "sg:postcode":"T5T 1L6",
    "sg:province":"AB",
    "wof:name":"CO-Operators General Insurance",
    "wof:placetype":"venue"
},
  "geometry": {"coordinates":[-113.61582199999999,53.524986],"type":"Point"}
}