{
  "type": "Feature",
  "properties": {
    "addr:full":"1275 Rue Papineau Longueuil QC J4K 3K9",
    "addr:housenumber":"1275",
    "addr:postcode":"j4k 3k9",
    "addr:street":"Rue Papineau",
    "iso:country":"CA",
    "sg:address":"1275 Rue Papineau",
    "sg:city":"Longueuil",
    "sg:classifiers":[
        {
            "category":"Education",
            "subcategory":"School",
            "type":"Public Place"
        }
    ],
    "sg:phone":"+1 450 674 1753",
    "sg:postcode":"J4K 3K9",
    "sg:province":"QC",
    "wof:name":"Ecole Paul DE Maricourt",
    "wof:placetype":"venue"
},
  "geometry": {"coordinates":[-73.5006408691,45.5168991089],"type":"Point"}
}