{
  "type": "Feature",
  "properties": {
    "addr:full":"208 St Mary's River Dr Sault Ste Marie ON P6A 5V4",
    "addr:housenumber":"208",
    "addr:postcode":"p6a 5v4",
    "addr:street":"St Mary'S River Dr",
    "iso:country":"CA",
    "sg:address":"208 St Mary's River Dr",
    "sg:city":"Sault Ste Marie",
    "sg:classifiers":[
        {
            "category":"Professional",
            "subcategory":"Business Services",
            "type":"Services"
        }
    ],
    "sg:phone":"+1 705 945 6950",
    "sg:postcode":"P6A 5V4",
    "sg:province":"ON",
    "sg:tags":[
        "convention",
        "meeting",
        "facility"
    ],
    "wof:name":"Holiday Inn Waterfront",
    "wof:placetype":"venue"
},
  "geometry": {"coordinates":[-84.25244903559999,46.5118751526],"type":"Point"}
}