{
  "type": "Feature",
  "properties": {
    "addr:full":"860 Boul DE L'Ange-Gardien L'Assomption QC J5W 1T5",
    "addr:housenumber":"860",
    "addr:postcode":"j5w 1t5",
    "addr:street":"Boul De L'Ange-Gardien",
    "iso:country":"CA",
    "sg:address":"860 Boul DE L'Ange-Gardien",
    "sg:city":"L'Assomption",
    "sg:classifiers":[
        {
            "category":"Autos & Motor Vehicles",
            "subcategory":"Auto Supplies",
            "type":"Retail Goods"
        }
    ],
    "sg:phone":"+1 450 589 3579",
    "sg:postcode":"J5W 1T5",
    "sg:province":"QC",
    "sg:tags":[
        "repairing",
        "automobile"
    ],
    "wof:name":"Hetu Auto Electric",
    "wof:placetype":"venue"
},
  "geometry": {"coordinates":[-73.4175872803,45.8330383301],"type":"Point"}
}