{
  "type": "Feature",
  "properties": {
    "iso:country":"CA",
    "sg:address":"165 Edgewater St",
    "sg:city":"Mahone Bay",
    "sg:classifiers":[
        {
            "category":"Government",
            "subcategory":"Office",
            "type":"Public Place"
        }
    ],
    "sg:phone":"+1 902 624 6151",
    "sg:postcode":"B0J 2E0",
    "sg:province":"NS",
    "sg:tags":[
        "information",
        "tourist",
        "village"
    ],
    "wof:name":"Mahone Bay Tourist Bureau",
    "wof:placetype":"venue"
},
  "geometry": {"coordinates":[-64.3812866211,44.4533462524],"type":"Point"}
}