{
  "type": "Feature",
  "properties": {
    "addr:full":"990 Montee Sainte-Julie Sainte-Julie QC J3E 1M2",
    "addr:housenumber":"990",
    "addr:postcode":"j3e 1m2",
    "addr:street":"Montee Sainte-Julie",
    "iso:country":"CA",
    "sg:address":"990 Montee Sainte-Julie",
    "sg:city":"Sainte-Julie",
    "sg:classifiers":[
        {
            "category":"Food & Beverages",
            "subcategory":"Groceries & Convenience Stores",
            "type":"Retail Goods"
        }
    ],
    "sg:phone":"+1 450 922 1922",
    "sg:postcode":"J3E 1M2",
    "sg:province":"QC",
    "wof:name":"Depanneur Np Lapierre Enr",
    "wof:placetype":"venue"
},
  "geometry": {"coordinates":[-73.33921051030001,45.5935897827],"type":"Point"}
}