{
  "type": "Feature",
  "properties": {
    "addr:full":"10 Rue Clavette Grand Falls NB E3Y 3W5",
    "addr:housenumber":"10",
    "addr:postcode":"e3y 3w5",
    "addr:street":"Rue Clavette",
    "iso:country":"CA",
    "sg:address":"10 Rue Clavette",
    "sg:city":"Grand Falls",
    "sg:classifiers":[
        {
            "category":"Autos & Motor Vehicles",
            "subcategory":"Auto Supplies",
            "type":"Retail Goods"
        }
    ],
    "sg:phone":"+1 506 475 8122",
    "sg:postcode":"E3Y 3W5",
    "sg:province":"NB",
    "sg:tags":[
        "automobile",
        "parts"
    ],
    "wof:name":"Carquest Auto Parts",
    "wof:placetype":"venue"
},
  "geometry": {"coordinates":[-67.75322723390001,47.0557632446],"type":"Point"}
}