{
  "type": "Feature",
  "properties": {
    "addr:full":"803 20A Ave NE Calgary AB T2E 1S1",
    "addr:postcode":"t2e 1s1",
    "addr:street":"803 20A Ave Ne",
    "iso:country":"CA",
    "sg:address":"803 20A Ave NE",
    "sg:city":"Calgary",
    "sg:classifiers":[
        {
            "category":"Organizations",
            "subcategory":"Religious Organization",
            "type":"Services"
        }
    ],
    "sg:phone":"+1 403 276 8088",
    "sg:postcode":"T2E 1S1",
    "sg:province":"AB",
    "sg:tags":[
        "church"
    ],
    "wof:name":"Church of Christ Northside",
    "wof:placetype":"venue"
},
  "geometry": {"coordinates":[-114.046684,51.070957],"type":"Point"}
}