{
  "type": "Feature",
  "properties": {
    "addr:full":"Richmond BC V6X 3K5",
    "addr:postcode":"v6x 3k5",
    "iso:country":"CA",
    "sg:city":"Richmond",
    "sg:classifiers":[
        {
            "category":"Retail",
            "subcategory":"Laundry & Dry Cleaning",
            "type":"Services"
        }
    ],
    "sg:phone":"+1 604 278 3393",
    "sg:postcode":"V6X 3K5",
    "sg:province":"BC",
    "sg:tags":[
        "cleaners"
    ],
    "wof:name":"Wong's Fine Dry Cleaning",
    "wof:placetype":"venue"
},
  "geometry": {"coordinates":[-123.133072,49.172173],"type":"Point"}
}