{
  "type": "Feature",
  "properties": {
    "addr:full":"179 Simcoe Ave Keswick ON L4P 2H6",
    "addr:housenumber":"179",
    "addr:postcode":"l4p 2h6",
    "addr:street":"Simcoe Ave",
    "iso:country":"CA",
    "sg:address":"179 Simcoe Ave",
    "sg:city":"Keswick",
    "sg:classifiers":[
        {
            "category":"Insurance",
            "subcategory":"Insurance Agent",
            "type":"Services"
        }
    ],
    "sg:phone":"+1 905 476 1717",
    "sg:postcode":"L4P 2H6",
    "sg:province":"ON",
    "wof:name":"Etherington Insurance Brokers",
    "wof:placetype":"venue"
},
  "geometry": {"coordinates":[-79.47351074220001,44.2418441772],"type":"Point"}
}