{
  "type": "Feature",
  "properties": {
    "addr:full":"12450 149 St NW Edmonton AB T5V 1G9",
    "addr:housenumber":"12450",
    "addr:postcode":"t5v 1g9",
    "addr:street":"149 St Nw",
    "iso:country":"CA",
    "sg:address":"12450 149 St NW",
    "sg:city":"Edmonton",
    "sg:classifiers":[
        {
            "category":"Shopping",
            "subcategory":"Department Store",
            "type":"Retail Goods"
        }
    ],
    "sg:phone":"+1 780 455 7575",
    "sg:postcode":"T5V 1G9",
    "sg:province":"AB",
    "sg:tags":[
        "grocer"
    ],
    "wof:name":"Costco Wholesale",
    "wof:placetype":"venue"
},
  "geometry": {"coordinates":[-113.578285217,53.5798683167],"type":"Point"}
}