{
  "type": "Feature",
  "properties": {
    "iso:country":"CA",
    "sg:address":"93 Green Lane",
    "sg:city":"Thornhill",
    "sg:classifiers":[
        {
            "category":"Shopping",
            "subcategory":"Hobbies, Toys, & Games",
            "type":"Retail Goods"
        }
    ],
    "sg:phone":"+1 905 707 7960",
    "sg:postcode":"L3T 6K6",
    "sg:province":"ON",
    "sg:tags":[
        "craft",
        "supply"
    ],
    "wof:name":"J & J Crafts",
    "wof:placetype":"venue"
},
  "geometry": {"coordinates":[-79.392815,43.822941],"type":"Point"}
}