{
  "type": "Feature",
  "properties": {
    "addr:full":"Regina SK S4P 3R9",
    "addr:postcode":"s4p 3r9",
    "iso:country":"CA",
    "sg:city":"Regina",
    "sg:classifiers":[
        {
            "category":"Autos & Motor Vehicles",
            "subcategory":"Recreational Vehicle Sales",
            "type":"Retail Goods"
        }
    ],
    "sg:phone":"+1 306 789 1900",
    "sg:postcode":"S4P 3R9",
    "sg:province":"SK",
    "sg:tags":[
        "automobile"
    ],
    "wof:name":"Mechanix Shop By Rett",
    "wof:placetype":"venue"
},
  "geometry": {"coordinates":[-104.58442700000001,50.447117],"type":"Point"}
}