{
  "type": "Feature",
  "properties": {
    "addr:full":"20 Mcgregor Pl Chatham ON N7M 5J4",
    "addr:housenumber":"20",
    "addr:postcode":"n7m 5j4",
    "addr:street":"Mcgregor Pl",
    "iso:country":"CA",
    "sg:address":"20 Mcgregor Pl",
    "sg:city":"Chatham",
    "sg:classifiers":[
        {
            "category":"Home & Garden",
            "subcategory":"Building Materials",
            "type":"Retail Goods"
        }
    ],
    "sg:phone":"+1 519 352 0720",
    "sg:postcode":"N7M 5J4",
    "sg:province":"ON",
    "sg:tags":[
        "paint"
    ],
    "wof:name":"Decorating Ideas",
    "wof:placetype":"venue"
},
  "geometry": {"coordinates":[-81.99932098390001,42.3359107971],"type":"Point"}
}