{
  "type": "Feature",
  "properties": {
    "addr:full":"858 Westwood St Coquitlam BC V3C 3L2",
    "addr:housenumber":"858",
    "addr:postcode":"bc v3c 3l2",
    "addr:street":"Westwood St",
    "iso:country":"CA",
    "sg:address":"858 Westwood St",
    "sg:city":"Coquitlam",
    "sg:classifiers":[
        {
            "category":"Autos & Motor Vehicles",
            "subcategory":"Fuel & Gas Station",
            "type":"Retail Goods"
        }
    ],
    "sg:phone":"+1 604 464 4535",
    "sg:postcode":"V3C 3L2",
    "sg:province":"BC",
    "sg:tags":[
        "oil"
    ],
    "wof:name":"Jutt Motors",
    "wof:placetype":"venue"
},
  "geometry": {"coordinates":[-122.791351318,49.2649917603],"type":"Point"}
}