{
  "type": "Feature",
  "properties": {
    "addr:full":"400 Collishaw St Moncton NB E1C 0B4",
    "addr:housenumber":"400",
    "addr:postcode":"e1c 0b4",
    "addr:street":"Collishaw St",
    "iso:country":"CA",
    "sg:address":"400 Collishaw St",
    "sg:city":"Moncton",
    "sg:classifiers":[
        {
            "category":"Building & Trades",
            "subcategory":"Construction",
            "type":"Services"
        }
    ],
    "sg:phone":"+1 506 858 9219",
    "sg:postcode":"E1C 0B4",
    "sg:province":"NB",
    "sg:tags":[
        "maker",
        "cabinet"
    ],
    "wof:name":"Wildwood Cabinet Ltd",
    "wof:placetype":"venue"
},
  "geometry": {"coordinates":[-64.814301,46.097031],"type":"Point"}
}