{
  "type": "Feature",
  "properties": {
    "addr:full":"101 Boul Arthur-Sauve Saint-Eustache QC J7P 2A1",
    "addr:housenumber":"101",
    "addr:postcode":"j7p 2a1",
    "addr:street":"Boul Arthur-Sauve",
    "iso:country":"CA",
    "sg:address":"101 Boul Arthur-Sauve",
    "sg:city":"Saint-Eustache",
    "sg:classifiers":[
        {
            "category":"Restaurant",
            "type":"Food & Drink"
        }
    ],
    "sg:phone":"+1 450 472 6835",
    "sg:postcode":"J7P 2A1",
    "sg:province":"QC",
    "wof:name":"Harvey's",
    "wof:placetype":"venue"
},
  "geometry": {"coordinates":[-73.8910751343,45.5620384216],"type":"Point"}
}