{
  "type": "Feature",
  "properties": {
    "iso:country":"CA",
    "sg:address":"23 Bow Village Cres NW",
    "sg:city":"Calgary",
    "sg:classifiers":[
        {
            "category":"Real Estate",
            "subcategory":"Real Estate Agent",
            "type":"Services"
        }
    ],
    "sg:phone":"+1 403 247 1612",
    "sg:postcode":"T3B 4X1",
    "sg:province":"AB",
    "wof:name":"Murray & CO Western Ltd",
    "wof:placetype":"venue"
},
  "geometry": {"coordinates":[-114.193824768,51.0964164734],"type":"Point"}
}