{
  "type": "Feature",
  "properties": {
    "addr:full":"Port-Cartier QC G5B 2M9",
    "addr:postcode":"g5b 2m9",
    "iso:country":"CA",
    "sg:city":"Port-Cartier",
    "sg:classifiers":[
        {
            "category":"Government",
            "subcategory":"Office",
            "type":"Public Place"
        }
    ],
    "sg:phone":"+1 418 766 2524",
    "sg:postcode":"G5B 2M9",
    "sg:province":"QC",
    "wof:name":"Reserve Faunique Port-Cartier",
    "wof:placetype":"venue"
},
  "geometry": {"coordinates":[-66.89078499999999,50.023682],"type":"Point"}
}