{
  "type": "Feature",
  "properties": {
    "addr:full":"18 Rue Principale Packington QC G0L 1Z0",
    "addr:housenumber":"18",
    "addr:postcode":"g0l 1z0",
    "addr:street":"Rue Principale",
    "iso:country":"CA",
    "sg:address":"18 Rue Principale",
    "sg:city":"Packington",
    "sg:classifiers":[
        {
            "category":"Food & Beverages",
            "subcategory":"Groceries & Convenience Stores",
            "type":"Retail Goods"
        }
    ],
    "sg:phone":"+1 418 853 3665",
    "sg:postcode":"G0L 1Z0",
    "sg:province":"QC",
    "sg:tags":[
        "grocer"
    ],
    "wof:name":"Epicerie Des 4 Sous",
    "wof:placetype":"venue"
},
  "geometry": {"coordinates":[-68.78375200000001,47.493156],"type":"Point"}
}