{
  "type": "Feature",
  "properties": {
    "addr:full":"110 Diamond Ave Spruce Grove AB T7X 4C6",
    "addr:housenumber":"110",
    "addr:postcode":"t7x 4c6",
    "addr:street":"Diamond Ave",
    "iso:country":"CA",
    "sg:address":"110 Diamond Ave",
    "sg:city":"Spruce Grove",
    "sg:classifiers":[
        {
            "category":"Freight",
            "type":"Transportation"
        }
    ],
    "sg:phone":"+1 780 962 1543",
    "sg:postcode":"T7X 4C6",
    "sg:province":"AB",
    "sg:tags":[
        "field",
        "oil",
        "trucking"
    ],
    "wof:name":"Pentastar Transportation Ltd",
    "wof:placetype":"venue"
},
  "geometry": {"coordinates":[-113.917640686,53.5353126526],"type":"Point"}
}