{
  "type": "Feature",
  "properties": {
    "iso:country":"CA",
    "sg:address":"728 Victoria Rd S",
    "sg:city":"Guelph",
    "sg:classifiers":[
        {
            "category":"Building & Trades",
            "subcategory":"Construction",
            "type":"Services"
        }
    ],
    "sg:phone":"+1 519 763 6430",
    "sg:postcode":"N1L 1C6",
    "sg:province":"ON",
    "sg:tags":[
        "general",
        "contractor"
    ],
    "wof:name":"Ron Marshall Construction",
    "wof:placetype":"venue"
},
  "geometry": {"coordinates":[-80.20575,43.539104],"type":"Point"}
}