{
  "type": "Feature",
  "properties": {
    "iso:country":"CA",
    "sg:address":"180 Stronach Cres #3B",
    "sg:city":"London",
    "sg:classifiers":[
        {
            "category":"Wholesale",
            "subcategory":"Machinery & Supplies",
            "type":"Manufacturing & Wholesale Goods"
        }
    ],
    "sg:phone":"+1 519 453 5201",
    "sg:postcode":"N5V 3A1",
    "sg:province":"ON",
    "sg:tags":[
        "director",
        "funeral"
    ],
    "wof:name":"Alton Caskets",
    "wof:placetype":"venue"
},
  "geometry": {"coordinates":[-81.187874,43.024334],"type":"Point"}
}