{
  "type": "Feature",
  "properties": {
    "addr:full":"140 Terminal Ave N #7 Nanaimo BC V9S 4J3",
    "addr:housenumber":"140",
    "addr:postcode":"v9s 4j3",
    "addr:street":"Terminal Ave N # 7",
    "iso:country":"CA",
    "sg:address":"140 Terminal Ave N #7",
    "sg:city":"Nanaimo",
    "sg:classifiers":[
        {
            "category":"Professional",
            "subcategory":"Accounting & Tax Preparation",
            "type":"Services"
        }
    ],
    "sg:phone":"+1 250 753 8832",
    "sg:postcode":"V9S 4J3",
    "sg:province":"BC",
    "sg:tags":[
        "consultant",
        "return",
        "filing"
    ],
    "wof:name":"H & R Block Canada Inc",
    "wof:placetype":"venue"
},
  "geometry": {"coordinates":[-123.944923,49.173611],"type":"Point"}
}