{
  "type": "Feature",
  "properties": {
    "addr:full":"305 Moyer Rd Kelowna BC V1X 4R9",
    "addr:housenumber":"305",
    "addr:postcode":"v1x 4r9",
    "addr:street":"Moyer Rd",
    "iso:country":"CA",
    "sg:address":"305 Moyer Rd",
    "sg:city":"Kelowna",
    "sg:classifiers":[
        {
            "category":"Recreation",
            "type":"Entertainment"
        }
    ],
    "sg:phone":"+1 250 491 1709",
    "sg:postcode":"V1X 4R9",
    "sg:province":"BC",
    "sg:tags":[
        "club",
        "baseball"
    ],
    "wof:name":"Rutland Minor Baseball Assn",
    "wof:placetype":"venue"
},
  "geometry": {"coordinates":[-119.378609,49.909042],"type":"Point"}
}