{
  "type": "Feature",
  "properties": {
    "addr:full":"21 Selby Rd Brampton ON L6W 1K5",
    "addr:housenumber":"21",
    "addr:postcode":"l6w 1k5",
    "addr:street":"Selby Rd",
    "iso:country":"CA",
    "sg:address":"21 Selby Rd",
    "sg:city":"Brampton",
    "sg:classifiers":[
        {
            "category":"Retail",
            "subcategory":"Auto Repair",
            "type":"Services"
        }
    ],
    "sg:phone":"+1 905 455 4210",
    "sg:postcode":"L6W 1K5",
    "sg:province":"ON",
    "sg:tags":[
        "cartage"
    ],
    "wof:name":"Alston Cartage Ltd",
    "wof:placetype":"venue"
},
  "geometry": {"coordinates":[-79.727974,43.69009],"type":"Point"}
}