{
  "type": "Feature",
  "properties": {
    "addr:full":"742 Broadview Ave Orillia ON L3V 6P3",
    "addr:housenumber":"742",
    "addr:postcode":"l3v 6p3",
    "addr:street":"Broadview Ave",
    "iso:country":"CA",
    "sg:address":"742 Broadview Ave",
    "sg:city":"Orillia",
    "sg:classifiers":[
        {
            "category":"Retail",
            "subcategory":"Laundry & Dry Cleaning",
            "type":"Services"
        }
    ],
    "sg:phone":"+1 705 327 1560",
    "sg:postcode":"L3V 6P3",
    "sg:province":"ON",
    "sg:tags":[
        "cleaners",
        "rug",
        "carpet"
    ],
    "wof:name":"Specialty Cleaners",
    "wof:placetype":"venue"
},
  "geometry": {"coordinates":[-79.377853,44.615273],"type":"Point"}
}