{
  "type": "Feature",
  "properties": {
    "iso:country":"CA",
    "sg:city":"Ignace",
    "sg:classifiers":[
        {
            "category":"Retail",
            "subcategory":"Auto Repair",
            "type":"Services"
        }
    ],
    "sg:phone":"+1 807 934 6868",
    "sg:postcode":"P0T 1T0",
    "sg:province":"ON",
    "sg:tags":[
        "repairing",
        "automobile",
        "wrecker"
    ],
    "wof:name":"C me Hauler Towing Div",
    "wof:placetype":"venue"
},
  "geometry": {"coordinates":[-91.654716,49.412319],"type":"Point"}
}