{
  "type": "Feature",
  "properties": {
    "addr:full":"2234 Bloor St W Toronto ON M6S 1N6",
    "addr:housenumber":"2234",
    "addr:postcode":"m6s 1n6",
    "addr:street":"Bloor St W",
    "iso:country":"CA",
    "sg:address":"2234 Bloor St W",
    "sg:city":"Toronto",
    "sg:classifiers":[
        {
            "category":"Shopping",
            "subcategory":"Department Store",
            "type":"Retail Goods"
        }
    ],
    "sg:phone":"+1 416 767 3088",
    "sg:postcode":"M6S 1N6",
    "sg:province":"ON",
    "sg:tags":[
        "shop"
    ],
    "wof:name":"Dollar & Bargain",
    "wof:placetype":"venue"
},
  "geometry": {"coordinates":[-79.47705841059999,43.6511001587],"type":"Point"}
}