{
  "type": "Feature",
  "properties": {
    "addr:full":"3304 Keele St North York ON M3M 2H7",
    "addr:housenumber":"3304",
    "addr:postcode":"m3m 2h7",
    "addr:street":"Keele St",
    "iso:country":"CA",
    "sg:address":"3304 Keele St",
    "sg:city":"North York",
    "sg:classifiers":[
        {
            "category":"Wholesale",
            "subcategory":"Machinery & Supplies",
            "type":"Manufacturing & Wholesale Goods"
        }
    ],
    "sg:phone":"+1 416 398 9494",
    "sg:postcode":"M3M 2H7",
    "sg:province":"ON",
    "sg:tags":[
        "salon",
        "beauty"
    ],
    "wof:name":"Beauty Supply Warehouse",
    "wof:placetype":"venue"
},
  "geometry": {"coordinates":[-79.4863357544,43.7438201904],"type":"Point"}
}