{
  "type": "Feature",
  "properties": {
    "addr:full":"Surrey BC V3S 6J9",
    "addr:postcode":"v3s 6j9",
    "iso:country":"CA",
    "sg:city":"Surrey",
    "sg:classifiers":[
        {
            "category":"Professional",
            "subcategory":"Engineering",
            "type":"Services"
        }
    ],
    "sg:phone":"+1 604 574 3336",
    "sg:postcode":"V3S 6J9",
    "sg:province":"BC",
    "sg:tags":[
        "engineer"
    ],
    "wof:name":"Binnie & Assoc",
    "wof:placetype":"venue"
},
  "geometry": {"coordinates":[-122.68930053699999,49.1076545715],"type":"Point"}
}