{
  "type": "Feature",
  "properties": {
    "addr:full":"1155 Appleby Line Burlington ON L7L 5H9",
    "addr:housenumber":"1155",
    "addr:postcode":"l7l 5h9",
    "addr:street":"Appleby Line",
    "iso:country":"CA",
    "sg:address":"1155 Appleby Line",
    "sg:city":"Burlington",
    "sg:classifiers":[
        {
            "category":"Wholesale",
            "subcategory":"Hardware",
            "type":"Manufacturing & Wholesale Goods"
        }
    ],
    "sg:phone":"+1 905 335 8003",
    "sg:postcode":"L7L 5H9",
    "sg:province":"ON",
    "sg:tags":[
        "fastener"
    ],
    "wof:name":"Brafasco",
    "wof:placetype":"venue"
},
  "geometry": {"coordinates":[-79.777199,43.384583],"type":"Point"}
}