{
  "type": "Feature",
  "properties": {
    "addr:full":"215 Rue DE Woodstock Saint-Lambert QC J4P 1W7",
    "addr:housenumber":"215",
    "addr:postcode":"j4p 1w7",
    "addr:street":"Rue De Woodstock",
    "iso:country":"CA",
    "sg:address":"215 Rue DE Woodstock",
    "sg:city":"Saint-Lambert",
    "sg:classifiers":[
        {
            "category":"Shopping",
            "subcategory":"Clothing, Apparel, & Fashions",
            "type":"Retail Goods"
        }
    ],
    "sg:phone":"+1 450 923 4938",
    "sg:postcode":"J4P 1W7",
    "sg:province":"QC",
    "sg:tags":[
        "infant"
    ],
    "wof:name":"Pirouette",
    "wof:placetype":"venue"
},
  "geometry": {"coordinates":[-73.509834,45.50053],"type":"Point"}
}