{
  "type": "Feature",
  "properties": {
    "addr:full":"220 3 Ave S # 305 Lethbridge AB T1J 0G9",
    "addr:housenumber":"220",
    "addr:postcode":"t1j 0g9",
    "addr:street":"3 Ave S # 305",
    "iso:country":"CA",
    "sg:address":"220 3 Ave S # 305",
    "sg:city":"Lethbridge",
    "sg:classifiers":[
        {
            "category":"Real Estate",
            "subcategory":"Real Estate Agent",
            "type":"Services"
        }
    ],
    "sg:phone":"+1 403 329 3777",
    "sg:postcode":"T1J 0G9",
    "sg:province":"AB",
    "sg:tags":[
        "management"
    ],
    "wof:name":"Braemore Management Ltd",
    "wof:placetype":"venue"
},
  "geometry": {"coordinates":[-112.843536,49.695576],"type":"Point"}
}