{
  "type": "Feature",
  "properties": {
    "addr:full":"143 Sackville Dr Lower Sackville NS B4C 2R3",
    "addr:housenumber":"143",
    "addr:postcode":"b4c 2r3",
    "addr:street":"Sackville Dr",
    "iso:country":"CA",
    "sg:address":"143 Sackville Dr",
    "sg:city":"Lower Sackville",
    "sg:classifiers":[
        {
            "category":"Home & Garden",
            "subcategory":"Garden Supply",
            "type":"Retail Goods"
        }
    ],
    "sg:phone":"+1 902 865 6306",
    "sg:postcode":"B4C 2R3",
    "sg:province":"NS",
    "sg:tags":[
        "lawn",
        "mower"
    ],
    "wof:name":"Sackville Small Engine Ctr",
    "wof:placetype":"venue"
},
  "geometry": {"coordinates":[-63.666935,44.755661],"type":"Point"}
}