{
  "type": "Feature",
  "properties": {
    "iso:country":"CA",
    "sg:address":"438 Dewitt Rd",
    "sg:city":"Stoney Creek",
    "sg:classifiers":[
        {
            "category":"Retail",
            "subcategory":"Auto Repair",
            "type":"Services"
        }
    ],
    "sg:phone":"+1 905 662 2135",
    "sg:postcode":"L8E 4C4",
    "sg:province":"ON",
    "sg:tags":[
        "repairing",
        "automobile",
        "welding"
    ],
    "wof:name":"Viau's Custom Welding",
    "wof:placetype":"venue"
},
  "geometry": {"coordinates":[-79.70556640620001,43.2329216003],"type":"Point"}
}