{
  "type": "Feature",
  "properties": {
    "iso:country":"CA",
    "sg:city":"Montreal-Est",
    "sg:classifiers":[
        {
            "category":"Wholesale",
            "subcategory":"Electrical",
            "type":"Manufacturing & Wholesale Goods"
        }
    ],
    "sg:phone":"+1 514 645 1502",
    "sg:postcode":"H1B 4T2",
    "sg:province":"QC",
    "sg:tags":[
        "lighting",
        "fixture"
    ],
    "wof:name":"Technilux Inc",
    "wof:placetype":"venue"
},
  "geometry": {"coordinates":[-73.49616241459999,45.633354187],"type":"Point"}
}