{
  "type": "Feature",
  "properties": {
    "iso:country":"CA",
    "sg:address":"568 Fortye Dr",
    "sg:city":"Peterborough",
    "sg:classifiers":[
        {
            "category":"Building & Trades",
            "subcategory":"Construction",
            "type":"Services"
        }
    ],
    "sg:phone":"+1 705 742 2292",
    "sg:postcode":"K9K 2H2",
    "sg:province":"ON",
    "sg:tags":[
        "plastering",
        "dry wall",
        "contractor"
    ],
    "wof:name":"C W Cunningham Plaster Drywall",
    "wof:placetype":"venue"
},
  "geometry": {"coordinates":[-78.361313,44.266548],"type":"Point"}
}