{
  "type": "Feature",
  "properties": {
    "addr:full":"95 Boul Panoramique Dolbeau-Mistassini QC G8L 5G8",
    "addr:housenumber":"95",
    "addr:postcode":"g8l 5g8",
    "addr:street":"Boul Panoramique",
    "iso:country":"CA",
    "sg:address":"95 Boul Panoramique",
    "sg:city":"Dolbeau-Mistassini",
    "sg:classifiers":[
        {
            "category":"Organizations",
            "subcategory":"Professional Association",
            "type":"Services"
        }
    ],
    "sg:phone":"+1 418 239 0080",
    "sg:postcode":"G8L 5G8",
    "sg:province":"QC",
    "sg:tags":[
        "club"
    ],
    "wof:name":"Club Conseil Bleunet Inc",
    "wof:placetype":"venue"
},
  "geometry": {"coordinates":[-72.207649231,48.8939933777],"type":"Point"}
}