{
  "type": "Feature",
  "properties": {
    "addr:full":"Come By Chance Rd Come By Chance NL A0B 1N0",
    "addr:postcode":"a0b 1n0",
    "addr:street":"Come By Chance Rd",
    "iso:country":"CA",
    "sg:address":"Come By Chance Rd",
    "sg:city":"Come By Chance",
    "sg:classifiers":[
        {
            "category":"Mining & Drilling",
            "type":"Manufacturing & Wholesale Goods"
        }
    ],
    "sg:phone":"+1 709 463 8811",
    "sg:postcode":"A0B 1N0",
    "sg:province":"NL",
    "sg:tags":[
        "oil",
        "gas",
        "producer"
    ],
    "wof:name":"North Atlantic Refining Ltd",
    "wof:placetype":"venue"
},
  "geometry": {"coordinates":[-53.998474,47.802681],"type":"Point"}
}