{
  "type": "Feature",
  "properties": {
    "addr:full":"13520 105 Ave Surrey BC V3T 1Z6",
    "addr:housenumber":"13520",
    "addr:postcode":"v3t 1z6",
    "addr:street":"105 Ave",
    "iso:country":"CA",
    "sg:address":"13520 105 Ave",
    "sg:city":"Surrey",
    "sg:classifiers":[
        {
            "category":"Retail",
            "subcategory":"Auto Repair",
            "type":"Services"
        }
    ],
    "sg:phone":"+1 604 581 6313",
    "sg:postcode":"V3T 1Z6",
    "sg:province":"BC",
    "sg:tags":[
        "body",
        "automobile",
        "painting"
    ],
    "wof:name":"T J Auto Body Glass Odyssey",
    "wof:placetype":"venue"
},
  "geometry": {"coordinates":[-122.847748,49.192924],"type":"Point"}
}