{
  "type": "Feature",
  "properties": {
    "iso:country":"CA",
    "sg:address":"628 Beresford Ave",
    "sg:city":"York",
    "sg:classifiers":[
        {
            "category":"Building & Trades",
            "subcategory":"Landscaping Services",
            "type":"Services"
        }
    ],
    "sg:phone":"+1 416 536 2637",
    "sg:postcode":"M6S 3C3",
    "sg:province":"ON",
    "sg:tags":[
        "landscape",
        "contractor"
    ],
    "wof:name":"Arcadia Gardening & Landscape",
    "wof:placetype":"venue"
},
  "geometry": {"coordinates":[-79.482552,43.662586],"type":"Point"}
}