{
  "type": "Feature",
  "properties": {
    "addr:full":"Mississauga ON L5T 2B4",
    "addr:postcode":"l5t 2b4",
    "iso:country":"CA",
    "sg:city":"Mississauga",
    "sg:classifiers":[
        {
            "category":"Retail",
            "subcategory":"Auto Repair",
            "type":"Services"
        }
    ],
    "sg:phone":"+1 905 670 9625",
    "sg:postcode":"L5T 2B4",
    "sg:province":"ON",
    "sg:tags":[
        "repairing",
        "automobile",
        "radiator"
    ],
    "wof:name":"Clements Radiator & Spring Svc",
    "wof:placetype":"venue"
},
  "geometry": {"coordinates":[-79.652534,43.656075],"type":"Point"}
}