{
  "type": "Feature",
  "properties": {
    "iso:country":"CA",
    "sg:address":"79 Main St S",
    "sg:city":"Georgetown",
    "sg:classifiers":[
        {
            "category":"Travel",
            "subcategory":"Hotels & Motels",
            "type":"Entertainment"
        }
    ],
    "sg:phone":"+1 905 877 3388",
    "sg:postcode":"L7G 3G2",
    "sg:province":"ON",
    "wof:name":"Mc Gibbon Hotel",
    "wof:placetype":"venue"
},
  "geometry": {"coordinates":[-79.926071167,43.6495246887],"type":"Point"}
}