{
  "type": "Feature",
  "properties": {
    "addr:full":"201 Main St Oyen AB T0J 2J0",
    "addr:housenumber":"201",
    "addr:postcode":"t0j 2j0",
    "addr:street":"Main St",
    "iso:country":"CA",
    "sg:address":"201 Main St",
    "sg:city":"Oyen",
    "sg:classifiers":[
        {
            "category":"Government",
            "subcategory":"Office",
            "type":"Public Place"
        }
    ],
    "sg:phone":"+1 403 664 3511",
    "sg:postcode":"T0J 2J0",
    "sg:province":"AB",
    "sg:tags":[
        "municipality"
    ],
    "wof:name":"Oyen Town Office",
    "wof:placetype":"venue"
},
  "geometry": {"coordinates":[-110.483482361,51.3548049927],"type":"Point"}
}