{
  "type": "Feature",
  "properties": {
    "addr:full":"264 Doyon Saint-Victor QC G0M 2B0",
    "addr:housenumber":"264",
    "addr:postcode":"g0m 2b0",
    "addr:street":"Doyon",
    "iso:country":"CA",
    "sg:address":"264 Doyon",
    "sg:city":"Saint-Victor",
    "sg:classifiers":[
        {
            "category":"Building & Trades",
            "subcategory":"Construction",
            "type":"Services"
        }
    ],
    "sg:phone":"+1 418 588 2521",
    "sg:postcode":"G0M 2B0",
    "sg:province":"QC",
    "sg:tags":[
        "general",
        "contractor"
    ],
    "wof:name":"Prevost & Freres Construction",
    "wof:placetype":"venue"
},
  "geometry": {"coordinates":[-70.903412,46.139774],"type":"Point"}
}