{
  "type": "Feature",
  "properties": {
    "iso:country":"CA",
    "sg:address":"451 Daly Ave",
    "sg:city":"Ottawa",
    "sg:classifiers":[
        {
            "category":"Real Estate",
            "subcategory":"Real Estate Agent",
            "type":"Services"
        }
    ],
    "sg:phone":"+1 613 244 1012",
    "sg:postcode":"K1N 6H6",
    "sg:province":"ON",
    "sg:tags":[
        "management"
    ],
    "wof:name":"Elk Property Management",
    "wof:placetype":"venue"
},
  "geometry": {"coordinates":[-75.673851,45.432209],"type":"Point"}
}