{
  "type": "Feature",
  "properties": {
    "addr:full":"3089 Bathurst St North York ON M6A 2A4",
    "addr:housenumber":"3089",
    "addr:postcode":"m6a 2a4",
    "addr:street":"Bathurst St",
    "iso:country":"CA",
    "sg:address":"3089 Bathurst St",
    "sg:city":"North York",
    "sg:classifiers":[
        {
            "category":"Professional",
            "subcategory":"Business Services",
            "type":"Services"
        }
    ],
    "sg:phone":"+1 416 783 8800",
    "sg:postcode":"M6A 2A4",
    "sg:province":"ON",
    "sg:tags":[
        "inventory"
    ],
    "wof:name":"J T Roberts Sales Ltd",
    "wof:placetype":"venue"
},
  "geometry": {"coordinates":[-79.4298171997,43.7203903198],"type":"Point"}
}