{
  "type": "Feature",
  "properties": {
    "addr:full":"537 Hwy 72 Sioux Lookout ON P8T 1A5",
    "addr:housenumber":"537",
    "addr:postcode":"p8t 1a5",
    "addr:street":"Hwy 72",
    "iso:country":"CA",
    "sg:address":"537 Hwy 72",
    "sg:city":"Sioux Lookout",
    "sg:classifiers":[
        {
            "category":"Travel",
            "subcategory":"Campground",
            "type":"Entertainment"
        }
    ],
    "sg:phone":"+1 807 737 3580",
    "sg:postcode":"P8T 1A5",
    "sg:province":"ON",
    "sg:tags":[
        "camp"
    ],
    "wof:name":"Northumbrian Tourist Camp",
    "wof:placetype":"venue"
},
  "geometry": {"coordinates":[-91.9727935791,50.0577087402],"type":"Point"}
}