{
  "type": "Feature",
  "properties": {
    "iso:country":"CA",
    "sg:city":"Saskatoon",
    "sg:classifiers":[
        {
            "category":"Health Services",
            "subcategory":"Medical Lab",
            "type":"Services"
        }
    ],
    "sg:phone":"+1 306 978 3355",
    "sg:postcode":"S7L 6Y4",
    "sg:province":"SK",
    "sg:tags":[
        "x",
        "laboratory"
    ],
    "wof:name":"Wedge Road X-Ray",
    "wof:placetype":"venue"
},
  "geometry": {"coordinates":[-106.72631072999999,52.1451644897],"type":"Point"}
}