{
  "type": "Feature",
  "properties": {
    "addr:full":"110 DE LA Plage Saint-Gedeon QC G0W 2P0",
    "addr:housenumber":"110",
    "addr:postcode":"g0w 2p0",
    "addr:street":"De La Plage Saint-Gedeon",
    "iso:country":"CA",
    "sg:address":"110 DE LA Plage",
    "sg:city":"Saint-Gedeon",
    "sg:classifiers":[
        {
            "category":"Restaurant",
            "type":"Food & Drink"
        }
    ],
    "sg:phone":"+1 418 345 8328",
    "sg:postcode":"G0W 2P0",
    "sg:province":"QC",
    "sg:tags":[
        "parlor",
        "ice",
        "cream"
    ],
    "wof:name":"Bar Laitier Le Frimas",
    "wof:placetype":"venue"
},
  "geometry": {"coordinates":[-71.77376599999999,48.497849],"type":"Point"}
}