{
  "type": "Feature",
  "properties": {
    "iso:country":"CA",
    "sg:address":"77 Boul Saint-Joseph O",
    "sg:city":"Montreal",
    "sg:classifiers":[
        {
            "category":"Wholesale",
            "subcategory":"Office Equipment",
            "type":"Manufacturing & Wholesale Goods"
        }
    ],
    "sg:phone":"+1 514 874 2007",
    "sg:postcode":"H2T 2P5",
    "sg:province":"QC",
    "sg:tags":[
        "accounting",
        "accountant",
        "bookkeeping",
        "system"
    ],
    "wof:name":"Gestion Mosand",
    "wof:placetype":"venue"
},
  "geometry": {"coordinates":[-73.5908660889,45.523273468],"type":"Point"}
}