{
  "type": "Feature",
  "properties": {
    "addr:full":"3500 Mainway Burlington ON L7M 1A8",
    "addr:housenumber":"3500",
    "addr:postcode":"l7m 1a8",
    "addr:street":"Mainway",
    "iso:country":"CA",
    "sg:address":"3500 Mainway",
    "sg:city":"Burlington",
    "sg:classifiers":[
        {
            "category":"Professional",
            "subcategory":"Detective & Security Services",
            "type":"Services"
        }
    ],
    "sg:phone":"+1 905 335 4313",
    "sg:postcode":"L7M 1A8",
    "sg:province":"ON",
    "sg:tags":[
        "guard",
        "patrol",
        "investigator"
    ],
    "wof:name":"Total Investigation Svc Ltd",
    "wof:placetype":"venue"
},
  "geometry": {"coordinates":[-79.7975387573,43.3698768616],"type":"Point"}
}