{
  "type": "Feature",
  "properties": {
    "addr:full":"Stoney Creek ON L8G 2C5",
    "addr:postcode":"l8g 2c5",
    "iso:country":"CA",
    "sg:city":"Stoney Creek",
    "sg:classifiers":[
        {
            "category":"Health Services",
            "subcategory":"Doctor",
            "type":"Services"
        }
    ],
    "sg:phone":"+1 905 662 1234",
    "sg:postcode":"L8G 2C5",
    "sg:province":"ON",
    "sg:tags":[
        "physician",
        "surgeon"
    ],
    "wof:name":"Schweitzer, M MD",
    "wof:placetype":"venue"
},
  "geometry": {"coordinates":[-79.774506,43.177597],"type":"Point"}
}