{
  "type": "Feature",
  "properties": {
    "addr:full":"Nanton AB T0L 1R0",
    "addr:postcode":"t0l 1r0",
    "iso:country":"CA",
    "sg:city":"Nanton",
    "sg:classifiers":[
        {
            "category":"Manufacturing",
            "subcategory":"Metals",
            "type":"Manufacturing & Wholesale Goods"
        }
    ],
    "sg:phone":"+1 403 646 2244",
    "sg:postcode":"T0L 1R0",
    "sg:province":"AB",
    "sg:tags":[
        "ornamental",
        "work"
    ],
    "wof:name":"Willow Creek Forge Gallery",
    "wof:placetype":"venue"
},
  "geometry": {"coordinates":[-113.771850586,50.348690033],"type":"Point"}
}