{
  "type": "Feature",
  "properties": {
    "iso:country":"CA",
    "sg:city":"Hunter River",
    "sg:classifiers":[
        {
            "category":"Professional",
            "subcategory":"Accounting & Tax Preparation",
            "type":"Services"
        }
    ],
    "sg:phone":"+1 902 964 2225",
    "sg:postcode":"C0A 1N0",
    "sg:province":"PE",
    "sg:tags":[
        "bookkeeping",
        "general"
    ],
    "wof:name":"Clyde View Girl Friday",
    "wof:placetype":"venue"
},
  "geometry": {"coordinates":[-63.343147,46.351761],"type":"Point"}
}