{
  "type": "Feature",
  "properties": {
    "addr:full":"1911 105 St NW Edmonton AB T6J 5V9",
    "addr:housenumber":"1911",
    "addr:postcode":"t6j 5v9",
    "addr:street":"105 St Nw",
    "iso:country":"CA",
    "sg:address":"1911 105 St NW",
    "sg:city":"Edmonton",
    "sg:classifiers":[
        {
            "category":"Retail",
            "subcategory":"Laundry & Dry Cleaning",
            "type":"Services"
        }
    ],
    "sg:phone":"+1 780 438 1356",
    "sg:postcode":"T6J 5V9",
    "sg:province":"AB",
    "sg:tags":[
        "cleaners"
    ],
    "wof:name":"Sparky's Drycleaners",
    "wof:placetype":"venue"
},
  "geometry": {"coordinates":[-113.50097700000001,53.448547],"type":"Point"}
}