{
  "type": "Feature",
  "properties": {
    "iso:country":"CA",
    "sg:address":"308 King St",
    "sg:city":"Midland",
    "sg:classifiers":[
        {
            "category":"Organizations",
            "subcategory":"Religious Organization",
            "type":"Services"
        }
    ],
    "sg:phone":"+1 705 526 6077",
    "sg:postcode":"L4R 3M6",
    "sg:province":"ON",
    "sg:tags":[
        "church"
    ],
    "wof:name":"St Paul's United Church",
    "wof:placetype":"venue"
},
  "geometry": {"coordinates":[-79.8849029541,44.7490692139],"type":"Point"}
}