{
  "type": "Feature",
  "properties": {
    "addr:full":"Bromont QC J2L 2N8",
    "addr:postcode":"j2l 2n8",
    "iso:country":"CA",
    "sg:city":"Bromont",
    "sg:classifiers":[
        {
            "category":"Shopping",
            "subcategory":"Computers & Home Electronics",
            "type":"Retail Goods"
        }
    ],
    "sg:phone":"+1 450 534 5336",
    "sg:postcode":"J2L 2N8",
    "sg:province":"QC",
    "sg:tags":[
        "software"
    ],
    "wof:name":"N B Automation Inc",
    "wof:placetype":"venue"
},
  "geometry": {"coordinates":[-72.657265,45.316086],"type":"Point"}
}