{
  "type": "Feature",
  "properties": {
    "addr:full":"Calgary AB T2K 5Y4",
    "addr:postcode":"t2k 5y4",
    "iso:country":"CA",
    "sg:city":"Calgary",
    "sg:classifiers":[
        {
            "category":"Retail",
            "subcategory":"Repair Shop",
            "type":"Services"
        }
    ],
    "sg:phone":"+1 403 295 0055",
    "sg:postcode":"T2K 5Y4",
    "sg:province":"AB",
    "sg:tags":[
        "steel",
        "welding"
    ],
    "wof:name":"Aero-Tech Specialty Welding",
    "wof:placetype":"venue"
},
  "geometry": {"coordinates":[-114.04846999999999,51.10083],"type":"Point"}
}