{
  "type": "Feature",
  "properties": {
    "addr:full":"435 Bond St E Oshawa ON L1G 1B9",
    "addr:housenumber":"435",
    "addr:postcode":"l1g 1b9",
    "addr:street":"Bond St E",
    "iso:country":"CA",
    "sg:address":"435 Bond St E",
    "sg:city":"Oshawa",
    "sg:classifiers":[
        {
            "category":"Education",
            "subcategory":"Dance Studio",
            "type":"Public Place"
        }
    ],
    "sg:phone":"+1 905 723 0593",
    "sg:postcode":"L1G 1B9",
    "sg:province":"ON",
    "sg:tags":[
        "instruction",
        "dancing"
    ],
    "wof:name":"Theatre Dance Academy",
    "wof:placetype":"venue"
},
  "geometry": {"coordinates":[-78.848465,43.902802],"type":"Point"}
}