{
  "type": "Feature",
  "properties": {
    "addr:full":"389 Rue Preising Saint-Eustache QC J7R 2X7",
    "addr:housenumber":"389",
    "addr:postcode":"j7r 2x7",
    "addr:street":"Rue Preising",
    "iso:country":"CA",
    "sg:address":"389 Rue Preising",
    "sg:city":"Saint-Eustache",
    "sg:classifiers":[
        {
            "category":"Building & Trades",
            "subcategory":"Construction",
            "type":"Services"
        }
    ],
    "sg:phone":"+1 450 473 8528",
    "sg:postcode":"J7R 2X7",
    "sg:province":"QC",
    "sg:tags":[
        "contractor"
    ],
    "wof:name":"Construction Rejean Couture",
    "wof:placetype":"venue"
},
  "geometry": {"coordinates":[-73.9103317261,45.5651435852],"type":"Point"}
}