{
  "type": "Feature",
  "properties": {
    "addr:full":"339 Rue Du Moulin Tracadie-Sheila NB E1X 1A4",
    "addr:housenumber":"339",
    "addr:postcode":"e1x 1a4",
    "addr:street":"Rue Du Moulin",
    "iso:country":"CA",
    "sg:address":"339 Rue Du Moulin",
    "sg:city":"Tracadie-Sheila",
    "sg:classifiers":[
        {
            "category":"Insurance",
            "subcategory":"Insurance Agent",
            "type":"Services"
        }
    ],
    "sg:phone":"+1 506 395 6313",
    "sg:postcode":"E1X 1A4",
    "sg:province":"NB",
    "wof:name":"Assurance Mourant Ltee",
    "wof:placetype":"venue"
},
  "geometry": {"coordinates":[-64.917297,47.522678],"type":"Point"}
}