{
  "type": "Feature",
  "properties": {
    "addr:full":"856 Danforth Ave Toronto ON M4J 1L7",
    "addr:housenumber":"856",
    "addr:postcode":"m4j 1l7",
    "addr:street":"Danforth Ave",
    "iso:country":"CA",
    "sg:address":"856 Danforth Ave",
    "sg:city":"Toronto",
    "sg:classifiers":[
        {
            "category":"Retail",
            "subcategory":"Laundry & Dry Cleaning",
            "type":"Services"
        }
    ],
    "sg:phone":"+1 416 405 8221",
    "sg:postcode":"M4J 1L7",
    "sg:province":"ON",
    "sg:tags":[
        "cleaners"
    ],
    "wof:name":"Megas Cleaners",
    "wof:placetype":"venue"
},
  "geometry": {"coordinates":[-79.3403015137,43.67993927],"type":"Point"}
}