{
  "type": "Feature",
  "properties": {
    "addr:full":"2117 25th St Nanton AB T0L 1R0",
    "addr:housenumber":"2117",
    "addr:postcode":"t0l 1r0",
    "addr:street":"25Th St",
    "iso:country":"CA",
    "sg:address":"2117 25th St",
    "sg:city":"Nanton",
    "sg:classifiers":[
        {
            "category":"Wholesale",
            "subcategory":"Farm Supplies",
            "type":"Manufacturing & Wholesale Goods"
        }
    ],
    "sg:phone":"+1 403 646 2595",
    "sg:postcode":"T0L 1R0",
    "sg:province":"AB",
    "sg:tags":[
        "equipment",
        "livestock"
    ],
    "wof:name":"Cattlemen's Corner",
    "wof:placetype":"venue"
},
  "geometry": {"coordinates":[-113.767601013,50.3443832397],"type":"Point"}
}