{
  "type": "Feature",
  "properties": {
    "addr:full":"Scarborough ON M1S 2B7",
    "addr:postcode":"m1s 2b7",
    "iso:country":"CA",
    "sg:city":"Scarborough",
    "sg:classifiers":[
        {
            "category":"Wholesale",
            "subcategory":"Drugs",
            "type":"Manufacturing & Wholesale Goods"
        }
    ],
    "sg:phone":"+1 416 321 6167",
    "sg:postcode":"M1S 2B7",
    "sg:province":"ON",
    "sg:tags":[
        "cosmetic"
    ],
    "wof:name":"Citiart CO",
    "wof:placetype":"venue"
},
  "geometry": {"coordinates":[-79.27578,43.786694],"type":"Point"}
}