{
  "type": "Feature",
  "properties": {
    "iso:country":"CA",
    "sg:city":"Concord",
    "sg:classifiers":[
        {
            "category":"Manufacturing",
            "subcategory":"Paper Products",
            "type":"Manufacturing & Wholesale Goods"
        }
    ],
    "sg:phone":"+1 905 760 9922",
    "sg:postcode":"L4K 1J5",
    "sg:province":"ON",
    "sg:tags":[
        "converter"
    ],
    "wof:name":"B T Paper Sales & Converting",
    "wof:placetype":"venue"
},
  "geometry": {"coordinates":[-79.49723052980001,43.81615448],"type":"Point"}
}