{
  "type": "Feature",
  "properties": {
    "addr:full":"Farm Carrot River SK S0E 0L0",
    "addr:postcode":"s0e 0l0",
    "iso:country":"CA",
    "sg:address":"Farm",
    "sg:city":"Carrot River",
    "sg:classifiers":[
        {
            "category":"Shopping",
            "type":"Retail Goods"
        }
    ],
    "sg:phone":"+1 306 768 2681",
    "sg:postcode":"S0E 0L0",
    "sg:province":"SK",
    "sg:tags":[
        "cosmetic",
        "perfume"
    ],
    "wof:name":"Mary Kay Cosmetics",
    "wof:placetype":"venue"
},
  "geometry": {"coordinates":[-103.587532,53.28336],"type":"Point"}
}