{
  "type": "Feature",
  "properties": {
    "addr:full":"2115 Grand Pre Rd Grand Pre NS B0P 1M0",
    "addr:housenumber":"2115",
    "addr:postcode":"b0p 1m0",
    "addr:street":"Grand Pre Rd",
    "iso:country":"CA",
    "sg:address":"2115 Grand Pre Rd",
    "sg:city":"Grand Pre",
    "sg:classifiers":[
        {
            "category":"Shopping",
            "subcategory":"Gifts & Souvenirs",
            "type":"Retail Goods"
        }
    ],
    "sg:phone":"+1 902 542 3609",
    "sg:postcode":"B0P 1M0",
    "sg:province":"NS",
    "sg:tags":[
        "shop",
        "glass"
    ],
    "wof:name":"Fancy Glass & Crafts",
    "wof:placetype":"venue"
},
  "geometry": {"coordinates":[-64.30722045900001,45.1055603027],"type":"Point"}
}