{
  "type": "Feature",
  "properties": {
    "addr:full":"1610 Midland Ave Scarborough ON M1P 3C2",
    "addr:housenumber":"1610",
    "addr:postcode":"m1p 3c2",
    "addr:street":"Midland Ave",
    "iso:country":"CA",
    "sg:address":"1610 Midland Ave",
    "sg:city":"Scarborough",
    "sg:classifiers":[
        {
            "category":"Wholesale",
            "subcategory":"Non-durable Goods",
            "type":"Manufacturing & Wholesale Goods"
        }
    ],
    "sg:phone":"+1 416 285 0900",
    "sg:postcode":"M1P 3C2",
    "sg:province":"ON",
    "sg:tags":[
        "glassware",
        "chinaware"
    ],
    "wof:name":"Aurora Collectibles Fine China",
    "wof:placetype":"venue"
},
  "geometry": {"coordinates":[-79.267044,43.75642],"type":"Point"}
}