{
  "type": "Feature",
  "properties": {
    "addr:full":"8540 Rue Lafrenaie Saint-Leonard QC H1P 2B4",
    "addr:housenumber":"8540",
    "addr:postcode":"h1p 2b4",
    "addr:street":"Rue Lafrenaie",
    "iso:country":"CA",
    "sg:address":"8540 Rue Lafrenaie",
    "sg:city":"Saint-Leonard",
    "sg:classifiers":[
        {
            "category":"Retail",
            "subcategory":"Auto Repair",
            "type":"Services"
        }
    ],
    "sg:phone":"+1 514 327 5415",
    "sg:postcode":"H1P 2B4",
    "sg:province":"QC",
    "sg:tags":[
        "repairing",
        "automobile"
    ],
    "wof:name":"R G Auto Electric",
    "wof:placetype":"venue"
},
  "geometry": {"coordinates":[-73.588539,45.599136],"type":"Point"}
}