{
  "type": "Feature",
  "properties": {
    "addr:full":"2449 Dunwin Dr Mississauga ON L5L 1T1",
    "addr:housenumber":"2449",
    "addr:postcode":"l5l 1t1",
    "addr:street":"Dunwin Dr",
    "iso:country":"CA",
    "sg:address":"2449 Dunwin Dr",
    "sg:city":"Mississauga",
    "sg:classifiers":[
        {
            "category":"Social Services",
            "subcategory":"Child Care",
            "type":"Services"
        }
    ],
    "sg:phone":"+1 905 569 3112",
    "sg:postcode":"L5L 1T1",
    "sg:province":"ON",
    "wof:name":"Kaban Montessori Inc",
    "wof:placetype":"venue"
},
  "geometry": {"coordinates":[-79.679596,43.530865],"type":"Point"}
}