{
  "type": "Feature",
  "properties": {
    "addr:full":"12 Knickle Rd Lunenburg NS B0J 2C0",
    "addr:housenumber":"12",
    "addr:postcode":"b0j 2c0",
    "addr:street":"Knickle Rd",
    "iso:country":"CA",
    "sg:address":"12 Knickle Rd",
    "sg:city":"Lunenburg",
    "sg:classifiers":[
        {
            "category":"Education",
            "subcategory":"School",
            "type":"Public Place"
        }
    ],
    "sg:phone":"+1 902 634 2230",
    "sg:postcode":"B0J 2C0",
    "sg:province":"NS",
    "wof:name":"Lunenburg Jr/Sr High School",
    "wof:placetype":"venue"
},
  "geometry": {"coordinates":[-64.31991600000001,44.37484],"type":"Point"}
}