{
  "type": "Feature",
  "properties": {
    "addr:full":"145 Rue Du Tremblay Sainte-Anne-DE-LA-Perade QC G0X 2J0",
    "addr:housenumber":"145",
    "addr:postcode":"g0x 2j0",
    "addr:street":"Rue Du Tremblay",
    "iso:country":"CA",
    "sg:address":"145 Rue Du Tremblay",
    "sg:city":"Sainte-Anne-DE-LA-Perade",
    "sg:classifiers":[
        {
            "category":"Social Services",
            "subcategory":"Child Care",
            "type":"Services"
        }
    ],
    "sg:phone":"+1 418 325 3414",
    "sg:postcode":"G0X 2J0",
    "sg:province":"QC",
    "wof:name":"Centre DE LA Petite Enfance",
    "wof:placetype":"venue"
},
  "geometry": {"coordinates":[-72.210953,46.568695],"type":"Point"}
}