{
  "type": "Feature",
  "properties": {
    "addr:full":"185 Manitoba St Bracebridge ON P1L 1S3",
    "addr:housenumber":"185",
    "addr:postcode":"p1l 1s3",
    "addr:street":"Manitoba St",
    "iso:country":"CA",
    "sg:address":"185 Manitoba St",
    "sg:city":"Bracebridge",
    "sg:classifiers":[
        {
            "category":"Shopping",
            "subcategory":"Used Merchandise",
            "type":"Retail Goods"
        }
    ],
    "sg:phone":"+1 705 645 5961",
    "sg:postcode":"P1L 1S3",
    "sg:province":"ON",
    "sg:tags":[
        "second",
        "store",
        "hand"
    ],
    "wof:name":"Salvation Army Thrift Store",
    "wof:placetype":"venue"
},
  "geometry": {"coordinates":[-79.31573486329999,45.0439720154],"type":"Point"}
}