{
  "type": "Feature",
  "properties": {
    "addr:full":"5123 4 Ave Edson AB T7E 1T6",
    "addr:housenumber":"5123",
    "addr:postcode":"t7e 1t6",
    "addr:street":"4 Ave",
    "iso:country":"CA",
    "sg:address":"5123 4 Ave",
    "sg:city":"Edson",
    "sg:classifiers":[
        {
            "category":"Autos & Motor Vehicles",
            "subcategory":"Automobile Sales",
            "type":"Retail Goods"
        }
    ],
    "sg:phone":"+1 780 723 6608",
    "sg:postcode":"T7E 1T6",
    "sg:province":"AB",
    "sg:tags":[
        "car",
        "dealer"
    ],
    "wof:name":"Gateway Honda & Ski-Doo",
    "wof:placetype":"venue"
},
  "geometry": {"coordinates":[-116.43504299999999,53.582268],"type":"Point"}
}