{
  "type": "Feature",
  "properties": {
    "addr:full":"950 Wyandotte St W Windsor ON N9A 5Y2",
    "addr:housenumber":"950",
    "addr:postcode":"n9a 5y2",
    "addr:street":"Wyandotte St W",
    "iso:country":"CA",
    "sg:address":"950 Wyandotte St W",
    "sg:city":"Windsor",
    "sg:classifiers":[
        {
            "category":"Restaurant",
            "type":"Food & Drink"
        }
    ],
    "sg:phone":"+1 519 253 9595",
    "sg:postcode":"N9A 5Y2",
    "sg:province":"ON",
    "wof:name":"Szechuan Garden Restaurant",
    "wof:placetype":"venue"
},
  "geometry": {"coordinates":[-83.047676,42.310383],"type":"Point"}
}