{
  "type": "Feature",
  "properties": {
    "iso:country":"CA",
    "sg:address":"34 Jardine Cres",
    "sg:city":"Creemore",
    "sg:classifiers":[
        {
            "category":"Building & Trades",
            "subcategory":"Construction",
            "type":"Services"
        }
    ],
    "sg:phone":"+1 705 466 3202",
    "sg:postcode":"L0M 1G0",
    "sg:province":"ON",
    "sg:tags":[
        "contractor",
        "general"
    ],
    "wof:name":"Village Builders Inc",
    "wof:placetype":"venue"
},
  "geometry": {"coordinates":[-80.10437011720001,44.332485199],"type":"Point"}
}