{
  "type": "Feature",
  "properties": {
    "addr:full":"Victoria BC V8Z 5A7",
    "addr:postcode":"v8z 5a7",
    "iso:country":"CA",
    "sg:city":"Victoria",
    "sg:classifiers":[
        {
            "category":"Shopping",
            "type":"Retail Goods"
        }
    ],
    "sg:phone":"+1 250 744 2739",
    "sg:postcode":"V8Z 5A7",
    "sg:province":"BC",
    "sg:tags":[
        "equipment",
        "beer",
        "supply"
    ],
    "wof:name":"Brew Works",
    "wof:placetype":"venue"
},
  "geometry": {"coordinates":[-123.364517212,48.428314209],"type":"Point"}
}