{
  "type": "Feature",
  "properties": {
    "addr:full":"1440 12th Ave W Vancouver BC V6H 1M8",
    "addr:housenumber":"1440",
    "addr:postcode":"v6h 1m8",
    "addr:street":"12Th Ave W",
    "iso:country":"CA",
    "sg:address":"1440 12th Ave W",
    "sg:city":"Vancouver",
    "sg:classifiers":[
        {
            "category":"Cinema",
            "subcategory":"Movie Theater",
            "type":"Entertainment"
        }
    ],
    "sg:phone":"+1 604 731 5483",
    "sg:postcode":"V6H 1M8",
    "sg:province":"BC",
    "wof:name":"Pacific Theatre CO",
    "wof:placetype":"venue"
},
  "geometry": {"coordinates":[-123.137253,49.260651],"type":"Point"}
}