{
  "type": "Feature",
  "properties": {
    "iso:country":"CA",
    "sg:address":"75 Sq Sir-G.-Etienne-Cartier",
    "sg:city":"Montreal",
    "sg:classifiers":[
        {
            "category":"Social Services",
            "type":"Services"
        }
    ],
    "sg:phone":"+1 514 931 4089",
    "sg:postcode":"H4C 3A1",
    "sg:province":"QC",
    "sg:tags":[
        "organization",
        "welfare"
    ],
    "wof:name":"Source Milieu Educatif",
    "wof:placetype":"venue"
},
  "geometry": {"coordinates":[-73.583809,45.472794],"type":"Point"}
}