{
  "type": "Feature",
  "properties": {
    "addr:full":"255 Boul Roland-Therrien Longueuil QC J4H 4A6",
    "addr:housenumber":"255",
    "addr:postcode":"j4h 4a6",
    "addr:street":"Boul Roland-Therrien",
    "iso:country":"CA",
    "sg:address":"255 Boul Roland-Therrien",
    "sg:city":"Longueuil",
    "sg:classifiers":[
        {
            "category":"Health Services",
            "subcategory":"Medical Lab",
            "type":"Services"
        }
    ],
    "sg:phone":"+1 450 651 3097",
    "sg:postcode":"J4H 4A6",
    "sg:province":"QC",
    "sg:tags":[
        "laboratory"
    ],
    "wof:name":"Laboratoire Dentaire Beldent",
    "wof:placetype":"venue"
},
  "geometry": {"coordinates":[-73.4945068359,45.5476951599],"type":"Point"}
}