{
  "type": "Feature",
  "properties": {
    "addr:full":"4695 Rue Sherbrooke O Westmount QC H3Z 1G2",
    "addr:housenumber":"4695",
    "addr:postcode":"h3z 1g2",
    "addr:street":"Rue Sherbrooke O",
    "iso:country":"CA",
    "sg:address":"4695 Rue Sherbrooke O",
    "sg:city":"Westmount",
    "sg:classifiers":[
        {
            "category":"Health Services",
            "subcategory":"Doctor",
            "type":"Services"
        }
    ],
    "sg:phone":"+1 514 935 5024",
    "sg:postcode":"H3Z 1G2",
    "sg:province":"QC",
    "sg:tags":[
        "dentist"
    ],
    "wof:name":"Fenwick, John D DDS",
    "wof:placetype":"venue"
},
  "geometry": {"coordinates":[-73.601219,45.481064],"type":"Point"}
}