{
  "type": "Feature",
  "properties": {
    "iso:country":"CA",
    "sg:address":"883 Rue Germaine-Guevremont",
    "sg:city":"Montreal",
    "sg:classifiers":[
        {
            "category":"Wholesale",
            "subcategory":"Non-durable Goods",
            "type":"Manufacturing & Wholesale Goods"
        }
    ],
    "sg:phone":"+1 514 332 8171",
    "sg:postcode":"H4N 3H3",
    "sg:province":"QC",
    "sg:tags":[
        "pet",
        "supply"
    ],
    "wof:name":"Importations Aquamarin Imports",
    "wof:placetype":"venue"
},
  "geometry": {"coordinates":[-73.665733,45.537601],"type":"Point"}
}