{
  "type": "Feature",
  "properties": {
    "addr:full":"735 Rue Dufferin Canton-DE-Granby QC J2H 2H5",
    "addr:housenumber":"735",
    "addr:postcode":"j2h 2h5",
    "addr:street":"Rue Dufferin Canton-De-Granby",
    "iso:country":"CA",
    "sg:address":"735 Rue Dufferin",
    "sg:city":"Canton-DE-Granby",
    "sg:classifiers":[
        {
            "category":"Government",
            "subcategory":"Office",
            "type":"Public Place"
        }
    ],
    "sg:phone":"+1 450 372 3442",
    "sg:postcode":"J2H 2H5",
    "sg:province":"QC",
    "sg:tags":[
        "village"
    ],
    "wof:name":"Granby Adm Taxation Evaluation",
    "wof:placetype":"venue"
},
  "geometry": {"coordinates":[-72.7217712402,45.3979949951],"type":"Point"}
}