{
  "type": "Feature",
  "properties": {
    "addr:full":"1160 Av Victoria Lemoyne QC J4R 1R1",
    "addr:housenumber":"1160",
    "addr:postcode":"j4r 1r1",
    "addr:street":"Av Victoria",
    "iso:country":"CA",
    "sg:address":"1160 Av Victoria",
    "sg:city":"Lemoyne",
    "sg:classifiers":[
        {
            "category":"Health Services",
            "subcategory":"Doctor",
            "type":"Services"
        }
    ],
    "sg:phone":"+1 450 465 0655",
    "sg:postcode":"J4R 1R1",
    "sg:province":"QC",
    "sg:tags":[
        "clinic"
    ],
    "wof:name":"Clinique Medicale Supra",
    "wof:placetype":"venue"
},
  "geometry": {"coordinates":[-73.4972229004,45.493144989],"type":"Point"}
}