{
  "type": "Feature",
  "properties": {
    "addr:full":"Matane QC G4W 3G8",
    "addr:postcode":"g4w 3g8",
    "iso:country":"CA",
    "sg:city":"Matane",
    "sg:classifiers":[
        {
            "category":"Autos & Motor Vehicles",
            "subcategory":"Auto Supplies",
            "type":"Retail Goods"
        }
    ],
    "sg:phone":"+1 418 562 0668",
    "sg:postcode":"G4W 3G8",
    "sg:province":"QC",
    "sg:tags":[
        "automobile",
        "parts"
    ],
    "wof:name":"Uap Napa Pieces D'Auto",
    "wof:placetype":"venue"
},
  "geometry": {"coordinates":[-67.538757,48.850243],"type":"Point"}
}