{
  "type": "Feature",
  "properties": {
    "iso:country":"CA",
    "sg:city":"Trois-Pistoles",
    "sg:classifiers":[
        {
            "category":"Health Services",
            "subcategory":"Hospital",
            "type":"Services"
        }
    ],
    "sg:phone":"+1 418 851 3398",
    "sg:postcode":"G0L 4K0",
    "sg:province":"QC",
    "sg:tags":[
        "mental"
    ],
    "wof:name":"Periscope Des Basques",
    "wof:placetype":"venue"
},
  "geometry": {"coordinates":[-69.17496490480001,48.1256027222],"type":"Point"}
}