{
  "type": "Feature",
  "properties": {
    "addr:full":"104 Sunset Way Priddis AB T0L 1W0",
    "addr:housenumber":"104",
    "addr:postcode":"t0l 1w0",
    "addr:street":"Sunset Way",
    "iso:country":"CA",
    "sg:address":"104 Sunset Way",
    "sg:city":"Priddis",
    "sg:classifiers":[
        {
            "category":"Professional",
            "subcategory":"Engineering",
            "type":"Services"
        }
    ],
    "sg:phone":"+1 403 931 2085",
    "sg:postcode":"T0L 1W0",
    "sg:province":"AB",
    "sg:tags":[
        "engineer"
    ],
    "wof:name":"Endeco International",
    "wof:placetype":"venue"
},
  "geometry": {"coordinates":[-114.327454,50.883289],"type":"Point"}
}