{
  "type": "Feature",
  "properties": {
    "addr:full":"Hagersville ON N0A 1H0",
    "addr:postcode":"n0a 1h0",
    "iso:country":"CA",
    "sg:city":"Hagersville",
    "sg:classifiers":[
        {
            "category":"Shopping",
            "type":"Retail Goods"
        }
    ],
    "sg:phone":"+1 905 768 1046",
    "sg:postcode":"N0A 1H0",
    "sg:province":"ON",
    "sg:tags":[
        "pet",
        "food",
        "supply"
    ],
    "wof:name":"Hagersville Pet Supplies",
    "wof:placetype":"venue"
},
  "geometry": {"coordinates":[-80.05100299999999,42.962555],"type":"Point"}
}