{
  "type": "Feature",
  "properties": {
    "iso:country":"CA",
    "sg:address":"1303 Main St E",
    "sg:city":"Hamilton",
    "sg:classifiers":[
        {
            "category":"Manufacturing",
            "subcategory":"Tools & Machinery",
            "type":"Manufacturing & Wholesale Goods"
        }
    ],
    "sg:phone":"+1 905 312 1488",
    "sg:postcode":"L8K 1B3",
    "sg:province":"ON",
    "sg:tags":[
        "laboratory",
        "optical"
    ],
    "wof:name":"R & R Optical Laboratory",
    "wof:placetype":"venue"
},
  "geometry": {"coordinates":[-79.8141174316,43.2414131165],"type":"Point"}
}