{
  "type": "Feature",
  "properties": {
    "addr:full":"6 Scott Dr Richmond Hill ON L4C 6V6",
    "addr:housenumber":"6",
    "addr:postcode":"l4c 6v6",
    "addr:street":"Scott Dr",
    "iso:country":"CA",
    "sg:address":"6 Scott Dr",
    "sg:city":"Richmond Hill",
    "sg:classifiers":[
        {
            "category":"Recreation",
            "type":"Entertainment"
        }
    ],
    "sg:phone":"+1 905 882 1442",
    "sg:postcode":"L4C 6V6",
    "sg:province":"ON",
    "sg:tags":[
        "yoga",
        "instruction",
        "program",
        "fitness",
        "exercise",
        "physical"
    ],
    "wof:name":"Pilates North",
    "wof:placetype":"venue"
},
  "geometry": {"coordinates":[-79.43244900000001,43.846336],"type":"Point"}
}