{
  "type": "Feature",
  "properties": {
    "addr:full":"Etobicoke ON M9C 5K1",
    "addr:postcode":"m9c 5k1",
    "iso:country":"CA",
    "sg:city":"Etobicoke",
    "sg:classifiers":[
        {
            "category":"Banks & Credit Unions",
            "subcategory":"Investment Brokerage",
            "type":"Services"
        }
    ],
    "sg:phone":"+1 416 626 9111",
    "sg:postcode":"M9C 5K1",
    "sg:province":"ON",
    "sg:tags":[
        "consultant",
        "planning",
        "financial"
    ],
    "wof:name":"Kingsgate Wealth Mgmt Svc Ltd",
    "wof:placetype":"venue"
},
  "geometry": {"coordinates":[-79.5587692261,43.626701355],"type":"Point"}
}