{
  "type": "Feature",
  "properties": {
    "addr:full":"PO Box 74 Lcd 1 Medicine Hat AB T1A 7E5",
    "addr:housenumber":"po box 74;1",
    "addr:postcode":"t1a 7e5",
    "addr:street":"Lcd",
    "iso:country":"CA",
    "sg:address":"PO Box 74 Lcd 1",
    "sg:city":"Medicine Hat",
    "sg:classifiers":[
        {
            "category":"Retail",
            "subcategory":"Repair Shop",
            "type":"Services"
        }
    ],
    "sg:phone":"+1 403 527 0294",
    "sg:postcode":"T1A 7E5",
    "sg:province":"AB",
    "sg:tags":[
        "welding"
    ],
    "wof:name":"Stock Welding Ltd",
    "wof:placetype":"venue"
},
  "geometry": {"coordinates":[-110.678093,50.041069],"type":"Point"}
}