{
  "type": "Feature",
  "properties": {
    "iso:country":"CA",
    "sg:address":"922 Rue Berlier",
    "sg:city":"Laval",
    "sg:classifiers":[
        {
            "category":"Retail",
            "subcategory":"Auto Repair",
            "type":"Services"
        }
    ],
    "sg:phone":"+1 450 668 2023",
    "sg:postcode":"H7L 4K5",
    "sg:province":"QC",
    "sg:tags":[
        "body",
        "automobile",
        "painting"
    ],
    "wof:name":"Carrosserie 2020 Inc",
    "wof:placetype":"venue"
},
  "geometry": {"coordinates":[-73.7406845093,45.5869445801],"type":"Point"}
}