{
  "type": "Feature",
  "properties": {
    "addr:full":"7144 Airport Rd Mississauga ON L4T 2H1",
    "addr:housenumber":"7144",
    "addr:postcode":"l4t 2h1",
    "addr:street":"Airport Rd",
    "iso:country":"CA",
    "sg:address":"7144 Airport Rd",
    "sg:city":"Mississauga",
    "sg:classifiers":[
        {
            "category":"Travel",
            "subcategory":"Travel Agent",
            "type":"Entertainment"
        }
    ],
    "sg:phone":"+1 905 678 9555",
    "sg:postcode":"L4T 2H1",
    "sg:province":"ON",
    "sg:tags":[
        "agency",
        "bureau"
    ],
    "wof:name":"Onkar Travels",
    "wof:placetype":"venue"
},
  "geometry": {"coordinates":[-79.646263,43.706486],"type":"Point"}
}