{
  "type": "Feature",
  "properties": {
    "addr:full":"260 Silver Springs Blvd Scarborough ON M1V 1S4",
    "addr:housenumber":"260",
    "addr:postcode":"m1v 1s4",
    "addr:street":"Silver Springs Blvd",
    "iso:country":"CA",
    "sg:address":"260 Silver Springs Blvd",
    "sg:city":"Scarborough",
    "sg:classifiers":[
        {
            "category":"Education",
            "subcategory":"School",
            "type":"Public Place"
        }
    ],
    "sg:phone":"+1 416 393 5373",
    "sg:postcode":"M1V 1S4",
    "sg:province":"ON",
    "wof:name":"Saint Sylvester Elementary",
    "wof:placetype":"venue"
},
  "geometry": {"coordinates":[-79.3017730713,43.8053512573],"type":"Point"}
}