{
  "type": "Feature",
  "properties": {
    "addr:full":"SW 36-8-6W Haywood MB R0G 0W0",
    "addr:postcode":"r0g 0w0",
    "addr:street":"Sw",
    "iso:country":"CA",
    "sg:address":"SW 36-8-6W",
    "sg:city":"Haywood",
    "sg:classifiers":[
        {
            "category":"Farming",
            "subcategory":"Farm",
            "type":"Manufacturing & Wholesale Goods"
        }
    ],
    "sg:phone":"+1 204 379 2121",
    "sg:postcode":"R0G 0W0",
    "sg:province":"MB",
    "wof:name":"Poirier Farms",
    "wof:placetype":"venue"
},
  "geometry": {"coordinates":[-98.196609,49.666985],"type":"Point"}
}