{
  "type": "Feature",
  "properties": {
    "addr:full":"North York ON M6M 3Z5",
    "addr:postcode":"m6m 3z5",
    "iso:country":"CA",
    "sg:city":"North York",
    "sg:classifiers":[
        {
            "category":"Health Services",
            "subcategory":"Doctor",
            "type":"Services"
        }
    ],
    "sg:phone":"+1 416 248 9872",
    "sg:postcode":"M6M 3Z5",
    "sg:province":"ON",
    "sg:tags":[
        "physician",
        "surgeon"
    ],
    "wof:name":"Craddock, G N MD",
    "wof:placetype":"venue"
},
  "geometry": {"coordinates":[-79.47550200000001,43.698318],"type":"Point"}
}