{
  "type": "Feature",
  "properties": {
    "addr:full":"542 Talbot St Port Mcnicoll ON L0K 1R0",
    "addr:housenumber":"542",
    "addr:postcode":"l0k 1r0",
    "addr:street":"Talbot St",
    "iso:country":"CA",
    "sg:address":"542 Talbot St",
    "sg:city":"Port Mcnicoll",
    "sg:classifiers":[
        {
            "category":"Food & Beverages",
            "subcategory":"Groceries & Convenience Stores",
            "type":"Retail Goods"
        }
    ],
    "sg:phone":"+1 705 534 3664",
    "sg:postcode":"L0K 1R0",
    "sg:province":"ON",
    "wof:name":"Garrett's Convenience",
    "wof:placetype":"venue"
},
  "geometry": {"coordinates":[-79.8132324219,44.7437553406],"type":"Point"}
}