{
  "type": "Feature",
  "properties": {
    "addr:full":"1009 Richmond St Chatham ON N7M 5J5",
    "addr:housenumber":"1009",
    "addr:postcode":"n7m 5j5",
    "addr:street":"Richmond St",
    "iso:country":"CA",
    "sg:address":"1009 Richmond St",
    "sg:city":"Chatham",
    "sg:classifiers":[
        {
            "category":"Manufacturing",
            "subcategory":"Tools & Machinery",
            "type":"Manufacturing & Wholesale Goods"
        }
    ],
    "sg:phone":"+1 519 351 5011",
    "sg:postcode":"N7M 5J5",
    "sg:province":"ON",
    "sg:tags":[
        "steel",
        "machine",
        "shop"
    ],
    "wof:name":"Nova Industrial Contractors",
    "wof:placetype":"venue"
},
  "geometry": {"coordinates":[-82.21470600000001,42.381145],"type":"Point"}
}