{
  "type": "Feature",
  "properties": {
    "addr:full":"3525 Fraser St Vancouver BC V5V 4C5",
    "addr:housenumber":"3525",
    "addr:postcode":"v5v 4c5",
    "addr:street":"Fraser St",
    "iso:country":"CA",
    "sg:address":"3525 Fraser St",
    "sg:city":"Vancouver",
    "sg:classifiers":[
        {
            "category":"Organizations",
            "subcategory":"Religious Organization",
            "type":"Services"
        }
    ],
    "sg:phone":"+1 604 872 1189",
    "sg:postcode":"V5V 4C5",
    "sg:province":"BC",
    "sg:tags":[
        "church"
    ],
    "wof:name":"Jehovah's Witnesses",
    "wof:placetype":"venue"
},
  "geometry": {"coordinates":[-123.09009552000001,49.2534828186],"type":"Point"}
}