{
  "type": "Feature",
  "properties": {
    "addr:full":"1130 10 Ave SW Calgary AB T2R 0B6",
    "addr:housenumber":"1130",
    "addr:postcode":"t2r 0b6",
    "addr:street":"10 Ave Sw",
    "iso:country":"CA",
    "sg:address":"1130 10 Ave SW",
    "sg:city":"Calgary",
    "sg:classifiers":[
        {
            "category":"Social Services",
            "type":"Services"
        }
    ],
    "sg:phone":"+1 403 216 9250",
    "sg:postcode":"T2R 0B6",
    "sg:province":"AB",
    "sg:tags":[
        "organization",
        "welfare"
    ],
    "wof:name":"Potential Place Clubhouse",
    "wof:placetype":"venue"
},
  "geometry": {"coordinates":[-114.08715057400001,51.044128418],"type":"Point"}
}