{
  "type": "Feature",
  "properties": {
    "iso:country":"CA",
    "sg:city":"Matagami",
    "sg:classifiers":[
        {
            "category":"Autos & Motor Vehicles",
            "subcategory":"Motorcycle Sales",
            "type":"Retail Goods"
        }
    ],
    "sg:phone":"+1 819 739 5758",
    "sg:postcode":"J0Y 2A0",
    "sg:province":"QC",
    "sg:tags":[
        "snowmobile"
    ],
    "wof:name":"Ultra Sport",
    "wof:placetype":"venue"
},
  "geometry": {"coordinates":[-77.63079833979999,49.7671203613],"type":"Point"}
}