{
  "type": "Feature",
  "properties": {
    "addr:full":"Westmount QC H3Z 2A7",
    "addr:postcode":"h3z 2a7",
    "iso:country":"CA",
    "sg:city":"Westmount",
    "sg:classifiers":[
        {
            "category":"Real Estate",
            "subcategory":"Real Estate Agent",
            "type":"Services"
        }
    ],
    "sg:phone":"+1 514 933 4711",
    "sg:postcode":"H3Z 2A7",
    "sg:province":"QC",
    "wof:name":"E & P Holdings Ltd",
    "wof:placetype":"venue"
},
  "geometry": {"coordinates":[-73.589714,45.487137],"type":"Point"}
}