{
  "type": "Feature",
  "properties": {
    "addr:full":"6090 176 St Surrey BC V3S 4E7",
    "addr:housenumber":"6090",
    "addr:postcode":"v3s 4e7",
    "addr:street":"176 St",
    "iso:country":"CA",
    "sg:address":"6090 176 St",
    "sg:city":"Surrey",
    "sg:classifiers":[
        {
            "category":"Arena",
            "subcategory":"Sports Club",
            "type":"Entertainment"
        }
    ],
    "sg:phone":"+1 604 502 6410",
    "sg:postcode":"V3S 4E7",
    "sg:province":"BC",
    "sg:tags":[
        "athletic",
        "fields",
        "stadium",
        "government"
    ],
    "wof:name":"Cloverdale Arena",
    "wof:placetype":"venue"
},
  "geometry": {"coordinates":[-122.73469543500001,49.1132507324],"type":"Point"}
}