{
  "type": "Feature",
  "properties": {
    "addr:full":"488 Locust St Burlington ON L7S 1V2",
    "addr:housenumber":"488",
    "addr:postcode":"l7s 1v2",
    "addr:street":"Locust St",
    "iso:country":"CA",
    "sg:address":"488 Locust St",
    "sg:city":"Burlington",
    "sg:classifiers":[
        {
            "category":"Health Services",
            "subcategory":"Doctor",
            "type":"Services"
        }
    ],
    "sg:phone":"+1 905 632 3025",
    "sg:postcode":"L7S 1V2",
    "sg:province":"ON",
    "sg:tags":[
        "physician",
        "surgeon"
    ],
    "wof:name":"Love Jr, William R MD",
    "wof:placetype":"venue"
},
  "geometry": {"coordinates":[-79.800247,43.325878],"type":"Point"}
}