{
  "type": "Feature",
  "properties": {
    "iso:country":"CA",
    "sg:address":"1010 Mcdonald St",
    "sg:city":"Regina",
    "sg:classifiers":[
        {
            "category":"Home & Garden",
            "subcategory":"Building Materials",
            "type":"Retail Goods"
        }
    ],
    "sg:phone":"+1 306 721 4652",
    "sg:postcode":"S4N 2X8",
    "sg:province":"SK",
    "sg:tags":[
        "glass",
        "window",
        "plate"
    ],
    "wof:name":"Tierdon Glass Ltd",
    "wof:placetype":"venue"
},
  "geometry": {"coordinates":[-104.58383178699999,50.4626808167],"type":"Point"}
}