{
  "type": "Feature",
  "properties": {
    "addr:full":"Surrey BC V3W 8J9",
    "addr:postcode":"v3w 8j9",
    "iso:country":"CA",
    "sg:city":"Surrey",
    "sg:phone":"+1 604 572 5666",
    "sg:postcode":"V3W 8J9",
    "sg:province":"BC",
    "sg:tags":[
        "equipment",
        "station"
    ],
    "wof:name":"Babco Sales Ltd",
    "wof:placetype":"venue"
},
  "geometry": {"coordinates":[-122.86196099999999,49.153904],"type":"Point"}
}