{
  "type": "Feature",
  "properties": {
    "addr:full":"825 Av Melan Saint-Jerome QC J7Z 4L1",
    "addr:housenumber":"825",
    "addr:postcode":"j7z 4l1",
    "addr:street":"Av Melan Saint-Jerome",
    "iso:country":"CA",
    "sg:address":"825 Av Melan",
    "sg:city":"Saint-Jerome",
    "sg:classifiers":[
        {
            "category":"Health Services",
            "subcategory":"Nursing And Care Facility",
            "type":"Services"
        }
    ],
    "sg:phone":"+1 450 432 3100",
    "sg:postcode":"J7Z 4L1",
    "sg:province":"QC",
    "sg:tags":[
        "home",
        "rest"
    ],
    "wof:name":"Chsld Villa Soleil",
    "wof:placetype":"venue"
},
  "geometry": {"coordinates":[-74.00351000000001,45.775009],"type":"Point"}
}