{
  "type": "Feature",
  "properties": {
    "addr:full":"780 Av Du Phare O Matane QC G4W 1V7",
    "addr:housenumber":"780",
    "addr:postcode":"g4w 1v7",
    "addr:street":"Av Du Phare O",
    "iso:country":"CA",
    "sg:address":"780 Av Du Phare O",
    "sg:city":"Matane",
    "sg:classifiers":[
        {
            "category":"Autos & Motor Vehicles",
            "subcategory":"Auto Supplies",
            "type":"Retail Goods"
        }
    ],
    "sg:phone":"+1 418 562 5144",
    "sg:postcode":"G4W 1V7",
    "sg:province":"QC",
    "sg:tags":[
        "automobile",
        "parts"
    ],
    "wof:name":"Canadian Tire",
    "wof:placetype":"venue"
},
  "geometry": {"coordinates":[-67.499641,48.852573],"type":"Point"}
}