{
  "type": "Feature",
  "properties": {
    "addr:full":"500 6th St E Rosthern SK S0K 3R0",
    "addr:housenumber":"500",
    "addr:postcode":"s0k 3r0",
    "addr:street":"6Th St E Rosthern",
    "iso:country":"CA",
    "sg:address":"500 6th St E",
    "sg:city":"Rosthern",
    "sg:classifiers":[
        {
            "category":"Government",
            "subcategory":"Office",
            "type":"Public Place"
        }
    ],
    "sg:phone":"+1 306 232 5151",
    "sg:postcode":"S0K 3R0",
    "sg:province":"SK",
    "sg:tags":[
        "village"
    ],
    "wof:name":"Rosthern Tourism Booth",
    "wof:placetype":"venue"
},
  "geometry": {"coordinates":[-106.33169599999999,52.657753],"type":"Point"}
}