{
  "type": "Feature",
  "properties": {
    "addr:full":"31 Adelaide St N Lindsay ON K9V 4K8",
    "addr:housenumber":"31",
    "addr:postcode":"k9v 4k8",
    "addr:street":"Adelaide St N",
    "iso:country":"CA",
    "sg:address":"31 Adelaide St N",
    "sg:city":"Lindsay",
    "sg:classifiers":[
        {
            "category":"Building & Trades",
            "subcategory":"Construction",
            "type":"Services"
        }
    ],
    "sg:phone":"+1 705 324 4585",
    "sg:postcode":"K9V 4K8",
    "sg:province":"ON",
    "sg:tags":[
        "resurfacing",
        "laying",
        "refinishing",
        "floor"
    ],
    "wof:name":"Dean J Floor Finishing",
    "wof:placetype":"venue"
},
  "geometry": {"coordinates":[-78.749107,44.354469],"type":"Point"}
}