{
  "type": "Feature",
  "properties": {
    "addr:full":"3123 Portage Ave Winnipeg MB R3K 0W4",
    "addr:housenumber":"3123",
    "addr:postcode":"r3k 0w4",
    "addr:street":"Portage Ave",
    "iso:country":"CA",
    "sg:address":"3123 Portage Ave",
    "sg:city":"Winnipeg",
    "sg:classifiers":[
        {
            "category":"Restaurant",
            "type":"Food & Drink"
        }
    ],
    "sg:phone":"+1 204 831 5531",
    "sg:postcode":"R3K 0W4",
    "sg:province":"MB",
    "wof:name":"Steve's Place Family Dining",
    "wof:placetype":"venue"
},
  "geometry": {"coordinates":[-97.285202,49.880669],"type":"Point"}
}