{
  "type": "Feature",
  "properties": {
    "addr:full":"1795 Kilborn Ave Ottawa ON K1H 6N1",
    "addr:housenumber":"1795",
    "addr:postcode":"k1h 6n1",
    "addr:street":"Kilborn Ave",
    "iso:country":"CA",
    "sg:address":"1795 Kilborn Ave",
    "sg:city":"Ottawa",
    "sg:classifiers":[
        {
            "category":"Government",
            "subcategory":"Office",
            "type":"Public Place"
        }
    ],
    "sg:phone":"+1 613 736 9573",
    "sg:postcode":"K1H 6N1",
    "sg:province":"ON",
    "wof:name":"Mc Guinty, Dalton",
    "wof:placetype":"venue"
},
  "geometry": {"coordinates":[-75.645454,45.387974],"type":"Point"}
}