{
  "type": "Feature",
  "properties": {
    "iso:country":"CA",
    "sg:address":"5623 Wolf Creek Dr",
    "sg:city":"Lacombe",
    "sg:classifiers":[
        {
            "category":"Freight",
            "type":"Transportation"
        }
    ],
    "sg:phone":"+1 403 782 9991",
    "sg:postcode":"T4L 2H8",
    "sg:province":"AB",
    "sg:tags":[
        "commercial",
        "storage"
    ],
    "wof:name":"Central Storage",
    "wof:placetype":"venue"
},
  "geometry": {"coordinates":[-113.714981079,52.4732818604],"type":"Point"}
}