{
  "type": "Feature",
  "properties": {
    "addr:full":"Edmonton AB T5K 0M1",
    "addr:postcode":"t5k 0m1",
    "iso:country":"CA",
    "sg:city":"Edmonton",
    "sg:classifiers":[
        {
            "category":"Real Estate",
            "subcategory":"Architect",
            "type":"Services"
        }
    ],
    "sg:phone":"+1 780 488 0554",
    "sg:postcode":"T5K 0M1",
    "sg:province":"AB",
    "wof:name":"Raimond Fung Architect Ltd",
    "wof:placetype":"venue"
},
  "geometry": {"coordinates":[-113.518654,53.541164],"type":"Point"}
}