{
  "type": "Feature",
  "properties": {
    "addr:full":"36 Adelaide St Frankford ON K0K 2C0",
    "addr:housenumber":"36",
    "addr:postcode":"k0k 2c0",
    "addr:street":"Adelaide St",
    "iso:country":"CA",
    "sg:address":"36 Adelaide St",
    "sg:city":"Frankford",
    "sg:classifiers":[
        {
            "category":"Education",
            "subcategory":"School",
            "type":"Public Place"
        }
    ],
    "sg:phone":"+1 613 398 6425",
    "sg:postcode":"K0K 2C0",
    "sg:province":"ON",
    "wof:name":"Frankford Elementary School",
    "wof:placetype":"venue"
},
  "geometry": {"coordinates":[-77.598366,44.204079],"type":"Point"}
}