{
  "type": "Feature",
  "properties": {
    "addr:full":"Ottawa ON K1G 3W4",
    "addr:postcode":"k1g 3w4",
    "iso:country":"CA",
    "sg:city":"Ottawa",
    "sg:classifiers":[
        {
            "category":"Building & Trades",
            "subcategory":"Electrical",
            "type":"Services"
        }
    ],
    "sg:phone":"+1 613 738 8047",
    "sg:postcode":"K1G 3W4",
    "sg:province":"ON",
    "sg:tags":[
        "electric",
        "contractor"
    ],
    "wof:name":"P G Electric",
    "wof:placetype":"venue"
},
  "geometry": {"coordinates":[-75.6065979004,45.382270813],"type":"Point"}
}