{
  "type": "Feature",
  "properties": {
    "iso:country":"CA",
    "sg:address":"234 Rue Dufferin",
    "sg:city":"Sherbrooke",
    "sg:classifiers":[
        {
            "category":"Health Services",
            "subcategory":"Health Practitioner",
            "type":"Services"
        }
    ],
    "sg:phone":"+1 819 821 3778",
    "sg:postcode":"J1H 4M2",
    "sg:province":"QC",
    "sg:tags":[
        "psychologist"
    ],
    "wof:name":"Perras, Gauvin N",
    "wof:placetype":"venue"
},
  "geometry": {"coordinates":[-71.894089,45.405159],"type":"Point"}
}