{
  "type": "Feature",
  "properties": {
    "addr:full":"2 Townley St Nottawa ON L0M 1P0",
    "addr:housenumber":"2",
    "addr:postcode":"l0m 1p0",
    "addr:street":"Townley St",
    "iso:country":"CA",
    "sg:address":"2 Townley St",
    "sg:city":"Nottawa",
    "sg:classifiers":[
        {
            "category":"Manufacturing",
            "subcategory":"Glass & Minerals",
            "type":"Manufacturing & Wholesale Goods"
        }
    ],
    "sg:phone":"+1 705 446 1078",
    "sg:postcode":"L0M 1P0",
    "sg:province":"ON",
    "sg:tags":[
        "decoration",
        "glassware",
        "decorator"
    ],
    "wof:name":"Harriet Spot Designs",
    "wof:placetype":"venue"
},
  "geometry": {"coordinates":[-80.2072982788,44.462600708],"type":"Point"}
}