{
  "type": "Feature",
  "properties": {
    "addr:full":"7881 Government Rd Burnaby BC V5A 2C9",
    "addr:housenumber":"7881",
    "addr:postcode":"v5a 2c9",
    "addr:street":"Rd",
    "iso:country":"CA",
    "sg:address":"7881 Government Rd",
    "sg:city":"Burnaby",
    "sg:classifiers":[
        {
            "category":"Education",
            "subcategory":"School",
            "type":"Public Place"
        }
    ],
    "sg:phone":"+1 604 664 8808",
    "sg:postcode":"V5A 2C9",
    "sg:province":"BC",
    "wof:name":"Seaforth Elementary School",
    "wof:placetype":"venue"
},
  "geometry": {"coordinates":[-122.935715,49.251011],"type":"Point"}
}