{
  "type": "Feature",
  "properties": {
    "addr:full":"Rocanville SK S0A 3L0",
    "addr:postcode":"s0a 3l0",
    "iso:country":"CA",
    "sg:city":"Rocanville",
    "sg:classifiers":[
        {
            "category":"Organizations",
            "subcategory":"Religious Organization",
            "type":"Services"
        }
    ],
    "sg:phone":"+1 306 645 2652",
    "sg:postcode":"S0A 3L0",
    "sg:province":"SK",
    "sg:tags":[
        "church"
    ],
    "wof:name":"St Alphonsus Church",
    "wof:placetype":"venue"
},
  "geometry": {"coordinates":[-101.699920654,50.3824424744],"type":"Point"}
}