{
  "type": "Feature",
  "properties": {
    "iso:country":"CA",
    "sg:address":"254 Talbot St E",
    "sg:city":"Blenheim",
    "sg:classifiers":[
        {
            "category":"Restaurant",
            "type":"Food & Drink"
        }
    ],
    "sg:phone":"+1 519 676 6909",
    "sg:postcode":"N0P 1A0",
    "sg:province":"ON",
    "wof:name":"Sunrise Cafe",
    "wof:placetype":"venue"
},
  "geometry": {"coordinates":[-82.001953,42.330139],"type":"Point"}
}