{
  "type": "Feature",
  "properties": {
    "addr:full":"2600 Richmond Rd SW Calgary AB T3E 4M3",
    "addr:housenumber":"2600",
    "addr:postcode":"t3e 4m3",
    "addr:street":"Richmond Rd Sw",
    "iso:country":"CA",
    "sg:address":"2600 Richmond Rd SW",
    "sg:city":"Calgary",
    "sg:classifiers":[
        {
            "category":"Organizations",
            "subcategory":"Religious Organization",
            "type":"Services"
        }
    ],
    "sg:phone":"+1 403 249 8784",
    "sg:postcode":"T3E 4M3",
    "sg:province":"AB",
    "sg:tags":[
        "church"
    ],
    "wof:name":"First Mennonite Church",
    "wof:placetype":"venue"
},
  "geometry": {"coordinates":[-114.121132,51.028831],"type":"Point"}
}