{
  "type": "Feature",
  "properties": {
    "addr:full":"1212 Dundas St W Toronto ON M6J 1X5",
    "addr:housenumber":"1212",
    "addr:postcode":"m6j 1x5",
    "addr:street":"Dundas St W",
    "iso:country":"CA",
    "sg:address":"1212 Dundas St W",
    "sg:city":"Toronto",
    "sg:classifiers":[
        {
            "category":"Restaurant",
            "type":"Food & Drink"
        }
    ],
    "sg:phone":"+1 416 588 4900",
    "sg:postcode":"M6J 1X5",
    "sg:province":"ON",
    "wof:name":"If Lounge",
    "wof:placetype":"venue"
},
  "geometry": {"coordinates":[-79.42287445069999,43.6494598389],"type":"Point"}
}