{
  "type": "Feature",
  "properties": {
    "iso:country":"CA",
    "sg:address":"1212 Dundas St W",
    "sg:city":"Toronto",
    "sg:classifiers":[
        {
            "category":"Restaurant",
            "type":"Food & Drink"
        }
    ],
    "sg:phone":"+1 416 588 4900",
    "sg:postcode":"M6J 1X5",
    "sg:province":"ON",
    "wof:name":"If Lounge",
    "wof:placetype":"venue"
},
  "geometry": {"coordinates":[-79.42287445069999,43.6494598389],"type":"Point"}
}