{
  "type": "Feature",
  "properties": {
    "addr:full":"4397 12th Ave W Vancouver BC V6R 2P9",
    "addr:housenumber":"4397",
    "addr:postcode":"v6r 2p9",
    "addr:street":"12Th Ave W",
    "iso:country":"CA",
    "sg:address":"4397 12th Ave W",
    "sg:city":"Vancouver",
    "sg:classifiers":[
        {
            "category":"Organizations",
            "subcategory":"Religious Organization",
            "type":"Services"
        }
    ],
    "sg:phone":"+1 604 224 7744",
    "sg:postcode":"V6R 2P9",
    "sg:province":"BC",
    "sg:tags":[
        "church"
    ],
    "wof:name":"West Point Grey Presbyterian",
    "wof:placetype":"venue"
},
  "geometry": {"coordinates":[-123.20574999999999,49.262119],"type":"Point"}
}