{
  "type": "Feature",
  "properties": {
    "addr:full":"Charlesbourg QC G1G 5S9",
    "addr:postcode":"g1g 5s9",
    "iso:country":"CA",
    "sg:city":"Charlesbourg",
    "sg:classifiers":[
        {
            "category":"Health Services",
            "subcategory":"Medical Lab",
            "type":"Services"
        }
    ],
    "sg:phone":"+1 418 627 5040",
    "sg:postcode":"G1G 5S9",
    "sg:province":"QC",
    "wof:name":"Jourdain, Serge",
    "wof:placetype":"venue"
},
  "geometry": {"coordinates":[-71.28564453120001,46.8796386719],"type":"Point"}
}