{
  "type": "Feature",
  "properties": {
    "addr:full":"1275 Jane St York ON M6M 4Y1",
    "addr:housenumber":"1275",
    "addr:postcode":"m6m 4y1",
    "addr:street":"Jane St",
    "iso:country":"CA",
    "sg:address":"1275 Jane St",
    "sg:city":"York",
    "sg:classifiers":[
        {
            "category":"Banks & Credit Unions",
            "subcategory":"Bank",
            "type":"Services"
        }
    ],
    "sg:phone":"+1 416 247 9997",
    "sg:postcode":"M6M 4Y1",
    "sg:province":"ON",
    "sg:tags":[
        "money",
        "order",
        "transfer"
    ],
    "wof:name":"Canada Cash Express Inc",
    "wof:placetype":"venue"
},
  "geometry": {"coordinates":[-79.5008010864,43.6913948059],"type":"Point"}
}