{
  "type": "Feature",
  "properties": {
    "addr:full":"150 Boul Saint-Martin O Laval QC H7M 3Y8",
    "addr:housenumber":"150",
    "addr:postcode":"h7m 3y8",
    "addr:street":"Boul Saint-Martin O",
    "iso:country":"CA",
    "sg:address":"150 Boul Saint-Martin O",
    "sg:city":"Laval",
    "sg:classifiers":[
        {
            "category":"Autos & Motor Vehicles",
            "subcategory":"Auto Supplies",
            "type":"Retail Goods"
        }
    ],
    "sg:phone":"+1 450 669 5444",
    "sg:postcode":"H7M 3Y8",
    "sg:province":"QC",
    "sg:tags":[
        "automobile",
        "stereo",
        "radio"
    ],
    "wof:name":"Radio D'Auto Chomedey Inc",
    "wof:placetype":"venue"
},
  "geometry": {"coordinates":[-73.70737457280001,45.5805397034],"type":"Point"}
}