{
  "type": "Feature",
  "properties": {
    "addr:full":"Edson AB T7E 1T8",
    "addr:postcode":"t7e 1t8",
    "iso:country":"CA",
    "sg:city":"Edson",
    "sg:classifiers":[
        {
            "category":"Shopping",
            "subcategory":"Computers & Home Electronics",
            "type":"Retail Goods"
        }
    ],
    "sg:phone":"+1 780 723 4850",
    "sg:postcode":"T7E 1T8",
    "sg:province":"AB",
    "sg:tags":[
        "equipment",
        "dealer"
    ],
    "wof:name":"Computers Place",
    "wof:placetype":"venue"
},
  "geometry": {"coordinates":[-116.43135100000001,53.58136],"type":"Point"}
}