{
  "type": "Feature",
  "properties": {
    "addr:full":"Edmonton AB T5P 4A4",
    "addr:postcode":"t5p 4a4",
    "iso:country":"CA",
    "sg:city":"Edmonton",
    "sg:classifiers":[
        {
            "category":"Professional",
            "subcategory":"Credit Reporting & Collection",
            "type":"Services"
        }
    ],
    "sg:phone":"+1 780 486 1011",
    "sg:postcode":"T5P 4A4",
    "sg:province":"AB",
    "sg:tags":[
        "agency"
    ],
    "wof:name":"Vanguard Collection Agencies",
    "wof:placetype":"venue"
},
  "geometry": {"coordinates":[-113.601364,53.541431],"type":"Point"}
}