{
  "type": "Feature",
  "properties": {
    "addr:full":"North Battleford SK S9A 3K2",
    "addr:postcode":"s9a 3k2",
    "iso:country":"CA",
    "sg:city":"North Battleford",
    "sg:classifiers":[
        {
            "category":"Wholesale",
            "subcategory":"Farm Supplies",
            "type":"Manufacturing & Wholesale Goods"
        }
    ],
    "sg:phone":"+1 306 446 3177",
    "sg:postcode":"S9A 3K2",
    "sg:province":"SK",
    "sg:tags":[
        "livestock"
    ],
    "wof:name":"Campbell Livestock Inc",
    "wof:placetype":"venue"
},
  "geometry": {"coordinates":[-108.252342,52.744328],"type":"Point"}
}