{
  "type": "Feature",
  "properties": {
    "addr:full":"816 Baker St Cranbrook BC V1C 1A2",
    "addr:housenumber":"816",
    "addr:postcode":"bc v1c 1a2",
    "addr:street":"Baker St",
    "iso:country":"CA",
    "sg:address":"816 Baker St",
    "sg:city":"Cranbrook",
    "sg:classifiers":[
        {
            "category":"Shopping",
            "subcategory":"Bicycles & Sporting Goods",
            "type":"Retail Goods"
        }
    ],
    "sg:phone":"+1 250 489 4568",
    "sg:postcode":"V1C 1A2",
    "sg:province":"BC",
    "wof:name":"Boarders Choice",
    "wof:placetype":"venue"
},
  "geometry": {"coordinates":[-115.76947784399999,49.5123558044],"type":"Point"}
}