{
  "type": "Feature",
  "properties": {
    "addr:full":"49 Queenston Rd Niagara on the Lake ON L0S 1J0",
    "addr:housenumber":"49",
    "addr:postcode":"l0s 1j0",
    "addr:street":"Queenston Rd;On",
    "iso:country":"CA",
    "sg:address":"49 Queenston Rd",
    "sg:city":"Niagara on the Lake",
    "sg:classifiers":[
        {
            "category":"Manufacturing",
            "subcategory":"Lumber",
            "type":"Manufacturing & Wholesale Goods"
        }
    ],
    "sg:phone":"+1 905 682 1135",
    "sg:postcode":"L0S 1J0",
    "sg:province":"ON",
    "sg:tags":[
        "wood"
    ],
    "wof:name":"German, William J",
    "wof:placetype":"venue"
},
  "geometry": {"coordinates":[-79.184731,43.165916],"type":"Point"}
}