{
  "type": "Feature",
  "properties": {
    "iso:country":"CA",
    "sg:address":"37 Rue Bellefeuille",
    "sg:city":"Repentigny",
    "sg:classifiers":[
        {
            "category":"Wholesale",
            "subcategory":"Machinery & Supplies",
            "type":"Manufacturing & Wholesale Goods"
        }
    ],
    "sg:phone":"+1 450 654 1417",
    "sg:postcode":"J6A 5G2",
    "sg:province":"QC",
    "sg:tags":[
        "repairing"
    ],
    "wof:name":"C M Entreprises Enrg",
    "wof:placetype":"venue"
},
  "geometry": {"coordinates":[-73.4316711426,45.7569732666],"type":"Point"}
}