{
  "type": "Feature",
  "properties": {
    "addr:full":"Scarborough ON M1V 5H4",
    "addr:postcode":"m1v 5h4",
    "iso:country":"CA",
    "sg:city":"Scarborough",
    "sg:classifiers":[
        {
            "category":"Home & Garden",
            "subcategory":"Building Materials",
            "type":"Retail Goods"
        }
    ],
    "sg:phone":"+1 416 321 0177",
    "sg:postcode":"M1V 5H4",
    "sg:province":"ON",
    "sg:tags":[
        "glass",
        "window",
        "plate"
    ],
    "wof:name":"Winners Mirror & Glass",
    "wof:placetype":"venue"
},
  "geometry": {"coordinates":[-79.29285400000001,43.809364],"type":"Point"}
}