{
  "type": "Feature",
  "properties": {
    "addr:full":"805 Kalamalka Lake Rd Vernon BC V1T 6V4",
    "addr:housenumber":"805",
    "addr:postcode":"v1t 6v4",
    "addr:street":"Kalamalka Lake Rd",
    "iso:country":"CA",
    "sg:address":"805 Kalamalka Lake Rd",
    "sg:city":"Vernon",
    "sg:classifiers":[
        {
            "category":"Retail",
            "subcategory":"Veterinary Services",
            "type":"Services"
        }
    ],
    "sg:phone":"+1 250 542 9707",
    "sg:postcode":"V1T 6V4",
    "sg:province":"BC",
    "sg:tags":[
        "veterinarian"
    ],
    "wof:name":"Mehl, Herbert DVM",
    "wof:placetype":"venue"
},
  "geometry": {"coordinates":[-119.263504028,50.2466697693],"type":"Point"}
}