{
  "type": "Feature",
  "properties": {
    "iso:country":"CA",
    "sg:address":"555 Rossland Rd E",
    "sg:city":"Oshawa",
    "sg:classifiers":[
        {
            "category":"Recreation",
            "type":"Entertainment"
        }
    ],
    "sg:phone":"+1 905 666 1991",
    "sg:postcode":"L1K 1K8",
    "sg:province":"ON",
    "sg:tags":[
        "government",
        "swimming"
    ],
    "wof:name":"Whitby Civic Recreation Ctr",
    "wof:placetype":"venue"
},
  "geometry": {"coordinates":[-78.850402832,43.9197769165],"type":"Point"}
}