{
  "type": "Feature",
  "properties": {
    "addr:full":"Burnaby BC V5C 4E7",
    "addr:postcode":"v5c 4e7",
    "iso:country":"CA",
    "sg:city":"Burnaby",
    "sg:classifiers":[
        {
            "category":"Professional",
            "subcategory":"Engineering",
            "type":"Services"
        }
    ],
    "sg:phone":"+1 604 433 8515",
    "sg:postcode":"V5C 4E7",
    "sg:province":"BC",
    "sg:tags":[
        "control",
        "vibration",
        "engineer"
    ],
    "wof:name":"Primac Reliability Cnsltns",
    "wof:placetype":"venue"
},
  "geometry": {"coordinates":[-123.020386,49.260246],"type":"Point"}
}