{
  "type": "Feature",
  "properties": {
    "iso:country":"CA",
    "sg:address":"3025 Rue Principale",
    "sg:city":"Saint-Leandre",
    "sg:classifiers":[
        {
            "category":"Organizations",
            "subcategory":"Religious Organization",
            "type":"Services"
        }
    ],
    "sg:phone":"+1 418 737 4971",
    "sg:postcode":"G0J 2V0",
    "sg:province":"QC",
    "sg:tags":[
        "church"
    ],
    "wof:name":"Presbytere St-Leandre",
    "wof:placetype":"venue"
},
  "geometry": {"coordinates":[-67.60688018800001,48.7309074402],"type":"Point"}
}