{
  "type": "Feature",
  "properties": {
    "addr:full":"1905 Main St Westville NS B0K 2A0",
    "addr:housenumber":"1905",
    "addr:postcode":"b0k 2a0",
    "addr:street":"Main St",
    "iso:country":"CA",
    "sg:address":"1905 Main St",
    "sg:city":"Westville",
    "sg:classifiers":[
        {
            "category":"Personal",
            "subcategory":"Beauty Salon",
            "type":"Services"
        }
    ],
    "sg:phone":"+1 902 396 5697",
    "sg:postcode":"B0K 2A0",
    "sg:province":"NS",
    "wof:name":"Jackie's Beauty Salon",
    "wof:placetype":"venue"
},
  "geometry": {"coordinates":[-62.711517334,45.5601882935],"type":"Point"}
}