{
  "type": "Feature",
  "properties": {
    "addr:full":"114 Rue Notre-Dame Kedgwick NB E8B 1H8",
    "addr:housenumber":"114",
    "addr:postcode":"e8b 1h8",
    "addr:street":"Rue Notre-Dame",
    "iso:country":"CA",
    "sg:address":"114 Rue Notre-Dame",
    "sg:city":"Kedgwick",
    "sg:classifiers":[
        {
            "category":"Government",
            "subcategory":"Office",
            "type":"Public Place"
        }
    ],
    "sg:phone":"+1 506 284 2160",
    "sg:postcode":"E8B 1H8",
    "sg:province":"NB",
    "sg:tags":[
        "municipality"
    ],
    "wof:name":"Kedgwick Municipalite",
    "wof:placetype":"venue"
},
  "geometry": {"coordinates":[-67.34955600000001,47.64584],"type":"Point"}
}