{
  "type": "Feature",
  "properties": {
    "iso:country":"CA",
    "sg:city":"Mississauga",
    "sg:classifiers":[
        {
            "category":"Health Services",
            "subcategory":"Doctor",
            "type":"Services"
        }
    ],
    "sg:phone":"+1 905 672 1662",
    "sg:postcode":"L4T 4H7",
    "sg:province":"ON",
    "sg:tags":[
        "clinic",
        "dentist"
    ],
    "wof:name":"Derry Dental Ctr",
    "wof:placetype":"venue"
},
  "geometry": {"coordinates":[-79.6335449219,43.7123146057],"type":"Point"}
}