{
  "type": "Feature",
  "properties": {
    "addr:full":"Montreal QC H2V 4E6",
    "addr:postcode":"h2v 4e6",
    "iso:country":"CA",
    "sg:city":"Montreal",
    "sg:classifiers":[
        {
            "category":"Home & Garden",
            "subcategory":"Carpets & Floor Coverings",
            "type":"Retail Goods"
        }
    ],
    "sg:phone":"+1 514 271 1108",
    "sg:postcode":"H2V 4E6",
    "sg:province":"QC",
    "sg:tags":[
        "dealer",
        "rug"
    ],
    "wof:name":"P P Lalonde Ltee",
    "wof:placetype":"venue"
},
  "geometry": {"coordinates":[-73.59270477290001,45.5181121826],"type":"Point"}
}