{
  "type": "Feature",
  "properties": {
    "addr:full":"165 Marina Park Ave Midland ON L4R 4L1",
    "addr:housenumber":"165",
    "addr:postcode":"l4r 4l1",
    "addr:street":"Marina Park Ave",
    "iso:country":"CA",
    "sg:address":"165 Marina Park Ave",
    "sg:city":"Midland",
    "sg:classifiers":[
        {
            "category":"Recreation",
            "subcategory":"Marina",
            "type":"Entertainment"
        }
    ],
    "sg:phone":"+1 705 527 1212",
    "sg:postcode":"L4R 4L1",
    "sg:province":"ON",
    "sg:tags":[
        "dealer",
        "boat",
        "sales"
    ],
    "wof:name":"Skyline Marina Ltd",
    "wof:placetype":"venue"
},
  "geometry": {"coordinates":[-79.898285,44.757748],"type":"Point"}
}