{
  "type": "Feature",
  "properties": {
    "addr:full":"282 Hamilton Neepawa MB R0J 1H0",
    "addr:housenumber":"282",
    "addr:postcode":"r0j 1h0",
    "addr:street":"Hamilton",
    "iso:country":"CA",
    "sg:address":"282 Hamilton",
    "sg:city":"Neepawa",
    "sg:classifiers":[
        {
            "category":"Government",
            "subcategory":"Fire Station",
            "type":"Public Place"
        }
    ],
    "sg:phone":"+1 ",
    "sg:postcode":"R0J 1H0",
    "sg:province":"MB",
    "sg:tags":[
        "department"
    ],
    "wof:name":"Neepawa Waterworks Supt Office",
    "wof:placetype":"venue"
},
  "geometry": {"coordinates":[-99.47068,50.228497],"type":"Point"}
}