{
  "type": "Feature",
  "properties": {
    "addr:full":"12 Kimberly Dr Kapuskasing ON P5N 1L5",
    "addr:housenumber":"12",
    "addr:postcode":"p5n 1l5",
    "addr:street":"Kimberly Dr",
    "iso:country":"CA",
    "sg:address":"12 Kimberly Dr",
    "sg:city":"Kapuskasing",
    "sg:classifiers":[
        {
            "category":"Social Services",
            "type":"Services"
        }
    ],
    "sg:phone":"+1 705 337 1417",
    "sg:postcode":"P5N 1L5",
    "sg:province":"ON",
    "sg:tags":[
        "organization",
        "welfare"
    ],
    "wof:name":"Kapuskasing & District Assn",
    "wof:placetype":"venue"
},
  "geometry": {"coordinates":[-82.43349499999999,49.42424],"type":"Point"}
}