{
  "type": "Feature",
  "properties": {
    "iso:country":"CA",
    "sg:address":"1566 Johnston Rd",
    "sg:city":"White Rock",
    "sg:classifiers":[
        {
            "category":"Personal",
            "subcategory":"Barber",
            "type":"Services"
        }
    ],
    "sg:phone":"+1 604 531 3771",
    "sg:postcode":"V4B 3Z7",
    "sg:province":"BC",
    "wof:name":"White Rock Barbers",
    "wof:placetype":"venue"
},
  "geometry": {"coordinates":[-122.800964355,49.0305519104],"type":"Point"}
}