{
  "type": "Feature",
  "properties": {
    "iso:country":"CA",
    "sg:address":"48 Fisher St",
    "sg:city":"Toronto",
    "sg:classifiers":[
        {
            "category":"Organizations",
            "subcategory":"Religious Organization",
            "type":"Services"
        }
    ],
    "sg:phone":"+1 416 535 7178",
    "sg:postcode":"M6K 1V8",
    "sg:province":"ON",
    "sg:tags":[
        "church"
    ],
    "wof:name":"Seventh Day Baptist Church",
    "wof:placetype":"venue"
},
  "geometry": {"coordinates":[-79.43338775629999,43.6507415771],"type":"Point"}
}