{
  "type": "Feature",
  "properties": {
    "addr:full":"Burnaby BC V5J 3H6",
    "addr:postcode":"v5j 3h6",
    "iso:country":"CA",
    "sg:city":"Burnaby",
    "sg:classifiers":[
        {
            "category":"Wholesale",
            "subcategory":"Non-durable Goods",
            "type":"Manufacturing & Wholesale Goods"
        }
    ],
    "sg:phone":"+1 604 433 8664",
    "sg:postcode":"V5J 3H6",
    "sg:province":"BC",
    "wof:name":"Mega Flow Investments",
    "wof:placetype":"venue"
},
  "geometry": {"coordinates":[-122.99711600000001,49.193756],"type":"Point"}
}