{
  "type": "Feature",
  "properties": {
    "addr:full":"1052 Wilson Ave North York ON M3K 1G6",
    "addr:housenumber":"1052",
    "addr:postcode":"m3k 1g6",
    "addr:street":"Wilson Ave",
    "iso:country":"CA",
    "sg:address":"1052 Wilson Ave",
    "sg:city":"North York",
    "sg:classifiers":[
        {
            "category":"Shopping",
            "subcategory":"Florist",
            "type":"Retail Goods"
        }
    ],
    "sg:phone":"+1 416 630 3662",
    "sg:postcode":"M3K 1G6",
    "sg:province":"ON",
    "wof:name":"Morningdew Flowers Ltd",
    "wof:placetype":"venue"
},
  "geometry": {"coordinates":[-79.48039199999999,43.727528],"type":"Point"}
}