{
  "type": "Feature",
  "properties": {
    "iso:country":"CA",
    "sg:address":"20 Nordale Cres",
    "sg:city":"North York",
    "sg:classifiers":[
        {
            "category":"Building & Trades",
            "subcategory":"Construction",
            "type":"Services"
        }
    ],
    "sg:phone":"+1 416 241 1804",
    "sg:postcode":"M6M 3A1",
    "sg:province":"ON",
    "sg:tags":[
        "contractor"
    ],
    "wof:name":"Craftsmen Custom Builders",
    "wof:placetype":"venue"
},
  "geometry": {"coordinates":[-79.4934387207,43.7007865906],"type":"Point"}
}