{
  "type": "Feature",
  "properties": {
    "addr:full":"Winnipeg MB R3C 4S8",
    "addr:postcode":"r3c 4s8",
    "iso:country":"CA",
    "sg:city":"Winnipeg",
    "sg:classifiers":[
        {
            "category":"Shopping",
            "type":"Retail Goods"
        }
    ],
    "sg:phone":"+1 204 949 0419",
    "sg:postcode":"R3C 4S8",
    "sg:province":"MB",
    "sg:tags":[
        "decoration",
        "light",
        "christmas"
    ],
    "wof:name":"Christmas Traditions the Forks",
    "wof:placetype":"venue"
},
  "geometry": {"coordinates":[-97.12951700000001,49.887482],"type":"Point"}
}