{
  "type": "Feature",
  "properties": {
    "addr:full":"26 Pitt St Cornwall ON K6J 3P2",
    "addr:housenumber":"26",
    "addr:postcode":"k6j 3p2",
    "addr:street":"Pitt St",
    "iso:country":"CA",
    "sg:address":"26 Pitt St",
    "sg:city":"Cornwall",
    "sg:classifiers":[
        {
            "category":"Government",
            "subcategory":"Office",
            "type":"Public Place"
        }
    ],
    "sg:phone":"+1 613 933 4301",
    "sg:postcode":"K6J 3P2",
    "sg:province":"ON",
    "sg:tags":[
        "village"
    ],
    "wof:name":"Stormont Dunas & Glengarry Ofc",
    "wof:placetype":"venue"
},
  "geometry": {"coordinates":[-74.727486,45.015751],"type":"Point"}
}