{
  "type": "Feature",
  "properties": {
    "addr:full":"137 Boul Jutras E Victoriaville QC G6P 4L7",
    "addr:housenumber":"137",
    "addr:postcode":"g6p 4l7",
    "addr:street":"Boul Jutras E",
    "iso:country":"CA",
    "sg:address":"137 Boul Jutras E",
    "sg:city":"Victoriaville",
    "sg:classifiers":[
        {
            "category":"Health Services",
            "subcategory":"Clinic",
            "type":"Services"
        }
    ],
    "sg:phone":"+1 819 752 9252",
    "sg:postcode":"G6P 4L7",
    "sg:province":"QC",
    "sg:tags":[
        "holistic",
        "practitioner"
    ],
    "wof:name":"Clinic Pontbriand",
    "wof:placetype":"venue"
},
  "geometry": {"coordinates":[-71.94593,46.05468],"type":"Point"}
}