{
  "type": "Feature",
  "properties": {
    "addr:full":"10 Downey Lane Valley Road NB E3L 4V9",
    "addr:housenumber":"10",
    "addr:postcode":"e3l 4v9",
    "addr:street":"Downey Lane;Road",
    "iso:country":"CA",
    "sg:address":"10 Downey Lane",
    "sg:city":"Valley Road",
    "sg:classifiers":[
        {
            "category":"Arts & Performance",
            "subcategory":"Theater",
            "type":"Entertainment"
        }
    ],
    "sg:phone":"+1 506 465 9260",
    "sg:postcode":"E3L 4V9",
    "sg:province":"NB",
    "sg:tags":[
        "live",
        "music"
    ],
    "wof:name":"Tempo-Lite Sound & Light Show",
    "wof:placetype":"venue"
},
  "geometry": {"coordinates":[-67.2747879028,45.2368354797],"type":"Point"}
}