{
  "type": "Feature",
  "properties": {
    "addr:full":"1002 Yuill St SE Medicine Hat AB T1A 0Z2",
    "addr:housenumber":"1002",
    "addr:postcode":"t1a 0z2",
    "addr:street":"Yuill St Se",
    "iso:country":"CA",
    "sg:address":"1002 Yuill St SE",
    "sg:city":"Medicine Hat",
    "sg:classifiers":[
        {
            "category":"Organizations",
            "subcategory":"Religious Organization",
            "type":"Services"
        }
    ],
    "sg:phone":"+1 403 526 5803",
    "sg:postcode":"T1A 0Z2",
    "sg:province":"AB",
    "sg:tags":[
        "church"
    ],
    "wof:name":"Iglesia Evangelica Hispana",
    "wof:placetype":"venue"
},
  "geometry": {"coordinates":[-110.661636352,50.0375747681],"type":"Point"}
}