{
  "type": "Feature",
  "properties": {
    "addr:full":"101 Greely Rd Fort Mcmurray AB T9H 4V4",
    "addr:housenumber":"101",
    "addr:postcode":"t9h 4v4",
    "addr:street":"Greely Rd",
    "iso:country":"CA",
    "sg:address":"101 Greely Rd",
    "sg:city":"Fort Mcmurray",
    "sg:classifiers":[
        {
            "category":"Organizations",
            "subcategory":"Religious Organization",
            "type":"Services"
        }
    ],
    "sg:phone":"+1 780 743 3475",
    "sg:postcode":"T9H 4V4",
    "sg:province":"AB",
    "sg:tags":[
        "church"
    ],
    "wof:name":"Seventh Day Adventist Church",
    "wof:placetype":"venue"
},
  "geometry": {"coordinates":[-111.34487915,56.6749038696],"type":"Point"}
}