{
  "type": "Feature",
  "properties": {
    "addr:full":"140 Thomas St # A Oakville ON L6J 3B1",
    "addr:housenumber":"140",
    "addr:postcode":"l6j 3b1",
    "addr:street":"Thomas St # A",
    "iso:country":"CA",
    "sg:address":"140 Thomas St # A",
    "sg:city":"Oakville",
    "sg:classifiers":[
        {
            "category":"Shopping",
            "type":"Retail Goods"
        }
    ],
    "sg:phone":"+1 905 339 1506",
    "sg:postcode":"L6J 3B1",
    "sg:province":"ON",
    "sg:tags":[
        "equipment",
        "wine",
        "supply"
    ],
    "wof:name":"Wine Not",
    "wof:placetype":"venue"
},
  "geometry": {"coordinates":[-79.670349,43.445404],"type":"Point"}
}