{
  "type": "Feature",
  "properties": {
    "iso:country":"CA",
    "sg:address":"633 Main St",
    "sg:city":"Lillooet",
    "sg:classifiers":[
        {
            "category":"Wholesale",
            "subcategory":"Groceries",
            "type":"Manufacturing & Wholesale Goods"
        }
    ],
    "sg:phone":"+1 250 256 7833",
    "sg:postcode":"V0K 1V0",
    "sg:province":"BC",
    "sg:tags":[
        "food",
        "facility"
    ],
    "wof:name":"Gold Panner Restaurant",
    "wof:placetype":"venue"
},
  "geometry": {"coordinates":[-121.93284606900001,50.6827888489],"type":"Point"}
}