{
  "type": "Feature",
  "properties": {
    "addr:full":"19 Eagle Lane Bedford NS B4A 2J5",
    "addr:housenumber":"19",
    "addr:postcode":"b4a 2j5",
    "addr:street":"Eagle Lane",
    "iso:country":"CA",
    "sg:address":"19 Eagle Lane",
    "sg:city":"Bedford",
    "sg:classifiers":[
        {
            "category":"Mining & Drilling",
            "type":"Manufacturing & Wholesale Goods"
        }
    ],
    "sg:phone":"+1 902 835 4776",
    "sg:postcode":"B4A 2J5",
    "sg:province":"NS",
    "sg:tags":[
        "oil",
        "well"
    ],
    "wof:name":"Fmc Energy Systems",
    "wof:placetype":"venue"
},
  "geometry": {"coordinates":[-63.651932,44.724762],"type":"Point"}
}