{
  "type": "Feature",
  "properties": {
    "addr:full":"820 2nd Ave Alameda SK S0C 0A0",
    "addr:housenumber":"820",
    "addr:postcode":"s0c 0a0",
    "addr:street":"2Nd Ave",
    "iso:country":"CA",
    "sg:address":"820 2nd Ave",
    "sg:city":"Alameda",
    "sg:classifiers":[
        {
            "category":"Education",
            "subcategory":"School",
            "type":"Public Place"
        }
    ],
    "sg:phone":"+1 306 489 2230",
    "sg:postcode":"S0C 0A0",
    "sg:province":"SK",
    "wof:name":"Alameda School",
    "wof:placetype":"venue"
},
  "geometry": {"coordinates":[-102.282341,49.266716],"type":"Point"}
}