{
  "type": "Feature",
  "properties": {
    "addr:full":"1 Haanel Dr Nepean ON K1A 1M1",
    "addr:housenumber":"1",
    "addr:postcode":"k1a 1m1",
    "addr:street":"Haanel Dr",
    "iso:country":"CA",
    "sg:address":"1 Haanel Dr",
    "sg:city":"Nepean",
    "sg:classifiers":[
        {
            "category":"Restaurant",
            "type":"Food & Drink"
        }
    ],
    "sg:phone":"+1 613 596 5813",
    "sg:postcode":"K1A 1M1",
    "sg:province":"ON",
    "sg:tags":[
        "caterer"
    ],
    "wof:name":"Lorne Murphy Foods Ltd",
    "wof:placetype":"venue"
},
  "geometry": {"coordinates":[-75.86299099999999,45.318985],"type":"Point"}
}