{
  "type": "Feature",
  "properties": {
    "addr:full":"5037 51 Ave Olds AB T4H 1P5",
    "addr:housenumber":"5037",
    "addr:postcode":"t4h 1p5",
    "addr:street":"51 Ave",
    "iso:country":"CA",
    "sg:address":"5037 51 Ave",
    "sg:city":"Olds",
    "sg:classifiers":[
        {
            "category":"Retail",
            "subcategory":"Portrait Studio",
            "type":"Services"
        }
    ],
    "sg:phone":"+1 403 556 1191",
    "sg:postcode":"T4H 1P5",
    "sg:province":"AB",
    "sg:tags":[
        "photographer"
    ],
    "wof:name":"Harvey Walsh Photography",
    "wof:placetype":"venue"
},
  "geometry": {"coordinates":[-114.106613,51.791203],"type":"Point"}
}