{
  "type": "Feature",
  "properties": {
    "iso:country":"CA",
    "sg:address":"165 Rue Joseph-Robertson",
    "sg:city":"Sherbrooke",
    "sg:classifiers":[
        {
            "category":"Manufacturing",
            "subcategory":"Tools & Machinery",
            "type":"Manufacturing & Wholesale Goods"
        }
    ],
    "sg:phone":"+1 819 569 4207",
    "sg:postcode":"J1L 2W7",
    "sg:province":"QC",
    "sg:tags":[
        "boring",
        "drilling"
    ],
    "wof:name":"Accessoires Geo-Roc-For",
    "wof:placetype":"venue"
},
  "geometry": {"coordinates":[-71.973755,45.39146],"type":"Point"}
}