{
  "type": "Feature",
  "properties": {
    "addr:full":"2385 Marine Dr West Vancouver BC V7V 1K9",
    "addr:housenumber":"2385",
    "addr:postcode":"v7v 1k9",
    "addr:street":"Marine Dr",
    "iso:country":"CA",
    "sg:address":"2385 Marine Dr",
    "sg:city":"West Vancouver",
    "sg:classifiers":[
        {
            "category":"Restaurant",
            "type":"Food & Drink"
        }
    ],
    "sg:phone":"+1 604 926 6060",
    "sg:postcode":"V7V 1K9",
    "sg:province":"BC",
    "wof:name":"Sorrento's Pizza",
    "wof:placetype":"venue"
},
  "geometry": {"coordinates":[-123.17817700000001,49.334061],"type":"Point"}
}