{
  "type": "Feature",
  "properties": {
    "addr:full":"32 Severn Cres Thompson MB R8N 1M6",
    "addr:housenumber":"32",
    "addr:postcode":"r8n 1m6",
    "addr:street":"Severn Cres",
    "iso:country":"CA",
    "sg:address":"32 Severn Cres",
    "sg:city":"Thompson",
    "sg:classifiers":[
        {
            "category":"Building & Trades",
            "subcategory":"Plumbing",
            "type":"Services"
        }
    ],
    "sg:phone":"+1 204 677 3162",
    "sg:postcode":"R8N 1M6",
    "sg:province":"MB",
    "sg:tags":[
        "contractor"
    ],
    "wof:name":"Paul's Plumbing & Heating Ltd",
    "wof:placetype":"venue"
},
  "geometry": {"coordinates":[-97.8685302734,55.7280807495],"type":"Point"}
}