{
  "type": "Feature",
  "properties": {
    "iso:country":"CA",
    "sg:city":"Red Deer",
    "sg:classifiers":[
        {
            "category":"Shopping",
            "subcategory":"Gifts & Souvenirs",
            "type":"Retail Goods"
        }
    ],
    "sg:phone":"+1 403 340 8814",
    "sg:postcode":"T4R 3A2",
    "sg:province":"AB",
    "sg:tags":[
        "collectible"
    ],
    "wof:name":"Hallmark Cards",
    "wof:placetype":"venue"
},
  "geometry": {"coordinates":[-113.814308,52.233261],"type":"Point"}
}