{
  "type": "Feature",
  "properties": {
    "addr:full":"1110 Seymour St Vancouver BC V6B 3N3",
    "addr:housenumber":"1110",
    "addr:postcode":"bc v6b 3n3",
    "addr:street":"Seymour St",
    "iso:country":"CA",
    "sg:address":"1110 Seymour St",
    "sg:city":"Vancouver",
    "sg:classifiers":[
        {
            "category":"Personal",
            "type":"Services"
        }
    ],
    "sg:phone":"+1 604 688 2481",
    "sg:postcode":"V6B 3N3",
    "sg:province":"BC",
    "sg:tags":[
        "wear",
        "formal"
    ],
    "wof:name":"Black & Lee Formal Wear Rntls",
    "wof:placetype":"venue"
},
  "geometry": {"coordinates":[-123.123771667,49.2772941589],"type":"Point"}
}