{
  "type": "Feature",
  "properties": {
    "addr:full":"Vancouver BC V6E 1S3",
    "addr:postcode":"v6e 1s3",
    "iso:country":"CA",
    "sg:city":"Vancouver",
    "sg:classifiers":[
        {
            "category":"Real Estate",
            "subcategory":"Real Estate Operator",
            "type":"Services"
        }
    ],
    "sg:phone":"+1 604 684 5611",
    "sg:postcode":"V6E 1S3",
    "sg:province":"BC",
    "sg:tags":[
        "apartment"
    ],
    "wof:name":"Pacific Cove",
    "wof:placetype":"venue"
},
  "geometry": {"coordinates":[-123.13582599999999,49.280434],"type":"Point"}
}