{
  "type": "Feature",
  "properties": {
    "addr:full":"50 Rue Grande-Ile Salaberry-DE-Valleyfield QC J6S 3L8",
    "addr:housenumber":"50",
    "addr:postcode":"j6s 3l8",
    "addr:street":"Rue Grande-Ile",
    "iso:country":"CA",
    "sg:address":"50 Rue Grande-Ile",
    "sg:city":"Salaberry-DE-Valleyfield",
    "sg:classifiers":[
        {
            "category":"Health Services",
            "subcategory":"Doctor",
            "type":"Services"
        }
    ],
    "sg:phone":"+1 450 371 1580",
    "sg:postcode":"J6S 3L8",
    "sg:province":"QC",
    "sg:tags":[
        "physician",
        "surgeon"
    ],
    "wof:name":"Proulx, Clement MD",
    "wof:placetype":"venue"
},
  "geometry": {"coordinates":[-74.1324539185,45.2631607056],"type":"Point"}
}