{
  "type": "Feature",
  "properties": {
    "addr:full":"2999 Bathurst St North York ON M6B 3B3",
    "addr:housenumber":"2999",
    "addr:postcode":"m6b 3b3",
    "addr:street":"Bathurst St",
    "iso:country":"CA",
    "sg:address":"2999 Bathurst St",
    "sg:city":"North York",
    "sg:classifiers":[
        {
            "category":"Food & Beverages",
            "subcategory":"Fruits & Vegetables",
            "type":"Retail Goods"
        }
    ],
    "sg:phone":"+1 416 780 1347",
    "sg:postcode":"M6B 3B3",
    "sg:province":"ON",
    "sg:tags":[
        "produce"
    ],
    "wof:name":"North Yonge Fruit Market",
    "wof:placetype":"venue"
},
  "geometry": {"coordinates":[-79.42910766599999,43.7173118591],"type":"Point"}
}