{
  "type": "Feature",
  "properties": {
    "addr:full":"4949 Hubalta Rd SE Calgary AB T2B 1T5",
    "addr:housenumber":"4949",
    "addr:postcode":"t2b 1t5",
    "addr:street":"Hubalta Rd Se",
    "iso:country":"CA",
    "sg:address":"4949 Hubalta Rd SE",
    "sg:city":"Calgary",
    "sg:classifiers":[
        {
            "category":"Building & Trades",
            "subcategory":"Construction",
            "type":"Services"
        }
    ],
    "sg:phone":"+1 403 273 7500",
    "sg:postcode":"T2B 1T5",
    "sg:province":"AB",
    "sg:tags":[
        "excavating",
        "breaking",
        "contractor",
        "concrete",
        "cutting",
        "sawing"
    ],
    "wof:name":"A-1 Concrete Cutting & Coring",
    "wof:placetype":"venue"
},
  "geometry": {"coordinates":[-113.962936,51.030956],"type":"Point"}
}