{
  "type": "Feature",
  "properties": {
    "addr:full":"1244 Marine Dr North Vancouver BC V7P 1T2",
    "addr:housenumber":"1244",
    "addr:postcode":"v7p 1t2",
    "addr:street":"Marine Dr",
    "iso:country":"CA",
    "sg:address":"1244 Marine Dr",
    "sg:city":"North Vancouver",
    "sg:classifiers":[
        {
            "category":"Retail",
            "subcategory":"Laundry & Dry Cleaning",
            "type":"Services"
        }
    ],
    "sg:phone":"+1 604 980 2267",
    "sg:postcode":"V7P 1T2",
    "sg:province":"BC",
    "sg:tags":[
        "cleaners"
    ],
    "wof:name":"Valiant Cleaners Ltd",
    "wof:placetype":"venue"
},
  "geometry": {"coordinates":[-123.109008789,49.3239479065],"type":"Point"}
}