{
  "type": "Feature",
  "properties": {
    "addr:full":"5000 Dufferin St North York ON M3H 5T5",
    "addr:housenumber":"5000",
    "addr:postcode":"m3h 5t5",
    "addr:street":"Dufferin St",
    "iso:country":"CA",
    "sg:address":"5000 Dufferin St",
    "sg:city":"North York",
    "sg:classifiers":[
        {
            "category":"Restaurant",
            "type":"Food & Drink"
        }
    ],
    "sg:phone":"+1 416 739 7748",
    "sg:postcode":"M3H 5T5",
    "sg:province":"ON",
    "wof:name":"Banners Restaurants of Canada",
    "wof:placetype":"venue"
},
  "geometry": {"coordinates":[-79.47013099999999,43.781361],"type":"Point"}
}