{
  "type": "Feature",
  "properties": {
    "addr:full":"3470 Mainway Burlington ON L7M 1A8",
    "addr:housenumber":"3470",
    "addr:postcode":"l7m 1a8",
    "addr:street":"Mainway",
    "iso:country":"CA",
    "sg:address":"3470 Mainway",
    "sg:city":"Burlington",
    "sg:classifiers":[
        {
            "category":"Manufacturing",
            "subcategory":"Tools & Machinery",
            "type":"Manufacturing & Wholesale Goods"
        }
    ],
    "sg:phone":"+1 905 335 4196",
    "sg:postcode":"L7M 1A8",
    "sg:province":"ON",
    "sg:tags":[
        "machine",
        "shop"
    ],
    "wof:name":"Johnsen Machine CO Ltd",
    "wof:placetype":"venue"
},
  "geometry": {"coordinates":[-79.79795799999999,43.369392],"type":"Point"}
}