{
  "type": "Feature",
  "properties": {
    "addr:full":"54 Prince St Sydney NS B1P 5J7",
    "addr:housenumber":"54",
    "addr:postcode":"b1p 5j7",
    "addr:street":"Prince St",
    "iso:country":"CA",
    "sg:address":"54 Prince St",
    "sg:city":"Sydney",
    "sg:classifiers":[
        {
            "category":"Health Services",
            "subcategory":"Hospital",
            "type":"Services"
        }
    ],
    "sg:phone":"+1 902 539 0025",
    "sg:postcode":"B1P 5J7",
    "sg:province":"NS",
    "sg:tags":[
        "mental"
    ],
    "wof:name":"Cape Breton Community Housing",
    "wof:placetype":"venue"
},
  "geometry": {"coordinates":[-60.194397,46.138004],"type":"Point"}
}