{
  "type": "Feature",
  "properties": {
    "addr:full":"Toronto ON M5H 3Y2",
    "addr:postcode":"m5h 3y2",
    "iso:country":"CA",
    "sg:city":"Toronto",
    "sg:classifiers":[
        {
            "category":"Banks & Credit Unions",
            "subcategory":"Bank",
            "type":"Services"
        }
    ],
    "sg:phone":"+1 416 933 2730",
    "sg:postcode":"M5H 3Y2",
    "sg:province":"ON",
    "sg:tags":[
        "loan"
    ],
    "wof:name":"Roy Nat Inc",
    "wof:placetype":"venue"
},
  "geometry": {"coordinates":[-79.379654,43.648899],"type":"Point"}
}