{
  "type": "Feature",
  "properties": {
    "addr:full":"74 Rue Albert Sherbrooke QC J1H 1M9",
    "addr:housenumber":"74",
    "addr:postcode":"j1h 1m9",
    "addr:street":"Rue Albert",
    "iso:country":"CA",
    "sg:address":"74 Rue Albert",
    "sg:city":"Sherbrooke",
    "sg:classifiers":[
        {
            "category":"Shopping",
            "type":"Retail Goods"
        }
    ],
    "sg:phone":"+1 819 821 2326",
    "sg:postcode":"J1H 1M9",
    "sg:province":"QC",
    "sg:tags":[
        "art",
        "gallery",
        "dealer"
    ],
    "wof:name":"Regroupement Des Artistes Cntn",
    "wof:placetype":"venue"
},
  "geometry": {"coordinates":[-71.890266,45.402714],"type":"Point"}
}