{
  "type": "Feature",
  "properties": {
    "addr:full":"Highway 5 E Humboldt SK S0K 2A0",
    "addr:postcode":"s0k 2a0",
    "addr:street":"Highway 5 E",
    "iso:country":"CA",
    "sg:address":"Highway 5 E",
    "sg:city":"Humboldt",
    "sg:classifiers":[
        {
            "category":"Wholesale",
            "subcategory":"Machinery & Supplies",
            "type":"Manufacturing & Wholesale Goods"
        }
    ],
    "sg:phone":"+1 306 682 9920",
    "sg:postcode":"S0K 2A0",
    "sg:province":"SK",
    "sg:tags":[
        "agricultural",
        "implement"
    ],
    "wof:name":"Farm World Equipment Ltd",
    "wof:placetype":"venue"
},
  "geometry": {"coordinates":[-105.12146758999999,52.2019004822],"type":"Point"}
}