{
  "type": "Feature",
  "properties": {
    "addr:full":"10600 Boul Sainte-Gertrude Montreal-Nord QC H1G 5N4",
    "addr:housenumber":"10600",
    "addr:postcode":"h1g 5n4",
    "addr:street":"Boul Sainte-Gertrude",
    "iso:country":"CA",
    "sg:address":"10600 Boul Sainte-Gertrude",
    "sg:city":"Montreal-Nord",
    "sg:classifiers":[
        {
            "category":"Manufacturing",
            "subcategory":"Tools & Machinery",
            "type":"Manufacturing & Wholesale Goods"
        }
    ],
    "sg:phone":"+1 514 323 0868",
    "sg:postcode":"H1G 5N4",
    "sg:province":"QC",
    "sg:tags":[
        "built",
        "designed"
    ],
    "wof:name":"Shell-O-Matic Inc",
    "wof:placetype":"venue"
},
  "geometry": {"coordinates":[-73.62365,45.594185],"type":"Point"}
}