{
  "type": "Feature",
  "properties": {
    "iso:country":"CA",
    "sg:address":"359 Martindale Rd",
    "sg:city":"Parksville",
    "sg:classifiers":[
        {
            "category":"Real Estate",
            "subcategory":"Architect",
            "type":"Services"
        }
    ],
    "sg:phone":"+1 250 954 0644",
    "sg:postcode":"V9P 1P9",
    "sg:province":"BC",
    "sg:tags":[
        "course",
        "golf"
    ],
    "wof:name":"Ross Rivers Enterprises Ltd",
    "wof:placetype":"venue"
},
  "geometry": {"coordinates":[-124.28800200000001,49.312191],"type":"Point"}
}