{
  "type": "Feature",
  "properties": {
    "addr:full":"Montreal QC H3B 4P7",
    "addr:postcode":"h3b 4p7",
    "iso:country":"CA",
    "sg:city":"Montreal",
    "sg:classifiers":[
        {
            "category":"Professional",
            "type":"Services"
        }
    ],
    "sg:phone":"+1 514 935 0702",
    "sg:postcode":"H3B 4P7",
    "sg:province":"QC",
    "sg:tags":[
        "establishment"
    ],
    "wof:name":"Fox Aviation Inc",
    "wof:placetype":"venue"
},
  "geometry": {"coordinates":[-73.55443572999999,45.5170631409],"type":"Point"}
}