{
  "type": "Feature",
  "properties": {
    "addr:full":"Orillia ON L3V 7T4",
    "addr:postcode":"l3v 7t4",
    "iso:country":"CA",
    "sg:city":"Orillia",
    "sg:classifiers":[
        {
            "category":"Recreation",
            "type":"Entertainment"
        }
    ],
    "sg:phone":"+1 705 325 4194",
    "sg:postcode":"L3V 7T4",
    "sg:province":"ON",
    "sg:tags":[
        "martial",
        "arts",
        "instruction"
    ],
    "wof:name":"Orillia Martial Arts Ctr",
    "wof:placetype":"venue"
},
  "geometry": {"coordinates":[-79.42035675050001,44.638004303],"type":"Point"}
}