{
  "type": "Feature",
  "properties": {
    "addr:full":"1135 Concession St Russell ON K4R 1C8",
    "addr:housenumber":"1135",
    "addr:postcode":"k4r 1c8",
    "addr:street":"Concession St",
    "iso:country":"CA",
    "sg:address":"1135 Concession St",
    "sg:city":"Russell",
    "sg:classifiers":[
        {
            "category":"Shopping",
            "subcategory":"Computers & Home Electronics",
            "type":"Retail Goods"
        }
    ],
    "sg:phone":"+1 613 445 3162",
    "sg:postcode":"K4R 1C8",
    "sg:province":"ON",
    "sg:tags":[
        "equipment",
        "video"
    ],
    "wof:name":"Town & Country Video",
    "wof:placetype":"venue"
},
  "geometry": {"coordinates":[-75.357674,45.256542],"type":"Point"}
}