{
  "type": "Feature",
  "properties": {
    "addr:full":"4900 Rue Pare Montreal QC H4P 1P3",
    "addr:housenumber":"4900",
    "addr:postcode":"h4p 1p3",
    "addr:street":"Rue Pare",
    "iso:country":"CA",
    "sg:address":"4900 Rue Pare",
    "sg:city":"Montreal",
    "sg:classifiers":[
        {
            "category":"Autos & Motor Vehicles",
            "subcategory":"Automobile Sales",
            "type":"Retail Goods"
        }
    ],
    "sg:phone":"+1 514 737 6666",
    "sg:postcode":"H4P 1P3",
    "sg:province":"QC",
    "sg:tags":[
        "car",
        "dealer"
    ],
    "wof:name":"Up-Town Volvo",
    "wof:placetype":"venue"
},
  "geometry": {"coordinates":[-73.651039,45.49918],"type":"Point"}
}