{
  "type": "Feature",
  "properties": {
    "addr:full":"Burnaby BC V5H 2G3",
    "addr:postcode":"v5h 2g3",
    "iso:country":"CA",
    "sg:city":"Burnaby",
    "sg:classifiers":[
        {
            "category":"Health Services",
            "subcategory":"Chiropractor",
            "type":"Services"
        }
    ],
    "sg:phone":"+1 604 438 1150",
    "sg:postcode":"V5H 2G3",
    "sg:province":"BC",
    "wof:name":"Leung, Eric H DC",
    "wof:placetype":"venue"
},
  "geometry": {"coordinates":[-122.982513,49.223141],"type":"Point"}
}