{
  "type": "Feature",
  "properties": {
    "addr:full":"6877 Edwards Blvd Mississauga ON L5T 2T9",
    "addr:housenumber":"6877",
    "addr:postcode":"l5t 2t9",
    "addr:street":"Edwards Blvd",
    "iso:country":"CA",
    "sg:address":"6877 Edwards Blvd",
    "sg:city":"Mississauga",
    "sg:classifiers":[
        {
            "category":"Wholesale",
            "subcategory":"Machinery & Supplies",
            "type":"Manufacturing & Wholesale Goods"
        }
    ],
    "sg:phone":"+1 905 564 9272",
    "sg:postcode":"L5T 2T9",
    "sg:province":"ON",
    "sg:tags":[
        "machine",
        "shop",
        "establishment"
    ],
    "wof:name":"Kar Industrial Ltd",
    "wof:placetype":"venue"
},
  "geometry": {"coordinates":[-79.698776,43.644726],"type":"Point"}
}