{
  "type": "Feature",
  "properties": {
    "addr:full":"2600 John St #112 Markham ON L3R 3W3",
    "addr:housenumber":"2600",
    "addr:postcode":"l3r 3w3",
    "addr:street":"John St # 112",
    "iso:country":"CA",
    "sg:address":"2600 John St #112",
    "sg:city":"Markham",
    "sg:classifiers":[
        {
            "category":"Wholesale",
            "subcategory":"Machinery & Supplies",
            "type":"Manufacturing & Wholesale Goods"
        }
    ],
    "sg:phone":"+1 905 886 0048",
    "sg:postcode":"L3R 3W3",
    "sg:province":"ON",
    "sg:tags":[
        "equipment",
        "motel",
        "hotel"
    ],
    "wof:name":"Henry's Electronics Ltd",
    "wof:placetype":"venue"
},
  "geometry": {"coordinates":[-79.361794,43.824341],"type":"Point"}
}