{
  "type": "Feature",
  "properties": {
    "addr:full":"2 Alpine Ave Winnipeg MB R2M 0Y5",
    "addr:housenumber":"2",
    "addr:postcode":"r2m 0y5",
    "addr:street":"Alpine Ave",
    "iso:country":"CA",
    "sg:address":"2 Alpine Ave",
    "sg:city":"Winnipeg",
    "sg:classifiers":[
        {
            "category":"Banks & Credit Unions",
            "subcategory":"Bank",
            "type":"Services"
        }
    ],
    "sg:phone":"+1 204 985 2710",
    "sg:postcode":"R2M 0Y5",
    "sg:province":"MB",
    "wof:name":"Bank of Montreal",
    "wof:placetype":"venue"
},
  "geometry": {"coordinates":[-97.101021,49.856068],"type":"Point"}
}