{
  "type": "Feature",
  "properties": {
    "iso:country":"CA",
    "sg:address":"2 Alpine Ave",
    "sg:city":"Winnipeg",
    "sg:classifiers":[
        {
            "category":"Banks & Credit Unions",
            "subcategory":"Bank",
            "type":"Services"
        }
    ],
    "sg:phone":"+1 204 985 2710",
    "sg:postcode":"R2M 0Y5",
    "sg:province":"MB",
    "wof:name":"Bank of Montreal",
    "wof:placetype":"venue"
},
  "geometry": {"coordinates":[-97.101021,49.856068],"type":"Point"}
}