{
  "type": "Feature",
  "properties": {
    "iso:country":"CA",
    "sg:address":"1717 Harvey Ave",
    "sg:city":"Kelowna",
    "sg:classifiers":[
        {
            "category":"Retail",
            "subcategory":"Auto Repair",
            "type":"Services"
        }
    ],
    "sg:phone":"+1 250 860 1196",
    "sg:postcode":"V1Y 6G3",
    "sg:province":"BC",
    "sg:tags":[
        "body",
        "automobile",
        "painting"
    ],
    "wof:name":"Mervyn's the Body Shop Ltd",
    "wof:placetype":"venue"
},
  "geometry": {"coordinates":[-119.459274292,49.8818206787],"type":"Point"}
}