{
  "type": "Feature",
  "properties": {
    "addr:full":"626 Mulvey Ave Winnipeg MB R3M 1H4",
    "addr:housenumber":"626",
    "addr:postcode":"r3m 1h4",
    "addr:street":"Mulvey Ave",
    "iso:country":"CA",
    "sg:address":"626 Mulvey Ave",
    "sg:city":"Winnipeg",
    "sg:classifiers":[
        {
            "category":"Building & Trades",
            "subcategory":"Construction",
            "type":"Services"
        }
    ],
    "sg:phone":"+1 204 284 3399",
    "sg:postcode":"R3M 1H4",
    "sg:province":"MB",
    "sg:tags":[
        "marking",
        "maintenance",
        "parking"
    ],
    "wof:name":"Vosper's Parking Lot Ln Pntng",
    "wof:placetype":"venue"
},
  "geometry": {"coordinates":[-97.14801799999999,49.869503],"type":"Point"}
}