{
  "type": "Feature",
  "properties": {
    "iso:country":"CA",
    "sg:address":"130 Muskoka Rd S",
    "sg:city":"Gravenhurst",
    "sg:classifiers":[
        {
            "category":"Shopping",
            "subcategory":"Gifts & Souvenirs",
            "type":"Retail Goods"
        }
    ],
    "sg:phone":"+1 705 687 4333",
    "sg:postcode":"P1P 1X2",
    "sg:province":"ON",
    "sg:tags":[
        "shop"
    ],
    "wof:name":"Chickadee Hollow Country Store",
    "wof:placetype":"venue"
},
  "geometry": {"coordinates":[-79.37371826170001,44.9195556641],"type":"Point"}
}