{
  "type": "Feature",
  "properties": {
    "addr:full":"305 Rang Raimbeault Sainte-Victoire-DE-Sorel QC J0G 1T0",
    "addr:housenumber":"305",
    "addr:postcode":"j0g 1t0",
    "addr:street":"Rang Raimbeault",
    "iso:country":"CA",
    "sg:address":"305 Rang Raimbeault",
    "sg:city":"Sainte-Victoire-DE-Sorel",
    "sg:classifiers":[
        {
            "category":"Wholesale",
            "subcategory":"Auto Parts",
            "type":"Manufacturing & Wholesale Goods"
        }
    ],
    "sg:phone":"+1 450 782 2310",
    "sg:postcode":"J0G 1T0",
    "sg:province":"QC",
    "sg:tags":[
        "automobile",
        "rebuilt"
    ],
    "wof:name":"Garage Yvon Mathieu",
    "wof:placetype":"venue"
},
  "geometry": {"coordinates":[-73.104218,45.973759],"type":"Point"}
}