{
  "type": "Feature",
  "properties": {
    "iso:country":"CA",
    "sg:address":"117 Dundas St",
    "sg:city":"Thamesford",
    "sg:classifiers":[
        {
            "category":"Restaurant",
            "type":"Food & Drink"
        }
    ],
    "sg:phone":"+1 519 285 3466",
    "sg:postcode":"N0M 2M0",
    "sg:province":"ON",
    "sg:tags":[
        "delicatessen",
        "caterer"
    ],
    "wof:name":"Fran's Village Deli",
    "wof:placetype":"venue"
},
  "geometry": {"coordinates":[-80.99360656739999,43.0596618652],"type":"Point"}
}