{
  "type": "Feature",
  "properties": {
    "addr:full":"Toronto ON M5B 2E5",
    "addr:postcode":"m5b 2e5",
    "iso:country":"CA",
    "sg:city":"Toronto",
    "sg:classifiers":[
        {
            "category":"Restaurant",
            "type":"Food & Drink"
        }
    ],
    "sg:phone":"+1 416 977 4777",
    "sg:postcode":"M5B 2E5",
    "sg:province":"ON",
    "wof:name":"Studio Restaurant Tavern",
    "wof:placetype":"venue"
},
  "geometry": {"coordinates":[-79.3789978027,43.6615638733],"type":"Point"}
}