{
  "type": "Feature",
  "properties": {
    "addr:full":"Lindsay ON K9V 4Z1",
    "addr:postcode":"k9v 4z1",
    "iso:country":"CA",
    "sg:city":"Lindsay",
    "sg:classifiers":[
        {
            "category":"Shopping",
            "subcategory":"Clothing, Apparel, & Fashions",
            "type":"Retail Goods"
        }
    ],
    "sg:phone":"+1 705 878 0971",
    "sg:postcode":"K9V 4Z1",
    "sg:province":"ON",
    "wof:name":"Northern Reflections",
    "wof:placetype":"venue"
},
  "geometry": {"coordinates":[-78.75933074949999,44.3500518799],"type":"Point"}
}