{
  "type": "Feature",
  "properties": {
    "addr:full":"55 Rosslinn Rd Cambridge ON N1S 3K2",
    "addr:housenumber":"55",
    "addr:postcode":"n1s 3k2",
    "addr:street":"Rosslinn Rd",
    "iso:country":"CA",
    "sg:address":"55 Rosslinn Rd",
    "sg:city":"Cambridge",
    "sg:classifiers":[
        {
            "category":"Professional",
            "subcategory":"Testing Lab",
            "type":"Services"
        }
    ],
    "sg:phone":"+1 519 240 3909",
    "sg:postcode":"N1S 3K2",
    "sg:province":"ON",
    "sg:tags":[
        "metallurgist"
    ],
    "wof:name":"P J Wiedemann & Assoc",
    "wof:placetype":"venue"
},
  "geometry": {"coordinates":[-80.34214799999999,43.37254],"type":"Point"}
}