{
  "type": "Feature",
  "properties": {
    "addr:full":"2699 Av Watt Sainte-Foy QC G1P 3X3",
    "addr:housenumber":"2699",
    "addr:postcode":"g1p 3x3",
    "addr:street":"Av Watt",
    "iso:country":"CA",
    "sg:address":"2699 Av Watt",
    "sg:city":"Sainte-Foy",
    "sg:classifiers":[
        {
            "category":"Wholesale",
            "subcategory":"Home Furnishings",
            "type":"Manufacturing & Wholesale Goods"
        }
    ],
    "sg:phone":"+1 418 653 5267",
    "sg:postcode":"G1P 3X3",
    "sg:province":"QC",
    "sg:tags":[
        "rug",
        "carpet"
    ],
    "wof:name":"Centura Quebec Ltee",
    "wof:placetype":"venue"
},
  "geometry": {"coordinates":[-71.30583190919999,46.7868881226],"type":"Point"}
}