{
  "type": "Feature",
  "properties": {
    "addr:full":"Huntsville ON P1H 1C2",
    "addr:postcode":"p1h 1c2",
    "iso:country":"CA",
    "sg:city":"Huntsville",
    "sg:classifiers":[
        {
            "category":"Shopping",
            "subcategory":"Computers & Home Electronics",
            "type":"Retail Goods"
        }
    ],
    "sg:phone":"+1 705 789 6600",
    "sg:postcode":"P1H 1C2",
    "sg:province":"ON",
    "sg:tags":[
        "equipment",
        "dealer"
    ],
    "wof:name":"Macs At Work",
    "wof:placetype":"venue"
},
  "geometry": {"coordinates":[-79.2180023193,45.3265647888],"type":"Point"}
}