{
  "type": "Feature",
  "properties": {
    "addr:full":"1710 56 St Delta BC V4L 2B1",
    "addr:housenumber":"1710",
    "addr:postcode":"v4l 2b1",
    "addr:street":"56 St",
    "iso:country":"CA",
    "sg:address":"1710 56 St",
    "sg:city":"Delta",
    "sg:classifiers":[
        {
            "category":"Museum",
            "type":"Entertainment"
        }
    ],
    "sg:phone":"+1 604 943 3313",
    "sg:postcode":"V4L 2B1",
    "sg:province":"BC",
    "sg:tags":[
        "organization",
        "arts",
        "information"
    ],
    "wof:name":"South Delta Artist's Guild",
    "wof:placetype":"venue"
},
  "geometry": {"coordinates":[-123.068557739,49.0348930359],"type":"Point"}
}