{
  "type": "Feature",
  "properties": {
    "addr:full":"213 Main St Maidstone SK S0M 1M0",
    "addr:housenumber":"213",
    "addr:postcode":"s0m 1m0",
    "addr:street":"Main St",
    "iso:country":"CA",
    "sg:address":"213 Main St",
    "sg:city":"Maidstone",
    "sg:classifiers":[
        {
            "category":"Banks & Credit Unions",
            "subcategory":"Bank",
            "type":"Services"
        }
    ],
    "sg:phone":"+1 306 893 2651",
    "sg:postcode":"S0M 1M0",
    "sg:province":"SK",
    "wof:name":"Lloydminster Credit Union",
    "wof:placetype":"venue"
},
  "geometry": {"coordinates":[-109.28984800000001,53.087479],"type":"Point"}
}