{
  "type": "Feature",
  "properties": {
    "addr:full":"3800 Memorial Dr NE Calgary AB T2A 2K2",
    "addr:housenumber":"3800",
    "addr:postcode":"t2a 2k2",
    "addr:street":"Memorial Dr Ne",
    "iso:country":"CA",
    "sg:address":"3800 Memorial Dr NE",
    "sg:city":"Calgary",
    "sg:classifiers":[
        {
            "category":"Shopping",
            "subcategory":"Clothing, Apparel, & Fashions",
            "type":"Retail Goods"
        }
    ],
    "sg:phone":"+1 403 248 7600",
    "sg:postcode":"T2A 2K2",
    "sg:province":"AB",
    "wof:name":"Ricki's Bootlegger",
    "wof:placetype":"venue"
},
  "geometry": {"coordinates":[-113.979935,51.052528],"type":"Point"}
}