{
  "type": "Feature",
  "properties": {
    "addr:full":"2185 Austin Ave Coquitlam BC V3K 3R9",
    "addr:housenumber":"2185",
    "addr:postcode":"v3k 3r9",
    "addr:street":"Austin Ave",
    "iso:country":"CA",
    "sg:address":"2185 Austin Ave",
    "sg:city":"Coquitlam",
    "sg:classifiers":[
        {
            "category":"Real Estate",
            "subcategory":"Real Estate Agent",
            "type":"Services"
        }
    ],
    "sg:phone":"+1 604 945 2414",
    "sg:postcode":"V3K 3R9",
    "sg:province":"BC",
    "wof:name":"Ty-Con Properties Ltd",
    "wof:placetype":"venue"
},
  "geometry": {"coordinates":[-122.834716797,49.2491607666],"type":"Point"}
}