{
  "type": "Feature",
  "properties": {
    "iso:country":"CA",
    "sg:city":"Burlington",
    "sg:classifiers":[
        {
            "category":"Home & Garden",
            "subcategory":"Building Materials",
            "type":"Retail Goods"
        }
    ],
    "sg:phone":"+1 905 319 6240",
    "sg:postcode":"L7L 4X9",
    "sg:province":"ON",
    "sg:tags":[
        "front",
        "plate",
        "window",
        "store"
    ],
    "wof:name":"Braniff Intercity Glass Ltd",
    "wof:placetype":"venue"
},
  "geometry": {"coordinates":[-79.7852554321,43.3760757446],"type":"Point"}
}