{
  "type": "Feature",
  "properties": {
    "iso:country":"CA",
    "sg:city":"Chateau-Richer",
    "sg:classifiers":[
        {
            "category":"Home & Garden",
            "subcategory":"Furniture",
            "type":"Retail Goods"
        }
    ],
    "sg:phone":"+1 418 824 9394",
    "sg:postcode":"G0A 1N0",
    "sg:province":"QC",
    "sg:tags":[
        "hammock"
    ],
    "wof:name":"Maison Du Hamac Inc",
    "wof:placetype":"venue"
},
  "geometry": {"coordinates":[-71.0195617676,46.9677772522],"type":"Point"}
}