{
  "type": "Feature",
  "properties": {
    "iso:country":"CA",
    "sg:city":"Bella Coola",
    "sg:classifiers":[
        {
            "category":"Organizations",
            "subcategory":"Professional Association",
            "type":"Services"
        }
    ],
    "sg:phone":"+1 250 799 5914",
    "sg:postcode":"V0T 1C0",
    "sg:province":"BC",
    "sg:tags":[
        "native"
    ],
    "wof:name":"Healthy Beginnings",
    "wof:placetype":"venue"
},
  "geometry": {"coordinates":[-126.753341675,52.3698158264],"type":"Point"}
}