{
  "type": "Feature",
  "properties": {
    "addr:full":"Front St Bellevue AB T0K 0C0",
    "addr:postcode":"t0k 0c0",
    "addr:street":"Front St",
    "iso:country":"CA",
    "sg:address":"Front St",
    "sg:city":"Bellevue",
    "sg:classifiers":[
        {
            "category":"Personal",
            "subcategory":"Beauty Salon",
            "type":"Services"
        }
    ],
    "sg:phone":"+1 403 564 4141",
    "sg:postcode":"T0K 0C0",
    "sg:province":"AB",
    "wof:name":"Kinga's Hair Shoppe",
    "wof:placetype":"venue"
},
  "geometry": {"coordinates":[-114.365066528,49.576499939],"type":"Point"}
}