{
  "type": "Feature",
  "properties": {
    "addr:full":"1458 Av Maguire Sillery QC G1T 1Z4",
    "addr:housenumber":"1458",
    "addr:postcode":"g1t 1z4",
    "addr:street":"Av Maguire",
    "iso:country":"CA",
    "sg:address":"1458 Av Maguire",
    "sg:city":"Sillery",
    "sg:classifiers":[
        {
            "category":"Professional",
            "subcategory":"Management & Consulting",
            "type":"Services"
        }
    ],
    "sg:phone":"+1 418 681 9382",
    "sg:postcode":"G1T 1Z4",
    "sg:province":"QC",
    "sg:tags":[
        "consultant",
        "business"
    ],
    "wof:name":"Orion Cooperative DE Recherche",
    "wof:placetype":"venue"
},
  "geometry": {"coordinates":[-71.2498016357,46.7796707153],"type":"Point"}
}