{
  "type": "Feature",
  "properties": {
    "addr:full":"60 Lassie Rd Balmertown ON P0V 1C0",
    "addr:housenumber":"60",
    "addr:postcode":"p0v 1c0",
    "addr:street":"Lassie Rd",
    "iso:country":"CA",
    "sg:address":"60 Lassie Rd",
    "sg:city":"Balmertown",
    "sg:classifiers":[
        {
            "category":"Taxi",
            "type":"Transportation"
        }
    ],
    "sg:phone":"+1 807 735 2000",
    "sg:postcode":"P0V 1C0",
    "sg:province":"ON",
    "sg:tags":[
        "taxicab"
    ],
    "wof:name":"Balmer Taxi",
    "wof:placetype":"venue"
},
  "geometry": {"coordinates":[-93.7440567017,51.0569992065],"type":"Point"}
}