{
  "type": "Feature",
  "properties": {
    "iso:country":"CA",
    "sg:address":"PO Box 336",
    "sg:city":"Picture Butte",
    "sg:classifiers":[
        {
            "category":"Farming",
            "subcategory":"Livestock Farm",
            "type":"Manufacturing & Wholesale Goods"
        }
    ],
    "sg:phone":"+1 403 328 9775",
    "sg:postcode":"T0K 1V0",
    "sg:province":"AB",
    "sg:tags":[
        "feeding"
    ],
    "wof:name":"Grandview Cattle Feeders Ltd",
    "wof:placetype":"venue"
},
  "geometry": {"coordinates":[-112.788833618,49.8729743958],"type":"Point"}
}