{
  "type": "Feature",
  "properties": {
    "iso:country":"CA",
    "sg:address":"624 14th St E",
    "sg:city":"Brandon",
    "sg:classifiers":[
        {
            "category":"Communications",
            "subcategory":"Radio Station",
            "type":"Services"
        }
    ],
    "sg:phone":"+1 204 727 7827",
    "sg:postcode":"R7A 7E1",
    "sg:province":"MB",
    "sg:tags":[
        "company",
        "broadcasting"
    ],
    "wof:name":"Star FM",
    "wof:placetype":"venue"
},
  "geometry": {"coordinates":[-99.9210739136,49.8400192261],"type":"Point"}
}