{
  "type": "Feature",
  "properties": {
    "addr:full":"3641 Kingsway # B Vancouver BC V5R 5M1",
    "addr:housenumber":"3641;# b",
    "addr:postcode":"v5r 5m1",
    "addr:street":"Kingsway",
    "iso:country":"CA",
    "sg:address":"3641 Kingsway # B",
    "sg:city":"Vancouver",
    "sg:classifiers":[
        {
            "category":"Wholesale",
            "subcategory":"Durable Goods & Equipment",
            "type":"Manufacturing & Wholesale Goods"
        }
    ],
    "sg:phone":"+1 604 436 4444",
    "sg:postcode":"V5R 5M1",
    "sg:province":"BC",
    "sg:tags":[
        "importer"
    ],
    "wof:name":"Aba Imports",
    "wof:placetype":"venue"
},
  "geometry": {"coordinates":[-123.02507018999999,49.2322692871],"type":"Point"}
}