{
  "type": "Feature",
  "properties": {
    "iso:country":"CA",
    "sg:address":"6654 Rue Sherbrooke E",
    "sg:city":"Montreal",
    "sg:classifiers":[
        {
            "category":"Shopping",
            "subcategory":"Optical Goods",
            "type":"Retail Goods"
        }
    ],
    "sg:phone":"+1 514 255 8727",
    "sg:postcode":"H1N 1C9",
    "sg:province":"QC",
    "sg:tags":[
        "optician"
    ],
    "wof:name":"Lunetterie F Farhat",
    "wof:placetype":"venue"
},
  "geometry": {"coordinates":[-73.542831,45.582878],"type":"Point"}
}