{
  "type": "Feature",
  "properties": {
    "addr:full":"4280 Boul Metropolitain E Saint-Leonard QC H1S 1A2",
    "addr:housenumber":"4280",
    "addr:postcode":"h1s 1a2",
    "addr:street":"Boul Metropolitain E",
    "iso:country":"CA",
    "sg:address":"4280 Boul Metropolitain E",
    "sg:city":"Saint-Leonard",
    "sg:classifiers":[
        {
            "category":"Professional",
            "subcategory":"Computer Services",
            "type":"Services"
        }
    ],
    "sg:phone":"+1 514 728 4584",
    "sg:postcode":"H1S 1A2",
    "sg:province":"QC",
    "wof:name":"Datacom 2000",
    "wof:placetype":"venue"
},
  "geometry": {"coordinates":[-73.59786200000001,45.571827],"type":"Point"}
}