{
  "type": "Feature",
  "properties": {
    "addr:full":"786 Mahon St New Waterford NS B1H 3K9",
    "addr:housenumber":"786",
    "addr:postcode":"b1h 3k9",
    "addr:street":"Mahon St",
    "iso:country":"CA",
    "sg:address":"786 Mahon St",
    "sg:city":"New Waterford",
    "sg:classifiers":[
        {
            "category":"Personal",
            "subcategory":"Beauty Salon",
            "type":"Services"
        }
    ],
    "sg:phone":"+1 902 862 7470",
    "sg:postcode":"B1H 3K9",
    "sg:province":"NS",
    "wof:name":"Unique Hairstyling",
    "wof:placetype":"venue"
},
  "geometry": {"coordinates":[-60.095699,46.240604],"type":"Point"}
}