{
  "type": "Feature",
  "properties": {
    "addr:full":"123 King St Port Colborne ON L3K 4G3",
    "addr:housenumber":"123",
    "addr:postcode":"l3k 4g3",
    "addr:street":"King St",
    "iso:country":"CA",
    "sg:address":"123 King St",
    "sg:city":"Port Colborne",
    "sg:classifiers":[
        {
            "category":"Organizations",
            "subcategory":"Religious Organization",
            "type":"Services"
        }
    ],
    "sg:phone":"+1 905 834 6426",
    "sg:postcode":"L3K 4G3",
    "sg:province":"ON",
    "sg:tags":[
        "church"
    ],
    "wof:name":"St Patrick's Church",
    "wof:placetype":"venue"
},
  "geometry": {"coordinates":[-79.2508773804,42.8832969666],"type":"Point"}
}