{
  "type": "Feature",
  "properties": {
    "addr:full":"6620 Royal Ave West Vancouver BC V7W 2B9",
    "addr:housenumber":"6620",
    "addr:postcode":"v7w 2b9",
    "addr:street":"Royal Ave",
    "iso:country":"CA",
    "sg:address":"6620 Royal Ave",
    "sg:city":"West Vancouver",
    "sg:classifiers":[
        {
            "category":"Restaurant",
            "type":"Food & Drink"
        }
    ],
    "sg:phone":"+1 604 921 6866",
    "sg:postcode":"V7W 2B9",
    "sg:province":"BC",
    "wof:name":"Pudgie's Pizza & Pasta",
    "wof:placetype":"venue"
},
  "geometry": {"coordinates":[-123.274536133,49.3738098145],"type":"Point"}
}