{
  "type": "Feature",
  "properties": {
    "iso:country":"CA",
    "sg:address":"675 Church St",
    "sg:city":"Plantagenet",
    "sg:classifiers":[
        {
            "category":"Home & Garden",
            "subcategory":"Building Materials",
            "type":"Retail Goods"
        }
    ],
    "sg:phone":"+1 613 673 4862",
    "sg:postcode":"K0B 1L0",
    "sg:province":"ON",
    "sg:tags":[
        "lumber"
    ],
    "wof:name":"Lalonde Lumber Inc",
    "wof:placetype":"venue"
},
  "geometry": {"coordinates":[-74.99816894529999,45.5352592468],"type":"Point"}
}