{
  "type": "Feature",
  "properties": {
    "addr:full":"1641 Car Du Gerfaut LA Plaine QC J7M 1H8",
    "addr:housenumber":"1641",
    "addr:postcode":"j7m 1h8",
    "addr:street":"Car Du Gerfaut",
    "iso:country":"CA",
    "sg:address":"1641 Car Du Gerfaut",
    "sg:city":"LA Plaine",
    "sg:classifiers":[
        {
            "category":"Building & Trades",
            "subcategory":"Construction",
            "type":"Services"
        }
    ],
    "sg:phone":"+1 450 477 2554",
    "sg:postcode":"J7M 1H8",
    "sg:province":"QC",
    "sg:tags":[
        "general",
        "contractor"
    ],
    "wof:name":"Jamco Constructions Inc",
    "wof:placetype":"venue"
},
  "geometry": {"coordinates":[-73.727249,45.762386],"type":"Point"}
}