{
  "type": "Feature",
  "properties": {
    "addr:full":"915 Rue Saint-Vallier E Quebec QC G1K 3P9",
    "addr:housenumber":"915",
    "addr:postcode":"g1k 3p9",
    "addr:street":"Rue Saint-Vallier E",
    "iso:country":"CA",
    "sg:address":"915 Rue Saint-Vallier E",
    "sg:city":"Quebec",
    "sg:classifiers":[
        {
            "category":"Shopping",
            "subcategory":"Used Merchandise",
            "type":"Retail Goods"
        }
    ],
    "sg:phone":"+1 418 692 0385",
    "sg:postcode":"G1K 3P9",
    "sg:province":"QC",
    "sg:tags":[
        "second",
        "hand",
        "store",
        "furniture"
    ],
    "wof:name":"Comptoir Emmaus",
    "wof:placetype":"venue"
},
  "geometry": {"coordinates":[-71.215355,46.814728],"type":"Point"}
}