{
  "type": "Feature",
  "properties": {
    "addr:full":"3517 Boul Le Corbusier Laval QC H7L 4Z4",
    "addr:housenumber":"3517",
    "addr:postcode":"h7l 4z4",
    "addr:street":"Boul Le Corbusier",
    "iso:country":"CA",
    "sg:address":"3517 Boul Le Corbusier",
    "sg:city":"Laval",
    "sg:classifiers":[
        {
            "category":"Home & Garden",
            "subcategory":"Building Materials",
            "type":"Retail Goods"
        }
    ],
    "sg:phone":"+1 450 663 2510",
    "sg:postcode":"H7L 4Z4",
    "sg:province":"QC",
    "sg:tags":[
        "windows",
        "door"
    ],
    "wof:name":"Fenetres Thermex Inc",
    "wof:placetype":"venue"
},
  "geometry": {"coordinates":[-73.7565460205,45.5896606445],"type":"Point"}
}