{
  "type": "Feature",
  "properties": {
    "addr:full":"11007 107 Ave NW Edmonton AB T5H 0X6",
    "addr:housenumber":"11007",
    "addr:postcode":"t5h 0x6",
    "addr:street":"107 Ave Nw",
    "iso:country":"CA",
    "sg:address":"11007 107 Ave NW",
    "sg:city":"Edmonton",
    "sg:classifiers":[
        {
            "category":"Social Services",
            "subcategory":"Child Care",
            "type":"Services"
        }
    ],
    "sg:phone":"+1 780 426 6871",
    "sg:postcode":"T5H 0X6",
    "sg:province":"AB",
    "wof:name":"Little Golden Day Care",
    "wof:placetype":"venue"
},
  "geometry": {"coordinates":[-113.51055145300001,53.5512733459],"type":"Point"}
}