{
  "type": "Feature",
  "properties": {
    "addr:full":"PO Box 104 STN Main Edmonton AB T5J 2G9",
    "addr:housenumber":"po",
    "addr:postcode":"t5j 2g9",
    "addr:street":"Box 104 Stn",
    "iso:country":"CA",
    "sg:address":"PO Box 104 STN Main",
    "sg:city":"Edmonton",
    "sg:classifiers":[
        {
            "category":"Wholesale",
            "subcategory":"Electrical",
            "type":"Manufacturing & Wholesale Goods"
        }
    ],
    "sg:phone":"+1 780 975 5021",
    "sg:postcode":"T5J 2G9",
    "sg:province":"AB",
    "sg:tags":[
        "appliance"
    ],
    "wof:name":"Appliance Care",
    "wof:placetype":"venue"
},
  "geometry": {"coordinates":[-113.49037199999999,53.546219],"type":"Point"}
}