{
  "type": "Feature",
  "properties": {
    "addr:full":"Lower Sackville NS B4E 1K3",
    "addr:postcode":"b4e 1k3",
    "iso:country":"CA",
    "sg:city":"Lower Sackville",
    "sg:classifiers":[
        {
            "category":"Food & Beverages",
            "subcategory":"Groceries & Convenience Stores",
            "type":"Retail Goods"
        }
    ],
    "sg:phone":"+1 902 864 1346",
    "sg:postcode":"B4E 1K3",
    "sg:province":"NS",
    "sg:tags":[
        "grocer"
    ],
    "wof:name":"Yohnna Variety",
    "wof:placetype":"venue"
},
  "geometry": {"coordinates":[-63.689808,44.79686],"type":"Point"}
}