{
  "type": "Feature",
  "properties": {
    "addr:full":"1 Boul Cure-Poirier E Longueuil QC J4J 5K7",
    "addr:housenumber":"1",
    "addr:postcode":"j4j 5k7",
    "addr:street":"Boul Cure-Poirier E",
    "iso:country":"CA",
    "sg:address":"1 Boul Cure-Poirier E",
    "sg:city":"Longueuil",
    "sg:classifiers":[
        {
            "category":"Government",
            "subcategory":"Office",
            "type":"Public Place"
        }
    ],
    "sg:phone":"+1 450 463 7085",
    "sg:postcode":"J4J 5K7",
    "sg:province":"QC",
    "sg:tags":[
        "village"
    ],
    "wof:name":"Centre Jeanne-Dufresnoy",
    "wof:placetype":"venue"
},
  "geometry": {"coordinates":[-73.48168200000001,45.529503],"type":"Point"}
}