{
  "type": "Feature",
  "properties": {
    "addr:full":"Highway 2 N Prince Albert SK S6V 5R3",
    "addr:postcode":"s6v 5r3",
    "addr:street":"Highway 2 N",
    "iso:country":"CA",
    "sg:address":"Highway 2 N",
    "sg:city":"Prince Albert",
    "sg:classifiers":[
        {
            "category":"Freight",
            "type":"Transportation"
        }
    ],
    "sg:phone":"+1 306 763 4224",
    "sg:postcode":"S6V 5R3",
    "sg:province":"SK",
    "sg:tags":[
        "commercial",
        "storage"
    ],
    "wof:name":"Pa U-Store-It Ltd",
    "wof:placetype":"venue"
},
  "geometry": {"coordinates":[-105.752876282,53.1994400024],"type":"Point"}
}