{
  "type": "Feature",
  "properties": {
    "addr:full":"Calgary AB T2T 0A2",
    "addr:postcode":"t2t 0a2",
    "iso:country":"CA",
    "sg:city":"Calgary",
    "sg:classifiers":[
        {
            "category":"Social Services",
            "type":"Services"
        }
    ],
    "sg:phone":"+1 403 286 2822",
    "sg:postcode":"T2T 0A2",
    "sg:province":"AB",
    "sg:tags":[
        "counseling"
    ],
    "wof:name":"Footprints Counselling Svc",
    "wof:placetype":"venue"
},
  "geometry": {"coordinates":[-114.08253499999999,51.037937],"type":"Point"}
}