{
  "type": "Feature",
  "properties": {
    "addr:full":"1027 34 St SE Calgary AB T2A 0Z7",
    "addr:housenumber":"1027",
    "addr:postcode":"t2a 0z7",
    "addr:street":"34 St Se",
    "iso:country":"CA",
    "sg:address":"1027 34 St SE",
    "sg:city":"Calgary",
    "sg:classifiers":[
        {
            "category":"Manufacturing",
            "subcategory":"Metals",
            "type":"Manufacturing & Wholesale Goods"
        }
    ],
    "sg:phone":"+1 403 272 5095",
    "sg:postcode":"T2A 0Z7",
    "sg:province":"AB",
    "sg:tags":[
        "steel"
    ],
    "wof:name":"Gee-Pard Industries Inc",
    "wof:placetype":"venue"
},
  "geometry": {"coordinates":[-113.984848,51.044174],"type":"Point"}
}