{
  "type": "Feature",
  "properties": {
    "addr:full":"3126 Rue Principale Saint-Jean-Baptiste QC J0L 2B0",
    "addr:housenumber":"3126",
    "addr:postcode":"j0l 2b0",
    "addr:street":"Rue Principale",
    "iso:country":"CA",
    "sg:address":"3126 Rue Principale",
    "sg:city":"Saint-Jean-Baptiste",
    "sg:classifiers":[
        {
            "category":"Cinema",
            "subcategory":"Movie Rental",
            "type":"Entertainment"
        }
    ],
    "sg:phone":"+1 450 467 0004",
    "sg:postcode":"J0L 2B0",
    "sg:province":"QC",
    "sg:tags":[
        "leasing",
        "video",
        "disc",
        "tape"
    ],
    "wof:name":"Video Action Enr",
    "wof:placetype":"venue"
},
  "geometry": {"coordinates":[-73.1260299683,45.5192909241],"type":"Point"}
}