{
  "type": "Feature",
  "properties": {
    "addr:full":"1135 Barmac Dr North York ON M9L 1X4",
    "addr:housenumber":"1135",
    "addr:postcode":"m9l 1x4",
    "addr:street":"Barmac Dr",
    "iso:country":"CA",
    "sg:address":"1135 Barmac Dr",
    "sg:city":"North York",
    "sg:classifiers":[
        {
            "category":"Retail",
            "subcategory":"Auto Repair",
            "type":"Services"
        }
    ],
    "sg:phone":"+1 416 746 8270",
    "sg:postcode":"M9L 1X4",
    "sg:province":"ON",
    "sg:tags":[
        "repairing",
        "automobile",
        "painting"
    ],
    "wof:name":"Thompson Auto Body",
    "wof:placetype":"venue"
},
  "geometry": {"coordinates":[-79.55414581300001,43.7670059204],"type":"Point"}
}