{
  "type": "Feature",
  "properties": {
    "addr:full":"192 Raglan St S Renfrew ON K7V 1R1",
    "addr:housenumber":"192",
    "addr:postcode":"k7v 1r1",
    "addr:street":"Raglan St S",
    "iso:country":"CA",
    "sg:address":"192 Raglan St S",
    "sg:city":"Renfrew",
    "sg:classifiers":[
        {
            "category":"Organizations",
            "subcategory":"Labor Organization",
            "type":"Services"
        }
    ],
    "sg:phone":"+1 613 432 8873",
    "sg:postcode":"K7V 1R1",
    "sg:province":"ON",
    "wof:name":"Cupe",
    "wof:placetype":"venue"
},
  "geometry": {"coordinates":[-76.6842956543,45.4718856812],"type":"Point"}
}