{
  "type": "Feature",
  "properties": {
    "iso:country":"CA",
    "sg:address":"1740 Broadway W",
    "sg:city":"Vancouver",
    "sg:classifiers":[
        {
            "category":"Shopping",
            "subcategory":"Computers & Home Electronics",
            "type":"Retail Goods"
        }
    ],
    "sg:phone":"+1 604 739 3000",
    "sg:postcode":"V6J 1Y1",
    "sg:province":"BC",
    "sg:tags":[
        "equipment",
        "electronic",
        "supply"
    ],
    "wof:name":"Future Shop",
    "wof:placetype":"venue"
},
  "geometry": {"coordinates":[-123.144439697,49.2635726929],"type":"Point"}
}