{
  "type": "Feature",
  "properties": {
    "addr:full":"Burlington ON L7R 2H3",
    "addr:postcode":"l7r 2h3",
    "iso:country":"CA",
    "sg:city":"Burlington",
    "sg:classifiers":[
        {
            "category":"Health Services",
            "subcategory":"Doctor",
            "type":"Services"
        }
    ],
    "sg:phone":"+1 905 333 9255",
    "sg:postcode":"L7R 2H3",
    "sg:province":"ON",
    "sg:tags":[
        "physician",
        "surgeon"
    ],
    "wof:name":"Korkis, J A MD",
    "wof:placetype":"venue"
},
  "geometry": {"coordinates":[-79.805779,43.330971],"type":"Point"}
}