{
  "type": "Feature",
  "properties": {
    "addr:full":"39195 Cariboo Hwy Hixon BC V0K 1S0",
    "addr:postcode":"39195;v0k 1s0",
    "addr:street":"Cariboo Hwy",
    "iso:country":"CA",
    "sg:address":"39195 Cariboo Hwy",
    "sg:city":"Hixon",
    "sg:classifiers":[
        {
            "category":"Restaurant",
            "type":"Food & Drink"
        }
    ],
    "sg:phone":"+1 250 998 4563",
    "sg:postcode":"V0K 1S0",
    "sg:province":"BC",
    "wof:name":"Hixon Take Out",
    "wof:placetype":"venue"
},
  "geometry": {"coordinates":[-122.58530426,53.4194602966],"type":"Point"}
}