{
  "type": "Feature",
  "properties": {
    "addr:full":"Nepean ON K2E 1A2",
    "addr:postcode":"k2e 1a2",
    "iso:country":"CA",
    "sg:city":"Nepean",
    "sg:classifiers":[
        {
            "category":"Professional",
            "subcategory":"Research",
            "type":"Services"
        }
    ],
    "sg:phone":"+1 613 226 2456",
    "sg:postcode":"K2E 1A2",
    "sg:province":"ON",
    "sg:tags":[
        "environmental",
        "ecological"
    ],
    "wof:name":"Aqua Terre Solutions Inc",
    "wof:placetype":"venue"
},
  "geometry": {"coordinates":[-75.702873,45.335693],"type":"Point"}
}