{
  "type": "Feature",
  "properties": {
    "addr:full":"765 Myrtle St W Ashburn ON L0B 1A0",
    "addr:housenumber":"765",
    "addr:postcode":"l0b 1a0",
    "addr:street":"Myrtle St W",
    "iso:country":"CA",
    "sg:address":"765 Myrtle St W",
    "sg:city":"Ashburn",
    "sg:classifiers":[
        {
            "category":"Organizations",
            "subcategory":"Religious Organization",
            "type":"Services"
        }
    ],
    "sg:phone":"+1 905 655 8509",
    "sg:postcode":"L0B 1A0",
    "sg:province":"ON",
    "sg:tags":[
        "church"
    ],
    "wof:name":"Burns Presbyterian Church",
    "wof:placetype":"venue"
},
  "geometry": {"coordinates":[-78.998947,44.00116],"type":"Point"}
}