{
  "type": "Feature",
  "properties": {
    "iso:country":"CA",
    "sg:address":"145 Turbine Dr",
    "sg:city":"North York",
    "sg:classifiers":[
        {
            "category":"Retail",
            "subcategory":"Auto Repair",
            "type":"Services"
        }
    ],
    "sg:phone":"+1 416 747 5659",
    "sg:postcode":"M9L 2S7",
    "sg:province":"ON",
    "sg:tags":[
        "repairing",
        "automobile"
    ],
    "wof:name":"Silvio's Service Ctr",
    "wof:placetype":"venue"
},
  "geometry": {"coordinates":[-79.557281,43.7672],"type":"Point"}
}