{
  "type": "Feature",
  "properties": {
    "addr:full":"PO Box 609 STN Main Cobourg ON K9A 4L3",
    "addr:housenumber":"po",
    "addr:postcode":"k9a 4l3",
    "addr:street":"Box 609 Stn Main",
    "iso:country":"CA",
    "sg:address":"PO Box 609 STN Main",
    "sg:city":"Cobourg",
    "sg:classifiers":[
        {
            "category":"Wholesale",
            "subcategory":"Machinery & Supplies",
            "type":"Manufacturing & Wholesale Goods"
        }
    ],
    "sg:phone":"+1 905 372 0400",
    "sg:postcode":"K9A 4L3",
    "sg:province":"ON",
    "sg:tags":[
        "contractor"
    ],
    "wof:name":"D F Batten Equipment Inc",
    "wof:placetype":"venue"
},
  "geometry": {"coordinates":[-78.1677780151,43.9596061707],"type":"Point"}
}