{
  "type": "Feature",
  "properties": {
    "addr:full":"396 Main St Lawrencetown. NS B0S 1M0",
    "addr:housenumber":"396",
    "addr:postcode":"b0s 1m0",
    "addr:street":"Main St",
    "iso:country":"CA",
    "sg:address":"396 Main St",
    "sg:city":"Lawrencetown.",
    "sg:classifiers":[
        {
            "category":"Government",
            "subcategory":"Office",
            "type":"Public Place"
        }
    ],
    "sg:phone":"+1 902 584 2266",
    "sg:postcode":"B0S 1M0",
    "sg:province":"NS",
    "wof:name":"Land Registration & Info",
    "wof:placetype":"venue"
},
  "geometry": {"coordinates":[-63.338531,44.645439],"type":"Point"}
}