{
  "type": "Feature",
  "properties": {
    "addr:full":"165 Arthur St Truro NS B2N 1Y3",
    "addr:housenumber":"165",
    "addr:postcode":"b2n 1y3",
    "addr:street":"Arthur St",
    "iso:country":"CA",
    "sg:address":"165 Arthur St",
    "sg:city":"Truro",
    "sg:classifiers":[
        {
            "category":"Retail",
            "subcategory":"Veterinary Services",
            "type":"Services"
        }
    ],
    "sg:phone":"+1 902 893 2341",
    "sg:postcode":"B2N 1Y3",
    "sg:province":"NS",
    "sg:tags":[
        "veterinarian"
    ],
    "wof:name":"Truro Veterinary Hospital",
    "wof:placetype":"venue"
},
  "geometry": {"coordinates":[-63.281021,45.36198],"type":"Point"}
}