{
  "type": "Feature",
  "properties": {
    "addr:full":"18 Ponderosa Ave Logan Lake BC V0K 1W0",
    "addr:housenumber":"18",
    "addr:postcode":"v0k 1w0",
    "addr:street":"Ponderosa Ave",
    "iso:country":"CA",
    "sg:address":"18 Ponderosa Ave",
    "sg:city":"Logan Lake",
    "sg:classifiers":[
        {
            "category":"Autos & Motor Vehicles",
            "subcategory":"Fuel & Gas Station",
            "type":"Retail Goods"
        }
    ],
    "sg:phone":"+1 250 523 6420",
    "sg:postcode":"V0K 1W0",
    "sg:province":"BC",
    "sg:tags":[
        "oil"
    ],
    "wof:name":"Copper Valley Grocery & Gas",
    "wof:placetype":"venue"
},
  "geometry": {"coordinates":[-120.811859,50.485901],"type":"Point"}
}