{
  "type": "Feature",
  "properties": {
    "iso:country":"CA",
    "sg:city":"Bancroft",
    "sg:classifiers":[
        {
            "category":"Shopping",
            "subcategory":"Used Merchandise",
            "type":"Retail Goods"
        }
    ],
    "sg:phone":"+1 613 339 2350",
    "sg:postcode":"K0L 1C0",
    "sg:province":"ON",
    "sg:tags":[
        "grocer"
    ],
    "wof:name":"White's General Store",
    "wof:placetype":"venue"
},
  "geometry": {"coordinates":[-77.85334777830001,45.0565414429],"type":"Point"}
}