{
  "type": "Feature",
  "properties": {
    "addr:full":"2529 Rue Du Shetland Saint-Lazare QC J7T 2B1",
    "addr:housenumber":"2529",
    "addr:postcode":"j7t 2b1",
    "addr:street":"Rue Du Shetland",
    "iso:country":"CA",
    "sg:address":"2529 Rue Du Shetland",
    "sg:city":"Saint-Lazare",
    "sg:classifiers":[
        {
            "category":"Wholesale",
            "subcategory":"Apparel",
            "type":"Manufacturing & Wholesale Goods"
        }
    ],
    "sg:phone":"+1 450 458 3328",
    "sg:postcode":"J7T 2B1",
    "sg:province":"QC",
    "sg:tags":[
        "clothing"
    ],
    "wof:name":"Geoff Mccrudden Agencies Inc",
    "wof:placetype":"venue"
},
  "geometry": {"coordinates":[-74.156998,45.423168],"type":"Point"}
}