{
  "type": "Feature",
  "properties": {
    "iso:country":"CA",
    "sg:address":"420 North Service Rd E",
    "sg:city":"Oakville",
    "sg:classifiers":[
        {
            "category":"Health Services",
            "subcategory":"Doctor",
            "type":"Services"
        }
    ],
    "sg:phone":"+1 905 845 4370",
    "sg:postcode":"L6H 5R2",
    "sg:province":"ON",
    "sg:tags":[
        "clinic"
    ],
    "wof:name":"Sleep Disorders Investigative",
    "wof:placetype":"venue"
},
  "geometry": {"coordinates":[-79.6834411621,43.4650917053],"type":"Point"}
}