{
  "type": "Feature",
  "properties": {
    "addr:full":"North York ON M2J 5C2",
    "addr:postcode":"m2j 5c2",
    "iso:country":"CA",
    "sg:city":"North York",
    "sg:classifiers":[
        {
            "category":"Wholesale",
            "subcategory":"Plants",
            "type":"Manufacturing & Wholesale Goods"
        }
    ],
    "sg:phone":"+1 416 494 5200",
    "sg:postcode":"M2J 5C2",
    "sg:province":"ON",
    "wof:name":"Tropic International Ltd",
    "wof:placetype":"venue"
},
  "geometry": {"coordinates":[-79.32971999999999,43.774776],"type":"Point"}
}