{
  "type": "Feature",
  "properties": {
    "addr:full":"Qualicum Beach BC V9K 2K1",
    "addr:postcode":"v9k 2k1",
    "iso:country":"CA",
    "sg:city":"Qualicum Beach",
    "sg:classifiers":[
        {
            "category":"Professional",
            "subcategory":"Lawyer & Legal Services",
            "type":"Services"
        }
    ],
    "sg:phone":"+1 250 752 6951",
    "sg:postcode":"V9K 2K1",
    "sg:province":"BC",
    "sg:tags":[
        "attorney"
    ],
    "wof:name":"Walker & Wilson",
    "wof:placetype":"venue"
},
  "geometry": {"coordinates":[-124.44455000000001,49.346722],"type":"Point"}
}