{
  "type": "Feature",
  "properties": {
    "addr:full":"3437 12 St NE Calgary AB T2E 6S6",
    "addr:housenumber":"3437",
    "addr:postcode":"t2e 6s6",
    "addr:street":"12 St Ne",
    "iso:country":"CA",
    "sg:address":"3437 12 St NE",
    "sg:city":"Calgary",
    "sg:classifiers":[
        {
            "category":"Wholesale",
            "subcategory":"Hardware",
            "type":"Manufacturing & Wholesale Goods"
        }
    ],
    "sg:phone":"+1 403 250 2658",
    "sg:postcode":"T2E 6S6",
    "sg:province":"AB",
    "sg:tags":[
        "fastener"
    ],
    "wof:name":"Bolt Supply House Ltd",
    "wof:placetype":"venue"
},
  "geometry": {"coordinates":[-114.029823303,51.0823287964],"type":"Point"}
}