{
  "type": "Feature",
  "properties": {
    "addr:full":"10826 Av Moisan Montreal-Nord QC H1G 4N7",
    "addr:postcode":"h1g 4n7",
    "addr:street":"Av Moisan",
    "iso:country":"CA",
    "sg:address":"10826 Av Moisan",
    "sg:city":"Montreal-Nord",
    "sg:classifiers":[
        {
            "category":"Wholesale",
            "subcategory":"Non-durable Goods",
            "type":"Manufacturing & Wholesale Goods"
        }
    ],
    "sg:phone":"+1 514 321 4964",
    "sg:postcode":"H1G 4N7",
    "sg:province":"QC",
    "wof:name":"Innovart Design Enr",
    "wof:placetype":"venue"
},
  "geometry": {"coordinates":[-73.615776,45.601143],"type":"Point"}
}