{
  "type": "Feature",
  "properties": {
    "addr:full":"601 Boul Valcartier Loretteville QC G2A 2P2",
    "addr:housenumber":"601",
    "addr:postcode":"g2a 2p2",
    "addr:street":"Boul Valcartier",
    "iso:country":"CA",
    "sg:address":"601 Boul Valcartier",
    "sg:city":"Loretteville",
    "sg:classifiers":[
        {
            "category":"Food & Beverages",
            "subcategory":"Groceries & Convenience Stores",
            "type":"Retail Goods"
        }
    ],
    "sg:phone":"+1 418 847 0307",
    "sg:postcode":"G2A 2P2",
    "sg:province":"QC",
    "wof:name":"Marchand Du Faubourg",
    "wof:placetype":"venue"
},
  "geometry": {"coordinates":[-71.378944397,46.8671760559],"type":"Point"}
}