{
  "type": "Feature",
  "properties": {
    "iso:country":"CA",
    "sg:address":"723 Shuswap Ave",
    "sg:city":"Chase",
    "sg:classifiers":[
        {
            "category":"Retail",
            "subcategory":"Repair Shop",
            "type":"Services"
        }
    ],
    "sg:phone":"+1 250 679 8077",
    "sg:postcode":"V0E 1M0",
    "sg:province":"BC",
    "sg:tags":[
        "watch"
    ],
    "wof:name":"Chase Jewellers",
    "wof:placetype":"venue"
},
  "geometry": {"coordinates":[-119.688964844,50.8194885254],"type":"Point"}
}