{
  "type": "Feature",
  "properties": {
    "addr:full":"PO Stan Hope York PE C0A 1P0",
    "addr:postcode":"c0a 1p0",
    "iso:country":"CA",
    "sg:address":"PO Stan Hope",
    "sg:city":"York",
    "sg:classifiers":[
        {
            "category":"Travel",
            "subcategory":"Hotels & Motels",
            "type":"Entertainment"
        }
    ],
    "sg:phone":"+1 902 672 2307",
    "sg:postcode":"C0A 1P0",
    "sg:province":"PE",
    "sg:tags":[
        "cottage",
        "cabin"
    ],
    "wof:name":"By the Bay Cottages",
    "wof:placetype":"venue"
},
  "geometry": {"coordinates":[-63.0950889587,46.3103408813],"type":"Point"}
}