{
  "type": "Feature",
  "properties": {
    "addr:full":"Mount Forest ON N0G 2L0",
    "addr:postcode":"n0g 2l0",
    "iso:country":"CA",
    "sg:city":"Mount Forest",
    "sg:classifiers":[
        {
            "category":"Arts & Performance",
            "subcategory":"Theater",
            "type":"Entertainment"
        }
    ],
    "sg:phone":"+1 519 323 0433",
    "sg:postcode":"N0G 2L0",
    "sg:province":"ON",
    "wof:name":"Old Roxy",
    "wof:placetype":"venue"
},
  "geometry": {"coordinates":[-80.735824585,43.9821395874],"type":"Point"}
}