{
  "type": "Feature",
  "properties": {
    "iso:country":"CA",
    "sg:address":"7421 Rue Saint-Hubert",
    "sg:city":"Montreal",
    "sg:classifiers":[
        {
            "category":"Personal",
            "type":"Services"
        }
    ],
    "sg:phone":"+1 514 279 4203",
    "sg:postcode":"H2R 2N4",
    "sg:province":"QC",
    "sg:tags":[
        "therapist",
        "massage"
    ],
    "wof:name":"Clinique Massotherapie Des",
    "wof:placetype":"venue"
},
  "geometry": {"coordinates":[-73.61647033689999,45.5423927307],"type":"Point"}
}