{
  "type": "Feature",
  "properties": {
    "addr:full":"North Vancouver BC V7P 3G1",
    "addr:postcode":"v7p 3g1",
    "iso:country":"CA",
    "sg:city":"North Vancouver",
    "sg:classifiers":[
        {
            "category":"Organizations",
            "subcategory":"Professional Association",
            "type":"Services"
        }
    ],
    "sg:phone":"+1 604 988 5564",
    "sg:postcode":"V7P 3G1",
    "sg:province":"BC",
    "wof:name":"Aboriginal Financial Officers",
    "wof:placetype":"venue"
},
  "geometry": {"coordinates":[-123.121475,49.323814],"type":"Point"}
}