{
  "type": "Feature",
  "properties": {
    "addr:full":"1140 Sheppard Ave W #1 North York ON M3K 2A2",
    "addr:housenumber":"1140",
    "addr:postcode":"m3k 2a2",
    "addr:street":"Sheppard Ave W # 1",
    "iso:country":"CA",
    "sg:address":"1140 Sheppard Ave W #1",
    "sg:city":"North York",
    "sg:classifiers":[
        {
            "category":"Professional",
            "type":"Services"
        }
    ],
    "sg:phone":"+1 416 398 7500",
    "sg:postcode":"M3K 2A2",
    "sg:province":"ON",
    "sg:tags":[
        "establishment",
        "architect"
    ],
    "wof:name":"Rafael & Bigauskas",
    "wof:placetype":"venue"
},
  "geometry": {"coordinates":[-79.4685516357,43.7534446716],"type":"Point"}
}