{
  "type": "Feature",
  "properties": {
    "addr:full":"545747 Sideroad 4 Markdale ON N0C 1H0",
    "addr:housenumber":"545747",
    "addr:postcode":"n0c 1h0",
    "addr:street":"Sideroad 4",
    "iso:country":"CA",
    "sg:address":"545747 Sideroad 4",
    "sg:city":"Markdale",
    "sg:classifiers":[
        {
            "category":"Recreation",
            "type":"Entertainment"
        }
    ],
    "sg:phone":"+1 519 986 4412",
    "sg:postcode":"N0C 1H0",
    "sg:province":"ON",
    "sg:tags":[
        "riding",
        "academy"
    ],
    "wof:name":"Hunter Hollow Equestrian Ctr",
    "wof:placetype":"venue"
},
  "geometry": {"coordinates":[-80.648895,44.319134],"type":"Point"}
}