{
  "type": "Feature",
  "properties": {
    "addr:full":"381 Park Ave W Chatham ON N7M 1W6",
    "addr:housenumber":"381",
    "addr:postcode":"n7m 1w6",
    "addr:street":"Park Ave W",
    "iso:country":"CA",
    "sg:address":"381 Park Ave W",
    "sg:city":"Chatham",
    "sg:classifiers":[
        {
            "category":"Manufacturing",
            "subcategory":"Tools & Machinery",
            "type":"Manufacturing & Wholesale Goods"
        }
    ],
    "sg:phone":"+1 519 352 8168",
    "sg:postcode":"N7M 1W6",
    "sg:province":"ON",
    "sg:tags":[
        "die",
        "maker"
    ],
    "wof:name":"Russell Tool & Die Ltd",
    "wof:placetype":"venue"
},
  "geometry": {"coordinates":[-82.1884765625,42.3892631531],"type":"Point"}
}