{
  "type": "Feature",
  "properties": {
    "addr:full":"Nepean ON K2B 8C1",
    "addr:postcode":"k2b 8c1",
    "iso:country":"CA",
    "sg:city":"Nepean",
    "sg:classifiers":[
        {
            "category":"Shopping",
            "subcategory":"Clothing, Apparel, & Fashions",
            "type":"Retail Goods"
        }
    ],
    "sg:phone":"+1 613 726 6547",
    "sg:postcode":"K2B 8C1",
    "sg:province":"ON",
    "wof:name":"Urban Trade",
    "wof:placetype":"venue"
},
  "geometry": {"coordinates":[-75.8051376343,45.3490486145],"type":"Point"}
}