{
  "type": "Feature",
  "properties": {
    "addr:full":"3333 Richardson Way SW Calgary AB T3E 7B6",
    "addr:housenumber":"3333",
    "addr:postcode":"t3e 7b6",
    "addr:street":"Richardson Way Sw",
    "iso:country":"CA",
    "sg:address":"3333 Richardson Way SW",
    "sg:city":"Calgary",
    "sg:classifiers":[
        {
            "category":"Organizations",
            "subcategory":"Religious Organization",
            "type":"Services"
        }
    ],
    "sg:phone":"+1 403 249 8605",
    "sg:postcode":"T3E 7B6",
    "sg:province":"AB",
    "sg:tags":[
        "church"
    ],
    "wof:name":"Bethany Chapel",
    "wof:placetype":"venue"
},
  "geometry": {"coordinates":[-114.131202698,51.0152015686],"type":"Point"}
}