{
  "type": "Feature",
  "properties": {
    "addr:full":"Calgary AB T2P 3H7",
    "addr:postcode":"t2p 3h7",
    "iso:country":"CA",
    "sg:city":"Calgary",
    "sg:classifiers":[
        {
            "category":"Organizations",
            "subcategory":"Community Association",
            "type":"Services"
        }
    ],
    "sg:phone":"+1 403 265 9074",
    "sg:postcode":"T2P 3H7",
    "sg:province":"AB",
    "sg:tags":[
        "club"
    ],
    "wof:name":"Bow Valley Club",
    "wof:placetype":"venue"
},
  "geometry": {"coordinates":[-114.066551,51.047661],"type":"Point"}
}