{
  "type": "Feature",
  "properties": {
    "iso:country":"CA",
    "sg:address":"2 Ch Saint-Lazare # 1",
    "sg:city":"Sainte-Marie-DE-Kent",
    "sg:classifiers":[
        {
            "category":"Food & Beverages",
            "subcategory":"Groceries & Convenience Stores",
            "type":"Retail Goods"
        }
    ],
    "sg:phone":"+1 506 955 3716",
    "sg:postcode":"E4S 2K4",
    "sg:province":"NB",
    "sg:tags":[
        "grocer"
    ],
    "wof:name":"Le Blanc Magasin General",
    "wof:placetype":"venue"
},
  "geometry": {"coordinates":[-67.6262435913,46.530418396],"type":"Point"}
}