{
  "type": "Feature",
  "properties": {
    "addr:full":"St Marys ON N4X 1C9",
    "addr:postcode":"n4x 1c9",
    "iso:country":"CA",
    "sg:city":"St Marys",
    "sg:classifiers":[
        {
            "category":"Manufacturing",
            "subcategory":"Signs",
            "type":"Manufacturing & Wholesale Goods"
        }
    ],
    "sg:phone":"+1 519 393 6657",
    "sg:postcode":"N4X 1C9",
    "sg:province":"ON",
    "wof:name":"Ron Mundy Signs",
    "wof:placetype":"venue"
},
  "geometry": {"coordinates":[-81.141418,43.259491],"type":"Point"}
}