{
  "type": "Feature",
  "properties": {
    "addr:full":"2705 Hwy 3 Creston BC V0B 1G1",
    "addr:housenumber":"2705",
    "addr:postcode":"bc v0b 1g1",
    "addr:street":"Hwy 3",
    "iso:country":"CA",
    "sg:address":"2705 Hwy 3",
    "sg:city":"Creston",
    "sg:classifiers":[
        {
            "category":"Travel",
            "subcategory":"Hotels & Motels",
            "type":"Entertainment"
        }
    ],
    "sg:phone":"+1 250 428 2229",
    "sg:postcode":"V0B 1G1",
    "sg:province":"BC",
    "wof:name":"Sunset Motel",
    "wof:placetype":"venue"
},
  "geometry": {"coordinates":[-116.492081,49.095383],"type":"Point"}
}