{
  "type": "Feature",
  "properties": {
    "addr:full":"630 Boul Rene-Levesque O Montreal QC H3B 1S6",
    "addr:housenumber":"630",
    "addr:postcode":"h3b 1s6",
    "addr:street":"Boul Rene-Levesque O",
    "iso:country":"CA",
    "sg:address":"630 Boul Rene-Levesque O",
    "sg:city":"Montreal",
    "sg:classifiers":[
        {
            "category":"Restaurant",
            "type":"Food & Drink"
        }
    ],
    "sg:phone":"+1 514 866 3347",
    "sg:postcode":"H3B 1S6",
    "sg:province":"QC",
    "wof:name":"Restaurant Bar Le 400 6-30",
    "wof:placetype":"venue"
},
  "geometry": {"coordinates":[-73.566711,45.502335],"type":"Point"}
}