{
  "type": "Feature",
  "properties": {
    "addr:full":"8540 Chilliwack Mountain Rd Chilliwack BC V2R 3W8",
    "addr:housenumber":"8540",
    "addr:postcode":"v2r 3w8",
    "addr:street":"Chilliwack Mountain Rd",
    "iso:country":"CA",
    "sg:address":"8540 Chilliwack Mountain Rd",
    "sg:city":"Chilliwack",
    "sg:classifiers":[
        {
            "category":"Freight",
            "type":"Transportation"
        }
    ],
    "sg:phone":"+1 604 792 0362",
    "sg:postcode":"V2R 3W8",
    "sg:province":"BC",
    "sg:tags":[
        "trucking"
    ],
    "wof:name":"J & L Holdings Ltd",
    "wof:placetype":"venue"
},
  "geometry": {"coordinates":[-121.996933,49.156979],"type":"Point"}
}