{
  "type": "Feature",
  "properties": {
    "addr:full":"Toronto ON M4P 2J3",
    "addr:postcode":"m4p 2j3",
    "iso:country":"CA",
    "sg:city":"Toronto",
    "sg:classifiers":[
        {
            "category":"Personal",
            "subcategory":"Beauty Salon",
            "type":"Services"
        }
    ],
    "sg:phone":"+1 416 322 4884",
    "sg:postcode":"M4P 2J3",
    "sg:province":"ON",
    "wof:name":"Armond Beauty Salon",
    "wof:placetype":"venue"
},
  "geometry": {"coordinates":[-79.40013885499999,43.7143173218],"type":"Point"}
}