{
  "type": "Feature",
  "properties": {
    "iso:country":"CA",
    "sg:address":"62 Clermont Cres",
    "sg:city":"Dartmouth",
    "sg:classifiers":[
        {
            "category":"Manufacturing",
            "subcategory":"Printing",
            "type":"Manufacturing & Wholesale Goods"
        }
    ],
    "sg:phone":"+1 902 435 1805",
    "sg:postcode":"B2W 4P1",
    "sg:province":"NS",
    "sg:tags":[
        "printer"
    ],
    "wof:name":"Forest Printing",
    "wof:placetype":"venue"
},
  "geometry": {"coordinates":[-63.488483429,44.6765785217],"type":"Point"}
}