{
  "type": "Feature",
  "properties": {
    "iso:country":"CA",
    "sg:address":"20 Church Ave",
    "sg:city":"Raymond",
    "sg:classifiers":[
        {
            "category":"Health Services",
            "subcategory":"Doctor",
            "type":"Services"
        }
    ],
    "sg:phone":"+1 403 752 3337",
    "sg:postcode":"T0K 2S0",
    "sg:province":"AB",
    "sg:tags":[
        "physician",
        "surgeon"
    ],
    "wof:name":"Raymond Medical Clinic",
    "wof:placetype":"venue"
},
  "geometry": {"coordinates":[-112.66294860799999,49.4610519409],"type":"Point"}
}