{
  "type": "Feature",
  "properties": {
    "iso:country":"CA",
    "sg:address":"3537 Boul Le Corbusier",
    "sg:city":"Laval",
    "sg:classifiers":[
        {
            "category":"Wholesale",
            "subcategory":"Drugs",
            "type":"Manufacturing & Wholesale Goods"
        }
    ],
    "sg:phone":"+1 450 963 5096",
    "sg:postcode":"H7L 4Z4",
    "sg:province":"QC",
    "sg:tags":[
        "preparation",
        "toilet"
    ],
    "wof:name":"Prestilux Inc",
    "wof:placetype":"venue"
},
  "geometry": {"coordinates":[-73.757149,45.590183],"type":"Point"}
}