{
  "type": "Feature",
  "properties": {
    "addr:full":"41797 Howick-Turnberry Rd Wingham ON N0G 2W0",
    "addr:housenumber":"41797",
    "addr:postcode":"n0g 2w0",
    "addr:street":"Howick-Turnberry Rd",
    "iso:country":"CA",
    "sg:address":"41797 Howick-Turnberry Rd",
    "sg:city":"Wingham",
    "sg:classifiers":[
        {
            "category":"Freight",
            "type":"Transportation"
        }
    ],
    "sg:phone":"+1 519 335 3579",
    "sg:postcode":"N0G 2W0",
    "sg:province":"ON",
    "sg:tags":[
        "grain",
        "elevator"
    ],
    "wof:name":"Underwood Grain Ltd",
    "wof:placetype":"venue"
},
  "geometry": {"coordinates":[-81.3105773926,43.8892440796],"type":"Point"}
}