{
  "type": "Feature",
  "properties": {
    "addr:full":"Winnipeg MB R2K 1G6",
    "addr:postcode":"r2k 1g6",
    "iso:country":"CA",
    "sg:city":"Winnipeg",
    "sg:classifiers":[
        {
            "category":"Retail",
            "subcategory":"Repair Shop",
            "type":"Services"
        }
    ],
    "sg:phone":"+1 204 957 5707",
    "sg:postcode":"R2K 1G6",
    "sg:province":"MB",
    "sg:tags":[
        "lock",
        "locksmith"
    ],
    "wof:name":"Active Key & Lock CO",
    "wof:placetype":"venue"
},
  "geometry": {"coordinates":[-97.10698699949999,49.9217720032],"type":"Point"}
}