{
  "type": "Feature",
  "properties": {
    "addr:full":"2407 Kaladar Ave Ottawa ON K1V 8B9",
    "addr:housenumber":"2407",
    "addr:postcode":"k1v 8b9",
    "addr:street":"Kaladar Ave",
    "iso:country":"CA",
    "sg:address":"2407 Kaladar Ave",
    "sg:city":"Ottawa",
    "sg:classifiers":[
        {
            "category":"Retail",
            "subcategory":"Auto Repair",
            "type":"Services"
        }
    ],
    "sg:phone":"+1 613 237 2102",
    "sg:postcode":"K1V 8B9",
    "sg:province":"ON",
    "sg:tags":[
        "repairing",
        "automobile"
    ],
    "wof:name":"Art's Auto Repair",
    "wof:placetype":"venue"
},
  "geometry": {"coordinates":[-75.671333,45.377914],"type":"Point"}
}