{
  "type": "Feature",
  "properties": {
    "addr:full":"424 15 St S Lethbridge AB T1J 2Z3",
    "addr:housenumber":"15",
    "addr:postcode":"t1j 2z3",
    "addr:street":"424;St S",
    "iso:country":"CA",
    "sg:address":"424 15 St S",
    "sg:city":"Lethbridge",
    "sg:classifiers":[
        {
            "category":"Building & Trades",
            "subcategory":"Cleaning & Sanitation",
            "type":"Services"
        }
    ],
    "sg:phone":"+1 403 328 8519",
    "sg:postcode":"T1J 2Z3",
    "sg:province":"AB",
    "sg:tags":[
        "janitor"
    ],
    "wof:name":"Landex Carpet Care",
    "wof:placetype":"venue"
},
  "geometry": {"coordinates":[-112.821136475,49.6945381165],"type":"Point"}
}