{
  "type": "Feature",
  "properties": {
    "addr:full":"Oakville ON L6K 3V1",
    "addr:postcode":"l6k 3v1",
    "iso:country":"CA",
    "sg:city":"Oakville",
    "sg:classifiers":[
        {
            "category":"Professional",
            "subcategory":"Detective & Security Services",
            "type":"Services"
        }
    ],
    "sg:phone":"+1 905 844 0028",
    "sg:postcode":"L6K 3V1",
    "sg:province":"ON",
    "sg:tags":[
        "investigator"
    ],
    "wof:name":"R T Brockbank & Assoc",
    "wof:placetype":"venue"
},
  "geometry": {"coordinates":[-79.6949081421,43.4470443726],"type":"Point"}
}