{
  "type": "Feature",
  "properties": {
    "iso:country":"CA",
    "sg:address":"1029 Markham Rd",
    "sg:city":"Scarborough",
    "sg:classifiers":[
        {
            "category":"Retail",
            "subcategory":"Laundry & Dry Cleaning",
            "type":"Services"
        }
    ],
    "sg:phone":"+1 416 439 5258",
    "sg:postcode":"M1H 2Y5",
    "sg:province":"ON",
    "sg:tags":[
        "cleaners"
    ],
    "wof:name":"Brimark Cleaners",
    "wof:placetype":"venue"
},
  "geometry": {"coordinates":[-79.2307128906,43.7741508484],"type":"Point"}
}