{
  "type": "Feature",
  "properties": {
    "addr:full":"225 6th Ave E Regina SK S4N 6A6",
    "addr:housenumber":"225",
    "addr:postcode":"s4n 6a6",
    "addr:street":"6Th Ave E",
    "iso:country":"CA",
    "sg:address":"225 6th Ave E",
    "sg:city":"Regina",
    "sg:classifiers":[
        {
            "category":"Wholesale",
            "subcategory":"Scrap",
            "type":"Manufacturing & Wholesale Goods"
        }
    ],
    "sg:phone":"+1 306 545 5454",
    "sg:postcode":"S4N 6A6",
    "sg:province":"SK",
    "sg:tags":[
        "recycling",
        "center"
    ],
    "wof:name":"Crown Shred & Recycle Inc",
    "wof:placetype":"venue"
},
  "geometry": {"coordinates":[-104.579933166,50.459777832],"type":"Point"}
}