{
  "type": "Feature",
  "properties": {
    "addr:full":"11 Franklin Ave Fort Smith NT X0E 0P0",
    "addr:housenumber":"11",
    "addr:postcode":"x0e 0p0",
    "addr:street":"Franklin Ave",
    "iso:country":"CA",
    "sg:address":"11 Franklin Ave",
    "sg:city":"Fort Smith",
    "sg:classifiers":[
        {
            "category":"Organizations",
            "subcategory":"Community Association",
            "type":"Services"
        }
    ],
    "sg:phone":"+1 867 872 2980",
    "sg:postcode":"X0E 0P0",
    "sg:province":"NT",
    "sg:tags":[
        "native"
    ],
    "wof:name":"Salt River First Nation 195",
    "wof:placetype":"venue"
},
  "geometry": {"coordinates":[-111.902633667,60.0000953674],"type":"Point"}
}