{
  "type": "Feature",
  "properties": {
    "iso:country":"CA",
    "sg:address":"75 Centennial Pky N",
    "sg:city":"Hamilton",
    "sg:classifiers":[
        {
            "category":"Shopping",
            "subcategory":"Photographic Equipment",
            "type":"Retail Goods"
        }
    ],
    "sg:phone":"+1 905 578 5733",
    "sg:postcode":"L8E 2P2",
    "sg:province":"ON",
    "sg:tags":[
        "supply"
    ],
    "wof:name":"Black's Photography",
    "wof:placetype":"venue"
},
  "geometry": {"coordinates":[-79.7634506226,43.2304039001],"type":"Point"}
}