{
  "type": "Feature",
  "properties": {
    "addr:full":"1495 Rue Cunard Laval QC H7S 2H8",
    "addr:housenumber":"1495",
    "addr:postcode":"h7s 2h8",
    "addr:street":"Rue Cunard",
    "iso:country":"CA",
    "sg:address":"1495 Rue Cunard",
    "sg:city":"Laval",
    "sg:classifiers":[
        {
            "category":"Government",
            "subcategory":"Office",
            "type":"Public Place"
        }
    ],
    "sg:phone":"+1 450 662 7569",
    "sg:postcode":"H7S 2H8",
    "sg:province":"QC",
    "sg:tags":[
        "village"
    ],
    "wof:name":"Laval Encan Public",
    "wof:placetype":"venue"
},
  "geometry": {"coordinates":[-73.735573,45.580429],"type":"Point"}
}