{
  "type": "Feature",
  "properties": {
    "addr:full":"9 Broadway St W Yorkton SK S3N 0L3",
    "addr:housenumber":"9",
    "addr:postcode":"s3n 0l3",
    "addr:street":"Broadway St W",
    "iso:country":"CA",
    "sg:address":"9 Broadway St W",
    "sg:city":"Yorkton",
    "sg:classifiers":[
        {
            "category":"Recreation",
            "type":"Entertainment"
        }
    ],
    "sg:phone":"+1 306 783 0650",
    "sg:postcode":"S3N 0L3",
    "sg:province":"SK",
    "sg:tags":[
        "karate",
        "martial",
        "arts",
        "instruction",
        "judo"
    ],
    "wof:name":"Kee's Taekwondo",
    "wof:placetype":"venue"
},
  "geometry": {"coordinates":[-102.463081,51.210445],"type":"Point"}
}