{
  "type": "Feature",
  "properties": {
    "addr:full":"2000 Hawksbrow Pt NW Calgary AB T3G 4C9",
    "addr:postcode":"t3g 4c9",
    "addr:street":"Pt Nw",
    "iso:country":"CA",
    "sg:address":"2000 Hawksbrow Pt NW",
    "sg:city":"Calgary",
    "sg:classifiers":[
        {
            "category":"Real Estate",
            "subcategory":"Real Estate Agent",
            "type":"Services"
        }
    ],
    "sg:phone":"+1 403 547 7210",
    "sg:postcode":"T3G 4C9",
    "sg:province":"AB",
    "wof:name":"Hawkwood Condominium",
    "wof:placetype":"venue"
},
  "geometry": {"coordinates":[-114.176940918,51.1290626526],"type":"Point"}
}