{
  "type": "Feature",
  "properties": {
    "addr:full":"4726 Montrose Rd Niagara Falls ON L2H 1K3",
    "addr:housenumber":"4726",
    "addr:postcode":"l2h 1k3",
    "addr:street":"Montrose Rd",
    "iso:country":"CA",
    "sg:address":"4726 Montrose Rd",
    "sg:city":"Niagara Falls",
    "sg:classifiers":[
        {
            "category":"Food & Beverages",
            "subcategory":"Bakery",
            "type":"Retail Goods"
        }
    ],
    "sg:phone":"+1 905 354 3323",
    "sg:postcode":"L2H 1K3",
    "sg:province":"ON",
    "sg:tags":[
        "baker"
    ],
    "wof:name":"Tartan Bake Shop",
    "wof:placetype":"venue"
},
  "geometry": {"coordinates":[-79.12396240229999,43.1048431396],"type":"Point"}
}