{
  "type": "Feature",
  "properties": {
    "iso:country":"CA",
    "sg:address":"145 Magill St",
    "sg:city":"Lively",
    "sg:classifiers":[
        {
            "category":"Manufacturing",
            "subcategory":"Tools & Machinery",
            "type":"Manufacturing & Wholesale Goods"
        }
    ],
    "sg:phone":"+1 705 692 3661",
    "sg:postcode":"P3Y 1K6",
    "sg:province":"ON",
    "sg:tags":[
        "boring",
        "mining",
        "drilling",
        "equipment"
    ],
    "wof:name":"Mining Technologies Intl",
    "wof:placetype":"venue"
},
  "geometry": {"coordinates":[-81.1202468872,46.4369850159],"type":"Point"}
}