{
  "type": "Feature",
  "properties": {
    "iso:country":"CA",
    "sg:address":"1867 O'Brien St",
    "sg:city":"North Bay",
    "sg:classifiers":[
        {
            "category":"Travel",
            "subcategory":"Travel Agent",
            "type":"Entertainment"
        }
    ],
    "sg:phone":"+1 705 476 3030",
    "sg:postcode":"P1B 5Y7",
    "sg:province":"ON",
    "sg:tags":[
        "agency",
        "bureau"
    ],
    "wof:name":"Letts Travel Svc Ltd",
    "wof:placetype":"venue"
},
  "geometry": {"coordinates":[-79.4554519653,46.3374404907],"type":"Point"}
}