{
  "type": "Feature",
  "properties": {
    "addr:full":"2357 Bridge Rd Oakville ON L6L 2G9",
    "addr:housenumber":"2357",
    "addr:postcode":"l6l 2g9",
    "addr:street":"Bridge Rd",
    "iso:country":"CA",
    "sg:address":"2357 Bridge Rd",
    "sg:city":"Oakville",
    "sg:classifiers":[
        {
            "category":"Professional",
            "subcategory":"Business Services",
            "type":"Services"
        }
    ],
    "sg:phone":"+1 905 825 9269",
    "sg:postcode":"L6L 2G9",
    "sg:province":"ON",
    "sg:tags":[
        "translator",
        "interpreter"
    ],
    "wof:name":"Chartrand Translation Svc",
    "wof:placetype":"venue"
},
  "geometry": {"coordinates":[-79.72350299999999,43.404797],"type":"Point"}
}