{
  "type": "Feature",
  "properties": {
    "addr:full":"2812 Bathurst St North York ON M6B 3A6",
    "addr:housenumber":"2812",
    "addr:postcode":"m6b 3a6",
    "addr:street":"Bathurst St",
    "iso:country":"CA",
    "sg:address":"2812 Bathurst St",
    "sg:city":"North York",
    "sg:classifiers":[
        {
            "category":"Food & Beverages",
            "subcategory":"Groceries & Convenience Stores",
            "type":"Retail Goods"
        }
    ],
    "sg:phone":"+1 416 781 3341",
    "sg:postcode":"M6B 3A6",
    "sg:province":"ON",
    "wof:name":"Glen Park Convenience",
    "wof:placetype":"venue"
},
  "geometry": {"coordinates":[-79.4284667969,43.7133102417],"type":"Point"}
}