{
  "type": "Feature",
  "properties": {
    "addr:full":"1941 Uxbridge Dr NW # 2 Calgary AB T2N 2V2",
    "addr:housenumber":"1941",
    "addr:postcode":"t2n 2v2",
    "addr:street":"Uxbridge Dr Nw # 2",
    "iso:country":"CA",
    "sg:address":"1941 Uxbridge Dr NW # 2",
    "sg:city":"Calgary",
    "sg:classifiers":[
        {
            "category":"Shopping",
            "subcategory":"Pharmacy",
            "type":"Retail Goods"
        }
    ],
    "sg:phone":"+1 403 289 0208",
    "sg:postcode":"T2N 2V2",
    "sg:province":"AB",
    "wof:name":"Stadium Super Drug Mart",
    "wof:placetype":"venue"
},
  "geometry": {"coordinates":[-114.129784,51.070011],"type":"Point"}
}