{
  "type": "Feature",
  "properties": {
    "addr:full":"423 Maple Ave S Burford ON N0E 1A0",
    "addr:housenumber":"423",
    "addr:postcode":"n0e 1a0",
    "addr:street":"Maple Ave S Burford",
    "iso:country":"CA",
    "sg:address":"423 Maple Ave S",
    "sg:city":"Burford",
    "sg:classifiers":[
        {
            "category":"Restaurant",
            "type":"Food & Drink"
        }
    ],
    "sg:phone":"+1 519 449 9999",
    "sg:postcode":"N0E 1A0",
    "sg:province":"ON",
    "sg:tags":[
        "pizza"
    ],
    "wof:name":"Godfather Pizza",
    "wof:placetype":"venue"
},
  "geometry": {"coordinates":[-80.428726,43.101864],"type":"Point"}
}