{
  "type": "Feature",
  "properties": {
    "addr:full":"9016 Commercial St New Minas NS B4N 3E2",
    "addr:housenumber":"9016",
    "addr:postcode":"b4n 3e2",
    "addr:street":"Commercial St",
    "iso:country":"CA",
    "sg:address":"9016 Commercial St",
    "sg:city":"New Minas",
    "sg:classifiers":[
        {
            "category":"Travel",
            "subcategory":"Hotels & Motels",
            "type":"Entertainment"
        }
    ],
    "sg:phone":"+1 902 681 3201",
    "sg:postcode":"B4N 3E2",
    "sg:province":"NS",
    "wof:name":"Greensboro Inn",
    "wof:placetype":"venue"
},
  "geometry": {"coordinates":[-64.459084,45.067734],"type":"Point"}
}