{
  "type": "Feature",
  "properties": {
    "addr:full":"195 King St St Catharines ON L2R 3J6",
    "addr:housenumber":"195",
    "addr:postcode":"l2r 3j6",
    "addr:street":"King St",
    "iso:country":"CA",
    "sg:address":"195 King St",
    "sg:city":"St Catharines",
    "sg:classifiers":[
        {
            "category":"Professional",
            "subcategory":"Lawyer & Legal Services",
            "type":"Services"
        }
    ],
    "sg:phone":"+1 905 687 6551",
    "sg:postcode":"L2R 3J6",
    "sg:province":"ON",
    "sg:tags":[
        "attorney"
    ],
    "wof:name":"Martens, Ron",
    "wof:placetype":"venue"
},
  "geometry": {"coordinates":[-79.24332427980001,43.1617507935],"type":"Point"}
}