{
  "type": "Feature",
  "properties": {
    "addr:full":"Shawinigan QC G9N 1G1",
    "addr:postcode":"g9n 1g1",
    "iso:country":"CA",
    "sg:city":"Shawinigan",
    "sg:classifiers":[
        {
            "category":"Professional",
            "subcategory":"Accounting & Tax Preparation",
            "type":"Services"
        }
    ],
    "sg:phone":"+1 819 536 2561",
    "sg:postcode":"G9N 1G1",
    "sg:province":"QC",
    "sg:tags":[
        "consultant",
        "accountant"
    ],
    "wof:name":"Dessureault Leblanc Lefebvre",
    "wof:placetype":"venue"
},
  "geometry": {"coordinates":[-72.75187683110001,46.5404777527],"type":"Point"}
}