{
  "type": "Feature",
  "properties": {
    "addr:full":"524 Rue DE LA Fabrique Pohenegamook QC G0L 1J0",
    "addr:housenumber":"524",
    "addr:postcode":"g0l 1j0",
    "addr:street":"Rue De La Fabrique",
    "iso:country":"CA",
    "sg:address":"524 Rue DE LA Fabrique",
    "sg:city":"Pohenegamook",
    "sg:classifiers":[
        {
            "category":"Recreation",
            "type":"Entertainment"
        }
    ],
    "sg:phone":"+1 418 893 2982",
    "sg:postcode":"G0L 1J0",
    "sg:province":"QC",
    "sg:tags":[
        "center",
        "hall",
        "auditorium"
    ],
    "wof:name":"Centre Communautaire Sully",
    "wof:placetype":"venue"
},
  "geometry": {"coordinates":[-69.1518173218,47.4554710388],"type":"Point"}
}