{
  "type": "Feature",
  "properties": {
    "iso:country":"CA",
    "sg:address":"2790 Arbutus St",
    "sg:city":"Vancouver",
    "sg:classifiers":[
        {
            "category":"Banks & Credit Unions",
            "subcategory":"Investment Brokerage",
            "type":"Services"
        }
    ],
    "sg:phone":"+1 604 736 5726",
    "sg:postcode":"V6J 3Y6",
    "sg:province":"BC",
    "sg:tags":[
        "company",
        "holding"
    ],
    "wof:name":"Seacliff Holdings Ltd",
    "wof:placetype":"venue"
},
  "geometry": {"coordinates":[-123.15282440199999,49.2611694336],"type":"Point"}
}