{
  "type": "Feature",
  "properties": {
    "addr:full":"Barrie ON L4N 5J4",
    "addr:postcode":"l4n 5j4",
    "iso:country":"CA",
    "sg:city":"Barrie",
    "sg:classifiers":[
        {
            "category":"Shopping",
            "type":"Retail Goods"
        }
    ],
    "sg:phone":"+1 705 739 0617",
    "sg:postcode":"L4N 5J4",
    "sg:province":"ON",
    "sg:tags":[
        "hearing",
        "equipment",
        "supply",
        "impaired"
    ],
    "wof:name":"Sound Central Inc",
    "wof:placetype":"venue"
},
  "geometry": {"coordinates":[-79.694534,44.387619],"type":"Point"}
}