{
  "type": "Feature",
  "properties": {
    "addr:full":"1222 Monks Pass Oakville ON L6M 1M2",
    "addr:housenumber":"1222",
    "addr:postcode":"l6m 1m2",
    "addr:street":"Monks Pass",
    "iso:country":"CA",
    "sg:address":"1222 Monks Pass",
    "sg:city":"Oakville",
    "sg:classifiers":[
        {
            "category":"Professional",
            "subcategory":"Management & Consulting",
            "type":"Services"
        }
    ],
    "sg:phone":"+1 905 825 9677",
    "sg:postcode":"L6M 1M2",
    "sg:province":"ON",
    "sg:tags":[
        "consultant",
        "business"
    ],
    "wof:name":"J V Management & Marketing Svc",
    "wof:placetype":"venue"
},
  "geometry": {"coordinates":[-79.7194519043,43.4425354004],"type":"Point"}
}