{
  "type": "Feature",
  "properties": {
    "addr:full":"135 Dolores Rd North York ON M3L 2L8",
    "addr:housenumber":"135",
    "addr:postcode":"m3l 2l8",
    "addr:street":"Dolores Rd",
    "iso:country":"CA",
    "sg:address":"135 Dolores Rd",
    "sg:city":"North York",
    "sg:classifiers":[
        {
            "category":"Building & Trades",
            "subcategory":"Construction",
            "type":"Services"
        }
    ],
    "sg:phone":"+1 416 630 3974",
    "sg:postcode":"M3L 2L8",
    "sg:province":"ON",
    "sg:tags":[
        "resurfacing",
        "laying",
        "refinishing",
        "floor"
    ],
    "wof:name":"Royal Floor Finish CO Ltd",
    "wof:placetype":"venue"
},
  "geometry": {"coordinates":[-79.510368,43.746601],"type":"Point"}
}