{
  "type": "Feature",
  "properties": {
    "addr:full":"9 Rue Yvan Blainville QC J7C 2A1",
    "addr:housenumber":"9",
    "addr:postcode":"j7c 2a1",
    "addr:street":"Rue Yvan",
    "iso:country":"CA",
    "sg:address":"9 Rue Yvan",
    "sg:city":"Blainville",
    "sg:classifiers":[
        {
            "category":"Home & Garden",
            "subcategory":"Household Appliances",
            "type":"Retail Goods"
        }
    ],
    "sg:phone":"+1 450 435 9999",
    "sg:postcode":"J7C 2A1",
    "sg:province":"QC",
    "wof:name":"J-M Desmarais Enr",
    "wof:placetype":"venue"
},
  "geometry": {"coordinates":[-73.90585327150001,45.6874084473],"type":"Point"}
}