{
  "type": "Feature",
  "properties": {
    "addr:full":"1119 Desmond St Grenfell SK S0G 2B0",
    "addr:housenumber":"1119",
    "addr:postcode":"s0g 2b0",
    "addr:street":"Desmond St",
    "iso:country":"CA",
    "sg:address":"1119 Desmond St",
    "sg:city":"Grenfell",
    "sg:classifiers":[
        {
            "category":"Travel",
            "subcategory":"Hotels & Motels",
            "type":"Entertainment"
        }
    ],
    "sg:phone":"+1 306 697 2846",
    "sg:postcode":"S0G 2B0",
    "sg:province":"SK",
    "wof:name":"Grenfell Homestead Motel",
    "wof:placetype":"venue"
},
  "geometry": {"coordinates":[-102.922607,50.410583],"type":"Point"}
}