{
  "type": "Feature",
  "properties": {
    "addr:full":"1406 Erie St E Windsor ON N9A 3Z9",
    "addr:housenumber":"1406",
    "addr:postcode":"n9a 3z9",
    "addr:street":"Erie St E",
    "iso:country":"CA",
    "sg:address":"1406 Erie St E",
    "sg:city":"Windsor",
    "sg:classifiers":[
        {
            "category":"Personal",
            "subcategory":"Beauty Salon",
            "type":"Services"
        }
    ],
    "sg:phone":"+1 519 256 5693",
    "sg:postcode":"N9A 3Z9",
    "sg:province":"ON",
    "wof:name":"Hana's Beauty Salon",
    "wof:placetype":"venue"
},
  "geometry": {"coordinates":[-83.014565,42.315826],"type":"Point"}
}