{
  "type": "Feature",
  "properties": {
    "addr:full":"Edmonton AB T5S 1H4",
    "addr:postcode":"t5s 1h4",
    "iso:country":"CA",
    "sg:city":"Edmonton",
    "sg:classifiers":[
        {
            "category":"Wholesale",
            "subcategory":"Machinery & Supplies",
            "type":"Manufacturing & Wholesale Goods"
        }
    ],
    "sg:phone":"+1 780 489 3586",
    "sg:postcode":"T5S 1H4",
    "sg:province":"AB",
    "sg:tags":[
        "salon",
        "beauty"
    ],
    "wof:name":"Impact Salon Sales",
    "wof:placetype":"venue"
},
  "geometry": {"coordinates":[-113.62758599999999,53.551888],"type":"Point"}
}