{
  "type": "Feature",
  "properties": {
    "addr:full":"2704 52 St SE Calgary AB T2B 1N2",
    "addr:housenumber":"2704",
    "addr:postcode":"t2b 1n2",
    "addr:street":"52 St Se",
    "iso:country":"CA",
    "sg:address":"2704 52 St SE",
    "sg:city":"Calgary",
    "sg:classifiers":[
        {
            "category":"Autos & Motor Vehicles",
            "subcategory":"Automobile Sales",
            "type":"Retail Goods"
        }
    ],
    "sg:phone":"+1 403 202 7296",
    "sg:postcode":"T2B 1N2",
    "sg:province":"AB",
    "sg:tags":[
        "car",
        "dealer"
    ],
    "wof:name":"Roadsport Auto Credit",
    "wof:placetype":"venue"
},
  "geometry": {"coordinates":[-113.95829773,51.0293960571],"type":"Point"}
}