{
  "type": "Feature",
  "properties": {
    "iso:country":"CA",
    "sg:address":"1817 Campbell Way",
    "sg:city":"Port Mcneill",
    "sg:classifiers":[
        {
            "category":"Restaurant",
            "type":"Food & Drink"
        }
    ],
    "sg:phone":"+1 250 956 3263",
    "sg:postcode":"V0N 2R0",
    "sg:province":"BC",
    "wof:name":"Northern Lights Restaurant",
    "wof:placetype":"venue"
},
  "geometry": {"coordinates":[-127.087486267,50.5892486572],"type":"Point"}
}