{
  "type": "Feature",
  "properties": {
    "addr:full":"53 Riverton Ave Riverton MB R0C 2R0",
    "addr:housenumber":"53",
    "addr:postcode":"r0c 2r0",
    "addr:street":"Riverton Ave",
    "iso:country":"CA",
    "sg:address":"53 Riverton Ave",
    "sg:city":"Riverton",
    "sg:classifiers":[
        {
            "category":"Organizations",
            "subcategory":"Religious Organization",
            "type":"Services"
        }
    ],
    "sg:phone":"+1 204 378 2325",
    "sg:postcode":"R0C 2R0",
    "sg:province":"MB",
    "sg:tags":[
        "church"
    ],
    "wof:name":"Riverton Hnausa Lutheran Ch",
    "wof:placetype":"venue"
},
  "geometry": {"coordinates":[-96.9964523315,50.9984130859],"type":"Point"}
}