{
  "type": "Feature",
  "properties": {
    "addr:full":"52 Canbury Cres Nepean ON K2G 4L4",
    "addr:housenumber":"52",
    "addr:postcode":"k2g 4l4",
    "addr:street":"Canbury Cres",
    "iso:country":"CA",
    "sg:address":"52 Canbury Cres",
    "sg:city":"Nepean",
    "sg:classifiers":[
        {
            "category":"Building & Trades",
            "subcategory":"Landscaping Services",
            "type":"Services"
        }
    ],
    "sg:phone":"+1 613 226 5660",
    "sg:postcode":"K2G 4L4",
    "sg:province":"ON",
    "sg:tags":[
        "landscape",
        "contractor"
    ],
    "wof:name":"F M Interlock Inc",
    "wof:placetype":"venue"
},
  "geometry": {"coordinates":[-75.7440948486,45.3372840881],"type":"Point"}
}