{
  "type": "Feature",
  "properties": {
    "addr:full":"1963 Rue Notre-Dame-DE-Fatima Laval QC H7G 4R9",
    "addr:housenumber":"1963",
    "addr:postcode":"qc h7g 4r9",
    "addr:street":"Rue Notre-Dame-De-Fatima",
    "iso:country":"CA",
    "sg:address":"1963 Rue Notre-Dame-DE-Fatima",
    "sg:city":"Laval",
    "sg:classifiers":[
        {
            "category":"Manufacturing",
            "subcategory":"Apparel",
            "type":"Manufacturing & Wholesale Goods"
        }
    ],
    "sg:phone":"+1 450 668 3766",
    "sg:postcode":"H7G 4R9",
    "sg:province":"QC",
    "sg:tags":[
        "work",
        "clothing"
    ],
    "wof:name":"Louis Hebert Uniforme Inc",
    "wof:placetype":"venue"
},
  "geometry": {"coordinates":[-73.69667800000001,45.592972],"type":"Point"}
}