{
  "type": "Feature",
  "properties": {
    "addr:full":"250 Glenview Ave Toronto ON M4R 1R3",
    "addr:housenumber":"250",
    "addr:postcode":"m4r 1r3",
    "addr:street":"Glenview Ave",
    "iso:country":"CA",
    "sg:address":"250 Glenview Ave",
    "sg:city":"Toronto",
    "sg:classifiers":[
        {
            "category":"Shopping",
            "subcategory":"Computers & Home Electronics",
            "type":"Retail Goods"
        }
    ],
    "sg:phone":"+1 416 489 3840",
    "sg:postcode":"M4R 1R3",
    "sg:province":"ON",
    "sg:tags":[
        "laboratory",
        "software"
    ],
    "wof:name":"User Lab Inc",
    "wof:placetype":"venue"
},
  "geometry": {"coordinates":[-79.412888,43.718327],"type":"Point"}
}