{
  "type": "Feature",
  "properties": {
    "addr:full":"4333 Ledger Ave Burnaby BC V5G 3T3",
    "addr:postcode":"4333;v5g 3t3",
    "addr:street":"Ledger Ave",
    "iso:country":"CA",
    "sg:address":"4333 Ledger Ave",
    "sg:city":"Burnaby",
    "sg:classifiers":[
        {
            "category":"Restaurant",
            "type":"Food & Drink"
        }
    ],
    "sg:phone":"+1 604 298 6621",
    "sg:postcode":"V5G 3T3",
    "sg:province":"BC",
    "sg:tags":[
        "caterer"
    ],
    "wof:name":"Len's Catering Ltd",
    "wof:placetype":"venue"
},
  "geometry": {"coordinates":[-122.971962,49.246334],"type":"Point"}
}