{
  "type": "Feature",
  "properties": {
    "addr:full":"825 Boul Rosemont Montreal QC H2S 1Z7",
    "addr:housenumber":"825",
    "addr:postcode":"h2s 1z7",
    "addr:street":"Boul Rosemont",
    "iso:country":"CA",
    "sg:address":"825 Boul Rosemont",
    "sg:city":"Montreal",
    "sg:classifiers":[
        {
            "category":"Education",
            "subcategory":"Special Training",
            "type":"Public Place"
        }
    ],
    "sg:phone":"+1 514 277 3735",
    "sg:postcode":"H2S 1Z7",
    "sg:province":"QC",
    "sg:tags":[
        "instruction",
        "driving"
    ],
    "wof:name":"Ecole DE Conduite Tecnitec Enr",
    "wof:placetype":"venue"
},
  "geometry": {"coordinates":[-73.596565,45.533421],"type":"Point"}
}