{
  "type": "Feature",
  "properties": {
    "addr:full":"84 Forsythe Ave Brantford ON N3R 3L8",
    "addr:housenumber":"84",
    "addr:postcode":"n3r 3l8",
    "addr:street":"Forsythe Ave",
    "iso:country":"CA",
    "sg:address":"84 Forsythe Ave",
    "sg:city":"Brantford",
    "sg:classifiers":[
        {
            "category":"Personal",
            "subcategory":"Beauty Salon",
            "type":"Services"
        }
    ],
    "sg:phone":"+1 519 754 0094",
    "sg:postcode":"N3R 3L8",
    "sg:province":"ON",
    "wof:name":"Creatatress",
    "wof:placetype":"venue"
},
  "geometry": {"coordinates":[-80.2710723877,43.1807403564],"type":"Point"}
}