{
  "type": "Feature",
  "properties": {
    "iso:country":"CA",
    "sg:address":"132 Banff Rd",
    "sg:city":"Toronto",
    "sg:classifiers":[
        {
            "category":"Professional",
            "subcategory":"Management & Consulting",
            "type":"Services"
        }
    ],
    "sg:phone":"+1 416 489 8438",
    "sg:postcode":"M4P 2P5",
    "sg:province":"ON",
    "sg:tags":[
        "export"
    ],
    "wof:name":"Norditrade Inc",
    "wof:placetype":"venue"
},
  "geometry": {"coordinates":[-79.38275146479999,43.7108802795],"type":"Point"}
}