{
  "type": "Feature",
  "properties": {
    "addr:full":"1671 Hwy 72 Sioux Lookout ON P8T 1A3",
    "addr:housenumber":"1671",
    "addr:postcode":"p8t 1a3",
    "addr:street":"Hwy 72",
    "iso:country":"CA",
    "sg:address":"1671 Hwy 72",
    "sg:city":"Sioux Lookout",
    "sg:classifiers":[
        {
            "category":"Travel",
            "subcategory":"Campground",
            "type":"Entertainment"
        }
    ],
    "sg:phone":"+1 807 737 1349",
    "sg:postcode":"P8T 1A3",
    "sg:province":"ON",
    "sg:tags":[
        "camp",
        "fishing"
    ],
    "wof:name":"Hidden Bay Lodge & Camps",
    "wof:placetype":"venue"
},
  "geometry": {"coordinates":[-91.97279399999999,50.057709],"type":"Point"}
}