{
  "type": "Feature",
  "properties": {
    "addr:full":"1438 Townline Rd N Oshawa ON L1H 8L7",
    "addr:housenumber":"1438",
    "addr:postcode":"l1h 8l7",
    "addr:street":"Townline Rd N",
    "iso:country":"CA",
    "sg:address":"1438 Townline Rd N",
    "sg:city":"Oshawa",
    "sg:classifiers":[
        {
            "category":"Recreation",
            "subcategory":"Marina",
            "type":"Entertainment"
        }
    ],
    "sg:phone":"+1 905 571 3906",
    "sg:postcode":"L1H 8L7",
    "sg:province":"ON",
    "wof:name":"John's Repair Ctr",
    "wof:placetype":"venue"
},
  "geometry": {"coordinates":[-78.8309020996,43.9459648132],"type":"Point"}
}