{
  "type": "Feature",
  "properties": {
    "iso:country":"CA",
    "sg:city":"New Westminster",
    "sg:classifiers":[
        {
            "category":"Real Estate",
            "subcategory":"Real Estate Agent",
            "type":"Services"
        }
    ],
    "sg:phone":"+1 604 522 2312",
    "sg:postcode":"V3L 5S5",
    "sg:province":"BC",
    "sg:tags":[
        "appraiser"
    ],
    "wof:name":"Pacific Appraisals Ltd",
    "wof:placetype":"venue"
},
  "geometry": {"coordinates":[-122.894714355,49.2184295654],"type":"Point"}
}