{
  "type": "Feature",
  "properties": {
    "addr:full":"Sydney NS B1P 6S9",
    "addr:postcode":"b1p 6s9",
    "iso:country":"CA",
    "sg:city":"Sydney",
    "sg:classifiers":[
        {
            "category":"Shopping",
            "subcategory":"Jewelry",
            "type":"Retail Goods"
        }
    ],
    "sg:phone":"+1 902 562 4722",
    "sg:postcode":"B1P 6S9",
    "sg:province":"NS",
    "sg:tags":[
        "jeweler"
    ],
    "wof:name":"Ardene",
    "wof:placetype":"venue"
},
  "geometry": {"coordinates":[-60.128559,46.153339],"type":"Point"}
}