{
  "type": "Feature",
  "properties": {
    "iso:country":"CA",
    "sg:address":"11655 Av Lucien-Gendron",
    "sg:city":"Montreal",
    "sg:classifiers":[
        {
            "category":"Manufacturing",
            "subcategory":"Glass & Minerals",
            "type":"Manufacturing & Wholesale Goods"
        }
    ],
    "sg:phone":"+1 514 648 0865",
    "sg:postcode":"H1E 7A9",
    "sg:province":"QC",
    "sg:tags":[
        "granite",
        "stone"
    ],
    "wof:name":"Primcar Inc Les Pierres",
    "wof:placetype":"venue"
},
  "geometry": {"coordinates":[-73.564293,45.644356],"type":"Point"}
}