{
  "type": "Feature",
  "properties": {
    "addr:full":"800 Grand Lake Rd # 29 Sydney NS B1P 6S9",
    "addr:housenumber":"800;29",
    "addr:postcode":"b1p 6s9",
    "addr:street":"Grand Lake Rd #",
    "iso:country":"CA",
    "sg:address":"800 Grand Lake Rd # 29",
    "sg:city":"Sydney",
    "sg:classifiers":[
        {
            "category":"Shopping",
            "subcategory":"Clothing, Apparel, & Fashions",
            "type":"Retail Goods"
        }
    ],
    "sg:phone":"+1 902 567 3339",
    "sg:postcode":"B1P 6S9",
    "sg:province":"NS",
    "wof:name":"Tabi International",
    "wof:placetype":"venue"
},
  "geometry": {"coordinates":[-60.128559,46.153339],"type":"Point"}
}