{
  "type": "Feature",
  "properties": {
    "addr:full":"3667 Strawberry Hill St Halifax NS B3K 5A8",
    "addr:housenumber":"3667",
    "addr:postcode":"b3k 5a8",
    "addr:street":"Strawberry Hill St",
    "iso:country":"CA",
    "sg:address":"3667 Strawberry Hill St",
    "sg:city":"Halifax",
    "sg:classifiers":[
        {
            "category":"Shopping",
            "subcategory":"Used Merchandise",
            "type":"Retail Goods"
        }
    ],
    "sg:phone":"+1 902 453 1880",
    "sg:postcode":"B3K 5A8",
    "sg:province":"NS",
    "sg:tags":[
        "clothing"
    ],
    "wof:name":"Salvation Army",
    "wof:placetype":"venue"
},
  "geometry": {"coordinates":[-63.6203536987,44.6621322632],"type":"Point"}
}