{
  "type": "Feature",
  "properties": {
    "addr:full":"2775 Rue Saint-Pierre Drummondville QC J2C 7Y1",
    "addr:housenumber":"2775",
    "addr:postcode":"j2c 7y1",
    "addr:street":"Rue Saint-Pierre",
    "iso:country":"CA",
    "sg:address":"2775 Rue Saint-Pierre",
    "sg:city":"Drummondville",
    "sg:classifiers":[
        {
            "category":"Wholesale",
            "subcategory":"Machinery & Supplies",
            "type":"Manufacturing & Wholesale Goods"
        }
    ],
    "sg:phone":"+1 819 472 0999",
    "sg:postcode":"J2C 7Y1",
    "sg:province":"QC",
    "sg:tags":[
        "equipment",
        "pneumatic",
        "component"
    ],
    "wof:name":"Hydraulique & Technologie",
    "wof:placetype":"venue"
},
  "geometry": {"coordinates":[-72.526421,45.863129],"type":"Point"}
}