{
  "type": "Feature",
  "properties": {
    "addr:full":"888 Wallbridge-Loyalist Rd Belleville ON K8N 4Z5",
    "addr:housenumber":"888",
    "addr:postcode":"k8n 4z5",
    "addr:street":"Wallbridge-Loyalist Rd",
    "iso:country":"CA",
    "sg:address":"888 Wallbridge-Loyalist Rd",
    "sg:city":"Belleville",
    "sg:classifiers":[
        {
            "category":"Retail",
            "subcategory":"Auto Repair",
            "type":"Services"
        }
    ],
    "sg:phone":"+1 613 966 0631",
    "sg:postcode":"K8N 4Z5",
    "sg:province":"ON",
    "sg:tags":[
        "truck"
    ],
    "wof:name":"Wheelers Garage Inc",
    "wof:placetype":"venue"
},
  "geometry": {"coordinates":[-77.436066,44.157688],"type":"Point"}
}