{
  "type": "Feature",
  "properties": {
    "addr:full":"15 Government Rd E Kirkland Lake ON P2N 1A1",
    "addr:housenumber":"15",
    "addr:postcode":"p2n 1a1",
    "addr:street":"Government Rd E",
    "iso:country":"CA",
    "sg:address":"15 Government Rd E",
    "sg:city":"Kirkland Lake",
    "sg:classifiers":[
        {
            "category":"Professional",
            "subcategory":"Business Services",
            "type":"Services"
        }
    ],
    "sg:phone":"+1 705 567 9349",
    "sg:postcode":"P2N 1A1",
    "sg:province":"ON",
    "sg:tags":[
        "arbitration",
        "government"
    ],
    "wof:name":"Aide Juridique Ontario",
    "wof:placetype":"venue"
},
  "geometry": {"coordinates":[-80.03173828120001,48.1522445679],"type":"Point"}
}