{
  "type": "Feature",
  "properties": {
    "iso:country":"CA",
    "sg:address":"29 Meadowview Dr",
    "sg:city":"Bedford",
    "sg:classifiers":[
        {
            "category":"Social Services",
            "subcategory":"Child Care",
            "type":"Services"
        }
    ],
    "sg:phone":"+1 902 835 7929",
    "sg:postcode":"B4A 2C3",
    "sg:province":"NS",
    "sg:tags":[
        "school"
    ],
    "wof:name":"Judy's Nursery School",
    "wof:placetype":"venue"
},
  "geometry": {"coordinates":[-63.6572303772,44.7379989624],"type":"Point"}
}