{
  "type": "Feature",
  "properties": {
    "iso:country":"CA",
    "sg:address":"5320 48 Ave SE",
    "sg:city":"Salmon Arm",
    "sg:classifiers":[
        {
            "category":"Manufacturing",
            "subcategory":"Tools & Machinery",
            "type":"Manufacturing & Wholesale Goods"
        }
    ],
    "sg:phone":"+1 250 832 6477",
    "sg:postcode":"V1E 1X2",
    "sg:province":"BC",
    "sg:tags":[
        "equipment",
        "electric"
    ],
    "wof:name":"Valid Mfg Ltd",
    "wof:placetype":"venue"
},
  "geometry": {"coordinates":[-119.223976135,50.664226532],"type":"Point"}
}