{
  "type": "Feature",
  "properties": {
    "addr:full":"489 College St #301 Toronto ON M6G 1A5",
    "addr:housenumber":"489",
    "addr:postcode":"m6g 1a5",
    "addr:street":"College St # 301",
    "iso:country":"CA",
    "sg:address":"489 College St #301",
    "sg:city":"Toronto",
    "sg:classifiers":[
        {
            "category":"Professional",
            "subcategory":"Lawyer & Legal Services",
            "type":"Services"
        }
    ],
    "sg:phone":"+1 416 483 4381",
    "sg:postcode":"M6G 1A5",
    "sg:province":"ON",
    "sg:tags":[
        "attorney"
    ],
    "wof:name":"Bruce, Catherine",
    "wof:placetype":"venue"
},
  "geometry": {"coordinates":[-79.4093551636,43.656036377],"type":"Point"}
}