{
  "type": "Feature",
  "properties": {
    "addr:full":"York ON M6C 1L9",
    "addr:postcode":"m6c 1l9",
    "iso:country":"CA",
    "sg:city":"York",
    "sg:classifiers":[
        {
            "category":"Shopping",
            "subcategory":"Music",
            "type":"Retail Goods"
        }
    ],
    "sg:phone":"+1 416 652 5486",
    "sg:postcode":"M6C 1L9",
    "sg:province":"ON",
    "sg:tags":[
        "compact",
        "record",
        "disc",
        "tape"
    ],
    "wof:name":"Dep Ltee",
    "wof:placetype":"venue"
},
  "geometry": {"coordinates":[-79.4238357544,43.6884307861],"type":"Point"}
}