{
  "type": "Feature",
  "properties": {
    "addr:full":"900 Central Ave Prince Albert SK S6V 4V3",
    "addr:housenumber":"900",
    "addr:postcode":"s6v 4v3",
    "addr:street":"Central Ave",
    "iso:country":"CA",
    "sg:address":"900 Central Ave",
    "sg:city":"Prince Albert",
    "sg:classifiers":[
        {
            "category":"Organizations",
            "subcategory":"Religious Organization",
            "type":"Services"
        }
    ],
    "sg:phone":"+1 306 763 6078",
    "sg:postcode":"S6V 4V3",
    "sg:province":"SK",
    "sg:tags":[
        "church"
    ],
    "wof:name":"Salvation Army",
    "wof:placetype":"venue"
},
  "geometry": {"coordinates":[-105.754150391,53.2047576904],"type":"Point"}
}