{
  "type": "Feature",
  "properties": {
    "addr:full":"38 Brydon Dr Etobicoke ON M9W 4N2",
    "addr:housenumber":"38",
    "addr:postcode":"m9w 4n2",
    "addr:street":"Brydon Dr",
    "iso:country":"CA",
    "sg:address":"38 Brydon Dr",
    "sg:city":"Etobicoke",
    "sg:classifiers":[
        {
            "category":"Retail",
            "subcategory":"Auto Repair",
            "type":"Services"
        }
    ],
    "sg:phone":"+1 416 743 3201",
    "sg:postcode":"M9W 4N2",
    "sg:province":"ON",
    "sg:tags":[
        "repairing",
        "automobile"
    ],
    "wof:name":"Lawrence Transmission",
    "wof:placetype":"venue"
},
  "geometry": {"coordinates":[-79.572388,43.716171],"type":"Point"}
}