{
  "type": "Feature",
  "properties": {
    "addr:full":"675 6th St E Owen Sound ON N4K 1G5",
    "addr:housenumber":"675",
    "addr:postcode":"n4k 1g5",
    "addr:street":"6Th St E",
    "iso:country":"CA",
    "sg:address":"675 6th St E",
    "sg:city":"Owen Sound",
    "sg:classifiers":[
        {
            "category":"Retail",
            "subcategory":"Animal Services",
            "type":"Services"
        }
    ],
    "sg:phone":"+1 519 371 6636",
    "sg:postcode":"N4K 1G5",
    "sg:province":"ON",
    "sg:tags":[
        "pet",
        "grooming",
        "washing"
    ],
    "wof:name":"Doggy Doo's",
    "wof:placetype":"venue"
},
  "geometry": {"coordinates":[-80.9325790405,44.5610466003],"type":"Point"}
}