{
  "type": "Feature",
  "properties": {
    "iso:country":"CA",
    "sg:address":"3141 Boul Taschereau",
    "sg:city":"Greenfield Park",
    "sg:classifiers":[
        {
            "category":"Autos & Motor Vehicles",
            "subcategory":"Automobile Sales",
            "type":"Retail Goods"
        }
    ],
    "sg:phone":"+1 450 671 6115",
    "sg:postcode":"J4V 2H2",
    "sg:province":"QC",
    "sg:tags":[
        "car",
        "dealer"
    ],
    "wof:name":"Automobile Pierre Brault Ltee",
    "wof:placetype":"venue"
},
  "geometry": {"coordinates":[-73.487511,45.500797],"type":"Point"}
}