{
  "type": "Feature",
  "properties": {
    "addr:full":"700 Rue Victoria Edmundston NB E3V 3S9",
    "addr:housenumber":"700",
    "addr:postcode":"e3v 3s9",
    "addr:street":"Rue Victoria",
    "iso:country":"CA",
    "sg:address":"700 Rue Victoria",
    "sg:city":"Edmundston",
    "sg:classifiers":[
        {
            "category":"Building & Trades",
            "subcategory":"Construction",
            "type":"Services"
        }
    ],
    "sg:phone":"+1 506 739 1811",
    "sg:postcode":"E3V 3S9",
    "sg:province":"NB",
    "sg:tags":[
        "roofing",
        "contractor"
    ],
    "wof:name":"Northwest Roofers Ltd",
    "wof:placetype":"venue"
},
  "geometry": {"coordinates":[-68.34172100000001,47.389553],"type":"Point"}
}