{
  "type": "Feature",
  "properties": {
    "addr:full":"Elora ON N0B 1S0",
    "addr:postcode":"n0b 1s0",
    "iso:country":"CA",
    "sg:city":"Elora",
    "sg:classifiers":[
        {
            "category":"Home & Garden",
            "subcategory":"Building Materials",
            "type":"Retail Goods"
        }
    ],
    "sg:phone":"+1 519 846 5318",
    "sg:postcode":"N0B 1S0",
    "sg:province":"ON",
    "sg:tags":[
        "mixed",
        "concrete"
    ],
    "wof:name":"Canada Building Materials",
    "wof:placetype":"venue"
},
  "geometry": {"coordinates":[-80.429749,43.68158],"type":"Point"}
}