{
  "type": "Feature",
  "properties": {
    "iso:country":"CA",
    "sg:address":"8466 Rue Bonamour",
    "sg:city":"Laval",
    "sg:classifiers":[
        {
            "category":"Food & Beverages",
            "subcategory":"Specialty",
            "type":"Retail Goods"
        }
    ],
    "sg:phone":"+1 450 622 5845",
    "sg:postcode":"H7H 2Y6",
    "sg:province":"QC",
    "wof:name":"Herbalife Distributeur",
    "wof:placetype":"venue"
},
  "geometry": {"coordinates":[-73.751518,45.656548],"type":"Point"}
}