{
  "type": "Feature",
  "properties": {
    "addr:full":"Cap-DE-LA-Madeleine QC G8T 6Y6",
    "addr:postcode":"g8t 6y6",
    "iso:country":"CA",
    "sg:city":"Cap-DE-LA-Madeleine",
    "sg:classifiers":[
        {
            "category":"Autos & Motor Vehicles",
            "subcategory":"Auto Supplies",
            "type":"Retail Goods"
        }
    ],
    "sg:phone":"+1 819 379 4366",
    "sg:postcode":"G8T 6Y6",
    "sg:province":"QC",
    "sg:tags":[
        "equipment",
        "stereo",
        "video",
        "radio",
        "automobile"
    ],
    "wof:name":"Marchand Audio Video Inc",
    "wof:placetype":"venue"
},
  "geometry": {"coordinates":[-72.53555299999999,46.374447],"type":"Point"}
}