{
  "type": "Feature",
  "properties": {
    "addr:full":"416 Roncesvalles Ave Toronto ON M6R 2N2",
    "addr:housenumber":"416",
    "addr:postcode":"m6r 2n2",
    "addr:street":"Roncesvalles Ave",
    "iso:country":"CA",
    "sg:address":"416 Roncesvalles Ave",
    "sg:city":"Toronto",
    "sg:classifiers":[
        {
            "category":"Bars & Pubs",
            "type":"Food & Drink"
        }
    ],
    "sg:phone":"+1 416 535 8561",
    "sg:postcode":"M6R 2N2",
    "sg:province":"ON",
    "wof:name":"Loons",
    "wof:placetype":"venue"
},
  "geometry": {"coordinates":[-79.451263,43.651691],"type":"Point"}
}