{
  "type": "Feature",
  "properties": {
    "addr:full":"316 May St S Thunder Bay ON P7E 1B6",
    "addr:housenumber":"316",
    "addr:postcode":"p7e 1b6",
    "addr:street":"May St S Thunder",
    "iso:country":"CA",
    "sg:address":"316 May St S",
    "sg:city":"Thunder Bay",
    "sg:classifiers":[
        {
            "category":"Autos & Motor Vehicles",
            "subcategory":"Motorcycle Sales",
            "type":"Retail Goods"
        }
    ],
    "sg:phone":"+1 807 622 0007",
    "sg:postcode":"P7E 1B6",
    "sg:province":"ON",
    "sg:tags":[
        "scooter"
    ],
    "wof:name":"Excalibur Motorcycle Works Ltd",
    "wof:placetype":"venue"
},
  "geometry": {"coordinates":[-89.24527,48.380577],"type":"Point"}
}