{
  "type": "Feature",
  "properties": {
    "addr:full":"8691 Rue Hochelaga Montreal QC H1L 6J5",
    "addr:housenumber":"8691",
    "addr:postcode":"h1l 6j5",
    "addr:street":"Rue Hochelaga",
    "iso:country":"CA",
    "sg:address":"8691 Rue Hochelaga",
    "sg:city":"Montreal",
    "sg:classifiers":[
        {
            "category":"Shopping",
            "subcategory":"Optical Goods",
            "type":"Retail Goods"
        }
    ],
    "sg:phone":"+1 514 642 7663",
    "sg:postcode":"H1L 6J5",
    "sg:province":"QC",
    "sg:tags":[
        "optician"
    ],
    "wof:name":"Lunetterie Farhat",
    "wof:placetype":"venue"
},
  "geometry": {"coordinates":[-73.5200881958,45.6014060974],"type":"Point"}
}