{
  "type": "Feature",
  "properties": {
    "iso:country":"CA",
    "sg:city":"Saint-Honore-DE-Chicoutimi",
    "sg:classifiers":[
        {
            "category":"Local Transit",
            "type":"Transportation"
        }
    ],
    "sg:phone":"+1 418 673 3838",
    "sg:postcode":"G0V 1L0",
    "sg:province":"QC",
    "sg:tags":[
        "aircraft",
        "ferrying",
        "transporting",
        "ambulance"
    ],
    "wof:name":"Airmedic",
    "wof:placetype":"venue"
},
  "geometry": {"coordinates":[-71.0613937378,48.428943634],"type":"Point"}
}