{
  "type": "Feature",
  "properties": {
    "iso:country":"CA",
    "sg:address":"1240 Rue Des Artisans",
    "sg:city":"Quebec",
    "sg:classifiers":[
        {
            "category":"Manufacturing",
            "subcategory":"Metals",
            "type":"Manufacturing & Wholesale Goods"
        }
    ],
    "sg:phone":"+1 418 527 3885",
    "sg:postcode":"G1N 1N3",
    "sg:province":"QC",
    "sg:tags":[
        "instrument",
        "scientific",
        "apparatus"
    ],
    "wof:name":"Acier Inoxydable Den-Mar Inc",
    "wof:placetype":"venue"
},
  "geometry": {"coordinates":[-71.258614,46.802925],"type":"Point"}
}