{
  "type": "Feature",
  "properties": {
    "addr:full":"602 Patricia St Jasper AB T0E 1E0",
    "addr:housenumber":"602",
    "addr:postcode":"t0e 1e0",
    "addr:street":"Patricia St",
    "iso:country":"CA",
    "sg:address":"602 Patricia St",
    "sg:city":"Jasper",
    "sg:classifiers":[
        {
            "category":"Shopping",
            "subcategory":"Pharmacy",
            "type":"Retail Goods"
        }
    ],
    "sg:phone":"+1 780 852 4441",
    "sg:postcode":"T0E 1E0",
    "sg:province":"AB",
    "wof:name":"Cavell Value Drug Mart",
    "wof:placetype":"venue"
},
  "geometry": {"coordinates":[-118.081711,52.876083],"type":"Point"}
}