{
  "type": "Feature",
  "properties": {
    "iso:country":"CA",
    "sg:city":"Berthierville",
    "sg:classifiers":[
        {
            "category":"Banks & Credit Unions",
            "subcategory":"Investment Brokerage",
            "type":"Services"
        }
    ],
    "sg:phone":"+1 450 836 2727",
    "sg:postcode":"J0K 1A0",
    "sg:province":"QC",
    "wof:name":"LA Financiere Banque Nationale",
    "wof:placetype":"venue"
},
  "geometry": {"coordinates":[-73.1771392822,46.0921440125],"type":"Point"}
}