{
  "type": "Feature",
  "properties": {
    "addr:full":"1320 Loudoun Rd Winnipeg MB R3S 1A4",
    "addr:housenumber":"1320",
    "addr:postcode":"r3s 1a4",
    "addr:street":"Loudoun Rd",
    "iso:country":"CA",
    "sg:address":"1320 Loudoun Rd",
    "sg:city":"Winnipeg",
    "sg:classifiers":[
        {
            "category":"Manufacturing",
            "subcategory":"Building Materials",
            "type":"Manufacturing & Wholesale Goods"
        }
    ],
    "sg:phone":"+1 204 895 2323",
    "sg:postcode":"R3S 1A4",
    "sg:province":"MB",
    "wof:name":"R J Millwork CO Ltd",
    "wof:placetype":"venue"
},
  "geometry": {"coordinates":[-97.25608800000001,49.838238],"type":"Point"}
}