{
  "type": "Feature",
  "properties": {
    "addr:full":"1318 Regal Cres NE Calgary AB T2E 6Y6",
    "addr:housenumber":"1318",
    "addr:postcode":"t2e 6y6",
    "addr:street":"Regal Cres Ne",
    "iso:country":"CA",
    "sg:address":"1318 Regal Cres NE",
    "sg:city":"Calgary",
    "sg:classifiers":[
        {
            "category":"Organizations",
            "subcategory":"Community Association",
            "type":"Services"
        }
    ],
    "sg:phone":"+1 403 276 4747",
    "sg:postcode":"T2E 6Y6",
    "sg:province":"AB",
    "sg:tags":[
        "club"
    ],
    "wof:name":"Renfrew Fifty Plus Club",
    "wof:placetype":"venue"
},
  "geometry": {"coordinates":[-114.046494,51.063381],"type":"Point"}
}