{
  "type": "Feature",
  "properties": {
    "iso:country":"CA",
    "sg:address":"1444 Irvine Rd",
    "sg:city":"Niagara on the Lake",
    "sg:classifiers":[
        {
            "category":"Wholesale",
            "subcategory":"Fruits & Vegetables",
            "type":"Manufacturing & Wholesale Goods"
        }
    ],
    "sg:phone":"+1 905 934 3925",
    "sg:postcode":"L0S 1J0",
    "sg:province":"ON",
    "wof:name":"Meyers Fruit Farms",
    "wof:placetype":"venue"
},
  "geometry": {"coordinates":[-79.1718292236,43.2340927124],"type":"Point"}
}