{
  "type": "Feature",
  "properties": {
    "addr:full":"77 Saint Regis Cres S North York ON M3J 1Y6",
    "addr:housenumber":"77",
    "addr:postcode":"m3j 1y6",
    "addr:street":"Saint Regis Cres S North",
    "iso:country":"CA",
    "sg:address":"77 Saint Regis Cres S",
    "sg:city":"North York",
    "sg:classifiers":[
        {
            "category":"Home & Garden",
            "subcategory":"Carpets & Floor Coverings",
            "type":"Retail Goods"
        }
    ],
    "sg:phone":"+1 416 630 4800",
    "sg:postcode":"M3J 1Y6",
    "sg:province":"ON",
    "sg:tags":[
        "tile",
        "material"
    ],
    "wof:name":"Sterling Tile Hardwood Carpet",
    "wof:placetype":"venue"
},
  "geometry": {"coordinates":[-79.4854049683,43.7542953491],"type":"Point"}
}