{
  "type": "Feature",
  "properties": {
    "addr:full":"Range Rd 45 Caroline AB T0M 0M0",
    "addr:housenumber":"45",
    "addr:postcode":"t0m 0m0",
    "addr:street":"Range Rd",
    "iso:country":"CA",
    "sg:address":"Range Rd 45",
    "sg:city":"Caroline",
    "sg:classifiers":[
        {
            "category":"Home & Garden",
            "subcategory":"Building Materials",
            "type":"Retail Goods"
        }
    ],
    "sg:phone":"+1 403 728 3832",
    "sg:postcode":"T0M 0M0",
    "sg:province":"AB",
    "wof:name":"Harriman Lumber & Construction",
    "wof:placetype":"venue"
},
  "geometry": {"coordinates":[-114.740707,52.09359],"type":"Point"}
}