{
  "type": "Feature",
  "properties": {
    "addr:full":"5288 Nauvoo Rd Watford ON N0M 2S0",
    "addr:housenumber":"5288",
    "addr:postcode":"n0m 2s0",
    "addr:street":"Nauvoo Rd",
    "iso:country":"CA",
    "sg:address":"5288 Nauvoo Rd",
    "sg:city":"Watford",
    "sg:classifiers":[
        {
            "category":"Shopping",
            "subcategory":"Florist",
            "type":"Retail Goods"
        }
    ],
    "sg:phone":"+1 519 876 2916",
    "sg:postcode":"N0M 2S0",
    "sg:province":"ON",
    "wof:name":"Mc Clung's Flowers",
    "wof:placetype":"venue"
},
  "geometry": {"coordinates":[-81.879852,42.947571],"type":"Point"}
}