{
  "type": "Feature",
  "properties": {
    "addr:full":"663 Park Ave Beausejour MB R0E 0C0",
    "addr:housenumber":"663",
    "addr:postcode":"r0e 0c0",
    "addr:street":"Park Ave",
    "iso:country":"CA",
    "sg:address":"663 Park Ave",
    "sg:city":"Beausejour",
    "sg:classifiers":[
        {
            "category":"Restaurant",
            "type":"Food & Drink"
        }
    ],
    "sg:phone":"+1 204 268 7500",
    "sg:postcode":"R0E 0C0",
    "sg:province":"MB",
    "wof:name":"Chicken Delight",
    "wof:placetype":"venue"
},
  "geometry": {"coordinates":[-96.513077,50.061924],"type":"Point"}
}