{
  "type": "Feature",
  "properties": {
    "iso:country":"CA",
    "sg:address":"634 Rue Saint-Jacques",
    "sg:city":"Montreal",
    "sg:classifiers":[
        {
            "category":"Real Estate",
            "subcategory":"Real Estate Agent",
            "type":"Services"
        }
    ],
    "sg:phone":"+1 514 861 7272",
    "sg:postcode":"H3C 1C7",
    "sg:province":"QC",
    "wof:name":"Inter Commercial Svc",
    "wof:placetype":"venue"
},
  "geometry": {"coordinates":[-73.56089019780001,45.5006217957],"type":"Point"}
}