{
  "type": "Feature",
  "properties": {
    "iso:country":"CA",
    "sg:address":"315 Rue Migneault",
    "sg:city":"Gatineau",
    "sg:classifiers":[
        {
            "category":"Organizations",
            "subcategory":"Professional Association",
            "type":"Services"
        }
    ],
    "sg:phone":"+1 819 663 8337",
    "sg:postcode":"J8P 7A3",
    "sg:province":"QC",
    "wof:name":"Relais Des Jeunes Gatinois",
    "wof:placetype":"venue"
},
  "geometry": {"coordinates":[-75.6680603027,45.487197876],"type":"Point"}
}