{
  "type": "Feature",
  "properties": {
    "addr:full":"8438 144 St Surrey BC V3W 5T7",
    "addr:housenumber":"8438",
    "addr:postcode":"v3w 5t7",
    "addr:street":"144 St",
    "iso:country":"CA",
    "sg:address":"8438 144 St",
    "sg:city":"Surrey",
    "sg:classifiers":[
        {
            "category":"Professional",
            "subcategory":"Accounting & Tax Preparation",
            "type":"Services"
        }
    ],
    "sg:phone":"+1 604 572 8888",
    "sg:postcode":"V3W 5T7",
    "sg:province":"BC",
    "sg:tags":[
        "bookkeeping",
        "general"
    ],
    "wof:name":"Paperworks Business",
    "wof:placetype":"venue"
},
  "geometry": {"coordinates":[-122.82324199999999,49.1563],"type":"Point"}
}