{
  "type": "Feature",
  "properties": {
    "addr:full":"3 Renaud St Miramichi NB E1V 6T2",
    "addr:housenumber":"3",
    "addr:postcode":"e1v 6t2",
    "addr:street":"Renaud St",
    "iso:country":"CA",
    "sg:address":"3 Renaud St",
    "sg:city":"Miramichi",
    "sg:classifiers":[
        {
            "category":"Health Services",
            "subcategory":"Health Practitioner",
            "type":"Services"
        }
    ],
    "sg:phone":"+1 506 778 0069",
    "sg:postcode":"E1V 6T2",
    "sg:province":"NB",
    "sg:tags":[
        "physiotherapist"
    ],
    "wof:name":"Miramichi Physiotherapy Inc",
    "wof:placetype":"venue"
},
  "geometry": {"coordinates":[-65.499611,47.025993],"type":"Point"}
}