{
  "type": "Feature",
  "properties": {
    "iso:country":"CA",
    "sg:address":"2200 St Henry Ave",
    "sg:city":"Saskatoon",
    "sg:classifiers":[
        {
            "category":"Health Services",
            "subcategory":"Nursing And Care Facility",
            "type":"Services"
        }
    ],
    "sg:phone":"+1 306 653 1267",
    "sg:postcode":"S7M 0P5",
    "sg:province":"SK",
    "sg:tags":[
        "home",
        "convalescent"
    ],
    "wof:name":"Sunnyside Nursing Home",
    "wof:placetype":"venue"
},
  "geometry": {"coordinates":[-106.682296753,52.1032600403],"type":"Point"}
}