{
  "type": "Feature",
  "properties": {
    "addr:full":"5258 Rumble St Burnaby BC V5J 2B6",
    "addr:housenumber":"5258",
    "addr:postcode":"v5j 2b6",
    "addr:street":"Rumble St",
    "iso:country":"CA",
    "sg:address":"5258 Rumble St",
    "sg:city":"Burnaby",
    "sg:classifiers":[
        {
            "category":"Insurance",
            "subcategory":"Insurance Agent",
            "type":"Services"
        }
    ],
    "sg:phone":"+1 604 437 0033",
    "sg:postcode":"V5J 2B6",
    "sg:province":"BC",
    "wof:name":"Garrison Beatty & Garrison Ltd",
    "wof:placetype":"venue"
},
  "geometry": {"coordinates":[-122.98754119900001,49.2146224976],"type":"Point"}
}