{
  "type": "Feature",
  "properties": {
    "addr:full":"10 Rue Du Pont Saint-Etienne-DE-Lauzon QC G6J 1H6",
    "addr:housenumber":"10",
    "addr:postcode":"g6j 1h6",
    "addr:street":"Rue Du Pont Saint-Etienne-De-Lauzon",
    "iso:country":"CA",
    "sg:address":"10 Rue Du Pont",
    "sg:city":"Saint-Etienne-DE-Lauzon",
    "sg:classifiers":[
        {
            "category":"Personal",
            "subcategory":"Beauty Salon",
            "type":"Services"
        }
    ],
    "sg:phone":"+1 418 831 5854",
    "sg:postcode":"G6J 1H6",
    "sg:province":"QC",
    "wof:name":"Salon DE Coiffure Pl Coiffure",
    "wof:placetype":"venue"
},
  "geometry": {"coordinates":[-71.300606,46.650837],"type":"Point"}
}