{
  "type": "Feature",
  "properties": {
    "addr:full":"Degelis QC G5T 2G3",
    "addr:postcode":"g5t 2g3",
    "iso:country":"CA",
    "sg:city":"Degelis",
    "sg:classifiers":[
        {
            "category":"Social Services",
            "type":"Services"
        }
    ],
    "sg:phone":"+1 418 853 2546",
    "sg:postcode":"G5T 2G3",
    "sg:province":"QC",
    "sg:tags":[
        "organization",
        "association",
        "welfare"
    ],
    "wof:name":"Centre D'Action Benevole Reg",
    "wof:placetype":"venue"
},
  "geometry": {"coordinates":[-68.6467056274,47.5478286743],"type":"Point"}
}