{
  "type": "Feature",
  "properties": {
    "addr:full":"1030 Rue Saint-Georges Saint-Jerome QC J7Z 5E8",
    "addr:housenumber":"1030",
    "addr:postcode":"j7z 5e8",
    "addr:street":"Rue Saint-Georges Saint-Jerome",
    "iso:country":"CA",
    "sg:address":"1030 Rue Saint-Georges",
    "sg:city":"Saint-Jerome",
    "sg:classifiers":[
        {
            "category":"Education",
            "subcategory":"School",
            "type":"Public Place"
        }
    ],
    "sg:phone":"+1 450 436 1757",
    "sg:postcode":"J7Z 5E8",
    "sg:province":"QC",
    "wof:name":"Ecole Ste-Paule",
    "wof:placetype":"venue"
},
  "geometry": {"coordinates":[-74.005814,45.793053],"type":"Point"}
}