{
  "type": "Feature",
  "properties": {
    "addr:full":"824 Deuxieme Rang Sainte-Clotilde-DE-Chateauguay QC J0L 1W0",
    "addr:housenumber":"824",
    "addr:postcode":"j0l 1w0",
    "addr:street":"Deuxieme Rang Sainte-Clotilde-De-Chateauguay",
    "iso:country":"CA",
    "sg:address":"824 Deuxieme Rang",
    "sg:city":"Sainte-Clotilde-DE-Chateauguay",
    "sg:classifiers":[
        {
            "category":"Organizations",
            "subcategory":"Professional Association",
            "type":"Services"
        }
    ],
    "sg:phone":"+1 450 826 0550",
    "sg:postcode":"J0L 1W0",
    "sg:province":"QC",
    "wof:name":"Association Sportive Chasse",
    "wof:placetype":"venue"
},
  "geometry": {"coordinates":[-73.749878,45.361267],"type":"Point"}
}