{
  "type": "Feature",
  "properties": {
    "iso:country":"CA",
    "sg:address":"7016 Farrell Rd SE",
    "sg:city":"Calgary",
    "sg:classifiers":[
        {
            "category":"Retail",
            "subcategory":"Funeral Services",
            "type":"Services"
        }
    ],
    "sg:phone":"+1 403 216 5111",
    "sg:postcode":"T2H 0T2",
    "sg:province":"AB",
    "sg:tags":[
        "director",
        "plan"
    ],
    "wof:name":"Personal Alternative Funeral",
    "wof:placetype":"venue"
},
  "geometry": {"coordinates":[-114.059242248,50.9921798706],"type":"Point"}
}