{
  "type": "Feature",
  "properties": {
    "iso:country":"CA",
    "sg:address":"200 Av Vincent-D'Indy",
    "sg:city":"Outremont",
    "sg:classifiers":[
        {
            "category":"Professional",
            "type":"Services"
        }
    ],
    "sg:phone":"+1 514 343 5962",
    "sg:postcode":"H2V 2T2",
    "sg:province":"QC",
    "sg:tags":[
        "establishment",
        "music"
    ],
    "wof:name":"Nouvel Ensemble Moderne",
    "wof:placetype":"venue"
},
  "geometry": {"coordinates":[-73.6140365601,45.5109672546],"type":"Point"}
}