{
  "type": "Feature",
  "properties": {
    "iso:country":"CA",
    "sg:address":"10 Dignard St",
    "sg:city":"Embrun",
    "sg:classifiers":[
        {
            "category":"Personal",
            "subcategory":"Beauty Salon",
            "type":"Services"
        }
    ],
    "sg:phone":"+1 613 443 2230",
    "sg:postcode":"K0A 1W1",
    "sg:province":"ON",
    "wof:name":"Salon Le Ciseau D'Or",
    "wof:placetype":"venue"
},
  "geometry": {"coordinates":[-75.2922668457,45.2723045349],"type":"Point"}
}