{
  "type": "Feature",
  "properties": {
    "iso:country":"CA",
    "sg:address":"487 Boul Sainte-Genevieve",
    "sg:city":"Chicoutimi",
    "sg:classifiers":[
        {
            "category":"Retail",
            "subcategory":"Auto Repair",
            "type":"Services"
        }
    ],
    "sg:phone":"+1 418 543 0279",
    "sg:postcode":"G7G 2E5",
    "sg:province":"QC",
    "sg:tags":[
        "repairing",
        "automobile"
    ],
    "wof:name":"Garage Raynald Beaulieu Enr",
    "wof:placetype":"venue"
},
  "geometry": {"coordinates":[-71.074806,48.442047],"type":"Point"}
}