{
  "type": "Feature",
  "properties": {
    "addr:full":"PO Box 55 Dinorwic ON P0V 1P0",
    "addr:housenumber":"po box 55",
    "addr:postcode":"p0v 1p0",
    "iso:country":"CA",
    "sg:address":"PO Box 55",
    "sg:city":"Dinorwic",
    "sg:classifiers":[
        {
            "category":"Building & Trades",
            "subcategory":"Construction",
            "type":"Services"
        }
    ],
    "sg:phone":"+1 807 938 2322",
    "sg:postcode":"P0V 1P0",
    "sg:province":"ON",
    "sg:tags":[
        "general",
        "contractor"
    ],
    "wof:name":"William Huckell & Son Contr",
    "wof:placetype":"venue"
},
  "geometry": {"coordinates":[-92.49400300000001,49.696854],"type":"Point"}
}