{
  "type": "Feature",
  "properties": {
    "addr:full":"305 Finch Ave W North York ON M2R 1N2",
    "addr:housenumber":"305",
    "addr:postcode":"m2r 1n2",
    "addr:street":"Finch Ave W",
    "iso:country":"CA",
    "sg:address":"305 Finch Ave W",
    "sg:city":"North York",
    "sg:classifiers":[
        {
            "category":"Health Services",
            "subcategory":"Doctor",
            "type":"Services"
        }
    ],
    "sg:phone":"+1 416 226 5510",
    "sg:postcode":"M2R 1N2",
    "sg:province":"ON",
    "sg:tags":[
        "physician",
        "surgeon"
    ],
    "wof:name":"Gotesman, Galina MD",
    "wof:placetype":"venue"
},
  "geometry": {"coordinates":[-79.4413070679,43.7739295959],"type":"Point"}
}