{
  "type": "Feature",
  "properties": {
    "addr:full":"233 Main St Chipman NB E4A 2H2",
    "addr:housenumber":"233",
    "addr:postcode":"e4a 2h2",
    "addr:street":"Main St",
    "iso:country":"CA",
    "sg:address":"233 Main St",
    "sg:city":"Chipman",
    "sg:classifiers":[
        {
            "category":"Insurance",
            "subcategory":"Insurance Agent",
            "type":"Services"
        }
    ],
    "sg:phone":"+1 506 339 6635",
    "sg:postcode":"E4A 2H2",
    "sg:province":"NB",
    "wof:name":"Doherty's General Insurance",
    "wof:placetype":"venue"
},
  "geometry": {"coordinates":[-65.881668,46.175228],"type":"Point"}
}