{
  "type": "Feature",
  "properties": {
    "addr:full":"188 Ch Du Ruisseau-Saint-Louis Marieville QC J3M 1P1",
    "addr:housenumber":"188",
    "addr:postcode":"j3m 1p1",
    "addr:street":"Ch Du Ruisseau-Saint-Louis",
    "iso:country":"CA",
    "sg:address":"188 Ch Du Ruisseau-Saint-Louis",
    "sg:city":"Marieville",
    "sg:classifiers":[
        {
            "category":"Retail",
            "subcategory":"Auto Repair",
            "type":"Services"
        }
    ],
    "sg:phone":"+1 450 460 2387",
    "sg:postcode":"J3M 1P1",
    "sg:province":"QC",
    "sg:tags":[
        "repairing",
        "automobile"
    ],
    "wof:name":"Cailloux Rod Shop Enr",
    "wof:placetype":"venue"
},
  "geometry": {"coordinates":[-73.1732330322,45.4443817139],"type":"Point"}
}