{
  "type": "Feature",
  "properties": {
    "addr:full":"3446 Wonderland Rd S London ON N6L 1A7",
    "addr:housenumber":"3446",
    "addr:postcode":"n6l 1a7",
    "addr:street":"Wonderland Rd",
    "iso:country":"CA",
    "sg:address":"3446 Wonderland Rd S",
    "sg:city":"London",
    "sg:classifiers":[
        {
            "category":"Freight",
            "type":"Transportation"
        }
    ],
    "sg:phone":"+1 519 652 9920",
    "sg:postcode":"N6L 1A7",
    "sg:province":"ON",
    "sg:tags":[
        "commercial",
        "storage"
    ],
    "wof:name":"Wonderland Mini Storage",
    "wof:placetype":"venue"
},
  "geometry": {"coordinates":[-81.2787246704,42.9280357361],"type":"Point"}
}