{
  "type": "Feature",
  "properties": {
    "addr:full":"London ON N6H 3S2",
    "addr:postcode":"n6h 3s2",
    "iso:country":"CA",
    "sg:city":"London",
    "sg:classifiers":[
        {
            "category":"Professional",
            "subcategory":"Lawyer & Legal Services",
            "type":"Services"
        }
    ],
    "sg:phone":"+1 519 472 6310",
    "sg:postcode":"N6H 3S2",
    "sg:province":"ON",
    "sg:tags":[
        "attorney"
    ],
    "wof:name":"Gallagher, W Scott",
    "wof:placetype":"venue"
},
  "geometry": {"coordinates":[-81.32122039790001,42.9777145386],"type":"Point"}
}