{
  "type": "Feature",
  "properties": {
    "addr:full":"247 Queen St W Toronto ON M5V 1Z4",
    "addr:housenumber":"247",
    "addr:postcode":"m5v 1z4",
    "addr:street":"Queen St W",
    "iso:country":"CA",
    "sg:address":"247 Queen St W",
    "sg:city":"Toronto",
    "sg:classifiers":[
        {
            "category":"Shopping",
            "subcategory":"Stationery & Office Supplies",
            "type":"Retail Goods"
        }
    ],
    "sg:phone":"+1 416 598 3833",
    "sg:postcode":"M5V 1Z4",
    "sg:province":"ON",
    "wof:name":"Empire Office Equipment Ltd",
    "wof:placetype":"venue"
},
  "geometry": {"coordinates":[-79.388893,43.6502],"type":"Point"}
}