{
  "type": "Feature",
  "properties": {
    "addr:full":"Chesley ON N0G 1L0",
    "addr:postcode":"n0g 1l0",
    "iso:country":"CA",
    "sg:city":"Chesley",
    "sg:classifiers":[
        {
            "category":"Insurance",
            "subcategory":"Insurance Agent",
            "type":"Services"
        }
    ],
    "sg:phone":"+1 519 363 3962",
    "sg:postcode":"N0G 1L0",
    "sg:province":"ON",
    "sg:tags":[
        "funds",
        "retirement",
        "income"
    ],
    "wof:name":"Ackert Insurance Brokers",
    "wof:placetype":"venue"
},
  "geometry": {"coordinates":[-81.094833374,44.2973098755],"type":"Point"}
}