{
  "type": "Feature",
  "properties": {
    "addr:full":"171 Mckinstry Rd Duncan BC V9L 3K9",
    "addr:housenumber":"171",
    "addr:postcode":"v9l 3k9",
    "addr:street":"Mckinstry Rd",
    "iso:country":"CA",
    "sg:address":"171 Mckinstry Rd",
    "sg:city":"Duncan",
    "sg:classifiers":[
        {
            "category":"Building & Trades",
            "subcategory":"Electrical",
            "type":"Services"
        }
    ],
    "sg:phone":"+1 250 748 2424",
    "sg:postcode":"V9L 3K9",
    "sg:province":"BC",
    "sg:tags":[
        "electric",
        "contractor"
    ],
    "wof:name":"Shur-Power Electric Ltd",
    "wof:placetype":"venue"
},
  "geometry": {"coordinates":[-123.695099,48.774956],"type":"Point"}
}