{
  "type": "Feature",
  "properties": {
    "addr:full":"2050 Marine Dr North Vancouver BC V7P 1V7",
    "addr:housenumber":"2050",
    "addr:postcode":"v7p 1v7",
    "addr:street":"Marine Dr",
    "iso:country":"CA",
    "sg:address":"2050 Marine Dr",
    "sg:city":"North Vancouver",
    "sg:classifiers":[
        {
            "category":"Restaurant",
            "type":"Food & Drink"
        }
    ],
    "sg:phone":"+1 604 980 8210",
    "sg:postcode":"V7P 1V7",
    "sg:province":"BC",
    "wof:name":"Denny's of Canada Ltd",
    "wof:placetype":"venue"
},
  "geometry": {"coordinates":[-123.12326049799999,49.3247528076],"type":"Point"}
}