{
  "type": "Feature",
  "properties": {
    "iso:country":"CA",
    "sg:address":"411 Lakeshore Rd E",
    "sg:city":"Mississauga",
    "sg:classifiers":[
        {
            "category":"Retail",
            "subcategory":"Auto Repair",
            "type":"Services"
        }
    ],
    "sg:phone":"+1 905 891 6776",
    "sg:postcode":"L5G 1H8",
    "sg:province":"ON",
    "sg:tags":[
        "repairing",
        "automobile"
    ],
    "wof:name":"Abv Autocare Corp",
    "wof:placetype":"venue"
},
  "geometry": {"coordinates":[-79.5722351074,43.5643768311],"type":"Point"}
}