{
  "type": "Feature",
  "properties": {
    "addr:full":"134 Rue DE Chantilly Saint-Jean-Sur-Richelieu QC J3B 4C6",
    "addr:housenumber":"134",
    "addr:postcode":"j3b 4c6",
    "addr:street":"Rue De Chantilly",
    "iso:country":"CA",
    "sg:address":"134 Rue DE Chantilly",
    "sg:city":"Saint-Jean-Sur-Richelieu",
    "sg:classifiers":[
        {
            "category":"Building & Trades",
            "subcategory":"Construction",
            "type":"Services"
        }
    ],
    "sg:phone":"+1 450 347 0627",
    "sg:postcode":"J3B 4C6",
    "sg:province":"QC",
    "sg:tags":[
        "resurfacing",
        "laying",
        "refinishing",
        "floor"
    ],
    "wof:name":"A-1 Sablage DE Plancher Enr",
    "wof:placetype":"venue"
},
  "geometry": {"coordinates":[-73.25753,45.274059],"type":"Point"}
}