{
  "type": "Feature",
  "properties": {
    "addr:full":"4130 Versatile Pl Prince George BC V2N 4K9",
    "addr:housenumber":"4130",
    "addr:postcode":"v2n 4k9",
    "addr:street":"Versatile Pl",
    "iso:country":"CA",
    "sg:address":"4130 Versatile Pl",
    "sg:city":"Prince George",
    "sg:classifiers":[
        {
            "category":"Home & Garden",
            "subcategory":"Furniture",
            "type":"Retail Goods"
        }
    ],
    "sg:phone":"+1 250 564 2700",
    "sg:postcode":"V2N 4K9",
    "sg:province":"BC",
    "wof:name":"United Furniture Warehouse",
    "wof:placetype":"venue"
},
  "geometry": {"coordinates":[-122.771683,53.879505],"type":"Point"}
}