{
  "type": "Feature",
  "properties": {
    "addr:full":"901 Millwood Rd East York ON M4G 1X2",
    "addr:housenumber":"901",
    "addr:postcode":"m4g 1x2",
    "addr:street":"Millwood Rd",
    "iso:country":"CA",
    "sg:address":"901 Millwood Rd",
    "sg:city":"East York",
    "sg:classifiers":[
        {
            "category":"Restaurant",
            "type":"Food & Drink"
        }
    ],
    "sg:phone":"+1 416 425 2500",
    "sg:postcode":"M4G 1X2",
    "sg:province":"ON",
    "sg:tags":[
        "pizza"
    ],
    "wof:name":"Bravo Pizza",
    "wof:placetype":"venue"
},
  "geometry": {"coordinates":[-79.3638763428,43.7032165527],"type":"Point"}
}