{
  "type": "Feature",
  "properties": {
    "iso:country":"CA",
    "sg:address":"1300 King St E #11",
    "sg:city":"Oshawa",
    "sg:classifiers":[
        {
            "category":"Shopping",
            "subcategory":"Discount & Variety Stores",
            "type":"Retail Goods"
        }
    ],
    "sg:phone":"+1 905 433 1618",
    "sg:postcode":"L1H 8J4",
    "sg:province":"ON",
    "wof:name":"Rave Convenience",
    "wof:placetype":"venue"
},
  "geometry": {"coordinates":[-78.815475,43.906456],"type":"Point"}
}