{
  "type": "Feature",
  "properties": {
    "iso:country":"CA",
    "sg:city":"Markham",
    "sg:classifiers":[
        {
            "category":"Real Estate",
            "subcategory":"Real Estate Agent",
            "type":"Services"
        }
    ],
    "sg:phone":"+1 905 471 6333",
    "sg:postcode":"L3P 7R4",
    "sg:province":"ON",
    "wof:name":"Willco Realty Ltd",
    "wof:placetype":"venue"
},
  "geometry": {"coordinates":[-79.281464,43.873615],"type":"Point"}
}