{
  "type": "Feature",
  "properties": {
    "addr:full":"133 1st St S Wakaw SK S0K 4P0",
    "addr:housenumber":"133",
    "addr:postcode":"s0k 4p0",
    "addr:street":"1St St S",
    "iso:country":"CA",
    "sg:address":"133 1st St S",
    "sg:city":"Wakaw",
    "sg:classifiers":[
        {
            "category":"Travel",
            "subcategory":"Hotels & Motels",
            "type":"Entertainment"
        }
    ],
    "sg:phone":"+1 306 233 5120",
    "sg:postcode":"S0K 4P0",
    "sg:province":"SK",
    "wof:name":"Wakaw Inn",
    "wof:placetype":"venue"
},
  "geometry": {"coordinates":[-105.74270629900001,52.6529502869],"type":"Point"}
}