{
  "type": "Feature",
  "properties": {
    "iso:country":"CA",
    "sg:address":"438 Quebec St",
    "sg:city":"Regina",
    "sg:classifiers":[
        {
            "category":"Shopping",
            "subcategory":"Bicycles & Sporting Goods",
            "type":"Retail Goods"
        }
    ],
    "sg:phone":"+1 306 569 9880",
    "sg:postcode":"S4R 1K7",
    "sg:province":"SK",
    "sg:tags":[
        "uniform"
    ],
    "wof:name":"Queen City Sports & Uniform",
    "wof:placetype":"venue"
},
  "geometry": {"coordinates":[-104.59648132300001,50.4717712402],"type":"Point"}
}