{
  "type": "Feature",
  "properties": {
    "addr:full":"7691 Balfour Wharf Balfour BC V0G 1C0",
    "addr:housenumber":"7691",
    "addr:postcode":"v0g 1c0",
    "addr:street":"Balfour Wharf",
    "iso:country":"CA",
    "sg:address":"7691 Balfour Wharf",
    "sg:city":"Balfour",
    "sg:classifiers":[
        {
            "category":"Manufacturing",
            "subcategory":"Lumber",
            "type":"Manufacturing & Wholesale Goods"
        }
    ],
    "sg:phone":"+1 250 229 4310",
    "sg:postcode":"V0G 1C0",
    "sg:province":"BC",
    "sg:tags":[
        "company",
        "logging"
    ],
    "wof:name":"G Veale Holdings Ltd",
    "wof:placetype":"venue"
},
  "geometry": {"coordinates":[-116.954116821,49.6306495667],"type":"Point"}
}