{
  "type": "Feature",
  "properties": {
    "iso:country":"CA",
    "sg:address":"26 Juniper Crt",
    "sg:city":"Nepean",
    "sg:classifiers":[
        {
            "category":"Building & Trades",
            "subcategory":"Electrical",
            "type":"Services"
        }
    ],
    "sg:phone":"+1 613 228 8419",
    "sg:postcode":"K2E 5M6",
    "sg:province":"ON",
    "sg:tags":[
        "electric",
        "contractor"
    ],
    "wof:name":"Silco Electric",
    "wof:placetype":"venue"
},
  "geometry": {"coordinates":[-75.71803300000001,45.349049],"type":"Point"}
}