{
  "type": "Feature",
  "properties": {
    "addr:full":"46 Major Button's Dr Markham ON L3P 3G7",
    "addr:housenumber":"46",
    "addr:postcode":"l3p 3g7",
    "addr:street":"Major Button'S Dr",
    "iso:country":"CA",
    "sg:address":"46 Major Button's Dr",
    "sg:city":"Markham",
    "sg:classifiers":[
        {
            "category":"Building & Trades",
            "subcategory":"Plumbing",
            "type":"Services"
        }
    ],
    "sg:phone":"+1 416 492 9408",
    "sg:postcode":"L3P 3G7",
    "sg:province":"ON",
    "sg:tags":[
        "balancing",
        "air"
    ],
    "wof:name":"Technical Aire Balancing Inc",
    "wof:placetype":"venue"
},
  "geometry": {"coordinates":[-79.312775,43.860123],"type":"Point"}
}