{
  "type": "Feature",
  "properties": {
    "addr:full":"North York ON M3C 3P4",
    "addr:postcode":"m3c 3p4",
    "iso:country":"CA",
    "sg:city":"North York",
    "sg:classifiers":[
        {
            "category":"Real Estate",
            "subcategory":"Real Estate Operator",
            "type":"Services"
        }
    ],
    "sg:phone":"+1 416 696 5502",
    "sg:postcode":"M3C 3P4",
    "sg:province":"ON",
    "sg:tags":[
        "apartment",
        "condominium"
    ],
    "wof:name":"Palisades Condominiums",
    "wof:placetype":"venue"
},
  "geometry": {"coordinates":[-79.32512699999999,43.723633],"type":"Point"}
}