{
  "type": "Feature",
  "properties": {
    "addr:full":"Winnipeg MB R3T 5P4",
    "addr:postcode":"r3t 5p4",
    "iso:country":"CA",
    "sg:city":"Winnipeg",
    "sg:classifiers":[
        {
            "category":"Professional",
            "subcategory":"Engineering",
            "type":"Services"
        }
    ],
    "sg:phone":"+1 204 453 2301",
    "sg:postcode":"R3T 5P4",
    "sg:province":"MB",
    "sg:tags":[
        "environmental",
        "ecological"
    ],
    "wof:name":"Dillon Consulting Ltd",
    "wof:placetype":"venue"
},
  "geometry": {"coordinates":[-97.17993927000001,49.843952179],"type":"Point"}
}