{
  "type": "Feature",
  "properties": {
    "addr:full":"Mont-Laurier QC J9L 3J1",
    "addr:postcode":"j9l 3j1",
    "iso:country":"CA",
    "sg:city":"Mont-Laurier",
    "sg:classifiers":[
        {
            "category":"Restaurant",
            "type":"Food & Drink"
        }
    ],
    "sg:phone":"+1 819 623 3414",
    "sg:postcode":"J9L 3J1",
    "sg:province":"QC",
    "wof:name":"Casse-Croute DE LA Plaza",
    "wof:placetype":"venue"
},
  "geometry": {"coordinates":[-75.4869384766,46.5511207581],"type":"Point"}
}