{
  "type": "Feature",
  "properties": {
    "iso:country":"CA",
    "sg:address":"1300 Regent Ave W",
    "sg:city":"Winnipeg",
    "sg:classifiers":[
        {
            "category":"Autos & Motor Vehicles",
            "subcategory":"Automobile Sales",
            "type":"Retail Goods"
        }
    ],
    "sg:phone":"+1 204 661 9555",
    "sg:postcode":"R2C 3A8",
    "sg:province":"MB",
    "sg:tags":[
        "car",
        "dealer"
    ],
    "wof:name":"Keystone Ford Sales",
    "wof:placetype":"venue"
},
  "geometry": {"coordinates":[-97.0398483276,49.8950843811],"type":"Point"}
}