{
  "type": "Feature",
  "properties": {
    "addr:full":"866 1Ere Rue DE Tracy Chambly QC J3L 1M9",
    "addr:housenumber":"866",
    "addr:postcode":"j3l 1m9",
    "addr:street":"1Ere Rue De Tracy",
    "iso:country":"CA",
    "sg:address":"866 1Ere Rue DE Tracy",
    "sg:city":"Chambly",
    "sg:classifiers":[
        {
            "category":"Wholesale",
            "subcategory":"Electrical",
            "type":"Manufacturing & Wholesale Goods"
        }
    ],
    "sg:phone":"+1 450 447 2892",
    "sg:postcode":"J3L 1M9",
    "sg:province":"QC",
    "sg:tags":[
        "generator"
    ],
    "wof:name":"Gen-Ro Inc",
    "wof:placetype":"venue"
},
  "geometry": {"coordinates":[-73.303062,45.4506],"type":"Point"}
}