{
  "type": "Feature",
  "properties": {
    "iso:country":"CA",
    "sg:address":"10316 124 St NW",
    "sg:city":"Edmonton",
    "sg:classifiers":[
        {
            "category":"Banks & Credit Unions",
            "subcategory":"Investment Brokerage",
            "type":"Services"
        }
    ],
    "sg:phone":"+1 780 447 5557",
    "sg:postcode":"T5N 1R2",
    "sg:province":"AB",
    "sg:tags":[
        "consultant",
        "planning",
        "financial"
    ],
    "wof:name":"Merkur International Inc",
    "wof:placetype":"venue"
},
  "geometry": {"coordinates":[-113.53613281200001,53.5449867249],"type":"Point"}
}