{
  "type": "Feature",
  "properties": {
    "addr:full":"North York ON M2N 6K7",
    "addr:postcode":"m2n 6k7",
    "iso:country":"CA",
    "sg:city":"North York",
    "sg:classifiers":[
        {
            "category":"Health Services",
            "subcategory":"Doctor",
            "type":"Services"
        }
    ],
    "sg:phone":"+1 416 222 3011",
    "sg:postcode":"M2N 6K7",
    "sg:province":"ON",
    "sg:tags":[
        "physician",
        "surgeon"
    ],
    "wof:name":"Jaskolka, Kenneth MD",
    "wof:placetype":"venue"
},
  "geometry": {"coordinates":[-79.4150772095,43.7772216797],"type":"Point"}
}