{
  "type": "Feature",
  "properties": {
    "addr:full":"4981 7 Hwy # 3 Markham ON L3R 1N1",
    "addr:housenumber":"4981",
    "addr:postcode":"l3r 1n1",
    "addr:street":"7 Hwy # 3",
    "iso:country":"CA",
    "sg:address":"4981 7 Hwy # 3",
    "sg:city":"Markham",
    "sg:classifiers":[
        {
            "category":"Retail",
            "subcategory":"Laundry & Dry Cleaning",
            "type":"Services"
        }
    ],
    "sg:phone":"+1 905 477 3745",
    "sg:postcode":"L3R 1N1",
    "sg:province":"ON",
    "sg:tags":[
        "cleaners"
    ],
    "wof:name":"Manhattan Cleaners",
    "wof:placetype":"venue"
},
  "geometry": {"coordinates":[-79.3399429321,43.8560333252],"type":"Point"}
}