{
  "type": "Feature",
  "properties": {
    "addr:full":"45 School St Mahone Bay NS B0J 2E0",
    "addr:housenumber":"45",
    "addr:postcode":"b0j 2e0",
    "addr:street":"School St",
    "iso:country":"CA",
    "sg:address":"45 School St",
    "sg:city":"Mahone Bay",
    "sg:classifiers":[
        {
            "category":"Organizations",
            "subcategory":"Non-profit Organization",
            "type":"Services"
        }
    ],
    "sg:phone":"+1 902 624 0890",
    "sg:postcode":"B0J 2E0",
    "sg:province":"NS",
    "sg:tags":[
        "charitable",
        "institution"
    ],
    "wof:name":"Mahone Bay Centre Society",
    "wof:placetype":"venue"
},
  "geometry": {"coordinates":[-64.381012,44.448647],"type":"Point"}
}