{
  "type": "Feature",
  "properties": {
    "addr:full":"452 Gleneagles Dr Kamloops BC V2E 1Z4",
    "addr:housenumber":"452",
    "addr:postcode":"bc v2e 1z4",
    "addr:street":"Gleneagles Dr",
    "iso:country":"CA",
    "sg:address":"452 Gleneagles Dr",
    "sg:city":"Kamloops",
    "sg:classifiers":[
        {
            "category":"Professional",
            "subcategory":"Management & Consulting",
            "type":"Services"
        }
    ],
    "sg:phone":"+1 250 314 0689",
    "sg:postcode":"V2E 1Z4",
    "sg:province":"BC",
    "sg:tags":[
        "consultant",
        "business"
    ],
    "wof:name":"Catalysis Consulting",
    "wof:placetype":"venue"
},
  "geometry": {"coordinates":[-120.349388,50.654873],"type":"Point"}
}