{
  "type": "Feature",
  "properties": {
    "addr:full":"82 Connaught Dr Jasper AB T0E 1E0",
    "addr:housenumber":"82",
    "addr:postcode":"t0e 1e0",
    "addr:street":"Connaught Dr",
    "iso:country":"CA",
    "sg:address":"82 Connaught Dr",
    "sg:city":"Jasper",
    "sg:classifiers":[
        {
            "category":"Travel",
            "subcategory":"Hotels & Motels",
            "type":"Entertainment"
        }
    ],
    "sg:phone":"+1 780 852 5111",
    "sg:postcode":"T0E 1E0",
    "sg:province":"AB",
    "wof:name":"Sawridge Hotel & Conf Ctr",
    "wof:placetype":"venue"
},
  "geometry": {"coordinates":[-118.077301025,52.8871498108],"type":"Point"}
}