{
  "type": "Feature",
  "properties": {
    "addr:full":"720 Main St Vancouver BC V6A 2V7",
    "addr:housenumber":"720",
    "addr:postcode":"v6a 2v7",
    "addr:street":"Main St",
    "iso:country":"CA",
    "sg:address":"720 Main St",
    "sg:city":"Vancouver",
    "sg:classifiers":[
        {
            "category":"Shopping",
            "type":"Retail Goods"
        }
    ],
    "sg:phone":"+1 604 685 3344",
    "sg:postcode":"V6A 2V7",
    "sg:province":"BC",
    "sg:tags":[
        "miscellaneous",
        "store"
    ],
    "wof:name":"Venus Theatre",
    "wof:placetype":"venue"
},
  "geometry": {"coordinates":[-123.09954071,49.2783241272],"type":"Point"}
}