{
  "type": "Feature",
  "properties": {
    "addr:full":"189 Cote St-Louis E Blainville QC J7E 4H5",
    "addr:housenumber":"189",
    "addr:postcode":"j7e 4h5",
    "addr:street":"Cote St-Louis E",
    "iso:country":"CA",
    "sg:address":"189 Cote St-Louis E",
    "sg:city":"Blainville",
    "sg:classifiers":[
        {
            "category":"Manufacturing",
            "subcategory":"Metals",
            "type":"Manufacturing & Wholesale Goods"
        }
    ],
    "sg:phone":"+1 450 433 8556",
    "sg:postcode":"J7E 4H5",
    "sg:province":"QC",
    "sg:tags":[
        "welding"
    ],
    "wof:name":"Soudures Gravel",
    "wof:placetype":"venue"
},
  "geometry": {"coordinates":[-73.8440856934,45.6681556702],"type":"Point"}
}