{
  "type": "Feature",
  "properties": {
    "iso:country":"CA",
    "sg:city":"Victoria",
    "sg:classifiers":[
        {
            "category":"Health Services",
            "subcategory":"Medical Lab",
            "type":"Services"
        }
    ],
    "sg:phone":"+1 250 381 0400",
    "sg:postcode":"V8T 4M1",
    "sg:province":"BC",
    "sg:tags":[
        "laboratory"
    ],
    "wof:name":"Emni Dental Lab Inc",
    "wof:placetype":"venue"
},
  "geometry": {"coordinates":[-123.366119385,48.4366226196],"type":"Point"}
}