{
  "type": "Feature",
  "properties": {
    "addr:full":"795 3E Av Val-D'Or QC J9P 1S8",
    "addr:housenumber":"795",
    "addr:postcode":"j9p 1s8",
    "addr:street":"3E Av Val-D'Or",
    "iso:country":"CA",
    "sg:address":"795 3E Av",
    "sg:city":"Val-D'Or",
    "sg:classifiers":[
        {
            "category":"Professional",
            "subcategory":"Lawyer & Legal Services",
            "type":"Services"
        }
    ],
    "sg:phone":"+1 819 825 2787",
    "sg:postcode":"J9P 1S8",
    "sg:province":"QC",
    "sg:tags":[
        "attorney"
    ],
    "wof:name":"Cossette, Claude",
    "wof:placetype":"venue"
},
  "geometry": {"coordinates":[-71.66799899999999,48.689648],"type":"Point"}
}