{
  "type": "Feature",
  "properties": {
    "addr:full":"399 John St Burlington ON L7R 2K3",
    "addr:housenumber":"399",
    "addr:postcode":"l7r 2k3",
    "addr:street":"John St",
    "iso:country":"CA",
    "sg:address":"399 John St",
    "sg:city":"Burlington",
    "sg:classifiers":[
        {
            "category":"Shopping",
            "subcategory":"Clothing, Apparel, & Fashions",
            "type":"Retail Goods"
        }
    ],
    "sg:phone":"+1 905 637 3969",
    "sg:postcode":"L7R 2K3",
    "sg:province":"ON",
    "wof:name":"M C Phiver",
    "wof:placetype":"venue"
},
  "geometry": {"coordinates":[-79.79594400000001,43.325275],"type":"Point"}
}