{
  "type": "Feature",
  "properties": {
    "addr:full":"200 Midwest Rd Scarborough ON M1P 3A9",
    "addr:housenumber":"200",
    "addr:postcode":"m1p 3a9",
    "addr:street":"Midwest Rd",
    "iso:country":"CA",
    "sg:address":"200 Midwest Rd",
    "sg:city":"Scarborough",
    "sg:classifiers":[
        {
            "category":"Building & Trades",
            "subcategory":"Construction",
            "type":"Services"
        }
    ],
    "sg:phone":"+1 416 285 0024",
    "sg:postcode":"M1P 3A9",
    "sg:province":"ON",
    "sg:tags":[
        "erectors",
        "machinery"
    ],
    "wof:name":"J Lalonde Machinery Movers Ltd",
    "wof:placetype":"venue"
},
  "geometry": {"coordinates":[-79.27001199999999,43.757607],"type":"Point"}
}