{
  "type": "Feature",
  "properties": {
    "iso:country":"CA",
    "sg:address":"521 Rue Saint-Germain E",
    "sg:city":"Rimouski-Est",
    "sg:classifiers":[
        {
            "category":"Education",
            "subcategory":"School",
            "type":"Public Place"
        }
    ],
    "sg:phone":"+1 418 724 3558",
    "sg:postcode":"G5L 1E8",
    "sg:province":"QC",
    "wof:name":"St-Yves Ecole",
    "wof:placetype":"venue"
},
  "geometry": {"coordinates":[-68.5130767822,48.4744758606],"type":"Point"}
}