{
  "type": "Feature",
  "properties": {
    "iso:country":"CA",
    "sg:city":"Coboconk",
    "sg:classifiers":[
        {
            "category":"Autos & Motor Vehicles",
            "subcategory":"Auto Supplies",
            "type":"Retail Goods"
        }
    ],
    "sg:phone":"+1 705 454 8956",
    "sg:postcode":"K0M 1K0",
    "sg:province":"ON",
    "sg:tags":[
        "tire"
    ],
    "wof:name":"Central Ontario Tire",
    "wof:placetype":"venue"
},
  "geometry": {"coordinates":[-78.80187988279999,44.6634712219],"type":"Point"}
}