{
  "type": "Feature",
  "properties": {
    "addr:full":"1290 Ogilvie Rd Gloucester ON K1J 1H5",
    "addr:housenumber":"1290",
    "addr:postcode":"k1j 1h5",
    "addr:street":"Ogilvie Rd",
    "iso:country":"CA",
    "sg:address":"1290 Ogilvie Rd",
    "sg:city":"Gloucester",
    "sg:classifiers":[
        {
            "category":"Organizations",
            "subcategory":"Religious Organization",
            "type":"Services"
        }
    ],
    "sg:phone":"+1 613 746 9278",
    "sg:postcode":"K1J 1H5",
    "sg:province":"ON",
    "sg:tags":[
        "church"
    ],
    "wof:name":"Epiphany Anglican Church",
    "wof:placetype":"venue"
},
  "geometry": {"coordinates":[-75.6253890991,45.4284172058],"type":"Point"}
}