{
  "type": "Feature",
  "properties": {
    "addr:full":"150 Wellington St E Guelph ON N1H 7P5",
    "addr:housenumber":"150",
    "addr:postcode":"n1h 7p5",
    "addr:street":"Wellington St E",
    "iso:country":"CA",
    "sg:address":"150 Wellington St E",
    "sg:city":"Guelph",
    "sg:classifiers":[
        {
            "category":"Autos & Motor Vehicles",
            "subcategory":"Automobile Sales",
            "type":"Retail Goods"
        }
    ],
    "sg:phone":"+1 519 821 1622",
    "sg:postcode":"N1H 7P5",
    "sg:province":"ON",
    "sg:tags":[
        "car",
        "dealer"
    ],
    "wof:name":"Marsh Auto",
    "wof:placetype":"venue"
},
  "geometry": {"coordinates":[-80.2431793213,43.5456886292],"type":"Point"}
}