{
  "type": "Feature",
  "properties": {
    "addr:full":"7371 Maple Line Pain Court ON N0P 1Z0",
    "addr:housenumber":"7371",
    "addr:postcode":"n0p 1z0",
    "addr:street":"Maple Line;Court",
    "iso:country":"CA",
    "sg:address":"7371 Maple Line",
    "sg:city":"Pain Court",
    "sg:classifiers":[
        {
            "category":"Farming",
            "subcategory":"Farm",
            "type":"Manufacturing & Wholesale Goods"
        }
    ],
    "sg:phone":"+1 519 351 6633",
    "sg:postcode":"N0P 1Z0",
    "sg:province":"ON",
    "wof:name":"Laprise Farms Ltd",
    "wof:placetype":"venue"
},
  "geometry": {"coordinates":[-82.293648,42.392891],"type":"Point"}
}