{
  "type": "Feature",
  "properties": {
    "addr:full":"Montreal QC H3W 1X3",
    "addr:postcode":"h3w 1x3",
    "iso:country":"CA",
    "sg:city":"Montreal",
    "sg:classifiers":[
        {
            "category":"Professional",
            "subcategory":"Accounting & Tax Preparation",
            "type":"Services"
        }
    ],
    "sg:phone":"+1 514 529 8181",
    "sg:postcode":"H3W 1X3",
    "sg:province":"QC",
    "sg:tags":[
        "accountant"
    ],
    "wof:name":"Lary, Kurlender CA",
    "wof:placetype":"venue"
},
  "geometry": {"coordinates":[-73.62648,45.486485],"type":"Point"}
}