{
  "type": "Feature",
  "properties": {
    "iso:country":"CA",
    "sg:address":"85 Norfolk St",
    "sg:city":"Guelph",
    "sg:classifiers":[
        {
            "category":"Shopping",
            "subcategory":"Pharmacy",
            "type":"Retail Goods"
        }
    ],
    "sg:phone":"+1 519 837 1860",
    "sg:postcode":"N1H 4J4",
    "sg:province":"ON",
    "wof:name":"Norfolk Pharmacy & Surgical",
    "wof:placetype":"venue"
},
  "geometry": {"coordinates":[-80.251442,43.544857],"type":"Point"}
}