{
  "type": "Feature",
  "properties": {
    "addr:full":"70 Orchard Park Blvd Toronto ON M4L 3E2",
    "addr:housenumber":"70",
    "addr:postcode":"m4l 3e2",
    "addr:street":"Orchard Park Blvd",
    "iso:country":"CA",
    "sg:address":"70 Orchard Park Blvd",
    "sg:city":"Toronto",
    "sg:classifiers":[
        {
            "category":"Professional",
            "subcategory":"Management & Consulting",
            "type":"Services"
        }
    ],
    "sg:phone":"+1 416 698 9899",
    "sg:postcode":"M4L 3E2",
    "sg:province":"ON",
    "sg:tags":[
        "consultant",
        "lighting"
    ],
    "wof:name":"Lightbrigade Architectural",
    "wof:placetype":"venue"
},
  "geometry": {"coordinates":[-79.312927,43.668987],"type":"Point"}
}