{
  "type": "Feature",
  "properties": {
    "iso:country":"CA",
    "sg:address":"277 Plymouth Rd",
    "sg:city":"Welland",
    "sg:classifiers":[
        {
            "category":"Government",
            "subcategory":"Office",
            "type":"Public Place"
        }
    ],
    "sg:phone":"+1 905 714 7428",
    "sg:postcode":"L3B 6E3",
    "sg:province":"ON",
    "sg:tags":[
        "village"
    ],
    "wof:name":"Douglas H Rapelje Lodge",
    "wof:placetype":"venue"
},
  "geometry": {"coordinates":[-79.2466812134,42.9750099182],"type":"Point"}
}