{
  "type": "Feature",
  "properties": {
    "iso:country":"CA",
    "sg:address":"371 Av Jolliet",
    "sg:city":"Sept-Iles",
    "sg:classifiers":[
        {
            "category":"Home & Garden",
            "subcategory":"Building Materials",
            "type":"Retail Goods"
        }
    ],
    "sg:phone":"+1 418 962 2627",
    "sg:postcode":"G4R 2B1",
    "sg:province":"QC",
    "sg:tags":[
        "door"
    ],
    "wof:name":"Vitrerie Vitronor Inc",
    "wof:placetype":"venue"
},
  "geometry": {"coordinates":[-66.3743057251,50.2090072632],"type":"Point"}
}