{
  "type": "Feature",
  "properties": {
    "addr:full":"114 Kingsmere Pl Saskatoon SK S7J 3V7",
    "addr:housenumber":"114",
    "addr:postcode":"s7j 3v7",
    "addr:street":"Kingsmere Pl",
    "iso:country":"CA",
    "sg:address":"114 Kingsmere Pl",
    "sg:city":"Saskatoon",
    "sg:classifiers":[
        {
            "category":"Organizations",
            "subcategory":"Religious Organization",
            "type":"Services"
        }
    ],
    "sg:phone":"+1 306 374 1425",
    "sg:postcode":"S7J 3V7",
    "sg:province":"SK",
    "sg:tags":[
        "church"
    ],
    "wof:name":"Holy Spirit Parish",
    "wof:placetype":"venue"
},
  "geometry": {"coordinates":[-106.59742,52.103165],"type":"Point"}
}