{
  "type": "Feature",
  "properties": {
    "addr:full":"350 Hwy 17 W Espanola ON P5E 1S1",
    "addr:housenumber":"350",
    "addr:postcode":"p5e 1s1",
    "addr:street":"Hwy 17 W",
    "iso:country":"CA",
    "sg:address":"350 Hwy 17 W",
    "sg:city":"Espanola",
    "sg:classifiers":[
        {
            "category":"Autos & Motor Vehicles",
            "subcategory":"Automobile Sales",
            "type":"Retail Goods"
        }
    ],
    "sg:phone":"+1 705 869 3000",
    "sg:postcode":"P5E 1S1",
    "sg:province":"ON",
    "sg:tags":[
        "car",
        "dealer"
    ],
    "wof:name":"Rainbow Country Chrysler Ltd",
    "wof:placetype":"venue"
},
  "geometry": {"coordinates":[-81.7642364502,46.2567710876],"type":"Point"}
}