{
  "type": "Feature",
  "properties": {
    "addr:full":"319 Korah Rd Sault Ste Marie ON P6C 4H2",
    "addr:housenumber":"319",
    "addr:postcode":"p6c 4h2",
    "addr:street":"Korah Rd",
    "iso:country":"CA",
    "sg:address":"319 Korah Rd",
    "sg:city":"Sault Ste Marie",
    "sg:classifiers":[
        {
            "category":"Restaurant",
            "type":"Food & Drink"
        }
    ],
    "sg:phone":"+1 705 759 2126",
    "sg:postcode":"P6C 4H2",
    "sg:province":"ON",
    "sg:tags":[
        "pizza"
    ],
    "wof:name":"Service Grill Pizza",
    "wof:placetype":"venue"
},
  "geometry": {"coordinates":[-84.362442,46.531551],"type":"Point"}
}