{
  "type": "Feature",
  "properties": {
    "iso:country":"CA",
    "sg:city":"Golden",
    "sg:classifiers":[
        {
            "category":"Travel",
            "subcategory":"Hotels & Motels",
            "type":"Entertainment"
        }
    ],
    "sg:phone":"+1 250 344 2326",
    "sg:postcode":"V0A 1H0",
    "sg:province":"BC",
    "sg:tags":[
        "resort",
        "center",
        "skiing"
    ],
    "wof:name":"Great Canadian Helisking Ltd",
    "wof:placetype":"venue"
},
  "geometry": {"coordinates":[-116.967002869,51.3002166748],"type":"Point"}
}