{
  "type": "Feature",
  "properties": {
    "addr:full":"888 Pape Ave East York ON M4K 3T8",
    "addr:housenumber":"888",
    "addr:postcode":"m4k 3t8",
    "addr:street":"Pape Ave",
    "iso:country":"CA",
    "sg:address":"888 Pape Ave",
    "sg:city":"East York",
    "sg:classifiers":[
        {
            "category":"Professional",
            "subcategory":"Advertising",
            "type":"Services"
        }
    ],
    "sg:phone":"+1 416 696 9887",
    "sg:postcode":"M4K 3T8",
    "sg:province":"ON",
    "sg:tags":[
        "counselor"
    ],
    "wof:name":"Arfin Allen & Assoc Inc",
    "wof:placetype":"venue"
},
  "geometry": {"coordinates":[-79.347488,43.685436],"type":"Point"}
}