{
  "type": "Feature",
  "properties": {
    "addr:full":"90 Main St Fredericton NB E3A 1C5",
    "addr:housenumber":"90",
    "addr:postcode":"e3a 1c5",
    "addr:street":"Main St",
    "iso:country":"CA",
    "sg:address":"90 Main St",
    "sg:city":"Fredericton",
    "sg:classifiers":[
        {
            "category":"Insurance",
            "subcategory":"Insurance Agent",
            "type":"Services"
        }
    ],
    "sg:phone":"+1 506 459 2767",
    "sg:postcode":"E3A 1C5",
    "sg:province":"NB",
    "wof:name":"Stanley Mutual Insurance CO",
    "wof:placetype":"venue"
},
  "geometry": {"coordinates":[-66.658531189,45.9802436829],"type":"Point"}
}