{
  "type": "Feature",
  "properties": {
    "addr:full":"2113 Rue Sainte-Catherine E Montreal QC H2K 2H9",
    "addr:housenumber":"2113",
    "addr:postcode":"h2k 2h9",
    "addr:street":"Rue Sainte-Catherine E",
    "iso:country":"CA",
    "sg:address":"2113 Rue Sainte-Catherine E",
    "sg:city":"Montreal",
    "sg:classifiers":[
        {
            "category":"Wholesale",
            "subcategory":"Scrap",
            "type":"Manufacturing & Wholesale Goods"
        }
    ],
    "sg:phone":"+1 514 523 9220",
    "sg:postcode":"H2K 2H9",
    "sg:province":"QC",
    "sg:tags":[
        "recycling",
        "center"
    ],
    "wof:name":"Eco Cartier Sainte-Marie",
    "wof:placetype":"venue"
},
  "geometry": {"coordinates":[-73.55024719239999,45.5251312256],"type":"Point"}
}