{
  "type": "Feature",
  "properties": {
    "addr:full":"Toronto ON M5B 1B7",
    "addr:postcode":"m5b 1b7",
    "iso:country":"CA",
    "sg:city":"Toronto",
    "sg:classifiers":[
        {
            "category":"Wholesale",
            "subcategory":"Jewelry",
            "type":"Manufacturing & Wholesale Goods"
        }
    ],
    "sg:phone":"+1 416 366 6745",
    "sg:postcode":"M5B 1B7",
    "sg:province":"ON",
    "sg:tags":[
        "jeweler"
    ],
    "wof:name":"M A Diamonds & Jewellery Whol",
    "wof:placetype":"venue"
},
  "geometry": {"coordinates":[-79.3798904419,43.655834198],"type":"Point"}
}