{
  "type": "Feature",
  "properties": {
    "addr:full":"55 Rue Saint-Louis Victoriaville QC G6P 3P6",
    "addr:housenumber":"55",
    "addr:postcode":"g6p 3p6",
    "addr:street":"Rue Saint-Louis",
    "iso:country":"CA",
    "sg:address":"55 Rue Saint-Louis",
    "sg:city":"Victoriaville",
    "sg:classifiers":[
        {
            "category":"Travel",
            "subcategory":"Travel Agent",
            "type":"Entertainment"
        }
    ],
    "sg:phone":"+1 819 758 3151",
    "sg:postcode":"G6P 3P6",
    "sg:province":"QC",
    "sg:tags":[
        "agency",
        "bureau"
    ],
    "wof:name":"Voyages Escapades Enr",
    "wof:placetype":"venue"
},
  "geometry": {"coordinates":[-71.960106,46.055862],"type":"Point"}
}