{
  "type": "Feature",
  "properties": {
    "addr:full":"Markham ON L3S 1Y6",
    "addr:postcode":"l3s 1y6",
    "iso:country":"CA",
    "sg:city":"Markham",
    "sg:classifiers":[
        {
            "category":"Personal",
            "subcategory":"Beauty Salon",
            "type":"Services"
        }
    ],
    "sg:phone":"+1 905 294 2752",
    "sg:postcode":"L3S 1Y6",
    "sg:province":"ON",
    "wof:name":"Anointed Handz Beauty Salon",
    "wof:placetype":"venue"
},
  "geometry": {"coordinates":[-79.2681884766,43.8329467773],"type":"Point"}
}