{
  "type": "Feature",
  "properties": {
    "addr:full":"340 Provencher Blvd Winnipeg MB R2H 0G7",
    "addr:housenumber":"340",
    "addr:postcode":"r2h 0g7",
    "addr:street":"Provencher Blvd",
    "iso:country":"CA",
    "sg:address":"340 Provencher Blvd",
    "sg:city":"Winnipeg",
    "sg:classifiers":[
        {
            "category":"Recreation",
            "type":"Entertainment"
        }
    ],
    "sg:phone":"+1 204 233 8972",
    "sg:postcode":"R2H 0G7",
    "sg:province":"MB",
    "sg:tags":[
        "hall",
        "association",
        "auditorium"
    ],
    "wof:name":"Centre Cultural Franco-MB",
    "wof:placetype":"venue"
},
  "geometry": {"coordinates":[-97.114655,49.893776],"type":"Point"}
}