{
  "type": "Feature",
  "properties": {
    "addr:full":"1019 Northern Ave Thunder Bay ON P7C 5L6",
    "addr:housenumber":"1019",
    "addr:postcode":"p7c 5l6",
    "addr:street":"Northern Ave",
    "iso:country":"CA",
    "sg:address":"1019 Northern Ave",
    "sg:city":"Thunder Bay",
    "sg:classifiers":[
        {
            "category":"Building & Trades",
            "subcategory":"Plumbing",
            "type":"Services"
        }
    ],
    "sg:phone":"+1 807 623 6414",
    "sg:postcode":"P7C 5L6",
    "sg:province":"ON",
    "sg:tags":[
        "mechanical",
        "contractor"
    ],
    "wof:name":"Venshore Mechanical Ltd",
    "wof:placetype":"venue"
},
  "geometry": {"coordinates":[-89.25205200000001,48.394802],"type":"Point"}
}