{
  "type": "Feature",
  "properties": {
    "addr:full":"166 Bullock Dr Markham ON L3P 1W2",
    "addr:housenumber":"166",
    "addr:postcode":"l3p 1w2",
    "addr:street":"Bullock Dr",
    "iso:country":"CA",
    "sg:address":"166 Bullock Dr",
    "sg:city":"Markham",
    "sg:classifiers":[
        {
            "category":"Restaurant",
            "type":"Food & Drink"
        }
    ],
    "sg:phone":"+1 905 472 2555",
    "sg:postcode":"L3P 1W2",
    "sg:province":"ON",
    "sg:tags":[
        "parlor",
        "billiard"
    ],
    "wof:name":"Spectrum Billiards Club",
    "wof:placetype":"venue"
},
  "geometry": {"coordinates":[-79.27722167970001,43.875415802],"type":"Point"}
}