{
  "type": "Feature",
  "properties": {
    "addr:full":"261 Baseline Rd E Bowmanville ON L1C 4B5",
    "addr:housenumber":"261",
    "addr:postcode":"l1c 4b5",
    "addr:street":"Baseline Rd E",
    "iso:country":"CA",
    "sg:address":"261 Baseline Rd E",
    "sg:city":"Bowmanville",
    "sg:classifiers":[
        {
            "category":"Manufacturing",
            "subcategory":"Wood Products",
            "type":"Manufacturing & Wholesale Goods"
        }
    ],
    "sg:phone":"+1 905 623 8383",
    "sg:postcode":"L1C 4B5",
    "sg:province":"ON",
    "sg:tags":[
        "pallet",
        "equipment",
        "material",
        "handling"
    ],
    "wof:name":"Bowmanville Wood Products Inc",
    "wof:placetype":"venue"
},
  "geometry": {"coordinates":[-78.6627960205,43.9039878845],"type":"Point"}
}