{
  "type": "Feature",
  "properties": {
    "addr:full":"416 Av Grosvenor Westmount QC H3Y 2S4",
    "addr:housenumber":"416",
    "addr:postcode":"h3y 2s4",
    "addr:street":"Av Grosvenor",
    "iso:country":"CA",
    "sg:address":"416 Av Grosvenor",
    "sg:city":"Westmount",
    "sg:classifiers":[
        {
            "category":"Professional",
            "subcategory":"Computer Services",
            "type":"Services"
        }
    ],
    "sg:phone":"+1 514 846 3737",
    "sg:postcode":"H3Y 2S4",
    "sg:province":"QC",
    "sg:tags":[
        "graphics"
    ],
    "wof:name":"Compu Art",
    "wof:placetype":"venue"
},
  "geometry": {"coordinates":[-73.603645,45.479885],"type":"Point"}
}