{
  "type": "Feature",
  "properties": {
    "iso:country":"CA",
    "sg:address":"1721 Lakeshore Rd W",
    "sg:city":"Mississauga",
    "sg:classifiers":[
        {
            "category":"Health Services",
            "subcategory":"Medical Lab",
            "type":"Services"
        }
    ],
    "sg:phone":"+1 905 822 6659",
    "sg:postcode":"L5J 1J4",
    "sg:province":"ON",
    "wof:name":"Denture Clinic",
    "wof:placetype":"venue"
},
  "geometry": {"coordinates":[-79.62270355219999,43.5178947449],"type":"Point"}
}