{
  "type": "Feature",
  "properties": {
    "addr:full":"362 the East Mall Etobicoke ON M9B 6C4",
    "addr:housenumber":"362",
    "addr:postcode":"m9b 6c4",
    "addr:street":"The East Mall",
    "iso:country":"CA",
    "sg:address":"362 the East Mall",
    "sg:city":"Etobicoke",
    "sg:classifiers":[
        {
            "category":"Personal",
            "subcategory":"Beauty Salon",
            "type":"Services"
        }
    ],
    "sg:phone":"+1 416 620 4974",
    "sg:postcode":"M9B 6C4",
    "sg:province":"ON",
    "wof:name":"Wisps Unisex Hair Salon",
    "wof:placetype":"venue"
},
  "geometry": {"coordinates":[-79.558144,43.642193],"type":"Point"}
}