{
  "type": "Feature",
  "properties": {
    "iso:country":"CA",
    "sg:address":"34 Gleneagles Rd",
    "sg:city":"Winnipeg",
    "sg:classifiers":[
        {
            "category":"Building & Trades",
            "subcategory":"Electrical",
            "type":"Services"
        }
    ],
    "sg:phone":"+1 204 254 3470",
    "sg:postcode":"R2J 2Y2",
    "sg:province":"MB",
    "sg:tags":[
        "electric",
        "contractor"
    ],
    "wof:name":"Winnipeg Electric",
    "wof:placetype":"venue"
},
  "geometry": {"coordinates":[-97.083763,49.848309],"type":"Point"}
}