{
  "type": "Feature",
  "properties": {
    "addr:full":"Toronto ON M5S 1L6",
    "addr:postcode":"m5s 1l6",
    "iso:country":"CA",
    "sg:city":"Toronto",
    "sg:classifiers":[
        {
            "category":"Education",
            "subcategory":"Special Training",
            "type":"Public Place"
        }
    ],
    "sg:phone":"+1 416 921 6998",
    "sg:postcode":"M5S 1L6",
    "sg:province":"ON",
    "sg:tags":[
        "school",
        "language"
    ],
    "wof:name":"Mws Student Camps",
    "wof:placetype":"venue"
},
  "geometry": {"coordinates":[-79.39054899999999,43.668571],"type":"Point"}
}