{
  "type": "Feature",
  "properties": {
    "iso:country":"CA",
    "sg:address":"10722 Boul Olympia",
    "sg:city":"Montreal",
    "sg:classifiers":[
        {
            "category":"Professional",
            "subcategory":"Advertising",
            "type":"Services"
        }
    ],
    "sg:phone":"+1 514 384 8123",
    "sg:postcode":"H2C 2W5",
    "sg:province":"QC",
    "sg:tags":[
        "counselor"
    ],
    "wof:name":"Emergence Creation Visuelle",
    "wof:placetype":"venue"
},
  "geometry": {"coordinates":[-73.662766,45.563389],"type":"Point"}
}