{
  "type": "Feature",
  "properties": {
    "iso:country":"CA",
    "sg:address":"215 Oakland Ave",
    "sg:city":"Winnipeg",
    "sg:classifiers":[
        {
            "category":"Professional",
            "subcategory":"Art Services",
            "type":"Services"
        }
    ],
    "sg:phone":"+1 204 992 2222",
    "sg:postcode":"R2G 0A7",
    "sg:province":"MB",
    "sg:tags":[
        "graphic",
        "designer"
    ],
    "wof:name":"Score Advertising",
    "wof:placetype":"venue"
},
  "geometry": {"coordinates":[-97.0917510986,49.9372138977],"type":"Point"}
}