{
  "type": "Feature",
  "properties": {
    "addr:full":"895 Century St Winnipeg MB R3H 0M3",
    "addr:housenumber":"895",
    "addr:postcode":"r3h 0m3",
    "addr:street":"Century St",
    "iso:country":"CA",
    "sg:address":"895 Century St",
    "sg:city":"Winnipeg",
    "sg:classifiers":[
        {
            "category":"Home & Garden",
            "subcategory":"Furniture",
            "type":"Retail Goods"
        }
    ],
    "sg:phone":"+1 204 786 5400",
    "sg:postcode":"R3H 0M3",
    "sg:province":"MB",
    "wof:name":"Heart Mattress Stores",
    "wof:placetype":"venue"
},
  "geometry": {"coordinates":[-97.202003479,49.9050445557],"type":"Point"}
}