{
  "type": "Feature",
  "properties": {
    "addr:full":"5315 50 Ave Taber AB T1G 1V3",
    "addr:housenumber":"5315",
    "addr:postcode":"t1g 1v3",
    "addr:street":"50 Ave",
    "iso:country":"CA",
    "sg:address":"5315 50 Ave",
    "sg:city":"Taber",
    "sg:classifiers":[
        {
            "category":"Professional",
            "subcategory":"Accounting & Tax Preparation",
            "type":"Services"
        }
    ],
    "sg:phone":"+1 403 223 3000",
    "sg:postcode":"T1G 1V3",
    "sg:province":"AB",
    "sg:tags":[
        "accountant"
    ],
    "wof:name":"Moedt & CO",
    "wof:placetype":"venue"
},
  "geometry": {"coordinates":[-112.144379,49.786209],"type":"Point"}
}