{
  "type": "Feature",
  "properties": {
    "addr:full":"44 Rue Laval Hull QC J8X 3G7",
    "addr:housenumber":"44",
    "addr:postcode":"j8x 3g7",
    "addr:street":"Rue Laval",
    "iso:country":"CA",
    "sg:address":"44 Rue Laval",
    "sg:city":"Hull",
    "sg:classifiers":[
        {
            "category":"Restaurant",
            "type":"Food & Drink"
        }
    ],
    "sg:phone":"+1 819 771 9557",
    "sg:postcode":"J8X 3G7",
    "sg:province":"QC",
    "sg:tags":[
        "shop",
        "coffee"
    ],
    "wof:name":"Cafe Aux Quatre Jeudis",
    "wof:placetype":"venue"
},
  "geometry": {"coordinates":[-75.716179,45.426926],"type":"Point"}
}