{
  "type": "Feature",
  "properties": {
    "addr:full":"328 Centreville Rd Florenceville NB E7L 3K6",
    "addr:housenumber":"328",
    "addr:postcode":"e7l 3k6",
    "addr:street":"Centreville Rd",
    "iso:country":"CA",
    "sg:address":"328 Centreville Rd",
    "sg:city":"Florenceville",
    "sg:classifiers":[
        {
            "category":"Retail",
            "subcategory":"Auto Repair",
            "type":"Services"
        }
    ],
    "sg:phone":"+1 506 392 6558",
    "sg:postcode":"E7L 3K6",
    "sg:province":"NB",
    "sg:tags":[
        "repairing",
        "automobile",
        "polishing",
        "washing",
        "car"
    ],
    "wof:name":"Bridge Front Auto Svc Ltd",
    "wof:placetype":"venue"
},
  "geometry": {"coordinates":[-67.612129,46.441971],"type":"Point"}
}