{
  "type": "Feature",
  "properties": {
    "addr:full":"460 Torbay Rd St. John's NL A1A 5J3",
    "addr:housenumber":"460",
    "addr:postcode":"a1a 5j3",
    "addr:street":"Torbay Rd",
    "iso:country":"CA",
    "sg:address":"460 Torbay Rd",
    "sg:city":"St. John's",
    "sg:classifiers":[
        {
            "category":"Organizations",
            "subcategory":"Professional Association",
            "type":"Services"
        }
    ],
    "sg:phone":"+1 709 753 6820",
    "sg:postcode":"A1A 5J3",
    "sg:province":"NL",
    "wof:name":"Newfoundland & Labrador Fdrtn",
    "wof:placetype":"venue"
},
  "geometry": {"coordinates":[-52.720428,47.607384],"type":"Point"}
}