{
  "type": "Feature",
  "properties": {
    "iso:country":"CA",
    "sg:address":"118 Main St E",
    "sg:city":"Grimsby",
    "sg:classifiers":[
        {
            "category":"Education",
            "subcategory":"School",
            "type":"Public Place"
        }
    ],
    "sg:phone":"+1 905 945 8022",
    "sg:postcode":"L3M 1N8",
    "sg:province":"ON",
    "wof:name":"Nelles School",
    "wof:placetype":"venue"
},
  "geometry": {"coordinates":[-79.5503997803,43.1893730164],"type":"Point"}
}