{
  "type": "Feature",
  "properties": {
    "addr:full":"St Williams ON N0E 1P0",
    "addr:postcode":"n0e 1p0",
    "iso:country":"CA",
    "sg:city":"St Williams",
    "sg:classifiers":[
        {
            "category":"Recreation",
            "subcategory":"Marina",
            "type":"Entertainment"
        }
    ],
    "sg:phone":"+1 519 586 2212",
    "sg:postcode":"N0E 1P0",
    "sg:province":"ON",
    "sg:tags":[
        "campground"
    ],
    "wof:name":"Shady Aker's Marine & Trailer",
    "wof:placetype":"venue"
},
  "geometry": {"coordinates":[-80.41552734379999,42.6678581238],"type":"Point"}
}