{
  "type": "Feature",
  "properties": {
    "addr:full":"319 Queen St Port Perry ON L9L 1L5",
    "addr:housenumber":"319",
    "addr:postcode":"l9l 1l5",
    "addr:street":"Queen St",
    "iso:country":"CA",
    "sg:address":"319 Queen St",
    "sg:city":"Port Perry",
    "sg:classifiers":[
        {
            "category":"Organizations",
            "subcategory":"Religious Organization",
            "type":"Services"
        }
    ],
    "sg:phone":"+1 905 985 3881",
    "sg:postcode":"L9L 1L5",
    "sg:province":"ON",
    "sg:tags":[
        "church"
    ],
    "wof:name":"Presbyterian Church St John's",
    "wof:placetype":"venue"
},
  "geometry": {"coordinates":[-78.94812,44.103302],"type":"Point"}
}