{
  "type": "Feature",
  "properties": {
    "iso:country":"CA",
    "sg:address":"5006 52nd Ave #6",
    "sg:city":"Vegreville",
    "sg:classifiers":[
        {
            "category":"Personal",
            "subcategory":"Barber",
            "type":"Services"
        }
    ],
    "sg:phone":"+1 780 632 2220",
    "sg:postcode":"T9C 1R1",
    "sg:province":"AB",
    "wof:name":"Len's Barber & Hairstyling",
    "wof:placetype":"venue"
},
  "geometry": {"coordinates":[-112.05062866199999,53.4962921143],"type":"Point"}
}