{
  "type": "Feature",
  "properties": {
    "addr:full":"Dollard-Des-Ormeaux QC H9B 1Z8",
    "addr:postcode":"h9b 1z8",
    "iso:country":"CA",
    "sg:city":"Dollard-Des-Ormeaux",
    "sg:classifiers":[
        {
            "category":"Restaurant",
            "type":"Food & Drink"
        }
    ],
    "sg:phone":"+1 514 685 2046",
    "sg:postcode":"H9B 1Z8",
    "sg:province":"QC",
    "wof:name":"Dagwoods Sandwichs Et Salades",
    "wof:placetype":"venue"
},
  "geometry": {"coordinates":[-73.79633331300001,45.4839363098],"type":"Point"}
}