{
  "type": "Feature",
  "properties": {
    "addr:full":"Edmonton AB T5T 4J5",
    "addr:postcode":"t5t 4j5",
    "iso:country":"CA",
    "sg:city":"Edmonton",
    "sg:classifiers":[
        {
            "category":"Health Services",
            "subcategory":"Doctor",
            "type":"Services"
        }
    ],
    "sg:phone":"+1 780 487 1223",
    "sg:postcode":"T5T 4J5",
    "sg:province":"AB",
    "sg:tags":[
        "physician",
        "surgeon"
    ],
    "wof:name":"Chew, Brian MD",
    "wof:placetype":"venue"
},
  "geometry": {"coordinates":[-113.627487,53.501625],"type":"Point"}
}