{
  "type": "Feature",
  "properties": {
    "addr:full":"290 King St W Prescott ON K0E 1T0",
    "addr:housenumber":"290",
    "addr:postcode":"k0e 1t0",
    "addr:street":"King St W",
    "iso:country":"CA",
    "sg:address":"290 King St W",
    "sg:city":"Prescott",
    "sg:classifiers":[
        {
            "category":"Shopping",
            "subcategory":"Pharmacy",
            "type":"Retail Goods"
        }
    ],
    "sg:phone":"+1 613 925 2891",
    "sg:postcode":"K0E 1T0",
    "sg:province":"ON",
    "wof:name":"Grenville Pharmacy",
    "wof:placetype":"venue"
},
  "geometry": {"coordinates":[-75.515961,44.708672],"type":"Point"}
}