{
  "type": "Feature",
  "properties": {
    "addr:full":"21 Industrial Dr Caledonia ON N3W 1H8",
    "addr:housenumber":"21",
    "addr:postcode":"n3w 1h8",
    "addr:street":"Industrial Dr",
    "iso:country":"CA",
    "sg:address":"21 Industrial Dr",
    "sg:city":"Caledonia",
    "sg:classifiers":[
        {
            "category":"Freight",
            "type":"Transportation"
        }
    ],
    "sg:phone":"+1 905 765 7867",
    "sg:postcode":"N3W 1H8",
    "sg:province":"ON",
    "sg:tags":[
        "commercial",
        "storage"
    ],
    "wof:name":"Caledonia Mini Storage",
    "wof:placetype":"venue"
},
  "geometry": {"coordinates":[-79.95162999999999,43.090271],"type":"Point"}
}