{
  "type": "Feature",
  "properties": {
    "addr:full":"9 Cornwall Rd Cornwall PE C0A 1H0",
    "addr:housenumber":"9",
    "addr:postcode":"c0a 1h0",
    "addr:street":"Cornwall Rd",
    "iso:country":"CA",
    "sg:address":"9 Cornwall Rd",
    "sg:city":"Cornwall",
    "sg:classifiers":[
        {
            "category":"Organizations",
            "subcategory":"Religious Organization",
            "type":"Services"
        }
    ],
    "sg:phone":"+1 902 566 4052",
    "sg:postcode":"C0A 1H0",
    "sg:province":"PE",
    "sg:tags":[
        "church"
    ],
    "wof:name":"Cornwall United Church",
    "wof:placetype":"venue"
},
  "geometry": {"coordinates":[-63.2174072266,46.2287559509],"type":"Point"}
}