{
  "type": "Feature",
  "properties": {
    "addr:full":"580 Montee Bertrand Sabrevois QC J0J 2G0",
    "addr:housenumber":"580",
    "addr:postcode":"j0j 2g0",
    "addr:street":"Montee Bertrand",
    "iso:country":"CA",
    "sg:address":"580 Montee Bertrand",
    "sg:city":"Sabrevois",
    "sg:classifiers":[
        {
            "category":"Building & Trades",
            "subcategory":"Construction",
            "type":"Services"
        }
    ],
    "sg:phone":"+1 450 346 2433",
    "sg:postcode":"J0J 2G0",
    "sg:province":"QC",
    "sg:tags":[
        "general",
        "contractor"
    ],
    "wof:name":"Constructions Gilles Duquette",
    "wof:placetype":"venue"
},
  "geometry": {"coordinates":[-73.2304992676,45.2063903809],"type":"Point"}
}