{
  "type": "Feature",
  "properties": {
    "addr:full":"310 Danforth Ave Toronto ON M4K 1N6",
    "addr:housenumber":"310",
    "addr:postcode":"m4k 1n6",
    "addr:street":"Danforth Ave",
    "iso:country":"CA",
    "sg:address":"310 Danforth Ave",
    "sg:city":"Toronto",
    "sg:classifiers":[
        {
            "category":"Organizations",
            "subcategory":"Professional Association",
            "type":"Services"
        }
    ],
    "sg:phone":"+1 416 463 4384",
    "sg:postcode":"M4K 1N6",
    "sg:province":"ON",
    "wof:name":"Federal Superannuates Nat Assn",
    "wof:placetype":"venue"
},
  "geometry": {"coordinates":[-79.35349273680001,43.6773529053],"type":"Point"}
}