{
  "type": "Feature",
  "properties": {
    "addr:full":"415 Ch DE Touraine Sainte-Julie QC J3E 1Y2",
    "addr:housenumber":"415",
    "addr:postcode":"j3e 1y2",
    "addr:street":"Ch De Touraine",
    "iso:country":"CA",
    "sg:address":"415 Ch DE Touraine",
    "sg:city":"Sainte-Julie",
    "sg:classifiers":[
        {
            "category":"Autos & Motor Vehicles",
            "subcategory":"Auto Supplies",
            "type":"Retail Goods"
        }
    ],
    "sg:phone":"+1 450 649 1489",
    "sg:postcode":"J3E 1Y2",
    "sg:province":"QC",
    "sg:tags":[
        "automobile",
        "parts"
    ],
    "wof:name":"Fontaine O Pieces D'Autos Inc",
    "wof:placetype":"venue"
},
  "geometry": {"coordinates":[-73.323959,45.630112],"type":"Point"}
}