{
  "type": "Feature",
  "properties": {
    "addr:full":"330 Ross Ave The Pas MB R9A 1L5",
    "addr:housenumber":"330",
    "addr:postcode":"r9a 1l5",
    "addr:street":"Ross Ave",
    "iso:country":"CA",
    "sg:address":"330 Ross Ave",
    "sg:city":"The Pas",
    "sg:classifiers":[
        {
            "category":"Real Estate",
            "subcategory":"Real Estate Operator",
            "type":"Services"
        }
    ],
    "sg:phone":"+1 204 623 2761",
    "sg:postcode":"R9A 1L5",
    "sg:province":"MB",
    "sg:tags":[
        "apartment"
    ],
    "wof:name":"Canada House",
    "wof:placetype":"venue"
},
  "geometry": {"coordinates":[-101.248627,53.824306],"type":"Point"}
}