{
  "type": "Feature",
  "properties": {
    "iso:country":"CA",
    "sg:address":"308 Colony St",
    "sg:city":"Winnipeg",
    "sg:classifiers":[
        {
            "category":"Building & Trades",
            "subcategory":"Construction",
            "type":"Services"
        }
    ],
    "sg:phone":"+1 204 783 0413",
    "sg:postcode":"R3C 1W6",
    "sg:province":"MB",
    "sg:tags":[
        "front",
        "store"
    ],
    "wof:name":"Afgd Glass Ctr",
    "wof:placetype":"venue"
},
  "geometry": {"coordinates":[-97.15119934080001,49.8893013],"type":"Point"}
}