{
  "type": "Feature",
  "properties": {
    "addr:full":"1441 Marine Dr North Vancouver BC V7P 1T5",
    "addr:housenumber":"1441",
    "addr:postcode":"v7p 1t5",
    "addr:street":"Marine Dr",
    "iso:country":"CA",
    "sg:address":"1441 Marine Dr",
    "sg:city":"North Vancouver",
    "sg:classifiers":[
        {
            "category":"Personal",
            "subcategory":"Tanning Parlor",
            "type":"Services"
        }
    ],
    "sg:phone":"+1 604 984 7737",
    "sg:postcode":"V7P 1T5",
    "sg:province":"BC",
    "sg:tags":[
        "salon"
    ],
    "wof:name":"Sunshine Tanning Studios",
    "wof:placetype":"venue"
},
  "geometry": {"coordinates":[-123.20589447,49.2743110657],"type":"Point"}
}