{
  "type": "Feature",
  "properties": {
    "addr:full":"Cache Creek BC V0K 1H0",
    "addr:postcode":"v0k 1h0",
    "iso:country":"CA",
    "sg:city":"Cache Creek",
    "sg:classifiers":[
        {
            "category":"Retail",
            "subcategory":"Auto Repair",
            "type":"Services"
        }
    ],
    "sg:phone":"+1 250 457 6753",
    "sg:postcode":"V0K 1H0",
    "sg:province":"BC",
    "sg:tags":[
        "wrecker"
    ],
    "wof:name":"Chanor Radiator Muffler",
    "wof:placetype":"venue"
},
  "geometry": {"coordinates":[-121.322975,50.811008],"type":"Point"}
}