{
  "type": "Feature",
  "properties": {
    "addr:full":"Macklin SK S0L 2C0",
    "addr:postcode":"s0l 2c0",
    "addr:street":"Macklin",
    "iso:country":"CA",
    "sg:city":"Macklin",
    "sg:classifiers":[
        {
            "category":"Banks & Credit Unions",
            "subcategory":"Bank",
            "type":"Services"
        }
    ],
    "sg:phone":"+1 306 753 2045",
    "sg:postcode":"S0L 2C0",
    "sg:province":"SK",
    "wof:name":"Royal Bank Financial Group",
    "wof:placetype":"venue"
},
  "geometry": {"coordinates":[-109.93589,52.332813],"type":"Point"}
}