{
  "type": "Feature",
  "properties": {
    "iso:country":"CA",
    "sg:address":"75 Mary St",
    "sg:city":"Aurora",
    "sg:classifiers":[
        {
            "category":"Building & Trades",
            "subcategory":"Construction",
            "type":"Services"
        }
    ],
    "sg:phone":"+1 905 713 2713",
    "sg:postcode":"L4G 1G3",
    "sg:province":"ON",
    "sg:tags":[
        "concrete",
        "contractor"
    ],
    "wof:name":"Formtech International Corp",
    "wof:placetype":"venue"
},
  "geometry": {"coordinates":[-79.45286560060001,43.9997291565],"type":"Point"}
}