{
  "type": "Feature",
  "properties": {
    "iso:country":"CA",
    "sg:address":"1087 Meyerside Dr # 4",
    "sg:city":"Mississauga",
    "sg:classifiers":[
        {
            "category":"Wholesale",
            "subcategory":"Electrical",
            "type":"Manufacturing & Wholesale Goods"
        }
    ],
    "sg:phone":"+1 905 564 3599",
    "sg:postcode":"L5T 1M5",
    "sg:province":"ON",
    "sg:tags":[
        "control",
        "security",
        "system"
    ],
    "wof:name":"Future Security Controls Inc",
    "wof:placetype":"venue"
},
  "geometry": {"coordinates":[-79.662727,43.652908],"type":"Point"}
}