{
  "type": "Feature",
  "properties": {
    "addr:full":"3235 Boul Pitfield Saint-Laurent QC H4S 1H3",
    "addr:housenumber":"3235",
    "addr:postcode":"h4s 1h3",
    "addr:street":"Boul Pitfield",
    "iso:country":"CA",
    "sg:address":"3235 Boul Pitfield",
    "sg:city":"Saint-Laurent",
    "sg:classifiers":[
        {
            "category":"Wholesale",
            "subcategory":"Machinery & Supplies",
            "type":"Manufacturing & Wholesale Goods"
        }
    ],
    "sg:phone":"+1 514 956 1000",
    "sg:postcode":"H4S 1H3",
    "sg:province":"QC",
    "sg:tags":[
        "machine",
        "tool"
    ],
    "wof:name":"Mirotec",
    "wof:placetype":"venue"
},
  "geometry": {"coordinates":[-73.7518615723,45.5003738403],"type":"Point"}
}