{
  "type": "Feature",
  "properties": {
    "addr:full":"19433 Mccowan Rd Mount Albert ON L0G 1M0",
    "addr:housenumber":"19433",
    "addr:postcode":"l0g 1m0",
    "addr:street":"Mccowan Rd",
    "iso:country":"CA",
    "sg:address":"19433 Mccowan Rd",
    "sg:city":"Mount Albert",
    "sg:classifiers":[
        {
            "category":"Retail",
            "subcategory":"Repair Shop",
            "type":"Services"
        }
    ],
    "sg:phone":"+1 905 473 2124",
    "sg:postcode":"L0G 1M0",
    "sg:province":"ON",
    "sg:tags":[
        "taxidermist"
    ],
    "wof:name":"Doug's Taxidermy",
    "wof:placetype":"venue"
},
  "geometry": {"coordinates":[-79.34612300000001,44.134052],"type":"Point"}
}