{
  "type": "Feature",
  "properties": {
    "addr:full":"8 Foursome Cres North York ON M2P 1W2",
    "addr:housenumber":"8",
    "addr:postcode":"m2p 1w2",
    "addr:street":"Foursome Cres",
    "iso:country":"CA",
    "sg:address":"8 Foursome Cres",
    "sg:city":"North York",
    "sg:classifiers":[
        {
            "category":"Professional",
            "subcategory":"Accounting & Tax Preparation",
            "type":"Services"
        }
    ],
    "sg:phone":"+1 416 512 7088",
    "sg:postcode":"M2P 1W2",
    "sg:province":"ON",
    "sg:tags":[
        "accountant",
        "bookkeeping",
        "general"
    ],
    "wof:name":"Comprehensive Business Svc",
    "wof:placetype":"venue"
},
  "geometry": {"coordinates":[-79.3974151611,43.7503051758],"type":"Point"}
}