{
  "type": "Feature",
  "properties": {
    "addr:full":"1415 Boul Laure Sept-Iles QC G4R 4K1",
    "addr:housenumber":"1415",
    "addr:postcode":"g4r 4k1",
    "addr:street":"Boul Laure Sept-Iles",
    "iso:country":"CA",
    "sg:address":"1415 Boul Laure",
    "sg:city":"Sept-Iles",
    "sg:classifiers":[
        {
            "category":"Travel",
            "subcategory":"Hotels & Motels",
            "type":"Entertainment"
        }
    ],
    "sg:phone":"+1 418 962 2228",
    "sg:postcode":"G4R 4K1",
    "sg:province":"QC",
    "wof:name":"Motel Le Voyageur",
    "wof:placetype":"venue"
},
  "geometry": {"coordinates":[-66.3972854614,50.245174408],"type":"Point"}
}