{
  "type": "Feature",
  "properties": {
    "addr:full":"1731 Middleton Ave Brandon MB R7C 1A7",
    "addr:housenumber":"1731",
    "addr:postcode":"r7c 1a7",
    "addr:street":"Middleton Ave",
    "iso:country":"CA",
    "sg:address":"1731 Middleton Ave",
    "sg:city":"Brandon",
    "sg:classifiers":[
        {
            "category":"Retail",
            "subcategory":"Auto Repair",
            "type":"Services"
        }
    ],
    "sg:phone":"+1 204 726 0000",
    "sg:postcode":"R7C 1A7",
    "sg:province":"MB",
    "sg:tags":[
        "equipment",
        "parts",
        "truck"
    ],
    "wof:name":"Freightliner Manitoba Ltd",
    "wof:placetype":"venue"
},
  "geometry": {"coordinates":[-99.9592590332,49.887348175],"type":"Point"}
}