{
  "type": "Feature",
  "properties": {
    "addr:full":"21 Peter St S Orillia ON L3V 5A8",
    "addr:housenumber":"21",
    "addr:postcode":"l3v 5a8",
    "addr:street":"Peter St S",
    "iso:country":"CA",
    "sg:address":"21 Peter St S",
    "sg:city":"Orillia",
    "sg:classifiers":[
        {
            "category":"Personal",
            "subcategory":"Barber",
            "type":"Services"
        }
    ],
    "sg:phone":"+1 705 329 2836",
    "sg:postcode":"L3V 5A8",
    "sg:province":"ON",
    "wof:name":"Rocky's Barber Shop",
    "wof:placetype":"venue"
},
  "geometry": {"coordinates":[-79.417511,44.608658],"type":"Point"}
}