{
  "type": "Feature",
  "properties": {
    "addr:full":"41 Bennett St Bell Island NL A0A 4H0",
    "addr:housenumber":"41",
    "addr:postcode":"a0a 4h0",
    "addr:street":"Bennett St Bell",
    "iso:country":"CA",
    "sg:address":"41 Bennett St",
    "sg:city":"Bell Island",
    "sg:classifiers":[
        {
            "category":"Food & Beverages",
            "subcategory":"Groceries & Convenience Stores",
            "type":"Retail Goods"
        }
    ],
    "sg:phone":"+1 709 488 2985",
    "sg:postcode":"A0A 4H0",
    "sg:province":"NL",
    "sg:tags":[
        "grocer"
    ],
    "wof:name":"G D Byrne Easysave",
    "wof:placetype":"venue"
},
  "geometry": {"coordinates":[-52.94907,47.622978],"type":"Point"}
}