{
  "type": "Feature",
  "properties": {
    "addr:full":"Calgary AB T2L 2J8",
    "addr:postcode":"t2l 2j8",
    "iso:country":"CA",
    "sg:city":"Calgary",
    "sg:classifiers":[
        {
            "category":"Shopping",
            "subcategory":"Hobbies, Toys, & Games",
            "type":"Retail Goods"
        }
    ],
    "sg:phone":"+1 403 247 4143",
    "sg:postcode":"T2L 2J8",
    "sg:province":"AB",
    "sg:tags":[
        "house",
        "bird",
        "feeder"
    ],
    "wof:name":"Back To Nature Store",
    "wof:placetype":"venue"
},
  "geometry": {"coordinates":[-114.141571,51.098434],"type":"Point"}
}