{
  "type": "Feature",
  "properties": {
    "addr:full":"1394 Av Du Mont-Royal E Montreal QC H2J 1Y7",
    "addr:housenumber":"1394",
    "addr:postcode":"h2j 1y7",
    "addr:street":"Av Du Mont-Royal E",
    "iso:country":"CA",
    "sg:address":"1394 Av Du Mont-Royal E",
    "sg:city":"Montreal",
    "sg:classifiers":[
        {
            "category":"Social Services",
            "subcategory":"Job Training",
            "type":"Services"
        }
    ],
    "sg:phone":"+1 514 523 7553",
    "sg:postcode":"H2J 1Y7",
    "sg:province":"QC",
    "sg:tags":[
        "career",
        "counseling",
        "vocational"
    ],
    "wof:name":"St-Pierre, Louise",
    "wof:placetype":"venue"
},
  "geometry": {"coordinates":[-73.576469,45.530708],"type":"Point"}
}