{
  "type": "Feature",
  "properties": {
    "addr:full":"6 Boul Mercier Beaumont QC G0R 1C0",
    "addr:housenumber":"6",
    "addr:postcode":"g0r 1c0",
    "addr:street":"Boul Mercier",
    "iso:country":"CA",
    "sg:address":"6 Boul Mercier",
    "sg:city":"Beaumont",
    "sg:classifiers":[
        {
            "category":"Government",
            "subcategory":"Fire Station",
            "type":"Public Place"
        }
    ],
    "sg:phone":"+1 ",
    "sg:postcode":"G0R 1C0",
    "sg:province":"QC",
    "sg:tags":[
        "department"
    ],
    "wof:name":"Beaumont Feu",
    "wof:placetype":"venue"
},
  "geometry": {"coordinates":[-71.011246,46.829063],"type":"Point"}
}