{
  "type": "Feature",
  "properties": {
    "addr:full":"SW 12 10 26W Virden MB R0M 2C0",
    "addr:housenumber":"10 26w",
    "addr:postcode":"r0m 2c0",
    "addr:street":"Sw 12",
    "iso:country":"CA",
    "sg:address":"SW 12 10 26W",
    "sg:city":"Virden",
    "sg:classifiers":[
        {
            "category":"Retail",
            "subcategory":"Repair Shop",
            "type":"Services"
        }
    ],
    "sg:phone":"+1 204 748 2863",
    "sg:postcode":"R0M 2C0",
    "sg:province":"MB",
    "sg:tags":[
        "sharpening"
    ],
    "wof:name":"Always Twice As Sharp",
    "wof:placetype":"venue"
},
  "geometry": {"coordinates":[-100.91971599999999,49.856026],"type":"Point"}
}