{
  "type": "Feature",
  "properties": {
    "addr:full":"269 Queen St Port Perry ON L9L 1B9",
    "addr:housenumber":"269",
    "addr:postcode":"l9l 1b9",
    "addr:street":"Queen St",
    "iso:country":"CA",
    "sg:address":"269 Queen St",
    "sg:city":"Port Perry",
    "sg:classifiers":[
        {
            "category":"Travel",
            "subcategory":"Travel Agent",
            "type":"Entertainment"
        }
    ],
    "sg:phone":"+1 905 985 4971",
    "sg:postcode":"L9L 1B9",
    "sg:province":"ON",
    "sg:tags":[
        "information",
        "tourist"
    ],
    "wof:name":"Scugog Tourist Information Ctr",
    "wof:placetype":"venue"
},
  "geometry": {"coordinates":[-78.94586200000001,44.104172],"type":"Point"}
}