{
  "type": "Feature",
  "properties": {
    "addr:full":"81 Brant Ave Brantford ON N3T 3H2",
    "addr:housenumber":"81",
    "addr:postcode":"n3t 3h2",
    "addr:street":"Brant Ave",
    "iso:country":"CA",
    "sg:address":"81 Brant Ave",
    "sg:city":"Brantford",
    "sg:classifiers":[
        {
            "category":"Restaurant",
            "type":"Food & Drink"
        }
    ],
    "sg:phone":"+1 519 756 9939",
    "sg:postcode":"N3T 3H2",
    "sg:province":"ON",
    "sg:tags":[
        "pizza"
    ],
    "wof:name":"Cliffy's Pizzeria & Rstrnt",
    "wof:placetype":"venue"
},
  "geometry": {"coordinates":[-80.27137,43.141518],"type":"Point"}
}