{
  "type": "Feature",
  "properties": {
    "iso:country":"CA",
    "sg:address":"91 Saskatchewan St S",
    "sg:city":"Eyebrow",
    "sg:classifiers":[
        {
            "category":"Organizations",
            "subcategory":"Religious Organization",
            "type":"Services"
        }
    ],
    "sg:phone":"+1 306 759 2272",
    "sg:postcode":"S0H 1L0",
    "sg:province":"SK",
    "sg:tags":[
        "church"
    ],
    "wof:name":"Free Methodist Church",
    "wof:placetype":"venue"
},
  "geometry": {"coordinates":[-106.14982605,50.8024864197],"type":"Point"}
}