{
  "type": "Feature",
  "properties": {
    "addr:full":"123 Rue Baby Joliette QC J6E 2V4",
    "addr:housenumber":"123",
    "addr:postcode":"j6e 2v4",
    "addr:street":"Rue Baby",
    "iso:country":"CA",
    "sg:address":"123 Rue Baby",
    "sg:city":"Joliette",
    "sg:classifiers":[
        {
            "category":"Autos & Motor Vehicles",
            "subcategory":"Fuel & Gas Station",
            "type":"Retail Goods"
        }
    ],
    "sg:phone":"+1 450 759 4542",
    "sg:postcode":"J6E 2V4",
    "sg:province":"QC",
    "sg:tags":[
        "oil"
    ],
    "wof:name":"Station DE Svc Ferland Inc",
    "wof:placetype":"venue"
},
  "geometry": {"coordinates":[-73.4366226196,46.0309791565],"type":"Point"}
}