{
  "type": "Feature",
  "properties": {
    "addr:full":"RR 1 Bowden AB T0M 0K0",
    "addr:postcode":"t0m 0k0",
    "addr:street":"Rr 1",
    "iso:country":"CA",
    "sg:address":"RR 1",
    "sg:city":"Bowden",
    "sg:classifiers":[
        {
            "category":"Manufacturing",
            "subcategory":"Buildings",
            "type":"Manufacturing & Wholesale Goods"
        }
    ],
    "sg:phone":"+1 403 224 3991",
    "sg:postcode":"T0M 0K0",
    "sg:province":"AB",
    "sg:tags":[
        "home",
        "log",
        "cabin"
    ],
    "wof:name":"Eagle Creek Custom Logs",
    "wof:placetype":"venue"
},
  "geometry": {"coordinates":[-114.02984600000001,51.938614],"type":"Point"}
}