{
  "type": "Feature",
  "properties": {
    "iso:country":"CA",
    "sg:city":"Dieppe",
    "sg:classifiers":[
        {
            "category":"Manufacturing",
            "subcategory":"Tools & Machinery",
            "type":"Manufacturing & Wholesale Goods"
        }
    ],
    "sg:phone":"+1 506 854 2496",
    "sg:postcode":"E1A 1G3",
    "sg:province":"NB",
    "sg:tags":[
        "control",
        "system",
        "automation"
    ],
    "wof:name":"Memco Controls Ltd",
    "wof:placetype":"venue"
},
  "geometry": {"coordinates":[-64.7330856323,46.0848960876],"type":"Point"}
}