{
  "type": "Feature",
  "properties": {
    "addr:full":"1243 Anderson Line Coldwater ON L0K 1E0",
    "addr:housenumber":"1243",
    "addr:postcode":"l0k 1e0",
    "addr:street":"Anderson Line",
    "iso:country":"CA",
    "sg:address":"1243 Anderson Line",
    "sg:city":"Coldwater",
    "sg:classifiers":[
        {
            "category":"Retail",
            "subcategory":"Laundry & Dry Cleaning",
            "type":"Services"
        }
    ],
    "sg:phone":"+1 705 734 2969",
    "sg:postcode":"L0K 1E0",
    "sg:province":"ON",
    "sg:tags":[
        "cleaners",
        "rug",
        "carpet"
    ],
    "wof:name":"Excellent Cleaning Svc Ltd",
    "wof:placetype":"venue"
},
  "geometry": {"coordinates":[-79.631844,44.711063],"type":"Point"}
}