{
  "type": "Feature",
  "properties": {
    "addr:full":"Niagara Falls ON L2E 6S5",
    "addr:postcode":"l2e 6s5",
    "iso:country":"CA",
    "sg:city":"Niagara Falls",
    "sg:classifiers":[
        {
            "category":"Building & Trades",
            "subcategory":"Plumbing",
            "type":"Services"
        }
    ],
    "sg:phone":"+1 905 646 0233",
    "sg:postcode":"L2E 6S5",
    "sg:province":"ON",
    "sg:tags":[
        "septic"
    ],
    "wof:name":"Bruce Reaman Septic Tank Svc",
    "wof:placetype":"venue"
},
  "geometry": {"coordinates":[-79.1250839233,43.0592651367],"type":"Point"}
}