{
  "type": "Feature",
  "properties": {
    "addr:full":"380 295 Rte Degelis QC G5T 1R5",
    "addr:housenumber":"380 295",
    "addr:postcode":"g5t 1r5",
    "addr:street":"Rte Degelis",
    "iso:country":"CA",
    "sg:address":"380 295 Rte",
    "sg:city":"Degelis",
    "sg:classifiers":[
        {
            "category":"Travel",
            "subcategory":"Campground",
            "type":"Entertainment"
        }
    ],
    "sg:phone":"+1 418 853 2655",
    "sg:postcode":"G5T 1R5",
    "sg:province":"QC",
    "sg:tags":[
        "government"
    ],
    "wof:name":"Degelis Chalet Des Sports",
    "wof:placetype":"venue"
},
  "geometry": {"coordinates":[-68.642517,47.546989],"type":"Point"}
}