{
  "type": "Feature",
  "properties": {
    "iso:country":"CA",
    "sg:city":"Etobicoke",
    "sg:classifiers":[
        {
            "category":"Professional",
            "subcategory":"Engineering",
            "type":"Services"
        }
    ],
    "sg:phone":"+1 416 674 3017",
    "sg:postcode":"M9P 3V4",
    "sg:province":"ON",
    "sg:tags":[
        "engineer"
    ],
    "wof:name":"Aiolos Engineering",
    "wof:placetype":"venue"
},
  "geometry": {"coordinates":[-79.5506896973,43.7053108215],"type":"Point"}
}