{
  "type": "Feature",
  "properties": {
    "addr:full":"Mar ON N0H 1X0",
    "addr:postcode":"n0h 1x0",
    "iso:country":"CA",
    "sg:city":"Mar",
    "sg:classifiers":[
        {
            "category":"Travel",
            "subcategory":"Hotels & Motels",
            "type":"Entertainment"
        }
    ],
    "sg:phone":"+1 519 534 4002",
    "sg:postcode":"N0H 1X0",
    "sg:province":"ON",
    "sg:tags":[
        "breakfast",
        "accommodation",
        "bed"
    ],
    "wof:name":"Haven on the Bay Bed & Brkfst",
    "wof:placetype":"venue"
},
  "geometry": {"coordinates":[-81.2121505737,44.8207015991],"type":"Point"}
}