{
  "type": "Feature",
  "properties": {
    "addr:full":"216 Airport Blvd Gander NL A1V 1L6",
    "addr:housenumber":"216",
    "addr:postcode":"a1v 1l6",
    "addr:street":"Airport Blvd",
    "iso:country":"CA",
    "sg:address":"216 Airport Blvd",
    "sg:city":"Gander",
    "sg:classifiers":[
        {
            "category":"Food & Beverages",
            "subcategory":"Specialty",
            "type":"Retail Goods"
        }
    ],
    "sg:phone":"+1 709 256 7946",
    "sg:postcode":"A1V 1L6",
    "sg:province":"NL",
    "sg:tags":[
        "health",
        "diet"
    ],
    "wof:name":"Nan's Pantry",
    "wof:placetype":"venue"
},
  "geometry": {"coordinates":[-54.607487,48.956055],"type":"Point"}
}