{
  "type": "Feature",
  "properties": {
    "addr:full":"203752 Hwy 26 Owen Sound ON N4K 5W4",
    "addr:housenumber":"203752",
    "addr:postcode":"n4k 5w4",
    "addr:street":"Hwy 26",
    "iso:country":"CA",
    "sg:address":"203752 Hwy 26",
    "sg:city":"Owen Sound",
    "sg:classifiers":[
        {
            "category":"Communications",
            "subcategory":"Film & Video Production",
            "type":"Services"
        }
    ],
    "sg:phone":"+1 519 371 1916",
    "sg:postcode":"N4K 5W4",
    "sg:province":"ON",
    "sg:tags":[
        "motion",
        "picture",
        "studio",
        "producer"
    ],
    "wof:name":"Going Fishing",
    "wof:placetype":"venue"
},
  "geometry": {"coordinates":[-80.92259979249999,44.5740585327],"type":"Point"}
}