{
  "type": "Feature",
  "properties": {
    "addr:full":"PO Box 5162 STN Main Drayton Valley AB T7A 1R4",
    "addr:housenumber":"po",
    "addr:postcode":"5162;t7a 1r4",
    "addr:street":"Box;Stn Main",
    "iso:country":"CA",
    "sg:address":"PO Box 5162 STN Main",
    "sg:city":"Drayton Valley",
    "sg:classifiers":[
        {
            "category":"Real Estate",
            "subcategory":"Developer",
            "type":"Services"
        }
    ],
    "sg:phone":"+1 780 542 7329",
    "sg:postcode":"T7A 1R4",
    "sg:province":"AB",
    "sg:tags":[
        "mobile",
        "home"
    ],
    "wof:name":"Gmb Property Rentals Ltd",
    "wof:placetype":"venue"
},
  "geometry": {"coordinates":[-117.27177399999999,55.068642],"type":"Point"}
}