{
  "type": "Feature",
  "properties": {
    "addr:full":"3250 Boul Des Entreprises Terrebonne QC J6X 4J8",
    "addr:housenumber":"3250",
    "addr:postcode":"j6x 4j8",
    "addr:street":"Boul Des Entreprises",
    "iso:country":"CA",
    "sg:address":"3250 Boul Des Entreprises",
    "sg:city":"Terrebonne",
    "sg:classifiers":[
        {
            "category":"Manufacturing",
            "subcategory":"Tools & Machinery",
            "type":"Manufacturing & Wholesale Goods"
        }
    ],
    "sg:phone":"+1 450 477 4000",
    "sg:postcode":"J6X 4J8",
    "sg:province":"QC",
    "sg:tags":[
        "lawn",
        "mower"
    ],
    "wof:name":"Motos Illimitees",
    "wof:placetype":"venue"
},
  "geometry": {"coordinates":[-73.69119262700001,45.7243003845],"type":"Point"}
}