{
  "type": "Feature",
  "properties": {
    "addr:full":"601 Rue Adoncour Longueuil QC J4G 2M6",
    "addr:housenumber":"601",
    "addr:postcode":"j4g 2m6",
    "addr:street":"Rue Adoncour",
    "iso:country":"CA",
    "sg:address":"601 Rue Adoncour",
    "sg:city":"Longueuil",
    "sg:classifiers":[
        {
            "category":"Organizations",
            "subcategory":"Labor Organization",
            "type":"Services"
        }
    ],
    "sg:phone":"+1 450 646 3762",
    "sg:postcode":"J4G 2M6",
    "sg:province":"QC",
    "wof:name":"Travailleurs Canadiens-L'Auto",
    "wof:placetype":"venue"
},
  "geometry": {"coordinates":[-73.484489,45.553207],"type":"Point"}
}