{
  "type": "Feature",
  "properties": {
    "iso:country":"CA",
    "sg:address":"601 Rue Adoncour",
    "sg:city":"Longueuil",
    "sg:classifiers":[
        {
            "category":"Organizations",
            "subcategory":"Labor Organization",
            "type":"Services"
        }
    ],
    "sg:phone":"+1 450 646 3762",
    "sg:postcode":"J4G 2M6",
    "sg:province":"QC",
    "wof:name":"Travailleurs Canadiens-L'Auto",
    "wof:placetype":"venue"
},
  "geometry": {"coordinates":[-73.484489,45.553207],"type":"Point"}
}