{
  "type": "Feature",
  "properties": {
    "addr:full":"541 William St Cobourg ON K9A 3A4",
    "addr:housenumber":"541",
    "addr:postcode":"k9a 3a4",
    "addr:street":"William St",
    "iso:country":"CA",
    "sg:address":"541 William St",
    "sg:city":"Cobourg",
    "sg:classifiers":[
        {
            "category":"Food & Beverages",
            "subcategory":"Groceries & Convenience Stores",
            "type":"Retail Goods"
        }
    ],
    "sg:phone":"+1 905 372 0722",
    "sg:postcode":"K9A 3A4",
    "sg:province":"ON",
    "wof:name":"Total Convenience",
    "wof:placetype":"venue"
},
  "geometry": {"coordinates":[-78.181648,43.963486],"type":"Point"}
}