{
  "type": "Feature",
  "properties": {
    "addr:full":"4994 Rue Beaubien E Montreal QC H1T 1V4",
    "addr:housenumber":"4994",
    "addr:postcode":"h1t 1v4",
    "addr:street":"Rue Beaubien E",
    "iso:country":"CA",
    "sg:address":"4994 Rue Beaubien E",
    "sg:city":"Montreal",
    "sg:classifiers":[
        {
            "category":"Government",
            "subcategory":"Office",
            "type":"Public Place"
        }
    ],
    "sg:phone":"+1 514 872 5005",
    "sg:postcode":"H1T 1V4",
    "sg:province":"QC",
    "wof:name":"Quebec Centre Local D'Emploi",
    "wof:placetype":"venue"
},
  "geometry": {"coordinates":[-73.57164,45.571621],"type":"Point"}
}