{
  "type": "Feature",
  "properties": {
    "iso:country":"CA",
    "sg:address":"9551 111 Ave NW",
    "sg:city":"Edmonton",
    "sg:classifiers":[
        {
            "category":"Home & Garden",
            "subcategory":"Building Materials",
            "type":"Retail Goods"
        }
    ],
    "sg:phone":"+1 780 426 7654",
    "sg:postcode":"T5G 0A5",
    "sg:province":"AB",
    "sg:tags":[
        "glass",
        "window",
        "plate"
    ],
    "wof:name":"Crystal Glass Canada Ltd",
    "wof:placetype":"venue"
},
  "geometry": {"coordinates":[-113.488853455,53.5593070984],"type":"Point"}
}