{
  "type": "Feature",
  "properties": {
    "addr:full":"Saint-Simeon QC G0T 1X0",
    "addr:postcode":"g0t 1x0",
    "iso:country":"CA",
    "sg:city":"Saint-Simeon",
    "sg:classifiers":[
        {
            "category":"Home & Garden",
            "subcategory":"Building Materials",
            "type":"Retail Goods"
        }
    ],
    "sg:phone":"+1 418 638 2323",
    "sg:postcode":"G0T 1X0",
    "sg:province":"QC",
    "wof:name":"Materiaux DE Constr Rjm Inc",
    "wof:placetype":"venue"
},
  "geometry": {"coordinates":[-69.87505299999999,47.846462],"type":"Point"}
}