{
  "type": "Feature",
  "properties": {
    "addr:full":"1199 Mountain View Rd Armstrong BC V0E 1B8",
    "addr:housenumber":"1199",
    "addr:postcode":"v0e 1b8",
    "addr:street":"Mountain View Rd",
    "iso:country":"CA",
    "sg:address":"1199 Mountain View Rd",
    "sg:city":"Armstrong",
    "sg:classifiers":[
        {
            "category":"Building & Trades",
            "subcategory":"Construction",
            "type":"Services"
        }
    ],
    "sg:phone":"+1 250 549 3130",
    "sg:postcode":"V0E 1B8",
    "sg:province":"BC",
    "sg:tags":[
        "boring",
        "drilling",
        "contractor"
    ],
    "wof:name":"Dan-Gare Drilling Ltd",
    "wof:placetype":"venue"
},
  "geometry": {"coordinates":[-119.183701,50.441818],"type":"Point"}
}