{
  "type": "Feature",
  "properties": {
    "iso:country":"CA",
    "sg:address":"2072 Kingsway",
    "sg:city":"Vancouver",
    "sg:classifiers":[
        {
            "category":"Personal",
            "subcategory":"Barber",
            "type":"Services"
        }
    ],
    "sg:phone":"+1 604 879 1614",
    "sg:postcode":"V5N 2T3",
    "sg:province":"BC",
    "wof:name":"Kings Cut Men's Hair Styling",
    "wof:placetype":"venue"
},
  "geometry": {"coordinates":[-123.06431600000001,49.244598],"type":"Point"}
}