{
  "type": "Feature",
  "properties": {
    "addr:full":"7491 Cougarsmith Rd Fanny Bay BC V0R 1W0",
    "addr:housenumber":"7491",
    "addr:postcode":"v0r 1w0",
    "addr:street":"Cougarsmith Rd",
    "iso:country":"CA",
    "sg:address":"7491 Cougarsmith Rd",
    "sg:city":"Fanny Bay",
    "sg:classifiers":[
        {
            "category":"Retail",
            "subcategory":"Animal Services",
            "type":"Services"
        }
    ],
    "sg:phone":"+1 250 335 2378",
    "sg:postcode":"V0R 1W0",
    "sg:province":"BC",
    "sg:tags":[
        "pet",
        "boarding",
        "sitting"
    ],
    "wof:name":"Best Friend Dog Care",
    "wof:placetype":"venue"
},
  "geometry": {"coordinates":[-124.827423,49.501678],"type":"Point"}
}