{
  "type": "Feature",
  "properties": {
    "addr:full":"622 Birchmount Rd Scarborough ON M1K 1P9",
    "addr:housenumber":"622",
    "addr:postcode":"m1k 1p9",
    "addr:street":"Birchmount Rd",
    "iso:country":"CA",
    "sg:address":"622 Birchmount Rd",
    "sg:city":"Scarborough",
    "sg:classifiers":[
        {
            "category":"Retail",
            "subcategory":"Repair Shop",
            "type":"Services"
        }
    ],
    "sg:phone":"+1 416 261 1281",
    "sg:postcode":"M1K 1P9",
    "sg:province":"ON",
    "sg:tags":[
        "upholsterer"
    ],
    "wof:name":"George Interiors",
    "wof:placetype":"venue"
},
  "geometry": {"coordinates":[-79.272682,43.71748],"type":"Point"}
}