{
  "type": "Feature",
  "properties": {
    "addr:full":"537 Pleasant St Dartmouth NS B2W 1A6",
    "addr:housenumber":"537",
    "addr:postcode":"b2w 1a6",
    "addr:street":"Pleasant St",
    "iso:country":"CA",
    "sg:address":"537 Pleasant St",
    "sg:city":"Dartmouth",
    "sg:classifiers":[
        {
            "category":"Restaurant",
            "type":"Food & Drink"
        }
    ],
    "sg:phone":"+1 902 463 4995",
    "sg:postcode":"B2W 1A6",
    "sg:province":"NS",
    "sg:tags":[
        "pizza"
    ],
    "wof:name":"Mason Pizza & Donair",
    "wof:placetype":"venue"
},
  "geometry": {"coordinates":[-63.541214,44.644703],"type":"Point"}
}