{
  "type": "Feature",
  "properties": {
    "iso:country":"CA",
    "sg:address":"1079 South River Rd",
    "sg:city":"Whitefish Falls",
    "sg:classifiers":[
        {
            "category":"Travel",
            "subcategory":"Hotels & Motels",
            "type":"Entertainment"
        }
    ],
    "sg:phone":"+1 705 285 4266",
    "sg:postcode":"P0P 2H0",
    "sg:province":"ON",
    "sg:tags":[
        "cottage",
        "cabin"
    ],
    "wof:name":"Bay Villa Lodge",
    "wof:placetype":"venue"
},
  "geometry": {"coordinates":[-81.7310791016,46.1101493835],"type":"Point"}
}