{
  "type": "Feature",
  "properties": {
    "addr:full":"8020 Rue Jean-Brillon Lasalle QC H8N 2L5",
    "addr:housenumber":"8020",
    "addr:postcode":"h8n 2l5",
    "addr:street":"Rue Jean-Brillon",
    "iso:country":"CA",
    "sg:address":"8020 Rue Jean-Brillon",
    "sg:city":"Lasalle",
    "sg:classifiers":[
        {
            "category":"Wholesale",
            "subcategory":"Books, Periodicals, & Newspapers",
            "type":"Manufacturing & Wholesale Goods"
        }
    ],
    "sg:phone":"+1 514 363 7272",
    "sg:postcode":"H8N 2L5",
    "sg:province":"QC",
    "sg:tags":[
        "magazine"
    ],
    "wof:name":"Messageries DE Presse Benjamin",
    "wof:placetype":"venue"
},
  "geometry": {"coordinates":[-73.615692,45.434345],"type":"Point"}
}