{
  "type": "Feature",
  "properties": {
    "addr:full":"902 Railway St Kipling SK S0G 2S0",
    "addr:housenumber":"902",
    "addr:postcode":"s0g 2s0",
    "addr:street":"Railway St",
    "iso:country":"CA",
    "sg:address":"902 Railway St",
    "sg:city":"Kipling",
    "sg:classifiers":[
        {
            "category":"Freight",
            "type":"Transportation"
        }
    ],
    "sg:phone":"+1 306 736 2303",
    "sg:postcode":"S0G 2S0",
    "sg:province":"SK",
    "sg:tags":[
        "grain",
        "elevator"
    ],
    "wof:name":"N M Paterson & CO Ltd",
    "wof:placetype":"venue"
},
  "geometry": {"coordinates":[-102.63407100000001,50.103569],"type":"Point"}
}