{
  "type": "Feature",
  "properties": {
    "addr:full":"366 Queen St S Hamilton ON L8P 3T9",
    "addr:housenumber":"366",
    "addr:postcode":"l8p 3t9",
    "addr:street":"Queen St S",
    "iso:country":"CA",
    "sg:address":"366 Queen St S",
    "sg:city":"Hamilton",
    "sg:classifiers":[
        {
            "category":"Social Services",
            "subcategory":"Job Training",
            "type":"Services"
        }
    ],
    "sg:phone":"+1 905 521 1484",
    "sg:postcode":"L8P 3T9",
    "sg:province":"ON",
    "sg:tags":[
        "rehabilitation"
    ],
    "wof:name":"Hill Program Inc",
    "wof:placetype":"venue"
},
  "geometry": {"coordinates":[-79.8833694458,43.2484016418],"type":"Point"}
}