{
  "type": "Feature",
  "properties": {
    "addr:full":"4892 Hwy 17 Upsala ON P0T 2Y0",
    "addr:housenumber":"4892",
    "addr:postcode":"p0t 2y0",
    "addr:street":"Hwy 17",
    "iso:country":"CA",
    "sg:address":"4892 Hwy 17",
    "sg:city":"Upsala",
    "sg:classifiers":[
        {
            "category":"Shopping",
            "subcategory":"Discount & Variety Stores",
            "type":"Retail Goods"
        }
    ],
    "sg:phone":"+1 807 986 2228",
    "sg:postcode":"P0T 2Y0",
    "sg:province":"ON",
    "sg:tags":[
        "merchandise",
        "general"
    ],
    "wof:name":"General Store",
    "wof:placetype":"venue"
},
  "geometry": {"coordinates":[-90.46900177000001,49.0431098938],"type":"Point"}
}