{
  "type": "Feature",
  "properties": {
    "addr:full":"Brantford ON N3R 6T2",
    "addr:postcode":"n3r 6t2",
    "iso:country":"CA",
    "sg:city":"Brantford",
    "sg:classifiers":[
        {
            "category":"Personal",
            "subcategory":"Tanning Parlor",
            "type":"Services"
        }
    ],
    "sg:phone":"+1 519 757 1266",
    "sg:postcode":"N3R 6T2",
    "sg:province":"ON",
    "sg:tags":[
        "salon"
    ],
    "wof:name":"Tan To Perfection",
    "wof:placetype":"venue"
},
  "geometry": {"coordinates":[-80.2516174316,43.1719741821],"type":"Point"}
}