{
  "type": "Feature",
  "properties": {
    "addr:full":"729 Mill St Calabogie ON K0J 1H0",
    "addr:housenumber":"729",
    "addr:postcode":"k0j 1h0",
    "addr:street":"Mill St",
    "iso:country":"CA",
    "sg:address":"729 Mill St",
    "sg:city":"Calabogie",
    "sg:classifiers":[
        {
            "category":"Travel",
            "subcategory":"Hotels & Motels",
            "type":"Entertainment"
        }
    ],
    "sg:phone":"+1 613 752 2676",
    "sg:postcode":"K0J 1H0",
    "sg:province":"ON",
    "sg:tags":[
        "resort"
    ],
    "wof:name":"Calabogie Lodge",
    "wof:placetype":"venue"
},
  "geometry": {"coordinates":[-76.73323822019999,45.2944259644],"type":"Point"}
}