{
  "type": "Feature",
  "properties": {
    "addr:full":"2 Fourth St Balmertown ON P0V 1C0",
    "addr:housenumber":"2",
    "addr:postcode":"p0v 1c0",
    "addr:street":"Fourth St",
    "iso:country":"CA",
    "sg:address":"2 Fourth St",
    "sg:city":"Balmertown",
    "sg:classifiers":[
        {
            "category":"Organizations",
            "subcategory":"Religious Organization",
            "type":"Services"
        }
    ],
    "sg:phone":"+1 807 735 3239",
    "sg:postcode":"P0V 1C0",
    "sg:province":"ON",
    "sg:tags":[
        "church"
    ],
    "wof:name":"Calvary Baptist Church",
    "wof:placetype":"venue"
},
  "geometry": {"coordinates":[-93.7400970459,51.0598678589],"type":"Point"}
}