{
  "type": "Feature",
  "properties": {
    "addr:full":"697 Wentworth St Nanaimo BC V9R 3E6",
    "addr:housenumber":"697",
    "addr:postcode":"v9r 3e6",
    "addr:street":"Wentworth St",
    "iso:country":"CA",
    "sg:address":"697 Wentworth St",
    "sg:city":"Nanaimo",
    "sg:classifiers":[
        {
            "category":"Health Services",
            "subcategory":"Health Practitioner",
            "type":"Services"
        }
    ],
    "sg:phone":"+1 250 754 2182",
    "sg:postcode":"V9R 3E6",
    "sg:province":"BC",
    "sg:tags":[
        "psychologist"
    ],
    "wof:name":"Penner, Ronald PhD",
    "wof:placetype":"venue"
},
  "geometry": {"coordinates":[-123.945953,49.166496],"type":"Point"}
}