{
  "type": "Feature",
  "properties": {
    "addr:full":"1162 Lakeshore Rd W St Catharines ON L2R 6P9",
    "addr:housenumber":"1162",
    "addr:postcode":"l2r 6p9",
    "addr:street":"Lakeshore Rd W",
    "iso:country":"CA",
    "sg:address":"1162 Lakeshore Rd W",
    "sg:city":"St Catharines",
    "sg:classifiers":[
        {
            "category":"Wholesale",
            "subcategory":"Electrical",
            "type":"Manufacturing & Wholesale Goods"
        }
    ],
    "sg:phone":"+1 905 646 9011",
    "sg:postcode":"L2R 6P9",
    "sg:province":"ON",
    "sg:tags":[
        "alarm",
        "burglar",
        "system"
    ],
    "wof:name":"Base Security Svc",
    "wof:placetype":"venue"
},
  "geometry": {"coordinates":[-79.3039093018,43.1860809326],"type":"Point"}
}