{
  "type": "Feature",
  "properties": {
    "addr:full":"6345 Boul Leger Montreal-Nord QC H1G 1L4",
    "addr:housenumber":"6345",
    "addr:postcode":"h1g 1l4",
    "addr:street":"Boul Leger",
    "iso:country":"CA",
    "sg:address":"6345 Boul Leger",
    "sg:city":"Montreal-Nord",
    "sg:classifiers":[
        {
            "category":"Food & Beverages",
            "subcategory":"Fruits & Vegetables",
            "type":"Retail Goods"
        }
    ],
    "sg:phone":"+1 514 329 2322",
    "sg:postcode":"H1G 1L4",
    "sg:province":"QC",
    "sg:tags":[
        "produce"
    ],
    "wof:name":"Marche-Zamzam",
    "wof:placetype":"venue"
},
  "geometry": {"coordinates":[-73.623664856,45.6226997375],"type":"Point"}
}