{
  "type": "Feature",
  "properties": {
    "iso:country":"CA",
    "sg:address":"208 Main St",
    "sg:city":"Cudworth",
    "sg:classifiers":[
        {
            "category":"Retail",
            "subcategory":"Laundry & Dry Cleaning",
            "type":"Services"
        }
    ],
    "sg:phone":"+1 306 256 7000",
    "sg:postcode":"S0K 1B0",
    "sg:province":"SK",
    "sg:tags":[
        "cleaners"
    ],
    "wof:name":"Cudworth Laundromat & Saw",
    "wof:placetype":"venue"
},
  "geometry": {"coordinates":[-105.733291626,52.4929008484],"type":"Point"}
}