{
  "type": "Feature",
  "properties": {
    "addr:full":"4219 Huron St Niagara Falls ON L2E 2G6",
    "addr:housenumber":"4219",
    "addr:postcode":"l2e 2g6",
    "addr:street":"Huron St",
    "iso:country":"CA",
    "sg:address":"4219 Huron St",
    "sg:city":"Niagara Falls",
    "sg:classifiers":[
        {
            "category":"Travel",
            "subcategory":"Hotels & Motels",
            "type":"Entertainment"
        }
    ],
    "sg:phone":"+1 905 357 4266",
    "sg:postcode":"L2E 2G6",
    "sg:province":"ON",
    "sg:tags":[
        "tourist",
        "accommodation"
    ],
    "wof:name":"Hostel Noagara Falls Backpaker",
    "wof:placetype":"venue"
},
  "geometry": {"coordinates":[-79.061981,43.10577],"type":"Point"}
}