{
  "type": "Feature",
  "properties": {
    "addr:full":"6105 Kestrel Rd Mississauga ON L5T 1Y8",
    "addr:housenumber":"6105",
    "addr:postcode":"l5t 1y8",
    "addr:street":"Kestrel Rd",
    "iso:country":"CA",
    "sg:address":"6105 Kestrel Rd",
    "sg:city":"Mississauga",
    "sg:classifiers":[
        {
            "category":"Wholesale",
            "subcategory":"Machinery & Supplies",
            "type":"Manufacturing & Wholesale Goods"
        }
    ],
    "sg:phone":"+1 905 564 9479",
    "sg:postcode":"L5T 1Y8",
    "sg:province":"ON",
    "sg:tags":[
        "machine",
        "tool"
    ],
    "wof:name":"Heinman Machinery Ltd",
    "wof:placetype":"venue"
},
  "geometry": {"coordinates":[-79.663574,43.646057],"type":"Point"}
}