{
  "type": "Feature",
  "properties": {
    "addr:full":"1600 Queen St E Toronto ON M4L 1G2",
    "addr:housenumber":"1600",
    "addr:postcode":"m4l 1g2",
    "addr:street":"Queen St E",
    "iso:country":"CA",
    "sg:address":"1600 Queen St E",
    "sg:city":"Toronto",
    "sg:classifiers":[
        {
            "category":"Retail",
            "subcategory":"Veterinary Services",
            "type":"Services"
        }
    ],
    "sg:phone":"+1 416 778 4598",
    "sg:postcode":"M4L 1G2",
    "sg:province":"ON",
    "sg:tags":[
        "veterinarian"
    ],
    "wof:name":"Kew Beach Veterinary Hospital",
    "wof:placetype":"venue"
},
  "geometry": {"coordinates":[-79.317291,43.666306],"type":"Point"}
}