{
  "type": "Feature",
  "properties": {
    "iso:country":"CA",
    "sg:address":"1081 Cambie St",
    "sg:city":"Vancouver",
    "sg:classifiers":[
        {
            "category":"Professional",
            "subcategory":"Art Services",
            "type":"Services"
        }
    ],
    "sg:phone":"+1 604 408 4575",
    "sg:postcode":"V6B 5L7",
    "sg:province":"BC",
    "sg:tags":[
        "graphic"
    ],
    "wof:name":"Markings Visual Communications",
    "wof:placetype":"venue"
},
  "geometry": {"coordinates":[-123.119346619,49.2750663757],"type":"Point"}
}