{
  "type": "Feature",
  "properties": {
    "addr:full":"154 James St St Catharines ON L2R 5C5",
    "addr:housenumber":"154",
    "addr:postcode":"l2r 5c5",
    "addr:street":"James St",
    "iso:country":"CA",
    "sg:address":"154 James St",
    "sg:city":"St Catharines",
    "sg:classifiers":[
        {
            "category":"Personal",
            "type":"Services"
        }
    ],
    "sg:phone":"+1 905 984 8330",
    "sg:postcode":"L2R 5C5",
    "sg:province":"ON",
    "sg:tags":[
        "credit",
        "debt",
        "counseling"
    ],
    "wof:name":"Perry Krieger & Assoc Inc",
    "wof:placetype":"venue"
},
  "geometry": {"coordinates":[-79.2489852905,43.1611709595],"type":"Point"}
}