{
  "type": "Feature",
  "properties": {
    "addr:full":"4004 Wesbrook Mall Vancouver BC V6T 2A3",
    "addr:housenumber":"4004",
    "addr:postcode":"v6t 2a3",
    "addr:street":"Wesbrook Mall",
    "iso:country":"CA",
    "sg:address":"4004 Wesbrook Mall",
    "sg:city":"Vancouver",
    "sg:classifiers":[
        {
            "category":"Professional",
            "subcategory":"Research",
            "type":"Services"
        }
    ],
    "sg:phone":"+1 604 222 1047",
    "sg:postcode":"V6T 2A3",
    "sg:province":"BC",
    "sg:tags":[
        "historical"
    ],
    "wof:name":"Triumf",
    "wof:placetype":"venue"
},
  "geometry": {"coordinates":[-123.23214,49.246407],"type":"Point"}
}