{
  "type": "Feature",
  "properties": {
    "addr:full":"8120 Lawson Rd Milton ON L9T 5C4",
    "addr:housenumber":"8120",
    "addr:postcode":"l9t 5c4",
    "addr:street":"Lawson Rd",
    "iso:country":"CA",
    "sg:address":"8120 Lawson Rd",
    "sg:city":"Milton",
    "sg:classifiers":[
        {
            "category":"Manufacturing",
            "subcategory":"Rubber & Plastics",
            "type":"Manufacturing & Wholesale Goods"
        }
    ],
    "sg:phone":"+1 905 878 7890",
    "sg:postcode":"L9T 5C4",
    "sg:province":"ON",
    "sg:tags":[
        "forming"
    ],
    "wof:name":"Custom Vacform Components Inc",
    "wof:placetype":"venue"
},
  "geometry": {"coordinates":[-79.8765335083,43.5464630127],"type":"Point"}
}