{
  "type": "Feature",
  "properties": {
    "addr:full":"Vancouver BC V6H 3R9",
    "addr:postcode":"v6h 3r9",
    "iso:country":"CA",
    "sg:city":"Vancouver",
    "sg:classifiers":[
        {
            "category":"Professional",
            "subcategory":"Management & Consulting",
            "type":"Services"
        }
    ],
    "sg:phone":"+1 604 684 9845",
    "sg:postcode":"V6H 3R9",
    "sg:province":"BC",
    "sg:tags":[
        "consultant",
        "business"
    ],
    "wof:name":"Whistler Lodging CO",
    "wof:placetype":"venue"
},
  "geometry": {"coordinates":[-123.132553,49.270195],"type":"Point"}
}