{
  "type": "Feature",
  "properties": {
    "addr:full":"509 Dickson Dr Fergus ON N1M 2W7",
    "addr:housenumber":"509",
    "addr:postcode":"n1m 2w7",
    "addr:street":"Dickson Dr",
    "iso:country":"CA",
    "sg:address":"509 Dickson Dr",
    "sg:city":"Fergus",
    "sg:classifiers":[
        {
            "category":"Freight",
            "type":"Transportation"
        }
    ],
    "sg:phone":"+1 519 787 1994",
    "sg:postcode":"N1M 2W7",
    "sg:province":"ON",
    "sg:tags":[
        "trucking"
    ],
    "wof:name":"Thistletown Motor Freight",
    "wof:placetype":"venue"
},
  "geometry": {"coordinates":[-80.381157,43.720615],"type":"Point"}
}