{
  "type": "Feature",
  "properties": {
    "addr:full":"229 Charlotte St Ottawa ON K1N 8L1",
    "addr:housenumber":"229",
    "addr:postcode":"k1n 8l1",
    "addr:street":"Charlotte St",
    "iso:country":"CA",
    "sg:address":"229 Charlotte St",
    "sg:city":"Ottawa",
    "sg:classifiers":[
        {
            "category":"Professional",
            "subcategory":"Computer Services",
            "type":"Services"
        }
    ],
    "sg:phone":"+1 613 562 9905",
    "sg:postcode":"K1N 8L1",
    "sg:province":"ON",
    "sg:tags":[
        "consultant"
    ],
    "wof:name":"Mindspan Consultants",
    "wof:placetype":"venue"
},
  "geometry": {"coordinates":[-75.6748428345,45.4313163757],"type":"Point"}
}