{
  "type": "Feature",
  "properties": {
    "addr:full":"Bancroft ON K0L 1C0",
    "addr:postcode":"k0l 1c0",
    "iso:country":"CA",
    "sg:city":"Bancroft",
    "sg:classifiers":[
        {
            "category":"Health Services",
            "subcategory":"Doctor",
            "type":"Services"
        }
    ],
    "sg:phone":"+1 613 332 2626",
    "sg:postcode":"K0L 1C0",
    "sg:province":"ON",
    "sg:tags":[
        "physician",
        "surgeon"
    ],
    "wof:name":"Doren, Denis MD",
    "wof:placetype":"venue"
},
  "geometry": {"coordinates":[-77.8530502319,45.0562858582],"type":"Point"}
}