{
  "type": "Feature",
  "properties": {
    "addr:full":"23930 16 Ave Langley BC V2Z 1L1",
    "addr:housenumber":"23930",
    "addr:postcode":"v2z 1l1",
    "addr:street":"16 Ave",
    "iso:country":"CA",
    "sg:address":"23930 16 Ave",
    "sg:city":"Langley",
    "sg:classifiers":[
        {
            "category":"Home & Garden",
            "subcategory":"Garden Supply",
            "type":"Retail Goods"
        }
    ],
    "sg:phone":"+1 604 534 3448",
    "sg:postcode":"V2Z 1L1",
    "sg:province":"BC",
    "sg:tags":[
        "nurseryman",
        "center"
    ],
    "wof:name":"Kelly's Country Garden Ltd",
    "wof:placetype":"venue"
},
  "geometry": {"coordinates":[-122.562225342,49.0304718018],"type":"Point"}
}