{
  "type": "Feature",
  "properties": {
    "iso:country":"CA",
    "sg:address":"38 George St",
    "sg:city":"New Glasgow",
    "sg:classifiers":[
        {
            "category":"Food & Beverages",
            "subcategory":"Groceries & Convenience Stores",
            "type":"Retail Goods"
        }
    ],
    "sg:phone":"+1 902 755 9777",
    "sg:postcode":"B2H 2K1",
    "sg:province":"NS",
    "sg:tags":[
        "grocer"
    ],
    "wof:name":"Sobeys Inc",
    "wof:placetype":"venue"
},
  "geometry": {"coordinates":[-62.6490631104,45.5900764465],"type":"Point"}
}