{
  "type": "Feature",
  "properties": {
    "addr:full":"111 Main St N Markham ON L3P 1X9",
    "addr:housenumber":"111",
    "addr:postcode":"l3p 1x9",
    "addr:street":"Main St N",
    "iso:country":"CA",
    "sg:address":"111 Main St N",
    "sg:city":"Markham",
    "sg:classifiers":[
        {
            "category":"Professional",
            "subcategory":"Accounting & Tax Preparation",
            "type":"Services"
        }
    ],
    "sg:phone":"+1 905 472 9501",
    "sg:postcode":"L3P 1X9",
    "sg:province":"ON",
    "sg:tags":[
        "return",
        "filing"
    ],
    "wof:name":"H & R Block Canada Inc",
    "wof:placetype":"venue"
},
  "geometry": {"coordinates":[-79.2607803345,43.8778877258],"type":"Point"}
}