{
  "type": "Feature",
  "properties": {
    "addr:full":"6111 Av Du Pont N Alma QC G8E 1X5",
    "addr:housenumber":"6111",
    "addr:postcode":"g8e 1x5",
    "addr:street":"Av Du Pont N",
    "iso:country":"CA",
    "sg:address":"6111 Av Du Pont N",
    "sg:city":"Alma",
    "sg:classifiers":[
        {
            "category":"Home & Garden",
            "subcategory":"Building Materials",
            "type":"Retail Goods"
        }
    ],
    "sg:phone":"+1 418 347 4613",
    "sg:postcode":"G8E 1X5",
    "sg:province":"QC",
    "sg:tags":[
        "glass",
        "door"
    ],
    "wof:name":"Volets Decoratifs Du Lac",
    "wof:placetype":"venue"
},
  "geometry": {"coordinates":[-71.716431,48.636555],"type":"Point"}
}