{
  "type": "Feature",
  "properties": {
    "addr:full":"6 Church St W Delhi ON N4B 1V7",
    "addr:housenumber":"6",
    "addr:postcode":"n4b 1v7",
    "addr:street":"Church St W",
    "iso:country":"CA",
    "sg:address":"6 Church St W",
    "sg:city":"Delhi",
    "sg:classifiers":[
        {
            "category":"Shopping",
            "subcategory":"Gifts & Souvenirs",
            "type":"Retail Goods"
        }
    ],
    "sg:phone":"+1 519 582 8651",
    "sg:postcode":"N4B 1V7",
    "sg:province":"ON",
    "sg:tags":[
        "shop",
        "candle"
    ],
    "wof:name":"Country Home Candle Store",
    "wof:placetype":"venue"
},
  "geometry": {"coordinates":[-80.4940872192,42.8536491394],"type":"Point"}
}