{
  "type": "Feature",
  "properties": {
    "iso:country":"CA",
    "sg:city":"Hamilton",
    "sg:classifiers":[
        {
            "category":"Building & Trades",
            "subcategory":"Construction",
            "type":"Services"
        }
    ],
    "sg:phone":"+1 905 387 0951",
    "sg:postcode":"L8W 2C7",
    "sg:province":"ON",
    "sg:tags":[
        "insulation",
        "heat",
        "contractor"
    ],
    "wof:name":"Ken Mason Insulation",
    "wof:placetype":"venue"
},
  "geometry": {"coordinates":[-79.8359451294,43.197971344],"type":"Point"}
}