{
  "type": "Feature",
  "properties": {
    "addr:full":"3100 Steeles Ave E Markham ON L3R 8T3",
    "addr:housenumber":"3100",
    "addr:postcode":"l3r 8t3",
    "addr:street":"Steeles Ave E",
    "iso:country":"CA",
    "sg:address":"3100 Steeles Ave E",
    "sg:city":"Markham",
    "sg:classifiers":[
        {
            "category":"Shopping",
            "subcategory":"Computers & Home Electronics",
            "type":"Retail Goods"
        }
    ],
    "sg:phone":"+1 905 948 1709",
    "sg:postcode":"L3R 8T3",
    "sg:province":"ON",
    "sg:tags":[
        "software"
    ],
    "wof:name":"Smartsales Inc",
    "wof:placetype":"venue"
},
  "geometry": {"coordinates":[-79.34646606450001,43.8145675659],"type":"Point"}
}