{
  "type": "Feature",
  "properties": {
    "iso:country":"CA",
    "sg:address":"1225 Government St",
    "sg:city":"Victoria",
    "sg:classifiers":[
        {
            "category":"Manufacturing",
            "subcategory":"Food",
            "type":"Manufacturing & Wholesale Goods"
        }
    ],
    "sg:phone":"+1 250 382 8811",
    "sg:postcode":"V8W 1Y6",
    "sg:province":"BC",
    "sg:tags":[
        "cocoa",
        "chocolate"
    ],
    "wof:name":"Rocky Mountain Chocolate Fctry",
    "wof:placetype":"venue"
},
  "geometry": {"coordinates":[-123.367546081,48.42603302],"type":"Point"}
}