{
  "type": "Feature",
  "properties": {
    "addr:full":"1104 Davie St Vancouver BC V6E 1N1",
    "addr:housenumber":"1104",
    "addr:postcode":"v6e 1n1",
    "addr:street":"Davie St",
    "iso:country":"CA",
    "sg:address":"1104 Davie St",
    "sg:city":"Vancouver",
    "sg:classifiers":[
        {
            "category":"Professional",
            "subcategory":"Computer Services",
            "type":"Services"
        }
    ],
    "sg:phone":"+1 604 682 6668",
    "sg:postcode":"V6E 1N1",
    "sg:province":"BC",
    "sg:tags":[
        "internet"
    ],
    "wof:name":"Internet Coffee",
    "wof:placetype":"venue"
},
  "geometry": {"coordinates":[-123.13166,49.280499],"type":"Point"}
}