{
  "type": "Feature",
  "properties": {
    "iso:country":"CA",
    "sg:address":"1104 Davie St",
    "sg:city":"Vancouver",
    "sg:classifiers":[
        {
            "category":"Professional",
            "subcategory":"Computer Services",
            "type":"Services"
        }
    ],
    "sg:phone":"+1 604 682 6668",
    "sg:postcode":"V6E 1N1",
    "sg:province":"BC",
    "sg:tags":[
        "internet"
    ],
    "wof:name":"Internet Coffee",
    "wof:placetype":"venue"
},
  "geometry": {"coordinates":[-123.13166,49.280499],"type":"Point"}
}