{
  "type": "Feature",
  "properties": {
    "addr:full":"90 Arthur Creak Dr Winnipeg MB R2Y 2E2",
    "addr:housenumber":"90",
    "addr:postcode":"r2y 2e2",
    "addr:street":"Arthur Creak Dr",
    "iso:country":"CA",
    "sg:address":"90 Arthur Creak Dr",
    "sg:city":"Winnipeg",
    "sg:classifiers":[
        {
            "category":"Wholesale",
            "subcategory":"Durable Goods & Equipment",
            "type":"Manufacturing & Wholesale Goods"
        }
    ],
    "sg:phone":"+1 204 885 9304",
    "sg:postcode":"R2Y 2E2",
    "sg:province":"MB",
    "sg:tags":[
        "representative",
        "manufacturer"
    ],
    "wof:name":"R K Mc Comb & Assoc",
    "wof:placetype":"venue"
},
  "geometry": {"coordinates":[-97.2904434204,49.8977622986],"type":"Point"}
}