{
  "type": "Feature",
  "properties": {
    "addr:full":"Sherwood Park AB T8A 4W2",
    "addr:postcode":"t8a 4w2",
    "iso:country":"CA",
    "sg:city":"Sherwood Park",
    "sg:classifiers":[
        {
            "category":"Shopping",
            "type":"Retail Goods"
        }
    ],
    "sg:phone":"+1 780 464 1228",
    "sg:postcode":"T8A 4W2",
    "sg:province":"AB",
    "sg:tags":[
        "pet",
        "food",
        "supply"
    ],
    "wof:name":"Pookey's Pet Food & Supplies",
    "wof:placetype":"venue"
},
  "geometry": {"coordinates":[-113.290215,53.528553],"type":"Point"}
}