{
  "type": "Feature",
  "properties": {
    "iso:country":"CA",
    "sg:address":"2010 Commercial Dr",
    "sg:city":"Vancouver",
    "sg:classifiers":[
        {
            "category":"Shopping",
            "subcategory":"Used Merchandise",
            "type":"Retail Goods"
        }
    ],
    "sg:phone":"+1 604 254 5520",
    "sg:postcode":"V5N 4A9",
    "sg:province":"BC",
    "sg:tags":[
        "book",
        "rare",
        "dealer"
    ],
    "wof:name":"Bibliophile Book Shop",
    "wof:placetype":"venue"
},
  "geometry": {"coordinates":[-123.069648743,49.2670173645],"type":"Point"}
}