{
  "type": "Feature",
  "properties": {
    "iso:country":"CA",
    "sg:address":"43 Hall St",
    "sg:city":"Gore Bay",
    "sg:classifiers":[
        {
            "category":"Education",
            "subcategory":"School",
            "type":"Public Place"
        }
    ],
    "sg:phone":"+1 705 282 2383",
    "sg:postcode":"P0P 1H0",
    "sg:province":"ON",
    "wof:name":"Charles C Mclean Public Schl",
    "wof:placetype":"venue"
},
  "geometry": {"coordinates":[-82.46472199999999,45.911564],"type":"Point"}
}