{
  "type": "Feature",
  "properties": {
    "addr:full":"7859 50 Ave # 3 Red Deer AB T4P 1M8",
    "addr:housenumber":"7859",
    "addr:postcode":"t4p 1m8",
    "addr:street":"50 Ave # 3",
    "iso:country":"CA",
    "sg:address":"7859 50 Ave # 3",
    "sg:city":"Red Deer",
    "sg:classifiers":[
        {
            "category":"Home & Garden",
            "subcategory":"Building Materials",
            "type":"Retail Goods"
        }
    ],
    "sg:phone":"+1 403 346 7737",
    "sg:postcode":"T4P 1M8",
    "sg:province":"AB",
    "sg:tags":[
        "glass",
        "window",
        "plate"
    ],
    "wof:name":"Standard Auto Glass",
    "wof:placetype":"venue"
},
  "geometry": {"coordinates":[-113.81353799999999,52.309799],"type":"Point"}
}