{
  "type": "Feature",
  "properties": {
    "addr:full":"411 New York Central Ave Embrun ON K0A 1W1",
    "addr:housenumber":"411",
    "addr:postcode":"k0a 1w1",
    "addr:street":"New York Central Ave",
    "iso:country":"CA",
    "sg:address":"411 New York Central Ave",
    "sg:city":"Embrun",
    "sg:classifiers":[
        {
            "category":"Government",
            "subcategory":"Police Station",
            "type":"Public Place"
        }
    ],
    "sg:phone":"+1 613 443 4499",
    "sg:postcode":"K0A 1W1",
    "sg:province":"ON",
    "sg:tags":[
        "department"
    ],
    "wof:name":"Russell County Police Dept",
    "wof:placetype":"venue"
},
  "geometry": {"coordinates":[-75.304108,45.270618],"type":"Point"}
}