{
  "type": "Feature",
  "properties": {
    "addr:full":"280 Burns Ave Southey SK S0G 4P0",
    "addr:housenumber":"280",
    "addr:postcode":"s0g 4p0",
    "addr:street":"Burns Ave",
    "iso:country":"CA",
    "sg:address":"280 Burns Ave",
    "sg:city":"Southey",
    "sg:classifiers":[
        {
            "category":"Education",
            "subcategory":"School",
            "type":"Public Place"
        }
    ],
    "sg:phone":"+1 306 726 5885",
    "sg:postcode":"S0G 4P0",
    "sg:province":"SK",
    "wof:name":"Carlton Trail Regional College",
    "wof:placetype":"venue"
},
  "geometry": {"coordinates":[-104.49850499999999,50.942989],"type":"Point"}
}