{
  "type": "Feature",
  "properties": {
    "addr:full":"5915 Rue DE Jumonville Montreal QC H1M 1R2",
    "addr:housenumber":"5915",
    "addr:postcode":"h1m 1r2",
    "addr:street":"Rue De Jumonville",
    "iso:country":"CA",
    "sg:address":"5915 Rue DE Jumonville",
    "sg:city":"Montreal",
    "sg:classifiers":[
        {
            "category":"Professional",
            "subcategory":"Accounting & Tax Preparation",
            "type":"Services"
        }
    ],
    "sg:phone":"+1 514 254 3141",
    "sg:postcode":"H1M 1R2",
    "sg:province":"QC",
    "sg:tags":[
        "notary",
        "accountant"
    ],
    "wof:name":"Chapman & Chapman",
    "wof:placetype":"venue"
},
  "geometry": {"coordinates":[-73.5506057739,45.5770263672],"type":"Point"}
}