{
  "type": "Feature",
  "properties": {
    "addr:full":"Napierville QC J0J 1L0",
    "addr:postcode":"j0j 1l0",
    "iso:country":"CA",
    "sg:city":"Napierville",
    "sg:classifiers":[
        {
            "category":"Autos & Motor Vehicles",
            "subcategory":"Motorcycle Sales",
            "type":"Retail Goods"
        }
    ],
    "sg:phone":"+1 450 245 3663",
    "sg:postcode":"J0J 1L0",
    "sg:province":"QC",
    "sg:tags":[
        "scooter"
    ],
    "wof:name":"Varin Yamaha",
    "wof:placetype":"venue"
},
  "geometry": {"coordinates":[-73.40239699999999,45.184044],"type":"Point"}
}