{
  "type": "Feature",
  "properties": {
    "addr:full":"333 Confederation Pky Concord ON L4K 4S1",
    "addr:housenumber":"333",
    "addr:postcode":"l4k 4s1",
    "addr:street":"Confederation Pky",
    "iso:country":"CA",
    "sg:address":"333 Confederation Pky",
    "sg:city":"Concord",
    "sg:classifiers":[
        {
            "category":"Wholesale",
            "subcategory":"Sporting Goods",
            "type":"Manufacturing & Wholesale Goods"
        }
    ],
    "sg:phone":"+1 905 738 4777",
    "sg:postcode":"L4K 4S1",
    "sg:province":"ON",
    "sg:tags":[
        "equipment",
        "camping"
    ],
    "wof:name":"World Famous Sales of Canada",
    "wof:placetype":"venue"
},
  "geometry": {"coordinates":[-79.489555,43.830147],"type":"Point"}
}