{
  "type": "Feature",
  "properties": {
    "addr:full":"2045 Mayor Magrath Dr S # 107 Lethbridge AB T1K 2S2",
    "addr:postcode":"2045;t1k 2s2",
    "addr:street":"Mayor Magrath Dr S # 107",
    "iso:country":"CA",
    "sg:address":"2045 Mayor Magrath Dr S # 107",
    "sg:city":"Lethbridge",
    "sg:classifiers":[
        {
            "category":"Shopping",
            "subcategory":"Books",
            "type":"Retail Goods"
        }
    ],
    "sg:phone":"+1 403 328 4010",
    "sg:postcode":"T1K 2S2",
    "sg:province":"AB",
    "sg:tags":[
        "dealer"
    ],
    "wof:name":"Oliver's Lds Book Ctr",
    "wof:placetype":"venue"
},
  "geometry": {"coordinates":[-112.7993927,49.6721916199],"type":"Point"}
}