{
  "type": "Feature",
  "properties": {
    "addr:full":"745 Marshall Rd Dunnville ON N1A 2W8",
    "addr:housenumber":"745",
    "addr:postcode":"n1a 2w8",
    "addr:street":"Marshall Rd",
    "iso:country":"CA",
    "sg:address":"745 Marshall Rd",
    "sg:city":"Dunnville",
    "sg:classifiers":[
        {
            "category":"Building & Trades",
            "subcategory":"Construction",
            "type":"Services"
        }
    ],
    "sg:phone":"+1 905 774 6888",
    "sg:postcode":"N1A 2W8",
    "sg:province":"ON",
    "sg:tags":[
        "contractor"
    ],
    "wof:name":"Aldor Construction",
    "wof:placetype":"venue"
},
  "geometry": {"coordinates":[-79.64537,42.891201],"type":"Point"}
}