{
  "type": "Feature",
  "properties": {
    "addr:full":"Saskatoon SK S7N 2T6",
    "addr:postcode":"s7n 2t6",
    "iso:country":"CA",
    "sg:city":"Saskatoon",
    "sg:classifiers":[
        {
            "category":"Real Estate",
            "subcategory":"Real Estate Operator",
            "type":"Services"
        }
    ],
    "sg:phone":"+1 306 343 3983",
    "sg:postcode":"S7N 2T6",
    "sg:province":"SK",
    "sg:tags":[
        "apartment"
    ],
    "wof:name":"Penthouse Apartments",
    "wof:placetype":"venue"
},
  "geometry": {"coordinates":[-106.667251587,52.1176567078],"type":"Point"}
}