{
  "type": "Feature",
  "properties": {
    "addr:full":"7 Glebemount Ave Toronto ON M4C 3R2",
    "addr:housenumber":"7",
    "addr:postcode":"m4c 3r2",
    "addr:street":"Glebemount Ave",
    "iso:country":"CA",
    "sg:address":"7 Glebemount Ave",
    "sg:city":"Toronto",
    "sg:classifiers":[
        {
            "category":"Retail",
            "subcategory":"Repair Shop",
            "type":"Services"
        }
    ],
    "sg:phone":"+1 416 421 4153",
    "sg:postcode":"M4C 3R2",
    "sg:province":"ON",
    "sg:tags":[
        "instrument",
        "musical"
    ],
    "wof:name":"Dowd Musical Instruments Inc",
    "wof:placetype":"venue"
},
  "geometry": {"coordinates":[-79.317566,43.684891],"type":"Point"}
}