{
  "type": "Feature",
  "properties": {
    "addr:full":"103 Centennial Dr Windsor NS B0N 2T0",
    "addr:housenumber":"103",
    "addr:postcode":"b0n 2t0",
    "addr:street":"Centennial Dr",
    "iso:country":"CA",
    "sg:address":"103 Centennial Dr",
    "sg:city":"Windsor",
    "sg:classifiers":[
        {
            "category":"Autos & Motor Vehicles",
            "subcategory":"Auto Supplies",
            "type":"Retail Goods"
        }
    ],
    "sg:phone":"+1 902 798 9551",
    "sg:postcode":"B0N 2T0",
    "sg:province":"NS",
    "sg:tags":[
        "tire"
    ],
    "wof:name":"Miller Tire Svc Ltd",
    "wof:placetype":"venue"
},
  "geometry": {"coordinates":[-64.12365,44.993011],"type":"Point"}
}