{
  "type": "Feature",
  "properties": {
    "addr:full":"5647 Alta Vista Dr Ottawa ON K1V 7T5",
    "addr:housenumber":"5647",
    "addr:postcode":"k1v 7t5",
    "addr:street":"Alta Vista Dr",
    "iso:country":"CA",
    "sg:address":"5647 Alta Vista Dr",
    "sg:city":"Ottawa",
    "sg:classifiers":[
        {
            "category":"Food & Beverages",
            "subcategory":"Groceries & Convenience Stores",
            "type":"Retail Goods"
        }
    ],
    "sg:phone":"+1 613 521 5603",
    "sg:postcode":"K1V 7T5",
    "sg:province":"ON",
    "wof:name":"Jack's Place",
    "wof:placetype":"venue"
},
  "geometry": {"coordinates":[-75.66175800000001,45.39901],"type":"Point"}
}