{
  "type": "Feature",
  "properties": {
    "iso:country":"CA",
    "sg:address":"PO Box 160",
    "sg:city":"Marwayne",
    "sg:classifiers":[
        {
            "category":"Food & Beverages",
            "subcategory":"Groceries & Convenience Stores",
            "type":"Retail Goods"
        }
    ],
    "sg:phone":"+1 780 847 2103",
    "sg:postcode":"T0B 2X0",
    "sg:province":"AB",
    "sg:tags":[
        "grocer"
    ],
    "wof:name":"Onion Lake Makaoo Mall Store",
    "wof:placetype":"venue"
},
  "geometry": {"coordinates":[-110.332214355,53.5189781189],"type":"Point"}
}