{
  "type": "Feature",
  "properties": {
    "addr:full":"1750 Innes Rd Gloucester ON K1B 3K5",
    "addr:housenumber":"1750",
    "addr:postcode":"k1b 3k5",
    "addr:street":"Innes Rd",
    "iso:country":"CA",
    "sg:address":"1750 Innes Rd",
    "sg:city":"Gloucester",
    "sg:classifiers":[
        {
            "category":"Shopping",
            "subcategory":"Shoes",
            "type":"Retail Goods"
        }
    ],
    "sg:phone":"+1 613 747 0006",
    "sg:postcode":"K1B 3K5",
    "sg:province":"ON",
    "wof:name":"Shoe CO",
    "wof:placetype":"venue"
},
  "geometry": {"coordinates":[-75.6011810303,45.4168052673],"type":"Point"}
}