{
  "type": "Feature",
  "properties": {
    "iso:country":"CA",
    "sg:address":"1105 Wellington Rd",
    "sg:city":"London",
    "sg:classifiers":[
        {
            "category":"Shopping",
            "subcategory":"Gifts & Souvenirs",
            "type":"Retail Goods"
        }
    ],
    "sg:phone":"+1 519 681 3241",
    "sg:postcode":"N6E 1V4",
    "sg:province":"ON",
    "sg:tags":[
        "shop"
    ],
    "wof:name":"Brandy Tree Shoppes Inc",
    "wof:placetype":"venue"
},
  "geometry": {"coordinates":[-81.2216415405,42.9316215515],"type":"Point"}
}