{
  "type": "Feature",
  "properties": {
    "addr:full":"351 Select Dr Kingston ON K7M 8R1",
    "addr:housenumber":"351",
    "addr:postcode":"k7m 8r1",
    "addr:street":"Select Dr",
    "iso:country":"CA",
    "sg:address":"351 Select Dr",
    "sg:city":"Kingston",
    "sg:classifiers":[
        {
            "category":"Home & Garden",
            "subcategory":"Furniture",
            "type":"Retail Goods"
        }
    ],
    "sg:phone":"+1 613 549 5135",
    "sg:postcode":"K7M 8R1",
    "sg:province":"ON",
    "wof:name":"United Furniture Warehouse Lp",
    "wof:placetype":"venue"
},
  "geometry": {"coordinates":[-76.554436,44.25687],"type":"Point"}
}