{
  "type": "Feature",
  "properties": {
    "iso:country":"CA",
    "sg:city":"Westbank",
    "sg:classifiers":[
        {
            "category":"Wholesale",
            "subcategory":"Seafood",
            "type":"Manufacturing & Wholesale Goods"
        }
    ],
    "sg:phone":"+1 250 768 6977",
    "sg:postcode":"V4T 1X6",
    "sg:province":"BC",
    "wof:name":"Little Miss Chief Gourmet Prod",
    "wof:placetype":"venue"
},
  "geometry": {"coordinates":[-119.612991333,49.8441047668],"type":"Point"}
}