{
  "type": "Feature",
  "properties": {
    "addr:full":"50 Wingen Lane Tofino BC V0R 2Z0",
    "addr:housenumber":"50",
    "addr:postcode":"v0r 2z0",
    "addr:street":"Wingen Lane",
    "iso:country":"CA",
    "sg:address":"50 Wingen Lane",
    "sg:city":"Tofino",
    "sg:classifiers":[
        {
            "category":"Airline",
            "type":"Transportation"
        }
    ],
    "sg:phone":"+1 250 725 2205",
    "sg:postcode":"V0R 2Z0",
    "sg:province":"BC",
    "sg:tags":[
        "aircraft",
        "rental",
        "charter",
        "leasing",
        "company"
    ],
    "wof:name":"Atleo River Air Svc Ltd",
    "wof:placetype":"venue"
},
  "geometry": {"coordinates":[-125.90351099999999,49.152538],"type":"Point"}
}