{
  "type": "Feature",
  "properties": {
    "addr:full":"450 Boul Saint-Joseph E Montreal QC H2J 1J7",
    "addr:housenumber":"450",
    "addr:postcode":"h2j 1j7",
    "addr:street":"Boul Saint-Joseph E",
    "iso:country":"CA",
    "sg:address":"450 Boul Saint-Joseph E",
    "sg:city":"Montreal",
    "sg:classifiers":[
        {
            "category":"Professional",
            "subcategory":"Advertising",
            "type":"Services"
        }
    ],
    "sg:phone":"+1 514 288 8850",
    "sg:postcode":"H2J 1J7",
    "sg:province":"QC",
    "sg:tags":[
        "counselor"
    ],
    "wof:name":"Despins Communication Inc",
    "wof:placetype":"venue"
},
  "geometry": {"coordinates":[-73.5871505737,45.5268096924],"type":"Point"}
}