{
  "type": "Feature",
  "properties": {
    "addr:full":"Vancouver BC V6P 4Z4",
    "addr:postcode":"v6p 4z4",
    "iso:country":"CA",
    "sg:city":"Vancouver",
    "sg:classifiers":[
        {
            "category":"Building & Trades",
            "subcategory":"Construction",
            "type":"Services"
        }
    ],
    "sg:phone":"+1 604 267 1328",
    "sg:postcode":"V6P 4Z4",
    "sg:province":"BC",
    "sg:tags":[
        "general",
        "contractor"
    ],
    "wof:name":"Renaissance Developments Corp",
    "wof:placetype":"venue"
},
  "geometry": {"coordinates":[-123.140182,49.21191],"type":"Point"}
}