{
  "type": "Feature",
  "properties": {
    "addr:full":"136167 Conc 8 Desboro ON N0H 1K0",
    "addr:housenumber":"136167;8",
    "addr:postcode":"n0h 1k0",
    "addr:street":"Conc",
    "iso:country":"CA",
    "sg:address":"136167 Conc 8",
    "sg:city":"Desboro",
    "sg:classifiers":[
        {
            "category":"Organizations",
            "subcategory":"Religious Organization",
            "type":"Services"
        }
    ],
    "sg:phone":"+1 519 794 3795",
    "sg:postcode":"N0H 1K0",
    "sg:province":"ON",
    "sg:tags":[
        "church"
    ],
    "wof:name":"Faith Lutheran Church",
    "wof:placetype":"venue"
},
  "geometry": {"coordinates":[-80.98904400000001,44.394432],"type":"Point"}
}