{
  "type": "Feature",
  "properties": {
    "addr:full":"740 5th Ave E Owen Sound ON N4K 2R6",
    "addr:housenumber":"740",
    "addr:postcode":"n4k 2r6",
    "addr:street":"5Th Ave E",
    "iso:country":"CA",
    "sg:address":"740 5th Ave E",
    "sg:city":"Owen Sound",
    "sg:classifiers":[
        {
            "category":"Personal",
            "type":"Services"
        }
    ],
    "sg:phone":"+1 519 372 2505",
    "sg:postcode":"N4K 2R6",
    "sg:province":"ON",
    "sg:tags":[
        "therapist",
        "massage"
    ],
    "wof:name":"Hasstins, Heather",
    "wof:placetype":"venue"
},
  "geometry": {"coordinates":[-80.9368057251,44.5634536743],"type":"Point"}
}