{
  "type": "Feature",
  "properties": {
    "addr:full":"501 Prince St Hudson Bay SK S0E 0Y0",
    "addr:housenumber":"501",
    "addr:postcode":"s0e 0y0",
    "addr:street":"Prince St",
    "iso:country":"CA",
    "sg:address":"501 Prince St",
    "sg:city":"Hudson Bay",
    "sg:classifiers":[
        {
            "category":"Government",
            "subcategory":"Office",
            "type":"Public Place"
        }
    ],
    "sg:phone":"+1 306 865 4400",
    "sg:postcode":"S0E 0Y0",
    "sg:province":"SK",
    "wof:name":"SK Environment & Resource",
    "wof:placetype":"venue"
},
  "geometry": {"coordinates":[-102.38819100000001,52.857414],"type":"Point"}
}