{
  "type": "Feature",
  "properties": {
    "addr:full":"1850 1st St N Brandon MB R7C 1A9",
    "addr:housenumber":"1850",
    "addr:postcode":"r7c 1a9",
    "addr:street":"1St St N",
    "iso:country":"CA",
    "sg:address":"1850 1st St N",
    "sg:city":"Brandon",
    "sg:classifiers":[
        {
            "category":"Restaurant",
            "type":"Food & Drink"
        }
    ],
    "sg:phone":"+1 204 725 1200",
    "sg:postcode":"R7C 1A9",
    "sg:province":"MB",
    "wof:name":"Beef & Barrel Restaurant",
    "wof:placetype":"venue"
},
  "geometry": {"coordinates":[-99.939255,49.880802],"type":"Point"}
}