{
  "type": "Feature",
  "properties": {
    "addr:full":"218 Martin St Penticton BC V2A 5K3",
    "addr:housenumber":"218",
    "addr:postcode":"v2a 5k3",
    "addr:street":"Martin St",
    "iso:country":"CA",
    "sg:address":"218 Martin St",
    "sg:city":"Penticton",
    "sg:classifiers":[
        {
            "category":"Bars & Pubs",
            "type":"Food & Drink"
        }
    ],
    "sg:phone":"+1 250 493 1819",
    "sg:postcode":"V2A 5K3",
    "sg:province":"BC",
    "sg:tags":[
        "club",
        "night"
    ],
    "wof:name":"Blue Mule Night Club",
    "wof:placetype":"venue"
},
  "geometry": {"coordinates":[-119.594048,49.499798],"type":"Point"}
}