{
  "type": "Feature",
  "properties": {
    "iso:country":"CA",
    "sg:address":"1401 Comox St",
    "sg:city":"Vancouver",
    "sg:classifiers":[
        {
            "category":"Organizations",
            "subcategory":"Religious Organization",
            "type":"Services"
        }
    ],
    "sg:phone":"+1 604 685 9726",
    "sg:postcode":"V6G 1N9",
    "sg:province":"BC",
    "sg:tags":[
        "church"
    ],
    "wof:name":"St Johns United Church-Canada",
    "wof:placetype":"venue"
},
  "geometry": {"coordinates":[-123.134269714,49.2852478027],"type":"Point"}
}