{
  "type": "Feature",
  "properties": {
    "addr:full":"43 Millpark Way SW Calgary AB T2Y 2N1",
    "addr:housenumber":"43",
    "addr:postcode":"t2y 2n1",
    "addr:street":"Millpark Way Sw",
    "iso:country":"CA",
    "sg:address":"43 Millpark Way SW",
    "sg:city":"Calgary",
    "sg:classifiers":[
        {
            "category":"Building & Trades",
            "subcategory":"Electrical",
            "type":"Services"
        }
    ],
    "sg:phone":"+1 403 254 2616",
    "sg:postcode":"T2Y 2N1",
    "sg:province":"AB",
    "sg:tags":[
        "electric",
        "contractor"
    ],
    "wof:name":"Doug's Service Electric",
    "wof:placetype":"venue"
},
  "geometry": {"coordinates":[-114.083504,50.918858],"type":"Point"}
}