{
  "type": "Feature",
  "properties": {
    "addr:full":"17235 Old Yonge St Newmarket ON L3Y 4V8",
    "addr:housenumber":"17235",
    "addr:postcode":"l3y 4v8",
    "addr:street":"Old Yonge St",
    "iso:country":"CA",
    "sg:address":"17235 Old Yonge St",
    "sg:city":"Newmarket",
    "sg:classifiers":[
        {
            "category":"Home & Garden",
            "subcategory":"Garden Supply",
            "type":"Retail Goods"
        }
    ],
    "sg:phone":"+1 905 895 9727",
    "sg:postcode":"L3Y 4V8",
    "sg:province":"ON",
    "sg:tags":[
        "sand",
        "gravel",
        "nurseryman"
    ],
    "wof:name":"Holland Valley Nursery",
    "wof:placetype":"venue"
},
  "geometry": {"coordinates":[-79.4786224365,44.0482406616],"type":"Point"}
}