{
  "type": "Feature",
  "properties": {
    "addr:full":"122 Railway Ave NW Falher AB T0H 1M0",
    "addr:housenumber":"122",
    "addr:postcode":"t0h 1m0",
    "addr:street":"Railway Ave Nw",
    "iso:country":"CA",
    "sg:address":"122 Railway Ave NW",
    "sg:city":"Falher",
    "sg:classifiers":[
        {
            "category":"Wholesale",
            "subcategory":"Machinery & Supplies",
            "type":"Manufacturing & Wholesale Goods"
        }
    ],
    "sg:phone":"+1 780 837 4691",
    "sg:postcode":"T0H 1M0",
    "sg:province":"AB",
    "sg:tags":[
        "farm",
        "equipment"
    ],
    "wof:name":"Houlder Farm Supply",
    "wof:placetype":"venue"
},
  "geometry": {"coordinates":[-117.19843292199999,55.7391700745],"type":"Point"}
}