{
  "type": "Feature",
  "properties": {
    "addr:full":"2549 Baseline Rd Ottawa ON K2H 7B3",
    "addr:housenumber":"2549",
    "addr:postcode":"k2h 7b3",
    "addr:street":"Baseline Rd",
    "iso:country":"CA",
    "sg:address":"2549 Baseline Rd",
    "sg:city":"Ottawa",
    "sg:classifiers":[
        {
            "category":"Personal",
            "subcategory":"Beauty Salon",
            "type":"Services"
        }
    ],
    "sg:phone":"+1 613 820 0128",
    "sg:postcode":"K2H 7B3",
    "sg:province":"ON",
    "wof:name":"David's Hair Design",
    "wof:placetype":"venue"
},
  "geometry": {"coordinates":[-75.786446,45.341846],"type":"Point"}
}