{
  "type": "Feature",
  "properties": {
    "iso:country":"CA",
    "sg:city":"Ottawa",
    "sg:classifiers":[
        {
            "category":"Building & Trades",
            "subcategory":"Construction",
            "type":"Services"
        }
    ],
    "sg:phone":"+1 613 747 5013",
    "sg:postcode":"K1K 4L3",
    "sg:province":"ON",
    "sg:tags":[
        "general",
        "contractor"
    ],
    "wof:name":"Current Construction",
    "wof:placetype":"venue"
},
  "geometry": {"coordinates":[-75.630569458,45.4462127686],"type":"Point"}
}