{
  "type": "Feature",
  "properties": {
    "addr:full":"800 Rue Saint-Alphonse Lac-Aux-Sables QC G0X 1M0",
    "addr:housenumber":"800",
    "addr:postcode":"g0x 1m0",
    "addr:street":"Rue Saint-Alphonse",
    "iso:country":"CA",
    "sg:address":"800 Rue Saint-Alphonse",
    "sg:city":"Lac-Aux-Sables",
    "sg:classifiers":[
        {
            "category":"Health Services",
            "subcategory":"Nursing And Care Facility",
            "type":"Services"
        }
    ],
    "sg:phone":"+1 418 336 2092",
    "sg:postcode":"G0X 1M0",
    "sg:province":"QC",
    "sg:tags":[
        "home",
        "retirement",
        "community"
    ],
    "wof:name":"Villa Des Sablois Inc",
    "wof:placetype":"venue"
},
  "geometry": {"coordinates":[-72.4006652832,46.8592338562],"type":"Point"}
}