{
  "type": "Feature",
  "properties": {
    "addr:full":"1908 Queensway Prince George BC V2L 1M2",
    "addr:housenumber":"1908",
    "addr:postcode":"v2l 1m2",
    "addr:street":"Queensway",
    "iso:country":"CA",
    "sg:address":"1908 Queensway",
    "sg:city":"Prince George",
    "sg:classifiers":[
        {
            "category":"Retail",
            "subcategory":"Funeral Services",
            "type":"Services"
        }
    ],
    "sg:phone":"+1 250 564 4431",
    "sg:postcode":"V2L 1M2",
    "sg:province":"BC",
    "sg:tags":[
        "director"
    ],
    "wof:name":"Assman's Funeral Chapel Ltd",
    "wof:placetype":"venue"
},
  "geometry": {"coordinates":[-122.74207305900001,53.9062805176],"type":"Point"}
}