{
  "type": "Feature",
  "properties": {
    "addr:full":"235 King St W Chatham ON N7M 1E6",
    "addr:housenumber":"235",
    "addr:postcode":"n7m 1e6",
    "addr:street":"King St W",
    "iso:country":"CA",
    "sg:address":"235 King St W",
    "sg:city":"Chatham",
    "sg:classifiers":[
        {
            "category":"Organizations",
            "subcategory":"Professional Association",
            "type":"Services"
        }
    ],
    "sg:phone":"+1 519 352 7540",
    "sg:postcode":"N7M 1E6",
    "sg:province":"ON",
    "wof:name":"Chatham & Dist Chamber of Comm",
    "wof:placetype":"venue"
},
  "geometry": {"coordinates":[-82.188965,42.405361],"type":"Point"}
}