{
  "type": "Feature",
  "properties": {
    "addr:full":"1610 Dunbar Rd Cambridge ON N1R 8J5",
    "addr:housenumber":"1610",
    "addr:postcode":"n1r 8j5",
    "addr:street":"Dunbar Rd",
    "iso:country":"CA",
    "sg:address":"1610 Dunbar Rd",
    "sg:city":"Cambridge",
    "sg:classifiers":[
        {
            "category":"Recreation",
            "type":"Entertainment"
        }
    ],
    "sg:phone":"+1 519 621 6020",
    "sg:postcode":"N1R 8J5",
    "sg:province":"ON",
    "sg:tags":[
        "hall",
        "auditorium"
    ],
    "wof:name":"Galt Curling Club",
    "wof:placetype":"venue"
},
  "geometry": {"coordinates":[-80.31428527830001,43.3914489746],"type":"Point"}
}