{
  "type": "Feature",
  "properties": {
    "addr:full":"50 Anderson Ave # 1 Markham ON L6E 1A6",
    "addr:housenumber":"50",
    "addr:postcode":"l6e 1a6",
    "addr:street":"Anderson Ave # 1",
    "iso:country":"CA",
    "sg:address":"50 Anderson Ave # 1",
    "sg:city":"Markham",
    "sg:classifiers":[
        {
            "category":"Home & Garden",
            "subcategory":"Garden Supply",
            "type":"Retail Goods"
        }
    ],
    "sg:phone":"+1 905 294 2644",
    "sg:postcode":"L6E 1A6",
    "sg:province":"ON",
    "sg:tags":[
        "engine",
        "lawn",
        "mower"
    ],
    "wof:name":"Markham Mower",
    "wof:placetype":"venue"
},
  "geometry": {"coordinates":[-79.26457977290001,43.9018936157],"type":"Point"}
}