{
  "type": "Feature",
  "properties": {
    "iso:country":"CA",
    "sg:address":"184 York St",
    "sg:city":"London",
    "sg:classifiers":[
        {
            "category":"Organizations",
            "subcategory":"Professional Association",
            "type":"Services"
        }
    ],
    "sg:phone":"+1 519 434 9149",
    "sg:postcode":"N6A 1B5",
    "sg:province":"ON",
    "sg:tags":[
        "club"
    ],
    "wof:name":"Indian Friendship Ctr",
    "wof:placetype":"venue"
},
  "geometry": {"coordinates":[-81.247795,42.981632],"type":"Point"}
}