{
  "type": "Feature",
  "properties": {
    "addr:full":"271 Granville Bridgetown NS B0S 1C0",
    "addr:housenumber":"271",
    "addr:postcode":"b0s 1c0",
    "addr:street":"Granville",
    "iso:country":"CA",
    "sg:address":"271 Granville",
    "sg:city":"Bridgetown",
    "sg:classifiers":[
        {
            "category":"Government",
            "subcategory":"Office",
            "type":"Public Place"
        }
    ],
    "sg:phone":"+1 902 665 4637",
    "sg:postcode":"B0S 1C0",
    "sg:province":"NS",
    "sg:tags":[
        "village"
    ],
    "wof:name":"Bridgetown Town Clerk",
    "wof:placetype":"venue"
},
  "geometry": {"coordinates":[-65.27066802980001,44.8455505371],"type":"Point"}
}