{
  "type": "Feature",
  "properties": {
    "addr:full":"178 Main St West Lorne ON N0L 2P0",
    "addr:housenumber":"178",
    "addr:postcode":"n0l 2p0",
    "addr:street":"Main St",
    "iso:country":"CA",
    "sg:address":"178 Main St",
    "sg:city":"West Lorne",
    "sg:classifiers":[
        {
            "category":"Restaurant",
            "type":"Food & Drink"
        }
    ],
    "sg:phone":"+1 519 768 1436",
    "sg:postcode":"N0L 2P0",
    "sg:province":"ON",
    "wof:name":"Machado Restaurant",
    "wof:placetype":"venue"
},
  "geometry": {"coordinates":[-81.607376,42.603035],"type":"Point"}
}