{
  "type": "Feature",
  "properties": {
    "addr:full":"1 Carr Cres Gander NL A1V 2E2",
    "addr:housenumber":"1",
    "addr:postcode":"a1v 2e2",
    "addr:street":"Carr Cres",
    "iso:country":"CA",
    "sg:address":"1 Carr Cres",
    "sg:city":"Gander",
    "sg:classifiers":[
        {
            "category":"Retail",
            "subcategory":"Auto Repair",
            "type":"Services"
        }
    ],
    "sg:phone":"+1 709 256 8874",
    "sg:postcode":"A1V 2E2",
    "sg:province":"NL",
    "sg:tags":[
        "body",
        "automobile",
        "painting"
    ],
    "wof:name":"Gew Auto Body Shop CO Ltd",
    "wof:placetype":"venue"
},
  "geometry": {"coordinates":[-54.63205,48.96611],"type":"Point"}
}