{
  "type": "Feature",
  "properties": {
    "addr:full":"1060 Gerrard St E Toronto ON M4M 1Z8",
    "addr:housenumber":"1060",
    "addr:postcode":"m4m 1z8",
    "addr:street":"Gerrard St E",
    "iso:country":"CA",
    "sg:address":"1060 Gerrard St E",
    "sg:city":"Toronto",
    "sg:classifiers":[
        {
            "category":"Restaurant",
            "type":"Food & Drink"
        }
    ],
    "sg:phone":"+1 416 465 4167",
    "sg:postcode":"M4M 1Z8",
    "sg:province":"ON",
    "wof:name":"Sum Kee Noodle House",
    "wof:placetype":"venue"
},
  "geometry": {"coordinates":[-79.33586099999999,43.669312],"type":"Point"}
}