{
  "type": "Feature",
  "properties": {
    "addr:full":"5207 8E Av Montreal QC H1Y 2L3",
    "addr:housenumber":"5207",
    "addr:postcode":"h1y 2l3",
    "addr:street":"8E Av",
    "iso:country":"CA",
    "sg:address":"5207 8E Av",
    "sg:city":"Montreal",
    "sg:classifiers":[
        {
            "category":"Retail",
            "subcategory":"Auto Repair",
            "type":"Services"
        }
    ],
    "sg:phone":"+1 514 721 5515",
    "sg:postcode":"H1Y 2L3",
    "sg:province":"QC",
    "sg:tags":[
        "body",
        "automobile",
        "painting"
    ],
    "wof:name":"Carrosserie C Chouinard Inc",
    "wof:placetype":"venue"
},
  "geometry": {"coordinates":[-73.57208300000001,45.548752],"type":"Point"}
}