{
  "type": "Feature",
  "properties": {
    "addr:full":"307 Rte Marie-Victorin Sorel-Tracy QC J3R 1K6",
    "addr:housenumber":"307",
    "addr:postcode":"j3r 1k6",
    "addr:street":"Rte Marie-Victorin",
    "iso:country":"CA",
    "sg:address":"307 Rte Marie-Victorin",
    "sg:city":"Sorel-Tracy",
    "sg:classifiers":[
        {
            "category":"Government",
            "subcategory":"Office",
            "type":"Public Place"
        }
    ],
    "sg:phone":"+1 450 742 0479",
    "sg:postcode":"J3R 1K6",
    "sg:province":"QC",
    "wof:name":"Canada Depute Federal",
    "wof:placetype":"venue"
},
  "geometry": {"coordinates":[-73.12260437010001,46.0401306152],"type":"Point"}
}