{
  "type": "Feature",
  "properties": {
    "addr:full":"4105 53 St Athabasca AB T9S 1A7",
    "addr:housenumber":"4105",
    "addr:postcode":"t9s 1a7",
    "addr:street":"53 St",
    "iso:country":"CA",
    "sg:address":"4105 53 St",
    "sg:city":"Athabasca",
    "sg:classifiers":[
        {
            "category":"Building & Trades",
            "subcategory":"Construction",
            "type":"Services"
        }
    ],
    "sg:phone":"+1 780 675 5661",
    "sg:postcode":"T9S 1A7",
    "sg:province":"AB",
    "sg:tags":[
        "pipe",
        "line",
        "contractor"
    ],
    "wof:name":"Saddle Tech Inc",
    "wof:placetype":"venue"
},
  "geometry": {"coordinates":[-113.295074,54.708054],"type":"Point"}
}