{
  "type": "Feature",
  "properties": {
    "addr:full":"PO Box 37 Old Perlican NL A0A 3G0",
    "addr:housenumber":"po box 37",
    "addr:postcode":"perlican;a0a 3g0",
    "iso:country":"CA",
    "sg:address":"PO Box 37",
    "sg:city":"Old Perlican",
    "sg:classifiers":[
        {
            "category":"Organizations",
            "subcategory":"Religious Organization",
            "type":"Services"
        }
    ],
    "sg:phone":"+1 709 587 2080",
    "sg:postcode":"A0A 3G0",
    "sg:province":"NL",
    "sg:tags":[
        "church"
    ],
    "wof:name":"Old Perlican United Church",
    "wof:placetype":"venue"
},
  "geometry": {"coordinates":[-53.0059585571,48.0817947388],"type":"Point"}
}