{
  "type": "Feature",
  "properties": {
    "addr:full":"336 Portland St Dartmouth NS B2Y 1K6",
    "addr:housenumber":"336",
    "addr:postcode":"b2y 1k6",
    "addr:street":"Portland St",
    "iso:country":"CA",
    "sg:address":"336 Portland St",
    "sg:city":"Dartmouth",
    "sg:classifiers":[
        {
            "category":"Retail",
            "subcategory":"Auto Repair",
            "type":"Services"
        }
    ],
    "sg:phone":"+1 902 461 1858",
    "sg:postcode":"B2Y 1K6",
    "sg:province":"NS",
    "sg:tags":[
        "repairing",
        "automobile"
    ],
    "wof:name":"Car's City Auto Repairs",
    "wof:placetype":"venue"
},
  "geometry": {"coordinates":[-63.5518,44.667816],"type":"Point"}
}