{
  "type": "Feature",
  "properties": {
    "addr:full":"PO Box 29 Leslieville AB T0M 1H0",
    "addr:housenumber":"po box 29;ab",
    "addr:postcode":"t0m 1h0",
    "addr:street":"Leslieville",
    "iso:country":"CA",
    "sg:address":"PO Box 29",
    "sg:city":"Leslieville",
    "sg:classifiers":[
        {
            "category":"Mining & Drilling",
            "type":"Manufacturing & Wholesale Goods"
        }
    ],
    "sg:phone":"+1 403 729 2270",
    "sg:postcode":"T0M 1H0",
    "sg:province":"AB",
    "sg:tags":[
        "field",
        "oil"
    ],
    "wof:name":"Shale Oilfield Svc Ltd",
    "wof:placetype":"venue"
},
  "geometry": {"coordinates":[-114.601456,52.383816],"type":"Point"}
}