{
  "type": "Feature",
  "properties": {
    "addr:full":"18 Oakley Dr Lundbreck AB T0K 1H0",
    "addr:housenumber":"18",
    "addr:postcode":"t0k 1h0",
    "addr:street":"Oakley Dr",
    "iso:country":"CA",
    "sg:address":"18 Oakley Dr",
    "sg:city":"Lundbreck",
    "sg:classifiers":[
        {
            "category":"Shopping",
            "subcategory":"Computers & Home Electronics",
            "type":"Retail Goods"
        }
    ],
    "sg:phone":"+1 403 628 3786",
    "sg:postcode":"T0K 1H0",
    "sg:province":"AB",
    "sg:tags":[
        "equipment",
        "dealer"
    ],
    "wof:name":"Grb Computers & Software",
    "wof:placetype":"venue"
},
  "geometry": {"coordinates":[-114.164779663,49.5837059021],"type":"Point"}
}