{
  "type": "Feature",
  "properties": {
    "addr:full":"1135 17 Ave SW Calgary AB T2T 0B6",
    "addr:housenumber":"1135",
    "addr:postcode":"t2t 0b6",
    "addr:street":"17 Ave Sw",
    "iso:country":"CA",
    "sg:address":"1135 17 Ave SW",
    "sg:city":"Calgary",
    "sg:classifiers":[
        {
            "category":"Farming",
            "subcategory":"Farm & Veterinary Services",
            "type":"Manufacturing & Wholesale Goods"
        }
    ],
    "sg:phone":"+1 403 245 4366",
    "sg:postcode":"T2T 0B6",
    "sg:province":"AB",
    "sg:tags":[
        "management"
    ],
    "wof:name":"Toole Peet Real Estate",
    "wof:placetype":"venue"
},
  "geometry": {"coordinates":[-114.089111328,51.0377044678],"type":"Point"}
}