{
  "type": "Feature",
  "properties": {
    "addr:full":"187 St. George St Bathurst NB E2A 1B6",
    "addr:housenumber":"187",
    "addr:postcode":"e2a 1b6",
    "addr:street":"St. George St",
    "iso:country":"CA",
    "sg:address":"187 St. George St",
    "sg:city":"Bathurst",
    "sg:classifiers":[
        {
            "category":"Retail",
            "subcategory":"Funeral Services",
            "type":"Services"
        }
    ],
    "sg:phone":"+1 506 546 2716",
    "sg:postcode":"E2A 1B6",
    "sg:province":"NB",
    "sg:tags":[
        "director"
    ],
    "wof:name":"Elhatton's Funeral Home Ltd",
    "wof:placetype":"venue"
},
  "geometry": {"coordinates":[-65.65387699999999,47.619301],"type":"Point"}
}