{
  "type": "Feature",
  "properties": {
    "addr:full":"2006 Kings Rd Sydney NS B1L 1C4",
    "addr:housenumber":"2006",
    "addr:postcode":"b1l 1c4",
    "addr:street":"Kings Rd",
    "iso:country":"CA",
    "sg:address":"2006 Kings Rd",
    "sg:city":"Sydney",
    "sg:classifiers":[
        {
            "category":"Retail",
            "subcategory":"Auto Repair",
            "type":"Services"
        }
    ],
    "sg:phone":"+1 902 562 0475",
    "sg:postcode":"B1L 1C4",
    "sg:province":"NS",
    "sg:tags":[
        "repairing",
        "automobile"
    ],
    "wof:name":"B & F Barrington's Svc Ctr Ltd",
    "wof:placetype":"venue"
},
  "geometry": {"coordinates":[-60.225479,46.10651],"type":"Point"}
}