{
  "type": "Feature",
  "properties": {
    "addr:full":"7705 Yonge St Thornhill ON L3T 2C4",
    "addr:housenumber":"7705",
    "addr:postcode":"l3t 2c4",
    "addr:street":"Yonge St",
    "iso:country":"CA",
    "sg:address":"7705 Yonge St",
    "sg:city":"Thornhill",
    "sg:classifiers":[
        {
            "category":"Health Services",
            "subcategory":"Medical Lab",
            "type":"Services"
        }
    ],
    "sg:phone":"+1 905 763 8998",
    "sg:postcode":"L3T 2C4",
    "sg:province":"ON",
    "wof:name":"Thornhill Denture Clinic",
    "wof:placetype":"venue"
},
  "geometry": {"coordinates":[-79.424118042,43.8155288696],"type":"Point"}
}