{
  "type": "Feature",
  "properties": {
    "iso:country":"CA",
    "sg:city":"Calgary",
    "sg:classifiers":[
        {
            "category":"Health Services",
            "subcategory":"Chiropractor",
            "type":"Services"
        }
    ],
    "sg:phone":"+1 403 281 7777",
    "sg:postcode":"T2W 1G8",
    "sg:province":"AB",
    "wof:name":"Canyon Meadows Chiropractic",
    "wof:placetype":"venue"
},
  "geometry": {"coordinates":[-114.084754944,50.9491233826],"type":"Point"}
}