{
  "type": "Feature",
  "properties": {
    "addr:full":"Chatham ON N7M 1J5",
    "addr:postcode":"n7m 1j5",
    "iso:country":"CA",
    "sg:city":"Chatham",
    "sg:classifiers":[
        {
            "category":"Professional",
            "subcategory":"Lawyer & Legal Services",
            "type":"Services"
        }
    ],
    "sg:phone":"+1 519 354 2844",
    "sg:postcode":"N7M 1J5",
    "sg:province":"ON",
    "sg:tags":[
        "attorney"
    ],
    "wof:name":"Pascoe, Judith R",
    "wof:placetype":"venue"
},
  "geometry": {"coordinates":[-82.185951,42.404438],"type":"Point"}
}