{
  "type": "Feature",
  "properties": {
    "iso:country":"CA",
    "sg:address":"410 Saskatchewan Ave W",
    "sg:city":"Outlook",
    "sg:classifiers":[
        {
            "category":"Professional",
            "subcategory":"Research",
            "type":"Services"
        }
    ],
    "sg:phone":"+1 306 867 9566",
    "sg:postcode":"S0L 2N0",
    "sg:province":"SK",
    "sg:tags":[
        "economic",
        "analysis"
    ],
    "wof:name":"Economic Development Office",
    "wof:placetype":"venue"
},
  "geometry": {"coordinates":[-107.051445007,51.4883117676],"type":"Point"}
}