{
  "type": "Feature",
  "properties": {
    "addr:full":"400 Rue Hector-Lanthier Saint-Eustache QC J7P 4C1",
    "addr:housenumber":"400",
    "addr:postcode":"j7p 4c1",
    "addr:street":"Rue Hector-Lanthier",
    "iso:country":"CA",
    "sg:address":"400 Rue Hector-Lanthier",
    "sg:city":"Saint-Eustache",
    "sg:classifiers":[
        {
            "category":"Restaurant",
            "type":"Food & Drink"
        }
    ],
    "sg:phone":"+1 450 473 4000",
    "sg:postcode":"J7P 4C1",
    "sg:province":"QC",
    "wof:name":"Memphis Belle",
    "wof:placetype":"venue"
},
  "geometry": {"coordinates":[-73.8737411499,45.5853614807],"type":"Point"}
}