{
  "type": "Feature",
  "properties": {
    "addr:full":"3817 99 St NW Edmonton AB T6E 6J1",
    "addr:housenumber":"3817",
    "addr:postcode":"t6e 6j1",
    "addr:street":"99 St Nw",
    "iso:country":"CA",
    "sg:address":"3817 99 St NW",
    "sg:city":"Edmonton",
    "sg:classifiers":[
        {
            "category":"Restaurant",
            "type":"Food & Drink"
        }
    ],
    "sg:phone":"+1 780 462 5200",
    "sg:postcode":"T6E 6J1",
    "sg:province":"AB",
    "wof:name":"Subway Sandwiches & Salads",
    "wof:placetype":"venue"
},
  "geometry": {"coordinates":[-113.48580200000001,53.472706],"type":"Point"}
}