{
  "type": "Feature",
  "properties": {
    "addr:full":"140 Young St St Jacobs ON N0B 2N0",
    "addr:housenumber":"140",
    "addr:postcode":"n0b 2n0",
    "addr:street":"Young St St",
    "iso:country":"CA",
    "sg:address":"140 Young St",
    "sg:city":"St Jacobs",
    "sg:classifiers":[
        {
            "category":"Shopping",
            "type":"Retail Goods"
        }
    ],
    "sg:phone":"+1 519 664 2866",
    "sg:postcode":"N0B 2N0",
    "sg:province":"ON",
    "sg:tags":[
        "trophy",
        "medal",
        "award"
    ],
    "wof:name":"Northside Trophies & Awards",
    "wof:placetype":"venue"
},
  "geometry": {"coordinates":[-80.553673,43.532242],"type":"Point"}
}