{
  "type": "Feature",
  "properties": {
    "iso:country":"CA",
    "sg:address":"398 Texas Rd",
    "sg:city":"Amherstburg",
    "sg:classifiers":[
        {
            "category":"Autos & Motor Vehicles",
            "subcategory":"Auto Supplies",
            "type":"Retail Goods"
        }
    ],
    "sg:phone":"+1 519 736 7274",
    "sg:postcode":"N9V 2R7",
    "sg:province":"ON",
    "sg:tags":[
        "automobile",
        "kit"
    ],
    "wof:name":"West Coast Dreams",
    "wof:placetype":"venue"
},
  "geometry": {"coordinates":[-83.10903167719999,42.127658844],"type":"Point"}
}