{
  "type": "Feature",
  "properties": {
    "addr:full":"367 Oakdale Rd North York ON M3N 1W7",
    "addr:housenumber":"367",
    "addr:postcode":"m3n 1w7",
    "addr:street":"Oakdale Rd",
    "iso:country":"CA",
    "sg:address":"367 Oakdale Rd",
    "sg:city":"North York",
    "sg:classifiers":[
        {
            "category":"Manufacturing",
            "subcategory":"Metals",
            "type":"Manufacturing & Wholesale Goods"
        }
    ],
    "sg:phone":"+1 416 745 0144",
    "sg:postcode":"M3N 1W7",
    "sg:province":"ON",
    "sg:tags":[
        "stacks",
        "smoke"
    ],
    "wof:name":"Environ",
    "wof:placetype":"venue"
},
  "geometry": {"coordinates":[-79.52648162840001,43.747833252],"type":"Point"}
}