{
  "type": "Feature",
  "properties": {
    "iso:country":"CA",
    "sg:address":"17301 Ch Charles",
    "sg:city":"Mirabel",
    "sg:classifiers":[
        {
            "category":"Building & Trades",
            "subcategory":"Landscaping Services",
            "type":"Services"
        }
    ],
    "sg:phone":"+1 450 435 8862",
    "sg:postcode":"J7J 1P3",
    "sg:province":"QC",
    "sg:tags":[
        "landscape",
        "contractor"
    ],
    "wof:name":"Gazon R Lacroix Inc",
    "wof:placetype":"venue"
},
  "geometry": {"coordinates":[-73.9393157959,45.6894950867],"type":"Point"}
}