{
  "type": "Feature",
  "properties": {
    "addr:full":"1895 Bank St Ottawa ON K1V 8A1",
    "addr:housenumber":"1895",
    "addr:postcode":"k1v 8a1",
    "addr:street":"Bank St",
    "iso:country":"CA",
    "sg:address":"1895 Bank St",
    "sg:city":"Ottawa",
    "sg:classifiers":[
        {
            "category":"Shopping",
            "subcategory":"Optical Goods",
            "type":"Retail Goods"
        }
    ],
    "sg:phone":"+1 613 526 1110",
    "sg:postcode":"K1V 8A1",
    "sg:province":"ON",
    "sg:tags":[
        "optician"
    ],
    "wof:name":"Hakim Optical",
    "wof:placetype":"venue"
},
  "geometry": {"coordinates":[-75.6624298096,45.3689842224],"type":"Point"}
}