{
  "type": "Feature",
  "properties": {
    "addr:full":"Alexandria ON K0C 1A0",
    "addr:postcode":"k0c 1a0",
    "iso:country":"CA",
    "sg:city":"Alexandria",
    "sg:classifiers":[
        {
            "category":"Social Services",
            "type":"Services"
        }
    ],
    "sg:phone":"+1 613 525 4443",
    "sg:postcode":"K0C 1A0",
    "sg:province":"ON",
    "sg:tags":[
        "senior",
        "citizen"
    ],
    "wof:name":"Services DE Soutien Aux Aine",
    "wof:placetype":"venue"
},
  "geometry": {"coordinates":[-74.63576507569999,45.3123817444],"type":"Point"}
}