{
  "type": "Feature",
  "properties": {
    "addr:full":"3600 Rue Notre-Dame O Montreal QC H4C 1P5",
    "addr:housenumber":"3600",
    "addr:postcode":"h4c 1p5",
    "addr:street":"Rue Notre-Dame O",
    "iso:country":"CA",
    "sg:address":"3600 Rue Notre-Dame O",
    "sg:city":"Montreal",
    "sg:classifiers":[
        {
            "category":"Professional",
            "type":"Services"
        }
    ],
    "sg:phone":"+1 514 940 0771",
    "sg:postcode":"H4C 1P5",
    "sg:province":"QC",
    "sg:tags":[
        "printer",
        "establishment"
    ],
    "wof:name":"Media Graphi Expresso",
    "wof:placetype":"venue"
},
  "geometry": {"coordinates":[-73.536255,45.542419],"type":"Point"}
}