{
  "type": "Feature",
  "properties": {
    "iso:country":"CA",
    "sg:address":"1822 Av Du Mont-Royal E",
    "sg:city":"Montreal",
    "sg:classifiers":[
        {
            "category":"Shopping",
            "subcategory":"Shoes",
            "type":"Retail Goods"
        }
    ],
    "sg:phone":"+1 514 521 0820",
    "sg:postcode":"H2H 1J1",
    "sg:province":"QC",
    "wof:name":"Cordonnerie Tony Pappas Inc",
    "wof:placetype":"venue"
},
  "geometry": {"coordinates":[-73.574142,45.533127],"type":"Point"}
}