{
  "type": "Feature",
  "properties": {
    "addr:full":"232 8 Ave SW Calgary AB T2P 1B5",
    "addr:housenumber":"232",
    "addr:postcode":"t2p 1b5",
    "addr:street":"8 Ave Sw",
    "iso:country":"CA",
    "sg:address":"232 8 Ave SW",
    "sg:city":"Calgary",
    "sg:classifiers":[
        {
            "category":"Restaurant",
            "type":"Food & Drink"
        }
    ],
    "sg:phone":"+1 403 262 9530",
    "sg:postcode":"T2P 1B5",
    "sg:province":"AB",
    "wof:name":"Oriental House Restaurant",
    "wof:placetype":"venue"
},
  "geometry": {"coordinates":[-114.06636047400001,51.0457572937],"type":"Point"}
}