{
  "type": "Feature",
  "properties": {
    "addr:full":"227 7 Ave N Vauxhall AB T0K 2K0",
    "addr:housenumber":"227",
    "addr:postcode":"t0k 2k0",
    "addr:street":"7 Ave N",
    "iso:country":"CA",
    "sg:address":"227 7 Ave N",
    "sg:city":"Vauxhall",
    "sg:classifiers":[
        {
            "category":"Shopping",
            "subcategory":"Bicycles & Sporting Goods",
            "type":"Retail Goods"
        }
    ],
    "sg:phone":"+1 403 654 4145",
    "sg:postcode":"T0K 2K0",
    "sg:province":"AB",
    "sg:tags":[
        "tackle",
        "fishing"
    ],
    "wof:name":"Rolf's Flies",
    "wof:placetype":"venue"
},
  "geometry": {"coordinates":[-112.101868,50.073093],"type":"Point"}
}