{
  "type": "Feature",
  "properties": {
    "addr:full":"1755 Rue DE Toulon Sherbrooke QC J1J 3V6",
    "addr:housenumber":"1755",
    "addr:postcode":"j1j 3v6",
    "addr:street":"Rue De Toulon",
    "iso:country":"CA",
    "sg:address":"1755 Rue DE Toulon",
    "sg:city":"Sherbrooke",
    "sg:classifiers":[
        {
            "category":"Professional",
            "subcategory":"Business Services",
            "type":"Services"
        }
    ],
    "sg:phone":"+1 819 829 2000",
    "sg:postcode":"J1J 3V6",
    "sg:province":"QC",
    "sg:tags":[
        "interior",
        "consultant",
        "design",
        "decorator"
    ],
    "wof:name":"Roy Line Design",
    "wof:placetype":"venue"
},
  "geometry": {"coordinates":[-71.9497909546,45.3678817749],"type":"Point"}
}