{
  "type": "Feature",
  "properties": {
    "addr:full":"39 Av Somerville Westmount QC H3Z 1J3",
    "addr:postcode":"h3z 1j3",
    "addr:street":"39 Av Somerville",
    "iso:country":"CA",
    "sg:address":"39 Av Somerville",
    "sg:city":"Westmount",
    "sg:classifiers":[
        {
            "category":"Shopping",
            "type":"Retail Goods"
        }
    ],
    "sg:phone":"+1 514 488 3163",
    "sg:postcode":"H3Z 1J3",
    "sg:province":"QC",
    "sg:tags":[
        "art",
        "gallery",
        "dealer"
    ],
    "wof:name":"Farfelu Montreal",
    "wof:placetype":"venue"
},
  "geometry": {"coordinates":[-73.602592,45.477818],"type":"Point"}
}