{
  "type": "Feature",
  "properties": {
    "addr:full":"3514 Av Lacombe Montreal QC H3T 1M1",
    "addr:housenumber":"3514",
    "addr:postcode":"h3t 1m1",
    "addr:street":"Av Lacombe",
    "iso:country":"CA",
    "sg:address":"3514 Av Lacombe",
    "sg:city":"Montreal",
    "sg:classifiers":[
        {
            "category":"Travel",
            "subcategory":"Hotels & Motels",
            "type":"Entertainment"
        }
    ],
    "sg:phone":"+1 514 731 1015",
    "sg:postcode":"H3T 1M1",
    "sg:province":"QC",
    "wof:name":"Auberge Jeunesse Du St Laurent",
    "wof:placetype":"venue"
},
  "geometry": {"coordinates":[-73.6227111816,45.4973220825],"type":"Point"}
}