{
  "type": "Feature",
  "properties": {
    "iso:country":"CA",
    "sg:city":"Belleville",
    "sg:classifiers":[
        {
            "category":"Shopping",
            "subcategory":"Clothing, Apparel, & Fashions",
            "type":"Retail Goods"
        }
    ],
    "sg:phone":"+1 613 966 7970",
    "sg:postcode":"K8P 3E1",
    "sg:province":"ON",
    "sg:tags":[
        "maternity"
    ],
    "wof:name":"Thyme Maternity",
    "wof:placetype":"venue"
},
  "geometry": {"coordinates":[-77.396515,44.188393],"type":"Point"}
}