{
  "type": "Feature",
  "properties": {
    "addr:full":"Montreal QC H2L 1L3",
    "addr:postcode":"h2l 1l3",
    "iso:country":"CA",
    "sg:city":"Montreal",
    "sg:classifiers":[
        {
            "category":"Manufacturing",
            "subcategory":"Printing",
            "type":"Manufacturing & Wholesale Goods"
        }
    ],
    "sg:phone":"+1 514 849 4800",
    "sg:postcode":"H2L 1L3",
    "sg:province":"QC",
    "sg:tags":[
        "multimedia",
        "advertising"
    ],
    "wof:name":"Kutoka",
    "wof:placetype":"venue"
},
  "geometry": {"coordinates":[-73.565842,45.520729],"type":"Point"}
}