{
  "type": "Feature",
  "properties": {
    "addr:full":"45 Rue Academy Lennoxville QC J1M 1P9",
    "addr:housenumber":"45",
    "addr:postcode":"j1m 1p9",
    "addr:street":"Rue Academy",
    "iso:country":"CA",
    "sg:address":"45 Rue Academy",
    "sg:city":"Lennoxville",
    "sg:classifiers":[
        {
            "category":"Manufacturing",
            "subcategory":"Signs",
            "type":"Manufacturing & Wholesale Goods"
        }
    ],
    "sg:phone":"+1 819 562 3461",
    "sg:postcode":"J1M 1P9",
    "sg:province":"QC",
    "wof:name":"Pittoresco",
    "wof:placetype":"venue"
},
  "geometry": {"coordinates":[-71.86438,45.369476],"type":"Point"}
}