{
  "type": "Feature",
  "properties": {
    "iso:country":"CA",
    "sg:address":"45 Rue Academy",
    "sg:city":"Lennoxville",
    "sg:classifiers":[
        {
            "category":"Manufacturing",
            "subcategory":"Signs",
            "type":"Manufacturing & Wholesale Goods"
        }
    ],
    "sg:phone":"+1 819 562 3461",
    "sg:postcode":"J1M 1P9",
    "sg:province":"QC",
    "wof:name":"Pittoresco",
    "wof:placetype":"venue"
},
  "geometry": {"coordinates":[-71.86438,45.369476],"type":"Point"}
}