{
  "type": "Feature",
  "properties": {
    "iso:country":"CA",
    "sg:address":"1024 Kensington Blvd",
    "sg:city":"Sarnia",
    "sg:classifiers":[
        {
            "category":"Building & Trades",
            "subcategory":"Construction",
            "type":"Services"
        }
    ],
    "sg:phone":"+1 519 490 3077",
    "sg:postcode":"N7S 1N2",
    "sg:province":"ON",
    "sg:tags":[
        "downspouts",
        "siding",
        "gutter",
        "contractor"
    ],
    "wof:name":"B P Siding",
    "wof:placetype":"venue"
},
  "geometry": {"coordinates":[-82.3705825806,42.9772415161],"type":"Point"}
}