{
  "type": "Feature",
  "properties": {
    "addr:full":"104 Florence Ave North York ON M2N 1G3",
    "addr:housenumber":"104",
    "addr:postcode":"m2n 1g3",
    "addr:street":"Florence Ave",
    "iso:country":"CA",
    "sg:address":"104 Florence Ave",
    "sg:city":"North York",
    "sg:classifiers":[
        {
            "category":"Building & Trades",
            "subcategory":"Plumbing",
            "type":"Services"
        }
    ],
    "sg:phone":"+1 416 604 7558",
    "sg:postcode":"M2N 1G3",
    "sg:province":"ON",
    "sg:tags":[
        "mechanical",
        "contractor"
    ],
    "wof:name":"Black Creek Mechanical Ltd",
    "wof:placetype":"venue"
},
  "geometry": {"coordinates":[-79.41539,43.757198],"type":"Point"}
}