{
  "type": "Feature",
  "properties": {
    "iso:country":"CA",
    "sg:city":"Verdun",
    "sg:classifiers":[
        {
            "category":"Social Services",
            "type":"Services"
        }
    ],
    "sg:phone":"+1 514 362 8530",
    "sg:postcode":"H4G 3E7",
    "sg:province":"QC",
    "sg:tags":[
        "organization",
        "welfare"
    ],
    "wof:name":"Clinique DE Toxicologie DE Mtl",
    "wof:placetype":"venue"
},
  "geometry": {"coordinates":[-73.563828,45.456539],"type":"Point"}
}