{
  "type": "Feature",
  "properties": {
    "addr:full":"610 Lagimodiere Blvd Winnipeg MB R2J 0T7",
    "addr:housenumber":"610",
    "addr:postcode":"r2j 0t7",
    "addr:street":"Lagimodiere Blvd",
    "iso:country":"CA",
    "sg:address":"610 Lagimodiere Blvd",
    "sg:city":"Winnipeg",
    "sg:classifiers":[
        {
            "category":"Autos & Motor Vehicles",
            "subcategory":"Fuel & Gas Station",
            "type":"Retail Goods"
        }
    ],
    "sg:phone":"+1 204 254 1437",
    "sg:postcode":"R2J 0T7",
    "sg:province":"MB",
    "sg:tags":[
        "oil"
    ],
    "wof:name":"Mint Corner Self Serve",
    "wof:placetype":"venue"
},
  "geometry": {"coordinates":[-97.049911499,49.8570594788],"type":"Point"}
}