{
  "type": "Feature",
  "properties": {
    "addr:full":"1012 22nd St W North Vancouver BC V7P 2E5",
    "addr:housenumber":"1012",
    "addr:postcode":"v7p 2e5",
    "addr:street":"22Nd St W",
    "iso:country":"CA",
    "sg:address":"1012 22nd St W",
    "sg:city":"North Vancouver",
    "sg:classifiers":[
        {
            "category":"Building & Trades",
            "subcategory":"Construction",
            "type":"Services"
        }
    ],
    "sg:phone":"+1 604 988 9523",
    "sg:postcode":"V7P 2E5",
    "sg:province":"BC",
    "sg:tags":[
        "concrete",
        "contractor"
    ],
    "wof:name":"Ncb Enterprises Ltd",
    "wof:placetype":"venue"
},
  "geometry": {"coordinates":[-123.089256287,49.3294487],"type":"Point"}
}