{
  "type": "Feature",
  "properties": {
    "addr:full":"774495 Hwy 10 Markdale ON N0C 1H0",
    "addr:housenumber":"774495",
    "addr:postcode":"n0c 1h0",
    "addr:street":"Hwy 10",
    "iso:country":"CA",
    "sg:address":"774495 Hwy 10",
    "sg:city":"Markdale",
    "sg:classifiers":[
        {
            "category":"Autos & Motor Vehicles",
            "subcategory":"Automobile Sales",
            "type":"Retail Goods"
        }
    ],
    "sg:phone":"+1 519 924 2022",
    "sg:postcode":"N0C 1H0",
    "sg:province":"ON",
    "sg:tags":[
        "car",
        "dealer"
    ],
    "wof:name":"Hutchinson Automotive",
    "wof:placetype":"venue"
},
  "geometry": {"coordinates":[-80.58857,44.283619],"type":"Point"}
}