{
  "type": "Feature",
  "properties": {
    "iso:country":"CA",
    "sg:address":"355 Rue Sainte-Anne",
    "sg:city":"Chicoutimi",
    "sg:classifiers":[
        {
            "category":"Food & Beverages",
            "subcategory":"Groceries & Convenience Stores",
            "type":"Retail Goods"
        }
    ],
    "sg:phone":"+1 418 696 3133",
    "sg:postcode":"G7J 2M7",
    "sg:province":"QC",
    "wof:name":"Accomodation Ja-Fa",
    "wof:placetype":"venue"
},
  "geometry": {"coordinates":[-71.0684585571,48.4262428284],"type":"Point"}
}