{
  "type": "Feature",
  "properties": {
    "iso:country":"CA",
    "sg:address":"213 Rue DE L'Eglise",
    "sg:city":"Martinville",
    "sg:classifiers":[
        {
            "category":"Restaurant",
            "type":"Food & Drink"
        }
    ],
    "sg:phone":"+1 819 835 5355",
    "sg:postcode":"J0B 2A0",
    "sg:province":"QC",
    "sg:tags":[
        "site",
        "reception",
        "wedding"
    ],
    "wof:name":"Pavillon St-Gabriel Enr",
    "wof:placetype":"venue"
},
  "geometry": {"coordinates":[-72.2296829224,45.1519813538],"type":"Point"}
}