{
  "type": "Feature",
  "properties": {
    "addr:full":"52 Rue Elie-Rochefort Port-Cartier QC G5B 1N2",
    "addr:housenumber":"52",
    "addr:postcode":"g5b 1n2",
    "addr:street":"Rue Elie-Rochefort",
    "iso:country":"CA",
    "sg:address":"52 Rue Elie-Rochefort",
    "sg:city":"Port-Cartier",
    "sg:classifiers":[
        {
            "category":"Communications",
            "subcategory":"Radio Station",
            "type":"Services"
        }
    ],
    "sg:phone":"+1 418 766 6868",
    "sg:postcode":"G5B 1N2",
    "sg:province":"QC",
    "sg:tags":[
        "company",
        "broadcasting"
    ],
    "wof:name":"Radio Cipc",
    "wof:placetype":"venue"
},
  "geometry": {"coordinates":[-66.889427,50.026691],"type":"Point"}
}