{
  "type": "Feature",
  "properties": {
    "iso:country":"CA",
    "sg:address":"5401 Boul Des Galeries",
    "sg:city":"Quebec",
    "sg:classifiers":[
        {
            "category":"Shopping",
            "subcategory":"Pharmacy",
            "type":"Retail Goods"
        }
    ],
    "sg:phone":"+1 418 623 8917",
    "sg:postcode":"G2K 1N4",
    "sg:province":"QC",
    "wof:name":"Jean Coutu",
    "wof:placetype":"venue"
},
  "geometry": {"coordinates":[-71.295677,46.831238],"type":"Point"}
}