{
  "type": "Feature",
  "properties": {
    "addr:full":"265 Rue Seigneuriale Beauport QC G1C 3P7",
    "addr:housenumber":"265",
    "addr:postcode":"qc g1c 3p7",
    "addr:street":"Rue Seigneuriale",
    "iso:country":"CA",
    "sg:address":"265 Rue Seigneuriale",
    "sg:city":"Beauport",
    "sg:classifiers":[
        {
            "category":"Autos & Motor Vehicles",
            "subcategory":"Automobile Sales",
            "type":"Retail Goods"
        }
    ],
    "sg:phone":"+1 418 661 3222",
    "sg:postcode":"G1C 3P7",
    "sg:province":"QC",
    "sg:tags":[
        "car",
        "dealer"
    ],
    "wof:name":"Auto Pjs Inc",
    "wof:placetype":"venue"
},
  "geometry": {"coordinates":[-71.198792,46.876369],"type":"Point"}
}