{
  "type": "Feature",
  "properties": {
    "addr:full":"Kelowna BC V1X 6Y5",
    "addr:postcode":"v1x 6y5",
    "iso:country":"CA",
    "sg:city":"Kelowna",
    "sg:classifiers":[
        {
            "category":"Professional",
            "subcategory":"Management & Consulting",
            "type":"Services"
        }
    ],
    "sg:phone":"+1 250 861 4849",
    "sg:postcode":"V1X 6Y5",
    "sg:province":"BC",
    "sg:tags":[
        "construction"
    ],
    "wof:name":"Wasa Developments Inc",
    "wof:placetype":"venue"
},
  "geometry": {"coordinates":[-119.43493700000001,49.885296],"type":"Point"}
}