{
  "type": "Feature",
  "properties": {
    "addr:full":"100 Village Lane Okotoks AB T1S 1Z6",
    "addr:housenumber":"100",
    "addr:postcode":"t1s 1z6",
    "addr:street":"Village Lane Okotoks Ab",
    "iso:country":"CA",
    "sg:address":"100 Village Lane",
    "sg:city":"Okotoks",
    "sg:classifiers":[
        {
            "category":"Restaurant",
            "type":"Food & Drink"
        }
    ],
    "sg:phone":"+1 403 938 7500",
    "sg:postcode":"T1S 1Z6",
    "sg:province":"AB",
    "sg:tags":[
        "parlor",
        "ice",
        "cream"
    ],
    "wof:name":"Dairy Queen",
    "wof:placetype":"venue"
},
  "geometry": {"coordinates":[-113.98337600000001,50.718014],"type":"Point"}
}