{
  "type": "Feature",
  "properties": {
    "addr:full":"192 Biesenthal Rd Pembroke ON K8A 6W7",
    "addr:housenumber":"192",
    "addr:postcode":"k8a 6w7",
    "addr:street":"Biesenthal Rd",
    "iso:country":"CA",
    "sg:address":"192 Biesenthal Rd",
    "sg:city":"Pembroke",
    "sg:classifiers":[
        {
            "category":"Manufacturing",
            "subcategory":"Glass & Minerals",
            "type":"Manufacturing & Wholesale Goods"
        }
    ],
    "sg:phone":"+1 613 687 8417",
    "sg:postcode":"K8A 6W7",
    "sg:province":"ON",
    "sg:tags":[
        "brick",
        "general",
        "contractor"
    ],
    "wof:name":"Allied Concrete Products",
    "wof:placetype":"venue"
},
  "geometry": {"coordinates":[-77.1122131348,45.8264808655],"type":"Point"}
}