{
  "type": "Feature",
  "properties": {
    "addr:full":"Mississauga ON L5L 5X5",
    "addr:postcode":"l5l 5x5",
    "iso:country":"CA",
    "sg:city":"Mississauga",
    "sg:classifiers":[
        {
            "category":"Manufacturing",
            "subcategory":"Metals",
            "type":"Manufacturing & Wholesale Goods"
        }
    ],
    "sg:phone":"+1 905 828 2399",
    "sg:postcode":"L5L 5X5",
    "sg:province":"ON",
    "sg:tags":[
        "coating"
    ],
    "wof:name":"Downing Products Ltd",
    "wof:placetype":"venue"
},
  "geometry": {"coordinates":[-79.715958,43.528969],"type":"Point"}
}