{
  "type": "Feature",
  "properties": {
    "addr:full":"2575 Rue Remembrance Lachine QC H8S 1X4",
    "addr:housenumber":"2575",
    "addr:postcode":"h8s 1x4",
    "addr:street":"Rue Remembrance",
    "iso:country":"CA",
    "sg:address":"2575 Rue Remembrance",
    "sg:city":"Lachine",
    "sg:classifiers":[
        {
            "category":"Autos & Motor Vehicles",
            "subcategory":"Motorcycle Sales",
            "type":"Retail Goods"
        }
    ],
    "sg:phone":"+1 514 637 2581",
    "sg:postcode":"H8S 1X4",
    "sg:province":"QC",
    "sg:tags":[
        "all",
        "terrain",
        "scooter"
    ],
    "wof:name":"Pro Tech Suspension",
    "wof:placetype":"venue"
},
  "geometry": {"coordinates":[-73.6869506836,45.4377174377],"type":"Point"}
}