{
  "type": "Feature",
  "properties": {
    "addr:full":"9809 71 St NW Edmonton AB T6A 2T8",
    "addr:housenumber":"9809",
    "addr:postcode":"t6a 2t8",
    "addr:street":"71 St Nw",
    "iso:country":"CA",
    "sg:address":"9809 71 St NW",
    "sg:city":"Edmonton",
    "sg:classifiers":[
        {
            "category":"Personal",
            "subcategory":"Beauty Salon",
            "type":"Services"
        }
    ],
    "sg:phone":"+1 780 465 3765",
    "sg:postcode":"T6A 2T8",
    "sg:province":"AB",
    "wof:name":"Hair Encounters",
    "wof:placetype":"venue"
},
  "geometry": {"coordinates":[-113.436637878,53.5379714966],"type":"Point"}
}