{
  "type": "Feature",
  "properties": {
    "iso:country":"CA",
    "sg:address":"536 Av Atwater",
    "sg:city":"Montreal",
    "sg:classifiers":[
        {
            "category":"Banks & Credit Unions",
            "subcategory":"Bank",
            "type":"Services"
        }
    ],
    "sg:phone":"+1 514 935 6027",
    "sg:postcode":"H4C 2G5",
    "sg:province":"QC",
    "sg:tags":[
        "cashing",
        "check"
    ],
    "wof:name":"Insta-Cheques",
    "wof:placetype":"venue"
},
  "geometry": {"coordinates":[-73.578491,45.481575],"type":"Point"}
}