{
  "type": "Feature",
  "properties": {
    "addr:full":"10 Huron St Clinton ON N0M 1L0",
    "addr:housenumber":"10",
    "addr:postcode":"n0m 1l0",
    "addr:street":"Huron St",
    "iso:country":"CA",
    "sg:address":"10 Huron St",
    "sg:city":"Clinton",
    "sg:classifiers":[
        {
            "category":"Shopping",
            "subcategory":"Computers & Home Electronics",
            "type":"Retail Goods"
        }
    ],
    "sg:phone":"+1 519 482 9414",
    "sg:postcode":"N0M 1L0",
    "sg:province":"ON",
    "sg:tags":[
        "equipment",
        "satellite",
        "system"
    ],
    "wof:name":"Groves Tv & Appliance Ctr",
    "wof:placetype":"venue"
},
  "geometry": {"coordinates":[-81.54026,43.617222],"type":"Point"}
}