{
  "type": "Feature",
  "properties": {
    "addr:full":"Lamont AB T0B 2R0",
    "addr:postcode":"t0b 2r0",
    "iso:country":"CA",
    "sg:city":"Lamont",
    "sg:classifiers":[
        {
            "category":"Retail",
            "subcategory":"Repair Shop",
            "type":"Services"
        }
    ],
    "sg:phone":"+1 780 895 2238",
    "sg:postcode":"T0B 2R0",
    "sg:province":"AB",
    "sg:tags":[
        "farm",
        "equipment",
        "parts"
    ],
    "wof:name":"Park Investments Ltd",
    "wof:placetype":"venue"
},
  "geometry": {"coordinates":[-112.78599548299999,53.758266449],"type":"Point"}
}