{
  "type": "Feature",
  "properties": {
    "addr:full":"10626 Bayview Ave Richmond Hill ON L4C 3N8",
    "addr:housenumber":"10626",
    "addr:postcode":"l4c 3n8",
    "addr:street":"Bayview Ave",
    "iso:country":"CA",
    "sg:address":"10626 Bayview Ave",
    "sg:city":"Richmond Hill",
    "sg:classifiers":[
        {
            "category":"Food & Beverages",
            "subcategory":"Bakery",
            "type":"Retail Goods"
        }
    ],
    "sg:phone":"+1 905 787 1660",
    "sg:postcode":"L4C 3N8",
    "sg:province":"ON",
    "sg:tags":[
        "doughnut"
    ],
    "wof:name":"Coffee Time Donuts",
    "wof:placetype":"venue"
},
  "geometry": {"coordinates":[-79.4192199707,43.8905105591],"type":"Point"}
}