{
  "type": "Feature",
  "properties": {
    "addr:full":"167 Industrial Blvd St George Brant ON N0E 1N0",
    "addr:housenumber":"167",
    "addr:postcode":"n0e 1n0",
    "addr:street":"Industrial Blvd",
    "iso:country":"CA",
    "sg:address":"167 Industrial Blvd",
    "sg:city":"St George Brant",
    "sg:classifiers":[
        {
            "category":"Manufacturing",
            "subcategory":"Tools & Machinery",
            "type":"Manufacturing & Wholesale Goods"
        }
    ],
    "sg:phone":"+1 519 448 4605",
    "sg:postcode":"N0E 1N0",
    "sg:province":"ON",
    "sg:tags":[
        "pattern",
        "maker"
    ],
    "wof:name":"Future Patterns & Prototypes",
    "wof:placetype":"venue"
},
  "geometry": {"coordinates":[-80.426659,43.10247],"type":"Point"}
}