{
  "type": "Feature",
  "properties": {
    "addr:full":"77 Prom Du Portage Hull QC J8X 2J9",
    "addr:housenumber":"77",
    "addr:postcode":"j8x 2j9",
    "addr:street":"Prom Du Portage",
    "iso:country":"CA",
    "sg:address":"77 Prom Du Portage",
    "sg:city":"Hull",
    "sg:classifiers":[
        {
            "category":"Restaurant",
            "type":"Food & Drink"
        }
    ],
    "sg:phone":"+1 819 771 2224",
    "sg:postcode":"J8X 2J9",
    "sg:province":"QC",
    "wof:name":"Cafe Baci",
    "wof:placetype":"venue"
},
  "geometry": {"coordinates":[-75.718277,45.42522],"type":"Point"}
}