{
  "type": "Feature",
  "properties": {
    "addr:full":"Sainte-Hedwidge-DE-Roberval QC G0W 2R0",
    "addr:postcode":"g0w 2r0",
    "iso:country":"CA",
    "sg:city":"Sainte-Hedwidge-DE-Roberval",
    "sg:classifiers":[
        {
            "category":"Government",
            "subcategory":"Office",
            "type":"Public Place"
        }
    ],
    "sg:phone":"+1 418 275 3020",
    "sg:postcode":"G0W 2R0",
    "sg:province":"QC",
    "sg:tags":[
        "village"
    ],
    "wof:name":"Ste Hedwidge",
    "wof:placetype":"venue"
},
  "geometry": {"coordinates":[-72.362747,48.481396],"type":"Point"}
}