{
  "type": "Feature",
  "properties": {
    "addr:full":"Port Rowan ON N0E 1M0",
    "addr:postcode":"n0e 1m0",
    "iso:country":"CA",
    "sg:city":"Port Rowan",
    "sg:classifiers":[
        {
            "category":"Manufacturing",
            "subcategory":"Printing",
            "type":"Manufacturing & Wholesale Goods"
        }
    ],
    "sg:phone":"+1 519 586 2291",
    "sg:postcode":"N0E 1M0",
    "sg:province":"ON",
    "sg:tags":[
        "newspaper"
    ],
    "wof:name":"Port Rowan Good News",
    "wof:placetype":"venue"
},
  "geometry": {"coordinates":[-80.522186,42.672077],"type":"Point"}
}