{
  "type": "Feature",
  "properties": {
    "addr:full":"3364 Carp Rd Carp ON K0A 1L0",
    "addr:housenumber":"3364",
    "addr:postcode":"k0a 1l0",
    "addr:street":"Carp Rd",
    "iso:country":"CA",
    "sg:address":"3364 Carp Rd",
    "sg:city":"Carp",
    "sg:classifiers":[
        {
            "category":"Building & Trades",
            "subcategory":"Electrical",
            "type":"Services"
        }
    ],
    "sg:phone":"+1 613 839 0062",
    "sg:postcode":"K0A 1L0",
    "sg:province":"ON",
    "sg:tags":[
        "electric",
        "contractor"
    ],
    "wof:name":"Valley Utilities Ltd",
    "wof:placetype":"venue"
},
  "geometry": {"coordinates":[-76.016243,45.329227],"type":"Point"}
}