{
  "type": "Feature",
  "properties": {
    "addr:full":"16 Walker St Swan Hills AB T0G 2C0",
    "addr:housenumber":"16",
    "addr:postcode":"t0g 2c0",
    "addr:street":"Walker St",
    "iso:country":"CA",
    "sg:address":"16 Walker St",
    "sg:city":"Swan Hills",
    "sg:classifiers":[
        {
            "category":"Building & Trades",
            "subcategory":"Construction",
            "type":"Services"
        }
    ],
    "sg:phone":"+1 780 333 2115",
    "sg:postcode":"T0G 2C0",
    "sg:province":"AB",
    "sg:tags":[
        "millwright"
    ],
    "wof:name":"Joke Maintenance Svc Ltd",
    "wof:placetype":"venue"
},
  "geometry": {"coordinates":[-115.40461731000001,54.7252120972],"type":"Point"}
}