{
  "type": "Feature",
  "properties": {
    "addr:full":"4105 Talbot St Vernon ON K0A 3J0",
    "addr:housenumber":"4105",
    "addr:postcode":"k0a 3j0",
    "addr:street":"Talbot St",
    "iso:country":"CA",
    "sg:address":"4105 Talbot St",
    "sg:city":"Vernon",
    "sg:classifiers":[
        {
            "category":"Home & Garden",
            "subcategory":"Furniture",
            "type":"Retail Goods"
        }
    ],
    "sg:phone":"+1 613 791 0041",
    "sg:postcode":"K0A 3J0",
    "sg:province":"ON",
    "sg:tags":[
        "equipment",
        "kitchen",
        "cabinet"
    ],
    "wof:name":"Kitchens & Windows By Douglas",
    "wof:placetype":"venue"
},
  "geometry": {"coordinates":[-75.463562,45.161968],"type":"Point"}
}