{
  "type": "Feature",
  "properties": {
    "addr:full":"Dollard-Des-Ormeaux QC H9B 1Z8",
    "addr:postcode":"h9b 1z8",
    "iso:country":"CA",
    "sg:city":"Dollard-Des-Ormeaux",
    "sg:classifiers":[
        {
            "category":"Shopping",
            "subcategory":"Books",
            "type":"Retail Goods"
        }
    ],
    "sg:phone":"+1 514 683 9890",
    "sg:postcode":"H9B 1Z8",
    "sg:province":"QC",
    "sg:tags":[
        "dealer"
    ],
    "wof:name":"Book Market",
    "wof:placetype":"venue"
},
  "geometry": {"coordinates":[-73.79633331300001,45.4839363098],"type":"Point"}
}