{
  "type": "Feature",
  "properties": {
    "addr:full":"4820 the Bench Rd Windermere BC V0B 2L0",
    "addr:housenumber":"4820",
    "addr:postcode":"bc v0b 2l0",
    "addr:street":"The Bench Rd",
    "iso:country":"CA",
    "sg:address":"4820 the Bench Rd",
    "sg:city":"Windermere",
    "sg:classifiers":[
        {
            "category":"Food & Beverages",
            "subcategory":"Fruits & Vegetables",
            "type":"Retail Goods"
        }
    ],
    "sg:phone":"+1 250 342 0213",
    "sg:postcode":"V0B 2L0",
    "sg:province":"BC",
    "sg:tags":[
        "produce"
    ],
    "wof:name":"Win-Valley Gardens",
    "wof:placetype":"venue"
},
  "geometry": {"coordinates":[-115.98133900000001,50.466957],"type":"Point"}
}