{
  "type": "Feature",
  "properties": {
    "addr:full":"7665 Kennedy Rd Markham ON L3R 0L7",
    "addr:housenumber":"7665",
    "addr:postcode":"l3r 0l7",
    "addr:street":"Kennedy Rd",
    "iso:country":"CA",
    "sg:address":"7665 Kennedy Rd",
    "sg:city":"Markham",
    "sg:classifiers":[
        {
            "category":"Personal",
            "subcategory":"Beauty Salon",
            "type":"Services"
        }
    ],
    "sg:phone":"+1 905 479 4114",
    "sg:postcode":"L3R 0L7",
    "sg:province":"ON",
    "wof:name":"Hair Effects",
    "wof:placetype":"venue"
},
  "geometry": {"coordinates":[-79.30418400000001,43.841347],"type":"Point"}
}