{
  "type": "Feature",
  "properties": {
    "addr:full":"10960 104 St NW Edmonton AB T5H 2W6",
    "addr:housenumber":"10960",
    "addr:postcode":"t5h 2w6",
    "addr:street":"104 St Nw",
    "iso:country":"CA",
    "sg:address":"10960 104 St NW",
    "sg:city":"Edmonton",
    "sg:classifiers":[
        {
            "category":"Recreation",
            "type":"Entertainment"
        }
    ],
    "sg:phone":"+1 780 426 1856",
    "sg:postcode":"T5H 2W6",
    "sg:province":"AB",
    "sg:tags":[
        "caterer",
        "hall",
        "auditorium"
    ],
    "wof:name":"Polish Hall",
    "wof:placetype":"venue"
},
  "geometry": {"coordinates":[-113.499465942,53.5558700562],"type":"Point"}
}