{
  "type": "Feature",
  "properties": {
    "iso:country":"CA",
    "sg:address":"483 Main St W",
    "sg:city":"North Bay",
    "sg:classifiers":[
        {
            "category":"Professional",
            "subcategory":"Lawyer & Legal Services",
            "type":"Services"
        }
    ],
    "sg:phone":"+1 705 476 5600",
    "sg:postcode":"P1B 2V3",
    "sg:province":"ON",
    "sg:tags":[
        "attorney"
    ],
    "wof:name":"Manning, Fraser L",
    "wof:placetype":"venue"
},
  "geometry": {"coordinates":[-79.4682998657,46.3150024414],"type":"Point"}
}