{
  "type": "Feature",
  "properties": {
    "addr:full":"4364 Garden Bay Rd Garden Bay BC V0N 1S0",
    "addr:housenumber":"4364",
    "addr:postcode":"v0n 1s0",
    "addr:street":"Garden Bay Rd",
    "iso:country":"CA",
    "sg:address":"4364 Garden Bay Rd",
    "sg:city":"Garden Bay",
    "sg:classifiers":[
        {
            "category":"Travel",
            "subcategory":"Hotels & Motels",
            "type":"Entertainment"
        }
    ],
    "sg:phone":"+1 604 883 2244",
    "sg:postcode":"V0N 1S0",
    "sg:province":"BC",
    "sg:tags":[
        "resort"
    ],
    "wof:name":"Pender Harbour Auto Court",
    "wof:placetype":"venue"
},
  "geometry": {"coordinates":[-123.97567749,49.6411628723],"type":"Point"}
}