{
  "type": "Feature",
  "properties": {
    "addr:full":"Quebec QC G1N 1S7",
    "addr:postcode":"g1n 1s7",
    "iso:country":"CA",
    "sg:city":"Quebec",
    "sg:classifiers":[
        {
            "category":"Professional",
            "subcategory":"Engineering",
            "type":"Services"
        }
    ],
    "sg:phone":"+1 418 682 1156",
    "sg:postcode":"G1N 1S7",
    "sg:province":"QC",
    "sg:tags":[
        "engineer"
    ],
    "wof:name":"Ruesecure",
    "wof:placetype":"venue"
},
  "geometry": {"coordinates":[-71.246971,46.806038],"type":"Point"}
}