{
  "type": "Feature",
  "properties": {
    "addr:full":"Toronto ON M6J 1X2",
    "addr:postcode":"m6j 1x2",
    "iso:country":"CA",
    "sg:city":"Toronto",
    "sg:classifiers":[
        {
            "category":"Professional",
            "subcategory":"Business Services",
            "type":"Services"
        }
    ],
    "sg:phone":"+1 416 532 2845",
    "sg:postcode":"M6J 1X2",
    "sg:province":"ON",
    "sg:tags":[
        "drafting"
    ],
    "wof:name":"G Bettencourt Designs Ltd",
    "wof:placetype":"venue"
},
  "geometry": {"coordinates":[-79.419899,43.649643],"type":"Point"}
}