{
  "type": "Feature",
  "properties": {
    "addr:full":"1346 Queen St E Toronto ON M4L 1C5",
    "addr:housenumber":"1346",
    "addr:postcode":"m4l 1c5",
    "addr:street":"Queen St E",
    "iso:country":"CA",
    "sg:address":"1346 Queen St E",
    "sg:city":"Toronto",
    "sg:classifiers":[
        {
            "category":"Food & Beverages",
            "subcategory":"Bakery",
            "type":"Retail Goods"
        }
    ],
    "sg:phone":"+1 416 461 7519",
    "sg:postcode":"M4L 1C5",
    "sg:province":"ON",
    "sg:tags":[
        "baker"
    ],
    "wof:name":"Altitude Baking",
    "wof:placetype":"venue"
},
  "geometry": {"coordinates":[-79.32646200000001,43.664246],"type":"Point"}
}