{
  "type": "Feature",
  "properties": {
    "addr:full":"York ON M6M 1T5",
    "addr:postcode":"m6m 1t5",
    "iso:country":"CA",
    "sg:city":"York",
    "sg:classifiers":[
        {
            "category":"Health Services",
            "subcategory":"Doctor",
            "type":"Services"
        }
    ],
    "sg:phone":"+1 416 651 5111",
    "sg:postcode":"M6M 1T5",
    "sg:province":"ON",
    "sg:tags":[
        "physician",
        "surgeon"
    ],
    "wof:name":"Fenton, Brian MD",
    "wof:placetype":"venue"
},
  "geometry": {"coordinates":[-79.4733657837,43.6906700134],"type":"Point"}
}