{
  "type": "Feature",
  "properties": {
    "iso:country":"CA",
    "sg:address":"130 Albert St #501",
    "sg:city":"Ottawa",
    "sg:classifiers":[
        {
            "category":"Health Services",
            "subcategory":"Doctor",
            "type":"Services"
        }
    ],
    "sg:phone":"+1 613 232 3883",
    "sg:postcode":"K1P 5G4",
    "sg:province":"ON",
    "sg:tags":[
        "dentist"
    ],
    "wof:name":"Izzard, John A DDS",
    "wof:placetype":"venue"
},
  "geometry": {"coordinates":[-75.697395,45.421055],"type":"Point"}
}