{
  "type": "Feature",
  "properties": {
    "addr:full":"167 Rue Fleury O Montreal QC H3L 1T6",
    "addr:housenumber":"167",
    "addr:postcode":"h3l 1t6",
    "addr:street":"Rue Fleury O",
    "iso:country":"CA",
    "sg:address":"167 Rue Fleury O",
    "sg:city":"Montreal",
    "sg:classifiers":[
        {
            "category":"Personal",
            "subcategory":"Beauty Salon",
            "type":"Services"
        }
    ],
    "sg:phone":"+1 514 858 5178",
    "sg:postcode":"H3L 1T6",
    "sg:province":"QC",
    "wof:name":"Institut DE Beaute Corps & Ame",
    "wof:placetype":"venue"
},
  "geometry": {"coordinates":[-73.66436,45.549633],"type":"Point"}
}