{
  "type": "Feature",
  "properties": {
    "addr:full":"Renfrew ON K7V 4G1",
    "addr:postcode":"k7v 4g1",
    "iso:country":"CA",
    "sg:city":"Renfrew",
    "sg:classifiers":[
        {
            "category":"Health Services",
            "subcategory":"Doctor",
            "type":"Services"
        }
    ],
    "sg:phone":"+1 613 432 4864",
    "sg:postcode":"K7V 4G1",
    "sg:province":"ON",
    "sg:tags":[
        "dentist"
    ],
    "wof:name":"Mac Donald, Alasbair DDS",
    "wof:placetype":"venue"
},
  "geometry": {"coordinates":[-76.68367004389999,45.4699401855],"type":"Point"}
}