{
  "type": "Feature",
  "properties": {
    "addr:full":"61 Mcinnis Rd Whycocomagh NS B0E 3M0",
    "addr:housenumber":"61",
    "addr:postcode":"b0e 3m0",
    "addr:street":"Mcinnis Rd",
    "iso:country":"CA",
    "sg:address":"61 Mcinnis Rd",
    "sg:city":"Whycocomagh",
    "sg:classifiers":[
        {
            "category":"Wholesale",
            "subcategory":"Machinery & Supplies",
            "type":"Manufacturing & Wholesale Goods"
        }
    ],
    "sg:phone":"+1 902 756 2665",
    "sg:postcode":"B0E 3M0",
    "sg:province":"NS",
    "sg:tags":[
        "salon",
        "beauty"
    ],
    "wof:name":"Cosmetology Essentials CO Ltd",
    "wof:placetype":"venue"
},
  "geometry": {"coordinates":[-61.125492,45.975029],"type":"Point"}
}