{
  "type": "Feature",
  "properties": {
    "addr:full":"West Vancouver BC V7V 1A4",
    "addr:postcode":"v7v 1a4",
    "iso:country":"CA",
    "sg:city":"West Vancouver",
    "sg:classifiers":[
        {
            "category":"Banks & Credit Unions",
            "subcategory":"Investment Brokerage",
            "type":"Services"
        }
    ],
    "sg:phone":"+1 604 926 8707",
    "sg:postcode":"V7V 1A4",
    "sg:province":"BC",
    "wof:name":"Resource Capital Corp",
    "wof:placetype":"venue"
},
  "geometry": {"coordinates":[-123.17079925500001,49.3287315369],"type":"Point"}
}