{
  "type": "Feature",
  "properties": {
    "addr:full":"Mont-Royal QC H4P 1P7",
    "addr:postcode":"h4p 1p7",
    "iso:country":"CA",
    "sg:city":"Mont-Royal",
    "sg:classifiers":[
        {
            "category":"Wholesale",
            "subcategory":"Groceries",
            "type":"Manufacturing & Wholesale Goods"
        }
    ],
    "sg:phone":"+1 514 731 2299",
    "sg:postcode":"H4P 1P7",
    "sg:province":"QC",
    "sg:tags":[
        "food",
        "broker"
    ],
    "wof:name":"Agritrade International",
    "wof:placetype":"venue"
},
  "geometry": {"coordinates":[-73.658417,45.493988],"type":"Point"}
}