{
  "type": "Feature",
  "properties": {
    "addr:full":"340 Wellington St Port Colborne ON L3K 2K6",
    "addr:housenumber":"340",
    "addr:postcode":"l3k 2k6",
    "addr:street":"Wellington St",
    "iso:country":"CA",
    "sg:address":"340 Wellington St",
    "sg:city":"Port Colborne",
    "sg:classifiers":[
        {
            "category":"Real Estate",
            "subcategory":"Real Estate Operator",
            "type":"Services"
        }
    ],
    "sg:phone":"+1 905 834 5808",
    "sg:postcode":"L3K 2K6",
    "sg:province":"ON",
    "sg:tags":[
        "apartment"
    ],
    "wof:name":"South Niagara Gateway Family",
    "wof:placetype":"venue"
},
  "geometry": {"coordinates":[-79.240433,42.901138],"type":"Point"}
}