{
  "type": "Feature",
  "properties": {
    "addr:full":"648 Mckellar St Peterborough ON K9J 1R3",
    "addr:housenumber":"648",
    "addr:postcode":"k9j 1r3",
    "addr:street":"Mckellar St",
    "iso:country":"CA",
    "sg:address":"648 Mckellar St",
    "sg:city":"Peterborough",
    "sg:classifiers":[
        {
            "category":"Personal",
            "subcategory":"Beauty Salon",
            "type":"Services"
        }
    ],
    "sg:phone":"+1 705 741 2267",
    "sg:postcode":"K9J 1R3",
    "sg:province":"ON",
    "sg:tags":[
        "hair",
        "removing"
    ],
    "wof:name":"Alexandria Body Sugaring",
    "wof:placetype":"venue"
},
  "geometry": {"coordinates":[-78.328293,44.279552],"type":"Point"}
}