{
  "type": "Feature",
  "properties": {
    "addr:full":"7633 Ch DE Chambly Saint-Hubert QC J3Y 5K2",
    "addr:postcode":"7633;j3y 5k2",
    "addr:street":"Ch De Chambly",
    "iso:country":"CA",
    "sg:address":"7633 Ch DE Chambly",
    "sg:city":"Saint-Hubert",
    "sg:classifiers":[
        {
            "category":"Retail",
            "subcategory":"Animal Services",
            "type":"Services"
        }
    ],
    "sg:phone":"+1 450 926 0770",
    "sg:postcode":"J3Y 5K2",
    "sg:province":"QC",
    "sg:tags":[
        "pet",
        "grooming",
        "washing"
    ],
    "wof:name":"Boule DE Poils",
    "wof:placetype":"venue"
},
  "geometry": {"coordinates":[-73.3870773315,45.4892311096],"type":"Point"}
}