{
  "type": "Feature",
  "properties": {
    "addr:full":"1430 Rue DE LA Montagne Montreal QC H3G 1Z5",
    "addr:housenumber":"1430",
    "addr:postcode":"h3g 1z5",
    "addr:street":"Rue De La Montagne",
    "iso:country":"CA",
    "sg:address":"1430 Rue DE LA Montagne",
    "sg:city":"Montreal",
    "sg:classifiers":[
        {
            "category":"Restaurant",
            "type":"Food & Drink"
        }
    ],
    "sg:phone":"+1 514 281 5340",
    "sg:postcode":"H3G 1Z5",
    "sg:province":"QC",
    "wof:name":"Restaurant Le Lutetia",
    "wof:placetype":"venue"
},
  "geometry": {"coordinates":[-73.57575199999999,45.498096],"type":"Point"}
}