{
  "type": "Feature",
  "properties": {
    "addr:full":"RR 3 Eckville AB T0M 0X0",
    "addr:postcode":"t0m 0x0",
    "addr:street":"Rr 3",
    "iso:country":"CA",
    "sg:address":"RR 3",
    "sg:city":"Eckville",
    "sg:classifiers":[
        {
            "category":"Farming",
            "subcategory":"Farm",
            "type":"Manufacturing & Wholesale Goods"
        }
    ],
    "sg:phone":"+1 403 746 5737",
    "sg:postcode":"T0M 0X0",
    "sg:province":"AB",
    "wof:name":"Stauffer Farm Feedlot",
    "wof:placetype":"venue"
},
  "geometry": {"coordinates":[-114.361465,52.359573],"type":"Point"}
}