{
  "type": "Feature",
  "properties": {
    "addr:full":"Peterborough ON K9J 3H2",
    "addr:postcode":"k9j 3h2",
    "iso:country":"CA",
    "sg:city":"Peterborough",
    "sg:classifiers":[
        {
            "category":"Professional",
            "subcategory":"Employment Agencies",
            "type":"Services"
        }
    ],
    "sg:phone":"+1 705 760 9111",
    "sg:postcode":"K9J 3H2",
    "sg:province":"ON",
    "sg:tags":[
        "help",
        "contractor"
    ],
    "wof:name":"Labour Ready Temporary Svc",
    "wof:placetype":"venue"
},
  "geometry": {"coordinates":[-78.319633,44.302765],"type":"Point"}
}