{
  "type": "Feature",
  "properties": {
    "addr:full":"445 Winnipeg St Regina SK S4R 8P2",
    "addr:housenumber":"445",
    "addr:postcode":"s4r 8p2",
    "addr:street":"Winnipeg St",
    "iso:country":"CA",
    "sg:address":"445 Winnipeg St",
    "sg:city":"Regina",
    "sg:classifiers":[
        {
            "category":"Wholesale",
            "subcategory":"Groceries",
            "type":"Manufacturing & Wholesale Goods"
        }
    ],
    "sg:phone":"+1 306 546 5444",
    "sg:postcode":"S4R 8P2",
    "sg:province":"SK",
    "sg:tags":[
        "grocer"
    ],
    "wof:name":"Independent Choice Distri",
    "wof:placetype":"venue"
},
  "geometry": {"coordinates":[-104.59504699999999,50.471703],"type":"Point"}
}