{
  "type": "Feature",
  "properties": {
    "addr:full":"Burnaby BC V5C 6R5",
    "addr:postcode":"v5c 6r5",
    "iso:country":"CA",
    "sg:city":"Burnaby",
    "sg:classifiers":[
        {
            "category":"Health Services",
            "subcategory":"Doctor",
            "type":"Services"
        }
    ],
    "sg:phone":"+1 604 299 4010",
    "sg:postcode":"V5C 6R5",
    "sg:province":"BC",
    "sg:tags":[
        "dentist"
    ],
    "wof:name":"Madison Centre Dental",
    "wof:placetype":"venue"
},
  "geometry": {"coordinates":[-123.006058,49.267536],"type":"Point"}
}