{
  "type": "Feature",
  "properties": {
    "addr:full":"1612 Mountain Rd Moncton NB E1G 1A4",
    "addr:housenumber":"1612",
    "addr:postcode":"e1g 1a4",
    "addr:street":"Mountain Rd",
    "iso:country":"CA",
    "sg:address":"1612 Mountain Rd",
    "sg:city":"Moncton",
    "sg:classifiers":[
        {
            "category":"Shopping",
            "subcategory":"Computers & Home Electronics",
            "type":"Retail Goods"
        }
    ],
    "sg:phone":"+1 506 852 4291",
    "sg:postcode":"E1G 1A4",
    "sg:province":"NB",
    "sg:tags":[
        "equipment",
        "dealer"
    ],
    "wof:name":"Unison Digital Systems",
    "wof:placetype":"venue"
},
  "geometry": {"coordinates":[-64.8401107788,46.116809845],"type":"Point"}
}