{
  "type": "Feature",
  "properties": {
    "addr:full":"251 11th St E Prince Albert SK S6V 1A4",
    "addr:housenumber":"251",
    "addr:postcode":"s6v 1a4",
    "addr:street":"11Th St",
    "iso:country":"CA",
    "sg:address":"251 11th St E",
    "sg:city":"Prince Albert",
    "sg:classifiers":[
        {
            "category":"Manufacturing",
            "subcategory":"Printing",
            "type":"Manufacturing & Wholesale Goods"
        }
    ],
    "sg:phone":"+1 306 922 0000",
    "sg:postcode":"S6V 1A4",
    "sg:province":"SK",
    "sg:tags":[
        "printer"
    ],
    "wof:name":"Castle Printing",
    "wof:placetype":"venue"
},
  "geometry": {"coordinates":[-105.748069763,53.2029266357],"type":"Point"}
}