{
  "type": "Feature",
  "properties": {
    "iso:country":"CA",
    "sg:address":"1777 Rte Du Carrefour",
    "sg:city":"Val-Des-Monts",
    "sg:classifiers":[
        {
            "category":"Restaurant",
            "type":"Food & Drink"
        }
    ],
    "sg:phone":"+1 819 671 4848",
    "sg:postcode":"J8N 7M7",
    "sg:province":"QC",
    "wof:name":"Casse-Croute Mont-Valois",
    "wof:placetype":"venue"
},
  "geometry": {"coordinates":[-75.6170120239,45.59532547],"type":"Point"}
}