{
  "type": "Feature",
  "properties": {
    "addr:full":"48 Crockford Blvd Scarborough ON M1R 3C3",
    "addr:housenumber":"48",
    "addr:postcode":"m1r 3c3",
    "addr:street":"Crockford Blvd",
    "iso:country":"CA",
    "sg:address":"48 Crockford Blvd",
    "sg:city":"Scarborough",
    "sg:classifiers":[
        {
            "category":"Manufacturing",
            "subcategory":"Metals",
            "type":"Manufacturing & Wholesale Goods"
        }
    ],
    "sg:phone":"+1 416 752 6266",
    "sg:postcode":"M1R 3C3",
    "sg:province":"ON",
    "sg:tags":[
        "production",
        "grinding"
    ],
    "wof:name":"Ingadale Industries Inc",
    "wof:placetype":"venue"
},
  "geometry": {"coordinates":[-79.288292,43.739029],"type":"Point"}
}