{
  "type": "Feature",
  "properties": {
    "addr:full":"Oshawa ON L1J 2J9",
    "addr:postcode":"l1j 2j9",
    "iso:country":"CA",
    "sg:city":"Oshawa",
    "sg:classifiers":[
        {
            "category":"Restaurant",
            "type":"Food & Drink"
        }
    ],
    "sg:phone":"+1 905 723 5951",
    "sg:postcode":"L1J 2J9",
    "sg:province":"ON",
    "wof:name":"Dines Family Restaurant",
    "wof:placetype":"venue"
},
  "geometry": {"coordinates":[-78.8781204224,43.8943519592],"type":"Point"}
}