{
  "type": "Feature",
  "properties": {
    "addr:full":"Whitecourt AB T7S 1N3",
    "addr:postcode":"t7s 1n3",
    "iso:country":"CA",
    "sg:city":"Whitecourt",
    "sg:classifiers":[
        {
            "category":"Organizations",
            "subcategory":"Religious Organization",
            "type":"Services"
        }
    ],
    "sg:phone":"+1 780 778 2572",
    "sg:postcode":"T7S 1N3",
    "sg:province":"AB",
    "sg:tags":[
        "church"
    ],
    "wof:name":"Family Worship Centre",
    "wof:placetype":"venue"
},
  "geometry": {"coordinates":[-115.70787799999999,54.139435],"type":"Point"}
}