{
  "type": "Feature",
  "properties": {
    "addr:full":"11 Boul Saint-Benoit O Amqui QC G5J 3S7",
    "addr:housenumber":"11",
    "addr:postcode":"g5j 3s7",
    "addr:street":"Boul Saint-Benoit O",
    "iso:country":"CA",
    "sg:address":"11 Boul Saint-Benoit O",
    "sg:city":"Amqui",
    "sg:classifiers":[
        {
            "category":"Professional",
            "subcategory":"Accounting & Tax Preparation",
            "type":"Services"
        }
    ],
    "sg:phone":"+1 418 629 2495",
    "sg:postcode":"G5J 3S7",
    "sg:province":"QC",
    "sg:tags":[
        "accountant"
    ],
    "wof:name":"Services Informatiques L'Est",
    "wof:placetype":"venue"
},
  "geometry": {"coordinates":[-67.424919,48.464378],"type":"Point"}
}