{
  "type": "Feature",
  "properties": {
    "addr:full":"4870 Boul Bourque Rock Forest QC J1N 3S5",
    "addr:housenumber":"4870",
    "addr:postcode":"j1n 3s5",
    "addr:street":"Boul Bourque",
    "iso:country":"CA",
    "sg:address":"4870 Boul Bourque",
    "sg:city":"Rock Forest",
    "sg:classifiers":[
        {
            "category":"Health Services",
            "subcategory":"Doctor",
            "type":"Services"
        }
    ],
    "sg:phone":"+1 819 820 2827",
    "sg:postcode":"J1N 3S5",
    "sg:province":"QC",
    "sg:tags":[
        "x",
        "surgeon",
        "physician"
    ],
    "wof:name":"Centre Radiologique DE L'Estri",
    "wof:placetype":"venue"
},
  "geometry": {"coordinates":[-71.986931,45.371716],"type":"Point"}
}