{
  "type": "Feature",
  "properties": {
    "addr:full":"1800 17th St E Owen Sound ON N4K 5Z9",
    "addr:housenumber":"1800",
    "addr:postcode":"n4k 5z9",
    "addr:street":"17Th St E",
    "iso:country":"CA",
    "sg:address":"1800 17th St E",
    "sg:city":"Owen Sound",
    "sg:classifiers":[
        {
            "category":"Wholesale",
            "subcategory":"Auto Parts",
            "type":"Manufacturing & Wholesale Goods"
        }
    ],
    "sg:phone":"+1 519 376 9650",
    "sg:postcode":"N4K 5Z9",
    "sg:province":"ON",
    "sg:tags":[
        "automobile",
        "supply"
    ],
    "wof:name":"Tenneco Canada Inc",
    "wof:placetype":"venue"
},
  "geometry": {"coordinates":[-80.909401,44.577106],"type":"Point"}
}