{
  "type": "Feature",
  "properties": {
    "addr:full":"11 Main St Ashern MB R0C 0E0",
    "addr:housenumber":"11",
    "addr:postcode":"r0c 0e0",
    "addr:street":"Main St",
    "iso:country":"CA",
    "sg:address":"11 Main St",
    "sg:city":"Ashern",
    "sg:classifiers":[
        {
            "category":"Health Services",
            "subcategory":"Chiropractor",
            "type":"Services"
        }
    ],
    "sg:phone":"+1 204 768 3319",
    "sg:postcode":"R0C 0E0",
    "sg:province":"MB",
    "wof:name":"Palaschuk, Greg DC",
    "wof:placetype":"venue"
},
  "geometry": {"coordinates":[-98.350266,51.180805],"type":"Point"}
}