{
  "type": "Feature",
  "properties": {
    "addr:full":"17 Riverside St W Listuguj QC G0C 2R0",
    "addr:housenumber":"17",
    "addr:postcode":"g0c 2r0",
    "addr:street":"Riverside St W",
    "iso:country":"CA",
    "sg:address":"17 Riverside St W",
    "sg:city":"Listuguj",
    "sg:classifiers":[
        {
            "category":"Organizations",
            "subcategory":"Professional Association",
            "type":"Services"
        }
    ],
    "sg:phone":"+1 418 788 2136",
    "sg:postcode":"G0C 2R0",
    "sg:province":"QC",
    "wof:name":"Listuguj Mi'Mgaq First Nation",
    "wof:placetype":"venue"
},
  "geometry": {"coordinates":[-66.6985092163,48.0124664307],"type":"Point"}
}