{
  "type": "Feature",
  "properties": {
    "addr:full":"521 Industrial Rd Brooks AB T1R 1C7",
    "addr:housenumber":"521",
    "addr:postcode":"t1r 1c7",
    "addr:street":"Industrial Rd",
    "iso:country":"CA",
    "sg:address":"521 Industrial Rd",
    "sg:city":"Brooks",
    "sg:classifiers":[
        {
            "category":"Building & Trades",
            "subcategory":"Construction",
            "type":"Services"
        }
    ],
    "sg:phone":"+1 403 362 4181",
    "sg:postcode":"T1R 1C7",
    "sg:province":"AB",
    "wof:name":"Big Foot Metal Systems Ltd",
    "wof:placetype":"venue"
},
  "geometry": {"coordinates":[-111.887497,50.553707],"type":"Point"}
}