{
  "type": "Feature",
  "properties": {
    "addr:full":"180 Elizabeth St Stratford ON N5A 4Z3",
    "addr:housenumber":"180",
    "addr:postcode":"n5a 4z3",
    "addr:street":"Elizabeth St",
    "iso:country":"CA",
    "sg:address":"180 Elizabeth St",
    "sg:city":"Stratford",
    "sg:classifiers":[
        {
            "category":"Travel",
            "subcategory":"Hotels & Motels",
            "type":"Entertainment"
        }
    ],
    "sg:phone":"+1 519 273 6393",
    "sg:postcode":"N5A 4Z3",
    "sg:province":"ON",
    "sg:tags":[
        "breakfast",
        "accommodation",
        "bed"
    ],
    "wof:name":"Spindles",
    "wof:placetype":"venue"
},
  "geometry": {"coordinates":[-80.977852,43.376778],"type":"Point"}
}