{
  "type": "Feature",
  "properties": {
    "iso:country":"CA",
    "sg:address":"3561 Rue Georges-Corbeil",
    "sg:city":"Terrebonne",
    "sg:classifiers":[
        {
            "category":"Home & Garden",
            "subcategory":"Building Materials",
            "type":"Retail Goods"
        }
    ],
    "sg:phone":"+1 450 968 2220",
    "sg:postcode":"J6X 4J5",
    "sg:province":"QC",
    "sg:tags":[
        "plate",
        "window",
        "glazier"
    ],
    "wof:name":"Maison Du Verre DE L'Est Enr",
    "wof:placetype":"venue"
},
  "geometry": {"coordinates":[-73.67659759519999,45.7267379761],"type":"Point"}
}