{
  "type": "Feature",
  "properties": {
    "addr:full":"Likely BC V0L 1N0",
    "addr:postcode":"v0l 1n0",
    "iso:country":"CA",
    "sg:city":"Likely",
    "sg:classifiers":[
        {
            "category":"Mining & Drilling",
            "type":"Manufacturing & Wholesale Goods"
        }
    ],
    "sg:phone":"+1 250 790 2215",
    "sg:postcode":"V0L 1N0",
    "sg:province":"BC",
    "sg:tags":[
        "company"
    ],
    "wof:name":"Mount Polley Mining Corp",
    "wof:placetype":"venue"
},
  "geometry": {"coordinates":[-121.569847,52.617023],"type":"Point"}
}