{
  "type": "Feature",
  "properties": {
    "iso:country":"CA",
    "sg:address":"123522 Story Book Park Rd",
    "sg:city":"Owen Sound",
    "sg:classifiers":[
        {
            "category":"Retail",
            "subcategory":"Auto Repair",
            "type":"Services"
        }
    ],
    "sg:phone":"+1 519 371 6965",
    "sg:postcode":"N4K 5N8",
    "sg:province":"ON",
    "sg:tags":[
        "automobile",
        "testing",
        "emission"
    ],
    "wof:name":"Pure Air Mobile Emission Test",
    "wof:placetype":"venue"
},
  "geometry": {"coordinates":[-80.9426040649,44.5648765564],"type":"Point"}
}