{
  "type": "Feature",
  "properties": {
    "addr:full":"902 33rd St W Saskatoon SK S7L 0W6",
    "addr:housenumber":"902",
    "addr:postcode":"s7l 0w6",
    "addr:street":"33Rd St W",
    "iso:country":"CA",
    "sg:address":"902 33rd St W",
    "sg:city":"Saskatoon",
    "sg:classifiers":[
        {
            "category":"Organizations",
            "subcategory":"Religious Organization",
            "type":"Services"
        }
    ],
    "sg:phone":"+1 306 382 6446",
    "sg:postcode":"S7L 0W6",
    "sg:province":"SK",
    "sg:tags":[
        "church"
    ],
    "wof:name":"Mayfair United Church",
    "wof:placetype":"venue"
},
  "geometry": {"coordinates":[-106.683044,52.143929],"type":"Point"}
}