{
  "type": "Feature",
  "properties": {
    "iso:country":"CA",
    "sg:city":"Gatineau",
    "sg:classifiers":[
        {
            "category":"Building & Trades",
            "subcategory":"Construction",
            "type":"Services"
        }
    ],
    "sg:phone":"+1 819 243 4115",
    "sg:postcode":"J8T 8G8",
    "sg:province":"QC",
    "sg:tags":[
        "roofing",
        "contractor"
    ],
    "wof:name":"Entreprises Berube Inc",
    "wof:placetype":"venue"
},
  "geometry": {"coordinates":[-75.70714569090001,45.4908332825],"type":"Point"}
}