{
  "type": "Feature",
  "properties": {
    "addr:full":"411 Elgin St Brantford ON N3S 7P5",
    "addr:housenumber":"411",
    "addr:postcode":"n3s 7p5",
    "addr:street":"Elgin St",
    "iso:country":"CA",
    "sg:address":"411 Elgin St",
    "sg:city":"Brantford",
    "sg:classifiers":[
        {
            "category":"Education",
            "subcategory":"College",
            "type":"Public Place"
        }
    ],
    "sg:phone":"+1 519 759 7200",
    "sg:postcode":"N3S 7P5",
    "sg:province":"ON",
    "sg:tags":[
        "academic",
        "school"
    ],
    "wof:name":"Mohawk College",
    "wof:placetype":"venue"
},
  "geometry": {"coordinates":[-80.2276,43.151894],"type":"Point"}
}