{
  "type": "Feature",
  "properties": {
    "addr:full":"8611 Weston Rd # 5 Woodbridge ON L4L 9P1",
    "addr:housenumber":"8611",
    "addr:postcode":"l4l 9p1",
    "addr:street":"Weston Rd # 5",
    "iso:country":"CA",
    "sg:address":"8611 Weston Rd # 5",
    "sg:city":"Woodbridge",
    "sg:classifiers":[
        {
            "category":"Retail",
            "subcategory":"Veterinary Services",
            "type":"Services"
        }
    ],
    "sg:phone":"+1 905 264 6085",
    "sg:postcode":"L4L 9P1",
    "sg:province":"ON",
    "sg:tags":[
        "veterinarian"
    ],
    "wof:name":"Northview Pet Hospital",
    "wof:placetype":"venue"
},
  "geometry": {"coordinates":[-79.55239899999999,43.810978],"type":"Point"}
}