{
  "type": "Feature",
  "properties": {
    "addr:full":"2303 Rue Beaubien E Montreal QC H2G 1N1",
    "addr:housenumber":"2303",
    "addr:postcode":"h2g 1n1",
    "addr:street":"Rue Beaubien E",
    "iso:country":"CA",
    "sg:address":"2303 Rue Beaubien E",
    "sg:city":"Montreal",
    "sg:classifiers":[
        {
            "category":"Banks & Credit Unions",
            "subcategory":"Bank",
            "type":"Services"
        }
    ],
    "sg:phone":"+1 514 394 5555",
    "sg:postcode":"H2G 1N1",
    "sg:province":"QC",
    "wof:name":"Banque National Du Canada",
    "wof:placetype":"venue"
},
  "geometry": {"coordinates":[-73.593338,45.547089],"type":"Point"}
}