{
  "type": "Feature",
  "properties": {
    "addr:full":"5250 Rue Ferrier # 505 Montreal QC H4P 1L4",
    "addr:housenumber":"5250",
    "addr:postcode":"h4p 1l4",
    "addr:street":"Rue Ferrier # 505",
    "iso:country":"CA",
    "sg:address":"5250 Rue Ferrier # 505",
    "sg:city":"Montreal",
    "sg:classifiers":[
        {
            "category":"Professional",
            "subcategory":"Accounting & Tax Preparation",
            "type":"Services"
        }
    ],
    "sg:phone":"+1 514 341 4230",
    "sg:postcode":"H4P 1L4",
    "sg:province":"QC",
    "sg:tags":[
        "accountant"
    ],
    "wof:name":"Levitt Feldstein Dubin Epstein",
    "wof:placetype":"venue"
},
  "geometry": {"coordinates":[-73.6567764282,45.4981155396],"type":"Point"}
}