{
  "type": "Feature",
  "properties": {
    "addr:full":"264 8th St Brandon MB R7A 3X3",
    "addr:housenumber":"264",
    "addr:postcode":"r7a 3x3",
    "addr:street":"8Th St",
    "iso:country":"CA",
    "sg:address":"264 8th St",
    "sg:city":"Brandon",
    "sg:classifiers":[
        {
            "category":"Personal",
            "subcategory":"Beauty Salon",
            "type":"Services"
        }
    ],
    "sg:phone":"+1 204 571 6145",
    "sg:postcode":"R7A 3X3",
    "sg:province":"MB",
    "wof:name":"Total Eclipse Hair Studio",
    "wof:placetype":"venue"
},
  "geometry": {"coordinates":[-99.948936,49.845943],"type":"Point"}
}