{
  "type": "Feature",
  "properties": {
    "addr:full":"324 North Front St Belleville ON K8P 3C5",
    "addr:housenumber":"324",
    "addr:postcode":"k8p 3c5",
    "addr:street":"North Front St",
    "iso:country":"CA",
    "sg:address":"324 North Front St",
    "sg:city":"Belleville",
    "sg:classifiers":[
        {
            "category":"Home & Garden",
            "subcategory":"Furniture",
            "type":"Retail Goods"
        }
    ],
    "sg:phone":"+1 613 966 7024",
    "sg:postcode":"K8P 3C5",
    "sg:province":"ON",
    "sg:tags":[
        "bedding"
    ],
    "wof:name":"Master Bedroom Inc",
    "wof:placetype":"venue"
},
  "geometry": {"coordinates":[-77.395149231,44.1854248047],"type":"Point"}
}