{
  "type": "Feature",
  "properties": {
    "addr:full":"401 Boul Sainte-Anne Sainte-Anne-Des-Plaines QC J0N 1H0",
    "addr:housenumber":"401",
    "addr:postcode":"j0n 1h0",
    "addr:street":"Boul Sainte-Anne",
    "iso:country":"CA",
    "sg:address":"401 Boul Sainte-Anne",
    "sg:city":"Sainte-Anne-Des-Plaines",
    "sg:classifiers":[
        {
            "category":"Manufacturing",
            "subcategory":"Metals",
            "type":"Manufacturing & Wholesale Goods"
        }
    ],
    "sg:phone":"+1 450 838 8055",
    "sg:postcode":"J0N 1H0",
    "sg:province":"QC",
    "sg:tags":[
        "repairing",
        "temporary",
        "shelter",
        "boot",
        "garage",
        "shoe"
    ],
    "wof:name":"Cordonnerie Ste-Anne Inc",
    "wof:placetype":"venue"
},
  "geometry": {"coordinates":[-73.8144454956,45.7602043152],"type":"Point"}
}