{
  "type": "Feature",
  "properties": {
    "addr:full":"647 Des Pionniers Ave Balmoral NB E8E 1B3",
    "addr:housenumber":"647",
    "addr:postcode":"e8e 1b3",
    "addr:street":"Des Pionniers Ave",
    "iso:country":"CA",
    "sg:address":"647 Des Pionniers Ave",
    "sg:city":"Balmoral",
    "sg:classifiers":[
        {
            "category":"Food & Beverages",
            "subcategory":"Groceries & Convenience Stores",
            "type":"Retail Goods"
        }
    ],
    "sg:phone":"+1 506 826 2545",
    "sg:postcode":"E8E 1B3",
    "sg:province":"NB",
    "sg:tags":[
        "grocer"
    ],
    "wof:name":"Save Easy Belmoral",
    "wof:placetype":"venue"
},
  "geometry": {"coordinates":[-66.416344,47.980465],"type":"Point"}
}