{
  "type": "Feature",
  "properties": {
    "addr:full":"46345 Yale Rd Chilliwack BC V2P 2P8",
    "addr:housenumber":"46345",
    "addr:postcode":"v2p 2p8",
    "addr:street":"Yale Rd",
    "iso:country":"CA",
    "sg:address":"46345 Yale Rd",
    "sg:city":"Chilliwack",
    "sg:classifiers":[
        {
            "category":"Food & Beverages",
            "subcategory":"Bakery",
            "type":"Retail Goods"
        }
    ],
    "sg:phone":"+1 604 792 1300",
    "sg:postcode":"V2P 2P8",
    "sg:province":"BC",
    "sg:tags":[
        "doughnut"
    ],
    "wof:name":"Tim Horton's",
    "wof:placetype":"venue"
},
  "geometry": {"coordinates":[-121.943939,49.174271],"type":"Point"}
}