{
  "type": "Feature",
  "properties": {
    "addr:full":"81 Charles St W Ingersoll ON N5C 2L7",
    "addr:housenumber":"81",
    "addr:postcode":"n5c 2l7",
    "addr:street":"Charles St W",
    "iso:country":"CA",
    "sg:address":"81 Charles St W",
    "sg:city":"Ingersoll",
    "sg:classifiers":[
        {
            "category":"Health Services",
            "subcategory":"Doctor",
            "type":"Services"
        }
    ],
    "sg:phone":"+1 519 485 3810",
    "sg:postcode":"N5C 2L7",
    "sg:province":"ON",
    "sg:tags":[
        "physician",
        "surgeon"
    ],
    "wof:name":"Pariser, Marc MD",
    "wof:placetype":"venue"
},
  "geometry": {"coordinates":[-80.886276,43.037846],"type":"Point"}
}