{
  "type": "Feature",
  "properties": {
    "addr:full":"9856 Cawley St Chilliwack BC V2P 4K9",
    "addr:housenumber":"9856",
    "addr:postcode":"v2p 4k9",
    "addr:street":"Cawley St",
    "iso:country":"CA",
    "sg:address":"9856 Cawley St",
    "sg:city":"Chilliwack",
    "sg:classifiers":[
        {
            "category":"Building & Trades",
            "subcategory":"Cleaning & Sanitation",
            "type":"Services"
        }
    ],
    "sg:phone":"+1 604 792 1923",
    "sg:postcode":"V2P 4K9",
    "sg:province":"BC",
    "sg:tags":[
        "janitor"
    ],
    "wof:name":"Ke-San Janitorial Svc",
    "wof:placetype":"venue"
},
  "geometry": {"coordinates":[-121.954193,49.181053],"type":"Point"}
}