{
  "type": "Feature",
  "properties": {
    "iso:country":"CA",
    "sg:address":"1194 Oxford St E",
    "sg:city":"London",
    "sg:classifiers":[
        {
            "category":"Autos & Motor Vehicles",
            "subcategory":"Automobile Sales",
            "type":"Retail Goods"
        }
    ],
    "sg:phone":"+1 519 455 7771",
    "sg:postcode":"N5Y 3M3",
    "sg:province":"ON",
    "sg:tags":[
        "car",
        "dealer"
    ],
    "wof:name":"Oxford Motors",
    "wof:placetype":"venue"
},
  "geometry": {"coordinates":[-81.212944,43.007328],"type":"Point"}
}