{
  "type": "Feature",
  "properties": {
    "iso:country":"CA",
    "sg:address":"2100 Av Saint-Edouard",
    "sg:city":"Plessisville",
    "sg:classifiers":[
        {
            "category":"Wholesale",
            "subcategory":"Auto Parts",
            "type":"Manufacturing & Wholesale Goods"
        }
    ],
    "sg:phone":"+1 819 362 6321",
    "sg:postcode":"G6L 2L4",
    "sg:province":"QC",
    "sg:tags":[
        "automobile",
        "supply"
    ],
    "wof:name":"Freins Demarreurs Plessis Inc",
    "wof:placetype":"venue"
},
  "geometry": {"coordinates":[-71.7793426514,46.2243423462],"type":"Point"}
}