{
  "type": "Feature",
  "properties": {
    "iso:country":"CA",
    "sg:city":"Montreal",
    "sg:classifiers":[
        {
            "category":"Mining & Drilling",
            "type":"Manufacturing & Wholesale Goods"
        }
    ],
    "sg:phone":"+1 514 866 6500",
    "sg:postcode":"H3B 2N2",
    "sg:province":"QC",
    "sg:tags":[
        "company",
        "mine"
    ],
    "wof:name":"Northern Mining Explorations",
    "wof:placetype":"venue"
},
  "geometry": {"coordinates":[-73.553627,45.515373],"type":"Point"}
}