{
  "type": "Feature",
  "properties": {
    "addr:full":"Magog QC J1X 1T5",
    "addr:postcode":"j1x 1t5",
    "iso:country":"CA",
    "sg:city":"Magog",
    "sg:classifiers":[
        {
            "category":"Shopping",
            "subcategory":"Pharmacy",
            "type":"Retail Goods"
        }
    ],
    "sg:phone":"+1 819 843 1773",
    "sg:postcode":"J1X 1T5",
    "sg:province":"QC",
    "wof:name":"Famili-Prix",
    "wof:placetype":"venue"
},
  "geometry": {"coordinates":[-72.144684,45.265751],"type":"Point"}
}