{
  "type": "Feature",
  "properties": {
    "addr:full":"1111 Rue DE Clarendon # A Quyon QC J0X 2V0",
    "addr:housenumber":"1111",
    "addr:postcode":"j0x 2v0",
    "addr:street":"Rue De Clarendon # A",
    "iso:country":"CA",
    "sg:address":"1111 Rue DE Clarendon # A",
    "sg:city":"Quyon",
    "sg:classifiers":[
        {
            "category":"Health Services",
            "subcategory":"Doctor",
            "type":"Services"
        }
    ],
    "sg:phone":"+1 819 458 2397",
    "sg:postcode":"J0X 2V0",
    "sg:province":"QC",
    "sg:tags":[
        "physician",
        "surgeon"
    ],
    "wof:name":"Croteau, Pascal MD",
    "wof:placetype":"venue"
},
  "geometry": {"coordinates":[-76.2334442139,45.5204238892],"type":"Point"}
}