{
  "type": "Feature",
  "properties": {
    "addr:full":"240 First Ave W North Bay ON P1B 3C1",
    "addr:housenumber":"240",
    "addr:postcode":"p1b 3c1",
    "addr:street":"First Ave W",
    "iso:country":"CA",
    "sg:address":"240 First Ave W",
    "sg:city":"North Bay",
    "sg:classifiers":[
        {
            "category":"Health Services",
            "subcategory":"Chiropractor",
            "type":"Services"
        }
    ],
    "sg:phone":"+1 705 472 2700",
    "sg:postcode":"P1B 3C1",
    "sg:province":"ON",
    "wof:name":"Nesterenko, G E DC",
    "wof:placetype":"venue"
},
  "geometry": {"coordinates":[-79.4625701904,46.3141517639],"type":"Point"}
}