{
  "type": "Feature",
  "properties": {
    "addr:full":"436 Dewdney Ave Regina SK S4N 0E9",
    "addr:housenumber":"436",
    "addr:postcode":"s4n 0e9",
    "addr:street":"Dewdney Ave",
    "iso:country":"CA",
    "sg:address":"436 Dewdney Ave",
    "sg:city":"Regina",
    "sg:classifiers":[
        {
            "category":"Restaurant",
            "type":"Food & Drink"
        }
    ],
    "sg:phone":"+1 306 757 1457",
    "sg:postcode":"S4N 0E9",
    "sg:province":"SK",
    "wof:name":"Happy Garden Restaurant",
    "wof:placetype":"venue"
},
  "geometry": {"coordinates":[-104.58711242699999,50.455291748],"type":"Point"}
}