{
  "type": "Feature",
  "properties": {
    "addr:full":"1103 Confederation Dr Port Coquitlam BC V3C 5Y6",
    "addr:housenumber":"1103",
    "addr:postcode":"v3c 5y6",
    "addr:street":"Confederation Dr",
    "iso:country":"CA",
    "sg:address":"1103 Confederation Dr",
    "sg:city":"Port Coquitlam",
    "sg:classifiers":[
        {
            "category":"Social Services",
            "subcategory":"Child Care",
            "type":"Services"
        }
    ],
    "sg:phone":"+1 604 942 1234",
    "sg:postcode":"V3C 5Y6",
    "sg:province":"BC",
    "wof:name":"Citadel Montessori Childcare",
    "wof:placetype":"venue"
},
  "geometry": {"coordinates":[-122.78591919,49.2320632935],"type":"Point"}
}