{
  "type": "Feature",
  "properties": {
    "addr:full":"50 Lennon Cres Saskatoon SK S7L 6K2",
    "addr:housenumber":"50",
    "addr:postcode":"s7l 6k2",
    "addr:street":"Lennon Cres",
    "iso:country":"CA",
    "sg:address":"50 Lennon Cres",
    "sg:city":"Saskatoon",
    "sg:classifiers":[
        {
            "category":"Building & Trades",
            "subcategory":"Landscaping Services",
            "type":"Services"
        }
    ],
    "sg:phone":"+1 306 382 5942",
    "sg:postcode":"S7L 6K2",
    "sg:province":"SK",
    "sg:tags":[
        "landscape",
        "contractor"
    ],
    "wof:name":"D & D Tree Stump Removal",
    "wof:placetype":"venue"
},
  "geometry": {"coordinates":[-106.740532,52.145855],"type":"Point"}
}