{
  "type": "Feature",
  "properties": {
    "iso:country":"CA",
    "sg:address":"2355 Skymark Avenue Suite 100",
    "sg:city":"Mississauga",
    "sg:classifiers":[
        {
            "category":"Manufacturing",
            "subcategory":"Electronics",
            "type":"Manufacturing & Wholesale Goods"
        }
    ],
    "sg:postcode":"L4W 4Y6",
    "sg:tags":[
        "peripherals",
        "mice",
        "keyboards",
        "speakers"
    ],
    "sg:website":"http://logitech.com",
    "wof:name":"Logitech",
    "wof:placetype":"venue"
},
  "geometry": {"coordinates":[-79.60423900000001,43.653647],"type":"Point"}
}