{
  "type": "Feature",
  "properties": {
    "addr:full":"284 Woodland Dr Oakville ON L6J 4W5",
    "addr:housenumber":"284",
    "addr:postcode":"l6j 4w5",
    "addr:street":"Woodland Dr",
    "iso:country":"CA",
    "sg:address":"284 Woodland Dr",
    "sg:city":"Oakville",
    "sg:classifiers":[
        {
            "category":"Professional",
            "subcategory":"Engineering",
            "type":"Services"
        }
    ],
    "sg:phone":"+1 905 339 2733",
    "sg:postcode":"L6J 4W5",
    "sg:province":"ON",
    "sg:tags":[
        "engineer"
    ],
    "wof:name":"Michael P Sudbury Consulting",
    "wof:placetype":"venue"
},
  "geometry": {"coordinates":[-79.648178,43.473705],"type":"Point"}
}