{
  "type": "Feature",
  "properties": {
    "addr:full":"1889 Boul Lionel-Bertrand Boisbriand QC J7H 1N8",
    "addr:housenumber":"1889",
    "addr:postcode":"j7h 1n8",
    "addr:street":"Boul Lionel-Bertrand",
    "iso:country":"CA",
    "sg:address":"1889 Boul Lionel-Bertrand",
    "sg:city":"Boisbriand",
    "sg:classifiers":[
        {
            "category":"Home & Garden",
            "subcategory":"Furniture",
            "type":"Retail Goods"
        }
    ],
    "sg:phone":"+1 450 437 3610",
    "sg:postcode":"J7H 1N8",
    "sg:province":"QC",
    "sg:tags":[
        "equipment",
        "kitchen",
        "cabinet"
    ],
    "wof:name":"Cuisines Dakkar Ltee",
    "wof:placetype":"venue"
},
  "geometry": {"coordinates":[-73.85573599999999,45.609524],"type":"Point"}
}