{
  "type": "Feature",
  "properties": {
    "iso:country":"CA",
    "sg:city":"Courtice",
    "sg:classifiers":[
        {
            "category":"Social Services",
            "subcategory":"Child Care",
            "type":"Services"
        }
    ],
    "sg:phone":"+1 905 433 0558",
    "sg:postcode":"L1E 2N3",
    "sg:province":"ON",
    "wof:name":"Wee Watch Private Home Daycare",
    "wof:placetype":"venue"
},
  "geometry": {"coordinates":[-78.7866897583,43.9075088501],"type":"Point"}
}