{
  "type": "Feature",
  "properties": {
    "addr:full":"Saint-Henri-DE-Levis QC G0R 3E0",
    "addr:postcode":"g0r 3e0",
    "iso:country":"CA",
    "sg:city":"Saint-Henri-DE-Levis",
    "sg:classifiers":[
        {
            "category":"Manufacturing",
            "subcategory":"Metals",
            "type":"Manufacturing & Wholesale Goods"
        }
    ],
    "sg:phone":"+1 418 882 2553",
    "sg:postcode":"G0R 3E0",
    "sg:province":"QC",
    "sg:tags":[
        "solder"
    ],
    "wof:name":"Soudure Dion Enr",
    "wof:placetype":"venue"
},
  "geometry": {"coordinates":[-71.070351,46.690098],"type":"Point"}
}