{
  "type": "Feature",
  "properties": {
    "addr:full":"3121 Arbutus St Vancouver BC V6J 3Z3",
    "addr:housenumber":"3121",
    "addr:postcode":"v6j 3z3",
    "addr:street":"Arbutus St",
    "iso:country":"CA",
    "sg:address":"3121 Arbutus St",
    "sg:city":"Vancouver",
    "sg:classifiers":[
        {
            "category":"Home & Garden",
            "subcategory":"Hardware",
            "type":"Retail Goods"
        }
    ],
    "sg:phone":"+1 604 738 3031",
    "sg:postcode":"V6J 3Z3",
    "sg:province":"BC",
    "wof:name":"Good Neighbor Hardware Ltd",
    "wof:placetype":"venue"
},
  "geometry": {"coordinates":[-123.15322876,49.2579612732],"type":"Point"}
}