{
  "type": "Feature",
  "properties": {
    "addr:full":"Saint-Philemon QC G0R 4A0",
    "addr:postcode":"g0r 4a0",
    "iso:country":"CA",
    "sg:city":"Saint-Philemon",
    "sg:classifiers":[
        {
            "category":"Retail",
            "subcategory":"Repair Shop",
            "type":"Services"
        }
    ],
    "sg:phone":"+1 418 469 3550",
    "sg:postcode":"G0R 4A0",
    "sg:province":"QC",
    "sg:tags":[
        "taxidermist"
    ],
    "wof:name":"Taxiderme Bellechasse Enr",
    "wof:placetype":"venue"
},
  "geometry": {"coordinates":[-70.482765,46.699955],"type":"Point"}
}