{
  "type": "Feature",
  "properties": {
    "addr:full":"4925 45 St Yellowknife NT X1A 1K6",
    "addr:housenumber":"4925",
    "addr:postcode":"x1a 1k6",
    "addr:street":"45 St",
    "iso:country":"CA",
    "sg:address":"4925 45 St",
    "sg:city":"Yellowknife",
    "sg:classifiers":[
        {
            "category":"Social Services",
            "type":"Services"
        }
    ],
    "sg:phone":"+1 867 920 4673",
    "sg:postcode":"X1A 1K6",
    "sg:province":"NT",
    "sg:tags":[
        "organization",
        "welfare"
    ],
    "wof:name":"Salvation Army",
    "wof:placetype":"venue"
},
  "geometry": {"coordinates":[-114.36718,62.457623],"type":"Point"}
}