{
  "type": "Feature",
  "properties": {
    "addr:full":"634 Broadway Ave Saskatoon SK S7N 1A9",
    "addr:housenumber":"634",
    "addr:postcode":"s7n 1a9",
    "addr:street":"Broadway Ave",
    "iso:country":"CA",
    "sg:address":"634 Broadway Ave",
    "sg:city":"Saskatoon",
    "sg:classifiers":[
        {
            "category":"Shopping",
            "subcategory":"Jewelry",
            "type":"Retail Goods"
        }
    ],
    "sg:phone":"+1 306 664 3144",
    "sg:postcode":"S7N 1A9",
    "sg:province":"SK",
    "sg:tags":[
        "shop",
        "gift"
    ],
    "wof:name":"Alter Nations",
    "wof:placetype":"venue"
},
  "geometry": {"coordinates":[-106.656998,52.119431],"type":"Point"}
}