{
  "type": "Feature",
  "properties": {
    "addr:full":"Rimouski-Est QC G5L 7M9",
    "addr:postcode":"g5l 7m9",
    "iso:country":"CA",
    "sg:city":"Rimouski-Est",
    "sg:classifiers":[
        {
            "category":"Professional",
            "subcategory":"Detective & Security Services",
            "type":"Services"
        }
    ],
    "sg:phone":"+1 418 723 0277",
    "sg:postcode":"G5L 7M9",
    "sg:province":"QC",
    "sg:tags":[
        "guard",
        "patrol"
    ],
    "wof:name":"Securite Bsl Ltee",
    "wof:placetype":"venue"
},
  "geometry": {"coordinates":[-68.500793,48.4827],"type":"Point"}
}