{
  "type": "Feature",
  "properties": {
    "addr:full":"Chilliwack BC V2P 4L6",
    "addr:postcode":"v2p 4l6",
    "iso:country":"CA",
    "sg:city":"Chilliwack",
    "sg:classifiers":[
        {
            "category":"Organizations",
            "subcategory":"Professional Association",
            "type":"Services"
        }
    ],
    "sg:phone":"+1 604 792 5535",
    "sg:postcode":"V2P 4L6",
    "sg:province":"BC",
    "sg:tags":[
        "native"
    ],
    "wof:name":"Native Courtworker & Cnslng",
    "wof:placetype":"venue"
},
  "geometry": {"coordinates":[-121.954826,49.172626],"type":"Point"}
}