{
  "type": "Feature",
  "properties": {
    "addr:full":"1170 Rue Du Bourg-Joli Sainte-Adele QC J8B 1W8",
    "addr:housenumber":"1170",
    "addr:postcode":"j8b 1w8",
    "addr:street":"Rue Du Bourg-Joli Sainte-Adele",
    "iso:country":"CA",
    "sg:address":"1170 Rue Du Bourg-Joli",
    "sg:city":"Sainte-Adele",
    "sg:classifiers":[
        {
            "category":"Health Services",
            "subcategory":"Medical Lab",
            "type":"Services"
        }
    ],
    "sg:phone":"+1 450 229 6631",
    "sg:postcode":"J8B 1W8",
    "sg:province":"QC",
    "sg:tags":[
        "dentist"
    ],
    "wof:name":"Clinic Dentaire Bourg-Joli",
    "wof:placetype":"venue"
},
  "geometry": {"coordinates":[-74.1325759888,45.9558830261],"type":"Point"}
}