{
  "type": "Feature",
  "properties": {
    "iso:country":"CA",
    "sg:address":"415 2nd Ave N",
    "sg:city":"Vauxhall",
    "sg:classifiers":[
        {
            "category":"Shopping",
            "subcategory":"Pharmacy",
            "type":"Retail Goods"
        }
    ],
    "sg:phone":"+1 403 654 2515",
    "sg:postcode":"T0K 2K0",
    "sg:province":"AB",
    "wof:name":"Fishers Vauxhall Pharmacy Ltd",
    "wof:placetype":"venue"
},
  "geometry": {"coordinates":[-112.10399627699999,50.0679588318],"type":"Point"}
}