{
  "type": "Feature",
  "properties": {
    "addr:full":"38 Bridge St S Hastings ON K0L 1Y0",
    "addr:housenumber":"38",
    "addr:postcode":"k0l 1y0",
    "addr:street":"Bridge St S",
    "iso:country":"CA",
    "sg:address":"38 Bridge St S",
    "sg:city":"Hastings",
    "sg:classifiers":[
        {
            "category":"Organizations",
            "subcategory":"Religious Organization",
            "type":"Services"
        }
    ],
    "sg:phone":"+1 705 696 3964",
    "sg:postcode":"K0L 1Y0",
    "sg:province":"ON",
    "sg:tags":[
        "church"
    ],
    "wof:name":"St George's Anglican Church",
    "wof:placetype":"venue"
},
  "geometry": {"coordinates":[-77.95703899999999,44.309921],"type":"Point"}
}