{
  "type": "Feature",
  "properties": {
    "addr:full":"256 Stafford St Winnipeg MB R3M 2V9",
    "addr:housenumber":"256",
    "addr:postcode":"r3m 2v9",
    "addr:street":"Stafford St",
    "iso:country":"CA",
    "sg:address":"256 Stafford St",
    "sg:city":"Winnipeg",
    "sg:classifiers":[
        {
            "category":"Personal",
            "subcategory":"Barber",
            "type":"Services"
        }
    ],
    "sg:phone":"+1 204 452 4194",
    "sg:postcode":"R3M 2V9",
    "sg:province":"MB",
    "wof:name":"Steve's Hair Stylists",
    "wof:placetype":"venue"
},
  "geometry": {"coordinates":[-97.161095,49.867989],"type":"Point"}
}