{
  "type": "Feature",
  "properties": {
    "addr:full":"50 Clark Rd Rothesay NB E2E 2K8",
    "addr:housenumber":"50",
    "addr:postcode":"e2e 2k8",
    "addr:street":"Clark Rd",
    "iso:country":"CA",
    "sg:address":"50 Clark Rd",
    "sg:city":"Rothesay",
    "sg:classifiers":[
        {
            "category":"Professional",
            "subcategory":"Lawyer & Legal Services",
            "type":"Services"
        }
    ],
    "sg:phone":"+1 506 847 4704",
    "sg:postcode":"E2E 2K8",
    "sg:province":"NB",
    "sg:tags":[
        "attorney"
    ],
    "wof:name":"Darren Marr Law Office",
    "wof:placetype":"venue"
},
  "geometry": {"coordinates":[-65.98505401609999,45.3972396851],"type":"Point"}
}