{
  "type": "Feature",
  "properties": {
    "addr:full":"North Vancouver BC V7P 1S3",
    "addr:postcode":"v7p 1s3",
    "iso:country":"CA",
    "sg:city":"North Vancouver",
    "sg:classifiers":[
        {
            "category":"Recreation",
            "type":"Entertainment"
        }
    ],
    "sg:phone":"+1 604 985 3536",
    "sg:postcode":"V7P 1S3",
    "sg:province":"BC",
    "sg:tags":[
        "lottery",
        "agent"
    ],
    "wof:name":"Capilano Mall Lottery Ticket",
    "wof:placetype":"venue"
},
  "geometry": {"coordinates":[-123.099121,49.32262],"type":"Point"}
}