{
  "type": "Feature",
  "properties": {
    "addr:full":"1632 Bayview Ave Toronto ON M4G 3B7",
    "addr:housenumber":"1632",
    "addr:postcode":"m4g 3b7",
    "addr:street":"Bayview Ave",
    "iso:country":"CA",
    "sg:address":"1632 Bayview Ave",
    "sg:city":"Toronto",
    "sg:classifiers":[
        {
            "category":"Personal",
            "subcategory":"Beauty Salon",
            "type":"Services"
        }
    ],
    "sg:phone":"+1 416 440 8420",
    "sg:postcode":"M4G 3B7",
    "sg:province":"ON",
    "wof:name":"Hairscapes",
    "wof:placetype":"venue"
},
  "geometry": {"coordinates":[-79.37567138670001,43.7065849304],"type":"Point"}
}