{
  "type": "Feature",
  "properties": {
    "addr:full":"3108 Parkedale Ave W Brockville ON K6V 3G6",
    "addr:housenumber":"3108",
    "addr:postcode":"k6v 3g6",
    "addr:street":"Parkedale Ave W",
    "iso:country":"CA",
    "sg:address":"3108 Parkedale Ave W",
    "sg:city":"Brockville",
    "sg:classifiers":[
        {
            "category":"Building & Trades",
            "subcategory":"Plumbing",
            "type":"Services"
        }
    ],
    "sg:phone":"+1 613 345 0911",
    "sg:postcode":"K6V 3G6",
    "sg:province":"ON",
    "sg:tags":[
        "contractor"
    ],
    "wof:name":"J J Jensen Plumbing & Heating",
    "wof:placetype":"venue"
},
  "geometry": {"coordinates":[-75.712585,44.596626],"type":"Point"}
}