{
  "type": "Feature",
  "properties": {
    "addr:full":"174 Main St Dartmouth NS B2X 1S2",
    "addr:housenumber":"174",
    "addr:postcode":"b2x 1s2",
    "addr:street":"Main St",
    "iso:country":"CA",
    "sg:address":"174 Main St",
    "sg:city":"Dartmouth",
    "sg:classifiers":[
        {
            "category":"Restaurant",
            "type":"Food & Drink"
        }
    ],
    "sg:phone":"+1 902 435 7777",
    "sg:postcode":"B2X 1S2",
    "sg:province":"NS",
    "wof:name":"Garden View Restaurant Ltd",
    "wof:placetype":"venue"
},
  "geometry": {"coordinates":[-63.535313,44.682766],"type":"Point"}
}