{
  "type": "Feature",
  "properties": {
    "addr:full":"206 Highway 21 N Maidstone SK S0M 1M0",
    "addr:housenumber":"206",
    "addr:postcode":"s0m 1m0",
    "addr:street":"Highway 21 N",
    "iso:country":"CA",
    "sg:address":"206 Highway 21 N",
    "sg:city":"Maidstone",
    "sg:classifiers":[
        {
            "category":"Professional",
            "type":"Services"
        }
    ],
    "sg:phone":"+1 306 893 4213",
    "sg:postcode":"S0M 1M0",
    "sg:province":"SK",
    "sg:tags":[
        "establishment",
        "oil",
        "well"
    ],
    "wof:name":"B & M Flushby Svc Ltd",
    "wof:placetype":"venue"
},
  "geometry": {"coordinates":[-109.296607971,53.0874595642],"type":"Point"}
}