{
  "type": "Feature",
  "properties": {
    "addr:full":"244 Candy Mountain Rd Thunder Bay ON P7C 5N5",
    "addr:housenumber":"244",
    "addr:postcode":"p7c 5n5",
    "addr:street":"Candy Mountain Rd",
    "iso:country":"CA",
    "sg:address":"244 Candy Mountain Rd",
    "sg:city":"Thunder Bay",
    "sg:classifiers":[
        {
            "category":"Building & Trades",
            "subcategory":"Landscaping Services",
            "type":"Services"
        }
    ],
    "sg:phone":"+1 807 475 5681",
    "sg:postcode":"P7C 5N5",
    "sg:province":"ON",
    "sg:tags":[
        "sod",
        "sodding"
    ],
    "wof:name":"Sunshine Landscaping & Sod",
    "wof:placetype":"venue"
},
  "geometry": {"coordinates":[-89.3424377441,48.316860199],"type":"Point"}
}