{
  "type": "Feature",
  "properties": {
    "addr:full":"123 202 Rte Canton Bedford QC J0J 1A0",
    "addr:housenumber":"202",
    "addr:postcode":"j0j 1a0",
    "addr:street":"Rte Canton",
    "iso:country":"CA",
    "sg:address":"123 202 Rte",
    "sg:city":"Canton Bedford",
    "sg:classifiers":[
        {
            "category":"Manufacturing",
            "subcategory":"Tools & Machinery",
            "type":"Manufacturing & Wholesale Goods"
        }
    ],
    "sg:phone":"+1 450 248 2551",
    "sg:postcode":"J0J 1A0",
    "sg:province":"QC",
    "sg:tags":[
        "machine",
        "shop"
    ],
    "wof:name":"Ajustage Mecanique Jl Inc",
    "wof:placetype":"venue"
},
  "geometry": {"coordinates":[-72.98598480219999,45.1198005676],"type":"Point"}
}