{
  "type": "Feature",
  "properties": {
    "addr:full":"601 3 Ave S Lethbridge AB T1J 0H4",
    "addr:housenumber":"601",
    "addr:postcode":"t1j 0h4",
    "addr:street":"3 Ave S",
    "iso:country":"CA",
    "sg:address":"601 3 Ave S",
    "sg:city":"Lethbridge",
    "sg:classifiers":[
        {
            "category":"Shopping",
            "type":"Retail Goods"
        }
    ],
    "sg:phone":"+1 403 327 8770",
    "sg:postcode":"T1J 0H4",
    "sg:province":"AB",
    "sg:tags":[
        "art",
        "gallery",
        "dealer"
    ],
    "wof:name":"Southern Alberta Art Gallery",
    "wof:placetype":"venue"
},
  "geometry": {"coordinates":[-112.83853149399999,49.695941925],"type":"Point"}
}