{
  "type": "Feature",
  "properties": {
    "iso:country":"CA",
    "sg:address":"110 Rue Georges",
    "sg:city":"Masson-Angers",
    "sg:classifiers":[
        {
            "category":"Recreation",
            "type":"Entertainment"
        }
    ],
    "sg:phone":"+1 819 986 1664",
    "sg:postcode":"J8M 1A2",
    "sg:province":"QC",
    "sg:tags":[
        "lottery",
        "agent"
    ],
    "wof:name":"Boutique Lotto Quebec",
    "wof:placetype":"venue"
},
  "geometry": {"coordinates":[-75.435585,45.554287],"type":"Point"}
}