{
  "type": "Feature",
  "properties": {
    "iso:country":"CA",
    "sg:address":"1606 Sedlescomb Dr",
    "sg:city":"Mississauga",
    "sg:classifiers":[
        {
            "category":"Building & Trades",
            "subcategory":"Construction",
            "type":"Services"
        }
    ],
    "sg:phone":"+1 905 625 8080",
    "sg:postcode":"L4X 1M6",
    "sg:province":"ON",
    "sg:tags":[
        "general",
        "contractor"
    ],
    "wof:name":"Pronto General Contractor",
    "wof:placetype":"venue"
},
  "geometry": {"coordinates":[-79.58223724370001,43.6159515381],"type":"Point"}
}