{
  "type": "Feature",
  "properties": {
    "addr:full":"35 Bridge St Picton ON K0K 2T0",
    "addr:housenumber":"35",
    "addr:postcode":"k0k 2t0",
    "addr:street":"Bridge St",
    "iso:country":"CA",
    "sg:address":"35 Bridge St",
    "sg:city":"Picton",
    "sg:classifiers":[
        {
            "category":"Travel",
            "subcategory":"Hotels & Motels",
            "type":"Entertainment"
        }
    ],
    "sg:phone":"+1 613 476 2156",
    "sg:postcode":"K0K 2T0",
    "sg:province":"ON",
    "wof:name":"Tip of the Bay Motor Hotel",
    "wof:placetype":"venue"
},
  "geometry": {"coordinates":[-77.13623809809999,44.0086860657],"type":"Point"}
}