{
  "type": "Feature",
  "properties": {
    "addr:full":"90 Av Barron Lachute QC J8H 4N2",
    "addr:postcode":"j8h 4n2",
    "addr:street":"90 Av Barron",
    "iso:country":"CA",
    "sg:address":"90 Av Barron",
    "sg:city":"Lachute",
    "sg:classifiers":[
        {
            "category":"Government",
            "subcategory":"Fire Station",
            "type":"Public Place"
        }
    ],
    "sg:phone":"+1 450 562 3781",
    "sg:postcode":"J8H 4N2",
    "sg:province":"QC",
    "sg:tags":[
        "department"
    ],
    "wof:name":"Lachute Incendie-Admin",
    "wof:placetype":"venue"
},
  "geometry": {"coordinates":[-74.33725,45.655647],"type":"Point"}
}