{
  "type": "Feature",
  "properties": {
    "addr:full":"North Bay ON P1B 2V2",
    "addr:postcode":"p1b 2v2",
    "iso:country":"CA",
    "sg:city":"North Bay",
    "sg:classifiers":[
        {
            "category":"Health Services",
            "subcategory":"Chiropractor",
            "type":"Services"
        }
    ],
    "sg:phone":"+1 705 840 2502",
    "sg:postcode":"P1B 2V2",
    "sg:province":"ON",
    "wof:name":"Body Back in Motion",
    "wof:placetype":"venue"
},
  "geometry": {"coordinates":[-79.467606,46.314697],"type":"Point"}
}