{
  "type": "Feature",
  "properties": {
    "iso:country":"CA",
    "sg:address":"101 Applewood Dr",
    "sg:city":"Brighton",
    "sg:classifiers":[
        {
            "category":"Shopping",
            "type":"Retail Goods"
        }
    ],
    "sg:phone":"+1 613 475 6561",
    "sg:postcode":"K0K 1H0",
    "sg:province":"ON",
    "sg:tags":[
        "material",
        "artist",
        "supply"
    ],
    "wof:name":"Chaloria Wood Art Inc",
    "wof:placetype":"venue"
},
  "geometry": {"coordinates":[-77.72905731199999,44.0378036499],"type":"Point"}
}