{
  "type": "Feature",
  "properties": {
    "addr:full":"58 Ontario St St Catharines ON L2R 5J4",
    "addr:housenumber":"58",
    "addr:postcode":"l2r 5j4",
    "addr:street":"Ontario St",
    "iso:country":"CA",
    "sg:address":"58 Ontario St",
    "sg:city":"St Catharines",
    "sg:classifiers":[
        {
            "category":"Professional",
            "subcategory":"Business Services",
            "type":"Services"
        }
    ],
    "sg:phone":"+1 905 641 2627",
    "sg:postcode":"L2R 5J4",
    "sg:province":"ON",
    "sg:tags":[
        "paralegal"
    ],
    "wof:name":"Pointts Traffic Ticket Spec",
    "wof:placetype":"venue"
},
  "geometry": {"coordinates":[-79.24968,43.156822],"type":"Point"}
}