{
  "type": "Feature",
  "properties": {
    "addr:full":"970 Av Du Semaphore Quebec QC G1P 4E2",
    "addr:housenumber":"970",
    "addr:postcode":"g1p 4e2",
    "addr:street":"Av Du Semaphore",
    "iso:country":"CA",
    "sg:address":"970 Av Du Semaphore",
    "sg:city":"Quebec",
    "sg:classifiers":[
        {
            "category":"Professional",
            "subcategory":"Business Services",
            "type":"Services"
        }
    ],
    "sg:phone":"+1 418 872 5328",
    "sg:postcode":"G1P 4E2",
    "sg:province":"QC",
    "sg:tags":[
        "notary"
    ],
    "wof:name":"Perreault, Diane",
    "wof:placetype":"venue"
},
  "geometry": {"coordinates":[-71.30399300000001,46.802685],"type":"Point"}
}