{
  "type": "Feature",
  "properties": {
    "addr:full":"Chibougamau QC G8P 1N7",
    "addr:postcode":"g8p 1n7",
    "iso:country":"CA",
    "sg:city":"Chibougamau",
    "sg:classifiers":[
        {
            "category":"Professional",
            "subcategory":"Business Services",
            "type":"Services"
        }
    ],
    "sg:phone":"+1 418 748 4741",
    "sg:postcode":"G8P 1N7",
    "sg:province":"QC",
    "sg:tags":[
        "notary"
    ],
    "wof:name":"Leblanc Girard-Gendron Notary",
    "wof:placetype":"venue"
},
  "geometry": {"coordinates":[-74.36164100000001,49.913509],"type":"Point"}
}