{
  "type": "Feature",
  "properties": {
    "iso:country":"CA",
    "sg:address":"105 Elizabeth St",
    "sg:city":"Carleton Place",
    "sg:classifiers":[
        {
            "category":"Real Estate",
            "subcategory":"Real Estate Operator",
            "type":"Services"
        }
    ],
    "sg:phone":"+1 613 257 4812",
    "sg:postcode":"K7C 2V9",
    "sg:province":"ON",
    "sg:tags":[
        "apartment"
    ],
    "wof:name":"Elizabeth Court",
    "wof:placetype":"venue"
},
  "geometry": {"coordinates":[-76.1396560669,45.1332778931],"type":"Point"}
}