{
  "type": "Feature",
  "properties": {
    "iso:country":"CA",
    "sg:address":"10900 Av Jean-Meunier",
    "sg:city":"Montreal-Nord",
    "sg:classifiers":[
        {
            "category":"Manufacturing",
            "subcategory":"Printing",
            "type":"Manufacturing & Wholesale Goods"
        }
    ],
    "sg:phone":"+1 514 955 4567",
    "sg:postcode":"H1G 4S4",
    "sg:province":"QC",
    "sg:tags":[
        "screen"
    ],
    "wof:name":"Seriton Enr",
    "wof:placetype":"venue"
},
  "geometry": {"coordinates":[-73.619164,45.601101],"type":"Point"}
}