{
  "type": "Feature",
  "properties": {
    "iso:country":"CA",
    "sg:address":"2877 Kingston Rd",
    "sg:city":"Scarborough",
    "sg:classifiers":[
        {
            "category":"Real Estate",
            "subcategory":"Real Estate Agent",
            "type":"Services"
        }
    ],
    "sg:phone":"+1 416 264 3484",
    "sg:postcode":"M1M 1N3",
    "sg:province":"ON",
    "wof:name":"Phillip Sperl Real Estate",
    "wof:placetype":"venue"
},
  "geometry": {"coordinates":[-79.2355041504,43.7222175598],"type":"Point"}
}