{
  "type": "Feature",
  "properties": {
    "addr:full":"Edmonton AB T6H 5X9",
    "addr:postcode":"t6h 5x9",
    "iso:country":"CA",
    "sg:city":"Edmonton",
    "sg:classifiers":[
        {
            "category":"Travel",
            "subcategory":"Travel Agent",
            "type":"Entertainment"
        }
    ],
    "sg:phone":"+1 780 430 5468",
    "sg:postcode":"T6H 5X9",
    "sg:province":"AB",
    "sg:tags":[
        "agency",
        "bureau"
    ],
    "wof:name":"Ama Travel",
    "wof:placetype":"venue"
},
  "geometry": {"coordinates":[-113.499778748,53.474571228],"type":"Point"}
}