{
  "type": "Feature",
  "properties": {
    "addr:full":"7115 Rue DE Lisieux Saint-Leonard QC H1S 2G3",
    "addr:housenumber":"7115",
    "addr:postcode":"h1s 2g3",
    "addr:street":"Rue De Lisieux",
    "iso:country":"CA",
    "sg:address":"7115 Rue DE Lisieux",
    "sg:city":"Saint-Leonard",
    "sg:classifiers":[
        {
            "category":"Health Services",
            "subcategory":"Medical Lab",
            "type":"Services"
        }
    ],
    "sg:phone":"+1 514 727 8632",
    "sg:postcode":"H1S 2G3",
    "sg:province":"QC",
    "wof:name":"Gariepy, Richard",
    "wof:placetype":"venue"
},
  "geometry": {"coordinates":[-73.57904052729999,45.5782775879],"type":"Point"}
}