{
  "type": "Feature",
  "properties": {
    "addr:full":"599 Norris Crt Kingston ON K7P 2R9",
    "addr:housenumber":"599",
    "addr:postcode":"k7p 2r9",
    "addr:street":"Norris Crt",
    "iso:country":"CA",
    "sg:address":"599 Norris Crt",
    "sg:city":"Kingston",
    "sg:classifiers":[
        {
            "category":"Wholesale",
            "subcategory":"Electrical",
            "type":"Manufacturing & Wholesale Goods"
        }
    ],
    "sg:phone":"+1 613 384 4144",
    "sg:postcode":"K7P 2R9",
    "sg:province":"ON",
    "sg:tags":[
        "equipment",
        "fuse",
        "electric"
    ],
    "wof:name":"Fusetek",
    "wof:placetype":"venue"
},
  "geometry": {"coordinates":[-76.56725299999999,44.263252],"type":"Point"}
}