{
  "type": "Feature",
  "properties": {
    "addr:full":"8115 137 Ave NW Edmonton AB T5C 2L7",
    "addr:housenumber":"8115",
    "addr:postcode":"t5c 2l7",
    "addr:street":"137 Ave Nw",
    "iso:country":"CA",
    "sg:address":"8115 137 Ave NW",
    "sg:city":"Edmonton",
    "sg:classifiers":[
        {
            "category":"Retail",
            "subcategory":"Car Wash",
            "type":"Services"
        }
    ],
    "sg:phone":"+1 780 475 6742",
    "sg:postcode":"T5C 2L7",
    "sg:province":"AB",
    "sg:tags":[
        "polishing",
        "washing"
    ],
    "wof:name":"Delwood Car Wash",
    "wof:placetype":"venue"
},
  "geometry": {"coordinates":[-113.46569061300001,53.5992469788],"type":"Point"}
}