{
  "type": "Feature",
  "properties": {
    "addr:full":"1801 20th Ave Coaldale AB T1M 1N1",
    "addr:housenumber":"1801",
    "addr:postcode":"t1m 1n1",
    "addr:street":"20Th Ave",
    "iso:country":"CA",
    "sg:address":"1801 20th Ave",
    "sg:city":"Coaldale",
    "sg:classifiers":[
        {
            "category":"Insurance",
            "subcategory":"Insurance Agent",
            "type":"Services"
        }
    ],
    "sg:phone":"+1 403 345 4466",
    "sg:postcode":"T1M 1N1",
    "sg:province":"AB",
    "wof:name":"Coaldale Insurance Ltd",
    "wof:placetype":"venue"
},
  "geometry": {"coordinates":[-112.619766235,49.7274131775],"type":"Point"}
}