{
  "type": "Feature",
  "properties": {
    "iso:country":"CA",
    "sg:address":"3800 Memorial Dr NE",
    "sg:city":"Calgary",
    "sg:classifiers":[
        {
            "category":"Personal",
            "subcategory":"Beauty Salon",
            "type":"Services"
        }
    ],
    "sg:phone":"+1 403 235 1794",
    "sg:postcode":"T2A 2K2",
    "sg:province":"AB",
    "wof:name":"Ultracuts",
    "wof:placetype":"venue"
},
  "geometry": {"coordinates":[-113.979934692,51.0525283813],"type":"Point"}
}