{
  "type": "Feature",
  "properties": {
    "iso:country":"CA",
    "sg:address":"785 Boul DE L'Universite",
    "sg:city":"Rouyn-Noranda",
    "sg:classifiers":[
        {
            "category":"Manufacturing",
            "subcategory":"Furniture",
            "type":"Manufacturing & Wholesale Goods"
        }
    ],
    "sg:phone":"+1 819 797 2008",
    "sg:postcode":"J9X 7C5",
    "sg:province":"QC",
    "sg:tags":[
        "maker",
        "cabinet"
    ],
    "wof:name":"Ebenisterie Haut-Niveau",
    "wof:placetype":"venue"
},
  "geometry": {"coordinates":[-79.0073394775,48.2371025085],"type":"Point"}
}