{
  "type": "Feature",
  "properties": {
    "addr:full":"Surrey BC V4A 2J4",
    "addr:postcode":"v4a 2j4",
    "iso:country":"CA",
    "sg:city":"Surrey",
    "sg:classifiers":[
        {
            "category":"Building & Trades",
            "subcategory":"Construction",
            "type":"Services"
        }
    ],
    "sg:phone":"+1 604 538 9622",
    "sg:postcode":"V4A 2J4",
    "sg:province":"BC",
    "sg:tags":[
        "repairing",
        "remodeling",
        "contractor"
    ],
    "wof:name":"Mpb Construction Ltd",
    "wof:placetype":"venue"
},
  "geometry": {"coordinates":[-122.792816,49.045715],"type":"Point"}
}