{
  "type": "Feature",
  "properties": {
    "addr:full":"5 Av Langevin Baie-Comeau QC G4Z 2T5",
    "addr:postcode":"g4z 2t5",
    "addr:street":"Av Langevin",
    "iso:country":"CA",
    "sg:address":"5 Av Langevin",
    "sg:city":"Baie-Comeau",
    "sg:classifiers":[
        {
            "category":"Building & Trades",
            "subcategory":"Construction",
            "type":"Services"
        }
    ],
    "sg:phone":"+1 418 296 9866",
    "sg:postcode":"G4Z 2T5",
    "sg:province":"QC",
    "sg:tags":[
        "general",
        "contractor"
    ],
    "wof:name":"Jean-Marie Fillion Inc",
    "wof:placetype":"venue"
},
  "geometry": {"coordinates":[-68.186218,49.207035],"type":"Point"}
}