{
  "type": "Feature",
  "properties": {
    "addr:full":"2057 Rue DE LA Montagne Montreal QC H3G 1Z8",
    "addr:housenumber":"2057",
    "addr:postcode":"h3g 1z8",
    "addr:street":"Rue De La Montagne",
    "iso:country":"CA",
    "sg:address":"2057 Rue DE LA Montagne",
    "sg:city":"Montreal",
    "sg:classifiers":[
        {
            "category":"Shopping",
            "subcategory":"Clothing, Apparel, & Fashions",
            "type":"Retail Goods"
        }
    ],
    "sg:phone":"+1 514 350 9090",
    "sg:postcode":"H3G 1Z8",
    "sg:province":"QC",
    "sg:tags":[
        "item",
        "boutique"
    ],
    "wof:name":"Nadya Toto Inc",
    "wof:placetype":"venue"
},
  "geometry": {"coordinates":[-73.57720947270001,45.499130249],"type":"Point"}
}