{
  "type": "Feature",
  "properties": {
    "addr:full":"160 Old Placentia Rd Mount Pearl NL A1N 4Y9",
    "addr:housenumber":"160",
    "addr:postcode":"a1n 4y9",
    "addr:street":"Old Placentia Rd",
    "iso:country":"CA",
    "sg:address":"160 Old Placentia Rd",
    "sg:city":"Mount Pearl",
    "sg:classifiers":[
        {
            "category":"Shopping",
            "subcategory":"Department Store",
            "type":"Retail Goods"
        }
    ],
    "sg:phone":"+1 709 364 8555",
    "sg:postcode":"A1N 4Y9",
    "sg:province":"NL",
    "sg:tags":[
        "shop"
    ],
    "wof:name":"Only Deals",
    "wof:placetype":"venue"
},
  "geometry": {"coordinates":[-52.8171424866,47.5094070435],"type":"Point"}
}