{
  "type": "Feature",
  "properties": {
    "addr:full":"Ottawa ON K1V 0W3",
    "addr:postcode":"k1v 0w3",
    "iso:country":"CA",
    "sg:city":"Ottawa",
    "sg:classifiers":[
        {
            "category":"Travel",
            "subcategory":"Travel Agent",
            "type":"Entertainment"
        }
    ],
    "sg:phone":"+1 613 248 0505",
    "sg:postcode":"K1V 0W3",
    "sg:province":"ON",
    "sg:tags":[
        "agency",
        "bureau"
    ],
    "wof:name":"Diamond Travel",
    "wof:placetype":"venue"
},
  "geometry": {"coordinates":[-75.66418457029999,45.3719062805],"type":"Point"}
}