{
  "type": "Feature",
  "properties": {
    "addr:full":"30 Spring St Amherst NS B4H 1R7",
    "addr:housenumber":"30",
    "addr:postcode":"b4h 1r7",
    "addr:street":"Spring St",
    "iso:country":"CA",
    "sg:address":"30 Spring St",
    "sg:city":"Amherst",
    "sg:classifiers":[
        {
            "category":"Personal",
            "subcategory":"Beauty Salon",
            "type":"Services"
        }
    ],
    "sg:phone":"+1 902 667 0193",
    "sg:postcode":"B4H 1R7",
    "sg:province":"NS",
    "wof:name":"Kim's Hair Studio",
    "wof:placetype":"venue"
},
  "geometry": {"coordinates":[-64.2072677612,45.8289375305],"type":"Point"}
}