{
  "type": "Feature",
  "properties": {
    "addr:full":"5555 Boul Des Forges Trois-Rivieres QC G8Y 5L5",
    "addr:housenumber":"5555",
    "addr:postcode":"g8y 5l5",
    "addr:street":"Boul Des Forges Trois-Rivieres",
    "iso:country":"CA",
    "sg:address":"5555 Boul Des Forges",
    "sg:city":"Trois-Rivieres",
    "sg:classifiers":[
        {
            "category":"Insurance",
            "subcategory":"Insurance Agent",
            "type":"Services"
        }
    ],
    "sg:phone":"+1 819 693 2233",
    "sg:postcode":"G8Y 5L5",
    "sg:province":"QC",
    "wof:name":"Groupe D'Assurances Verrier",
    "wof:placetype":"venue"
},
  "geometry": {"coordinates":[-72.596474,46.363976],"type":"Point"}
}