{
  "type": "Feature",
  "properties": {
    "addr:full":"2675 4th Ave W Prince Albert SK S6V 5H8",
    "addr:housenumber":"2675",
    "addr:postcode":"s6v 5h8",
    "addr:street":"4Th Ave W",
    "iso:country":"CA",
    "sg:address":"2675 4th Ave W",
    "sg:city":"Prince Albert",
    "sg:classifiers":[
        {
            "category":"Education",
            "subcategory":"School",
            "type":"Public Place"
        }
    ],
    "sg:phone":"+1 306 922 9229",
    "sg:postcode":"S6V 5H8",
    "sg:province":"SK",
    "wof:name":"Arthur Pechey School",
    "wof:placetype":"venue"
},
  "geometry": {"coordinates":[-105.76527404799999,53.1885147095],"type":"Point"}
}