{
  "type": "Feature",
  "properties": {
    "addr:full":"Smallwood Dr Gambo NL A0G 1T0",
    "addr:postcode":"a0g 1t0",
    "addr:street":"Smallwood Dr",
    "iso:country":"CA",
    "sg:address":"Smallwood Dr",
    "sg:city":"Gambo",
    "sg:classifiers":[
        {
            "category":"Recreation",
            "type":"Entertainment"
        }
    ],
    "sg:phone":"+1 709 674 4497",
    "sg:postcode":"A0G 1T0",
    "sg:province":"NL",
    "sg:tags":[
        "hall",
        "auditorium"
    ],
    "wof:name":"United Church Hall",
    "wof:placetype":"venue"
},
  "geometry": {"coordinates":[-54.211369,48.786755],"type":"Point"}
}