{
  "type": "Feature",
  "properties": {
    "iso:country":"CA",
    "sg:city":"Hamilton",
    "sg:classifiers":[
        {
            "category":"Shopping",
            "subcategory":"Musical Instruments",
            "type":"Retail Goods"
        }
    ],
    "sg:phone":"+1 905 545 0992",
    "sg:postcode":"L8M 1B1",
    "sg:province":"ON",
    "wof:name":"Smart Pedals For Drums",
    "wof:placetype":"venue"
},
  "geometry": {"coordinates":[-79.84191131590001,43.2514762878],"type":"Point"}
}