{
  "type": "Feature",
  "properties": {
    "addr:full":"79 Rue Frontenac Hull QC J8X 4H5",
    "addr:housenumber":"79",
    "addr:postcode":"j8x 4h5",
    "addr:street":"Rue Frontenac",
    "iso:country":"CA",
    "sg:address":"79 Rue Frontenac",
    "sg:city":"Hull",
    "sg:classifiers":[
        {
            "category":"Personal",
            "subcategory":"Beauty Salon",
            "type":"Services"
        }
    ],
    "sg:phone":"+1 819 770 0775",
    "sg:postcode":"J8X 4H5",
    "sg:province":"QC",
    "wof:name":"Coiffure Le Chateau Elle & Liu",
    "wof:placetype":"venue"
},
  "geometry": {"coordinates":[-75.71726200000001,45.429142],"type":"Point"}
}