{
  "type": "Feature",
  "properties": {
    "addr:full":"5540 106 Ave NW Edmonton AB T6A 1G3",
    "addr:housenumber":"5540",
    "addr:postcode":"t6a 1g3",
    "addr:street":"106 Ave Nw",
    "iso:country":"CA",
    "sg:address":"5540 106 Ave NW",
    "sg:city":"Edmonton",
    "sg:classifiers":[
        {
            "category":"Social Services",
            "subcategory":"Child Care",
            "type":"Services"
        }
    ],
    "sg:phone":"+1 780 469 3468",
    "sg:postcode":"T6A 1G3",
    "sg:province":"AB",
    "wof:name":"Galaxy",
    "wof:placetype":"venue"
},
  "geometry": {"coordinates":[-113.42361450200001,53.5503425598],"type":"Point"}
}