{
  "type": "Feature",
  "properties": {
    "addr:full":"Cambridge ON N3H 5G7",
    "addr:postcode":"n3h 5g7",
    "iso:country":"CA",
    "sg:city":"Cambridge",
    "sg:classifiers":[
        {
            "category":"Manufacturing",
            "subcategory":"Printing",
            "type":"Manufacturing & Wholesale Goods"
        }
    ],
    "sg:phone":"+1 519 653 2530",
    "sg:postcode":"N3H 5G7",
    "sg:province":"ON",
    "sg:tags":[
        "printer",
        "duplicating",
        "copying"
    ],
    "wof:name":"Bee's Universal Printers Ltd",
    "wof:placetype":"venue"
},
  "geometry": {"coordinates":[-80.3295211792,43.3933105469],"type":"Point"}
}