{
  "type": "Feature",
  "properties": {
    "addr:full":"10003 98th St Grande Cache AB T0E 0Y0",
    "addr:housenumber":"10003",
    "addr:postcode":"t0e 0y0",
    "addr:street":"98Th St",
    "iso:country":"CA",
    "sg:address":"10003 98th St",
    "sg:city":"Grande Cache",
    "sg:classifiers":[
        {
            "category":"Retail",
            "subcategory":"Repair Shop",
            "type":"Services"
        }
    ],
    "sg:phone":"+1 780 827 4490",
    "sg:postcode":"T0E 0Y0",
    "sg:province":"AB",
    "sg:tags":[
        "welding"
    ],
    "wof:name":"B & B Welding",
    "wof:placetype":"venue"
},
  "geometry": {"coordinates":[-119.109573,53.889896],"type":"Point"}
}