{
  "type": "Feature",
  "properties": {
    "addr:full":"10 Fort William St. John's NL A1C 1K4",
    "addr:housenumber":"10",
    "addr:postcode":"a1c 1k4",
    "addr:street":"Fort William",
    "iso:country":"CA",
    "sg:address":"10 Fort William",
    "sg:city":"St. John's",
    "sg:classifiers":[
        {
            "category":"Restaurant",
            "type":"Food & Drink"
        }
    ],
    "sg:phone":"+1 709 576 3038",
    "sg:postcode":"A1C 1K4",
    "sg:province":"NL",
    "wof:name":"Court Yard Cafe",
    "wof:placetype":"venue"
},
  "geometry": {"coordinates":[-52.699375,47.572086],"type":"Point"}
}