{
  "type": "Feature",
  "properties": {
    "addr:full":"474 Ch Saint-Michel Crabtree QC J0K 1B0",
    "addr:housenumber":"474",
    "addr:postcode":"j0k 1b0",
    "addr:street":"Ch Saint-Michel",
    "iso:country":"CA",
    "sg:address":"474 Ch Saint-Michel",
    "sg:city":"Crabtree",
    "sg:classifiers":[
        {
            "category":"Retail",
            "subcategory":"Auto Repair",
            "type":"Services"
        }
    ],
    "sg:phone":"+1 450 759 9699",
    "sg:postcode":"J0K 1B0",
    "sg:province":"QC",
    "sg:tags":[
        "repairing",
        "automobile"
    ],
    "wof:name":"Atelier Mecanique Bessette Inc",
    "wof:placetype":"venue"
},
  "geometry": {"coordinates":[-73.4601364136,45.9740562439],"type":"Point"}
}