{
  "type": "Feature",
  "properties": {
    "iso:country":"CA",
    "sg:address":"10117 150 St NW",
    "sg:city":"Edmonton",
    "sg:classifiers":[
        {
            "category":"Social Services",
            "type":"Services"
        }
    ],
    "sg:phone":"+1 780 481 3451",
    "sg:postcode":"T5P 1P2",
    "sg:province":"AB",
    "sg:tags":[
        "organization",
        "welfare",
        "personnel",
        "consultant"
    ],
    "wof:name":"Bent Arrow",
    "wof:placetype":"venue"
},
  "geometry": {"coordinates":[-113.579544067,53.5417976379],"type":"Point"}
}