{
  "type": "Feature",
  "properties": {
    "addr:full":"4824 51 Ave Vermilion AB T9X 1T6",
    "addr:housenumber":"4824",
    "addr:postcode":"t9x 1t6",
    "addr:street":"51 Ave",
    "iso:country":"CA",
    "sg:address":"4824 51 Ave",
    "sg:city":"Vermilion",
    "sg:classifiers":[
        {
            "category":"Retail",
            "subcategory":"Funeral Services",
            "type":"Services"
        }
    ],
    "sg:phone":"+1 780 853 5100",
    "sg:postcode":"T9X 1T6",
    "sg:province":"AB",
    "sg:tags":[
        "director"
    ],
    "wof:name":"Lakeland Funeral Home",
    "wof:placetype":"venue"
},
  "geometry": {"coordinates":[-110.84729799999999,53.355095],"type":"Point"}
}