{
  "type": "Feature",
  "properties": {
    "addr:full":"238 Wellington St W Sault Ste Marie ON P6A 1H7",
    "addr:housenumber":"238",
    "addr:postcode":"p6a 1h7",
    "addr:street":"Wellington St W",
    "iso:country":"CA",
    "sg:address":"238 Wellington St W",
    "sg:city":"Sault Ste Marie",
    "sg:classifiers":[
        {
            "category":"Wholesale",
            "subcategory":"Fruits & Vegetables",
            "type":"Manufacturing & Wholesale Goods"
        }
    ],
    "sg:phone":"+1 705 759 3264",
    "sg:postcode":"P6A 1H7",
    "sg:province":"ON",
    "wof:name":"Steelton Produce",
    "wof:placetype":"venue"
},
  "geometry": {"coordinates":[-84.3450469971,46.5246391296],"type":"Point"}
}