{
  "type": "Feature",
  "properties": {
    "addr:full":"218 Bosworth St Wynyard SK S0A 4T0",
    "addr:housenumber":"218",
    "addr:postcode":"s0a 4t0",
    "addr:street":"Bosworth St",
    "iso:country":"CA",
    "sg:address":"218 Bosworth St",
    "sg:city":"Wynyard",
    "sg:classifiers":[
        {
            "category":"Health Services",
            "subcategory":"Doctor",
            "type":"Services"
        }
    ],
    "sg:phone":"+1 306 554 2424",
    "sg:postcode":"S0A 4T0",
    "sg:province":"SK",
    "sg:tags":[
        "physician",
        "surgeon"
    ],
    "wof:name":"Dewar, Dale MD",
    "wof:placetype":"venue"
},
  "geometry": {"coordinates":[-104.185653687,51.7702255249],"type":"Point"}
}