{
  "type": "Feature",
  "properties": {
    "addr:full":"9025 158 St Surrey BC V4N 2Y6",
    "addr:housenumber":"9025",
    "addr:postcode":"v4n 2y6",
    "addr:street":"158 St",
    "iso:country":"CA",
    "sg:address":"9025 158 St",
    "sg:city":"Surrey",
    "sg:classifiers":[
        {
            "category":"Education",
            "subcategory":"School",
            "type":"Public Place"
        }
    ],
    "sg:phone":"+1 604 589 5957",
    "sg:postcode":"V4N 2Y6",
    "sg:province":"BC",
    "wof:name":"Woodland Park Elementary Schl",
    "wof:placetype":"venue"
},
  "geometry": {"coordinates":[-122.784706116,49.166934967],"type":"Point"}
}