{
  "type": "Feature",
  "properties": {
    "addr:full":"2546 Granville St Vancouver BC V6H 3G8",
    "addr:housenumber":"2546",
    "addr:postcode":"v6h 3g8",
    "addr:street":"Granville St",
    "iso:country":"CA",
    "sg:address":"2546 Granville St",
    "sg:city":"Vancouver",
    "sg:classifiers":[
        {
            "category":"Wholesale",
            "subcategory":"Apparel",
            "type":"Manufacturing & Wholesale Goods"
        }
    ],
    "sg:phone":"+1 604 736 7768",
    "sg:postcode":"V6H 3G8",
    "sg:province":"BC",
    "sg:tags":[
        "clothing"
    ],
    "wof:name":"Mantique Fashions Ltd",
    "wof:placetype":"venue"
},
  "geometry": {"coordinates":[-123.13838958700001,49.2631645203],"type":"Point"}
}