{
  "type": "Feature",
  "properties": {
    "addr:full":"135 Huron Rd 6 Embro ON N0J 1J0",
    "addr:housenumber":"135",
    "addr:postcode":"n0j 1j0",
    "addr:street":"Huron Rd 6",
    "iso:country":"CA",
    "sg:address":"135 Huron Rd 6",
    "sg:city":"Embro",
    "sg:classifiers":[
        {
            "category":"Education",
            "subcategory":"Library",
            "type":"Public Place"
        }
    ],
    "sg:phone":"+1 519 475 4172",
    "sg:postcode":"N0J 1J0",
    "sg:province":"ON",
    "wof:name":"Embro Library",
    "wof:placetype":"venue"
},
  "geometry": {"coordinates":[-80.9012680054,43.1557807922],"type":"Point"}
}