{
  "type": "Feature",
  "properties": {
    "addr:full":"60 Rue Sauvageau Cap-DE-LA-Madeleine QC G8T 6B3",
    "addr:housenumber":"60",
    "addr:postcode":"g8t 6b3",
    "addr:street":"Rue Sauvageau",
    "iso:country":"CA",
    "sg:address":"60 Rue Sauvageau",
    "sg:city":"Cap-DE-LA-Madeleine",
    "sg:classifiers":[
        {
            "category":"Wholesale",
            "subcategory":"Electrical",
            "type":"Manufacturing & Wholesale Goods"
        }
    ],
    "sg:phone":"+1 819 379 8908",
    "sg:postcode":"G8T 6B3",
    "sg:province":"QC",
    "sg:tags":[
        "equipment",
        "electric",
        "supply"
    ],
    "wof:name":"Jesstec Industries Inc",
    "wof:placetype":"venue"
},
  "geometry": {"coordinates":[-72.54135894780001,46.384185791],"type":"Point"}
}