{
  "type": "Feature",
  "properties": {
    "addr:full":"95 King St E Hamilton ON L8N 1A9",
    "addr:housenumber":"95",
    "addr:postcode":"l8n 1a9",
    "addr:street":"King St E",
    "iso:country":"CA",
    "sg:address":"95 King St E",
    "sg:city":"Hamilton",
    "sg:classifiers":[
        {
            "category":"Restaurant",
            "type":"Food & Drink"
        }
    ],
    "sg:phone":"+1 905 540 8536",
    "sg:postcode":"L8N 1A9",
    "sg:province":"ON",
    "wof:name":"Safin Grill",
    "wof:placetype":"venue"
},
  "geometry": {"coordinates":[-79.866051,43.255779],"type":"Point"}
}