{
  "type": "Feature",
  "properties": {
    "addr:full":"980 Boul DE Sainte-Adele Sainte-Adele QC J8B 2N3",
    "addr:housenumber":"980",
    "addr:postcode":"j8b 2n3",
    "addr:street":"Boul De Sainte-Adele Sainte-Adele",
    "iso:country":"CA",
    "sg:address":"980 Boul DE Sainte-Adele",
    "sg:city":"Sainte-Adele",
    "sg:classifiers":[
        {
            "category":"Restaurant",
            "type":"Food & Drink"
        }
    ],
    "sg:phone":"+1 450 229 4991",
    "sg:postcode":"J8B 2N3",
    "sg:province":"QC",
    "wof:name":"Restaurant John Le Grec Inc",
    "wof:placetype":"venue"
},
  "geometry": {"coordinates":[-74.1148757935,45.9612998962],"type":"Point"}
}