{
  "type": "Feature",
  "properties": {
    "iso:country":"CA",
    "sg:address":"725 Notre Dame Dr",
    "sg:city":"London",
    "sg:classifiers":[
        {
            "category":"Home & Garden",
            "subcategory":"Hardware",
            "type":"Retail Goods"
        }
    ],
    "sg:phone":"+1 519 668 6888",
    "sg:postcode":"N6J 3V5",
    "sg:province":"ON",
    "wof:name":"Plaza Home Hardware West",
    "wof:placetype":"venue"
},
  "geometry": {"coordinates":[-81.269798,42.947498],"type":"Point"}
}