{
  "type": "Feature",
  "properties": {
    "addr:full":"Toronto ON M4W 3C7",
    "addr:postcode":"m4w 3c7",
    "iso:country":"CA",
    "sg:city":"Toronto",
    "sg:classifiers":[
        {
            "category":"Real Estate",
            "subcategory":"Architect",
            "type":"Services"
        }
    ],
    "sg:phone":"+1 416 926 9097",
    "sg:postcode":"M4W 3C7",
    "sg:province":"ON",
    "wof:name":"Cristescu, Emil",
    "wof:placetype":"venue"
},
  "geometry": {"coordinates":[-79.388496,43.673946],"type":"Point"}
}