{
  "type": "Feature",
  "properties": {
    "addr:full":"2423 Cashmere Ave Mississauga ON L5B 2M7",
    "addr:housenumber":"2423",
    "addr:postcode":"l5b 2m7",
    "addr:street":"Cashmere Ave",
    "iso:country":"CA",
    "sg:address":"2423 Cashmere Ave",
    "sg:city":"Mississauga",
    "sg:classifiers":[
        {
            "category":"Building & Trades",
            "subcategory":"Construction",
            "type":"Services"
        }
    ],
    "sg:phone":"+1 905 276 4595",
    "sg:postcode":"L5B 2M7",
    "sg:province":"ON",
    "sg:tags":[
        "painter"
    ],
    "wof:name":"Orva Painting",
    "wof:placetype":"venue"
},
  "geometry": {"coordinates":[-79.6251068115,43.5642776489],"type":"Point"}
}