{
  "type": "Feature",
  "properties": {
    "addr:full":"1603 Rue Principale Canton-DE-Granby QC J2G 8C8",
    "addr:housenumber":"1603",
    "addr:postcode":"j2g 8c8",
    "addr:street":"Rue Principale",
    "iso:country":"CA",
    "sg:address":"1603 Rue Principale",
    "sg:city":"Canton-DE-Granby",
    "sg:classifiers":[
        {
            "category":"Autos & Motor Vehicles",
            "subcategory":"Automobile Sales",
            "type":"Retail Goods"
        }
    ],
    "sg:phone":"+1 450 531 4990",
    "sg:postcode":"J2G 8C8",
    "sg:province":"QC",
    "sg:tags":[
        "car",
        "dealer"
    ],
    "wof:name":"Auto Max Enr",
    "wof:placetype":"venue"
},
  "geometry": {"coordinates":[-72.8134613037,45.4263458252],"type":"Point"}
}