{
  "type": "Feature",
  "properties": {
    "iso:country":"CA",
    "sg:city":"Markham",
    "sg:classifiers":[
        {
            "category":"Food & Beverages",
            "subcategory":"Bakery",
            "type":"Retail Goods"
        }
    ],
    "sg:phone":"+1 905 477 3555",
    "sg:postcode":"L3R 4G9",
    "sg:province":"ON",
    "sg:tags":[
        "baker"
    ],
    "wof:name":"Bakery Nakamura",
    "wof:placetype":"venue"
},
  "geometry": {"coordinates":[-79.34558868409999,43.8147697449],"type":"Point"}
}