{
  "type": "Feature",
  "properties": {
    "addr:full":"130 Adelaide St W Toronto ON M5H 3P5",
    "addr:housenumber":"130",
    "addr:postcode":"m5h 3p5",
    "addr:street":"Adelaide St W",
    "iso:country":"CA",
    "sg:address":"130 Adelaide St W",
    "sg:city":"Toronto",
    "sg:classifiers":[
        {
            "category":"Retail",
            "subcategory":"Laundry & Dry Cleaning",
            "type":"Services"
        }
    ],
    "sg:phone":"+1 416 363 0815",
    "sg:postcode":"M5H 3P5",
    "sg:province":"ON",
    "sg:tags":[
        "cleaners"
    ],
    "wof:name":"Sisters Cleaner",
    "wof:placetype":"venue"
},
  "geometry": {"coordinates":[-79.383888,43.649353],"type":"Point"}
}