{
  "type": "Feature",
  "properties": {
    "addr:full":"Montreal QC H3A 2L1",
    "addr:postcode":"h3a 2l1",
    "iso:country":"CA",
    "sg:city":"Montreal",
    "sg:classifiers":[
        {
            "category":"Professional",
            "subcategory":"Management & Consulting",
            "type":"Services"
        }
    ],
    "sg:phone":"+1 514 286 7004",
    "sg:postcode":"H3A 2L1",
    "sg:province":"QC",
    "sg:tags":[
        "consultant",
        "instructional"
    ],
    "wof:name":"Cide Inc",
    "wof:placetype":"venue"
},
  "geometry": {"coordinates":[-73.5724868774,45.5046005249],"type":"Point"}
}