{
  "type": "Feature",
  "properties": {
    "addr:full":"30 Williams Ave Dartmouth NS B3B 2E2",
    "addr:housenumber":"30",
    "addr:postcode":"b3b 2e2",
    "addr:street":"Williams Ave",
    "iso:country":"CA",
    "sg:address":"30 Williams Ave",
    "sg:city":"Dartmouth",
    "sg:classifiers":[
        {
            "category":"Manufacturing",
            "subcategory":"Building Materials",
            "type":"Manufacturing & Wholesale Goods"
        }
    ],
    "sg:phone":"+1 902 468 3555",
    "sg:postcode":"B3B 2E2",
    "sg:province":"NS",
    "wof:name":"Robert Bury & CO Ltd",
    "wof:placetype":"venue"
},
  "geometry": {"coordinates":[-63.585659,44.713505],"type":"Point"}
}