{
  "type": "Feature",
  "properties": {
    "addr:full":"389 Av Saint-Jerome Matane QC G4W 3B4",
    "addr:postcode":"g4w 3b4",
    "addr:street":"389 Av Saint-Jerome",
    "iso:country":"CA",
    "sg:address":"389 Av Saint-Jerome",
    "sg:city":"Matane",
    "sg:classifiers":[
        {
            "category":"Restaurant",
            "type":"Food & Drink"
        }
    ],
    "sg:phone":"+1 418 562 2577",
    "sg:postcode":"G4W 3B4",
    "sg:province":"QC",
    "wof:name":"Brasserie Au Vieux Loup DE Mer",
    "wof:placetype":"venue"
},
  "geometry": {"coordinates":[-67.52958700000001,48.846523],"type":"Point"}
}