{
  "type": "Feature",
  "properties": {
    "iso:country":"CA",
    "sg:address":"1095 Petrolia Rd",
    "sg:city":"North York",
    "sg:classifiers":[
        {
            "category":"Wholesale",
            "subcategory":"Furniture",
            "type":"Manufacturing & Wholesale Goods"
        }
    ],
    "sg:phone":"+1 416 663 2223",
    "sg:postcode":"M3J 2X7",
    "sg:province":"ON",
    "sg:tags":[
        "manufacturer"
    ],
    "wof:name":"Rosner International",
    "wof:placetype":"venue"
},
  "geometry": {"coordinates":[-79.489349,43.781292],"type":"Point"}
}