{
  "type": "Feature",
  "properties": {
    "addr:full":"9 Densley Ave North York ON M6M 2P5",
    "addr:housenumber":"9",
    "addr:postcode":"m6m 2p5",
    "addr:street":"Densley Ave",
    "iso:country":"CA",
    "sg:address":"9 Densley Ave",
    "sg:city":"North York",
    "sg:classifiers":[
        {
            "category":"Manufacturing",
            "subcategory":"Textiles",
            "type":"Manufacturing & Wholesale Goods"
        }
    ],
    "sg:phone":"+1 416 241 2345",
    "sg:postcode":"M6M 2P5",
    "sg:province":"ON",
    "sg:tags":[
        "hosiery"
    ],
    "wof:name":"Gertex Hosiery Inc",
    "wof:placetype":"venue"
},
  "geometry": {"coordinates":[-79.475464,43.703056],"type":"Point"}
}