{
  "type": "Feature",
  "properties": {
    "addr:full":"Markham ON L6E 1A1",
    "addr:postcode":"l6e 1a1",
    "iso:country":"CA",
    "sg:city":"Markham",
    "sg:classifiers":[
        {
            "category":"Health Services",
            "subcategory":"Doctor",
            "type":"Services"
        }
    ],
    "sg:phone":"+1 905 472 2454",
    "sg:postcode":"L6E 1A1",
    "sg:province":"ON",
    "sg:tags":[
        "dentist"
    ],
    "wof:name":"Sunmark Dental Ctr",
    "wof:placetype":"venue"
},
  "geometry": {"coordinates":[-79.33994300000001,43.856033],"type":"Point"}
}