{
  "type": "Feature",
  "properties": {
    "addr:full":"3131 Lakeshore Rd Kelowna BC V1W 3S9",
    "addr:housenumber":"3131",
    "addr:postcode":"v1w 3s9",
    "addr:street":"Lakeshore Rd",
    "iso:country":"CA",
    "sg:address":"3131 Lakeshore Rd",
    "sg:city":"Kelowna",
    "sg:classifiers":[
        {
            "category":"Organizations",
            "subcategory":"Religious Organization",
            "type":"Services"
        }
    ],
    "sg:phone":"+1 250 762 5443",
    "sg:postcode":"V1W 3S9",
    "sg:province":"BC",
    "sg:tags":[
        "church"
    ],
    "wof:name":"St Paul's United Church",
    "wof:placetype":"venue"
},
  "geometry": {"coordinates":[-119.491004944,49.8610839844],"type":"Point"}
}