{
  "type": "Feature",
  "properties": {
    "addr:full":"191 Welland Ave St Catharines ON L2R 2P2",
    "addr:housenumber":"191",
    "addr:postcode":"l2r 2p2",
    "addr:street":"Welland Ave",
    "iso:country":"CA",
    "sg:address":"191 Welland Ave",
    "sg:city":"St Catharines",
    "sg:classifiers":[
        {
            "category":"Health Services",
            "subcategory":"Optometrist",
            "type":"Services"
        }
    ],
    "sg:phone":"+1 905 688 5361",
    "sg:postcode":"L2R 2P2",
    "sg:province":"ON",
    "wof:name":"Marsh, Jason OD",
    "wof:placetype":"venue"
},
  "geometry": {"coordinates":[-79.23923492430001,43.1662750244],"type":"Point"}
}