{
  "type": "Feature",
  "properties": {
    "addr:full":"2009 39 Ave NE Calgary AB T2E 6R7",
    "addr:housenumber":"2009",
    "addr:postcode":"t2e 6r7",
    "addr:street":"39 Ave Ne",
    "iso:country":"CA",
    "sg:address":"2009 39 Ave NE",
    "sg:city":"Calgary",
    "sg:classifiers":[
        {
            "category":"Wholesale",
            "subcategory":"Non-durable Goods",
            "type":"Manufacturing & Wholesale Goods"
        }
    ],
    "sg:phone":"+1 403 291 9148",
    "sg:postcode":"T2E 6R7",
    "sg:province":"AB",
    "sg:tags":[
        "advertising"
    ],
    "wof:name":"Accessories West Ltd",
    "wof:placetype":"venue"
},
  "geometry": {"coordinates":[-114.011353,51.088181],"type":"Point"}
}