{
  "type": "Feature",
  "properties": {
    "addr:full":"Sioux Lookout ON P8T 1A3",
    "addr:postcode":"p8t 1a3",
    "iso:country":"CA",
    "sg:city":"Sioux Lookout",
    "sg:classifiers":[
        {
            "category":"Social Services",
            "type":"Services"
        }
    ],
    "sg:phone":"+1 807 737 2292",
    "sg:postcode":"P8T 1A3",
    "sg:province":"ON",
    "sg:tags":[
        "organization",
        "welfare"
    ],
    "wof:name":"Northwestern Health Unit",
    "wof:placetype":"venue"
},
  "geometry": {"coordinates":[-91.919746,50.098892],"type":"Point"}
}