{
  "type": "Feature",
  "properties": {
    "addr:full":"Brampton ON L6V 1N2",
    "addr:postcode":"l6v 1n2",
    "iso:country":"CA",
    "sg:city":"Brampton",
    "sg:classifiers":[
        {
            "category":"Retail",
            "subcategory":"Photofinishing",
            "type":"Services"
        }
    ],
    "sg:phone":"+1 905 455 3732",
    "sg:postcode":"L6V 1N2",
    "sg:province":"ON",
    "sg:tags":[
        "photo",
        "finishing"
    ],
    "wof:name":"Rainbow Photo Lab",
    "wof:placetype":"venue"
},
  "geometry": {"coordinates":[-79.757149,43.703995],"type":"Point"}
}