{
  "type": "Feature",
  "properties": {
    "addr:full":"189 Joseph St Kitchener ON N2G 1J8",
    "addr:housenumber":"189",
    "addr:postcode":"n2g 1j8",
    "addr:street":"Joseph St",
    "iso:country":"CA",
    "sg:address":"189 Joseph St",
    "sg:city":"Kitchener",
    "sg:classifiers":[
        {
            "category":"Building & Trades",
            "subcategory":"Electrical",
            "type":"Services"
        }
    ],
    "sg:phone":"+1 519 576 0718",
    "sg:postcode":"N2G 1J8",
    "sg:province":"ON",
    "sg:tags":[
        "electric",
        "contractor"
    ],
    "wof:name":"Patlin Electric Ltd",
    "wof:placetype":"venue"
},
  "geometry": {"coordinates":[-80.49895477290001,43.4506034851],"type":"Point"}
}