{
  "type": "Feature",
  "properties": {
    "addr:full":"Terrace BC V8G 1S6",
    "addr:postcode":"v8g 1s6",
    "iso:country":"CA",
    "sg:city":"Terrace",
    "sg:classifiers":[
        {
            "category":"Professional",
            "subcategory":"Management & Consulting",
            "type":"Services"
        }
    ],
    "sg:phone":"+1 250 635 5449",
    "sg:postcode":"V8G 1S6",
    "sg:province":"BC",
    "sg:tags":[
        "consultant",
        "business"
    ],
    "wof:name":"16-37 Community Futures & Bus",
    "wof:placetype":"venue"
},
  "geometry": {"coordinates":[-128.589417,54.517643],"type":"Point"}
}