{
  "type": "Feature",
  "properties": {
    "addr:full":"1762 Bedford Hwy Bedford NS B4A 1G2",
    "addr:housenumber":"1762",
    "addr:postcode":"b4a 1g2",
    "addr:street":"Bedford Hwy",
    "iso:country":"CA",
    "sg:address":"1762 Bedford Hwy",
    "sg:city":"Bedford",
    "sg:classifiers":[
        {
            "category":"Restaurant",
            "type":"Food & Drink"
        }
    ],
    "sg:phone":"+1 902 835 1788",
    "sg:postcode":"B4A 1G2",
    "sg:province":"NS",
    "wof:name":"Arby's",
    "wof:placetype":"venue"
},
  "geometry": {"coordinates":[-63.655002594,44.740436554],"type":"Point"}
}