{
  "type": "Feature",
  "properties": {
    "addr:full":"32 Grand Ave S Cambridge ON N1S 2L6",
    "addr:housenumber":"32",
    "addr:postcode":"n1s 2l6",
    "addr:street":"Grand Ave S",
    "iso:country":"CA",
    "sg:address":"32 Grand Ave S",
    "sg:city":"Cambridge",
    "sg:classifiers":[
        {
            "category":"Real Estate",
            "subcategory":"Real Estate Agent",
            "type":"Services"
        }
    ],
    "sg:phone":"+1 519 622 2130",
    "sg:postcode":"N1S 2L6",
    "sg:province":"ON",
    "wof:name":"Gord Ridsdale Realty Ltd",
    "wof:placetype":"venue"
},
  "geometry": {"coordinates":[-80.317673,43.357071],"type":"Point"}
}