{
  "type": "Feature",
  "properties": {
    "addr:full":"142 Albion St S Amherst NS B4H 4H4",
    "addr:housenumber":"142",
    "addr:postcode":"b4h 4h4",
    "addr:street":"Albion St S",
    "iso:country":"CA",
    "sg:address":"142 Albion St S",
    "sg:city":"Amherst",
    "sg:classifiers":[
        {
            "category":"Shopping",
            "subcategory":"Clothing, Apparel, & Fashions",
            "type":"Retail Goods"
        }
    ],
    "sg:phone":"+1 902 661 1589",
    "sg:postcode":"B4H 4H4",
    "sg:province":"NS",
    "wof:name":"Eclipse",
    "wof:placetype":"venue"
},
  "geometry": {"coordinates":[-64.202438,45.812096],"type":"Point"}
}