{
  "type": "Feature",
  "properties": {
    "addr:full":"Salmon Arm BC V1E 1J6",
    "addr:postcode":"v1e 1j6",
    "iso:country":"CA",
    "sg:city":"Salmon Arm",
    "sg:classifiers":[
        {
            "category":"Real Estate",
            "subcategory":"Real Estate Operator",
            "type":"Services"
        }
    ],
    "sg:phone":"+1 250 832 4666",
    "sg:postcode":"V1E 1J6",
    "sg:province":"BC",
    "sg:tags":[
        "mobile",
        "home",
        "community"
    ],
    "wof:name":"Evergreen Mobile Home Park",
    "wof:placetype":"venue"
},
  "geometry": {"coordinates":[-119.24567399999999,50.707035],"type":"Point"}
}