{
  "type": "Feature",
  "properties": {
    "addr:full":"2395 Boul Rosemont Montreal QC H2G 1T9",
    "addr:housenumber":"2395",
    "addr:postcode":"h2g 1t9",
    "addr:street":"Boul Rosemont",
    "iso:country":"CA",
    "sg:address":"2395 Boul Rosemont",
    "sg:city":"Montreal",
    "sg:classifiers":[
        {
            "category":"Health Services",
            "subcategory":"Doctor",
            "type":"Services"
        }
    ],
    "sg:phone":"+1 514 722 3151",
    "sg:postcode":"H2G 1T9",
    "sg:province":"QC",
    "sg:tags":[
        "dentist"
    ],
    "wof:name":"Clinique Dentaire Enrico",
    "wof:placetype":"venue"
},
  "geometry": {"coordinates":[-73.58704400000001,45.545795],"type":"Point"}
}