{
  "type": "Feature",
  "properties": {
    "iso:country":"CA",
    "sg:address":"2395 Boul Rosemont",
    "sg:city":"Montreal",
    "sg:classifiers":[
        {
            "category":"Health Services",
            "subcategory":"Doctor",
            "type":"Services"
        }
    ],
    "sg:phone":"+1 514 722 3151",
    "sg:postcode":"H2G 1T9",
    "sg:province":"QC",
    "sg:tags":[
        "dentist"
    ],
    "wof:name":"Clinique Dentaire Enrico",
    "wof:placetype":"venue"
},
  "geometry": {"coordinates":[-73.587044,45.545795],"type":"Point"}
}