{
  "type": "Feature",
  "properties": {
    "iso:country":"CA",
    "sg:address":"765 Balm Beach Rd",
    "sg:city":"Midland",
    "sg:classifiers":[
        {
            "category":"Cinema",
            "subcategory":"Movie Rental",
            "type":"Entertainment"
        }
    ],
    "sg:phone":"+1 705 526 2515",
    "sg:postcode":"L4R 4K4",
    "sg:province":"ON",
    "sg:tags":[
        "leasing",
        "video",
        "disc",
        "tape"
    ],
    "wof:name":"No Frills Super Video",
    "wof:placetype":"venue"
},
  "geometry": {"coordinates":[-79.90859985349999,44.7340164185],"type":"Point"}
}