{
  "type": "Feature",
  "properties": {
    "iso:country":"CA",
    "sg:address":"1647 Rue Fleury E",
    "sg:city":"Montreal",
    "sg:classifiers":[
        {
            "category":"Restaurant",
            "type":"Food & Drink"
        }
    ],
    "sg:phone":"+1 514 388 8676",
    "sg:postcode":"H2C 1S9",
    "sg:province":"QC",
    "wof:name":"Restaurant El Toro LA Maison",
    "wof:placetype":"venue"
},
  "geometry": {"coordinates":[-73.655563,45.564548],"type":"Point"}
}