{
  "type": "Feature",
  "properties": {
    "addr:full":"573 Goderich St Port Elgin ON N0H 2C0",
    "addr:housenumber":"573",
    "addr:postcode":"n0h 2c0",
    "addr:street":"Goderich St",
    "iso:country":"CA",
    "sg:address":"573 Goderich St",
    "sg:city":"Port Elgin",
    "sg:classifiers":[
        {
            "category":"Health Services",
            "subcategory":"Doctor",
            "type":"Services"
        }
    ],
    "sg:phone":"+1 519 832 5780",
    "sg:postcode":"N0H 2C0",
    "sg:province":"ON",
    "sg:tags":[
        "physician",
        "surgeon"
    ],
    "wof:name":"Von Heyman, J MD",
    "wof:placetype":"venue"
},
  "geometry": {"coordinates":[-81.3894577026,44.4352073669],"type":"Point"}
}