{
  "type": "Feature",
  "properties": {
    "iso:country":"CA",
    "sg:address":"2970 University Ave W",
    "sg:city":"Windsor",
    "sg:classifiers":[
        {
            "category":"Retail",
            "subcategory":"Auto Repair",
            "type":"Services"
        }
    ],
    "sg:phone":"+1 519 252 9089",
    "sg:postcode":"N9C 1G2",
    "sg:province":"ON",
    "sg:tags":[
        "repairing",
        "automobile"
    ],
    "wof:name":"Nick's Auto Clinic",
    "wof:placetype":"venue"
},
  "geometry": {"coordinates":[-83.072662,42.307106],"type":"Point"}
}