{
  "type": "Feature",
  "properties": {
    "addr:full":"65 Pembroke St W Pembroke ON K8A 5M5",
    "addr:housenumber":"65",
    "addr:postcode":"k8a 5m5",
    "addr:street":"Pembroke St W",
    "iso:country":"CA",
    "sg:address":"65 Pembroke St W",
    "sg:city":"Pembroke",
    "sg:classifiers":[
        {
            "category":"Shopping",
            "subcategory":"Jewelry",
            "type":"Retail Goods"
        }
    ],
    "sg:phone":"+1 613 732 2961",
    "sg:postcode":"K8A 5M5",
    "sg:province":"ON",
    "sg:tags":[
        "jeweler"
    ],
    "wof:name":"J Deacon Taylor Jewellers",
    "wof:placetype":"venue"
},
  "geometry": {"coordinates":[-77.11428100000001,45.826],"type":"Point"}
}