{
  "type": "Feature",
  "properties": {
    "addr:full":"625 Elphinstone St Regina SK S4T 3L1",
    "addr:housenumber":"625",
    "addr:postcode":"s4t 3l1",
    "addr:street":"Elphinstone St",
    "iso:country":"CA",
    "sg:address":"625 Elphinstone St",
    "sg:city":"Regina",
    "sg:classifiers":[
        {
            "category":"Education",
            "subcategory":"School",
            "type":"Public Place"
        }
    ],
    "sg:phone":"+1 306 791 7248",
    "sg:postcode":"S4T 3L1",
    "sg:province":"SK",
    "wof:name":"St Luke School",
    "wof:placetype":"venue"
},
  "geometry": {"coordinates":[-104.63104199999999,50.468922],"type":"Point"}
}