{
  "type": "Feature",
  "properties": {
    "addr:full":"3385 Muskoka Rd Bala ON P0C 1A0",
    "addr:housenumber":"3385",
    "addr:postcode":"p0c 1a0",
    "addr:street":"Muskoka Rd",
    "iso:country":"CA",
    "sg:address":"3385 Muskoka Rd",
    "sg:city":"Bala",
    "sg:classifiers":[
        {
            "category":"Shopping",
            "subcategory":"Bicycles & Sporting Goods",
            "type":"Retail Goods"
        }
    ],
    "sg:phone":"+1 705 762 5722",
    "sg:postcode":"P0C 1A0",
    "sg:province":"ON",
    "sg:tags":[
        "water",
        "equipment",
        "skiing",
        "supply"
    ],
    "wof:name":"Bush's Water Ski Ctr",
    "wof:placetype":"venue"
},
  "geometry": {"coordinates":[-79.6145935059,45.0164451599],"type":"Point"}
}