{
  "type": "Feature",
  "properties": {
    "addr:full":"4895 Delta St Delta BC V4K 2T9",
    "addr:housenumber":"4895",
    "addr:postcode":"v4k 2t9",
    "addr:street":"Delta St",
    "iso:country":"CA",
    "sg:address":"4895 Delta St",
    "sg:city":"Delta",
    "sg:classifiers":[
        {
            "category":"Manufacturing",
            "subcategory":"Signs",
            "type":"Manufacturing & Wholesale Goods"
        }
    ],
    "sg:phone":"+1 604 946 0884",
    "sg:postcode":"V4K 2T9",
    "sg:province":"BC",
    "wof:name":"Designs Instant Signs Ltd",
    "wof:placetype":"venue"
},
  "geometry": {"coordinates":[-123.086868,49.091873],"type":"Point"}
}