{
  "type": "Feature",
  "properties": {
    "addr:full":"Woodbridge ON L4L 9L3",
    "addr:postcode":"l4l 9l3",
    "iso:country":"CA",
    "sg:city":"Woodbridge",
    "sg:classifiers":[
        {
            "category":"Shopping",
            "subcategory":"Gifts & Souvenirs",
            "type":"Retail Goods"
        }
    ],
    "sg:phone":"+1 905 264 8496",
    "sg:postcode":"L4L 9L3",
    "sg:province":"ON",
    "sg:tags":[
        "shop"
    ],
    "wof:name":"English Butler",
    "wof:placetype":"venue"
},
  "geometry": {"coordinates":[-79.557281,43.78952],"type":"Point"}
}