{
  "type": "Feature",
  "properties": {
    "addr:full":"398 Steeles Ave W Thornhill ON L4J 6X6",
    "addr:housenumber":"398",
    "addr:postcode":"l4j 6x6",
    "addr:street":"Steeles Ave W",
    "iso:country":"CA",
    "sg:address":"398 Steeles Ave W",
    "sg:city":"Thornhill",
    "sg:classifiers":[
        {
            "category":"Travel",
            "subcategory":"Travel Agent",
            "type":"Entertainment"
        }
    ],
    "sg:phone":"+1 905 709 0147",
    "sg:postcode":"L4J 6X6",
    "sg:province":"ON",
    "sg:tags":[
        "agency",
        "bureau"
    ],
    "wof:name":"Travel in Style Inc",
    "wof:placetype":"venue"
},
  "geometry": {"coordinates":[-79.43380000000001,43.795166],"type":"Point"}
}