{
  "type": "Feature",
  "properties": {
    "iso:country":"CA",
    "sg:address":"40 Erskine Ave",
    "sg:city":"Toronto",
    "sg:classifiers":[
        {
            "category":"Education",
            "subcategory":"School",
            "type":"Public Place"
        }
    ],
    "sg:phone":"+1 416 393 0643",
    "sg:postcode":"M4P 1Y2",
    "sg:province":"ON",
    "wof:name":"John Fisher Junior Public Schl",
    "wof:placetype":"venue"
},
  "geometry": {"coordinates":[-79.397591,43.711552],"type":"Point"}
}