{
  "type": "Feature",
  "properties": {
    "addr:full":"109 Brant Ave Brantford ON N3T 3H4",
    "addr:housenumber":"109",
    "addr:postcode":"n3t 3h4",
    "addr:street":"Brant Ave",
    "iso:country":"CA",
    "sg:address":"109 Brant Ave",
    "sg:city":"Brantford",
    "sg:classifiers":[
        {
            "category":"Retail",
            "subcategory":"Repair Shop",
            "type":"Services"
        }
    ],
    "sg:phone":"+1 519 753 3218",
    "sg:postcode":"N3T 3H4",
    "sg:province":"ON",
    "sg:tags":[
        "lock",
        "locksmith"
    ],
    "wof:name":"Lloyd's Lock & Security",
    "wof:placetype":"venue"
},
  "geometry": {"coordinates":[-80.272346,43.142647],"type":"Point"}
}