{
  "type": "Feature",
  "properties": {
    "addr:full":"Etobicoke ON M8X 1Y6",
    "addr:postcode":"m8x 1y6",
    "iso:country":"CA",
    "sg:city":"Etobicoke",
    "sg:classifiers":[
        {
            "category":"Manufacturing",
            "subcategory":"Signs",
            "type":"Manufacturing & Wholesale Goods"
        }
    ],
    "sg:phone":"+1 416 231 2896",
    "sg:postcode":"M8X 1Y6",
    "sg:province":"ON",
    "wof:name":"Jiffy Sign",
    "wof:placetype":"venue"
},
  "geometry": {"coordinates":[-79.511337,43.660461],"type":"Point"}
}