{
  "type": "Feature",
  "properties": {
    "addr:full":"612 6th Ave Midway BC V0H 1M0",
    "addr:housenumber":"612",
    "addr:postcode":"v0h 1m0",
    "addr:street":"6Th Ave",
    "iso:country":"CA",
    "sg:address":"612 6th Ave",
    "sg:city":"Midway",
    "sg:classifiers":[
        {
            "category":"Education",
            "subcategory":"Library",
            "type":"Public Place"
        }
    ],
    "sg:phone":"+1 250 449 2620",
    "sg:postcode":"V0H 1M0",
    "sg:province":"BC",
    "wof:name":"Midway Public Library",
    "wof:placetype":"venue"
},
  "geometry": {"coordinates":[-118.775268555,49.0066413879],"type":"Point"}
}