{
  "type": "Feature",
  "properties": {
    "addr:full":"15 Rue Du College Saint-Adalbert QC G0R 2M0",
    "addr:housenumber":"15",
    "addr:postcode":"g0r 2m0",
    "addr:street":"Rue Du College",
    "iso:country":"CA",
    "sg:address":"15 Rue Du College",
    "sg:city":"Saint-Adalbert",
    "sg:classifiers":[
        {
            "category":"Education",
            "subcategory":"School",
            "type":"Public Place"
        }
    ],
    "sg:phone":"+1 418 356 5131",
    "sg:postcode":"G0R 2M0",
    "sg:province":"QC",
    "wof:name":"Ecole St-Adalbert",
    "wof:placetype":"venue"
},
  "geometry": {"coordinates":[-69.899902,46.865025],"type":"Point"}
}