{
  "type": "Feature",
  "properties": {
    "addr:full":"Penticton BC V2A 6E8",
    "addr:postcode":"v2a 6e8",
    "iso:country":"CA",
    "sg:city":"Penticton",
    "sg:classifiers":[
        {
            "category":"Personal",
            "subcategory":"Beauty Salon",
            "type":"Services"
        }
    ],
    "sg:phone":"+1 250 490 8515",
    "sg:postcode":"V2A 6E8",
    "sg:province":"BC",
    "wof:name":"Body & Sol Spa & Salon",
    "wof:placetype":"venue"
},
  "geometry": {"coordinates":[-119.58556400000001,49.46751],"type":"Point"}
}