{
  "type": "Feature",
  "properties": {
    "addr:full":"447 Rue Runnymede Dollard-Des-Ormeaux QC H9G 1K8",
    "addr:housenumber":"447",
    "addr:postcode":"h9g 1k8",
    "addr:street":"Rue Runnymede",
    "iso:country":"CA",
    "sg:address":"447 Rue Runnymede",
    "sg:city":"Dollard-Des-Ormeaux",
    "sg:classifiers":[
        {
            "category":"Building & Trades",
            "subcategory":"Construction",
            "type":"Services"
        }
    ],
    "sg:phone":"+1 514 626 0207",
    "sg:postcode":"H9G 1K8",
    "sg:province":"QC",
    "sg:tags":[
        "masonry",
        "contractor"
    ],
    "wof:name":"A & S Tuckpointing",
    "wof:placetype":"venue"
},
  "geometry": {"coordinates":[-73.83699,45.469864],"type":"Point"}
}