{
  "type": "Feature",
  "properties": {
    "iso:country":"CA",
    "sg:address":"777 Portage Ave",
    "sg:city":"Winnipeg",
    "sg:classifiers":[
        {
            "category":"Retail",
            "subcategory":"Animal Services",
            "type":"Services"
        }
    ],
    "sg:phone":"+1 204 943 9777",
    "sg:postcode":"R3G 0N3",
    "sg:province":"MB",
    "sg:tags":[
        "pet",
        "consultant"
    ],
    "wof:name":"Pet Plan Insurance",
    "wof:placetype":"venue"
},
  "geometry": {"coordinates":[-97.165237,49.886883],"type":"Point"}
}