{
  "type": "Feature",
  "properties": {
    "addr:full":"5209 Ladner Trunk Rd Delta BC V4K 1W4",
    "addr:housenumber":"5209",
    "addr:postcode":"v4k 1w4",
    "addr:street":"Ladner Trunk Rd",
    "iso:country":"CA",
    "sg:address":"5209 Ladner Trunk Rd",
    "sg:city":"Delta",
    "sg:classifiers":[
        {
            "category":"Shopping",
            "subcategory":"Gifts & Souvenirs",
            "type":"Retail Goods"
        }
    ],
    "sg:phone":"+1 604 940 1812",
    "sg:postcode":"V4K 1W4",
    "sg:province":"BC",
    "sg:tags":[
        "shop"
    ],
    "wof:name":"Fancy This Gift Boutique",
    "wof:placetype":"venue"
},
  "geometry": {"coordinates":[-123.078667,49.090328],"type":"Point"}
}