{
  "type": "Feature",
  "properties": {
    "addr:full":"502 Bayfield St Barrie ON L4M 5A2",
    "addr:housenumber":"502",
    "addr:postcode":"l4m 5a2",
    "addr:street":"Bayfield St",
    "iso:country":"CA",
    "sg:address":"502 Bayfield St",
    "sg:city":"Barrie",
    "sg:classifiers":[
        {
            "category":"Restaurant",
            "type":"Food & Drink"
        }
    ],
    "sg:phone":"+1 705 721 5722",
    "sg:postcode":"L4M 5A2",
    "sg:province":"ON",
    "wof:name":"East Side Mario's",
    "wof:placetype":"venue"
},
  "geometry": {"coordinates":[-79.7113952637,44.4134674072],"type":"Point"}
}