{
  "type": "Feature",
  "properties": {
    "addr:full":"Saskatoon SK S7N 3R3",
    "addr:postcode":"s7n 3r3",
    "iso:country":"CA",
    "sg:city":"Saskatoon",
    "sg:classifiers":[
        {
            "category":"Professional",
            "subcategory":"Research",
            "type":"Services"
        }
    ],
    "sg:phone":"+1 306 373 1110",
    "sg:postcode":"S7N 3R3",
    "sg:province":"SK",
    "sg:tags":[
        "environmental",
        "ecological"
    ],
    "wof:name":"Northern Enviro Search",
    "wof:placetype":"venue"
},
  "geometry": {"coordinates":[-106.63035600000001,52.142311],"type":"Point"}
}