{
  "type": "Feature",
  "properties": {
    "addr:full":"302 Victoria St E Alliston ON L9R 1T7",
    "addr:housenumber":"302",
    "addr:postcode":"l9r 1t7",
    "addr:street":"Victoria St E Alliston",
    "iso:country":"CA",
    "sg:address":"302 Victoria St E",
    "sg:city":"Alliston",
    "sg:classifiers":[
        {
            "category":"Shopping",
            "subcategory":"Used Merchandise",
            "type":"Retail Goods"
        }
    ],
    "sg:phone":"+1 705 435 3094",
    "sg:postcode":"L9R 1T7",
    "sg:province":"ON",
    "sg:tags":[
        "second",
        "store",
        "hand"
    ],
    "wof:name":"Global Village Shoppe",
    "wof:placetype":"venue"
},
  "geometry": {"coordinates":[-79.856056,44.15696],"type":"Point"}
}