{
  "type": "Feature",
  "properties": {
    "iso:country":"CA",
    "sg:address":"282 Rue DE Dublin",
    "sg:city":"Charlesbourg",
    "sg:classifiers":[
        {
            "category":"Travel",
            "subcategory":"Campground",
            "type":"Entertainment"
        }
    ],
    "sg:phone":"+1 418 849 7441",
    "sg:postcode":"G2M 1C5",
    "sg:province":"QC",
    "wof:name":"Camping Plage Laurentide",
    "wof:placetype":"venue"
},
  "geometry": {"coordinates":[-71.299103,46.904846],"type":"Point"}
}