{
  "type": "Feature",
  "properties": {
    "addr:full":"14740 111 Ave NW Edmonton AB T5M 2P5",
    "addr:housenumber":"14740",
    "addr:postcode":"t5m 2p5",
    "addr:street":"111 Ave Nw",
    "iso:country":"CA",
    "sg:address":"14740 111 Ave NW",
    "sg:city":"Edmonton",
    "sg:classifiers":[
        {
            "category":"Food & Beverages",
            "subcategory":"Groceries & Convenience Stores",
            "type":"Retail Goods"
        }
    ],
    "sg:phone":"+1 780 452 5411",
    "sg:postcode":"T5M 2P5",
    "sg:province":"AB",
    "sg:tags":[
        "grocer"
    ],
    "wof:name":"Real Canadian Wholesale Club",
    "wof:placetype":"venue"
},
  "geometry": {"coordinates":[-113.574684,53.559078],"type":"Point"}
}