{
  "type": "Feature",
  "properties": {
    "addr:full":"390 Midwest Rd Scarborough ON M1P 3B5",
    "addr:housenumber":"390",
    "addr:postcode":"m1p 3b5",
    "addr:street":"Midwest Rd",
    "iso:country":"CA",
    "sg:address":"390 Midwest Rd",
    "sg:city":"Scarborough",
    "sg:classifiers":[
        {
            "category":"Manufacturing",
            "subcategory":"Tools & Machinery",
            "type":"Manufacturing & Wholesale Goods"
        }
    ],
    "sg:phone":"+1 416 751 8570",
    "sg:postcode":"M1P 3B5",
    "sg:province":"ON",
    "sg:tags":[
        "equipment",
        "electric"
    ],
    "wof:name":"Trench Ltd",
    "wof:placetype":"venue"
},
  "geometry": {"coordinates":[-79.271629,43.761356],"type":"Point"}
}