{
  "type": "Feature",
  "properties": {
    "iso:country":"CA",
    "sg:city":"Val-Des-Bois",
    "sg:classifiers":[
        {
            "category":"Social Services",
            "type":"Services"
        }
    ],
    "sg:phone":"+1 819 454 2355",
    "sg:postcode":"J0X 3C0",
    "sg:province":"QC",
    "sg:tags":[
        "organization",
        "welfare"
    ],
    "wof:name":"Clsc Vallee DE LA Lievre",
    "wof:placetype":"venue"
},
  "geometry": {"coordinates":[-75.5955276489,45.9125328064],"type":"Point"}
}