{
  "type": "Feature",
  "properties": {
    "addr:full":"1836 Davenport Rd Toronto ON M6N 1B7",
    "addr:housenumber":"1836",
    "addr:postcode":"m6n 1b7",
    "addr:street":"Davenport Rd",
    "iso:country":"CA",
    "sg:address":"1836 Davenport Rd",
    "sg:city":"Toronto",
    "sg:classifiers":[
        {
            "category":"Retail",
            "subcategory":"Repair Shop",
            "type":"Services"
        }
    ],
    "sg:phone":"+1 416 656 1700",
    "sg:postcode":"M6N 1B7",
    "sg:province":"ON",
    "sg:tags":[
        "refinishing",
        "furniture"
    ],
    "wof:name":"Bamboo Bazaar",
    "wof:placetype":"venue"
},
  "geometry": {"coordinates":[-79.45264434809999,43.6709327698],"type":"Point"}
}