{
  "type": "Feature",
  "properties": {
    "addr:full":"74 Rue Boulanger S Victoriaville QC G6P 3V1",
    "addr:housenumber":"74",
    "addr:postcode":"g6p 3v1",
    "addr:street":"Rue Boulanger S",
    "iso:country":"CA",
    "sg:address":"74 Rue Boulanger S",
    "sg:city":"Victoriaville",
    "sg:classifiers":[
        {
            "category":"Personal",
            "subcategory":"Beauty Salon",
            "type":"Services"
        }
    ],
    "sg:phone":"+1 819 758 3338",
    "sg:postcode":"G6P 3V1",
    "sg:province":"QC",
    "wof:name":"Salon DE Coiffure Concept 9",
    "wof:placetype":"venue"
},
  "geometry": {"coordinates":[-71.94564099999999,46.065426],"type":"Point"}
}