{
  "type": "Feature",
  "properties": {
    "addr:full":"233 Elgin St Ottawa ON K2P 1L6",
    "addr:housenumber":"233",
    "addr:postcode":"k2p 1l6",
    "addr:street":"Elgin St",
    "iso:country":"CA",
    "sg:address":"233 Elgin St",
    "sg:city":"Ottawa",
    "sg:classifiers":[
        {
            "category":"Personal",
            "subcategory":"Barber",
            "type":"Services"
        }
    ],
    "sg:phone":"+1 613 235 3841",
    "sg:postcode":"K2P 1L6",
    "sg:province":"ON",
    "wof:name":"Roma Barber Shop",
    "wof:placetype":"venue"
},
  "geometry": {"coordinates":[-75.6910858154,45.4189224243],"type":"Point"}
}