{
  "type": "Feature",
  "properties": {
    "addr:full":"Scarborough ON M1S 4Z4",
    "addr:postcode":"m1s 4z4",
    "iso:country":"CA",
    "sg:city":"Scarborough",
    "sg:classifiers":[
        {
            "category":"Travel",
            "subcategory":"Travel Agent",
            "type":"Entertainment"
        }
    ],
    "sg:phone":"+1 416 292 6200",
    "sg:postcode":"M1S 4Z4",
    "sg:province":"ON",
    "sg:tags":[
        "agency",
        "bureau"
    ],
    "wof:name":"Air Link Travel Ltd",
    "wof:placetype":"venue"
},
  "geometry": {"coordinates":[-79.25721,43.810101],"type":"Point"}
}