{
  "type": "Feature",
  "properties": {
    "addr:full":"Lakeview Ave Buchans NL A0H 1G0",
    "addr:postcode":"a0h 1g0",
    "addr:street":"Lakeview Ave",
    "iso:country":"CA",
    "sg:address":"Lakeview Ave",
    "sg:city":"Buchans",
    "sg:classifiers":[
        {
            "category":"Organizations",
            "subcategory":"Religious Organization",
            "type":"Services"
        }
    ],
    "sg:phone":"+1 709 672 3754",
    "sg:postcode":"A0H 1G0",
    "sg:province":"NL",
    "sg:tags":[
        "church"
    ],
    "wof:name":"Salvation Army",
    "wof:placetype":"venue"
},
  "geometry": {"coordinates":[-56.855198,48.825554],"type":"Point"}
}