{
  "type": "Feature",
  "properties": {
    "iso:country":"CA",
    "sg:address":"560 Main St",
    "sg:city":"Glace Bay",
    "sg:classifiers":[
        {
            "category":"Manufacturing",
            "subcategory":"Printing",
            "type":"Manufacturing & Wholesale Goods"
        }
    ],
    "sg:phone":"+1 902 849 5002",
    "sg:postcode":"B1A 4X6",
    "sg:province":"NS",
    "sg:tags":[
        "printer"
    ],
    "wof:name":"Robertson Print-Craft Ltd",
    "wof:placetype":"venue"
},
  "geometry": {"coordinates":[-59.9536972046,46.1972885132],"type":"Point"}
}