{
  "type": "Feature",
  "properties": {
    "addr:full":"512 Main St NW Turner Valley AB T0L 2A0",
    "addr:housenumber":"512",
    "addr:postcode":"t0l 2a0",
    "addr:street":"Main St Nw",
    "iso:country":"CA",
    "sg:address":"512 Main St NW",
    "sg:city":"Turner Valley",
    "sg:classifiers":[
        {
            "category":"Professional",
            "subcategory":"Computer Services",
            "type":"Services"
        }
    ],
    "sg:phone":"+1 403 933 2996",
    "sg:postcode":"T0L 2A0",
    "sg:province":"AB",
    "sg:tags":[
        "scanning"
    ],
    "wof:name":"Wolfpack Studio",
    "wof:placetype":"venue"
},
  "geometry": {"coordinates":[-114.279022,50.678741],"type":"Point"}
}