{
  "type": "Feature",
  "properties": {
    "addr:full":"3083 River Dr Thornhill BC V8G 3P6",
    "addr:housenumber":"3083",
    "addr:postcode":"v8g 3p6",
    "addr:street":"River Dr",
    "iso:country":"CA",
    "sg:address":"3083 River Dr",
    "sg:city":"Thornhill",
    "sg:classifiers":[
        {
            "category":"Wholesale",
            "subcategory":"Auto Parts",
            "type":"Manufacturing & Wholesale Goods"
        }
    ],
    "sg:phone":"+1 250 635 7726",
    "sg:postcode":"V8G 3P6",
    "sg:province":"BC",
    "sg:tags":[
        "automobile",
        "supply"
    ],
    "wof:name":"Big D's Automotive",
    "wof:placetype":"venue"
},
  "geometry": {"coordinates":[-128.543533325,54.5151405334],"type":"Point"}
}