{
  "type": "Feature",
  "properties": {
    "addr:full":"500 E 4th Ave Regina SK S4N 4Z5",
    "addr:housenumber":"500",
    "addr:postcode":"s4n 4z5",
    "addr:street":"E 4Th Ave",
    "iso:country":"CA",
    "sg:address":"500 E 4th Ave",
    "sg:city":"Regina",
    "sg:classifiers":[
        {
            "category":"Manufacturing",
            "subcategory":"Tools & Machinery",
            "type":"Manufacturing & Wholesale Goods"
        }
    ],
    "sg:phone":"+1 306 757 3533",
    "sg:postcode":"S4N 4Z5",
    "sg:province":"SK",
    "sg:tags":[
        "equipment",
        "station"
    ],
    "wof:name":"Capital Petroleum Svc Ltd",
    "wof:placetype":"venue"
},
  "geometry": {"coordinates":[-104.57634,50.463108],"type":"Point"}
}