{
  "type": "Feature",
  "properties": {
    "addr:full":"1592 Ch Pierre-Peladeau Sainte-Adele QC J8B 1Z5",
    "addr:postcode":"1592;j8b 1z5",
    "addr:street":"Ch Pierre-Peladeau Sainte-Adele",
    "iso:country":"CA",
    "sg:address":"1592 Ch Pierre-Peladeau",
    "sg:city":"Sainte-Adele",
    "sg:classifiers":[
        {
            "category":"Professional",
            "subcategory":"Business Services",
            "type":"Services"
        }
    ],
    "sg:phone":"+1 450 229 5602",
    "sg:postcode":"J8B 1Z5",
    "sg:province":"QC",
    "sg:tags":[
        "designer",
        "dealer",
        "pool",
        "swimming"
    ],
    "wof:name":"Ckc Sports Inc",
    "wof:placetype":"venue"
},
  "geometry": {"coordinates":[-74.119095,45.988564],"type":"Point"}
}