{
  "type": "Feature",
  "properties": {
    "addr:full":"488 Ch Des Patriotes S Mont-Saint-Hilaire QC J3H 3G8",
    "addr:housenumber":"488",
    "addr:postcode":"j3h 3g8",
    "addr:street":"Ch Des Patriotes S Mont-Saint-Hilaire",
    "iso:country":"CA",
    "sg:address":"488 Ch Des Patriotes S",
    "sg:city":"Mont-Saint-Hilaire",
    "sg:classifiers":[
        {
            "category":"Restaurant",
            "type":"Food & Drink"
        }
    ],
    "sg:phone":"+1 450 446 8888",
    "sg:postcode":"J3H 3G8",
    "sg:province":"QC",
    "wof:name":"Restaurant Du Pont Noir",
    "wof:placetype":"venue"
},
  "geometry": {"coordinates":[-73.2052230835,45.5491714478],"type":"Point"}
}