{
  "type": "Feature",
  "properties": {
    "addr:full":"637 Main St Winnipeg MB R3B 1E3",
    "addr:housenumber":"637",
    "addr:postcode":"r3b 1e3",
    "addr:street":"Main St",
    "iso:country":"CA",
    "sg:address":"637 Main St",
    "sg:city":"Winnipeg",
    "sg:classifiers":[
        {
            "category":"Shopping",
            "subcategory":"Crafts & Fabrics",
            "type":"Retail Goods"
        }
    ],
    "sg:phone":"+1 204 942 6327",
    "sg:postcode":"R3B 1E3",
    "sg:province":"MB",
    "sg:tags":[
        "shop",
        "textile"
    ],
    "wof:name":"Mitchell Fabrics Ltd",
    "wof:placetype":"venue"
},
  "geometry": {"coordinates":[-97.13544464109999,49.9026412964],"type":"Point"}
}