{
  "type": "Feature",
  "properties": {
    "addr:full":"165 Rue Joseph-Carrier Vaudreuil-Dorion QC J7V 5V5",
    "addr:housenumber":"165",
    "addr:postcode":"j7v 5v5",
    "addr:street":"Rue Joseph-Carrier",
    "iso:country":"CA",
    "sg:address":"165 Rue Joseph-Carrier",
    "sg:city":"Vaudreuil-Dorion",
    "sg:classifiers":[
        {
            "category":"Wholesale",
            "subcategory":"Seafood",
            "type":"Manufacturing & Wholesale Goods"
        }
    ],
    "sg:phone":"+1 450 455 7219",
    "sg:postcode":"J7V 5V5",
    "sg:province":"QC",
    "wof:name":"Distributeur Homards Rb Inc",
    "wof:placetype":"venue"
},
  "geometry": {"coordinates":[-74.04429626460001,45.4090499878],"type":"Point"}
}