{
  "type": "Feature",
  "properties": {
    "addr:full":"92 Sand Bay Rd Combermere ON K0J 1L0",
    "addr:housenumber":"92",
    "addr:postcode":"k0j 1l0",
    "addr:street":"Sand Bay Rd",
    "iso:country":"CA",
    "sg:address":"92 Sand Bay Rd",
    "sg:city":"Combermere",
    "sg:classifiers":[
        {
            "category":"Travel",
            "subcategory":"Campground",
            "type":"Entertainment"
        }
    ],
    "sg:phone":"+1 613 756 5060",
    "sg:postcode":"K0J 1L0",
    "sg:province":"ON",
    "sg:tags":[
        "tourist",
        "accommodation"
    ],
    "wof:name":"Sand Bay Camp",
    "wof:placetype":"venue"
},
  "geometry": {"coordinates":[-77.614182,45.365211],"type":"Point"}
}