{
  "type": "Feature",
  "properties": {
    "addr:full":"Etobicoke ON M9W 5A3",
    "addr:postcode":"m9w 5a3",
    "iso:country":"CA",
    "sg:city":"Etobicoke",
    "sg:classifiers":[
        {
            "category":"Shopping",
            "subcategory":"Computers & Home Electronics",
            "type":"Retail Goods"
        }
    ],
    "sg:phone":"+1 416 248 5757",
    "sg:postcode":"M9W 5A3",
    "sg:province":"ON",
    "sg:tags":[
        "parts",
        "supply"
    ],
    "wof:name":"Laser Choices",
    "wof:placetype":"venue"
},
  "geometry": {"coordinates":[-79.579018,43.686306],"type":"Point"}
}