{
  "type": "Feature",
  "properties": {
    "addr:full":"1300 Pinecrest Rd # 110 Ottawa ON K2C 3M5",
    "addr:housenumber":"1300",
    "addr:postcode":"k2c 3m5",
    "addr:street":"Pinecrest Rd # 110",
    "iso:country":"CA",
    "sg:address":"1300 Pinecrest Rd # 110",
    "sg:city":"Ottawa",
    "sg:classifiers":[
        {
            "category":"Real Estate",
            "subcategory":"Real Estate Operator",
            "type":"Services"
        }
    ],
    "sg:phone":"+1 613 828 0181",
    "sg:postcode":"K2C 3M5",
    "sg:province":"ON",
    "sg:tags":[
        "apartment"
    ],
    "wof:name":"Riviera Gate Apartments",
    "wof:placetype":"venue"
},
  "geometry": {"coordinates":[-75.786934,45.343735],"type":"Point"}
}