{
  "type": "Feature",
  "properties": {
    "addr:full":"730 Albert St Regina SK S4R 2P5",
    "addr:housenumber":"730",
    "addr:postcode":"s4r 2p5",
    "addr:street":"Albert St",
    "iso:country":"CA",
    "sg:address":"730 Albert St",
    "sg:city":"Regina",
    "sg:classifiers":[
        {
            "category":"Shopping",
            "subcategory":"Hobbies, Toys, & Games",
            "type":"Retail Goods"
        }
    ],
    "sg:phone":"+1 306 781 8697",
    "sg:postcode":"S4R 2P5",
    "sg:province":"SK",
    "wof:name":"Toys 'R' US",
    "wof:placetype":"venue"
},
  "geometry": {"coordinates":[-104.618438721,50.4671325684],"type":"Point"}
}