{
  "type": "Feature",
  "properties": {
    "addr:full":"Dartmouth NS B3B 1W2",
    "addr:postcode":"b3b 1w2",
    "iso:country":"CA",
    "sg:city":"Dartmouth",
    "sg:classifiers":[
        {
            "category":"Shopping",
            "subcategory":"Computers & Home Electronics",
            "type":"Retail Goods"
        }
    ],
    "sg:phone":"+1 902 468 5557",
    "sg:postcode":"B3B 1W2",
    "sg:province":"NS",
    "sg:tags":[
        "radio",
        "television",
        "video",
        "equipment"
    ],
    "wof:name":"Inter-City Electronics",
    "wof:placetype":"venue"
},
  "geometry": {"coordinates":[-63.580925,44.6996],"type":"Point"}
}