{
  "type": "Feature",
  "properties": {
    "addr:full":"231 3rd Ave W Prince Rupert BC V8J 1L2",
    "addr:housenumber":"231",
    "addr:postcode":"v8j 1l2",
    "addr:street":"3Rd Ave W",
    "iso:country":"CA",
    "sg:address":"231 3rd Ave W",
    "sg:city":"Prince Rupert",
    "sg:classifiers":[
        {
            "category":"Banks & Credit Unions",
            "subcategory":"Bank",
            "type":"Services"
        }
    ],
    "sg:phone":"+1 250 622 2390",
    "sg:postcode":"V8J 1L2",
    "sg:province":"BC",
    "sg:tags":[
        "cashing",
        "loan",
        "real estate",
        "check"
    ],
    "wof:name":"Instaloans Financial Solutions",
    "wof:placetype":"venue"
},
  "geometry": {"coordinates":[-130.32252500000001,54.313946],"type":"Point"}
}