{
  "type": "Feature",
  "properties": {
    "addr:full":"374 Wilbrod St Ottawa ON K1N 6M8",
    "addr:housenumber":"374",
    "addr:postcode":"k1n 6m8",
    "addr:street":"Wilbrod St",
    "iso:country":"CA",
    "sg:address":"374 Wilbrod St",
    "sg:city":"Ottawa",
    "sg:classifiers":[
        {
            "category":"Building & Trades",
            "subcategory":"Construction",
            "type":"Services"
        }
    ],
    "sg:phone":"+1 613 237 4420",
    "sg:postcode":"K1N 6M8",
    "sg:province":"ON",
    "sg:tags":[
        "seafood",
        "contractor"
    ],
    "wof:name":"Captecon Inc",
    "wof:placetype":"venue"
},
  "geometry": {"coordinates":[-75.678467,45.428337],"type":"Point"}
}