{
  "type": "Feature",
  "properties": {
    "addr:full":"6726 4 St NE Calgary AB T2K 6G9",
    "addr:housenumber":"6726 4",
    "addr:postcode":"t2k 6g9",
    "addr:street":"St Ne",
    "iso:country":"CA",
    "sg:address":"6726 4 St NE",
    "sg:city":"Calgary",
    "sg:classifiers":[
        {
            "category":"Personal",
            "subcategory":"Beauty Salon",
            "type":"Services"
        }
    ],
    "sg:phone":"+1 403 275 8535",
    "sg:postcode":"T2K 6G9",
    "sg:province":"AB",
    "wof:name":"First Choice Haircutters",
    "wof:placetype":"venue"
},
  "geometry": {"coordinates":[-114.056167602,51.1128578186],"type":"Point"}
}