{
  "type": "Feature",
  "properties": {
    "addr:full":"294 Main St Toronto ON M4C 4X5",
    "addr:housenumber":"294",
    "addr:postcode":"m4c 4x5",
    "addr:street":"Main St",
    "iso:country":"CA",
    "sg:address":"294 Main St",
    "sg:city":"Toronto",
    "sg:classifiers":[
        {
            "category":"Shopping",
            "subcategory":"Optical Goods",
            "type":"Retail Goods"
        }
    ],
    "sg:phone":"+1 416 690 4649",
    "sg:postcode":"M4C 4X5",
    "sg:province":"ON",
    "sg:tags":[
        "optician"
    ],
    "wof:name":"Optimart",
    "wof:placetype":"venue"
},
  "geometry": {"coordinates":[-79.30188,43.687973],"type":"Point"}
}