{
  "type": "Feature",
  "properties": {
    "iso:country":"CA",
    "sg:address":"752 Ch Du Mont-Granit S",
    "sg:city":"Thetford Mines",
    "sg:classifiers":[
        {
            "category":"Manufacturing",
            "subcategory":"Tools & Machinery",
            "type":"Manufacturing & Wholesale Goods"
        }
    ],
    "sg:phone":"+1 418 335 6155",
    "sg:postcode":"G6G 5R7",
    "sg:province":"QC",
    "sg:tags":[
        "equipment",
        "system",
        "automation"
    ],
    "wof:name":"Bic Inc",
    "wof:placetype":"venue"
},
  "geometry": {"coordinates":[-71.2908401489,46.0658531189],"type":"Point"}
}