{
  "type": "Feature",
  "properties": {
    "addr:full":"384 Smythe St Fredericton NB E3B 3E4",
    "addr:housenumber":"384",
    "addr:postcode":"e3b 3e4",
    "addr:street":"Smythe St",
    "iso:country":"CA",
    "sg:address":"384 Smythe St",
    "sg:city":"Fredericton",
    "sg:classifiers":[
        {
            "category":"Organizations",
            "subcategory":"Professional Association",
            "type":"Services"
        }
    ],
    "sg:phone":"+1 506 453 0747",
    "sg:postcode":"E3B 3E4",
    "sg:province":"NB",
    "sg:tags":[
        "nurse",
        "unlicensed"
    ],
    "wof:name":"L'Association Des Infirmieres",
    "wof:placetype":"venue"
},
  "geometry": {"coordinates":[-66.6547622681,45.960105896],"type":"Point"}
}