{
  "type": "Feature",
  "properties": {
    "addr:full":"Saint-Jean-Chrysostome QC G6Z 2E5",
    "addr:postcode":"g6z 2e5",
    "iso:country":"CA",
    "sg:city":"Saint-Jean-Chrysostome",
    "sg:classifiers":[
        {
            "category":"Professional",
            "subcategory":"Credit Reporting & Collection",
            "type":"Services"
        }
    ],
    "sg:phone":"+1 418 834 0110",
    "sg:postcode":"G6Z 2E5",
    "sg:province":"QC",
    "sg:tags":[
        "agency"
    ],
    "wof:name":"Rsm D.net",
    "wof:placetype":"venue"
},
  "geometry": {"coordinates":[-71.20208740229999,46.7243423462],"type":"Point"}
}