{
  "type": "Feature",
  "properties": {
    "addr:full":"Hampton ON L0B 1J0",
    "addr:postcode":"l0b 1j0",
    "iso:country":"CA",
    "sg:city":"Hampton",
    "sg:classifiers":[
        {
            "category":"Building & Trades",
            "subcategory":"Construction",
            "type":"Services"
        }
    ],
    "sg:phone":"+1 905 263 8515",
    "sg:postcode":"L0B 1J0",
    "sg:province":"ON",
    "sg:tags":[
        "excavating",
        "contractor"
    ],
    "wof:name":"Jed's Backhoe & Excavating",
    "wof:placetype":"venue"
},
  "geometry": {"coordinates":[-78.7511291504,43.9625205994],"type":"Point"}
}