{
  "type": "Feature",
  "properties": {
    "addr:full":"5036 51st Ave Viking AB T0B 4N0",
    "addr:housenumber":"5036",
    "addr:postcode":"t0b 4n0",
    "addr:street":"51St Ave",
    "iso:country":"CA",
    "sg:address":"5036 51st Ave",
    "sg:city":"Viking",
    "sg:classifiers":[
        {
            "category":"Restaurant",
            "type":"Food & Drink"
        }
    ],
    "sg:phone":"+1 780 336 4740",
    "sg:postcode":"T0B 4N0",
    "sg:province":"AB",
    "wof:name":"Burger Queen",
    "wof:placetype":"venue"
},
  "geometry": {"coordinates":[-111.780517578,53.0942611694],"type":"Point"}
}