{
  "type": "Feature",
  "properties": {
    "iso:country":"CA",
    "sg:address":"110 Brock St",
    "sg:city":"Smithville",
    "sg:classifiers":[
        {
            "category":"Restaurant",
            "type":"Food & Drink"
        }
    ],
    "sg:phone":"+1 905 957 7778",
    "sg:postcode":"L0R 2A0",
    "sg:province":"ON",
    "sg:tags":[
        "pizza"
    ],
    "wof:name":"Smithville Pizzeria & Rstrnt",
    "wof:placetype":"venue"
},
  "geometry": {"coordinates":[-79.5452804565,43.0985832214],"type":"Point"}
}