{
  "type": "Feature",
  "properties": {
    "iso:country":"CA",
    "sg:address":"2475 Rue Notre-Dame O",
    "sg:city":"Montreal",
    "sg:classifiers":[
        {
            "category":"Shopping",
            "subcategory":"Used Merchandise",
            "type":"Retail Goods"
        }
    ],
    "sg:phone":"+1 514 846 3314",
    "sg:postcode":"H3J 1N6",
    "sg:province":"QC",
    "sg:tags":[
        "antique"
    ],
    "wof:name":"Arcadia Antiquites & Arts",
    "wof:placetype":"venue"
},
  "geometry": {"coordinates":[-73.54467010499999,45.5289726257],"type":"Point"}
}