{
  "type": "Feature",
  "properties": {
    "addr:full":"237 Wellington St London ON N6B 2L2",
    "addr:housenumber":"237",
    "addr:postcode":"n6b 2l2",
    "addr:street":"Wellington St",
    "iso:country":"CA",
    "sg:address":"237 Wellington St",
    "sg:city":"London",
    "sg:classifiers":[
        {
            "category":"Food & Beverages",
            "subcategory":"Groceries & Convenience Stores",
            "type":"Retail Goods"
        }
    ],
    "sg:phone":"+1 519 434 5953",
    "sg:postcode":"N6B 2L2",
    "sg:province":"ON",
    "sg:tags":[
        "grocer"
    ],
    "wof:name":"Murray's Food & Variety Store",
    "wof:placetype":"venue"
},
  "geometry": {"coordinates":[-81.242813,42.979729],"type":"Point"}
}