{
  "type": "Feature",
  "properties": {
    "addr:full":"11083 Boul Saint-Vital Montreal-Nord QC H1H 4T7",
    "addr:housenumber":"11083",
    "addr:postcode":"h1h 4t7",
    "addr:street":"Boul Saint-Vital",
    "iso:country":"CA",
    "sg:address":"11083 Boul Saint-Vital",
    "sg:city":"Montreal-Nord",
    "sg:classifiers":[
        {
            "category":"Recreation",
            "type":"Entertainment"
        }
    ],
    "sg:phone":"+1 514 323 7017",
    "sg:postcode":"H1H 4T7",
    "sg:province":"QC",
    "sg:tags":[
        "book",
        "dealer",
        "astrologer"
    ],
    "wof:name":"A LA Maison Sciences Occultes",
    "wof:placetype":"venue"
},
  "geometry": {"coordinates":[-73.64553070069999,45.5896606445],"type":"Point"}
}