{
  "type": "Feature",
  "properties": {
    "iso:country":"CA",
    "sg:city":"Calgary",
    "sg:classifiers":[
        {
            "category":"Building & Trades",
            "subcategory":"Plumbing",
            "type":"Services"
        }
    ],
    "sg:phone":"+1 403 279 3633",
    "sg:postcode":"T2C 2H9",
    "sg:province":"AB",
    "sg:tags":[
        "system",
        "air",
        "equipment",
        "refrigeration",
        "conditioning",
        "contractor"
    ],
    "wof:name":"Polar Mobility Research Ltd",
    "wof:placetype":"venue"
},
  "geometry": {"coordinates":[-113.97936248800001,50.9879875183],"type":"Point"}
}