{
  "type": "Feature",
  "properties": {
    "addr:full":"67 Boul Leveille Saint-Eustache QC J7R 7A6",
    "addr:housenumber":"67",
    "addr:postcode":"j7r 7a6",
    "addr:street":"Boul Leveille",
    "iso:country":"CA",
    "sg:address":"67 Boul Leveille",
    "sg:city":"Saint-Eustache",
    "sg:classifiers":[
        {
            "category":"Manufacturing",
            "subcategory":"Signs",
            "type":"Manufacturing & Wholesale Goods"
        }
    ],
    "sg:phone":"+1 450 472 3300",
    "sg:postcode":"J7R 7A6",
    "sg:province":"QC",
    "wof:name":"Perfection Lettrage",
    "wof:placetype":"venue"
},
  "geometry": {"coordinates":[-73.923828125,45.5814361572],"type":"Point"}
}