{
  "type": "Feature",
  "properties": {
    "addr:full":"230 Rue Varin Saint-Pascal QC G0L 3Y0",
    "addr:housenumber":"230",
    "addr:postcode":"g0l 3y0",
    "addr:street":"Rue Varin",
    "iso:country":"CA",
    "sg:address":"230 Rue Varin",
    "sg:city":"Saint-Pascal",
    "sg:classifiers":[
        {
            "category":"Manufacturing",
            "subcategory":"Rubber & Plastics",
            "type":"Manufacturing & Wholesale Goods"
        }
    ],
    "sg:phone":"+1 418 492 2033",
    "sg:postcode":"G0L 3Y0",
    "sg:province":"QC",
    "sg:tags":[
        "container"
    ],
    "wof:name":"Services Sanitaires Roy Inc",
    "wof:placetype":"venue"
},
  "geometry": {"coordinates":[-69.817711,47.529823],"type":"Point"}
}