{
  "type": "Feature",
  "properties": {
    "addr:full":"647 Petrolia Rd North York ON M3J 2X8",
    "addr:housenumber":"647",
    "addr:postcode":"m3j 2x8",
    "addr:street":"Petrolia Rd",
    "iso:country":"CA",
    "sg:address":"647 Petrolia Rd",
    "sg:city":"North York",
    "sg:classifiers":[
        {
            "category":"Retail",
            "subcategory":"Auto Repair",
            "type":"Services"
        }
    ],
    "sg:phone":"+1 416 665 7996",
    "sg:postcode":"M3J 2X8",
    "sg:province":"ON",
    "sg:tags":[
        "repairing",
        "automobile"
    ],
    "wof:name":"Petrolia Auto Svc & Sales",
    "wof:placetype":"venue"
},
  "geometry": {"coordinates":[-79.48857099999999,43.775654],"type":"Point"}
}