{
  "type": "Feature",
  "properties": {
    "addr:full":"184 Munro St Toronto ON M4M 2B9",
    "addr:housenumber":"184",
    "addr:postcode":"m4m 2b9",
    "addr:street":"Munro St",
    "iso:country":"CA",
    "sg:address":"184 Munro St",
    "sg:city":"Toronto",
    "sg:classifiers":[
        {
            "category":"Professional",
            "subcategory":"Advertising",
            "type":"Services"
        }
    ],
    "sg:phone":"+1 416 406 3694",
    "sg:postcode":"M4M 2B9",
    "sg:province":"ON",
    "sg:tags":[
        "counselor"
    ],
    "wof:name":"Power Communications",
    "wof:placetype":"venue"
},
  "geometry": {"coordinates":[-79.3537597656,43.6632766724],"type":"Point"}
}