{
  "type": "Feature",
  "properties": {
    "addr:full":"Etobicoke ON M9C 5K5",
    "addr:postcode":"m9c 5k5",
    "iso:country":"CA",
    "sg:city":"Etobicoke",
    "sg:classifiers":[
        {
            "category":"Food & Beverages",
            "subcategory":"Bakery",
            "type":"Retail Goods"
        }
    ],
    "sg:phone":"+1 416 620 6524",
    "sg:postcode":"M9C 5K5",
    "sg:province":"ON",
    "sg:tags":[
        "doughnut"
    ],
    "wof:name":"Country Style Donuts",
    "wof:placetype":"venue"
},
  "geometry": {"coordinates":[-79.599739,43.654282],"type":"Point"}
}