{
  "type": "Feature",
  "properties": {
    "addr:full":"1485 Caldwell Ave Ottawa ON K1Z 8M1",
    "addr:housenumber":"1485",
    "addr:postcode":"k1z 8m1",
    "addr:street":"Caldwell Ave",
    "iso:country":"CA",
    "sg:address":"1485 Caldwell Ave",
    "sg:city":"Ottawa",
    "sg:classifiers":[
        {
            "category":"Real Estate",
            "subcategory":"Real Estate Agent",
            "type":"Services"
        }
    ],
    "sg:phone":"+1 613 729 5755",
    "sg:postcode":"K1Z 8M1",
    "sg:province":"ON",
    "wof:name":"Venus Realty Ltd",
    "wof:placetype":"venue"
},
  "geometry": {"coordinates":[-75.736786,45.372448],"type":"Point"}
}