{
  "type": "Feature",
  "properties": {
    "addr:full":"113 Av Saint-Patrick Saint-Joseph-DE-Coleraine QC G0N 1B0",
    "addr:postcode":"g0n 1b0",
    "addr:street":"113 Av Saint-Patrick",
    "iso:country":"CA",
    "sg:address":"113 Av Saint-Patrick",
    "sg:city":"Saint-Joseph-DE-Coleraine",
    "sg:classifiers":[
        {
            "category":"Travel",
            "subcategory":"Campground",
            "type":"Entertainment"
        }
    ],
    "sg:phone":"+1 418 423 5548",
    "sg:postcode":"G0N 1B0",
    "sg:province":"QC",
    "wof:name":"Camping Coleraine",
    "wof:placetype":"venue"
},
  "geometry": {"coordinates":[-71.364479,45.957878],"type":"Point"}
}