{
  "type": "Feature",
  "properties": {
    "addr:full":"Buckingham QC J8L 2W8",
    "addr:postcode":"j8l 2w8",
    "iso:country":"CA",
    "sg:city":"Buckingham",
    "sg:classifiers":[
        {
            "category":"Real Estate",
            "subcategory":"Real Estate Agent",
            "type":"Services"
        }
    ],
    "sg:phone":"+1 819 281 4644",
    "sg:postcode":"J8L 2W8",
    "sg:province":"QC",
    "wof:name":"Services Immobiliers Express",
    "wof:placetype":"venue"
},
  "geometry": {"coordinates":[-75.40709699999999,45.594112],"type":"Point"}
}