{
  "type": "Feature",
  "properties": {
    "addr:full":"Gascons QC G0C 1P0",
    "addr:postcode":"g0c 1p0",
    "addr:street":"Gascons",
    "iso:country":"CA",
    "sg:city":"Gascons",
    "sg:classifiers":[
        {
            "category":"Organizations",
            "subcategory":"Religious Organization",
            "type":"Services"
        }
    ],
    "sg:phone":"+1 418 396 2717",
    "sg:postcode":"G0C 1P0",
    "sg:province":"QC",
    "sg:tags":[
        "church"
    ],
    "wof:name":"Gascons",
    "wof:placetype":"venue"
},
  "geometry": {"coordinates":[-64.861000061,48.1939048767],"type":"Point"}
}