{
  "type": "Feature",
  "properties": {
    "addr:full":"Montreal QC H2W 1Y9",
    "addr:postcode":"h2w 1y9",
    "iso:country":"CA",
    "sg:city":"Montreal",
    "sg:classifiers":[
        {
            "category":"Manufacturing",
            "subcategory":"Printing",
            "type":"Manufacturing & Wholesale Goods"
        }
    ],
    "sg:phone":"+1 514 842 9805",
    "sg:postcode":"H2W 1Y9",
    "sg:province":"QC",
    "sg:tags":[
        "publisher"
    ],
    "wof:name":"Parachute-Revue D'Art Contemp",
    "wof:placetype":"venue"
},
  "geometry": {"coordinates":[-73.58005523680001,45.5171432495],"type":"Point"}
}