{
  "type": "Feature",
  "properties": {
    "addr:full":"46 Av William-Dobell Baie-Comeau QC G4Z 1T7",
    "addr:postcode":"g4z 1t7",
    "addr:street":"46 Av William-Dobell",
    "iso:country":"CA",
    "sg:address":"46 Av William-Dobell",
    "sg:city":"Baie-Comeau",
    "sg:classifiers":[
        {
            "category":"Manufacturing",
            "subcategory":"Metals",
            "type":"Manufacturing & Wholesale Goods"
        }
    ],
    "sg:phone":"+1 418 296 5842",
    "sg:postcode":"G4Z 1T7",
    "sg:province":"QC",
    "sg:tags":[
        "scrap",
        "iron"
    ],
    "wof:name":"Baie-Comeau Metal Enr",
    "wof:placetype":"venue"
},
  "geometry": {"coordinates":[-68.18032073969999,49.2169456482],"type":"Point"}
}