{
  "type": "Feature",
  "properties": {
    "addr:full":"Etobicoke ON M9W 6K1",
    "addr:postcode":"m9w 6k1",
    "iso:country":"CA",
    "sg:city":"Etobicoke",
    "sg:classifiers":[
        {
            "category":"Shopping",
            "type":"Retail Goods"
        }
    ],
    "sg:phone":"+1 416 244 8255",
    "sg:postcode":"M9W 6K1",
    "sg:province":"ON",
    "sg:tags":[
        "telephone",
        "cellular"
    ],
    "wof:name":"Telecom Store",
    "wof:placetype":"venue"
},
  "geometry": {"coordinates":[-79.57107499999999,43.69133],"type":"Point"}
}