{
  "type": "Feature",
  "properties": {
    "addr:full":"270 Myles Bay Shore Rd Lions Head ON N0H 1W0",
    "addr:housenumber":"270",
    "addr:postcode":"n0h 1w0",
    "addr:street":"Myles Bay Shore Rd",
    "iso:country":"CA",
    "sg:address":"270 Myles Bay Shore Rd",
    "sg:city":"Lions Head",
    "sg:classifiers":[
        {
            "category":"Travel",
            "subcategory":"Hotels & Motels",
            "type":"Entertainment"
        }
    ],
    "sg:phone":"+1 519 793 3219",
    "sg:postcode":"N0H 1W0",
    "sg:province":"ON",
    "sg:tags":[
        "cottage",
        "cabin"
    ],
    "wof:name":"Whispering Cedars",
    "wof:placetype":"venue"
},
  "geometry": {"coordinates":[-81.25420379640001,44.986579895],"type":"Point"}
}