{
  "type": "Feature",
  "properties": {
    "addr:full":"Mississauga ON L5B 2C9",
    "addr:postcode":"l5b 2c9",
    "iso:country":"CA",
    "sg:city":"Mississauga",
    "sg:classifiers":[
        {
            "category":"Shopping",
            "subcategory":"Gifts & Souvenirs",
            "type":"Retail Goods"
        }
    ],
    "sg:phone":"+1 905 848 0453",
    "sg:postcode":"L5B 2C9",
    "sg:province":"ON",
    "sg:tags":[
        "shop"
    ],
    "wof:name":"Spencer Gifts",
    "wof:placetype":"venue"
},
  "geometry": {"coordinates":[-79.6395111084,43.5920944214],"type":"Point"}
}