{
  "type": "Feature",
  "properties": {
    "iso:country":"CA",
    "sg:address":"100 Montee Major",
    "sg:city":"Laval",
    "sg:classifiers":[
        {
            "category":"Arena",
            "subcategory":"Sports Club",
            "type":"Entertainment"
        }
    ],
    "sg:phone":"+1 450 662 4958",
    "sg:postcode":"H7N 4S4",
    "sg:province":"QC",
    "sg:tags":[
        "athletic",
        "provincial",
        "stadium",
        "parks",
        "fields"
    ],
    "wof:name":"Cartier Arenas Municipales",
    "wof:placetype":"venue"
},
  "geometry": {"coordinates":[-73.68376159669999,45.5591964722],"type":"Point"}
}