{
  "type": "Feature",
  "properties": {
    "addr:full":"995 Main St Moncton NB E1C 1G9",
    "addr:housenumber":"995",
    "addr:postcode":"e1c 1g9",
    "addr:street":"Main St",
    "iso:country":"CA",
    "sg:address":"995 Main St",
    "sg:city":"Moncton",
    "sg:classifiers":[
        {
            "category":"Professional",
            "subcategory":"Computer Services",
            "type":"Services"
        }
    ],
    "sg:phone":"+1 506 388 3338",
    "sg:postcode":"E1C 1G9",
    "sg:province":"NB",
    "sg:tags":[
        "consultant"
    ],
    "wof:name":"Syntact Consulting",
    "wof:placetype":"venue"
},
  "geometry": {"coordinates":[-64.783241,46.08707],"type":"Point"}
}