{
  "type": "Feature",
  "properties": {
    "addr:full":"44 Rue Labrosse Moose Creek ON K0C 1W0",
    "addr:housenumber":"44",
    "addr:postcode":"k0c 1w0",
    "addr:street":"Rue Labrosse Moose Creek",
    "iso:country":"CA",
    "sg:address":"44 Rue Labrosse",
    "sg:city":"Moose Creek",
    "sg:classifiers":[
        {
            "category":"Professional",
            "subcategory":"Business Services",
            "type":"Services"
        }
    ],
    "sg:phone":"+1 613 538 2221",
    "sg:postcode":"K0C 1W0",
    "sg:province":"ON",
    "sg:tags":[
        "license",
        "government"
    ],
    "wof:name":"Ontario Licences & Permits",
    "wof:placetype":"venue"
},
  "geometry": {"coordinates":[-74.971428,45.260979],"type":"Point"}
}