{
  "type": "Feature",
  "properties": {
    "addr:full":"Spruce Grove AB T7X 4B9",
    "addr:postcode":"t7x 4b9",
    "iso:country":"CA",
    "sg:city":"Spruce Grove",
    "sg:classifiers":[
        {
            "category":"Wholesale",
            "subcategory":"Chemicals & Plastics",
            "type":"Manufacturing & Wholesale Goods"
        }
    ],
    "sg:phone":"+1 780 960 9290",
    "sg:postcode":"T7X 4B9",
    "sg:province":"AB",
    "sg:tags":[
        "product"
    ],
    "wof:name":"Alberta Industrial Ltd",
    "wof:placetype":"venue"
},
  "geometry": {"coordinates":[-113.91709136999999,53.5374526978],"type":"Point"}
}