{
  "type": "Feature",
  "properties": {
    "addr:full":"295 Rue St-Jovite Saint-Jerome QC J7Z 7B2",
    "addr:housenumber":"295",
    "addr:postcode":"j7z 7b2",
    "addr:street":"Rue St-Jovite Saint-Jerome",
    "iso:country":"CA",
    "sg:address":"295 Rue St-Jovite",
    "sg:city":"Saint-Jerome",
    "sg:classifiers":[
        {
            "category":"Personal",
            "subcategory":"Beauty Salon",
            "type":"Services"
        }
    ],
    "sg:phone":"+1 450 565 2643",
    "sg:postcode":"J7Z 7B2",
    "sg:province":"QC",
    "wof:name":"Coiffure Mobile Gm",
    "wof:placetype":"venue"
},
  "geometry": {"coordinates":[-73.99748200000001,45.766808],"type":"Point"}
}