{
  "type": "Feature",
  "properties": {
    "addr:full":"205 Ch Fordyce Brigham QC J2K 4W9",
    "addr:housenumber":"205",
    "addr:postcode":"j2k 4w9",
    "addr:street":"Ch Fordyce",
    "iso:country":"CA",
    "sg:address":"205 Ch Fordyce",
    "sg:city":"Brigham",
    "sg:classifiers":[
        {
            "category":"Retail",
            "subcategory":"Repair Shop",
            "type":"Services"
        }
    ],
    "sg:phone":"+1 450 263 3645",
    "sg:postcode":"J2K 4W9",
    "sg:province":"QC",
    "sg:tags":[
        "welding"
    ],
    "wof:name":"Fabrications Forand Enr",
    "wof:placetype":"venue"
},
  "geometry": {"coordinates":[-72.8002319336,45.2438087463],"type":"Point"}
}