{
  "type": "Feature",
  "properties": {
    "addr:full":"1102 Cumberland St Cornwall ON K6J 4K4",
    "addr:housenumber":"1102",
    "addr:postcode":"k6j 4k4",
    "addr:street":"Cumberland St",
    "iso:country":"CA",
    "sg:address":"1102 Cumberland St",
    "sg:city":"Cornwall",
    "sg:classifiers":[
        {
            "category":"Food & Beverages",
            "subcategory":"Groceries & Convenience Stores",
            "type":"Retail Goods"
        }
    ],
    "sg:phone":"+1 613 937 0600",
    "sg:postcode":"K6J 4K4",
    "sg:province":"ON",
    "wof:name":"Gilles' Quick Stop",
    "wof:placetype":"venue"
},
  "geometry": {"coordinates":[-74.74402600000001,45.027512],"type":"Point"}
}