{
  "type": "Feature",
  "properties": {
    "addr:full":"Kitimat BC V8C 1T6",
    "addr:postcode":"bc v8c 1t6",
    "iso:country":"CA",
    "sg:city":"Kitimat",
    "sg:classifiers":[
        {
            "category":"Government",
            "subcategory":"Office",
            "type":"Public Place"
        }
    ],
    "sg:phone":"+1 250 632 4884",
    "sg:postcode":"V8C 1T6",
    "sg:province":"BC",
    "wof:name":"Canada Fisheries & Oceans Dept",
    "wof:placetype":"venue"
},
  "geometry": {"coordinates":[-128.65541099999999,54.053326],"type":"Point"}
}