{
  "type": "Feature",
  "properties": {
    "addr:full":"7050 Rue Saint-Jacques Montreal QC H4B 1V8",
    "addr:housenumber":"7050",
    "addr:postcode":"h4b 1v8",
    "addr:street":"Rue Saint-Jacques",
    "iso:country":"CA",
    "sg:address":"7050 Rue Saint-Jacques",
    "sg:city":"Montreal",
    "sg:classifiers":[
        {
            "category":"Autos & Motor Vehicles",
            "subcategory":"Auto Supplies",
            "type":"Retail Goods"
        }
    ],
    "sg:phone":"+1 514 484 7329",
    "sg:postcode":"H4B 1V8",
    "sg:province":"QC",
    "sg:tags":[
        "automobile",
        "parts"
    ],
    "wof:name":"Automax Gabriel",
    "wof:placetype":"venue"
},
  "geometry": {"coordinates":[-73.63099699999999,45.456059],"type":"Point"}
}