{
  "type": "Feature",
  "properties": {
    "addr:full":"4333 Ch Du Lac-Brennan Rawdon QC J0K 1S0",
    "addr:postcode":"4333;j0k 1s0",
    "addr:street":"Ch Du Lac-Brennan",
    "iso:country":"CA",
    "sg:address":"4333 Ch Du Lac-Brennan",
    "sg:city":"Rawdon",
    "sg:classifiers":[
        {
            "category":"Health Services",
            "subcategory":"Nursing And Care Facility",
            "type":"Services"
        }
    ],
    "sg:phone":"+1 450 834 2364",
    "sg:postcode":"J0K 1S0",
    "sg:province":"QC",
    "wof:name":"Cinquiemen Saison D'Eliah",
    "wof:placetype":"venue"
},
  "geometry": {"coordinates":[-73.76056699999999,46.071899],"type":"Point"}
}