{
  "type": "Feature",
  "properties": {
    "iso:country":"CA",
    "sg:city":"Hinton",
    "sg:classifiers":[
        {
            "category":"Retail",
            "subcategory":"Auto Repair",
            "type":"Services"
        }
    ],
    "sg:phone":"+1 780 865 5590",
    "sg:postcode":"T7V 1G8",
    "sg:province":"AB",
    "sg:tags":[
        "repairing",
        "automobile"
    ],
    "wof:name":"Dunrite Auto Repairs",
    "wof:placetype":"venue"
},
  "geometry": {"coordinates":[-117.55808258099999,53.4193916321],"type":"Point"}
}