{
  "type": "Feature",
  "properties": {
    "iso:country":"CA",
    "sg:address":"4857 Boul Bourque # 8086",
    "sg:city":"Rock Forest",
    "sg:classifiers":[
        {
            "category":"Food & Beverages",
            "subcategory":"Groceries & Convenience Stores",
            "type":"Retail Goods"
        }
    ],
    "sg:phone":"+1 819 564 1808",
    "sg:postcode":"J1N 1E8",
    "sg:province":"QC",
    "sg:tags":[
        "grocer"
    ],
    "wof:name":"Provigo",
    "wof:placetype":"venue"
},
  "geometry": {"coordinates":[-71.9866027832,45.3724403381],"type":"Point"}
}