{
  "type": "Feature",
  "properties": {
    "addr:full":"56 Lakeshore Rd W Oakville ON L6K 1C7",
    "addr:housenumber":"56",
    "addr:postcode":"l6k 1c7",
    "addr:street":"Lakeshore Rd W",
    "iso:country":"CA",
    "sg:address":"56 Lakeshore Rd W",
    "sg:city":"Oakville",
    "sg:classifiers":[
        {
            "category":"Retail",
            "subcategory":"Funeral Services",
            "type":"Services"
        }
    ],
    "sg:phone":"+1 905 842 2252",
    "sg:postcode":"L6K 1C7",
    "sg:province":"ON",
    "sg:tags":[
        "director"
    ],
    "wof:name":"Oakview Funeral Home",
    "wof:placetype":"venue"
},
  "geometry": {"coordinates":[-79.67345400000001,43.440662],"type":"Point"}
}