{
  "type": "Feature",
  "properties": {
    "addr:full":"7 Norman Rd Grand Manan NB E5G 4M1",
    "addr:housenumber":"7",
    "addr:postcode":"e5g 4m1",
    "addr:street":"Norman Rd",
    "iso:country":"CA",
    "sg:address":"7 Norman Rd",
    "sg:city":"Grand Manan",
    "sg:classifiers":[
        {
            "category":"Manufacturing",
            "subcategory":"Food",
            "type":"Manufacturing & Wholesale Goods"
        }
    ],
    "sg:phone":"+1 506 662 3696",
    "sg:postcode":"E5G 4M1",
    "sg:province":"NB",
    "sg:tags":[
        "product",
        "seafood",
        "fish",
        "prepared"
    ],
    "wof:name":"M G Fisheries Ltd",
    "wof:placetype":"venue"
},
  "geometry": {"coordinates":[-66.79814910890001,44.675453186],"type":"Point"}
}