{
  "type": "Feature",
  "properties": {
    "addr:full":"121 17 Hwy E North Bay ON P1B 8G4",
    "addr:housenumber":"121",
    "addr:postcode":"p1b 8g4",
    "addr:street":"17 Hwy E",
    "iso:country":"CA",
    "sg:address":"121 17 Hwy E",
    "sg:city":"North Bay",
    "sg:classifiers":[
        {
            "category":"Building & Trades",
            "subcategory":"Equipment Rental",
            "type":"Services"
        }
    ],
    "sg:phone":"+1 705 472 4570",
    "sg:postcode":"P1B 8G4",
    "sg:province":"ON",
    "sg:tags":[
        "crane"
    ],
    "wof:name":"Gallardi Crane Rentals",
    "wof:placetype":"venue"
},
  "geometry": {"coordinates":[-79.426552,46.304771],"type":"Point"}
}