{
  "type": "Feature",
  "properties": {
    "addr:full":"13014 50 St NW Edmonton AB T5A 4V9",
    "addr:housenumber":"13014",
    "addr:postcode":"t5a 4v9",
    "addr:street":"50 St Nw",
    "iso:country":"CA",
    "sg:address":"13014 50 St NW",
    "sg:city":"Edmonton",
    "sg:classifiers":[
        {
            "category":"Banks & Credit Unions",
            "subcategory":"Bank",
            "type":"Services"
        }
    ],
    "sg:phone":"+1 780 478 9071",
    "sg:postcode":"T5A 4V9",
    "sg:province":"AB",
    "sg:tags":[
        "cashing",
        "check"
    ],
    "wof:name":"Money Mart",
    "wof:placetype":"venue"
},
  "geometry": {"coordinates":[-113.418083,53.590233],"type":"Point"}
}