{
  "type": "Feature",
  "properties": {
    "iso:country":"CA",
    "sg:address":"54 Tuscarora Rd",
    "sg:city":"Hagersville",
    "sg:classifiers":[
        {
            "category":"Professional",
            "subcategory":"Business Services",
            "type":"Services"
        }
    ],
    "sg:phone":"+1 905 768 0868",
    "sg:postcode":"N0A 1H0",
    "sg:province":"ON",
    "sg:tags":[
        "pool",
        "swimming"
    ],
    "wof:name":"Nixon Watertrux",
    "wof:placetype":"venue"
},
  "geometry": {"coordinates":[-80.0502319336,42.9682502747],"type":"Point"}
}