{
  "type": "Feature",
  "properties": {
    "addr:full":"Christina Lake BC V0H 1E3",
    "addr:postcode":"bc v0h 1e3",
    "iso:country":"CA",
    "sg:city":"Christina Lake",
    "sg:classifiers":[
        {
            "category":"Real Estate",
            "subcategory":"Real Estate Operator",
            "type":"Services"
        }
    ],
    "sg:phone":"+1 250 447 9443",
    "sg:postcode":"V0H 1E3",
    "sg:province":"BC",
    "sg:tags":[
        "mobile",
        "home",
        "community"
    ],
    "wof:name":"Cedar Cove Mobile Home Park",
    "wof:placetype":"venue"
},
  "geometry": {"coordinates":[-118.21022000000001,49.055145],"type":"Point"}
}