{
  "type": "Feature",
  "properties": {
    "addr:full":"Cranbrook BC V1C 3S8",
    "addr:postcode":"v1c 3s8",
    "iso:country":"CA",
    "sg:city":"Cranbrook",
    "sg:classifiers":[
        {
            "category":"Shopping",
            "subcategory":"Clothing, Apparel, & Fashions",
            "type":"Retail Goods"
        }
    ],
    "sg:phone":"+1 250 489 4614",
    "sg:postcode":"V1C 3S8",
    "sg:province":"BC",
    "sg:tags":[
        "jean"
    ],
    "wof:name":"Bootlegger",
    "wof:placetype":"venue"
},
  "geometry": {"coordinates":[-115.753356934,49.5244674683],"type":"Point"}
}