{
  "type": "Feature",
  "properties": {
    "iso:country":"CA",
    "sg:address":"60 Rue Adelaide",
    "sg:city":"Sorel-Tracy",
    "sg:classifiers":[
        {
            "category":"Retail",
            "subcategory":"Auto Repair",
            "type":"Services"
        }
    ],
    "sg:phone":"+1 450 742 6450",
    "sg:postcode":"J3P 1W5",
    "sg:province":"QC",
    "sg:tags":[
        "repairing",
        "automobile"
    ],
    "wof:name":"Essieux Pro",
    "wof:placetype":"venue"
},
  "geometry": {"coordinates":[-73.11209869379999,46.0394363403],"type":"Point"}
}