{
  "type": "Feature",
  "properties": {
    "addr:full":"9624 45 Ave NW Edmonton AB T6E 5Y9",
    "addr:housenumber":"9624",
    "addr:postcode":"t6e 5y9",
    "addr:street":"45 Ave Nw",
    "iso:country":"CA",
    "sg:address":"9624 45 Ave NW",
    "sg:city":"Edmonton",
    "sg:classifiers":[
        {
            "category":"Manufacturing",
            "subcategory":"Metals",
            "type":"Manufacturing & Wholesale Goods"
        }
    ],
    "sg:phone":"+1 780 436 9271",
    "sg:postcode":"T6E 5Y9",
    "sg:province":"AB",
    "sg:tags":[
        "joint",
        "expansion"
    ],
    "wof:name":"Hydro-Flex Hose Western Ltd",
    "wof:placetype":"venue"
},
  "geometry": {"coordinates":[-113.47773742699999,53.4833106995],"type":"Point"}
}