{
  "type": "Feature",
  "properties": {
    "addr:full":"Fort St John BC V1J 3W9",
    "addr:postcode":"v1j 3w9",
    "iso:country":"CA",
    "sg:city":"Fort St John",
    "sg:classifiers":[
        {
            "category":"Utilities",
            "subcategory":"Mobile Phone",
            "type":"Services"
        }
    ],
    "sg:phone":"+1 250 785 0310",
    "sg:postcode":"V1J 3W9",
    "sg:province":"BC",
    "sg:tags":[
        "communications",
        "telephone",
        "cellular",
        "consultant"
    ],
    "wof:name":"T & T Communications",
    "wof:placetype":"venue"
},
  "geometry": {"coordinates":[-120.847694,56.234486],"type":"Point"}
}