{
  "type": "Feature",
  "properties": {
    "iso:country":"CA",
    "sg:address":"PO Box 5",
    "sg:city":"Milner",
    "sg:classifiers":[
        {
            "category":"Wholesale",
            "subcategory":"Non-durable Goods",
            "type":"Manufacturing & Wholesale Goods"
        }
    ],
    "sg:phone":"+1 604 533 3242",
    "sg:postcode":"V0X 1T0",
    "sg:province":"BC",
    "wof:name":"Remember When",
    "wof:placetype":"venue"
},
  "geometry": {"coordinates":[-122.614822,49.133316],"type":"Point"}
}