{
  "type": "Feature",
  "properties": {
    "addr:full":"PO Box 5 Milner BC V0X 1T0",
    "addr:housenumber":"po;5",
    "addr:postcode":"v0x 1t0",
    "addr:street":"Box",
    "iso:country":"CA",
    "sg:address":"PO Box 5",
    "sg:city":"Milner",
    "sg:classifiers":[
        {
            "category":"Wholesale",
            "subcategory":"Non-durable Goods",
            "type":"Manufacturing & Wholesale Goods"
        }
    ],
    "sg:phone":"+1 604 533 3242",
    "sg:postcode":"V0X 1T0",
    "sg:province":"BC",
    "wof:name":"Remember When",
    "wof:placetype":"venue"
},
  "geometry": {"coordinates":[-122.614822,49.133316],"type":"Point"}
}