{
  "type": "Feature",
  "properties": {
    "addr:full":"47 Rue Demers O Princeville QC G6L 4G1",
    "addr:housenumber":"47",
    "addr:postcode":"g6l 4g1",
    "addr:street":"Rue Demers O",
    "iso:country":"CA",
    "sg:address":"47 Rue Demers O",
    "sg:city":"Princeville",
    "sg:classifiers":[
        {
            "category":"Manufacturing",
            "subcategory":"Metals",
            "type":"Manufacturing & Wholesale Goods"
        }
    ],
    "sg:phone":"+1 819 364 5269",
    "sg:postcode":"G6L 4G1",
    "sg:province":"QC",
    "sg:tags":[
        "scrap",
        "container"
    ],
    "wof:name":"Blondeau Metal Inc",
    "wof:placetype":"venue"
},
  "geometry": {"coordinates":[-71.87956200000001,46.176285],"type":"Point"}
}