{
  "type": "Feature",
  "properties": {
    "addr:full":"463 Silverthorn Ave York ON M6M 3H6",
    "addr:housenumber":"463",
    "addr:postcode":"m6m 3h6",
    "addr:street":"Silverthorn Ave",
    "iso:country":"CA",
    "sg:address":"463 Silverthorn Ave",
    "sg:city":"York",
    "sg:classifiers":[
        {
            "category":"Building & Trades",
            "subcategory":"Electrical",
            "type":"Services"
        }
    ],
    "sg:phone":"+1 416 651 8555",
    "sg:postcode":"M6M 3H6",
    "sg:province":"ON",
    "sg:tags":[
        "lighting",
        "landscape"
    ],
    "wof:name":"J C Lightning",
    "wof:placetype":"venue"
},
  "geometry": {"coordinates":[-79.466468811,43.6867752075],"type":"Point"}
}