{
  "type": "Feature",
  "properties": {
    "addr:full":"7171 Boul Thimens Saint-Laurent QC H4S 2A2",
    "addr:housenumber":"7171",
    "addr:postcode":"h4s 2a2",
    "addr:street":"Boul Thimens",
    "iso:country":"CA",
    "sg:address":"7171 Boul Thimens",
    "sg:city":"Saint-Laurent",
    "sg:classifiers":[
        {
            "category":"Wholesale",
            "subcategory":"Groceries",
            "type":"Manufacturing & Wholesale Goods"
        }
    ],
    "sg:phone":"+1 514 856 1000",
    "sg:postcode":"H4S 2A2",
    "sg:province":"QC",
    "sg:tags":[
        "grocer"
    ],
    "wof:name":"Major Canada Inc",
    "wof:placetype":"venue"
},
  "geometry": {"coordinates":[-73.7432098389,45.5069694519],"type":"Point"}
}