{
  "type": "Feature",
  "properties": {
    "addr:full":"1800 Main St Saskatoon SK S7H 4B3",
    "addr:housenumber":"1800",
    "addr:postcode":"s7h 4b3",
    "addr:street":"Main St",
    "iso:country":"CA",
    "sg:address":"1800 Main St",
    "sg:city":"Saskatoon",
    "sg:classifiers":[
        {
            "category":"Real Estate",
            "subcategory":"Real Estate Operator",
            "type":"Services"
        }
    ],
    "sg:phone":"+1 306 374 2939",
    "sg:postcode":"S7H 4B3",
    "sg:province":"SK",
    "sg:tags":[
        "apartment"
    ],
    "wof:name":"Mah Holdings Ltd",
    "wof:placetype":"venue"
},
  "geometry": {"coordinates":[-106.62854799999999,52.116623],"type":"Point"}
}