{
  "type": "Feature",
  "properties": {
    "iso:country":"CA",
    "sg:address":"5050 Edwards Blvd",
    "sg:city":"Mississauga",
    "sg:classifiers":[
        {
            "category":"Manufacturing",
            "subcategory":"Leather Goods",
            "type":"Manufacturing & Wholesale Goods"
        }
    ],
    "sg:phone":"+1 905 696 0016",
    "sg:postcode":"L5T 2W3",
    "sg:province":"ON",
    "sg:tags":[
        "case"
    ],
    "wof:name":"National Case CO",
    "wof:placetype":"venue"
},
  "geometry": {"coordinates":[-79.6752166748,43.6408195496],"type":"Point"}
}