{
  "type": "Feature",
  "properties": {
    "addr:full":"4 Ontario St Hwy 11 Sundridge ON P0A 1Z0",
    "addr:housenumber":"4",
    "addr:postcode":"p0a 1z0",
    "addr:street":"Ontario St Hwy 11",
    "iso:country":"CA",
    "sg:address":"4 Ontario St Hwy 11",
    "sg:city":"Sundridge",
    "sg:classifiers":[
        {
            "category":"Government",
            "subcategory":"Office",
            "type":"Public Place"
        }
    ],
    "sg:phone":"+1 705 384 7022",
    "sg:postcode":"P0A 1Z0",
    "sg:province":"ON",
    "wof:name":"Sundridge Drivers & Vehicles",
    "wof:placetype":"venue"
},
  "geometry": {"coordinates":[-79.40013885499999,45.7662963867],"type":"Point"}
}