{
  "type": "Feature",
  "properties": {
    "addr:full":"137 Martin Dr Maidstone ON N0R 1K0",
    "addr:housenumber":"137",
    "addr:postcode":"n0r 1k0",
    "addr:street":"Martin Dr",
    "iso:country":"CA",
    "sg:address":"137 Martin Dr",
    "sg:city":"Maidstone",
    "sg:classifiers":[
        {
            "category":"Building & Trades",
            "subcategory":"Construction",
            "type":"Services"
        }
    ],
    "sg:phone":"+1 519 979 9104",
    "sg:postcode":"N0R 1K0",
    "sg:province":"ON",
    "sg:tags":[
        "contractor"
    ],
    "wof:name":"Sprint Construction",
    "wof:placetype":"venue"
},
  "geometry": {"coordinates":[-82.890511,42.210068],"type":"Point"}
}