{
  "type": "Feature",
  "properties": {
    "addr:full":"184 Boul Iberville Repentigny QC J6A 1Y9",
    "addr:housenumber":"184",
    "addr:postcode":"j6a 1y9",
    "addr:street":"Boul Iberville",
    "iso:country":"CA",
    "sg:address":"184 Boul Iberville",
    "sg:city":"Repentigny",
    "sg:classifiers":[
        {
            "category":"Professional",
            "subcategory":"Business Services",
            "type":"Services"
        }
    ],
    "sg:phone":"+1 450 581 0549",
    "sg:postcode":"J6A 1Y9",
    "sg:province":"QC",
    "sg:tags":[
        "arbitration"
    ],
    "wof:name":"Lortie, Louise",
    "wof:placetype":"venue"
},
  "geometry": {"coordinates":[-73.469933,45.720783],"type":"Point"}
}