{
  "type": "Feature",
  "properties": {
    "addr:full":"601 2nd Ave Esterhazy SK S0A 0X0",
    "addr:housenumber":"601",
    "addr:postcode":"s0a 0x0",
    "addr:street":"2Nd Ave",
    "iso:country":"CA",
    "sg:address":"601 2nd Ave",
    "sg:city":"Esterhazy",
    "sg:classifiers":[
        {
            "category":"Sports & Exercise",
            "subcategory":"Bowling",
            "type":"Entertainment"
        }
    ],
    "sg:phone":"+1 306 745 2847",
    "sg:postcode":"S0A 0X0",
    "sg:province":"SK",
    "sg:tags":[
        "center"
    ],
    "wof:name":"Esterhazy Bowl Arena Ltd",
    "wof:placetype":"venue"
},
  "geometry": {"coordinates":[-102.087753296,50.6567115784],"type":"Point"}
}