{
  "type": "Feature",
  "properties": {
    "iso:country":"CA",
    "sg:address":"601 2nd Ave",
    "sg:city":"Esterhazy",
    "sg:classifiers":[
        {
            "category":"Sports & Exercise",
            "subcategory":"Bowling",
            "type":"Entertainment"
        }
    ],
    "sg:phone":"+1 306 745 2847",
    "sg:postcode":"S0A 0X0",
    "sg:province":"SK",
    "sg:tags":[
        "center"
    ],
    "wof:name":"Esterhazy Bowl Arena Ltd",
    "wof:placetype":"venue"
},
  "geometry": {"coordinates":[-102.087753296,50.6567115784],"type":"Point"}
}