{
  "type": "Feature",
  "properties": {
    "addr:full":"Montreal-Est QC H1B 5W1",
    "addr:postcode":"h1b 5w1",
    "iso:country":"CA",
    "sg:city":"Montreal-Est",
    "sg:classifiers":[
        {
            "category":"Retail",
            "subcategory":"Repair Shop",
            "type":"Services"
        }
    ],
    "sg:phone":"+1 514 640 1762",
    "sg:postcode":"H1B 5W1",
    "sg:province":"QC",
    "sg:tags":[
        "tank",
        "cleaning"
    ],
    "wof:name":"Envirotech Inc",
    "wof:placetype":"venue"
},
  "geometry": {"coordinates":[-73.516769,45.631119],"type":"Point"}
}