{
  "type": "Feature",
  "properties": {
    "addr:full":"Molloys Ln Trepassey NL A0A 4B0",
    "addr:postcode":"a0a 4b0",
    "addr:street":"Molloys Ln",
    "iso:country":"CA",
    "sg:address":"Molloys Ln",
    "sg:city":"Trepassey",
    "sg:classifiers":[
        {
            "category":"Restaurant",
            "type":"Food & Drink"
        }
    ],
    "sg:phone":"+1 709 438 2003",
    "sg:postcode":"A0A 4B0",
    "sg:province":"NL",
    "wof:name":"First Venture",
    "wof:placetype":"venue"
},
  "geometry": {"coordinates":[-53.364887,46.737453],"type":"Point"}
}