{
  "type": "Feature",
  "properties": {
    "addr:full":"1915 Stainsbury Ave Vancouver BC V5N 2M6",
    "addr:housenumber":"1915",
    "addr:postcode":"v5n 2m6",
    "addr:street":"Stainsbury Ave",
    "iso:country":"CA",
    "sg:address":"1915 Stainsbury Ave",
    "sg:city":"Vancouver",
    "sg:classifiers":[
        {
            "category":"Shopping",
            "subcategory":"Clothing, Apparel, & Fashions",
            "type":"Retail Goods"
        }
    ],
    "sg:phone":"+1 604 254 8330",
    "sg:postcode":"V5N 2M6",
    "sg:province":"BC",
    "sg:tags":[
        "t"
    ],
    "wof:name":"Dagoli Studio Inc",
    "wof:placetype":"venue"
},
  "geometry": {"coordinates":[-123.066162109,49.2519760132],"type":"Point"}
}