{
  "type": "Feature",
  "properties": {
    "addr:full":"1245 Rue Plamondon Saint-Cesaire QC J0L 1T0",
    "addr:housenumber":"1245",
    "addr:postcode":"j0l 1t0",
    "addr:street":"Rue Plamondon Saint-Cesaire",
    "iso:country":"CA",
    "sg:address":"1245 Rue Plamondon",
    "sg:city":"Saint-Cesaire",
    "sg:classifiers":[
        {
            "category":"Health Services",
            "subcategory":"Doctor",
            "type":"Services"
        }
    ],
    "sg:phone":"+1 450 469 5551",
    "sg:postcode":"J0L 1T0",
    "sg:province":"QC",
    "sg:tags":[
        "clinic"
    ],
    "wof:name":"Clinique Medicale St-Cesaire",
    "wof:placetype":"venue"
},
  "geometry": {"coordinates":[-73.00344800000001,45.410938],"type":"Point"}
}