{
  "type": "Feature",
  "properties": {
    "addr:full":"119 King St Woodstock NB E7M 2Y4",
    "addr:housenumber":"119",
    "addr:postcode":"e7m 2y4",
    "addr:street":"King St",
    "iso:country":"CA",
    "sg:address":"119 King St",
    "sg:city":"Woodstock",
    "sg:classifiers":[
        {
            "category":"Shopping",
            "subcategory":"Clothing, Apparel, & Fashions",
            "type":"Retail Goods"
        }
    ],
    "sg:phone":"+1 506 328 9123",
    "sg:postcode":"E7M 2Y4",
    "sg:province":"NB",
    "wof:name":"Fashion Today",
    "wof:placetype":"venue"
},
  "geometry": {"coordinates":[-67.58392333979999,46.1405258179],"type":"Point"}
}