{
  "type": "Feature",
  "properties": {
    "iso:country":"CA",
    "sg:address":"326 Montee Gagnon",
    "sg:city":"Sainte-Anne-Des-Plaines",
    "sg:classifiers":[
        {
            "category":"Autos & Motor Vehicles",
            "subcategory":"Automobile Sales",
            "type":"Retail Goods"
        }
    ],
    "sg:phone":"+1 450 478 7033",
    "sg:postcode":"J0N 1H0",
    "sg:province":"QC",
    "sg:tags":[
        "body",
        "car"
    ],
    "wof:name":"Jocelyn Gagnon Autos Inc",
    "wof:placetype":"venue"
},
  "geometry": {"coordinates":[-73.8231430054,45.7339859009],"type":"Point"}
}