{
  "type": "Feature",
  "properties": {
    "iso:country":"CA",
    "sg:city":"Mississauga",
    "sg:classifiers":[
        {
            "category":"Professional",
            "subcategory":"Employment Agencies",
            "type":"Services"
        }
    ],
    "sg:phone":"+1 905 405 6210",
    "sg:postcode":"L4V 1W1",
    "sg:province":"ON",
    "sg:tags":[
        "consultant",
        "search",
        "executive"
    ],
    "wof:name":"Yorkland Search Technologies",
    "wof:placetype":"venue"
},
  "geometry": {"coordinates":[-79.608109,43.686043],"type":"Point"}
}