{
  "type": "Feature",
  "properties": {
    "addr:full":"30 Rue Principale S Sutton QC J0E 2K0",
    "addr:housenumber":"30",
    "addr:postcode":"j0e 2k0",
    "addr:street":"Rue Principale S",
    "iso:country":"CA",
    "sg:address":"30 Rue Principale S",
    "sg:city":"Sutton",
    "sg:classifiers":[
        {
            "category":"Museum",
            "type":"Entertainment"
        }
    ],
    "sg:phone":"+1 450 538 3222",
    "sg:postcode":"J0E 2K0",
    "sg:province":"QC",
    "wof:name":"Musee Des Communications",
    "wof:placetype":"venue"
},
  "geometry": {"coordinates":[-72.615067,45.104969],"type":"Point"}
}