{
  "type": "Feature",
  "properties": {
    "addr:full":"345 Cote Joyeuse Saint-Raymond QC G3L 4A8",
    "addr:housenumber":"345",
    "addr:postcode":"g3l 4a8",
    "addr:street":"Cote Joyeuse",
    "iso:country":"CA",
    "sg:address":"345 Cote Joyeuse",
    "sg:city":"Saint-Raymond",
    "sg:classifiers":[
        {
            "category":"Autos & Motor Vehicles",
            "subcategory":"Fuel & Gas Station",
            "type":"Retail Goods"
        }
    ],
    "sg:phone":"+1 418 337 7256",
    "sg:postcode":"G3L 4A8",
    "sg:province":"QC",
    "sg:tags":[
        "oil"
    ],
    "wof:name":"Ultramar",
    "wof:placetype":"venue"
},
  "geometry": {"coordinates":[-71.8340911865,46.88256073],"type":"Point"}
}