{
  "type": "Feature",
  "properties": {
    "addr:full":"168 Annette St Toronto ON M6P 1P4",
    "addr:housenumber":"168",
    "addr:postcode":"m6p 1p4",
    "addr:street":"Annette St",
    "iso:country":"CA",
    "sg:address":"168 Annette St",
    "sg:city":"Toronto",
    "sg:classifiers":[
        {
            "category":"Health Services",
            "subcategory":"Chiropractor",
            "type":"Services"
        }
    ],
    "sg:phone":"+1 416 767 9356",
    "sg:postcode":"M6P 1P4",
    "sg:province":"ON",
    "wof:name":"Murray, Brian DC",
    "wof:placetype":"venue"
},
  "geometry": {"coordinates":[-79.4673461914,43.6634407043],"type":"Point"}
}