{
  "type": "Feature",
  "properties": {
    "addr:full":"5124 49 St Yellowknife NT X1A 1P8",
    "addr:housenumber":"5124",
    "addr:postcode":"x1a 1p8",
    "addr:street":"49 St",
    "iso:country":"CA",
    "sg:address":"5124 49 St",
    "sg:city":"Yellowknife",
    "sg:classifiers":[
        {
            "category":"Education",
            "subcategory":"School",
            "type":"Public Place"
        }
    ],
    "sg:phone":"+1 867 766 7400",
    "sg:postcode":"X1A 1P8",
    "sg:province":"NT",
    "wof:name":"Yellowknife Catholic Schools",
    "wof:placetype":"venue"
},
  "geometry": {"coordinates":[-114.365578,62.452152],"type":"Point"}
}