{
  "type": "Feature",
  "properties": {
    "addr:full":"11 Rue St-Eugene Gracefield QC J0X 1W0",
    "addr:housenumber":"11",
    "addr:postcode":"j0x 1w0",
    "addr:street":"Rue St-Eugene",
    "iso:country":"CA",
    "sg:address":"11 Rue St-Eugene",
    "sg:city":"Gracefield",
    "sg:classifiers":[
        {
            "category":"Education",
            "subcategory":"School",
            "type":"Public Place"
        }
    ],
    "sg:phone":"+1 819 463 2949",
    "sg:postcode":"J0X 1W0",
    "sg:province":"QC",
    "wof:name":"Ecole Sacre-Coeur",
    "wof:placetype":"venue"
},
  "geometry": {"coordinates":[-76.055038,46.092518],"type":"Point"}
}