{
  "type": "Feature",
  "properties": {
    "addr:full":"95 York St Fredericton NB E3B 3N4",
    "addr:housenumber":"95",
    "addr:postcode":"e3b 3n4",
    "addr:street":"York St",
    "iso:country":"CA",
    "sg:address":"95 York St",
    "sg:city":"Fredericton",
    "sg:classifiers":[
        {
            "category":"Shopping",
            "subcategory":"Jewelry",
            "type":"Retail Goods"
        }
    ],
    "sg:phone":"+1 506 455 1711",
    "sg:postcode":"E3B 3N4",
    "sg:province":"NB",
    "sg:tags":[
        "jeweler"
    ],
    "wof:name":"Paradise Imports",
    "wof:placetype":"venue"
},
  "geometry": {"coordinates":[-66.64400500000001,45.962257],"type":"Point"}
}