{
  "type": "Feature",
  "properties": {
    "addr:full":"5219 87 St NW Edmonton AB T6E 5L5",
    "addr:housenumber":"5219",
    "addr:postcode":"t6e 5l5",
    "addr:street":"87 St Nw",
    "iso:country":"CA",
    "sg:address":"5219 87 St NW",
    "sg:city":"Edmonton",
    "sg:classifiers":[
        {
            "category":"Wholesale",
            "subcategory":"Fruits & Vegetables",
            "type":"Manufacturing & Wholesale Goods"
        }
    ],
    "sg:phone":"+1 780 463 4766",
    "sg:postcode":"T6E 5L5",
    "sg:province":"AB",
    "wof:name":"Chapman's Fresh Produce",
    "wof:placetype":"venue"
},
  "geometry": {"coordinates":[-113.45706199999999,53.489841],"type":"Point"}
}