{
  "type": "Feature",
  "properties": {
    "addr:full":"774 Ney Ave Port Mcnicoll ON L0K 1R0",
    "addr:housenumber":"774",
    "addr:postcode":"l0k 1r0",
    "addr:street":"Ney Ave",
    "iso:country":"CA",
    "sg:address":"774 Ney Ave",
    "sg:city":"Port Mcnicoll",
    "sg:classifiers":[
        {
            "category":"Personal",
            "subcategory":"Beauty Salon",
            "type":"Services"
        }
    ],
    "sg:phone":"+1 705 534 4607",
    "sg:postcode":"L0K 1R0",
    "sg:province":"ON",
    "wof:name":"Kate's Korner",
    "wof:placetype":"venue"
},
  "geometry": {"coordinates":[-79.80769348139999,44.7453842163],"type":"Point"}
}