{
  "type": "Feature",
  "properties": {
    "iso:country":"CA",
    "sg:city":"Winnipeg",
    "sg:classifiers":[
        {
            "category":"Social Services",
            "type":"Services"
        }
    ],
    "sg:phone":"+1 204 477 5360",
    "sg:postcode":"R3L 2T4",
    "sg:province":"MB",
    "sg:tags":[
        "organization",
        "welfare"
    ],
    "wof:name":"United Way of Winnipeg",
    "wof:placetype":"venue"
},
  "geometry": {"coordinates":[-97.1374282837,49.8802642822],"type":"Point"}
}