{
  "type": "Feature",
  "properties": {
    "addr:full":"3171 Kingsway E Sudbury ON P3B 2G5",
    "addr:housenumber":"3171",
    "addr:postcode":"p3b 2g5",
    "addr:street":"Kingsway E",
    "iso:country":"CA",
    "sg:address":"3171 Kingsway E",
    "sg:city":"Sudbury",
    "sg:classifiers":[
        {
            "category":"Building & Trades",
            "subcategory":"Construction",
            "type":"Services"
        }
    ],
    "sg:phone":"+1 705 560 1266",
    "sg:postcode":"P3B 2G5",
    "sg:province":"ON",
    "sg:tags":[
        "general",
        "contractor"
    ],
    "wof:name":"Kona Builders Ltd",
    "wof:placetype":"venue"
},
  "geometry": {"coordinates":[-80.896339,46.494144],"type":"Point"}
}