{
  "type": "Feature",
  "properties": {
    "iso:country":"CA",
    "sg:address":"34 South Alder St",
    "sg:city":"Campbell River",
    "sg:classifiers":[
        {
            "category":"Organizations",
            "subcategory":"Religious Organization",
            "type":"Services"
        }
    ],
    "sg:phone":"+1 250 287 3498",
    "sg:postcode":"V9W 2M8",
    "sg:province":"BC",
    "sg:tags":[
        "church"
    ],
    "wof:name":"St Patrick's Roman Catholic",
    "wof:placetype":"venue"
},
  "geometry": {"coordinates":[-125.239624023,50.0068397522],"type":"Point"}
}