{
  "type": "Feature",
  "properties": {
    "iso:country":"CA",
    "sg:address":"215 Highland Rd W",
    "sg:city":"Kitchener",
    "sg:classifiers":[
        {
            "category":"Cinema",
            "subcategory":"Movie Rental",
            "type":"Entertainment"
        }
    ],
    "sg:phone":"+1 519 578 6364",
    "sg:postcode":"N2M 3C1",
    "sg:province":"ON",
    "sg:tags":[
        "leasing",
        "video",
        "disc",
        "tape"
    ],
    "wof:name":"Adult Movie Warehouse",
    "wof:placetype":"venue"
},
  "geometry": {"coordinates":[-80.5062332153,43.4402580261],"type":"Point"}
}