{
  "type": "Feature",
  "properties": {
    "addr:full":"83 Prennan Ave Etobicoke ON M9B 4C2",
    "addr:housenumber":"83",
    "addr:postcode":"m9b 4c2",
    "addr:street":"Prennan Ave",
    "iso:country":"CA",
    "sg:address":"83 Prennan Ave",
    "sg:city":"Etobicoke",
    "sg:classifiers":[
        {
            "category":"Retail",
            "subcategory":"Laundry & Dry Cleaning",
            "type":"Services"
        }
    ],
    "sg:phone":"+1 416 233 0166",
    "sg:postcode":"M9B 4C2",
    "sg:province":"ON",
    "sg:tags":[
        "cleaners",
        "rug",
        "carpet"
    ],
    "wof:name":"Royal Rug Cleaning",
    "wof:placetype":"venue"
},
  "geometry": {"coordinates":[-79.53928399999999,43.647923],"type":"Point"}
}