{
  "type": "Feature",
  "properties": {
    "addr:full":"155 Boul Pierre-Laporte Cowansville QC J2K 2G3",
    "addr:housenumber":"155",
    "addr:postcode":"j2k 2g3",
    "addr:street":"Boul Pierre-Laporte",
    "iso:country":"CA",
    "sg:address":"155 Boul Pierre-Laporte",
    "sg:city":"Cowansville",
    "sg:classifiers":[
        {
            "category":"Shopping",
            "subcategory":"Florist",
            "type":"Retail Goods"
        }
    ],
    "sg:phone":"+1 450 263 0140",
    "sg:postcode":"J2K 2G3",
    "sg:province":"QC",
    "sg:tags":[
        "garden",
        "center"
    ],
    "wof:name":"Serres Cherbourg Enr",
    "wof:placetype":"venue"
},
  "geometry": {"coordinates":[-72.7150726318,45.2100753784],"type":"Point"}
}