{
  "type": "Feature",
  "properties": {
    "addr:full":"365 Dupont St Toronto ON M5R 1W2",
    "addr:housenumber":"365",
    "addr:postcode":"m5r 1w2",
    "addr:street":"Dupont St",
    "iso:country":"CA",
    "sg:address":"365 Dupont St",
    "sg:city":"Toronto",
    "sg:classifiers":[
        {
            "category":"Retail",
            "subcategory":"Auto Repair",
            "type":"Services"
        }
    ],
    "sg:phone":"+1 416 968 7433",
    "sg:postcode":"M5R 1W2",
    "sg:province":"ON",
    "sg:tags":[
        "repairing",
        "automobile"
    ],
    "wof:name":"Weltmeister Autowerk",
    "wof:placetype":"venue"
},
  "geometry": {"coordinates":[-79.411239624,43.6736755371],"type":"Point"}
}