{
  "type": "Feature",
  "properties": {
    "addr:full":"Calgary AB T2E 3P3",
    "addr:postcode":"t2e 3p3",
    "iso:country":"CA",
    "sg:city":"Calgary",
    "sg:classifiers":[
        {
            "category":"Manufacturing",
            "subcategory":"Food",
            "type":"Manufacturing & Wholesale Goods"
        }
    ],
    "sg:phone":"+1 403 265 1383",
    "sg:postcode":"T2E 3P3",
    "sg:province":"AB",
    "sg:tags":[
        "grocer",
        "product",
        "manufacturer"
    ],
    "wof:name":"Mandarin Noodle Mfg CO Ltd",
    "wof:placetype":"venue"
},
  "geometry": {"coordinates":[-114.05217,51.085175],"type":"Point"}
}