{
  "type": "Feature",
  "properties": {
    "addr:full":"Brampton ON L6X 4H5",
    "addr:postcode":"l6x 4h5",
    "iso:country":"CA",
    "sg:city":"Brampton",
    "sg:classifiers":[
        {
            "category":"Retail",
            "subcategory":"Auto Repair",
            "type":"Services"
        }
    ],
    "sg:phone":"+1 905 455 1122",
    "sg:postcode":"L6X 4H5",
    "sg:province":"ON",
    "sg:tags":[
        "transmission"
    ],
    "wof:name":"Canadian Transmission",
    "wof:placetype":"venue"
},
  "geometry": {"coordinates":[-79.77066802980001,43.6874656677],"type":"Point"}
}