{
  "type": "Feature",
  "properties": {
    "addr:full":"1067 4th St Courtenay BC V9N 1H6",
    "addr:housenumber":"1067",
    "addr:postcode":"v9n 1h6",
    "addr:street":"4Th St",
    "iso:country":"CA",
    "sg:address":"1067 4th St",
    "sg:city":"Courtenay",
    "sg:classifiers":[
        {
            "category":"Building & Trades",
            "subcategory":"Construction",
            "type":"Services"
        }
    ],
    "sg:phone":"+1 250 338 7467",
    "sg:postcode":"V9N 1H6",
    "sg:province":"BC",
    "sg:tags":[
        "roofing",
        "contractor"
    ],
    "wof:name":"Gulf Roofing",
    "wof:placetype":"venue"
},
  "geometry": {"coordinates":[-125.010894775,49.6864433289],"type":"Point"}
}