{
  "type": "Feature",
  "properties": {
    "iso:country":"CA",
    "sg:address":"1530 Broadway W",
    "sg:city":"Vancouver",
    "sg:classifiers":[
        {
            "category":"Restaurant",
            "type":"Food & Drink"
        }
    ],
    "sg:phone":"+1 604 733 0434",
    "sg:postcode":"V6J 5K9",
    "sg:province":"BC",
    "wof:name":"Cactus Club Cafe",
    "wof:placetype":"venue"
},
  "geometry": {"coordinates":[-123.139389038,49.2635116577],"type":"Point"}
}