{
  "type": "Feature",
  "properties": {
    "addr:full":"35 Rue DE Port-Royal E Montreal QC H3L 3T1",
    "addr:housenumber":"35",
    "addr:postcode":"h3l 3t1",
    "addr:street":"Rue De Port-Royal E",
    "iso:country":"CA",
    "sg:address":"35 Rue DE Port-Royal E",
    "sg:city":"Montreal",
    "sg:classifiers":[
        {
            "category":"Shopping",
            "subcategory":"Tobacco",
            "type":"Retail Goods"
        }
    ],
    "sg:phone":"+1 514 388 0428",
    "sg:postcode":"H3L 3T1",
    "sg:province":"QC",
    "sg:tags":[
        "cigarette",
        "cigar",
        "dealer"
    ],
    "wof:name":"Tabagie Depanneur Port-Royal",
    "wof:placetype":"venue"
},
  "geometry": {"coordinates":[-73.657143,45.546677],"type":"Point"}
}