{
  "type": "Feature",
  "properties": {
    "addr:full":"733 Ch Saint-Fereol Les Cedres QC J7T 1M9",
    "addr:housenumber":"733",
    "addr:postcode":"j7t 1m9",
    "addr:street":"Ch Saint-Fereol",
    "iso:country":"CA",
    "sg:address":"733 Ch Saint-Fereol",
    "sg:city":"Les Cedres",
    "sg:classifiers":[
        {
            "category":"Retail",
            "subcategory":"Auto Repair",
            "type":"Services"
        }
    ],
    "sg:phone":"+1 450 452 2882",
    "sg:postcode":"J7T 1M9",
    "sg:province":"QC",
    "sg:tags":[
        "repairing",
        "automobile"
    ],
    "wof:name":"Atelier Mecanique Jm Enr",
    "wof:placetype":"venue"
},
  "geometry": {"coordinates":[-74.0809173584,45.3358612061],"type":"Point"}
}