{
  "type": "Feature",
  "properties": {
    "addr:full":"54 Wolseley St Toronto ON M5T 1A5",
    "addr:housenumber":"54",
    "addr:postcode":"m5t 1a5",
    "addr:street":"Wolseley St",
    "iso:country":"CA",
    "sg:address":"54 Wolseley St",
    "sg:city":"Toronto",
    "sg:classifiers":[
        {
            "category":"Wholesale",
            "subcategory":"Non-durable Goods",
            "type":"Manufacturing & Wholesale Goods"
        }
    ],
    "sg:phone":"+1 416 681 0287",
    "sg:postcode":"M5T 1A5",
    "sg:province":"ON",
    "sg:tags":[
        "interior",
        "consultant",
        "design",
        "decorator"
    ],
    "wof:name":"Interior Excessories",
    "wof:placetype":"venue"
},
  "geometry": {"coordinates":[-79.402649,43.648483],"type":"Point"}
}