{
  "type": "Feature",
  "properties": {
    "addr:full":"Surrey BC V4A 1N8",
    "addr:postcode":"v4a 1n8",
    "iso:country":"CA",
    "sg:city":"Surrey",
    "sg:classifiers":[
        {
            "category":"Restaurant",
            "type":"Food & Drink"
        }
    ],
    "sg:phone":"+1 604 536 3133",
    "sg:postcode":"V4A 1N8",
    "sg:province":"BC",
    "sg:tags":[
        "delicatessen"
    ],
    "wof:name":"Salt Cellar Delicatessen",
    "wof:placetype":"venue"
},
  "geometry": {"coordinates":[-122.86434199999999,49.031406],"type":"Point"}
}