{
  "type": "Feature",
  "properties": {
    "addr:full":"Edmonton AB T6E 5V8",
    "addr:postcode":"t6e 5v8",
    "iso:country":"CA",
    "sg:city":"Edmonton",
    "sg:classifiers":[
        {
            "category":"Professional",
            "type":"Services"
        }
    ],
    "sg:phone":"+1 780 439 5380",
    "sg:postcode":"T6E 5V8",
    "sg:province":"AB",
    "sg:tags":[
        "consultant",
        "geological"
    ],
    "wof:name":"Apex Geoscience Ltd",
    "wof:placetype":"venue"
},
  "geometry": {"coordinates":[-113.48261261,53.4829025269],"type":"Point"}
}