{
  "type": "Feature",
  "properties": {
    "addr:full":"790 Rue Principale Lac-Drolet QC G0Y 1C0",
    "addr:housenumber":"790",
    "addr:postcode":"g0y 1c0",
    "addr:street":"Rue Principale",
    "iso:country":"CA",
    "sg:address":"790 Rue Principale",
    "sg:city":"Lac-Drolet",
    "sg:classifiers":[
        {
            "category":"Shopping",
            "subcategory":"Shoes",
            "type":"Retail Goods"
        }
    ],
    "sg:phone":"+1 819 549 2008",
    "sg:postcode":"G0Y 1C0",
    "sg:province":"QC",
    "wof:name":"Comptoir Manufacturier DE Lac",
    "wof:placetype":"venue"
},
  "geometry": {"coordinates":[-70.8557434082,45.7223052979],"type":"Point"}
}