{
  "type": "Feature",
  "properties": {
    "addr:full":"11232 96 St NW Edmonton AB T5G 1S9",
    "addr:housenumber":"11232",
    "addr:postcode":"t5g 1s9",
    "addr:street":"96 St Nw",
    "iso:country":"CA",
    "sg:address":"11232 96 St NW",
    "sg:city":"Edmonton",
    "sg:classifiers":[
        {
            "category":"Professional",
            "subcategory":"Engineering",
            "type":"Services"
        }
    ],
    "sg:phone":"+1 780 438 6732",
    "sg:postcode":"T5G 1S9",
    "sg:province":"AB",
    "sg:tags":[
        "engineer"
    ],
    "wof:name":"Barrett Crane Design",
    "wof:placetype":"venue"
},
  "geometry": {"coordinates":[-113.490364,53.561642],"type":"Point"}
}