{
  "type": "Feature",
  "properties": {
    "addr:full":"6178 Netherhart Rd Mississauga ON L5T 1B7",
    "addr:housenumber":"6178",
    "addr:postcode":"l5t 1b7",
    "addr:street":"Netherhart Rd",
    "iso:country":"CA",
    "sg:address":"6178 Netherhart Rd",
    "sg:city":"Mississauga",
    "sg:classifiers":[
        {
            "category":"Home & Garden",
            "subcategory":"Building Materials",
            "type":"Retail Goods"
        }
    ],
    "sg:phone":"+1 905 564 6100",
    "sg:postcode":"L5T 1B7",
    "sg:province":"ON",
    "sg:tags":[
        "roofing"
    ],
    "wof:name":"Permaquik Corp",
    "wof:placetype":"venue"
},
  "geometry": {"coordinates":[-79.64370700000001,43.665398],"type":"Point"}
}