{
  "type": "Feature",
  "properties": {
    "addr:full":"8901 101 Ave NW Edmonton AB T5H 0B1",
    "addr:housenumber":"8901",
    "addr:postcode":"t5h 0b1",
    "addr:street":"101 Ave Nw",
    "iso:country":"CA",
    "sg:address":"8901 101 Ave NW",
    "sg:city":"Edmonton",
    "sg:classifiers":[
        {
            "category":"Education",
            "subcategory":"School",
            "type":"Public Place"
        }
    ],
    "sg:phone":"+1 780 425 7600",
    "sg:postcode":"T5H 0B1",
    "sg:province":"AB",
    "wof:name":"Riverdale Elementary School",
    "wof:placetype":"venue"
},
  "geometry": {"coordinates":[-113.468605041,53.5435447693],"type":"Point"}
}