{
  "type": "Feature",
  "properties": {
    "addr:full":"Vancouver BC V6J 1R3",
    "addr:postcode":"v6j 1r3",
    "iso:country":"CA",
    "sg:city":"Vancouver",
    "sg:classifiers":[
        {
            "category":"Professional",
            "subcategory":"Management & Consulting",
            "type":"Services"
        }
    ],
    "sg:phone":"+1 604 844 7827",
    "sg:postcode":"V6J 1R3",
    "sg:province":"BC",
    "sg:tags":[
        "communications",
        "consultant"
    ],
    "wof:name":"West Star Communications",
    "wof:placetype":"venue"
},
  "geometry": {"coordinates":[-123.14115099999999,49.266102],"type":"Point"}
}