{
  "type": "Feature",
  "properties": {
    "addr:full":"1429 80E Rue E Charlesbourg QC G2L 1M4",
    "addr:housenumber":"1429",
    "addr:postcode":"g2l 1m4",
    "addr:street":"80E Rue E",
    "iso:country":"CA",
    "sg:address":"1429 80E Rue E",
    "sg:city":"Charlesbourg",
    "sg:classifiers":[
        {
            "category":"Home & Garden",
            "subcategory":"Home Furnishings",
            "type":"Retail Goods"
        }
    ],
    "sg:phone":"+1 418 628 6466",
    "sg:postcode":"G2L 1M4",
    "sg:province":"QC",
    "sg:tags":[
        "venetian",
        "window",
        "covering"
    ],
    "wof:name":"Stores Nordique Inc",
    "wof:placetype":"venue"
},
  "geometry": {"coordinates":[-71.251159668,46.8457183838],"type":"Point"}
}