{
  "type": "Feature",
  "properties": {
    "addr:full":"50 Rue Dufferin Salaberry-DE-Valleyfield QC J6S 4W4",
    "addr:housenumber":"50",
    "addr:postcode":"j6s 4w4",
    "addr:street":"Rue Dufferin",
    "iso:country":"CA",
    "sg:address":"50 Rue Dufferin",
    "sg:city":"Salaberry-DE-Valleyfield",
    "sg:classifiers":[
        {
            "category":"Real Estate",
            "subcategory":"Real Estate Operator",
            "type":"Services"
        }
    ],
    "sg:phone":"+1 450 371 3366",
    "sg:postcode":"J6S 4W4",
    "sg:province":"QC",
    "sg:tags":[
        "mall",
        "recreational",
        "shopping",
        "center",
        "vehicle"
    ],
    "wof:name":"Centre Valleyfield Ltee",
    "wof:placetype":"venue"
},
  "geometry": {"coordinates":[-74.1289367676,45.2623977661],"type":"Point"}
}