{
  "type": "Feature",
  "properties": {
    "addr:full":"1636 Regan Ave Coquitlam BC V3J 3B8",
    "addr:housenumber":"1636",
    "addr:postcode":"v3j 3b8",
    "addr:street":"Regan Ave",
    "iso:country":"CA",
    "sg:address":"1636 Regan Ave",
    "sg:city":"Coquitlam",
    "sg:classifiers":[
        {
            "category":"Organizations",
            "subcategory":"Religious Organization",
            "type":"Services"
        }
    ],
    "sg:phone":"+1 604 936 8242",
    "sg:postcode":"V3J 3B8",
    "sg:province":"BC",
    "sg:tags":[
        "church"
    ],
    "wof:name":"Calvary Baptist Church",
    "wof:placetype":"venue"
},
  "geometry": {"coordinates":[-122.848274231,49.2614250183],"type":"Point"}
}