{
  "type": "Feature",
  "properties": {
    "addr:full":"1457 117 Rte Val-David QC J0T 2N0",
    "addr:housenumber":"1457",
    "addr:postcode":"j0t 2n0",
    "addr:street":"117 Rte Val-David",
    "iso:country":"CA",
    "sg:address":"1457 117 Rte",
    "sg:city":"Val-David",
    "sg:classifiers":[
        {
            "category":"Autos & Motor Vehicles",
            "subcategory":"Boat Sales",
            "type":"Retail Goods"
        }
    ],
    "sg:phone":"+1 819 322 2140",
    "sg:postcode":"J0T 2N0",
    "sg:province":"QC",
    "sg:tags":[
        "dealer"
    ],
    "wof:name":"Theo Marine Enr",
    "wof:placetype":"venue"
},
  "geometry": {"coordinates":[-74.216347,46.02861],"type":"Point"}
}