{
  "type": "Feature",
  "properties": {
    "iso:country":"CA",
    "sg:address":"2725 Highway 62",
    "sg:city":"Hazelton",
    "sg:classifiers":[
        {
            "category":"Education",
            "subcategory":"School",
            "type":"Public Place"
        }
    ],
    "sg:phone":"+1 250 842 5858",
    "sg:postcode":"V0J 1Y0",
    "sg:province":"BC",
    "wof:name":"Home School CO-Ordinator",
    "wof:placetype":"venue"
},
  "geometry": {"coordinates":[-127.643867493,55.2642593384],"type":"Point"}
}