{
  "type": "Feature",
  "properties": {
    "addr:full":"Camin Lake S Rd Canim Lake BC V0K 1J0",
    "addr:postcode":"v0k 1j0",
    "addr:street":"Camin Lake S",
    "iso:country":"CA",
    "sg:address":"Camin Lake S Rd",
    "sg:city":"Canim Lake",
    "sg:classifiers":[
        {
            "category":"Building & Trades",
            "subcategory":"Construction",
            "type":"Services"
        }
    ],
    "sg:phone":"+1 250 397 2519",
    "sg:postcode":"V0K 1J0",
    "sg:province":"BC",
    "sg:tags":[
        "contractor"
    ],
    "wof:name":"Three Feathers Construction",
    "wof:placetype":"venue"
},
  "geometry": {"coordinates":[-120.91002655,51.7684059143],"type":"Point"}
}