{
  "type": "Feature",
  "properties": {
    "addr:full":"67 Main St E Kingsville ON N9Y 1A1",
    "addr:housenumber":"67",
    "addr:postcode":"n9y 1a1",
    "addr:street":"Main St E",
    "iso:country":"CA",
    "sg:address":"67 Main St E",
    "sg:city":"Kingsville",
    "sg:classifiers":[
        {
            "category":"Organizations",
            "subcategory":"Religious Organization",
            "type":"Services"
        }
    ],
    "sg:phone":"+1 519 733 6591",
    "sg:postcode":"N9Y 1A1",
    "sg:province":"ON",
    "sg:tags":[
        "church"
    ],
    "wof:name":"St John DE Brebuef Church",
    "wof:placetype":"venue"
},
  "geometry": {"coordinates":[-82.73696136469999,42.0378990173],"type":"Point"}
}