{
  "type": "Feature",
  "properties": {
    "iso:country":"CA",
    "sg:address":"58 Grosvenor Ave",
    "sg:city":"Ottawa",
    "sg:classifiers":[
        {
            "category":"Organizations",
            "subcategory":"Religious Organization",
            "type":"Services"
        }
    ],
    "sg:phone":"+1 613 730 9411",
    "sg:postcode":"K1S 4S4",
    "sg:province":"ON",
    "sg:tags":[
        "church"
    ],
    "wof:name":"Sunnyside Wesleyan Church",
    "wof:placetype":"venue"
},
  "geometry": {"coordinates":[-75.68631744379999,45.3933258057],"type":"Point"}
}