{
  "type": "Feature",
  "properties": {
    "addr:full":"51 Boul Mercier Amos QC J9T 2N8",
    "addr:housenumber":"51",
    "addr:postcode":"j9t 2n8",
    "addr:street":"Boul Mercier",
    "iso:country":"CA",
    "sg:address":"51 Boul Mercier",
    "sg:city":"Amos",
    "sg:classifiers":[
        {
            "category":"Health Services",
            "subcategory":"Doctor",
            "type":"Services"
        }
    ],
    "sg:phone":"+1 819 732 8368",
    "sg:postcode":"J9T 2N8",
    "sg:province":"QC",
    "sg:tags":[
        "dentist"
    ],
    "wof:name":"Arseneault, Eric DDS",
    "wof:placetype":"venue"
},
  "geometry": {"coordinates":[-78.1216812134,48.5712165833],"type":"Point"}
}