{
  "type": "Feature",
  "properties": {
    "iso:country":"CA",
    "sg:city":"Sainte-Anne-Des-Lacs",
    "sg:classifiers":[
        {
            "category":"Home & Garden",
            "subcategory":"Hardware",
            "type":"Retail Goods"
        }
    ],
    "sg:phone":"+1 450 224 2068",
    "sg:postcode":"J0R 1B0",
    "sg:province":"QC",
    "sg:tags":[
        "building",
        "material"
    ],
    "wof:name":"Robert Boyer Materiaux-Constr",
    "wof:placetype":"venue"
},
  "geometry": {"coordinates":[-74.12757873539999,45.8598480225],"type":"Point"}
}