{
  "type": "Feature",
  "properties": {
    "addr:full":"25 Mccurdy Dr Gander NL A1V 1A1",
    "addr:housenumber":"25",
    "addr:postcode":"a1v 1a1",
    "addr:street":"Mccurdy Dr",
    "iso:country":"CA",
    "sg:address":"25 Mccurdy Dr",
    "sg:city":"Gander",
    "sg:classifiers":[
        {
            "category":"Wholesale",
            "subcategory":"Auto Parts",
            "type":"Manufacturing & Wholesale Goods"
        }
    ],
    "sg:phone":"+1 709 256 7912",
    "sg:postcode":"A1V 1A1",
    "sg:province":"NL",
    "sg:tags":[
        "automobile",
        "rebuilt"
    ],
    "wof:name":"Quinlan's Bern Auto Body",
    "wof:placetype":"venue"
},
  "geometry": {"coordinates":[-54.621899,48.963562],"type":"Point"}
}