{
  "type": "Feature",
  "properties": {
    "addr:full":"202 Rye St Yellow Grass SK S0G 5J0",
    "addr:housenumber":"202",
    "addr:postcode":"s0g 5j0",
    "addr:street":"Rye St",
    "iso:country":"CA",
    "sg:address":"202 Rye St",
    "sg:city":"Yellow Grass",
    "sg:classifiers":[
        {
            "category":"Organizations",
            "subcategory":"Religious Organization",
            "type":"Services"
        }
    ],
    "sg:phone":"+1 306 465 2852",
    "sg:postcode":"S0G 5J0",
    "sg:province":"SK",
    "sg:tags":[
        "church"
    ],
    "wof:name":"Peace Lutheran Church",
    "wof:placetype":"venue"
},
  "geometry": {"coordinates":[-104.15883599999999,49.806889],"type":"Point"}
}