{
  "type": "Feature",
  "properties": {
    "addr:full":"Glace Bay NS B1A 6H4",
    "addr:postcode":"b1a 6h4",
    "iso:country":"CA",
    "sg:city":"Glace Bay",
    "sg:classifiers":[
        {
            "category":"Insurance",
            "subcategory":"Insurance Agent",
            "type":"Services"
        }
    ],
    "sg:phone":"+1 902 849 4585",
    "sg:postcode":"B1A 6H4",
    "sg:province":"NS",
    "wof:name":"Mac Kenzie Insurance",
    "wof:placetype":"venue"
},
  "geometry": {"coordinates":[-59.957615,46.20116],"type":"Point"}
}