{
  "type": "Feature",
  "properties": {
    "addr:full":"10112 107 St NW Edmonton AB T5J 1J4",
    "addr:housenumber":"10112",
    "addr:postcode":"t5j 1j4",
    "addr:street":"107 St Nw",
    "iso:country":"CA",
    "sg:address":"10112 107 St NW",
    "sg:city":"Edmonton",
    "sg:classifiers":[
        {
            "category":"Shopping",
            "subcategory":"Clothing, Apparel, & Fashions",
            "type":"Retail Goods"
        }
    ],
    "sg:phone":"+1 780 424 4543",
    "sg:postcode":"T5J 1J4",
    "sg:province":"AB",
    "sg:tags":[
        "designer"
    ],
    "wof:name":"Morris Furs Ltd",
    "wof:placetype":"venue"
},
  "geometry": {"coordinates":[-113.504989624,53.5413589478],"type":"Point"}
}