{
  "type": "Feature",
  "properties": {
    "addr:full":"15 Talbot St E Leamington ON N8H 1L1",
    "addr:housenumber":"15",
    "addr:postcode":"n8h 1l1",
    "addr:street":"Talbot St E",
    "iso:country":"CA",
    "sg:address":"15 Talbot St E",
    "sg:city":"Leamington",
    "sg:classifiers":[
        {
            "category":"Education",
            "subcategory":"Special Training",
            "type":"Public Place"
        }
    ],
    "sg:phone":"+1 519 324 0616",
    "sg:postcode":"N8H 1L1",
    "sg:province":"ON",
    "sg:tags":[
        "instruction",
        "driving"
    ],
    "wof:name":"Leamington School of Motoring",
    "wof:placetype":"venue"
},
  "geometry": {"coordinates":[-82.59936500000001,42.053349],"type":"Point"}
}