{
  "type": "Feature",
  "properties": {
    "iso:country":"CA",
    "sg:address":"2362 Rue Beaubien E",
    "sg:city":"Montreal",
    "sg:classifiers":[
        {
            "category":"Shopping",
            "subcategory":"Clothing, Apparel, & Fashions",
            "type":"Retail Goods"
        }
    ],
    "sg:phone":"+1 514 722 7104",
    "sg:postcode":"H2G 1N2",
    "sg:province":"QC",
    "sg:tags":[
        "jean"
    ],
    "wof:name":"Vetements Le Loft",
    "wof:placetype":"venue"
},
  "geometry": {"coordinates":[-73.592415,45.547775],"type":"Point"}
}