{
  "type": "Feature",
  "properties": {
    "addr:full":"Ferme-Neuve QC J0W 1C0",
    "addr:postcode":"j0w 1c0",
    "iso:country":"CA",
    "sg:city":"Ferme-Neuve",
    "sg:classifiers":[
        {
            "category":"Shopping",
            "subcategory":"Pharmacy",
            "type":"Retail Goods"
        }
    ],
    "sg:phone":"+1 819 587 3411",
    "sg:postcode":"J0W 1C0",
    "sg:province":"QC",
    "sg:tags":[
        "orthopedic",
        "appliance"
    ],
    "wof:name":"Duval & Delombaerde Pharmacien",
    "wof:placetype":"venue"
},
  "geometry": {"coordinates":[-75.45362900000001,46.70084],"type":"Point"}
}