{
  "type": "Feature",
  "properties": {
    "addr:full":"104 Bond St Toronto ON M5B 1X9",
    "addr:housenumber":"104",
    "addr:postcode":"m5b 1x9",
    "addr:street":"Bond St",
    "iso:country":"CA",
    "sg:address":"104 Bond St",
    "sg:city":"Toronto",
    "sg:classifiers":[
        {
            "category":"Health Services",
            "subcategory":"Medical Lab",
            "type":"Services"
        }
    ],
    "sg:phone":"+1 416 977 0700",
    "sg:postcode":"M5B 1X9",
    "sg:province":"ON",
    "sg:tags":[
        "laboratory"
    ],
    "wof:name":"Shaw Laboratories Inc",
    "wof:placetype":"venue"
},
  "geometry": {"coordinates":[-79.37876900000001,43.656967],"type":"Point"}
}