{
  "type": "Feature",
  "properties": {
    "addr:full":"66 Sheridan Ave Toronto ON M6K 2G9",
    "addr:housenumber":"66",
    "addr:postcode":"m6k 2g9",
    "addr:street":"Sheridan Ave",
    "iso:country":"CA",
    "sg:address":"66 Sheridan Ave",
    "sg:city":"Toronto",
    "sg:classifiers":[
        {
            "category":"Recreation",
            "type":"Entertainment"
        }
    ],
    "sg:phone":"+1 416 392 0742",
    "sg:postcode":"M6K 2G9",
    "sg:province":"ON",
    "sg:tags":[
        "government",
        "hall",
        "auditorium"
    ],
    "wof:name":"Mc Cormick Community Ctr",
    "wof:placetype":"venue"
},
  "geometry": {"coordinates":[-79.432991,43.647568],"type":"Point"}
}