{
  "type": "Feature",
  "properties": {
    "addr:full":"19 Rue Papillon Cap-Sante QC G0A 1L0",
    "addr:housenumber":"19",
    "addr:postcode":"g0a 1l0",
    "addr:street":"Rue Papillon Cap-Sante",
    "iso:country":"CA",
    "sg:address":"19 Rue Papillon",
    "sg:city":"Cap-Sante",
    "sg:classifiers":[
        {
            "category":"Wholesale",
            "subcategory":"Meat",
            "type":"Manufacturing & Wholesale Goods"
        }
    ],
    "sg:phone":"+1 418 285 2755",
    "sg:postcode":"G0A 1L0",
    "sg:province":"QC",
    "sg:tags":[
        "butchering"
    ],
    "wof:name":"Boucherie A Godin Inc",
    "wof:placetype":"venue"
},
  "geometry": {"coordinates":[-71.7579956055,46.6712188721],"type":"Point"}
}