{
  "type": "Feature",
  "properties": {
    "addr:full":"PO Box 98 Birch Island ON P0P 1A0",
    "addr:housenumber":"po box 98",
    "addr:postcode":"p0p 1a0",
    "addr:street":"Island",
    "iso:country":"CA",
    "sg:address":"PO Box 98",
    "sg:city":"Birch Island",
    "sg:classifiers":[
        {
            "category":"Travel",
            "subcategory":"Hotels & Motels",
            "type":"Entertainment"
        }
    ],
    "sg:phone":"+1 705 285 4848",
    "sg:postcode":"P0P 1A0",
    "sg:province":"ON",
    "sg:tags":[
        "cottage",
        "cabin"
    ],
    "wof:name":"Mc Gregor Bay Lodge",
    "wof:placetype":"venue"
},
  "geometry": {"coordinates":[-81.77177399999999,46.063595],"type":"Point"}
}