{
  "type": "Feature",
  "properties": {
    "addr:full":"3831 Bow Trail SW # A Calgary AB T3C 2E8",
    "addr:housenumber":"3831",
    "addr:postcode":"t3c 2e8",
    "addr:street":"Bow Trail Sw # A",
    "iso:country":"CA",
    "sg:address":"3831 Bow Trail SW # A",
    "sg:city":"Calgary",
    "sg:classifiers":[
        {
            "category":"Manufacturing",
            "subcategory":"Jewelry",
            "type":"Manufacturing & Wholesale Goods"
        }
    ],
    "sg:phone":"+1 403 246 8833",
    "sg:postcode":"T3C 2E8",
    "sg:province":"AB",
    "wof:name":"Goldsmiths Workshop Inc",
    "wof:placetype":"venue"
},
  "geometry": {"coordinates":[-114.141701,51.045113],"type":"Point"}
}