{
  "type": "Feature",
  "properties": {
    "iso:country":"CA",
    "sg:address":"1764 Rathburn Rd E",
    "sg:city":"Mississauga",
    "sg:classifiers":[
        {
            "category":"Manufacturing",
            "subcategory":"Tools & Machinery",
            "type":"Manufacturing & Wholesale Goods"
        }
    ],
    "sg:phone":"+1 905 625 4500",
    "sg:postcode":"L4W 2N8",
    "sg:province":"ON",
    "sg:tags":[
        "equipment",
        "laboratory",
        "supply"
    ],
    "wof:name":"Marsys Inc",
    "wof:placetype":"venue"
},
  "geometry": {"coordinates":[-79.5987167358,43.6343841553],"type":"Point"}
}