{
  "type": "Feature",
  "properties": {
    "addr:full":"415 Main St Hepburn SK S0K 1Z0",
    "addr:housenumber":"415",
    "addr:postcode":"s0k 1z0",
    "addr:street":"Main St",
    "iso:country":"CA",
    "sg:address":"415 Main St",
    "sg:city":"Hepburn",
    "sg:classifiers":[
        {
            "category":"Real Estate",
            "subcategory":"Real Estate Agent",
            "type":"Services"
        }
    ],
    "sg:phone":"+1 306 947 2188",
    "sg:postcode":"S0K 1Z0",
    "sg:province":"SK",
    "sg:tags":[
        "cooperative"
    ],
    "wof:name":"Hepburn CO-OP",
    "wof:placetype":"venue"
},
  "geometry": {"coordinates":[-106.73151397700001,52.5221633911],"type":"Point"}
}