{
  "type": "Feature",
  "properties": {
    "addr:full":"3 Oakhurst Dr North York ON M2K 2N2",
    "addr:housenumber":"3",
    "addr:postcode":"m2k 2n2",
    "addr:street":"Oakhurst Dr",
    "iso:country":"CA",
    "sg:address":"3 Oakhurst Dr",
    "sg:city":"North York",
    "sg:classifiers":[
        {
            "category":"Health Services",
            "subcategory":"Clinic",
            "type":"Services"
        }
    ],
    "sg:phone":"+1 416 218 0696",
    "sg:postcode":"M2K 2N2",
    "sg:province":"ON",
    "sg:tags":[
        "holistic",
        "practitioner"
    ],
    "wof:name":"Usui Reiki Ctr",
    "wof:placetype":"venue"
},
  "geometry": {"coordinates":[-79.3918685913,43.7930793762],"type":"Point"}
}