{
  "type": "Feature",
  "properties": {
    "iso:country":"CA",
    "sg:address":"9737 Yonge St # 217",
    "sg:city":"Richmond Hill",
    "sg:classifiers":[
        {
            "category":"Wholesale",
            "subcategory":"Machinery & Supplies",
            "type":"Manufacturing & Wholesale Goods"
        }
    ],
    "sg:phone":"+1 905 508 7089",
    "sg:postcode":"L4C 8S7",
    "sg:province":"ON",
    "sg:tags":[
        "salon",
        "beauty"
    ],
    "wof:name":"Toronto Barber & Beauty Supply",
    "wof:placetype":"venue"
},
  "geometry": {"coordinates":[-79.4356307983,43.8650436401],"type":"Point"}
}