{
  "type": "Feature",
  "properties": {
    "addr:full":"35 Oak St North York ON M9N 1A1",
    "addr:housenumber":"35",
    "addr:postcode":"m9n 1a1",
    "addr:street":"Oak St",
    "iso:country":"CA",
    "sg:address":"35 Oak St",
    "sg:city":"North York",
    "sg:classifiers":[
        {
            "category":"Building & Trades",
            "subcategory":"Construction",
            "type":"Services"
        }
    ],
    "sg:phone":"+1 416 244 5860",
    "sg:postcode":"M9N 1A1",
    "sg:province":"ON",
    "sg:tags":[
        "concrete",
        "contractor"
    ],
    "wof:name":"Brentview Construction Ltd",
    "wof:placetype":"venue"
},
  "geometry": {"coordinates":[-79.52992248539999,43.7084197998],"type":"Point"}
}