{
  "type": "Feature",
  "properties": {
    "addr:full":"2946 Baseline Rd Nepean ON K2H 8T5",
    "addr:housenumber":"2946",
    "addr:postcode":"k2h 8t5",
    "addr:street":"Baseline Rd",
    "iso:country":"CA",
    "sg:address":"2946 Baseline Rd",
    "sg:city":"Nepean",
    "sg:classifiers":[
        {
            "category":"Wholesale",
            "subcategory":"Non-durable Goods",
            "type":"Manufacturing & Wholesale Goods"
        }
    ],
    "sg:phone":"+1 613 820 6920",
    "sg:postcode":"K2H 8T5",
    "sg:province":"ON",
    "sg:tags":[
        "shop",
        "interior",
        "fabric"
    ],
    "wof:name":"Bou Clair Inc",
    "wof:placetype":"venue"
},
  "geometry": {"coordinates":[-75.7997741699,45.335723877],"type":"Point"}
}