{
  "type": "Feature",
  "properties": {
    "addr:full":"5136 51st Ave Drayton Valley AB T7A 1S5",
    "addr:housenumber":"5136",
    "addr:postcode":"t7a 1s5",
    "addr:street":"51St Ave",
    "iso:country":"CA",
    "sg:address":"5136 51st Ave",
    "sg:city":"Drayton Valley",
    "sg:classifiers":[
        {
            "category":"Social Services",
            "type":"Services"
        }
    ],
    "sg:phone":"+1 780 542 3140",
    "sg:postcode":"T7A 1S5",
    "sg:province":"AB",
    "sg:tags":[
        "counseling"
    ],
    "wof:name":"Mental Health",
    "wof:placetype":"venue"
},
  "geometry": {"coordinates":[-114.978981,53.222527],"type":"Point"}
}