{
  "type": "Feature",
  "properties": {
    "addr:full":"Red Sucker Lake MB R0B 1H0",
    "addr:postcode":"r0b 1h0",
    "iso:country":"CA",
    "sg:city":"Red Sucker Lake",
    "sg:classifiers":[
        {
            "category":"Organizations",
            "subcategory":"Community Association",
            "type":"Services"
        }
    ],
    "sg:phone":"+1 204 469 5042",
    "sg:postcode":"R0B 1H0",
    "sg:province":"MB",
    "sg:tags":[
        "social",
        "native",
        "welfare"
    ],
    "wof:name":"Red Sucker Lake First Nation",
    "wof:placetype":"venue"
},
  "geometry": {"coordinates":[-93.5749969482,54.1552848816],"type":"Point"}
}