{
  "type": "Feature",
  "properties": {
    "addr:full":"1265 County Road 18 Oxford Mills ON K0G 1S0",
    "addr:housenumber":"1265",
    "addr:postcode":"k0g 1s0",
    "addr:street":"County Road 18",
    "iso:country":"CA",
    "sg:address":"1265 County Road 18",
    "sg:city":"Oxford Mills",
    "sg:classifiers":[
        {
            "category":"Retail",
            "subcategory":"Repair Shop",
            "type":"Services"
        }
    ],
    "sg:phone":"+1 613 258 2088",
    "sg:postcode":"K0G 1S0",
    "sg:province":"ON",
    "sg:tags":[
        "upholsterer"
    ],
    "wof:name":"Kate's Upholstery",
    "wof:placetype":"venue"
},
  "geometry": {"coordinates":[-75.6793060303,44.9659385681],"type":"Point"}
}