{
  "type": "Feature",
  "properties": {
    "addr:full":"13441 St Albert Trail NW Edmonton AB T5L 4X1",
    "addr:housenumber":"13441",
    "addr:postcode":"t5l 4x1",
    "addr:street":"St Albert Trail Nw",
    "iso:country":"CA",
    "sg:address":"13441 St Albert Trail NW",
    "sg:city":"Edmonton",
    "sg:classifiers":[
        {
            "category":"Freight",
            "type":"Transportation"
        }
    ],
    "sg:phone":"+1 780 413 6464",
    "sg:postcode":"T5L 4X1",
    "sg:province":"AB",
    "sg:tags":[
        "commercial",
        "storage"
    ],
    "wof:name":"Affordable Storage Ctr",
    "wof:placetype":"venue"
},
  "geometry": {"coordinates":[-113.57093,53.595791],"type":"Point"}
}