{
  "type": "Feature",
  "properties": {
    "iso:country":"CA",
    "sg:address":"1062 Boul Saint-Laurent",
    "sg:city":"Montreal",
    "sg:classifiers":[
        {
            "category":"Food & Beverages",
            "subcategory":"Groceries & Convenience Stores",
            "type":"Retail Goods"
        }
    ],
    "sg:phone":"+1 514 393 1030",
    "sg:postcode":"H2Z 1J5",
    "sg:province":"QC",
    "sg:tags":[
        "grocer"
    ],
    "wof:name":"Kien Vinh Corp",
    "wof:placetype":"venue"
},
  "geometry": {"coordinates":[-73.560371,45.50816],"type":"Point"}
}