{
  "type": "Feature",
  "properties": {
    "addr:full":"5013 49 St Wetaskiwin AB T9A 1H6",
    "addr:housenumber":"5013",
    "addr:postcode":"t9a 1h6",
    "addr:street":"49 St",
    "iso:country":"CA",
    "sg:address":"5013 49 St",
    "sg:city":"Wetaskiwin",
    "sg:classifiers":[
        {
            "category":"Sports & Exercise",
            "subcategory":"Bowling",
            "type":"Entertainment"
        }
    ],
    "sg:phone":"+1 780 352 4705",
    "sg:postcode":"T9A 1H6",
    "sg:province":"AB",
    "sg:tags":[
        "center"
    ],
    "wof:name":"Western Lanes Bowling",
    "wof:placetype":"venue"
},
  "geometry": {"coordinates":[-113.37223053,52.969619751],"type":"Point"}
}