{
  "type": "Feature",
  "properties": {
    "addr:full":"400 Mccurdy Rd Kelowna BC V1X 2P3",
    "addr:housenumber":"400",
    "addr:postcode":"v1x 2p3",
    "addr:street":"Mccurdy Rd",
    "iso:country":"CA",
    "sg:address":"400 Mccurdy Rd",
    "sg:city":"Kelowna",
    "sg:classifiers":[
        {
            "category":"Retail",
            "subcategory":"Repair Shop",
            "type":"Services"
        }
    ],
    "sg:phone":"+1 250 765 4793",
    "sg:postcode":"V1X 2P3",
    "sg:province":"BC",
    "sg:tags":[
        "vinyl"
    ],
    "wof:name":"Red's Repair & Touchup",
    "wof:placetype":"venue"
},
  "geometry": {"coordinates":[-119.393204,49.901367],"type":"Point"}
}