{
  "type": "Feature",
  "properties": {
    "addr:full":"44 Brack Pl Thornhill ON L4J 2W3",
    "addr:housenumber":"44",
    "addr:postcode":"l4j 2w3",
    "addr:street":"Brack Pl",
    "iso:country":"CA",
    "sg:address":"44 Brack Pl",
    "sg:city":"Thornhill",
    "sg:classifiers":[
        {
            "category":"Home & Garden",
            "subcategory":"Home Furnishings",
            "type":"Retail Goods"
        }
    ],
    "sg:phone":"+1 905 660 4374",
    "sg:postcode":"L4J 2W3",
    "sg:province":"ON",
    "sg:tags":[
        "venetian",
        "blind"
    ],
    "wof:name":"Roma Drapery",
    "wof:placetype":"venue"
},
  "geometry": {"coordinates":[-79.4647979736,43.7905731201],"type":"Point"}
}