{
  "type": "Feature",
  "properties": {
    "addr:full":"335 Adelaide St Thunder Bay ON P7A 7T8",
    "addr:housenumber":"335",
    "addr:postcode":"p7a 7t8",
    "addr:street":"Adelaide St",
    "iso:country":"CA",
    "sg:address":"335 Adelaide St",
    "sg:city":"Thunder Bay",
    "sg:classifiers":[
        {
            "category":"Real Estate",
            "subcategory":"Real Estate Operator",
            "type":"Services"
        }
    ],
    "sg:phone":"+1 807 683 6692",
    "sg:postcode":"P7A 7T8",
    "sg:province":"ON",
    "sg:tags":[
        "apartment"
    ],
    "wof:name":"Harbour Heights Apartments",
    "wof:placetype":"venue"
},
  "geometry": {"coordinates":[-89.185799,48.457348],"type":"Point"}
}