{
  "type": "Feature",
  "properties": {
    "addr:full":"85 Rue Notre-Dame Nicolet QC J3T 1V8",
    "addr:housenumber":"85",
    "addr:postcode":"j3t 1v8",
    "addr:street":"Rue Notre-Dame",
    "iso:country":"CA",
    "sg:address":"85 Rue Notre-Dame",
    "sg:city":"Nicolet",
    "sg:classifiers":[
        {
            "category":"Professional",
            "subcategory":"Accounting & Tax Preparation",
            "type":"Services"
        }
    ],
    "sg:phone":"+1 819 293 6181",
    "sg:postcode":"J3T 1V8",
    "sg:province":"QC",
    "sg:tags":[
        "accountant"
    ],
    "wof:name":"Verrier Paquin Hebert",
    "wof:placetype":"venue"
},
  "geometry": {"coordinates":[-72.61842300000001,46.226635],"type":"Point"}
}