{
  "type": "Feature",
  "properties": {
    "addr:full":"Scarborough ON M1X 1L6",
    "addr:postcode":"m1x 1l6",
    "iso:country":"CA",
    "sg:city":"Scarborough",
    "sg:classifiers":[
        {
            "category":"Home & Garden",
            "subcategory":"Furniture",
            "type":"Retail Goods"
        }
    ],
    "sg:phone":"+1 416 321 6336",
    "sg:postcode":"M1X 1L6",
    "sg:province":"ON",
    "sg:tags":[
        "builder",
        "custom"
    ],
    "wof:name":"Golden Renovation CO",
    "wof:placetype":"venue"
},
  "geometry": {"coordinates":[-79.249832,43.829308],"type":"Point"}
}