{
  "type": "Feature",
  "properties": {
    "addr:full":"205 Granville St Vanier ON K1L 6Y7",
    "addr:housenumber":"205",
    "addr:postcode":"k1l 6y7",
    "addr:street":"Granville St",
    "iso:country":"CA",
    "sg:address":"205 Granville St",
    "sg:city":"Vanier",
    "sg:classifiers":[
        {
            "category":"Building & Trades",
            "subcategory":"Plumbing",
            "type":"Services"
        }
    ],
    "sg:phone":"+1 613 745 2872",
    "sg:postcode":"K1L 6Y7",
    "sg:province":"ON",
    "sg:tags":[
        "contractor"
    ],
    "wof:name":"Belanger Plumbing & Heating",
    "wof:placetype":"venue"
},
  "geometry": {"coordinates":[-75.656693,45.440346],"type":"Point"}
}