{
  "type": "Feature",
  "properties": {
    "addr:full":"255 Railway Ave Duchess AB T0J 0Z0",
    "addr:housenumber":"255",
    "addr:postcode":"t0j 0z0",
    "addr:street":"Railway Ave",
    "iso:country":"CA",
    "sg:address":"255 Railway Ave",
    "sg:city":"Duchess",
    "sg:classifiers":[
        {
            "category":"Food & Beverages",
            "subcategory":"Groceries & Convenience Stores",
            "type":"Retail Goods"
        }
    ],
    "sg:phone":"+1 403 378 3133",
    "sg:postcode":"T0J 0Z0",
    "sg:province":"AB",
    "wof:name":"Whistle Stop Convenience Store",
    "wof:placetype":"venue"
},
  "geometry": {"coordinates":[-111.90036000000001,50.731575],"type":"Point"}
}