{
  "type": "Feature",
  "properties": {
    "addr:full":"1189 13th St Kamloops BC V2B 8K4",
    "addr:housenumber":"1189",
    "addr:postcode":"bc v2b 8k4",
    "addr:street":"13Th St",
    "iso:country":"CA",
    "sg:address":"1189 13th St",
    "sg:city":"Kamloops",
    "sg:classifiers":[
        {
            "category":"Retail",
            "subcategory":"Repair Shop",
            "type":"Services"
        }
    ],
    "sg:phone":"+1 250 376 2185",
    "sg:postcode":"V2B 8K4",
    "sg:province":"BC",
    "sg:tags":[
        "television",
        "radio"
    ],
    "wof:name":"Onkar Electronics",
    "wof:placetype":"venue"
},
  "geometry": {"coordinates":[-120.37505299999999,50.706787],"type":"Point"}
}