{
  "type": "Feature",
  "properties": {
    "addr:full":"Halifax NS B3K 2R7",
    "addr:postcode":"b3k 2r7",
    "iso:country":"CA",
    "sg:city":"Halifax",
    "sg:classifiers":[
        {
            "category":"Banks & Credit Unions",
            "subcategory":"Investment Brokerage",
            "type":"Services"
        }
    ],
    "sg:phone":"+1 902 453 4220",
    "sg:postcode":"B3K 2R7",
    "sg:province":"NS",
    "wof:name":"League Savings & Mortgage",
    "wof:placetype":"venue"
},
  "geometry": {"coordinates":[-63.6125717163,44.6650924683],"type":"Point"}
}