{
  "type": "Feature",
  "properties": {
    "iso:country":"CA",
    "sg:address":"111 54 St",
    "sg:city":"Edson",
    "sg:classifiers":[
        {
            "category":"Government",
            "subcategory":"Office",
            "type":"Public Place"
        }
    ],
    "sg:phone":"+1 780 723 8229",
    "sg:postcode":"T7E 1T2",
    "sg:province":"AB",
    "wof:name":"Alberta Business Svc",
    "wof:placetype":"venue"
},
  "geometry": {"coordinates":[-116.43901062,53.5780410767],"type":"Point"}
}