{
  "type": "Feature",
  "properties": {
    "addr:full":"Scarborough ON M1P 2R2",
    "addr:postcode":"m1p 2r2",
    "iso:country":"CA",
    "sg:city":"Scarborough",
    "sg:classifiers":[
        {
            "category":"Professional",
            "subcategory":"Accounting & Tax Preparation",
            "type":"Services"
        }
    ],
    "sg:phone":"+1 416 701 1075",
    "sg:postcode":"M1P 2R2",
    "sg:province":"ON",
    "sg:tags":[
        "return",
        "filing"
    ],
    "wof:name":"Executive Management & Acctg",
    "wof:placetype":"venue"
},
  "geometry": {"coordinates":[-79.27741241459999,43.7491645813],"type":"Point"}
}