{
  "type": "Feature",
  "properties": {
    "addr:full":"Wawa ON P0S 1K0",
    "addr:postcode":"p0s 1k0",
    "iso:country":"CA",
    "sg:city":"Wawa",
    "sg:classifiers":[
        {
            "category":"Retail",
            "subcategory":"Auto Repair",
            "type":"Services"
        }
    ],
    "sg:phone":"+1 705 856 0006",
    "sg:postcode":"P0S 1K0",
    "sg:province":"ON",
    "sg:tags":[
        "repairing",
        "automobile"
    ],
    "wof:name":"Z M Repairs",
    "wof:placetype":"venue"
},
  "geometry": {"coordinates":[-84.77266693120001,47.9909858704],"type":"Point"}
}