{
  "type": "Feature",
  "properties": {
    "addr:full":"Toronto ON M5A 3W7",
    "addr:postcode":"m5a 3w7",
    "iso:country":"CA",
    "sg:city":"Toronto",
    "sg:classifiers":[
        {
            "category":"Restaurant",
            "type":"Food & Drink"
        }
    ],
    "sg:phone":"+1 416 924 2399",
    "sg:postcode":"M5A 3W7",
    "sg:province":"ON",
    "wof:name":"Carlton Burger Palace",
    "wof:placetype":"venue"
},
  "geometry": {"coordinates":[-79.37549591059999,43.6628112793],"type":"Point"}
}