{
  "type": "Feature",
  "properties": {
    "addr:full":"175 Bloor St E Toronto ON M4W 3R8",
    "addr:housenumber":"175",
    "addr:postcode":"m4w 3r8",
    "addr:street":"Bloor St E",
    "iso:country":"CA",
    "sg:address":"175 Bloor St E",
    "sg:city":"Toronto",
    "sg:classifiers":[
        {
            "category":"Personal",
            "subcategory":"Beauty Salon",
            "type":"Services"
        }
    ],
    "sg:phone":"+1 416 968 1300",
    "sg:postcode":"M4W 3R8",
    "sg:province":"ON",
    "wof:name":"Salon Riccardo",
    "wof:placetype":"venue"
},
  "geometry": {"coordinates":[-79.38299600000001,43.670967],"type":"Point"}
}