{
  "type": "Feature",
  "properties": {
    "addr:full":"1386 Victoria Park Ave North York ON M4A 2L8",
    "addr:housenumber":"1386",
    "addr:postcode":"m4a 2l8",
    "addr:street":"Victoria Park Ave",
    "iso:country":"CA",
    "sg:address":"1386 Victoria Park Ave",
    "sg:city":"North York",
    "sg:classifiers":[
        {
            "category":"Social Services",
            "subcategory":"Child Care",
            "type":"Services"
        }
    ],
    "sg:phone":"+1 416 392 6545",
    "sg:postcode":"M4A 2L8",
    "sg:province":"ON",
    "sg:tags":[
        "government"
    ],
    "wof:name":"Toronto Child Care Ctr",
    "wof:placetype":"venue"
},
  "geometry": {"coordinates":[-79.299835,43.717709],"type":"Point"}
}