{
  "type": "Feature",
  "properties": {
    "addr:full":"5541 Doyle Rd Manotick ON K4M 1B4",
    "addr:housenumber":"5541",
    "addr:postcode":"k4m 1b4",
    "addr:street":"Doyle Rd",
    "iso:country":"CA",
    "sg:address":"5541 Doyle Rd",
    "sg:city":"Manotick",
    "sg:classifiers":[
        {
            "category":"Wholesale",
            "subcategory":"Fruits & Vegetables",
            "type":"Manufacturing & Wholesale Goods"
        }
    ],
    "sg:phone":"+1 613 692 3388",
    "sg:postcode":"K4M 1B4",
    "sg:province":"ON",
    "sg:tags":[
        "shipper"
    ],
    "wof:name":"Sun Tech Greenhouses Ltd",
    "wof:placetype":"venue"
},
  "geometry": {"coordinates":[-75.685936,45.226265],"type":"Point"}
}