{
  "type": "Feature",
  "properties": {
    "addr:full":"824 Dewdney Ave Regina SK S4N 0G7",
    "addr:housenumber":"824",
    "addr:postcode":"s4n 0g7",
    "addr:street":"Dewdney Ave",
    "iso:country":"CA",
    "sg:address":"824 Dewdney Ave",
    "sg:city":"Regina",
    "sg:classifiers":[
        {
            "category":"Manufacturing",
            "subcategory":"Motor Vehicles & Parts",
            "type":"Manufacturing & Wholesale Goods"
        }
    ],
    "sg:phone":"+1 306 522 8547",
    "sg:postcode":"S4N 0G7",
    "sg:province":"SK",
    "sg:tags":[
        "automobile",
        "wrecking"
    ],
    "wof:name":"Best Buy Auto Parts Ltd",
    "wof:placetype":"venue"
},
  "geometry": {"coordinates":[-104.592887878,50.455280304],"type":"Point"}
}