{
  "type": "Feature",
  "properties": {
    "addr:full":"Toronto ON M5V 3C7",
    "addr:postcode":"m5v 3c7",
    "iso:country":"CA",
    "sg:city":"Toronto",
    "sg:classifiers":[
        {
            "category":"Shopping",
            "subcategory":"Computers & Home Electronics",
            "type":"Retail Goods"
        }
    ],
    "sg:phone":"+1 416 598 9500",
    "sg:postcode":"M5V 3C7",
    "sg:province":"ON",
    "sg:tags":[
        "software"
    ],
    "wof:name":"Fri Corp",
    "wof:placetype":"venue"
},
  "geometry": {"coordinates":[-79.38603973390001,43.6460723877],"type":"Point"}
}