{
  "type": "Feature",
  "properties": {
    "addr:full":"1 Market Sq Saint John NB E2L 4Z6",
    "addr:housenumber":"1",
    "addr:postcode":"e2l 4z6",
    "addr:street":"Market Sq",
    "iso:country":"CA",
    "sg:address":"1 Market Sq",
    "sg:city":"Saint John",
    "sg:classifiers":[
        {
            "category":"Parking",
            "type":"Transportation"
        }
    ],
    "sg:phone":"+1 506 693 2509",
    "sg:postcode":"E2L 4Z6",
    "sg:province":"NB",
    "sg:tags":[
        "garage"
    ],
    "wof:name":"Canpark Services Ltd",
    "wof:placetype":"venue"
},
  "geometry": {"coordinates":[-66.0630111694,45.2742156982],"type":"Point"}
}