{
  "type": "Feature",
  "properties": {
    "addr:full":"1802 20th Ave Coaldale AB T1M 1M2",
    "addr:housenumber":"1802",
    "addr:postcode":"t1m 1m2",
    "addr:street":"20Th Ave",
    "iso:country":"CA",
    "sg:address":"1802 20th Ave",
    "sg:city":"Coaldale",
    "sg:classifiers":[
        {
            "category":"Manufacturing",
            "subcategory":"Printing",
            "type":"Manufacturing & Wholesale Goods"
        }
    ],
    "sg:phone":"+1 403 345 3081",
    "sg:postcode":"T1M 1M2",
    "sg:province":"AB",
    "sg:tags":[
        "newspaper"
    ],
    "wof:name":"Sunny South News",
    "wof:placetype":"venue"
},
  "geometry": {"coordinates":[-112.619796753,49.7277069092],"type":"Point"}
}