{
  "type": "Feature",
  "properties": {
    "iso:country":"CA",
    "sg:address":"120 Mcintosh Rd",
    "sg:city":"Kelowna",
    "sg:classifiers":[
        {
            "category":"Real Estate",
            "subcategory":"Real Estate Operator",
            "type":"Services"
        }
    ],
    "sg:phone":"+1 250 765 3832",
    "sg:postcode":"V1X 7E8",
    "sg:province":"BC",
    "sg:tags":[
        "apartment"
    ],
    "wof:name":"Centennial House",
    "wof:placetype":"venue"
},
  "geometry": {"coordinates":[-119.387672424,49.8922805786],"type":"Point"}
}