{
  "type": "Feature",
  "properties": {
    "addr:full":"Montreal QC H2L 3Y8",
    "addr:postcode":"h2l 3y8",
    "iso:country":"CA",
    "sg:city":"Montreal",
    "sg:classifiers":[
        {
            "category":"Manufacturing",
            "subcategory":"Printing",
            "type":"Manufacturing & Wholesale Goods"
        }
    ],
    "sg:phone":"+1 514 845 2975",
    "sg:postcode":"H2L 3Y8",
    "sg:province":"QC",
    "sg:tags":[
        "publisher"
    ],
    "wof:name":"Rogy Comics",
    "wof:placetype":"venue"
},
  "geometry": {"coordinates":[-73.55744934080001,45.5150222778],"type":"Point"}
}