{
  "type": "Feature",
  "properties": {
    "addr:full":"923 Queen St Kincardine ON N2Z 2Y2",
    "addr:housenumber":"923",
    "addr:postcode":"n2z 2y2",
    "addr:street":"Queen St",
    "iso:country":"CA",
    "sg:address":"923 Queen St",
    "sg:city":"Kincardine",
    "sg:classifiers":[
        {
            "category":"Restaurant",
            "type":"Food & Drink"
        }
    ],
    "sg:phone":"+1 519 396 3100",
    "sg:postcode":"N2Z 2Y2",
    "sg:province":"ON",
    "sg:tags":[
        "pizza"
    ],
    "wof:name":"New Orleans Pizza",
    "wof:placetype":"venue"
},
  "geometry": {"coordinates":[-81.63278200000001,44.179989],"type":"Point"}
}