{
  "type": "Feature",
  "properties": {
    "addr:full":"115 2 Ave SE Calgary AB T2G 0B2",
    "addr:housenumber":"115",
    "addr:postcode":"t2g 0b2",
    "addr:street":"2 Ave Se",
    "iso:country":"CA",
    "sg:address":"115 2 Ave SE",
    "sg:city":"Calgary",
    "sg:classifiers":[
        {
            "category":"Personal",
            "subcategory":"Beauty Salon",
            "type":"Services"
        }
    ],
    "sg:phone":"+1 403 261 2728",
    "sg:postcode":"T2G 0B2",
    "sg:province":"AB",
    "wof:name":"Elegant Hairstyling",
    "wof:placetype":"venue"
},
  "geometry": {"coordinates":[-114.062225,51.051033],"type":"Point"}
}