{
  "type": "Feature",
  "properties": {
    "addr:full":"145 Prospect Ave Thunder Bay ON P7A 5L5",
    "addr:housenumber":"145",
    "addr:postcode":"p7a 5l5",
    "addr:street":"Prospect Ave",
    "iso:country":"CA",
    "sg:address":"145 Prospect Ave",
    "sg:city":"Thunder Bay",
    "sg:classifiers":[
        {
            "category":"Wholesale",
            "subcategory":"Jewelry",
            "type":"Manufacturing & Wholesale Goods"
        }
    ],
    "sg:phone":"+1 807 344 7732",
    "sg:postcode":"P7A 5L5",
    "sg:province":"ON",
    "sg:tags":[
        "beads",
        "craft",
        "supply"
    ],
    "wof:name":"Unique Family Crafts",
    "wof:placetype":"venue"
},
  "geometry": {"coordinates":[-89.22744,48.442387],"type":"Point"}
}