{
  "type": "Feature",
  "properties": {
    "addr:full":"Ear Falls ON P0V 1T0",
    "addr:postcode":"p0v 1t0",
    "iso:country":"CA",
    "sg:city":"Ear Falls",
    "sg:classifiers":[
        {
            "category":"Travel",
            "subcategory":"Hotels & Motels",
            "type":"Entertainment"
        }
    ],
    "sg:phone":"+1 807 222 3131",
    "sg:postcode":"P0V 1T0",
    "sg:province":"ON",
    "sg:tags":[
        "resort"
    ],
    "wof:name":"Timberlane Lodge",
    "wof:placetype":"venue"
},
  "geometry": {"coordinates":[-93.225403,50.644215],"type":"Point"}
}