{
  "type": "Feature",
  "properties": {
    "iso:country":"CA",
    "sg:city":"Abbotsford",
    "sg:classifiers":[
        {
            "category":"Health Services",
            "subcategory":"Doctor",
            "type":"Services"
        }
    ],
    "sg:phone":"+1 604 854 3236",
    "sg:postcode":"V2S 3N5",
    "sg:province":"BC",
    "sg:tags":[
        "dentist"
    ],
    "wof:name":"Peter Dueckman Inc",
    "wof:placetype":"venue"
},
  "geometry": {"coordinates":[-122.293464661,49.0391235352],"type":"Point"}
}