{
  "type": "Feature",
  "properties": {
    "addr:full":"Chilliwack BC V2P 4N8",
    "addr:postcode":"v2p 4n8",
    "iso:country":"CA",
    "sg:city":"Chilliwack",
    "sg:classifiers":[
        {
            "category":"Retail",
            "subcategory":"Veterinary Services",
            "type":"Services"
        }
    ],
    "sg:phone":"+1 604 795 5721",
    "sg:postcode":"V2P 4N8",
    "sg:province":"BC",
    "sg:tags":[
        "veterinarian"
    ],
    "wof:name":"Cheam View Veterinary Hospital",
    "wof:placetype":"venue"
},
  "geometry": {"coordinates":[-121.95159099999999,49.154076],"type":"Point"}
}