{
  "type": "Feature",
  "properties": {
    "addr:full":"3830 Boul DE LA Cote-Vertu Saint-Laurent QC H4R 1P8",
    "addr:housenumber":"3830",
    "addr:postcode":"h4r 1p8",
    "addr:street":"Boul De La Cote-Vertu",
    "iso:country":"CA",
    "sg:address":"3830 Boul DE LA Cote-Vertu",
    "sg:city":"Saint-Laurent",
    "sg:classifiers":[
        {
            "category":"Shopping",
            "subcategory":"Shoes",
            "type":"Retail Goods"
        }
    ],
    "sg:phone":"+1 514 332 7263",
    "sg:postcode":"H4R 1P8",
    "sg:province":"QC",
    "sg:tags":[
        "clothing",
        "furnishing"
    ],
    "wof:name":"Moores Vetements Pour Hommes",
    "wof:placetype":"venue"
},
  "geometry": {"coordinates":[-73.7095718384,45.4925765991],"type":"Point"}
}