{
  "type": "Feature",
  "properties": {
    "addr:full":"3971 Hwy 7A Nestleton Station ON L0B 1L0",
    "addr:housenumber":"3971",
    "addr:postcode":"l0b 1l0",
    "addr:street":"Hwy 7A",
    "iso:country":"CA",
    "sg:address":"3971 Hwy 7A",
    "sg:city":"Nestleton Station",
    "sg:classifiers":[
        {
            "category":"Recreation",
            "type":"Entertainment"
        }
    ],
    "sg:phone":"+1 905 986 5032",
    "sg:postcode":"L0B 1L0",
    "sg:province":"ON",
    "sg:tags":[
        "hall",
        "auditorium"
    ],
    "wof:name":"Nestleton Community Ctr",
    "wof:placetype":"venue"
},
  "geometry": {"coordinates":[-78.796791,44.139538],"type":"Point"}
}