{
  "type": "Feature",
  "properties": {
    "addr:full":"17867 12 Ave Surrey BC V3S 9R9",
    "addr:housenumber":"17867",
    "addr:postcode":"v3s 9r9",
    "addr:street":"12 Ave",
    "iso:country":"CA",
    "sg:address":"17867 12 Ave",
    "sg:city":"Surrey",
    "sg:classifiers":[
        {
            "category":"Building & Trades",
            "subcategory":"Construction",
            "type":"Services"
        }
    ],
    "sg:phone":"+1 604 535 0765",
    "sg:postcode":"V3S 9R9",
    "sg:province":"BC",
    "sg:tags":[
        "excavating",
        "contractor"
    ],
    "wof:name":"Hartmann Excavating",
    "wof:placetype":"venue"
},
  "geometry": {"coordinates":[-122.726326,49.024021],"type":"Point"}
}