{
  "type": "Feature",
  "properties": {
    "iso:country":"CA",
    "sg:address":"1502 Centre St NE",
    "sg:city":"Calgary",
    "sg:classifiers":[
        {
            "category":"Restaurant",
            "type":"Food & Drink"
        }
    ],
    "sg:phone":"+1 403 276 8363",
    "sg:postcode":"T2E 2R9",
    "sg:province":"AB",
    "wof:name":"Santorini Greek Taverna",
    "wof:placetype":"venue"
},
  "geometry": {"coordinates":[-114.060951233,51.0653533936],"type":"Point"}
}