{
  "type": "Feature",
  "properties": {
    "addr:full":"7071 Airport Rd # 41 Mississauga ON L4T 4J3",
    "addr:housenumber":"7071",
    "addr:postcode":"l4t 4j3",
    "addr:street":"Airport Rd # 41",
    "iso:country":"CA",
    "sg:address":"7071 Airport Rd # 41",
    "sg:city":"Mississauga",
    "sg:classifiers":[
        {
            "category":"Professional",
            "subcategory":"Lawyer & Legal Services",
            "type":"Services"
        }
    ],
    "sg:phone":"+1 905 612 8951",
    "sg:postcode":"L4T 4J3",
    "sg:province":"ON",
    "sg:tags":[
        "attorney"
    ],
    "wof:name":"Karan, Singh",
    "wof:placetype":"venue"
},
  "geometry": {"coordinates":[-79.64324951170001,43.7044258118],"type":"Point"}
}