{
  "type": "Feature",
  "properties": {
    "iso:country":"CA",
    "sg:address":"420 Laidlaw Blvd",
    "sg:city":"Winnipeg",
    "sg:classifiers":[
        {
            "category":"Real Estate",
            "subcategory":"Architect",
            "type":"Services"
        }
    ],
    "sg:phone":"+1 204 888 9078",
    "sg:postcode":"R3P 0K7",
    "sg:province":"MB",
    "wof:name":"Schevelik, L F",
    "wof:placetype":"venue"
},
  "geometry": {"coordinates":[-97.2266159058,49.8638687134],"type":"Point"}
}