{
  "type": "Feature",
  "properties": {
    "addr:full":"74 Firwood Ave Courtice ON L1E 2B2",
    "addr:housenumber":"74",
    "addr:postcode":"l1e 2b2",
    "addr:street":"Firwood Ave",
    "iso:country":"CA",
    "sg:address":"74 Firwood Ave",
    "sg:city":"Courtice",
    "sg:classifiers":[
        {
            "category":"Professional",
            "subcategory":"Advertising",
            "type":"Services"
        }
    ],
    "sg:phone":"+1 905 434 1331",
    "sg:postcode":"L1E 2B2",
    "sg:province":"ON",
    "sg:tags":[
        "mail"
    ],
    "wof:name":"Val-Park of East Durham",
    "wof:placetype":"venue"
},
  "geometry": {"coordinates":[-78.7966842651,43.9183731079],"type":"Point"}
}