{
  "type": "Feature",
  "properties": {
    "addr:full":"630 1E Rue O Barraute QC J0Y 1A0",
    "addr:housenumber":"630",
    "addr:postcode":"j0y 1a0",
    "addr:street":"1E Rue O",
    "iso:country":"CA",
    "sg:address":"630 1E Rue O",
    "sg:city":"Barraute",
    "sg:classifiers":[
        {
            "category":"Organizations",
            "subcategory":"Religious Organization",
            "type":"Services"
        }
    ],
    "sg:phone":"+1 819 734 6405",
    "sg:postcode":"J0Y 1A0",
    "sg:province":"QC",
    "sg:tags":[
        "church"
    ],
    "wof:name":"Presbyteres DE Barraute",
    "wof:placetype":"venue"
},
  "geometry": {"coordinates":[-77.63720703120001,48.4402542114],"type":"Point"}
}