{
  "type": "Feature",
  "properties": {
    "addr:full":"Saint-Polycarpe QC J0P 1X0",
    "addr:postcode":"j0p 1x0",
    "iso:country":"CA",
    "sg:city":"Saint-Polycarpe",
    "sg:classifiers":[
        {
            "category":"Personal",
            "subcategory":"Beauty Salon",
            "type":"Services"
        }
    ],
    "sg:phone":"+1 450 265 3011",
    "sg:postcode":"J0P 1X0",
    "sg:province":"QC",
    "wof:name":"Salon Carolle Pour Elle Et Lui",
    "wof:placetype":"venue"
},
  "geometry": {"coordinates":[-74.31395000000001,45.29599],"type":"Point"}
}