{
  "type": "Feature",
  "properties": {
    "iso:country":"CA",
    "sg:city":"Saint-Constant",
    "sg:classifiers":[
        {
            "category":"Food & Beverages",
            "subcategory":"Groceries & Convenience Stores",
            "type":"Retail Goods"
        }
    ],
    "sg:phone":"+1 450 638 6127",
    "sg:postcode":"J5A 2J6",
    "sg:province":"QC",
    "wof:name":"Depanneur Ste Catherine",
    "wof:placetype":"venue"
},
  "geometry": {"coordinates":[-73.5961074829,45.3865890503],"type":"Point"}
}