{
  "type": "Feature",
  "properties": {
    "addr:full":"5202 Ch Saint-Anicet LA Baie QC G7B 3N8",
    "addr:postcode":"5202;g7b 3n8",
    "addr:street":"Ch Saint-Anicet",
    "iso:country":"CA",
    "sg:address":"5202 Ch Saint-Anicet",
    "sg:city":"LA Baie",
    "sg:classifiers":[
        {
            "category":"Wholesale",
            "subcategory":"Construction Materials",
            "type":"Manufacturing & Wholesale Goods"
        }
    ],
    "sg:phone":"+1 418 677 2646",
    "sg:postcode":"G7B 3N8",
    "sg:province":"QC",
    "sg:tags":[
        "granite"
    ],
    "wof:name":"Granicor Inc",
    "wof:placetype":"venue"
},
  "geometry": {"coordinates":[-70.9520950317,48.3270339966],"type":"Point"}
}