{
  "type": "Feature",
  "properties": {
    "addr:full":"7589 Rue Saint-Denis Montreal QC H2R 2E7",
    "addr:housenumber":"7589",
    "addr:postcode":"h2r 2e7",
    "addr:street":"Rue Saint-Denis",
    "iso:country":"CA",
    "sg:address":"7589 Rue Saint-Denis",
    "sg:city":"Montreal",
    "sg:classifiers":[
        {
            "category":"Health Services",
            "subcategory":"Doctor",
            "type":"Services"
        }
    ],
    "sg:phone":"+1 514 273 6111",
    "sg:postcode":"H2R 2E7",
    "sg:province":"QC",
    "sg:tags":[
        "physician",
        "clinic",
        "surgeon"
    ],
    "wof:name":"Clinique Jean Gilbert",
    "wof:placetype":"venue"
},
  "geometry": {"coordinates":[-73.621421814,45.5405006409],"type":"Point"}
}