{
  "type": "Feature",
  "properties": {
    "addr:full":"Cleardale AB T0H 3Y0",
    "addr:postcode":"t0h 3y0",
    "iso:country":"CA",
    "sg:city":"Cleardale",
    "sg:classifiers":[
        {
            "category":"Education",
            "subcategory":"School",
            "type":"Public Place"
        }
    ],
    "sg:phone":"+1 780 685 2340",
    "sg:postcode":"T0H 3Y0",
    "sg:province":"AB",
    "wof:name":"Menno-Simons School",
    "wof:placetype":"venue"
},
  "geometry": {"coordinates":[-119.510002136,56.352230072],"type":"Point"}
}