{
  "type": "Feature",
  "properties": {
    "addr:full":"9 Canso Rd Etobicoke ON M9W 4L9",
    "addr:housenumber":"9",
    "addr:postcode":"m9w 4l9",
    "addr:street":"Canso Rd",
    "iso:country":"CA",
    "sg:address":"9 Canso Rd",
    "sg:city":"Etobicoke",
    "sg:classifiers":[
        {
            "category":"Wholesale",
            "subcategory":"Electrical",
            "type":"Manufacturing & Wholesale Goods"
        }
    ],
    "sg:phone":"+1 416 241 4647",
    "sg:postcode":"M9W 4L9",
    "sg:province":"ON",
    "sg:tags":[
        "testing",
        "apparatus"
    ],
    "wof:name":"R B Atlas Inc",
    "wof:placetype":"venue"
},
  "geometry": {"coordinates":[-79.567078,43.698177],"type":"Point"}
}