{
  "type": "Feature",
  "properties": {
    "iso:country":"CA",
    "sg:city":"Toronto",
    "sg:classifiers":[
        {
            "category":"Professional",
            "subcategory":"Art Services",
            "type":"Services"
        }
    ],
    "sg:phone":"+1 416 463 5180",
    "sg:postcode":"M4M 3L4",
    "sg:province":"ON",
    "sg:tags":[
        "photographer"
    ],
    "wof:name":"Paul J Rozario Photography",
    "wof:placetype":"venue"
},
  "geometry": {"coordinates":[-79.3287124634,43.6594047546],"type":"Point"}
}