{
  "type": "Feature",
  "properties": {
    "addr:full":"1120 Simcoe St N Oshawa ON L1G 4W6",
    "addr:housenumber":"1120",
    "addr:postcode":"l1g 4w6",
    "addr:street":"Simcoe St N",
    "iso:country":"CA",
    "sg:address":"1120 Simcoe St N",
    "sg:city":"Oshawa",
    "sg:classifiers":[
        {
            "category":"Manufacturing",
            "subcategory":"Metals",
            "type":"Manufacturing & Wholesale Goods"
        }
    ],
    "sg:phone":"+1 905 571 2887",
    "sg:postcode":"L1G 4W6",
    "sg:province":"ON",
    "sg:tags":[
        "downspouts",
        "gutter"
    ],
    "wof:name":"Bttr Window & Door Products",
    "wof:placetype":"venue"
},
  "geometry": {"coordinates":[-78.87663999999999,43.927155],"type":"Point"}
}