{
  "type": "Feature",
  "properties": {
    "addr:full":"310 2nd Ave E Canora SK S0A 0L0",
    "addr:housenumber":"310",
    "addr:postcode":"s0a 0l0",
    "addr:street":"2Nd Ave E Canora",
    "iso:country":"CA",
    "sg:address":"310 2nd Ave E",
    "sg:city":"Canora",
    "sg:classifiers":[
        {
            "category":"Food & Beverages",
            "subcategory":"Groceries & Convenience Stores",
            "type":"Retail Goods"
        }
    ],
    "sg:phone":"+1 306 563 5161",
    "sg:postcode":"S0A 0L0",
    "sg:province":"SK",
    "wof:name":"Northstar Esso Convenience Str",
    "wof:placetype":"venue"
},
  "geometry": {"coordinates":[-102.432434082,51.6354560852],"type":"Point"}
}