{
  "type": "Feature",
  "properties": {
    "iso:country":"CA",
    "sg:address":"226 Harwood Ave S",
    "sg:city":"Ajax",
    "sg:classifiers":[
        {
            "category":"Health Services",
            "subcategory":"Chiropractor",
            "type":"Services"
        }
    ],
    "sg:phone":"+1 905 426 9116",
    "sg:postcode":"L1S 2H6",
    "sg:province":"ON",
    "wof:name":"Family Chiropractic & Homeo",
    "wof:placetype":"venue"
},
  "geometry": {"coordinates":[-79.020622,43.848675],"type":"Point"}
}