{
  "type": "Feature",
  "properties": {
    "addr:full":"17 Main St Corner Brook NL A2H 1C2",
    "addr:housenumber":"17",
    "addr:postcode":"a2h 1c2",
    "addr:street":"Main St",
    "iso:country":"CA",
    "sg:address":"17 Main St",
    "sg:city":"Corner Brook",
    "sg:classifiers":[
        {
            "category":"Insurance",
            "subcategory":"Insurance Agent",
            "type":"Services"
        }
    ],
    "sg:phone":"+1 709 634 5117",
    "sg:postcode":"A2H 1C2",
    "sg:province":"NL",
    "wof:name":"Johnson Inc",
    "wof:placetype":"venue"
},
  "geometry": {"coordinates":[-57.944283,48.954273],"type":"Point"}
}