{
  "type": "Feature",
  "properties": {
    "addr:full":"1950 Vermillion Lake Rd Chelmsford ON P0M 1L0",
    "addr:housenumber":"1950",
    "addr:postcode":"p0m 1l0",
    "addr:street":"Vermillion Lake Rd",
    "iso:country":"CA",
    "sg:address":"1950 Vermillion Lake Rd",
    "sg:city":"Chelmsford",
    "sg:classifiers":[
        {
            "category":"Travel",
            "subcategory":"Campground",
            "type":"Entertainment"
        }
    ],
    "sg:phone":"+1 705 855 9980",
    "sg:postcode":"P0M 1L0",
    "sg:province":"ON",
    "wof:name":"Vermillion Lake Park",
    "wof:placetype":"venue"
},
  "geometry": {"coordinates":[-81.197357,46.568874],"type":"Point"}
}