{
  "type": "Feature",
  "properties": {
    "addr:full":"582 Rue Principale Saint-Sebastien-DE-Frontenac QC G0Y 1M0",
    "addr:housenumber":"582",
    "addr:postcode":"g0y 1m0",
    "addr:street":"Rue Principale",
    "iso:country":"CA",
    "sg:address":"582 Rue Principale",
    "sg:city":"Saint-Sebastien-DE-Frontenac",
    "sg:classifiers":[
        {
            "category":"Health Services",
            "subcategory":"Doctor",
            "type":"Services"
        }
    ],
    "sg:phone":"+1 819 652 2402",
    "sg:postcode":"G0Y 1M0",
    "sg:province":"QC",
    "sg:tags":[
        "physician",
        "surgeon"
    ],
    "wof:name":"Laflamme, Paule MD",
    "wof:placetype":"venue"
},
  "geometry": {"coordinates":[-70.97039794920001,45.7823638916],"type":"Point"}
}