{
  "type": "Feature",
  "properties": {
    "addr:full":"253210 Bearspaw Rd Calgary AB T3L 2S5",
    "addr:housenumber":"253210",
    "addr:postcode":"t3l 2s5",
    "addr:street":"Bearspaw Rd",
    "iso:country":"CA",
    "sg:address":"253210 Bearspaw Rd",
    "sg:city":"Calgary",
    "sg:classifiers":[
        {
            "category":"Education",
            "subcategory":"School",
            "type":"Public Place"
        }
    ],
    "sg:phone":"+1 403 239 9607",
    "sg:postcode":"T3L 2S5",
    "sg:province":"AB",
    "wof:name":"Bearspaw School",
    "wof:placetype":"venue"
},
  "geometry": {"coordinates":[-114.28047180199999,51.1603813171],"type":"Point"}
}