{
  "type": "Feature",
  "properties": {
    "addr:full":"North York ON M3J 2E5",
    "addr:postcode":"m3j 2e5",
    "iso:country":"CA",
    "sg:city":"North York",
    "sg:classifiers":[
        {
            "category":"Wholesale",
            "subcategory":"Jewelry",
            "type":"Manufacturing & Wholesale Goods"
        }
    ],
    "sg:phone":"+1 416 665 8600",
    "sg:postcode":"M3J 2E5",
    "sg:province":"ON",
    "sg:tags":[
        "jeweler",
        "supply"
    ],
    "wof:name":"Eisinger Canada Ltd",
    "wof:placetype":"venue"
},
  "geometry": {"coordinates":[-79.4723739624,43.7674980164],"type":"Point"}
}