{
  "type": "Feature",
  "properties": {
    "addr:full":"1775 Shannon Lake Rd Westbank BC V4T 2N7",
    "addr:housenumber":"1775",
    "addr:postcode":"v4t 2n7",
    "addr:street":"Shannon Lake Rd",
    "iso:country":"CA",
    "sg:address":"1775 Shannon Lake Rd",
    "sg:city":"Westbank",
    "sg:classifiers":[
        {
            "category":"Government",
            "subcategory":"Office",
            "type":"Public Place"
        }
    ],
    "sg:phone":"+1 250 862 4040",
    "sg:postcode":"V4T 2N7",
    "sg:province":"BC",
    "wof:name":"Brookhaven Care Ctr",
    "wof:placetype":"venue"
},
  "geometry": {"coordinates":[-119.59066799999999,49.866817],"type":"Point"}
}