{
  "type": "Feature",
  "properties": {
    "addr:full":"116 Railway Ave W Drumheller AB T0J 0Y0",
    "addr:housenumber":"116",
    "addr:postcode":"t0j 0y0",
    "addr:street":"Railway Ave W",
    "iso:country":"CA",
    "sg:address":"116 Railway Ave W",
    "sg:city":"Drumheller",
    "sg:classifiers":[
        {
            "category":"Autos & Motor Vehicles",
            "subcategory":"Auto Supplies",
            "type":"Retail Goods"
        }
    ],
    "sg:phone":"+1 403 823 2650",
    "sg:postcode":"T0J 0Y0",
    "sg:province":"AB",
    "sg:tags":[
        "tire"
    ],
    "wof:name":"A & D Harper Tire 1979 Ltd",
    "wof:placetype":"venue"
},
  "geometry": {"coordinates":[-112.70948799999999,51.462822],"type":"Point"}
}