{
  "type": "Feature",
  "properties": {
    "iso:country":"CA",
    "sg:address":"432 Niagara St",
    "sg:city":"St Catharines",
    "sg:classifiers":[
        {
            "category":"Insurance",
            "subcategory":"Insurance Agent",
            "type":"Services"
        }
    ],
    "sg:phone":"+1 905 935 4142",
    "sg:postcode":"L2M 4W3",
    "sg:province":"ON",
    "wof:name":"Rachel Delaney Insurance",
    "wof:placetype":"venue"
},
  "geometry": {"coordinates":[-79.2256317139,43.1891937256],"type":"Point"}
}