{
  "type": "Feature",
  "properties": {
    "addr:full":"87 First St Orangeville ON L9W 2E8",
    "addr:housenumber":"87",
    "addr:postcode":"l9w 2e8",
    "addr:street":"First St",
    "iso:country":"CA",
    "sg:address":"87 First St",
    "sg:city":"Orangeville",
    "sg:classifiers":[
        {
            "category":"Retail",
            "subcategory":"Auto Repair",
            "type":"Services"
        }
    ],
    "sg:phone":"+1 519 942 4990",
    "sg:postcode":"L9W 2E8",
    "sg:province":"ON",
    "sg:tags":[
        "repairing",
        "automobile"
    ],
    "wof:name":"North Peel Tire & Auto",
    "wof:placetype":"venue"
},
  "geometry": {"coordinates":[-80.09936500000001,43.92767],"type":"Point"}
}