{
  "type": "Feature",
  "properties": {
    "iso:country":"CA",
    "sg:address":"87 First St",
    "sg:city":"Orangeville",
    "sg:classifiers":[
        {
            "category":"Retail",
            "subcategory":"Auto Repair",
            "type":"Services"
        }
    ],
    "sg:phone":"+1 519 942 4990",
    "sg:postcode":"L9W 2E8",
    "sg:province":"ON",
    "sg:tags":[
        "repairing",
        "automobile"
    ],
    "wof:name":"North Peel Tire & Auto",
    "wof:placetype":"venue"
},
  "geometry": {"coordinates":[-80.099365,43.92767],"type":"Point"}
}