{
  "type": "Feature",
  "properties": {
    "addr:full":"53 Main St N Brampton ON L6X 1M8",
    "addr:housenumber":"53",
    "addr:postcode":"l6x 1m8",
    "addr:street":"Main St N",
    "iso:country":"CA",
    "sg:address":"53 Main St N",
    "sg:city":"Brampton",
    "sg:classifiers":[
        {
            "category":"Retail",
            "subcategory":"Portrait Studio",
            "type":"Services"
        }
    ],
    "sg:phone":"+1 905 453 5550",
    "sg:postcode":"L6X 1M8",
    "sg:province":"ON",
    "sg:tags":[
        "photographer"
    ],
    "wof:name":"Custodio Photo Studio",
    "wof:placetype":"venue"
},
  "geometry": {"coordinates":[-79.7610778809,43.6865348816],"type":"Point"}
}