{
  "type": "Feature",
  "properties": {
    "addr:full":"Dawson Creek BC V1G 2B7",
    "addr:postcode":"v1g 2b7",
    "iso:country":"CA",
    "sg:city":"Dawson Creek",
    "sg:classifiers":[
        {
            "category":"Travel",
            "subcategory":"Travel Agent",
            "type":"Entertainment"
        }
    ],
    "sg:phone":"+1 250 782 2004",
    "sg:postcode":"V1G 2B7",
    "sg:province":"BC",
    "sg:tags":[
        "agency",
        "bureau"
    ],
    "wof:name":"Travel Professional Intl",
    "wof:placetype":"venue"
},
  "geometry": {"coordinates":[-120.22644805900001,55.758014679],"type":"Point"}
}