{
  "type": "Feature",
  "properties": {
    "addr:full":"3109 Dougall Ave Windsor ON N9E 1S5",
    "addr:housenumber":"3109",
    "addr:postcode":"n9e 1s5",
    "addr:street":"Dougall Ave",
    "iso:country":"CA",
    "sg:address":"3109 Dougall Ave",
    "sg:city":"Windsor",
    "sg:classifiers":[
        {
            "category":"Health Services",
            "subcategory":"Doctor",
            "type":"Services"
        }
    ],
    "sg:phone":"+1 519 969 7000",
    "sg:postcode":"N9E 1S5",
    "sg:province":"ON",
    "sg:tags":[
        "dentist"
    ],
    "wof:name":"Ghilzon, James E DDS",
    "wof:placetype":"venue"
},
  "geometry": {"coordinates":[-83.01225280760001,42.2700843811],"type":"Point"}
}