{
  "type": "Feature",
  "properties": {
    "addr:full":"1480 Dupont St Toronto ON M6P 3S1",
    "addr:housenumber":"1480",
    "addr:postcode":"m6p 3s1",
    "addr:street":"Dupont St",
    "iso:country":"CA",
    "sg:address":"1480 Dupont St",
    "sg:city":"Toronto",
    "sg:classifiers":[
        {
            "category":"Building & Trades",
            "subcategory":"Construction",
            "type":"Services"
        }
    ],
    "sg:phone":"+1 416 533 5252",
    "sg:postcode":"M6P 3S1",
    "sg:province":"ON",
    "sg:tags":[
        "general",
        "contractor"
    ],
    "wof:name":"Alpha Store Fixtures",
    "wof:placetype":"venue"
},
  "geometry": {"coordinates":[-79.450203,43.666058],"type":"Point"}
}