{
  "type": "Feature",
  "properties": {
    "addr:full":"329 132 Rte E Amqui QC G5J 2B5",
    "addr:housenumber":"132",
    "addr:postcode":"g5j 2b5",
    "addr:street":"Rte E",
    "iso:country":"CA",
    "sg:address":"329 132 Rte E",
    "sg:city":"Amqui",
    "sg:classifiers":[
        {
            "category":"Manufacturing",
            "subcategory":"Metals",
            "type":"Manufacturing & Wholesale Goods"
        }
    ],
    "sg:phone":"+1 418 629 4230",
    "sg:postcode":"G5J 2B5",
    "sg:province":"QC",
    "sg:tags":[
        "shelter",
        "garage",
        "canopy",
        "temporary",
        "awning"
    ],
    "wof:name":"Toiles DE LA Vallee Inc",
    "wof:placetype":"venue"
},
  "geometry": {"coordinates":[-67.425873,48.46468],"type":"Point"}
}