{
  "type": "Feature",
  "properties": {
    "iso:country":"CA",
    "sg:address":"28 Franklin St",
    "sg:city":"Markham",
    "sg:classifiers":[
        {
            "category":"Organizations",
            "subcategory":"Professional Association",
            "type":"Services"
        }
    ],
    "sg:phone":"+1 905 294 2078",
    "sg:postcode":"L3P 2S8",
    "sg:province":"ON",
    "sg:tags":[
        "club"
    ],
    "wof:name":"Markham Lawn Bowling Club",
    "wof:placetype":"venue"
},
  "geometry": {"coordinates":[-79.2590637207,43.8792686462],"type":"Point"}
}