{
  "type": "Feature",
  "properties": {
    "addr:full":"Prince George BC V2L 3G3",
    "addr:postcode":"v2l 3g3",
    "iso:country":"CA",
    "sg:city":"Prince George",
    "sg:classifiers":[
        {
            "category":"Professional",
            "subcategory":"Engineering",
            "type":"Services"
        }
    ],
    "sg:phone":"+1 250 562 9345",
    "sg:postcode":"V2L 3G3",
    "sg:province":"BC",
    "sg:tags":[
        "engineer"
    ],
    "wof:name":"Access Engineering Consultants",
    "wof:placetype":"venue"
},
  "geometry": {"coordinates":[-122.749824524,53.9179534912],"type":"Point"}
}