{
  "type": "Feature",
  "properties": {
    "addr:full":"2119 Ogilvie St S Prince George BC V2N 1X2",
    "addr:housenumber":"2119",
    "addr:postcode":"v2n 1x2",
    "addr:street":"Ogilvie St S",
    "iso:country":"CA",
    "sg:address":"2119 Ogilvie St S",
    "sg:city":"Prince George",
    "sg:classifiers":[
        {
            "category":"Freight",
            "type":"Transportation"
        }
    ],
    "sg:phone":"+1 250 562 0153",
    "sg:postcode":"V2N 1X2",
    "sg:province":"BC",
    "sg:tags":[
        "courier",
        "trucking"
    ],
    "wof:name":"P G Lite Express Ltd",
    "wof:placetype":"venue"
},
  "geometry": {"coordinates":[-122.78945899999999,53.904598],"type":"Point"}
}