{
  "type": "Feature",
  "properties": {
    "iso:country":"CA",
    "sg:city":"Plamondon",
    "sg:classifiers":[
        {
            "category":"Travel",
            "subcategory":"Campground",
            "type":"Entertainment"
        }
    ],
    "sg:phone":"+1 780 798 2254",
    "sg:postcode":"T0A 2T0",
    "sg:province":"AB",
    "wof:name":"Plamondon White Sands Resort",
    "wof:placetype":"venue"
},
  "geometry": {"coordinates":[-112.344474792,54.8497810364],"type":"Point"}
}