{
  "type": "Feature",
  "properties": {
    "addr:full":"44 Boul Brien Repentigny QC J6A 4S2",
    "addr:housenumber":"44",
    "addr:postcode":"j6a 4s2",
    "addr:street":"Boul Brien",
    "iso:country":"CA",
    "sg:address":"44 Boul Brien",
    "sg:city":"Repentigny",
    "sg:classifiers":[
        {
            "category":"Freight",
            "type":"Transportation"
        }
    ],
    "sg:phone":"+1 450 585 4888",
    "sg:postcode":"J6A 4S2",
    "sg:province":"QC",
    "sg:tags":[
        "broker",
        "trucking"
    ],
    "wof:name":"Massif Transport Inc",
    "wof:placetype":"venue"
},
  "geometry": {"coordinates":[-73.44838,45.741283],"type":"Point"}
}