{
  "type": "Feature",
  "properties": {
    "addr:full":"2320 Ch Lucerne Mont-Royal QC H3R 2J8",
    "addr:postcode":"2320;h3r 2j8",
    "addr:street":"Ch Lucerne",
    "iso:country":"CA",
    "sg:address":"2320 Ch Lucerne",
    "sg:city":"Mont-Royal",
    "sg:classifiers":[
        {
            "category":"Shopping",
            "subcategory":"Florist",
            "type":"Retail Goods"
        }
    ],
    "sg:phone":"+1 514 735 2444",
    "sg:postcode":"H3R 2J8",
    "sg:province":"QC",
    "wof:name":"Cornfield Florist",
    "wof:placetype":"venue"
},
  "geometry": {"coordinates":[-73.6612625122,45.5072097778],"type":"Point"}
}