{
  "type": "Feature",
  "properties": {
    "addr:full":"13528 Fort Rd NW Edmonton AB T5A 1C5",
    "addr:housenumber":"13528",
    "addr:postcode":"t5a 1c5",
    "addr:street":"Fort Rd Nw",
    "iso:country":"CA",
    "sg:address":"13528 Fort Rd NW",
    "sg:city":"Edmonton",
    "sg:classifiers":[
        {
            "category":"Autos & Motor Vehicles",
            "subcategory":"Auto Supplies",
            "type":"Retail Goods"
        }
    ],
    "sg:phone":"+1 780 406 7030",
    "sg:postcode":"T5A 1C5",
    "sg:province":"AB",
    "sg:tags":[
        "automobile",
        "parts",
        "accessory"
    ],
    "wof:name":"J B's Power Ctr Ltd",
    "wof:placetype":"venue"
},
  "geometry": {"coordinates":[-113.42450700000001,53.597244],"type":"Point"}
}