{
  "type": "Feature",
  "properties": {
    "addr:full":"1250 Rue Borne Quebec QC G1N 1M4",
    "addr:housenumber":"1250",
    "addr:postcode":"g1n 1m4",
    "addr:street":"Rue Borne",
    "iso:country":"CA",
    "sg:address":"1250 Rue Borne",
    "sg:city":"Quebec",
    "sg:classifiers":[
        {
            "category":"Freight",
            "type":"Transportation"
        }
    ],
    "sg:phone":"+1 418 681 6161",
    "sg:postcode":"G1N 1M4",
    "sg:province":"QC",
    "sg:tags":[
        "trucking"
    ],
    "wof:name":"Entrepot St Andre",
    "wof:placetype":"venue"
},
  "geometry": {"coordinates":[-71.260643,46.803749],"type":"Point"}
}