{
  "type": "Feature",
  "properties": {
    "iso:country":"CA",
    "sg:address":"293 Church St",
    "sg:city":"Oakville",
    "sg:classifiers":[
        {
            "category":"Professional",
            "subcategory":"Management & Consulting",
            "type":"Services"
        }
    ],
    "sg:phone":"+1 905 643 8279",
    "sg:postcode":"L6J 1N9",
    "sg:province":"ON",
    "sg:tags":[
        "consultant",
        "trademark",
        "agent"
    ],
    "wof:name":"Dekkers Office of Aletta",
    "wof:placetype":"venue"
},
  "geometry": {"coordinates":[-79.6671829224,43.4482307434],"type":"Point"}
}