{
  "type": "Feature",
  "properties": {
    "addr:full":"1555 Moraine Rd NE Calgary AB T2A 2P5",
    "addr:housenumber":"1555",
    "addr:postcode":"t2a 2p5",
    "addr:street":"Moraine Rd Ne",
    "iso:country":"CA",
    "sg:address":"1555 Moraine Rd NE",
    "sg:city":"Calgary",
    "sg:classifiers":[
        {
            "category":"Autos & Motor Vehicles",
            "subcategory":"Recreational Vehicle Sales",
            "type":"Retail Goods"
        }
    ],
    "sg:phone":"+1 403 291 2774",
    "sg:postcode":"T2A 2P5",
    "sg:province":"AB",
    "wof:name":"Westcoast Mountain Campers",
    "wof:placetype":"venue"
},
  "geometry": {"coordinates":[-113.994804,51.065193],"type":"Point"}
}