{
  "type": "Feature",
  "properties": {
    "addr:full":"939 Kingsway Ave SE Medicine Hat AB T1A 2X6",
    "addr:housenumber":"939",
    "addr:postcode":"t1a 2x6",
    "addr:street":"Kingsway Ave Se",
    "iso:country":"CA",
    "sg:address":"939 Kingsway Ave SE",
    "sg:city":"Medicine Hat",
    "sg:classifiers":[
        {
            "category":"Shopping",
            "subcategory":"Stationery & Office Supplies",
            "type":"Retail Goods"
        }
    ],
    "sg:phone":"+1 403 527 2130",
    "sg:postcode":"T1A 2X6",
    "sg:province":"AB",
    "wof:name":"Ben's Office Machines Ltd",
    "wof:placetype":"venue"
},
  "geometry": {"coordinates":[-110.668961,50.029819],"type":"Point"}
}