{
  "type": "Feature",
  "properties": {
    "addr:full":"678 Rue Kirouac Quebec QC G1N 2J2",
    "addr:housenumber":"678",
    "addr:postcode":"g1n 2j2",
    "addr:street":"Rue Kirouac",
    "iso:country":"CA",
    "sg:address":"678 Rue Kirouac",
    "sg:city":"Quebec",
    "sg:classifiers":[
        {
            "category":"Professional",
            "subcategory":"Business Services",
            "type":"Services"
        }
    ],
    "sg:phone":"+1 418 683 1533",
    "sg:postcode":"G1N 2J2",
    "sg:province":"QC",
    "sg:tags":[
        "embroidery"
    ],
    "wof:name":"Fee DE LA Broderie Enr",
    "wof:placetype":"venue"
},
  "geometry": {"coordinates":[-71.24082900000001,46.805054],"type":"Point"}
}