{
  "type": "Feature",
  "properties": {
    "addr:full":"117 Industrial Park Dr Haliburton ON K0M 1S0",
    "addr:housenumber":"117",
    "addr:postcode":"k0m 1s0",
    "addr:street":"Industrial Park Dr",
    "iso:country":"CA",
    "sg:address":"117 Industrial Park Dr",
    "sg:city":"Haliburton",
    "sg:classifiers":[
        {
            "category":"Home & Garden",
            "subcategory":"Building Materials",
            "type":"Retail Goods"
        }
    ],
    "sg:phone":"+1 705 457 9077",
    "sg:postcode":"K0M 1S0",
    "sg:province":"ON",
    "sg:tags":[
        "glass"
    ],
    "wof:name":"K Enterprises",
    "wof:placetype":"venue"
},
  "geometry": {"coordinates":[-78.540977,45.053501],"type":"Point"}
}