{
  "type": "Feature",
  "properties": {
    "iso:country":"CA",
    "sg:address":"2905 12 St NE",
    "sg:city":"Calgary",
    "sg:classifiers":[
        {
            "category":"Education",
            "subcategory":"Special Training",
            "type":"Public Place"
        }
    ],
    "sg:phone":"+1 403 250 2922",
    "sg:postcode":"T2E 7J2",
    "sg:province":"AB",
    "sg:tags":[
        "aid",
        "instruction",
        "institution",
        "first",
        "charitable"
    ],
    "wof:name":"St John Ambulance",
    "wof:placetype":"venue"
},
  "geometry": {"coordinates":[-114.025825501,51.077999115],"type":"Point"}
}