{
  "type": "Feature",
  "properties": {
    "addr:full":"1995 Merivale Rd Nepean ON K2G 1G1",
    "addr:housenumber":"1995",
    "addr:postcode":"k2g 1g1",
    "addr:street":"Merivale Rd",
    "iso:country":"CA",
    "sg:address":"1995 Merivale Rd",
    "sg:city":"Nepean",
    "sg:classifiers":[
        {
            "category":"Building & Trades",
            "subcategory":"Construction",
            "type":"Services"
        }
    ],
    "sg:phone":"+1 613 226 1525",
    "sg:postcode":"K2G 1G1",
    "sg:province":"ON",
    "sg:tags":[
        "tank"
    ],
    "wof:name":"Eastway Tank Pump & Meter Ltd",
    "wof:placetype":"venue"
},
  "geometry": {"coordinates":[-75.71868133540001,45.3257026672],"type":"Point"}
}