{
  "type": "Feature",
  "properties": {
    "addr:full":"3329 Douglas St Victoria BC V8Z 3L2",
    "addr:housenumber":"3329",
    "addr:postcode":"v8z 3l2",
    "addr:street":"Douglas St",
    "iso:country":"CA",
    "sg:address":"3329 Douglas St",
    "sg:city":"Victoria",
    "sg:classifiers":[
        {
            "category":"Autos & Motor Vehicles",
            "subcategory":"Auto Supplies",
            "type":"Retail Goods"
        }
    ],
    "sg:phone":"+1 250 475 2415",
    "sg:postcode":"V8Z 3L2",
    "sg:province":"BC",
    "sg:tags":[
        "automobile",
        "parts",
        "dealer",
        "car"
    ],
    "wof:name":"Speedway Motors Ltd",
    "wof:placetype":"venue"
},
  "geometry": {"coordinates":[-123.372329712,48.4476699829],"type":"Point"}
}