{
  "type": "Feature",
  "properties": {
    "addr:full":"564 Coronation Blvd Cambridge ON N1R 5Y3",
    "addr:housenumber":"564",
    "addr:postcode":"n1r 5y3",
    "addr:street":"Coronation Blvd",
    "iso:country":"CA",
    "sg:address":"564 Coronation Blvd",
    "sg:city":"Cambridge",
    "sg:classifiers":[
        {
            "category":"Personal",
            "type":"Services"
        }
    ],
    "sg:phone":"+1 519 622 6892",
    "sg:postcode":"N1R 5Y3",
    "sg:province":"ON",
    "sg:tags":[
        "therapist",
        "massage"
    ],
    "wof:name":"Intergrative Therapeutics",
    "wof:placetype":"venue"
},
  "geometry": {"coordinates":[-80.3213195801,43.3747215271],"type":"Point"}
}