{
  "type": "Feature",
  "properties": {
    "addr:full":"Dundas ON L9H 5E2",
    "addr:postcode":"l9h 5e2",
    "iso:country":"CA",
    "sg:city":"Dundas",
    "sg:classifiers":[
        {
            "category":"Wholesale",
            "subcategory":"Farm Supplies",
            "type":"Manufacturing & Wholesale Goods"
        }
    ],
    "sg:phone":"+1 905 628 4488",
    "sg:postcode":"L9H 5E2",
    "sg:province":"ON",
    "sg:tags":[
        "fertilizer"
    ],
    "wof:name":"County Ag Svc Inc",
    "wof:placetype":"venue"
},
  "geometry": {"coordinates":[-79.9523773193,43.2637786865],"type":"Point"}
}