{
  "type": "Feature",
  "properties": {
    "addr:full":"1921 Saskatchewan Ave Saskatoon SK S7K 1R3",
    "addr:housenumber":"1921",
    "addr:postcode":"s7k 1r3",
    "addr:street":"Saskatchewan Ave",
    "iso:country":"CA",
    "sg:address":"1921 Saskatchewan Ave",
    "sg:city":"Saskatoon",
    "sg:classifiers":[
        {
            "category":"Retail",
            "subcategory":"Auto Repair",
            "type":"Services"
        }
    ],
    "sg:phone":"+1 306 931 2884",
    "sg:postcode":"S7K 1R3",
    "sg:province":"SK",
    "sg:tags":[
        "repairing",
        "automobile"
    ],
    "wof:name":"Ruben's Auto Repair",
    "wof:placetype":"venue"
},
  "geometry": {"coordinates":[-106.669113,52.155514],"type":"Point"}
}