{
  "type": "Feature",
  "properties": {
    "iso:country":"CA",
    "sg:city":"Montreal",
    "sg:classifiers":[
        {
            "category":"Manufacturing",
            "subcategory":"Retail Goods",
            "type":"Manufacturing & Wholesale Goods"
        }
    ],
    "sg:phone":"+1 514 272 1107",
    "sg:postcode":"H3N 1V1",
    "sg:province":"QC",
    "sg:tags":[
        "buckle"
    ],
    "wof:name":"Approved Trimmings of Canada",
    "wof:placetype":"venue"
},
  "geometry": {"coordinates":[-73.619614,45.527084],"type":"Point"}
}