{
  "type": "Feature",
  "properties": {
    "addr:full":"25 Rue Principale Sainte-Francoise QC G0L 3B0",
    "addr:housenumber":"25",
    "addr:postcode":"g0l 3b0",
    "addr:street":"Rue Principale",
    "iso:country":"CA",
    "sg:address":"25 Rue Principale",
    "sg:city":"Sainte-Francoise",
    "sg:classifiers":[
        {
            "category":"Recreation",
            "type":"Entertainment"
        }
    ],
    "sg:phone":"+1 418 851 1801",
    "sg:postcode":"G0L 3B0",
    "sg:province":"QC",
    "sg:tags":[
        "center"
    ],
    "wof:name":"Comite Des Loisirs Rioux Inc",
    "wof:placetype":"venue"
},
  "geometry": {"coordinates":[-69.06326293950001,48.0938949585],"type":"Point"}
}