{
  "type": "Feature",
  "properties": {
    "iso:country":"CA",
    "sg:address":"4351 Boul Notre-Dame",
    "sg:city":"Laval",
    "sg:classifiers":[
        {
            "category":"Health Services",
            "subcategory":"Doctor",
            "type":"Services"
        }
    ],
    "sg:phone":"+1 450 681 7413",
    "sg:postcode":"H7W 1T3",
    "sg:province":"QC",
    "sg:tags":[
        "dentist"
    ],
    "wof:name":"Ornstein, Michael D DDS",
    "wof:placetype":"venue"
},
  "geometry": {"coordinates":[-73.75815582280001,45.5379104614],"type":"Point"}
}