{
  "type": "Feature",
  "properties": {
    "addr:full":"56-509 Commissioners Road West London N6J 1Y5",
    "addr:housenumber":"56-509",
    "addr:postcode":"n6j 1y5",
    "addr:street":"Commissioners Road West",
    "iso:country":"CA",
    "sg:address":"56-509 Commissioners Road West",
    "sg:city":"London",
    "sg:classifiers":[
        {
            "category":"Professional",
            "subcategory":"Computer Services",
            "type":"Services"
        }
    ],
    "sg:postcode":"N6J 1Y5",
    "sg:tags":[
        "insurance-rate-comparison",
        "mortgage-rate-comparison",
        "loa--rate-comparison",
        "credit-card-comparison",
        "cell-phone-comparison"
    ],
    "sg:website":"http://comparevillage.ca/",
    "wof:name":"CompareVillage.ca",
    "wof:placetype":"venue"
},
  "geometry": {"coordinates":[-81.261539,42.956806],"type":"Point"}
}