{
  "type": "Feature",
  "properties": {
    "iso:country":"CA",
    "sg:address":"1508 8 St",
    "sg:city":"Nisku",
    "sg:classifiers":[
        {
            "category":"Manufacturing",
            "subcategory":"Metals",
            "type":"Manufacturing & Wholesale Goods"
        }
    ],
    "sg:phone":"+1 780 955 2233",
    "sg:postcode":"T9E 7S6",
    "sg:province":"AB",
    "sg:tags":[
        "tank"
    ],
    "wof:name":"Glm Tanks & Equipment Ltd",
    "wof:placetype":"venue"
},
  "geometry": {"coordinates":[-113.51633453399999,53.3213996887],"type":"Point"}
}