{
  "type": "Feature",
  "properties": {
    "addr:full":"63880 Flood Hope Rd Hope BC V0X 1L2",
    "addr:postcode":"63880;v0x 1l2",
    "addr:street":"Flood Hope Rd",
    "iso:country":"CA",
    "sg:address":"63880 Flood Hope Rd",
    "sg:city":"Hope",
    "sg:classifiers":[
        {
            "category":"Autos & Motor Vehicles",
            "subcategory":"Fuel & Gas Station",
            "type":"Retail Goods"
        }
    ],
    "sg:phone":"+1 604 869 9214",
    "sg:postcode":"V0X 1L2",
    "sg:province":"BC",
    "sg:tags":[
        "oil"
    ],
    "wof:name":"Hope Mohawk",
    "wof:placetype":"venue"
},
  "geometry": {"coordinates":[-121.482338,49.36586],"type":"Point"}
}