{
  "type": "Feature",
  "properties": {
    "addr:full":"158 Leslie Ave Hornepayne ON P0M 1Z0",
    "addr:housenumber":"158",
    "addr:postcode":"p0m 1z0",
    "addr:street":"Leslie Ave",
    "iso:country":"CA",
    "sg:address":"158 Leslie Ave",
    "sg:city":"Hornepayne",
    "sg:classifiers":[
        {
            "category":"Organizations",
            "subcategory":"Religious Organization",
            "type":"Services"
        }
    ],
    "sg:phone":"+1 807 868 2616",
    "sg:postcode":"P0M 1Z0",
    "sg:province":"ON",
    "sg:tags":[
        "church"
    ],
    "wof:name":"Calvary Gospel Church",
    "wof:placetype":"venue"
},
  "geometry": {"coordinates":[-84.7773513794,49.2124786377],"type":"Point"}
}