{
  "type": "Feature",
  "properties": {
    "addr:full":"3235 Wharton Way Mississauga ON L4X 2B6",
    "addr:housenumber":"3235",
    "addr:postcode":"l4x 2b6",
    "addr:street":"Wharton Way",
    "iso:country":"CA",
    "sg:address":"3235 Wharton Way",
    "sg:city":"Mississauga",
    "sg:classifiers":[
        {
            "category":"Wholesale",
            "subcategory":"Machinery & Supplies",
            "type":"Manufacturing & Wholesale Goods"
        }
    ],
    "sg:phone":"+1 905 629 3100",
    "sg:postcode":"L4X 2B6",
    "sg:province":"ON",
    "sg:tags":[
        "pump"
    ],
    "wof:name":"Prospec Technologies Inc",
    "wof:placetype":"venue"
},
  "geometry": {"coordinates":[-79.579521,43.623329],"type":"Point"}
}