{
  "type": "Feature",
  "properties": {
    "addr:full":"39 Athabasca St W Moose Jaw SK S6H 2B6",
    "addr:housenumber":"39",
    "addr:postcode":"s6h 2b6",
    "addr:street":"Athabasca St W",
    "iso:country":"CA",
    "sg:address":"39 Athabasca St W",
    "sg:city":"Moose Jaw",
    "sg:classifiers":[
        {
            "category":"Organizations",
            "subcategory":"Labor Organization",
            "type":"Services"
        }
    ],
    "sg:phone":"+1 306 693 7922",
    "sg:postcode":"S6H 2B6",
    "sg:province":"SK",
    "wof:name":"Service Employees Union Local",
    "wof:placetype":"venue"
},
  "geometry": {"coordinates":[-105.536026001,50.3952064514],"type":"Point"}
}