{
  "type": "Feature",
  "properties": {
    "iso:country":"CA",
    "sg:address":"452 Rue Principale",
    "sg:city":"Granby",
    "sg:classifiers":[
        {
            "category":"Restaurant",
            "type":"Food & Drink"
        }
    ],
    "sg:phone":"+1 450 777 1016",
    "sg:postcode":"J2G 2X1",
    "sg:province":"QC",
    "wof:name":"Restaurant Le Retro",
    "wof:placetype":"venue"
},
  "geometry": {"coordinates":[-72.7355422974,45.4039573669],"type":"Point"}
}