{
  "type": "Feature",
  "properties": {
    "addr:full":"655 Rue DE L'Argon Charlesbourg QC G2N 2G7",
    "addr:housenumber":"655",
    "addr:postcode":"g2n 2g7",
    "addr:street":"Rue De L'Argon",
    "iso:country":"CA",
    "sg:address":"655 Rue DE L'Argon",
    "sg:city":"Charlesbourg",
    "sg:classifiers":[
        {
            "category":"Manufacturing",
            "subcategory":"Leather Goods",
            "type":"Manufacturing & Wholesale Goods"
        }
    ],
    "sg:phone":"+1 418 849 7997",
    "sg:postcode":"G2N 2G7",
    "sg:province":"QC",
    "sg:tags":[
        "shoes"
    ],
    "wof:name":"Chaussures Regence Inc",
    "wof:placetype":"venue"
},
  "geometry": {"coordinates":[-71.317855835,46.8936691284],"type":"Point"}
}