{
  "type": "Feature",
  "properties": {
    "addr:full":"5502 Lougheed Hwy Burnaby BC V5B 2Z8",
    "addr:housenumber":"5502",
    "addr:postcode":"v5b 2z8",
    "addr:street":"Lougheed Hwy",
    "iso:country":"CA",
    "sg:address":"5502 Lougheed Hwy",
    "sg:city":"Burnaby",
    "sg:classifiers":[
        {
            "category":"Restaurant",
            "type":"Food & Drink"
        }
    ],
    "sg:phone":"+1 604 299 9381",
    "sg:postcode":"V5B 2Z8",
    "sg:province":"BC",
    "sg:tags":[
        "center",
        "bowling"
    ],
    "wof:name":"Rev's Bowling Ctr",
    "wof:placetype":"venue"
},
  "geometry": {"coordinates":[-122.98353576700001,49.2648735046],"type":"Point"}
}