{
  "type": "Feature",
  "properties": {
    "iso:country":"CA",
    "sg:address":"440 Av DE L'Hotel-Dieu",
    "sg:city":"Saint-Hyacinthe",
    "sg:classifiers":[
        {
            "category":"Personal",
            "type":"Services"
        }
    ],
    "sg:phone":"+1 450 774 2425",
    "sg:postcode":"J2S 5J5",
    "sg:province":"QC",
    "sg:tags":[
        "therapist",
        "massage"
    ],
    "wof:name":"Estheteque",
    "wof:placetype":"venue"
},
  "geometry": {"coordinates":[-72.945930481,45.6227378845],"type":"Point"}
}