{
  "type": "Feature",
  "properties": {
    "addr:full":"340 Simpson St Thunder Bay ON P7C 3H7",
    "addr:housenumber":"340",
    "addr:postcode":"p7c 3h7",
    "addr:street":"Simpson St",
    "iso:country":"CA",
    "sg:address":"340 Simpson St",
    "sg:city":"Thunder Bay",
    "sg:classifiers":[
        {
            "category":"Freight",
            "type":"Transportation"
        }
    ],
    "sg:phone":"+1 807 623 3278",
    "sg:postcode":"P7C 3H7",
    "sg:province":"ON",
    "sg:tags":[
        "trucking"
    ],
    "wof:name":"Courtesy Freight Systems",
    "wof:placetype":"venue"
},
  "geometry": {"coordinates":[-89.23941802980001,48.3881454468],"type":"Point"}
}