{
  "type": "Feature",
  "properties": {
    "addr:full":"24 Dawnridge Trail Brampton ON L6Z 2A1",
    "addr:housenumber":"24",
    "addr:postcode":"l6z 2a1",
    "addr:street":"Dawnridge Trail",
    "iso:country":"CA",
    "sg:address":"24 Dawnridge Trail",
    "sg:city":"Brampton",
    "sg:classifiers":[
        {
            "category":"Professional",
            "subcategory":"Business Services",
            "type":"Services"
        }
    ],
    "sg:phone":"+1 905 840 3160",
    "sg:postcode":"L6Z 2A1",
    "sg:province":"ON",
    "sg:tags":[
        "interior",
        "consultant",
        "design",
        "decorator"
    ],
    "wof:name":"Abbington Interiors",
    "wof:placetype":"venue"
},
  "geometry": {"coordinates":[-79.807258606,43.7298316956],"type":"Point"}
}