{
  "type": "Feature",
  "properties": {
    "addr:full":"Farm Oungre SK S0C 1Z0",
    "addr:postcode":"s0c 1z0",
    "iso:country":"CA",
    "sg:address":"Farm",
    "sg:city":"Oungre",
    "sg:classifiers":[
        {
            "category":"Retail",
            "subcategory":"Repair Shop",
            "type":"Services"
        }
    ],
    "sg:phone":"+1 306 456 2739",
    "sg:postcode":"S0C 1Z0",
    "sg:province":"SK",
    "sg:tags":[
        "welding"
    ],
    "wof:name":"Randy Olson Welding",
    "wof:placetype":"venue"
},
  "geometry": {"coordinates":[-103.800415,49.145229],"type":"Point"}
}