{
  "type": "Feature",
  "properties": {
    "addr:full":"10 Windwood Dr Etobicoke ON M9W 6E7",
    "addr:housenumber":"10",
    "addr:postcode":"m9w 6e7",
    "addr:street":"Windwood Dr",
    "iso:country":"CA",
    "sg:address":"10 Windwood Dr",
    "sg:city":"Etobicoke",
    "sg:classifiers":[
        {
            "category":"Professional",
            "subcategory":"Engineering",
            "type":"Services"
        }
    ],
    "sg:phone":"+1 416 674 6155",
    "sg:postcode":"M9W 6E7",
    "sg:province":"ON",
    "sg:tags":[
        "engineer"
    ],
    "wof:name":"Wong & Wong Engineering Inc",
    "wof:placetype":"venue"
},
  "geometry": {"coordinates":[-79.604782,43.73085],"type":"Point"}
}