{
  "type": "Feature",
  "properties": {
    "addr:full":"47 Kent St Georgetown PE C0A 1L0",
    "addr:housenumber":"47",
    "addr:postcode":"c0a 1l0",
    "addr:street":"Kent St",
    "iso:country":"CA",
    "sg:address":"47 Kent St",
    "sg:city":"Georgetown",
    "sg:classifiers":[
        {
            "category":"Education",
            "subcategory":"School",
            "type":"Public Place"
        }
    ],
    "sg:phone":"+1 902 652 8970",
    "sg:postcode":"C0A 1L0",
    "sg:province":"PE",
    "wof:name":"Georgetown Elementary School",
    "wof:placetype":"venue"
},
  "geometry": {"coordinates":[-62.5334320068,46.1830596924],"type":"Point"}
}