{
  "type": "Feature",
  "properties": {
    "iso:country":"CA",
    "sg:city":"Verdun",
    "sg:classifiers":[
        {
            "category":"Shopping",
            "subcategory":"Pharmacy",
            "type":"Retail Goods"
        }
    ],
    "sg:phone":"+1 514 769 8566",
    "sg:postcode":"H4H 1M6",
    "sg:province":"QC",
    "wof:name":"Obonsoins",
    "wof:placetype":"venue"
},
  "geometry": {"coordinates":[-73.572884,45.447933],"type":"Point"}
}