{
  "type": "Feature",
  "properties": {
    "addr:full":"75 5th Ave W Vancouver BC V5Y 1H4",
    "addr:housenumber":"75",
    "addr:postcode":"v5y 1h4",
    "addr:street":"5Th Ave W",
    "iso:country":"CA",
    "sg:address":"75 5th Ave W",
    "sg:city":"Vancouver",
    "sg:classifiers":[
        {
            "category":"Manufacturing",
            "subcategory":"Apparel",
            "type":"Manufacturing & Wholesale Goods"
        }
    ],
    "sg:phone":"+1 604 876 6044",
    "sg:postcode":"V5Y 1H4",
    "sg:province":"BC",
    "sg:tags":[
        "clothing"
    ],
    "wof:name":"Intracan Sportswear Mfg CO Ltd",
    "wof:placetype":"venue"
},
  "geometry": {"coordinates":[-123.106140137,49.2666473389],"type":"Point"}
}