{
  "type": "Feature",
  "properties": {
    "addr:full":"640 Garson Coniston Rd Garson ON P3L 1R3",
    "addr:housenumber":"640",
    "addr:postcode":"p3l 1r3",
    "addr:street":"Garson Coniston Rd",
    "iso:country":"CA",
    "sg:address":"640 Garson Coniston Rd",
    "sg:city":"Garson",
    "sg:classifiers":[
        {
            "category":"Building & Trades",
            "subcategory":"Construction",
            "type":"Services"
        }
    ],
    "sg:phone":"+1 705 693 3887",
    "sg:postcode":"P3L 1R3",
    "sg:province":"ON",
    "sg:tags":[
        "demolition",
        "contractor"
    ],
    "wof:name":"Castonguay Blasting Ltd",
    "wof:placetype":"venue"
},
  "geometry": {"coordinates":[-80.839172,46.517052],"type":"Point"}
}