{
  "type": "Feature",
  "properties": {
    "iso:country":"CA",
    "sg:city":"Fredericton",
    "sg:classifiers":[
        {
            "category":"Health Services",
            "subcategory":"Doctor",
            "type":"Services"
        }
    ],
    "sg:phone":"+1 506 457 1087",
    "sg:postcode":"E3B 2T8",
    "sg:province":"NB",
    "sg:tags":[
        "clinic",
        "holistic",
        "practitioner"
    ],
    "wof:name":"Brawn-Gesner, Ruth-Ann",
    "wof:placetype":"venue"
},
  "geometry": {"coordinates":[-66.672424,45.943516],"type":"Point"}
}