{
  "type": "Feature",
  "properties": {
    "addr:full":"189 Broadway W Vancouver BC V5Y 1P4",
    "addr:housenumber":"189",
    "addr:postcode":"v5y 1p4",
    "addr:street":"Broadway W",
    "iso:country":"CA",
    "sg:address":"189 Broadway W",
    "sg:city":"Vancouver",
    "sg:classifiers":[
        {
            "category":"Restaurant",
            "type":"Food & Drink"
        }
    ],
    "sg:phone":"+1 604 873 2696",
    "sg:postcode":"V5Y 1P4",
    "sg:province":"BC",
    "wof:name":"Gigi's Pizza & Spaghetti House",
    "wof:placetype":"venue"
},
  "geometry": {"coordinates":[-123.10897799999999,49.263245],"type":"Point"}
}