{
  "type": "Feature",
  "properties": {
    "iso:country":"CA",
    "sg:address":"3954 Rue Nathalie",
    "sg:city":"Laval",
    "sg:classifiers":[
        {
            "category":"Professional",
            "subcategory":"Lawyer & Legal Services",
            "type":"Services"
        }
    ],
    "sg:phone":"+1 450 622 4011",
    "sg:postcode":"H7P 1N3",
    "sg:province":"QC",
    "sg:tags":[
        "attorney"
    ],
    "wof:name":"Bachand, Jacques",
    "wof:placetype":"venue"
},
  "geometry": {"coordinates":[-73.825439,45.571602],"type":"Point"}
}