{
  "type": "Feature",
  "properties": {
    "iso:country":"CA",
    "sg:address":"1020 Denman St",
    "sg:city":"Vancouver",
    "sg:classifiers":[
        {
            "category":"Shopping",
            "subcategory":"Pharmacy",
            "type":"Retail Goods"
        }
    ],
    "sg:phone":"+1 604 681 3411",
    "sg:postcode":"V6G 2M5",
    "sg:province":"BC",
    "wof:name":"Shoppers Drug Mart",
    "wof:placetype":"venue"
},
  "geometry": {"coordinates":[-123.138946533,49.2889823914],"type":"Point"}
}