{
  "type": "Feature",
  "properties": {
    "addr:full":"2986 Dundas St W Toronto ON M6P 1Z3",
    "addr:housenumber":"2986",
    "addr:postcode":"m6p 1z3",
    "addr:street":"Dundas St W",
    "iso:country":"CA",
    "sg:address":"2986 Dundas St W",
    "sg:city":"Toronto",
    "sg:classifiers":[
        {
            "category":"Wholesale",
            "subcategory":"Meat",
            "type":"Manufacturing & Wholesale Goods"
        }
    ],
    "sg:phone":"+1 416 767 0000",
    "sg:postcode":"M6P 1Z3",
    "sg:province":"ON",
    "sg:tags":[
        "delicatessen",
        "butchering"
    ],
    "wof:name":"Steve's Meat & Sausages Ltd",
    "wof:placetype":"venue"
},
  "geometry": {"coordinates":[-79.469009,43.6656],"type":"Point"}
}