{
  "type": "Feature",
  "properties": {
    "addr:full":"3712 Queens Gate Regina SK S4S 7J1",
    "addr:housenumber":"3712",
    "addr:postcode":"s4s 7j1",
    "addr:street":"Queens Gate",
    "iso:country":"CA",
    "sg:address":"3712 Queens Gate",
    "sg:city":"Regina",
    "sg:classifiers":[
        {
            "category":"Real Estate",
            "subcategory":"Developer",
            "type":"Services"
        }
    ],
    "sg:phone":"+1 306 584 5378",
    "sg:postcode":"S4S 7J1",
    "sg:province":"SK",
    "sg:tags":[
        "company",
        "land"
    ],
    "wof:name":"Evans Development Group Inc",
    "wof:placetype":"venue"
},
  "geometry": {"coordinates":[-104.638161,50.41898],"type":"Point"}
}