{
  "type": "Feature",
  "properties": {
    "addr:full":"5316 48 Ave Taber AB T1G 1S2",
    "addr:housenumber":"5316",
    "addr:postcode":"t1g 1s2",
    "addr:street":"48 Ave Taber",
    "iso:country":"CA",
    "sg:address":"5316 48 Ave",
    "sg:city":"Taber",
    "sg:classifiers":[
        {
            "category":"Retail",
            "subcategory":"Photofinishing",
            "type":"Services"
        }
    ],
    "sg:phone":"+1 403 223 8230",
    "sg:postcode":"T1G 1S2",
    "sg:province":"AB",
    "sg:tags":[
        "photo",
        "finishing"
    ],
    "wof:name":"Camera Expert",
    "wof:placetype":"venue"
},
  "geometry": {"coordinates":[-112.14434799999999,49.784595],"type":"Point"}
}