{
  "type": "Feature",
  "properties": {
    "iso:country":"CA",
    "sg:city":"Winnipeg",
    "sg:classifiers":[
        {
            "category":"Building & Trades",
            "subcategory":"Construction",
            "type":"Services"
        }
    ],
    "sg:phone":"+1 204 237 5267",
    "sg:postcode":"R2J 0K4",
    "sg:province":"MB",
    "sg:tags":[
        "bathroom",
        "remodeling"
    ],
    "wof:name":"Bathtub King",
    "wof:placetype":"venue"
},
  "geometry": {"coordinates":[-97.0847625732,49.8817024231],"type":"Point"}
}