{
  "type": "Feature",
  "properties": {
    "addr:full":"10150 80 St NW Edmonton AB T6A 3H8",
    "addr:housenumber":"10150",
    "addr:postcode":"t6a 3h8",
    "addr:street":"80 St Nw",
    "iso:country":"CA",
    "sg:address":"10150 80 St NW",
    "sg:city":"Edmonton",
    "sg:classifiers":[
        {
            "category":"Recreation",
            "type":"Entertainment"
        }
    ],
    "sg:phone":"+1 780 468 1798",
    "sg:postcode":"T6A 3H8",
    "sg:province":"AB",
    "sg:tags":[
        "hall",
        "auditorium"
    ],
    "wof:name":"Forest Heights Community Ctr",
    "wof:placetype":"venue"
},
  "geometry": {"coordinates":[-113.45107299999999,53.542179],"type":"Point"}
}