{
  "type": "Feature",
  "properties": {
    "addr:full":"117 4 Ave NE Calgary AB T2E 6K7",
    "addr:housenumber":"117",
    "addr:postcode":"t2e 6k7",
    "addr:street":"4 Ave Ne",
    "iso:country":"CA",
    "sg:address":"117 4 Ave NE",
    "sg:city":"Calgary",
    "sg:classifiers":[
        {
            "category":"Recreation",
            "type":"Entertainment"
        }
    ],
    "sg:phone":"+1 403 276 3013",
    "sg:postcode":"T2E 6K7",
    "sg:province":"AB",
    "sg:tags":[
        "tennis",
        "court"
    ],
    "wof:name":"Mount Pleasant Tennis Club",
    "wof:placetype":"venue"
},
  "geometry": {"coordinates":[-114.051804,51.052868],"type":"Point"}
}