{
  "type": "Feature",
  "properties": {
    "addr:full":"2715 Rue DE Reading Montreal QC H3K 1P7",
    "addr:housenumber":"2715",
    "addr:postcode":"h3k 1p7",
    "addr:street":"Rue De Reading",
    "iso:country":"CA",
    "sg:address":"2715 Rue DE Reading",
    "sg:city":"Montreal",
    "sg:classifiers":[
        {
            "category":"Wholesale",
            "subcategory":"Meat",
            "type":"Manufacturing & Wholesale Goods"
        }
    ],
    "sg:phone":"+1 514 932 2692",
    "sg:postcode":"H3K 1P7",
    "sg:province":"QC",
    "sg:tags":[
        "poultry",
        "product"
    ],
    "wof:name":"Aliments Atwater Inc",
    "wof:placetype":"venue"
},
  "geometry": {"coordinates":[-73.56708500000001,45.475697],"type":"Point"}
}