{
  "type": "Feature",
  "properties": {
    "addr:full":"Barrie ON L4M 6C1",
    "addr:postcode":"l4m 6c1",
    "iso:country":"CA",
    "sg:city":"Barrie",
    "sg:classifiers":[
        {
            "category":"Professional",
            "subcategory":"Lawyer & Legal Services",
            "type":"Services"
        }
    ],
    "sg:phone":"+1 705 726 9021",
    "sg:postcode":"L4M 6C1",
    "sg:province":"ON",
    "sg:tags":[
        "attorney"
    ],
    "wof:name":"Edgell, Dean F",
    "wof:placetype":"venue"
},
  "geometry": {"coordinates":[-79.69045257569999,44.4081611633],"type":"Point"}
}