{
  "type": "Feature",
  "properties": {
    "iso:country":"CA",
    "sg:address":"Conway St",
    "sg:city":"Stewart",
    "sg:classifiers":[
        {
            "category":"Recreation",
            "type":"Entertainment"
        }
    ],
    "sg:phone":"+1 250 636 9172",
    "sg:postcode":"V0T 1W0",
    "sg:province":"BC",
    "sg:tags":[
        "party",
        "fishing"
    ],
    "wof:name":"Richard's Outfitting Inc",
    "wof:placetype":"venue"
},
  "geometry": {"coordinates":[-129.989013672,55.9327354431],"type":"Point"}
}