{
  "type": "Feature",
  "properties": {
    "addr:full":"823 Manning Ave Toronto ON M6G 2W9",
    "addr:housenumber":"823",
    "addr:postcode":"m6g 2w9",
    "addr:street":"Manning Ave",
    "iso:country":"CA",
    "sg:address":"823 Manning Ave",
    "sg:city":"Toronto",
    "sg:classifiers":[
        {
            "category":"Organizations",
            "subcategory":"Religious Organization",
            "type":"Services"
        }
    ],
    "sg:phone":"+1 416 534 1763",
    "sg:postcode":"M6G 2W9",
    "sg:province":"ON",
    "sg:tags":[
        "church"
    ],
    "wof:name":"Russian Orthodox Christ",
    "wof:placetype":"venue"
},
  "geometry": {"coordinates":[-79.417686,43.668926],"type":"Point"}
}