{
  "type": "Feature",
  "properties": {
    "addr:full":"2310 Battleford Rd # 4 Mississauga ON L5N 3K6",
    "addr:housenumber":"2310",
    "addr:postcode":"l5n 3k6",
    "addr:street":"Battleford Rd # 4",
    "iso:country":"CA",
    "sg:address":"2310 Battleford Rd # 4",
    "sg:city":"Mississauga",
    "sg:classifiers":[
        {
            "category":"Retail",
            "subcategory":"Auto Repair",
            "type":"Services"
        }
    ],
    "sg:phone":"+1 905 821 7920",
    "sg:postcode":"L5N 3K6",
    "sg:province":"ON",
    "sg:tags":[
        "repairing",
        "automobile"
    ],
    "wof:name":"Miracle Auto Ctr Ltd",
    "wof:placetype":"venue"
},
  "geometry": {"coordinates":[-79.74100494379999,43.5856361389],"type":"Point"}
}