{
  "type": "Feature",
  "properties": {
    "iso:country":"CA",
    "sg:address":"878 Wellington Rd",
    "sg:city":"London",
    "sg:classifiers":[
        {
            "category":"Manufacturing",
            "subcategory":"Metals",
            "type":"Manufacturing & Wholesale Goods"
        }
    ],
    "sg:phone":"+1 519 681 2450",
    "sg:postcode":"N6E 1L9",
    "sg:province":"ON",
    "sg:tags":[
        "conditioning",
        "air",
        "system",
        "contractor"
    ],
    "wof:name":"Roy Inch & Sons Ltd",
    "wof:placetype":"venue"
},
  "geometry": {"coordinates":[-81.22522,42.94186],"type":"Point"}
}