{
  "type": "Feature",
  "properties": {
    "addr:full":"5939 Hwy 97B SE Salmon Arm BC V1E 2R1",
    "addr:housenumber":"5939",
    "addr:postcode":"v1e 2r1",
    "addr:street":"Hwy 97B Se",
    "iso:country":"CA",
    "sg:address":"5939 Hwy 97B SE",
    "sg:city":"Salmon Arm",
    "sg:classifiers":[
        {
            "category":"Food & Beverages",
            "subcategory":"Groceries & Convenience Stores",
            "type":"Retail Goods"
        }
    ],
    "sg:phone":"+1 250 832 6888",
    "sg:postcode":"V1E 2R1",
    "sg:province":"BC",
    "sg:tags":[
        "meat"
    ],
    "wof:name":"Mellor's Lucky Dollar Foods",
    "wof:placetype":"venue"
},
  "geometry": {"coordinates":[-119.208358765,50.6633682251],"type":"Point"}
}