{
  "type": "Feature",
  "properties": {
    "iso:country":"CA",
    "sg:address":"222 Av Laurier O",
    "sg:city":"Montreal",
    "sg:classifiers":[
        {
            "category":"Restaurant",
            "type":"Food & Drink"
        }
    ],
    "sg:phone":"+1 514 495 4961",
    "sg:postcode":"H2T 2N8",
    "sg:province":"QC",
    "wof:name":"Restaurant LA Petite Ardoise",
    "wof:placetype":"venue"
},
  "geometry": {"coordinates":[-73.590645,45.525272],"type":"Point"}
}