{
  "type": "Feature",
  "properties": {
    "addr:full":"2074 Robie St Halifax NS B3K 5L3",
    "addr:housenumber":"2074",
    "addr:postcode":"b3k 5l3",
    "addr:street":"Robie St",
    "iso:country":"CA",
    "sg:address":"2074 Robie St",
    "sg:city":"Halifax",
    "sg:classifiers":[
        {
            "category":"Real Estate",
            "subcategory":"Real Estate Operator",
            "type":"Services"
        }
    ],
    "sg:phone":"+1 902 422 4744",
    "sg:postcode":"B3K 5L3",
    "sg:province":"NS",
    "sg:tags":[
        "apartment"
    ],
    "wof:name":"Welsford Rental Office",
    "wof:placetype":"venue"
},
  "geometry": {"coordinates":[-63.591362,44.648418],"type":"Point"}
}