{
  "type": "Feature",
  "properties": {
    "addr:full":"3000 Boul Des Laurentides Vimont QC H7K 3G5",
    "addr:housenumber":"3000",
    "addr:postcode":"h7k 3g5",
    "addr:street":"Boul Des Laurentides",
    "iso:country":"CA",
    "sg:address":"3000 Boul Des Laurentides",
    "sg:city":"Vimont",
    "sg:classifiers":[
        {
            "category":"Shopping",
            "subcategory":"Jewelry",
            "type":"Retail Goods"
        }
    ],
    "sg:phone":"+1 450 629 2959",
    "sg:postcode":"H7K 3G5",
    "sg:province":"QC",
    "sg:tags":[
        "jeweler"
    ],
    "wof:name":"Bijouterie Daly'Or",
    "wof:placetype":"venue"
},
  "geometry": {"coordinates":[-73.7394485474,45.614654541],"type":"Point"}
}