{
  "type": "Feature",
  "properties": {
    "addr:full":"Christopher Lake SK S0J 0N0",
    "addr:postcode":"s0j 0n0",
    "addr:street":"Christopher Lake",
    "iso:country":"CA",
    "sg:city":"Christopher Lake",
    "sg:classifiers":[
        {
            "category":"Restaurant",
            "type":"Food & Drink"
        }
    ],
    "sg:phone":"+1 306 982 3060",
    "sg:postcode":"S0J 0N0",
    "sg:province":"SK",
    "wof:name":"Lake Country Cottage Restaurnt",
    "wof:placetype":"venue"
},
  "geometry": {"coordinates":[-105.79064200000001,53.539902],"type":"Point"}
}