{
  "type": "Feature",
  "properties": {
    "addr:full":"503 Rue Principale Lachute QC J8H 1Y5",
    "addr:housenumber":"503",
    "addr:postcode":"j8h 1y5",
    "addr:street":"Rue Principale",
    "iso:country":"CA",
    "sg:address":"503 Rue Principale",
    "sg:city":"Lachute",
    "sg:classifiers":[
        {
            "category":"Shopping",
            "subcategory":"Bicycles & Sporting Goods",
            "type":"Retail Goods"
        }
    ],
    "sg:phone":"+1 450 566 0006",
    "sg:postcode":"J8H 1Y5",
    "sg:province":"QC",
    "wof:name":"Samuel Chasse & Peche Inc",
    "wof:placetype":"venue"
},
  "geometry": {"coordinates":[-74.3350143433,45.6570167542],"type":"Point"}
}