{
  "type": "Feature",
  "properties": {
    "addr:full":"London ON N5Y 5A1",
    "addr:postcode":"n5y 5a1",
    "iso:country":"CA",
    "sg:city":"London",
    "sg:classifiers":[
        {
            "category":"Health Services",
            "subcategory":"Health Practitioner",
            "type":"Services"
        }
    ],
    "sg:phone":"+1 519 455 4030",
    "sg:postcode":"N5Y 5A1",
    "sg:province":"ON",
    "sg:tags":[
        "physiotherapist"
    ],
    "wof:name":"Body Mechanics Physiotherapy",
    "wof:placetype":"venue"
},
  "geometry": {"coordinates":[-81.2266921997,43.0033683777],"type":"Point"}
}