{
  "type": "Feature",
  "properties": {
    "addr:full":"526 Cliffe Ave Courtenay BC V9N 2J4",
    "addr:housenumber":"526",
    "addr:postcode":"v9n 2j4",
    "addr:street":"Cliffe Ave",
    "iso:country":"CA",
    "sg:address":"526 Cliffe Ave",
    "sg:city":"Courtenay",
    "sg:classifiers":[
        {
            "category":"Shopping",
            "subcategory":"Luggage & Leather Goods",
            "type":"Retail Goods"
        }
    ],
    "sg:phone":"+1 250 703 0168",
    "sg:postcode":"V9N 2J4",
    "sg:province":"BC",
    "sg:tags":[
        "travel",
        "accessory"
    ],
    "wof:name":"Traveller's Tale Shop",
    "wof:placetype":"venue"
},
  "geometry": {"coordinates":[-124.99689499999999,49.691307],"type":"Point"}
}