{
  "type": "Feature",
  "properties": {
    "addr:full":"1746 Eglinton Ave W York ON M6E 2H6",
    "addr:housenumber":"1746",
    "addr:postcode":"m6e 2h6",
    "addr:street":"Eglinton Ave W",
    "iso:country":"CA",
    "sg:address":"1746 Eglinton Ave W",
    "sg:city":"York",
    "sg:classifiers":[
        {
            "category":"Retail",
            "subcategory":"Repair Shop",
            "type":"Services"
        }
    ],
    "sg:phone":"+1 416 782 5357",
    "sg:postcode":"M6E 2H6",
    "sg:province":"ON",
    "sg:tags":[
        "upholsterer"
    ],
    "wof:name":"Joe Spadafina Upholstering",
    "wof:placetype":"venue"
},
  "geometry": {"coordinates":[-79.44800600000001,43.696316],"type":"Point"}
}