{
  "type": "Feature",
  "properties": {
    "addr:full":"288 East St Port Stanley ON N5L 1J6",
    "addr:housenumber":"288",
    "addr:postcode":"n5l 1j6",
    "addr:street":"East St",
    "iso:country":"CA",
    "sg:address":"288 East St",
    "sg:city":"Port Stanley",
    "sg:classifiers":[
        {
            "category":"Health Services",
            "subcategory":"Nursing And Care Facility",
            "type":"Services"
        }
    ],
    "sg:phone":"+1 519 782 3339",
    "sg:postcode":"N5L 1J6",
    "sg:province":"ON",
    "sg:tags":[
        "home",
        "convalescent"
    ],
    "wof:name":"Extendicare",
    "wof:placetype":"venue"
},
  "geometry": {"coordinates":[-81.2095718384,42.6673316956],"type":"Point"}
}