{
  "type": "Feature",
  "properties": {
    "addr:full":"5362 Madawaska Blvd Arnprior ON K7S 3H2",
    "addr:housenumber":"5362",
    "addr:postcode":"k7s 3h2",
    "addr:street":"Madawaska Blvd",
    "iso:country":"CA",
    "sg:address":"5362 Madawaska Blvd",
    "sg:city":"Arnprior",
    "sg:classifiers":[
        {
            "category":"Autos & Motor Vehicles",
            "subcategory":"Automobile Sales",
            "type":"Retail Goods"
        }
    ],
    "sg:phone":"+1 613 623 7344",
    "sg:postcode":"K7S 3H2",
    "sg:province":"ON",
    "sg:tags":[
        "car",
        "dealer"
    ],
    "wof:name":"Mc Allister Ford Sales Ltd",
    "wof:placetype":"venue"
},
  "geometry": {"coordinates":[-76.32794199999999,45.42741],"type":"Point"}
}