{
  "type": "Feature",
  "properties": {
    "addr:full":"603 Notre Dame St Belle River ON N0R 1A0",
    "addr:housenumber":"603",
    "addr:postcode":"n0r 1a0",
    "addr:street":"Notre Dame St",
    "iso:country":"CA",
    "sg:address":"603 Notre Dame St",
    "sg:city":"Belle River",
    "sg:classifiers":[
        {
            "category":"Shopping",
            "subcategory":"Bicycles & Sporting Goods",
            "type":"Retail Goods"
        }
    ],
    "sg:phone":"+1 519 728 1021",
    "sg:postcode":"N0R 1A0",
    "sg:province":"ON",
    "sg:tags":[
        "tackle",
        "fishing"
    ],
    "wof:name":"R & D Tackle & Bait",
    "wof:placetype":"venue"
},
  "geometry": {"coordinates":[-82.711044,42.293369],"type":"Point"}
}