{
  "type": "Feature",
  "properties": {
    "addr:full":"333 Elgin St N #B Cambridge ON N1R 7H9",
    "addr:housenumber":"333",
    "addr:postcode":"n1r 7h9",
    "addr:street":"Elgin St N # B",
    "iso:country":"CA",
    "sg:address":"333 Elgin St N #B",
    "sg:city":"Cambridge",
    "sg:classifiers":[
        {
            "category":"Retail",
            "subcategory":"Auto Repair",
            "type":"Services"
        }
    ],
    "sg:phone":"+1 519 620 1271",
    "sg:postcode":"N1R 7H9",
    "sg:province":"ON",
    "sg:tags":[
        "repairing",
        "automobile"
    ],
    "wof:name":"Phady's Automotive",
    "wof:placetype":"venue"
},
  "geometry": {"coordinates":[-80.305656,43.377384],"type":"Point"}
}