{
  "type": "Feature",
  "properties": {
    "addr:full":"Calgary AB T2E 6Z4",
    "addr:postcode":"t2e 6z4",
    "iso:country":"CA",
    "sg:city":"Calgary",
    "sg:classifiers":[
        {
            "category":"Home & Garden",
            "subcategory":"Furniture",
            "type":"Retail Goods"
        }
    ],
    "sg:phone":"+1 403 245 0110",
    "sg:postcode":"T2E 6Z4",
    "sg:province":"AB",
    "sg:tags":[
        "repairing",
        "top",
        "counter",
        "remodeling",
        "contractor"
    ],
    "wof:name":"Contemporary Countertops",
    "wof:placetype":"venue"
},
  "geometry": {"coordinates":[-114.012306,51.075119],"type":"Point"}
}