{
  "type": "Feature",
  "properties": {
    "iso:country":"CA",
    "sg:city":"Sprague",
    "sg:classifiers":[
        {
            "category":"Travel",
            "subcategory":"Campground",
            "type":"Entertainment"
        }
    ],
    "sg:phone":"+1 204 437 2091",
    "sg:postcode":"R0A 1Z0",
    "sg:province":"MB",
    "sg:tags":[
        "camp"
    ],
    "wof:name":"Camp Moose Lake",
    "wof:placetype":"venue"
},
  "geometry": {"coordinates":[-95.64288330079999,49.0350494385],"type":"Point"}
}