{
  "type": "Feature",
  "properties": {
    "addr:full":"9240 Boul Pie-Ix Montreal QC H1Z 4H7",
    "addr:housenumber":"9240",
    "addr:postcode":"h1z 4h7",
    "addr:street":"Boul Pie-Ix",
    "iso:country":"CA",
    "sg:address":"9240 Boul Pie-Ix",
    "sg:city":"Montreal",
    "sg:classifiers":[
        {
            "category":"Wholesale",
            "subcategory":"Fruits & Vegetables",
            "type":"Manufacturing & Wholesale Goods"
        }
    ],
    "sg:phone":"+1 514 323 9240",
    "sg:postcode":"H1Z 4H7",
    "sg:province":"QC",
    "wof:name":"Agri-Mondo",
    "wof:placetype":"venue"
},
  "geometry": {"coordinates":[-73.623734,45.580624],"type":"Point"}
}