{
  "type": "Feature",
  "properties": {
    "addr:full":"6455 Fallsview Blvd Niagara Falls ON L2G 3V9",
    "addr:housenumber":"6455",
    "addr:postcode":"l2g 3v9",
    "addr:street":"Fallsview Blvd",
    "iso:country":"CA",
    "sg:address":"6455 Fallsview Blvd",
    "sg:city":"Niagara Falls",
    "sg:classifiers":[
        {
            "category":"Travel",
            "subcategory":"Hotels & Motels",
            "type":"Entertainment"
        }
    ],
    "sg:phone":"+1 905 357 5200",
    "sg:postcode":"L2G 3V9",
    "sg:province":"ON",
    "wof:name":"Renaissance Hotel Fallsview",
    "wof:placetype":"venue"
},
  "geometry": {"coordinates":[-79.0828704834,43.0820770264],"type":"Point"}
}