{
  "type": "Feature",
  "properties": {
    "addr:full":"629 Richmond St London ON N6A 3G5",
    "addr:housenumber":"629",
    "addr:postcode":"n6a 3g5",
    "addr:street":"Richmond St",
    "iso:country":"CA",
    "sg:address":"629 Richmond St",
    "sg:city":"London",
    "sg:classifiers":[
        {
            "category":"Wholesale",
            "subcategory":"Machinery & Supplies",
            "type":"Manufacturing & Wholesale Goods"
        }
    ],
    "sg:phone":"+1 519 433 2971",
    "sg:postcode":"N6A 3G5",
    "sg:province":"ON",
    "sg:tags":[
        "salon",
        "beauty"
    ],
    "wof:name":"Burman's Beauty Supplies Ltd",
    "wof:placetype":"venue"
},
  "geometry": {"coordinates":[-81.251305,42.991512],"type":"Point"}
}