{
  "type": "Feature",
  "properties": {
    "addr:full":"Abbotsford BC V4X 2N6",
    "addr:postcode":"v4x 2n6",
    "iso:country":"CA",
    "sg:city":"Abbotsford",
    "sg:classifiers":[
        {
            "category":"Shopping",
            "type":"Retail Goods"
        }
    ],
    "sg:phone":"+1 604 864 0180",
    "sg:postcode":"V4X 2N6",
    "sg:province":"BC",
    "sg:tags":[
        "equipment",
        "supply",
        "wine"
    ],
    "wof:name":"Valley Wines",
    "wof:placetype":"venue"
},
  "geometry": {"coordinates":[-122.380966187,49.0547523499],"type":"Point"}
}