{
  "type": "Feature",
  "properties": {
    "addr:full":"Courtenay BC V9N 1N5",
    "addr:postcode":"v9n 1n5",
    "iso:country":"CA",
    "sg:city":"Courtenay",
    "sg:classifiers":[
        {
            "category":"Personal",
            "subcategory":"Beauty Salon",
            "type":"Services"
        }
    ],
    "sg:phone":"+1 250 334 4542",
    "sg:postcode":"V9N 1N5",
    "sg:province":"BC",
    "wof:name":"Mane Lines Hair Fashion",
    "wof:placetype":"venue"
},
  "geometry": {"coordinates":[-124.998993,49.688339],"type":"Point"}
}