{
  "type": "Feature",
  "properties": {
    "addr:full":"57 Benson Rd Oak Bay NB E3L 3W3",
    "addr:housenumber":"57",
    "addr:postcode":"e3l 3w3",
    "addr:street":"Benson Rd",
    "iso:country":"CA",
    "sg:address":"57 Benson Rd",
    "sg:city":"Oak Bay",
    "sg:classifiers":[
        {
            "category":"Home & Garden",
            "subcategory":"Garden Supply",
            "type":"Retail Goods"
        }
    ],
    "sg:phone":"+1 506 466 1673",
    "sg:postcode":"E3L 3W3",
    "sg:province":"NB",
    "sg:tags":[
        "tree",
        "christmas"
    ],
    "wof:name":"Mc Knight Farms",
    "wof:placetype":"venue"
},
  "geometry": {"coordinates":[-67.199524,45.217747],"type":"Point"}
}