{
  "type": "Feature",
  "properties": {
    "iso:country":"CA",
    "sg:address":"9477 Rue Meilleur",
    "sg:city":"Montreal",
    "sg:classifiers":[
        {
            "category":"Wholesale",
            "subcategory":"Apparel",
            "type":"Manufacturing & Wholesale Goods"
        }
    ],
    "sg:phone":"+1 514 383 5300",
    "sg:postcode":"H2N 2C4",
    "sg:province":"QC",
    "sg:tags":[
        "clothing"
    ],
    "wof:name":"Hollywood Jeans",
    "wof:placetype":"venue"
},
  "geometry": {"coordinates":[-73.65803527830001,45.5385513306],"type":"Point"}
}