{
  "type": "Feature",
  "properties": {
    "addr:full":"280 Armstrong St New Liskeard ON P0J 1P0",
    "addr:housenumber":"280",
    "addr:postcode":"p0j 1p0",
    "addr:street":"Armstrong St",
    "iso:country":"CA",
    "sg:address":"280 Armstrong St",
    "sg:city":"New Liskeard",
    "sg:classifiers":[
        {
            "category":"Government",
            "subcategory":"Office",
            "type":"Public Place"
        }
    ],
    "sg:phone":"+1 705 647 7391",
    "sg:postcode":"P0J 1P0",
    "sg:province":"ON",
    "wof:name":"Ontario Centre D'Information",
    "wof:placetype":"venue"
},
  "geometry": {"coordinates":[-79.67366800000001,47.508579],"type":"Point"}
}