{
  "type": "Feature",
  "properties": {
    "addr:full":"543 Main St Saint-Zotique QC J0P 1Z0",
    "addr:housenumber":"543",
    "addr:postcode":"j0p 1z0",
    "addr:street":"Main St",
    "iso:country":"CA",
    "sg:address":"543 Main St",
    "sg:city":"Saint-Zotique",
    "sg:classifiers":[
        {
            "category":"Building & Trades",
            "subcategory":"Plumbing",
            "type":"Services"
        }
    ],
    "sg:phone":"+1 450 267 8268",
    "sg:postcode":"J0P 1Z0",
    "sg:province":"QC",
    "sg:tags":[
        "mechanical",
        "contractor"
    ],
    "wof:name":"Mecanique Industrielle Mmv",
    "wof:placetype":"venue"
},
  "geometry": {"coordinates":[-74.2488708496,45.2414207458],"type":"Point"}
}