{
  "type": "Feature",
  "properties": {
    "iso:country":"CA",
    "sg:address":"336 40 Ave NE",
    "sg:city":"Calgary",
    "sg:classifiers":[
        {
            "category":"Utilities",
            "type":"Services"
        }
    ],
    "sg:phone":"+1 403 277 3300",
    "sg:postcode":"T2E 2M7",
    "sg:province":"AB",
    "sg:tags":[
        "locating"
    ],
    "wof:name":"Alberta Locators Inc",
    "wof:placetype":"venue"
},
  "geometry": {"coordinates":[-114.055367,51.08884],"type":"Point"}
}