{
  "type": "Feature",
  "properties": {
    "iso:country":"CA",
    "sg:address":"1470 55E Av",
    "sg:city":"Laval",
    "sg:classifiers":[
        {
            "category":"Wholesale",
            "subcategory":"Machinery & Supplies",
            "type":"Manufacturing & Wholesale Goods"
        }
    ],
    "sg:phone":"+1 450 627 0150",
    "sg:postcode":"H7R 4C6",
    "sg:province":"QC",
    "sg:tags":[
        "machine",
        "tool"
    ],
    "wof:name":"Mecani-Comp Inc",
    "wof:placetype":"venue"
},
  "geometry": {"coordinates":[-73.8681564331,45.5570487976],"type":"Point"}
}