{
  "type": "Feature",
  "properties": {
    "addr:full":"259 Worthington St W North Bay ON P1B 3B5",
    "addr:housenumber":"259",
    "addr:postcode":"p1b 3b5",
    "addr:street":"Worthington St W",
    "iso:country":"CA",
    "sg:address":"259 Worthington St W",
    "sg:city":"North Bay",
    "sg:classifiers":[
        {
            "category":"Manufacturing",
            "subcategory":"Printing",
            "type":"Manufacturing & Wholesale Goods"
        }
    ],
    "sg:phone":"+1 705 472 3200",
    "sg:postcode":"P1B 3B5",
    "sg:province":"ON",
    "sg:tags":[
        "newspaper"
    ],
    "wof:name":"Nugget",
    "wof:placetype":"venue"
},
  "geometry": {"coordinates":[-79.46418,46.313744],"type":"Point"}
}