{
  "type": "Feature",
  "properties": {
    "addr:full":"95 Lowcrest Blvd Scarborough ON M1T 1K7",
    "addr:housenumber":"95",
    "addr:postcode":"m1t 1k7",
    "addr:street":"Lowcrest Blvd",
    "iso:country":"CA",
    "sg:address":"95 Lowcrest Blvd",
    "sg:city":"Scarborough",
    "sg:classifiers":[
        {
            "category":"Banks & Credit Unions",
            "subcategory":"Investment Brokerage",
            "type":"Services"
        }
    ],
    "sg:phone":"+1 416 533 1305",
    "sg:postcode":"M1T 1K7",
    "sg:province":"ON",
    "sg:tags":[
        "consultant",
        "planning",
        "financial"
    ],
    "wof:name":"First Mutual Intl CO Ltd",
    "wof:placetype":"venue"
},
  "geometry": {"coordinates":[-79.306168,43.77364],"type":"Point"}
}