{
  "type": "Feature",
  "properties": {
    "addr:full":"521 Av Lepine Dorval QC H9P 2S9",
    "addr:postcode":"h9p 2s9",
    "addr:street":"521 Av Lepine",
    "iso:country":"CA",
    "sg:address":"521 Av Lepine",
    "sg:city":"Dorval",
    "sg:classifiers":[
        {
            "category":"Manufacturing",
            "subcategory":"Electronics",
            "type":"Manufacturing & Wholesale Goods"
        }
    ],
    "sg:phone":"+1 514 631 7956",
    "sg:postcode":"H9P 2S9",
    "sg:province":"QC",
    "sg:tags":[
        "printed",
        "circuit",
        "etched"
    ],
    "wof:name":"Jls Svc",
    "wof:placetype":"venue"
},
  "geometry": {"coordinates":[-73.72821044920001,45.4514122009],"type":"Point"}
}