{
  "type": "Feature",
  "properties": {
    "addr:full":"165 Goyeau St Windsor ON N9A 1G5",
    "addr:housenumber":"165",
    "addr:postcode":"n9a 1g5",
    "addr:street":"Goyeau St",
    "iso:country":"CA",
    "sg:address":"165 Goyeau St",
    "sg:city":"Windsor",
    "sg:classifiers":[
        {
            "category":"Shopping",
            "subcategory":"Pharmacy",
            "type":"Retail Goods"
        }
    ],
    "sg:phone":"+1 519 256 4954",
    "sg:postcode":"N9A 1G5",
    "sg:province":"ON",
    "wof:name":"Yee Pharmacy Ltd",
    "wof:placetype":"venue"
},
  "geometry": {"coordinates":[-83.037857,42.318874],"type":"Point"}
}