{
  "type": "Feature",
  "properties": {
    "iso:country":"CA",
    "sg:address":"1717 Vernon Dr",
    "sg:city":"Vancouver",
    "sg:classifiers":[
        {
            "category":"Autos & Motor Vehicles",
            "subcategory":"Automobile Sales",
            "type":"Retail Goods"
        }
    ],
    "sg:phone":"+1 604 659 1270",
    "sg:postcode":"V6A 3P8",
    "sg:province":"BC",
    "sg:tags":[
        "car",
        "truck"
    ],
    "wof:name":"Albert's Auto Sales",
    "wof:placetype":"venue"
},
  "geometry": {"coordinates":[-123.07890319800001,49.2696876526],"type":"Point"}
}