{
  "type": "Feature",
  "properties": {
    "addr:full":"205 Main St Spy Hill SK S0A 3W0",
    "addr:housenumber":"205",
    "addr:postcode":"s0a 3w0",
    "addr:street":"Main St Spy Hill",
    "iso:country":"CA",
    "sg:address":"205 Main St",
    "sg:city":"Spy Hill",
    "sg:classifiers":[
        {
            "category":"Government",
            "subcategory":"Office",
            "type":"Public Place"
        }
    ],
    "sg:phone":"+1 306 534 2255",
    "sg:postcode":"S0A 3W0",
    "sg:province":"SK",
    "sg:tags":[
        "village"
    ],
    "wof:name":"Spy Hill Village Office",
    "wof:placetype":"venue"
},
  "geometry": {"coordinates":[-101.686775208,50.6023902893],"type":"Point"}
}