{
  "type": "Feature",
  "properties": {
    "iso:country":"CA",
    "sg:address":"1696 Av Dollard",
    "sg:city":"Lasalle",
    "sg:classifiers":[
        {
            "category":"Shopping",
            "subcategory":"Shoes",
            "type":"Retail Goods"
        }
    ],
    "sg:phone":"+1 514 365 9044",
    "sg:postcode":"H8N 1T8",
    "sg:province":"QC",
    "wof:name":"Savignano Shoe Store",
    "wof:placetype":"venue"
},
  "geometry": {"coordinates":[-73.630821,45.428455],"type":"Point"}
}