{
  "type": "Feature",
  "properties": {
    "addr:full":"59 Ottawa St Arnprior ON K7S 1X2",
    "addr:housenumber":"59",
    "addr:postcode":"k7s 1x2",
    "addr:street":"Ottawa St",
    "iso:country":"CA",
    "sg:address":"59 Ottawa St",
    "sg:city":"Arnprior",
    "sg:classifiers":[
        {
            "category":"Education",
            "subcategory":"School",
            "type":"Public Place"
        }
    ],
    "sg:phone":"+1 613 623 3183",
    "sg:postcode":"K7S 1X2",
    "sg:province":"ON",
    "wof:name":"Arnprior District High School",
    "wof:placetype":"venue"
},
  "geometry": {"coordinates":[-76.35404968260001,45.4384994507],"type":"Point"}
}