{
  "type": "Feature",
  "properties": {
    "iso:country":"CA",
    "sg:address":"112 Parent Ave",
    "sg:city":"Ottawa",
    "sg:classifiers":[
        {
            "category":"Shopping",
            "subcategory":"Clothing, Apparel, & Fashions",
            "type":"Retail Goods"
        }
    ],
    "sg:phone":"+1 613 241 4111",
    "sg:postcode":"K1N 7B4",
    "sg:province":"ON",
    "sg:tags":[
        "boutique"
    ],
    "wof:name":"Lida Boutique Inc",
    "wof:placetype":"venue"
},
  "geometry": {"coordinates":[-75.69464111329999,45.429813385],"type":"Point"}
}