{
  "type": "Feature",
  "properties": {
    "addr:full":"991 Rang 7 E LA Sarre QC J9Z 2X4",
    "addr:housenumber":"991",
    "addr:postcode":"j9z 2x4",
    "addr:street":"Rang 7 E La Sarre",
    "iso:country":"CA",
    "sg:address":"991 Rang 7 E",
    "sg:city":"LA Sarre",
    "sg:classifiers":[
        {
            "category":"Retail",
            "subcategory":"Auto Repair",
            "type":"Services"
        }
    ],
    "sg:phone":"+1 819 333 4736",
    "sg:postcode":"J9Z 2X4",
    "sg:province":"QC",
    "sg:tags":[
        "repairing",
        "automobile"
    ],
    "wof:name":"Garage Letourneau & Fils",
    "wof:placetype":"venue"
},
  "geometry": {"coordinates":[-79.10832977290001,48.8075752258],"type":"Point"}
}