{
  "type": "Feature",
  "properties": {
    "addr:full":"1144 Islington Ave Etobicoke ON M8Z 4S5",
    "addr:housenumber":"1144",
    "addr:postcode":"m8z 4s5",
    "addr:street":"Islington Ave",
    "iso:country":"CA",
    "sg:address":"1144 Islington Ave",
    "sg:city":"Etobicoke",
    "sg:classifiers":[
        {
            "category":"Shopping",
            "subcategory":"Florist",
            "type":"Retail Goods"
        }
    ],
    "sg:phone":"+1 416 231 1226",
    "sg:postcode":"M8Z 4S5",
    "sg:province":"ON",
    "wof:name":"Islington Florist & Garden Ctr",
    "wof:placetype":"venue"
},
  "geometry": {"coordinates":[-79.52154541020001,43.6397323608],"type":"Point"}
}