{
  "type": "Feature",
  "properties": {
    "addr:full":"11 Progress Ave Scarborough ON M1P 4S7",
    "addr:housenumber":"11",
    "addr:postcode":"m1p 4s7",
    "addr:street":"Progress Ave",
    "iso:country":"CA",
    "sg:address":"11 Progress Ave",
    "sg:city":"Scarborough",
    "sg:classifiers":[
        {
            "category":"Manufacturing",
            "subcategory":"Tools & Machinery",
            "type":"Manufacturing & Wholesale Goods"
        }
    ],
    "sg:phone":"+1 416 299 4819",
    "sg:postcode":"M1P 4S7",
    "sg:province":"ON",
    "sg:tags":[
        "machine",
        "shop"
    ],
    "wof:name":"Iso Machine & Tool",
    "wof:placetype":"venue"
},
  "geometry": {"coordinates":[-79.2811508179,43.7694969177],"type":"Point"}
}