{
  "type": "Feature",
  "properties": {
    "addr:full":"Farm Kronau SK S0G 2T0",
    "addr:postcode":"s0g 2t0",
    "iso:country":"CA",
    "sg:address":"Farm",
    "sg:city":"Kronau",
    "sg:classifiers":[
        {
            "category":"Retail",
            "subcategory":"Animal Services",
            "type":"Services"
        }
    ],
    "sg:phone":"+1 306 781 2774",
    "sg:postcode":"S0G 2T0",
    "sg:province":"SK",
    "sg:tags":[
        "pet",
        "boarding",
        "sitting"
    ],
    "wof:name":"K-Lane Kennels",
    "wof:placetype":"venue"
},
  "geometry": {"coordinates":[-104.29450988799999,50.3074836731],"type":"Point"}
}