{
  "type": "Feature",
  "properties": {
    "addr:full":"5316 Airport Dr Fort Nelson BC V0C 1R0",
    "addr:housenumber":"5316",
    "addr:postcode":"bc v0c 1r0",
    "addr:street":"Airport Dr",
    "iso:country":"CA",
    "sg:address":"5316 Airport Dr",
    "sg:city":"Fort Nelson",
    "sg:classifiers":[
        {
            "category":"Real Estate",
            "subcategory":"Real Estate Operator",
            "type":"Services"
        }
    ],
    "sg:phone":"+1 250 774 2126",
    "sg:postcode":"V0C 1R0",
    "sg:province":"BC",
    "sg:tags":[
        "apartment"
    ],
    "wof:name":"Fort Nelson Apartment Rentals",
    "wof:placetype":"venue"
},
  "geometry": {"coordinates":[-122.691429,58.809231],"type":"Point"}
}