{
  "type": "Feature",
  "properties": {
    "addr:full":"119 Water St Harbour Grace NL A0A 2M0",
    "addr:housenumber":"119",
    "addr:postcode":"a0a 2m0",
    "addr:street":"Water St",
    "iso:country":"CA",
    "sg:address":"119 Water St",
    "sg:city":"Harbour Grace",
    "sg:classifiers":[
        {
            "category":"Freight",
            "type":"Transportation"
        }
    ],
    "sg:phone":"+1 709 596 0097",
    "sg:postcode":"A0A 2M0",
    "sg:province":"NL",
    "sg:tags":[
        "warehouse",
        "storage"
    ],
    "wof:name":"Harbour Grace Cs Inc",
    "wof:placetype":"venue"
},
  "geometry": {"coordinates":[-53.24401474,47.6816673279],"type":"Point"}
}