{
  "type": "Feature",
  "properties": {
    "addr:full":"98 Gore St E Perth ON K7H 1J2",
    "addr:housenumber":"98",
    "addr:postcode":"k7h 1j2",
    "addr:street":"Gore St E",
    "iso:country":"CA",
    "sg:address":"98 Gore St E",
    "sg:city":"Perth",
    "sg:classifiers":[
        {
            "category":"Personal",
            "subcategory":"Shoe Repair & Shine",
            "type":"Services"
        }
    ],
    "sg:phone":"+1 613 267 6626",
    "sg:postcode":"K7H 1J2",
    "sg:province":"ON",
    "sg:tags":[
        "repairing",
        "boot"
    ],
    "wof:name":"Mark's Cobbler Shop",
    "wof:placetype":"venue"
},
  "geometry": {"coordinates":[-76.2482299805,44.8987846375],"type":"Point"}
}