{
  "type": "Feature",
  "properties": {
    "addr:full":"75 Fernstaff Crt # 18 Concord ON L4K 3R3",
    "addr:housenumber":"75",
    "addr:postcode":"l4k 3r3",
    "addr:street":"Fernstaff Crt # 18",
    "iso:country":"CA",
    "sg:address":"75 Fernstaff Crt # 18",
    "sg:city":"Concord",
    "sg:classifiers":[
        {
            "category":"Shopping",
            "subcategory":"Computers & Home Electronics",
            "type":"Retail Goods"
        }
    ],
    "sg:phone":"+1 905 660 5452",
    "sg:postcode":"L4K 3R3",
    "sg:province":"ON",
    "sg:tags":[
        "equipment",
        "dealer"
    ],
    "wof:name":"Goldtech Computer Systems Ltd",
    "wof:placetype":"venue"
},
  "geometry": {"coordinates":[-79.480873,43.827076],"type":"Point"}
}