{
  "type": "Feature",
  "properties": {
    "addr:full":"3241 St Mary's Rd Winnipeg MB R2N 4B4",
    "addr:housenumber":"3241",
    "addr:postcode":"r2n 4b4",
    "addr:street":"St Mary'S Rd",
    "iso:country":"CA",
    "sg:address":"3241 St Mary's Rd",
    "sg:city":"Winnipeg",
    "sg:classifiers":[
        {
            "category":"Manufacturing",
            "subcategory":"Food",
            "type":"Manufacturing & Wholesale Goods"
        }
    ],
    "sg:phone":"+1 204 954 2060",
    "sg:postcode":"R2N 4B4",
    "sg:province":"MB",
    "sg:tags":[
        "product",
        "fund",
        "organization",
        "counselor",
        "raising",
        "manufacturer"
    ],
    "wof:name":"Mom's Pantry Products",
    "wof:placetype":"venue"
},
  "geometry": {"coordinates":[-97.1286621094,49.7670135498],"type":"Point"}
}