{
  "type": "Feature",
  "properties": {
    "addr:full":"316 Ridgeway Rd Crystal Beach ON L0S 1B0",
    "addr:housenumber":"316",
    "addr:postcode":"l0s 1b0",
    "addr:street":"Ridgeway Rd",
    "iso:country":"CA",
    "sg:address":"316 Ridgeway Rd",
    "sg:city":"Crystal Beach",
    "sg:classifiers":[
        {
            "category":"Retail",
            "subcategory":"Repair Shop",
            "type":"Services"
        }
    ],
    "sg:phone":"+1 905 894 5621",
    "sg:postcode":"L0S 1B0",
    "sg:province":"ON",
    "sg:tags":[
        "welding"
    ],
    "wof:name":"Reichel's Welding & Fab",
    "wof:placetype":"venue"
},
  "geometry": {"coordinates":[-79.0587768555,42.8668251038],"type":"Point"}
}