{
  "type": "Feature",
  "properties": {
    "addr:full":"8479 Boul Viau Saint-Leonard QC H1R 2T6",
    "addr:housenumber":"8479",
    "addr:postcode":"h1r 2t6",
    "addr:street":"Boul Viau",
    "iso:country":"CA",
    "sg:address":"8479 Boul Viau",
    "sg:city":"Saint-Leonard",
    "sg:classifiers":[
        {
            "category":"Shopping",
            "subcategory":"Pharmacy",
            "type":"Retail Goods"
        }
    ],
    "sg:phone":"+1 514 328 1222",
    "sg:postcode":"H1R 2T6",
    "sg:province":"QC",
    "wof:name":"Pharmacies Associees A Uniprix",
    "wof:placetype":"venue"
},
  "geometry": {"coordinates":[-73.60276,45.581867],"type":"Point"}
}