{
  "type": "Feature",
  "properties": {
    "addr:full":"153 Rue Blainville E Sainte-Therese QC J7E 1M6",
    "addr:housenumber":"153",
    "addr:postcode":"j7e 1m6",
    "addr:street":"Rue Blainville E Sainte-Therese",
    "iso:country":"CA",
    "sg:address":"153 Rue Blainville E",
    "sg:city":"Sainte-Therese",
    "sg:classifiers":[
        {
            "category":"Autos & Motor Vehicles",
            "subcategory":"Motorcycle Sales",
            "type":"Retail Goods"
        }
    ],
    "sg:phone":"+1 450 435 2711",
    "sg:postcode":"J7E 1M6",
    "sg:province":"QC",
    "sg:tags":[
        "scooter"
    ],
    "wof:name":"Ste Therese Moto-Sport",
    "wof:placetype":"venue"
},
  "geometry": {"coordinates":[-73.8297042847,45.639465332],"type":"Point"}
}