{
  "type": "Feature",
  "properties": {
    "addr:full":"297 2E Rue E LA Sarre QC J9Z 2H1",
    "addr:housenumber":"297",
    "addr:postcode":"j9z 2h1",
    "addr:street":"2E Rue E La Sarre",
    "iso:country":"CA",
    "sg:address":"297 2E Rue E",
    "sg:city":"LA Sarre",
    "sg:classifiers":[
        {
            "category":"Professional",
            "subcategory":"Management & Consulting",
            "type":"Services"
        }
    ],
    "sg:phone":"+1 819 339 5551",
    "sg:postcode":"J9Z 2H1",
    "sg:province":"QC",
    "sg:tags":[
        "communication",
        "consultant",
        "radio",
        "system",
        "telecommunication"
    ],
    "wof:name":"Tremcom",
    "wof:placetype":"venue"
},
  "geometry": {"coordinates":[-79.200485,48.815582],"type":"Point"}
}