{
  "type": "Feature",
  "properties": {
    "iso:country":"CA",
    "sg:address":"427 Bloor St W",
    "sg:city":"Toronto",
    "sg:classifiers":[
        {
            "category":"Arts & Performance",
            "subcategory":"Theater",
            "type":"Entertainment"
        }
    ],
    "sg:phone":"+1 416 966 1409",
    "sg:postcode":"M5S 1X7",
    "sg:province":"ON",
    "sg:tags":[
        "musician"
    ],
    "wof:name":"Toronto Early Music Ctr",
    "wof:placetype":"venue"
},
  "geometry": {"coordinates":[-79.405418,43.666245],"type":"Point"}
}