{
  "type": "Feature",
  "properties": {
    "addr:full":"70 Rte 132 O Nouvelle QC G0C 2E0",
    "addr:housenumber":"70",
    "addr:postcode":"qc g0c 2e0",
    "addr:street":"Rte 132 O",
    "iso:country":"CA",
    "sg:address":"70 Rte 132 O",
    "sg:city":"Nouvelle",
    "sg:classifiers":[
        {
            "category":"Home & Garden",
            "subcategory":"Garden Supply",
            "type":"Retail Goods"
        }
    ],
    "sg:phone":"+1 418 794 2882",
    "sg:postcode":"G0C 2E0",
    "sg:province":"QC",
    "sg:tags":[
        "engine",
        "lawn"
    ],
    "wof:name":"Garage Elvin Mc Brearty",
    "wof:placetype":"venue"
},
  "geometry": {"coordinates":[-66.31359863279999,48.1376724243],"type":"Point"}
}