{
  "type": "Feature",
  "properties": {
    "addr:full":"147 Symington Ave Toronto ON M6P 3W5",
    "addr:housenumber":"147",
    "addr:postcode":"m6p 3w5",
    "addr:street":"Symington Ave",
    "iso:country":"CA",
    "sg:address":"147 Symington Ave",
    "sg:city":"Toronto",
    "sg:classifiers":[
        {
            "category":"Food & Beverages",
            "subcategory":"Groceries & Convenience Stores",
            "type":"Retail Goods"
        }
    ],
    "sg:phone":"+1 416 532 6858",
    "sg:postcode":"M6P 3W5",
    "sg:province":"ON",
    "sg:tags":[
        "grocer"
    ],
    "wof:name":"Wallace Market",
    "wof:placetype":"venue"
},
  "geometry": {"coordinates":[-79.449326,43.661606],"type":"Point"}
}