{
  "type": "Feature",
  "properties": {
    "iso:country":"CA",
    "sg:address":"38 Micmac Rd",
    "sg:city":"Eel Ground",
    "sg:classifiers":[
        {
            "category":"Organizations",
            "subcategory":"Professional Association",
            "type":"Services"
        }
    ],
    "sg:phone":"+1 506 627 4611",
    "sg:postcode":"E1V 4B1",
    "sg:province":"NB",
    "wof:name":"North Shore Micmac District",
    "wof:placetype":"venue"
},
  "geometry": {"coordinates":[-65.627289,46.96925],"type":"Point"}
}