{
  "type": "Feature",
  "properties": {
    "addr:full":"136 Rue Main O Coaticook QC J1A 1P2",
    "addr:housenumber":"136",
    "addr:postcode":"j1a 1p2",
    "addr:street":"Rue Main O",
    "iso:country":"CA",
    "sg:address":"136 Rue Main O",
    "sg:city":"Coaticook",
    "sg:classifiers":[
        {
            "category":"Organizations",
            "subcategory":"Religious Organization",
            "type":"Services"
        }
    ],
    "sg:phone":"+1 819 849 3444",
    "sg:postcode":"J1A 1P2",
    "sg:province":"QC",
    "sg:tags":[
        "home",
        "retirement",
        "community",
        "retreat",
        "house"
    ],
    "wof:name":"Maison Familiale DE Coaticook",
    "wof:placetype":"venue"
},
  "geometry": {"coordinates":[-71.802345,45.132416],"type":"Point"}
}