{
  "type": "Feature",
  "properties": {
    "addr:full":"755 Wonderland Rd N London ON N6H 4L1",
    "addr:housenumber":"755",
    "addr:postcode":"n6h 4l1",
    "addr:street":"Wonderland Rd N",
    "iso:country":"CA",
    "sg:address":"755 Wonderland Rd N",
    "sg:city":"London",
    "sg:classifiers":[
        {
            "category":"Food & Beverages",
            "subcategory":"Bakery",
            "type":"Retail Goods"
        }
    ],
    "sg:phone":"+1 519 473 7772",
    "sg:postcode":"N6H 4L1",
    "sg:province":"ON",
    "wof:name":"Angelo's Italian Bakery & Deli",
    "wof:placetype":"venue"
},
  "geometry": {"coordinates":[-81.29566199999999,42.990078],"type":"Point"}
}