{
  "type": "Feature",
  "properties": {
    "addr:full":"450 Albert St Renfrew ON K7V 4K4",
    "addr:housenumber":"450",
    "addr:postcode":"k7v 4k4",
    "addr:street":"Albert St",
    "iso:country":"CA",
    "sg:address":"450 Albert St",
    "sg:city":"Renfrew",
    "sg:classifiers":[
        {
            "category":"Health Services",
            "subcategory":"Nursing And Care Facility",
            "type":"Services"
        }
    ],
    "sg:phone":"+1 613 432 9502",
    "sg:postcode":"K7V 4K4",
    "sg:province":"ON",
    "sg:tags":[
        "home",
        "retirement",
        "community"
    ],
    "wof:name":"Quail Creek Retirement Ctr",
    "wof:placetype":"venue"
},
  "geometry": {"coordinates":[-76.697639,45.480701],"type":"Point"}
}