{
  "type": "Feature",
  "properties": {
    "iso:country":"CA",
    "sg:address":"201 Pinebush Rd",
    "sg:city":"Cambridge",
    "sg:classifiers":[
        {
            "category":"Manufacturing",
            "subcategory":"Metals",
            "type":"Manufacturing & Wholesale Goods"
        }
    ],
    "sg:phone":"+1 519 740 6031",
    "sg:postcode":"N1R 7H8",
    "sg:province":"ON",
    "sg:tags":[
        "steel"
    ],
    "wof:name":"Gsm Mechanical Systems",
    "wof:placetype":"venue"
},
  "geometry": {"coordinates":[-80.31052398680001,43.4110717773],"type":"Point"}
}