{
  "type": "Feature",
  "properties": {
    "addr:full":"20 Fisherman's Wharf Rd Bayfield ON N0M 1G0",
    "addr:housenumber":"20",
    "addr:postcode":"n0m 1g0",
    "addr:street":"Fisherman'S Wharf Rd",
    "iso:country":"CA",
    "sg:address":"20 Fisherman's Wharf Rd",
    "sg:city":"Bayfield",
    "sg:classifiers":[
        {
            "category":"Recreation",
            "subcategory":"Marina",
            "type":"Entertainment"
        }
    ],
    "sg:phone":"+1 519 565 2411",
    "sg:postcode":"N0M 1G0",
    "sg:province":"ON",
    "sg:tags":[
        "repairing",
        "boat"
    ],
    "wof:name":"Bayfield Marine Svc",
    "wof:placetype":"venue"
},
  "geometry": {"coordinates":[-81.696426,43.561378],"type":"Point"}
}