{
  "type": "Feature",
  "properties": {
    "addr:full":"3079 Universal Dr Mississauga ON L4X 2E2",
    "addr:housenumber":"3079",
    "addr:postcode":"l4x 2e2",
    "addr:street":"Universal Dr",
    "iso:country":"CA",
    "sg:address":"3079 Universal Dr",
    "sg:city":"Mississauga",
    "sg:classifiers":[
        {
            "category":"Wholesale",
            "subcategory":"Machinery & Supplies",
            "type":"Manufacturing & Wholesale Goods"
        }
    ],
    "sg:phone":"+1 905 625 1972",
    "sg:postcode":"L4X 2E2",
    "sg:province":"ON",
    "sg:tags":[
        "chains"
    ],
    "wof:name":"Merley Chains Ltd",
    "wof:placetype":"venue"
},
  "geometry": {"coordinates":[-79.57192999999999,43.624058],"type":"Point"}
}