{
  "type": "Feature",
  "properties": {
    "addr:full":"Mississauga ON L5N 3E7",
    "addr:postcode":"l5n 3e7",
    "iso:country":"CA",
    "sg:city":"Mississauga",
    "sg:classifiers":[
        {
            "category":"Home & Garden",
            "subcategory":"Carpets & Floor Coverings",
            "type":"Retail Goods"
        }
    ],
    "sg:phone":"+1 905 567 3336",
    "sg:postcode":"L5N 3E7",
    "sg:province":"ON",
    "sg:tags":[
        "resurfacing",
        "laying",
        "refinishing",
        "rug"
    ],
    "wof:name":"Mississauga Tile Ctr Ltd",
    "wof:placetype":"venue"
},
  "geometry": {"coordinates":[-79.739098,43.589455],"type":"Point"}
}