{
  "type": "Feature",
  "properties": {
    "addr:full":"234 Main St W Palmerston ON N0G 2P0",
    "addr:housenumber":"234",
    "addr:postcode":"n0g 2p0",
    "addr:street":"Main St W",
    "iso:country":"CA",
    "sg:address":"234 Main St W",
    "sg:city":"Palmerston",
    "sg:classifiers":[
        {
            "category":"Cinema",
            "subcategory":"Movie Rental",
            "type":"Entertainment"
        }
    ],
    "sg:phone":"+1 519 343 4422",
    "sg:postcode":"N0G 2P0",
    "sg:province":"ON",
    "sg:tags":[
        "leasing",
        "video",
        "disc",
        "tape"
    ],
    "wof:name":"Main Street Video",
    "wof:placetype":"venue"
},
  "geometry": {"coordinates":[-80.85013600000001,43.834007],"type":"Point"}
}