{
  "type": "Feature",
  "properties": {
    "addr:full":"3020 3rd Ave Port Alberni BC V9Y 2A5",
    "addr:housenumber":"3020",
    "addr:postcode":"v9y 2a5",
    "addr:street":"3Rd Ave",
    "iso:country":"CA",
    "sg:address":"3020 3rd Ave",
    "sg:city":"Port Alberni",
    "sg:classifiers":[
        {
            "category":"Shopping",
            "subcategory":"Florist",
            "type":"Retail Goods"
        }
    ],
    "sg:phone":"+1 250 723 6201",
    "sg:postcode":"V9Y 2A5",
    "sg:province":"BC",
    "wof:name":"Taylor's Flower Shop",
    "wof:placetype":"venue"
},
  "geometry": {"coordinates":[-124.807769775,49.2336883545],"type":"Point"}
}