{
  "type": "Feature",
  "properties": {
    "addr:full":"3783 Av Grey Montreal QC H4A 3N8",
    "addr:housenumber":"3783",
    "addr:postcode":"h4a 3n8",
    "addr:street":"Av Grey",
    "iso:country":"CA",
    "sg:address":"3783 Av Grey",
    "sg:city":"Montreal",
    "sg:classifiers":[
        {
            "category":"Communications",
            "subcategory":"Television Station",
            "type":"Services"
        }
    ],
    "sg:phone":"+1 514 487 1320",
    "sg:postcode":"H4A 3N8",
    "sg:province":"QC",
    "sg:tags":[
        "tv",
        "radio",
        "school",
        "broadcasting",
        "co"
    ],
    "wof:name":"Wide Sea Enterprises",
    "wof:placetype":"venue"
},
  "geometry": {"coordinates":[-73.611603,45.479046],"type":"Point"}
}