{
  "type": "Feature",
  "properties": {
    "addr:full":"9770 Boul Henri-Bourassa O Saint-Laurent QC H4S 1R5",
    "addr:housenumber":"9770",
    "addr:postcode":"h4s 1r5",
    "addr:street":"Boul Henri-Bourassa O",
    "iso:country":"CA",
    "sg:address":"9770 Boul Henri-Bourassa O",
    "sg:city":"Saint-Laurent",
    "sg:classifiers":[
        {
            "category":"Wholesale",
            "subcategory":"Computers",
            "type":"Manufacturing & Wholesale Goods"
        }
    ],
    "sg:phone":"+1 514 745 4500",
    "sg:postcode":"H4S 1R5",
    "sg:province":"QC",
    "wof:name":"Emj Data Systems Ltd",
    "wof:placetype":"venue"
},
  "geometry": {"coordinates":[-73.7530212402,45.496055603],"type":"Point"}
}