{
  "type": "Feature",
  "properties": {
    "addr:full":"2903 Treeview Rd Sudbury ON P3E 5C7",
    "addr:housenumber":"2903",
    "addr:postcode":"p3e 5c7",
    "addr:street":"Treeview Rd",
    "iso:country":"CA",
    "sg:address":"2903 Treeview Rd",
    "sg:city":"Sudbury",
    "sg:classifiers":[
        {
            "category":"Building & Trades",
            "subcategory":"Construction",
            "type":"Services"
        }
    ],
    "sg:phone":"+1 705 522 4210",
    "sg:postcode":"P3E 5C7",
    "sg:province":"ON",
    "sg:tags":[
        "demolition",
        "contractor"
    ],
    "wof:name":"Hardrock Mine Developers Ltd",
    "wof:placetype":"venue"
},
  "geometry": {"coordinates":[-81.02262878419999,46.4350547791],"type":"Point"}
}