{
  "type": "Feature",
  "properties": {
    "iso:country":"CA",
    "sg:city":"St George",
    "sg:classifiers":[
        {
            "category":"Organizations",
            "subcategory":"Religious Organization",
            "type":"Services"
        }
    ],
    "sg:phone":"+1 204 367 2571",
    "sg:postcode":"R0E 1V0",
    "sg:province":"MB",
    "sg:tags":[
        "church"
    ],
    "wof:name":"St George Parish",
    "wof:placetype":"venue"
},
  "geometry": {"coordinates":[-96.14958190919999,50.5391273499],"type":"Point"}
}