{
  "type": "Feature",
  "properties": {
    "addr:full":"1 Bradwick Dr Concord ON L4K 2T4",
    "addr:housenumber":"1",
    "addr:postcode":"l4k 2t4",
    "addr:street":"Bradwick Dr",
    "iso:country":"CA",
    "sg:address":"1 Bradwick Dr",
    "sg:city":"Concord",
    "sg:classifiers":[
        {
            "category":"Building & Trades",
            "subcategory":"Construction",
            "type":"Services"
        }
    ],
    "sg:phone":"+1 905 669 1615",
    "sg:postcode":"L4K 2T4",
    "sg:province":"ON",
    "sg:tags":[
        "contractor"
    ],
    "wof:name":"Townwood Homes Inc",
    "wof:placetype":"venue"
},
  "geometry": {"coordinates":[-79.48155975340001,43.8184280396],"type":"Point"}
}