{
  "type": "Feature",
  "properties": {
    "addr:full":"3401 Rg Ramsay Saint-Felix-DE-Valois QC J0K 2M0",
    "addr:housenumber":"3401",
    "addr:postcode":"j0k 2m0",
    "addr:street":"Rg Ramsay Saint-Felix-De-Valois",
    "iso:country":"CA",
    "sg:address":"3401 Rg Ramsay",
    "sg:city":"Saint-Felix-DE-Valois",
    "sg:classifiers":[
        {
            "category":"Manufacturing",
            "subcategory":"Lumber",
            "type":"Manufacturing & Wholesale Goods"
        }
    ],
    "sg:phone":"+1 450 889 4442",
    "sg:postcode":"J0K 2M0",
    "sg:province":"QC",
    "sg:tags":[
        "syrup",
        "maple",
        "sugar"
    ],
    "wof:name":"Cabane A Sucre Cyssie",
    "wof:placetype":"venue"
},
  "geometry": {"coordinates":[-73.431015,46.156181],"type":"Point"}
}