{
  "type": "Feature",
  "properties": {
    "iso:country":"CA",
    "sg:city":"Charlesbourg",
    "sg:classifiers":[
        {
            "category":"Real Estate",
            "subcategory":"Real Estate Operator",
            "type":"Services"
        }
    ],
    "sg:phone":"+1 418 623 4124",
    "sg:postcode":"G1H 7A5",
    "sg:province":"QC",
    "sg:tags":[
        "apartment"
    ],
    "wof:name":"Residences DE LA Capitale",
    "wof:placetype":"venue"
},
  "geometry": {"coordinates":[-71.241226,46.845909],"type":"Point"}
}