{
  "type": "Feature",
  "properties": {
    "addr:full":"4 Caxton Close Halifax NS B3M 4J5",
    "addr:housenumber":"4",
    "addr:postcode":"b3m 4j5",
    "addr:street":"Caxton Close",
    "iso:country":"CA",
    "sg:address":"4 Caxton Close",
    "sg:city":"Halifax",
    "sg:classifiers":[
        {
            "category":"Retail",
            "subcategory":"Portrait Studio",
            "type":"Services"
        }
    ],
    "sg:phone":"+1 902 445 1810",
    "sg:postcode":"B3M 4J5",
    "sg:province":"NS",
    "sg:tags":[
        "photographer"
    ],
    "wof:name":"Fairclough Photographic Images",
    "wof:placetype":"venue"
},
  "geometry": {"coordinates":[-63.659157,44.662102],"type":"Point"}
}