{
  "type": "Feature",
  "properties": {
    "addr:full":"222 Saint Patrick St Toronto ON M5T 1V4",
    "addr:housenumber":"222",
    "addr:postcode":"m5t 1v4",
    "addr:street":"Saint Patrick St",
    "iso:country":"CA",
    "sg:address":"222 Saint Patrick St",
    "sg:city":"Toronto",
    "sg:classifiers":[
        {
            "category":"Health Services",
            "subcategory":"Health Practitioner",
            "type":"Services"
        }
    ],
    "sg:phone":"+1 416 596 3199",
    "sg:postcode":"M5T 1V4",
    "sg:province":"ON",
    "sg:tags":[
        "acupuncture"
    ],
    "wof:name":"Acupuncture Clinic & Education",
    "wof:placetype":"venue"
},
  "geometry": {"coordinates":[-79.3908081055,43.6551322937],"type":"Point"}
}