{
  "type": "Feature",
  "properties": {
    "addr:full":"933 Ch Des Pres Sainte-Marie-Salome QC J0K 2Z0",
    "addr:housenumber":"933",
    "addr:postcode":"j0k 2z0",
    "addr:street":"Ch Des Pres Sainte-Marie-Salome",
    "iso:country":"CA",
    "sg:address":"933 Ch Des Pres",
    "sg:city":"Sainte-Marie-Salome",
    "sg:classifiers":[
        {
            "category":"Building & Trades",
            "subcategory":"Plumbing",
            "type":"Services"
        }
    ],
    "sg:phone":"+1 450 754 2547",
    "sg:postcode":"J0K 2Z0",
    "sg:province":"QC",
    "sg:tags":[
        "contractor"
    ],
    "wof:name":"Plomberie Sylvain Granger",
    "wof:placetype":"venue"
},
  "geometry": {"coordinates":[-73.50970458979999,45.9465560913],"type":"Point"}
}