{
  "type": "Feature",
  "properties": {
    "addr:full":"4 Craftsman Pvt Ottawa ON K1Y 4W9",
    "addr:housenumber":"4",
    "addr:postcode":"k1y 4w9",
    "addr:street":"Craftsman Pvt",
    "iso:country":"CA",
    "sg:address":"4 Craftsman Pvt",
    "sg:city":"Ottawa",
    "sg:classifiers":[
        {
            "category":"Education",
            "subcategory":"Special Training",
            "type":"Public Place"
        }
    ],
    "sg:phone":"+1 613 721 5900",
    "sg:postcode":"K1Y 4W9",
    "sg:province":"ON",
    "sg:tags":[
        "consultant",
        "management",
        "business"
    ],
    "wof:name":"Calnan & Assoc Ltd",
    "wof:placetype":"venue"
},
  "geometry": {"coordinates":[-75.73146820069999,45.402671814],"type":"Point"}
}