{
  "type": "Feature",
  "properties": {
    "addr:full":"309 22nd St E North Vancouver BC V7L 3C8",
    "addr:housenumber":"309",
    "addr:postcode":"v7l 3c8",
    "addr:street":"22Nd St E",
    "iso:country":"CA",
    "sg:address":"309 22nd St E",
    "sg:city":"North Vancouver",
    "sg:classifiers":[
        {
            "category":"Retail",
            "subcategory":"Portrait Studio",
            "type":"Services"
        }
    ],
    "sg:phone":"+1 604 980 7244",
    "sg:postcode":"V7L 3C8",
    "sg:province":"BC",
    "sg:tags":[
        "photographer"
    ],
    "wof:name":"Tom Burley Photography",
    "wof:placetype":"venue"
},
  "geometry": {"coordinates":[-123.065376,49.329067],"type":"Point"}
}