{
  "type": "Feature",
  "properties": {
    "addr:full":"690 Rue Trans-Canada Longueuil QC J4G 1P1",
    "addr:housenumber":"690",
    "addr:postcode":"j4g 1p1",
    "addr:street":"Rue Trans-Canada",
    "iso:country":"CA",
    "sg:address":"690 Rue Trans-Canada",
    "sg:city":"Longueuil",
    "sg:classifiers":[
        {
            "category":"Professional",
            "type":"Services"
        }
    ],
    "sg:phone":"+1 450 651 2511",
    "sg:postcode":"J4G 1P1",
    "sg:province":"QC",
    "sg:tags":[
        "heat",
        "establishment",
        "pump"
    ],
    "wof:name":"Turkhot Tech Inc",
    "wof:placetype":"venue"
},
  "geometry": {"coordinates":[-73.4574203491,45.5739555359],"type":"Point"}
}