{
  "type": "Feature",
  "properties": {
    "iso:country":"CA",
    "sg:address":"100 Rue Du Pont",
    "sg:city":"Vallee-Jonction",
    "sg:classifiers":[
        {
            "category":"Building & Trades",
            "subcategory":"Electrical",
            "type":"Services"
        }
    ],
    "sg:phone":"+1 418 253 5441",
    "sg:postcode":"G0S 3J0",
    "sg:province":"QC",
    "sg:tags":[
        "electric",
        "contractor"
    ],
    "wof:name":"Camil Jacob Inc",
    "wof:placetype":"venue"
},
  "geometry": {"coordinates":[-70.92779541020001,46.3746948242],"type":"Point"}
}