{
  "type": "Feature",
  "properties": {
    "iso:country":"CA",
    "sg:city":"Milton",
    "sg:classifiers":[
        {
            "category":"Personal",
            "subcategory":"Beauty Salon",
            "type":"Services"
        }
    ],
    "sg:phone":"+1 905 876 2842",
    "sg:postcode":"L9T 2H6",
    "sg:province":"ON",
    "wof:name":"Gold Scissors",
    "wof:placetype":"venue"
},
  "geometry": {"coordinates":[-79.880943,43.514065],"type":"Point"}
}