{
  "type": "Feature",
  "properties": {
    "addr:full":"1283 1E Av Lac-Saint-Charles QC G3G 2T6",
    "addr:housenumber":"1283",
    "addr:postcode":"g3g 2t6",
    "addr:street":"1E Av Lac-Saint-Charles",
    "iso:country":"CA",
    "sg:address":"1283 1E Av",
    "sg:city":"Lac-Saint-Charles",
    "sg:classifiers":[
        {
            "category":"Personal",
            "subcategory":"Beauty Salon",
            "type":"Services"
        }
    ],
    "sg:phone":"+1 418 849 6643",
    "sg:postcode":"G3G 2T6",
    "sg:province":"QC",
    "wof:name":"Salon Chantale",
    "wof:placetype":"venue"
},
  "geometry": {"coordinates":[-71.37591552729999,46.9081993103],"type":"Point"}
}