{
  "type": "Feature",
  "properties": {
    "addr:full":"Calgary AB T2P 4K8",
    "addr:postcode":"t2p 4k8",
    "iso:country":"CA",
    "sg:city":"Calgary",
    "sg:classifiers":[
        {
            "category":"Restaurant",
            "type":"Food & Drink"
        }
    ],
    "sg:phone":"+1 403 265 8248",
    "sg:postcode":"T2P 4K8",
    "sg:province":"AB",
    "wof:name":"Manchu Wok",
    "wof:placetype":"venue"
},
  "geometry": {"coordinates":[-114.07056427000001,51.0462112427],"type":"Point"}
}