{
  "type": "Feature",
  "properties": {
    "addr:full":"1283 St Clair Ave W Toronto ON M6E 1B8",
    "addr:housenumber":"1283",
    "addr:postcode":"m6e 1b8",
    "addr:street":"St Clair Ave W",
    "iso:country":"CA",
    "sg:address":"1283 St Clair Ave W",
    "sg:city":"Toronto",
    "sg:classifiers":[
        {
            "category":"Personal",
            "subcategory":"Beauty Salon",
            "type":"Services"
        }
    ],
    "sg:phone":"+1 416 658 4528",
    "sg:postcode":"M6E 1B8",
    "sg:province":"ON",
    "wof:name":"Shampoo Hair Design",
    "wof:placetype":"venue"
},
  "geometry": {"coordinates":[-79.44761699999999,43.676804],"type":"Point"}
}