{
  "type": "Feature",
  "properties": {
    "addr:full":"Dawson Creek BC V1G 4K6",
    "addr:postcode":"v1g 4k6",
    "iso:country":"CA",
    "sg:city":"Dawson Creek",
    "sg:classifiers":[
        {
            "category":"Real Estate",
            "subcategory":"Real Estate Operator",
            "type":"Services"
        }
    ],
    "sg:phone":"+1 250 782 5531",
    "sg:postcode":"V1G 4K6",
    "sg:province":"BC",
    "sg:tags":[
        "mall",
        "shopping",
        "center"
    ],
    "wof:name":"Dawson Mall",
    "wof:placetype":"venue"
},
  "geometry": {"coordinates":[-120.22423553500001,55.7505989075],"type":"Point"}
}