{
  "type": "Feature",
  "properties": {
    "addr:full":"1010 Warner St Moose Jaw SK S6H 5S5",
    "addr:housenumber":"1010",
    "addr:postcode":"s6h 5s5",
    "addr:street":"Warner St",
    "iso:country":"CA",
    "sg:address":"1010 Warner St",
    "sg:city":"Moose Jaw",
    "sg:classifiers":[
        {
            "category":"Retail",
            "subcategory":"Repair Shop",
            "type":"Services"
        }
    ],
    "sg:phone":"+1 306 692 2204",
    "sg:postcode":"S6H 5S5",
    "sg:province":"SK",
    "sg:tags":[
        "upholsterer"
    ],
    "wof:name":"D & S Upholstery",
    "wof:placetype":"venue"
},
  "geometry": {"coordinates":[-105.562034607,50.3775024414],"type":"Point"}
}