{
  "type": "Feature",
  "properties": {
    "addr:full":"10 South Ave Spruce Grove AB T7X 4G3",
    "addr:housenumber":"10",
    "addr:postcode":"t7x 4g3",
    "addr:street":"South Ave",
    "iso:country":"CA",
    "sg:address":"10 South Ave",
    "sg:city":"Spruce Grove",
    "sg:classifiers":[
        {
            "category":"Wholesale",
            "subcategory":"Auto Parts",
            "type":"Manufacturing & Wholesale Goods"
        }
    ],
    "sg:phone":"+1 780 962 0082",
    "sg:postcode":"T7X 4G3",
    "sg:province":"AB",
    "sg:tags":[
        "body",
        "automobile",
        "shop"
    ],
    "wof:name":"Part-Stop Auto & Ind Supply",
    "wof:placetype":"venue"
},
  "geometry": {"coordinates":[-118.862190247,55.0251312256],"type":"Point"}
}