{
  "type": "Feature",
  "properties": {
    "addr:full":"540 Rue DE Beauharnois O Montreal QC H2N 1L2",
    "addr:housenumber":"540",
    "addr:postcode":"h2n 1l2",
    "addr:street":"Rue De Beauharnois O",
    "iso:country":"CA",
    "sg:address":"540 Rue DE Beauharnois O",
    "sg:city":"Montreal",
    "sg:classifiers":[
        {
            "category":"Manufacturing",
            "subcategory":"Apparel",
            "type":"Manufacturing & Wholesale Goods"
        }
    ],
    "sg:phone":"+1 514 381 2301",
    "sg:postcode":"H2N 1L2",
    "sg:province":"QC",
    "sg:tags":[
        "garment",
        "disposable"
    ],
    "wof:name":"Titan Limitee",
    "wof:placetype":"venue"
},
  "geometry": {"coordinates":[-73.648476,45.536121],"type":"Point"}
}