{
  "type": "Feature",
  "properties": {
    "addr:full":"4610 Eastgate Pky #2 Mississauga ON L4W 3W6",
    "addr:housenumber":"4610;# 2",
    "addr:postcode":"l4w 3w6",
    "addr:street":"Eastgate Pky",
    "iso:country":"CA",
    "sg:address":"4610 Eastgate Pky #2",
    "sg:city":"Mississauga",
    "sg:classifiers":[
        {
            "category":"Freight",
            "type":"Transportation"
        }
    ],
    "sg:phone":"+1 905 625 5333",
    "sg:postcode":"L4W 3W6",
    "sg:province":"ON",
    "wof:name":"Roe Logistics Inc",
    "wof:placetype":"venue"
},
  "geometry": {"coordinates":[-79.611778,43.639252],"type":"Point"}
}