{
  "type": "Feature",
  "properties": {
    "addr:full":"Langley BC V3A 9J9",
    "addr:postcode":"v3a 9j9",
    "iso:country":"CA",
    "sg:city":"Langley",
    "sg:classifiers":[
        {
            "category":"Shopping",
            "subcategory":"Jewelry",
            "type":"Retail Goods"
        }
    ],
    "sg:phone":"+1 604 530 7213",
    "sg:postcode":"V3A 9J9",
    "sg:province":"BC",
    "sg:tags":[
        "jeweler"
    ],
    "wof:name":"Creative Goldsmiths Ltd",
    "wof:placetype":"venue"
},
  "geometry": {"coordinates":[-122.664131165,49.1132011414],"type":"Point"}
}