{
  "type": "Feature",
  "properties": {
    "addr:full":"13953 Ninth Line Stouffville ON L4A 7X3",
    "addr:housenumber":"13953",
    "addr:postcode":"l4a 7x3",
    "addr:street":"Ninth Line",
    "iso:country":"CA",
    "sg:address":"13953 Ninth Line",
    "sg:city":"Stouffville",
    "sg:classifiers":[
        {
            "category":"Recreation",
            "type":"Entertainment"
        }
    ],
    "sg:phone":"+1 905 640 2347",
    "sg:postcode":"L4A 7X3",
    "sg:province":"ON",
    "sg:tags":[
        "hay",
        "ride"
    ],
    "wof:name":"Magic Hill Farm",
    "wof:placetype":"venue"
},
  "geometry": {"coordinates":[-79.2652893066,44.0123634338],"type":"Point"}
}