{
  "type": "Feature",
  "properties": {
    "iso:country":"CA",
    "sg:address":"1259 1E Av",
    "sg:city":"Lac-Saint-Charles",
    "sg:classifiers":[
        {
            "category":"Personal",
            "subcategory":"Beauty Salon",
            "type":"Services"
        }
    ],
    "sg:phone":"+1 418 849 0548",
    "sg:postcode":"G3G 2T4",
    "sg:province":"QC",
    "wof:name":"Coiffure Martin Rheaume",
    "wof:placetype":"venue"
},
  "geometry": {"coordinates":[-71.375916,46.908199],"type":"Point"}
}