{
  "type": "Feature",
  "properties": {
    "iso:country":"CA",
    "sg:address":"2179 Boul Marcel-Laurin",
    "sg:city":"Saint-Laurent",
    "sg:classifiers":[
        {
            "category":"Government",
            "subcategory":"Office",
            "type":"Public Place"
        }
    ],
    "sg:phone":"+1 514 339 9630",
    "sg:postcode":"H4R 1K4",
    "sg:province":"QC",
    "wof:name":"Societe DE L'Assurance",
    "wof:placetype":"venue"
},
  "geometry": {"coordinates":[-73.702873,45.519497],"type":"Point"}
}