{
  "type": "Feature",
  "properties": {
    "iso:country":"CA",
    "sg:address":"201 Main St E",
    "sg:city":"Milton",
    "sg:classifiers":[
        {
            "category":"Restaurant",
            "type":"Food & Drink"
        }
    ],
    "sg:phone":"+1 905 876 4899",
    "sg:postcode":"L9T 1N7",
    "sg:province":"ON",
    "wof:name":"Ivy Arms",
    "wof:placetype":"venue"
},
  "geometry": {"coordinates":[-79.88372802729999,43.5128288269],"type":"Point"}
}