{
  "type": "Feature",
  "properties": {
    "iso:country":"CA",
    "sg:address":"17 Queen St",
    "sg:city":"Campbellford",
    "sg:classifiers":[
        {
            "category":"Shopping",
            "subcategory":"Computers & Home Electronics",
            "type":"Retail Goods"
        }
    ],
    "sg:phone":"+1 705 653 4165",
    "sg:postcode":"K0L 1L0",
    "sg:province":"ON",
    "sg:tags":[
        "television",
        "radio"
    ],
    "wof:name":"Cunningham Electronics",
    "wof:placetype":"venue"
},
  "geometry": {"coordinates":[-77.799949646,44.309173584],"type":"Point"}
}