{
  "type": "Feature",
  "properties": {
    "addr:full":"220 Crowchild Trail NW Calgary AB T2N 2R2",
    "addr:housenumber":"220",
    "addr:postcode":"t2n 2r2",
    "addr:street":"Crowchild Trail Nw",
    "iso:country":"CA",
    "sg:address":"220 Crowchild Trail NW",
    "sg:city":"Calgary",
    "sg:classifiers":[
        {
            "category":"Shopping",
            "subcategory":"Gifts & Souvenirs",
            "type":"Retail Goods"
        }
    ],
    "sg:phone":"+1 403 270 0631",
    "sg:postcode":"T2N 2R2",
    "sg:province":"AB",
    "sg:tags":[
        "shop"
    ],
    "wof:name":"Ten Thousand Villages",
    "wof:placetype":"venue"
},
  "geometry": {"coordinates":[-114.117645264,51.053855896],"type":"Point"}
}