{
  "type": "Feature",
  "properties": {
    "addr:full":"Markham ON L3R 3W5",
    "addr:postcode":"l3r 3w5",
    "iso:country":"CA",
    "sg:city":"Markham",
    "sg:classifiers":[
        {
            "category":"Home & Garden",
            "subcategory":"Furniture",
            "type":"Retail Goods"
        }
    ],
    "sg:phone":"+1 905 947 9575",
    "sg:postcode":"L3R 3W5",
    "sg:province":"ON",
    "sg:tags":[
        "upholsterer"
    ],
    "wof:name":"Markham Furniture Inc",
    "wof:placetype":"venue"
},
  "geometry": {"coordinates":[-79.3292388916,43.8269844055],"type":"Point"}
}