{
  "type": "Feature",
  "properties": {
    "iso:country":"CA",
    "sg:address":"207 Av Bethany",
    "sg:city":"Lachute",
    "sg:classifiers":[
        {
            "category":"Insurance",
            "subcategory":"Insurance Agent",
            "type":"Services"
        }
    ],
    "sg:phone":"+1 450 562 3727",
    "sg:postcode":"J8H 2M6",
    "sg:province":"QC",
    "wof:name":"Groupe Lyras",
    "wof:placetype":"venue"
},
  "geometry": {"coordinates":[-74.33079528810001,45.6530380249],"type":"Point"}
}