{
  "type": "Feature",
  "properties": {
    "addr:full":"Peterborough ON K9H 7E8",
    "addr:postcode":"k9h 7e8",
    "iso:country":"CA",
    "sg:city":"Peterborough",
    "sg:classifiers":[
        {
            "category":"Banks & Credit Unions",
            "subcategory":"Bank",
            "type":"Services"
        }
    ],
    "sg:phone":"+1 705 750 4800",
    "sg:postcode":"K9H 7E8",
    "sg:province":"ON",
    "wof:name":"Business Development Bank",
    "wof:placetype":"venue"
},
  "geometry": {"coordinates":[-78.31970200000001,44.303616],"type":"Point"}
}