{
  "type": "Feature",
  "properties": {
    "iso:country":"CA",
    "sg:address":"4740 Rue Hochelaga",
    "sg:city":"Montreal",
    "sg:classifiers":[
        {
            "category":"Shopping",
            "subcategory":"Used Merchandise",
            "type":"Retail Goods"
        }
    ],
    "sg:phone":"+1 514 256 4258",
    "sg:postcode":"H1V 1E3",
    "sg:province":"QC",
    "sg:tags":[
        "antique"
    ],
    "wof:name":"Antiquaire Denis",
    "wof:placetype":"venue"
},
  "geometry": {"coordinates":[-73.5437088013,45.5591316223],"type":"Point"}
}