{
  "type": "Feature",
  "properties": {
    "addr:full":"91 Rang Mathieu Victoriaville QC G6P 6R8",
    "addr:housenumber":"91",
    "addr:postcode":"g6p 6r8",
    "addr:street":"Rang Mathieu",
    "iso:country":"CA",
    "sg:address":"91 Rang Mathieu",
    "sg:city":"Victoriaville",
    "sg:classifiers":[
        {
            "category":"Restaurant",
            "type":"Food & Drink"
        }
    ],
    "sg:phone":"+1 819 752 6572",
    "sg:postcode":"G6P 6R8",
    "sg:province":"QC",
    "sg:tags":[
        "bulk",
        "oil",
        "gasoline"
    ],
    "wof:name":"Cantine Bois-Francs Enr",
    "wof:placetype":"venue"
},
  "geometry": {"coordinates":[-71.971954,46.036163],"type":"Point"}
}