{
  "type": "Feature",
  "properties": {
    "addr:full":"735 Broughton St Victoria BC V8W 3H2",
    "addr:housenumber":"735",
    "addr:postcode":"v8w 3h2",
    "addr:street":"Broughton St",
    "iso:country":"CA",
    "sg:address":"735 Broughton St",
    "sg:city":"Victoria",
    "sg:classifiers":[
        {
            "category":"Education",
            "subcategory":"Library",
            "type":"Public Place"
        }
    ],
    "sg:phone":"+1 250 382 7241",
    "sg:postcode":"V8W 3H2",
    "sg:province":"BC",
    "sg:tags":[
        "government"
    ],
    "wof:name":"Greater Victoria Public Libry",
    "wof:placetype":"venue"
},
  "geometry": {"coordinates":[-123.36449399999999,48.423565],"type":"Point"}
}