{
  "type": "Feature",
  "properties": {
    "addr:full":"47 Boul Hymus Pointe-Claire QC H9R 4T2",
    "addr:housenumber":"47",
    "addr:postcode":"h9r 4t2",
    "addr:street":"Boul Hymus",
    "iso:country":"CA",
    "sg:address":"47 Boul Hymus",
    "sg:city":"Pointe-Claire",
    "sg:classifiers":[
        {
            "category":"Manufacturing",
            "subcategory":"Apparel",
            "type":"Manufacturing & Wholesale Goods"
        }
    ],
    "sg:phone":"+1 514 695 3382",
    "sg:postcode":"H9R 4T2",
    "sg:province":"QC",
    "sg:tags":[
        "tarpaulin"
    ],
    "wof:name":"Chameleon Transportation Syst",
    "wof:placetype":"venue"
},
  "geometry": {"coordinates":[-73.795601,45.473755],"type":"Point"}
}