{
  "type": "Feature",
  "properties": {
    "addr:full":"150 Barrette St Vanier ON K1L 8A1",
    "addr:housenumber":"150",
    "addr:postcode":"k1l 8a1",
    "addr:street":"Barrette St",
    "iso:country":"CA",
    "sg:address":"150 Barrette St",
    "sg:city":"Vanier",
    "sg:classifiers":[
        {
            "category":"Building & Trades",
            "subcategory":"Construction",
            "type":"Services"
        }
    ],
    "sg:phone":"+1 613 745 6201",
    "sg:postcode":"K1L 8A1",
    "sg:province":"ON",
    "sg:tags":[
        "repairing",
        "home",
        "improvement",
        "remodeling",
        "contractor"
    ],
    "wof:name":"Jobin Design Construction",
    "wof:placetype":"venue"
},
  "geometry": {"coordinates":[-75.67237091059999,45.4410362244],"type":"Point"}
}