{
  "type": "Feature",
  "properties": {
    "iso:country":"CA",
    "sg:address":"441 Boul Lacombe",
    "sg:city":"Le Gardeur",
    "sg:classifiers":[
        {
            "category":"Shopping",
            "subcategory":"Florist",
            "type":"Retail Goods"
        }
    ],
    "sg:phone":"+1 450 581 4288",
    "sg:postcode":"J5Z 1N9",
    "sg:province":"QC",
    "wof:name":"Fleuriste Marie-Soleil Enr",
    "wof:placetype":"venue"
},
  "geometry": {"coordinates":[-73.4695281982,45.7539367676],"type":"Point"}
}