{
  "type": "Feature",
  "properties": {
    "iso:country":"CA",
    "sg:address":"90 Cholette St",
    "sg:city":"Sturgeon Falls",
    "sg:classifiers":[
        {
            "category":"Social Services",
            "type":"Services"
        }
    ],
    "sg:phone":"+1 705 753 5455",
    "sg:postcode":"P2B 3C1",
    "sg:province":"ON",
    "sg:tags":[
        "organization",
        "welfare"
    ],
    "wof:name":"Carrefour Jeunesse",
    "wof:placetype":"venue"
},
  "geometry": {"coordinates":[-79.91748809809999,46.3593482971],"type":"Point"}
}