{
  "type": "Feature",
  "properties": {
    "iso:country":"CA",
    "sg:address":"1720 Boul Lafleche",
    "sg:city":"Baie-Comeau",
    "sg:classifiers":[
        {
            "category":"Real Estate",
            "subcategory":"Real Estate Agent",
            "type":"Services"
        }
    ],
    "sg:phone":"+1 418 589 3344",
    "sg:postcode":"G5C 1C9",
    "sg:province":"QC",
    "sg:tags":[
        "tool",
        "agency",
        "rental"
    ],
    "wof:name":"Location Sito Inc",
    "wof:placetype":"venue"
},
  "geometry": {"coordinates":[-68.2774963379,49.1953811646],"type":"Point"}
}