{
  "type": "Feature",
  "properties": {
    "addr:full":"227 Rue Richelieu Quebec QC G1R 1J7",
    "addr:housenumber":"227",
    "addr:postcode":"g1r 1j7",
    "addr:street":"Rue Richelieu",
    "iso:country":"CA",
    "sg:address":"227 Rue Richelieu",
    "sg:city":"Quebec",
    "sg:classifiers":[
        {
            "category":"Wholesale",
            "subcategory":"Electrical",
            "type":"Manufacturing & Wholesale Goods"
        }
    ],
    "sg:phone":"+1 418 523 8856",
    "sg:postcode":"G1R 1J7",
    "sg:province":"QC",
    "sg:tags":[
        "electric",
        "motor"
    ],
    "wof:name":"Rochette Electrique Enr",
    "wof:placetype":"venue"
},
  "geometry": {"coordinates":[-71.22514343260001,46.8087043762],"type":"Point"}
}