{
  "type": "Feature",
  "properties": {
    "addr:full":"65 Milvan Dr North York ON M9L 1Y8",
    "addr:housenumber":"65",
    "addr:postcode":"m9l 1y8",
    "addr:street":"Milvan Dr",
    "iso:country":"CA",
    "sg:address":"65 Milvan Dr",
    "sg:city":"North York",
    "sg:classifiers":[
        {
            "category":"Building & Trades",
            "subcategory":"Construction",
            "type":"Services"
        }
    ],
    "sg:phone":"+1 416 743 2813",
    "sg:postcode":"M9L 1Y8",
    "sg:province":"ON",
    "sg:tags":[
        "roofing",
        "contractor"
    ],
    "wof:name":"Dufferin Roofing CO",
    "wof:placetype":"venue"
},
  "geometry": {"coordinates":[-79.55596199999999,43.754314],"type":"Point"}
}