{
  "type": "Feature",
  "properties": {
    "iso:country":"CA",
    "sg:city":"Saint-Laurent",
    "sg:classifiers":[
        {
            "category":"Health Services",
            "subcategory":"Doctor",
            "type":"Services"
        }
    ],
    "sg:phone":"+1 514 744 6444",
    "sg:postcode":"H4L 1Z1",
    "sg:province":"QC",
    "sg:tags":[
        "dentist"
    ],
    "wof:name":"Centre Dentaire Belanger",
    "wof:placetype":"venue"
},
  "geometry": {"coordinates":[-73.6808853149,45.5158081055],"type":"Point"}
}