{
  "type": "Feature",
  "properties": {
    "iso:country":"CA",
    "sg:address":"5 Amber Bay",
    "sg:city":"Morden",
    "sg:classifiers":[
        {
            "category":"Building & Trades",
            "subcategory":"Plumbing",
            "type":"Services"
        }
    ],
    "sg:phone":"+1 204 822 3294",
    "sg:postcode":"R6M 1J1",
    "sg:province":"MB",
    "sg:tags":[
        "contractor"
    ],
    "wof:name":"Bergmann Plumbing & Heating",
    "wof:placetype":"venue"
},
  "geometry": {"coordinates":[-98.1185913086,49.1841926575],"type":"Point"}
}