{
  "type": "Feature",
  "properties": {
    "addr:full":"236 Edwards Ave The Pas MB R9A 1M2",
    "addr:housenumber":"236",
    "addr:postcode":"r9a 1m2",
    "addr:street":"Edwards Ave",
    "iso:country":"CA",
    "sg:address":"236 Edwards Ave",
    "sg:city":"The Pas",
    "sg:classifiers":[
        {
            "category":"Professional",
            "subcategory":"Lawyer & Legal Services",
            "type":"Services"
        }
    ],
    "sg:phone":"+1 204 627 4820",
    "sg:postcode":"R9A 1M2",
    "sg:province":"MB",
    "sg:tags":[
        "attorney"
    ],
    "wof:name":"Legal Aid Manitoba",
    "wof:placetype":"venue"
},
  "geometry": {"coordinates":[-101.251366,53.823872],"type":"Point"}
}