{
  "type": "Feature",
  "properties": {
    "addr:full":"Seaforth ON N0K 1W0",
    "addr:postcode":"n0k 1w0",
    "iso:country":"CA",
    "sg:city":"Seaforth",
    "sg:classifiers":[
        {
            "category":"Manufacturing",
            "subcategory":"Signs",
            "type":"Manufacturing & Wholesale Goods"
        }
    ],
    "sg:phone":"+1 519 527 2200",
    "sg:postcode":"N0K 1W0",
    "sg:province":"ON",
    "wof:name":"Artech",
    "wof:placetype":"venue"
},
  "geometry": {"coordinates":[-81.3937072754,43.5530433655],"type":"Point"}
}