{
  "type": "Feature",
  "properties": {
    "iso:country":"CA",
    "sg:city":"Montreal",
    "sg:classifiers":[
        {
            "category":"Food & Beverages",
            "subcategory":"Groceries & Convenience Stores",
            "type":"Retail Goods"
        }
    ],
    "sg:phone":"+1 514 733 1572",
    "sg:postcode":"H3S 2H8",
    "sg:province":"QC",
    "wof:name":"Depanneur Alexandre Le Grand",
    "wof:placetype":"venue"
},
  "geometry": {"coordinates":[-73.624321,45.507164],"type":"Point"}
}