{
  "type": "Feature",
  "properties": {
    "addr:full":"9 Barrie Blvd St Thomas ON N5P 4B9",
    "addr:housenumber":"9",
    "addr:postcode":"n5p 4b9",
    "addr:street":"Barrie Blvd",
    "iso:country":"CA",
    "sg:address":"9 Barrie Blvd",
    "sg:city":"St Thomas",
    "sg:classifiers":[
        {
            "category":"Manufacturing",
            "subcategory":"Watercraft",
            "type":"Manufacturing & Wholesale Goods"
        }
    ],
    "sg:phone":"+1 519 633 1058",
    "sg:postcode":"N5P 4B9",
    "sg:province":"ON",
    "sg:tags":[
        "boat"
    ],
    "wof:name":"Kanter Yachts Corp",
    "wof:placetype":"venue"
},
  "geometry": {"coordinates":[-81.150764,42.786346],"type":"Point"}
}