{
  "type": "Feature",
  "properties": {
    "addr:full":"Kelowna BC V1Y 4N7",
    "addr:postcode":"v1y 4n7",
    "iso:country":"CA",
    "sg:city":"Kelowna",
    "sg:classifiers":[
        {
            "category":"Manufacturing",
            "subcategory":"Rubber & Plastics",
            "type":"Manufacturing & Wholesale Goods"
        }
    ],
    "sg:phone":"+1 250 868 2217",
    "sg:postcode":"V1Y 4N7",
    "sg:province":"BC",
    "sg:tags":[
        "fitting",
        "hose",
        "coupling"
    ],
    "wof:name":"Goodall Rubber",
    "wof:placetype":"venue"
},
  "geometry": {"coordinates":[-119.458084,49.880104],"type":"Point"}
}