{
  "type": "Feature",
  "properties": {
    "addr:full":"8115 120 St Delta BC V4C 6P7",
    "addr:housenumber":"8115",
    "addr:postcode":"v4c 6p7",
    "addr:street":"120 St",
    "iso:country":"CA",
    "sg:address":"8115 120 St",
    "sg:city":"Delta",
    "sg:classifiers":[
        {
            "category":"Professional",
            "subcategory":"Business Services",
            "type":"Services"
        }
    ],
    "sg:phone":"+1 604 696 2000",
    "sg:postcode":"V4C 6P7",
    "sg:province":"BC",
    "sg:tags":[
        "information",
        "referral",
        "investigator"
    ],
    "wof:name":"Shadow Investigations Ltd",
    "wof:placetype":"venue"
},
  "geometry": {"coordinates":[-122.890503,49.150681],"type":"Point"}
}