{
  "type": "Feature",
  "properties": {
    "addr:full":"192 W 100 N Raymond AB T0K 2S0",
    "addr:housenumber":"192",
    "addr:postcode":"t0k 2s0",
    "addr:street":"W 100 N Raymond",
    "iso:country":"CA",
    "sg:address":"192 W 100 N",
    "sg:city":"Raymond",
    "sg:classifiers":[
        {
            "category":"Building & Trades",
            "subcategory":"Cleaning & Sanitation",
            "type":"Services"
        }
    ],
    "sg:phone":"+1 403 752 3770",
    "sg:postcode":"T0K 2S0",
    "sg:province":"AB",
    "sg:tags":[
        "janitor"
    ],
    "wof:name":"A M Cleaning",
    "wof:placetype":"venue"
},
  "geometry": {"coordinates":[-112.663887024,49.4655189514],"type":"Point"}
}