{
  "type": "Feature",
  "properties": {
    "iso:country":"CA",
    "sg:address":"216 Rang Sainte-Catherine",
    "sg:city":"Saint-Raphael",
    "sg:classifiers":[
        {
            "category":"Farming",
            "subcategory":"Farm",
            "type":"Manufacturing & Wholesale Goods"
        }
    ],
    "sg:phone":"+1 418 243 3222",
    "sg:postcode":"G0R 4C0",
    "sg:province":"QC",
    "wof:name":"Ferme Porasseny Inc",
    "wof:placetype":"venue"
},
  "geometry": {"coordinates":[-70.7550811768,46.7954216003],"type":"Point"}
}