{
  "type": "Feature",
  "properties": {
    "addr:full":"1012 14 Ave Nisku AB T9E 8J5",
    "addr:housenumber":"1012",
    "addr:postcode":"t9e 8j5",
    "addr:street":"14 Ave",
    "iso:country":"CA",
    "sg:address":"1012 14 Ave",
    "sg:city":"Nisku",
    "sg:classifiers":[
        {
            "category":"Manufacturing",
            "subcategory":"Tools & Machinery",
            "type":"Manufacturing & Wholesale Goods"
        }
    ],
    "sg:phone":"+1 780 955 3333",
    "sg:postcode":"T9E 8J5",
    "sg:province":"AB",
    "sg:tags":[
        "machine",
        "shop"
    ],
    "wof:name":"Tps Machining & Welding Ltd",
    "wof:placetype":"venue"
},
  "geometry": {"coordinates":[-113.52796936,53.3174095154],"type":"Point"}
}