{
  "type": "Feature",
  "properties": {
    "addr:full":"1 Bessborough Ave Pinawa MB R0E 1L0",
    "addr:housenumber":"1",
    "addr:postcode":"r0e 1l0",
    "addr:street":"Bessborough Ave",
    "iso:country":"CA",
    "sg:address":"1 Bessborough Ave",
    "sg:city":"Pinawa",
    "sg:classifiers":[
        {
            "category":"Organizations",
            "subcategory":"Religious Organization",
            "type":"Services"
        }
    ],
    "sg:phone":"+1 204 753 2927",
    "sg:postcode":"R0E 1L0",
    "sg:province":"MB",
    "sg:tags":[
        "church"
    ],
    "wof:name":"Pinawa Alliance Church",
    "wof:placetype":"venue"
},
  "geometry": {"coordinates":[-95.88037872309999,50.1457710266],"type":"Point"}
}