{
  "type": "Feature",
  "properties": {
    "addr:full":"462 Grey St London ON N6B 1H3",
    "addr:housenumber":"462",
    "addr:postcode":"n6b 1h3",
    "addr:street":"Grey St",
    "iso:country":"CA",
    "sg:address":"462 Grey St",
    "sg:city":"London",
    "sg:classifiers":[
        {
            "category":"Building & Trades",
            "subcategory":"Plumbing",
            "type":"Services"
        }
    ],
    "sg:phone":"+1 519 439 3014",
    "sg:postcode":"N6B 1H3",
    "sg:province":"ON",
    "sg:tags":[
        "contractor"
    ],
    "wof:name":"Rose Plumbing & Heating Ltd",
    "wof:placetype":"venue"
},
  "geometry": {"coordinates":[-81.23395499999999,42.980057],"type":"Point"}
}