{
  "type": "Feature",
  "properties": {
    "iso:country":"CA",
    "sg:address":"562 College St",
    "sg:city":"Toronto",
    "sg:classifiers":[
        {
            "category":"Health Services",
            "subcategory":"Doctor",
            "type":"Services"
        }
    ],
    "sg:phone":"+1 416 962 7792",
    "sg:postcode":"M6G 1B1",
    "sg:province":"ON",
    "sg:tags":[
        "dentist"
    ],
    "wof:name":"Allen, Lawrence DDS",
    "wof:placetype":"venue"
},
  "geometry": {"coordinates":[-79.412346,43.655674],"type":"Point"}
}