{
  "type": "Feature",
  "properties": {
    "addr:full":"4140 Steeles Ave W # 7 Woodbridge ON L4L 4V3",
    "addr:housenumber":"4140",
    "addr:postcode":"l4l 4v3",
    "addr:street":"Steeles Ave W # 7",
    "iso:country":"CA",
    "sg:address":"4140 Steeles Ave W # 7",
    "sg:city":"Woodbridge",
    "sg:classifiers":[
        {
            "category":"Home & Garden",
            "subcategory":"Building Materials",
            "type":"Retail Goods"
        }
    ],
    "sg:phone":"+1 416 743 4040",
    "sg:postcode":"L4L 4V3",
    "sg:province":"ON",
    "sg:tags":[
        "paint"
    ],
    "wof:name":"Steeles Paint",
    "wof:placetype":"venue"
},
  "geometry": {"coordinates":[-79.556793,43.768322],"type":"Point"}
}