{
  "type": "Feature",
  "properties": {
    "iso:country":"CA",
    "sg:city":"Moncton",
    "sg:classifiers":[
        {
            "category":"Wholesale",
            "subcategory":"Electrical",
            "type":"Manufacturing & Wholesale Goods"
        }
    ],
    "sg:phone":"+1 506 852 3332",
    "sg:postcode":"E1H 3N4",
    "sg:province":"NB",
    "sg:tags":[
        "equipment",
        "marine",
        "supply"
    ],
    "wof:name":"Marindustrial",
    "wof:placetype":"venue"
},
  "geometry": {"coordinates":[-64.73012542719999,46.1333351135],"type":"Point"}
}