{
  "type": "Feature",
  "properties": {
    "addr:full":"4350 Oak St Vancouver BC V6H 2N4",
    "addr:housenumber":"4350",
    "addr:postcode":"v6h 2n4",
    "addr:street":"Oak St",
    "iso:country":"CA",
    "sg:address":"4350 Oak St",
    "sg:city":"Vancouver",
    "sg:classifiers":[
        {
            "category":"Organizations",
            "subcategory":"Religious Organization",
            "type":"Services"
        }
    ],
    "sg:phone":"+1 604 731 4161",
    "sg:postcode":"V6H 2N4",
    "sg:province":"BC",
    "sg:tags":[
        "synagogue"
    ],
    "wof:name":"Beth Israel",
    "wof:placetype":"venue"
},
  "geometry": {"coordinates":[-123.12747192400001,49.2468414307],"type":"Point"}
}