{
  "type": "Feature",
  "properties": {
    "iso:country":"CA",
    "sg:city":"Trois-Rivieres-Ouest",
    "sg:classifiers":[
        {
            "category":"Freight",
            "type":"Transportation"
        }
    ],
    "sg:phone":"+1 819 373 4602",
    "sg:postcode":"G9A 5Z9",
    "sg:province":"QC",
    "sg:tags":[
        "trucking"
    ],
    "wof:name":"Transporteurs En Vrac Region",
    "wof:placetype":"venue"
},
  "geometry": {"coordinates":[-72.572578,46.317871],"type":"Point"}
}