{
  "type": "Feature",
  "properties": {
    "addr:full":"RR 2 Grand Bend ON N0M 1T0",
    "addr:postcode":"n0m 1t0",
    "addr:street":"Rr 2",
    "iso:country":"CA",
    "sg:address":"RR 2",
    "sg:city":"Grand Bend",
    "sg:classifiers":[
        {
            "category":"Building & Trades",
            "subcategory":"Landscaping Services",
            "type":"Services"
        }
    ],
    "sg:phone":"+1 519 238 5451",
    "sg:postcode":"N0M 1T0",
    "sg:province":"ON",
    "sg:tags":[
        "landscape",
        "contractor"
    ],
    "wof:name":"Dave Taylor Tree Svc",
    "wof:placetype":"venue"
},
  "geometry": {"coordinates":[-81.75653076170001,43.3124732971],"type":"Point"}
}