{
  "type": "Feature",
  "properties": {
    "addr:full":"Montreal QC H2K 1C3",
    "addr:postcode":"h2k 1c3",
    "iso:country":"CA",
    "sg:city":"Montreal",
    "sg:classifiers":[
        {
            "category":"Professional",
            "subcategory":"Advertising",
            "type":"Services"
        }
    ],
    "sg:phone":"+1 514 522 4815",
    "sg:postcode":"H2K 1C3",
    "sg:province":"QC",
    "sg:tags":[
        "counselor"
    ],
    "wof:name":"Eureka Media Concept",
    "wof:placetype":"venue"
},
  "geometry": {"coordinates":[-73.5627441406,45.5310668945],"type":"Point"}
}