{
  "type": "Feature",
  "properties": {
    "addr:full":"3 Principale Laverlochere QC J0Z 2P0",
    "addr:housenumber":"3",
    "addr:postcode":"j0z 2p0",
    "addr:street":"Principale Laverlochere",
    "iso:country":"CA",
    "sg:address":"3 Principale",
    "sg:city":"Laverlochere",
    "sg:classifiers":[
        {
            "category":"Organizations",
            "subcategory":"Religious Organization",
            "type":"Services"
        }
    ],
    "sg:phone":"+1 819 765 3131",
    "sg:postcode":"J0Z 2P0",
    "sg:province":"QC",
    "sg:tags":[
        "church"
    ],
    "wof:name":"Presbyteres DE St-Isidore",
    "wof:placetype":"venue"
},
  "geometry": {"coordinates":[-79.30786895750001,47.4269638062],"type":"Point"}
}