{
  "type": "Feature",
  "properties": {
    "addr:full":"137 Elgin St Madoc ON K0K 2K0",
    "addr:housenumber":"137",
    "addr:postcode":"k0k 2k0",
    "addr:street":"Elgin St",
    "iso:country":"CA",
    "sg:address":"137 Elgin St",
    "sg:city":"Madoc",
    "sg:classifiers":[
        {
            "category":"Organizations",
            "subcategory":"Religious Organization",
            "type":"Services"
        }
    ],
    "sg:phone":"+1 613 473 2451",
    "sg:postcode":"K0K 2K0",
    "sg:province":"ON",
    "sg:tags":[
        "church"
    ],
    "wof:name":"Wesleyan & Free Methodist Chr",
    "wof:placetype":"venue"
},
  "geometry": {"coordinates":[-77.467735,44.505131],"type":"Point"}
}