{
  "type": "Feature",
  "properties": {
    "addr:full":"216 Brodie St S Thunder Bay ON P7E 1C2",
    "addr:housenumber":"216",
    "addr:postcode":"p7e 1c2",
    "addr:street":"Brodie St S",
    "iso:country":"CA",
    "sg:address":"216 Brodie St S",
    "sg:city":"Thunder Bay",
    "sg:classifiers":[
        {
            "category":"Education",
            "subcategory":"Library",
            "type":"Public Place"
        }
    ],
    "sg:phone":"+1 807 623 0925",
    "sg:postcode":"P7E 1C2",
    "sg:province":"ON",
    "sg:tags":[
        "government"
    ],
    "wof:name":"Brodie Resource Library",
    "wof:placetype":"venue"
},
  "geometry": {"coordinates":[-89.24638400000001,48.382118],"type":"Point"}
}