{
  "type": "Feature",
  "properties": {
    "addr:full":"380 12E Av Ferme-Neuve QC J0W 1C0",
    "addr:housenumber":"380",
    "addr:postcode":"j0w 1c0",
    "addr:street":"12E Av Ferme-Neuve",
    "iso:country":"CA",
    "sg:address":"380 12E Av",
    "sg:city":"Ferme-Neuve",
    "sg:classifiers":[
        {
            "category":"Personal",
            "subcategory":"Shoe Repair & Shine",
            "type":"Services"
        }
    ],
    "sg:phone":"+1 819 587 3313",
    "sg:postcode":"J0W 1C0",
    "sg:province":"QC",
    "sg:tags":[
        "repairing",
        "boot"
    ],
    "wof:name":"Pilon Sports Enr",
    "wof:placetype":"venue"
},
  "geometry": {"coordinates":[-75.45026397709999,46.7046813965],"type":"Point"}
}