{
  "type": "Feature",
  "properties": {
    "addr:full":"800 Rte Louis Hemon Peribonka QC G0W 2G0",
    "addr:housenumber":"800",
    "addr:postcode":"g0w 2g0",
    "addr:street":"Rte Louis Hemon Peribonka",
    "iso:country":"CA",
    "sg:address":"800 Rte Louis Hemon",
    "sg:city":"Peribonka",
    "sg:classifiers":[
        {
            "category":"Food & Beverages",
            "subcategory":"Groceries & Convenience Stores",
            "type":"Retail Goods"
        }
    ],
    "sg:phone":"+1 418 374 2004",
    "sg:postcode":"G0W 2G0",
    "sg:province":"QC",
    "wof:name":"Depanneur Bertrand Brassard",
    "wof:placetype":"venue"
},
  "geometry": {"coordinates":[-72.03215026860001,48.80676651],"type":"Point"}
}