{
  "type": "Feature",
  "properties": {
    "iso:country":"CA",
    "sg:address":"425 Adelaide St W",
    "sg:city":"Toronto",
    "sg:classifiers":[
        {
            "category":"Wholesale",
            "subcategory":"Apparel",
            "type":"Manufacturing & Wholesale Goods"
        }
    ],
    "sg:phone":"+1 905 761 5146",
    "sg:postcode":"M5V 3C1",
    "sg:province":"ON",
    "sg:tags":[
        "clothing"
    ],
    "wof:name":"Furs By al Gelfant",
    "wof:placetype":"venue"
},
  "geometry": {"coordinates":[-79.39766693120001,43.6461753845],"type":"Point"}
}