{
  "type": "Feature",
  "properties": {
    "addr:full":"620 Portland St Dartmouth NS B2W 2M3",
    "addr:housenumber":"620",
    "addr:postcode":"b2w 2m3",
    "addr:street":"Portland St",
    "iso:country":"CA",
    "sg:address":"620 Portland St",
    "sg:city":"Dartmouth",
    "sg:classifiers":[
        {
            "category":"Restaurant",
            "type":"Food & Drink"
        }
    ],
    "sg:phone":"+1 902 434 8814",
    "sg:postcode":"B2W 2M3",
    "sg:province":"NS",
    "wof:name":"Steak & Stein Family Restaurnt",
    "wof:placetype":"venue"
},
  "geometry": {"coordinates":[-63.529358,44.670807],"type":"Point"}
}