{
  "type": "Feature",
  "properties": {
    "addr:full":"348 Boul Des Bois-Francs N Victoriaville QC G6P 1G7",
    "addr:housenumber":"348",
    "addr:postcode":"g6p 1g7",
    "addr:street":"Boul Des Bois-Francs N",
    "iso:country":"CA",
    "sg:address":"348 Boul Des Bois-Francs N",
    "sg:city":"Victoriaville",
    "sg:classifiers":[
        {
            "category":"Retail",
            "subcategory":"Animal Services",
            "type":"Services"
        }
    ],
    "sg:phone":"+1 819 758 6107",
    "sg:postcode":"G6P 1G7",
    "sg:province":"QC",
    "sg:tags":[
        "pet",
        "grooming",
        "washing"
    ],
    "wof:name":"Tonte & Toilettage J Provencal",
    "wof:placetype":"venue"
},
  "geometry": {"coordinates":[-71.9620513916,46.0646629333],"type":"Point"}
}