{
  "type": "Feature",
  "properties": {
    "addr:full":"2918 Eglinton Ave E Scarborough ON M1J 2E4",
    "addr:housenumber":"2918",
    "addr:postcode":"m1j 2e4",
    "addr:street":"Eglinton Ave E",
    "iso:country":"CA",
    "sg:address":"2918 Eglinton Ave E",
    "sg:city":"Scarborough",
    "sg:classifiers":[
        {
            "category":"Autos & Motor Vehicles",
            "subcategory":"Auto Supplies",
            "type":"Retail Goods"
        }
    ],
    "sg:phone":"+1 416 289 7777",
    "sg:postcode":"M1J 2E4",
    "sg:province":"ON",
    "sg:tags":[
        "repairing",
        "automobile",
        "parts"
    ],
    "wof:name":"Best Eglinton Auto Repair",
    "wof:placetype":"venue"
},
  "geometry": {"coordinates":[-79.23699951170001,43.7393226624],"type":"Point"}
}