{
  "type": "Feature",
  "properties": {
    "addr:full":"216 Main St Big Cove NB E4W 2X9",
    "addr:housenumber":"216",
    "addr:postcode":"e4w 2x9",
    "addr:street":"Main St",
    "iso:country":"CA",
    "sg:address":"216 Main St",
    "sg:city":"Big Cove",
    "sg:classifiers":[
        {
            "category":"Retail",
            "subcategory":"Car Wash",
            "type":"Services"
        }
    ],
    "sg:phone":"+1 506 533 1553",
    "sg:postcode":"E4W 2X9",
    "sg:province":"NB",
    "sg:tags":[
        "glass",
        "detail",
        "automobile"
    ],
    "wof:name":"Cormier's Auto Glass & Dtlng",
    "wof:placetype":"venue"
},
  "geometry": {"coordinates":[-64.984467,46.586258],"type":"Point"}
}