{
  "type": "Feature",
  "properties": {
    "iso:country":"CA",
    "sg:address":"150 Chatham St",
    "sg:city":"Hamilton",
    "sg:classifiers":[
        {
            "category":"Manufacturing",
            "subcategory":"Apparel",
            "type":"Manufacturing & Wholesale Goods"
        }
    ],
    "sg:phone":"+1 905 777 0700",
    "sg:postcode":"L8P 2B6",
    "sg:province":"ON",
    "sg:tags":[
        "hat"
    ],
    "wof:name":"Heaslip Headwear",
    "wof:placetype":"venue"
},
  "geometry": {"coordinates":[-79.894318,43.256313],"type":"Point"}
}