{
  "type": "Feature",
  "properties": {
    "addr:full":"PO Box 1832 STN Del.centre Yorkton SK S3N 3R2",
    "addr:housenumber":"po",
    "addr:postcode":"1832;s3n 3r2",
    "addr:street":"Box",
    "iso:country":"CA",
    "sg:address":"PO Box 1832 STN Del.centre",
    "sg:city":"Yorkton",
    "sg:classifiers":[
        {
            "category":"Organizations",
            "subcategory":"Religious Organization",
            "type":"Services"
        }
    ],
    "sg:phone":"+1 306 783 3001",
    "sg:postcode":"S3N 3R2",
    "sg:province":"SK",
    "sg:tags":[
        "church"
    ],
    "wof:name":"Yorkton Apostolic Church",
    "wof:placetype":"venue"
},
  "geometry": {"coordinates":[-102.449874878,51.2040557861],"type":"Point"}
}