{
  "type": "Feature",
  "properties": {
    "addr:full":"Hull QC J8Z 1V4",
    "addr:postcode":"j8z 1v4",
    "iso:country":"CA",
    "sg:city":"Hull",
    "sg:classifiers":[
        {
            "category":"Manufacturing",
            "subcategory":"Metals",
            "type":"Manufacturing & Wholesale Goods"
        }
    ],
    "sg:phone":"+1 819 772 2080",
    "sg:postcode":"J8Z 1V4",
    "sg:province":"QC",
    "sg:tags":[
        "tank"
    ],
    "wof:name":"Construction Aquabec Inc",
    "wof:placetype":"venue"
},
  "geometry": {"coordinates":[-75.73277299999999,45.463657],"type":"Point"}
}