{
  "type": "Feature",
  "properties": {
    "addr:full":"27 Av DE Gaspe O Saint-Jean-Port-Joli QC G0R 3G0",
    "addr:postcode":"g0r 3g0",
    "addr:street":"27 Av De Gaspe O",
    "iso:country":"CA",
    "sg:address":"27 Av DE Gaspe O",
    "sg:city":"Saint-Jean-Port-Joli",
    "sg:classifiers":[
        {
            "category":"Restaurant",
            "type":"Food & Drink"
        }
    ],
    "sg:phone":"+1 418 598 6266",
    "sg:postcode":"G0R 3G0",
    "sg:province":"QC",
    "sg:tags":[
        "motel",
        "hotel"
    ],
    "wof:name":"Restaurant St-Jean Enr",
    "wof:placetype":"venue"
},
  "geometry": {"coordinates":[-70.2693862915,47.2158584595],"type":"Point"}
}