{
  "type": "Feature",
  "properties": {
    "iso:country":"CA",
    "sg:city":"Winnipeg",
    "sg:classifiers":[
        {
            "category":"Insurance",
            "subcategory":"Insurance Agent",
            "type":"Services"
        }
    ],
    "sg:phone":"+1 204 956 2802",
    "sg:postcode":"R3B 3K6",
    "sg:province":"MB",
    "wof:name":"National Life Assurance CO",
    "wof:placetype":"venue"
},
  "geometry": {"coordinates":[-97.13913,49.89539],"type":"Point"}
}