{
  "type": "Feature",
  "properties": {
    "addr:full":"48 Dennis St W Gladstone MB R0J 0T0",
    "addr:housenumber":"48",
    "addr:postcode":"r0j 0t0",
    "addr:street":"Dennis St W",
    "iso:country":"CA",
    "sg:address":"48 Dennis St W",
    "sg:city":"Gladstone",
    "sg:classifiers":[
        {
            "category":"Government",
            "subcategory":"Office",
            "type":"Public Place"
        }
    ],
    "sg:phone":"+1 204 385 6622",
    "sg:postcode":"R0J 0T0",
    "sg:province":"MB",
    "wof:name":"Manitoba Conservation District",
    "wof:placetype":"venue"
},
  "geometry": {"coordinates":[-98.9507522583,50.2254219055],"type":"Point"}
}