{
  "type": "Feature",
  "properties": {
    "addr:full":"Zephyr ON L0E 1T0",
    "addr:postcode":"l0e 1t0",
    "iso:country":"CA",
    "sg:city":"Zephyr",
    "sg:classifiers":[
        {
            "category":"Building & Trades",
            "subcategory":"Landscaping Services",
            "type":"Services"
        }
    ],
    "sg:phone":"+1 905 473 5244",
    "sg:postcode":"L0E 1T0",
    "sg:province":"ON",
    "sg:tags":[
        "topsoil"
    ],
    "wof:name":"Zephyr Peat Land Harvesting",
    "wof:placetype":"venue"
},
  "geometry": {"coordinates":[-79.24588775629999,44.2148628235],"type":"Point"}
}