{
  "type": "Feature",
  "properties": {
    "addr:full":"5548 Boul Bourque Rock Forest QC J1N 1H3",
    "addr:housenumber":"5548",
    "addr:postcode":"j1n 1h3",
    "addr:street":"Boul Bourque",
    "iso:country":"CA",
    "sg:address":"5548 Boul Bourque",
    "sg:city":"Rock Forest",
    "sg:classifiers":[
        {
            "category":"Retail",
            "subcategory":"Auto Rental",
            "type":"Services"
        }
    ],
    "sg:phone":"+1 819 864 8550",
    "sg:postcode":"J1N 1H3",
    "sg:province":"QC",
    "sg:tags":[
        "renting",
        "leasing",
        "trailer"
    ],
    "wof:name":"Location Rgc Inc",
    "wof:placetype":"venue"
},
  "geometry": {"coordinates":[-72.00282300000001,45.362823],"type":"Point"}
}