{
  "type": "Feature",
  "properties": {
    "addr:full":"18 Rue Des Eboulis Victoriaville QC G6T 1M5",
    "addr:housenumber":"18",
    "addr:postcode":"g6t 1m5",
    "addr:street":"Rue Des Eboulis",
    "iso:country":"CA",
    "sg:address":"18 Rue Des Eboulis",
    "sg:city":"Victoriaville",
    "sg:classifiers":[
        {
            "category":"Health Services",
            "subcategory":"Doctor",
            "type":"Services"
        }
    ],
    "sg:phone":"+1 819 758 2920",
    "sg:postcode":"G6T 1M5",
    "sg:province":"QC",
    "sg:tags":[
        "physiotherapist",
        "clinic"
    ],
    "wof:name":"Physiotherapie Des Bois-Francs",
    "wof:placetype":"venue"
},
  "geometry": {"coordinates":[-71.9856796265,46.0701828003],"type":"Point"}
}