{
  "type": "Feature",
  "properties": {
    "addr:full":"Main St Burr SK S0K 0T0",
    "addr:postcode":"s0k 0t0",
    "addr:street":"Main St",
    "iso:country":"CA",
    "sg:address":"Main St",
    "sg:city":"Burr",
    "sg:classifiers":[
        {
            "category":"Recreation",
            "type":"Entertainment"
        }
    ],
    "sg:phone":"+1 306 682 4463",
    "sg:postcode":"S0K 0T0",
    "sg:province":"SK",
    "sg:tags":[
        "hall",
        "auditorium"
    ],
    "wof:name":"Burr Hall",
    "wof:placetype":"venue"
},
  "geometry": {"coordinates":[-105.143974,52.056278],"type":"Point"}
}