{
  "type": "Feature",
  "properties": {
    "addr:full":"16727 116 Ave NW Edmonton AB T5M 3V1",
    "addr:housenumber":"16727",
    "addr:postcode":"t5m 3v1",
    "addr:street":"116 Ave Nw",
    "iso:country":"CA",
    "sg:address":"16727 116 Ave NW",
    "sg:city":"Edmonton",
    "sg:classifiers":[
        {
            "category":"Home & Garden",
            "subcategory":"Building Materials",
            "type":"Retail Goods"
        }
    ],
    "sg:phone":"+1 780 452 4966",
    "sg:postcode":"T5M 3V1",
    "sg:province":"AB",
    "sg:tags":[
        "insulation",
        "heat"
    ],
    "wof:name":"Burnaby Insulation Supplies",
    "wof:placetype":"venue"
},
  "geometry": {"coordinates":[-113.52372699999999,53.629776],"type":"Point"}
}