{
  "type": "Feature",
  "properties": {
    "addr:full":"6440 Rue Des Erables Saint-Emile QC G3E 1L2",
    "addr:housenumber":"6440",
    "addr:postcode":"g3e 1l2",
    "addr:street":"Rue Des Erables Saint-Emile",
    "iso:country":"CA",
    "sg:address":"6440 Rue Des Erables",
    "sg:city":"Saint-Emile",
    "sg:classifiers":[
        {
            "category":"Shopping",
            "subcategory":"Pharmacy",
            "type":"Retail Goods"
        }
    ],
    "sg:phone":"+1 418 842 6745",
    "sg:postcode":"G3E 1L2",
    "sg:province":"QC",
    "wof:name":"Pharmacie Catherine Tremblay",
    "wof:placetype":"venue"
},
  "geometry": {"coordinates":[-71.33708190919999,46.8712081909],"type":"Point"}
}