{
  "type": "Feature",
  "properties": {
    "addr:full":"St. John's NL A1C 6K3",
    "addr:postcode":"a1c 6k3",
    "iso:country":"CA",
    "sg:city":"St. John's",
    "sg:classifiers":[
        {
            "category":"Real Estate",
            "subcategory":"Real Estate Agent",
            "type":"Services"
        }
    ],
    "sg:phone":"+1 709 739 6300",
    "sg:postcode":"A1C 6K3",
    "sg:province":"NL",
    "sg:tags":[
        "management"
    ],
    "wof:name":"Fortis Properties Corp",
    "wof:placetype":"venue"
},
  "geometry": {"coordinates":[-52.7143859863,47.5566177368],"type":"Point"}
}