{
  "type": "Feature",
  "properties": {
    "addr:full":"Saint-Elzear-DE-Bonaventure QC G0C 2W0",
    "addr:postcode":"g0c 2w0",
    "iso:country":"CA",
    "sg:city":"Saint-Elzear-DE-Bonaventure",
    "sg:classifiers":[
        {
            "category":"Retail",
            "subcategory":"Repair Shop",
            "type":"Services"
        }
    ],
    "sg:phone":"+1 418 534 3380",
    "sg:postcode":"G0C 2W0",
    "sg:province":"QC",
    "sg:tags":[
        "appliance"
    ],
    "wof:name":"Babin, Gerard",
    "wof:placetype":"venue"
},
  "geometry": {"coordinates":[-65.494446,48.045422],"type":"Point"}
}