{
  "type": "Feature",
  "properties": {
    "addr:full":"61 Industial Ave Petawawa ON K8H 2W8",
    "addr:housenumber":"61",
    "addr:postcode":"k8h 2w8",
    "addr:street":"Industial Ave",
    "iso:country":"CA",
    "sg:address":"61 Industial Ave",
    "sg:city":"Petawawa",
    "sg:classifiers":[
        {
            "category":"Manufacturing",
            "subcategory":"Lumber",
            "type":"Manufacturing & Wholesale Goods"
        }
    ],
    "sg:phone":"+1 613 687 0222",
    "sg:postcode":"K8H 2W8",
    "sg:province":"ON",
    "sg:tags":[
        "planing",
        "mills"
    ],
    "wof:name":"Forest Valley Lumber",
    "wof:placetype":"venue"
},
  "geometry": {"coordinates":[-77.2580795288,45.876033783],"type":"Point"}
}