{
  "type": "Feature",
  "properties": {
    "addr:full":"Surrey BC V3R 0R8",
    "addr:postcode":"v3r 0r8",
    "iso:country":"CA",
    "sg:city":"Surrey",
    "sg:classifiers":[
        {
            "category":"Retail",
            "subcategory":"Laundry & Dry Cleaning",
            "type":"Services"
        }
    ],
    "sg:phone":"+1 604 580 1136",
    "sg:postcode":"V3R 0R8",
    "sg:province":"BC",
    "sg:tags":[
        "cleaners",
        "rug",
        "carpet"
    ],
    "wof:name":"Pro Carpet Care",
    "wof:placetype":"venue"
},
  "geometry": {"coordinates":[-122.852897644,49.2131881714],"type":"Point"}
}