{
  "type": "Feature",
  "properties": {
    "addr:full":"573 Rue Richelieu Saint-Marc-Sur-Richelieu QC J0L 2E0",
    "addr:housenumber":"573",
    "addr:postcode":"j0l 2e0",
    "addr:street":"Rue Richelieu",
    "iso:country":"CA",
    "sg:address":"573 Rue Richelieu",
    "sg:city":"Saint-Marc-Sur-Richelieu",
    "sg:classifiers":[
        {
            "category":"Retail",
            "subcategory":"Repair Shop",
            "type":"Services"
        }
    ],
    "sg:phone":"+1 450 584 2807",
    "sg:postcode":"J0L 2E0",
    "sg:province":"QC",
    "sg:tags":[
        "clocks",
        "parts"
    ],
    "wof:name":"A & D Pelletier Horloger Enr",
    "wof:placetype":"venue"
},
  "geometry": {"coordinates":[-73.193787,45.675705],"type":"Point"}
}