{
  "type": "Feature",
  "properties": {
    "addr:full":"270 Rue Saint-Paul Quebec QC G1K 3W7",
    "addr:housenumber":"270",
    "addr:postcode":"g1k 3w7",
    "addr:street":"Rue Saint-Paul",
    "iso:country":"CA",
    "sg:address":"270 Rue Saint-Paul",
    "sg:city":"Quebec",
    "sg:classifiers":[
        {
            "category":"Autos & Motor Vehicles",
            "subcategory":"Fuel & Gas Station",
            "type":"Retail Goods"
        }
    ],
    "sg:phone":"+1 418 692 1452",
    "sg:postcode":"G1K 3W7",
    "sg:province":"QC",
    "sg:tags":[
        "oil"
    ],
    "wof:name":"Stationnement St-Paul",
    "wof:placetype":"venue"
},
  "geometry": {"coordinates":[-71.210869,46.817192],"type":"Point"}
}