{
  "type": "Feature",
  "properties": {
    "addr:full":"420 Camden Cir Mississauga ON L4Z 2P4",
    "addr:housenumber":"420",
    "addr:postcode":"l4z 2p4",
    "addr:street":"Camden Cir",
    "iso:country":"CA",
    "sg:address":"420 Camden Cir",
    "sg:city":"Mississauga",
    "sg:classifiers":[
        {
            "category":"Professional",
            "subcategory":"Art Services",
            "type":"Services"
        }
    ],
    "sg:phone":"+1 905 890 3333",
    "sg:postcode":"L4Z 2P4",
    "sg:province":"ON",
    "sg:tags":[
        "photographer"
    ],
    "wof:name":"Alan Mc Kenzie Photography",
    "wof:placetype":"venue"
},
  "geometry": {"coordinates":[-79.63865699999999,43.613586],"type":"Point"}
}