{
  "type": "Feature",
  "properties": {
    "iso:country":"CA",
    "sg:address":"420 Camden Cir",
    "sg:city":"Mississauga",
    "sg:classifiers":[
        {
            "category":"Professional",
            "subcategory":"Art Services",
            "type":"Services"
        }
    ],
    "sg:phone":"+1 905 890 3333",
    "sg:postcode":"L4Z 2P4",
    "sg:province":"ON",
    "sg:tags":[
        "photographer"
    ],
    "wof:name":"Alan Mc Kenzie Photography",
    "wof:placetype":"venue"
},
  "geometry": {"coordinates":[-79.638657,43.613586],"type":"Point"}
}