{
  "type": "Feature",
  "properties": {
    "addr:full":"Calgary AB T2E 7C8",
    "addr:postcode":"t2e 7c8",
    "iso:country":"CA",
    "sg:city":"Calgary",
    "sg:classifiers":[
        {
            "category":"Retail",
            "subcategory":"Auto Repair",
            "type":"Services"
        }
    ],
    "sg:phone":"+1 403 250 3961",
    "sg:postcode":"T2E 7C8",
    "sg:province":"AB",
    "sg:tags":[
        "repairing",
        "automobile"
    ],
    "wof:name":"Elmo's Automotive Ltd",
    "wof:placetype":"venue"
},
  "geometry": {"coordinates":[-114.019340515,51.0812759399],"type":"Point"}
}