{
  "type": "Feature",
  "properties": {
    "addr:full":"2864 Mccoomb Dr Coquitlam BC V3B 6B3",
    "addr:housenumber":"2864",
    "addr:postcode":"v3b 6b3",
    "addr:street":"Mccoomb Dr",
    "iso:country":"CA",
    "sg:address":"2864 Mccoomb Dr",
    "sg:city":"Coquitlam",
    "sg:classifiers":[
        {
            "category":"Social Services",
            "subcategory":"Child Care",
            "type":"Services"
        }
    ],
    "sg:phone":"+1 604 464 6442",
    "sg:postcode":"V3B 6B3",
    "sg:province":"BC",
    "wof:name":"Funshine Learning Ctr",
    "wof:placetype":"venue"
},
  "geometry": {"coordinates":[-122.805290222,49.281955719],"type":"Point"}
}