{
  "type": "Feature",
  "properties": {
    "addr:full":"154 Lombard St Smiths Falls ON K7A 5B8",
    "addr:housenumber":"154",
    "addr:postcode":"k7a 5b8",
    "addr:street":"Lombard St",
    "iso:country":"CA",
    "sg:address":"154 Lombard St",
    "sg:city":"Smiths Falls",
    "sg:classifiers":[
        {
            "category":"Freight",
            "type":"Transportation"
        }
    ],
    "sg:phone":"+1 613 283 0574",
    "sg:postcode":"K7A 5B8",
    "sg:province":"ON",
    "sg:tags":[
        "commercial",
        "storage"
    ],
    "wof:name":"Smiths Falls Mini Storage",
    "wof:placetype":"venue"
},
  "geometry": {"coordinates":[-76.0215148926,44.9025840759],"type":"Point"}
}