{
  "type": "Feature",
  "properties": {
    "addr:full":"6824 Glacier Gulch Rd Smithers BC V0J 2N2",
    "addr:housenumber":"6824",
    "addr:postcode":"v0j 2n2",
    "addr:street":"Glacier Gulch Rd",
    "iso:country":"CA",
    "sg:address":"6824 Glacier Gulch Rd",
    "sg:city":"Smithers",
    "sg:classifiers":[
        {
            "category":"Professional",
            "subcategory":"Engineering",
            "type":"Services"
        }
    ],
    "sg:phone":"+1 250 847 5966",
    "sg:postcode":"V0J 2N2",
    "sg:province":"BC",
    "sg:tags":[
        "engineer"
    ],
    "wof:name":"Outback Aviation",
    "wof:placetype":"venue"
},
  "geometry": {"coordinates":[-127.168128967,54.7828025818],"type":"Point"}
}