{
  "type": "Feature",
  "properties": {
    "addr:full":"3213 110A St NW Edmonton AB T6J 3G3",
    "addr:housenumber":"3213",
    "addr:postcode":"t6j 3g3",
    "addr:street":"110A St Nw",
    "iso:country":"CA",
    "sg:address":"3213 110A St NW",
    "sg:city":"Edmonton",
    "sg:classifiers":[
        {
            "category":"Wholesale",
            "subcategory":"Durable Goods & Equipment",
            "type":"Manufacturing & Wholesale Goods"
        }
    ],
    "sg:phone":"+1 780 436 2230",
    "sg:postcode":"T6J 3G3",
    "sg:province":"AB",
    "sg:tags":[
        "exporter"
    ],
    "wof:name":"Full Way Intl Inc",
    "wof:placetype":"venue"
},
  "geometry": {"coordinates":[-113.51415252699999,53.464012146],"type":"Point"}
}