{
  "type": "Feature",
  "properties": {
    "addr:full":"8166 Boul Maurice-Duplessis Montreal QC H1E 2Y5",
    "addr:housenumber":"8166",
    "addr:postcode":"h1e 2y5",
    "addr:street":"Boul Maurice-Duplessis",
    "iso:country":"CA",
    "sg:address":"8166 Boul Maurice-Duplessis",
    "sg:city":"Montreal",
    "sg:classifiers":[
        {
            "category":"Wholesale",
            "subcategory":"Fruits & Vegetables",
            "type":"Manufacturing & Wholesale Goods"
        }
    ],
    "sg:phone":"+1 514 643 0690",
    "sg:postcode":"H1E 2Y5",
    "sg:province":"QC",
    "wof:name":"Produits Lomeck",
    "wof:placetype":"venue"
},
  "geometry": {"coordinates":[-73.586792,45.633263],"type":"Point"}
}