{
  "type": "Feature",
  "properties": {
    "addr:full":"Quebec QC G1K 8K6",
    "addr:postcode":"g1k 8k6",
    "iso:country":"CA",
    "sg:city":"Quebec",
    "sg:classifiers":[
        {
            "category":"Professional",
            "subcategory":"Lawyer & Legal Services",
            "type":"Services"
        }
    ],
    "sg:phone":"+1 418 529 0301",
    "sg:postcode":"G1K 8K6",
    "sg:province":"QC",
    "sg:tags":[
        "attorney"
    ],
    "wof:name":"Barreau Du Quebec",
    "wof:placetype":"venue"
},
  "geometry": {"coordinates":[-71.215591,46.819298],"type":"Point"}
}