{
  "type": "Feature",
  "properties": {
    "addr:full":"99 Ontario St S Grand Bend ON N0M 1T0",
    "addr:housenumber":"99",
    "addr:postcode":"n0m 1t0",
    "addr:street":"Ontario St S",
    "iso:country":"CA",
    "sg:address":"99 Ontario St S",
    "sg:city":"Grand Bend",
    "sg:classifiers":[
        {
            "category":"Restaurant",
            "type":"Food & Drink"
        }
    ],
    "sg:phone":"+1 519 238 8330",
    "sg:postcode":"N0M 1T0",
    "sg:province":"ON",
    "sg:tags":[
        "pizza"
    ],
    "wof:name":"Pizza Delight",
    "wof:placetype":"venue"
},
  "geometry": {"coordinates":[-81.760712,43.307682],"type":"Point"}
}