{
  "type": "Feature",
  "properties": {
    "iso:country":"CA",
    "sg:city":"Anjou",
    "sg:classifiers":[
        {
            "category":"Shopping",
            "type":"Retail Goods"
        }
    ],
    "sg:phone":"+1 514 493 8891",
    "sg:postcode":"H1M 1W9",
    "sg:province":"QC",
    "sg:tags":[
        "cosmetic",
        "perfume"
    ],
    "wof:name":"Centre DE Beaute Yves Rocher",
    "wof:placetype":"venue"
},
  "geometry": {"coordinates":[-73.539665,45.610252],"type":"Point"}
}