{
  "type": "Feature",
  "properties": {
    "addr:full":"1112 Boul Raymond Beauport QC G1B 2P3",
    "addr:housenumber":"1112",
    "addr:postcode":"g1b 2p3",
    "addr:street":"Boul Raymond",
    "iso:country":"CA",
    "sg:address":"1112 Boul Raymond",
    "sg:city":"Beauport",
    "sg:classifiers":[
        {
            "category":"Autos & Motor Vehicles",
            "subcategory":"Automobile Sales",
            "type":"Retail Goods"
        }
    ],
    "sg:phone":"+1 418 667 6243",
    "sg:postcode":"G1B 2P3",
    "sg:province":"QC",
    "sg:tags":[
        "car",
        "dealer"
    ],
    "wof:name":"Concept Amc Inc",
    "wof:placetype":"venue"
},
  "geometry": {"coordinates":[-71.1921157837,46.9094429016],"type":"Point"}
}