{
  "type": "Feature",
  "properties": {
    "addr:full":"Lac Du Bonnet MB R0E 1A0",
    "addr:postcode":"r0e 1a0",
    "iso:country":"CA",
    "sg:city":"Lac Du Bonnet",
    "sg:classifiers":[
        {
            "category":"Travel",
            "subcategory":"Campground",
            "type":"Entertainment"
        }
    ],
    "sg:phone":"+1 204 345 2993",
    "sg:postcode":"R0E 1A0",
    "sg:province":"MB",
    "wof:name":"Poplar Bay Park Tourist Camp",
    "wof:placetype":"venue"
},
  "geometry": {"coordinates":[-96.52267500000001,50.063835],"type":"Point"}
}