{
  "type": "Feature",
  "properties": {
    "addr:full":"Cache Creek BC V0K 1H0",
    "addr:postcode":"v0k 1h0",
    "iso:country":"CA",
    "sg:city":"Cache Creek",
    "sg:classifiers":[
        {
            "category":"Wholesale",
            "subcategory":"Scrap",
            "type":"Manufacturing & Wholesale Goods"
        }
    ],
    "sg:phone":"+1 250 457 6464",
    "sg:postcode":"V0K 1H0",
    "sg:province":"BC",
    "sg:tags":[
        "waste"
    ],
    "wof:name":"Wastech Services Ltd",
    "wof:placetype":"venue"
},
  "geometry": {"coordinates":[-121.316856384,50.789642334],"type":"Point"}
}