{
  "type": "Feature",
  "properties": {
    "addr:full":"404 Rossland Ave Trail BC V1R 3M8",
    "addr:housenumber":"404",
    "addr:postcode":"bc v1r 3m8",
    "addr:street":"Rossland Ave Trail",
    "iso:country":"CA",
    "sg:address":"404 Rossland Ave",
    "sg:city":"Trail",
    "sg:classifiers":[
        {
            "category":"Social Services",
            "type":"Services"
        }
    ],
    "sg:phone":"+1 250 364 1718",
    "sg:postcode":"V1R 3M8",
    "sg:province":"BC",
    "sg:tags":[
        "crisis",
        "center"
    ],
    "wof:name":"Trail Family & Individual",
    "wof:placetype":"venue"
},
  "geometry": {"coordinates":[-117.721558,49.098232],"type":"Point"}
}