{
  "type": "Feature",
  "properties": {
    "iso:country":"CA",
    "sg:address":"5142 Still Creek Ave",
    "sg:city":"Burnaby",
    "sg:classifiers":[
        {
            "category":"Manufacturing",
            "subcategory":"Apparel",
            "type":"Manufacturing & Wholesale Goods"
        }
    ],
    "sg:phone":"+1 604 293 1863",
    "sg:postcode":"V5C 4E4",
    "sg:province":"BC",
    "sg:tags":[
        "sign"
    ],
    "wof:name":"Accord Pacific Enterprises Ltd",
    "wof:placetype":"venue"
},
  "geometry": {"coordinates":[-122.98948669400001,49.2607192993],"type":"Point"}
}