{
  "type": "Feature",
  "properties": {
    "addr:full":"149 Kent St Ottawa ON K1P 5P3",
    "addr:housenumber":"149",
    "addr:postcode":"k1p 5p3",
    "addr:street":"Kent St",
    "iso:country":"CA",
    "sg:address":"149 Kent St",
    "sg:city":"Ottawa",
    "sg:classifiers":[
        {
            "category":"Restaurant",
            "type":"Food & Drink"
        }
    ],
    "sg:phone":"+1 613 234 1224",
    "sg:postcode":"K1P 5P3",
    "sg:province":"ON",
    "wof:name":"Festival Japan",
    "wof:placetype":"venue"
},
  "geometry": {"coordinates":[-75.702225,45.41898],"type":"Point"}
}