{
  "type": "Feature",
  "properties": {
    "iso:country":"CA",
    "sg:address":"880 Malkin Ave",
    "sg:city":"Vancouver",
    "sg:classifiers":[
        {
            "category":"Wholesale",
            "subcategory":"Durable Goods & Equipment",
            "type":"Manufacturing & Wholesale Goods"
        }
    ],
    "sg:phone":"+1 604 251 9866",
    "sg:postcode":"V6A 2K6",
    "sg:province":"BC",
    "sg:tags":[
        "importer"
    ],
    "wof:name":"Pacific Rim Intl Brokerage Inc",
    "wof:placetype":"venue"
},
  "geometry": {"coordinates":[-123.085479736,49.2737998962],"type":"Point"}
}