{
  "type": "Feature",
  "properties": {
    "addr:full":"5 Marilyn Ave Scarborough ON M1S 1B9",
    "addr:housenumber":"5",
    "addr:postcode":"m1s 1b9",
    "addr:street":"Marilyn Ave",
    "iso:country":"CA",
    "sg:address":"5 Marilyn Ave",
    "sg:city":"Scarborough",
    "sg:classifiers":[
        {
            "category":"Building & Trades",
            "subcategory":"Landscaping Services",
            "type":"Services"
        }
    ],
    "sg:phone":"+1 416 293 7151",
    "sg:postcode":"M1S 1B9",
    "sg:province":"ON",
    "sg:tags":[
        "lawn",
        "maintenance",
        "grounds"
    ],
    "wof:name":"Fromme's Garden Svc Ltd",
    "wof:placetype":"venue"
},
  "geometry": {"coordinates":[-79.28911600000001,43.787296],"type":"Point"}
}