{
  "type": "Feature",
  "properties": {
    "addr:full":"40 Airview Rd Etobicoke ON M9W 4P2",
    "addr:housenumber":"40",
    "addr:postcode":"m9w 4p2",
    "addr:street":"Airview Rd",
    "iso:country":"CA",
    "sg:address":"40 Airview Rd",
    "sg:city":"Etobicoke",
    "sg:classifiers":[
        {
            "category":"Professional",
            "subcategory":"Engineering",
            "type":"Services"
        }
    ],
    "sg:phone":"+1 416 742 7647",
    "sg:postcode":"M9W 4P2",
    "sg:province":"ON",
    "sg:tags":[
        "engineer"
    ],
    "wof:name":"Moore & Gentry Engineering",
    "wof:placetype":"venue"
},
  "geometry": {"coordinates":[-79.57591247560001,43.720703125],"type":"Point"}
}