{
  "type": "Feature",
  "properties": {
    "addr:full":"2850 Arens Rd Regina SK S4V 1N8",
    "addr:housenumber":"2850",
    "addr:postcode":"s4v 1n8",
    "addr:street":"Arens Rd",
    "iso:country":"CA",
    "sg:address":"2850 Arens Rd",
    "sg:city":"Regina",
    "sg:classifiers":[
        {
            "category":"Real Estate",
            "subcategory":"Real Estate Operator",
            "type":"Services"
        }
    ],
    "sg:phone":"+1 306 789 7614",
    "sg:postcode":"S4V 1N8",
    "sg:province":"SK",
    "sg:tags":[
        "apartment"
    ],
    "wof:name":"Carriage Court Apartments",
    "wof:placetype":"venue"
},
  "geometry": {"coordinates":[-104.542625427,50.4398269653],"type":"Point"}
}