{
  "type": "Feature",
  "properties": {
    "addr:full":"4489 10th Ave Port Alberni BC V9Y 4X6",
    "addr:housenumber":"4489",
    "addr:postcode":"v9y 4x6",
    "addr:street":"10Th Ave",
    "iso:country":"CA",
    "sg:address":"4489 10th Ave",
    "sg:city":"Port Alberni",
    "sg:classifiers":[
        {
            "category":"Farming",
            "subcategory":"Dairy Farm",
            "type":"Manufacturing & Wholesale Goods"
        }
    ],
    "sg:phone":"+1 250 723 2713",
    "sg:postcode":"V9Y 4X6",
    "sg:province":"BC",
    "wof:name":"Circle Dairy Ltd",
    "wof:placetype":"venue"
},
  "geometry": {"coordinates":[-124.797691,49.256447],"type":"Point"}
}