{
  "type": "Feature",
  "properties": {
    "addr:full":"1195 Dundas St London ON N5W 3A9",
    "addr:housenumber":"1195",
    "addr:postcode":"n5w 3a9",
    "addr:street":"Dundas St",
    "iso:country":"CA",
    "sg:address":"1195 Dundas St",
    "sg:city":"London",
    "sg:classifiers":[
        {
            "category":"Banks & Credit Unions",
            "subcategory":"Bank",
            "type":"Services"
        }
    ],
    "sg:phone":"+1 519 457 1565",
    "sg:postcode":"N5W 3A9",
    "sg:province":"ON",
    "sg:tags":[
        "loan"
    ],
    "wof:name":"Pdk Money",
    "wof:placetype":"venue"
},
  "geometry": {"coordinates":[-81.2096710205,42.9950180054],"type":"Point"}
}