{
  "type": "Feature",
  "properties": {
    "addr:full":"1837 Scugog St Port Perry ON L9L 1J3",
    "addr:housenumber":"1837",
    "addr:postcode":"l9l 1j3",
    "addr:street":"Scugog St",
    "iso:country":"CA",
    "sg:address":"1837 Scugog St",
    "sg:city":"Port Perry",
    "sg:classifiers":[
        {
            "category":"Building & Trades",
            "subcategory":"Construction",
            "type":"Services"
        }
    ],
    "sg:phone":"+1 905 985 4613",
    "sg:postcode":"L9L 1J3",
    "sg:province":"ON",
    "sg:tags":[
        "general",
        "contractor"
    ],
    "wof:name":"Parker Construction",
    "wof:placetype":"venue"
},
  "geometry": {"coordinates":[-78.942329,44.100597],"type":"Point"}
}