{
  "type": "Feature",
  "properties": {
    "addr:full":"650 Windsor Junction Rd Windsor Junction NS B2T 1G6",
    "addr:housenumber":"650",
    "addr:postcode":"b2t 1g6",
    "addr:street":"Windsor Junction Rd",
    "iso:country":"CA",
    "sg:address":"650 Windsor Junction Rd",
    "sg:city":"Windsor Junction",
    "sg:classifiers":[
        {
            "category":"Personal",
            "subcategory":"Beauty Salon",
            "type":"Services"
        }
    ],
    "sg:phone":"+1 902 861 2397",
    "sg:postcode":"B2T 1G6",
    "sg:province":"NS",
    "wof:name":"Lil's Hair Today",
    "wof:placetype":"venue"
},
  "geometry": {"coordinates":[-63.641620636,44.8017044067],"type":"Point"}
}