{
  "type": "Feature",
  "properties": {
    "addr:full":"524 Wilson Heights Blvd North York ON M3H 2V6",
    "addr:housenumber":"524",
    "addr:postcode":"m3h 2v6",
    "addr:street":"Wilson Heights Blvd",
    "iso:country":"CA",
    "sg:address":"524 Wilson Heights Blvd",
    "sg:city":"North York",
    "sg:classifiers":[
        {
            "category":"Food & Beverages",
            "subcategory":"Bakery",
            "type":"Retail Goods"
        }
    ],
    "sg:phone":"+1 416 630 4039",
    "sg:postcode":"M3H 2V6",
    "sg:province":"ON",
    "sg:tags":[
        "doughnut"
    ],
    "wof:name":"Country Style Donuts",
    "wof:placetype":"venue"
},
  "geometry": {"coordinates":[-79.455871582,43.7504043579],"type":"Point"}
}