{
  "type": "Feature",
  "properties": {
    "addr:full":"42 Bond St W Fenelon Falls ON K0M 1N0",
    "addr:housenumber":"42",
    "addr:postcode":"k0m 1n0",
    "addr:street":"Bond St W Fenelon",
    "iso:country":"CA",
    "sg:address":"42 Bond St W",
    "sg:city":"Fenelon Falls",
    "sg:classifiers":[
        {
            "category":"Social Services",
            "type":"Services"
        }
    ],
    "sg:phone":"+1 705 887 1408",
    "sg:postcode":"K0M 1N0",
    "sg:province":"ON",
    "sg:tags":[
        "organization",
        "welfare"
    ],
    "wof:name":"Salvation Army Citadel",
    "wof:placetype":"venue"
},
  "geometry": {"coordinates":[-78.737793,44.539165],"type":"Point"}
}