{
  "type": "Feature",
  "properties": {
    "addr:full":"213 Johnson St Dauphin MB R7N 2L7",
    "addr:housenumber":"213",
    "addr:postcode":"r7n 2l7",
    "addr:street":"Johnson St",
    "iso:country":"CA",
    "sg:address":"213 Johnson St",
    "sg:city":"Dauphin",
    "sg:classifiers":[
        {
            "category":"Wholesale",
            "subcategory":"Electrical",
            "type":"Manufacturing & Wholesale Goods"
        }
    ],
    "sg:phone":"+1 204 638 9191",
    "sg:postcode":"R7N 2L7",
    "sg:province":"MB",
    "sg:tags":[
        "appliance"
    ],
    "wof:name":"J K Appliance Repair Svc",
    "wof:placetype":"venue"
},
  "geometry": {"coordinates":[-100.06493399999999,51.152805],"type":"Point"}
}