{
  "type": "Feature",
  "properties": {
    "iso:country":"CA",
    "sg:city":"Peachland",
    "sg:classifiers":[
        {
            "category":"Social Services",
            "type":"Services"
        }
    ],
    "sg:phone":"+1 250 767 0183",
    "sg:postcode":"V0H 1X6",
    "sg:province":"BC",
    "sg:tags":[
        "senior",
        "citizen"
    ],
    "wof:name":"Peachland Senior Citizen's",
    "wof:placetype":"venue"
},
  "geometry": {"coordinates":[-119.735496521,49.7756958008],"type":"Point"}
}