{
  "type": "Feature",
  "properties": {
    "addr:full":"115 Boul Du Havre Salaberry-DE-Valleyfield QC J6S 1R3",
    "addr:housenumber":"115",
    "addr:postcode":"j6s 1r3",
    "addr:street":"Boul Du Havre",
    "iso:country":"CA",
    "sg:address":"115 Boul Du Havre",
    "sg:city":"Salaberry-DE-Valleyfield",
    "sg:classifiers":[
        {
            "category":"Wholesale",
            "subcategory":"Office Equipment",
            "type":"Manufacturing & Wholesale Goods"
        }
    ],
    "sg:phone":"+1 450 373 7506",
    "sg:postcode":"J6S 1R3",
    "sg:province":"QC",
    "sg:tags":[
        "register",
        "cash",
        "supply"
    ],
    "wof:name":"Caisse Lab Enr",
    "wof:placetype":"venue"
},
  "geometry": {"coordinates":[-74.14836120610001,45.2580718994],"type":"Point"}
}