{
  "type": "Feature",
  "properties": {
    "iso:country":"CA",
    "sg:address":"14 Pepperrell Rd",
    "sg:city":"St. John's",
    "sg:classifiers":[
        {
            "category":"Manufacturing",
            "subcategory":"Metals",
            "type":"Manufacturing & Wholesale Goods"
        }
    ],
    "sg:phone":"+1 709 754 5591",
    "sg:postcode":"A1A 5N8",
    "sg:province":"NL",
    "sg:tags":[
        "steel"
    ],
    "wof:name":"Allstar Rebar Ltd",
    "wof:placetype":"venue"
},
  "geometry": {"coordinates":[-52.69298172,47.6015319824],"type":"Point"}
}