{
  "type": "Feature",
  "properties": {
    "addr:full":"183 Main Dutton ON N0L 1J0",
    "addr:housenumber":"183",
    "addr:postcode":"n0l 1j0",
    "addr:street":"Main",
    "iso:country":"CA",
    "sg:address":"183 Main",
    "sg:city":"Dutton",
    "sg:classifiers":[
        {
            "category":"Organizations",
            "subcategory":"Membership Organization",
            "type":"Services"
        }
    ],
    "sg:phone":"+1 519 762 5757",
    "sg:postcode":"N0L 1J0",
    "sg:province":"ON",
    "wof:name":"West Elgin Daffodil Auxiliary",
    "wof:placetype":"venue"
},
  "geometry": {"coordinates":[-81.502022,42.663364],"type":"Point"}
}