{
  "type": "Feature",
  "properties": {
    "addr:full":"155 Rideau St Ottawa ON K1N 5X4",
    "addr:housenumber":"155",
    "addr:postcode":"k1n 5x4",
    "addr:street":"Rideau St",
    "iso:country":"CA",
    "sg:address":"155 Rideau St",
    "sg:city":"Ottawa",
    "sg:classifiers":[
        {
            "category":"Personal",
            "subcategory":"Beauty Salon",
            "type":"Services"
        }
    ],
    "sg:phone":"+1 613 241 1313",
    "sg:postcode":"K1N 5X4",
    "sg:province":"ON",
    "wof:name":"Scissor Hands",
    "wof:placetype":"venue"
},
  "geometry": {"coordinates":[-75.69004099999999,45.427135],"type":"Point"}
}