{
  "type": "Feature",
  "properties": {
    "addr:full":"27 Rue Bagot Laval QC H7H 1Z7",
    "addr:housenumber":"27",
    "addr:postcode":"h7h 1z7",
    "addr:street":"Rue Bagot",
    "iso:country":"CA",
    "sg:address":"27 Rue Bagot",
    "sg:city":"Laval",
    "sg:classifiers":[
        {
            "category":"Manufacturing",
            "subcategory":"Metals",
            "type":"Manufacturing & Wholesale Goods"
        }
    ],
    "sg:phone":"+1 514 808 4405",
    "sg:postcode":"H7H 1Z7",
    "sg:province":"QC",
    "sg:tags":[
        "solder"
    ],
    "wof:name":"Ideal Soudure A L'Arc",
    "wof:placetype":"venue"
},
  "geometry": {"coordinates":[-73.7587738037,45.6498451233],"type":"Point"}
}