{
  "type": "Feature",
  "properties": {
    "addr:full":"Scarborough ON M1H 3A4",
    "addr:postcode":"m1h 3a4",
    "iso:country":"CA",
    "sg:city":"Scarborough",
    "sg:classifiers":[
        {
            "category":"Wholesale",
            "subcategory":"Machinery & Supplies",
            "type":"Manufacturing & Wholesale Goods"
        }
    ],
    "sg:phone":"+1 416 438 8177",
    "sg:postcode":"M1H 3A4",
    "sg:province":"ON",
    "sg:tags":[
        "dyer",
        "cleaners"
    ],
    "wof:name":"Gba Refineries Ltd",
    "wof:placetype":"venue"
},
  "geometry": {"coordinates":[-79.2476730347,43.7777137756],"type":"Point"}
}