{
  "type": "Feature",
  "properties": {
    "addr:full":"2800 Bradbury Dr Prince Albert SK S6V 7K8",
    "addr:housenumber":"2800",
    "addr:postcode":"s6v 7k8",
    "addr:street":"Bradbury Dr",
    "iso:country":"CA",
    "sg:address":"2800 Bradbury Dr",
    "sg:city":"Prince Albert",
    "sg:classifiers":[
        {
            "category":"Education",
            "subcategory":"School",
            "type":"Public Place"
        }
    ],
    "sg:phone":"+1 306 922 6446",
    "sg:postcode":"S6V 7K8",
    "sg:province":"SK",
    "wof:name":"Vickers School",
    "wof:placetype":"venue"
},
  "geometry": {"coordinates":[-105.704574585,53.1870040894],"type":"Point"}
}