{
  "type": "Feature",
  "properties": {
    "addr:full":"2 Grenadier Rd Brampton ON L6S 1T4",
    "addr:housenumber":"2",
    "addr:postcode":"l6s 1t4",
    "addr:street":"Grenadier Rd",
    "iso:country":"CA",
    "sg:address":"2 Grenadier Rd",
    "sg:city":"Brampton",
    "sg:classifiers":[
        {
            "category":"Professional",
            "subcategory":"Employment Agencies",
            "type":"Services"
        }
    ],
    "sg:phone":"+1 905 790 8090",
    "sg:postcode":"L6S 1T4",
    "sg:province":"ON",
    "sg:tags":[
        "opportunity"
    ],
    "wof:name":"I T Hunters Inc",
    "wof:placetype":"venue"
},
  "geometry": {"coordinates":[-79.709717,43.736073],"type":"Point"}
}