{
  "type": "Feature",
  "properties": {
    "addr:full":"53218 Range Road 231 Sherwood Park AB T8A 4V2",
    "addr:housenumber":"53218",
    "addr:postcode":"t8a 4v2",
    "addr:street":"Range Road 231;Park",
    "iso:country":"CA",
    "sg:address":"53218 Range Road 231",
    "sg:city":"Sherwood Park",
    "sg:classifiers":[
        {
            "category":"Farming",
            "subcategory":"Nursery",
            "type":"Manufacturing & Wholesale Goods"
        }
    ],
    "sg:phone":"+1 780 467 3091",
    "sg:postcode":"T8A 4V2",
    "sg:province":"AB",
    "sg:tags":[
        "greenhouse"
    ],
    "wof:name":"Wallish Greenhouses Ltd",
    "wof:placetype":"venue"
},
  "geometry": {"coordinates":[-113.271026611,53.5737342834],"type":"Point"}
}