{
  "type": "Feature",
  "properties": {
    "addr:full":"1289 133A St Surrey BC V4A 4C4",
    "addr:housenumber":"1289",
    "addr:postcode":"v4a 4c4",
    "addr:street":"133A St",
    "iso:country":"CA",
    "sg:address":"1289 133A St",
    "sg:city":"Surrey",
    "sg:classifiers":[
        {
            "category":"Professional",
            "subcategory":"Management & Consulting",
            "type":"Services"
        }
    ],
    "sg:phone":"+1 604 535 0707",
    "sg:postcode":"V4A 4C4",
    "sg:province":"BC",
    "sg:tags":[
        "consultant",
        "business"
    ],
    "wof:name":"Anderson Programs Inc",
    "wof:placetype":"venue"
},
  "geometry": {"coordinates":[-122.830215,49.105179],"type":"Point"}
}