{
  "type": "Feature",
  "properties": {
    "addr:full":"5070 Riverbottom Rd Duncan BC V9L 3X9",
    "addr:housenumber":"5070",
    "addr:postcode":"v9l 3x9",
    "addr:street":"Riverbottom Rd",
    "iso:country":"CA",
    "sg:address":"5070 Riverbottom Rd",
    "sg:city":"Duncan",
    "sg:classifiers":[
        {
            "category":"Organizations",
            "subcategory":"Religious Organization",
            "type":"Services"
        }
    ],
    "sg:phone":"+1 604 748 5205",
    "sg:postcode":"V9L 3X9",
    "sg:province":"BC",
    "sg:tags":[
        "church"
    ],
    "wof:name":"Cowichan Full Gospel Flshp",
    "wof:placetype":"venue"
},
  "geometry": {"coordinates":[-123.70738220200001,48.779094696],"type":"Point"}
}