{
  "type": "Feature",
  "properties": {
    "addr:full":"Barrie ON L4M 5N4",
    "addr:postcode":"l4m 5n4",
    "iso:country":"CA",
    "sg:city":"Barrie",
    "sg:classifiers":[
        {
            "category":"Professional",
            "subcategory":"Computer Services",
            "type":"Services"
        }
    ],
    "sg:phone":"+1 705 720 1111",
    "sg:postcode":"L4M 5N4",
    "sg:province":"ON",
    "sg:tags":[
        "repair",
        "dealer",
        "equipment"
    ],
    "wof:name":"Poweredge Systems Inc",
    "wof:placetype":"venue"
},
  "geometry": {"coordinates":[-79.68843099999999,44.404682],"type":"Point"}
}