{
  "type": "Feature",
  "properties": {
    "addr:full":"Mckellar ON P0G 1C0",
    "addr:postcode":"p0g 1c0",
    "iso:country":"CA",
    "sg:city":"Mckellar",
    "sg:classifiers":[
        {
            "category":"Government",
            "subcategory":"Fire Station",
            "type":"Public Place"
        }
    ],
    "sg:phone":"+1 705 389 1036",
    "sg:postcode":"P0G 1C0",
    "sg:province":"ON",
    "sg:tags":[
        "department"
    ],
    "wof:name":"Ardberg Fire Department",
    "wof:placetype":"venue"
},
  "geometry": {"coordinates":[-79.91986799999999,45.50856],"type":"Point"}
}