{
  "type": "Feature",
  "properties": {
    "iso:country":"CA",
    "sg:city":"Richmond Hill",
    "sg:classifiers":[
        {
            "category":"Wholesale",
            "subcategory":"Durable Goods & Equipment",
            "type":"Manufacturing & Wholesale Goods"
        }
    ],
    "sg:phone":"+1 905 881 2771",
    "sg:postcode":"L4B 2N2",
    "sg:province":"ON",
    "sg:tags":[
        "importer"
    ],
    "wof:name":"Everlux Corp",
    "wof:placetype":"venue"
},
  "geometry": {"coordinates":[-79.37758636469999,43.8491897583],"type":"Point"}
}