{
  "type": "Feature",
  "properties": {
    "addr:full":"11 Av Riordon Temiscaming QC J0Z 3R0",
    "addr:postcode":"j0z 3r0",
    "addr:street":"11 Av Riordon Temiscaming",
    "iso:country":"CA",
    "sg:address":"11 Av Riordon",
    "sg:city":"Temiscaming",
    "sg:classifiers":[
        {
            "category":"Retail",
            "subcategory":"Funeral Services",
            "type":"Services"
        }
    ],
    "sg:phone":"+1 819 627 9636",
    "sg:postcode":"J0Z 3R0",
    "sg:province":"QC",
    "sg:tags":[
        "director"
    ],
    "wof:name":"Perron Funeral Home",
    "wof:placetype":"venue"
},
  "geometry": {"coordinates":[-79.099953,46.719135],"type":"Point"}
}