{
  "type": "Feature",
  "properties": {
    "addr:full":"Kemptville ON K0G 1J0",
    "addr:postcode":"k0g 1j0",
    "iso:country":"CA",
    "sg:city":"Kemptville",
    "sg:classifiers":[
        {
            "category":"Retail",
            "subcategory":"Repair Shop",
            "type":"Services"
        }
    ],
    "sg:phone":"+1 613 258 9935",
    "sg:postcode":"K0G 1J0",
    "sg:province":"ON",
    "sg:tags":[
        "welding"
    ],
    "wof:name":"Welding Shop",
    "wof:placetype":"venue"
},
  "geometry": {"coordinates":[-75.645614624,45.0159187317],"type":"Point"}
}