{
  "type": "Feature",
  "properties": {
    "iso:country":"CA",
    "sg:address":"4109 Grace Cres",
    "sg:city":"North Vancouver",
    "sg:classifiers":[
        {
            "category":"Real Estate",
            "subcategory":"Developer",
            "type":"Services"
        }
    ],
    "sg:phone":"+1 604 985 5427",
    "sg:postcode":"V7R 3Z9",
    "sg:province":"BC",
    "sg:tags":[
        "company",
        "land"
    ],
    "wof:name":"David Birch & Assoc Ltd",
    "wof:placetype":"venue"
},
  "geometry": {"coordinates":[-123.101898193,49.3486175537],"type":"Point"}
}