{
  "type": "Feature",
  "properties": {
    "iso:country":"CA",
    "sg:address":"342 King St W",
    "sg:city":"Oshawa",
    "sg:classifiers":[
        {
            "category":"Real Estate",
            "subcategory":"Real Estate Agent",
            "type":"Services"
        }
    ],
    "sg:phone":"+1 905 576 5200",
    "sg:postcode":"L1J 2J9",
    "sg:province":"ON",
    "wof:name":"Coldwell Banker 2M Realty",
    "wof:placetype":"venue"
},
  "geometry": {"coordinates":[-78.876007,43.894875],"type":"Point"}
}