{
  "type": "Feature",
  "properties": {
    "addr:full":"77 Av Gagnon Falardeau QC G0V 1C0",
    "addr:postcode":"g0v 1c0",
    "addr:street":"77 Av Gagnon Falardeau",
    "iso:country":"CA",
    "sg:address":"77 Av Gagnon",
    "sg:city":"Falardeau",
    "sg:classifiers":[
        {
            "category":"Building & Trades",
            "subcategory":"Construction",
            "type":"Services"
        }
    ],
    "sg:phone":"+1 418 673 4525",
    "sg:postcode":"G0V 1C0",
    "sg:province":"QC",
    "sg:tags":[
        "concrete",
        "contractor"
    ],
    "wof:name":"Betons Christian Tremblay",
    "wof:placetype":"venue"
},
  "geometry": {"coordinates":[-71.107925415,48.6199226379],"type":"Point"}
}