{
  "type": "Feature",
  "properties": {
    "addr:full":"26 Churchill Cres St Thomas ON N5R 1N9",
    "addr:housenumber":"26",
    "addr:postcode":"n5r 1n9",
    "addr:street":"Churchill Cres",
    "iso:country":"CA",
    "sg:address":"26 Churchill Cres",
    "sg:city":"St Thomas",
    "sg:classifiers":[
        {
            "category":"Shopping",
            "subcategory":"Discount & Variety Stores",
            "type":"Retail Goods"
        }
    ],
    "sg:phone":"+1 519 633 1983",
    "sg:postcode":"N5R 1N9",
    "sg:province":"ON",
    "wof:name":"Convenience Food Mart",
    "wof:placetype":"venue"
},
  "geometry": {"coordinates":[-81.1846160889,42.7666816711],"type":"Point"}
}