{
  "type": "Feature",
  "properties": {
    "addr:full":"Ingleside ON K0C 1M0",
    "addr:postcode":"k0c 1m0",
    "iso:country":"CA",
    "sg:city":"Ingleside",
    "sg:classifiers":[
        {
            "category":"Organizations",
            "subcategory":"Religious Organization",
            "type":"Services"
        }
    ],
    "sg:phone":"+1 613 537 2892",
    "sg:postcode":"K0C 1M0",
    "sg:province":"ON",
    "sg:tags":[
        "church"
    ],
    "wof:name":"St Matthew's Presbyterian",
    "wof:placetype":"venue"
},
  "geometry": {"coordinates":[-74.993393,44.99839],"type":"Point"}
}