{
  "type": "Feature",
  "properties": {
    "addr:full":"514 Boul Saint-Germain Rimouski QC G5L 3P8",
    "addr:housenumber":"514",
    "addr:postcode":"g5l 3p8",
    "addr:street":"Boul Saint-Germain",
    "iso:country":"CA",
    "sg:address":"514 Boul Saint-Germain",
    "sg:city":"Rimouski",
    "sg:classifiers":[
        {
            "category":"Autos & Motor Vehicles",
            "subcategory":"Automobile Sales",
            "type":"Retail Goods"
        }
    ],
    "sg:phone":"+1 418 723 6533",
    "sg:postcode":"G5L 3P8",
    "sg:province":"QC",
    "sg:tags":[
        "car",
        "dealer"
    ],
    "wof:name":"Lamontagne Auto Ltee",
    "wof:placetype":"venue"
},
  "geometry": {"coordinates":[-68.5613250732,48.4403953552],"type":"Point"}
}