{
  "type": "Feature",
  "properties": {
    "addr:full":"257 Riverton Ave Winnipeg MB R2L 0N2",
    "addr:housenumber":"257",
    "addr:postcode":"r2l 0n2",
    "addr:street":"Riverton Ave",
    "iso:country":"CA",
    "sg:address":"257 Riverton Ave",
    "sg:city":"Winnipeg",
    "sg:classifiers":[
        {
            "category":"Organizations",
            "subcategory":"Religious Organization",
            "type":"Services"
        }
    ],
    "sg:phone":"+1 204 668 3181",
    "sg:postcode":"R2L 0N2",
    "sg:province":"MB",
    "sg:tags":[
        "church"
    ],
    "wof:name":"Riverwood Church Community",
    "wof:placetype":"venue"
},
  "geometry": {"coordinates":[-97.11371612550001,49.9093322754],"type":"Point"}
}