{
  "type": "Feature",
  "properties": {
    "addr:full":"1071 Britannia Rd E Mississauga ON L4W 3X1",
    "addr:housenumber":"1071",
    "addr:postcode":"l4w 3x1",
    "addr:street":"Britannia Rd E",
    "iso:country":"CA",
    "sg:address":"1071 Britannia Rd E",
    "sg:city":"Mississauga",
    "sg:classifiers":[
        {
            "category":"Building & Trades",
            "subcategory":"Plumbing",
            "type":"Services"
        }
    ],
    "sg:phone":"+1 905 670 3292",
    "sg:postcode":"L4W 3X1",
    "sg:province":"ON",
    "sg:tags":[
        "equipment",
        "refrigeration",
        "contractor"
    ],
    "wof:name":"Quality Mechanical Inc",
    "wof:placetype":"venue"
},
  "geometry": {"coordinates":[-79.657295,43.646797],"type":"Point"}
}