{
  "type": "Feature",
  "properties": {
    "addr:full":"Mississauga ON L5T 1N9",
    "addr:postcode":"l5t 1n9",
    "iso:country":"CA",
    "sg:city":"Mississauga",
    "sg:classifiers":[
        {
            "category":"Wholesale",
            "subcategory":"Office Equipment",
            "type":"Manufacturing & Wholesale Goods"
        }
    ],
    "sg:phone":"+1 905 795 8111",
    "sg:postcode":"L5T 1N9",
    "sg:province":"ON",
    "sg:tags":[
        "scanning",
        "code",
        "bar"
    ],
    "wof:name":"Psc Inc",
    "wof:placetype":"venue"
},
  "geometry": {"coordinates":[-79.6506195068,43.6584968567],"type":"Point"}
}