{
  "type": "Feature",
  "properties": {
    "addr:full":"Laval QC H7Y 1M7",
    "addr:postcode":"h7y 1m7",
    "iso:country":"CA",
    "sg:city":"Laval",
    "sg:classifiers":[
        {
            "category":"Freight",
            "type":"Transportation"
        }
    ],
    "sg:phone":"+1 514 323 3981",
    "sg:postcode":"H7Y 1M7",
    "sg:province":"QC",
    "sg:tags":[
        "trucking"
    ],
    "wof:name":"Laurin Transport & Fils Inc",
    "wof:placetype":"venue"
},
  "geometry": {"coordinates":[-73.85169999999999,45.526333],"type":"Point"}
}