{
  "type": "Feature",
  "properties": {
    "addr:full":"216 Railway St Treherne MB R0G 2V0",
    "addr:housenumber":"216",
    "addr:postcode":"r0g 2v0",
    "addr:street":"Railway St",
    "iso:country":"CA",
    "sg:address":"216 Railway St",
    "sg:city":"Treherne",
    "sg:classifiers":[
        {
            "category":"Sports & Exercise",
            "subcategory":"Bowling",
            "type":"Entertainment"
        }
    ],
    "sg:phone":"+1 204 723 2202",
    "sg:postcode":"R0G 2V0",
    "sg:province":"MB",
    "sg:tags":[
        "center"
    ],
    "wof:name":"Treherne Bowling & Billards",
    "wof:placetype":"venue"
},
  "geometry": {"coordinates":[-98.696167,49.630455],"type":"Point"}
}