{
  "type": "Feature",
  "properties": {
    "addr:full":"4440 44 Ave NE Calgary AB T1Y 4W5",
    "addr:housenumber":"4440",
    "addr:postcode":"t1y 4w5",
    "addr:street":"44 Ave Ne",
    "iso:country":"CA",
    "sg:address":"4440 44 Ave NE",
    "sg:city":"Calgary",
    "sg:classifiers":[
        {
            "category":"Food & Beverages",
            "subcategory":"Groceries & Convenience Stores",
            "type":"Retail Goods"
        }
    ],
    "sg:phone":"+1 403 285 3519",
    "sg:postcode":"T1Y 4W5",
    "sg:province":"AB",
    "wof:name":"White Rooster",
    "wof:placetype":"venue"
},
  "geometry": {"coordinates":[-113.966728,51.092716],"type":"Point"}
}