{
  "type": "Feature",
  "properties": {
    "addr:full":"115 Rue Rachel E Montreal QC H2W 1C8",
    "addr:housenumber":"115",
    "addr:postcode":"h2w 1c8",
    "addr:street":"Rue Rachel E",
    "iso:country":"CA",
    "sg:address":"115 Rue Rachel E",
    "sg:city":"Montreal",
    "sg:classifiers":[
        {
            "category":"Food & Beverages",
            "subcategory":"Bakery",
            "type":"Retail Goods"
        }
    ],
    "sg:phone":"+1 514 849 1803",
    "sg:postcode":"H2W 1C8",
    "sg:province":"QC",
    "sg:tags":[
        "butchering"
    ],
    "wof:name":"Rotisserie Romados",
    "wof:placetype":"venue"
},
  "geometry": {"coordinates":[-73.5808181763,45.5191764832],"type":"Point"}
}