{
  "type": "Feature",
  "properties": {
    "addr:full":"Charlesbourg QC G1H 1A1",
    "addr:postcode":"g1h 1a1",
    "iso:country":"CA",
    "sg:city":"Charlesbourg",
    "sg:classifiers":[
        {
            "category":"Retail",
            "subcategory":"Veterinary Services",
            "type":"Services"
        }
    ],
    "sg:phone":"+1 418 626 1461",
    "sg:postcode":"G1H 1A1",
    "sg:province":"QC",
    "sg:tags":[
        "veterinarian"
    ],
    "wof:name":"Hopital Veterinaire DE Chsbrg",
    "wof:placetype":"venue"
},
  "geometry": {"coordinates":[-71.251159668,46.8457183838],"type":"Point"}
}