{
  "type": "Feature",
  "properties": {
    "addr:full":"33 Gilmore Rd Fort Erie ON L2A 2L9",
    "addr:housenumber":"33",
    "addr:postcode":"l2a 2l9",
    "addr:street":"Gilmore Rd",
    "iso:country":"CA",
    "sg:address":"33 Gilmore Rd",
    "sg:city":"Fort Erie",
    "sg:classifiers":[
        {
            "category":"Freight",
            "type":"Transportation"
        }
    ],
    "sg:phone":"+1 905 871 6607",
    "sg:postcode":"L2A 2L9",
    "sg:province":"ON",
    "wof:name":"Fyke Trading CO",
    "wof:placetype":"venue"
},
  "geometry": {"coordinates":[-78.913048,42.920532],"type":"Point"}
}