{
  "type": "Feature",
  "properties": {
    "addr:full":"110 Highway 582 Dorion ON P0T 1K0",
    "addr:housenumber":"110",
    "addr:postcode":"p0t 1k0",
    "addr:street":"Highway 582",
    "iso:country":"CA",
    "sg:address":"110 Highway 582",
    "sg:city":"Dorion",
    "sg:classifiers":[
        {
            "category":"Recreation",
            "type":"Entertainment"
        }
    ],
    "sg:phone":"+1 807 857 2208",
    "sg:postcode":"P0T 1K0",
    "sg:province":"ON",
    "sg:tags":[
        "center"
    ],
    "wof:name":"Hurkett Community Ctr",
    "wof:placetype":"venue"
},
  "geometry": {"coordinates":[-88.54020690919999,48.7883911133],"type":"Point"}
}