{
  "type": "Feature",
  "properties": {
    "addr:full":"Lamont AB T0B 2R0",
    "addr:postcode":"t0b 2r0",
    "iso:country":"CA",
    "sg:city":"Lamont",
    "sg:classifiers":[
        {
            "category":"Food & Beverages",
            "subcategory":"Groceries & Convenience Stores",
            "type":"Retail Goods"
        }
    ],
    "sg:phone":"+1 780 895 2080",
    "sg:postcode":"T0B 2R0",
    "sg:province":"AB",
    "sg:tags":[
        "grocer"
    ],
    "wof:name":"Lamont Iga",
    "wof:placetype":"venue"
},
  "geometry": {"coordinates":[-112.778381348,53.7599563599],"type":"Point"}
}