{
  "type": "Feature",
  "properties": {
    "addr:full":"894 Boul Saint-Jean-Baptiste Mercier QC J6R 2K8",
    "addr:housenumber":"894",
    "addr:postcode":"j6r 2k8",
    "addr:street":"Boul Saint-Jean-Baptiste",
    "iso:country":"CA",
    "sg:address":"894 Boul Saint-Jean-Baptiste",
    "sg:city":"Mercier",
    "sg:classifiers":[
        {
            "category":"Food & Beverages",
            "subcategory":"Bakery",
            "type":"Retail Goods"
        }
    ],
    "sg:phone":"+1 450 691 5700",
    "sg:postcode":"J6R 2K8",
    "sg:province":"QC",
    "sg:tags":[
        "baker"
    ],
    "wof:name":"Boulangerie Dj Martinez",
    "wof:placetype":"venue"
},
  "geometry": {"coordinates":[-73.74533081049999,45.3104476929],"type":"Point"}
}