{
  "type": "Feature",
  "properties": {
    "addr:full":"1220 Kensington Rd NW Calgary AB T2N 3P5",
    "addr:housenumber":"1220",
    "addr:postcode":"t2n 3p5",
    "addr:street":"Kensington Rd Nw",
    "iso:country":"CA",
    "sg:address":"1220 Kensington Rd NW",
    "sg:city":"Calgary",
    "sg:classifiers":[
        {
            "category":"Restaurant",
            "type":"Food & Drink"
        }
    ],
    "sg:phone":"+1 403 670 5637",
    "sg:postcode":"T2N 3P5",
    "sg:province":"AB",
    "wof:name":"Original Joe's Restaurant & Br",
    "wof:placetype":"venue"
},
  "geometry": {"coordinates":[-114.089912,51.052708],"type":"Point"}
}