{
  "type": "Feature",
  "properties": {
    "addr:full":"440 Rue Principale Saint-Jacques NB E7B 1Y1",
    "addr:housenumber":"440",
    "addr:postcode":"e7b 1y1",
    "addr:street":"Rue Principale",
    "iso:country":"CA",
    "sg:address":"440 Rue Principale",
    "sg:city":"Saint-Jacques",
    "sg:classifiers":[
        {
            "category":"Shopping",
            "subcategory":"Computers & Home Electronics",
            "type":"Retail Goods"
        }
    ],
    "sg:phone":"+1 506 735 7764",
    "sg:postcode":"E7B 1Y1",
    "sg:province":"NB",
    "sg:tags":[
        "television",
        "radio"
    ],
    "wof:name":"Republique Tv Svc & Satellite",
    "wof:placetype":"venue"
},
  "geometry": {"coordinates":[-68.377449,47.4184],"type":"Point"}
}