{
  "type": "Feature",
  "properties": {
    "addr:full":"Petit-Saguenay QC G0V 1N0",
    "addr:postcode":"g0v 1n0",
    "iso:country":"CA",
    "sg:city":"Petit-Saguenay",
    "sg:classifiers":[
        {
            "category":"Travel",
            "subcategory":"Hotels & Motels",
            "type":"Entertainment"
        }
    ],
    "sg:phone":"+1 418 272 3193",
    "sg:postcode":"G0V 1N0",
    "sg:province":"QC",
    "sg:tags":[
        "cottage",
        "cabin"
    ],
    "wof:name":"Village Vacances Petit-Sgny",
    "wof:placetype":"venue"
},
  "geometry": {"coordinates":[-70.08424377439999,48.2198448181],"type":"Point"}
}