{
  "type": "Feature",
  "properties": {
    "addr:full":"8525 52 St SE Calgary AB T2C 2R3",
    "addr:housenumber":"8525",
    "addr:postcode":"t2c 2r3",
    "addr:street":"52 St Se",
    "iso:country":"CA",
    "sg:address":"8525 52 St SE",
    "sg:city":"Calgary",
    "sg:classifiers":[
        {
            "category":"Manufacturing",
            "subcategory":"Metals",
            "type":"Manufacturing & Wholesale Goods"
        }
    ],
    "sg:phone":"+1 403 279 7751",
    "sg:postcode":"T2C 2R3",
    "sg:province":"AB",
    "sg:tags":[
        "steel"
    ],
    "wof:name":"Ensteel Industries Ltd",
    "wof:placetype":"venue"
},
  "geometry": {"coordinates":[-113.958618164,50.9777297974],"type":"Point"}
}