{
  "type": "Feature",
  "properties": {
    "addr:full":"202 1st St Winkler MB R6W 3N1",
    "addr:housenumber":"202",
    "addr:postcode":"r6w 3n1",
    "addr:street":"1St St",
    "iso:country":"CA",
    "sg:address":"202 1st St",
    "sg:city":"Winkler",
    "sg:classifiers":[
        {
            "category":"Food & Beverages",
            "subcategory":"Groceries & Convenience Stores",
            "type":"Retail Goods"
        }
    ],
    "sg:phone":"+1 204 325 7673",
    "sg:postcode":"R6W 3N1",
    "sg:province":"MB",
    "wof:name":"Hi-Way Groceteria",
    "wof:placetype":"venue"
},
  "geometry": {"coordinates":[-97.933502,49.180271],"type":"Point"}
}