{
  "type": "Feature",
  "properties": {
    "addr:full":"132 Tudhope St Espanola ON P5E 1S6",
    "addr:housenumber":"132",
    "addr:postcode":"p5e 1s6",
    "addr:street":"Tudhope St",
    "iso:country":"CA",
    "sg:address":"132 Tudhope St",
    "sg:city":"Espanola",
    "sg:classifiers":[
        {
            "category":"Personal",
            "subcategory":"Barber",
            "type":"Services"
        }
    ],
    "sg:phone":"+1 705 869 3612",
    "sg:postcode":"P5E 1S6",
    "sg:province":"ON",
    "wof:name":"Meloche's Barber Shop",
    "wof:placetype":"venue"
},
  "geometry": {"coordinates":[-81.7714385986,46.2650413513],"type":"Point"}
}