{
  "type": "Feature",
  "properties": {
    "addr:full":"72 Joseph St Port Carling ON P0B 1J0",
    "addr:housenumber":"72",
    "addr:postcode":"p0b 1j0",
    "addr:street":"Joseph St",
    "iso:country":"CA",
    "sg:address":"72 Joseph St",
    "sg:city":"Port Carling",
    "sg:classifiers":[
        {
            "category":"Insurance",
            "subcategory":"Insurance Agent",
            "type":"Services"
        }
    ],
    "sg:phone":"+1 705 765 6844",
    "sg:postcode":"P0B 1J0",
    "sg:province":"ON",
    "wof:name":"Firstbrook Cassie & Anderson",
    "wof:placetype":"venue"
},
  "geometry": {"coordinates":[-79.57620199999999,45.116875],"type":"Point"}
}