{
  "type": "Feature",
  "properties": {
    "iso:country":"CA",
    "sg:city":"Crossfield",
    "sg:classifiers":[
        {
            "category":"Wholesale",
            "subcategory":"Non-durable Goods",
            "type":"Manufacturing & Wholesale Goods"
        }
    ],
    "sg:phone":"+1 403 946 5503",
    "sg:postcode":"T0M 0S0",
    "sg:province":"AB",
    "sg:tags":[
        "advertising"
    ],
    "wof:name":"Obp Promotions & Awards Ltd",
    "wof:placetype":"venue"
},
  "geometry": {"coordinates":[-114.027076721,51.4295387268],"type":"Point"}
}