{
  "type": "Feature",
  "properties": {
    "addr:full":"3848 Schnupp Ch Bourget ON K0A 1E0",
    "addr:housenumber":"3848",
    "addr:postcode":"k0a 1e0",
    "addr:street":"Schnupp Ch Bourget",
    "iso:country":"CA",
    "sg:address":"3848 Schnupp Ch",
    "sg:city":"Bourget",
    "sg:classifiers":[
        {
            "category":"Building & Trades",
            "subcategory":"Electrical",
            "type":"Services"
        }
    ],
    "sg:phone":"+1 613 487 9408",
    "sg:postcode":"K0A 1E0",
    "sg:province":"ON",
    "sg:tags":[
        "electric",
        "contractor"
    ],
    "wof:name":"Jemteck Electric",
    "wof:placetype":"venue"
},
  "geometry": {"coordinates":[-75.1403045654,45.435256958],"type":"Point"}
}