{
  "type": "Feature",
  "properties": {
    "iso:country":"CA",
    "sg:city":"Maxville",
    "sg:classifiers":[
        {
            "category":"Building & Trades",
            "subcategory":"Construction",
            "type":"Services"
        }
    ],
    "sg:phone":"+1 613 527 5685",
    "sg:postcode":"K0C 1T0",
    "sg:province":"ON",
    "sg:tags":[
        "excavating",
        "contractor"
    ],
    "wof:name":"Allan M Crites Excavation Ltd",
    "wof:placetype":"venue"
},
  "geometry": {"coordinates":[-74.8559417725,45.2889633179],"type":"Point"}
}