{
  "type": "Feature",
  "properties": {
    "addr:full":"32 Chadbourne Dr North Bay ON P1B 8G2",
    "addr:housenumber":"32",
    "addr:postcode":"p1b 8g2",
    "addr:street":"Chadbourne Dr",
    "iso:country":"CA",
    "sg:address":"32 Chadbourne Dr",
    "sg:city":"North Bay",
    "sg:classifiers":[
        {
            "category":"Building & Trades",
            "subcategory":"Construction",
            "type":"Services"
        }
    ],
    "sg:phone":"+1 705 497 0555",
    "sg:postcode":"P1B 8G2",
    "sg:province":"ON",
    "sg:tags":[
        "general",
        "contractor"
    ],
    "wof:name":"Pine Creek Enterprises",
    "wof:placetype":"venue"
},
  "geometry": {"coordinates":[-79.402908,46.384106],"type":"Point"}
}