{
  "type": "Feature",
  "properties": {
    "iso:country":"CA",
    "sg:city":"Vancouver",
    "sg:classifiers":[
        {
            "category":"Professional",
            "subcategory":"Lawyer & Legal Services",
            "type":"Services"
        }
    ],
    "sg:phone":"+1 604 434 9929",
    "sg:postcode":"V5R 5W2",
    "sg:province":"BC",
    "sg:tags":[
        "attorney"
    ],
    "wof:name":"Mc Lellan, David J",
    "wof:placetype":"venue"
},
  "geometry": {"coordinates":[-123.02438354500001,49.2324142456],"type":"Point"}
}