{
  "type": "Feature",
  "properties": {
    "addr:full":"Vancouver BC V6E 4S1",
    "addr:postcode":"v6e 4s1",
    "iso:country":"CA",
    "sg:city":"Vancouver",
    "sg:classifiers":[
        {
            "category":"Wholesale",
            "subcategory":"Durable Goods & Equipment",
            "type":"Manufacturing & Wholesale Goods"
        }
    ],
    "sg:phone":"+1 604 602 9250",
    "sg:postcode":"V6E 4S1",
    "sg:province":"BC",
    "sg:tags":[
        "exporter"
    ],
    "wof:name":"Rodus International Trading",
    "wof:placetype":"venue"
},
  "geometry": {"coordinates":[-123.128044,49.288128],"type":"Point"}
}