{
  "type": "Feature",
  "properties": {
    "iso:country":"CA",
    "sg:address":"5410 4 Ave",
    "sg:city":"Delta",
    "sg:classifiers":[
        {
            "category":"Building & Trades",
            "subcategory":"Plumbing",
            "type":"Services"
        }
    ],
    "sg:phone":"+1 604 943 1234",
    "sg:postcode":"V4M 1H1",
    "sg:province":"BC",
    "sg:tags":[
        "contractor"
    ],
    "wof:name":"Sierra Mechanical Ltd",
    "wof:placetype":"venue"
},
  "geometry": {"coordinates":[-123.073745727,49.0099716187],"type":"Point"}
}