{
  "type": "Feature",
  "properties": {
    "addr:full":"Kitchener ON N2G 1A7",
    "addr:postcode":"n2g 1a7",
    "iso:country":"CA",
    "sg:city":"Kitchener",
    "sg:classifiers":[
        {
            "category":"Organizations",
            "subcategory":"Religious Organization",
            "type":"Services"
        }
    ],
    "sg:phone":"+1 519 884 5907",
    "sg:postcode":"N2G 1A7",
    "sg:province":"ON",
    "wof:name":"Baha'l Information Ctr",
    "wof:placetype":"venue"
},
  "geometry": {"coordinates":[-80.491066,43.450371],"type":"Point"}
}