{
  "type": "Feature",
  "properties": {
    "iso:country":"CA",
    "sg:address":"8695 10E Av",
    "sg:city":"Montreal",
    "sg:classifiers":[
        {
            "category":"Retail",
            "subcategory":"Auto Repair",
            "type":"Services"
        }
    ],
    "sg:phone":"+1 514 721 1768",
    "sg:postcode":"H1Z 3B9",
    "sg:province":"QC",
    "sg:tags":[
        "body",
        "automobile",
        "painting"
    ],
    "wof:name":"Ken Carrosserie Plus",
    "wof:placetype":"venue"
},
  "geometry": {"coordinates":[-73.620834,45.568073],"type":"Point"}
}