{
  "type": "Feature",
  "properties": {
    "addr:full":"158 Rue Edouard E Magog QC J1X 1H2",
    "addr:housenumber":"158",
    "addr:postcode":"j1x 1h2",
    "addr:street":"Rue Edouard E",
    "iso:country":"CA",
    "sg:address":"158 Rue Edouard E",
    "sg:city":"Magog",
    "sg:classifiers":[
        {
            "category":"Building & Trades",
            "subcategory":"Cleaning & Sanitation",
            "type":"Services"
        }
    ],
    "sg:phone":"+1 819 868 1493",
    "sg:postcode":"J1X 1H2",
    "sg:province":"QC",
    "sg:tags":[
        "fireplace",
        "chimney"
    ],
    "wof:name":"Ramoneur Mario Gaudreau",
    "wof:placetype":"venue"
},
  "geometry": {"coordinates":[-72.13897705079999,45.2692565918],"type":"Point"}
}