{
  "type": "Feature",
  "properties": {
    "iso:country":"CA",
    "sg:address":"68 Ch Des Guides",
    "sg:city":"Ripon",
    "sg:classifiers":[
        {
            "category":"Building & Trades",
            "subcategory":"Construction",
            "type":"Services"
        }
    ],
    "sg:phone":"+1 819 428 7690",
    "sg:postcode":"J0V 1V0",
    "sg:province":"QC",
    "sg:tags":[
        "maker",
        "cabinet"
    ],
    "wof:name":"Ebenisterie DE L'Hermitage",
    "wof:placetype":"venue"
},
  "geometry": {"coordinates":[-75.0852737427,45.8419075012],"type":"Point"}
}