{
  "type": "Feature",
  "properties": {
    "iso:country":"CA",
    "sg:address":"28 Water St",
    "sg:city":"Grand Bank",
    "sg:classifiers":[
        {
            "category":"Shopping",
            "subcategory":"Discount & Variety Stores",
            "type":"Retail Goods"
        }
    ],
    "sg:phone":"+1 709 832 1310",
    "sg:postcode":"A0E 1W0",
    "sg:province":"NL",
    "sg:tags":[
        "merchandise",
        "general"
    ],
    "wof:name":"J B Foote & Sons Ltd",
    "wof:placetype":"venue"
},
  "geometry": {"coordinates":[-55.751537323,47.1011962891],"type":"Point"}
}