{
  "type": "Feature",
  "properties": {
    "addr:full":"977 Wellington Dr North Vancouver BC V7K 1L1",
    "addr:housenumber":"977",
    "addr:postcode":"v7k 1l1",
    "addr:street":"Wellington Dr",
    "iso:country":"CA",
    "sg:address":"977 Wellington Dr",
    "sg:city":"North Vancouver",
    "sg:classifiers":[
        {
            "category":"Organizations",
            "subcategory":"Professional Association",
            "type":"Services"
        }
    ],
    "sg:phone":"+1 604 988 5231",
    "sg:postcode":"V7K 1L1",
    "sg:province":"BC",
    "sg:tags":[
        "club"
    ],
    "wof:name":"Tgif Singles Inc",
    "wof:placetype":"venue"
},
  "geometry": {"coordinates":[-123.046684265,49.3433952332],"type":"Point"}
}