{
  "type": "Feature",
  "properties": {
    "iso:country":"CA",
    "sg:address":"181 Bank St",
    "sg:city":"Ottawa",
    "sg:classifiers":[
        {
            "category":"Government",
            "subcategory":"Post Office",
            "type":"Public Place"
        }
    ],
    "sg:phone":"+1 613 238 5758",
    "sg:postcode":"K2P 1W5",
    "sg:province":"ON",
    "wof:name":"Unicentre",
    "wof:placetype":"venue"
},
  "geometry": {"coordinates":[-75.698547,45.418163],"type":"Point"}
}