{
  "type": "Feature",
  "properties": {
    "addr:full":"271 Wilsey Rd Fredericton NB E3B 5J2",
    "addr:housenumber":"271",
    "addr:postcode":"e3b 5j2",
    "addr:street":"Wilsey Rd",
    "iso:country":"CA",
    "sg:address":"271 Wilsey Rd",
    "sg:city":"Fredericton",
    "sg:classifiers":[
        {
            "category":"Retail",
            "subcategory":"Auto Repair",
            "type":"Services"
        }
    ],
    "sg:phone":"+1 506 453 1105",
    "sg:postcode":"E3B 5J2",
    "sg:province":"NB",
    "sg:tags":[
        "transmission"
    ],
    "wof:name":"Norco Transmission Svc",
    "wof:placetype":"venue"
},
  "geometry": {"coordinates":[-66.6188201904,45.9242286682],"type":"Point"}
}