{
  "type": "Feature",
  "properties": {
    "iso:country":"CA",
    "sg:address":"1221 Rue Labadie",
    "sg:city":"Longueuil",
    "sg:classifiers":[
        {
            "category":"Autos & Motor Vehicles",
            "subcategory":"Motorcycle Sales",
            "type":"Retail Goods"
        }
    ],
    "sg:phone":"+1 450 670 3727",
    "sg:postcode":"J4N 1E2",
    "sg:province":"QC",
    "wof:name":"Cosden Specialites",
    "wof:placetype":"venue"
},
  "geometry": {"coordinates":[-73.455086,45.563904],"type":"Point"}
}