{
  "type": "Feature",
  "properties": {
    "addr:full":"1600 Rue Sauriol E Montreal QC H2C 1X1",
    "addr:housenumber":"1600",
    "addr:postcode":"h2c 1x1",
    "addr:street":"Rue Sauriol E",
    "iso:country":"CA",
    "sg:address":"1600 Rue Sauriol E",
    "sg:city":"Montreal",
    "sg:classifiers":[
        {
            "category":"Professional",
            "subcategory":"Engineering",
            "type":"Services"
        }
    ],
    "sg:phone":"+1 514 384 8276",
    "sg:postcode":"H2C 1X1",
    "sg:province":"QC",
    "sg:tags":[
        "engineer"
    ],
    "wof:name":"Robert Forcione & Assoc Inc",
    "wof:placetype":"venue"
},
  "geometry": {"coordinates":[-73.652382,45.563107],"type":"Point"}
}