{
  "type": "Feature",
  "properties": {
    "addr:full":"592 Upper James St Hamilton ON L9C 2Y8",
    "addr:housenumber":"592",
    "addr:postcode":"l9c 2y8",
    "addr:street":"Upper James St",
    "iso:country":"CA",
    "sg:address":"592 Upper James St",
    "sg:city":"Hamilton",
    "sg:classifiers":[
        {
            "category":"Professional",
            "subcategory":"Accounting & Tax Preparation",
            "type":"Services"
        }
    ],
    "sg:phone":"+1 905 575 9001",
    "sg:postcode":"L9C 2Y8",
    "sg:province":"ON",
    "sg:tags":[
        "accountant"
    ],
    "wof:name":"Accounting & Business Svc",
    "wof:placetype":"venue"
},
  "geometry": {"coordinates":[-79.87725830079999,43.2393722534],"type":"Point"}
}