{
  "type": "Feature",
  "properties": {
    "addr:full":"1217 Car Des Bouleaux Saint-Felicien QC G8K 2K9",
    "addr:housenumber":"1217",
    "addr:postcode":"g8k 2k9",
    "addr:street":"Car Des Bouleaux",
    "iso:country":"CA",
    "sg:address":"1217 Car Des Bouleaux",
    "sg:city":"Saint-Felicien",
    "sg:classifiers":[
        {
            "category":"Building & Trades",
            "subcategory":"Construction",
            "type":"Services"
        }
    ],
    "sg:phone":"+1 418 679 3494",
    "sg:postcode":"G8K 2K9",
    "sg:province":"QC",
    "sg:tags":[
        "general",
        "contractor"
    ],
    "wof:name":"Constructions Bdg",
    "wof:placetype":"venue"
},
  "geometry": {"coordinates":[-72.454475,48.652111],"type":"Point"}
}