{
  "type": "Feature",
  "properties": {
    "addr:full":"310 Arnold Rd Abbotsford BC V3G 1S4",
    "addr:housenumber":"310",
    "addr:postcode":"v3g 1s4",
    "addr:street":"Arnold Rd",
    "iso:country":"CA",
    "sg:address":"310 Arnold Rd",
    "sg:city":"Abbotsford",
    "sg:classifiers":[
        {
            "category":"Organizations",
            "subcategory":"Religious Organization",
            "type":"Services"
        }
    ],
    "sg:phone":"+1 604 864 2208",
    "sg:postcode":"V3G 1S4",
    "sg:province":"BC",
    "sg:tags":[
        "church"
    ],
    "wof:name":"Arnold Community Church",
    "wof:placetype":"venue"
},
  "geometry": {"coordinates":[-122.150352,49.008873],"type":"Point"}
}