{
  "type": "Feature",
  "properties": {
    "addr:full":"20 Bryant St Regina SK S4S 3W6",
    "addr:housenumber":"20",
    "addr:postcode":"s4s 3w6",
    "addr:street":"Bryant St",
    "iso:country":"CA",
    "sg:address":"20 Bryant St",
    "sg:city":"Regina",
    "sg:classifiers":[
        {
            "category":"Retail",
            "subcategory":"Auto Repair",
            "type":"Services"
        }
    ],
    "sg:phone":"+1 306 569 9002",
    "sg:postcode":"S4S 3W6",
    "sg:province":"SK",
    "sg:tags":[
        "tire"
    ],
    "wof:name":"Prairie Truck Tire Svc Ltd",
    "wof:placetype":"venue"
},
  "geometry": {"coordinates":[-104.603111267,50.4128608704],"type":"Point"}
}