{
  "type": "Feature",
  "properties": {
    "addr:full":"710 Balmoral St Thunder Bay ON P7C 5V3",
    "addr:housenumber":"710",
    "addr:postcode":"p7c 5v3",
    "addr:street":"Balmoral St",
    "iso:country":"CA",
    "sg:address":"710 Balmoral St",
    "sg:city":"Thunder Bay",
    "sg:classifiers":[
        {
            "category":"Wholesale",
            "subcategory":"Machinery & Supplies",
            "type":"Manufacturing & Wholesale Goods"
        }
    ],
    "sg:phone":"+1 807 623 4447",
    "sg:postcode":"P7C 5V3",
    "sg:province":"ON",
    "sg:tags":[
        "contractor"
    ],
    "wof:name":"George O Hill Supply Ltd",
    "wof:placetype":"venue"
},
  "geometry": {"coordinates":[-89.25803399999999,48.395359],"type":"Point"}
}