{
  "type": "Feature",
  "properties": {
    "addr:full":"506 Boul Saint-Joseph E Montreal QC H2J 1J9",
    "addr:housenumber":"506",
    "addr:postcode":"h2j 1j9",
    "addr:street":"Boul Saint-Joseph E",
    "iso:country":"CA",
    "sg:address":"506 Boul Saint-Joseph E",
    "sg:city":"Montreal",
    "sg:classifiers":[
        {
            "category":"Professional",
            "subcategory":"Lawyer & Legal Services",
            "type":"Services"
        }
    ],
    "sg:phone":"+1 514 523 1455",
    "sg:postcode":"H2J 1J9",
    "sg:province":"QC",
    "sg:tags":[
        "attorney"
    ],
    "wof:name":"Laplante & Assoc",
    "wof:placetype":"venue"
},
  "geometry": {"coordinates":[-73.586647,45.527435],"type":"Point"}
}