{
  "type": "Feature",
  "properties": {
    "addr:full":"West Vancouver BC V7T 2J2",
    "addr:postcode":"v7t 2j2",
    "iso:country":"CA",
    "sg:city":"West Vancouver",
    "sg:classifiers":[
        {
            "category":"Restaurant",
            "type":"Food & Drink"
        }
    ],
    "sg:phone":"+1 604 984 4606",
    "sg:postcode":"V7T 2J2",
    "sg:province":"BC",
    "wof:name":"Earl's Restaurants Ltd",
    "wof:placetype":"venue"
},
  "geometry": {"coordinates":[-123.12434399999999,49.33316],"type":"Point"}
}