{
  "type": "Feature",
  "properties": {
    "iso:country":"CA",
    "sg:city":"Ottawa",
    "sg:classifiers":[
        {
            "category":"Shopping",
            "subcategory":"Music",
            "type":"Retail Goods"
        }
    ],
    "sg:phone":"+1 613 230 2699",
    "sg:postcode":"K1N 9J7",
    "sg:province":"ON",
    "sg:tags":[
        "compact",
        "record",
        "disc",
        "tape"
    ],
    "wof:name":"Music World",
    "wof:placetype":"venue"
},
  "geometry": {"coordinates":[-75.691765,45.444431],"type":"Point"}
}