{
  "type": "Feature",
  "properties": {
    "addr:full":"Waterloo ON N2L 3V4",
    "addr:postcode":"n2l 3v4",
    "iso:country":"CA",
    "sg:city":"Waterloo",
    "sg:classifiers":[
        {
            "category":"Insurance",
            "subcategory":"Insurance Agent",
            "type":"Services"
        }
    ],
    "sg:phone":"+1 519 885 1500",
    "sg:postcode":"N2L 3V4",
    "sg:province":"ON",
    "wof:name":"State Farm Insurance CO",
    "wof:placetype":"venue"
},
  "geometry": {"coordinates":[-80.541229,43.486683],"type":"Point"}
}