{
  "type": "Feature",
  "properties": {
    "addr:full":"Toronto ON M4W 2G9",
    "addr:postcode":"m4w 2g9",
    "iso:country":"CA",
    "sg:city":"Toronto",
    "sg:classifiers":[
        {
            "category":"Professional",
            "subcategory":"Management & Consulting",
            "type":"Services"
        }
    ],
    "sg:phone":"+1 416 972 1901",
    "sg:postcode":"M4W 2G9",
    "sg:province":"ON",
    "sg:tags":[
        "town",
        "city",
        "regional",
        "planner"
    ],
    "wof:name":"Mmc Intl Canada Architects",
    "wof:placetype":"venue"
},
  "geometry": {"coordinates":[-79.387535,43.672562],"type":"Point"}
}