{
  "type": "Feature",
  "properties": {
    "addr:full":"32 Lakeshore Rd New Liskeard ON P0J 1P0",
    "addr:housenumber":"32",
    "addr:postcode":"p0j 1p0",
    "addr:street":"Lakeshore Rd",
    "iso:country":"CA",
    "sg:address":"32 Lakeshore Rd",
    "sg:city":"New Liskeard",
    "sg:classifiers":[
        {
            "category":"Social Services",
            "type":"Services"
        }
    ],
    "sg:phone":"+1 705 647 3662",
    "sg:postcode":"P0J 1P0",
    "sg:province":"ON",
    "sg:tags":[
        "organization",
        "welfare"
    ],
    "wof:name":"Hope Ctr",
    "wof:placetype":"venue"
},
  "geometry": {"coordinates":[-79.674736,47.507805],"type":"Point"}
}