{
  "type": "Feature",
  "properties": {
    "addr:full":"250 Rue Principale O Magog QC J1X 2A5",
    "addr:housenumber":"250",
    "addr:postcode":"j1x 2a5",
    "addr:street":"Rue Principale O",
    "iso:country":"CA",
    "sg:address":"250 Rue Principale O",
    "sg:city":"Magog",
    "sg:classifiers":[
        {
            "category":"Shopping",
            "type":"Retail Goods"
        }
    ],
    "sg:phone":"+1 819 843 2834",
    "sg:postcode":"J1X 2A5",
    "sg:province":"QC",
    "sg:tags":[
        "picture",
        "frame"
    ],
    "wof:name":"Studio Rc",
    "wof:placetype":"venue"
},
  "geometry": {"coordinates":[-72.1397323608,45.2627029419],"type":"Point"}
}