{
  "type": "Feature",
  "properties": {
    "addr:full":"12 St Clair Ave E Toronto ON M4T 1L7",
    "addr:housenumber":"12",
    "addr:postcode":"m4t 1l7",
    "addr:street":"St Clair Ave E",
    "iso:country":"CA",
    "sg:address":"12 St Clair Ave E",
    "sg:city":"Toronto",
    "sg:classifiers":[
        {
            "category":"Shopping",
            "subcategory":"Luggage & Leather Goods",
            "type":"Retail Goods"
        }
    ],
    "sg:phone":"+1 416 923 2112",
    "sg:postcode":"M4T 1L7",
    "sg:province":"ON",
    "wof:name":"K Jamson Luggage CO",
    "wof:placetype":"venue"
},
  "geometry": {"coordinates":[-79.393631,43.688305],"type":"Point"}
}