{
  "type": "Feature",
  "properties": {
    "addr:full":"200 Rue Principale St-Sauveur-Des-Monts QC J0R 1R0",
    "addr:housenumber":"200",
    "addr:postcode":"j0r 1r0",
    "addr:street":"Rue Principale",
    "iso:country":"CA",
    "sg:address":"200 Rue Principale",
    "sg:city":"St-Sauveur-Des-Monts",
    "sg:classifiers":[
        {
            "category":"Professional",
            "subcategory":"Computer Services",
            "type":"Services"
        }
    ],
    "sg:phone":"+1 450 227 6200",
    "sg:postcode":"J0R 1R0",
    "sg:province":"QC",
    "sg:tags":[
        "internet"
    ],
    "wof:name":"Programaction Marketing Inc",
    "wof:placetype":"venue"
},
  "geometry": {"coordinates":[-74.156509,45.895504],"type":"Point"}
}