{
  "type": "Feature",
  "properties": {
    "addr:full":"1435 Ch Sainte-Foy Quebec QC G1S 2N7",
    "addr:housenumber":"1435",
    "addr:postcode":"g1s 2n7",
    "addr:street":"Ch Sainte-Foy",
    "iso:country":"CA",
    "sg:address":"1435 Ch Sainte-Foy",
    "sg:city":"Quebec",
    "sg:classifiers":[
        {
            "category":"Retail",
            "subcategory":"Animal Services",
            "type":"Services"
        }
    ],
    "sg:phone":"+1 418 688 1222",
    "sg:postcode":"G1S 2N7",
    "sg:province":"QC",
    "sg:tags":[
        "pet",
        "shop"
    ],
    "wof:name":"Animalerie Belle-Griffe",
    "wof:placetype":"venue"
},
  "geometry": {"coordinates":[-71.2565994263,46.7935409546],"type":"Point"}
}