{
  "type": "Feature",
  "properties": {
    "addr:full":"5360 Forest Hill Dr Mississauga ON L5M 5B7",
    "addr:housenumber":"5360",
    "addr:postcode":"l5m 5b7",
    "addr:street":"Forest Hill Dr",
    "iso:country":"CA",
    "sg:address":"5360 Forest Hill Dr",
    "sg:city":"Mississauga",
    "sg:classifiers":[
        {
            "category":"Marine",
            "type":"Transportation"
        }
    ],
    "sg:phone":"+1 905 858 2563",
    "sg:postcode":"L5M 5B7",
    "sg:province":"ON",
    "sg:tags":[
        "surveyor"
    ],
    "wof:name":"Apex Marine Surveyors",
    "wof:placetype":"venue"
},
  "geometry": {"coordinates":[-79.71228000000001,43.570007],"type":"Point"}
}