{
  "type": "Feature",
  "properties": {
    "iso:country":"CA",
    "sg:address":"5360 Forest Hill Dr",
    "sg:city":"Mississauga",
    "sg:classifiers":[
        {
            "category":"Marine",
            "type":"Transportation"
        }
    ],
    "sg:phone":"+1 905 858 2563",
    "sg:postcode":"L5M 5B7",
    "sg:province":"ON",
    "sg:tags":[
        "surveyor"
    ],
    "wof:name":"Apex Marine Surveyors",
    "wof:placetype":"venue"
},
  "geometry": {"coordinates":[-79.71228,43.570007],"type":"Point"}
}