{
  "type": "Feature",
  "properties": {
    "addr:full":"4112 91A St NW Edmonton AB T6E 5V2",
    "addr:housenumber":"4112",
    "addr:postcode":"t6e 5v2",
    "addr:street":"91A St Nw",
    "iso:country":"CA",
    "sg:address":"4112 91A St NW",
    "sg:city":"Edmonton",
    "sg:classifiers":[
        {
            "category":"Wholesale",
            "subcategory":"Machinery & Supplies",
            "type":"Manufacturing & Wholesale Goods"
        }
    ],
    "sg:phone":"+1 780 450 3600",
    "sg:postcode":"T6E 5V2",
    "sg:province":"AB",
    "sg:tags":[
        "actuator",
        "valve"
    ],
    "wof:name":"Bettis Canada Ltd",
    "wof:placetype":"venue"
},
  "geometry": {"coordinates":[-113.46790313699999,53.4771156311],"type":"Point"}
}