{
  "type": "Feature",
  "properties": {
    "addr:full":"1676 Robson St Vancouver BC V6G 1C7",
    "addr:housenumber":"1676",
    "addr:postcode":"v6g 1c7",
    "addr:street":"Robson St",
    "iso:country":"CA",
    "sg:address":"1676 Robson St",
    "sg:city":"Vancouver",
    "sg:classifiers":[
        {
            "category":"Sports & Exercise",
            "subcategory":"Gym",
            "type":"Entertainment"
        }
    ],
    "sg:phone":"+1 604 915 3032",
    "sg:postcode":"V6G 1C7",
    "sg:province":"BC",
    "sg:tags":[
        "club",
        "health",
        "studio",
        "gymnasium"
    ],
    "wof:name":"World Gym",
    "wof:placetype":"venue"
},
  "geometry": {"coordinates":[-123.133636475,49.2900848389],"type":"Point"}
}