{
  "type": "Feature",
  "properties": {
    "addr:full":"3395 Rue Du Mont-Terrible Sainte-Adele QC J8B 2G8",
    "addr:housenumber":"3395",
    "addr:postcode":"j8b 2g8",
    "addr:street":"Rue Du Mont-Terrible Sainte-Adele",
    "iso:country":"CA",
    "sg:address":"3395 Rue Du Mont-Terrible",
    "sg:city":"Sainte-Adele",
    "sg:classifiers":[
        {
            "category":"Insurance",
            "subcategory":"Insurance Agent",
            "type":"Services"
        }
    ],
    "sg:phone":"+1 450 229 4025",
    "sg:postcode":"J8B 2G8",
    "sg:province":"QC",
    "wof:name":"Bentley Berthiaume Inc",
    "wof:placetype":"venue"
},
  "geometry": {"coordinates":[-74.154205,45.982533],"type":"Point"}
}