{
  "type": "Feature",
  "properties": {
    "addr:full":"2141 Government St Victoria BC V8T 4P2",
    "addr:housenumber":"2141",
    "addr:postcode":"v8t 4p2",
    "addr:street":"Government St",
    "iso:country":"CA",
    "sg:address":"2141 Government St",
    "sg:city":"Victoria",
    "sg:classifiers":[
        {
            "category":"Autos & Motor Vehicles",
            "subcategory":"Auto Supplies",
            "type":"Retail Goods"
        }
    ],
    "sg:phone":"+1 250 361 3933",
    "sg:postcode":"V8T 4P2",
    "sg:province":"BC",
    "sg:tags":[
        "battery"
    ],
    "wof:name":"Battery Direct Victoria",
    "wof:placetype":"venue"
},
  "geometry": {"coordinates":[-123.367050171,48.4330978394],"type":"Point"}
}