{
  "type": "Feature",
  "properties": {
    "addr:full":"Nepean ON K2J 1A1",
    "addr:postcode":"k2j 1a1",
    "iso:country":"CA",
    "sg:city":"Nepean",
    "sg:classifiers":[
        {
            "category":"Personal",
            "subcategory":"Beauty Salon",
            "type":"Services"
        }
    ],
    "sg:phone":"+1 613 825 2225",
    "sg:postcode":"K2J 1A1",
    "sg:province":"ON",
    "wof:name":"Salon Europa Hair Moda",
    "wof:placetype":"venue"
},
  "geometry": {"coordinates":[-75.757462,45.287663],"type":"Point"}
}