{
  "type": "Feature",
  "properties": {
    "addr:full":"558 Dundas St W Toronto ON M5T 1H3",
    "addr:housenumber":"558",
    "addr:postcode":"m5t 1h3",
    "addr:street":"Dundas St W",
    "iso:country":"CA",
    "sg:address":"558 Dundas St W",
    "sg:city":"Toronto",
    "sg:classifiers":[
        {
            "category":"Food & Beverages",
            "subcategory":"Specialty",
            "type":"Retail Goods"
        }
    ],
    "sg:phone":"+1 416 597 8367",
    "sg:postcode":"M5T 1H3",
    "sg:province":"ON",
    "sg:tags":[
        "herb"
    ],
    "wof:name":"Hu Chun Tang Chinese",
    "wof:placetype":"venue"
},
  "geometry": {"coordinates":[-79.3996963501,43.6526756287],"type":"Point"}
}