{
  "type": "Feature",
  "properties": {
    "addr:full":"36 Mississaga St W Orillia ON L3V 3A6",
    "addr:housenumber":"36",
    "addr:postcode":"l3v 3a6",
    "addr:street":"Mississaga St W",
    "iso:country":"CA",
    "sg:address":"36 Mississaga St W",
    "sg:city":"Orillia",
    "sg:classifiers":[
        {
            "category":"Education",
            "subcategory":"Library",
            "type":"Public Place"
        }
    ],
    "sg:phone":"+1 705 325 2556",
    "sg:postcode":"L3V 3A6",
    "sg:province":"ON",
    "wof:name":"Orillia Public Library",
    "wof:placetype":"venue"
},
  "geometry": {"coordinates":[-79.420784,44.607956],"type":"Point"}
}