{
  "type": "Feature",
  "properties": {
    "addr:full":"1349 Lasalle Blvd Sudbury ON P3A 1Z2",
    "addr:housenumber":"1349",
    "addr:postcode":"p3a 1z2",
    "addr:street":"Lasalle Blvd",
    "iso:country":"CA",
    "sg:address":"1349 Lasalle Blvd",
    "sg:city":"Sudbury",
    "sg:classifiers":[
        {
            "category":"Shopping",
            "subcategory":"Clothing, Apparel, & Fashions",
            "type":"Retail Goods"
        }
    ],
    "sg:phone":"+1 705 566 6699",
    "sg:postcode":"P3A 1Z2",
    "sg:province":"ON",
    "wof:name":"Cleo",
    "wof:placetype":"venue"
},
  "geometry": {"coordinates":[-80.949989,46.52198],"type":"Point"}
}