{
  "type": "Feature",
  "properties": {
    "addr:full":"Oakville ON L6H 2B9",
    "addr:postcode":"l6h 2b9",
    "iso:country":"CA",
    "sg:city":"Oakville",
    "sg:classifiers":[
        {
            "category":"Insurance",
            "subcategory":"Insurance Agent",
            "type":"Services"
        }
    ],
    "sg:phone":"+1 905 842 1020",
    "sg:postcode":"L6H 2B9",
    "sg:province":"ON",
    "wof:name":"State Farm Insurance CO",
    "wof:placetype":"venue"
},
  "geometry": {"coordinates":[-79.688889,43.468231],"type":"Point"}
}