{
  "type": "Feature",
  "properties": {
    "addr:full":"Head of Chezzetcook NS B0J 1N0",
    "addr:postcode":"b0j 1n0",
    "iso:country":"CA",
    "sg:city":"Head of Chezzetcook",
    "sg:classifiers":[
        {
            "category":"Recreation",
            "type":"Entertainment"
        }
    ],
    "sg:phone":"+1 902 827 4265",
    "sg:postcode":"B0J 1N0",
    "sg:province":"NS",
    "sg:tags":[
        "provincial",
        "parks"
    ],
    "wof:name":"Nathan Smith Park",
    "wof:placetype":"venue"
},
  "geometry": {"coordinates":[-63.2361450195,44.7488555908],"type":"Point"}
}