{
  "type": "Feature",
  "properties": {
    "addr:full":"Scarborough ON M1J 1A1",
    "addr:postcode":"m1j 1a1",
    "iso:country":"CA",
    "sg:city":"Scarborough",
    "sg:classifiers":[
        {
            "category":"Building & Trades",
            "subcategory":"Construction",
            "type":"Services"
        }
    ],
    "sg:phone":"+1 416 264 3127",
    "sg:postcode":"M1J 1A1",
    "sg:province":"ON",
    "sg:tags":[
        "railing"
    ],
    "wof:name":"J Wyka Welding",
    "wof:placetype":"venue"
},
  "geometry": {"coordinates":[-79.246048,43.731464],"type":"Point"}
}