{
  "type": "Feature",
  "properties": {
    "addr:full":"339 Bloor St W # 213 Toronto ON M5S 1W7",
    "addr:housenumber":"339",
    "addr:postcode":"m5s 1w7",
    "addr:street":"Bloor St W # 213",
    "iso:country":"CA",
    "sg:address":"339 Bloor St W # 213",
    "sg:city":"Toronto",
    "sg:classifiers":[
        {
            "category":"Professional",
            "subcategory":"Business Services",
            "type":"Services"
        }
    ],
    "sg:phone":"+1 416 599 9393",
    "sg:postcode":"M5S 1W7",
    "sg:province":"ON",
    "sg:tags":[
        "event"
    ],
    "wof:name":"Butler Did It Event Design Inc",
    "wof:placetype":"venue"
},
  "geometry": {"coordinates":[-79.4006729126,43.6671791077],"type":"Point"}
}