{
  "type": "Feature",
  "properties": {
    "addr:full":"173 Brock St N Whitby ON L1N 4H3",
    "addr:housenumber":"173",
    "addr:postcode":"l1n 4h3",
    "addr:street":"Brock St N",
    "iso:country":"CA",
    "sg:address":"173 Brock St N",
    "sg:city":"Whitby",
    "sg:classifiers":[
        {
            "category":"Education",
            "subcategory":"Special Training",
            "type":"Public Place"
        }
    ],
    "sg:phone":"+1 905 655 0138",
    "sg:postcode":"L1N 4H3",
    "sg:province":"ON",
    "sg:tags":[
        "lecture",
        "management",
        "bureau",
        "seminar"
    ],
    "wof:name":"Life By Design",
    "wof:placetype":"venue"
},
  "geometry": {"coordinates":[-78.9424667358,43.8812904358],"type":"Point"}
}