{
  "type": "Feature",
  "properties": {
    "addr:full":"8740 14E Av Montreal QC H1Z 3M5",
    "addr:housenumber":"8740",
    "addr:postcode":"h1z 3m5",
    "addr:street":"14E Av",
    "iso:country":"CA",
    "sg:address":"8740 14E Av",
    "sg:city":"Montreal",
    "sg:classifiers":[
        {
            "category":"Shopping",
            "subcategory":"Clothing, Apparel, & Fashions",
            "type":"Retail Goods"
        }
    ],
    "sg:phone":"+1 514 722 2222",
    "sg:postcode":"H1Z 3M5",
    "sg:province":"QC",
    "sg:tags":[
        "item",
        "boutique"
    ],
    "wof:name":"Moda Spani Inc",
    "wof:placetype":"venue"
},
  "geometry": {"coordinates":[-73.61990400000001,45.570229],"type":"Point"}
}