{
  "type": "Feature",
  "properties": {
    "addr:full":"172 Hillcrest Ave Hamilton ON L8P 2X4",
    "addr:housenumber":"172",
    "addr:postcode":"l8p 2x4",
    "addr:street":"Hillcrest Ave",
    "iso:country":"CA",
    "sg:address":"172 Hillcrest Ave",
    "sg:city":"Hamilton",
    "sg:classifiers":[
        {
            "category":"Professional",
            "subcategory":"Research",
            "type":"Services"
        }
    ],
    "sg:phone":"+1 905 529 0678",
    "sg:postcode":"L8P 2X4",
    "sg:province":"ON",
    "sg:tags":[
        "environmental",
        "ecological"
    ],
    "wof:name":"M & A Environmental Consultant",
    "wof:placetype":"venue"
},
  "geometry": {"coordinates":[-79.8956375122,43.2469215393],"type":"Point"}
}