{
  "type": "Feature",
  "properties": {
    "addr:full":"5017 50 St Beaumont AB T4X 1J9",
    "addr:housenumber":"5017",
    "addr:postcode":"t4x 1j9",
    "addr:street":"50 St",
    "iso:country":"CA",
    "sg:address":"5017 50 St",
    "sg:city":"Beaumont",
    "sg:classifiers":[
        {
            "category":"Restaurant",
            "type":"Food & Drink"
        }
    ],
    "sg:phone":"+1 780 929 5515",
    "sg:postcode":"T4X 1J9",
    "sg:province":"AB",
    "wof:name":"Beaujolais Restaurant Pizza",
    "wof:placetype":"venue"
},
  "geometry": {"coordinates":[-113.415161,53.352798],"type":"Point"}
}