{
  "type": "Feature",
  "properties": {
    "addr:full":"380 Foyston Rd London ON N6K 2J8",
    "addr:housenumber":"380",
    "addr:postcode":"n6k 2j8",
    "addr:street":"Foyston Rd",
    "iso:country":"CA",
    "sg:address":"380 Foyston Rd",
    "sg:city":"London",
    "sg:classifiers":[
        {
            "category":"Insurance",
            "subcategory":"Insurance Agent",
            "type":"Services"
        }
    ],
    "sg:phone":"+1 519 472 1074",
    "sg:postcode":"N6K 2J8",
    "sg:province":"ON",
    "wof:name":"Conrad Eggel Insurance",
    "wof:placetype":"venue"
},
  "geometry": {"coordinates":[-81.330254,42.955231],"type":"Point"}
}