{
  "type": "Feature",
  "properties": {
    "iso:country":"CA",
    "sg:address":"380 Foyston Rd",
    "sg:city":"London",
    "sg:classifiers":[
        {
            "category":"Insurance",
            "subcategory":"Insurance Agent",
            "type":"Services"
        }
    ],
    "sg:phone":"+1 519 472 1074",
    "sg:postcode":"N6K 2J8",
    "sg:province":"ON",
    "wof:name":"Conrad Eggel Insurance",
    "wof:placetype":"venue"
},
  "geometry": {"coordinates":[-81.330254,42.955231],"type":"Point"}
}