{
  "type": "Feature",
  "properties": {
    "addr:full":"220 Rue Longueuil Saint-Jean-Sur-Richelieu QC J3B 6P4",
    "addr:housenumber":"220",
    "addr:postcode":"j3b 6p4",
    "addr:street":"Rue Longueuil",
    "iso:country":"CA",
    "sg:address":"220 Rue Longueuil",
    "sg:city":"Saint-Jean-Sur-Richelieu",
    "sg:classifiers":[
        {
            "category":"Professional",
            "subcategory":"Business Services",
            "type":"Services"
        }
    ],
    "sg:phone":"+1 450 347 1424",
    "sg:postcode":"J3B 6P4",
    "sg:province":"QC",
    "sg:tags":[
        "notary"
    ],
    "wof:name":"Ouimet, Johanne",
    "wof:placetype":"venue"
},
  "geometry": {"coordinates":[-73.254989624,45.3065109253],"type":"Point"}
}