{
  "type": "Feature",
  "properties": {
    "iso:country":"CA",
    "sg:address":"4726 Rue Alexander",
    "sg:city":"Pierrefonds",
    "sg:classifiers":[
        {
            "category":"Retail",
            "subcategory":"Laundry & Dry Cleaning",
            "type":"Services"
        }
    ],
    "sg:phone":"+1 514 421 4554",
    "sg:postcode":"H8Y 2B1",
    "sg:province":"QC",
    "sg:tags":[
        "cleaners"
    ],
    "wof:name":"Westside Cleaners",
    "wof:placetype":"venue"
},
  "geometry": {"coordinates":[-73.776443,45.502617],"type":"Point"}
}