{
  "type": "Feature",
  "properties": {
    "iso:country":"CA",
    "sg:address":"734 Rue Notre-Dame E",
    "sg:city":"Trois-Pistoles",
    "sg:classifiers":[
        {
            "category":"Travel",
            "subcategory":"Hotels & Motels",
            "type":"Entertainment"
        }
    ],
    "sg:phone":"+1 418 851 2736",
    "sg:postcode":"G0L 4K0",
    "sg:province":"QC",
    "wof:name":"Motel LA Seigneurie Inc",
    "wof:placetype":"venue"
},
  "geometry": {"coordinates":[-69.15529632569999,48.1360664368],"type":"Point"}
}