{
  "type": "Feature",
  "properties": {
    "addr:full":"150 Ottawa St N Hamilton ON L8H 3Z3",
    "addr:housenumber":"150",
    "addr:postcode":"l8h 3z3",
    "addr:street":"Ottawa St N",
    "iso:country":"CA",
    "sg:address":"150 Ottawa St N",
    "sg:city":"Hamilton",
    "sg:classifiers":[
        {
            "category":"Food & Beverages",
            "subcategory":"Bakery",
            "type":"Retail Goods"
        }
    ],
    "sg:phone":"+1 905 545 2154",
    "sg:postcode":"L8H 3Z3",
    "sg:province":"ON",
    "sg:tags":[
        "baker"
    ],
    "wof:name":"Quality Bakery",
    "wof:placetype":"venue"
},
  "geometry": {"coordinates":[-79.81787109379999,43.2467041016],"type":"Point"}
}