{
  "type": "Feature",
  "properties": {
    "addr:full":"2411 West Railway St Abbotsford BC V2S 2E3",
    "addr:housenumber":"2411",
    "addr:postcode":"v2s 2e3",
    "addr:street":"West Railway St",
    "iso:country":"CA",
    "sg:address":"2411 West Railway St",
    "sg:city":"Abbotsford",
    "sg:classifiers":[
        {
            "category":"Social Services",
            "subcategory":"Adult Care",
            "type":"Services"
        }
    ],
    "sg:phone":"+1 604 853 3078",
    "sg:postcode":"V2S 2E3",
    "sg:province":"BC",
    "sg:tags":[
        "community",
        "facility"
    ],
    "wof:name":"Sunrise Special Care Facility",
    "wof:placetype":"venue"
},
  "geometry": {"coordinates":[-122.285042,49.045315],"type":"Point"}
}