{
  "type": "Feature",
  "properties": {
    "iso:country":"CA",
    "sg:address":"971 Chancery St",
    "sg:city":"Kingston",
    "sg:classifiers":[
        {
            "category":"Health Services",
            "subcategory":"Health Practitioner",
            "type":"Services"
        }
    ],
    "sg:phone":"+1 613 384 7557",
    "sg:postcode":"K7P 1R4",
    "sg:province":"ON",
    "sg:tags":[
        "nurse",
        "registry"
    ],
    "wof:name":"Caracare Community Health Svc",
    "wof:placetype":"venue"
},
  "geometry": {"coordinates":[-76.5915527344,44.2554893494],"type":"Point"}
}