{
  "type": "Feature",
  "properties": {
    "addr:full":"4450 Tucana Crt Mississauga ON L5R 3R4",
    "addr:housenumber":"4450",
    "addr:postcode":"l5r 3r4",
    "addr:street":"Tucana Crt",
    "iso:country":"CA",
    "sg:address":"4450 Tucana Crt",
    "sg:city":"Mississauga",
    "sg:classifiers":[
        {
            "category":"Real Estate",
            "subcategory":"Real Estate Operator",
            "type":"Services"
        }
    ],
    "sg:phone":"+1 905 507 8490",
    "sg:postcode":"L5R 3R4",
    "sg:province":"ON",
    "sg:tags":[
        "condominium"
    ],
    "wof:name":"Peel Condominium Corp 455",
    "wof:placetype":"venue"
},
  "geometry": {"coordinates":[-79.6490783691,43.6022758484],"type":"Point"}
}