{
  "type": "Feature",
  "properties": {
    "addr:full":"3072 Post Rd Antigonish NS B2G 2K3",
    "addr:housenumber":"3072",
    "addr:postcode":"b2g 2k3",
    "addr:street":"Post Rd",
    "iso:country":"CA",
    "sg:address":"3072 Post Rd",
    "sg:city":"Antigonish",
    "sg:classifiers":[
        {
            "category":"Sports & Exercise",
            "subcategory":"Bowling",
            "type":"Entertainment"
        }
    ],
    "sg:phone":"+1 902 863 2695",
    "sg:postcode":"B2G 2K3",
    "sg:province":"NS",
    "sg:tags":[
        "center"
    ],
    "wof:name":"Pinns Entertainment Bowling",
    "wof:placetype":"venue"
},
  "geometry": {"coordinates":[-62.01812,45.60857],"type":"Point"}
}