{
  "type": "Feature",
  "properties": {
    "addr:full":"111 Rue Commerciale Saint-Lazare-DE-Bellechasse QC G0R 3J0",
    "addr:housenumber":"111",
    "addr:postcode":"g0r 3j0",
    "addr:street":"Rue Commerciale",
    "iso:country":"CA",
    "sg:address":"111 Rue Commerciale",
    "sg:city":"Saint-Lazare-DE-Bellechasse",
    "sg:classifiers":[
        {
            "category":"Building & Trades",
            "subcategory":"Construction",
            "type":"Services"
        }
    ],
    "sg:phone":"+1 418 883 2547",
    "sg:postcode":"G0R 3J0",
    "sg:province":"QC",
    "sg:tags":[
        "foundation"
    ],
    "wof:name":"Fondations Bellechasse Inc",
    "wof:placetype":"venue"
},
  "geometry": {"coordinates":[-70.80735,46.655025],"type":"Point"}
}