{
  "type": "Feature",
  "properties": {
    "iso:country":"CA",
    "sg:city":"Calgary",
    "sg:classifiers":[
        {
            "category":"Shopping",
            "subcategory":"Clothing, Apparel, & Fashions",
            "type":"Retail Goods"
        }
    ],
    "sg:phone":"+1 403 237 0737",
    "sg:postcode":"T2P 4K8",
    "sg:province":"AB",
    "sg:tags":[
        "lingerie"
    ],
    "wof:name":"LA Senza Lingerie",
    "wof:placetype":"venue"
},
  "geometry": {"coordinates":[-114.07056427000001,51.0462112427],"type":"Point"}
}