{
  "type": "Feature",
  "properties": {
    "iso:country":"CA",
    "sg:address":"15923 116 Ave NW",
    "sg:city":"Edmonton",
    "sg:classifiers":[
        {
            "category":"Wholesale",
            "subcategory":"Apparel",
            "type":"Manufacturing & Wholesale Goods"
        }
    ],
    "sg:phone":"+1 780 448 9380",
    "sg:postcode":"T5M 3W1",
    "sg:province":"AB",
    "sg:tags":[
        "clothing"
    ],
    "wof:name":"Mpt-Shirt Inc",
    "wof:placetype":"venue"
},
  "geometry": {"coordinates":[-113.595596313,53.5663986206],"type":"Point"}
}