{
  "type": "Feature",
  "properties": {
    "addr:full":"1128 8th Ave W Vancouver BC V6H 3Z5",
    "addr:housenumber":"1128",
    "addr:postcode":"v6h 3z5",
    "addr:street":"8Th Ave W",
    "iso:country":"CA",
    "sg:address":"1128 8th Ave W",
    "sg:city":"Vancouver",
    "sg:classifiers":[
        {
            "category":"Manufacturing",
            "subcategory":"Printing",
            "type":"Manufacturing & Wholesale Goods"
        }
    ],
    "sg:phone":"+1 604 662 3419",
    "sg:postcode":"V6H 3Z5",
    "sg:province":"BC",
    "sg:tags":[
        "printer"
    ],
    "wof:name":"Ricoh Document Management",
    "wof:placetype":"venue"
},
  "geometry": {"coordinates":[-123.129768,49.264259],"type":"Point"}
}