{
  "type": "Feature",
  "properties": {
    "addr:full":"281 Ottawa St N Hamilton ON L8H 3Z8",
    "addr:housenumber":"281",
    "addr:postcode":"l8h 3z8",
    "addr:street":"Ottawa St N",
    "iso:country":"CA",
    "sg:address":"281 Ottawa St N",
    "sg:city":"Hamilton",
    "sg:classifiers":[
        {
            "category":"Shopping",
            "subcategory":"Clothing, Apparel, & Fashions",
            "type":"Retail Goods"
        }
    ],
    "sg:phone":"+1 905 549 3015",
    "sg:postcode":"L8H 3Z8",
    "sg:province":"ON",
    "sg:tags":[
        "fur",
        "business"
    ],
    "wof:name":"Nadel's Furs Inc",
    "wof:placetype":"venue"
},
  "geometry": {"coordinates":[-79.816895,43.250092],"type":"Point"}
}