{
  "type": "Feature",
  "properties": {
    "iso:country":"CA",
    "sg:city":"Kanata",
    "sg:classifiers":[
        {
            "category":"Cinema",
            "subcategory":"Movie Rental",
            "type":"Entertainment"
        }
    ],
    "sg:phone":"+1 613 591 5255",
    "sg:postcode":"K2M 2G1",
    "sg:province":"ON",
    "sg:tags":[
        "leasing",
        "video",
        "disc",
        "tape"
    ],
    "wof:name":"Flicks & Flavours",
    "wof:placetype":"venue"
},
  "geometry": {"coordinates":[-75.8676147461,45.2875862122],"type":"Point"}
}