{
  "type": "Feature",
  "properties": {
    "addr:full":"921 Rue Des Carrieres Saint-Jean-Sur-Richelieu QC J3B 2P1",
    "addr:housenumber":"921",
    "addr:postcode":"j3b 2p1",
    "addr:street":"Rue Des Carrieres",
    "iso:country":"CA",
    "sg:address":"921 Rue Des Carrieres",
    "sg:city":"Saint-Jean-Sur-Richelieu",
    "sg:classifiers":[
        {
            "category":"Retail",
            "subcategory":"Auto Repair",
            "type":"Services"
        }
    ],
    "sg:phone":"+1 450 357 0056",
    "sg:postcode":"J3B 2P1",
    "sg:province":"QC",
    "sg:tags":[
        "repairing",
        "automobile"
    ],
    "wof:name":"Jec Mecanique",
    "wof:placetype":"venue"
},
  "geometry": {"coordinates":[-73.3011474609,45.3037071228],"type":"Point"}
}