{
  "type": "Feature",
  "properties": {
    "addr:full":"298 Water St Summerside PE C1N 1B8",
    "addr:housenumber":"298",
    "addr:postcode":"c1n 1b8",
    "addr:street":"Water St",
    "iso:country":"CA",
    "sg:address":"298 Water St",
    "sg:city":"Summerside",
    "sg:classifiers":[
        {
            "category":"Recreation",
            "type":"Entertainment"
        }
    ],
    "sg:phone":"+1 902 436 7675",
    "sg:postcode":"C1N 1B8",
    "sg:province":"PE",
    "sg:tags":[
        "parlor",
        "billiard"
    ],
    "wof:name":"Doolys",
    "wof:placetype":"venue"
},
  "geometry": {"coordinates":[-63.792229,46.391579],"type":"Point"}
}