{
  "type": "Feature",
  "properties": {
    "addr:full":"43 7th Ave E Vancouver BC V5T 1M4",
    "addr:housenumber":"43",
    "addr:postcode":"v5t 1m4",
    "addr:street":"7Th Ave E",
    "iso:country":"CA",
    "sg:address":"43 7th Ave E",
    "sg:city":"Vancouver",
    "sg:classifiers":[
        {
            "category":"Manufacturing",
            "subcategory":"Printing",
            "type":"Manufacturing & Wholesale Goods"
        }
    ],
    "sg:phone":"+1 604 879 1541",
    "sg:postcode":"V5T 1M4",
    "sg:province":"BC",
    "sg:tags":[
        "printer"
    ],
    "wof:name":"New West Press CO Ltd",
    "wof:placetype":"venue"
},
  "geometry": {"coordinates":[-123.103973,49.264801],"type":"Point"}
}