{
  "type": "Feature",
  "properties": {
    "addr:full":"157 John St Toronto ON M5T 1X3",
    "addr:housenumber":"157",
    "addr:postcode":"m5t 1x3",
    "addr:street":"John St",
    "iso:country":"CA",
    "sg:address":"157 John St",
    "sg:city":"Toronto",
    "sg:classifiers":[
        {
            "category":"Shopping",
            "subcategory":"Computers & Home Electronics",
            "type":"Retail Goods"
        }
    ],
    "sg:phone":"+1 416 246 9155",
    "sg:postcode":"M5T 1X3",
    "sg:province":"ON",
    "sg:tags":[
        "equipment",
        "dealer"
    ],
    "wof:name":"Micromarcuz",
    "wof:placetype":"venue"
},
  "geometry": {"coordinates":[-79.391014,43.650097],"type":"Point"}
}