{
  "type": "Feature",
  "properties": {
    "iso:country":"CA",
    "sg:city":"Labelle",
    "sg:classifiers":[
        {
            "category":"Manufacturing",
            "subcategory":"Printing",
            "type":"Manufacturing & Wholesale Goods"
        }
    ],
    "sg:phone":"+1 819 686 2059",
    "sg:postcode":"J0T 1H0",
    "sg:province":"QC",
    "sg:tags":[
        "bookbinder"
    ],
    "wof:name":"Reliures Caron & Letourneau",
    "wof:placetype":"venue"
},
  "geometry": {"coordinates":[-74.74239349370001,46.2823181152],"type":"Point"}
}