{
  "type": "Feature",
  "properties": {
    "addr:full":"PO Box 36 Priddis AB T0L 1W0",
    "addr:housenumber":"po box 36",
    "addr:postcode":"t0l 1w0",
    "addr:street":"Priddis Ab",
    "iso:country":"CA",
    "sg:address":"PO Box 36",
    "sg:city":"Priddis",
    "sg:classifiers":[
        {
            "category":"Utilities",
            "subcategory":"Natural Gas",
            "type":"Services"
        }
    ],
    "sg:phone":"+1 403 931 2161",
    "sg:postcode":"T0L 1W0",
    "sg:province":"AB",
    "sg:tags":[
        "company"
    ],
    "wof:name":"Meota Gas CO-Operative Assn",
    "wof:placetype":"venue"
},
  "geometry": {"coordinates":[-114.327454,50.883289],"type":"Point"}
}