{
  "type": "Feature",
  "properties": {
    "addr:full":"2575 Inkster Blvd Winnipeg MB R3C 2E6",
    "addr:housenumber":"2575",
    "addr:postcode":"r3c 2e6",
    "addr:street":"Inkster Blvd",
    "iso:country":"CA",
    "sg:address":"2575 Inkster Blvd",
    "sg:city":"Winnipeg",
    "sg:classifiers":[
        {
            "category":"Freight",
            "type":"Transportation"
        }
    ],
    "sg:phone":"+1 204 694 7066",
    "sg:postcode":"R3C 2E6",
    "sg:province":"MB",
    "sg:tags":[
        "trucking"
    ],
    "wof:name":"Quik X Transportation Inc",
    "wof:placetype":"venue"
},
  "geometry": {"coordinates":[-97.228477,49.946018],"type":"Point"}
}