{
  "type": "Feature",
  "properties": {
    "addr:full":"772 Boul Blanche Baie-Comeau QC G5C 2B5",
    "addr:housenumber":"772",
    "addr:postcode":"g5c 2b5",
    "addr:street":"Boul Blanche",
    "iso:country":"CA",
    "sg:address":"772 Boul Blanche",
    "sg:city":"Baie-Comeau",
    "sg:classifiers":[
        {
            "category":"Organizations",
            "subcategory":"Professional Association",
            "type":"Services"
        }
    ],
    "sg:phone":"+1 418 589 9366",
    "sg:postcode":"G5C 2B5",
    "sg:province":"QC",
    "wof:name":"Centre DE Femmes L'Etincelle",
    "wof:placetype":"venue"
},
  "geometry": {"coordinates":[-68.259834,49.191257],"type":"Point"}
}