{
  "type": "Feature",
  "properties": {
    "addr:full":"5971 Rue Saint-Hubert Montreal QC H2S 2L8",
    "addr:housenumber":"5971",
    "addr:postcode":"h2s 2l8",
    "addr:street":"Rue Saint-Hubert",
    "iso:country":"CA",
    "sg:address":"5971 Rue Saint-Hubert",
    "sg:city":"Montreal",
    "sg:classifiers":[
        {
            "category":"Professional",
            "subcategory":"Lawyer & Legal Services",
            "type":"Services"
        }
    ],
    "sg:phone":"+1 514 277 2164",
    "sg:postcode":"H2S 2L8",
    "sg:province":"QC",
    "sg:tags":[
        "attorney"
    ],
    "wof:name":"Lachapelle, Lucien",
    "wof:placetype":"venue"
},
  "geometry": {"coordinates":[-73.5979309082,45.5339546204],"type":"Point"}
}