{
  "type": "Feature",
  "properties": {
    "addr:full":"714 Circle Dr E Saskatoon SK S7K 3T7",
    "addr:housenumber":"714",
    "addr:postcode":"s7k 3t7",
    "addr:street":"Circle Dr E",
    "iso:country":"CA",
    "sg:address":"714 Circle Dr E",
    "sg:city":"Saskatoon",
    "sg:classifiers":[
        {
            "category":"Utilities",
            "subcategory":"Mobile Phone",
            "type":"Services"
        }
    ],
    "sg:phone":"+1 306 664 3666",
    "sg:postcode":"S7K 3T7",
    "sg:province":"SK",
    "sg:tags":[
        "television",
        "radio",
        "telephone",
        "cellular"
    ],
    "wof:name":"Visions Electronics",
    "wof:placetype":"venue"
},
  "geometry": {"coordinates":[-106.65682200000001,52.158226],"type":"Point"}
}