{
  "type": "Feature",
  "properties": {
    "iso:country":"CA",
    "sg:address":"283 Boul Saint-Jean",
    "sg:city":"Pointe-Claire",
    "sg:classifiers":[
        {
            "category":"Shopping",
            "subcategory":"Clothing, Apparel, & Fashions",
            "type":"Retail Goods"
        }
    ],
    "sg:phone":"+1 514 694 2088",
    "sg:postcode":"H9R 3J1",
    "sg:province":"QC",
    "sg:tags":[
        "lingerie"
    ],
    "wof:name":"Hanna W Lingerie",
    "wof:placetype":"venue"
},
  "geometry": {"coordinates":[-73.8161697388,45.4456634521],"type":"Point"}
}