{
  "type": "Feature",
  "properties": {
    "addr:full":"1583 Dupont St Toronto ON M6P 3S5",
    "addr:housenumber":"1583",
    "addr:postcode":"m6p 3s5",
    "addr:street":"Dupont St",
    "iso:country":"CA",
    "sg:address":"1583 Dupont St",
    "sg:city":"Toronto",
    "sg:classifiers":[
        {
            "category":"Restaurant",
            "type":"Food & Drink"
        }
    ],
    "sg:phone":"+1 416 538 2626",
    "sg:postcode":"M6P 3S5",
    "sg:province":"ON",
    "sg:tags":[
        "caterer"
    ],
    "wof:name":"Picotte & Damore Catering",
    "wof:placetype":"venue"
},
  "geometry": {"coordinates":[-79.453644,43.665104],"type":"Point"}
}