{
  "type": "Feature",
  "properties": {
    "iso:country":"CA",
    "sg:city":"Kamloops",
    "sg:classifiers":[
        {
            "category":"Professional",
            "subcategory":"Lawyer & Legal Services",
            "type":"Services"
        }
    ],
    "sg:phone":"+1 250 374 3456",
    "sg:postcode":"V2C 2C8",
    "sg:province":"BC",
    "sg:tags":[
        "attorney"
    ],
    "wof:name":"Taylor Epp & Dolder",
    "wof:placetype":"venue"
},
  "geometry": {"coordinates":[-120.337807,50.675018],"type":"Point"}
}