{
  "type": "Feature",
  "properties": {
    "addr:full":"1 Willis Dr Pinawa MB R0E 1L0",
    "addr:housenumber":"1",
    "addr:postcode":"r0e 1l0",
    "addr:street":"Willis Dr Pinawa",
    "iso:country":"CA",
    "sg:address":"1 Willis Dr",
    "sg:city":"Pinawa",
    "sg:classifiers":[
        {
            "category":"Restaurant",
            "type":"Food & Drink"
        }
    ],
    "sg:phone":"+1 204 753 2760",
    "sg:postcode":"R0E 1L0",
    "sg:province":"MB",
    "sg:tags":[
        "course",
        "golf"
    ],
    "wof:name":"Pinawa Club",
    "wof:placetype":"venue"
},
  "geometry": {"coordinates":[-95.8966140747,50.1395683289],"type":"Point"}
}