{
  "type": "Feature",
  "properties": {
    "addr:full":"169 Dundonald St Fredericton NB E3B 1W7",
    "addr:housenumber":"169",
    "addr:postcode":"e3b 1w7",
    "addr:street":"Dundonald St",
    "iso:country":"CA",
    "sg:address":"169 Dundonald St",
    "sg:city":"Fredericton",
    "sg:classifiers":[
        {
            "category":"Restaurant",
            "type":"Food & Drink"
        }
    ],
    "sg:phone":"+1 506 458 8284",
    "sg:postcode":"E3B 1W7",
    "sg:province":"NB",
    "sg:tags":[
        "parlor",
        "ice",
        "cream"
    ],
    "wof:name":"Dundonald Dairy Bar",
    "wof:placetype":"venue"
},
  "geometry": {"coordinates":[-66.65554,45.956993],"type":"Point"}
}