{
  "type": "Feature",
  "properties": {
    "iso:country":"CA",
    "sg:city":"Barrie",
    "sg:classifiers":[
        {
            "category":"Retail",
            "subcategory":"Auto Repair",
            "type":"Services"
        }
    ],
    "sg:phone":"+1 705 726 1465",
    "sg:postcode":"L4N 3B6",
    "sg:province":"ON",
    "sg:tags":[
        "repairing",
        "automobile",
        "electric"
    ],
    "wof:name":"Harris Auto Electric Ltd",
    "wof:placetype":"venue"
},
  "geometry": {"coordinates":[-79.69281,44.376282],"type":"Point"}
}