{
  "type": "Feature",
  "properties": {
    "addr:full":"387 Constance Ave Victoria BC V9A 6N2",
    "addr:housenumber":"387",
    "addr:postcode":"v9a 6n2",
    "addr:street":"Constance Ave",
    "iso:country":"CA",
    "sg:address":"387 Constance Ave",
    "sg:city":"Victoria",
    "sg:classifiers":[
        {
            "category":"Home & Garden",
            "subcategory":"Building Materials",
            "type":"Retail Goods"
        }
    ],
    "sg:phone":"+1 250 361 9333",
    "sg:postcode":"V9A 6N2",
    "sg:province":"BC",
    "sg:tags":[
        "energy",
        "conservation",
        "prod"
    ],
    "wof:name":"Sundog Energy Management Inc",
    "wof:placetype":"venue"
},
  "geometry": {"coordinates":[-123.36451700000001,48.428314],"type":"Point"}
}