{
  "type": "Feature",
  "properties": {
    "addr:full":"240 Silvercreek Pky N Guelph ON N1H 1E7",
    "addr:housenumber":"240",
    "addr:postcode":"n1h 1e7",
    "addr:street":"Silvercreek Pky N",
    "iso:country":"CA",
    "sg:address":"240 Silvercreek Pky N",
    "sg:city":"Guelph",
    "sg:classifiers":[
        {
            "category":"Restaurant",
            "type":"Food & Drink"
        }
    ],
    "sg:phone":"+1 519 822 2820",
    "sg:postcode":"N1H 1E7",
    "sg:province":"ON",
    "wof:name":"Mr Sub",
    "wof:placetype":"venue"
},
  "geometry": {"coordinates":[-80.28745269780001,43.5448532104],"type":"Point"}
}