{
  "type": "Feature",
  "properties": {
    "addr:full":"63 Morrow Rd Barrie ON L4N 3V7",
    "addr:housenumber":"63",
    "addr:postcode":"l4n 3v7",
    "addr:street":"Morrow Rd",
    "iso:country":"CA",
    "sg:address":"63 Morrow Rd",
    "sg:city":"Barrie",
    "sg:classifiers":[
        {
            "category":"Wholesale",
            "subcategory":"Stationery",
            "type":"Manufacturing & Wholesale Goods"
        }
    ],
    "sg:phone":"+1 705 733 1111",
    "sg:postcode":"L4N 3V7",
    "sg:province":"ON",
    "sg:tags":[
        "product",
        "paper"
    ],
    "wof:name":"Crawford Packaging",
    "wof:placetype":"venue"
},
  "geometry": {"coordinates":[-79.70264434809999,44.3619155884],"type":"Point"}
}