{
  "type": "Feature",
  "properties": {
    "addr:full":"83 Ontario St Stratford ON N5A 3H1",
    "addr:housenumber":"83",
    "addr:postcode":"n5a 3h1",
    "addr:street":"Ontario St",
    "iso:country":"CA",
    "sg:address":"83 Ontario St",
    "sg:city":"Stratford",
    "sg:classifiers":[
        {
            "category":"Shopping",
            "subcategory":"Jewelry",
            "type":"Retail Goods"
        }
    ],
    "sg:phone":"+1 519 271 3131",
    "sg:postcode":"N5A 3H1",
    "sg:province":"ON",
    "sg:tags":[
        "jeweler"
    ],
    "wof:name":"Swansons' Jewellers",
    "wof:placetype":"venue"
},
  "geometry": {"coordinates":[-80.9818191528,43.3712921143],"type":"Point"}
}