{
  "type": "Feature",
  "properties": {
    "addr:full":"248 Rue Principale Les Eboulements QC G0A 2M0",
    "addr:housenumber":"248",
    "addr:postcode":"g0a 2m0",
    "addr:street":"Rue Principale Les Eboulements",
    "iso:country":"CA",
    "sg:address":"248 Rue Principale",
    "sg:city":"Les Eboulements",
    "sg:classifiers":[
        {
            "category":"Education",
            "subcategory":"Library",
            "type":"Public Place"
        }
    ],
    "sg:phone":"+1 418 635 2586",
    "sg:postcode":"G0A 2M0",
    "sg:province":"QC",
    "wof:name":"Bibliotheque F-A Savard",
    "wof:placetype":"venue"
},
  "geometry": {"coordinates":[-70.3170547485,47.4791564941],"type":"Point"}
}