{
  "type": "Feature",
  "properties": {
    "addr:full":"156 Rue Deland L'Acadie QC J2Y 1L1",
    "addr:housenumber":"156",
    "addr:postcode":"j2y 1l1",
    "addr:street":"Rue Deland",
    "iso:country":"CA",
    "sg:address":"156 Rue Deland",
    "sg:city":"L'Acadie",
    "sg:classifiers":[
        {
            "category":"Food & Beverages",
            "subcategory":"Groceries & Convenience Stores",
            "type":"Retail Goods"
        }
    ],
    "sg:phone":"+1 450 347 8103",
    "sg:postcode":"J2Y 1L1",
    "sg:province":"QC",
    "wof:name":"Depanneur Domaine Deland Enr",
    "wof:placetype":"venue"
},
  "geometry": {"coordinates":[-73.3043136597,45.3182868958],"type":"Point"}
}