{
  "type": "Feature",
  "properties": {
    "addr:full":"Calgary AB T3B 4M9",
    "addr:postcode":"t3b 4m9",
    "iso:country":"CA",
    "sg:city":"Calgary",
    "sg:classifiers":[
        {
            "category":"Restaurant",
            "type":"Food & Drink"
        }
    ],
    "sg:phone":"+1 403 247 1110",
    "sg:postcode":"T3B 4M9",
    "sg:province":"AB",
    "sg:tags":[
        "out",
        "pizza"
    ],
    "wof:name":"Rocco's Pizza",
    "wof:placetype":"venue"
},
  "geometry": {"coordinates":[-114.167007,51.075268],"type":"Point"}
}