{
  "type": "Feature",
  "properties": {
    "addr:full":"4643 Georgia St Burnaby BC V5C 2V6",
    "addr:housenumber":"4643",
    "addr:postcode":"v5c 2v6",
    "addr:street":"Georgia St",
    "iso:country":"CA",
    "sg:address":"4643 Georgia St",
    "sg:city":"Burnaby",
    "sg:classifiers":[
        {
            "category":"Freight",
            "type":"Transportation"
        }
    ],
    "sg:phone":"+1 604 299 7019",
    "sg:postcode":"V5C 2V6",
    "sg:province":"BC",
    "sg:tags":[
        "trucking"
    ],
    "wof:name":"Orvs Trucking Inc",
    "wof:placetype":"venue"
},
  "geometry": {"coordinates":[-122.999015808,49.278339386],"type":"Point"}
}