{
  "type": "Feature",
  "properties": {
    "addr:full":"1488 Inkster Blvd Winnipeg MB R2X 2T8",
    "addr:housenumber":"1488",
    "addr:postcode":"r2x 2t8",
    "addr:street":"Inkster Blvd",
    "iso:country":"CA",
    "sg:address":"1488 Inkster Blvd",
    "sg:city":"Winnipeg",
    "sg:classifiers":[
        {
            "category":"Autos & Motor Vehicles",
            "subcategory":"Fuel & Gas Station",
            "type":"Retail Goods"
        }
    ],
    "sg:phone":"+1 204 697 1557",
    "sg:postcode":"R2X 2T8",
    "sg:province":"MB",
    "sg:tags":[
        "oil"
    ],
    "wof:name":"Inkster Park Tempo",
    "wof:placetype":"venue"
},
  "geometry": {"coordinates":[-97.1764221191,49.9440040588],"type":"Point"}
}