{
  "type": "Feature",
  "properties": {
    "addr:full":"5716 47th St Tofield AB T0B 4J0",
    "addr:housenumber":"5716",
    "addr:postcode":"t0b 4j0",
    "addr:street":"47Th St",
    "iso:country":"CA",
    "sg:address":"5716 47th St",
    "sg:city":"Tofield",
    "sg:classifiers":[
        {
            "category":"Education",
            "subcategory":"School",
            "type":"Public Place"
        }
    ],
    "sg:phone":"+1 780 662 3010",
    "sg:postcode":"T0B 4J0",
    "sg:province":"AB",
    "wof:name":"C W Sears Elementary School",
    "wof:placetype":"venue"
},
  "geometry": {"coordinates":[-112.65625799999999,53.372894],"type":"Point"}
}