{
  "type": "Feature",
  "properties": {
    "addr:full":"Sainte-Julie QC J3E 1G2",
    "addr:postcode":"j3e 1g2",
    "iso:country":"CA",
    "sg:city":"Sainte-Julie",
    "sg:classifiers":[
        {
            "category":"Retail",
            "subcategory":"Laundry & Dry Cleaning",
            "type":"Services"
        }
    ],
    "sg:phone":"+1 450 649 2401",
    "sg:postcode":"J3E 1G2",
    "sg:province":"QC",
    "sg:tags":[
        "cleaners"
    ],
    "wof:name":"Nettoyeurs Daoust",
    "wof:placetype":"venue"
},
  "geometry": {"coordinates":[-73.32659099999999,45.585289],"type":"Point"}
}