{
  "type": "Feature",
  "properties": {
    "addr:full":"1550 Upper James St # 8 Hamilton ON L9B 2L6",
    "addr:housenumber":"1550",
    "addr:postcode":"l9b 2l6",
    "addr:street":"Upper James St # 8",
    "iso:country":"CA",
    "sg:address":"1550 Upper James St # 8",
    "sg:city":"Hamilton",
    "sg:classifiers":[
        {
            "category":"Health Services",
            "subcategory":"Doctor",
            "type":"Services"
        }
    ],
    "sg:phone":"+1 905 383 5566",
    "sg:postcode":"L9B 2L6",
    "sg:province":"ON",
    "sg:tags":[
        "dentist"
    ],
    "wof:name":"Mahler, Daniel DDS",
    "wof:placetype":"venue"
},
  "geometry": {"coordinates":[-79.892563,43.204082],"type":"Point"}
}