{
  "type": "Feature",
  "properties": {
    "addr:full":"449 Rang 8 S Saint-Bruno-Lac-Saint-Jean QC G0W 2L0",
    "addr:housenumber":"449",
    "addr:postcode":"g0w 2l0",
    "addr:street":"Rang 8 S Saint-Bruno-Lac-Saint-Jean",
    "iso:country":"CA",
    "sg:address":"449 Rang 8 S",
    "sg:city":"Saint-Bruno-Lac-Saint-Jean",
    "sg:classifiers":[
        {
            "category":"Manufacturing",
            "subcategory":"Lumber",
            "type":"Manufacturing & Wholesale Goods"
        }
    ],
    "sg:phone":"+1 418 343 3173",
    "sg:postcode":"G0W 2L0",
    "sg:province":"QC",
    "sg:tags":[
        "sawmill"
    ],
    "wof:name":"Scierie Lachance Ltee",
    "wof:placetype":"venue"
},
  "geometry": {"coordinates":[-70.889702,46.92123],"type":"Point"}
}