{
  "type": "Feature",
  "properties": {
    "iso:country":"CA",
    "sg:address":"966 Barrydowne Rd",
    "sg:city":"Sudbury",
    "sg:classifiers":[
        {
            "category":"Professional",
            "subcategory":"Management & Consulting",
            "type":"Services"
        }
    ],
    "sg:phone":"+1 705 560 9303",
    "sg:postcode":"P3A 3V3",
    "sg:province":"ON",
    "sg:tags":[
        "consultant",
        "business"
    ],
    "wof:name":"Nra Consulting Inc",
    "wof:placetype":"venue"
},
  "geometry": {"coordinates":[-80.943985,46.518272],"type":"Point"}
}