{
  "type": "Feature",
  "properties": {
    "addr:full":"Montreal QC H2L 4T3",
    "addr:postcode":"h2l 4t3",
    "iso:country":"CA",
    "sg:city":"Montreal",
    "sg:classifiers":[
        {
            "category":"Professional",
            "subcategory":"Advertising",
            "type":"Services"
        }
    ],
    "sg:phone":"+1 514 529 6664",
    "sg:postcode":"H2L 4T3",
    "sg:province":"QC",
    "wof:name":"Astral Media Outdoors Lp",
    "wof:placetype":"venue"
},
  "geometry": {"coordinates":[-73.55024,45.521309],"type":"Point"}
}