{
  "type": "Feature",
  "properties": {
    "addr:full":"501 33 St NW Calgary AB T2N 2W5",
    "addr:housenumber":"33",
    "addr:postcode":"t2n 2w5",
    "addr:street":"501;St Nw",
    "iso:country":"CA",
    "sg:address":"501 33 St NW",
    "sg:city":"Calgary",
    "sg:classifiers":[
        {
            "category":"Retail",
            "subcategory":"Auto Repair",
            "type":"Services"
        }
    ],
    "sg:phone":"+1 403 283 8585",
    "sg:postcode":"T2N 2W5",
    "sg:province":"AB",
    "sg:tags":[
        "repairing",
        "automobile"
    ],
    "wof:name":"Parkdale Auto Svc",
    "wof:placetype":"venue"
},
  "geometry": {"coordinates":[-114.135307,51.057392],"type":"Point"}
}