{
  "type": "Feature",
  "properties": {
    "iso:country":"CA",
    "sg:address":"1895 County Road 22",
    "sg:city":"Castleton",
    "sg:classifiers":[
        {
            "category":"Building & Trades",
            "subcategory":"Construction",
            "type":"Services"
        }
    ],
    "sg:phone":"+1 905 349 2360",
    "sg:postcode":"K0K 1M0",
    "sg:province":"ON",
    "sg:tags":[
        "millwright"
    ],
    "wof:name":"Cosh Mechanical Inc",
    "wof:placetype":"venue"
},
  "geometry": {"coordinates":[-77.9381103516,44.0927085876],"type":"Point"}
}