{
  "type": "Feature",
  "properties": {
    "addr:full":"8 North Ave Creighton SK S0P 0A0",
    "addr:housenumber":"8",
    "addr:postcode":"s0p 0a0",
    "addr:street":"North Ave",
    "iso:country":"CA",
    "sg:address":"8 North Ave",
    "sg:city":"Creighton",
    "sg:classifiers":[
        {
            "category":"Manufacturing",
            "subcategory":"Printing",
            "type":"Manufacturing & Wholesale Goods"
        }
    ],
    "sg:phone":"+1 306 688 3999",
    "sg:postcode":"S0P 0A0",
    "sg:province":"SK",
    "sg:tags":[
        "newspaper"
    ],
    "wof:name":"Northern Vision Gazette",
    "wof:placetype":"venue"
},
  "geometry": {"coordinates":[-101.899360657,54.7564582825],"type":"Point"}
}