{
  "type": "Feature",
  "properties": {
    "addr:full":"5000 Rue Belanger Montreal QC H1T 1C8",
    "addr:housenumber":"5000",
    "addr:postcode":"h1t 1c8",
    "addr:street":"Rue Belanger",
    "iso:country":"CA",
    "sg:address":"5000 Rue Belanger",
    "sg:city":"Montreal",
    "sg:classifiers":[
        {
            "category":"Health Services",
            "subcategory":"Hospital",
            "type":"Services"
        }
    ],
    "sg:phone":"+1 514 376 3330",
    "sg:postcode":"H1T 1C8",
    "sg:province":"QC",
    "wof:name":"Institut DE Cardiologie",
    "wof:placetype":"venue"
},
  "geometry": {"coordinates":[-73.579758,45.573551],"type":"Point"}
}