{
  "type": "Feature",
  "properties": {
    "addr:full":"Rail Lake Rd Lac LA Hache BC V0K 1T0",
    "addr:postcode":"v0k 1t0",
    "addr:street":"Rail Lake Rd",
    "iso:country":"CA",
    "sg:address":"Rail Lake Rd",
    "sg:city":"Lac LA Hache",
    "sg:classifiers":[
        {
            "category":"Travel",
            "subcategory":"Hotels & Motels",
            "type":"Entertainment"
        }
    ],
    "sg:phone":"+1 250 395 7302",
    "sg:postcode":"V0K 1T0",
    "sg:province":"BC",
    "sg:tags":[
        "resort"
    ],
    "wof:name":"Ten-Ee-Ah Lodge",
    "wof:placetype":"venue"
},
  "geometry": {"coordinates":[-121.533195496,51.8289222717],"type":"Point"}
}