{
  "type": "Feature",
  "properties": {
    "addr:full":"14 Connie Cres Concord ON L4K 2W8",
    "addr:housenumber":"14",
    "addr:postcode":"l4k 2w8",
    "addr:street":"Connie Cres",
    "iso:country":"CA",
    "sg:address":"14 Connie Cres",
    "sg:city":"Concord",
    "sg:classifiers":[
        {
            "category":"Building & Trades",
            "subcategory":"Construction",
            "type":"Services"
        }
    ],
    "sg:phone":"+1 905 669 4233",
    "sg:postcode":"L4K 2W8",
    "sg:province":"ON",
    "sg:tags":[
        "contractor"
    ],
    "wof:name":"K C Ltd",
    "wof:placetype":"venue"
},
  "geometry": {"coordinates":[-79.4905014038,43.8204536438],"type":"Point"}
}