{
  "type": "Feature",
  "properties": {
    "addr:full":"614 Connaught Dr # C Jasper AB T0E 1E0",
    "addr:housenumber":"614",
    "addr:postcode":"t0e 1e0",
    "addr:street":"Connaught Dr # C",
    "iso:country":"CA",
    "sg:address":"614 Connaught Dr # C",
    "sg:city":"Jasper",
    "sg:classifiers":[
        {
            "category":"Shopping",
            "subcategory":"Florist",
            "type":"Retail Goods"
        }
    ],
    "sg:phone":"+1 780 852 3230",
    "sg:postcode":"T0E 1E0",
    "sg:province":"AB",
    "wof:name":"Elysion Florals Antiques & Gft",
    "wof:placetype":"venue"
},
  "geometry": {"coordinates":[-118.080383,52.876179],"type":"Point"}
}