{
  "type": "Feature",
  "properties": {
    "addr:full":"70 Main St S Carman MB R0G 0J0",
    "addr:housenumber":"70",
    "addr:postcode":"r0g 0j0",
    "addr:street":"Main St S",
    "iso:country":"CA",
    "sg:address":"70 Main St S",
    "sg:city":"Carman",
    "sg:classifiers":[
        {
            "category":"Health Services",
            "subcategory":"Medical Lab",
            "type":"Services"
        }
    ],
    "sg:phone":"+1 204 745 6816",
    "sg:postcode":"R0G 0J0",
    "sg:province":"MB",
    "wof:name":"Tru-Fit Denture Clinic",
    "wof:placetype":"venue"
},
  "geometry": {"coordinates":[-98.00183105470001,49.5068855286],"type":"Point"}
}