{
  "type": "Feature",
  "properties": {
    "addr:full":"Keats Island Gibsons BC V0N 1V0",
    "addr:postcode":"v0n 1v0",
    "iso:country":"CA",
    "sg:address":"Keats Island",
    "sg:city":"Gibsons",
    "sg:classifiers":[
        {
            "category":"Travel",
            "subcategory":"Campground",
            "type":"Entertainment"
        }
    ],
    "sg:phone":"+1 604 886 7612",
    "sg:postcode":"V0N 1V0",
    "sg:province":"BC",
    "sg:tags":[
        "camp"
    ],
    "wof:name":"Keat's Camp",
    "wof:placetype":"venue"
},
  "geometry": {"coordinates":[-123.503441,49.403454],"type":"Point"}
}