{
  "type": "Feature",
  "properties": {
    "iso:country":"CA",
    "sg:address":"401 Ferguson Ave",
    "sg:city":"Haileybury",
    "sg:classifiers":[
        {
            "category":"Retail",
            "subcategory":"Portrait Studio",
            "type":"Services"
        }
    ],
    "sg:phone":"+1 705 672 2751",
    "sg:postcode":"P0J 1K0",
    "sg:province":"ON",
    "sg:tags":[
        "photographer"
    ],
    "wof:name":"Photografiks",
    "wof:placetype":"venue"
},
  "geometry": {"coordinates":[-79.63293457029999,47.4469985962],"type":"Point"}
}