{
  "type": "Feature",
  "properties": {
    "addr:full":"24 Rue Marechal Saint-Jacques QC J0K 2R0",
    "addr:housenumber":"24",
    "addr:postcode":"j0k 2r0",
    "addr:street":"Rue Marechal Saint-Jacques",
    "iso:country":"CA",
    "sg:address":"24 Rue Marechal",
    "sg:city":"Saint-Jacques",
    "sg:classifiers":[
        {
            "category":"Retail",
            "subcategory":"Auto Repair",
            "type":"Services"
        }
    ],
    "sg:phone":"+1 450 839 2621",
    "sg:postcode":"J0K 2R0",
    "sg:province":"QC",
    "sg:tags":[
        "spring"
    ],
    "wof:name":"Suspensions Mireault Et Fils",
    "wof:placetype":"venue"
},
  "geometry": {"coordinates":[-73.57196,45.944939],"type":"Point"}
}