{
  "type": "Feature",
  "properties": {
    "iso:country":"CA",
    "sg:city":"Vancouver",
    "sg:classifiers":[
        {
            "category":"Health Services",
            "subcategory":"Doctor",
            "type":"Services"
        }
    ],
    "sg:phone":"+1 604 872 7877",
    "sg:postcode":"V5N 4C8",
    "sg:province":"BC",
    "sg:tags":[
        "dentist"
    ],
    "wof:name":"Thomas Kohlgrueber Inc",
    "wof:placetype":"venue"
},
  "geometry": {"coordinates":[-123.070083618,49.2583999634],"type":"Point"}
}