{
  "type": "Feature",
  "properties": {
    "addr:full":"944 Queen's Blvd Kitchener ON N2M 1B4",
    "addr:housenumber":"944",
    "addr:postcode":"n2m 1b4",
    "addr:street":"Queen'S Blvd",
    "iso:country":"CA",
    "sg:address":"944 Queen's Blvd",
    "sg:city":"Kitchener",
    "sg:classifiers":[
        {
            "category":"Health Services",
            "subcategory":"Doctor",
            "type":"Services"
        }
    ],
    "sg:phone":"+1 519 579 3020",
    "sg:postcode":"N2M 1B4",
    "sg:province":"ON",
    "sg:tags":[
        "physician",
        "surgeon"
    ],
    "wof:name":"Tiegs, Richard G MD",
    "wof:placetype":"venue"
},
  "geometry": {"coordinates":[-80.50178527830001,43.4360847473],"type":"Point"}
}