{
  "type": "Feature",
  "properties": {
    "addr:full":"3126 Devon Dr Windsor ON N8X 4L2",
    "addr:housenumber":"3126",
    "addr:postcode":"n8x 4l2",
    "addr:street":"Devon Dr",
    "iso:country":"CA",
    "sg:address":"3126 Devon Dr",
    "sg:city":"Windsor",
    "sg:classifiers":[
        {
            "category":"Wholesale",
            "subcategory":"Metals & Minerals",
            "type":"Manufacturing & Wholesale Goods"
        }
    ],
    "sg:phone":"+1 519 972 8792",
    "sg:postcode":"N8X 4L2",
    "sg:province":"ON",
    "sg:tags":[
        "steel",
        "warehouse"
    ],
    "wof:name":"Anchor Lamina Inc",
    "wof:placetype":"venue"
},
  "geometry": {"coordinates":[-82.9961090088,42.2771224976],"type":"Point"}
}