{
  "type": "Feature",
  "properties": {
    "addr:full":"Scarborough ON M1S 4L8",
    "addr:postcode":"m1s 4l8",
    "iso:country":"CA",
    "sg:city":"Scarborough",
    "sg:classifiers":[
        {
            "category":"Insurance",
            "subcategory":"Insurance Agent",
            "type":"Services"
        }
    ],
    "sg:phone":"+1 416 298 7555",
    "sg:postcode":"M1S 4L8",
    "sg:province":"ON",
    "wof:name":"Kavluk Insurance Brokers Ltd",
    "wof:placetype":"venue"
},
  "geometry": {"coordinates":[-79.24401855470001,43.7979202271],"type":"Point"}
}