{
  "type": "Feature",
  "properties": {
    "addr:full":"1770 Halifax St Regina SK S4P 1T1",
    "addr:housenumber":"1770",
    "addr:postcode":"s4p 1t1",
    "addr:street":"Halifax St",
    "iso:country":"CA",
    "sg:address":"1770 Halifax St",
    "sg:city":"Regina",
    "sg:classifiers":[
        {
            "category":"Organizations",
            "subcategory":"Non-profit Organization",
            "type":"Services"
        }
    ],
    "sg:phone":"+1 306 569 1977",
    "sg:postcode":"S4P 1T1",
    "sg:province":"SK",
    "sg:tags":[
        "charitable",
        "institution"
    ],
    "wof:name":"Phoenix Residential Society",
    "wof:placetype":"venue"
},
  "geometry": {"coordinates":[-104.603607,50.450886],"type":"Point"}
}