{
  "type": "Feature",
  "properties": {
    "iso:country":"CA",
    "sg:city":"Parksville",
    "sg:classifiers":[
        {
            "category":"Shopping",
            "type":"Retail Goods"
        }
    ],
    "sg:phone":"+1 250 248 9844",
    "sg:postcode":"V9P 2H3",
    "sg:province":"BC",
    "sg:tags":[
        "awning",
        "canopy"
    ],
    "wof:name":"Coast Aluminum",
    "wof:placetype":"venue"
},
  "geometry": {"coordinates":[-124.304924011,49.3199729919],"type":"Point"}
}