{
  "type": "Feature",
  "properties": {
    "addr:full":"961 Boul Guimond Longueuil QC J4G 2M7",
    "addr:housenumber":"961",
    "addr:postcode":"j4g 2m7",
    "addr:street":"Boul Guimond",
    "iso:country":"CA",
    "sg:address":"961 Boul Guimond",
    "sg:city":"Longueuil",
    "sg:classifiers":[
        {
            "category":"Home & Garden",
            "subcategory":"Building Materials",
            "type":"Retail Goods"
        }
    ],
    "sg:phone":"+1 450 677 5211",
    "sg:postcode":"J4G 2M7",
    "sg:province":"QC",
    "sg:tags":[
        "door"
    ],
    "wof:name":"Menuiserie Des Pins Lf Ltee",
    "wof:placetype":"venue"
},
  "geometry": {"coordinates":[-73.4625701904,45.5629196167],"type":"Point"}
}