{
  "type": "Feature",
  "properties": {
    "addr:full":"109 Avenue B E Wynyard SK S0A 4T0",
    "addr:housenumber":"109",
    "addr:postcode":"s0a 4t0",
    "addr:street":"Avenue B E Wynyard",
    "iso:country":"CA",
    "sg:address":"109 Avenue B E",
    "sg:city":"Wynyard",
    "sg:classifiers":[
        {
            "category":"Home & Garden",
            "subcategory":"Building Materials",
            "type":"Retail Goods"
        }
    ],
    "sg:phone":"+1 306 554 2132",
    "sg:postcode":"S0A 4T0",
    "sg:province":"SK",
    "sg:tags":[
        "paint"
    ],
    "wof:name":"Lamb & Hunter Hardware Ltd",
    "wof:placetype":"venue"
},
  "geometry": {"coordinates":[-104.170417786,51.7707633972],"type":"Point"}
}