{
  "type": "Feature",
  "properties": {
    "addr:full":"Sunderland ON L0C 1H0",
    "addr:postcode":"l0c 1h0",
    "iso:country":"CA",
    "sg:city":"Sunderland",
    "sg:classifiers":[
        {
            "category":"Wholesale",
            "subcategory":"Construction Materials",
            "type":"Manufacturing & Wholesale Goods"
        }
    ],
    "sg:phone":"+1 705 357 3334",
    "sg:postcode":"L0C 1H0",
    "sg:province":"ON",
    "sg:tags":[
        "sand",
        "gravel"
    ],
    "wof:name":"Brock Aggregates Inc",
    "wof:placetype":"venue"
},
  "geometry": {"coordinates":[-79.0661392212,44.2549133301],"type":"Point"}
}