{
  "type": "Feature",
  "properties": {
    "addr:full":"2240 Av Du Mont-Royal E Montreal QC H2H 1K4",
    "addr:housenumber":"2240",
    "addr:postcode":"h2h 1k4",
    "addr:street":"Av Du Mont-Royal E",
    "iso:country":"CA",
    "sg:address":"2240 Av Du Mont-Royal E",
    "sg:city":"Montreal",
    "sg:classifiers":[
        {
            "category":"Retail",
            "subcategory":"Self-service Laundry",
            "type":"Services"
        }
    ],
    "sg:phone":"+1 514 598 9481",
    "sg:postcode":"H2H 1K4",
    "sg:province":"QC",
    "wof:name":"Buanderette Mont-Royal",
    "wof:placetype":"venue"
},
  "geometry": {"coordinates":[-73.57070899999999,45.536789],"type":"Point"}
}