{
  "type": "Feature",
  "properties": {
    "addr:full":"290 Boul Laure Sept-Iles QC G4R 1W9",
    "addr:housenumber":"290",
    "addr:postcode":"g4r 1w9",
    "addr:street":"Boul Laure Sept-Iles",
    "iso:country":"CA",
    "sg:address":"290 Boul Laure",
    "sg:city":"Sept-Iles",
    "sg:classifiers":[
        {
            "category":"Building & Trades",
            "subcategory":"Cleaning & Sanitation",
            "type":"Services"
        }
    ],
    "sg:phone":"+1 418 968 0729",
    "sg:postcode":"G4R 1W9",
    "sg:province":"QC",
    "sg:tags":[
        "janitor"
    ],
    "wof:name":"S I Net Inc",
    "wof:placetype":"venue"
},
  "geometry": {"coordinates":[-66.3690414429,50.2083015442],"type":"Point"}
}