{
  "type": "Feature",
  "properties": {
    "addr:full":"7345 Rue Saint-Hubert Montreal QC H2R 2N4",
    "addr:housenumber":"7345",
    "addr:postcode":"h2r 2n4",
    "addr:street":"Rue Saint-Hubert",
    "iso:country":"CA",
    "sg:address":"7345 Rue Saint-Hubert",
    "sg:city":"Montreal",
    "sg:classifiers":[
        {
            "category":"Building & Trades",
            "subcategory":"Equipment Rental",
            "type":"Services"
        }
    ],
    "sg:phone":"+1 514 948 4811",
    "sg:postcode":"H2R 2N4",
    "sg:province":"QC",
    "sg:tags":[
        "instrument",
        "leasing",
        "musical"
    ],
    "wof:name":"G S Audio",
    "wof:placetype":"venue"
},
  "geometry": {"coordinates":[-73.6156463623,45.5420265198],"type":"Point"}
}