{
  "type": "Feature",
  "properties": {
    "addr:full":"Regina SK S4V 1A2",
    "addr:postcode":"s4v 1a2",
    "iso:country":"CA",
    "sg:city":"Regina",
    "sg:classifiers":[
        {
            "category":"Manufacturing",
            "subcategory":"Apparel",
            "type":"Manufacturing & Wholesale Goods"
        }
    ],
    "sg:phone":"+1 306 789 2652",
    "sg:postcode":"S4V 1A2",
    "sg:province":"SK",
    "sg:tags":[
        "clothing"
    ],
    "wof:name":"Thing-A-Ma-Gyms",
    "wof:placetype":"venue"
},
  "geometry": {"coordinates":[-104.542907715,50.4361457825],"type":"Point"}
}