{
  "type": "Feature",
  "properties": {
    "addr:full":"143 Bell St Ingersoll ON N5C 2N9",
    "addr:housenumber":"143",
    "addr:postcode":"n5c 2n9",
    "addr:street":"Bell St",
    "iso:country":"CA",
    "sg:address":"143 Bell St",
    "sg:city":"Ingersoll",
    "sg:classifiers":[
        {
            "category":"Utilities",
            "subcategory":"Electric",
            "type":"Services"
        }
    ],
    "sg:phone":"+1 519 485 1820",
    "sg:postcode":"N5C 2N9",
    "sg:province":"ON",
    "sg:tags":[
        "company"
    ],
    "wof:name":"Erie Thames Power Corp",
    "wof:placetype":"venue"
},
  "geometry": {"coordinates":[-80.892357,43.040867],"type":"Point"}
}