{
  "type": "Feature",
  "properties": {
    "addr:full":"4906 Rue Jean-Talon O Montreal QC H4P 1W9",
    "addr:housenumber":"4906",
    "addr:postcode":"h4p 1w9",
    "addr:street":"Rue Jean-Talon O",
    "iso:country":"CA",
    "sg:address":"4906 Rue Jean-Talon O",
    "sg:city":"Montreal",
    "sg:classifiers":[
        {
            "category":"Shopping",
            "subcategory":"Department Store",
            "type":"Retail Goods"
        }
    ],
    "sg:phone":"+1 514 739 1962",
    "sg:postcode":"H4P 1W9",
    "sg:province":"QC",
    "sg:tags":[
        "shop",
        "second",
        "hand"
    ],
    "wof:name":"Village Valeurs Ltd",
    "wof:placetype":"venue"
},
  "geometry": {"coordinates":[-73.6490402222,45.4975013733],"type":"Point"}
}