{
  "type": "Feature",
  "properties": {
    "addr:full":"660 Main St Bengough SK S0C 0K0",
    "addr:housenumber":"660",
    "addr:postcode":"s0c 0k0",
    "addr:street":"Main St",
    "iso:country":"CA",
    "sg:address":"660 Main St",
    "sg:city":"Bengough",
    "sg:classifiers":[
        {
            "category":"Personal",
            "subcategory":"Beauty Salon",
            "type":"Services"
        }
    ],
    "sg:phone":"+1 306 268 2134",
    "sg:postcode":"S0C 0K0",
    "sg:province":"SK",
    "wof:name":"Brenda's Beauty Salon",
    "wof:placetype":"venue"
},
  "geometry": {"coordinates":[-105.12273407000001,49.3972854614],"type":"Point"}
}