{
  "type": "Feature",
  "properties": {
    "iso:country":"CA",
    "sg:address":"275 Lakeshore Rd E #A",
    "sg:city":"Mississauga",
    "sg:classifiers":[
        {
            "category":"Wholesale",
            "subcategory":"Machinery & Supplies",
            "type":"Manufacturing & Wholesale Goods"
        }
    ],
    "sg:phone":"+1 905 274 4115",
    "sg:postcode":"L5G 1G8",
    "sg:province":"ON",
    "sg:tags":[
        "machine",
        "knitting",
        "yarn"
    ],
    "wof:name":"Linda's Craftique",
    "wof:placetype":"venue"
},
  "geometry": {"coordinates":[-79.576088,43.560333],"type":"Point"}
}