{
  "type": "Feature",
  "properties": {
    "addr:full":"Mississauga ON L5C 4E7",
    "addr:postcode":"l5c 4e7",
    "iso:country":"CA",
    "sg:city":"Mississauga",
    "sg:classifiers":[
        {
            "category":"Retail",
            "subcategory":"Laundry & Dry Cleaning",
            "type":"Services"
        }
    ],
    "sg:phone":"+1 905 897 0841",
    "sg:postcode":"L5C 4E7",
    "sg:province":"ON",
    "sg:tags":[
        "cleaners"
    ],
    "wof:name":"Texus Cleaners",
    "wof:placetype":"venue"
},
  "geometry": {"coordinates":[-79.6431884766,43.5568618774],"type":"Point"}
}