{
  "type": "Feature",
  "properties": {
    "addr:full":"57 Water St Digby NS B0V 1A0",
    "addr:housenumber":"57",
    "addr:postcode":"b0v 1a0",
    "addr:street":"Water St",
    "iso:country":"CA",
    "sg:address":"57 Water St",
    "sg:city":"Digby",
    "sg:classifiers":[
        {
            "category":"Shopping",
            "subcategory":"Jewelry",
            "type":"Retail Goods"
        }
    ],
    "sg:phone":"+1 902 245 2431",
    "sg:postcode":"B0V 1A0",
    "sg:province":"NS",
    "sg:tags":[
        "jeweler"
    ],
    "wof:name":"Fancy Jewellers",
    "wof:placetype":"venue"
},
  "geometry": {"coordinates":[-65.75681299999999,44.624092],"type":"Point"}
}