{
  "type": "Feature",
  "properties": {
    "iso:country":"CA",
    "sg:address":"2304 Lakeshore Rd W",
    "sg:city":"Oakville",
    "sg:classifiers":[
        {
            "category":"Retail",
            "subcategory":"Laundry & Dry Cleaning",
            "type":"Services"
        }
    ],
    "sg:phone":"+1 905 469 1832",
    "sg:postcode":"L6L 1H3",
    "sg:province":"ON",
    "sg:tags":[
        "cleaners"
    ],
    "wof:name":"Touch of Class Dry Cleaning",
    "wof:placetype":"venue"
},
  "geometry": {"coordinates":[-79.7075424194,43.3980407715],"type":"Point"}
}