{
  "type": "Feature",
  "properties": {
    "addr:full":"Richmond BC V6V 2S6",
    "addr:postcode":"v6v 2s6",
    "iso:country":"CA",
    "sg:city":"Richmond",
    "sg:classifiers":[
        {
            "category":"Manufacturing",
            "subcategory":"Rubber & Plastics",
            "type":"Manufacturing & Wholesale Goods"
        }
    ],
    "sg:phone":"+1 604 278 8362",
    "sg:postcode":"V6V 2S6",
    "sg:province":"BC",
    "sg:tags":[
        "mold",
        "maker"
    ],
    "wof:name":"Top Fit Mould Mfg Ltd",
    "wof:placetype":"venue"
},
  "geometry": {"coordinates":[-123.081802,49.187561],"type":"Point"}
}