{
  "type": "Feature",
  "properties": {
    "addr:full":"Elmira ON N3B 2C9",
    "addr:postcode":"n3b 2c9",
    "iso:country":"CA",
    "sg:city":"Elmira",
    "sg:classifiers":[
        {
            "category":"Retail",
            "subcategory":"Auto Repair",
            "type":"Services"
        }
    ],
    "sg:phone":"+1 519 669 4400",
    "sg:postcode":"N3B 2C9",
    "sg:province":"ON",
    "sg:tags":[
        "repairing",
        "automobile"
    ],
    "wof:name":"Thompson's Auto Tech Inc",
    "wof:placetype":"venue"
},
  "geometry": {"coordinates":[-80.559242,43.590012],"type":"Point"}
}