{
  "type": "Feature",
  "properties": {
    "addr:full":"2119 Lakeshore Rd Burlington ON L7R 1A4",
    "addr:housenumber":"2119",
    "addr:postcode":"l7r 1a4",
    "addr:street":"Lakeshore Rd",
    "iso:country":"CA",
    "sg:address":"2119 Lakeshore Rd",
    "sg:city":"Burlington",
    "sg:classifiers":[
        {
            "category":"Banks & Credit Unions",
            "subcategory":"Investment Brokerage",
            "type":"Services"
        }
    ],
    "sg:phone":"+1 905 681 2122",
    "sg:postcode":"L7R 1A4",
    "sg:province":"ON",
    "sg:tags":[
        "stock",
        "broker",
        "bond"
    ],
    "wof:name":"Bmo Nesbitt Burns Inc",
    "wof:placetype":"venue"
},
  "geometry": {"coordinates":[-79.7917480469,43.3269233704],"type":"Point"}
}