{
  "type": "Feature",
  "properties": {
    "iso:country":"CA",
    "sg:address":"1711 Mccowan Rd",
    "sg:city":"Scarborough",
    "sg:classifiers":[
        {
            "category":"Government",
            "subcategory":"Post Office",
            "type":"Public Place"
        }
    ],
    "sg:phone":"+1 416 298 7840",
    "sg:postcode":"M1S 2Y3",
    "sg:province":"ON",
    "wof:name":"Canada Post Corp",
    "wof:placetype":"venue"
},
  "geometry": {"coordinates":[-79.2574310303,43.7878761292],"type":"Point"}
}