{
  "type": "Feature",
  "properties": {
    "iso:country":"CA",
    "sg:address":"116 Skyway Ave",
    "sg:city":"Etobicoke",
    "sg:classifiers":[
        {
            "category":"Freight",
            "type":"Transportation"
        }
    ],
    "sg:phone":"+1 416 674 7999",
    "sg:postcode":"M9W 4Y9",
    "sg:province":"ON",
    "wof:name":"Global Logistics Ltd",
    "wof:placetype":"venue"
},
  "geometry": {"coordinates":[-79.58257293699999,43.6829452515],"type":"Point"}
}