{
  "type": "Feature",
  "properties": {
    "addr:full":"110 Rue Cyr Saint-Bonaventure QC J0C 1C0",
    "addr:housenumber":"110",
    "addr:postcode":"j0c 1c0",
    "addr:street":"Rue Cyr",
    "iso:country":"CA",
    "sg:address":"110 Rue Cyr",
    "sg:city":"Saint-Bonaventure",
    "sg:classifiers":[
        {
            "category":"Education",
            "subcategory":"Library",
            "type":"Public Place"
        }
    ],
    "sg:phone":"+1 819 396 1676",
    "sg:postcode":"J0C 1C0",
    "sg:province":"QC",
    "wof:name":"Bibliotheque St-Bonaventure",
    "wof:placetype":"venue"
},
  "geometry": {"coordinates":[-72.68008399999999,45.965508],"type":"Point"}
}