{
  "type": "Feature",
  "properties": {
    "iso:country":"CA",
    "sg:address":"1334 Island Highway Suite 124",
    "sg:city":"Campbell River",
    "sg:classifiers":[
        {
            "category":"Professional",
            "subcategory":"Computer Services",
            "type":"Services"
        }
    ],
    "sg:postcode":"V9W 8C9",
    "sg:tags":[
        "aquaculture",
        "atlantic-salmon",
        "fish-farm",
        "west-coast",
        "vancouver-island",
        "british-columbia"
    ],
    "sg:website":"http://www.marineharvestcanada.com",
    "wof:name":"Marine Harvest Canada",
    "wof:placetype":"venue"
},
  "geometry": {"coordinates":[-125.246049,50.03142],"type":"Point"}
}