{
  "type": "Feature",
  "properties": {
    "addr:full":"1029 8th Ave W Vancouver BC V6H 1C3",
    "addr:housenumber":"1029",
    "addr:postcode":"v6h 1c3",
    "addr:street":"8Th Ave W",
    "iso:country":"CA",
    "sg:address":"1029 8th Ave W",
    "sg:city":"Vancouver",
    "sg:classifiers":[
        {
            "category":"Professional",
            "subcategory":"Art Services",
            "type":"Services"
        }
    ],
    "sg:phone":"+1 604 738 6944",
    "sg:postcode":"V6H 1C3",
    "sg:province":"BC",
    "sg:tags":[
        "graphic",
        "designer"
    ],
    "wof:name":"Brandstorm Strategies Inc",
    "wof:placetype":"venue"
},
  "geometry": {"coordinates":[-123.127380371,49.2644805908],"type":"Point"}
}