{
  "type": "Feature",
  "properties": {
    "addr:full":"Toronto ON M5T 2Z5",
    "addr:postcode":"m5t 2z5",
    "iso:country":"CA",
    "sg:city":"Toronto",
    "sg:classifiers":[
        {
            "category":"Organizations",
            "subcategory":"Professional Association",
            "type":"Services"
        }
    ],
    "sg:phone":"+1 416 597 8408",
    "sg:postcode":"M5T 2Z5",
    "sg:province":"ON",
    "wof:name":"Greenpeace Canada",
    "wof:placetype":"venue"
},
  "geometry": {"coordinates":[-79.38958700000001,43.654716],"type":"Point"}
}