{
  "type": "Feature",
  "properties": {
    "addr:full":"Destor QC J9X 5A3",
    "addr:postcode":"j9x 5a3",
    "iso:country":"CA",
    "sg:city":"Destor",
    "sg:classifiers":[
        {
            "category":"Recreation",
            "type":"Entertainment"
        }
    ],
    "sg:phone":"+1 819 637 2727",
    "sg:postcode":"J9X 5A3",
    "sg:province":"QC",
    "sg:tags":[
        "tours",
        "sightseeing"
    ],
    "wof:name":"Destination or",
    "wof:placetype":"venue"
},
  "geometry": {"coordinates":[-78.9496307373,48.4594497681],"type":"Point"}
}