{
  "type": "Feature",
  "properties": {
    "addr:full":"328 Main St E Kingsville ON N9Y 1A8",
    "addr:housenumber":"328",
    "addr:postcode":"n9y 1a8",
    "addr:street":"Main St E",
    "iso:country":"CA",
    "sg:address":"328 Main St E",
    "sg:city":"Kingsville",
    "sg:classifiers":[
        {
            "category":"Banks & Credit Unions",
            "subcategory":"Bank",
            "type":"Services"
        }
    ],
    "sg:phone":"+1 519 733 6521",
    "sg:postcode":"N9Y 1A8",
    "sg:province":"ON",
    "wof:name":"Woodslee Credit Union Ltd",
    "wof:placetype":"venue"
},
  "geometry": {"coordinates":[-82.725555,42.038597],"type":"Point"}
}