{
  "type": "Feature",
  "properties": {
    "addr:full":"1093 Prince St Lansdowne ON K0E 1L0",
    "addr:housenumber":"1093",
    "addr:postcode":"k0e 1l0",
    "addr:street":"Prince St",
    "iso:country":"CA",
    "sg:address":"1093 Prince St",
    "sg:city":"Lansdowne",
    "sg:classifiers":[
        {
            "category":"Retail",
            "subcategory":"Funeral Services",
            "type":"Services"
        }
    ],
    "sg:phone":"+1 613 659 2127",
    "sg:postcode":"K0E 1L0",
    "sg:province":"ON",
    "sg:tags":[
        "director"
    ],
    "wof:name":"Barclay Funeral Home",
    "wof:placetype":"venue"
},
  "geometry": {"coordinates":[-76.018005,44.404819],"type":"Point"}
}