{
  "type": "Feature",
  "properties": {
    "addr:full":"30 Harriet St Welland ON L3B 2H5",
    "addr:housenumber":"30",
    "addr:postcode":"l3b 2h5",
    "addr:street":"Harriet St",
    "iso:country":"CA",
    "sg:address":"30 Harriet St",
    "sg:city":"Welland",
    "sg:classifiers":[
        {
            "category":"Building & Trades",
            "subcategory":"Construction",
            "type":"Services"
        }
    ],
    "sg:phone":"+1 905 732 3390",
    "sg:postcode":"L3B 2H5",
    "sg:province":"ON",
    "sg:tags":[
        "concrete",
        "contractor",
        "general"
    ],
    "wof:name":"Zacharchuk Construction",
    "wof:placetype":"venue"
},
  "geometry": {"coordinates":[-79.23828899999999,42.974098],"type":"Point"}
}