{
  "type": "Feature",
  "properties": {
    "addr:full":"10 Rue DE L'Eglise Notre-Dame-Du-Lac QC G0L 1X0",
    "addr:housenumber":"10",
    "addr:postcode":"g0l 1x0",
    "addr:street":"Rue De L'Eglise",
    "iso:country":"CA",
    "sg:address":"10 Rue DE L'Eglise",
    "sg:city":"Notre-Dame-Du-Lac",
    "sg:classifiers":[
        {
            "category":"Insurance",
            "subcategory":"Insurance Agent",
            "type":"Services"
        }
    ],
    "sg:phone":"+1 418 899 6717",
    "sg:postcode":"G0L 1X0",
    "sg:province":"QC",
    "wof:name":"Services Financiers Garon Inc",
    "wof:placetype":"venue"
},
  "geometry": {"coordinates":[-68.7958068848,47.6134681702],"type":"Point"}
}