{
  "type": "Feature",
  "properties": {
    "addr:full":"10359 61 Ave NW Edmonton AB T6H 1L1",
    "addr:housenumber":"10359",
    "addr:postcode":"t6h 1l1",
    "addr:street":"61 Ave Nw",
    "iso:country":"CA",
    "sg:address":"10359 61 Ave NW",
    "sg:city":"Edmonton",
    "sg:classifiers":[
        {
            "category":"Retail",
            "subcategory":"Auto Repair",
            "type":"Services"
        }
    ],
    "sg:phone":"+1 780 438 0637",
    "sg:postcode":"T6H 1L1",
    "sg:province":"AB",
    "sg:tags":[
        "body",
        "automobile",
        "painting"
    ],
    "wof:name":"Brunei Autobody Ltd",
    "wof:placetype":"venue"
},
  "geometry": {"coordinates":[-113.495857,53.497746],"type":"Point"}
}