{
  "type": "Feature",
  "properties": {
    "addr:full":"Lake Louise AB T0L 1E0",
    "addr:postcode":"t0l 1e0",
    "iso:country":"CA",
    "sg:city":"Lake Louise",
    "sg:classifiers":[
        {
            "category":"Government",
            "subcategory":"Office",
            "type":"Public Place"
        }
    ],
    "sg:phone":"+1 403 522 3833",
    "sg:postcode":"T0L 1E0",
    "sg:province":"AB",
    "wof:name":"Canada Visitor Ctr",
    "wof:placetype":"venue"
},
  "geometry": {"coordinates":[-116.177978516,51.4262466431],"type":"Point"}
}