{
  "type": "Feature",
  "properties": {
    "addr:full":"8 Evergreen Estates Dr Meadow Lake SK S9X 1G3",
    "addr:housenumber":"8",
    "addr:postcode":"s9x 1g3",
    "addr:street":"Evergreen Estates Dr",
    "iso:country":"CA",
    "sg:address":"8 Evergreen Estates Dr",
    "sg:city":"Meadow Lake",
    "sg:classifiers":[
        {
            "category":"Building & Trades",
            "subcategory":"Electrical",
            "type":"Services"
        }
    ],
    "sg:phone":"+1 306 236 5747",
    "sg:postcode":"S9X 1G3",
    "sg:province":"SK",
    "sg:tags":[
        "electric",
        "contractor"
    ],
    "wof:name":"Weber Electric Ltd",
    "wof:placetype":"venue"
},
  "geometry": {"coordinates":[-108.45204200000001,54.133282],"type":"Point"}
}