{
  "type": "Feature",
  "properties": {
    "addr:full":"355 Cooper St Ottawa ON K2P 0G8",
    "addr:housenumber":"355",
    "addr:postcode":"k2p 0g8",
    "addr:street":"Cooper St",
    "iso:country":"CA",
    "sg:address":"355 Cooper St",
    "sg:city":"Ottawa",
    "sg:classifiers":[
        {
            "category":"Organizations",
            "subcategory":"Religious Organization",
            "type":"Services"
        }
    ],
    "sg:phone":"+1 613 235 5143",
    "sg:postcode":"K2P 0G8",
    "sg:province":"ON",
    "sg:tags":[
        "church"
    ],
    "wof:name":"Dominion Chalmers United Chr",
    "wof:placetype":"venue"
},
  "geometry": {"coordinates":[-75.69529,45.416912],"type":"Point"}
}