{
  "type": "Feature",
  "properties": {
    "addr:full":"75 Paquin Rd Winnipeg MB R2J 3V9",
    "addr:housenumber":"75",
    "addr:postcode":"r2j 3v9",
    "addr:street":"Paquin Rd",
    "iso:country":"CA",
    "sg:address":"75 Paquin Rd",
    "sg:city":"Winnipeg",
    "sg:classifiers":[
        {
            "category":"Wholesale",
            "subcategory":"Electrical",
            "type":"Manufacturing & Wholesale Goods"
        }
    ],
    "sg:phone":"+1 204 661 8677",
    "sg:postcode":"R2J 3V9",
    "sg:province":"MB",
    "sg:tags":[
        "transmission",
        "equipment",
        "power"
    ],
    "wof:name":"Drive-Line Svc",
    "wof:placetype":"venue"
},
  "geometry": {"coordinates":[-97.0413513184,49.8804779053],"type":"Point"}
}