{
  "type": "Feature",
  "properties": {
    "addr:full":"RR 2 Cameron ON K0M 1G0",
    "addr:postcode":"k0m 1g0",
    "addr:street":"Rr 2",
    "iso:country":"CA",
    "sg:address":"RR 2",
    "sg:city":"Cameron",
    "sg:classifiers":[
        {
            "category":"Travel",
            "subcategory":"Hotels & Motels",
            "type":"Entertainment"
        }
    ],
    "sg:phone":"+1 705 887 2909",
    "sg:postcode":"K0M 1G0",
    "sg:province":"ON",
    "sg:tags":[
        "resort"
    ],
    "wof:name":"Glen Vale Village",
    "wof:placetype":"venue"
},
  "geometry": {"coordinates":[-78.774597,44.439243],"type":"Point"}
}