{
  "type": "Feature",
  "properties": {
    "iso:country":"CA",
    "sg:address":"310 Princess St",
    "sg:city":"Saint John",
    "sg:classifiers":[
        {
            "category":"Social Services",
            "subcategory":"Child Care",
            "type":"Services"
        }
    ],
    "sg:phone":"+1 506 635 8292",
    "sg:postcode":"E2L 1L5",
    "sg:province":"NB",
    "wof:name":"Centenary Queen Square Day Ctr",
    "wof:placetype":"venue"
},
  "geometry": {"coordinates":[-66.0509567261,45.2730407715],"type":"Point"}
}