{
  "type": "Feature",
  "properties": {
    "addr:full":"1490 Boul Gaboury Mont-Joli QC G5H 3H3",
    "addr:housenumber":"1490",
    "addr:postcode":"g5h 3h3",
    "addr:street":"Boul Gaboury",
    "iso:country":"CA",
    "sg:address":"1490 Boul Gaboury",
    "sg:city":"Mont-Joli",
    "sg:classifiers":[
        {
            "category":"Restaurant",
            "type":"Food & Drink"
        }
    ],
    "sg:phone":"+1 418 775 2116",
    "sg:postcode":"G5H 3H3",
    "sg:province":"QC",
    "wof:name":"Dixie Lee Poulet Frit",
    "wof:placetype":"venue"
},
  "geometry": {"coordinates":[-68.19523599999999,48.584904],"type":"Point"}
}