{
  "type": "Feature",
  "properties": {
    "addr:full":"761 the Queensway Etobicoke ON M8Z 1N1",
    "addr:housenumber":"761",
    "addr:postcode":"m8z 1n1",
    "addr:street":"The Queensway",
    "iso:country":"CA",
    "sg:address":"761 the Queensway",
    "sg:city":"Etobicoke",
    "sg:classifiers":[
        {
            "category":"Shopping",
            "subcategory":"Computers & Home Electronics",
            "type":"Retail Goods"
        }
    ],
    "sg:phone":"+1 416 252 8494",
    "sg:postcode":"M8Z 1N1",
    "sg:province":"ON",
    "sg:tags":[
        "equipment",
        "dealer"
    ],
    "wof:name":"Compuwarex Center",
    "wof:placetype":"venue"
},
  "geometry": {"coordinates":[-79.503998,43.625961],"type":"Point"}
}