{
  "type": "Feature",
  "properties": {
    "addr:full":"51 Rue Jeannotte Vaudreuil-Dorion QC J7V 6E6",
    "addr:housenumber":"51",
    "addr:postcode":"j7v 6e6",
    "addr:street":"Rue Jeannotte",
    "iso:country":"CA",
    "sg:address":"51 Rue Jeannotte",
    "sg:city":"Vaudreuil-Dorion",
    "sg:classifiers":[
        {
            "category":"Education",
            "subcategory":"Library",
            "type":"Public Place"
        }
    ],
    "sg:phone":"+1 450 455 5588",
    "sg:postcode":"J7V 6E6",
    "sg:province":"QC",
    "wof:name":"Bibliotheque Municipale",
    "wof:placetype":"venue"
},
  "geometry": {"coordinates":[-74.0302200317,45.3970909119],"type":"Point"}
}