{
  "type": "Feature",
  "properties": {
    "addr:full":"Darlingford MB R0G 0L0",
    "addr:postcode":"r0g 0l0",
    "iso:country":"CA",
    "sg:city":"Darlingford",
    "sg:classifiers":[
        {
            "category":"Farming",
            "subcategory":"Farm & Veterinary Services",
            "type":"Manufacturing & Wholesale Goods"
        }
    ],
    "sg:phone":"+1 204 246 2500",
    "sg:postcode":"R0G 0L0",
    "sg:province":"MB",
    "sg:tags":[
        "product",
        "protection",
        "crop"
    ],
    "wof:name":"Agricore United",
    "wof:placetype":"venue"
},
  "geometry": {"coordinates":[-98.377663,49.204361],"type":"Point"}
}