{
  "type": "Feature",
  "properties": {
    "iso:country":"CA",
    "sg:address":"636 Laurier St",
    "sg:city":"Rockland",
    "sg:classifiers":[
        {
            "category":"Shopping",
            "subcategory":"Clothing, Apparel, & Fashions",
            "type":"Retail Goods"
        }
    ],
    "sg:phone":"+1 613 446 4338",
    "sg:postcode":"K4K 1E7",
    "sg:province":"ON",
    "sg:tags":[
        "shop",
        "bridal"
    ],
    "wof:name":"Bridals O.S.A",
    "wof:placetype":"venue"
},
  "geometry": {"coordinates":[-75.27448272709999,45.5542411804],"type":"Point"}
}