{
  "type": "Feature",
  "properties": {
    "addr:full":"577 Erie St Stratford ON N5A 2N7",
    "addr:housenumber":"577",
    "addr:postcode":"n5a 2n7",
    "addr:street":"Erie St",
    "iso:country":"CA",
    "sg:address":"577 Erie St",
    "sg:city":"Stratford",
    "sg:classifiers":[
        {
            "category":"Manufacturing",
            "subcategory":"Chemicals & Compounds",
            "type":"Manufacturing & Wholesale Goods"
        }
    ],
    "sg:phone":"+1 519 271 1680",
    "sg:postcode":"N5A 2N7",
    "sg:province":"ON",
    "sg:tags":[
        "plastic"
    ],
    "wof:name":"Spartech Color",
    "wof:placetype":"venue"
},
  "geometry": {"coordinates":[-80.994225,43.357677],"type":"Point"}
}