{
  "type": "Feature",
  "properties": {
    "addr:full":"460 South Railway E Boissevain MB R0K 0E0",
    "addr:housenumber":"460",
    "addr:postcode":"r0k 0e0",
    "addr:street":"South Railway E Boissevain",
    "iso:country":"CA",
    "sg:address":"460 South Railway E",
    "sg:city":"Boissevain",
    "sg:classifiers":[
        {
            "category":"Government",
            "subcategory":"Office",
            "type":"Public Place"
        }
    ],
    "sg:phone":"+1 204 534 2010",
    "sg:postcode":"R0K 0E0",
    "sg:province":"MB",
    "wof:name":"Manitoba Agriculture & Food",
    "wof:placetype":"venue"
},
  "geometry": {"coordinates":[-100.058975,49.230293],"type":"Point"}
}