{
  "type": "Feature",
  "properties": {
    "addr:full":"46 Avondale Blvd Brampton ON L6T 1H3",
    "addr:housenumber":"46",
    "addr:postcode":"l6t 1h3",
    "addr:street":"Avondale Blvd",
    "iso:country":"CA",
    "sg:address":"46 Avondale Blvd",
    "sg:city":"Brampton",
    "sg:classifiers":[
        {
            "category":"Personal",
            "subcategory":"Barber",
            "type":"Services"
        }
    ],
    "sg:phone":"+1 905 793 2189",
    "sg:postcode":"L6T 1H3",
    "sg:province":"ON",
    "sg:tags":[
        "salon",
        "beauty"
    ],
    "wof:name":"Avondale Barber Shop",
    "wof:placetype":"venue"
},
  "geometry": {"coordinates":[-79.6993026733,43.7069702148],"type":"Point"}
}