{
  "type": "Feature",
  "properties": {
    "addr:full":"Prince Albert SK S6V 3A8",
    "addr:postcode":"s6v 3a8",
    "iso:country":"CA",
    "sg:city":"Prince Albert",
    "sg:classifiers":[
        {
            "category":"Professional",
            "subcategory":"Lawyer & Legal Services",
            "type":"Services"
        }
    ],
    "sg:phone":"+1 306 764 3451",
    "sg:postcode":"S6V 3A8",
    "sg:province":"SK",
    "sg:tags":[
        "attorney"
    ],
    "wof:name":"Simonot & Hansen",
    "wof:placetype":"venue"
},
  "geometry": {"coordinates":[-105.755310059,53.2029266357],"type":"Point"}
}