{
  "type": "Feature",
  "properties": {
    "addr:full":"1770 Selkirk Ave Winnipeg MB R2R 0N6",
    "addr:housenumber":"1770",
    "addr:postcode":"r2r 0n6",
    "addr:street":"Selkirk Ave",
    "iso:country":"CA",
    "sg:address":"1770 Selkirk Ave",
    "sg:city":"Winnipeg",
    "sg:classifiers":[
        {
            "category":"Autos & Motor Vehicles",
            "subcategory":"Recreational Vehicle Sales",
            "type":"Retail Goods"
        }
    ],
    "sg:phone":"+1 204 633 1885",
    "sg:postcode":"R2R 0N6",
    "sg:province":"MB",
    "sg:tags":[
        "canopy",
        "shell",
        "truck",
        "cap"
    ],
    "wof:name":"Western Fibre Craft Ltd",
    "wof:placetype":"venue"
},
  "geometry": {"coordinates":[-97.1966018677,49.9311218262],"type":"Point"}
}