{
  "type": "Feature",
  "properties": {
    "addr:full":"191 11E Ave Senneterre QC J0Y 2M0",
    "addr:housenumber":"191",
    "addr:postcode":"j0y 2m0",
    "addr:street":"11E Ave",
    "iso:country":"CA",
    "sg:address":"191 11E Ave",
    "sg:city":"Senneterre",
    "sg:classifiers":[
        {
            "category":"Food & Beverages",
            "subcategory":"Groceries & Convenience Stores",
            "type":"Retail Goods"
        }
    ],
    "sg:phone":"+1 819 737 2145",
    "sg:postcode":"J0Y 2M0",
    "sg:province":"QC",
    "wof:name":"Depanneur M Et M",
    "wof:placetype":"venue"
},
  "geometry": {"coordinates":[-77.228928,48.391472],"type":"Point"}
}