{
  "type": "Feature",
  "properties": {
    "addr:full":"32 Ashton Rd Newmarket ON L3Y 5R4",
    "addr:housenumber":"32",
    "addr:postcode":"l3y 5r4",
    "addr:street":"Ashton Rd",
    "iso:country":"CA",
    "sg:address":"32 Ashton Rd",
    "sg:city":"Newmarket",
    "sg:classifiers":[
        {
            "category":"Professional",
            "subcategory":"Computer Services",
            "type":"Services"
        }
    ],
    "sg:phone":"+1 905 836 5727",
    "sg:postcode":"L3Y 5R4",
    "sg:province":"ON",
    "sg:tags":[
        "repair"
    ],
    "wof:name":"Systems Support Svc",
    "wof:placetype":"venue"
},
  "geometry": {"coordinates":[-79.43999481199999,44.0651931763],"type":"Point"}
}