{
  "type": "Feature",
  "properties": {
    "addr:full":"84 Walnut St S Hamilton ON L8N 2L3",
    "addr:housenumber":"84",
    "addr:postcode":"l8n 2l3",
    "addr:street":"Walnut St S",
    "iso:country":"CA",
    "sg:address":"84 Walnut St S",
    "sg:city":"Hamilton",
    "sg:classifiers":[
        {
            "category":"Personal",
            "subcategory":"Beauty Salon",
            "type":"Services"
        }
    ],
    "sg:phone":"+1 905 540 4960",
    "sg:postcode":"L8N 2L3",
    "sg:province":"ON",
    "wof:name":"Fuze",
    "wof:placetype":"venue"
},
  "geometry": {"coordinates":[-79.86451,43.252316],"type":"Point"}
}