{
  "type": "Feature",
  "properties": {
    "iso:country":"CA",
    "sg:address":"1809 Fremont Rd",
    "sg:city":"Nanaimo",
    "sg:classifiers":[
        {
            "category":"Wholesale",
            "subcategory":"Electrical",
            "type":"Manufacturing & Wholesale Goods"
        }
    ],
    "sg:phone":"+1 250 758 1777",
    "sg:postcode":"V9S 3H3",
    "sg:province":"BC",
    "sg:tags":[
        "equipment",
        "electric",
        "supply"
    ],
    "wof:name":"Wesco Distribution-Canada Inc",
    "wof:placetype":"venue"
},
  "geometry": {"coordinates":[-123.982093811,49.1938667297],"type":"Point"}
}