{
  "type": "Feature",
  "properties": {
    "iso:country":"CA",
    "sg:city":"Oshawa",
    "sg:classifiers":[
        {
            "category":"Manufacturing",
            "subcategory":"Metals",
            "type":"Manufacturing & Wholesale Goods"
        }
    ],
    "sg:phone":"+1 905 723 4400",
    "sg:postcode":"L1J 7A5",
    "sg:province":"ON",
    "sg:tags":[
        "steel"
    ],
    "wof:name":"Warren Steel",
    "wof:placetype":"venue"
},
  "geometry": {"coordinates":[-78.87651062010001,43.8563194275],"type":"Point"}
}