{
  "type": "Feature",
  "properties": {
    "iso:country":"CA",
    "sg:address":"PO Box 8116 STN Main",
    "sg:city":"Canmore",
    "sg:classifiers":[
        {
            "category":"Building & Trades",
            "subcategory":"Construction",
            "type":"Services"
        }
    ],
    "sg:phone":"+1 403 678 4353",
    "sg:postcode":"T1W 2T8",
    "sg:province":"AB",
    "sg:tags":[
        "general",
        "contractor"
    ],
    "wof:name":"J I Thomas Construction Ltd",
    "wof:placetype":"venue"
},
  "geometry": {"coordinates":[-115.360839844,51.0895652771],"type":"Point"}
}