{
  "type": "Feature",
  "properties": {
    "addr:full":"8 Bell St Stittsville ON K2S 1P3",
    "addr:housenumber":"8",
    "addr:postcode":"k2s 1p3",
    "addr:street":"Bell St",
    "iso:country":"CA",
    "sg:address":"8 Bell St",
    "sg:city":"Stittsville",
    "sg:classifiers":[
        {
            "category":"Building & Trades",
            "subcategory":"Plumbing",
            "type":"Services"
        }
    ],
    "sg:phone":"+1 613 836 2736",
    "sg:postcode":"K2S 1P3",
    "sg:province":"ON",
    "sg:tags":[
        "contractor"
    ],
    "wof:name":"Bell Plumbing",
    "wof:placetype":"venue"
},
  "geometry": {"coordinates":[-75.915947,45.253139],"type":"Point"}
}