{
  "type": "Feature",
  "properties": {
    "addr:full":"2383 Dundas St W Oakville ON L6M 4J3",
    "addr:housenumber":"2383",
    "addr:postcode":"l6m 4j3",
    "addr:street":"Dundas St W",
    "iso:country":"CA",
    "sg:address":"2383 Dundas St W",
    "sg:city":"Oakville",
    "sg:classifiers":[
        {
            "category":"Retail",
            "subcategory":"Auto Repair",
            "type":"Services"
        }
    ],
    "sg:phone":"+1 905 827 2442",
    "sg:postcode":"L6M 4J3",
    "sg:province":"ON",
    "sg:tags":[
        "repairing",
        "automobile"
    ],
    "wof:name":"George's Auto Ctr",
    "wof:placetype":"venue"
},
  "geometry": {"coordinates":[-79.77195,43.440212],"type":"Point"}
}