{
  "type": "Feature",
  "properties": {
    "iso:country":"CA",
    "sg:city":"Langley",
    "sg:classifiers":[
        {
            "category":"Wholesale",
            "subcategory":"Electrical",
            "type":"Manufacturing & Wholesale Goods"
        }
    ],
    "sg:phone":"+1 604 532 8636",
    "sg:postcode":"V3A 7A3",
    "sg:province":"BC",
    "sg:tags":[
        "equipment",
        "electric",
        "supply"
    ],
    "wof:name":"Guillevin International",
    "wof:placetype":"venue"
},
  "geometry": {"coordinates":[-122.652603,49.110146],"type":"Point"}
}