{
  "type": "Feature",
  "properties": {
    "addr:full":"322 Ottawa Ave N Saskatoon SK S7L 3P1",
    "addr:housenumber":"322",
    "addr:postcode":"s7l 3p1",
    "addr:street":"Ottawa Ave N",
    "iso:country":"CA",
    "sg:address":"322 Ottawa Ave N",
    "sg:city":"Saskatoon",
    "sg:classifiers":[
        {
            "category":"Building & Trades",
            "subcategory":"Plumbing",
            "type":"Services"
        }
    ],
    "sg:phone":"+1 306 978 2249",
    "sg:postcode":"S7L 3P1",
    "sg:province":"SK",
    "sg:tags":[
        "contractor"
    ],
    "wof:name":"Roto-Rooter Sewer & Drain Svc",
    "wof:placetype":"venue"
},
  "geometry": {"coordinates":[-106.713050842,52.1326789856],"type":"Point"}
}