{
  "type": "Feature",
  "properties": {
    "addr:full":"Chateauguay QC J6J 4Z2",
    "addr:postcode":"j6j 4z2",
    "iso:country":"CA",
    "sg:city":"Chateauguay",
    "sg:classifiers":[
        {
            "category":"Manufacturing",
            "subcategory":"Paper Products",
            "type":"Manufacturing & Wholesale Goods"
        }
    ],
    "sg:phone":"+1 450 699 4330",
    "sg:postcode":"J6J 4Z2",
    "sg:province":"QC",
    "sg:tags":[
        "tag"
    ],
    "wof:name":"Etiquettes Trelco Inc",
    "wof:placetype":"venue"
},
  "geometry": {"coordinates":[-73.698021,45.358833],"type":"Point"}
}