{
  "type": "Feature",
  "properties": {
    "addr:full":"930 Corner Ave Lefroy ON L0L 1W0",
    "addr:housenumber":"930",
    "addr:postcode":"l0l 1w0",
    "addr:street":"Corner Ave",
    "iso:country":"CA",
    "sg:address":"930 Corner Ave",
    "sg:city":"Lefroy",
    "sg:classifiers":[
        {
            "category":"Professional",
            "subcategory":"Accounting & Tax Preparation",
            "type":"Services"
        }
    ],
    "sg:phone":"+1 705 456 3053",
    "sg:postcode":"L0L 1W0",
    "sg:province":"ON",
    "sg:tags":[
        "accountant",
        "bookkeeping",
        "general"
    ],
    "wof:name":"Toplitsky, Jeff",
    "wof:placetype":"venue"
},
  "geometry": {"coordinates":[-79.554649,44.263618],"type":"Point"}
}