{
  "type": "Feature",
  "properties": {
    "addr:full":"210 P Ave S Saskatoon SK S7M 2W2",
    "addr:housenumber":"210",
    "addr:postcode":"s7m 2w2",
    "addr:street":"P Ave S",
    "iso:country":"CA",
    "sg:address":"210 P Ave S",
    "sg:city":"Saskatoon",
    "sg:classifiers":[
        {
            "category":"Social Services",
            "subcategory":"Job Training",
            "type":"Services"
        }
    ],
    "sg:phone":"+1 306 975 0210",
    "sg:postcode":"S7M 2W2",
    "sg:province":"SK",
    "sg:tags":[
        "rehabilitation"
    ],
    "wof:name":"Arthur Grey Rehabilitation",
    "wof:placetype":"venue"
},
  "geometry": {"coordinates":[-106.693832398,52.1274757385],"type":"Point"}
}