{
  "type": "Feature",
  "properties": {
    "iso:country":"CA",
    "sg:address":"11723 Boul Gouin O",
    "sg:city":"Pierrefonds",
    "sg:classifiers":[
        {
            "category":"Retail",
            "subcategory":"Auto Repair",
            "type":"Services"
        }
    ],
    "sg:phone":"+1 514 685 1441",
    "sg:postcode":"H8Z 1V7",
    "sg:province":"QC",
    "sg:tags":[
        "repairing",
        "automobile",
        "parts",
        "supply"
    ],
    "wof:name":"American Automobile Ctr Ltee",
    "wof:placetype":"venue"
},
  "geometry": {"coordinates":[-73.82251739500001,45.5083885193],"type":"Point"}
}