{
  "type": "Feature",
  "properties": {
    "addr:full":"38 Joseph St Parry Sound ON P2A 2G5",
    "addr:housenumber":"38",
    "addr:postcode":"p2a 2g5",
    "addr:street":"Joseph St",
    "iso:country":"CA",
    "sg:address":"38 Joseph St",
    "sg:city":"Parry Sound",
    "sg:classifiers":[
        {
            "category":"Organizations",
            "subcategory":"Professional Association",
            "type":"Services"
        }
    ],
    "sg:phone":"+1 705 746 9330",
    "sg:postcode":"P2A 2G5",
    "sg:province":"ON",
    "wof:name":"Community Living Parry Sound",
    "wof:placetype":"venue"
},
  "geometry": {"coordinates":[-80.03941345210001,45.3576393127],"type":"Point"}
}