{
  "type": "Feature",
  "properties": {
    "addr:full":"11905 Kingsway NW Edmonton AB T5G 0X7",
    "addr:housenumber":"11905",
    "addr:postcode":"t5g 0x7",
    "addr:street":"Kingsway Nw",
    "iso:country":"CA",
    "sg:address":"11905 Kingsway NW",
    "sg:city":"Edmonton",
    "sg:classifiers":[
        {
            "category":"Autos & Motor Vehicles",
            "subcategory":"Fuel & Gas Station",
            "type":"Retail Goods"
        }
    ],
    "sg:phone":"+1 780 453 2277",
    "sg:postcode":"T5G 0X7",
    "sg:province":"AB",
    "sg:tags":[
        "oil"
    ],
    "wof:name":"Kingsway Gas For Less",
    "wof:placetype":"venue"
},
  "geometry": {"coordinates":[-113.527046,53.568497],"type":"Point"}
}