{
  "type": "Feature",
  "properties": {
    "addr:full":"1495 Seymour St North Bay ON P1B 8G4",
    "addr:housenumber":"1495",
    "addr:postcode":"p1b 8g4",
    "addr:street":"Seymour St",
    "iso:country":"CA",
    "sg:address":"1495 Seymour St",
    "sg:city":"North Bay",
    "sg:classifiers":[
        {
            "category":"Restaurant",
            "type":"Food & Drink"
        }
    ],
    "sg:phone":"+1 705 472 0519",
    "sg:postcode":"P1B 8G4",
    "sg:province":"ON",
    "sg:tags":[
        "out"
    ],
    "wof:name":"Sub Zero Subs & Salads",
    "wof:placetype":"venue"
},
  "geometry": {"coordinates":[-79.439156,46.30846],"type":"Point"}
}