{
  "type": "Feature",
  "properties": {
    "iso:country":"CA",
    "sg:address":"15 Rue Francoise-Langlois",
    "sg:city":"Montreal",
    "sg:classifiers":[
        {
            "category":"Professional",
            "subcategory":"Lawyer & Legal Services",
            "type":"Services"
        }
    ],
    "sg:phone":"+1 514 642 1214",
    "sg:postcode":"H1A 5B5",
    "sg:province":"QC",
    "sg:tags":[
        "attorney"
    ],
    "wof:name":"Robert, Pierre",
    "wof:placetype":"venue"
},
  "geometry": {"coordinates":[-73.491104,45.677135],"type":"Point"}
}