{
  "type": "Feature",
  "properties": {
    "addr:full":"883 Hesketh Rd Quesnel BC V2J 7H5",
    "addr:housenumber":"883",
    "addr:postcode":"v2j 7h5",
    "addr:street":"Hesketh Rd",
    "iso:country":"CA",
    "sg:address":"883 Hesketh Rd",
    "sg:city":"Quesnel",
    "sg:classifiers":[
        {
            "category":"Building & Trades",
            "subcategory":"Construction",
            "type":"Services"
        }
    ],
    "sg:phone":"+1 250 992 8714",
    "sg:postcode":"V2J 7H5",
    "sg:province":"BC",
    "sg:tags":[
        "excavating",
        "contractor"
    ],
    "wof:name":"Four Star Snowplowing & Contr",
    "wof:placetype":"venue"
},
  "geometry": {"coordinates":[-122.498245,52.978119],"type":"Point"}
}