{
  "type": "Feature",
  "properties": {
    "addr:full":"Edmonton AB T5G 3A6",
    "addr:postcode":"t5g 3a6",
    "iso:country":"CA",
    "sg:city":"Edmonton",
    "sg:classifiers":[
        {
            "category":"Shopping",
            "subcategory":"Clothing, Apparel, & Fashions",
            "type":"Retail Goods"
        }
    ],
    "sg:phone":"+1 780 477 9312",
    "sg:postcode":"T5G 3A6",
    "sg:province":"AB",
    "wof:name":"Dynamite",
    "wof:placetype":"venue"
},
  "geometry": {"coordinates":[-113.508492,53.564041],"type":"Point"}
}