{
  "type": "Feature",
  "properties": {
    "iso:country":"CA",
    "sg:city":"Scarborough",
    "sg:classifiers":[
        {
            "category":"Shopping",
            "subcategory":"Optical Goods",
            "type":"Retail Goods"
        }
    ],
    "sg:phone":"+1 416 759 5671",
    "sg:postcode":"M1L 2L9",
    "sg:province":"ON",
    "sg:tags":[
        "optician"
    ],
    "wof:name":"Hakim Optical Factory Outlet",
    "wof:placetype":"venue"
},
  "geometry": {"coordinates":[-79.29485321040001,43.7264328003],"type":"Point"}
}