{
  "type": "Feature",
  "properties": {
    "addr:full":"1197 Rte Principale Sainte-Anne-Du-Sault QC G0Z 1C0",
    "addr:housenumber":"1197",
    "addr:postcode":"g0z 1c0",
    "addr:street":"Rte Principale",
    "iso:country":"CA",
    "sg:address":"1197 Rte Principale",
    "sg:city":"Sainte-Anne-Du-Sault",
    "sg:classifiers":[
        {
            "category":"Manufacturing",
            "subcategory":"Furniture",
            "type":"Manufacturing & Wholesale Goods"
        }
    ],
    "sg:phone":"+1 819 367 2078",
    "sg:postcode":"G0Z 1C0",
    "sg:province":"QC",
    "sg:tags":[
        "maker",
        "cabinet"
    ],
    "wof:name":"Pierre Et Claire Inc",
    "wof:placetype":"venue"
},
  "geometry": {"coordinates":[-72.136223,46.158871],"type":"Point"}
}