{
  "type": "Feature",
  "properties": {
    "addr:full":"133 4th Ave Regina SK S4N 6T2",
    "addr:housenumber":"133",
    "addr:postcode":"s4n 6t2",
    "addr:street":"4Th Ave",
    "iso:country":"CA",
    "sg:address":"133 4th Ave",
    "sg:city":"Regina",
    "sg:classifiers":[
        {
            "category":"Retail",
            "subcategory":"Auto Rental",
            "type":"Services"
        }
    ],
    "sg:phone":"+1 306 569 9021",
    "sg:postcode":"S4N 6T2",
    "sg:province":"SK",
    "sg:tags":[
        "renting",
        "truck",
        "leasing"
    ],
    "wof:name":"Custom Truck Sales Inc",
    "wof:placetype":"venue"
},
  "geometry": {"coordinates":[-104.582703,50.462833],"type":"Point"}
}