{
  "type": "Feature",
  "properties": {
    "iso:country":"CA",
    "sg:address":"122 Simcoe St N",
    "sg:city":"Oshawa",
    "sg:classifiers":[
        {
            "category":"Health Services",
            "subcategory":"Doctor",
            "type":"Services"
        }
    ],
    "sg:phone":"+1 905 436 6199",
    "sg:postcode":"L1G 4S5",
    "sg:province":"ON",
    "sg:tags":[
        "dentist"
    ],
    "wof:name":"Luczak, Dorothy DDS",
    "wof:placetype":"venue"
},
  "geometry": {"coordinates":[-78.86521148680001,43.9007263184],"type":"Point"}
}