{
  "type": "Feature",
  "properties": {
    "iso:country":"CA",
    "sg:address":"31 Boul Rene-Levesque O",
    "sg:city":"Quebec",
    "sg:classifiers":[
        {
            "category":"Restaurant",
            "type":"Food & Drink"
        }
    ],
    "sg:phone":"+1 418 529 8457",
    "sg:postcode":"G1R 2A3",
    "sg:province":"QC",
    "wof:name":"Restaurant Trattoria LA Scala",
    "wof:placetype":"venue"
},
  "geometry": {"coordinates":[-71.22486877439999,46.8051452637],"type":"Point"}
}