{
  "type": "Feature",
  "properties": {
    "addr:full":"RR 1 Riverhead Harbour Grace NL A0A 3P0",
    "addr:postcode":"a0a 3p0",
    "addr:street":"Rr 1",
    "iso:country":"CA",
    "sg:address":"RR 1",
    "sg:city":"Riverhead Harbour Grace",
    "sg:classifiers":[
        {
            "category":"Building & Trades",
            "subcategory":"Construction",
            "type":"Services"
        }
    ],
    "sg:phone":"+1 709 596 6023",
    "sg:postcode":"A0A 3P0",
    "sg:province":"NL",
    "sg:tags":[
        "maker",
        "cabinet"
    ],
    "wof:name":"Economy Cabinet Doors Ltd",
    "wof:placetype":"venue"
},
  "geometry": {"coordinates":[-53.24401474,47.6816673279],"type":"Point"}
}