{
  "type": "Feature",
  "properties": {
    "addr:full":"Thunder Bay ON P7B 5T1",
    "addr:postcode":"p7b 5t1",
    "iso:country":"CA",
    "sg:city":"Thunder Bay",
    "sg:classifiers":[
        {
            "category":"Real Estate",
            "subcategory":"Real Estate Operator",
            "type":"Services"
        }
    ],
    "sg:phone":"+1 807 767 4911",
    "sg:postcode":"P7B 5T1",
    "sg:province":"ON",
    "sg:tags":[
        "apartment"
    ],
    "wof:name":"Shelter Canadian Properties",
    "wof:placetype":"venue"
},
  "geometry": {"coordinates":[-89.266113,48.445526],"type":"Point"}
}