{
  "type": "Feature",
  "properties": {
    "addr:full":"7 Rue Sainte-Ursule Quebec QC G1R 4C7",
    "addr:housenumber":"7",
    "addr:postcode":"g1r 4c7",
    "addr:street":"Rue Sainte-Ursule",
    "iso:country":"CA",
    "sg:address":"7 Rue Sainte-Ursule",
    "sg:city":"Quebec",
    "sg:classifiers":[
        {
            "category":"Restaurant",
            "type":"Food & Drink"
        }
    ],
    "sg:phone":"+1 418 692 5315",
    "sg:postcode":"G1R 4C7",
    "sg:province":"QC",
    "wof:name":"Un the Au Sahara",
    "wof:placetype":"venue"
},
  "geometry": {"coordinates":[-71.211815,46.81287],"type":"Point"}
}