{
  "type": "Feature",
  "properties": {
    "addr:full":"1300 Boul Saint-Joseph Quebec QC G2K 1G2",
    "addr:housenumber":"1300",
    "addr:postcode":"g2k 1g2",
    "addr:street":"Boul Saint-Joseph",
    "iso:country":"CA",
    "sg:address":"1300 Boul Saint-Joseph",
    "sg:city":"Quebec",
    "sg:classifiers":[
        {
            "category":"Building & Trades",
            "subcategory":"Landscaping Services",
            "type":"Services"
        }
    ],
    "sg:phone":"+1 418 628 9440",
    "sg:postcode":"G2K 1G2",
    "sg:province":"QC",
    "sg:tags":[
        "nurseryman",
        "landscape",
        "contractor"
    ],
    "wof:name":"Pepiniere Moraldo & Fils Inc",
    "wof:placetype":"venue"
},
  "geometry": {"coordinates":[-71.283699,46.85347],"type":"Point"}
}