{
  "type": "Feature",
  "properties": {
    "iso:country":"CA",
    "sg:city":"London",
    "sg:classifiers":[
        {
            "category":"Building & Trades",
            "subcategory":"Construction",
            "type":"Services"
        }
    ],
    "sg:phone":"+1 519 686 9606",
    "sg:postcode":"N5Z 1Z8",
    "sg:province":"ON",
    "sg:tags":[
        "erectors",
        "machinery"
    ],
    "wof:name":"E & M Tilt Svc Ltd",
    "wof:placetype":"venue"
},
  "geometry": {"coordinates":[-81.21937561039999,42.979347229],"type":"Point"}
}