{
  "type": "Feature",
  "properties": {
    "addr:full":"3660 3E Rang N Valcourt QC J0E 2L0",
    "addr:housenumber":"3660",
    "addr:postcode":"j0e 2l0",
    "addr:street":"3E Rang N Valcourt",
    "iso:country":"CA",
    "sg:address":"3660 3E Rang N",
    "sg:city":"Valcourt",
    "sg:classifiers":[
        {
            "category":"Wholesale",
            "subcategory":"Electrical",
            "type":"Manufacturing & Wholesale Goods"
        }
    ],
    "sg:phone":"+1 450 532 4375",
    "sg:postcode":"J0E 2L0",
    "sg:province":"QC",
    "sg:tags":[
        "electric",
        "motor"
    ],
    "wof:name":"Clinique Du Moteur Elec Enr",
    "wof:placetype":"venue"
},
  "geometry": {"coordinates":[-72.296989,45.517002],"type":"Point"}
}