{
  "type": "Feature",
  "properties": {
    "addr:full":"5615 84 St SE Calgary AB T2C 4S2",
    "addr:housenumber":"5615",
    "addr:postcode":"t2c 4s2",
    "addr:street":"84 St Se",
    "iso:country":"CA",
    "sg:address":"5615 84 St SE",
    "sg:city":"Calgary",
    "sg:classifiers":[
        {
            "category":"Freight",
            "type":"Transportation"
        }
    ],
    "sg:phone":"+1 403 236 1518",
    "sg:postcode":"T2C 4S2",
    "sg:province":"AB",
    "sg:tags":[
        "horse",
        "transporting"
    ],
    "wof:name":"Moore Horse Transport Ltd",
    "wof:placetype":"venue"
},
  "geometry": {"coordinates":[-113.912139893,51.0046691895],"type":"Point"}
}