{
  "type": "Feature",
  "properties": {
    "addr:full":"237 Calvington Dr North York ON M3M 2N3",
    "addr:housenumber":"237",
    "addr:postcode":"m3m 2n3",
    "addr:street":"Calvington Dr",
    "iso:country":"CA",
    "sg:address":"237 Calvington Dr",
    "sg:city":"North York",
    "sg:classifiers":[
        {
            "category":"Building & Trades",
            "subcategory":"Construction",
            "type":"Services"
        }
    ],
    "sg:phone":"+1 416 243 3411",
    "sg:postcode":"M3M 2N3",
    "sg:province":"ON",
    "sg:tags":[
        "concrete",
        "cutting",
        "breaking",
        "sawing"
    ],
    "wof:name":"Accucore Limited",
    "wof:placetype":"venue"
},
  "geometry": {"coordinates":[-79.501053,43.729488],"type":"Point"}
}