{
  "type": "Feature",
  "properties": {
    "iso:country":"CA",
    "sg:address":"360 Rue Saint-Jacques",
    "sg:city":"Montreal",
    "sg:classifiers":[
        {
            "category":"Professional",
            "subcategory":"Business Services",
            "type":"Services"
        }
    ],
    "sg:phone":"+1 514 288 4446",
    "sg:postcode":"H2Y 1P5",
    "sg:province":"QC",
    "sg:tags":[
        "notary"
    ],
    "wof:name":"Cros Bergeron",
    "wof:placetype":"venue"
},
  "geometry": {"coordinates":[-73.559425354,45.5022315979],"type":"Point"}
}