{
  "type": "Feature",
  "properties": {
    "addr:full":"7216 Rue Saint-Hubert Montreal QC H2R 2N1",
    "addr:housenumber":"7216",
    "addr:postcode":"h2r 2n1",
    "addr:street":"Rue Saint-Hubert",
    "iso:country":"CA",
    "sg:address":"7216 Rue Saint-Hubert",
    "sg:city":"Montreal",
    "sg:classifiers":[
        {
            "category":"Restaurant",
            "type":"Food & Drink"
        }
    ],
    "sg:phone":"+1 514 276 3243",
    "sg:postcode":"H2R 2N1",
    "sg:province":"QC",
    "wof:name":"Restaurant Eche Pa'Echarle",
    "wof:placetype":"venue"
},
  "geometry": {"coordinates":[-73.614143,45.541019],"type":"Point"}
}