{
  "type": "Feature",
  "properties": {
    "addr:full":"75 Company Rd Port Hood NS B0E 2W0",
    "addr:housenumber":"75",
    "addr:postcode":"ns b0e 2w0",
    "addr:street":"Company Rd",
    "iso:country":"CA",
    "sg:address":"75 Company Rd",
    "sg:city":"Port Hood",
    "sg:classifiers":[
        {
            "category":"Utilities",
            "subcategory":"Refuse",
            "type":"Services"
        }
    ],
    "sg:phone":"+1 902 787 2622",
    "sg:postcode":"B0E 2W0",
    "sg:province":"NS",
    "sg:tags":[
        "garbage",
        "collection"
    ],
    "wof:name":"Seaside Sanitation Ltd",
    "wof:placetype":"venue"
},
  "geometry": {"coordinates":[-61.5306625366,46.0158004761],"type":"Point"}
}