{
  "type": "Feature",
  "properties": {
    "addr:full":"Mississauga ON L5N 3L8",
    "addr:postcode":"l5n 3l8",
    "iso:country":"CA",
    "sg:city":"Mississauga",
    "sg:classifiers":[
        {
            "category":"Wholesale",
            "subcategory":"Machinery & Supplies",
            "type":"Manufacturing & Wholesale Goods"
        }
    ],
    "sg:phone":"+1 905 858 2330",
    "sg:postcode":"L5N 3L8",
    "sg:province":"ON",
    "sg:tags":[
        "equipment",
        "conveyor",
        "material",
        "handling",
        "conveying"
    ],
    "wof:name":"Pacline Conveyor Corp",
    "wof:placetype":"venue"
},
  "geometry": {"coordinates":[-79.7253112793,43.5927047729],"type":"Point"}
}