{
  "type": "Feature",
  "properties": {
    "addr:full":"29 Rue Principale Saint-Andre-Avellin QC J0V 1W0",
    "addr:housenumber":"29",
    "addr:postcode":"j0v 1w0",
    "addr:street":"Rue Principale",
    "iso:country":"CA",
    "sg:address":"29 Rue Principale",
    "sg:city":"Saint-Andre-Avellin",
    "sg:classifiers":[
        {
            "category":"Retail",
            "subcategory":"Auto Repair",
            "type":"Services"
        }
    ],
    "sg:phone":"+1 819 983 2261",
    "sg:postcode":"J0V 1W0",
    "sg:province":"QC",
    "sg:tags":[
        "repairing",
        "automobile"
    ],
    "wof:name":"Garage Alain Boivin",
    "wof:placetype":"venue"
},
  "geometry": {"coordinates":[-75.05694580079999,45.7196540833],"type":"Point"}
}