{
  "type": "Feature",
  "properties": {
    "addr:full":"7548 Fallowfield Rd Stittsville ON K2S 1B8",
    "addr:housenumber":"7548",
    "addr:postcode":"k2s 1b8",
    "addr:street":"Fallowfield Rd",
    "iso:country":"CA",
    "sg:address":"7548 Fallowfield Rd",
    "sg:city":"Stittsville",
    "sg:classifiers":[
        {
            "category":"Building & Trades",
            "subcategory":"Plumbing",
            "type":"Services"
        }
    ],
    "sg:phone":"+1 613 831 3202",
    "sg:postcode":"K2S 1B8",
    "sg:province":"ON",
    "sg:tags":[
        "contractor"
    ],
    "wof:name":"Allan J Anderson Ltd",
    "wof:placetype":"venue"
},
  "geometry": {"coordinates":[-75.95166,45.18951],"type":"Point"}
}