{
  "type": "Feature",
  "properties": {
    "addr:full":"5622 Kincaid St Burnaby BC V5G 1W3",
    "addr:housenumber":"5622",
    "addr:postcode":"v5g 1w3",
    "addr:street":"Kincaid St",
    "iso:country":"CA",
    "sg:address":"5622 Kincaid St",
    "sg:city":"Burnaby",
    "sg:classifiers":[
        {
            "category":"Home & Garden",
            "subcategory":"Home Furnishings",
            "type":"Retail Goods"
        }
    ],
    "sg:phone":"+1 604 294 8028",
    "sg:postcode":"V5G 1W3",
    "sg:province":"BC",
    "sg:tags":[
        "venetian",
        "blind"
    ],
    "wof:name":"Up-Date Blinds & Parts Svc",
    "wof:placetype":"venue"
},
  "geometry": {"coordinates":[-122.980957,49.248165],"type":"Point"}
}