{
  "type": "Feature",
  "properties": {
    "iso:country":"CA",
    "sg:address":"628 Av Royale",
    "sg:city":"Beauport",
    "sg:classifiers":[
        {
            "category":"Health Services",
            "subcategory":"Chiropractor",
            "type":"Services"
        }
    ],
    "sg:phone":"+1 418 663 7744",
    "sg:postcode":"G1E 1Y7",
    "sg:province":"QC",
    "wof:name":"Clinique Chiropratique-Bprt",
    "wof:placetype":"venue"
},
  "geometry": {"coordinates":[-71.191719,46.859715],"type":"Point"}
}