{
  "type": "Feature",
  "properties": {
    "addr:full":"2009 41st Ave W Vancouver BC V6M 1Y7",
    "addr:housenumber":"2009",
    "addr:postcode":"v6m 1y7",
    "addr:street":"41St Ave W",
    "iso:country":"CA",
    "sg:address":"2009 41st Ave W",
    "sg:city":"Vancouver",
    "sg:classifiers":[
        {
            "category":"Shopping",
            "subcategory":"Used Merchandise",
            "type":"Retail Goods"
        }
    ],
    "sg:phone":"+1 604 266 8411",
    "sg:postcode":"V6M 1Y7",
    "sg:province":"BC",
    "sg:tags":[
        "shop",
        "consignment"
    ],
    "wof:name":"N2O",
    "wof:placetype":"venue"
},
  "geometry": {"coordinates":[-123.152412415,49.2346496582],"type":"Point"}
}