{
  "type": "Feature",
  "properties": {
    "addr:full":"2860 Keele St North York ON M3M 2G8",
    "addr:housenumber":"2860",
    "addr:postcode":"m3m 2g8",
    "addr:street":"Keele St",
    "iso:country":"CA",
    "sg:address":"2860 Keele St",
    "sg:city":"North York",
    "sg:classifiers":[
        {
            "category":"Personal",
            "subcategory":"Barber",
            "type":"Services"
        }
    ],
    "sg:phone":"+1 416 633 9656",
    "sg:postcode":"M3M 2G8",
    "sg:province":"ON",
    "wof:name":"Iabonis Barber Shop",
    "wof:placetype":"venue"
},
  "geometry": {"coordinates":[-79.4835357666,43.73204422],"type":"Point"}
}