{
  "type": "Feature",
  "properties": {
    "addr:full":"5561 Rue Frontenac Lac-Megantic QC G6B 1H6",
    "addr:housenumber":"5561",
    "addr:postcode":"g6b 1h6",
    "addr:street":"Rue Frontenac Lac-Megantic",
    "iso:country":"CA",
    "sg:address":"5561 Rue Frontenac",
    "sg:city":"Lac-Megantic",
    "sg:classifiers":[
        {
            "category":"Government",
            "subcategory":"Office",
            "type":"Public Place"
        }
    ],
    "sg:phone":"+1 819 583 0630",
    "sg:postcode":"G6B 1H6",
    "sg:province":"QC",
    "sg:tags":[
        "village"
    ],
    "wof:name":"Lac Megantic Svc Loisirs",
    "wof:placetype":"venue"
},
  "geometry": {"coordinates":[-70.881531,45.573666],"type":"Point"}
}