{
  "type": "Feature",
  "properties": {
    "addr:full":"Brockville ON K6V 3T5",
    "addr:postcode":"k6v 3t5",
    "iso:country":"CA",
    "sg:city":"Brockville",
    "sg:classifiers":[
        {
            "category":"Food & Beverages",
            "subcategory":"Groceries & Convenience Stores",
            "type":"Retail Goods"
        }
    ],
    "sg:phone":"+1 613 345 1818",
    "sg:postcode":"K6V 3T5",
    "sg:province":"ON",
    "wof:name":"Long Beach Convenience Store",
    "wof:placetype":"venue"
},
  "geometry": {"coordinates":[-75.683014,44.590389],"type":"Point"}
}