{
  "type": "Feature",
  "properties": {
    "addr:full":"3292 Dunmore Rd SE # 230 Medicine Hat AB T1B 2R4",
    "addr:housenumber":"3292",
    "addr:postcode":"t1b 2r4",
    "addr:street":"Dunmore Rd Se # 230",
    "iso:country":"CA",
    "sg:address":"3292 Dunmore Rd SE # 230",
    "sg:city":"Medicine Hat",
    "sg:classifiers":[
        {
            "category":"Shopping",
            "subcategory":"Clothing, Apparel, & Fashions",
            "type":"Retail Goods"
        }
    ],
    "sg:phone":"+1 403 528 9597",
    "sg:postcode":"T1B 2R4",
    "sg:province":"AB",
    "wof:name":"Cotton Ginny",
    "wof:placetype":"venue"
},
  "geometry": {"coordinates":[-110.647041,50.007183],"type":"Point"}
}