{
  "type": "Feature",
  "properties": {
    "iso:country":"CA",
    "sg:address":"4390 Grange St #103",
    "sg:city":"Burnaby",
    "sg:classifiers":[
        {
            "category":"Real Estate",
            "subcategory":"Real Estate Operator",
            "type":"Services"
        }
    ],
    "sg:phone":"+1 604 433 2424",
    "sg:postcode":"V5H 1P6",
    "sg:province":"BC",
    "sg:tags":[
        "apartment"
    ],
    "wof:name":"Panarama Tower",
    "wof:placetype":"venue"
},
  "geometry": {"coordinates":[-123.006484985,49.2321357727],"type":"Point"}
}