{
  "type": "Feature",
  "properties": {
    "addr:full":"640 Ellis Rd W Cambridge ON N3C 4K1",
    "addr:housenumber":"640",
    "addr:postcode":"n3c 4k1",
    "addr:street":"Ellis Rd W",
    "iso:country":"CA",
    "sg:address":"640 Ellis Rd W",
    "sg:city":"Cambridge",
    "sg:classifiers":[
        {
            "category":"Retail",
            "subcategory":"Repair Shop",
            "type":"Services"
        }
    ],
    "sg:phone":"+1 519 658 5282",
    "sg:postcode":"N3C 4K1",
    "sg:province":"ON",
    "sg:tags":[
        "sharpening"
    ],
    "wof:name":"Don's Sports Repair Svc",
    "wof:placetype":"venue"
},
  "geometry": {"coordinates":[-80.29429626460001,43.4279670715],"type":"Point"}
}