{
  "type": "Feature",
  "properties": {
    "addr:full":"1545 Lyn Rd Brockville ON K6V 5T3",
    "addr:housenumber":"1545",
    "addr:postcode":"k6v 5t3",
    "addr:street":"Lyn Rd",
    "iso:country":"CA",
    "sg:address":"1545 Lyn Rd",
    "sg:city":"Brockville",
    "sg:classifiers":[
        {
            "category":"Shopping",
            "subcategory":"Musical Instruments",
            "type":"Retail Goods"
        }
    ],
    "sg:phone":"+1 613 342 0115",
    "sg:postcode":"K6V 5T3",
    "sg:province":"ON",
    "sg:tags":[
        "music",
        "dealer"
    ],
    "wof:name":"Harmack Music",
    "wof:placetype":"venue"
},
  "geometry": {"coordinates":[-75.683014,44.590389],"type":"Point"}
}