{
  "type": "Feature",
  "properties": {
    "addr:full":"8 Grenfell Happy Valley-Goose Bay NL A0P 1E0",
    "addr:housenumber":"8",
    "addr:postcode":"a0p 1e0",
    "addr:street":"Grenfell",
    "iso:country":"CA",
    "sg:address":"8 Grenfell",
    "sg:city":"Happy Valley-Goose Bay",
    "sg:classifiers":[
        {
            "category":"Personal",
            "subcategory":"Tattoo Parlor",
            "type":"Services"
        }
    ],
    "sg:phone":"+1 709 896 5235",
    "sg:postcode":"A0P 1E0",
    "sg:province":"NL",
    "sg:tags":[
        "tattooing"
    ],
    "wof:name":"Tattoos By Sam",
    "wof:placetype":"venue"
},
  "geometry": {"coordinates":[-60.29594,53.29583],"type":"Point"}
}