{
  "type": "Feature",
  "properties": {
    "addr:full":"5003 50 St Lougheed AB T0B 2V0",
    "addr:housenumber":"5003",
    "addr:postcode":"t0b 2v0",
    "addr:street":"50 St",
    "iso:country":"CA",
    "sg:address":"5003 50 St",
    "sg:city":"Lougheed",
    "sg:classifiers":[
        {
            "category":"Food & Beverages",
            "subcategory":"Liquor & Beverages",
            "type":"Retail Goods"
        }
    ],
    "sg:phone":"+1 780 386 0008",
    "sg:postcode":"T0B 2V0",
    "sg:province":"AB",
    "sg:tags":[
        "store"
    ],
    "wof:name":"Tippy's Liquor Store",
    "wof:placetype":"venue"
},
  "geometry": {"coordinates":[-111.54434204099999,52.744846344],"type":"Point"}
}