{
  "type": "Feature",
  "properties": {
    "addr:full":"2500 4 St SW Calgary AB T2S 1X6",
    "addr:housenumber":"2500 4",
    "addr:postcode":"t2s 1x6",
    "addr:street":"St Sw",
    "iso:country":"CA",
    "sg:address":"2500 4 St SW",
    "sg:city":"Calgary",
    "sg:classifiers":[
        {
            "category":"Personal",
            "subcategory":"Tanning Parlor",
            "type":"Services"
        }
    ],
    "sg:phone":"+1 403 244 1976",
    "sg:postcode":"T2S 1X6",
    "sg:province":"AB",
    "sg:tags":[
        "salon"
    ],
    "wof:name":"Fabutan Sun Tan Studios",
    "wof:placetype":"venue"
},
  "geometry": {"coordinates":[-114.071411133,51.0304756165],"type":"Point"}
}