{
  "type": "Feature",
  "properties": {
    "addr:full":"Calgary AB T2P 2Y9",
    "addr:postcode":"t2p 2y9",
    "iso:country":"CA",
    "sg:city":"Calgary",
    "sg:classifiers":[
        {
            "category":"Food & Beverages",
            "subcategory":"Specialty",
            "type":"Retail Goods"
        }
    ],
    "sg:phone":"+1 403 237 5630",
    "sg:postcode":"T2P 2Y9",
    "sg:province":"AB",
    "sg:tags":[
        "vitamin"
    ],
    "wof:name":"Vitamin Farm",
    "wof:placetype":"venue"
},
  "geometry": {"coordinates":[-114.068443,51.046471],"type":"Point"}
}