{
  "type": "Feature",
  "properties": {
    "addr:full":"North Vancouver BC V7J 3H2",
    "addr:postcode":"v7j 3h2",
    "iso:country":"CA",
    "sg:city":"North Vancouver",
    "sg:classifiers":[
        {
            "category":"Food & Beverages",
            "subcategory":"Liquor & Beverages",
            "type":"Retail Goods"
        }
    ],
    "sg:phone":"+1 604 981 0014",
    "sg:postcode":"V7J 3H2",
    "sg:province":"BC",
    "sg:tags":[
        "store"
    ],
    "wof:name":"Liquor Stores-Government",
    "wof:placetype":"venue"
},
  "geometry": {"coordinates":[-123.040817,49.335442],"type":"Point"}
}