{
  "type": "Feature",
  "properties": {
    "addr:full":"1567 Ch Des Patriotes Sainte-Victoire-DE-Sorel QC J0G 1T0",
    "addr:housenumber":"1567",
    "addr:postcode":"j0g 1t0",
    "addr:street":"Ch Des Patriotes",
    "iso:country":"CA",
    "sg:address":"1567 Ch Des Patriotes",
    "sg:city":"Sainte-Victoire-DE-Sorel",
    "sg:classifiers":[
        {
            "category":"Sports & Exercise",
            "subcategory":"Golf",
            "type":"Entertainment"
        }
    ],
    "sg:phone":"+1 450 742 0552",
    "sg:postcode":"J0G 1T0",
    "sg:province":"QC",
    "sg:tags":[
        "course"
    ],
    "wof:name":"Club DE Golf Continental",
    "wof:placetype":"venue"
},
  "geometry": {"coordinates":[-73.1369628906,45.9849357605],"type":"Point"}
}