{
  "type": "Feature",
  "properties": {
    "addr:full":"Westmount QC H3Z 2P9",
    "addr:postcode":"h3z 2p9",
    "iso:country":"CA",
    "sg:city":"Westmount",
    "sg:classifiers":[
        {
            "category":"Real Estate",
            "subcategory":"Developer",
            "type":"Services"
        }
    ],
    "sg:phone":"+1 514 933 8417",
    "sg:postcode":"H3Z 2P9",
    "sg:province":"QC",
    "wof:name":"Urbandale Realty Corp Ltd",
    "wof:placetype":"venue"
},
  "geometry": {"coordinates":[-73.587509,45.486759],"type":"Point"}
}