{
  "type": "Feature",
  "properties": {
    "iso:country":"CA",
    "sg:address":"4908 Royal St # A",
    "sg:city":"Coronation",
    "sg:classifiers":[
        {
            "category":"Building & Trades",
            "subcategory":"Equipment Rental",
            "type":"Services"
        }
    ],
    "sg:phone":"+1 403 578 3300",
    "sg:postcode":"T0C 1C0",
    "sg:province":"AB",
    "sg:tags":[
        "player",
        "recorder",
        "video"
    ],
    "wof:name":"Jims Video",
    "wof:placetype":"venue"
},
  "geometry": {"coordinates":[-111.449401855,52.0927238464],"type":"Point"}
}