{
  "type": "Feature",
  "properties": {
    "iso:country":"CA",
    "sg:city":"Ottawa",
    "sg:classifiers":[
        {
            "category":"Shopping",
            "subcategory":"Computers & Home Electronics",
            "type":"Retail Goods"
        }
    ],
    "sg:phone":"+1 613 523 5500",
    "sg:postcode":"K1B 4S5",
    "sg:province":"ON",
    "sg:tags":[
        "software"
    ],
    "wof:name":"Data Kinetics Ltd",
    "wof:placetype":"venue"
},
  "geometry": {"coordinates":[-75.6170806885,45.4020347595],"type":"Point"}
}