{
  "type": "Feature",
  "properties": {
    "addr:full":"1296 Westcott Rd Windsor ON N8Y 4C1",
    "addr:housenumber":"1296",
    "addr:postcode":"n8y 4c1",
    "addr:street":"Westcott Rd",
    "iso:country":"CA",
    "sg:address":"1296 Westcott Rd",
    "sg:city":"Windsor",
    "sg:classifiers":[
        {
            "category":"Organizations",
            "subcategory":"Membership Organization",
            "type":"Services"
        }
    ],
    "sg:phone":"+1 519 948 1231",
    "sg:postcode":"N8Y 4C1",
    "sg:province":"ON",
    "wof:name":"Windsor East Little League",
    "wof:placetype":"venue"
},
  "geometry": {"coordinates":[-82.987312,42.319584],"type":"Point"}
}