{
  "type": "Feature",
  "properties": {
    "addr:full":"RR 1 STN Main Napanee ON K7R 3K6",
    "addr:postcode":"k7r 3k6",
    "addr:street":"Rr 1 Stn Main",
    "iso:country":"CA",
    "sg:address":"RR 1 STN Main",
    "sg:city":"Napanee",
    "sg:classifiers":[
        {
            "category":"Retail",
            "subcategory":"Auto Repair",
            "type":"Services"
        }
    ],
    "sg:phone":"+1 613 354 7309",
    "sg:postcode":"K7R 3K6",
    "sg:province":"ON",
    "sg:tags":[
        "repairing",
        "automobile"
    ],
    "wof:name":"Hank's Auto Svc",
    "wof:placetype":"venue"
},
  "geometry": {"coordinates":[-76.951584,44.248325],"type":"Point"}
}