{
  "type": "Feature",
  "properties": {
    "addr:full":"Fishing Lake Reserve Wadena SK S0A 4J0",
    "addr:postcode":"s0a 4j0",
    "addr:street":"Fishing",
    "iso:country":"CA",
    "sg:address":"Fishing Lake Reserve",
    "sg:city":"Wadena",
    "sg:classifiers":[
        {
            "category":"Social Services",
            "subcategory":"Child Care",
            "type":"Services"
        }
    ],
    "sg:phone":"+1 306 338 3768",
    "sg:postcode":"S0A 4J0",
    "sg:province":"SK",
    "sg:tags":[
        "kindergarten",
        "academic",
        "school"
    ],
    "wof:name":"Fishing Lake Kindergarten",
    "wof:placetype":"venue"
},
  "geometry": {"coordinates":[-103.79473900000001,51.942619],"type":"Point"}
}