{
  "type": "Feature",
  "properties": {
    "addr:full":"12 Lake Ave Silverton BC V0G 2B0",
    "addr:housenumber":"12",
    "addr:postcode":"v0g 2b0",
    "addr:street":"Lake Ave",
    "iso:country":"CA",
    "sg:address":"12 Lake Ave",
    "sg:city":"Silverton",
    "sg:classifiers":[
        {
            "category":"Travel",
            "subcategory":"Hotels & Motels",
            "type":"Entertainment"
        }
    ],
    "sg:phone":"+1 250 358 7929",
    "sg:postcode":"V0G 2B0",
    "sg:province":"BC",
    "wof:name":"Silverton Country Inn",
    "wof:placetype":"venue"
},
  "geometry": {"coordinates":[-117.356811523,49.9525337219],"type":"Point"}
}