{
  "type": "Feature",
  "properties": {
    "addr:full":"Brantford ON N3S 7K7",
    "addr:postcode":"n3s 7k7",
    "iso:country":"CA",
    "sg:city":"Brantford",
    "sg:classifiers":[
        {
            "category":"Real Estate",
            "subcategory":"Real Estate Operator",
            "type":"Services"
        }
    ],
    "sg:phone":"+1 519 756 5655",
    "sg:postcode":"N3S 7K7",
    "sg:province":"ON",
    "sg:tags":[
        "apartment"
    ],
    "wof:name":"Cedarview Residence",
    "wof:placetype":"venue"
},
  "geometry": {"coordinates":[-80.241317749,43.1549377441],"type":"Point"}
}