{
  "type": "Feature",
  "properties": {
    "iso:country":"CA",
    "sg:address":"851 Boul Daniel-Johnson",
    "sg:city":"Saint-Jerome",
    "sg:classifiers":[
        {
            "category":"Freight",
            "type":"Transportation"
        }
    ],
    "sg:phone":"+1 450 438 6685",
    "sg:postcode":"J7Y 4C2",
    "sg:province":"QC",
    "sg:tags":[
        "trucking"
    ],
    "wof:name":"Transport Nordique Inc",
    "wof:placetype":"venue"
},
  "geometry": {"coordinates":[-74.02904510499999,45.7867507935],"type":"Point"}
}