{
  "type": "Feature",
  "properties": {
    "addr:full":"262 Rue Principale Saint-Evariste-DE-Forsyth QC G0M 1S0",
    "addr:housenumber":"262",
    "addr:postcode":"g0m 1s0",
    "addr:street":"Rue Principale",
    "iso:country":"CA",
    "sg:address":"262 Rue Principale",
    "sg:city":"Saint-Evariste-DE-Forsyth",
    "sg:classifiers":[
        {
            "category":"Wholesale",
            "subcategory":"Durable Goods & Equipment",
            "type":"Manufacturing & Wholesale Goods"
        }
    ],
    "sg:phone":"+1 418 459 3140",
    "sg:postcode":"G0M 1S0",
    "sg:province":"QC",
    "sg:tags":[
        "fire",
        "extinguisher"
    ],
    "wof:name":"Extincteurs Kaouin Enr",
    "wof:placetype":"venue"
},
  "geometry": {"coordinates":[-70.94017791749999,45.9411048889],"type":"Point"}
}