{
  "type": "Feature",
  "properties": {
    "addr:full":"75 St. George St Moncton NB E1C 1T5",
    "addr:housenumber":"75",
    "addr:postcode":"e1c 1t5",
    "addr:street":"St. George St",
    "iso:country":"CA",
    "sg:address":"75 St. George St",
    "sg:city":"Moncton",
    "sg:classifiers":[
        {
            "category":"Professional",
            "subcategory":"Art Services",
            "type":"Services"
        }
    ],
    "sg:phone":"+1 506 387 4200",
    "sg:postcode":"E1C 1T5",
    "sg:province":"NB",
    "sg:tags":[
        "marketing",
        "graphic",
        "designer",
        "consultant"
    ],
    "wof:name":"Apropos Marketing Comms",
    "wof:placetype":"venue"
},
  "geometry": {"coordinates":[-64.77552799999999,46.092793],"type":"Point"}
}