{
  "type": "Feature",
  "properties": {
    "addr:full":"917 Davie St Vancouver BC V6Z 1B9",
    "addr:housenumber":"917",
    "addr:postcode":"v6z 1b9",
    "addr:street":"Davie St",
    "iso:country":"CA",
    "sg:address":"917 Davie St",
    "sg:city":"Vancouver",
    "sg:classifiers":[
        {
            "category":"Restaurant",
            "type":"Food & Drink"
        }
    ],
    "sg:phone":"+1 604 688 6868",
    "sg:postcode":"V6Z 1B9",
    "sg:province":"BC",
    "wof:name":"New Hong Kong Kitchen",
    "wof:placetype":"venue"
},
  "geometry": {"coordinates":[-123.12827299999999,49.278679],"type":"Point"}
}