{
  "type": "Feature",
  "properties": {
    "addr:full":"4808 50 Ave Wetaskiwin AB T9A 0S2",
    "addr:housenumber":"4808",
    "addr:postcode":"t9a 0s2",
    "addr:street":"50 Ave",
    "iso:country":"CA",
    "sg:address":"4808 50 Ave",
    "sg:city":"Wetaskiwin",
    "sg:classifiers":[
        {
            "category":"Restaurant",
            "type":"Food & Drink"
        }
    ],
    "sg:phone":"+1 780 361 2334",
    "sg:postcode":"T9A 0S2",
    "sg:province":"AB",
    "sg:tags":[
        "caterer"
    ],
    "wof:name":"Bearco Catering",
    "wof:placetype":"venue"
},
  "geometry": {"coordinates":[-113.37106300000001,52.969456],"type":"Point"}
}