{
  "type": "Feature",
  "properties": {
    "iso:country":"CA",
    "sg:address":"6095 Boul Metropolitain E",
    "sg:city":"Saint-Leonard",
    "sg:classifiers":[
        {
            "category":"Professional",
            "subcategory":"Business Services",
            "type":"Services"
        }
    ],
    "sg:phone":"+1 514 955 5556",
    "sg:postcode":"H1P 1X7",
    "sg:province":"QC",
    "sg:tags":[
        "appraiser"
    ],
    "wof:name":"Beaulieu Coutu Belanger Inc",
    "wof:placetype":"venue"
},
  "geometry": {"coordinates":[-73.5824584961,45.590171814],"type":"Point"}
}