{
  "type": "Feature",
  "properties": {
    "addr:full":"6095 Boul Metropolitain E Saint-Leonard QC H1P 1X7",
    "addr:housenumber":"6095",
    "addr:postcode":"h1p 1x7",
    "addr:street":"Boul Metropolitain E",
    "iso:country":"CA",
    "sg:address":"6095 Boul Metropolitain E",
    "sg:city":"Saint-Leonard",
    "sg:classifiers":[
        {
            "category":"Professional",
            "subcategory":"Business Services",
            "type":"Services"
        }
    ],
    "sg:phone":"+1 514 955 5556",
    "sg:postcode":"H1P 1X7",
    "sg:province":"QC",
    "sg:tags":[
        "appraiser"
    ],
    "wof:name":"Beaulieu Coutu Belanger Inc",
    "wof:placetype":"venue"
},
  "geometry": {"coordinates":[-73.5824584961,45.590171814],"type":"Point"}
}