{
  "type": "Feature",
  "properties": {
    "iso:country":"CA",
    "sg:address":"1271 Confederation St",
    "sg:city":"Sarnia",
    "sg:classifiers":[
        {
            "category":"Building & Trades",
            "subcategory":"Construction",
            "type":"Services"
        }
    ],
    "sg:phone":"+1 519 336 1010",
    "sg:postcode":"N7S 4M7",
    "sg:province":"ON",
    "sg:tags":[
        "mobile",
        "commercial",
        "unit"
    ],
    "wof:name":"Williams Scotsman",
    "wof:placetype":"venue"
},
  "geometry": {"coordinates":[-82.36241912840001,42.9601783752],"type":"Point"}
}