{
  "type": "Feature",
  "properties": {
    "addr:full":"9827 Horton Rd SW Calgary AB T2V 2X5",
    "addr:housenumber":"9827",
    "addr:postcode":"t2v 2x5",
    "addr:street":"Horton Rd Sw",
    "iso:country":"CA",
    "sg:address":"9827 Horton Rd SW",
    "sg:city":"Calgary",
    "sg:classifiers":[
        {
            "category":"Wholesale",
            "subcategory":"Machinery & Supplies",
            "type":"Manufacturing & Wholesale Goods"
        }
    ],
    "sg:phone":"+1 403 253 3541",
    "sg:postcode":"T2V 2X5",
    "sg:province":"AB",
    "sg:tags":[
        "farm",
        "equipment"
    ],
    "wof:name":"Lawnmower Doktor Inc",
    "wof:placetype":"venue"
},
  "geometry": {"coordinates":[-114.074989,50.966831],"type":"Point"}
}