{
  "type": "Feature",
  "properties": {
    "iso:country":"CA",
    "sg:address":"220 North St",
    "sg:city":"Bridgewater",
    "sg:classifiers":[
        {
            "category":"Professional",
            "subcategory":"Management & Consulting",
            "type":"Services"
        }
    ],
    "sg:phone":"+1 902 543 3988",
    "sg:postcode":"B4V 2V6",
    "sg:province":"NS",
    "sg:tags":[
        "consultant",
        "business"
    ],
    "wof:name":"South Shore Opportunities Inc",
    "wof:placetype":"venue"
},
  "geometry": {"coordinates":[-64.522659,44.389389],"type":"Point"}
}