{
  "type": "Feature",
  "properties": {
    "addr:full":"6382 Quinpool Rd Halifax NS B3L 4N2",
    "addr:housenumber":"6382",
    "addr:postcode":"b3l 4n2",
    "addr:street":"Quinpool Rd",
    "iso:country":"CA",
    "sg:address":"6382 Quinpool Rd",
    "sg:city":"Halifax",
    "sg:classifiers":[
        {
            "category":"Personal",
            "subcategory":"Beauty Salon",
            "type":"Services"
        }
    ],
    "sg:phone":"+1 902 422 4403",
    "sg:postcode":"B3L 4N2",
    "sg:province":"NS",
    "sg:tags":[
        "manicuring"
    ],
    "wof:name":"Lee's Nails Professional",
    "wof:placetype":"venue"
},
  "geometry": {"coordinates":[-63.5999717712,44.6444702148],"type":"Point"}
}