{
  "type": "Feature",
  "properties": {
    "addr:full":"6770 Boul Pie-Ix Montreal QC H1X 2C8",
    "addr:housenumber":"6770",
    "addr:postcode":"h1x 2c8",
    "addr:street":"Boul Pie-Ix",
    "iso:country":"CA",
    "sg:address":"6770 Boul Pie-Ix",
    "sg:city":"Montreal",
    "sg:classifiers":[
        {
            "category":"Health Services",
            "subcategory":"Nursing And Care Facility",
            "type":"Services"
        }
    ],
    "sg:phone":"+1 514 725 8198",
    "sg:postcode":"H1X 2C8",
    "sg:province":"QC",
    "sg:tags":[
        "home",
        "retirement",
        "community"
    ],
    "wof:name":"Residence Jardin Du Boulevard",
    "wof:placetype":"venue"
},
  "geometry": {"coordinates":[-73.5846939087,45.5639419556],"type":"Point"}
}