{
  "type": "Feature",
  "properties": {
    "iso:country":"CA",
    "sg:address":"29 Rue Notre-Dame O",
    "sg:city":"Montreal",
    "sg:classifiers":[
        {
            "category":"Wholesale",
            "subcategory":"Jewelry",
            "type":"Manufacturing & Wholesale Goods"
        }
    ],
    "sg:phone":"+1 514 350 8700",
    "sg:postcode":"H2Y 1S5",
    "sg:province":"QC",
    "sg:tags":[
        "watch"
    ],
    "wof:name":"Michel Homatter Etablissements",
    "wof:placetype":"venue"
},
  "geometry": {"coordinates":[-73.5554275513,45.5067481995],"type":"Point"}
}