{
  "type": "Feature",
  "properties": {
    "addr:full":"1475 Noel Ave Comox BC V9M 3H8",
    "addr:housenumber":"1475",
    "addr:postcode":"v9m 3h8",
    "addr:street":"Noel Ave",
    "iso:country":"CA",
    "sg:address":"1475 Noel Ave",
    "sg:city":"Comox",
    "sg:classifiers":[
        {
            "category":"Education",
            "subcategory":"School",
            "type":"Public Place"
        }
    ],
    "sg:phone":"+1 250 339 4866",
    "sg:postcode":"V9M 3H8",
    "sg:province":"BC",
    "wof:name":"Brooklyn Elementary School",
    "wof:placetype":"venue"
},
  "geometry": {"coordinates":[-124.91179700000001,49.681919],"type":"Point"}
}