{
  "type": "Feature",
  "properties": {
    "addr:full":"2090 Rue Cherrier Saint-Hyacinthe QC J2S 8R3",
    "addr:housenumber":"2090",
    "addr:postcode":"j2s 8r3",
    "addr:street":"Rue Cherrier",
    "iso:country":"CA",
    "sg:address":"2090 Rue Cherrier",
    "sg:city":"Saint-Hyacinthe",
    "sg:classifiers":[
        {
            "category":"Government",
            "subcategory":"Office",
            "type":"Public Place"
        }
    ],
    "sg:phone":"+1 450 774 7276",
    "sg:postcode":"J2S 8R3",
    "sg:province":"QC",
    "sg:tags":[
        "information",
        "referral",
        "village"
    ],
    "wof:name":"Bureau DE Tourisme Et-Congres",
    "wof:placetype":"venue"
},
  "geometry": {"coordinates":[-72.9622039795,45.6329803467],"type":"Point"}
}