{
  "type": "Feature",
  "properties": {
    "addr:full":"219 Jamieson Bone Rd Belleville ON K8N 5T4",
    "addr:housenumber":"219",
    "addr:postcode":"k8n 5t4",
    "addr:street":"Jamieson Bone Rd",
    "iso:country":"CA",
    "sg:address":"219 Jamieson Bone Rd",
    "sg:city":"Belleville",
    "sg:classifiers":[
        {
            "category":"Manufacturing",
            "subcategory":"Rubber & Plastics",
            "type":"Manufacturing & Wholesale Goods"
        }
    ],
    "sg:phone":"+1 613 966 4400",
    "sg:postcode":"K8N 5T4",
    "sg:province":"ON",
    "sg:tags":[
        "producer"
    ],
    "wof:name":"Sigma Stretch Film of Canada",
    "wof:placetype":"venue"
},
  "geometry": {"coordinates":[-77.36302947999999,44.1926727295],"type":"Point"}
}