{
  "type": "Feature",
  "properties": {
    "iso:country":"CA",
    "sg:address":"781 Rue William",
    "sg:city":"Montreal",
    "sg:classifiers":[
        {
            "category":"Professional",
            "subcategory":"Management & Consulting",
            "type":"Services"
        }
    ],
    "sg:phone":"+1 514 872 8205",
    "sg:postcode":"H3C 1N8",
    "sg:province":"QC",
    "sg:tags":[
        "consultant",
        "recreation",
        "program"
    ],
    "wof:name":"Groupe DE Gestion Dynamo",
    "wof:placetype":"venue"
},
  "geometry": {"coordinates":[-73.5584106445,45.497882843],"type":"Point"}
}