{
  "type": "Feature",
  "properties": {
    "addr:full":"6534 Sherwood Rd Niagara Falls ON L2E 5M3",
    "addr:housenumber":"6534",
    "addr:postcode":"l2e 5m3",
    "addr:street":"Sherwood Rd",
    "iso:country":"CA",
    "sg:address":"6534 Sherwood Rd",
    "sg:city":"Niagara Falls",
    "sg:classifiers":[
        {
            "category":"Organizations",
            "subcategory":"Religious Organization",
            "type":"Services"
        }
    ],
    "sg:phone":"+1 905 354 3540",
    "sg:postcode":"L2E 5M3",
    "sg:province":"ON",
    "wof:name":"Peter Deyneka Russian Ministry",
    "wof:placetype":"venue"
},
  "geometry": {"coordinates":[-79.1043930054,43.1078681946],"type":"Point"}
}