{
  "type": "Feature",
  "properties": {
    "addr:full":"67 Fourth St W # 4 Collingwood ON L9Y 1R5",
    "addr:housenumber":"67",
    "addr:postcode":"l9y 1r5",
    "addr:street":"Fourth St W # 4",
    "iso:country":"CA",
    "sg:address":"67 Fourth St W # 4",
    "sg:city":"Collingwood",
    "sg:classifiers":[
        {
            "category":"Wholesale",
            "subcategory":"Groceries",
            "type":"Manufacturing & Wholesale Goods"
        }
    ],
    "sg:phone":"+1 705 444 0923",
    "sg:postcode":"L9Y 1R5",
    "sg:province":"ON",
    "sg:tags":[
        "food",
        "product",
        "health"
    ],
    "wof:name":"Organic Farm Svc",
    "wof:placetype":"venue"
},
  "geometry": {"coordinates":[-80.218002,44.496838],"type":"Point"}
}