{
  "type": "Feature",
  "properties": {
    "addr:full":"815 Boul Henri-Bourassa E Montreal QC H2C 1E7",
    "addr:housenumber":"815",
    "addr:postcode":"h2c 1e7",
    "addr:street":"Boul Henri-Bourassa E",
    "iso:country":"CA",
    "sg:address":"815 Boul Henri-Bourassa E",
    "sg:city":"Montreal",
    "sg:classifiers":[
        {
            "category":"Health Services",
            "subcategory":"Doctor",
            "type":"Services"
        }
    ],
    "sg:phone":"+1 514 383 1001",
    "sg:postcode":"H2C 1E7",
    "sg:province":"QC",
    "sg:tags":[
        "physician",
        "surgeon"
    ],
    "wof:name":"Valiquette, Catherine MD",
    "wof:placetype":"venue"
},
  "geometry": {"coordinates":[-73.66732,45.558571],"type":"Point"}
}