{
  "type": "Feature",
  "properties": {
    "addr:full":"Montreal QC H2N 2J2",
    "addr:postcode":"h2n 2j2",
    "iso:country":"CA",
    "sg:city":"Montreal",
    "sg:classifiers":[
        {
            "category":"Manufacturing",
            "subcategory":"Printing",
            "type":"Manufacturing & Wholesale Goods"
        }
    ],
    "sg:phone":"+1 514 381 5921",
    "sg:postcode":"H2N 2J2",
    "sg:province":"QC",
    "sg:tags":[
        "publisher"
    ],
    "wof:name":"Marcarko Limited",
    "wof:placetype":"venue"
},
  "geometry": {"coordinates":[-73.6481552124,45.549533844],"type":"Point"}
}