{
  "type": "Feature",
  "properties": {
    "iso:country":"CA",
    "sg:address":"15179 Russell Ave",
    "sg:city":"White Rock",
    "sg:classifiers":[
        {
            "category":"Shopping",
            "type":"Retail Goods"
        }
    ],
    "sg:phone":"+1 604 536 1223",
    "sg:postcode":"V4B 2P4",
    "sg:province":"BC",
    "sg:tags":[
        "art",
        "gallery",
        "dealer"
    ],
    "wof:name":"Art Nook",
    "wof:placetype":"venue"
},
  "geometry": {"coordinates":[-122.801888,49.029533],"type":"Point"}
}