{
  "type": "Feature",
  "properties": {
    "addr:full":"15179 Russell Ave White Rock BC V4B 2P4",
    "addr:housenumber":"15179",
    "addr:postcode":"v4b 2p4",
    "addr:street":"Russell Ave",
    "iso:country":"CA",
    "sg:address":"15179 Russell Ave",
    "sg:city":"White Rock",
    "sg:classifiers":[
        {
            "category":"Shopping",
            "type":"Retail Goods"
        }
    ],
    "sg:phone":"+1 604 536 1223",
    "sg:postcode":"V4B 2P4",
    "sg:province":"BC",
    "sg:tags":[
        "art",
        "gallery",
        "dealer"
    ],
    "wof:name":"Art Nook",
    "wof:placetype":"venue"
},
  "geometry": {"coordinates":[-122.80188800000001,49.029533],"type":"Point"}
}