{
  "type": "Feature",
  "properties": {
    "addr:full":"67 Rue Augusta Sorel-Tracy QC J3P 1A6",
    "addr:housenumber":"67",
    "addr:postcode":"j3p 1a6",
    "addr:street":"Rue Augusta",
    "iso:country":"CA",
    "sg:address":"67 Rue Augusta",
    "sg:city":"Sorel-Tracy",
    "sg:classifiers":[
        {
            "category":"Shopping",
            "subcategory":"Jewelry",
            "type":"Retail Goods"
        }
    ],
    "sg:phone":"+1 450 743 5471",
    "sg:postcode":"J3P 1A6",
    "sg:province":"QC",
    "sg:tags":[
        "jeweler"
    ],
    "wof:name":"Bijouterie Pierre Gagnon Inc",
    "wof:placetype":"venue"
},
  "geometry": {"coordinates":[-73.114632,46.045998],"type":"Point"}
}