{
  "type": "Feature",
  "properties": {
    "addr:full":"41 Churchill Ave Leamington ON N8H 3R6",
    "addr:housenumber":"41",
    "addr:postcode":"n8h 3r6",
    "addr:street":"Churchill Ave",
    "iso:country":"CA",
    "sg:address":"41 Churchill Ave",
    "sg:city":"Leamington",
    "sg:classifiers":[
        {
            "category":"Freight",
            "type":"Transportation"
        }
    ],
    "sg:phone":"+1 519 322 2662",
    "sg:postcode":"N8H 3R6",
    "sg:province":"ON",
    "sg:tags":[
        "trucking"
    ],
    "wof:name":"South Pacific Transportation",
    "wof:placetype":"venue"
},
  "geometry": {"coordinates":[-82.61172500000001,42.048073],"type":"Point"}
}