{
  "type": "Feature",
  "properties": {
    "addr:full":"4716 99 St NW Edmonton AB T6E 5H5",
    "addr:housenumber":"4716",
    "addr:postcode":"t6e 5h5",
    "addr:street":"99 St Nw",
    "iso:country":"CA",
    "sg:address":"4716 99 St NW",
    "sg:city":"Edmonton",
    "sg:classifiers":[
        {
            "category":"Health Services",
            "subcategory":"Health Practitioner",
            "type":"Services"
        }
    ],
    "sg:phone":"+1 780 431 1956",
    "sg:postcode":"T6E 5H5",
    "sg:province":"AB",
    "sg:tags":[
        "acupuncture"
    ],
    "wof:name":"Acupuncture & Health Ctr",
    "wof:placetype":"venue"
},
  "geometry": {"coordinates":[-113.48642,53.485054],"type":"Point"}
}