{
  "type": "Feature",
  "properties": {
    "addr:full":"Hamilton ON L8H 2Y7",
    "addr:postcode":"l8h 2y7",
    "iso:country":"CA",
    "sg:city":"Hamilton",
    "sg:classifiers":[
        {
            "category":"Organizations",
            "subcategory":"Professional Association",
            "type":"Services"
        }
    ],
    "sg:phone":"+1 905 549 8734",
    "sg:postcode":"L8H 2Y7",
    "sg:province":"ON",
    "sg:tags":[
        "club"
    ],
    "wof:name":"Croatian National Home Office",
    "wof:placetype":"venue"
},
  "geometry": {"coordinates":[-79.782417,43.243843],"type":"Point"}
}