{
  "type": "Feature",
  "properties": {
    "addr:full":"304 George St Prince George BC V2L 1R3",
    "addr:housenumber":"304",
    "addr:postcode":"v2l 1r3",
    "addr:street":"George St",
    "iso:country":"CA",
    "sg:address":"304 George St",
    "sg:city":"Prince George",
    "sg:classifiers":[
        {
            "category":"Restaurant",
            "type":"Food & Drink"
        }
    ],
    "sg:phone":"+1 250 649 0987",
    "sg:postcode":"V2L 1R3",
    "sg:province":"BC",
    "sg:tags":[
        "shop",
        "coffee"
    ],
    "wof:name":"Javva Mugga Mocha",
    "wof:placetype":"venue"
},
  "geometry": {"coordinates":[-122.74269866900001,53.9159126282],"type":"Point"}
}