{
  "type": "Feature",
  "properties": {
    "addr:full":"28 Confederation Dr Corner Brook NL A2H 6C3",
    "addr:housenumber":"28",
    "addr:postcode":"a2h 6c3",
    "addr:street":"Confederation Dr",
    "iso:country":"CA",
    "sg:address":"28 Confederation Dr",
    "sg:city":"Corner Brook",
    "sg:classifiers":[
        {
            "category":"Home & Garden",
            "subcategory":"Furniture",
            "type":"Retail Goods"
        }
    ],
    "sg:phone":"+1 709 639 8412",
    "sg:postcode":"A2H 6C3",
    "sg:province":"NL",
    "wof:name":"Cohen's Home Furnishings Ltd",
    "wof:placetype":"venue"
},
  "geometry": {"coordinates":[-57.9185562134,48.9461402893],"type":"Point"}
}