{
  "type": "Feature",
  "properties": {
    "addr:full":"Cape Forchu Rd Yarmouth NS B5A 4A7",
    "addr:postcode":"b5a 4a7",
    "addr:street":"Cape Forchu Rd",
    "iso:country":"CA",
    "sg:address":"Cape Forchu Rd",
    "sg:city":"Yarmouth",
    "sg:classifiers":[
        {
            "category":"Shopping",
            "subcategory":"Gifts & Souvenirs",
            "type":"Retail Goods"
        }
    ],
    "sg:phone":"+1 902 742 1433",
    "sg:postcode":"B5A 4A7",
    "sg:province":"NS",
    "sg:tags":[
        "shop"
    ],
    "wof:name":"Yarmouth Light Gift Shop",
    "wof:placetype":"venue"
},
  "geometry": {"coordinates":[-66.118850708,43.8412818909],"type":"Point"}
}