{
  "type": "Feature",
  "properties": {
    "addr:full":"4806 Parkridge Dr Kelowna BC V1W 3A1",
    "addr:housenumber":"4806",
    "addr:postcode":"v1w 3a1",
    "addr:street":"Parkridge Dr",
    "iso:country":"CA",
    "sg:address":"4806 Parkridge Dr",
    "sg:city":"Kelowna",
    "sg:classifiers":[
        {
            "category":"Building & Trades",
            "subcategory":"Plumbing",
            "type":"Services"
        }
    ],
    "sg:phone":"+1 250 764 7300",
    "sg:postcode":"V1W 3A1",
    "sg:province":"BC",
    "sg:tags":[
        "conditioning",
        "air",
        "system",
        "contractor"
    ],
    "wof:name":"Dmn Mechanical",
    "wof:placetype":"venue"
},
  "geometry": {"coordinates":[-119.456253,49.808758],"type":"Point"}
}