{
  "type": "Feature",
  "properties": {
    "addr:full":"1893 Finch Ave W North York ON M3N 2V2",
    "addr:housenumber":"1893",
    "addr:postcode":"m3n 2v2",
    "addr:street":"Finch Ave W",
    "iso:country":"CA",
    "sg:address":"1893 Finch Ave W",
    "sg:city":"North York",
    "sg:classifiers":[
        {
            "category":"Recreation",
            "type":"Entertainment"
        }
    ],
    "sg:phone":"+1 416 631 0556",
    "sg:postcode":"M3N 2V2",
    "sg:province":"ON",
    "sg:tags":[
        "lottery",
        "agent"
    ],
    "wof:name":"Jane Finch Lottery Kiosk",
    "wof:placetype":"venue"
},
  "geometry": {"coordinates":[-79.51619700000001,43.757294],"type":"Point"}
}