{
  "type": "Feature",
  "properties": {
    "addr:full":"Victoria BC V8T 2C5",
    "addr:postcode":"v8t 2c5",
    "iso:country":"CA",
    "sg:city":"Victoria",
    "sg:classifiers":[
        {
            "category":"Shopping",
            "subcategory":"Jewelry",
            "type":"Retail Goods"
        }
    ],
    "sg:phone":"+1 250 595 3169",
    "sg:postcode":"V8T 2C5",
    "sg:province":"BC",
    "sg:tags":[
        "jeweler"
    ],
    "wof:name":"Peoples Jewellers",
    "wof:placetype":"venue"
},
  "geometry": {"coordinates":[-123.332672,48.445881],"type":"Point"}
}