{
  "type": "Feature",
  "properties": {
    "addr:full":"25583 88 Ave Langley BC V1M 3N8",
    "addr:housenumber":"25583",
    "addr:postcode":"v1m 3n8",
    "addr:street":"88 Ave",
    "iso:country":"CA",
    "sg:address":"25583 88 Ave",
    "sg:city":"Langley",
    "sg:classifiers":[
        {
            "category":"Manufacturing",
            "subcategory":"Lumber",
            "type":"Manufacturing & Wholesale Goods"
        }
    ],
    "sg:phone":"+1 604 888 2585",
    "sg:postcode":"V1M 3N8",
    "sg:province":"BC",
    "wof:name":"West Creek Panel Products Ltd",
    "wof:placetype":"venue"
},
  "geometry": {"coordinates":[-122.515632629,49.1618728638],"type":"Point"}
}