{
  "type": "Feature",
  "properties": {
    "addr:full":"New Denver BC V0G 1S0",
    "addr:postcode":"v0g 1s0",
    "iso:country":"CA",
    "sg:city":"New Denver",
    "sg:classifiers":[
        {
            "category":"Personal",
            "subcategory":"Beauty Salon",
            "type":"Services"
        }
    ],
    "sg:phone":"+1 250 358 7700",
    "sg:postcode":"V0G 1S0",
    "sg:province":"BC",
    "wof:name":"Anita's Hair Designs",
    "wof:placetype":"venue"
},
  "geometry": {"coordinates":[-117.371368,49.992474],"type":"Point"}
}