{
  "type": "Feature",
  "properties": {
    "iso:country":"CA",
    "sg:address":"2442 Danforth Ave",
    "sg:city":"Toronto",
    "sg:classifiers":[
        {
            "category":"Shopping",
            "subcategory":"Music",
            "type":"Retail Goods"
        }
    ],
    "sg:phone":"+1 416 691 3187",
    "sg:postcode":"M4C 1K9",
    "sg:province":"ON",
    "sg:tags":[
        "compact",
        "record",
        "book",
        "tape",
        "dealer"
    ],
    "wof:name":"Books Plus",
    "wof:placetype":"venue"
},
  "geometry": {"coordinates":[-79.304237,43.687767],"type":"Point"}
}