{
  "type": "Feature",
  "properties": {
    "addr:full":"18 Tamara Pl Brantford ON N3P 1M8",
    "addr:housenumber":"18",
    "addr:postcode":"n3p 1m8",
    "addr:street":"Tamara Pl",
    "iso:country":"CA",
    "sg:address":"18 Tamara Pl",
    "sg:city":"Brantford",
    "sg:classifiers":[
        {
            "category":"Manufacturing",
            "subcategory":"Tools & Machinery",
            "type":"Manufacturing & Wholesale Goods"
        }
    ],
    "sg:phone":"+1 519 752 4838",
    "sg:postcode":"N3P 1M8",
    "sg:province":"ON",
    "sg:tags":[
        "machine",
        "shop"
    ],
    "wof:name":"Chatterson Machine & Tool CO",
    "wof:placetype":"venue"
},
  "geometry": {"coordinates":[-80.23801400000001,43.178841],"type":"Point"}
}