{
  "type": "Feature",
  "properties": {
    "addr:full":"1185 Conyers Cres Mississauga ON L5C 1K2",
    "addr:housenumber":"1185",
    "addr:postcode":"l5c 1k2",
    "addr:street":"Conyers Cres",
    "iso:country":"CA",
    "sg:address":"1185 Conyers Cres",
    "sg:city":"Mississauga",
    "sg:classifiers":[
        {
            "category":"Building & Trades",
            "subcategory":"Construction",
            "type":"Services"
        }
    ],
    "sg:phone":"+1 905 275 5559",
    "sg:postcode":"L5C 1K2",
    "sg:province":"ON",
    "sg:tags":[
        "home",
        "improvement"
    ],
    "wof:name":"Mortson Renovations",
    "wof:placetype":"venue"
},
  "geometry": {"coordinates":[-79.65007799999999,43.558666],"type":"Point"}
}