{
  "type": "Feature",
  "properties": {
    "iso:country":"CA",
    "sg:address":"2229 Wyandotte St W",
    "sg:city":"Windsor",
    "sg:classifiers":[
        {
            "category":"Shopping",
            "subcategory":"Florist",
            "type":"Retail Goods"
        }
    ],
    "sg:phone":"+1 519 252 1424",
    "sg:postcode":"N9B 1K3",
    "sg:province":"ON",
    "wof:name":"Bruce Philp Florist",
    "wof:placetype":"venue"
},
  "geometry": {"coordinates":[-83.061371,42.305454],"type":"Point"}
}