{
  "type": "Feature",
  "properties": {
    "iso:country":"CA",
    "sg:address":"840 Rue Marguerite-Bourgeoys",
    "sg:city":"Chicoutimi",
    "sg:classifiers":[
        {
            "category":"Retail",
            "subcategory":"Repair Shop",
            "type":"Services"
        }
    ],
    "sg:phone":"+1 418 696 2488",
    "sg:postcode":"G7J 3V8",
    "sg:province":"QC",
    "sg:tags":[
        "upholsterer"
    ],
    "wof:name":"Rembourrage Boulay",
    "wof:placetype":"venue"
},
  "geometry": {"coordinates":[-71.095558,48.425793],"type":"Point"}
}