{
  "type": "Feature",
  "properties": {
    "addr:full":"5280 Kincaid St Burnaby BC V5G 1V9",
    "addr:housenumber":"5280",
    "addr:postcode":"v5g 1v9",
    "addr:street":"Kincaid St",
    "iso:country":"CA",
    "sg:address":"5280 Kincaid St",
    "sg:city":"Burnaby",
    "sg:classifiers":[
        {
            "category":"Organizations",
            "subcategory":"Religious Organization",
            "type":"Services"
        }
    ],
    "sg:phone":"+1 604 291 1734",
    "sg:postcode":"V5G 1V9",
    "sg:province":"BC",
    "sg:tags":[
        "church"
    ],
    "wof:name":"Church of Jesus Christ-Lds",
    "wof:placetype":"venue"
},
  "geometry": {"coordinates":[-122.987693787,49.2482147217],"type":"Point"}
}