{
  "type": "Feature",
  "properties": {
    "addr:full":"2146 Navaho Dr Ottawa ON K2C 0V6",
    "addr:housenumber":"2146",
    "addr:postcode":"k2c 0v6",
    "addr:street":"Navaho Dr",
    "iso:country":"CA",
    "sg:address":"2146 Navaho Dr",
    "sg:city":"Ottawa",
    "sg:classifiers":[
        {
            "category":"Building & Trades",
            "subcategory":"Cleaning & Sanitation",
            "type":"Services"
        }
    ],
    "sg:phone":"+1 613 728 8911",
    "sg:postcode":"K2C 0V6",
    "sg:province":"ON",
    "sg:tags":[
        "repairing",
        "automobile",
        "janitor"
    ],
    "wof:name":"Dunright",
    "wof:placetype":"venue"
},
  "geometry": {"coordinates":[-75.75811,45.357258],"type":"Point"}
}