{
  "type": "Feature",
  "properties": {
    "addr:full":"227 Main St E Milton ON L9T 1N9",
    "addr:housenumber":"227",
    "addr:postcode":"l9t 1n9",
    "addr:street":"Main St E",
    "iso:country":"CA",
    "sg:address":"227 Main St E",
    "sg:city":"Milton",
    "sg:classifiers":[
        {
            "category":"Home & Garden",
            "subcategory":"Home Furnishings",
            "type":"Retail Goods"
        }
    ],
    "sg:phone":"+1 905 878 0050",
    "sg:postcode":"L9T 1N9",
    "sg:province":"ON",
    "sg:tags":[
        "glassware",
        "chinaware"
    ],
    "wof:name":"Delacourts",
    "wof:placetype":"venue"
},
  "geometry": {"coordinates":[-79.883263,43.51326],"type":"Point"}
}