{
  "type": "Feature",
  "properties": {
    "iso:country":"CA",
    "sg:address":"2775 Erin Centre Blvd",
    "sg:city":"Mississauga",
    "sg:classifiers":[
        {
            "category":"Organizations",
            "subcategory":"Religious Organization",
            "type":"Services"
        }
    ],
    "sg:phone":"+1 905 812 0030",
    "sg:postcode":"L5M 5W2",
    "sg:province":"ON",
    "sg:tags":[
        "church"
    ],
    "wof:name":"Merciful Redeemer Parish",
    "wof:placetype":"venue"
},
  "geometry": {"coordinates":[-79.719032,43.556744],"type":"Point"}
}