{
  "type": "Feature",
  "properties": {
    "addr:full":"325 Main St Foam Lake SK S0A 1A0",
    "addr:housenumber":"325",
    "addr:postcode":"s0a 1a0",
    "addr:street":"Main St",
    "iso:country":"CA",
    "sg:address":"325 Main St",
    "sg:city":"Foam Lake",
    "sg:classifiers":[
        {
            "category":"Manufacturing",
            "subcategory":"Printing",
            "type":"Manufacturing & Wholesale Goods"
        }
    ],
    "sg:phone":"+1 306 272 3262",
    "sg:postcode":"S0A 1A0",
    "sg:province":"SK",
    "sg:tags":[
        "newspaper"
    ],
    "wof:name":"Foam Lake Review",
    "wof:placetype":"venue"
},
  "geometry": {"coordinates":[-103.53357699999999,51.641514],"type":"Point"}
}