{
  "type": "Feature",
  "properties": {
    "addr:full":"4955 Trans Canada Hwy Duncan BC V9L 6L3",
    "addr:housenumber":"4955",
    "addr:postcode":"v9l 6l3",
    "addr:street":"Trans Canada Hwy",
    "iso:country":"CA",
    "sg:address":"4955 Trans Canada Hwy",
    "sg:city":"Duncan",
    "sg:classifiers":[
        {
            "category":"Recreation",
            "type":"Entertainment"
        }
    ],
    "sg:phone":"+1 250 746 7211",
    "sg:postcode":"V9L 6L3",
    "sg:province":"BC",
    "sg:tags":[
        "golf"
    ],
    "wof:name":"Cowichan Golf & Country Club",
    "wof:placetype":"venue"
},
  "geometry": {"coordinates":[-123.698822022,48.7804908752],"type":"Point"}
}