{
  "type": "Feature",
  "properties": {
    "iso:country":"CA",
    "sg:address":"4550 Rue Sainte-Emilie",
    "sg:city":"Montreal",
    "sg:classifiers":[
        {
            "category":"Government",
            "subcategory":"Office",
            "type":"Public Place"
        }
    ],
    "sg:phone":"+1 514 872 3539",
    "sg:postcode":"H4C 2B1",
    "sg:province":"QC",
    "sg:tags":[
        "swimming",
        "pool",
        "village"
    ],
    "wof:name":"Montreal Piscines Exterieures",
    "wof:placetype":"venue"
},
  "geometry": {"coordinates":[-73.585396,45.472485],"type":"Point"}
}