{
  "type": "Feature",
  "properties": {
    "iso:country":"CA",
    "sg:address":"1081 King St E",
    "sg:city":"Kitchener",
    "sg:classifiers":[
        {
            "category":"Retail",
            "subcategory":"Auto Rental",
            "type":"Services"
        }
    ],
    "sg:phone":"+1 519 581 8650",
    "sg:postcode":"N2G 2N1",
    "sg:province":"ON",
    "sg:tags":[
        "renting",
        "automobile"
    ],
    "wof:name":"Discount Car & Truck Rentals",
    "wof:placetype":"venue"
},
  "geometry": {"coordinates":[-80.4720916748,43.4419059753],"type":"Point"}
}