{
  "type": "Feature",
  "properties": {
    "addr:full":"PO Box 44 Edberg AB T0B 1J0",
    "addr:housenumber":"po box 44",
    "addr:postcode":"t0b 1j0",
    "addr:street":"Edberg Ab",
    "iso:country":"CA",
    "sg:address":"PO Box 44",
    "sg:city":"Edberg",
    "sg:classifiers":[
        {
            "category":"Building & Trades",
            "subcategory":"Construction",
            "type":"Services"
        }
    ],
    "sg:phone":"+1 780 877 2215",
    "sg:postcode":"T0B 1J0",
    "sg:province":"AB",
    "sg:tags":[
        "insulation",
        "heat",
        "contractor"
    ],
    "wof:name":"A Plus Enviro Insulation Ltd",
    "wof:placetype":"venue"
},
  "geometry": {"coordinates":[-112.788383,52.786289],"type":"Point"}
}