{
  "type": "Feature",
  "properties": {
    "addr:full":"646 1 Ave NE Calgary AB T2E 0B6",
    "addr:housenumber":"646",
    "addr:postcode":"t2e 0b6",
    "addr:street":"1 Ave Ne",
    "iso:country":"CA",
    "sg:address":"646 1 Ave NE",
    "sg:city":"Calgary",
    "sg:classifiers":[
        {
            "category":"Organizations",
            "subcategory":"Professional Association",
            "type":"Services"
        }
    ],
    "sg:phone":"+1 403 264 1155",
    "sg:postcode":"T2E 0B6",
    "sg:province":"AB",
    "wof:name":"Women's Centre of Calgary",
    "wof:placetype":"venue"
},
  "geometry": {"coordinates":[-114.049659729,51.0533180237],"type":"Point"}
}