{
  "type": "Feature",
  "properties": {
    "addr:full":"387 117 Rte Mont-Tremblant QC J8E 2X4",
    "addr:housenumber":"387 117",
    "addr:postcode":"j8e 2x4",
    "addr:street":"Rte Mont-Tremblant",
    "iso:country":"CA",
    "sg:address":"387 117 Rte",
    "sg:city":"Mont-Tremblant",
    "sg:classifiers":[
        {
            "category":"Restaurant",
            "type":"Food & Drink"
        }
    ],
    "sg:phone":"+1 819 425 1333",
    "sg:postcode":"J8E 2X4",
    "sg:province":"QC",
    "wof:name":"Mc Donald's",
    "wof:placetype":"venue"
},
  "geometry": {"coordinates":[-74.570930481,46.1158447266],"type":"Point"}
}