{
  "type": "Feature",
  "properties": {
    "addr:full":"179 Ch Lanteigne Saint-Simon NB E8P 1Z2",
    "addr:housenumber":"179",
    "addr:postcode":"e8p 1z2",
    "addr:street":"Ch Lanteigne",
    "iso:country":"CA",
    "sg:address":"179 Ch Lanteigne",
    "sg:city":"Saint-Simon",
    "sg:classifiers":[
        {
            "category":"Organizations",
            "subcategory":"Community Association",
            "type":"Services"
        }
    ],
    "sg:phone":"+1 506 727 6131",
    "sg:postcode":"E8P 1Z2",
    "sg:province":"NB",
    "sg:tags":[
        "club"
    ],
    "wof:name":"Chalet Du Capitaine",
    "wof:placetype":"venue"
},
  "geometry": {"coordinates":[-65.681702,47.637215],"type":"Point"}
}