{
  "type": "Feature",
  "properties": {
    "addr:full":"4080 North Service Rd E Windsor ON N8W 5X2",
    "addr:housenumber":"4080",
    "addr:postcode":"n8w 5x2",
    "addr:street":"North Service Rd E",
    "iso:country":"CA",
    "sg:address":"4080 North Service Rd E",
    "sg:city":"Windsor",
    "sg:classifiers":[
        {
            "category":"Manufacturing",
            "subcategory":"Tools & Machinery",
            "type":"Manufacturing & Wholesale Goods"
        }
    ],
    "sg:phone":"+1 519 945 2211",
    "sg:postcode":"N8W 5X2",
    "sg:province":"ON",
    "sg:tags":[
        "built",
        "designed"
    ],
    "wof:name":"Trillium Machine",
    "wof:placetype":"venue"
},
  "geometry": {"coordinates":[-82.964691,42.286312],"type":"Point"}
}