{
  "type": "Feature",
  "properties": {
    "addr:full":"12519 Pilgrim St Mission BC V4S 1C5",
    "addr:housenumber":"12519",
    "addr:postcode":"v4s 1c5",
    "addr:street":"Pilgrim St",
    "iso:country":"CA",
    "sg:address":"12519 Pilgrim St",
    "sg:city":"Mission",
    "sg:classifiers":[
        {
            "category":"Manufacturing",
            "subcategory":"Rubber & Plastics",
            "type":"Manufacturing & Wholesale Goods"
        }
    ],
    "sg:phone":"+1 604 462 9013",
    "sg:postcode":"V4S 1C5",
    "sg:province":"BC",
    "sg:tags":[
        "producer"
    ],
    "wof:name":"Arbortec Industries Ltd",
    "wof:placetype":"venue"
},
  "geometry": {"coordinates":[-122.36898803699999,49.2299041748],"type":"Point"}
}