{
  "type": "Feature",
  "properties": {
    "iso:country":"CA",
    "sg:address":"3740 Napier St",
    "sg:city":"Burnaby",
    "sg:classifiers":[
        {
            "category":"Wholesale",
            "subcategory":"Computers",
            "type":"Manufacturing & Wholesale Goods"
        }
    ],
    "sg:phone":"+1 604 291 7870",
    "sg:postcode":"V5C 3E5",
    "sg:province":"BC",
    "sg:tags":[
        "communications",
        "datum"
    ],
    "wof:name":"Wavetek Communications Inc",
    "wof:placetype":"venue"
},
  "geometry": {"coordinates":[-123.022476196,49.2747306824],"type":"Point"}
}