{
  "type": "Feature",
  "properties": {
    "iso:country":"CA",
    "sg:address":"33 Davies Ave",
    "sg:city":"Toronto",
    "sg:classifiers":[
        {
            "category":"Professional",
            "subcategory":"Art Services",
            "type":"Services"
        }
    ],
    "sg:phone":"+1 416 462 0950",
    "sg:postcode":"M4M 2A9",
    "sg:province":"ON",
    "sg:tags":[
        "photographer"
    ],
    "wof:name":"Graf Studios",
    "wof:placetype":"venue"
},
  "geometry": {"coordinates":[-79.353516,43.658978],"type":"Point"}
}