{
  "type": "Feature",
  "properties": {
    "addr:full":"2706 St. Johns St Port Moody BC V3H 2B7",
    "addr:housenumber":"2706",
    "addr:postcode":"v3h 2b7",
    "addr:street":"St. Johns St",
    "iso:country":"CA",
    "sg:address":"2706 St. Johns St",
    "sg:city":"Port Moody",
    "sg:classifiers":[
        {
            "category":"Autos & Motor Vehicles",
            "subcategory":"Fuel & Gas Station",
            "type":"Retail Goods"
        }
    ],
    "sg:phone":"+1 604 936 2556",
    "sg:postcode":"V3H 2B7",
    "sg:province":"BC",
    "sg:tags":[
        "oil"
    ],
    "wof:name":"Port Moody Town Pantry",
    "wof:placetype":"venue"
},
  "geometry": {"coordinates":[-122.852096558,49.2768363953],"type":"Point"}
}