{
  "type": "Feature",
  "properties": {
    "addr:full":"700 14th St W Cornwall ON K6J 5T9",
    "addr:housenumber":"700",
    "addr:postcode":"k6j 5t9",
    "addr:street":"14Th St W",
    "iso:country":"CA",
    "sg:address":"700 14th St W",
    "sg:city":"Cornwall",
    "sg:classifiers":[
        {
            "category":"Food & Beverages",
            "subcategory":"Groceries & Convenience Stores",
            "type":"Retail Goods"
        }
    ],
    "sg:phone":"+1 613 932 0295",
    "sg:postcode":"K6J 5T9",
    "sg:province":"ON",
    "wof:name":"Quickie Convenience Store",
    "wof:placetype":"venue"
},
  "geometry": {"coordinates":[-74.75447800000001,45.030483],"type":"Point"}
}