{
  "type": "Feature",
  "properties": {
    "addr:full":"31 Rue Sainte-Anne Sainte-Anne-DE-Bellevue QC H9X 1L2",
    "addr:housenumber":"31",
    "addr:postcode":"h9x 1l2",
    "addr:street":"Rue Sainte-Anne",
    "iso:country":"CA",
    "sg:address":"31 Rue Sainte-Anne",
    "sg:city":"Sainte-Anne-DE-Bellevue",
    "sg:classifiers":[
        {
            "category":"Bars & Pubs",
            "type":"Food & Drink"
        }
    ],
    "sg:phone":"+1 514 457 5104",
    "sg:postcode":"H9X 1L2",
    "sg:province":"QC",
    "sg:tags":[
        "lounge",
        "cocktail"
    ],
    "wof:name":"Taverne Cousineau",
    "wof:placetype":"venue"
},
  "geometry": {"coordinates":[-73.95246899999999,45.403725],"type":"Point"}
}