{
  "type": "Feature",
  "properties": {
    "iso:country":"CA",
    "sg:address":"31 Rue Sainte-Anne",
    "sg:city":"Sainte-Anne-DE-Bellevue",
    "sg:classifiers":[
        {
            "category":"Bars & Pubs",
            "type":"Food & Drink"
        }
    ],
    "sg:phone":"+1 514 457 5104",
    "sg:postcode":"H9X 1L2",
    "sg:province":"QC",
    "sg:tags":[
        "lounge",
        "cocktail"
    ],
    "wof:name":"Taverne Cousineau",
    "wof:placetype":"venue"
},
  "geometry": {"coordinates":[-73.952469,45.403725],"type":"Point"}
}