{
  "type": "Feature",
  "properties": {
    "iso:country":"CA",
    "sg:address":"148 James St N",
    "sg:city":"Hamilton",
    "sg:classifiers":[
        {
            "category":"Shopping",
            "subcategory":"Jewelry",
            "type":"Retail Goods"
        }
    ],
    "sg:phone":"+1 905 527 5233",
    "sg:postcode":"L8R 2K7",
    "sg:province":"ON",
    "sg:tags":[
        "jeweler"
    ],
    "wof:name":"Hamilton Jewellers",
    "wof:placetype":"venue"
},
  "geometry": {"coordinates":[-79.8671951294,43.2604637146],"type":"Point"}
}