{
  "type": "Feature",
  "properties": {
    "iso:country":"CA",
    "sg:address":"28 Westwood Ave",
    "sg:city":"East York",
    "sg:classifiers":[
        {
            "category":"Local Transit",
            "type":"Transportation"
        }
    ],
    "sg:phone":"+1 416 618 9500",
    "sg:postcode":"M4K 2A8",
    "sg:province":"ON",
    "sg:tags":[
        "limousine"
    ],
    "wof:name":"Olympic Limousine",
    "wof:placetype":"venue"
},
  "geometry": {"coordinates":[-79.3545761108,43.6853790283],"type":"Point"}
}