{
  "type": "Feature",
  "properties": {
    "addr:full":"RR 12 Lcd 5 Calgary AB T3E 6W3",
    "addr:housenumber":"12;5",
    "addr:postcode":"t3e 6w3",
    "addr:street":"Rr;Lcd",
    "iso:country":"CA",
    "sg:address":"RR 12 Lcd 5",
    "sg:city":"Calgary",
    "sg:classifiers":[
        {
            "category":"Mining & Drilling",
            "type":"Manufacturing & Wholesale Goods"
        }
    ],
    "sg:phone":"+1 403 265 7426",
    "sg:postcode":"T3E 6W3",
    "sg:province":"AB",
    "sg:tags":[
        "mud",
        "oil",
        "well",
        "additive"
    ],
    "wof:name":"Marcur Management Ltd",
    "wof:placetype":"venue"
},
  "geometry": {"coordinates":[-114.063194275,51.0450744629],"type":"Point"}
}