{
  "type": "Feature",
  "properties": {
    "addr:full":"222 Wascana Cres SE Calgary AB T2J 1H3",
    "addr:housenumber":"222",
    "addr:postcode":"t2j 1h3",
    "addr:street":"Wascana Cres Se",
    "iso:country":"CA",
    "sg:address":"222 Wascana Cres SE",
    "sg:city":"Calgary",
    "sg:classifiers":[
        {
            "category":"Health Services",
            "subcategory":"Health Practitioner",
            "type":"Services"
        }
    ],
    "sg:phone":"+1 403 271 1846",
    "sg:postcode":"T2J 1H3",
    "sg:province":"AB",
    "sg:tags":[
        "psychologist"
    ],
    "wof:name":"Effect Psychological Svc",
    "wof:placetype":"venue"
},
  "geometry": {"coordinates":[-114.062759,50.9604],"type":"Point"}
}