{
  "type": "Feature",
  "properties": {
    "addr:full":"4894 Dundas St W Etobicoke ON M9A 1B5",
    "addr:housenumber":"4894",
    "addr:postcode":"m9a 1b5",
    "addr:street":"Dundas St W",
    "iso:country":"CA",
    "sg:address":"4894 Dundas St W",
    "sg:city":"Etobicoke",
    "sg:classifiers":[
        {
            "category":"Insurance",
            "subcategory":"Insurance Agent",
            "type":"Services"
        }
    ],
    "sg:phone":"+1 416 231 2248",
    "sg:postcode":"M9A 1B5",
    "sg:province":"ON",
    "wof:name":"Portch Insurance Brokers",
    "wof:placetype":"venue"
},
  "geometry": {"coordinates":[-79.528305,43.649483],"type":"Point"}
}