{
  "type": "Feature",
  "properties": {
    "addr:full":"Scarborough ON M1S 4N8",
    "addr:postcode":"m1s 4n8",
    "iso:country":"CA",
    "sg:city":"Scarborough",
    "sg:classifiers":[
        {
            "category":"Health Services",
            "subcategory":"Doctor",
            "type":"Services"
        }
    ],
    "sg:phone":"+1 416 292 3332",
    "sg:postcode":"M1S 4N8",
    "sg:province":"ON",
    "sg:tags":[
        "dentist"
    ],
    "wof:name":"Bernard Ng & Assoc",
    "wof:placetype":"venue"
},
  "geometry": {"coordinates":[-79.24118,43.793186],"type":"Point"}
}