{
  "type": "Feature",
  "properties": {
    "addr:full":"Etobicoke ON M9C 2Y3",
    "addr:postcode":"m9c 2y3",
    "iso:country":"CA",
    "sg:city":"Etobicoke",
    "sg:classifiers":[
        {
            "category":"Health Services",
            "subcategory":"Doctor",
            "type":"Services"
        }
    ],
    "sg:phone":"+1 416 621 4461",
    "sg:postcode":"M9C 2Y3",
    "sg:province":"ON",
    "sg:tags":[
        "physician",
        "surgeon"
    ],
    "wof:name":"Strom, Brian MD",
    "wof:placetype":"venue"
},
  "geometry": {"coordinates":[-79.568321,43.64447],"type":"Point"}
}