{
  "type": "Feature",
  "properties": {
    "addr:full":"629 Main St Saskatoon SK S7H 0J8",
    "addr:housenumber":"629",
    "addr:postcode":"s7h 0j8",
    "addr:street":"Main St",
    "iso:country":"CA",
    "sg:address":"629 Main St",
    "sg:city":"Saskatoon",
    "sg:classifiers":[
        {
            "category":"Retail",
            "subcategory":"Auto Repair",
            "type":"Services"
        }
    ],
    "sg:phone":"+1 306 664 4588",
    "sg:postcode":"S7H 0J8",
    "sg:province":"SK",
    "sg:tags":[
        "repairing",
        "automobile",
        "radiator"
    ],
    "wof:name":"Reliable Radiator Ltd",
    "wof:placetype":"venue"
},
  "geometry": {"coordinates":[-106.655815,52.11694],"type":"Point"}
}