{
  "type": "Feature",
  "properties": {
    "addr:full":"2824 Jacklin Rd Victoria BC V9B 3X9",
    "addr:housenumber":"2824",
    "addr:postcode":"v9b 3x9",
    "addr:street":"Jacklin Rd",
    "iso:country":"CA",
    "sg:address":"2824 Jacklin Rd",
    "sg:city":"Victoria",
    "sg:classifiers":[
        {
            "category":"Personal",
            "subcategory":"Beauty Salon",
            "type":"Services"
        }
    ],
    "sg:phone":"+1 250 478 8855",
    "sg:postcode":"V9B 3X9",
    "sg:province":"BC",
    "wof:name":"Perfection Hair Studio",
    "wof:placetype":"venue"
},
  "geometry": {"coordinates":[-123.364517212,48.428314209],"type":"Point"}
}