{
  "type": "Feature",
  "properties": {
    "addr:full":"1270 Lynn Valley Rd North Vancouver BC V7J 2A3",
    "addr:housenumber":"1270",
    "addr:postcode":"v7j 2a3",
    "addr:street":"Lynn Valley Rd",
    "iso:country":"CA",
    "sg:address":"1270 Lynn Valley Rd",
    "sg:city":"North Vancouver",
    "sg:classifiers":[
        {
            "category":"Retail",
            "subcategory":"Auto Repair",
            "type":"Services"
        }
    ],
    "sg:phone":"+1 604 985 8811",
    "sg:postcode":"V7J 2A3",
    "sg:province":"BC",
    "sg:tags":[
        "repairing",
        "automobile"
    ],
    "wof:name":"Westlynn Service",
    "wof:placetype":"venue"
},
  "geometry": {"coordinates":[-123.03894043,49.3368377686],"type":"Point"}
}