{
  "type": "Feature",
  "properties": {
    "addr:full":"2145 15th Ave W Vancouver BC V6K 2Y4",
    "addr:housenumber":"2145",
    "addr:postcode":"v6k 2y4",
    "addr:street":"15Th Ave W",
    "iso:country":"CA",
    "sg:address":"2145 15th Ave W",
    "sg:city":"Vancouver",
    "sg:classifiers":[
        {
            "category":"Personal",
            "type":"Services"
        }
    ],
    "sg:phone":"+1 604 731 7838",
    "sg:postcode":"V6K 2Y4",
    "sg:province":"BC",
    "sg:tags":[
        "therapist",
        "massage"
    ],
    "wof:name":"Approach Cranial Sacral",
    "wof:placetype":"venue"
},
  "geometry": {"coordinates":[-123.154175,49.258389],"type":"Point"}
}