{
  "type": "Feature",
  "properties": {
    "addr:full":"Marmora ON K0K 2M0",
    "addr:postcode":"k0k 2m0",
    "iso:country":"CA",
    "sg:city":"Marmora",
    "sg:classifiers":[
        {
            "category":"Retail",
            "subcategory":"Animal Services",
            "type":"Services"
        }
    ],
    "sg:phone":"+1 613 472 1353",
    "sg:postcode":"K0K 2M0",
    "sg:province":"ON",
    "sg:tags":[
        "breeder",
        "horse"
    ],
    "wof:name":"Shiloh Ranch",
    "wof:placetype":"venue"
},
  "geometry": {"coordinates":[-77.681557,44.483089],"type":"Point"}
}