{
  "type": "Feature",
  "properties": {
    "addr:full":"Vancouver BC V6J 1W8",
    "addr:postcode":"v6j 1w8",
    "iso:country":"CA",
    "sg:city":"Vancouver",
    "sg:classifiers":[
        {
            "category":"Professional",
            "type":"Services"
        }
    ],
    "sg:phone":"+1 604 739 7833",
    "sg:postcode":"V6J 1W8",
    "sg:province":"BC",
    "sg:tags":[
        "establishment"
    ],
    "wof:name":"Allegro Enterprises Inc",
    "wof:placetype":"venue"
},
  "geometry": {"coordinates":[-123.138901,49.2635],"type":"Point"}
}