{
  "type": "Feature",
  "properties": {
    "addr:full":"860 College St Toronto ON M6H 1A2",
    "addr:housenumber":"860",
    "addr:postcode":"m6h 1a2",
    "addr:street":"College St",
    "iso:country":"CA",
    "sg:address":"860 College St",
    "sg:city":"Toronto",
    "sg:classifiers":[
        {
            "category":"Real Estate",
            "subcategory":"Real Estate Agent",
            "type":"Services"
        }
    ],
    "sg:phone":"+1 416 532 5400",
    "sg:postcode":"M6H 1A2",
    "sg:province":"ON",
    "wof:name":"Canada Group",
    "wof:placetype":"venue"
},
  "geometry": {"coordinates":[-79.42382000000001,43.654259],"type":"Point"}
}