{
  "type": "Feature",
  "properties": {
    "addr:full":"1500 Boul Laframboise Saint-Hyacinthe QC J2S 4W9",
    "addr:housenumber":"1500",
    "addr:postcode":"j2s 4w9",
    "addr:street":"Boul Laframboise",
    "iso:country":"CA",
    "sg:address":"1500 Boul Laframboise",
    "sg:city":"Saint-Hyacinthe",
    "sg:classifiers":[
        {
            "category":"Building & Trades",
            "subcategory":"Landscaping Services",
            "type":"Services"
        }
    ],
    "sg:phone":"+1 450 771 1001",
    "sg:postcode":"J2S 4W9",
    "sg:province":"QC",
    "sg:tags":[
        "lawn",
        "maintenance",
        "grounds"
    ],
    "wof:name":"Verdur St-Hyacinthe",
    "wof:placetype":"venue"
},
  "geometry": {"coordinates":[-72.948761,45.62854],"type":"Point"}
}