{
  "type": "Feature",
  "properties": {
    "iso:country":"CA",
    "sg:city":"Aylmer",
    "sg:classifiers":[
        {
            "category":"Building & Trades",
            "subcategory":"Construction",
            "type":"Services"
        }
    ],
    "sg:phone":"+1 819 684 1279",
    "sg:postcode":"J9H 5B6",
    "sg:province":"QC",
    "sg:tags":[
        "roofing",
        "contractor"
    ],
    "wof:name":"Toitures Bien Faites",
    "wof:placetype":"venue"
},
  "geometry": {"coordinates":[-75.844872,45.394909],"type":"Point"}
}