{
  "type": "Feature",
  "properties": {
    "iso:country":"CA",
    "sg:address":"1430 31 St N # D",
    "sg:city":"Lethbridge",
    "sg:classifiers":[
        {
            "category":"Wholesale",
            "subcategory":"Office Equipment",
            "type":"Manufacturing & Wholesale Goods"
        }
    ],
    "sg:phone":"+1 403 328 8077",
    "sg:postcode":"T1H 5J8",
    "sg:province":"AB",
    "sg:tags":[
        "supply",
        "register",
        "cash",
        "duplicating",
        "machine",
        "copying"
    ],
    "wof:name":"Tri-Tech Office Products Ltd",
    "wof:placetype":"venue"
},
  "geometry": {"coordinates":[-112.794724,49.718475],"type":"Point"}
}