{
  "type": "Feature",
  "properties": {
    "iso:country":"CA",
    "sg:city":"Oakville",
    "sg:classifiers":[
        {
            "category":"Banks & Credit Unions",
            "subcategory":"Investment Brokerage",
            "type":"Services"
        }
    ],
    "sg:phone":"+1 905 825 9000",
    "sg:postcode":"L6M 3G4",
    "sg:province":"ON",
    "sg:tags":[
        "advisory",
        "financial"
    ],
    "wof:name":"Lincluden Management Ltd",
    "wof:placetype":"venue"
},
  "geometry": {"coordinates":[-79.71709442140001,43.4321098328],"type":"Point"}
}