{
  "type": "Feature",
  "properties": {
    "addr:full":"Cote DE LA Citadelle Quebec QC G1R 4V7",
    "addr:postcode":"g1r 4v7",
    "addr:street":"Cote De La Citadelle",
    "iso:country":"CA",
    "sg:address":"Cote DE LA Citadelle",
    "sg:city":"Quebec",
    "sg:classifiers":[
        {
            "category":"Organizations",
            "subcategory":"Community Association",
            "type":"Services"
        }
    ],
    "sg:phone":"+1 418 692 3391",
    "sg:postcode":"G1R 4V7",
    "sg:province":"QC",
    "sg:tags":[
        "club"
    ],
    "wof:name":"Club Patenaude",
    "wof:placetype":"venue"
},
  "geometry": {"coordinates":[-71.210556,46.808453],"type":"Point"}
}