{
  "type": "Feature",
  "properties": {
    "iso:country":"CA",
    "sg:city":"Dorval",
    "sg:classifiers":[
        {
            "category":"Shopping",
            "subcategory":"Computers & Home Electronics",
            "type":"Retail Goods"
        }
    ],
    "sg:phone":"+1 514 421 6656",
    "sg:postcode":"H9P 1H6",
    "sg:province":"QC",
    "sg:tags":[
        "equipment",
        "satellite",
        "system"
    ],
    "wof:name":"Gregory Electronics-Omni Stat",
    "wof:placetype":"venue"
},
  "geometry": {"coordinates":[-73.783936,45.486767],"type":"Point"}
}