{
  "type": "Feature",
  "properties": {
    "addr:full":"201 Main St Wakaw SK S0K 4P0",
    "addr:housenumber":"201",
    "addr:postcode":"s0k 4p0",
    "addr:street":"Main St",
    "iso:country":"CA",
    "sg:address":"201 Main St",
    "sg:city":"Wakaw",
    "sg:classifiers":[
        {
            "category":"Recreation",
            "type":"Entertainment"
        }
    ],
    "sg:phone":"+1 306 233 5223",
    "sg:postcode":"S0K 4P0",
    "sg:province":"SK",
    "sg:tags":[
        "consultant",
        "program",
        "center"
    ],
    "wof:name":"Wakaw Recreation Ctr",
    "wof:placetype":"venue"
},
  "geometry": {"coordinates":[-105.74270629900001,52.6529502869],"type":"Point"}
}