{
  "type": "Feature",
  "properties": {
    "iso:country":"CA",
    "sg:address":"235 River Rd",
    "sg:city":"Hazelton",
    "sg:classifiers":[
        {
            "category":"Education",
            "subcategory":"Special Training",
            "type":"Public Place"
        }
    ],
    "sg:phone":"+1 250 842 6028",
    "sg:postcode":"V0J 1Y0",
    "sg:province":"BC",
    "sg:tags":[
        "school",
        "instruction",
        "art"
    ],
    "wof:name":"Kitanmax School of Northwest",
    "wof:placetype":"venue"
},
  "geometry": {"coordinates":[-127.643867493,55.2642593384],"type":"Point"}
}