{
  "type": "Feature",
  "properties": {
    "addr:full":"3587 Rue DE L'Hetriere Saint-Augustin-DE-Desmaures QC G3A 2L4",
    "addr:housenumber":"3587",
    "addr:postcode":"g3a 2l4",
    "addr:street":"Rue De L'Hetriere",
    "iso:country":"CA",
    "sg:address":"3587 Rue DE L'Hetriere",
    "sg:city":"Saint-Augustin-DE-Desmaures",
    "sg:classifiers":[
        {
            "category":"Home & Garden",
            "subcategory":"Home Furnishings",
            "type":"Retail Goods"
        }
    ],
    "sg:phone":"+1 418 877 5532",
    "sg:postcode":"G3A 2L4",
    "sg:province":"QC",
    "sg:tags":[
        "door",
        "mirror"
    ],
    "wof:name":"Vitrerie Denis Savard Inc",
    "wof:placetype":"venue"
},
  "geometry": {"coordinates":[-71.3835144043,46.7499847412],"type":"Point"}
}