{
  "type": "Feature",
  "properties": {
    "iso:country":"CA",
    "sg:city":"Victoriaville",
    "sg:classifiers":[
        {
            "category":"Personal",
            "subcategory":"Beauty Salon",
            "type":"Services"
        }
    ],
    "sg:phone":"+1 819 758 5454",
    "sg:postcode":"G6P 6R9",
    "sg:province":"QC",
    "sg:tags":[
        "therapist",
        "manicuring",
        "massage"
    ],
    "wof:name":"Centre DE Sante Beaute Maryse",
    "wof:placetype":"venue"
},
  "geometry": {"coordinates":[-71.95947265620001,46.0556564331],"type":"Point"}
}