{
  "type": "Feature",
  "properties": {
    "iso:country":"CA",
    "sg:address":"4011 Kingston Crt",
    "sg:city":"Burlington",
    "sg:classifiers":[
        {
            "category":"Wholesale",
            "subcategory":"Auto Parts",
            "type":"Manufacturing & Wholesale Goods"
        }
    ],
    "sg:phone":"+1 905 637 2202",
    "sg:postcode":"L7L 4Y4",
    "sg:province":"ON",
    "sg:tags":[
        "body",
        "automobile",
        "shop"
    ],
    "wof:name":"Mike's Body Shop Supplies",
    "wof:placetype":"venue"
},
  "geometry": {"coordinates":[-79.772567749,43.3554840088],"type":"Point"}
}