{
  "type": "Feature",
  "properties": {
    "addr:full":"1966 Harrison Way Kamloops BC V1S 1M9",
    "addr:housenumber":"1966",
    "addr:postcode":"bc v1s 1m9",
    "addr:street":"Harrison Way",
    "iso:country":"CA",
    "sg:address":"1966 Harrison Way",
    "sg:city":"Kamloops",
    "sg:classifiers":[
        {
            "category":"Health Services",
            "subcategory":"Doctor",
            "type":"Services"
        }
    ],
    "sg:phone":"+1 250 314 5300",
    "sg:postcode":"V1S 1M9",
    "sg:province":"BC",
    "sg:tags":[
        "physician",
        "surgeon"
    ],
    "wof:name":"Aberdeen Medical Ctr",
    "wof:placetype":"venue"
},
  "geometry": {"coordinates":[-120.37411499,50.649017334],"type":"Point"}
}