{
  "type": "Feature",
  "properties": {
    "addr:full":"10260 99 St Grande Prairie AB T8V 2H4",
    "addr:housenumber":"10260",
    "addr:postcode":"t8v 2h4",
    "addr:street":"99 St",
    "iso:country":"CA",
    "sg:address":"10260 99 St",
    "sg:city":"Grande Prairie",
    "sg:classifiers":[
        {
            "category":"Government",
            "subcategory":"Office",
            "type":"Public Place"
        }
    ],
    "sg:phone":"+1 780 538 5360",
    "sg:postcode":"T8V 2H4",
    "sg:province":"AB",
    "wof:name":"Alberta Provincial Court",
    "wof:placetype":"venue"
},
  "geometry": {"coordinates":[-118.80426,55.17004],"type":"Point"}
}