{
  "type": "Feature",
  "properties": {
    "addr:full":"Surrey BC V3W 0K8",
    "addr:postcode":"v3w 0k8",
    "iso:country":"CA",
    "sg:city":"Surrey",
    "sg:classifiers":[
        {
            "category":"Professional",
            "subcategory":"Engineering",
            "type":"Services"
        }
    ],
    "sg:phone":"+1 604 543 8871",
    "sg:postcode":"V3W 0K8",
    "sg:province":"BC",
    "sg:tags":[
        "engineer"
    ],
    "wof:name":"Metro Testing",
    "wof:placetype":"venue"
},
  "geometry": {"coordinates":[-122.865882873,49.1575126648],"type":"Point"}
}