{
  "type": "Feature",
  "properties": {
    "addr:full":"2580 Burrard St Vancouver BC V6J 3J7",
    "addr:housenumber":"2580",
    "addr:postcode":"v6j 3j7",
    "addr:street":"Burrard St",
    "iso:country":"CA",
    "sg:address":"2580 Burrard St",
    "sg:city":"Vancouver",
    "sg:classifiers":[
        {
            "category":"Retail",
            "subcategory":"Portrait Studio",
            "type":"Services"
        }
    ],
    "sg:phone":"+1 604 736 0261",
    "sg:postcode":"V6J 3J7",
    "sg:province":"BC",
    "sg:tags":[
        "photographer"
    ],
    "wof:name":"Campbell Studios Ltd",
    "wof:placetype":"venue"
},
  "geometry": {"coordinates":[-123.145584,49.263008],"type":"Point"}
}