{
  "type": "Feature",
  "properties": {
    "addr:full":"1328 Rue Beaubien E Montreal QC H2G 1K8",
    "addr:housenumber":"1328",
    "addr:postcode":"h2g 1k8",
    "addr:street":"Rue Beaubien E",
    "iso:country":"CA",
    "sg:address":"1328 Rue Beaubien E",
    "sg:city":"Montreal",
    "sg:classifiers":[
        {
            "category":"Shopping",
            "subcategory":"Clothing, Apparel, & Fashions",
            "type":"Retail Goods"
        }
    ],
    "sg:phone":"+1 514 279 4528",
    "sg:postcode":"H2G 1K8",
    "sg:province":"QC",
    "sg:tags":[
        "item",
        "boutique"
    ],
    "wof:name":"Detour En Province",
    "wof:placetype":"venue"
},
  "geometry": {"coordinates":[-73.59902200000001,45.54031],"type":"Point"}
}