{
  "type": "Feature",
  "properties": {
    "iso:country":"CA",
    "sg:address":"1328 Rue Beaubien E",
    "sg:city":"Montreal",
    "sg:classifiers":[
        {
            "category":"Shopping",
            "subcategory":"Clothing, Apparel, & Fashions",
            "type":"Retail Goods"
        }
    ],
    "sg:phone":"+1 514 279 4528",
    "sg:postcode":"H2G 1K8",
    "sg:province":"QC",
    "sg:tags":[
        "item",
        "boutique"
    ],
    "wof:name":"Detour En Province",
    "wof:placetype":"venue"
},
  "geometry": {"coordinates":[-73.599022,45.54031],"type":"Point"}
}