{
  "type": "Feature",
  "properties": {
    "addr:full":"5 Agassiz Ave Stonewall MB R0C 2Z0",
    "addr:housenumber":"5",
    "addr:postcode":"r0c 2z0",
    "addr:street":"Agassiz Ave",
    "iso:country":"CA",
    "sg:address":"5 Agassiz Ave",
    "sg:city":"Stonewall",
    "sg:classifiers":[
        {
            "category":"Building & Trades",
            "subcategory":"Electrical",
            "type":"Services"
        }
    ],
    "sg:phone":"+1 204 467 2933",
    "sg:postcode":"R0C 2Z0",
    "sg:province":"MB",
    "sg:tags":[
        "electric",
        "contractor"
    ],
    "wof:name":"Richman Electric Ltd",
    "wof:placetype":"venue"
},
  "geometry": {"coordinates":[-97.314667,50.139679],"type":"Point"}
}