{
  "type": "Feature",
  "properties": {
    "addr:full":"985 Fennell Ave E Hamilton ON L8T 1R1",
    "addr:housenumber":"985",
    "addr:postcode":"l8t 1r1",
    "addr:street":"Fennell Ave E",
    "iso:country":"CA",
    "sg:address":"985 Fennell Ave E",
    "sg:city":"Hamilton",
    "sg:classifiers":[
        {
            "category":"Insurance",
            "subcategory":"Insurance Agent",
            "type":"Services"
        }
    ],
    "sg:phone":"+1 905 387 2121",
    "sg:postcode":"L8T 1R1",
    "sg:province":"ON",
    "wof:name":"Allen & DE Blauw Insurance",
    "wof:placetype":"venue"
},
  "geometry": {"coordinates":[-79.83731079099999,43.2277030945],"type":"Point"}
}