{
  "type": "Feature",
  "properties": {
    "addr:full":"Delta BC V4C 6R4",
    "addr:postcode":"v4c 6r4",
    "iso:country":"CA",
    "sg:city":"Delta",
    "sg:classifiers":[
        {
            "category":"Restaurant",
            "type":"Food & Drink"
        }
    ],
    "sg:phone":"+1 604 590 2277",
    "sg:postcode":"V4C 6R4",
    "sg:province":"BC",
    "wof:name":"Mamma Gina's",
    "wof:placetype":"venue"
},
  "geometry": {"coordinates":[-122.89050293,49.1606483459],"type":"Point"}
}