{
  "type": "Feature",
  "properties": {
    "iso:country":"CA",
    "sg:address":"287 Wexford Ave S",
    "sg:city":"Hamilton",
    "sg:classifiers":[
        {
            "category":"Social Services",
            "type":"Services"
        }
    ],
    "sg:phone":"+1 905 528 8216",
    "sg:postcode":"L8K 2P4",
    "sg:province":"ON",
    "sg:tags":[
        "counselor",
        "human",
        "relations"
    ],
    "wof:name":"Capability Corps Inc",
    "wof:placetype":"venue"
},
  "geometry": {"coordinates":[-79.8158187866,43.2334060669],"type":"Point"}
}