{
  "type": "Feature",
  "properties": {
    "addr:full":"1920 4 St SW Calgary AB T2S 1W3",
    "addr:housenumber":"1920 4",
    "addr:postcode":"t2s 1w3",
    "addr:street":"St Sw",
    "iso:country":"CA",
    "sg:address":"1920 4 St SW",
    "sg:city":"Calgary",
    "sg:classifiers":[
        {
            "category":"Retail",
            "subcategory":"Car Wash",
            "type":"Services"
        }
    ],
    "sg:phone":"+1 403 228 6473",
    "sg:postcode":"T2S 1W3",
    "sg:province":"AB",
    "sg:tags":[
        "polishing",
        "washing"
    ],
    "wof:name":"Petro-Canada",
    "wof:placetype":"venue"
},
  "geometry": {"coordinates":[-114.07128899999999,51.035835],"type":"Point"}
}