{
  "type": "Feature",
  "properties": {
    "addr:full":"7 Old King Rd Nobleton ON L0G 1N0",
    "addr:housenumber":"7",
    "addr:postcode":"l0g 1n0",
    "addr:street":"Old King Rd",
    "iso:country":"CA",
    "sg:address":"7 Old King Rd",
    "sg:city":"Nobleton",
    "sg:classifiers":[
        {
            "category":"Wholesale",
            "subcategory":"Farm Supplies",
            "type":"Manufacturing & Wholesale Goods"
        }
    ],
    "sg:phone":"+1 905 859 0762",
    "sg:postcode":"L0G 1N0",
    "sg:province":"ON",
    "sg:tags":[
        "feed"
    ],
    "wof:name":"Nobleton Feed Mill",
    "wof:placetype":"venue"
},
  "geometry": {"coordinates":[-79.652199,43.901562],"type":"Point"}
}