{
  "type": "Feature",
  "properties": {
    "addr:full":"Saint-Omer-L'Islet QC G0R 4R0",
    "addr:postcode":"g0r 4r0",
    "iso:country":"CA",
    "sg:city":"Saint-Omer-L'Islet",
    "sg:classifiers":[
        {
            "category":"Manufacturing",
            "subcategory":"Building Materials",
            "type":"Manufacturing & Wholesale Goods"
        }
    ],
    "sg:phone":"+1 418 356 3682",
    "sg:postcode":"G0R 4R0",
    "sg:province":"QC",
    "sg:tags":[
        "contractor"
    ],
    "wof:name":"Construction L'Islet Sud Inc",
    "wof:placetype":"venue"
},
  "geometry": {"coordinates":[-70.331535,47.089802],"type":"Point"}
}