{
  "type": "Feature",
  "properties": {
    "iso:country":"CA",
    "sg:city":"Pierrefonds",
    "sg:classifiers":[
        {
            "category":"Professional",
            "subcategory":"Lawyer & Legal Services",
            "type":"Services"
        }
    ],
    "sg:phone":"+1 514 624 0446",
    "sg:postcode":"H8Z 3K5",
    "sg:province":"QC",
    "sg:tags":[
        "naturalization",
        "immigration"
    ],
    "wof:name":"Canada Immigration & Investmnt",
    "wof:placetype":"venue"
},
  "geometry": {"coordinates":[-73.852776,45.497505],"type":"Point"}
}