{
  "type": "Feature",
  "properties": {
    "addr:full":"1455 Marine Dr West Vancouver BC V7T 1B8",
    "addr:housenumber":"1455",
    "addr:postcode":"v7t 1b8",
    "addr:street":"Marine Dr",
    "iso:country":"CA",
    "sg:address":"1455 Marine Dr",
    "sg:city":"West Vancouver",
    "sg:classifiers":[
        {
            "category":"Shopping",
            "subcategory":"Bicycles & Sporting Goods",
            "type":"Retail Goods"
        }
    ],
    "sg:phone":"+1 604 921 4537",
    "sg:postcode":"V7T 1B8",
    "sg:province":"BC",
    "wof:name":"Bicycle Sports Pacific",
    "wof:placetype":"venue"
},
  "geometry": {"coordinates":[-123.15560913100001,49.3282661438],"type":"Point"}
}