{
  "type": "Feature",
  "properties": {
    "iso:country":"CA",
    "sg:address":"10108 104th Ave",
    "sg:city":"Hythe",
    "sg:classifiers":[
        {
            "category":"Education",
            "subcategory":"School",
            "type":"Public Place"
        }
    ],
    "sg:phone":"+1 780 356 3934",
    "sg:postcode":"T0H 2C0",
    "sg:province":"AB",
    "wof:name":"Hythe Elementary School",
    "wof:placetype":"venue"
},
  "geometry": {"coordinates":[-119.551231384,55.329990387],"type":"Point"}
}