{
  "type": "Feature",
  "properties": {
    "addr:full":"Brandon MB R7A 2X1",
    "addr:postcode":"r7a 2x1",
    "iso:country":"CA",
    "sg:city":"Brandon",
    "sg:classifiers":[
        {
            "category":"Banks & Credit Unions",
            "subcategory":"Investment Brokerage",
            "type":"Services"
        }
    ],
    "sg:phone":"+1 204 726 4167",
    "sg:postcode":"R7A 2X1",
    "sg:province":"MB",
    "wof:name":"Edward Jones",
    "wof:placetype":"venue"
},
  "geometry": {"coordinates":[-99.939346,49.841869],"type":"Point"}
}