{
  "type": "Feature",
  "properties": {
    "addr:full":"260 Park Dr Clearwater BC V0E 1N0",
    "addr:housenumber":"260",
    "addr:postcode":"v0e 1n0",
    "addr:street":"Park Dr",
    "iso:country":"CA",
    "sg:address":"260 Park Dr",
    "sg:city":"Clearwater",
    "sg:classifiers":[
        {
            "category":"Restaurant",
            "type":"Food & Drink"
        }
    ],
    "sg:phone":"+1 250 674 2945",
    "sg:postcode":"V0E 1N0",
    "sg:province":"BC",
    "wof:name":"Old Caboose Restaurant Ltd",
    "wof:placetype":"venue"
},
  "geometry": {"coordinates":[-120.021255,51.646881],"type":"Point"}
}