{
  "type": "Feature",
  "properties": {
    "addr:full":"Concord ON L4K 2A9",
    "addr:postcode":"l4k 2a9",
    "iso:country":"CA",
    "sg:city":"Concord",
    "sg:classifiers":[
        {
            "category":"Manufacturing",
            "subcategory":"Metals",
            "type":"Manufacturing & Wholesale Goods"
        }
    ],
    "sg:phone":"+1 905 669 6260",
    "sg:postcode":"L4K 2A9",
    "sg:province":"ON",
    "sg:tags":[
        "production",
        "grinding"
    ],
    "wof:name":"Microchrome Crankshaft CO Ltd",
    "wof:placetype":"venue"
},
  "geometry": {"coordinates":[-79.51364898680001,43.7944946289],"type":"Point"}
}