{
  "type": "Feature",
  "properties": {
    "addr:full":"Toronto ON M6G 1L5",
    "addr:postcode":"m6g 1l5",
    "iso:country":"CA",
    "sg:city":"Toronto",
    "sg:classifiers":[
        {
            "category":"Travel",
            "subcategory":"Travel Agent",
            "type":"Entertainment"
        }
    ],
    "sg:phone":"+1 416 534 7557",
    "sg:postcode":"M6G 1L5",
    "sg:province":"ON",
    "sg:tags":[
        "agency",
        "bureau"
    ],
    "wof:name":"Earl Warren Travel",
    "wof:placetype":"venue"
},
  "geometry": {"coordinates":[-79.417755,43.663567],"type":"Point"}
}