{
  "type": "Feature",
  "properties": {
    "addr:full":"15 Rue Du Moulin Saint-Vianney QC G0J 3J0",
    "addr:housenumber":"15",
    "addr:postcode":"g0j 3j0",
    "addr:street":"Rue Du Moulin",
    "iso:country":"CA",
    "sg:address":"15 Rue Du Moulin",
    "sg:city":"Saint-Vianney",
    "sg:classifiers":[
        {
            "category":"Freight",
            "type":"Transportation"
        }
    ],
    "sg:phone":"+1 418 629 4766",
    "sg:postcode":"G0J 3J0",
    "sg:province":"QC",
    "sg:tags":[
        "trucking"
    ],
    "wof:name":"Transport Jean-Claude",
    "wof:placetype":"venue"
},
  "geometry": {"coordinates":[-67.410309,48.614353],"type":"Point"}
}