{
  "type": "Feature",
  "properties": {
    "addr:full":"250 Rue Lacroix Saint-Gervais QC G0R 3C0",
    "addr:housenumber":"250",
    "addr:postcode":"g0r 3c0",
    "addr:street":"Rue Lacroix",
    "iso:country":"CA",
    "sg:address":"250 Rue Lacroix",
    "sg:city":"Saint-Gervais",
    "sg:classifiers":[
        {
            "category":"Retail",
            "subcategory":"Auto Repair",
            "type":"Services"
        }
    ],
    "sg:phone":"+1 418 887 3596",
    "sg:postcode":"G0R 3C0",
    "sg:province":"QC",
    "sg:tags":[
        "repairing",
        "automobile"
    ],
    "wof:name":"Garage Roger Godbout",
    "wof:placetype":"venue"
},
  "geometry": {"coordinates":[-70.88502502439999,46.7137107849],"type":"Point"}
}