{
  "type": "Feature",
  "properties": {
    "addr:full":"11940 224 St Maple Ridge BC V2X 8T1",
    "addr:housenumber":"11940",
    "addr:postcode":"v2x 8t1",
    "addr:street":"224 St",
    "iso:country":"CA",
    "sg:address":"11940 224 St",
    "sg:city":"Maple Ridge",
    "sg:classifiers":[
        {
            "category":"Social Services",
            "type":"Services"
        }
    ],
    "sg:phone":"+1 604 463 9388",
    "sg:postcode":"V2X 8T1",
    "sg:province":"BC",
    "sg:tags":[
        "organization",
        "welfare"
    ],
    "wof:name":"Air Cadet 583 Squadron",
    "wof:placetype":"venue"
},
  "geometry": {"coordinates":[-122.601555,49.219322],"type":"Point"}
}