{
  "type": "Feature",
  "properties": {
    "addr:full":"4506 10 St NE Calgary AB T2E 6K3",
    "addr:housenumber":"4506",
    "addr:postcode":"t2e 6k3",
    "addr:street":"10 St Ne",
    "iso:country":"CA",
    "sg:address":"4506 10 St NE",
    "sg:city":"Calgary",
    "sg:classifiers":[
        {
            "category":"Wholesale",
            "subcategory":"Chemicals & Plastics",
            "type":"Manufacturing & Wholesale Goods"
        }
    ],
    "sg:phone":"+1 403 296 0030",
    "sg:postcode":"T2E 6K3",
    "sg:province":"AB",
    "sg:tags":[
        "adhesive",
        "glue",
        "gluing",
        "equipment"
    ],
    "wof:name":"E B Peerless Ltd",
    "wof:placetype":"venue"
},
  "geometry": {"coordinates":[-114.03819300000001,51.092175],"type":"Point"}
}