{
  "type": "Feature",
  "properties": {
    "addr:full":"332 Guelph St Georgetown ON L7G 4B5",
    "addr:housenumber":"332",
    "addr:postcode":"l7g 4b5",
    "addr:street":"Guelph St",
    "iso:country":"CA",
    "sg:address":"332 Guelph St",
    "sg:city":"Georgetown",
    "sg:classifiers":[
        {
            "category":"Retail",
            "subcategory":"Laundry & Dry Cleaning",
            "type":"Services"
        }
    ],
    "sg:phone":"+1 905 877 2279",
    "sg:postcode":"L7G 4B5",
    "sg:province":"ON",
    "sg:tags":[
        "cleaners"
    ],
    "wof:name":"Barrager's Cleaners",
    "wof:placetype":"venue"
},
  "geometry": {"coordinates":[-79.88768,43.649269],"type":"Point"}
}