{
  "type": "Feature",
  "properties": {
    "addr:full":"339 Rue Saint-Paul E Montreal QC H2Y 1H3",
    "addr:housenumber":"339",
    "addr:postcode":"h2y 1h3",
    "addr:street":"Rue Saint-Paul E",
    "iso:country":"CA",
    "sg:address":"339 Rue Saint-Paul E",
    "sg:city":"Montreal",
    "sg:classifiers":[
        {
            "category":"Travel",
            "subcategory":"Travel Agent",
            "type":"Entertainment"
        }
    ],
    "sg:phone":"+1 514 848 7292",
    "sg:postcode":"H2Y 1H3",
    "sg:province":"QC",
    "sg:tags":[
        "consultant"
    ],
    "wof:name":"Prometour Inc",
    "wof:placetype":"venue"
},
  "geometry": {"coordinates":[-73.551864624,45.509059906],"type":"Point"}
}