{
  "type": "Feature",
  "properties": {
    "addr:full":"2012 2nd St N Cranbrook BC V1C 4M5",
    "addr:housenumber":"2012",
    "addr:postcode":"v1c 4m5",
    "addr:street":"2Nd St N",
    "iso:country":"CA",
    "sg:address":"2012 2nd St N",
    "sg:city":"Cranbrook",
    "sg:classifiers":[
        {
            "category":"Health Services",
            "subcategory":"Doctor",
            "type":"Services"
        }
    ],
    "sg:phone":"+1 250 426 2610",
    "sg:postcode":"V1C 4M5",
    "sg:province":"BC",
    "sg:tags":[
        "physician",
        "surgeon"
    ],
    "wof:name":"Baverstock Medical Svc Ltd",
    "wof:placetype":"venue"
},
  "geometry": {"coordinates":[-115.753334045,49.5140686035],"type":"Point"}
}