{
  "type": "Feature",
  "properties": {
    "iso:country":"CA",
    "sg:address":"5027 47A Ave",
    "sg:city":"Delta",
    "sg:classifiers":[
        {
            "category":"Organizations",
            "subcategory":"Religious Organization",
            "type":"Services"
        }
    ],
    "sg:phone":"+1 604 946 1227",
    "sg:postcode":"V4K 1T9",
    "sg:province":"BC",
    "sg:tags":[
        "church"
    ],
    "wof:name":"North America Indian Mission",
    "wof:placetype":"venue"
},
  "geometry": {"coordinates":[-123.059616,49.084801],"type":"Point"}
}