{
  "type": "Feature",
  "properties": {
    "addr:full":"Coquitlam BC V3J 3X2",
    "addr:postcode":"v3j 3x2",
    "iso:country":"CA",
    "sg:city":"Coquitlam",
    "sg:classifiers":[
        {
            "category":"Organizations",
            "subcategory":"Labor Organization",
            "type":"Services"
        }
    ],
    "sg:phone":"+1 604 931 2471",
    "sg:postcode":"V3J 3X2",
    "sg:province":"BC",
    "wof:name":"Union of Psychiatric Nurses",
    "wof:placetype":"venue"
},
  "geometry": {"coordinates":[-122.892288208,49.259513855],"type":"Point"}
}