{
  "type": "Feature",
  "properties": {
    "iso:country":"CA",
    "sg:address":"45955 Yale Rd",
    "sg:city":"Chilliwack",
    "sg:classifiers":[
        {
            "category":"Autos & Motor Vehicles",
            "subcategory":"Boat Sales",
            "type":"Retail Goods"
        }
    ],
    "sg:phone":"+1 604 795 9484",
    "sg:postcode":"V2P 2M4",
    "sg:province":"BC",
    "sg:tags":[
        "automobile",
        "dealer"
    ],
    "wof:name":"Leo Edwards & Sons Ltd",
    "wof:placetype":"venue"
},
  "geometry": {"coordinates":[-121.95777130099999,49.1681022644],"type":"Point"}
}