{
  "type": "Feature",
  "properties": {
    "addr:full":"261 Colony St Winnipeg MB R3C 1W4",
    "addr:housenumber":"261",
    "addr:postcode":"r3c 1w4",
    "addr:street":"Colony St",
    "iso:country":"CA",
    "sg:address":"261 Colony St",
    "sg:city":"Winnipeg",
    "sg:classifiers":[
        {
            "category":"Organizations",
            "subcategory":"Religious Organization",
            "type":"Services"
        }
    ],
    "sg:phone":"+1 204 772 0917",
    "sg:postcode":"R3C 1W4",
    "sg:province":"MB",
    "sg:tags":[
        "church"
    ],
    "wof:name":"Winnipeg Chinese Alliance Chr",
    "wof:placetype":"venue"
},
  "geometry": {"coordinates":[-97.15087127690001,49.8881225586],"type":"Point"}
}