{
  "type": "Feature",
  "properties": {
    "iso:country":"CA",
    "sg:address":"2 Renny Cres",
    "sg:city":"London",
    "sg:classifiers":[
        {
            "category":"Travel",
            "subcategory":"Travel Agent",
            "type":"Entertainment"
        }
    ],
    "sg:phone":"+1 519 685 0024",
    "sg:postcode":"N6E 2C5",
    "sg:province":"ON",
    "sg:tags":[
        "agency",
        "bureau"
    ],
    "wof:name":"Covenant Travel & Tours Inc",
    "wof:placetype":"venue"
},
  "geometry": {"coordinates":[-81.2276916504,42.9305725098],"type":"Point"}
}