{
  "type": "Feature",
  "properties": {
    "addr:full":"48 Bridgeport Rd E Waterloo ON N2J 2J6",
    "addr:housenumber":"48",
    "addr:postcode":"n2j 2j6",
    "addr:street":"Bridgeport Rd E",
    "iso:country":"CA",
    "sg:address":"48 Bridgeport Rd E",
    "sg:city":"Waterloo",
    "sg:classifiers":[
        {
            "category":"Health Services",
            "subcategory":"Medical Lab",
            "type":"Services"
        }
    ],
    "sg:phone":"+1 519 884 8386",
    "sg:postcode":"N2J 2J6",
    "sg:province":"ON",
    "wof:name":"Denture Clinic",
    "wof:placetype":"venue"
},
  "geometry": {"coordinates":[-80.51937100000001,43.4683],"type":"Point"}
}