{
  "type": "Feature",
  "properties": {
    "iso:country":"CA",
    "sg:address":"48 Bridgeport Rd E",
    "sg:city":"Waterloo",
    "sg:classifiers":[
        {
            "category":"Health Services",
            "subcategory":"Medical Lab",
            "type":"Services"
        }
    ],
    "sg:phone":"+1 519 884 8386",
    "sg:postcode":"N2J 2J6",
    "sg:province":"ON",
    "wof:name":"Denture Clinic",
    "wof:placetype":"venue"
},
  "geometry": {"coordinates":[-80.519371,43.4683],"type":"Point"}
}