{
  "type": "Feature",
  "properties": {
    "iso:country":"CA",
    "sg:address":"6 Loomcroft Lane",
    "sg:city":"Gagetown",
    "sg:classifiers":[
        {
            "category":"Education",
            "subcategory":"School",
            "type":"Public Place"
        }
    ],
    "sg:phone":"+1 506 488 3561",
    "sg:postcode":"E5M 1H2",
    "sg:province":"NB",
    "wof:name":"Gagetown School",
    "wof:placetype":"venue"
},
  "geometry": {"coordinates":[-66.15239,45.778137],"type":"Point"}
}