{
  "type": "Feature",
  "properties": {
    "addr:full":"360 Finchdene Sq #14 Scarborough ON M1X 1E1",
    "addr:housenumber":"360",
    "addr:postcode":"m1x 1e1",
    "addr:street":"Finchdene Sq # 14",
    "iso:country":"CA",
    "sg:address":"360 Finchdene Sq #14",
    "sg:city":"Scarborough",
    "sg:classifiers":[
        {
            "category":"Wholesale",
            "subcategory":"Machinery & Supplies",
            "type":"Manufacturing & Wholesale Goods"
        }
    ],
    "sg:phone":"+1 416 299 5027",
    "sg:postcode":"M1X 1E1",
    "sg:province":"ON",
    "sg:tags":[
        "repairing"
    ],
    "wof:name":"Reg Marsh Machine Repair Ltd",
    "wof:placetype":"venue"
},
  "geometry": {"coordinates":[-79.2373046875,43.8192977905],"type":"Point"}
}