{
  "type": "Feature",
  "properties": {
    "iso:country":"CA",
    "sg:address":"2285 Av Ekers",
    "sg:city":"Mont-Royal",
    "sg:classifiers":[
        {
            "category":"Wholesale",
            "subcategory":"Construction Materials",
            "type":"Manufacturing & Wholesale Goods"
        }
    ],
    "sg:phone":"+1 514 707 7752",
    "sg:postcode":"H3S 1C6",
    "sg:province":"QC",
    "sg:tags":[
        "art",
        "work",
        "metal"
    ],
    "wof:name":"Lamaire Francois Ferronnerie",
    "wof:placetype":"venue"
},
  "geometry": {"coordinates":[-73.628693,45.514912],"type":"Point"}
}