{
  "type": "Feature",
  "properties": {
    "iso:country":"CA",
    "sg:address":"920 King Edward Ave W",
    "sg:city":"Vancouver",
    "sg:classifiers":[
        {
            "category":"Personal",
            "subcategory":"Beauty Salon",
            "type":"Services"
        }
    ],
    "sg:phone":"+1 604 738 3603",
    "sg:postcode":"V5Z 2E2",
    "sg:province":"BC",
    "wof:name":"J Beauty Skin Care",
    "wof:placetype":"venue"
},
  "geometry": {"coordinates":[-123.125343323,49.249004364],"type":"Point"}
}