{
  "type": "Feature",
  "properties": {
    "iso:country":"CA",
    "sg:address":"94 Wellington St S",
    "sg:city":"Hamilton",
    "sg:classifiers":[
        {
            "category":"Health Services",
            "subcategory":"Nursing And Care Facility",
            "type":"Services"
        }
    ],
    "sg:phone":"+1 905 522 9342",
    "sg:postcode":"L8N 2R2",
    "sg:province":"ON",
    "sg:tags":[
        "home",
        "rest"
    ],
    "wof:name":"Wellington Lodge",
    "wof:placetype":"venue"
},
  "geometry": {"coordinates":[-79.8607711792,43.2507667542],"type":"Point"}
}