{
  "type": "Feature",
  "properties": {
    "addr:full":"17 St Mary's Rd Winnipeg MB R2H 1H2",
    "addr:housenumber":"17",
    "addr:postcode":"r2h 1h2",
    "addr:street":"St Mary'S Rd",
    "iso:country":"CA",
    "sg:address":"17 St Mary's Rd",
    "sg:city":"Winnipeg",
    "sg:classifiers":[
        {
            "category":"Professional",
            "subcategory":"Computer Services",
            "type":"Services"
        }
    ],
    "sg:phone":"+1 204 929 3818",
    "sg:postcode":"R2H 1H2",
    "sg:province":"MB",
    "sg:tags":[
        "repair",
        "internet"
    ],
    "wof:name":"I C Enternet",
    "wof:placetype":"venue"
},
  "geometry": {"coordinates":[-97.127174,49.880474],"type":"Point"}
}