{
  "type": "Feature",
  "properties": {
    "addr:full":"1630 Wellington Rd E Nanaimo BC V9S 5P8",
    "addr:housenumber":"1630",
    "addr:postcode":"v9s 5p8",
    "addr:street":"Wellington Rd E",
    "iso:country":"CA",
    "sg:address":"1630 Wellington Rd E",
    "sg:city":"Nanaimo",
    "sg:classifiers":[
        {
            "category":"Organizations",
            "subcategory":"Professional Association",
            "type":"Services"
        }
    ],
    "sg:phone":"+1 250 754 8128",
    "sg:postcode":"V9S 5P8",
    "sg:province":"BC",
    "sg:tags":[
        "fraternal"
    ],
    "wof:name":"Royal Canadian Legion MT",
    "wof:placetype":"venue"
},
  "geometry": {"coordinates":[-123.975182,49.181065],"type":"Point"}
}