{
  "type": "Feature",
  "properties": {
    "addr:full":"3515 Mcbean St Richmond ON K0A 2Z0",
    "addr:housenumber":"3515",
    "addr:postcode":"k0a 2z0",
    "addr:street":"Mcbean St",
    "iso:country":"CA",
    "sg:address":"3515 Mcbean St",
    "sg:city":"Richmond",
    "sg:classifiers":[
        {
            "category":"Personal",
            "subcategory":"Beauty Salon",
            "type":"Services"
        }
    ],
    "sg:phone":"+1 613 838 4753",
    "sg:postcode":"K0A 2Z0",
    "sg:province":"ON",
    "wof:name":"Sue's Hair Advantage",
    "wof:placetype":"venue"
},
  "geometry": {"coordinates":[-75.8347702026,45.1912078857],"type":"Point"}
}