{
  "type": "Feature",
  "properties": {
    "iso:country":"CA",
    "sg:city":"Guelph",
    "sg:classifiers":[
        {
            "category":"Retail",
            "subcategory":"Auto Repair",
            "type":"Services"
        }
    ],
    "sg:phone":"+1 519 836 4545",
    "sg:postcode":"N1K 1S5",
    "sg:province":"ON",
    "sg:tags":[
        "repairing",
        "automobile"
    ],
    "wof:name":"Apm Automotive",
    "wof:placetype":"venue"
},
  "geometry": {"coordinates":[-80.3061828613,43.5327262878],"type":"Point"}
}