{
  "type": "Feature",
  "properties": {
    "addr:full":"8391 Ch Brassard Saint-Michel-Des-Saints QC J0K 3B0",
    "addr:postcode":"8391;j0k 3b0",
    "addr:street":"Ch Brassard",
    "iso:country":"CA",
    "sg:address":"8391 Ch Brassard",
    "sg:city":"Saint-Michel-Des-Saints",
    "sg:classifiers":[
        {
            "category":"Autos & Motor Vehicles",
            "subcategory":"Boat Sales",
            "type":"Retail Goods"
        }
    ],
    "sg:phone":"+1 450 833 5000",
    "sg:postcode":"J0K 3B0",
    "sg:province":"QC",
    "sg:tags":[
        "dealer"
    ],
    "wof:name":"Blr Motorise",
    "wof:placetype":"venue"
},
  "geometry": {"coordinates":[-73.91584,46.663387],"type":"Point"}
}