{
  "type": "Feature",
  "properties": {
    "addr:full":"200 Park Lawn Rd Etobicoke ON M8Y 3J1",
    "addr:housenumber":"200",
    "addr:postcode":"m8y 3j1",
    "addr:street":"Park Lawn Rd",
    "iso:country":"CA",
    "sg:address":"200 Park Lawn Rd",
    "sg:city":"Etobicoke",
    "sg:classifiers":[
        {
            "category":"Education",
            "subcategory":"Library",
            "type":"Public Place"
        }
    ],
    "sg:phone":"+1 416 394 5300",
    "sg:postcode":"M8Y 3J1",
    "sg:province":"ON",
    "wof:name":"Humber Bay Public Library",
    "wof:placetype":"venue"
},
  "geometry": {"coordinates":[-79.490936,43.630146],"type":"Point"}
}