{
  "type": "Feature",
  "properties": {
    "addr:full":"90 Esna Park Dr Markham ON L3R 2R7",
    "addr:housenumber":"90",
    "addr:postcode":"l3r 2r7",
    "addr:street":"Esna Park Dr",
    "iso:country":"CA",
    "sg:address":"90 Esna Park Dr",
    "sg:city":"Markham",
    "sg:classifiers":[
        {
            "category":"Building & Trades",
            "subcategory":"Construction",
            "type":"Services"
        }
    ],
    "sg:phone":"+1 905 513 8523",
    "sg:postcode":"L3R 2R7",
    "sg:province":"ON",
    "sg:tags":[
        "general",
        "contractor"
    ],
    "wof:name":"Soumart Construction Mgmt Ltd",
    "wof:placetype":"venue"
},
  "geometry": {"coordinates":[-79.3398361206,43.8275680542],"type":"Point"}
}