{
  "type": "Feature",
  "properties": {
    "iso:country":"CA",
    "sg:address":"8790 Av Du Parc",
    "sg:city":"Montreal",
    "sg:classifiers":[
        {
            "category":"Professional",
            "subcategory":"Engineering",
            "type":"Services"
        }
    ],
    "sg:phone":"+1 514 381 9205",
    "sg:postcode":"H2N 1Y6",
    "sg:province":"QC",
    "sg:tags":[
        "engineer"
    ],
    "wof:name":"Dupras Ledoux & Assoc",
    "wof:placetype":"venue"
},
  "geometry": {"coordinates":[-73.647133,45.535904],"type":"Point"}
}