{
  "type": "Feature",
  "properties": {
    "addr:full":"64 Heritage Lane Welland ON L3C 6Z4",
    "addr:housenumber":"64",
    "addr:postcode":"l3c 6z4",
    "addr:street":"Heritage Lane",
    "iso:country":"CA",
    "sg:address":"64 Heritage Lane",
    "sg:city":"Welland",
    "sg:classifiers":[
        {
            "category":"Building & Trades",
            "subcategory":"Plumbing",
            "type":"Services"
        }
    ],
    "sg:phone":"+1 905 735 3346",
    "sg:postcode":"L3C 6Z4",
    "sg:province":"ON",
    "sg:tags":[
        "contractor"
    ],
    "wof:name":"Vince Vitucci Plumbing & Htg",
    "wof:placetype":"venue"
},
  "geometry": {"coordinates":[-79.2832183838,43.0151176453],"type":"Point"}
}