{
  "type": "Feature",
  "properties": {
    "addr:full":"Montreal QC H1T 4B3",
    "addr:postcode":"h1t 4b3",
    "iso:country":"CA",
    "sg:city":"Montreal",
    "sg:classifiers":[
        {
            "category":"Shopping",
            "type":"Retail Goods"
        }
    ],
    "sg:phone":"+1 514 254 9433",
    "sg:postcode":"H1T 4B3",
    "sg:province":"QC",
    "sg:tags":[
        "orthopedic",
        "appliance"
    ],
    "wof:name":"J E Hanger Ltd of Montreal",
    "wof:placetype":"venue"
},
  "geometry": {"coordinates":[-73.63369,45.581413],"type":"Point"}
}