{
  "type": "Feature",
  "properties": {
    "iso:country":"CA",
    "sg:address":"600 Boul Lafleche",
    "sg:city":"Baie-Comeau",
    "sg:classifiers":[
        {
            "category":"Personal",
            "subcategory":"Beauty Salon",
            "type":"Services"
        }
    ],
    "sg:phone":"+1 418 589 5606",
    "sg:postcode":"G5C 2X8",
    "sg:province":"QC",
    "wof:name":"Salon DE Coiffure Elle & Lui",
    "wof:placetype":"venue"
},
  "geometry": {"coordinates":[-68.25690460209999,49.2008209229],"type":"Point"}
}