{
  "type": "Feature",
  "properties": {
    "addr:full":"340 12E Rue Ferme-Neuve QC J0W 1C0",
    "addr:housenumber":"340",
    "addr:postcode":"j0w 1c0",
    "addr:street":"12E Rue",
    "iso:country":"CA",
    "sg:address":"340 12E Rue",
    "sg:city":"Ferme-Neuve",
    "sg:classifiers":[
        {
            "category":"Food & Beverages",
            "subcategory":"Liquor & Beverages",
            "type":"Retail Goods"
        }
    ],
    "sg:phone":"+1 819 587 4221",
    "sg:postcode":"J0W 1C0",
    "sg:province":"QC",
    "sg:tags":[
        "convenience",
        "store"
    ],
    "wof:name":"Depanneur Melanie & Chrystelle",
    "wof:placetype":"venue"
},
  "geometry": {"coordinates":[-75.45011100000001,46.703617],"type":"Point"}
}