{
  "type": "Feature",
  "properties": {
    "addr:full":"775 Rue Du Sacre-Coeur O Saint-Hyacinthe QC J2S 1V2",
    "addr:housenumber":"775",
    "addr:postcode":"j2s 1v2",
    "addr:street":"Rue Du Sacre-Coeur O",
    "iso:country":"CA",
    "sg:address":"775 Rue Du Sacre-Coeur O",
    "sg:city":"Saint-Hyacinthe",
    "sg:classifiers":[
        {
            "category":"Education",
            "subcategory":"School",
            "type":"Public Place"
        }
    ],
    "sg:phone":"+1 450 774 5130",
    "sg:postcode":"J2S 1V2",
    "sg:province":"QC",
    "wof:name":"Ecole Boisjoli Sacre-Coeur",
    "wof:placetype":"venue"
},
  "geometry": {"coordinates":[-72.9477233887,45.6376075745],"type":"Point"}
}