{
  "type": "Feature",
  "properties": {
    "addr:full":"514 15 Ave SW Calgary AB T2R 0R2",
    "addr:postcode":"t2r 0r2",
    "addr:street":"514 15 Ave Sw",
    "iso:country":"CA",
    "sg:address":"514 15 Ave SW",
    "sg:city":"Calgary",
    "sg:classifiers":[
        {
            "category":"Professional",
            "subcategory":"Business Services",
            "type":"Services"
        }
    ],
    "sg:phone":"+1 403 283 0197",
    "sg:postcode":"T2R 0R2",
    "sg:province":"AB",
    "sg:tags":[
        "appraiser"
    ],
    "wof:name":"Appraisal Consultants",
    "wof:placetype":"venue"
},
  "geometry": {"coordinates":[-114.07211303699999,51.0389404297],"type":"Point"}
}