{
  "type": "Feature",
  "properties": {
    "addr:full":"Calgary AB T2E 7K6",
    "addr:postcode":"t2e 7k6",
    "iso:country":"CA",
    "sg:city":"Calgary",
    "sg:classifiers":[
        {
            "category":"Retail",
            "subcategory":"Laundry & Dry Cleaning",
            "type":"Services"
        }
    ],
    "sg:phone":"+1 403 283 3456",
    "sg:postcode":"T2E 7K6",
    "sg:province":"AB",
    "sg:tags":[
        "cleaners",
        "upholstery"
    ],
    "wof:name":"Alberta Rug & Upholstery Clnrs",
    "wof:placetype":"venue"
},
  "geometry": {"coordinates":[-114.062737,51.061813],"type":"Point"}
}