{
  "type": "Feature",
  "properties": {
    "iso:country":"CA",
    "sg:address":"5593 Ch Saint-Francois",
    "sg:city":"Saint-Laurent",
    "sg:classifiers":[
        {
            "category":"Freight",
            "type":"Transportation"
        }
    ],
    "sg:phone":"+1 514 483 9333",
    "sg:postcode":"H4S 1W6",
    "sg:province":"QC",
    "sg:tags":[
        "courier"
    ],
    "wof:name":"Ldi Svc DE Courrier",
    "wof:placetype":"venue"
},
  "geometry": {"coordinates":[-73.736824,45.488274],"type":"Point"}
}