{
  "type": "Feature",
  "properties": {
    "addr:full":"835 Queen St Chatham ON N7M 2K5",
    "addr:housenumber":"835",
    "addr:postcode":"n7m 2k5",
    "addr:street":"Queen St",
    "iso:country":"CA",
    "sg:address":"835 Queen St",
    "sg:city":"Chatham",
    "sg:classifiers":[
        {
            "category":"Shopping",
            "subcategory":"Department Store",
            "type":"Retail Goods"
        }
    ],
    "sg:phone":"+1 519 354 2352",
    "sg:postcode":"N7M 2K5",
    "sg:province":"ON",
    "sg:tags":[
        "shop"
    ],
    "wof:name":"Top Dollar Bargain Ctr",
    "wof:placetype":"venue"
},
  "geometry": {"coordinates":[-82.16687774659999,42.3885803223],"type":"Point"}
}