{
  "type": "Feature",
  "properties": {
    "iso:country":"CA",
    "sg:address":"3435 13th Ave",
    "sg:city":"Regina",
    "sg:classifiers":[
        {
            "category":"Education",
            "subcategory":"Library",
            "type":"Public Place"
        }
    ],
    "sg:phone":"+1 306 777 6078",
    "sg:postcode":"S4T 1P8",
    "sg:province":"SK",
    "wof:name":"Connaught Library",
    "wof:placetype":"venue"
},
  "geometry": {"coordinates":[-104.630241394,50.4453086853],"type":"Point"}
}