{
  "type": "Feature",
  "properties": {
    "addr:full":"5200 Dixie Rd #4 Mississauga ON L4W 1E4",
    "addr:housenumber":"5200",
    "addr:postcode":"l4w 1e4",
    "addr:street":"Dixie Rd # 4",
    "iso:country":"CA",
    "sg:address":"5200 Dixie Rd #4",
    "sg:city":"Mississauga",
    "sg:classifiers":[
        {
            "category":"Shopping",
            "subcategory":"Bicycles & Sporting Goods",
            "type":"Retail Goods"
        }
    ],
    "sg:phone":"+1 905 602 9933",
    "sg:postcode":"L4W 1E4",
    "sg:province":"ON",
    "sg:tags":[
        "equipment",
        "exercise"
    ],
    "wof:name":"Treadmill Factory",
    "wof:placetype":"venue"
},
  "geometry": {"coordinates":[-79.626274,43.639473],"type":"Point"}
}