{
  "type": "Feature",
  "properties": {
    "iso:country":"CA",
    "sg:city":"Victoriaville",
    "sg:classifiers":[
        {
            "category":"Restaurant",
            "type":"Food & Drink"
        }
    ],
    "sg:phone":"+1 819 357 2225",
    "sg:postcode":"G6S 1C1",
    "sg:province":"QC",
    "wof:name":"Brasserie Le Pichet",
    "wof:placetype":"venue"
},
  "geometry": {"coordinates":[-71.92882537840001,46.0626182556],"type":"Point"}
}