{
  "type": "Feature",
  "properties": {
    "addr:full":"1313 Ranchlands Way NW Calgary AB T3G 2A1",
    "addr:housenumber":"1313",
    "addr:postcode":"t3g 2a1",
    "addr:street":"Ranchlands Way Nw",
    "iso:country":"CA",
    "sg:address":"1313 Ranchlands Way NW",
    "sg:city":"Calgary",
    "sg:classifiers":[
        {
            "category":"Organizations",
            "subcategory":"Religious Organization",
            "type":"Services"
        }
    ],
    "sg:phone":"+1 403 239 1114",
    "sg:postcode":"T3G 2A1",
    "sg:province":"AB",
    "sg:tags":[
        "church"
    ],
    "wof:name":"Westview Baptist Church",
    "wof:placetype":"venue"
},
  "geometry": {"coordinates":[-114.196335,51.119946],"type":"Point"}
}