{
  "type": "Feature",
  "properties": {
    "addr:full":"416 Main St Port Dover ON N0A 1N0",
    "addr:housenumber":"416",
    "addr:postcode":"n0a 1n0",
    "addr:street":"Main St",
    "iso:country":"CA",
    "sg:address":"416 Main St",
    "sg:city":"Port Dover",
    "sg:classifiers":[
        {
            "category":"Professional",
            "subcategory":"Business Services",
            "type":"Services"
        }
    ],
    "sg:phone":"+1 519 583 3268",
    "sg:postcode":"N0A 1N0",
    "sg:province":"ON",
    "sg:tags":[
        "interior",
        "consultant",
        "design",
        "decorator"
    ],
    "wof:name":"Easy Living",
    "wof:placetype":"venue"
},
  "geometry": {"coordinates":[-80.205124,42.787952],"type":"Point"}
}