{
  "type": "Feature",
  "properties": {
    "iso:country":"CA",
    "sg:address":"14186 Wheatley Ave",
    "sg:city":"White Rock",
    "sg:classifiers":[
        {
            "category":"Retail",
            "subcategory":"Laundry & Dry Cleaning",
            "type":"Services"
        }
    ],
    "sg:phone":"+1 604 536 4473",
    "sg:postcode":"V4B 2W5",
    "sg:province":"BC",
    "sg:tags":[
        "cleaners",
        "rug",
        "carpet"
    ],
    "wof:name":"Mariner's Carpet & Upholstery",
    "wof:placetype":"venue"
},
  "geometry": {"coordinates":[-122.829315185,49.0273017883],"type":"Point"}
}