{
  "type": "Feature",
  "properties": {
    "addr:full":"109 Souris St Yellow Grass SK S0G 5J0",
    "addr:housenumber":"109",
    "addr:postcode":"s0g 5j0",
    "addr:street":"Souris St",
    "iso:country":"CA",
    "sg:address":"109 Souris St",
    "sg:city":"Yellow Grass",
    "sg:classifiers":[
        {
            "category":"Insurance",
            "subcategory":"Insurance Agent",
            "type":"Services"
        }
    ],
    "sg:phone":"+1 306 465 2565",
    "sg:postcode":"S0G 5J0",
    "sg:province":"SK",
    "wof:name":"Pleckham Agencies",
    "wof:placetype":"venue"
},
  "geometry": {"coordinates":[-104.16069,49.805389],"type":"Point"}
}