{
  "type": "Feature",
  "properties": {
    "addr:full":"4886 56 St Delta BC V4K 3C4",
    "addr:housenumber":"4886",
    "addr:postcode":"v4k 3c4",
    "addr:street":"56 St",
    "iso:country":"CA",
    "sg:address":"4886 56 St",
    "sg:city":"Delta",
    "sg:classifiers":[
        {
            "category":"Home & Garden",
            "subcategory":"Garden Supply",
            "type":"Retail Goods"
        }
    ],
    "sg:phone":"+1 604 940 1444",
    "sg:postcode":"V4K 3C4",
    "sg:province":"BC",
    "sg:tags":[
        "sprinkler"
    ],
    "wof:name":"Oliver Irrigation Ltd",
    "wof:placetype":"venue"
},
  "geometry": {"coordinates":[-123.06718444800001,49.092086792],"type":"Point"}
}