{
  "type": "Feature",
  "properties": {
    "addr:full":"200 Isabella St Pembroke ON K8A 5S7",
    "addr:housenumber":"200",
    "addr:postcode":"k8a 5s7",
    "addr:street":"Isabella St",
    "iso:country":"CA",
    "sg:address":"200 Isabella St",
    "sg:city":"Pembroke",
    "sg:classifiers":[
        {
            "category":"Education",
            "subcategory":"School",
            "type":"Public Place"
        }
    ],
    "sg:phone":"+1 613 732 8054",
    "sg:postcode":"K8A 5S7",
    "sg:province":"ON",
    "wof:name":"Cathedral School",
    "wof:placetype":"venue"
},
  "geometry": {"coordinates":[-77.11623400000001,45.823246],"type":"Point"}
}