{
  "type": "Feature",
  "properties": {
    "iso:country":"CA",
    "sg:address":"596 Hwy 15",
    "sg:city":"Lombardy",
    "sg:classifiers":[
        {
            "category":"Education",
            "subcategory":"School",
            "type":"Public Place"
        }
    ],
    "sg:phone":"+1 613 283 0860",
    "sg:postcode":"K0G 1L0",
    "sg:province":"ON",
    "wof:name":"Lombardy Public School",
    "wof:placetype":"venue"
},
  "geometry": {"coordinates":[-76.0735778809,44.8356056213],"type":"Point"}
}