{
  "type": "Feature",
  "properties": {
    "addr:full":"Black Duck Siding NL A0N 2G0",
    "addr:postcode":"a0n 2g0",
    "iso:country":"CA",
    "sg:city":"Black Duck Siding",
    "sg:classifiers":[
        {
            "category":"Home & Garden",
            "subcategory":"Garden Supply",
            "type":"Retail Goods"
        }
    ],
    "sg:phone":"+1 709 646 5514",
    "sg:postcode":"A0N 2G0",
    "sg:province":"NL",
    "sg:tags":[
        "nurseryman",
        "center"
    ],
    "wof:name":"Black Duck Garden Ctr",
    "wof:placetype":"venue"
},
  "geometry": {"coordinates":[-58.383331,48.57872],"type":"Point"}
}