{
  "type": "Feature",
  "properties": {
    "iso:country":"CA",
    "sg:address":"999 Av DE Bourgogne",
    "sg:city":"Sainte-Foy",
    "sg:classifiers":[
        {
            "category":"Shopping",
            "subcategory":"Clothing, Apparel, & Fashions",
            "type":"Retail Goods"
        }
    ],
    "sg:phone":"+1 418 654 1186",
    "sg:postcode":"G1W 4S6",
    "sg:province":"QC",
    "wof:name":"Winners Apparel Ltee",
    "wof:placetype":"venue"
},
  "geometry": {"coordinates":[-71.309952,46.765598],"type":"Point"}
}