{
  "type": "Feature",
  "properties": {
    "addr:full":"22745 Dewdney Trunk Rd Maple Ridge BC V2X 3K4",
    "addr:housenumber":"22745",
    "addr:postcode":"v2x 3k4",
    "addr:street":"Dewdney Trunk Rd",
    "iso:country":"CA",
    "sg:address":"22745 Dewdney Trunk Rd",
    "sg:city":"Maple Ridge",
    "sg:classifiers":[
        {
            "category":"Shopping",
            "type":"Retail Goods"
        }
    ],
    "sg:phone":"+1 604 463 3855",
    "sg:postcode":"V2X 3K4",
    "sg:province":"BC",
    "sg:tags":[
        "pet",
        "food",
        "supply"
    ],
    "wof:name":"Bosley's Pet Food Mart",
    "wof:placetype":"venue"
},
  "geometry": {"coordinates":[-122.591621,49.220524],"type":"Point"}
}