{
  "type": "Feature",
  "properties": {
    "iso:country":"CA",
    "sg:address":"355 Boul Montpellier",
    "sg:city":"Saint-Laurent",
    "sg:classifiers":[
        {
            "category":"Building & Trades",
            "subcategory":"Plumbing",
            "type":"Services"
        }
    ],
    "sg:phone":"+1 514 747 2580",
    "sg:postcode":"H4N 2G6",
    "sg:province":"QC",
    "sg:tags":[
        "conditioning",
        "air",
        "system",
        "contractor"
    ],
    "wof:name":"Societe DE Controle Johnson",
    "wof:placetype":"venue"
},
  "geometry": {"coordinates":[-73.6629943848,45.5187759399],"type":"Point"}
}