{
  "type": "Feature",
  "properties": {
    "addr:full":"Rang 3 E Saint-Gervais QC G0R 3C0",
    "addr:postcode":"g0r 3c0",
    "addr:street":"Rang 3 E",
    "iso:country":"CA",
    "sg:address":"Rang 3 E",
    "sg:city":"Saint-Gervais",
    "sg:classifiers":[
        {
            "category":"Mining & Drilling",
            "type":"Manufacturing & Wholesale Goods"
        }
    ],
    "sg:phone":"+1 418 887 5098",
    "sg:postcode":"G0R 3C0",
    "sg:province":"QC",
    "sg:tags":[
        "quarry"
    ],
    "wof:name":"Carriere Bellechasse",
    "wof:placetype":"venue"
},
  "geometry": {"coordinates":[-70.860771,46.687126],"type":"Point"}
}