{
  "type": "Feature",
  "properties": {
    "addr:full":"72 Steeles Ave W Thornhill ON L4J 1A1",
    "addr:housenumber":"72",
    "addr:postcode":"l4j 1a1",
    "addr:street":"Steeles Ave W",
    "iso:country":"CA",
    "sg:address":"72 Steeles Ave W",
    "sg:city":"Thornhill",
    "sg:classifiers":[
        {
            "category":"Education",
            "subcategory":"School",
            "type":"Public Place"
        }
    ],
    "sg:phone":"+1 905 889 0012",
    "sg:postcode":"L4J 1A1",
    "sg:province":"ON",
    "wof:name":"Central Montessori Schools",
    "wof:placetype":"venue"
},
  "geometry": {"coordinates":[-79.4228134155,43.7976074219],"type":"Point"}
}