{
  "type": "Feature",
  "properties": {
    "addr:full":"902 Front St Nelson BC V1L 4C2",
    "addr:housenumber":"902",
    "addr:postcode":"bc v1l 4c2",
    "addr:street":"Front St",
    "iso:country":"CA",
    "sg:address":"902 Front St",
    "sg:city":"Nelson",
    "sg:classifiers":[
        {
            "category":"Shopping",
            "subcategory":"Computers & Home Electronics",
            "type":"Retail Goods"
        }
    ],
    "sg:phone":"+1 250 352 7292",
    "sg:postcode":"V1L 4C2",
    "sg:province":"BC",
    "sg:tags":[
        "equipment",
        "electronic",
        "system",
        "radio",
        "communication"
    ],
    "wof:name":"S K Electronics Ltd",
    "wof:placetype":"venue"
},
  "geometry": {"coordinates":[-117.291832,49.495827],"type":"Point"}
}