{
  "type": "Feature",
  "properties": {
    "addr:full":"22349 Selkirk Ave Maple Ridge BC V2X 2X6",
    "addr:housenumber":"22349",
    "addr:postcode":"v2x 2x6",
    "addr:street":"Selkirk Ave",
    "iso:country":"CA",
    "sg:address":"22349 Selkirk Ave",
    "sg:city":"Maple Ridge",
    "sg:classifiers":[
        {
            "category":"Health Services",
            "subcategory":"Clinic",
            "type":"Services"
        }
    ],
    "sg:phone":"+1 604 463 6600",
    "sg:postcode":"V2X 2X6",
    "sg:province":"BC",
    "sg:tags":[
        "agency",
        "welfare"
    ],
    "wof:name":"Canadian Red Cross Society",
    "wof:placetype":"venue"
},
  "geometry": {"coordinates":[-122.603111,49.217838],"type":"Point"}
}