{
  "type": "Feature",
  "properties": {
    "addr:full":"Hay River NT X0E 1G2",
    "addr:postcode":"x0e 1g2",
    "iso:country":"CA",
    "sg:city":"Hay River",
    "sg:classifiers":[
        {
            "category":"Wholesale",
            "subcategory":"Furniture",
            "type":"Manufacturing & Wholesale Goods"
        }
    ],
    "sg:phone":"+1 867 874 6784",
    "sg:postcode":"X0E 1G2",
    "sg:province":"NT",
    "wof:name":"Xerox Canada Ltd",
    "wof:placetype":"venue"
},
  "geometry": {"coordinates":[-115.787811279,60.8093643188],"type":"Point"}
}