{
  "type": "Feature",
  "properties": {
    "iso:country":"CA",
    "sg:address":"400 Rue Beaubien E",
    "sg:city":"Montreal",
    "sg:classifiers":[
        {
            "category":"Personal",
            "type":"Services"
        }
    ],
    "sg:phone":"+1 514 271 7515",
    "sg:postcode":"H2S 1S3",
    "sg:province":"QC",
    "sg:tags":[
        "therapist",
        "massage"
    ],
    "wof:name":"Bains Flottants Ovarium",
    "wof:placetype":"venue"
},
  "geometry": {"coordinates":[-73.6048583984,45.5340461731],"type":"Point"}
}