{
  "type": "Feature",
  "properties": {
    "addr:full":"4308 Patterdale Dr North Vancouver BC V7R 4L5",
    "addr:postcode":"4308;v7r 4l5",
    "addr:street":"Patterdale Dr",
    "iso:country":"CA",
    "sg:address":"4308 Patterdale Dr",
    "sg:city":"North Vancouver",
    "sg:classifiers":[
        {
            "category":"Building & Trades",
            "subcategory":"Construction",
            "type":"Services"
        }
    ],
    "sg:phone":"+1 604 986 9921",
    "sg:postcode":"V7R 4L5",
    "sg:province":"BC",
    "sg:tags":[
        "general",
        "contractor"
    ],
    "wof:name":"Kenwood Construction Corp",
    "wof:placetype":"venue"
},
  "geometry": {"coordinates":[-123.110489,49.349541],"type":"Point"}
}