{
  "type": "Feature",
  "properties": {
    "addr:full":"2536 Rue Everett Montreal QC H2A 1P9",
    "addr:housenumber":"2536",
    "addr:postcode":"h2a 1p9",
    "addr:street":"Rue Everett",
    "iso:country":"CA",
    "sg:address":"2536 Rue Everett",
    "sg:city":"Montreal",
    "sg:classifiers":[
        {
            "category":"Organizations",
            "subcategory":"Religious Organization",
            "type":"Services"
        }
    ],
    "sg:phone":"+1 514 376 0837",
    "sg:postcode":"H2A 1P9",
    "sg:province":"QC",
    "sg:tags":[
        "church"
    ],
    "wof:name":"Eglise Baptista Sinai",
    "wof:placetype":"venue"
},
  "geometry": {"coordinates":[-73.60438499999999,45.554661],"type":"Point"}
}