{
  "type": "Feature",
  "properties": {
    "addr:full":"1005 Richmond St Chatham ON N7M 5J5",
    "addr:housenumber":"1005",
    "addr:postcode":"n7m 5j5",
    "addr:street":"Richmond St",
    "iso:country":"CA",
    "sg:address":"1005 Richmond St",
    "sg:city":"Chatham",
    "sg:classifiers":[
        {
            "category":"Building & Trades",
            "subcategory":"Construction",
            "type":"Services"
        }
    ],
    "sg:phone":"+1 519 352 4341",
    "sg:postcode":"N7M 5J5",
    "sg:province":"ON",
    "sg:tags":[
        "general",
        "contractor"
    ],
    "wof:name":"Manniger Bros Construction Ltd",
    "wof:placetype":"venue"
},
  "geometry": {"coordinates":[-82.2146,42.381222],"type":"Point"}
}