{
  "type": "Feature",
  "properties": {
    "addr:full":"5556 Almon St Halifax NS B3K 1T3",
    "addr:housenumber":"5556",
    "addr:postcode":"b3k 1t3",
    "addr:street":"Almon St",
    "iso:country":"CA",
    "sg:address":"5556 Almon St",
    "sg:city":"Halifax",
    "sg:classifiers":[
        {
            "category":"Retail",
            "subcategory":"Portrait Studio",
            "type":"Services"
        }
    ],
    "sg:phone":"+1 902 455 8484",
    "sg:postcode":"B3K 1T3",
    "sg:province":"NS",
    "sg:tags":[
        "photographer"
    ],
    "wof:name":"Georgakakos, George",
    "wof:placetype":"venue"
},
  "geometry": {"coordinates":[-63.5956,44.659443],"type":"Point"}
}