{
  "type": "Feature",
  "properties": {
    "addr:full":"1000 Kindred Rd Midland ON L4R 4K9",
    "addr:housenumber":"1000",
    "addr:postcode":"l4r 4k9",
    "addr:street":"Kindred Rd",
    "iso:country":"CA",
    "sg:address":"1000 Kindred Rd",
    "sg:city":"Midland",
    "sg:classifiers":[
        {
            "category":"Wholesale",
            "subcategory":"Hardware",
            "type":"Manufacturing & Wholesale Goods"
        }
    ],
    "sg:phone":"+1 705 526 5427",
    "sg:postcode":"L4R 4K9",
    "sg:province":"ON",
    "sg:tags":[
        "plumbing",
        "fixture",
        "supply"
    ],
    "wof:name":"Kindred Industries",
    "wof:placetype":"venue"
},
  "geometry": {"coordinates":[-79.85052490229999,44.7354621887],"type":"Point"}
}