{
  "type": "Feature",
  "properties": {
    "iso:country":"CA",
    "sg:address":"1919 Lionel Bertrand Suite 203",
    "sg:city":"Boisbriand",
    "sg:classifiers":[
        {
            "category":"Professional",
            "subcategory":"Management & Consulting",
            "type":"Services"
        }
    ],
    "sg:postcode":"J7H1N8",
    "sg:tags":[
        "information-security",
        "security-consulting",
        "managed-security",
        "security-monitoring"
    ],
    "sg:website":"http://www.abovesecurity.com",
    "wof:name":"Above Security",
    "wof:placetype":"venue"
},
  "geometry": {"coordinates":[-73.8553,45.6099327],"type":"Point"}
}