{
  "type": "Feature",
  "properties": {
    "iso:country":"CA",
    "sg:address":"978 University Ave W",
    "sg:city":"Windsor",
    "sg:classifiers":[
        {
            "category":"Restaurant",
            "type":"Food & Drink"
        }
    ],
    "sg:phone":"+1 519 252 1449",
    "sg:postcode":"N9A 5S2",
    "sg:province":"ON",
    "wof:name":"Shin Shin Chinese Restaurant",
    "wof:placetype":"venue"
},
  "geometry": {"coordinates":[-83.050667,42.314514],"type":"Point"}
}