{
  "type": "Feature",
  "properties": {
    "addr:full":"513 Main St Three Hills AB T0M 2A0",
    "addr:housenumber":"513",
    "addr:postcode":"t0m 2a0",
    "addr:street":"Main St",
    "iso:country":"CA",
    "sg:address":"513 Main St",
    "sg:city":"Three Hills",
    "sg:classifiers":[
        {
            "category":"Health Services",
            "subcategory":"Medical Lab",
            "type":"Services"
        }
    ],
    "sg:phone":"+1 403 443 7745",
    "sg:postcode":"T0M 2A0",
    "sg:province":"AB",
    "wof:name":"Three Hills Denture Clinic",
    "wof:placetype":"venue"
},
  "geometry": {"coordinates":[-113.267608643,51.7038421631],"type":"Point"}
}