{
  "type": "Feature",
  "properties": {
    "addr:full":"36 Sykes St N Meaford ON N4L 1A5",
    "addr:housenumber":"36",
    "addr:postcode":"n4l 1a5",
    "addr:street":"Sykes St N",
    "iso:country":"CA",
    "sg:address":"36 Sykes St N",
    "sg:city":"Meaford",
    "sg:classifiers":[
        {
            "category":"Insurance",
            "subcategory":"Insurance Agent",
            "type":"Services"
        }
    ],
    "sg:phone":"+1 519 538 2102",
    "sg:postcode":"N4L 1A5",
    "sg:province":"ON",
    "wof:name":"Clarica Life Insurance CO",
    "wof:placetype":"venue"
},
  "geometry": {"coordinates":[-80.59204099999999,44.607178],"type":"Point"}
}