{
  "type": "Feature",
  "properties": {
    "addr:full":"198 Raglan St S Renfrew ON K7V 1R1",
    "addr:housenumber":"198",
    "addr:postcode":"k7v 1r1",
    "addr:street":"Raglan St S",
    "iso:country":"CA",
    "sg:address":"198 Raglan St S",
    "sg:city":"Renfrew",
    "sg:classifiers":[
        {
            "category":"Home & Garden",
            "subcategory":"Building Materials",
            "type":"Retail Goods"
        }
    ],
    "sg:phone":"+1 613 433 3367",
    "sg:postcode":"K7V 1R1",
    "sg:province":"ON",
    "sg:tags":[
        "glass",
        "leaded"
    ],
    "wof:name":"Stained Glass Design Studio",
    "wof:placetype":"venue"
},
  "geometry": {"coordinates":[-76.684212,45.471821],"type":"Point"}
}