{
  "type": "Feature",
  "properties": {
    "iso:country":"CA",
    "sg:address":"10800 Ch DE LA Cote-DE-Liesse",
    "sg:city":"Lachine",
    "sg:classifiers":[
        {
            "category":"Restaurant",
            "type":"Food & Drink"
        }
    ],
    "sg:phone":"+1 514 631 4962",
    "sg:postcode":"H8T 1A6",
    "sg:province":"QC",
    "wof:name":"Restaurants D Lafleur Inc",
    "wof:placetype":"venue"
},
  "geometry": {"coordinates":[-73.72277832029999,45.4620018005],"type":"Point"}
}