{
  "type": "Feature",
  "properties": {
    "iso:country":"CA",
    "sg:address":"186 Algoma St S",
    "sg:city":"Thunder Bay",
    "sg:classifiers":[
        {
            "category":"Shopping",
            "subcategory":"Books",
            "type":"Retail Goods"
        }
    ],
    "sg:phone":"+1 807 345 5700",
    "sg:postcode":"P7B 3B9",
    "sg:province":"ON",
    "sg:tags":[
        "collectible",
        "comic"
    ],
    "wof:name":"Comix Plus/Music Exchange",
    "wof:placetype":"venue"
},
  "geometry": {"coordinates":[-89.2304,48.431107],"type":"Point"}
}