{
  "type": "Feature",
  "properties": {
    "addr:full":"1330 Boul Industriel Baie-Comeau QC G5C 1B9",
    "addr:housenumber":"1330",
    "addr:postcode":"g5c 1b9",
    "addr:street":"Boul Industriel",
    "iso:country":"CA",
    "sg:address":"1330 Boul Industriel",
    "sg:city":"Baie-Comeau",
    "sg:classifiers":[
        {
            "category":"Freight",
            "type":"Transportation"
        }
    ],
    "sg:phone":"+1 418 589 2078",
    "sg:postcode":"G5C 1B9",
    "sg:province":"QC",
    "sg:tags":[
        "trucking"
    ],
    "wof:name":"Transport Tst Overland Exprs",
    "wof:placetype":"venue"
},
  "geometry": {"coordinates":[-68.28363,49.196487],"type":"Point"}
}