{
  "type": "Feature",
  "properties": {
    "addr:full":"1000 Rue DE LA Gauchetiere O # 650 Montreal QC H3B 4W5",
    "addr:housenumber":"1000",
    "addr:postcode":"h3b 4w5",
    "addr:street":"Rue De La Gauchetiere O # 650",
    "iso:country":"CA",
    "sg:address":"1000 Rue DE LA Gauchetiere O # 650",
    "sg:city":"Montreal",
    "sg:classifiers":[
        {
            "category":"Banks & Credit Unions",
            "subcategory":"Investment Brokerage",
            "type":"Services"
        }
    ],
    "sg:phone":"+1 514 878 9848",
    "sg:postcode":"H3B 4W5",
    "sg:province":"QC",
    "sg:tags":[
        "consultant",
        "planning",
        "financial"
    ],
    "wof:name":"Fiducie Prive MD Private Trst",
    "wof:placetype":"venue"
},
  "geometry": {"coordinates":[-73.553764,45.515373],"type":"Point"}
}