{
  "type": "Feature",
  "properties": {
    "iso:country":"CA",
    "sg:address":"16850 Boul Lacroix",
    "sg:city":"Saint-Georges",
    "sg:classifiers":[
        {
            "category":"Restaurant",
            "type":"Food & Drink"
        }
    ],
    "sg:phone":"+1 418 228 8661",
    "sg:postcode":"G5Y 8G9",
    "sg:province":"QC",
    "sg:tags":[
        "grocer"
    ],
    "wof:name":"Marche Laval Veilleux & Fils",
    "wof:placetype":"venue"
},
  "geometry": {"coordinates":[-70.6482620239,46.0972213745],"type":"Point"}
}