{
  "type": "Feature",
  "properties": {
    "addr:full":"74 Tycos Dr North York ON M6B 1V9",
    "addr:housenumber":"74",
    "addr:postcode":"m6b 1v9",
    "addr:street":"Tycos Dr",
    "iso:country":"CA",
    "sg:address":"74 Tycos Dr",
    "sg:city":"North York",
    "sg:classifiers":[
        {
            "category":"Organizations",
            "subcategory":"Professional Association",
            "type":"Services"
        }
    ],
    "sg:phone":"+1 416 785 0515",
    "sg:postcode":"M6B 1V9",
    "sg:province":"ON",
    "sg:tags":[
        "consultant",
        "educational"
    ],
    "wof:name":"Jewish Vocational Svc of Metro",
    "wof:placetype":"venue"
},
  "geometry": {"coordinates":[-79.4571380615,43.70495224],"type":"Point"}
}