{
  "type": "Feature",
  "properties": {
    "addr:full":"3465 Kingston Rd Scarborough ON M1M 1R4",
    "addr:housenumber":"3465",
    "addr:postcode":"m1m 1r4",
    "addr:street":"Kingston Rd",
    "iso:country":"CA",
    "sg:address":"3465 Kingston Rd",
    "sg:city":"Scarborough",
    "sg:classifiers":[
        {
            "category":"Food & Beverages",
            "subcategory":"Bakery",
            "type":"Retail Goods"
        }
    ],
    "sg:phone":"+1 416 266 0786",
    "sg:postcode":"M1M 1R4",
    "sg:province":"ON",
    "sg:tags":[
        "tea",
        "coffee",
        "doughnut"
    ],
    "wof:name":"Tim Hortons",
    "wof:placetype":"venue"
},
  "geometry": {"coordinates":[-79.2180404663,43.7376289368],"type":"Point"}
}