{
  "type": "Feature",
  "properties": {
    "addr:full":"140 Queensway E Simcoe ON N3Y 4Y7",
    "addr:housenumber":"140",
    "addr:postcode":"n3y 4y7",
    "addr:street":"Queensway E",
    "iso:country":"CA",
    "sg:address":"140 Queensway E",
    "sg:city":"Simcoe",
    "sg:classifiers":[
        {
            "category":"Banks & Credit Unions",
            "subcategory":"Bank",
            "type":"Services"
        }
    ],
    "sg:phone":"+1 519 428 0800",
    "sg:postcode":"N3Y 4Y7",
    "sg:province":"ON",
    "wof:name":"First Ontario Credit Union",
    "wof:placetype":"venue"
},
  "geometry": {"coordinates":[-80.29170999999999,42.848316],"type":"Point"}
}