{
  "type": "Feature",
  "properties": {
    "addr:full":"1331 3rd Ave E Owen Sound ON N4K 2L8",
    "addr:housenumber":"1331",
    "addr:postcode":"n4k 2l8",
    "addr:street":"3Rd Ave E",
    "iso:country":"CA",
    "sg:address":"1331 3rd Ave E",
    "sg:city":"Owen Sound",
    "sg:classifiers":[
        {
            "category":"Retail",
            "subcategory":"Laundry & Dry Cleaning",
            "type":"Services"
        }
    ],
    "sg:phone":"+1 519 371 4527",
    "sg:postcode":"N4K 2L8",
    "sg:province":"ON",
    "sg:tags":[
        "fire",
        "cleaners",
        "rug",
        "damage",
        "restoration",
        "carpet"
    ],
    "wof:name":"Horizon Carpet & Uphlstry Care",
    "wof:placetype":"venue"
},
  "geometry": {"coordinates":[-80.93744700000001,44.573738],"type":"Point"}
}