{
  "type": "Feature",
  "properties": {
    "addr:full":"394 Rue Laurier Laval QC H7N 2P2",
    "addr:housenumber":"394",
    "addr:postcode":"h7n 2p2",
    "addr:street":"Rue Laurier",
    "iso:country":"CA",
    "sg:address":"394 Rue Laurier",
    "sg:city":"Laval",
    "sg:classifiers":[
        {
            "category":"Health Services",
            "subcategory":"Doctor",
            "type":"Services"
        }
    ],
    "sg:phone":"+1 450 686 2808",
    "sg:postcode":"H7N 2P2",
    "sg:province":"QC",
    "sg:tags":[
        "clinic"
    ],
    "wof:name":"Clinique Chiro Laval-DE-Rpds",
    "wof:placetype":"venue"
},
  "geometry": {"coordinates":[-73.71032700000001,45.547585],"type":"Point"}
}