{
  "type": "Feature",
  "properties": {
    "iso:country":"CA",
    "sg:address":"394 Rue Laurier",
    "sg:city":"Laval",
    "sg:classifiers":[
        {
            "category":"Health Services",
            "subcategory":"Doctor",
            "type":"Services"
        }
    ],
    "sg:phone":"+1 450 686 2808",
    "sg:postcode":"H7N 2P2",
    "sg:province":"QC",
    "sg:tags":[
        "clinic"
    ],
    "wof:name":"Clinique Chiro Laval-DE-Rpds",
    "wof:placetype":"venue"
},
  "geometry": {"coordinates":[-73.710327,45.547585],"type":"Point"}
}