{
  "type": "Feature",
  "properties": {
    "iso:country":"CA",
    "sg:address":"661 Bloor St W",
    "sg:city":"Toronto",
    "sg:classifiers":[
        {
            "category":"Restaurant",
            "type":"Food & Drink"
        }
    ],
    "sg:phone":"+1 416 516 8395",
    "sg:postcode":"M6G 1L1",
    "sg:province":"ON",
    "wof:name":"Korye Snack",
    "wof:placetype":"venue"
},
  "geometry": {"coordinates":[-79.41553497309999,43.6640319824],"type":"Point"}
}