{
  "type": "Feature",
  "properties": {
    "addr:full":"403 Silverwood Rd Saskatoon SK S7K 6G1",
    "addr:housenumber":"403",
    "addr:postcode":"s7k 6g1",
    "addr:street":"Silverwood Rd",
    "iso:country":"CA",
    "sg:address":"403 Silverwood Rd",
    "sg:city":"Saskatoon",
    "sg:classifiers":[
        {
            "category":"Education",
            "subcategory":"School",
            "type":"Public Place"
        }
    ],
    "sg:phone":"+1 306 683 7450",
    "sg:postcode":"S7K 6G1",
    "sg:province":"SK",
    "wof:name":"Silverwood Heights School",
    "wof:placetype":"venue"
},
  "geometry": {"coordinates":[-106.61964399999999,52.181683],"type":"Point"}
}