{
  "type": "Feature",
  "properties": {
    "addr:full":"183 Rue Pie-Xi Thetford Mines QC G6G 3N3",
    "addr:housenumber":"183",
    "addr:postcode":"g6g 3n3",
    "addr:street":"Rue Pie-Xi",
    "iso:country":"CA",
    "sg:address":"183 Rue Pie-Xi",
    "sg:city":"Thetford Mines",
    "sg:classifiers":[
        {
            "category":"Professional",
            "subcategory":"Accounting & Tax Preparation",
            "type":"Services"
        }
    ],
    "sg:phone":"+1 418 338 2578",
    "sg:postcode":"G6G 3N3",
    "sg:province":"QC",
    "sg:tags":[
        "bookkeeping",
        "return",
        "system",
        "filing"
    ],
    "wof:name":"Ordi-Gesco Inc",
    "wof:placetype":"venue"
},
  "geometry": {"coordinates":[-71.30600738530001,46.0890045166],"type":"Point"}
}