{
  "type": "Feature",
  "properties": {
    "addr:full":"386 Smith St Hinton AB T7V 2A1",
    "addr:housenumber":"386",
    "addr:postcode":"t7v 2a1",
    "addr:street":"Smith St",
    "iso:country":"CA",
    "sg:address":"386 Smith St",
    "sg:city":"Hinton",
    "sg:classifiers":[
        {
            "category":"Travel",
            "subcategory":"Hotels & Motels",
            "type":"Entertainment"
        }
    ],
    "sg:phone":"+1 780 865 5099",
    "sg:postcode":"T7V 2A1",
    "sg:province":"AB",
    "wof:name":"Best Canadian Motor Inn Hinton",
    "wof:placetype":"venue"
},
  "geometry": {"coordinates":[-117.558266,53.405605],"type":"Point"}
}