{
  "type": "Feature",
  "properties": {
    "iso:country":"CA",
    "sg:address":"1830 Glasgow St",
    "sg:city":"Kitchener",
    "sg:classifiers":[
        {
            "category":"Building & Trades",
            "subcategory":"Construction",
            "type":"Services"
        }
    ],
    "sg:phone":"+1 519 743 8338",
    "sg:postcode":"N2G 3W7",
    "sg:province":"ON",
    "sg:tags":[
        "excavating",
        "paving",
        "contractor"
    ],
    "wof:name":"Quality Paving Ltd",
    "wof:placetype":"venue"
},
  "geometry": {"coordinates":[-80.559822,43.423843],"type":"Point"}
}