{
  "type": "Feature",
  "properties": {
    "addr:full":"642 Dinsdale St Bridgenorth ON K0L 1H0",
    "addr:housenumber":"642",
    "addr:postcode":"k0l 1h0",
    "addr:street":"Dinsdale St",
    "iso:country":"CA",
    "sg:address":"642 Dinsdale St",
    "sg:city":"Bridgenorth",
    "sg:classifiers":[
        {
            "category":"Health Services",
            "subcategory":"Health Practitioner",
            "type":"Services"
        }
    ],
    "sg:phone":"+1 705 292 1208",
    "sg:postcode":"K0L 1H0",
    "sg:province":"ON",
    "sg:tags":[
        "psychologist"
    ],
    "wof:name":"Burger, Michael PhD",
    "wof:placetype":"venue"
},
  "geometry": {"coordinates":[-78.392906189,44.3678131104],"type":"Point"}
}