{
  "type": "Feature",
  "properties": {
    "addr:full":"818 Automall Dr North Vancouver BC V7P 3R8",
    "addr:housenumber":"818",
    "addr:postcode":"v7p 3r8",
    "addr:street":"Automall Dr",
    "iso:country":"CA",
    "sg:address":"818 Automall Dr",
    "sg:city":"North Vancouver",
    "sg:classifiers":[
        {
            "category":"Autos & Motor Vehicles",
            "subcategory":"Automobile Sales",
            "type":"Retail Goods"
        }
    ],
    "sg:phone":"+1 604 984 9211",
    "sg:postcode":"V7P 3R8",
    "sg:province":"BC",
    "sg:tags":[
        "car",
        "dealer"
    ],
    "wof:name":"Morrey Mazda Northshore",
    "wof:placetype":"venue"
},
  "geometry": {"coordinates":[-123.097145,49.316711],"type":"Point"}
}