{
  "type": "Feature",
  "properties": {
    "addr:full":"1740 Creek St Thornhill BC V8G 4Y1",
    "addr:housenumber":"1740",
    "addr:postcode":"v8g 4y1",
    "addr:street":"Creek St",
    "iso:country":"CA",
    "sg:address":"1740 Creek St",
    "sg:city":"Thornhill",
    "sg:classifiers":[
        {
            "category":"Wholesale",
            "subcategory":"Construction Materials",
            "type":"Manufacturing & Wholesale Goods"
        }
    ],
    "sg:phone":"+1 250 635 7081",
    "sg:postcode":"V8G 4Y1",
    "sg:province":"BC",
    "sg:tags":[
        "fence"
    ],
    "wof:name":"L A Fence",
    "wof:placetype":"venue"
},
  "geometry": {"coordinates":[-128.532623,54.498039],"type":"Point"}
}