{
  "type": "Feature",
  "properties": {
    "iso:country":"CA",
    "sg:address":"5263 Imperial St",
    "sg:city":"Burnaby",
    "sg:classifiers":[
        {
            "category":"Shopping",
            "subcategory":"Used Merchandise",
            "type":"Retail Goods"
        }
    ],
    "sg:phone":"+1 604 438 6629",
    "sg:postcode":"V5J 1E5",
    "sg:province":"BC",
    "sg:tags":[
        "antique"
    ],
    "wof:name":"Metrotown Antiques & China",
    "wof:placetype":"venue"
},
  "geometry": {"coordinates":[-122.98761,49.222061],"type":"Point"}
}