{
  "type": "Feature",
  "properties": {
    "addr:full":"7470 Mcniven Rd Campbellville ON L0P 1B0",
    "addr:housenumber":"7470",
    "addr:postcode":"l0p 1b0",
    "addr:street":"Mcniven Rd",
    "iso:country":"CA",
    "sg:address":"7470 Mcniven Rd",
    "sg:city":"Campbellville",
    "sg:classifiers":[
        {
            "category":"Organizations",
            "subcategory":"Religious Organization",
            "type":"Services"
        }
    ],
    "sg:phone":"+1 905 878 0043",
    "sg:postcode":"L0P 1B0",
    "sg:province":"ON",
    "sg:tags":[
        "church"
    ],
    "wof:name":"Serbian Orthodox Diocese",
    "wof:placetype":"venue"
},
  "geometry": {"coordinates":[-79.983047,43.48774],"type":"Point"}
}