{
  "type": "Feature",
  "properties": {
    "addr:full":"15 Woodridge Close SW #A Calgary AB T2W 5M2",
    "addr:housenumber":"15",
    "addr:postcode":"t2w 5m2",
    "addr:street":"Woodridge Close Sw # A",
    "iso:country":"CA",
    "sg:address":"15 Woodridge Close SW #A",
    "sg:city":"Calgary",
    "sg:classifiers":[
        {
            "category":"Shopping",
            "subcategory":"Bicycles & Sporting Goods",
            "type":"Retail Goods"
        }
    ],
    "sg:phone":"+1 403 238 3618",
    "sg:postcode":"T2W 5M2",
    "sg:province":"AB",
    "sg:tags":[
        "saddlery",
        "harness"
    ],
    "wof:name":"Calgary Leather & Tack",
    "wof:placetype":"venue"
},
  "geometry": {"coordinates":[-114.110764,50.935772],"type":"Point"}
}