{
  "type": "Feature",
  "properties": {
    "addr:full":"Courtenay BC V9N 8P1",
    "addr:postcode":"v9n 8p1",
    "iso:country":"CA",
    "sg:city":"Courtenay",
    "sg:classifiers":[
        {
            "category":"Shopping",
            "subcategory":"Department Store",
            "type":"Retail Goods"
        }
    ],
    "sg:phone":"+1 250 703 0424",
    "sg:postcode":"V9N 8P1",
    "sg:province":"BC",
    "sg:tags":[
        "shop"
    ],
    "wof:name":"Liquidation World Inc",
    "wof:placetype":"venue"
},
  "geometry": {"coordinates":[-124.98101800000001,49.670345],"type":"Point"}
}