{
  "type": "Feature",
  "properties": {
    "addr:full":"1750 Ch Gascon Terrebonne QC J6X 3A4",
    "addr:housenumber":"1750",
    "addr:postcode":"j6x 3a4",
    "addr:street":"Ch Gascon",
    "iso:country":"CA",
    "sg:address":"1750 Ch Gascon",
    "sg:city":"Terrebonne",
    "sg:classifiers":[
        {
            "category":"Wholesale",
            "subcategory":"Electrical",
            "type":"Manufacturing & Wholesale Goods"
        }
    ],
    "sg:phone":"+1 450 964 4499",
    "sg:postcode":"J6X 3A4",
    "sg:province":"QC",
    "sg:tags":[
        "equipment",
        "electronic",
        "electric",
        "supply"
    ],
    "wof:name":"Add-Tronique Inc",
    "wof:placetype":"venue"
},
  "geometry": {"coordinates":[-73.656128,45.717522],"type":"Point"}
}