{
  "type": "Feature",
  "properties": {
    "iso:country":"CA",
    "sg:address":"22 Boul Arthur-Sauve",
    "sg:city":"Saint-Eustache",
    "sg:classifiers":[
        {
            "category":"Food & Beverages",
            "subcategory":"Groceries & Convenience Stores",
            "type":"Retail Goods"
        }
    ],
    "sg:phone":"+1 450 472 0939",
    "sg:postcode":"J7R 2H5",
    "sg:province":"QC",
    "wof:name":"Shell Canada Ltd",
    "wof:placetype":"venue"
},
  "geometry": {"coordinates":[-73.8878479004,45.5604248047],"type":"Point"}
}