{
  "type": "Feature",
  "properties": {
    "iso:country":"CA",
    "sg:address":"546 Rue Jean-Talon O",
    "sg:city":"Montreal",
    "sg:classifiers":[
        {
            "category":"Shopping",
            "subcategory":"Clothing, Apparel, & Fashions",
            "type":"Retail Goods"
        }
    ],
    "sg:phone":"+1 514 278 2050",
    "sg:postcode":"H3N 1R5",
    "sg:province":"QC",
    "sg:tags":[
        "item",
        "boutique"
    ],
    "wof:name":"Univers Jeans 717",
    "wof:placetype":"venue"
},
  "geometry": {"coordinates":[-73.6137084961,45.5394821167],"type":"Point"}
}