{
  "type": "Feature",
  "properties": {
    "addr:full":"3700 Rue Damien-Gauthier Montreal QC H1A 5S2",
    "addr:housenumber":"3700",
    "addr:postcode":"h1a 5s2",
    "addr:street":"Rue Damien-Gauthier",
    "iso:country":"CA",
    "sg:address":"3700 Rue Damien-Gauthier",
    "sg:city":"Montreal",
    "sg:classifiers":[
        {
            "category":"Sports & Exercise",
            "subcategory":"Golf",
            "type":"Entertainment"
        }
    ],
    "sg:phone":"+1 514 642 5648",
    "sg:postcode":"H1A 5S2",
    "sg:province":"QC",
    "sg:tags":[
        "course",
        "establishment"
    ],
    "wof:name":"Golf Club DE L'Ile DE Montreal",
    "wof:placetype":"venue"
},
  "geometry": {"coordinates":[-73.5112457275,45.6856918335],"type":"Point"}
}