{
  "type": "Feature",
  "properties": {
    "iso:country":"CA",
    "sg:city":"Mackenzie",
    "sg:classifiers":[
        {
            "category":"Banks & Credit Unions",
            "subcategory":"Bank",
            "type":"Services"
        }
    ],
    "sg:phone":"+1 250 997 3223",
    "sg:postcode":"V0J 2C0",
    "sg:province":"BC",
    "wof:name":"Scotiabank",
    "wof:placetype":"venue"
},
  "geometry": {"coordinates":[-123.09426879900001,55.3385620117],"type":"Point"}
}