{
  "type": "Feature",
  "properties": {
    "addr:full":"1430 Rte 209 Franklin QC J0S 1E0",
    "addr:housenumber":"1430",
    "addr:postcode":"j0s 1e0",
    "addr:street":"Rte 209",
    "iso:country":"CA",
    "sg:address":"1430 Rte 209",
    "sg:city":"Franklin",
    "sg:classifiers":[
        {
            "category":"Retail",
            "subcategory":"Auto Repair",
            "type":"Services"
        }
    ],
    "sg:phone":"+1 450 827 2253",
    "sg:postcode":"J0S 1E0",
    "sg:province":"QC",
    "sg:tags":[
        "body",
        "automobile",
        "painting"
    ],
    "wof:name":"Garage Glen Forget",
    "wof:placetype":"venue"
},
  "geometry": {"coordinates":[-73.92532300000001,45.027653],"type":"Point"}
}