{
  "type": "Feature",
  "properties": {
    "addr:full":"3750 Boul Saint-Martin O Laval QC H7T 1B1",
    "addr:housenumber":"3750",
    "addr:postcode":"h7t 1b1",
    "addr:street":"Boul Saint-Martin O",
    "iso:country":"CA",
    "sg:address":"3750 Boul Saint-Martin O",
    "sg:city":"Laval",
    "sg:classifiers":[
        {
            "category":"Restaurant",
            "type":"Food & Drink"
        }
    ],
    "sg:phone":"+1 450 681 9248",
    "sg:postcode":"H7T 1B1",
    "sg:province":"QC",
    "wof:name":"Georges Deli Restaurant",
    "wof:placetype":"venue"
},
  "geometry": {"coordinates":[-73.75733184809999,45.5526733398],"type":"Point"}
}