{
  "type": "Feature",
  "properties": {
    "addr:full":"27 Maple St S Timmins ON P4N 1Y5",
    "addr:housenumber":"27",
    "addr:postcode":"p4n 1y5",
    "addr:street":"Maple St S",
    "iso:country":"CA",
    "sg:address":"27 Maple St S",
    "sg:city":"Timmins",
    "sg:classifiers":[
        {
            "category":"Bars & Pubs",
            "type":"Food & Drink"
        }
    ],
    "sg:phone":"+1 705 268 9470",
    "sg:postcode":"P4N 1Y5",
    "sg:province":"ON",
    "sg:tags":[
        "motel",
        "hotel"
    ],
    "wof:name":"J C's Pub",
    "wof:placetype":"venue"
},
  "geometry": {"coordinates":[-81.333534,48.475555],"type":"Point"}
}