{
  "type": "Feature",
  "properties": {
    "iso:country":"CA",
    "sg:city":"Woodbridge",
    "sg:classifiers":[
        {
            "category":"Wholesale",
            "subcategory":"Electrical",
            "type":"Manufacturing & Wholesale Goods"
        }
    ],
    "sg:phone":"+1 905 850 9600",
    "sg:postcode":"L4L 5Z8",
    "sg:province":"ON",
    "sg:tags":[
        "control",
        "equipment",
        "security",
        "locksmith",
        "supply"
    ],
    "wof:name":"Papaiz of Canada Ltd",
    "wof:placetype":"venue"
},
  "geometry": {"coordinates":[-79.5625076294,43.7851676941],"type":"Point"}
}