{
  "type": "Feature",
  "properties": {
    "iso:country":"CA",
    "sg:address":"2765 Rue King O",
    "sg:city":"Sherbrooke",
    "sg:classifiers":[
        {
            "category":"Restaurant",
            "type":"Food & Drink"
        }
    ],
    "sg:phone":"+1 819 823 3338",
    "sg:postcode":"J1L 1C1",
    "sg:province":"QC",
    "wof:name":"Bacchus",
    "wof:placetype":"venue"
},
  "geometry": {"coordinates":[-71.941132,45.398167],"type":"Point"}
}