{
  "type": "Feature",
  "properties": {
    "addr:full":"7 Arlstan Dr North York ON M3H 4V7",
    "addr:housenumber":"7",
    "addr:postcode":"m3h 4v7",
    "addr:street":"Arlstan Dr",
    "iso:country":"CA",
    "sg:address":"7 Arlstan Dr",
    "sg:city":"North York",
    "sg:classifiers":[
        {
            "category":"Real Estate",
            "subcategory":"Real Estate Agent",
            "type":"Services"
        }
    ],
    "sg:phone":"+1 416 630 2668",
    "sg:postcode":"M3H 4V7",
    "sg:province":"ON",
    "sg:tags":[
        "appraiser"
    ],
    "wof:name":"Edjiline Appraisal Svc",
    "wof:placetype":"venue"
},
  "geometry": {"coordinates":[-79.4590301514,43.7650108337],"type":"Point"}
}