{
  "type": "Feature",
  "properties": {
    "iso:country":"CA",
    "sg:city":"Windsor",
    "sg:classifiers":[
        {
            "category":"Professional",
            "subcategory":"Engineering",
            "type":"Services"
        }
    ],
    "sg:phone":"+1 519 254 7926",
    "sg:postcode":"N9A 3Y4",
    "sg:province":"ON",
    "sg:tags":[
        "engineer"
    ],
    "wof:name":"Aleo Associates Inc",
    "wof:placetype":"venue"
},
  "geometry": {"coordinates":[-83.0226364136,42.3129882812],"type":"Point"}
}