{
  "type": "Feature",
  "properties": {
    "iso:country":"CA",
    "sg:address":"1990 Boul Le Corbusier",
    "sg:city":"Laval",
    "sg:classifiers":[
        {
            "category":"Home & Garden",
            "subcategory":"Furniture",
            "type":"Retail Goods"
        }
    ],
    "sg:phone":"+1 450 686 0555",
    "sg:postcode":"H7S 2K1",
    "sg:province":"QC",
    "wof:name":"Mobilier Victoria Carozza",
    "wof:placetype":"venue"
},
  "geometry": {"coordinates":[-73.7384338379,45.56980896],"type":"Point"}
}