{
  "type": "Feature",
  "properties": {
    "addr:full":"337 Montgomery St Vanier ON K1L 7X1",
    "addr:housenumber":"337",
    "addr:postcode":"k1l 7x1",
    "addr:street":"Montgomery St",
    "iso:country":"CA",
    "sg:address":"337 Montgomery St",
    "sg:city":"Vanier",
    "sg:classifiers":[
        {
            "category":"Restaurant",
            "type":"Food & Drink"
        }
    ],
    "sg:phone":"+1 613 746 5147",
    "sg:postcode":"K1L 7X1",
    "sg:province":"ON",
    "wof:name":"Chez Taffy",
    "wof:placetype":"venue"
},
  "geometry": {"coordinates":[-75.6663284302,45.4319534302],"type":"Point"}
}