{
  "type": "Feature",
  "properties": {
    "iso:country":"CA",
    "sg:address":"106 Stevenson Rd S",
    "sg:city":"Oshawa",
    "sg:classifiers":[
        {
            "category":"Professional",
            "subcategory":"Lawyer & Legal Services",
            "type":"Services"
        }
    ],
    "sg:phone":"+1 905 433 1991",
    "sg:postcode":"L1J 5M1",
    "sg:province":"ON",
    "sg:tags":[
        "attorney"
    ],
    "wof:name":"Neubauer, Josef",
    "wof:placetype":"venue"
},
  "geometry": {"coordinates":[-78.882294,43.890331],"type":"Point"}
}