{
  "type": "Feature",
  "properties": {
    "iso:country":"CA",
    "sg:address":"1010 LA Petite Caroline",
    "sg:city":"Rougemont",
    "sg:classifiers":[
        {
            "category":"Wholesale",
            "subcategory":"Fruits & Vegetables",
            "type":"Manufacturing & Wholesale Goods"
        }
    ],
    "sg:phone":"+1 450 469 1723",
    "sg:postcode":"J0L 1M0",
    "sg:province":"QC",
    "sg:tags":[
        "shipper"
    ],
    "wof:name":"Serres Hang",
    "wof:placetype":"venue"
},
  "geometry": {"coordinates":[-73.0488433838,45.4473495483],"type":"Point"}
}