{
  "type": "Feature",
  "properties": {
    "addr:full":"65 Front St W Toronto ON M5J 1E6",
    "addr:housenumber":"65",
    "addr:postcode":"m5j 1e6",
    "addr:street":"Front St W",
    "iso:country":"CA",
    "sg:address":"65 Front St W",
    "sg:city":"Toronto",
    "sg:classifiers":[
        {
            "category":"Food & Beverages",
            "subcategory":"Candy",
            "type":"Retail Goods"
        }
    ],
    "sg:phone":"+1 416 955 9953",
    "sg:postcode":"M5J 1E6",
    "sg:province":"ON",
    "sg:tags":[
        "confectionery"
    ],
    "wof:name":"Sweet Factory",
    "wof:placetype":"venue"
},
  "geometry": {"coordinates":[-79.3801498413,43.6455307007],"type":"Point"}
}