{
  "type": "Feature",
  "properties": {
    "iso:country":"CA",
    "sg:address":"3714 Broomhill Cres",
    "sg:city":"Mississauga",
    "sg:classifiers":[
        {
            "category":"Building & Trades",
            "subcategory":"Landscaping Services",
            "type":"Services"
        }
    ],
    "sg:phone":"+1 905 949 5511",
    "sg:postcode":"L4Y 3N6",
    "sg:province":"ON",
    "sg:tags":[
        "landscape",
        "contractor"
    ],
    "wof:name":"Tree Fellers Ltd",
    "wof:placetype":"venue"
},
  "geometry": {"coordinates":[-79.615456,43.609215],"type":"Point"}
}