{
  "type": "Feature",
  "properties": {
    "addr:full":"3714 Broomhill Cres Mississauga ON L4Y 3N6",
    "addr:housenumber":"3714",
    "addr:postcode":"l4y 3n6",
    "addr:street":"Broomhill Cres",
    "iso:country":"CA",
    "sg:address":"3714 Broomhill Cres",
    "sg:city":"Mississauga",
    "sg:classifiers":[
        {
            "category":"Building & Trades",
            "subcategory":"Landscaping Services",
            "type":"Services"
        }
    ],
    "sg:phone":"+1 905 949 5511",
    "sg:postcode":"L4Y 3N6",
    "sg:province":"ON",
    "sg:tags":[
        "landscape",
        "contractor"
    ],
    "wof:name":"Tree Fellers Ltd",
    "wof:placetype":"venue"
},
  "geometry": {"coordinates":[-79.61545599999999,43.609215],"type":"Point"}
}