{
  "type": "Feature",
  "properties": {
    "iso:country":"CA",
    "sg:city":"Sidney",
    "sg:classifiers":[
        {
            "category":"Building & Trades",
            "subcategory":"Construction",
            "type":"Services"
        }
    ],
    "sg:phone":"+1 204 466 2778",
    "sg:postcode":"R0H 1L0",
    "sg:province":"MB",
    "sg:tags":[
        "painter"
    ],
    "wof:name":"Bradley Painting & Decorating",
    "wof:placetype":"venue"
},
  "geometry": {"coordinates":[-99.0853271484,49.8994560242],"type":"Point"}
}