{
  "type": "Feature",
  "properties": {
    "addr:full":"5199 Rue Sherbrooke E Montreal QC H1V 1A1",
    "addr:housenumber":"5199",
    "addr:postcode":"h1v 1a1",
    "addr:street":"Rue Sherbrooke E",
    "iso:country":"CA",
    "sg:address":"5199 Rue Sherbrooke E",
    "sg:city":"Montreal",
    "sg:classifiers":[
        {
            "category":"Government",
            "subcategory":"Office",
            "type":"Public Place"
        }
    ],
    "sg:phone":"+1 514 873 3636",
    "sg:postcode":"H1V 1A1",
    "sg:province":"QC",
    "wof:name":"Quebec Faunce & Parcs Quebec",
    "wof:placetype":"venue"
},
  "geometry": {"coordinates":[-73.552773,45.568336],"type":"Point"}
}