{
  "type": "Feature",
  "properties": {
    "addr:full":"963 St Laurent Blvd Ottawa ON K1K 3B1",
    "addr:housenumber":"963",
    "addr:postcode":"k1k 3b1",
    "addr:street":"St Laurent Blvd",
    "iso:country":"CA",
    "sg:address":"963 St Laurent Blvd",
    "sg:city":"Ottawa",
    "sg:classifiers":[
        {
            "category":"Retail",
            "subcategory":"Auto Repair",
            "type":"Services"
        }
    ],
    "sg:phone":"+1 613 745 0029",
    "sg:postcode":"K1K 3B1",
    "sg:province":"ON",
    "sg:tags":[
        "repairing",
        "automobile"
    ],
    "wof:name":"Speedy Auto Svc",
    "wof:placetype":"venue"
},
  "geometry": {"coordinates":[-75.64020499999999,45.429813],"type":"Point"}
}