{
  "type": "Feature",
  "properties": {
    "addr:full":"1454 Av Saint-Luc Plessisville QC G6L 2P4",
    "addr:housenumber":"1454",
    "addr:postcode":"g6l 2p4",
    "addr:street":"Av Saint-Luc",
    "iso:country":"CA",
    "sg:address":"1454 Av Saint-Luc",
    "sg:city":"Plessisville",
    "sg:classifiers":[
        {
            "category":"Retail",
            "subcategory":"Repair Shop",
            "type":"Services"
        }
    ],
    "sg:phone":"+1 819 362 6288",
    "sg:postcode":"G6L 2P4",
    "sg:province":"QC",
    "sg:tags":[
        "machine",
        "welding"
    ],
    "wof:name":"Machinerie Gilles Godbout Inc",
    "wof:placetype":"venue"
},
  "geometry": {"coordinates":[-71.7692184448,46.2188301086],"type":"Point"}
}