{
  "type": "Feature",
  "properties": {
    "addr:full":"326 St Mary's Rd Winnipeg MB R2H 1J9",
    "addr:housenumber":"326",
    "addr:postcode":"r2h 1j9",
    "addr:street":"St Mary'S Rd",
    "iso:country":"CA",
    "sg:address":"326 St Mary's Rd",
    "sg:city":"Winnipeg",
    "sg:classifiers":[
        {
            "category":"Shopping",
            "subcategory":"Bicycles & Sporting Goods",
            "type":"Retail Goods"
        }
    ],
    "sg:phone":"+1 204 237 8909",
    "sg:postcode":"R2H 1J9",
    "sg:province":"MB",
    "wof:name":"Olympia Cycle & Ski",
    "wof:placetype":"venue"
},
  "geometry": {"coordinates":[-97.142448,49.890369],"type":"Point"}
}