{
  "type": "Feature",
  "properties": {
    "addr:full":"10925 139 St NW Edmonton AB T5M 1P8",
    "addr:housenumber":"10925",
    "addr:postcode":"t5m 1p8",
    "addr:street":"139 St Nw",
    "iso:country":"CA",
    "sg:address":"10925 139 St NW",
    "sg:city":"Edmonton",
    "sg:classifiers":[
        {
            "category":"Education",
            "subcategory":"School",
            "type":"Public Place"
        }
    ],
    "sg:phone":"+1 780 455 2008",
    "sg:postcode":"T5M 1P8",
    "sg:province":"AB",
    "wof:name":"Coronation Elementary School",
    "wof:placetype":"venue"
},
  "geometry": {"coordinates":[-113.561234,53.555084],"type":"Point"}
}