{
  "type": "Feature",
  "properties": {
    "addr:full":"790 Regent Dr Oshawa ON L1G 1H9",
    "addr:housenumber":"790",
    "addr:postcode":"l1g 1h9",
    "addr:street":"Regent Dr",
    "iso:country":"CA",
    "sg:address":"790 Regent Dr",
    "sg:city":"Oshawa",
    "sg:classifiers":[
        {
            "category":"Professional",
            "subcategory":"Computer Services",
            "type":"Services"
        }
    ],
    "sg:phone":"+1 905 721 2222",
    "sg:postcode":"L1G 1H9",
    "sg:province":"ON",
    "sg:tags":[
        "consultant"
    ],
    "wof:name":"Consulting Principles Inc",
    "wof:placetype":"venue"
},
  "geometry": {"coordinates":[-78.83620500000001,43.907085],"type":"Point"}
}