{
  "type": "Feature",
  "properties": {
    "addr:full":"810 Av Ellingham Pointe-Claire QC H9R 3S4",
    "addr:housenumber":"810",
    "addr:postcode":"h9r 3s4",
    "addr:street":"Av Ellingham",
    "iso:country":"CA",
    "sg:address":"810 Av Ellingham",
    "sg:city":"Pointe-Claire",
    "sg:classifiers":[
        {
            "category":"Manufacturing",
            "subcategory":"Tools & Machinery",
            "type":"Manufacturing & Wholesale Goods"
        }
    ],
    "sg:phone":"+1 514 694 4440",
    "sg:postcode":"H9R 3S4",
    "sg:province":"QC",
    "sg:tags":[
        "equipment",
        "screening",
        "sifting"
    ],
    "wof:name":"Separator Engineering Ltd",
    "wof:placetype":"venue"
},
  "geometry": {"coordinates":[-73.820122,45.468132],"type":"Point"}
}