{
  "type": "Feature",
  "properties": {
    "iso:country":"CA",
    "sg:address":"260 Place Du Tangara",
    "sg:city":"Laval",
    "sg:classifiers":[
        {
            "category":"Professional",
            "subcategory":"Accounting & Tax Preparation",
            "type":"Services"
        }
    ],
    "sg:phone":"+1 450 665 5157",
    "sg:postcode":"H7A 3Y2",
    "sg:province":"QC",
    "sg:tags":[
        "accountant"
    ],
    "wof:name":"Ouellette, Jean CA",
    "wof:placetype":"venue"
},
  "geometry": {"coordinates":[-73.610451,45.649464],"type":"Point"}
}