{
  "type": "Feature",
  "properties": {
    "addr:full":"13905 108 Ave Surrey BC V3T 2L1",
    "addr:housenumber":"13905",
    "addr:postcode":"v3t 2l1",
    "addr:street":"108 Ave",
    "iso:country":"CA",
    "sg:address":"13905 108 Ave",
    "sg:city":"Surrey",
    "sg:classifiers":[
        {
            "category":"Organizations",
            "subcategory":"Religious Organization",
            "type":"Services"
        }
    ],
    "sg:phone":"+1 604 588 8020",
    "sg:postcode":"V3T 2L1",
    "sg:province":"BC",
    "sg:tags":[
        "church"
    ],
    "wof:name":"Coptic Orthodox Egyptian",
    "wof:placetype":"venue"
},
  "geometry": {"coordinates":[-122.834121704,49.198841095],"type":"Point"}
}