{
  "type": "Feature",
  "properties": {
    "addr:full":"100 King St W Stoney Creek ON L8G 1J1",
    "addr:housenumber":"100",
    "addr:postcode":"l8g 1j1",
    "addr:street":"King St W",
    "iso:country":"CA",
    "sg:address":"100 King St W",
    "sg:city":"Stoney Creek",
    "sg:classifiers":[
        {
            "category":"Restaurant",
            "type":"Food & Drink"
        }
    ],
    "sg:phone":"+1 905 664 7124",
    "sg:postcode":"L8G 1J1",
    "sg:province":"ON",
    "sg:tags":[
        "cafe"
    ],
    "wof:name":"Scout Cafe Restaurant",
    "wof:placetype":"venue"
},
  "geometry": {"coordinates":[-79.76709700000001,43.219002],"type":"Point"}
}