{
  "type": "Feature",
  "properties": {
    "addr:full":"413 Mud St E Stoney Creek ON L8J 3B5",
    "addr:housenumber":"413",
    "addr:postcode":"l8j 3b5",
    "addr:street":"Mud St E",
    "iso:country":"CA",
    "sg:address":"413 Mud St E",
    "sg:city":"Stoney Creek",
    "sg:classifiers":[
        {
            "category":"Organizations",
            "subcategory":"Religious Organization",
            "type":"Services"
        }
    ],
    "sg:phone":"+1 905 662 2677",
    "sg:postcode":"L8J 3B5",
    "sg:province":"ON",
    "sg:tags":[
        "church"
    ],
    "wof:name":"Tapleytown United Church",
    "wof:placetype":"venue"
},
  "geometry": {"coordinates":[-79.73217,43.18121],"type":"Point"}
}