{
  "type": "Feature",
  "properties": {
    "addr:full":"8673 Av Chaumont Anjou QC H1K 1N4",
    "addr:housenumber":"8673",
    "addr:postcode":"h1k 1n4",
    "addr:street":"Av Chaumont",
    "iso:country":"CA",
    "sg:address":"8673 Av Chaumont",
    "sg:city":"Anjou",
    "sg:classifiers":[
        {
            "category":"Shopping",
            "subcategory":"Shoes",
            "type":"Retail Goods"
        }
    ],
    "sg:phone":"+1 514 352 1160",
    "sg:postcode":"H1K 1N4",
    "sg:province":"QC",
    "wof:name":"Chaussures Pitt Ltee",
    "wof:placetype":"venue"
},
  "geometry": {"coordinates":[-73.54743999999999,45.610344],"type":"Point"}
}