{
  "type": "Feature",
  "properties": {
    "addr:full":"3 Rue Beausejour Pabos Mills QC G0C 2J0",
    "addr:housenumber":"3",
    "addr:postcode":"g0c 2j0",
    "addr:street":"Rue Beausejour;Mills",
    "iso:country":"CA",
    "sg:address":"3 Rue Beausejour",
    "sg:city":"Pabos Mills",
    "sg:classifiers":[
        {
            "category":"Travel",
            "subcategory":"Hotels & Motels",
            "type":"Entertainment"
        }
    ],
    "sg:phone":"+1 418 689 4079",
    "sg:postcode":"G0C 2J0",
    "sg:province":"QC",
    "sg:tags":[
        "breakfast",
        "accommodation",
        "bed"
    ],
    "wof:name":"Gite LA Baie Du Grand Pabos",
    "wof:placetype":"venue"
},
  "geometry": {"coordinates":[-64.7136459351,48.3406448364],"type":"Point"}
}