{
  "type": "Feature",
  "properties": {
    "addr:full":"30 Wellesbourne Cres North York ON M2H 1Y7",
    "addr:housenumber":"30",
    "addr:postcode":"m2h 1y7",
    "addr:street":"Wellesbourne Cres",
    "iso:country":"CA",
    "sg:address":"30 Wellesbourne Cres",
    "sg:city":"North York",
    "sg:classifiers":[
        {
            "category":"Professional",
            "subcategory":"Accounting & Tax Preparation",
            "type":"Services"
        }
    ],
    "sg:phone":"+1 416 496 1411",
    "sg:postcode":"M2H 1Y7",
    "sg:province":"ON",
    "sg:tags":[
        "accountant"
    ],
    "wof:name":"Propas, Lorne CA",
    "wof:placetype":"venue"
},
  "geometry": {"coordinates":[-79.3559341431,43.8009300232],"type":"Point"}
}