{
  "type": "Feature",
  "properties": {
    "addr:full":"Halifax NS B3P 2J8",
    "addr:postcode":"b3p 2j8",
    "iso:country":"CA",
    "sg:city":"Halifax",
    "sg:classifiers":[
        {
            "category":"Real Estate",
            "subcategory":"Real Estate Operator",
            "type":"Services"
        }
    ],
    "sg:phone":"+1 902 477 0490",
    "sg:postcode":"B3P 2J8",
    "sg:province":"NS",
    "sg:tags":[
        "apartment"
    ],
    "wof:name":"Ridgeway Towers",
    "wof:placetype":"venue"
},
  "geometry": {"coordinates":[-63.573921,44.64616],"type":"Point"}
}