{
  "type": "Feature",
  "properties": {
    "addr:full":"490 Rue Du Lac Saint-Benjamin QC G0M 1N0",
    "addr:housenumber":"490",
    "addr:postcode":"g0m 1n0",
    "addr:street":"Rue Du Lac",
    "iso:country":"CA",
    "sg:address":"490 Rue Du Lac",
    "sg:city":"Saint-Benjamin",
    "sg:classifiers":[
        {
            "category":"Sports & Exercise",
            "subcategory":"Golf",
            "type":"Entertainment"
        }
    ],
    "sg:phone":"+1 418 594 5545",
    "sg:postcode":"G0M 1N0",
    "sg:province":"QC",
    "sg:tags":[
        "course"
    ],
    "wof:name":"Club DE Golf Le Grand Heron",
    "wof:placetype":"venue"
},
  "geometry": {"coordinates":[-70.5986404419,46.2780799866],"type":"Point"}
}