{
  "type": "Feature",
  "properties": {
    "addr:full":"Surrey BC V4N 3R1",
    "addr:postcode":"v4n 3r1",
    "iso:country":"CA",
    "sg:city":"Surrey",
    "sg:classifiers":[
        {
            "category":"Wholesale",
            "subcategory":"Hardware",
            "type":"Manufacturing & Wholesale Goods"
        }
    ],
    "sg:phone":"+1 604 882 9773",
    "sg:postcode":"V4N 3R1",
    "sg:province":"BC",
    "sg:tags":[
        "equipment",
        "heating",
        "system"
    ],
    "wof:name":"Energy Wise Distributors",
    "wof:placetype":"venue"
},
  "geometry": {"coordinates":[-122.700561523,49.1768569946],"type":"Point"}
}