{
  "type": "Feature",
  "properties": {
    "addr:full":"Highway 148 Shawville QC J0X 2Y0",
    "addr:postcode":"j0x 2y0",
    "addr:street":"Highway 148",
    "iso:country":"CA",
    "sg:address":"Highway 148",
    "sg:city":"Shawville",
    "sg:classifiers":[
        {
            "category":"Professional",
            "subcategory":"Accounting & Tax Preparation",
            "type":"Services"
        }
    ],
    "sg:phone":"+1 819 647 6640",
    "sg:postcode":"J0X 2Y0",
    "sg:province":"QC",
    "sg:tags":[
        "consultant",
        "return",
        "filing"
    ],
    "wof:name":"H & R Block Canada Inc",
    "wof:placetype":"venue"
},
  "geometry": {"coordinates":[-76.49297300000001,45.604244],"type":"Point"}
}