{
  "type": "Feature",
  "properties": {
    "iso:country":"CA",
    "sg:address":"73 Rue Carole",
    "sg:city":"Rougemont",
    "sg:classifiers":[
        {
            "category":"Retail",
            "subcategory":"Laundry & Dry Cleaning",
            "type":"Services"
        }
    ],
    "sg:phone":"+1 450 469 4008",
    "sg:postcode":"J0L 1M0",
    "sg:province":"QC",
    "sg:tags":[
        "cleaners",
        "rug",
        "carpet"
    ],
    "wof:name":"Nettoyage DE Tapis D Langlois",
    "wof:placetype":"venue"
},
  "geometry": {"coordinates":[-73.0756,45.440823],"type":"Point"}
}