{
  "type": "Feature",
  "properties": {
    "addr:full":"162 Rue Sansregret Repentigny QC J5Y 1Z1",
    "addr:housenumber":"162",
    "addr:postcode":"j5y 1z1",
    "addr:street":"Rue Sansregret",
    "iso:country":"CA",
    "sg:address":"162 Rue Sansregret",
    "sg:city":"Repentigny",
    "sg:classifiers":[
        {
            "category":"Building & Trades",
            "subcategory":"Electrical",
            "type":"Services"
        }
    ],
    "sg:phone":"+1 450 585 9424",
    "sg:postcode":"J5Y 1Z1",
    "sg:province":"QC",
    "sg:tags":[
        "electric",
        "contractor"
    ],
    "wof:name":"Gilles Leblanc Electrique Inc",
    "wof:placetype":"venue"
},
  "geometry": {"coordinates":[-73.431625,45.7687],"type":"Point"}
}