{
  "type": "Feature",
  "properties": {
    "addr:full":"342 Runnymede Rd Toronto ON M6S 2Y6",
    "addr:housenumber":"342",
    "addr:postcode":"m6s 2y6",
    "addr:street":"Runnymede Rd",
    "iso:country":"CA",
    "sg:address":"342 Runnymede Rd",
    "sg:city":"Toronto",
    "sg:classifiers":[
        {
            "category":"Social Services",
            "subcategory":"Child Care",
            "type":"Services"
        }
    ],
    "sg:phone":"+1 416 769 9719",
    "sg:postcode":"M6S 2Y6",
    "sg:province":"ON",
    "sg:tags":[
        "kindergarten",
        "academic"
    ],
    "wof:name":"Stepping Stones Montessori",
    "wof:placetype":"venue"
},
  "geometry": {"coordinates":[-79.4775238037,43.6538124084],"type":"Point"}
}