{
  "type": "Feature",
  "properties": {
    "addr:full":"Calgary AB T2P 2Y9",
    "addr:postcode":"t2p 2y9",
    "iso:country":"CA",
    "sg:city":"Calgary",
    "sg:classifiers":[
        {
            "category":"Shopping",
            "subcategory":"Pharmacy",
            "type":"Retail Goods"
        }
    ],
    "sg:phone":"+1 403 266 7328",
    "sg:postcode":"T2P 2Y9",
    "sg:province":"AB",
    "wof:name":"Shoppers Drug Mart",
    "wof:placetype":"venue"
},
  "geometry": {"coordinates":[-114.06844329800001,51.0464706421],"type":"Point"}
}