{
  "type": "Feature",
  "properties": {
    "iso:country":"CA",
    "sg:city":"Surrey",
    "sg:classifiers":[
        {
            "category":"Building & Trades",
            "subcategory":"Construction",
            "type":"Services"
        }
    ],
    "sg:phone":"+1 604 590 9541",
    "sg:postcode":"V3W 0N2",
    "sg:province":"BC",
    "sg:tags":[
        "elevator"
    ],
    "wof:name":"Eci Mfg Inc",
    "wof:placetype":"venue"
},
  "geometry": {"coordinates":[-122.88150024399999,49.1557006836],"type":"Point"}
}