{
  "type": "Feature",
  "properties": {
    "addr:full":"420 Hastings St E Vancouver BC V6A 1P7",
    "addr:housenumber":"420",
    "addr:postcode":"v6a 1p7",
    "addr:street":"Hastings St E",
    "iso:country":"CA",
    "sg:address":"420 Hastings St E",
    "sg:city":"Vancouver",
    "sg:classifiers":[
        {
            "category":"Wholesale",
            "subcategory":"Durable Goods & Equipment",
            "type":"Manufacturing & Wholesale Goods"
        }
    ],
    "sg:phone":"+1 604 254 0022",
    "sg:postcode":"V6A 1P7",
    "sg:province":"BC",
    "sg:tags":[
        "importer"
    ],
    "wof:name":"Nam Hing CO Ltd",
    "wof:placetype":"venue"
},
  "geometry": {"coordinates":[-123.09477200000001,49.281101],"type":"Point"}
}