{
  "type": "Feature",
  "properties": {
    "addr:full":"12105 Rue Sherbrooke E Pointe-Aux-Trembles QC H1B 5L4",
    "addr:housenumber":"12105",
    "addr:postcode":"h1b 5l4",
    "addr:street":"Rue Sherbrooke E Pointe-Aux-Trembles",
    "iso:country":"CA",
    "sg:address":"12105 Rue Sherbrooke E",
    "sg:city":"Pointe-Aux-Trembles",
    "sg:classifiers":[
        {
            "category":"Retail",
            "subcategory":"Auto Repair",
            "type":"Services"
        }
    ],
    "sg:phone":"+1 514 645 6401",
    "sg:postcode":"H1B 5L4",
    "sg:province":"QC",
    "sg:tags":[
        "muffler",
        "exhaust",
        "system"
    ],
    "wof:name":"Monsieur Muffler",
    "wof:placetype":"venue"
},
  "geometry": {"coordinates":[-73.5139160156,45.6444854736],"type":"Point"}
}