{
  "type": "Feature",
  "properties": {
    "iso:country":"CA",
    "sg:address":"2328 2E Rang",
    "sg:city":"Saint-Hugues",
    "sg:classifiers":[
        {
            "category":"Retail",
            "subcategory":"Auto Repair",
            "type":"Services"
        }
    ],
    "sg:phone":"+1 450 794 2359",
    "sg:postcode":"J0H 1N0",
    "sg:province":"QC",
    "sg:tags":[
        "transmission"
    ],
    "wof:name":"Transmissions Jean-Guy Chabot",
    "wof:placetype":"venue"
},
  "geometry": {"coordinates":[-72.8097610474,45.7602577209],"type":"Point"}
}