{
  "type": "Feature",
  "properties": {
    "addr:full":"1 Oriole St Winnipeg MB R3T 0K2",
    "addr:housenumber":"1",
    "addr:postcode":"r3t 0k2",
    "addr:street":"Oriole St",
    "iso:country":"CA",
    "sg:address":"1 Oriole St",
    "sg:city":"Winnipeg",
    "sg:classifiers":[
        {
            "category":"Building & Trades",
            "subcategory":"Construction",
            "type":"Services"
        }
    ],
    "sg:phone":"+1 204 452 4442",
    "sg:postcode":"R3T 0K2",
    "sg:province":"MB",
    "sg:tags":[
        "tile",
        "dealer"
    ],
    "wof:name":"Cannata Tile Design",
    "wof:placetype":"venue"
},
  "geometry": {"coordinates":[-97.14418000000001,49.837357],"type":"Point"}
}