{
  "type": "Feature",
  "properties": {
    "iso:country":"CA",
    "sg:address":"161 Spadina Ave",
    "sg:city":"Toronto",
    "sg:classifiers":[
        {
            "category":"Shopping",
            "subcategory":"Clothing, Apparel, & Fashions",
            "type":"Retail Goods"
        }
    ],
    "sg:phone":"+1 416 598 3174",
    "sg:postcode":"M5V 2L6",
    "sg:province":"ON",
    "sg:tags":[
        "shop",
        "bridal"
    ],
    "wof:name":"Bridal Fashion Faire",
    "wof:placetype":"venue"
},
  "geometry": {"coordinates":[-79.3959655762,43.6485824585],"type":"Point"}
}