{
  "type": "Feature",
  "properties": {
    "iso:country":"CA",
    "sg:address":"3201 Marentette Ave",
    "sg:city":"Windsor",
    "sg:classifiers":[
        {
            "category":"Professional",
            "subcategory":"Computer Services",
            "type":"Services"
        }
    ],
    "sg:phone":"+1 519 251 0548",
    "sg:postcode":"N8X 4G3",
    "sg:province":"ON",
    "wof:name":"On Site Svc",
    "wof:placetype":"venue"
},
  "geometry": {"coordinates":[-82.998016,42.274132],"type":"Point"}
}