{
  "type": "Feature",
  "properties": {
    "addr:full":"1275 Montee Masson Lachenaie QC J6W 6A6",
    "addr:housenumber":"1275",
    "addr:postcode":"j6w 6a6",
    "addr:street":"Montee Masson",
    "iso:country":"CA",
    "sg:address":"1275 Montee Masson",
    "sg:city":"Lachenaie",
    "sg:classifiers":[
        {
            "category":"Autos & Motor Vehicles",
            "subcategory":"Automobile Sales",
            "type":"Retail Goods"
        }
    ],
    "sg:phone":"+1 450 471 9444",
    "sg:postcode":"J6W 6A6",
    "sg:province":"QC",
    "sg:tags":[
        "repairing",
        "car"
    ],
    "wof:name":"Grenier Nissan Inc",
    "wof:placetype":"venue"
},
  "geometry": {"coordinates":[-73.623268,45.717529],"type":"Point"}
}