{
  "type": "Feature",
  "properties": {
    "addr:full":"624 Ch Plaisance Chute-Saint-Philippe QC J0W 1A0",
    "addr:housenumber":"624",
    "addr:postcode":"j0w 1a0",
    "addr:street":"Ch Plaisance",
    "iso:country":"CA",
    "sg:address":"624 Ch Plaisance",
    "sg:city":"Chute-Saint-Philippe",
    "sg:classifiers":[
        {
            "category":"Farming",
            "subcategory":"Aquatic Farm",
            "type":"Manufacturing & Wholesale Goods"
        }
    ],
    "sg:phone":"+1 819 585 3137",
    "sg:postcode":"J0W 1A0",
    "sg:province":"QC",
    "sg:tags":[
        "hatchery",
        "fish"
    ],
    "wof:name":"Pisciculture Gramp-Jalac Enr",
    "wof:placetype":"venue"
},
  "geometry": {"coordinates":[-75.2611160278,46.6665496826],"type":"Point"}
}