{
  "type": "Feature",
  "properties": {
    "addr:full":"270 Railway Ave Treherne MB R0G 2V0",
    "addr:housenumber":"270",
    "addr:postcode":"r0g 2v0",
    "addr:street":"Railway Ave",
    "iso:country":"CA",
    "sg:address":"270 Railway Ave",
    "sg:city":"Treherne",
    "sg:classifiers":[
        {
            "category":"Food & Beverages",
            "subcategory":"Bakery",
            "type":"Retail Goods"
        }
    ],
    "sg:phone":"+1 204 723 2466",
    "sg:postcode":"R0G 2V0",
    "sg:province":"MB",
    "sg:tags":[
        "baker"
    ],
    "wof:name":"Treherne Bakery",
    "wof:placetype":"venue"
},
  "geometry": {"coordinates":[-98.69616699220001,49.6304550171],"type":"Point"}
}