{
  "type": "Feature",
  "properties": {
    "addr:full":"Chambord QC G0W 1G0",
    "addr:postcode":"g0w 1g0",
    "iso:country":"CA",
    "sg:city":"Chambord",
    "sg:classifiers":[
        {
            "category":"Personal",
            "subcategory":"Beauty Salon",
            "type":"Services"
        }
    ],
    "sg:phone":"+1 418 342 1096",
    "sg:postcode":"G0W 1G0",
    "sg:province":"QC",
    "wof:name":"Coiffure Annie Tremblay Enr",
    "wof:placetype":"venue"
},
  "geometry": {"coordinates":[-72.05689239500001,48.4266014099],"type":"Point"}
}