{
  "type": "Feature",
  "properties": {
    "addr:full":"37 Laut Cres Crossfield AB T0M 0S0",
    "addr:housenumber":"37",
    "addr:postcode":"t0m 0s0",
    "addr:street":"Laut Cres",
    "iso:country":"CA",
    "sg:address":"37 Laut Cres",
    "sg:city":"Crossfield",
    "sg:classifiers":[
        {
            "category":"Wholesale",
            "subcategory":"Machinery & Supplies",
            "type":"Manufacturing & Wholesale Goods"
        }
    ],
    "sg:phone":"+1 403 946 4861",
    "sg:postcode":"T0M 0S0",
    "sg:province":"AB",
    "sg:tags":[
        "dyer",
        "cleaners",
        "equipment"
    ],
    "wof:name":"Bearspaw Carbon",
    "wof:placetype":"venue"
},
  "geometry": {"coordinates":[-114.032104,51.421585],"type":"Point"}
}