{
  "type": "Feature",
  "properties": {
    "addr:full":"3840 Boul Taschereau Greenfield Park QC J4V 2H9",
    "addr:housenumber":"3840",
    "addr:postcode":"j4v 2h9",
    "addr:street":"Boul Taschereau",
    "iso:country":"CA",
    "sg:address":"3840 Boul Taschereau",
    "sg:city":"Greenfield Park",
    "sg:classifiers":[
        {
            "category":"Food & Beverages",
            "subcategory":"Meat & Fish",
            "type":"Retail Goods"
        }
    ],
    "sg:phone":"+1 450 923 8790",
    "sg:postcode":"J4V 2H9",
    "sg:province":"QC",
    "sg:tags":[
        "sausage"
    ],
    "wof:name":"William J Walter Inc",
    "wof:placetype":"venue"
},
  "geometry": {"coordinates":[-73.470016,45.487026],"type":"Point"}
}