{
  "type": "Feature",
  "properties": {
    "addr:full":"373 Bridge St W # 10 Waterloo ON N2K 3K3",
    "addr:housenumber":"373",
    "addr:postcode":"n2k 3k3",
    "addr:street":"Bridge St W # 10",
    "iso:country":"CA",
    "sg:address":"373 Bridge St W # 10",
    "sg:city":"Waterloo",
    "sg:classifiers":[
        {
            "category":"Restaurant",
            "type":"Food & Drink"
        }
    ],
    "sg:phone":"+1 519 746 6663",
    "sg:postcode":"N2K 3K3",
    "sg:province":"ON",
    "sg:tags":[
        "pizza"
    ],
    "wof:name":"Little Caesars Pizza",
    "wof:placetype":"venue"
},
  "geometry": {"coordinates":[-80.5009460449,43.4955940247],"type":"Point"}
}