{
  "type": "Feature",
  "properties": {
    "addr:full":"319 Macintosh Dr Stoney Creek ON L8E 4E1",
    "addr:housenumber":"319",
    "addr:postcode":"l8e 4e1",
    "addr:street":"Macintosh Dr",
    "iso:country":"CA",
    "sg:address":"319 Macintosh Dr",
    "sg:city":"Stoney Creek",
    "sg:classifiers":[
        {
            "category":"Professional",
            "subcategory":"Business Services",
            "type":"Services"
        }
    ],
    "sg:phone":"+1 905 662 4032",
    "sg:postcode":"L8E 4E1",
    "sg:province":"ON",
    "sg:tags":[
        "drafting"
    ],
    "wof:name":"Eddie's Drafting & Design Svc",
    "wof:placetype":"venue"
},
  "geometry": {"coordinates":[-79.714378,43.224258],"type":"Point"}
}