{
  "type": "Feature",
  "properties": {
    "addr:full":"Elmvale ON L0L 1P0",
    "addr:postcode":"l0l 1p0",
    "iso:country":"CA",
    "sg:city":"Elmvale",
    "sg:classifiers":[
        {
            "category":"Building & Trades",
            "subcategory":"Construction",
            "type":"Services"
        }
    ],
    "sg:phone":"+1 705 322 1881",
    "sg:postcode":"L0L 1P0",
    "sg:province":"ON",
    "sg:tags":[
        "excavating",
        "road",
        "contractor"
    ],
    "wof:name":"Ken Truax Construction Ltd",
    "wof:placetype":"venue"
},
  "geometry": {"coordinates":[-79.8664855957,44.583984375],"type":"Point"}
}