{
  "type": "Feature",
  "properties": {
    "addr:full":"264 Rue Sherbrooke O Montreal QC H2X 1X9",
    "addr:housenumber":"264",
    "addr:postcode":"h2x 1x9",
    "addr:street":"Rue Sherbrooke O",
    "iso:country":"CA",
    "sg:address":"264 Rue Sherbrooke O",
    "sg:city":"Montreal",
    "sg:classifiers":[
        {
            "category":"Travel",
            "subcategory":"Hotels & Motels",
            "type":"Entertainment"
        }
    ],
    "sg:phone":"+1 514 849 2777",
    "sg:postcode":"H2X 1X9",
    "sg:province":"QC",
    "wof:name":"Hotel Casa Bella",
    "wof:placetype":"venue"
},
  "geometry": {"coordinates":[-73.567932,45.515377],"type":"Point"}
}