{
  "type": "Feature",
  "properties": {
    "addr:full":"291 Rutherford Rd S Brampton ON L6W 3R5",
    "addr:housenumber":"291",
    "addr:postcode":"l6w 3r5",
    "addr:street":"Rutherford Rd S",
    "iso:country":"CA",
    "sg:address":"291 Rutherford Rd S",
    "sg:city":"Brampton",
    "sg:classifiers":[
        {
            "category":"Organizations",
            "subcategory":"Membership Organization",
            "type":"Services"
        }
    ],
    "sg:phone":"+1 905 459 2614",
    "sg:postcode":"L6W 3R5",
    "sg:province":"ON",
    "wof:name":"Rotary Club of Brampton",
    "wof:placetype":"venue"
},
  "geometry": {"coordinates":[-79.72380099999999,43.685089],"type":"Point"}
}