{
  "type": "Feature",
  "properties": {
    "iso:country":"CA",
    "sg:address":"207 Cayley St",
    "sg:city":"Walkerton",
    "sg:classifiers":[
        {
            "category":"Professional",
            "subcategory":"Lawyer & Legal Services",
            "type":"Services"
        }
    ],
    "sg:phone":"+1 519 881 2384",
    "sg:postcode":"N0G 2V0",
    "sg:province":"ON",
    "sg:tags":[
        "attorney"
    ],
    "wof:name":"Bruce Law Assn Library",
    "wof:placetype":"venue"
},
  "geometry": {"coordinates":[-81.1505432129,44.1310997009],"type":"Point"}
}