{
  "type": "Feature",
  "properties": {
    "addr:full":"1285 Kingsway Vancouver BC V5V 3E2",
    "addr:housenumber":"1285",
    "addr:postcode":"v5v 3e2",
    "addr:street":"Kingsway",
    "iso:country":"CA",
    "sg:address":"1285 Kingsway",
    "sg:city":"Vancouver",
    "sg:classifiers":[
        {
            "category":"Personal",
            "subcategory":"Beauty Salon",
            "type":"Services"
        }
    ],
    "sg:phone":"+1 604 879 2021",
    "sg:postcode":"V5V 3E2",
    "sg:province":"BC",
    "wof:name":"Teeze Hair Design",
    "wof:placetype":"venue"
},
  "geometry": {"coordinates":[-123.07820892300001,49.2514228821],"type":"Point"}
}