{
  "type": "Feature",
  "properties": {
    "addr:full":"206 2E Rue Quebec QC G1L 4Z1",
    "addr:housenumber":"206",
    "addr:postcode":"g1l 4z1",
    "addr:street":"2E Rue Quebec",
    "iso:country":"CA",
    "sg:address":"206 2E Rue",
    "sg:city":"Quebec",
    "sg:classifiers":[
        {
            "category":"Taxi",
            "type":"Transportation"
        }
    ],
    "sg:phone":"+1 418 641 8294",
    "sg:postcode":"G1L 4Z1",
    "sg:province":"QC",
    "sg:tags":[
        "taxicab"
    ],
    "wof:name":"Taxi Accessible",
    "wof:placetype":"venue"
},
  "geometry": {"coordinates":[-71.226364,46.820499],"type":"Point"}
}