{
  "type": "Feature",
  "properties": {
    "addr:full":"371 Park Ave E Brandon MB R7A 7A5",
    "addr:housenumber":"371",
    "addr:postcode":"r7a 7a5",
    "addr:street":"Park Ave E",
    "iso:country":"CA",
    "sg:address":"371 Park Ave E",
    "sg:city":"Brandon",
    "sg:classifiers":[
        {
            "category":"Wholesale",
            "subcategory":"Groceries",
            "type":"Manufacturing & Wholesale Goods"
        }
    ],
    "sg:phone":"+1 204 728 2214",
    "sg:postcode":"R7A 7A5",
    "sg:province":"MB",
    "sg:tags":[
        "baker"
    ],
    "wof:name":"Canada Bread CO Ltd",
    "wof:placetype":"venue"
},
  "geometry": {"coordinates":[-99.924942,49.831062],"type":"Point"}
}