{
  "type": "Feature",
  "properties": {
    "iso:country":"CA",
    "sg:address":"1430 Rue Notre-Dame",
    "sg:city":"Trois-Rivieres",
    "sg:classifiers":[
        {
            "category":"Personal",
            "subcategory":"Beauty Salon",
            "type":"Services"
        }
    ],
    "sg:phone":"+1 819 373 4737",
    "sg:postcode":"G9A 4X3",
    "sg:province":"QC",
    "wof:name":"Boite A Coupe 1500-Trs-Rvrs",
    "wof:placetype":"venue"
},
  "geometry": {"coordinates":[-72.4859924316,46.3811836243],"type":"Point"}
}