{
  "type": "Feature",
  "properties": {
    "addr:full":"162 Main St Glencoe ON N0L 1M0",
    "addr:housenumber":"162",
    "addr:postcode":"n0l 1m0",
    "addr:street":"Main St",
    "iso:country":"CA",
    "sg:address":"162 Main St",
    "sg:city":"Glencoe",
    "sg:classifiers":[
        {
            "category":"Social Services",
            "subcategory":"Child Care",
            "type":"Services"
        }
    ],
    "sg:phone":"+1 519 287 2835",
    "sg:postcode":"N0L 1M0",
    "sg:province":"ON",
    "wof:name":"Elm Children's Ctr Inc",
    "wof:placetype":"venue"
},
  "geometry": {"coordinates":[-81.7072601318,42.7448806763],"type":"Point"}
}