{
  "type": "Feature",
  "properties": {
    "iso:country":"CA",
    "sg:address":"431 Alden Rd",
    "sg:city":"Markham",
    "sg:classifiers":[
        {
            "category":"Manufacturing",
            "subcategory":"Tools & Machinery",
            "type":"Manufacturing & Wholesale Goods"
        }
    ],
    "sg:phone":"+1 905 305 1718",
    "sg:postcode":"L3R 3L4",
    "sg:province":"ON",
    "sg:tags":[
        "machine",
        "shop"
    ],
    "wof:name":"Cutting Edge Tooling Inc",
    "wof:placetype":"venue"
},
  "geometry": {"coordinates":[-79.333458,43.834377],"type":"Point"}
}