{
  "type": "Feature",
  "properties": {
    "addr:full":"St Pauls Station ON N0K 1V0",
    "addr:postcode":"n0k 1v0",
    "iso:country":"CA",
    "sg:city":"St Pauls Station",
    "sg:classifiers":[
        {
            "category":"Real Estate",
            "subcategory":"Real Estate Agent",
            "type":"Services"
        }
    ],
    "sg:phone":"+1 519 271 1171",
    "sg:postcode":"N0K 1V0",
    "sg:province":"ON",
    "wof:name":"J E Jackson Realty Ltd",
    "wof:placetype":"venue"
},
  "geometry": {"coordinates":[-81.058182,43.318661],"type":"Point"}
}