{
  "type": "Feature",
  "properties": {
    "addr:full":"465 Hazeldean Rd Kanata ON K2L 1V1",
    "addr:housenumber":"465",
    "addr:postcode":"k2l 1v1",
    "addr:street":"Hazeldean Rd",
    "iso:country":"CA",
    "sg:address":"465 Hazeldean Rd",
    "sg:city":"Kanata",
    "sg:classifiers":[
        {
            "category":"Organizations",
            "subcategory":"Religious Organization",
            "type":"Services"
        }
    ],
    "sg:phone":"+1 613 836 3145",
    "sg:postcode":"K2L 1V1",
    "sg:province":"ON",
    "sg:tags":[
        "church"
    ],
    "wof:name":"Kanata Baptist Church",
    "wof:placetype":"venue"
},
  "geometry": {"coordinates":[-75.887314,45.299011],"type":"Point"}
}