{
  "type": "Feature",
  "properties": {
    "addr:full":"1427 Newtonville Rd Newtonville ON L0A 1J0",
    "addr:housenumber":"1427",
    "addr:postcode":"l0a 1j0",
    "addr:street":"Newtonville Rd",
    "iso:country":"CA",
    "sg:address":"1427 Newtonville Rd",
    "sg:city":"Newtonville",
    "sg:classifiers":[
        {
            "category":"Education",
            "subcategory":"School",
            "type":"Public Place"
        }
    ],
    "sg:phone":"+1 905 786 2550",
    "sg:postcode":"L0A 1J0",
    "sg:province":"ON",
    "wof:name":"Newtonville Public School",
    "wof:placetype":"venue"
},
  "geometry": {"coordinates":[-78.48992200000001,43.933918],"type":"Point"}
}