{
  "type": "Feature",
  "properties": {
    "addr:full":"124 Victoria St Kamloops BC V2C 1Z7",
    "addr:housenumber":"124",
    "addr:postcode":"bc v2c 1z7",
    "addr:street":"Victoria St",
    "iso:country":"CA",
    "sg:address":"124 Victoria St",
    "sg:city":"Kamloops",
    "sg:classifiers":[
        {
            "category":"Professional",
            "subcategory":"Printing & Photocopies",
            "type":"Services"
        }
    ],
    "sg:phone":"+1 250 372 3866",
    "sg:postcode":"V2C 1Z7",
    "sg:province":"BC",
    "sg:tags":[
        "duplicating",
        "copying"
    ],
    "wof:name":"Universal Reproduction-Enginee",
    "wof:placetype":"venue"
},
  "geometry": {"coordinates":[-120.338295,50.676346],"type":"Point"}
}