{
  "type": "Feature",
  "properties": {
    "iso:country":"CA",
    "sg:address":"175 Av Rouleau",
    "sg:city":"Rimouski",
    "sg:classifiers":[
        {
            "category":"Shopping",
            "subcategory":"Pharmacy",
            "type":"Retail Goods"
        }
    ],
    "sg:phone":"+1 418 723 3333",
    "sg:postcode":"G5L 5T4",
    "sg:province":"QC",
    "wof:name":"Pharmacie A Laurent Poisson",
    "wof:placetype":"venue"
},
  "geometry": {"coordinates":[-68.5310516357,48.4460105896],"type":"Point"}
}