{
  "type": "Feature",
  "properties": {
    "addr:full":"121 22nd St Fort Macleod AB T0L 0Z0",
    "addr:housenumber":"121",
    "addr:postcode":"t0l 0z0",
    "addr:street":"22Nd St",
    "iso:country":"CA",
    "sg:address":"121 22nd St",
    "sg:city":"Fort Macleod",
    "sg:classifiers":[
        {
            "category":"Retail",
            "subcategory":"Laundry & Dry Cleaning",
            "type":"Services"
        }
    ],
    "sg:phone":"+1 403 553 3788",
    "sg:postcode":"T0L 0Z0",
    "sg:province":"AB",
    "sg:tags":[
        "cleaners",
        "janitor"
    ],
    "wof:name":"Elite Cleaning Svc",
    "wof:placetype":"venue"
},
  "geometry": {"coordinates":[-113.410774231,49.7241134644],"type":"Point"}
}