{
  "type": "Feature",
  "properties": {
    "addr:full":"125 Lakeshore Rd St Catharines ON L2N 2T6",
    "addr:housenumber":"125",
    "addr:postcode":"l2n 2t6",
    "addr:street":"Lakeshore Rd",
    "iso:country":"CA",
    "sg:address":"125 Lakeshore Rd",
    "sg:city":"St Catharines",
    "sg:classifiers":[
        {
            "category":"Retail",
            "subcategory":"Auto Repair",
            "type":"Services"
        }
    ],
    "sg:phone":"+1 905 934 1723",
    "sg:postcode":"L2N 2T6",
    "sg:province":"ON",
    "sg:tags":[
        "repairing",
        "automobile"
    ],
    "wof:name":"Bob Berg's Automotive",
    "wof:placetype":"venue"
},
  "geometry": {"coordinates":[-79.2432022095,43.204334259],"type":"Point"}
}