{
  "type": "Feature",
  "properties": {
    "addr:full":"Edmonton AB T5K 0M9",
    "addr:postcode":"t5k 0m9",
    "iso:country":"CA",
    "sg:city":"Edmonton",
    "sg:classifiers":[
        {
            "category":"Real Estate",
            "subcategory":"Real Estate Agent",
            "type":"Services"
        }
    ],
    "sg:phone":"+1 780 482 6597",
    "sg:postcode":"T5K 0M9",
    "sg:province":"AB",
    "sg:tags":[
        "management"
    ],
    "wof:name":"Bond Investments Ltd",
    "wof:placetype":"venue"
},
  "geometry": {"coordinates":[-113.52209499999999,53.540714],"type":"Point"}
}