{
  "type": "Feature",
  "properties": {
    "addr:full":"Victoria BC V8T 2C1",
    "addr:postcode":"v8t 2c1",
    "iso:country":"CA",
    "sg:city":"Victoria",
    "sg:classifiers":[
        {
            "category":"Shopping",
            "subcategory":"Books",
            "type":"Retail Goods"
        }
    ],
    "sg:phone":"+1 250 592 1656",
    "sg:postcode":"V8T 2C1",
    "sg:province":"BC",
    "sg:tags":[
        "comic"
    ],
    "wof:name":"Curious Comics",
    "wof:placetype":"venue"
},
  "geometry": {"coordinates":[-123.33628845200001,48.4442977905],"type":"Point"}
}