{
  "type": "Feature",
  "properties": {
    "addr:full":"58 Elora St Mildmay ON N0G 2J0",
    "addr:housenumber":"58",
    "addr:postcode":"n0g 2j0",
    "addr:street":"Elora St",
    "iso:country":"CA",
    "sg:address":"58 Elora St",
    "sg:city":"Mildmay",
    "sg:classifiers":[
        {
            "category":"Shopping",
            "type":"Retail Goods"
        }
    ],
    "sg:phone":"+1 519 367 2636",
    "sg:postcode":"N0G 2J0",
    "sg:province":"ON",
    "sg:tags":[
        "picture",
        "frame"
    ],
    "wof:name":"Surroundings",
    "wof:placetype":"venue"
},
  "geometry": {"coordinates":[-81.1179428101,44.0418968201],"type":"Point"}
}