{
  "type": "Feature",
  "properties": {
    "addr:full":"560 2E Av Weedon QC J0B 3J0",
    "addr:housenumber":"560",
    "addr:postcode":"j0b 3j0",
    "addr:street":"2E Av",
    "iso:country":"CA",
    "sg:address":"560 2E Av",
    "sg:city":"Weedon",
    "sg:classifiers":[
        {
            "category":"Real Estate",
            "subcategory":"Real Estate Agent",
            "type":"Services"
        }
    ],
    "sg:phone":"+1 819 877 2811",
    "sg:postcode":"J0B 3J0",
    "sg:province":"QC",
    "sg:tags":[
        "agency",
        "rental"
    ],
    "wof:name":"Breton Location Inc",
    "wof:placetype":"venue"
},
  "geometry": {"coordinates":[-71.459824,45.708916],"type":"Point"}
}