{
  "type": "Feature",
  "properties": {
    "addr:full":"16 116 Rte O Danville QC J0A 1A0",
    "addr:housenumber":"116",
    "addr:postcode":"j0a 1a0",
    "addr:street":"16;Rte O",
    "iso:country":"CA",
    "sg:address":"16 116 Rte O",
    "sg:city":"Danville",
    "sg:classifiers":[
        {
            "category":"Shopping",
            "subcategory":"Gifts & Souvenirs",
            "type":"Retail Goods"
        }
    ],
    "sg:phone":"+1 819 839 3690",
    "sg:postcode":"J0A 1A0",
    "sg:province":"QC",
    "sg:tags":[
        "shop",
        "handicraft"
    ],
    "wof:name":"Petit Tresor",
    "wof:placetype":"venue"
},
  "geometry": {"coordinates":[-72.0236358643,45.7859992981],"type":"Point"}
}