{
  "type": "Feature",
  "properties": {
    "addr:full":"216 Gavel Rd Tusket NS B0W 3M0",
    "addr:housenumber":"216",
    "addr:postcode":"b0w 3m0",
    "addr:street":"Gavel Rd",
    "iso:country":"CA",
    "sg:address":"216 Gavel Rd",
    "sg:city":"Tusket",
    "sg:classifiers":[
        {
            "category":"Manufacturing",
            "subcategory":"Apparel",
            "type":"Manufacturing & Wholesale Goods"
        }
    ],
    "sg:phone":"+1 902 648 3435",
    "sg:postcode":"B0W 3M0",
    "sg:province":"NS",
    "sg:tags":[
        "wiping",
        "clothing"
    ],
    "wof:name":"Frenchy's",
    "wof:placetype":"venue"
},
  "geometry": {"coordinates":[-65.9767532349,43.8594474792],"type":"Point"}
}