{
  "type": "Feature",
  "properties": {
    "iso:country":"CA",
    "sg:city":"Langley",
    "sg:classifiers":[
        {
            "category":"Personal",
            "subcategory":"Beauty Salon",
            "type":"Services"
        }
    ],
    "sg:phone":"+1 604 530 2003",
    "sg:postcode":"V3A 5N8",
    "sg:province":"BC",
    "wof:name":"Hairways Studio",
    "wof:placetype":"venue"
},
  "geometry": {"coordinates":[-122.65675354,49.1026611328],"type":"Point"}
}