{
  "type": "Feature",
  "properties": {
    "addr:full":"York ON M6S 3Z7",
    "addr:postcode":"m6s 3z7",
    "iso:country":"CA",
    "sg:city":"York",
    "sg:classifiers":[
        {
            "category":"Insurance",
            "subcategory":"Insurance Agent",
            "type":"Services"
        }
    ],
    "sg:phone":"+1 416 763 4181",
    "sg:postcode":"M6S 3Z7",
    "sg:province":"ON",
    "wof:name":"State Farm Insurance CO",
    "wof:placetype":"venue"
},
  "geometry": {"coordinates":[-79.48825100000001,43.658985],"type":"Point"}
}