{
  "type": "Feature",
  "properties": {
    "addr:full":"5800 Boul Cavendish # D8 Cote Saint-Luc QC H4W 2T5",
    "addr:housenumber":"5800",
    "addr:postcode":"h4w 2t5",
    "addr:street":"Boul Cavendish # D8 Cote",
    "iso:country":"CA",
    "sg:address":"5800 Boul Cavendish # D8",
    "sg:city":"Cote Saint-Luc",
    "sg:classifiers":[
        {
            "category":"Shopping",
            "subcategory":"Shoes",
            "type":"Retail Goods"
        }
    ],
    "sg:phone":"+1 514 489 5115",
    "sg:postcode":"H4W 2T5",
    "sg:province":"QC",
    "wof:name":"Chou Chou Bis",
    "wof:placetype":"venue"
},
  "geometry": {"coordinates":[-73.66176605219999,45.4759483337],"type":"Point"}
}