{
  "type": "Feature",
  "properties": {
    "addr:full":"1085 Bellamy Rd N # 1 Scarborough ON M1H 3C7",
    "addr:housenumber":"1085",
    "addr:postcode":"m1h 3c7",
    "addr:street":"Bellamy Rd N # 1",
    "iso:country":"CA",
    "sg:address":"1085 Bellamy Rd N # 1",
    "sg:city":"Scarborough",
    "sg:classifiers":[
        {
            "category":"Food & Beverages",
            "subcategory":"Bakery",
            "type":"Retail Goods"
        }
    ],
    "sg:phone":"+1 416 438 9800",
    "sg:postcode":"M1H 3C7",
    "sg:province":"ON",
    "sg:tags":[
        "baker"
    ],
    "wof:name":"Gerhard's Cafe",
    "wof:placetype":"venue"
},
  "geometry": {"coordinates":[-79.2420578003,43.7761039734],"type":"Point"}
}