{
  "type": "Feature",
  "properties": {
    "addr:full":"549 North River Rd Charlottetown PE C1E 1J6",
    "addr:housenumber":"549",
    "addr:postcode":"c1e 1j6",
    "addr:street":"North River Rd",
    "iso:country":"CA",
    "sg:address":"549 North River Rd",
    "sg:city":"Charlottetown",
    "sg:classifiers":[
        {
            "category":"Organizations",
            "subcategory":"Professional Association",
            "type":"Services"
        }
    ],
    "sg:phone":"+1 902 566 1268",
    "sg:postcode":"C1E 1J6",
    "sg:province":"PE",
    "wof:name":"Association of Pro Engineers",
    "wof:placetype":"venue"
},
  "geometry": {"coordinates":[-63.155197,46.259323],"type":"Point"}
}