{
  "type": "Feature",
  "properties": {
    "addr:full":"4123 200 St Langley BC V3A 1K8",
    "addr:housenumber":"4123",
    "addr:postcode":"v3a 1k8",
    "addr:street":"200 St",
    "iso:country":"CA",
    "sg:address":"4123 200 St",
    "sg:city":"Langley",
    "sg:classifiers":[
        {
            "category":"Food & Beverages",
            "subcategory":"Bakery",
            "type":"Retail Goods"
        }
    ],
    "sg:phone":"+1 604 530 1737",
    "sg:postcode":"V3A 1K8",
    "sg:province":"BC",
    "sg:tags":[
        "baker"
    ],
    "wof:name":"Cedarbrook Bakery",
    "wof:placetype":"venue"
},
  "geometry": {"coordinates":[-122.66963958700001,49.0771636963],"type":"Point"}
}