{
  "type": "Feature",
  "properties": {
    "iso:country":"CA",
    "sg:address":"1280 Florence St",
    "sg:city":"London",
    "sg:classifiers":[
        {
            "category":"Building & Trades",
            "subcategory":"Construction",
            "type":"Services"
        }
    ],
    "sg:phone":"+1 519 455 7294",
    "sg:postcode":"N5W 2N5",
    "sg:province":"ON",
    "sg:tags":[
        "fire",
        "restoration",
        "general",
        "damage",
        "contractor"
    ],
    "wof:name":"S A Thomas/Dyna-Build Inc",
    "wof:placetype":"venue"
},
  "geometry": {"coordinates":[-81.204552,42.99321],"type":"Point"}
}