{
  "type": "Feature",
  "properties": {
    "addr:full":"5901 3 St SE Calgary AB T2H 1K3",
    "addr:housenumber":"5901 3",
    "addr:postcode":"t2h 1k3",
    "addr:street":"St Se",
    "iso:country":"CA",
    "sg:address":"5901 3 St SE",
    "sg:city":"Calgary",
    "sg:classifiers":[
        {
            "category":"Manufacturing",
            "subcategory":"Printing",
            "type":"Manufacturing & Wholesale Goods"
        }
    ],
    "sg:phone":"+1 403 255 3511",
    "sg:postcode":"T2H 1K3",
    "sg:province":"AB",
    "sg:tags":[
        "newspaper"
    ],
    "wof:name":"Bargain Finder Press",
    "wof:placetype":"venue"
},
  "geometry": {"coordinates":[-114.069733,51.001183],"type":"Point"}
}