{
  "type": "Feature",
  "properties": {
    "addr:full":"Scarborough ON M1V 4Y5",
    "addr:postcode":"m1v 4y5",
    "iso:country":"CA",
    "sg:city":"Scarborough",
    "sg:classifiers":[
        {
            "category":"Manufacturing",
            "subcategory":"Apparel",
            "type":"Manufacturing & Wholesale Goods"
        }
    ],
    "sg:phone":"+1 416 502 2633",
    "sg:postcode":"M1V 4Y5",
    "sg:province":"ON",
    "sg:tags":[
        "clothing"
    ],
    "wof:name":"Tianjin Garments Canada Ltd",
    "wof:placetype":"venue"
},
  "geometry": {"coordinates":[-79.258247,43.811646],"type":"Point"}
}