{
  "type": "Feature",
  "properties": {
    "addr:full":"112 Front St # 23 Wolfville NS B4P 1A4",
    "addr:housenumber":"112",
    "addr:postcode":"b4p 1a4",
    "addr:street":"Front St # 23",
    "iso:country":"CA",
    "sg:address":"112 Front St # 23",
    "sg:city":"Wolfville",
    "sg:classifiers":[
        {
            "category":"Health Services",
            "subcategory":"Doctor",
            "type":"Services"
        }
    ],
    "sg:phone":"+1 902 542 9343",
    "sg:postcode":"B4P 1A4",
    "sg:province":"NS",
    "sg:tags":[
        "physician",
        "surgeon"
    ],
    "wof:name":"Nichols, Blair A MD",
    "wof:placetype":"venue"
},
  "geometry": {"coordinates":[-64.3632965088,45.0920791626],"type":"Point"}
}