{
  "type": "Feature",
  "properties": {
    "addr:full":"4316 Boul Saint-Laurent Montreal QC H2W 1Z3",
    "addr:housenumber":"4316",
    "addr:postcode":"h2w 1z3",
    "addr:street":"Boul Saint-Laurent",
    "iso:country":"CA",
    "sg:address":"4316 Boul Saint-Laurent",
    "sg:city":"Montreal",
    "sg:classifiers":[
        {
            "category":"Professional",
            "subcategory":"Management & Consulting",
            "type":"Services"
        }
    ],
    "sg:phone":"+1 514 849 0760",
    "sg:postcode":"H2W 1Z3",
    "sg:province":"QC",
    "sg:tags":[
        "communications",
        "consultant"
    ],
    "wof:name":"Catherine Corne Communications",
    "wof:placetype":"venue"
},
  "geometry": {"coordinates":[-73.5837478638,45.5188522339],"type":"Point"}
}