{
  "type": "Feature",
  "properties": {
    "addr:full":"1 Front St W # Ll Toronto ON M5J 2X5",
    "addr:housenumber":"1",
    "addr:postcode":"m5j 2x5",
    "addr:street":"Front St W # Ll",
    "iso:country":"CA",
    "sg:address":"1 Front St W # Ll",
    "sg:city":"Toronto",
    "sg:classifiers":[
        {
            "category":"Restaurant",
            "type":"Food & Drink"
        }
    ],
    "sg:phone":"+1 416 304 0000",
    "sg:postcode":"M5J 2X5",
    "sg:province":"ON",
    "sg:tags":[
        "caterer"
    ],
    "wof:name":"Druxy's Famous Deli Sandwiches",
    "wof:placetype":"venue"
},
  "geometry": {"coordinates":[-79.3769378662,43.6465835571],"type":"Point"}
}