{
  "type": "Feature",
  "properties": {
    "addr:full":"105 Clarington Blvd Bowmanville ON L1C 4Z3",
    "addr:housenumber":"105",
    "addr:postcode":"l1c 4z3",
    "addr:street":"Clarington Blvd",
    "iso:country":"CA",
    "sg:address":"105 Clarington Blvd",
    "sg:city":"Bowmanville",
    "sg:classifiers":[
        {
            "category":"Restaurant",
            "type":"Food & Drink"
        }
    ],
    "sg:phone":"+1 905 697 2533",
    "sg:postcode":"L1C 4Z3",
    "sg:province":"ON",
    "wof:name":"Burger King",
    "wof:placetype":"venue"
},
  "geometry": {"coordinates":[-78.707565,43.91],"type":"Point"}
}