{
  "type": "Feature",
  "properties": {
    "addr:full":"950 Rue Sainte-Genevieve Trois-Rivieres QC G9A 3X6",
    "addr:housenumber":"950",
    "addr:postcode":"g9a 3x6",
    "addr:street":"Rue Sainte-Genevieve Trois-Rivieres",
    "iso:country":"CA",
    "sg:address":"950 Rue Sainte-Genevieve",
    "sg:city":"Trois-Rivieres",
    "sg:classifiers":[
        {
            "category":"Manufacturing",
            "subcategory":"Printing",
            "type":"Manufacturing & Wholesale Goods"
        }
    ],
    "sg:phone":"+1 819 375 4012",
    "sg:postcode":"G9A 3X6",
    "sg:province":"QC",
    "sg:tags":[
        "newspaper"
    ],
    "wof:name":"Gazette Populaire DE Trois-Riv",
    "wof:placetype":"venue"
},
  "geometry": {"coordinates":[-72.54341125489999,46.3465576172],"type":"Point"}
}