{
  "type": "Feature",
  "properties": {
    "addr:full":"2786 Victoria Park Ave North York ON M2J 4A8",
    "addr:housenumber":"2786",
    "addr:postcode":"m2j 4a8",
    "addr:street":"Victoria Park Ave",
    "iso:country":"CA",
    "sg:address":"2786 Victoria Park Ave",
    "sg:city":"North York",
    "sg:classifiers":[
        {
            "category":"Banks & Credit Unions",
            "subcategory":"Bank",
            "type":"Services"
        }
    ],
    "sg:phone":"+1 416 491 2173",
    "sg:postcode":"M2J 4A8",
    "sg:province":"ON",
    "wof:name":"Royal Bank Financial Group",
    "wof:placetype":"venue"
},
  "geometry": {"coordinates":[-79.32865905760001,43.7868804932],"type":"Point"}
}