{
  "type": "Feature",
  "properties": {
    "iso:country":"CA",
    "sg:address":"3341 Redfern Pl",
    "sg:city":"North Vancouver",
    "sg:classifiers":[
        {
            "category":"Professional",
            "subcategory":"Business Services",
            "type":"Services"
        }
    ],
    "sg:phone":"+1 604 980 3968",
    "sg:postcode":"V7N 3W2",
    "sg:province":"BC",
    "sg:tags":[
        "translator",
        "interpreter"
    ],
    "wof:name":"Westview Communications Ltd",
    "wof:placetype":"venue"
},
  "geometry": {"coordinates":[-123.083298,49.339714],"type":"Point"}
}