{
  "type": "Feature",
  "properties": {
    "addr:full":"15612 116 Ave NW Edmonton AB T5M 3S5",
    "addr:housenumber":"15612",
    "addr:postcode":"t5m 3s5",
    "addr:street":"116 Ave Nw",
    "iso:country":"CA",
    "sg:address":"15612 116 Ave NW",
    "sg:city":"Edmonton",
    "sg:classifiers":[
        {
            "category":"Wholesale",
            "subcategory":"Toys & Hobbies",
            "type":"Manufacturing & Wholesale Goods"
        }
    ],
    "sg:phone":"+1 780 451 1112",
    "sg:postcode":"T5M 3S5",
    "sg:province":"AB",
    "wof:name":"Comet Strip Enterprises Ltd",
    "wof:placetype":"venue"
},
  "geometry": {"coordinates":[-113.59104919400001,53.5667572021],"type":"Point"}
}