{
  "type": "Feature",
  "properties": {
    "iso:country":"CA",
    "sg:address":"1882 Parkedale Ave E",
    "sg:city":"Brockville",
    "sg:classifiers":[
        {
            "category":"Building & Trades",
            "subcategory":"Plumbing",
            "type":"Services"
        }
    ],
    "sg:phone":"+1 613 498 2734",
    "sg:postcode":"K6V 5T2",
    "sg:province":"ON",
    "sg:tags":[
        "refrigeration",
        "cleaning",
        "contractor"
    ],
    "wof:name":"Ron Ball Refrigeration Ltd",
    "wof:placetype":"venue"
},
  "geometry": {"coordinates":[-75.6794967651,44.617893219],"type":"Point"}
}