{
  "type": "Feature",
  "properties": {
    "addr:full":"117 Little Ridge Rd N Marius MB R0H 0T0",
    "addr:housenumber":"117",
    "addr:postcode":"r0h 0t0",
    "addr:street":"Little Ridge Rd N Marius",
    "iso:country":"CA",
    "sg:address":"117 Little Ridge Rd N",
    "sg:city":"Marius",
    "sg:classifiers":[
        {
            "category":"Shopping",
            "subcategory":"Used Merchandise",
            "type":"Retail Goods"
        }
    ],
    "sg:phone":"+1 204 843 4727",
    "sg:postcode":"R0H 0T0",
    "sg:province":"MB",
    "sg:tags":[
        "pawnbroker"
    ],
    "wof:name":"R & A Trading",
    "wof:placetype":"venue"
},
  "geometry": {"coordinates":[-98.6529846191,50.5493049622],"type":"Point"}
}