{
  "type": "Feature",
  "properties": {
    "addr:full":"527 Aboujagane Rd Haute-Aboujagane NB E4P 5M2",
    "addr:housenumber":"527",
    "addr:postcode":"e4p 5m2",
    "addr:street":"Aboujagane Rd",
    "iso:country":"CA",
    "sg:address":"527 Aboujagane Rd",
    "sg:city":"Haute-Aboujagane",
    "sg:classifiers":[
        {
            "category":"Building & Trades",
            "subcategory":"Construction",
            "type":"Services"
        }
    ],
    "sg:phone":"+1 506 532 4591",
    "sg:postcode":"E4P 5M2",
    "sg:province":"NB",
    "sg:tags":[
        "paving",
        "contractor"
    ],
    "wof:name":"Archille Leblanc Constr Ltee",
    "wof:placetype":"venue"
},
  "geometry": {"coordinates":[-64.400879,46.151005],"type":"Point"}
}