{
  "type": "Feature",
  "properties": {
    "addr:full":"Drayton Valley AB T7A 2A2",
    "addr:postcode":"t7a 2a2",
    "addr:street":"Drayton",
    "iso:country":"CA",
    "sg:city":"Drayton Valley",
    "sg:classifiers":[
        {
            "category":"Building & Trades",
            "subcategory":"Construction",
            "type":"Services"
        }
    ],
    "sg:phone":"+1 780 542 5089",
    "sg:postcode":"T7A 2A2",
    "sg:province":"AB",
    "sg:tags":[
        "water",
        "well",
        "drilling"
    ],
    "wof:name":"Morrill's Water Well Drill Ltd",
    "wof:placetype":"venue"
},
  "geometry": {"coordinates":[-114.98689299999999,53.227997],"type":"Point"}
}