{
  "type": "Feature",
  "properties": {
    "addr:full":"620 Av Dalcourt Louiseville QC J5V 2Z6",
    "addr:housenumber":"620",
    "addr:postcode":"j5v 2z6",
    "addr:street":"Av Dalcourt",
    "iso:country":"CA",
    "sg:address":"620 Av Dalcourt",
    "sg:city":"Louiseville",
    "sg:classifiers":[
        {
            "category":"Manufacturing",
            "subcategory":"Tools & Machinery",
            "type":"Manufacturing & Wholesale Goods"
        }
    ],
    "sg:phone":"+1 819 228 9976",
    "sg:postcode":"J5V 2Z6",
    "sg:province":"QC",
    "sg:tags":[
        "automobile",
        "parts",
        "hydraulic",
        "supply"
    ],
    "wof:name":"Atelier Mecanique DC",
    "wof:placetype":"venue"
},
  "geometry": {"coordinates":[-72.951843,46.26107],"type":"Point"}
}