{
  "type": "Feature",
  "properties": {
    "addr:full":"Alma ON N0B 1A0",
    "addr:postcode":"n0b 1a0",
    "iso:country":"CA",
    "sg:city":"Alma",
    "sg:classifiers":[
        {
            "category":"Building & Trades",
            "subcategory":"Construction",
            "type":"Services"
        }
    ],
    "sg:phone":"+1 519 638 8993",
    "sg:postcode":"N0B 1A0",
    "sg:province":"ON",
    "sg:tags":[
        "masonry",
        "contractor"
    ],
    "wof:name":"N M Bauman & Sons",
    "wof:placetype":"venue"
},
  "geometry": {"coordinates":[-80.5027008057,43.7297935486],"type":"Point"}
}