{
  "type": "Feature",
  "properties": {
    "iso:country":"CA",
    "sg:address":"59 Rue Nelder",
    "sg:city":"Morin-Heights",
    "sg:classifiers":[
        {
            "category":"Manufacturing",
            "subcategory":"Tools & Machinery",
            "type":"Manufacturing & Wholesale Goods"
        }
    ],
    "sg:phone":"+1 450 226 6997",
    "sg:postcode":"J0R 1H0",
    "sg:province":"QC",
    "sg:tags":[
        "equipment",
        "electric"
    ],
    "wof:name":"Z-Trauq Inc",
    "wof:placetype":"venue"
},
  "geometry": {"coordinates":[-74.27313232420001,45.9218177795],"type":"Point"}
}