{
  "type": "Feature",
  "properties": {
    "addr:full":"Berwick ON K0C 1G0",
    "addr:postcode":"k0c 1g0",
    "iso:country":"CA",
    "sg:city":"Berwick",
    "sg:classifiers":[
        {
            "category":"Retail",
            "subcategory":"Repair Shop",
            "type":"Services"
        }
    ],
    "sg:phone":"+1 613 987 2747",
    "sg:postcode":"K0C 1G0",
    "sg:province":"ON",
    "sg:tags":[
        "welding"
    ],
    "wof:name":"Berny's Welding & Fabricating",
    "wof:placetype":"venue"
},
  "geometry": {"coordinates":[-75.110741,45.177551],"type":"Point"}
}