{
  "type": "Feature",
  "properties": {
    "addr:full":"61 Baywood Rd Etobicoke ON M9V 3Y8",
    "addr:housenumber":"61",
    "addr:postcode":"m9v 3y8",
    "addr:street":"Baywood Rd",
    "iso:country":"CA",
    "sg:address":"61 Baywood Rd",
    "sg:city":"Etobicoke",
    "sg:classifiers":[
        {
            "category":"Wholesale",
            "subcategory":"Chemicals & Plastics",
            "type":"Manufacturing & Wholesale Goods"
        }
    ],
    "sg:phone":"+1 416 740 3080",
    "sg:postcode":"M9V 3Y8",
    "sg:province":"ON",
    "wof:name":"Idn Registry Inc",
    "wof:placetype":"venue"
},
  "geometry": {"coordinates":[-79.6063613892,43.747833252],"type":"Point"}
}