{
  "type": "Feature",
  "properties": {
    "iso:country":"CA",
    "sg:address":"1009 Coxwell Ave",
    "sg:city":"East York",
    "sg:classifiers":[
        {
            "category":"Government",
            "subcategory":"Office",
            "type":"Public Place"
        }
    ],
    "sg:phone":"+1 416 423 5213",
    "sg:postcode":"M4C 3G4",
    "sg:province":"ON",
    "wof:name":"Ontario Lcbo Permit Issuing",
    "wof:placetype":"venue"
},
  "geometry": {"coordinates":[-79.3288574219,43.6966629028],"type":"Point"}
}