{
  "type": "Feature",
  "properties": {
    "addr:full":"216 Bay St # 3 Thunder Bay ON P7B 1R2",
    "addr:housenumber":"216",
    "addr:postcode":"p7b 1r2",
    "addr:street":"Bay St # 3",
    "iso:country":"CA",
    "sg:address":"216 Bay St # 3",
    "sg:city":"Thunder Bay",
    "sg:classifiers":[
        {
            "category":"Personal",
            "subcategory":"Beauty Salon",
            "type":"Services"
        }
    ],
    "sg:phone":"+1 807 343 9454",
    "sg:postcode":"P7B 1R2",
    "sg:province":"ON",
    "wof:name":"Rose's High Styling Beauty Sln",
    "wof:placetype":"venue"
},
  "geometry": {"coordinates":[-89.225266,48.43],"type":"Point"}
}