{
  "type": "Feature",
  "properties": {
    "iso:country":"CA",
    "sg:address":"5025 Yonge St",
    "sg:city":"North York",
    "sg:classifiers":[
        {
            "category":"Shopping",
            "subcategory":"Optical Goods",
            "type":"Retail Goods"
        }
    ],
    "sg:phone":"+1 416 225 0362",
    "sg:postcode":"M2N 5P2",
    "sg:province":"ON",
    "sg:tags":[
        "optician"
    ],
    "wof:name":"Optic Creations Ltd",
    "wof:placetype":"venue"
},
  "geometry": {"coordinates":[-79.412109375,43.7666702271],"type":"Point"}
}