{
  "type": "Feature",
  "properties": {
    "addr:full":"2715 14th Ave Markham ON L3R 0H9",
    "addr:housenumber":"2715",
    "addr:postcode":"l3r 0h9",
    "addr:street":"14Th Ave",
    "iso:country":"CA",
    "sg:address":"2715 14th Ave",
    "sg:city":"Markham",
    "sg:classifiers":[
        {
            "category":"Shopping",
            "type":"Retail Goods"
        }
    ],
    "sg:phone":"+1 905 470 9066",
    "sg:postcode":"L3R 0H9",
    "sg:province":"ON",
    "sg:tags":[
        "whirlpool",
        "equipment",
        "bath",
        "supply"
    ],
    "wof:name":"Tubco Whirlpool Ltd",
    "wof:placetype":"venue"
},
  "geometry": {"coordinates":[-79.360123,43.829651],"type":"Point"}
}