{
  "type": "Feature",
  "properties": {
    "addr:full":"161 Main St NW Roblin MB R0L 1P0",
    "addr:housenumber":"161",
    "addr:postcode":"roblin;r0l 1p0",
    "addr:street":"Main St Nw",
    "iso:country":"CA",
    "sg:address":"161 Main St NW",
    "sg:city":"Roblin",
    "sg:classifiers":[
        {
            "category":"Banks & Credit Unions",
            "subcategory":"Investment Brokerage",
            "type":"Services"
        }
    ],
    "sg:phone":"+1 204 937 4299",
    "sg:postcode":"R0L 1P0",
    "sg:province":"MB",
    "wof:name":"Wellington West Financial",
    "wof:placetype":"venue"
},
  "geometry": {"coordinates":[-101.35105896,51.2308731079],"type":"Point"}
}