{
  "type": "Feature",
  "properties": {
    "addr:full":"Wingham ON N0G 2W0",
    "addr:postcode":"n0g 2w0",
    "iso:country":"CA",
    "sg:city":"Wingham",
    "sg:classifiers":[
        {
            "category":"Personal",
            "subcategory":"Beauty Salon",
            "type":"Services"
        }
    ],
    "sg:phone":"+1 519 357 2211",
    "sg:postcode":"N0G 2W0",
    "sg:province":"ON",
    "wof:name":"Crystal's Aesthetics",
    "wof:placetype":"venue"
},
  "geometry": {"coordinates":[-81.31207999999999,43.887634],"type":"Point"}
}