{
  "type": "Feature",
  "properties": {
    "addr:full":"257 Rue Rachel E Montreal QC H2W 1E5",
    "addr:housenumber":"257",
    "addr:postcode":"h2w 1e5",
    "addr:street":"Rue Rachel E",
    "iso:country":"CA",
    "sg:address":"257 Rue Rachel E",
    "sg:city":"Montreal",
    "sg:classifiers":[
        {
            "category":"Retail",
            "subcategory":"Repair Shop",
            "type":"Services"
        }
    ],
    "sg:phone":"+1 514 289 0849",
    "sg:postcode":"H2W 1E5",
    "sg:province":"QC",
    "sg:tags":[
        "violin",
        "musical",
        "maker"
    ],
    "wof:name":"Wilder & Davis Luthiers Inc",
    "wof:placetype":"venue"
},
  "geometry": {"coordinates":[-73.57957500000001,45.520451],"type":"Point"}
}