{
  "type": "Feature",
  "properties": {
    "iso:country":"CA",
    "sg:address":"1101 Rue Vincent-Massey",
    "sg:city":"Laval",
    "sg:classifiers":[
        {
            "category":"Social Services",
            "type":"Services"
        }
    ],
    "sg:phone":"+1 450 686 0363",
    "sg:postcode":"H7V 3N3",
    "sg:province":"QC",
    "sg:tags":[
        "organization",
        "welfare"
    ],
    "wof:name":"Arret DE Laval Inc",
    "wof:placetype":"venue"
},
  "geometry": {"coordinates":[-73.750526,45.545204],"type":"Point"}
}