{
  "type": "Feature",
  "properties": {
    "addr:full":"100 Edinburgh Rd N Guelph ON N1H 5R3",
    "addr:housenumber":"100",
    "addr:postcode":"n1h 5r3",
    "addr:street":"Edinburgh Rd N",
    "iso:country":"CA",
    "sg:address":"100 Edinburgh Rd N",
    "sg:city":"Guelph",
    "sg:classifiers":[
        {
            "category":"Shopping",
            "subcategory":"Optical Goods",
            "type":"Retail Goods"
        }
    ],
    "sg:phone":"+1 519 836 0470",
    "sg:postcode":"N1H 5R3",
    "sg:province":"ON",
    "sg:tags":[
        "optician"
    ],
    "wof:name":"Cardow Optical",
    "wof:placetype":"venue"
},
  "geometry": {"coordinates":[-80.26194,43.54007],"type":"Point"}
}