{
  "type": "Feature",
  "properties": {
    "iso:country":"CA",
    "sg:address":"7435 Av Louis-Hebert",
    "sg:city":"Montreal",
    "sg:classifiers":[
        {
            "category":"Wholesale",
            "subcategory":"Stationery",
            "type":"Manufacturing & Wholesale Goods"
        }
    ],
    "sg:phone":"+1 514 374 9284",
    "sg:postcode":"H2E 2X5",
    "sg:province":"QC",
    "wof:name":"Mancini & Assocs Inc",
    "wof:placetype":"venue"
},
  "geometry": {"coordinates":[-73.60627746580001,45.5548553467],"type":"Point"}
}