{
  "type": "Feature",
  "properties": {
    "addr:full":"1018 Deep Cove Rd North Vancouver BC V7G 1S3",
    "addr:housenumber":"1018",
    "addr:postcode":"v7g 1s3",
    "addr:street":"Deep Cove Rd",
    "iso:country":"CA",
    "sg:address":"1018 Deep Cove Rd",
    "sg:city":"North Vancouver",
    "sg:classifiers":[
        {
            "category":"Retail",
            "subcategory":"Veterinary Services",
            "type":"Services"
        }
    ],
    "sg:phone":"+1 604 929 7367",
    "sg:postcode":"V7G 1S3",
    "sg:province":"BC",
    "sg:tags":[
        "veterinarian"
    ],
    "wof:name":"Seymour Animal Care Clinic",
    "wof:placetype":"venue"
},
  "geometry": {"coordinates":[-122.953384399,49.3161010742],"type":"Point"}
}