{
  "type": "Feature",
  "properties": {
    "addr:full":"934 Rosser Ave Brandon MB R7A 0L4",
    "addr:housenumber":"934",
    "addr:postcode":"r7a 0l4",
    "addr:street":"Rosser Ave",
    "iso:country":"CA",
    "sg:address":"934 Rosser Ave",
    "sg:city":"Brandon",
    "sg:classifiers":[
        {
            "category":"Shopping",
            "subcategory":"Gifts & Souvenirs",
            "type":"Retail Goods"
        }
    ],
    "sg:phone":"+1 204 727 8630",
    "sg:postcode":"R7A 0L4",
    "sg:province":"MB",
    "sg:tags":[
        "shop"
    ],
    "wof:name":"Cinnamon Tree",
    "wof:placetype":"venue"
},
  "geometry": {"coordinates":[-99.95060700000001,49.848263],"type":"Point"}
}