{
  "type": "Feature",
  "properties": {
    "addr:full":"1910 Glenaire Dr North Vancouver BC V7P 1Y1",
    "addr:housenumber":"1910",
    "addr:postcode":"v7p 1y1",
    "addr:street":"Glenaire Dr",
    "iso:country":"CA",
    "sg:address":"1910 Glenaire Dr",
    "sg:city":"North Vancouver",
    "sg:classifiers":[
        {
            "category":"Recreation",
            "type":"Entertainment"
        }
    ],
    "sg:phone":"+1 604 980 6738",
    "sg:postcode":"V7P 1Y1",
    "sg:province":"BC",
    "sg:tags":[
        "club",
        "organization",
        "sport",
        "rugby"
    ],
    "wof:name":"Capilano Rugby Clubhouse",
    "wof:placetype":"venue"
},
  "geometry": {"coordinates":[-123.124374,49.327724],"type":"Point"}
}