{
  "type": "Feature",
  "properties": {
    "addr:full":"3704 66 St NW Calgary AB T3B 2H9",
    "addr:housenumber":"3704",
    "addr:postcode":"t3b 2h9",
    "addr:street":"66 St Nw",
    "iso:country":"CA",
    "sg:address":"3704 66 St NW",
    "sg:city":"Calgary",
    "sg:classifiers":[
        {
            "category":"Professional",
            "subcategory":"Accounting & Tax Preparation",
            "type":"Services"
        }
    ],
    "sg:phone":"+1 403 247 8984",
    "sg:postcode":"T3B 2H9",
    "sg:province":"AB",
    "sg:tags":[
        "bookkeeping",
        "general"
    ],
    "wof:name":"Double M Accounting & Scrtrl",
    "wof:placetype":"venue"
},
  "geometry": {"coordinates":[-114.186630249,51.0871505737],"type":"Point"}
}