{
  "type": "Feature",
  "properties": {
    "addr:full":"76 Hidden Ridge Close NW Calgary AB T3A 5L6",
    "addr:housenumber":"76",
    "addr:postcode":"t3a 5l6",
    "addr:street":"Hidden Ridge Close Nw",
    "iso:country":"CA",
    "sg:address":"76 Hidden Ridge Close NW",
    "sg:city":"Calgary",
    "sg:classifiers":[
        {
            "category":"Professional",
            "subcategory":"Accounting & Tax Preparation",
            "type":"Services"
        }
    ],
    "sg:phone":"+1 403 274 1514",
    "sg:postcode":"T3A 5L6",
    "sg:province":"AB",
    "sg:tags":[
        "accountant"
    ],
    "wof:name":"Murray Business Svc Ltd",
    "wof:placetype":"venue"
},
  "geometry": {"coordinates":[-114.113769531,51.1502342224],"type":"Point"}
}