{
  "type": "Feature",
  "properties": {
    "addr:full":"14-16 Railroad Bay L'Argent NL A0E 1B0",
    "addr:housenumber":"14-16",
    "addr:postcode":"a0e 1b0",
    "addr:street":"Railroad Bay",
    "iso:country":"CA",
    "sg:address":"14-16 Railroad",
    "sg:city":"Bay L'Argent",
    "sg:classifiers":[
        {
            "category":"Government",
            "subcategory":"Office",
            "type":"Public Place"
        }
    ],
    "sg:phone":"+1 709 461 2606",
    "sg:postcode":"A0E 1B0",
    "sg:province":"NL",
    "sg:tags":[
        "village"
    ],
    "wof:name":"Bay L'Argent Town Hall",
    "wof:placetype":"venue"
},
  "geometry": {"coordinates":[-59.170185,47.582825],"type":"Point"}
}