{
  "type": "Feature",
  "properties": {
    "addr:full":"76 Rue Duranceau Chateauguay QC J6J 2T1",
    "addr:housenumber":"76",
    "addr:postcode":"j6j 2t1",
    "addr:street":"Rue Duranceau",
    "iso:country":"CA",
    "sg:address":"76 Rue Duranceau",
    "sg:city":"Chateauguay",
    "sg:classifiers":[
        {
            "category":"Home & Garden",
            "subcategory":"Household Appliances",
            "type":"Retail Goods"
        }
    ],
    "sg:phone":"+1 450 698 1256",
    "sg:postcode":"J6J 2T1",
    "sg:province":"QC",
    "wof:name":"Electro Menager Chateauguay",
    "wof:placetype":"venue"
},
  "geometry": {"coordinates":[-73.76181800000001,45.375946],"type":"Point"}
}