{
  "type": "Feature",
  "properties": {
    "addr:full":"26 Boul DE Bromont Bromont QC J2L 2K3",
    "addr:housenumber":"26",
    "addr:postcode":"j2l 2k3",
    "addr:street":"Boul De Bromont",
    "iso:country":"CA",
    "sg:address":"26 Boul DE Bromont",
    "sg:city":"Bromont",
    "sg:classifiers":[
        {
            "category":"Building & Trades",
            "subcategory":"Construction",
            "type":"Services"
        }
    ],
    "sg:phone":"+1 450 534 1785",
    "sg:postcode":"J2L 2K3",
    "sg:province":"QC",
    "sg:tags":[
        "general",
        "contractor"
    ],
    "wof:name":"Construction Mayton & Assoc",
    "wof:placetype":"venue"
},
  "geometry": {"coordinates":[-72.64877300000001,45.330093],"type":"Point"}
}