{
  "type": "Feature",
  "properties": {
    "addr:full":"8702 113 St Grande Prairie AB T8V 6K5",
    "addr:housenumber":"8702",
    "addr:postcode":"t8v 6k5",
    "addr:street":"113 St",
    "iso:country":"CA",
    "sg:address":"8702 113 St",
    "sg:city":"Grande Prairie",
    "sg:classifiers":[
        {
            "category":"Home & Garden",
            "subcategory":"Furniture",
            "type":"Retail Goods"
        }
    ],
    "sg:phone":"+1 780 532 0236",
    "sg:postcode":"T8V 6K5",
    "sg:province":"AB",
    "wof:name":"Swan Industries",
    "wof:placetype":"venue"
},
  "geometry": {"coordinates":[-118.837929,55.157967],"type":"Point"}
}