{
  "type": "Feature",
  "properties": {
    "addr:full":"277 Menzies St Victoria BC V8V 2G6",
    "addr:housenumber":"277",
    "addr:postcode":"v8v 2g6",
    "addr:street":"Menzies St",
    "iso:country":"CA",
    "sg:address":"277 Menzies St",
    "sg:city":"Victoria",
    "sg:classifiers":[
        {
            "category":"Personal",
            "subcategory":"Beauty Salon",
            "type":"Services"
        }
    ],
    "sg:phone":"+1 250 385 3061",
    "sg:postcode":"V8V 2G6",
    "sg:province":"BC",
    "wof:name":"Gary's Hair Place",
    "wof:placetype":"venue"
},
  "geometry": {"coordinates":[-123.373016357,48.416633606],"type":"Point"}
}