{
  "type": "Feature",
  "properties": {
    "addr:full":"190 Rue Du Centre Magog QC J1X 5P8",
    "addr:housenumber":"190",
    "addr:postcode":"j1x 5p8",
    "addr:street":"Rue Du Centre",
    "iso:country":"CA",
    "sg:address":"190 Rue Du Centre",
    "sg:city":"Magog",
    "sg:classifiers":[
        {
            "category":"Professional",
            "subcategory":"Testing Lab",
            "type":"Services"
        }
    ],
    "sg:phone":"+1 819 843 3443",
    "sg:postcode":"J1X 5P8",
    "sg:province":"QC",
    "sg:tags":[
        "laboratory"
    ],
    "wof:name":"Laboratoire Lti",
    "wof:placetype":"venue"
},
  "geometry": {"coordinates":[-72.127213,45.276314],"type":"Point"}
}