{
  "type": "Feature",
  "properties": {
    "iso:country":"CA",
    "sg:address":"7535 Rue Saint-Denis",
    "sg:city":"Montreal",
    "sg:classifiers":[
        {
            "category":"Communications",
            "subcategory":"Film & Video Production",
            "type":"Services"
        }
    ],
    "sg:phone":"+1 514 948 2000",
    "sg:postcode":"H2R 2E7",
    "sg:province":"QC",
    "sg:tags":[
        "motion",
        "picture",
        "casting"
    ],
    "wof:name":"Andrea Kenyon Casting Assoc",
    "wof:placetype":"venue"
},
  "geometry": {"coordinates":[-73.620834,45.540333],"type":"Point"}
}