{
  "type": "Feature",
  "properties": {
    "addr:full":"Wishart Pt Tabusintac NB E9H 1Z5",
    "addr:postcode":"e9h 1z5",
    "addr:street":"Wishart Pt Tabusintac",
    "iso:country":"CA",
    "sg:address":"Wishart Pt",
    "sg:city":"Tabusintac",
    "sg:classifiers":[
        {
            "category":"Organizations",
            "subcategory":"Professional Association",
            "type":"Services"
        }
    ],
    "sg:phone":"+1 506 779 9228",
    "sg:postcode":"E9H 1Z5",
    "sg:province":"NB",
    "sg:tags":[
        "club"
    ],
    "wof:name":"Tabusintac Club",
    "wof:placetype":"venue"
},
  "geometry": {"coordinates":[-65.0107040405,47.3284454346],"type":"Point"}
}