{
  "type": "Feature",
  "properties": {
    "iso:country":"CA",
    "sg:address":"2004 Blackwell Rd",
    "sg:city":"Sarnia",
    "sg:classifiers":[
        {
            "category":"Building & Trades",
            "subcategory":"Construction",
            "type":"Services"
        }
    ],
    "sg:phone":"+1 519 542 4361",
    "sg:postcode":"N7T 7H4",
    "sg:province":"ON",
    "sg:tags":[
        "general",
        "contractor"
    ],
    "wof:name":"Fazio Construction Ltd",
    "wof:placetype":"venue"
},
  "geometry": {"coordinates":[-82.2971878052,43.0220756531],"type":"Point"}
}