{
  "type": "Feature",
  "properties": {
    "iso:country":"CA",
    "sg:address":"218 Rue Dorchester",
    "sg:city":"Bromont",
    "sg:classifiers":[
        {
            "category":"Personal",
            "type":"Services"
        }
    ],
    "sg:phone":"+1 450 534 2570",
    "sg:postcode":"J2L 1R2",
    "sg:province":"QC",
    "sg:tags":[
        "therapist",
        "massage"
    ],
    "wof:name":"Salon DE L'Electrolyse",
    "wof:placetype":"venue"
},
  "geometry": {"coordinates":[-72.63121032710001,45.2962265015],"type":"Point"}
}