{
  "type": "Feature",
  "properties": {
    "addr:full":"Vancouver BC V6Z 2M2",
    "addr:postcode":"v6z 2m2",
    "iso:country":"CA",
    "sg:city":"Vancouver",
    "sg:classifiers":[
        {
            "category":"Restaurant",
            "type":"Food & Drink"
        }
    ],
    "sg:phone":"+1 604 605 3888",
    "sg:postcode":"V6Z 2M2",
    "sg:province":"BC",
    "sg:tags":[
        "shop",
        "coffee"
    ],
    "wof:name":"Prego Coffee & Deli",
    "wof:placetype":"venue"
},
  "geometry": {"coordinates":[-123.13365899999999,49.274872],"type":"Point"}
}