{
  "type": "Feature",
  "properties": {
    "addr:full":"816 Regional Road 3 E Selkirk ON N0A 1P0",
    "addr:housenumber":"816",
    "addr:postcode":"n0a 1p0",
    "addr:street":"Regional Road 3 E",
    "iso:country":"CA",
    "sg:address":"816 Regional Road 3 E",
    "sg:city":"Selkirk",
    "sg:classifiers":[
        {
            "category":"Retail",
            "subcategory":"Repair Shop",
            "type":"Services"
        }
    ],
    "sg:phone":"+1 905 776 2620",
    "sg:postcode":"N0A 1P0",
    "sg:province":"ON",
    "sg:tags":[
        "welding"
    ],
    "wof:name":"A Swent & Sons Ltd",
    "wof:placetype":"venue"
},
  "geometry": {"coordinates":[-79.932076,42.834236],"type":"Point"}
}