{
  "type": "Feature",
  "properties": {
    "addr:full":"1400 Onondaga St Oromocto NB E2V 2H6",
    "addr:housenumber":"1400",
    "addr:postcode":"e2v 2h6",
    "addr:street":"Onondaga St",
    "iso:country":"CA",
    "sg:address":"1400 Onondaga St",
    "sg:city":"Oromocto",
    "sg:classifiers":[
        {
            "category":"Wholesale",
            "subcategory":"Meat",
            "type":"Manufacturing & Wholesale Goods"
        }
    ],
    "sg:phone":"+1 506 357 8862",
    "sg:postcode":"E2V 2H6",
    "sg:province":"NB",
    "wof:name":"Mulder's Meat Ltd",
    "wof:placetype":"venue"
},
  "geometry": {"coordinates":[-66.472443,45.852852],"type":"Point"}
}