{
  "type": "Feature",
  "properties": {
    "iso:country":"CA",
    "sg:city":"Toronto",
    "sg:classifiers":[
        {
            "category":"Professional",
            "subcategory":"Management & Consulting",
            "type":"Services"
        }
    ],
    "sg:phone":"+1 416 482 2248",
    "sg:postcode":"M4P 1J5",
    "sg:province":"ON",
    "sg:tags":[
        "communications",
        "consultant"
    ],
    "wof:name":"Veritas Communications Inc",
    "wof:placetype":"venue"
},
  "geometry": {"coordinates":[-79.39250183110001,43.7078514099],"type":"Point"}
}