{
  "type": "Feature",
  "properties": {
    "addr:full":"Schreiber ON P0T 2S0",
    "addr:postcode":"p0t 2s0",
    "iso:country":"CA",
    "sg:city":"Schreiber",
    "sg:classifiers":[
        {
            "category":"Government",
            "subcategory":"Office",
            "type":"Public Place"
        }
    ],
    "sg:phone":"+1 807 826 3227",
    "sg:postcode":"P0T 2S0",
    "sg:province":"ON",
    "sg:tags":[
        "village"
    ],
    "wof:name":"Manitouwadge Building Depart",
    "wof:placetype":"venue"
},
  "geometry": {"coordinates":[-87.2664718628,48.8138656616],"type":"Point"}
}