{
  "type": "Feature",
  "properties": {
    "iso:country":"CA",
    "sg:city":"Barrie",
    "sg:classifiers":[
        {
            "category":"Restaurant",
            "type":"Food & Drink"
        }
    ],
    "sg:phone":"+1 705 739 7830",
    "sg:postcode":"L4M 6E5",
    "sg:province":"ON",
    "sg:tags":[
        "baker"
    ],
    "wof:name":"Great Canadian Bagel",
    "wof:placetype":"venue"
},
  "geometry": {"coordinates":[-79.7065200806,44.4084625244],"type":"Point"}
}