{
  "type": "Feature",
  "properties": {
    "addr:full":"301 Oxford St W London ON N6H 1S6",
    "addr:housenumber":"301",
    "addr:postcode":"n6h 1s6",
    "addr:street":"Oxford St W",
    "iso:country":"CA",
    "sg:address":"301 Oxford St W",
    "sg:city":"London",
    "sg:classifiers":[
        {
            "category":"Restaurant",
            "type":"Food & Drink"
        }
    ],
    "sg:phone":"+1 519 434 1141",
    "sg:postcode":"N6H 1S6",
    "sg:province":"ON",
    "wof:name":"Chinese Court",
    "wof:placetype":"venue"
},
  "geometry": {"coordinates":[-81.2755813599,42.9889984131],"type":"Point"}
}