{
  "type": "Feature",
  "properties": {
    "addr:full":"233 1st St E North Vancouver BC V7L 1B4",
    "addr:housenumber":"233",
    "addr:postcode":"v7l 1b4",
    "addr:street":"1St St E",
    "iso:country":"CA",
    "sg:address":"233 1st St E",
    "sg:city":"North Vancouver",
    "sg:classifiers":[
        {
            "category":"Manufacturing",
            "subcategory":"Pottery",
            "type":"Manufacturing & Wholesale Goods"
        }
    ],
    "sg:phone":"+1 604 987 9434",
    "sg:postcode":"V7L 1B4",
    "sg:province":"BC",
    "wof:name":"Boma Manufacturing",
    "wof:placetype":"venue"
},
  "geometry": {"coordinates":[-123.074577331,49.3099594116],"type":"Point"}
}