{
  "type": "Feature",
  "properties": {
    "addr:full":"Morewood ON K0A 2R0",
    "addr:postcode":"k0a 2r0",
    "addr:street":"Morewood",
    "iso:country":"CA",
    "sg:city":"Morewood",
    "sg:classifiers":[
        {
            "category":"Education",
            "subcategory":"Library",
            "type":"Public Place"
        }
    ],
    "sg:phone":"+1 613 448 3822",
    "sg:postcode":"K0A 2R0",
    "sg:province":"ON",
    "wof:name":"Morewood Public Library",
    "wof:placetype":"venue"
},
  "geometry": {"coordinates":[-75.286278,45.177135],"type":"Point"}
}