{
  "type": "Feature",
  "properties": {
    "iso:country":"CA",
    "sg:city":"North York",
    "sg:classifiers":[
        {
            "category":"Organizations",
            "subcategory":"Professional Association",
            "type":"Services"
        }
    ],
    "sg:phone":"+1 416 444 7473",
    "sg:postcode":"M3A 3R3",
    "sg:province":"ON",
    "wof:name":"East York Scarborough Reading",
    "wof:placetype":"venue"
},
  "geometry": {"coordinates":[-79.3218460083,43.7408790588],"type":"Point"}
}