{
  "type": "Feature",
  "properties": {
    "addr:full":"Powell River BC V8A 2K2",
    "addr:postcode":"v8a 2k2",
    "iso:country":"CA",
    "sg:city":"Powell River",
    "sg:classifiers":[
        {
            "category":"Professional",
            "subcategory":"Lawyer & Legal Services",
            "type":"Services"
        }
    ],
    "sg:phone":"+1 604 485 6188",
    "sg:postcode":"V8A 2K2",
    "sg:province":"BC",
    "sg:tags":[
        "attorney"
    ],
    "wof:name":"Villani, Robert D",
    "wof:placetype":"venue"
},
  "geometry": {"coordinates":[-124.526977539,49.8365364075],"type":"Point"}
}