{
  "type": "Feature",
  "properties": {
    "iso:country":"CA",
    "sg:city":"Calgary",
    "sg:classifiers":[
        {
            "category":"Communications",
            "subcategory":"Film & Video Production",
            "type":"Services"
        }
    ],
    "sg:phone":"+1 403 269 7771",
    "sg:postcode":"T2G 3G1",
    "sg:province":"AB",
    "sg:tags":[
        "taping"
    ],
    "wof:name":"Digital Magic & F/X",
    "wof:placetype":"venue"
},
  "geometry": {"coordinates":[-114.03704834,51.0374107361],"type":"Point"}
}