{
  "type": "Feature",
  "properties": {
    "addr:full":"15 Forest Wood North York ON M5N 2V5",
    "addr:housenumber":"15",
    "addr:postcode":"m5n 2v5",
    "addr:street":"Forest Wood",
    "iso:country":"CA",
    "sg:address":"15 Forest Wood",
    "sg:city":"North York",
    "sg:classifiers":[
        {
            "category":"Shopping",
            "type":"Retail Goods"
        }
    ],
    "sg:phone":"+1 416 782 3005",
    "sg:postcode":"M5N 2V5",
    "sg:province":"ON",
    "sg:tags":[
        "antique",
        "art",
        "gallery",
        "dealer"
    ],
    "wof:name":"Pende Fine Arts",
    "wof:placetype":"venue"
},
  "geometry": {"coordinates":[-79.426247,43.711994],"type":"Point"}
}