{
  "type": "Feature",
  "properties": {
    "addr:full":"1275 Great Northern Rd RR 2 Sault Ste Marie ON P6A 5K7",
    "addr:housenumber":"1275",
    "addr:postcode":"p6a 5k7",
    "addr:street":"Great Northern Rd;2",
    "iso:country":"CA",
    "sg:address":"1275 Great Northern Rd RR 2",
    "sg:city":"Sault Ste Marie",
    "sg:classifiers":[
        {
            "category":"Travel",
            "subcategory":"Hotels & Motels",
            "type":"Entertainment"
        }
    ],
    "sg:phone":"+1 705 759 6199",
    "sg:postcode":"P6A 5K7",
    "sg:province":"ON",
    "wof:name":"Ambassador Motel",
    "wof:placetype":"venue"
},
  "geometry": {"coordinates":[-84.3209075928,46.5656166077],"type":"Point"}
}