{
  "type": "Feature",
  "properties": {
    "addr:full":"2673 Alta Vista Dr Ottawa ON K1V 7T5",
    "addr:housenumber":"2673",
    "addr:postcode":"k1v 7t5",
    "addr:street":"Alta Vista Dr",
    "iso:country":"CA",
    "sg:address":"2673 Alta Vista Dr",
    "sg:city":"Ottawa",
    "sg:classifiers":[
        {
            "category":"Personal",
            "subcategory":"Beauty Salon",
            "type":"Services"
        }
    ],
    "sg:phone":"+1 613 526 9811",
    "sg:postcode":"K1V 7T5",
    "sg:province":"ON",
    "wof:name":"Select One Nail",
    "wof:placetype":"venue"
},
  "geometry": {"coordinates":[-75.662941,45.37326],"type":"Point"}
}