{
  "type": "Feature",
  "properties": {
    "addr:full":"471 Pefferlaw Rd Pefferlaw ON L0E 1N0",
    "addr:housenumber":"471",
    "addr:postcode":"l0e 1n0",
    "addr:street":"Pefferlaw Rd",
    "iso:country":"CA",
    "sg:address":"471 Pefferlaw Rd",
    "sg:city":"Pefferlaw",
    "sg:classifiers":[
        {
            "category":"Organizations",
            "subcategory":"Religious Organization",
            "type":"Services"
        }
    ],
    "sg:phone":"+1 705 437 2170",
    "sg:postcode":"L0E 1N0",
    "sg:province":"ON",
    "sg:tags":[
        "church"
    ],
    "wof:name":"Church of the Nazarene",
    "wof:placetype":"venue"
},
  "geometry": {"coordinates":[-79.21486663819999,44.3215789795],"type":"Point"}
}