{
  "type": "Feature",
  "properties": {
    "addr:full":"1402 Railway Ave Canmore AB T1W 1P6",
    "addr:housenumber":"1402",
    "addr:postcode":"t1w 1p6",
    "addr:street":"Railway Ave",
    "iso:country":"CA",
    "sg:address":"1402 Railway Ave",
    "sg:city":"Canmore",
    "sg:classifiers":[
        {
            "category":"Building & Trades",
            "subcategory":"Construction",
            "type":"Services"
        }
    ],
    "sg:phone":"+1 403 678 0775",
    "sg:postcode":"T1W 1P6",
    "sg:province":"AB",
    "sg:tags":[
        "resurfacing",
        "material",
        "laying",
        "refinishing",
        "floor"
    ],
    "wof:name":"Timber Town Building Ctr",
    "wof:placetype":"venue"
},
  "geometry": {"coordinates":[-115.358543396,51.0940895081],"type":"Point"}
}