{
  "type": "Feature",
  "properties": {
    "addr:full":"Grande Prairie AB T8V 5V4",
    "addr:postcode":"t8v 5v4",
    "iso:country":"CA",
    "sg:city":"Grande Prairie",
    "sg:classifiers":[
        {
            "category":"Real Estate",
            "subcategory":"Architect",
            "type":"Services"
        }
    ],
    "sg:phone":"+1 780 532 3690",
    "sg:postcode":"T8V 5V4",
    "sg:province":"AB",
    "wof:name":"Field Field & Field Architects",
    "wof:placetype":"venue"
},
  "geometry": {"coordinates":[-118.789756775,55.1714401245],"type":"Point"}
}