{
  "type": "Feature",
  "properties": {
    "iso:country":"CA",
    "sg:address":"838 Rue DE L'Ontario",
    "sg:city":"Sherbrooke",
    "sg:classifiers":[
        {
            "category":"Social Services",
            "subcategory":"Child Care",
            "type":"Services"
        }
    ],
    "sg:phone":"+1 819 563 8755",
    "sg:postcode":"J1J 3S2",
    "sg:province":"QC",
    "wof:name":"Cpe Chez Les Amis Inc",
    "wof:placetype":"venue"
},
  "geometry": {"coordinates":[-71.908058,45.399338],"type":"Point"}
}