{
  "type": "Feature",
  "properties": {
    "addr:full":"Waterloo ON N2V 2B2",
    "addr:postcode":"n2v 2b2",
    "iso:country":"CA",
    "sg:city":"Waterloo",
    "sg:classifiers":[
        {
            "category":"Manufacturing",
            "subcategory":"Tools & Machinery",
            "type":"Manufacturing & Wholesale Goods"
        }
    ],
    "sg:phone":"+1 519 746 0009",
    "sg:postcode":"N2V 2B2",
    "sg:province":"ON",
    "sg:tags":[
        "equipment",
        "system",
        "automation"
    ],
    "wof:name":"Tethco Technologies",
    "wof:placetype":"venue"
},
  "geometry": {"coordinates":[-80.52758799999999,43.512375],"type":"Point"}
}