{
  "type": "Feature",
  "properties": {
    "addr:full":"Sexsmith AB T0H 3C0",
    "addr:postcode":"t0h 3c0",
    "iso:country":"CA",
    "sg:city":"Sexsmith",
    "sg:classifiers":[
        {
            "category":"Farming",
            "subcategory":"Nursery",
            "type":"Manufacturing & Wholesale Goods"
        }
    ],
    "sg:phone":"+1 780 568 3400",
    "sg:postcode":"T0H 3C0",
    "sg:province":"AB",
    "sg:tags":[
        "fertilizer",
        "greenhouse"
    ],
    "wof:name":"Agricore United",
    "wof:placetype":"venue"
},
  "geometry": {"coordinates":[-118.780762,55.345112],"type":"Point"}
}