{
  "type": "Feature",
  "properties": {
    "iso:country":"CA",
    "sg:city":"Vancouver",
    "sg:classifiers":[
        {
            "category":"Shopping",
            "subcategory":"Clothing, Apparel, & Fashions",
            "type":"Retail Goods"
        }
    ],
    "sg:phone":"+1 604 328 3817",
    "sg:postcode":"V6M 3W8",
    "sg:province":"BC",
    "sg:tags":[
        "theatrical",
        "costume"
    ],
    "wof:name":"Costumes on A Shoestring",
    "wof:placetype":"venue"
},
  "geometry": {"coordinates":[-123.155792236,49.2342453003],"type":"Point"}
}