{
  "type": "Feature",
  "properties": {
    "addr:full":"812 Rue DE LA Madone Mont-Laurier QC J9L 1T5",
    "addr:housenumber":"812",
    "addr:postcode":"j9l 1t5",
    "addr:street":"Rue De La Madone",
    "iso:country":"CA",
    "sg:address":"812 Rue DE LA Madone",
    "sg:city":"Mont-Laurier",
    "sg:classifiers":[
        {
            "category":"Food & Beverages",
            "subcategory":"Groceries & Convenience Stores",
            "type":"Retail Goods"
        }
    ],
    "sg:phone":"+1 819 623 2574",
    "sg:postcode":"J9L 1T5",
    "sg:province":"QC",
    "wof:name":"Depanneur Jules Bonisoir",
    "wof:placetype":"venue"
},
  "geometry": {"coordinates":[-75.49251599999999,46.557663],"type":"Point"}
}