{
  "type": "Feature",
  "properties": {
    "addr:full":"Etobicoke ON M8Y 1L5",
    "addr:postcode":"m8y 1l5",
    "iso:country":"CA",
    "sg:city":"Etobicoke",
    "sg:classifiers":[
        {
            "category":"Personal",
            "subcategory":"Beauty Salon",
            "type":"Services"
        }
    ],
    "sg:phone":"+1 416 255 7848",
    "sg:postcode":"M8Y 1L5",
    "sg:province":"ON",
    "wof:name":"Hairway",
    "wof:placetype":"venue"
},
  "geometry": {"coordinates":[-79.502182,43.626572],"type":"Point"}
}