{
  "type": "Feature",
  "properties": {
    "addr:full":"4084 31st Ave W Vancouver BC V6S 1Y6",
    "addr:housenumber":"4084",
    "addr:postcode":"v6s 1y6",
    "addr:street":"31St Ave W",
    "iso:country":"CA",
    "sg:address":"4084 31st Ave W",
    "sg:city":"Vancouver",
    "sg:classifiers":[
        {
            "category":"Wholesale",
            "subcategory":"Electrical",
            "type":"Manufacturing & Wholesale Goods"
        }
    ],
    "sg:phone":"+1 604 222 0188",
    "sg:postcode":"V6S 1Y6",
    "sg:province":"BC",
    "sg:tags":[
        "control",
        "recorder",
        "time"
    ],
    "wof:name":"Valtech Information Systems",
    "wof:placetype":"venue"
},
  "geometry": {"coordinates":[-123.19600699999999,49.244114],"type":"Point"}
}