{
  "type": "Feature",
  "properties": {
    "addr:full":"Scarborough ON M1H 3G3",
    "addr:postcode":"m1h 3g3",
    "iso:country":"CA",
    "sg:city":"Scarborough",
    "sg:classifiers":[
        {
            "category":"Professional",
            "subcategory":"Lawyer & Legal Services",
            "type":"Services"
        }
    ],
    "sg:phone":"+1 416 438 7500",
    "sg:postcode":"M1H 3G3",
    "sg:province":"ON",
    "sg:tags":[
        "attorney"
    ],
    "wof:name":"Scott M Cook Law Offices",
    "wof:placetype":"venue"
},
  "geometry": {"coordinates":[-79.236176,43.781151],"type":"Point"}
}