{
  "type": "Feature",
  "properties": {
    "addr:full":"1295 12th Ave E Vancouver BC V5T 2J8",
    "addr:housenumber":"1295",
    "addr:postcode":"v5t 2j8",
    "addr:street":"12Th Ave E",
    "iso:country":"CA",
    "sg:address":"1295 12th Ave E",
    "sg:city":"Vancouver",
    "sg:classifiers":[
        {
            "category":"Food & Beverages",
            "subcategory":"Groceries & Convenience Stores",
            "type":"Retail Goods"
        }
    ],
    "sg:phone":"+1 604 874 5314",
    "sg:postcode":"V5T 2J8",
    "sg:province":"BC",
    "sg:tags":[
        "grocer"
    ],
    "wof:name":"Shell Select",
    "wof:placetype":"venue"
},
  "geometry": {"coordinates":[-123.078003,49.259769],"type":"Point"}
}