{
  "type": "Feature",
  "properties": {
    "iso:country":"CA",
    "sg:city":"London",
    "sg:classifiers":[
        {
            "category":"Health Services",
            "subcategory":"Doctor",
            "type":"Services"
        }
    ],
    "sg:phone":"+1 519 685 8470",
    "sg:postcode":"N6C 2R6",
    "sg:province":"ON",
    "sg:tags":[
        "physician",
        "surgeon"
    ],
    "wof:name":"Payton, Keith MD",
    "wof:placetype":"venue"
},
  "geometry": {"coordinates":[-81.225449,42.962093],"type":"Point"}
}