{
  "type": "Feature",
  "properties": {
    "iso:country":"CA",
    "sg:address":"5000 Boul Metropolitain E",
    "sg:city":"Saint-Leonard",
    "sg:classifiers":[
        {
            "category":"Shopping",
            "subcategory":"Pharmacy",
            "type":"Retail Goods"
        }
    ],
    "sg:phone":"+1 514 725 1212",
    "sg:postcode":"H1S 3G7",
    "sg:province":"QC",
    "wof:name":"Uniprix Inc",
    "wof:placetype":"venue"
},
  "geometry": {"coordinates":[-73.591835022,45.5786437988],"type":"Point"}
}