{
  "type": "Feature",
  "properties": {
    "iso:country":"CA",
    "sg:address":"460 19E Av",
    "sg:city":"Lachine",
    "sg:classifiers":[
        {
            "category":"Manufacturing",
            "subcategory":"Printing",
            "type":"Manufacturing & Wholesale Goods"
        }
    ],
    "sg:phone":"+1 514 634 4290",
    "sg:postcode":"H8S 3S2",
    "sg:province":"QC",
    "sg:tags":[
        "printer"
    ],
    "wof:name":"Docupro",
    "wof:placetype":"venue"
},
  "geometry": {"coordinates":[-73.68115234379999,45.4369621277],"type":"Point"}
}