{
  "type": "Feature",
  "properties": {
    "addr:full":"1870 Burnhamthorpe Rd E Mississauga ON L4X 2S5",
    "addr:housenumber":"1870",
    "addr:postcode":"l4x 2s5",
    "addr:street":"Burnhamthorpe Rd E",
    "iso:country":"CA",
    "sg:address":"1870 Burnhamthorpe Rd E",
    "sg:city":"Mississauga",
    "sg:classifiers":[
        {
            "category":"Organizations",
            "subcategory":"Religious Organization",
            "type":"Services"
        }
    ],
    "sg:phone":"+1 905 625 5670",
    "sg:postcode":"L4X 2S5",
    "sg:province":"ON",
    "sg:tags":[
        "church"
    ],
    "wof:name":"Saints Martha & Mary Church",
    "wof:placetype":"venue"
},
  "geometry": {"coordinates":[-79.5917892456,43.6320571899],"type":"Point"}
}