{
  "type": "Feature",
  "properties": {
    "addr:full":"108 Marshall St Barrie ON L4N 4L5",
    "addr:housenumber":"108",
    "addr:postcode":"l4n 4l5",
    "addr:street":"Marshall St",
    "iso:country":"CA",
    "sg:address":"108 Marshall St",
    "sg:city":"Barrie",
    "sg:classifiers":[
        {
            "category":"Professional",
            "subcategory":"Accounting & Tax Preparation",
            "type":"Services"
        }
    ],
    "sg:phone":"+1 705 737 0798",
    "sg:postcode":"L4N 4L5",
    "sg:province":"ON",
    "sg:tags":[
        "accountant"
    ],
    "wof:name":"Doering, Dennis J CA",
    "wof:placetype":"venue"
},
  "geometry": {"coordinates":[-79.69026947019999,44.3598442078],"type":"Point"}
}