{
  "type": "Feature",
  "properties": {
    "addr:full":"1651 Nash Rd Courtice ON L1E 1S8",
    "addr:housenumber":"1651",
    "addr:postcode":"l1e 1s8",
    "addr:street":"Nash Rd",
    "iso:country":"CA",
    "sg:address":"1651 Nash Rd",
    "sg:city":"Courtice",
    "sg:classifiers":[
        {
            "category":"Real Estate",
            "subcategory":"Real Estate Operator",
            "type":"Services"
        }
    ],
    "sg:phone":"+1 905 432 1172",
    "sg:postcode":"L1E 1S8",
    "sg:province":"ON",
    "sg:tags":[
        "condominium"
    ],
    "wof:name":"Newcastle Condominium Corp #5",
    "wof:placetype":"venue"
},
  "geometry": {"coordinates":[-78.78949,43.913944],"type":"Point"}
}