{
  "type": "Feature",
  "properties": {
    "addr:full":"1550 Rue Robinson Laval QC H7W 2W2",
    "addr:housenumber":"1550",
    "addr:postcode":"h7w 2w2",
    "addr:street":"Rue Robinson",
    "iso:country":"CA",
    "sg:address":"1550 Rue Robinson",
    "sg:city":"Laval",
    "sg:classifiers":[
        {
            "category":"Health Services",
            "subcategory":"Doctor",
            "type":"Services"
        }
    ],
    "sg:phone":"+1 450 688 6405",
    "sg:postcode":"H7W 2W2",
    "sg:province":"QC",
    "sg:tags":[
        "clinic"
    ],
    "wof:name":"Clinique DE Dermatologie Laval",
    "wof:placetype":"venue"
},
  "geometry": {"coordinates":[-73.7586135864,45.5493812561],"type":"Point"}
}