{
  "type": "Feature",
  "properties": {
    "addr:full":"7280 Hwy 69 S Mactier ON P0C 1H0",
    "addr:housenumber":"7280",
    "addr:postcode":"p0c 1h0",
    "addr:street":"Hwy 69 S Mactier",
    "iso:country":"CA",
    "sg:address":"7280 Hwy 69 S",
    "sg:city":"Mactier",
    "sg:classifiers":[
        {
            "category":"Restaurant",
            "type":"Food & Drink"
        }
    ],
    "sg:phone":"+1 705 375 2963",
    "sg:postcode":"P0C 1H0",
    "sg:province":"ON",
    "wof:name":"Sunys Gas Bar",
    "wof:placetype":"venue"
},
  "geometry": {"coordinates":[-79.7760314941,45.10887146],"type":"Point"}
}