{
  "type": "Feature",
  "properties": {
    "iso:country":"CA",
    "sg:address":"759 Pape Ave",
    "sg:city":"Toronto",
    "sg:classifiers":[
        {
            "category":"Professional",
            "subcategory":"Art Services",
            "type":"Services"
        }
    ],
    "sg:phone":"+1 416 462 2748",
    "sg:postcode":"M4K 3T2",
    "sg:province":"ON",
    "sg:tags":[
        "graphic",
        "designer"
    ],
    "wof:name":"Charis Graphic Design",
    "wof:placetype":"venue"
},
  "geometry": {"coordinates":[-79.3452987671,43.6806678772],"type":"Point"}
}