{
  "type": "Feature",
  "properties": {
    "addr:full":"Girouxville AB T0H 1S0",
    "addr:postcode":"t0h 1s0",
    "iso:country":"CA",
    "sg:city":"Girouxville",
    "sg:classifiers":[
        {
            "category":"Freight",
            "type":"Transportation"
        }
    ],
    "sg:phone":"+1 780 323 4224",
    "sg:postcode":"T0H 1S0",
    "sg:province":"AB",
    "sg:tags":[
        "grocer",
        "courier"
    ],
    "wof:name":"Greyhound Lines of Canada Ltd",
    "wof:placetype":"venue"
},
  "geometry": {"coordinates":[-117.33807373,55.7540855408],"type":"Point"}
}