{
  "type": "Feature",
  "properties": {
    "addr:full":"RR 2 Shelburne ON L0N 1S6",
    "addr:postcode":"l0n 1s6",
    "addr:street":"Rr 2",
    "iso:country":"CA",
    "sg:address":"RR 2",
    "sg:city":"Shelburne",
    "sg:classifiers":[
        {
            "category":"Wholesale",
            "subcategory":"Fruits & Vegetables",
            "type":"Manufacturing & Wholesale Goods"
        }
    ],
    "sg:phone":"+1 519 925 3209",
    "sg:postcode":"L0N 1S6",
    "sg:province":"ON",
    "wof:name":"Dufferin Potato Storage",
    "wof:placetype":"venue"
},
  "geometry": {"coordinates":[-80.20208700000001,44.078785],"type":"Point"}
}