{
  "type": "Feature",
  "properties": {
    "addr:full":"Wainwright AB T9W 1P5",
    "addr:postcode":"t9w 1p5",
    "iso:country":"CA",
    "sg:city":"Wainwright",
    "sg:classifiers":[
        {
            "category":"Insurance",
            "subcategory":"Insurance Agent",
            "type":"Services"
        }
    ],
    "sg:phone":"+1 780 842 4357",
    "sg:postcode":"T9W 1P5",
    "sg:province":"AB",
    "wof:name":"CO-Operators General Insurance",
    "wof:placetype":"venue"
},
  "geometry": {"coordinates":[-110.859176636,52.8353424072],"type":"Point"}
}