{
  "type": "Feature",
  "properties": {
    "iso:country":"CA",
    "sg:address":"46 Melgund Rd",
    "sg:city":"Toronto",
    "sg:classifiers":[
        {
            "category":"Sports & Exercise",
            "subcategory":"Bowling",
            "type":"Entertainment"
        }
    ],
    "sg:phone":"+1 416 533 0242",
    "sg:postcode":"M5R 3M7",
    "sg:province":"ON",
    "sg:tags":[
        "center"
    ],
    "wof:name":"Wells Hill Lawn Bowling",
    "wof:placetype":"venue"
},
  "geometry": {"coordinates":[-79.4170227051,43.6821975708],"type":"Point"}
}