{
  "type": "Feature",
  "properties": {
    "iso:country":"CA",
    "sg:address":"3168 Boul Industriel",
    "sg:city":"Laval",
    "sg:classifiers":[
        {
            "category":"Home & Garden",
            "subcategory":"Building Materials",
            "type":"Retail Goods"
        }
    ],
    "sg:phone":"+1 450 668 8086",
    "sg:postcode":"H7L 4P7",
    "sg:province":"QC",
    "sg:tags":[
        "equipment",
        "electric",
        "supply"
    ],
    "wof:name":"Asc Futech Inc",
    "wof:placetype":"venue"
},
  "geometry": {"coordinates":[-73.743637085,45.5911979675],"type":"Point"}
}