{
  "type": "Feature",
  "properties": {
    "addr:full":"Laval QC H7M 2Y6",
    "addr:postcode":"h7m 2y6",
    "iso:country":"CA",
    "sg:city":"Laval",
    "sg:classifiers":[
        {
            "category":"Shopping",
            "type":"Retail Goods"
        }
    ],
    "sg:phone":"+1 450 975 1188",
    "sg:postcode":"H7M 2Y6",
    "sg:province":"QC",
    "sg:tags":[
        "art",
        "gallery",
        "association",
        "dealer"
    ],
    "wof:name":"Galerie Verticale Art Cont",
    "wof:placetype":"venue"
},
  "geometry": {"coordinates":[-73.71163900000001,45.587337],"type":"Point"}
}