{
  "type": "Feature",
  "properties": {
    "addr:full":"1071 Cote Du Beaver Hall Montreal QC H2Z 1S5",
    "addr:housenumber":"1071",
    "addr:postcode":"h2z 1s5",
    "addr:street":"Cote Du Beaver Hall",
    "iso:country":"CA",
    "sg:address":"1071 Cote Du Beaver Hall",
    "sg:city":"Montreal",
    "sg:classifiers":[
        {
            "category":"Bars & Pubs",
            "type":"Food & Drink"
        }
    ],
    "sg:phone":"+1 514 866 4963",
    "sg:postcode":"H2Z 1S5",
    "sg:province":"QC",
    "sg:tags":[
        "lounge",
        "cocktail"
    ],
    "wof:name":"West Side Bar",
    "wof:placetype":"venue"
},
  "geometry": {"coordinates":[-73.56476600000001,45.50246],"type":"Point"}
}