{
  "type": "Feature",
  "properties": {
    "addr:full":"203 Dundas St London ON N6A 1G4",
    "addr:housenumber":"203",
    "addr:postcode":"n6a 1g4",
    "addr:street":"Dundas St",
    "iso:country":"CA",
    "sg:address":"203 Dundas St",
    "sg:city":"London",
    "sg:classifiers":[
        {
            "category":"Museum",
            "type":"Entertainment"
        }
    ],
    "sg:phone":"+1 519 642 2767",
    "sg:postcode":"N6A 1G4",
    "sg:province":"ON",
    "sg:tags":[
        "organization",
        "arts",
        "association",
        "information"
    ],
    "wof:name":"Arts Project",
    "wof:placetype":"venue"
},
  "geometry": {"coordinates":[-81.248108,42.984013],"type":"Point"}
}