{
  "type": "Feature",
  "properties": {
    "addr:full":"408 13 St N Lethbridge AB T1H 2S2",
    "addr:housenumber":"408 13",
    "addr:postcode":"t1h 2s2",
    "addr:street":"St N",
    "iso:country":"CA",
    "sg:address":"408 13 St N",
    "sg:city":"Lethbridge",
    "sg:classifiers":[
        {
            "category":"Organizations",
            "subcategory":"Professional Association",
            "type":"Services"
        }
    ],
    "sg:phone":"+1 403 328 3246",
    "sg:postcode":"T1H 2S2",
    "sg:province":"AB",
    "sg:tags":[
        "club"
    ],
    "wof:name":"A A Club",
    "wof:placetype":"venue"
},
  "geometry": {"coordinates":[-112.82429500000001,49.704838],"type":"Point"}
}