{
  "type": "Feature",
  "properties": {
    "iso:country":"CA",
    "sg:city":"Falher",
    "sg:classifiers":[
        {
            "category":"Government",
            "subcategory":"Office",
            "type":"Public Place"
        }
    ],
    "sg:phone":"+1 780 837 2433",
    "sg:postcode":"T0H 1M0",
    "sg:province":"AB",
    "wof:name":"Alberta Provincial Courts",
    "wof:placetype":"venue"
},
  "geometry": {"coordinates":[-117.201897,55.741131],"type":"Point"}
}