{
  "type": "Feature",
  "properties": {
    "addr:full":"238 4th St Estevan SK S4A 0T6",
    "addr:housenumber":"238",
    "addr:postcode":"s4a 0t6",
    "addr:street":"4Th St",
    "iso:country":"CA",
    "sg:address":"238 4th St",
    "sg:city":"Estevan",
    "sg:classifiers":[
        {
            "category":"Retail",
            "subcategory":"Car Wash",
            "type":"Services"
        }
    ],
    "sg:phone":"+1 306 634 6276",
    "sg:postcode":"S4A 0T6",
    "sg:province":"SK",
    "sg:tags":[
        "polishing",
        "automobile",
        "washing",
        "lubrication"
    ],
    "wof:name":"Fast Track Auto Care Ltd",
    "wof:placetype":"venue"
},
  "geometry": {"coordinates":[-102.97585296600001,49.1330757141],"type":"Point"}
}