{
  "type": "Feature",
  "properties": {
    "addr:full":"Burlington ON L7L 5Y9",
    "addr:postcode":"l7l 5y9",
    "iso:country":"CA",
    "sg:city":"Burlington",
    "sg:classifiers":[
        {
            "category":"Home & Garden",
            "subcategory":"Home Furnishings",
            "type":"Retail Goods"
        }
    ],
    "sg:phone":"+1 905 336 5341",
    "sg:postcode":"L7L 5Y9",
    "sg:province":"ON",
    "sg:tags":[
        "venetian",
        "blind",
        "made",
        "drapery"
    ],
    "wof:name":"Blind Advantage",
    "wof:placetype":"venue"
},
  "geometry": {"coordinates":[-79.7651672363,43.3798980713],"type":"Point"}
}