{
  "type": "Feature",
  "properties": {
    "addr:full":"1288 Ritson Rd N Oshawa ON L1G 7Z9",
    "addr:housenumber":"1288",
    "addr:postcode":"l1g 7z9",
    "addr:street":"Ritson Rd N",
    "iso:country":"CA",
    "sg:address":"1288 Ritson Rd N",
    "sg:city":"Oshawa",
    "sg:classifiers":[
        {
            "category":"Travel",
            "subcategory":"Travel Agent",
            "type":"Entertainment"
        }
    ],
    "sg:phone":"+1 905 438 8888",
    "sg:postcode":"L1G 7Z9",
    "sg:province":"ON",
    "sg:tags":[
        "agency",
        "bureau"
    ],
    "wof:name":"Bel Air Travel",
    "wof:placetype":"venue"
},
  "geometry": {"coordinates":[-78.868454,43.933029],"type":"Point"}
}