{
  "type": "Feature",
  "properties": {
    "iso:country":"CA",
    "sg:address":"693 Av Meloche",
    "sg:city":"Dorval",
    "sg:classifiers":[
        {
            "category":"Professional",
            "subcategory":"Computer Services",
            "type":"Services"
        }
    ],
    "sg:phone":"+1 514 631 4341",
    "sg:postcode":"H9P 2S4",
    "sg:province":"QC",
    "sg:tags":[
        "electronics"
    ],
    "wof:name":"Fabrication Dec",
    "wof:placetype":"venue"
},
  "geometry": {"coordinates":[-73.727547,45.455853],"type":"Point"}
}