{
  "type": "Feature",
  "properties": {
    "addr:full":"4050 2nd Ave W Prince Albert SK S6W 1A2",
    "addr:housenumber":"4050",
    "addr:postcode":"s6w 1a2",
    "addr:street":"2Nd Ave W",
    "iso:country":"CA",
    "sg:address":"4050 2nd Ave W",
    "sg:city":"Prince Albert",
    "sg:classifiers":[
        {
            "category":"Food & Beverages",
            "subcategory":"Groceries & Convenience Stores",
            "type":"Retail Goods"
        }
    ],
    "sg:phone":"+1 306 763 1522",
    "sg:postcode":"S6W 1A2",
    "sg:province":"SK",
    "sg:tags":[
        "grocer"
    ],
    "wof:name":"Sunspun Shopping Svc",
    "wof:placetype":"venue"
},
  "geometry": {"coordinates":[-105.76020813,53.1749610901],"type":"Point"}
}