{
  "type": "Feature",
  "properties": {
    "addr:full":"2570 Argyle Rd Mississauga ON L5B 1V2",
    "addr:housenumber":"2570",
    "addr:postcode":"l5b 1v2",
    "addr:street":"Argyle Rd",
    "iso:country":"CA",
    "sg:address":"2570 Argyle Rd",
    "sg:city":"Mississauga",
    "sg:classifiers":[
        {
            "category":"Shopping",
            "subcategory":"Discount & Variety Stores",
            "type":"Retail Goods"
        }
    ],
    "sg:phone":"+1 905 277 1697",
    "sg:postcode":"L5B 1V2",
    "sg:province":"ON",
    "wof:name":"Centennial Towers Variety Str",
    "wof:placetype":"venue"
},
  "geometry": {"coordinates":[-79.6205825806,43.5748977661],"type":"Point"}
}