{
  "type": "Feature",
  "properties": {
    "addr:full":"503 1st Ave Maple Creek SK S0N 1N0",
    "addr:housenumber":"503",
    "addr:postcode":"s0n 1n0",
    "addr:street":"1St Ave",
    "iso:country":"CA",
    "sg:address":"503 1st Ave",
    "sg:city":"Maple Creek",
    "sg:classifiers":[
        {
            "category":"Personal",
            "subcategory":"Beauty Salon",
            "type":"Services"
        }
    ],
    "sg:phone":"+1 306 662 2348",
    "sg:postcode":"S0N 1N0",
    "sg:province":"SK",
    "wof:name":"Haillo Beauty Salon",
    "wof:placetype":"venue"
},
  "geometry": {"coordinates":[-109.480407715,49.9065856934],"type":"Point"}
}