{
  "type": "Feature",
  "properties": {
    "iso:country":"CA",
    "sg:city":"Sherbrooke",
    "sg:classifiers":[
        {
            "category":"Professional",
            "subcategory":"Engineering",
            "type":"Services"
        }
    ],
    "sg:phone":"+1 819 346 6484",
    "sg:postcode":"J1E 2S2",
    "sg:province":"QC",
    "sg:tags":[
        "engineer"
    ],
    "wof:name":"Groupe Genitiqu Inc",
    "wof:placetype":"venue"
},
  "geometry": {"coordinates":[-71.8760757446,45.4143829346],"type":"Point"}
}