{
  "type": "Feature",
  "properties": {
    "addr:full":"9019 Shaughnessy St Vancouver BC V6P 6R9",
    "addr:housenumber":"9019",
    "addr:postcode":"v6p 6r9",
    "addr:street":"Shaughnessy St",
    "iso:country":"CA",
    "sg:address":"9019 Shaughnessy St",
    "sg:city":"Vancouver",
    "sg:classifiers":[
        {
            "category":"Autos & Motor Vehicles",
            "subcategory":"Motorcycle Sales",
            "type":"Retail Goods"
        }
    ],
    "sg:phone":"+1 604 301 3755",
    "sg:postcode":"V6P 6R9",
    "sg:province":"BC",
    "sg:tags":[
        "scooter"
    ],
    "wof:name":"Qrp Distributing",
    "wof:placetype":"venue"
},
  "geometry": {"coordinates":[-123.128211975,49.203338623],"type":"Point"}
}