{
  "type": "Feature",
  "properties": {
    "addr:full":"1494 Baseline Rd Ottawa ON K2C 0B2",
    "addr:housenumber":"1494",
    "addr:postcode":"k2c 0b2",
    "addr:street":"Baseline Rd",
    "iso:country":"CA",
    "sg:address":"1494 Baseline Rd",
    "sg:city":"Ottawa",
    "sg:classifiers":[
        {
            "category":"Personal",
            "subcategory":"Beauty Salon",
            "type":"Services"
        }
    ],
    "sg:phone":"+1 613 225 5725",
    "sg:postcode":"K2C 0B2",
    "sg:province":"ON",
    "wof:name":"Jean's Hair Creations",
    "wof:placetype":"venue"
},
  "geometry": {"coordinates":[-75.74202728269999,45.3602218628],"type":"Point"}
}