{
  "type": "Feature",
  "properties": {
    "addr:full":"475 Conestogo Rd Waterloo ON N2L 4C9",
    "addr:housenumber":"475",
    "addr:postcode":"n2l 4c9",
    "addr:street":"Conestogo Rd",
    "iso:country":"CA",
    "sg:address":"475 Conestogo Rd",
    "sg:city":"Waterloo",
    "sg:classifiers":[
        {
            "category":"Manufacturing",
            "subcategory":"Metals",
            "type":"Manufacturing & Wholesale Goods"
        }
    ],
    "sg:phone":"+1 519 886 6290",
    "sg:postcode":"N2L 4C9",
    "sg:province":"ON",
    "sg:tags":[
        "finisher"
    ],
    "wof:name":"Latem Industries Ltd",
    "wof:placetype":"venue"
},
  "geometry": {"coordinates":[-80.532776,43.495693],"type":"Point"}
}