{
  "type": "Feature",
  "properties": {
    "addr:full":"705 1st Ave NW Weyburn SK S4H 1P4",
    "addr:housenumber":"705",
    "addr:postcode":"s4h 1p4",
    "addr:street":"1St Ave Nw",
    "iso:country":"CA",
    "sg:address":"705 1st Ave NW",
    "sg:city":"Weyburn",
    "sg:classifiers":[
        {
            "category":"Health Services",
            "subcategory":"Nursing And Care Facility",
            "type":"Services"
        }
    ],
    "sg:phone":"+1 306 848 0490",
    "sg:postcode":"S4H 1P4",
    "sg:province":"SK",
    "sg:tags":[
        "personal",
        "home"
    ],
    "wof:name":"Doris Happy Care Home-Seniors",
    "wof:placetype":"venue"
},
  "geometry": {"coordinates":[-103.866722,49.668365],"type":"Point"}
}