{
  "type": "Feature",
  "properties": {
    "addr:full":"210 Burrows Ave W Melfort SK S0E 1A0",
    "addr:housenumber":"210",
    "addr:postcode":"s0e 1a0",
    "addr:street":"Burrows Ave W Melfort",
    "iso:country":"CA",
    "sg:address":"210 Burrows Ave W",
    "sg:city":"Melfort",
    "sg:classifiers":[
        {
            "category":"Banks & Credit Unions",
            "subcategory":"Investment Brokerage",
            "type":"Services"
        }
    ],
    "sg:phone":"+1 306 752 9351",
    "sg:postcode":"S0E 1A0",
    "sg:province":"SK",
    "wof:name":"Cherry Financial Svc",
    "wof:placetype":"venue"
},
  "geometry": {"coordinates":[-104.613746643,52.8614463806],"type":"Point"}
}