{
  "type": "Feature",
  "properties": {
    "addr:full":"Ottawa ON K1G 4G5",
    "addr:postcode":"k1g 4g5",
    "iso:country":"CA",
    "sg:city":"Ottawa",
    "sg:classifiers":[
        {
            "category":"Real Estate",
            "subcategory":"Developer",
            "type":"Services"
        }
    ],
    "sg:phone":"+1 613 737 7100",
    "sg:postcode":"K1G 4G5",
    "sg:province":"ON",
    "wof:name":"Commerce City Investments Ltd",
    "wof:placetype":"venue"
},
  "geometry": {"coordinates":[-75.6357269287,45.4080314636],"type":"Point"}
}