{
  "type": "Feature",
  "properties": {
    "addr:full":"1 Maritime Ontario Blvd Brampton ON L6S 6G4",
    "addr:housenumber":"1",
    "addr:postcode":"l6s 6g4",
    "addr:street":"Maritime Ontario Blvd",
    "iso:country":"CA",
    "sg:address":"1 Maritime Ontario Blvd",
    "sg:city":"Brampton",
    "sg:classifiers":[
        {
            "category":"Freight",
            "type":"Transportation"
        }
    ],
    "sg:phone":"+1 905 453 3072",
    "sg:postcode":"L6S 6G4",
    "sg:province":"ON",
    "sg:tags":[
        "trucking"
    ],
    "wof:name":"Group VA",
    "wof:placetype":"venue"
},
  "geometry": {"coordinates":[-79.6932220459,43.7466659546],"type":"Point"}
}