{
  "type": "Feature",
  "properties": {
    "addr:full":"4586 96 St Delta BC V4K 3N3",
    "addr:housenumber":"4586",
    "addr:postcode":"v4k 3n3",
    "addr:street":"96 St",
    "iso:country":"CA",
    "sg:address":"4586 96 St",
    "sg:city":"Delta",
    "sg:classifiers":[
        {
            "category":"Recreation",
            "type":"Entertainment"
        }
    ],
    "sg:phone":"+1 604 594 8465",
    "sg:postcode":"V4K 3N3",
    "sg:province":"BC",
    "sg:tags":[
        "stable"
    ],
    "wof:name":"Cambridge Stables",
    "wof:placetype":"venue"
},
  "geometry": {"coordinates":[-122.956863403,49.0848388672],"type":"Point"}
}