{
  "type": "Feature",
  "properties": {
    "iso:country":"CA",
    "sg:address":"390 Boul Des Mille-Iles E",
    "sg:city":"Sainte-Therese",
    "sg:classifiers":[
        {
            "category":"Professional",
            "subcategory":"Lawyer & Legal Services",
            "type":"Services"
        }
    ],
    "sg:phone":"+1 450 434 4652",
    "sg:postcode":"J7E 3Z9",
    "sg:province":"QC",
    "sg:tags":[
        "attorney"
    ],
    "wof:name":"Roy, Suzanne",
    "wof:placetype":"venue"
},
  "geometry": {"coordinates":[-73.8546829224,45.6491470337],"type":"Point"}
}