{
  "type": "Feature",
  "properties": {
    "addr:full":"Cine Valley Rd Grande Prairie AB T8V 4B5",
    "addr:postcode":"t8v 4b5",
    "addr:street":"Valley Rd",
    "iso:country":"CA",
    "sg:address":"Cine Valley Rd",
    "sg:city":"Grande Prairie",
    "sg:classifiers":[
        {
            "category":"Organizations",
            "subcategory":"Religious Organization",
            "type":"Services"
        }
    ],
    "sg:phone":"+1 780 532 3808",
    "sg:postcode":"T8V 4B5",
    "sg:province":"AB",
    "sg:tags":[
        "church"
    ],
    "wof:name":"Seventh Day Adventist Church",
    "wof:placetype":"venue"
},
  "geometry": {"coordinates":[-118.79489100000001,55.171162],"type":"Point"}
}