{
  "type": "Feature",
  "properties": {
    "addr:full":"361 Carrville Rd Richmond Hill ON L4C 6E4",
    "addr:housenumber":"361",
    "addr:postcode":"l4c 6e4",
    "addr:street":"Carrville Rd",
    "iso:country":"CA",
    "sg:address":"361 Carrville Rd",
    "sg:city":"Richmond Hill",
    "sg:classifiers":[
        {
            "category":"Personal",
            "subcategory":"Beauty Salon",
            "type":"Services"
        }
    ],
    "sg:phone":"+1 905 886 0740",
    "sg:postcode":"L4C 6E4",
    "sg:province":"ON",
    "wof:name":"Hair Designs By Mimma",
    "wof:placetype":"venue"
},
  "geometry": {"coordinates":[-79.4439086914,43.8505516052],"type":"Point"}
}