{
  "type": "Feature",
  "properties": {
    "iso:country":"CA",
    "sg:address":"2806 County Rd 8",
    "sg:city":"Campbellford",
    "sg:classifiers":[
        {
            "category":"Shopping",
            "subcategory":"Discount & Variety Stores",
            "type":"Retail Goods"
        }
    ],
    "sg:phone":"+1 705 653 0601",
    "sg:postcode":"K0L 1L0",
    "sg:province":"ON",
    "wof:name":"Station Variety",
    "wof:placetype":"venue"
},
  "geometry": {"coordinates":[-77.797492981,44.309211731],"type":"Point"}
}