{
  "type": "Feature",
  "properties": {
    "iso:country":"CA",
    "sg:address":"11871 No. 3 Rd",
    "sg:city":"Richmond",
    "sg:classifiers":[
        {
            "category":"Building & Trades",
            "subcategory":"Construction",
            "type":"Services"
        }
    ],
    "sg:phone":"+1 604 274 3831",
    "sg:postcode":"V7A 1X3",
    "sg:province":"BC",
    "sg:tags":[
        "excavating",
        "contractor"
    ],
    "wof:name":"Tempo Construction Ltd",
    "wof:placetype":"venue"
},
  "geometry": {"coordinates":[-123.136848,49.127026],"type":"Point"}
}