{
  "type": "Feature",
  "properties": {
    "iso:country":"CA",
    "sg:address":"360 Caradoc St S",
    "sg:city":"Strathroy",
    "sg:classifiers":[
        {
            "category":"Shopping",
            "subcategory":"Photographic Equipment",
            "type":"Retail Goods"
        }
    ],
    "sg:phone":"+1 519 245 3690",
    "sg:postcode":"N7G 2P6",
    "sg:province":"ON",
    "sg:tags":[
        "supply"
    ],
    "wof:name":"Carman's Foto Source",
    "wof:placetype":"venue"
},
  "geometry": {"coordinates":[-81.6136474609,42.9474983215],"type":"Point"}
}