{
  "type": "Feature",
  "properties": {
    "addr:full":"40 Rue Notre-Dame O Montreal QC H2Y 1S6",
    "addr:housenumber":"40",
    "addr:postcode":"h2y 1s6",
    "addr:street":"Rue Notre-Dame O",
    "iso:country":"CA",
    "sg:address":"40 Rue Notre-Dame O",
    "sg:city":"Montreal",
    "sg:classifiers":[
        {
            "category":"Shopping",
            "subcategory":"Gifts & Souvenirs",
            "type":"Retail Goods"
        }
    ],
    "sg:phone":"+1 514 982 0276",
    "sg:postcode":"H2Y 1S6",
    "sg:province":"QC",
    "sg:tags":[
        "shop"
    ],
    "wof:name":"Souvenir Notre Ville",
    "wof:placetype":"venue"
},
  "geometry": {"coordinates":[-73.55513000000001,45.506596],"type":"Point"}
}