{
  "type": "Feature",
  "properties": {
    "addr:full":"92 6 Ave NW Nakusp BC V0G 1R0",
    "addr:postcode":"v0g 1r0",
    "addr:street":"92 6 Ave Nw",
    "iso:country":"CA",
    "sg:address":"92 6 Ave NW",
    "sg:city":"Nakusp",
    "sg:classifiers":[
        {
            "category":"Museum",
            "type":"Entertainment"
        }
    ],
    "sg:phone":"+1 250 265 0015",
    "sg:postcode":"V0G 1R0",
    "sg:province":"BC",
    "wof:name":"Nakusp & District Museum",
    "wof:placetype":"venue"
},
  "geometry": {"coordinates":[-117.805351,50.240166],"type":"Point"}
}