{
  "type": "Feature",
  "properties": {
    "addr:full":"2308 Rue Duvernay Montreal QC H3J 2X1",
    "addr:housenumber":"2308",
    "addr:postcode":"h3j 2x1",
    "addr:street":"Rue Duvernay",
    "iso:country":"CA",
    "sg:address":"2308 Rue Duvernay",
    "sg:city":"Montreal",
    "sg:classifiers":[
        {
            "category":"Professional",
            "subcategory":"Management & Consulting",
            "type":"Services"
        }
    ],
    "sg:phone":"+1 514 937 1357",
    "sg:postcode":"H3J 2X1",
    "sg:province":"QC",
    "sg:tags":[
        "consultant",
        "business"
    ],
    "wof:name":"Carver Institute Inc",
    "wof:placetype":"venue"
},
  "geometry": {"coordinates":[-73.572594,45.483273],"type":"Point"}
}