{
  "type": "Feature",
  "properties": {
    "addr:full":"Newmarket ON L3Y 3S9",
    "addr:postcode":"l3y 3s9",
    "iso:country":"CA",
    "sg:city":"Newmarket",
    "sg:classifiers":[
        {
            "category":"Professional",
            "subcategory":"Lawyer & Legal Services",
            "type":"Services"
        }
    ],
    "sg:phone":"+1 905 853 4577",
    "sg:postcode":"L3Y 3S9",
    "sg:province":"ON",
    "sg:tags":[
        "attorney"
    ],
    "wof:name":"Bryan, Penelope",
    "wof:placetype":"venue"
},
  "geometry": {"coordinates":[-79.4538650513,44.0584526062],"type":"Point"}
}