{
  "type": "Feature",
  "properties": {
    "addr:full":"118 Pitt St Cornwall ON K6J 3P4",
    "addr:housenumber":"118",
    "addr:postcode":"k6j 3p4",
    "addr:street":"Pitt St",
    "iso:country":"CA",
    "sg:address":"118 Pitt St",
    "sg:city":"Cornwall",
    "sg:classifiers":[
        {
            "category":"Restaurant",
            "type":"Food & Drink"
        }
    ],
    "sg:phone":"+1 613 938 7311",
    "sg:postcode":"K6J 3P4",
    "sg:province":"ON",
    "wof:name":"Spinners Diner",
    "wof:placetype":"venue"
},
  "geometry": {"coordinates":[-74.72826385499999,45.0171432495],"type":"Point"}
}