{
  "type": "Feature",
  "properties": {
    "addr:full":"10609 124 St NW Edmonton AB T5N 1S5",
    "addr:housenumber":"10609",
    "addr:postcode":"t5n 1s5",
    "addr:street":"124 St Nw",
    "iso:country":"CA",
    "sg:address":"10609 124 St NW",
    "sg:city":"Edmonton",
    "sg:classifiers":[
        {
            "category":"Professional",
            "subcategory":"Management & Consulting",
            "type":"Services"
        }
    ],
    "sg:phone":"+1 780 428 1501",
    "sg:postcode":"T5N 1S5",
    "sg:province":"AB",
    "sg:tags":[
        "consultant",
        "business"
    ],
    "wof:name":"Western Management Consultants",
    "wof:placetype":"venue"
},
  "geometry": {"coordinates":[-113.53567504900001,53.5496330261],"type":"Point"}
}