{
  "type": "Feature",
  "properties": {
    "iso:country":"CA",
    "sg:address":"3661 Boul Dagenais O",
    "sg:city":"Laval",
    "sg:classifiers":[
        {
            "category":"Health Services",
            "subcategory":"Doctor",
            "type":"Services"
        }
    ],
    "sg:phone":"+1 450 625 7271",
    "sg:postcode":"H7P 5C9",
    "sg:province":"QC",
    "sg:tags":[
        "clinic",
        "chiropractor"
    ],
    "wof:name":"Centre Chiropratique Dagenais",
    "wof:placetype":"venue"
},
  "geometry": {"coordinates":[-73.817024231,45.5737876892],"type":"Point"}
}