{
  "type": "Feature",
  "properties": {
    "addr:full":"334 15E Rue Laval QC H7N 1L4",
    "addr:housenumber":"334",
    "addr:postcode":"h7n 1l4",
    "addr:street":"15E Rue",
    "iso:country":"CA",
    "sg:address":"334 15E Rue",
    "sg:city":"Laval",
    "sg:classifiers":[
        {
            "category":"Retail",
            "subcategory":"Laundry & Dry Cleaning",
            "type":"Services"
        }
    ],
    "sg:phone":"+1 450 967 9099",
    "sg:postcode":"H7N 1L4",
    "sg:province":"QC",
    "sg:tags":[
        "cleaners",
        "rug",
        "painter",
        "carpet"
    ],
    "wof:name":"Abc Entretien Normand Enr",
    "wof:placetype":"venue"
},
  "geometry": {"coordinates":[-73.6992721558,45.5598907471],"type":"Point"}
}