{
  "type": "Feature",
  "properties": {
    "addr:full":"3040 Rue Brochu LA Plaine QC J7M 2C1",
    "addr:housenumber":"3040",
    "addr:postcode":"j7m 2c1",
    "addr:street":"Rue Brochu",
    "iso:country":"CA",
    "sg:address":"3040 Rue Brochu",
    "sg:city":"LA Plaine",
    "sg:classifiers":[
        {
            "category":"Social Services",
            "subcategory":"Child Care",
            "type":"Services"
        }
    ],
    "sg:phone":"+1 450 478 0169",
    "sg:postcode":"J7M 2C1",
    "sg:province":"QC",
    "wof:name":"Garderie Les Poussinots",
    "wof:placetype":"venue"
},
  "geometry": {"coordinates":[-73.7080154419,45.7717094421],"type":"Point"}
}