{
  "type": "Feature",
  "properties": {
    "iso:country":"CA",
    "sg:address":"9250 Macleod Trail SE",
    "sg:city":"Calgary",
    "sg:classifiers":[
        {
            "category":"Home & Garden",
            "subcategory":"Furniture",
            "type":"Retail Goods"
        }
    ],
    "sg:phone":"+1 403 543 1066",
    "sg:postcode":"T2J 0P5",
    "sg:province":"AB",
    "sg:tags":[
        "infant",
        "wear"
    ],
    "wof:name":"Once Upon A Child",
    "wof:placetype":"venue"
},
  "geometry": {"coordinates":[-114.07125854500001,50.9710502625],"type":"Point"}
}