{
  "type": "Feature",
  "properties": {
    "addr:full":"2370 Norwood Rd Quesnel BC V2J 7G6",
    "addr:housenumber":"2370",
    "addr:postcode":"v2j 7g6",
    "addr:street":"Norwood Rd",
    "iso:country":"CA",
    "sg:address":"2370 Norwood Rd",
    "sg:city":"Quesnel",
    "sg:classifiers":[
        {
            "category":"Shopping",
            "type":"Retail Goods"
        }
    ],
    "sg:phone":"+1 250 249 5277",
    "sg:postcode":"V2J 7G6",
    "sg:province":"BC",
    "sg:tags":[
        "art",
        "gallery",
        "dealer"
    ],
    "wof:name":"Design Frames",
    "wof:placetype":"venue"
},
  "geometry": {"coordinates":[-122.498245239,52.9781188965],"type":"Point"}
}