{
  "type": "Feature",
  "properties": {
    "addr:full":"2043 Av Du Phare O Matane QC G4W 3M6",
    "addr:housenumber":"2043",
    "addr:postcode":"g4w 3m6",
    "addr:street":"Av Du Phare O",
    "iso:country":"CA",
    "sg:address":"2043 Av Du Phare O",
    "sg:city":"Matane",
    "sg:classifiers":[
        {
            "category":"Recreation",
            "type":"Entertainment"
        }
    ],
    "sg:phone":"+1 418 562 4218",
    "sg:postcode":"G4W 3M6",
    "sg:province":"QC",
    "sg:tags":[
        "stable"
    ],
    "wof:name":"Centre Equestre Du Phare Ouest",
    "wof:placetype":"venue"
},
  "geometry": {"coordinates":[-67.5896224976,48.8222618103],"type":"Point"}
}