{
  "type": "Feature",
  "properties": {
    "addr:full":"65 Van Horne Ave Dryden ON P8N 2B2",
    "addr:housenumber":"65",
    "addr:postcode":"p8n 2b2",
    "addr:street":"Van Horne Ave",
    "iso:country":"CA",
    "sg:address":"65 Van Horne Ave",
    "sg:city":"Dryden",
    "sg:classifiers":[
        {
            "category":"Retail",
            "subcategory":"Auto Repair",
            "type":"Services"
        }
    ],
    "sg:phone":"+1 807 221 2273",
    "sg:postcode":"P8N 2B2",
    "sg:province":"ON",
    "sg:tags":[
        "automobile",
        "rustproofing",
        "undercoating"
    ],
    "wof:name":"Rust Check",
    "wof:placetype":"venue"
},
  "geometry": {"coordinates":[-92.8361206055,49.7818946838],"type":"Point"}
}