{
  "type": "Feature",
  "properties": {
    "iso:country":"CA",
    "sg:address":"8921 Sodom Rd",
    "sg:city":"Niagara Falls",
    "sg:classifiers":[
        {
            "category":"Restaurant",
            "type":"Food & Drink"
        }
    ],
    "sg:phone":"+1 905 295 4436",
    "sg:postcode":"L2E 6S6",
    "sg:province":"ON",
    "wof:name":"Betty's Restaurant",
    "wof:placetype":"venue"
},
  "geometry": {"coordinates":[-79.05921936039999,43.0485801697],"type":"Point"}
}