{
  "type": "Feature",
  "properties": {
    "addr:full":"6000 Boul Henri-Bourassa E Montreal-Nord QC H1G 2T6",
    "addr:housenumber":"6000",
    "addr:postcode":"h1g 2t6",
    "addr:street":"Boul Henri-Bourassa E",
    "iso:country":"CA",
    "sg:address":"6000 Boul Henri-Bourassa E",
    "sg:city":"Montreal-Nord",
    "sg:classifiers":[
        {
            "category":"Shopping",
            "subcategory":"Clothing, Apparel, & Fashions",
            "type":"Retail Goods"
        }
    ],
    "sg:phone":"+1 514 322 1428",
    "sg:postcode":"H1G 2T6",
    "sg:province":"QC",
    "wof:name":"Lindor Inc",
    "wof:placetype":"venue"
},
  "geometry": {"coordinates":[-73.6173248291,45.6073951721],"type":"Point"}
}