{
  "type": "Feature",
  "properties": {
    "addr:full":"4020 Boul Grand Montreal QC H4B 2X5",
    "addr:housenumber":"4020",
    "addr:postcode":"h4b 2x5",
    "addr:street":"Boul Grand",
    "iso:country":"CA",
    "sg:address":"4020 Boul Grand",
    "sg:city":"Montreal",
    "sg:classifiers":[
        {
            "category":"Organizations",
            "subcategory":"Religious Organization",
            "type":"Services"
        }
    ],
    "sg:phone":"+1 514 486 5404",
    "sg:postcode":"H4B 2X5",
    "sg:province":"QC",
    "sg:tags":[
        "church"
    ],
    "wof:name":"St Ansgar Lutheran Church",
    "wof:placetype":"venue"
},
  "geometry": {"coordinates":[-73.625038,45.467197],"type":"Point"}
}