{
  "type": "Feature",
  "properties": {
    "addr:full":"61 Carium Rd Schumacher ON P0N 1G0",
    "addr:housenumber":"61",
    "addr:postcode":"p0n 1g0",
    "addr:street":"Carium Rd",
    "iso:country":"CA",
    "sg:address":"61 Carium Rd",
    "sg:city":"Schumacher",
    "sg:classifiers":[
        {
            "category":"Home & Garden",
            "subcategory":"Carpets & Floor Coverings",
            "type":"Retail Goods"
        }
    ],
    "sg:phone":"+1 705 268 1999",
    "sg:postcode":"P0N 1G0",
    "sg:province":"ON",
    "sg:tags":[
        "cleaners",
        "material",
        "rug"
    ],
    "wof:name":"Broker Mart",
    "wof:placetype":"venue"
},
  "geometry": {"coordinates":[-81.297302,48.47691],"type":"Point"}
}