{
  "type": "Feature",
  "properties": {
    "addr:full":"1035 Rue Yvon-Pichette Masson-Angers QC J8M 1T3",
    "addr:housenumber":"1035",
    "addr:postcode":"j8m 1t3",
    "addr:street":"Rue Yvon-Pichette",
    "iso:country":"CA",
    "sg:address":"1035 Rue Yvon-Pichette",
    "sg:city":"Masson-Angers",
    "sg:classifiers":[
        {
            "category":"Social Services",
            "subcategory":"Child Care",
            "type":"Services"
        }
    ],
    "sg:phone":"+1 819 281 5772",
    "sg:postcode":"J8M 1T3",
    "sg:province":"QC",
    "wof:name":"Centre DE LA Petite Enfance",
    "wof:placetype":"venue"
},
  "geometry": {"coordinates":[-75.4146652222,45.5445137024],"type":"Point"}
}