{
  "type": "Feature",
  "properties": {
    "addr:full":"6958 Palm Ave Burnaby BC V5J 4M3",
    "addr:housenumber":"6958",
    "addr:postcode":"v5j 4m3",
    "addr:street":"Palm Ave",
    "iso:country":"CA",
    "sg:address":"6958 Palm Ave",
    "sg:city":"Burnaby",
    "sg:classifiers":[
        {
            "category":"Freight",
            "type":"Transportation"
        }
    ],
    "sg:phone":"+1 604 437 3627",
    "sg:postcode":"V5J 4M3",
    "sg:province":"BC",
    "sg:tags":[
        "delivery"
    ],
    "wof:name":"Doc Services",
    "wof:placetype":"venue"
},
  "geometry": {"coordinates":[-122.98664856000001,49.220615387],"type":"Point"}
}