{
  "type": "Feature",
  "properties": {
    "addr:full":"337 Ontario St Sarnia ON N7T 1M1",
    "addr:housenumber":"337",
    "addr:postcode":"n7t 1m1",
    "addr:street":"Ontario St",
    "iso:country":"CA",
    "sg:address":"337 Ontario St",
    "sg:city":"Sarnia",
    "sg:classifiers":[
        {
            "category":"Retail",
            "subcategory":"Auto Repair",
            "type":"Services"
        }
    ],
    "sg:phone":"+1 519 337 7447",
    "sg:postcode":"N7T 1M1",
    "sg:province":"ON",
    "sg:tags":[
        "automobile",
        "top",
        "upholstery",
        "upholsterer"
    ],
    "wof:name":"Dave's Auto Trim",
    "wof:placetype":"venue"
},
  "geometry": {"coordinates":[-82.3887557983,42.963180542],"type":"Point"}
}