{
  "type": "Feature",
  "properties": {
    "addr:full":"North York ON M3H 3R8",
    "addr:postcode":"m3h 3r8",
    "iso:country":"CA",
    "sg:city":"North York",
    "sg:classifiers":[
        {
            "category":"Travel",
            "subcategory":"Travel Agent",
            "type":"Entertainment"
        }
    ],
    "sg:phone":"+1 416 630 4400",
    "sg:postcode":"M3H 3R8",
    "sg:province":"ON",
    "sg:tags":[
        "agency",
        "bureau"
    ],
    "wof:name":"Meridian Travel Agency",
    "wof:placetype":"venue"
},
  "geometry": {"coordinates":[-79.4387054443,43.7556686401],"type":"Point"}
}