{
  "type": "Feature",
  "properties": {
    "addr:full":"8 Laidlaw Blvd Markham ON L3P 1W6",
    "addr:housenumber":"8",
    "addr:postcode":"l3p 1w6",
    "addr:street":"Laidlaw Blvd",
    "iso:country":"CA",
    "sg:address":"8 Laidlaw Blvd",
    "sg:city":"Markham",
    "sg:classifiers":[
        {
            "category":"Retail",
            "subcategory":"Auto Repair",
            "type":"Services"
        }
    ],
    "sg:phone":"+1 905 471 6042",
    "sg:postcode":"L3P 1W6",
    "sg:province":"ON",
    "sg:tags":[
        "body",
        "automobile",
        "painting"
    ],
    "wof:name":"Quality Care Collision",
    "wof:placetype":"venue"
},
  "geometry": {"coordinates":[-79.278358,43.870388],"type":"Point"}
}