{
  "type": "Feature",
  "properties": {
    "addr:full":"Saint-Charles-Borromee QC J6E 7B5",
    "addr:postcode":"j6e 7b5",
    "iso:country":"CA",
    "sg:city":"Saint-Charles-Borromee",
    "sg:classifiers":[
        {
            "category":"Personal",
            "subcategory":"Beauty Salon",
            "type":"Services"
        }
    ],
    "sg:phone":"+1 450 752 4125",
    "sg:postcode":"J6E 7B5",
    "sg:province":"QC",
    "wof:name":"Salon Nouvelle Vague Louise",
    "wof:placetype":"venue"
},
  "geometry": {"coordinates":[-73.4645996094,46.0506477356],"type":"Point"}
}