{
  "type": "Feature",
  "properties": {
    "addr:full":"Lac-Etchemin QC G0R 1S0",
    "addr:postcode":"g0r 1s0",
    "iso:country":"CA",
    "sg:city":"Lac-Etchemin",
    "sg:classifiers":[
        {
            "category":"Personal",
            "subcategory":"Barber",
            "type":"Services"
        }
    ],
    "sg:phone":"+1 418 625 1321",
    "sg:postcode":"G0R 1S0",
    "sg:province":"QC",
    "wof:name":"Salon Hetero Coiffure",
    "wof:placetype":"venue"
},
  "geometry": {"coordinates":[-70.5246963501,46.403427124],"type":"Point"}
}