{
  "type": "Feature",
  "properties": {
    "addr:full":"Calgary AB T3A 0X9",
    "addr:postcode":"t3a 0x9",
    "iso:country":"CA",
    "sg:city":"Calgary",
    "sg:classifiers":[
        {
            "category":"Health Services",
            "subcategory":"Doctor",
            "type":"Services"
        }
    ],
    "sg:phone":"+1 403 250 5674",
    "sg:postcode":"T3A 0X9",
    "sg:province":"AB",
    "sg:tags":[
        "clinic",
        "oxygen"
    ],
    "wof:name":"Respiratory Wellness Ctr",
    "wof:placetype":"venue"
},
  "geometry": {"coordinates":[-114.15297700000001,51.090942],"type":"Point"}
}