{
  "type": "Feature",
  "properties": {
    "addr:full":"221 Rideau St Ottawa ON K1N 5X8",
    "addr:housenumber":"221",
    "addr:postcode":"k1n 5x8",
    "addr:street":"Rideau St",
    "iso:country":"CA",
    "sg:address":"221 Rideau St",
    "sg:city":"Ottawa",
    "sg:classifiers":[
        {
            "category":"Professional",
            "type":"Services"
        }
    ],
    "sg:phone":"+1 613 241 2623",
    "sg:postcode":"K1N 5X8",
    "sg:province":"ON",
    "sg:tags":[
        "management",
        "establishment",
        "real estate"
    ],
    "wof:name":"Grandsak Enterprises",
    "wof:placetype":"venue"
},
  "geometry": {"coordinates":[-75.6882476807,45.4278793335],"type":"Point"}
}