{
  "type": "Feature",
  "properties": {
    "addr:full":"989 Rue Notre-Dame Repentigny QC J5Y 1C9",
    "addr:housenumber":"989",
    "addr:postcode":"j5y 1c9",
    "addr:street":"Rue Notre-Dame",
    "iso:country":"CA",
    "sg:address":"989 Rue Notre-Dame",
    "sg:city":"Repentigny",
    "sg:classifiers":[
        {
            "category":"Personal",
            "subcategory":"Tanning Parlor",
            "type":"Services"
        }
    ],
    "sg:phone":"+1 450 581 9305",
    "sg:postcode":"J5Y 1C9",
    "sg:province":"QC",
    "sg:tags":[
        "salon"
    ],
    "wof:name":"Bronzage Notre Dame",
    "wof:placetype":"venue"
},
  "geometry": {"coordinates":[-73.41320800779999,45.7726020813],"type":"Point"}
}