{
  "type": "Feature",
  "properties": {
    "addr:full":"2629 Hastings St E Vancouver BC V5K 1Z5",
    "addr:housenumber":"2629",
    "addr:postcode":"v5k 1z5",
    "addr:street":"Hastings St E",
    "iso:country":"CA",
    "sg:address":"2629 Hastings St E",
    "sg:city":"Vancouver",
    "sg:classifiers":[
        {
            "category":"Shopping",
            "subcategory":"Optical Goods",
            "type":"Retail Goods"
        }
    ],
    "sg:phone":"+1 604 255 8882",
    "sg:postcode":"V5K 1Z5",
    "sg:province":"BC",
    "sg:tags":[
        "contact",
        "lense",
        "optician"
    ],
    "wof:name":"Hi-Care Optical",
    "wof:placetype":"venue"
},
  "geometry": {"coordinates":[-123.051018,49.281284],"type":"Point"}
}