{
  "type": "Feature",
  "properties": {
    "addr:full":"11319 107 Ave NW Edmonton AB T5H 0Y4",
    "addr:housenumber":"11319",
    "addr:postcode":"t5h 0y4",
    "addr:street":"107 Ave Nw",
    "iso:country":"CA",
    "sg:address":"11319 107 Ave NW",
    "sg:city":"Edmonton",
    "sg:classifiers":[
        {
            "category":"Professional",
            "subcategory":"Computer Services",
            "type":"Services"
        }
    ],
    "sg:phone":"+1 780 424 3838",
    "sg:postcode":"T5H 0Y4",
    "sg:province":"AB",
    "sg:tags":[
        "repair",
        "appliance"
    ],
    "wof:name":"A-Tech Electronic Svc",
    "wof:placetype":"venue"
},
  "geometry": {"coordinates":[-113.516235352,53.5511856079],"type":"Point"}
}