{
  "type": "Feature",
  "properties": {
    "iso:country":"CA",
    "sg:city":"Thamesford",
    "sg:classifiers":[
        {
            "category":"Professional",
            "subcategory":"Business Services",
            "type":"Services"
        }
    ],
    "sg:phone":"+1 519 285 5438",
    "sg:postcode":"N0M 2M0",
    "sg:province":"ON",
    "sg:tags":[
        "paralegal"
    ],
    "wof:name":"E & B Paralegal",
    "wof:placetype":"venue"
},
  "geometry": {"coordinates":[-80.9796295166,43.0583839417],"type":"Point"}
}