{
  "type": "Feature",
  "properties": {
    "addr:full":"1030 Kamato Rd # 18 Mississauga ON L4W 4B6",
    "addr:housenumber":"1030",
    "addr:postcode":"l4w 4b6",
    "addr:street":"Kamato Rd # 18",
    "iso:country":"CA",
    "sg:address":"1030 Kamato Rd # 18",
    "sg:city":"Mississauga",
    "sg:classifiers":[
        {
            "category":"Wholesale",
            "subcategory":"Electrical",
            "type":"Manufacturing & Wholesale Goods"
        }
    ],
    "sg:phone":"+1 905 625 3442",
    "sg:postcode":"L4W 4B6",
    "sg:province":"ON",
    "sg:tags":[
        "lighting",
        "fixture"
    ],
    "wof:name":"Project Lighting Svc Ltd",
    "wof:placetype":"venue"
},
  "geometry": {"coordinates":[-79.644142,43.638332],"type":"Point"}
}