{
  "type": "Feature",
  "properties": {
    "addr:full":"1812 Boul Cure-Labelle Laval QC H7T 1L2",
    "addr:housenumber":"1812",
    "addr:postcode":"h7t 1l2",
    "addr:street":"Boul Cure-Labelle",
    "iso:country":"CA",
    "sg:address":"1812 Boul Cure-Labelle",
    "sg:city":"Laval",
    "sg:classifiers":[
        {
            "category":"Retail",
            "subcategory":"Auto Repair",
            "type":"Services"
        }
    ],
    "sg:phone":"+1 450 681 4421",
    "sg:postcode":"H7T 1L2",
    "sg:province":"QC",
    "sg:tags":[
        "repairing",
        "automobile"
    ],
    "wof:name":"J C Lavoie Alignment DE Roues",
    "wof:placetype":"venue"
},
  "geometry": {"coordinates":[-73.76185599999999,45.553265],"type":"Point"}
}