{
  "type": "Feature",
  "properties": {
    "iso:country":"CA",
    "sg:address":"533 Rue Principale",
    "sg:city":"Lachute",
    "sg:classifiers":[
        {
            "category":"Shopping",
            "subcategory":"Florist",
            "type":"Retail Goods"
        }
    ],
    "sg:phone":"+1 450 562 2825",
    "sg:postcode":"J8H 1Y6",
    "sg:province":"QC",
    "wof:name":"Bernard Tessier Fleuriste Enrg",
    "wof:placetype":"venue"
},
  "geometry": {"coordinates":[-74.3338775635,45.6572418213],"type":"Point"}
}