{
  "type": "Feature",
  "properties": {
    "addr:full":"Vancouver BC V5Y 1G4",
    "addr:postcode":"v5y 1g4",
    "iso:country":"CA",
    "sg:city":"Vancouver",
    "sg:classifiers":[
        {
            "category":"Manufacturing",
            "subcategory":"Wood Products",
            "type":"Manufacturing & Wholesale Goods"
        }
    ],
    "sg:phone":"+1 604 879 9965",
    "sg:postcode":"V5Y 1G4",
    "sg:province":"BC",
    "sg:tags":[
        "picture",
        "frame"
    ],
    "wof:name":"Browning & CO",
    "wof:placetype":"venue"
},
  "geometry": {"coordinates":[-123.108352661,49.2676048279],"type":"Point"}
}