{
  "type": "Feature",
  "properties": {
    "addr:full":"3805 2nd Ave Burnaby BC V5C 3W7",
    "addr:housenumber":"3805",
    "addr:postcode":"v5c 3w7",
    "addr:street":"2Nd Ave",
    "iso:country":"CA",
    "sg:address":"3805 2nd Ave",
    "sg:city":"Burnaby",
    "sg:classifiers":[
        {
            "category":"Local Transit",
            "type":"Transportation"
        }
    ],
    "sg:phone":"+1 604 299 7100",
    "sg:postcode":"V5C 3W7",
    "sg:province":"BC",
    "sg:tags":[
        "airport",
        "limousine"
    ],
    "wof:name":"Custom Limousine Svc",
    "wof:placetype":"venue"
},
  "geometry": {"coordinates":[-123.020866,49.2686],"type":"Point"}
}