{
  "type": "Feature",
  "properties": {
    "addr:full":"2875 Rue Botham Saint-Laurent QC H4S 1H8",
    "addr:housenumber":"2875",
    "addr:postcode":"h4s 1h8",
    "addr:street":"Rue Botham Saint-Laurent",
    "iso:country":"CA",
    "sg:address":"2875 Rue Botham",
    "sg:city":"Saint-Laurent",
    "sg:classifiers":[
        {
            "category":"Manufacturing",
            "subcategory":"Tools & Machinery",
            "type":"Manufacturing & Wholesale Goods"
        }
    ],
    "sg:phone":"+1 514 745 3300",
    "sg:postcode":"H4S 1H8",
    "sg:province":"QC",
    "sg:tags":[
        "machine",
        "shop"
    ],
    "wof:name":"Vusitec Inc",
    "wof:placetype":"venue"
},
  "geometry": {"coordinates":[-73.744377,45.498482],"type":"Point"}
}