{
  "type": "Feature",
  "properties": {
    "addr:full":"230 Northern Lights St Enterprise NT X0E 0R1",
    "addr:housenumber":"230",
    "addr:postcode":"x0e 0r1",
    "addr:street":"Northern Lights St",
    "iso:country":"CA",
    "sg:address":"230 Northern Lights St",
    "sg:city":"Enterprise",
    "sg:classifiers":[
        {
            "category":"Travel",
            "subcategory":"Hotels & Motels",
            "type":"Entertainment"
        }
    ],
    "sg:phone":"+1 867 984 3711",
    "sg:postcode":"X0E 0R1",
    "sg:province":"NT",
    "wof:name":"Twin Falls Inn",
    "wof:placetype":"venue"
},
  "geometry": {"coordinates":[-116.284462,60.612076],"type":"Point"}
}