{
  "type": "Feature",
  "properties": {
    "addr:full":"106 Rue Principale E Sainte-Agathe-Des-Monts QC J8C 1J8",
    "addr:housenumber":"106",
    "addr:postcode":"j8c 1j8",
    "addr:street":"Rue Principale E Sainte-Agathe-Des-Monts",
    "iso:country":"CA",
    "sg:address":"106 Rue Principale E",
    "sg:city":"Sainte-Agathe-Des-Monts",
    "sg:classifiers":[
        {
            "category":"Insurance",
            "subcategory":"Insurance Agent",
            "type":"Services"
        }
    ],
    "sg:phone":"+1 819 321 0434",
    "sg:postcode":"J8C 1J8",
    "sg:province":"QC",
    "wof:name":"Groupe Vezina & Assoc Ltee",
    "wof:placetype":"venue"
},
  "geometry": {"coordinates":[-74.283379,46.046444],"type":"Point"}
}