{
  "type": "Feature",
  "properties": {
    "addr:full":"Airport Rd RR 8 Quesnel BC V2J 5E6",
    "addr:postcode":"v2j 5e6",
    "addr:street":"Airport Rd",
    "iso:country":"CA",
    "sg:address":"Airport Rd RR 8",
    "sg:city":"Quesnel",
    "sg:classifiers":[
        {
            "category":"Government",
            "subcategory":"Office",
            "type":"Public Place"
        }
    ],
    "sg:phone":"+1 250 992 2144",
    "sg:postcode":"V2J 5E6",
    "sg:province":"BC",
    "wof:name":"BC Forests",
    "wof:placetype":"venue"
},
  "geometry": {"coordinates":[-122.498245,52.978119],"type":"Point"}
}