{
  "type": "Feature",
  "properties": {
    "addr:full":"5255 128 Ave NW Edmonton AB T5A 5C2",
    "addr:housenumber":"5255",
    "addr:postcode":"t5a 5c2",
    "addr:street":"128 Ave Nw",
    "iso:country":"CA",
    "sg:address":"5255 128 Ave NW",
    "sg:city":"Edmonton",
    "sg:classifiers":[
        {
            "category":"Home & Garden",
            "subcategory":"Building Materials",
            "type":"Retail Goods"
        }
    ],
    "sg:phone":"+1 780 478 9663",
    "sg:postcode":"T5A 5C2",
    "sg:province":"AB",
    "wof:name":"Windsor Plywood",
    "wof:placetype":"venue"
},
  "geometry": {"coordinates":[-113.422302,53.585915],"type":"Point"}
}