{
  "type": "Feature",
  "properties": {
    "addr:full":"382 Keele St Toronto ON M6P 2K8",
    "addr:housenumber":"382",
    "addr:postcode":"m6p 2k8",
    "addr:street":"Keele St",
    "iso:country":"CA",
    "sg:address":"382 Keele St",
    "sg:city":"Toronto",
    "sg:classifiers":[
        {
            "category":"Wholesale",
            "subcategory":"Durable Goods & Equipment",
            "type":"Manufacturing & Wholesale Goods"
        }
    ],
    "sg:phone":"+1 416 766 3653",
    "sg:postcode":"M6P 2K8",
    "sg:province":"ON",
    "sg:tags":[
        "importer"
    ],
    "wof:name":"Oberoi Overseas Importers",
    "wof:placetype":"venue"
},
  "geometry": {"coordinates":[-79.46483600000001,43.665623],"type":"Point"}
}