{
  "type": "Feature",
  "properties": {
    "addr:full":"29 Fairfield Rd Toronto ON M4P 1S9",
    "addr:housenumber":"29",
    "addr:postcode":"m4p 1s9",
    "addr:street":"Fairfield Rd",
    "iso:country":"CA",
    "sg:address":"29 Fairfield Rd",
    "sg:city":"Toronto",
    "sg:classifiers":[
        {
            "category":"Professional",
            "subcategory":"Advertising",
            "type":"Services"
        }
    ],
    "sg:phone":"+1 416 485 1580",
    "sg:postcode":"M4P 1S9",
    "sg:province":"ON",
    "sg:tags":[
        "counselor"
    ],
    "wof:name":"Brooks Media Svc Inc",
    "wof:placetype":"venue"
},
  "geometry": {"coordinates":[-79.386871,43.710945],"type":"Point"}
}