{
  "type": "Feature",
  "properties": {
    "addr:full":"41 Brentford Rd Winnipeg MB R2M 4C3",
    "addr:housenumber":"41",
    "addr:postcode":"r2m 4c3",
    "addr:street":"Brentford Rd",
    "iso:country":"CA",
    "sg:address":"41 Brentford Rd",
    "sg:city":"Winnipeg",
    "sg:classifiers":[
        {
            "category":"Retail",
            "subcategory":"Laundry & Dry Cleaning",
            "type":"Services"
        }
    ],
    "sg:phone":"+1 204 255 1814",
    "sg:postcode":"R2M 4C3",
    "sg:province":"MB",
    "sg:tags":[
        "cleaners",
        "rug",
        "carpet"
    ],
    "wof:name":"Fibre Care Cleaning Svc",
    "wof:placetype":"venue"
},
  "geometry": {"coordinates":[-97.0991516113,49.8291931152],"type":"Point"}
}