{
  "type": "Feature",
  "properties": {
    "iso:country":"CA",
    "sg:city":"Langley",
    "sg:classifiers":[
        {
            "category":"Shopping",
            "subcategory":"Hobbies, Toys, & Games",
            "type":"Retail Goods"
        }
    ],
    "sg:phone":"+1 604 534 2665",
    "sg:postcode":"V3A 2P1",
    "sg:province":"BC",
    "sg:tags":[
        "craft"
    ],
    "wof:name":"Memory Book Lane",
    "wof:placetype":"venue"
},
  "geometry": {"coordinates":[-122.611732483,49.0901412964],"type":"Point"}
}