{
  "type": "Feature",
  "properties": {
    "addr:full":"822 Barrington Ave Penticton BC V2A 1S1",
    "addr:housenumber":"822",
    "addr:postcode":"v2a 1s1",
    "addr:street":"Barrington Ave",
    "iso:country":"CA",
    "sg:address":"822 Barrington Ave",
    "sg:city":"Penticton",
    "sg:classifiers":[
        {
            "category":"Building & Trades",
            "subcategory":"Landscaping Services",
            "type":"Services"
        }
    ],
    "sg:phone":"+1 250 492 6403",
    "sg:postcode":"V2A 1S1",
    "sg:province":"BC",
    "sg:tags":[
        "landscape",
        "contractor"
    ],
    "wof:name":"Dunham's Landscaping Ltd",
    "wof:placetype":"venue"
},
  "geometry": {"coordinates":[-119.580269,49.498676],"type":"Point"}
}