{
  "type": "Feature",
  "properties": {
    "addr:full":"245 Main Shawville QC J0X 2Y0",
    "addr:housenumber":"245",
    "addr:postcode":"j0x 2y0",
    "addr:street":"Main",
    "iso:country":"CA",
    "sg:address":"245 Main",
    "sg:city":"Shawville",
    "sg:classifiers":[
        {
            "category":"Wholesale",
            "subcategory":"Durable Goods & Equipment",
            "type":"Manufacturing & Wholesale Goods"
        }
    ],
    "sg:phone":"+1 819 647 2891",
    "sg:postcode":"J0X 2Y0",
    "sg:province":"QC",
    "sg:tags":[
        "fire",
        "extinguisher"
    ],
    "wof:name":"Taylor Fire Extinguishers",
    "wof:placetype":"venue"
},
  "geometry": {"coordinates":[-76.4874954224,45.6026077271],"type":"Point"}
}