{
  "type": "Feature",
  "properties": {
    "iso:country":"CA",
    "sg:address":"719 81 St SW",
    "sg:city":"Calgary",
    "sg:classifiers":[
        {
            "category":"Organizations",
            "subcategory":"Professional Association",
            "type":"Services"
        }
    ],
    "sg:phone":"+1 403 246 1776",
    "sg:postcode":"T3H 4C6",
    "sg:province":"AB",
    "wof:name":"Sikh Temple",
    "wof:placetype":"venue"
},
  "geometry": {"coordinates":[-114.205223084,51.0660858154],"type":"Point"}
}