{
  "type": "Feature",
  "properties": {
    "addr:full":"10950 84 Ave NW Edmonton AB T6G 0V4",
    "addr:housenumber":"10950",
    "addr:postcode":"t6g 0v4",
    "addr:street":"84 Ave Nw",
    "iso:country":"CA",
    "sg:address":"10950 84 Ave NW",
    "sg:city":"Edmonton",
    "sg:classifiers":[
        {
            "category":"Organizations",
            "subcategory":"Professional Association",
            "type":"Services"
        }
    ],
    "sg:phone":"+1 780 432 1333",
    "sg:postcode":"T6G 0V4",
    "sg:province":"AB",
    "wof:name":"Lambda Chi Alpha",
    "wof:placetype":"venue"
},
  "geometry": {"coordinates":[-113.51391599999999,53.520164],"type":"Point"}
}