{
  "type": "Feature",
  "properties": {
    "addr:full":"1777 Langan Ave Port Coquitlam BC V3C 1K8",
    "addr:housenumber":"1777",
    "addr:postcode":"v3c 1k8",
    "addr:street":"Langan Ave",
    "iso:country":"CA",
    "sg:address":"1777 Langan Ave",
    "sg:city":"Port Coquitlam",
    "sg:classifiers":[
        {
            "category":"Professional",
            "subcategory":"Art Services",
            "type":"Services"
        }
    ],
    "sg:phone":"+1 604 941 1024",
    "sg:postcode":"V3C 1K8",
    "sg:province":"BC",
    "sg:tags":[
        "calligrapher"
    ],
    "wof:name":"Calligraphy By Edna Cooper",
    "wof:placetype":"venue"
},
  "geometry": {"coordinates":[-122.765366,49.250313],"type":"Point"}
}