{
  "type": "Feature",
  "properties": {
    "addr:full":"931 Rue Des Erables Saint-Lambert-DE-Lauzon QC G0S 2W0",
    "addr:housenumber":"931",
    "addr:postcode":"g0s 2w0",
    "addr:street":"Rue Des Erables",
    "iso:country":"CA",
    "sg:address":"931 Rue Des Erables",
    "sg:city":"Saint-Lambert-DE-Lauzon",
    "sg:classifiers":[
        {
            "category":"Professional",
            "subcategory":"Art Services",
            "type":"Services"
        }
    ],
    "sg:phone":"+1 418 889 0354",
    "sg:postcode":"G0S 2W0",
    "sg:province":"QC",
    "sg:tags":[
        "photographer"
    ],
    "wof:name":"Photographe Jacques Plante Enr",
    "wof:placetype":"venue"
},
  "geometry": {"coordinates":[-71.236496,46.600029],"type":"Point"}
}