{
  "type": "Feature",
  "properties": {
    "addr:full":"2330 Ottawa St Port Coquitlam BC V3B 7Z1",
    "addr:housenumber":"2330",
    "addr:postcode":"v3b 7z1",
    "addr:street":"Ottawa St",
    "iso:country":"CA",
    "sg:address":"2330 Ottawa St",
    "sg:city":"Port Coquitlam",
    "sg:classifiers":[
        {
            "category":"Restaurant",
            "type":"Food & Drink"
        }
    ],
    "sg:phone":"+1 604 552 6380",
    "sg:postcode":"V3B 7Z1",
    "sg:province":"BC",
    "wof:name":"Mc Donald's",
    "wof:placetype":"venue"
},
  "geometry": {"coordinates":[-122.74680328399999,49.2561607361],"type":"Point"}
}