{
  "type": "Feature",
  "properties": {
    "addr:full":"51 Comstock Rd Scarborough ON M1L 2G6",
    "addr:housenumber":"51",
    "addr:postcode":"m1l 2g6",
    "addr:street":"Comstock Rd",
    "iso:country":"CA",
    "sg:address":"51 Comstock Rd",
    "sg:city":"Scarborough",
    "sg:classifiers":[
        {
            "category":"Manufacturing",
            "subcategory":"Food",
            "type":"Manufacturing & Wholesale Goods"
        }
    ],
    "sg:phone":"+1 416 751 0909",
    "sg:postcode":"M1L 2G6",
    "sg:province":"ON",
    "sg:tags":[
        "tea",
        "coffee"
    ],
    "wof:name":"Primrose Coffee CO Inc",
    "wof:placetype":"venue"
},
  "geometry": {"coordinates":[-79.2895355225,43.7203598022],"type":"Point"}
}