{
  "type": "Feature",
  "properties": {
    "addr:full":"601 Manitou Rd SE Calgary AB T2G 4C2",
    "addr:housenumber":"601",
    "addr:postcode":"t2g 4c2",
    "addr:street":"Manitou Rd Se",
    "iso:country":"CA",
    "sg:address":"601 Manitou Rd SE",
    "sg:city":"Calgary",
    "sg:classifiers":[
        {
            "category":"Wholesale",
            "subcategory":"Hardware",
            "type":"Manufacturing & Wholesale Goods"
        }
    ],
    "sg:phone":"+1 403 221 8181",
    "sg:postcode":"T2G 4C2",
    "sg:province":"AB",
    "sg:tags":[
        "plumbing",
        "fixture",
        "supply"
    ],
    "wof:name":"Val Temp Sales Ltd",
    "wof:placetype":"venue"
},
  "geometry": {"coordinates":[-114.051552,51.010509],"type":"Point"}
}