{
  "type": "Feature",
  "properties": {
    "addr:full":"76 Stuart St #D3 Kingston ON K7L 2V7",
    "addr:housenumber":"76",
    "addr:postcode":"k7l 2v7",
    "addr:street":"Stuart St # D3",
    "iso:country":"CA",
    "sg:address":"76 Stuart St #D3",
    "sg:city":"Kingston",
    "sg:classifiers":[
        {
            "category":"Health Services",
            "subcategory":"Doctor",
            "type":"Services"
        }
    ],
    "sg:phone":"+1 613 547 9205",
    "sg:postcode":"K7L 2V7",
    "sg:province":"ON",
    "sg:tags":[
        "physician",
        "surgeon"
    ],
    "wof:name":"Ellis, P M MD",
    "wof:placetype":"venue"
},
  "geometry": {"coordinates":[-76.49327099999999,44.22438],"type":"Point"}
}