{
  "type": "Feature",
  "properties": {
    "addr:full":"Montreal QC H3B 4R4",
    "addr:postcode":"h3b 4r4",
    "iso:country":"CA",
    "sg:city":"Montreal",
    "sg:classifiers":[
        {
            "category":"Professional",
            "subcategory":"Computer Services",
            "type":"Services"
        }
    ],
    "sg:phone":"+1 514 866 2224",
    "sg:postcode":"H3B 4R4",
    "sg:province":"QC",
    "sg:tags":[
        "information",
        "system",
        "consultant"
    ],
    "wof:name":"Dgem Inc",
    "wof:placetype":"venue"
},
  "geometry": {"coordinates":[-73.56797,45.50182],"type":"Point"}
}