{
  "type": "Feature",
  "properties": {
    "addr:full":"58 Rue Saint-Antoine N Granby QC J2G 5G3",
    "addr:housenumber":"58",
    "addr:postcode":"j2g 5g3",
    "addr:street":"Rue Saint-Antoine N",
    "iso:country":"CA",
    "sg:address":"58 Rue Saint-Antoine N",
    "sg:city":"Granby",
    "sg:classifiers":[
        {
            "category":"Health Services",
            "subcategory":"Chiropractor",
            "type":"Services"
        }
    ],
    "sg:phone":"+1 450 378 2432",
    "sg:postcode":"J2G 5G3",
    "sg:province":"QC",
    "wof:name":"Bouchard, Luc R DC",
    "wof:placetype":"venue"
},
  "geometry": {"coordinates":[-72.7293930054,45.4025611877],"type":"Point"}
}