{
  "type": "Feature",
  "properties": {
    "addr:full":"633 Main St Moosomin SK S0G 3N0",
    "addr:housenumber":"633",
    "addr:postcode":"s0g 3n0",
    "addr:street":"Main St",
    "iso:country":"CA",
    "sg:address":"633 Main St",
    "sg:city":"Moosomin",
    "sg:classifiers":[
        {
            "category":"Banks & Credit Unions",
            "subcategory":"Bank",
            "type":"Services"
        }
    ],
    "sg:phone":"+1 306 435 3387",
    "sg:postcode":"S0G 3N0",
    "sg:province":"SK",
    "wof:name":"Royal Bank Financial Group",
    "wof:placetype":"venue"
},
  "geometry": {"coordinates":[-101.66658,50.144142],"type":"Point"}
}