{
  "type": "Feature",
  "properties": {
    "addr:full":"178 Plaunt St S Renfrew ON K7V 1M8",
    "addr:housenumber":"178",
    "addr:postcode":"k7v 1m8",
    "addr:street":"Plaunt St S",
    "iso:country":"CA",
    "sg:address":"178 Plaunt St S",
    "sg:city":"Renfrew",
    "sg:classifiers":[
        {
            "category":"Organizations",
            "subcategory":"Labor Organization",
            "type":"Services"
        }
    ],
    "sg:phone":"+1 613 432 2494",
    "sg:postcode":"K7V 1M8",
    "sg:province":"ON",
    "wof:name":"United Steelworkers of America",
    "wof:placetype":"venue"
},
  "geometry": {"coordinates":[-76.683571,45.47245],"type":"Point"}
}