{
  "type": "Feature",
  "properties": {
    "addr:full":"55 Grand River Ave Brantford ON N3T 4X1",
    "addr:housenumber":"55",
    "addr:postcode":"n3t 4x1",
    "addr:street":"Grand River Ave",
    "iso:country":"CA",
    "sg:address":"55 Grand River Ave",
    "sg:city":"Brantford",
    "sg:classifiers":[
        {
            "category":"Retail",
            "subcategory":"Repair Shop",
            "type":"Services"
        }
    ],
    "sg:phone":"+1 519 759 1537",
    "sg:postcode":"N3T 4X1",
    "sg:province":"ON",
    "sg:tags":[
        "cover",
        "upholsterer",
        "slip"
    ],
    "wof:name":"Rudy & Richard's Custom Uphols",
    "wof:placetype":"venue"
},
  "geometry": {"coordinates":[-80.27546691889999,43.1412124634],"type":"Point"}
}