{
  "type": "Feature",
  "properties": {
    "addr:full":"1221 Rue Labadie Longueuil QC J4N 1E2",
    "addr:housenumber":"1221",
    "addr:postcode":"j4n 1e2",
    "addr:street":"Rue Labadie",
    "iso:country":"CA",
    "sg:address":"1221 Rue Labadie",
    "sg:city":"Longueuil",
    "sg:classifiers":[
        {
            "category":"Shopping",
            "type":"Retail Goods"
        }
    ],
    "sg:phone":"+1 450 677 1441",
    "sg:postcode":"J4N 1E2",
    "sg:province":"QC",
    "sg:tags":[
        "orthopedic",
        "appliance"
    ],
    "wof:name":"Visibilite Inc",
    "wof:placetype":"venue"
},
  "geometry": {"coordinates":[-73.45508599999999,45.563904],"type":"Point"}
}