{
  "type": "Feature",
  "properties": {
    "iso:country":"CA",
    "sg:address":"4303 Cherry Ave S",
    "sg:city":"Beamsville",
    "sg:classifiers":[
        {
            "category":"Farming",
            "subcategory":"Farm",
            "type":"Manufacturing & Wholesale Goods"
        }
    ],
    "sg:phone":"+1 905 562 5481",
    "sg:postcode":"L0R 1B1",
    "sg:province":"ON",
    "wof:name":"Cherry Avenue Farms Pick Your",
    "wof:placetype":"venue"
},
  "geometry": {"coordinates":[-79.4726104736,43.1885528564],"type":"Point"}
}