{
  "type": "Feature",
  "properties": {
    "iso:country":"CA",
    "sg:address":"14600 50 Hwy",
    "sg:city":"Bolton",
    "sg:classifiers":[
        {
            "category":"Home & Garden",
            "subcategory":"Building Materials",
            "type":"Retail Goods"
        }
    ],
    "sg:phone":"+1 905 857 3992",
    "sg:postcode":"L7E 5R8",
    "sg:province":"ON",
    "sg:tags":[
        "glass",
        "window",
        "plate"
    ],
    "wof:name":"Jay-R's Auto Glass",
    "wof:placetype":"venue"
},
  "geometry": {"coordinates":[-79.7655410767,43.8991851807],"type":"Point"}
}