{
  "type": "Feature",
  "properties": {
    "addr:full":"295 Rue Saint-Jacques N Coaticook QC J1A 2R2",
    "addr:housenumber":"295",
    "addr:postcode":"j1a 2r2",
    "addr:street":"Rue Saint-Jacques N",
    "iso:country":"CA",
    "sg:address":"295 Rue Saint-Jacques N",
    "sg:city":"Coaticook",
    "sg:classifiers":[
        {
            "category":"Organizations",
            "subcategory":"Religious Organization",
            "type":"Services"
        }
    ],
    "sg:phone":"+1 819 859 3645",
    "sg:postcode":"J1A 2R2",
    "sg:province":"QC",
    "sg:tags":[
        "church"
    ],
    "wof:name":"Presbytere Eglise Catholique",
    "wof:placetype":"venue"
},
  "geometry": {"coordinates":[-71.796707,45.136806],"type":"Point"}
}