{
  "type": "Feature",
  "properties": {
    "iso:country":"CA",
    "sg:city":"Newmarket",
    "sg:classifiers":[
        {
            "category":"Social Services",
            "type":"Services"
        }
    ],
    "sg:phone":"+1 905 853 6433",
    "sg:postcode":"L3Y 8J9",
    "sg:province":"ON",
    "sg:tags":[
        "youth",
        "organization",
        "center"
    ],
    "wof:name":"Girl Guides of Canada",
    "wof:placetype":"venue"
},
  "geometry": {"coordinates":[-79.47272491459999,44.0550537109],"type":"Point"}
}