{
  "type": "Feature",
  "properties": {
    "addr:full":"Merrickville ON K0G 1N0",
    "addr:postcode":"k0g 1n0",
    "iso:country":"CA",
    "sg:city":"Merrickville",
    "sg:classifiers":[
        {
            "category":"Autos & Motor Vehicles",
            "subcategory":"Automobile Sales",
            "type":"Retail Goods"
        }
    ],
    "sg:phone":"+1 613 269 2413",
    "sg:postcode":"K0G 1N0",
    "sg:province":"ON",
    "sg:tags":[
        "car",
        "dealer"
    ],
    "wof:name":"Major's Auto",
    "wof:placetype":"venue"
},
  "geometry": {"coordinates":[-75.836838,44.915741],"type":"Point"}
}