{
  "type": "Feature",
  "properties": {
    "addr:full":"3571 Hwy 31 Ainsworth Hot Springs BC V0G 1A0",
    "addr:housenumber":"3571",
    "addr:postcode":"v0g 1a0",
    "addr:street":"Hwy 31",
    "iso:country":"CA",
    "sg:address":"3571 Hwy 31",
    "sg:city":"Ainsworth Hot Springs",
    "sg:classifiers":[
        {
            "category":"Travel",
            "subcategory":"Hotels & Motels",
            "type":"Entertainment"
        }
    ],
    "sg:phone":"+1 250 229 4711",
    "sg:postcode":"V0G 1A0",
    "sg:province":"BC",
    "wof:name":"Ainsworth Motel",
    "wof:placetype":"venue"
},
  "geometry": {"coordinates":[-116.910453796,49.7329444885],"type":"Point"}
}