{
  "type": "Feature",
  "properties": {
    "addr:full":"5403 136 Ave NW Edmonton AB T5A 4W1",
    "addr:housenumber":"5403",
    "addr:postcode":"t5a 4w1",
    "addr:street":"136 Ave Nw",
    "iso:country":"CA",
    "sg:address":"5403 136 Ave NW",
    "sg:city":"Edmonton",
    "sg:classifiers":[
        {
            "category":"Freight",
            "type":"Transportation"
        }
    ],
    "sg:phone":"+1 780 478 3069",
    "sg:postcode":"T5A 4W1",
    "sg:province":"AB",
    "sg:tags":[
        "commercial",
        "storage"
    ],
    "wof:name":"Sentinel Self-Storage",
    "wof:placetype":"venue"
},
  "geometry": {"coordinates":[-113.42068500000001,53.596767],"type":"Point"}
}