{
  "type": "Feature",
  "properties": {
    "addr:full":"Montreal QC H3A 3J5",
    "addr:postcode":"h3a 3j5",
    "iso:country":"CA",
    "sg:city":"Montreal",
    "sg:classifiers":[
        {
            "category":"Shopping",
            "subcategory":"Shoes",
            "type":"Retail Goods"
        }
    ],
    "sg:phone":"+1 514 849 5406",
    "sg:postcode":"H3A 3J5",
    "sg:province":"QC",
    "wof:name":"Chaussures Minitalia Inc",
    "wof:placetype":"venue"
},
  "geometry": {"coordinates":[-73.57178497309999,45.5020713806],"type":"Point"}
}