{
  "type": "Feature",
  "properties": {
    "addr:full":"1931 Boul Keller Saint-Laurent QC H4K 2V6",
    "addr:housenumber":"1931",
    "addr:postcode":"h4k 2v6",
    "addr:street":"Boul Keller",
    "iso:country":"CA",
    "sg:address":"1931 Boul Keller",
    "sg:city":"Saint-Laurent",
    "sg:classifiers":[
        {
            "category":"Personal",
            "subcategory":"Beauty Salon",
            "type":"Services"
        }
    ],
    "sg:phone":"+1 514 333 0548",
    "sg:postcode":"H4K 2V6",
    "sg:province":"QC",
    "wof:name":"Salon DE Coiffure Unique II",
    "wof:placetype":"venue"
},
  "geometry": {"coordinates":[-73.7129058838,45.5244102478],"type":"Point"}
}