{
  "type": "Feature",
  "properties": {
    "addr:full":"Ranger Lake Thessalon ON P0R 1L0",
    "addr:postcode":"p0r 1l0",
    "addr:street":"Ranger",
    "iso:country":"CA",
    "sg:address":"Ranger Lake",
    "sg:city":"Thessalon",
    "sg:classifiers":[
        {
            "category":"Travel",
            "subcategory":"Hotels & Motels",
            "type":"Entertainment"
        }
    ],
    "sg:phone":"+1 705 841 1329",
    "sg:postcode":"P0R 1L0",
    "sg:province":"ON",
    "sg:tags":[
        "resort"
    ],
    "wof:name":"Hidden Bay Lodge",
    "wof:placetype":"venue"
},
  "geometry": {"coordinates":[-83.5464553833,46.265411377],"type":"Point"}
}