{
  "type": "Feature",
  "properties": {
    "addr:full":"4358 Rue Forest Montreal-Nord QC H1H 2N8",
    "addr:housenumber":"4358",
    "addr:postcode":"h1h 2n8",
    "addr:street":"Rue Forest",
    "iso:country":"CA",
    "sg:address":"4358 Rue Forest",
    "sg:city":"Montreal-Nord",
    "sg:classifiers":[
        {
            "category":"Autos & Motor Vehicles",
            "subcategory":"Auto Supplies",
            "type":"Retail Goods"
        }
    ],
    "sg:phone":"+1 514 322 2299",
    "sg:postcode":"H1H 2N8",
    "sg:province":"QC",
    "sg:tags":[
        "automobile",
        "parts"
    ],
    "wof:name":"Miska Automotive",
    "wof:placetype":"venue"
},
  "geometry": {"coordinates":[-73.630409,45.588928],"type":"Point"}
}