{
  "type": "Feature",
  "properties": {
    "addr:full":"308 Salerno St Oshawa ON L1J 6W2",
    "addr:housenumber":"308",
    "addr:postcode":"l1j 6w2",
    "addr:street":"Salerno St",
    "iso:country":"CA",
    "sg:address":"308 Salerno St",
    "sg:city":"Oshawa",
    "sg:classifiers":[
        {
            "category":"Home & Garden",
            "subcategory":"Household Appliances",
            "type":"Retail Goods"
        }
    ],
    "sg:phone":"+1 905 434 8271",
    "sg:postcode":"L1J 6W2",
    "sg:province":"ON",
    "wof:name":"A All Durham Appliances Svc",
    "wof:placetype":"venue"
},
  "geometry": {"coordinates":[-78.898224,43.89872],"type":"Point"}
}