{
  "type": "Feature",
  "properties": {
    "addr:full":"826 Ch Rosenberry Sutton QC J0E 2K0",
    "addr:housenumber":"826",
    "addr:postcode":"j0e 2k0",
    "addr:street":"Ch Rosenberry",
    "iso:country":"CA",
    "sg:address":"826 Ch Rosenberry",
    "sg:city":"Sutton",
    "sg:classifiers":[
        {
            "category":"Professional",
            "subcategory":"Business Services",
            "type":"Services"
        }
    ],
    "sg:phone":"+1 450 242 1888",
    "sg:postcode":"J0E 2K0",
    "sg:province":"QC",
    "sg:tags":[
        "translator",
        "interpreter"
    ],
    "wof:name":"Textaid",
    "wof:placetype":"venue"
},
  "geometry": {"coordinates":[-72.546577,45.145065],"type":"Point"}
}