{
  "type": "Feature",
  "properties": {
    "addr:full":"9200 Av Du Parc Montreal QC H2N 1Z4",
    "addr:housenumber":"9200",
    "addr:postcode":"h2n 1z4",
    "addr:street":"Av Du Parc",
    "iso:country":"CA",
    "sg:address":"9200 Av Du Parc",
    "sg:city":"Montreal",
    "sg:classifiers":[
        {
            "category":"Shopping",
            "subcategory":"Clothing, Apparel, & Fashions",
            "type":"Retail Goods"
        }
    ],
    "sg:phone":"+1 514 387 5262",
    "sg:postcode":"H2N 1Z4",
    "sg:province":"QC",
    "wof:name":"9075-0027 Quebec Inc",
    "wof:placetype":"venue"
},
  "geometry": {"coordinates":[-73.65325900000001,45.537701],"type":"Point"}
}