{
  "type": "Feature",
  "properties": {
    "addr:full":"347 6E Rue O Amos QC J9T 2V6",
    "addr:housenumber":"347",
    "addr:postcode":"j9t 2v6",
    "addr:street":"6E Rue O Amos",
    "iso:country":"CA",
    "sg:address":"347 6E Rue O",
    "sg:city":"Amos",
    "sg:classifiers":[
        {
            "category":"Wholesale",
            "subcategory":"Office Equipment",
            "type":"Manufacturing & Wholesale Goods"
        }
    ],
    "sg:phone":"+1 819 732 3335",
    "sg:postcode":"J9T 2V6",
    "sg:province":"QC",
    "sg:tags":[
        "accounting",
        "training",
        "computer",
        "system",
        "bookkeeping"
    ],
    "wof:name":"Comptabilite Cs Plus",
    "wof:placetype":"venue"
},
  "geometry": {"coordinates":[-78.111023,48.562447],"type":"Point"}
}