{
  "type": "Feature",
  "properties": {
    "addr:full":"1300 Montee Saint-Francois Laval QC H7C 1S5",
    "addr:housenumber":"1300",
    "addr:postcode":"h7c 1s5",
    "addr:street":"Montee Saint-Francois",
    "iso:country":"CA",
    "sg:address":"1300 Montee Saint-Francois",
    "sg:city":"Laval",
    "sg:classifiers":[
        {
            "category":"Government",
            "subcategory":"Office",
            "type":"Public Place"
        }
    ],
    "sg:phone":"+1 450 661 9620",
    "sg:postcode":"H7C 1S5",
    "sg:province":"QC",
    "wof:name":"Canada Solicitor General Dept",
    "wof:placetype":"venue"
},
  "geometry": {"coordinates":[-73.655373,45.626152],"type":"Point"}
}