{
  "type": "Feature",
  "properties": {
    "iso:country":"CA",
    "sg:address":"65 Front St W",
    "sg:city":"Toronto",
    "sg:classifiers":[
        {
            "category":"Retail",
            "subcategory":"Auto Rental",
            "type":"Services"
        }
    ],
    "sg:phone":"+1 416 364 4191",
    "sg:postcode":"M5J 1E6",
    "sg:province":"ON",
    "sg:tags":[
        "renting",
        "automobile"
    ],
    "wof:name":"National Car & Truck Rental",
    "wof:placetype":"venue"
},
  "geometry": {"coordinates":[-79.3801498413,43.6455307007],"type":"Point"}
}