{
  "type": "Feature",
  "properties": {
    "addr:full":"295 Rue Chapleau Cap-DE-LA-Madeleine QC G8W 2A5",
    "addr:housenumber":"295",
    "addr:postcode":"g8w 2a5",
    "addr:street":"Rue Chapleau",
    "iso:country":"CA",
    "sg:address":"295 Rue Chapleau",
    "sg:city":"Cap-DE-LA-Madeleine",
    "sg:classifiers":[
        {
            "category":"Organizations",
            "subcategory":"Religious Organization",
            "type":"Services"
        }
    ],
    "sg:phone":"+1 819 370 8185",
    "sg:postcode":"G8W 2A5",
    "sg:province":"QC",
    "sg:tags":[
        "home",
        "retirement",
        "community",
        "retreat",
        "house"
    ],
    "wof:name":"Residences Fernand Blais",
    "wof:placetype":"venue"
},
  "geometry": {"coordinates":[-72.5572967529,46.3776855469],"type":"Point"}
}