{
  "type": "Feature",
  "properties": {
    "iso:country":"CA",
    "sg:address":"16201 Mckenzie Lake Blvd SE",
    "sg:city":"Calgary",
    "sg:classifiers":[
        {
            "category":"Education",
            "subcategory":"School",
            "type":"Public Place"
        }
    ],
    "sg:phone":"+1 403 257 0707",
    "sg:postcode":"T2Z 2G7",
    "sg:province":"AB",
    "wof:name":"Cardinal Newman Elem Jh School",
    "wof:placetype":"venue"
},
  "geometry": {"coordinates":[-113.98737335200001,50.9073448181],"type":"Point"}
}