{
  "type": "Feature",
  "properties": {
    "addr:full":"Richmond BC V6X 1E4",
    "addr:postcode":"v6x 1e4",
    "iso:country":"CA",
    "sg:city":"Richmond",
    "sg:classifiers":[
        {
            "category":"Restaurant",
            "type":"Food & Drink"
        }
    ],
    "sg:phone":"+1 604 270 3633",
    "sg:postcode":"V6X 1E4",
    "sg:province":"BC",
    "wof:name":"DE Dutch Pannekoek House",
    "wof:placetype":"venue"
},
  "geometry": {"coordinates":[-123.13584899999999,49.179878],"type":"Point"}
}