{
  "type": "Feature",
  "properties": {
    "addr:full":"373 Danforth Rd Scarborough ON M1L 3X8",
    "addr:housenumber":"373",
    "addr:postcode":"m1l 3x8",
    "addr:street":"Danforth Rd",
    "iso:country":"CA",
    "sg:address":"373 Danforth Rd",
    "sg:city":"Scarborough",
    "sg:classifiers":[
        {
            "category":"Manufacturing",
            "subcategory":"Motor Vehicles & Parts",
            "type":"Manufacturing & Wholesale Goods"
        }
    ],
    "sg:phone":"+1 416 686 5788",
    "sg:postcode":"M1L 3X8",
    "sg:province":"ON",
    "sg:tags":[
        "automobile"
    ],
    "wof:name":"Jpn Inc",
    "wof:placetype":"venue"
},
  "geometry": {"coordinates":[-79.2692489624,43.7048072815],"type":"Point"}
}