{
  "type": "Feature",
  "properties": {
    "addr:full":"47 Rue Denise-Friend Aylmer QC J9H 3A8",
    "addr:housenumber":"47",
    "addr:postcode":"j9h 3a8",
    "addr:street":"Rue Denise-Friend",
    "iso:country":"CA",
    "sg:address":"47 Rue Denise-Friend",
    "sg:city":"Aylmer",
    "sg:classifiers":[
        {
            "category":"Retail",
            "subcategory":"Funeral Services",
            "type":"Services"
        }
    ],
    "sg:phone":"+1 819 684 1155",
    "sg:postcode":"J9H 3A8",
    "sg:province":"QC",
    "sg:tags":[
        "director"
    ],
    "wof:name":"Beauchamp Funeral Home Ltd",
    "wof:placetype":"venue"
},
  "geometry": {"coordinates":[-75.8471908569,45.3979873657],"type":"Point"}
}