{
  "type": "Feature",
  "properties": {
    "addr:full":"503 Downey Rd North Saanich BC V8L 5M6",
    "addr:housenumber":"503",
    "addr:postcode":"v8l 5m6",
    "addr:street":"Downey Rd",
    "iso:country":"CA",
    "sg:address":"503 Downey Rd",
    "sg:city":"North Saanich",
    "sg:classifiers":[
        {
            "category":"Building & Trades",
            "subcategory":"Construction",
            "type":"Services"
        }
    ],
    "sg:phone":"+1 250 655 1404",
    "sg:postcode":"V8L 5M6",
    "sg:province":"BC",
    "sg:tags":[
        "general",
        "contractor"
    ],
    "wof:name":"Kappa Developments Corp",
    "wof:placetype":"venue"
},
  "geometry": {"coordinates":[-123.477333,48.673344],"type":"Point"}
}