{
  "type": "Feature",
  "properties": {
    "addr:full":"325 Rue Laurier Disraeli QC G0N 1E0",
    "addr:housenumber":"325",
    "addr:postcode":"g0n 1e0",
    "addr:street":"Rue Laurier",
    "iso:country":"CA",
    "sg:address":"325 Rue Laurier",
    "sg:city":"Disraeli",
    "sg:classifiers":[
        {
            "category":"Shopping",
            "subcategory":"Department Store",
            "type":"Retail Goods"
        }
    ],
    "sg:phone":"+1 418 449 1226",
    "sg:postcode":"G0N 1E0",
    "sg:province":"QC",
    "wof:name":"Korvette",
    "wof:placetype":"venue"
},
  "geometry": {"coordinates":[-71.3591,45.904236],"type":"Point"}
}