{
  "type": "Feature",
  "properties": {
    "addr:full":"11028 51 Ave NW Edmonton AB T6H 0L4",
    "addr:housenumber":"11028",
    "addr:postcode":"t6h 0l4",
    "addr:street":"51 Ave Nw",
    "iso:country":"CA",
    "sg:address":"11028 51 Ave NW",
    "sg:city":"Edmonton",
    "sg:classifiers":[
        {
            "category":"Health Services",
            "subcategory":"Doctor",
            "type":"Services"
        }
    ],
    "sg:phone":"+1 780 471 3004",
    "sg:postcode":"T6H 0L4",
    "sg:province":"AB",
    "sg:tags":[
        "physician",
        "surgeon"
    ],
    "wof:name":"Mc Laren, Sherry L MD",
    "wof:placetype":"venue"
},
  "geometry": {"coordinates":[-113.514503,53.488419],"type":"Point"}
}