{
  "type": "Feature",
  "properties": {
    "addr:full":"589 Grey Ox Ave Lucknow ON N0G 2H0",
    "addr:housenumber":"589",
    "addr:postcode":"n0g 2h0",
    "addr:street":"Grey Ox Ave",
    "iso:country":"CA",
    "sg:address":"589 Grey Ox Ave",
    "sg:city":"Lucknow",
    "sg:classifiers":[
        {
            "category":"Building & Trades",
            "subcategory":"Construction",
            "type":"Services"
        }
    ],
    "sg:phone":"+1 519 528 2003",
    "sg:postcode":"N0G 2H0",
    "sg:province":"ON",
    "sg:tags":[
        "contractor"
    ],
    "wof:name":"Eric Stewart Construction Ltd",
    "wof:placetype":"venue"
},
  "geometry": {"coordinates":[-81.51606750489999,43.9613037109],"type":"Point"}
}