{
  "type": "Feature",
  "properties": {
    "iso:country":"CA",
    "sg:address":"512 Rue Saint-Germain E",
    "sg:city":"Rimouski-Est",
    "sg:classifiers":[
        {
            "category":"Personal",
            "subcategory":"Beauty Salon",
            "type":"Services"
        }
    ],
    "sg:phone":"+1 418 722 0011",
    "sg:postcode":"G5L 1E6",
    "sg:province":"QC",
    "wof:name":"Studio Martine Enr",
    "wof:placetype":"venue"
},
  "geometry": {"coordinates":[-68.513596,48.474518],"type":"Point"}
}