{
  "type": "Feature",
  "properties": {
    "addr:full":"223 7th Ave W Vancouver BC V5Y 1L9",
    "addr:housenumber":"223",
    "addr:postcode":"v5y 1l9",
    "addr:street":"7Th Ave W",
    "iso:country":"CA",
    "sg:address":"223 7th Ave W",
    "sg:city":"Vancouver",
    "sg:classifiers":[
        {
            "category":"Manufacturing",
            "subcategory":"Food",
            "type":"Manufacturing & Wholesale Goods"
        }
    ],
    "sg:phone":"+1 604 879 0701",
    "sg:postcode":"V5Y 1L9",
    "sg:province":"BC",
    "sg:tags":[
        "product",
        "manufacturer"
    ],
    "wof:name":"Toko Foods Ltd",
    "wof:placetype":"venue"
},
  "geometry": {"coordinates":[-123.109863,49.264912],"type":"Point"}
}