{
  "type": "Feature",
  "properties": {
    "addr:full":"136 Rue Saint-Jean-Baptiste L'Isle-Verte QC G0L 1K0",
    "addr:housenumber":"136",
    "addr:postcode":"g0l 1k0",
    "addr:street":"Rue Saint-Jean-Baptiste",
    "iso:country":"CA",
    "sg:address":"136 Rue Saint-Jean-Baptiste",
    "sg:city":"L'Isle-Verte",
    "sg:classifiers":[
        {
            "category":"Education",
            "subcategory":"School",
            "type":"Public Place"
        }
    ],
    "sg:phone":"+1 418 898 3031",
    "sg:postcode":"G0L 1K0",
    "sg:province":"QC",
    "wof:name":"Ecole Moisson D'Arts",
    "wof:placetype":"venue"
},
  "geometry": {"coordinates":[-69.33596,48.014931],"type":"Point"}
}