{
  "type": "Feature",
  "properties": {
    "iso:country":"CA",
    "sg:address":"42 Ch Victoria",
    "sg:city":"Scotstown",
    "sg:classifiers":[
        {
            "category":"Banks & Credit Unions",
            "subcategory":"Bank",
            "type":"Services"
        }
    ],
    "sg:phone":"+1 819 657 4264",
    "sg:postcode":"J0B 3B0",
    "sg:province":"QC",
    "wof:name":"Caisse Desjardins",
    "wof:placetype":"venue"
},
  "geometry": {"coordinates":[-71.3119430542,45.5178337097],"type":"Point"}
}