{
  "type": "Feature",
  "properties": {
    "iso:country":"CA",
    "sg:address":"1355 Boul Des Laurentides",
    "sg:city":"Laval",
    "sg:classifiers":[
        {
            "category":"Shopping",
            "subcategory":"Bicycles & Sporting Goods",
            "type":"Retail Goods"
        }
    ],
    "sg:phone":"+1 450 669 5123",
    "sg:postcode":"H7N 4Y5",
    "sg:province":"QC",
    "sg:tags":[
        "equipment",
        "skiing"
    ],
    "wof:name":"Oberson Ski",
    "wof:placetype":"venue"
},
  "geometry": {"coordinates":[-73.701149,45.578484],"type":"Point"}
}