{
  "type": "Feature",
  "properties": {
    "addr:full":"710 9 St Canmore AB T1W 2V7",
    "addr:housenumber":"710 9",
    "addr:postcode":"t1w 2v7",
    "addr:street":"St",
    "iso:country":"CA",
    "sg:address":"710 9 St",
    "sg:city":"Canmore",
    "sg:classifiers":[
        {
            "category":"Restaurant",
            "type":"Food & Drink"
        }
    ],
    "sg:phone":"+1 403 609 2000",
    "sg:postcode":"T1W 2V7",
    "sg:province":"AB",
    "wof:name":"Zona's Bistro",
    "wof:placetype":"venue"
},
  "geometry": {"coordinates":[-115.35882599999999,51.090088],"type":"Point"}
}