{
  "type": "Feature",
  "properties": {
    "addr:full":"4687 Amblewood Dr Victoria BC V8Y 1C4",
    "addr:housenumber":"4687",
    "addr:postcode":"v8y 1c4",
    "addr:street":"Amblewood Dr",
    "iso:country":"CA",
    "sg:address":"4687 Amblewood Dr",
    "sg:city":"Victoria",
    "sg:classifiers":[
        {
            "category":"Professional",
            "subcategory":"Management & Consulting",
            "type":"Services"
        }
    ],
    "sg:phone":"+1 250 658 4007",
    "sg:postcode":"V8Y 1C4",
    "sg:province":"BC",
    "sg:tags":[
        "consultant",
        "government"
    ],
    "wof:name":"Crown Western Consulting Svc",
    "wof:placetype":"venue"
},
  "geometry": {"coordinates":[-123.364517212,48.428314209],"type":"Point"}
}