{
  "type": "Feature",
  "properties": {
    "addr:full":"45th Ave Two Hills AB T0B 4K0",
    "addr:postcode":"t0b 4k0",
    "addr:street":"45Th Ave",
    "iso:country":"CA",
    "sg:address":"45th Ave",
    "sg:city":"Two Hills",
    "sg:classifiers":[
        {
            "category":"Government",
            "subcategory":"Office",
            "type":"Public Place"
        }
    ],
    "sg:phone":"+1 780 657 2791",
    "sg:postcode":"T0B 4K0",
    "sg:province":"AB",
    "sg:tags":[
        "village"
    ],
    "wof:name":"Two Hills Centennial Hall",
    "wof:placetype":"venue"
},
  "geometry": {"coordinates":[-111.75174699999999,53.70713],"type":"Point"}
}