{
  "type": "Feature",
  "properties": {
    "addr:full":"652 Rue Principale Lac-Drolet QC G0Y 1C0",
    "addr:housenumber":"652",
    "addr:postcode":"g0y 1c0",
    "addr:street":"Rue Principale",
    "iso:country":"CA",
    "sg:address":"652 Rue Principale",
    "sg:city":"Lac-Drolet",
    "sg:classifiers":[
        {
            "category":"Shopping",
            "subcategory":"Pharmacy",
            "type":"Retail Goods"
        }
    ],
    "sg:phone":"+1 819 549 2556",
    "sg:postcode":"G0Y 1C0",
    "sg:province":"QC",
    "wof:name":"Toulouse, Marjolaine",
    "wof:placetype":"venue"
},
  "geometry": {"coordinates":[-70.8477935791,45.7182540894],"type":"Point"}
}