{
  "type": "Feature",
  "properties": {
    "iso:country":"CA",
    "sg:address":"227 Church St",
    "sg:city":"Newmarket",
    "sg:classifiers":[
        {
            "category":"Organizations",
            "subcategory":"Religious Organization",
            "type":"Services"
        }
    ],
    "sg:phone":"+1 905 853 7285",
    "sg:postcode":"L3Y 4C5",
    "sg:province":"ON",
    "sg:tags":[
        "church"
    ],
    "wof:name":"St Paul's Anglican Church",
    "wof:placetype":"venue"
},
  "geometry": {"coordinates":[-79.458824,44.051239],"type":"Point"}
}