{
  "type": "Feature",
  "properties": {
    "addr:full":"5778 Av Eldridge Cote Saint-Luc QC H4W 2E4",
    "addr:housenumber":"5778",
    "addr:postcode":"h4w 2e4",
    "addr:street":"Av Eldridge Cote",
    "iso:country":"CA",
    "sg:address":"5778 Av Eldridge",
    "sg:city":"Cote Saint-Luc",
    "sg:classifiers":[
        {
            "category":"Professional",
            "subcategory":"Advertising",
            "type":"Services"
        }
    ],
    "sg:phone":"+1 514 489 3438",
    "sg:postcode":"H4W 2E4",
    "sg:province":"QC",
    "sg:tags":[
        "publicity"
    ],
    "wof:name":"Dyna Marketing",
    "wof:placetype":"venue"
},
  "geometry": {"coordinates":[-73.66967,45.465641],"type":"Point"}
}