{
  "type": "Feature",
  "properties": {
    "addr:full":"111 Browning Trail Barrie ON L4N 6R2",
    "addr:housenumber":"111",
    "addr:postcode":"l4n 6r2",
    "addr:street":"Browning Trail",
    "iso:country":"CA",
    "sg:address":"111 Browning Trail",
    "sg:city":"Barrie",
    "sg:classifiers":[
        {
            "category":"Arts & Performance",
            "subcategory":"Theater",
            "type":"Entertainment"
        }
    ],
    "sg:phone":"+1 705 726 0446",
    "sg:postcode":"L4N 6R2",
    "sg:province":"ON",
    "sg:tags":[
        "bureau",
        "concert"
    ],
    "wof:name":"Jim Ford & Assoc Inc",
    "wof:placetype":"venue"
},
  "geometry": {"coordinates":[-79.7267379761,44.3844985962],"type":"Point"}
}