{
  "type": "Feature",
  "properties": {
    "addr:full":"Calgary AB T2V 4V4",
    "addr:postcode":"t2v 4v4",
    "iso:country":"CA",
    "sg:city":"Calgary",
    "sg:classifiers":[
        {
            "category":"Health Services",
            "subcategory":"Health Practitioner",
            "type":"Services"
        }
    ],
    "sg:phone":"+1 403 262 4399",
    "sg:postcode":"T2V 4V4",
    "sg:province":"AB",
    "sg:tags":[
        "psychologist"
    ],
    "wof:name":"Horback Psychological Svc",
    "wof:placetype":"venue"
},
  "geometry": {"coordinates":[-114.07232666,50.9897613525],"type":"Point"}
}