{
  "type": "Feature",
  "properties": {
    "addr:full":"L'Annonciation QC J0T 1T0",
    "addr:postcode":"j0t 1t0",
    "iso:country":"CA",
    "sg:city":"L'Annonciation",
    "sg:classifiers":[
        {
            "category":"Travel",
            "subcategory":"Campground",
            "type":"Entertainment"
        }
    ],
    "sg:phone":"+1 819 275 2086",
    "sg:postcode":"J0T 1T0",
    "sg:province":"QC",
    "wof:name":"Boise Du Fou Du Roi Camping",
    "wof:placetype":"venue"
},
  "geometry": {"coordinates":[-74.883675,46.425343],"type":"Point"}
}