{
  "type": "Feature",
  "properties": {
    "iso:country":"CA",
    "sg:address":"115 Askin St",
    "sg:city":"London",
    "sg:classifiers":[
        {
            "category":"Organizations",
            "subcategory":"Religious Organization",
            "type":"Services"
        }
    ],
    "sg:phone":"+1 519 432 1915",
    "sg:postcode":"N6C 1E7",
    "sg:province":"ON",
    "sg:tags":[
        "church"
    ],
    "wof:name":"St James Westminister Church",
    "wof:placetype":"venue"
},
  "geometry": {"coordinates":[-81.2559127808,42.97315979],"type":"Point"}
}