{
  "type": "Feature",
  "properties": {
    "addr:full":"92 Boul Sainte-Anne Pointe-Au-Pere QC G5M 1K2",
    "addr:housenumber":"92",
    "addr:postcode":"g5m 1k2",
    "addr:street":"Boul Sainte-Anne Pointe-Au-Pere",
    "iso:country":"CA",
    "sg:address":"92 Boul Sainte-Anne",
    "sg:city":"Pointe-Au-Pere",
    "sg:classifiers":[
        {
            "category":"Travel",
            "subcategory":"Hotels & Motels",
            "type":"Entertainment"
        }
    ],
    "sg:phone":"+1 418 723 3533",
    "sg:postcode":"G5M 1K2",
    "sg:province":"QC",
    "wof:name":"Motel Marcel Enr",
    "wof:placetype":"venue"
},
  "geometry": {"coordinates":[-68.49213399999999,48.487667],"type":"Point"}
}