{
  "type": "Feature",
  "properties": {
    "addr:full":"2 Rue DE L'Hotel-DE-Ville Gaspe QC G4X 2A4",
    "addr:housenumber":"2",
    "addr:postcode":"g4x 2a4",
    "addr:street":"Rue De L'Hotel-De-Ville Gaspe",
    "iso:country":"CA",
    "sg:address":"2 Rue DE L'Hotel-DE-Ville",
    "sg:city":"Gaspe",
    "sg:classifiers":[
        {
            "category":"Home & Garden",
            "subcategory":"Carpets & Floor Coverings",
            "type":"Retail Goods"
        }
    ],
    "sg:phone":"+1 418 368 5356",
    "sg:postcode":"G4X 2A4",
    "sg:province":"QC",
    "sg:tags":[
        "dealer",
        "rug"
    ],
    "wof:name":"Maison Du Tapis Decor Gaspe",
    "wof:placetype":"venue"
},
  "geometry": {"coordinates":[-64.476738,48.825455],"type":"Point"}
}