{
  "type": "Feature",
  "properties": {
    "iso:country":"CA",
    "sg:city":"Mississauga",
    "sg:classifiers":[
        {
            "category":"Manufacturing",
            "subcategory":"Tools & Machinery",
            "type":"Manufacturing & Wholesale Goods"
        }
    ],
    "sg:phone":"+1 905 624 2002",
    "sg:postcode":"L4W 1E4",
    "sg:province":"ON",
    "sg:tags":[
        "equipment",
        "station"
    ],
    "wof:name":"Deer Dispensing Inc",
    "wof:placetype":"venue"
},
  "geometry": {"coordinates":[-79.626274,43.639473],"type":"Point"}
}