{
  "type": "Feature",
  "properties": {
    "addr:full":"126 Niagara St St Catharines ON L2R 4L4",
    "addr:housenumber":"126",
    "addr:postcode":"l2r 4l4",
    "addr:street":"Niagara St",
    "iso:country":"CA",
    "sg:address":"126 Niagara St",
    "sg:city":"St Catharines",
    "sg:classifiers":[
        {
            "category":"Social Services",
            "type":"Services"
        }
    ],
    "sg:phone":"+1 905 684 5050",
    "sg:postcode":"L2R 4L4",
    "sg:province":"ON",
    "sg:tags":[
        "counselor",
        "marriage",
        "family"
    ],
    "wof:name":"Lidkea Stob Venema & Assoc",
    "wof:placetype":"venue"
},
  "geometry": {"coordinates":[-79.2347488403,43.1690940857],"type":"Point"}
}