{
  "type": "Feature",
  "properties": {
    "addr:full":"1125 Av Du Palais Saint-Joseph-DE-Beauce QC G0S 2V0",
    "addr:housenumber":"1125",
    "addr:postcode":"g0s 2v0",
    "addr:street":"Av Du Palais",
    "iso:country":"CA",
    "sg:address":"1125 Av Du Palais",
    "sg:city":"Saint-Joseph-DE-Beauce",
    "sg:classifiers":[
        {
            "category":"Social Services",
            "type":"Services"
        }
    ],
    "sg:phone":"+1 418 397 5722",
    "sg:postcode":"G0S 2V0",
    "sg:province":"QC",
    "sg:tags":[
        "organization",
        "welfare"
    ],
    "wof:name":"Clsc Beauce-Ctr",
    "wof:placetype":"venue"
},
  "geometry": {"coordinates":[-70.8717803955,46.2994384766],"type":"Point"}
}