{
  "type": "Feature",
  "properties": {
    "addr:full":"300 West St Trenton ON K8V 2N3",
    "addr:housenumber":"300",
    "addr:postcode":"k8v 2n3",
    "addr:street":"West St",
    "iso:country":"CA",
    "sg:address":"300 West St",
    "sg:city":"Trenton",
    "sg:classifiers":[
        {
            "category":"Wholesale",
            "subcategory":"Metals & Minerals",
            "type":"Manufacturing & Wholesale Goods"
        }
    ],
    "sg:phone":"+1 613 394 1994",
    "sg:postcode":"K8V 2N3",
    "sg:province":"ON",
    "sg:tags":[
        "steel",
        "warehouse"
    ],
    "wof:name":"Crawford Metal Corp",
    "wof:placetype":"venue"
},
  "geometry": {"coordinates":[-77.581963,44.118473],"type":"Point"}
}