{
  "type": "Feature",
  "properties": {
    "addr:full":"59 Collier St Barrie ON L4M 1G7",
    "addr:housenumber":"59",
    "addr:postcode":"l4m 1g7",
    "addr:street":"Collier St",
    "iso:country":"CA",
    "sg:address":"59 Collier St",
    "sg:city":"Barrie",
    "sg:classifiers":[
        {
            "category":"Professional",
            "subcategory":"Lawyer & Legal Services",
            "type":"Services"
        }
    ],
    "sg:phone":"+1 705 726 4511",
    "sg:postcode":"L4M 1G7",
    "sg:province":"ON",
    "sg:tags":[
        "attorney"
    ],
    "wof:name":"Archibald, Peter D",
    "wof:placetype":"venue"
},
  "geometry": {"coordinates":[-79.6868896484,44.3902778625],"type":"Point"}
}