{
  "type": "Feature",
  "properties": {
    "addr:full":"1900 the Collegeway Mississauga ON L5L 5Y8",
    "addr:housenumber":"1900",
    "addr:postcode":"l5l 5y8",
    "addr:street":"The Collegeway",
    "iso:country":"CA",
    "sg:address":"1900 the Collegeway",
    "sg:city":"Mississauga",
    "sg:classifiers":[
        {
            "category":"Real Estate",
            "subcategory":"Real Estate Operator",
            "type":"Services"
        }
    ],
    "sg:phone":"+1 905 820 5445",
    "sg:postcode":"L5L 5Y8",
    "sg:province":"ON",
    "sg:tags":[
        "condominium"
    ],
    "wof:name":"Palace Security",
    "wof:placetype":"venue"
},
  "geometry": {"coordinates":[-79.67384300000001,43.546173],"type":"Point"}
}