{
  "type": "Feature",
  "properties": {
    "iso:country":"CA",
    "sg:address":"1900 the Collegeway",
    "sg:city":"Mississauga",
    "sg:classifiers":[
        {
            "category":"Real Estate",
            "subcategory":"Real Estate Operator",
            "type":"Services"
        }
    ],
    "sg:phone":"+1 905 820 5445",
    "sg:postcode":"L5L 5Y8",
    "sg:province":"ON",
    "sg:tags":[
        "condominium"
    ],
    "wof:name":"Palace Security",
    "wof:placetype":"venue"
},
  "geometry": {"coordinates":[-79.673843,43.546173],"type":"Point"}
}