{
  "type": "Feature",
  "properties": {
    "addr:full":"113 1st Ave N Kelvington SK S0A 1W0",
    "addr:housenumber":"113",
    "addr:postcode":"s0a 1w0",
    "addr:street":"1St Ave N Kelvington",
    "iso:country":"CA",
    "sg:address":"113 1st Ave N",
    "sg:city":"Kelvington",
    "sg:classifiers":[
        {
            "category":"Personal",
            "subcategory":"Beauty Salon",
            "type":"Services"
        }
    ],
    "sg:phone":"+1 306 327 4460",
    "sg:postcode":"S0A 1W0",
    "sg:province":"SK",
    "wof:name":"Nut Mountain Shear Shack",
    "wof:placetype":"venue"
},
  "geometry": {"coordinates":[-103.52950300000001,52.164566],"type":"Point"}
}