{
  "type": "Feature",
  "properties": {
    "addr:full":"1424 54 St Edson AB T7E 1H4",
    "addr:housenumber":"1424",
    "addr:postcode":"t7e 1h4",
    "addr:street":"54 St",
    "iso:country":"CA",
    "sg:address":"1424 54 St",
    "sg:city":"Edson",
    "sg:classifiers":[
        {
            "category":"Shopping",
            "type":"Retail Goods"
        }
    ],
    "sg:phone":"+1 780 723 2533",
    "sg:postcode":"T7E 1H4",
    "sg:province":"AB",
    "sg:tags":[
        "equipment",
        "wine",
        "supply"
    ],
    "wof:name":"Country Craft Wine & Beer",
    "wof:placetype":"venue"
},
  "geometry": {"coordinates":[-116.443946838,53.5913772583],"type":"Point"}
}