{
  "type": "Feature",
  "properties": {
    "addr:full":"PO Box 40 Dungannon ON N0M 1R0",
    "addr:housenumber":"po box 40",
    "addr:postcode":"n0m 1r0",
    "iso:country":"CA",
    "sg:address":"PO Box 40",
    "sg:city":"Dungannon",
    "sg:classifiers":[
        {
            "category":"Organizations",
            "subcategory":"Religious Organization",
            "type":"Services"
        }
    ],
    "sg:phone":"+1 519 529 7936",
    "sg:postcode":"N0M 1R0",
    "sg:province":"ON",
    "sg:tags":[
        "church"
    ],
    "wof:name":"United Church Manse",
    "wof:placetype":"venue"
},
  "geometry": {"coordinates":[-81.59934199999999,43.85479],"type":"Point"}
}