{
  "type": "Feature",
  "properties": {
    "addr:full":"Toronto ON M5V 3K2",
    "addr:postcode":"m5v 3k2",
    "iso:country":"CA",
    "sg:city":"Toronto",
    "sg:classifiers":[
        {
            "category":"Restaurant",
            "type":"Food & Drink"
        }
    ],
    "sg:phone":"+1 416 598 7981",
    "sg:postcode":"M5V 3K2",
    "sg:province":"ON",
    "wof:name":"Casa Manna",
    "wof:placetype":"venue"
},
  "geometry": {"coordinates":[-79.38520800000001,43.644802],"type":"Point"}
}