{
  "type": "Feature",
  "properties": {
    "iso:country":"CA",
    "sg:address":"8520 142 St NW",
    "sg:city":"Edmonton",
    "sg:classifiers":[
        {
            "category":"Wholesale",
            "subcategory":"Non-durable Goods",
            "type":"Manufacturing & Wholesale Goods"
        }
    ],
    "sg:phone":"+1 780 489 8101",
    "sg:postcode":"T5R 0M1",
    "sg:province":"AB",
    "sg:tags":[
        "calendar"
    ],
    "wof:name":"Allstar Specialties",
    "wof:placetype":"venue"
},
  "geometry": {"coordinates":[-113.56590271,53.5175209045],"type":"Point"}
}