{
  "type": "Feature",
  "properties": {
    "addr:full":"3085 Deziel Dr Windsor ON N8W 5A5",
    "addr:housenumber":"3085",
    "addr:postcode":"n8w 5a5",
    "addr:street":"Deziel Dr",
    "iso:country":"CA",
    "sg:address":"3085 Deziel Dr",
    "sg:city":"Windsor",
    "sg:classifiers":[
        {
            "category":"Wholesale",
            "subcategory":"Machinery & Supplies",
            "type":"Manufacturing & Wholesale Goods"
        }
    ],
    "sg:phone":"+1 519 948 5430",
    "sg:postcode":"N8W 5A5",
    "sg:province":"ON",
    "sg:tags":[
        "repairing"
    ],
    "wof:name":"H Beck Machinery Ltd",
    "wof:placetype":"venue"
},
  "geometry": {"coordinates":[-82.971786499,42.281993866],"type":"Point"}
}