{
  "type": "Feature",
  "properties": {
    "addr:full":"1 Monarch Rd Guelph ON N1K 1N4",
    "addr:housenumber":"1",
    "addr:postcode":"n1k 1n4",
    "addr:street":"Monarch Rd",
    "iso:country":"CA",
    "sg:address":"1 Monarch Rd",
    "sg:city":"Guelph",
    "sg:classifiers":[
        {
            "category":"Wholesale",
            "subcategory":"Machinery & Supplies",
            "type":"Manufacturing & Wholesale Goods"
        }
    ],
    "sg:phone":"+1 519 822 2020",
    "sg:postcode":"N1K 1N4",
    "sg:province":"ON",
    "sg:tags":[
        "crane",
        "parts"
    ],
    "wof:name":"Industrial Power & Control",
    "wof:placetype":"venue"
},
  "geometry": {"coordinates":[-80.305443,43.548283],"type":"Point"}
}