{
  "type": "Feature",
  "properties": {
    "iso:country":"CA",
    "sg:address":"425 Columbia St",
    "sg:city":"Kamloops",
    "sg:classifiers":[
        {
            "category":"Government",
            "subcategory":"Office",
            "type":"Public Place"
        }
    ],
    "sg:phone":"+1 250 374 5671",
    "sg:postcode":"V2C 2T4",
    "sg:province":"BC",
    "wof:name":"Life Line Ponderosa Lodge",
    "wof:placetype":"venue"
},
  "geometry": {"coordinates":[-120.331314087,50.6712722778],"type":"Point"}
}