{
  "type": "Feature",
  "properties": {
    "iso:country":"CA",
    "sg:address":"3180 Rue Masson",
    "sg:city":"Montreal",
    "sg:classifiers":[
        {
            "category":"Restaurant",
            "type":"Food & Drink"
        }
    ],
    "sg:phone":"+1 514 727 2222",
    "sg:postcode":"H1Y 1Y1",
    "sg:province":"QC",
    "wof:name":"Restaurant Reveil-Matin Diners",
    "wof:placetype":"venue"
},
  "geometry": {"coordinates":[-73.5734634399,45.5500869751],"type":"Point"}
}