{
  "type": "Feature",
  "properties": {
    "addr:full":"569 Cayley Dr London ON N6H 3G7",
    "addr:housenumber":"569",
    "addr:postcode":"n6h 3g7",
    "addr:street":"Cayley Dr",
    "iso:country":"CA",
    "sg:address":"569 Cayley Dr",
    "sg:city":"London",
    "sg:classifiers":[
        {
            "category":"Professional",
            "subcategory":"Accounting & Tax Preparation",
            "type":"Services"
        }
    ],
    "sg:phone":"+1 519 657 2586",
    "sg:postcode":"N6H 3G7",
    "sg:province":"ON",
    "sg:tags":[
        "accountant"
    ],
    "wof:name":"Prangley, Robert B CA",
    "wof:placetype":"venue"
},
  "geometry": {"coordinates":[-81.296043,42.976566],"type":"Point"}
}