{
  "type": "Feature",
  "properties": {
    "addr:full":"55 King St E Thornbury ON N0H 2P0",
    "addr:housenumber":"55",
    "addr:postcode":"n0h 2p0",
    "addr:street":"King St",
    "iso:country":"CA",
    "sg:address":"55 King St E",
    "sg:city":"Thornbury",
    "sg:classifiers":[
        {
            "category":"Autos & Motor Vehicles",
            "subcategory":"Auto Supplies",
            "type":"Retail Goods"
        }
    ],
    "sg:phone":"+1 519 599 2010",
    "sg:postcode":"N0H 2P0",
    "sg:province":"ON",
    "sg:tags":[
        "automobile",
        "parts"
    ],
    "wof:name":"Thornbury Auto Parts",
    "wof:placetype":"venue"
},
  "geometry": {"coordinates":[-80.449051,44.560932],"type":"Point"}
}