{
  "type": "Feature",
  "properties": {
    "iso:country":"CA",
    "sg:city":"Bowen Island",
    "sg:classifiers":[
        {
            "category":"Insurance",
            "subcategory":"Insurance Agent",
            "type":"Services"
        }
    ],
    "sg:phone":"+1 604 947 2113",
    "sg:postcode":"V0N 1G0",
    "sg:province":"BC",
    "wof:name":"Bowen Island Insurance",
    "wof:placetype":"venue"
},
  "geometry": {"coordinates":[-123.34191131599999,49.3798675537],"type":"Point"}
}