{
  "type": "Feature",
  "properties": {
    "addr:full":"North York ON M3J 3A4",
    "addr:postcode":"m3j 3a4",
    "iso:country":"CA",
    "sg:city":"North York",
    "sg:classifiers":[
        {
            "category":"Wholesale",
            "subcategory":"Electrical",
            "type":"Manufacturing & Wholesale Goods"
        }
    ],
    "sg:phone":"+1 416 736 3726",
    "sg:postcode":"M3J 3A4",
    "sg:province":"ON",
    "sg:tags":[
        "electric",
        "motor"
    ],
    "wof:name":"Karamian Electric Motor Svc",
    "wof:placetype":"venue"
},
  "geometry": {"coordinates":[-79.493782,43.775646],"type":"Point"}
}