{
  "type": "Feature",
  "properties": {
    "addr:full":"Red Deer AB T4N 6T3",
    "addr:postcode":"t4n 6t3",
    "iso:country":"CA",
    "sg:city":"Red Deer",
    "sg:classifiers":[
        {
            "category":"Home & Garden",
            "subcategory":"Building Materials",
            "type":"Retail Goods"
        }
    ],
    "sg:phone":"+1 403 340 1131",
    "sg:postcode":"T4N 6T3",
    "sg:province":"AB",
    "sg:tags":[
        "glass",
        "window",
        "plate"
    ],
    "wof:name":"Glass Doctors",
    "wof:placetype":"venue"
},
  "geometry": {"coordinates":[-113.802833557,52.2856483459],"type":"Point"}
}