{
  "type": "Feature",
  "properties": {
    "addr:full":"431 Queen St W Toronto ON M5V 2A5",
    "addr:housenumber":"431",
    "addr:postcode":"m5v 2a5",
    "addr:street":"Queen St W",
    "iso:country":"CA",
    "sg:address":"431 Queen St W",
    "sg:city":"Toronto",
    "sg:classifiers":[
        {
            "category":"Shopping",
            "subcategory":"Clothing, Apparel, & Fashions",
            "type":"Retail Goods"
        }
    ],
    "sg:phone":"+1 416 593 6267",
    "sg:postcode":"M5V 2A5",
    "sg:province":"ON",
    "sg:tags":[
        "leather"
    ],
    "wof:name":"Due West Clothing CO",
    "wof:placetype":"venue"
},
  "geometry": {"coordinates":[-79.39559199999999,43.648762],"type":"Point"}
}