{
  "type": "Feature",
  "properties": {
    "addr:full":"379 Rue Notre-Dame N Thetford Mines QC G6G 2S5",
    "addr:housenumber":"379",
    "addr:postcode":"g6g 2s5",
    "addr:street":"Rue Notre-Dame N",
    "iso:country":"CA",
    "sg:address":"379 Rue Notre-Dame N",
    "sg:city":"Thetford Mines",
    "sg:classifiers":[
        {
            "category":"Personal",
            "type":"Services"
        }
    ],
    "sg:phone":"+1 418 335 4095",
    "sg:postcode":"G6G 2S5",
    "sg:province":"QC",
    "sg:tags":[
        "therapist",
        "massage"
    ],
    "wof:name":"Massotherpaie Nathalie Goulet",
    "wof:placetype":"venue"
},
  "geometry": {"coordinates":[-71.294533,46.095795],"type":"Point"}
}