{
  "type": "Feature",
  "properties": {
    "iso:country":"CA",
    "sg:address":"40 Weldon St",
    "sg:city":"Moncton",
    "sg:classifiers":[
        {
            "category":"Personal",
            "subcategory":"Beauty Salon",
            "type":"Services"
        }
    ],
    "sg:phone":"+1 506 859 4333",
    "sg:postcode":"E1C 5V8",
    "sg:province":"NB",
    "wof:name":"Du Beers Hair Design",
    "wof:placetype":"venue"
},
  "geometry": {"coordinates":[-64.78684997560001,46.0869789124],"type":"Point"}
}