{
  "type": "Feature",
  "properties": {
    "addr:full":"4950 Boul Levesque E Laval QC H7C 1N1",
    "addr:housenumber":"4950",
    "addr:postcode":"h7c 1n1",
    "addr:street":"Boul Levesque E",
    "iso:country":"CA",
    "sg:address":"4950 Boul Levesque E",
    "sg:city":"Laval",
    "sg:classifiers":[
        {
            "category":"Professional",
            "subcategory":"Business Services",
            "type":"Services"
        }
    ],
    "sg:phone":"+1 450 664 2256",
    "sg:postcode":"H7C 1N1",
    "sg:province":"QC",
    "sg:tags":[
        "trophy",
        "medal",
        "award"
    ],
    "wof:name":"Meritas",
    "wof:placetype":"venue"
},
  "geometry": {"coordinates":[-73.64479064939999,45.6102676392],"type":"Point"}
}