{
  "type": "Feature",
  "properties": {
    "addr:full":"459 Rue Jacques-Bedard Lac-Saint-Charles QC G3G 1R1",
    "addr:housenumber":"459",
    "addr:postcode":"g3g 1r1",
    "addr:street":"Rue Jacques-Bedard Lac-Saint-Charles",
    "iso:country":"CA",
    "sg:address":"459 Rue Jacques-Bedard",
    "sg:city":"Lac-Saint-Charles",
    "sg:classifiers":[
        {
            "category":"Retail",
            "subcategory":"Car Wash",
            "type":"Services"
        }
    ],
    "sg:phone":"+1 418 849 4711",
    "sg:postcode":"G3G 1R1",
    "sg:province":"QC",
    "sg:tags":[
        "polishing",
        "washing"
    ],
    "wof:name":"Lave Auto Du Lac Enr",
    "wof:placetype":"venue"
},
  "geometry": {"coordinates":[-71.3698348999,46.9022827148],"type":"Point"}
}