{
  "type": "Feature",
  "properties": {
    "addr:full":"250 King St W Gananoque ON K7G 2G6",
    "addr:housenumber":"250",
    "addr:postcode":"k7g 2g6",
    "addr:street":"King St W",
    "iso:country":"CA",
    "sg:address":"250 King St W",
    "sg:city":"Gananoque",
    "sg:classifiers":[
        {
            "category":"Travel",
            "subcategory":"Hotels & Motels",
            "type":"Entertainment"
        }
    ],
    "sg:phone":"+1 613 382 3822",
    "sg:postcode":"K7G 2G6",
    "sg:province":"ON",
    "sg:tags":[
        "breakfast",
        "accommodation",
        "bed"
    ],
    "wof:name":"Athlone Inn",
    "wof:placetype":"venue"
},
  "geometry": {"coordinates":[-76.16931200000001,44.326103],"type":"Point"}
}