{
  "type": "Feature",
  "properties": {
    "addr:full":"Lynn Lake MB R0B 0W0",
    "addr:postcode":"r0b 0w0",
    "addr:street":"Lynn",
    "iso:country":"CA",
    "sg:city":"Lynn Lake",
    "sg:classifiers":[
        {
            "category":"Building & Trades",
            "subcategory":"Construction",
            "type":"Services"
        }
    ],
    "sg:phone":"+1 204 356 8008",
    "sg:postcode":"R0B 0W0",
    "sg:province":"MB",
    "sg:tags":[
        "general",
        "contractor"
    ],
    "wof:name":"Midnorth Hauling",
    "wof:placetype":"venue"
},
  "geometry": {"coordinates":[-101.048935,56.851471],"type":"Point"}
}