{
  "type": "Feature",
  "properties": {
    "addr:full":"122 5 St SE Sundre AB T0M 1X0",
    "addr:housenumber":"122 5",
    "addr:postcode":"t0m 1x0",
    "addr:street":"St Se",
    "iso:country":"CA",
    "sg:address":"122 5 St SE",
    "sg:city":"Sundre",
    "sg:classifiers":[
        {
            "category":"Food & Beverages",
            "subcategory":"Liquor & Beverages",
            "type":"Retail Goods"
        }
    ],
    "sg:phone":"+1 403 638 9334",
    "sg:postcode":"T0M 1X0",
    "sg:province":"AB",
    "sg:tags":[
        "store"
    ],
    "wof:name":"Bergen Road Liquor Store Ltd",
    "wof:placetype":"venue"
},
  "geometry": {"coordinates":[-114.63047790500001,51.7941436768],"type":"Point"}
}