{
  "type": "Feature",
  "properties": {
    "addr:full":"1030 Walker Rd Windsor ON N8Y 2N5",
    "addr:housenumber":"1030",
    "addr:postcode":"n8y 2n5",
    "addr:street":"Walker Rd",
    "iso:country":"CA",
    "sg:address":"1030 Walker Rd",
    "sg:city":"Windsor",
    "sg:classifiers":[
        {
            "category":"Shopping",
            "subcategory":"Gifts & Souvenirs",
            "type":"Retail Goods"
        }
    ],
    "sg:phone":"+1 519 252 5369",
    "sg:postcode":"N8Y 2N5",
    "sg:province":"ON",
    "sg:tags":[
        "party",
        "supply"
    ],
    "wof:name":"Party Warehouse",
    "wof:placetype":"venue"
},
  "geometry": {"coordinates":[-83.0051727295,42.3192405701],"type":"Point"}
}