{
  "type": "Feature",
  "properties": {
    "addr:full":"74 Hewitt Crt Kanata ON K2L 3R3",
    "addr:housenumber":"74",
    "addr:postcode":"k2l 3r3",
    "addr:street":"Hewitt Crt",
    "iso:country":"CA",
    "sg:address":"74 Hewitt Crt",
    "sg:city":"Kanata",
    "sg:classifiers":[
        {
            "category":"Banks & Credit Unions",
            "subcategory":"Investment Brokerage",
            "type":"Services"
        }
    ],
    "sg:phone":"+1 613 599 7118",
    "sg:postcode":"K2L 3R3",
    "sg:province":"ON",
    "sg:tags":[
        "consultant",
        "planning",
        "financial"
    ],
    "wof:name":"Clearwater Financial",
    "wof:placetype":"venue"
},
  "geometry": {"coordinates":[-75.884148,45.30484],"type":"Point"}
}