{
  "type": "Feature",
  "properties": {
    "addr:full":"8380 River Rd Delta BC V4G 1B5",
    "addr:housenumber":"8380",
    "addr:postcode":"v4g 1b5",
    "addr:street":"River Rd",
    "iso:country":"CA",
    "sg:address":"8380 River Rd",
    "sg:city":"Delta",
    "sg:classifiers":[
        {
            "category":"Building & Trades",
            "subcategory":"Construction",
            "type":"Services"
        }
    ],
    "sg:phone":"+1 604 940 0495",
    "sg:postcode":"V4G 1B5",
    "sg:province":"BC",
    "sg:tags":[
        "downspouts",
        "roofing",
        "gutter",
        "contractor"
    ],
    "wof:name":"Garden City Roofing Ltd",
    "wof:placetype":"venue"
},
  "geometry": {"coordinates":[-122.986656,49.151646],"type":"Point"}
}