{
  "type": "Feature",
  "properties": {
    "iso:country":"CA",
    "sg:address":"327 Charlotte St",
    "sg:city":"Peterborough",
    "sg:classifiers":[
        {
            "category":"Health Services",
            "subcategory":"Doctor",
            "type":"Services"
        }
    ],
    "sg:phone":"+1 705 740 6882",
    "sg:postcode":"K9J 7C3",
    "sg:province":"ON",
    "sg:tags":[
        "physician",
        "surgeon"
    ],
    "wof:name":"Kramer, B N MD",
    "wof:placetype":"venue"
},
  "geometry": {"coordinates":[-78.327469,44.302937],"type":"Point"}
}