{
  "type": "Feature",
  "properties": {
    "iso:country":"CA",
    "sg:address":"90 Wellington St N",
    "sg:city":"Hamilton",
    "sg:classifiers":[
        {
            "category":"Restaurant",
            "type":"Food & Drink"
        }
    ],
    "sg:phone":"+1 905 523 5251",
    "sg:postcode":"L8R 1N1",
    "sg:province":"ON",
    "wof:name":"Viet Nam Restaurant",
    "wof:placetype":"venue"
},
  "geometry": {"coordinates":[-79.8580245972,43.2560424805],"type":"Point"}
}