{
  "type": "Feature",
  "properties": {
    "addr:full":"428 Blake St Barrie ON L4M 1L3",
    "addr:housenumber":"428",
    "addr:postcode":"l4m 1l3",
    "addr:street":"Blake St",
    "iso:country":"CA",
    "sg:address":"428 Blake St",
    "sg:city":"Barrie",
    "sg:classifiers":[
        {
            "category":"Restaurant",
            "type":"Food & Drink"
        }
    ],
    "sg:phone":"+1 705 737 2802",
    "sg:postcode":"L4M 1L3",
    "sg:province":"ON",
    "wof:name":"Sophie's Place",
    "wof:placetype":"venue"
},
  "geometry": {"coordinates":[-79.651505,44.399364],"type":"Point"}
}