{
  "type": "Feature",
  "properties": {
    "iso:country":"CA",
    "sg:address":"800 6E Av",
    "sg:city":"Shawinigan-Sud",
    "sg:classifiers":[
        {
            "category":"Social Services",
            "type":"Services"
        }
    ],
    "sg:phone":"+1 819 536 0026",
    "sg:postcode":"G9P 5H1",
    "sg:province":"QC",
    "sg:tags":[
        "organization",
        "welfare"
    ],
    "wof:name":"Centre DE Svc En Deficience",
    "wof:placetype":"venue"
},
  "geometry": {"coordinates":[-72.7546844482,46.5250511169],"type":"Point"}
}