{
  "type": "Feature",
  "properties": {
    "iso:country":"CA",
    "sg:address":"40324 Hood Rd",
    "sg:city":"Garibaldi Highlands",
    "sg:classifiers":[
        {
            "category":"Building & Trades",
            "subcategory":"Construction",
            "type":"Services"
        }
    ],
    "sg:phone":"+1 604 898 9399",
    "sg:postcode":"V0N 1T0",
    "sg:province":"BC",
    "sg:tags":[
        "demolition",
        "contractor"
    ],
    "wof:name":"Thunder Road Blasting CO Ltd",
    "wof:placetype":"venue"
},
  "geometry": {"coordinates":[-123.130142212,49.7396774292],"type":"Point"}
}