{
  "type": "Feature",
  "properties": {
    "addr:full":"10946 125 St NW Edmonton AB T5M 0L6",
    "addr:housenumber":"10946",
    "addr:postcode":"t5m 0l6",
    "addr:street":"125 St Nw",
    "iso:country":"CA",
    "sg:address":"10946 125 St NW",
    "sg:city":"Edmonton",
    "sg:classifiers":[
        {
            "category":"Communications",
            "subcategory":"Film & Video Production",
            "type":"Services"
        }
    ],
    "sg:phone":"+1 780 944 0340",
    "sg:postcode":"T5M 0L6",
    "sg:province":"AB",
    "sg:tags":[
        "motion",
        "picture",
        "studio",
        "producer"
    ],
    "wof:name":"Blue Sky Communications Inc",
    "wof:placetype":"venue"
},
  "geometry": {"coordinates":[-113.537888,53.555244],"type":"Point"}
}