{
  "type": "Feature",
  "properties": {
    "addr:full":"3425 Roblin Blvd Winnipeg MB R3R 0C6",
    "addr:postcode":"3425;r3r 0c6",
    "addr:street":"Roblin Blvd",
    "iso:country":"CA",
    "sg:address":"3425 Roblin Blvd",
    "sg:city":"Winnipeg",
    "sg:classifiers":[
        {
            "category":"Travel",
            "subcategory":"Hotels & Motels",
            "type":"Entertainment"
        }
    ],
    "sg:phone":"+1 204 837 1391",
    "sg:postcode":"R3R 0C6",
    "sg:province":"MB",
    "sg:tags":[
        "pub"
    ],
    "wof:name":"Charleswood Motor Hotel",
    "wof:placetype":"venue"
},
  "geometry": {"coordinates":[-97.25715599999999,49.868633],"type":"Point"}
}