{
  "type": "Feature",
  "properties": {
    "addr:full":"Charlottetown PE C1A 4B3",
    "addr:postcode":"c1a 4b3",
    "iso:country":"CA",
    "sg:city":"Charlottetown",
    "sg:classifiers":[
        {
            "category":"Professional",
            "subcategory":"Lawyer & Legal Services",
            "type":"Services"
        }
    ],
    "sg:phone":"+1 902 894 7051",
    "sg:postcode":"C1A 4B3",
    "sg:province":"PE",
    "sg:tags":[
        "attorney"
    ],
    "wof:name":"Murray, M Lynn QC",
    "wof:placetype":"venue"
},
  "geometry": {"coordinates":[-63.12764,46.233891],"type":"Point"}
}