{
  "type": "Feature",
  "properties": {
    "addr:full":"4665 Fordham Rd Kelowna BC V1W 1P1",
    "addr:housenumber":"4665",
    "addr:postcode":"v1w 1p1",
    "addr:street":"Fordham Rd",
    "iso:country":"CA",
    "sg:address":"4665 Fordham Rd",
    "sg:city":"Kelowna",
    "sg:classifiers":[
        {
            "category":"Professional",
            "subcategory":"Business Services",
            "type":"Services"
        }
    ],
    "sg:phone":"+1 250 764 9132",
    "sg:postcode":"V1W 1P1",
    "sg:province":"BC",
    "sg:tags":[
        "specification",
        "architectural",
        "drafting"
    ],
    "wof:name":"Arbour Building Consultant",
    "wof:placetype":"venue"
},
  "geometry": {"coordinates":[-119.479004,49.813869],"type":"Point"}
}