{
  "type": "Feature",
  "properties": {
    "addr:full":"458 Prior St Vancouver BC V6A 2E5",
    "addr:housenumber":"458",
    "addr:postcode":"v6a 2e5",
    "addr:street":"Prior St",
    "iso:country":"CA",
    "sg:address":"458 Prior St",
    "sg:city":"Vancouver",
    "sg:classifiers":[
        {
            "category":"Wholesale",
            "subcategory":"Meat",
            "type":"Manufacturing & Wholesale Goods"
        }
    ],
    "sg:phone":"+1 604 681 1999",
    "sg:postcode":"V6A 2E5",
    "sg:province":"BC",
    "sg:tags":[
        "poultry",
        "plant",
        "processing"
    ],
    "wof:name":"Lekiu Poultry Ltd",
    "wof:placetype":"venue"
},
  "geometry": {"coordinates":[-123.09442900000001,49.276485],"type":"Point"}
}