{
  "type": "Feature",
  "properties": {
    "iso:country":"CA",
    "sg:address":"Hwy 5 E",
    "sg:city":"Humboldt",
    "sg:classifiers":[
        {
            "category":"Home & Garden",
            "subcategory":"Hardware",
            "type":"Retail Goods"
        }
    ],
    "sg:phone":"+1 306 682 2982",
    "sg:postcode":"S0K 2A0",
    "sg:province":"SK",
    "wof:name":"Peavey Mart",
    "wof:placetype":"venue"
},
  "geometry": {"coordinates":[-105.09254455599999,52.2019386292],"type":"Point"}
}