{
  "type": "Feature",
  "properties": {
    "iso:country":"CA",
    "sg:address":"4035 Rue Saint-Ambroise",
    "sg:city":"Montreal",
    "sg:classifiers":[
        {
            "category":"Professional",
            "subcategory":"Art Services",
            "type":"Services"
        }
    ],
    "sg:phone":"+1 514 939 5770",
    "sg:postcode":"H4C 2E1",
    "sg:province":"QC",
    "sg:tags":[
        "photographer"
    ],
    "wof:name":"Desjardin, Louis",
    "wof:placetype":"venue"
},
  "geometry": {"coordinates":[-73.58103179930001,45.4752807617],"type":"Point"}
}