{
  "type": "Feature",
  "properties": {
    "addr:full":"Falardeau QC G0V 1C0",
    "addr:postcode":"g0v 1c0",
    "iso:country":"CA",
    "sg:city":"Falardeau",
    "sg:classifiers":[
        {
            "category":"Wholesale",
            "subcategory":"Machinery & Supplies",
            "type":"Manufacturing & Wholesale Goods"
        }
    ],
    "sg:phone":"+1 418 673 3802",
    "sg:postcode":"G0V 1C0",
    "sg:province":"QC",
    "sg:tags":[
        "contractor"
    ],
    "wof:name":"Pierres Naturelles Tremblay",
    "wof:placetype":"venue"
},
  "geometry": {"coordinates":[-71.110336,48.620945],"type":"Point"}
}