{
  "type": "Feature",
  "properties": {
    "addr:full":"153 Ambridge Dr Iroquois Falls ON P0K 1E0",
    "addr:housenumber":"153",
    "addr:postcode":"p0k 1e0",
    "addr:street":"Ambridge Dr",
    "iso:country":"CA",
    "sg:address":"153 Ambridge Dr",
    "sg:city":"Iroquois Falls",
    "sg:classifiers":[
        {
            "category":"Health Services",
            "subcategory":"Doctor",
            "type":"Services"
        }
    ],
    "sg:phone":"+1 705 232 4073",
    "sg:postcode":"P0K 1E0",
    "sg:province":"ON",
    "sg:tags":[
        "dentist"
    ],
    "wof:name":"Vockeroth, Tom DDS",
    "wof:placetype":"venue"
},
  "geometry": {"coordinates":[-80.6834182739,48.7594032288],"type":"Point"}
}