{
  "type": "Feature",
  "properties": {
    "addr:full":"22367 Dewdney Trunk Rd Maple Ridge BC V2X 3J4",
    "addr:housenumber":"22367",
    "addr:postcode":"v2x 3j4",
    "addr:street":"Dewdney Trunk Rd",
    "iso:country":"CA",
    "sg:address":"22367 Dewdney Trunk Rd",
    "sg:city":"Maple Ridge",
    "sg:classifiers":[
        {
            "category":"Insurance",
            "subcategory":"Insurance Agent",
            "type":"Services"
        }
    ],
    "sg:phone":"+1 604 467 4184",
    "sg:postcode":"V2X 3J4",
    "sg:province":"BC",
    "wof:name":"Johnston Meier Insurance Group",
    "wof:placetype":"venue"
},
  "geometry": {"coordinates":[-122.60247,49.220638],"type":"Point"}
}