{
  "type": "Feature",
  "properties": {
    "addr:full":"4449 Hwy 24 Collingwood ON L9Y 3Z1",
    "addr:housenumber":"4449",
    "addr:postcode":"l9y 3z1",
    "addr:street":"Hwy 24",
    "iso:country":"CA",
    "sg:address":"4449 Hwy 24",
    "sg:city":"Collingwood",
    "sg:classifiers":[
        {
            "category":"Food & Beverages",
            "subcategory":"Fruits & Vegetables",
            "type":"Retail Goods"
        }
    ],
    "sg:phone":"+1 705 446 2159",
    "sg:postcode":"L9Y 3Z1",
    "sg:province":"ON",
    "sg:tags":[
        "produce"
    ],
    "wof:name":"Morrisons Berry Patch",
    "wof:placetype":"venue"
},
  "geometry": {"coordinates":[-80.215103,44.49107],"type":"Point"}
}