{
  "type": "Feature",
  "properties": {
    "addr:full":"Fort St John BC V1J 4M6",
    "addr:postcode":"v1j 4m6",
    "iso:country":"CA",
    "sg:city":"Fort St John",
    "sg:classifiers":[
        {
            "category":"Manufacturing",
            "subcategory":"Metals",
            "type":"Manufacturing & Wholesale Goods"
        }
    ],
    "sg:phone":"+1 250 785 5135",
    "sg:postcode":"V1J 4M6",
    "sg:province":"BC",
    "sg:tags":[
        "equipment",
        "oil",
        "well",
        "supply"
    ],
    "wof:name":"Argo Sales Ltd",
    "wof:placetype":"venue"
},
  "geometry": {"coordinates":[-120.786865234,56.2464599609],"type":"Point"}
}