{
  "type": "Feature",
  "properties": {
    "iso:country":"CA",
    "sg:city":"Mont-Royal",
    "sg:classifiers":[
        {
            "category":"Shopping",
            "subcategory":"Department Store",
            "type":"Retail Goods"
        }
    ],
    "sg:phone":"+1 514 738 3500",
    "sg:postcode":"H3P 3E9",
    "sg:province":"QC",
    "wof:name":"Holt Renfrew & Cie Ltee",
    "wof:placetype":"venue"
},
  "geometry": {"coordinates":[-73.648483,45.52673],"type":"Point"}
}