{
  "type": "Feature",
  "properties": {
    "addr:full":"2531 Wharton Glen Ave Mississauga ON L4X 2A8",
    "addr:housenumber":"2531",
    "addr:postcode":"l4x 2a8",
    "addr:street":"Wharton Glen Ave",
    "iso:country":"CA",
    "sg:address":"2531 Wharton Glen Ave",
    "sg:city":"Mississauga",
    "sg:classifiers":[
        {
            "category":"Retail",
            "subcategory":"Auto Repair",
            "type":"Services"
        }
    ],
    "sg:phone":"+1 905 270 7870",
    "sg:postcode":"L4X 2A8",
    "sg:province":"ON",
    "sg:tags":[
        "repairing",
        "automobile"
    ],
    "wof:name":"Martini's Automotive Specs",
    "wof:placetype":"venue"
},
  "geometry": {"coordinates":[-79.5700683594,43.6179199219],"type":"Point"}
}