{
  "type": "Feature",
  "properties": {
    "iso:country":"CA",
    "sg:city":"Saint-Laurent",
    "sg:classifiers":[
        {
            "category":"Building & Trades",
            "subcategory":"Cleaning & Sanitation",
            "type":"Services"
        }
    ],
    "sg:phone":"+1 514 920 0250",
    "sg:postcode":"H4N 1S2",
    "sg:province":"QC",
    "sg:tags":[
        "janitor"
    ],
    "wof:name":"Bo-Lav Svc D'Entretien Inc",
    "wof:placetype":"venue"
},
  "geometry": {"coordinates":[-73.66198730470001,45.5270423889],"type":"Point"}
}