{
  "type": "Feature",
  "properties": {
    "addr:full":"Plum Coulee MB R0G 1R0",
    "addr:postcode":"r0g 1r0",
    "iso:country":"CA",
    "sg:city":"Plum Coulee",
    "sg:classifiers":[
        {
            "category":"Manufacturing",
            "subcategory":"Tools & Machinery",
            "type":"Manufacturing & Wholesale Goods"
        }
    ],
    "sg:phone":"+1 204 829 2334",
    "sg:postcode":"R0G 1R0",
    "sg:province":"MB",
    "sg:tags":[
        "machine"
    ],
    "wof:name":"Giesbrecht Machining",
    "wof:placetype":"venue"
},
  "geometry": {"coordinates":[-97.7672042847,49.1894493103],"type":"Point"}
}