{
  "type": "Feature",
  "properties": {
    "iso:country":"CA",
    "sg:address":"107 Rue Bombardier",
    "sg:city":"Chateauguay",
    "sg:classifiers":[
        {
            "category":"Professional",
            "subcategory":"Art Services",
            "type":"Services"
        }
    ],
    "sg:phone":"+1 450 692 2923",
    "sg:postcode":"J6J 4Z2",
    "sg:province":"QC",
    "sg:tags":[
        "graphic",
        "printer",
        "designer"
    ],
    "wof:name":"Imprimerie DE LA Salle Inc",
    "wof:placetype":"venue"
},
  "geometry": {"coordinates":[-73.69128417970001,45.3478012085],"type":"Point"}
}