{
  "type": "Feature",
  "properties": {
    "addr:full":"523 Main Hudson QC J0P 1H0",
    "addr:housenumber":"523",
    "addr:postcode":"j0p 1h0",
    "addr:street":"Main Hudson",
    "iso:country":"CA",
    "sg:address":"523 Main",
    "sg:city":"Hudson",
    "sg:classifiers":[
        {
            "category":"Government",
            "subcategory":"Fire Station",
            "type":"Public Place"
        }
    ],
    "sg:phone":"+1 ",
    "sg:postcode":"J0P 1H0",
    "sg:province":"QC",
    "sg:tags":[
        "department"
    ],
    "wof:name":"Hudson Feu Dept",
    "wof:placetype":"venue"
},
  "geometry": {"coordinates":[-74.14483642579999,45.4599990845],"type":"Point"}
}