{
  "type": "Feature",
  "properties": {
    "addr:full":"228 Bonis Ave Scarborough ON M1T 3W4",
    "addr:housenumber":"228",
    "addr:postcode":"m1t 3w4",
    "addr:street":"Bonis Ave",
    "iso:country":"CA",
    "sg:address":"228 Bonis Ave",
    "sg:city":"Scarborough",
    "sg:classifiers":[
        {
            "category":"Wholesale",
            "subcategory":"Electrical",
            "type":"Manufacturing & Wholesale Goods"
        }
    ],
    "sg:phone":"+1 416 291 3868",
    "sg:postcode":"M1T 3W4",
    "sg:province":"ON",
    "sg:tags":[
        "game",
        "video"
    ],
    "wof:name":"Universal Space Video Game Ltd",
    "wof:placetype":"venue"
},
  "geometry": {"coordinates":[-79.2925033569,43.7861061096],"type":"Point"}
}