{
  "type": "Feature",
  "properties": {
    "addr:full":"543 Av Saint-Jacques Louiseville QC J5V 1E2",
    "addr:postcode":"j5v 1e2",
    "addr:street":"543 Av Saint-Jacques",
    "iso:country":"CA",
    "sg:address":"543 Av Saint-Jacques",
    "sg:city":"Louiseville",
    "sg:classifiers":[
        {
            "category":"Manufacturing",
            "subcategory":"Tools & Machinery",
            "type":"Manufacturing & Wholesale Goods"
        }
    ],
    "sg:phone":"+1 819 228 4423",
    "sg:postcode":"J5V 1E2",
    "sg:province":"QC",
    "sg:tags":[
        "electric",
        "motor"
    ],
    "wof:name":"Luc Gagnon Electrique Inc",
    "wof:placetype":"venue"
},
  "geometry": {"coordinates":[-72.9502792358,46.2570304871],"type":"Point"}
}