{
  "type": "Feature",
  "properties": {
    "iso:country":"CA",
    "sg:address":"27 Rue Marie-DE-L'Incarnation",
    "sg:city":"Quebec",
    "sg:classifiers":[
        {
            "category":"Professional",
            "subcategory":"Art Services",
            "type":"Services"
        }
    ],
    "sg:phone":"+1 418 683 1285",
    "sg:postcode":"G1N 3E5",
    "sg:province":"QC",
    "sg:tags":[
        "graphic",
        "publishing",
        "designer"
    ],
    "wof:name":"Compo-Alphatek Inc",
    "wof:placetype":"venue"
},
  "geometry": {"coordinates":[-71.419472,46.858582],"type":"Point"}
}