{
  "type": "Feature",
  "properties": {
    "addr:full":"3060 Airport Rd Penticton BC V2A 8X1",
    "addr:housenumber":"3060",
    "addr:postcode":"v2a 8x1",
    "addr:street":"Airport Rd",
    "iso:country":"CA",
    "sg:address":"3060 Airport Rd",
    "sg:city":"Penticton",
    "sg:classifiers":[
        {
            "category":"Airport",
            "type":"Transportation"
        }
    ],
    "sg:phone":"+1 250 493 5323",
    "sg:postcode":"V2A 8X1",
    "sg:province":"BC",
    "sg:tags":[
        "aircraft",
        "maintenance"
    ],
    "wof:name":"Spencer Aviation Svc Ltd",
    "wof:placetype":"venue"
},
  "geometry": {"coordinates":[-119.60533100000001,49.460625],"type":"Point"}
}