{
  "type": "Feature",
  "properties": {
    "addr:full":"18 Kemper Cres Headingley MB R4J 1A6",
    "addr:housenumber":"18",
    "addr:postcode":"r4j 1a6",
    "addr:street":"Kemper Cres",
    "iso:country":"CA",
    "sg:address":"18 Kemper Cres",
    "sg:city":"Headingley",
    "sg:classifiers":[
        {
            "category":"Building & Trades",
            "subcategory":"Construction",
            "type":"Services"
        }
    ],
    "sg:phone":"+1 204 837 1802",
    "sg:postcode":"R4J 1A6",
    "sg:province":"MB",
    "sg:tags":[
        "excavating",
        "contractor"
    ],
    "wof:name":"Wilkes Enterprises Ltd",
    "wof:placetype":"venue"
},
  "geometry": {"coordinates":[-97.412758,49.864475],"type":"Point"}
}