{
  "type": "Feature",
  "properties": {
    "addr:full":"1245 Rte Marie-Victorin O Deschaillons-Sur-Saint-Laurent QC G0S 1G0",
    "addr:housenumber":"1245",
    "addr:postcode":"g0s 1g0",
    "addr:street":"Rte Marie-Victorin O",
    "iso:country":"CA",
    "sg:address":"1245 Rte Marie-Victorin O",
    "sg:city":"Deschaillons-Sur-Saint-Laurent",
    "sg:classifiers":[
        {
            "category":"Food & Beverages",
            "subcategory":"Groceries & Convenience Stores",
            "type":"Retail Goods"
        }
    ],
    "sg:phone":"+1 819 292 2822",
    "sg:postcode":"G0S 1G0",
    "sg:province":"QC",
    "wof:name":"Depanneur Deschaillons Enr",
    "wof:placetype":"venue"
},
  "geometry": {"coordinates":[-72.119919,46.554775],"type":"Point"}
}