{
  "type": "Feature",
  "properties": {
    "addr:full":"409 Boul Renault Beauceville QC G5X 1N7",
    "addr:housenumber":"409",
    "addr:postcode":"g5x 1n7",
    "addr:street":"Boul Renault",
    "iso:country":"CA",
    "sg:address":"409 Boul Renault",
    "sg:city":"Beauceville",
    "sg:classifiers":[
        {
            "category":"Wholesale",
            "subcategory":"Metals & Minerals",
            "type":"Manufacturing & Wholesale Goods"
        }
    ],
    "sg:phone":"+1 418 774 9881",
    "sg:postcode":"G5X 1N7",
    "sg:province":"QC",
    "sg:tags":[
        "iron"
    ],
    "wof:name":"Quirion Metal Inc",
    "wof:placetype":"venue"
},
  "geometry": {"coordinates":[-70.797791,46.225094],"type":"Point"}
}