{
  "type": "Feature",
  "properties": {
    "addr:full":"2751 Kingsway Vancouver BC V5R 5H4",
    "addr:housenumber":"2751",
    "addr:postcode":"v5r 5h4",
    "addr:street":"Kingsway",
    "iso:country":"CA",
    "sg:address":"2751 Kingsway",
    "sg:city":"Vancouver",
    "sg:classifiers":[
        {
            "category":"Home & Garden",
            "subcategory":"Furniture",
            "type":"Retail Goods"
        }
    ],
    "sg:phone":"+1 604 434 3151",
    "sg:postcode":"V5R 5H4",
    "sg:province":"BC",
    "sg:tags":[
        "plumbing",
        "contractor"
    ],
    "wof:name":"Harvey's Stores Ltd",
    "wof:placetype":"venue"
},
  "geometry": {"coordinates":[-123.04894256599999,49.2377815247],"type":"Point"}
}