{
  "type": "Feature",
  "properties": {
    "addr:full":"Lloydminster AB T9V 2G1",
    "addr:postcode":"t9v 2g1",
    "iso:country":"CA",
    "sg:city":"Lloydminster",
    "sg:classifiers":[
        {
            "category":"Building & Trades",
            "subcategory":"Electrical",
            "type":"Services"
        }
    ],
    "sg:phone":"+1 780 875 3336",
    "sg:postcode":"T9V 2G1",
    "sg:province":"AB",
    "sg:tags":[
        "electric",
        "contractor"
    ],
    "wof:name":"Harris Electric CO Ltd",
    "wof:placetype":"venue"
},
  "geometry": {"coordinates":[-110.03460699999999,53.28194],"type":"Point"}
}