{
  "type": "Feature",
  "properties": {
    "addr:full":"25 Poynter Dr Etobicoke ON M9R 1K8",
    "addr:housenumber":"25",
    "addr:postcode":"m9r 1k8",
    "addr:street":"Poynter Dr",
    "iso:country":"CA",
    "sg:address":"25 Poynter Dr",
    "sg:city":"Etobicoke",
    "sg:classifiers":[
        {
            "category":"Social Services",
            "subcategory":"Child Care",
            "type":"Services"
        }
    ],
    "sg:phone":"+1 416 241 2000",
    "sg:postcode":"M9R 1K8",
    "sg:province":"ON",
    "wof:name":"Gold Circle Early Childhood",
    "wof:placetype":"venue"
},
  "geometry": {"coordinates":[-79.54853799999999,43.691166],"type":"Point"}
}