{
  "type": "Feature",
  "properties": {
    "addr:full":"240 Commissioners Rd W London ON N6J 1Y1",
    "addr:housenumber":"240",
    "addr:postcode":"n6j 1y1",
    "addr:street":"Commissioners Rd W",
    "iso:country":"CA",
    "sg:address":"240 Commissioners Rd W",
    "sg:city":"London",
    "sg:classifiers":[
        {
            "category":"Insurance",
            "subcategory":"Insurance Agent",
            "type":"Services"
        }
    ],
    "sg:phone":"+1 519 681 6811",
    "sg:postcode":"N6J 1Y1",
    "sg:province":"ON",
    "wof:name":"Joseph Kastelanac Insurance",
    "wof:placetype":"venue"
},
  "geometry": {"coordinates":[-81.272186,42.956203],"type":"Point"}
}