{
  "type": "Feature",
  "properties": {
    "addr:full":"5 Rue Saint-Jean-Baptiste E Montmagny QC G5V 1J6",
    "addr:housenumber":"5",
    "addr:postcode":"g5v 1j6",
    "addr:street":"Rue Saint-Jean-Baptiste E",
    "iso:country":"CA",
    "sg:address":"5 Rue Saint-Jean-Baptiste E",
    "sg:city":"Montmagny",
    "sg:classifiers":[
        {
            "category":"Health Services",
            "subcategory":"Nursing And Care Facility",
            "type":"Services"
        }
    ],
    "sg:phone":"+1 418 248 2090",
    "sg:postcode":"G5V 1J6",
    "sg:province":"QC",
    "sg:tags":[
        "home",
        "retirement",
        "community"
    ],
    "wof:name":"Chateau Canadien",
    "wof:placetype":"venue"
},
  "geometry": {"coordinates":[-70.5626907349,46.9795761108],"type":"Point"}
}