{
  "type": "Feature",
  "properties": {
    "addr:full":"231 Pitt St Cornwall ON K6J 3P8",
    "addr:housenumber":"231",
    "addr:postcode":"k6j 3p8",
    "addr:street":"Pitt St",
    "iso:country":"CA",
    "sg:address":"231 Pitt St",
    "sg:city":"Cornwall",
    "sg:classifiers":[
        {
            "category":"Travel",
            "subcategory":"Travel Agent",
            "type":"Entertainment"
        }
    ],
    "sg:phone":"+1 613 938 6401",
    "sg:postcode":"K6J 3P8",
    "sg:province":"ON",
    "sg:tags":[
        "agency",
        "bureau"
    ],
    "wof:name":"Ferns Travel Agency & Custom",
    "wof:placetype":"venue"
},
  "geometry": {"coordinates":[-74.72882799999999,45.018856],"type":"Point"}
}