{
  "type": "Feature",
  "properties": {
    "addr:full":"5807 142 St NW Edmonton AB T6H 4C3",
    "addr:housenumber":"5807",
    "addr:postcode":"t6h 4c3",
    "addr:street":"142 St Nw",
    "iso:country":"CA",
    "sg:address":"5807 142 St NW",
    "sg:city":"Edmonton",
    "sg:classifiers":[
        {
            "category":"Building & Trades",
            "subcategory":"Construction",
            "type":"Services"
        }
    ],
    "sg:phone":"+1 780 433 1736",
    "sg:postcode":"T6H 4C3",
    "sg:province":"AB",
    "sg:tags":[
        "general",
        "contractor"
    ],
    "wof:name":"Aarlex Construction Ltd",
    "wof:placetype":"venue"
},
  "geometry": {"coordinates":[-113.56477356000001,53.4952545166],"type":"Point"}
}