{
  "type": "Feature",
  "properties": {
    "addr:full":"5638 Inlet Ave Sechelt BC V0N 3A0",
    "addr:housenumber":"5638",
    "addr:postcode":"v0n 3a0",
    "addr:street":"Inlet Ave",
    "iso:country":"CA",
    "sg:address":"5638 Inlet Ave",
    "sg:city":"Sechelt",
    "sg:classifiers":[
        {
            "category":"Social Services",
            "type":"Services"
        }
    ],
    "sg:phone":"+1 604 885 5881",
    "sg:postcode":"V0N 3A0",
    "sg:province":"BC",
    "sg:tags":[
        "organization",
        "welfare"
    ],
    "wof:name":"Parent-Tot Drop-In",
    "wof:placetype":"venue"
},
  "geometry": {"coordinates":[-123.756241,49.476177],"type":"Point"}
}