{
  "type": "Feature",
  "properties": {
    "iso:country":"CA",
    "sg:city":"Delta",
    "sg:classifiers":[
        {
            "category":"Health Services",
            "subcategory":"Doctor",
            "type":"Services"
        }
    ],
    "sg:phone":"+1 604 946 9588",
    "sg:postcode":"V4K 2K5",
    "sg:province":"BC",
    "sg:tags":[
        "dentist"
    ],
    "wof:name":"Ariss, C A DDS",
    "wof:placetype":"venue"
},
  "geometry": {"coordinates":[-123.085548,49.0924],"type":"Point"}
}