{
  "type": "Feature",
  "properties": {
    "iso:country":"CA",
    "sg:address":"1001 Rue Saint-Dominique",
    "sg:city":"Montreal",
    "sg:classifiers":[
        {
            "category":"Real Estate",
            "subcategory":"Real Estate Operator",
            "type":"Services"
        }
    ],
    "sg:phone":"+1 514 395 8636",
    "sg:postcode":"H2X 2W1",
    "sg:province":"QC",
    "sg:tags":[
        "apartment"
    ],
    "wof:name":"Montreal Chinese Community",
    "wof:placetype":"venue"
},
  "geometry": {"coordinates":[-73.5583190918,45.5081672668],"type":"Point"}
}