{
  "type": "Feature",
  "properties": {
    "addr:full":"1237 Ch DE LA 3E-Concession Noyan QC J0J 1B0",
    "addr:housenumber":"1237",
    "addr:postcode":"j0j 1b0",
    "addr:street":"Ch De La 3E-Concession",
    "iso:country":"CA",
    "sg:address":"1237 Ch DE LA 3E-Concession",
    "sg:city":"Noyan",
    "sg:classifiers":[
        {
            "category":"Travel",
            "subcategory":"Hotels & Motels",
            "type":"Entertainment"
        }
    ],
    "sg:phone":"+1 450 294 2327",
    "sg:postcode":"J0J 1B0",
    "sg:province":"QC",
    "wof:name":"Hotel Noyan Inn",
    "wof:placetype":"venue"
},
  "geometry": {"coordinates":[-73.299217,45.060795],"type":"Point"}
}