{
  "type": "Feature",
  "properties": {
    "addr:full":"Calgary AB T2H 2S5",
    "addr:postcode":"t2h 2s5",
    "iso:country":"CA",
    "sg:city":"Calgary",
    "sg:classifiers":[
        {
            "category":"Professional",
            "subcategory":"Management & Consulting",
            "type":"Services"
        }
    ],
    "sg:phone":"+1 403 294 1583",
    "sg:postcode":"T2H 2S5",
    "sg:province":"AB",
    "sg:tags":[
        "consultant",
        "safety"
    ],
    "wof:name":"Vision Hse Management Svc",
    "wof:placetype":"venue"
},
  "geometry": {"coordinates":[-114.036705,50.989555],"type":"Point"}
}