{
  "type": "Feature",
  "properties": {
    "addr:full":"1 Mall Dr Parry Sound ON P2A 3A9",
    "addr:housenumber":"1",
    "addr:postcode":"p2a 3a9",
    "addr:street":"Mall Dr",
    "iso:country":"CA",
    "sg:address":"1 Mall Dr",
    "sg:city":"Parry Sound",
    "sg:classifiers":[
        {
            "category":"Shopping",
            "type":"Retail Goods"
        }
    ],
    "sg:phone":"+1 705 746 5010",
    "sg:postcode":"P2A 3A9",
    "sg:province":"ON",
    "sg:tags":[
        "pet",
        "food",
        "supply"
    ],
    "wof:name":"Parry Sound Pet Stop",
    "wof:placetype":"venue"
},
  "geometry": {"coordinates":[-80.040291,45.360477],"type":"Point"}
}