{
  "type": "Feature",
  "properties": {
    "addr:full":"5260 Av Ponsard Montreal QC H3W 2A8",
    "addr:housenumber":"5260",
    "addr:postcode":"h3w 2a8",
    "addr:street":"Av Ponsard",
    "iso:country":"CA",
    "sg:address":"5260 Av Ponsard",
    "sg:city":"Montreal",
    "sg:classifiers":[
        {
            "category":"Personal",
            "type":"Services"
        }
    ],
    "sg:phone":"+1 514 487 9555",
    "sg:postcode":"H3W 2A8",
    "sg:province":"QC",
    "sg:tags":[
        "control",
        "weight"
    ],
    "wof:name":"Images 2000 Controle Du Poids",
    "wof:placetype":"venue"
},
  "geometry": {"coordinates":[-73.62367248539999,45.4819602966],"type":"Point"}
}