{
  "type": "Feature",
  "properties": {
    "addr:full":"12 King St E Hamilton ON L8N 1A3",
    "addr:housenumber":"12",
    "addr:postcode":"l8n 1a3",
    "addr:street":"King St E",
    "iso:country":"CA",
    "sg:address":"12 King St E",
    "sg:city":"Hamilton",
    "sg:classifiers":[
        {
            "category":"Banks & Credit Unions",
            "subcategory":"Bank",
            "type":"Services"
        }
    ],
    "sg:phone":"+1 905 528 7501",
    "sg:postcode":"L8N 1A3",
    "sg:province":"ON",
    "wof:name":"Scotiabank",
    "wof:placetype":"venue"
},
  "geometry": {"coordinates":[-79.86895,43.256062],"type":"Point"}
}