{
  "type": "Feature",
  "properties": {
    "addr:full":"10 Wilony Rd Loretto ON L0G 1L0",
    "addr:housenumber":"10",
    "addr:postcode":"l0g 1l0",
    "addr:street":"Wilony Rd",
    "iso:country":"CA",
    "sg:address":"10 Wilony Rd",
    "sg:city":"Loretto",
    "sg:classifiers":[
        {
            "category":"Home & Garden",
            "subcategory":"Household Appliances",
            "type":"Retail Goods"
        }
    ],
    "sg:phone":"+1 905 936 2494",
    "sg:postcode":"L0G 1L0",
    "sg:province":"ON",
    "wof:name":"Affordable High Tech Appl Svc",
    "wof:placetype":"venue"
},
  "geometry": {"coordinates":[-79.888367,44.049278],"type":"Point"}
}