{
  "type": "Feature",
  "properties": {
    "iso:country":"CA",
    "sg:address":"164 Rue Principale",
    "sg:city":"Aylmer",
    "sg:classifiers":[
        {
            "category":"Organizations",
            "subcategory":"Religious Organization",
            "type":"Services"
        }
    ],
    "sg:phone":"+1 819 684 5345",
    "sg:postcode":"J9H 3M8",
    "sg:province":"QC",
    "sg:tags":[
        "church"
    ],
    "wof:name":"Aylmer United Church",
    "wof:placetype":"venue"
},
  "geometry": {"coordinates":[-75.838760376,45.3951950073],"type":"Point"}
}