{
  "type": "Feature",
  "properties": {
    "iso:country":"CA",
    "sg:address":"590 Main St",
    "sg:city":"Mahone Bay",
    "sg:classifiers":[
        {
            "category":"Home & Garden",
            "subcategory":"Home Furnishings",
            "type":"Retail Goods"
        }
    ],
    "sg:phone":"+1 902 624 9447",
    "sg:postcode":"B0J 2E0",
    "sg:province":"NS",
    "sg:tags":[
        "pottery"
    ],
    "wof:name":"Birdsall-Worthington Pottery",
    "wof:placetype":"venue"
},
  "geometry": {"coordinates":[-64.3782653809,44.4485588074],"type":"Point"}
}