{
  "type": "Feature",
  "properties": {
    "addr:full":"245 Rue Saint-Georges Saint-Jerome QC J7Z 5A1",
    "addr:housenumber":"245",
    "addr:postcode":"j7z 5a1",
    "addr:street":"Rue Saint-Georges Saint-Jerome",
    "iso:country":"CA",
    "sg:address":"245 Rue Saint-Georges",
    "sg:city":"Saint-Jerome",
    "sg:classifiers":[
        {
            "category":"Restaurant",
            "type":"Food & Drink"
        }
    ],
    "sg:phone":"+1 450 565 6262",
    "sg:postcode":"J7Z 5A1",
    "sg:province":"QC",
    "wof:name":"Restaurant Bel Azur",
    "wof:placetype":"venue"
},
  "geometry": {"coordinates":[-74.002754,45.774731],"type":"Point"}
}