{
  "type": "Feature",
  "properties": {
    "addr:full":"236 Broadway Orangeville ON L9W 1K5",
    "addr:housenumber":"236",
    "addr:postcode":"l9w 1k5",
    "addr:street":"Broadway",
    "iso:country":"CA",
    "sg:address":"236 Broadway",
    "sg:city":"Orangeville",
    "sg:classifiers":[
        {
            "category":"Retail",
            "subcategory":"Veterinary Services",
            "type":"Services"
        }
    ],
    "sg:phone":"+1 519 941 2275",
    "sg:postcode":"L9W 1K5",
    "sg:province":"ON",
    "sg:tags":[
        "veterinarian"
    ],
    "wof:name":"Orangeville Animal Hospital",
    "wof:placetype":"venue"
},
  "geometry": {"coordinates":[-80.099503,43.918652],"type":"Point"}
}