{
  "type": "Feature",
  "properties": {
    "addr:full":"Orillia ON L3V 5S2",
    "addr:postcode":"l3v 5s2",
    "iso:country":"CA",
    "sg:city":"Orillia",
    "sg:classifiers":[
        {
            "category":"Health Services",
            "subcategory":"Doctor",
            "type":"Services"
        }
    ],
    "sg:phone":"+1 705 326 4401",
    "sg:postcode":"L3V 5S2",
    "sg:province":"ON",
    "sg:tags":[
        "physician",
        "surgeon"
    ],
    "wof:name":"Daniel, Peter MD",
    "wof:placetype":"venue"
},
  "geometry": {"coordinates":[-79.418228,44.60659],"type":"Point"}
}