{
  "type": "Feature",
  "properties": {
    "addr:full":"460 Main Rd Hudson QC J0P 1H0",
    "addr:housenumber":"460",
    "addr:postcode":"j0p 1h0",
    "addr:street":"Main Rd",
    "iso:country":"CA",
    "sg:address":"460 Main Rd",
    "sg:city":"Hudson",
    "sg:classifiers":[
        {
            "category":"Bars & Pubs",
            "type":"Food & Drink"
        }
    ],
    "sg:phone":"+1 450 458 4092",
    "sg:postcode":"J0P 1H0",
    "sg:province":"QC",
    "sg:tags":[
        "lounge",
        "cocktail"
    ],
    "wof:name":"Chateau Du Lac Bar Enrg",
    "wof:placetype":"venue"
},
  "geometry": {"coordinates":[-74.1408081055,45.4588394165],"type":"Point"}
}