{
  "type": "Feature",
  "properties": {
    "addr:full":"Lloydminster SK S9V 0P6",
    "addr:postcode":"s9v 0p6",
    "iso:country":"CA",
    "sg:city":"Lloydminster",
    "sg:classifiers":[
        {
            "category":"Home & Garden",
            "subcategory":"Furniture",
            "type":"Retail Goods"
        }
    ],
    "sg:phone":"+1 306 825 3060",
    "sg:postcode":"S9V 0P6",
    "sg:province":"SK",
    "wof:name":"Reynolds Discount Sofas & Beds",
    "wof:placetype":"venue"
},
  "geometry": {"coordinates":[-110.005402,53.281754],"type":"Point"}
}