{
  "type": "Feature",
  "properties": {
    "addr:full":"2470 Dougall Ave Windsor ON N8X 1T2",
    "addr:housenumber":"2470",
    "addr:postcode":"n8x 1t2",
    "addr:street":"Dougall Ave",
    "iso:country":"CA",
    "sg:address":"2470 Dougall Ave",
    "sg:city":"Windsor",
    "sg:classifiers":[
        {
            "category":"Government",
            "subcategory":"Office",
            "type":"Public Place"
        }
    ],
    "sg:phone":"+1 519 972 7349",
    "sg:postcode":"N8X 1T2",
    "sg:province":"ON",
    "wof:name":"Ontario Driver Examination",
    "wof:placetype":"venue"
},
  "geometry": {"coordinates":[-83.022598,42.286755],"type":"Point"}
}