{
  "type": "Feature",
  "properties": {
    "addr:full":"Renous NB E9E 2E8",
    "addr:postcode":"e9e 2e8",
    "iso:country":"CA",
    "sg:city":"Renous",
    "sg:classifiers":[
        {
            "category":"Home & Garden",
            "subcategory":"Building Materials",
            "type":"Retail Goods"
        }
    ],
    "sg:phone":"+1 506 627 0807",
    "sg:postcode":"E9E 2E8",
    "sg:province":"NB",
    "sg:tags":[
        "glass",
        "leaded"
    ],
    "wof:name":"Schofield Stainedglass & Wood",
    "wof:placetype":"venue"
},
  "geometry": {"coordinates":[-65.796654,46.814064],"type":"Point"}
}