{
  "type": "Feature",
  "properties": {
    "iso:country":"CA",
    "sg:address":"3650 Boul Des Sources",
    "sg:city":"Dollard-Des-Ormeaux",
    "sg:classifiers":[
        {
            "category":"Autos & Motor Vehicles",
            "subcategory":"Automobile Sales",
            "type":"Retail Goods"
        }
    ],
    "sg:phone":"+1 514 683 5533",
    "sg:postcode":"H9B 1Z9",
    "sg:province":"QC",
    "sg:tags":[
        "car",
        "dealer"
    ],
    "wof:name":"Civic Honda Ddo Svc",
    "wof:placetype":"venue"
},
  "geometry": {"coordinates":[-73.800919,45.487888],"type":"Point"}
}