{
  "type": "Feature",
  "properties": {
    "iso:country":"CA",
    "sg:address":"505 Charlotte St",
    "sg:city":"Fredericton",
    "sg:classifiers":[
        {
            "category":"Health Services",
            "subcategory":"Doctor",
            "type":"Services"
        }
    ],
    "sg:phone":"+1 506 454 6326",
    "sg:postcode":"E3B 1M1",
    "sg:province":"NB",
    "sg:tags":[
        "dentist"
    ],
    "wof:name":"Mac Kenzie, Michael R DDS",
    "wof:placetype":"venue"
},
  "geometry": {"coordinates":[-66.643723,45.958256],"type":"Point"}
}