{
  "type": "Feature",
  "properties": {
    "addr:full":"1840 London Line Sarnia ON N7T 7H2",
    "addr:housenumber":"1840",
    "addr:postcode":"n7t 7h2",
    "addr:street":"London Line",
    "iso:country":"CA",
    "sg:address":"1840 London Line",
    "sg:city":"Sarnia",
    "sg:classifiers":[
        {
            "category":"Home & Garden",
            "subcategory":"Garden Supply",
            "type":"Retail Goods"
        }
    ],
    "sg:phone":"+1 519 542 3435",
    "sg:postcode":"N7T 7H2",
    "sg:province":"ON",
    "sg:tags":[
        "center"
    ],
    "wof:name":"DE Groot's Nurseries",
    "wof:placetype":"venue"
},
  "geometry": {"coordinates":[-82.318703,42.983727],"type":"Point"}
}