{
  "type": "Feature",
  "properties": {
    "addr:full":"Owen Sound ON N4K 5W4",
    "addr:postcode":"n4k 5w4",
    "iso:country":"CA",
    "sg:city":"Owen Sound",
    "sg:classifiers":[
        {
            "category":"Building & Trades",
            "subcategory":"Equipment Rental",
            "type":"Services"
        }
    ],
    "sg:phone":"+1 519 372 2025",
    "sg:postcode":"N4K 5W4",
    "sg:province":"ON",
    "sg:tags":[
        "crane"
    ],
    "wof:name":"Vanwyck Crane Svc Ltd",
    "wof:placetype":"venue"
},
  "geometry": {"coordinates":[-80.92259979249999,44.5740585327],"type":"Point"}
}