{
  "type": "Feature",
  "properties": {
    "addr:full":"Quebec QC G2K 2K2",
    "addr:postcode":"g2k 2k2",
    "iso:country":"CA",
    "sg:city":"Quebec",
    "sg:classifiers":[
        {
            "category":"Recreation",
            "type":"Entertainment"
        }
    ],
    "sg:phone":"+1 418 683 1989",
    "sg:postcode":"G2K 2K2",
    "sg:province":"QC",
    "sg:tags":[
        "tours",
        "guide",
        "sightseeing"
    ],
    "wof:name":"Pro Guide Quebec Inc",
    "wof:placetype":"venue"
},
  "geometry": {"coordinates":[-71.292862,46.837776],"type":"Point"}
}