{
  "type": "Feature",
  "properties": {
    "addr:full":"Joliette QC J6E 4T3",
    "addr:postcode":"j6e 4t3",
    "iso:country":"CA",
    "sg:city":"Joliette",
    "sg:classifiers":[
        {
            "category":"Arts & Performance",
            "subcategory":"Theater",
            "type":"Entertainment"
        }
    ],
    "sg:phone":"+1 450 752 0403",
    "sg:postcode":"J6E 4T3",
    "sg:province":"QC",
    "wof:name":"Theatre DE Zef",
    "wof:placetype":"venue"
},
  "geometry": {"coordinates":[-73.43692,46.024197],"type":"Point"}
}