{
  "type": "Feature",
  "properties": {
    "addr:full":"209 Maple St W Whitby ON L1N 2Z9",
    "addr:housenumber":"209",
    "addr:postcode":"l1n 2z9",
    "addr:street":"Maple St W",
    "iso:country":"CA",
    "sg:address":"209 Maple St W",
    "sg:city":"Whitby",
    "sg:classifiers":[
        {
            "category":"Building & Trades",
            "subcategory":"Construction",
            "type":"Services"
        }
    ],
    "sg:phone":"+1 905 668 3649",
    "sg:postcode":"L1N 2Z9",
    "sg:province":"ON",
    "sg:tags":[
        "painter"
    ],
    "wof:name":"Mike's Painting & Decorating",
    "wof:placetype":"venue"
},
  "geometry": {"coordinates":[-78.94650268549999,43.8860816956],"type":"Point"}
}