{
  "type": "Feature",
  "properties": {
    "iso:country":"CA",
    "sg:city":"Victoria",
    "sg:classifiers":[
        {
            "category":"Health Services",
            "subcategory":"Doctor",
            "type":"Services"
        }
    ],
    "sg:phone":"+1 250 384 2733",
    "sg:postcode":"V8V 3P9",
    "sg:province":"BC",
    "sg:tags":[
        "physician",
        "surgeon"
    ],
    "wof:name":"Atkins, Christopher MD",
    "wof:placetype":"venue"
},
  "geometry": {"coordinates":[-123.352837,48.426678],"type":"Point"}
}