{
  "type": "Feature",
  "properties": {
    "iso:country":"CA",
    "sg:address":"151 Du Portage Prom",
    "sg:city":"Hull",
    "sg:classifiers":[
        {
            "category":"Shopping",
            "subcategory":"Tobacco",
            "type":"Retail Goods"
        }
    ],
    "sg:phone":"+1 819 777 0383",
    "sg:postcode":"J8X 2K4",
    "sg:province":"QC",
    "sg:tags":[
        "cigarette",
        "cigar",
        "dealer"
    ],
    "wof:name":"Tabagie L'Humidor",
    "wof:placetype":"venue"
},
  "geometry": {"coordinates":[-75.7160110474,45.4261627197],"type":"Point"}
}