{
  "type": "Feature",
  "properties": {
    "iso:country":"CA",
    "sg:city":"Bay Roberts",
    "sg:classifiers":[
        {
            "category":"Shopping",
            "subcategory":"Catalog Store",
            "type":"Retail Goods"
        }
    ],
    "sg:phone":"+1 709 786 7165",
    "sg:postcode":"A0A 1G0",
    "sg:province":"NL",
    "sg:tags":[
        "mail",
        "order",
        "internet"
    ],
    "wof:name":"Sears Canada Inc",
    "wof:placetype":"venue"
},
  "geometry": {"coordinates":[-53.2815093994,47.583984375],"type":"Point"}
}