{
  "type": "Feature",
  "properties": {
    "addr:full":"674 Briar Hill Ave Toronto ON M6B 1L3",
    "addr:housenumber":"674",
    "addr:postcode":"m6b 1l3",
    "addr:street":"Briar Hill Ave",
    "iso:country":"CA",
    "sg:address":"674 Briar Hill Ave",
    "sg:city":"Toronto",
    "sg:classifiers":[
        {
            "category":"Utilities",
            "subcategory":"Telephone",
            "type":"Services"
        }
    ],
    "sg:phone":"+1 905 729 0709",
    "sg:postcode":"M6B 1L3",
    "sg:province":"ON",
    "sg:tags":[
        "company"
    ],
    "wof:name":"Telehop Communications Inc",
    "wof:placetype":"venue"
},
  "geometry": {"coordinates":[-79.42919921879999,43.707572937],"type":"Point"}
}