{
  "type": "Feature",
  "properties": {
    "addr:full":"Burford ON N0E 1A0",
    "addr:postcode":"n0e 1a0",
    "iso:country":"CA",
    "sg:city":"Burford",
    "sg:classifiers":[
        {
            "category":"Building & Trades",
            "subcategory":"Plumbing",
            "type":"Services"
        }
    ],
    "sg:phone":"+1 519 449 2810",
    "sg:postcode":"N0E 1A0",
    "sg:province":"ON",
    "sg:tags":[
        "conditioning",
        "air",
        "system",
        "contractor"
    ],
    "wof:name":"Burford Heating & Air Cond Ltd",
    "wof:placetype":"venue"
},
  "geometry": {"coordinates":[-80.42305,43.104103],"type":"Point"}
}