{
  "type": "Feature",
  "properties": {
    "addr:full":"Trois-Rivieres QC G8Y 1W1",
    "addr:postcode":"g8y 1w1",
    "iso:country":"CA",
    "sg:city":"Trois-Rivieres",
    "sg:classifiers":[
        {
            "category":"Shopping",
            "subcategory":"Hobbies, Toys, & Games",
            "type":"Retail Goods"
        }
    ],
    "sg:phone":"+1 819 370 8697",
    "sg:postcode":"G8Y 1W1",
    "sg:province":"QC",
    "wof:name":"Toys R US",
    "wof:placetype":"venue"
},
  "geometry": {"coordinates":[-72.58625000000001,46.356396],"type":"Point"}
}