{
  "type": "Feature",
  "properties": {
    "addr:full":"1775 Nanaimo St Vancouver BC V5N 5C1",
    "addr:housenumber":"1775",
    "addr:postcode":"v5n 5c1",
    "addr:street":"Nanaimo St",
    "iso:country":"CA",
    "sg:address":"1775 Nanaimo St",
    "sg:city":"Vancouver",
    "sg:classifiers":[
        {
            "category":"Health Services",
            "subcategory":"Chiropractor",
            "type":"Services"
        }
    ],
    "sg:phone":"+1 604 253 0004",
    "sg:postcode":"V5N 5C1",
    "sg:province":"BC",
    "wof:name":"Read, Steven J DC",
    "wof:placetype":"venue"
},
  "geometry": {"coordinates":[-123.05672454800001,49.2689094543],"type":"Point"}
}