{
  "type": "Feature",
  "properties": {
    "addr:full":"111 Kaiser William Ave E Langenburg SK S0A 2A0",
    "addr:housenumber":"111",
    "addr:postcode":"s0a 2a0",
    "addr:street":"Kaiser William Ave E",
    "iso:country":"CA",
    "sg:address":"111 Kaiser William Ave E",
    "sg:city":"Langenburg",
    "sg:classifiers":[
        {
            "category":"Sports & Exercise",
            "subcategory":"Bowling",
            "type":"Entertainment"
        }
    ],
    "sg:phone":"+1 306 743 5555",
    "sg:postcode":"S0A 2A0",
    "sg:province":"SK",
    "sg:tags":[
        "center"
    ],
    "wof:name":"Woodland Lanes Inc",
    "wof:placetype":"venue"
},
  "geometry": {"coordinates":[-101.695168,50.840549],"type":"Point"}
}