{
  "type": "Feature",
  "properties": {
    "addr:full":"4737 Gordon Rd Campbell River BC V9H 1T3",
    "addr:housenumber":"4737",
    "addr:postcode":"v9h 1t3",
    "addr:street":"Gordon Rd",
    "iso:country":"CA",
    "sg:address":"4737 Gordon Rd",
    "sg:city":"Campbell River",
    "sg:classifiers":[
        {
            "category":"Home & Garden",
            "subcategory":"Garden Supply",
            "type":"Retail Goods"
        }
    ],
    "sg:phone":"+1 250 286 1340",
    "sg:postcode":"V9H 1T3",
    "sg:province":"BC",
    "sg:tags":[
        "nurseryman"
    ],
    "wof:name":"Mystic Woods Nursery",
    "wof:placetype":"venue"
},
  "geometry": {"coordinates":[-125.317993,50.071323],"type":"Point"}
}