{
  "type": "Feature",
  "properties": {
    "addr:full":"48 White Oak Dr E Sault Ste Marie ON P6B 4J8",
    "addr:housenumber":"48",
    "addr:postcode":"p6b 4j8",
    "addr:street":"White Oak Dr E",
    "iso:country":"CA",
    "sg:address":"48 White Oak Dr E",
    "sg:city":"Sault Ste Marie",
    "sg:classifiers":[
        {
            "category":"Wholesale",
            "subcategory":"Machinery & Supplies",
            "type":"Manufacturing & Wholesale Goods"
        }
    ],
    "sg:phone":"+1 705 949 2550",
    "sg:postcode":"P6B 4J8",
    "sg:province":"ON",
    "sg:tags":[
        "equipment",
        "industrial"
    ],
    "wof:name":"Kinecor Inc",
    "wof:placetype":"venue"
},
  "geometry": {"coordinates":[-84.3336105347,46.5375823975],"type":"Point"}
}