{
  "type": "Feature",
  "properties": {
    "addr:full":"Water St Bay Roberts NL A0A 1G0",
    "addr:postcode":"a0a 1g0",
    "addr:street":"Water St",
    "iso:country":"CA",
    "sg:address":"Water St",
    "sg:city":"Bay Roberts",
    "sg:classifiers":[
        {
            "category":"Organizations",
            "subcategory":"Religious Organization",
            "type":"Services"
        }
    ],
    "sg:phone":"+1 709 786 6337",
    "sg:postcode":"A0A 1G0",
    "sg:province":"NL",
    "sg:tags":[
        "church"
    ],
    "wof:name":"Salvation Army",
    "wof:placetype":"venue"
},
  "geometry": {"coordinates":[-53.234692,47.602684],"type":"Point"}
}