{
  "type": "Feature",
  "properties": {
    "iso:country":"CA",
    "sg:address":"750 Clark Blvd",
    "sg:city":"Brampton",
    "sg:classifiers":[
        {
            "category":"Organizations",
            "subcategory":"Religious Organization",
            "type":"Services"
        }
    ],
    "sg:phone":"+1 905 792 2297",
    "sg:postcode":"L6T 3Y2",
    "sg:province":"ON",
    "sg:tags":[
        "church"
    ],
    "wof:name":"Church of Christ",
    "wof:placetype":"venue"
},
  "geometry": {"coordinates":[-79.708206,43.7258],"type":"Point"}
}