{
  "type": "Feature",
  "properties": {
    "addr:full":"Toronto ON M4T 1L9",
    "addr:postcode":"m4t 1l9",
    "iso:country":"CA",
    "sg:city":"Toronto",
    "sg:classifiers":[
        {
            "category":"Insurance",
            "subcategory":"Insurance Agent",
            "type":"Services"
        }
    ],
    "sg:phone":"+1 416 922 7570",
    "sg:postcode":"M4T 1L9",
    "sg:province":"ON",
    "wof:name":"John Lueger Insurance Inc",
    "wof:placetype":"venue"
},
  "geometry": {"coordinates":[-79.392776,43.688225],"type":"Point"}
}