{
  "type": "Feature",
  "properties": {
    "addr:full":"Calgary AB T2Y 2Z3",
    "addr:postcode":"t2y 2z3",
    "iso:country":"CA",
    "sg:city":"Calgary",
    "sg:classifiers":[
        {
            "category":"Health Services",
            "subcategory":"Chiropractor",
            "type":"Services"
        }
    ],
    "sg:phone":"+1 403 256 1377",
    "sg:postcode":"T2Y 2Z3",
    "sg:province":"AB",
    "wof:name":"Shawnessy Village Chiropractic",
    "wof:placetype":"venue"
},
  "geometry": {"coordinates":[-114.066666,50.906666],"type":"Point"}
}