{
  "type": "Feature",
  "properties": {
    "iso:country":"CA",
    "sg:address":"244 Mcmahon Ave",
    "sg:city":"Kingston",
    "sg:classifiers":[
        {
            "category":"Organizations",
            "subcategory":"Religious Organization",
            "type":"Services"
        }
    ],
    "sg:phone":"+1 613 542 5579",
    "sg:postcode":"K7M 3H2",
    "sg:province":"ON",
    "sg:tags":[
        "church"
    ],
    "wof:name":"Strathcona Park Presbyterian",
    "wof:placetype":"venue"
},
  "geometry": {"coordinates":[-76.523186,44.249798],"type":"Point"}
}