{
  "type": "Feature",
  "properties": {
    "addr:full":"Highway 1 Moosomin SK S0G 3N0",
    "addr:postcode":"s0g 3n0",
    "addr:street":"Highway 1",
    "iso:country":"CA",
    "sg:address":"Highway 1",
    "sg:city":"Moosomin",
    "sg:classifiers":[
        {
            "category":"Restaurant",
            "type":"Food & Drink"
        }
    ],
    "sg:phone":"+1 306 435 3371",
    "sg:postcode":"S0G 3N0",
    "sg:province":"SK",
    "wof:name":"Pizza Hut",
    "wof:placetype":"venue"
},
  "geometry": {"coordinates":[-101.663291931,50.1470336914],"type":"Point"}
}