{
  "type": "Feature",
  "properties": {
    "iso:country":"CA",
    "sg:city":"Galiano",
    "sg:classifiers":[
        {
            "category":"Shopping",
            "subcategory":"Bicycles & Sporting Goods",
            "type":"Retail Goods"
        }
    ],
    "sg:phone":"+1 250 539 2930",
    "sg:postcode":"V0N 1P0",
    "sg:province":"BC",
    "sg:tags":[
        "equipment",
        "camping"
    ],
    "wof:name":"Hennessy Hammock.com",
    "wof:placetype":"venue"
},
  "geometry": {"coordinates":[-123.34271200000001,48.889454],"type":"Point"}
}