{
  "type": "Feature",
  "properties": {
    "addr:full":"80 Main Lumsden NL A0G 3E0",
    "addr:housenumber":"80",
    "addr:postcode":"a0g 3e0",
    "addr:street":"Main",
    "iso:country":"CA",
    "sg:address":"80 Main",
    "sg:city":"Lumsden",
    "sg:classifiers":[
        {
            "category":"Organizations",
            "subcategory":"Religious Organization",
            "type":"Services"
        }
    ],
    "sg:phone":"+1 709 530 2506",
    "sg:postcode":"A0G 3E0",
    "sg:province":"NL",
    "sg:tags":[
        "church"
    ],
    "wof:name":"Kingdom Hall Jehovah's Witness",
    "wof:placetype":"venue"
},
  "geometry": {"coordinates":[-53.603638,49.296249],"type":"Point"}
}