{
  "type": "Feature",
  "properties": {
    "addr:full":"2345 Alta Vista Dr Ottawa ON K1H 7M6",
    "addr:housenumber":"2345",
    "addr:postcode":"k1h 7m6",
    "addr:street":"Alta Vista Dr",
    "iso:country":"CA",
    "sg:address":"2345 Alta Vista Dr",
    "sg:city":"Ottawa",
    "sg:classifiers":[
        {
            "category":"Social Services",
            "subcategory":"Child Care",
            "type":"Services"
        }
    ],
    "sg:phone":"+1 613 266 3344",
    "sg:postcode":"K1H 7M6",
    "sg:province":"ON",
    "wof:name":"Vista School Age Program",
    "wof:placetype":"venue"
},
  "geometry": {"coordinates":[-75.6620941162,45.3837471008],"type":"Point"}
}