{
  "type": "Feature",
  "properties": {
    "addr:full":"1111 7th Ave Prince George BC V2L 3N8",
    "addr:housenumber":"1111",
    "addr:postcode":"v2l 3n8",
    "addr:street":"7Th Ave",
    "iso:country":"CA",
    "sg:address":"1111 7th Ave",
    "sg:city":"Prince George",
    "sg:classifiers":[
        {
            "category":"Government",
            "subcategory":"Fire Station",
            "type":"Public Place"
        }
    ],
    "sg:phone":"+1 ",
    "sg:postcode":"V2L 3N8",
    "sg:province":"BC",
    "sg:tags":[
        "department"
    ],
    "wof:name":"Prince George Fire Inspection",
    "wof:placetype":"venue"
},
  "geometry": {"coordinates":[-122.74497985799999,53.9133682251],"type":"Point"}
}