{
  "type": "Feature",
  "properties": {
    "addr:full":"Calgary AB T2P 0M2",
    "addr:postcode":"t2p 0m2",
    "iso:country":"CA",
    "sg:city":"Calgary",
    "sg:classifiers":[
        {
            "category":"Freight",
            "type":"Transportation"
        }
    ],
    "sg:phone":"+1 403 262 2191",
    "sg:postcode":"T2P 0M2",
    "sg:province":"AB",
    "sg:tags":[
        "car",
        "railroad",
        "leasing"
    ],
    "wof:name":"Gatx Rail Canada",
    "wof:placetype":"venue"
},
  "geometry": {"coordinates":[-114.072364807,51.0487632751],"type":"Point"}
}