{
  "type": "Feature",
  "properties": {
    "addr:full":"Saskatoon SK S7K 6Y6",
    "addr:postcode":"s7k 6y6",
    "iso:country":"CA",
    "sg:city":"Saskatoon",
    "sg:classifiers":[
        {
            "category":"Restaurant",
            "type":"Food & Drink"
        }
    ],
    "sg:phone":"+1 306 668 3070",
    "sg:postcode":"S7K 6Y6",
    "sg:province":"SK",
    "sg:tags":[
        "out"
    ],
    "wof:name":"Pizza Hut",
    "wof:placetype":"venue"
},
  "geometry": {"coordinates":[-106.63713799999999,52.167545],"type":"Point"}
}