{
  "type": "Feature",
  "properties": {
    "addr:full":"Calgary AB T2E 6V6",
    "addr:postcode":"t2e 6v6",
    "iso:country":"CA",
    "sg:city":"Calgary",
    "sg:classifiers":[
        {
            "category":"Wholesale",
            "subcategory":"Machinery & Supplies",
            "type":"Manufacturing & Wholesale Goods"
        }
    ],
    "sg:phone":"+1 403 250 3600",
    "sg:postcode":"T2E 6V6",
    "sg:province":"AB",
    "sg:tags":[
        "car"
    ],
    "wof:name":"Lynco Products Inc",
    "wof:placetype":"venue"
},
  "geometry": {"coordinates":[-114.008422852,51.0843811035],"type":"Point"}
}