{
  "type": "Feature",
  "properties": {
    "addr:full":"179 Boul Perron E New Richmond QC G0C 2B0",
    "addr:housenumber":"179",
    "addr:postcode":"g0c 2b0",
    "addr:street":"Boul Perron E",
    "iso:country":"CA",
    "sg:address":"179 Boul Perron E",
    "sg:city":"New Richmond",
    "sg:classifiers":[
        {
            "category":"Personal",
            "subcategory":"Beauty Salon",
            "type":"Services"
        }
    ],
    "sg:phone":"+1 418 392 4777",
    "sg:postcode":"G0C 2B0",
    "sg:province":"QC",
    "wof:name":"Salon Coiffure E Poirier",
    "wof:placetype":"venue"
},
  "geometry": {"coordinates":[-65.845657,48.153427],"type":"Point"}
}