{
  "type": "Feature",
  "properties": {
    "addr:full":"949 St Clair Ave W Toronto ON M6C 1C7",
    "addr:housenumber":"949",
    "addr:postcode":"m6c 1c7",
    "addr:street":"St Clair Ave W",
    "iso:country":"CA",
    "sg:address":"949 St Clair Ave W",
    "sg:city":"Toronto",
    "sg:classifiers":[
        {
            "category":"Banks & Credit Unions",
            "subcategory":"Bank",
            "type":"Services"
        }
    ],
    "sg:phone":"+1 416 654 4343",
    "sg:postcode":"M6C 1C7",
    "sg:province":"ON",
    "wof:name":"Scotiabank",
    "wof:placetype":"venue"
},
  "geometry": {"coordinates":[-79.43584442140001,43.6795310974],"type":"Point"}
}