{
  "type": "Feature",
  "properties": {
    "addr:full":"208 2E Av Lac-Etchemin QC G0R 1S0",
    "addr:housenumber":"208",
    "addr:postcode":"g0r 1s0",
    "addr:street":"2E Av Lac-Etchemin",
    "iso:country":"CA",
    "sg:address":"208 2E Av",
    "sg:city":"Lac-Etchemin",
    "sg:classifiers":[
        {
            "category":"Government",
            "subcategory":"Office",
            "type":"Public Place"
        }
    ],
    "sg:phone":"+1 418 625 4521",
    "sg:postcode":"G0R 1S0",
    "sg:province":"QC",
    "sg:tags":[
        "village"
    ],
    "wof:name":"Lac Etchemin Ville",
    "wof:placetype":"venue"
},
  "geometry": {"coordinates":[-70.5044708252,46.3963317871],"type":"Point"}
}