{
  "type": "Feature",
  "properties": {
    "addr:full":"5815 Datsun Rd Mississauga ON L4W 1V8",
    "addr:housenumber":"5815",
    "addr:postcode":"l4w 1v8",
    "addr:street":"Datsun Rd",
    "iso:country":"CA",
    "sg:address":"5815 Datsun Rd",
    "sg:city":"Mississauga",
    "sg:classifiers":[
        {
            "category":"Retail",
            "subcategory":"Auto Repair",
            "type":"Services"
        }
    ],
    "sg:phone":"+1 905 795 1588",
    "sg:postcode":"L4W 1V8",
    "sg:province":"ON",
    "sg:tags":[
        "truck"
    ],
    "wof:name":"Majik Collision",
    "wof:placetype":"venue"
},
  "geometry": {"coordinates":[-79.6448669434,43.6491699219],"type":"Point"}
}