{
  "type": "Feature",
  "properties": {
    "iso:country":"CA",
    "sg:city":"Westmount",
    "sg:classifiers":[
        {
            "category":"Insurance",
            "subcategory":"Insurance Agent",
            "type":"Services"
        }
    ],
    "sg:phone":"+1 514 937 9303",
    "sg:postcode":"H3Z 2A4",
    "sg:province":"QC",
    "wof:name":"Murray Yaffe Insurance Svc Ltd",
    "wof:placetype":"venue"
},
  "geometry": {"coordinates":[-73.588631,45.48666],"type":"Point"}
}