{
  "type": "Feature",
  "properties": {
    "addr:full":"New Liskeard ON P0J 1P0",
    "addr:postcode":"p0j 1p0",
    "iso:country":"CA",
    "sg:city":"New Liskeard",
    "sg:classifiers":[
        {
            "category":"Travel",
            "subcategory":"Hotels & Motels",
            "type":"Entertainment"
        }
    ],
    "sg:phone":"+1 705 647 5470",
    "sg:postcode":"P0J 1P0",
    "sg:province":"ON",
    "sg:tags":[
        "cottage",
        "resort",
        "cabin"
    ],
    "wof:name":"Sunnydale Cottages",
    "wof:placetype":"venue"
},
  "geometry": {"coordinates":[-79.663673,47.512699],"type":"Point"}
}