{
  "type": "Feature",
  "properties": {
    "addr:full":"2370 United Blvd Coquitlam BC V3K 6A3",
    "addr:housenumber":"2370",
    "addr:postcode":"v3k 6a3",
    "addr:street":"United Blvd",
    "iso:country":"CA",
    "sg:address":"2370 United Blvd",
    "sg:city":"Coquitlam",
    "sg:classifiers":[
        {
            "category":"Government",
            "subcategory":"Office",
            "type":"Public Place"
        }
    ],
    "sg:phone":"+1 604 660 0500",
    "sg:postcode":"V3K 6A3",
    "sg:province":"BC",
    "wof:name":"BC Purchasing",
    "wof:placetype":"venue"
},
  "geometry": {"coordinates":[-122.825615,49.226551],"type":"Point"}
}