{
  "type": "Feature",
  "properties": {
    "addr:full":"Calgary AB T2C 4E4",
    "addr:postcode":"t2c 4e4",
    "iso:country":"CA",
    "sg:city":"Calgary",
    "sg:classifiers":[
        {
            "category":"Shopping",
            "subcategory":"Pharmacy",
            "type":"Retail Goods"
        }
    ],
    "sg:phone":"+1 403 236 1999",
    "sg:postcode":"T2C 4E4",
    "sg:province":"AB",
    "wof:name":"Super Drug Mart",
    "wof:placetype":"venue"
},
  "geometry": {"coordinates":[-114.0154953,50.9770545959],"type":"Point"}
}