{
  "type": "Feature",
  "properties": {
    "addr:full":"36076 97th St Oliver BC V0H 1T0",
    "addr:housenumber":"36076",
    "addr:postcode":"bc v0h 1t0",
    "addr:street":"97Th St",
    "iso:country":"CA",
    "sg:address":"36076 97th St",
    "sg:city":"Oliver",
    "sg:classifiers":[
        {
            "category":"Personal",
            "subcategory":"Beauty Salon",
            "type":"Services"
        }
    ],
    "sg:phone":"+1 250 498 4002",
    "sg:postcode":"V0H 1T0",
    "sg:province":"BC",
    "wof:name":"Uptown Beauty Studio",
    "wof:placetype":"venue"
},
  "geometry": {"coordinates":[-119.550621033,49.1847000122],"type":"Point"}
}