{
  "type": "Feature",
  "properties": {
    "addr:full":"604 Av Du Phare E Matane QC G4W 1B1",
    "addr:postcode":"g4w 1b1",
    "addr:street":"604 Av Du Phare E",
    "iso:country":"CA",
    "sg:address":"604 Av Du Phare E",
    "sg:city":"Matane",
    "sg:classifiers":[
        {
            "category":"Restaurant",
            "type":"Food & Drink"
        }
    ],
    "sg:phone":"+1 418 562 0610",
    "sg:postcode":"G4W 1B1",
    "sg:province":"QC",
    "wof:name":"Restaurant Du Chef Matane Inc",
    "wof:placetype":"venue"
},
  "geometry": {"coordinates":[-67.5081939697,48.8525276184],"type":"Point"}
}