{
  "type": "Feature",
  "properties": {
    "addr:full":"674 Otonabee Dr Peterborough ON K9J 7P9",
    "addr:housenumber":"674",
    "addr:postcode":"k9j 7p9",
    "addr:street":"Otonabee Dr",
    "iso:country":"CA",
    "sg:address":"674 Otonabee Dr",
    "sg:city":"Peterborough",
    "sg:classifiers":[
        {
            "category":"Building & Trades",
            "subcategory":"Construction",
            "type":"Services"
        }
    ],
    "sg:phone":"+1 705 742 8788",
    "sg:postcode":"K9J 7P9",
    "sg:province":"ON",
    "sg:tags":[
        "masonry",
        "contractor"
    ],
    "wof:name":"Sweeting Masonry Ltd",
    "wof:placetype":"venue"
},
  "geometry": {"coordinates":[-78.299057,44.287628],"type":"Point"}
}