{
  "type": "Feature",
  "properties": {
    "addr:full":"2675 Shaughnessy St Port Coquitlam BC V3C 3G7",
    "addr:housenumber":"2675",
    "addr:postcode":"v3c 3g7",
    "addr:street":"Shaughnessy St",
    "iso:country":"CA",
    "sg:address":"2675 Shaughnessy St",
    "sg:city":"Port Coquitlam",
    "sg:classifiers":[
        {
            "category":"Organizations",
            "subcategory":"Community Association",
            "type":"Services"
        }
    ],
    "sg:phone":"+1 604 942 8911",
    "sg:postcode":"V3C 3G7",
    "sg:province":"BC",
    "sg:tags":[
        "fraternal"
    ],
    "wof:name":"Royal Canadian Legion",
    "wof:placetype":"venue"
},
  "geometry": {"coordinates":[-122.779968,49.264194],"type":"Point"}
}