{
  "type": "Feature",
  "properties": {
    "addr:full":"15514 Stony Plain Rd NW Edmonton AB T5P 3Z2",
    "addr:housenumber":"15514",
    "addr:postcode":"t5p 3z2",
    "addr:street":"Stony Plain Rd Nw",
    "iso:country":"CA",
    "sg:address":"15514 Stony Plain Rd NW",
    "sg:city":"Edmonton",
    "sg:classifiers":[
        {
            "category":"Personal",
            "subcategory":"Barber",
            "type":"Services"
        }
    ],
    "sg:phone":"+1 780 489 0840",
    "sg:postcode":"T5P 3Z2",
    "sg:province":"AB",
    "wof:name":"Saxony Hairstyling",
    "wof:placetype":"venue"
},
  "geometry": {"coordinates":[-113.58891300000001,53.541515],"type":"Point"}
}