{
  "type": "Feature",
  "properties": {
    "addr:full":"450 Appleby Line Burlington ON L7L 2Y2",
    "addr:housenumber":"450",
    "addr:postcode":"l7l 2y2",
    "addr:street":"Appleby Line",
    "iso:country":"CA",
    "sg:address":"450 Appleby Line",
    "sg:city":"Burlington",
    "sg:classifiers":[
        {
            "category":"Personal",
            "subcategory":"Beauty Salon",
            "type":"Services"
        }
    ],
    "sg:phone":"+1 905 637 0648",
    "sg:postcode":"L7L 2Y2",
    "sg:province":"ON",
    "wof:name":"First Choice Haircutters",
    "wof:placetype":"venue"
},
  "geometry": {"coordinates":[-79.7529296875,43.3664703369],"type":"Point"}
}