{
  "type": "Feature",
  "properties": {
    "addr:full":"16718 121 Ave NW Edmonton AB T5V 1P6",
    "addr:housenumber":"16718",
    "addr:postcode":"t5v 1p6",
    "addr:street":"121 Ave Nw",
    "iso:country":"CA",
    "sg:address":"16718 121 Ave NW",
    "sg:city":"Edmonton",
    "sg:classifiers":[
        {
            "category":"Freight",
            "type":"Transportation"
        }
    ],
    "sg:phone":"+1 780 413 9993",
    "sg:postcode":"T5V 1P6",
    "sg:province":"AB",
    "sg:tags":[
        "trucking"
    ],
    "wof:name":"Deckyx Transport",
    "wof:placetype":"venue"
},
  "geometry": {"coordinates":[-113.609467,53.572922],"type":"Point"}
}