{
  "type": "Feature",
  "properties": {
    "addr:full":"16581 County Rd 36 Long Sault ON K0C 1P0",
    "addr:housenumber":"16581;36",
    "addr:postcode":"k0c 1p0",
    "addr:street":"County Rd;Sault",
    "iso:country":"CA",
    "sg:address":"16581 County Rd 36",
    "sg:city":"Long Sault",
    "sg:classifiers":[
        {
            "category":"Building & Trades",
            "subcategory":"Landscaping Services",
            "type":"Services"
        }
    ],
    "sg:phone":"+1 613 534 2934",
    "sg:postcode":"K0C 1P0",
    "sg:province":"ON",
    "sg:tags":[
        "equipment",
        "supply",
        "landscape",
        "contractor"
    ],
    "wof:name":"Lasting Impressions",
    "wof:placetype":"venue"
},
  "geometry": {"coordinates":[-74.89831542970001,45.0299835205],"type":"Point"}
}