{
  "type": "Feature",
  "properties": {
    "addr:full":"11960 Av L'Archeveque Montreal-Nord QC H1H 3B9",
    "addr:housenumber":"11960",
    "addr:postcode":"h1h 3b9",
    "addr:street":"Av L'Archeveque",
    "iso:country":"CA",
    "sg:address":"11960 Av L'Archeveque",
    "sg:city":"Montreal-Nord",
    "sg:classifiers":[
        {
            "category":"Building & Trades",
            "subcategory":"Plumbing",
            "type":"Services"
        }
    ],
    "sg:phone":"+1 514 328 9608",
    "sg:postcode":"H1H 3B9",
    "sg:province":"QC",
    "sg:tags":[
        "propane",
        "gas",
        "contractor"
    ],
    "wof:name":"Pro-Carbur Inc",
    "wof:placetype":"venue"
},
  "geometry": {"coordinates":[-73.63851200000001,45.605042],"type":"Point"}
}