{
  "type": "Feature",
  "properties": {
    "addr:full":"5380 Drenkelly Crt Mississauga ON L5M 2H4",
    "addr:housenumber":"5380",
    "addr:postcode":"l5m 2h4",
    "addr:street":"Drenkelly Crt",
    "iso:country":"CA",
    "sg:address":"5380 Drenkelly Crt",
    "sg:city":"Mississauga",
    "sg:classifiers":[
        {
            "category":"Professional",
            "subcategory":"Management & Consulting",
            "type":"Services"
        }
    ],
    "sg:phone":"+1 905 826 5477",
    "sg:postcode":"L5M 2H4",
    "sg:province":"ON",
    "sg:tags":[
        "consultant",
        "business"
    ],
    "wof:name":"Synchronicity Business Coach",
    "wof:placetype":"venue"
},
  "geometry": {"coordinates":[-79.7029037476,43.5790328979],"type":"Point"}
}