{
  "type": "Feature",
  "properties": {
    "addr:full":"3750 Rue Pascal-Gagnon Terrebonne QC J6X 4J2",
    "addr:housenumber":"3750",
    "addr:postcode":"j6x 4j2",
    "addr:street":"Rue Pascal-Gagnon",
    "iso:country":"CA",
    "sg:address":"3750 Rue Pascal-Gagnon",
    "sg:city":"Terrebonne",
    "sg:classifiers":[
        {
            "category":"Autos & Motor Vehicles",
            "subcategory":"Automobile Sales",
            "type":"Retail Goods"
        }
    ],
    "sg:phone":"+1 450 477 1465",
    "sg:postcode":"J6X 4J2",
    "sg:province":"QC",
    "sg:tags":[
        "car",
        "dealer"
    ],
    "wof:name":"Prestige Collision Inc",
    "wof:placetype":"venue"
},
  "geometry": {"coordinates":[-73.67681899999999,45.728306],"type":"Point"}
}