{
  "type": "Feature",
  "properties": {
    "addr:full":"1300 Oxford St E London ON N5V 4P7",
    "addr:housenumber":"1300",
    "addr:postcode":"n5v 4p7",
    "addr:street":"Oxford St E",
    "iso:country":"CA",
    "sg:address":"1300 Oxford St E",
    "sg:city":"London",
    "sg:classifiers":[
        {
            "category":"Education",
            "subcategory":"School",
            "type":"Public Place"
        }
    ],
    "sg:phone":"+1 519 457 3440",
    "sg:postcode":"N5V 4P7",
    "sg:province":"ON",
    "wof:name":"John Paul II Secondary School",
    "wof:placetype":"venue"
},
  "geometry": {"coordinates":[-81.20850372309999,43.0086593628],"type":"Point"}
}