{
  "type": "Feature",
  "properties": {
    "iso:country":"CA",
    "sg:city":"Richmond",
    "sg:classifiers":[
        {
            "category":"Recreation",
            "subcategory":"Marina",
            "type":"Entertainment"
        }
    ],
    "sg:phone":"+1 604 275 2706",
    "sg:postcode":"V7E 2G3",
    "sg:province":"BC",
    "sg:tags":[
        "repairing",
        "repair",
        "marine",
        "automobile"
    ],
    "wof:name":"Abir Auto Marine Electric Ltd",
    "wof:placetype":"venue"
},
  "geometry": {"coordinates":[-123.15901947,49.1228141785],"type":"Point"}
}