{
  "type": "Feature",
  "properties": {
    "iso:country":"CA",
    "sg:city":"Hamilton",
    "sg:classifiers":[
        {
            "category":"Restaurant",
            "type":"Food & Drink"
        }
    ],
    "sg:phone":"+1 905 575 9118",
    "sg:postcode":"L8V 5B7",
    "sg:province":"ON",
    "sg:tags":[
        "sandwich"
    ],
    "wof:name":"Mike's Submarines",
    "wof:placetype":"venue"
},
  "geometry": {"coordinates":[-79.8460235596,43.2119903564],"type":"Point"}
}