{
  "type": "Feature",
  "properties": {
    "iso:country":"CA",
    "sg:address":"30 Barrhead Cres",
    "sg:city":"Etobicoke",
    "sg:classifiers":[
        {
            "category":"Education",
            "subcategory":"School",
            "type":"Public Place"
        }
    ],
    "sg:phone":"+1 416 745 1328",
    "sg:postcode":"M9W 3Z7",
    "sg:province":"ON",
    "wof:name":"Mississauga Private School",
    "wof:placetype":"venue"
},
  "geometry": {"coordinates":[-79.5666046143,43.7192077637],"type":"Point"}
}