{
  "type": "Feature",
  "properties": {
    "addr:full":"Beiseker AB T0M 0G0",
    "addr:postcode":"t0m 0g0",
    "iso:country":"CA",
    "sg:city":"Beiseker",
    "sg:classifiers":[
        {
            "category":"Food & Beverages",
            "subcategory":"Liquor & Beverages",
            "type":"Retail Goods"
        }
    ],
    "sg:phone":"+1 403 947 2092",
    "sg:postcode":"T0M 0G0",
    "sg:province":"AB",
    "sg:tags":[
        "store"
    ],
    "wof:name":"Manyee Liquor Store",
    "wof:placetype":"venue"
},
  "geometry": {"coordinates":[-113.536575317,51.386631012],"type":"Point"}
}