{
  "type": "Feature",
  "properties": {
    "addr:full":"607 13 Ave Nisku AB T9E 7P4",
    "addr:postcode":"t9e 7p4",
    "addr:street":"607 13 Ave",
    "iso:country":"CA",
    "sg:address":"607 13 Ave",
    "sg:city":"Nisku",
    "sg:classifiers":[
        {
            "category":"Manufacturing",
            "subcategory":"Tools & Machinery",
            "type":"Manufacturing & Wholesale Goods"
        }
    ],
    "sg:phone":"+1 780 955 7598",
    "sg:postcode":"T9E 7P4",
    "sg:province":"AB",
    "sg:tags":[
        "machine",
        "shop"
    ],
    "wof:name":"Clem Industrial Machine Ltd",
    "wof:placetype":"venue"
},
  "geometry": {"coordinates":[-113.526939,53.314503],"type":"Point"}
}