{
  "type": "Feature",
  "properties": {
    "addr:full":"2879 Highway 44 Carp ON K0A 1L0",
    "addr:housenumber":"2879",
    "addr:postcode":"k0a 1l0",
    "addr:street":"Highway 44",
    "iso:country":"CA",
    "sg:address":"2879 Highway 44",
    "sg:city":"Carp",
    "sg:phone":"+1 613 839 3200",
    "sg:postcode":"K0A 1L0",
    "sg:province":"ON",
    "sg:tags":[
        "oil"
    ],
    "wof:name":"Ultramar",
    "wof:placetype":"venue"
},
  "geometry": {"coordinates":[-76.0425872803,45.3500442505],"type":"Point"}
}