{
  "type": "Feature",
  "properties": {
    "addr:full":"1 Kintail Crt Stittsville ON K2S 1G8",
    "addr:housenumber":"1",
    "addr:postcode":"k2s 1g8",
    "addr:street":"Kintail Crt",
    "iso:country":"CA",
    "sg:address":"1 Kintail Crt",
    "sg:city":"Stittsville",
    "sg:classifiers":[
        {
            "category":"Wholesale",
            "subcategory":"Furniture",
            "type":"Manufacturing & Wholesale Goods"
        }
    ],
    "sg:phone":"+1 613 836 6210",
    "sg:postcode":"K2S 1G8",
    "sg:province":"ON",
    "wof:name":"Patrick R Mc Gee Sales Inc",
    "wof:placetype":"venue"
},
  "geometry": {"coordinates":[-75.93222,45.266563],"type":"Point"}
}