{
  "type": "Feature",
  "properties": {
    "addr:full":"812 Rte 289 Saint-Alexandre-DE-Kamouraska QC G0L 2G0",
    "addr:housenumber":"812",
    "addr:postcode":"g0l 2g0",
    "addr:street":"Rte 289",
    "iso:country":"CA",
    "sg:address":"812 Rte 289",
    "sg:city":"Saint-Alexandre-DE-Kamouraska",
    "sg:classifiers":[
        {
            "category":"Restaurant",
            "type":"Food & Drink"
        }
    ],
    "sg:phone":"+1 418 495 2842",
    "sg:postcode":"G0L 2G0",
    "sg:province":"QC",
    "sg:tags":[
        "delicatessen",
        "butchering"
    ],
    "wof:name":"Charcuterie Boucher Inc",
    "wof:placetype":"venue"
},
  "geometry": {"coordinates":[-69.86264801030001,47.5639762878],"type":"Point"}
}