{
  "type": "Feature",
  "properties": {
    "addr:full":"Magnetawan ON P0A 1P0",
    "addr:postcode":"p0a 1p0",
    "iso:country":"CA",
    "sg:city":"Magnetawan",
    "sg:classifiers":[
        {
            "category":"Restaurant",
            "type":"Food & Drink"
        }
    ],
    "sg:phone":"+1 705 387 3933",
    "sg:postcode":"P0A 1P0",
    "sg:province":"ON",
    "wof:name":"Schmeler House Hotel",
    "wof:placetype":"venue"
},
  "geometry": {"coordinates":[-79.6435394287,45.6662940979],"type":"Point"}
}