{
  "type": "Feature",
  "properties": {
    "addr:full":"465 Broadway W Vancouver BC V5Y 1R4",
    "addr:housenumber":"465",
    "addr:postcode":"v5y 1r4",
    "addr:street":"Broadway W",
    "iso:country":"CA",
    "sg:address":"465 Broadway W",
    "sg:city":"Vancouver",
    "sg:classifiers":[
        {
            "category":"Government",
            "subcategory":"Fire Station",
            "type":"Public Place"
        }
    ],
    "sg:phone":"+1 604 873 7595",
    "sg:postcode":"V5Y 1R4",
    "sg:province":"BC",
    "sg:tags":[
        "department"
    ],
    "wof:name":"Vancouver Fire Prevention",
    "wof:placetype":"venue"
},
  "geometry": {"coordinates":[-123.114143372,49.2633628845],"type":"Point"}
}