{
  "type": "Feature",
  "properties": {
    "addr:full":"111 Echo Dr Ottawa ON K1S 5K8",
    "addr:housenumber":"111",
    "addr:postcode":"k1s 5k8",
    "addr:street":"Echo Dr",
    "iso:country":"CA",
    "sg:address":"111 Echo Dr",
    "sg:city":"Ottawa",
    "sg:classifiers":[
        {
            "category":"Real Estate",
            "subcategory":"Developer",
            "type":"Services"
        }
    ],
    "sg:phone":"+1 613 230 1754",
    "sg:postcode":"K1S 5K8",
    "sg:province":"ON",
    "wof:name":"Canal One Eleven",
    "wof:placetype":"venue"
},
  "geometry": {"coordinates":[-75.68115997309999,45.4152641296],"type":"Point"}
}