{
  "type": "Feature",
  "properties": {
    "addr:full":"50 34E Av Lachine QC H8T 1Z2",
    "addr:housenumber":"50",
    "addr:postcode":"h8t 1z2",
    "addr:street":"34E Av",
    "iso:country":"CA",
    "sg:address":"50 34E Av",
    "sg:city":"Lachine",
    "sg:classifiers":[
        {
            "category":"Education",
            "subcategory":"School",
            "type":"Public Place"
        }
    ],
    "sg:phone":"+1 514 634 4448",
    "sg:postcode":"H8T 1Z2",
    "sg:province":"QC",
    "wof:name":"College St-Louis Ecole",
    "wof:placetype":"venue"
},
  "geometry": {"coordinates":[-73.6937179565,45.4336204529],"type":"Point"}
}