{
  "type": "Feature",
  "properties": {
    "addr:full":"1892 Mattawa Ave Mississauga ON L4X 1K1",
    "addr:housenumber":"1892",
    "addr:postcode":"l4x 1k1",
    "addr:street":"Mattawa Ave",
    "iso:country":"CA",
    "sg:address":"1892 Mattawa Ave",
    "sg:city":"Mississauga",
    "sg:classifiers":[
        {
            "category":"Home & Garden",
            "subcategory":"Furniture",
            "type":"Retail Goods"
        }
    ],
    "sg:phone":"+1 905 897 9889",
    "sg:postcode":"L4X 1K1",
    "sg:province":"ON",
    "sg:tags":[
        "builder",
        "custom"
    ],
    "wof:name":"Ironwood",
    "wof:placetype":"venue"
},
  "geometry": {"coordinates":[-79.5683746338,43.6177444458],"type":"Point"}
}