{
  "type": "Feature",
  "properties": {
    "addr:full":"434 Hotel DE Ville Taillon QC G0W 2X0",
    "addr:housenumber":"434",
    "addr:postcode":"g0w 2x0",
    "addr:street":"Hotel De Ville Taillon",
    "iso:country":"CA",
    "sg:address":"434 Hotel DE Ville",
    "sg:city":"Taillon",
    "sg:classifiers":[
        {
            "category":"Restaurant",
            "type":"Food & Drink"
        }
    ],
    "sg:phone":"+1 418 347 4698",
    "sg:postcode":"G0W 2X0",
    "sg:province":"QC",
    "wof:name":"Casse-Croute Chez Ju-Ly",
    "wof:placetype":"venue"
},
  "geometry": {"coordinates":[-71.821236,48.670753],"type":"Point"}
}