{
  "type": "Feature",
  "properties": {
    "iso:country":"CA",
    "sg:city":"Aurora",
    "sg:classifiers":[
        {
            "category":"Education",
            "subcategory":"School",
            "type":"Public Place"
        }
    ],
    "sg:phone":"+1 905 713 3733",
    "sg:postcode":"L4G 1W9",
    "sg:province":"ON",
    "wof:name":"Ontario New Drivers Training",
    "wof:placetype":"venue"
},
  "geometry": {"coordinates":[-79.4604263306,44.0001220703],"type":"Point"}
}