{
  "type": "Feature",
  "properties": {
    "addr:full":"96 Rue Boucher Fassett QC J0V 1H0",
    "addr:housenumber":"96",
    "addr:postcode":"j0v 1h0",
    "addr:street":"Rue Boucher",
    "iso:country":"CA",
    "sg:address":"96 Rue Boucher",
    "sg:city":"Fassett",
    "sg:classifiers":[
        {
            "category":"Personal",
            "subcategory":"Beauty Salon",
            "type":"Services"
        }
    ],
    "sg:phone":"+1 819 423 5696",
    "sg:postcode":"J0V 1H0",
    "sg:province":"QC",
    "wof:name":"Salon Coiffure Nouvelle Vague",
    "wof:placetype":"venue"
},
  "geometry": {"coordinates":[-74.8658447266,45.6466522217],"type":"Point"}
}