{
  "type": "Feature",
  "properties": {
    "iso:country":"CA",
    "sg:address":"187 Maxwell Ave",
    "sg:city":"Peterborough",
    "sg:classifiers":[
        {
            "category":"Building & Trades",
            "subcategory":"Construction",
            "type":"Services"
        }
    ],
    "sg:phone":"+1 705 749 1082",
    "sg:postcode":"K9J 1B3",
    "sg:province":"ON",
    "sg:tags":[
        "home",
        "improvement"
    ],
    "wof:name":"Roots & Wings Home Improvement",
    "wof:placetype":"venue"
},
  "geometry": {"coordinates":[-78.3114700317,44.2803993225],"type":"Point"}
}