{
  "type": "Feature",
  "properties": {
    "addr:full":"20 Emmeline Cres Scarborough ON M1S 1L2",
    "addr:housenumber":"20",
    "addr:postcode":"m1s 1l2",
    "addr:street":"Emmeline Cres",
    "iso:country":"CA",
    "sg:address":"20 Emmeline Cres",
    "sg:city":"Scarborough",
    "sg:classifiers":[
        {
            "category":"Retail",
            "subcategory":"Laundry & Dry Cleaning",
            "type":"Services"
        }
    ],
    "sg:phone":"+1 416 754 7120",
    "sg:postcode":"M1S 1L2",
    "sg:province":"ON",
    "sg:tags":[
        "repairing",
        "rug",
        "carpet"
    ],
    "wof:name":"Magic Carpet Repairs",
    "wof:placetype":"venue"
},
  "geometry": {"coordinates":[-79.285881,43.794567],"type":"Point"}
}