{
  "type": "Feature",
  "properties": {
    "iso:country":"CA",
    "sg:address":"1423 89 Ave SW",
    "sg:city":"Calgary",
    "sg:classifiers":[
        {
            "category":"Home & Garden",
            "subcategory":"Carpets & Floor Coverings",
            "type":"Retail Goods"
        }
    ],
    "sg:phone":"+1 403 252 1960",
    "sg:postcode":"T2V 0W9",
    "sg:province":"AB",
    "sg:tags":[
        "dealer",
        "rug"
    ],
    "wof:name":"Creating A Masterpiece",
    "wof:placetype":"venue"
},
  "geometry": {"coordinates":[-114.093345642,50.9744033813],"type":"Point"}
}