{
  "type": "Feature",
  "properties": {
    "addr:full":"9210 Ellis Rd Prince George BC V2N 6E3",
    "addr:housenumber":"9210",
    "addr:postcode":"v2n 6e3",
    "addr:street":"Ellis Rd",
    "iso:country":"CA",
    "sg:address":"9210 Ellis Rd",
    "sg:city":"Prince George",
    "sg:classifiers":[
        {
            "category":"Building & Trades",
            "subcategory":"Construction",
            "type":"Services"
        }
    ],
    "sg:phone":"+1 250 963 8829",
    "sg:postcode":"V2N 6E3",
    "sg:province":"BC",
    "sg:tags":[
        "excavating",
        "contractor"
    ],
    "wof:name":"S Wilson Enterprises",
    "wof:placetype":"venue"
},
  "geometry": {"coordinates":[-122.675575256,53.8805580139],"type":"Point"}
}