{
  "type": "Feature",
  "properties": {
    "addr:full":"113 Talbot St S Essex ON N8M 1B3",
    "addr:housenumber":"113",
    "addr:postcode":"n8m 1b3",
    "addr:street":"Talbot St S",
    "iso:country":"CA",
    "sg:address":"113 Talbot St S",
    "sg:city":"Essex",
    "sg:classifiers":[
        {
            "category":"Health Services",
            "subcategory":"Optometrist",
            "type":"Services"
        }
    ],
    "sg:phone":"+1 519 776 8211",
    "sg:postcode":"N8M 1B3",
    "sg:province":"ON",
    "wof:name":"Kniaziew, R D OD",
    "wof:placetype":"venue"
},
  "geometry": {"coordinates":[-82.8168563843,42.1706848145],"type":"Point"}
}