{
  "type": "Feature",
  "properties": {
    "addr:full":"112 Lovett St S Deloraine MB R0M 0M0",
    "addr:housenumber":"112",
    "addr:postcode":"r0m 0m0",
    "addr:street":"Lovett St S Deloraine",
    "iso:country":"CA",
    "sg:address":"112 Lovett St S",
    "sg:city":"Deloraine",
    "sg:classifiers":[
        {
            "category":"Real Estate",
            "subcategory":"Real Estate Agent",
            "type":"Services"
        }
    ],
    "sg:phone":"+1 204 747 3154",
    "sg:postcode":"R0M 0M0",
    "sg:province":"MB",
    "sg:tags":[
        "housing"
    ],
    "wof:name":"Boarder Hills Housing CO-OP",
    "wof:placetype":"venue"
},
  "geometry": {"coordinates":[-100.496070862,49.1933364868],"type":"Point"}
}