{
  "type": "Feature",
  "properties": {
    "addr:full":"2381 St Clair Ave W Toronto ON M6N 1K9",
    "addr:housenumber":"2381",
    "addr:postcode":"m6n 1k9",
    "addr:street":"St Clair Ave W",
    "iso:country":"CA",
    "sg:address":"2381 St Clair Ave W",
    "sg:city":"Toronto",
    "sg:classifiers":[
        {
            "category":"Retail",
            "subcategory":"Auto Repair",
            "type":"Services"
        }
    ],
    "sg:phone":"+1 416 769 0961",
    "sg:postcode":"M6N 1K9",
    "sg:province":"ON",
    "sg:tags":[
        "repairing",
        "automobile"
    ],
    "wof:name":"Simpsons Auto Specialists",
    "wof:placetype":"venue"
},
  "geometry": {"coordinates":[-79.48143,43.669319],"type":"Point"}
}