{
  "type": "Feature",
  "properties": {
    "iso:country":"CA",
    "sg:address":"79 Prince Edward St #E",
    "sg:city":"Saint John",
    "sg:classifiers":[
        {
            "category":"Wholesale",
            "subcategory":"Machinery & Supplies",
            "type":"Manufacturing & Wholesale Goods"
        }
    ],
    "sg:phone":"+1 506 634 0026",
    "sg:postcode":"E2L 3S1",
    "sg:province":"NB",
    "sg:tags":[
        "equipment",
        "industrial"
    ],
    "wof:name":"Dcs Controls",
    "wof:placetype":"venue"
},
  "geometry": {"coordinates":[-66.05519104,45.2768478394],"type":"Point"}
}