{
  "type": "Feature",
  "properties": {
    "addr:full":"Richmond BC V7C 4N3",
    "addr:postcode":"v7c 4n3",
    "iso:country":"CA",
    "sg:city":"Richmond",
    "sg:classifiers":[
        {
            "category":"Professional",
            "subcategory":"Management & Consulting",
            "type":"Services"
        }
    ],
    "sg:phone":"+1 604 273 7765",
    "sg:postcode":"V7C 4N3",
    "sg:province":"BC",
    "sg:tags":[
        "construction",
        "general",
        "contractor"
    ],
    "wof:name":"Stuart Olson Construction Ltd",
    "wof:placetype":"venue"
},
  "geometry": {"coordinates":[-123.150032,49.176071],"type":"Point"}
}