{
  "type": "Feature",
  "properties": {
    "addr:full":"1688 Avenue Rd North York ON M5M 3Y4",
    "addr:housenumber":"1688",
    "addr:postcode":"m5m 3y4",
    "addr:street":"Avenue Rd",
    "iso:country":"CA",
    "sg:address":"1688 Avenue Rd",
    "sg:city":"North York",
    "sg:classifiers":[
        {
            "category":"Real Estate",
            "subcategory":"Real Estate Agent",
            "type":"Services"
        }
    ],
    "sg:phone":"+1 416 785 1500",
    "sg:postcode":"M5M 3Y4",
    "sg:province":"ON",
    "wof:name":"Forest Hill Real Estate Inc",
    "wof:placetype":"venue"
},
  "geometry": {"coordinates":[-79.41255200000001,43.767914],"type":"Point"}
}