{
  "type": "Feature",
  "properties": {
    "addr:full":"324 Av Principale Degelis QC G5T 1M4",
    "addr:postcode":"g5t 1m4",
    "addr:street":"324 Av Principale",
    "iso:country":"CA",
    "sg:address":"324 Av Principale",
    "sg:city":"Degelis",
    "sg:classifiers":[
        {
            "category":"Personal",
            "subcategory":"Beauty Salon",
            "type":"Services"
        }
    ],
    "sg:phone":"+1 418 853 3474",
    "sg:postcode":"G5T 1M4",
    "sg:province":"QC",
    "wof:name":"Liberte Coiffure Unisex Enr",
    "wof:placetype":"venue"
},
  "geometry": {"coordinates":[-68.64966583250001,47.5480575562],"type":"Point"}
}