{
  "type": "Feature",
  "properties": {
    "iso:country":"CA",
    "sg:address":"7317 Victoria Dr",
    "sg:city":"Vancouver",
    "sg:classifiers":[
        {
            "category":"Organizations",
            "subcategory":"Religious Organization",
            "type":"Services"
        }
    ],
    "sg:phone":"+1 604 324 2550",
    "sg:postcode":"V5P 3Z4",
    "sg:province":"BC",
    "sg:tags":[
        "church"
    ],
    "wof:name":"Young Kwang Presbyterian Chr",
    "wof:placetype":"venue"
},
  "geometry": {"coordinates":[-123.066101074,49.2178688049],"type":"Point"}
}