{
  "type": "Feature",
  "properties": {
    "addr:full":"12201 Keele St Maple ON L6A 1S1",
    "addr:housenumber":"12201",
    "addr:postcode":"l6a 1s1",
    "addr:street":"Keele St",
    "iso:country":"CA",
    "sg:address":"12201 Keele St",
    "sg:city":"Maple",
    "sg:classifiers":[
        {
            "category":"Building & Trades",
            "subcategory":"Construction",
            "type":"Services"
        }
    ],
    "sg:phone":"+1 905 303 1832",
    "sg:postcode":"L6A 1S1",
    "sg:province":"ON",
    "sg:tags":[
        "mantel"
    ],
    "wof:name":"King Fireplace Mantels Inc",
    "wof:placetype":"venue"
},
  "geometry": {"coordinates":[-79.52282,43.909546],"type":"Point"}
}