{
  "type": "Feature",
  "properties": {
    "addr:full":"Coleman PE C0B 1H0",
    "addr:postcode":"c0b 1h0",
    "iso:country":"CA",
    "sg:city":"Coleman",
    "sg:classifiers":[
        {
            "category":"Professional",
            "subcategory":"Business Services",
            "type":"Services"
        }
    ],
    "sg:phone":"+1 902 859 2350",
    "sg:postcode":"C0B 1H0",
    "sg:province":"PE",
    "sg:tags":[
        "equipment",
        "parts",
        "truck"
    ],
    "wof:name":"Morrison's Truck Salvage",
    "wof:placetype":"venue"
},
  "geometry": {"coordinates":[-64.17045593260001,46.6849708557],"type":"Point"}
}