{
  "type": "Feature",
  "properties": {
    "addr:full":"Middleton NS B0S 1P0",
    "addr:postcode":"b0s 1p0",
    "iso:country":"CA",
    "sg:city":"Middleton",
    "sg:classifiers":[
        {
            "category":"Professional",
            "subcategory":"Accounting & Tax Preparation",
            "type":"Services"
        }
    ],
    "sg:phone":"+1 902 825 6043",
    "sg:postcode":"B0S 1P0",
    "sg:province":"NS",
    "sg:tags":[
        "return",
        "filing"
    ],
    "wof:name":"H & R Block Canada Inc",
    "wof:placetype":"venue"
},
  "geometry": {"coordinates":[-65.0696105957,44.9417381287],"type":"Point"}
}