{
  "type": "Feature",
  "properties": {
    "iso:country":"CA",
    "sg:address":"5112 50 St",
    "sg:city":"Cold Lake",
    "sg:classifiers":[
        {
            "category":"Food & Beverages",
            "subcategory":"Bakery",
            "type":"Retail Goods"
        }
    ],
    "sg:phone":"+1 780 594 4962",
    "sg:postcode":"T9M 1X2",
    "sg:province":"AB",
    "sg:tags":[
        "baker"
    ],
    "wof:name":"Flying Dutchman Bakery",
    "wof:placetype":"venue"
},
  "geometry": {"coordinates":[-110.20598602299999,54.414604187],"type":"Point"}
}