{
  "type": "Feature",
  "properties": {
    "addr:full":"SE 36-1-24W Hwy 21 Goodlands MB R0M 0R0",
    "addr:postcode":"r0m 0r0",
    "addr:street":"Se 36-1-24W Hwy 21 Goodlands",
    "iso:country":"CA",
    "sg:address":"SE 36-1-24W Hwy 21",
    "sg:city":"Goodlands",
    "sg:classifiers":[
        {
            "category":"Freight",
            "type":"Transportation"
        }
    ],
    "sg:phone":"+1 204 658 3347",
    "sg:postcode":"R0M 0R0",
    "sg:province":"MB",
    "sg:tags":[
        "trucking"
    ],
    "wof:name":"Culbertson Trucking Ltd",
    "wof:placetype":"venue"
},
  "geometry": {"coordinates":[-100.600631714,49.0951843262],"type":"Point"}
}