{
  "type": "Feature",
  "properties": {
    "addr:full":"142 Trepanier St Landrienne QC J0Y 1V0",
    "addr:housenumber":"142",
    "addr:postcode":"j0y 1v0",
    "addr:street":"Trepanier St",
    "iso:country":"CA",
    "sg:address":"142 Trepanier St",
    "sg:city":"Landrienne",
    "sg:classifiers":[
        {
            "category":"Professional",
            "subcategory":"Management & Consulting",
            "type":"Services"
        }
    ],
    "sg:phone":"+1 819 732 4416",
    "sg:postcode":"J0Y 1V0",
    "sg:province":"QC",
    "sg:tags":[
        "consultant",
        "mining"
    ],
    "wof:name":"Lavoie & Freres Inc",
    "wof:placetype":"venue"
},
  "geometry": {"coordinates":[-77.94850158689999,48.5463523865],"type":"Point"}
}