{
  "type": "Feature",
  "properties": {
    "addr:full":"Waterloo ON N2J 4R4",
    "addr:postcode":"n2j 4r4",
    "iso:country":"CA",
    "sg:city":"Waterloo",
    "sg:classifiers":[
        {
            "category":"Wholesale",
            "subcategory":"Jewelry",
            "type":"Manufacturing & Wholesale Goods"
        }
    ],
    "sg:phone":"+1 519 886 4484",
    "sg:postcode":"N2J 4R4",
    "sg:province":"ON",
    "sg:tags":[
        "jeweler"
    ],
    "wof:name":"Chelsea International",
    "wof:placetype":"venue"
},
  "geometry": {"coordinates":[-80.5153503418,43.4892692566],"type":"Point"}
}