{
  "type": "Feature",
  "properties": {
    "addr:full":"25 Grand Marshall Dr Scarborough ON M1B 5N6",
    "addr:housenumber":"25",
    "addr:postcode":"m1b 5n6",
    "addr:street":"Grand Marshall Dr",
    "iso:country":"CA",
    "sg:address":"25 Grand Marshall Dr",
    "sg:city":"Scarborough",
    "sg:classifiers":[
        {
            "category":"Wholesale",
            "subcategory":"Groceries",
            "type":"Manufacturing & Wholesale Goods"
        }
    ],
    "sg:phone":"+1 416 299 5741",
    "sg:postcode":"M1B 5N6",
    "sg:province":"ON",
    "sg:tags":[
        "grocer"
    ],
    "wof:name":"B K Sethi Marketing Ltd",
    "wof:placetype":"venue"
},
  "geometry": {"coordinates":[-79.19533538819999,43.8004379272],"type":"Point"}
}