{
  "type": "Feature",
  "properties": {
    "iso:country":"CA",
    "sg:address":"106 High St",
    "sg:city":"Sutton West",
    "sg:classifiers":[
        {
            "category":"Banks & Credit Unions",
            "subcategory":"Bank",
            "type":"Services"
        }
    ],
    "sg:phone":"+1 905 722 3293",
    "sg:postcode":"L0E 1R0",
    "sg:province":"ON",
    "wof:name":"Bank of Montreal",
    "wof:placetype":"venue"
},
  "geometry": {"coordinates":[-79.358009,44.303253],"type":"Point"}
}