{
  "type": "Feature",
  "properties": {
    "addr:full":"139 Laurent O Maskinonge QC J0K 1N0",
    "addr:housenumber":"139",
    "addr:postcode":"j0k 1n0",
    "addr:street":"Laurent O",
    "iso:country":"CA",
    "sg:address":"139 Laurent O",
    "sg:city":"Maskinonge",
    "sg:classifiers":[
        {
            "category":"Restaurant",
            "type":"Food & Drink"
        }
    ],
    "sg:phone":"+1 819 227 1399",
    "sg:postcode":"J0K 1N0",
    "sg:province":"QC",
    "wof:name":"Restaurant Stexas",
    "wof:placetype":"venue"
},
  "geometry": {"coordinates":[-73.020348,46.229004],"type":"Point"}
}