{
  "type": "Feature",
  "properties": {
    "addr:full":"3185 Cawthra Rd Mississauga ON L5A 2X4",
    "addr:housenumber":"3185",
    "addr:postcode":"l5a 2x4",
    "addr:street":"Cawthra Rd",
    "iso:country":"CA",
    "sg:address":"3185 Cawthra Rd",
    "sg:city":"Mississauga",
    "sg:classifiers":[
        {
            "category":"Health Services",
            "subcategory":"Chiropractor",
            "type":"Services"
        }
    ],
    "sg:phone":"+1 905 276 2200",
    "sg:postcode":"L5A 2X4",
    "sg:province":"ON",
    "wof:name":"Cawthra Dundas Chiropractic",
    "wof:placetype":"venue"
},
  "geometry": {"coordinates":[-79.605217,43.598518],"type":"Point"}
}