{
  "type": "Feature",
  "properties": {
    "addr:full":"31 Albro Lake Rd Dartmouth NS B3A 3X9",
    "addr:housenumber":"31",
    "addr:postcode":"b3a 3x9",
    "addr:street":"Albro Lake Rd",
    "iso:country":"CA",
    "sg:address":"31 Albro Lake Rd",
    "sg:city":"Dartmouth",
    "sg:classifiers":[
        {
            "category":"Cinema",
            "subcategory":"Movie Rental",
            "type":"Entertainment"
        }
    ],
    "sg:phone":"+1 902 464 3573",
    "sg:postcode":"B3A 3X9",
    "sg:province":"NS",
    "sg:tags":[
        "leasing",
        "video",
        "disc",
        "tape"
    ],
    "wof:name":"J C's Video Store",
    "wof:placetype":"venue"
},
  "geometry": {"coordinates":[-63.58807,44.676613],"type":"Point"}
}