{
  "type": "Feature",
  "properties": {
    "addr:full":"236 Rutherford Rd S Brampton ON L6W 3J6",
    "addr:housenumber":"236",
    "addr:postcode":"l6w 3j6",
    "addr:street":"Rutherford Rd S",
    "iso:country":"CA",
    "sg:address":"236 Rutherford Rd S",
    "sg:city":"Brampton",
    "sg:classifiers":[
        {
            "category":"Retail",
            "subcategory":"Auto Repair",
            "type":"Services"
        }
    ],
    "sg:phone":"+1 905 459 1011",
    "sg:postcode":"L6W 3J6",
    "sg:province":"ON",
    "sg:tags":[
        "wrecker"
    ],
    "wof:name":"Hansen Towing",
    "wof:placetype":"venue"
},
  "geometry": {"coordinates":[-79.7295837402,43.6894454956],"type":"Point"}
}