{
  "type": "Feature",
  "properties": {
    "addr:full":"231 Bayfield Rd Goderich ON N7A 3G5",
    "addr:housenumber":"231",
    "addr:postcode":"n7a 3g5",
    "addr:street":"Bayfield Rd",
    "iso:country":"CA",
    "sg:address":"231 Bayfield Rd",
    "sg:city":"Goderich",
    "sg:classifiers":[
        {
            "category":"Organizations",
            "subcategory":"Religious Organization",
            "type":"Services"
        }
    ],
    "sg:phone":"+1 519 524 6445",
    "sg:postcode":"N7A 3G5",
    "sg:province":"ON",
    "sg:tags":[
        "church"
    ],
    "wof:name":"Calvary Baptist Church",
    "wof:placetype":"venue"
},
  "geometry": {"coordinates":[-81.70574999999999,43.73526],"type":"Point"}
}