{
  "type": "Feature",
  "properties": {
    "addr:full":"182 Mill St Creemore ON L0M 1G0",
    "addr:housenumber":"182",
    "addr:postcode":"l0m 1g0",
    "addr:street":"Mill St",
    "iso:country":"CA",
    "sg:address":"182 Mill St",
    "sg:city":"Creemore",
    "sg:classifiers":[
        {
            "category":"Retail",
            "subcategory":"Funeral Services",
            "type":"Services"
        }
    ],
    "sg:phone":"+1 705 466 2108",
    "sg:postcode":"L0M 1G0",
    "sg:province":"ON",
    "sg:tags":[
        "director"
    ],
    "wof:name":"Fawcett Funeral Home",
    "wof:placetype":"venue"
},
  "geometry": {"coordinates":[-80.106262207,44.3267593384],"type":"Point"}
}