{
  "type": "Feature",
  "properties": {
    "addr:full":"9325 51 Ave NW Edmonton AB T6E 4W8",
    "addr:housenumber":"9325",
    "addr:postcode":"t6e 4w8",
    "addr:street":"51 Ave Nw",
    "iso:country":"CA",
    "sg:address":"9325 51 Ave NW",
    "sg:city":"Edmonton",
    "sg:classifiers":[
        {
            "category":"Manufacturing",
            "subcategory":"Metals",
            "type":"Manufacturing & Wholesale Goods"
        }
    ],
    "sg:phone":"+1 780 434 8900",
    "sg:postcode":"T6E 4W8",
    "sg:province":"AB",
    "sg:tags":[
        "steel"
    ],
    "wof:name":"Dacro Industries Ltd",
    "wof:placetype":"venue"
},
  "geometry": {"coordinates":[-113.47154235799999,53.487865448],"type":"Point"}
}