{
  "type": "Feature",
  "properties": {
    "addr:full":"26 Whitetail Dr Winnipeg MB R3R 2X8",
    "addr:housenumber":"26",
    "addr:postcode":"r3r 2x8",
    "addr:street":"Whitetail Dr",
    "iso:country":"CA",
    "sg:address":"26 Whitetail Dr",
    "sg:city":"Winnipeg",
    "sg:classifiers":[
        {
            "category":"Building & Trades",
            "subcategory":"Cleaning & Sanitation",
            "type":"Services"
        }
    ],
    "sg:phone":"+1 204 885 7500",
    "sg:postcode":"R3R 2X8",
    "sg:province":"MB",
    "sg:tags":[
        "janitor"
    ],
    "wof:name":"Never So Clean",
    "wof:placetype":"venue"
},
  "geometry": {"coordinates":[-97.2525634766,49.8528366089],"type":"Point"}
}