{
  "type": "Feature",
  "properties": {
    "addr:full":"3200 Dufferin St #301 North York ON M6A 3B2",
    "addr:housenumber":"3200",
    "addr:postcode":"m6a 3b2",
    "addr:street":"Dufferin St # 301",
    "iso:country":"CA",
    "sg:address":"3200 Dufferin St #301",
    "sg:city":"North York",
    "sg:classifiers":[
        {
            "category":"Professional",
            "subcategory":"Lawyer & Legal Services",
            "type":"Services"
        }
    ],
    "sg:phone":"+1 416 780 1413",
    "sg:postcode":"M6A 3B2",
    "sg:province":"ON",
    "sg:tags":[
        "attorney"
    ],
    "wof:name":"Reybroek, Todd A",
    "wof:placetype":"venue"
},
  "geometry": {"coordinates":[-79.455879,43.718487],"type":"Point"}
}