{
  "type": "Feature",
  "properties": {
    "addr:full":"20 West Lodge Ave Toronto ON M6K 2T4",
    "addr:housenumber":"20",
    "addr:postcode":"m6k 2t4",
    "addr:street":"West Lodge Ave",
    "iso:country":"CA",
    "sg:address":"20 West Lodge Ave",
    "sg:city":"Toronto",
    "sg:classifiers":[
        {
            "category":"Social Services",
            "type":"Services"
        }
    ],
    "sg:phone":"+1 416 537 3553",
    "sg:postcode":"M6K 2T4",
    "sg:province":"ON",
    "sg:tags":[
        "organization",
        "welfare"
    ],
    "wof:name":"Parkdale Senior Supportive",
    "wof:placetype":"venue"
},
  "geometry": {"coordinates":[-79.43603515620001,43.6417732239],"type":"Point"}
}