{
  "type": "Feature",
  "properties": {
    "addr:full":"94 Crown Heights Cres Thornhill ON L4J 5T1",
    "addr:housenumber":"94",
    "addr:postcode":"l4j 5t1",
    "addr:street":"Crown",
    "iso:country":"CA",
    "sg:address":"94 Crown Heights Cres",
    "sg:city":"Thornhill",
    "sg:classifiers":[
        {
            "category":"Professional",
            "subcategory":"Business Services",
            "type":"Services"
        }
    ],
    "sg:phone":"+1 905 731 5773",
    "sg:postcode":"L4J 5T1",
    "sg:province":"ON",
    "sg:tags":[
        "interior",
        "consultant",
        "design",
        "decorator"
    ],
    "wof:name":"Belle Designs",
    "wof:placetype":"venue"
},
  "geometry": {"coordinates":[-79.446144104,43.7971000671],"type":"Point"}
}