{
  "type": "Feature",
  "properties": {
    "addr:full":"9527 Horton Rd SW Calgary AB T2V 2X5",
    "addr:housenumber":"9527",
    "addr:postcode":"t2v 2x5",
    "addr:street":"Horton Rd Sw",
    "iso:country":"CA",
    "sg:address":"9527 Horton Rd SW",
    "sg:city":"Calgary",
    "sg:classifiers":[
        {
            "category":"Freight",
            "type":"Transportation"
        }
    ],
    "sg:phone":"+1 403 255 0116",
    "sg:postcode":"T2V 2X5",
    "sg:province":"AB",
    "sg:tags":[
        "warehouse",
        "self",
        "storage"
    ],
    "wof:name":"Storage Van Rentals",
    "wof:placetype":"venue"
},
  "geometry": {"coordinates":[-114.075211,50.969654],"type":"Point"}
}