{
  "type": "Feature",
  "properties": {
    "iso:country":"CA",
    "sg:address":"318 E River Rd",
    "sg:city":"New Glasgow",
    "sg:classifiers":[
        {
            "category":"Retail",
            "subcategory":"Laundry & Dry Cleaning",
            "type":"Services"
        }
    ],
    "sg:phone":"+1 902 752 1563",
    "sg:postcode":"B2H 5C5",
    "sg:province":"NS",
    "sg:tags":[
        "cleaners"
    ],
    "wof:name":"Sunshine Dry Cleaners Ltd",
    "wof:placetype":"venue"
},
  "geometry": {"coordinates":[-62.6450538635,45.5845413208],"type":"Point"}
}