{
  "type": "Feature",
  "properties": {
    "iso:country":"CA",
    "sg:address":"1911 Kennedy Rd",
    "sg:city":"Scarborough",
    "sg:classifiers":[
        {
            "category":"Personal",
            "subcategory":"Tanning Parlor",
            "type":"Services"
        }
    ],
    "sg:phone":"+1 416 297 7279",
    "sg:postcode":"M1P 2L9",
    "sg:province":"ON",
    "sg:tags":[
        "salon"
    ],
    "wof:name":"Good Life Fitness Club",
    "wof:placetype":"venue"
},
  "geometry": {"coordinates":[-79.28125,43.7672653198],"type":"Point"}
}