{
  "type": "Feature",
  "properties": {
    "addr:full":"3915 Albert St Regina SK S4S 3R4",
    "addr:housenumber":"3915",
    "addr:postcode":"s4s 3r4",
    "addr:street":"Albert St",
    "iso:country":"CA",
    "sg:address":"3915 Albert St",
    "sg:city":"Regina",
    "sg:classifiers":[
        {
            "category":"Restaurant",
            "type":"Food & Drink"
        }
    ],
    "sg:phone":"+1 306 585 9000",
    "sg:postcode":"S4S 3R4",
    "sg:province":"SK",
    "wof:name":"Tomas Cook Restaurant & Sports",
    "wof:placetype":"venue"
},
  "geometry": {"coordinates":[-104.61773700000001,50.416836],"type":"Point"}
}