{
  "type": "Feature",
  "properties": {
    "addr:full":"2295 Concession Rd 2 # C Woodville ON K0M 2T0",
    "addr:housenumber":"2295",
    "addr:postcode":"k0m 2t0",
    "addr:street":"Concession Rd 2 # C",
    "iso:country":"CA",
    "sg:address":"2295 Concession Rd 2 # C",
    "sg:city":"Woodville",
    "sg:classifiers":[
        {
            "category":"Building & Trades",
            "subcategory":"Electrical",
            "type":"Services"
        }
    ],
    "sg:phone":"+1 705 439 1261",
    "sg:postcode":"K0M 2T0",
    "sg:province":"ON",
    "sg:tags":[
        "electric",
        "contractor"
    ],
    "wof:name":"Veale Electric",
    "wof:placetype":"venue"
},
  "geometry": {"coordinates":[-78.72584500000001,44.531769],"type":"Point"}
}