{
  "type": "Feature",
  "properties": {
    "iso:country":"CA",
    "sg:address":"41 Micmac Blvd",
    "sg:city":"Dartmouth",
    "sg:classifiers":[
        {
            "category":"Shopping",
            "subcategory":"Books",
            "type":"Retail Goods"
        }
    ],
    "sg:phone":"+1 902 466 1640",
    "sg:postcode":"B3A 4Y8",
    "sg:province":"NS",
    "sg:tags":[
        "dealer"
    ],
    "wof:name":"Chapters",
    "wof:placetype":"venue"
},
  "geometry": {"coordinates":[-63.559368,44.684116],"type":"Point"}
}