{
  "type": "Feature",
  "properties": {
    "addr:full":"Fermeuse NL A0A 2G0",
    "addr:postcode":"a0a 2g0",
    "iso:country":"CA",
    "sg:city":"Fermeuse",
    "sg:classifiers":[
        {
            "category":"Government",
            "subcategory":"Office",
            "type":"Public Place"
        }
    ],
    "sg:phone":"+1 709 363 2400",
    "sg:postcode":"A0A 2G0",
    "sg:province":"NL",
    "sg:tags":[
        "village"
    ],
    "wof:name":"Community Council of Fermeuse",
    "wof:placetype":"venue"
},
  "geometry": {"coordinates":[-52.958096,46.973972],"type":"Point"}
}