{
  "type": "Feature",
  "properties": {
    "addr:full":"Hamilton ON L8L 3B4",
    "addr:postcode":"l8l 3b4",
    "iso:country":"CA",
    "sg:city":"Hamilton",
    "sg:classifiers":[
        {
            "category":"Restaurant",
            "type":"Food & Drink"
        }
    ],
    "sg:phone":"+1 905 547 7360",
    "sg:postcode":"L8L 3B4",
    "sg:province":"ON",
    "wof:name":"Subway Sandwiches & Salads",
    "wof:placetype":"venue"
},
  "geometry": {"coordinates":[-79.82822400000001,43.254555],"type":"Point"}
}