{
  "type": "Feature",
  "properties": {
    "addr:full":"4025 Rue Lavoisier # B Boisbriand QC J7H 1N1",
    "addr:housenumber":"4025;# b",
    "addr:postcode":"j7h 1n1",
    "addr:street":"Rue Lavoisier",
    "iso:country":"CA",
    "sg:address":"4025 Rue Lavoisier # B",
    "sg:city":"Boisbriand",
    "sg:classifiers":[
        {
            "category":"Manufacturing",
            "subcategory":"Signs",
            "type":"Manufacturing & Wholesale Goods"
        }
    ],
    "sg:phone":"+1 450 430 3906",
    "sg:postcode":"J7H 1N1",
    "sg:province":"QC",
    "wof:name":"Gravure Mille-Iles Inc",
    "wof:placetype":"venue"
},
  "geometry": {"coordinates":[-73.868362,45.631603],"type":"Point"}
}