{
  "type": "Feature",
  "properties": {
    "addr:full":"6771 Kirkpatrick Cres Saanichton BC V8M 1Z8",
    "addr:housenumber":"6771",
    "addr:postcode":"v8m 1z8",
    "addr:street":"Kirkpatrick Cres",
    "iso:country":"CA",
    "sg:address":"6771 Kirkpatrick Cres",
    "sg:city":"Saanichton",
    "sg:classifiers":[
        {
            "category":"Manufacturing",
            "subcategory":"Toys & Sporting Goods",
            "type":"Manufacturing & Wholesale Goods"
        }
    ],
    "sg:phone":"+1 250 544 1440",
    "sg:postcode":"V8M 1Z8",
    "sg:province":"BC",
    "sg:tags":[
        "tackle",
        "fishing"
    ],
    "wof:name":"Islander Reels",
    "wof:placetype":"venue"
},
  "geometry": {"coordinates":[-123.41689300500001,48.595199585],"type":"Point"}
}