{
  "type": "Feature",
  "properties": {
    "addr:full":"1822 Highway 11 Sundridge ON P0A 1Z0",
    "addr:housenumber":"1822",
    "addr:postcode":"p0a 1z0",
    "addr:street":"Highway 11",
    "iso:country":"CA",
    "sg:address":"1822 Highway 11",
    "sg:city":"Sundridge",
    "sg:classifiers":[
        {
            "category":"Organizations",
            "subcategory":"Religious Organization",
            "type":"Services"
        }
    ],
    "sg:phone":"+1 705 384 7323",
    "sg:postcode":"P0A 1Z0",
    "sg:province":"ON",
    "sg:tags":[
        "church"
    ],
    "wof:name":"Sundridge Gospel Mission",
    "wof:placetype":"venue"
},
  "geometry": {"coordinates":[-79.399536,45.766579],"type":"Point"}
}