{
  "type": "Feature",
  "properties": {
    "addr:full":"855 Oliver Rd Thunder Bay ON P7B 5E1",
    "addr:housenumber":"855",
    "addr:postcode":"p7b 5e1",
    "addr:street":"Oliver Rd",
    "iso:country":"CA",
    "sg:address":"855 Oliver Rd",
    "sg:city":"Thunder Bay",
    "sg:classifiers":[
        {
            "category":"Social Services",
            "subcategory":"Child Care",
            "type":"Services"
        }
    ],
    "sg:phone":"+1 807 343 8369",
    "sg:postcode":"P7B 5E1",
    "sg:province":"ON",
    "wof:name":"Nanabijou Childcare Ctr",
    "wof:placetype":"venue"
},
  "geometry": {"coordinates":[-89.258827,48.424271],"type":"Point"}
}