{
  "type": "Feature",
  "properties": {
    "addr:full":"200 2nd Ave W Assiniboia SK S0H 0B0",
    "addr:housenumber":"200",
    "addr:postcode":"s0h 0b0",
    "addr:street":"2Nd Ave W Assiniboia",
    "iso:country":"CA",
    "sg:address":"200 2nd Ave W",
    "sg:city":"Assiniboia",
    "sg:classifiers":[
        {
            "category":"Home & Garden",
            "subcategory":"Carpets & Floor Coverings",
            "type":"Retail Goods"
        }
    ],
    "sg:phone":"+1 306 642 3339",
    "sg:postcode":"S0H 0B0",
    "sg:province":"SK",
    "sg:tags":[
        "rug"
    ],
    "wof:name":"Homestyle Floors & Interiors",
    "wof:placetype":"venue"
},
  "geometry": {"coordinates":[-105.993118,49.632839],"type":"Point"}
}