{
  "type": "Feature",
  "properties": {
    "addr:full":"Toronto ON M4P 2Y1",
    "addr:postcode":"m4p 2y1",
    "iso:country":"CA",
    "sg:city":"Toronto",
    "sg:classifiers":[
        {
            "category":"Communications",
            "subcategory":"Film & Video Production",
            "type":"Services"
        }
    ],
    "sg:phone":"+1 416 483 9773",
    "sg:postcode":"M4P 2Y1",
    "sg:province":"ON",
    "sg:tags":[
        "television",
        "producer"
    ],
    "wof:name":"Portfolio Entertainment",
    "wof:placetype":"venue"
},
  "geometry": {"coordinates":[-79.39516399999999,43.707554],"type":"Point"}
}