{
  "type": "Feature",
  "properties": {
    "addr:full":"455 Boul Henri-Bourassa O Montreal QC H3L 1P3",
    "addr:housenumber":"455",
    "addr:postcode":"h3l 1p3",
    "addr:street":"Boul Henri-Bourassa O",
    "iso:country":"CA",
    "sg:address":"455 Boul Henri-Bourassa O",
    "sg:city":"Montreal",
    "sg:classifiers":[
        {
            "category":"Local Transit",
            "type":"Transportation"
        }
    ],
    "sg:phone":"+1 514 878 2789",
    "sg:postcode":"H3L 1P3",
    "sg:province":"QC",
    "sg:tags":[
        "limousine"
    ],
    "wof:name":"Limousine Quartz Inc",
    "wof:placetype":"venue"
},
  "geometry": {"coordinates":[-73.669090271,45.5542030334],"type":"Point"}
}