{
  "type": "Feature",
  "properties": {
    "iso:country":"CA",
    "sg:address":"120 Water St",
    "sg:city":"Summerside",
    "sg:classifiers":[
        {
            "category":"Government",
            "subcategory":"Office",
            "type":"Public Place"
        }
    ],
    "sg:phone":"+1 902 888 8000",
    "sg:postcode":"C1N 1A9",
    "sg:province":"PE",
    "wof:name":"P E Access-Pei",
    "wof:placetype":"venue"
},
  "geometry": {"coordinates":[-63.7720108032,46.3929100037],"type":"Point"}
}