{
  "type": "Feature",
  "properties": {
    "addr:full":"870 Montee Laurin Saint-Eustache QC J7R 4K3",
    "addr:housenumber":"870",
    "addr:postcode":"j7r 4k3",
    "addr:street":"Montee Laurin",
    "iso:country":"CA",
    "sg:address":"870 Montee Laurin",
    "sg:city":"Saint-Eustache",
    "sg:classifiers":[
        {
            "category":"Cinema",
            "subcategory":"Movie Theater",
            "type":"Entertainment"
        }
    ],
    "sg:phone":"+1 450 473 3357",
    "sg:postcode":"J7R 4K3",
    "sg:province":"QC",
    "wof:name":"Theatre Des Erables",
    "wof:placetype":"venue"
},
  "geometry": {"coordinates":[-73.978989,45.567993],"type":"Point"}
}