{
  "type": "Feature",
  "properties": {
    "iso:country":"CA",
    "sg:address":"5081 50 St",
    "sg:city":"Waskatenau",
    "sg:classifiers":[
        {
            "category":"Retail",
            "subcategory":"Repair Shop",
            "type":"Services"
        }
    ],
    "sg:phone":"+1 780 623 8227",
    "sg:postcode":"T0A 3P0",
    "sg:province":"AB",
    "sg:tags":[
        "upholsterer"
    ],
    "wof:name":"Pete's Upholstery",
    "wof:placetype":"venue"
},
  "geometry": {"coordinates":[-112.784782,54.094296],"type":"Point"}
}