{
  "type": "Feature",
  "properties": {
    "addr:full":"1350 Rue Dessaulles Saint-Hyacinthe QC J2S 2S4",
    "addr:housenumber":"1350",
    "addr:postcode":"j2s 2s4",
    "addr:street":"Rue Dessaulles",
    "iso:country":"CA",
    "sg:address":"1350 Rue Dessaulles",
    "sg:city":"Saint-Hyacinthe",
    "sg:classifiers":[
        {
            "category":"Autos & Motor Vehicles",
            "subcategory":"Fuel & Gas Station",
            "type":"Retail Goods"
        }
    ],
    "sg:phone":"+1 450 774 3014",
    "sg:postcode":"J2S 2S4",
    "sg:province":"QC",
    "sg:tags":[
        "oil"
    ],
    "wof:name":"Depanneur 24 Heures Inc",
    "wof:placetype":"venue"
},
  "geometry": {"coordinates":[-72.946793,45.62709],"type":"Point"}
}