{
  "type": "Feature",
  "properties": {
    "addr:full":"131 East Dr Brampton ON L6T 1B5",
    "addr:housenumber":"131",
    "addr:postcode":"l6t 1b5",
    "addr:street":"East Dr",
    "iso:country":"CA",
    "sg:address":"131 East Dr",
    "sg:city":"Brampton",
    "sg:classifiers":[
        {
            "category":"Manufacturing",
            "subcategory":"Chemicals & Compounds",
            "type":"Manufacturing & Wholesale Goods"
        }
    ],
    "sg:phone":"+1 905 791 1788",
    "sg:postcode":"L6T 1B5",
    "sg:province":"ON",
    "wof:name":"Recochem Inc",
    "wof:placetype":"venue"
},
  "geometry": {"coordinates":[-79.69072,43.710716],"type":"Point"}
}