{
  "type": "Feature",
  "properties": {
    "addr:full":"Lloydminster AB T9V 2Y8",
    "addr:postcode":"t9v 2y8",
    "iso:country":"CA",
    "sg:city":"Lloydminster",
    "sg:classifiers":[
        {
            "category":"Personal",
            "subcategory":"Beauty Salon",
            "type":"Services"
        }
    ],
    "sg:phone":"+1 780 808 2777",
    "sg:postcode":"T9V 2Y8",
    "sg:province":"AB",
    "wof:name":"Hair Designers",
    "wof:placetype":"venue"
},
  "geometry": {"coordinates":[-110.00592804,53.273525238],"type":"Point"}
}