{
  "type": "Feature",
  "properties": {
    "addr:full":"50 Ch DE Gaspe Bromont QC J2L 2N8",
    "addr:housenumber":"50",
    "addr:postcode":"j2l 2n8",
    "addr:street":"Ch De Gaspe",
    "iso:country":"CA",
    "sg:address":"50 Ch DE Gaspe",
    "sg:city":"Bromont",
    "sg:classifiers":[
        {
            "category":"Professional",
            "subcategory":"Business Services",
            "type":"Services"
        }
    ],
    "sg:phone":"+1 450 534 3638",
    "sg:postcode":"J2L 2N8",
    "sg:province":"QC",
    "sg:tags":[
        "embroidery"
    ],
    "wof:name":"Super Punch",
    "wof:placetype":"venue"
},
  "geometry": {"coordinates":[-72.657265,45.316105],"type":"Point"}
}