{
  "type": "Feature",
  "properties": {
    "addr:full":"836 Yates St Victoria BC V8W 1L8",
    "addr:housenumber":"836",
    "addr:postcode":"v8w 1l8",
    "addr:street":"Yates St",
    "iso:country":"CA",
    "sg:address":"836 Yates St",
    "sg:city":"Victoria",
    "sg:classifiers":[
        {
            "category":"Government",
            "subcategory":"Office",
            "type":"Public Place"
        }
    ],
    "sg:phone":"+1 250 387 5664",
    "sg:postcode":"V8W 1L8",
    "sg:province":"BC",
    "wof:name":"BC Social Health Svc",
    "wof:placetype":"venue"
},
  "geometry": {"coordinates":[-123.36090850799999,48.4260025024],"type":"Point"}
}