{
  "type": "Feature",
  "properties": {
    "addr:full":"Montmagny QC G5V 4L9",
    "addr:postcode":"g5v 4l9",
    "iso:country":"CA",
    "sg:city":"Montmagny",
    "sg:classifiers":[
        {
            "category":"Health Services",
            "subcategory":"Nursing And Care Facility",
            "type":"Services"
        }
    ],
    "sg:phone":"+1 418 248 1517",
    "sg:postcode":"G5V 4L9",
    "sg:province":"QC",
    "sg:tags":[
        "home",
        "retirement",
        "community"
    ],
    "wof:name":"Habitation Mgr Deschenes",
    "wof:placetype":"venue"
},
  "geometry": {"coordinates":[-70.55722,46.982647],"type":"Point"}
}