{
  "type": "Feature",
  "properties": {
    "addr:full":"135 3rd Ave Cochrane ON P0L 1C0",
    "addr:housenumber":"135",
    "addr:postcode":"p0l 1c0",
    "addr:street":"3Rd Ave",
    "iso:country":"CA",
    "sg:address":"135 3rd Ave",
    "sg:city":"Cochrane",
    "sg:classifiers":[
        {
            "category":"Home & Garden",
            "subcategory":"Garden Supply",
            "type":"Retail Goods"
        }
    ],
    "sg:phone":"+1 705 272 3254",
    "sg:postcode":"P0L 1C0",
    "sg:province":"ON",
    "sg:tags":[
        "lawn",
        "mower",
        "scooter",
        "motor",
        "motorcycle"
    ],
    "wof:name":"Paps Power Shop Ltd",
    "wof:placetype":"venue"
},
  "geometry": {"coordinates":[-81.029831,49.061871],"type":"Point"}
}