{
  "type": "Feature",
  "properties": {
    "addr:full":"PO Box 215 Worsley AB T0H 3W0",
    "addr:housenumber":"po",
    "addr:postcode":"t0h 3w0",
    "addr:street":"Box 215",
    "iso:country":"CA",
    "sg:address":"PO Box 215",
    "sg:city":"Worsley",
    "sg:classifiers":[
        {
            "category":"Home & Garden",
            "subcategory":"Building Materials",
            "type":"Retail Goods"
        }
    ],
    "sg:phone":"+1 780 685 2481",
    "sg:postcode":"T0H 3W0",
    "sg:province":"AB",
    "sg:tags":[
        "glass",
        "window",
        "plate"
    ],
    "wof:name":"Westown Enterprises Ltd",
    "wof:placetype":"venue"
},
  "geometry": {"coordinates":[-119.13988494900001,56.5087165833],"type":"Point"}
}