{
  "type": "Feature",
  "properties": {
    "addr:full":"6560 Rue Hochelaga Montreal QC H1N 1X9",
    "addr:housenumber":"6560",
    "addr:postcode":"h1n 1x9",
    "addr:street":"Rue Hochelaga",
    "iso:country":"CA",
    "sg:address":"6560 Rue Hochelaga",
    "sg:city":"Montreal",
    "sg:classifiers":[
        {
            "category":"Museum",
            "type":"Entertainment"
        }
    ],
    "sg:phone":"+1 514 899 3224",
    "sg:postcode":"H1N 1X9",
    "sg:province":"QC",
    "wof:name":"Musee Militaire Crcmm/Rcoc",
    "wof:placetype":"venue"
},
  "geometry": {"coordinates":[-73.53215,45.578941],"type":"Point"}
}