{
  "type": "Feature",
  "properties": {
    "addr:full":"115 King St Shelburne NS B0T 1W0",
    "addr:housenumber":"115",
    "addr:postcode":"b0t 1w0",
    "addr:street":"King St",
    "iso:country":"CA",
    "sg:address":"115 King St",
    "sg:city":"Shelburne",
    "sg:classifiers":[
        {
            "category":"Real Estate",
            "subcategory":"Real Estate Operator",
            "type":"Services"
        }
    ],
    "sg:phone":"+1 902 875 2579",
    "sg:postcode":"B0T 1W0",
    "sg:province":"NS",
    "sg:tags":[
        "mall",
        "shopping",
        "center"
    ],
    "wof:name":"Shelburne Mall",
    "wof:placetype":"venue"
},
  "geometry": {"coordinates":[-65.31564331049999,43.7656593323],"type":"Point"}
}