{
  "type": "Feature",
  "properties": {
    "addr:full":"9858 Hwy 8 Caledonia NS B0T 1B0",
    "addr:housenumber":"9858",
    "addr:postcode":"b0t 1b0",
    "addr:street":"Hwy 8",
    "iso:country":"CA",
    "sg:address":"9858 Hwy 8",
    "sg:city":"Caledonia",
    "sg:classifiers":[
        {
            "category":"Organizations",
            "subcategory":"Religious Organization",
            "type":"Services"
        }
    ],
    "sg:phone":"+1 902 682 2546",
    "sg:postcode":"B0T 1B0",
    "sg:province":"NS",
    "sg:tags":[
        "church"
    ],
    "wof:name":"United Church Manse",
    "wof:placetype":"venue"
},
  "geometry": {"coordinates":[-65.03215026860001,44.3758201599],"type":"Point"}
}