{
  "type": "Feature",
  "properties": {
    "addr:full":"Val Marie SK S0N 2T0",
    "addr:postcode":"s0n 2t0",
    "addr:street":"Val",
    "iso:country":"CA",
    "sg:city":"Val Marie",
    "sg:classifiers":[
        {
            "category":"Government",
            "subcategory":"Office",
            "type":"Public Place"
        }
    ],
    "sg:phone":"+1 306 298 4606",
    "sg:postcode":"S0N 2T0",
    "sg:province":"SK",
    "wof:name":"Canada Community Pastures",
    "wof:placetype":"venue"
},
  "geometry": {"coordinates":[-107.725311279,49.2469940186],"type":"Point"}
}