{
  "type": "Feature",
  "properties": {
    "iso:country":"CA",
    "sg:address":"3610 Mavis Rd",
    "sg:city":"Mississauga",
    "sg:classifiers":[
        {
            "category":"Manufacturing",
            "subcategory":"Tools & Machinery",
            "type":"Manufacturing & Wholesale Goods"
        }
    ],
    "sg:phone":"+1 905 279 5370",
    "sg:postcode":"L5C 1W2",
    "sg:province":"ON",
    "sg:tags":[
        "equipment",
        "material",
        "handling"
    ],
    "wof:name":"Mobile Industries Inc",
    "wof:placetype":"venue"
},
  "geometry": {"coordinates":[-79.649520874,43.5774803162],"type":"Point"}
}