{
  "type": "Feature",
  "properties": {
    "addr:full":"1684 Ch Noiseux Dunham QC J0E 1M0",
    "addr:postcode":"1684;j0e 1m0",
    "addr:street":"Ch Noiseux",
    "iso:country":"CA",
    "sg:address":"1684 Ch Noiseux",
    "sg:city":"Dunham",
    "sg:classifiers":[
        {
            "category":"Building & Trades",
            "subcategory":"Construction",
            "type":"Services"
        }
    ],
    "sg:phone":"+1 450 266 5804",
    "sg:postcode":"J0E 1M0",
    "sg:province":"QC",
    "sg:tags":[
        "contractor"
    ],
    "wof:name":"Construction Gilles Noiseux",
    "wof:placetype":"venue"
},
  "geometry": {"coordinates":[-72.822304,45.156788],"type":"Point"}
}