{
  "type": "Feature",
  "properties": {
    "addr:full":"880 Main St Moncton NB E1C 1G4",
    "addr:housenumber":"880",
    "addr:postcode":"e1c 1g4",
    "addr:street":"Main St",
    "iso:country":"CA",
    "sg:address":"880 Main St",
    "sg:city":"Moncton",
    "sg:classifiers":[
        {
            "category":"Wholesale",
            "subcategory":"Hardware",
            "type":"Manufacturing & Wholesale Goods"
        }
    ],
    "sg:phone":"+1 506 867 0380",
    "sg:postcode":"E1C 1G4",
    "sg:province":"NB",
    "sg:tags":[
        "equipment",
        "heating",
        "system"
    ],
    "wof:name":"Hydropower Canada Engineering",
    "wof:placetype":"venue"
},
  "geometry": {"coordinates":[-64.779633,46.088051],"type":"Point"}
}