{
  "type": "Feature",
  "properties": {
    "addr:full":"3614 Second Division Rd Church Point NS B0W 1M0",
    "addr:housenumber":"3614",
    "addr:postcode":"b0w 1m0",
    "addr:street":"Second Division Rd",
    "iso:country":"CA",
    "sg:address":"3614 Second Division Rd",
    "sg:city":"Church Point",
    "sg:classifiers":[
        {
            "category":"Organizations",
            "subcategory":"Religious Organization",
            "type":"Services"
        }
    ],
    "sg:phone":"+1 902 769 2320",
    "sg:postcode":"B0W 1M0",
    "sg:province":"NS",
    "sg:tags":[
        "church"
    ],
    "wof:name":"Our Lady of MT Carmel",
    "wof:placetype":"venue"
},
  "geometry": {"coordinates":[-66.11591339109999,44.3361778259],"type":"Point"}
}