{
  "type": "Feature",
  "properties": {
    "addr:full":"Nepean ON K2J 3Z6",
    "addr:postcode":"k2j 3z6",
    "iso:country":"CA",
    "sg:city":"Nepean",
    "sg:classifiers":[
        {
            "category":"Health Services",
            "subcategory":"Doctor",
            "type":"Services"
        }
    ],
    "sg:phone":"+1 613 825 9192",
    "sg:postcode":"K2J 3Z6",
    "sg:province":"ON",
    "sg:tags":[
        "physician",
        "surgeon"
    ],
    "wof:name":"DE Souza, Eleanor MD",
    "wof:placetype":"venue"
},
  "geometry": {"coordinates":[-75.75709500000001,45.285927],"type":"Point"}
}