{
  "type": "Feature",
  "properties": {
    "addr:full":"Burlington ON L7L 5L6",
    "addr:postcode":"l7l 5l6",
    "iso:country":"CA",
    "sg:city":"Burlington",
    "sg:classifiers":[
        {
            "category":"Wholesale",
            "subcategory":"Construction Materials",
            "type":"Manufacturing & Wholesale Goods"
        }
    ],
    "sg:phone":"+1 905 632 0508",
    "sg:postcode":"L7L 5L6",
    "sg:province":"ON",
    "sg:tags":[
        "frame",
        "industrial",
        "door"
    ],
    "wof:name":"Entra Tech Inc",
    "wof:placetype":"venue"
},
  "geometry": {"coordinates":[-79.780869,43.368488],"type":"Point"}
}