{
  "type": "Feature",
  "properties": {
    "addr:full":"1725 8th Ave E Prince Rupert BC V8J 2N9",
    "addr:housenumber":"1725",
    "addr:postcode":"v8j 2n9",
    "addr:street":"8Th Ave E",
    "iso:country":"CA",
    "sg:address":"1725 8th Ave E",
    "sg:city":"Prince Rupert",
    "sg:classifiers":[
        {
            "category":"Education",
            "subcategory":"School",
            "type":"Public Place"
        }
    ],
    "sg:phone":"+1 250 624 6361",
    "sg:postcode":"V8J 2N9",
    "sg:province":"BC",
    "wof:name":"Seal Cove Elementary",
    "wof:placetype":"venue"
},
  "geometry": {"coordinates":[-130.29272499999999,54.326225],"type":"Point"}
}