{
  "type": "Feature",
  "properties": {
    "addr:full":"700 Brookdale Ave Cornwall ON K6J 5M2",
    "addr:housenumber":"700",
    "addr:postcode":"k6j 5m2",
    "addr:street":"Brookdale Ave",
    "iso:country":"CA",
    "sg:address":"700 Brookdale Ave",
    "sg:city":"Cornwall",
    "sg:classifiers":[
        {
            "category":"Restaurant",
            "type":"Food & Drink"
        }
    ],
    "sg:phone":"+1 613 938 2555",
    "sg:postcode":"K6J 5M2",
    "sg:province":"ON",
    "wof:name":"Harvey's",
    "wof:placetype":"venue"
},
  "geometry": {"coordinates":[-74.74659,45.021088],"type":"Point"}
}