{
  "type": "Feature",
  "properties": {
    "addr:full":"3033 Kingston Rd Scarborough ON M1M 1P1",
    "addr:housenumber":"3033",
    "addr:postcode":"m1m 1p1",
    "addr:street":"Kingston Rd",
    "iso:country":"CA",
    "sg:address":"3033 Kingston Rd",
    "sg:city":"Scarborough",
    "sg:classifiers":[
        {
            "category":"Personal",
            "subcategory":"Beauty Salon",
            "type":"Services"
        }
    ],
    "sg:phone":"+1 416 266 8861",
    "sg:postcode":"M1M 1P1",
    "sg:province":"ON",
    "wof:name":"Cliffcrest Unisex Hairstylist",
    "wof:placetype":"venue"
},
  "geometry": {"coordinates":[-79.2309417725,43.7261772156],"type":"Point"}
}