{
  "type": "Feature",
  "properties": {
    "addr:full":"71 Sparks St Ottawa ON K1P 5A5",
    "addr:housenumber":"71",
    "addr:postcode":"k1p 5a5",
    "addr:street":"Sparks St",
    "iso:country":"CA",
    "sg:address":"71 Sparks St",
    "sg:city":"Ottawa",
    "sg:classifiers":[
        {
            "category":"Shopping",
            "subcategory":"Used Merchandise",
            "type":"Retail Goods"
        }
    ],
    "sg:phone":"+1 613 234 2348",
    "sg:postcode":"K1P 5A5",
    "sg:province":"ON",
    "sg:tags":[
        "antique"
    ],
    "wof:name":"Astrolabe Gallery",
    "wof:placetype":"venue"
},
  "geometry": {"coordinates":[-75.697052,45.423183],"type":"Point"}
}