{
  "type": "Feature",
  "properties": {
    "addr:full":"Lethbridge AB T1J 2G7",
    "addr:postcode":"t1j 2g7",
    "iso:country":"CA",
    "sg:city":"Lethbridge",
    "sg:classifiers":[
        {
            "category":"Professional",
            "subcategory":"Lawyer & Legal Services",
            "type":"Services"
        }
    ],
    "sg:phone":"+1 403 380 6005",
    "sg:postcode":"T1J 2G7",
    "sg:province":"AB",
    "sg:tags":[
        "attorney"
    ],
    "wof:name":"Doug Alger Law Office",
    "wof:placetype":"venue"
},
  "geometry": {"coordinates":[-112.837143,49.693859],"type":"Point"}
}