{
  "type": "Feature",
  "properties": {
    "iso:country":"CA",
    "sg:address":"369 Mclaughlin Dr",
    "sg:city":"Moncton",
    "sg:classifiers":[
        {
            "category":"Food & Beverages",
            "subcategory":"Groceries & Convenience Stores",
            "type":"Retail Goods"
        }
    ],
    "sg:phone":"+1 506 856 5908",
    "sg:postcode":"E1A 4R3",
    "sg:province":"NB",
    "sg:tags":[
        "grocer"
    ],
    "wof:name":"A & C Convenience Store Ltd",
    "wof:placetype":"venue"
},
  "geometry": {"coordinates":[-64.7835922241,46.1161308289],"type":"Point"}
}