{
  "type": "Feature",
  "properties": {
    "addr:full":"1212 Boul Saint-Laurent Montreal QC H2X 2S5",
    "addr:housenumber":"1212",
    "addr:postcode":"h2x 2s5",
    "addr:street":"Boul Saint-Laurent",
    "iso:country":"CA",
    "sg:address":"1212 Boul Saint-Laurent",
    "sg:city":"Montreal",
    "sg:classifiers":[
        {
            "category":"Restaurant",
            "type":"Food & Drink"
        }
    ],
    "sg:phone":"+1 514 866 0790",
    "sg:postcode":"H2X 2S5",
    "sg:province":"QC",
    "wof:name":"New Frites Dorees",
    "wof:placetype":"venue"
},
  "geometry": {"coordinates":[-73.56295799999999,45.509319],"type":"Point"}
}