{
  "type": "Feature",
  "properties": {
    "addr:full":"Oakville ON L6K 3W9",
    "addr:postcode":"l6k 3w9",
    "iso:country":"CA",
    "sg:city":"Oakville",
    "sg:classifiers":[
        {
            "category":"Real Estate",
            "subcategory":"Real Estate Agent",
            "type":"Services"
        }
    ],
    "sg:phone":"+1 905 849 9987",
    "sg:postcode":"L6K 3W9",
    "sg:province":"ON",
    "sg:tags":[
        "desk",
        "space"
    ],
    "wof:name":"Baldwin Business Ctr",
    "wof:placetype":"venue"
},
  "geometry": {"coordinates":[-79.6964645386,43.4375495911],"type":"Point"}
}