{
  "type": "Feature",
  "properties": {
    "addr:full":"600 Boul Jacques-Bizard L'Ile-Bizard QC H9C 2H2",
    "addr:housenumber":"600",
    "addr:postcode":"h9c 2h2",
    "addr:street":"Boul Jacques-Bizard",
    "iso:country":"CA",
    "sg:address":"600 Boul Jacques-Bizard",
    "sg:city":"L'Ile-Bizard",
    "sg:classifiers":[
        {
            "category":"Cinema",
            "subcategory":"Movie Rental",
            "type":"Entertainment"
        }
    ],
    "sg:phone":"+1 514 626 8843",
    "sg:postcode":"H9C 2H2",
    "sg:province":"QC",
    "sg:tags":[
        "leasing",
        "video",
        "tape",
        "equipment"
    ],
    "wof:name":"Superclub Videotron Ltee",
    "wof:placetype":"venue"
},
  "geometry": {"coordinates":[-73.876442,45.494671],"type":"Point"}
}