{
  "type": "Feature",
  "properties": {
    "addr:full":"5125 Victoria Dr Vancouver BC V5P 3V1",
    "addr:housenumber":"5125",
    "addr:postcode":"v5p 3v1",
    "addr:street":"Victoria Dr",
    "iso:country":"CA",
    "sg:address":"5125 Victoria Dr",
    "sg:city":"Vancouver",
    "sg:classifiers":[
        {
            "category":"Wholesale",
            "subcategory":"Groceries",
            "type":"Manufacturing & Wholesale Goods"
        }
    ],
    "sg:phone":"+1 604 327 0295",
    "sg:postcode":"V5P 3V1",
    "sg:province":"BC",
    "sg:tags":[
        "grocer"
    ],
    "wof:name":"Ambika Enterprises Ltd",
    "wof:placetype":"venue"
},
  "geometry": {"coordinates":[-123.06540699999999,49.238228],"type":"Point"}
}