{
  "type": "Feature",
  "properties": {
    "addr:full":"323 Richmond St E # 2000 Toronto ON M5A 4R3",
    "addr:housenumber":"323",
    "addr:postcode":"m5a 4r3",
    "addr:street":"Richmond St E # 2000",
    "iso:country":"CA",
    "sg:address":"323 Richmond St E # 2000",
    "sg:city":"Toronto",
    "sg:classifiers":[
        {
            "category":"Food & Beverages",
            "subcategory":"Bakery",
            "type":"Retail Goods"
        }
    ],
    "sg:phone":"+1 416 703 0340",
    "sg:postcode":"M5A 4R3",
    "sg:province":"ON",
    "sg:tags":[
        "tea",
        "coffee",
        "doughnut"
    ],
    "wof:name":"Tim Hortons",
    "wof:placetype":"venue"
},
  "geometry": {"coordinates":[-79.368759,43.65329],"type":"Point"}
}