{
  "type": "Feature",
  "properties": {
    "iso:country":"CA",
    "sg:address":"1059 Rte 309 N",
    "sg:city":"Notre-Dame-Du-Laus",
    "sg:classifiers":[
        {
            "category":"Travel",
            "subcategory":"Campground",
            "type":"Entertainment"
        }
    ],
    "sg:phone":"+1 819 767 2889",
    "sg:postcode":"J0X 2M0",
    "sg:province":"QC",
    "sg:tags":[
        "camp",
        "fishing"
    ],
    "wof:name":"Claudette Domaine Et Real",
    "wof:placetype":"venue"
},
  "geometry": {"coordinates":[-75.664108,46.169743],"type":"Point"}
}