{
  "type": "Feature",
  "properties": {
    "addr:full":"8358 Victoria St Metcalfe ON K0A 2P0",
    "addr:housenumber":"8358",
    "addr:postcode":"k0a 2p0",
    "addr:street":"Victoria St",
    "iso:country":"CA",
    "sg:address":"8358 Victoria St",
    "sg:city":"Metcalfe",
    "sg:classifiers":[
        {
            "category":"Wholesale",
            "subcategory":"Farm Supplies",
            "type":"Manufacturing & Wholesale Goods"
        }
    ],
    "sg:phone":"+1 613 821 2797",
    "sg:postcode":"K0A 2P0",
    "sg:province":"ON",
    "sg:tags":[
        "candle",
        "beekeeper"
    ],
    "wof:name":"Benson Bee Supplies",
    "wof:placetype":"venue"
},
  "geometry": {"coordinates":[-75.465599,45.238789],"type":"Point"}
}