{
  "type": "Feature",
  "properties": {
    "addr:full":"RR 430 Viking Trail St Pauls NL A0K 4Y0",
    "addr:housenumber":"430",
    "addr:postcode":"a0k 4y0",
    "addr:street":"Viking Trail",
    "iso:country":"CA",
    "sg:address":"RR 430 Viking Trail",
    "sg:city":"St Pauls",
    "sg:classifiers":[
        {
            "category":"Restaurant",
            "type":"Food & Drink"
        }
    ],
    "sg:phone":"+1 709 243 2250",
    "sg:postcode":"A0K 4Y0",
    "sg:province":"NL",
    "wof:name":"Gros Morne Restaurant",
    "wof:placetype":"venue"
},
  "geometry": {"coordinates":[-57.8067779541,49.852230072],"type":"Point"}
}