{
  "type": "Feature",
  "properties": {
    "iso:country":"CA",
    "sg:city":"Markdale",
    "sg:classifiers":[
        {
            "category":"Personal",
            "subcategory":"Tattoo Parlor",
            "type":"Services"
        }
    ],
    "sg:phone":"+1 519 986 1494",
    "sg:postcode":"N0C 1H0",
    "sg:province":"ON",
    "sg:tags":[
        "tattooing"
    ],
    "wof:name":"Expressions in Ink",
    "wof:placetype":"venue"
},
  "geometry": {"coordinates":[-80.6475601196,44.3185081482],"type":"Point"}
}