{
  "type": "Feature",
  "properties": {
    "addr:full":"1321 Rte Marie-Victorin Saint-Nicolas QC G7A 4G4",
    "addr:housenumber":"1321",
    "addr:postcode":"g7a 4g4",
    "addr:street":"Rte Marie-Victorin",
    "iso:country":"CA",
    "sg:address":"1321 Rte Marie-Victorin",
    "sg:city":"Saint-Nicolas",
    "sg:classifiers":[
        {
            "category":"Shopping",
            "subcategory":"Stationery & Office Supplies",
            "type":"Retail Goods"
        }
    ],
    "sg:phone":"+1 418 831 3811",
    "sg:postcode":"G7A 4G4",
    "sg:province":"QC",
    "sg:tags":[
        "instrument",
        "surveying"
    ],
    "wof:name":"J P Morasse Inc",
    "wof:placetype":"venue"
},
  "geometry": {"coordinates":[-71.390907,46.701828],"type":"Point"}
}