{
  "type": "Feature",
  "properties": {
    "addr:full":"1123 Newmarket St Ottawa ON K1B 4N4",
    "addr:housenumber":"1123",
    "addr:postcode":"k1b 4n4",
    "addr:street":"Newmarket St",
    "iso:country":"CA",
    "sg:address":"1123 Newmarket St",
    "sg:city":"Ottawa",
    "sg:classifiers":[
        {
            "category":"Wholesale",
            "subcategory":"Furniture",
            "type":"Manufacturing & Wholesale Goods"
        }
    ],
    "sg:phone":"+1 613 731 4433",
    "sg:postcode":"K1B 4N4",
    "sg:province":"ON",
    "wof:name":"Corporate Furniture Group",
    "wof:placetype":"venue"
},
  "geometry": {"coordinates":[-75.62413787840001,45.4094467163],"type":"Point"}
}