{
  "type": "Feature",
  "properties": {
    "addr:full":"980 Alder St Campbell River BC V9W 2P9",
    "addr:housenumber":"980",
    "addr:postcode":"v9w 2p9",
    "addr:street":"Alder St",
    "iso:country":"CA",
    "sg:address":"980 Alder St",
    "sg:city":"Campbell River",
    "sg:classifiers":[
        {
            "category":"Professional",
            "subcategory":"Accounting & Tax Preparation",
            "type":"Services"
        }
    ],
    "sg:phone":"+1 250 286 0744",
    "sg:postcode":"V9W 2P9",
    "sg:province":"BC",
    "sg:tags":[
        "accountant"
    ],
    "wof:name":"Chan Nowosad & Boates",
    "wof:placetype":"venue"
},
  "geometry": {"coordinates":[-125.244484,50.02504],"type":"Point"}
}