{
  "type": "Feature",
  "properties": {
    "addr:full":"Centennial Rd Lumsden NL A0G 3E0",
    "addr:postcode":"a0g 3e0",
    "addr:street":"Centennial Rd",
    "iso:country":"CA",
    "sg:address":"Centennial Rd",
    "sg:city":"Lumsden",
    "sg:classifiers":[
        {
            "category":"Restaurant",
            "type":"Food & Drink"
        }
    ],
    "sg:phone":"+1 709 530 2304",
    "sg:postcode":"A0G 3E0",
    "sg:province":"NL",
    "wof:name":"Chester Fried",
    "wof:placetype":"venue"
},
  "geometry": {"coordinates":[-53.603638,49.296249],"type":"Point"}
}