{
  "type": "Feature",
  "properties": {
    "addr:full":"Lanoraie QC J0K 1E0",
    "addr:postcode":"j0k 1e0",
    "iso:country":"CA",
    "sg:city":"Lanoraie",
    "sg:classifiers":[
        {
            "category":"Bars & Pubs",
            "type":"Food & Drink"
        }
    ],
    "sg:phone":"+1 450 887 0869",
    "sg:postcode":"J0K 1E0",
    "sg:province":"QC",
    "sg:tags":[
        "lounge",
        "cocktail"
    ],
    "wof:name":"Bar Chez Pasteur",
    "wof:placetype":"venue"
},
  "geometry": {"coordinates":[-73.22633399999999,45.959419],"type":"Point"}
}