{
  "type": "Feature",
  "properties": {
    "iso:country":"CA",
    "sg:address":"23 River Ridge Rd",
    "sg:city":"Barrie",
    "sg:classifiers":[
        {
            "category":"Building & Trades",
            "subcategory":"Construction",
            "type":"Services"
        }
    ],
    "sg:phone":"+1 705 739 0048",
    "sg:postcode":"L4N 7G1",
    "sg:province":"ON",
    "sg:tags":[
        "contractor",
        "general"
    ],
    "wof:name":"Ant Construction Inc",
    "wof:placetype":"venue"
},
  "geometry": {"coordinates":[-79.640785,44.362858],"type":"Point"}
}