{
  "type": "Feature",
  "properties": {
    "addr:full":"10806 Gold Creek Dr Komoka ON N0L 1R0",
    "addr:housenumber":"10806",
    "addr:postcode":"n0l 1r0",
    "addr:street":"Gold Creek Dr",
    "iso:country":"CA",
    "sg:address":"10806 Gold Creek Dr",
    "sg:city":"Komoka",
    "sg:classifiers":[
        {
            "category":"Building & Trades",
            "subcategory":"Construction",
            "type":"Services"
        }
    ],
    "sg:phone":"+1 519 666 1017",
    "sg:postcode":"N0L 1R0",
    "sg:province":"ON",
    "sg:tags":[
        "resurfacing",
        "floor",
        "laying",
        "refinishing",
        "woodworker"
    ],
    "wof:name":"Katt Woodworking",
    "wof:placetype":"venue"
},
  "geometry": {"coordinates":[-81.4303741455,42.9983291626],"type":"Point"}
}