{
  "type": "Feature",
  "properties": {
    "addr:full":"Cape Dorset NU X0A 0C0",
    "addr:postcode":"x0a 0c0",
    "iso:country":"CA",
    "sg:city":"Cape Dorset",
    "sg:classifiers":[
        {
            "category":"Government",
            "subcategory":"Office",
            "type":"Public Place"
        }
    ],
    "sg:phone":"+1 867 897 8231",
    "sg:postcode":"X0A 0C0",
    "sg:province":"NU",
    "wof:name":"Nwt Justice",
    "wof:placetype":"venue"
},
  "geometry": {"coordinates":[-76.54080963129999,64.2313461304],"type":"Point"}
}