{
  "type": "Feature",
  "properties": {
    "addr:full":"2080 Kelland Rd Black Creek BC V9J 1G4",
    "addr:housenumber":"2080",
    "addr:postcode":"v9j 1g4",
    "addr:street":"Kelland Rd",
    "iso:country":"CA",
    "sg:address":"2080 Kelland Rd",
    "sg:city":"Black Creek",
    "sg:classifiers":[
        {
            "category":"Manufacturing",
            "subcategory":"Lumber",
            "type":"Manufacturing & Wholesale Goods"
        }
    ],
    "sg:phone":"+1 250 337 8408",
    "sg:postcode":"V9J 1G4",
    "sg:province":"BC",
    "sg:tags":[
        "company",
        "logging"
    ],
    "wof:name":"Chase Timber Contracting",
    "wof:placetype":"venue"
},
  "geometry": {"coordinates":[-125.135002136,49.843006134],"type":"Point"}
}