{
  "type": "Feature",
  "properties": {
    "addr:full":"Cascade Grand Forks BC V0H 1H0",
    "addr:postcode":"v0h 1h0",
    "iso:country":"CA",
    "sg:address":"Cascade",
    "sg:city":"Grand Forks",
    "sg:classifiers":[
        {
            "category":"Government",
            "subcategory":"Office",
            "type":"Public Place"
        }
    ],
    "sg:phone":"+1 250 447 9418",
    "sg:postcode":"V0H 1H0",
    "sg:province":"BC",
    "wof:name":"Canada Customs",
    "wof:placetype":"venue"
},
  "geometry": {"coordinates":[-118.44326,49.032372],"type":"Point"}
}