{
  "type": "Feature",
  "properties": {
    "addr:full":"1417 Waynco Rd Cambridge ON N1R 6C9",
    "addr:housenumber":"1417",
    "addr:postcode":"n1r 6c9",
    "addr:street":"Waynco Rd",
    "iso:country":"CA",
    "sg:address":"1417 Waynco Rd",
    "sg:city":"Cambridge",
    "sg:classifiers":[
        {
            "category":"Wholesale",
            "subcategory":"Construction Materials",
            "type":"Manufacturing & Wholesale Goods"
        }
    ],
    "sg:phone":"+1 519 623 0240",
    "sg:postcode":"N1R 6C9",
    "sg:province":"ON",
    "sg:tags":[
        "sand",
        "gravel"
    ],
    "wof:name":"Waynco Limited",
    "wof:placetype":"venue"
},
  "geometry": {"coordinates":[-80.3153305054,43.3614082336],"type":"Point"}
}