{
  "type": "Feature",
  "properties": {
    "addr:full":"650 Ch Des Ruisseaux Saint-Honore-DE-Chicoutimi QC G0V 1L0",
    "addr:housenumber":"650",
    "addr:postcode":"g0v 1l0",
    "addr:street":"Ch Des Ruisseaux Saint-Honore-De-Chicoutimi",
    "iso:country":"CA",
    "sg:address":"650 Ch Des Ruisseaux",
    "sg:city":"Saint-Honore-DE-Chicoutimi",
    "sg:classifiers":[
        {
            "category":"Shopping",
            "subcategory":"Clothing, Apparel, & Fashions",
            "type":"Retail Goods"
        }
    ],
    "sg:phone":"+1 418 673 7353",
    "sg:postcode":"G0V 1L0",
    "sg:province":"QC",
    "sg:tags":[
        "dressmaker",
        "bathing",
        "suit",
        "accessory"
    ],
    "wof:name":"Confection Fado",
    "wof:placetype":"venue"
},
  "geometry": {"coordinates":[-71.06139400000001,48.428944],"type":"Point"}
}