{
  "type": "Feature",
  "properties": {
    "addr:full":"275 Campion St Kelowna BC V1X 7S9",
    "addr:housenumber":"275",
    "addr:postcode":"v1x 7s9",
    "addr:street":"Campion St",
    "iso:country":"CA",
    "sg:address":"275 Campion St",
    "sg:city":"Kelowna",
    "sg:classifiers":[
        {
            "category":"Mining & Drilling",
            "type":"Manufacturing & Wholesale Goods"
        }
    ],
    "sg:phone":"+1 250 491 0427",
    "sg:postcode":"V1X 7S9",
    "sg:province":"BC",
    "sg:tags":[
        "company",
        "oil"
    ],
    "wof:name":"Spring Fuel Distributors",
    "wof:placetype":"venue"
},
  "geometry": {"coordinates":[-119.402428,49.915657],"type":"Point"}
}