{
  "type": "Feature",
  "properties": {
    "addr:full":"200 Place Du 21-Mars Nicolet QC J3T 1E9",
    "addr:housenumber":"200",
    "addr:postcode":"j3t 1e9",
    "addr:street":"Place Du 21-Mars",
    "iso:country":"CA",
    "sg:address":"200 Place Du 21-Mars",
    "sg:city":"Nicolet",
    "sg:classifiers":[
        {
            "category":"Shopping",
            "subcategory":"Department Store",
            "type":"Retail Goods"
        }
    ],
    "sg:phone":"+1 819 293 8440",
    "sg:postcode":"J3T 1E9",
    "sg:province":"QC",
    "wof:name":"Korvette Limitee",
    "wof:placetype":"venue"
},
  "geometry": {"coordinates":[-72.61756099999999,46.225418],"type":"Point"}
}