{
  "type": "Feature",
  "properties": {
    "addr:full":"Langley BC V1M 3J9",
    "addr:postcode":"v1m 3j9",
    "iso:country":"CA",
    "sg:city":"Langley",
    "sg:classifiers":[
        {
            "category":"Home & Garden",
            "subcategory":"Building Materials",
            "type":"Retail Goods"
        }
    ],
    "sg:phone":"+1 604 882 2590",
    "sg:postcode":"V1M 3J9",
    "sg:province":"BC",
    "sg:tags":[
        "insulation",
        "heat"
    ],
    "wof:name":"Austin Icf",
    "wof:placetype":"venue"
},
  "geometry": {"coordinates":[-122.674133301,49.1731910706],"type":"Point"}
}