{
  "type": "Feature",
  "properties": {
    "addr:full":"74 Ewen Dr Uxbridge ON L9P 1L5",
    "addr:housenumber":"74",
    "addr:postcode":"l9p 1l5",
    "addr:street":"Ewen Dr",
    "iso:country":"CA",
    "sg:address":"74 Ewen Dr",
    "sg:city":"Uxbridge",
    "sg:classifiers":[
        {
            "category":"Building & Trades",
            "subcategory":"Plumbing",
            "type":"Services"
        }
    ],
    "sg:phone":"+1 905 852 7157",
    "sg:postcode":"L9P 1L5",
    "sg:province":"ON",
    "sg:tags":[
        "heating",
        "contractor"
    ],
    "wof:name":"Uxbridge Heating & Cooling Ltd",
    "wof:placetype":"venue"
},
  "geometry": {"coordinates":[-79.110855,44.101814],"type":"Point"}
}