{
  "type": "Feature",
  "properties": {
    "addr:full":"1031 Teron Rd Kanata ON K2K 1R2",
    "addr:housenumber":"1031",
    "addr:postcode":"k2k 1r2",
    "addr:street":"Teron Rd",
    "iso:country":"CA",
    "sg:address":"1031 Teron Rd",
    "sg:city":"Kanata",
    "sg:classifiers":[
        {
            "category":"Food & Beverages",
            "subcategory":"Groceries & Convenience Stores",
            "type":"Retail Goods"
        }
    ],
    "sg:phone":"+1 613 592 4000",
    "sg:postcode":"K2K 1R2",
    "sg:province":"ON",
    "wof:name":"Mac's Convenience Stores Ltd",
    "wof:placetype":"venue"
},
  "geometry": {"coordinates":[-75.9010848999,45.3306846619],"type":"Point"}
}