{
  "type": "Feature",
  "properties": {
    "addr:full":"15 William Kitchen Rd Scarborough ON M1P 5B7",
    "addr:housenumber":"15",
    "addr:postcode":"m1p 5b7",
    "addr:street":"William Kitchen Rd",
    "iso:country":"CA",
    "sg:address":"15 William Kitchen Rd",
    "sg:city":"Scarborough",
    "sg:classifiers":[
        {
            "category":"Restaurant",
            "type":"Food & Drink"
        }
    ],
    "sg:phone":"+1 416 335 9600",
    "sg:postcode":"M1P 5B7",
    "sg:province":"ON",
    "wof:name":"Mr Greek Mediterranean",
    "wof:placetype":"venue"
},
  "geometry": {"coordinates":[-79.278938,43.771362],"type":"Point"}
}