{
  "type": "Feature",
  "properties": {
    "addr:full":"109 Sheppard Ave W North York ON M2N 1M7",
    "addr:housenumber":"109",
    "addr:postcode":"m2n 1m7",
    "addr:street":"Sheppard Ave W",
    "iso:country":"CA",
    "sg:address":"109 Sheppard Ave W",
    "sg:city":"North York",
    "sg:classifiers":[
        {
            "category":"Health Services",
            "subcategory":"Doctor",
            "type":"Services"
        }
    ],
    "sg:phone":"+1 416 226 3363",
    "sg:postcode":"M2N 1M7",
    "sg:province":"ON",
    "sg:tags":[
        "dentist"
    ],
    "wof:name":"Oral & Maxillofacial Assoc",
    "wof:placetype":"venue"
},
  "geometry": {"coordinates":[-79.41649627690001,43.7601699829],"type":"Point"}
}