{
  "type": "Feature",
  "properties": {
    "iso:country":"CA",
    "sg:address":"4284 Main St",
    "sg:city":"West St Paul",
    "sg:classifiers":[
        {
            "category":"Shopping",
            "type":"Retail Goods"
        }
    ],
    "sg:phone":"+1 204 339 6523",
    "sg:postcode":"R4A 2A7",
    "sg:province":"MB",
    "sg:tags":[
        "monument"
    ],
    "wof:name":"Westwood Memorials",
    "wof:placetype":"venue"
},
  "geometry": {"coordinates":[-97.05423,50.002899],"type":"Point"}
}