{
  "type": "Feature",
  "properties": {
    "addr:full":"Calgary AB T2P 0G7",
    "addr:postcode":"t2p 0g7",
    "iso:country":"CA",
    "sg:city":"Calgary",
    "sg:classifiers":[
        {
            "category":"Restaurant",
            "type":"Food & Drink"
        }
    ],
    "sg:phone":"+1 403 261 4646",
    "sg:postcode":"T2P 0G7",
    "sg:province":"AB",
    "wof:name":"Buchanan's Restaurant",
    "wof:placetype":"venue"
},
  "geometry": {"coordinates":[-114.07695770300001,51.0507659912],"type":"Point"}
}