{
  "type": "Feature",
  "properties": {
    "addr:full":"North Battleford SK S9A 1E9",
    "addr:postcode":"s9a 1e9",
    "iso:country":"CA",
    "sg:city":"North Battleford",
    "sg:classifiers":[
        {
            "category":"Shopping",
            "type":"Retail Goods"
        }
    ],
    "sg:phone":"+1 306 446 6415",
    "sg:postcode":"S9A 1E9",
    "sg:province":"SK",
    "sg:tags":[
        "hearing",
        "equipment",
        "supply",
        "impaired"
    ],
    "wof:name":"Hearing Aid Plan",
    "wof:placetype":"venue"
},
  "geometry": {"coordinates":[-108.295845,52.774136],"type":"Point"}
}