{
  "type": "Feature",
  "properties": {
    "addr:full":"1199 Lynn Valley Rd # 11B North Vancouver BC V7J 3H2",
    "addr:housenumber":"1199;11b",
    "addr:postcode":"v7j 3h2",
    "addr:street":"Lynn Valley Rd #",
    "iso:country":"CA",
    "sg:address":"1199 Lynn Valley Rd # 11B",
    "sg:city":"North Vancouver",
    "sg:classifiers":[
        {
            "category":"Retail",
            "subcategory":"Laundry & Dry Cleaning",
            "type":"Services"
        }
    ],
    "sg:phone":"+1 604 984 6458",
    "sg:postcode":"V7J 3H2",
    "sg:province":"BC",
    "sg:tags":[
        "cleaners"
    ],
    "wof:name":"Courtesy Cleaners",
    "wof:placetype":"venue"
},
  "geometry": {"coordinates":[-123.040817,49.335442],"type":"Point"}
}