{
  "type": "Feature",
  "properties": {
    "addr:full":"29015 Sharrow Rd Thamesville ON N0P 2K0",
    "addr:housenumber":"29015",
    "addr:postcode":"n0p 2k0",
    "addr:street":"Sharrow Rd",
    "iso:country":"CA",
    "sg:address":"29015 Sharrow Rd",
    "sg:city":"Thamesville",
    "sg:classifiers":[
        {
            "category":"Organizations",
            "subcategory":"Religious Organization",
            "type":"Services"
        }
    ],
    "sg:phone":"+1 519 692 5696",
    "sg:postcode":"N0P 2K0",
    "sg:province":"ON",
    "wof:name":"Community of Christ",
    "wof:placetype":"venue"
},
  "geometry": {"coordinates":[-81.97650146479999,42.5518531799],"type":"Point"}
}