{
  "type": "Feature",
  "properties": {
    "iso:country":"CA",
    "sg:address":"190 Rue Dube",
    "sg:city":"Courcelette",
    "sg:classifiers":[
        {
            "category":"Shopping",
            "subcategory":"Pharmacy",
            "type":"Retail Goods"
        }
    ],
    "sg:phone":"+1 418 844 3608",
    "sg:postcode":"G0A 1R1",
    "sg:province":"QC",
    "wof:name":"Pharmacie Lyne Lefebvre",
    "wof:placetype":"venue"
},
  "geometry": {"coordinates":[-71.5079421997,46.8875198364],"type":"Point"}
}