{
  "type": "Feature",
  "properties": {
    "iso:country":"CA",
    "sg:address":"742 Third Line E",
    "sg:city":"Sault Ste Marie",
    "sg:classifiers":[
        {
            "category":"Organizations",
            "subcategory":"Religious Organization",
            "type":"Services"
        }
    ],
    "sg:phone":"+1 705 945 8911",
    "sg:postcode":"P6A 6J8",
    "sg:province":"ON",
    "sg:tags":[
        "church"
    ],
    "wof:name":"Kingdom Hall Jehovah's Witness",
    "wof:placetype":"venue"
},
  "geometry": {"coordinates":[-84.3118362427,46.5532836914],"type":"Point"}
}