{
  "type": "Feature",
  "properties": {
    "iso:country":"CA",
    "sg:address":"1200 Rue Neveu",
    "sg:city":"Saint-Cesaire",
    "sg:classifiers":[
        {
            "category":"Wholesale",
            "subcategory":"Durable Goods & Equipment",
            "type":"Manufacturing & Wholesale Goods"
        }
    ],
    "sg:phone":"+1 450 469 1629",
    "sg:postcode":"J0L 1T0",
    "sg:province":"QC",
    "sg:tags":[
        "exporter"
    ],
    "wof:name":"Impex Monteregie Inc",
    "wof:placetype":"venue"
},
  "geometry": {"coordinates":[-73.01676177980001,45.41223526],"type":"Point"}
}