{
  "type": "Feature",
  "properties": {
    "iso:country":"CA",
    "sg:address":"572 Niagara St",
    "sg:city":"Welland",
    "sg:classifiers":[
        {
            "category":"Shopping",
            "subcategory":"Shoes",
            "type":"Retail Goods"
        }
    ],
    "sg:phone":"+1 905 735 7909",
    "sg:postcode":"L3C 6T8",
    "sg:province":"ON",
    "wof:name":"Niagara Shoe Factory Outlet",
    "wof:placetype":"venue"
},
  "geometry": {"coordinates":[-79.2515869141,43.0068702698],"type":"Point"}
}