{
  "type": "Feature",
  "properties": {
    "addr:full":"99 Rue Chabanel O Montreal QC H2N 1C3",
    "addr:housenumber":"99",
    "addr:postcode":"h2n 1c3",
    "addr:street":"Rue Chabanel O",
    "iso:country":"CA",
    "sg:address":"99 Rue Chabanel O",
    "sg:city":"Montreal",
    "sg:classifiers":[
        {
            "category":"Shopping",
            "subcategory":"Clothing, Apparel, & Fashions",
            "type":"Retail Goods"
        }
    ],
    "sg:phone":"+1 514 858 7131",
    "sg:postcode":"H2N 1C3",
    "sg:province":"QC",
    "sg:tags":[
        "infant",
        "wear"
    ],
    "wof:name":"Flare Leggings",
    "wof:placetype":"venue"
},
  "geometry": {"coordinates":[-73.65074157710001,45.5452651978],"type":"Point"}
}