{
  "type": "Feature",
  "properties": {
    "addr:full":"685 Topsail Rd St. John's NL A1E 2E3",
    "addr:housenumber":"685",
    "addr:postcode":"a1e 2e3",
    "addr:street":"Topsail Rd",
    "iso:country":"CA",
    "sg:address":"685 Topsail Rd",
    "sg:city":"St. John's",
    "sg:classifiers":[
        {
            "category":"Retail",
            "subcategory":"Car Wash",
            "type":"Services"
        }
    ],
    "sg:phone":"+1 709 368 0804",
    "sg:postcode":"A1E 2E3",
    "sg:province":"NL",
    "sg:tags":[
        "polishing",
        "washing"
    ],
    "wof:name":"Perma-Shine",
    "wof:placetype":"venue"
},
  "geometry": {"coordinates":[-52.7763519287,47.5231437683],"type":"Point"}
}