{
  "type": "Feature",
  "properties": {
    "addr:full":"Winnipeg MB R2H 0E4",
    "addr:postcode":"r2h 0e4",
    "iso:country":"CA",
    "sg:city":"Winnipeg",
    "sg:classifiers":[
        {
            "category":"Shopping",
            "subcategory":"Gifts & Souvenirs",
            "type":"Retail Goods"
        }
    ],
    "sg:phone":"+1 204 231 1701",
    "sg:postcode":"R2H 0E4",
    "sg:province":"MB",
    "sg:tags":[
        "party",
        "designer",
        "display",
        "producer",
        "supply"
    ],
    "wof:name":"Creating A Scene",
    "wof:placetype":"venue"
},
  "geometry": {"coordinates":[-97.122169,49.893299],"type":"Point"}
}