{
  "type": "Feature",
  "properties": {
    "iso:country":"CA",
    "sg:address":"2022 Ch Des Patriotes",
    "sg:city":"Saint-Ours",
    "sg:classifiers":[
        {
            "category":"Building & Trades",
            "subcategory":"Plumbing",
            "type":"Services"
        }
    ],
    "sg:phone":"+1 450 785 2232",
    "sg:postcode":"J0G 1P0",
    "sg:province":"QC",
    "sg:tags":[
        "contractor"
    ],
    "wof:name":"Plomberie Denis Descheneaux",
    "wof:placetype":"venue"
},
  "geometry": {"coordinates":[-73.1478271484,45.9316482544],"type":"Point"}
}