{
  "type": "Feature",
  "properties": {
    "iso:country":"CA",
    "sg:address":"2213 Ninth Line",
    "sg:city":"Oakville",
    "sg:classifiers":[
        {
            "category":"Building & Trades",
            "subcategory":"Construction",
            "type":"Services"
        }
    ],
    "sg:phone":"+1 905 338 6363",
    "sg:postcode":"L6H 7G7",
    "sg:province":"ON",
    "sg:tags":[
        "excavating",
        "paving",
        "contractor"
    ],
    "wof:name":"Oakville Paving",
    "wof:placetype":"venue"
},
  "geometry": {"coordinates":[-79.6842880249,43.4988555908],"type":"Point"}
}