{
  "type": "Feature",
  "properties": {
    "addr:full":"2070 Boul Du Cure-Labelle Saint-Jerome QC J7Y 1S4",
    "addr:housenumber":"2070",
    "addr:postcode":"j7y 1s4",
    "addr:street":"Boul Du Cure-Labelle Saint-Jerome",
    "iso:country":"CA",
    "sg:address":"2070 Boul Du Cure-Labelle",
    "sg:city":"Saint-Jerome",
    "sg:classifiers":[
        {
            "category":"Restaurant",
            "type":"Food & Drink"
        }
    ],
    "sg:phone":"+1 450 431 1155",
    "sg:postcode":"J7Y 1S4",
    "sg:province":"QC",
    "sg:tags":[
        "parlor",
        "ice",
        "cream"
    ],
    "wof:name":"Bar Laitier Mr Freezy Enr",
    "wof:placetype":"venue"
},
  "geometry": {"coordinates":[-74.010338,45.797691],"type":"Point"}
}