{
  "type": "Feature",
  "properties": {
    "addr:full":"8312 Boul Provencher Saint-Leonard QC H1R 2Z1",
    "addr:housenumber":"8312",
    "addr:postcode":"h1r 2z1",
    "addr:street":"Boul Provencher",
    "iso:country":"CA",
    "sg:address":"8312 Boul Provencher",
    "sg:city":"Saint-Leonard",
    "sg:classifiers":[
        {
            "category":"Building & Trades",
            "subcategory":"Construction",
            "type":"Services"
        }
    ],
    "sg:phone":"+1 514 729 0910",
    "sg:postcode":"H1R 2Z1",
    "sg:province":"QC",
    "sg:tags":[
        "repairing",
        "remodeling",
        "contractor"
    ],
    "wof:name":"Gianni Renovation",
    "wof:placetype":"venue"
},
  "geometry": {"coordinates":[-73.60428619379999,45.5763320923],"type":"Point"}
}