{
  "type": "Feature",
  "properties": {
    "addr:full":"12701 King George Hwy Surrey BC V3V 3K7",
    "addr:housenumber":"12701",
    "addr:postcode":"v3v 3k7",
    "addr:street":"King George Hwy",
    "iso:country":"CA",
    "sg:address":"12701 King George Hwy",
    "sg:city":"Surrey",
    "sg:classifiers":[
        {
            "category":"Autos & Motor Vehicles",
            "subcategory":"Automobile Sales",
            "type":"Retail Goods"
        }
    ],
    "sg:phone":"+1 604 634 1020",
    "sg:postcode":"V3V 3K7",
    "sg:province":"BC",
    "sg:tags":[
        "car",
        "dealer"
    ],
    "wof:name":"Saman Auto Sales Ltd",
    "wof:placetype":"venue"
},
  "geometry": {"coordinates":[-122.869827,49.206474],"type":"Point"}
}