{
  "type": "Feature",
  "properties": {
    "addr:full":"4960 Boul Des Grandes-Prairies Saint-Leonard QC H1R 1A1",
    "addr:housenumber":"4960",
    "addr:postcode":"h1r 1a1",
    "addr:street":"Boul Des Grandes-Prairies",
    "iso:country":"CA",
    "sg:address":"4960 Boul Des Grandes-Prairies",
    "sg:city":"Saint-Leonard",
    "sg:classifiers":[
        {
            "category":"Manufacturing",
            "subcategory":"Rubber & Plastics",
            "type":"Manufacturing & Wholesale Goods"
        }
    ],
    "sg:phone":"+1 514 326 0411",
    "sg:postcode":"H1R 1A1",
    "sg:province":"QC",
    "wof:name":"Queplex Limitee",
    "wof:placetype":"venue"
},
  "geometry": {"coordinates":[-73.61897277830001,45.5889854431],"type":"Point"}
}