{
  "type": "Feature",
  "properties": {
    "iso:country":"CA",
    "sg:address":"342 Bloor St W",
    "sg:city":"Toronto",
    "sg:classifiers":[
        {
            "category":"Retail",
            "subcategory":"Repair Shop",
            "type":"Services"
        }
    ],
    "sg:phone":"+1 416 925 9441",
    "sg:postcode":"M5S 1W9",
    "sg:province":"ON",
    "sg:tags":[
        "jewelry"
    ],
    "wof:name":"Simman's Credit Jewlrs",
    "wof:placetype":"venue"
},
  "geometry": {"coordinates":[-79.4042510986,43.6666908264],"type":"Point"}
}