{
  "type": "Feature",
  "properties": {
    "addr:full":"6413 Rue Des Erables Saint-Emile QC G3E 1L2",
    "addr:housenumber":"6413",
    "addr:postcode":"g3e 1l2",
    "addr:street":"Rue Des Erables Saint-Emile",
    "iso:country":"CA",
    "sg:address":"6413 Rue Des Erables",
    "sg:city":"Saint-Emile",
    "sg:classifiers":[
        {
            "category":"Professional",
            "subcategory":"Business Services",
            "type":"Services"
        }
    ],
    "sg:phone":"+1 418 842 2743",
    "sg:postcode":"G3E 1L2",
    "sg:province":"QC",
    "sg:tags":[
        "arbitration"
    ],
    "wof:name":"Dion Chantal",
    "wof:placetype":"venue"
},
  "geometry": {"coordinates":[-71.3221282959,46.8779296875],"type":"Point"}
}