{
  "type": "Feature",
  "properties": {
    "addr:full":"231 Douro St Stratford ON N5A 3S1",
    "addr:housenumber":"231",
    "addr:postcode":"n5a 3s1",
    "addr:street":"Douro St",
    "iso:country":"CA",
    "sg:address":"231 Douro St",
    "sg:city":"Stratford",
    "sg:classifiers":[
        {
            "category":"Food & Beverages",
            "subcategory":"Bakery",
            "type":"Retail Goods"
        }
    ],
    "sg:phone":"+1 519 271 4267",
    "sg:postcode":"N5A 3S1",
    "sg:province":"ON",
    "sg:tags":[
        "baker"
    ],
    "wof:name":"East End Variety",
    "wof:placetype":"venue"
},
  "geometry": {"coordinates":[-80.970528,43.3671],"type":"Point"}
}