{
  "type": "Feature",
  "properties": {
    "addr:full":"Wilkie SK S0K 4W0",
    "addr:postcode":"s0k 4w0",
    "addr:street":"Wilkie",
    "iso:country":"CA",
    "sg:city":"Wilkie",
    "sg:classifiers":[
        {
            "category":"Banks & Credit Unions",
            "subcategory":"Bank",
            "type":"Services"
        }
    ],
    "sg:phone":"+1 306 843 2255",
    "sg:postcode":"S0K 4W0",
    "sg:province":"SK",
    "wof:name":"Cibc",
    "wof:placetype":"venue"
},
  "geometry": {"coordinates":[-108.702110291,52.4110412598],"type":"Point"}
}