{
  "type": "Feature",
  "properties": {
    "addr:full":"Langley BC V3A 8M8",
    "addr:postcode":"v3a 8m8",
    "iso:country":"CA",
    "sg:city":"Langley",
    "sg:classifiers":[
        {
            "category":"Banks & Credit Unions",
            "subcategory":"Bank",
            "type":"Services"
        }
    ],
    "sg:phone":"+1 604 539 9424",
    "sg:postcode":"V3A 8M8",
    "sg:province":"BC",
    "sg:tags":[
        "cashing",
        "loan",
        "check"
    ],
    "wof:name":"Check Station",
    "wof:placetype":"venue"
},
  "geometry": {"coordinates":[-122.651657,49.10767],"type":"Point"}
}