{
  "type": "Feature",
  "properties": {
    "iso:country":"CA",
    "sg:address":"5467 Victoria Ave",
    "sg:city":"Niagara Falls",
    "sg:classifiers":[
        {
            "category":"Restaurant",
            "type":"Food & Drink"
        }
    ],
    "sg:phone":"+1 905 354 7225",
    "sg:postcode":"L2G 3L3",
    "sg:province":"ON",
    "wof:name":"Tony's Place",
    "wof:placetype":"venue"
},
  "geometry": {"coordinates":[-79.07294464109999,43.0951919556],"type":"Point"}
}