{
  "type": "Feature",
  "properties": {
    "addr:full":"3460 Rutland Ave Gull Lake SK S0N 1A0",
    "addr:housenumber":"3460",
    "addr:postcode":"s0n 1a0",
    "addr:street":"Rutland Ave",
    "iso:country":"CA",
    "sg:address":"3460 Rutland Ave",
    "sg:city":"Gull Lake",
    "sg:classifiers":[
        {
            "category":"Food & Beverages",
            "subcategory":"Groceries & Convenience Stores",
            "type":"Retail Goods"
        }
    ],
    "sg:phone":"+1 306 672 4111",
    "sg:postcode":"S0N 1A0",
    "sg:province":"SK",
    "sg:tags":[
        "grocer"
    ],
    "wof:name":"Peterson's Ag Foods",
    "wof:placetype":"venue"
},
  "geometry": {"coordinates":[-108.483924866,50.0979690552],"type":"Point"}
}