{
  "type": "Feature",
  "properties": {
    "iso:country":"CA",
    "sg:address":"55 5E Av",
    "sg:city":"Lasalle",
    "sg:classifiers":[
        {
            "category":"Education",
            "subcategory":"School",
            "type":"Public Place"
        }
    ],
    "sg:phone":"+1 514 595 2040",
    "sg:postcode":"H8P 2K1",
    "sg:province":"QC",
    "wof:name":"Allion Ecole",
    "wof:placetype":"venue"
},
  "geometry": {"coordinates":[-73.662819,45.428658],"type":"Point"}
}