{
  "type": "Feature",
  "properties": {
    "iso:country":"CA",
    "sg:address":"9200 Weston Rd",
    "sg:city":"Woodbridge",
    "sg:classifiers":[
        {
            "category":"Cinema",
            "subcategory":"Movie Rental",
            "type":"Entertainment"
        }
    ],
    "sg:phone":"+1 905 417 9325",
    "sg:postcode":"L4H 2P8",
    "sg:province":"ON",
    "sg:tags":[
        "leasing",
        "video",
        "disc",
        "tape"
    ],
    "wof:name":"Rogers Video",
    "wof:placetype":"venue"
},
  "geometry": {"coordinates":[-79.556465,43.826328],"type":"Point"}
}