{
  "type": "Feature",
  "properties": {
    "iso:country":"CA",
    "sg:address":"19 Secord Dr",
    "sg:city":"St Catharines",
    "sg:classifiers":[
        {
            "category":"Building & Trades",
            "subcategory":"Construction",
            "type":"Services"
        }
    ],
    "sg:phone":"+1 905 646 1701",
    "sg:postcode":"L2N 1K9",
    "sg:province":"ON",
    "sg:tags":[
        "dry wall",
        "contractor"
    ],
    "wof:name":"R G Drywall Inc",
    "wof:placetype":"venue"
},
  "geometry": {"coordinates":[-79.24816894529999,43.1833496094],"type":"Point"}
}