{
  "type": "Feature",
  "properties": {
    "addr:full":"Saint-Tite QC G0X 3H0",
    "addr:postcode":"g0x 3h0",
    "iso:country":"CA",
    "sg:city":"Saint-Tite",
    "sg:classifiers":[
        {
            "category":"Professional",
            "subcategory":"Business Services",
            "type":"Services"
        }
    ],
    "sg:phone":"+1 418 365 3669",
    "sg:postcode":"G0X 3H0",
    "sg:province":"QC",
    "sg:tags":[
        "youth",
        "organization",
        "referral",
        "center",
        "information"
    ],
    "wof:name":"Maison Des Jeunes Le Refuge",
    "wof:placetype":"venue"
},
  "geometry": {"coordinates":[-72.56532300000001,46.727436],"type":"Point"}
}