{
  "type": "Feature",
  "properties": {
    "addr:full":"740 Boul DE LA Cote-Vertu # 118 Saint-Laurent QC H4L 5C8",
    "addr:housenumber":"740",
    "addr:postcode":"h4l 5c8",
    "addr:street":"Boul De La Cote-Vertu # 118 Saint-Laurent",
    "iso:country":"CA",
    "sg:address":"740 Boul DE LA Cote-Vertu # 118",
    "sg:city":"Saint-Laurent",
    "sg:classifiers":[
        {
            "category":"Travel",
            "subcategory":"Travel Agent",
            "type":"Entertainment"
        }
    ],
    "sg:phone":"+1 514 744 8030",
    "sg:postcode":"H4L 5C8",
    "sg:province":"QC",
    "sg:tags":[
        "agency",
        "bureau"
    ],
    "wof:name":"Voyages Air & Port 2000 Inc",
    "wof:placetype":"venue"
},
  "geometry": {"coordinates":[-73.6745376587,45.5202407837],"type":"Point"}
}