{
  "type": "Feature",
  "properties": {
    "addr:full":"766 6E Av Grand-Mere QC G9T 2H7",
    "addr:housenumber":"766",
    "addr:postcode":"g9t 2h7",
    "addr:street":"6E Av Grand-Mere",
    "iso:country":"CA",
    "sg:address":"766 6E Av",
    "sg:city":"Grand-Mere",
    "sg:classifiers":[
        {
            "category":"Bars & Pubs",
            "type":"Food & Drink"
        }
    ],
    "sg:phone":"+1 819 533 3745",
    "sg:postcode":"G9T 2H7",
    "sg:province":"QC",
    "sg:tags":[
        "lounge",
        "cocktail"
    ],
    "wof:name":"Bess Bar",
    "wof:placetype":"venue"
},
  "geometry": {"coordinates":[-72.694328,46.613354],"type":"Point"}
}