{
  "type": "Feature",
  "properties": {
    "iso:country":"CA",
    "sg:address":"395 Boul Samson",
    "sg:city":"Laval",
    "sg:classifiers":[
        {
            "category":"Local Transit",
            "type":"Transportation"
        }
    ],
    "sg:phone":"+1 514 952 0327",
    "sg:postcode":"H7X 2X6",
    "sg:province":"QC",
    "sg:tags":[
        "limousine"
    ],
    "wof:name":"Abc Limousine",
    "wof:placetype":"venue"
},
  "geometry": {"coordinates":[-73.804725647,45.5250320435],"type":"Point"}
}