{
  "type": "Feature",
  "properties": {
    "addr:full":"540 Rue Saint-Jean Longueuil QC J4H 2Y4",
    "addr:housenumber":"540",
    "addr:postcode":"j4h 2y4",
    "addr:street":"Rue Saint-Jean",
    "iso:country":"CA",
    "sg:address":"540 Rue Saint-Jean",
    "sg:city":"Longueuil",
    "sg:classifiers":[
        {
            "category":"Home & Garden",
            "subcategory":"Furniture",
            "type":"Retail Goods"
        }
    ],
    "sg:phone":"+1 450 677 1672",
    "sg:postcode":"J4H 2Y4",
    "sg:province":"QC",
    "wof:name":"Ameublement DE LA Rive Sud",
    "wof:placetype":"venue"
},
  "geometry": {"coordinates":[-73.50559199999999,45.534641],"type":"Point"}
}