{
  "type": "Feature",
  "properties": {
    "addr:full":"PO Box 743 Cochrane ON P0L 1C0",
    "addr:housenumber":"po",
    "addr:postcode":"p0l 1c0",
    "addr:street":"Box 743",
    "iso:country":"CA",
    "sg:address":"PO Box 743",
    "sg:city":"Cochrane",
    "sg:classifiers":[
        {
            "category":"Building & Trades",
            "subcategory":"Construction",
            "type":"Services"
        }
    ],
    "sg:phone":"+1 705 272 6325",
    "sg:postcode":"P0L 1C0",
    "sg:province":"ON",
    "sg:tags":[
        "general",
        "contractor"
    ],
    "wof:name":"C S Enterprises Ltd",
    "wof:placetype":"venue"
},
  "geometry": {"coordinates":[-81.028954,49.06522],"type":"Point"}
}