{
  "type": "Feature",
  "properties": {
    "addr:full":"54 Glenview Ave Toronto ON M4R 1P6",
    "addr:housenumber":"54",
    "addr:postcode":"m4r 1p6",
    "addr:street":"Glenview Ave",
    "iso:country":"CA",
    "sg:address":"54 Glenview Ave",
    "sg:city":"Toronto",
    "sg:classifiers":[
        {
            "category":"Professional",
            "subcategory":"Management & Consulting",
            "type":"Services"
        }
    ],
    "sg:phone":"+1 416 487 3646",
    "sg:postcode":"M4R 1P6",
    "sg:province":"ON",
    "sg:tags":[
        "consultant",
        "business"
    ],
    "wof:name":"Harry B Kennedy Ltd",
    "wof:placetype":"venue"
},
  "geometry": {"coordinates":[-79.4036026001,43.7202453613],"type":"Point"}
}