{
  "type": "Feature",
  "properties": {
    "addr:full":"468 Trafalgar Rd Oakville ON L6J 3H9",
    "addr:housenumber":"468",
    "addr:postcode":"l6j 3h9",
    "addr:street":"Trafalgar Rd",
    "iso:country":"CA",
    "sg:address":"468 Trafalgar Rd",
    "sg:city":"Oakville",
    "sg:classifiers":[
        {
            "category":"Banks & Credit Unions",
            "subcategory":"Investment Brokerage",
            "type":"Services"
        }
    ],
    "sg:phone":"+1 905 823 5559",
    "sg:postcode":"L6J 3H9",
    "sg:province":"ON",
    "wof:name":"DE Thomas Financial Corp",
    "wof:placetype":"venue"
},
  "geometry": {"coordinates":[-79.68064117430001,43.4552841187],"type":"Point"}
}