{
  "type": "Feature",
  "properties": {
    "addr:full":"171 Rue Quevillon Varennes QC J3X 1J7",
    "addr:housenumber":"171",
    "addr:postcode":"j3x 1j7",
    "addr:street":"Rue Quevillon",
    "iso:country":"CA",
    "sg:address":"171 Rue Quevillon",
    "sg:city":"Varennes",
    "sg:classifiers":[
        {
            "category":"Building & Trades",
            "subcategory":"Construction",
            "type":"Services"
        }
    ],
    "sg:phone":"+1 450 652 9393",
    "sg:postcode":"J3X 1J7",
    "sg:province":"QC",
    "sg:tags":[
        "painter"
    ],
    "wof:name":"Peintres Clo-Mar Inc",
    "wof:placetype":"venue"
},
  "geometry": {"coordinates":[-73.42691802980001,45.6842536926],"type":"Point"}
}