{
  "type": "Feature",
  "properties": {
    "iso:country":"CA",
    "sg:city":"Saskatoon",
    "sg:classifiers":[
        {
            "category":"Personal",
            "subcategory":"Beauty Salon",
            "type":"Services"
        }
    ],
    "sg:phone":"+1 306 664 6001",
    "sg:postcode":"S7H 0J8",
    "sg:province":"SK",
    "wof:name":"Crop For Hair",
    "wof:placetype":"venue"
},
  "geometry": {"coordinates":[-106.65586853000001,52.1169433594],"type":"Point"}
}