{
  "type": "Feature",
  "properties": {
    "addr:full":"5316 Hwy 3 Chester Basin NS B0J 1K0",
    "addr:housenumber":"5316",
    "addr:postcode":"b0j 1k0",
    "addr:street":"Hwy 3",
    "iso:country":"CA",
    "sg:address":"5316 Hwy 3",
    "sg:city":"Chester Basin",
    "sg:classifiers":[
        {
            "category":"Autos & Motor Vehicles",
            "subcategory":"Fuel & Gas Station",
            "type":"Retail Goods"
        }
    ],
    "sg:phone":"+1 902 275 2544",
    "sg:postcode":"B0J 1K0",
    "sg:province":"NS",
    "sg:tags":[
        "oil"
    ],
    "wof:name":"Kaizer's Service Ctr",
    "wof:placetype":"venue"
},
  "geometry": {"coordinates":[-64.30652618409999,44.5679283142],"type":"Point"}
}