{
  "type": "Feature",
  "properties": {
    "addr:full":"32 Bay St Tobermory ON N0H 2R0",
    "addr:housenumber":"32",
    "addr:postcode":"n0h 2r0",
    "addr:street":"Bay St",
    "iso:country":"CA",
    "sg:address":"32 Bay St",
    "sg:city":"Tobermory",
    "sg:classifiers":[
        {
            "category":"Travel",
            "subcategory":"Hotels & Motels",
            "type":"Entertainment"
        }
    ],
    "sg:phone":"+1 519 596 2392",
    "sg:postcode":"N0H 2R0",
    "sg:province":"ON",
    "wof:name":"Blue Bay Motel",
    "wof:placetype":"venue"
},
  "geometry": {"coordinates":[-81.66274300000001,45.25502],"type":"Point"}
}