{
  "type": "Feature",
  "properties": {
    "addr:full":"13 Maitland St Harriston ON N0G 1Z0",
    "addr:housenumber":"13",
    "addr:postcode":"n0g 1z0",
    "addr:street":"Maitland St",
    "iso:country":"CA",
    "sg:address":"13 Maitland St",
    "sg:city":"Harriston",
    "sg:classifiers":[
        {
            "category":"Retail",
            "subcategory":"Portrait Studio",
            "type":"Services"
        }
    ],
    "sg:phone":"+1 519 338 3470",
    "sg:postcode":"N0G 1Z0",
    "sg:province":"ON",
    "sg:tags":[
        "photographer"
    ],
    "wof:name":"Jaz Image",
    "wof:placetype":"venue"
},
  "geometry": {"coordinates":[-80.8700637817,43.9130706787],"type":"Point"}
}