{
  "type": "Feature",
  "properties": {
    "addr:full":"8300 Rue DE L'Industrie Anjou QC H1J 1S7",
    "addr:housenumber":"8300",
    "addr:postcode":"h1j 1s7",
    "addr:street":"Rue De L'Industrie",
    "iso:country":"CA",
    "sg:address":"8300 Rue DE L'Industrie",
    "sg:city":"Anjou",
    "sg:classifiers":[
        {
            "category":"Communications",
            "subcategory":"Film & Video Production",
            "type":"Services"
        }
    ],
    "sg:phone":"+1 514 351 3539",
    "sg:postcode":"H1J 1S7",
    "sg:province":"QC",
    "sg:tags":[
        "taping"
    ],
    "wof:name":"Productions Video Expec Enr",
    "wof:placetype":"venue"
},
  "geometry": {"coordinates":[-73.562637,45.611706],"type":"Point"}
}