{
  "type": "Feature",
  "properties": {
    "addr:full":"22 Park Lane Orangeville ON L9W 4E4",
    "addr:housenumber":"22",
    "addr:postcode":"l9w 4e4",
    "addr:street":"Park Lane",
    "iso:country":"CA",
    "sg:address":"22 Park Lane",
    "sg:city":"Orangeville",
    "sg:classifiers":[
        {
            "category":"Real Estate",
            "subcategory":"Real Estate Agent",
            "type":"Services"
        }
    ],
    "sg:phone":"+1 519 941 3500",
    "sg:postcode":"L9W 4E4",
    "sg:province":"ON",
    "sg:tags":[
        "management"
    ],
    "wof:name":"Edelbrock Brothers Ltd",
    "wof:placetype":"venue"
},
  "geometry": {"coordinates":[-80.0994338989,43.9066047668],"type":"Point"}
}