{
  "type": "Feature",
  "properties": {
    "addr:full":"2179 Gottingen St Halifax NS B3K 3B5",
    "addr:housenumber":"2179",
    "addr:postcode":"b3k 3b5",
    "addr:street":"Gottingen St",
    "iso:country":"CA",
    "sg:address":"2179 Gottingen St",
    "sg:city":"Halifax",
    "sg:classifiers":[
        {
            "category":"Restaurant",
            "type":"Food & Drink"
        }
    ],
    "sg:phone":"+1 902 422 3150",
    "sg:postcode":"B3K 3B5",
    "sg:province":"NS",
    "wof:name":"Bob & Lori's Food Emporium",
    "wof:placetype":"venue"
},
  "geometry": {"coordinates":[-63.5845756531,44.6530303955],"type":"Point"}
}