{
  "type": "Feature",
  "properties": {
    "addr:full":"1476 Century Rd Manotick ON K4M 1B2",
    "addr:housenumber":"1476",
    "addr:postcode":"k4m 1b2",
    "addr:street":"Century Rd",
    "iso:country":"CA",
    "sg:address":"1476 Century Rd",
    "sg:city":"Manotick",
    "sg:classifiers":[
        {
            "category":"Retail",
            "subcategory":"Auto Repair",
            "type":"Services"
        }
    ],
    "sg:phone":"+1 613 692 4472",
    "sg:postcode":"K4M 1B2",
    "sg:province":"ON",
    "sg:tags":[
        "repairing",
        "automobile"
    ],
    "wof:name":"16 Servicentre",
    "wof:placetype":"venue"
},
  "geometry": {"coordinates":[-75.6985778809,45.2042198181],"type":"Point"}
}