{
  "type": "Feature",
  "properties": {
    "addr:full":"100 North Augusta Rd Brockville ON K6V 2X9",
    "addr:housenumber":"100",
    "addr:postcode":"k6v 2x9",
    "addr:street":"North Augusta Rd",
    "iso:country":"CA",
    "sg:address":"100 North Augusta Rd",
    "sg:city":"Brockville",
    "sg:classifiers":[
        {
            "category":"Manufacturing",
            "subcategory":"Metals",
            "type":"Manufacturing & Wholesale Goods"
        }
    ],
    "sg:phone":"+1 613 345 6116",
    "sg:postcode":"K6V 2X9",
    "sg:province":"ON",
    "sg:tags":[
        "machine",
        "screw",
        "product"
    ],
    "wof:name":"Intech Precision Ltd",
    "wof:placetype":"venue"
},
  "geometry": {"coordinates":[-75.6768951416,44.5994606018],"type":"Point"}
}