{
  "type": "Feature",
  "properties": {
    "iso:country":"CA",
    "sg:address":"1790 Rang Saint-Louis",
    "sg:city":"Saint-Gabriel-DE-Brandon",
    "sg:classifiers":[
        {
            "category":"Building & Trades",
            "subcategory":"Construction",
            "type":"Services"
        }
    ],
    "sg:phone":"+1 450 835 5206",
    "sg:postcode":"J0K 2N0",
    "sg:province":"QC",
    "sg:tags":[
        "builder",
        "stair"
    ],
    "wof:name":"Lafreniere, Arsene",
    "wof:placetype":"venue"
},
  "geometry": {"coordinates":[-73.3525772095,46.3292541504],"type":"Point"}
}