{
  "type": "Feature",
  "properties": {
    "addr:full":"4949 49 St Innisfail AB T4G 1A5",
    "addr:housenumber":"4949",
    "addr:postcode":"t4g 1a5",
    "addr:street":"49 St",
    "iso:country":"CA",
    "sg:address":"4949 49 St",
    "sg:city":"Innisfail",
    "sg:classifiers":[
        {
            "category":"Education",
            "subcategory":"Library",
            "type":"Public Place"
        }
    ],
    "sg:phone":"+1 403 227 4407",
    "sg:postcode":"T4G 1A5",
    "sg:province":"AB",
    "wof:name":"Innisfail Public Library",
    "wof:placetype":"venue"
},
  "geometry": {"coordinates":[-113.94846344,52.0263595581],"type":"Point"}
}