{
  "type": "Feature",
  "properties": {
    "addr:full":"Marmora ON K0K 2M0",
    "addr:postcode":"k0k 2m0",
    "iso:country":"CA",
    "sg:city":"Marmora",
    "sg:classifiers":[
        {
            "category":"Retail",
            "subcategory":"Repair Shop",
            "type":"Services"
        }
    ],
    "sg:phone":"+1 613 472 2114",
    "sg:postcode":"K0K 2M0",
    "sg:province":"ON",
    "sg:tags":[
        "sharpening"
    ],
    "wof:name":"Leo's Sport Shop",
    "wof:placetype":"venue"
},
  "geometry": {"coordinates":[-77.68283099999999,44.48381],"type":"Point"}
}