{
  "type": "Feature",
  "properties": {
    "addr:full":"Mississauga ON L5M 1K8",
    "addr:postcode":"l5m 1k8",
    "iso:country":"CA",
    "sg:city":"Mississauga",
    "sg:classifiers":[
        {
            "category":"Personal",
            "subcategory":"Barber",
            "type":"Services"
        }
    ],
    "sg:phone":"+1 905 542 8692",
    "sg:postcode":"L5M 1K8",
    "sg:province":"ON",
    "wof:name":"Sammy's Barber Shop",
    "wof:placetype":"venue"
},
  "geometry": {"coordinates":[-79.59749603269999,43.5459823608],"type":"Point"}
}