{
  "type": "Feature",
  "properties": {
    "addr:full":"115 Midglen Pl SE Calgary AB T2X 1H6",
    "addr:housenumber":"115",
    "addr:postcode":"t2x 1h6",
    "addr:street":"Midglen Pl Se",
    "iso:country":"CA",
    "sg:address":"115 Midglen Pl SE",
    "sg:city":"Calgary",
    "sg:classifiers":[
        {
            "category":"Utilities",
            "subcategory":"Refuse",
            "type":"Services"
        }
    ],
    "sg:phone":"+1 403 238 6660",
    "sg:postcode":"T2X 1H6",
    "sg:province":"AB",
    "sg:tags":[
        "pet",
        "waste",
        "removal"
    ],
    "wof:name":"Alberta Top Choice Pooper",
    "wof:placetype":"venue"
},
  "geometry": {"coordinates":[-114.048241,50.916214],"type":"Point"}
}