{
  "type": "Feature",
  "properties": {
    "addr:full":"1113 Ch DE LA Paix St-Sauveur QC J0R 1R2",
    "addr:housenumber":"1113",
    "addr:postcode":"j0r 1r2",
    "addr:street":"Ch De La Paix St-Sauveur",
    "iso:country":"CA",
    "sg:address":"1113 Ch DE LA Paix",
    "sg:city":"St-Sauveur",
    "sg:classifiers":[
        {
            "category":"Manufacturing",
            "subcategory":"Printing",
            "type":"Manufacturing & Wholesale Goods"
        }
    ],
    "sg:phone":"+1 450 227 1923",
    "sg:postcode":"J0R 1R2",
    "sg:province":"QC",
    "sg:tags":[
        "publisher"
    ],
    "wof:name":"O'Brien Publishing",
    "wof:placetype":"venue"
},
  "geometry": {"coordinates":[-74.199821,45.87212],"type":"Point"}
}