{
  "type": "Feature",
  "properties": {
    "addr:full":"1011 Stewart Line Cavan ON L0A 1C0",
    "addr:housenumber":"1011",
    "addr:postcode":"l0a 1c0",
    "addr:street":"Stewart Line",
    "iso:country":"CA",
    "sg:address":"1011 Stewart Line",
    "sg:city":"Cavan",
    "sg:classifiers":[
        {
            "category":"Building & Trades",
            "subcategory":"Construction",
            "type":"Services"
        }
    ],
    "sg:phone":"+1 705 944 8952",
    "sg:postcode":"L0A 1C0",
    "sg:province":"ON",
    "sg:tags":[
        "general",
        "contractor"
    ],
    "wof:name":"Kloosterman Construction Ltd",
    "wof:placetype":"venue"
},
  "geometry": {"coordinates":[-78.47023799999999,44.203602],"type":"Point"}
}