{
  "type": "Feature",
  "properties": {
    "addr:full":"1563 Hwy 11 Sundridge ON P0A 1Z0",
    "addr:housenumber":"1563",
    "addr:postcode":"p0a 1z0",
    "addr:street":"Hwy 11",
    "iso:country":"CA",
    "sg:address":"1563 Hwy 11",
    "sg:city":"Sundridge",
    "sg:classifiers":[
        {
            "category":"Retail",
            "subcategory":"Auto Repair",
            "type":"Services"
        }
    ],
    "sg:phone":"+1 705 384 5870",
    "sg:postcode":"P0A 1Z0",
    "sg:province":"ON",
    "sg:tags":[
        "repairing",
        "automobile"
    ],
    "wof:name":"Danny's Shell",
    "wof:placetype":"venue"
},
  "geometry": {"coordinates":[-79.38005099999999,45.779758],"type":"Point"}
}