{
  "type": "Feature",
  "properties": {
    "addr:full":"700 1st Ave Regina SK S4N 4Z2",
    "addr:housenumber":"700",
    "addr:postcode":"s4n 4z2",
    "addr:street":"1St Ave",
    "iso:country":"CA",
    "sg:address":"700 1st Ave",
    "sg:city":"Regina",
    "sg:classifiers":[
        {
            "category":"Autos & Motor Vehicles",
            "subcategory":"Auto Supplies",
            "type":"Retail Goods"
        }
    ],
    "sg:phone":"+1 306 775 1244",
    "sg:postcode":"S4N 4Z2",
    "sg:province":"SK",
    "sg:tags":[
        "tire"
    ],
    "wof:name":"Bell Tire Store",
    "wof:placetype":"venue"
},
  "geometry": {"coordinates":[-104.59046936,50.4677276611],"type":"Point"}
}