{
  "type": "Feature",
  "properties": {
    "addr:full":"RR 4 STN Main Lacombe AB T4L 2N4",
    "addr:postcode":"t4l 2n4",
    "addr:street":"Rr 4 Stn Main",
    "iso:country":"CA",
    "sg:address":"RR 4 STN Main",
    "sg:city":"Lacombe",
    "sg:classifiers":[
        {
            "category":"Manufacturing",
            "subcategory":"Tools & Machinery",
            "type":"Manufacturing & Wholesale Goods"
        }
    ],
    "sg:phone":"+1 403 784 3518",
    "sg:postcode":"T4L 2N4",
    "sg:province":"AB",
    "sg:tags":[
        "farm",
        "equipment",
        "livestock",
        "supply"
    ],
    "wof:name":"Renn Mill Ctr",
    "wof:placetype":"venue"
},
  "geometry": {"coordinates":[-113.73670196499999,52.4631118774],"type":"Point"}
}