{
  "type": "Feature",
  "properties": {
    "addr:full":"5370 Av Papineau Montreal QC H2H 1W2",
    "addr:housenumber":"5370",
    "addr:postcode":"h2h 1w2",
    "addr:street":"Av Papineau",
    "iso:country":"CA",
    "sg:address":"5370 Av Papineau",
    "sg:city":"Montreal",
    "sg:classifiers":[
        {
            "category":"Shopping",
            "subcategory":"Optical Goods",
            "type":"Retail Goods"
        }
    ],
    "sg:phone":"+1 514 522 3680",
    "sg:postcode":"H2H 1W2",
    "sg:province":"QC",
    "sg:tags":[
        "optician"
    ],
    "wof:name":"Lunetier",
    "wof:placetype":"venue"
},
  "geometry": {"coordinates":[-73.584419,45.537323],"type":"Point"}
}