{
  "type": "Feature",
  "properties": {
    "addr:full":"49 Elizabeth Ave # 202 St. John's NL A1A 1W9",
    "addr:housenumber":"49",
    "addr:postcode":"a1a 1w9",
    "addr:street":"Elizabeth Ave # 202",
    "iso:country":"CA",
    "sg:address":"49 Elizabeth Ave # 202",
    "sg:city":"St. John's",
    "sg:classifiers":[
        {
            "category":"Professional",
            "subcategory":"Management & Consulting",
            "type":"Services"
        }
    ],
    "sg:phone":"+1 709 753 9392",
    "sg:postcode":"A1A 1W9",
    "sg:province":"NL",
    "sg:tags":[
        "employee",
        "consultant",
        "benefit"
    ],
    "wof:name":"Benefit Plan Administrators",
    "wof:placetype":"venue"
},
  "geometry": {"coordinates":[-58.577404,48.554279],"type":"Point"}
}