{
  "type": "Feature",
  "properties": {
    "addr:full":"200 Sheldon Ch Stanstead QC J0B 3E0",
    "addr:housenumber":"200",
    "addr:postcode":"j0b 3e0",
    "addr:street":"Sheldon Ch",
    "iso:country":"CA",
    "sg:address":"200 Sheldon Ch",
    "sg:city":"Stanstead",
    "sg:classifiers":[
        {
            "category":"Building & Trades",
            "subcategory":"Construction",
            "type":"Services"
        }
    ],
    "sg:phone":"+1 819 843 5321",
    "sg:postcode":"J0B 3E0",
    "sg:province":"QC",
    "sg:tags":[
        "excavating",
        "contractor"
    ],
    "wof:name":"Noel N Marcel Excavation",
    "wof:placetype":"venue"
},
  "geometry": {"coordinates":[-72.15186300000001,45.020874],"type":"Point"}
}