{
  "type": "Feature",
  "properties": {
    "addr:full":"21 Mews Pl St. John's NL A1B 4N2",
    "addr:housenumber":"21",
    "addr:postcode":"a1b 4n2",
    "addr:street":"Mews Pl",
    "iso:country":"CA",
    "sg:address":"21 Mews Pl",
    "sg:city":"St. John's",
    "sg:classifiers":[
        {
            "category":"Professional",
            "subcategory":"Engineering",
            "type":"Services"
        }
    ],
    "sg:phone":"+1 709 754 1911",
    "sg:postcode":"A1B 4N2",
    "sg:province":"NL",
    "sg:tags":[
        "engineer"
    ],
    "wof:name":"Crosbie Engineering Ltd",
    "wof:placetype":"venue"
},
  "geometry": {"coordinates":[-52.773975,47.560303],"type":"Point"}
}