{
  "type": "Feature",
  "properties": {
    "addr:full":"Kitchener ON N2H 1K8",
    "addr:postcode":"n2h 1k8",
    "iso:country":"CA",
    "sg:city":"Kitchener",
    "sg:classifiers":[
        {
            "category":"Organizations",
            "subcategory":"Professional Association",
            "type":"Services"
        }
    ],
    "sg:phone":"+1 519 837 9455",
    "sg:postcode":"N2H 1K8",
    "sg:province":"ON",
    "wof:name":"Canadian Diabetes Assn",
    "wof:placetype":"venue"
},
  "geometry": {"coordinates":[-80.48345947270001,43.452167511],"type":"Point"}
}