{
  "type": "Feature",
  "properties": {
    "addr:full":"34 Warren Ave Riverview NB E1B 3M3",
    "addr:housenumber":"34",
    "addr:postcode":"e1b 3m3",
    "addr:street":"Warren Ave",
    "iso:country":"CA",
    "sg:address":"34 Warren Ave",
    "sg:city":"Riverview",
    "sg:classifiers":[
        {
            "category":"Recreation",
            "type":"Entertainment"
        }
    ],
    "sg:phone":"+1 506 386 4361",
    "sg:postcode":"E1B 3M3",
    "sg:province":"NB",
    "sg:tags":[
        "bingo",
        "game",
        "supply"
    ],
    "wof:name":"Lakefront Distributors",
    "wof:placetype":"venue"
},
  "geometry": {"coordinates":[-64.810295,46.04837],"type":"Point"}
}