{
  "type": "Feature",
  "properties": {
    "addr:full":"285 Geneva St St Catharines ON L2N 2G1",
    "addr:housenumber":"285",
    "addr:postcode":"l2n 2g1",
    "addr:street":"Geneva St",
    "iso:country":"CA",
    "sg:address":"285 Geneva St",
    "sg:city":"St Catharines",
    "sg:classifiers":[
        {
            "category":"Personal",
            "subcategory":"Beauty Salon",
            "type":"Services"
        }
    ],
    "sg:phone":"+1 905 935 3317",
    "sg:postcode":"L2N 2G1",
    "sg:province":"ON",
    "wof:name":"Hairquarters Unisex",
    "wof:placetype":"venue"
},
  "geometry": {"coordinates":[-79.2409896851,43.1771812439],"type":"Point"}
}