{
  "type": "Feature",
  "properties": {
    "addr:full":"1063 Main St Hampton NB E5N 6E9",
    "addr:housenumber":"1063",
    "addr:postcode":"e5n 6e9",
    "addr:street":"Main St",
    "iso:country":"CA",
    "sg:address":"1063 Main St",
    "sg:city":"Hampton",
    "sg:classifiers":[
        {
            "category":"Retail",
            "subcategory":"Funeral Services",
            "type":"Services"
        }
    ],
    "sg:phone":"+1 506 832 5541",
    "sg:postcode":"E5N 6E9",
    "sg:province":"NB",
    "sg:tags":[
        "director"
    ],
    "wof:name":"Reid's Funeral Home",
    "wof:placetype":"venue"
},
  "geometry": {"coordinates":[-65.83651733400001,45.5424804688],"type":"Point"}
}