{
  "type": "Feature",
  "properties": {
    "addr:full":"944 9E Rue E Degelis QC G5T 2B4",
    "addr:housenumber":"944",
    "addr:postcode":"g5t 2b4",
    "addr:street":"9E Rue E Degelis",
    "iso:country":"CA",
    "sg:address":"944 9E Rue E",
    "sg:city":"Degelis",
    "sg:classifiers":[
        {
            "category":"Wholesale",
            "subcategory":"Office Equipment",
            "type":"Manufacturing & Wholesale Goods"
        }
    ],
    "sg:phone":"+1 418 853 2374",
    "sg:postcode":"G5T 2B4",
    "sg:province":"QC",
    "sg:tags":[
        "accounting",
        "bookkeeping",
        "system"
    ],
    "wof:name":"Comptabilite Simone Fraser",
    "wof:placetype":"venue"
},
  "geometry": {"coordinates":[-68.642899,47.547318],"type":"Point"}
}