{
  "type": "Feature",
  "properties": {
    "addr:full":"Longueuil QC J4J 1W9",
    "addr:postcode":"j4j 1w9",
    "iso:country":"CA",
    "sg:city":"Longueuil",
    "sg:classifiers":[
        {
            "category":"Food & Beverages",
            "subcategory":"Specialty",
            "type":"Retail Goods"
        }
    ],
    "sg:phone":"+1 450 442 2244",
    "sg:postcode":"J4J 1W9",
    "sg:province":"QC",
    "wof:name":"Naturiste Jmb Inc",
    "wof:placetype":"venue"
},
  "geometry": {"coordinates":[-73.48664100000001,45.529873],"type":"Point"}
}