{
  "type": "Feature",
  "properties": {
    "addr:full":"170 Charlotte St Peterborough ON K9J 2T8",
    "addr:housenumber":"170",
    "addr:postcode":"k9j 2t8",
    "addr:street":"Charlotte St",
    "iso:country":"CA",
    "sg:address":"170 Charlotte St",
    "sg:city":"Peterborough",
    "sg:classifiers":[
        {
            "category":"Restaurant",
            "type":"Food & Drink"
        }
    ],
    "sg:phone":"+1 705 741 6491",
    "sg:postcode":"K9J 2T8",
    "sg:province":"ON",
    "wof:name":"Cosmic Charlie's Cafe",
    "wof:placetype":"venue"
},
  "geometry": {"coordinates":[-78.320801,44.303532],"type":"Point"}
}