{
  "type": "Feature",
  "properties": {
    "addr:full":"1419 Lakeshore Rd Selkirk ON N0A 1P0",
    "addr:housenumber":"1419",
    "addr:postcode":"n0a 1p0",
    "addr:street":"Lakeshore Rd",
    "iso:country":"CA",
    "sg:address":"1419 Lakeshore Rd",
    "sg:city":"Selkirk",
    "sg:classifiers":[
        {
            "category":"Home & Garden",
            "subcategory":"Home Furnishings",
            "type":"Retail Goods"
        }
    ],
    "sg:phone":"+1 905 776 5555",
    "sg:postcode":"N0A 1P0",
    "sg:province":"ON",
    "sg:tags":[
        "venetian",
        "blind"
    ],
    "wof:name":"Krok's Blinds",
    "wof:placetype":"venue"
},
  "geometry": {"coordinates":[-79.88163,42.823292],"type":"Point"}
}