{
  "type": "Feature",
  "properties": {
    "addr:full":"1460 Ryan St Victoria BC V8R 2X1",
    "addr:housenumber":"1460",
    "addr:postcode":"v8r 2x1",
    "addr:street":"Ryan St",
    "iso:country":"CA",
    "sg:address":"1460 Ryan St",
    "sg:city":"Victoria",
    "sg:classifiers":[
        {
            "category":"Building & Trades",
            "subcategory":"Construction",
            "type":"Services"
        }
    ],
    "sg:phone":"+1 250 595 2211",
    "sg:postcode":"V8R 2X1",
    "sg:province":"BC",
    "sg:tags":[
        "dry wall",
        "contractor"
    ],
    "wof:name":"Island Dry-Wall",
    "wof:placetype":"venue"
},
  "geometry": {"coordinates":[-123.34058400000001,48.440117],"type":"Point"}
}