{
  "type": "Feature",
  "properties": {
    "addr:full":"52 Labrosse St Moose Creek ON K0C 1W0",
    "addr:housenumber":"52",
    "addr:postcode":"k0c 1w0",
    "addr:street":"Labrosse St",
    "iso:country":"CA",
    "sg:address":"52 Labrosse St",
    "sg:city":"Moose Creek",
    "sg:classifiers":[
        {
            "category":"Travel",
            "subcategory":"Hotels & Motels",
            "type":"Entertainment"
        }
    ],
    "sg:phone":"+1 613 538 2842",
    "sg:postcode":"K0C 1W0",
    "sg:province":"ON",
    "sg:tags":[
        "bars"
    ],
    "wof:name":"Central Hotel",
    "wof:placetype":"venue"
},
  "geometry": {"coordinates":[-74.97077899999999,45.261314],"type":"Point"}
}