{
  "type": "Feature",
  "properties": {
    "iso:country":"CA",
    "sg:address":"241 19th St",
    "sg:city":"Morden",
    "sg:classifiers":[
        {
            "category":"Professional",
            "subcategory":"Business Services",
            "type":"Services"
        }
    ],
    "sg:phone":"+1 204 822 4555",
    "sg:postcode":"R6M 1K3",
    "sg:province":"MB",
    "wof:name":"Pembina Water Transport",
    "wof:placetype":"venue"
},
  "geometry": {"coordinates":[-98.120277,49.195717],"type":"Point"}
}