{
  "type": "Feature",
  "properties": {
    "addr:full":"241 19th St Morden MB R6M 1K3",
    "addr:housenumber":"241",
    "addr:postcode":"r6m 1k3",
    "addr:street":"19Th St",
    "iso:country":"CA",
    "sg:address":"241 19th St",
    "sg:city":"Morden",
    "sg:classifiers":[
        {
            "category":"Professional",
            "subcategory":"Business Services",
            "type":"Services"
        }
    ],
    "sg:phone":"+1 204 822 4555",
    "sg:postcode":"R6M 1K3",
    "sg:province":"MB",
    "wof:name":"Pembina Water Transport",
    "wof:placetype":"venue"
},
  "geometry": {"coordinates":[-98.120277,49.195717],"type":"Point"}
}