{
  "type": "Feature",
  "properties": {
    "iso:country":"CA",
    "sg:address":"146 Liberty St N",
    "sg:city":"Bowmanville",
    "sg:classifiers":[
        {
            "category":"Food & Beverages",
            "subcategory":"Bakery",
            "type":"Retail Goods"
        }
    ],
    "sg:phone":"+1 905 623 6507",
    "sg:postcode":"L1C 2M3",
    "sg:province":"ON",
    "sg:tags":[
        "doughnut"
    ],
    "wof:name":"Skylight Donuts Drive Thru",
    "wof:placetype":"venue"
},
  "geometry": {"coordinates":[-78.6842803955,43.9199409485],"type":"Point"}
}