{
  "type": "Feature",
  "properties": {
    "iso:country":"CA",
    "sg:city":"Kleinburg",
    "sg:classifiers":[
        {
            "category":"Personal",
            "subcategory":"Beauty Salon",
            "type":"Services"
        }
    ],
    "sg:phone":"+1 905 893 2520",
    "sg:postcode":"L0J 1C0",
    "sg:province":"ON",
    "wof:name":"Salon Daniel Luis",
    "wof:placetype":"venue"
},
  "geometry": {"coordinates":[-79.6276931763,43.8434143066],"type":"Point"}
}