{
  "type": "Feature",
  "properties": {
    "addr:full":"7373 Boul Langelier Saint-Leonard QC H1S 1V7",
    "addr:housenumber":"7373",
    "addr:postcode":"h1s 1v7",
    "addr:street":"Boul Langelier",
    "iso:country":"CA",
    "sg:address":"7373 Boul Langelier",
    "sg:city":"Saint-Leonard",
    "sg:classifiers":[
        {
            "category":"Shopping",
            "subcategory":"Florist",
            "type":"Retail Goods"
        }
    ],
    "sg:phone":"+1 514 253 2488",
    "sg:postcode":"H1S 1V7",
    "sg:province":"QC",
    "wof:name":"Fleuriste Point Vert",
    "wof:placetype":"venue"
},
  "geometry": {"coordinates":[-73.57231899999999,45.591568],"type":"Point"}
}