{
  "type": "Feature",
  "properties": {
    "addr:full":"1257 Marine Dr North Vancouver BC V7P 1T3",
    "addr:housenumber":"1257",
    "addr:postcode":"v7p 1t3",
    "addr:street":"Marine Dr",
    "iso:country":"CA",
    "sg:address":"1257 Marine Dr",
    "sg:city":"North Vancouver",
    "sg:classifiers":[
        {
            "category":"Retail",
            "subcategory":"Auto Repair",
            "type":"Services"
        }
    ],
    "sg:phone":"+1 604 987 5310",
    "sg:postcode":"V7P 1T3",
    "sg:province":"BC",
    "sg:tags":[
        "automobile",
        "top",
        "upholstery"
    ],
    "wof:name":"Ben-Ray Enterprises Ltd",
    "wof:placetype":"venue"
},
  "geometry": {"coordinates":[-123.109283,49.323681],"type":"Point"}
}