{
  "type": "Feature",
  "properties": {
    "addr:full":"677 Rue Sainte-Catherine O # 1019 Montreal QC H3B 5K4",
    "addr:housenumber":"677",
    "addr:postcode":"h3b 5k4",
    "addr:street":"Rue Sainte-Catherine O # 1019",
    "iso:country":"CA",
    "sg:address":"677 Rue Sainte-Catherine O # 1019",
    "sg:city":"Montreal",
    "sg:classifiers":[
        {
            "category":"Shopping",
            "subcategory":"Shoes",
            "type":"Retail Goods"
        }
    ],
    "sg:phone":"+1 514 842 3144",
    "sg:postcode":"H3B 5K4",
    "sg:province":"QC",
    "wof:name":"Chaussures Aldo Inc",
    "wof:placetype":"venue"
},
  "geometry": {"coordinates":[-73.55922698969999,45.5153236389],"type":"Point"}
}