{
  "type": "Feature",
  "properties": {
    "addr:full":"121 King St E Hamilton ON L8N 1A9",
    "addr:housenumber":"121",
    "addr:postcode":"l8n 1a9",
    "addr:street":"King St E",
    "iso:country":"CA",
    "sg:address":"121 King St E",
    "sg:city":"Hamilton",
    "sg:classifiers":[
        {
            "category":"Shopping",
            "subcategory":"Pharmacy",
            "type":"Retail Goods"
        }
    ],
    "sg:phone":"+1 905 521 2273",
    "sg:postcode":"L8N 1A9",
    "sg:province":"ON",
    "wof:name":"Power Drug Mart",
    "wof:placetype":"venue"
},
  "geometry": {"coordinates":[-79.86539459230001,43.2555198669],"type":"Point"}
}