{
  "type": "Feature",
  "properties": {
    "addr:full":"5440 Imperial St Burnaby BC V5J 1E6",
    "addr:housenumber":"5440",
    "addr:postcode":"v5j 1e6",
    "addr:street":"Imperial St",
    "iso:country":"CA",
    "sg:address":"5440 Imperial St",
    "sg:city":"Burnaby",
    "sg:classifiers":[
        {
            "category":"Retail",
            "subcategory":"Auto Repair",
            "type":"Services"
        }
    ],
    "sg:phone":"+1 604 438 1485",
    "sg:postcode":"V5J 1E6",
    "sg:province":"BC",
    "sg:tags":[
        "repairing",
        "automobile"
    ],
    "wof:name":"Conset Auto Svc",
    "wof:placetype":"venue"
},
  "geometry": {"coordinates":[-122.98556499999999,49.221703],"type":"Point"}
}