{
  "type": "Feature",
  "properties": {
    "addr:full":"Saint-Hubert QC J3Y 3P6",
    "addr:postcode":"j3y 3p6",
    "iso:country":"CA",
    "sg:city":"Saint-Hubert",
    "sg:classifiers":[
        {
            "category":"Shopping",
            "subcategory":"Computers & Home Electronics",
            "type":"Retail Goods"
        }
    ],
    "sg:phone":"+1 450 462 5455",
    "sg:postcode":"J3Y 3P6",
    "sg:province":"QC",
    "sg:tags":[
        "equipment",
        "dealer"
    ],
    "wof:name":"Msn Informatique",
    "wof:placetype":"venue"
},
  "geometry": {"coordinates":[-73.416679,45.501972],"type":"Point"}
}