{
  "type": "Feature",
  "properties": {
    "addr:full":"Nanaimo BC V9S 5L6",
    "addr:postcode":"v9s 5l6",
    "iso:country":"CA",
    "sg:city":"Nanaimo",
    "sg:classifiers":[
        {
            "category":"Building & Trades",
            "subcategory":"Construction",
            "type":"Services"
        }
    ],
    "sg:phone":"+1 250 756 3190",
    "sg:postcode":"V9S 5L6",
    "sg:province":"BC",
    "sg:tags":[
        "paving",
        "contractor"
    ],
    "wof:name":"Whitecap Paving Ltd",
    "wof:placetype":"venue"
},
  "geometry": {"coordinates":[-123.95399500000001,49.182812],"type":"Point"}
}