{
  "type": "Feature",
  "properties": {
    "addr:full":"1036 39th Ave E Vancouver BC V5W 1L1",
    "addr:housenumber":"1036",
    "addr:postcode":"v5w 1l1",
    "addr:street":"39Th Ave E",
    "iso:country":"CA",
    "sg:address":"1036 39th Ave E",
    "sg:city":"Vancouver",
    "sg:classifiers":[
        {
            "category":"Building & Trades",
            "subcategory":"Construction",
            "type":"Services"
        }
    ],
    "sg:phone":"+1 604 324 0766",
    "sg:postcode":"V5W 1L1",
    "sg:province":"BC",
    "sg:tags":[
        "painter"
    ],
    "wof:name":"Vancity Painting & Decorating",
    "wof:placetype":"venue"
},
  "geometry": {"coordinates":[-123.083778381,49.2345924377],"type":"Point"}
}