{
  "type": "Feature",
  "properties": {
    "addr:full":"Killam AB T0B 2L0",
    "addr:postcode":"t0b 2l0",
    "iso:country":"CA",
    "sg:city":"Killam",
    "sg:classifiers":[
        {
            "category":"Retail",
            "subcategory":"Repair Shop",
            "type":"Services"
        }
    ],
    "sg:phone":"+1 780 385 3808",
    "sg:postcode":"T0B 2L0",
    "sg:province":"AB",
    "sg:tags":[
        "welding"
    ],
    "wof:name":"Mc Gowan Welding Ltd",
    "wof:placetype":"venue"
},
  "geometry": {"coordinates":[-111.85592699999999,52.790718],"type":"Point"}
}