{
  "type": "Feature",
  "properties": {
    "addr:full":"Whistler BC V0N 1B4",
    "addr:postcode":"v0n 1b4",
    "iso:country":"CA",
    "sg:city":"Whistler",
    "sg:classifiers":[
        {
            "category":"Restaurant",
            "type":"Food & Drink"
        }
    ],
    "sg:phone":"+1 604 932 2223",
    "sg:postcode":"V0N 1B4",
    "sg:province":"BC",
    "wof:name":"Teppan Village",
    "wof:placetype":"venue"
},
  "geometry": {"coordinates":[-122.95500199999999,50.113598],"type":"Point"}
}