{
  "type": "Feature",
  "properties": {
    "addr:full":"11 Guildwood Dr Hamilton ON L9C 7K2",
    "addr:housenumber":"11",
    "addr:postcode":"l9c 7k2",
    "addr:street":"Guildwood Dr",
    "iso:country":"CA",
    "sg:address":"11 Guildwood Dr",
    "sg:city":"Hamilton",
    "sg:classifiers":[
        {
            "category":"Education",
            "subcategory":"School",
            "type":"Public Place"
        }
    ],
    "sg:phone":"+1 905 574 6336",
    "sg:postcode":"L9C 7K2",
    "sg:province":"ON",
    "wof:name":"Gordon Price School",
    "wof:placetype":"venue"
},
  "geometry": {"coordinates":[-79.919518,43.222721],"type":"Point"}
}