{
  "type": "Feature",
  "properties": {
    "iso:country":"CA",
    "sg:address":"325 Bleecker St",
    "sg:city":"Toronto",
    "sg:classifiers":[
        {
            "category":"Social Services",
            "subcategory":"Job Training",
            "type":"Services"
        }
    ],
    "sg:phone":"+1 416 364 4837",
    "sg:postcode":"M4X 1M2",
    "sg:province":"ON",
    "sg:tags":[
        "rehabilitation"
    ],
    "wof:name":"Psychogeriatric Community",
    "wof:placetype":"venue"
},
  "geometry": {"coordinates":[-79.3744506836,43.6693840027],"type":"Point"}
}