{
  "type": "Feature",
  "properties": {
    "addr:full":"75 Rue Saint-Jean Quebec QC G1R 1N4",
    "addr:housenumber":"75",
    "addr:postcode":"g1r 1n4",
    "addr:street":"Rue Saint-Jean",
    "iso:country":"CA",
    "sg:address":"75 Rue Saint-Jean",
    "sg:city":"Quebec",
    "sg:classifiers":[
        {
            "category":"Professional",
            "subcategory":"Lawyer & Legal Services",
            "type":"Services"
        }
    ],
    "sg:phone":"+1 418 529 5881",
    "sg:postcode":"G1R 1N4",
    "sg:province":"QC",
    "sg:tags":[
        "attorney"
    ],
    "wof:name":"Larochelle, Jacques",
    "wof:placetype":"venue"
},
  "geometry": {"coordinates":[-71.22663900000001,46.807026],"type":"Point"}
}