{
  "type": "Feature",
  "properties": {
    "addr:full":"Halifax NS B3J 3T2",
    "addr:postcode":"ns b3j 3t2",
    "iso:country":"CA",
    "sg:city":"Halifax",
    "sg:classifiers":[
        {
            "category":"Organizations",
            "subcategory":"Professional Association",
            "type":"Services"
        }
    ],
    "sg:phone":"+1 902 423 2378",
    "sg:postcode":"B3J 3T2",
    "sg:province":"NS",
    "sg:tags":[
        "boat"
    ],
    "wof:name":"N S Boat Builders Assn",
    "wof:placetype":"venue"
},
  "geometry": {"coordinates":[-63.5760917664,44.6433296204],"type":"Point"}
}