{
  "type": "Feature",
  "properties": {
    "addr:full":"103 12E Rue Ferme-Neuve QC J0W 1C0",
    "addr:housenumber":"103",
    "addr:postcode":"j0w 1c0",
    "addr:street":"12E Rue",
    "iso:country":"CA",
    "sg:address":"103 12E Rue",
    "sg:city":"Ferme-Neuve",
    "sg:classifiers":[
        {
            "category":"Banks & Credit Unions",
            "subcategory":"Bank",
            "type":"Services"
        }
    ],
    "sg:phone":"+1 819 587 3121",
    "sg:postcode":"J0W 1C0",
    "sg:province":"QC",
    "wof:name":"Banque Nationale Du Canada",
    "wof:placetype":"venue"
},
  "geometry": {"coordinates":[-75.449387,46.698223],"type":"Point"}
}