{
  "type": "Feature",
  "properties": {
    "addr:full":"Stanbridge East QC J0J 2H0",
    "addr:postcode":"j0j 2h0",
    "iso:country":"CA",
    "sg:city":"Stanbridge East",
    "sg:classifiers":[
        {
            "category":"Organizations",
            "subcategory":"Professional Association",
            "type":"Services"
        }
    ],
    "sg:phone":"+1 450 248 7998",
    "sg:postcode":"J0J 2H0",
    "sg:province":"QC",
    "wof:name":"Stanbridge East Sports",
    "wof:placetype":"venue"
},
  "geometry": {"coordinates":[-72.914314,45.121639],"type":"Point"}
}