{
  "type": "Feature",
  "properties": {
    "addr:full":"950 Talbot St St Thomas ON N5P 1E7",
    "addr:housenumber":"950",
    "addr:postcode":"n5p 1e7",
    "addr:street":"Talbot St",
    "iso:country":"CA",
    "sg:address":"950 Talbot St",
    "sg:city":"St Thomas",
    "sg:classifiers":[
        {
            "category":"Restaurant",
            "type":"Food & Drink"
        }
    ],
    "sg:phone":"+1 519 633 9024",
    "sg:postcode":"N5P 1E7",
    "sg:province":"ON",
    "wof:name":"Taco Bell",
    "wof:placetype":"venue"
},
  "geometry": {"coordinates":[-81.179626,42.778648],"type":"Point"}
}