{
  "type": "Feature",
  "properties": {
    "addr:full":"240 Dupont Rd North Bay ON P1B 8Z4",
    "addr:housenumber":"240",
    "addr:postcode":"p1b 8z4",
    "addr:street":"Dupont Rd",
    "iso:country":"CA",
    "sg:address":"240 Dupont Rd",
    "sg:city":"North Bay",
    "sg:classifiers":[
        {
            "category":"Wholesale",
            "subcategory":"Chemicals & Plastics",
            "type":"Manufacturing & Wholesale Goods"
        }
    ],
    "sg:phone":"+1 705 476 7057",
    "sg:postcode":"P1B 8Z4",
    "sg:province":"ON",
    "wof:name":"Pgi Fabrene Inc",
    "wof:placetype":"venue"
},
  "geometry": {"coordinates":[-79.38149261469999,46.2670402527],"type":"Point"}
}