{
  "type": "Feature",
  "properties": {
    "addr:full":"Erin ON N0B 1T0",
    "addr:postcode":"n0b 1t0",
    "iso:country":"CA",
    "sg:city":"Erin",
    "sg:classifiers":[
        {
            "category":"Autos & Motor Vehicles",
            "subcategory":"Automobile Sales",
            "type":"Retail Goods"
        }
    ],
    "sg:phone":"+1 519 833 2411",
    "sg:postcode":"N0B 1T0",
    "sg:province":"ON",
    "sg:tags":[
        "car",
        "dealer"
    ],
    "wof:name":"Erin Auto House",
    "wof:placetype":"venue"
},
  "geometry": {"coordinates":[-80.0585479736,43.7648468018],"type":"Point"}
}