{
  "type": "Feature",
  "properties": {
    "addr:full":"17380 Warina Rd Maxville ON K0C 1T0",
    "addr:housenumber":"17380",
    "addr:postcode":"k0c 1t0",
    "addr:street":"Warina Rd",
    "iso:country":"CA",
    "sg:address":"17380 Warina Rd",
    "sg:city":"Maxville",
    "sg:classifiers":[
        {
            "category":"Shopping",
            "subcategory":"Florist",
            "type":"Retail Goods"
        }
    ],
    "sg:phone":"+1 613 527 2877",
    "sg:postcode":"K0C 1T0",
    "sg:province":"ON",
    "sg:tags":[
        "garden",
        "center"
    ],
    "wof:name":"Freeland Flowers",
    "wof:placetype":"venue"
},
  "geometry": {"coordinates":[-74.8559417725,45.2889633179],"type":"Point"}
}