{
  "type": "Feature",
  "properties": {
    "iso:country":"CA",
    "sg:address":"6235 8E Av",
    "sg:city":"Montreal",
    "sg:classifiers":[
        {
            "category":"Health Services",
            "subcategory":"Nursing And Care Facility",
            "type":"Services"
        }
    ],
    "sg:phone":"+1 514 593 1110",
    "sg:postcode":"H1Y 2M3",
    "sg:province":"QC",
    "sg:tags":[
        "home",
        "rest"
    ],
    "wof:name":"Residence L'Air Du Temps",
    "wof:placetype":"venue"
},
  "geometry": {"coordinates":[-73.584709,45.552467],"type":"Point"}
}