{
  "type": "Feature",
  "properties": {
    "addr:full":"4021 4 St SE Calgary AB T2G 2W4",
    "addr:housenumber":"4021 4",
    "addr:postcode":"t2g 2w4",
    "addr:street":"St Se",
    "iso:country":"CA",
    "sg:address":"4021 4 St SE",
    "sg:city":"Calgary",
    "sg:classifiers":[
        {
            "category":"Building & Trades",
            "subcategory":"Construction",
            "type":"Services"
        }
    ],
    "sg:phone":"+1 403 243 7444",
    "sg:postcode":"T2G 2W4",
    "sg:province":"AB",
    "sg:tags":[
        "general",
        "contractor"
    ],
    "wof:name":"Alta Interior Contracting Ltd",
    "wof:placetype":"venue"
},
  "geometry": {"coordinates":[-114.04941599999999,51.021843],"type":"Point"}
}