{
  "type": "Feature",
  "properties": {
    "addr:full":"7 Hollingbury Pl Winnipeg MB R2N 3W3",
    "addr:housenumber":"7",
    "addr:postcode":"r2n 3w3",
    "addr:street":"Hollingbury Pl",
    "iso:country":"CA",
    "sg:address":"7 Hollingbury Pl",
    "sg:city":"Winnipeg",
    "sg:classifiers":[
        {
            "category":"Professional",
            "subcategory":"Accounting & Tax Preparation",
            "type":"Services"
        }
    ],
    "sg:phone":"+1 204 256 6151",
    "sg:postcode":"R2N 3W3",
    "sg:province":"MB",
    "sg:tags":[
        "accountant"
    ],
    "wof:name":"Accountable Management Conslnt",
    "wof:placetype":"venue"
},
  "geometry": {"coordinates":[-97.09324599999999,49.813339],"type":"Point"}
}