{
  "type": "Feature",
  "properties": {
    "addr:full":"530 Macgregor Rd Sarnia ON N7T 7H5",
    "addr:housenumber":"530",
    "addr:postcode":"n7t 7h5",
    "addr:street":"Macgregor Rd",
    "iso:country":"CA",
    "sg:address":"530 Macgregor Rd",
    "sg:city":"Sarnia",
    "sg:classifiers":[
        {
            "category":"Building & Trades",
            "subcategory":"Plumbing",
            "type":"Services"
        }
    ],
    "sg:phone":"+1 519 336 2753",
    "sg:postcode":"N7T 7H5",
    "sg:province":"ON",
    "sg:tags":[
        "contractor",
        "mechanical"
    ],
    "wof:name":"Anderson Webb",
    "wof:placetype":"venue"
},
  "geometry": {"coordinates":[-82.3684539795,42.9537849426],"type":"Point"}
}