{
  "type": "Feature",
  "properties": {
    "addr:full":"2099 Lougheed Hwy Port Coquitlam BC V3B 1A8",
    "addr:housenumber":"2099",
    "addr:postcode":"v3b 1a8",
    "addr:street":"Lougheed Hwy",
    "iso:country":"CA",
    "sg:address":"2099 Lougheed Hwy",
    "sg:city":"Port Coquitlam",
    "sg:classifiers":[
        {
            "category":"Bars & Pubs",
            "type":"Food & Drink"
        }
    ],
    "sg:phone":"+1 604 942 6020",
    "sg:postcode":"V3B 1A8",
    "sg:province":"BC",
    "wof:name":"Treehouse Bar & Grill",
    "wof:placetype":"venue"
},
  "geometry": {"coordinates":[-122.77424621599999,49.266708374],"type":"Point"}
}