{
  "type": "Feature",
  "properties": {
    "iso:country":"CA",
    "sg:address":"37 Holland St W",
    "sg:city":"Bradford",
    "sg:classifiers":[
        {
            "category":"Food & Beverages",
            "subcategory":"Meat & Fish",
            "type":"Retail Goods"
        }
    ],
    "sg:phone":"+1 905 775 0408",
    "sg:postcode":"L3Z 2B3",
    "sg:province":"ON",
    "sg:tags":[
        "seafood"
    ],
    "wof:name":"Mar Alto Fish Market",
    "wof:placetype":"venue"
},
  "geometry": {"coordinates":[-79.56614685060001,44.1140899658],"type":"Point"}
}