{
  "type": "Feature",
  "properties": {
    "iso:country":"CA",
    "sg:address":"PO Box 560",
    "sg:city":"Plamondon",
    "sg:classifiers":[
        {
            "category":"Organizations",
            "subcategory":"Professional Association",
            "type":"Services"
        }
    ],
    "sg:phone":"+1 780 798 3844",
    "sg:postcode":"T0A 2T0",
    "sg:province":"AB",
    "sg:tags":[
        "club"
    ],
    "wof:name":"Plamondon Pioneer Club",
    "wof:placetype":"venue"
},
  "geometry": {"coordinates":[-112.344474792,54.8497810364],"type":"Point"}
}