{
  "type": "Feature",
  "properties": {
    "addr:full":"7 Ave NW Manning AB T0H 2M0",
    "addr:postcode":"t0h 2m0",
    "addr:street":"7 Ave Nw",
    "iso:country":"CA",
    "sg:address":"7 Ave NW",
    "sg:city":"Manning",
    "sg:classifiers":[
        {
            "category":"Building & Trades",
            "subcategory":"Construction",
            "type":"Services"
        }
    ],
    "sg:phone":"+1 780 836 3413",
    "sg:postcode":"T0H 2M0",
    "sg:province":"AB",
    "sg:tags":[
        "maker",
        "cabinet"
    ],
    "wof:name":"Craig's Carpentry",
    "wof:placetype":"venue"
},
  "geometry": {"coordinates":[-117.63153800000001,56.930077],"type":"Point"}
}