{
  "type": "Feature",
  "properties": {
    "addr:full":"421 Columbia St E New Westminster BC V3L 3X3",
    "addr:housenumber":"421",
    "addr:postcode":"v3l 3x3",
    "addr:street":"Columbia St E",
    "iso:country":"CA",
    "sg:address":"421 Columbia St E",
    "sg:city":"New Westminster",
    "sg:classifiers":[
        {
            "category":"Bars & Pubs",
            "type":"Food & Drink"
        }
    ],
    "sg:phone":"+1 604 521 1144",
    "sg:postcode":"V3L 3X3",
    "sg:province":"BC",
    "wof:name":"Fireside Pub",
    "wof:placetype":"venue"
},
  "geometry": {"coordinates":[-122.892982,49.229027],"type":"Point"}
}