{
  "type": "Feature",
  "properties": {
    "iso:country":"CA",
    "sg:address":"710 15th Ave E",
    "sg:city":"Prince Albert",
    "sg:classifiers":[
        {
            "category":"Food & Beverages",
            "subcategory":"Groceries & Convenience Stores",
            "type":"Retail Goods"
        }
    ],
    "sg:phone":"+1 306 922 0101",
    "sg:postcode":"S6V 7A4",
    "sg:province":"SK",
    "wof:name":"Mac's Convenience Stores Ltd",
    "wof:placetype":"venue"
},
  "geometry": {"coordinates":[-105.706596374,53.2024841309],"type":"Point"}
}