{
  "type": "Feature",
  "properties": {
    "iso:country":"CA",
    "sg:address":"25241 Fraser Hwy",
    "sg:city":"Aldergrove",
    "sg:classifiers":[
        {
            "category":"Recreation",
            "type":"Entertainment"
        }
    ],
    "sg:phone":"+1 604 857 0098",
    "sg:postcode":"V4W 1Z9",
    "sg:province":"BC",
    "sg:tags":[
        "stable"
    ],
    "wof:name":"Windsor Stables",
    "wof:placetype":"venue"
},
  "geometry": {"coordinates":[-122.492721558,49.059551239],"type":"Point"}
}