{
  "type": "Feature",
  "properties": {
    "addr:full":"1620 Boul Trudel E Saint-Boniface-DE-Shawinigan QC G0X 2L0",
    "addr:housenumber":"1620",
    "addr:postcode":"g0x 2l0",
    "addr:street":"Boul Trudel E Saint-Boniface-De-Shawinigan",
    "iso:country":"CA",
    "sg:address":"1620 Boul Trudel E",
    "sg:city":"Saint-Boniface-DE-Shawinigan",
    "sg:classifiers":[
        {
            "category":"Autos & Motor Vehicles",
            "subcategory":"Fuel & Gas Station",
            "type":"Retail Goods"
        }
    ],
    "sg:phone":"+1 819 535 3373",
    "sg:postcode":"G0X 2L0",
    "sg:province":"QC",
    "sg:tags":[
        "oil"
    ],
    "wof:name":"Garage Mich Station-Svc Enr",
    "wof:placetype":"venue"
},
  "geometry": {"coordinates":[-72.8117523193,46.5232696533],"type":"Point"}
}