{
  "type": "Feature",
  "properties": {
    "addr:full":"2220 Rue Lapierre Lasalle QC H8N 2N1",
    "addr:housenumber":"2220",
    "addr:postcode":"h8n 2n1",
    "addr:street":"Rue Lapierre",
    "iso:country":"CA",
    "sg:address":"2220 Rue Lapierre",
    "sg:city":"Lasalle",
    "sg:classifiers":[
        {
            "category":"Bars & Pubs",
            "type":"Food & Drink"
        }
    ],
    "sg:phone":"+1 514 367 1065",
    "sg:postcode":"H8N 2N1",
    "sg:province":"QC",
    "sg:tags":[
        "lounge",
        "cocktail"
    ],
    "wof:name":"Bar Le Petit Mene",
    "wof:placetype":"venue"
},
  "geometry": {"coordinates":[-73.622559,45.439453],"type":"Point"}
}