{
  "type": "Feature",
  "properties": {
    "addr:full":"703 East Main St Welland ON L3B 3Y5",
    "addr:housenumber":"703",
    "addr:postcode":"l3b 3y5",
    "addr:street":"East Main St",
    "iso:country":"CA",
    "sg:address":"703 East Main St",
    "sg:city":"Welland",
    "sg:classifiers":[
        {
            "category":"Insurance",
            "subcategory":"Insurance Agent",
            "type":"Services"
        }
    ],
    "sg:phone":"+1 905 734 9764",
    "sg:postcode":"L3B 3Y5",
    "sg:province":"ON",
    "wof:name":"Arthur Boulanger Insurance",
    "wof:placetype":"venue"
},
  "geometry": {"coordinates":[-79.23310089109999,42.9933776855],"type":"Point"}
}