{
  "type": "Feature",
  "properties": {
    "iso:country":"CA",
    "sg:address":"116 Weston Ave E",
    "sg:city":"Maidstone",
    "sg:classifiers":[
        {
            "category":"Autos & Motor Vehicles",
            "subcategory":"Auto Supplies",
            "type":"Retail Goods"
        }
    ],
    "sg:phone":"+1 306 893 4522",
    "sg:postcode":"S0M 1M0",
    "sg:province":"SK",
    "sg:tags":[
        "tire"
    ],
    "wof:name":"Rhinehart Tire",
    "wof:placetype":"venue"
},
  "geometry": {"coordinates":[-109.296607971,53.0874595642],"type":"Point"}
}