{
  "type": "Feature",
  "properties": {
    "addr:full":"Hull QC J8X 1P3",
    "addr:postcode":"j8x 1p3",
    "iso:country":"CA",
    "sg:city":"Hull",
    "sg:classifiers":[
        {
            "category":"Social Services",
            "type":"Services"
        }
    ],
    "sg:phone":"+1 819 778 0173",
    "sg:postcode":"J8X 1P3",
    "sg:province":"QC",
    "sg:tags":[
        "organization",
        "welfare"
    ],
    "wof:name":"Soupe Populaire DE Hull Inc",
    "wof:placetype":"venue"
},
  "geometry": {"coordinates":[-75.722488,45.43195],"type":"Point"}
}