{
  "type": "Feature",
  "properties": {
    "addr:full":"North York ON M3B 2T5",
    "addr:postcode":"m3b 2t5",
    "iso:country":"CA",
    "sg:city":"North York",
    "sg:classifiers":[
        {
            "category":"Real Estate",
            "subcategory":"Developer",
            "type":"Services"
        }
    ],
    "sg:phone":"+1 416 733 2202",
    "sg:postcode":"M3B 2T5",
    "sg:province":"ON",
    "wof:name":"Kerbel Group",
    "wof:placetype":"venue"
},
  "geometry": {"coordinates":[-79.35311900000001,43.75679],"type":"Point"}
}