{
  "type": "Feature",
  "properties": {
    "addr:full":"608 Courtney St Victoria BC V8W 1B6",
    "addr:housenumber":"608",
    "addr:postcode":"v8w 1b6",
    "addr:street":"Courtney St",
    "iso:country":"CA",
    "sg:address":"608 Courtney St",
    "sg:city":"Victoria",
    "sg:classifiers":[
        {
            "category":"Shopping",
            "subcategory":"Jewelry",
            "type":"Retail Goods"
        }
    ],
    "sg:phone":"+1 250 388 5162",
    "sg:postcode":"V8W 1B6",
    "sg:province":"BC",
    "sg:tags":[
        "designer"
    ],
    "wof:name":"Soleil Jewelers",
    "wof:placetype":"venue"
},
  "geometry": {"coordinates":[-123.367614746,48.42370224],"type":"Point"}
}