{
  "type": "Feature",
  "properties": {
    "iso:country":"CA",
    "sg:address":"36 Main St",
    "sg:city":"Catalina",
    "sg:classifiers":[
        {
            "category":"Home & Garden",
            "subcategory":"Furniture",
            "type":"Retail Goods"
        }
    ],
    "sg:phone":"+1 709 469 2940",
    "sg:postcode":"A0C 1J0",
    "sg:province":"NL",
    "wof:name":"Catalina Home Furnishings",
    "wof:placetype":"venue"
},
  "geometry": {"coordinates":[-53.077618,48.517845],"type":"Point"}
}