{
  "type": "Feature",
  "properties": {
    "addr:full":"9808 Baseline Rd Dresden ON N0P 1M0",
    "addr:housenumber":"9808",
    "addr:postcode":"n0p 1m0",
    "addr:street":"Baseline Rd",
    "iso:country":"CA",
    "sg:address":"9808 Baseline Rd",
    "sg:city":"Dresden",
    "sg:classifiers":[
        {
            "category":"Freight",
            "type":"Transportation"
        }
    ],
    "sg:phone":"+1 519 683 6668",
    "sg:postcode":"N0P 1M0",
    "sg:province":"ON",
    "sg:tags":[
        "mover",
        "hauling"
    ],
    "wof:name":"Marchand Truck & Float",
    "wof:placetype":"venue"
},
  "geometry": {"coordinates":[-82.179642,42.58952],"type":"Point"}
}