{
  "type": "Feature",
  "properties": {
    "addr:full":"161 Court St S Thunder Bay ON P7B 2X7",
    "addr:housenumber":"161",
    "addr:postcode":"p7b 2x7",
    "addr:street":"Court St S Thunder",
    "iso:country":"CA",
    "sg:address":"161 Court St S",
    "sg:city":"Thunder Bay",
    "sg:classifiers":[
        {
            "category":"Food & Beverages",
            "subcategory":"Groceries & Convenience Stores",
            "type":"Retail Goods"
        }
    ],
    "sg:phone":"+1 807 345 3947",
    "sg:postcode":"P7B 2X7",
    "sg:province":"ON",
    "sg:tags":[
        "grocer"
    ],
    "wof:name":"Renco Foods",
    "wof:placetype":"venue"
},
  "geometry": {"coordinates":[-89.227554,48.430668],"type":"Point"}
}