{
  "type": "Feature",
  "properties": {
    "addr:full":"Quill Lake SK S0A 3E0",
    "addr:postcode":"s0a 3e0",
    "addr:street":"Quill Lake",
    "iso:country":"CA",
    "sg:city":"Quill Lake",
    "sg:classifiers":[
        {
            "category":"Organizations",
            "subcategory":"Religious Organization",
            "type":"Services"
        }
    ],
    "sg:phone":"+1 306 383 2321",
    "sg:postcode":"S0A 3E0",
    "sg:province":"SK",
    "sg:tags":[
        "church"
    ],
    "wof:name":"United Church of Canada",
    "wof:placetype":"venue"
},
  "geometry": {"coordinates":[-104.256981,52.069935],"type":"Point"}
}