{
  "type": "Feature",
  "properties": {
    "addr:full":"701 Columbia St New Westminster BC V3M 1B1",
    "addr:housenumber":"701",
    "addr:postcode":"v3m 1b1",
    "addr:street":"Columbia",
    "iso:country":"CA",
    "sg:address":"701 Columbia St",
    "sg:city":"New Westminster",
    "sg:classifiers":[
        {
            "category":"Shopping",
            "subcategory":"Clothing, Apparel, & Fashions",
            "type":"Retail Goods"
        }
    ],
    "sg:phone":"+1 604 521 8433",
    "sg:postcode":"V3M 1B1",
    "sg:province":"BC",
    "sg:tags":[
        "shop",
        "bridal"
    ],
    "wof:name":"Bridal Gallery",
    "wof:placetype":"venue"
},
  "geometry": {"coordinates":[-122.909896851,49.2021598816],"type":"Point"}
}