{
  "type": "Feature",
  "properties": {
    "addr:full":"Brampton ON L6W 1T4",
    "addr:postcode":"l6w 1t4",
    "iso:country":"CA",
    "sg:city":"Brampton",
    "sg:classifiers":[
        {
            "category":"Manufacturing",
            "subcategory":"Rubber & Plastics",
            "type":"Manufacturing & Wholesale Goods"
        }
    ],
    "sg:phone":"+1 905 454 0016",
    "sg:postcode":"L6W 1T4",
    "sg:province":"ON",
    "sg:tags":[
        "mold",
        "maker"
    ],
    "wof:name":"Frescott Plastics Inc",
    "wof:placetype":"venue"
},
  "geometry": {"coordinates":[-79.7372512817,43.6909179688],"type":"Point"}
}