{
  "type": "Feature",
  "properties": {
    "iso:country":"CA",
    "sg:address":"21 Dundas St W",
    "sg:city":"Napanee",
    "sg:classifiers":[
        {
            "category":"Personal",
            "subcategory":"Beauty Salon",
            "type":"Services"
        }
    ],
    "sg:phone":"+1 613 354 9991",
    "sg:postcode":"K7R 1Z3",
    "sg:province":"ON",
    "wof:name":"Thecla's Style Salon",
    "wof:placetype":"venue"
},
  "geometry": {"coordinates":[-76.951302,44.247051],"type":"Point"}
}