{
  "type": "Feature",
  "properties": {
    "addr:full":"21283 Lougheed Hwy Maple Ridge BC V2X 2R6",
    "addr:housenumber":"21283",
    "addr:postcode":"v2x 2r6",
    "addr:street":"Lougheed Hwy",
    "iso:country":"CA",
    "sg:address":"21283 Lougheed Hwy",
    "sg:city":"Maple Ridge",
    "sg:classifiers":[
        {
            "category":"Autos & Motor Vehicles",
            "subcategory":"Automobile Sales",
            "type":"Retail Goods"
        }
    ],
    "sg:phone":"+1 604 466 4224",
    "sg:postcode":"V2X 2R6",
    "sg:province":"BC",
    "sg:tags":[
        "car",
        "dealer"
    ],
    "wof:name":"Igm Auto Sales",
    "wof:placetype":"venue"
},
  "geometry": {"coordinates":[-122.631073,49.217224],"type":"Point"}
}