{
  "type": "Feature",
  "properties": {
    "addr:full":"6910 Av Wilderton Montreal QC H3S 2M5",
    "addr:housenumber":"6910",
    "addr:postcode":"h3s 2m5",
    "addr:street":"Av Wilderton",
    "iso:country":"CA",
    "sg:address":"6910 Av Wilderton",
    "sg:city":"Montreal",
    "sg:classifiers":[
        {
            "category":"Food & Beverages",
            "subcategory":"Groceries & Convenience Stores",
            "type":"Retail Goods"
        }
    ],
    "sg:phone":"+1 514 733 7371",
    "sg:postcode":"H3S 2M5",
    "sg:province":"QC",
    "sg:tags":[
        "grocer"
    ],
    "wof:name":"Depanneur Wilderton",
    "wof:placetype":"venue"
},
  "geometry": {"coordinates":[-73.6304779053,45.5130195618],"type":"Point"}
}