{
  "type": "Feature",
  "properties": {
    "addr:full":"61 Rue Saint-Jean-Baptiste Baie-Saint-Paul QC G3Z 1M3",
    "addr:housenumber":"61",
    "addr:postcode":"g3z 1m3",
    "addr:street":"Rue Saint-Jean-Baptiste",
    "iso:country":"CA",
    "sg:address":"61 Rue Saint-Jean-Baptiste",
    "sg:city":"Baie-Saint-Paul",
    "sg:classifiers":[
        {
            "category":"Shopping",
            "type":"Retail Goods"
        }
    ],
    "sg:phone":"+1 418 435 2428",
    "sg:postcode":"G3Z 1M3",
    "sg:province":"QC",
    "sg:tags":[
        "art",
        "gallery",
        "dealer"
    ],
    "wof:name":"Galerie D'Art Clarence Gagnon",
    "wof:placetype":"venue"
},
  "geometry": {"coordinates":[-70.507385,47.442932],"type":"Point"}
}