{
  "type": "Feature",
  "properties": {
    "addr:full":"8004 152C Ave NW Edmonton AB T5C 3L8",
    "addr:housenumber":"8004",
    "addr:postcode":"t5c 3l8",
    "addr:street":"152C Ave Nw",
    "iso:country":"CA",
    "sg:address":"8004 152C Ave NW",
    "sg:city":"Edmonton",
    "sg:classifiers":[
        {
            "category":"Arts & Performance",
            "subcategory":"Theater",
            "type":"Entertainment"
        }
    ],
    "sg:phone":"+1 780 457 4961",
    "sg:postcode":"T5C 3L8",
    "sg:province":"AB",
    "sg:tags":[
        "live",
        "music"
    ],
    "wof:name":"Ultra Sound Music",
    "wof:placetype":"venue"
},
  "geometry": {"coordinates":[-113.46482849100001,53.6154708862],"type":"Point"}
}