{
  "type": "Feature",
  "properties": {
    "addr:full":"Montreal QC H3B 4L4",
    "addr:postcode":"h3b 4l4",
    "iso:country":"CA",
    "sg:city":"Montreal",
    "sg:classifiers":[
        {
            "category":"Shopping",
            "subcategory":"Shoes",
            "type":"Retail Goods"
        }
    ],
    "sg:phone":"+1 514 879 1633",
    "sg:postcode":"H3B 4L4",
    "sg:province":"QC",
    "wof:name":"Zenobie Inc",
    "wof:placetype":"venue"
},
  "geometry": {"coordinates":[-73.5646438599,45.5007400513],"type":"Point"}
}