{
  "type": "Feature",
  "properties": {
    "addr:full":"Burnaby BC V5C 2J3",
    "addr:postcode":"v5c 2j3",
    "iso:country":"CA",
    "sg:city":"Burnaby",
    "sg:classifiers":[
        {
            "category":"Food & Beverages",
            "subcategory":"Groceries & Convenience Stores",
            "type":"Retail Goods"
        }
    ],
    "sg:phone":"+1 604 294 1140",
    "sg:postcode":"V5C 2J3",
    "sg:province":"BC",
    "sg:tags":[
        "grocer"
    ],
    "wof:name":"Stop 'N Go",
    "wof:placetype":"venue"
},
  "geometry": {"coordinates":[-123.01250457800001,49.2811927795],"type":"Point"}
}