{
  "type": "Feature",
  "properties": {
    "addr:full":"197 Ottawa St S Kitchener ON N2G 3T3",
    "addr:housenumber":"197",
    "addr:postcode":"n2g 3t3",
    "addr:street":"Ottawa St S",
    "iso:country":"CA",
    "sg:address":"197 Ottawa St S",
    "sg:city":"Kitchener",
    "sg:classifiers":[
        {
            "category":"Retail",
            "subcategory":"Animal Services",
            "type":"Services"
        }
    ],
    "sg:phone":"+1 519 749 0344",
    "sg:postcode":"N2G 3T3",
    "sg:province":"ON",
    "sg:tags":[
        "pet",
        "grooming",
        "washing"
    ],
    "wof:name":"Clipper's Pet Grooming",
    "wof:placetype":"venue"
},
  "geometry": {"coordinates":[-80.4764099121,43.437210083],"type":"Point"}
}