{
  "type": "Feature",
  "properties": {
    "iso:country":"CA",
    "sg:city":"Toronto",
    "sg:classifiers":[
        {
            "category":"Personal",
            "subcategory":"Shoe Repair & Shine",
            "type":"Services"
        }
    ],
    "sg:phone":"+1 416 593 7463",
    "sg:postcode":"M5V 3C7",
    "sg:province":"ON",
    "sg:tags":[
        "repairing",
        "boot"
    ],
    "wof:name":"It's A Shoe Repair",
    "wof:placetype":"venue"
},
  "geometry": {"coordinates":[-79.38603973390001,43.6460723877],"type":"Point"}
}