{
  "type": "Feature",
  "properties": {
    "addr:full":"157 Coldwater Rd W Orillia ON L3V 3L7",
    "addr:housenumber":"157",
    "addr:postcode":"l3v 3l7",
    "addr:street":"Coldwater Rd W",
    "iso:country":"CA",
    "sg:address":"157 Coldwater Rd W",
    "sg:city":"Orillia",
    "sg:classifiers":[
        {
            "category":"Organizations",
            "subcategory":"Religious Organization",
            "type":"Services"
        }
    ],
    "sg:phone":"+1 705 326 3284",
    "sg:postcode":"L3V 3L7",
    "sg:province":"ON",
    "sg:tags":[
        "church"
    ],
    "wof:name":"Salvation Army",
    "wof:placetype":"venue"
},
  "geometry": {"coordinates":[-79.4293746948,44.6090621948],"type":"Point"}
}