{
  "type": "Feature",
  "properties": {
    "addr:full":"6940 Av Papineau Montreal QC H2G 2X7",
    "addr:housenumber":"6940",
    "addr:postcode":"h2g 2x7",
    "addr:street":"Av Papineau",
    "iso:country":"CA",
    "sg:address":"6940 Av Papineau",
    "sg:city":"Montreal",
    "sg:classifiers":[
        {
            "category":"Shopping",
            "subcategory":"Pharmacy",
            "type":"Retail Goods"
        }
    ],
    "sg:phone":"+1 514 729 1828",
    "sg:postcode":"H2G 2X7",
    "sg:province":"QC",
    "wof:name":"Jean Coutu Pharmacie",
    "wof:placetype":"venue"
},
  "geometry": {"coordinates":[-73.60346199999999,45.546162],"type":"Point"}
}