{
  "type": "Feature",
  "properties": {
    "addr:full":"1971 Queen St E Toronto ON M4L 1H9",
    "addr:housenumber":"1971",
    "addr:postcode":"m4l 1h9",
    "addr:street":"Queen St E",
    "iso:country":"CA",
    "sg:address":"1971 Queen St E",
    "sg:city":"Toronto",
    "sg:classifiers":[
        {
            "category":"Health Services",
            "subcategory":"Doctor",
            "type":"Services"
        }
    ],
    "sg:phone":"+1 416 691 6453",
    "sg:postcode":"M4L 1H9",
    "sg:province":"ON",
    "sg:tags":[
        "dentist"
    ],
    "wof:name":"Gueli, Diego DDS",
    "wof:placetype":"venue"
},
  "geometry": {"coordinates":[-79.301125,43.669659],"type":"Point"}
}