{
  "type": "Feature",
  "properties": {
    "addr:full":"467 Sherritt St Lynn Lake MB R0B 0W0",
    "addr:housenumber":"467",
    "addr:postcode":"r0b 0w0",
    "addr:street":"Sherritt St",
    "iso:country":"CA",
    "sg:address":"467 Sherritt St",
    "sg:city":"Lynn Lake",
    "sg:classifiers":[
        {
            "category":"Organizations",
            "subcategory":"Professional Association",
            "type":"Services"
        }
    ],
    "sg:phone":"+1 204 356 2238",
    "sg:postcode":"R0B 0W0",
    "sg:province":"MB",
    "sg:tags":[
        "club"
    ],
    "wof:name":"Royal Canadian Legion",
    "wof:placetype":"venue"
},
  "geometry": {"coordinates":[-101.048935,56.851471],"type":"Point"}
}