{
  "type": "Feature",
  "properties": {
    "iso:country":"CA",
    "sg:address":"255 Rue Benjamin-Hudon",
    "sg:city":"Saint-Laurent",
    "sg:classifiers":[
        {
            "category":"Wholesale",
            "subcategory":"Construction Materials",
            "type":"Manufacturing & Wholesale Goods"
        }
    ],
    "sg:phone":"+1 514 331 9533",
    "sg:postcode":"H4N 1J3",
    "sg:province":"QC",
    "sg:tags":[
        "building",
        "plywood",
        "veneer"
    ],
    "wof:name":"Materiaux Industriels Gordon",
    "wof:placetype":"venue"
},
  "geometry": {"coordinates":[-73.6583023071,45.5248260498],"type":"Point"}
}