{
  "type": "Feature",
  "properties": {
    "addr:full":"218 Rue Des Negociants Rimouski QC G5M 1B6",
    "addr:housenumber":"218",
    "addr:postcode":"g5m 1b6",
    "addr:street":"Rue Des Negociants",
    "iso:country":"CA",
    "sg:address":"218 Rue Des Negociants",
    "sg:city":"Rimouski",
    "sg:classifiers":[
        {
            "category":"Restaurant",
            "type":"Food & Drink"
        }
    ],
    "sg:phone":"+1 418 722 3778",
    "sg:postcode":"G5M 1B6",
    "sg:province":"QC",
    "sg:tags":[
        "parlor",
        "ice",
        "cream"
    ],
    "wof:name":"Distribution Carol Roussel",
    "wof:placetype":"venue"
},
  "geometry": {"coordinates":[-68.502655,48.464195],"type":"Point"}
}