{
  "type": "Feature",
  "properties": {
    "addr:full":"236 Hibiscus Crt Newmarket ON L3Y 5K9",
    "addr:housenumber":"236",
    "addr:postcode":"l3y 5k9",
    "addr:street":"Hibiscus Crt",
    "iso:country":"CA",
    "sg:address":"236 Hibiscus Crt",
    "sg:city":"Newmarket",
    "sg:classifiers":[
        {
            "category":"Home & Garden",
            "subcategory":"Building Materials",
            "type":"Retail Goods"
        }
    ],
    "sg:phone":"+1 905 895 1379",
    "sg:postcode":"L3Y 5K9",
    "sg:province":"ON",
    "sg:tags":[
        "windows",
        "improvement"
    ],
    "wof:name":"East Side Windows & Doors",
    "wof:placetype":"venue"
},
  "geometry": {"coordinates":[-79.445427,44.07111],"type":"Point"}
}