{
  "type": "Feature",
  "properties": {
    "addr:full":"1919 Highfield Cres SE Calgary AB T2G 5M1",
    "addr:housenumber":"1919",
    "addr:postcode":"t2g 5m1",
    "addr:street":"Highfield Cres Se",
    "iso:country":"CA",
    "sg:address":"1919 Highfield Cres SE",
    "sg:city":"Calgary",
    "sg:classifiers":[
        {
            "category":"Building & Trades",
            "subcategory":"Plumbing",
            "type":"Services"
        }
    ],
    "sg:phone":"+1 403 243 2822",
    "sg:postcode":"T2G 5M1",
    "sg:province":"AB",
    "sg:tags":[
        "cooling",
        "computer",
        "rooms",
        "tower"
    ],
    "wof:name":"Western Air & Power Ltd",
    "wof:placetype":"venue"
},
  "geometry": {"coordinates":[-114.043678,51.011581],"type":"Point"}
}