{
  "type": "Feature",
  "properties": {
    "addr:full":"4725 Whispering Willow Dr Navan ON K4B 1J1",
    "addr:housenumber":"4725",
    "addr:postcode":"k4b 1j1",
    "addr:street":"Whispering Willow Dr",
    "iso:country":"CA",
    "sg:address":"4725 Whispering Willow Dr",
    "sg:city":"Navan",
    "sg:classifiers":[
        {
            "category":"Recreation",
            "type":"Entertainment"
        }
    ],
    "sg:phone":"+1 613 835 4444",
    "sg:postcode":"K4B 1J1",
    "sg:province":"ON",
    "sg:tags":[
        "course",
        "golf"
    ],
    "wof:name":"Bearbrook Golf Club",
    "wof:placetype":"venue"
},
  "geometry": {"coordinates":[-75.426491,45.42046],"type":"Point"}
}