{
  "type": "Feature",
  "properties": {
    "iso:country":"CA",
    "sg:address":"613 Boul Sainte-Foy",
    "sg:city":"Longueuil",
    "sg:classifiers":[
        {
            "category":"Autos & Motor Vehicles",
            "subcategory":"Auto Supplies",
            "type":"Retail Goods"
        }
    ],
    "sg:phone":"+1 450 677 6777",
    "sg:postcode":"J4J 1Y8",
    "sg:province":"QC",
    "sg:tags":[
        "tire"
    ],
    "wof:name":"Pneus Ouellette",
    "wof:placetype":"venue"
},
  "geometry": {"coordinates":[-73.493431,45.52494],"type":"Point"}
}