{
  "type": "Feature",
  "properties": {
    "addr:full":"369 Spokane St Kimberley BC V1A 2E7",
    "addr:housenumber":"369",
    "addr:postcode":"v1a 2e7",
    "addr:street":"Spokane St",
    "iso:country":"CA",
    "sg:address":"369 Spokane St",
    "sg:city":"Kimberley",
    "sg:classifiers":[
        {
            "category":"Personal",
            "subcategory":"Beauty Salon",
            "type":"Services"
        }
    ],
    "sg:phone":"+1 250 427 7514",
    "sg:postcode":"V1A 2E7",
    "sg:province":"BC",
    "wof:name":"Head Pins",
    "wof:placetype":"venue"
},
  "geometry": {"coordinates":[-115.98181200000001,49.685398],"type":"Point"}
}