{
  "type": "Feature",
  "properties": {
    "addr:full":"86572 Lucknow Line Lucknow ON N0G 2H0",
    "addr:housenumber":"86572",
    "addr:postcode":"n0g 2h0",
    "addr:street":"Lucknow Line",
    "iso:country":"CA",
    "sg:address":"86572 Lucknow Line",
    "sg:city":"Lucknow",
    "sg:classifiers":[
        {
            "category":"Manufacturing",
            "subcategory":"Tools & Machinery",
            "type":"Manufacturing & Wholesale Goods"
        }
    ],
    "sg:phone":"+1 519 529 3820",
    "sg:postcode":"N0G 2H0",
    "sg:province":"ON",
    "sg:tags":[
        "farm",
        "equipment"
    ],
    "wof:name":"Maitland Valley Agri Systems",
    "wof:placetype":"venue"
},
  "geometry": {"coordinates":[-81.51606750489999,43.9613037109],"type":"Point"}
}