{
  "type": "Feature",
  "properties": {
    "addr:full":"375 Banks Rd Kelowna BC V1X 6A2",
    "addr:housenumber":"375",
    "addr:postcode":"v1x 6a2",
    "addr:street":"Banks Rd",
    "iso:country":"CA",
    "sg:address":"375 Banks Rd",
    "sg:city":"Kelowna",
    "sg:classifiers":[
        {
            "category":"Wholesale",
            "subcategory":"Auto Parts",
            "type":"Manufacturing & Wholesale Goods"
        }
    ],
    "sg:phone":"+1 250 762 5441",
    "sg:postcode":"V1X 6A2",
    "sg:province":"BC",
    "sg:tags":[
        "body",
        "automobile",
        "shop"
    ],
    "wof:name":"White & Peters Ltd",
    "wof:placetype":"venue"
},
  "geometry": {"coordinates":[-119.424057,49.885586],"type":"Point"}
}