{
  "type": "Feature",
  "properties": {
    "iso:country":"CA",
    "sg:address":"10669 Boul Pie-Ix",
    "sg:city":"Montreal-Nord",
    "sg:classifiers":[
        {
            "category":"Health Services",
            "subcategory":"Optometrist",
            "type":"Services"
        }
    ],
    "sg:phone":"+1 514 321 2412",
    "sg:postcode":"H1H 4A3",
    "sg:province":"QC",
    "wof:name":"Greiche & Scaff Optometristes",
    "wof:placetype":"venue"
},
  "geometry": {"coordinates":[-73.635017,45.58902],"type":"Point"}
}