{
  "type": "Feature",
  "properties": {
    "iso:country":"CA",
    "sg:address":"648 Finch Ave E",
    "sg:city":"North York",
    "sg:classifiers":[
        {
            "category":"Restaurant",
            "type":"Food & Drink"
        }
    ],
    "sg:phone":"+1 416 730 1080",
    "sg:postcode":"M2K 2E6",
    "sg:province":"ON",
    "wof:name":"Cafe Maxim's Patisserie",
    "wof:placetype":"venue"
},
  "geometry": {"coordinates":[-79.385895,43.786549],"type":"Point"}
}