{
  "type": "Feature",
  "properties": {
    "addr:full":"13 Abbott St Peterview NL A0H 1Y0",
    "addr:housenumber":"13",
    "addr:postcode":"a0h 1y0",
    "addr:street":"Abbott St",
    "iso:country":"CA",
    "sg:address":"13 Abbott St",
    "sg:city":"Peterview",
    "sg:classifiers":[
        {
            "category":"Food & Beverages",
            "subcategory":"Groceries & Convenience Stores",
            "type":"Retail Goods"
        }
    ],
    "sg:phone":"+1 709 257 3312",
    "sg:postcode":"A0H 1Y0",
    "sg:province":"NL",
    "wof:name":"Mr B's Variety",
    "wof:placetype":"venue"
},
  "geometry": {"coordinates":[-55.3474273682,49.1233024597],"type":"Point"}
}