{
  "type": "Feature",
  "properties": {
    "addr:full":"5488 Ch DE LA Cote-Saint-Luc Montreal QC H3X 2C7",
    "addr:housenumber":"5488",
    "addr:postcode":"h3x 2c7",
    "addr:street":"Ch De La Cote-Saint-Luc",
    "iso:country":"CA",
    "sg:address":"5488 Ch DE LA Cote-Saint-Luc",
    "sg:city":"Montreal",
    "sg:classifiers":[
        {
            "category":"Restaurant",
            "type":"Food & Drink"
        }
    ],
    "sg:phone":"+1 514 484 5555",
    "sg:postcode":"H3X 2C7",
    "sg:province":"QC",
    "wof:name":"Domino's Pizza",
    "wof:placetype":"venue"
},
  "geometry": {"coordinates":[-73.6258773804,45.4788780212],"type":"Point"}
}