{
  "type": "Feature",
  "properties": {
    "addr:full":"PO Box 457 Mclennan AB T0H 2L0",
    "addr:housenumber":"po",
    "addr:postcode":"t0h 2l0",
    "addr:street":"Box 457",
    "iso:country":"CA",
    "sg:address":"PO Box 457",
    "sg:city":"Mclennan",
    "sg:classifiers":[
        {
            "category":"Organizations",
            "subcategory":"Religious Organization",
            "type":"Services"
        }
    ],
    "sg:phone":"+1 403 324 3745",
    "sg:postcode":"T0H 2L0",
    "sg:province":"AB",
    "sg:tags":[
        "church"
    ],
    "wof:name":"St Pauls Anglican Church",
    "wof:placetype":"venue"
},
  "geometry": {"coordinates":[-116.891281128,55.7115440369],"type":"Point"}
}