{
  "type": "Feature",
  "properties": {
    "addr:full":"1019 Rue DE Lanaudiere Joliette QC J6E 3N7",
    "addr:housenumber":"1019",
    "addr:postcode":"j6e 3n7",
    "addr:street":"Rue De Lanaudiere",
    "iso:country":"CA",
    "sg:address":"1019 Rue DE Lanaudiere",
    "sg:city":"Joliette",
    "sg:classifiers":[
        {
            "category":"Shopping",
            "subcategory":"Computers & Home Electronics",
            "type":"Retail Goods"
        }
    ],
    "sg:phone":"+1 450 753 7664",
    "sg:postcode":"J6E 3N7",
    "sg:province":"QC",
    "sg:tags":[
        "game",
        "video"
    ],
    "wof:name":"Jeux Express",
    "wof:placetype":"venue"
},
  "geometry": {"coordinates":[-73.44609800000001,46.016815],"type":"Point"}
}