{
  "type": "Feature",
  "properties": {
    "addr:full":"7025 Ch Kildare Cote Saint-Luc QC H4W 1C1",
    "addr:postcode":"7025;h4w 1c1",
    "addr:street":"Ch Kildare Cote",
    "iso:country":"CA",
    "sg:address":"7025 Ch Kildare",
    "sg:city":"Cote Saint-Luc",
    "sg:classifiers":[
        {
            "category":"Food & Beverages",
            "subcategory":"Groceries & Convenience Stores",
            "type":"Retail Goods"
        }
    ],
    "sg:phone":"+1 514 481 0365",
    "sg:postcode":"H4W 1C1",
    "sg:province":"QC",
    "sg:tags":[
        "grocer"
    ],
    "wof:name":"Caldwell Provisions Inc",
    "wof:placetype":"venue"
},
  "geometry": {"coordinates":[-73.66507,45.47084],"type":"Point"}
}