{
  "type": "Feature",
  "properties": {
    "iso:country":"CA",
    "sg:city":"Mississauga",
    "sg:classifiers":[
        {
            "category":"Professional",
            "subcategory":"Art Services",
            "type":"Services"
        }
    ],
    "sg:phone":"+1 905 602 8112",
    "sg:postcode":"L4W 4M2",
    "sg:province":"ON",
    "sg:tags":[
        "graphic",
        "printer",
        "designer"
    ],
    "wof:name":"Danice Professional Svc",
    "wof:placetype":"venue"
},
  "geometry": {"coordinates":[-79.637276,43.625401],"type":"Point"}
}