{
  "type": "Feature",
  "properties": {
    "addr:full":"34 1/2 Ainslie St S Cambridge ON N1R 3K1",
    "addr:housenumber":"1 / 2",
    "addr:postcode":"n1r 3k1",
    "addr:street":"34;Ainslie St S",
    "iso:country":"CA",
    "sg:address":"34 1/2 Ainslie St S",
    "sg:city":"Cambridge",
    "sg:classifiers":[
        {
            "category":"Shopping",
            "subcategory":"Clothing, Apparel, & Fashions",
            "type":"Retail Goods"
        }
    ],
    "sg:phone":"+1 519 624 8883",
    "sg:postcode":"N1R 3K1",
    "sg:province":"ON",
    "wof:name":"Country Roads Ladies Wear",
    "wof:placetype":"venue"
},
  "geometry": {"coordinates":[-80.3139419556,43.357673645],"type":"Point"}
}