{
  "type": "Feature",
  "properties": {
    "addr:full":"Port Hardy BC V0N 2P0",
    "addr:postcode":"v0n 2p0",
    "iso:country":"CA",
    "sg:city":"Port Hardy",
    "sg:classifiers":[
        {
            "category":"Banks & Credit Unions",
            "subcategory":"Investment Brokerage",
            "type":"Services"
        }
    ],
    "sg:phone":"+1 250 949 2310",
    "sg:postcode":"V0N 2P0",
    "sg:province":"BC",
    "sg:tags":[
        "consultant",
        "planning",
        "financial"
    ],
    "wof:name":"Investors Group",
    "wof:placetype":"venue"
},
  "geometry": {"coordinates":[-127.409424,50.689877],"type":"Point"}
}