{
  "type": "Feature",
  "properties": {
    "iso:country":"CA",
    "sg:address":"1 World Dr",
    "sg:city":"Mississauga",
    "sg:classifiers":[
        {
            "category":"Organizations",
            "subcategory":"Non-profit Organization",
            "type":"Services"
        }
    ],
    "sg:phone":"+1 905 565 6100",
    "sg:postcode":"L5T 2Y4",
    "sg:province":"ON",
    "sg:tags":[
        "charitable",
        "institution"
    ],
    "wof:name":"World Vision Canada",
    "wof:placetype":"venue"
},
  "geometry": {"coordinates":[-79.68895721440001,43.6336593628],"type":"Point"}
}