{
  "type": "Feature",
  "properties": {
    "iso:country":"CA",
    "sg:address":"485 Ch Madawaska",
    "sg:city":"Grand Falls",
    "sg:classifiers":[
        {
            "category":"Retail",
            "subcategory":"Car Wash",
            "type":"Services"
        }
    ],
    "sg:phone":"+1 506 473 3080",
    "sg:postcode":"E3Y 1A3",
    "sg:province":"NB",
    "sg:tags":[
        "polishing",
        "washing"
    ],
    "wof:name":"Julie's Car Wash",
    "wof:placetype":"venue"
},
  "geometry": {"coordinates":[-67.7539596558,47.0587348938],"type":"Point"}
}