{
  "type": "Feature",
  "properties": {
    "addr:full":"Nelson BC V1L 4G3",
    "addr:postcode":"bc v1l 4g3",
    "iso:country":"CA",
    "sg:city":"Nelson",
    "sg:classifiers":[
        {
            "category":"Recreation",
            "type":"Entertainment"
        }
    ],
    "sg:phone":"+1 250 352 2227",
    "sg:postcode":"V1L 4G3",
    "sg:province":"BC",
    "sg:tags":[
        "instruction",
        "gymnastic"
    ],
    "wof:name":"Glacier Gymnastics Club",
    "wof:placetype":"venue"
},
  "geometry": {"coordinates":[-117.291778565,49.4941177368],"type":"Point"}
}