{
  "type": "Feature",
  "properties": {
    "addr:full":"8 Simpson Hughenden AB T0B 2E0",
    "addr:housenumber":"8",
    "addr:postcode":"t0b 2e0",
    "addr:street":"Simpson",
    "iso:country":"CA",
    "sg:address":"8 Simpson",
    "sg:city":"Hughenden",
    "sg:classifiers":[
        {
            "category":"Wholesale",
            "subcategory":"Scrap",
            "type":"Manufacturing & Wholesale Goods"
        }
    ],
    "sg:phone":"+1 780 856 2700",
    "sg:postcode":"T0B 2E0",
    "sg:province":"AB",
    "sg:tags":[
        "recycling",
        "can",
        "bottle",
        "depot"
    ],
    "wof:name":"Hughenden Bottle Depot",
    "wof:placetype":"venue"
},
  "geometry": {"coordinates":[-110.96693399999999,52.510075],"type":"Point"}
}