{
  "type": "Feature",
  "properties": {
    "addr:full":"490 111 Rte Vassan QC J0Y 2R0",
    "addr:housenumber":"111",
    "addr:postcode":"j0y 2r0",
    "addr:street":"Rte Vassan",
    "iso:country":"CA",
    "sg:address":"490 111 Rte",
    "sg:city":"Vassan",
    "sg:classifiers":[
        {
            "category":"Food & Beverages",
            "subcategory":"Groceries & Convenience Stores",
            "type":"Retail Goods"
        }
    ],
    "sg:phone":"+1 819 824 3146",
    "sg:postcode":"J0Y 2R0",
    "sg:province":"QC",
    "sg:tags":[
        "grocer"
    ],
    "wof:name":"Epicerie Vassan Enr",
    "wof:placetype":"venue"
},
  "geometry": {"coordinates":[-77.927246,48.229183],"type":"Point"}
}