{
  "type": "Feature",
  "properties": {
    "addr:full":"250 Gibbs Rd W Kelowna BC V1X 2W3",
    "addr:housenumber":"250",
    "addr:postcode":"v1x 2w3",
    "addr:street":"Gibbs Rd",
    "iso:country":"CA",
    "sg:address":"250 Gibbs Rd W",
    "sg:city":"Kelowna",
    "sg:classifiers":[
        {
            "category":"Organizations",
            "subcategory":"Religious Organization",
            "type":"Services"
        }
    ],
    "sg:phone":"+1 250 765 0671",
    "sg:postcode":"V1X 2W3",
    "sg:province":"BC",
    "sg:tags":[
        "church"
    ],
    "wof:name":"Faith Elcic",
    "wof:placetype":"venue"
},
  "geometry": {"coordinates":[-119.382126,49.890999],"type":"Point"}
}