{
  "type": "Feature",
  "properties": {
    "addr:full":"Collingwood ON L9Y 3Y9",
    "addr:postcode":"l9y 3y9",
    "iso:country":"CA",
    "sg:city":"Collingwood",
    "sg:classifiers":[
        {
            "category":"Building & Trades",
            "subcategory":"Construction",
            "type":"Services"
        }
    ],
    "sg:phone":"+1 705 445 5077",
    "sg:postcode":"L9Y 3Y9",
    "sg:province":"ON",
    "sg:tags":[
        "roofing",
        "contractor"
    ],
    "wof:name":"J & J Woods Roofing",
    "wof:placetype":"venue"
},
  "geometry": {"coordinates":[-80.21682699999999,44.499889],"type":"Point"}
}