{
  "type": "Feature",
  "properties": {
    "iso:country":"CA",
    "sg:address":"5402 Victoria Dr",
    "sg:city":"Vancouver",
    "sg:classifiers":[
        {
            "category":"Government",
            "subcategory":"Fire Station",
            "type":"Public Place"
        }
    ],
    "sg:phone":"+1 604 665 6020",
    "sg:postcode":"V5P 3V8",
    "sg:province":"BC",
    "sg:tags":[
        "department"
    ],
    "wof:name":"Vancouver Firehall",
    "wof:placetype":"venue"
},
  "geometry": {"coordinates":[-123.065322876,49.2358856201],"type":"Point"}
}