{
  "type": "Feature",
  "properties": {
    "addr:full":"208 Rochester St Ottawa ON K1R 7M8",
    "addr:housenumber":"208",
    "addr:postcode":"k1r 7m8",
    "addr:street":"Rochester St",
    "iso:country":"CA",
    "sg:address":"208 Rochester St",
    "sg:city":"Ottawa",
    "sg:classifiers":[
        {
            "category":"Home & Garden",
            "subcategory":"Building Materials",
            "type":"Retail Goods"
        }
    ],
    "sg:phone":"+1 613 233 6268",
    "sg:postcode":"K1R 7M8",
    "sg:province":"ON",
    "sg:tags":[
        "paint"
    ],
    "wof:name":"Colourlux",
    "wof:placetype":"venue"
},
  "geometry": {"coordinates":[-75.71105194090001,45.4071655273],"type":"Point"}
}