{
  "type": "Feature",
  "properties": {
    "addr:full":"477 Paul St Dieppe NB E1A 4X5",
    "addr:housenumber":"477",
    "addr:postcode":"e1a 4x5",
    "addr:street":"Paul St",
    "iso:country":"CA",
    "sg:address":"477 Paul St",
    "sg:city":"Dieppe",
    "sg:classifiers":[
        {
            "category":"Shopping",
            "subcategory":"Clothing, Apparel, & Fashions",
            "type":"Retail Goods"
        }
    ],
    "sg:phone":"+1 506 862 0818",
    "sg:postcode":"E1A 4X5",
    "sg:province":"NB",
    "wof:name":"Ricki's",
    "wof:placetype":"venue"
},
  "geometry": {"coordinates":[-64.761002,46.098885],"type":"Point"}
}