{
  "type": "Feature",
  "properties": {
    "addr:full":"6305 Northam Dr Mississauga ON L4V 1W9",
    "addr:housenumber":"6305",
    "addr:postcode":"l4v 1w9",
    "addr:street":"Northam Dr",
    "iso:country":"CA",
    "sg:address":"6305 Northam Dr",
    "sg:city":"Mississauga",
    "sg:classifiers":[
        {
            "category":"Shopping",
            "type":"Retail Goods"
        }
    ],
    "sg:phone":"+1 905 405 0234",
    "sg:postcode":"L4V 1W9",
    "sg:province":"ON",
    "sg:tags":[
        "equipment",
        "telephone",
        "supply"
    ],
    "wof:name":"Isys Canada Inc",
    "wof:placetype":"venue"
},
  "geometry": {"coordinates":[-79.61586800000001,43.695423],"type":"Point"}
}