{
  "type": "Feature",
  "properties": {
    "iso:country":"CA",
    "sg:address":"501 Kennedy Dr",
    "sg:city":"Esterhazy",
    "sg:classifiers":[
        {
            "category":"Education",
            "subcategory":"School",
            "type":"Public Place"
        }
    ],
    "sg:phone":"+1 306 745 2878",
    "sg:postcode":"S0A 0X0",
    "sg:province":"SK",
    "wof:name":"Parkland Regional College",
    "wof:placetype":"venue"
},
  "geometry": {"coordinates":[-102.06043243400001,50.6559906006],"type":"Point"}
}