{
  "type": "Feature",
  "properties": {
    "addr:full":"213 Rue Saint-Joseph E Quebec QC G1K 3B1",
    "addr:housenumber":"213",
    "addr:postcode":"g1k 3b1",
    "addr:street":"Rue Saint-Joseph E",
    "iso:country":"CA",
    "sg:address":"213 Rue Saint-Joseph E",
    "sg:city":"Quebec",
    "sg:classifiers":[
        {
            "category":"Shopping",
            "subcategory":"Books",
            "type":"Retail Goods"
        }
    ],
    "sg:phone":"+1 418 525 6402",
    "sg:postcode":"G1K 3B1",
    "sg:province":"QC",
    "sg:tags":[
        "dealer"
    ],
    "wof:name":"Comptoir Du Livre Enr",
    "wof:placetype":"venue"
},
  "geometry": {"coordinates":[-71.2279281616,46.8129348755],"type":"Point"}
}