{
  "type": "Feature",
  "properties": {
    "addr:full":"Saint-Hubert QC J4T 3R5",
    "addr:postcode":"j4t 3r5",
    "iso:country":"CA",
    "sg:city":"Saint-Hubert",
    "sg:classifiers":[
        {
            "category":"Health Services",
            "subcategory":"Doctor",
            "type":"Services"
        }
    ],
    "sg:phone":"+1 450 443 8070",
    "sg:postcode":"J4T 3R5",
    "sg:province":"QC",
    "sg:tags":[
        "dentist"
    ],
    "wof:name":"Centre DE LA Rive Sud",
    "wof:placetype":"venue"
},
  "geometry": {"coordinates":[-73.4693908691,45.4903488159],"type":"Point"}
}