{
  "type": "Feature",
  "properties": {
    "addr:full":"10 Rue Boulet Princeville QC G6L 4M1",
    "addr:housenumber":"10",
    "addr:postcode":"g6l 4m1",
    "addr:street":"Rue Boulet",
    "iso:country":"CA",
    "sg:address":"10 Rue Boulet",
    "sg:city":"Princeville",
    "sg:classifiers":[
        {
            "category":"Manufacturing",
            "subcategory":"Tools & Machinery",
            "type":"Manufacturing & Wholesale Goods"
        }
    ],
    "sg:phone":"+1 819 364 2022",
    "sg:postcode":"G6L 4M1",
    "sg:province":"QC",
    "sg:tags":[
        "equipment",
        "system",
        "automation"
    ],
    "wof:name":"Robovic Inc",
    "wof:placetype":"venue"
},
  "geometry": {"coordinates":[-71.8889465332,46.1567611694],"type":"Point"}
}