{
  "type": "Feature",
  "properties": {
    "addr:full":"448 Campbell St Cobourg ON K9A 4C4",
    "addr:housenumber":"448",
    "addr:postcode":"k9a 4c4",
    "addr:street":"Campbell St",
    "iso:country":"CA",
    "sg:address":"448 Campbell St",
    "sg:city":"Cobourg",
    "sg:classifiers":[
        {
            "category":"Building & Trades",
            "subcategory":"Equipment Rental",
            "type":"Services"
        }
    ],
    "sg:phone":"+1 905 372 1453",
    "sg:postcode":"K9A 4C4",
    "sg:province":"ON",
    "sg:tags":[
        "rug",
        "carpet"
    ],
    "wof:name":"Royal Rug Renting",
    "wof:placetype":"venue"
},
  "geometry": {"coordinates":[-78.15646362299999,43.967502594],"type":"Point"}
}