{
  "type": "Feature",
  "properties": {
    "addr:full":"2020 Westview Dr North Vancouver BC V7M 3B2",
    "addr:housenumber":"2020",
    "addr:postcode":"v7m 3b2",
    "addr:street":"Westview Dr",
    "iso:country":"CA",
    "sg:address":"2020 Westview Dr",
    "sg:city":"North Vancouver",
    "sg:classifiers":[
        {
            "category":"Retail",
            "subcategory":"Portrait Studio",
            "type":"Services"
        }
    ],
    "sg:phone":"+1 604 987 6600",
    "sg:postcode":"V7M 3B2",
    "sg:province":"BC",
    "sg:tags":[
        "photographer"
    ],
    "wof:name":"Robert Kwong Photography",
    "wof:placetype":"venue"
},
  "geometry": {"coordinates":[-123.089225769,49.327709198],"type":"Point"}
}