{
  "type": "Feature",
  "properties": {
    "addr:full":"1140 Mayland Dr NE Calgary AB T2E 6C8",
    "addr:housenumber":"1140",
    "addr:postcode":"t2e 6c8",
    "addr:street":"Mayland Dr Ne",
    "iso:country":"CA",
    "sg:address":"1140 Mayland Dr NE",
    "sg:city":"Calgary",
    "sg:classifiers":[
        {
            "category":"Education",
            "subcategory":"School",
            "type":"Public Place"
        }
    ],
    "sg:phone":"+1 403 277 8397",
    "sg:postcode":"T2E 6C8",
    "sg:province":"AB",
    "wof:name":"St Clement Elementary School",
    "wof:placetype":"venue"
},
  "geometry": {"coordinates":[-114.010895,51.063976],"type":"Point"}
}