{
  "type": "Feature",
  "properties": {
    "addr:full":"713 9th Ave E Owen Sound ON N4K 3E6",
    "addr:housenumber":"713",
    "addr:postcode":"n4k 3e6",
    "addr:street":"9Th Ave E",
    "iso:country":"CA",
    "sg:address":"713 9th Ave E",
    "sg:city":"Owen Sound",
    "sg:classifiers":[
        {
            "category":"Travel",
            "subcategory":"Hotels & Motels",
            "type":"Entertainment"
        }
    ],
    "sg:phone":"+1 519 371 2011",
    "sg:postcode":"N4K 3E6",
    "sg:province":"ON",
    "wof:name":"Diamond Motor Inn",
    "wof:placetype":"venue"
},
  "geometry": {"coordinates":[-80.926895,44.564133],"type":"Point"}
}