{
  "type": "Feature",
  "properties": {
    "addr:full":"10 Principale Nedelec QC J0Z 2Z0",
    "addr:housenumber":"10",
    "addr:postcode":"j0z 2z0",
    "addr:street":"Principale Nedelec",
    "iso:country":"CA",
    "sg:address":"10 Principale",
    "sg:city":"Nedelec",
    "sg:classifiers":[
        {
            "category":"Recreation",
            "type":"Entertainment"
        }
    ],
    "sg:phone":"+1 819 784 3351",
    "sg:postcode":"J0Z 2Z0",
    "sg:province":"QC",
    "sg:tags":[
        "center",
        "government"
    ],
    "wof:name":"Nedelec Centre DE Loisirs",
    "wof:placetype":"venue"
},
  "geometry": {"coordinates":[-79.4247055054,47.6877822876],"type":"Point"}
}