{
  "type": "Feature",
  "properties": {
    "addr:full":"2765 Chestnut St Jordan Station ON L0R 1S0",
    "addr:housenumber":"2765",
    "addr:postcode":"l0r 1s0",
    "addr:street":"Chestnut St",
    "iso:country":"CA",
    "sg:address":"2765 Chestnut St",
    "sg:city":"Jordan Station",
    "sg:classifiers":[
        {
            "category":"Professional",
            "subcategory":"Business Services",
            "type":"Services"
        }
    ],
    "sg:phone":"+1 905 562 4984",
    "sg:postcode":"L0R 1S0",
    "sg:province":"ON",
    "sg:tags":[
        "interior",
        "consultant",
        "design",
        "decorator"
    ],
    "wof:name":"Michael Vh Interior Design",
    "wof:placetype":"venue"
},
  "geometry": {"coordinates":[-79.361671,43.164696],"type":"Point"}
}