{
  "type": "Feature",
  "properties": {
    "iso:country":"CA",
    "sg:address":"715 Front St",
    "sg:city":"Keewatin",
    "sg:classifiers":[
        {
            "category":"Personal",
            "subcategory":"Beauty Salon",
            "type":"Services"
        }
    ],
    "sg:phone":"+1 807 547 2635",
    "sg:postcode":"P0X 1C0",
    "sg:province":"ON",
    "wof:name":"House of Hair Design",
    "wof:placetype":"venue"
},
  "geometry": {"coordinates":[-94.5541610718,49.7618789673],"type":"Point"}
}