{
  "type": "Feature",
  "properties": {
    "addr:full":"Lamont AB T0B 2R0",
    "addr:postcode":"t0b 2r0",
    "iso:country":"CA",
    "sg:city":"Lamont",
    "sg:classifiers":[
        {
            "category":"Insurance",
            "subcategory":"Insurance Agent",
            "type":"Services"
        }
    ],
    "sg:phone":"+1 780 895 2256",
    "sg:postcode":"T0B 2R0",
    "sg:province":"AB",
    "wof:name":"Elk Island Insurance Ltd",
    "wof:placetype":"venue"
},
  "geometry": {"coordinates":[-112.781051636,53.7610626221],"type":"Point"}
}