{
  "type": "Feature",
  "properties": {
    "iso:country":"CA",
    "sg:address":"480 Rue Foch",
    "sg:city":"Granby",
    "sg:classifiers":[
        {
            "category":"Building & Trades",
            "subcategory":"Construction",
            "type":"Services"
        }
    ],
    "sg:phone":"+1 450 777 2431",
    "sg:postcode":"J2G 6C9",
    "sg:province":"QC",
    "sg:tags":[
        "janitor",
        "steam"
    ],
    "wof:name":"Entretiens F & L Enr",
    "wof:placetype":"venue"
},
  "geometry": {"coordinates":[-72.73491668699999,45.4195556641],"type":"Point"}
}