{
  "type": "Feature",
  "properties": {
    "addr:full":"2702 Stone Cres Ottawa ON K2H 6Z1",
    "addr:housenumber":"2702",
    "addr:postcode":"k2h 6z1",
    "addr:street":"Stone Cres",
    "iso:country":"CA",
    "sg:address":"2702 Stone Cres",
    "sg:city":"Ottawa",
    "sg:classifiers":[
        {
            "category":"Building & Trades",
            "subcategory":"Construction",
            "type":"Services"
        }
    ],
    "sg:phone":"+1 613 761 7629",
    "sg:postcode":"K2H 6Z1",
    "sg:province":"ON",
    "sg:tags":[
        "cabinet",
        "maker",
        "woodworker"
    ],
    "wof:name":"From the Cherry Tree Custom",
    "wof:placetype":"venue"
},
  "geometry": {"coordinates":[-75.7941436768,45.3414459229],"type":"Point"}
}