{
  "type": "Feature",
  "properties": {
    "addr:full":"Hwy 45 Lucky Lake SK S0L 1Z0",
    "addr:postcode":"s0l 1z0",
    "addr:street":"Hwy 45",
    "iso:country":"CA",
    "sg:address":"Hwy 45",
    "sg:city":"Lucky Lake",
    "sg:classifiers":[
        {
            "category":"Real Estate",
            "subcategory":"Real Estate Agent",
            "type":"Services"
        }
    ],
    "sg:phone":"+1 306 858 2660",
    "sg:postcode":"S0L 1Z0",
    "sg:province":"SK",
    "sg:tags":[
        "cooperative"
    ],
    "wof:name":"Tullis CO-OP",
    "wof:placetype":"venue"
},
  "geometry": {"coordinates":[-107.136841,50.985905],"type":"Point"}
}