{
  "type": "Feature",
  "properties": {
    "iso:country":"CA",
    "sg:address":"1 Henderson Dr",
    "sg:city":"Aurora",
    "sg:classifiers":[
        {
            "category":"Health Services",
            "subcategory":"Doctor",
            "type":"Services"
        }
    ],
    "sg:phone":"+1 905 713 6800",
    "sg:postcode":"L4G 4J7",
    "sg:province":"ON",
    "sg:tags":[
        "physician",
        "surgeon"
    ],
    "wof:name":"Hindocha, Sandeep MD",
    "wof:placetype":"venue"
},
  "geometry": {"coordinates":[-79.4639129639,43.9836006165],"type":"Point"}
}