{
  "type": "Feature",
  "properties": {
    "addr:full":"1025 Boul Saint-Laurent Montreal QC H2Z 1J4",
    "addr:housenumber":"1025",
    "addr:postcode":"h2z 1j4",
    "addr:street":"Boul Saint-Laurent",
    "iso:country":"CA",
    "sg:address":"1025 Boul Saint-Laurent",
    "sg:city":"Montreal",
    "sg:classifiers":[
        {
            "category":"Food & Beverages",
            "subcategory":"Fruits & Vegetables",
            "type":"Retail Goods"
        }
    ],
    "sg:phone":"+1 514 878 8080",
    "sg:postcode":"H2Z 1J4",
    "sg:province":"QC",
    "sg:tags":[
        "farm",
        "market"
    ],
    "wof:name":"Marche Pappap",
    "wof:placetype":"venue"
},
  "geometry": {"coordinates":[-73.55940246580001,45.5080223083],"type":"Point"}
}