{
  "type": "Feature",
  "properties": {
    "addr:full":"1030 Birch Blvd Dwight ON P0A 1H0",
    "addr:housenumber":"1030",
    "addr:postcode":"p0a 1h0",
    "addr:street":"Birch Blvd",
    "iso:country":"CA",
    "sg:address":"1030 Birch Blvd",
    "sg:city":"Dwight",
    "sg:classifiers":[
        {
            "category":"Professional",
            "subcategory":"Management & Consulting",
            "type":"Services"
        }
    ],
    "sg:phone":"+1 705 635 3729",
    "sg:postcode":"P0A 1H0",
    "sg:province":"ON",
    "sg:tags":[
        "consultant",
        "business"
    ],
    "wof:name":"Pct Intl",
    "wof:placetype":"venue"
},
  "geometry": {"coordinates":[-79.05210099999999,45.257656],"type":"Point"}
}