{
  "type": "Feature",
  "properties": {
    "iso:country":"CA",
    "sg:address":"9807 71 St NW",
    "sg:city":"Edmonton",
    "sg:classifiers":[
        {
            "category":"Government",
            "subcategory":"Police Station",
            "type":"Public Place"
        }
    ],
    "sg:phone":"+1 780 496 8516",
    "sg:postcode":"T6A 2T8",
    "sg:province":"AB",
    "sg:tags":[
        "department"
    ],
    "wof:name":"Ottewell Station",
    "wof:placetype":"venue"
},
  "geometry": {"coordinates":[-113.436637878,53.5378952026],"type":"Point"}
}