{
  "type": "Feature",
  "properties": {
    "addr:full":"Pilot Mound MB R0G 1P0",
    "addr:postcode":"r0g 1p0",
    "iso:country":"CA",
    "sg:city":"Pilot Mound",
    "sg:classifiers":[
        {
            "category":"Shopping",
            "subcategory":"Florist",
            "type":"Retail Goods"
        }
    ],
    "sg:phone":"+1 204 825 2145",
    "sg:postcode":"R0G 1P0",
    "sg:province":"MB",
    "wof:name":"Smith's Florists",
    "wof:placetype":"venue"
},
  "geometry": {"coordinates":[-98.8960723877,49.202381134],"type":"Point"}
}