{
  "type": "Feature",
  "properties": {
    "addr:full":"445 Hodder Ave Thunder Bay ON P7A 1V2",
    "addr:housenumber":"445",
    "addr:postcode":"p7a 1v2",
    "addr:street":"Hodder Ave",
    "iso:country":"CA",
    "sg:address":"445 Hodder Ave",
    "sg:city":"Thunder Bay",
    "sg:classifiers":[
        {
            "category":"Food & Beverages",
            "subcategory":"Groceries & Convenience Stores",
            "type":"Retail Goods"
        }
    ],
    "sg:phone":"+1 807 683 8741",
    "sg:postcode":"P7A 1V2",
    "sg:province":"ON",
    "wof:name":"Hodder Ave Grocery",
    "wof:placetype":"venue"
},
  "geometry": {"coordinates":[-89.18235799999999,48.467312],"type":"Point"}
}