{
  "type": "Feature",
  "properties": {
    "iso:country":"CA",
    "sg:city":"Ottawa",
    "sg:classifiers":[
        {
            "category":"Personal",
            "subcategory":"Tanning Parlor",
            "type":"Services"
        }
    ],
    "sg:phone":"+1 613 232 6454",
    "sg:postcode":"K2P 0L6",
    "sg:province":"ON",
    "sg:tags":[
        "salon"
    ],
    "wof:name":"Supertan Suntan Ctr",
    "wof:placetype":"venue"
},
  "geometry": {"coordinates":[-75.68994903559999,45.4170150757],"type":"Point"}
}