{
  "type": "Feature",
  "properties": {
    "addr:full":"4310 Ontario St Beamsville ON L0R 1B0",
    "addr:housenumber":"4310",
    "addr:postcode":"l0r 1b0",
    "addr:street":"Ontario St",
    "iso:country":"CA",
    "sg:address":"4310 Ontario St",
    "sg:city":"Beamsville",
    "sg:classifiers":[
        {
            "category":"Banks & Credit Unions",
            "subcategory":"Bank",
            "type":"Services"
        }
    ],
    "sg:phone":"+1 905 563 8296",
    "sg:postcode":"L0R 1B0",
    "sg:province":"ON",
    "wof:name":"Royal Bank Financial Group",
    "wof:placetype":"venue"
},
  "geometry": {"coordinates":[-79.4764175415,43.1661643982],"type":"Point"}
}