{
  "type": "Feature",
  "properties": {
    "iso:country":"CA",
    "sg:address":"33 Princess St # 410",
    "sg:city":"Leamington",
    "sg:classifiers":[
        {
            "category":"Banks & Credit Unions",
            "subcategory":"Bank",
            "type":"Services"
        }
    ],
    "sg:phone":"+1 519 326 7777",
    "sg:postcode":"N8H 5C5",
    "sg:province":"ON",
    "sg:tags":[
        "loan",
        "real estate"
    ],
    "wof:name":"Mortgage Intelligence",
    "wof:placetype":"venue"
},
  "geometry": {"coordinates":[-82.5985412598,42.0517463684],"type":"Point"}
}