{
  "type": "Feature",
  "properties": {
    "addr:full":"SE 7-10-14W Carberry MB R0K 0H0",
    "addr:postcode":"r0k 0h0",
    "addr:street":"Se 7-10-14W",
    "iso:country":"CA",
    "sg:address":"SE 7-10-14W",
    "sg:city":"Carberry",
    "sg:classifiers":[
        {
            "category":"Recreation",
            "type":"Entertainment"
        }
    ],
    "sg:phone":"+1 204 834 2325",
    "sg:postcode":"R0K 0H0",
    "sg:province":"MB",
    "sg:tags":[
        "course",
        "golf"
    ],
    "wof:name":"Sandhills Golf & Country Club",
    "wof:placetype":"venue"
},
  "geometry": {"coordinates":[-99.357849,49.871185],"type":"Point"}
}