{
  "type": "Feature",
  "properties": {
    "iso:country":"CA",
    "sg:city":"Peterborough",
    "sg:classifiers":[
        {
            "category":"Building & Trades",
            "subcategory":"Equipment Rental",
            "type":"Services"
        }
    ],
    "sg:phone":"+1 705 742 0060",
    "sg:postcode":"K9J 6X8",
    "sg:province":"ON",
    "sg:tags":[
        "yard"
    ],
    "wof:name":"Renters Choice Equipment Ltd",
    "wof:placetype":"venue"
},
  "geometry": {"coordinates":[-78.27658081049999,44.2953796387],"type":"Point"}
}