{
  "type": "Feature",
  "properties": {
    "addr:full":"471 Irwin St Nanaimo BC V9R 4X9",
    "addr:housenumber":"471",
    "addr:postcode":"v9r 4x9",
    "addr:street":"Irwin St",
    "iso:country":"CA",
    "sg:address":"471 Irwin St",
    "sg:city":"Nanaimo",
    "sg:classifiers":[
        {
            "category":"Organizations",
            "subcategory":"Religious Organization",
            "type":"Services"
        }
    ],
    "sg:phone":"+1 250 754 7866",
    "sg:postcode":"V9R 4X9",
    "sg:province":"BC",
    "sg:tags":[
        "church"
    ],
    "wof:name":"Nanaimo Native Victory Chapel",
    "wof:placetype":"venue"
},
  "geometry": {"coordinates":[-123.930908203,49.1541938782],"type":"Point"}
}