{
  "type": "Feature",
  "properties": {
    "addr:full":"129 Newcastle Blvd Miramichi NB E1V 2L9",
    "addr:housenumber":"129",
    "addr:postcode":"e1v 2l9",
    "addr:street":"Newcastle Blvd",
    "iso:country":"CA",
    "sg:address":"129 Newcastle Blvd",
    "sg:city":"Miramichi",
    "sg:classifiers":[
        {
            "category":"Health Services",
            "subcategory":"Doctor",
            "type":"Services"
        }
    ],
    "sg:phone":"+1 506 622 8922",
    "sg:postcode":"E1V 2L9",
    "sg:province":"NB",
    "sg:tags":[
        "dentist"
    ],
    "wof:name":"Degrace, Hugues DDS",
    "wof:placetype":"venue"
},
  "geometry": {"coordinates":[-65.5652008057,47.0017623901],"type":"Point"}
}