{
  "type": "Feature",
  "properties": {
    "addr:full":"44 Hawthorne St Yarmouth NS B5A 1M7",
    "addr:housenumber":"44",
    "addr:postcode":"b5a 1m7",
    "addr:street":"Hawthorne St",
    "iso:country":"CA",
    "sg:address":"44 Hawthorne St",
    "sg:city":"Yarmouth",
    "sg:classifiers":[
        {
            "category":"Shopping",
            "subcategory":"Bicycles & Sporting Goods",
            "type":"Retail Goods"
        }
    ],
    "sg:phone":"+1 902 742 9283",
    "sg:postcode":"B5A 1M7",
    "sg:province":"NS",
    "sg:tags":[
        "tackle",
        "fishing"
    ],
    "wof:name":"Imp Group Ltd",
    "wof:placetype":"venue"
},
  "geometry": {"coordinates":[-66.120819,43.834949],"type":"Point"}
}