{
  "type": "Feature",
  "properties": {
    "iso:country":"CA",
    "sg:address":"1801 Dundas St E",
    "sg:city":"Whitby",
    "sg:classifiers":[
        {
            "category":"Shopping",
            "subcategory":"Crafts & Fabrics",
            "type":"Retail Goods"
        }
    ],
    "sg:phone":"+1 905 721 9152",
    "sg:postcode":"L1N 7C5",
    "sg:province":"ON",
    "sg:tags":[
        "shop"
    ],
    "wof:name":"Fabricland Distributors CO",
    "wof:placetype":"venue"
},
  "geometry": {"coordinates":[-78.904251,43.88829],"type":"Point"}
}