{
  "type": "Feature",
  "properties": {
    "addr:full":"2250 2nd Ave Whitehorse YT Y1A 1C8",
    "addr:housenumber":"2250",
    "addr:postcode":"y1a 1c8",
    "addr:street":"2Nd Ave",
    "iso:country":"CA",
    "sg:address":"2250 2nd Ave",
    "sg:city":"Whitehorse",
    "sg:classifiers":[
        {
            "category":"Wholesale",
            "subcategory":"Machinery & Supplies",
            "type":"Manufacturing & Wholesale Goods"
        }
    ],
    "sg:phone":"+1 867 667 6660",
    "sg:postcode":"Y1A 1C8",
    "sg:province":"YT",
    "sg:tags":[
        "equipment",
        "industrial"
    ],
    "wof:name":"Acklands-Grainger",
    "wof:placetype":"venue"
},
  "geometry": {"coordinates":[-135.06179800000001,60.729496],"type":"Point"}
}