{
  "type": "Feature",
  "properties": {
    "addr:full":"7 Strathearn Ave Brampton ON L6T 4P1",
    "addr:housenumber":"7",
    "addr:postcode":"l6t 4p1",
    "addr:street":"Strathearn Ave",
    "iso:country":"CA",
    "sg:address":"7 Strathearn Ave",
    "sg:city":"Brampton",
    "sg:classifiers":[
        {
            "category":"Freight",
            "type":"Transportation"
        }
    ],
    "sg:phone":"+1 905 790 8510",
    "sg:postcode":"L6T 4P1",
    "sg:province":"ON",
    "sg:tags":[
        "trucking"
    ],
    "wof:name":"Conor Transportation Inc",
    "wof:placetype":"venue"
},
  "geometry": {"coordinates":[-79.695053,43.6931],"type":"Point"}
}