{
  "type": "Feature",
  "properties": {
    "addr:full":"1001 Park Ave Moosomin SK S0G 3N0",
    "addr:housenumber":"1001",
    "addr:postcode":"s0g 3n0",
    "addr:street":"Park Ave",
    "iso:country":"CA",
    "sg:address":"1001 Park Ave",
    "sg:city":"Moosomin",
    "sg:classifiers":[
        {
            "category":"Autos & Motor Vehicles",
            "subcategory":"Fuel & Gas Station",
            "type":"Retail Goods"
        }
    ],
    "sg:phone":"+1 306 435 2195",
    "sg:postcode":"S0G 3N0",
    "sg:province":"SK",
    "sg:tags":[
        "convenience",
        "oil",
        "store"
    ],
    "wof:name":"Shell Canada Products Ltd",
    "wof:placetype":"venue"
},
  "geometry": {"coordinates":[-101.6612854,50.1469535828],"type":"Point"}
}