{
  "type": "Feature",
  "properties": {
    "iso:country":"CA",
    "sg:city":"Brampton",
    "sg:classifiers":[
        {
            "category":"Shopping",
            "type":"Retail Goods"
        }
    ],
    "sg:phone":"+1 905 790 1108",
    "sg:postcode":"L6T 5B9",
    "sg:province":"ON",
    "sg:tags":[
        "pet",
        "shop"
    ],
    "wof:name":"Aquarium Depot",
    "wof:placetype":"venue"
},
  "geometry": {"coordinates":[-79.6780090332,43.7132873535],"type":"Point"}
}