{
  "type": "Feature",
  "properties": {
    "addr:full":"1 Clam Bay Rd Blubber Bay BC V0N 1E0",
    "addr:housenumber":"1",
    "addr:postcode":"v0n 1e0",
    "addr:street":"Clam Bay Rd",
    "iso:country":"CA",
    "sg:address":"1 Clam Bay Rd",
    "sg:city":"Blubber Bay",
    "sg:classifiers":[
        {
            "category":"Mining & Drilling",
            "type":"Manufacturing & Wholesale Goods"
        }
    ],
    "sg:phone":"+1 604 486 7715",
    "sg:postcode":"V0N 1E0",
    "sg:province":"BC",
    "sg:tags":[
        "limestone"
    ],
    "wof:name":"Blubber Bay Quarry",
    "wof:placetype":"venue"
},
  "geometry": {"coordinates":[-124.62303900000001,49.79533],"type":"Point"}
}