{
  "type": "Feature",
  "properties": {
    "addr:full":"Grimshaw AB T0H 1W0",
    "addr:postcode":"t0h 1w0",
    "iso:country":"CA",
    "sg:city":"Grimshaw",
    "sg:classifiers":[
        {
            "category":"Sports & Exercise",
            "subcategory":"Golf",
            "type":"Entertainment"
        }
    ],
    "sg:phone":"+1 780 332 4949",
    "sg:postcode":"T0H 1W0",
    "sg:province":"AB",
    "sg:tags":[
        "course"
    ],
    "wof:name":"Creek Golf & Country Club",
    "wof:placetype":"venue"
},
  "geometry": {"coordinates":[-117.610466003,56.1913795471],"type":"Point"}
}