{
  "type": "Feature",
  "properties": {
    "addr:full":"Winnipeg MB R3R 3P9",
    "addr:postcode":"r3r 3p9",
    "iso:country":"CA",
    "sg:city":"Winnipeg",
    "sg:classifiers":[
        {
            "category":"Restaurant",
            "type":"Food & Drink"
        }
    ],
    "sg:phone":"+1 204 889 1252",
    "sg:postcode":"R3R 3P9",
    "sg:province":"MB",
    "wof:name":"Bella Roma",
    "wof:placetype":"venue"
},
  "geometry": {"coordinates":[-97.312569,49.862858],"type":"Point"}
}