{
  "type": "Feature",
  "properties": {
    "addr:full":"9936 106 St Westlock AB T7P 2K2",
    "addr:housenumber":"9936",
    "addr:postcode":"t7p 2k2",
    "addr:street":"106 St",
    "iso:country":"CA",
    "sg:address":"9936 106 St",
    "sg:city":"Westlock",
    "sg:classifiers":[
        {
            "category":"Food & Beverages",
            "subcategory":"Specialty",
            "type":"Retail Goods"
        }
    ],
    "sg:phone":"+1 780 349 5755",
    "sg:postcode":"T7P 2K2",
    "sg:province":"AB",
    "sg:tags":[
        "health",
        "diet"
    ],
    "wof:name":"Westlock Health Foods",
    "wof:placetype":"venue"
},
  "geometry": {"coordinates":[-113.86316680900001,54.1543998718],"type":"Point"}
}