{
  "type": "Feature",
  "properties": {
    "addr:full":"958 Ch Maskinonge Boileau QC J0V 1N0",
    "addr:housenumber":"958",
    "addr:postcode":"j0v 1n0",
    "addr:street":"Ch Maskinonge Boileau",
    "iso:country":"CA",
    "sg:address":"958 Ch Maskinonge",
    "sg:city":"Boileau",
    "sg:classifiers":[
        {
            "category":"Food & Beverages",
            "subcategory":"Groceries & Convenience Stores",
            "type":"Retail Goods"
        }
    ],
    "sg:phone":"+1 819 687 9915",
    "sg:postcode":"J0V 1N0",
    "sg:province":"QC",
    "wof:name":"Depanneur Du Parc",
    "wof:placetype":"venue"
},
  "geometry": {"coordinates":[-74.77293400000001,45.901016],"type":"Point"}
}