{
  "type": "Feature",
  "properties": {
    "addr:full":"12535 1E Av # 1 Saint-Georges QC G5Y 2E4",
    "addr:housenumber":"12535",
    "addr:postcode":"g5y 2e4",
    "addr:street":"1E Av # 1",
    "iso:country":"CA",
    "sg:address":"12535 1E Av # 1",
    "sg:city":"Saint-Georges",
    "sg:classifiers":[
        {
            "category":"Shopping",
            "subcategory":"Bicycles & Sporting Goods",
            "type":"Retail Goods"
        }
    ],
    "sg:phone":"+1 418 228 2463",
    "sg:postcode":"G5Y 2E4",
    "sg:province":"QC",
    "sg:tags":[
        "work",
        "clothing"
    ],
    "wof:name":"Au Bon Mache Bernard Inc",
    "wof:placetype":"venue"
},
  "geometry": {"coordinates":[-70.67115,46.123348],"type":"Point"}
}