{
  "type": "Feature",
  "properties": {
    "addr:full":"344 Prince Albert Rd Dartmouth NS B2Y 1N6",
    "addr:housenumber":"344",
    "addr:postcode":"b2y 1n6",
    "addr:street":"Prince Albert Rd",
    "iso:country":"CA",
    "sg:address":"344 Prince Albert Rd",
    "sg:city":"Dartmouth",
    "sg:classifiers":[
        {
            "category":"Professional",
            "subcategory":"Accounting & Tax Preparation",
            "type":"Services"
        }
    ],
    "sg:phone":"+1 902 464 9300",
    "sg:postcode":"B2Y 1N6",
    "sg:province":"NS",
    "sg:tags":[
        "accountant"
    ],
    "wof:name":"Mc Neil Porter Hetu",
    "wof:placetype":"venue"
},
  "geometry": {"coordinates":[-63.548313,44.680378],"type":"Point"}
}