{
  "type": "Feature",
  "properties": {
    "addr:full":"871 10th St Hanover ON N4N 1S1",
    "addr:housenumber":"871",
    "addr:postcode":"n4n 1s1",
    "addr:street":"10Th St",
    "iso:country":"CA",
    "sg:address":"871 10th St",
    "sg:city":"Hanover",
    "sg:classifiers":[
        {
            "category":"Shopping",
            "subcategory":"Computers & Home Electronics",
            "type":"Retail Goods"
        }
    ],
    "sg:phone":"+1 519 364 1011",
    "sg:postcode":"N4N 1S1",
    "sg:province":"ON",
    "sg:tags":[
        "equipment",
        "satellite",
        "appliance"
    ],
    "wof:name":"Modern Electronics Appliances",
    "wof:placetype":"venue"
},
  "geometry": {"coordinates":[-81.00711800000001,44.155151],"type":"Point"}
}