{
  "type": "Feature",
  "properties": {
    "addr:full":"8178 Post Rd Niagara Falls ON L2H 2L3",
    "addr:housenumber":"8178",
    "addr:postcode":"l2h 2l3",
    "addr:street":"Post Rd",
    "iso:country":"CA",
    "sg:address":"8178 Post Rd",
    "sg:city":"Niagara Falls",
    "sg:classifiers":[
        {
            "category":"Recreation",
            "type":"Entertainment"
        }
    ],
    "sg:phone":"+1 905 358 6774",
    "sg:postcode":"L2H 2L3",
    "sg:province":"ON",
    "sg:tags":[
        "tours",
        "sightseeing"
    ],
    "wof:name":"Personal Tours of Niagara",
    "wof:placetype":"venue"
},
  "geometry": {"coordinates":[-79.134254,43.099506],"type":"Point"}
}