{
  "type": "Feature",
  "properties": {
    "addr:full":"700 Richmond St Chatham ON N7M 5J5",
    "addr:housenumber":"700",
    "addr:postcode":"n7m 5j5",
    "addr:street":"Richmond St",
    "iso:country":"CA",
    "sg:address":"700 Richmond St",
    "sg:city":"Chatham",
    "sg:classifiers":[
        {
            "category":"Retail",
            "subcategory":"Auto Repair",
            "type":"Services"
        }
    ],
    "sg:phone":"+1 519 352 7240",
    "sg:postcode":"N7M 5J5",
    "sg:province":"ON",
    "sg:tags":[
        "automobile",
        "painting",
        "truck"
    ],
    "wof:name":"Waycon International Trucks",
    "wof:placetype":"venue"
},
  "geometry": {"coordinates":[-82.204437,42.387325],"type":"Point"}
}