{
  "type": "Feature",
  "properties": {
    "addr:full":"687 Industrial Way Gibsons BC V0N 1V7",
    "addr:housenumber":"687",
    "addr:postcode":"v0n 1v7",
    "addr:street":"Industrial Way",
    "iso:country":"CA",
    "sg:address":"687 Industrial Way",
    "sg:city":"Gibsons",
    "sg:classifiers":[
        {
            "category":"Retail",
            "subcategory":"Repair Shop",
            "type":"Services"
        }
    ],
    "sg:phone":"+1 604 886 2292",
    "sg:postcode":"V0N 1V7",
    "sg:province":"BC",
    "sg:tags":[
        "roofing",
        "contractor",
        "welding"
    ],
    "wof:name":"Coast Sheet Metal Works Ltd",
    "wof:placetype":"venue"
},
  "geometry": {"coordinates":[-123.52835082999999,49.4079551697],"type":"Point"}
}