{
  "type": "Feature",
  "properties": {
    "addr:full":"21 2nd Ave W Letellier MB R0G 1C0",
    "addr:housenumber":"21",
    "addr:postcode":"r0g 1c0",
    "addr:street":"2Nd Ave W Letellier",
    "iso:country":"CA",
    "sg:address":"21 2nd Ave W",
    "sg:city":"Letellier",
    "sg:classifiers":[
        {
            "category":"Travel",
            "subcategory":"Hotels & Motels",
            "type":"Entertainment"
        }
    ],
    "sg:phone":"+1 204 737 2699",
    "sg:postcode":"R0G 1C0",
    "sg:province":"MB",
    "wof:name":"Prairie's Edge Motel",
    "wof:placetype":"venue"
},
  "geometry": {"coordinates":[-97.30285600000001,49.142326],"type":"Point"}
}