{
  "type": "Feature",
  "properties": {
    "addr:full":"Delta BC V4G 1L5",
    "addr:postcode":"v4g 1l5",
    "iso:country":"CA",
    "sg:city":"Delta",
    "sg:classifiers":[
        {
            "category":"Manufacturing",
            "subcategory":"Tools & Machinery",
            "type":"Manufacturing & Wholesale Goods"
        }
    ],
    "sg:phone":"+1 604 946 3188",
    "sg:postcode":"V4G 1L5",
    "sg:province":"BC",
    "sg:tags":[
        "equipment",
        "household",
        "laundry"
    ],
    "wof:name":"Dyer Equipment Sales Ltd",
    "wof:placetype":"venue"
},
  "geometry": {"coordinates":[-123.025497437,49.1363868713],"type":"Point"}
}