{
  "type": "Feature",
  "properties": {
    "addr:full":"200 Bathurst Dr Waterloo ON N2V 2L7",
    "addr:housenumber":"200",
    "addr:postcode":"n2v 2l7",
    "addr:street":"Bathurst Dr",
    "iso:country":"CA",
    "sg:address":"200 Bathurst Dr",
    "sg:city":"Waterloo",
    "sg:classifiers":[
        {
            "category":"Professional",
            "subcategory":"Management & Consulting",
            "type":"Services"
        }
    ],
    "sg:phone":"+1 519 746 6644",
    "sg:postcode":"N2V 2L7",
    "sg:province":"ON",
    "sg:tags":[
        "training",
        "sales"
    ],
    "wof:name":"Creative Options Inc",
    "wof:placetype":"venue"
},
  "geometry": {"coordinates":[-80.52886199949999,43.5122070312],"type":"Point"}
}