{
  "type": "Feature",
  "properties": {
    "addr:full":"1405 Rte DE Saint-Philippe Dubuisson QC J9P 4N7",
    "addr:housenumber":"1405",
    "addr:postcode":"j9p 4n7",
    "addr:street":"Rte De Saint-Philippe",
    "iso:country":"CA",
    "sg:address":"1405 Rte DE Saint-Philippe",
    "sg:city":"Dubuisson",
    "sg:classifiers":[
        {
            "category":"Government",
            "subcategory":"Office",
            "type":"Public Place"
        }
    ],
    "sg:phone":"+1 819 738 4881",
    "sg:postcode":"J9P 4N7",
    "sg:province":"QC",
    "sg:tags":[
        "village",
        "hall",
        "auditorium"
    ],
    "wof:name":"Maison Du Citoyen",
    "wof:placetype":"venue"
},
  "geometry": {"coordinates":[-77.947769165,48.113494873],"type":"Point"}
}