{
  "type": "Feature",
  "properties": {
    "addr:full":"1990 Boul DE Comporte LA Malbaie QC G5A 3C3",
    "addr:housenumber":"1990",
    "addr:postcode":"g5a 3c3",
    "addr:street":"Boul De Comporte",
    "iso:country":"CA",
    "sg:address":"1990 Boul DE Comporte",
    "sg:city":"LA Malbaie",
    "sg:classifiers":[
        {
            "category":"Home & Garden",
            "subcategory":"Hardware",
            "type":"Retail Goods"
        }
    ],
    "sg:phone":"+1 418 665 1267",
    "sg:postcode":"G5A 3C3",
    "sg:province":"QC",
    "sg:tags":[
        "building",
        "material"
    ],
    "wof:name":"Jean Henri & Fils Inc",
    "wof:placetype":"venue"
},
  "geometry": {"coordinates":[-70.170998,47.672813],"type":"Point"}
}