{
  "type": "Feature",
  "properties": {
    "iso:country":"CA",
    "sg:city":"Ottawa",
    "sg:classifiers":[
        {
            "category":"Professional",
            "subcategory":"Research",
            "type":"Services"
        }
    ],
    "sg:phone":"+1 613 733 5353",
    "sg:postcode":"K1G 4B8",
    "sg:province":"ON",
    "sg:tags":[
        "environmental",
        "ecological",
        "product"
    ],
    "wof:name":"Liumar Technologies Corp",
    "wof:placetype":"venue"
},
  "geometry": {"coordinates":[-75.633026,45.407555],"type":"Point"}
}