{
  "type": "Feature",
  "properties": {
    "addr:full":"1120 Clyde Crt # 4 Kingston ON K7P 2E4",
    "addr:housenumber":"1120",
    "addr:postcode":"k7p 2e4",
    "addr:street":"Clyde Crt # 4",
    "iso:country":"CA",
    "sg:address":"1120 Clyde Crt # 4",
    "sg:city":"Kingston",
    "sg:classifiers":[
        {
            "category":"Manufacturing",
            "subcategory":"Tools & Machinery",
            "type":"Manufacturing & Wholesale Goods"
        }
    ],
    "sg:phone":"+1 613 384 8884",
    "sg:postcode":"K7P 2E4",
    "sg:province":"ON",
    "sg:tags":[
        "equipment",
        "pneumatic",
        "component"
    ],
    "wof:name":"Eastern Fluid Power Inc",
    "wof:placetype":"venue"
},
  "geometry": {"coordinates":[-76.56285095210001,44.266746521],"type":"Point"}
}