{
  "type": "Feature",
  "properties": {
    "addr:full":"Victoria BC V8V 3X5",
    "addr:postcode":"v8v 3x5",
    "iso:country":"CA",
    "sg:city":"Victoria",
    "sg:classifiers":[
        {
            "category":"Health Services",
            "subcategory":"Chiropractor",
            "type":"Services"
        }
    ],
    "sg:phone":"+1 250 361 9311",
    "sg:postcode":"V8V 3X5",
    "sg:province":"BC",
    "wof:name":"Fairfield Chiropractic Office",
    "wof:placetype":"venue"
},
  "geometry": {"coordinates":[-123.35623200000001,48.414806],"type":"Point"}
}