{
  "type": "Feature",
  "properties": {
    "addr:full":"15 Victoria Rd N Guelph ON N1E 5G6",
    "addr:housenumber":"15",
    "addr:postcode":"n1e 5g6",
    "addr:street":"Victoria Rd N",
    "iso:country":"CA",
    "sg:address":"15 Victoria Rd N",
    "sg:city":"Guelph",
    "sg:classifiers":[
        {
            "category":"Shopping",
            "subcategory":"Computers & Home Electronics",
            "type":"Retail Goods"
        }
    ],
    "sg:phone":"+1 519 821 4594",
    "sg:postcode":"N1E 5G6",
    "sg:province":"ON",
    "sg:tags":[
        "equipment",
        "dealer"
    ],
    "wof:name":"Dorotech Canada",
    "wof:placetype":"venue"
},
  "geometry": {"coordinates":[-80.23049163819999,43.5568695068],"type":"Point"}
}