{
  "type": "Feature",
  "properties": {
    "addr:full":"306 132 Rte W Saint-Omer QC G0C 2Z0",
    "addr:housenumber":"132",
    "addr:postcode":"g0c 2z0",
    "addr:street":"Rte W Saint-Omer",
    "iso:country":"CA",
    "sg:address":"306 132 Rte W",
    "sg:city":"Saint-Omer",
    "sg:classifiers":[
        {
            "category":"Personal",
            "subcategory":"Beauty Salon",
            "type":"Services"
        }
    ],
    "sg:phone":"+1 418 364 7522",
    "sg:postcode":"G0C 2Z0",
    "sg:province":"QC",
    "wof:name":"Salon Sylvie Bujold",
    "wof:placetype":"venue"
},
  "geometry": {"coordinates":[-69.69001799999999,47.035435],"type":"Point"}
}