{
  "type": "Feature",
  "properties": {
    "iso:country":"CA",
    "sg:address":"723 Tecumseh Rd E",
    "sg:city":"Windsor",
    "sg:classifiers":[
        {
            "category":"Manufacturing",
            "subcategory":"Metals",
            "type":"Manufacturing & Wholesale Goods"
        }
    ],
    "sg:phone":"+1 519 972 5625",
    "sg:postcode":"N8X 2S1",
    "sg:province":"ON",
    "sg:tags":[
        "lock",
        "safe",
        "locksmith"
    ],
    "wof:name":"Better Locksmiths",
    "wof:placetype":"venue"
},
  "geometry": {"coordinates":[-83.01401519780001,42.29845047],"type":"Point"}
}