{
  "type": "Feature",
  "properties": {
    "iso:country":"CA",
    "sg:address":"3400 D'Aoust Ave",
    "sg:city":"Gloucester",
    "sg:classifiers":[
        {
            "category":"Education",
            "subcategory":"School",
            "type":"Public Place"
        }
    ],
    "sg:phone":"+1 613 521 5922",
    "sg:postcode":"K1T 1R5",
    "sg:province":"ON",
    "wof:name":"Sawmill Creek Elementary Schl",
    "wof:placetype":"venue"
},
  "geometry": {"coordinates":[-75.604683,45.427879],"type":"Point"}
}