{
  "type": "Feature",
  "properties": {
    "iso:country":"CA",
    "sg:address":"375 3rd St W",
    "sg:city":"Drumheller",
    "sg:classifiers":[
        {
            "category":"Personal",
            "subcategory":"Beauty Salon",
            "type":"Services"
        }
    ],
    "sg:phone":"+1 403 823 4284",
    "sg:postcode":"T0J 0Y0",
    "sg:province":"AB",
    "wof:name":"Bevan Scott",
    "wof:placetype":"venue"
},
  "geometry": {"coordinates":[-112.712501526,51.4632492065],"type":"Point"}
}