{
  "type": "Feature",
  "properties": {
    "addr:full":"Hudson QC J0P 1H0",
    "addr:postcode":"j0p 1h0",
    "iso:country":"CA",
    "sg:city":"Hudson",
    "sg:classifiers":[
        {
            "category":"Freight",
            "type":"Transportation"
        }
    ],
    "sg:phone":"+1 450 458 1108",
    "sg:postcode":"J0P 1H0",
    "sg:province":"QC",
    "sg:tags":[
        "trucking"
    ],
    "wof:name":"Transportation Logistics CO",
    "wof:placetype":"venue"
},
  "geometry": {"coordinates":[-74.1573104858,45.4441184998],"type":"Point"}
}