{
  "type": "Feature",
  "properties": {
    "addr:full":"Kirkland QC H9H 4B5",
    "addr:postcode":"h9h 4b5",
    "iso:country":"CA",
    "sg:city":"Kirkland",
    "sg:classifiers":[
        {
            "category":"Health Services",
            "subcategory":"Nursing And Care Facility",
            "type":"Services"
        }
    ],
    "sg:phone":"+1 514 695 1253",
    "sg:postcode":"H9H 4B5",
    "sg:province":"QC",
    "sg:tags":[
        "home",
        "retirement",
        "community"
    ],
    "wof:name":"Manoir Kirkland Sec",
    "wof:placetype":"venue"
},
  "geometry": {"coordinates":[-73.835335,45.45013],"type":"Point"}
}