{
  "type": "Feature",
  "properties": {
    "addr:full":"Hawkestone ON L0L 1T0",
    "addr:postcode":"l0l 1t0",
    "iso:country":"CA",
    "sg:city":"Hawkestone",
    "sg:classifiers":[
        {
            "category":"Home & Garden",
            "subcategory":"Furniture",
            "type":"Retail Goods"
        }
    ],
    "sg:phone":"+1 705 487 3441",
    "sg:postcode":"L0L 1T0",
    "sg:province":"ON",
    "wof:name":"Hodges Landing Country Furn",
    "wof:placetype":"venue"
},
  "geometry": {"coordinates":[-79.4906234741,44.5006790161],"type":"Point"}
}