{
  "type": "Feature",
  "properties": {
    "addr:full":"RR 1 Marystown NL A0E 2M0",
    "addr:postcode":"a0e 2m0",
    "addr:street":"Rr 1",
    "iso:country":"CA",
    "sg:address":"RR 1",
    "sg:city":"Marystown",
    "sg:classifiers":[
        {
            "category":"Shopping",
            "subcategory":"Clothing, Apparel, & Fashions",
            "type":"Retail Goods"
        }
    ],
    "sg:phone":"+1 709 279 4616",
    "sg:postcode":"A0E 2M0",
    "sg:province":"NL",
    "wof:name":"Northern Reflections",
    "wof:placetype":"venue"
},
  "geometry": {"coordinates":[-55.157001,47.16375],"type":"Point"}
}