{
  "type": "Feature",
  "properties": {
    "addr:full":"20900 Fairview Rd Thorndale ON N0M 2P0",
    "addr:housenumber":"20900",
    "addr:postcode":"n0m 2p0",
    "addr:street":"Fairview Rd",
    "iso:country":"CA",
    "sg:address":"20900 Fairview Rd",
    "sg:city":"Thorndale",
    "sg:classifiers":[
        {
            "category":"Home & Garden",
            "subcategory":"Building Materials",
            "type":"Retail Goods"
        }
    ],
    "sg:phone":"+1 519 461 0050",
    "sg:postcode":"N0M 2P0",
    "sg:province":"ON",
    "sg:tags":[
        "windows",
        "door"
    ],
    "wof:name":"Westminster Glass & Mirror Ltd",
    "wof:placetype":"venue"
},
  "geometry": {"coordinates":[-81.1200180054,43.0663337708],"type":"Point"}
}