{
  "type": "Feature",
  "properties": {
    "iso:country":"CA",
    "sg:city":"Orleans",
    "sg:classifiers":[
        {
            "category":"Social Services",
            "subcategory":"Child Care",
            "type":"Services"
        }
    ],
    "sg:phone":"+1 613 841 3535",
    "sg:postcode":"K4A 4T6",
    "sg:province":"ON",
    "wof:name":"Coccinelle Ecole DE Cumberland",
    "wof:placetype":"venue"
},
  "geometry": {"coordinates":[-75.46184539790001,45.4641151428],"type":"Point"}
}