{
  "type": "Feature",
  "properties": {
    "addr:full":"175 Main St Fredericton NB E3A 1E1",
    "addr:housenumber":"175",
    "addr:postcode":"e3a 1e1",
    "addr:street":"Main St",
    "iso:country":"CA",
    "sg:address":"175 Main St",
    "sg:city":"Fredericton",
    "sg:classifiers":[
        {
            "category":"Food & Beverages",
            "subcategory":"Groceries & Convenience Stores",
            "type":"Retail Goods"
        }
    ],
    "sg:phone":"+1 506 450 8002",
    "sg:postcode":"E3A 1E1",
    "sg:province":"NB",
    "wof:name":"Fulton Heights Ultramar",
    "wof:placetype":"venue"
},
  "geometry": {"coordinates":[-66.6527557373,45.9781608582],"type":"Point"}
}