{
  "type": "Feature",
  "properties": {
    "addr:full":"1678 Valleyview Dr Kamloops BC V2C 4B5",
    "addr:housenumber":"1678",
    "addr:postcode":"bc v2c 4b5",
    "addr:street":"Valleyview Dr",
    "iso:country":"CA",
    "sg:address":"1678 Valleyview Dr",
    "sg:city":"Kamloops",
    "sg:classifiers":[
        {
            "category":"Building & Trades",
            "subcategory":"Construction",
            "type":"Services"
        }
    ],
    "sg:phone":"+1 250 372 0095",
    "sg:postcode":"V2C 4B5",
    "sg:province":"BC",
    "sg:tags":[
        "contractor",
        "paving",
        "general"
    ],
    "wof:name":"88 Pave-Rite Ltd",
    "wof:placetype":"venue"
},
  "geometry": {"coordinates":[-120.29186248800001,50.6736412048],"type":"Point"}
}