{
  "type": "Feature",
  "properties": {
    "addr:full":"Mississauga ON L5T 1M9",
    "addr:postcode":"l5t 1m9",
    "iso:country":"CA",
    "sg:city":"Mississauga",
    "sg:classifiers":[
        {
            "category":"Manufacturing",
            "subcategory":"Apparel",
            "type":"Manufacturing & Wholesale Goods"
        }
    ],
    "sg:phone":"+1 905 565 0447",
    "sg:postcode":"L5T 1M9",
    "sg:province":"ON",
    "sg:tags":[
        "bag",
        "canvas"
    ],
    "wof:name":"Fairdeal Import & Export Ltd",
    "wof:placetype":"venue"
},
  "geometry": {"coordinates":[-79.6536941528,43.6610679626],"type":"Point"}
}