{
  "type": "Feature",
  "properties": {
    "addr:full":"1400 Whitehorse Rd North York ON M3J 3A7",
    "addr:housenumber":"1400",
    "addr:postcode":"m3j 3a7",
    "addr:street":"Whitehorse Rd",
    "iso:country":"CA",
    "sg:address":"1400 Whitehorse Rd",
    "sg:city":"North York",
    "sg:classifiers":[
        {
            "category":"Manufacturing",
            "subcategory":"Apparel",
            "type":"Manufacturing & Wholesale Goods"
        }
    ],
    "sg:phone":"+1 416 636 5900",
    "sg:postcode":"M3J 3A7",
    "sg:province":"ON",
    "sg:tags":[
        "clothing"
    ],
    "wof:name":"Caulfeild Apparel Group Ltd",
    "wof:placetype":"venue"
},
  "geometry": {"coordinates":[-79.47172500000001,43.757408],"type":"Point"}
}