{
  "type": "Feature",
  "properties": {
    "addr:full":"4400 Rue DE Salaberry # 200 Montreal QC H4J 1H4",
    "addr:housenumber":"4400",
    "addr:postcode":"h4j 1h4",
    "addr:street":"Rue De Salaberry # 200",
    "iso:country":"CA",
    "sg:address":"4400 Rue DE Salaberry # 200",
    "sg:city":"Montreal",
    "sg:classifiers":[
        {
            "category":"Health Services",
            "subcategory":"Doctor",
            "type":"Services"
        }
    ],
    "sg:phone":"+1 514 331 8300",
    "sg:postcode":"H4J 1H4",
    "sg:province":"QC",
    "sg:tags":[
        "dentist"
    ],
    "wof:name":"Pilon, Marie-Josee DDS",
    "wof:placetype":"venue"
},
  "geometry": {"coordinates":[-73.7049789429,45.53383255],"type":"Point"}
}