{
  "type": "Feature",
  "properties": {
    "addr:full":"950 Rue Jean-Talon E Montreal QC H2R 1V4",
    "addr:housenumber":"950",
    "addr:postcode":"h2r 1v4",
    "addr:street":"Rue Jean-Talon E",
    "iso:country":"CA",
    "sg:address":"950 Rue Jean-Talon E",
    "sg:city":"Montreal",
    "sg:classifiers":[
        {
            "category":"Wholesale",
            "subcategory":"Groceries",
            "type":"Manufacturing & Wholesale Goods"
        }
    ],
    "sg:phone":"+1 514 271 4767",
    "sg:postcode":"H2R 1V4",
    "sg:province":"QC",
    "sg:tags":[
        "grocer"
    ],
    "wof:name":"Bonbons Guay Inc",
    "wof:placetype":"venue"
},
  "geometry": {"coordinates":[-73.6126174927,45.5413475037],"type":"Point"}
}