{
  "type": "Feature",
  "properties": {
    "addr:full":"20404 107 Ave NW Edmonton AB T5S 1W9",
    "addr:housenumber":"20404",
    "addr:postcode":"t5s 1w9",
    "addr:street":"107 Ave Nw",
    "iso:country":"CA",
    "sg:address":"20404 107 Ave NW",
    "sg:city":"Edmonton",
    "sg:classifiers":[
        {
            "category":"Wholesale",
            "subcategory":"Machinery & Supplies",
            "type":"Manufacturing & Wholesale Goods"
        }
    ],
    "sg:phone":"+1 780 447 4473",
    "sg:postcode":"T5S 1W9",
    "sg:province":"AB",
    "sg:tags":[
        "crane",
        "derrick"
    ],
    "wof:name":"Meridian Electric Ltd",
    "wof:placetype":"venue"
},
  "geometry": {"coordinates":[-113.672783,53.551422],"type":"Point"}
}