{
  "type": "Feature",
  "properties": {
    "addr:full":"318 Ontario St St Catharines ON L2R 5L8",
    "addr:housenumber":"318",
    "addr:postcode":"l2r 5l8",
    "addr:street":"Ontario St",
    "iso:country":"CA",
    "sg:address":"318 Ontario St",
    "sg:city":"St Catharines",
    "sg:classifiers":[
        {
            "category":"Shopping",
            "subcategory":"Stationery & Office Supplies",
            "type":"Retail Goods"
        }
    ],
    "sg:phone":"+1 905 687 1603",
    "sg:postcode":"L2R 5L8",
    "sg:province":"ON",
    "sg:tags":[
        "educational",
        "material"
    ],
    "wof:name":"G A Educational Books & Toys",
    "wof:placetype":"venue"
},
  "geometry": {"coordinates":[-79.264076,43.169563],"type":"Point"}
}