{
  "type": "Feature",
  "properties": {
    "addr:full":"176 Goddard Blvd London ON N5W 5A1",
    "addr:housenumber":"176",
    "addr:postcode":"n5w 5a1",
    "addr:street":"Goddard Blvd",
    "iso:country":"CA",
    "sg:address":"176 Goddard Blvd",
    "sg:city":"London",
    "sg:classifiers":[
        {
            "category":"Retail",
            "subcategory":"Animal Services",
            "type":"Services"
        }
    ],
    "sg:phone":"+1 519 451 1881",
    "sg:postcode":"N5W 5A1",
    "sg:province":"ON",
    "sg:tags":[
        "pet",
        "grooming",
        "washing"
    ],
    "wof:name":"Carleen's Grooming",
    "wof:placetype":"venue"
},
  "geometry": {"coordinates":[-81.17630800000001,42.993607],"type":"Point"}
}