{
  "type": "Feature",
  "properties": {
    "iso:country":"CA",
    "sg:city":"Whitby",
    "sg:classifiers":[
        {
            "category":"Health Services",
            "subcategory":"Doctor",
            "type":"Services"
        }
    ],
    "sg:phone":"+1 905 571 0516",
    "sg:postcode":"L1N 7C5",
    "sg:province":"ON",
    "sg:tags":[
        "dentist"
    ],
    "wof:name":"Busman, Harmen DDS",
    "wof:placetype":"venue"
},
  "geometry": {"coordinates":[-78.904251,43.88829],"type":"Point"}
}