{
  "type": "Feature",
  "properties": {
    "iso:country":"CA",
    "sg:address":"90 Wexford Dr",
    "sg:city":"Keswick",
    "sg:classifiers":[
        {
            "category":"Arena",
            "subcategory":"Sports Club",
            "type":"Entertainment"
        }
    ],
    "sg:phone":"+1 905 476 4423",
    "sg:postcode":"L4P 3P7",
    "sg:province":"ON",
    "sg:tags":[
        "athletic",
        "fields",
        "stadium",
        "government"
    ],
    "wof:name":"Georgina Parks Arenas & Pools",
    "wof:placetype":"venue"
},
  "geometry": {"coordinates":[-79.4511642456,44.2404441833],"type":"Point"}
}