{
  "type": "Feature",
  "properties": {
    "iso:country":"CA",
    "sg:address":"115 Varty Rd",
    "sg:city":"Tweed",
    "sg:classifiers":[
        {
            "category":"Travel",
            "subcategory":"Campground",
            "type":"Entertainment"
        }
    ],
    "sg:phone":"+1 613 478 6844",
    "sg:postcode":"K0K 3J0",
    "sg:province":"ON",
    "wof:name":"Tipper's Family Campground",
    "wof:placetype":"venue"
},
  "geometry": {"coordinates":[-77.2492523193,44.5606651306],"type":"Point"}
}