{
  "type": "Feature",
  "properties": {
    "iso:country":"CA",
    "sg:address":"1 Water St",
    "sg:city":"Little Current",
    "sg:classifiers":[
        {
            "category":"Restaurant",
            "type":"Food & Drink"
        }
    ],
    "sg:phone":"+1 705 368 2023",
    "sg:postcode":"P0P 1K0",
    "sg:province":"ON",
    "wof:name":"Anchor Inn Hotel",
    "wof:placetype":"venue"
},
  "geometry": {"coordinates":[-81.9225311279,45.9804992676],"type":"Point"}
}