{
  "type": "Feature",
  "properties": {
    "addr:full":"Stittsville ON K2S 1A6",
    "addr:postcode":"k2s 1a6",
    "iso:country":"CA",
    "sg:city":"Stittsville",
    "sg:classifiers":[
        {
            "category":"Shopping",
            "subcategory":"Catalog Store",
            "type":"Retail Goods"
        }
    ],
    "sg:phone":"+1 613 831 0845",
    "sg:postcode":"K2S 1A6",
    "sg:province":"ON",
    "sg:tags":[
        "mail",
        "order",
        "internet"
    ],
    "wof:name":"Sears Canada Inc",
    "wof:placetype":"venue"
},
  "geometry": {"coordinates":[-75.9272155762,45.2638549805],"type":"Point"}
}