{
  "type": "Feature",
  "properties": {
    "addr:full":"2555 Pharmacy Ave Scarborough ON M1W 2K2",
    "addr:housenumber":"2555",
    "addr:postcode":"m1w 2k2",
    "addr:street":"Pharmacy Ave",
    "iso:country":"CA",
    "sg:address":"2555 Pharmacy Ave",
    "sg:city":"Scarborough",
    "sg:classifiers":[
        {
            "category":"Retail",
            "subcategory":"Auto Repair",
            "type":"Services"
        }
    ],
    "sg:phone":"+1 416 495 7075",
    "sg:postcode":"M1W 2K2",
    "sg:province":"ON",
    "sg:tags":[
        "repairing",
        "automobile"
    ],
    "wof:name":"Pro Performance Automotive Inc",
    "wof:placetype":"venue"
},
  "geometry": {"coordinates":[-79.32495900000001,43.793133],"type":"Point"}
}