{
  "type": "Feature",
  "properties": {
    "addr:full":"Stirling ON K0K 3E0",
    "addr:postcode":"k0k 3e0",
    "iso:country":"CA",
    "sg:city":"Stirling",
    "sg:classifiers":[
        {
            "category":"Organizations",
            "subcategory":"Religious Organization",
            "type":"Services"
        }
    ],
    "sg:phone":"+1 613 395 1745",
    "sg:postcode":"K0K 3E0",
    "sg:province":"ON",
    "sg:tags":[
        "church"
    ],
    "wof:name":"St John's Anglican Church",
    "wof:placetype":"venue"
},
  "geometry": {"coordinates":[-77.548508,44.298149],"type":"Point"}
}