{
  "type": "Feature",
  "properties": {
    "addr:full":"4372 Macdonald Rd Armstrong BC V0E 1B5",
    "addr:housenumber":"4372",
    "addr:postcode":"v0e 1b5",
    "addr:street":"Macdonald Rd",
    "iso:country":"CA",
    "sg:address":"4372 Macdonald Rd",
    "sg:city":"Armstrong",
    "sg:classifiers":[
        {
            "category":"Building & Trades",
            "subcategory":"Construction",
            "type":"Services"
        }
    ],
    "sg:phone":"+1 250 546 3725",
    "sg:postcode":"V0E 1B5",
    "sg:province":"BC",
    "sg:tags":[
        "bridge",
        "builder"
    ],
    "wof:name":"Timber Span Bridge Builders",
    "wof:placetype":"venue"
},
  "geometry": {"coordinates":[-119.183700562,50.4418182373],"type":"Point"}
}