{
  "type": "Feature",
  "properties": {
    "addr:full":"5115 48 St Bashaw AB T0B 0H0",
    "addr:housenumber":"5115",
    "addr:postcode":"t0b 0h0",
    "addr:street":"48 St",
    "iso:country":"CA",
    "sg:address":"5115 48 St",
    "sg:city":"Bashaw",
    "sg:classifiers":[
        {
            "category":"Farming",
            "subcategory":"Nursery",
            "type":"Manufacturing & Wholesale Goods"
        }
    ],
    "sg:phone":"+1 780 372 3745",
    "sg:postcode":"T0B 0H0",
    "sg:province":"AB",
    "sg:tags":[
        "fertilizer",
        "greenhouse"
    ],
    "wof:name":"Agricore United",
    "wof:placetype":"venue"
},
  "geometry": {"coordinates":[-112.970878601,52.5837783813],"type":"Point"}
}