{
  "type": "Feature",
  "properties": {
    "iso:country":"CA",
    "sg:address":"1755 Rue Saint-Regis",
    "sg:city":"Dollard-Des-Ormeaux",
    "sg:classifiers":[
        {
            "category":"Health Services",
            "subcategory":"Clinic",
            "type":"Services"
        }
    ],
    "sg:phone":"+1 514 683 1511",
    "sg:postcode":"H9B 2M9",
    "sg:province":"QC",
    "sg:tags":[
        "information",
        "medical"
    ],
    "wof:name":"Complete Medical Communication",
    "wof:placetype":"venue"
},
  "geometry": {"coordinates":[-73.78257751460001,45.4877586365],"type":"Point"}
}