{
  "type": "Feature",
  "properties": {
    "addr:full":"10 Rue Des Pins Port-Cartier QC G5B 2A5",
    "addr:housenumber":"10",
    "addr:postcode":"g5b 2a5",
    "addr:street":"Rue Des Pins",
    "iso:country":"CA",
    "sg:address":"10 Rue Des Pins",
    "sg:city":"Port-Cartier",
    "sg:classifiers":[
        {
            "category":"Manufacturing",
            "subcategory":"Printing",
            "type":"Manufacturing & Wholesale Goods"
        }
    ],
    "sg:phone":"+1 418 766 5321",
    "sg:postcode":"G5B 2A5",
    "sg:province":"QC",
    "sg:tags":[
        "newspaper"
    ],
    "wof:name":"Journal Le Port-Cartois",
    "wof:placetype":"venue"
},
  "geometry": {"coordinates":[-66.8762893677,50.0198402405],"type":"Point"}
}