{
  "type": "Feature",
  "properties": {
    "addr:full":"12690 260 Rd Montney BC V0C 1Y0",
    "addr:housenumber":"12690",
    "addr:postcode":"bc v0c 1y0",
    "addr:street":"260 Rd",
    "iso:country":"CA",
    "sg:address":"12690 260 Rd",
    "sg:city":"Montney",
    "sg:classifiers":[
        {
            "category":"Wholesale",
            "subcategory":"Apparel",
            "type":"Manufacturing & Wholesale Goods"
        }
    ],
    "sg:phone":"+1 250 827 3215",
    "sg:postcode":"V0C 1Y0",
    "sg:province":"BC",
    "sg:tags":[
        "woolen",
        "wool"
    ],
    "wof:name":"Wooly Acres Custom Carding",
    "wof:placetype":"venue"
},
  "geometry": {"coordinates":[-120.924331665,56.4500656128],"type":"Point"}
}