{
  "type": "Feature",
  "properties": {
    "addr:full":"170 Hampton Rd Quispamsis NB E2E 4J8",
    "addr:housenumber":"170",
    "addr:postcode":"e2e 4j8",
    "addr:street":"Hampton Rd",
    "iso:country":"CA",
    "sg:address":"170 Hampton Rd",
    "sg:city":"Quispamsis",
    "sg:classifiers":[
        {
            "category":"Home & Garden",
            "subcategory":"Building Materials",
            "type":"Retail Goods"
        }
    ],
    "sg:phone":"+1 506 847 2468",
    "sg:postcode":"E2E 4J8",
    "sg:province":"NB",
    "sg:tags":[
        "paint"
    ],
    "wof:name":"Paint Supplies & Decorating",
    "wof:placetype":"venue"
},
  "geometry": {"coordinates":[-65.971329,45.403889],"type":"Point"}
}