{
  "type": "Feature",
  "properties": {
    "addr:full":"Winnipeg MB R2R 1V6",
    "addr:postcode":"r2r 1v6",
    "iso:country":"CA",
    "sg:city":"Winnipeg",
    "sg:classifiers":[
        {
            "category":"Freight",
            "type":"Transportation"
        }
    ],
    "sg:phone":"+1 204 694 5008",
    "sg:postcode":"R2R 1V6",
    "sg:province":"MB",
    "sg:tags":[
        "courier"
    ],
    "wof:name":"Goodway Express CO",
    "wof:placetype":"venue"
},
  "geometry": {"coordinates":[-97.22949199999999,49.936279],"type":"Point"}
}