{
  "type": "Feature",
  "properties": {
    "iso:country":"CA",
    "sg:address":"157 John Doucette Rd",
    "sg:city":"Mavillette",
    "sg:classifiers":[
        {
            "category":"Restaurant",
            "type":"Food & Drink"
        }
    ],
    "sg:phone":"+1 902 645 2519",
    "sg:postcode":"B0W 2H0",
    "sg:province":"NS",
    "wof:name":"Cape View Restaurant",
    "wof:placetype":"venue"
},
  "geometry": {"coordinates":[-66.1848831177,44.102596283],"type":"Point"}
}