{
  "type": "Feature",
  "properties": {
    "addr:full":"588 Rue Principale Saint-Prime QC G8J 1T1",
    "addr:housenumber":"588",
    "addr:postcode":"g8j 1t1",
    "addr:street":"Rue Principale",
    "iso:country":"CA",
    "sg:address":"588 Rue Principale",
    "sg:city":"Saint-Prime",
    "sg:classifiers":[
        {
            "category":"Shopping",
            "subcategory":"Clothing, Apparel, & Fashions",
            "type":"Retail Goods"
        }
    ],
    "sg:phone":"+1 418 251 3232",
    "sg:postcode":"G8J 1T1",
    "sg:province":"QC",
    "sg:tags":[
        "furnishing"
    ],
    "wof:name":"Mercerie Guy Inc",
    "wof:placetype":"venue"
},
  "geometry": {"coordinates":[-72.33522033689999,48.5928192139],"type":"Point"}
}