{
  "type": "Feature",
  "properties": {
    "addr:full":"Montreal QC H2Y 2H2",
    "addr:postcode":"h2y 2h2",
    "iso:country":"CA",
    "sg:city":"Montreal",
    "sg:classifiers":[
        {
            "category":"Shopping",
            "subcategory":"Florist",
            "type":"Retail Goods"
        }
    ],
    "sg:phone":"+1 514 398 0707",
    "sg:postcode":"H2Y 2H2",
    "sg:province":"QC",
    "wof:name":"Fleuriste Le Tulipier",
    "wof:placetype":"venue"
},
  "geometry": {"coordinates":[-73.5593032837,45.5008049011],"type":"Point"}
}