{
  "type": "Feature",
  "properties": {
    "addr:full":"Calgary AB T2C 2C8",
    "addr:postcode":"t2c 2c8",
    "iso:country":"CA",
    "sg:city":"Calgary",
    "sg:classifiers":[
        {
            "category":"Retail",
            "subcategory":"Repair Shop",
            "type":"Services"
        }
    ],
    "sg:phone":"+1 403 279 3432",
    "sg:postcode":"T2C 2C8",
    "sg:province":"AB",
    "sg:tags":[
        "equipment",
        "welding"
    ],
    "wof:name":"Weldertech",
    "wof:placetype":"venue"
},
  "geometry": {"coordinates":[-113.97300720200001,50.9964523315],"type":"Point"}
}