{
  "type": "Feature",
  "properties": {
    "addr:full":"Caplan QC G0C 1H0",
    "addr:postcode":"g0c 1h0",
    "iso:country":"CA",
    "sg:city":"Caplan",
    "sg:classifiers":[
        {
            "category":"Manufacturing",
            "subcategory":"Signs",
            "type":"Manufacturing & Wholesale Goods"
        }
    ],
    "sg:phone":"+1 418 388 2327",
    "sg:postcode":"G0C 1H0",
    "sg:province":"QC",
    "wof:name":"Arsenault Service D'Enseignes",
    "wof:placetype":"venue"
},
  "geometry": {"coordinates":[-65.725174,48.117558],"type":"Point"}
}