{
  "type": "Feature",
  "properties": {
    "addr:full":"210 Industrial Dr Mount Forest ON N0G 2L1",
    "addr:housenumber":"210",
    "addr:postcode":"n0g 2l1",
    "addr:street":"Industrial Dr",
    "iso:country":"CA",
    "sg:address":"210 Industrial Dr",
    "sg:city":"Mount Forest",
    "sg:classifiers":[
        {
            "category":"Retail",
            "subcategory":"Auto Repair",
            "type":"Services"
        }
    ],
    "sg:phone":"+1 519 323 1322",
    "sg:postcode":"N0G 2L1",
    "sg:province":"ON",
    "sg:tags":[
        "repairing",
        "automobile"
    ],
    "wof:name":"Officer's Auto Care Inc",
    "wof:placetype":"venue"
},
  "geometry": {"coordinates":[-80.74619300000001,43.986134],"type":"Point"}
}