{
  "type": "Feature",
  "properties": {
    "addr:full":"5515 Ch Queen-Mary Montreal QC H3X 1V4",
    "addr:postcode":"5515;h3x 1v4",
    "addr:street":"Ch Queen-Mary",
    "iso:country":"CA",
    "sg:address":"5515 Ch Queen-Mary",
    "sg:city":"Montreal",
    "sg:classifiers":[
        {
            "category":"Health Services",
            "subcategory":"Health Practitioner",
            "type":"Services"
        }
    ],
    "sg:phone":"+1 514 488 7202",
    "sg:postcode":"H3X 1V4",
    "sg:province":"QC",
    "sg:tags":[
        "psychologist"
    ],
    "wof:name":"Csank, Patricia",
    "wof:placetype":"venue"
},
  "geometry": {"coordinates":[-73.6314239502,45.4814071655],"type":"Point"}
}