{
  "type": "Feature",
  "properties": {
    "addr:full":"100 City Centre Dr #F29 Mississauga ON L5B 2C9",
    "addr:housenumber":"100",
    "addr:postcode":"l5b 2c9",
    "addr:street":"City Centre Dr # F29",
    "iso:country":"CA",
    "sg:address":"100 City Centre Dr #F29",
    "sg:city":"Mississauga",
    "sg:classifiers":[
        {
            "category":"Shopping",
            "subcategory":"Shoes",
            "type":"Retail Goods"
        }
    ],
    "sg:phone":"+1 905 276 9296",
    "sg:postcode":"L5B 2C9",
    "sg:province":"ON",
    "wof:name":"Town Shoes",
    "wof:placetype":"venue"
},
  "geometry": {"coordinates":[-79.6393585205,43.5922584534],"type":"Point"}
}