{
  "type": "Feature",
  "properties": {
    "addr:full":"Roberval QC G8H 2N2",
    "addr:postcode":"g8h 2n2",
    "iso:country":"CA",
    "sg:city":"Roberval",
    "sg:classifiers":[
        {
            "category":"Professional",
            "subcategory":"Testing Lab",
            "type":"Services"
        }
    ],
    "sg:phone":"+1 418 275 3435",
    "sg:postcode":"G8H 2N2",
    "sg:province":"QC",
    "sg:tags":[
        "laboratory"
    ],
    "wof:name":"Laboratoire Techmat Inc",
    "wof:placetype":"venue"
},
  "geometry": {"coordinates":[-72.224098,48.534847],"type":"Point"}
}