{
  "type": "Feature",
  "properties": {
    "addr:full":"1 Palace Pier Crt Etobicoke ON M8V 3W9",
    "addr:housenumber":"1",
    "addr:postcode":"m8v 3w9",
    "addr:street":"Palace Pier Crt",
    "iso:country":"CA",
    "sg:address":"1 Palace Pier Crt",
    "sg:city":"Etobicoke",
    "sg:classifiers":[
        {
            "category":"Professional",
            "subcategory":"Computer Services",
            "type":"Services"
        }
    ],
    "sg:phone":"+1 416 345 1824",
    "sg:postcode":"M8V 3W9",
    "sg:province":"ON",
    "sg:tags":[
        "consultant"
    ],
    "wof:name":"Shiferaw Enterprises Inc",
    "wof:placetype":"venue"
},
  "geometry": {"coordinates":[-79.4729003906,43.6301307678],"type":"Point"}
}