{
  "type": "Feature",
  "properties": {
    "addr:full":"3916 Boul Wilfrid-Hamel Quebec QC G1P 2J2",
    "addr:housenumber":"3916",
    "addr:postcode":"g1p 2j2",
    "addr:street":"Boul Wilfrid-Hamel",
    "iso:country":"CA",
    "sg:address":"3916 Boul Wilfrid-Hamel",
    "sg:city":"Quebec",
    "sg:classifiers":[
        {
            "category":"Shopping",
            "subcategory":"Music",
            "type":"Retail Goods"
        }
    ],
    "sg:phone":"+1 418 877 8774",
    "sg:postcode":"G1P 2J2",
    "sg:province":"QC",
    "sg:tags":[
        "compact",
        "record",
        "disc",
        "tape"
    ],
    "wof:name":"Import-O-Son Inc",
    "wof:placetype":"venue"
},
  "geometry": {"coordinates":[-71.31364440919999,46.8063697815],"type":"Point"}
}