{
  "type": "Feature",
  "properties": {
    "addr:full":"1010 7th St Rosthern SK S0K 3R0",
    "addr:housenumber":"1010",
    "addr:postcode":"s0k 3r0",
    "addr:street":"7Th St",
    "iso:country":"CA",
    "sg:address":"1010 7th St",
    "sg:city":"Rosthern",
    "sg:classifiers":[
        {
            "category":"Retail",
            "subcategory":"Funeral Services",
            "type":"Services"
        }
    ],
    "sg:phone":"+1 306 232 5245",
    "sg:postcode":"S0K 3R0",
    "sg:province":"SK",
    "sg:tags":[
        "director"
    ],
    "wof:name":"Funk's Funeral Home",
    "wof:placetype":"venue"
},
  "geometry": {"coordinates":[-106.33169599999999,52.657753],"type":"Point"}
}