{
  "type": "Feature",
  "properties": {
    "addr:full":"250 Ch Du Pin-Rouge # A Marieville QC J3M 1N9",
    "addr:housenumber":"250",
    "addr:postcode":"j3m 1n9",
    "addr:street":"Ch Du Pin-Rouge # A",
    "iso:country":"CA",
    "sg:address":"250 Ch Du Pin-Rouge # A",
    "sg:city":"Marieville",
    "sg:classifiers":[
        {
            "category":"Professional",
            "subcategory":"Business Services",
            "type":"Services"
        }
    ],
    "sg:phone":"+1 450 460 3224",
    "sg:postcode":"J3M 1N9",
    "sg:province":"QC",
    "sg:tags":[
        "packaging"
    ],
    "wof:name":"Emballages Marieville Inc",
    "wof:placetype":"venue"
},
  "geometry": {"coordinates":[-73.1622543335,45.4535903931],"type":"Point"}
}