{
  "type": "Feature",
  "properties": {
    "addr:full":"310 Rue Alphonse-Desjardins L'Ile-Bizard QC H9E 1R8",
    "addr:housenumber":"310",
    "addr:postcode":"h9e 1r8",
    "addr:street":"Rue Alphonse-Desjardins",
    "iso:country":"CA",
    "sg:address":"310 Rue Alphonse-Desjardins",
    "sg:city":"L'Ile-Bizard",
    "sg:classifiers":[
        {
            "category":"Building & Trades",
            "subcategory":"Landscaping Services",
            "type":"Services"
        }
    ],
    "sg:phone":"+1 514 626 3600",
    "sg:postcode":"H9E 1R8",
    "sg:province":"QC",
    "sg:tags":[
        "lawn",
        "maintenance",
        "grounds"
    ],
    "wof:name":"J C Trepanier Entretien",
    "wof:placetype":"venue"
},
  "geometry": {"coordinates":[-73.901482,45.503044],"type":"Point"}
}