{
  "type": "Feature",
  "properties": {
    "addr:full":"5669 Av DE Monkland Montreal QC H4A 1E5",
    "addr:housenumber":"5669",
    "addr:postcode":"h4a 1e5",
    "addr:street":"Av De Monkland",
    "iso:country":"CA",
    "sg:address":"5669 Av DE Monkland",
    "sg:city":"Montreal",
    "sg:classifiers":[
        {
            "category":"Cinema",
            "subcategory":"Movie Rental",
            "type":"Entertainment"
        }
    ],
    "sg:phone":"+1 514 481 7765",
    "sg:postcode":"H4A 1E5",
    "sg:province":"QC",
    "sg:tags":[
        "leasing",
        "video",
        "disc",
        "tape"
    ],
    "wof:name":"Avenue Video",
    "wof:placetype":"venue"
},
  "geometry": {"coordinates":[-73.62365699999999,45.474903],"type":"Point"}
}