{
  "type": "Feature",
  "properties": {
    "addr:full":"144 Rue Jean-Talon Saint-Luc QC J2W 1N7",
    "addr:housenumber":"144",
    "addr:postcode":"j2w 1n7",
    "addr:street":"Rue Jean-Talon",
    "iso:country":"CA",
    "sg:address":"144 Rue Jean-Talon",
    "sg:city":"Saint-Luc",
    "sg:classifiers":[
        {
            "category":"Personal",
            "type":"Services"
        }
    ],
    "sg:phone":"+1 450 349 1859",
    "sg:postcode":"J2W 1N7",
    "sg:province":"QC",
    "sg:tags":[
        "electrolysis"
    ],
    "wof:name":"Esthetique & Electrolyse",
    "wof:placetype":"venue"
},
  "geometry": {"coordinates":[-73.26670799999999,45.349819],"type":"Point"}
}