{
  "type": "Feature",
  "properties": {
    "addr:full":"Duchess AB T0J 0Z0",
    "addr:postcode":"t0j 0z0",
    "iso:country":"CA",
    "sg:city":"Duchess",
    "sg:classifiers":[
        {
            "category":"Building & Trades",
            "subcategory":"Construction",
            "type":"Services"
        }
    ],
    "sg:phone":"+1 403 793 1843",
    "sg:postcode":"T0J 0Z0",
    "sg:province":"AB",
    "sg:tags":[
        "repairing",
        "siding",
        "remodeling",
        "contractor"
    ],
    "wof:name":"Russ's Siding",
    "wof:placetype":"venue"
},
  "geometry": {"coordinates":[-111.904411,50.732498],"type":"Point"}
}