{
  "type": "Feature",
  "properties": {
    "iso:country":"CA",
    "sg:address":"6905 Rue Jarry E",
    "sg:city":"Saint-Leonard",
    "sg:classifiers":[
        {
            "category":"Retail",
            "subcategory":"Laundry & Dry Cleaning",
            "type":"Services"
        }
    ],
    "sg:phone":"+1 514 327 3030",
    "sg:postcode":"H1P 1W7",
    "sg:province":"QC",
    "sg:tags":[
        "rubber",
        "cleaners"
    ],
    "wof:name":"Nettuno Asg Inc",
    "wof:placetype":"venue"
},
  "geometry": {"coordinates":[-73.578163147,45.5989074707],"type":"Point"}
}