{
  "type": "Feature",
  "properties": {
    "addr:full":"1834 Lakeshore Rd W Mississauga ON L5J 1J7",
    "addr:housenumber":"1834",
    "addr:postcode":"l5j 1j7",
    "addr:street":"Lakeshore Rd W",
    "iso:country":"CA",
    "sg:address":"1834 Lakeshore Rd W",
    "sg:city":"Mississauga",
    "sg:classifiers":[
        {
            "category":"Food & Beverages",
            "subcategory":"Bakery",
            "type":"Retail Goods"
        }
    ],
    "sg:phone":"+1 905 822 9922",
    "sg:postcode":"L5J 1J7",
    "sg:province":"ON",
    "wof:name":"Felicita Bakery & Pasticceria",
    "wof:placetype":"venue"
},
  "geometry": {"coordinates":[-79.625092,43.515251],"type":"Point"}
}