{
  "type": "Feature",
  "properties": {
    "addr:full":"50 Rideau St # 327A Ottawa ON K1N 9J7",
    "addr:housenumber":"50",
    "addr:postcode":"k1n 9j7",
    "addr:street":"Rideau St # 327A",
    "iso:country":"CA",
    "sg:address":"50 Rideau St # 327A",
    "sg:city":"Ottawa",
    "sg:classifiers":[
        {
            "category":"Restaurant",
            "type":"Food & Drink"
        }
    ],
    "sg:phone":"+1 613 569 0645",
    "sg:postcode":"K1N 9J7",
    "sg:province":"ON",
    "wof:name":"Booster Juice",
    "wof:placetype":"venue"
},
  "geometry": {"coordinates":[-75.6917648315,45.4444313049],"type":"Point"}
}