{
  "type": "Feature",
  "properties": {
    "addr:full":"278 4th Ave NE Moose Jaw SK S6H 0C6",
    "addr:housenumber":"278",
    "addr:postcode":"s6h 0c6",
    "addr:street":"4Th Ave Ne",
    "iso:country":"CA",
    "sg:address":"278 4th Ave NE",
    "sg:city":"Moose Jaw",
    "sg:classifiers":[
        {
            "category":"Shopping",
            "subcategory":"Pharmacy",
            "type":"Retail Goods"
        }
    ],
    "sg:phone":"+1 306 693 5000",
    "sg:postcode":"S6H 0C6",
    "sg:province":"SK",
    "wof:name":"Family Centre Prescription",
    "wof:placetype":"venue"
},
  "geometry": {"coordinates":[-105.524925,50.392136],"type":"Point"}
}