{
  "type": "Feature",
  "properties": {
    "iso:country":"CA",
    "sg:address":"95 Southvale Dr",
    "sg:city":"East York",
    "sg:classifiers":[
        {
            "category":"Building & Trades",
            "subcategory":"Construction",
            "type":"Services"
        }
    ],
    "sg:phone":"+1 416 425 2092",
    "sg:postcode":"M4G 1G4",
    "sg:province":"ON",
    "sg:tags":[
        "roofing",
        "contractor"
    ],
    "wof:name":"Everest Roofing & Constr Ltd",
    "wof:placetype":"venue"
},
  "geometry": {"coordinates":[-79.3648147583,43.6992797852],"type":"Point"}
}