{
  "type": "Feature",
  "properties": {
    "iso:country":"CA",
    "sg:address":"130 Rue Victoria",
    "sg:city":"Sherbrooke",
    "sg:classifiers":[
        {
            "category":"Personal",
            "type":"Services"
        }
    ],
    "sg:phone":"+1 819 564 0196",
    "sg:postcode":"J1H 3H7",
    "sg:province":"QC",
    "sg:tags":[
        "therapist",
        "massage"
    ],
    "wof:name":"Deziel, Francine",
    "wof:placetype":"venue"
},
  "geometry": {"coordinates":[-71.905861,45.400684],"type":"Point"}
}