{
  "type": "Feature",
  "properties": {
    "addr:full":"56 Little River Rd Golden Valley ON P0H 1N0",
    "addr:housenumber":"56",
    "addr:postcode":"p0h 1n0",
    "addr:street":"Little River Rd",
    "iso:country":"CA",
    "sg:address":"56 Little River Rd",
    "sg:city":"Golden Valley",
    "sg:classifiers":[
        {
            "category":"Retail",
            "subcategory":"Auto Repair",
            "type":"Services"
        }
    ],
    "sg:phone":"+1 705 757 2195",
    "sg:postcode":"P0H 1N0",
    "sg:province":"ON",
    "sg:tags":[
        "truck"
    ],
    "wof:name":"G R Moore Truck & Tractor",
    "wof:placetype":"venue"
},
  "geometry": {"coordinates":[-79.78504180909999,45.9285087585],"type":"Point"}
}