{
  "type": "Feature",
  "properties": {
    "addr:full":"6375 Av Baffin Brossard QC J4Z 2H9",
    "addr:housenumber":"6375",
    "addr:postcode":"j4z 2h9",
    "addr:street":"Av Baffin",
    "iso:country":"CA",
    "sg:address":"6375 Av Baffin",
    "sg:city":"Brossard",
    "sg:classifiers":[
        {
            "category":"Education",
            "subcategory":"School",
            "type":"Public Place"
        }
    ],
    "sg:phone":"+1 450 676 2651",
    "sg:postcode":"J4Z 2H9",
    "sg:province":"QC",
    "wof:name":"Harold Napper Ecole",
    "wof:placetype":"venue"
},
  "geometry": {"coordinates":[-73.44622039790001,45.463508606],"type":"Point"}
}