{
  "type": "Feature",
  "properties": {
    "iso:country":"CA",
    "sg:city":"North York",
    "sg:classifiers":[
        {
            "category":"Manufacturing",
            "subcategory":"Printing",
            "type":"Manufacturing & Wholesale Goods"
        }
    ],
    "sg:phone":"+1 416 493 6882",
    "sg:postcode":"M2J 1V6",
    "sg:province":"ON",
    "sg:tags":[
        "printer"
    ],
    "wof:name":"Rjm Group",
    "wof:placetype":"venue"
},
  "geometry": {"coordinates":[-79.336372,43.775558],"type":"Point"}
}