{
  "type": "Feature",
  "properties": {
    "addr:full":"1593 Bank St Ottawa ON K1H 7Z3",
    "addr:housenumber":"1593",
    "addr:postcode":"k1h 7z3",
    "addr:street":"Bank St",
    "iso:country":"CA",
    "sg:address":"1593 Bank St",
    "sg:city":"Ottawa",
    "sg:classifiers":[
        {
            "category":"Home & Garden",
            "subcategory":"Hardware",
            "type":"Retail Goods"
        }
    ],
    "sg:phone":"+1 613 783 3492",
    "sg:postcode":"K1H 7Z3",
    "sg:province":"ON",
    "wof:name":"Home Hardware Stores",
    "wof:placetype":"venue"
},
  "geometry": {"coordinates":[-75.667564,45.378792],"type":"Point"}
}