{
  "type": "Feature",
  "properties": {
    "addr:full":"433 1st Ave Petrolia ON N0N 1R0",
    "addr:housenumber":"433",
    "addr:postcode":"n0n 1r0",
    "addr:street":"1St Ave",
    "iso:country":"CA",
    "sg:address":"433 1st Ave",
    "sg:city":"Petrolia",
    "sg:classifiers":[
        {
            "category":"Education",
            "subcategory":"School",
            "type":"Public Place"
        }
    ],
    "sg:phone":"+1 519 882 2260",
    "sg:postcode":"N0N 1R0",
    "sg:province":"ON",
    "wof:name":"Hillcrest Public School",
    "wof:placetype":"venue"
},
  "geometry": {"coordinates":[-82.1352844238,42.8788986206],"type":"Point"}
}