{
  "type": "Feature",
  "properties": {
    "addr:full":"101 Progress Ave Belleville ON K8P 4Z3",
    "addr:housenumber":"101",
    "addr:postcode":"k8p 4z3",
    "addr:street":"Progress Ave",
    "iso:country":"CA",
    "sg:address":"101 Progress Ave",
    "sg:city":"Belleville",
    "sg:classifiers":[
        {
            "category":"Professional",
            "subcategory":"Accounting & Tax Preparation",
            "type":"Services"
        }
    ],
    "sg:phone":"+1 613 969 7807",
    "sg:postcode":"K8P 4Z3",
    "sg:province":"ON",
    "sg:tags":[
        "bookkeeping",
        "general"
    ],
    "wof:name":"Clarke Accounting Svc",
    "wof:placetype":"venue"
},
  "geometry": {"coordinates":[-77.40804300000001,44.169834],"type":"Point"}
}