{
  "type": "Feature",
  "properties": {
    "addr:full":"108 Rue Georges Pierreville QC J0G 1J0",
    "addr:housenumber":"108",
    "addr:postcode":"j0g 1j0",
    "addr:street":"Rue Georges",
    "iso:country":"CA",
    "sg:address":"108 Rue Georges",
    "sg:city":"Pierreville",
    "sg:classifiers":[
        {
            "category":"Home & Garden",
            "subcategory":"Household Appliances",
            "type":"Retail Goods"
        }
    ],
    "sg:phone":"+1 450 568 2667",
    "sg:postcode":"J0G 1J0",
    "sg:province":"QC",
    "wof:name":"Gill, Rene",
    "wof:placetype":"venue"
},
  "geometry": {"coordinates":[-72.80596160890001,46.0684509277],"type":"Point"}
}