{
  "type": "Feature",
  "properties": {
    "iso:country":"CA",
    "sg:address":"1024 Montee Saint-Robert",
    "sg:city":"Saint-Lazare",
    "sg:classifiers":[
        {
            "category":"Professional",
            "subcategory":"Computer Services",
            "type":"Services"
        }
    ],
    "sg:phone":"+1 450 424 9055",
    "sg:postcode":"J7T 2L8",
    "sg:province":"QC",
    "sg:tags":[
        "consultant"
    ],
    "wof:name":"Ordinacom Informatique",
    "wof:placetype":"venue"
},
  "geometry": {"coordinates":[-74.16065216059999,45.3903541565],"type":"Point"}
}