{
  "type": "Feature",
  "properties": {
    "iso:country":"CA",
    "sg:address":"323 Highland Rd W",
    "sg:city":"Kitchener",
    "sg:classifiers":[
        {
            "category":"Health Services",
            "subcategory":"Doctor",
            "type":"Services"
        }
    ],
    "sg:phone":"+1 519 744 9331",
    "sg:postcode":"N2M 3C6",
    "sg:province":"ON",
    "sg:tags":[
        "physician",
        "surgeon"
    ],
    "wof:name":"Wong, Frank F MD",
    "wof:placetype":"venue"
},
  "geometry": {"coordinates":[-80.5093383789,43.4384994507],"type":"Point"}
}