{
  "type": "Feature",
  "properties": {
    "addr:full":"3034 Rue DE LA Visitation Saint-Charles-Borromee QC J6E 7Y8",
    "addr:housenumber":"3034",
    "addr:postcode":"j6e 7y8",
    "addr:street":"Rue De La Visitation Saint-Charles-Borromee",
    "iso:country":"CA",
    "sg:address":"3034 Rue DE LA Visitation",
    "sg:city":"Saint-Charles-Borromee",
    "sg:classifiers":[
        {
            "category":"Real Estate",
            "subcategory":"Real Estate Agent",
            "type":"Services"
        }
    ],
    "sg:phone":"+1 450 756 1990",
    "sg:postcode":"J6E 7Y8",
    "sg:province":"QC",
    "sg:tags":[
        "agency",
        "rental"
    ],
    "wof:name":"Loca-Plus",
    "wof:placetype":"venue"
},
  "geometry": {"coordinates":[-73.5033111572,46.0736236572],"type":"Point"}
}