{
  "type": "Feature",
  "properties": {
    "addr:full":"18948 80 Ave NW Edmonton AB T5T 5C1",
    "addr:housenumber":"18948",
    "addr:postcode":"t5t 5c1",
    "addr:street":"80 Ave Nw",
    "iso:country":"CA",
    "sg:address":"18948 80 Ave NW",
    "sg:city":"Edmonton",
    "sg:classifiers":[
        {
            "category":"Health Services",
            "subcategory":"Health Practitioner",
            "type":"Services"
        }
    ],
    "sg:phone":"+1 780 443 2601",
    "sg:postcode":"T5T 5C1",
    "sg:province":"AB",
    "sg:tags":[
        "nurse",
        "registry"
    ],
    "wof:name":"Alberta Male Nursing Svc",
    "wof:placetype":"venue"
},
  "geometry": {"coordinates":[-113.650939941,53.5138053894],"type":"Point"}
}