{
  "type": "Feature",
  "properties": {
    "addr:full":"241 Boul Bona-Dussault Saint-Marc-Des-Carrieres QC G0A 4B0",
    "addr:housenumber":"241",
    "addr:postcode":"g0a 4b0",
    "addr:street":"Boul Bona-Dussault Saint-Marc-Des-Carrieres",
    "iso:country":"CA",
    "sg:address":"241 Boul Bona-Dussault",
    "sg:city":"Saint-Marc-Des-Carrieres",
    "sg:classifiers":[
        {
            "category":"Retail",
            "subcategory":"Auto Repair",
            "type":"Services"
        }
    ],
    "sg:phone":"+1 418 268 8780",
    "sg:postcode":"G0A 4B0",
    "sg:province":"QC",
    "sg:tags":[
        "repairing",
        "automobile"
    ],
    "wof:name":"Garage Yvon Rivard Inc",
    "wof:placetype":"venue"
},
  "geometry": {"coordinates":[-72.027367,46.66692],"type":"Point"}
}