{
  "type": "Feature",
  "properties": {
    "addr:full":"Kingsley Rd Kingsley NB E3A 6G7",
    "addr:postcode":"e3a 6g7",
    "addr:street":"Kingsley Rd",
    "iso:country":"CA",
    "sg:address":"Kingsley Rd",
    "sg:city":"Kingsley",
    "sg:classifiers":[
        {
            "category":"Real Estate",
            "subcategory":"Real Estate Operator",
            "type":"Services"
        }
    ],
    "sg:phone":"+1 506 452 7680",
    "sg:postcode":"E3A 6G7",
    "sg:province":"NB",
    "sg:tags":[
        "mobile",
        "home",
        "community"
    ],
    "wof:name":"Apple Blossom Trailer Park",
    "wof:placetype":"venue"
},
  "geometry": {"coordinates":[-66.74585,46.05159],"type":"Point"}
}