{
  "type": "Feature",
  "properties": {
    "addr:full":"4150 Columbia Valley Rd Cultus Lake BC V2R 5H6",
    "addr:housenumber":"4150",
    "addr:postcode":"bc v2r 5h6",
    "addr:street":"Columbia Valley Rd",
    "iso:country":"CA",
    "sg:address":"4150 Columbia Valley Rd",
    "sg:city":"Cultus Lake",
    "sg:classifiers":[
        {
            "category":"Recreation",
            "type":"Entertainment"
        }
    ],
    "sg:phone":"+1 604 858 7241",
    "sg:postcode":"V2R 5H6",
    "sg:province":"BC",
    "sg:tags":[
        "amusement",
        "swimming"
    ],
    "wof:name":"Cultus Lake Waterpark",
    "wof:placetype":"venue"
},
  "geometry": {"coordinates":[-121.976364,49.074837],"type":"Point"}
}