{
  "type": "Feature",
  "properties": {
    "addr:full":"205 Norton Ave North York ON M2N 4B1",
    "addr:housenumber":"205",
    "addr:postcode":"m2n 4b1",
    "addr:street":"Norton Ave",
    "iso:country":"CA",
    "sg:address":"205 Norton Ave",
    "sg:city":"North York",
    "sg:classifiers":[
        {
            "category":"Organizations",
            "subcategory":"Religious Organization",
            "type":"Services"
        }
    ],
    "sg:phone":"+1 416 256 9168",
    "sg:postcode":"M2N 4B1",
    "sg:province":"ON",
    "sg:tags":[
        "church"
    ],
    "wof:name":"Taiwan Revival Mennonite Ch",
    "wof:placetype":"venue"
},
  "geometry": {"coordinates":[-79.4009475708,43.7746086121],"type":"Point"}
}