{
  "type": "Feature",
  "properties": {
    "addr:full":"236 Wyatt Cres Saint John NB E2J 4E1",
    "addr:housenumber":"236",
    "addr:postcode":"e2j 4e1",
    "addr:street":"Wyatt Cres",
    "iso:country":"CA",
    "sg:address":"236 Wyatt Cres",
    "sg:city":"Saint John",
    "sg:classifiers":[
        {
            "category":"Building & Trades",
            "subcategory":"Plumbing",
            "type":"Services"
        }
    ],
    "sg:phone":"+1 506 696 3365",
    "sg:postcode":"E2J 4E1",
    "sg:province":"NB",
    "sg:tags":[
        "contractor"
    ],
    "wof:name":"Lloyd Wilson Ltd",
    "wof:placetype":"venue"
},
  "geometry": {"coordinates":[-65.9838485718,45.2969665527],"type":"Point"}
}