{
  "type": "Feature",
  "properties": {
    "addr:full":"420 Abington Ave Mississauga ON L5A 1L7",
    "addr:housenumber":"420",
    "addr:postcode":"l5a 1l7",
    "addr:street":"Abington Ave",
    "iso:country":"CA",
    "sg:address":"420 Abington Ave",
    "sg:city":"Mississauga",
    "sg:classifiers":[
        {
            "category":"Professional",
            "subcategory":"Business Services",
            "type":"Services"
        }
    ],
    "sg:phone":"+1 905 270 6182",
    "sg:postcode":"L5A 1L7",
    "sg:province":"ON",
    "sg:tags":[
        "auctioneer"
    ],
    "wof:name":"Brian Bell Enterprises",
    "wof:placetype":"venue"
},
  "geometry": {"coordinates":[-79.596191,43.58202],"type":"Point"}
}