{
  "type": "Feature",
  "properties": {
    "addr:full":"Hampstead QC H3X 3A1",
    "addr:postcode":"h3x 3a1",
    "iso:country":"CA",
    "sg:city":"Hampstead",
    "sg:classifiers":[
        {
            "category":"Banks & Credit Unions",
            "subcategory":"Bank",
            "type":"Services"
        }
    ],
    "sg:phone":"+1 514 487 6971",
    "sg:postcode":"H3X 3A1",
    "sg:province":"QC",
    "sg:tags":[
        "financing"
    ],
    "wof:name":"Joddes Limited",
    "wof:placetype":"venue"
},
  "geometry": {"coordinates":[-73.64134979249999,45.4828338623],"type":"Point"}
}