{
  "type": "Feature",
  "properties": {
    "addr:full":"8558 126 Ave NW Edmonton AB T5B 1G9",
    "addr:housenumber":"8558",
    "addr:postcode":"t5b 1g9",
    "addr:street":"126 Ave Nw",
    "iso:country":"CA",
    "sg:address":"8558 126 Ave NW",
    "sg:city":"Edmonton",
    "sg:classifiers":[
        {
            "category":"Retail",
            "subcategory":"Auto Rental",
            "type":"Services"
        }
    ],
    "sg:phone":"+1 780 477 1717",
    "sg:postcode":"T5B 1G9",
    "sg:province":"AB",
    "sg:tags":[
        "renting",
        "automobile"
    ],
    "wof:name":"Enterprise Rent-A-Car",
    "wof:placetype":"venue"
},
  "geometry": {"coordinates":[-113.473884583,53.5827903748],"type":"Point"}
}