{
  "type": "Feature",
  "properties": {
    "addr:full":"Woodbridge ON L4L 3S8",
    "addr:postcode":"l4l 3s8",
    "iso:country":"CA",
    "sg:city":"Woodbridge",
    "sg:classifiers":[
        {
            "category":"Travel",
            "subcategory":"Travel Agent",
            "type":"Entertainment"
        }
    ],
    "sg:phone":"+1 416 798 7314",
    "sg:postcode":"L4L 3S8",
    "sg:province":"ON",
    "sg:tags":[
        "agency",
        "bureau"
    ],
    "wof:name":"H A Mc Lean Travel Inc",
    "wof:placetype":"venue"
},
  "geometry": {"coordinates":[-79.55909729,43.7678413391],"type":"Point"}
}