{
  "type": "Feature",
  "properties": {
    "addr:full":"70 Mcgee St Toronto ON M4M 2K9",
    "addr:housenumber":"70",
    "addr:postcode":"m4m 2k9",
    "addr:street":"Mcgee St",
    "iso:country":"CA",
    "sg:address":"70 Mcgee St",
    "sg:city":"Toronto",
    "sg:classifiers":[
        {
            "category":"Professional",
            "subcategory":"Business Services",
            "type":"Services"
        }
    ],
    "sg:phone":"+1 416 461 5584",
    "sg:postcode":"M4M 2K9",
    "sg:province":"ON",
    "sg:tags":[
        "interior",
        "consultant",
        "design",
        "decorator"
    ],
    "wof:name":"Luc Wintzen Design Inc",
    "wof:placetype":"venue"
},
  "geometry": {"coordinates":[-79.3452377319,43.658908844],"type":"Point"}
}