{
  "type": "Feature",
  "properties": {
    "addr:full":"690 Notre Dame Ave Winnipeg MB R3E 0L7",
    "addr:housenumber":"690",
    "addr:postcode":"r3e 0l7",
    "addr:street":"Notre Dame Ave",
    "iso:country":"CA",
    "sg:address":"690 Notre Dame Ave",
    "sg:city":"Winnipeg",
    "sg:classifiers":[
        {
            "category":"Travel",
            "subcategory":"Hotels & Motels",
            "type":"Entertainment"
        }
    ],
    "sg:phone":"+1 204 786 5981",
    "sg:postcode":"R3E 0L7",
    "sg:province":"MB",
    "wof:name":"Maryland Motor Hotel",
    "wof:placetype":"venue"
},
  "geometry": {"coordinates":[-97.157822,49.900894],"type":"Point"}
}