{
  "type": "Feature",
  "properties": {
    "addr:full":"22186 Loyalist Pky Carrying Place ON K0K 1L0",
    "addr:housenumber":"22186",
    "addr:postcode":"k0k 1l0",
    "addr:street":"Loyalist Pky;Place",
    "iso:country":"CA",
    "sg:address":"22186 Loyalist Pky",
    "sg:city":"Carrying Place",
    "sg:classifiers":[
        {
            "category":"Food & Beverages",
            "subcategory":"Groceries & Convenience Stores",
            "type":"Retail Goods"
        }
    ],
    "sg:phone":"+1 613 392 6800",
    "sg:postcode":"K0K 1L0",
    "sg:province":"ON",
    "sg:tags":[
        "butchering"
    ],
    "wof:name":"Sprenkels Meat & Variety",
    "wof:placetype":"venue"
},
  "geometry": {"coordinates":[-77.581688,44.048721],"type":"Point"}
}