{
  "type": "Feature",
  "properties": {
    "addr:full":"4020 Poplar Ave Fort Nelson BC V0C 1R0",
    "addr:housenumber":"4020",
    "addr:postcode":"bc v0c 1r0",
    "addr:street":"Poplar Ave",
    "iso:country":"CA",
    "sg:address":"4020 Poplar Ave",
    "sg:city":"Fort Nelson",
    "sg:classifiers":[
        {
            "category":"Health Services",
            "subcategory":"Health Practitioner",
            "type":"Services"
        }
    ],
    "sg:phone":"+1 250 774 3424",
    "sg:postcode":"V0C 1R0",
    "sg:province":"BC",
    "sg:tags":[
        "acupuncture",
        "holistic"
    ],
    "wof:name":"Rainbows End Wellness Clinic",
    "wof:placetype":"venue"
},
  "geometry": {"coordinates":[-122.677299,58.807468],"type":"Point"}
}