{
  "type": "Feature",
  "properties": {
    "addr:full":"8222 168A St Surrey BC V4N 4T8",
    "addr:housenumber":"8222",
    "addr:postcode":"v4n 4t8",
    "addr:street":"168A St",
    "iso:country":"CA",
    "sg:address":"8222 168A St",
    "sg:city":"Surrey",
    "sg:classifiers":[
        {
            "category":"Education",
            "subcategory":"School",
            "type":"Public Place"
        }
    ],
    "sg:phone":"+1 604 574 6036",
    "sg:postcode":"V4N 4T8",
    "sg:province":"BC",
    "wof:name":"Coast Meridian Elementary Schl",
    "wof:placetype":"venue"
},
  "geometry": {"coordinates":[-122.830215454,49.105178833],"type":"Point"}
}