{
  "type": "Feature",
  "properties": {
    "addr:full":"New Westminster BC V3M 6B9",
    "addr:postcode":"v3m 6b9",
    "iso:country":"CA",
    "sg:city":"New Westminster",
    "sg:classifiers":[
        {
            "category":"Bars & Pubs",
            "type":"Food & Drink"
        }
    ],
    "sg:phone":"+1 604 524 1894",
    "sg:postcode":"V3M 6B9",
    "sg:province":"BC",
    "wof:name":"Paddle Wheeler Neighbourhood",
    "wof:placetype":"venue"
},
  "geometry": {"coordinates":[-122.911827,49.200249],"type":"Point"}
}