{
  "type": "Feature",
  "properties": {
    "iso:country":"CA",
    "sg:address":"888 Dundas St E # K1",
    "sg:city":"Mississauga",
    "sg:classifiers":[
        {
            "category":"Cinema",
            "subcategory":"Movie Rental",
            "type":"Entertainment"
        }
    ],
    "sg:phone":"+1 905 803 0737",
    "sg:postcode":"L4Y 4G6",
    "sg:province":"ON",
    "sg:tags":[
        "leasing",
        "video",
        "disc",
        "tape"
    ],
    "wof:name":"Saigon Video 3",
    "wof:placetype":"venue"
},
  "geometry": {"coordinates":[-79.594909668,43.5990524292],"type":"Point"}
}