{
  "type": "Feature",
  "properties": {
    "iso:country":"CA",
    "sg:address":"8903 112 St NW",
    "sg:city":"Edmonton",
    "sg:classifiers":[
        {
            "category":"Professional",
            "subcategory":"Lawyer & Legal Services",
            "type":"Services"
        }
    ],
    "sg:phone":"+1 780 439 9360",
    "sg:postcode":"T6G 2C5",
    "sg:province":"AB",
    "sg:tags":[
        "attorney"
    ],
    "wof:name":"Armstrong Law",
    "wof:placetype":"venue"
},
  "geometry": {"coordinates":[-113.520629883,53.5240364075],"type":"Point"}
}