{
  "type": "Feature",
  "properties": {
    "addr:full":"675 King St Port Colborne ON L3K 4H9",
    "addr:housenumber":"675",
    "addr:postcode":"l3k 4h9",
    "addr:street":"King St",
    "iso:country":"CA",
    "sg:address":"675 King St",
    "sg:city":"Port Colborne",
    "sg:classifiers":[
        {
            "category":"Shopping",
            "subcategory":"Discount & Variety Stores",
            "type":"Retail Goods"
        }
    ],
    "sg:phone":"+1 905 834 6441",
    "sg:postcode":"L3K 4H9",
    "sg:province":"ON",
    "wof:name":"Paul's Variety",
    "wof:placetype":"venue"
},
  "geometry": {"coordinates":[-79.25194500000001,42.895733],"type":"Point"}
}