{
  "type": "Feature",
  "properties": {
    "addr:full":"Mozart Ave Handel SK S0K 1Y0",
    "addr:postcode":"s0k 1y0",
    "addr:street":"Mozart Ave",
    "iso:country":"CA",
    "sg:address":"Mozart Ave",
    "sg:city":"Handel",
    "sg:classifiers":[
        {
            "category":"Travel",
            "subcategory":"Hotels & Motels",
            "type":"Entertainment"
        }
    ],
    "sg:phone":"+1 306 658 4211",
    "sg:postcode":"S0K 1Y0",
    "sg:province":"SK",
    "wof:name":"Handel Hotel",
    "wof:placetype":"venue"
},
  "geometry": {"coordinates":[-108.69300800000001,52.06031],"type":"Point"}
}