{
  "type": "Feature",
  "properties": {
    "iso:country":"CA",
    "sg:city":"Repentigny",
    "sg:classifiers":[
        {
            "category":"Health Services",
            "subcategory":"Podiatrist",
            "type":"Services"
        }
    ],
    "sg:phone":"+1 450 585 6347",
    "sg:postcode":"J6A 2P8",
    "sg:province":"QC",
    "wof:name":"Guillette, Claude DPM",
    "wof:placetype":"venue"
},
  "geometry": {"coordinates":[-73.468544,45.718182],"type":"Point"}
}