{
  "type": "Feature",
  "properties": {
    "addr:full":"133 Centre St Ponteix SK S0N 1Z0",
    "addr:housenumber":"133",
    "addr:postcode":"s0n 1z0",
    "addr:street":"Centre St",
    "iso:country":"CA",
    "sg:address":"133 Centre St",
    "sg:city":"Ponteix",
    "sg:classifiers":[
        {
            "category":"Personal",
            "subcategory":"Beauty Salon",
            "type":"Services"
        }
    ],
    "sg:phone":"+1 306 625 3937",
    "sg:postcode":"S0N 1Z0",
    "sg:province":"SK",
    "wof:name":"Helena's Hair Fashion & Barber",
    "wof:placetype":"venue"
},
  "geometry": {"coordinates":[-107.489372,49.746239],"type":"Point"}
}