{
  "type": "Feature",
  "properties": {
    "addr:full":"1747 Boul Saint-Antoine Saint-Jerome QC J7Z 7M1",
    "addr:housenumber":"1747",
    "addr:postcode":"j7z 7m1",
    "addr:street":"Boul Saint-Antoine",
    "iso:country":"CA",
    "sg:address":"1747 Boul Saint-Antoine",
    "sg:city":"Saint-Jerome",
    "sg:classifiers":[
        {
            "category":"Autos & Motor Vehicles",
            "subcategory":"Auto Supplies",
            "type":"Retail Goods"
        }
    ],
    "sg:phone":"+1 450 438 0787",
    "sg:postcode":"J7Z 7M1",
    "sg:province":"QC",
    "sg:tags":[
        "automobile",
        "parts"
    ],
    "wof:name":"Pieces D'Auto Presseault Inc",
    "wof:placetype":"venue"
},
  "geometry": {"coordinates":[-73.96821594239999,45.7742843628],"type":"Point"}
}