{
  "type": "Feature",
  "properties": {
    "addr:full":"1137 Centre Ste Thornhill ON L4J 3M6",
    "addr:housenumber":"1137",
    "addr:postcode":"l4j 3m6",
    "addr:street":"Centre Ste",
    "iso:country":"CA",
    "sg:address":"1137 Centre Ste",
    "sg:city":"Thornhill",
    "sg:classifiers":[
        {
            "category":"Real Estate",
            "subcategory":"Surveying",
            "type":"Services"
        }
    ],
    "sg:phone":"+1 905 264 2780",
    "sg:postcode":"L4J 3M6",
    "sg:province":"ON",
    "sg:tags":[
        "surveyor"
    ],
    "wof:name":"Krcmar Surveyors Ltd",
    "wof:placetype":"venue"
},
  "geometry": {"coordinates":[-79.461823,43.808247],"type":"Point"}
}