{
  "type": "Feature",
  "properties": {
    "addr:full":"33 Dupont St E Waterloo ON N2J 2G8",
    "addr:housenumber":"33",
    "addr:postcode":"n2j 2g8",
    "addr:street":"Dupont St E",
    "iso:country":"CA",
    "sg:address":"33 Dupont St E",
    "sg:city":"Waterloo",
    "sg:classifiers":[
        {
            "category":"Government",
            "subcategory":"Office",
            "type":"Public Place"
        }
    ],
    "sg:phone":"+1 519 884 2604",
    "sg:postcode":"N2J 2G8",
    "sg:province":"ON",
    "sg:tags":[
        "village",
        "computer",
        "software"
    ],
    "wof:name":"Waterloo Information Systems",
    "wof:placetype":"venue"
},
  "geometry": {"coordinates":[-80.52095799999999,43.466049],"type":"Point"}
}