{
  "type": "Feature",
  "properties": {
    "addr:full":"602 Twelfth St New Westminster BC V3M 4J2",
    "addr:housenumber":"602",
    "addr:postcode":"v3m 4j2",
    "addr:street":"Twelfth St",
    "iso:country":"CA",
    "sg:address":"602 Twelfth St",
    "sg:city":"New Westminster",
    "sg:classifiers":[
        {
            "category":"Insurance",
            "subcategory":"Insurance Agent",
            "type":"Services"
        }
    ],
    "sg:phone":"+1 604 777 9999",
    "sg:postcode":"V3M 4J2",
    "sg:province":"BC",
    "wof:name":"Meier & CO Insurance Agencies",
    "wof:placetype":"venue"
},
  "geometry": {"coordinates":[-122.930839539,49.2076835632],"type":"Point"}
}