{
  "type": "Feature",
  "properties": {
    "addr:full":"1316 Carling Ave Ottawa ON K1Z 7L1",
    "addr:housenumber":"1316",
    "addr:postcode":"k1z 7l1",
    "addr:street":"Carling Ave",
    "iso:country":"CA",
    "sg:address":"1316 Carling Ave",
    "sg:city":"Ottawa",
    "sg:classifiers":[
        {
            "category":"Real Estate",
            "subcategory":"Real Estate Operator",
            "type":"Services"
        }
    ],
    "sg:phone":"+1 613 728 8126",
    "sg:postcode":"K1Z 7L1",
    "sg:province":"ON",
    "sg:tags":[
        "apartment"
    ],
    "wof:name":"Phoenix Apartments",
    "wof:placetype":"venue"
},
  "geometry": {"coordinates":[-75.734634,45.385609],"type":"Point"}
}