{
  "type": "Feature",
  "properties": {
    "addr:full":"185 Carlingview Dr Etobicoke ON M9W 5E8",
    "addr:housenumber":"185",
    "addr:postcode":"m9w 5e8",
    "addr:street":"Carlingview Dr",
    "iso:country":"CA",
    "sg:address":"185 Carlingview Dr",
    "sg:city":"Etobicoke",
    "sg:classifiers":[
        {
            "category":"Professional",
            "subcategory":"Lawyer & Legal Services",
            "type":"Services"
        }
    ],
    "sg:phone":"+1 416 798 9800",
    "sg:postcode":"M9W 5E8",
    "sg:province":"ON",
    "sg:tags":[
        "attorney"
    ],
    "wof:name":"Tonello, A Edward",
    "wof:placetype":"venue"
},
  "geometry": {"coordinates":[-79.593421936,43.682598114],"type":"Point"}
}