{
  "type": "Feature",
  "properties": {
    "addr:full":"234 Rue Monseigneur-Leblanc Gaspe QC G4X 1S4",
    "addr:housenumber":"234",
    "addr:postcode":"g4x 1s4",
    "addr:street":"Rue Monseigneur-Leblanc",
    "iso:country":"CA",
    "sg:address":"234 Rue Monseigneur-Leblanc",
    "sg:city":"Gaspe",
    "sg:classifiers":[
        {
            "category":"Education",
            "subcategory":"School",
            "type":"Public Place"
        }
    ],
    "sg:phone":"+1 418 368 2259",
    "sg:postcode":"G4X 1S4",
    "sg:province":"QC",
    "wof:name":"Gaspe Elementary School",
    "wof:placetype":"venue"
},
  "geometry": {"coordinates":[-64.4925613403,48.8276901245],"type":"Point"}
}