{
  "type": "Feature",
  "properties": {
    "addr:full":"PO Box 383 Eastend SK S0N 0T0",
    "addr:housenumber":"po",
    "addr:postcode":"s0n 0t0",
    "addr:street":"Box 383 Eastend",
    "iso:country":"CA",
    "sg:address":"PO Box 383",
    "sg:city":"Eastend",
    "sg:classifiers":[
        {
            "category":"Real Estate",
            "subcategory":"Surveying",
            "type":"Services"
        }
    ],
    "sg:phone":"+1 306 295 3388",
    "sg:postcode":"S0N 0T0",
    "sg:province":"SK",
    "sg:tags":[
        "surveyor"
    ],
    "wof:name":"Orion Surveys Ltd",
    "wof:placetype":"venue"
},
  "geometry": {"coordinates":[-108.828705,49.513657],"type":"Point"}
}