{
  "type": "Feature",
  "properties": {
    "addr:full":"1101 Clarkson Rd Mississauga ON L5J 2W1",
    "addr:housenumber":"1101",
    "addr:postcode":"l5j 2w1",
    "addr:street":"Clarkson Rd",
    "iso:country":"CA",
    "sg:address":"1101 Clarkson Rd",
    "sg:city":"Mississauga",
    "sg:classifiers":[
        {
            "category":"Professional",
            "subcategory":"Computer Services",
            "type":"Services"
        }
    ],
    "sg:phone":"+1 905 403 0401",
    "sg:postcode":"L5J 2W1",
    "sg:province":"ON",
    "sg:tags":[
        "consultant"
    ],
    "wof:name":"Interpix Design Inc",
    "wof:placetype":"venue"
},
  "geometry": {"coordinates":[-79.62608299999999,43.519348],"type":"Point"}
}