{
  "type": "Feature",
  "properties": {
    "addr:full":"11060 Elevator Rd Surrey BC V3V 2R7",
    "addr:housenumber":"11060",
    "addr:postcode":"v3v 2r7",
    "addr:street":"Elevator Rd",
    "iso:country":"CA",
    "sg:address":"11060 Elevator Rd",
    "sg:city":"Surrey",
    "sg:classifiers":[
        {
            "category":"Organizations",
            "subcategory":"Religious Organization",
            "type":"Services"
        }
    ],
    "sg:phone":"+1 604 583 1868",
    "sg:postcode":"V3V 2R7",
    "sg:province":"BC",
    "sg:tags":[
        "church"
    ],
    "wof:name":"Lighthouse Harbour Ministries",
    "wof:placetype":"venue"
},
  "geometry": {"coordinates":[-122.914986,49.177776],"type":"Point"}
}