{
  "type": "Feature",
  "properties": {
    "iso:country":"CA",
    "sg:address":"17325 Hwy 60 E",
    "sg:city":"Wilno",
    "sg:classifiers":[
        {
            "category":"Organizations",
            "subcategory":"Religious Organization",
            "type":"Services"
        }
    ],
    "sg:phone":"+1 613 756 2344",
    "sg:postcode":"K0J 2N0",
    "sg:province":"ON",
    "sg:tags":[
        "church"
    ],
    "wof:name":"St Mary's Church",
    "wof:placetype":"venue"
},
  "geometry": {"coordinates":[-77.5584411621,45.5138015747],"type":"Point"}
}