{
  "type": "Feature",
  "properties": {
    "addr:full":"PO Box 12510 Rpo Martinway Pla Etobicoke ON M9R 4C7",
    "addr:housenumber":"po box",
    "addr:postcode":"12510;m9r 4c7",
    "addr:street":"Martinway Pla",
    "iso:country":"CA",
    "sg:address":"PO Box 12510 Rpo Martinway Pla",
    "sg:city":"Etobicoke",
    "sg:classifiers":[
        {
            "category":"Arts & Performance",
            "subcategory":"Theater",
            "type":"Entertainment"
        }
    ],
    "sg:phone":"+1 416 248 0410",
    "sg:postcode":"M9R 4C7",
    "sg:province":"ON",
    "wof:name":"Etobicoke Musical Productions",
    "wof:placetype":"venue"
},
  "geometry": {"coordinates":[-79.566696167,43.6433944702],"type":"Point"}
}