{
  "type": "Feature",
  "properties": {
    "addr:full":"Ashmont AB T0A 0C0",
    "addr:postcode":"t0a 0c0",
    "iso:country":"CA",
    "sg:city":"Ashmont",
    "sg:classifiers":[
        {
            "category":"Autos & Motor Vehicles",
            "subcategory":"Fuel & Gas Station",
            "type":"Retail Goods"
        }
    ],
    "sg:phone":"+1 780 726 3941",
    "sg:postcode":"T0A 0C0",
    "sg:province":"AB",
    "sg:tags":[
        "oil"
    ],
    "wof:name":"Doug's Service Garage Ltd",
    "wof:placetype":"venue"
},
  "geometry": {"coordinates":[-111.56830596899999,54.128074646],"type":"Point"}
}