{
  "type": "Feature",
  "properties": {
    "addr:full":"91870 Alaska Hwy Whitehorse YT Y1A 5B7",
    "addr:housenumber":"91870",
    "addr:postcode":"y1a 5b7",
    "addr:street":"Alaska Hwy",
    "iso:country":"CA",
    "sg:address":"91870 Alaska Hwy",
    "sg:city":"Whitehorse",
    "sg:classifiers":[
        {
            "category":"Freight",
            "type":"Transportation"
        }
    ],
    "sg:phone":"+1 867 667 7447",
    "sg:postcode":"Y1A 5B7",
    "sg:province":"YT",
    "sg:tags":[
        "trucking"
    ],
    "wof:name":"Kluane Freight Lines Ltd",
    "wof:placetype":"venue"
},
  "geometry": {"coordinates":[-135.11241100000001,60.741722],"type":"Point"}
}