{
  "type": "Feature",
  "properties": {
    "iso:country":"CA",
    "sg:address":"304 Toronto St S # 108",
    "sg:city":"Uxbridge",
    "sg:classifiers":[
        {
            "category":"Home & Garden",
            "subcategory":"Household Appliances",
            "type":"Retail Goods"
        }
    ],
    "sg:phone":"+1 905 852 3304",
    "sg:postcode":"L9P 1Y2",
    "sg:province":"ON",
    "wof:name":"Sears Canada Inc",
    "wof:placetype":"venue"
},
  "geometry": {"coordinates":[-79.132858,44.091396],"type":"Point"}
}