{
  "type": "Feature",
  "properties": {
    "iso:country":"CA",
    "sg:address":"8957 Wellington Road 50",
    "sg:city":"Acton",
    "sg:classifiers":[
        {
            "category":"Building & Trades",
            "subcategory":"Plumbing",
            "type":"Services"
        }
    ],
    "sg:phone":"+1 519 853 4110",
    "sg:postcode":"L7J 2L8",
    "sg:province":"ON",
    "sg:tags":[
        "refrigeration",
        "contractor"
    ],
    "wof:name":"G A Enns Industrial Refrigerat",
    "wof:placetype":"venue"
},
  "geometry": {"coordinates":[-80.040329,43.630733],"type":"Point"}
}