{
  "type": "Feature",
  "properties": {
    "addr:full":"4949 Bathurst St North York ON M2R 1Y1",
    "addr:housenumber":"4949",
    "addr:postcode":"m2r 1y1",
    "addr:street":"Bathurst St",
    "iso:country":"CA",
    "sg:address":"4949 Bathurst St",
    "sg:city":"North York",
    "sg:classifiers":[
        {
            "category":"Restaurant",
            "type":"Food & Drink"
        }
    ],
    "sg:phone":"+1 416 225 1078",
    "sg:postcode":"M2R 1Y1",
    "sg:province":"ON",
    "wof:name":"Manila By Night Karaoke Bar",
    "wof:placetype":"venue"
},
  "geometry": {"coordinates":[-79.442863,43.774109],"type":"Point"}
}