{
  "type": "Feature",
  "properties": {
    "iso:country":"CA",
    "sg:address":"97 Springmount Ave",
    "sg:city":"Toronto",
    "sg:classifiers":[
        {
            "category":"Personal",
            "type":"Services"
        }
    ],
    "sg:phone":"+1 416 658 8565",
    "sg:postcode":"M6H 2Y5",
    "sg:province":"ON",
    "sg:tags":[
        "program",
        "physical",
        "exercise",
        "fitness"
    ],
    "wof:name":"Vital Steps Personal Training",
    "wof:placetype":"venue"
},
  "geometry": {"coordinates":[-79.436668,43.676182],"type":"Point"}
}