{
  "type": "Feature",
  "properties": {
    "iso:country":"CA",
    "sg:address":"15 Tandridge Cres",
    "sg:city":"Etobicoke",
    "sg:classifiers":[
        {
            "category":"Education",
            "subcategory":"School",
            "type":"Public Place"
        }
    ],
    "sg:phone":"+1 416 394 7772",
    "sg:postcode":"M9W 2N8",
    "sg:province":"ON",
    "wof:name":"Braeburn Junior School",
    "wof:placetype":"venue"
},
  "geometry": {"coordinates":[-79.5495223999,43.7280807495],"type":"Point"}
}