{
  "type": "Feature",
  "properties": {
    "addr:full":"2359 Lakeshore Rd W Oakville ON L6L 1H4",
    "addr:housenumber":"2359",
    "addr:postcode":"l6l 1h4",
    "addr:street":"Lakeshore Rd W",
    "iso:country":"CA",
    "sg:address":"2359 Lakeshore Rd W",
    "sg:city":"Oakville",
    "sg:classifiers":[
        {
            "category":"Shopping",
            "subcategory":"Used Merchandise",
            "type":"Retail Goods"
        }
    ],
    "sg:phone":"+1 905 847 2922",
    "sg:postcode":"L6L 1H4",
    "sg:province":"ON",
    "sg:tags":[
        "antique"
    ],
    "wof:name":"My Back Shed",
    "wof:placetype":"venue"
},
  "geometry": {"coordinates":[-79.709274292,43.3968772888],"type":"Point"}
}