{
  "type": "Feature",
  "properties": {
    "addr:full":"9809 102 Ave Fairview AB T0H 1L0",
    "addr:housenumber":"9809",
    "addr:postcode":"t0h 1l0",
    "addr:street":"102 Ave",
    "iso:country":"CA",
    "sg:address":"9809 102 Ave",
    "sg:city":"Fairview",
    "sg:classifiers":[
        {
            "category":"Utilities",
            "subcategory":"Fuel Oil & Lpg",
            "type":"Services"
        }
    ],
    "sg:phone":"+1 780 835 5557",
    "sg:postcode":"T0H 1L0",
    "sg:province":"AB",
    "sg:tags":[
        "propane",
        "gas"
    ],
    "wof:name":"Joy Propane",
    "wof:placetype":"venue"
},
  "geometry": {"coordinates":[-118.363907,56.06546],"type":"Point"}
}