{
  "type": "Feature",
  "properties": {
    "iso:country":"CA",
    "sg:address":"866 King Edward St",
    "sg:city":"Winnipeg",
    "sg:classifiers":[
        {
            "category":"Retail",
            "subcategory":"Auto Repair",
            "type":"Services"
        }
    ],
    "sg:phone":"+1 204 783 4327",
    "sg:postcode":"R3H 0P7",
    "sg:province":"MB",
    "sg:tags":[
        "transmission"
    ],
    "wof:name":"Pro-Gear Transmission",
    "wof:placetype":"venue"
},
  "geometry": {"coordinates":[-97.2071380615,49.9030647278],"type":"Point"}
}