{
  "type": "Feature",
  "properties": {
    "addr:full":"100 Hersey St Oromocto NB E2V 1J3",
    "addr:housenumber":"100",
    "addr:postcode":"e2v 1j3",
    "addr:street":"Hersey St",
    "iso:country":"CA",
    "sg:address":"100 Hersey St",
    "sg:city":"Oromocto",
    "sg:classifiers":[
        {
            "category":"Travel",
            "subcategory":"Hotels & Motels",
            "type":"Entertainment"
        }
    ],
    "sg:phone":"+1 506 357 8424",
    "sg:postcode":"E2V 1J3",
    "sg:province":"NB",
    "wof:name":"Oromocto Hotel",
    "wof:placetype":"venue"
},
  "geometry": {"coordinates":[-66.47663879389999,45.8512115479],"type":"Point"}
}