{
  "type": "Feature",
  "properties": {
    "addr:full":"Canmore AB T1W 1P2",
    "addr:postcode":"t1w 1p2",
    "iso:country":"CA",
    "sg:city":"Canmore",
    "sg:classifiers":[
        {
            "category":"Personal",
            "type":"Services"
        }
    ],
    "sg:phone":"+1 403 678 3266",
    "sg:postcode":"T1W 1P2",
    "sg:province":"AB",
    "sg:tags":[
        "therapist",
        "massage"
    ],
    "wof:name":"Magic Fingers Clinic",
    "wof:placetype":"venue"
},
  "geometry": {"coordinates":[-115.351768494,51.0885009766],"type":"Point"}
}