{
  "type": "Feature",
  "properties": {
    "addr:full":"1564 Rue Gilford Montreal QC H2J 1S2",
    "addr:housenumber":"1564",
    "addr:postcode":"h2j 1s2",
    "addr:street":"Rue Gilford",
    "iso:country":"CA",
    "sg:address":"1564 Rue Gilford",
    "sg:city":"Montreal",
    "sg:classifiers":[
        {
            "category":"Professional",
            "subcategory":"Business Services",
            "type":"Services"
        }
    ],
    "sg:phone":"+1 514 521 9442",
    "sg:postcode":"H2J 1S2",
    "sg:province":"QC",
    "sg:tags":[
        "event"
    ],
    "wof:name":"Abdelahad Nadia Communications",
    "wof:placetype":"venue"
},
  "geometry": {"coordinates":[-73.579033,45.533207],"type":"Point"}
}