{
  "type": "Feature",
  "properties": {
    "addr:full":"12 Rue Sainte-Helene Sainte-Helene-DE-Breakeyville QC G0S 1E2",
    "addr:housenumber":"12",
    "addr:postcode":"g0s 1e2",
    "addr:street":"Rue Sainte-Helene Sainte-Helene-De-Breakeyville",
    "iso:country":"CA",
    "sg:address":"12 Rue Sainte-Helene",
    "sg:city":"Sainte-Helene-DE-Breakeyville",
    "sg:classifiers":[
        {
            "category":"Organizations",
            "subcategory":"Professional Association",
            "type":"Services"
        }
    ],
    "sg:phone":"+1 418 832 1671",
    "sg:postcode":"G0S 1E2",
    "sg:province":"QC",
    "wof:name":"Service D'Entraide-Breakeyvle",
    "wof:placetype":"venue"
},
  "geometry": {"coordinates":[-71.2280426025,46.6760635376],"type":"Point"}
}