{
  "type": "Feature",
  "properties": {
    "addr:full":"405 Geddes St Elora ON N0B 1S0",
    "addr:housenumber":"405",
    "addr:postcode":"n0b 1s0",
    "addr:street":"Geddes St",
    "iso:country":"CA",
    "sg:address":"405 Geddes St",
    "sg:city":"Elora",
    "sg:classifiers":[
        {
            "category":"Autos & Motor Vehicles",
            "subcategory":"Auto Supplies",
            "type":"Retail Goods"
        }
    ],
    "sg:phone":"+1 519 846 5685",
    "sg:postcode":"N0B 1S0",
    "sg:province":"ON",
    "sg:tags":[
        "tire"
    ],
    "wof:name":"C & W Enterprises",
    "wof:placetype":"venue"
},
  "geometry": {"coordinates":[-80.43956756590001,43.6909446716],"type":"Point"}
}