{
  "type": "Feature",
  "properties": {
    "addr:full":"1423 Centre St NW Calgary AB T2E 2R8",
    "addr:housenumber":"1423",
    "addr:postcode":"t2e 2r8",
    "addr:street":"Centre St Nw",
    "iso:country":"CA",
    "sg:address":"1423 Centre St NW",
    "sg:city":"Calgary",
    "sg:classifiers":[
        {
            "category":"Restaurant",
            "type":"Food & Drink"
        }
    ],
    "sg:phone":"+1 403 277 8988",
    "sg:postcode":"T2E 2R8",
    "sg:province":"AB",
    "wof:name":"Maxima Bakery",
    "wof:placetype":"venue"
},
  "geometry": {"coordinates":[-114.06398,51.064651],"type":"Point"}
}