{
  "type": "Feature",
  "properties": {
    "addr:full":"39 Dunvegan Dr Richmond Hill ON L4C 9P8",
    "addr:housenumber":"39",
    "addr:postcode":"l4c 9p8",
    "addr:street":"Dunvegan Dr",
    "iso:country":"CA",
    "sg:address":"39 Dunvegan Dr",
    "sg:city":"Richmond Hill",
    "sg:classifiers":[
        {
            "category":"Home & Garden",
            "subcategory":"Building Materials",
            "type":"Retail Goods"
        }
    ],
    "sg:phone":"+1 905 707 6969",
    "sg:postcode":"L4C 9P8",
    "sg:province":"ON",
    "sg:tags":[
        "glass",
        "window",
        "plate"
    ],
    "wof:name":"Agp Auto Glass Professional",
    "wof:placetype":"venue"
},
  "geometry": {"coordinates":[-79.43724060060001,43.8343734741],"type":"Point"}
}