{
  "type": "Feature",
  "properties": {
    "addr:full":"1916 Merivale Rd Nepean ON K2G 1E8",
    "addr:housenumber":"1916",
    "addr:postcode":"k2g 1e8",
    "addr:street":"Merivale Rd",
    "iso:country":"CA",
    "sg:address":"1916 Merivale Rd",
    "sg:city":"Nepean",
    "sg:classifiers":[
        {
            "category":"Sports & Exercise",
            "subcategory":"Bowling",
            "type":"Entertainment"
        }
    ],
    "sg:phone":"+1 613 228 9190",
    "sg:postcode":"K2G 1E8",
    "sg:province":"ON",
    "sg:tags":[
        "center"
    ],
    "wof:name":"Merivale Bowling Ctr",
    "wof:placetype":"venue"
},
  "geometry": {"coordinates":[-75.721008,45.328827],"type":"Point"}
}