{
  "type": "Feature",
  "properties": {
    "addr:full":"672 Arvin Ave Stoney Creek ON L8E 5M8",
    "addr:housenumber":"672",
    "addr:postcode":"l8e 5m8",
    "addr:street":"Arvin Ave",
    "iso:country":"CA",
    "sg:address":"672 Arvin Ave",
    "sg:city":"Stoney Creek",
    "sg:classifiers":[
        {
            "category":"Freight",
            "type":"Transportation"
        }
    ],
    "sg:phone":"+1 905 643 4025",
    "sg:postcode":"L8E 5M8",
    "sg:province":"ON",
    "sg:tags":[
        "trucking"
    ],
    "wof:name":"Penco Transport",
    "wof:placetype":"venue"
},
  "geometry": {"coordinates":[-79.696831,43.224861],"type":"Point"}
}