{
  "type": "Feature",
  "properties": {
    "addr:full":"391 Rue Saint-Hilaire Chicoutimi QC G7J 4E6",
    "addr:housenumber":"391",
    "addr:postcode":"g7j 4e6",
    "addr:street":"Rue Saint-Hilaire",
    "iso:country":"CA",
    "sg:address":"391 Rue Saint-Hilaire",
    "sg:city":"Chicoutimi",
    "sg:classifiers":[
        {
            "category":"Building & Trades",
            "subcategory":"Construction",
            "type":"Services"
        }
    ],
    "sg:phone":"+1 418 543 6677",
    "sg:postcode":"G7J 4E6",
    "sg:province":"QC",
    "sg:tags":[
        "excavating",
        "contractor",
        "general"
    ],
    "wof:name":"Morneau Excavation Enr",
    "wof:placetype":"venue"
},
  "geometry": {"coordinates":[-71.0849,48.426502],"type":"Point"}
}