{
  "type": "Feature",
  "properties": {
    "addr:full":"Montreal QC H1Z 2L2",
    "addr:postcode":"h1z 2l2",
    "iso:country":"CA",
    "sg:city":"Montreal",
    "sg:classifiers":[
        {
            "category":"Insurance",
            "subcategory":"Insurance Agent",
            "type":"Services"
        }
    ],
    "sg:phone":"+1 514 727 0888",
    "sg:postcode":"H1Z 2L2",
    "sg:province":"QC",
    "wof:name":"Assurance Racine & Chamberland",
    "wof:placetype":"venue"
},
  "geometry": {"coordinates":[-73.600479126,45.5700416565],"type":"Point"}
}