{
  "type": "Feature",
  "properties": {
    "addr:full":"Scarborough ON M1V 5E5",
    "addr:postcode":"m1v 5e5",
    "iso:country":"CA",
    "sg:city":"Scarborough",
    "sg:classifiers":[
        {
            "category":"Wholesale",
            "subcategory":"Electrical",
            "type":"Manufacturing & Wholesale Goods"
        }
    ],
    "sg:phone":"+1 416 298 8399",
    "sg:postcode":"M1V 5E5",
    "sg:province":"ON",
    "sg:tags":[
        "alarm",
        "burglar",
        "system"
    ],
    "wof:name":"Peace Security",
    "wof:placetype":"venue"
},
  "geometry": {"coordinates":[-79.291031,43.806625],"type":"Point"}
}