{
  "type": "Feature",
  "properties": {
    "addr:full":"593 Barlow Ave Quesnel BC V2J 2C5",
    "addr:housenumber":"593",
    "addr:postcode":"v2j 2c5",
    "addr:street":"Barlow Ave",
    "iso:country":"CA",
    "sg:address":"593 Barlow Ave",
    "sg:city":"Quesnel",
    "sg:classifiers":[
        {
            "category":"Education",
            "subcategory":"Library",
            "type":"Public Place"
        }
    ],
    "sg:phone":"+1 250 992 7912",
    "sg:postcode":"V2J 2C5",
    "sg:province":"BC",
    "wof:name":"Quesnel Library",
    "wof:placetype":"venue"
},
  "geometry": {"coordinates":[-122.490883,52.977802],"type":"Point"}
}