{
  "type": "Feature",
  "properties": {
    "iso:country":"CA",
    "sg:address":"56 Main St E",
    "sg:city":"Ridgetown",
    "sg:classifiers":[
        {
            "category":"Health Services",
            "subcategory":"Doctor",
            "type":"Services"
        }
    ],
    "sg:phone":"+1 519 674 5560",
    "sg:postcode":"N0P 2C0",
    "sg:province":"ON",
    "sg:tags":[
        "dentist"
    ],
    "wof:name":"Campbell, David B DDS",
    "wof:placetype":"venue"
},
  "geometry": {"coordinates":[-81.885635376,42.4403991699],"type":"Point"}
}