{
  "type": "Feature",
  "properties": {
    "addr:full":"167 Rue Saint-Louis Saint-Donat-DE-Montcalm QC J0T 2C0",
    "addr:housenumber":"167",
    "addr:postcode":"j0t 2c0",
    "addr:street":"Rue Saint-Louis",
    "iso:country":"CA",
    "sg:address":"167 Rue Saint-Louis",
    "sg:city":"Saint-Donat-DE-Montcalm",
    "sg:classifiers":[
        {
            "category":"Building & Trades",
            "subcategory":"Construction",
            "type":"Services"
        }
    ],
    "sg:phone":"+1 819 424 1321",
    "sg:postcode":"J0T 2C0",
    "sg:province":"QC",
    "sg:tags":[
        "demolition",
        "contractor"
    ],
    "wof:name":"S Lavoie Dynamitage Inc",
    "wof:placetype":"venue"
},
  "geometry": {"coordinates":[-74.203552,46.318039],"type":"Point"}
}