{
  "type": "Feature",
  "properties": {
    "addr:full":"6 Times Rd York ON M6E 3B7",
    "addr:housenumber":"6",
    "addr:postcode":"m6e 3b7",
    "addr:street":"Times Rd",
    "iso:country":"CA",
    "sg:address":"6 Times Rd",
    "sg:city":"York",
    "sg:classifiers":[
        {
            "category":"Shopping",
            "subcategory":"Clothing, Apparel, & Fashions",
            "type":"Retail Goods"
        }
    ],
    "sg:phone":"+1 416 781 6403",
    "sg:postcode":"M6E 3B7",
    "sg:province":"ON",
    "sg:tags":[
        "tailor"
    ],
    "wof:name":"Wailer's Connections",
    "wof:placetype":"venue"
},
  "geometry": {"coordinates":[-79.444695,43.697304],"type":"Point"}
}