{
  "type": "Feature",
  "properties": {
    "addr:full":"494 Ch Bella-Vista Saint-Basile-Le-Grand QC J3N 1M4",
    "addr:housenumber":"494",
    "addr:postcode":"j3n 1m4",
    "addr:street":"Ch Bella-Vista",
    "iso:country":"CA",
    "sg:address":"494 Ch Bella-Vista",
    "sg:city":"Saint-Basile-Le-Grand",
    "sg:classifiers":[
        {
            "category":"Retail",
            "subcategory":"Animal Services",
            "type":"Services"
        }
    ],
    "sg:phone":"+1 450 653 3232",
    "sg:postcode":"J3N 1M4",
    "sg:province":"QC",
    "sg:tags":[
        "pet",
        "boarding",
        "sitting"
    ],
    "wof:name":"Laka Inc",
    "wof:placetype":"venue"
},
  "geometry": {"coordinates":[-73.299431,45.497185],"type":"Point"}
}