{
  "type": "Feature",
  "properties": {
    "iso:country":"CA",
    "sg:city":"Rouyn-Noranda",
    "sg:classifiers":[
        {
            "category":"Organizations",
            "subcategory":"Labor Organization",
            "type":"Services"
        }
    ],
    "sg:phone":"+1 819 762 1354",
    "sg:postcode":"J9X 7A2",
    "sg:province":"QC",
    "wof:name":"Ftq",
    "wof:placetype":"venue"
},
  "geometry": {"coordinates":[-79.02718353269999,48.2417488098],"type":"Point"}
}