{
  "type": "Feature",
  "properties": {
    "addr:full":"Granby QC J2G 8C8",
    "addr:postcode":"j2g 8c8",
    "iso:country":"CA",
    "sg:city":"Granby",
    "sg:classifiers":[
        {
            "category":"Autos & Motor Vehicles",
            "subcategory":"Auto Supplies",
            "type":"Retail Goods"
        }
    ],
    "sg:phone":"+1 450 375 4660",
    "sg:postcode":"J2G 8C8",
    "sg:province":"QC",
    "sg:tags":[
        "equipment",
        "parts",
        "truck",
        "automobile"
    ],
    "wof:name":"Peintures Pieces Autos Granby",
    "wof:placetype":"venue"
},
  "geometry": {"coordinates":[-72.721771,45.397995],"type":"Point"}
}