{
  "type": "Feature",
  "properties": {
    "addr:full":"Saint-Lambert-DE-Lauzon QC G0S 2W0",
    "addr:postcode":"g0s 2w0",
    "iso:country":"CA",
    "sg:city":"Saint-Lambert-DE-Lauzon",
    "sg:classifiers":[
        {
            "category":"Building & Trades",
            "subcategory":"Plumbing",
            "type":"Services"
        }
    ],
    "sg:phone":"+1 418 889 9239",
    "sg:postcode":"G0S 2W0",
    "sg:province":"QC",
    "sg:tags":[
        "conditioning",
        "air",
        "system",
        "contractor"
    ],
    "wof:name":"Ventilation C Fortier Inc",
    "wof:placetype":"venue"
},
  "geometry": {"coordinates":[-71.23717499999999,46.600571],"type":"Point"}
}