{
  "type": "Feature",
  "properties": {
    "addr:full":"Edmonton AB T5K 2J1",
    "addr:postcode":"t5k 2j1",
    "iso:country":"CA",
    "sg:city":"Edmonton",
    "sg:classifiers":[
        {
            "category":"Health Services",
            "subcategory":"Doctor",
            "type":"Services"
        }
    ],
    "sg:phone":"+1 780 488 5966",
    "sg:postcode":"T5K 2J1",
    "sg:province":"AB",
    "sg:tags":[
        "dentist"
    ],
    "wof:name":"Chalk, W Nigel DDS",
    "wof:placetype":"venue"
},
  "geometry": {"coordinates":[-113.514168,53.539906],"type":"Point"}
}