{
  "type": "Feature",
  "properties": {
    "addr:full":"1 Adelaide St E # 1500 Toronto ON M5C 2V9",
    "addr:housenumber":"1",
    "addr:postcode":"m5c 2v9",
    "addr:street":"Adelaide St E # 1500",
    "iso:country":"CA",
    "sg:address":"1 Adelaide St E # 1500",
    "sg:city":"Toronto",
    "sg:classifiers":[
        {
            "category":"Insurance",
            "subcategory":"Insurance Agent",
            "type":"Services"
        }
    ],
    "sg:phone":"+1 416 863 0550",
    "sg:postcode":"M5C 2V9",
    "sg:province":"ON",
    "wof:name":"Chubb Insurance CO of Canada",
    "wof:placetype":"venue"
},
  "geometry": {"coordinates":[-79.37823486329999,43.6503601074],"type":"Point"}
}