{
  "type": "Feature",
  "properties": {
    "addr:full":"6431 Steeles Ave E Scarborough ON M1X 1N6",
    "addr:housenumber":"6431",
    "addr:postcode":"m1x 1n6",
    "addr:street":"Steeles Ave E",
    "iso:country":"CA",
    "sg:address":"6431 Steeles Ave E",
    "sg:city":"Scarborough",
    "sg:classifiers":[
        {
            "category":"Recreation",
            "type":"Entertainment"
        }
    ],
    "sg:phone":"+1 416 293 4161",
    "sg:postcode":"M1X 1N6",
    "sg:province":"ON",
    "sg:tags":[
        "course",
        "golf"
    ],
    "wof:name":"Cedar Brae Golf & Country Club",
    "wof:placetype":"venue"
},
  "geometry": {"coordinates":[-79.231621,43.841141],"type":"Point"}
}