{
  "type": "Feature",
  "properties": {
    "addr:full":"Sainte-Sophie-D'Halifax QC G0P 1L0",
    "addr:postcode":"g0p 1l0",
    "iso:country":"CA",
    "sg:city":"Sainte-Sophie-D'Halifax",
    "sg:classifiers":[
        {
            "category":"Building & Trades",
            "subcategory":"Plumbing",
            "type":"Services"
        }
    ],
    "sg:phone":"+1 819 362 3391",
    "sg:postcode":"G0P 1L0",
    "sg:province":"QC",
    "sg:tags":[
        "conditioning",
        "air",
        "system",
        "contractor"
    ],
    "wof:name":"Refrigeration J-G Bizier",
    "wof:placetype":"venue"
},
  "geometry": {"coordinates":[-73.522423,45.388367],"type":"Point"}
}