{
  "type": "Feature",
  "properties": {
    "addr:full":"Mississauga ON L4W 3A4",
    "addr:postcode":"l4w 3a4",
    "iso:country":"CA",
    "sg:city":"Mississauga",
    "sg:classifiers":[
        {
            "category":"Shopping",
            "subcategory":"Clothing, Apparel, & Fashions",
            "type":"Retail Goods"
        }
    ],
    "sg:phone":"+1 905 238 6856",
    "sg:postcode":"L4W 3A4",
    "sg:province":"ON",
    "sg:tags":[
        "shop",
        "bridal"
    ],
    "wof:name":"Elizabeth Stuart Discount Brdl",
    "wof:placetype":"venue"
},
  "geometry": {"coordinates":[-79.640503,43.633751],"type":"Point"}
}