{
  "type": "Feature",
  "properties": {
    "iso:country":"CA",
    "sg:address":"2253 Av Royale",
    "sg:city":"Beauport",
    "sg:classifiers":[
        {
            "category":"Personal",
            "subcategory":"Shoe Repair & Shine",
            "type":"Services"
        }
    ],
    "sg:phone":"+1 418 663 4704",
    "sg:postcode":"G1C 1P5",
    "sg:province":"QC",
    "sg:tags":[
        "repairing",
        "boot"
    ],
    "wof:name":"Cordonnerie Botterie Orleans",
    "wof:placetype":"venue"
},
  "geometry": {"coordinates":[-71.160004,46.883251],"type":"Point"}
}