{
  "type": "Feature",
  "properties": {
    "addr:full":"849 Danforth Ave Toronto ON M4J 1L2",
    "addr:housenumber":"849",
    "addr:postcode":"m4j 1l2",
    "addr:street":"Danforth Ave",
    "iso:country":"CA",
    "sg:address":"849 Danforth Ave",
    "sg:city":"Toronto",
    "sg:classifiers":[
        {
            "category":"Shopping",
            "subcategory":"Department Store",
            "type":"Retail Goods"
        }
    ],
    "sg:phone":"+1 416 465 9599",
    "sg:postcode":"M4J 1L2",
    "sg:province":"ON",
    "sg:tags":[
        "shop"
    ],
    "wof:name":"What A Bargain",
    "wof:placetype":"venue"
},
  "geometry": {"coordinates":[-79.340171814,43.6797904968],"type":"Point"}
}