{
  "type": "Feature",
  "properties": {
    "addr:full":"219 Cardinal Cres Saskatoon SK S7L 7K8",
    "addr:housenumber":"219",
    "addr:postcode":"s7l 7k8",
    "addr:street":"Cardinal Cres",
    "iso:country":"CA",
    "sg:address":"219 Cardinal Cres",
    "sg:city":"Saskatoon",
    "sg:classifiers":[
        {
            "category":"Freight",
            "type":"Transportation"
        }
    ],
    "sg:phone":"+1 306 242 8300",
    "sg:postcode":"S7L 7K8",
    "sg:province":"SK",
    "sg:tags":[
        "trucking"
    ],
    "wof:name":"Rsb Logistic Inc",
    "wof:placetype":"venue"
},
  "geometry": {"coordinates":[-106.68701934800001,52.1535377502],"type":"Point"}
}