{
  "type": "Feature",
  "properties": {
    "addr:full":"10006 103 St Morinville AB T8R 1R7",
    "addr:housenumber":"10006",
    "addr:postcode":"t8r 1r7",
    "addr:street":"103 St",
    "iso:country":"CA",
    "sg:address":"10006 103 St",
    "sg:city":"Morinville",
    "sg:classifiers":[
        {
            "category":"Professional",
            "subcategory":"Accounting & Tax Preparation",
            "type":"Services"
        }
    ],
    "sg:phone":"+1 780 939 5543",
    "sg:postcode":"T8R 1R7",
    "sg:province":"AB",
    "sg:tags":[
        "return",
        "filing"
    ],
    "wof:name":"H & R Block Canada Inc",
    "wof:placetype":"venue"
},
  "geometry": {"coordinates":[-113.651405,53.802025],"type":"Point"}
}