{
  "type": "Feature",
  "properties": {
    "addr:full":"419 Rue Alice Joliette QC J6E 5B7",
    "addr:housenumber":"419",
    "addr:postcode":"j6e 5b7",
    "addr:street":"Rue Alice",
    "iso:country":"CA",
    "sg:address":"419 Rue Alice",
    "sg:city":"Joliette",
    "sg:classifiers":[
        {
            "category":"Food & Beverages",
            "subcategory":"Groceries & Convenience Stores",
            "type":"Retail Goods"
        }
    ],
    "sg:phone":"+1 450 753 3706",
    "sg:postcode":"J6E 5B7",
    "sg:province":"QC",
    "wof:name":"Depanneur St-Jean-Baptiste Enr",
    "wof:placetype":"venue"
},
  "geometry": {"coordinates":[-73.432716,46.02124],"type":"Point"}
}