{
  "type": "Feature",
  "properties": {
    "addr:full":"343 11 Ave SW Calgary AB T2R 0C7",
    "addr:postcode":"t2r 0c7",
    "addr:street":"343 11 Ave Sw",
    "iso:country":"CA",
    "sg:address":"343 11 Ave SW",
    "sg:city":"Calgary",
    "sg:classifiers":[
        {
            "category":"Utilities",
            "subcategory":"Mobile Phone",
            "type":"Services"
        }
    ],
    "sg:phone":"+1 403 543 5045",
    "sg:postcode":"T2R 0C7",
    "sg:province":"AB",
    "sg:tags":[
        "system",
        "telephone",
        "equipment",
        "paging",
        "signaling",
        "cellular"
    ],
    "wof:name":"Air Source",
    "wof:placetype":"venue"
},
  "geometry": {"coordinates":[-114.069061,51.042404],"type":"Point"}
}