{
  "type": "Feature",
  "properties": {
    "addr:full":"429 Rue Saint-Germain E Rimouski-Est QC G5L 1E3",
    "addr:housenumber":"429",
    "addr:postcode":"g5l 1e3",
    "addr:street":"Rue Saint-Germain E Rimouski-Est",
    "iso:country":"CA",
    "sg:address":"429 Rue Saint-Germain E",
    "sg:city":"Rimouski-Est",
    "sg:classifiers":[
        {
            "category":"Health Services",
            "subcategory":"Doctor",
            "type":"Services"
        }
    ],
    "sg:phone":"+1 418 723 0213",
    "sg:postcode":"G5L 1E3",
    "sg:province":"QC",
    "sg:tags":[
        "clinic",
        "dentist"
    ],
    "wof:name":"Clinique De'Orthodontie DE",
    "wof:placetype":"venue"
},
  "geometry": {"coordinates":[-68.51533499999999,48.471355],"type":"Point"}
}