{
  "type": "Feature",
  "properties": {
    "addr:full":"1170 Powell St Vancouver BC V6A 1J3",
    "addr:housenumber":"1170",
    "addr:postcode":"v6a 1j3",
    "addr:street":"Powell St",
    "iso:country":"CA",
    "sg:address":"1170 Powell St",
    "sg:city":"Vancouver",
    "sg:classifiers":[
        {
            "category":"Wholesale",
            "subcategory":"Scrap",
            "type":"Manufacturing & Wholesale Goods"
        }
    ],
    "sg:phone":"+1 604 254 2734",
    "sg:postcode":"V6A 1J3",
    "sg:province":"BC",
    "sg:tags":[
        "recycling",
        "center"
    ],
    "wof:name":"North Star Metal Salvage Ltd",
    "wof:placetype":"venue"
},
  "geometry": {"coordinates":[-123.07953643800001,49.2828598022],"type":"Point"}
}