{
  "type": "Feature",
  "properties": {
    "addr:full":"66 Rue Calder Shediac NB E4P 1K8",
    "addr:housenumber":"66",
    "addr:postcode":"e4p 1k8",
    "addr:street":"Rue Calder",
    "iso:country":"CA",
    "sg:address":"66 Rue Calder",
    "sg:city":"Shediac",
    "sg:classifiers":[
        {
            "category":"Government",
            "subcategory":"Office",
            "type":"Public Place"
        }
    ],
    "sg:phone":"+1 506 532 7013",
    "sg:postcode":"E4P 1K8",
    "sg:province":"NB",
    "sg:tags":[
        "village"
    ],
    "wof:name":"Shediac Municipal Garage",
    "wof:placetype":"venue"
},
  "geometry": {"coordinates":[-64.545753479,46.2226448059],"type":"Point"}
}