{
  "type": "Feature",
  "properties": {
    "addr:full":"Calgary AB T2R 0C9",
    "addr:postcode":"t2r 0c9",
    "iso:country":"CA",
    "sg:city":"Calgary",
    "sg:classifiers":[
        {
            "category":"Professional",
            "subcategory":"Accounting & Tax Preparation",
            "type":"Services"
        }
    ],
    "sg:phone":"+1 403 266 1575",
    "sg:postcode":"T2R 0C9",
    "sg:province":"AB",
    "sg:tags":[
        "accountant"
    ],
    "wof:name":"Rahal Warren & Chugh",
    "wof:placetype":"venue"
},
  "geometry": {"coordinates":[-114.072257996,51.0425033569],"type":"Point"}
}