{
  "type": "Feature",
  "properties": {
    "addr:full":"Edmonton AB T5H 1B8",
    "addr:postcode":"t5h 1b8",
    "iso:country":"CA",
    "sg:city":"Edmonton",
    "sg:classifiers":[
        {
            "category":"Restaurant",
            "type":"Food & Drink"
        }
    ],
    "sg:phone":"+1 780 447 4727",
    "sg:postcode":"T5H 1B8",
    "sg:province":"AB",
    "wof:name":"Rosario's Pizza & Pub",
    "wof:placetype":"venue"
},
  "geometry": {"coordinates":[-113.524108887,53.5532989502],"type":"Point"}
}