{
  "type": "Feature",
  "properties": {
    "addr:full":"Slave Lake AB T0G 2A3",
    "addr:postcode":"t0g 2a3",
    "iso:country":"CA",
    "sg:city":"Slave Lake",
    "sg:classifiers":[
        {
            "category":"Real Estate",
            "subcategory":"Real Estate Agent",
            "type":"Services"
        }
    ],
    "sg:phone":"+1 780 849 4113",
    "sg:postcode":"T0G 2A3",
    "sg:province":"AB",
    "sg:tags":[
        "apartment",
        "rental",
        "agency"
    ],
    "wof:name":"Spruce Land Developments Ltd",
    "wof:placetype":"venue"
},
  "geometry": {"coordinates":[-114.771912,55.269184],"type":"Point"}
}