{
  "type": "Feature",
  "properties": {
    "addr:full":"Sainte-Foy QC G2G 2P2",
    "addr:postcode":"g2g 2p2",
    "iso:country":"CA",
    "sg:city":"Sainte-Foy",
    "sg:classifiers":[
        {
            "category":"Wholesale",
            "subcategory":"Machinery & Supplies",
            "type":"Manufacturing & Wholesale Goods"
        }
    ],
    "sg:phone":"+1 418 872 6010",
    "sg:postcode":"G2G 2P2",
    "sg:province":"QC",
    "sg:tags":[
        "equipment",
        "parts",
        "tractor"
    ],
    "wof:name":"O'Neil Traction & Equipement",
    "wof:placetype":"venue"
},
  "geometry": {"coordinates":[-71.384941,46.807003],"type":"Point"}
}