{
  "type": "Feature",
  "properties": {
    "addr:full":"1 Boul Desjardins O Sainte-Therese QC J7E 1C9",
    "addr:housenumber":"1",
    "addr:postcode":"j7e 1c9",
    "addr:street":"Boul Desjardins O Sainte-Therese",
    "iso:country":"CA",
    "sg:address":"1 Boul Desjardins O",
    "sg:city":"Sainte-Therese",
    "sg:classifiers":[
        {
            "category":"Retail",
            "subcategory":"Auto Repair",
            "type":"Services"
        }
    ],
    "sg:phone":"+1 450 437 4550",
    "sg:postcode":"J7E 1C9",
    "sg:province":"QC",
    "sg:tags":[
        "repairing",
        "automobile"
    ],
    "wof:name":"J Brosseau Garage Inc",
    "wof:placetype":"venue"
},
  "geometry": {"coordinates":[-73.83275604249999,45.6333656311],"type":"Point"}
}