{
  "type": "Feature",
  "properties": {
    "addr:full":"127 3rd Ave W Melville SK S0A 2P0",
    "addr:housenumber":"127",
    "addr:postcode":"s0a 2p0",
    "addr:street":"3Rd Ave W",
    "iso:country":"CA",
    "sg:address":"127 3rd Ave W",
    "sg:city":"Melville",
    "sg:classifiers":[
        {
            "category":"Food & Beverages",
            "subcategory":"Meat & Fish",
            "type":"Retail Goods"
        }
    ],
    "sg:phone":"+1 306 728 2435",
    "sg:postcode":"S0A 2P0",
    "sg:province":"SK",
    "wof:name":"Napady Meats",
    "wof:placetype":"venue"
},
  "geometry": {"coordinates":[-102.816093,50.931126],"type":"Point"}
}