{
  "type": "Feature",
  "properties": {
    "addr:full":"875 King Edward St Winnipeg MB R3H 0P8",
    "addr:housenumber":"875",
    "addr:postcode":"r3h 0p8",
    "addr:street":"King Edward St",
    "iso:country":"CA",
    "sg:address":"875 King Edward St",
    "sg:city":"Winnipeg",
    "sg:classifiers":[
        {
            "category":"Manufacturing",
            "subcategory":"Tools & Machinery",
            "type":"Manufacturing & Wholesale Goods"
        }
    ],
    "sg:phone":"+1 204 987 7800",
    "sg:postcode":"R3H 0P8",
    "sg:province":"MB",
    "sg:tags":[
        "equipment",
        "oxygen",
        "welding"
    ],
    "wof:name":"Boc Gases",
    "wof:placetype":"venue"
},
  "geometry": {"coordinates":[-97.206665,49.903603],"type":"Point"}
}