{
  "type": "Feature",
  "properties": {
    "addr:full":"3777 Strandherd Dr Nepean ON K2J 4B1",
    "addr:housenumber":"3777",
    "addr:postcode":"k2j 4b1",
    "addr:street":"Strandherd Dr",
    "iso:country":"CA",
    "sg:address":"3777 Strandherd Dr",
    "sg:city":"Nepean",
    "sg:classifiers":[
        {
            "category":"Shopping",
            "subcategory":"Computers & Home Electronics",
            "type":"Retail Goods"
        }
    ],
    "sg:phone":"+1 613 823 7667",
    "sg:postcode":"K2J 4B1",
    "sg:province":"ON",
    "sg:tags":[
        "equipment",
        "dealer"
    ],
    "wof:name":"Kaylen Computers Inc",
    "wof:placetype":"venue"
},
  "geometry": {"coordinates":[-75.74799299999999,45.269745],"type":"Point"}
}