{
  "type": "Feature",
  "properties": {
    "addr:full":"414 Kenneth Ave North York ON M2N 4W1",
    "addr:housenumber":"414",
    "addr:postcode":"m2n 4w1",
    "addr:street":"Kenneth Ave",
    "iso:country":"CA",
    "sg:address":"414 Kenneth Ave",
    "sg:city":"North York",
    "sg:classifiers":[
        {
            "category":"Health Services",
            "subcategory":"Doctor",
            "type":"Services"
        }
    ],
    "sg:phone":"+1 416 222 2331",
    "sg:postcode":"M2N 4W1",
    "sg:province":"ON",
    "sg:tags":[
        "physician",
        "surgeon"
    ],
    "wof:name":"Steinberg, Jeffrey M MD",
    "wof:placetype":"venue"
},
  "geometry": {"coordinates":[-79.411079,43.776985],"type":"Point"}
}