{
  "type": "Feature",
  "properties": {
    "iso:country":"CA",
    "sg:address":"310 Bartlett Ave N",
    "sg:city":"Toronto",
    "sg:classifiers":[
        {
            "category":"Manufacturing",
            "subcategory":"Tools & Machinery",
            "type":"Manufacturing & Wholesale Goods"
        }
    ],
    "sg:phone":"+1 416 531 4611",
    "sg:postcode":"M6H 3G7",
    "sg:province":"ON",
    "sg:tags":[
        "machine",
        "shop"
    ],
    "wof:name":"Viking Engine & Tool CO Ltd",
    "wof:placetype":"venue"
},
  "geometry": {"coordinates":[-79.43715667719999,43.6703414917],"type":"Point"}
}