{
  "type": "Feature",
  "properties": {
    "addr:full":"Honey Harbour ON P0E 1E0",
    "addr:postcode":"p0e 1e0",
    "iso:country":"CA",
    "sg:city":"Honey Harbour",
    "sg:classifiers":[
        {
            "category":"Recreation",
            "subcategory":"Marina",
            "type":"Entertainment"
        }
    ],
    "sg:phone":"+1 705 756 1660",
    "sg:postcode":"P0E 1E0",
    "sg:province":"ON",
    "wof:name":"Minors Bay Marina",
    "wof:placetype":"venue"
},
  "geometry": {"coordinates":[-79.82055699999999,44.867599],"type":"Point"}
}