{
  "type": "Feature",
  "properties": {
    "addr:full":"Miramichi NB E1N 6K8",
    "addr:postcode":"e1n 6k8",
    "iso:country":"CA",
    "sg:city":"Miramichi",
    "sg:classifiers":[
        {
            "category":"Professional",
            "subcategory":"Research",
            "type":"Services"
        }
    ],
    "sg:phone":"+1 506 778 6700",
    "sg:postcode":"E1N 6K8",
    "sg:province":"NB",
    "sg:tags":[
        "assistance",
        "program",
        "technology"
    ],
    "wof:name":"Miratech Inc",
    "wof:placetype":"venue"
},
  "geometry": {"coordinates":[-65.44701385499999,47.0138511658],"type":"Point"}
}