{
  "type": "Feature",
  "properties": {
    "addr:full":"40 Finchgate Blvd # 123 Brampton ON L6T 3J1",
    "addr:housenumber":"40",
    "addr:postcode":"l6t 3j1",
    "addr:street":"Finchgate Blvd # 123",
    "iso:country":"CA",
    "sg:address":"40 Finchgate Blvd # 123",
    "sg:city":"Brampton",
    "sg:classifiers":[
        {
            "category":"Health Services",
            "subcategory":"Doctor",
            "type":"Services"
        }
    ],
    "sg:phone":"+1 905 789 6800",
    "sg:postcode":"L6T 3J1",
    "sg:province":"ON",
    "sg:tags":[
        "physician",
        "surgeon"
    ],
    "wof:name":"Chang, Daniel MD",
    "wof:placetype":"venue"
},
  "geometry": {"coordinates":[-79.7118148804,43.7273521423],"type":"Point"}
}