{
  "type": "Feature",
  "properties": {
    "addr:full":"Nanisivik NU X0A 0X0",
    "addr:postcode":"x0a 0x0",
    "iso:country":"CA",
    "sg:city":"Nanisivik",
    "sg:classifiers":[
        {
            "category":"Government",
            "subcategory":"Office",
            "type":"Public Place"
        }
    ],
    "sg:phone":"+1 867 436 7404",
    "sg:postcode":"X0A 0X0",
    "sg:province":"NU",
    "wof:name":"N T Executive",
    "wof:placetype":"venue"
},
  "geometry": {"coordinates":[-84.5329208374,73.0354232788],"type":"Point"}
}