{
  "type": "Feature",
  "properties": {
    "addr:full":"PO Box 156 Brigus NL A0A 1K0",
    "addr:housenumber":"po",
    "addr:postcode":"a0a 1k0",
    "addr:street":"Box 156",
    "iso:country":"CA",
    "sg:address":"PO Box 156",
    "sg:city":"Brigus",
    "sg:classifiers":[
        {
            "category":"Organizations",
            "subcategory":"Professional Association",
            "type":"Services"
        }
    ],
    "sg:phone":"+1 709 528 4443",
    "sg:postcode":"A0A 1K0",
    "sg:province":"NL",
    "sg:tags":[
        "club"
    ],
    "wof:name":"Royal Canadian Legion 65",
    "wof:placetype":"venue"
},
  "geometry": {"coordinates":[-53.232131958,47.530632019],"type":"Point"}
}