{
  "type": "Feature",
  "properties": {
    "addr:full":"4904 50th St Onoway AB T0E 1V0",
    "addr:housenumber":"4904",
    "addr:postcode":"t0e 1v0",
    "addr:street":"50Th St",
    "iso:country":"CA",
    "sg:address":"4904 50th St",
    "sg:city":"Onoway",
    "sg:classifiers":[
        {
            "category":"Restaurant",
            "type":"Food & Drink"
        }
    ],
    "sg:phone":"+1 780 967 2808",
    "sg:postcode":"T0E 1V0",
    "sg:province":"AB",
    "wof:name":"Laramie's Saloon",
    "wof:placetype":"venue"
},
  "geometry": {"coordinates":[-114.193016052,53.70287323],"type":"Point"}
}