{
  "type": "Feature",
  "properties": {
    "iso:country":"CA",
    "sg:address":"SW 33 5 4E",
    "sg:city":"St Pierre Jolys",
    "sg:classifiers":[
        {
            "category":"Wholesale",
            "subcategory":"Construction Materials",
            "type":"Manufacturing & Wholesale Goods"
        }
    ],
    "sg:phone":"+1 204 433 7654",
    "sg:postcode":"R0A 1V0",
    "sg:province":"MB",
    "sg:tags":[
        "sand",
        "gravel"
    ],
    "wof:name":"St Pierre Gravel",
    "wof:placetype":"venue"
},
  "geometry": {"coordinates":[-96.9851226807,49.4407081604],"type":"Point"}
}