{
  "type": "Feature",
  "properties": {
    "addr:full":"5411 the Ace Line Erin ON N0B 1T0",
    "addr:housenumber":"5411",
    "addr:postcode":"n0b 1t0",
    "addr:street":"The Ace Line",
    "iso:country":"CA",
    "sg:address":"5411 the Ace Line",
    "sg:city":"Erin",
    "sg:classifiers":[
        {
            "category":"Real Estate",
            "subcategory":"Surveying",
            "type":"Services"
        }
    ],
    "sg:phone":"+1 519 833 2380",
    "sg:postcode":"N0B 1T0",
    "sg:province":"ON",
    "sg:tags":[
        "surveyor"
    ],
    "wof:name":"J R Finnie Ontario Land Srvyr",
    "wof:placetype":"venue"
},
  "geometry": {"coordinates":[-80.064201,43.770481],"type":"Point"}
}