{
  "type": "Feature",
  "properties": {
    "addr:full":"1310 1E Av # 15 Saint-Redempteur QC G6K 1A5",
    "addr:housenumber":"1310",
    "addr:postcode":"g6k 1a5",
    "addr:street":"1E Av # 15 Saint-Redempteur",
    "iso:country":"CA",
    "sg:address":"1310 1E Av # 15",
    "sg:city":"Saint-Redempteur",
    "sg:classifiers":[
        {
            "category":"Personal",
            "subcategory":"Beauty Salon",
            "type":"Services"
        }
    ],
    "sg:phone":"+1 418 831 7548",
    "sg:postcode":"G6K 1A5",
    "sg:province":"QC",
    "wof:name":"Salon DE Coiffure Studiocoiffe",
    "wof:placetype":"venue"
},
  "geometry": {"coordinates":[-71.28537,46.699284],"type":"Point"}
}