{
  "type": "Feature",
  "properties": {
    "addr:full":"181 Rue Pie-Xii Baie-Comeau QC G5C 1S1",
    "addr:housenumber":"181",
    "addr:postcode":"g5c 1s1",
    "addr:street":"Rue Pie-Xii",
    "iso:country":"CA",
    "sg:address":"181 Rue Pie-Xii",
    "sg:city":"Baie-Comeau",
    "sg:classifiers":[
        {
            "category":"Building & Trades",
            "subcategory":"Landscaping Services",
            "type":"Services"
        }
    ],
    "sg:phone":"+1 418 589 2855",
    "sg:postcode":"G5C 1S1",
    "sg:province":"QC",
    "sg:tags":[
        "lawn",
        "maintenance",
        "grounds"
    ],
    "wof:name":"Soluvert Inc",
    "wof:placetype":"venue"
},
  "geometry": {"coordinates":[-68.243233,49.190643],"type":"Point"}
}