{
  "type": "Feature",
  "properties": {
    "iso:country":"CA",
    "sg:address":"219 Bell St N #A",
    "sg:city":"Ottawa",
    "sg:classifiers":[
        {
            "category":"Shopping",
            "subcategory":"Computers & Home Electronics",
            "type":"Retail Goods"
        }
    ],
    "sg:phone":"+1 613 234 8257",
    "sg:postcode":"K1R 7E4",
    "sg:province":"ON",
    "sg:tags":[
        "equipment",
        "dealer"
    ],
    "wof:name":"Trans Computer Systems",
    "wof:placetype":"venue"
},
  "geometry": {"coordinates":[-75.7051849365,45.405670166],"type":"Point"}
}