{
  "type": "Feature",
  "properties": {
    "addr:full":"Brantford ON N3R 1H9",
    "addr:postcode":"n3r 1h9",
    "iso:country":"CA",
    "sg:city":"Brantford",
    "sg:classifiers":[
        {
            "category":"Organizations",
            "subcategory":"Professional Association",
            "type":"Services"
        }
    ],
    "sg:phone":"+1 519 753 2566",
    "sg:postcode":"N3R 1H9",
    "sg:province":"ON",
    "wof:name":"Cancer Society",
    "wof:placetype":"venue"
},
  "geometry": {"coordinates":[-80.28997039790001,43.1610908508],"type":"Point"}
}