{
  "type": "Feature",
  "properties": {
    "iso:country":"CA",
    "sg:address":"152 High St",
    "sg:city":"Sutton West",
    "sg:classifiers":[
        {
            "category":"Social Services",
            "type":"Services"
        }
    ],
    "sg:phone":"+1 905 722 6484",
    "sg:postcode":"L0E 1R0",
    "sg:province":"ON",
    "sg:tags":[
        "organization",
        "welfare"
    ],
    "wof:name":"York Support Svc Network",
    "wof:placetype":"venue"
},
  "geometry": {"coordinates":[-79.358009,44.303253],"type":"Point"}
}