{
  "type": "Feature",
  "properties": {
    "addr:full":"3612 Kingsway Vancouver BC V5R 5M2",
    "addr:housenumber":"3612",
    "addr:postcode":"v5r 5m2",
    "addr:street":"Kingsway",
    "iso:country":"CA",
    "sg:address":"3612 Kingsway",
    "sg:city":"Vancouver",
    "sg:classifiers":[
        {
            "category":"Personal",
            "subcategory":"Beauty Salon",
            "type":"Services"
        }
    ],
    "sg:phone":"+1 604 438 3346",
    "sg:postcode":"V5R 5M2",
    "sg:province":"BC",
    "wof:name":"Anita Hair Studio",
    "wof:placetype":"venue"
},
  "geometry": {"coordinates":[-123.026733398,49.2320480347],"type":"Point"}
}