{
  "type": "Feature",
  "properties": {
    "addr:full":"Elliot Lake ON P5A 2T1",
    "addr:postcode":"p5a 2t1",
    "iso:country":"CA",
    "sg:city":"Elliot Lake",
    "sg:classifiers":[
        {
            "category":"Building & Trades",
            "subcategory":"Construction",
            "type":"Services"
        }
    ],
    "sg:phone":"+1 705 848 2062",
    "sg:postcode":"P5A 2T1",
    "sg:province":"ON",
    "sg:tags":[
        "maker",
        "cabinet"
    ],
    "wof:name":"Timber Cabinet & Custom",
    "wof:placetype":"venue"
},
  "geometry": {"coordinates":[-82.667511,46.40097],"type":"Point"}
}