{
  "type": "Feature",
  "properties": {
    "iso:country":"CA",
    "sg:address":"184 Av Du Parc",
    "sg:city":"Laval",
    "sg:classifiers":[
        {
            "category":"Organizations",
            "subcategory":"Religious Organization",
            "type":"Services"
        }
    ],
    "sg:phone":"+1 450 629 1700",
    "sg:postcode":"H7N 3X2",
    "sg:province":"QC",
    "sg:tags":[
        "church"
    ],
    "wof:name":"First Romanian Baptist Church",
    "wof:placetype":"venue"
},
  "geometry": {"coordinates":[-73.707321,45.554447],"type":"Point"}
}