{
  "type": "Feature",
  "properties": {
    "addr:full":"25 10th Ave S Cranbrook BC V1C 2M9",
    "addr:housenumber":"25",
    "addr:postcode":"bc v1c 2m9",
    "addr:street":"10Th Ave S",
    "iso:country":"CA",
    "sg:address":"25 10th Ave S",
    "sg:city":"Cranbrook",
    "sg:classifiers":[
        {
            "category":"Banks & Credit Unions",
            "subcategory":"Bank",
            "type":"Services"
        }
    ],
    "sg:phone":"+1 250 426 1888",
    "sg:postcode":"V1C 2M9",
    "sg:province":"BC",
    "sg:tags":[
        "loan",
        "real estate"
    ],
    "wof:name":"Cmc Automated Mortgage Corp",
    "wof:placetype":"venue"
},
  "geometry": {"coordinates":[-115.76776886,49.511592865],"type":"Point"}
}