{
  "type": "Feature",
  "properties": {
    "addr:full":"360 Industrial Pky S Aurora ON L4G 3V7",
    "addr:housenumber":"360",
    "addr:postcode":"l4g 3v7",
    "addr:street":"Industrial Pky",
    "iso:country":"CA",
    "sg:address":"360 Industrial Pky S",
    "sg:city":"Aurora",
    "sg:classifiers":[
        {
            "category":"Manufacturing",
            "subcategory":"Glass & Minerals",
            "type":"Manufacturing & Wholesale Goods"
        }
    ],
    "sg:phone":"+1 905 727 5161",
    "sg:postcode":"L4G 3V7",
    "sg:province":"ON",
    "sg:tags":[
        "instrument",
        "scientific",
        "apparatus"
    ],
    "wof:name":"Aurora Scientific Inc",
    "wof:placetype":"venue"
},
  "geometry": {"coordinates":[-79.4547042847,43.9856643677],"type":"Point"}
}