{
  "type": "Feature",
  "properties": {
    "addr:full":"585 Rue DE L'Arena Saint-Nicolas QC G7A 1E4",
    "addr:housenumber":"585",
    "addr:postcode":"g7a 1e4",
    "addr:street":"Rue De L'Arena",
    "iso:country":"CA",
    "sg:address":"585 Rue DE L'Arena",
    "sg:city":"Saint-Nicolas",
    "sg:classifiers":[
        {
            "category":"Arena",
            "subcategory":"Sports Club",
            "type":"Entertainment"
        }
    ],
    "sg:phone":"+1 418 831 3836",
    "sg:postcode":"G7A 1E4",
    "sg:province":"QC",
    "sg:tags":[
        "athletic",
        "fields",
        "stadium",
        "government"
    ],
    "wof:name":"Bernieres Bsr Arena",
    "wof:placetype":"venue"
},
  "geometry": {"coordinates":[-71.29836299999999,46.69923],"type":"Point"}
}