{
  "type": "Feature",
  "properties": {
    "addr:full":"256 Mercer St Chatham ON N7M 4B7",
    "addr:housenumber":"256",
    "addr:postcode":"n7m 4b7",
    "addr:street":"Mercer St",
    "iso:country":"CA",
    "sg:address":"256 Mercer St",
    "sg:city":"Chatham",
    "sg:classifiers":[
        {
            "category":"Home & Garden",
            "subcategory":"Household Appliances",
            "type":"Retail Goods"
        }
    ],
    "sg:phone":"+1 519 354 0514",
    "sg:postcode":"N7M 4B7",
    "sg:province":"ON",
    "wof:name":"Ken's Appliance Repair",
    "wof:placetype":"venue"
},
  "geometry": {"coordinates":[-82.16371917719999,42.3973731995],"type":"Point"}
}