{
  "type": "Feature",
  "properties": {
    "addr:full":"360 Caradoc St S Strathroy ON N7G 2P6",
    "addr:housenumber":"360",
    "addr:postcode":"n7g 2p6",
    "addr:street":"Caradoc St S",
    "iso:country":"CA",
    "sg:address":"360 Caradoc St S",
    "sg:city":"Strathroy",
    "sg:classifiers":[
        {
            "category":"Shopping",
            "type":"Retail Goods"
        }
    ],
    "sg:phone":"+1 519 246 1021",
    "sg:postcode":"N7G 2P6",
    "sg:province":"ON",
    "sg:tags":[
        "pet",
        "food",
        "supply"
    ],
    "wof:name":"Pet Valu Discount Pet Foods",
    "wof:placetype":"venue"
},
  "geometry": {"coordinates":[-81.613647,42.947498],"type":"Point"}
}