{
  "type": "Feature",
  "properties": {
    "addr:full":"610 Queen St E Sault Ste Marie ON P6A 2A4",
    "addr:housenumber":"610",
    "addr:postcode":"p6a 2a4",
    "addr:street":"Queen St E",
    "iso:country":"CA",
    "sg:address":"610 Queen St E",
    "sg:city":"Sault Ste Marie",
    "sg:classifiers":[
        {
            "category":"Shopping",
            "subcategory":"Clothing, Apparel, & Fashions",
            "type":"Retail Goods"
        }
    ],
    "sg:phone":"+1 705 942 3456",
    "sg:postcode":"P6A 2A4",
    "sg:province":"ON",
    "sg:tags":[
        "shop",
        "bridal"
    ],
    "wof:name":"Bridal Closet",
    "wof:placetype":"venue"
},
  "geometry": {"coordinates":[-84.3288345337,46.5086479187],"type":"Point"}
}