{
  "type": "Feature",
  "properties": {
    "addr:full":"345 Blake St Barrie ON L4M 1L1",
    "addr:housenumber":"345",
    "addr:postcode":"l4m 1l1",
    "addr:street":"Blake St",
    "iso:country":"CA",
    "sg:address":"345 Blake St",
    "sg:city":"Barrie",
    "sg:classifiers":[
        {
            "category":"Building & Trades",
            "subcategory":"Construction",
            "type":"Services"
        }
    ],
    "sg:phone":"+1 705 733 8302",
    "sg:postcode":"L4M 1L1",
    "sg:province":"ON",
    "sg:tags":[
        "roofing",
        "contractor"
    ],
    "wof:name":"Superior Roofing",
    "wof:placetype":"venue"
},
  "geometry": {"coordinates":[-79.6552200317,44.3976325989],"type":"Point"}
}