{
  "type": "Feature",
  "properties": {
    "addr:full":"47 Rue Principale Saint-Basile-Le-Grand QC J3N 1M3",
    "addr:housenumber":"47",
    "addr:postcode":"j3n 1m3",
    "addr:street":"Rue Principale",
    "iso:country":"CA",
    "sg:address":"47 Rue Principale",
    "sg:city":"Saint-Basile-Le-Grand",
    "sg:classifiers":[
        {
            "category":"Freight",
            "type":"Transportation"
        }
    ],
    "sg:phone":"+1 450 653 0751",
    "sg:postcode":"J3N 1M3",
    "sg:province":"QC",
    "sg:tags":[
        "carriage"
    ],
    "wof:name":"Caleches Boisvert Inc",
    "wof:placetype":"venue"
},
  "geometry": {"coordinates":[-73.271568,45.546944],"type":"Point"}
}