{
  "type": "Feature",
  "properties": {
    "addr:full":"2808 Lupine Crt Coquitlam BC V3E 2S4",
    "addr:housenumber":"2808",
    "addr:postcode":"v3e 2s4",
    "addr:street":"Lupine Crt",
    "iso:country":"CA",
    "sg:address":"2808 Lupine Crt",
    "sg:city":"Coquitlam",
    "sg:classifiers":[
        {
            "category":"Wholesale",
            "subcategory":"Electrical",
            "type":"Manufacturing & Wholesale Goods"
        }
    ],
    "sg:phone":"+1 604 472 0288",
    "sg:postcode":"V3E 2S4",
    "sg:province":"BC",
    "sg:tags":[
        "instrument",
        "testing",
        "scientific",
        "apparatus"
    ],
    "wof:name":"Alternative Inspection",
    "wof:placetype":"venue"
},
  "geometry": {"coordinates":[-122.81142425500001,49.2948417664],"type":"Point"}
}