{
  "type": "Feature",
  "properties": {
    "addr:full":"185 Bartley Dr North York ON M4A 1E6",
    "addr:housenumber":"185",
    "addr:postcode":"m4a 1e6",
    "addr:street":"Bartley Dr",
    "iso:country":"CA",
    "sg:address":"185 Bartley Dr",
    "sg:city":"North York",
    "sg:classifiers":[
        {
            "category":"Professional",
            "subcategory":"Computer Services",
            "type":"Services"
        }
    ],
    "sg:phone":"+1 416 750 0210",
    "sg:postcode":"M4A 1E6",
    "sg:province":"ON",
    "sg:tags":[
        "internet"
    ],
    "wof:name":"Sonic E Learning Inc",
    "wof:placetype":"venue"
},
  "geometry": {"coordinates":[-79.312714,43.720421],"type":"Point"}
}