{
  "type": "Feature",
  "properties": {
    "addr:full":"1727 Rue Jean-Talon E Montreal QC H2E 1T3",
    "addr:housenumber":"1727",
    "addr:postcode":"h2e 1t3",
    "addr:street":"Rue Jean-Talon E",
    "iso:country":"CA",
    "sg:address":"1727 Rue Jean-Talon E",
    "sg:city":"Montreal",
    "sg:classifiers":[
        {
            "category":"Shopping",
            "subcategory":"Florist",
            "type":"Retail Goods"
        }
    ],
    "sg:phone":"+1 514 376 6901",
    "sg:postcode":"H2E 1T3",
    "sg:province":"QC",
    "wof:name":"Fleuriste San Remo",
    "wof:placetype":"venue"
},
  "geometry": {"coordinates":[-73.607597,45.547615],"type":"Point"}
}