{
  "type": "Feature",
  "properties": {
    "iso:country":"CA",
    "sg:address":"651 8E Av",
    "sg:city":"Senneterre",
    "sg:classifiers":[
        {
            "category":"Education",
            "subcategory":"School",
            "type":"Public Place"
        }
    ],
    "sg:phone":"+1 819 737 2914",
    "sg:postcode":"J0Y 2M0",
    "sg:province":"QC",
    "wof:name":"Ecole St-Paul",
    "wof:placetype":"venue"
},
  "geometry": {"coordinates":[-77.2428817749,48.3882064819],"type":"Point"}
}