{
  "type": "Feature",
  "properties": {
    "iso:country":"CA",
    "sg:address":"950 Boul Du Seminaire N",
    "sg:city":"Saint-Jean-Sur-Richelieu",
    "sg:classifiers":[
        {
            "category":"Personal",
            "type":"Services"
        }
    ],
    "sg:phone":"+1 450 349 2741",
    "sg:postcode":"J3A 1L2",
    "sg:province":"QC",
    "sg:tags":[
        "electrolysis"
    ],
    "wof:name":"Electro-Beaute",
    "wof:placetype":"venue"
},
  "geometry": {"coordinates":[-73.268211,45.334339],"type":"Point"}
}