{
  "type": "Feature",
  "properties": {
    "addr:full":"4142 Rumble St Burnaby BC V5J 1Z8",
    "addr:housenumber":"4142",
    "addr:postcode":"v5j 1z8",
    "addr:street":"Rumble St",
    "iso:country":"CA",
    "sg:address":"4142 Rumble St",
    "sg:city":"Burnaby",
    "sg:classifiers":[
        {
            "category":"Building & Trades",
            "subcategory":"Construction",
            "type":"Services"
        }
    ],
    "sg:phone":"+1 604 683 7477",
    "sg:postcode":"V5J 1Z8",
    "sg:province":"BC",
    "sg:tags":[
        "general",
        "contractor"
    ],
    "wof:name":"Fuhrmann Construction Group",
    "wof:placetype":"venue"
},
  "geometry": {"coordinates":[-123.011391,49.214649],"type":"Point"}
}