{
  "type": "Feature",
  "properties": {
    "addr:full":"12516 118 Ave NW Edmonton AB T5L 2K6",
    "addr:housenumber":"12516",
    "addr:postcode":"t5l 2k6",
    "addr:street":"118 Ave Nw",
    "iso:country":"CA",
    "sg:address":"12516 118 Ave NW",
    "sg:city":"Edmonton",
    "sg:classifiers":[
        {
            "category":"Shopping",
            "type":"Retail Goods"
        }
    ],
    "sg:phone":"+1 780 424 8511",
    "sg:postcode":"T5L 2K6",
    "sg:province":"AB",
    "sg:tags":[
        "cards",
        "sport",
        "baseball",
        "memorabilia"
    ],
    "wof:name":"Northgate Card Shop",
    "wof:placetype":"venue"
},
  "geometry": {"coordinates":[-113.538124,53.570442],"type":"Point"}
}