{
  "type": "Feature",
  "properties": {
    "addr:full":"36 Pepperwood Pl Brampton ON L6S 3R9",
    "addr:housenumber":"36",
    "addr:postcode":"l6s 3r9",
    "addr:street":"Pepperwood Pl",
    "iso:country":"CA",
    "sg:address":"36 Pepperwood Pl",
    "sg:city":"Brampton",
    "sg:classifiers":[
        {
            "category":"Building & Trades",
            "subcategory":"Plumbing",
            "type":"Services"
        }
    ],
    "sg:phone":"+1 905 792 8169",
    "sg:postcode":"L6S 3R9",
    "sg:province":"ON",
    "sg:tags":[
        "sewer",
        "cleaning",
        "drain"
    ],
    "wof:name":"Aquaflow Technology",
    "wof:placetype":"venue"
},
  "geometry": {"coordinates":[-79.738518,43.741325],"type":"Point"}
}