{
  "type": "Feature",
  "properties": {
    "iso:country":"CA",
    "sg:address":"1410 Poplar St",
    "sg:city":"Pemberton",
    "sg:classifiers":[
        {
            "category":"Travel",
            "subcategory":"Hotels & Motels",
            "type":"Entertainment"
        }
    ],
    "sg:phone":"+1 604 894 6424",
    "sg:postcode":"V0N 2L0",
    "sg:province":"BC",
    "sg:tags":[
        "breakfast",
        "accommodation",
        "bed"
    ],
    "wof:name":"Home Comforts Bed & Breakfast",
    "wof:placetype":"venue"
},
  "geometry": {"coordinates":[-122.804916382,50.3219795227],"type":"Point"}
}