{
  "type": "Feature",
  "properties": {
    "iso:country":"CA",
    "sg:address":"33 Centre Ave",
    "sg:city":"Gimli",
    "sg:classifiers":[
        {
            "category":"Professional",
            "subcategory":"Lawyer & Legal Services",
            "type":"Services"
        }
    ],
    "sg:phone":"+1 204 642 7955",
    "sg:postcode":"R0C 1B0",
    "sg:province":"MB",
    "sg:tags":[
        "attorney"
    ],
    "wof:name":"Skinner, David J",
    "wof:placetype":"venue"
},
  "geometry": {"coordinates":[-97.005013,50.631901],"type":"Point"}
}