{
  "type": "Feature",
  "properties": {
    "addr:full":"Surrey BC V4A 1N2",
    "addr:postcode":"v4a 1n2",
    "iso:country":"CA",
    "sg:city":"Surrey",
    "sg:classifiers":[
        {
            "category":"Professional",
            "subcategory":"Accounting & Tax Preparation",
            "type":"Services"
        }
    ],
    "sg:phone":"+1 604 535 5912",
    "sg:postcode":"V4A 1N2",
    "sg:province":"BC",
    "sg:tags":[
        "accountant"
    ],
    "wof:name":"D Brown Business Svc",
    "wof:placetype":"venue"
},
  "geometry": {"coordinates":[-122.868652,49.031425],"type":"Point"}
}