{
  "type": "Feature",
  "properties": {
    "addr:full":"930 4th Ave Regina SK S4N 0A7",
    "addr:housenumber":"930",
    "addr:postcode":"s4n 0a7",
    "addr:street":"4Th Ave",
    "iso:country":"CA",
    "sg:address":"930 4th Ave",
    "sg:city":"Regina",
    "sg:classifiers":[
        {
            "category":"Organizations",
            "subcategory":"Religious Organization",
            "type":"Services"
        }
    ],
    "sg:phone":"+1 306 347 0988",
    "sg:postcode":"S4N 0A7",
    "sg:province":"SK",
    "sg:tags":[
        "church"
    ],
    "wof:name":"New Life Tabernacle Upc",
    "wof:placetype":"venue"
},
  "geometry": {"coordinates":[-104.594269,50.463161],"type":"Point"}
}