{
  "type": "Feature",
  "properties": {
    "addr:full":"125 Balsam St S Timmins ON P4N 2E1",
    "addr:housenumber":"125",
    "addr:postcode":"p4n 2e1",
    "addr:street":"Balsam St S",
    "iso:country":"CA",
    "sg:address":"125 Balsam St S",
    "sg:city":"Timmins",
    "sg:classifiers":[
        {
            "category":"Health Services",
            "subcategory":"Medical Lab",
            "type":"Services"
        }
    ],
    "sg:phone":"+1 705 267 7949",
    "sg:postcode":"P4N 2E1",
    "sg:province":"ON",
    "wof:name":"Don Collins Denturist Clinic",
    "wof:placetype":"venue"
},
  "geometry": {"coordinates":[-81.3310241699,48.4732284546],"type":"Point"}
}