{
  "type": "Feature",
  "properties": {
    "addr:full":"9532 87 St NW Edmonton AB T6C 3J1",
    "addr:housenumber":"9532",
    "addr:postcode":"t6c 3j1",
    "addr:street":"87 St Nw",
    "iso:country":"CA",
    "sg:address":"9532 87 St NW",
    "sg:city":"Edmonton",
    "sg:classifiers":[
        {
            "category":"Shopping",
            "subcategory":"Hobbies, Toys, & Games",
            "type":"Retail Goods"
        }
    ],
    "sg:phone":"+1 780 430 9072",
    "sg:postcode":"T6C 3J1",
    "sg:province":"AB",
    "sg:tags":[
        "model",
        "supply"
    ],
    "wof:name":"Roundhouse Sales",
    "wof:placetype":"venue"
},
  "geometry": {"coordinates":[-113.46107499999999,53.532589],"type":"Point"}
}