{
  "type": "Feature",
  "properties": {
    "addr:full":"14932 45 Ave NW Edmonton AB T6H 5T5",
    "addr:housenumber":"14932",
    "addr:postcode":"t6h 5t5",
    "addr:street":"45 Ave Nw",
    "iso:country":"CA",
    "sg:address":"14932 45 Ave NW",
    "sg:city":"Edmonton",
    "sg:classifiers":[
        {
            "category":"Education",
            "subcategory":"School",
            "type":"Public Place"
        }
    ],
    "sg:phone":"+1 780 433 0078",
    "sg:postcode":"T6H 5T5",
    "sg:province":"AB",
    "wof:name":"Oxford Learning Ctr",
    "wof:placetype":"venue"
},
  "geometry": {"coordinates":[-113.579353333,53.4838790894],"type":"Point"}
}