{
  "type": "Feature",
  "properties": {
    "addr:full":"130 Fanshawe Park Rd W London ON N6G 5C4",
    "addr:housenumber":"130",
    "addr:postcode":"n6g 5c4",
    "addr:street":"Fanshawe Park Rd W",
    "iso:country":"CA",
    "sg:address":"130 Fanshawe Park Rd W",
    "sg:city":"London",
    "sg:classifiers":[
        {
            "category":"Home & Garden",
            "subcategory":"Home Furnishings",
            "type":"Retail Goods"
        }
    ],
    "sg:phone":"+1 519 433 6602",
    "sg:postcode":"N6G 5C4",
    "sg:province":"ON",
    "sg:tags":[
        "venetian",
        "blind",
        "made",
        "drapery"
    ],
    "wof:name":"Blind Spot",
    "wof:placetype":"venue"
},
  "geometry": {"coordinates":[-81.2908859253,43.0240325928],"type":"Point"}
}