{
  "type": "Feature",
  "properties": {
    "iso:country":"CA",
    "sg:address":"50 de Lauzon Suite 200",
    "sg:city":"Boucherville",
    "sg:classifiers":[
        {
            "category":"Professional",
            "subcategory":"Computer Services",
            "type":"Services"
        }
    ],
    "sg:postcode":"J4B 1E6",
    "sg:tags":[
        "loyalty-program",
        "relationship-marketing"
    ],
    "sg:website":"http://www.fanbox.net",
    "wof:name":"FanBox",
    "wof:placetype":"venue"
},
  "geometry": {"coordinates":[-73.4578903,45.5767077],"type":"Point"}
}