{
  "type": "Feature",
  "properties": {
    "iso:country":"CA",
    "sg:city":"Altona",
    "sg:classifiers":[
        {
            "category":"Professional",
            "subcategory":"Lawyer & Legal Services",
            "type":"Services"
        }
    ],
    "sg:phone":"+1 204 324 8830",
    "sg:postcode":"R0G 0B0",
    "sg:province":"MB",
    "sg:tags":[
        "attorney"
    ],
    "wof:name":"Gary Gilmore Law Office",
    "wof:placetype":"venue"
},
  "geometry": {"coordinates":[-97.55549621580001,49.1070594788],"type":"Point"}
}