{
  "type": "Feature",
  "properties": {
    "addr:full":"351 Main St Yarmouth NS B5A 1E7",
    "addr:housenumber":"351",
    "addr:postcode":"b5a 1e7",
    "addr:street":"Main St",
    "iso:country":"CA",
    "sg:address":"351 Main St",
    "sg:city":"Yarmouth",
    "sg:classifiers":[
        {
            "category":"Restaurant",
            "type":"Food & Drink"
        }
    ],
    "sg:phone":"+1 902 742 7779",
    "sg:postcode":"B5A 1E7",
    "sg:province":"NS",
    "wof:name":"Wilson's Family Restaurant",
    "wof:placetype":"venue"
},
  "geometry": {"coordinates":[-66.1196975708,43.8372879028],"type":"Point"}
}