{
  "type": "Feature",
  "properties": {
    "addr:full":"1720 Edmonton St Prince George BC V2M 1X4",
    "addr:housenumber":"1720",
    "addr:postcode":"v2m 1x4",
    "addr:street":"Edmonton St",
    "iso:country":"CA",
    "sg:address":"1720 Edmonton St",
    "sg:city":"Prince George",
    "sg:classifiers":[
        {
            "category":"Insurance",
            "subcategory":"Insurance Agent",
            "type":"Services"
        }
    ],
    "sg:phone":"+1 250 564 5625",
    "sg:postcode":"V2M 1X4",
    "sg:province":"BC",
    "wof:name":"DE Wit Insurance & Estate Plng",
    "wof:placetype":"venue"
},
  "geometry": {"coordinates":[-122.76683800000001,53.908379],"type":"Point"}
}