{
  "type": "Feature",
  "properties": {
    "addr:full":"534 Hespeler Rd # A2 Cambridge ON N1R 6J7",
    "addr:housenumber":"534",
    "addr:postcode":"n1r 6j7",
    "addr:street":"Hespeler Rd # A2",
    "iso:country":"CA",
    "sg:address":"534 Hespeler Rd # A2",
    "sg:city":"Cambridge",
    "sg:classifiers":[
        {
            "category":"Professional",
            "subcategory":"Employment Agencies",
            "type":"Services"
        }
    ],
    "sg:phone":"+1 519 622 7788",
    "sg:postcode":"N1R 6J7",
    "sg:province":"ON",
    "sg:tags":[
        "opportunity",
        "help"
    ],
    "wof:name":"Kas Personnel Svc",
    "wof:placetype":"venue"
},
  "geometry": {"coordinates":[-80.325981,43.40062],"type":"Point"}
}