{
  "type": "Feature",
  "properties": {
    "addr:full":"3835 112 Ave NW Edmonton AB T5W 0M5",
    "addr:housenumber":"3835",
    "addr:postcode":"t5w 0m5",
    "addr:street":"112 Ave Nw",
    "iso:country":"CA",
    "sg:address":"3835 112 Ave NW",
    "sg:city":"Edmonton",
    "sg:classifiers":[
        {
            "category":"Organizations",
            "subcategory":"Religious Organization",
            "type":"Services"
        }
    ],
    "sg:phone":"+1 780 471 5010",
    "sg:postcode":"T5W 0M5",
    "sg:province":"AB",
    "sg:tags":[
        "church"
    ],
    "wof:name":"Ukrainan Catholic Brotherhood",
    "wof:placetype":"venue"
},
  "geometry": {"coordinates":[-113.401115,53.564781],"type":"Point"}
}