{
  "type": "Feature",
  "properties": {
    "iso:country":"CA",
    "sg:address":"522 Princess Ave",
    "sg:city":"London",
    "sg:classifiers":[
        {
            "category":"Professional",
            "subcategory":"Computer Services",
            "type":"Services"
        }
    ],
    "sg:phone":"+1 519 858 1900",
    "sg:postcode":"N6B 2B8",
    "sg:province":"ON",
    "sg:tags":[
        "graphics"
    ],
    "wof:name":"Projected Images",
    "wof:placetype":"venue"
},
  "geometry": {"coordinates":[-81.236969,42.991917],"type":"Point"}
}