{
  "type": "Feature",
  "properties": {
    "addr:full":"Winnipeg MB R3N 0B8",
    "addr:postcode":"r3n 0b8",
    "iso:country":"CA",
    "sg:city":"Winnipeg",
    "sg:classifiers":[
        {
            "category":"Health Services",
            "subcategory":"Optometrist",
            "type":"Services"
        }
    ],
    "sg:phone":"+1 204 943 9811",
    "sg:postcode":"R3N 0B8",
    "sg:province":"MB",
    "wof:name":"Manitoba Association-Optmtrsts",
    "wof:placetype":"venue"
},
  "geometry": {"coordinates":[-97.1826705933,49.8736152649],"type":"Point"}
}