{
  "type": "Feature",
  "properties": {
    "addr:full":"Norway Rd N Canora SK S0A 0L0",
    "addr:postcode":"s0a 0l0",
    "addr:street":"Norway Rd N",
    "iso:country":"CA",
    "sg:address":"Norway Rd N",
    "sg:city":"Canora",
    "sg:classifiers":[
        {
            "category":"Building & Trades",
            "subcategory":"Construction",
            "type":"Services"
        }
    ],
    "sg:phone":"+1 306 563 6431",
    "sg:postcode":"S0A 0L0",
    "sg:province":"SK",
    "sg:tags":[
        "excavating",
        "contractor",
        "general"
    ],
    "wof:name":"Ludba Construction Ltd",
    "wof:placetype":"venue"
},
  "geometry": {"coordinates":[-102.432434,51.635456],"type":"Point"}
}