{
  "type": "Feature",
  "properties": {
    "addr:full":"6611 Reid Rd Chilliwack BC V2R 2Z8",
    "addr:housenumber":"6611",
    "addr:postcode":"v2r 2z8",
    "addr:street":"Reid Rd",
    "iso:country":"CA",
    "sg:address":"6611 Reid Rd",
    "sg:city":"Chilliwack",
    "sg:classifiers":[
        {
            "category":"Building & Trades",
            "subcategory":"Plumbing",
            "type":"Services"
        }
    ],
    "sg:phone":"+1 604 819 7211",
    "sg:postcode":"V2R 2Z8",
    "sg:province":"BC",
    "sg:tags":[
        "heating",
        "contractor"
    ],
    "wof:name":"West-Teck Gas Svc",
    "wof:placetype":"venue"
},
  "geometry": {"coordinates":[-121.9515,49.156319],"type":"Point"}
}