{
  "type": "Feature",
  "properties": {
    "addr:full":"1251 Scugog Line 8 Port Perry ON L9L 1B2",
    "addr:housenumber":"1251",
    "addr:postcode":"l9l 1b2",
    "addr:street":"Scugog Line 8",
    "iso:country":"CA",
    "sg:address":"1251 Scugog Line 8",
    "sg:city":"Port Perry",
    "sg:classifiers":[
        {
            "category":"Manufacturing",
            "subcategory":"Printing",
            "type":"Manufacturing & Wholesale Goods"
        }
    ],
    "sg:phone":"+1 905 985 3555",
    "sg:postcode":"L9L 1B2",
    "sg:province":"ON",
    "sg:tags":[
        "publisher"
    ],
    "wof:name":"Silvio Mattacchione & CO",
    "wof:placetype":"venue"
},
  "geometry": {"coordinates":[-78.9925765991,44.1168060303],"type":"Point"}
}