{
  "type": "Feature",
  "properties": {
    "addr:full":"539 Boul Du Seminaire N Saint-Jean-Sur-Richelieu QC J3B 5L9",
    "addr:housenumber":"539",
    "addr:postcode":"j3b 5l9",
    "addr:street":"Boul Du Seminaire N",
    "iso:country":"CA",
    "sg:address":"539 Boul Du Seminaire N",
    "sg:city":"Saint-Jean-Sur-Richelieu",
    "sg:classifiers":[
        {
            "category":"Real Estate",
            "subcategory":"Real Estate Agent",
            "type":"Services"
        }
    ],
    "sg:phone":"+1 450 359 9633",
    "sg:postcode":"J3B 5L9",
    "sg:province":"QC",
    "sg:tags":[
        "appraiser"
    ],
    "wof:name":"Baillargeon Bergeron Deneault",
    "wof:placetype":"venue"
},
  "geometry": {"coordinates":[-73.263931,45.317291],"type":"Point"}
}