{
  "type": "Feature",
  "properties": {
    "addr:full":"4065 Dufferin Ave Petrolia ON N0N 1R0",
    "addr:housenumber":"4065",
    "addr:postcode":"n0n 1r0",
    "addr:street":"Dufferin Ave",
    "iso:country":"CA",
    "sg:address":"4065 Dufferin Ave",
    "sg:city":"Petrolia",
    "sg:classifiers":[
        {
            "category":"Arena",
            "subcategory":"Sports Club",
            "type":"Entertainment"
        }
    ],
    "sg:phone":"+1 519 882 1570",
    "sg:postcode":"N0N 1R0",
    "sg:province":"ON",
    "sg:tags":[
        "athletic",
        "fields",
        "stadium",
        "government"
    ],
    "wof:name":"Petrolia Arena",
    "wof:placetype":"venue"
},
  "geometry": {"coordinates":[-82.15368700000001,42.878845],"type":"Point"}
}