{
  "type": "Feature",
  "properties": {
    "addr:full":"466 Dovercourt Rd Toronto ON M6H 2W4",
    "addr:housenumber":"466",
    "addr:postcode":"m6h 2w4",
    "addr:street":"Dovercourt Rd",
    "iso:country":"CA",
    "sg:address":"466 Dovercourt Rd",
    "sg:city":"Toronto",
    "sg:classifiers":[
        {
            "category":"Bars & Pubs",
            "type":"Food & Drink"
        }
    ],
    "sg:phone":"+1 416 533 9311",
    "sg:postcode":"M6H 2W4",
    "sg:province":"ON",
    "sg:tags":[
        "club",
        "night"
    ],
    "wof:name":"Matador Club Country Music",
    "wof:placetype":"venue"
},
  "geometry": {"coordinates":[-79.42682600000001,43.654213],"type":"Point"}
}