{
  "type": "Feature",
  "properties": {
    "addr:full":"11385 352nd Ave Oliver BC V0H 1T0",
    "addr:housenumber":"11385",
    "addr:postcode":"bc v0h 1t0",
    "addr:street":"352Nd Ave",
    "iso:country":"CA",
    "sg:address":"11385 352nd Ave",
    "sg:city":"Oliver",
    "sg:classifiers":[
        {
            "category":"Professional",
            "subcategory":"Accounting & Tax Preparation",
            "type":"Services"
        }
    ],
    "sg:phone":"+1 250 498 2722",
    "sg:postcode":"V0H 1T0",
    "sg:province":"BC",
    "sg:tags":[
        "accountant"
    ],
    "wof:name":"Okanagan Accounting Svc",
    "wof:placetype":"venue"
},
  "geometry": {"coordinates":[-119.567291,49.176888],"type":"Point"}
}