{
  "type": "Feature",
  "properties": {
    "addr:full":"2282 Bloor St W Toronto ON M6S 1N9",
    "addr:housenumber":"2282",
    "addr:postcode":"m6s 1n9",
    "addr:street":"Bloor St W",
    "iso:country":"CA",
    "sg:address":"2282 Bloor St W",
    "sg:city":"Toronto",
    "sg:classifiers":[
        {
            "category":"Shopping",
            "subcategory":"Books",
            "type":"Retail Goods"
        }
    ],
    "sg:phone":"+1 416 762 8751",
    "sg:postcode":"M6S 1N9",
    "sg:province":"ON",
    "sg:tags":[
        "shop",
        "gift"
    ],
    "wof:name":"West Arka",
    "wof:placetype":"venue"
},
  "geometry": {"coordinates":[-79.478691,43.650738],"type":"Point"}
}