{
  "type": "Feature",
  "properties": {
    "addr:full":"Surrey BC V3W 8J9",
    "addr:postcode":"v3w 8j9",
    "iso:country":"CA",
    "sg:city":"Surrey",
    "sg:classifiers":[
        {
            "category":"Manufacturing",
            "subcategory":"Rubber & Plastics",
            "type":"Manufacturing & Wholesale Goods"
        }
    ],
    "sg:phone":"+1 604 599 0388",
    "sg:postcode":"V3W 8J9",
    "sg:province":"BC",
    "wof:name":"Pittfield Design Inc",
    "wof:placetype":"venue"
},
  "geometry": {"coordinates":[-122.861969,49.1506],"type":"Point"}
}