{
  "type": "Feature",
  "properties": {
    "addr:full":"1523 Hurontario St Mississauga ON L5G 3H7",
    "addr:housenumber":"1523",
    "addr:postcode":"l5g 3h7",
    "addr:street":"Hurontario St",
    "iso:country":"CA",
    "sg:address":"1523 Hurontario St",
    "sg:city":"Mississauga",
    "sg:classifiers":[
        {
            "category":"Professional",
            "subcategory":"Lawyer & Legal Services",
            "type":"Services"
        }
    ],
    "sg:phone":"+1 905 271 3939",
    "sg:postcode":"L5G 3H7",
    "sg:province":"ON",
    "sg:tags":[
        "attorney"
    ],
    "wof:name":"Bacon, John R E QC",
    "wof:placetype":"venue"
},
  "geometry": {"coordinates":[-79.59581756590001,43.5656089783],"type":"Point"}
}