{
  "type": "Feature",
  "properties": {
    "addr:full":"124 Rue Principale Courcelles QC G0M 1C0",
    "addr:housenumber":"124",
    "addr:postcode":"g0m 1c0",
    "addr:street":"Rue Principale",
    "iso:country":"CA",
    "sg:address":"124 Rue Principale",
    "sg:city":"Courcelles",
    "sg:classifiers":[
        {
            "category":"Shopping",
            "subcategory":"Clothing, Apparel, & Fashions",
            "type":"Retail Goods"
        }
    ],
    "sg:phone":"+1 418 483 5511",
    "sg:postcode":"G0M 1C0",
    "sg:province":"QC",
    "sg:tags":[
        "item",
        "boutique"
    ],
    "wof:name":"Boutique Emotion Mode",
    "wof:placetype":"venue"
},
  "geometry": {"coordinates":[-70.9867858887,45.8778800964],"type":"Point"}
}