{
  "type": "Feature",
  "properties": {
    "addr:full":"PO Box 317 Christopher Lake SK S0J 0N0",
    "addr:housenumber":"po;317",
    "addr:postcode":"s0j 0n0",
    "addr:street":"Box;Christopher Lake",
    "iso:country":"CA",
    "sg:address":"PO Box 317",
    "sg:city":"Christopher Lake",
    "sg:classifiers":[
        {
            "category":"Organizations",
            "subcategory":"Religious Organization",
            "type":"Services"
        }
    ],
    "sg:phone":"+1 306 982 4758",
    "sg:postcode":"S0J 0N0",
    "sg:province":"SK",
    "sg:tags":[
        "church"
    ],
    "wof:name":"Kinasao Lutheran Bible Camp",
    "wof:placetype":"venue"
},
  "geometry": {"coordinates":[-105.79064200000001,53.539902],"type":"Point"}
}