{
  "type": "Feature",
  "properties": {
    "addr:full":"3007 Turner St Abbotsford BC V2S 7T9",
    "addr:housenumber":"3007",
    "addr:postcode":"v2s 7t9",
    "addr:street":"Turner St",
    "iso:country":"CA",
    "sg:address":"3007 Turner St",
    "sg:city":"Abbotsford",
    "sg:classifiers":[
        {
            "category":"Manufacturing",
            "subcategory":"Pet Food",
            "type":"Manufacturing & Wholesale Goods"
        }
    ],
    "sg:phone":"+1 604 853 9235",
    "sg:postcode":"V2S 7T9",
    "sg:province":"BC",
    "sg:tags":[
        "feed"
    ],
    "wof:name":"Excel Feeds Inc",
    "wof:placetype":"venue"
},
  "geometry": {"coordinates":[-122.287323,49.057365],"type":"Point"}
}