{
  "type": "Feature",
  "properties": {
    "iso:country":"CA",
    "sg:address":"417 Av Sainte-Brigitte",
    "sg:city":"Sainte-Brigitte-DE-Laval",
    "sg:classifiers":[
        {
            "category":"Taxi",
            "type":"Transportation"
        }
    ],
    "sg:phone":"+1 418 825 2344",
    "sg:postcode":"G0A 3K0",
    "sg:province":"QC",
    "sg:tags":[
        "taxicab"
    ],
    "wof:name":"Taxi DE Laval",
    "wof:placetype":"venue"
},
  "geometry": {"coordinates":[-71.1937255859,47.0038757324],"type":"Point"}
}