{
  "type": "Feature",
  "properties": {
    "addr:full":"RR 10 STN Main Charlottetown PE C1E 1Z4",
    "addr:housenumber":"10 stn",
    "addr:postcode":"c1e 1z4",
    "addr:street":"Rr;Main",
    "iso:country":"CA",
    "sg:address":"RR 10 STN Main",
    "sg:city":"Charlottetown",
    "sg:classifiers":[
        {
            "category":"Recreation",
            "type":"Entertainment"
        }
    ],
    "sg:phone":"+1 902 566 3154",
    "sg:postcode":"C1E 1Z4",
    "sg:province":"PE",
    "sg:tags":[
        "hall",
        "auditorium"
    ],
    "wof:name":"Milton Community Hall",
    "wof:placetype":"venue"
},
  "geometry": {"coordinates":[-63.1281700134,46.2365913391],"type":"Point"}
}