{
  "type": "Feature",
  "properties": {
    "addr:full":"344 Main St Wolfville NS B4P 1C4",
    "addr:housenumber":"344",
    "addr:postcode":"b4p 1c4",
    "addr:street":"Main St",
    "iso:country":"CA",
    "sg:address":"344 Main St",
    "sg:city":"Wolfville",
    "sg:classifiers":[
        {
            "category":"Shopping",
            "subcategory":"Bicycles & Sporting Goods",
            "type":"Retail Goods"
        }
    ],
    "sg:phone":"+1 902 542 1063",
    "sg:postcode":"B4P 1C4",
    "sg:province":"NS",
    "wof:name":"Juandaro's Soccer Boutique",
    "wof:placetype":"venue"
},
  "geometry": {"coordinates":[-64.3728256226,45.0900688171],"type":"Point"}
}