{
  "type": "Feature",
  "properties": {
    "addr:full":"550 Queen St Fredericton NB E3B 1B9",
    "addr:housenumber":"550",
    "addr:postcode":"e3b 1b9",
    "addr:street":"Queen St",
    "iso:country":"CA",
    "sg:address":"550 Queen St",
    "sg:city":"Fredericton",
    "sg:classifiers":[
        {
            "category":"Personal",
            "subcategory":"Beauty Salon",
            "type":"Services"
        }
    ],
    "sg:phone":"+1 506 457 2922",
    "sg:postcode":"E3B 1B9",
    "sg:province":"NB",
    "wof:name":"Sue Lawrence Hair & Spa Gllry",
    "wof:placetype":"venue"
},
  "geometry": {"coordinates":[-66.639877,45.961468],"type":"Point"}
}