{
  "type": "Feature",
  "properties": {
    "addr:full":"55 Milvan Dr North York ON M9L 1Y8",
    "addr:housenumber":"55",
    "addr:postcode":"m9l 1y8",
    "addr:street":"Milvan Dr",
    "iso:country":"CA",
    "sg:address":"55 Milvan Dr",
    "sg:city":"North York",
    "sg:classifiers":[
        {
            "category":"Manufacturing",
            "subcategory":"Metals",
            "type":"Manufacturing & Wholesale Goods"
        }
    ],
    "sg:phone":"+1 416 741 3141",
    "sg:postcode":"M9L 1Y8",
    "sg:province":"ON",
    "sg:tags":[
        "anodizing"
    ],
    "wof:name":"Holly's Anodizing Svc Ltd",
    "wof:placetype":"venue"
},
  "geometry": {"coordinates":[-79.55521400000001,43.753948],"type":"Point"}
}