{
  "type": "Feature",
  "properties": {
    "iso:country":"CA",
    "sg:city":"Aurora",
    "sg:classifiers":[
        {
            "category":"Shopping",
            "subcategory":"Gifts & Souvenirs",
            "type":"Retail Goods"
        }
    ],
    "sg:phone":"+1 905 841 3437",
    "sg:postcode":"L4G 3V5",
    "sg:province":"ON",
    "sg:tags":[
        "shop",
        "basket",
        "cookie",
        "parcel"
    ],
    "wof:name":"Cookie It Up",
    "wof:placetype":"venue"
},
  "geometry": {"coordinates":[-79.45416259770001,43.99193573],"type":"Point"}
}