{
  "type": "Feature",
  "properties": {
    "addr:full":"Toronto ON M5E 1K3",
    "addr:postcode":"m5e 1k3",
    "iso:country":"CA",
    "sg:city":"Toronto",
    "sg:classifiers":[
        {
            "category":"Professional",
            "subcategory":"Research",
            "type":"Services"
        }
    ],
    "sg:phone":"+1 416 364 3043",
    "sg:postcode":"M5E 1K3",
    "sg:province":"ON",
    "sg:tags":[
        "foundation",
        "philanthropic"
    ],
    "wof:name":"Charis Foundation",
    "wof:placetype":"venue"
},
  "geometry": {"coordinates":[-79.377571,43.648842],"type":"Point"}
}