{
  "type": "Feature",
  "properties": {
    "addr:full":"1310 Rue Ottawa Montreal QC H3C 1S7",
    "addr:housenumber":"1310",
    "addr:postcode":"h3c 1s7",
    "addr:street":"Rue Ottawa",
    "iso:country":"CA",
    "sg:address":"1310 Rue Ottawa",
    "sg:city":"Montreal",
    "sg:classifiers":[
        {
            "category":"Real Estate",
            "subcategory":"Real Estate Agent",
            "type":"Services"
        }
    ],
    "sg:phone":"+1 514 932 5134",
    "sg:postcode":"H3C 1S7",
    "sg:province":"QC",
    "sg:tags":[
        "management"
    ],
    "wof:name":"Mccord Street Sites Ltd",
    "wof:placetype":"venue"
},
  "geometry": {"coordinates":[-73.560913,45.491943],"type":"Point"}
}