{
  "type": "Feature",
  "properties": {
    "addr:full":"8875 Boul Henri-Bourassa Charlesbourg QC G1G 4E4",
    "addr:housenumber":"8875",
    "addr:postcode":"g1g 4e4",
    "addr:street":"Boul Henri-Bourassa",
    "iso:country":"CA",
    "sg:address":"8875 Boul Henri-Bourassa",
    "sg:city":"Charlesbourg",
    "sg:classifiers":[
        {
            "category":"Travel",
            "subcategory":"Travel Agent",
            "type":"Entertainment"
        }
    ],
    "sg:phone":"+1 418 627 0911",
    "sg:postcode":"G1G 4E4",
    "sg:province":"QC",
    "sg:tags":[
        "agency",
        "bureau"
    ],
    "wof:name":"Agence DE Voyages Paradis",
    "wof:placetype":"venue"
},
  "geometry": {"coordinates":[-71.273239,46.866745],"type":"Point"}
}