{
  "type": "Feature",
  "properties": {
    "addr:full":"398 Union Blvd Kitchener ON N2M 2T4",
    "addr:housenumber":"398",
    "addr:postcode":"n2m 2t4",
    "addr:street":"Union Blvd",
    "iso:country":"CA",
    "sg:address":"398 Union Blvd",
    "sg:city":"Kitchener",
    "sg:classifiers":[
        {
            "category":"Professional",
            "subcategory":"Management & Consulting",
            "type":"Services"
        }
    ],
    "sg:phone":"+1 519 579 1199",
    "sg:postcode":"N2M 2T4",
    "sg:province":"ON",
    "sg:tags":[
        "resource",
        "consultant",
        "relation",
        "human",
        "labor"
    ],
    "wof:name":"Concordia Consulting Inc",
    "wof:placetype":"venue"
},
  "geometry": {"coordinates":[-80.5276184082,43.4512901306],"type":"Point"}
}