{
  "type": "Feature",
  "properties": {
    "addr:full":"10 Rue Saint-Joseph Saint-Jerome QC J7Z 7G7",
    "addr:housenumber":"10",
    "addr:postcode":"j7z 7g7",
    "addr:street":"Rue Saint-Joseph Saint-Jerome",
    "iso:country":"CA",
    "sg:address":"10 Rue Saint-Joseph",
    "sg:city":"Saint-Jerome",
    "sg:classifiers":[
        {
            "category":"Government",
            "subcategory":"Office",
            "type":"Public Place"
        }
    ],
    "sg:phone":"+1 450 569 3031",
    "sg:postcode":"J7Z 7G7",
    "sg:province":"QC",
    "wof:name":"Quebec Industrie Commerce",
    "wof:placetype":"venue"
},
  "geometry": {"coordinates":[-74.003326,45.775173],"type":"Point"}
}