{
  "type": "Feature",
  "properties": {
    "addr:full":"10620 Av L'Archeveque Montreal-Nord QC H1H 3A2",
    "addr:housenumber":"10620",
    "addr:postcode":"h1h 3a2",
    "addr:street":"Av L'Archeveque",
    "iso:country":"CA",
    "sg:address":"10620 Av L'Archeveque",
    "sg:city":"Montreal-Nord",
    "sg:classifiers":[
        {
            "category":"Retail",
            "subcategory":"Auto Repair",
            "type":"Services"
        }
    ],
    "sg:phone":"+1 514 322 1696",
    "sg:postcode":"H1H 3A2",
    "sg:province":"QC",
    "sg:tags":[
        "repairing",
        "automobile"
    ],
    "wof:name":"Sebastianelli & Fils Inc",
    "wof:placetype":"venue"
},
  "geometry": {"coordinates":[-73.626053,45.593208],"type":"Point"}
}