{
  "type": "Feature",
  "properties": {
    "addr:full":"850 Av Selkirk Pointe-Claire QC H9R 3S3",
    "addr:housenumber":"850",
    "addr:postcode":"h9r 3s3",
    "addr:street":"Av Selkirk",
    "iso:country":"CA",
    "sg:address":"850 Av Selkirk",
    "sg:city":"Pointe-Claire",
    "sg:classifiers":[
        {
            "category":"Manufacturing",
            "subcategory":"Electronics",
            "type":"Manufacturing & Wholesale Goods"
        }
    ],
    "sg:phone":"+1 514 426 5525",
    "sg:postcode":"H9R 3S3",
    "sg:province":"QC",
    "sg:tags":[
        "printed",
        "circuit",
        "etched"
    ],
    "wof:name":"Circuits Cmr Ltee",
    "wof:placetype":"venue"
},
  "geometry": {"coordinates":[-73.82283,45.468189],"type":"Point"}
}