{
  "type": "Feature",
  "properties": {
    "addr:full":"Carbonear NL A1Y 1A6",
    "addr:postcode":"a1y 1a6",
    "iso:country":"CA",
    "sg:city":"Carbonear",
    "sg:classifiers":[
        {
            "category":"Organizations",
            "subcategory":"Membership Organization",
            "type":"Services"
        }
    ],
    "sg:phone":"+1 709 596 6217",
    "sg:postcode":"A1Y 1A6",
    "sg:province":"NL",
    "sg:tags":[
        "development",
        "economic",
        "agency"
    ],
    "wof:name":"Mariner Resource Opportunities",
    "wof:placetype":"venue"
},
  "geometry": {"coordinates":[-53.2295,47.736382],"type":"Point"}
}