{
  "type": "Feature",
  "properties": {
    "addr:full":"4195 Dundas St W # 233 Etobicoke ON M8X 1Y4",
    "addr:housenumber":"4195",
    "addr:postcode":"m8x 1y4",
    "addr:street":"Dundas St W # 233",
    "iso:country":"CA",
    "sg:address":"4195 Dundas St W # 233",
    "sg:city":"Etobicoke",
    "sg:classifiers":[
        {
            "category":"Professional",
            "subcategory":"Management & Consulting",
            "type":"Services"
        }
    ],
    "sg:phone":"+1 416 762 3808",
    "sg:postcode":"M8X 1Y4",
    "sg:province":"ON",
    "sg:tags":[
        "fire",
        "consultant",
        "protection"
    ],
    "wof:name":"Larden Muniak Consulting Inc",
    "wof:placetype":"venue"
},
  "geometry": {"coordinates":[-79.51084899999999,43.660343],"type":"Point"}
}