{
  "type": "Feature",
  "properties": {
    "iso:country":"CA",
    "sg:address":"7 Tsse Chatel",
    "sg:city":"Laval",
    "sg:classifiers":[
        {
            "category":"Building & Trades",
            "subcategory":"Construction",
            "type":"Services"
        }
    ],
    "sg:phone":"+1 514 321 1751",
    "sg:postcode":"H7L 3A4",
    "sg:province":"QC",
    "sg:tags":[
        "roofing",
        "contractor"
    ],
    "wof:name":"Toitures J Belanger & Fils Inc",
    "wof:placetype":"venue"
},
  "geometry": {"coordinates":[-73.788230896,45.5893287659],"type":"Point"}
}