{
  "type": "Feature",
  "properties": {
    "addr:full":"Aylmer ON N5H 2C1",
    "addr:postcode":"n5h 2c1",
    "iso:country":"CA",
    "sg:city":"Aylmer",
    "sg:classifiers":[
        {
            "category":"Health Services",
            "subcategory":"Doctor",
            "type":"Services"
        }
    ],
    "sg:phone":"+1 519 765 2330",
    "sg:postcode":"N5H 2C1",
    "sg:province":"ON",
    "sg:tags":[
        "dentist"
    ],
    "wof:name":"Curtis, J R DDS",
    "wof:placetype":"venue"
},
  "geometry": {"coordinates":[-80.982758,42.77269],"type":"Point"}
}