{
  "type": "Feature",
  "properties": {
    "addr:full":"1902 5A St SW Calgary AB T2S 2G1",
    "addr:housenumber":"1902 5a",
    "addr:postcode":"t2s 2g1",
    "addr:street":"St Sw",
    "iso:country":"CA",
    "sg:address":"1902 5A St SW",
    "sg:city":"Calgary",
    "sg:classifiers":[
        {
            "category":"Health Services",
            "subcategory":"Health Practitioner",
            "type":"Services"
        }
    ],
    "sg:phone":"+1 403 256 8449",
    "sg:postcode":"T2S 2G1",
    "sg:province":"AB",
    "sg:tags":[
        "psychologist"
    ],
    "wof:name":"Monteith & Forsyth Counselling",
    "wof:placetype":"venue"
},
  "geometry": {"coordinates":[-114.075287,51.03611],"type":"Point"}
}