{
  "type": "Feature",
  "properties": {
    "addr:full":"1100C Memorial Ave #154 Thunder Bay ON P7B 4A3",
    "addr:housenumber":"1100c",
    "addr:postcode":"p7b 4a3",
    "addr:street":"Memorial Ave # 154",
    "iso:country":"CA",
    "sg:address":"1100C Memorial Ave #154",
    "sg:city":"Thunder Bay",
    "sg:classifiers":[
        {
            "category":"Professional",
            "subcategory":"Management & Consulting",
            "type":"Services"
        }
    ],
    "sg:phone":"+1 807 623 3766",
    "sg:postcode":"P7B 4A3",
    "sg:province":"ON",
    "sg:tags":[
        "consultant",
        "training",
        "business"
    ],
    "wof:name":"Trendline Consulting Svc",
    "wof:placetype":"venue"
},
  "geometry": {"coordinates":[-89.2457351685,48.4039573669],"type":"Point"}
}