{
  "type": "Feature",
  "properties": {
    "addr:full":"36 Dean Dr Hay River NT X0E 0R6",
    "addr:housenumber":"36",
    "addr:postcode":"x0e 0r6",
    "addr:street":"Dean Dr",
    "iso:country":"CA",
    "sg:address":"36 Dean Dr",
    "sg:city":"Hay River",
    "sg:classifiers":[
        {
            "category":"Building & Trades",
            "subcategory":"Construction",
            "type":"Services"
        }
    ],
    "sg:phone":"+1 867 874 2844",
    "sg:postcode":"X0E 0R6",
    "sg:province":"NT",
    "sg:tags":[
        "paving",
        "contractor"
    ],
    "wof:name":"South Slave Paving Ltd",
    "wof:placetype":"venue"
},
  "geometry": {"coordinates":[-115.800453,60.810356],"type":"Point"}
}