{
  "type": "Feature",
  "properties": {
    "iso:country":"CA",
    "sg:city":"Baie-Comeau",
    "sg:classifiers":[
        {
            "category":"Travel",
            "subcategory":"Travel Agent",
            "type":"Entertainment"
        }
    ],
    "sg:phone":"+1 418 296 0132",
    "sg:postcode":"G4Z 1J8",
    "sg:province":"QC",
    "sg:tags":[
        "consultant",
        "marketing"
    ],
    "wof:name":"Creno Group Conseil Marketing",
    "wof:placetype":"venue"
},
  "geometry": {"coordinates":[-68.15269499999999,49.221256],"type":"Point"}
}