{
  "type": "Feature",
  "properties": {
    "addr:full":"10 Grand Ave S Cambridge ON N1S 2L4",
    "addr:housenumber":"10",
    "addr:postcode":"n1s 2l4",
    "addr:street":"Grand Ave S",
    "iso:country":"CA",
    "sg:address":"10 Grand Ave S",
    "sg:city":"Cambridge",
    "sg:classifiers":[
        {
            "category":"Shopping",
            "subcategory":"Used Merchandise",
            "type":"Retail Goods"
        }
    ],
    "sg:phone":"+1 519 624 1880",
    "sg:postcode":"N1S 2L4",
    "sg:province":"ON",
    "sg:tags":[
        "antique"
    ],
    "wof:name":"Ten Grand Antiques",
    "wof:placetype":"venue"
},
  "geometry": {"coordinates":[-80.317604,43.358044],"type":"Point"}
}