{
  "type": "Feature",
  "properties": {
    "iso:country":"CA",
    "sg:city":"Empress",
    "sg:classifiers":[
        {
            "category":"Professional",
            "subcategory":"Business Services",
            "type":"Services"
        }
    ],
    "sg:phone":"+1 403 565 3952",
    "sg:postcode":"T0J 1E0",
    "sg:province":"AB",
    "sg:tags":[
        "reservation",
        "motel",
        "hotel"
    ],
    "wof:name":"Empress Motor Inn",
    "wof:placetype":"venue"
},
  "geometry": {"coordinates":[-110.00789642300001,50.9557533264],"type":"Point"}
}