{
  "type": "Feature",
  "properties": {
    "addr:full":"738 Wyandotte St E Windsor ON N9A 3J4",
    "addr:housenumber":"738",
    "addr:postcode":"n9a 3j4",
    "addr:street":"Wyandotte St E",
    "iso:country":"CA",
    "sg:address":"738 Wyandotte St E",
    "sg:city":"Windsor",
    "sg:classifiers":[
        {
            "category":"Personal",
            "subcategory":"Beauty Salon",
            "type":"Services"
        }
    ],
    "sg:phone":"+1 519 252 1466",
    "sg:postcode":"N9A 3J4",
    "sg:province":"ON",
    "wof:name":"Expression Beauty Salon",
    "wof:placetype":"venue"
},
  "geometry": {"coordinates":[-83.02680206300001,42.317817688],"type":"Point"}
}