{
  "type": "Feature",
  "properties": {
    "addr:full":"Coquitlam BC V3K 6R2",
    "addr:postcode":"v3k 6r2",
    "iso:country":"CA",
    "sg:city":"Coquitlam",
    "sg:classifiers":[
        {
            "category":"Manufacturing",
            "subcategory":"Building Materials",
            "type":"Manufacturing & Wholesale Goods"
        }
    ],
    "sg:phone":"+1 604 941 3226",
    "sg:postcode":"V3K 6R2",
    "sg:province":"BC",
    "wof:name":"Shaw Installations Ltd",
    "wof:placetype":"venue"
},
  "geometry": {"coordinates":[-122.824257,49.231117],"type":"Point"}
}