{
  "type": "Feature",
  "properties": {
    "iso:country":"CA",
    "sg:address":"131 Oak Lane",
    "sg:city":"Lake Cowichan",
    "sg:classifiers":[
        {
            "category":"Farming",
            "subcategory":"Aquatic Farm",
            "type":"Manufacturing & Wholesale Goods"
        }
    ],
    "sg:phone":"+1 250 749 0119",
    "sg:postcode":"V0R 2G0",
    "sg:province":"BC",
    "sg:tags":[
        "hatchery",
        "fish"
    ],
    "wof:name":"Cowichan Lake Salmonid Society",
    "wof:placetype":"venue"
},
  "geometry": {"coordinates":[-124.047477722,48.8309440613],"type":"Point"}
}