{
  "type": "Feature",
  "properties": {
    "addr:full":"2 Gledhill Ave East York ON M4C 5K6",
    "addr:housenumber":"2",
    "addr:postcode":"m4c 5k6",
    "addr:street":"Gledhill Ave",
    "iso:country":"CA",
    "sg:address":"2 Gledhill Ave",
    "sg:city":"East York",
    "sg:classifiers":[
        {
            "category":"Education",
            "subcategory":"School",
            "type":"Public Place"
        }
    ],
    "sg:phone":"+1 416 393 9979",
    "sg:postcode":"M4C 5K6",
    "sg:province":"ON",
    "wof:name":"Gledhill Junior Public School",
    "wof:placetype":"venue"
},
  "geometry": {"coordinates":[-79.3090057373,43.6874542236],"type":"Point"}
}