{
  "type": "Feature",
  "properties": {
    "addr:full":"49 Beaconsfield Ave Toronto ON M6J 3J1",
    "addr:housenumber":"49",
    "addr:postcode":"m6j 3j1",
    "addr:street":"Beaconsfield Ave",
    "iso:country":"CA",
    "sg:address":"49 Beaconsfield Ave",
    "sg:city":"Toronto",
    "sg:classifiers":[
        {
            "category":"Building & Trades",
            "subcategory":"Construction",
            "type":"Services"
        }
    ],
    "sg:phone":"+1 416 537 5373",
    "sg:postcode":"M6J 3J1",
    "sg:province":"ON",
    "sg:tags":[
        "excavating",
        "contractor"
    ],
    "wof:name":"Lakeside Excavating CO",
    "wof:placetype":"venue"
},
  "geometry": {"coordinates":[-79.425247,43.644653],"type":"Point"}
}