{
  "type": "Feature",
  "properties": {
    "addr:full":"921 Rue Thibault Baie-Comeau QC G5C 3A2",
    "addr:housenumber":"921",
    "addr:postcode":"g5c 3a2",
    "addr:street":"Rue Thibault",
    "iso:country":"CA",
    "sg:address":"921 Rue Thibault",
    "sg:city":"Baie-Comeau",
    "sg:classifiers":[
        {
            "category":"Building & Trades",
            "subcategory":"Construction",
            "type":"Services"
        }
    ],
    "sg:phone":"+1 418 589 3555",
    "sg:postcode":"G5C 3A2",
    "sg:province":"QC",
    "sg:tags":[
        "contractor",
        "general"
    ],
    "wof:name":"Constructions Gilles Levasseur",
    "wof:placetype":"venue"
},
  "geometry": {"coordinates":[-68.27271270750001,49.1916885376],"type":"Point"}
}