{
  "type": "Feature",
  "properties": {
    "addr:full":"6075 Rue Jarry E Saint-Leonard QC H1P 1V7",
    "addr:housenumber":"6075",
    "addr:postcode":"h1p 1v7",
    "addr:street":"Rue Jarry E",
    "iso:country":"CA",
    "sg:address":"6075 Rue Jarry E",
    "sg:city":"Saint-Leonard",
    "sg:classifiers":[
        {
            "category":"Professional",
            "subcategory":"Business Services",
            "type":"Services"
        }
    ],
    "sg:phone":"+1 514 353 3381",
    "sg:postcode":"H1P 1V7",
    "sg:province":"QC",
    "sg:tags":[
        "drafting"
    ],
    "wof:name":"Laser Cad Inc",
    "wof:placetype":"venue"
},
  "geometry": {"coordinates":[-73.58554077150001,45.5909080505],"type":"Point"}
}