{
  "type": "Feature",
  "properties": {
    "addr:full":"130 Mccarty St Thamesford ON N0M 2M0",
    "addr:housenumber":"130",
    "addr:postcode":"n0m 2m0",
    "addr:street":"Mccarty St",
    "iso:country":"CA",
    "sg:address":"130 Mccarty St",
    "sg:city":"Thamesford",
    "sg:classifiers":[
        {
            "category":"Education",
            "subcategory":"School",
            "type":"Public Place"
        }
    ],
    "sg:phone":"+1 519 285 2043",
    "sg:postcode":"N0M 2M0",
    "sg:province":"ON",
    "wof:name":"Thamesford Public School",
    "wof:placetype":"venue"
},
  "geometry": {"coordinates":[-81.000648,43.062428],"type":"Point"}
}