{
  "type": "Feature",
  "properties": {
    "addr:full":"Toronto ON M5T 2E7",
    "addr:postcode":"m5t 2e7",
    "iso:country":"CA",
    "sg:city":"Toronto",
    "sg:classifiers":[
        {
            "category":"Food & Beverages",
            "subcategory":"Fruits & Vegetables",
            "type":"Retail Goods"
        }
    ],
    "sg:phone":"+1 416 979 3435",
    "sg:postcode":"M5T 2E7",
    "sg:province":"ON",
    "sg:tags":[
        "produce"
    ],
    "wof:name":"K & K Specialty",
    "wof:placetype":"venue"
},
  "geometry": {"coordinates":[-79.398399,43.653137],"type":"Point"}
}