{
  "type": "Feature",
  "properties": {
    "addr:full":"RR 2 STN Main Regina SK S4P 2Z2",
    "addr:postcode":"s4p 2z2",
    "addr:street":"Rr 2 Stn",
    "iso:country":"CA",
    "sg:address":"RR 2 STN Main",
    "sg:city":"Regina",
    "sg:classifiers":[
        {
            "category":"Sports & Exercise",
            "subcategory":"Golf",
            "type":"Entertainment"
        }
    ],
    "sg:phone":"+1 306 545 0330",
    "sg:postcode":"S4P 2Z2",
    "sg:province":"SK",
    "sg:tags":[
        "course"
    ],
    "wof:name":"Sherwood Forest Country Club",
    "wof:placetype":"venue"
},
  "geometry": {"coordinates":[-104.59517700000001,50.448013],"type":"Point"}
}