{
  "type": "Feature",
  "properties": {
    "addr:full":"276 Ch Trois-Ruisseaux Cap-Pele NB E4N 2C1",
    "addr:housenumber":"276",
    "addr:postcode":"e4n 2c1",
    "addr:street":"Ch Trois-Ruisseaux",
    "iso:country":"CA",
    "sg:address":"276 Ch Trois-Ruisseaux",
    "sg:city":"Cap-Pele",
    "sg:classifiers":[
        {
            "category":"Recreation",
            "type":"Entertainment"
        }
    ],
    "sg:phone":"+1 506 577 4033",
    "sg:postcode":"E4N 2C1",
    "sg:province":"NB",
    "sg:tags":[
        "stable"
    ],
    "wof:name":"D & D Stables",
    "wof:placetype":"venue"
},
  "geometry": {"coordinates":[-64.24353000000001,46.21228],"type":"Point"}
}