{
  "type": "Feature",
  "properties": {
    "addr:full":"10724 97 St NW Edmonton AB T5H 2L8",
    "addr:housenumber":"10724",
    "addr:postcode":"t5h 2l8",
    "addr:street":"97 St Nw",
    "iso:country":"CA",
    "sg:address":"10724 97 St NW",
    "sg:city":"Edmonton",
    "sg:classifiers":[
        {
            "category":"Shopping",
            "subcategory":"Pharmacy",
            "type":"Retail Goods"
        }
    ],
    "sg:phone":"+1 780 424 6577",
    "sg:postcode":"T5H 2L8",
    "sg:province":"AB",
    "wof:name":"Linton Drugs Ltd",
    "wof:placetype":"venue"
},
  "geometry": {"coordinates":[-113.489830017,53.552154541],"type":"Point"}
}