{
  "type": "Feature",
  "properties": {
    "addr:full":"Saskatoon SK S7N 5A4",
    "addr:postcode":"s7n 5a4",
    "iso:country":"CA",
    "sg:city":"Saskatoon",
    "sg:classifiers":[
        {
            "category":"Education",
            "subcategory":"College",
            "type":"Public Place"
        }
    ],
    "sg:phone":"+1 306 966 2774",
    "sg:postcode":"S7N 5A4",
    "sg:province":"SK",
    "sg:tags":[
        "academic",
        "school"
    ],
    "wof:name":"University of Saskatoon",
    "wof:placetype":"venue"
},
  "geometry": {"coordinates":[-106.63620758099999,52.1304779053],"type":"Point"}
}