{
  "type": "Feature",
  "properties": {
    "addr:full":"North York ON M2J 4P8",
    "addr:postcode":"m2j 4p8",
    "iso:country":"CA",
    "sg:city":"North York",
    "sg:classifiers":[
        {
            "category":"Insurance",
            "subcategory":"Insurance Agent",
            "type":"Services"
        }
    ],
    "sg:phone":"+1 416 491 7900",
    "sg:postcode":"M2J 4P8",
    "sg:province":"ON",
    "sg:tags":[
        "adjuster"
    ],
    "wof:name":"Shumka Craig & Moore Adjusters",
    "wof:placetype":"venue"
},
  "geometry": {"coordinates":[-79.325569,43.773476],"type":"Point"}
}