{
  "type": "Feature",
  "properties": {
    "addr:full":"Conception Bay Hwy Bay Roberts NL A0A 1G0",
    "addr:postcode":"a0a 1g0",
    "addr:street":"Conception Bay Hwy Bay",
    "iso:country":"CA",
    "sg:address":"Conception Bay Hwy",
    "sg:city":"Bay Roberts",
    "sg:classifiers":[
        {
            "category":"Restaurant",
            "type":"Food & Drink"
        }
    ],
    "sg:phone":"+1 709 786 6501",
    "sg:postcode":"A0A 1G0",
    "sg:province":"NL",
    "wof:name":"Mary Brown's Fried Chicken",
    "wof:placetype":"venue"
},
  "geometry": {"coordinates":[-53.279858,47.581745],"type":"Point"}
}