{
  "type": "Feature",
  "properties": {
    "addr:full":"Chilliwack BC V2P 5Z6",
    "addr:postcode":"v2p 5z6",
    "iso:country":"CA",
    "sg:city":"Chilliwack",
    "sg:classifiers":[
        {
            "category":"Cinema",
            "subcategory":"Movie Rental",
            "type":"Entertainment"
        }
    ],
    "sg:phone":"+1 604 793 4661",
    "sg:postcode":"V2P 5Z6",
    "sg:province":"BC",
    "sg:tags":[
        "leasing",
        "video",
        "disc",
        "tape"
    ],
    "wof:name":"Video Station",
    "wof:placetype":"venue"
},
  "geometry": {"coordinates":[-121.93374633800001,49.1783103943],"type":"Point"}
}