{
  "type": "Feature",
  "properties": {
    "addr:full":"55 Adelaide St E Toronto ON M5C 1K6",
    "addr:housenumber":"55",
    "addr:postcode":"m5c 1k6",
    "addr:street":"Adelaide St E",
    "iso:country":"CA",
    "sg:address":"55 Adelaide St E",
    "sg:city":"Toronto",
    "sg:classifiers":[
        {
            "category":"Restaurant",
            "type":"Food & Drink"
        }
    ],
    "sg:phone":"+1 416 362 7373",
    "sg:postcode":"M5C 1K6",
    "sg:province":"ON",
    "wof:name":"Nami Japanese Seafood Rstrnt",
    "wof:placetype":"venue"
},
  "geometry": {"coordinates":[-79.376045,43.650799],"type":"Point"}
}