{
  "type": "Feature",
  "properties": {
    "iso:country":"CA",
    "sg:address":"4942 50 Ave",
    "sg:city":"Bentley",
    "sg:classifiers":[
        {
            "category":"Banks & Credit Unions",
            "subcategory":"Bank",
            "type":"Services"
        }
    ],
    "sg:phone":"+1 403 748 4202",
    "sg:postcode":"T0C 0J0",
    "sg:province":"AB",
    "wof:name":"Community Savings",
    "wof:placetype":"venue"
},
  "geometry": {"coordinates":[-114.048202515,52.4652671814],"type":"Point"}
}