{
  "type": "Feature",
  "properties": {
    "iso:country":"CA",
    "sg:address":"209 Boul DE LA Marine",
    "sg:city":"Varennes",
    "sg:classifiers":[
        {
            "category":"Building & Trades",
            "subcategory":"Construction",
            "type":"Services"
        }
    ],
    "sg:phone":"+1 450 652 3163",
    "sg:postcode":"J3X 7Y5",
    "sg:province":"QC",
    "sg:tags":[
        "contractor"
    ],
    "wof:name":"Construction Johnny Roy Inc",
    "wof:placetype":"venue"
},
  "geometry": {"coordinates":[-73.426804,45.660263],"type":"Point"}
}