{
  "type": "Feature",
  "properties": {
    "addr:full":"8251 120 St Delta BC V4C 6R1",
    "addr:housenumber":"8251",
    "addr:postcode":"v4c 6r1",
    "addr:street":"120 St",
    "iso:country":"CA",
    "sg:address":"8251 120 St",
    "sg:city":"Delta",
    "sg:classifiers":[
        {
            "category":"Health Services",
            "subcategory":"Doctor",
            "type":"Services"
        }
    ],
    "sg:phone":"+1 604 591 8848",
    "sg:postcode":"V4C 6R1",
    "sg:province":"BC",
    "sg:tags":[
        "dentist"
    ],
    "wof:name":"Chan, Angelyn S DDS",
    "wof:placetype":"venue"
},
  "geometry": {"coordinates":[-122.890511,49.153439],"type":"Point"}
}