{
  "type": "Feature",
  "properties": {
    "addr:full":"1538 Niagara Stone Rd Virgil ON L0S 1T0",
    "addr:housenumber":"1538",
    "addr:postcode":"l0s 1t0",
    "addr:street":"Niagara Stone Rd",
    "iso:country":"CA",
    "sg:address":"1538 Niagara Stone Rd",
    "sg:city":"Virgil",
    "sg:classifiers":[
        {
            "category":"Restaurant",
            "type":"Food & Drink"
        }
    ],
    "sg:phone":"+1 905 468 1200",
    "sg:postcode":"L0S 1T0",
    "sg:province":"ON",
    "sg:tags":[
        "pizza"
    ],
    "wof:name":"Italian Pizza & Subs",
    "wof:placetype":"venue"
},
  "geometry": {"coordinates":[-79.12093400000001,43.223076],"type":"Point"}
}