{
  "type": "Feature",
  "properties": {
    "addr:full":"400 3rd St S Kipling SK S0G 2S0",
    "addr:housenumber":"400",
    "addr:postcode":"s0g 2s0",
    "addr:street":"3Rd St S Kipling",
    "iso:country":"CA",
    "sg:address":"400 3rd St S",
    "sg:city":"Kipling",
    "sg:classifiers":[
        {
            "category":"Organizations",
            "subcategory":"Religious Organization",
            "type":"Services"
        }
    ],
    "sg:phone":"+1 306 736 8141",
    "sg:postcode":"S0G 2S0",
    "sg:province":"SK",
    "sg:tags":[
        "church"
    ],
    "wof:name":"Calvary Baptist Church",
    "wof:placetype":"venue"
},
  "geometry": {"coordinates":[-102.623566,50.101879],"type":"Point"}
}