{
  "type": "Feature",
  "properties": {
    "addr:full":"22789 Hagerty St Newbury ON N0L 1Z0",
    "addr:housenumber":"22789",
    "addr:postcode":"n0l 1z0",
    "addr:street":"Hagerty St",
    "iso:country":"CA",
    "sg:address":"22789 Hagerty St",
    "sg:city":"Newbury",
    "sg:classifiers":[
        {
            "category":"Food & Beverages",
            "subcategory":"Meat & Fish",
            "type":"Retail Goods"
        }
    ],
    "sg:phone":"+1 519 693 0144",
    "sg:postcode":"N0L 1Z0",
    "sg:province":"ON",
    "sg:tags":[
        "frozen"
    ],
    "wof:name":"M & M Meat Shops",
    "wof:placetype":"venue"
},
  "geometry": {"coordinates":[-81.79346466059999,42.6813545227],"type":"Point"}
}