{
  "type": "Feature",
  "properties": {
    "addr:full":"Ottawa ON K2A 3Z3",
    "addr:postcode":"k2a 3z3",
    "iso:country":"CA",
    "sg:city":"Ottawa",
    "sg:classifiers":[
        {
            "category":"Health Services",
            "subcategory":"Doctor",
            "type":"Services"
        }
    ],
    "sg:phone":"+1 613 728 5104",
    "sg:postcode":"K2A 3Z3",
    "sg:province":"ON",
    "sg:tags":[
        "physician",
        "surgeon"
    ],
    "wof:name":"Barwin, B Norman MD",
    "wof:placetype":"venue"
},
  "geometry": {"coordinates":[-75.7551040649,45.3776359558],"type":"Point"}
}