{
  "type": "Feature",
  "properties": {
    "addr:full":"172 Milvan Dr North York ON M9L 1Z9",
    "addr:housenumber":"172",
    "addr:postcode":"m9l 1z9",
    "addr:street":"Milvan Dr",
    "iso:country":"CA",
    "sg:address":"172 Milvan Dr",
    "sg:city":"North York",
    "sg:classifiers":[
        {
            "category":"Wholesale",
            "subcategory":"Hardware",
            "type":"Manufacturing & Wholesale Goods"
        }
    ],
    "sg:phone":"+1 416 741 2525",
    "sg:postcode":"M9L 1Z9",
    "sg:province":"ON",
    "sg:tags":[
        "equipment",
        "industrial",
        "supply"
    ],
    "wof:name":"Anda Tool & Fastener Ltd",
    "wof:placetype":"venue"
},
  "geometry": {"coordinates":[-79.56476600000001,43.757843],"type":"Point"}
}