{
  "type": "Feature",
  "properties": {
    "addr:full":"15454 Longswood Rd Bothwell ON N0P 1C0",
    "addr:housenumber":"15454",
    "addr:postcode":"n0p 1c0",
    "addr:street":"Longswood Rd",
    "iso:country":"CA",
    "sg:address":"15454 Longswood Rd",
    "sg:city":"Bothwell",
    "sg:classifiers":[
        {
            "category":"Freight",
            "type":"Transportation"
        }
    ],
    "sg:phone":"+1 519 695 5000",
    "sg:postcode":"N0P 1C0",
    "sg:province":"ON",
    "sg:tags":[
        "building",
        "house",
        "mover"
    ],
    "wof:name":"Leslie Steele Moving",
    "wof:placetype":"venue"
},
  "geometry": {"coordinates":[-81.87219238279999,42.6319007874],"type":"Point"}
}