{
  "type": "Feature",
  "properties": {
    "addr:full":"486 Rue Principale Neguac NB E9G 1N1",
    "addr:housenumber":"486",
    "addr:postcode":"e9g 1n1",
    "addr:street":"Rue Principale",
    "iso:country":"CA",
    "sg:address":"486 Rue Principale",
    "sg:city":"Neguac",
    "sg:classifiers":[
        {
            "category":"Travel",
            "subcategory":"Hotels & Motels",
            "type":"Entertainment"
        }
    ],
    "sg:phone":"+1 506 776 8718",
    "sg:postcode":"E9G 1N1",
    "sg:province":"NB",
    "wof:name":"Motel Beausejour",
    "wof:placetype":"venue"
},
  "geometry": {"coordinates":[-65.0840911865,47.2438812256],"type":"Point"}
}