{
  "type": "Feature",
  "properties": {
    "addr:full":"267 Dunn Ave Toronto ON M6K 2S1",
    "addr:housenumber":"267",
    "addr:postcode":"m6k 2s1",
    "addr:street":"Dunn Ave",
    "iso:country":"CA",
    "sg:address":"267 Dunn Ave",
    "sg:city":"Toronto",
    "sg:classifiers":[
        {
            "category":"Personal",
            "subcategory":"Beauty Salon",
            "type":"Services"
        }
    ],
    "sg:phone":"+1 416 537 1129",
    "sg:postcode":"M6K 2S1",
    "sg:province":"ON",
    "wof:name":"Lovina Hair Design",
    "wof:placetype":"venue"
},
  "geometry": {"coordinates":[-79.4339141846,43.6400146484],"type":"Point"}
}