{
  "type": "Feature",
  "properties": {
    "addr:full":"5682 Fraser St Vancouver BC V5W 2Z4",
    "addr:housenumber":"5682",
    "addr:postcode":"v5w 2z4",
    "addr:street":"Fraser St",
    "iso:country":"CA",
    "sg:address":"5682 Fraser St",
    "sg:city":"Vancouver",
    "sg:classifiers":[
        {
            "category":"Restaurant",
            "type":"Food & Drink"
        }
    ],
    "sg:phone":"+1 604 323 1218",
    "sg:postcode":"V5W 2Z4",
    "sg:province":"BC",
    "wof:name":"Koon Bo Restaurant",
    "wof:placetype":"venue"
},
  "geometry": {"coordinates":[-123.09034,49.233185],"type":"Point"}
}