{
  "type": "Feature",
  "properties": {
    "addr:full":"500 Second St W Geraldton ON P0T 1M0",
    "addr:housenumber":"500",
    "addr:postcode":"p0t 1m0",
    "addr:street":"Second St W",
    "iso:country":"CA",
    "sg:address":"500 Second St W",
    "sg:city":"Geraldton",
    "sg:classifiers":[
        {
            "category":"Professional",
            "subcategory":"Business Services",
            "type":"Services"
        }
    ],
    "sg:phone":"+1 807 854 0542",
    "sg:postcode":"P0T 1M0",
    "sg:province":"ON",
    "sg:tags":[
        "teleconferencing",
        "video",
        "conferencing"
    ],
    "wof:name":"Contact North",
    "wof:placetype":"venue"
},
  "geometry": {"coordinates":[-86.951706,49.725155],"type":"Point"}
}