{
  "type": "Feature",
  "properties": {
    "iso:country":"CA",
    "sg:city":"Winnipeg",
    "sg:classifiers":[
        {
            "category":"Insurance",
            "subcategory":"Insurance Agent",
            "type":"Services"
        }
    ],
    "sg:phone":"+1 204 943 7590",
    "sg:postcode":"R3C 3P2",
    "sg:province":"MB",
    "wof:name":"Meyer Rypp & Assoc",
    "wof:placetype":"venue"
},
  "geometry": {"coordinates":[-97.137825,49.889095],"type":"Point"}
}