{
  "type": "Feature",
  "properties": {
    "addr:full":"2115 Boul Mercure Drummondville QC J2B 3P7",
    "addr:housenumber":"2115",
    "addr:postcode":"j2b 3p7",
    "addr:street":"Boul Mercure",
    "iso:country":"CA",
    "sg:address":"2115 Boul Mercure",
    "sg:city":"Drummondville",
    "sg:classifiers":[
        {
            "category":"Retail",
            "subcategory":"Funeral Services",
            "type":"Services"
        }
    ],
    "sg:phone":"+1 819 478 3223",
    "sg:postcode":"J2B 3P7",
    "sg:province":"QC",
    "sg:tags":[
        "director"
    ],
    "wof:name":"Centre Funeraire Yves Houle",
    "wof:placetype":"venue"
},
  "geometry": {"coordinates":[-72.45845,45.856667],"type":"Point"}
}