{
  "type": "Feature",
  "properties": {
    "iso:country":"CA",
    "sg:address":"40 Russell St E",
    "sg:city":"Lindsay",
    "sg:classifiers":[
        {
            "category":"Organizations",
            "subcategory":"Religious Organization",
            "type":"Services"
        }
    ],
    "sg:phone":"+1 705 324 4828",
    "sg:postcode":"K9V 2A4",
    "sg:province":"ON",
    "sg:tags":[
        "church"
    ],
    "wof:name":"St Mary's Rectory",
    "wof:placetype":"venue"
},
  "geometry": {"coordinates":[-78.7300949097,44.3553199768],"type":"Point"}
}