{
  "type": "Feature",
  "properties": {
    "addr:full":"133 20th St W Prince Albert SK S6V 4G1",
    "addr:housenumber":"133",
    "addr:postcode":"s6v 4g1",
    "addr:street":"20Th St",
    "iso:country":"CA",
    "sg:address":"133 20th St W",
    "sg:city":"Prince Albert",
    "sg:classifiers":[
        {
            "category":"Travel",
            "subcategory":"Hotels & Motels",
            "type":"Entertainment"
        }
    ],
    "sg:phone":"+1 306 763 4113",
    "sg:postcode":"S6V 4G1",
    "sg:province":"SK",
    "sg:tags":[
        "breakfast",
        "accommodation",
        "bed"
    ],
    "wof:name":"Hillcrest Inn Bed & Breakfast",
    "wof:placetype":"venue"
},
  "geometry": {"coordinates":[-105.75865173299999,53.194858551],"type":"Point"}
}