{
  "type": "Feature",
  "properties": {
    "iso:country":"CA",
    "sg:address":"4892 Elliott St",
    "sg:city":"Delta",
    "sg:classifiers":[
        {
            "category":"Retail",
            "subcategory":"Auto Repair",
            "type":"Services"
        }
    ],
    "sg:phone":"+1 604 946 6626",
    "sg:postcode":"V4K 2X8",
    "sg:province":"BC",
    "sg:tags":[
        "repairing",
        "automobile"
    ],
    "wof:name":"John's Thistle Auto Ltd",
    "wof:placetype":"venue"
},
  "geometry": {"coordinates":[-123.083816528,49.0917930603],"type":"Point"}
}