{
  "type": "Feature",
  "properties": {
    "addr:full":"Burnaby BC V5G 3L1",
    "addr:postcode":"v5g 3l1",
    "iso:country":"CA",
    "sg:city":"Burnaby",
    "sg:classifiers":[
        {
            "category":"Retail",
            "subcategory":"Auto Repair",
            "type":"Services"
        }
    ],
    "sg:phone":"+1 604 436 2640",
    "sg:postcode":"V5G 3L1",
    "sg:province":"BC",
    "sg:tags":[
        "automotive",
        "car",
        "wash"
    ],
    "wof:name":"Ebco-Hamilton Partners",
    "wof:placetype":"venue"
},
  "geometry": {"coordinates":[-122.998276,49.242672],"type":"Point"}
}