{
  "type": "Feature",
  "properties": {
    "iso:country":"CA",
    "sg:address":"200 Ch Bates",
    "sg:city":"Mont-Royal",
    "sg:classifiers":[
        {
            "category":"Wholesale",
            "subcategory":"Non-durable Goods",
            "type":"Manufacturing & Wholesale Goods"
        }
    ],
    "sg:phone":"+1 514 341 0269",
    "sg:postcode":"H3S 1A3",
    "sg:province":"QC",
    "sg:tags":[
        "pet",
        "supply"
    ],
    "wof:name":"Reparation D'Arrareils Elect",
    "wof:placetype":"venue"
},
  "geometry": {"coordinates":[-73.628258,45.515991],"type":"Point"}
}