{
  "type": "Feature",
  "properties": {
    "addr:full":"2323 St Laurent Blvd Ottawa ON K1G 4J8",
    "addr:housenumber":"2323",
    "addr:postcode":"k1g 4j8",
    "addr:street":"St Laurent Blvd",
    "iso:country":"CA",
    "sg:address":"2323 St Laurent Blvd",
    "sg:city":"Ottawa",
    "sg:classifiers":[
        {
            "category":"Organizations",
            "subcategory":"Professional Association",
            "type":"Services"
        }
    ],
    "sg:phone":"+1 613 736 1350",
    "sg:postcode":"K1G 4J8",
    "sg:province":"ON",
    "wof:name":"Transportation Assn of Canada",
    "wof:placetype":"venue"
},
  "geometry": {"coordinates":[-75.61861399999999,45.384403],"type":"Point"}
}