{
  "type": "Feature",
  "properties": {
    "addr:full":"400 Hoehn Rd Big River SK S0J 0E0",
    "addr:housenumber":"400",
    "addr:postcode":"s0j 0e0",
    "addr:street":"Hoehn Rd",
    "iso:country":"CA",
    "sg:address":"400 Hoehn Rd",
    "sg:city":"Big River",
    "sg:classifiers":[
        {
            "category":"Utilities",
            "subcategory":"Fuel Oil & Lpg",
            "type":"Services"
        }
    ],
    "sg:phone":"+1 306 469 5777",
    "sg:postcode":"S0J 0E0",
    "sg:province":"SK",
    "wof:name":"Big River CO-OP",
    "wof:placetype":"venue"
},
  "geometry": {"coordinates":[-107.031937,53.834133],"type":"Point"}
}