{
  "type": "Feature",
  "properties": {
    "addr:full":"Sainte-Anne-DE-LA-Perade QC G0X 2J0",
    "addr:postcode":"g0x 2j0",
    "iso:country":"CA",
    "sg:city":"Sainte-Anne-DE-LA-Perade",
    "sg:classifiers":[
        {
            "category":"Building & Trades",
            "subcategory":"Construction",
            "type":"Services"
        }
    ],
    "sg:phone":"+1 418 325 3151",
    "sg:postcode":"G0X 2J0",
    "sg:province":"QC",
    "sg:tags":[
        "excavating",
        "contractor"
    ],
    "wof:name":"Soulevement Excavation MO-VI",
    "wof:placetype":"venue"
},
  "geometry": {"coordinates":[-72.210953,46.568695],"type":"Point"}
}