{
  "type": "Feature",
  "properties": {
    "iso:country":"CA",
    "sg:address":"301 Ottawa Ave",
    "sg:city":"Winnipeg",
    "sg:classifiers":[
        {
            "category":"Food & Beverages",
            "subcategory":"Groceries & Convenience Stores",
            "type":"Retail Goods"
        }
    ],
    "sg:phone":"+1 204 668 0844",
    "sg:postcode":"R2K 1K9",
    "sg:province":"MB",
    "sg:tags":[
        "grocer"
    ],
    "wof:name":"Ottawa Grocery",
    "wof:placetype":"venue"
},
  "geometry": {"coordinates":[-97.106300354,49.9190406799],"type":"Point"}
}