{
  "type": "Feature",
  "properties": {
    "addr:full":"Montreal QC H3H 1E8",
    "addr:postcode":"h3h 1e8",
    "iso:country":"CA",
    "sg:city":"Montreal",
    "sg:classifiers":[
        {
            "category":"Manufacturing",
            "subcategory":"Printing",
            "type":"Manufacturing & Wholesale Goods"
        }
    ],
    "sg:phone":"+1 514 935 0464",
    "sg:postcode":"H3H 1E8",
    "sg:province":"QC",
    "sg:tags":[
        "publisher"
    ],
    "wof:name":"Editions Du Meridien",
    "wof:placetype":"venue"
},
  "geometry": {"coordinates":[-73.56317138670001,45.5297393799],"type":"Point"}
}