{
  "type": "Feature",
  "properties": {
    "addr:full":"514 Gormanville Rd North Bay ON P1B 4V5",
    "addr:housenumber":"514",
    "addr:postcode":"p1b 4v5",
    "addr:street":"Gormanville Rd",
    "iso:country":"CA",
    "sg:address":"514 Gormanville Rd",
    "sg:city":"North Bay",
    "sg:classifiers":[
        {
            "category":"Retail",
            "subcategory":"Auto Repair",
            "type":"Services"
        }
    ],
    "sg:phone":"+1 705 494 7685",
    "sg:postcode":"P1B 4V5",
    "sg:province":"ON",
    "sg:tags":[
        "repairing",
        "automobile"
    ],
    "wof:name":"Auto Centre",
    "wof:placetype":"venue"
},
  "geometry": {"coordinates":[-79.48732800000001,46.325436],"type":"Point"}
}