{
  "type": "Feature",
  "properties": {
    "addr:full":"845 Boul DE LA Carriere # 5 Hull QC J8Y 6S5",
    "addr:housenumber":"845",
    "addr:postcode":"j8y 6s5",
    "addr:street":"Boul De La Carriere # 5",
    "iso:country":"CA",
    "sg:address":"845 Boul DE LA Carriere # 5",
    "sg:city":"Hull",
    "sg:classifiers":[
        {
            "category":"Home & Garden",
            "subcategory":"Building Materials",
            "type":"Retail Goods"
        }
    ],
    "sg:phone":"+1 819 772 0909",
    "sg:postcode":"J8Y 6S5",
    "sg:province":"QC",
    "sg:tags":[
        "door"
    ],
    "wof:name":"Cadroporte Manufacturier Inc",
    "wof:placetype":"venue"
},
  "geometry": {"coordinates":[-75.73016357420001,45.4537696838],"type":"Point"}
}