{
  "type": "Feature",
  "properties": {
    "iso:country":"CA",
    "sg:address":"3506 27 Ave",
    "sg:city":"Vernon",
    "sg:classifiers":[
        {
            "category":"Health Services",
            "subcategory":"Nursing And Care Facility",
            "type":"Services"
        }
    ],
    "sg:phone":"+1 250 503 1800",
    "sg:postcode":"V1T 1S4",
    "sg:province":"BC",
    "sg:tags":[
        "hospice"
    ],
    "wof:name":"Vernon & District Hospice",
    "wof:placetype":"venue"
},
  "geometry": {"coordinates":[-119.279945373,50.2614097595],"type":"Point"}
}