{
  "type": "Feature",
  "properties": {
    "addr:full":"Calgary AB T2N 3P9",
    "addr:postcode":"t2n 3p9",
    "iso:country":"CA",
    "sg:city":"Calgary",
    "sg:classifiers":[
        {
            "category":"Personal",
            "subcategory":"Beauty Salon",
            "type":"Services"
        }
    ],
    "sg:phone":"+1 403 283 8844",
    "sg:postcode":"T2N 3P9",
    "sg:province":"AB",
    "sg:tags":[
        "make",
        "studio"
    ],
    "wof:name":"Make-Up Unlimited",
    "wof:placetype":"venue"
},
  "geometry": {"coordinates":[-114.093475342,51.0526390076],"type":"Point"}
}