{
  "type": "Feature",
  "properties": {
    "addr:full":"161 Rue Galipeau Thurso QC J0X 3B0",
    "addr:housenumber":"161",
    "addr:postcode":"j0x 3b0",
    "addr:street":"Rue Galipeau",
    "iso:country":"CA",
    "sg:address":"161 Rue Galipeau",
    "sg:city":"Thurso",
    "sg:classifiers":[
        {
            "category":"Government",
            "subcategory":"Office",
            "type":"Public Place"
        }
    ],
    "sg:phone":"+1 819 985 2701",
    "sg:postcode":"J0X 3B0",
    "sg:province":"QC",
    "sg:tags":[
        "village"
    ],
    "wof:name":"Thurso Hotel DE Ville",
    "wof:placetype":"venue"
},
  "geometry": {"coordinates":[-75.2435913086,45.5994415283],"type":"Point"}
}