{
  "type": "Feature",
  "properties": {
    "addr:full":"44 Boul Saint-Jean-Baptiste Chateauguay QC J6K 3A4",
    "addr:housenumber":"44",
    "addr:postcode":"j6k 3a4",
    "addr:street":"Boul Saint-Jean-Baptiste",
    "iso:country":"CA",
    "sg:address":"44 Boul Saint-Jean-Baptiste",
    "sg:city":"Chateauguay",
    "sg:classifiers":[
        {
            "category":"Autos & Motor Vehicles",
            "subcategory":"Automobile Sales",
            "type":"Retail Goods"
        }
    ],
    "sg:phone":"+1 450 699 8626",
    "sg:postcode":"J6K 3A4",
    "sg:province":"QC",
    "sg:tags":[
        "car",
        "dealer"
    ],
    "wof:name":"Adc Automobile Liberte Inc",
    "wof:placetype":"venue"
},
  "geometry": {"coordinates":[-73.7117385864,45.3652763367],"type":"Point"}
}