{
  "type": "Feature",
  "properties": {
    "addr:full":"4380 No. 3 Rd # 1060 Richmond BC V6X 2C2",
    "addr:postcode":"4380;v6x 2c2",
    "addr:street":"3 Rd # 1060",
    "iso:country":"CA",
    "sg:address":"4380 No. 3 Rd # 1060",
    "sg:city":"Richmond",
    "sg:classifiers":[
        {
            "category":"Food & Beverages",
            "subcategory":"Bakery",
            "type":"Retail Goods"
        }
    ],
    "sg:phone":"+1 604 214 9863",
    "sg:postcode":"V6X 2C2",
    "sg:province":"BC",
    "sg:tags":[
        "baker"
    ],
    "wof:name":"Pine House Bakery",
    "wof:placetype":"venue"
},
  "geometry": {"coordinates":[-123.136260986,49.181854248],"type":"Point"}
}