{
  "type": "Feature",
  "properties": {
    "addr:full":"482 Av Larochelle Saint-Marc-Des-Carrieres QC G0A 4B0",
    "addr:postcode":"g0a 4b0",
    "addr:street":"482 Av Larochelle Saint-Marc-Des-Carrieres",
    "iso:country":"CA",
    "sg:address":"482 Av Larochelle",
    "sg:city":"Saint-Marc-Des-Carrieres",
    "sg:classifiers":[
        {
            "category":"Organizations",
            "subcategory":"Professional Association",
            "type":"Services"
        }
    ],
    "sg:phone":"+1 418 268 8766",
    "sg:postcode":"G0A 4B0",
    "sg:province":"QC",
    "wof:name":"Comite Conjoint Des Races",
    "wof:placetype":"venue"
},
  "geometry": {"coordinates":[-72.05178100000001,46.682899],"type":"Point"}
}