{
  "type": "Feature",
  "properties": {
    "addr:full":"RR 1 St Peters NS B0E 3B0",
    "addr:postcode":"b0e 3b0",
    "addr:street":"Rr 1",
    "iso:country":"CA",
    "sg:address":"RR 1",
    "sg:city":"St Peters",
    "sg:classifiers":[
        {
            "category":"Wholesale",
            "subcategory":"Construction Materials",
            "type":"Manufacturing & Wholesale Goods"
        }
    ],
    "sg:phone":"+1 902 535 2400",
    "sg:postcode":"B0E 3B0",
    "sg:province":"NS",
    "sg:tags":[
        "sand",
        "gravel"
    ],
    "wof:name":"Kellys Trucking Ltd",
    "wof:placetype":"venue"
},
  "geometry": {"coordinates":[-63.5875511169,44.7273788452],"type":"Point"}
}