{
  "type": "Feature",
  "properties": {
    "addr:full":"Burlington ON L7T 4A8",
    "addr:postcode":"l7t 4a8",
    "iso:country":"CA",
    "sg:city":"Burlington",
    "sg:classifiers":[
        {
            "category":"Manufacturing",
            "subcategory":"Metals",
            "type":"Manufacturing & Wholesale Goods"
        }
    ],
    "sg:phone":"+1 905 333 8743",
    "sg:postcode":"L7T 4A8",
    "sg:province":"ON",
    "sg:tags":[
        "valve"
    ],
    "wof:name":"Primary Fluid Systems Inc",
    "wof:placetype":"venue"
},
  "geometry": {"coordinates":[-79.8529891968,43.3087158203],"type":"Point"}
}