{
  "type": "Feature",
  "properties": {
    "addr:full":"House 4325 Gods Lake Narrows MB R0B 0M0",
    "addr:postcode":"4325;r0b 0m0",
    "addr:street":"Gods Lake",
    "iso:country":"CA",
    "sg:address":"House 4325",
    "sg:city":"Gods Lake Narrows",
    "sg:classifiers":[
        {
            "category":"Food & Beverages",
            "subcategory":"Groceries & Convenience Stores",
            "type":"Retail Goods"
        }
    ],
    "sg:phone":"+1 204 335 2540",
    "sg:postcode":"R0B 0M0",
    "sg:province":"MB",
    "sg:tags":[
        "grocer"
    ],
    "wof:name":"Louie's Grocery",
    "wof:placetype":"venue"
},
  "geometry": {"coordinates":[-94.5227355957,54.546169281],"type":"Point"}
}