{
  "type": "Feature",
  "properties": {
    "addr:full":"9022 Rue DE LA Montagne Valcourt QC J0E 2L0",
    "addr:housenumber":"9022",
    "addr:postcode":"j0e 2l0",
    "addr:street":"Rue De La Montagne",
    "iso:country":"CA",
    "sg:address":"9022 Rue DE LA Montagne",
    "sg:city":"Valcourt",
    "sg:classifiers":[
        {
            "category":"Travel",
            "subcategory":"Hotels & Motels",
            "type":"Entertainment"
        }
    ],
    "sg:phone":"+1 450 532 3475",
    "sg:postcode":"J0E 2L0",
    "sg:province":"QC",
    "wof:name":"Motel Du Canton",
    "wof:placetype":"venue"
},
  "geometry": {"coordinates":[-72.31044,45.488445],"type":"Point"}
}