{
  "type": "Feature",
  "properties": {
    "addr:full":"4860 Mackenzie St Vancouver BC V6L 2R6",
    "addr:housenumber":"4860",
    "addr:postcode":"v6l 2r6",
    "addr:street":"Mackenzie St",
    "iso:country":"CA",
    "sg:address":"4860 Mackenzie St",
    "sg:city":"Vancouver",
    "sg:classifiers":[
        {
            "category":"Insurance",
            "subcategory":"Insurance Agent",
            "type":"Services"
        }
    ],
    "sg:phone":"+1 604 266 2357",
    "sg:postcode":"V6L 2R6",
    "sg:province":"BC",
    "wof:name":"Adams Greer Insurance",
    "wof:placetype":"venue"
},
  "geometry": {"coordinates":[-123.17000579800001,49.2426872253],"type":"Point"}
}