{
  "type": "Feature",
  "properties": {
    "iso:country":"CA",
    "sg:city":"Yamachiche",
    "sg:classifiers":[
        {
            "category":"Restaurant",
            "type":"Food & Drink"
        }
    ],
    "sg:phone":"+1 819 296 2158",
    "sg:postcode":"G0X 3L0",
    "sg:province":"QC",
    "wof:name":"Restaurant Chez Maurice",
    "wof:placetype":"venue"
},
  "geometry": {"coordinates":[-72.8446884155,46.2772636414],"type":"Point"}
}