{
  "type": "Feature",
  "properties": {
    "addr:full":"Etobicoke ON M8Y 1W3",
    "addr:postcode":"m8y 1w3",
    "iso:country":"CA",
    "sg:city":"Etobicoke",
    "sg:classifiers":[
        {
            "category":"Retail",
            "subcategory":"Laundry & Dry Cleaning",
            "type":"Services"
        }
    ],
    "sg:phone":"+1 416 236 0260",
    "sg:postcode":"M8Y 1W3",
    "sg:province":"ON",
    "sg:tags":[
        "cleaners"
    ],
    "wof:name":"Berry Cleaners",
    "wof:placetype":"venue"
},
  "geometry": {"coordinates":[-79.4881057739,43.6374473572],"type":"Point"}
}