{
  "type": "Feature",
  "properties": {
    "addr:full":"295 Commercial St North Sydney NS B2A 1B9",
    "addr:housenumber":"295",
    "addr:postcode":"b2a 1b9",
    "addr:street":"Commercial St",
    "iso:country":"CA",
    "sg:address":"295 Commercial St",
    "sg:city":"North Sydney",
    "sg:classifiers":[
        {
            "category":"Shopping",
            "subcategory":"Used Merchandise",
            "type":"Retail Goods"
        }
    ],
    "sg:phone":"+1 902 794 1618",
    "sg:postcode":"B2A 1B9",
    "sg:province":"NS",
    "sg:tags":[
        "second",
        "store",
        "hand"
    ],
    "wof:name":"Jo's Sell & Buy",
    "wof:placetype":"venue"
},
  "geometry": {"coordinates":[-60.24792099,46.2096672058],"type":"Point"}
}