{
  "type": "Feature",
  "properties": {
    "addr:full":"1507 Pandora Ave Victoria BC V8R 6P9",
    "addr:housenumber":"1507",
    "addr:postcode":"v8r 6p9",
    "addr:street":"Pandora Ave",
    "iso:country":"CA",
    "sg:address":"1507 Pandora Ave",
    "sg:city":"Victoria",
    "sg:classifiers":[
        {
            "category":"Restaurant",
            "type":"Food & Drink"
        }
    ],
    "sg:phone":"+1 250 598 6112",
    "sg:postcode":"V8R 6P9",
    "sg:province":"BC",
    "wof:name":"Old British Fish & Chips Ltd",
    "wof:placetype":"venue"
},
  "geometry": {"coordinates":[-123.339653,48.426411],"type":"Point"}
}