{
  "type": "Feature",
  "properties": {
    "addr:full":"30 Main St Springhill NS B0M 1X0",
    "addr:housenumber":"30",
    "addr:postcode":"b0m 1x0",
    "addr:street":"Main St",
    "iso:country":"CA",
    "sg:address":"30 Main St",
    "sg:city":"Springhill",
    "sg:classifiers":[
        {
            "category":"Restaurant",
            "type":"Food & Drink"
        }
    ],
    "sg:phone":"+1 902 597 2888",
    "sg:postcode":"B0M 1X0",
    "sg:province":"NS",
    "wof:name":"J B's Steakhouse & Pub",
    "wof:placetype":"venue"
},
  "geometry": {"coordinates":[-64.05693817140001,45.6506500244],"type":"Point"}
}