{
  "type": "Feature",
  "properties": {
    "addr:full":"226 Rue Migneron Saint-Laurent QC H4T 1Y7",
    "addr:housenumber":"226",
    "addr:postcode":"h4t 1y7",
    "addr:street":"Rue Migneron",
    "iso:country":"CA",
    "sg:address":"226 Rue Migneron",
    "sg:city":"Saint-Laurent",
    "sg:classifiers":[
        {
            "category":"Wholesale",
            "subcategory":"Electrical",
            "type":"Manufacturing & Wholesale Goods"
        }
    ],
    "sg:phone":"+1 514 340 1300",
    "sg:postcode":"H4T 1Y7",
    "sg:province":"QC",
    "sg:tags":[
        "transmission",
        "equipment",
        "power"
    ],
    "wof:name":"S M Cyclo Canada Ltee",
    "wof:placetype":"venue"
},
  "geometry": {"coordinates":[-73.6909942627,45.4878082275],"type":"Point"}
}