{
  "type": "Feature",
  "properties": {
    "addr:full":"200 Mcewen Rd Lillooet BC V0K 1V0",
    "addr:housenumber":"200",
    "addr:postcode":"v0k 1v0",
    "addr:street":"Mcewen Rd",
    "iso:country":"CA",
    "sg:address":"200 Mcewen Rd",
    "sg:city":"Lillooet",
    "sg:classifiers":[
        {
            "category":"Building & Trades",
            "subcategory":"Cleaning & Sanitation",
            "type":"Services"
        }
    ],
    "sg:phone":"+1 250 256 7836",
    "sg:postcode":"V0K 1V0",
    "sg:province":"BC",
    "sg:tags":[
        "janitor"
    ],
    "wof:name":"Lavigne Janitorial",
    "wof:placetype":"venue"
},
  "geometry": {"coordinates":[-121.921577454,50.7051353455],"type":"Point"}
}