{
  "type": "Feature",
  "properties": {
    "addr:full":"517 Westmorland Rd Saint John NB E2J 4B8",
    "addr:housenumber":"517",
    "addr:postcode":"e2j 4b8",
    "addr:street":"Westmorland Rd",
    "iso:country":"CA",
    "sg:address":"517 Westmorland Rd",
    "sg:city":"Saint John",
    "sg:classifiers":[
        {
            "category":"Shopping",
            "subcategory":"Pharmacy",
            "type":"Retail Goods"
        }
    ],
    "sg:phone":"+1 506 642 1051",
    "sg:postcode":"E2J 4B8",
    "sg:province":"NB",
    "wof:name":"Zellers Pharmacy",
    "wof:placetype":"venue"
},
  "geometry": {"coordinates":[-66.016525,45.309319],"type":"Point"}
}