{
  "type": "Feature",
  "properties": {
    "addr:full":"7060 Av Bloomfield Montreal QC H3N 2G8",
    "addr:housenumber":"7060",
    "addr:postcode":"h3n 2g8",
    "addr:street":"Av Bloomfield",
    "iso:country":"CA",
    "sg:address":"7060 Av Bloomfield",
    "sg:city":"Montreal",
    "sg:classifiers":[
        {
            "category":"Social Services",
            "type":"Services"
        }
    ],
    "sg:phone":"+1 514 276 2786",
    "sg:postcode":"H3N 2G8",
    "sg:province":"QC",
    "sg:tags":[
        "youth",
        "organization",
        "center"
    ],
    "wof:name":"Centre Communautaire Jeunesse",
    "wof:placetype":"venue"
},
  "geometry": {"coordinates":[-73.6224441528,45.5267753601],"type":"Point"}
}