{
  "type": "Feature",
  "properties": {
    "addr:full":"Winnipeg MB R2J 3W7",
    "addr:postcode":"r2j 3w7",
    "iso:country":"CA",
    "sg:city":"Winnipeg",
    "sg:classifiers":[
        {
            "category":"Shopping",
            "subcategory":"Florist",
            "type":"Retail Goods"
        }
    ],
    "sg:phone":"+1 204 256 3336",
    "sg:postcode":"R2J 3W7",
    "sg:province":"MB",
    "wof:name":"Macyk's Florists",
    "wof:placetype":"venue"
},
  "geometry": {"coordinates":[-97.074005,49.854069],"type":"Point"}
}