{
  "type": "Feature",
  "properties": {
    "addr:full":"4056 Dorchester Rd Niagara Falls ON L2E 6M9",
    "addr:housenumber":"4056",
    "addr:postcode":"l2e 6m9",
    "addr:street":"Dorchester Rd",
    "iso:country":"CA",
    "sg:address":"4056 Dorchester Rd",
    "sg:city":"Niagara Falls",
    "sg:classifiers":[
        {
            "category":"Professional",
            "subcategory":"Lawyer & Legal Services",
            "type":"Services"
        }
    ],
    "sg:phone":"+1 905 357 4510",
    "sg:postcode":"L2E 6M9",
    "sg:province":"ON",
    "sg:tags":[
        "attorney"
    ],
    "wof:name":"Mc Nab, Gordon F",
    "wof:placetype":"venue"
},
  "geometry": {"coordinates":[-79.1115570068,43.1138343811],"type":"Point"}
}