{
  "type": "Feature",
  "properties": {
    "addr:full":"40 Cowdray Crt Scarborough ON M1S 1A1",
    "addr:housenumber":"40",
    "addr:postcode":"m1s 1a1",
    "addr:street":"Cowdray Crt",
    "iso:country":"CA",
    "sg:address":"40 Cowdray Crt",
    "sg:city":"Scarborough",
    "sg:classifiers":[
        {
            "category":"Building & Trades",
            "subcategory":"Construction",
            "type":"Services"
        }
    ],
    "sg:phone":"+1 416 332 8280",
    "sg:postcode":"M1S 1A1",
    "sg:province":"ON",
    "sg:tags":[
        "elevator"
    ],
    "wof:name":"Schindler Elevator Corp",
    "wof:placetype":"venue"
},
  "geometry": {"coordinates":[-79.28494999999999,43.780735],"type":"Point"}
}