{
  "type": "Feature",
  "properties": {
    "addr:full":"860 Denison Cres Ottawa ON K2A 2N5",
    "addr:housenumber":"860",
    "addr:postcode":"k2a 2n5",
    "addr:street":"Denison Cres",
    "iso:country":"CA",
    "sg:address":"860 Denison Cres",
    "sg:city":"Ottawa",
    "sg:classifiers":[
        {
            "category":"Building & Trades",
            "subcategory":"Construction",
            "type":"Services"
        }
    ],
    "sg:phone":"+1 613 728 6835",
    "sg:postcode":"K2A 2N5",
    "sg:province":"ON",
    "sg:tags":[
        "dry wall",
        "contractor"
    ],
    "wof:name":"Calarco Drywall CO Ltd",
    "wof:placetype":"venue"
},
  "geometry": {"coordinates":[-75.7544708252,45.3749656677],"type":"Point"}
}