{
  "type": "Feature",
  "properties": {
    "iso:country":"CA",
    "sg:address":"3525 Rue Ashby",
    "sg:city":"Saint-Laurent",
    "sg:classifiers":[
        {
            "category":"Wholesale",
            "subcategory":"Machinery & Supplies",
            "type":"Manufacturing & Wholesale Goods"
        }
    ],
    "sg:phone":"+1 514 745 7476",
    "sg:postcode":"H4R 2K3",
    "sg:province":"QC",
    "sg:tags":[
        "machine",
        "equipment",
        "printing",
        "duplicating",
        "copying"
    ],
    "wof:name":"Riso Canada Inc",
    "wof:placetype":"venue"
},
  "geometry": {"coordinates":[-73.7167816162,45.4985656738],"type":"Point"}
}