{
  "type": "Feature",
  "properties": {
    "addr:full":"695 Bank St Ottawa ON K1S 3T8",
    "addr:housenumber":"695",
    "addr:postcode":"k1s 3t8",
    "addr:street":"Bank St",
    "iso:country":"CA",
    "sg:address":"695 Bank St",
    "sg:city":"Ottawa",
    "sg:classifiers":[
        {
            "category":"Shopping",
            "subcategory":"Musical Instruments",
            "type":"Retail Goods"
        }
    ],
    "sg:phone":"+1 613 233 9688",
    "sg:postcode":"K1S 3T8",
    "sg:province":"ON",
    "wof:name":"Metro Music",
    "wof:placetype":"venue"
},
  "geometry": {"coordinates":[-75.68950700000001,45.405472],"type":"Point"}
}