{
  "type": "Feature",
  "properties": {
    "addr:full":"10820 82 Ave NW Edmonton AB T6E 2B3",
    "addr:housenumber":"10820",
    "addr:postcode":"t6e 2b3",
    "addr:street":"82 Ave Nw",
    "iso:country":"CA",
    "sg:address":"10820 82 Ave NW",
    "sg:city":"Edmonton",
    "sg:classifiers":[
        {
            "category":"Education",
            "subcategory":"Special Training",
            "type":"Public Place"
        }
    ],
    "sg:phone":"+1 780 433 2264",
    "sg:postcode":"T6E 2B3",
    "sg:province":"AB",
    "sg:tags":[
        "instruction",
        "music"
    ],
    "wof:name":"Lotsberg, Carl",
    "wof:placetype":"venue"
},
  "geometry": {"coordinates":[-113.510063,53.518375],"type":"Point"}
}