{
  "type": "Feature",
  "properties": {
    "addr:full":"Castor AB T0C 0X0",
    "addr:postcode":"t0c 0x0",
    "iso:country":"CA",
    "sg:city":"Castor",
    "sg:classifiers":[
        {
            "category":"Shopping",
            "subcategory":"Catalog Store",
            "type":"Retail Goods"
        }
    ],
    "sg:phone":"+1 403 882 3760",
    "sg:postcode":"T0C 0X0",
    "sg:province":"AB",
    "sg:tags":[
        "mail",
        "order",
        "internet"
    ],
    "wof:name":"Sears Canada Inc",
    "wof:placetype":"venue"
},
  "geometry": {"coordinates":[-111.90657043500001,52.2195472717],"type":"Point"}
}