{
  "type": "Feature",
  "properties": {
    "addr:full":"83 Rue Chatillon Dollard-Des-Ormeaux QC H9B 1B4",
    "addr:housenumber":"83",
    "addr:postcode":"h9b 1b4",
    "addr:street":"Rue Chatillon",
    "iso:country":"CA",
    "sg:address":"83 Rue Chatillon",
    "sg:city":"Dollard-Des-Ormeaux",
    "sg:classifiers":[
        {
            "category":"Manufacturing",
            "subcategory":"Paper Products",
            "type":"Manufacturing & Wholesale Goods"
        }
    ],
    "sg:phone":"+1 514 685 6693",
    "sg:postcode":"H9B 1B4",
    "sg:province":"QC",
    "sg:tags":[
        "corrugated",
        "solid",
        "fiber",
        "box"
    ],
    "wof:name":"Emballage Centsible Inc",
    "wof:placetype":"venue"
},
  "geometry": {"coordinates":[-73.82415,45.489689],"type":"Point"}
}