{
  "type": "Feature",
  "properties": {
    "addr:full":"3 Forsyth St Marmora ON K0K 2M0",
    "addr:housenumber":"3",
    "addr:postcode":"k0k 2m0",
    "addr:street":"Forsyth St",
    "iso:country":"CA",
    "sg:address":"3 Forsyth St",
    "sg:city":"Marmora",
    "sg:classifiers":[
        {
            "category":"Health Services",
            "subcategory":"Doctor",
            "type":"Services"
        }
    ],
    "sg:phone":"+1 613 472 2469",
    "sg:postcode":"K0K 2M0",
    "sg:province":"ON",
    "sg:tags":[
        "physician",
        "surgeon"
    ],
    "wof:name":"Dosaj, Arun K MD",
    "wof:placetype":"venue"
},
  "geometry": {"coordinates":[-77.6833648682,44.4839248657],"type":"Point"}
}