{
  "type": "Feature",
  "properties": {
    "addr:full":"Holden AB T0B 2C0",
    "addr:postcode":"t0b 2c0",
    "iso:country":"CA",
    "sg:city":"Holden",
    "sg:classifiers":[
        {
            "category":"Farming",
            "subcategory":"Farm & Veterinary Services",
            "type":"Manufacturing & Wholesale Goods"
        }
    ],
    "sg:phone":"+1 780 688 3917",
    "sg:postcode":"T0B 2C0",
    "sg:province":"AB",
    "sg:tags":[
        "seed",
        "grain",
        "cleaning"
    ],
    "wof:name":"County of Beaver Seed Cleaning",
    "wof:placetype":"venue"
},
  "geometry": {"coordinates":[-112.226776,53.224625],"type":"Point"}
}