{
  "type": "Feature",
  "properties": {
    "addr:full":"Vancouver BC V6C 1J9",
    "addr:postcode":"v6c 1j9",
    "iso:country":"CA",
    "sg:city":"Vancouver",
    "sg:classifiers":[
        {
            "category":"Insurance",
            "subcategory":"Hazard Insurance",
            "type":"Services"
        }
    ],
    "sg:phone":"+1 604 681 5188",
    "sg:postcode":"V6C 1J9",
    "sg:province":"BC",
    "sg:tags":[
        "employee",
        "benefit",
        "compensation",
        "plan"
    ],
    "wof:name":"Vimc",
    "wof:placetype":"venue"
},
  "geometry": {"coordinates":[-123.116653442,49.2857284546],"type":"Point"}
}