{
  "type": "Feature",
  "properties": {
    "addr:full":"2566 Mccaig Cres SE Medicine Hat AB T1B 1B4",
    "addr:housenumber":"2566",
    "addr:postcode":"t1b 1b4",
    "addr:street":"Mccaig Cres Se",
    "iso:country":"CA",
    "sg:address":"2566 Mccaig Cres SE",
    "sg:city":"Medicine Hat",
    "sg:classifiers":[
        {
            "category":"Mining & Drilling",
            "type":"Manufacturing & Wholesale Goods"
        }
    ],
    "sg:phone":"+1 403 548 5555",
    "sg:postcode":"T1B 1B4",
    "sg:province":"AB",
    "sg:tags":[
        "field",
        "oil"
    ],
    "wof:name":"Alberta Plug Systems",
    "wof:placetype":"venue"
},
  "geometry": {"coordinates":[-110.651588,50.015347],"type":"Point"}
}