{
  "type": "Feature",
  "properties": {
    "iso:country":"CA",
    "sg:address":"606 Boul Rene-Levesque O",
    "sg:city":"Quebec",
    "sg:classifiers":[
        {
            "category":"Health Services",
            "subcategory":"Health Practitioner",
            "type":"Services"
        }
    ],
    "sg:phone":"+1 418 955 2135",
    "sg:postcode":"G1S 1S8",
    "sg:province":"QC",
    "sg:tags":[
        "psychologist"
    ],
    "wof:name":"Harvey, Gilles",
    "wof:placetype":"venue"
},
  "geometry": {"coordinates":[-71.218346,46.80872],"type":"Point"}
}