{
  "type": "Feature",
  "properties": {
    "iso:country":"CA",
    "sg:address":"7182 Drummond Rd",
    "sg:city":"Niagara Falls",
    "sg:classifiers":[
        {
            "category":"Building & Trades",
            "subcategory":"Plumbing",
            "type":"Services"
        }
    ],
    "sg:phone":"+1 905 354 8156",
    "sg:postcode":"L2G 4P6",
    "sg:province":"ON",
    "sg:tags":[
        "conditioning",
        "air",
        "system",
        "contractor"
    ],
    "wof:name":"Joe Salvatore Electrical/Mecan",
    "wof:placetype":"venue"
},
  "geometry": {"coordinates":[-79.096824646,43.0718154907],"type":"Point"}
}