{
  "type": "Feature",
  "properties": {
    "iso:country":"CA",
    "sg:address":"1537 Michael St",
    "sg:city":"Ottawa",
    "sg:classifiers":[
        {
            "category":"Wholesale",
            "subcategory":"Construction Materials",
            "type":"Manufacturing & Wholesale Goods"
        }
    ],
    "sg:phone":"+1 613 747 4878",
    "sg:postcode":"K1B 3T3",
    "sg:province":"ON",
    "sg:tags":[
        "frame",
        "door"
    ],
    "wof:name":"Doorcorp Ottawa",
    "wof:placetype":"venue"
},
  "geometry": {"coordinates":[-75.6265411377,45.412147522],"type":"Point"}
}