{
  "type": "Feature",
  "properties": {
    "addr:full":"Montreal QC H2X 2H5",
    "addr:postcode":"h2x 2h5",
    "iso:country":"CA",
    "sg:city":"Montreal",
    "sg:classifiers":[
        {
            "category":"Organizations",
            "subcategory":"Labor Organization",
            "type":"Services"
        }
    ],
    "sg:phone":"+1 514 844 7233",
    "sg:postcode":"H2X 2H5",
    "sg:province":"QC",
    "wof:name":"Intl Alliance Theatrical Stage",
    "wof:placetype":"venue"
},
  "geometry": {"coordinates":[-73.571693,45.508396],"type":"Point"}
}