{
  "type": "Feature",
  "properties": {
    "addr:full":"51 4th St SE Hamiota MB R0M 0T0",
    "addr:housenumber":"51",
    "addr:postcode":"r0m 0t0",
    "addr:street":"4Th St Se",
    "iso:country":"CA",
    "sg:address":"51 4th St SE",
    "sg:city":"Hamiota",
    "sg:classifiers":[
        {
            "category":"Travel",
            "subcategory":"Hotels & Motels",
            "type":"Entertainment"
        }
    ],
    "sg:phone":"+1 204 764 2426",
    "sg:postcode":"R0M 0T0",
    "sg:province":"MB",
    "wof:name":"Hamiota Hotel",
    "wof:placetype":"venue"
},
  "geometry": {"coordinates":[-100.595116,50.181648],"type":"Point"}
}