{
  "type": "Feature",
  "properties": {
    "addr:full":"2994 Douglas St Victoria BC V8T 4N4",
    "addr:housenumber":"2994",
    "addr:postcode":"v8t 4n4",
    "addr:street":"Douglas St",
    "iso:country":"CA",
    "sg:address":"2994 Douglas St",
    "sg:city":"Victoria",
    "sg:classifiers":[
        {
            "category":"Organizations",
            "subcategory":"Labor Organization",
            "type":"Services"
        }
    ],
    "sg:phone":"+1 250 388 9948",
    "sg:postcode":"V8T 4N4",
    "sg:province":"BC",
    "wof:name":"B C Government Employees Union",
    "wof:placetype":"venue"
},
  "geometry": {"coordinates":[-123.370026,48.443481],"type":"Point"}
}