{
  "type": "Feature",
  "properties": {
    "addr:full":"335 George St Sydney NS B1P 1J7",
    "addr:housenumber":"335",
    "addr:postcode":"b1p 1j7",
    "addr:street":"George St",
    "iso:country":"CA",
    "sg:address":"335 George St",
    "sg:city":"Sydney",
    "sg:classifiers":[
        {
            "category":"Wholesale",
            "subcategory":"Office Equipment",
            "type":"Manufacturing & Wholesale Goods"
        }
    ],
    "sg:phone":"+1 902 539 2677",
    "sg:postcode":"B1P 1J7",
    "sg:province":"NS",
    "sg:tags":[
        "machine",
        "duplicating",
        "copying"
    ],
    "wof:name":"Ikon Office Solutions",
    "wof:placetype":"venue"
},
  "geometry": {"coordinates":[-60.192883,46.139832],"type":"Point"}
}