{
  "type": "Feature",
  "properties": {
    "iso:country":"CA",
    "sg:address":"2414 Division Rd",
    "sg:city":"Windsor",
    "sg:classifiers":[
        {
            "category":"Travel",
            "subcategory":"Hotels & Motels",
            "type":"Entertainment"
        }
    ],
    "sg:phone":"+1 519 969 9935",
    "sg:postcode":"N8W 4Z8",
    "sg:province":"ON",
    "wof:name":"Economy Inn",
    "wof:placetype":"venue"
},
  "geometry": {"coordinates":[-82.967827,42.263443],"type":"Point"}
}