{
  "type": "Feature",
  "properties": {
    "iso:country":"CA",
    "sg:address":"3949 Rue Wellington",
    "sg:city":"Verdun",
    "sg:classifiers":[
        {
            "category":"Shopping",
            "subcategory":"Jewelry",
            "type":"Retail Goods"
        }
    ],
    "sg:phone":"+1 514 767 1010",
    "sg:postcode":"H4G 1V6",
    "sg:province":"QC",
    "sg:tags":[
        "clothing"
    ],
    "wof:name":"Cute Kids",
    "wof:placetype":"venue"
},
  "geometry": {"coordinates":[-73.56708526609999,45.4642906189],"type":"Point"}
}