{
  "type": "Feature",
  "properties": {
    "addr:full":"Calgary AB T2C 2J9",
    "addr:postcode":"t2c 2j9",
    "iso:country":"CA",
    "sg:city":"Calgary",
    "sg:classifiers":[
        {
            "category":"Manufacturing",
            "subcategory":"Metals",
            "type":"Manufacturing & Wholesale Goods"
        }
    ],
    "sg:phone":"+1 403 236 9252",
    "sg:postcode":"T2C 2J9",
    "sg:province":"AB",
    "sg:tags":[
        "steel"
    ],
    "wof:name":"Metal Tech Fabricators Ltd",
    "wof:placetype":"venue"
},
  "geometry": {"coordinates":[-113.976745605,50.9958190918],"type":"Point"}
}