{
  "type": "Feature",
  "properties": {
    "addr:full":"537 Cleveland Cres SE Calgary AB T2G 4R8",
    "addr:housenumber":"537",
    "addr:postcode":"t2g 4r8",
    "addr:street":"Cleveland Cres Se",
    "iso:country":"CA",
    "sg:address":"537 Cleveland Cres SE",
    "sg:city":"Calgary",
    "sg:classifiers":[
        {
            "category":"Wholesale",
            "subcategory":"Machinery & Supplies",
            "type":"Manufacturing & Wholesale Goods"
        }
    ],
    "sg:phone":"+1 403 640 0135",
    "sg:postcode":"T2G 4R8",
    "sg:province":"AB",
    "sg:tags":[
        "equipment",
        "baker"
    ],
    "wof:name":"Bakery & Food Equipment CO",
    "wof:placetype":"venue"
},
  "geometry": {"coordinates":[-114.052909851,51.0163955688],"type":"Point"}
}