{
  "type": "Feature",
  "properties": {
    "addr:full":"44 St. Margaret's Bay Rd Halifax NS B3N 1J9",
    "addr:housenumber":"44",
    "addr:postcode":"b3n 1j9",
    "addr:street":"St. Margaret'S Bay Rd",
    "iso:country":"CA",
    "sg:address":"44 St. Margaret's Bay Rd",
    "sg:city":"Halifax",
    "sg:classifiers":[
        {
            "category":"Building & Trades",
            "subcategory":"Landscaping Services",
            "type":"Services"
        }
    ],
    "sg:phone":"+1 902 497 3339",
    "sg:postcode":"B3N 1J9",
    "sg:province":"NS",
    "sg:tags":[
        "landscape",
        "contractor"
    ],
    "wof:name":"Eddy Landscaping",
    "wof:placetype":"venue"
},
  "geometry": {"coordinates":[-62.286179,44.927834],"type":"Point"}
}