{
  "type": "Feature",
  "properties": {
    "addr:full":"Gander NL A1V 2S3",
    "addr:postcode":"a1v 2s3",
    "iso:country":"CA",
    "sg:city":"Gander",
    "sg:classifiers":[
        {
            "category":"Health Services",
            "subcategory":"Doctor",
            "type":"Services"
        }
    ],
    "sg:phone":"+1 709 256 7400",
    "sg:postcode":"A1V 2S3",
    "sg:province":"NL",
    "sg:tags":[
        "dentist"
    ],
    "wof:name":"Mast, Meino DDS",
    "wof:placetype":"venue"
},
  "geometry": {"coordinates":[-54.608635,48.956451],"type":"Point"}
}