{
  "type": "Feature",
  "properties": {
    "iso:country":"CA",
    "sg:address":"227 2nd Ave S",
    "sg:city":"Saskatoon",
    "sg:classifiers":[
        {
            "category":"Restaurant",
            "type":"Food & Drink"
        }
    ],
    "sg:phone":"+1 306 651 3888",
    "sg:postcode":"S7K 1K8",
    "sg:province":"SK",
    "wof:name":"Otowa Japanese Restaurant",
    "wof:placetype":"venue"
},
  "geometry": {"coordinates":[-106.66506957999999,52.1267433167],"type":"Point"}
}