{
  "type": "Feature",
  "properties": {
    "addr:full":"5604 41 Ave Wetaskiwin AB T9A 3M7",
    "addr:housenumber":"5604",
    "addr:postcode":"t9a 3m7",
    "addr:street":"41 Ave",
    "iso:country":"CA",
    "sg:address":"5604 41 Ave",
    "sg:city":"Wetaskiwin",
    "sg:classifiers":[
        {
            "category":"Autos & Motor Vehicles",
            "subcategory":"Automobile Sales",
            "type":"Retail Goods"
        }
    ],
    "sg:phone":"+1 780 352 6048",
    "sg:postcode":"T9A 3M7",
    "sg:province":"AB",
    "sg:tags":[
        "car",
        "dealer"
    ],
    "wof:name":"Brentridge Ford",
    "wof:placetype":"venue"
},
  "geometry": {"coordinates":[-113.388206,52.961872],"type":"Point"}
}