{
  "type": "Feature",
  "properties": {
    "addr:full":"Grand Bay-Westfield NB E5K 1R3",
    "addr:postcode":"e5k 1r3",
    "iso:country":"CA",
    "sg:city":"Grand Bay-Westfield",
    "sg:classifiers":[
        {
            "category":"Freight",
            "type":"Transportation"
        }
    ],
    "sg:phone":"+1 506 738 8085",
    "sg:postcode":"E5K 1R3",
    "sg:province":"NB",
    "sg:tags":[
        "equipment",
        "wine",
        "storage",
        "supply"
    ],
    "wof:name":"Wine & Stein Home Brewing Ctr",
    "wof:placetype":"venue"
},
  "geometry": {"coordinates":[-66.195396,45.307377],"type":"Point"}
}