{
  "type": "Feature",
  "properties": {
    "addr:full":"822 45th St E Saskatoon SK S7K 0W5",
    "addr:housenumber":"822",
    "addr:postcode":"s7k 0w5",
    "addr:street":"45Th St E",
    "iso:country":"CA",
    "sg:address":"822 45th St E",
    "sg:city":"Saskatoon",
    "sg:classifiers":[
        {
            "category":"Home & Garden",
            "subcategory":"Building Materials",
            "type":"Retail Goods"
        }
    ],
    "sg:phone":"+1 306 242 9600",
    "sg:postcode":"S7K 0W5",
    "sg:province":"SK",
    "sg:tags":[
        "windows"
    ],
    "wof:name":"All Weather Windows",
    "wof:placetype":"venue"
},
  "geometry": {"coordinates":[-106.651932,52.162621],"type":"Point"}
}