{
  "type": "Feature",
  "properties": {
    "addr:full":"825 Manitoba Ave Selkirk MB R1A 2B5",
    "addr:housenumber":"825",
    "addr:postcode":"r1a 2b5",
    "addr:street":"Manitoba Ave",
    "iso:country":"CA",
    "sg:address":"825 Manitoba Ave",
    "sg:city":"Selkirk",
    "sg:classifiers":[
        {
            "category":"Government",
            "subcategory":"Office",
            "type":"Public Place"
        }
    ],
    "sg:phone":"+1 204 482 3810",
    "sg:postcode":"R1A 2B5",
    "sg:province":"MB",
    "wof:name":"Manitoba Property Management",
    "wof:placetype":"venue"
},
  "geometry": {"coordinates":[-96.8881072998,50.1519317627],"type":"Point"}
}