{
  "type": "Feature",
  "properties": {
    "addr:full":"3816 45 St SW Calgary AB T3E 3V6",
    "addr:housenumber":"3816",
    "addr:postcode":"t3e 3v6",
    "addr:street":"45 St Sw",
    "iso:country":"CA",
    "sg:address":"3816 45 St SW",
    "sg:city":"Calgary",
    "sg:classifiers":[
        {
            "category":"Shopping",
            "subcategory":"Computers & Home Electronics",
            "type":"Retail Goods"
        }
    ],
    "sg:phone":"+1 403 217 4515",
    "sg:postcode":"T3E 3V6",
    "sg:province":"AB",
    "sg:tags":[
        "software"
    ],
    "wof:name":"Wysertech Canada Corp",
    "wof:placetype":"venue"
},
  "geometry": {"coordinates":[-114.152275,51.020409],"type":"Point"}
}