{
  "type": "Feature",
  "properties": {
    "addr:full":"112 35E Av Edmundston NB E3V 2V3",
    "addr:housenumber":"112",
    "addr:postcode":"e3v 2v3",
    "addr:street":"35E Av",
    "iso:country":"CA",
    "sg:address":"112 35E Av",
    "sg:city":"Edmundston",
    "sg:classifiers":[
        {
            "category":"Social Services",
            "type":"Services"
        }
    ],
    "sg:phone":"+1 506 739 5950",
    "sg:postcode":"E3V 2V3",
    "sg:province":"NB",
    "sg:tags":[
        "counselor",
        "marriage",
        "family"
    ],
    "wof:name":"Mercure, Rachel",
    "wof:placetype":"venue"
},
  "geometry": {"coordinates":[-68.3204040527,47.3739242554],"type":"Point"}
}