{
  "type": "Feature",
  "properties": {
    "iso:country":"CA",
    "sg:city":"Eatonia",
    "sg:classifiers":[
        {
            "category":"Government",
            "subcategory":"Office",
            "type":"Public Place"
        }
    ],
    "sg:phone":"+1 306 967 7311",
    "sg:postcode":"S0L 0Y0",
    "sg:province":"SK",
    "wof:name":"Eatonia Bayhurst Compressor",
    "wof:placetype":"venue"
},
  "geometry": {"coordinates":[-109.389266968,51.2211494446],"type":"Point"}
}