{
  "type": "Feature",
  "properties": {
    "iso:country":"CA",
    "sg:address":"175 York St",
    "sg:city":"Napanee",
    "sg:classifiers":[
        {
            "category":"Bars & Pubs",
            "type":"Food & Drink"
        }
    ],
    "sg:phone":"+1 613 354 3761",
    "sg:postcode":"K7R 2Y8",
    "sg:province":"ON",
    "sg:tags":[
        "club"
    ],
    "wof:name":"Napanee Curling Club",
    "wof:placetype":"venue"
},
  "geometry": {"coordinates":[-76.9623184204,44.2441558838],"type":"Point"}
}