{
  "type": "Feature",
  "properties": {
    "addr:full":"4924 Telqua Dr 108 Mile Ranch BC V0K 2Z0",
    "addr:housenumber":"4924;108",
    "addr:postcode":"v0k 2z0",
    "addr:street":"Telqua Dr;Mile Ranch",
    "iso:country":"CA",
    "sg:address":"4924 Telqua Dr",
    "sg:city":"108 Mile Ranch",
    "sg:classifiers":[
        {
            "category":"Organizations",
            "subcategory":"Professional Association",
            "type":"Services"
        }
    ],
    "sg:phone":"+1 250 791 5599",
    "sg:postcode":"V0K 2Z0",
    "sg:province":"BC",
    "sg:tags":[
        "club"
    ],
    "wof:name":"108 Community Centre",
    "wof:placetype":"venue"
},
  "geometry": {"coordinates":[-121.34844207800001,51.7511444092],"type":"Point"}
}