{
  "type": "Feature",
  "properties": {
    "iso:country":"CA",
    "sg:address":"1150 Gladwin Dr",
    "sg:city":"North Vancouver",
    "sg:classifiers":[
        {
            "category":"Organizations",
            "subcategory":"Professional Association",
            "type":"Services"
        }
    ],
    "sg:phone":"+1 604 988 1934",
    "sg:postcode":"V7R 1A2",
    "sg:province":"BC",
    "wof:name":"Ismaili Jematkanas",
    "wof:placetype":"venue"
},
  "geometry": {"coordinates":[-123.106194,49.332901],"type":"Point"}
}