{
  "type": "Feature",
  "properties": {
    "iso:country":"CA",
    "sg:address":"34 Barnard St",
    "sg:city":"Yarmouth",
    "sg:classifiers":[
        {
            "category":"Social Services",
            "subcategory":"Child Care",
            "type":"Services"
        }
    ],
    "sg:phone":"+1 902 749 1718",
    "sg:postcode":"B5A 3T5",
    "sg:province":"NS",
    "sg:tags":[
        "charitable",
        "institution"
    ],
    "wof:name":"Parents Place",
    "wof:placetype":"venue"
},
  "geometry": {"coordinates":[-66.12060546879999,43.8287086487],"type":"Point"}
}