{
  "type": "Feature",
  "properties": {
    "addr:full":"523 Hwy 7 Oakwood ON K0M 2M0",
    "addr:housenumber":"523",
    "addr:postcode":"k0m 2m0",
    "addr:street":"Hwy 7",
    "iso:country":"CA",
    "sg:address":"523 Hwy 7",
    "sg:city":"Oakwood",
    "sg:classifiers":[
        {
            "category":"Building & Trades",
            "subcategory":"Plumbing",
            "type":"Services"
        }
    ],
    "sg:phone":"+1 705 953 9919",
    "sg:postcode":"K0M 2M0",
    "sg:province":"ON",
    "sg:tags":[
        "conditioning",
        "air",
        "system",
        "refrigerating",
        "contractor"
    ],
    "wof:name":"DE Groot Refrigeration",
    "wof:placetype":"venue"
},
  "geometry": {"coordinates":[-78.9268035889,44.3227119446],"type":"Point"}
}