{
  "type": "Feature",
  "properties": {
    "iso:country":"CA",
    "sg:address":"956 Rue Principale",
    "sg:city":"Beresford",
    "sg:classifiers":[
        {
            "category":"Restaurant",
            "type":"Food & Drink"
        }
    ],
    "sg:phone":"+1 506 546 3600",
    "sg:postcode":"E8K 2H6",
    "sg:province":"NB",
    "wof:name":"Lucky Dragon Dining Room",
    "wof:placetype":"venue"
},
  "geometry": {"coordinates":[-65.70124053959999,47.692440033],"type":"Point"}
}