{
  "type": "Feature",
  "properties": {
    "addr:full":"271 Water St Botwood NL A0H 1E0",
    "addr:housenumber":"271",
    "addr:postcode":"a0h 1e0",
    "addr:street":"Water St",
    "iso:country":"CA",
    "sg:address":"271 Water St",
    "sg:city":"Botwood",
    "sg:classifiers":[
        {
            "category":"Retail",
            "subcategory":"Funeral Services",
            "type":"Services"
        }
    ],
    "sg:phone":"+1 709 257 4899",
    "sg:postcode":"A0H 1E0",
    "sg:province":"NL",
    "sg:tags":[
        "director"
    ],
    "wof:name":"Hoskins Funeral Homes Ltd",
    "wof:placetype":"venue"
},
  "geometry": {"coordinates":[-55.359222,49.129429],"type":"Point"}
}