{
  "type": "Feature",
  "properties": {
    "addr:full":"4278 Holt Rd Hampton ON L0B 1J0",
    "addr:housenumber":"4278",
    "addr:postcode":"l0b 1j0",
    "addr:street":"Holt Rd",
    "iso:country":"CA",
    "sg:address":"4278 Holt Rd",
    "sg:city":"Hampton",
    "sg:classifiers":[
        {
            "category":"Building & Trades",
            "subcategory":"Construction",
            "type":"Services"
        }
    ],
    "sg:phone":"+1 905 263 8512",
    "sg:postcode":"L0B 1J0",
    "sg:province":"ON",
    "sg:tags":[
        "insulation",
        "heat",
        "contractor"
    ],
    "wof:name":"Whitby Insulation",
    "wof:placetype":"venue"
},
  "geometry": {"coordinates":[-78.75672900000001,43.96109],"type":"Point"}
}