{
  "type": "Feature",
  "properties": {
    "iso:country":"CA",
    "sg:address":"1946 Boul Le Corbusier",
    "sg:city":"Laval",
    "sg:classifiers":[
        {
            "category":"Home & Garden",
            "subcategory":"Furniture",
            "type":"Retail Goods"
        }
    ],
    "sg:phone":"+1 450 682 3022",
    "sg:postcode":"H7S 2K1",
    "sg:province":"QC",
    "wof:name":"Maison Corbeil Meubles Inc",
    "wof:placetype":"venue"
},
  "geometry": {"coordinates":[-73.7380447388,45.5694656372],"type":"Point"}
}