{
  "type": "Feature",
  "properties": {
    "addr:full":"77 Bloor St W #1406 Toronto ON M5S 1M2",
    "addr:housenumber":"77",
    "addr:postcode":"m5s 1m2",
    "addr:street":"Bloor St W # 1406",
    "iso:country":"CA",
    "sg:address":"77 Bloor St W #1406",
    "sg:city":"Toronto",
    "sg:classifiers":[
        {
            "category":"Airline",
            "type":"Transportation"
        }
    ],
    "sg:phone":"+1 416 966 4853",
    "sg:postcode":"M5S 1M2",
    "sg:province":"ON",
    "sg:tags":[
        "company"
    ],
    "wof:name":"Gulf Air",
    "wof:placetype":"venue"
},
  "geometry": {"coordinates":[-79.3898468018,43.6694412231],"type":"Point"}
}