{
  "type": "Feature",
  "properties": {
    "iso:country":"CA",
    "sg:address":"105 Maple St",
    "sg:city":"St Catharines",
    "sg:classifiers":[
        {
            "category":"Organizations",
            "subcategory":"Religious Organization",
            "type":"Services"
        }
    ],
    "sg:phone":"+1 905 641 5050",
    "sg:postcode":"L2R 2B4",
    "sg:province":"ON",
    "sg:tags":[
        "church"
    ],
    "wof:name":"Memorial United Church",
    "wof:placetype":"venue"
},
  "geometry": {"coordinates":[-79.23728179930001,43.1678009033],"type":"Point"}
}