{
  "type": "Feature",
  "properties": {
    "addr:full":"Scarborough ON M1W 3K6",
    "addr:postcode":"m1w 3k6",
    "iso:country":"CA",
    "sg:city":"Scarborough",
    "sg:classifiers":[
        {
            "category":"Wholesale",
            "subcategory":"Electrical",
            "type":"Manufacturing & Wholesale Goods"
        }
    ],
    "sg:phone":"+1 416 494 8999",
    "sg:postcode":"M1W 3K6",
    "sg:province":"ON",
    "sg:tags":[
        "equipment",
        "electronic",
        "supply"
    ],
    "wof:name":"Sayal Electronics",
    "wof:placetype":"venue"
},
  "geometry": {"coordinates":[-79.3386306763,43.8097877502],"type":"Point"}
}