{
  "type": "Feature",
  "properties": {
    "addr:full":"12960 112 St NW Edmonton AB T5E 6J1",
    "addr:housenumber":"12960",
    "addr:postcode":"t5e 6j1",
    "addr:street":"112 St Nw",
    "iso:country":"CA",
    "sg:address":"12960 112 St NW",
    "sg:city":"Edmonton",
    "sg:classifiers":[
        {
            "category":"Organizations",
            "subcategory":"Religious Organization",
            "type":"Services"
        }
    ],
    "sg:phone":"+1 780 452 1198",
    "sg:postcode":"T5E 6J1",
    "sg:province":"AB",
    "sg:tags":[
        "church"
    ],
    "wof:name":"St Emerick Roman Catholic Chr",
    "wof:placetype":"venue"
},
  "geometry": {"coordinates":[-113.51380899999999,53.588661],"type":"Point"}
}