{
  "type": "Feature",
  "properties": {
    "addr:full":"69 Main St W Huntsville ON P1H 1W9",
    "addr:housenumber":"69",
    "addr:postcode":"p1h 1w9",
    "addr:street":"Main St W",
    "iso:country":"CA",
    "sg:address":"69 Main St W",
    "sg:city":"Huntsville",
    "sg:classifiers":[
        {
            "category":"Travel",
            "subcategory":"Hotels & Motels",
            "type":"Entertainment"
        }
    ],
    "sg:phone":"+1 705 789 4414",
    "sg:postcode":"P1H 1W9",
    "sg:province":"ON",
    "wof:name":"Sunset Inn Motel",
    "wof:placetype":"venue"
},
  "geometry": {"coordinates":[-79.225578,45.323307],"type":"Point"}
}