{
  "type": "Feature",
  "properties": {
    "addr:full":"Mississauga ON L5G 1C9",
    "addr:postcode":"l5g 1c9",
    "iso:country":"CA",
    "sg:city":"Mississauga",
    "sg:classifiers":[
        {
            "category":"Professional",
            "subcategory":"Lawyer & Legal Services",
            "type":"Services"
        }
    ],
    "sg:phone":"+1 905 891 5750",
    "sg:postcode":"L5G 1C9",
    "sg:province":"ON",
    "sg:tags":[
        "attorney"
    ],
    "wof:name":"Loucks, Douglas G",
    "wof:placetype":"venue"
},
  "geometry": {"coordinates":[-79.58485400000001,43.552246],"type":"Point"}
}