{
  "type": "Feature",
  "properties": {
    "iso:country":"CA",
    "sg:address":"59 Church St",
    "sg:city":"St Catharines",
    "sg:classifiers":[
        {
            "category":"Professional",
            "subcategory":"Lawyer & Legal Services",
            "type":"Services"
        }
    ],
    "sg:phone":"+1 905 685 9094",
    "sg:postcode":"L2R 3C3",
    "sg:province":"ON",
    "sg:tags":[
        "attorney"
    ],
    "wof:name":"Lincoln County Law Assn Lbrary",
    "wof:placetype":"venue"
},
  "geometry": {"coordinates":[-79.24718475340001,43.1599082947],"type":"Point"}
}