{
  "type": "Feature",
  "properties": {
    "addr:full":"6 Main St W # 1 Huntsville ON P1H 2E1",
    "addr:housenumber":"6",
    "addr:postcode":"p1h 2e1",
    "addr:street":"Main St W # 1",
    "iso:country":"CA",
    "sg:address":"6 Main St W # 1",
    "sg:city":"Huntsville",
    "sg:classifiers":[
        {
            "category":"Professional",
            "subcategory":"Lawyer & Legal Services",
            "type":"Services"
        }
    ],
    "sg:phone":"+1 705 789 8844",
    "sg:postcode":"P1H 2E1",
    "sg:province":"ON",
    "sg:tags":[
        "attorney"
    ],
    "wof:name":"Thoms & Currie",
    "wof:placetype":"venue"
},
  "geometry": {"coordinates":[-79.22075700000001,45.326183],"type":"Point"}
}