{
  "type": "Feature",
  "properties": {
    "addr:full":"9917 100 Ave Grande Prairie AB T8V 0V1",
    "addr:housenumber":"9917",
    "addr:postcode":"t8v 0v1",
    "addr:street":"100 Ave",
    "iso:country":"CA",
    "sg:address":"9917 100 Ave",
    "sg:city":"Grande Prairie",
    "sg:classifiers":[
        {
            "category":"Home & Garden",
            "subcategory":"Furniture",
            "type":"Retail Goods"
        }
    ],
    "sg:phone":"+1 780 532 5115",
    "sg:postcode":"T8V 0V1",
    "sg:province":"AB",
    "wof:name":"Englander Home Interiors",
    "wof:placetype":"venue"
},
  "geometry": {"coordinates":[-118.79239699999999,55.170605],"type":"Point"}
}