{
  "type": "Feature",
  "properties": {
    "addr:full":"2088 United Blvd Coquitlam BC V3K 6W3",
    "addr:housenumber":"2088",
    "addr:postcode":"v3k 6w3",
    "addr:street":"United Blvd",
    "iso:country":"CA",
    "sg:address":"2088 United Blvd",
    "sg:city":"Coquitlam",
    "sg:classifiers":[
        {
            "category":"Restaurant",
            "type":"Food & Drink"
        }
    ],
    "sg:phone":"+1 604 523 1300",
    "sg:postcode":"V3K 6W3",
    "sg:province":"BC",
    "wof:name":"Weinlager & Amichi Cafe",
    "wof:placetype":"venue"
},
  "geometry": {"coordinates":[-122.836303711,49.2286567688],"type":"Point"}
}