{
  "type": "Feature",
  "properties": {
    "addr:full":"258 Trenton Rd New Glasgow NS B2H 2S9",
    "addr:housenumber":"258",
    "addr:postcode":"b2h 2s9",
    "addr:street":"Trenton Rd",
    "iso:country":"CA",
    "sg:address":"258 Trenton Rd",
    "sg:city":"New Glasgow",
    "sg:classifiers":[
        {
            "category":"Retail",
            "subcategory":"Repair Shop",
            "type":"Services"
        }
    ],
    "sg:phone":"+1 902 752 4255",
    "sg:postcode":"B2H 2S9",
    "sg:province":"NS",
    "sg:tags":[
        "upholsterer"
    ],
    "wof:name":"Mattress Shop Ltd",
    "wof:placetype":"venue"
},
  "geometry": {"coordinates":[-62.6400375366,45.5966796875],"type":"Point"}
}