{
  "type": "Feature",
  "properties": {
    "addr:full":"580 Court House Rd Cobourg ON K9A 5J6",
    "addr:housenumber":"580",
    "addr:postcode":"k9a 5j6",
    "addr:street":"Court House Rd",
    "iso:country":"CA",
    "sg:address":"580 Court House Rd",
    "sg:city":"Cobourg",
    "sg:classifiers":[
        {
            "category":"Real Estate",
            "subcategory":"Real Estate Operator",
            "type":"Services"
        }
    ],
    "sg:phone":"+1 905 373 1366",
    "sg:postcode":"K9A 5J6",
    "sg:province":"ON",
    "sg:tags":[
        "apartment"
    ],
    "wof:name":"Halcyon Place",
    "wof:placetype":"venue"
},
  "geometry": {"coordinates":[-78.19564800000001,43.973289],"type":"Point"}
}