{
  "type": "Feature",
  "properties": {
    "addr:full":"245 Av Kensington Westmount QC H3Z 2G9",
    "addr:housenumber":"245",
    "addr:postcode":"h3z 2g9",
    "addr:street":"Av Kensington",
    "iso:country":"CA",
    "sg:address":"245 Av Kensington",
    "sg:city":"Westmount",
    "sg:classifiers":[
        {
            "category":"Wholesale",
            "subcategory":"Apparel",
            "type":"Manufacturing & Wholesale Goods"
        }
    ],
    "sg:phone":"+1 514 933 9633",
    "sg:postcode":"H3Z 2G9",
    "sg:province":"QC",
    "sg:tags":[
        "textile"
    ],
    "wof:name":"Albatex Le Groupe",
    "wof:placetype":"venue"
},
  "geometry": {"coordinates":[-73.592422,45.483047],"type":"Point"}
}