{
  "type": "Feature",
  "properties": {
    "iso:country":"CA",
    "sg:address":"282 Graham St",
    "sg:city":"Meaford",
    "sg:classifiers":[
        {
            "category":"Shopping",
            "type":"Retail Goods"
        }
    ],
    "sg:phone":"+1 519 538 4000",
    "sg:postcode":"N4L 1B3",
    "sg:province":"ON",
    "sg:tags":[
        "equipment",
        "telephone",
        "supply"
    ],
    "wof:name":"Georgian Bay Telephone Systems",
    "wof:placetype":"venue"
},
  "geometry": {"coordinates":[-80.5773696899,44.5988197327],"type":"Point"}
}