{
  "type": "Feature",
  "properties": {
    "addr:full":"1500 Rue DE L'Eclair Val-Belair QC G3K 1P7",
    "addr:housenumber":"1500",
    "addr:postcode":"g3k 1p7",
    "addr:street":"Rue De L'Eclair Val-Belair",
    "iso:country":"CA",
    "sg:address":"1500 Rue DE L'Eclair",
    "sg:city":"Val-Belair",
    "sg:classifiers":[
        {
            "category":"Shopping",
            "subcategory":"Computers & Home Electronics",
            "type":"Retail Goods"
        }
    ],
    "sg:phone":"+1 418 847 1999",
    "sg:postcode":"G3K 1P7",
    "sg:province":"QC",
    "sg:tags":[
        "parts",
        "supply"
    ],
    "wof:name":"Info-Pro Pla",
    "wof:placetype":"venue"
},
  "geometry": {"coordinates":[-71.415657,46.853455],"type":"Point"}
}