{
  "type": "Feature",
  "properties": {
    "addr:full":"450 Westmorland Rd Saint John NB E2J 4Z2",
    "addr:housenumber":"450",
    "addr:postcode":"e2j 4z2",
    "addr:street":"Westmorland Rd",
    "iso:country":"CA",
    "sg:address":"450 Westmorland Rd",
    "sg:city":"Saint John",
    "sg:classifiers":[
        {
            "category":"Shopping",
            "subcategory":"Shoes",
            "type":"Retail Goods"
        }
    ],
    "sg:phone":"+1 506 652 7935",
    "sg:postcode":"E2J 4Z2",
    "sg:province":"NB",
    "wof:name":"Payless Shoe Source",
    "wof:placetype":"venue"
},
  "geometry": {"coordinates":[-66.018379,45.307564],"type":"Point"}
}