{
  "type": "Feature",
  "properties": {
    "addr:full":"North York ON M9L 1N2",
    "addr:postcode":"m9l 1n2",
    "iso:country":"CA",
    "sg:city":"North York",
    "sg:classifiers":[
        {
            "category":"Building & Trades",
            "subcategory":"Electrical",
            "type":"Services"
        }
    ],
    "sg:phone":"+1 416 749 3050",
    "sg:postcode":"M9L 1N2",
    "sg:province":"ON",
    "sg:tags":[
        "electric",
        "contractor"
    ],
    "wof:name":"Commerce Electric CO Inc",
    "wof:placetype":"venue"
},
  "geometry": {"coordinates":[-79.54583,43.761562],"type":"Point"}
}