{
  "type": "Feature",
  "properties": {
    "addr:full":"501 Arlington Ave York ON M6C 3A4",
    "addr:housenumber":"501",
    "addr:postcode":"m6c 3a4",
    "addr:street":"Arlington Ave",
    "iso:country":"CA",
    "sg:address":"501 Arlington Ave",
    "sg:city":"York",
    "sg:classifiers":[
        {
            "category":"Education",
            "subcategory":"School",
            "type":"Public Place"
        }
    ],
    "sg:phone":"+1 416 394 2200",
    "sg:postcode":"M6C 3A4",
    "sg:province":"ON",
    "wof:name":"Arlington Middle School",
    "wof:placetype":"venue"
},
  "geometry": {"coordinates":[-79.4332046509,43.6920661926],"type":"Point"}
}