{
  "type": "Feature",
  "properties": {
    "addr:full":"Terrace BC V8G 1R3",
    "addr:postcode":"v8g 1r3",
    "iso:country":"CA",
    "sg:city":"Terrace",
    "sg:classifiers":[
        {
            "category":"Food & Beverages",
            "subcategory":"Groceries & Convenience Stores",
            "type":"Retail Goods"
        }
    ],
    "sg:phone":"+1 250 635 7261",
    "sg:postcode":"V8G 1R3",
    "sg:province":"BC",
    "sg:tags":[
        "pharmacy"
    ],
    "wof:name":"Shoppers Drug Mart",
    "wof:placetype":"venue"
},
  "geometry": {"coordinates":[-128.58981323200001,54.5165786743],"type":"Point"}
}