{
  "type": "Feature",
  "properties": {
    "addr:full":"13072 Sherbrooke Ave NW Edmonton AB T5L 4E9",
    "addr:housenumber":"13072",
    "addr:postcode":"t5l 4e9",
    "addr:street":"Sherbrooke Ave Nw",
    "iso:country":"CA",
    "sg:address":"13072 Sherbrooke Ave NW",
    "sg:city":"Edmonton",
    "sg:classifiers":[
        {
            "category":"Organizations",
            "subcategory":"Religious Organization",
            "type":"Services"
        }
    ],
    "sg:phone":"+1 780 455 1333",
    "sg:postcode":"T5L 4E9",
    "sg:province":"AB",
    "sg:tags":[
        "church"
    ],
    "wof:name":"St Pius X Roman Catholic Chr",
    "wof:placetype":"venue"
},
  "geometry": {"coordinates":[-113.55014,53.578384],"type":"Point"}
}