{
  "type": "Feature",
  "properties": {
    "addr:full":"5A Rte Principale O Sainte-Cecile-DE-Masham QC J0X 2W0",
    "addr:housenumber":"5a",
    "addr:postcode":"j0x 2w0",
    "addr:street":"Rte Principale O Sainte-Cecile-De-Masham",
    "iso:country":"CA",
    "sg:address":"5A Rte Principale O",
    "sg:city":"Sainte-Cecile-DE-Masham",
    "sg:classifiers":[
        {
            "category":"Education",
            "subcategory":"School",
            "type":"Public Place"
        }
    ],
    "sg:phone":"+1 819 456 2274",
    "sg:postcode":"J0X 2W0",
    "sg:province":"QC",
    "wof:name":"Centre LA Peche-Ed Aux Adultes",
    "wof:placetype":"venue"
},
  "geometry": {"coordinates":[-76.03668999999999,45.642174],"type":"Point"}
}