{
  "type": "Feature",
  "properties": {
    "addr:full":"40 Mill St Hillsborough NB E4H 2Z8",
    "addr:housenumber":"40",
    "addr:postcode":"e4h 2z8",
    "addr:street":"Mill St",
    "iso:country":"CA",
    "sg:address":"40 Mill St",
    "sg:city":"Hillsborough",
    "sg:classifiers":[
        {
            "category":"Museum",
            "type":"Entertainment"
        }
    ],
    "sg:phone":"+1 506 734 3102",
    "sg:postcode":"E4H 2Z8",
    "sg:province":"NB",
    "wof:name":"Steeves William Henry House",
    "wof:placetype":"venue"
},
  "geometry": {"coordinates":[-64.64571380620001,45.9250602722],"type":"Point"}
}