{
  "type": "Feature",
  "properties": {
    "addr:full":"3321 Dufferin St North York ON M6A 2T8",
    "addr:housenumber":"3321",
    "addr:postcode":"m6a 2t8",
    "addr:street":"Dufferin St",
    "iso:country":"CA",
    "sg:address":"3321 Dufferin St",
    "sg:city":"North York",
    "sg:classifiers":[
        {
            "category":"Autos & Motor Vehicles",
            "subcategory":"Fuel & Gas Station",
            "type":"Retail Goods"
        }
    ],
    "sg:phone":"+1 416 782 7523",
    "sg:postcode":"M6A 2T8",
    "sg:province":"ON",
    "sg:tags":[
        "oil"
    ],
    "wof:name":"M's Esso",
    "wof:placetype":"venue"
},
  "geometry": {"coordinates":[-79.456535,43.722641],"type":"Point"}
}