{
  "type": "Feature",
  "properties": {
    "addr:full":"439 King West 3rd Floor Toronto M5V1K4",
    "addr:housenumber":"439;3rd",
    "addr:postcode":"m5v1k4",
    "addr:street":"King West;Floor",
    "iso:country":"CA",
    "sg:address":"439 King West 3rd Floor",
    "sg:city":"Toronto",
    "sg:classifiers":[
        {
            "category":"Professional",
            "subcategory":"Computer Services",
            "type":"Services"
        }
    ],
    "sg:postcode":"M5V1K4",
    "sg:tags":[
        "social-networking",
        "social-consciousness",
        "social-change",
        "pay-it-forward"
    ],
    "sg:website":"http://www.dailychallenge.org",
    "wof:name":"Daily Challenge",
    "wof:placetype":"venue"
},
  "geometry": {"coordinates":[-79.3956689,43.6453258],"type":"Point"}
}