{
  "type": "Feature",
  "properties": {
    "iso:country":"CA",
    "sg:city":"Richmond",
    "sg:classifiers":[
        {
            "category":"Retail",
            "subcategory":"Laundry & Dry Cleaning",
            "type":"Services"
        }
    ],
    "sg:phone":"+1 604 275 1716",
    "sg:postcode":"V7E 2C9",
    "sg:province":"BC",
    "sg:tags":[
        "cleaners"
    ],
    "wof:name":"Canterbury Cleaners Ltd",
    "wof:placetype":"venue"
},
  "geometry": {"coordinates":[-123.15911102299999,49.1443367004],"type":"Point"}
}