{
  "type": "Feature",
  "properties": {
    "iso:country":"CA",
    "sg:city":"Grande Prairie",
    "sg:classifiers":[
        {
            "category":"Professional",
            "subcategory":"Lawyer & Legal Services",
            "type":"Services"
        }
    ],
    "sg:phone":"+1 780 539 6800",
    "sg:postcode":"T8V 7K2",
    "sg:province":"AB",
    "sg:tags":[
        "attorney"
    ],
    "wof:name":"Lewis & Chrenek",
    "wof:placetype":"venue"
},
  "geometry": {"coordinates":[-118.786407471,55.1694297791],"type":"Point"}
}