{
  "type": "Feature",
  "properties": {
    "addr:full":"215 Rue Bourque Saint-Marc-Des-Carrieres QC G0A 4B0",
    "addr:housenumber":"215",
    "addr:postcode":"g0a 4b0",
    "addr:street":"Rue Bourque Saint-Marc-Des-Carrieres",
    "iso:country":"CA",
    "sg:address":"215 Rue Bourque",
    "sg:city":"Saint-Marc-Des-Carrieres",
    "sg:classifiers":[
        {
            "category":"Personal",
            "subcategory":"Beauty Salon",
            "type":"Services"
        }
    ],
    "sg:phone":"+1 418 268 3004",
    "sg:postcode":"G0A 4B0",
    "sg:province":"QC",
    "wof:name":"Coiffure Suzanne Delisle",
    "wof:placetype":"venue"
},
  "geometry": {"coordinates":[-72.0624847412,46.6836395264],"type":"Point"}
}