{
  "type": "Feature",
  "properties": {
    "iso:country":"CA",
    "sg:address":"3979 Tecumseh Rd E",
    "sg:city":"Windsor",
    "sg:classifiers":[
        {
            "category":"Shopping",
            "subcategory":"Computers & Home Electronics",
            "type":"Retail Goods"
        }
    ],
    "sg:phone":"+1 519 974 0163",
    "sg:postcode":"N8W 1J5",
    "sg:province":"ON",
    "sg:tags":[
        "equipment",
        "dealer"
    ],
    "wof:name":"Axxon of Canada",
    "wof:placetype":"venue"
},
  "geometry": {"coordinates":[-82.975594,42.305855],"type":"Point"}
}