{
  "type": "Feature",
  "properties": {
    "addr:full":"660 Boul DE Quen N Alma QC G8B 6H5",
    "addr:housenumber":"660",
    "addr:postcode":"g8b 6h5",
    "addr:street":"Boul De Quen N",
    "iso:country":"CA",
    "sg:address":"660 Boul DE Quen N",
    "sg:city":"Alma",
    "sg:classifiers":[
        {
            "category":"Bars & Pubs",
            "type":"Food & Drink"
        }
    ],
    "sg:phone":"+1 418 662 4043",
    "sg:postcode":"G8B 6H5",
    "sg:province":"QC",
    "sg:tags":[
        "lounge",
        "cocktail"
    ],
    "wof:name":"Bar Imperial Enr",
    "wof:placetype":"venue"
},
  "geometry": {"coordinates":[-71.64411200000001,48.561371],"type":"Point"}
}