{
  "type": "Feature",
  "properties": {
    "iso:country":"CA",
    "sg:address":"807 Henderson Hwy",
    "sg:city":"Winnipeg",
    "sg:classifiers":[
        {
            "category":"Health Services",
            "subcategory":"Doctor",
            "type":"Services"
        }
    ],
    "sg:phone":"+1 204 661 2614",
    "sg:postcode":"R2K 2K9",
    "sg:province":"MB",
    "sg:tags":[
        "dentist"
    ],
    "wof:name":"East Kidonan Kelvin Dental Grp",
    "wof:placetype":"venue"
},
  "geometry": {"coordinates":[-97.10177612299999,49.9295959473],"type":"Point"}
}