{
  "type": "Feature",
  "properties": {
    "addr:full":"1435 Rue Provinciale Quebec QC G1N 4A4",
    "addr:housenumber":"1435",
    "addr:postcode":"g1n 4a4",
    "addr:street":"Rue Provinciale Quebec",
    "iso:country":"CA",
    "sg:address":"1435 Rue Provinciale",
    "sg:city":"Quebec",
    "sg:classifiers":[
        {
            "category":"Wholesale",
            "subcategory":"Groceries",
            "type":"Manufacturing & Wholesale Goods"
        }
    ],
    "sg:phone":"+1 418 688 7042",
    "sg:postcode":"G1N 4A4",
    "sg:province":"QC",
    "sg:tags":[
        "frozen",
        "dessert",
        "ice",
        "cream"
    ],
    "wof:name":"Entreprises Rf Fournier Inc",
    "wof:placetype":"venue"
},
  "geometry": {"coordinates":[-71.2665634155,46.8019104004],"type":"Point"}
}