{
  "type": "Feature",
  "properties": {
    "iso:country":"CA",
    "sg:address":"RR 1 STN Main",
    "sg:city":"St Marys",
    "sg:classifiers":[
        {
            "category":"Sports & Exercise",
            "subcategory":"Golf",
            "type":"Entertainment"
        }
    ],
    "sg:phone":"+1 519 284 3621",
    "sg:postcode":"N4X 1C4",
    "sg:province":"ON",
    "sg:tags":[
        "course"
    ],
    "wof:name":"Science Hill Country Club",
    "wof:placetype":"venue"
},
  "geometry": {"coordinates":[-81.1414260864,43.2594947815],"type":"Point"}
}