{
  "type": "Feature",
  "properties": {
    "addr:full":"204 Rue Du Coteau Chateau-Richer QC G0A 1N0",
    "addr:housenumber":"204",
    "addr:postcode":"g0a 1n0",
    "addr:street":"Rue Du Coteau Chateau-Richer",
    "iso:country":"CA",
    "sg:address":"204 Rue Du Coteau",
    "sg:city":"Chateau-Richer",
    "sg:classifiers":[
        {
            "category":"Mining & Drilling",
            "type":"Manufacturing & Wholesale Goods"
        }
    ],
    "sg:phone":"+1 418 824 4884",
    "sg:postcode":"G0A 1N0",
    "sg:province":"QC",
    "sg:tags":[
        "stone",
        "quarry"
    ],
    "wof:name":"Carriere Laplante Enr",
    "wof:placetype":"venue"
},
  "geometry": {"coordinates":[-71.0252838135,46.9682159424],"type":"Point"}
}