{
  "type": "Feature",
  "properties": {
    "addr:full":"607 Saint Clair St Point Edward ON N7V 1P2",
    "addr:housenumber":"607",
    "addr:postcode":"n7v 1p2",
    "addr:street":"Saint Clair St",
    "iso:country":"CA",
    "sg:address":"607 Saint Clair St",
    "sg:city":"Point Edward",
    "sg:classifiers":[
        {
            "category":"Bars & Pubs",
            "type":"Food & Drink"
        }
    ],
    "sg:phone":"+1 519 344 7621",
    "sg:postcode":"N7V 1P2",
    "sg:province":"ON",
    "wof:name":"Bottoms Up Sports Bar & Grill",
    "wof:placetype":"venue"
},
  "geometry": {"coordinates":[-82.40729522709999,42.9911575317],"type":"Point"}
}