{
  "type": "Feature",
  "properties": {
    "addr:full":"Barrie ON L4M 4S5",
    "addr:postcode":"l4m 4s5",
    "iso:country":"CA",
    "sg:city":"Barrie",
    "sg:classifiers":[
        {
            "category":"Health Services",
            "subcategory":"Doctor",
            "type":"Services"
        }
    ],
    "sg:phone":"+1 705 728 4242",
    "sg:postcode":"L4M 4S5",
    "sg:province":"ON",
    "sg:tags":[
        "physician",
        "surgeon"
    ],
    "wof:name":"Levine, Gerald M MD",
    "wof:placetype":"venue"
},
  "geometry": {"coordinates":[-79.68873596189999,44.4117622375],"type":"Point"}
}