{
  "type": "Feature",
  "properties": {
    "addr:full":"Scarborough ON M1T 3K4",
    "addr:postcode":"m1t 3k4",
    "iso:country":"CA",
    "sg:city":"Scarborough",
    "sg:classifiers":[
        {
            "category":"Real Estate",
            "subcategory":"Developer",
            "type":"Services"
        }
    ],
    "sg:phone":"+1 416 291 6665",
    "sg:postcode":"M1T 3K4",
    "sg:province":"ON",
    "wof:name":"Noik Development Inc",
    "wof:placetype":"venue"
},
  "geometry": {"coordinates":[-79.30735,43.778996],"type":"Point"}
}