{
  "type": "Feature",
  "properties": {
    "addr:full":"89 Av Boutin S Sainte-Helene-DE-Breakeyville QC G0S 1E3",
    "addr:postcode":"g0s 1e3",
    "addr:street":"89 Av Boutin S Sainte-Helene-De-Breakeyville",
    "iso:country":"CA",
    "sg:address":"89 Av Boutin S",
    "sg:city":"Sainte-Helene-DE-Breakeyville",
    "sg:classifiers":[
        {
            "category":"Wholesale",
            "subcategory":"Machinery & Supplies",
            "type":"Manufacturing & Wholesale Goods"
        }
    ],
    "sg:phone":"+1 418 832 2727",
    "sg:postcode":"G0S 1E3",
    "sg:province":"QC",
    "sg:tags":[
        "salon",
        "beauty"
    ],
    "wof:name":"Cosm'Art Mjd",
    "wof:placetype":"venue"
},
  "geometry": {"coordinates":[-71.24839782710001,46.6545372009],"type":"Point"}
}