{
  "type": "Feature",
  "properties": {
    "iso:country":"CA",
    "sg:city":"Calgary",
    "sg:classifiers":[
        {
            "category":"Professional",
            "subcategory":"Research",
            "type":"Services"
        }
    ],
    "sg:phone":"+1 403 219 8519",
    "sg:postcode":"T2E 7B1",
    "sg:province":"AB",
    "sg:tags":[
        "environmental",
        "ecological"
    ],
    "wof:name":"Stantec Lab",
    "wof:placetype":"venue"
},
  "geometry": {"coordinates":[-114.014434815,51.0786170959],"type":"Point"}
}