{
  "type": "Feature",
  "properties": {
    "addr:full":"579 Artisan Lane Bowen Island BC V0N 1G0",
    "addr:housenumber":"579",
    "addr:postcode":"v0n 1g0",
    "addr:street":"Artisan Lane",
    "iso:country":"CA",
    "sg:address":"579 Artisan Lane",
    "sg:city":"Bowen Island",
    "sg:classifiers":[
        {
            "category":"Travel",
            "subcategory":"Travel Agent",
            "type":"Entertainment"
        }
    ],
    "sg:phone":"+1 604 947 0222",
    "sg:postcode":"V0N 1G0",
    "sg:province":"BC",
    "sg:tags":[
        "agency",
        "bureau"
    ],
    "wof:name":"Personal Travel Management",
    "wof:placetype":"venue"
},
  "geometry": {"coordinates":[-123.345192,49.380207],"type":"Point"}
}