{
  "type": "Feature",
  "properties": {
    "addr:full":"650 Rue Des Forges Laval QC H7E 3Z2",
    "addr:housenumber":"650",
    "addr:postcode":"h7e 3z2",
    "addr:street":"Rue Des Forges",
    "iso:country":"CA",
    "sg:address":"650 Rue Des Forges",
    "sg:city":"Laval",
    "sg:classifiers":[
        {
            "category":"Building & Trades",
            "subcategory":"Construction",
            "type":"Services"
        }
    ],
    "sg:phone":"+1 450 967 7012",
    "sg:postcode":"H7E 3Z2",
    "sg:province":"QC",
    "sg:tags":[
        "repairing",
        "remodeling",
        "contractor"
    ],
    "wof:name":"Entreprises Zyrcon",
    "wof:placetype":"venue"
},
  "geometry": {"coordinates":[-73.668396,45.584583],"type":"Point"}
}