{
  "type": "Feature",
  "properties": {
    "iso:country":"CA",
    "sg:address":"411 3E Rang",
    "sg:city":"Saint-Athanase",
    "sg:classifiers":[
        {
            "category":"Wholesale",
            "subcategory":"Machinery & Supplies",
            "type":"Manufacturing & Wholesale Goods"
        }
    ],
    "sg:phone":"+1 450 347 2895",
    "sg:postcode":"J2X 4M9",
    "sg:province":"QC",
    "sg:tags":[
        "equipment",
        "dairy"
    ],
    "wof:name":"Comeau Trayeuses Inc",
    "wof:placetype":"venue"
},
  "geometry": {"coordinates":[-73.209328,45.310032],"type":"Point"}
}