{
  "type": "Feature",
  "properties": {
    "addr:full":"131 Stuart Ave Bengough SK S0C 0K0",
    "addr:housenumber":"131",
    "addr:postcode":"s0c 0k0",
    "addr:street":"Stuart Ave",
    "iso:country":"CA",
    "sg:address":"131 Stuart Ave",
    "sg:city":"Bengough",
    "sg:classifiers":[
        {
            "category":"Building & Trades",
            "subcategory":"Construction",
            "type":"Services"
        }
    ],
    "sg:phone":"+1 306 268 2887",
    "sg:postcode":"S0C 0K0",
    "sg:province":"SK",
    "sg:tags":[
        "excavating",
        "contractor"
    ],
    "wof:name":"Mc Ewen Excavation & Redi Mix",
    "wof:placetype":"venue"
},
  "geometry": {"coordinates":[-105.12273399999999,49.397285],"type":"Point"}
}