{
  "type": "Feature",
  "properties": {
    "addr:full":"Port Coquitlam BC V3C 3L7",
    "addr:postcode":"v3c 3l7",
    "iso:country":"CA",
    "sg:city":"Port Coquitlam",
    "sg:classifiers":[
        {
            "category":"Home & Garden",
            "subcategory":"Carpets & Floor Coverings",
            "type":"Retail Goods"
        }
    ],
    "sg:phone":"+1 604 941 6644",
    "sg:postcode":"V3C 3L7",
    "sg:province":"BC",
    "sg:tags":[
        "dealer",
        "rug"
    ],
    "wof:name":"Westwood Floors",
    "wof:placetype":"venue"
},
  "geometry": {"coordinates":[-122.790451,49.268776],"type":"Point"}
}