{
  "type": "Feature",
  "properties": {
    "addr:full":"4926 89 St NW Edmonton AB T6E 5K1",
    "addr:housenumber":"4926",
    "addr:postcode":"t6e 5k1",
    "addr:street":"89 St Nw",
    "iso:country":"CA",
    "sg:address":"4926 89 St NW",
    "sg:city":"Edmonton",
    "sg:classifiers":[
        {
            "category":"Government",
            "subcategory":"Office",
            "type":"Public Place"
        }
    ],
    "sg:phone":"+1 780 462 9221",
    "sg:postcode":"T6E 5K1",
    "sg:province":"AB",
    "sg:tags":[
        "federal",
        "affairs"
    ],
    "wof:name":"Consular Agency of Switzerland",
    "wof:placetype":"venue"
},
  "geometry": {"coordinates":[-113.464317322,53.4859733582],"type":"Point"}
}