{
  "type": "Feature",
  "properties": {
    "iso:country":"CA",
    "sg:city":"Elmvale",
    "sg:classifiers":[
        {
            "category":"Shopping",
            "subcategory":"Discount & Variety Stores",
            "type":"Retail Goods"
        }
    ],
    "sg:phone":"+1 705 322 3368",
    "sg:postcode":"L0L 1P0",
    "sg:province":"ON",
    "wof:name":"Beaudoin's Variety",
    "wof:placetype":"venue"
},
  "geometry": {"coordinates":[-79.8664855957,44.583984375],"type":"Point"}
}