{
  "type": "Feature",
  "properties": {
    "addr:full":"1124 Boul Saint-Rene O Gatineau QC J8T 6H1",
    "addr:housenumber":"1124",
    "addr:postcode":"j8t 6h1",
    "addr:street":"Boul Saint-Rene O",
    "iso:country":"CA",
    "sg:address":"1124 Boul Saint-Rene O",
    "sg:city":"Gatineau",
    "sg:classifiers":[
        {
            "category":"Health Services",
            "subcategory":"Chiropractor",
            "type":"Services"
        }
    ],
    "sg:phone":"+1 819 561 2242",
    "sg:postcode":"J8T 6H1",
    "sg:province":"QC",
    "wof:name":"Audet, Johanne DC",
    "wof:placetype":"venue"
},
  "geometry": {"coordinates":[-75.59246826170001,45.503868103],"type":"Point"}
}