{
  "type": "Feature",
  "properties": {
    "addr:full":"248 Medley St Fredericton NB E3A 3B3",
    "addr:housenumber":"248",
    "addr:postcode":"e3a 3b3",
    "addr:street":"Medley St",
    "iso:country":"CA",
    "sg:address":"248 Medley St",
    "sg:city":"Fredericton",
    "sg:classifiers":[
        {
            "category":"Social Services",
            "type":"Services"
        }
    ],
    "sg:phone":"+1 506 472 4528",
    "sg:postcode":"E3A 3B3",
    "sg:province":"NB",
    "sg:tags":[
        "youth",
        "organization",
        "center"
    ],
    "wof:name":"Fredericton Boys & Girls Club",
    "wof:placetype":"venue"
},
  "geometry": {"coordinates":[-66.620323,45.96579],"type":"Point"}
}