{
  "type": "Feature",
  "properties": {
    "addr:full":"Beaupre QC G0A 1E0",
    "addr:postcode":"g0a 1e0",
    "addr:street":"Beaupre",
    "iso:country":"CA",
    "sg:city":"Beaupre",
    "sg:classifiers":[
        {
            "category":"Sports & Exercise",
            "subcategory":"Bowling",
            "type":"Entertainment"
        }
    ],
    "sg:phone":"+1 418 827 8894",
    "sg:postcode":"G0A 1E0",
    "sg:province":"QC",
    "sg:tags":[
        "center"
    ],
    "wof:name":"Quillorama DE LA Cote",
    "wof:placetype":"venue"
},
  "geometry": {"coordinates":[-71.89045,46.713318],"type":"Point"}
}