{
  "type": "Feature",
  "properties": {
    "addr:full":"5 Rue Francoeur Saint-Basile NB E7C 2H8",
    "addr:housenumber":"5",
    "addr:postcode":"e7c 2h8",
    "addr:street":"Rue Francoeur",
    "iso:country":"CA",
    "sg:address":"5 Rue Francoeur",
    "sg:city":"Saint-Basile",
    "sg:classifiers":[
        {
            "category":"Professional",
            "type":"Services"
        }
    ],
    "sg:phone":"+1 506 263 8376",
    "sg:postcode":"E7C 2H8",
    "sg:province":"NB",
    "sg:tags":[
        "arts",
        "artist"
    ],
    "wof:name":"Eveline Gallant Fournier",
    "wof:placetype":"venue"
},
  "geometry": {"coordinates":[-68.1958618164,47.4211044312],"type":"Point"}
}