{
  "type": "Feature",
  "properties": {
    "iso:country":"CA",
    "sg:address":"318 Lonsdale Ave",
    "sg:city":"North Vancouver",
    "sg:classifiers":[
        {
            "category":"Shopping",
            "subcategory":"Discount & Variety Stores",
            "type":"Retail Goods"
        }
    ],
    "sg:phone":"+1 604 985 1628",
    "sg:postcode":"V7M 2G2",
    "sg:province":"BC",
    "wof:name":"Lonsdale Dollar Shop",
    "wof:placetype":"venue"
},
  "geometry": {"coordinates":[-123.076637,49.31358],"type":"Point"}
}