{
  "type": "Feature",
  "properties": {
    "iso:country":"CA",
    "sg:address":"1810 Broad St",
    "sg:city":"Regina",
    "sg:classifiers":[
        {
            "category":"Shopping",
            "subcategory":"Clothing, Apparel, & Fashions",
            "type":"Retail Goods"
        }
    ],
    "sg:phone":"+1 306 352 7932",
    "sg:postcode":"S4P 1X6",
    "sg:province":"SK",
    "wof:name":"Love Plus",
    "wof:placetype":"venue"
},
  "geometry": {"coordinates":[-104.606704712,50.4500808716],"type":"Point"}
}