{
  "type": "Feature",
  "properties": {
    "addr:full":"West Vancouver BC V7V 1H9",
    "addr:postcode":"v7v 1h9",
    "iso:country":"CA",
    "sg:city":"West Vancouver",
    "sg:classifiers":[
        {
            "category":"Real Estate",
            "subcategory":"Developer",
            "type":"Services"
        }
    ],
    "sg:phone":"+1 604 926 8109",
    "sg:postcode":"V7V 1H9",
    "sg:province":"BC",
    "sg:tags":[
        "company",
        "land"
    ],
    "wof:name":"Bcorp Holdings Inc",
    "wof:placetype":"venue"
},
  "geometry": {"coordinates":[-123.157867432,49.3286018372],"type":"Point"}
}