{
  "type": "Feature",
  "properties": {
    "iso:country":"CA",
    "sg:address":"119 North Railway Ave",
    "sg:city":"Deloraine",
    "sg:classifiers":[
        {
            "category":"Shopping",
            "subcategory":"Department Store",
            "type":"Retail Goods"
        }
    ],
    "sg:phone":"+1 204 747 2447",
    "sg:postcode":"R0M 0M0",
    "sg:province":"MB",
    "sg:tags":[
        "shop"
    ],
    "wof:name":"Bargain Shop",
    "wof:placetype":"venue"
},
  "geometry": {"coordinates":[-100.497436523,49.1933364868],"type":"Point"}
}