{
  "type": "Feature",
  "properties": {
    "iso:country":"CA",
    "sg:address":"1400 Rue Sauve O",
    "sg:city":"Montreal",
    "sg:classifiers":[
        {
            "category":"Education",
            "subcategory":"Special Training",
            "type":"Public Place"
        }
    ],
    "sg:phone":"+1 514 337 0332",
    "sg:postcode":"H4N 1C5",
    "sg:province":"QC",
    "sg:tags":[
        "instruction",
        "music"
    ],
    "wof:name":"Conservatoire Superieur DE",
    "wof:placetype":"venue"
},
  "geometry": {"coordinates":[-73.665367,45.535358],"type":"Point"}
}