{
  "type": "Feature",
  "properties": {
    "addr:full":"1988 56 St Delta BC V4L 2B1",
    "addr:housenumber":"1988",
    "addr:postcode":"v4l 2b1",
    "addr:street":"56 St",
    "iso:country":"CA",
    "sg:address":"1988 56 St",
    "sg:city":"Delta",
    "sg:classifiers":[
        {
            "category":"Organizations",
            "subcategory":"Religious Organization",
            "type":"Services"
        }
    ],
    "sg:phone":"+1 604 943 8244",
    "sg:postcode":"V4L 2B1",
    "sg:province":"BC",
    "sg:tags":[
        "church"
    ],
    "wof:name":"South Delta Baptist Church",
    "wof:placetype":"venue"
},
  "geometry": {"coordinates":[-123.06852000000001,49.03936],"type":"Point"}
}