{
  "type": "Feature",
  "properties": {
    "addr:full":"14937 112 Ave NW Edmonton AB T5M 2V6",
    "addr:housenumber":"14937",
    "addr:postcode":"t5m 2v6",
    "addr:street":"112 Ave Nw",
    "iso:country":"CA",
    "sg:address":"14937 112 Ave NW",
    "sg:city":"Edmonton",
    "sg:classifiers":[
        {
            "category":"Wholesale",
            "subcategory":"Office Equipment",
            "type":"Manufacturing & Wholesale Goods"
        }
    ],
    "sg:phone":"+1 780 455 7636",
    "sg:postcode":"T5M 2V6",
    "sg:province":"AB",
    "sg:tags":[
        "register",
        "cash",
        "supply"
    ],
    "wof:name":"Star Cash Register",
    "wof:placetype":"venue"
},
  "geometry": {"coordinates":[-113.57886499999999,53.560532],"type":"Point"}
}