{
  "type": "Feature",
  "properties": {
    "addr:full":"3240 Main St Vancouver BC V5V 3M5",
    "addr:housenumber":"3240",
    "addr:postcode":"v5v 3m5",
    "addr:street":"Main St",
    "iso:country":"CA",
    "sg:address":"3240 Main St",
    "sg:city":"Vancouver",
    "sg:classifiers":[
        {
            "category":"Retail",
            "subcategory":"Repair Shop",
            "type":"Services"
        }
    ],
    "sg:phone":"+1 604 873 9810",
    "sg:postcode":"V5V 3M5",
    "sg:province":"BC",
    "sg:tags":[
        "television",
        "radio"
    ],
    "wof:name":"Universal Sound & Video Inc",
    "wof:placetype":"venue"
},
  "geometry": {"coordinates":[-123.10098266599999,49.25623703],"type":"Point"}
}