{
  "type": "Feature",
  "properties": {
    "addr:full":"261 12th Ave W Vancouver BC V5Y 1T9",
    "addr:housenumber":"261",
    "addr:postcode":"v5y 1t9",
    "addr:street":"12Th Ave W",
    "iso:country":"CA",
    "sg:address":"261 12th Ave W",
    "sg:city":"Vancouver",
    "sg:classifiers":[
        {
            "category":"Social Services",
            "type":"Services"
        }
    ],
    "sg:phone":"+1 604 708 9955",
    "sg:postcode":"V5Y 1T9",
    "sg:province":"BC",
    "sg:tags":[
        "organization",
        "welfare"
    ],
    "wof:name":"Vancouver Recovery Club",
    "wof:placetype":"venue"
},
  "geometry": {"coordinates":[-123.110291,49.260498],"type":"Point"}
}