{
  "type": "Feature",
  "properties": {
    "addr:full":"5850 Av Marc-Chagall # 512 Cote Saint-Luc QC H4W 3H2",
    "addr:housenumber":"5850",
    "addr:postcode":"h4w 3h2",
    "addr:street":"Av Marc-Chagall # 512 Cote",
    "iso:country":"CA",
    "sg:address":"5850 Av Marc-Chagall # 512",
    "sg:city":"Cote Saint-Luc",
    "sg:classifiers":[
        {
            "category":"Wholesale",
            "subcategory":"Medical Equipment & Supplies",
            "type":"Manufacturing & Wholesale Goods"
        }
    ],
    "sg:phone":"+1 514 481 8488",
    "sg:postcode":"H4W 3H2",
    "sg:province":"QC",
    "sg:tags":[
        "dental"
    ],
    "wof:name":"Universadent Inc",
    "wof:placetype":"venue"
},
  "geometry": {"coordinates":[-73.664154,45.479698],"type":"Point"}
}