{
  "type": "Feature",
  "properties": {
    "addr:full":"4705 50th Ave Valleyview AB T0H 3N0",
    "addr:housenumber":"4705",
    "addr:postcode":"ab t0h 3n0",
    "addr:street":"50Th Ave",
    "iso:country":"CA",
    "sg:address":"4705 50th Ave",
    "sg:city":"Valleyview",
    "sg:classifiers":[
        {
            "category":"Shopping",
            "subcategory":"Catalog Store",
            "type":"Retail Goods"
        }
    ],
    "sg:phone":"+1 780 524 3346",
    "sg:postcode":"T0H 3N0",
    "sg:province":"AB",
    "sg:tags":[
        "mail",
        "order",
        "internet"
    ],
    "wof:name":"Sears Canada Inc",
    "wof:placetype":"venue"
},
  "geometry": {"coordinates":[-117.280647278,55.0641746521],"type":"Point"}
}