{
  "type": "Feature",
  "properties": {
    "addr:full":"North Vancouver BC V7J 1G1",
    "addr:postcode":"v7j 1g1",
    "iso:country":"CA",
    "sg:city":"North Vancouver",
    "sg:classifiers":[
        {
            "category":"Freight",
            "type":"Transportation"
        }
    ],
    "sg:phone":"+1 604 984 2282",
    "sg:postcode":"V7J 1G1",
    "sg:province":"BC",
    "sg:tags":[
        "delivery",
        "courier"
    ],
    "wof:name":"Sterling Express Couriers",
    "wof:placetype":"venue"
},
  "geometry": {"coordinates":[-123.03272200000001,49.3078],"type":"Point"}
}