{
  "type": "Feature",
  "properties": {
    "addr:full":"Tavistock ON N0B 2R0",
    "addr:postcode":"n0b 2r0",
    "iso:country":"CA",
    "sg:city":"Tavistock",
    "sg:classifiers":[
        {
            "category":"Building & Trades",
            "subcategory":"Plumbing",
            "type":"Services"
        }
    ],
    "sg:phone":"+1 519 655 3111",
    "sg:postcode":"N0B 2R0",
    "sg:province":"ON",
    "sg:tags":[
        "contractor"
    ],
    "wof:name":"Schultz Plumbing & Heating",
    "wof:placetype":"venue"
},
  "geometry": {"coordinates":[-80.836349,43.321392],"type":"Point"}
}