{
  "type": "Feature",
  "properties": {
    "addr:full":"6545 Boul Pie-Ix Montreal QC H1X 2C5",
    "addr:housenumber":"6545",
    "addr:postcode":"h1x 2c5",
    "addr:street":"Boul Pie-Ix",
    "iso:country":"CA",
    "sg:address":"6545 Boul Pie-Ix",
    "sg:city":"Montreal",
    "sg:classifiers":[
        {
            "category":"Health Services",
            "subcategory":"Podiatrist",
            "type":"Services"
        }
    ],
    "sg:phone":"+1 514 727 3533",
    "sg:postcode":"H1X 2C5",
    "sg:province":"QC",
    "wof:name":"Justino, Manuel DPM",
    "wof:placetype":"venue"
},
  "geometry": {"coordinates":[-73.58061981199999,45.5630912781],"type":"Point"}
}