{
  "type": "Feature",
  "properties": {
    "addr:full":"42 6th Ave S Cranbrook BC V1C 2H3",
    "addr:housenumber":"42",
    "addr:postcode":"bc v1c 2h3",
    "addr:street":"6Th Ave S",
    "iso:country":"CA",
    "sg:address":"42 6th Ave S",
    "sg:city":"Cranbrook",
    "sg:classifiers":[
        {
            "category":"Education",
            "subcategory":"Dance Studio",
            "type":"Public Place"
        }
    ],
    "sg:phone":"+1 250 426 3506",
    "sg:postcode":"V1C 2H3",
    "sg:province":"BC",
    "sg:tags":[
        "instruction",
        "dancing"
    ],
    "wof:name":"Stages School of Dance",
    "wof:placetype":"venue"
},
  "geometry": {"coordinates":[-115.77293400000001,49.51059],"type":"Point"}
}