{
  "type": "Feature",
  "properties": {
    "iso:country":"CA",
    "sg:city":"Stratford",
    "sg:classifiers":[
        {
            "category":"Recreation",
            "type":"Entertainment"
        }
    ],
    "sg:phone":"+1 519 272 0408",
    "sg:postcode":"N5A 6S4",
    "sg:province":"ON",
    "sg:tags":[
        "martial",
        "arts",
        "instruction"
    ],
    "wof:name":"Stratford Martial Arts & Hlth",
    "wof:placetype":"venue"
},
  "geometry": {"coordinates":[-80.98547363279999,43.3530464172],"type":"Point"}
}