{
  "type": "Feature",
  "properties": {
    "addr:full":"783 Rue Principale Cowansville QC J2K 1J8",
    "addr:housenumber":"783",
    "addr:postcode":"j2k 1j8",
    "addr:street":"Rue Principale",
    "iso:country":"CA",
    "sg:address":"783 Rue Principale",
    "sg:city":"Cowansville",
    "sg:classifiers":[
        {
            "category":"Building & Trades",
            "subcategory":"Landscaping Services",
            "type":"Services"
        }
    ],
    "sg:phone":"+1 450 266 0757",
    "sg:postcode":"J2K 1J8",
    "sg:province":"QC",
    "sg:tags":[
        "landscape",
        "contractor"
    ],
    "wof:name":"Paysagistes Cowansville Lndscp",
    "wof:placetype":"venue"
},
  "geometry": {"coordinates":[-72.722572,45.209011],"type":"Point"}
}