{
  "type": "Feature",
  "properties": {
    "addr:full":"2111 Route 640 Hanwell NB E3C 1M7",
    "addr:housenumber":"2111",
    "addr:postcode":"e3c 1m7",
    "addr:street":"Route 640",
    "iso:country":"CA",
    "sg:address":"2111 Route 640",
    "sg:city":"Hanwell",
    "sg:classifiers":[
        {
            "category":"Manufacturing",
            "subcategory":"Tools & Machinery",
            "type":"Manufacturing & Wholesale Goods"
        }
    ],
    "sg:phone":"+1 506 462 9119",
    "sg:postcode":"E3C 1M7",
    "sg:province":"NB",
    "sg:tags":[
        "recording",
        "instrument",
        "testing",
        "electronic",
        "equipment"
    ],
    "wof:name":"Measurand",
    "wof:placetype":"venue"
},
  "geometry": {"coordinates":[-66.7954406738,45.8684844971],"type":"Point"}
}