{
  "type": "Feature",
  "properties": {
    "iso:country":"CA",
    "sg:address":"2111 Route 640",
    "sg:city":"Hanwell",
    "sg:classifiers":[
        {
            "category":"Manufacturing",
            "subcategory":"Tools & Machinery",
            "type":"Manufacturing & Wholesale Goods"
        }
    ],
    "sg:phone":"+1 506 462 9119",
    "sg:postcode":"E3C 1M7",
    "sg:province":"NB",
    "sg:tags":[
        "recording",
        "instrument",
        "testing",
        "electronic",
        "equipment"
    ],
    "wof:name":"Measurand",
    "wof:placetype":"venue"
},
  "geometry": {"coordinates":[-66.7954406738,45.8684844971],"type":"Point"}
}