{
  "type": "Feature",
  "properties": {
    "addr:full":"638 Queen St Newmarket ON L3Y 2J2",
    "addr:housenumber":"638",
    "addr:postcode":"l3y 2j2",
    "addr:street":"Queen St",
    "iso:country":"CA",
    "sg:address":"638 Queen St",
    "sg:city":"Newmarket",
    "sg:classifiers":[
        {
            "category":"Building & Trades",
            "subcategory":"Plumbing",
            "type":"Services"
        }
    ],
    "sg:phone":"+1 905 967 0555",
    "sg:postcode":"L3Y 2J2",
    "sg:province":"ON",
    "sg:tags":[
        "cleaning",
        "boiler"
    ],
    "wof:name":"Steam Fab Ltd",
    "wof:placetype":"venue"
},
  "geometry": {"coordinates":[-79.450745,44.058292],"type":"Point"}
}