{
  "type": "Feature",
  "properties": {
    "addr:full":"10503 100 Ave Fort St John BC V1J 1Z1",
    "addr:housenumber":"10503",
    "addr:postcode":"v1j 1z1",
    "addr:street":"100 Ave",
    "iso:country":"CA",
    "sg:address":"10503 100 Ave",
    "sg:city":"Fort St John",
    "sg:classifiers":[
        {
            "category":"Manufacturing",
            "subcategory":"Printing",
            "type":"Manufacturing & Wholesale Goods"
        }
    ],
    "sg:phone":"+1 250 785 0203",
    "sg:postcode":"V1J 1Z1",
    "sg:province":"BC",
    "sg:tags":[
        "printer"
    ],
    "wof:name":"Community Printers & Stationer",
    "wof:placetype":"venue"
},
  "geometry": {"coordinates":[-120.855949,56.24622],"type":"Point"}
}