{
  "type": "Feature",
  "properties": {
    "addr:full":"1163 Victoria St Petawawa ON K8H 2E6",
    "addr:housenumber":"1163",
    "addr:postcode":"k8h 2e6",
    "addr:street":"Victoria St",
    "iso:country":"CA",
    "sg:address":"1163 Victoria St",
    "sg:city":"Petawawa",
    "sg:classifiers":[
        {
            "category":"Recreation",
            "type":"Entertainment"
        }
    ],
    "sg:phone":"+1 613 687 5020",
    "sg:postcode":"K8H 2E6",
    "sg:province":"ON",
    "sg:tags":[
        "hall",
        "auditorium"
    ],
    "wof:name":"Lions Community Hall",
    "wof:placetype":"venue"
},
  "geometry": {"coordinates":[-77.273567,45.900318],"type":"Point"}
}