{
  "type": "Feature",
  "properties": {
    "addr:full":"49 Ch Auckland Saint-Isidore-DE-Clifton QC J0B 2X0",
    "addr:housenumber":"49",
    "addr:postcode":"j0b 2x0",
    "addr:street":"Ch Auckland",
    "iso:country":"CA",
    "sg:address":"49 Ch Auckland",
    "sg:city":"Saint-Isidore-DE-Clifton",
    "sg:classifiers":[
        {
            "category":"Food & Beverages",
            "subcategory":"Groceries & Convenience Stores",
            "type":"Retail Goods"
        }
    ],
    "sg:phone":"+1 819 658 3338",
    "sg:postcode":"J0B 2X0",
    "sg:province":"QC",
    "wof:name":"Depanneur D'Auckland",
    "wof:placetype":"venue"
},
  "geometry": {"coordinates":[-71.5119400024,45.2654762268],"type":"Point"}
}