{
  "type": "Feature",
  "properties": {
    "addr:full":"199 Rue Principale Saint-Gabriel-DE-Rimouski QC G0K 1M0",
    "addr:housenumber":"199",
    "addr:postcode":"g0k 1m0",
    "addr:street":"Rue Principale",
    "iso:country":"CA",
    "sg:address":"199 Rue Principale",
    "sg:city":"Saint-Gabriel-DE-Rimouski",
    "sg:classifiers":[
        {
            "category":"Social Services",
            "type":"Services"
        }
    ],
    "sg:phone":"+1 418 798 4642",
    "sg:postcode":"G0K 1M0",
    "sg:province":"QC",
    "sg:tags":[
        "counselor",
        "tours",
        "human",
        "relations",
        "sightseeing"
    ],
    "wof:name":"Gallayann Aventure Enr",
    "wof:placetype":"venue"
},
  "geometry": {"coordinates":[-68.154800415,48.4365844727],"type":"Point"}
}