{
  "type": "Feature",
  "properties": {
    "addr:full":"303 Main St Springdale NL A0J 1T0",
    "addr:housenumber":"303",
    "addr:postcode":"a0j 1t0",
    "addr:street":"Main St",
    "iso:country":"CA",
    "sg:address":"303 Main St",
    "sg:city":"Springdale",
    "sg:classifiers":[
        {
            "category":"Building & Trades",
            "subcategory":"Electrical",
            "type":"Services"
        }
    ],
    "sg:phone":"+1 709 673 3730",
    "sg:postcode":"A0J 1T0",
    "sg:province":"NL",
    "sg:tags":[
        "electric",
        "contractor"
    ],
    "wof:name":"Pelley Electric Ltd",
    "wof:placetype":"venue"
},
  "geometry": {"coordinates":[-56.066757,49.501808],"type":"Point"}
}