{
  "type": "Feature",
  "properties": {
    "addr:full":"300 Rue Longpre Saint-Jerome QC J7Y 3B9",
    "addr:housenumber":"300",
    "addr:postcode":"j7y 3b9",
    "addr:street":"Rue Longpre Saint-Jerome",
    "iso:country":"CA",
    "sg:address":"300 Rue Longpre",
    "sg:city":"Saint-Jerome",
    "sg:classifiers":[
        {
            "category":"Professional",
            "subcategory":"Management & Consulting",
            "type":"Services"
        }
    ],
    "sg:phone":"+1 450 436 4051",
    "sg:postcode":"J7Y 3B9",
    "sg:province":"QC",
    "sg:tags":[
        "consultant",
        "recreation",
        "program",
        "organization"
    ],
    "wof:name":"Loisirs Laurentides",
    "wof:placetype":"venue"
},
  "geometry": {"coordinates":[-74.0105209351,45.7761802673],"type":"Point"}
}