{
  "type": "Feature",
  "properties": {
    "iso:country":"CA",
    "sg:address":"Cp 115",
    "sg:city":"Harrington Harbour",
    "sg:classifiers":[
        {
            "category":"Education",
            "subcategory":"School",
            "type":"Public Place"
        }
    ],
    "sg:phone":"+1 418 229 2333",
    "sg:postcode":"G0G 1N0",
    "sg:province":"QC",
    "wof:name":"Ecole Marie Sarah",
    "wof:placetype":"venue"
},
  "geometry": {"coordinates":[-59.4784011841,50.4970779419],"type":"Point"}
}