{
  "type": "Feature",
  "properties": {
    "iso:country":"CA",
    "sg:city":"Longueuil",
    "sg:classifiers":[
        {
            "category":"Building & Trades",
            "subcategory":"Construction",
            "type":"Services"
        }
    ],
    "sg:phone":"+1 450 670 5307",
    "sg:postcode":"J4J 1W1",
    "sg:province":"QC",
    "sg:tags":[
        "repairing",
        "remodeling",
        "painter",
        "contractor"
    ],
    "wof:name":"Belanger Touchatou",
    "wof:placetype":"venue"
},
  "geometry": {"coordinates":[-73.47756195069999,45.5397224426],"type":"Point"}
}