{
  "type": "Feature",
  "properties": {
    "addr:full":"1044 Howard Ave Windsor ON N9A 1S7",
    "addr:housenumber":"1044",
    "addr:postcode":"n9a 1s7",
    "addr:street":"Howard Ave",
    "iso:country":"CA",
    "sg:address":"1044 Howard Ave",
    "sg:city":"Windsor",
    "sg:classifiers":[
        {
            "category":"Manufacturing",
            "subcategory":"Metals",
            "type":"Manufacturing & Wholesale Goods"
        }
    ],
    "sg:phone":"+1 519 254 4502",
    "sg:postcode":"N9A 1S7",
    "sg:province":"ON",
    "sg:tags":[
        "name",
        "monument"
    ],
    "wof:name":"D Clarke Monuments",
    "wof:placetype":"venue"
},
  "geometry": {"coordinates":[-83.02513122560001,42.3108673096],"type":"Point"}
}