{
  "type": "Feature",
  "properties": {
    "addr:full":"298 Line 11 S Oro ON L0L 2X0",
    "addr:housenumber":"298",
    "addr:postcode":"l0l 2x0",
    "addr:street":"Line 11 S",
    "iso:country":"CA",
    "sg:address":"298 Line 11 S",
    "sg:city":"Oro",
    "sg:classifiers":[
        {
            "category":"Organizations",
            "subcategory":"Religious Organization",
            "type":"Services"
        }
    ],
    "sg:phone":"+1 705 487 5589",
    "sg:postcode":"L0L 2X0",
    "sg:province":"ON",
    "wof:name":"Hawkestone United Church",
    "wof:placetype":"venue"
},
  "geometry": {"coordinates":[-79.6295013428,44.4940490723],"type":"Point"}
}