{
  "type": "Feature",
  "properties": {
    "addr:full":"Whitedog ON P0X 1P0",
    "addr:postcode":"p0x 1p0",
    "iso:country":"CA",
    "sg:city":"Whitedog",
    "sg:classifiers":[
        {
            "category":"Government",
            "subcategory":"Office",
            "type":"Public Place"
        }
    ],
    "sg:phone":"+1 807 927 2440",
    "sg:postcode":"P0X 1P0",
    "sg:province":"ON",
    "wof:name":"Canada Medical Svc Branch",
    "wof:placetype":"venue"
},
  "geometry": {"coordinates":[-94.911751,50.176102],"type":"Point"}
}