{
  "type": "Feature",
  "properties": {
    "addr:full":"159 Thames St S Ingersoll ON N5C 2T3",
    "addr:housenumber":"159",
    "addr:postcode":"n5c 2t3",
    "addr:street":"Thames St S",
    "iso:country":"CA",
    "sg:address":"159 Thames St S",
    "sg:city":"Ingersoll",
    "sg:classifiers":[
        {
            "category":"Shopping",
            "type":"Retail Goods"
        }
    ],
    "sg:phone":"+1 519 485 2620",
    "sg:postcode":"N5C 2T3",
    "sg:province":"ON",
    "sg:tags":[
        "picture",
        "frame"
    ],
    "wof:name":"Frank's Convenience Store",
    "wof:placetype":"venue"
},
  "geometry": {"coordinates":[-80.88230900000001,43.038094],"type":"Point"}
}