{
  "type": "Feature",
  "properties": {
    "addr:full":"2141 Queen St Abbotsford BC V2T 6J3",
    "addr:housenumber":"2141",
    "addr:postcode":"v2t 6j3",
    "addr:street":"Queen St",
    "iso:country":"CA",
    "sg:address":"2141 Queen St",
    "sg:city":"Abbotsford",
    "sg:classifiers":[
        {
            "category":"Manufacturing",
            "subcategory":"Tools & Machinery",
            "type":"Manufacturing & Wholesale Goods"
        }
    ],
    "sg:phone":"+1 250 652 0382",
    "sg:postcode":"V2T 6J3",
    "sg:province":"BC",
    "sg:tags":[
        "disposal",
        "garbage"
    ],
    "wof:name":"Wasteline Containers Ltd",
    "wof:placetype":"venue"
},
  "geometry": {"coordinates":[-122.367828,49.041298],"type":"Point"}
}