{
  "type": "Feature",
  "properties": {
    "addr:full":"4917 Tecumseh Rd E Windsor ON N8T 1B9",
    "addr:housenumber":"4917",
    "addr:postcode":"n8t 1b9",
    "addr:street":"Tecumseh Rd E",
    "iso:country":"CA",
    "sg:address":"4917 Tecumseh Rd E",
    "sg:city":"Windsor",
    "sg:classifiers":[
        {
            "category":"Health Services",
            "subcategory":"Podiatrist",
            "type":"Services"
        }
    ],
    "sg:phone":"+1 519 974 3303",
    "sg:postcode":"N8T 1B9",
    "sg:province":"ON",
    "sg:tags":[
        "nurse",
        "registry"
    ],
    "wof:name":"Happy Soles",
    "wof:placetype":"venue"
},
  "geometry": {"coordinates":[-82.9657287598,42.3076858521],"type":"Point"}
}