{
  "type": "Feature",
  "properties": {
    "addr:full":"4180 Loch Lomond Rd Saint John NB E2N 1L7",
    "addr:housenumber":"4180",
    "addr:postcode":"e2n 1l7",
    "addr:street":"Loch Lomond Rd",
    "iso:country":"CA",
    "sg:address":"4180 Loch Lomond Rd",
    "sg:city":"Saint John",
    "sg:classifiers":[
        {
            "category":"Retail",
            "subcategory":"Auto Rental",
            "type":"Services"
        }
    ],
    "sg:phone":"+1 506 696 3340",
    "sg:postcode":"E2N 1L7",
    "sg:province":"NB",
    "sg:tags":[
        "renting",
        "automobile"
    ],
    "wof:name":"National Car Rental",
    "wof:placetype":"venue"
},
  "geometry": {"coordinates":[-65.89426400000001,45.330002],"type":"Point"}
}