{
  "type": "Feature",
  "properties": {
    "addr:full":"2609 19 Ave SW Calgary AB T3E 0E9",
    "addr:housenumber":"2609",
    "addr:postcode":"t3e 0e9",
    "addr:street":"19 Ave Sw",
    "iso:country":"CA",
    "sg:address":"2609 19 Ave SW",
    "sg:city":"Calgary",
    "sg:classifiers":[
        {
            "category":"Organizations",
            "subcategory":"Professional Association",
            "type":"Services"
        }
    ],
    "sg:phone":"+1 403 249 6991",
    "sg:postcode":"T3E 0E9",
    "sg:province":"AB",
    "sg:tags":[
        "club"
    ],
    "wof:name":"Good Companions Seniors Ctr",
    "wof:placetype":"venue"
},
  "geometry": {"coordinates":[-114.122619629,51.0361557007],"type":"Point"}
}