{
  "type": "Feature",
  "properties": {
    "addr:full":"1177 Hornby St # 1 Vancouver BC V6Z 2E9",
    "addr:housenumber":"1177",
    "addr:postcode":"v6z 2e9",
    "addr:street":"Hornby St # 1",
    "iso:country":"CA",
    "sg:address":"1177 Hornby St # 1",
    "sg:city":"Vancouver",
    "sg:classifiers":[
        {
            "category":"Professional",
            "subcategory":"Management & Consulting",
            "type":"Services"
        }
    ],
    "sg:phone":"+1 604 689 5511",
    "sg:postcode":"V6Z 2E9",
    "sg:province":"BC",
    "sg:tags":[
        "consultant",
        "market",
        "analysis",
        "business",
        "research"
    ],
    "wof:name":"William F Johnston & Assoc Ltd",
    "wof:placetype":"venue"
},
  "geometry": {"coordinates":[-123.127869,49.278828],"type":"Point"}
}