{
  "type": "Feature",
  "properties": {
    "addr:full":"364 Simcoe St Beaverton ON L0K 1A0",
    "addr:housenumber":"364",
    "addr:postcode":"l0k 1a0",
    "addr:street":"Simcoe St",
    "iso:country":"CA",
    "sg:address":"364 Simcoe St",
    "sg:city":"Beaverton",
    "sg:classifiers":[
        {
            "category":"Real Estate",
            "subcategory":"Real Estate Agent",
            "type":"Services"
        }
    ],
    "sg:phone":"+1 705 426 2905",
    "sg:postcode":"L0K 1A0",
    "sg:province":"ON",
    "wof:name":"Re/Max Country Lakes",
    "wof:placetype":"venue"
},
  "geometry": {"coordinates":[-79.153671,44.429695],"type":"Point"}
}