{
  "type": "Feature",
  "properties": {
    "addr:full":"97 Des Pruniers Lebel-Sur-Quevillon QC J0Y 1X0",
    "addr:housenumber":"97",
    "addr:postcode":"j0y 1x0",
    "addr:street":"Des Pruniers Lebel-Sur-Quevillon",
    "iso:country":"CA",
    "sg:address":"97 Des Pruniers",
    "sg:city":"Lebel-Sur-Quevillon",
    "sg:classifiers":[
        {
            "category":"Shopping",
            "subcategory":"Pharmacy",
            "type":"Retail Goods"
        }
    ],
    "sg:phone":"+1 819 755 4373",
    "sg:postcode":"J0Y 1X0",
    "sg:province":"QC",
    "wof:name":"Michel Trudel Pharmacien",
    "wof:placetype":"venue"
},
  "geometry": {"coordinates":[-76.9868392944,49.0557746887],"type":"Point"}
}