{
  "type": "Feature",
  "properties": {
    "addr:full":"4002 Rue Chateauguay Jonquiere QC G8A 1L1",
    "addr:housenumber":"4002",
    "addr:postcode":"g8a 1l1",
    "addr:street":"Rue Chateauguay",
    "iso:country":"CA",
    "sg:address":"4002 Rue Chateauguay",
    "sg:city":"Jonquiere",
    "sg:classifiers":[
        {
            "category":"Personal",
            "subcategory":"Beauty Salon",
            "type":"Services"
        }
    ],
    "sg:phone":"+1 418 695 4249",
    "sg:postcode":"G8A 1L1",
    "sg:province":"QC",
    "wof:name":"Salon DE Coiffure Bigoudis",
    "wof:placetype":"venue"
},
  "geometry": {"coordinates":[-71.260094,48.414566],"type":"Point"}
}