{
  "type": "Feature",
  "properties": {
    "addr:full":"510 6th Ave Ladysmith BC V9G 1A6",
    "addr:housenumber":"510",
    "addr:postcode":"v9g 1a6",
    "addr:street":"6Th Ave",
    "iso:country":"CA",
    "sg:address":"510 6th Ave",
    "sg:city":"Ladysmith",
    "sg:classifiers":[
        {
            "category":"Education",
            "subcategory":"School",
            "type":"Public Place"
        }
    ],
    "sg:phone":"+1 250 245 3912",
    "sg:postcode":"V9G 1A6",
    "sg:province":"BC",
    "wof:name":"Ladysmith Primary School",
    "wof:placetype":"venue"
},
  "geometry": {"coordinates":[-123.82421100000001,48.989094],"type":"Point"}
}