{
  "type": "Feature",
  "properties": {
    "iso:country":"CA",
    "sg:city":"Ottawa",
    "sg:classifiers":[
        {
            "category":"Professional",
            "subcategory":"Secretarial Services",
            "type":"Services"
        }
    ],
    "sg:phone":"+1 613 238 8501",
    "sg:postcode":"K1P 6E2",
    "sg:province":"ON",
    "sg:tags":[
        "convention",
        "court",
        "reporter"
    ],
    "wof:name":"Gillespie Reporting Svc",
    "wof:placetype":"venue"
},
  "geometry": {"coordinates":[-75.696754,45.420506],"type":"Point"}
}