{
  "type": "Feature",
  "properties": {
    "addr:full":"61 King St Fort Smith NT X0E 0P0",
    "addr:housenumber":"61",
    "addr:postcode":"x0e 0p0",
    "addr:street":"King St",
    "iso:country":"CA",
    "sg:address":"61 King St",
    "sg:city":"Fort Smith",
    "sg:classifiers":[
        {
            "category":"Government",
            "subcategory":"Office",
            "type":"Public Place"
        }
    ],
    "sg:phone":"+1 867 872 2835",
    "sg:postcode":"X0E 0P0",
    "sg:province":"NT",
    "sg:tags":[
        "village"
    ],
    "wof:name":"Fort Smith Garage",
    "wof:placetype":"venue"
},
  "geometry": {"coordinates":[-111.902633667,60.0000953674],"type":"Point"}
}