{
  "type": "Feature",
  "properties": {
    "addr:full":"5805 Almon St Halifax NS B3K 1T7",
    "addr:housenumber":"5805",
    "addr:postcode":"b3k 1t7",
    "addr:street":"Almon St",
    "iso:country":"CA",
    "sg:address":"5805 Almon St",
    "sg:city":"Halifax",
    "sg:classifiers":[
        {
            "category":"Banks & Credit Unions",
            "subcategory":"Bank",
            "type":"Services"
        }
    ],
    "sg:phone":"+1 902 421 8338",
    "sg:postcode":"B3K 1T7",
    "sg:province":"NS",
    "wof:name":"Royal Bank Financial Group",
    "wof:placetype":"venue"
},
  "geometry": {"coordinates":[-63.5977897644,44.6581878662],"type":"Point"}
}