{
  "type": "Feature",
  "properties": {
    "addr:full":"1125 Bloor St Mississauga ON L4Y 2N6",
    "addr:housenumber":"1125",
    "addr:postcode":"l4y 2n6",
    "addr:street":"Bloor St",
    "iso:country":"CA",
    "sg:address":"1125 Bloor St",
    "sg:city":"Mississauga",
    "sg:classifiers":[
        {
            "category":"Food & Beverages",
            "subcategory":"Liquor & Beverages",
            "type":"Retail Goods"
        }
    ],
    "sg:phone":"+1 905 279 0191",
    "sg:postcode":"L4Y 2N6",
    "sg:province":"ON",
    "sg:tags":[
        "beer",
        "ale"
    ],
    "wof:name":"Beer Store",
    "wof:placetype":"venue"
},
  "geometry": {"coordinates":[-79.600296,43.610981],"type":"Point"}
}