{
  "type": "Feature",
  "properties": {
    "addr:full":"60 Columbia Way Markham ON L3R 0C9",
    "addr:housenumber":"60",
    "addr:postcode":"l3r 0c9",
    "addr:street":"Columbia Way",
    "iso:country":"CA",
    "sg:address":"60 Columbia Way",
    "sg:city":"Markham",
    "sg:classifiers":[
        {
            "category":"Shopping",
            "subcategory":"Discount & Variety Stores",
            "type":"Retail Goods"
        }
    ],
    "sg:phone":"+1 905 415 0987",
    "sg:postcode":"L3R 0C9",
    "sg:province":"ON",
    "wof:name":"Valleywood Smoke & Variety",
    "wof:placetype":"venue"
},
  "geometry": {"coordinates":[-79.36940800000001,43.852329],"type":"Point"}
}