{
  "type": "Feature",
  "properties": {
    "addr:full":"216 4th Ave E # 228 Vancouver BC V5T 1G5",
    "addr:housenumber":"216",
    "addr:postcode":"v5t 1g5",
    "addr:street":"4Th Ave E # 228",
    "iso:country":"CA",
    "sg:address":"216 4th Ave E # 228",
    "sg:city":"Vancouver",
    "sg:classifiers":[
        {
            "category":"Restaurant",
            "type":"Food & Drink"
        }
    ],
    "sg:phone":"+1 604 873 8792",
    "sg:postcode":"V5T 1G5",
    "sg:province":"BC",
    "wof:name":"Moss Cafe",
    "wof:placetype":"venue"
},
  "geometry": {"coordinates":[-123.10032699999999,49.267204],"type":"Point"}
}