{
  "type": "Feature",
  "properties": {
    "addr:full":"Calgary AB T1Y 5T4",
    "addr:postcode":"t1y 5t4",
    "iso:country":"CA",
    "sg:city":"Calgary",
    "sg:classifiers":[
        {
            "category":"Restaurant",
            "type":"Food & Drink"
        }
    ],
    "sg:phone":"+1 403 280 0755",
    "sg:postcode":"T1Y 5T4",
    "sg:province":"AB",
    "wof:name":"Subway Sandwiches & Salads",
    "wof:placetype":"venue"
},
  "geometry": {"coordinates":[-113.982147,51.074059],"type":"Point"}
}