{
  "type": "Feature",
  "properties": {
    "addr:full":"229 Clark St Acme AB T0M 0A0",
    "addr:housenumber":"229",
    "addr:postcode":"t0m 0a0",
    "addr:street":"Clark St",
    "iso:country":"CA",
    "sg:address":"229 Clark St",
    "sg:city":"Acme",
    "sg:classifiers":[
        {
            "category":"Building & Trades",
            "subcategory":"Construction",
            "type":"Services"
        }
    ],
    "sg:phone":"+1 403 546 4381",
    "sg:postcode":"T0M 0A0",
    "sg:province":"AB",
    "sg:tags":[
        "repairing",
        "remodeling",
        "carpenter",
        "contractor"
    ],
    "wof:name":"Timmerman Enterprises",
    "wof:placetype":"venue"
},
  "geometry": {"coordinates":[-113.511253,51.497383],"type":"Point"}
}