{
  "type": "Feature",
  "properties": {
    "addr:full":"Gatineau QC J8P 1E6",
    "addr:postcode":"j8p 1e6",
    "iso:country":"CA",
    "sg:city":"Gatineau",
    "sg:classifiers":[
        {
            "category":"Health Services",
            "subcategory":"Doctor",
            "type":"Services"
        }
    ],
    "sg:phone":"+1 819 669 0313",
    "sg:postcode":"J8P 1E6",
    "sg:province":"QC",
    "sg:tags":[
        "dentist"
    ],
    "wof:name":"Gosselin, Louise DDS",
    "wof:placetype":"venue"
},
  "geometry": {"coordinates":[-75.639954,45.484482],"type":"Point"}
}