{
  "type": "Feature",
  "properties": {
    "addr:full":"11602 40 St NW Edmonton AB T5W 2K6",
    "addr:housenumber":"11602",
    "addr:postcode":"t5w 2k6",
    "addr:street":"40 St Nw",
    "iso:country":"CA",
    "sg:address":"11602 40 St NW",
    "sg:city":"Edmonton",
    "sg:classifiers":[
        {
            "category":"Education",
            "subcategory":"School",
            "type":"Public Place"
        }
    ],
    "sg:phone":"+1 780 471 1052",
    "sg:postcode":"T5W 2K6",
    "sg:province":"AB",
    "wof:name":"Lawton Junior High School",
    "wof:placetype":"venue"
},
  "geometry": {"coordinates":[-113.40310700000001,53.568691],"type":"Point"}
}