{
  "type": "Feature",
  "properties": {
    "addr:full":"405 Adolphus St Cornwall ON K6H 3S8",
    "addr:housenumber":"405",
    "addr:postcode":"k6h 3s8",
    "addr:street":"Adolphus St",
    "iso:country":"CA",
    "sg:address":"405 Adolphus St",
    "sg:city":"Cornwall",
    "sg:classifiers":[
        {
            "category":"Personal",
            "subcategory":"Beauty Salon",
            "type":"Services"
        }
    ],
    "sg:phone":"+1 613 936 9374",
    "sg:postcode":"K6H 3S8",
    "sg:province":"ON",
    "wof:name":"Sue's Esthetic Boutique",
    "wof:placetype":"venue"
},
  "geometry": {"coordinates":[-74.72402954099999,45.0232887268],"type":"Point"}
}