{
  "type": "Feature",
  "properties": {
    "addr:full":"231 Rue Principale Melocheville QC J0S 1J0",
    "addr:housenumber":"231",
    "addr:postcode":"j0s 1j0",
    "addr:street":"Rue Principale",
    "iso:country":"CA",
    "sg:address":"231 Rue Principale",
    "sg:city":"Melocheville",
    "sg:classifiers":[
        {
            "category":"Bars & Pubs",
            "type":"Food & Drink"
        }
    ],
    "sg:phone":"+1 450 225 5252",
    "sg:postcode":"J0S 1J0",
    "sg:province":"QC",
    "sg:tags":[
        "lounge",
        "cocktail"
    ],
    "wof:name":"Bar Des Rapides",
    "wof:placetype":"venue"
},
  "geometry": {"coordinates":[-73.9306488037,45.3173141479],"type":"Point"}
}