{
  "type": "Feature",
  "properties": {
    "addr:full":"Montreal QC H3W 1H9",
    "addr:postcode":"h3w 1h9",
    "iso:country":"CA",
    "sg:city":"Montreal",
    "sg:classifiers":[
        {
            "category":"Professional",
            "subcategory":"Research",
            "type":"Services"
        }
    ],
    "sg:phone":"+1 514 737 6076",
    "sg:postcode":"H3W 1H9",
    "sg:province":"QC",
    "sg:tags":[
        "foundation",
        "philanthropic"
    ],
    "wof:name":"Congregation Ezras Achim",
    "wof:placetype":"venue"
},
  "geometry": {"coordinates":[-73.6365890503,45.4957618713],"type":"Point"}
}