{
  "type": "Feature",
  "properties": {
    "addr:full":"38 Pth 20 S Camperville MB R0L 0J0",
    "addr:housenumber":"38",
    "addr:postcode":"r0l 0j0",
    "addr:street":"Pth 20 S Camperville",
    "iso:country":"CA",
    "sg:address":"38 Pth 20 S",
    "sg:city":"Camperville",
    "sg:classifiers":[
        {
            "category":"Government",
            "subcategory":"Fire Station",
            "type":"Public Place"
        }
    ],
    "sg:phone":"+1 ",
    "sg:postcode":"R0L 0J0",
    "sg:province":"MB",
    "sg:tags":[
        "department"
    ],
    "wof:name":"Campberville Fire Dept",
    "wof:placetype":"venue"
},
  "geometry": {"coordinates":[-100.145203,51.98592],"type":"Point"}
}