{
  "type": "Feature",
  "properties": {
    "addr:full":"460 4E Rang DE Simpson Saint-Cyrille-DE-Wendover QC J1Z 1T7",
    "addr:housenumber":"460",
    "addr:postcode":"j1z 1t7",
    "addr:street":"4E Rang De Simpson",
    "iso:country":"CA",
    "sg:address":"460 4E Rang DE Simpson",
    "sg:city":"Saint-Cyrille-DE-Wendover",
    "sg:classifiers":[
        {
            "category":"Mining & Drilling",
            "type":"Manufacturing & Wholesale Goods"
        }
    ],
    "sg:phone":"+1 819 397 4325",
    "sg:postcode":"J1Z 1T7",
    "sg:province":"QC",
    "sg:tags":[
        "quarry"
    ],
    "wof:name":"Carrieres Pcm Inc",
    "wof:placetype":"venue"
},
  "geometry": {"coordinates":[-72.45262146,45.9093132019],"type":"Point"}
}