{
  "type": "Feature",
  "properties": {
    "addr:full":"463 Falconbridge Rd Sudbury ON P3A 5N4",
    "addr:housenumber":"463",
    "addr:postcode":"p3a 5n4",
    "addr:street":"Falconbridge Rd",
    "iso:country":"CA",
    "sg:address":"463 Falconbridge Rd",
    "sg:city":"Sudbury",
    "sg:classifiers":[
        {
            "category":"Shopping",
            "type":"Retail Goods"
        }
    ],
    "sg:phone":"+1 705 521 0050",
    "sg:postcode":"P3A 5N4",
    "sg:province":"ON",
    "sg:tags":[
        "pet",
        "shop"
    ],
    "wof:name":"Peter's Reef Pond",
    "wof:placetype":"venue"
},
  "geometry": {"coordinates":[-80.93231964109999,46.5107307434],"type":"Point"}
}