{
  "type": "Feature",
  "properties": {
    "addr:full":"35 Mobile Dr North York ON M4A 2P6",
    "addr:housenumber":"35",
    "addr:postcode":"m4a 2p6",
    "addr:street":"Mobile Dr",
    "iso:country":"CA",
    "sg:address":"35 Mobile Dr",
    "sg:city":"North York",
    "sg:classifiers":[
        {
            "category":"Organizations",
            "subcategory":"Labor Organization",
            "type":"Services"
        }
    ],
    "sg:phone":"+1 416 757 6667",
    "sg:postcode":"M4A 2P6",
    "sg:province":"ON",
    "wof:name":"Osstf District 30 Provincial",
    "wof:placetype":"venue"
},
  "geometry": {"coordinates":[-79.316864,43.724693],"type":"Point"}
}