{
  "type": "Feature",
  "properties": {
    "addr:full":"928 6 Ave SW Calgary AB T2P 0V5",
    "addr:housenumber":"928",
    "addr:postcode":"t2p 0v5",
    "addr:street":"6 Ave Sw",
    "iso:country":"CA",
    "sg:address":"928 6 Ave SW",
    "sg:city":"Calgary",
    "sg:classifiers":[
        {
            "category":"Shopping",
            "subcategory":"Books",
            "type":"Retail Goods"
        }
    ],
    "sg:phone":"+1 403 265 0098",
    "sg:postcode":"T2P 0V5",
    "sg:province":"AB",
    "sg:tags":[
        "dealer"
    ],
    "wof:name":"Words Worth Books",
    "wof:placetype":"venue"
},
  "geometry": {"coordinates":[-114.082000732,51.0481147766],"type":"Point"}
}