{
  "type": "Feature",
  "properties": {
    "addr:full":"58 Dalhousie St Brantford ON N3T 2J2",
    "addr:housenumber":"58",
    "addr:postcode":"n3t 2j2",
    "addr:street":"Dalhousie St",
    "iso:country":"CA",
    "sg:address":"58 Dalhousie St",
    "sg:city":"Brantford",
    "sg:classifiers":[
        {
            "category":"Government",
            "subcategory":"Office",
            "type":"Public Place"
        }
    ],
    "sg:phone":"+1 519 751 6500",
    "sg:postcode":"N3T 2J2",
    "sg:province":"ON",
    "wof:name":"Canada Human Resources Dev",
    "wof:placetype":"venue"
},
  "geometry": {"coordinates":[-80.26560211180001,43.1394004822],"type":"Point"}
}