{
  "type": "Feature",
  "properties": {
    "iso:country":"CA",
    "sg:address":"1092 Kennedy N",
    "sg:city":"Saint-Come-Liniere",
    "sg:classifiers":[
        {
            "category":"Wholesale",
            "subcategory":"Machinery & Supplies",
            "type":"Manufacturing & Wholesale Goods"
        }
    ],
    "sg:phone":"+1 418 685 3864",
    "sg:postcode":"G0M 1J0",
    "sg:province":"QC",
    "sg:tags":[
        "glass",
        "product",
        "fiber"
    ],
    "wof:name":"Michel Loignon Registry",
    "wof:placetype":"venue"
},
  "geometry": {"coordinates":[-70.54637908940001,46.0602531433],"type":"Point"}
}