{
  "type": "Feature",
  "properties": {
    "iso:country":"CA",
    "sg:address":"329 Howe St",
    "sg:city":"Vancouver",
    "sg:classifiers":[
        {
            "category":"Shopping",
            "subcategory":"Jewelry",
            "type":"Retail Goods"
        }
    ],
    "sg:phone":"+1 604 685 8201",
    "sg:postcode":"V6C 3N2",
    "sg:province":"BC",
    "sg:tags":[
        "jeweler"
    ],
    "wof:name":"Crest Jewellers Ltd",
    "wof:placetype":"venue"
},
  "geometry": {"coordinates":[-123.114212036,49.2864074707],"type":"Point"}
}