{
  "type": "Feature",
  "properties": {
    "addr:full":"Scarborough ON M1T 3G3",
    "addr:postcode":"m1t 3g3",
    "iso:country":"CA",
    "sg:city":"Scarborough",
    "sg:classifiers":[
        {
            "category":"Freight",
            "type":"Transportation"
        }
    ],
    "sg:phone":"+1 416 291 4721",
    "sg:postcode":"M1T 3G3",
    "sg:province":"ON",
    "sg:tags":[
        "broker",
        "customs"
    ],
    "wof:name":"Aloha Customs Brokers",
    "wof:placetype":"venue"
},
  "geometry": {"coordinates":[-79.28527069090001,43.7771949768],"type":"Point"}
}