{
  "type": "Feature",
  "properties": {
    "iso:country":"CA",
    "sg:address":"3561 Main St",
    "sg:city":"Vancouver",
    "sg:classifiers":[
        {
            "category":"Shopping",
            "subcategory":"Music",
            "type":"Retail Goods"
        }
    ],
    "sg:phone":"+1 604 324 1229",
    "sg:postcode":"V5V 3N4",
    "sg:province":"BC",
    "sg:tags":[
        "compact",
        "video",
        "disc",
        "tape",
        "record"
    ],
    "wof:name":"Neptoon Records & Cd's",
    "wof:placetype":"venue"
},
  "geometry": {"coordinates":[-123.101036072,49.2532844543],"type":"Point"}
}