{
  "type": "Feature",
  "properties": {
    "addr:full":"Hwy 410 Baie Verte NL A0K 1B0",
    "addr:postcode":"a0k 1b0",
    "addr:street":"Hwy 410",
    "iso:country":"CA",
    "sg:address":"Hwy 410",
    "sg:city":"Baie Verte",
    "sg:classifiers":[
        {
            "category":"Banks & Credit Unions",
            "subcategory":"Bank",
            "type":"Services"
        }
    ],
    "sg:phone":"+1 709 532 8022",
    "sg:postcode":"A0K 1B0",
    "sg:province":"NL",
    "wof:name":"Scotiabank",
    "wof:placetype":"venue"
},
  "geometry": {"coordinates":[-56.1783103943,49.9606361389],"type":"Point"}
}