{
  "type": "Feature",
  "properties": {
    "addr:full":"1850 Bank St Ottawa ON K1V 7Z8",
    "addr:housenumber":"1850",
    "addr:postcode":"k1v 7z8",
    "addr:street":"Bank St",
    "iso:country":"CA",
    "sg:address":"1850 Bank St",
    "sg:city":"Ottawa",
    "sg:classifiers":[
        {
            "category":"Autos & Motor Vehicles",
            "subcategory":"Automobile Sales",
            "type":"Retail Goods"
        }
    ],
    "sg:phone":"+1 613 521 6262",
    "sg:postcode":"K1V 7Z8",
    "sg:province":"ON",
    "sg:tags":[
        "car",
        "dealer"
    ],
    "wof:name":"Walkley Nissan Ltd",
    "wof:placetype":"venue"
},
  "geometry": {"coordinates":[-75.66321600000001,45.369823],"type":"Point"}
}