{
  "type": "Feature",
  "properties": {
    "addr:full":"65 Rycon Dr Yellowknife NT X1A 2V7",
    "addr:housenumber":"65",
    "addr:postcode":"x1a 2v7",
    "addr:street":"Rycon Dr",
    "iso:country":"CA",
    "sg:address":"65 Rycon Dr",
    "sg:city":"Yellowknife",
    "sg:classifiers":[
        {
            "category":"Travel",
            "subcategory":"Hotels & Motels",
            "type":"Entertainment"
        }
    ],
    "sg:phone":"+1 867 920 4654",
    "sg:postcode":"X1A 2V7",
    "sg:province":"NT",
    "sg:tags":[
        "resort",
        "fraternal",
        "organization"
    ],
    "wof:name":"Peterson's Point Lake",
    "wof:placetype":"venue"
},
  "geometry": {"coordinates":[-114.367165,62.444508],"type":"Point"}
}