{
  "type": "Feature",
  "properties": {
    "addr:full":"1525 Ouellette Ave Windsor ON N8X 1K5",
    "addr:housenumber":"1525",
    "addr:postcode":"n8x 1k5",
    "addr:street":"Ouellette Ave",
    "iso:country":"CA",
    "sg:address":"1525 Ouellette Ave",
    "sg:city":"Windsor",
    "sg:classifiers":[
        {
            "category":"Personal",
            "subcategory":"Beauty Salon",
            "type":"Services"
        }
    ],
    "sg:phone":"+1 519 254 8912",
    "sg:postcode":"N8X 1K5",
    "sg:province":"ON",
    "wof:name":"Lee Nails",
    "wof:placetype":"venue"
},
  "geometry": {"coordinates":[-83.027756,42.299652],"type":"Point"}
}