{
  "type": "Feature",
  "properties": {
    "addr:full":"PO Box 38 STN Main Stickney NB E7L 4R8",
    "addr:housenumber":"po box 38",
    "addr:postcode":"e7l 4r8",
    "addr:street":"Stn Main",
    "iso:country":"CA",
    "sg:address":"PO Box 38 STN Main",
    "sg:city":"Stickney",
    "sg:classifiers":[
        {
            "category":"Organizations",
            "subcategory":"Religious Organization",
            "type":"Services"
        }
    ],
    "sg:phone":"+1 506 278 5644",
    "sg:postcode":"E7L 4R8",
    "sg:province":"NB",
    "sg:tags":[
        "church"
    ],
    "wof:name":"Bath United Baptist Church",
    "wof:placetype":"venue"
},
  "geometry": {"coordinates":[-67.570168,46.384506],"type":"Point"}
}