{
  "type": "Feature",
  "properties": {
    "addr:full":"11 New Castle Minden ON K0M 2K0",
    "addr:housenumber":"11",
    "addr:postcode":"k0m 2k0",
    "addr:street":"New",
    "iso:country":"CA",
    "sg:address":"11 New Castle",
    "sg:city":"Minden",
    "sg:classifiers":[
        {
            "category":"Government",
            "subcategory":"Office",
            "type":"Public Place"
        }
    ],
    "sg:phone":"+1 705 286 4085",
    "sg:postcode":"K0M 2K0",
    "sg:province":"ON",
    "sg:tags":[
        "village"
    ],
    "wof:name":"Minden Social Svc Dept",
    "wof:placetype":"venue"
},
  "geometry": {"coordinates":[-78.725899,44.926125],"type":"Point"}
}