{
  "type": "Feature",
  "properties": {
    "addr:full":"RR 4 Clinton ON N0M 1L0",
    "addr:postcode":"n0m 1l0",
    "addr:street":"Rr 4",
    "iso:country":"CA",
    "sg:address":"RR 4",
    "sg:city":"Clinton",
    "sg:classifiers":[
        {
            "category":"Building & Trades",
            "subcategory":"Landscaping Services",
            "type":"Services"
        }
    ],
    "sg:phone":"+1 519 233 3300",
    "sg:postcode":"N0M 1L0",
    "sg:province":"ON",
    "sg:tags":[
        "tree"
    ],
    "wof:name":"Treemendous",
    "wof:placetype":"venue"
},
  "geometry": {"coordinates":[-81.53969600000001,43.617668],"type":"Point"}
}