{
  "type": "Feature",
  "properties": {
    "addr:full":"780 Highway 277 Dutch Settlement NS B2S 2J5",
    "addr:housenumber":"780",
    "addr:postcode":"b2s 2j5",
    "addr:street":"Highway 277",
    "iso:country":"CA",
    "sg:address":"780 Highway 277",
    "sg:city":"Dutch Settlement",
    "sg:classifiers":[
        {
            "category":"Education",
            "subcategory":"School",
            "type":"Public Place"
        }
    ],
    "sg:phone":"+1 902 883 3000",
    "sg:postcode":"B2S 2J5",
    "sg:province":"NS",
    "wof:name":"Dutch Settlement School",
    "wof:placetype":"venue"
},
  "geometry": {"coordinates":[-63.444813,44.988689],"type":"Point"}
}