{
  "type": "Feature",
  "properties": {
    "addr:full":"6451 50 Ave SW Salmon Arm BC V1E 3C2",
    "addr:housenumber":"6451",
    "addr:postcode":"v1e 3c2",
    "addr:street":"50 Ave Sw",
    "iso:country":"CA",
    "sg:address":"6451 50 Ave SW",
    "sg:city":"Salmon Arm",
    "sg:classifiers":[
        {
            "category":"Education",
            "subcategory":"School",
            "type":"Public Place"
        }
    ],
    "sg:phone":"+1 250 832 4950",
    "sg:postcode":"V1E 3C2",
    "sg:province":"BC",
    "wof:name":"North Canoe Elementary",
    "wof:placetype":"venue"
},
  "geometry": {"coordinates":[-119.353424,50.663609],"type":"Point"}
}