{
  "type": "Feature",
  "properties": {
    "addr:full":"205 Forest St E #3A Dunnville ON N1A 3G5",
    "addr:housenumber":"205;3a",
    "addr:postcode":"n1a 3g5",
    "addr:street":"Forest St E #",
    "iso:country":"CA",
    "sg:address":"205 Forest St E #3A",
    "sg:city":"Dunnville",
    "sg:classifiers":[
        {
            "category":"Retail",
            "subcategory":"Auto Repair",
            "type":"Services"
        }
    ],
    "sg:phone":"+1 905 701 1952",
    "sg:postcode":"N1A 3G5",
    "sg:province":"ON",
    "sg:tags":[
        "truck"
    ],
    "wof:name":"Central Transportation Repairs",
    "wof:placetype":"venue"
},
  "geometry": {"coordinates":[-79.612556,42.905651],"type":"Point"}
}