{
  "type": "Feature",
  "properties": {
    "addr:full":"86 Greenwood Cres Regina SK S4X 1G2",
    "addr:housenumber":"86",
    "addr:postcode":"s4x 1g2",
    "addr:street":"Greenwood Cres",
    "iso:country":"CA",
    "sg:address":"86 Greenwood Cres",
    "sg:city":"Regina",
    "sg:classifiers":[
        {
            "category":"Building & Trades",
            "subcategory":"Electrical",
            "type":"Services"
        }
    ],
    "sg:phone":"+1 306 546 2535",
    "sg:postcode":"S4X 1G2",
    "sg:province":"SK",
    "sg:tags":[
        "electric",
        "contractor"
    ],
    "wof:name":"Schocker's Electric",
    "wof:placetype":"venue"
},
  "geometry": {"coordinates":[-104.676682,50.476692],"type":"Point"}
}