{
  "type": "Feature",
  "properties": {
    "addr:full":"NW 29-7-8W Notre Dame DE Lourdes MB R0G 1M0",
    "addr:postcode":"29-7-8w;r0g 1m0",
    "addr:street":"Nw",
    "iso:country":"CA",
    "sg:address":"NW 29-7-8W",
    "sg:city":"Notre Dame DE Lourdes",
    "sg:classifiers":[
        {
            "category":"Farming",
            "subcategory":"Farm & Veterinary Services",
            "type":"Manufacturing & Wholesale Goods"
        }
    ],
    "sg:phone":"+1 204 248 2535",
    "sg:postcode":"R0G 1M0",
    "sg:province":"MB",
    "wof:name":"Porcherie LA Montagne Ltee",
    "wof:placetype":"venue"
},
  "geometry": {"coordinates":[-98.557503,49.532719],"type":"Point"}
}