{
  "type": "Feature",
  "properties": {
    "addr:full":"Gravenhurst ON P1P 1R1",
    "addr:postcode":"p1p 1r1",
    "iso:country":"CA",
    "sg:city":"Gravenhurst",
    "sg:classifiers":[
        {
            "category":"Manufacturing",
            "subcategory":"Buildings",
            "type":"Manufacturing & Wholesale Goods"
        }
    ],
    "sg:phone":"+1 705 687 3494",
    "sg:postcode":"P1P 1R1",
    "sg:province":"ON",
    "sg:tags":[
        "prefabricated"
    ],
    "wof:name":"Viceroy Homes",
    "wof:placetype":"venue"
},
  "geometry": {"coordinates":[-79.3736953735,44.920841217],"type":"Point"}
}