{
  "type": "Feature",
  "properties": {
    "addr:full":"Vancouver BC V5T 1R8",
    "addr:postcode":"v5t 1r8",
    "iso:country":"CA",
    "sg:city":"Vancouver",
    "sg:classifiers":[
        {
            "category":"Professional",
            "subcategory":"Accounting & Tax Preparation",
            "type":"Services"
        }
    ],
    "sg:phone":"+1 604 873 4309",
    "sg:postcode":"V5T 1R8",
    "sg:province":"BC",
    "sg:tags":[
        "accountant"
    ],
    "wof:name":"Yeung & Chong",
    "wof:placetype":"venue"
},
  "geometry": {"coordinates":[-123.10219600000001,49.263851],"type":"Point"}
}