{
  "type": "Feature",
  "properties": {
    "iso:country":"CA",
    "sg:city":"Sundre",
    "sg:classifiers":[
        {
            "category":"Organizations",
            "subcategory":"Religious Organization",
            "type":"Services"
        }
    ],
    "sg:phone":"+1 403 638 3537",
    "sg:postcode":"T0M 1X0",
    "sg:province":"AB",
    "sg:tags":[
        "church"
    ],
    "wof:name":"Gospel Centre",
    "wof:placetype":"venue"
},
  "geometry": {"coordinates":[-114.637596,51.808815],"type":"Point"}
}