{
  "type": "Feature",
  "properties": {
    "addr:full":"5558 Clandeboye Dr Lucan ON N0M 2J0",
    "addr:housenumber":"5558",
    "addr:postcode":"n0m 2j0",
    "addr:street":"Clandeboye Dr",
    "iso:country":"CA",
    "sg:address":"5558 Clandeboye Dr",
    "sg:city":"Lucan",
    "sg:classifiers":[
        {
            "category":"Retail",
            "subcategory":"Auto Repair",
            "type":"Services"
        }
    ],
    "sg:phone":"+1 519 227 0237",
    "sg:postcode":"N0M 2J0",
    "sg:province":"ON",
    "sg:tags":[
        "repairing",
        "automobile"
    ],
    "wof:name":"Clandeboye Mechanical",
    "wof:placetype":"venue"
},
  "geometry": {"coordinates":[-81.451027,43.197739],"type":"Point"}
}