{
  "type": "Feature",
  "properties": {
    "addr:full":"60 Lodestar Lane Whitehorse YT Y1A 6E6",
    "addr:housenumber":"60",
    "addr:postcode":"y1a 6e6",
    "addr:street":"Lodestar Lane",
    "iso:country":"CA",
    "sg:address":"60 Lodestar Lane",
    "sg:city":"Whitehorse",
    "sg:classifiers":[
        {
            "category":"Building & Trades",
            "subcategory":"Equipment Rental",
            "type":"Services"
        }
    ],
    "sg:phone":"+1 867 668 4608",
    "sg:postcode":"Y1A 6E6",
    "sg:province":"YT",
    "sg:tags":[
        "aircraft",
        "leasing",
        "charter"
    ],
    "wof:name":"Big Salmon Air",
    "wof:placetype":"venue"
},
  "geometry": {"coordinates":[-135.05316199999999,60.720871],"type":"Point"}
}