{
  "type": "Feature",
  "properties": {
    "iso:country":"CA",
    "sg:address":"1406 Boul Taschereau",
    "sg:city":"Lemoyne",
    "sg:classifiers":[
        {
            "category":"Manufacturing",
            "subcategory":"Paper Products",
            "type":"Manufacturing & Wholesale Goods"
        }
    ],
    "sg:phone":"+1 450 923 9204",
    "sg:postcode":"J4P 3M6",
    "sg:province":"QC",
    "sg:tags":[
        "graphic",
        "designer"
    ],
    "wof:name":"Lettra Graphic Enr",
    "wof:placetype":"venue"
},
  "geometry": {"coordinates":[-73.49949646,45.512260437],"type":"Point"}
}