{
  "type": "Feature",
  "properties": {
    "iso:country":"CA",
    "sg:address":"344 Montee Du Golf",
    "sg:city":"Mont-Laurier",
    "sg:classifiers":[
        {
            "category":"Sports & Exercise",
            "subcategory":"Golf",
            "type":"Entertainment"
        }
    ],
    "sg:phone":"+1 819 623 6890",
    "sg:postcode":"J9L 3G5",
    "sg:province":"QC",
    "sg:tags":[
        "course"
    ],
    "wof:name":"Club DE Golf Vallee-LA Lievre",
    "wof:placetype":"venue"
},
  "geometry": {"coordinates":[-75.40999603269999,46.5708312988],"type":"Point"}
}