{
  "type": "Feature",
  "properties": {
    "addr:full":"11760 Mitchell Rd Richmond BC V6V 1V8",
    "addr:housenumber":"11760",
    "addr:postcode":"v6v 1v8",
    "addr:street":"Mitchell Rd",
    "iso:country":"CA",
    "sg:address":"11760 Mitchell Rd",
    "sg:city":"Richmond",
    "sg:classifiers":[
        {
            "category":"Wholesale",
            "subcategory":"Scrap",
            "type":"Manufacturing & Wholesale Goods"
        }
    ],
    "sg:phone":"+1 604 324 4656",
    "sg:postcode":"V6V 1V8",
    "sg:province":"BC",
    "sg:tags":[
        "recycling",
        "center"
    ],
    "wof:name":"Richmond Steel Recycling Ltd",
    "wof:placetype":"venue"
},
  "geometry": {"coordinates":[-123.091072,49.202255],"type":"Point"}
}