{
  "type": "Feature",
  "properties": {
    "iso:country":"CA",
    "sg:city":"Red Deer",
    "sg:classifiers":[
        {
            "category":"Professional",
            "subcategory":"Accounting & Tax Preparation",
            "type":"Services"
        }
    ],
    "sg:phone":"+1 403 342 5541",
    "sg:postcode":"T4N 6H2",
    "sg:province":"AB",
    "sg:tags":[
        "accountant"
    ],
    "wof:name":"Collins, Allan E CA",
    "wof:placetype":"venue"
},
  "geometry": {"coordinates":[-113.814460754,52.262462616],"type":"Point"}
}