{
  "type": "Feature",
  "properties": {
    "addr:full":"155 Boul Lachapelle Saint-Jerome QC J7Z 7L2",
    "addr:housenumber":"155",
    "addr:postcode":"j7z 7l2",
    "addr:street":"Boul Lachapelle Saint-Jerome",
    "iso:country":"CA",
    "sg:address":"155 Boul Lachapelle",
    "sg:city":"Saint-Jerome",
    "sg:classifiers":[
        {
            "category":"Autos & Motor Vehicles",
            "subcategory":"Automobile Sales",
            "type":"Retail Goods"
        }
    ],
    "sg:phone":"+1 450 438 3521",
    "sg:postcode":"J7Z 7L2",
    "sg:province":"QC",
    "sg:tags":[
        "car",
        "dealer"
    ],
    "wof:name":"Fugere Pontiac Buick Inc",
    "wof:placetype":"venue"
},
  "geometry": {"coordinates":[-73.99681854249999,45.7551193237],"type":"Point"}
}