{
  "type": "Feature",
  "properties": {
    "addr:full":"Sherwood Park AB T8A 4L7",
    "addr:postcode":"t8a 4l7",
    "iso:country":"CA",
    "sg:city":"Sherwood Park",
    "sg:classifiers":[
        {
            "category":"Travel",
            "subcategory":"Travel Agent",
            "type":"Entertainment"
        }
    ],
    "sg:phone":"+1 780 417 8888",
    "sg:postcode":"T8A 4L7",
    "sg:province":"AB",
    "sg:tags":[
        "agency",
        "bureau"
    ],
    "wof:name":"Cruise Ship Ctr",
    "wof:placetype":"venue"
},
  "geometry": {"coordinates":[-113.329933166,53.5132598877],"type":"Point"}
}