{
  "type": "Feature",
  "properties": {
    "iso:country":"CA",
    "sg:address":"2800 Barton St E",
    "sg:city":"Hamilton",
    "sg:classifiers":[
        {
            "category":"Restaurant",
            "type":"Food & Drink"
        }
    ],
    "sg:phone":"+1 905 578 5663",
    "sg:postcode":"L8E 2J9",
    "sg:province":"ON",
    "wof:name":"Harvey's",
    "wof:placetype":"venue"
},
  "geometry": {"coordinates":[-79.7426452637,43.2328186035],"type":"Point"}
}