{
  "type": "Feature",
  "properties": {
    "iso:country":"CA",
    "sg:address":"1425 Store St",
    "sg:city":"Victoria",
    "sg:classifiers":[
        {
            "category":"Restaurant",
            "type":"Food & Drink"
        }
    ],
    "sg:phone":"+1 250 386 1425",
    "sg:postcode":"V8W 3C6",
    "sg:province":"BC",
    "wof:name":"Cafe Mexico Ltd",
    "wof:placetype":"venue"
},
  "geometry": {"coordinates":[-123.369316101,48.4278755188],"type":"Point"}
}