{
  "type": "Feature",
  "properties": {
    "iso:country":"CA",
    "sg:city":"Duncan",
    "sg:classifiers":[
        {
            "category":"Real Estate",
            "subcategory":"Real Estate Operator",
            "type":"Services"
        }
    ],
    "sg:phone":"+1 250 746 6442",
    "sg:postcode":"V9L 4P5",
    "sg:province":"BC",
    "sg:tags":[
        "apartment"
    ],
    "wof:name":"Royal Alexander Apartments",
    "wof:placetype":"venue"
},
  "geometry": {"coordinates":[-123.70738220200001,48.779094696],"type":"Point"}
}