{
  "type": "Feature",
  "properties": {
    "addr:full":"4906 Boul Kimber Saint-Hubert QC J3Y 7Z8",
    "addr:housenumber":"4906",
    "addr:postcode":"j3y 7z8",
    "addr:street":"Boul Kimber",
    "iso:country":"CA",
    "sg:address":"4906 Boul Kimber",
    "sg:city":"Saint-Hubert",
    "sg:classifiers":[
        {
            "category":"Personal",
            "subcategory":"Beauty Salon",
            "type":"Services"
        }
    ],
    "sg:phone":"+1 450 656 8021",
    "sg:postcode":"J3Y 7Z8",
    "sg:province":"QC",
    "wof:name":"Sylvie Bilodeau Enr",
    "wof:placetype":"venue"
},
  "geometry": {"coordinates":[-73.4404296875,45.4943199158],"type":"Point"}
}