{
  "type": "Feature",
  "properties": {
    "addr:full":"234 Carlton St Toronto ON M5A 2L1",
    "addr:housenumber":"234",
    "addr:postcode":"m5a 2l1",
    "addr:street":"Carlton St",
    "iso:country":"CA",
    "sg:address":"234 Carlton St",
    "sg:city":"Toronto",
    "sg:classifiers":[
        {
            "category":"Organizations",
            "subcategory":"Non-profit Organization",
            "type":"Services"
        }
    ],
    "sg:phone":"+1 416 925 6042",
    "sg:postcode":"M5A 2L1",
    "sg:province":"ON",
    "sg:tags":[
        "addiction",
        "treatment",
        "center"
    ],
    "wof:name":"St Michael's Halfway Homes",
    "wof:placetype":"venue"
},
  "geometry": {"coordinates":[-79.36883544920001,43.6642227173],"type":"Point"}
}