{
  "type": "Feature",
  "properties": {
    "addr:full":"87 Rue Nord Waterloo QC J0E 2N0",
    "addr:housenumber":"87",
    "addr:postcode":"j0e 2n0",
    "addr:street":"Rue Nord",
    "iso:country":"CA",
    "sg:address":"87 Rue Nord",
    "sg:city":"Waterloo",
    "sg:classifiers":[
        {
            "category":"Retail",
            "subcategory":"Repair Shop",
            "type":"Services"
        }
    ],
    "sg:phone":"+1 450 539 0647",
    "sg:postcode":"J0E 2N0",
    "sg:province":"QC",
    "sg:tags":[
        "lock",
        "locksmith"
    ],
    "wof:name":"Serrurier Securitech Locksmith",
    "wof:placetype":"venue"
},
  "geometry": {"coordinates":[-72.51834106450001,45.3544006348],"type":"Point"}
}