{
  "type": "Feature",
  "properties": {
    "addr:full":"2 Forest Dr Corner Brook NL A2H 2N2",
    "addr:housenumber":"2",
    "addr:postcode":"a2h 2n2",
    "addr:street":"Forest Dr",
    "iso:country":"CA",
    "sg:address":"2 Forest Dr",
    "sg:city":"Corner Brook",
    "sg:classifiers":[
        {
            "category":"Travel",
            "subcategory":"Hotels & Motels",
            "type":"Entertainment"
        }
    ],
    "sg:phone":"+1 709 634 4999",
    "sg:postcode":"A2H 2N2",
    "sg:province":"NL",
    "sg:tags":[
        "breakfast",
        "accommodation",
        "bed"
    ],
    "wof:name":"Huxter's Bed & Breakfast",
    "wof:placetype":"venue"
},
  "geometry": {"coordinates":[-57.9203720093,48.9536933899],"type":"Point"}
}