{
  "type": "Feature",
  "properties": {
    "addr:full":"448 Horton St E London ON N6B 1M3",
    "addr:housenumber":"448",
    "addr:postcode":"n6b 1m3",
    "addr:street":"Horton St E",
    "iso:country":"CA",
    "sg:address":"448 Horton St E",
    "sg:city":"London",
    "sg:classifiers":[
        {
            "category":"Health Services",
            "subcategory":"Chiropractor",
            "type":"Services"
        }
    ],
    "sg:phone":"+1 519 663 1166",
    "sg:postcode":"N6B 1M3",
    "sg:province":"ON",
    "wof:name":"Millar Sports Chiropractic",
    "wof:placetype":"venue"
},
  "geometry": {"coordinates":[-81.235626,42.982296],"type":"Point"}
}