{
  "type": "Feature",
  "properties": {
    "iso:country":"CA",
    "sg:city":"Listowel",
    "sg:classifiers":[
        {
            "category":"Travel",
            "subcategory":"Hotels & Motels",
            "type":"Entertainment"
        }
    ],
    "sg:phone":"+1 519 291 1580",
    "sg:postcode":"N4W 3G6",
    "sg:province":"ON",
    "wof:name":"Listowel Country Inn",
    "wof:placetype":"venue"
},
  "geometry": {"coordinates":[-80.9537887573,43.7318191528],"type":"Point"}
}