{
  "type": "Feature",
  "properties": {
    "addr:full":"Surrey BC V4P 1A2",
    "addr:postcode":"v4p 1a2",
    "iso:country":"CA",
    "sg:city":"Surrey",
    "sg:classifiers":[
        {
            "category":"Insurance",
            "subcategory":"Insurance Agent",
            "type":"Services"
        }
    ],
    "sg:phone":"+1 604 536 7111",
    "sg:postcode":"V4P 1A2",
    "sg:province":"BC",
    "wof:name":"Daryl Page Insurance",
    "wof:placetype":"venue"
},
  "geometry": {"coordinates":[-122.808052,49.057507],"type":"Point"}
}