{
  "type": "Feature",
  "properties": {
    "addr:full":"891 Percy Cres Kingston ON K7M 4P3",
    "addr:housenumber":"891",
    "addr:postcode":"k7m 4p3",
    "addr:street":"Percy Cres",
    "iso:country":"CA",
    "sg:address":"891 Percy Cres",
    "sg:city":"Kingston",
    "sg:classifiers":[
        {
            "category":"Professional",
            "type":"Services"
        }
    ],
    "sg:phone":"+1 613 389 1281",
    "sg:postcode":"K7M 4P3",
    "sg:province":"ON",
    "sg:tags":[
        "establishment",
        "engineer"
    ],
    "wof:name":"Menary & Assoc",
    "wof:placetype":"venue"
},
  "geometry": {"coordinates":[-76.5821151733,44.2184524536],"type":"Point"}
}