{
  "type": "Feature",
  "properties": {
    "addr:full":"1743 Rue Des Tulipes Carignan QC J3L 5E7",
    "addr:housenumber":"1743",
    "addr:postcode":"j3l 5e7",
    "addr:street":"Rue Des Tulipes",
    "iso:country":"CA",
    "sg:address":"1743 Rue Des Tulipes",
    "sg:city":"Carignan",
    "sg:classifiers":[
        {
            "category":"Building & Trades",
            "subcategory":"Plumbing",
            "type":"Services"
        }
    ],
    "sg:phone":"+1 450 447 3858",
    "sg:postcode":"J3L 5E7",
    "sg:province":"QC",
    "sg:tags":[
        "contractor"
    ],
    "wof:name":"Plomberie Andre Moquin Inc",
    "wof:placetype":"venue"
},
  "geometry": {"coordinates":[-73.2759628296,45.4801483154],"type":"Point"}
}