{
  "type": "Feature",
  "properties": {
    "addr:full":"5420 49 Ave Red Deer AB T4N 5Z7",
    "addr:housenumber":"5420",
    "addr:postcode":"t4n 5z7",
    "addr:street":"49 Ave",
    "iso:country":"CA",
    "sg:address":"5420 49 Ave",
    "sg:city":"Red Deer",
    "sg:classifiers":[
        {
            "category":"Retail",
            "subcategory":"Auto Repair",
            "type":"Services"
        }
    ],
    "sg:phone":"+1 403 343 1420",
    "sg:postcode":"T4N 5Z7",
    "sg:province":"AB",
    "sg:tags":[
        "automobile",
        "lubrication"
    ],
    "wof:name":"Minit Lube Ltd",
    "wof:placetype":"venue"
},
  "geometry": {"coordinates":[-113.811722,52.27306],"type":"Point"}
}