{
  "type": "Feature",
  "properties": {
    "iso:country":"CA",
    "sg:address":"795 King St E",
    "sg:city":"Hamilton",
    "sg:classifiers":[
        {
            "category":"Government",
            "subcategory":"Office",
            "type":"Public Place"
        }
    ],
    "sg:phone":"+1 905 548 5417",
    "sg:postcode":"L8M 1A8",
    "sg:province":"ON",
    "sg:tags":[
        "apartment",
        "rental",
        "agency",
        "village"
    ],
    "wof:name":"Community Housing Registry",
    "wof:placetype":"venue"
},
  "geometry": {"coordinates":[-79.8436431885,43.2515106201],"type":"Point"}
}