{
  "type": "Feature",
  "properties": {
    "addr:full":"448 Arnhem Dr Oshawa ON L1G 2J4",
    "addr:housenumber":"448",
    "addr:postcode":"l1g 2j4",
    "addr:street":"Arnhem Dr",
    "iso:country":"CA",
    "sg:address":"448 Arnhem Dr",
    "sg:city":"Oshawa",
    "sg:classifiers":[
        {
            "category":"Building & Trades",
            "subcategory":"Electrical",
            "type":"Services"
        }
    ],
    "sg:phone":"+1 905 725 1662",
    "sg:postcode":"L1G 2J4",
    "sg:province":"ON",
    "sg:tags":[
        "water",
        "heater",
        "electric",
        "contractor"
    ],
    "wof:name":"Electric Water Heater Svc",
    "wof:placetype":"venue"
},
  "geometry": {"coordinates":[-78.851868,43.911003],"type":"Point"}
}