{
  "type": "Feature",
  "properties": {
    "iso:country":"CA",
    "sg:city":"Vancouver",
    "sg:classifiers":[
        {
            "category":"Communications",
            "subcategory":"Film & Video Production",
            "type":"Services"
        }
    ],
    "sg:phone":"+1 604 736 3001",
    "sg:postcode":"V6J 1M4",
    "sg:province":"BC",
    "sg:tags":[
        "motion",
        "picture",
        "studio",
        "producer"
    ],
    "wof:name":"Msi Entertainment",
    "wof:placetype":"venue"
},
  "geometry": {"coordinates":[-123.146881103,49.2682571411],"type":"Point"}
}