{
  "type": "Feature",
  "properties": {
    "addr:full":"Vancouver BC V5L 2S8",
    "addr:postcode":"v5l 2s8",
    "iso:country":"CA",
    "sg:city":"Vancouver",
    "sg:classifiers":[
        {
            "category":"Education",
            "subcategory":"Vocational School",
            "type":"Public Place"
        }
    ],
    "sg:phone":"+1 604 251 4322",
    "sg:postcode":"V5L 2S8",
    "sg:province":"BC",
    "sg:tags":[
        "technical",
        "trade"
    ],
    "wof:name":"Photo Documenting Vancouver",
    "wof:placetype":"venue"
},
  "geometry": {"coordinates":[-123.073769,49.272987],"type":"Point"}
}