{
  "type": "Feature",
  "properties": {
    "addr:full":"1050 Cassells St North Bay ON P1B 4A9",
    "addr:housenumber":"1050",
    "addr:postcode":"p1b 4a9",
    "addr:street":"Cassells St",
    "iso:country":"CA",
    "sg:address":"1050 Cassells St",
    "sg:city":"North Bay",
    "sg:classifiers":[
        {
            "category":"Food & Beverages",
            "subcategory":"Bakery",
            "type":"Retail Goods"
        }
    ],
    "sg:phone":"+1 705 474 3233",
    "sg:postcode":"P1B 4A9",
    "sg:province":"ON",
    "sg:tags":[
        "doughnut"
    ],
    "wof:name":"Tim Hortons",
    "wof:placetype":"venue"
},
  "geometry": {"coordinates":[-79.4585342407,46.3169746399],"type":"Point"}
}