{
  "type": "Feature",
  "properties": {
    "addr:full":"1200 King St W Toronto ON M6K 1G4",
    "addr:housenumber":"1200",
    "addr:postcode":"m6k 1g4",
    "addr:street":"King St W",
    "iso:country":"CA",
    "sg:address":"1200 King St W",
    "sg:city":"Toronto",
    "sg:classifiers":[
        {
            "category":"Banks & Credit Unions",
            "subcategory":"Bank",
            "type":"Services"
        }
    ],
    "sg:phone":"+1 416 531 4693",
    "sg:postcode":"M6K 1G4",
    "sg:province":"ON",
    "wof:name":"Cibc",
    "wof:placetype":"venue"
},
  "geometry": {"coordinates":[-79.4275817871,43.6390151978],"type":"Point"}
}