{
  "type": "Feature",
  "properties": {
    "addr:full":"8 Mill St Athens ON K0E 1B0",
    "addr:housenumber":"8",
    "addr:postcode":"k0e 1b0",
    "addr:street":"Mill St",
    "iso:country":"CA",
    "sg:address":"8 Mill St",
    "sg:city":"Athens",
    "sg:classifiers":[
        {
            "category":"Personal",
            "subcategory":"Beauty Salon",
            "type":"Services"
        }
    ],
    "sg:phone":"+1 613 924 2343",
    "sg:postcode":"K0E 1B0",
    "sg:province":"ON",
    "wof:name":"Beverly's Beauty Salon",
    "wof:placetype":"venue"
},
  "geometry": {"coordinates":[-75.947372,44.626751],"type":"Point"}
}