{
  "type": "Feature",
  "properties": {
    "addr:full":"88 Rue St-Isidore Saint-Esprit QC J0K 2L0",
    "addr:housenumber":"88",
    "addr:postcode":"j0k 2l0",
    "addr:street":"Rue St-Isidore",
    "iso:country":"CA",
    "sg:address":"88 Rue St-Isidore",
    "sg:city":"Saint-Esprit",
    "sg:classifiers":[
        {
            "category":"Organizations",
            "subcategory":"Religious Organization",
            "type":"Services"
        }
    ],
    "sg:phone":"+1 450 839 2573",
    "sg:postcode":"J0K 2L0",
    "sg:province":"QC",
    "sg:tags":[
        "church"
    ],
    "wof:name":"Presbytere St-Esprit",
    "wof:placetype":"venue"
},
  "geometry": {"coordinates":[-73.66412353520001,45.9034385681],"type":"Point"}
}