{
  "type": "Feature",
  "properties": {
    "addr:full":"6677 Meadowvale Town Centre Ci Mississauga ON L5N 2R5",
    "addr:housenumber":"6677",
    "addr:postcode":"l5n 2r5",
    "addr:street":"Meadowvale Town Centre Ci",
    "iso:country":"CA",
    "sg:address":"6677 Meadowvale Town Centre Ci",
    "sg:city":"Mississauga",
    "sg:classifiers":[
        {
            "category":"Real Estate",
            "subcategory":"Real Estate Agent",
            "type":"Services"
        }
    ],
    "sg:phone":"+1 905 826 9447",
    "sg:postcode":"L5N 2R5",
    "sg:province":"ON",
    "sg:tags":[
        "mall",
        "management",
        "shopping",
        "center"
    ],
    "wof:name":"Meadowvale Town Ctr",
    "wof:placetype":"venue"
},
  "geometry": {"coordinates":[-79.75960540769999,43.5814361572],"type":"Point"}
}