{
  "type": "Feature",
  "properties": {
    "addr:full":"65 Queen St Fort Erie ON L2A 1T7",
    "addr:housenumber":"65 queen",
    "addr:postcode":"l2a 1t7",
    "addr:street":"St",
    "iso:country":"CA",
    "sg:address":"65 Queen St",
    "sg:city":"Fort Erie",
    "sg:classifiers":[
        {
            "category":"Building & Trades",
            "subcategory":"Plumbing",
            "type":"Services"
        }
    ],
    "sg:phone":"+1 905 871 3629",
    "sg:postcode":"L2A 1T7",
    "sg:province":"ON",
    "sg:tags":[
        "contractor"
    ],
    "wof:name":"R J Denommee Plumbing & Htg",
    "wof:placetype":"venue"
},
  "geometry": {"coordinates":[-78.912903,42.90958],"type":"Point"}
}