{
  "type": "Feature",
  "properties": {
    "addr:full":"4850 Schummer Line Linwood ON N0B 2A0",
    "addr:housenumber":"4850",
    "addr:postcode":"n0b 2a0",
    "addr:street":"Schummer Line",
    "iso:country":"CA",
    "sg:address":"4850 Schummer Line",
    "sg:city":"Linwood",
    "sg:classifiers":[
        {
            "category":"Manufacturing",
            "subcategory":"Tools & Machinery",
            "type":"Manufacturing & Wholesale Goods"
        }
    ],
    "sg:phone":"+1 519 698 2265",
    "sg:postcode":"N0B 2A0",
    "sg:province":"ON",
    "sg:tags":[
        "farm",
        "equipment"
    ],
    "wof:name":"Martin Hayfeeders",
    "wof:placetype":"venue"
},
  "geometry": {"coordinates":[-80.72878300000001,43.553493],"type":"Point"}
}