{
  "type": "Feature",
  "properties": {
    "addr:full":"67 Brock St Kingston ON K7L 1R8",
    "addr:housenumber":"67",
    "addr:postcode":"k7l 1r8",
    "addr:street":"Brock St",
    "iso:country":"CA",
    "sg:address":"67 Brock St",
    "sg:city":"Kingston",
    "sg:classifiers":[
        {
            "category":"Organizations",
            "subcategory":"Professional Association",
            "type":"Services"
        }
    ],
    "sg:phone":"+1 613 548 4453",
    "sg:postcode":"K7L 1R8",
    "sg:province":"ON",
    "wof:name":"Chamber of Commerce",
    "wof:placetype":"venue"
},
  "geometry": {"coordinates":[-76.481956,44.230675],"type":"Point"}
}