{
  "type": "Feature",
  "properties": {
    "addr:full":"Cornwall ON K6J 5R1",
    "addr:postcode":"k6j 5r1",
    "iso:country":"CA",
    "sg:city":"Cornwall",
    "sg:classifiers":[
        {
            "category":"Wholesale",
            "subcategory":"Machinery & Supplies",
            "type":"Manufacturing & Wholesale Goods"
        }
    ],
    "sg:phone":"+1 613 933 0244",
    "sg:postcode":"K6J 5R1",
    "sg:province":"ON",
    "sg:tags":[
        "janitor"
    ],
    "wof:name":"Stormont Window & Floor Clean",
    "wof:placetype":"venue"
},
  "geometry": {"coordinates":[-74.734161,45.027481],"type":"Point"}
}