{
  "type": "Feature",
  "properties": {
    "addr:full":"12291 Tow Hill Rd Masset BC V0T 1M0",
    "addr:housenumber":"12291",
    "addr:postcode":"v0t 1m0",
    "addr:street":"Tow Hill Rd",
    "iso:country":"CA",
    "sg:address":"12291 Tow Hill Rd",
    "sg:city":"Masset",
    "sg:classifiers":[
        {
            "category":"Travel",
            "subcategory":"Hotels & Motels",
            "type":"Entertainment"
        }
    ],
    "sg:phone":"+1 250 626 3333",
    "sg:postcode":"V0T 1M0",
    "sg:province":"BC",
    "sg:tags":[
        "breakfast",
        "accommodation",
        "bed"
    ],
    "wof:name":"Alaska View Lodge",
    "wof:placetype":"venue"
},
  "geometry": {"coordinates":[-132.11686700000001,54.017792],"type":"Point"}
}