{
  "type": "Feature",
  "properties": {
    "addr:full":"223 Fern Rd W Qualicum Beach BC V9K 1S4",
    "addr:housenumber":"223",
    "addr:postcode":"v9k 1s4",
    "addr:street":"Fern Rd W",
    "iso:country":"CA",
    "sg:address":"223 Fern Rd W",
    "sg:city":"Qualicum Beach",
    "sg:classifiers":[
        {
            "category":"Real Estate",
            "subcategory":"Surveying",
            "type":"Services"
        }
    ],
    "sg:phone":"+1 250 752 9121",
    "sg:postcode":"V9K 1S4",
    "sg:province":"BC",
    "sg:tags":[
        "surveyor"
    ],
    "wof:name":"Sims Associates",
    "wof:placetype":"venue"
},
  "geometry": {"coordinates":[-124.44767761200001,49.3463478088],"type":"Point"}
}