{
  "type": "Feature",
  "properties": {
    "iso:country":"CA",
    "sg:address":"Woodcrest Dr",
    "sg:city":"Longlac",
    "sg:classifiers":[
        {
            "category":"Organizations",
            "subcategory":"Religious Organization",
            "type":"Services"
        }
    ],
    "sg:phone":"+1 807 876 4619",
    "sg:postcode":"P0T 2A0",
    "sg:province":"ON",
    "sg:tags":[
        "church"
    ],
    "wof:name":"Longlac Pentecostal Church",
    "wof:placetype":"venue"
},
  "geometry": {"coordinates":[-86.52977752690001,49.7780189514],"type":"Point"}
}