{
  "type": "Feature",
  "properties": {
    "addr:full":"1126 Kensington Rd NW Calgary AB T2N 3P3",
    "addr:housenumber":"1126",
    "addr:postcode":"t2n 3p3",
    "addr:street":"Kensington Rd Nw",
    "iso:country":"CA",
    "sg:address":"1126 Kensington Rd NW",
    "sg:city":"Calgary",
    "sg:classifiers":[
        {
            "category":"Shopping",
            "subcategory":"Clothing, Apparel, & Fashions",
            "type":"Retail Goods"
        }
    ],
    "sg:phone":"+1 403 283 2200",
    "sg:postcode":"T2N 3P3",
    "sg:province":"AB",
    "sg:tags":[
        "lingerie"
    ],
    "wof:name":"Cat's Pyjamas",
    "wof:placetype":"venue"
},
  "geometry": {"coordinates":[-114.08757799999999,51.052704],"type":"Point"}
}