{
  "type": "Feature",
  "properties": {
    "addr:full":"233 Rutland Rd N Kelowna BC V1X 3B1",
    "addr:housenumber":"233",
    "addr:postcode":"v1x 3b1",
    "addr:street":"Rutland Rd N",
    "iso:country":"CA",
    "sg:address":"233 Rutland Rd N",
    "sg:city":"Kelowna",
    "sg:classifiers":[
        {
            "category":"Restaurant",
            "type":"Food & Drink"
        }
    ],
    "sg:phone":"+1 250 765 1129",
    "sg:postcode":"V1X 3B1",
    "sg:province":"BC",
    "wof:name":"Imperial Banquet Restaurant",
    "wof:placetype":"venue"
},
  "geometry": {"coordinates":[-119.386742,49.890839],"type":"Point"}
}