{
  "type": "Feature",
  "properties": {
    "addr:full":"Calgary AB T2E 6V8",
    "addr:postcode":"t2e 6v8",
    "iso:country":"CA",
    "sg:city":"Calgary",
    "sg:classifiers":[
        {
            "category":"Recreation",
            "type":"Entertainment"
        }
    ],
    "sg:phone":"+1 403 291 9124",
    "sg:postcode":"T2E 6V8",
    "sg:province":"AB",
    "sg:tags":[
        "martial",
        "arts",
        "instruction"
    ],
    "wof:name":"Victory Martial Arts Studio",
    "wof:placetype":"venue"
},
  "geometry": {"coordinates":[-114.005325,51.083035],"type":"Point"}
}