{
  "type": "Feature",
  "properties": {
    "addr:full":"1523 Prairie Ave Port Coquitlam BC V3B 1T5",
    "addr:housenumber":"1523",
    "addr:postcode":"v3b 1t5",
    "addr:street":"Prairie Ave",
    "iso:country":"CA",
    "sg:address":"1523 Prairie Ave",
    "sg:city":"Port Coquitlam",
    "sg:classifiers":[
        {
            "category":"Autos & Motor Vehicles",
            "subcategory":"Fuel & Gas Station",
            "type":"Retail Goods"
        }
    ],
    "sg:phone":"+1 604 942 4513",
    "sg:postcode":"V3B 1T5",
    "sg:province":"BC",
    "sg:tags":[
        "oil"
    ],
    "wof:name":"Coquitlam Service",
    "wof:placetype":"venue"
},
  "geometry": {"coordinates":[-122.756874084,49.2714042664],"type":"Point"}
}