{
  "type": "Feature",
  "properties": {
    "addr:full":"28 Cayuga St N Cayuga ON N0A 1E0",
    "addr:housenumber":"28",
    "addr:postcode":"n0a 1e0",
    "addr:street":"Cayuga St N",
    "iso:country":"CA",
    "sg:address":"28 Cayuga St N",
    "sg:city":"Cayuga",
    "sg:classifiers":[
        {
            "category":"Education",
            "subcategory":"Library",
            "type":"Public Place"
        }
    ],
    "sg:phone":"+1 905 772 5726",
    "sg:postcode":"N0A 1E0",
    "sg:province":"ON",
    "wof:name":"Cayuga Public Library",
    "wof:placetype":"venue"
},
  "geometry": {"coordinates":[-79.85814666749999,42.9512405396],"type":"Point"}
}