{
  "type": "Feature",
  "properties": {
    "addr:full":"Toronto ON M4S 3B1",
    "addr:postcode":"m4s 3b1",
    "iso:country":"CA",
    "sg:city":"Toronto",
    "sg:classifiers":[
        {
            "category":"Professional",
            "subcategory":"Lawyer & Legal Services",
            "type":"Services"
        }
    ],
    "sg:phone":"+1 416 480 9582",
    "sg:postcode":"M4S 3B1",
    "sg:province":"ON",
    "sg:tags":[
        "attorney"
    ],
    "wof:name":"Kuuskne, Enn Allan",
    "wof:placetype":"venue"
},
  "geometry": {"coordinates":[-79.39634700000001,43.705303],"type":"Point"}
}