{
  "type": "Feature",
  "properties": {
    "addr:full":"4696 Rue DE LA Sarcelle Saint-Augustin-DE-Desmaures QC G3A 1Y8",
    "addr:housenumber":"4696",
    "addr:postcode":"qc g3a 1y8",
    "addr:street":"Rue De La Sarcelle",
    "iso:country":"CA",
    "sg:address":"4696 Rue DE LA Sarcelle",
    "sg:city":"Saint-Augustin-DE-Desmaures",
    "sg:classifiers":[
        {
            "category":"Manufacturing",
            "subcategory":"Printing",
            "type":"Manufacturing & Wholesale Goods"
        }
    ],
    "sg:phone":"+1 418 622 2626",
    "sg:postcode":"G3A 1Y8",
    "sg:province":"QC",
    "sg:tags":[
        "printer",
        "business",
        "form",
        "system"
    ],
    "wof:name":"Gestion MI-Ro pm Inc",
    "wof:placetype":"venue"
},
  "geometry": {"coordinates":[-71.378174,46.738392],"type":"Point"}
}