{
  "type": "Feature",
  "properties": {
    "addr:full":"Brandon MB R7A 5A8",
    "addr:postcode":"r7a 5a8",
    "iso:country":"CA",
    "sg:city":"Brandon",
    "sg:classifiers":[
        {
            "category":"Shopping",
            "type":"Retail Goods"
        }
    ],
    "sg:phone":"+1 204 726 5383",
    "sg:postcode":"R7A 5A8",
    "sg:province":"MB",
    "sg:tags":[
        "hearing",
        "equipment",
        "supply",
        "impaired"
    ],
    "wof:name":"Beltone Hearing Aid Ctr",
    "wof:placetype":"venue"
},
  "geometry": {"coordinates":[-99.9616775513,49.8448600769],"type":"Point"}
}