{
  "type": "Feature",
  "properties": {
    "addr:full":"5768 Cowrie St Sechelt BC V0N 3A0",
    "addr:housenumber":"5768",
    "addr:postcode":"v0n 3a0",
    "addr:street":"Cowrie St",
    "iso:country":"CA",
    "sg:address":"5768 Cowrie St",
    "sg:city":"Sechelt",
    "sg:classifiers":[
        {
            "category":"Health Services",
            "subcategory":"Optometrist",
            "type":"Services"
        }
    ],
    "sg:phone":"+1 604 885 2020",
    "sg:postcode":"V0N 3A0",
    "sg:province":"BC",
    "wof:name":"Sechelt Eye Care Ctr",
    "wof:placetype":"venue"
},
  "geometry": {"coordinates":[-123.761017,49.472546],"type":"Point"}
}