{
  "type": "Feature",
  "properties": {
    "addr:full":"4626 Davis Ave Terrace BC V8G 1X7",
    "addr:housenumber":"4626",
    "addr:postcode":"v8g 1x7",
    "addr:street":"Davis Ave",
    "iso:country":"CA",
    "sg:address":"4626 Davis Ave",
    "sg:city":"Terrace",
    "sg:classifiers":[
        {
            "category":"Retail",
            "subcategory":"Funeral Services",
            "type":"Services"
        }
    ],
    "sg:phone":"+1 250 635 2444",
    "sg:postcode":"V8G 1X7",
    "sg:province":"BC",
    "sg:tags":[
        "director"
    ],
    "wof:name":"Mac Kay's Funeral Svc Ltd",
    "wof:placetype":"venue"
},
  "geometry": {"coordinates":[-128.587784,54.519569],"type":"Point"}
}