{
  "type": "Feature",
  "properties": {
    "addr:full":"50 Southport St Toronto ON M6S 3N3",
    "addr:housenumber":"50",
    "addr:postcode":"m6s 3n3",
    "addr:street":"Southport St",
    "iso:country":"CA",
    "sg:address":"50 Southport St",
    "sg:city":"Toronto",
    "sg:classifiers":[
        {
            "category":"Food & Beverages",
            "subcategory":"Groceries & Convenience Stores",
            "type":"Retail Goods"
        }
    ],
    "sg:phone":"+1 416 762 4928",
    "sg:postcode":"M6S 3N3",
    "sg:province":"ON",
    "sg:tags":[
        "grocer"
    ],
    "wof:name":"Value Mart",
    "wof:placetype":"venue"
},
  "geometry": {"coordinates":[-79.471824646,43.637588501],"type":"Point"}
}