{
  "type": "Feature",
  "properties": {
    "iso:country":"CA",
    "sg:city":"Hamilton",
    "sg:classifiers":[
        {
            "category":"Shopping",
            "type":"Retail Goods"
        }
    ],
    "sg:phone":"+1 905 575 9797",
    "sg:postcode":"L9A 5C5",
    "sg:province":"ON",
    "sg:tags":[
        "orthopedic",
        "appliance",
        "shoes"
    ],
    "wof:name":"Bio Ped Foot Care Ctr",
    "wof:placetype":"venue"
},
  "geometry": {"coordinates":[-79.8638839722,43.2194595337],"type":"Point"}
}