{
  "type": "Feature",
  "properties": {
    "iso:country":"CA",
    "sg:address":"3205 31 Ave",
    "sg:city":"Vernon",
    "sg:classifiers":[
        {
            "category":"Organizations",
            "subcategory":"Professional Association",
            "type":"Services"
        }
    ],
    "sg:phone":"+1 250 545 8572",
    "sg:postcode":"V1T 2H2",
    "sg:province":"BC",
    "wof:name":"Social Planning Council",
    "wof:placetype":"venue"
},
  "geometry": {"coordinates":[-119.273986816,50.2646713257],"type":"Point"}
}