{
  "type": "Feature",
  "properties": {
    "iso:country":"CA",
    "sg:address":"491 Rideau St",
    "sg:city":"Ottawa",
    "sg:classifiers":[
        {
            "category":"Shopping",
            "type":"Retail Goods"
        }
    ],
    "sg:phone":"+1 613 241 2147",
    "sg:postcode":"K1N 5Z5",
    "sg:province":"ON",
    "sg:tags":[
        "video",
        "disc",
        "tape",
        "miscellaneous",
        "store"
    ],
    "wof:name":"Adult Video Warehouse",
    "wof:placetype":"venue"
},
  "geometry": {"coordinates":[-75.679268,45.431633],"type":"Point"}
}