{
  "type": "Feature",
  "properties": {
    "iso:country":"CA",
    "sg:address":"98 Rockwell Dr",
    "sg:city":"Harrison Hot Springs",
    "sg:classifiers":[
        {
            "category":"Organizations",
            "subcategory":"Professional Association",
            "type":"Services"
        }
    ],
    "sg:phone":"+1 604 796 2723",
    "sg:postcode":"V0M 1K0",
    "sg:province":"BC",
    "wof:name":"Kent Harrison Arts Counsel",
    "wof:placetype":"venue"
},
  "geometry": {"coordinates":[-121.77268219,49.3068275452],"type":"Point"}
}