{
  "type": "Feature",
  "properties": {
    "addr:full":"280 Shields Crt Markham ON L3R 8V2",
    "addr:housenumber":"280",
    "addr:postcode":"l3r 8v2",
    "addr:street":"Shields Crt",
    "iso:country":"CA",
    "sg:address":"280 Shields Crt",
    "sg:city":"Markham",
    "sg:classifiers":[
        {
            "category":"Wholesale",
            "subcategory":"Computers",
            "type":"Manufacturing & Wholesale Goods"
        }
    ],
    "sg:phone":"+1 905 513 6388",
    "sg:postcode":"L3R 8V2",
    "sg:province":"ON",
    "wof:name":"Cotec Advance Systems",
    "wof:placetype":"venue"
},
  "geometry": {"coordinates":[-79.36286200000001,43.831085],"type":"Point"}
}