{
  "type": "Feature",
  "properties": {
    "iso:country":"CA",
    "sg:address":"306 Rue Principale",
    "sg:city":"Brownsburg-Chatham",
    "sg:classifiers":[
        {
            "category":"Retail",
            "subcategory":"Funeral Services",
            "type":"Services"
        }
    ],
    "sg:phone":"+1 450 533 6503",
    "sg:postcode":"J8G 2Z8",
    "sg:province":"QC",
    "sg:tags":[
        "director"
    ],
    "wof:name":"Salon Funeraire Mozart",
    "wof:placetype":"venue"
},
  "geometry": {"coordinates":[-74.4104690552,45.6776428223],"type":"Point"}
}