{
  "type": "Feature",
  "properties": {
    "iso:country":"CA",
    "sg:address":"108 Inverness Rise SE",
    "sg:city":"Calgary",
    "sg:classifiers":[
        {
            "category":"Communications",
            "subcategory":"Film & Video Production",
            "type":"Services"
        }
    ],
    "sg:phone":"+1 403 257 2060",
    "sg:postcode":"T2Z 2X1",
    "sg:province":"AB",
    "sg:tags":[
        "taping"
    ],
    "wof:name":"Dvi Digital Video Imaging",
    "wof:placetype":"venue"
},
  "geometry": {"coordinates":[-113.971557617,50.9141311646],"type":"Point"}
}