{
  "type": "Feature",
  "properties": {
    "addr:full":"6055 Monterey Rd Prince George BC V2K 4M2",
    "addr:housenumber":"6055",
    "addr:postcode":"v2k 4m2",
    "addr:street":"Monterey Rd",
    "iso:country":"CA",
    "sg:address":"6055 Monterey Rd",
    "sg:city":"Prince George",
    "sg:classifiers":[
        {
            "category":"Restaurant",
            "type":"Food & Drink"
        }
    ],
    "sg:phone":"+1 250 962 8202",
    "sg:postcode":"V2K 4M2",
    "sg:province":"BC",
    "wof:name":"Hart Wheel Inn Restaurant",
    "wof:placetype":"venue"
},
  "geometry": {"coordinates":[-122.77164500000001,53.979069],"type":"Point"}
}