{
  "type": "Feature",
  "properties": {
    "addr:full":"585 Weber St N Waterloo ON N2V 1V8",
    "addr:housenumber":"585",
    "addr:postcode":"n2v 1v8",
    "addr:street":"Weber St N",
    "iso:country":"CA",
    "sg:address":"585 Weber St N",
    "sg:city":"Waterloo",
    "sg:classifiers":[
        {
            "category":"Cinema",
            "subcategory":"Movie Rental",
            "type":"Entertainment"
        }
    ],
    "sg:phone":"+1 519 746 6054",
    "sg:postcode":"N2V 1V8",
    "sg:province":"ON",
    "sg:tags":[
        "leasing",
        "video",
        "disc",
        "tape"
    ],
    "wof:name":"Rogers Video",
    "wof:placetype":"venue"
},
  "geometry": {"coordinates":[-80.54991912840001,43.4963798523],"type":"Point"}
}