{
  "type": "Feature",
  "properties": {
    "addr:full":"PO Box 67005 Rpo Northland Vlg Calgary AB T2L 2L2",
    "addr:housenumber":"po box",
    "addr:postcode":"67005;t2l 2l2",
    "iso:country":"CA",
    "sg:address":"PO Box 67005 Rpo Northland Vlg",
    "sg:city":"Calgary",
    "sg:classifiers":[
        {
            "category":"Real Estate",
            "subcategory":"Real Estate Agent",
            "type":"Services"
        }
    ],
    "sg:phone":"+1 403 286 6886",
    "sg:postcode":"T2L 2L2",
    "sg:province":"AB",
    "wof:name":"Schultz Realty Inc",
    "wof:placetype":"venue"
},
  "geometry": {"coordinates":[-114.063194275,51.0450744629],"type":"Point"}
}