{
  "type": "Feature",
  "properties": {
    "addr:full":"4435 Burnside Line Orillia ON L3V 7X8",
    "addr:housenumber":"4435",
    "addr:postcode":"l3v 7x8",
    "addr:street":"Burnside Line",
    "iso:country":"CA",
    "sg:address":"4435 Burnside Line",
    "sg:city":"Orillia",
    "sg:classifiers":[
        {
            "category":"Shopping",
            "subcategory":"Pharmacy",
            "type":"Retail Goods"
        }
    ],
    "sg:phone":"+1 705 326 7373",
    "sg:postcode":"L3V 7X8",
    "sg:province":"ON",
    "wof:name":"Shoppers Drug Mart",
    "wof:placetype":"venue"
},
  "geometry": {"coordinates":[-79.435043335,44.6268310547],"type":"Point"}
}