{
  "type": "Feature",
  "properties": {
    "addr:full":"Kelowna BC V1V 1Y5",
    "addr:postcode":"v1v 1y5",
    "iso:country":"CA",
    "sg:city":"Kelowna",
    "sg:classifiers":[
        {
            "category":"Banks & Credit Unions",
            "subcategory":"Investment Brokerage",
            "type":"Services"
        }
    ],
    "sg:phone":"+1 250 861 4971",
    "sg:postcode":"V1V 1Y5",
    "sg:province":"BC",
    "wof:name":"Edward Jones",
    "wof:placetype":"venue"
},
  "geometry": {"coordinates":[-119.447136,49.913761],"type":"Point"}
}