{
  "type": "Feature",
  "properties": {
    "iso:country":"CA",
    "sg:address":"404 Herring Cove Rd",
    "sg:city":"Halifax",
    "sg:classifiers":[
        {
            "category":"Retail",
            "subcategory":"Laundry & Dry Cleaning",
            "type":"Services"
        }
    ],
    "sg:phone":"+1 902 479 1036",
    "sg:postcode":"B3R 1W4",
    "sg:province":"NS",
    "wof:name":"Wash Dry N Fold Laundromat",
    "wof:placetype":"venue"
},
  "geometry": {"coordinates":[-63.6158103943,44.6086997986],"type":"Point"}
}