{
  "type": "Feature",
  "properties": {
    "iso:country":"CA",
    "sg:city":"Vernon",
    "sg:classifiers":[
        {
            "category":"Real Estate",
            "subcategory":"Real Estate Operator",
            "type":"Services"
        }
    ],
    "sg:phone":"+1 250 542 1533",
    "sg:postcode":"V1T 5G4",
    "sg:province":"BC",
    "sg:tags":[
        "management",
        "condominium"
    ],
    "wof:name":"Accent Property Management",
    "wof:placetype":"venue"
},
  "geometry": {"coordinates":[-119.268112183,50.2585334778],"type":"Point"}
}