{
  "type": "Feature",
  "properties": {
    "addr:full":"PO Box 29 Hilliard AB T0B 2B0",
    "addr:housenumber":"po box 29",
    "addr:postcode":"t0b 2b0",
    "iso:country":"CA",
    "sg:address":"PO Box 29",
    "sg:city":"Hilliard",
    "sg:classifiers":[
        {
            "category":"Professional",
            "subcategory":"Computer Services",
            "type":"Services"
        }
    ],
    "sg:phone":"+1 780 764 2088",
    "sg:postcode":"T0B 2B0",
    "sg:province":"AB",
    "sg:tags":[
        "repair"
    ],
    "wof:name":"Peter's Computer Troubleshooot",
    "wof:placetype":"venue"
},
  "geometry": {"coordinates":[-112.48086499999999,53.64077],"type":"Point"}
}