{
  "type": "Feature",
  "properties": {
    "addr:full":"2409 Albert St N Regina SK S4P 3E1",
    "addr:housenumber":"2409",
    "addr:postcode":"s4p 3e1",
    "addr:street":"Albert St N",
    "iso:country":"CA",
    "sg:address":"2409 Albert St N",
    "sg:city":"Regina",
    "sg:classifiers":[
        {
            "category":"Mining & Drilling",
            "type":"Manufacturing & Wholesale Goods"
        }
    ],
    "sg:phone":"+1 306 949 6606",
    "sg:postcode":"S4P 3E1",
    "sg:province":"SK",
    "sg:tags":[
        "contractor"
    ],
    "wof:name":"Thyssen Mining Construction",
    "wof:placetype":"venue"
},
  "geometry": {"coordinates":[-104.61807251,50.4404563904],"type":"Point"}
}