{
  "type": "Feature",
  "properties": {
    "addr:full":"5151 Boul Thimens Saint-Laurent QC H4R 2C8",
    "addr:housenumber":"5151",
    "addr:postcode":"h4r 2c8",
    "addr:street":"Boul Thimens",
    "iso:country":"CA",
    "sg:address":"5151 Boul Thimens",
    "sg:city":"Saint-Laurent",
    "sg:classifiers":[
        {
            "category":"Wholesale",
            "subcategory":"Home Furnishings",
            "type":"Manufacturing & Wholesale Goods"
        }
    ],
    "sg:phone":"+1 514 748 6721",
    "sg:postcode":"H4R 2C8",
    "sg:province":"QC",
    "sg:tags":[
        "housewares"
    ],
    "wof:name":"Accent Home Products Ltd",
    "wof:placetype":"venue"
},
  "geometry": {"coordinates":[-73.72663116459999,45.49659729],"type":"Point"}
}