{
  "type": "Feature",
  "properties": {
    "addr:full":"105 Gibson Dr Markham ON L3R 3K7",
    "addr:housenumber":"105",
    "addr:postcode":"l3r 3k7",
    "addr:street":"Gibson Dr",
    "iso:country":"CA",
    "sg:address":"105 Gibson Dr",
    "sg:city":"Markham",
    "sg:classifiers":[
        {
            "category":"Manufacturing",
            "subcategory":"Metals",
            "type":"Manufacturing & Wholesale Goods"
        }
    ],
    "sg:phone":"+1 905 415 1644",
    "sg:postcode":"L3R 3K7",
    "sg:province":"ON",
    "sg:tags":[
        "equipment",
        "heating",
        "system"
    ],
    "wof:name":"Alumatube Radiant Heaters",
    "wof:placetype":"venue"
},
  "geometry": {"coordinates":[-79.32862900000001,43.823135],"type":"Point"}
}