{
  "type": "Feature",
  "properties": {
    "iso:country":"CA",
    "sg:address":"1 Laidlaw Blvd",
    "sg:city":"Markham",
    "sg:classifiers":[
        {
            "category":"Retail",
            "subcategory":"Auto Repair",
            "type":"Services"
        }
    ],
    "sg:phone":"+1 905 472 5353",
    "sg:postcode":"L3P 1W5",
    "sg:province":"ON",
    "sg:tags":[
        "body",
        "automobile",
        "painting"
    ],
    "wof:name":"Maaco Auto Painting & Bodywork",
    "wof:placetype":"venue"
},
  "geometry": {"coordinates":[-79.2775726318,43.8691940308],"type":"Point"}
}