{
  "type": "Feature",
  "properties": {
    "addr:full":"Montreal QC H2Y 1N3",
    "addr:postcode":"h2y 1n3",
    "iso:country":"CA",
    "sg:city":"Montreal",
    "sg:classifiers":[
        {
            "category":"Banks & Credit Unions",
            "subcategory":"Investment Brokerage",
            "type":"Services"
        }
    ],
    "sg:phone":"+1 514 843 3332",
    "sg:postcode":"H2Y 1N3",
    "sg:province":"QC",
    "sg:tags":[
        "consultant",
        "planning",
        "financial"
    ],
    "wof:name":"Global Finance",
    "wof:placetype":"venue"
},
  "geometry": {"coordinates":[-73.558876,45.502983],"type":"Point"}
}