{
  "type": "Feature",
  "properties": {
    "iso:country":"CA",
    "sg:address":"4473 Regional Rd 35",
    "sg:city":"Azilda",
    "sg:classifiers":[
        {
            "category":"Building & Trades",
            "subcategory":"Construction",
            "type":"Services"
        }
    ],
    "sg:phone":"+1 705 983 2284",
    "sg:postcode":"P0M 1B0",
    "sg:province":"ON",
    "sg:tags":[
        "excavating",
        "contractor"
    ],
    "wof:name":"Theriault Construction",
    "wof:placetype":"venue"
},
  "geometry": {"coordinates":[-81.1237335205,46.5584106445],"type":"Point"}
}