{
  "type": "Feature",
  "properties": {
    "addr:full":"Montreal QC H2V 4L1",
    "addr:postcode":"h2v 4l1",
    "iso:country":"CA",
    "sg:city":"Montreal",
    "sg:classifiers":[
        {
            "category":"Professional",
            "type":"Services"
        }
    ],
    "sg:phone":"+1 514 948 2377",
    "sg:postcode":"H2V 4L1",
    "sg:province":"QC",
    "sg:tags":[
        "sculptor"
    ],
    "wof:name":"Attitudes",
    "wof:placetype":"venue"
},
  "geometry": {"coordinates":[-73.614304,45.528725],"type":"Point"}
}