{
  "type": "Feature",
  "properties": {
    "addr:full":"10079 Boul DE Saint-Canut Mirabel QC J7N 1K5",
    "addr:housenumber":"10079",
    "addr:postcode":"j7n 1k5",
    "addr:street":"Boul De Saint-Canut",
    "iso:country":"CA",
    "sg:address":"10079 Boul DE Saint-Canut",
    "sg:city":"Mirabel",
    "sg:classifiers":[
        {
            "category":"Retail",
            "subcategory":"Auto Repair",
            "type":"Services"
        }
    ],
    "sg:phone":"+1 450 436 7887",
    "sg:postcode":"J7N 1K5",
    "sg:province":"QC",
    "sg:tags":[
        "repairing",
        "automobile"
    ],
    "wof:name":"Mecanique Auto Sr",
    "wof:placetype":"venue"
},
  "geometry": {"coordinates":[-74.0811462402,45.7204971313],"type":"Point"}
}