{
  "type": "Feature",
  "properties": {
    "addr:full":"Chelmsford ON P0M 1L0",
    "addr:postcode":"p0m 1l0",
    "iso:country":"CA",
    "sg:city":"Chelmsford",
    "sg:classifiers":[
        {
            "category":"Cinema",
            "subcategory":"Movie Rental",
            "type":"Entertainment"
        }
    ],
    "sg:phone":"+1 705 855 1999",
    "sg:postcode":"P0M 1L0",
    "sg:province":"ON",
    "sg:tags":[
        "leasing",
        "video",
        "disc",
        "tape"
    ],
    "wof:name":"Bianco's Movie Supercenters",
    "wof:placetype":"venue"
},
  "geometry": {"coordinates":[-81.191879,46.568245],"type":"Point"}
}