{
  "type": "Feature",
  "properties": {
    "addr:full":"3536 Plummer Ave New Waterford NS B1H 1Z9",
    "addr:housenumber":"3536",
    "addr:postcode":"b1h 1z9",
    "addr:street":"Plummer Ave",
    "iso:country":"CA",
    "sg:address":"3536 Plummer Ave",
    "sg:city":"New Waterford",
    "sg:classifiers":[
        {
            "category":"Health Services",
            "subcategory":"Medical Lab",
            "type":"Services"
        }
    ],
    "sg:phone":"+1 902 862 7228",
    "sg:postcode":"B1H 1Z9",
    "sg:province":"NS",
    "wof:name":"Island Denture Clinic",
    "wof:placetype":"venue"
},
  "geometry": {"coordinates":[-60.092957,46.2491],"type":"Point"}
}