{
  "type": "Feature",
  "properties": {
    "addr:full":"126 Seaview Dr North Sydney NS B2A 3N3",
    "addr:housenumber":"126",
    "addr:postcode":"b2a 3n3",
    "addr:street":"Seaview Dr",
    "iso:country":"CA",
    "sg:address":"126 Seaview Dr",
    "sg:city":"North Sydney",
    "sg:classifiers":[
        {
            "category":"Autos & Motor Vehicles",
            "subcategory":"Automobile Sales",
            "type":"Retail Goods"
        }
    ],
    "sg:phone":"+1 902 794 4947",
    "sg:postcode":"B2A 3N3",
    "sg:province":"NS",
    "sg:tags":[
        "car",
        "dealer"
    ],
    "wof:name":"Seaview Motors Ltd",
    "wof:placetype":"venue"
},
  "geometry": {"coordinates":[-60.2746353149,46.188419342],"type":"Point"}
}