{
  "type": "Feature",
  "properties": {
    "addr:full":"7007 109 St NW Edmonton AB T6H 3B9",
    "addr:housenumber":"7007",
    "addr:postcode":"t6h 3b9",
    "addr:street":"109 St Nw",
    "iso:country":"CA",
    "sg:address":"7007 109 St NW",
    "sg:city":"Edmonton",
    "sg:classifiers":[
        {
            "category":"Organizations",
            "subcategory":"Religious Organization",
            "type":"Services"
        }
    ],
    "sg:phone":"+1 780 434 8010",
    "sg:postcode":"T6H 3B9",
    "sg:province":"AB",
    "sg:tags":[
        "church"
    ],
    "wof:name":"St Basil's Parish",
    "wof:placetype":"venue"
},
  "geometry": {"coordinates":[-113.51181800000001,53.506725],"type":"Point"}
}