{
  "type": "Feature",
  "properties": {
    "addr:full":"513 King St Bridgewater NS B4V 1B3",
    "addr:housenumber":"513",
    "addr:postcode":"b4v 1b3",
    "addr:street":"King St",
    "iso:country":"CA",
    "sg:address":"513 King St",
    "sg:city":"Bridgewater",
    "sg:classifiers":[
        {
            "category":"Shopping",
            "subcategory":"Optical Goods",
            "type":"Retail Goods"
        }
    ],
    "sg:phone":"+1 902 543 1199",
    "sg:postcode":"B4V 1B3",
    "sg:province":"NS",
    "sg:tags":[
        "optician"
    ],
    "wof:name":"Vogue Optical",
    "wof:placetype":"venue"
},
  "geometry": {"coordinates":[-64.5181427002,44.3769454956],"type":"Point"}
}