{
  "type": "Feature",
  "properties": {
    "iso:country":"CA",
    "sg:address":"65 High St",
    "sg:city":"Baddeck",
    "sg:classifiers":[
        {
            "category":"Health Services",
            "subcategory":"Doctor",
            "type":"Services"
        }
    ],
    "sg:phone":"+1 902 295 2443",
    "sg:postcode":"B0E 1B0",
    "sg:province":"NS",
    "sg:tags":[
        "physician",
        "surgeon"
    ],
    "wof:name":"Baddeck Medical Clinic",
    "wof:placetype":"venue"
},
  "geometry": {"coordinates":[-60.7569923401,46.1015548706],"type":"Point"}
}