{
  "type": "Feature",
  "properties": {
    "addr:full":"St Paul AB T0A 3A0",
    "addr:postcode":"t0a 3a0",
    "iso:country":"CA",
    "sg:city":"St Paul",
    "sg:classifiers":[
        {
            "category":"Insurance",
            "subcategory":"Insurance Agent",
            "type":"Services"
        }
    ],
    "sg:phone":"+1 780 645 2901",
    "sg:postcode":"T0A 3A0",
    "sg:province":"AB",
    "wof:name":"Duchesneau, Denis",
    "wof:placetype":"venue"
},
  "geometry": {"coordinates":[-111.29722599999999,53.990437],"type":"Point"}
}