{
  "type": "Feature",
  "properties": {
    "iso:country":"CA",
    "sg:city":"Mount Albert",
    "sg:classifiers":[
        {
            "category":"Food & Beverages",
            "subcategory":"Specialty",
            "type":"Retail Goods"
        }
    ],
    "sg:phone":"+1 905 473 2703",
    "sg:postcode":"L0G 1M0",
    "sg:province":"ON",
    "sg:tags":[
        "health",
        "diet"
    ],
    "wof:name":"Clean Food Connection",
    "wof:placetype":"venue"
},
  "geometry": {"coordinates":[-79.30949401860001,44.1356163025],"type":"Point"}
}