{
  "type": "Feature",
  "properties": {
    "addr:full":"430 Langside St Winnipeg MB R3B 2T5",
    "addr:housenumber":"430",
    "addr:postcode":"r3b 2t5",
    "addr:street":"Langside St",
    "iso:country":"CA",
    "sg:address":"430 Langside St",
    "sg:city":"Winnipeg",
    "sg:classifiers":[
        {
            "category":"Organizations",
            "subcategory":"Professional Association",
            "type":"Services"
        }
    ],
    "sg:phone":"+1 204 783 5000",
    "sg:postcode":"R3B 2T5",
    "sg:province":"MB",
    "wof:name":"Spence Neighbourhood Assn Inc",
    "wof:placetype":"venue"
},
  "geometry": {"coordinates":[-97.156273,49.891758],"type":"Point"}
}