{
  "type": "Feature",
  "properties": {
    "addr:full":"Coteau-Du-Lac QC J0P 1B0",
    "addr:postcode":"j0p 1b0",
    "iso:country":"CA",
    "sg:city":"Coteau-Du-Lac",
    "sg:classifiers":[
        {
            "category":"Utilities",
            "subcategory":"Refuse",
            "type":"Services"
        }
    ],
    "sg:phone":"+1 450 763 0066",
    "sg:postcode":"J0P 1B0",
    "sg:province":"QC",
    "sg:tags":[
        "hazardous",
        "material",
        "storage",
        "removal",
        "equipment",
        "toxic",
        "waste"
    ],
    "wof:name":"Chem-Tech Environnement Inc",
    "wof:placetype":"venue"
},
  "geometry": {"coordinates":[-74.1982803345,45.2962417603],"type":"Point"}
}