{
  "type": "Feature",
  "properties": {
    "addr:full":"300 Randall St Oakville ON L6J 1R1",
    "addr:housenumber":"300",
    "addr:postcode":"l6j 1r1",
    "addr:street":"Randall St",
    "iso:country":"CA",
    "sg:address":"300 Randall St",
    "sg:city":"Oakville",
    "sg:classifiers":[
        {
            "category":"Personal",
            "subcategory":"Beauty Salon",
            "type":"Services"
        }
    ],
    "sg:phone":"+1 905 845 5321",
    "sg:postcode":"L6J 1R1",
    "sg:province":"ON",
    "wof:name":"Sagio Hairstylists",
    "wof:placetype":"venue"
},
  "geometry": {"coordinates":[-79.667519,43.448627],"type":"Point"}
}