{
  "type": "Feature",
  "properties": {
    "iso:country":"CA",
    "sg:address":"328 Whittier Ave W",
    "sg:city":"Winnipeg",
    "sg:classifiers":[
        {
            "category":"Recreation",
            "type":"Entertainment"
        }
    ],
    "sg:phone":"+1 204 222 8473",
    "sg:postcode":"R2C 1Z8",
    "sg:province":"MB",
    "sg:tags":[
        "center"
    ],
    "wof:name":"Winnipeg Senior Ctr",
    "wof:placetype":"venue"
},
  "geometry": {"coordinates":[-97.010033,49.899761],"type":"Point"}
}