{
  "type": "Feature",
  "properties": {
    "addr:full":"48 Oxford St Toronto ON M5T 1N9",
    "addr:housenumber":"48",
    "addr:postcode":"m5t 1n9",
    "addr:street":"Oxford St",
    "iso:country":"CA",
    "sg:address":"48 Oxford St",
    "sg:city":"Toronto",
    "sg:classifiers":[
        {
            "category":"Professional",
            "subcategory":"Business Services",
            "type":"Services"
        }
    ],
    "sg:phone":"+1 416 925 8570",
    "sg:postcode":"M5T 1N9",
    "sg:province":"ON",
    "sg:tags":[
        "translator",
        "interpreter"
    ],
    "wof:name":"Italian Scientific & Trnsltns",
    "wof:placetype":"venue"
},
  "geometry": {"coordinates":[-79.401878,43.656384],"type":"Point"}
}