{
  "type": "Feature",
  "properties": {
    "addr:full":"5011 50 Ave Leduc AB T9E 6V9",
    "addr:housenumber":"5011",
    "addr:postcode":"t9e 6v9",
    "addr:street":"50 Ave",
    "iso:country":"CA",
    "sg:address":"5011 50 Ave",
    "sg:city":"Leduc",
    "sg:classifiers":[
        {
            "category":"Restaurant",
            "type":"Food & Drink"
        }
    ],
    "sg:phone":"+1 780 986 3122",
    "sg:postcode":"T9E 6V9",
    "sg:province":"AB",
    "wof:name":"Kosmos Restaurant & Lounge",
    "wof:placetype":"venue"
},
  "geometry": {"coordinates":[-113.553032,53.264656],"type":"Point"}
}