{
  "type": "Feature",
  "properties": {
    "iso:country":"CA",
    "sg:address":"34 Charles Tupper Dr",
    "sg:city":"Scarborough",
    "sg:classifiers":[
        {
            "category":"Home & Garden",
            "subcategory":"Building Materials",
            "type":"Retail Goods"
        }
    ],
    "sg:phone":"+1 416 281 1175",
    "sg:postcode":"M1C 2B1",
    "sg:province":"ON",
    "sg:tags":[
        "windows",
        "aluminum"
    ],
    "wof:name":"Pauli Juppi Aluminum Siding",
    "wof:placetype":"venue"
},
  "geometry": {"coordinates":[-79.1447677612,43.7801704407],"type":"Point"}
}