{
  "type": "Feature",
  "properties": {
    "addr:full":"Stoney Creek ON L8E 2K3",
    "addr:postcode":"l8e 2k3",
    "iso:country":"CA",
    "sg:city":"Stoney Creek",
    "sg:classifiers":[
        {
            "category":"Professional",
            "subcategory":"Business Services",
            "type":"Services"
        }
    ],
    "sg:phone":"+1 905 664 2466",
    "sg:postcode":"L8E 2K3",
    "sg:province":"ON",
    "sg:tags":[
        "embroidery"
    ],
    "wof:name":"Excel Embroidery",
    "wof:placetype":"venue"
},
  "geometry": {"coordinates":[-79.734825,43.231586],"type":"Point"}
}