{
  "type": "Feature",
  "properties": {
    "addr:full":"15 Brookpark Cres SW Calgary AB T2W 2W6",
    "addr:housenumber":"15",
    "addr:postcode":"t2w 2w6",
    "addr:street":"Brookpark Cres Sw",
    "iso:country":"CA",
    "sg:address":"15 Brookpark Cres SW",
    "sg:city":"Calgary",
    "sg:classifiers":[
        {
            "category":"Wholesale",
            "subcategory":"Sporting Goods",
            "type":"Manufacturing & Wholesale Goods"
        }
    ],
    "sg:phone":"+1 403 253 6929",
    "sg:postcode":"T2W 2W6",
    "sg:province":"AB",
    "wof:name":"Jim Phelan Sports Enterprises",
    "wof:placetype":"venue"
},
  "geometry": {"coordinates":[-114.116592407,50.958278656],"type":"Point"}
}