{
  "type": "Feature",
  "properties": {
    "addr:full":"34443 Thoreau Ave Abbotsford BC V2S 7H6",
    "addr:postcode":"34443;v2s 7h6",
    "addr:street":"Thoreau Ave",
    "iso:country":"CA",
    "sg:address":"34443 Thoreau Ave",
    "sg:city":"Abbotsford",
    "sg:classifiers":[
        {
            "category":"Personal",
            "subcategory":"Beauty Salon",
            "type":"Services"
        }
    ],
    "sg:phone":"+1 604 852 2231",
    "sg:postcode":"V2S 7H6",
    "sg:province":"BC",
    "wof:name":"Impressions",
    "wof:placetype":"venue"
},
  "geometry": {"coordinates":[-122.270523071,49.0674858093],"type":"Point"}
}