{
  "type": "Feature",
  "properties": {
    "addr:full":"184 Rue Jacques-Cartier E Chicoutimi QC G7H 1Y5",
    "addr:housenumber":"184",
    "addr:postcode":"g7h 1y5",
    "addr:street":"Rue Jacques-Cartier E",
    "iso:country":"CA",
    "sg:address":"184 Rue Jacques-Cartier E",
    "sg:city":"Chicoutimi",
    "sg:classifiers":[
        {
            "category":"Professional",
            "subcategory":"Business Services",
            "type":"Services"
        }
    ],
    "sg:phone":"+1 418 543 0230",
    "sg:postcode":"G7H 1Y5",
    "sg:province":"QC",
    "sg:tags":[
        "notary"
    ],
    "wof:name":"Gagnon Collard Gagnon & Gagnon",
    "wof:placetype":"venue"
},
  "geometry": {"coordinates":[-71.06317138670001,48.4262733459],"type":"Point"}
}