{
  "type": "Feature",
  "properties": {
    "addr:full":"150 Industrial Ave Carleton Place ON K7C 3T2",
    "addr:housenumber":"150",
    "addr:postcode":"k7c 3t2",
    "addr:street":"Industrial Ave",
    "iso:country":"CA",
    "sg:address":"150 Industrial Ave",
    "sg:city":"Carleton Place",
    "sg:classifiers":[
        {
            "category":"Building & Trades",
            "subcategory":"Plumbing",
            "type":"Services"
        }
    ],
    "sg:phone":"+1 613 257 8282",
    "sg:postcode":"K7C 3T2",
    "sg:province":"ON",
    "sg:tags":[
        "conditioning",
        "air",
        "system",
        "contractor"
    ],
    "wof:name":"Carleton Refrigeration & Ac",
    "wof:placetype":"venue"
},
  "geometry": {"coordinates":[-76.147469,45.151554],"type":"Point"}
}