{
  "type": "Feature",
  "properties": {
    "iso:country":"CA",
    "sg:address":"1312 Rang Saint-Denis",
    "sg:city":"Sainte-Foy",
    "sg:classifiers":[
        {
            "category":"Recreation",
            "type":"Entertainment"
        }
    ],
    "sg:phone":"+1 418 872 8205",
    "sg:postcode":"G2E 3L9",
    "sg:province":"QC",
    "sg:tags":[
        "riding",
        "academy"
    ],
    "wof:name":"Centre Equestre L'Excellence",
    "wof:placetype":"venue"
},
  "geometry": {"coordinates":[-71.421959,46.774406],"type":"Point"}
}