{
  "type": "Feature",
  "properties": {
    "addr:full":"Belleville ON K8P 3E1",
    "addr:postcode":"k8p 3e1",
    "iso:country":"CA",
    "sg:city":"Belleville",
    "sg:classifiers":[
        {
            "category":"Shopping",
            "subcategory":"Clothing, Apparel, & Fashions",
            "type":"Retail Goods"
        }
    ],
    "sg:phone":"+1 613 966 1291",
    "sg:postcode":"K8P 3E1",
    "sg:province":"ON",
    "wof:name":"Cotton Ginny",
    "wof:placetype":"venue"
},
  "geometry": {"coordinates":[-77.39651499999999,44.188393],"type":"Point"}
}