{
  "type": "Feature",
  "properties": {
    "addr:full":"124 Rang Saint Antoine Sainte-Sophie-DE-Levrard QC G0X 3C0",
    "addr:housenumber":"124",
    "addr:postcode":"g0x 3c0",
    "addr:street":"Rang Saint Antoine Sainte-Sophie-De-Levrard",
    "iso:country":"CA",
    "sg:address":"124 Rang Saint Antoine",
    "sg:city":"Sainte-Sophie-DE-Levrard",
    "sg:classifiers":[
        {
            "category":"Organizations",
            "subcategory":"Professional Association",
            "type":"Services"
        }
    ],
    "sg:phone":"+1 819 288 5533",
    "sg:postcode":"G0X 3C0",
    "sg:province":"QC",
    "wof:name":"Centre D'Action Benevole",
    "wof:placetype":"venue"
},
  "geometry": {"coordinates":[-72.106522,46.437378],"type":"Point"}
}