{
  "type": "Feature",
  "properties": {
    "addr:full":"1243 Kilborn Pl Ottawa ON K1H 6K9",
    "addr:housenumber":"1243",
    "addr:postcode":"k1h 6k9",
    "addr:street":"Kilborn Pl",
    "iso:country":"CA",
    "sg:address":"1243 Kilborn Pl",
    "sg:city":"Ottawa",
    "sg:classifiers":[
        {
            "category":"Social Services",
            "type":"Services"
        }
    ],
    "sg:phone":"+1 613 733 1118",
    "sg:postcode":"K1H 6K9",
    "sg:province":"ON",
    "sg:tags":[
        "psychotherapist",
        "counselor",
        "marriage",
        "family"
    ],
    "wof:name":"John Affleck Jungian Analyst",
    "wof:placetype":"venue"
},
  "geometry": {"coordinates":[-75.671043396,45.3849639893],"type":"Point"}
}