{
  "type": "Feature",
  "properties": {
    "addr:full":"409 Cedar Ave Kelowna BC V1Y 4X2",
    "addr:housenumber":"409",
    "addr:postcode":"v1y 4x2",
    "addr:street":"Cedar Ave",
    "iso:country":"CA",
    "sg:address":"409 Cedar Ave",
    "sg:city":"Kelowna",
    "sg:classifiers":[
        {
            "category":"Professional",
            "subcategory":"Lawyer & Legal Services",
            "type":"Services"
        }
    ],
    "sg:phone":"+1 250 763 6338",
    "sg:postcode":"V1Y 4X2",
    "sg:province":"BC",
    "sg:tags":[
        "attorney"
    ],
    "wof:name":"Gunnlaugson, Lance C",
    "wof:placetype":"venue"
},
  "geometry": {"coordinates":[-119.49309539799999,49.8617706299],"type":"Point"}
}