{
  "type": "Feature",
  "properties": {
    "addr:full":"4525 Boul Samson Laval QC H7W 2H2",
    "addr:housenumber":"4525",
    "addr:postcode":"h7w 2h2",
    "addr:street":"Boul Samson",
    "iso:country":"CA",
    "sg:address":"4525 Boul Samson",
    "sg:city":"Laval",
    "sg:classifiers":[
        {
            "category":"Home & Garden",
            "subcategory":"Building Materials",
            "type":"Retail Goods"
        }
    ],
    "sg:phone":"+1 450 681 1547",
    "sg:postcode":"H7W 2H2",
    "sg:province":"QC",
    "sg:tags":[
        "door"
    ],
    "wof:name":"Portes & Fenetres Verdun Inc",
    "wof:placetype":"venue"
},
  "geometry": {"coordinates":[-73.7564315796,45.5295715332],"type":"Point"}
}