{
  "type": "Feature",
  "properties": {
    "addr:full":"5 Rue Weredale Park Westmount QC H3Z 1Y5",
    "addr:housenumber":"5",
    "addr:postcode":"h3z 1y5",
    "addr:street":"Rue Weredale Park",
    "iso:country":"CA",
    "sg:address":"5 Rue Weredale Park",
    "sg:city":"Westmount",
    "sg:classifiers":[
        {
            "category":"Social Services",
            "type":"Services"
        }
    ],
    "sg:phone":"+1 514 989 1885",
    "sg:postcode":"H3Z 1Y5",
    "sg:province":"QC",
    "sg:tags":[
        "organization",
        "welfare"
    ],
    "wof:name":"Centres DE LA Jeunesse & DE LA",
    "wof:placetype":"venue"
},
  "geometry": {"coordinates":[-73.58313800000001,45.487305],"type":"Point"}
}