{
  "type": "Feature",
  "properties": {
    "iso:country":"CA",
    "sg:address":"8 Trites Rd",
    "sg:city":"Riverview",
    "sg:classifiers":[
        {
            "category":"Building & Trades",
            "subcategory":"Electrical",
            "type":"Services"
        }
    ],
    "sg:phone":"+1 506 387 4018",
    "sg:postcode":"E1B 2V6",
    "sg:province":"NB",
    "sg:tags":[
        "electric",
        "contractor"
    ],
    "wof:name":"Al's Electric Svc Ltd",
    "wof:placetype":"venue"
},
  "geometry": {"coordinates":[-64.81954193120001,46.0593414307],"type":"Point"}
}