{
  "type": "Feature",
  "properties": {
    "addr:full":"209 Boul Perron E Saint-Simeon-DE-Bonaventure QC G0C 3A0",
    "addr:housenumber":"209",
    "addr:postcode":"g0c 3a0",
    "addr:street":"Boul Perron E Saint-Simeon-De-Bonaventure",
    "iso:country":"CA",
    "sg:address":"209 Boul Perron E",
    "sg:city":"Saint-Simeon-DE-Bonaventure",
    "sg:classifiers":[
        {
            "category":"Personal",
            "subcategory":"Beauty Salon",
            "type":"Services"
        }
    ],
    "sg:phone":"+1 418 534 2754",
    "sg:postcode":"G0C 3A0",
    "sg:province":"QC",
    "wof:name":"Salon Coupe Mode",
    "wof:placetype":"venue"
},
  "geometry": {"coordinates":[-65.494446,48.045422],"type":"Point"}
}