{
  "type": "Feature",
  "properties": {
    "addr:full":"223 Hogg Way Saskatoon SK S7N 3W4",
    "addr:housenumber":"223",
    "addr:postcode":"s7n 3w4",
    "addr:street":"Hogg Way",
    "iso:country":"CA",
    "sg:address":"223 Hogg Way",
    "sg:city":"Saskatoon",
    "sg:classifiers":[
        {
            "category":"Retail",
            "subcategory":"Portrait Studio",
            "type":"Services"
        }
    ],
    "sg:phone":"+1 306 249 4922",
    "sg:postcode":"S7N 3W4",
    "sg:province":"SK",
    "sg:tags":[
        "photography"
    ],
    "wof:name":"Starlight Photography",
    "wof:placetype":"venue"
},
  "geometry": {"coordinates":[-106.57875061,52.1431236267],"type":"Point"}
}