{
  "type": "Feature",
  "properties": {
    "iso:country":"CA",
    "sg:address":"18 Amelia St",
    "sg:city":"Pontypool",
    "sg:classifiers":[
        {
            "category":"Retail",
            "subcategory":"Portrait Studio",
            "type":"Services"
        }
    ],
    "sg:phone":"+1 705 277 2261",
    "sg:postcode":"L0A 1K0",
    "sg:province":"ON",
    "sg:tags":[
        "photographer"
    ],
    "wof:name":"Hunt's Photo Studio & Frame",
    "wof:placetype":"venue"
},
  "geometry": {"coordinates":[-78.6278457642,44.0981864929],"type":"Point"}
}