{
  "type": "Feature",
  "properties": {
    "addr:full":"537 Ontario St St Catharines ON L2N 4N4",
    "addr:housenumber":"537",
    "addr:postcode":"l2n 4n4",
    "addr:street":"Ontario St",
    "iso:country":"CA",
    "sg:address":"537 Ontario St",
    "sg:city":"St Catharines",
    "sg:classifiers":[
        {
            "category":"Food & Beverages",
            "subcategory":"Fruits & Vegetables",
            "type":"Retail Goods"
        }
    ],
    "sg:phone":"+1 905 934 0353",
    "sg:postcode":"L2N 4N4",
    "sg:province":"ON",
    "sg:tags":[
        "produce"
    ],
    "wof:name":"Wright Brothers Produce",
    "wof:placetype":"venue"
},
  "geometry": {"coordinates":[-79.263206,43.188992],"type":"Point"}
}