{
  "type": "Feature",
  "properties": {
    "iso:country":"CA",
    "sg:address":"7018 Smith Industrial Dr",
    "sg:city":"Mcgregor",
    "sg:classifiers":[
        {
            "category":"Freight",
            "type":"Transportation"
        }
    ],
    "sg:phone":"+1 519 726 7111",
    "sg:postcode":"N0R 1J0",
    "sg:province":"ON",
    "sg:tags":[
        "trucking"
    ],
    "wof:name":"Roaring Express Inc",
    "wof:placetype":"venue"
},
  "geometry": {"coordinates":[-82.99363700000001,42.162395],"type":"Point"}
}