{
  "type": "Feature",
  "properties": {
    "addr:full":"Etobicoke ON M9R 1V6",
    "addr:postcode":"m9r 1v6",
    "iso:country":"CA",
    "sg:city":"Etobicoke",
    "sg:classifiers":[
        {
            "category":"Real Estate",
            "subcategory":"Real Estate Agent",
            "type":"Services"
        }
    ],
    "sg:phone":"+1 416 240 1501",
    "sg:postcode":"M9R 1V6",
    "sg:province":"ON",
    "wof:name":"William Martin Real Estate",
    "wof:placetype":"venue"
},
  "geometry": {"coordinates":[-79.56591,43.693558],"type":"Point"}
}