{
  "type": "Feature",
  "properties": {
    "addr:full":"2157 University Ave W Windsor ON N9B 1E3",
    "addr:housenumber":"2157",
    "addr:postcode":"n9b 1e3",
    "addr:street":"University Ave W",
    "iso:country":"CA",
    "sg:address":"2157 University Ave W",
    "sg:city":"Windsor",
    "sg:classifiers":[
        {
            "category":"Personal",
            "subcategory":"Shoe Repair & Shine",
            "type":"Services"
        }
    ],
    "sg:phone":"+1 519 252 4541",
    "sg:postcode":"N9B 1E3",
    "sg:province":"ON",
    "sg:tags":[
        "repairing",
        "boot"
    ],
    "wof:name":"University Shoe Repair",
    "wof:placetype":"venue"
},
  "geometry": {"coordinates":[-83.06347700000001,42.310207],"type":"Point"}
}