{
  "type": "Feature",
  "properties": {
    "iso:country":"CA",
    "sg:address":"7076 Bonpart Pl",
    "sg:city":"Saint-Leonard",
    "sg:classifiers":[
        {
            "category":"Building & Trades",
            "subcategory":"Construction",
            "type":"Services"
        }
    ],
    "sg:phone":"+1 514 256 1703",
    "sg:postcode":"H1S 1Y3",
    "sg:province":"QC",
    "sg:tags":[
        "general",
        "contractor"
    ],
    "wof:name":"Charpenterie & Menuiserie DE",
    "wof:placetype":"venue"
},
  "geometry": {"coordinates":[-73.5739822388,45.5844192505],"type":"Point"}
}