{
  "type": "Feature",
  "properties": {
    "addr:full":"1824 Pandora St Vancouver BC V5L 1M5",
    "addr:housenumber":"1824",
    "addr:postcode":"v5l 1m5",
    "addr:street":"Pandora St",
    "iso:country":"CA",
    "sg:address":"1824 Pandora St",
    "sg:city":"Vancouver",
    "sg:classifiers":[
        {
            "category":"Wholesale",
            "subcategory":"Machinery & Supplies",
            "type":"Manufacturing & Wholesale Goods"
        }
    ],
    "sg:phone":"+1 604 251 3554",
    "sg:postcode":"V5L 1M5",
    "sg:province":"BC",
    "sg:tags":[
        "equipment",
        "hydraulic"
    ],
    "wof:name":"Wriason Seals Ltd",
    "wof:placetype":"venue"
},
  "geometry": {"coordinates":[-123.067375,49.28297],"type":"Point"}
}