{
  "type": "Feature",
  "properties": {
    "addr:full":"Nelson BC V1L 4B7",
    "addr:postcode":"bc v1l 4b7",
    "iso:country":"CA",
    "sg:city":"Nelson",
    "sg:classifiers":[
        {
            "category":"Travel",
            "subcategory":"Hotels & Motels",
            "type":"Entertainment"
        }
    ],
    "sg:phone":"+1 250 352 9133",
    "sg:postcode":"V1L 4B7",
    "sg:province":"BC",
    "sg:tags":[
        "resort"
    ],
    "wof:name":"Peak Freak Expeditions",
    "wof:placetype":"venue"
},
  "geometry": {"coordinates":[-117.294052124,49.4946022034],"type":"Point"}
}