{
  "type": "Feature",
  "properties": {
    "addr:full":"17 Corporate Pl Brantford ON N3R 8A6",
    "addr:housenumber":"17",
    "addr:postcode":"n3r 8a6",
    "addr:street":"Corporate Pl",
    "iso:country":"CA",
    "sg:address":"17 Corporate Pl",
    "sg:city":"Brantford",
    "sg:classifiers":[
        {
            "category":"Professional",
            "subcategory":"Accounting & Tax Preparation",
            "type":"Services"
        }
    ],
    "sg:phone":"+1 519 756 2350",
    "sg:postcode":"N3R 8A6",
    "sg:province":"ON",
    "sg:tags":[
        "accountant"
    ],
    "wof:name":"Bettesworth Johnson",
    "wof:placetype":"venue"
},
  "geometry": {"coordinates":[-80.2300643921,43.1750297546],"type":"Point"}
}