{
  "type": "Feature",
  "properties": {
    "addr:full":"610 3rd Ave W Prince Rupert BC V8J 1M2",
    "addr:housenumber":"610",
    "addr:postcode":"v8j 1m2",
    "addr:street":"3Rd Ave W",
    "iso:country":"CA",
    "sg:address":"610 3rd Ave W",
    "sg:city":"Prince Rupert",
    "sg:classifiers":[
        {
            "category":"Restaurant",
            "type":"Food & Drink"
        }
    ],
    "sg:phone":"+1 250 624 4333",
    "sg:postcode":"V8J 1M2",
    "sg:province":"BC",
    "wof:name":"West End Restaurant Ltd",
    "wof:placetype":"venue"
},
  "geometry": {"coordinates":[-130.32701110799999,54.3115730286],"type":"Point"}
}