{
  "type": "Feature",
  "properties": {
    "addr:full":"42 Memorial Dr North Sydney NS B2A 3M3",
    "addr:housenumber":"42",
    "addr:postcode":"b2a 3m3",
    "addr:street":"Memorial Dr",
    "iso:country":"CA",
    "sg:address":"42 Memorial Dr",
    "sg:city":"North Sydney",
    "sg:classifiers":[
        {
            "category":"Manufacturing",
            "subcategory":"Textiles",
            "type":"Manufacturing & Wholesale Goods"
        }
    ],
    "sg:phone":"+1 902 794 8888",
    "sg:postcode":"B2A 3M3",
    "sg:province":"NS",
    "sg:tags":[
        "rope"
    ],
    "wof:name":"East Coast Rope Ltd",
    "wof:placetype":"venue"
},
  "geometry": {"coordinates":[-60.2514343262,46.2071151733],"type":"Point"}
}