{
  "type": "Feature",
  "properties": {
    "addr:full":"3887 Oak St Vancouver BC V6H 2M6",
    "addr:housenumber":"3887",
    "addr:postcode":"v6h 2m6",
    "addr:street":"Oak St",
    "iso:country":"CA",
    "sg:address":"3887 Oak St",
    "sg:city":"Vancouver",
    "sg:classifiers":[
        {
            "category":"Retail",
            "subcategory":"Veterinary Services",
            "type":"Services"
        }
    ],
    "sg:phone":"+1 604 739 7111",
    "sg:postcode":"V6H 2M6",
    "sg:province":"BC",
    "sg:tags":[
        "veterinarian"
    ],
    "wof:name":"Oak Animal Hospital",
    "wof:placetype":"venue"
},
  "geometry": {"coordinates":[-123.12770080599999,49.251033783],"type":"Point"}
}