{
  "type": "Feature",
  "properties": {
    "addr:full":"Howe Marathon ON P0T 2E0",
    "addr:postcode":"p0t 2e0",
    "iso:country":"CA",
    "sg:address":"Howe",
    "sg:city":"Marathon",
    "sg:classifiers":[
        {
            "category":"Government",
            "subcategory":"Office",
            "type":"Public Place"
        }
    ],
    "sg:phone":"+1 807 229 1186",
    "sg:postcode":"P0T 2E0",
    "sg:province":"ON",
    "wof:name":"Ontario Water Pollution Contrl",
    "wof:placetype":"venue"
},
  "geometry": {"coordinates":[-86.382668,48.709503],"type":"Point"}
}