{
  "type": "Feature",
  "properties": {
    "iso:country":"CA",
    "sg:address":"140 Maple Ave SE",
    "sg:city":"Medicine Hat",
    "sg:classifiers":[
        {
            "category":"Restaurant",
            "type":"Food & Drink"
        }
    ],
    "sg:phone":"+1 403 526 1807",
    "sg:postcode":"T1A 8C1",
    "sg:province":"AB",
    "wof:name":"Moby Dick's Fish & Chips",
    "wof:placetype":"venue"
},
  "geometry": {"coordinates":[-110.671684265,50.0428390503],"type":"Point"}
}