{
  "type": "Feature",
  "properties": {
    "addr:full":"102 Boul DE LA Concorde E Laval QC H7G 2B9",
    "addr:housenumber":"102",
    "addr:postcode":"qc h7g 2b9",
    "addr:street":"Boul De La Concorde E",
    "iso:country":"CA",
    "sg:address":"102 Boul DE LA Concorde E",
    "sg:city":"Laval",
    "sg:classifiers":[
        {
            "category":"Shopping",
            "subcategory":"Clothing, Apparel, & Fashions",
            "type":"Retail Goods"
        }
    ],
    "sg:phone":"+1 450 629 1389",
    "sg:postcode":"H7G 2B9",
    "sg:province":"QC",
    "sg:tags":[
        "item",
        "boutique"
    ],
    "wof:name":"France Mode",
    "wof:placetype":"venue"
},
  "geometry": {"coordinates":[-73.688591,45.572769],"type":"Point"}
}