{
  "type": "Feature",
  "properties": {
    "addr:full":"327 Frank St Ottawa ON K2P 0X7",
    "addr:housenumber":"327",
    "addr:postcode":"k2p 0x7",
    "addr:street":"Frank St",
    "iso:country":"CA",
    "sg:address":"327 Frank St",
    "sg:city":"Ottawa",
    "sg:classifiers":[
        {
            "category":"Health Services",
            "subcategory":"Health Practitioner",
            "type":"Services"
        }
    ],
    "sg:phone":"+1 613 234 6617",
    "sg:postcode":"K2P 0X7",
    "sg:province":"ON",
    "sg:tags":[
        "audiologists"
    ],
    "wof:name":"Olmstead, Eric D",
    "wof:placetype":"venue"
},
  "geometry": {"coordinates":[-75.69152099999999,45.413685],"type":"Point"}
}