{
  "type": "Feature",
  "properties": {
    "addr:full":"Calgary AB T2H 1J5",
    "addr:postcode":"t2h 1j5",
    "iso:country":"CA",
    "sg:city":"Calgary",
    "sg:classifiers":[
        {
            "category":"Manufacturing",
            "subcategory":"Tools & Machinery",
            "type":"Manufacturing & Wholesale Goods"
        }
    ],
    "sg:phone":"+1 403 253 1020",
    "sg:postcode":"T2H 1J5",
    "sg:province":"AB",
    "sg:tags":[
        "equipment",
        "system",
        "automation"
    ],
    "wof:name":"Rockwell Automation Canada Inc",
    "wof:placetype":"venue"
},
  "geometry": {"coordinates":[-114.060143,50.996216],"type":"Point"}
}