{
  "type": "Feature",
  "properties": {
    "iso:country":"CA",
    "sg:city":"Vancouver",
    "sg:classifiers":[
        {
            "category":"Professional",
            "subcategory":"Lawyer & Legal Services",
            "type":"Services"
        }
    ],
    "sg:phone":"+1 604 264 8331",
    "sg:postcode":"V5Z 2M9",
    "sg:province":"BC",
    "sg:tags":[
        "attorney"
    ],
    "wof:name":"Braaten, Sheila",
    "wof:placetype":"venue"
},
  "geometry": {"coordinates":[-123.117675781,49.2335510254],"type":"Point"}
}