{
  "type": "Feature",
  "properties": {
    "iso:country":"CA",
    "sg:city":"Vancouver",
    "sg:classifiers":[
        {
            "category":"Building & Trades",
            "subcategory":"Construction",
            "type":"Services"
        }
    ],
    "sg:phone":"+1 604 662 7034",
    "sg:postcode":"V6E 4A4",
    "sg:province":"BC",
    "sg:tags":[
        "control",
        "corrosion"
    ],
    "wof:name":"Savcor Consulting Inc",
    "wof:placetype":"venue"
},
  "geometry": {"coordinates":[-123.12191,49.287895],"type":"Point"}
}