{
  "type": "Feature",
  "properties": {
    "addr:full":"991 Belle Isle View Blvd Windsor ON N8S 3G6",
    "addr:housenumber":"991",
    "addr:postcode":"n8s 3g6",
    "addr:street":"Belle Isle View Blvd",
    "iso:country":"CA",
    "sg:address":"991 Belle Isle View Blvd",
    "sg:city":"Windsor",
    "sg:classifiers":[
        {
            "category":"Retail",
            "subcategory":"Portrait Studio",
            "type":"Services"
        }
    ],
    "sg:phone":"+1 519 945 8571",
    "sg:postcode":"N8S 3G6",
    "sg:province":"ON",
    "sg:tags":[
        "photographer"
    ],
    "wof:name":"Our Photographer",
    "wof:placetype":"venue"
},
  "geometry": {"coordinates":[-82.946091,42.328197],"type":"Point"}
}