{
  "type": "Feature",
  "properties": {
    "addr:full":"9809 17 St Dawson Creek BC V1G 4B4",
    "addr:housenumber":"9809",
    "addr:postcode":"v1g 4b4",
    "addr:street":"17 St",
    "iso:country":"CA",
    "sg:address":"9809 17 St",
    "sg:city":"Dawson Creek",
    "sg:classifiers":[
        {
            "category":"Building & Trades",
            "subcategory":"Construction",
            "type":"Services"
        }
    ],
    "sg:phone":"+1 250 782 2778",
    "sg:postcode":"V1G 4B4",
    "sg:province":"BC",
    "sg:tags":[
        "excavating",
        "contractor"
    ],
    "wof:name":"Reg Norman Trucking Ltd",
    "wof:placetype":"venue"
},
  "geometry": {"coordinates":[-120.25065600000001,55.762997],"type":"Point"}
}