{
  "type": "Feature",
  "properties": {
    "iso:country":"CA",
    "sg:address":"37 Young St",
    "sg:city":"Alliston",
    "sg:classifiers":[
        {
            "category":"Food & Beverages",
            "subcategory":"Groceries & Convenience Stores",
            "type":"Retail Goods"
        }
    ],
    "sg:phone":"+1 705 435 1405",
    "sg:postcode":"L9R 1B5",
    "sg:province":"ON",
    "sg:tags":[
        "frozen"
    ],
    "wof:name":"M & M Meat Shops",
    "wof:placetype":"venue"
},
  "geometry": {"coordinates":[-79.88002,44.148682],"type":"Point"}
}