{
  "type": "Feature",
  "properties": {
    "addr:full":"8 Copernicus Blvd Brantford ON N3P 1Y4",
    "addr:housenumber":"8",
    "addr:postcode":"n3p 1y4",
    "addr:street":"Copernicus Blvd",
    "iso:country":"CA",
    "sg:address":"8 Copernicus Blvd",
    "sg:city":"Brantford",
    "sg:classifiers":[
        {
            "category":"Manufacturing",
            "subcategory":"Metals",
            "type":"Manufacturing & Wholesale Goods"
        }
    ],
    "sg:phone":"+1 519 758 8111",
    "sg:postcode":"N3P 1Y4",
    "sg:province":"ON",
    "sg:tags":[
        "boiler"
    ],
    "wof:name":"Miura Boiler CO Ltd",
    "wof:placetype":"venue"
},
  "geometry": {"coordinates":[-80.243713,43.180229],"type":"Point"}
}