{
  "type": "Feature",
  "properties": {
    "addr:full":"Montreal QC H2X 3P9",
    "addr:postcode":"h2x 3p9",
    "iso:country":"CA",
    "sg:city":"Montreal",
    "sg:classifiers":[
        {
            "category":"Food & Beverages",
            "subcategory":"Bakery",
            "type":"Retail Goods"
        }
    ],
    "sg:phone":"+1 514 845 2486",
    "sg:postcode":"H2X 3P9",
    "sg:province":"QC",
    "sg:tags":[
        "shop",
        "cookie"
    ],
    "wof:name":"Biscuiterie Place Du Parc Enr",
    "wof:placetype":"venue"
},
  "geometry": {"coordinates":[-73.5749664307,45.510269165],"type":"Point"}
}