{
  "type": "Feature",
  "properties": {
    "addr:full":"Dawson Creek BC V1G 4K6",
    "addr:postcode":"v1g 4k6",
    "iso:country":"CA",
    "sg:city":"Dawson Creek",
    "sg:classifiers":[
        {
            "category":"Shopping",
            "subcategory":"Department Store",
            "type":"Retail Goods"
        }
    ],
    "sg:phone":"+1 250 782 3391",
    "sg:postcode":"V1G 4K6",
    "sg:province":"BC",
    "wof:name":"Zellers",
    "wof:placetype":"venue"
},
  "geometry": {"coordinates":[-120.224236,55.750599],"type":"Point"}
}