{
  "type": "Feature",
  "properties": {
    "addr:full":"393 Birchmount Rd Scarborough ON M1K 1N3",
    "addr:housenumber":"393",
    "addr:postcode":"m1k 1n3",
    "addr:street":"Birchmount Rd",
    "iso:country":"CA",
    "sg:address":"393 Birchmount Rd",
    "sg:city":"Scarborough",
    "sg:classifiers":[
        {
            "category":"Retail",
            "subcategory":"Auto Repair",
            "type":"Services"
        }
    ],
    "sg:phone":"+1 416 691 5353",
    "sg:postcode":"M1K 1N3",
    "sg:province":"ON",
    "sg:tags":[
        "repairing",
        "automobile"
    ],
    "wof:name":"G & T Automotive Ltd",
    "wof:placetype":"venue"
},
  "geometry": {"coordinates":[-79.265793,43.70187],"type":"Point"}
}