{
  "type": "Feature",
  "properties": {
    "addr:full":"Montreal QC H3A 2W5",
    "addr:postcode":"h3a 2w5",
    "iso:country":"CA",
    "sg:city":"Montreal",
    "sg:classifiers":[
        {
            "category":"Professional",
            "subcategory":"Computer Services",
            "type":"Services"
        }
    ],
    "sg:phone":"+1 514 848 9991",
    "sg:postcode":"H3A 2W5",
    "sg:province":"QC",
    "sg:tags":[
        "information",
        "system",
        "consultant"
    ],
    "wof:name":"Malcolm Rosen Software Conslnt",
    "wof:placetype":"venue"
},
  "geometry": {"coordinates":[-73.57501999999999,45.500912],"type":"Point"}
}