{
  "type": "Feature",
  "properties": {
    "iso:country":"CA",
    "sg:address":"315 Boul Labelle",
    "sg:city":"Rosemere",
    "sg:classifiers":[
        {
            "category":"Retail",
            "subcategory":"Animal Services",
            "type":"Services"
        }
    ],
    "sg:phone":"+1 450 437 4893",
    "sg:postcode":"J7A 2H7",
    "sg:province":"QC",
    "sg:tags":[
        "pet",
        "shop",
        "grooming",
        "washing"
    ],
    "wof:name":"Animalerie Aqua Tek",
    "wof:placetype":"venue"
},
  "geometry": {"coordinates":[-73.810669,45.629089],"type":"Point"}
}