{
  "type": "Feature",
  "properties": {
    "addr:full":"5618 Kerrigan Rd Wyoming ON N0N 1T0",
    "addr:housenumber":"5618",
    "addr:postcode":"n0n 1t0",
    "addr:street":"Kerrigan Rd",
    "iso:country":"CA",
    "sg:address":"5618 Kerrigan Rd",
    "sg:city":"Wyoming",
    "sg:classifiers":[
        {
            "category":"Building & Trades",
            "subcategory":"Electrical",
            "type":"Services"
        }
    ],
    "sg:phone":"+1 519 845 0151",
    "sg:postcode":"N0N 1T0",
    "sg:province":"ON",
    "sg:tags":[
        "electric",
        "contractor"
    ],
    "wof:name":"Gare Electric Ltd",
    "wof:placetype":"venue"
},
  "geometry": {"coordinates":[-82.1408233643,42.9673271179],"type":"Point"}
}