{
  "type": "Feature",
  "properties": {
    "iso:country":"CA",
    "sg:city":"Peterborough",
    "sg:classifiers":[
        {
            "category":"Food & Beverages",
            "subcategory":"Groceries & Convenience Stores",
            "type":"Retail Goods"
        }
    ],
    "sg:phone":"+1 705 292 6719",
    "sg:postcode":"K9J 6X2",
    "sg:province":"ON",
    "sg:tags":[
        "grocer"
    ],
    "wof:name":"Ennismore Iga",
    "wof:placetype":"venue"
},
  "geometry": {"coordinates":[-78.32131195069999,44.3007316589],"type":"Point"}
}