{
  "type": "Feature",
  "properties": {
    "iso:country":"CA",
    "sg:address":"3198 Danforth Ave",
    "sg:city":"Scarborough",
    "sg:classifiers":[
        {
            "category":"Shopping",
            "subcategory":"Used Merchandise",
            "type":"Retail Goods"
        }
    ],
    "sg:phone":"+1 416 691 3307",
    "sg:postcode":"M1L 1B7",
    "sg:province":"ON",
    "sg:tags":[
        "second",
        "hand",
        "store",
        "furniture"
    ],
    "wof:name":"Frontier Sales",
    "wof:placetype":"venue"
},
  "geometry": {"coordinates":[-79.283745,43.692322],"type":"Point"}
}