{
  "type": "Feature",
  "properties": {
    "addr:full":"599 Colby Dr # 1 Waterloo ON N2V 1A1",
    "addr:housenumber":"599",
    "addr:postcode":"n2v 1a1",
    "addr:street":"Colby Dr # 1",
    "iso:country":"CA",
    "sg:address":"599 Colby Dr # 1",
    "sg:city":"Waterloo",
    "sg:classifiers":[
        {
            "category":"Building & Trades",
            "subcategory":"Construction",
            "type":"Services"
        }
    ],
    "sg:phone":"+1 519 880 1469",
    "sg:postcode":"N2V 1A1",
    "sg:province":"ON",
    "sg:tags":[
        "roofing",
        "contractor"
    ],
    "wof:name":"Semple Gooder Roofing Ltd",
    "wof:placetype":"venue"
},
  "geometry": {"coordinates":[-80.541298,43.503296],"type":"Point"}
}