{
  "type": "Feature",
  "properties": {
    "addr:full":"66 Rue Fraser Riviere-Du-Loup QC G5R 1C2",
    "addr:housenumber":"66",
    "addr:postcode":"g5r 1c2",
    "addr:street":"Rue Fraser Riviere-Du-Loup",
    "iso:country":"CA",
    "sg:address":"66 Rue Fraser",
    "sg:city":"Riviere-Du-Loup",
    "sg:classifiers":[
        {
            "category":"Building & Trades",
            "subcategory":"Cleaning & Sanitation",
            "type":"Services"
        }
    ],
    "sg:phone":"+1 418 862 6393",
    "sg:postcode":"G5R 1C2",
    "sg:province":"QC",
    "sg:tags":[
        "janitor",
        "compound"
    ],
    "wof:name":"Manic Sanitation Inc",
    "wof:placetype":"venue"
},
  "geometry": {"coordinates":[-69.540779,47.839443],"type":"Point"}
}