{
  "type": "Feature",
  "properties": {
    "addr:full":"617 Foxgrove Ave East St Paul MB R2E 0A6",
    "addr:housenumber":"617",
    "addr:postcode":"r2e 0a6",
    "addr:street":"Foxgrove Ave",
    "iso:country":"CA",
    "sg:address":"617 Foxgrove Ave",
    "sg:city":"East St Paul",
    "sg:classifiers":[
        {
            "category":"Building & Trades",
            "subcategory":"Construction",
            "type":"Services"
        }
    ],
    "sg:phone":"+1 204 654 2229",
    "sg:postcode":"R2E 0A6",
    "sg:province":"MB",
    "sg:tags":[
        "maker",
        "cabinet"
    ],
    "wof:name":"Generations Woodworking",
    "wof:placetype":"venue"
},
  "geometry": {"coordinates":[-97.052139,49.956181],"type":"Point"}
}