{
  "type": "Feature",
  "properties": {
    "iso:country":"CA",
    "sg:address":"602 Main St",
    "sg:city":"Moosomin",
    "sg:classifiers":[
        {
            "category":"Social Services",
            "type":"Services"
        }
    ],
    "sg:phone":"+1 306 435 4055",
    "sg:postcode":"S0G 3N0",
    "sg:province":"SK",
    "sg:tags":[
        "information",
        "organization",
        "treatment",
        "alcoholism",
        "welfare"
    ],
    "wof:name":"Dr Jamieson Foundation",
    "wof:placetype":"venue"
},
  "geometry": {"coordinates":[-101.666572571,50.1443710327],"type":"Point"}
}