{
  "type": "Feature",
  "properties": {
    "iso:country":"CA",
    "sg:address":"5103 50th St",
    "sg:city":"Willingdon",
    "sg:classifiers":[
        {
            "category":"Travel",
            "subcategory":"Hotels & Motels",
            "type":"Entertainment"
        }
    ],
    "sg:phone":"+1 780 367 2271",
    "sg:postcode":"T0B 4R0",
    "sg:province":"AB",
    "wof:name":"Willingdon Hotel",
    "wof:placetype":"venue"
},
  "geometry": {"coordinates":[-112.117752,53.827854],"type":"Point"}
}