{
  "type": "Feature",
  "properties": {
    "iso:country":"CA",
    "sg:city":"Barrie",
    "sg:classifiers":[
        {
            "category":"Shopping",
            "subcategory":"Clothing, Apparel, & Fashions",
            "type":"Retail Goods"
        }
    ],
    "sg:phone":"+1 705 728 3112",
    "sg:postcode":"L4N 1E9",
    "sg:province":"ON",
    "sg:tags":[
        "swimwear",
        "accessory"
    ],
    "wof:name":"Hobson's Choice",
    "wof:placetype":"venue"
},
  "geometry": {"coordinates":[-79.694252,44.390907],"type":"Point"}
}