{
  "type": "Feature",
  "properties": {
    "addr:full":"Woodbridge ON L4L 3K8",
    "addr:postcode":"l4l 3k8",
    "iso:country":"CA",
    "sg:city":"Woodbridge",
    "sg:classifiers":[
        {
            "category":"Building & Trades",
            "subcategory":"Plumbing",
            "type":"Services"
        }
    ],
    "sg:phone":"+1 905 851 5022",
    "sg:postcode":"L4L 3K8",
    "sg:province":"ON",
    "sg:tags":[
        "sheet",
        "work",
        "metal",
        "contractor"
    ],
    "wof:name":"Secroft Metal Products Ltd",
    "wof:placetype":"venue"
},
  "geometry": {"coordinates":[-79.601006,43.784035],"type":"Point"}
}