{
  "type": "Feature",
  "properties": {
    "addr:full":"2334 Kingston Rd Scarborough ON M1N 1V2",
    "addr:housenumber":"2334",
    "addr:postcode":"m1n 1v2",
    "addr:street":"Kingston Rd",
    "iso:country":"CA",
    "sg:address":"2334 Kingston Rd",
    "sg:city":"Scarborough",
    "sg:classifiers":[
        {
            "category":"Retail",
            "subcategory":"Veterinary Services",
            "type":"Services"
        }
    ],
    "sg:phone":"+1 416 261 1391",
    "sg:postcode":"M1N 1V2",
    "sg:province":"ON",
    "sg:tags":[
        "veterinarian"
    ],
    "wof:name":"Scarborough Animal Hospital",
    "wof:placetype":"venue"
},
  "geometry": {"coordinates":[-79.251266,43.706783],"type":"Point"}
}