{
  "type": "Feature",
  "properties": {
    "addr:full":"RR 1 STN Main Grande Prairie AB T8V 2Z8",
    "addr:postcode":"t8v 2z8",
    "addr:street":"Rr 1 Stn Main",
    "iso:country":"CA",
    "sg:address":"RR 1 STN Main",
    "sg:city":"Grande Prairie",
    "sg:classifiers":[
        {
            "category":"Professional",
            "subcategory":"Business Services",
            "type":"Services"
        }
    ],
    "sg:phone":"+1 780 532 6639",
    "sg:postcode":"T8V 2Z8",
    "sg:province":"AB",
    "sg:tags":[
        "water",
        "hauling"
    ],
    "wof:name":"Boydland Water Hauling",
    "wof:placetype":"venue"
},
  "geometry": {"coordinates":[-118.79489100000001,55.171162],"type":"Point"}
}