{
  "type": "Feature",
  "properties": {
    "addr:full":"Orangeville ON L9W 1L1",
    "addr:postcode":"l9w 1l1",
    "iso:country":"CA",
    "sg:city":"Orangeville",
    "sg:classifiers":[
        {
            "category":"Personal",
            "subcategory":"Beauty Salon",
            "type":"Services"
        }
    ],
    "sg:phone":"+1 519 941 5444",
    "sg:postcode":"L9W 1L1",
    "sg:province":"ON",
    "wof:name":"Daniel's Hair Styling",
    "wof:placetype":"venue"
},
  "geometry": {"coordinates":[-80.10629299999999,43.917152],"type":"Point"}
}