{
  "type": "Feature",
  "properties": {
    "addr:full":"Red Earth Creek AB T0G 1X0",
    "addr:postcode":"t0g 1x0",
    "addr:street":"Red Earth",
    "iso:country":"CA",
    "sg:city":"Red Earth Creek",
    "sg:classifiers":[
        {
            "category":"Freight",
            "type":"Transportation"
        }
    ],
    "sg:phone":"+1 780 649 3801",
    "sg:postcode":"T0G 1X0",
    "sg:province":"AB",
    "sg:tags":[
        "field",
        "oil",
        "trucking"
    ],
    "wof:name":"Winalta Transport Ltd",
    "wof:placetype":"venue"
},
  "geometry": {"coordinates":[-115.209503,56.623489],"type":"Point"}
}