{
  "type": "Feature",
  "properties": {
    "iso:country":"CA",
    "sg:address":"96 Larch St",
    "sg:city":"Sudbury",
    "sg:classifiers":[
        {
            "category":"Professional",
            "subcategory":"Accounting & Tax Preparation",
            "type":"Services"
        }
    ],
    "sg:phone":"+1 705 674 8479",
    "sg:postcode":"P3E 1C1",
    "sg:province":"ON",
    "sg:tags":[
        "return",
        "filing"
    ],
    "wof:name":"Efile Plus",
    "wof:placetype":"venue"
},
  "geometry": {"coordinates":[-80.993195,46.491493],"type":"Point"}
}