{
  "type": "Feature",
  "properties": {
    "addr:full":"Edmonton AB T5S 2H1",
    "addr:postcode":"t5s 2h1",
    "iso:country":"CA",
    "sg:city":"Edmonton",
    "sg:classifiers":[
        {
            "category":"Wholesale",
            "subcategory":"Hardware",
            "type":"Manufacturing & Wholesale Goods"
        }
    ],
    "sg:phone":"+1 780 443 8092",
    "sg:postcode":"T5S 2H1",
    "sg:province":"AB",
    "wof:name":"Marathon Fasteners & Hardware",
    "wof:placetype":"venue"
},
  "geometry": {"coordinates":[-113.62931823700001,53.5498809814],"type":"Point"}
}