{
  "type": "Feature",
  "properties": {
    "addr:full":"Sainte-Genevieve-DE-Batiscan QC G0X 2R0",
    "addr:postcode":"g0x 2r0",
    "iso:country":"CA",
    "sg:city":"Sainte-Genevieve-DE-Batiscan",
    "sg:classifiers":[
        {
            "category":"Bars & Pubs",
            "type":"Food & Drink"
        }
    ],
    "sg:phone":"+1 418 362 2040",
    "sg:postcode":"G0X 2R0",
    "sg:province":"QC",
    "sg:tags":[
        "lounge",
        "cocktail"
    ],
    "wof:name":"Fouinard",
    "wof:placetype":"venue"
},
  "geometry": {"coordinates":[-72.33851623539999,46.5325660706],"type":"Point"}
}