{
  "type": "Feature",
  "properties": {
    "iso:country":"CA",
    "sg:city":"Montreal",
    "sg:classifiers":[
        {
            "category":"Shopping",
            "subcategory":"Clothing, Apparel, & Fashions",
            "type":"Retail Goods"
        }
    ],
    "sg:phone":"+1 514 282 0294",
    "sg:postcode":"H3A 1T5",
    "sg:province":"QC",
    "wof:name":"Giorgio Femme",
    "wof:placetype":"venue"
},
  "geometry": {"coordinates":[-73.5735702515,45.500453949],"type":"Point"}
}