{
  "type": "Feature",
  "properties": {
    "addr:full":"Saint-Donat-DE-Montcalm QC J0T 2C0",
    "addr:postcode":"j0t 2c0",
    "addr:street":"Saint-Donat-De-Montcalm",
    "iso:country":"CA",
    "sg:city":"Saint-Donat-DE-Montcalm",
    "sg:classifiers":[
        {
            "category":"Retail",
            "subcategory":"Animal Services",
            "type":"Services"
        }
    ],
    "sg:phone":"+1 819 424 4505",
    "sg:postcode":"J0T 2C0",
    "sg:province":"QC",
    "sg:tags":[
        "pet",
        "grooming",
        "washing"
    ],
    "wof:name":"Magichien",
    "wof:placetype":"venue"
},
  "geometry": {"coordinates":[-74.222466,46.319279],"type":"Point"}
}