{
  "type": "Feature",
  "properties": {
    "addr:full":"2548 Walsh Dr W Lethbridge AB T1J 4W5",
    "addr:housenumber":"2548",
    "addr:postcode":"t1j 4w5",
    "addr:street":"Walsh Dr W",
    "iso:country":"CA",
    "sg:address":"2548 Walsh Dr W",
    "sg:city":"Lethbridge",
    "sg:classifiers":[
        {
            "category":"Real Estate",
            "subcategory":"Real Estate Operator",
            "type":"Services"
        }
    ],
    "sg:phone":"+1 403 381 7477",
    "sg:postcode":"T1J 4W5",
    "sg:province":"AB",
    "sg:tags":[
        "apartment"
    ],
    "wof:name":"Woodsmere Holdings Corp",
    "wof:placetype":"venue"
},
  "geometry": {"coordinates":[-112.89852142300001,49.6979675293],"type":"Point"}
}