{
  "type": "Feature",
  "properties": {
    "addr:full":"410 Howe St Vancouver BC V6C 2X1",
    "addr:housenumber":"410",
    "addr:postcode":"bc v6c 2x1",
    "addr:street":"Howe St",
    "iso:country":"CA",
    "sg:address":"410 Howe St",
    "sg:city":"Vancouver",
    "sg:classifiers":[
        {
            "category":"Shopping",
            "type":"Retail Goods"
        }
    ],
    "sg:phone":"+1 604 874 6100",
    "sg:postcode":"V6C 2X1",
    "sg:province":"BC",
    "sg:tags":[
        "art",
        "consultant",
        "gallery",
        "design",
        "interior",
        "dealer",
        "decorator"
    ],
    "wof:name":"Dorian Rae Collection",
    "wof:placetype":"venue"
},
  "geometry": {"coordinates":[-123.114784241,49.2858390808],"type":"Point"}
}