{
  "type": "Feature",
  "properties": {
    "addr:full":"34537 Marshall Rd Abbotsford BC V2S 1M1",
    "addr:housenumber":"34537",
    "addr:postcode":"v2s 1m1",
    "addr:street":"Marshall Rd",
    "iso:country":"CA",
    "sg:address":"34537 Marshall Rd",
    "sg:city":"Abbotsford",
    "sg:classifiers":[
        {
            "category":"Retail",
            "subcategory":"Funeral Services",
            "type":"Services"
        }
    ],
    "sg:phone":"+1 604 854 5534",
    "sg:postcode":"V2S 1M1",
    "sg:province":"BC",
    "sg:tags":[
        "director"
    ],
    "wof:name":"Henderson's Fraser Vly Funeral",
    "wof:placetype":"venue"
},
  "geometry": {"coordinates":[-122.268081665,49.0382957458],"type":"Point"}
}