{
  "type": "Feature",
  "properties": {
    "addr:full":"25 Dunlop St W Barrie ON L4N 1A1",
    "addr:housenumber":"25",
    "addr:postcode":"l4n 1a1",
    "addr:street":"Dunlop St W",
    "iso:country":"CA",
    "sg:address":"25 Dunlop St W",
    "sg:city":"Barrie",
    "sg:classifiers":[
        {
            "category":"Shopping",
            "subcategory":"Books",
            "type":"Retail Goods"
        }
    ],
    "sg:phone":"+1 705 737 0312",
    "sg:postcode":"L4N 1A1",
    "sg:province":"ON",
    "sg:tags":[
        "dealer"
    ],
    "wof:name":"Kerry's Book Store",
    "wof:placetype":"venue"
},
  "geometry": {"coordinates":[-79.6907196045,44.3888282776],"type":"Point"}
}