{
  "type": "Feature",
  "properties": {
    "iso:country":"CA",
    "sg:address":"3812 Marbank Dr NE",
    "sg:city":"Calgary",
    "sg:classifiers":[
        {
            "category":"Organizations",
            "subcategory":"Religious Organization",
            "type":"Services"
        }
    ],
    "sg:phone":"+1 403 590 1722",
    "sg:postcode":"T2A 3Z7",
    "sg:province":"AB",
    "sg:tags":[
        "church"
    ],
    "wof:name":"Calgary Native Pentecostal",
    "wof:placetype":"venue"
},
  "geometry": {"coordinates":[-113.981056,51.062771],"type":"Point"}
}