{
  "type": "Feature",
  "properties": {
    "addr:full":"600 Rue Jean-Paul-Perrault Sherbrooke QC J1L 2Z2",
    "addr:housenumber":"600",
    "addr:postcode":"j1l 2z2",
    "addr:street":"Rue Jean-Paul-Perrault",
    "iso:country":"CA",
    "sg:address":"600 Rue Jean-Paul-Perrault",
    "sg:city":"Sherbrooke",
    "sg:classifiers":[
        {
            "category":"Building & Trades",
            "subcategory":"Construction",
            "type":"Services"
        }
    ],
    "sg:phone":"+1 819 566 5556",
    "sg:postcode":"J1L 2Z2",
    "sg:province":"QC",
    "sg:tags":[
        "hardware",
        "repairing",
        "remodeling",
        "contractor"
    ],
    "wof:name":"Reno Depot",
    "wof:placetype":"venue"
},
  "geometry": {"coordinates":[-71.888931,45.403263],"type":"Point"}
}