{
  "type": "Feature",
  "properties": {
    "addr:full":"114 Manor Rd E Toronto ON M4S 1P8",
    "addr:housenumber":"114",
    "addr:postcode":"m4s 1p8",
    "addr:street":"Manor Rd E",
    "iso:country":"CA",
    "sg:address":"114 Manor Rd E",
    "sg:city":"Toronto",
    "sg:classifiers":[
        {
            "category":"Building & Trades",
            "subcategory":"Construction",
            "type":"Services"
        }
    ],
    "sg:phone":"+1 416 488 3781",
    "sg:postcode":"M4S 1P8",
    "sg:province":"ON",
    "sg:tags":[
        "home",
        "general",
        "improvement",
        "contractor"
    ],
    "wof:name":"W E Kidd Construction Ltd",
    "wof:placetype":"venue"
},
  "geometry": {"coordinates":[-79.3917922974,43.7037811279],"type":"Point"}
}