{
  "type": "Feature",
  "properties": {
    "iso:country":"CA",
    "sg:address":"665 Millway Ave",
    "sg:city":"Concord",
    "sg:classifiers":[
        {
            "category":"Building & Trades",
            "subcategory":"Plumbing",
            "type":"Services"
        }
    ],
    "sg:phone":"+1 905 760 7887",
    "sg:postcode":"L4K 3T8",
    "sg:province":"ON",
    "sg:tags":[
        "contractor"
    ],
    "wof:name":"Plumbers Success Intl Canada",
    "wof:placetype":"venue"
},
  "geometry": {"coordinates":[-79.532082,43.810577],"type":"Point"}
}