{
  "type": "Feature",
  "properties": {
    "iso:country":"CA",
    "sg:address":"301 Oxford St W",
    "sg:city":"London",
    "sg:classifiers":[
        {
            "category":"Personal",
            "subcategory":"Beauty Salon",
            "type":"Services"
        }
    ],
    "sg:phone":"+1 519 679 9955",
    "sg:postcode":"N6H 1S6",
    "sg:province":"ON",
    "wof:name":"Hairmasters",
    "wof:placetype":"venue"
},
  "geometry": {"coordinates":[-81.275581,42.988998],"type":"Point"}
}