{
  "type": "Feature",
  "properties": {
    "addr:full":"392 Boul Grand L'Ile-Perrot QC J7V 4X2",
    "addr:housenumber":"392",
    "addr:postcode":"j7v 4x2",
    "addr:street":"Boul Grand L'Ile-Perrot",
    "iso:country":"CA",
    "sg:address":"392 Boul Grand",
    "sg:city":"L'Ile-Perrot",
    "sg:classifiers":[
        {
            "category":"Health Services",
            "subcategory":"Doctor",
            "type":"Services"
        }
    ],
    "sg:phone":"+1 514 453 2385",
    "sg:postcode":"J7V 4X2",
    "sg:province":"QC",
    "sg:tags":[
        "clinic"
    ],
    "wof:name":"Clinique Dentaire Fortin",
    "wof:placetype":"venue"
},
  "geometry": {"coordinates":[-73.96254,45.390732],"type":"Point"}
}