{
  "type": "Feature",
  "properties": {
    "iso:country":"CA",
    "sg:address":"989 Boul Decarie",
    "sg:city":"Saint-Laurent",
    "sg:classifiers":[
        {
            "category":"Professional",
            "subcategory":"Management & Consulting",
            "type":"Services"
        }
    ],
    "sg:phone":"+1 514 338 3958",
    "sg:postcode":"H4L 3M6",
    "sg:province":"QC",
    "sg:tags":[
        "marketing",
        "consultant"
    ],
    "wof:name":"Anaco Marketing",
    "wof:placetype":"venue"
},
  "geometry": {"coordinates":[-73.68226623539999,45.5141868591],"type":"Point"}
}