{
  "type": "Feature",
  "properties": {
    "addr:full":"3776 Route 115 Notre-Dame NB E4V 2H9",
    "addr:housenumber":"3776",
    "addr:postcode":"e4v 2h9",
    "addr:street":"Route 115",
    "iso:country":"CA",
    "sg:address":"3776 Route 115",
    "sg:city":"Notre-Dame",
    "sg:classifiers":[
        {
            "category":"Retail",
            "subcategory":"Auto Repair",
            "type":"Services"
        }
    ],
    "sg:phone":"+1 506 576 7741",
    "sg:postcode":"E4V 2H9",
    "sg:province":"NB",
    "sg:tags":[
        "body",
        "automobile",
        "painting"
    ],
    "wof:name":"Notre Dame Auto Body Ltd",
    "wof:placetype":"venue"
},
  "geometry": {"coordinates":[-64.74417099999999,46.297298],"type":"Point"}
}