{
  "type": "Feature",
  "properties": {
    "addr:full":"1051 Mac Leod Rd Pincher Creek AB T0K 1W0",
    "addr:housenumber":"1051",
    "addr:postcode":"t0k 1w0",
    "addr:street":"Mac Leod Rd",
    "iso:country":"CA",
    "sg:address":"1051 Mac Leod Rd",
    "sg:city":"Pincher Creek",
    "sg:classifiers":[
        {
            "category":"Government",
            "subcategory":"Office",
            "type":"Public Place"
        }
    ],
    "sg:phone":"+1 403 627 3484",
    "sg:postcode":"T0K 1W0",
    "sg:province":"AB",
    "sg:tags":[
        "village"
    ],
    "wof:name":"Pincher Creek Public Works",
    "wof:placetype":"venue"
},
  "geometry": {"coordinates":[-113.950096,49.485668],"type":"Point"}
}