{
  "type": "Feature",
  "properties": {
    "addr:full":"621 Rue Saint-Viateur Joliette QC J6E 3B8",
    "addr:housenumber":"621",
    "addr:postcode":"j6e 3b8",
    "addr:street":"Rue Saint-Viateur",
    "iso:country":"CA",
    "sg:address":"621 Rue Saint-Viateur",
    "sg:city":"Joliette",
    "sg:classifiers":[
        {
            "category":"Professional",
            "subcategory":"Detective & Security Services",
            "type":"Services"
        }
    ],
    "sg:phone":"+1 450 759 1433",
    "sg:postcode":"J6E 3B8",
    "sg:province":"QC",
    "sg:tags":[
        "burglary",
        "protective",
        "robbery"
    ],
    "wof:name":"Desmarais Electronique",
    "wof:placetype":"venue"
},
  "geometry": {"coordinates":[-73.4437408447,46.0235290527],"type":"Point"}
}