{
  "type": "Feature",
  "properties": {
    "addr:full":"802 Rue Principale Lac-Aux-Sables QC G0X 1M0",
    "addr:housenumber":"802",
    "addr:postcode":"g0x 1m0",
    "addr:street":"Rue Principale",
    "iso:country":"CA",
    "sg:address":"802 Rue Principale",
    "sg:city":"Lac-Aux-Sables",
    "sg:classifiers":[
        {
            "category":"Professional",
            "subcategory":"Accounting & Tax Preparation",
            "type":"Services"
        }
    ],
    "sg:phone":"+1 418 336 2179",
    "sg:postcode":"G0X 1M0",
    "sg:province":"QC",
    "sg:tags":[
        "accountant"
    ],
    "wof:name":"Buisson Beland Compt Agrees",
    "wof:placetype":"venue"
},
  "geometry": {"coordinates":[-72.389679,46.864613],"type":"Point"}
}