{
  "type": "Feature",
  "properties": {
    "addr:full":"636 Danforth Rd Scarborough ON M1K 1G2",
    "addr:housenumber":"636",
    "addr:postcode":"m1k 1g2",
    "addr:street":"Danforth Rd",
    "iso:country":"CA",
    "sg:address":"636 Danforth Rd",
    "sg:city":"Scarborough",
    "sg:classifiers":[
        {
            "category":"Restaurant",
            "type":"Food & Drink"
        }
    ],
    "sg:phone":"+1 416 267 7000",
    "sg:postcode":"M1K 1G2",
    "sg:province":"ON",
    "sg:tags":[
        "sandwich"
    ],
    "wof:name":"Mr Sub",
    "wof:placetype":"venue"
},
  "geometry": {"coordinates":[-79.26043701170001,43.7160606384],"type":"Point"}
}