{
  "type": "Feature",
  "properties": {
    "addr:full":"Calgary AB T3B 5P2",
    "addr:postcode":"t3b 5p2",
    "iso:country":"CA",
    "sg:city":"Calgary",
    "sg:classifiers":[
        {
            "category":"Professional",
            "subcategory":"Accounting & Tax Preparation",
            "type":"Services"
        }
    ],
    "sg:phone":"+1 403 242 2441",
    "sg:postcode":"T3B 5P2",
    "sg:province":"AB",
    "sg:tags":[
        "accountant"
    ],
    "wof:name":"Thompson, Jack",
    "wof:placetype":"venue"
},
  "geometry": {"coordinates":[-114.21241000000001,51.086395],"type":"Point"}
}