{
  "type": "Feature",
  "properties": {
    "addr:full":"Richmond BC V6V 2R6",
    "addr:postcode":"v6v 2r6",
    "iso:country":"CA",
    "sg:city":"Richmond",
    "sg:classifiers":[
        {
            "category":"Manufacturing",
            "subcategory":"Paper Products",
            "type":"Manufacturing & Wholesale Goods"
        }
    ],
    "sg:phone":"+1 604 821 0407",
    "sg:postcode":"V6V 2R6",
    "sg:province":"BC",
    "sg:tags":[
        "bag"
    ],
    "wof:name":"Sincere Plastic Bag & Printing",
    "wof:placetype":"venue"
},
  "geometry": {"coordinates":[-123.058021545,49.2013053894],"type":"Point"}
}