{
  "type": "Feature",
  "properties": {
    "iso:country":"CA",
    "sg:address":"18 Lagos Rd",
    "sg:city":"Etobicoke",
    "sg:classifiers":[
        {
            "category":"Social Services",
            "subcategory":"Job Training",
            "type":"Services"
        }
    ],
    "sg:phone":"+1 416 748 7737",
    "sg:postcode":"M9W 4E4",
    "sg:province":"ON",
    "sg:tags":[
        "rehabilitation"
    ],
    "wof:name":"George Chuvalo Fight Against",
    "wof:placetype":"venue"
},
  "geometry": {"coordinates":[-79.572899,43.730686],"type":"Point"}
}