{
  "type": "Feature",
  "properties": {
    "iso:country":"CA",
    "sg:city":"Brandon",
    "sg:classifiers":[
        {
            "category":"Wholesale",
            "subcategory":"Groceries",
            "type":"Manufacturing & Wholesale Goods"
        }
    ],
    "sg:phone":"+1 204 726 0440",
    "sg:postcode":"R7A 3X8",
    "sg:province":"MB",
    "sg:tags":[
        "bakery",
        "prod"
    ],
    "wof:name":"Mc Gavin Bread Basket",
    "wof:placetype":"venue"
},
  "geometry": {"coordinates":[-99.9485321045,49.8415184021],"type":"Point"}
}