{
  "type": "Feature",
  "properties": {
    "addr:full":"652 Rte Elgin N Saint-Pamphile QC G0R 3X0",
    "addr:housenumber":"652",
    "addr:postcode":"g0r 3x0",
    "addr:street":"Rte Elgin N",
    "iso:country":"CA",
    "sg:address":"652 Rte Elgin N",
    "sg:city":"Saint-Pamphile",
    "sg:classifiers":[
        {
            "category":"Home & Garden",
            "subcategory":"Building Materials",
            "type":"Retail Goods"
        }
    ],
    "sg:phone":"+1 418 356 3352",
    "sg:postcode":"G0R 3X0",
    "sg:province":"QC",
    "wof:name":"Centre DE Renovation M Jalbert",
    "wof:placetype":"venue"
},
  "geometry": {"coordinates":[-69.79542499999999,46.97187],"type":"Point"}
}