{
  "type": "Feature",
  "properties": {
    "addr:full":"Saint-Leonard QC H1P 2A9",
    "addr:postcode":"h1p 2a9",
    "iso:country":"CA",
    "sg:city":"Saint-Leonard",
    "sg:classifiers":[
        {
            "category":"Building & Trades",
            "subcategory":"Construction",
            "type":"Services"
        }
    ],
    "sg:phone":"+1 514 322 4370",
    "sg:postcode":"H1P 2A9",
    "sg:province":"QC",
    "sg:tags":[
        "general",
        "contractor"
    ],
    "wof:name":"Legrand Inc",
    "wof:placetype":"venue"
},
  "geometry": {"coordinates":[-73.582443,45.596481],"type":"Point"}
}