{
  "type": "Feature",
  "properties": {
    "iso:country":"CA",
    "sg:address":"30874 Hwy 28 E",
    "sg:city":"Bancroft",
    "sg:classifiers":[
        {
            "category":"Building & Trades",
            "subcategory":"Construction",
            "type":"Services"
        }
    ],
    "sg:phone":"+1 613 332 4401",
    "sg:postcode":"K0L 1C0",
    "sg:province":"ON",
    "sg:tags":[
        "layer",
        "carpet"
    ],
    "wof:name":"Ken's Installation",
    "wof:placetype":"venue"
},
  "geometry": {"coordinates":[-77.8291397095,45.0631332397],"type":"Point"}
}