{
  "type": "Feature",
  "properties": {
    "addr:full":"337 Inglewood St Winnipeg MB R3J 1X1",
    "addr:housenumber":"337",
    "addr:postcode":"r3j 1x1",
    "addr:street":"Inglewood St",
    "iso:country":"CA",
    "sg:address":"337 Inglewood St",
    "sg:city":"Winnipeg",
    "sg:classifiers":[
        {
            "category":"Organizations",
            "subcategory":"Religious Organization",
            "type":"Services"
        }
    ],
    "sg:phone":"+1 204 888 1535",
    "sg:postcode":"R3J 1X1",
    "sg:province":"MB",
    "sg:tags":[
        "church"
    ],
    "wof:name":"St James Gospel Chapel",
    "wof:placetype":"venue"
},
  "geometry": {"coordinates":[-97.219398,49.883698],"type":"Point"}
}