{
  "type": "Feature",
  "properties": {
    "addr:full":"180 Sharpe St W Gravenhurst ON P1P 1J1",
    "addr:housenumber":"180",
    "addr:postcode":"p1p 1j1",
    "addr:street":"Sharpe St W",
    "iso:country":"CA",
    "sg:address":"180 Sharpe St W",
    "sg:city":"Gravenhurst",
    "sg:classifiers":[
        {
            "category":"Education",
            "subcategory":"Library",
            "type":"Public Place"
        }
    ],
    "sg:phone":"+1 705 687 3382",
    "sg:postcode":"P1P 1J1",
    "sg:province":"ON",
    "wof:name":"Gravenhurst Public Library",
    "wof:placetype":"venue"
},
  "geometry": {"coordinates":[-79.3744354248,44.9179611206],"type":"Point"}
}