{
  "type": "Feature",
  "properties": {
    "addr:full":"Hammond ON K0A 2A0",
    "addr:postcode":"k0a 2a0",
    "iso:country":"CA",
    "sg:city":"Hammond",
    "sg:classifiers":[
        {
            "category":"Home & Garden",
            "subcategory":"Furniture",
            "type":"Retail Goods"
        }
    ],
    "sg:phone":"+1 613 487 3049",
    "sg:postcode":"K0A 2A0",
    "sg:province":"ON",
    "sg:tags":[
        "equipment",
        "kitchen",
        "cabinet"
    ],
    "wof:name":"Cabinet Shop",
    "wof:placetype":"venue"
},
  "geometry": {"coordinates":[-75.23921199999999,45.441975],"type":"Point"}
}