{
  "type": "Feature",
  "properties": {
    "addr:full":"5 Fanshore Dr Woodbridge ON L4H 1T8",
    "addr:housenumber":"5",
    "addr:postcode":"l4h 1t8",
    "addr:street":"Fanshore Dr",
    "iso:country":"CA",
    "sg:address":"5 Fanshore Dr",
    "sg:city":"Woodbridge",
    "sg:classifiers":[
        {
            "category":"Freight",
            "type":"Transportation"
        }
    ],
    "sg:phone":"+1 905 893 7506",
    "sg:postcode":"L4H 1T8",
    "sg:province":"ON",
    "sg:tags":[
        "cartage"
    ],
    "wof:name":"Motionsport Cartage Systems",
    "wof:placetype":"venue"
},
  "geometry": {"coordinates":[-79.61506652830001,43.8149986267],"type":"Point"}
}