{
  "type": "Feature",
  "properties": {
    "addr:full":"Sarnia ON N7S 1P4",
    "addr:postcode":"n7s 1p4",
    "iso:country":"CA",
    "sg:city":"Sarnia",
    "sg:classifiers":[
        {
            "category":"Personal",
            "subcategory":"Beauty Salon",
            "type":"Services"
        }
    ],
    "sg:phone":"+1 519 337 9767",
    "sg:postcode":"N7S 1P4",
    "sg:province":"ON",
    "sg:tags":[
        "manicuring"
    ],
    "wof:name":"K N Nails Design",
    "wof:placetype":"venue"
},
  "geometry": {"coordinates":[-82.363739,42.979511],"type":"Point"}
}