{
  "type": "Feature",
  "properties": {
    "addr:full":"237 Boul Des Prairies Laval QC H7N 2T8",
    "addr:housenumber":"237",
    "addr:postcode":"h7n 2t8",
    "addr:street":"Boul Des Prairies",
    "iso:country":"CA",
    "sg:address":"237 Boul Des Prairies",
    "sg:city":"Laval",
    "sg:classifiers":[
        {
            "category":"Professional",
            "subcategory":"Lawyer & Legal Services",
            "type":"Services"
        }
    ],
    "sg:phone":"+1 450 667 9802",
    "sg:postcode":"H7N 2T8",
    "sg:province":"QC",
    "sg:tags":[
        "attorney"
    ],
    "wof:name":"Lamarche, Pierre",
    "wof:placetype":"venue"
},
  "geometry": {"coordinates":[-73.69639599999999,45.551716],"type":"Point"}
}