{
  "type": "Feature",
  "properties": {
    "addr:full":"2066 Rte Mcwatters Mcwatters QC J9X 5B7",
    "addr:housenumber":"2066",
    "addr:postcode":"j9x 5b7",
    "addr:street":"Rte Mcwatters",
    "iso:country":"CA",
    "sg:address":"2066 Rte Mcwatters",
    "sg:city":"Mcwatters",
    "sg:classifiers":[
        {
            "category":"Retail",
            "subcategory":"Auto Repair",
            "type":"Services"
        }
    ],
    "sg:phone":"+1 819 764 9953",
    "sg:postcode":"J9X 5B7",
    "sg:province":"QC",
    "sg:tags":[
        "repairing",
        "automobile"
    ],
    "wof:name":"Garage Real Legendre Enr",
    "wof:placetype":"venue"
},
  "geometry": {"coordinates":[-78.94676971440001,48.2177314758],"type":"Point"}
}