{
  "type": "Feature",
  "properties": {
    "iso:country":"CA",
    "sg:address":"121 Ardagh Rd",
    "sg:city":"Barrie",
    "sg:classifiers":[
        {
            "category":"Personal",
            "subcategory":"Beauty Salon",
            "type":"Services"
        }
    ],
    "sg:phone":"+1 705 733 5293",
    "sg:postcode":"L4N 3V5",
    "sg:province":"ON",
    "wof:name":"Patty's Place",
    "wof:placetype":"venue"
},
  "geometry": {"coordinates":[-79.705788,44.356819],"type":"Point"}
}