{
  "type": "Feature",
  "properties": {
    "addr:full":"Dwight ON P0A 1H0",
    "addr:postcode":"p0a 1h0",
    "iso:country":"CA",
    "sg:city":"Dwight",
    "sg:classifiers":[
        {
            "category":"Travel",
            "subcategory":"Hotels & Motels",
            "type":"Entertainment"
        }
    ],
    "sg:phone":"+1 705 635 1097",
    "sg:postcode":"P0A 1H0",
    "sg:province":"ON",
    "sg:tags":[
        "cottage",
        "tourist",
        "cabin",
        "accommodation"
    ],
    "wof:name":"Timber Trail Algonquin",
    "wof:placetype":"venue"
},
  "geometry": {"coordinates":[-78.997131,45.3251],"type":"Point"}
}