{
  "type": "Feature",
  "properties": {
    "addr:full":"17535 100 Ave NW Edmonton AB T5S 2B8",
    "addr:housenumber":"17535",
    "addr:postcode":"t5s 2b8",
    "addr:street":"100 Ave Nw",
    "iso:country":"CA",
    "sg:address":"17535 100 Ave NW",
    "sg:city":"Edmonton",
    "sg:classifiers":[
        {
            "category":"Personal",
            "subcategory":"Beauty Salon",
            "type":"Services"
        }
    ],
    "sg:phone":"+1 780 483 8802",
    "sg:postcode":"T5S 2B8",
    "sg:province":"AB",
    "wof:name":"Salon DE Artist",
    "wof:placetype":"venue"
},
  "geometry": {"coordinates":[-113.622612,53.538479],"type":"Point"}
}