{
  "type": "Feature",
  "properties": {
    "addr:full":"Abbotsford BC V2T 4W1",
    "addr:postcode":"v2t 4w1",
    "iso:country":"CA",
    "sg:city":"Abbotsford",
    "sg:classifiers":[
        {
            "category":"Personal",
            "subcategory":"Barber",
            "type":"Services"
        }
    ],
    "sg:phone":"+1 604 852 6570",
    "sg:postcode":"V2T 4W1",
    "sg:province":"BC",
    "sg:tags":[
        "salon",
        "beauty"
    ],
    "wof:name":"Magicuts Clearbrook",
    "wof:placetype":"venue"
},
  "geometry": {"coordinates":[-122.315056,49.05106],"type":"Point"}
}