{
  "type": "Feature",
  "properties": {
    "addr:full":"1322 11 Ave Fernie BC V0B 1M0",
    "addr:housenumber":"1322",
    "addr:postcode":"bc v0b 1m0",
    "addr:street":"11 Ave",
    "iso:country":"CA",
    "sg:address":"1322 11 Ave",
    "sg:city":"Fernie",
    "sg:classifiers":[
        {
            "category":"Building & Trades",
            "subcategory":"Plumbing",
            "type":"Services"
        }
    ],
    "sg:phone":"+1 250 423 7004",
    "sg:postcode":"V0B 1M0",
    "sg:province":"BC",
    "sg:tags":[
        "heating",
        "contractor"
    ],
    "wof:name":"Johnson's Plumbing & Heating",
    "wof:placetype":"venue"
},
  "geometry": {"coordinates":[-115.064995,49.514046],"type":"Point"}
}