{
  "type": "Feature",
  "properties": {
    "iso:country":"CA",
    "sg:address":"867 Rue Notre-Dame # 101",
    "sg:city":"Saint-Remi",
    "sg:classifiers":[
        {
            "category":"Insurance",
            "subcategory":"Insurance Agent",
            "type":"Services"
        }
    ],
    "sg:phone":"+1 450 454 4654",
    "sg:postcode":"J0L 2L0",
    "sg:province":"QC",
    "wof:name":"Lareau Potvin Assurances Inc",
    "wof:placetype":"venue"
},
  "geometry": {"coordinates":[-73.61949157710001,45.2592735291],"type":"Point"}
}