{
  "type": "Feature",
  "properties": {
    "addr:full":"12005 Rue Raymonde-DE Laroche # 112 Mirabel QC J7N 1H2",
    "addr:housenumber":"12005",
    "addr:postcode":"j7n 1h2",
    "addr:street":"Rue Raymonde-De Laroche # 112",
    "iso:country":"CA",
    "sg:address":"12005 Rue Raymonde-DE Laroche # 112",
    "sg:city":"Mirabel",
    "sg:classifiers":[
        {
            "category":"Airline",
            "type":"Transportation"
        }
    ],
    "sg:phone":"+1 450 476 0974",
    "sg:postcode":"J7N 1H2",
    "sg:province":"QC",
    "sg:tags":[
        "cargo",
        "air"
    ],
    "wof:name":"Aeroterm DE Montreal Inc",
    "wof:placetype":"venue"
},
  "geometry": {"coordinates":[-74.0458450317,45.6793403625],"type":"Point"}
}