{
  "type": "Feature",
  "properties": {
    "iso:country":"CA",
    "sg:address":"969 Brookdale Ave",
    "sg:city":"Cornwall",
    "sg:classifiers":[
        {
            "category":"Personal",
            "subcategory":"Beauty Salon",
            "type":"Services"
        }
    ],
    "sg:phone":"+1 613 932 7718",
    "sg:postcode":"K6J 4P5",
    "sg:province":"ON",
    "wof:name":"He & She Hair Styling",
    "wof:placetype":"venue"
},
  "geometry": {"coordinates":[-74.7498931885,45.025138855],"type":"Point"}
}