{
  "type": "Feature",
  "properties": {
    "iso:country":"CA",
    "sg:city":"Montreal",
    "sg:classifiers":[
        {
            "category":"Health Services",
            "subcategory":"Health Practitioner",
            "type":"Services"
        }
    ],
    "sg:phone":"+1 514 257 6528",
    "sg:postcode":"H1N 1C1",
    "sg:province":"QC",
    "sg:tags":[
        "employee",
        "assistance",
        "program",
        "psychologist"
    ],
    "wof:name":"Jacques Lamarre & Assoc Inc",
    "wof:placetype":"venue"
},
  "geometry": {"coordinates":[-73.545769,45.577812],"type":"Point"}
}