{
  "type": "Feature",
  "properties": {
    "addr:full":"86 Broadway St Nakusp BC V0G 1R0",
    "addr:housenumber":"86",
    "addr:postcode":"v0g 1r0",
    "addr:street":"Broadway St",
    "iso:country":"CA",
    "sg:address":"86 Broadway St",
    "sg:city":"Nakusp",
    "sg:classifiers":[
        {
            "category":"Health Services",
            "subcategory":"Doctor",
            "type":"Services"
        }
    ],
    "sg:phone":"+1 250 265 9993",
    "sg:postcode":"V0G 1R0",
    "sg:province":"BC",
    "sg:tags":[
        "dentist"
    ],
    "wof:name":"Saddle Mountain Dental Clinic",
    "wof:placetype":"venue"
},
  "geometry": {"coordinates":[-117.79634900000001,50.238117],"type":"Point"}
}