{
  "type": "Feature",
  "properties": {
    "iso:country":"CA",
    "sg:address":"940 Lansdowne Ave # 26",
    "sg:city":"Toronto",
    "sg:classifiers":[
        {
            "category":"Wholesale",
            "subcategory":"Vending Machines",
            "type":"Manufacturing & Wholesale Goods"
        }
    ],
    "sg:phone":"+1 416 535 5013",
    "sg:postcode":"M6H 3Z4",
    "sg:province":"ON",
    "wof:name":"Marx Vending Equipment",
    "wof:placetype":"venue"
},
  "geometry": {"coordinates":[-79.447593689,43.6691818237],"type":"Point"}
}