{
  "type": "Feature",
  "properties": {
    "addr:full":"PO Box 407 Water Valley AB T0M 2E0",
    "addr:housenumber":"po",
    "addr:postcode":"t0m 2e0",
    "addr:street":"Box 407 Water",
    "iso:country":"CA",
    "sg:address":"PO Box 407",
    "sg:city":"Water Valley",
    "sg:classifiers":[
        {
            "category":"Manufacturing",
            "subcategory":"Tools & Machinery",
            "type":"Manufacturing & Wholesale Goods"
        }
    ],
    "sg:phone":"+1 403 637 3777",
    "sg:postcode":"T0M 2E0",
    "sg:province":"AB",
    "sg:tags":[
        "equipment",
        "gas"
    ],
    "wof:name":"Hollander Combustion Svc",
    "wof:placetype":"venue"
},
  "geometry": {"coordinates":[-114.60555267300001,51.5038909912],"type":"Point"}
}