{
  "type": "Feature",
  "properties": {
    "addr:full":"6660 Campobello Rd Mississauga ON L5N 2L9",
    "addr:postcode":"6660;l5n 2l9",
    "addr:street":"Campobello Rd",
    "iso:country":"CA",
    "sg:address":"6660 Campobello Rd",
    "sg:city":"Mississauga",
    "sg:classifiers":[
        {
            "category":"Manufacturing",
            "subcategory":"Tools & Machinery",
            "type":"Manufacturing & Wholesale Goods"
        }
    ],
    "sg:phone":"+1 905 693 8595",
    "sg:postcode":"L5N 2L9",
    "sg:province":"ON",
    "sg:tags":[
        "pump"
    ],
    "wof:name":"Hayward Gordon Ltd",
    "wof:placetype":"venue"
},
  "geometry": {"coordinates":[-79.733002,43.607792],"type":"Point"}
}