{
  "type": "Feature",
  "properties": {
    "iso:country":"CA",
    "sg:address":"174 Adelaide St",
    "sg:city":"Saint John",
    "sg:classifiers":[
        {
            "category":"Wholesale",
            "subcategory":"Machinery & Supplies",
            "type":"Manufacturing & Wholesale Goods"
        }
    ],
    "sg:phone":"+1 506 634 1672",
    "sg:postcode":"E2K 1X1",
    "sg:province":"NB",
    "sg:tags":[
        "ship",
        "broker"
    ],
    "wof:name":"Maritime Ship & Yacht Brokers",
    "wof:placetype":"venue"
},
  "geometry": {"coordinates":[-66.080452,45.278538],"type":"Point"}
}