{
  "type": "Feature",
  "properties": {
    "iso:country":"CA",
    "sg:address":"27107 Fraser Hwy",
    "sg:city":"Aldergrove",
    "sg:classifiers":[
        {
            "category":"Health Services",
            "subcategory":"Doctor",
            "type":"Services"
        }
    ],
    "sg:phone":"+1 604 856 3321",
    "sg:postcode":"V4W 3R2",
    "sg:province":"BC",
    "sg:tags":[
        "physician",
        "surgeon"
    ],
    "wof:name":"Anthony Ciavarella Inc",
    "wof:placetype":"venue"
},
  "geometry": {"coordinates":[-122.47328186,49.0583190918],"type":"Point"}
}