{
  "type": "Feature",
  "properties": {
    "addr:full":"213 Government Rd S Black Diamond AB T0L 0H0",
    "addr:housenumber":"213",
    "addr:postcode":"t0l 0h0",
    "addr:street":"Government Rd S",
    "iso:country":"CA",
    "sg:address":"213 Government Rd S",
    "sg:city":"Black Diamond",
    "sg:classifiers":[
        {
            "category":"Organizations",
            "subcategory":"Religious Organization",
            "type":"Services"
        }
    ],
    "sg:phone":"+1 403 933 4450",
    "sg:postcode":"T0L 0H0",
    "sg:province":"AB",
    "sg:tags":[
        "church"
    ],
    "wof:name":"Turner Valley Congregation of",
    "wof:placetype":"venue"
},
  "geometry": {"coordinates":[-114.232810974,50.6869544983],"type":"Point"}
}