{
  "type": "Feature",
  "properties": {
    "iso:country":"CA",
    "sg:address":"249 Mcleod St",
    "sg:city":"Ottawa",
    "sg:classifiers":[
        {
            "category":"Organizations",
            "subcategory":"Professional Association",
            "type":"Services"
        }
    ],
    "sg:phone":"+1 613 230 4739",
    "sg:postcode":"K2P 1A1",
    "sg:province":"ON",
    "wof:name":"Canadian Boreal Trust",
    "wof:placetype":"venue"
},
  "geometry": {"coordinates":[-75.689507,45.413219],"type":"Point"}
}