{
  "type": "Feature",
  "properties": {
    "iso:country":"CA",
    "sg:address":"330 Rue DE Port-Royal O",
    "sg:city":"Montreal",
    "sg:classifiers":[
        {
            "category":"Manufacturing",
            "subcategory":"Tools & Machinery",
            "type":"Manufacturing & Wholesale Goods"
        }
    ],
    "sg:phone":"+1 514 384 2235",
    "sg:postcode":"H3L 2B8",
    "sg:province":"QC",
    "sg:tags":[
        "equipment",
        "cutting",
        "room",
        "supply"
    ],
    "wof:name":"Joe Haich CO",
    "wof:placetype":"venue"
},
  "geometry": {"coordinates":[-73.655388,45.548977],"type":"Point"}
}