{
  "type": "Feature",
  "properties": {
    "addr:full":"11119 102nd Ave Fairview AB T0H 1L0",
    "addr:housenumber":"11119",
    "addr:postcode":"t0h 1l0",
    "addr:street":"102Nd Ave",
    "iso:country":"CA",
    "sg:address":"11119 102nd Ave",
    "sg:city":"Fairview",
    "sg:classifiers":[
        {
            "category":"Retail",
            "subcategory":"Car Wash",
            "type":"Services"
        }
    ],
    "sg:phone":"+1 780 835 3085",
    "sg:postcode":"T0H 1L0",
    "sg:province":"AB",
    "sg:tags":[
        "polishing",
        "washing"
    ],
    "wof:name":"A 1 Carwash",
    "wof:placetype":"venue"
},
  "geometry": {"coordinates":[-118.387451172,56.0664482117],"type":"Point"}
}