{
  "type": "Feature",
  "properties": {
    "addr:full":"27 Strathearn Ave Brampton ON L6T 4V5",
    "addr:housenumber":"27",
    "addr:postcode":"l6t 4v5",
    "addr:street":"Strathearn Ave",
    "iso:country":"CA",
    "sg:address":"27 Strathearn Ave",
    "sg:city":"Brampton",
    "sg:classifiers":[
        {
            "category":"Freight",
            "type":"Transportation"
        }
    ],
    "sg:phone":"+1 905 458 1046",
    "sg:postcode":"L6T 4V5",
    "sg:province":"ON",
    "sg:tags":[
        "trucking"
    ],
    "wof:name":"Cedar Creek Transportation Svc",
    "wof:placetype":"venue"
},
  "geometry": {"coordinates":[-79.696105957,43.693862915],"type":"Point"}
}