{
  "type": "Feature",
  "properties": {
    "addr:full":"Lockeport NS B0T 1L0",
    "addr:postcode":"b0t 1l0",
    "iso:country":"CA",
    "sg:city":"Lockeport",
    "sg:classifiers":[
        {
            "category":"Government",
            "subcategory":"Office",
            "type":"Public Place"
        }
    ],
    "sg:phone":"+1 902 656 3301",
    "sg:postcode":"B0T 1L0",
    "sg:province":"NS",
    "sg:tags":[
        "village"
    ],
    "wof:name":"Lockeport Sewage Treatment",
    "wof:placetype":"venue"
},
  "geometry": {"coordinates":[-65.1153335571,43.6970214844],"type":"Point"}
}