{
  "type": "Feature",
  "properties": {
    "addr:full":"1680 Blackrock Rd Waterville NS B0P 1V0",
    "addr:housenumber":"1680",
    "addr:postcode":"b0p 1v0",
    "addr:street":"Blackrock Rd",
    "iso:country":"CA",
    "sg:address":"1680 Blackrock Rd",
    "sg:city":"Waterville",
    "sg:classifiers":[
        {
            "category":"Building & Trades",
            "subcategory":"Construction",
            "type":"Services"
        }
    ],
    "sg:phone":"+1 902 538 7442",
    "sg:postcode":"B0P 1V0",
    "sg:province":"NS",
    "sg:tags":[
        "general",
        "contractor"
    ],
    "wof:name":"Beaumont Garage Door CO",
    "wof:placetype":"venue"
},
  "geometry": {"coordinates":[-64.677986,45.052334],"type":"Point"}
}