{
  "type": "Feature",
  "properties": {
    "addr:full":"18 Grey Abbey Trail Cambridge ON N3C 3G1",
    "addr:housenumber":"18",
    "addr:postcode":"n3c 3g1",
    "addr:street":"Grey Abbey Trail",
    "iso:country":"CA",
    "sg:address":"18 Grey Abbey Trail",
    "sg:city":"Cambridge",
    "sg:classifiers":[
        {
            "category":"Building & Trades",
            "subcategory":"Cleaning & Sanitation",
            "type":"Services"
        }
    ],
    "sg:phone":"+1 519 658 5226",
    "sg:postcode":"N3C 3G1",
    "sg:province":"ON",
    "sg:tags":[
        "janitor"
    ],
    "wof:name":"Adelino Maintenance Svc",
    "wof:placetype":"venue"
},
  "geometry": {"coordinates":[-80.306442,43.422199],"type":"Point"}
}