{
  "type": "Feature",
  "properties": {
    "addr:full":"3228 Dunbar St Vancouver BC V6S 2B7",
    "addr:housenumber":"3228",
    "addr:postcode":"v6s 2b7",
    "addr:street":"Dunbar St",
    "iso:country":"CA",
    "sg:address":"3228 Dunbar St",
    "sg:city":"Vancouver",
    "sg:classifiers":[
        {
            "category":"Shopping",
            "subcategory":"Bicycles & Sporting Goods",
            "type":"Retail Goods"
        }
    ],
    "sg:phone":"+1 604 734 1191",
    "sg:postcode":"V6S 2B7",
    "sg:province":"BC",
    "wof:name":"Cheapskates Too Consignment",
    "wof:placetype":"venue"
},
  "geometry": {"coordinates":[-123.18497499999999,49.257683],"type":"Point"}
}