{
  "type": "Feature",
  "properties": {
    "addr:full":"530 29E Rue Saint-Georges QC G5Y 4H6",
    "addr:housenumber":"530",
    "addr:postcode":"g5y 4h6",
    "addr:street":"29E Rue",
    "iso:country":"CA",
    "sg:address":"530 29E Rue",
    "sg:city":"Saint-Georges",
    "sg:classifiers":[
        {
            "category":"Building & Trades",
            "subcategory":"Construction",
            "type":"Services"
        }
    ],
    "sg:phone":"+1 418 228 4345",
    "sg:postcode":"G5Y 4H6",
    "sg:province":"QC",
    "sg:tags":[
        "tile",
        "dealer"
    ],
    "wof:name":"Recouvrements Dreanne Inc",
    "wof:placetype":"venue"
},
  "geometry": {"coordinates":[-70.669647,46.111103],"type":"Point"}
}