{
  "type": "Feature",
  "properties": {
    "addr:full":"Vancouver BC V6K 1R2",
    "addr:postcode":"v6k 1r2",
    "iso:country":"CA",
    "sg:city":"Vancouver",
    "sg:classifiers":[
        {
            "category":"Health Services",
            "subcategory":"Chiropractor",
            "type":"Services"
        }
    ],
    "sg:phone":"+1 604 731 6679",
    "sg:postcode":"V6K 1R2",
    "sg:province":"BC",
    "wof:name":"Armitage & Assoc Chiropractic",
    "wof:placetype":"venue"
},
  "geometry": {"coordinates":[-123.169746,49.268246],"type":"Point"}
}