{
  "type": "Feature",
  "properties": {
    "addr:full":"6200 Ledingham Rd Courtenay BC V9J 1M5",
    "addr:housenumber":"6200",
    "addr:postcode":"v9j 1m5",
    "addr:street":"Ledingham Rd",
    "iso:country":"CA",
    "sg:address":"6200 Ledingham Rd",
    "sg:city":"Courtenay",
    "sg:classifiers":[
        {
            "category":"Wholesale",
            "subcategory":"Meat",
            "type":"Manufacturing & Wholesale Goods"
        }
    ],
    "sg:phone":"+1 250 334 2960",
    "sg:postcode":"V9J 1M5",
    "sg:province":"BC",
    "sg:tags":[
        "packer"
    ],
    "wof:name":"Gunter Brothers Meat CO",
    "wof:placetype":"venue"
},
  "geometry": {"coordinates":[-124.99314099999999,49.686722],"type":"Point"}
}