{
  "type": "Feature",
  "properties": {
    "addr:full":"48 High St W Moose Jaw SK S6H 1S3",
    "addr:housenumber":"48",
    "addr:postcode":"s6h 1s3",
    "addr:street":"High St W",
    "iso:country":"CA",
    "sg:address":"48 High St W",
    "sg:city":"Moose Jaw",
    "sg:classifiers":[
        {
            "category":"Banks & Credit Unions",
            "subcategory":"Bank",
            "type":"Services"
        }
    ],
    "sg:phone":"+1 306 694 8130",
    "sg:postcode":"S6H 1S3",
    "sg:province":"SK",
    "wof:name":"Bank of Montreal",
    "wof:placetype":"venue"
},
  "geometry": {"coordinates":[-105.535988,50.391861],"type":"Point"}
}