{
  "type": "Feature",
  "properties": {
    "addr:full":"700 St Peter Ave Bathurst NB E2A 2Y7",
    "addr:housenumber":"700",
    "addr:postcode":"e2a 2y7",
    "addr:street":"St Peter Ave",
    "iso:country":"CA",
    "sg:address":"700 St Peter Ave",
    "sg:city":"Bathurst",
    "sg:classifiers":[
        {
            "category":"Shopping",
            "type":"Retail Goods"
        }
    ],
    "sg:phone":"+1 506 546 9520",
    "sg:postcode":"E2A 2Y7",
    "sg:province":"NB",
    "sg:tags":[
        "orthopedic",
        "appliance"
    ],
    "wof:name":"Chaussures Ortheses Mc Graw",
    "wof:placetype":"venue"
},
  "geometry": {"coordinates":[-65.66826629640001,47.6317100525],"type":"Point"}
}