{
  "type": "Feature",
  "properties": {
    "addr:full":"North York ON M2J 5A7",
    "addr:postcode":"m2j 5a7",
    "iso:country":"CA",
    "sg:city":"North York",
    "sg:classifiers":[
        {
            "category":"Restaurant",
            "type":"Food & Drink"
        }
    ],
    "sg:phone":"+1 416 756 9908",
    "sg:postcode":"M2J 5A7",
    "sg:province":"ON",
    "wof:name":"Mc Donald's",
    "wof:placetype":"venue"
},
  "geometry": {"coordinates":[-79.345367,43.775616],"type":"Point"}
}