{
  "type": "Feature",
  "properties": {
    "iso:country":"CA",
    "sg:address":"7080 Pacific Cir # 3",
    "sg:city":"Mississauga",
    "sg:classifiers":[
        {
            "category":"Home & Garden",
            "subcategory":"Garden Supply",
            "type":"Retail Goods"
        }
    ],
    "sg:phone":"+1 905 795 8088",
    "sg:postcode":"L5T 2A7",
    "sg:province":"ON",
    "sg:tags":[
        "sprinkler"
    ],
    "wof:name":"Central Irrigation Supply",
    "wof:placetype":"venue"
},
  "geometry": {"coordinates":[-79.6843338013,43.6603965759],"type":"Point"}
}