{
  "type": "Feature",
  "properties": {
    "addr:full":"435 10th Ave Cochrane ON P0L 1C0",
    "addr:housenumber":"435",
    "addr:postcode":"p0l 1c0",
    "addr:street":"10Th Ave",
    "iso:country":"CA",
    "sg:address":"435 10th Ave",
    "sg:city":"Cochrane",
    "sg:classifiers":[
        {
            "category":"Social Services",
            "subcategory":"Child Care",
            "type":"Services"
        }
    ],
    "sg:phone":"+1 705 272 6092",
    "sg:postcode":"P0L 1C0",
    "sg:province":"ON",
    "wof:name":"Cochrane Child Care Ctr Day",
    "wof:placetype":"venue"
},
  "geometry": {"coordinates":[-81.01918000000001,49.069698],"type":"Point"}
}