{
  "type": "Feature",
  "properties": {
    "addr:full":"14905 1E Av Saint-Georges QC G5Y 2E8",
    "addr:housenumber":"14905",
    "addr:postcode":"g5y 2e8",
    "addr:street":"1E Av",
    "iso:country":"CA",
    "sg:address":"14905 1E Av",
    "sg:city":"Saint-Georges",
    "sg:classifiers":[
        {
            "category":"Retail",
            "subcategory":"Repair Shop",
            "type":"Services"
        }
    ],
    "sg:phone":"+1 418 228 8511",
    "sg:postcode":"G5Y 2E8",
    "sg:province":"QC",
    "sg:tags":[
        "lock",
        "locksmith"
    ],
    "wof:name":"Serrurier Rancourt",
    "wof:placetype":"venue"
},
  "geometry": {"coordinates":[-70.67115020750001,46.1233482361],"type":"Point"}
}