{
  "type": "Feature",
  "properties": {
    "addr:full":"2342 Clarke St Port Moody BC V3H 1Y8",
    "addr:housenumber":"2342",
    "addr:postcode":"v3h 1y8",
    "addr:street":"Clarke St",
    "iso:country":"CA",
    "sg:address":"2342 Clarke St",
    "sg:city":"Port Moody",
    "sg:classifiers":[
        {
            "category":"Shopping",
            "subcategory":"Musical Instruments",
            "type":"Retail Goods"
        }
    ],
    "sg:phone":"+1 604 937 0703",
    "sg:postcode":"V3H 1Y8",
    "sg:province":"BC",
    "wof:name":"Crossroads Guitar",
    "wof:placetype":"venue"
},
  "geometry": {"coordinates":[-122.86039,49.277966],"type":"Point"}
}