{
  "type": "Feature",
  "properties": {
    "addr:full":"5629 Boul Jean-Xxiii Trois-Rivieres-Ouest QC G8Z 4B2",
    "addr:housenumber":"5629",
    "addr:postcode":"g8z 4b2",
    "addr:street":"Boul Jean-Xxiii Trois-Rivieres-Ouest",
    "iso:country":"CA",
    "sg:address":"5629 Boul Jean-Xxiii",
    "sg:city":"Trois-Rivieres-Ouest",
    "sg:classifiers":[
        {
            "category":"Personal",
            "subcategory":"Shoe Repair & Shine",
            "type":"Services"
        }
    ],
    "sg:phone":"+1 819 378 0567",
    "sg:postcode":"G8Z 4B2",
    "sg:province":"QC",
    "sg:tags":[
        "repairing",
        "boot"
    ],
    "wof:name":"Cordonnerie Trois-Rivieres-O",
    "wof:placetype":"venue"
},
  "geometry": {"coordinates":[-72.591286,46.333881],"type":"Point"}
}