{
  "type": "Feature",
  "properties": {
    "addr:full":"535 Mill St Woodstock ON N4S 7V6",
    "addr:housenumber":"535",
    "addr:postcode":"n4s 7v6",
    "addr:street":"Mill St",
    "iso:country":"CA",
    "sg:address":"535 Mill St",
    "sg:city":"Woodstock",
    "sg:classifiers":[
        {
            "category":"Personal",
            "subcategory":"Beauty Salon",
            "type":"Services"
        }
    ],
    "sg:phone":"+1 519 537 3191",
    "sg:postcode":"N4S 7V6",
    "sg:province":"ON",
    "wof:name":"European Hair & Beauty Salon",
    "wof:placetype":"venue"
},
  "geometry": {"coordinates":[-80.758247,43.103832],"type":"Point"}
}