{
  "type": "Feature",
  "properties": {
    "addr:full":"100 Water St St Andrews NB E5B 1A6",
    "addr:housenumber":"100",
    "addr:postcode":"e5b 1a6",
    "addr:street":"Water St",
    "iso:country":"CA",
    "sg:address":"100 Water St",
    "sg:city":"St Andrews",
    "sg:classifiers":[
        {
            "category":"Food & Beverages",
            "subcategory":"Liquor & Beverages",
            "type":"Retail Goods"
        }
    ],
    "sg:phone":"+1 506 529 6250",
    "sg:postcode":"E5B 1A6",
    "sg:province":"NB",
    "sg:tags":[
        "store"
    ],
    "wof:name":"N B Liquor Corp",
    "wof:placetype":"venue"
},
  "geometry": {"coordinates":[-67.05666351319999,45.0755462646],"type":"Point"}
}