{
  "type": "Feature",
  "properties": {
    "addr:full":"2336 Ch Sainte-Foy Sainte-Foy QC G1V 1S5",
    "addr:housenumber":"2336",
    "addr:postcode":"g1v 1s5",
    "addr:street":"Ch Sainte-Foy",
    "iso:country":"CA",
    "sg:address":"2336 Ch Sainte-Foy",
    "sg:city":"Sainte-Foy",
    "sg:classifiers":[
        {
            "category":"Cinema",
            "subcategory":"Movie Rental",
            "type":"Entertainment"
        }
    ],
    "sg:phone":"+1 418 653 6969",
    "sg:postcode":"G1V 1S5",
    "sg:province":"QC",
    "sg:tags":[
        "leasing",
        "video",
        "disc",
        "tape"
    ],
    "wof:name":"Club Video Eclair",
    "wof:placetype":"venue"
},
  "geometry": {"coordinates":[-71.2917633057,46.7692108154],"type":"Point"}
}