{
  "type": "Feature",
  "properties": {
    "addr:full":"498 Puntledge Rd Courtenay BC V9N 3R1",
    "addr:housenumber":"498",
    "addr:postcode":"v9n 3r1",
    "addr:street":"Puntledge Rd",
    "iso:country":"CA",
    "sg:address":"498 Puntledge Rd",
    "sg:city":"Courtenay",
    "sg:classifiers":[
        {
            "category":"Retail",
            "subcategory":"Auto Repair",
            "type":"Services"
        }
    ],
    "sg:phone":"+1 250 334 4932",
    "sg:postcode":"V9N 3R1",
    "sg:province":"BC",
    "sg:tags":[
        "repairing",
        "automobile",
        "radiator"
    ],
    "wof:name":"Island Radiator & Battery",
    "wof:placetype":"venue"
},
  "geometry": {"coordinates":[-124.99020400000001,49.696953],"type":"Point"}
}