{
  "type": "Feature",
  "properties": {
    "iso:country":"CA",
    "sg:address":"356 Ch Duval E",
    "sg:city":"Vassan",
    "sg:classifiers":[
        {
            "category":"Building & Trades",
            "subcategory":"Electrical",
            "type":"Services"
        }
    ],
    "sg:phone":"+1 819 824 8419",
    "sg:postcode":"J0Y 2R0",
    "sg:province":"QC",
    "sg:tags":[
        "electric",
        "contractor"
    ],
    "wof:name":"C C Voltex Inc",
    "wof:placetype":"venue"
},
  "geometry": {"coordinates":[-77.84799957280001,48.2290344238],"type":"Point"}
}