{
  "type": "Feature",
  "properties": {
    "addr:full":"5349 Maingate Dr Mississauga ON L4W 1G6",
    "addr:housenumber":"5349",
    "addr:postcode":"l4w 1g6",
    "addr:street":"Maingate Dr",
    "iso:country":"CA",
    "sg:address":"5349 Maingate Dr",
    "sg:city":"Mississauga",
    "sg:classifiers":[
        {
            "category":"Wholesale",
            "subcategory":"Metals & Minerals",
            "type":"Manufacturing & Wholesale Goods"
        }
    ],
    "sg:phone":"+1 905 212 1565",
    "sg:postcode":"L4W 1G6",
    "sg:province":"ON",
    "sg:tags":[
        "steel",
        "warehouse"
    ],
    "wof:name":"Steelebank Inc",
    "wof:placetype":"venue"
},
  "geometry": {"coordinates":[-79.6337738037,43.63489151],"type":"Point"}
}