{
  "type": "Feature",
  "properties": {
    "iso:country":"CA",
    "sg:address":"230 Airport Blvd",
    "sg:city":"Gander",
    "sg:classifiers":[
        {
            "category":"Food & Beverages",
            "subcategory":"Liquor & Beverages",
            "type":"Retail Goods"
        }
    ],
    "sg:phone":"+1 709 651 3915",
    "sg:postcode":"A1V 1L7",
    "sg:province":"NL",
    "sg:tags":[
        "store"
    ],
    "wof:name":"Newfoundland Liquor Corp",
    "wof:placetype":"venue"
},
  "geometry": {"coordinates":[-54.6068649292,48.9558258057],"type":"Point"}
}