{
  "type": "Feature",
  "properties": {
    "addr:full":"9816 5 St SE Calgary AB T2J 1K9",
    "addr:housenumber":"9816 5",
    "addr:postcode":"t2j 1k9",
    "addr:street":"St Se",
    "iso:country":"CA",
    "sg:address":"9816 5 St SE",
    "sg:city":"Calgary",
    "sg:classifiers":[
        {
            "category":"Building & Trades",
            "subcategory":"Construction",
            "type":"Services"
        }
    ],
    "sg:phone":"+1 403 255 4155",
    "sg:postcode":"T2J 1K9",
    "sg:province":"AB",
    "sg:tags":[
        "roofing",
        "contractor"
    ],
    "wof:name":"K-4 Consulting & Coatings",
    "wof:placetype":"venue"
},
  "geometry": {"coordinates":[-114.052025,50.965702],"type":"Point"}
}