{
  "type": "Feature",
  "properties": {
    "iso:country":"CA",
    "sg:city":"Irricana",
    "sg:classifiers":[
        {
            "category":"Museum",
            "type":"Entertainment"
        }
    ],
    "sg:phone":"+1 403 935 4357",
    "sg:postcode":"T0M 1B0",
    "sg:province":"AB",
    "wof:name":"Pioneer Acres of Alberta",
    "wof:placetype":"venue"
},
  "geometry": {"coordinates":[-113.59141540500001,51.3250465393],"type":"Point"}
}