{
  "type": "Feature",
  "properties": {
    "addr:full":"Langley BC V3A 5E8",
    "addr:postcode":"v3a 5e8",
    "iso:country":"CA",
    "sg:city":"Langley",
    "sg:classifiers":[
        {
            "category":"Home & Garden",
            "subcategory":"Home Furnishings",
            "type":"Retail Goods"
        }
    ],
    "sg:phone":"+1 604 533 2198",
    "sg:postcode":"V3A 5E8",
    "sg:province":"BC",
    "sg:tags":[
        "equipment",
        "fireplace"
    ],
    "wof:name":"Heat Zone",
    "wof:placetype":"venue"
},
  "geometry": {"coordinates":[-122.64724,49.112793],"type":"Point"}
}