{
  "type": "Feature",
  "properties": {
    "iso:country":"CA",
    "sg:address":"232 Echo Lake Rd",
    "sg:city":"Echo Bay",
    "sg:classifiers":[
        {
            "category":"Manufacturing",
            "subcategory":"Tools & Machinery",
            "type":"Manufacturing & Wholesale Goods"
        }
    ],
    "sg:phone":"+1 705 248 3421",
    "sg:postcode":"P0S 1C0",
    "sg:province":"ON",
    "sg:tags":[
        "machine",
        "shop"
    ],
    "wof:name":"Algo Machine Shop Ltd",
    "wof:placetype":"venue"
},
  "geometry": {"coordinates":[-84.0700454712,46.4849357605],"type":"Point"}
}