{
  "type": "Feature",
  "properties": {
    "addr:full":"35 Dunmurray Blvd Scarborough ON M1T 2K2",
    "addr:housenumber":"35",
    "addr:postcode":"m1t 2k2",
    "addr:street":"Dunmurray Blvd",
    "iso:country":"CA",
    "sg:address":"35 Dunmurray Blvd",
    "sg:city":"Scarborough",
    "sg:classifiers":[
        {
            "category":"Education",
            "subcategory":"School",
            "type":"Public Place"
        }
    ],
    "sg:phone":"+1 416 396 6510",
    "sg:postcode":"M1T 2K2",
    "sg:province":"ON",
    "wof:name":"Pauline Johnson Jr School",
    "wof:placetype":"venue"
},
  "geometry": {"coordinates":[-79.304001,43.785355],"type":"Point"}
}