{
  "type": "Feature",
  "properties": {
    "addr:full":"610 Alden Rd Markham ON L3R 9Z1",
    "addr:housenumber":"610",
    "addr:postcode":"l3r 9z1",
    "addr:street":"Alden Rd",
    "iso:country":"CA",
    "sg:address":"610 Alden Rd",
    "sg:city":"Markham",
    "sg:classifiers":[
        {
            "category":"Professional",
            "subcategory":"Computer Services",
            "type":"Services"
        }
    ],
    "sg:phone":"+1 905 946 0192",
    "sg:postcode":"L3R 9Z1",
    "sg:province":"ON",
    "sg:tags":[
        "information",
        "system",
        "consultant"
    ],
    "wof:name":"Ajc & Assoc Inc",
    "wof:placetype":"venue"
},
  "geometry": {"coordinates":[-79.3312454224,43.8373031616],"type":"Point"}
}