{
  "type": "Feature",
  "properties": {
    "addr:full":"1016 8 St SW Calgary AB T2R 1K2",
    "addr:housenumber":"1016 8",
    "addr:postcode":"t2r 1k2",
    "addr:street":"St Sw",
    "iso:country":"CA",
    "sg:address":"1016 8 St SW",
    "sg:city":"Calgary",
    "sg:classifiers":[
        {
            "category":"Restaurant",
            "type":"Food & Drink"
        }
    ],
    "sg:phone":"+1 403 262 8480",
    "sg:postcode":"T2R 1K2",
    "sg:province":"AB",
    "wof:name":"Bonterra Restaurant Ltd",
    "wof:placetype":"venue"
},
  "geometry": {"coordinates":[-114.081192,51.04361],"type":"Point"}
}