{
  "type": "Feature",
  "properties": {
    "addr:full":"180 Dufferin St Bridgewater NS B4V 2G7",
    "addr:housenumber":"180",
    "addr:postcode":"b4v 2g7",
    "addr:street":"Dufferin St",
    "iso:country":"CA",
    "sg:address":"180 Dufferin St",
    "sg:city":"Bridgewater",
    "sg:classifiers":[
        {
            "category":"Real Estate",
            "subcategory":"Real Estate Agent",
            "type":"Services"
        }
    ],
    "sg:phone":"+1 902 543 3000",
    "sg:postcode":"B4V 2G7",
    "sg:province":"NS",
    "sg:tags":[
        "appraiser"
    ],
    "wof:name":"Kempton Appraisals",
    "wof:placetype":"venue"
},
  "geometry": {"coordinates":[-64.52239227290001,44.3707618713],"type":"Point"}
}