{
  "type": "Feature",
  "properties": {
    "addr:full":"2535 Jefferson Blvd Windsor ON N8T 2W5",
    "addr:housenumber":"2535",
    "addr:postcode":"n8t 2w5",
    "addr:street":"Jefferson Blvd",
    "iso:country":"CA",
    "sg:address":"2535 Jefferson Blvd",
    "sg:city":"Windsor",
    "sg:classifiers":[
        {
            "category":"Health Services",
            "subcategory":"Chiropractor",
            "type":"Services"
        }
    ],
    "sg:phone":"+1 519 948 9710",
    "sg:postcode":"N8T 2W5",
    "sg:province":"ON",
    "wof:name":"Family Chiropractic Wellness",
    "wof:placetype":"venue"
},
  "geometry": {"coordinates":[-82.9500656128,42.307308197],"type":"Point"}
}