{
  "type": "Feature",
  "properties": {
    "addr:full":"Calgary AB T2B 3K7",
    "addr:postcode":"t2b 3k7",
    "iso:country":"CA",
    "sg:city":"Calgary",
    "sg:classifiers":[
        {
            "category":"Retail",
            "subcategory":"Repair Shop",
            "type":"Services"
        }
    ],
    "sg:phone":"+1 403 569 7444",
    "sg:postcode":"T2B 3K7",
    "sg:province":"AB",
    "sg:tags":[
        "tool",
        "grinding"
    ],
    "wof:name":"Calmet Industrial Supply Ltd",
    "wof:placetype":"venue"
},
  "geometry": {"coordinates":[-113.987312317,51.0124511719],"type":"Point"}
}