{
  "type": "Feature",
  "properties": {
    "addr:full":"Riverside Dr Hunter River PE C0A 1N0",
    "addr:postcode":"c0a 1n0",
    "addr:street":"Riverside Dr",
    "iso:country":"CA",
    "sg:address":"Riverside Dr",
    "sg:city":"Hunter River",
    "sg:classifiers":[
        {
            "category":"Government",
            "subcategory":"Office",
            "type":"Public Place"
        }
    ],
    "sg:phone":"+1 902 963 3211",
    "sg:postcode":"C0A 1N0",
    "sg:province":"PE",
    "sg:tags":[
        "village"
    ],
    "wof:name":"North Rustico Community Ofc",
    "wof:placetype":"venue"
},
  "geometry": {"coordinates":[-63.343147,46.351761],"type":"Point"}
}