{
  "type": "Feature",
  "properties": {
    "addr:full":"Ottawa ON K2P 1P9",
    "addr:postcode":"k2p 1p9",
    "iso:country":"CA",
    "sg:city":"Ottawa",
    "sg:classifiers":[
        {
            "category":"Professional",
            "subcategory":"Lawyer & Legal Services",
            "type":"Services"
        }
    ],
    "sg:phone":"+1 613 236 6628",
    "sg:postcode":"K2P 1P9",
    "sg:province":"ON",
    "sg:tags":[
        "attorney"
    ],
    "wof:name":"Potvin Law Office",
    "wof:placetype":"venue"
},
  "geometry": {"coordinates":[-75.69270299999999,45.417572],"type":"Point"}
}