{
  "type": "Feature",
  "properties": {
    "addr:full":"39 Mount Pleasant St Brantford ON N3T 1S7",
    "addr:housenumber":"39",
    "addr:postcode":"n3t 1s7",
    "addr:street":"Mount Pleasant St",
    "iso:country":"CA",
    "sg:address":"39 Mount Pleasant St",
    "sg:city":"Brantford",
    "sg:classifiers":[
        {
            "category":"Recreation",
            "type":"Entertainment"
        }
    ],
    "sg:phone":"+1 519 753 3153",
    "sg:postcode":"N3T 1S7",
    "sg:province":"ON",
    "sg:tags":[
        "youth",
        "information",
        "activity",
        "center",
        "organization"
    ],
    "wof:name":"Lansdowne Children's Ctr",
    "wof:placetype":"venue"
},
  "geometry": {"coordinates":[-80.275772,43.130451],"type":"Point"}
}