{
  "type": "Feature",
  "properties": {
    "iso:country":"CA",
    "sg:address":"2020 Springfield Rd",
    "sg:city":"Kelowna",
    "sg:classifiers":[
        {
            "category":"Retail",
            "subcategory":"Funeral Services",
            "type":"Services"
        }
    ],
    "sg:phone":"+1 250 860 7077",
    "sg:postcode":"V1Y 5V8",
    "sg:province":"BC",
    "sg:tags":[
        "director",
        "monument"
    ],
    "wof:name":"Springfield Funeral Home Ltd",
    "wof:placetype":"venue"
},
  "geometry": {"coordinates":[-119.449020386,49.8774490356],"type":"Point"}
}