{
  "type": "Feature",
  "properties": {
    "iso:country":"CA",
    "sg:city":"Cawston",
    "sg:classifiers":[
        {
            "category":"Food & Beverages",
            "subcategory":"Fruits & Vegetables",
            "type":"Retail Goods"
        }
    ],
    "sg:phone":"+1 250 499 2751",
    "sg:postcode":"V0X 1C0",
    "sg:province":"BC",
    "sg:tags":[
        "produce"
    ],
    "wof:name":"Harker's Fruit Ranch",
    "wof:placetype":"venue"
},
  "geometry": {"coordinates":[-119.751327515,49.1735076904],"type":"Point"}
}