{
  "type": "Feature",
  "properties": {
    "addr:full":"89 Foxtrap Access Rd Conception Bay South NL A1X 7N6",
    "addr:housenumber":"89",
    "addr:postcode":"a1x 7n6",
    "addr:street":"Foxtrap Access Rd",
    "iso:country":"CA",
    "sg:address":"89 Foxtrap Access Rd",
    "sg:city":"Conception Bay South",
    "sg:classifiers":[
        {
            "category":"Food & Beverages",
            "subcategory":"Groceries & Convenience Stores",
            "type":"Retail Goods"
        }
    ],
    "sg:phone":"+1 709 834 8505",
    "sg:postcode":"A1X 7N6",
    "sg:province":"NL",
    "wof:name":"Myrt's Store",
    "wof:placetype":"venue"
},
  "geometry": {"coordinates":[-52.968876,47.512619],"type":"Point"}
}