{
  "type": "Feature",
  "properties": {
    "addr:full":"11 Water St Elgin ON K0G 1E0",
    "addr:housenumber":"11",
    "addr:postcode":"k0g 1e0",
    "addr:street":"Water St",
    "iso:country":"CA",
    "sg:address":"11 Water St",
    "sg:city":"Elgin",
    "sg:classifiers":[
        {
            "category":"Professional",
            "subcategory":"Lawyer & Legal Services",
            "type":"Services"
        }
    ],
    "sg:phone":"+1 613 359 5108",
    "sg:postcode":"K0G 1E0",
    "sg:province":"ON",
    "sg:tags":[
        "attorney"
    ],
    "wof:name":"Monaghan, Jane",
    "wof:placetype":"venue"
},
  "geometry": {"coordinates":[-76.222252,44.607475],"type":"Point"}
}