{
  "type": "Feature",
  "properties": {
    "addr:full":"4201 Blakie Rd London ON N6L 1B9",
    "addr:housenumber":"4201",
    "addr:postcode":"n6l 1b9",
    "addr:street":"Blakie Rd",
    "iso:country":"CA",
    "sg:address":"4201 Blakie Rd",
    "sg:city":"London",
    "sg:classifiers":[
        {
            "category":"Building & Trades",
            "subcategory":"Landscaping Services",
            "type":"Services"
        }
    ],
    "sg:phone":"+1 519 652 5229",
    "sg:postcode":"N6L 1B9",
    "sg:province":"ON",
    "sg:tags":[
        "excavating",
        "tree",
        "contractor"
    ],
    "wof:name":"C H Excavating Ltd",
    "wof:placetype":"venue"
},
  "geometry": {"coordinates":[-81.25384521479999,42.9193382263],"type":"Point"}
}