{
  "type": "Feature",
  "properties": {
    "addr:full":"2375 Trans Canada Way SE Medicine Hat AB T1B 4E9",
    "addr:housenumber":"2375",
    "addr:postcode":"t1b 4e9",
    "addr:street":"Trans Canada Way Se",
    "iso:country":"CA",
    "sg:address":"2375 Trans Canada Way SE",
    "sg:city":"Medicine Hat",
    "sg:classifiers":[
        {
            "category":"Restaurant",
            "type":"Food & Drink"
        }
    ],
    "sg:phone":"+1 403 529 0600",
    "sg:postcode":"T1B 4E9",
    "sg:province":"AB",
    "wof:name":"Wendy's",
    "wof:placetype":"venue"
},
  "geometry": {"coordinates":[-110.669487,50.008072],"type":"Point"}
}