{
  "type": "Feature",
  "properties": {
    "addr:full":"Edmonton AB T6E 5Y4",
    "addr:postcode":"t6e 5y4",
    "iso:country":"CA",
    "sg:city":"Edmonton",
    "sg:classifiers":[
        {
            "category":"Restaurant",
            "type":"Food & Drink"
        }
    ],
    "sg:phone":"+1 780 485 1514",
    "sg:postcode":"T6E 5Y4",
    "sg:province":"AB",
    "sg:tags":[
        "caterer"
    ],
    "wof:name":"North Country Catering",
    "wof:placetype":"venue"
},
  "geometry": {"coordinates":[-113.477790833,53.4790306091],"type":"Point"}
}