{
  "type": "Feature",
  "properties": {
    "addr:full":"Markham ON L3R 2N7",
    "addr:postcode":"l3r 2n7",
    "iso:country":"CA",
    "sg:city":"Markham",
    "sg:classifiers":[
        {
            "category":"Banks & Credit Unions",
            "subcategory":"Investment Brokerage",
            "type":"Services"
        }
    ],
    "sg:phone":"+1 905 477 4999",
    "sg:postcode":"L3R 2N7",
    "sg:province":"ON",
    "sg:tags":[
        "consultant",
        "planning",
        "financial"
    ],
    "wof:name":"Afg Financial Svc Ltd",
    "wof:placetype":"venue"
},
  "geometry": {"coordinates":[-79.3539199829,43.8331222534],"type":"Point"}
}