{
  "type": "Feature",
  "properties": {
    "addr:full":"Cp 24 Succ Bureau-Chef Lachute QC J8H 3X2",
    "addr:housenumber":"24",
    "addr:postcode":"j8h 3x2",
    "addr:street":"Cp;Bureau-Chef",
    "iso:country":"CA",
    "sg:address":"Cp 24 Succ Bureau-Chef",
    "sg:city":"Lachute",
    "sg:classifiers":[
        {
            "category":"Organizations",
            "subcategory":"Religious Organization",
            "type":"Services"
        }
    ],
    "sg:phone":"+1 514 537 3897",
    "sg:postcode":"J8H 3X2",
    "sg:province":"QC",
    "sg:tags":[
        "church"
    ],
    "wof:name":"Assemblee Chretienne D Argente",
    "wof:placetype":"venue"
},
  "geometry": {"coordinates":[-74.3405532837,45.6558456421],"type":"Point"}
}