{
  "type": "Feature",
  "properties": {
    "addr:full":"2744 Ontario St Windsor ON N8Y 1N8",
    "addr:housenumber":"2744",
    "addr:postcode":"n8y 1n8",
    "addr:street":"Ontario St",
    "iso:country":"CA",
    "sg:address":"2744 Ontario St",
    "sg:city":"Windsor",
    "sg:classifiers":[
        {
            "category":"Shopping",
            "type":"Retail Goods"
        }
    ],
    "sg:phone":"+1 519 252 7473",
    "sg:postcode":"N8Y 1N8",
    "sg:province":"ON",
    "sg:tags":[
        "awning",
        "canopy"
    ],
    "wof:name":"Accurate Awning",
    "wof:placetype":"venue"
},
  "geometry": {"coordinates":[-82.99862670900001,42.3183021545],"type":"Point"}
}