{
  "type": "Feature",
  "properties": {
    "addr:full":"1040 Bellevue Rd Parksville BC V9P 2C2",
    "addr:housenumber":"1040",
    "addr:postcode":"v9p 2c2",
    "addr:street":"Bellevue Rd",
    "iso:country":"CA",
    "sg:address":"1040 Bellevue Rd",
    "sg:city":"Parksville",
    "sg:classifiers":[
        {
            "category":"Retail",
            "subcategory":"Repair Shop",
            "type":"Services"
        }
    ],
    "sg:phone":"+1 250 954 5494",
    "sg:postcode":"V9P 2C2",
    "sg:province":"BC",
    "sg:tags":[
        "appliance"
    ],
    "wof:name":"Bellevue Trade Ctr",
    "wof:placetype":"venue"
},
  "geometry": {"coordinates":[-124.31364440900001,49.3196907043],"type":"Point"}
}