{
  "type": "Feature",
  "properties": {
    "addr:full":"260 Bell Blvd Belleville ON K8P 5H6",
    "addr:housenumber":"260",
    "addr:postcode":"k8p 5h6",
    "addr:street":"Bell Blvd",
    "iso:country":"CA",
    "sg:address":"260 Bell Blvd",
    "sg:city":"Belleville",
    "sg:classifiers":[
        {
            "category":"Home & Garden",
            "subcategory":"Building Materials",
            "type":"Retail Goods"
        }
    ],
    "sg:phone":"+1 613 967 8080",
    "sg:postcode":"K8P 5H6",
    "sg:province":"ON",
    "wof:name":"Rona Cashway Building Ctr",
    "wof:placetype":"venue"
},
  "geometry": {"coordinates":[-77.41021000000001,44.1852],"type":"Point"}
}