{
  "type": "Feature",
  "properties": {
    "addr:full":"Grandes-Bergeronnes QC G0T 1G0",
    "addr:postcode":"g0t 1g0",
    "iso:country":"CA",
    "sg:city":"Grandes-Bergeronnes",
    "sg:classifiers":[
        {
            "category":"Travel",
            "subcategory":"Campground",
            "type":"Entertainment"
        }
    ],
    "sg:phone":"+1 418 232 2020",
    "sg:postcode":"G0T 1G0",
    "sg:province":"QC",
    "sg:tags":[
        "camp",
        "fishing"
    ],
    "wof:name":"Club Lac Des Sables & Paradis",
    "wof:placetype":"venue"
},
  "geometry": {"coordinates":[-69.626732,48.258553],"type":"Point"}
}