{
  "type": "Feature",
  "properties": {
    "addr:full":"3550 Rue Jeanne-Mance Montreal QC H2X 3P7",
    "addr:housenumber":"3550",
    "addr:postcode":"h2x 3p7",
    "addr:street":"Rue Jeanne-Mance",
    "iso:country":"CA",
    "sg:address":"3550 Rue Jeanne-Mance",
    "sg:city":"Montreal",
    "sg:classifiers":[
        {
            "category":"Arts & Performance",
            "subcategory":"Theater",
            "type":"Entertainment"
        }
    ],
    "sg:phone":"+1 514 844 2784",
    "sg:postcode":"H2X 3P7",
    "sg:province":"QC",
    "sg:tags":[
        "bureau"
    ],
    "wof:name":"I D Spec",
    "wof:placetype":"venue"
},
  "geometry": {"coordinates":[-73.5741348267,45.5105743408],"type":"Point"}
}