{
  "type": "Feature",
  "properties": {
    "iso:country":"CA",
    "sg:address":"5653 Boul Henri-Bourassa E # 102",
    "sg:city":"Montreal-Nord",
    "sg:classifiers":[
        {
            "category":"Government",
            "subcategory":"Police Station",
            "type":"Public Place"
        }
    ],
    "sg:phone":"+1 514 594 1217",
    "sg:postcode":"H1G 2T4",
    "sg:province":"QC",
    "sg:tags":[
        "bailiff"
    ],
    "wof:name":"Vitale Guiseppe Huissier",
    "wof:placetype":"venue"
},
  "geometry": {"coordinates":[-73.6208114624,45.6066169739],"type":"Point"}
}