{
  "type": "Feature",
  "properties": {
    "addr:full":"306 King St E Gananoque ON K7G 1G7",
    "addr:housenumber":"306",
    "addr:postcode":"k7g 1g7",
    "addr:street":"King St E",
    "iso:country":"CA",
    "sg:address":"306 King St E",
    "sg:city":"Gananoque",
    "sg:classifiers":[
        {
            "category":"Personal",
            "subcategory":"Barber",
            "type":"Services"
        }
    ],
    "sg:phone":"+1 613 382 2686",
    "sg:postcode":"K7G 1G7",
    "sg:province":"ON",
    "wof:name":"Cindy's Barber & Unisex Hair",
    "wof:placetype":"venue"
},
  "geometry": {"coordinates":[-76.1585769653,44.3323020935],"type":"Point"}
}