{
  "type": "Feature",
  "properties": {
    "addr:full":"3809 48 Ave Camrose AB T4V 2Y9",
    "addr:housenumber":"3809",
    "addr:postcode":"t4v 2y9",
    "addr:street":"48 Ave",
    "iso:country":"CA",
    "sg:address":"3809 48 Ave",
    "sg:city":"Camrose",
    "sg:classifiers":[
        {
            "category":"Retail",
            "subcategory":"Repair Shop",
            "type":"Services"
        }
    ],
    "sg:phone":"+1 780 672 4466",
    "sg:postcode":"T4V 2Y9",
    "sg:province":"AB",
    "sg:tags":[
        "upholsterer"
    ],
    "wof:name":"Camrose Upholstery",
    "wof:placetype":"venue"
},
  "geometry": {"coordinates":[-112.80445899999999,53.017799],"type":"Point"}
}