{
  "type": "Feature",
  "properties": {
    "iso:country":"CA",
    "sg:city":"Edmonton",
    "sg:classifiers":[
        {
            "category":"Wholesale",
            "subcategory":"Vending Machines",
            "type":"Manufacturing & Wholesale Goods"
        }
    ],
    "sg:phone":"+1 780 438 3542",
    "sg:postcode":"T6E 5P3",
    "sg:province":"AB",
    "wof:name":"Aramark Refreshments Svc",
    "wof:placetype":"venue"
},
  "geometry": {"coordinates":[-113.48346710200001,53.4849967957],"type":"Point"}
}