{
  "type": "Feature",
  "properties": {
    "addr:full":"5001 Yonge St North York ON M2N 6P6",
    "addr:housenumber":"5001",
    "addr:postcode":"m2n 6p6",
    "addr:street":"Yonge St",
    "iso:country":"CA",
    "sg:address":"5001 Yonge St",
    "sg:city":"North York",
    "sg:classifiers":[
        {
            "category":"Banks & Credit Unions",
            "subcategory":"Bank",
            "type":"Services"
        }
    ],
    "sg:phone":"+1 416 512 4600",
    "sg:postcode":"M2N 6P6",
    "sg:province":"ON",
    "wof:name":"Royal Bank Financial Group",
    "wof:placetype":"venue"
},
  "geometry": {"coordinates":[-79.411888,43.765797],"type":"Point"}
}