{
  "type": "Feature",
  "properties": {
    "iso:country":"CA",
    "sg:address":"125 Rue Augusta",
    "sg:city":"Sorel-Tracy",
    "sg:classifiers":[
        {
            "category":"Health Services",
            "subcategory":"Nursing And Care Facility",
            "type":"Services"
        }
    ],
    "sg:phone":"+1 450 746 8406",
    "sg:postcode":"J3P 1B1",
    "sg:province":"QC",
    "sg:tags":[
        "home",
        "retirement",
        "community"
    ],
    "wof:name":"Villa Du Mimosa",
    "wof:placetype":"venue"
},
  "geometry": {"coordinates":[-73.1112213135,46.0466804504],"type":"Point"}
}