{
  "type": "Feature",
  "properties": {
    "addr:full":"993 Fir St Sherwood Park AB T8A 4N5",
    "addr:housenumber":"993",
    "addr:postcode":"t8a 4n5",
    "addr:street":"Fir St",
    "iso:country":"CA",
    "sg:address":"993 Fir St",
    "sg:city":"Sherwood Park",
    "sg:classifiers":[
        {
            "category":"Retail",
            "subcategory":"Veterinary Services",
            "type":"Services"
        }
    ],
    "sg:phone":"+1 780 467 6223",
    "sg:postcode":"T8A 4N5",
    "sg:province":"AB",
    "sg:tags":[
        "veterinarian"
    ],
    "wof:name":"Lakeside Veterinary Clinic",
    "wof:placetype":"venue"
},
  "geometry": {"coordinates":[-113.322395,53.513565],"type":"Point"}
}