{
  "type": "Feature",
  "properties": {
    "addr:full":"2301 Rue Demers Drummondville QC J2B 1V4",
    "addr:housenumber":"2301",
    "addr:postcode":"j2b 1v4",
    "addr:street":"Rue Demers",
    "iso:country":"CA",
    "sg:address":"2301 Rue Demers",
    "sg:city":"Drummondville",
    "sg:classifiers":[
        {
            "category":"Shopping",
            "subcategory":"Jewelry",
            "type":"Retail Goods"
        }
    ],
    "sg:phone":"+1 819 478 0898",
    "sg:postcode":"J2B 1V4",
    "sg:province":"QC",
    "sg:tags":[
        "jeweler"
    ],
    "wof:name":"Bijouterie Jacques Enrg",
    "wof:placetype":"venue"
},
  "geometry": {"coordinates":[-72.4819488525,45.8741149902],"type":"Point"}
}