{
  "type": "Feature",
  "properties": {
    "addr:full":"115 Lilac Dr Sherwood Park AB T8H 1S7",
    "addr:housenumber":"115",
    "addr:postcode":"t8h 1s7",
    "addr:street":"Lilac Dr",
    "iso:country":"CA",
    "sg:address":"115 Lilac Dr",
    "sg:city":"Sherwood Park",
    "sg:classifiers":[
        {
            "category":"Professional",
            "subcategory":"Secretarial Services",
            "type":"Services"
        }
    ],
    "sg:phone":"+1 780 464 6354",
    "sg:postcode":"T8H 1S7",
    "sg:province":"AB",
    "sg:tags":[
        "reporting",
        "court",
        "resume"
    ],
    "wof:name":"D M Typing Svc",
    "wof:placetype":"venue"
},
  "geometry": {"coordinates":[-113.250092,53.544609],"type":"Point"}
}