{
  "type": "Feature",
  "properties": {
    "addr:full":"122 Clyde Ave Mount Pearl NL A1N 4S3",
    "addr:housenumber":"122",
    "addr:postcode":"a1n 4s3",
    "addr:street":"Clyde Ave",
    "iso:country":"CA",
    "sg:address":"122 Clyde Ave",
    "sg:city":"Mount Pearl",
    "sg:classifiers":[
        {
            "category":"Wholesale",
            "subcategory":"Machinery & Supplies",
            "type":"Manufacturing & Wholesale Goods"
        }
    ],
    "sg:phone":"+1 709 747 0176",
    "sg:postcode":"A1N 4S3",
    "sg:province":"NL",
    "sg:tags":[
        "engine"
    ],
    "wof:name":"Cummins Eastern Canada",
    "wof:placetype":"venue"
},
  "geometry": {"coordinates":[-52.832787,47.524967],"type":"Point"}
}