{
  "type": "Feature",
  "properties": {
    "iso:country":"CA",
    "sg:address":"2305 22nd St W",
    "sg:city":"Saskatoon",
    "sg:classifiers":[
        {
            "category":"Restaurant",
            "type":"Food & Drink"
        }
    ],
    "sg:phone":"+1 306 978 6628",
    "sg:postcode":"S7M 0V6",
    "sg:province":"SK",
    "wof:name":"Red Rock Grill",
    "wof:placetype":"venue"
},
  "geometry": {"coordinates":[-106.706039429,52.1291122437],"type":"Point"}
}