{
  "type": "Feature",
  "properties": {
    "addr:full":"Calgary AB T2H 0K9",
    "addr:postcode":"t2h 0k9",
    "iso:country":"CA",
    "sg:city":"Calgary",
    "sg:classifiers":[
        {
            "category":"Health Services",
            "subcategory":"Chiropractor",
            "type":"Services"
        }
    ],
    "sg:phone":"+1 403 255 8161",
    "sg:postcode":"T2H 0K9",
    "sg:province":"AB",
    "wof:name":"Ladell, Scott A DC",
    "wof:placetype":"venue"
},
  "geometry": {"coordinates":[-114.071831,50.996162],"type":"Point"}
}