{
  "type": "Feature",
  "properties": {
    "iso:country":"CA",
    "sg:address":"14 Bryden Ave",
    "sg:city":"Cornwall",
    "sg:classifiers":[
        {
            "category":"Building & Trades",
            "subcategory":"Construction",
            "type":"Services"
        }
    ],
    "sg:phone":"+1 613 933 7202",
    "sg:postcode":"K6H 5M5",
    "sg:province":"ON",
    "sg:tags":[
        "concrete",
        "contractor"
    ],
    "wof:name":"S D & G Concrete & Constr",
    "wof:placetype":"venue"
},
  "geometry": {"coordinates":[-74.68756103520001,45.0232391357],"type":"Point"}
}