{
  "type": "Feature",
  "properties": {
    "addr:full":"130 Livingstone St Yorkton SK S3N 3A8",
    "addr:housenumber":"130",
    "addr:postcode":"s3n 3a8",
    "addr:street":"Livingstone St",
    "iso:country":"CA",
    "sg:address":"130 Livingstone St",
    "sg:city":"Yorkton",
    "sg:classifiers":[
        {
            "category":"Building & Trades",
            "subcategory":"Construction",
            "type":"Services"
        }
    ],
    "sg:phone":"+1 306 786 7055",
    "sg:postcode":"S3N 3A8",
    "sg:province":"SK",
    "sg:tags":[
        "downspouts",
        "repairing",
        "gutter",
        "remodeling",
        "contractor"
    ],
    "wof:name":"Everlast Eaves & Exteriors Ltd",
    "wof:placetype":"venue"
},
  "geometry": {"coordinates":[-102.45502500000001,51.207661],"type":"Point"}
}