{
  "type": "Feature",
  "properties": {
    "addr:full":"59 Rue Principale Lameque NB E8T 1N1",
    "addr:housenumber":"59",
    "addr:postcode":"e8t 1n1",
    "addr:street":"Rue Principale",
    "iso:country":"CA",
    "sg:address":"59 Rue Principale",
    "sg:city":"Lameque",
    "sg:classifiers":[
        {
            "category":"Shopping",
            "subcategory":"Clothing, Apparel, & Fashions",
            "type":"Retail Goods"
        }
    ],
    "sg:phone":"+1 506 344 2297",
    "sg:postcode":"E8T 1N1",
    "sg:province":"NB",
    "sg:tags":[
        "boutique",
        "furnishing"
    ],
    "wof:name":"Jean Limitee",
    "wof:placetype":"venue"
},
  "geometry": {"coordinates":[-64.648071,47.793522],"type":"Point"}
}