{
  "type": "Feature",
  "properties": {
    "iso:country":"CA",
    "sg:address":"3133 Main St",
    "sg:city":"Vancouver",
    "sg:classifiers":[
        {
            "category":"Health Services",
            "subcategory":"Doctor",
            "type":"Services"
        }
    ],
    "sg:phone":"+1 604 873 1107",
    "sg:postcode":"V5T 3G8",
    "sg:province":"BC",
    "sg:tags":[
        "physician",
        "surgeon"
    ],
    "wof:name":"Edgardo Wee Inc",
    "wof:placetype":"venue"
},
  "geometry": {"coordinates":[-123.10134887700001,49.2572059631],"type":"Point"}
}