{
  "type": "Feature",
  "properties": {
    "iso:country":"CA",
    "sg:address":"5706 Ferry St",
    "sg:city":"Niagara Falls",
    "sg:classifiers":[
        {
            "category":"Travel",
            "subcategory":"Hotels & Motels",
            "type":"Entertainment"
        }
    ],
    "sg:phone":"+1 905 356 0052",
    "sg:postcode":"L2G 1S7",
    "sg:province":"ON",
    "wof:name":"Super 8 Hotel",
    "wof:placetype":"venue"
},
  "geometry": {"coordinates":[-79.08880615229999,43.0893821716],"type":"Point"}
}