{
  "type": "Feature",
  "properties": {
    "addr:full":"52 Piper Dr Red Deer AB T4P 1H8",
    "addr:housenumber":"52",
    "addr:postcode":"t4p 1h8",
    "addr:street":"Piper Dr",
    "iso:country":"CA",
    "sg:address":"52 Piper Dr",
    "sg:city":"Red Deer",
    "sg:classifiers":[
        {
            "category":"Social Services",
            "subcategory":"Adult Care",
            "type":"Services"
        }
    ],
    "sg:phone":"+1 403 343 0656",
    "sg:postcode":"T4P 1H8",
    "sg:province":"AB",
    "sg:tags":[
        "senior",
        "housing",
        "citizen"
    ],
    "wof:name":"Pines Lodge",
    "wof:placetype":"venue"
},
  "geometry": {"coordinates":[-113.80819700000001,52.292412],"type":"Point"}
}