{
  "type": "Feature",
  "properties": {
    "addr:full":"Cap-DE-LA-Madeleine QC G8T 6Y4",
    "addr:postcode":"g8t 6y4",
    "iso:country":"CA",
    "sg:city":"Cap-DE-LA-Madeleine",
    "sg:classifiers":[
        {
            "category":"Bars & Pubs",
            "type":"Food & Drink"
        }
    ],
    "sg:phone":"+1 819 372 0547",
    "sg:postcode":"G8T 6Y4",
    "sg:province":"QC",
    "sg:tags":[
        "lounge",
        "cocktail"
    ],
    "wof:name":"Bar L'Abasie",
    "wof:placetype":"venue"
},
  "geometry": {"coordinates":[-72.535774231,46.373626709],"type":"Point"}
}