{
  "type": "Feature",
  "properties": {
    "addr:full":"Pointe-Au-Pere QC G5M 1H3",
    "addr:postcode":"g5m 1h3",
    "iso:country":"CA",
    "sg:city":"Pointe-Au-Pere",
    "sg:classifiers":[
        {
            "category":"Professional",
            "subcategory":"Accounting & Tax Preparation",
            "type":"Services"
        }
    ],
    "sg:phone":"+1 418 723 6205",
    "sg:postcode":"G5M 1H3",
    "sg:province":"QC",
    "sg:tags":[
        "accountant"
    ],
    "wof:name":"Deschenes, Donald",
    "wof:placetype":"venue"
},
  "geometry": {"coordinates":[-68.46787999999999,48.502941],"type":"Point"}
}