{
  "type": "Feature",
  "properties": {
    "addr:full":"325 Main St Kentville NS B4N 1K5",
    "addr:housenumber":"325",
    "addr:postcode":"b4n 1k5",
    "addr:street":"Main St",
    "iso:country":"CA",
    "sg:address":"325 Main St",
    "sg:city":"Kentville",
    "sg:classifiers":[
        {
            "category":"Professional",
            "subcategory":"Lawyer & Legal Services",
            "type":"Services"
        }
    ],
    "sg:phone":"+1 902 679 6110",
    "sg:postcode":"B4N 1K5",
    "sg:province":"NS",
    "sg:tags":[
        "attorney"
    ],
    "wof:name":"Nova Scotia Legal Aid",
    "wof:placetype":"venue"
},
  "geometry": {"coordinates":[-64.4905166626,45.075756073],"type":"Point"}
}