{
  "type": "Feature",
  "properties": {
    "iso:country":"CA",
    "sg:address":"6800 Rte Des Ormes",
    "sg:city":"Becancour",
    "sg:classifiers":[
        {
            "category":"Home & Garden",
            "subcategory":"Building Materials",
            "type":"Retail Goods"
        }
    ],
    "sg:phone":"+1 819 297 2053",
    "sg:postcode":"G9H 3R1",
    "sg:province":"QC",
    "sg:tags":[
        "glass",
        "leaded"
    ],
    "wof:name":"Vitraux Rejac",
    "wof:placetype":"venue"
},
  "geometry": {"coordinates":[-72.3210144043,46.3014717102],"type":"Point"}
}