{
  "type": "Feature",
  "properties": {
    "addr:full":"11 Waterview Rd Cobden ON K0J 1K0",
    "addr:housenumber":"11",
    "addr:postcode":"k0j 1k0",
    "addr:street":"Waterview Rd",
    "iso:country":"CA",
    "sg:address":"11 Waterview Rd",
    "sg:city":"Cobden",
    "sg:classifiers":[
        {
            "category":"Travel",
            "subcategory":"Hotels & Motels",
            "type":"Entertainment"
        }
    ],
    "sg:phone":"+1 613 646 7446",
    "sg:postcode":"K0J 1K0",
    "sg:province":"ON",
    "sg:tags":[
        "cottage",
        "campground",
        "camp",
        "fishing",
        "cabin"
    ],
    "wof:name":"Lakeside Cottages & Trailer",
    "wof:placetype":"venue"
},
  "geometry": {"coordinates":[-76.879982,45.627075],"type":"Point"}
}