{
  "type": "Feature",
  "properties": {
    "addr:full":"1035 Camel Lake Exten Rd Bracebridge ON P1L 1T5",
    "addr:housenumber":"1035",
    "addr:postcode":"p1l 1t5",
    "addr:street":"Camel Lake Exten Rd",
    "iso:country":"CA",
    "sg:address":"1035 Camel Lake Exten Rd",
    "sg:city":"Bracebridge",
    "sg:classifiers":[
        {
            "category":"Building & Trades",
            "subcategory":"Electrical",
            "type":"Services"
        }
    ],
    "sg:phone":"+1 705 385 3493",
    "sg:postcode":"P1L 1T5",
    "sg:province":"ON",
    "sg:tags":[
        "electric",
        "contractor"
    ],
    "wof:name":"A & D Electric Ltd",
    "wof:placetype":"venue"
},
  "geometry": {"coordinates":[-79.2886352539,45.0555801392],"type":"Point"}
}