{
  "type": "Feature",
  "properties": {
    "iso:country":"CA",
    "sg:city":"Richmond Hill",
    "sg:classifiers":[
        {
            "category":"Wholesale",
            "subcategory":"Machinery & Supplies",
            "type":"Manufacturing & Wholesale Goods"
        }
    ],
    "sg:phone":"+1 905 707 0766",
    "sg:postcode":"L4B 3P8",
    "sg:province":"ON",
    "sg:tags":[
        "salon",
        "beauty"
    ],
    "wof:name":"L'Est Man Group",
    "wof:placetype":"venue"
},
  "geometry": {"coordinates":[-79.399673,43.840546],"type":"Point"}
}