{
  "type": "Feature",
  "properties": {
    "addr:full":"11070 108 St NW Edmonton AB T5H 3A9",
    "addr:housenumber":"11070",
    "addr:postcode":"t5h 3a9",
    "addr:street":"108 St Nw",
    "iso:country":"CA",
    "sg:address":"11070 108 St NW",
    "sg:city":"Edmonton",
    "sg:classifiers":[
        {
            "category":"Organizations",
            "subcategory":"Professional Association",
            "type":"Services"
        }
    ],
    "sg:phone":"+1 780 426 1409",
    "sg:postcode":"T5H 3A9",
    "sg:province":"AB",
    "wof:name":"Mc Dougall House",
    "wof:placetype":"venue"
},
  "geometry": {"coordinates":[-113.506821,53.558144],"type":"Point"}
}