{
  "type": "Feature",
  "properties": {
    "addr:full":"200 Whitney Ave Hamilton ON L8S 2G7",
    "addr:housenumber":"200",
    "addr:postcode":"l8s 2g7",
    "addr:street":"Whitney Ave",
    "iso:country":"CA",
    "sg:address":"200 Whitney Ave",
    "sg:city":"Hamilton",
    "sg:classifiers":[
        {
            "category":"Education",
            "subcategory":"School",
            "type":"Public Place"
        }
    ],
    "sg:phone":"+1 905 528 0214",
    "sg:postcode":"L8S 2G7",
    "sg:province":"ON",
    "wof:name":"St Mary's Catholic High School",
    "wof:placetype":"venue"
},
  "geometry": {"coordinates":[-79.9293060303,43.2528915405],"type":"Point"}
}