{
  "type": "Feature",
  "properties": {
    "addr:full":"505 5 St SW Calgary AB T2P 3J2",
    "addr:housenumber":"505 5",
    "addr:postcode":"t2p 3j2",
    "addr:street":"St Sw",
    "iso:country":"CA",
    "sg:address":"505 5 St SW",
    "sg:city":"Calgary",
    "sg:classifiers":[
        {
            "category":"Travel",
            "subcategory":"Travel Agent",
            "type":"Entertainment"
        }
    ],
    "sg:phone":"+1 403 263 2290",
    "sg:postcode":"T2P 3J2",
    "sg:province":"AB",
    "sg:tags":[
        "ticket",
        "agency",
        "bureau",
        "airline"
    ],
    "wof:name":"Marlin Travel",
    "wof:placetype":"venue"
},
  "geometry": {"coordinates":[-114.07379913299999,51.0485420227],"type":"Point"}
}