{
  "type": "Feature",
  "properties": {
    "addr:full":"880 Fourth Ave S Kenora ON P9N 3X6",
    "addr:housenumber":"880",
    "addr:postcode":"p9n 3x6",
    "addr:street":"Fourth Ave S",
    "iso:country":"CA",
    "sg:address":"880 Fourth Ave S",
    "sg:city":"Kenora",
    "sg:classifiers":[
        {
            "category":"Airport",
            "type":"Transportation"
        }
    ],
    "sg:phone":"+1 807 468 7954",
    "sg:postcode":"P9N 3X6",
    "sg:province":"ON",
    "sg:tags":[
        "aircraft",
        "maintenance"
    ],
    "wof:name":"Kuby's Aircraft Ltd",
    "wof:placetype":"venue"
},
  "geometry": {"coordinates":[-94.48503100000001,49.753147],"type":"Point"}
}