{
  "type": "Feature",
  "properties": {
    "iso:country":"CA",
    "sg:address":"1595 Bedford Hwy # 180",
    "sg:city":"Bedford",
    "sg:classifiers":[
        {
            "category":"Retail",
            "subcategory":"Laundry & Dry Cleaning",
            "type":"Services"
        }
    ],
    "sg:phone":"+1 902 832 3323",
    "sg:postcode":"B4A 3Y4",
    "sg:province":"NS",
    "sg:tags":[
        "cleaners"
    ],
    "wof:name":"Same Day Dry Cleaners",
    "wof:placetype":"venue"
},
  "geometry": {"coordinates":[-63.6559715271,44.7327804565],"type":"Point"}
}