{
  "type": "Feature",
  "properties": {
    "addr:full":"335 Superior Blvd Mississauga ON L5T 2L6",
    "addr:housenumber":"335",
    "addr:postcode":"l5t 2l6",
    "addr:street":"Superior Blvd",
    "iso:country":"CA",
    "sg:address":"335 Superior Blvd",
    "sg:city":"Mississauga",
    "sg:classifiers":[
        {
            "category":"Building & Trades",
            "subcategory":"Construction",
            "type":"Services"
        }
    ],
    "sg:phone":"+1 905 565 6840",
    "sg:postcode":"L5T 2L6",
    "sg:province":"ON",
    "sg:tags":[
        "designer",
        "hot",
        "spa",
        "tub",
        "dealer",
        "pool",
        "swimming"
    ],
    "wof:name":"California Spa & Fitness Strs",
    "wof:placetype":"venue"
},
  "geometry": {"coordinates":[-79.69214599999999,43.647594],"type":"Point"}
}