{
  "type": "Feature",
  "properties": {
    "addr:full":"2361 Rue Bauman Jonquiere QC G7S 5A9",
    "addr:housenumber":"2361",
    "addr:postcode":"g7s 5a9",
    "addr:street":"Rue Bauman",
    "iso:country":"CA",
    "sg:address":"2361 Rue Bauman",
    "sg:city":"Jonquiere",
    "sg:classifiers":[
        {
            "category":"Building & Trades",
            "subcategory":"Electrical",
            "type":"Services"
        }
    ],
    "sg:phone":"+1 418 548 1184",
    "sg:postcode":"G7S 5A9",
    "sg:province":"QC",
    "sg:tags":[
        "electric",
        "contractor"
    ],
    "wof:name":"Entreprises D'Elec Prowatt Inc",
    "wof:placetype":"venue"
},
  "geometry": {"coordinates":[-71.1616592407,48.4053344727],"type":"Point"}
}