{
  "type": "Feature",
  "properties": {
    "iso:country":"CA",
    "sg:address":"1430 36 St N",
    "sg:city":"Lethbridge",
    "sg:classifiers":[
        {
            "category":"Building & Trades",
            "subcategory":"Electrical",
            "type":"Services"
        }
    ],
    "sg:phone":"+1 403 320 0795",
    "sg:postcode":"T1H 5H8",
    "sg:province":"AB",
    "sg:tags":[
        "electric",
        "contractor"
    ],
    "wof:name":"Deltec Power & Control Systems",
    "wof:placetype":"venue"
},
  "geometry": {"coordinates":[-112.789321899,49.7183837891],"type":"Point"}
}