{
  "type": "Feature",
  "properties": {
    "addr:full":"110 3rd St W North Vancouver BC V7M 1E8",
    "addr:housenumber":"110",
    "addr:postcode":"v7m 1e8",
    "addr:street":"3Rd St W",
    "iso:country":"CA",
    "sg:address":"110 3rd St W",
    "sg:city":"North Vancouver",
    "sg:classifiers":[
        {
            "category":"Professional",
            "subcategory":"Printing & Photocopies",
            "type":"Services"
        }
    ],
    "sg:phone":"+1 604 984 0018",
    "sg:postcode":"V7M 1E8",
    "sg:province":"BC",
    "sg:tags":[
        "duplicating",
        "copying"
    ],
    "wof:name":"Magic Copy",
    "wof:placetype":"venue"
},
  "geometry": {"coordinates":[-123.07746899999999,49.31382],"type":"Point"}
}