{
  "type": "Feature",
  "properties": {
    "iso:country":"CA",
    "sg:address":"3536 Clarence St",
    "sg:city":"Camlachie",
    "sg:classifiers":[
        {
            "category":"Banks & Credit Unions",
            "subcategory":"Bank",
            "type":"Services"
        }
    ],
    "sg:phone":"+1 519 869 8444",
    "sg:postcode":"N0N 1E0",
    "sg:province":"ON",
    "sg:tags":[
        "loan",
        "real estate"
    ],
    "wof:name":"Royal Bank Mortgage Manager",
    "wof:placetype":"venue"
},
  "geometry": {"coordinates":[-82.1892166138,43.0469017029],"type":"Point"}
}