{
  "type": "Feature",
  "properties": {
    "addr:full":"1190 Waverley St Winnipeg MB R3T 0P4",
    "addr:housenumber":"1190",
    "addr:postcode":"r3t 0p4",
    "addr:street":"Waverley St",
    "iso:country":"CA",
    "sg:address":"1190 Waverley St",
    "sg:city":"Winnipeg",
    "sg:classifiers":[
        {
            "category":"Professional",
            "subcategory":"Engineering",
            "type":"Services"
        }
    ],
    "sg:phone":"+1 204 284 8100",
    "sg:postcode":"R3T 0P4",
    "sg:province":"MB",
    "sg:tags":[
        "engineer"
    ],
    "wof:name":"Amec Teshmont Consultants Inc",
    "wof:placetype":"venue"
},
  "geometry": {"coordinates":[-97.1790390015,49.8339614868],"type":"Point"}
}