{
  "type": "Feature",
  "properties": {
    "addr:full":"13160 80 Ave # B Surrey BC V3W 3B2",
    "addr:housenumber":"13160",
    "addr:postcode":"v3w 3b2",
    "addr:street":"80 Ave # B",
    "iso:country":"CA",
    "sg:address":"13160 80 Ave # B",
    "sg:city":"Surrey",
    "sg:classifiers":[
        {
            "category":"Retail",
            "subcategory":"Car Wash",
            "type":"Services"
        }
    ],
    "sg:phone":"+1 604 599 0362",
    "sg:postcode":"V3W 3B2",
    "sg:province":"BC",
    "sg:tags":[
        "polishing",
        "automobile",
        "washing",
        "detail",
        "clean"
    ],
    "wof:name":"Surrey Car Care",
    "wof:placetype":"venue"
},
  "geometry": {"coordinates":[-122.858177185,49.1480178833],"type":"Point"}
}