{
  "type": "Feature",
  "properties": {
    "addr:full":"2763 Av DE LA Montagne Shawinigan QC G9N 6K4",
    "addr:housenumber":"2763",
    "addr:postcode":"g9n 6k4",
    "addr:street":"Av De La Montagne",
    "iso:country":"CA",
    "sg:address":"2763 Av DE LA Montagne",
    "sg:city":"Shawinigan",
    "sg:classifiers":[
        {
            "category":"Autos & Motor Vehicles",
            "subcategory":"Motorcycle Sales",
            "type":"Retail Goods"
        }
    ],
    "sg:phone":"+1 819 539 5235",
    "sg:postcode":"G9N 6K4",
    "sg:province":"QC",
    "sg:tags":[
        "scooter"
    ],
    "wof:name":"Lamontagne Sport Inc",
    "wof:placetype":"venue"
},
  "geometry": {"coordinates":[-72.759682,46.574722],"type":"Point"}
}