{
  "type": "Feature",
  "properties": {
    "addr:full":"5644 Rue DE Verdun Verdun QC H4H 1L4",
    "addr:housenumber":"5644",
    "addr:postcode":"h4h 1l4",
    "addr:street":"Rue De Verdun",
    "iso:country":"CA",
    "sg:address":"5644 Rue DE Verdun",
    "sg:city":"Verdun",
    "sg:classifiers":[
        {
            "category":"Professional",
            "subcategory":"Lawyer & Legal Services",
            "type":"Services"
        }
    ],
    "sg:phone":"+1 514 762 6633",
    "sg:postcode":"H4H 1L4",
    "sg:province":"QC",
    "sg:tags":[
        "attorney"
    ],
    "wof:name":"Prud'Homme, Alain",
    "wof:placetype":"venue"
},
  "geometry": {"coordinates":[-73.572303772,45.4508705139],"type":"Point"}
}