{
  "type": "Feature",
  "properties": {
    "addr:full":"Langley BC V3A 3Z1",
    "addr:postcode":"v3a 3z1",
    "iso:country":"CA",
    "sg:city":"Langley",
    "sg:classifiers":[
        {
            "category":"Bars & Pubs",
            "type":"Food & Drink"
        }
    ],
    "sg:phone":"+1 604 534 3455",
    "sg:postcode":"V3A 3Z1",
    "sg:province":"BC",
    "wof:name":"Rendezvous Neighbourhood Pub",
    "wof:placetype":"venue"
},
  "geometry": {"coordinates":[-122.651809692,49.1046409607],"type":"Point"}
}