{
  "type": "Feature",
  "properties": {
    "addr:full":"401 A Ave Kaslo BC V0G 1M0",
    "addr:housenumber":"401 a",
    "addr:postcode":"v0g 1m0",
    "addr:street":"Ave",
    "iso:country":"CA",
    "sg:address":"401 A Ave",
    "sg:city":"Kaslo",
    "sg:classifiers":[
        {
            "category":"Manufacturing",
            "subcategory":"Printing",
            "type":"Manufacturing & Wholesale Goods"
        }
    ],
    "sg:phone":"+1 250 353 2602",
    "sg:postcode":"V0G 1M0",
    "sg:province":"BC",
    "sg:tags":[
        "newspaper"
    ],
    "wof:name":"Pennywise",
    "wof:placetype":"venue"
},
  "geometry": {"coordinates":[-116.912727,49.913502],"type":"Point"}
}