{
  "type": "Feature",
  "properties": {
    "addr:full":"524 Kimberly Ave Winnipeg MB R2K 0Y1",
    "addr:housenumber":"524",
    "addr:postcode":"r2k 0y1",
    "addr:street":"Kimberly Ave",
    "iso:country":"CA",
    "sg:address":"524 Kimberly Ave",
    "sg:city":"Winnipeg",
    "sg:classifiers":[
        {
            "category":"Retail",
            "subcategory":"Repair Shop",
            "type":"Services"
        }
    ],
    "sg:phone":"+1 204 668 3752",
    "sg:postcode":"R2K 0Y1",
    "sg:province":"MB",
    "sg:tags":[
        "plumbing",
        "drain",
        "cleaning",
        "sewer"
    ],
    "wof:name":"Winnipeg Sewer & Drain Ltd",
    "wof:placetype":"venue"
},
  "geometry": {"coordinates":[-97.0899734497,49.9227523804],"type":"Point"}
}