{
  "type": "Feature",
  "properties": {
    "iso:country":"CA",
    "sg:address":"497 Corydon Ave",
    "sg:city":"Winnipeg",
    "sg:classifiers":[
        {
            "category":"Organizations",
            "subcategory":"Professional Association",
            "type":"Services"
        }
    ],
    "sg:phone":"+1 204 284 3700",
    "sg:postcode":"R3L 0N9",
    "sg:province":"MB",
    "wof:name":"Corydon Avenue Business",
    "wof:placetype":"venue"
},
  "geometry": {"coordinates":[-97.1442565918,49.8740081787],"type":"Point"}
}