{
  "type": "Feature",
  "properties": {
    "addr:full":"Nanaimo BC V9S 3Y3",
    "addr:postcode":"v9s 3y3",
    "iso:country":"CA",
    "sg:city":"Nanaimo",
    "sg:classifiers":[
        {
            "category":"Health Services",
            "subcategory":"Doctor",
            "type":"Services"
        }
    ],
    "sg:phone":"+1 250 753 1181",
    "sg:postcode":"V9S 3Y3",
    "sg:province":"BC",
    "sg:tags":[
        "dentist"
    ],
    "wof:name":"Abdurahman, Rustin DDS",
    "wof:placetype":"venue"
},
  "geometry": {"coordinates":[-123.955696106,49.1853561401],"type":"Point"}
}