{
  "type": "Feature",
  "properties": {
    "addr:full":"Levis QC G6V 6K9",
    "addr:postcode":"g6v 6k9",
    "iso:country":"CA",
    "sg:city":"Levis",
    "sg:classifiers":[
        {
            "category":"Manufacturing",
            "subcategory":"Tools & Machinery",
            "type":"Manufacturing & Wholesale Goods"
        }
    ],
    "sg:phone":"+1 418 834 4321",
    "sg:postcode":"G6V 6K9",
    "sg:province":"QC",
    "sg:tags":[
        "control"
    ],
    "wof:name":"Reglages Mire Inc",
    "wof:placetype":"venue"
},
  "geometry": {"coordinates":[-71.183784,46.792431],"type":"Point"}
}