{
  "type": "Feature",
  "properties": {
    "addr:full":"Milverton ON N0K 1M0",
    "addr:postcode":"n0k 1m0",
    "iso:country":"CA",
    "sg:city":"Milverton",
    "sg:classifiers":[
        {
            "category":"Home & Garden",
            "subcategory":"Building Materials",
            "type":"Retail Goods"
        }
    ],
    "sg:phone":"+1 519 595 8173",
    "sg:postcode":"N0K 1M0",
    "sg:province":"ON",
    "wof:name":"R J Steel",
    "wof:placetype":"venue"
},
  "geometry": {"coordinates":[-80.90424299999999,43.544266],"type":"Point"}
}