{
  "type": "Feature",
  "properties": {
    "iso:country":"CA",
    "sg:address":"2580 Shepard Ave # 21",
    "sg:city":"Mississauga",
    "sg:classifiers":[
        {
            "category":"Restaurant",
            "type":"Food & Drink"
        }
    ],
    "sg:phone":"+1 905 275 4622",
    "sg:postcode":"L5A 4K3",
    "sg:province":"ON",
    "wof:name":"Curry Leaves",
    "wof:placetype":"venue"
},
  "geometry": {"coordinates":[-79.61456298829999,43.5807266235],"type":"Point"}
}