{
  "type": "Feature",
  "properties": {
    "addr:full":"1354 Island Hwy Campbell River BC V9W 8C9",
    "addr:housenumber":"1354",
    "addr:postcode":"v9w 8c9",
    "addr:street":"Island Hwy",
    "iso:country":"CA",
    "sg:address":"1354 Island Hwy",
    "sg:city":"Campbell River",
    "sg:classifiers":[
        {
            "category":"Shopping",
            "subcategory":"Clothing, Apparel, & Fashions",
            "type":"Retail Goods"
        }
    ],
    "sg:phone":"+1 250 286 1242",
    "sg:postcode":"V9W 8C9",
    "sg:province":"BC",
    "wof:name":"Wonderful Things",
    "wof:placetype":"venue"
},
  "geometry": {"coordinates":[-125.246696,50.032162],"type":"Point"}
}