{
  "type": "Feature",
  "properties": {
    "addr:full":"5 Lorraine St Swan River MB R0L 1Z0",
    "addr:housenumber":"5",
    "addr:postcode":"r0l 1z0",
    "addr:street":"Lorraine St",
    "iso:country":"CA",
    "sg:address":"5 Lorraine St",
    "sg:city":"Swan River",
    "sg:classifiers":[
        {
            "category":"Building & Trades",
            "subcategory":"Construction",
            "type":"Services"
        }
    ],
    "sg:phone":"+1 204 734 9471",
    "sg:postcode":"R0L 1Z0",
    "sg:province":"MB",
    "sg:tags":[
        "maker",
        "cabinet"
    ],
    "wof:name":"Swan Valley Cabinet & Woodwork",
    "wof:placetype":"venue"
},
  "geometry": {"coordinates":[-101.251495361,52.1132888794],"type":"Point"}
}