{
  "type": "Feature",
  "properties": {
    "addr:full":"326 Main St Morse SK S0H 3C0",
    "addr:housenumber":"326",
    "addr:postcode":"s0h 3c0",
    "addr:street":"Main St",
    "iso:country":"CA",
    "sg:address":"326 Main St",
    "sg:city":"Morse",
    "sg:classifiers":[
        {
            "category":"Recreation",
            "type":"Entertainment"
        }
    ],
    "sg:phone":"+1 306 629 3533",
    "sg:postcode":"S0H 3C0",
    "sg:province":"SK",
    "sg:tags":[
        "center"
    ],
    "wof:name":"Morse Bowling & Recreation",
    "wof:placetype":"venue"
},
  "geometry": {"coordinates":[-107.038917541,50.4139900208],"type":"Point"}
}