{
  "type": "Feature",
  "properties": {
    "addr:full":"1028 Pape Ave East York ON M4K 3V9",
    "addr:housenumber":"1028",
    "addr:postcode":"m4k 3v9",
    "addr:street":"Pape Ave",
    "iso:country":"CA",
    "sg:address":"1028 Pape Ave",
    "sg:city":"East York",
    "sg:classifiers":[
        {
            "category":"Food & Beverages",
            "subcategory":"Groceries & Convenience Stores",
            "type":"Retail Goods"
        }
    ],
    "sg:phone":"+1 416 422 4157",
    "sg:postcode":"M4K 3V9",
    "sg:province":"ON",
    "wof:name":"William's Convenience",
    "wof:placetype":"venue"
},
  "geometry": {"coordinates":[-79.34889200000001,43.68927],"type":"Point"}
}