{
  "type": "Feature",
  "properties": {
    "addr:full":"1101 101st St North Battleford SK S9A 0Z5",
    "addr:housenumber":"1101",
    "addr:postcode":"s9a 0z5",
    "addr:street":"101St St",
    "iso:country":"CA",
    "sg:address":"1101 101st St",
    "sg:city":"North Battleford",
    "sg:classifiers":[
        {
            "category":"Banks & Credit Unions",
            "subcategory":"Investment Brokerage",
            "type":"Services"
        }
    ],
    "sg:phone":"+1 306 937 5022",
    "sg:postcode":"S9A 0Z5",
    "sg:province":"SK",
    "wof:name":"Rbc Dominion Securities Inc",
    "wof:placetype":"venue"
},
  "geometry": {"coordinates":[-108.297783,52.773594],"type":"Point"}
}