{
  "type": "Feature",
  "properties": {
    "addr:full":"Lloydminster AB T9V 2E3",
    "addr:postcode":"t9v 2e3",
    "iso:country":"CA",
    "sg:city":"Lloydminster",
    "sg:classifiers":[
        {
            "category":"Manufacturing",
            "subcategory":"Tools & Machinery",
            "type":"Manufacturing & Wholesale Goods"
        }
    ],
    "sg:phone":"+1 780 875 2683",
    "sg:postcode":"T9V 2E3",
    "sg:province":"AB",
    "sg:tags":[
        "lamp",
        "pump"
    ],
    "wof:name":"Bartle & Gibson CO Ltd",
    "wof:placetype":"venue"
},
  "geometry": {"coordinates":[-110.01380899999999,53.299747],"type":"Point"}
}