{
  "type": "Feature",
  "properties": {
    "addr:full":"15 Alma St Moncton NB E1C 4Y2",
    "addr:housenumber":"15",
    "addr:postcode":"e1c 4y2",
    "addr:street":"Alma St",
    "iso:country":"CA",
    "sg:address":"15 Alma St",
    "sg:city":"Moncton",
    "sg:classifiers":[
        {
            "category":"Professional",
            "subcategory":"Lawyer & Legal Services",
            "type":"Services"
        }
    ],
    "sg:phone":"+1 506 858 9000",
    "sg:postcode":"E1C 4Y2",
    "sg:province":"NB",
    "sg:tags":[
        "attorney"
    ],
    "wof:name":"Landry, David M",
    "wof:placetype":"venue"
},
  "geometry": {"coordinates":[-64.77686309809999,46.0890350342],"type":"Point"}
}