{
  "type": "Feature",
  "properties": {
    "addr:full":"Winchester ON K0C 2K0",
    "addr:postcode":"k0c 2k0",
    "iso:country":"CA",
    "sg:city":"Winchester",
    "sg:classifiers":[
        {
            "category":"Real Estate",
            "subcategory":"Developer",
            "type":"Services"
        }
    ],
    "sg:phone":"+1 613 448 3112",
    "sg:postcode":"K0C 2K0",
    "sg:province":"ON",
    "sg:tags":[
        "cemetery"
    ],
    "wof:name":"Maple Ridge Cemetery",
    "wof:placetype":"venue"
},
  "geometry": {"coordinates":[-75.35082199999999,45.094002],"type":"Point"}
}