{
  "type": "Feature",
  "properties": {
    "addr:full":"Calgary AB T2R 1K6",
    "addr:postcode":"t2r 1k6",
    "iso:country":"CA",
    "sg:city":"Calgary",
    "sg:classifiers":[
        {
            "category":"Professional",
            "subcategory":"Computer Services",
            "type":"Services"
        }
    ],
    "sg:phone":"+1 403 244 8813",
    "sg:postcode":"T2R 1K6",
    "sg:province":"AB",
    "sg:tags":[
        "consultant"
    ],
    "wof:name":"Tardis Consulting Ltd",
    "wof:placetype":"venue"
},
  "geometry": {"coordinates":[-114.08768499999999,51.039352],"type":"Point"}
}