{
  "type": "Feature",
  "properties": {
    "addr:full":"2276 Highway 6 Crescent Valley BC V0G 1H0",
    "addr:housenumber":"2276",
    "addr:postcode":"v0g 1h0",
    "addr:street":"Highway 6 Crescent",
    "iso:country":"CA",
    "sg:address":"2276 Highway 6",
    "sg:city":"Crescent Valley",
    "sg:classifiers":[
        {
            "category":"Manufacturing",
            "subcategory":"Chemicals & Compounds",
            "type":"Manufacturing & Wholesale Goods"
        }
    ],
    "sg:phone":"+1 250 359 6850",
    "sg:postcode":"V0G 1H0",
    "sg:province":"BC",
    "sg:tags":[
        "equipment",
        "cosmetic"
    ],
    "wof:name":"Mountain Sky Soaps",
    "wof:placetype":"venue"
},
  "geometry": {"coordinates":[-117.560745,49.451195],"type":"Point"}
}