{
  "type": "Feature",
  "properties": {
    "addr:full":"7505 40 St SE Calgary AB T2C 2H5",
    "addr:housenumber":"7505",
    "addr:postcode":"t2c 2h5",
    "addr:street":"40 St Se",
    "iso:country":"CA",
    "sg:address":"7505 40 St SE",
    "sg:city":"Calgary",
    "sg:classifiers":[
        {
            "category":"Building & Trades",
            "subcategory":"Construction",
            "type":"Services"
        }
    ],
    "sg:phone":"+1 403 279 4170",
    "sg:postcode":"T2C 2H5",
    "sg:province":"AB",
    "sg:tags":[
        "concrete",
        "restoration",
        "cleaning",
        "repair"
    ],
    "wof:name":"Geo Grout Inc",
    "wof:placetype":"venue"
},
  "geometry": {"coordinates":[-113.97679100000001,50.987118],"type":"Point"}
}