{
  "type": "Feature",
  "properties": {
    "addr:full":"2027 Niagara Stone Rd Niagara on the Lake ON L0S 1J0",
    "addr:housenumber":"2027",
    "addr:postcode":"l0s 1j0",
    "addr:street":"Niagara Stone Rd;On",
    "iso:country":"CA",
    "sg:address":"2027 Niagara Stone Rd",
    "sg:city":"Niagara on the Lake",
    "sg:classifiers":[
        {
            "category":"Organizations",
            "subcategory":"Religious Organization",
            "type":"Services"
        }
    ],
    "sg:phone":"+1 905 468 2611",
    "sg:postcode":"L0S 1J0",
    "sg:province":"ON",
    "sg:tags":[
        "church"
    ],
    "wof:name":"Trinity Lutheran Church",
    "wof:placetype":"venue"
},
  "geometry": {"coordinates":[-79.09916687010001,43.2400054932],"type":"Point"}
}