{
  "type": "Feature",
  "properties": {
    "addr:full":"3218 Oak St Vancouver BC V6H 2L3",
    "addr:housenumber":"3218",
    "addr:postcode":"v6h 2l3",
    "addr:street":"Oak St",
    "iso:country":"CA",
    "sg:address":"3218 Oak St",
    "sg:city":"Vancouver",
    "sg:classifiers":[
        {
            "category":"Retail",
            "subcategory":"Laundry & Dry Cleaning",
            "type":"Services"
        }
    ],
    "sg:phone":"+1 604 738 2728",
    "sg:postcode":"V6H 2L3",
    "sg:province":"BC",
    "sg:tags":[
        "cleaners"
    ],
    "wof:name":"Connaught Cleaners",
    "wof:placetype":"venue"
},
  "geometry": {"coordinates":[-123.127045,49.256893],"type":"Point"}
}