{
  "type": "Feature",
  "properties": {
    "addr:full":"223 Reid St Quesnel BC V2J 2M1",
    "addr:housenumber":"223",
    "addr:postcode":"v2j 2m1",
    "addr:street":"Reid St",
    "iso:country":"CA",
    "sg:address":"223 Reid St",
    "sg:city":"Quesnel",
    "sg:classifiers":[
        {
            "category":"Professional",
            "subcategory":"Accounting & Tax Preparation",
            "type":"Services"
        }
    ],
    "sg:phone":"+1 250 991 0940",
    "sg:postcode":"V2J 2M1",
    "sg:province":"BC",
    "sg:tags":[
        "accountant"
    ],
    "wof:name":"Rasmussen, R E CA",
    "wof:placetype":"venue"
},
  "geometry": {"coordinates":[-122.496711731,52.9762153625],"type":"Point"}
}