{
  "type": "Feature",
  "properties": {
    "addr:full":"770 Rue Jolliet Chicoutimi QC G7J 2P8",
    "addr:housenumber":"770",
    "addr:postcode":"g7j 2p8",
    "addr:street":"Rue Jolliet",
    "iso:country":"CA",
    "sg:address":"770 Rue Jolliet",
    "sg:city":"Chicoutimi",
    "sg:classifiers":[
        {
            "category":"Sports & Exercise",
            "subcategory":"Bowling",
            "type":"Entertainment"
        }
    ],
    "sg:phone":"+1 418 696 0111",
    "sg:postcode":"G7J 2P8",
    "sg:province":"QC",
    "sg:tags":[
        "center"
    ],
    "wof:name":"Salon DE Quilles Le Dallo",
    "wof:placetype":"venue"
},
  "geometry": {"coordinates":[-71.069412,48.418301],"type":"Point"}
}