{
  "type": "Feature",
  "properties": {
    "addr:full":"800 Central Ave Prince Albert SK S6V 6Z2",
    "addr:housenumber":"800",
    "addr:postcode":"s6v 6z2",
    "addr:street":"Central Ave",
    "iso:country":"CA",
    "sg:address":"800 Central Ave",
    "sg:city":"Prince Albert",
    "sg:classifiers":[
        {
            "category":"Organizations",
            "subcategory":"Professional Association",
            "type":"Services"
        }
    ],
    "sg:phone":"+1 306 953 2796",
    "sg:postcode":"S6V 6Z2",
    "sg:province":"SK",
    "sg:tags":[
        "environmental",
        "org"
    ],
    "wof:name":"SK Conservation Learning Ctr",
    "wof:placetype":"venue"
},
  "geometry": {"coordinates":[-105.75425720200001,53.2058486938],"type":"Point"}
}