{
  "type": "Feature",
  "properties": {
    "addr:full":"220 Rue Guillerm Longueuil QC J4G 1L1",
    "addr:housenumber":"220",
    "addr:postcode":"j4g 1l1",
    "addr:street":"Rue Guillerm",
    "iso:country":"CA",
    "sg:address":"220 Rue Guillerm",
    "sg:city":"Longueuil",
    "sg:classifiers":[
        {
            "category":"Manufacturing",
            "subcategory":"Tools & Machinery",
            "type":"Manufacturing & Wholesale Goods"
        }
    ],
    "sg:phone":"+1 450 646 1916",
    "sg:postcode":"J4G 1L1",
    "sg:province":"QC",
    "sg:tags":[
        "booth",
        "lot",
        "parking"
    ],
    "wof:name":"Fabco Inc",
    "wof:placetype":"venue"
},
  "geometry": {"coordinates":[-73.476997,45.571766],"type":"Point"}
}