{
  "type": "Feature",
  "properties": {
    "addr:full":"1155 Rue Saint-Antoine Disraeli QC G0N 1E0",
    "addr:housenumber":"1155",
    "addr:postcode":"g0n 1e0",
    "addr:street":"Rue Saint-Antoine",
    "iso:country":"CA",
    "sg:address":"1155 Rue Saint-Antoine",
    "sg:city":"Disraeli",
    "sg:classifiers":[
        {
            "category":"Personal",
            "subcategory":"Beauty Salon",
            "type":"Services"
        }
    ],
    "sg:phone":"+1 418 449 3029",
    "sg:postcode":"G0N 1E0",
    "sg:province":"QC",
    "wof:name":"Coiffure New-Look Enr",
    "wof:placetype":"venue"
},
  "geometry": {"coordinates":[-71.3601074219,45.9114227295],"type":"Point"}
}