{
  "type": "Feature",
  "properties": {
    "addr:full":"130 the West Mall Etobicoke ON M9C 1B9",
    "addr:housenumber":"130",
    "addr:postcode":"m9c 1b9",
    "addr:street":"The West Mall",
    "iso:country":"CA",
    "sg:address":"130 the West Mall",
    "sg:city":"Etobicoke",
    "sg:classifiers":[
        {
            "category":"Wholesale",
            "subcategory":"Meat",
            "type":"Manufacturing & Wholesale Goods"
        }
    ],
    "sg:phone":"+1 416 622 6888",
    "sg:postcode":"M9C 1B9",
    "sg:province":"ON",
    "wof:name":"Honeyman's Beef Purveyors",
    "wof:placetype":"venue"
},
  "geometry": {"coordinates":[-79.56253100000001,43.619808],"type":"Point"}
}