{
  "type": "Feature",
  "properties": {
    "addr:full":"Calgary AB T3E 7K1",
    "addr:postcode":"t3e 7k1",
    "iso:country":"CA",
    "sg:city":"Calgary",
    "sg:classifiers":[
        {
            "category":"Building & Trades",
            "subcategory":"Construction",
            "type":"Services"
        }
    ],
    "sg:phone":"+1 403 252 8777",
    "sg:postcode":"T3E 7K1",
    "sg:province":"AB",
    "sg:tags":[
        "general",
        "contractor"
    ],
    "wof:name":"Royce Developments",
    "wof:placetype":"venue"
},
  "geometry": {"coordinates":[-114.120018,51.019436],"type":"Point"}
}