{
  "type": "Feature",
  "properties": {
    "iso:country":"CA",
    "sg:city":"Saint-Laurent",
    "sg:classifiers":[
        {
            "category":"Wholesale",
            "subcategory":"Durable Goods & Equipment",
            "type":"Manufacturing & Wholesale Goods"
        }
    ],
    "sg:phone":"+1 514 747 4848",
    "sg:postcode":"H4T 1S3",
    "sg:province":"QC",
    "sg:tags":[
        "instrument",
        "scientific",
        "apparatus"
    ],
    "wof:name":"Varian Canada Inc",
    "wof:placetype":"venue"
},
  "geometry": {"coordinates":[-73.689461,45.494984],"type":"Point"}
}