{
  "type": "Feature",
  "properties": {
    "addr:full":"4 Commerce Cres RR 3 North Bay ON P1B 8G4",
    "addr:housenumber":"4",
    "addr:postcode":"p1b 8g4",
    "addr:street":"Commerce Cres Rr 3",
    "iso:country":"CA",
    "sg:address":"4 Commerce Cres RR 3",
    "sg:city":"North Bay",
    "sg:classifiers":[
        {
            "category":"Freight",
            "type":"Transportation"
        }
    ],
    "sg:phone":"+1 705 476 7077",
    "sg:postcode":"P1B 8G4",
    "sg:province":"ON",
    "sg:tags":[
        "trucking"
    ],
    "wof:name":"Erb Transport Ltd",
    "wof:placetype":"venue"
},
  "geometry": {"coordinates":[-79.4599304199,46.3066291809],"type":"Point"}
}