{
  "type": "Feature",
  "properties": {
    "addr:full":"1523 Davie St # 100 Vancouver BC V6G 3A2",
    "addr:housenumber":"1523",
    "addr:postcode":"v6g 3a2",
    "addr:street":"Davie St # 100",
    "iso:country":"CA",
    "sg:address":"1523 Davie St # 100",
    "sg:city":"Vancouver",
    "sg:classifiers":[
        {
            "category":"Restaurant",
            "type":"Food & Drink"
        }
    ],
    "sg:phone":"+1 604 689 4334",
    "sg:postcode":"V6G 3A2",
    "sg:province":"BC",
    "wof:name":"Romano's Macaroni Grill",
    "wof:placetype":"venue"
},
  "geometry": {"coordinates":[-123.13771800000001,49.284771],"type":"Point"}
}