{
  "type": "Feature",
  "properties": {
    "iso:country":"CA",
    "sg:address":"602 Plantation Gate",
    "sg:city":"Newmarket",
    "sg:classifiers":[
        {
            "category":"Real Estate",
            "subcategory":"Developer",
            "type":"Services"
        }
    ],
    "sg:phone":"+1 905 853 0777",
    "sg:postcode":"L3X 2C2",
    "sg:province":"ON",
    "wof:name":"Acorn Development Corp",
    "wof:placetype":"venue"
},
  "geometry": {"coordinates":[-79.49086,44.03413],"type":"Point"}
}