{
  "type": "Feature",
  "properties": {
    "addr:full":"448 Av Saint-Jerome Matane QC G4W 3B5",
    "addr:postcode":"g4w 3b5",
    "addr:street":"448 Av Saint-Jerome",
    "iso:country":"CA",
    "sg:address":"448 Av Saint-Jerome",
    "sg:city":"Matane",
    "sg:classifiers":[
        {
            "category":"Shopping",
            "subcategory":"Clothing, Apparel, & Fashions",
            "type":"Retail Goods"
        }
    ],
    "sg:phone":"+1 418 562 3611",
    "sg:postcode":"G4W 3B5",
    "sg:province":"QC",
    "sg:tags":[
        "infant",
        "wear"
    ],
    "wof:name":"Arc En Ciel DE LA Mode",
    "wof:placetype":"venue"
},
  "geometry": {"coordinates":[-67.529488,48.847328],"type":"Point"}
}