{
  "type": "Feature",
  "properties": {
    "addr:full":"Scarborough ON M1E 4S4",
    "addr:postcode":"m1e 4s4",
    "iso:country":"CA",
    "sg:city":"Scarborough",
    "sg:classifiers":[
        {
            "category":"Professional",
            "subcategory":"Business Services",
            "type":"Services"
        }
    ],
    "sg:phone":"+1 416 265 5999",
    "sg:postcode":"M1E 4S4",
    "sg:province":"ON",
    "sg:tags":[
        "event"
    ],
    "wof:name":"Tyr Event Management Corp",
    "wof:placetype":"venue"
},
  "geometry": {"coordinates":[-79.1983795166,43.741104126],"type":"Point"}
}