{
  "type": "Feature",
  "properties": {
    "iso:country":"CA",
    "sg:city":"Winnipeg",
    "sg:classifiers":[
        {
            "category":"Government",
            "subcategory":"Fire Station",
            "type":"Public Place"
        }
    ],
    "sg:phone":"+1 204 986 6380",
    "sg:postcode":"R3B 1L1",
    "sg:province":"MB",
    "sg:tags":[
        "department"
    ],
    "wof:name":"Winnipeg Fire Dept",
    "wof:placetype":"venue"
},
  "geometry": {"coordinates":[-97.14106,49.899662],"type":"Point"}
}