{
  "type": "Feature",
  "properties": {
    "addr:full":"3020 Portage Ave Winnipeg MB R3K 0X9",
    "addr:housenumber":"3020",
    "addr:postcode":"r3k 0x9",
    "addr:street":"Portage Ave",
    "iso:country":"CA",
    "sg:address":"3020 Portage Ave",
    "sg:city":"Winnipeg",
    "sg:classifiers":[
        {
            "category":"Retail",
            "subcategory":"Auto Repair",
            "type":"Services"
        }
    ],
    "sg:phone":"+1 204 888 0808",
    "sg:postcode":"R3K 0X9",
    "sg:province":"MB",
    "sg:tags":[
        "repairing",
        "automobile"
    ],
    "wof:name":"Fountain Tire",
    "wof:placetype":"venue"
},
  "geometry": {"coordinates":[-97.2799987793,49.8795127869],"type":"Point"}
}