{
  "type": "Feature",
  "properties": {
    "addr:full":"3779 Ch Des 40 Erpents Lachenaie QC J6V 1A3",
    "addr:housenumber":"3779",
    "addr:postcode":"j6v 1a3",
    "addr:street":"Ch Des 40",
    "iso:country":"CA",
    "sg:address":"3779 Ch Des 40 Erpents",
    "sg:city":"Lachenaie",
    "sg:classifiers":[
        {
            "category":"Utilities",
            "subcategory":"Refuse",
            "type":"Services"
        }
    ],
    "sg:phone":"+1 450 474 2423",
    "sg:postcode":"J6V 1A3",
    "sg:province":"QC",
    "sg:tags":[
        "landfill"
    ],
    "wof:name":"Bfi",
    "wof:placetype":"venue"
},
  "geometry": {"coordinates":[-73.5634,45.701759],"type":"Point"}
}