{
  "type": "Feature",
  "properties": {
    "addr:full":"Eriksdale MB R0C 0W0",
    "addr:postcode":"r0c 0w0",
    "iso:country":"CA",
    "sg:city":"Eriksdale",
    "sg:classifiers":[
        {
            "category":"Restaurant",
            "type":"Food & Drink"
        }
    ],
    "sg:phone":"+1 204 739 2027",
    "sg:postcode":"R0C 0W0",
    "sg:province":"MB",
    "sg:tags":[
        "motel",
        "hotel"
    ],
    "wof:name":"Eriksdale Inn",
    "wof:placetype":"venue"
},
  "geometry": {"coordinates":[-98.15985107420001,50.9390258789],"type":"Point"}
}