{
  "type": "Feature",
  "properties": {
    "addr:full":"40 Garfield Ave London ON N6C 2B5",
    "addr:housenumber":"40",
    "addr:postcode":"n6c 2b5",
    "addr:street":"Garfield Ave",
    "iso:country":"CA",
    "sg:address":"40 Garfield Ave",
    "sg:city":"London",
    "sg:classifiers":[
        {
            "category":"Building & Trades",
            "subcategory":"Construction",
            "type":"Services"
        }
    ],
    "sg:phone":"+1 519 438 8077",
    "sg:postcode":"N6C 2B5",
    "sg:province":"ON",
    "sg:tags":[
        "resurfacing",
        "laying",
        "refinishing",
        "floor"
    ],
    "wof:name":"Len Gibson & Sons Flr Sanding",
    "wof:placetype":"venue"
},
  "geometry": {"coordinates":[-81.24748200000001,42.965717],"type":"Point"}
}