{
  "type": "Feature",
  "properties": {
    "iso:country":"CA",
    "sg:address":"40 Garfield Ave",
    "sg:city":"London",
    "sg:classifiers":[
        {
            "category":"Building & Trades",
            "subcategory":"Construction",
            "type":"Services"
        }
    ],
    "sg:phone":"+1 519 438 8077",
    "sg:postcode":"N6C 2B5",
    "sg:province":"ON",
    "sg:tags":[
        "resurfacing",
        "laying",
        "refinishing",
        "floor"
    ],
    "wof:name":"Len Gibson & Sons Flr Sanding",
    "wof:placetype":"venue"
},
  "geometry": {"coordinates":[-81.247482,42.965717],"type":"Point"}
}