{
  "type": "Feature",
  "properties": {
    "addr:full":"107 Plymouth St Winnipeg MB R2X 2V5",
    "addr:housenumber":"107",
    "addr:postcode":"r2x 2v5",
    "addr:street":"Plymouth St",
    "iso:country":"CA",
    "sg:address":"107 Plymouth St",
    "sg:city":"Winnipeg",
    "sg:classifiers":[
        {
            "category":"Wholesale",
            "subcategory":"Meat",
            "type":"Manufacturing & Wholesale Goods"
        }
    ],
    "sg:phone":"+1 204 633 3643",
    "sg:postcode":"R2X 2V5",
    "sg:province":"MB",
    "sg:tags":[
        "product"
    ],
    "wof:name":"Hoffmann's Catering Inc",
    "wof:placetype":"venue"
},
  "geometry": {"coordinates":[-97.188446,49.940536],"type":"Point"}
}