{
  "type": "Feature",
  "properties": {
    "iso:country":"CA",
    "sg:address":"3 Homestead Rd",
    "sg:city":"Rothesay",
    "sg:classifiers":[
        {
            "category":"Manufacturing",
            "subcategory":"Metals",
            "type":"Manufacturing & Wholesale Goods"
        }
    ],
    "sg:phone":"+1 506 849 4636",
    "sg:postcode":"E2E 5X5",
    "sg:province":"NB",
    "sg:tags":[
        "windows"
    ],
    "wof:name":"Bishops Windows & Doors Ltd",
    "wof:placetype":"venue"
},
  "geometry": {"coordinates":[-65.97076416020001,45.3918876648],"type":"Point"}
}