{
  "type": "Feature",
  "properties": {
    "addr:full":"6080 Highway 7 Markham ON L3P 3B1",
    "addr:housenumber":"6080",
    "addr:postcode":"l3p 3b1",
    "addr:street":"Highway 7",
    "iso:country":"CA",
    "sg:address":"6080 Highway 7",
    "sg:city":"Markham",
    "sg:classifiers":[
        {
            "category":"Retail",
            "subcategory":"Auto Repair",
            "type":"Services"
        }
    ],
    "sg:phone":"+1 905 201 0031",
    "sg:postcode":"L3P 3B1",
    "sg:province":"ON",
    "sg:tags":[
        "repairing",
        "automobile"
    ],
    "wof:name":"Autoknight Mechanical Ltd",
    "wof:placetype":"venue"
},
  "geometry": {"coordinates":[-79.3399429321,43.8560333252],"type":"Point"}
}