{
  "type": "Feature",
  "properties": {
    "addr:full":"836 Larchwood Cres Kingston ON K7P 2P8",
    "addr:housenumber":"836",
    "addr:postcode":"k7p 2p8",
    "addr:street":"Larchwood Cres",
    "iso:country":"CA",
    "sg:address":"836 Larchwood Cres",
    "sg:city":"Kingston",
    "sg:classifiers":[
        {
            "category":"Shopping",
            "type":"Retail Goods"
        }
    ],
    "sg:phone":"+1 613 634 3033",
    "sg:postcode":"K7P 2P8",
    "sg:province":"ON",
    "sg:tags":[
        "cosmetic",
        "perfume"
    ],
    "wof:name":"Mary Kay Cosmetics",
    "wof:placetype":"venue"
},
  "geometry": {"coordinates":[-76.58232879640001,44.2648544312],"type":"Point"}
}