{
  "type": "Feature",
  "properties": {
    "addr:full":"1 Monck Rd Cardiff ON K0L 1M0",
    "addr:housenumber":"1",
    "addr:postcode":"k0l 1m0",
    "addr:street":"Monck Rd",
    "iso:country":"CA",
    "sg:address":"1 Monck Rd",
    "sg:city":"Cardiff",
    "sg:classifiers":[
        {
            "category":"Organizations",
            "subcategory":"Religious Organization",
            "type":"Services"
        }
    ],
    "sg:phone":"+1 613 339 2852",
    "sg:postcode":"K0L 1M0",
    "sg:province":"ON",
    "sg:tags":[
        "church"
    ],
    "wof:name":"Our Lady of Lourdes Church",
    "wof:placetype":"venue"
},
  "geometry": {"coordinates":[-78.092468,44.992516],"type":"Point"}
}