{
  "type": "Feature",
  "properties": {
    "addr:full":"3520 32 St NE Calgary AB T1Y 6G7",
    "addr:housenumber":"3520",
    "addr:postcode":"t1y 6g7",
    "addr:street":"32 St Ne",
    "iso:country":"CA",
    "sg:address":"3520 32 St NE",
    "sg:city":"Calgary",
    "sg:classifiers":[
        {
            "category":"Retail",
            "subcategory":"Auto Repair",
            "type":"Services"
        }
    ],
    "sg:phone":"+1 403 291 4962",
    "sg:postcode":"T1Y 6G7",
    "sg:province":"AB",
    "sg:tags":[
        "body",
        "automobile",
        "painting"
    ],
    "wof:name":"Service Collision Repair Ctr",
    "wof:placetype":"venue"
},
  "geometry": {"coordinates":[-113.988388062,51.08411026],"type":"Point"}
}