{
  "type": "Feature",
  "properties": {
    "addr:full":"2000 Urquhart Ave Courtenay BC V9N 3K9",
    "addr:housenumber":"2000",
    "addr:postcode":"v9n 3k9",
    "addr:street":"Urquhart Ave",
    "iso:country":"CA",
    "sg:address":"2000 Urquhart Ave",
    "sg:city":"Courtenay",
    "sg:classifiers":[
        {
            "category":"Autos & Motor Vehicles",
            "subcategory":"Motorcycle Sales",
            "type":"Retail Goods"
        }
    ],
    "sg:phone":"+1 250 334 9310",
    "sg:postcode":"V9N 3K9",
    "sg:province":"BC",
    "sg:tags":[
        "instruction",
        "driving"
    ],
    "wof:name":"Comox Valley Driving School",
    "wof:placetype":"venue"
},
  "geometry": {"coordinates":[-124.999130249,49.6748809814],"type":"Point"}
}