{
  "type": "Feature",
  "properties": {
    "addr:full":"128 Queensway W Simcoe ON N3Y 2M6",
    "addr:housenumber":"128",
    "addr:postcode":"n3y 2m6",
    "addr:street":"Queensway W",
    "iso:country":"CA",
    "sg:address":"128 Queensway W",
    "sg:city":"Simcoe",
    "sg:classifiers":[
        {
            "category":"Shopping",
            "subcategory":"Discount & Variety Stores",
            "type":"Retail Goods"
        }
    ],
    "sg:phone":"+1 519 426 2309",
    "sg:postcode":"N3Y 2M6",
    "sg:province":"ON",
    "wof:name":"Target Convenience Stores",
    "wof:placetype":"venue"
},
  "geometry": {"coordinates":[-80.31165300000001,42.845215],"type":"Point"}
}