{
  "type": "Feature",
  "properties": {
    "addr:full":"100 Railway Ave Alvena SK S0K 0E0",
    "addr:housenumber":"100",
    "addr:postcode":"s0k 0e0",
    "addr:street":"Railway Ave",
    "iso:country":"CA",
    "sg:address":"100 Railway Ave",
    "sg:city":"Alvena",
    "sg:classifiers":[
        {
            "category":"Real Estate",
            "subcategory":"Real Estate Agent",
            "type":"Services"
        }
    ],
    "sg:phone":"+1 306 943 2006",
    "sg:postcode":"S0K 0E0",
    "sg:province":"SK",
    "sg:tags":[
        "cooperative"
    ],
    "wof:name":"Alvena CO-OP",
    "wof:placetype":"venue"
},
  "geometry": {"coordinates":[-106.020821,52.518459],"type":"Point"}
}