{
  "type": "Feature",
  "properties": {
    "addr:full":"471 Bowen Island Trunk Rd Bowen Island BC V0N 1G0",
    "addr:housenumber":"471",
    "addr:postcode":"v0n 1g0",
    "addr:street":"Bowen Island Trunk Rd Bowen Island",
    "iso:country":"CA",
    "sg:address":"471 Bowen Island Trunk Rd",
    "sg:city":"Bowen Island",
    "sg:classifiers":[
        {
            "category":"Food & Beverages",
            "subcategory":"Groceries & Convenience Stores",
            "type":"Retail Goods"
        }
    ],
    "sg:phone":"+1 604 947 9619",
    "sg:postcode":"V0N 1G0",
    "sg:province":"BC",
    "sg:tags":[
        "grocer"
    ],
    "wof:name":"Snug Cove General Store Ltd",
    "wof:placetype":"venue"
},
  "geometry": {"coordinates":[-123.336021,49.379547],"type":"Point"}
}