{
  "type": "Feature",
  "properties": {
    "iso:country":"CA",
    "sg:address":"1030 Hamilton St",
    "sg:city":"Vancouver",
    "sg:classifiers":[
        {
            "category":"Wholesale",
            "subcategory":"Apparel",
            "type":"Manufacturing & Wholesale Goods"
        }
    ],
    "sg:phone":"+1 604 685 3394",
    "sg:postcode":"V6B 2R9",
    "sg:province":"BC",
    "sg:tags":[
        "clothing"
    ],
    "wof:name":"Hibis Fashions",
    "wof:placetype":"venue"
},
  "geometry": {"coordinates":[-123.119873047,49.276550293],"type":"Point"}
}