{
  "type": "Feature",
  "properties": {
    "addr:full":"59 Powell St Vancouver BC V6A 1E9",
    "addr:housenumber":"59",
    "addr:postcode":"v6a 1e9",
    "addr:street":"Powell St",
    "iso:country":"CA",
    "sg:address":"59 Powell St",
    "sg:city":"Vancouver",
    "sg:classifiers":[
        {
            "category":"Social Services",
            "type":"Services"
        }
    ],
    "sg:phone":"+1 604 685 5239",
    "sg:postcode":"V6A 1E9",
    "sg:province":"BC",
    "sg:tags":[
        "organization",
        "welfare"
    ],
    "wof:name":"Dugout",
    "wof:placetype":"venue"
},
  "geometry": {"coordinates":[-123.102981567,49.2834205627],"type":"Point"}
}