{
  "type": "Feature",
  "properties": {
    "addr:full":"10147 115 St NW Edmonton AB T5K 1T3",
    "addr:housenumber":"10147",
    "addr:postcode":"t5k 1t3",
    "addr:street":"115 St Nw",
    "iso:country":"CA",
    "sg:address":"10147 115 St NW",
    "sg:city":"Edmonton",
    "sg:classifiers":[
        {
            "category":"Professional",
            "subcategory":"Lawyer & Legal Services",
            "type":"Services"
        }
    ],
    "sg:phone":"+1 780 482 7373",
    "sg:postcode":"T5K 1T3",
    "sg:province":"AB",
    "sg:tags":[
        "attorney"
    ],
    "wof:name":"Tatarchuk Olson",
    "wof:placetype":"venue"
},
  "geometry": {"coordinates":[-113.519226074,53.5419273376],"type":"Point"}
}