{
  "type": "Feature",
  "properties": {
    "addr:full":"7309 Rte 19 Judique NS B0E 1P0",
    "addr:housenumber":"7309",
    "addr:postcode":"b0e 1p0",
    "addr:street":"Rte 19",
    "iso:country":"CA",
    "sg:address":"7309 Rte 19",
    "sg:city":"Judique",
    "sg:classifiers":[
        {
            "category":"Personal",
            "subcategory":"Beauty Salon",
            "type":"Services"
        }
    ],
    "sg:phone":"+1 902 787 2664",
    "sg:postcode":"B0E 1P0",
    "sg:province":"NS",
    "wof:name":"Pat's Family Hair Care",
    "wof:placetype":"venue"
},
  "geometry": {"coordinates":[-61.4905128479,45.8756599426],"type":"Point"}
}