{
  "type": "Feature",
  "properties": {
    "addr:full":"2270 Keele St # 2 North York ON M6M 3Y9",
    "addr:housenumber":"2270",
    "addr:postcode":"m6m 3y9",
    "addr:street":"Keele St # 2",
    "iso:country":"CA",
    "sg:address":"2270 Keele St # 2",
    "sg:city":"North York",
    "sg:classifiers":[
        {
            "category":"Banks & Credit Unions",
            "subcategory":"Bank",
            "type":"Services"
        }
    ],
    "sg:phone":"+1 416 245 2274",
    "sg:postcode":"M6M 3Y9",
    "sg:province":"ON",
    "sg:tags":[
        "cashing",
        "check"
    ],
    "wof:name":"Money Mart",
    "wof:placetype":"venue"
},
  "geometry": {"coordinates":[-79.47681427000001,43.7024345398],"type":"Point"}
}