{
  "type": "Feature",
  "properties": {
    "iso:country":"CA",
    "sg:address":"1140 Route 776 # 1",
    "sg:city":"Grand Manan",
    "sg:classifiers":[
        {
            "category":"Shopping",
            "subcategory":"Gifts & Souvenirs",
            "type":"Retail Goods"
        }
    ],
    "sg:phone":"+1 506 662 3103",
    "sg:postcode":"E5G 4E8",
    "sg:province":"NB",
    "sg:tags":[
        "shop"
    ],
    "wof:name":"Harbour Gifts",
    "wof:placetype":"venue"
},
  "geometry": {"coordinates":[-66.84721374510001,44.6484527588],"type":"Point"}
}