{
  "type": "Feature",
  "properties": {
    "iso:country":"CA",
    "sg:address":"1672 Ch Gascon",
    "sg:city":"Terrebonne",
    "sg:classifiers":[
        {
            "category":"Shopping",
            "subcategory":"Computers & Home Electronics",
            "type":"Retail Goods"
        }
    ],
    "sg:phone":"+1 450 961 3280",
    "sg:postcode":"J6X 4H9",
    "sg:province":"QC",
    "sg:tags":[
        "equipment",
        "dealer"
    ],
    "wof:name":"Pro Info",
    "wof:placetype":"venue"
},
  "geometry": {"coordinates":[-73.6550750732,45.7157440186],"type":"Point"}
}