{
  "type": "Feature",
  "properties": {
    "addr:full":"Markham ON L3S 3K9",
    "addr:postcode":"l3s 3k9",
    "iso:country":"CA",
    "sg:city":"Markham",
    "sg:classifiers":[
        {
            "category":"Real Estate",
            "subcategory":"Real Estate Agent",
            "type":"Services"
        }
    ],
    "sg:phone":"+1 416 288 0800",
    "sg:postcode":"L3S 3K9",
    "sg:province":"ON",
    "wof:name":"New Star Real Estate Ltd",
    "wof:placetype":"venue"
},
  "geometry": {"coordinates":[-79.2615890503,43.8347053528],"type":"Point"}
}