{
  "type": "Feature",
  "properties": {
    "addr:full":"8280 Boul Saint-Laurent Montreal QC H2P 2L8",
    "addr:housenumber":"8280",
    "addr:postcode":"h2p 2l8",
    "addr:street":"Boul Saint-Laurent",
    "iso:country":"CA",
    "sg:address":"8280 Boul Saint-Laurent",
    "sg:city":"Montreal",
    "sg:classifiers":[
        {
            "category":"Manufacturing",
            "subcategory":"Apparel",
            "type":"Manufacturing & Wholesale Goods"
        }
    ],
    "sg:phone":"+1 514 389 3255",
    "sg:postcode":"H2P 2L8",
    "sg:province":"QC",
    "sg:tags":[
        "sewing",
        "contractor"
    ],
    "wof:name":"Pantalons Garantis & Fairmount",
    "wof:placetype":"venue"
},
  "geometry": {"coordinates":[-73.63404800000001,45.539501],"type":"Point"}
}