{
  "type": "Feature",
  "properties": {
    "addr:full":"428 Main St N Moose Jaw SK S6H 3K2",
    "addr:housenumber":"428",
    "addr:postcode":"s6h 3k2",
    "addr:street":"Main St N",
    "iso:country":"CA",
    "sg:address":"428 Main St N",
    "sg:city":"Moose Jaw",
    "sg:classifiers":[
        {
            "category":"Shopping",
            "subcategory":"Clothing, Apparel, & Fashions",
            "type":"Retail Goods"
        }
    ],
    "sg:phone":"+1 306 692 1930",
    "sg:postcode":"S6H 3K2",
    "sg:province":"SK",
    "sg:tags":[
        "furnishing"
    ],
    "wof:name":"Hunter's Mens Wear",
    "wof:placetype":"venue"
},
  "geometry": {"coordinates":[-105.535027,50.393761],"type":"Point"}
}