{
  "type": "Feature",
  "properties": {
    "addr:full":"1496 Stationmaster Lane Oakville ON L6M 3A8",
    "addr:housenumber":"1496",
    "addr:postcode":"l6m 3a8",
    "addr:street":"Stationmaster Lane",
    "iso:country":"CA",
    "sg:address":"1496 Stationmaster Lane",
    "sg:city":"Oakville",
    "sg:classifiers":[
        {
            "category":"Professional",
            "subcategory":"Computer Services",
            "type":"Services"
        }
    ],
    "sg:phone":"+1 905 847 8646",
    "sg:postcode":"L6M 3A8",
    "sg:province":"ON",
    "sg:tags":[
        "repair",
        "consultant"
    ],
    "wof:name":"Bliss Technologies",
    "wof:placetype":"venue"
},
  "geometry": {"coordinates":[-79.74992370610001,43.4275436401],"type":"Point"}
}