{
  "type": "Feature",
  "properties": {
    "iso:country":"CA",
    "sg:address":"5301 46 St",
    "sg:city":"Elk Point",
    "sg:classifiers":[
        {
            "category":"Retail",
            "subcategory":"Auto Repair",
            "type":"Services"
        }
    ],
    "sg:phone":"+1 780 724 2000",
    "sg:postcode":"T0A 1A0",
    "sg:province":"AB",
    "sg:tags":[
        "body",
        "automobile",
        "painting"
    ],
    "wof:name":"Signatures Collision & Frame",
    "wof:placetype":"venue"
},
  "geometry": {"coordinates":[-110.893470764,53.9000701904],"type":"Point"}
}