{
  "type": "Feature",
  "properties": {
    "addr:full":"Saskatoon SK S7M 2K4",
    "addr:postcode":"s7m 2k4",
    "iso:country":"CA",
    "sg:city":"Saskatoon",
    "sg:classifiers":[
        {
            "category":"Organizations",
            "subcategory":"Religious Organization",
            "type":"Services"
        }
    ],
    "sg:phone":"+1 306 664 3459",
    "sg:postcode":"S7M 2K4",
    "sg:province":"SK",
    "sg:tags":[
        "church"
    ],
    "wof:name":"St George's Ukrainian Catholic",
    "wof:placetype":"venue"
},
  "geometry": {"coordinates":[-106.68861389200001,52.1274375916],"type":"Point"}
}