{
  "type": "Feature",
  "properties": {
    "addr:full":"Denbigh ON K0H 1L0",
    "addr:postcode":"k0h 1l0",
    "iso:country":"CA",
    "sg:city":"Denbigh",
    "sg:classifiers":[
        {
            "category":"Manufacturing",
            "subcategory":"Lumber",
            "type":"Manufacturing & Wholesale Goods"
        }
    ],
    "sg:phone":"+1 613 333 2228",
    "sg:postcode":"K0H 1L0",
    "sg:province":"ON",
    "sg:tags":[
        "company",
        "logging"
    ],
    "wof:name":"Dlj Logging",
    "wof:placetype":"venue"
},
  "geometry": {"coordinates":[-77.2655410767,45.1427879333],"type":"Point"}
}