{
  "type": "Feature",
  "properties": {
    "addr:full":"Fort Erie ON L2A 2P1",
    "addr:postcode":"l2a 2p1",
    "iso:country":"CA",
    "sg:city":"Fort Erie",
    "sg:classifiers":[
        {
            "category":"Manufacturing",
            "subcategory":"Tools & Machinery",
            "type":"Manufacturing & Wholesale Goods"
        }
    ],
    "sg:phone":"+1 905 871 0863",
    "sg:postcode":"L2A 2P1",
    "sg:province":"ON",
    "sg:tags":[
        "die",
        "maker"
    ],
    "wof:name":"Die Forme Ltd",
    "wof:placetype":"venue"
},
  "geometry": {"coordinates":[-78.9211425781,42.9254302979],"type":"Point"}
}