{
  "type": "Feature",
  "properties": {
    "addr:full":"6100 Ch DE LA Cote-DE-Liesse Saint-Laurent QC H4T 1E3",
    "addr:postcode":"6100;h4t 1e3",
    "addr:street":"Ch De La Cote-De-Liesse",
    "iso:country":"CA",
    "sg:address":"6100 Ch DE LA Cote-DE-Liesse",
    "sg:city":"Saint-Laurent",
    "sg:classifiers":[
        {
            "category":"Freight",
            "type":"Transportation"
        }
    ],
    "sg:phone":"+1 514 734 0249",
    "sg:postcode":"H4T 1E3",
    "sg:province":"QC",
    "sg:tags":[
        "warehouse",
        "storage"
    ],
    "wof:name":"Entrepot Atlas Refrigeration",
    "wof:placetype":"venue"
},
  "geometry": {"coordinates":[-73.6874084473,45.4884872437],"type":"Point"}
}