{
  "type": "Feature",
  "properties": {
    "addr:full":"Maskinonge QC J0K 1N0",
    "addr:postcode":"j0k 1n0",
    "iso:country":"CA",
    "sg:city":"Maskinonge",
    "sg:classifiers":[
        {
            "category":"Personal",
            "subcategory":"Beauty Salon",
            "type":"Services"
        }
    ],
    "sg:phone":"+1 819 227 2443",
    "sg:postcode":"J0K 1N0",
    "sg:province":"QC",
    "wof:name":"Salon Jean-Rene",
    "wof:placetype":"venue"
},
  "geometry": {"coordinates":[-73.025429,46.194073],"type":"Point"}
}