{
  "type": "Feature",
  "properties": {
    "addr:full":"1286 Cartwright St Vancouver BC V6H 3R8",
    "addr:housenumber":"1286",
    "addr:postcode":"v6h 3r8",
    "addr:street":"Cartwright St",
    "iso:country":"CA",
    "sg:address":"1286 Cartwright St",
    "sg:city":"Vancouver",
    "sg:classifiers":[
        {
            "category":"Education",
            "subcategory":"Dance Studio",
            "type":"Public Place"
        }
    ],
    "sg:phone":"+1 604 681 5268",
    "sg:postcode":"V6H 3R8",
    "sg:province":"BC",
    "sg:tags":[
        "instruction",
        "dancing"
    ],
    "wof:name":"Arts Umbrella",
    "wof:placetype":"venue"
},
  "geometry": {"coordinates":[-123.133239746,49.2695808411],"type":"Point"}
}