{
  "type": "Feature",
  "properties": {
    "addr:full":"20091 113B Ave Maple Ridge BC V2X 0Z2",
    "addr:housenumber":"20091",
    "addr:postcode":"v2x 0z2",
    "addr:street":"113B Ave",
    "iso:country":"CA",
    "sg:address":"20091 113B Ave",
    "sg:city":"Maple Ridge",
    "sg:classifiers":[
        {
            "category":"Manufacturing",
            "subcategory":"Food",
            "type":"Manufacturing & Wholesale Goods"
        }
    ],
    "sg:phone":"+1 604 465 5112",
    "sg:postcode":"V2X 0Z2",
    "sg:province":"BC",
    "sg:tags":[
        "tea",
        "coffee",
        "product"
    ],
    "wof:name":"Best Gourmet Coffee Wholesale",
    "wof:placetype":"venue"
},
  "geometry": {"coordinates":[-122.605827331,49.2168464661],"type":"Point"}
}