{
  "type": "Feature",
  "properties": {
    "iso:country":"CA",
    "sg:address":"207 Broadway Ave E",
    "sg:city":"Redcliff",
    "sg:classifiers":[
        {
            "category":"Restaurant",
            "type":"Food & Drink"
        }
    ],
    "sg:phone":"+1 403 548 2656",
    "sg:postcode":"T0J 2P0",
    "sg:province":"AB",
    "wof:name":"Subway Sandwiches & Salads",
    "wof:placetype":"venue"
},
  "geometry": {"coordinates":[-110.786048889,50.0773468018],"type":"Point"}
}