{
  "type": "Feature",
  "properties": {
    "addr:full":"Winnipeg MB R3B 1K2",
    "addr:postcode":"r3b 1k2",
    "iso:country":"CA",
    "sg:city":"Winnipeg",
    "sg:classifiers":[
        {
            "category":"Shopping",
            "subcategory":"Stationery & Office Supplies",
            "type":"Retail Goods"
        }
    ],
    "sg:phone":"+1 204 943 0354",
    "sg:postcode":"R3B 1K2",
    "sg:province":"MB",
    "sg:tags":[
        "map"
    ],
    "wof:name":"Sherlock Publishing Ltd",
    "wof:placetype":"venue"
},
  "geometry": {"coordinates":[-97.143272,49.897278],"type":"Point"}
}