{
  "type": "Feature",
  "properties": {
    "addr:full":"219 Burton School Rd Burton BC V0G 1E0",
    "addr:housenumber":"219",
    "addr:postcode":"v0g 1e0",
    "addr:street":"Burton School Rd",
    "iso:country":"CA",
    "sg:address":"219 Burton School Rd",
    "sg:city":"Burton",
    "sg:classifiers":[
        {
            "category":"Education",
            "subcategory":"School",
            "type":"Public Place"
        }
    ],
    "sg:phone":"+1 250 265 3253",
    "sg:postcode":"V0G 1E0",
    "sg:province":"BC",
    "wof:name":"Burton Elementary School",
    "wof:placetype":"venue"
},
  "geometry": {"coordinates":[-117.87698399999999,49.990849],"type":"Point"}
}