{
  "type": "Feature",
  "properties": {
    "addr:full":"4 Simpson Rd Bolton ON L7E 1G9",
    "addr:housenumber":"4",
    "addr:postcode":"l7e 1g9",
    "addr:street":"Simpson Rd",
    "iso:country":"CA",
    "sg:address":"4 Simpson Rd",
    "sg:city":"Bolton",
    "sg:classifiers":[
        {
            "category":"Manufacturing",
            "subcategory":"Tools & Machinery",
            "type":"Manufacturing & Wholesale Goods"
        }
    ],
    "sg:phone":"+1 905 857 6747",
    "sg:postcode":"L7E 1G9",
    "sg:province":"ON",
    "sg:tags":[
        "furniture"
    ],
    "wof:name":"Teknaform Edge Banding Inc",
    "wof:placetype":"venue"
},
  "geometry": {"coordinates":[-79.727814,43.861908],"type":"Point"}
}