{
  "type": "Feature",
  "properties": {
    "iso:country":"CA",
    "sg:address":"1100 Rue Courval",
    "sg:city":"Lachine",
    "sg:classifiers":[
        {
            "category":"Retail",
            "subcategory":"Auto Rental",
            "type":"Services"
        }
    ],
    "sg:phone":"+1 514 633 5377",
    "sg:postcode":"H8T 3P5",
    "sg:province":"QC",
    "sg:tags":[
        "renting",
        "leasing",
        "trailer"
    ],
    "wof:name":"Action Utility Quebec Inc",
    "wof:placetype":"venue"
},
  "geometry": {"coordinates":[-73.69644927980001,45.4625282288],"type":"Point"}
}