{
  "type": "Feature",
  "properties": {
    "iso:country":"CA",
    "sg:city":"Sainte-Justine-DE-Newton",
    "sg:classifiers":[
        {
            "category":"Retail",
            "subcategory":"Repair Shop",
            "type":"Services"
        }
    ],
    "sg:phone":"+1 450 764 3685",
    "sg:postcode":"J0P 1T0",
    "sg:province":"QC",
    "sg:tags":[
        "taxidermist"
    ],
    "wof:name":"Taxidermie D Leroux",
    "wof:placetype":"venue"
},
  "geometry": {"coordinates":[-74.40473937989999,45.3737030029],"type":"Point"}
}