{
  "type": "Feature",
  "properties": {
    "addr:full":"29 Ch DE Mousson Lorraine QC J6Z 2X7",
    "addr:housenumber":"29",
    "addr:postcode":"j6z 2x7",
    "addr:street":"Ch De Mousson",
    "iso:country":"CA",
    "sg:address":"29 Ch DE Mousson",
    "sg:city":"Lorraine",
    "sg:classifiers":[
        {
            "category":"Insurance",
            "subcategory":"Insurance Agent",
            "type":"Services"
        }
    ],
    "sg:phone":"+1 450 965 0254",
    "sg:postcode":"J6Z 2X7",
    "sg:province":"QC",
    "wof:name":"Robert Brisson Courtier Inc",
    "wof:placetype":"venue"
},
  "geometry": {"coordinates":[-73.7814865112,45.6721954346],"type":"Point"}
}