{
  "type": "Feature",
  "properties": {
    "addr:full":"Calgary AB T2P 1G4",
    "addr:postcode":"t2p 1g4",
    "iso:country":"CA",
    "sg:city":"Calgary",
    "sg:classifiers":[
        {
            "category":"Professional",
            "subcategory":"Advertising",
            "type":"Services"
        }
    ],
    "sg:phone":"+1 403 508 6245",
    "sg:postcode":"T2P 1G4",
    "sg:province":"AB",
    "sg:tags":[
        "mailing",
        "shipping"
    ],
    "wof:name":"Mailstream Management Inc",
    "wof:placetype":"venue"
},
  "geometry": {"coordinates":[-114.074386597,51.0460586548],"type":"Point"}
}