{
  "type": "Feature",
  "properties": {
    "addr:full":"Saskatoon SK S7H 0V6",
    "addr:postcode":"s7h 0v6",
    "iso:country":"CA",
    "sg:city":"Saskatoon",
    "sg:classifiers":[
        {
            "category":"Shopping",
            "subcategory":"Bicycles & Sporting Goods",
            "type":"Retail Goods"
        }
    ],
    "sg:phone":"+1 306 652 1000",
    "sg:postcode":"S7H 0V6",
    "sg:province":"SK",
    "sg:tags":[
        "equipment",
        "golf",
        "supply"
    ],
    "wof:name":"Golf USA",
    "wof:placetype":"venue"
},
  "geometry": {"coordinates":[-106.618172,52.114555],"type":"Point"}
}