{
  "type": "Feature",
  "properties": {
    "addr:full":"Toronto ON M5T 2H4",
    "addr:postcode":"m5t 2h4",
    "iso:country":"CA",
    "sg:city":"Toronto",
    "sg:classifiers":[
        {
            "category":"Professional",
            "subcategory":"Business Services",
            "type":"Services"
        }
    ],
    "sg:phone":"+1 416 703 1606",
    "sg:postcode":"M5T 2H4",
    "sg:province":"ON",
    "sg:tags":[
        "interior",
        "consultant",
        "design",
        "decorator"
    ],
    "wof:name":"Spaces Interiors By",
    "wof:placetype":"venue"
},
  "geometry": {"coordinates":[-79.39868199999999,43.648525],"type":"Point"}
}