{
  "type": "Feature",
  "properties": {
    "iso:country":"CA",
    "sg:address":"5650 Victoria Dr",
    "sg:city":"Vancouver",
    "sg:classifiers":[
        {
            "category":"Food & Beverages",
            "subcategory":"Specialty",
            "type":"Retail Goods"
        }
    ],
    "sg:phone":"+1 604 322 9115",
    "sg:postcode":"V5P 3W4",
    "sg:province":"BC",
    "sg:tags":[
        "health",
        "diet"
    ],
    "wof:name":"PO Chi Tong",
    "wof:placetype":"venue"
},
  "geometry": {"coordinates":[-123.065285,49.233364],"type":"Point"}
}