{
  "type": "Feature",
  "properties": {
    "addr:full":"2958 Bloor St W Etobicoke ON M8X 1B7",
    "addr:housenumber":"2958",
    "addr:postcode":"m8x 1b7",
    "addr:street":"Bloor St W",
    "iso:country":"CA",
    "sg:address":"2958 Bloor St W",
    "sg:city":"Etobicoke",
    "sg:classifiers":[
        {
            "category":"Shopping",
            "subcategory":"Clothing, Apparel, & Fashions",
            "type":"Retail Goods"
        }
    ],
    "sg:phone":"+1 416 231 2238",
    "sg:postcode":"M8X 1B7",
    "sg:province":"ON",
    "wof:name":"Carriage Trade Ltd",
    "wof:placetype":"venue"
},
  "geometry": {"coordinates":[-79.5085525513,43.6481513977],"type":"Point"}
}