{
  "type": "Feature",
  "properties": {
    "addr:full":"Montreal QC H3A 3J5",
    "addr:postcode":"h3a 3j5",
    "iso:country":"CA",
    "sg:city":"Montreal",
    "sg:classifiers":[
        {
            "category":"Shopping",
            "subcategory":"Clothing, Apparel, & Fashions",
            "type":"Retail Goods"
        }
    ],
    "sg:phone":"+1 514 843 8623",
    "sg:postcode":"H3A 3J5",
    "sg:province":"QC",
    "wof:name":"Reitmans",
    "wof:placetype":"venue"
},
  "geometry": {"coordinates":[-73.57178500000001,45.502071],"type":"Point"}
}