{
  "type": "Feature",
  "properties": {
    "addr:full":"110 Geneva St St Catharines ON L2R 4N2",
    "addr:housenumber":"110",
    "addr:postcode":"l2r 4n2",
    "addr:street":"Geneva St",
    "iso:country":"CA",
    "sg:address":"110 Geneva St",
    "sg:city":"St Catharines",
    "sg:classifiers":[
        {
            "category":"Autos & Motor Vehicles",
            "subcategory":"Automobile Sales",
            "type":"Retail Goods"
        }
    ],
    "sg:phone":"+1 905 988 3663",
    "sg:postcode":"L2R 4N2",
    "sg:province":"ON",
    "sg:tags":[
        "repairing",
        "car"
    ],
    "wof:name":"E C Auto Repairs & Fine Cars",
    "wof:placetype":"venue"
},
  "geometry": {"coordinates":[-79.24007415769999,43.1655654907],"type":"Point"}
}