{
  "type": "Feature",
  "properties": {
    "addr:full":"2841 Kingston Rd Scarborough ON M1M 1N2",
    "addr:housenumber":"2841",
    "addr:postcode":"m1m 1n2",
    "addr:street":"Kingston Rd",
    "iso:country":"CA",
    "sg:address":"2841 Kingston Rd",
    "sg:city":"Scarborough",
    "sg:classifiers":[
        {
            "category":"Wholesale",
            "subcategory":"Office Equipment",
            "type":"Manufacturing & Wholesale Goods"
        }
    ],
    "sg:phone":"+1 416 261 4408",
    "sg:postcode":"M1M 1N2",
    "sg:province":"ON",
    "sg:tags":[
        "register",
        "cash",
        "supply"
    ],
    "wof:name":"Teletec Systems Inc",
    "wof:placetype":"venue"
},
  "geometry": {"coordinates":[-79.236328125,43.7214851379],"type":"Point"}
}