{
  "type": "Feature",
  "properties": {
    "iso:country":"CA",
    "sg:address":"154 Wharncliffe Rd S",
    "sg:city":"London",
    "sg:classifiers":[
        {
            "category":"Home & Garden",
            "subcategory":"Garden Supply",
            "type":"Retail Goods"
        }
    ],
    "sg:phone":"+1 519 685 1424",
    "sg:postcode":"N6J 2K6",
    "sg:province":"ON",
    "sg:tags":[
        "center"
    ],
    "wof:name":"Trillium Gardens Perennials",
    "wof:placetype":"venue"
},
  "geometry": {"coordinates":[-81.26187896730001,42.9725837708],"type":"Point"}
}