{
  "type": "Feature",
  "properties": {
    "iso:country":"CA",
    "sg:address":"2151 Boul Lapiniere # K14",
    "sg:city":"Brossard",
    "sg:classifiers":[
        {
            "category":"Shopping",
            "subcategory":"Jewelry",
            "type":"Retail Goods"
        }
    ],
    "sg:phone":"+1 450 671 2323",
    "sg:postcode":"J4W 2T5",
    "sg:province":"QC",
    "sg:tags":[
        "watch"
    ],
    "wof:name":"Boutique Key West Inc",
    "wof:placetype":"venue"
},
  "geometry": {"coordinates":[-73.470505,45.473446],"type":"Point"}
}