{
  "type": "Feature",
  "properties": {
    "iso:country":"CA",
    "sg:address":"140 Erickson Dr",
    "sg:city":"Red Deer",
    "sg:classifiers":[
        {
            "category":"Food & Beverages",
            "subcategory":"Groceries & Convenience Stores",
            "type":"Retail Goods"
        }
    ],
    "sg:phone":"+1 403 343 1101",
    "sg:postcode":"T4R 2C3",
    "sg:province":"AB",
    "sg:tags":[
        "grocer"
    ],
    "wof:name":"Express 24 Foodmart",
    "wof:placetype":"venue"
},
  "geometry": {"coordinates":[-113.773597717,52.2658309937],"type":"Point"}
}