{
  "type": "Feature",
  "properties": {
    "iso:country":"CA",
    "sg:address":"551 Boul Sir-Wilfrid-Laurier",
    "sg:city":"Beloeil",
    "sg:classifiers":[
        {
            "category":"Social Services",
            "type":"Services"
        }
    ],
    "sg:phone":"+1 450 446 6225",
    "sg:postcode":"J3G 4J1",
    "sg:province":"QC",
    "sg:tags":[
        "organization",
        "welfare"
    ],
    "wof:name":"Entraide Pour Hommes Inc",
    "wof:placetype":"venue"
},
  "geometry": {"coordinates":[-73.207054,45.561527],"type":"Point"}
}