{
  "type": "Feature",
  "properties": {
    "addr:full":"893 Boul Saint-Joseph Roberval QC G8H 2L8",
    "addr:housenumber":"893",
    "addr:postcode":"g8h 2l8",
    "addr:street":"Boul Saint-Joseph",
    "iso:country":"CA",
    "sg:address":"893 Boul Saint-Joseph",
    "sg:city":"Roberval",
    "sg:classifiers":[
        {
            "category":"Banks & Credit Unions",
            "subcategory":"Bank",
            "type":"Services"
        }
    ],
    "sg:phone":"+1 418 275 1302",
    "sg:postcode":"G8H 2L8",
    "sg:province":"QC",
    "wof:name":"Banque Royale",
    "wof:placetype":"venue"
},
  "geometry": {"coordinates":[-72.22207641599999,48.5194549561],"type":"Point"}
}