{
  "type": "Feature",
  "properties": {
    "iso:country":"CA",
    "sg:address":"25 Manor Park Ave",
    "sg:city":"Penticton",
    "sg:classifiers":[
        {
            "category":"Health Services",
            "subcategory":"Clinic",
            "type":"Services"
        }
    ],
    "sg:phone":"+1 250 490 9915",
    "sg:postcode":"V2A 2R1",
    "sg:province":"BC",
    "sg:tags":[
        "therapist",
        "massage"
    ],
    "wof:name":"Willow Massage Therapy Ctr",
    "wof:placetype":"venue"
},
  "geometry": {"coordinates":[-119.58558654799999,49.4847755432],"type":"Point"}
}