{
  "type": "Feature",
  "properties": {
    "iso:country":"CA",
    "sg:address":"1830 Kingsway Ave",
    "sg:city":"Port Coquitlam",
    "sg:classifiers":[
        {
            "category":"Manufacturing",
            "subcategory":"Paper Products",
            "type":"Manufacturing & Wholesale Goods"
        }
    ],
    "sg:phone":"+1 604 941 8722",
    "sg:postcode":"V3C 1S5",
    "sg:province":"BC",
    "sg:tags":[
        "bag"
    ],
    "wof:name":"New World Ind Ltd",
    "wof:placetype":"venue"
},
  "geometry": {"coordinates":[-122.767464,49.254795],"type":"Point"}
}