{
  "type": "Feature",
  "properties": {
    "addr:full":"101 Rue Royale Les Coteaux QC J7X 1A6",
    "addr:housenumber":"101",
    "addr:postcode":"j7x 1a6",
    "addr:street":"Rue Royale",
    "iso:country":"CA",
    "sg:address":"101 Rue Royale",
    "sg:city":"Les Coteaux",
    "sg:classifiers":[
        {
            "category":"Building & Trades",
            "subcategory":"Construction",
            "type":"Services"
        }
    ],
    "sg:phone":"+1 450 267 2350",
    "sg:postcode":"J7X 1A6",
    "sg:province":"QC",
    "sg:tags":[
        "downspouts",
        "gutter"
    ],
    "wof:name":"Aluminum Depot Inc",
    "wof:placetype":"venue"
},
  "geometry": {"coordinates":[-74.223434,45.269199],"type":"Point"}
}