{
  "type": "Feature",
  "properties": {
    "addr:full":"1250 Borland Rd # B Williams Lake BC V2G 4V1",
    "addr:housenumber":"1250",
    "addr:postcode":"v2g 4v1",
    "addr:street":"Borland Rd # B",
    "iso:country":"CA",
    "sg:address":"1250 Borland Rd # B",
    "sg:city":"Williams Lake",
    "sg:classifiers":[
        {
            "category":"Freight",
            "type":"Transportation"
        }
    ],
    "sg:phone":"+1 250 392 7900",
    "sg:postcode":"V2G 4V1",
    "sg:province":"BC",
    "sg:tags":[
        "log",
        "hauling"
    ],
    "wof:name":"O B Trucking Ltd",
    "wof:placetype":"venue"
},
  "geometry": {"coordinates":[-122.121864,52.124294],"type":"Point"}
}