{
  "type": "Feature",
  "properties": {
    "addr:full":"Concord ON L4K 4A4",
    "addr:postcode":"l4k 4a4",
    "iso:country":"CA",
    "sg:city":"Concord",
    "sg:classifiers":[
        {
            "category":"Manufacturing",
            "subcategory":"Apparel",
            "type":"Manufacturing & Wholesale Goods"
        }
    ],
    "sg:phone":"+1 905 660 7209",
    "sg:postcode":"L4K 4A4",
    "sg:province":"ON",
    "wof:name":"Acca Fashions Ltd",
    "wof:placetype":"venue"
},
  "geometry": {"coordinates":[-79.49794,43.815788],"type":"Point"}
}