{
  "type": "Feature",
  "properties": {
    "addr:full":"486 Rte Des Bosquets Sainte-Marie-DE-Blandford QC G0X 2W0",
    "addr:housenumber":"486",
    "addr:postcode":"g0x 2w0",
    "addr:street":"Rte Des Bosquets",
    "iso:country":"CA",
    "sg:address":"486 Rte Des Bosquets",
    "sg:city":"Sainte-Marie-DE-Blandford",
    "sg:classifiers":[
        {
            "category":"Organizations",
            "subcategory":"Religious Organization",
            "type":"Services"
        }
    ],
    "sg:phone":"+1 819 283 2113",
    "sg:postcode":"G0X 2W0",
    "sg:province":"QC",
    "sg:tags":[
        "church"
    ],
    "wof:name":"Presbytere Ste-Marie",
    "wof:placetype":"venue"
},
  "geometry": {"coordinates":[-72.177589,46.324928],"type":"Point"}
}