{
  "type": "Feature",
  "properties": {
    "addr:full":"8499 Hwy 23 N Listowel ON N4W 3G6",
    "addr:housenumber":"8499",
    "addr:postcode":"n4w 3g6",
    "addr:street":"Hwy 23 N",
    "iso:country":"CA",
    "sg:address":"8499 Hwy 23 N",
    "sg:city":"Listowel",
    "sg:classifiers":[
        {
            "category":"Wholesale",
            "subcategory":"Machinery & Supplies",
            "type":"Manufacturing & Wholesale Goods"
        }
    ],
    "sg:phone":"+1 519 291 2151",
    "sg:postcode":"N4W 3G6",
    "sg:province":"ON",
    "sg:tags":[
        "farm",
        "equipment"
    ],
    "wof:name":"Stoltz Sales & Svc",
    "wof:placetype":"venue"
},
  "geometry": {"coordinates":[-80.952057,43.732964],"type":"Point"}
}