{
  "type": "Feature",
  "properties": {
    "addr:full":"800 Salisbury Rd Moncton NB E1E 1C5",
    "addr:housenumber":"800",
    "addr:postcode":"e1e 1c5",
    "addr:street":"Salisbury Rd",
    "iso:country":"CA",
    "sg:address":"800 Salisbury Rd",
    "sg:city":"Moncton",
    "sg:classifiers":[
        {
            "category":"Building & Trades",
            "subcategory":"Construction",
            "type":"Services"
        }
    ],
    "sg:phone":"+1 506 855 4044",
    "sg:postcode":"E1E 1C5",
    "sg:province":"NB",
    "sg:tags":[
        "general",
        "contractor"
    ],
    "wof:name":"Rice Contracting Ltd",
    "wof:placetype":"venue"
},
  "geometry": {"coordinates":[-64.84886899999999,46.060768],"type":"Point"}
}