{
  "type": "Feature",
  "properties": {
    "addr:full":"Burnaby BC V5C 6N5",
    "addr:postcode":"v5c 6n5",
    "iso:country":"CA",
    "sg:city":"Burnaby",
    "sg:classifiers":[
        {
            "category":"Organizations",
            "subcategory":"Religious Organization",
            "type":"Services"
        }
    ],
    "sg:phone":"+1 604 299 3908",
    "sg:postcode":"V5C 6N5",
    "sg:province":"BC",
    "sg:tags":[
        "church"
    ],
    "wof:name":"Salvation Army",
    "wof:placetype":"venue"
},
  "geometry": {"coordinates":[-123.020386,49.264072],"type":"Point"}
}