{
  "type": "Feature",
  "properties": {
    "addr:full":"7013 Nesters Rd Whistler BC V0N 1B7",
    "addr:postcode":"7013;v0n 1b7",
    "addr:street":"Nesters Rd",
    "iso:country":"CA",
    "sg:address":"7013 Nesters Rd",
    "sg:city":"Whistler",
    "sg:classifiers":[
        {
            "category":"Restaurant",
            "type":"Food & Drink"
        }
    ],
    "sg:phone":"+1 604 938 0665",
    "sg:postcode":"V0N 1B7",
    "sg:province":"BC",
    "sg:tags":[
        "shop",
        "coffee"
    ],
    "wof:name":"Java At Nesters Ltd",
    "wof:placetype":"venue"
},
  "geometry": {"coordinates":[-122.954315185,50.1304855347],"type":"Point"}
}