{
  "type": "Feature",
  "properties": {
    "iso:country":"CA",
    "sg:address":"4065 Rue Marcel-Lacasse",
    "sg:city":"Boisbriand",
    "sg:classifiers":[
        {
            "category":"Retail",
            "subcategory":"Auto Repair",
            "type":"Services"
        }
    ],
    "sg:phone":"+1 450 430 7105",
    "sg:postcode":"J7H 1N4",
    "sg:province":"QC",
    "sg:tags":[
        "automobile",
        "co",
        "drive",
        "transporter"
    ],
    "wof:name":"Active Canada Inc",
    "wof:placetype":"venue"
},
  "geometry": {"coordinates":[-73.869034,45.633167],"type":"Point"}
}