{
  "type": "Feature",
  "properties": {
    "addr:full":"Brampton ON L6W 4P4",
    "addr:postcode":"l6w 4p4",
    "iso:country":"CA",
    "sg:city":"Brampton",
    "sg:classifiers":[
        {
            "category":"Personal",
            "subcategory":"Beauty Salon",
            "type":"Services"
        }
    ],
    "sg:phone":"+1 905 454 1782",
    "sg:postcode":"L6W 4P4",
    "sg:province":"ON",
    "wof:name":"Nations Hair Salon",
    "wof:placetype":"venue"
},
  "geometry": {"coordinates":[-79.7450332642,43.6919555664],"type":"Point"}
}