{
  "type": "Feature",
  "properties": {
    "addr:full":"Rimouski QC G5M 1A6",
    "addr:postcode":"g5m 1a6",
    "iso:country":"CA",
    "sg:city":"Rimouski",
    "sg:classifiers":[
        {
            "category":"Building & Trades",
            "subcategory":"Construction",
            "type":"Services"
        }
    ],
    "sg:phone":"+1 418 724 8944",
    "sg:postcode":"G5M 1A6",
    "sg:province":"QC",
    "sg:tags":[
        "cabinet",
        "maker",
        "woodworker"
    ],
    "wof:name":"Ebenisterie Dcg Ltee",
    "wof:placetype":"venue"
},
  "geometry": {"coordinates":[-68.505791,48.465336],"type":"Point"}
}