{
  "type": "Feature",
  "properties": {
    "addr:full":"24707 Woodbine Ave # 9 Keswick ON L4P 3E9",
    "addr:housenumber":"24707",
    "addr:postcode":"l4p 3e9",
    "addr:street":"Woodbine Ave # 9",
    "iso:country":"CA",
    "sg:address":"24707 Woodbine Ave # 9",
    "sg:city":"Keswick",
    "sg:classifiers":[
        {
            "category":"Retail",
            "subcategory":"Auto Repair",
            "type":"Services"
        }
    ],
    "sg:phone":"+1 905 989 1354",
    "sg:postcode":"L4P 3E9",
    "sg:province":"ON",
    "sg:tags":[
        "repairing",
        "automobile"
    ],
    "wof:name":"Tech 2 Auto Repair",
    "wof:placetype":"venue"
},
  "geometry": {"coordinates":[-79.4514160156,44.2456016541],"type":"Point"}
}