{
  "type": "Feature",
  "properties": {
    "addr:full":"1010 Elgin St Newmarket ON L3Y 3C1",
    "addr:housenumber":"1010",
    "addr:postcode":"l3y 3c1",
    "addr:street":"Elgin St",
    "iso:country":"CA",
    "sg:address":"1010 Elgin St",
    "sg:city":"Newmarket",
    "sg:classifiers":[
        {
            "category":"Building & Trades",
            "subcategory":"Construction",
            "type":"Services"
        }
    ],
    "sg:phone":"+1 905 953 9111",
    "sg:postcode":"L3Y 3C1",
    "sg:province":"ON",
    "sg:tags":[
        "general",
        "contractor"
    ],
    "wof:name":"Doran Custom Designs",
    "wof:placetype":"venue"
},
  "geometry": {"coordinates":[-79.436859,44.072784],"type":"Point"}
}