{
  "type": "Feature",
  "properties": {
    "addr:full":"17 Glen Stewart Dr Stratford PE C1B 2A8",
    "addr:housenumber":"17",
    "addr:postcode":"c1b 2a8",
    "addr:street":"Glen Stewart Dr",
    "iso:country":"CA",
    "sg:address":"17 Glen Stewart Dr",
    "sg:city":"Stratford",
    "sg:classifiers":[
        {
            "category":"Shopping",
            "subcategory":"Hobbies, Toys, & Games",
            "type":"Retail Goods"
        }
    ],
    "sg:phone":"+1 902 569 3262",
    "sg:postcode":"C1B 2A8",
    "sg:province":"PE",
    "sg:tags":[
        "model",
        "craft",
        "supply"
    ],
    "wof:name":"Great Hobbies",
    "wof:placetype":"venue"
},
  "geometry": {"coordinates":[-63.098751,46.226089],"type":"Point"}
}