{
  "type": "Feature",
  "properties": {
    "addr:full":"Harriston ON N0G 1Z0",
    "addr:postcode":"n0g 1z0",
    "iso:country":"CA",
    "sg:city":"Harriston",
    "sg:classifiers":[
        {
            "category":"Social Services",
            "subcategory":"Child Care",
            "type":"Services"
        }
    ],
    "sg:phone":"+1 519 338 2902",
    "sg:postcode":"N0G 1Z0",
    "sg:province":"ON",
    "wof:name":"Small Angels Day Care",
    "wof:placetype":"venue"
},
  "geometry": {"coordinates":[-80.865723,43.913067],"type":"Point"}
}