{
  "type": "Feature",
  "properties": {
    "iso:country":"CA",
    "sg:address":"598 Upper Branch Rd",
    "sg:city":"Bridgewater",
    "sg:classifiers":[
        {
            "category":"Wholesale",
            "subcategory":"Auto Parts",
            "type":"Manufacturing & Wholesale Goods"
        }
    ],
    "sg:phone":"+1 902 543 5392",
    "sg:postcode":"B4V 2V9",
    "sg:province":"NS",
    "sg:tags":[
        "automobile",
        "wrecking"
    ],
    "wof:name":"R Brown & Sons Auto Slvg Ltd",
    "wof:placetype":"venue"
},
  "geometry": {"coordinates":[-64.5230331421,44.3804969788],"type":"Point"}
}