{
  "type": "Feature",
  "properties": {
    "addr:full":"Calgary AB T2E 6S8",
    "addr:postcode":"t2e 6s8",
    "iso:country":"CA",
    "sg:city":"Calgary",
    "sg:classifiers":[
        {
            "category":"Organizations",
            "subcategory":"Religious Organization",
            "type":"Services"
        }
    ],
    "sg:phone":"+1 403 250 8191",
    "sg:postcode":"T2E 6S8",
    "sg:province":"AB",
    "sg:tags":[
        "church"
    ],
    "wof:name":"Jesus Saves Extended Ministrie",
    "wof:placetype":"venue"
},
  "geometry": {"coordinates":[-114.011894,51.081848],"type":"Point"}
}