{
  "type": "Feature",
  "properties": {
    "iso:country":"CA",
    "sg:city":"Richmond",
    "sg:classifiers":[
        {
            "category":"Shopping",
            "subcategory":"Clothing, Apparel, & Fashions",
            "type":"Retail Goods"
        }
    ],
    "sg:phone":"+1 604 278 1523",
    "sg:postcode":"V6X 1C3",
    "sg:province":"BC",
    "sg:tags":[
        "tailor"
    ],
    "wof:name":"Romarock Custom Tailors",
    "wof:placetype":"venue"
},
  "geometry": {"coordinates":[-123.132667541,49.1784973145],"type":"Point"}
}