{
  "type": "Feature",
  "properties": {
    "iso:country":"CA",
    "sg:address":"9453 198 St",
    "sg:city":"Langley",
    "sg:classifiers":[
        {
            "category":"Wholesale",
            "subcategory":"Auto Parts",
            "type":"Manufacturing & Wholesale Goods"
        }
    ],
    "sg:phone":"+1 604 881 0622",
    "sg:postcode":"V1M 3B8",
    "sg:province":"BC",
    "sg:tags":[
        "automobile",
        "supply"
    ],
    "wof:name":"Auto Sense Auto Parts",
    "wof:placetype":"venue"
},
  "geometry": {"coordinates":[-122.67407989500001,49.1748771667],"type":"Point"}
}