{
  "type": "Feature",
  "properties": {
    "iso:country":"CA",
    "sg:address":"2877 Ch DE Chambly",
    "sg:city":"Longueuil",
    "sg:classifiers":[
        {
            "category":"Personal",
            "subcategory":"Beauty Salon",
            "type":"Services"
        }
    ],
    "sg:phone":"+1 450 651 9715",
    "sg:postcode":"J4L 1M8",
    "sg:province":"QC",
    "wof:name":"Paris Carisme Coiffure",
    "wof:placetype":"venue"
},
  "geometry": {"coordinates":[-73.460663,45.520828],"type":"Point"}
}