{
  "type": "Feature",
  "properties": {
    "addr:full":"1749 Marian Cres Kingston ON K7L 4V3",
    "addr:housenumber":"1749",
    "addr:postcode":"k7l 4v3",
    "addr:street":"Marian Cres",
    "iso:country":"CA",
    "sg:address":"1749 Marian Cres",
    "sg:city":"Kingston",
    "sg:classifiers":[
        {
            "category":"Health Services",
            "subcategory":"Health Practitioner",
            "type":"Services"
        }
    ],
    "sg:phone":"+1 613 542 9396",
    "sg:postcode":"K7L 4V3",
    "sg:province":"ON",
    "sg:tags":[
        "home",
        "nurse",
        "registry"
    ],
    "wof:name":"Gentle Touch",
    "wof:placetype":"venue"
},
  "geometry": {"coordinates":[-76.42626199999999,44.299042],"type":"Point"}
}