{
  "type": "Feature",
  "properties": {
    "iso:country":"CA",
    "sg:address":"459 Ouellette Ave",
    "sg:city":"Windsor",
    "sg:classifiers":[
        {
            "category":"Bars & Pubs",
            "type":"Food & Drink"
        }
    ],
    "sg:phone":"+1 519 253 4040",
    "sg:postcode":"N9A 4J2",
    "sg:province":"ON",
    "sg:tags":[
        "club",
        "night"
    ],
    "wof:name":"Rush Nightclub",
    "wof:placetype":"venue"
},
  "geometry": {"coordinates":[-83.03754425050001,42.3150787354],"type":"Point"}
}