{
  "type": "Feature",
  "properties": {
    "addr:full":"Englehart ON P0J 1H0",
    "addr:postcode":"p0j 1h0",
    "iso:country":"CA",
    "sg:city":"Englehart",
    "sg:classifiers":[
        {
            "category":"Government",
            "subcategory":"Office",
            "type":"Public Place"
        }
    ],
    "sg:phone":"+1 705 544 2244",
    "sg:postcode":"P0J 1H0",
    "sg:province":"ON",
    "sg:tags":[
        "city",
        "hall"
    ],
    "wof:name":"Englehart Town Office",
    "wof:placetype":"venue"
},
  "geometry": {"coordinates":[-79.873161,47.824116],"type":"Point"}
}