{
  "type": "Feature",
  "properties": {
    "addr:full":"3313 30 Ave Vernon BC V1T 2C9",
    "addr:housenumber":"3313",
    "addr:postcode":"v1t 2c9",
    "addr:street":"30 Ave",
    "iso:country":"CA",
    "sg:address":"3313 30 Ave",
    "sg:city":"Vernon",
    "sg:classifiers":[
        {
            "category":"Retail",
            "subcategory":"Photofinishing",
            "type":"Services"
        }
    ],
    "sg:phone":"+1 250 549 1254",
    "sg:postcode":"V1T 2C9",
    "sg:province":"BC",
    "sg:tags":[
        "picture",
        "frame",
        "photo"
    ],
    "wof:name":"Big Picture Photo Finishing",
    "wof:placetype":"venue"
},
  "geometry": {"coordinates":[-119.275497,50.263969],"type":"Point"}
}