{
  "type": "Feature",
  "properties": {
    "addr:full":"3412 Hwy 3 Barrington Passage NS B0W 1G0",
    "addr:housenumber":"3412",
    "addr:postcode":"b0w 1g0",
    "addr:street":"Hwy 3",
    "iso:country":"CA",
    "sg:address":"3412 Hwy 3",
    "sg:city":"Barrington Passage",
    "sg:classifiers":[
        {
            "category":"Restaurant",
            "type":"Food & Drink"
        }
    ],
    "sg:phone":"+1 902 637 3770",
    "sg:postcode":"B0W 1G0",
    "sg:province":"NS",
    "wof:name":"Old School House Restaurant",
    "wof:placetype":"venue"
},
  "geometry": {"coordinates":[-65.6067810059,43.5339698792],"type":"Point"}
}