{
  "type": "Feature",
  "properties": {
    "addr:full":"Sherbrooke QC J1H 1R4",
    "addr:postcode":"j1h 1r4",
    "iso:country":"CA",
    "sg:city":"Sherbrooke",
    "sg:classifiers":[
        {
            "category":"Professional",
            "subcategory":"Business Services",
            "type":"Services"
        }
    ],
    "sg:phone":"+1 819 566 1676",
    "sg:postcode":"J1H 1R4",
    "sg:province":"QC",
    "sg:tags":[
        "arbitration",
        "attorney"
    ],
    "wof:name":"Belhumeur, Pierre",
    "wof:placetype":"venue"
},
  "geometry": {"coordinates":[-71.880409,45.407703],"type":"Point"}
}