{
  "type": "Feature",
  "properties": {
    "addr:full":"536 Dundas St W Toronto ON M5T 1H3",
    "addr:housenumber":"536",
    "addr:postcode":"m5t 1h3",
    "addr:street":"Dundas St W",
    "iso:country":"CA",
    "sg:address":"536 Dundas St W",
    "sg:city":"Toronto",
    "sg:classifiers":[
        {
            "category":"Restaurant",
            "type":"Food & Drink"
        }
    ],
    "sg:phone":"+1 416 299 9011",
    "sg:postcode":"M5T 1H3",
    "sg:province":"ON",
    "sg:tags":[
        "grocer"
    ],
    "wof:name":"Chinese Traditional Food CO",
    "wof:placetype":"venue"
},
  "geometry": {"coordinates":[-79.3988494873,43.65284729],"type":"Point"}
}