{
  "type": "Feature",
  "properties": {
    "addr:full":"133 Church St Antigonish NS B2G 2E2",
    "addr:housenumber":"133",
    "addr:postcode":"b2g 2e2",
    "addr:street":"Church St",
    "iso:country":"CA",
    "sg:address":"133 Church St",
    "sg:city":"Antigonish",
    "sg:classifiers":[
        {
            "category":"Restaurant",
            "type":"Food & Drink"
        }
    ],
    "sg:phone":"+1 902 863 1332",
    "sg:postcode":"B2G 2E2",
    "sg:province":"NS",
    "sg:tags":[
        "delicatessen"
    ],
    "wof:name":"Deli",
    "wof:placetype":"venue"
},
  "geometry": {"coordinates":[-61.9858894348,45.6161689758],"type":"Point"}
}