{
  "type": "Feature",
  "properties": {
    "addr:full":"Cumberland BC V0R 1S0",
    "addr:postcode":"v0r 1s0",
    "iso:country":"CA",
    "sg:city":"Cumberland",
    "sg:classifiers":[
        {
            "category":"Professional",
            "subcategory":"Accounting & Tax Preparation",
            "type":"Services"
        }
    ],
    "sg:phone":"+1 250 336 8612",
    "sg:postcode":"V0R 1S0",
    "sg:province":"BC",
    "sg:tags":[
        "accountant"
    ],
    "wof:name":"Cumberland Accounting & Income",
    "wof:placetype":"venue"
},
  "geometry": {"coordinates":[-125.029846191,49.6190223694],"type":"Point"}
}