{
  "type": "Feature",
  "properties": {
    "addr:full":"115 Clarence Biesenthal Dr Oshawa ON L1K 2H5",
    "addr:housenumber":"115",
    "addr:postcode":"l1k 2h5",
    "addr:street":"Clarence Biesenthal Dr",
    "iso:country":"CA",
    "sg:address":"115 Clarence Biesenthal Dr",
    "sg:city":"Oshawa",
    "sg:classifiers":[
        {
            "category":"Organizations",
            "subcategory":"Professional Association",
            "type":"Services"
        }
    ],
    "sg:phone":"+1 905 433 8004",
    "sg:postcode":"L1K 2H5",
    "sg:province":"ON",
    "wof:name":"Adra Canada",
    "wof:placetype":"venue"
},
  "geometry": {"coordinates":[-78.8188247681,43.9089202881],"type":"Point"}
}