{
  "type": "Feature",
  "properties": {
    "iso:country":"CA",
    "sg:city":"Halifax",
    "sg:classifiers":[
        {
            "category":"Professional",
            "subcategory":"Lawyer & Legal Services",
            "type":"Services"
        }
    ],
    "sg:phone":"+1 902 429 3400",
    "sg:postcode":"B3J 3K8",
    "sg:province":"NS",
    "sg:tags":[
        "attorney"
    ],
    "wof:name":"Ferguson, Margot",
    "wof:placetype":"venue"
},
  "geometry": {"coordinates":[-63.5745887756,44.6486549377],"type":"Point"}
}