{
  "type": "Feature",
  "properties": {
    "iso:country":"CA",
    "sg:address":"5570 Rte Marie-Victorin",
    "sg:city":"Contrecoeur",
    "sg:classifiers":[
        {
            "category":"Insurance",
            "subcategory":"Insurance Agent",
            "type":"Services"
        }
    ],
    "sg:phone":"+1 450 746 1000",
    "sg:postcode":"J0L 1C0",
    "sg:province":"QC",
    "wof:name":"Lussier Cabinet Assurance",
    "wof:placetype":"venue"
},
  "geometry": {"coordinates":[-73.23110198969999,45.8631973267],"type":"Point"}
}