{
  "type": "Feature",
  "properties": {
    "addr:full":"Selkirk MB R1A 2J7",
    "addr:postcode":"r1a 2j7",
    "iso:country":"CA",
    "sg:city":"Selkirk",
    "sg:classifiers":[
        {
            "category":"Restaurant",
            "type":"Food & Drink"
        }
    ],
    "sg:phone":"+1 204 482 3834",
    "sg:postcode":"R1A 2J7",
    "sg:province":"MB",
    "wof:name":"Riverboat Family Restaurant",
    "wof:placetype":"venue"
},
  "geometry": {"coordinates":[-96.87447400000001,50.14333],"type":"Point"}
}