{
  "type": "Feature",
  "properties": {
    "addr:full":"492 Rollingdam Rd Rollingdam NB E5A 2T6",
    "addr:housenumber":"492",
    "addr:postcode":"e5a 2t6",
    "addr:street":"Rollingdam Rd",
    "iso:country":"CA",
    "sg:address":"492 Rollingdam Rd",
    "sg:city":"Rollingdam",
    "sg:classifiers":[
        {
            "category":"Building & Trades",
            "subcategory":"Electrical",
            "type":"Services"
        }
    ],
    "sg:phone":"+1 506 466 5245",
    "sg:postcode":"E5A 2T6",
    "sg:province":"NB",
    "sg:tags":[
        "electric",
        "contractor"
    ],
    "wof:name":"Eddie Gregory Electric",
    "wof:placetype":"venue"
},
  "geometry": {"coordinates":[-67.090439,45.34277],"type":"Point"}
}