{
  "type": "Feature",
  "properties": {
    "addr:full":"83 Boul Des Prairies Laval QC H7N 2T3",
    "addr:housenumber":"83",
    "addr:postcode":"h7n 2t3",
    "addr:street":"Boul Des Prairies",
    "iso:country":"CA",
    "sg:address":"83 Boul Des Prairies",
    "sg:city":"Laval",
    "sg:classifiers":[
        {
            "category":"Education",
            "subcategory":"School",
            "type":"Public Place"
        }
    ],
    "sg:phone":"+1 450 972 6268",
    "sg:postcode":"H7N 2T3",
    "sg:province":"QC",
    "wof:name":"Ecole Vanguard Quebec Ltee",
    "wof:placetype":"venue"
},
  "geometry": {"coordinates":[-73.683548,45.554508],"type":"Point"}
}