{
  "type": "Feature",
  "properties": {
    "addr:full":"Saskatoon SK S7K 4B6",
    "addr:postcode":"s7k 4b6",
    "iso:country":"CA",
    "sg:city":"Saskatoon",
    "sg:classifiers":[
        {
            "category":"Organizations",
            "subcategory":"Labor Organization",
            "type":"Services"
        }
    ],
    "sg:phone":"+1 306 384 0529",
    "sg:postcode":"S7K 4B6",
    "sg:province":"SK",
    "wof:name":"International Brotherhood Eltr",
    "wof:placetype":"venue"
},
  "geometry": {"coordinates":[-106.656173706,52.1710662842],"type":"Point"}
}