{
  "type": "Feature",
  "properties": {
    "addr:full":"111 Heritage Rd Chatham ON N7M 5W7",
    "addr:housenumber":"111",
    "addr:postcode":"n7m 5w7",
    "addr:street":"Heritage Rd",
    "iso:country":"CA",
    "sg:address":"111 Heritage Rd",
    "sg:city":"Chatham",
    "sg:classifiers":[
        {
            "category":"Professional",
            "subcategory":"Advertising",
            "type":"Services"
        }
    ],
    "sg:phone":"+1 519 354 1232",
    "sg:postcode":"N7M 5W7",
    "sg:province":"ON",
    "sg:tags":[
        "counselor"
    ],
    "wof:name":"Hughes Creative",
    "wof:placetype":"venue"
},
  "geometry": {"coordinates":[-82.2100524902,42.3911819458],"type":"Point"}
}