{
  "type": "Feature",
  "properties": {
    "addr:full":"Brandon MB R7A 2S3",
    "addr:postcode":"r7a 2s3",
    "iso:country":"CA",
    "sg:city":"Brandon",
    "sg:classifiers":[
        {
            "category":"Manufacturing",
            "subcategory":"Printing",
            "type":"Manufacturing & Wholesale Goods"
        }
    ],
    "sg:phone":"+1 204 726 9463",
    "sg:postcode":"R7A 2S3",
    "sg:province":"MB",
    "sg:tags":[
        "newspaper"
    ],
    "wof:name":"Western Producer Publications",
    "wof:placetype":"venue"
},
  "geometry": {"coordinates":[-99.952591,49.851189],"type":"Point"}
}