{
  "type": "Feature",
  "properties": {
    "addr:full":"Summerland BC V0H 1Z0",
    "addr:postcode":"v0h 1z0",
    "iso:country":"CA",
    "sg:city":"Summerland",
    "sg:classifiers":[
        {
            "category":"Health Services",
            "subcategory":"Doctor",
            "type":"Services"
        }
    ],
    "sg:phone":"+1 250 494 9711",
    "sg:postcode":"V0H 1Z0",
    "sg:province":"BC",
    "sg:tags":[
        "dentist"
    ],
    "wof:name":"Summerland Dental Ctr",
    "wof:placetype":"venue"
},
  "geometry": {"coordinates":[-119.67768100000001,49.600716],"type":"Point"}
}