{
  "type": "Feature",
  "properties": {
    "iso:country":"CA",
    "sg:city":"Winnipeg",
    "sg:classifiers":[
        {
            "category":"Social Services",
            "type":"Services"
        }
    ],
    "sg:phone":"+1 204 786 8880",
    "sg:postcode":"R3J 3X3",
    "sg:province":"MB",
    "sg:tags":[
        "employee",
        "assistance",
        "program"
    ],
    "wof:name":"Employee Assistance Ctr",
    "wof:placetype":"venue"
},
  "geometry": {"coordinates":[-97.2048797607,49.8833961487],"type":"Point"}
}