{
  "type": "Feature",
  "properties": {
    "addr:full":"95 Ontario Rd Mitchell ON N0K 1N0",
    "addr:housenumber":"95",
    "addr:postcode":"n0k 1n0",
    "addr:street":"Ontario Rd",
    "iso:country":"CA",
    "sg:address":"95 Ontario Rd",
    "sg:city":"Mitchell",
    "sg:classifiers":[
        {
            "category":"Banks & Credit Unions",
            "subcategory":"Bank",
            "type":"Services"
        }
    ],
    "sg:phone":"+1 519 348 8421",
    "sg:postcode":"N0K 1N0",
    "sg:province":"ON",
    "wof:name":"Cibc",
    "wof:placetype":"venue"
},
  "geometry": {"coordinates":[-81.19622,43.467487],"type":"Point"}
}