{
  "type": "Feature",
  "properties": {
    "iso:country":"CA",
    "sg:address":"602 111 Rte 0",
    "sg:city":"Villemontel",
    "sg:classifiers":[
        {
            "category":"Home & Garden",
            "subcategory":"Furniture",
            "type":"Retail Goods"
        }
    ],
    "sg:phone":"+1 819 727 9777",
    "sg:postcode":"J0Y 2S0",
    "sg:province":"QC",
    "wof:name":"Meubles Marchand Ltd",
    "wof:placetype":"venue"
},
  "geometry": {"coordinates":[-78.3581619263,48.6319084167],"type":"Point"}
}