{
  "type": "Feature",
  "properties": {
    "addr:full":"1229 3E Av Saint-Redempteur QC G6K 1E9",
    "addr:housenumber":"1229",
    "addr:postcode":"g6k 1e9",
    "addr:street":"3E Av Saint-Redempteur",
    "iso:country":"CA",
    "sg:address":"1229 3E Av",
    "sg:city":"Saint-Redempteur",
    "sg:classifiers":[
        {
            "category":"Health Services",
            "subcategory":"Medical Lab",
            "type":"Services"
        }
    ],
    "sg:phone":"+1 418 831 2910",
    "sg:postcode":"G6K 1E9",
    "sg:province":"QC",
    "wof:name":"Marc Baron Denturist",
    "wof:placetype":"venue"
},
  "geometry": {"coordinates":[-71.28536987299999,46.6992835999],"type":"Point"}
}