{
  "type": "Feature",
  "properties": {
    "addr:full":"Toronto ON M6E 1B5",
    "addr:postcode":"m6e 1b5",
    "iso:country":"CA",
    "sg:city":"Toronto",
    "sg:classifiers":[
        {
            "category":"Health Services",
            "subcategory":"Doctor",
            "type":"Services"
        }
    ],
    "sg:phone":"+1 416 653 7745",
    "sg:postcode":"M6E 1B5",
    "sg:province":"ON",
    "sg:tags":[
        "physician",
        "surgeon"
    ],
    "wof:name":"Nguyen, Phuongbich MD",
    "wof:placetype":"venue"
},
  "geometry": {"coordinates":[-79.4451141357,43.6774215698],"type":"Point"}
}