{
  "type": "Feature",
  "properties": {
    "iso:country":"CA",
    "sg:city":"Ponoka",
    "sg:classifiers":[
        {
            "category":"Shopping",
            "type":"Retail Goods"
        }
    ],
    "sg:phone":"+1 403 783 5171",
    "sg:postcode":"T4J 1S1",
    "sg:province":"AB",
    "sg:tags":[
        "pet",
        "shop"
    ],
    "wof:name":"Ponoka Pet Shop",
    "wof:placetype":"venue"
},
  "geometry": {"coordinates":[-113.576179504,52.6762123108],"type":"Point"}
}