{
  "type": "Feature",
  "properties": {
    "addr:full":"15 Westcliffe Rd Nepean ON K2H 7X3",
    "addr:housenumber":"15",
    "addr:postcode":"k2h 7x3",
    "addr:street":"Westcliffe Rd",
    "iso:country":"CA",
    "sg:address":"15 Westcliffe Rd",
    "sg:city":"Nepean",
    "sg:classifiers":[
        {
            "category":"Shopping",
            "subcategory":"Clothing, Apparel, & Fashions",
            "type":"Retail Goods"
        }
    ],
    "sg:phone":"+1 613 829 4047",
    "sg:postcode":"K2H 7X3",
    "sg:province":"ON",
    "sg:tags":[
        "dressmaker",
        "tailor"
    ],
    "wof:name":"General Sewing & Alterations",
    "wof:placetype":"venue"
},
  "geometry": {"coordinates":[-75.841301,45.317451],"type":"Point"}
}