{
  "type": "Feature",
  "properties": {
    "iso:country":"CA",
    "sg:address":"556 Stirling Ave S",
    "sg:city":"Kitchener",
    "sg:classifiers":[
        {
            "category":"Food & Beverages",
            "subcategory":"Groceries & Convenience Stores",
            "type":"Retail Goods"
        }
    ],
    "sg:phone":"+1 519 576 4850",
    "sg:postcode":"N2M 3J6",
    "sg:province":"ON",
    "wof:name":"Little Short Stop Stores Ltd",
    "wof:placetype":"venue"
},
  "geometry": {"coordinates":[-80.4946136475,43.4351806641],"type":"Point"}
}