{
  "type": "Feature",
  "properties": {
    "addr:full":"Scarborough ON M1S 4T7",
    "addr:postcode":"m1s 4t7",
    "iso:country":"CA",
    "sg:city":"Scarborough",
    "sg:classifiers":[
        {
            "category":"Health Services",
            "subcategory":"Doctor",
            "type":"Services"
        }
    ],
    "sg:phone":"+1 416 293 3336",
    "sg:postcode":"M1S 4T7",
    "sg:province":"ON",
    "sg:tags":[
        "dentist"
    ],
    "wof:name":"Family Dentistry For Children",
    "wof:placetype":"venue"
},
  "geometry": {"coordinates":[-79.287064,43.803734],"type":"Point"}
}