{
  "type": "Feature",
  "properties": {
    "addr:full":"220 Norfinch Dr North York ON M3N 1Y4",
    "addr:housenumber":"220",
    "addr:postcode":"m3n 1y4",
    "addr:street":"Norfinch Dr",
    "iso:country":"CA",
    "sg:address":"220 Norfinch Dr",
    "sg:city":"North York",
    "sg:classifiers":[
        {
            "category":"Wholesale",
            "subcategory":"Hardware",
            "type":"Manufacturing & Wholesale Goods"
        }
    ],
    "sg:phone":"+1 416 663 9558",
    "sg:postcode":"M3N 1Y4",
    "sg:province":"ON",
    "sg:tags":[
        "purifying",
        "cleaning",
        "air"
    ],
    "wof:name":"Crystal Indoor Air Inc",
    "wof:placetype":"venue"
},
  "geometry": {"coordinates":[-79.529472,43.761642],"type":"Point"}
}