{
  "type": "Feature",
  "properties": {
    "addr:full":"3516 111 Ave NW Edmonton AB T5W 0J6",
    "addr:housenumber":"3516",
    "addr:postcode":"t5w 0j6",
    "addr:street":"111 Ave Nw",
    "iso:country":"CA",
    "sg:address":"3516 111 Ave NW",
    "sg:city":"Edmonton",
    "sg:classifiers":[
        {
            "category":"Wholesale",
            "subcategory":"Farm Supplies",
            "type":"Manufacturing & Wholesale Goods"
        }
    ],
    "sg:phone":"+1 780 471 3425",
    "sg:postcode":"T5W 0J6",
    "sg:province":"AB",
    "sg:tags":[
        "grain"
    ],
    "wof:name":"Certified Grain",
    "wof:placetype":"venue"
},
  "geometry": {"coordinates":[-113.395454407,53.5643424988],"type":"Point"}
}