{
  "type": "Feature",
  "properties": {
    "addr:full":"55 Snider Dr Markham ON L3P 6L7",
    "addr:housenumber":"55",
    "addr:postcode":"l3p 6l7",
    "addr:street":"Snider Dr",
    "iso:country":"CA",
    "sg:address":"55 Snider Dr",
    "sg:city":"Markham",
    "sg:classifiers":[
        {
            "category":"Professional",
            "subcategory":"Business Services",
            "type":"Services"
        }
    ],
    "sg:phone":"+1 905 471 5299",
    "sg:postcode":"L3P 6L7",
    "sg:province":"ON",
    "sg:tags":[
        "trade",
        "exposition",
        "fair",
        "show"
    ],
    "wof:name":"Markham Jazz Festival",
    "wof:placetype":"venue"
},
  "geometry": {"coordinates":[-79.2638626099,43.8812294006],"type":"Point"}
}