{
  "type": "Feature",
  "properties": {
    "addr:full":"5196 Rue Jarry E Saint-Leonard QC H1R 1Y4",
    "addr:housenumber":"5196",
    "addr:postcode":"h1r 1y4",
    "addr:street":"Rue Jarry E",
    "iso:country":"CA",
    "sg:address":"5196 Rue Jarry E",
    "sg:city":"Saint-Leonard",
    "sg:classifiers":[
        {
            "category":"Restaurant",
            "type":"Food & Drink"
        }
    ],
    "sg:phone":"+1 514 852 9452",
    "sg:postcode":"H1R 1Y4",
    "sg:province":"QC",
    "sg:tags":[
        "shop",
        "coffee"
    ],
    "wof:name":"Milano Cafe",
    "wof:placetype":"venue"
},
  "geometry": {"coordinates":[-73.59307098390001,45.5820045471],"type":"Point"}
}