{
  "type": "Feature",
  "properties": {
    "iso:country":"CA",
    "sg:address":"5196 Rue Jarry E",
    "sg:city":"Saint-Leonard",
    "sg:classifiers":[
        {
            "category":"Restaurant",
            "type":"Food & Drink"
        }
    ],
    "sg:phone":"+1 514 852 9452",
    "sg:postcode":"H1R 1Y4",
    "sg:province":"QC",
    "sg:tags":[
        "shop",
        "coffee"
    ],
    "wof:name":"Milano Cafe",
    "wof:placetype":"venue"
},
  "geometry": {"coordinates":[-73.59307098390001,45.5820045471],"type":"Point"}
}