{
  "type": "Feature",
  "properties": {
    "addr:full":"PO Box 80 Cat Lake ON P0V 1J0",
    "addr:housenumber":"po box 80",
    "addr:postcode":"p0v 1j0",
    "addr:street":"Cat Lake",
    "iso:country":"CA",
    "sg:address":"PO Box 80",
    "sg:city":"Cat Lake",
    "sg:classifiers":[
        {
            "category":"Food & Beverages",
            "subcategory":"Groceries & Convenience Stores",
            "type":"Retail Goods"
        }
    ],
    "sg:phone":"+1 807 347 2111",
    "sg:postcode":"P0V 1J0",
    "sg:province":"ON",
    "sg:tags":[
        "department"
    ],
    "wof:name":"Northern Stores",
    "wof:placetype":"venue"
},
  "geometry": {"coordinates":[-91.8353271484,51.7262382507],"type":"Point"}
}