{
  "type": "Feature",
  "properties": {
    "iso:country":"CA",
    "sg:address":"848 Main St E",
    "sg:city":"Hamilton",
    "sg:classifiers":[
        {
            "category":"Professional",
            "subcategory":"Management & Consulting",
            "type":"Services"
        }
    ],
    "sg:phone":"+1 905 545 5433",
    "sg:postcode":"L8M 1L9",
    "sg:province":"ON",
    "sg:tags":[
        "consultant",
        "safety"
    ],
    "wof:name":"Workers Health & Safety Ctr",
    "wof:placetype":"venue"
},
  "geometry": {"coordinates":[-79.835709,43.246487],"type":"Point"}
}