{
  "type": "Feature",
  "properties": {
    "addr:full":"2074 Kipling Ave Etobicoke ON M9W 4J9",
    "addr:housenumber":"2074",
    "addr:postcode":"m9w 4j9",
    "addr:street":"Kipling Ave",
    "iso:country":"CA",
    "sg:address":"2074 Kipling Ave",
    "sg:city":"Etobicoke",
    "sg:classifiers":[
        {
            "category":"Organizations",
            "subcategory":"Religious Organization",
            "type":"Services"
        }
    ],
    "sg:phone":"+1 416 748 8033",
    "sg:postcode":"M9W 4J9",
    "sg:province":"ON",
    "wof:name":"Uma Nabawi Mosque",
    "wof:placetype":"venue"
},
  "geometry": {"coordinates":[-79.568466,43.714996],"type":"Point"}
}