{
  "type": "Feature",
  "properties": {
    "addr:full":"4621 Rue DE Salaberry Montreal QC H4J 1H7",
    "addr:housenumber":"4621",
    "addr:postcode":"h4j 1h7",
    "addr:street":"Rue De Salaberry",
    "iso:country":"CA",
    "sg:address":"4621 Rue DE Salaberry",
    "sg:city":"Montreal",
    "sg:classifiers":[
        {
            "category":"Professional",
            "subcategory":"Computer Services",
            "type":"Services"
        }
    ],
    "sg:phone":"+1 514 331 5809",
    "sg:postcode":"H4J 1H7",
    "sg:province":"QC",
    "sg:tags":[
        "consultant"
    ],
    "wof:name":"Cbgi Inc",
    "wof:placetype":"venue"
},
  "geometry": {"coordinates":[-73.70584106450001,45.533416748],"type":"Point"}
}