{
  "type": "Feature",
  "properties": {
    "iso:country":"CA",
    "sg:address":"55663 Best Line",
    "sg:city":"Tillsonburg",
    "sg:classifiers":[
        {
            "category":"Home & Garden",
            "subcategory":"Garden Supply",
            "type":"Retail Goods"
        }
    ],
    "sg:phone":"+1 519 842 6049",
    "sg:postcode":"N4G 4G8",
    "sg:province":"ON",
    "sg:tags":[
        "center"
    ],
    "wof:name":"Reimer Waterscapes",
    "wof:placetype":"venue"
},
  "geometry": {"coordinates":[-80.7278671265,42.8606758118],"type":"Point"}
}