{
  "type": "Feature",
  "properties": {
    "addr:full":"979 Richmond Rd Ottawa ON K2B 6R1",
    "addr:housenumber":"979",
    "addr:postcode":"k2b 6r1",
    "addr:street":"Richmond Rd",
    "iso:country":"CA",
    "sg:address":"979 Richmond Rd",
    "sg:city":"Ottawa",
    "sg:classifiers":[
        {
            "category":"Retail",
            "subcategory":"Car Wash",
            "type":"Services"
        }
    ],
    "sg:phone":"+1 613 728 4232",
    "sg:postcode":"K2B 6R1",
    "sg:province":"ON",
    "sg:tags":[
        "polishing",
        "washing"
    ],
    "wof:name":"Tops Car Wash CO Ltd",
    "wof:placetype":"venue"
},
  "geometry": {"coordinates":[-75.776932,45.375889],"type":"Point"}
}