{
  "type": "Feature",
  "properties": {
    "addr:full":"1247 Loudoun Rd Winnipeg MB R3S 1A3",
    "addr:housenumber":"1247",
    "addr:postcode":"r3s 1a3",
    "addr:street":"Loudoun Rd",
    "iso:country":"CA",
    "sg:address":"1247 Loudoun Rd",
    "sg:city":"Winnipeg",
    "sg:classifiers":[
        {
            "category":"Manufacturing",
            "subcategory":"Tools & Machinery",
            "type":"Manufacturing & Wholesale Goods"
        }
    ],
    "sg:phone":"+1 204 885 0713",
    "sg:postcode":"R3S 1A3",
    "sg:province":"MB",
    "sg:tags":[
        "disposal",
        "garbage",
        "welding"
    ],
    "wof:name":"Wrought Iron Works",
    "wof:placetype":"venue"
},
  "geometry": {"coordinates":[-97.255486,49.840286],"type":"Point"}
}