{
  "type": "Feature",
  "properties": {
    "addr:full":"8530 101 St NW Edmonton AB T6E 3Z5",
    "addr:housenumber":"8530",
    "addr:postcode":"t6e 3z5",
    "addr:street":"101 St Nw",
    "iso:country":"CA",
    "sg:address":"8530 101 St NW",
    "sg:city":"Edmonton",
    "sg:classifiers":[
        {
            "category":"Social Services",
            "subcategory":"Child Care",
            "type":"Services"
        }
    ],
    "sg:phone":"+1 780 439 9014",
    "sg:postcode":"T6E 3Z5",
    "sg:province":"AB",
    "wof:name":"King Edward Child Care Ctr",
    "wof:placetype":"venue"
},
  "geometry": {"coordinates":[-113.491394043,53.5212478638],"type":"Point"}
}