{
  "type": "Feature",
  "properties": {
    "iso:country":"CA",
    "sg:address":"88 Cannon St W",
    "sg:city":"Hamilton",
    "sg:classifiers":[
        {
            "category":"Manufacturing",
            "subcategory":"Food",
            "type":"Manufacturing & Wholesale Goods"
        }
    ],
    "sg:phone":"+1 905 529 3762",
    "sg:postcode":"L8R 2B6",
    "sg:province":"ON",
    "sg:tags":[
        "juice",
        "fruit"
    ],
    "wof:name":"Mac Nab Grape CO",
    "wof:placetype":"venue"
},
  "geometry": {"coordinates":[-79.871407,43.261833],"type":"Point"}
}