{
  "type": "Feature",
  "properties": {
    "addr:full":"270 Rexdale Blvd Etobicoke ON M9W 1R2",
    "addr:housenumber":"270",
    "addr:postcode":"m9w 1r2",
    "addr:street":"Rexdale Blvd",
    "iso:country":"CA",
    "sg:address":"270 Rexdale Blvd",
    "sg:city":"Etobicoke",
    "sg:classifiers":[
        {
            "category":"Building & Trades",
            "subcategory":"Electrical",
            "type":"Services"
        }
    ],
    "sg:phone":"+1 416 747 0101",
    "sg:postcode":"M9W 1R2",
    "sg:province":"ON",
    "sg:tags":[
        "electric",
        "contractor"
    ],
    "wof:name":"Derock Electric",
    "wof:placetype":"venue"
},
  "geometry": {"coordinates":[-79.57843017579999,43.7133865356],"type":"Point"}
}