{
  "type": "Feature",
  "properties": {
    "addr:full":"3095 1E Av Quebec QC G1L 3P5",
    "addr:housenumber":"3095",
    "addr:postcode":"g1l 3p5",
    "addr:street":"1E Av",
    "iso:country":"CA",
    "sg:address":"3095 1E Av",
    "sg:city":"Quebec",
    "sg:classifiers":[
        {
            "category":"Shopping",
            "subcategory":"Used Merchandise",
            "type":"Retail Goods"
        }
    ],
    "sg:phone":"+1 418 628 7007",
    "sg:postcode":"G1L 3P5",
    "sg:province":"QC",
    "sg:tags":[
        "pawnbroker"
    ],
    "wof:name":"Urgent Comptant Inc",
    "wof:placetype":"venue"
},
  "geometry": {"coordinates":[-71.245628,46.838512],"type":"Point"}
}