{
  "type": "Feature",
  "properties": {
    "addr:full":"44 Meadow Dr Truro NS B2N 5V4",
    "addr:housenumber":"44",
    "addr:postcode":"b2n 5v4",
    "addr:street":"Meadow Dr",
    "iso:country":"CA",
    "sg:address":"44 Meadow Dr",
    "sg:city":"Truro",
    "sg:classifiers":[
        {
            "category":"Building & Trades",
            "subcategory":"Construction",
            "type":"Services"
        }
    ],
    "sg:phone":"+1 902 895 6952",
    "sg:postcode":"B2N 5V4",
    "sg:province":"NS",
    "sg:tags":[
        "general",
        "contractor"
    ],
    "wof:name":"Dexter Construction CO Ltd",
    "wof:placetype":"venue"
},
  "geometry": {"coordinates":[-63.2890396118,45.3660202026],"type":"Point"}
}