{
  "type": "Feature",
  "properties": {
    "addr:full":"546 Lorne St Kamloops BC V2C 1W3",
    "addr:housenumber":"546",
    "addr:postcode":"bc v2c 1w3",
    "addr:street":"Lorne St",
    "iso:country":"CA",
    "sg:address":"546 Lorne St",
    "sg:city":"Kamloops",
    "sg:classifiers":[
        {
            "category":"Building & Trades",
            "subcategory":"Construction",
            "type":"Services"
        }
    ],
    "sg:phone":"+1 250 377 4200",
    "sg:postcode":"V2C 1W3",
    "sg:province":"BC",
    "sg:tags":[
        "contractor"
    ],
    "wof:name":"Culos Development Inc",
    "wof:placetype":"venue"
},
  "geometry": {"coordinates":[-120.328056,50.678303],"type":"Point"}
}