{
  "type": "Feature",
  "properties": {
    "addr:full":"1019 Wharf St Victoria BC V8W 2Y9",
    "addr:housenumber":"1019",
    "addr:postcode":"v8w 2y9",
    "addr:street":"Wharf St",
    "iso:country":"CA",
    "sg:address":"1019 Wharf St",
    "sg:city":"Victoria",
    "sg:classifiers":[
        {
            "category":"Government",
            "subcategory":"Office",
            "type":"Public Place"
        }
    ],
    "sg:phone":"+1 250 387 1602",
    "sg:postcode":"V8W 2Y9",
    "sg:province":"BC",
    "wof:name":"BC Residential Tenancy Branch",
    "wof:placetype":"venue"
},
  "geometry": {"coordinates":[-123.369576,48.424538],"type":"Point"}
}