{
  "type": "Feature",
  "properties": {
    "addr:full":"777 Hornby St # 825 Vancouver BC V6Z 1S4",
    "addr:housenumber":"777;825",
    "addr:postcode":"v6z 1s4",
    "addr:street":"Hornby St #",
    "iso:country":"CA",
    "sg:address":"777 Hornby St # 825",
    "sg:city":"Vancouver",
    "sg:classifiers":[
        {
            "category":"Health Services",
            "subcategory":"Doctor",
            "type":"Services"
        }
    ],
    "sg:phone":"+1 604 685 5255",
    "sg:postcode":"V6Z 1S4",
    "sg:province":"BC",
    "sg:tags":[
        "dentist"
    ],
    "wof:name":"Gordon F Boyd Inc",
    "wof:placetype":"venue"
},
  "geometry": {"coordinates":[-123.12136099999999,49.283028],"type":"Point"}
}