{
  "type": "Feature",
  "properties": {
    "addr:full":"Hwy 2 Souris MB R0K 2C0",
    "addr:postcode":"r0k 2c0",
    "addr:street":"Hwy 2",
    "iso:country":"CA",
    "sg:address":"Hwy 2",
    "sg:city":"Souris",
    "sg:classifiers":[
        {
            "category":"Freight",
            "type":"Transportation"
        }
    ],
    "sg:phone":"+1 204 483 3860",
    "sg:postcode":"R0K 2C0",
    "sg:province":"MB",
    "sg:tags":[
        "grain",
        "elevator"
    ],
    "wof:name":"Agricore United",
    "wof:placetype":"venue"
},
  "geometry": {"coordinates":[-100.256264,49.620827],"type":"Point"}
}