{
  "type": "Feature",
  "properties": {
    "addr:full":"290 Rue Marie-Louise Quebec QC G1N 3J5",
    "addr:housenumber":"290",
    "addr:postcode":"g1n 3j5",
    "addr:street":"Rue Marie-Louise",
    "iso:country":"CA",
    "sg:address":"290 Rue Marie-Louise",
    "sg:city":"Quebec",
    "sg:classifiers":[
        {
            "category":"Manufacturing",
            "subcategory":"Food",
            "type":"Manufacturing & Wholesale Goods"
        }
    ],
    "sg:phone":"+1 418 527 4109",
    "sg:postcode":"G1N 3J5",
    "sg:province":"QC",
    "sg:tags":[
        "grocer",
        "cookie",
        "bakery"
    ],
    "wof:name":"Patisserie St-Albert Enr",
    "wof:placetype":"venue"
},
  "geometry": {"coordinates":[-71.2463226318,46.8068847656],"type":"Point"}
}