{
  "type": "Feature",
  "properties": {
    "addr:full":"16635 Yonge St # 16 Newmarket ON L3X 1V6",
    "addr:housenumber":"16635;16",
    "addr:postcode":"l3x 1v6",
    "addr:street":"Yonge St #",
    "iso:country":"CA",
    "sg:address":"16635 Yonge St # 16",
    "sg:city":"Newmarket",
    "sg:classifiers":[
        {
            "category":"Personal",
            "subcategory":"Beauty Salon",
            "type":"Services"
        }
    ],
    "sg:phone":"+1 905 830 9100",
    "sg:postcode":"L3X 1V6",
    "sg:province":"ON",
    "wof:name":"Ultra Look Unisex Hair Design",
    "wof:placetype":"venue"
},
  "geometry": {"coordinates":[-79.4752578735,44.0336723328],"type":"Point"}
}