{
  "type": "Feature",
  "properties": {
    "addr:full":"Surrey BC V3W 8J6",
    "addr:postcode":"v3w 8j6",
    "iso:country":"CA",
    "sg:city":"Surrey",
    "sg:classifiers":[
        {
            "category":"Building & Trades",
            "subcategory":"Construction",
            "type":"Services"
        }
    ],
    "sg:phone":"+1 604 590 8128",
    "sg:postcode":"V3W 8J6",
    "sg:province":"BC",
    "sg:tags":[
        "contractor"
    ],
    "wof:name":"Stengar Homes Ltd",
    "wof:placetype":"venue"
},
  "geometry": {"coordinates":[-122.849174,49.144325],"type":"Point"}
}