{
  "type": "Feature",
  "properties": {
    "addr:full":"650 Rue Girouard O Saint-Hyacinthe QC J2S 2Y4",
    "addr:housenumber":"650",
    "addr:postcode":"j2s 2y4",
    "addr:street":"Rue Girouard O",
    "iso:country":"CA",
    "sg:address":"650 Rue Girouard O",
    "sg:city":"Saint-Hyacinthe",
    "sg:classifiers":[
        {
            "category":"Education",
            "subcategory":"School",
            "type":"Public Place"
        }
    ],
    "sg:phone":"+1 450 773 2588",
    "sg:postcode":"J2S 2Y4",
    "sg:province":"QC",
    "wof:name":"Soeurs DE LA Presentation DE",
    "wof:placetype":"venue"
},
  "geometry": {"coordinates":[-72.94175720210001,45.6328315735],"type":"Point"}
}