{
  "type": "Feature",
  "properties": {
    "addr:full":"125 W 2nd Ave Qualicum Beach BC V9K 1T1",
    "addr:housenumber":"125",
    "addr:postcode":"v9k 1t1",
    "addr:street":"W 2Nd Ave",
    "iso:country":"CA",
    "sg:address":"125 W 2nd Ave",
    "sg:city":"Qualicum Beach",
    "sg:classifiers":[
        {
            "category":"Restaurant",
            "type":"Food & Drink"
        }
    ],
    "sg:phone":"+1 250 752 2198",
    "sg:postcode":"V9K 1T1",
    "sg:province":"BC",
    "wof:name":"Canton 800 Restaurant",
    "wof:placetype":"venue"
},
  "geometry": {"coordinates":[-124.44515991199999,49.347328186],"type":"Point"}
}