{
  "type": "Feature",
  "properties": {
    "addr:full":"102 Forsyth Cres Saskatoon SK S7N 4H2",
    "addr:housenumber":"102",
    "addr:postcode":"s7n 4h2",
    "addr:street":"Forsyth Cres",
    "iso:country":"CA",
    "sg:address":"102 Forsyth Cres",
    "sg:city":"Saskatoon",
    "sg:classifiers":[
        {
            "category":"Building & Trades",
            "subcategory":"Construction",
            "type":"Services"
        }
    ],
    "sg:phone":"+1 306 249 0119",
    "sg:postcode":"S7N 4H2",
    "sg:province":"SK",
    "sg:tags":[
        "insulation",
        "heat",
        "furnace"
    ],
    "wof:name":"Olson Air Vac Furnace Cleaning",
    "wof:placetype":"venue"
},
  "geometry": {"coordinates":[-106.56452899999999,52.140453],"type":"Point"}
}