{
  "type": "Feature",
  "properties": {
    "addr:full":"4310 Boul Des Forges Trois-Rivieres QC G8Y 1W4",
    "addr:housenumber":"4310",
    "addr:postcode":"g8y 1w4",
    "addr:street":"Boul Des Forges Trois-Rivieres",
    "iso:country":"CA",
    "sg:address":"4310 Boul Des Forges",
    "sg:city":"Trois-Rivieres",
    "sg:classifiers":[
        {
            "category":"Shopping",
            "subcategory":"Shoes",
            "type":"Retail Goods"
        }
    ],
    "sg:phone":"+1 819 376 6444",
    "sg:postcode":"G8Y 1W4",
    "sg:province":"QC",
    "wof:name":"Pieds Sur Terre",
    "wof:placetype":"venue"
},
  "geometry": {"coordinates":[-72.587845,46.357979],"type":"Point"}
}