{
  "type": "Feature",
  "properties": {
    "addr:full":"515 Westmorland Rd Saint John NB E2J 3T1",
    "addr:housenumber":"515",
    "addr:postcode":"e2j 3t1",
    "addr:street":"Westmorland Rd",
    "iso:country":"CA",
    "sg:address":"515 Westmorland Rd",
    "sg:city":"Saint John",
    "sg:classifiers":[
        {
            "category":"Personal",
            "subcategory":"Beauty Salon",
            "type":"Services"
        }
    ],
    "sg:phone":"+1 506 632 3644",
    "sg:postcode":"E2J 3T1",
    "sg:province":"NB",
    "wof:name":"Sears Hair Care",
    "wof:placetype":"venue"
},
  "geometry": {"coordinates":[-66.01664700000001,45.309208],"type":"Point"}
}