{
  "type": "Feature",
  "properties": {
    "addr:full":"484 Roncesvalles Ave Toronto ON M6R 2N5",
    "addr:housenumber":"484",
    "addr:postcode":"m6r 2n5",
    "addr:street":"Roncesvalles Ave",
    "iso:country":"CA",
    "sg:address":"484 Roncesvalles Ave",
    "sg:city":"Toronto",
    "sg:classifiers":[
        {
            "category":"Food & Beverages",
            "subcategory":"Groceries & Convenience Stores",
            "type":"Retail Goods"
        }
    ],
    "sg:phone":"+1 416 535 8006",
    "sg:postcode":"M6R 2N5",
    "sg:province":"ON",
    "wof:name":"Greenfield Grocery Store",
    "wof:placetype":"venue"
},
  "geometry": {"coordinates":[-79.4518737793,43.6533126831],"type":"Point"}
}