{
  "type": "Feature",
  "properties": {
    "addr:full":"Winnipeg MB R2V 4E2",
    "addr:postcode":"r2v 4e2",
    "iso:country":"CA",
    "sg:city":"Winnipeg",
    "sg:classifiers":[
        {
            "category":"Personal",
            "subcategory":"Beauty Salon",
            "type":"Services"
        }
    ],
    "sg:phone":"+1 204 334 3799",
    "sg:postcode":"R2V 4E2",
    "sg:province":"MB",
    "wof:name":"Authentique Hair Design",
    "wof:placetype":"venue"
},
  "geometry": {"coordinates":[-97.09304,49.959209],"type":"Point"}
}