{
  "type": "Feature",
  "properties": {
    "addr:full":"PO Box 127 Caroline AB T0M 0M0",
    "addr:housenumber":"po;127",
    "addr:postcode":"t0m 0m0",
    "addr:street":"Box",
    "iso:country":"CA",
    "sg:address":"PO Box 127",
    "sg:city":"Caroline",
    "sg:classifiers":[
        {
            "category":"Sports & Exercise",
            "subcategory":"Golf",
            "type":"Entertainment"
        }
    ],
    "sg:phone":"+1 403 722 4653",
    "sg:postcode":"T0M 0M0",
    "sg:province":"AB",
    "sg:tags":[
        "course"
    ],
    "wof:name":"Caroline District Golf Course",
    "wof:placetype":"venue"
},
  "geometry": {"coordinates":[-114.740707398,52.0935897827],"type":"Point"}
}