{
  "type": "Feature",
  "properties": {
    "addr:full":"18154 111 Ave NW Edmonton AB T5S 2R1",
    "addr:housenumber":"18154",
    "addr:postcode":"t5s 2r1",
    "addr:street":"111 Ave Nw",
    "iso:country":"CA",
    "sg:address":"18154 111 Ave NW",
    "sg:city":"Edmonton",
    "sg:classifiers":[
        {
            "category":"Building & Trades",
            "subcategory":"Construction",
            "type":"Services"
        }
    ],
    "sg:phone":"+1 780 455 0701",
    "sg:postcode":"T5S 2R1",
    "sg:province":"AB",
    "sg:tags":[
        "repairing",
        "remodeling",
        "contractor"
    ],
    "wof:name":"Pro-Exx Finishing Supplies Ltd",
    "wof:placetype":"venue"
},
  "geometry": {"coordinates":[-113.634048462,53.5598526001],"type":"Point"}
}