{
  "type": "Feature",
  "properties": {
    "addr:full":"Mississauga ON L4T 1A8",
    "addr:postcode":"l4t 1a8",
    "iso:country":"CA",
    "sg:city":"Mississauga",
    "sg:classifiers":[
        {
            "category":"Health Services",
            "subcategory":"Doctor",
            "type":"Services"
        }
    ],
    "sg:phone":"+1 905 673 3220",
    "sg:postcode":"L4T 1A8",
    "sg:province":"ON",
    "sg:tags":[
        "clinic"
    ],
    "wof:name":"Family Practice Ctr",
    "wof:placetype":"venue"
},
  "geometry": {"coordinates":[-79.633698,43.712173],"type":"Point"}
}