{
  "type": "Feature",
  "properties": {
    "addr:full":"39 Arlington St Regina SK S4S 3H7",
    "addr:housenumber":"39",
    "addr:postcode":"s4s 3h7",
    "addr:street":"Arlington St",
    "iso:country":"CA",
    "sg:address":"39 Arlington St",
    "sg:city":"Regina",
    "sg:classifiers":[
        {
            "category":"Education",
            "subcategory":"Special Training",
            "type":"Public Place"
        }
    ],
    "sg:phone":"+1 306 586 4940",
    "sg:postcode":"S4S 3H7",
    "sg:province":"SK",
    "sg:tags":[
        "instruction",
        "driving"
    ],
    "wof:name":"Driving Without Impairment",
    "wof:placetype":"venue"
},
  "geometry": {"coordinates":[-104.627144,50.403465],"type":"Point"}
}