{
  "type": "Feature",
  "properties": {
    "addr:full":"Etobicoke ON M9W 4K8",
    "addr:postcode":"m9w 4k8",
    "iso:country":"CA",
    "sg:city":"Etobicoke",
    "sg:classifiers":[
        {
            "category":"Shopping",
            "subcategory":"Florist",
            "type":"Retail Goods"
        }
    ],
    "sg:phone":"+1 416 748 2785",
    "sg:postcode":"M9W 4K8",
    "sg:province":"ON",
    "wof:name":"Flower Girl",
    "wof:placetype":"venue"
},
  "geometry": {"coordinates":[-79.57019042970001,43.7193069458],"type":"Point"}
}