{
  "type": "Feature",
  "properties": {
    "addr:full":"272 Rue Du Domaine-Lauzon Saint-Faustin-Lac-Carre QC J0T 1J2",
    "addr:housenumber":"272",
    "addr:postcode":"j0t 1j2",
    "addr:street":"Rue Du Domaine-Lauzon",
    "iso:country":"CA",
    "sg:address":"272 Rue Du Domaine-Lauzon",
    "sg:city":"Saint-Faustin-Lac-Carre",
    "sg:classifiers":[
        {
            "category":"Travel",
            "subcategory":"Hotels & Motels",
            "type":"Entertainment"
        }
    ],
    "sg:phone":"+1 819 688 6640",
    "sg:postcode":"J0T 1J2",
    "sg:province":"QC",
    "sg:tags":[
        "bed",
        "breakfast",
        "therapist",
        "accommodation",
        "massage"
    ],
    "wof:name":"Centre DE Sante Sonia Blanchar",
    "wof:placetype":"venue"
},
  "geometry": {"coordinates":[-74.527039,46.117825],"type":"Point"}
}