{
  "type": "Feature",
  "properties": {
    "addr:full":"12827 Lower Main St Middleton NS B0S 1P0",
    "addr:housenumber":"12827",
    "addr:postcode":"b0s 1p0",
    "addr:street":"Lower Main St",
    "iso:country":"CA",
    "sg:address":"12827 Lower Main St",
    "sg:city":"Middleton",
    "sg:classifiers":[
        {
            "category":"Food & Beverages",
            "subcategory":"Groceries & Convenience Stores",
            "type":"Retail Goods"
        }
    ],
    "sg:phone":"+1 902 825 3404",
    "sg:postcode":"B0S 1P0",
    "sg:province":"NS",
    "sg:tags":[
        "grocer"
    ],
    "wof:name":"Tra Atlantic",
    "wof:placetype":"venue"
},
  "geometry": {"coordinates":[-65.06864899999999,44.94241],"type":"Point"}
}