{
  "type": "Feature",
  "properties": {
    "addr:full":"5415 Liberty St N Bowmanville ON L1C 3K6",
    "addr:housenumber":"5415",
    "addr:postcode":"l1c 3k6",
    "addr:street":"Liberty St N",
    "iso:country":"CA",
    "sg:address":"5415 Liberty St N",
    "sg:city":"Bowmanville",
    "sg:classifiers":[
        {
            "category":"Building & Trades",
            "subcategory":"Electrical",
            "type":"Services"
        }
    ],
    "sg:phone":"+1 905 263 2840",
    "sg:postcode":"L1C 3K6",
    "sg:province":"ON",
    "sg:tags":[
        "electric",
        "contractor"
    ],
    "wof:name":"Bratan Installations",
    "wof:placetype":"venue"
},
  "geometry": {"coordinates":[-78.70807600000001,43.97242],"type":"Point"}
}