{
  "type": "Feature",
  "properties": {
    "iso:country":"CA",
    "sg:address":"1400 Bayly St #4B",
    "sg:city":"Pickering",
    "sg:classifiers":[
        {
            "category":"Professional",
            "subcategory":"Business Services",
            "type":"Services"
        }
    ],
    "sg:phone":"+1 905 831 3525",
    "sg:postcode":"L1W 3R2",
    "sg:province":"ON",
    "sg:tags":[
        "license"
    ],
    "wof:name":"Pickering Licence Bureau",
    "wof:placetype":"venue"
},
  "geometry": {"coordinates":[-79.081604,43.830078],"type":"Point"}
}