{
  "type": "Feature",
  "properties": {
    "iso:country":"CA",
    "sg:address":"1204 Rothesay St",
    "sg:city":"Winnipeg",
    "sg:classifiers":[
        {
            "category":"Health Services",
            "subcategory":"Health Practitioner",
            "type":"Services"
        }
    ],
    "sg:phone":"+1 204 982 9195",
    "sg:postcode":"R2G 1T7",
    "sg:province":"MB",
    "sg:tags":[
        "physiotherapist"
    ],
    "wof:name":"River East Physiotherapy",
    "wof:placetype":"venue"
},
  "geometry": {"coordinates":[-97.0807266235,49.936832428],"type":"Point"}
}