{
  "type": "Feature",
  "properties": {
    "addr:full":"762 Dundas St W Toronto ON M6J 1T8",
    "addr:housenumber":"762",
    "addr:postcode":"m6j 1t8",
    "addr:street":"Dundas St W",
    "iso:country":"CA",
    "sg:address":"762 Dundas St W",
    "sg:city":"Toronto",
    "sg:classifiers":[
        {
            "category":"Shopping",
            "subcategory":"Department Store",
            "type":"Retail Goods"
        }
    ],
    "sg:phone":"+1 416 293 7545",
    "sg:postcode":"M6J 1T8",
    "sg:province":"ON",
    "sg:tags":[
        "shop"
    ],
    "wof:name":"Dollar Express",
    "wof:placetype":"venue"
},
  "geometry": {"coordinates":[-79.40696699999999,43.652241],"type":"Point"}
}