{
  "type": "Feature",
  "properties": {
    "addr:full":"1245 Dupont St Toronto ON M6H 2A6",
    "addr:housenumber":"1245",
    "addr:postcode":"m6h 2a6",
    "addr:street":"Dupont St",
    "iso:country":"CA",
    "sg:address":"1245 Dupont St",
    "sg:city":"Toronto",
    "sg:classifiers":[
        {
            "category":"Real Estate",
            "subcategory":"Real Estate Operator",
            "type":"Services"
        }
    ],
    "sg:phone":"+1 416 533 2317",
    "sg:postcode":"M6H 2A6",
    "sg:province":"ON",
    "sg:tags":[
        "mall",
        "shopping",
        "center"
    ],
    "wof:name":"Galleria Shopping Ctr",
    "wof:placetype":"venue"
},
  "geometry": {"coordinates":[-79.44156646730001,43.6680870056],"type":"Point"}
}