{
  "type": "Feature",
  "properties": {
    "addr:full":"Toronto ON M4T 1M7",
    "addr:postcode":"m4t 1m7",
    "iso:country":"CA",
    "sg:city":"Toronto",
    "sg:classifiers":[
        {
            "category":"Shopping",
            "subcategory":"Pharmacy",
            "type":"Retail Goods"
        }
    ],
    "sg:phone":"+1 416 962 2111",
    "sg:postcode":"M4T 1M7",
    "sg:province":"ON",
    "wof:name":"May Pharmacy",
    "wof:placetype":"venue"
},
  "geometry": {"coordinates":[-79.3902359009,43.6887550354],"type":"Point"}
}