{
  "type": "Feature",
  "properties": {
    "addr:full":"Mount St & Montague Row Digby NS B0V 1A0",
    "addr:postcode":"b0v 1a0",
    "addr:street":"St & Montague Row",
    "iso:country":"CA",
    "sg:address":"Mount St & Montague Row",
    "sg:city":"Digby",
    "sg:classifiers":[
        {
            "category":"Organizations",
            "subcategory":"Religious Organization",
            "type":"Services"
        }
    ],
    "sg:phone":"+1 902 245 2113",
    "sg:postcode":"B0V 1A0",
    "sg:province":"NS",
    "sg:tags":[
        "church"
    ],
    "wof:name":"Baptist Church",
    "wof:placetype":"venue"
},
  "geometry": {"coordinates":[-65.754768,44.620377],"type":"Point"}
}