{
  "type": "Feature",
  "properties": {
    "addr:full":"249 Supertest Rd North York ON M3J 2M4",
    "addr:housenumber":"249",
    "addr:postcode":"m3j 2m4",
    "addr:street":"Supertest Rd",
    "iso:country":"CA",
    "sg:address":"249 Supertest Rd",
    "sg:city":"North York",
    "sg:classifiers":[
        {
            "category":"Home & Garden",
            "subcategory":"Building Materials",
            "type":"Retail Goods"
        }
    ],
    "sg:phone":"+1 416 736 0981",
    "sg:postcode":"M3J 2M4",
    "sg:province":"ON",
    "sg:tags":[
        "mixed",
        "concrete"
    ],
    "wof:name":"Central Mobile Concrete Ltd",
    "wof:placetype":"venue"
},
  "geometry": {"coordinates":[-79.470276,43.777538],"type":"Point"}
}