{
  "type": "Feature",
  "properties": {
    "addr:full":"Sainte-Elisabeth QC J0K 2J0",
    "addr:postcode":"j0k 2j0",
    "addr:street":"Sainte-Elisabeth",
    "iso:country":"CA",
    "sg:city":"Sainte-Elisabeth",
    "sg:classifiers":[
        {
            "category":"Organizations",
            "subcategory":"Non-profit Organization",
            "type":"Services"
        }
    ],
    "sg:phone":"+1 450 755 2377",
    "sg:postcode":"J0K 2J0",
    "sg:province":"QC",
    "sg:tags":[
        "info",
        "social",
        "drug",
        "abuse",
        "treatment",
        "welfare",
        "addiction"
    ],
    "wof:name":"Maison Semence DE Vie Inc",
    "wof:placetype":"venue"
},
  "geometry": {"coordinates":[-73.303406,46.097813],"type":"Point"}
}