{
  "type": "Feature",
  "properties": {
    "addr:full":"4807 20 Ave NW Calgary AB T3B 0V2",
    "addr:housenumber":"4807",
    "addr:postcode":"t3b 0v2",
    "addr:street":"20 Ave Nw",
    "iso:country":"CA",
    "sg:address":"4807 20 Ave NW",
    "sg:city":"Calgary",
    "sg:classifiers":[
        {
            "category":"Building & Trades",
            "subcategory":"Construction",
            "type":"Services"
        }
    ],
    "sg:phone":"+1 403 288 3484",
    "sg:postcode":"T3B 0V2",
    "sg:province":"AB",
    "sg:tags":[
        "roofing",
        "contractor"
    ],
    "wof:name":"D & S Home Improvements Ltd",
    "wof:placetype":"venue"
},
  "geometry": {"coordinates":[-114.1605,51.075123],"type":"Point"}
}