{
  "type": "Feature",
  "properties": {
    "addr:full":"1850 Champlain Ave Whitby ON L1N 6A7",
    "addr:housenumber":"1850",
    "addr:postcode":"l1n 6a7",
    "addr:street":"Champlain Ave",
    "iso:country":"CA",
    "sg:address":"1850 Champlain Ave",
    "sg:city":"Whitby",
    "sg:classifiers":[
        {
            "category":"Building & Trades",
            "subcategory":"Equipment Rental",
            "type":"Services"
        }
    ],
    "sg:phone":"+1 905 576 2800",
    "sg:postcode":"L1N 6A7",
    "sg:province":"ON",
    "sg:tags":[
        "yard",
        "contractor"
    ],
    "wof:name":"Rent All Ctr",
    "wof:placetype":"venue"
},
  "geometry": {"coordinates":[-78.8959350586,43.8718452454],"type":"Point"}
}