{
  "type": "Feature",
  "properties": {
    "addr:full":"8157 99 St NW Edmonton AB T6E 3S9",
    "addr:housenumber":"8157",
    "addr:postcode":"t6e 3s9",
    "addr:street":"99 St Nw",
    "iso:country":"CA",
    "sg:address":"8157 99 St NW",
    "sg:city":"Edmonton",
    "sg:classifiers":[
        {
            "category":"Shopping",
            "type":"Retail Goods"
        }
    ],
    "sg:phone":"+1 780 432 9233",
    "sg:postcode":"T6E 3S9",
    "sg:province":"AB",
    "sg:tags":[
        "miscellaneous",
        "store"
    ],
    "wof:name":"Love Boutique",
    "wof:placetype":"venue"
},
  "geometry": {"coordinates":[-113.485985,53.517593],"type":"Point"}
}