{
  "type": "Feature",
  "properties": {
    "addr:full":"Wellesley ON N0B 2T0",
    "addr:postcode":"n0b 2t0",
    "iso:country":"CA",
    "sg:city":"Wellesley",
    "sg:classifiers":[
        {
            "category":"Shopping",
            "subcategory":"Catalog Store",
            "type":"Retail Goods"
        }
    ],
    "sg:phone":"+1 519 656 2535",
    "sg:postcode":"N0B 2T0",
    "sg:province":"ON",
    "sg:tags":[
        "mail",
        "order",
        "internet"
    ],
    "wof:name":"Sears Canada Inc",
    "wof:placetype":"venue"
},
  "geometry": {"coordinates":[-80.7653503418,43.4700698853],"type":"Point"}
}