{
  "type": "Feature",
  "properties": {
    "iso:country":"CA",
    "sg:address":"2370 Irvine Cres",
    "sg:city":"Estevan",
    "sg:classifiers":[
        {
            "category":"Mining & Drilling",
            "type":"Manufacturing & Wholesale Goods"
        }
    ],
    "sg:phone":"+1 306 634 5566",
    "sg:postcode":"S4A 2S6",
    "sg:province":"SK",
    "sg:tags":[
        "oil",
        "well"
    ],
    "wof:name":"C & W Oilfield Construction",
    "wof:placetype":"venue"
},
  "geometry": {"coordinates":[-103.008102417,49.1533622742],"type":"Point"}
}