{
  "type": "Feature",
  "properties": {
    "iso:country":"CA",
    "sg:address":"595 Clifton St",
    "sg:city":"Winnipeg",
    "sg:classifiers":[
        {
            "category":"Real Estate",
            "subcategory":"Real Estate Operator",
            "type":"Services"
        }
    ],
    "sg:phone":"+1 204 488 2274",
    "sg:postcode":"R3G 2X5",
    "sg:province":"MB",
    "sg:tags":[
        "building",
        "register",
        "cash",
        "parks",
        "supply"
    ],
    "wof:name":"Optima Systems Inc",
    "wof:placetype":"venue"
},
  "geometry": {"coordinates":[-97.185989,49.884876],"type":"Point"}
}