{
  "type": "Feature",
  "properties": {
    "addr:full":"Placentia NL A0B 2Y0",
    "addr:postcode":"a0b 2y0",
    "iso:country":"CA",
    "sg:city":"Placentia",
    "sg:classifiers":[
        {
            "category":"Organizations",
            "subcategory":"Professional Association",
            "type":"Services"
        }
    ],
    "sg:phone":"+1 709 227 3531",
    "sg:postcode":"A0B 2Y0",
    "sg:province":"NL",
    "sg:tags":[
        "club"
    ],
    "wof:name":"Royal Canadian Legion",
    "wof:placetype":"venue"
},
  "geometry": {"coordinates":[-53.962219,47.254074],"type":"Point"}
}