{
  "type": "Feature",
  "properties": {
    "addr:full":"537 Alliford Bay Sandspit BC V0T 1T0",
    "addr:housenumber":"537",
    "addr:postcode":"v0t 1t0",
    "addr:street":"Alliford Bay",
    "iso:country":"CA",
    "sg:address":"537 Alliford Bay",
    "sg:city":"Sandspit",
    "sg:classifiers":[
        {
            "category":"Autos & Motor Vehicles",
            "subcategory":"Boat Sales",
            "type":"Retail Goods"
        }
    ],
    "sg:phone":"+1 250 637 5432",
    "sg:postcode":"V0T 1T0",
    "sg:province":"BC",
    "sg:tags":[
        "repairing",
        "repair",
        "outboard"
    ],
    "wof:name":"Don's Marine",
    "wof:placetype":"venue"
},
  "geometry": {"coordinates":[-131.838348,53.238579],"type":"Point"}
}