{
  "type": "Feature",
  "properties": {
    "iso:country":"CA",
    "sg:city":"Gatineau",
    "sg:classifiers":[
        {
            "category":"Home & Garden",
            "subcategory":"Household Appliances",
            "type":"Retail Goods"
        }
    ],
    "sg:phone":"+1 819 663 1789",
    "sg:postcode":"J8P 8A5",
    "sg:province":"QC",
    "wof:name":"Jarmicos Limitee",
    "wof:placetype":"venue"
},
  "geometry": {"coordinates":[-75.6358261108,45.4936561584],"type":"Point"}
}