{
  "type": "Feature",
  "properties": {
    "addr:full":"187 Pumping Station Rd Amherst NS B4H 3Y3",
    "addr:housenumber":"187",
    "addr:postcode":"b4h 3y3",
    "addr:street":"Pumping Station Rd",
    "iso:country":"CA",
    "sg:address":"187 Pumping Station Rd",
    "sg:city":"Amherst",
    "sg:classifiers":[
        {
            "category":"Building & Trades",
            "subcategory":"Plumbing",
            "type":"Services"
        }
    ],
    "sg:phone":"+1 902 667 0010",
    "sg:postcode":"B4H 3Y3",
    "sg:province":"NS",
    "sg:tags":[
        "septic"
    ],
    "wof:name":"Tuxedo Septic Cleaning",
    "wof:placetype":"venue"
},
  "geometry": {"coordinates":[-64.20993,45.832039],"type":"Point"}
}