{
  "type": "Feature",
  "properties": {
    "addr:full":"3066 Boul Dagenais O Laval QC H7P 1T6",
    "addr:housenumber":"3066",
    "addr:postcode":"h7p 1t6",
    "addr:street":"Boul Dagenais O",
    "iso:country":"CA",
    "sg:address":"3066 Boul Dagenais O",
    "sg:city":"Laval",
    "sg:classifiers":[
        {
            "category":"Professional",
            "subcategory":"Computer Services",
            "type":"Services"
        }
    ],
    "sg:phone":"+1 450 963 3391",
    "sg:postcode":"H7P 1T6",
    "sg:province":"QC",
    "sg:tags":[
        "information",
        "system",
        "consultant"
    ],
    "wof:name":"Plurilogic Inc",
    "wof:placetype":"venue"
},
  "geometry": {"coordinates":[-73.791359,45.578861],"type":"Point"}
}