{
  "type": "Feature",
  "properties": {
    "addr:full":"150 Ch Freeman Hull QC J8Z 2B4",
    "addr:housenumber":"150",
    "addr:postcode":"j8z 2b4",
    "addr:street":"Ch Freeman",
    "iso:country":"CA",
    "sg:address":"150 Ch Freeman",
    "sg:city":"Hull",
    "sg:classifiers":[
        {
            "category":"Wholesale",
            "subcategory":"Auto Parts",
            "type":"Manufacturing & Wholesale Goods"
        }
    ],
    "sg:phone":"+1 819 778 7088",
    "sg:postcode":"J8Z 2B4",
    "sg:province":"QC",
    "sg:tags":[
        "automobile",
        "supply"
    ],
    "wof:name":"At Pac",
    "wof:placetype":"venue"
},
  "geometry": {"coordinates":[-75.7432479858,45.4728660583],"type":"Point"}
}