{
  "type": "Feature",
  "properties": {
    "addr:full":"345 Gendron Saint-Leon-Le-Grand QC G0J 2W0",
    "addr:housenumber":"345",
    "addr:postcode":"g0j 2w0",
    "addr:street":"Saint-Leon-Le-Grand",
    "iso:country":"CA",
    "sg:address":"345 Gendron",
    "sg:city":"Saint-Leon-Le-Grand",
    "sg:classifiers":[
        {
            "category":"Organizations",
            "subcategory":"Professional Association",
            "type":"Services"
        }
    ],
    "sg:phone":"+1 418 743 5646",
    "sg:postcode":"G0J 2W0",
    "sg:province":"QC",
    "wof:name":"Chavaliers DE Colomb",
    "wof:placetype":"venue"
},
  "geometry": {"coordinates":[-67.510864,48.375332],"type":"Point"}
}