{
  "type": "Feature",
  "properties": {
    "addr:full":"14 Grant St Charlottetown PE C1A 7J7",
    "addr:housenumber":"14",
    "addr:postcode":"c1a 7j7",
    "addr:street":"Grant St",
    "iso:country":"CA",
    "sg:address":"14 Grant St",
    "sg:city":"Charlottetown",
    "sg:classifiers":[
        {
            "category":"Autos & Motor Vehicles",
            "subcategory":"Motorcycle Sales",
            "type":"Retail Goods"
        }
    ],
    "sg:phone":"+1 902 892 2453",
    "sg:postcode":"C1A 7J7",
    "sg:province":"PE",
    "sg:tags":[
        "scooter"
    ],
    "wof:name":"Glenn's Cycle Works",
    "wof:placetype":"venue"
},
  "geometry": {"coordinates":[-63.094028,46.285728],"type":"Point"}
}