{
  "type": "Feature",
  "properties": {
    "addr:full":"58 Queen Elizabeth Dr Morell PE C0A 1S0",
    "addr:housenumber":"58",
    "addr:postcode":"c0a 1s0",
    "addr:street":"Queen Elizabeth Dr",
    "iso:country":"CA",
    "sg:address":"58 Queen Elizabeth Dr",
    "sg:city":"Morell",
    "sg:classifiers":[
        {
            "category":"Recreation",
            "type":"Entertainment"
        }
    ],
    "sg:phone":"+1 902 961 2689",
    "sg:postcode":"C0A 1S0",
    "sg:province":"PE",
    "sg:tags":[
        "skating",
        "rink"
    ],
    "wof:name":"Morell Community Rink",
    "wof:placetype":"venue"
},
  "geometry": {"coordinates":[-62.7043571472,46.4161109924],"type":"Point"}
}