{
  "type": "Feature",
  "properties": {
    "addr:full":"215 38th St E Prince Albert SK S6W 1A5",
    "addr:housenumber":"215",
    "addr:postcode":"s6w 1a5",
    "addr:street":"38Th St",
    "iso:country":"CA",
    "sg:address":"215 38th St E",
    "sg:city":"Prince Albert",
    "sg:classifiers":[
        {
            "category":"Utilities",
            "subcategory":"Water",
            "type":"Services"
        }
    ],
    "sg:phone":"+1 306 764 6639",
    "sg:postcode":"S6W 1A5",
    "sg:province":"SK",
    "sg:tags":[
        "system",
        "supply"
    ],
    "wof:name":"Anderson Pump House Ltd",
    "wof:placetype":"venue"
},
  "geometry": {"coordinates":[-105.748711,53.178406],"type":"Point"}
}