{
  "type": "Feature",
  "properties": {
    "addr:full":"Sakwasew St Buffalo Narrows SK S0M 0J0",
    "addr:postcode":"s0m 0j0",
    "addr:street":"St",
    "iso:country":"CA",
    "sg:address":"Sakwasew St",
    "sg:city":"Buffalo Narrows",
    "sg:classifiers":[
        {
            "category":"Airport",
            "type":"Transportation"
        }
    ],
    "sg:phone":"+1 306 235 2222",
    "sg:postcode":"S0M 0J0",
    "sg:province":"SK",
    "sg:tags":[
        "helicopter",
        "maintenance"
    ],
    "wof:name":"North Central Helicopters Ltd",
    "wof:placetype":"venue"
},
  "geometry": {"coordinates":[-108.48188,55.865105],"type":"Point"}
}