{
  "type": "Feature",
  "properties": {
    "iso:country":"CA",
    "sg:address":"3407 Rue Jean-Talon E",
    "sg:city":"Montreal",
    "sg:classifiers":[
        {
            "category":"Shopping",
            "subcategory":"Tobacco",
            "type":"Retail Goods"
        }
    ],
    "sg:phone":"+1 514 721 1891",
    "sg:postcode":"H2A 1W7",
    "sg:province":"QC",
    "sg:tags":[
        "cigarette",
        "cigar",
        "dealer"
    ],
    "wof:name":"Tabagie Jean Talon",
    "wof:placetype":"venue"
},
  "geometry": {"coordinates":[-73.596924,45.56065],"type":"Point"}
}