{
  "type": "Feature",
  "properties": {
    "addr:full":"9912 82 Ave NW Edmonton AB T6E 1Y9",
    "addr:housenumber":"9912",
    "addr:postcode":"t6e 1y9",
    "addr:street":"82 Ave Nw",
    "iso:country":"CA",
    "sg:address":"9912 82 Ave NW",
    "sg:city":"Edmonton",
    "sg:classifiers":[
        {
            "category":"Restaurant",
            "type":"Food & Drink"
        }
    ],
    "sg:phone":"+1 780 432 0188",
    "sg:postcode":"T6E 1Y9",
    "sg:province":"AB",
    "wof:name":"Pig N Wistle",
    "wof:placetype":"venue"
},
  "geometry": {"coordinates":[-113.486649,53.518337],"type":"Point"}
}