{
  "type": "Feature",
  "properties": {
    "addr:full":"Mississauga ON L4Z 3E5",
    "addr:postcode":"l4z 3e5",
    "iso:country":"CA",
    "sg:city":"Mississauga",
    "sg:classifiers":[
        {
            "category":"Restaurant",
            "type":"Food & Drink"
        }
    ],
    "sg:phone":"+1 905 755 1249",
    "sg:postcode":"L4Z 3E5",
    "sg:province":"ON",
    "sg:tags":[
        "cafe"
    ],
    "wof:name":"Hannah's Coffee & Deli",
    "wof:placetype":"venue"
},
  "geometry": {"coordinates":[-79.67069244379999,43.6224784851],"type":"Point"}
}