{
  "type": "Feature",
  "properties": {
    "iso:country":"CA",
    "sg:address":"26 12E Ave",
    "sg:city":"Melocheville",
    "sg:classifiers":[
        {
            "category":"Wholesale",
            "subcategory":"Chemicals & Plastics",
            "type":"Manufacturing & Wholesale Goods"
        }
    ],
    "sg:phone":"+1 450 225 2446",
    "sg:postcode":"J0S 1J0",
    "sg:province":"QC",
    "sg:tags":[
        "oil"
    ],
    "wof:name":"LA Chimie Du Cocooning",
    "wof:placetype":"venue"
},
  "geometry": {"coordinates":[-73.95829,45.313801],"type":"Point"}
}