{
  "type": "Feature",
  "properties": {
    "addr:full":"6010 Rue Saint-Jacques Montreal QC H4A 2E9",
    "addr:housenumber":"6010",
    "addr:postcode":"h4a 2e9",
    "addr:street":"Rue Saint-Jacques",
    "iso:country":"CA",
    "sg:address":"6010 Rue Saint-Jacques",
    "sg:city":"Montreal",
    "sg:classifiers":[
        {
            "category":"Retail",
            "subcategory":"Auto Repair",
            "type":"Services"
        }
    ],
    "sg:phone":"+1 514 487 2424",
    "sg:postcode":"H4A 2E9",
    "sg:province":"QC",
    "sg:tags":[
        "body",
        "automobile",
        "painting"
    ],
    "wof:name":"Fix Auto Montreal Ouest",
    "wof:placetype":"venue"
},
  "geometry": {"coordinates":[-73.6158218384,45.4642601013],"type":"Point"}
}