{
  "type": "Feature",
  "properties": {
    "addr:full":"Markham ON L3R 3W5",
    "addr:postcode":"l3r 3w5",
    "iso:country":"CA",
    "sg:city":"Markham",
    "sg:classifiers":[
        {
            "category":"Professional",
            "subcategory":"Research",
            "type":"Services"
        }
    ],
    "sg:phone":"+1 905 474 0058",
    "sg:postcode":"L3R 3W5",
    "sg:province":"ON",
    "sg:tags":[
        "environmental",
        "ecological"
    ],
    "wof:name":"Aims Consulting Environmental",
    "wof:placetype":"venue"
},
  "geometry": {"coordinates":[-79.329239,43.826984],"type":"Point"}
}