{
  "type": "Feature",
  "properties": {
    "addr:full":"Trenton ON K8V 5P7",
    "addr:postcode":"k8v 5p7",
    "iso:country":"CA",
    "sg:city":"Trenton",
    "sg:classifiers":[
        {
            "category":"Professional",
            "subcategory":"Accounting & Tax Preparation",
            "type":"Services"
        }
    ],
    "sg:phone":"+1 613 392 2953",
    "sg:postcode":"K8V 5P7",
    "sg:province":"ON",
    "sg:tags":[
        "accountant"
    ],
    "wof:name":"Weyer, Frank C",
    "wof:placetype":"venue"
},
  "geometry": {"coordinates":[-77.612197876,44.0910186768],"type":"Point"}
}