{
  "type": "Feature",
  "properties": {
    "addr:full":"3500 Boul Poirier Saint-Laurent QC H4R 2J5",
    "addr:housenumber":"3500",
    "addr:postcode":"h4r 2j5",
    "addr:street":"Boul Poirier",
    "iso:country":"CA",
    "sg:address":"3500 Boul Poirier",
    "sg:city":"Saint-Laurent",
    "sg:classifiers":[
        {
            "category":"Wholesale",
            "subcategory":"Machinery & Supplies",
            "type":"Manufacturing & Wholesale Goods"
        }
    ],
    "sg:phone":"+1 514 745 1987",
    "sg:postcode":"H4R 2J5",
    "sg:province":"QC",
    "sg:tags":[
        "valve"
    ],
    "wof:name":"Pneumac",
    "wof:placetype":"venue"
},
  "geometry": {"coordinates":[-73.716942,45.500412],"type":"Point"}
}