{
  "type": "Feature",
  "properties": {
    "addr:full":"940 Queenston Rd Stoney Creek ON L8G 1B7",
    "addr:housenumber":"940",
    "addr:postcode":"l8g 1b7",
    "addr:street":"Queenston Rd",
    "iso:country":"CA",
    "sg:address":"940 Queenston Rd",
    "sg:city":"Stoney Creek",
    "sg:classifiers":[
        {
            "category":"Home & Garden",
            "subcategory":"Furniture",
            "type":"Retail Goods"
        }
    ],
    "sg:phone":"+1 905 662 9030",
    "sg:postcode":"L8G 1B7",
    "sg:province":"ON",
    "wof:name":"B J's Furniture Warehouse",
    "wof:placetype":"venue"
},
  "geometry": {"coordinates":[-79.753227,43.225384],"type":"Point"}
}