{
  "type": "Feature",
  "properties": {
    "addr:full":"Calgary AB T2J 0B2",
    "addr:postcode":"t2j 0b2",
    "iso:country":"CA",
    "sg:city":"Calgary",
    "sg:classifiers":[
        {
            "category":"Shopping",
            "subcategory":"Florist",
            "type":"Retail Goods"
        }
    ],
    "sg:phone":"+1 403 255 6775",
    "sg:postcode":"T2J 0B2",
    "sg:province":"AB",
    "wof:name":"Emery's Florist",
    "wof:placetype":"venue"
},
  "geometry": {"coordinates":[-114.048553,50.969685],"type":"Point"}
}