{
  "type": "Feature",
  "properties": {
    "iso:country":"CA",
    "sg:address":"1 Main St S",
    "sg:city":"Uxbridge",
    "sg:classifiers":[
        {
            "category":"Personal",
            "subcategory":"Beauty Salon",
            "type":"Services"
        }
    ],
    "sg:phone":"+1 905 852 3829",
    "sg:postcode":"L9P 1P7",
    "sg:province":"ON",
    "wof:name":"One Main Salon & Spa",
    "wof:placetype":"venue"
},
  "geometry": {"coordinates":[-79.120186,44.109215],"type":"Point"}
}