{
  "type": "Feature",
  "properties": {
    "addr:full":"1 Main St S Uxbridge ON L9P 1P7",
    "addr:housenumber":"1",
    "addr:postcode":"l9p 1p7",
    "addr:street":"Main St S",
    "iso:country":"CA",
    "sg:address":"1 Main St S",
    "sg:city":"Uxbridge",
    "sg:classifiers":[
        {
            "category":"Personal",
            "subcategory":"Beauty Salon",
            "type":"Services"
        }
    ],
    "sg:phone":"+1 905 852 3829",
    "sg:postcode":"L9P 1P7",
    "sg:province":"ON",
    "wof:name":"One Main Salon & Spa",
    "wof:placetype":"venue"
},
  "geometry": {"coordinates":[-79.120186,44.109215],"type":"Point"}
}