{
  "type": "Feature",
  "properties": {
    "addr:full":"95 Rue Chateauguay Huntingdon QC J0S 1H0",
    "addr:housenumber":"95",
    "addr:postcode":"j0s 1h0",
    "addr:street":"Rue Chateauguay",
    "iso:country":"CA",
    "sg:address":"95 Rue Chateauguay",
    "sg:city":"Huntingdon",
    "sg:classifiers":[
        {
            "category":"Shopping",
            "subcategory":"Clothing, Apparel, & Fashions",
            "type":"Retail Goods"
        }
    ],
    "sg:phone":"+1 450 264 6418",
    "sg:postcode":"J0S 1H0",
    "sg:province":"QC",
    "wof:name":"J L Rodrigue Vetements Enr",
    "wof:placetype":"venue"
},
  "geometry": {"coordinates":[-74.1732635498,45.0863494873],"type":"Point"}
}