{
  "type": "Feature",
  "properties": {
    "iso:country":"CA",
    "sg:address":"255 Rue York",
    "sg:city":"Granby",
    "sg:classifiers":[
        {
            "category":"Home & Garden",
            "subcategory":"Home Furnishings",
            "type":"Retail Goods"
        }
    ],
    "sg:phone":"+1 450 372 6155",
    "sg:postcode":"J2G 2C1",
    "sg:province":"QC",
    "sg:tags":[
        "shop",
        "made",
        "drapery",
        "gift"
    ],
    "wof:name":"Petit Coin Champetre",
    "wof:placetype":"venue"
},
  "geometry": {"coordinates":[-72.7252960205,45.4067153931],"type":"Point"}
}