{
  "type": "Feature",
  "properties": {
    "addr:full":"709 Kearney Lake Rd Bedford NS B4B 1E2",
    "addr:housenumber":"709",
    "addr:postcode":"b4b 1e2",
    "addr:street":"Kearney Lake Rd",
    "iso:country":"CA",
    "sg:address":"709 Kearney Lake Rd",
    "sg:city":"Bedford",
    "sg:classifiers":[
        {
            "category":"Retail",
            "subcategory":"Auto Repair",
            "type":"Services"
        }
    ],
    "sg:phone":"+1 902 835 0860",
    "sg:postcode":"B4B 1E2",
    "sg:province":"NS",
    "sg:tags":[
        "body",
        "automobile",
        "painting"
    ],
    "wof:name":"Rod Le Blanc Auto Body",
    "wof:placetype":"venue"
},
  "geometry": {"coordinates":[-63.721931,44.716595],"type":"Point"}
}