{
  "type": "Feature",
  "properties": {
    "iso:country":"CA",
    "sg:city":"O'Leary",
    "sg:classifiers":[
        {
            "category":"Organizations",
            "subcategory":"Religious Organization",
            "type":"Services"
        }
    ],
    "sg:phone":"+1 902 859 2868",
    "sg:postcode":"C0B 1V0",
    "sg:province":"PE",
    "sg:tags":[
        "church"
    ],
    "wof:name":"United Church Manse-Will",
    "wof:placetype":"venue"
},
  "geometry": {"coordinates":[-63.1035041809,46.2231445312],"type":"Point"}
}