{
  "type": "Feature",
  "properties": {
    "iso:country":"CA",
    "sg:address":"548 Winblest Ave",
    "sg:city":"London",
    "sg:classifiers":[
        {
            "category":"Professional",
            "subcategory":"Management & Consulting",
            "type":"Services"
        }
    ],
    "sg:phone":"+1 519 685 6726",
    "sg:postcode":"N6C 3C1",
    "sg:province":"ON",
    "sg:tags":[
        "consultant",
        "lighting",
        "electric",
        "contractor"
    ],
    "wof:name":"Global Electric London Ltd",
    "wof:placetype":"venue"
},
  "geometry": {"coordinates":[-81.234886,42.944164],"type":"Point"}
}