{
  "type": "Feature",
  "properties": {
    "addr:full":"1111 First St E Fort Frances ON P9A 1M1",
    "addr:housenumber":"1111",
    "addr:postcode":"p9a 1m1",
    "addr:street":"First St E",
    "iso:country":"CA",
    "sg:address":"1111 First St E",
    "sg:city":"Fort Frances",
    "sg:classifiers":[
        {
            "category":"Organizations",
            "subcategory":"Labor Organization",
            "type":"Services"
        }
    ],
    "sg:phone":"+1 807 274 0620",
    "sg:postcode":"P9A 1M1",
    "sg:province":"ON",
    "wof:name":"Cupe",
    "wof:placetype":"venue"
},
  "geometry": {"coordinates":[-93.373916626,48.6109275818],"type":"Point"}
}