{
  "type": "Feature",
  "properties": {
    "iso:country":"CA",
    "sg:address":"87 Rue Gauthier S",
    "sg:city":"Joliette",
    "sg:classifiers":[
        {
            "category":"Personal",
            "subcategory":"Beauty Salon",
            "type":"Services"
        }
    ],
    "sg:phone":"+1 450 752 1101",
    "sg:postcode":"J6E 4J3",
    "sg:province":"QC",
    "wof:name":"Esthetique Bo-Syl",
    "wof:placetype":"venue"
},
  "geometry": {"coordinates":[-73.4318237305,46.0314064026],"type":"Point"}
}