{
  "type": "Feature",
  "properties": {
    "addr:full":"647 Thurston Close Port Moody BC V3H 4J4",
    "addr:housenumber":"647",
    "addr:postcode":"v3h 4j4",
    "addr:street":"Thurston Close",
    "iso:country":"CA",
    "sg:address":"647 Thurston Close",
    "sg:city":"Port Moody",
    "sg:classifiers":[
        {
            "category":"Wholesale",
            "subcategory":"Hardware",
            "type":"Manufacturing & Wholesale Goods"
        }
    ],
    "sg:phone":"+1 604 469 4069",
    "sg:postcode":"V3H 4J4",
    "sg:province":"BC",
    "sg:tags":[
        "parts",
        "boiler"
    ],
    "wof:name":"Moody Industrial Sales Inc",
    "wof:placetype":"venue"
},
  "geometry": {"coordinates":[-122.822517,49.287724],"type":"Point"}
}