{
  "type": "Feature",
  "properties": {
    "addr:full":"58 Main St Ashern MB R0C 0E0",
    "addr:housenumber":"58",
    "addr:postcode":"r0c 0e0",
    "addr:street":"Main St",
    "iso:country":"CA",
    "sg:address":"58 Main St",
    "sg:city":"Ashern",
    "sg:classifiers":[
        {
            "category":"Education",
            "subcategory":"School",
            "type":"Public Place"
        }
    ],
    "sg:phone":"+1 204 768 2625",
    "sg:postcode":"R0C 0E0",
    "sg:province":"MB",
    "wof:name":"Ashern Early Years",
    "wof:placetype":"venue"
},
  "geometry": {"coordinates":[-98.350266,51.180805],"type":"Point"}
}