{
  "type": "Feature",
  "properties": {
    "addr:full":"575 Boul Armand-Frappier Laval QC H7V 4B3",
    "addr:housenumber":"575",
    "addr:postcode":"h7v 4b3",
    "addr:street":"Boul Armand-Frappier",
    "iso:country":"CA",
    "sg:address":"575 Boul Armand-Frappier",
    "sg:city":"Laval",
    "sg:classifiers":[
        {
            "category":"Professional",
            "subcategory":"Testing Lab",
            "type":"Services"
        }
    ],
    "sg:phone":"+1 450 973 6077",
    "sg:postcode":"H7V 4B3",
    "sg:province":"QC",
    "sg:tags":[
        "laboratory"
    ],
    "wof:name":"Algorythme Pharma Inc",
    "wof:placetype":"venue"
},
  "geometry": {"coordinates":[-73.744637,45.551567],"type":"Point"}
}