{
  "type": "Feature",
  "properties": {
    "addr:full":"RR 2 Thorsby AB T0C 2P0",
    "addr:postcode":"t0c 2p0",
    "addr:street":"Rr 2",
    "iso:country":"CA",
    "sg:address":"RR 2",
    "sg:city":"Thorsby",
    "sg:classifiers":[
        {
            "category":"Building & Trades",
            "subcategory":"Landscaping Services",
            "type":"Services"
        }
    ],
    "sg:phone":"+1 780 389 2173",
    "sg:postcode":"T0C 2P0",
    "sg:province":"AB",
    "sg:tags":[
        "landscape",
        "contractor"
    ],
    "wof:name":"Lakeview Trucking & Excavating",
    "wof:placetype":"venue"
},
  "geometry": {"coordinates":[-114.050598145,53.2280654907],"type":"Point"}
}