{
  "type": "Feature",
  "properties": {
    "addr:full":"8 Falk Ave Nepean ON K2J 1L1",
    "addr:housenumber":"8",
    "addr:postcode":"k2j 1l1",
    "addr:street":"Falk Ave",
    "iso:country":"CA",
    "sg:address":"8 Falk Ave",
    "sg:city":"Nepean",
    "sg:classifiers":[
        {
            "category":"Professional",
            "subcategory":"Management & Consulting",
            "type":"Services"
        }
    ],
    "sg:phone":"+1 613 825 6210",
    "sg:postcode":"K2J 1L1",
    "sg:province":"ON",
    "sg:tags":[
        "international",
        "consultant"
    ],
    "wof:name":"Comber & Assoc Consulting",
    "wof:placetype":"venue"
},
  "geometry": {"coordinates":[-75.75260900000001,45.28426],"type":"Point"}
}