{
  "type": "Feature",
  "properties": {
    "addr:full":"927 Kelvin Street Coquitlam, BC V3J 4W7",
    "addr:housenumber":"927",
    "addr:postcode":"v3j 4w7",
    "addr:street":"Kelvin Street",
    "iso:country":"CA",
    "sg:address":"927 Kelvin Street",
    "sg:city":"Coquitlam, BC",
    "sg:classifiers":[
        {
            "category":"Professional",
            "subcategory":"Computer Services",
            "type":"Services"
        }
    ],
    "sg:postcode":"V3J 4W7",
    "sg:website":"http://www.dinehere.ca/",
    "wof:name":"Here Enterprises",
    "wof:placetype":"venue"
},
  "geometry": {"coordinates":[-122.8671616,49.2679216],"type":"Point"}
}