{
  "type": "Feature",
  "properties": {
    "addr:full":"1661 Duranleau St Vancouver BC V6H 3S3",
    "addr:housenumber":"1661",
    "addr:postcode":"v6h 3s3",
    "addr:street":"Duranleau St",
    "iso:country":"CA",
    "sg:address":"1661 Duranleau St",
    "sg:city":"Vancouver",
    "sg:classifiers":[
        {
            "category":"Real Estate",
            "subcategory":"Architect",
            "type":"Services"
        }
    ],
    "sg:phone":"+1 604 682 4853",
    "sg:postcode":"V6H 3S3",
    "sg:province":"BC",
    "wof:name":"Hadfield & Turner Architecture",
    "wof:placetype":"venue"
},
  "geometry": {"coordinates":[-123.135948181,49.272190094],"type":"Point"}
}