{
  "type": "Feature",
  "properties": {
    "iso:country":"CA",
    "sg:address":"174 Spadina Ave",
    "sg:city":"Toronto",
    "sg:classifiers":[
        {
            "category":"Arts & Performance",
            "subcategory":"Theater",
            "type":"Entertainment"
        }
    ],
    "sg:phone":"+1 416 203 9000",
    "sg:postcode":"M5T 2C2",
    "sg:province":"ON",
    "wof:name":"Cahoots Theatre Projects",
    "wof:placetype":"venue"
},
  "geometry": {"coordinates":[-79.3968429565,43.6491394043],"type":"Point"}
}