{
  "type": "Feature",
  "properties": {
    "addr:full":"3200 Bayview Ave North York ON M2M 3R7",
    "addr:housenumber":"3200",
    "addr:postcode":"m2m 3r7",
    "addr:street":"Bayview Ave",
    "iso:country":"CA",
    "sg:address":"3200 Bayview Ave",
    "sg:city":"North York",
    "sg:classifiers":[
        {
            "category":"Organizations",
            "subcategory":"Religious Organization",
            "type":"Services"
        }
    ],
    "sg:phone":"+1 416 221 8900",
    "sg:postcode":"M2M 3R7",
    "sg:province":"ON",
    "sg:tags":[
        "church"
    ],
    "wof:name":"Lutheran Church of St Luke",
    "wof:placetype":"venue"
},
  "geometry": {"coordinates":[-79.39259300000001,43.786274],"type":"Point"}
}