{
  "type": "Feature",
  "properties": {
    "addr:full":"Stellarton NS B0K 1S0",
    "addr:postcode":"b0k 1s0",
    "iso:country":"CA",
    "sg:city":"Stellarton",
    "sg:classifiers":[
        {
            "category":"Retail",
            "subcategory":"Car Wash",
            "type":"Services"
        }
    ],
    "sg:phone":"+1 902 396 8317",
    "sg:postcode":"B0K 1S0",
    "sg:province":"NS",
    "sg:tags":[
        "polishing",
        "washing"
    ],
    "wof:name":"A H Mobile Wash",
    "wof:placetype":"venue"
},
  "geometry": {"coordinates":[-62.6596832275,45.5617446899],"type":"Point"}
}