{
  "type": "Feature",
  "properties": {
    "addr:full":"8922 Harvie Rd Surrey BC V4N 4B8",
    "addr:housenumber":"8922",
    "addr:postcode":"v4n 4b8",
    "addr:street":"Harvie Rd",
    "iso:country":"CA",
    "sg:address":"8922 Harvie Rd",
    "sg:city":"Surrey",
    "sg:classifiers":[
        {
            "category":"Real Estate",
            "subcategory":"Architect",
            "type":"Services"
        }
    ],
    "sg:phone":"+1 604 240 2611",
    "sg:postcode":"V4N 4B8",
    "sg:province":"BC",
    "sg:tags":[
        "course",
        "golf"
    ],
    "wof:name":"Region View Recreation Svc",
    "wof:placetype":"venue"
},
  "geometry": {"coordinates":[-122.69606781,49.164806366],"type":"Point"}
}