{
  "type": "Feature",
  "properties": {
    "addr:full":"5227 Boul Decarie Montreal QC H3W 3C2",
    "addr:housenumber":"5227",
    "addr:postcode":"h3w 3c2",
    "addr:street":"Boul Decarie",
    "iso:country":"CA",
    "sg:address":"5227 Boul Decarie",
    "sg:city":"Montreal",
    "sg:classifiers":[
        {
            "category":"Wholesale",
            "subcategory":"Office Equipment",
            "type":"Manufacturing & Wholesale Goods"
        }
    ],
    "sg:phone":"+1 514 488 0007",
    "sg:postcode":"H3W 3C2",
    "sg:province":"QC",
    "sg:tags":[
        "machine",
        "duplicating",
        "copying"
    ],
    "wof:name":"Copieur Decarie Enr",
    "wof:placetype":"venue"
},
  "geometry": {"coordinates":[-73.63091300000001,45.484818],"type":"Point"}
}