{
  "type": "Feature",
  "properties": {
    "addr:full":"286 Ouellette Ave Windsor ON N9A 1A5",
    "addr:housenumber":"286",
    "addr:postcode":"n9a 1a5",
    "addr:street":"Ouellette Ave",
    "iso:country":"CA",
    "sg:address":"286 Ouellette Ave",
    "sg:city":"Windsor",
    "sg:classifiers":[
        {
            "category":"Manufacturing",
            "subcategory":"Apparel",
            "type":"Manufacturing & Wholesale Goods"
        }
    ],
    "sg:phone":"+1 519 977 8773",
    "sg:postcode":"N9A 1A5",
    "sg:province":"ON",
    "sg:tags":[
        "fur",
        "business"
    ],
    "wof:name":"A & T Furriers Intl",
    "wof:placetype":"venue"
},
  "geometry": {"coordinates":[-83.03899383540001,42.317741394],"type":"Point"}
}