{
  "type": "Feature",
  "properties": {
    "addr:full":"1349 Wallace St Regina SK S4N 3Z5",
    "addr:housenumber":"1349",
    "addr:postcode":"s4n 3z5",
    "addr:street":"Wallace St",
    "iso:country":"CA",
    "sg:address":"1349 Wallace St",
    "sg:city":"Regina",
    "sg:classifiers":[
        {
            "category":"Shopping",
            "subcategory":"Computers & Home Electronics",
            "type":"Retail Goods"
        }
    ],
    "sg:phone":"+1 306 569 2678",
    "sg:postcode":"S4N 3Z5",
    "sg:province":"SK",
    "sg:tags":[
        "automobile",
        "stereo",
        "radio"
    ],
    "wof:name":"Low Cost Radio Tv Svc",
    "wof:placetype":"venue"
},
  "geometry": {"coordinates":[-104.59353637700001,50.4575309753],"type":"Point"}
}