{
  "type": "Feature",
  "properties": {
    "iso:country":"CA",
    "sg:city":"Mayerthorpe",
    "sg:classifiers":[
        {
            "category":"Manufacturing",
            "subcategory":"Printing",
            "type":"Manufacturing & Wholesale Goods"
        }
    ],
    "sg:phone":"+1 780 786 2602",
    "sg:postcode":"T0E 1N0",
    "sg:province":"AB",
    "sg:tags":[
        "newspaper"
    ],
    "wof:name":"Freelancer",
    "wof:placetype":"venue"
},
  "geometry": {"coordinates":[-115.13798523,53.9539375305],"type":"Point"}
}