{
  "type": "Feature",
  "properties": {
    "addr:full":"2785 Commercial Dr Vancouver BC V5N 4C5",
    "addr:housenumber":"2785",
    "addr:postcode":"v5n 4c5",
    "addr:street":"Commercial Dr",
    "iso:country":"CA",
    "sg:address":"2785 Commercial Dr",
    "sg:city":"Vancouver",
    "sg:classifiers":[
        {
            "category":"Food & Beverages",
            "subcategory":"Groceries & Convenience Stores",
            "type":"Retail Goods"
        }
    ],
    "sg:phone":"+1 604 872 5444",
    "sg:postcode":"V5N 4C5",
    "sg:province":"BC",
    "sg:tags":[
        "grocer"
    ],
    "wof:name":"Shop N Save Food Store",
    "wof:placetype":"venue"
},
  "geometry": {"coordinates":[-123.06999969500001,49.2597694397],"type":"Point"}
}