{
  "type": "Feature",
  "properties": {
    "addr:full":"Val-D'Or QC J9P 7A9",
    "addr:postcode":"j9p 7a9",
    "iso:country":"CA",
    "sg:city":"Val-D'Or",
    "sg:classifiers":[
        {
            "category":"Home & Garden",
            "subcategory":"Household Appliances",
            "type":"Retail Goods"
        }
    ],
    "sg:phone":"+1 819 874 0000",
    "sg:postcode":"J9P 7A9",
    "sg:province":"QC",
    "sg:tags":[
        "cleaners",
        "vacuum"
    ],
    "wof:name":"Hopital DE LA Machine A Coudre",
    "wof:placetype":"venue"
},
  "geometry": {"coordinates":[-68.42929077150001,53.89012146],"type":"Point"}
}