{
  "type": "Feature",
  "properties": {
    "iso:country":"CA",
    "sg:address":"1905 Avenue Rd",
    "sg:city":"North York",
    "sg:classifiers":[
        {
            "category":"Utilities",
            "subcategory":"Mobile Phone",
            "type":"Services"
        }
    ],
    "sg:phone":"+1 416 784 9400",
    "sg:postcode":"M5M 3Z9",
    "sg:province":"ON",
    "sg:tags":[
        "telephone",
        "cellular"
    ],
    "wof:name":"Lifestyle Communications Inc",
    "wof:placetype":"venue"
},
  "geometry": {"coordinates":[-79.41255187989999,43.7679138184],"type":"Point"}
}