{
  "type": "Feature",
  "properties": {
    "addr:full":"1623 Pandosy St Kelowna BC V1Y 1P6",
    "addr:housenumber":"1623",
    "addr:postcode":"v1y 1p6",
    "addr:street":"Pandosy St",
    "iso:country":"CA",
    "sg:address":"1623 Pandosy St",
    "sg:city":"Kelowna",
    "sg:classifiers":[
        {
            "category":"Home & Garden",
            "subcategory":"Furniture",
            "type":"Retail Goods"
        }
    ],
    "sg:phone":"+1 250 979 1250",
    "sg:postcode":"V1Y 1P6",
    "sg:province":"BC",
    "wof:name":"Oz By Cole",
    "wof:placetype":"venue"
},
  "geometry": {"coordinates":[-119.494865417,49.8849983215],"type":"Point"}
}