{
  "type": "Feature",
  "properties": {
    "addr:full":"670 Industrial Rd Cambridge ON N3H 4V9",
    "addr:housenumber":"670",
    "addr:postcode":"n3h 4v9",
    "addr:street":"Industrial Rd",
    "iso:country":"CA",
    "sg:address":"670 Industrial Rd",
    "sg:city":"Cambridge",
    "sg:classifiers":[
        {
            "category":"Retail",
            "subcategory":"Auto Repair",
            "type":"Services"
        }
    ],
    "sg:phone":"+1 519 653 1900",
    "sg:postcode":"N3H 4V9",
    "sg:province":"ON",
    "sg:tags":[
        "truck"
    ],
    "wof:name":"Eagle Truck & Trailer Parts",
    "wof:placetype":"venue"
},
  "geometry": {"coordinates":[-80.332954,43.405502],"type":"Point"}
}