{
  "type": "Feature",
  "properties": {
    "iso:country":"CA",
    "sg:address":"486 Grantham Ave",
    "sg:city":"St Catharines",
    "sg:classifiers":[
        {
            "category":"Shopping",
            "subcategory":"Discount & Variety Stores",
            "type":"Retail Goods"
        }
    ],
    "sg:phone":"+1 905 935 1211",
    "sg:postcode":"L2M 3J7",
    "sg:province":"ON",
    "wof:name":"Linwell Variety Store",
    "wof:placetype":"venue"
},
  "geometry": {"coordinates":[-79.221214,43.199844],"type":"Point"}
}