{
  "type": "Feature",
  "properties": {
    "addr:full":"81 Harcourt Ave Toronto ON M4J 1J3",
    "addr:housenumber":"81",
    "addr:postcode":"m4j 1j3",
    "addr:street":"Harcourt Ave",
    "iso:country":"CA",
    "sg:address":"81 Harcourt Ave",
    "sg:city":"Toronto",
    "sg:classifiers":[
        {
            "category":"Organizations",
            "subcategory":"Religious Organization",
            "type":"Services"
        }
    ],
    "sg:phone":"+1 416 461 7902",
    "sg:postcode":"M4J 1J3",
    "sg:province":"ON",
    "sg:tags":[
        "church"
    ],
    "wof:name":"Bethlehem Lutheran Church",
    "wof:placetype":"venue"
},
  "geometry": {"coordinates":[-79.3427276611,43.6775054932],"type":"Point"}
}