{
  "type": "Feature",
  "properties": {
    "addr:full":"Toronto ON M5J 1C4",
    "addr:postcode":"m5j 1c4",
    "iso:country":"CA",
    "sg:city":"Toronto",
    "sg:classifiers":[
        {
            "category":"Social Services",
            "subcategory":"Child Care",
            "type":"Services"
        }
    ],
    "sg:phone":"+1 416 367 1758",
    "sg:postcode":"M5J 1C4",
    "sg:province":"ON",
    "wof:name":"Bce Place Child Care Ctr",
    "wof:placetype":"venue"
},
  "geometry": {"coordinates":[-79.37764,43.646614],"type":"Point"}
}