{
  "type": "Feature",
  "properties": {
    "addr:full":"511 Granville St Summerside PE C1N 5J4",
    "addr:housenumber":"511",
    "addr:postcode":"c1n 5j4",
    "addr:street":"Granville St",
    "iso:country":"CA",
    "sg:address":"511 Granville St",
    "sg:city":"Summerside",
    "sg:classifiers":[
        {
            "category":"Restaurant",
            "type":"Food & Drink"
        }
    ],
    "sg:phone":"+1 902 436 4181",
    "sg:postcode":"C1N 5J4",
    "sg:province":"PE",
    "wof:name":"Mc Donald's",
    "wof:placetype":"venue"
},
  "geometry": {"coordinates":[-63.780166626,46.4171676636],"type":"Point"}
}