{
  "type": "Feature",
  "properties": {
    "addr:full":"1136 Clapp Lane Manotick ON K4M 1A3",
    "addr:housenumber":"1136",
    "addr:postcode":"k4m 1a3",
    "addr:street":"Clapp Lane",
    "iso:country":"CA",
    "sg:address":"1136 Clapp Lane",
    "sg:city":"Manotick",
    "sg:classifiers":[
        {
            "category":"Professional",
            "subcategory":"Accounting & Tax Preparation",
            "type":"Services"
        }
    ],
    "sg:phone":"+1 613 692 2553",
    "sg:postcode":"K4M 1A3",
    "sg:province":"ON",
    "sg:tags":[
        "accountant"
    ],
    "wof:name":"Collins Barrow",
    "wof:placetype":"venue"
},
  "geometry": {"coordinates":[-75.684181,45.226681],"type":"Point"}
}