{
  "type": "Feature",
  "properties": {
    "addr:full":"2704 Stones Bay Rd Fort St James BC V0J 1P0",
    "addr:housenumber":"2704",
    "addr:postcode":"v0j 1p0",
    "addr:street":"Stones Bay Rd",
    "iso:country":"CA",
    "sg:address":"2704 Stones Bay Rd",
    "sg:city":"Fort St James",
    "sg:classifiers":[
        {
            "category":"Sports & Exercise",
            "subcategory":"Golf",
            "type":"Entertainment"
        }
    ],
    "sg:phone":"+1 250 996 8736",
    "sg:postcode":"V0J 1P0",
    "sg:province":"BC",
    "sg:tags":[
        "course"
    ],
    "wof:name":"Stuart Lake Golf Club",
    "wof:placetype":"venue"
},
  "geometry": {"coordinates":[-124.294120789,54.4579734802],"type":"Point"}
}