{
  "type": "Feature",
  "properties": {
    "addr:full":"1576 Grist Mill Rd Eganville ON K0J 1T0",
    "addr:housenumber":"1576",
    "addr:postcode":"k0j 1t0",
    "addr:street":"Grist Mill Rd",
    "iso:country":"CA",
    "sg:address":"1576 Grist Mill Rd",
    "sg:city":"Eganville",
    "sg:classifiers":[
        {
            "category":"Building & Trades",
            "subcategory":"Plumbing",
            "type":"Services"
        }
    ],
    "sg:phone":"+1 613 628 2929",
    "sg:postcode":"K0J 1T0",
    "sg:province":"ON",
    "sg:tags":[
        "contractor"
    ],
    "wof:name":"L Schauer & Son Plumbing",
    "wof:placetype":"venue"
},
  "geometry": {"coordinates":[-77.1009063721,45.5400772095],"type":"Point"}
}