{
  "type": "Feature",
  "properties": {
    "addr:full":"6 Louise St Truro NS B2N 3K2",
    "addr:housenumber":"6",
    "addr:postcode":"b2n 3k2",
    "addr:street":"Louise St",
    "iso:country":"CA",
    "sg:address":"6 Louise St",
    "sg:city":"Truro",
    "sg:classifiers":[
        {
            "category":"Manufacturing",
            "subcategory":"Printing",
            "type":"Manufacturing & Wholesale Goods"
        }
    ],
    "sg:phone":"+1 902 895 4404",
    "sg:postcode":"B2N 3K2",
    "sg:province":"NS",
    "sg:tags":[
        "newspaper"
    ],
    "wof:name":"Truro Daily News",
    "wof:placetype":"venue"
},
  "geometry": {"coordinates":[-63.2825126648,45.3663063049],"type":"Point"}
}