{
  "type": "Feature",
  "properties": {
    "addr:full":"10102 King George Hwy Surrey BC V3T 2W4",
    "addr:housenumber":"10102",
    "addr:postcode":"v3t 2w4",
    "addr:street":"King George Hwy",
    "iso:country":"CA",
    "sg:address":"10102 King George Hwy",
    "sg:city":"Surrey",
    "sg:classifiers":[
        {
            "category":"Food & Beverages",
            "subcategory":"Bakery",
            "type":"Retail Goods"
        }
    ],
    "sg:phone":"+1 604 588 8141",
    "sg:postcode":"V3T 2W4",
    "sg:province":"BC",
    "sg:tags":[
        "baker"
    ],
    "wof:name":"San Fresgo Baker",
    "wof:placetype":"venue"
},
  "geometry": {"coordinates":[-122.845146,49.186123],"type":"Point"}
}