{
  "type": "Feature",
  "properties": {
    "iso:country":"CA",
    "sg:address":"324 Prince Edward Dr # 201",
    "sg:city":"Etobicoke",
    "sg:classifiers":[
        {
            "category":"Health Services",
            "subcategory":"Doctor",
            "type":"Services"
        }
    ],
    "sg:phone":"+1 416 233 9581",
    "sg:postcode":"M8Y 3Z5",
    "sg:province":"ON",
    "sg:tags":[
        "dentist"
    ],
    "wof:name":"May, Joel DDS",
    "wof:placetype":"venue"
},
  "geometry": {"coordinates":[-79.50592803959999,43.6493721008],"type":"Point"}
}