{
  "type": "Feature",
  "properties": {
    "addr:full":"1249 Chebogue Rd Yarmouth NS B5A 4A6",
    "addr:housenumber":"1249",
    "addr:postcode":"b5a 4a6",
    "addr:street":"Chebogue Rd",
    "iso:country":"CA",
    "sg:address":"1249 Chebogue Rd",
    "sg:city":"Yarmouth",
    "sg:classifiers":[
        {
            "category":"Taxi",
            "type":"Transportation"
        }
    ],
    "sg:phone":"+1 902 742 2323",
    "sg:postcode":"B5A 4A6",
    "sg:province":"NS",
    "sg:tags":[
        "taxicab"
    ],
    "wof:name":"Tri County Cab",
    "wof:placetype":"venue"
},
  "geometry": {"coordinates":[-66.1215515137,43.8174095154],"type":"Point"}
}