{
  "type": "Feature",
  "properties": {
    "addr:full":"Markham ON L3R 3W4",
    "addr:postcode":"l3r 3w4",
    "iso:country":"CA",
    "sg:city":"Markham",
    "sg:classifiers":[
        {
            "category":"Wholesale",
            "subcategory":"Fruits & Vegetables",
            "type":"Manufacturing & Wholesale Goods"
        }
    ],
    "sg:phone":"+1 905 944 9888",
    "sg:postcode":"L3R 3W4",
    "sg:province":"ON",
    "wof:name":"Golden Produce",
    "wof:placetype":"venue"
},
  "geometry": {"coordinates":[-79.34497833250001,43.8170623779],"type":"Point"}
}