{
  "type": "Feature",
  "properties": {
    "addr:full":"Woodbridge ON L4L 8K8",
    "addr:postcode":"l4l 8k8",
    "iso:country":"CA",
    "sg:city":"Woodbridge",
    "sg:classifiers":[
        {
            "category":"Banks & Credit Unions",
            "subcategory":"Bank",
            "type":"Services"
        }
    ],
    "sg:phone":"+1 905 850 5700",
    "sg:postcode":"L4L 8K8",
    "sg:province":"ON",
    "wof:name":"Cibc",
    "wof:placetype":"venue"
},
  "geometry": {"coordinates":[-79.5414886475,43.7714881897],"type":"Point"}
}