{
  "type": "Feature",
  "properties": {
    "addr:full":"6075 Inverness St Vancouver BC V5W 3P8",
    "addr:housenumber":"6075",
    "addr:postcode":"v5w 3p8",
    "addr:street":"Inverness St",
    "iso:country":"CA",
    "sg:address":"6075 Inverness St",
    "sg:city":"Vancouver",
    "sg:classifiers":[
        {
            "category":"Organizations",
            "subcategory":"Religious Organization",
            "type":"Services"
        }
    ],
    "sg:phone":"+1 604 327 4545",
    "sg:postcode":"V5W 3P8",
    "sg:province":"BC",
    "sg:tags":[
        "church"
    ],
    "wof:name":"Pilgrim Baptist Church",
    "wof:placetype":"venue"
},
  "geometry": {"coordinates":[-123.080085754,49.2294654846],"type":"Point"}
}