{
  "type": "Feature",
  "properties": {
    "addr:full":"325 Talbot Ave Winnipeg MB R2L 0P9",
    "addr:housenumber":"325",
    "addr:postcode":"r2l 0p9",
    "addr:street":"Talbot Ave",
    "iso:country":"CA",
    "sg:address":"325 Talbot Ave",
    "sg:city":"Winnipeg",
    "sg:classifiers":[
        {
            "category":"Organizations",
            "subcategory":"Religious Organization",
            "type":"Services"
        }
    ],
    "sg:phone":"+1 204 669 4205",
    "sg:postcode":"R2L 0P9",
    "sg:province":"MB",
    "wof:name":"Youth For Christ",
    "wof:placetype":"venue"
},
  "geometry": {"coordinates":[-97.110206604,49.9077033997],"type":"Point"}
}