{
  "type": "Feature",
  "properties": {
    "addr:full":"6015 Rue Louis-Hemon Montreal QC H2G 2K5",
    "addr:housenumber":"6015",
    "addr:postcode":"h2g 2k5",
    "addr:street":"Rue Louis-Hemon",
    "iso:country":"CA",
    "sg:address":"6015 Rue Louis-Hemon",
    "sg:city":"Montreal",
    "sg:classifiers":[
        {
            "category":"Shopping",
            "subcategory":"Clothing, Apparel, & Fashions",
            "type":"Retail Goods"
        }
    ],
    "sg:phone":"+1 514 728 6889",
    "sg:postcode":"H2G 2K5",
    "sg:province":"QC",
    "sg:tags":[
        "designer",
        "alteration"
    ],
    "wof:name":"Creation Confort Inc",
    "wof:placetype":"venue"
},
  "geometry": {"coordinates":[-73.5886688232,45.5449523926],"type":"Point"}
}