{
  "type": "Feature",
  "properties": {
    "addr:full":"75 Moorcrest Dr Aurora ON L4G 6C6",
    "addr:housenumber":"75",
    "addr:postcode":"l4g 6c6",
    "addr:street":"Moorcrest Dr",
    "iso:country":"CA",
    "sg:address":"75 Moorcrest Dr",
    "sg:city":"Aurora",
    "sg:classifiers":[
        {
            "category":"Wholesale",
            "subcategory":"Electrical",
            "type":"Manufacturing & Wholesale Goods"
        }
    ],
    "sg:phone":"+1 905 841 0347",
    "sg:postcode":"L4G 6C6",
    "sg:province":"ON",
    "sg:tags":[
        "communication",
        "radio",
        "system"
    ],
    "wof:name":"Communitronics Limited",
    "wof:placetype":"venue"
},
  "geometry": {"coordinates":[-79.466988,44.013493],"type":"Point"}
}