{
  "type": "Feature",
  "properties": {
    "addr:full":"PO Box 262 Seba Beach AB T0E 2B0",
    "addr:housenumber":"po",
    "addr:postcode":"t0e 2b0",
    "addr:street":"Box 262 Seba",
    "iso:country":"CA",
    "sg:address":"PO Box 262",
    "sg:city":"Seba Beach",
    "sg:classifiers":[
        {
            "category":"Building & Trades",
            "subcategory":"Electrical",
            "type":"Services"
        }
    ],
    "sg:phone":"+1 780 797 3822",
    "sg:postcode":"T0E 2B0",
    "sg:province":"AB",
    "sg:tags":[
        "electric",
        "contractor"
    ],
    "wof:name":"Bencar Electric CO Ltd",
    "wof:placetype":"venue"
},
  "geometry": {"coordinates":[-114.73866271999999,53.5593681335],"type":"Point"}
}