{
  "type": "Feature",
  "properties": {
    "iso:country":"CA",
    "sg:city":"Capreol",
    "sg:classifiers":[
        {
            "category":"Organizations",
            "subcategory":"Professional Association",
            "type":"Services"
        }
    ],
    "sg:phone":"+1 705 858 3554",
    "sg:postcode":"P0M 1H0",
    "sg:province":"ON",
    "wof:name":"Capreol Lions Club",
    "wof:placetype":"venue"
},
  "geometry": {"coordinates":[-80.9288406372,46.7148780823],"type":"Point"}
}