{
  "type": "Feature",
  "properties": {
    "addr:full":"71 James St Elora ON N0B 1S0",
    "addr:housenumber":"71",
    "addr:postcode":"n0b 1s0",
    "addr:street":"James St",
    "iso:country":"CA",
    "sg:address":"71 James St",
    "sg:city":"Elora",
    "sg:classifiers":[
        {
            "category":"Health Services",
            "subcategory":"Doctor",
            "type":"Services"
        }
    ],
    "sg:phone":"+1 519 846 5345",
    "sg:postcode":"N0B 1S0",
    "sg:province":"ON",
    "sg:tags":[
        "physician",
        "surgeon"
    ],
    "wof:name":"Elora Medical Group",
    "wof:placetype":"venue"
},
  "geometry": {"coordinates":[-80.431038,43.682602],"type":"Point"}
}