{
  "type": "Feature",
  "properties": {
    "addr:full":"3403 93 St NW Edmonton AB T6E 6A4",
    "addr:housenumber":"3403",
    "addr:postcode":"t6e 6a4",
    "addr:street":"93 St Nw",
    "iso:country":"CA",
    "sg:address":"3403 93 St NW",
    "sg:city":"Edmonton",
    "sg:classifiers":[
        {
            "category":"Autos & Motor Vehicles",
            "subcategory":"Automobile Sales",
            "type":"Retail Goods"
        }
    ],
    "sg:phone":"+1 780 450 4500",
    "sg:postcode":"T6E 6A4",
    "sg:province":"AB",
    "sg:tags":[
        "car",
        "dealer"
    ],
    "wof:name":"Millwoods Suzuki",
    "wof:placetype":"venue"
},
  "geometry": {"coordinates":[-113.47455600000001,53.466106],"type":"Point"}
}