{
  "type": "Feature",
  "properties": {
    "iso:country":"CA",
    "sg:address":"1652 102nd St",
    "sg:city":"North Battleford",
    "sg:classifiers":[
        {
            "category":"Social Services",
            "type":"Services"
        }
    ],
    "sg:phone":"+1 306 446 2808",
    "sg:postcode":"S9A 1H1",
    "sg:province":"SK",
    "sg:tags":[
        "organization",
        "welfare"
    ],
    "wof:name":"Teen-Aid",
    "wof:placetype":"venue"
},
  "geometry": {"coordinates":[-108.295883179,52.7819786072],"type":"Point"}
}