{
  "type": "Feature",
  "properties": {
    "addr:full":"10 Paisley St Guelph ON N1H 2N6",
    "addr:housenumber":"10",
    "addr:postcode":"n1h 2n6",
    "addr:street":"Paisley St",
    "iso:country":"CA",
    "sg:address":"10 Paisley St",
    "sg:city":"Guelph",
    "sg:classifiers":[
        {
            "category":"Restaurant",
            "type":"Food & Drink"
        }
    ],
    "sg:phone":"+1 519 837 0830",
    "sg:postcode":"N1H 2N6",
    "sg:province":"ON",
    "wof:name":"Cally's Restaurant",
    "wof:placetype":"venue"
},
  "geometry": {"coordinates":[-80.2528457642,43.5452003479],"type":"Point"}
}