{
  "type": "Feature",
  "properties": {
    "addr:full":"5728 1 St SW Calgary AB T2H 0E2",
    "addr:housenumber":"5728 1",
    "addr:postcode":"t2h 0e2",
    "addr:street":"St Sw",
    "iso:country":"CA",
    "sg:address":"5728 1 St SW",
    "sg:city":"Calgary",
    "sg:classifiers":[
        {
            "category":"Professional",
            "subcategory":"Business Services",
            "type":"Services"
        }
    ],
    "sg:phone":"+1 403 255 8191",
    "sg:postcode":"T2H 0E2",
    "sg:province":"AB",
    "sg:tags":[
        "water",
        "treatment"
    ],
    "wof:name":"Besco Industrial Products Ltd",
    "wof:placetype":"venue"
},
  "geometry": {"coordinates":[-114.06635300000001,51.002277],"type":"Point"}
}