{
  "type": "Feature",
  "properties": {
    "addr:full":"Lloydminster AB T9V 2E6",
    "addr:postcode":"t9v 2e6",
    "iso:country":"CA",
    "sg:city":"Lloydminster",
    "sg:classifiers":[
        {
            "category":"Wholesale",
            "subcategory":"Machinery & Supplies",
            "type":"Manufacturing & Wholesale Goods"
        }
    ],
    "sg:phone":"+1 780 875 5878",
    "sg:postcode":"T9V 2E6",
    "sg:province":"AB",
    "sg:tags":[
        "equipment",
        "industrial"
    ],
    "wof:name":"Acklands-Grainger",
    "wof:placetype":"venue"
},
  "geometry": {"coordinates":[-110.01277899999999,53.301804],"type":"Point"}
}