{
  "type": "Feature",
  "properties": {
    "addr:full":"200 Front St Hornepayne ON P0M 1Z0",
    "addr:housenumber":"200",
    "addr:postcode":"p0m 1z0",
    "addr:street":"Front St",
    "iso:country":"CA",
    "sg:address":"200 Front St",
    "sg:city":"Hornepayne",
    "sg:classifiers":[
        {
            "category":"Banks & Credit Unions",
            "subcategory":"Bank",
            "type":"Services"
        }
    ],
    "sg:phone":"+1 807 868 2544",
    "sg:postcode":"P0M 1Z0",
    "sg:province":"ON",
    "wof:name":"Cibc",
    "wof:placetype":"venue"
},
  "geometry": {"coordinates":[-84.775024,49.218201],"type":"Point"}
}