{
  "type": "Feature",
  "properties": {
    "iso:country":"CA",
    "sg:address":"146 Rue Manoir E",
    "sg:city":"Cap-Saint-Ignace",
    "sg:classifiers":[
        {
            "category":"Health Services",
            "subcategory":"Nursing And Care Facility",
            "type":"Services"
        }
    ],
    "sg:phone":"+1 418 246 5644",
    "sg:postcode":"G0R 1H0",
    "sg:province":"QC",
    "sg:tags":[
        "home",
        "rest"
    ],
    "wof:name":"Centre D'Accueil St-Ignace",
    "wof:placetype":"venue"
},
  "geometry": {"coordinates":[-70.4556808472,47.0401268005],"type":"Point"}
}