{
  "type": "Feature",
  "properties": {
    "addr:full":"RR 6 STN Main Perth ON K7H 3C8",
    "addr:postcode":"k7h 3c8",
    "addr:street":"Rr 6 Stn",
    "iso:country":"CA",
    "sg:address":"RR 6 STN Main",
    "sg:city":"Perth",
    "sg:classifiers":[
        {
            "category":"Real Estate",
            "subcategory":"Real Estate Operator",
            "type":"Services"
        }
    ],
    "sg:phone":"+1 613 267 4783",
    "sg:postcode":"K7H 3C8",
    "sg:province":"ON",
    "sg:tags":[
        "mobile",
        "home",
        "community"
    ],
    "wof:name":"Mississippi Hillview Inc",
    "wof:placetype":"venue"
},
  "geometry": {"coordinates":[-76.248329,44.898945],"type":"Point"}
}