{
  "type": "Feature",
  "properties": {
    "iso:country":"CA",
    "sg:address":"127 Langley Rd",
    "sg:city":"Salt Spring Island",
    "sg:classifiers":[
        {
            "category":"Personal",
            "subcategory":"Beauty Salon",
            "type":"Services"
        }
    ],
    "sg:phone":"+1 250 537 5002",
    "sg:postcode":"V8K 1K9",
    "sg:province":"BC",
    "wof:name":"Bevan's Salon",
    "wof:placetype":"venue"
},
  "geometry": {"coordinates":[-123.56963348399999,48.8800964355],"type":"Point"}
}