{
  "type": "Feature",
  "properties": {
    "iso:country":"CA",
    "sg:address":"110 Rue Georges",
    "sg:city":"Masson-Angers",
    "sg:classifiers":[
        {
            "category":"Shopping",
            "subcategory":"Shoes",
            "type":"Retail Goods"
        }
    ],
    "sg:phone":"+1 819 986 7015",
    "sg:postcode":"J8M 1A2",
    "sg:province":"QC",
    "wof:name":"J E Fashion",
    "wof:placetype":"venue"
},
  "geometry": {"coordinates":[-75.435585022,45.5542869568],"type":"Point"}
}