{
  "type": "Feature",
  "properties": {
    "addr:full":"2366 Rue Galvani # B Sainte-Foy QC G1N 4G4",
    "addr:housenumber":"2366;# b",
    "addr:postcode":"g1n 4g4",
    "addr:street":"Rue Galvani;Sainte-Foy",
    "iso:country":"CA",
    "sg:address":"2366 Rue Galvani # B",
    "sg:city":"Sainte-Foy",
    "sg:classifiers":[
        {
            "category":"Wholesale",
            "subcategory":"Durable Goods & Equipment",
            "type":"Manufacturing & Wholesale Goods"
        }
    ],
    "sg:phone":"+1 418 683 4066",
    "sg:postcode":"G1N 4G4",
    "sg:province":"QC",
    "sg:tags":[
        "laboratory",
        "instrument",
        "scientific",
        "apparatus",
        "supply"
    ],
    "wof:name":"Fisher Scientific Ltd",
    "wof:placetype":"venue"
},
  "geometry": {"coordinates":[-71.2883605957,46.7900657654],"type":"Point"}
}