{
  "type": "Feature",
  "properties": {
    "addr:full":"11559 Lang Crt Winfield BC V4V 1J9",
    "addr:housenumber":"11559",
    "addr:postcode":"v4v 1j9",
    "addr:street":"Lang Crt",
    "iso:country":"CA",
    "sg:address":"11559 Lang Crt",
    "sg:city":"Winfield",
    "sg:classifiers":[
        {
            "category":"Food & Beverages",
            "subcategory":"Meat & Fish",
            "type":"Retail Goods"
        }
    ],
    "sg:phone":"+1 250 766 0187",
    "sg:postcode":"V4V 1J9",
    "sg:province":"BC",
    "sg:tags":[
        "sausage"
    ],
    "wof:name":"Hank Penninga Quality Custom",
    "wof:placetype":"venue"
},
  "geometry": {"coordinates":[-119.405602,50.024536],"type":"Point"}
}