{
  "type": "Feature",
  "properties": {
    "addr:full":"6041 6th Conc N Amherstburg ON N9V 2Y9",
    "addr:housenumber":"6041",
    "addr:postcode":"n9v 2y9",
    "addr:street":"6Th Conc N",
    "iso:country":"CA",
    "sg:address":"6041 6th Conc N",
    "sg:city":"Amherstburg",
    "sg:classifiers":[
        {
            "category":"Professional",
            "subcategory":"Engineering",
            "type":"Services"
        }
    ],
    "sg:phone":"+1 519 726 6400",
    "sg:postcode":"N9V 2Y9",
    "sg:province":"ON",
    "sg:tags":[
        "engineer"
    ],
    "wof:name":"Fieldcraft Engineering Ltd",
    "wof:placetype":"venue"
},
  "geometry": {"coordinates":[-83.02151499999999,42.111866],"type":"Point"}
}