{
  "type": "Feature",
  "properties": {
    "addr:full":"682 109th St North Battleford SK S9A 2C4",
    "addr:housenumber":"682",
    "addr:postcode":"s9a 2c4",
    "addr:street":"109Th St",
    "iso:country":"CA",
    "sg:address":"682 109th St",
    "sg:city":"North Battleford",
    "sg:classifiers":[
        {
            "category":"Building & Trades",
            "subcategory":"Plumbing",
            "type":"Services"
        }
    ],
    "sg:phone":"+1 306 445 2341",
    "sg:postcode":"S9A 2C4",
    "sg:province":"SK",
    "sg:tags":[
        "contractor"
    ],
    "wof:name":"General Plumbing & Heating Ltd",
    "wof:placetype":"venue"
},
  "geometry": {"coordinates":[-108.285721,52.767006],"type":"Point"}
}