{
  "type": "Feature",
  "properties": {
    "iso:country":"CA",
    "sg:address":"5210 50 St",
    "sg:city":"Cold Lake",
    "sg:classifiers":[
        {
            "category":"Travel",
            "subcategory":"Travel Agent",
            "type":"Entertainment"
        }
    ],
    "sg:phone":"+1 780 594 5233",
    "sg:postcode":"T9M 1C9",
    "sg:province":"AB",
    "sg:tags":[
        "agency",
        "bureau"
    ],
    "wof:name":"Royal Travel",
    "wof:placetype":"venue"
},
  "geometry": {"coordinates":[-110.20588684099999,54.416229248],"type":"Point"}
}