{
  "type": "Feature",
  "properties": {
    "addr:full":"13 King St E Omemee ON K0L 2W0",
    "addr:housenumber":"13",
    "addr:postcode":"k0l 2w0",
    "addr:street":"King St E Omemee",
    "iso:country":"CA",
    "sg:address":"13 King St E",
    "sg:city":"Omemee",
    "sg:classifiers":[
        {
            "category":"Shopping",
            "subcategory":"Discount & Variety Stores",
            "type":"Retail Goods"
        }
    ],
    "sg:phone":"+1 705 799 6597",
    "sg:postcode":"K0L 2W0",
    "sg:province":"ON",
    "wof:name":"Mister Convenience",
    "wof:placetype":"venue"
},
  "geometry": {"coordinates":[-78.55896799999999,44.299229],"type":"Point"}
}