{
  "type": "Feature",
  "properties": {
    "addr:full":"2500 Boul DE LA Rive-Sud Saint-Romuald QC G6W 2R3",
    "addr:housenumber":"2500",
    "addr:postcode":"g6w 2r3",
    "addr:street":"Boul De La Rive-Sud",
    "iso:country":"CA",
    "sg:address":"2500 Boul DE LA Rive-Sud",
    "sg:city":"Saint-Romuald",
    "sg:classifiers":[
        {
            "category":"Taxi",
            "type":"Transportation"
        }
    ],
    "sg:phone":"+1 418 834 6666",
    "sg:postcode":"G6W 2R3",
    "sg:province":"QC",
    "sg:tags":[
        "taxicab"
    ],
    "wof:name":"Taxi Chaudiere Appalaches Inc",
    "wof:placetype":"venue"
},
  "geometry": {"coordinates":[-71.228874,46.758839],"type":"Point"}
}