{
  "type": "Feature",
  "properties": {
    "addr:full":"PO Box 159 Acadia Valley AB T0J 0A0",
    "addr:housenumber":"po",
    "addr:postcode":"t0j 0a0",
    "addr:street":"Box 159 Acadia Valley",
    "iso:country":"CA",
    "sg:address":"PO Box 159",
    "sg:city":"Acadia Valley",
    "sg:classifiers":[
        {
            "category":"Farming",
            "subcategory":"Farm & Veterinary Services",
            "type":"Manufacturing & Wholesale Goods"
        }
    ],
    "sg:phone":"+1 403 972 2024",
    "sg:postcode":"T0J 0A0",
    "sg:province":"AB",
    "sg:tags":[
        "seed",
        "grain",
        "cleaning"
    ],
    "wof:name":"Lemare Seed Cleaning",
    "wof:placetype":"venue"
},
  "geometry": {"coordinates":[-110.21421814,51.1582489014],"type":"Point"}
}