{
  "type": "Feature",
  "properties": {
    "addr:full":"415 Richmond St London ON N6A 3C8",
    "addr:housenumber":"415",
    "addr:postcode":"n6a 3c8",
    "addr:street":"Richmond St",
    "iso:country":"CA",
    "sg:address":"415 Richmond St",
    "sg:city":"London",
    "sg:classifiers":[
        {
            "category":"Real Estate",
            "subcategory":"Real Estate Agent",
            "type":"Services"
        }
    ],
    "sg:phone":"+1 519 432 9426",
    "sg:postcode":"N6A 3C8",
    "sg:province":"ON",
    "sg:tags":[
        "telephone",
        "cellular"
    ],
    "wof:name":"Cellular Centre",
    "wof:placetype":"venue"
},
  "geometry": {"coordinates":[-81.24994700000001,42.983852],"type":"Point"}
}