{
  "type": "Feature",
  "properties": {
    "addr:full":"RR 4 Waterford ON N0E 1Y0",
    "addr:postcode":"n0e 1y0",
    "addr:street":"Rr 4",
    "iso:country":"CA",
    "sg:address":"RR 4",
    "sg:city":"Waterford",
    "sg:classifiers":[
        {
            "category":"Organizations",
            "subcategory":"Religious Organization",
            "type":"Services"
        }
    ],
    "sg:phone":"+1 519 443 4954",
    "sg:postcode":"N0E 1Y0",
    "sg:province":"ON",
    "sg:tags":[
        "church"
    ],
    "wof:name":"Tyrrell Baptist Church",
    "wof:placetype":"venue"
},
  "geometry": {"coordinates":[-80.2886047363,42.925113678],"type":"Point"}
}