{
  "type": "Feature",
  "properties": {
    "iso:country":"CA",
    "sg:address":"2430 Rue Trudeau",
    "sg:city":"Quebec",
    "sg:classifiers":[
        {
            "category":"Building & Trades",
            "subcategory":"Construction",
            "type":"Services"
        }
    ],
    "sg:phone":"+1 418 681 8798",
    "sg:postcode":"G1P 3J8",
    "sg:province":"QC",
    "sg:tags":[
        "steam",
        "cleaning"
    ],
    "wof:name":"Nettoyage Fleur DE Lys Enr",
    "wof:placetype":"venue"
},
  "geometry": {"coordinates":[-71.303993,46.81181],"type":"Point"}
}