{
  "type": "Feature",
  "properties": {
    "addr:full":"2430 Rue Trudeau Quebec QC G1P 3J8",
    "addr:housenumber":"2430",
    "addr:postcode":"g1p 3j8",
    "addr:street":"Rue Trudeau",
    "iso:country":"CA",
    "sg:address":"2430 Rue Trudeau",
    "sg:city":"Quebec",
    "sg:classifiers":[
        {
            "category":"Building & Trades",
            "subcategory":"Construction",
            "type":"Services"
        }
    ],
    "sg:phone":"+1 418 681 8798",
    "sg:postcode":"G1P 3J8",
    "sg:province":"QC",
    "sg:tags":[
        "steam",
        "cleaning"
    ],
    "wof:name":"Nettoyage Fleur DE Lys Enr",
    "wof:placetype":"venue"
},
  "geometry": {"coordinates":[-71.30399300000001,46.81181],"type":"Point"}
}