{
  "type": "Feature",
  "properties": {
    "addr:full":"529 Consortium Crt London ON N6E 2S8",
    "addr:housenumber":"529",
    "addr:postcode":"n6e 2s8",
    "addr:street":"Consortium Crt",
    "iso:country":"CA",
    "sg:address":"529 Consortium Crt",
    "sg:city":"London",
    "sg:phone":"+1 519 680 1821",
    "sg:postcode":"N6E 2S8",
    "sg:province":"ON",
    "sg:tags":[
        "oil"
    ],
    "wof:name":"Petroline Petroleums",
    "wof:placetype":"venue"
},
  "geometry": {"coordinates":[-81.204041,42.933311],"type":"Point"}
}