{
  "type": "Feature",
  "properties": {
    "iso:country":"CA",
    "sg:address":"36 Rue Des Seigneurs",
    "sg:city":"Boucherville",
    "sg:classifiers":[
        {
            "category":"Organizations",
            "subcategory":"Religious Organization",
            "type":"Services"
        }
    ],
    "sg:phone":"+1 450 655 2340",
    "sg:postcode":"J4B 5Z8",
    "sg:province":"QC",
    "wof:name":"Soeurs DE LA Providence",
    "wof:placetype":"venue"
},
  "geometry": {"coordinates":[-73.455002,45.608055],"type":"Point"}
}