{
  "type": "Feature",
  "properties": {
    "addr:full":"7 Niagara St Brantford ON N3T 3X6",
    "addr:housenumber":"7",
    "addr:postcode":"n3t 3x6",
    "addr:street":"Niagara St",
    "iso:country":"CA",
    "sg:address":"7 Niagara St",
    "sg:city":"Brantford",
    "sg:classifiers":[
        {
            "category":"Professional",
            "subcategory":"Management & Consulting",
            "type":"Services"
        }
    ],
    "sg:phone":"+1 519 759 3507",
    "sg:postcode":"N3T 3X6",
    "sg:province":"ON",
    "sg:tags":[
        "general",
        "contractor"
    ],
    "wof:name":"R L Lancaster Construction Ltd",
    "wof:placetype":"venue"
},
  "geometry": {"coordinates":[-80.2722702026,43.148223877],"type":"Point"}
}