{
  "type": "Feature",
  "properties": {
    "addr:full":"346 Av Lariviere Rouyn-Noranda QC J9X 4H6",
    "addr:postcode":"j9x 4h6",
    "addr:street":"346 Av Lariviere",
    "iso:country":"CA",
    "sg:address":"346 Av Lariviere",
    "sg:city":"Rouyn-Noranda",
    "sg:classifiers":[
        {
            "category":"Home & Garden",
            "subcategory":"Household Appliances",
            "type":"Retail Goods"
        }
    ],
    "sg:phone":"+1 819 764 6985",
    "sg:postcode":"J9X 4H6",
    "sg:province":"QC",
    "sg:tags":[
        "cleaners",
        "vacuum"
    ],
    "wof:name":"Aspirateurs Du Nord Enr",
    "wof:placetype":"venue"
},
  "geometry": {"coordinates":[-79.0146942139,48.2332687378],"type":"Point"}
}