{
  "type": "Feature",
  "properties": {
    "addr:full":"905 Aut Dufferin-Montmorency Quebec QC G1R 5M6",
    "addr:housenumber":"905",
    "addr:postcode":"g1r 5m6",
    "iso:country":"CA",
    "sg:address":"905 Aut Dufferin-Montmorency",
    "sg:city":"Quebec",
    "sg:classifiers":[
        {
            "category":"Government",
            "subcategory":"Office",
            "type":"Public Place"
        }
    ],
    "sg:phone":"+1 418 648 4826",
    "sg:postcode":"G1R 5M6",
    "sg:province":"QC",
    "wof:name":"Canada Bureau Federal DE Dev",
    "wof:placetype":"venue"
},
  "geometry": {"coordinates":[-71.21729278559999,46.8265647888],"type":"Point"}
}