{
  "type": "Feature",
  "properties": {
    "addr:full":"217 Rue Saint-Joseph E Quebec QC G1K 3B1",
    "addr:housenumber":"217",
    "addr:postcode":"g1k 3b1",
    "addr:street":"Rue Saint-Joseph E",
    "iso:country":"CA",
    "sg:address":"217 Rue Saint-Joseph E",
    "sg:city":"Quebec",
    "sg:classifiers":[
        {
            "category":"Personal",
            "subcategory":"Tattoo Parlor",
            "type":"Services"
        }
    ],
    "sg:phone":"+1 418 522 0123",
    "sg:postcode":"G1K 3B1",
    "sg:province":"QC",
    "sg:tags":[
        "tattooing"
    ],
    "wof:name":"Doc Tattoo",
    "wof:placetype":"venue"
},
  "geometry": {"coordinates":[-71.227859,46.812958],"type":"Point"}
}