{
  "type": "Feature",
  "properties": {
    "addr:full":"374 Rue Principale Saint-Etienne-DE-Lauzon QC G6J 1E8",
    "addr:housenumber":"374",
    "addr:postcode":"g6j 1e8",
    "addr:street":"Rue Principale",
    "iso:country":"CA",
    "sg:address":"374 Rue Principale",
    "sg:city":"Saint-Etienne-DE-Lauzon",
    "sg:classifiers":[
        {
            "category":"Retail",
            "subcategory":"Animal Services",
            "type":"Services"
        }
    ],
    "sg:phone":"+1 418 831 2097",
    "sg:postcode":"G6J 1E8",
    "sg:province":"QC",
    "sg:tags":[
        "pet",
        "boarding",
        "sitting"
    ],
    "wof:name":"Pension St-Etienne",
    "wof:placetype":"venue"
},
  "geometry": {"coordinates":[-71.26551055909999,46.667552948],"type":"Point"}
}