{
  "type": "Feature",
  "properties": {
    "addr:full":"53 Fairwood Pl E Burlington ON L7T 2B7",
    "addr:housenumber":"53",
    "addr:postcode":"l7t 2b7",
    "addr:street":"Fairwood Pl E",
    "iso:country":"CA",
    "sg:address":"53 Fairwood Pl E",
    "sg:city":"Burlington",
    "sg:classifiers":[
        {
            "category":"Building & Trades",
            "subcategory":"Landscaping Services",
            "type":"Services"
        }
    ],
    "sg:phone":"+1 905 335 9999",
    "sg:postcode":"L7T 2B7",
    "sg:province":"ON",
    "sg:tags":[
        "landscape",
        "contractor"
    ],
    "wof:name":"Dutchman's Landscaping",
    "wof:placetype":"venue"
},
  "geometry": {"coordinates":[-79.8502731323,43.3069152832],"type":"Point"}
}