{
  "type": "Feature",
  "properties": {
    "addr:full":"Coquitlam BC V3K 6V7",
    "addr:postcode":"v3k 6v7",
    "iso:country":"CA",
    "sg:city":"Coquitlam",
    "sg:classifiers":[
        {
            "category":"Shopping",
            "type":"Retail Goods"
        }
    ],
    "sg:phone":"+1 604 520 3414",
    "sg:postcode":"V3K 6V7",
    "sg:province":"BC",
    "sg:tags":[
        "orthopedic",
        "appliance"
    ],
    "wof:name":"Ortho Active Appliances Ltd",
    "wof:placetype":"venue"
},
  "geometry": {"coordinates":[-122.852554321,49.238117218],"type":"Point"}
}