{
  "type": "Feature",
  "properties": {
    "addr:full":"805 Rue Saint-Louis Saint-Cyrille-DE-Wendover QC J1Z 1S2",
    "addr:housenumber":"805",
    "addr:postcode":"j1z 1s2",
    "addr:street":"Rue Saint-Louis",
    "iso:country":"CA",
    "sg:address":"805 Rue Saint-Louis",
    "sg:city":"Saint-Cyrille-DE-Wendover",
    "sg:classifiers":[
        {
            "category":"Freight",
            "type":"Transportation"
        }
    ],
    "sg:phone":"+1 819 397 2333",
    "sg:postcode":"J1Z 1S2",
    "sg:province":"QC",
    "sg:tags":[
        "building",
        "house",
        "mover"
    ],
    "wof:name":"Hilaire Gagne Inc",
    "wof:placetype":"venue"
},
  "geometry": {"coordinates":[-72.4358215332,45.9388694763],"type":"Point"}
}