{
  "type": "Feature",
  "properties": {
    "addr:full":"398 Rue DE LA Riviere Cowansville QC J2K 1N3",
    "addr:housenumber":"398",
    "addr:postcode":"j2k 1n3",
    "addr:street":"Rue De La Riviere",
    "iso:country":"CA",
    "sg:address":"398 Rue DE LA Riviere",
    "sg:city":"Cowansville",
    "sg:classifiers":[
        {
            "category":"Home & Garden",
            "subcategory":"Building Materials",
            "type":"Retail Goods"
        }
    ],
    "sg:phone":"+1 450 263 6803",
    "sg:postcode":"J2K 1N3",
    "sg:province":"QC",
    "sg:tags":[
        "glass",
        "window",
        "plate"
    ],
    "wof:name":"Docteur Du Pare-Brise",
    "wof:placetype":"venue"
},
  "geometry": {"coordinates":[-72.7639846802,45.2089195251],"type":"Point"}
}