{
  "type": "Feature",
  "properties": {
    "addr:full":"Surrey BC V3W 4Z3",
    "addr:postcode":"v3w 4z3",
    "iso:country":"CA",
    "sg:city":"Surrey",
    "sg:classifiers":[
        {
            "category":"Building & Trades",
            "subcategory":"Construction",
            "type":"Services"
        }
    ],
    "sg:phone":"+1 604 590 3183",
    "sg:postcode":"V3W 4Z3",
    "sg:province":"BC",
    "sg:tags":[
        "tile",
        "resurfacing",
        "laying",
        "refinishing",
        "floor"
    ],
    "wof:name":"Tile Town Ltd",
    "wof:placetype":"venue"
},
  "geometry": {"coordinates":[-122.845344544,49.120475769],"type":"Point"}
}