{
  "type": "Feature",
  "properties": {
    "addr:full":"297 Idema Rd #1 Markham ON L3R 1B1",
    "addr:housenumber":"297",
    "addr:postcode":"l3r 1b1",
    "addr:street":"Idema Rd # 1",
    "iso:country":"CA",
    "sg:address":"297 Idema Rd #1",
    "sg:city":"Markham",
    "sg:classifiers":[
        {
            "category":"Wholesale",
            "subcategory":"Drugs",
            "type":"Manufacturing & Wholesale Goods"
        }
    ],
    "sg:phone":"+1 905 948 8044",
    "sg:postcode":"L3R 1B1",
    "sg:province":"ON",
    "sg:tags":[
        "cosmetic"
    ],
    "wof:name":"Farleyco Marketing Inc",
    "wof:placetype":"venue"
},
  "geometry": {"coordinates":[-79.35559082029999,43.8174476624],"type":"Point"}
}