{
  "type": "Feature",
  "properties": {
    "iso:country":"CA",
    "sg:city":"Montreal",
    "sg:classifiers":[
        {
            "category":"Shopping",
            "subcategory":"Jewelry",
            "type":"Retail Goods"
        }
    ],
    "sg:phone":"+1 514 733 6233",
    "sg:postcode":"H3S 2B4",
    "sg:province":"QC",
    "sg:tags":[
        "jeweler"
    ],
    "wof:name":"Bijouterie Kathy",
    "wof:placetype":"venue"
},
  "geometry": {"coordinates":[-73.636185,45.502823],"type":"Point"}
}