{
  "type": "Feature",
  "properties": {
    "addr:full":"825 Foster Ave Windsor ON N8X 4W3",
    "addr:housenumber":"825",
    "addr:postcode":"n8x 4w3",
    "addr:street":"Foster Ave",
    "iso:country":"CA",
    "sg:address":"825 Foster Ave",
    "sg:city":"Windsor",
    "sg:classifiers":[
        {
            "category":"Building & Trades",
            "subcategory":"Electrical",
            "type":"Services"
        }
    ],
    "sg:phone":"+1 519 969 5270",
    "sg:postcode":"N8X 4W3",
    "sg:province":"ON",
    "sg:tags":[
        "electric",
        "contractor"
    ],
    "wof:name":"Rorison Industrial Elec Ltd",
    "wof:placetype":"venue"
},
  "geometry": {"coordinates":[-82.99430084230001,42.2702293396],"type":"Point"}
}