{
  "type": "Feature",
  "properties": {
    "iso:country":"CA",
    "sg:city":"Sudbury",
    "sg:classifiers":[
        {
            "category":"Professional",
            "subcategory":"Business Services",
            "type":"Services"
        }
    ],
    "sg:phone":"+1 705 523 8073",
    "sg:postcode":"P3E 6K4",
    "sg:province":"ON",
    "sg:tags":[
        "orthopedic",
        "appliance",
        "made"
    ],
    "wof:name":"Orthotic Centre",
    "wof:placetype":"venue"
},
  "geometry": {"coordinates":[-81.01001,46.462238],"type":"Point"}
}