{
  "type": "Feature",
  "properties": {
    "addr:full":"1048 Midland Ave Kingston ON K7P 2X9",
    "addr:housenumber":"1048",
    "addr:postcode":"k7p 2x9",
    "addr:street":"Midland Ave",
    "iso:country":"CA",
    "sg:address":"1048 Midland Ave",
    "sg:city":"Kingston",
    "sg:classifiers":[
        {
            "category":"Shopping",
            "subcategory":"Pharmacy",
            "type":"Retail Goods"
        }
    ],
    "sg:phone":"+1 613 389 4119",
    "sg:postcode":"K7P 2X9",
    "sg:province":"ON",
    "wof:name":"Drug Store Pharmacy",
    "wof:placetype":"venue"
},
  "geometry": {"coordinates":[-76.573944,44.261154],"type":"Point"}
}