{
  "type": "Feature",
  "properties": {
    "iso:country":"CA",
    "sg:address":"35 Valley Dr",
    "sg:city":"Wakefield",
    "sg:classifiers":[
        {
            "category":"Government",
            "subcategory":"Post Office",
            "type":"Public Place"
        }
    ],
    "sg:phone":"+1 819 459 2832",
    "sg:postcode":"J0X 3G0",
    "sg:province":"QC",
    "wof:name":"Post Office",
    "wof:placetype":"venue"
},
  "geometry": {"coordinates":[-75.9351425171,45.6271286011],"type":"Point"}
}