{
  "type": "Feature",
  "properties": {
    "addr:full":"35 Valley Dr Wakefield QC J0X 3G0",
    "addr:housenumber":"35",
    "addr:postcode":"j0x 3g0",
    "addr:street":"Valley Dr",
    "iso:country":"CA",
    "sg:address":"35 Valley Dr",
    "sg:city":"Wakefield",
    "sg:classifiers":[
        {
            "category":"Government",
            "subcategory":"Post Office",
            "type":"Public Place"
        }
    ],
    "sg:phone":"+1 819 459 2832",
    "sg:postcode":"J0X 3G0",
    "sg:province":"QC",
    "wof:name":"Post Office",
    "wof:placetype":"venue"
},
  "geometry": {"coordinates":[-75.9351425171,45.6271286011],"type":"Point"}
}