{
  "type": "Feature",
  "properties": {
    "addr:full":"1940 Rue Jolicoeur Montreal QC H4E 4M2",
    "addr:housenumber":"1940",
    "addr:postcode":"h4e 4m2",
    "addr:street":"Rue Jolicoeur",
    "iso:country":"CA",
    "sg:address":"1940 Rue Jolicoeur",
    "sg:city":"Montreal",
    "sg:classifiers":[
        {
            "category":"Health Services",
            "subcategory":"Nursing And Care Facility",
            "type":"Services"
        }
    ],
    "sg:phone":"+1 514 766 6653",
    "sg:postcode":"H4E 4M2",
    "sg:province":"QC",
    "sg:tags":[
        "home",
        "retirement",
        "community"
    ],
    "wof:name":"Holy Cross Comm Housing Corp",
    "wof:placetype":"venue"
},
  "geometry": {"coordinates":[-73.59120900000001,45.456928],"type":"Point"}
}