{
  "type": "Feature",
  "properties": {
    "iso:country":"CA",
    "sg:address":"5480 Rue Orchard",
    "sg:city":"Saint-Hubert",
    "sg:classifiers":[
        {
            "category":"Shopping",
            "subcategory":"Used Merchandise",
            "type":"Retail Goods"
        }
    ],
    "sg:phone":"+1 450 462 3180",
    "sg:postcode":"J3Y 2H1",
    "sg:province":"QC",
    "sg:tags":[
        "furniture"
    ],
    "wof:name":"Bazar Payer",
    "wof:placetype":"venue"
},
  "geometry": {"coordinates":[-73.4431152344,45.4754333496],"type":"Point"}
}