{
  "type": "Feature",
  "properties": {
    "iso:country":"CA",
    "sg:address":"4716 51 Ave",
    "sg:city":"Leduc",
    "sg:classifiers":[
        {
            "category":"Professional",
            "subcategory":"Accounting & Tax Preparation",
            "type":"Services"
        }
    ],
    "sg:phone":"+1 780 986 8383",
    "sg:postcode":"T9E 6Y8",
    "sg:province":"AB",
    "sg:tags":[
        "accountant"
    ],
    "wof:name":"Sofnowski, Wayne J M CA",
    "wof:placetype":"venue"
},
  "geometry": {"coordinates":[-113.548027039,53.2656402588],"type":"Point"}
}