{
  "type": "Feature",
  "properties": {
    "addr:full":"Main St Claresholm AB T0L 0T0",
    "addr:postcode":"t0l 0t0",
    "addr:street":"Main St",
    "iso:country":"CA",
    "sg:address":"Main St",
    "sg:city":"Claresholm",
    "sg:classifiers":[
        {
            "category":"Shopping",
            "subcategory":"Clothing, Apparel, & Fashions",
            "type":"Retail Goods"
        }
    ],
    "sg:phone":"+1 403 625 2777",
    "sg:postcode":"T0L 0T0",
    "sg:province":"AB",
    "sg:tags":[
        "riding",
        "western",
        "equipment"
    ],
    "wof:name":"Frontier Western Shop Ltd",
    "wof:placetype":"venue"
},
  "geometry": {"coordinates":[-113.581963,50.025795],"type":"Point"}
}