{
  "type": "Feature",
  "properties": {
    "addr:full":"14109 Boul Gouin O Pierrefonds QC H8Z 1Y2",
    "addr:housenumber":"14109",
    "addr:postcode":"h8z 1y2",
    "addr:street":"Boul Gouin O",
    "iso:country":"CA",
    "sg:address":"14109 Boul Gouin O",
    "sg:city":"Pierrefonds",
    "sg:classifiers":[
        {
            "category":"Bars & Pubs",
            "type":"Food & Drink"
        }
    ],
    "sg:phone":"+1 514 626 5529",
    "sg:postcode":"H8Z 1Y2",
    "sg:province":"QC",
    "sg:tags":[
        "lounge",
        "cocktail"
    ],
    "wof:name":"Bar Salon Chez Paul",
    "wof:placetype":"venue"
},
  "geometry": {"coordinates":[-73.85161600000001,45.495274],"type":"Point"}
}