{
  "type": "Feature",
  "properties": {
    "addr:full":"55 Glengrove Ave Hamilton ON L8H 1M9",
    "addr:housenumber":"55",
    "addr:postcode":"l8h 1m9",
    "addr:street":"Glengrove Ave",
    "iso:country":"CA",
    "sg:address":"55 Glengrove Ave",
    "sg:city":"Hamilton",
    "sg:classifiers":[
        {
            "category":"Wholesale",
            "subcategory":"Machinery & Supplies",
            "type":"Manufacturing & Wholesale Goods"
        }
    ],
    "sg:phone":"+1 905 549 4050",
    "sg:postcode":"L8H 1M9",
    "sg:province":"ON",
    "sg:tags":[
        "equipment",
        "clothing",
        "first",
        "safety",
        "aid"
    ],
    "wof:name":"Hamilton Industrial Safety",
    "wof:placetype":"venue"
},
  "geometry": {"coordinates":[-79.78359985349999,43.2378082275],"type":"Point"}
}