{
  "type": "Feature",
  "properties": {
    "addr:full":"Edmonton AB T5G 0Y5",
    "addr:postcode":"t5g 0y5",
    "iso:country":"CA",
    "sg:city":"Edmonton",
    "sg:classifiers":[
        {
            "category":"Organizations",
            "subcategory":"Labor Organization",
            "type":"Services"
        }
    ],
    "sg:phone":"+1 780 474 4747",
    "sg:postcode":"T5G 0Y5",
    "sg:province":"AB",
    "wof:name":"Edmonton & District Labour",
    "wof:placetype":"venue"
},
  "geometry": {"coordinates":[-113.502288818,53.5665817261],"type":"Point"}
}