{
  "type": "Feature",
  "properties": {
    "addr:full":"2168 Phillips Rd Sooke BC V0S 1N0",
    "addr:housenumber":"2168",
    "addr:postcode":"v0s 1n0",
    "addr:street":"Phillips Rd",
    "iso:country":"CA",
    "sg:address":"2168 Phillips Rd",
    "sg:city":"Sooke",
    "sg:classifiers":[
        {
            "category":"Government",
            "subcategory":"Office",
            "type":"Public Place"
        }
    ],
    "sg:phone":"+1 250 642 6311",
    "sg:postcode":"V0S 1N0",
    "sg:province":"BC",
    "sg:tags":[
        "village"
    ],
    "wof:name":"Sooke Electoral Area Parks",
    "wof:placetype":"venue"
},
  "geometry": {"coordinates":[-123.713013,48.402443],"type":"Point"}
}