{
  "type": "Feature",
  "properties": {
    "iso:country":"CA",
    "sg:address":"294 Rue Chabanel O",
    "sg:city":"Montreal",
    "sg:classifiers":[
        {
            "category":"Personal",
            "subcategory":"Beauty Salon",
            "type":"Services"
        }
    ],
    "sg:phone":"+1 514 387 5311",
    "sg:postcode":"H2N 1G5",
    "sg:province":"QC",
    "wof:name":"Extreme Coiffure Enr",
    "wof:placetype":"venue"
},
  "geometry": {"coordinates":[-73.65361,45.539894],"type":"Point"}
}