{
  "type": "Feature",
  "properties": {
    "iso:country":"CA",
    "sg:address":"203 Park St",
    "sg:city":"Orillia",
    "sg:classifiers":[
        {
            "category":"Food & Beverages",
            "subcategory":"Liquor & Beverages",
            "type":"Retail Goods"
        }
    ],
    "sg:phone":"+1 705 326 3225",
    "sg:postcode":"L3V 5V7",
    "sg:province":"ON",
    "sg:tags":[
        "beer",
        "ale"
    ],
    "wof:name":"Craw's Wine & Beer Supplies",
    "wof:placetype":"venue"
},
  "geometry": {"coordinates":[-79.432526,44.611622],"type":"Point"}
}