{
  "type": "Feature",
  "properties": {
    "iso:country":"CA",
    "sg:address":"168 Rothesay Ave",
    "sg:city":"Saint John",
    "sg:classifiers":[
        {
            "category":"Shopping",
            "subcategory":"Pharmacy",
            "type":"Retail Goods"
        }
    ],
    "sg:phone":"+1 506 648 1330",
    "sg:postcode":"E2J 2B5",
    "sg:province":"NB",
    "wof:name":"Drugstore Pharmacy",
    "wof:placetype":"venue"
},
  "geometry": {"coordinates":[-66.044052,45.289871],"type":"Point"}
}