{
  "type": "Feature",
  "properties": {
    "addr:full":"849 Laurel St Cambridge ON N3H 3Z6",
    "addr:housenumber":"849",
    "addr:postcode":"n3h 3z6",
    "addr:street":"Laurel St",
    "iso:country":"CA",
    "sg:address":"849 Laurel St",
    "sg:city":"Cambridge",
    "sg:classifiers":[
        {
            "category":"Personal",
            "type":"Services"
        }
    ],
    "sg:phone":"+1 519 653 2333",
    "sg:postcode":"N3H 3Z6",
    "sg:province":"ON",
    "sg:tags":[
        "control",
        "weight"
    ],
    "wof:name":"Slimmin Wimmin Ctr",
    "wof:placetype":"venue"
},
  "geometry": {"coordinates":[-80.353187561,43.3938865662],"type":"Point"}
}