{
  "type": "Feature",
  "properties": {
    "addr:full":"109 Av Sunnyside Westmount QC H3Y 1E3",
    "addr:postcode":"h3y 1e3",
    "addr:street":"109 Av Sunnyside",
    "iso:country":"CA",
    "sg:address":"109 Av Sunnyside",
    "sg:city":"Westmount",
    "sg:classifiers":[
        {
            "category":"Organizations",
            "subcategory":"Professional Association",
            "type":"Services"
        }
    ],
    "sg:phone":"+1 514 594 2284",
    "sg:postcode":"H3Y 1E3",
    "sg:province":"QC",
    "wof:name":"Chambre DE Commerce Canada",
    "wof:placetype":"venue"
},
  "geometry": {"coordinates":[-73.61539459230001,45.4859161377],"type":"Point"}
}