{
  "type": "Feature",
  "properties": {
    "addr:full":"300 Elgin St E St Marys ON N4X 1B9",
    "addr:housenumber":"300",
    "addr:postcode":"n4x 1b9",
    "addr:street":"Elgin St E",
    "iso:country":"CA",
    "sg:address":"300 Elgin St E",
    "sg:city":"St Marys",
    "sg:classifiers":[
        {
            "category":"Social Services",
            "type":"Services"
        }
    ],
    "sg:phone":"+1 519 284 1400",
    "sg:postcode":"N4X 1B9",
    "sg:province":"ON",
    "sg:tags":[
        "organization",
        "welfare"
    ],
    "wof:name":"James Purdue Ctr",
    "wof:placetype":"venue"
},
  "geometry": {"coordinates":[-81.1352157593,43.2579650879],"type":"Point"}
}