{
  "type": "Feature",
  "properties": {
    "addr:full":"3455 Fulton Ave Smithers BC V0J 2N0",
    "addr:housenumber":"3455",
    "addr:postcode":"v0j 2n0",
    "addr:street":"Fulton Ave",
    "iso:country":"CA",
    "sg:address":"3455 Fulton Ave",
    "sg:city":"Smithers",
    "sg:classifiers":[
        {
            "category":"Wholesale",
            "subcategory":"Electrical",
            "type":"Manufacturing & Wholesale Goods"
        }
    ],
    "sg:phone":"+1 250 847 8880",
    "sg:postcode":"V0J 2N0",
    "sg:province":"BC",
    "sg:tags":[
        "equipment",
        "electric",
        "supply"
    ],
    "wof:name":"Eecol Electric Ltd",
    "wof:placetype":"venue"
},
  "geometry": {"coordinates":[-127.157524,54.777573],"type":"Point"}
}