{
  "type": "Feature",
  "properties": {
    "addr:full":"474 Attwell Dr Etobicoke ON M9W 5C3",
    "addr:housenumber":"474",
    "addr:postcode":"m9w 5c3",
    "addr:street":"Attwell Dr",
    "iso:country":"CA",
    "sg:address":"474 Attwell Dr",
    "sg:city":"Etobicoke",
    "sg:classifiers":[
        {
            "category":"Wholesale",
            "subcategory":"Machinery & Supplies",
            "type":"Manufacturing & Wholesale Goods"
        }
    ],
    "sg:phone":"+1 416 480 0353",
    "sg:postcode":"M9W 5C3",
    "sg:province":"ON",
    "sg:tags":[
        "equipment",
        "industrial"
    ],
    "wof:name":"Etobicoke Tool & Mould Supplie",
    "wof:placetype":"venue"
},
  "geometry": {"coordinates":[-79.61004638670001,43.7037391663],"type":"Point"}
}