{
  "type": "Feature",
  "properties": {
    "addr:full":"2475 Tedlo St Mississauga ON L5A 4A8",
    "addr:housenumber":"2475",
    "addr:postcode":"l5a 4a8",
    "addr:street":"Tedlo St",
    "iso:country":"CA",
    "sg:address":"2475 Tedlo St",
    "sg:city":"Mississauga",
    "sg:classifiers":[
        {
            "category":"Wholesale",
            "subcategory":"Construction Materials",
            "type":"Manufacturing & Wholesale Goods"
        }
    ],
    "sg:phone":"+1 905 270 4438",
    "sg:postcode":"L5A 4A8",
    "sg:province":"ON",
    "sg:tags":[
        "fence"
    ],
    "wof:name":"Quest Plastics Ltd",
    "wof:placetype":"venue"
},
  "geometry": {"coordinates":[-79.59891500000001,43.588886],"type":"Point"}
}