{
  "type": "Feature",
  "properties": {
    "addr:full":"658 3E Av Lachine QC H8S 2T8",
    "addr:housenumber":"658",
    "addr:postcode":"h8s 2t8",
    "addr:street":"3E Av",
    "iso:country":"CA",
    "sg:address":"658 3E Av",
    "sg:city":"Lachine",
    "sg:classifiers":[
        {
            "category":"Social Services",
            "subcategory":"Child Care",
            "type":"Services"
        }
    ],
    "sg:phone":"+1 514 634 4600",
    "sg:postcode":"H8S 2T8",
    "sg:province":"QC",
    "wof:name":"Garderie Santa Casa",
    "wof:placetype":"venue"
},
  "geometry": {"coordinates":[-73.666534,45.441162],"type":"Point"}
}