{
  "type": "Feature",
  "properties": {
    "addr:full":"Conception Bay South NL A1X 6L1",
    "addr:postcode":"a1x 6l1",
    "iso:country":"CA",
    "sg:city":"Conception Bay South",
    "sg:phone":"+1 709 744 3026",
    "sg:postcode":"A1X 6L1",
    "sg:province":"NL",
    "sg:tags":[
        "equipment",
        "station"
    ],
    "wof:name":"Scotts Maintenance Ltd",
    "wof:placetype":"venue"
},
  "geometry": {"coordinates":[-52.968876,47.512619],"type":"Point"}
}