{
  "type": "Feature",
  "properties": {
    "addr:full":"7180 Airport Rd Mississauga ON L4T 2H2",
    "addr:housenumber":"7180",
    "addr:postcode":"l4t 2h2",
    "addr:street":"Airport Rd",
    "iso:country":"CA",
    "sg:address":"7180 Airport Rd",
    "sg:city":"Mississauga",
    "sg:classifiers":[
        {
            "category":"Food & Beverages",
            "subcategory":"Groceries & Convenience Stores",
            "type":"Retail Goods"
        }
    ],
    "sg:phone":"+1 905 612 8884",
    "sg:postcode":"L4T 2H2",
    "sg:province":"ON",
    "sg:tags":[
        "grocer"
    ],
    "wof:name":"Golden Groceries Ltd",
    "wof:placetype":"venue"
},
  "geometry": {"coordinates":[-79.64748400000001,43.707279],"type":"Point"}
}