{
  "type": "Feature",
  "properties": {
    "addr:full":"11905 Rue Industrielle Sorel-Tracy QC J3P 5N3",
    "addr:housenumber":"11905",
    "addr:postcode":"j3p 5n3",
    "addr:street":"Rue Industrielle",
    "iso:country":"CA",
    "sg:address":"11905 Rue Industrielle",
    "sg:city":"Sorel-Tracy",
    "sg:classifiers":[
        {
            "category":"Utilities",
            "subcategory":"Fuel Oil & Lpg",
            "type":"Services"
        }
    ],
    "sg:phone":"+1 450 746 0999",
    "sg:postcode":"J3P 5N3",
    "sg:province":"QC",
    "wof:name":"Kildair Service Ltee",
    "wof:placetype":"venue"
},
  "geometry": {"coordinates":[-73.159034729,45.9996299744],"type":"Point"}
}