{
  "type": "Feature",
  "properties": {
    "addr:full":"Surrey BC V4A 4N3",
    "addr:postcode":"v4a 4n3",
    "iso:country":"CA",
    "sg:city":"Surrey",
    "sg:classifiers":[
        {
            "category":"Home & Garden",
            "subcategory":"Home Furnishings",
            "type":"Retail Goods"
        }
    ],
    "sg:phone":"+1 604 531 9152",
    "sg:postcode":"V4A 4N3",
    "sg:province":"BC",
    "sg:tags":[
        "kitchen",
        "accessory"
    ],
    "wof:name":"My Kitchen Window",
    "wof:placetype":"venue"
},
  "geometry": {"coordinates":[-122.80132293699999,49.0332221985],"type":"Point"}
}