{
  "type": "Feature",
  "properties": {
    "iso:country":"CA",
    "sg:address":"19 John St",
    "sg:city":"Auburn",
    "sg:classifiers":[
        {
            "category":"Organizations",
            "subcategory":"Religious Organization",
            "type":"Services"
        }
    ],
    "sg:phone":"+1 519 526 1131",
    "sg:postcode":"N0M 1E0",
    "sg:province":"ON",
    "sg:tags":[
        "church"
    ],
    "wof:name":"Huron Chapel Missionery Church",
    "wof:placetype":"venue"
},
  "geometry": {"coordinates":[-81.5372161865,43.7720794678],"type":"Point"}
}