{
  "type": "Feature",
  "properties": {
    "addr:full":"502 Lake Nipissing Nipissing ON P0H 1W0",
    "addr:housenumber":"502",
    "addr:postcode":"p0h 1w0",
    "addr:street":"Lake",
    "iso:country":"CA",
    "sg:address":"502 Lake Nipissing",
    "sg:city":"Nipissing",
    "sg:classifiers":[
        {
            "category":"Travel",
            "subcategory":"Hotels & Motels",
            "type":"Entertainment"
        }
    ],
    "sg:phone":"+1 705 724 3130",
    "sg:postcode":"P0H 1W0",
    "sg:province":"ON",
    "sg:tags":[
        "cottage",
        "marina",
        "cabin"
    ],
    "wof:name":"Martin's Marina",
    "wof:placetype":"venue"
},
  "geometry": {"coordinates":[-79.528435,46.117691],"type":"Point"}
}