{
  "type": "Feature",
  "properties": {
    "addr:full":"9520 120 St Surrey BC V3V 4C1",
    "addr:housenumber":"9520",
    "addr:postcode":"v3v 4c1",
    "addr:street":"120 St",
    "iso:country":"CA",
    "sg:address":"9520 120 St",
    "sg:city":"Surrey",
    "sg:classifiers":[
        {
            "category":"Food & Beverages",
            "subcategory":"Specialty",
            "type":"Retail Goods"
        }
    ],
    "sg:phone":"+1 604 583 3911",
    "sg:postcode":"V3V 4C1",
    "sg:province":"BC",
    "sg:tags":[
        "health",
        "diet"
    ],
    "wof:name":"Happy Nut House Natural Foods",
    "wof:placetype":"venue"
},
  "geometry": {"coordinates":[-122.890091,49.175629],"type":"Point"}
}