{
  "type": "Feature",
  "properties": {
    "addr:full":"1617 Newman Cres Dorval QC H9P 2R6",
    "addr:housenumber":"1617",
    "addr:postcode":"h9p 2r6",
    "addr:street":"Newman Cres",
    "iso:country":"CA",
    "sg:address":"1617 Newman Cres",
    "sg:city":"Dorval",
    "sg:classifiers":[
        {
            "category":"Retail",
            "subcategory":"Auto Repair",
            "type":"Services"
        }
    ],
    "sg:phone":"+1 514 636 1404",
    "sg:postcode":"H9P 2R6",
    "sg:province":"QC",
    "sg:tags":[
        "repairing",
        "automobile"
    ],
    "wof:name":"Newman Auto",
    "wof:placetype":"venue"
},
  "geometry": {"coordinates":[-73.78179900000001,45.465263],"type":"Point"}
}