{
  "type": "Feature",
  "properties": {
    "addr:full":"5741 Finch Ave E Scarborough ON M1B 2G5",
    "addr:housenumber":"5741",
    "addr:postcode":"m1b 2g5",
    "addr:street":"Finch Ave E",
    "iso:country":"CA",
    "sg:address":"5741 Finch Ave E",
    "sg:city":"Scarborough",
    "sg:classifiers":[
        {
            "category":"Personal",
            "subcategory":"Beauty Salon",
            "type":"Services"
        }
    ],
    "sg:phone":"+1 416 281 8000",
    "sg:postcode":"M1B 2G5",
    "sg:province":"ON",
    "wof:name":"Top Flex Beauty Salon",
    "wof:placetype":"venue"
},
  "geometry": {"coordinates":[-79.233467,43.814903],"type":"Point"}
}