{
  "type": "Feature",
  "properties": {
    "addr:full":"1502 Wolseley Ave Grenfell SK S0G 2B0",
    "addr:housenumber":"1502",
    "addr:postcode":"s0g 2b0",
    "addr:street":"Wolseley Ave",
    "iso:country":"CA",
    "sg:address":"1502 Wolseley Ave",
    "sg:city":"Grenfell",
    "sg:classifiers":[
        {
            "category":"Wholesale",
            "subcategory":"Petroleum",
            "type":"Manufacturing & Wholesale Goods"
        }
    ],
    "sg:phone":"+1 306 697 2202",
    "sg:postcode":"S0G 2B0",
    "sg:province":"SK",
    "sg:tags":[
        "oil"
    ],
    "wof:name":"Petro-Canada",
    "wof:placetype":"venue"
},
  "geometry": {"coordinates":[-102.922607422,50.4105834961],"type":"Point"}
}