{
  "type": "Feature",
  "properties": {
    "iso:country":"CA",
    "sg:address":"10020 29 Ave NW",
    "sg:city":"Edmonton",
    "sg:classifiers":[
        {
            "category":"Manufacturing",
            "subcategory":"Tools & Machinery",
            "type":"Manufacturing & Wholesale Goods"
        }
    ],
    "sg:phone":"+1 780 462 6520",
    "sg:postcode":"T6N 1A2",
    "sg:province":"AB",
    "sg:tags":[
        "machine",
        "shop"
    ],
    "wof:name":"Bsl Machine Ltd",
    "wof:placetype":"venue"
},
  "geometry": {"coordinates":[-113.486671448,53.4580345154],"type":"Point"}
}