{
  "type": "Feature",
  "properties": {
    "addr:full":"Mississauga ON L4W 2Z3",
    "addr:postcode":"l4w 2z3",
    "iso:country":"CA",
    "sg:city":"Mississauga",
    "sg:classifiers":[
        {
            "category":"Wholesale",
            "subcategory":"Machinery & Supplies",
            "type":"Manufacturing & Wholesale Goods"
        }
    ],
    "sg:phone":"+1 905 238 6401",
    "sg:postcode":"L4W 2Z3",
    "sg:province":"ON",
    "sg:tags":[
        "hoist"
    ],
    "wof:name":"Mizia Hoist Inc",
    "wof:placetype":"venue"
},
  "geometry": {"coordinates":[-79.6364364624,43.6279983521],"type":"Point"}
}