{
  "type": "Feature",
  "properties": {
    "iso:country":"CA",
    "sg:address":"7220 Rue Clark",
    "sg:city":"Montreal",
    "sg:classifiers":[
        {
            "category":"Manufacturing",
            "subcategory":"Furniture",
            "type":"Manufacturing & Wholesale Goods"
        }
    ],
    "sg:phone":"+1 514 272 5787",
    "sg:postcode":"H2R 2Y3",
    "sg:province":"QC",
    "sg:tags":[
        "shelving"
    ],
    "wof:name":"Hopkins Specialties Mfg CO Ltd",
    "wof:placetype":"venue"
},
  "geometry": {"coordinates":[-73.619431,45.534187],"type":"Point"}
}