{
  "type": "Feature",
  "properties": {
    "addr:full":"7220 Rue Clark Montreal QC H2R 2Y3",
    "addr:housenumber":"7220",
    "addr:postcode":"h2r 2y3",
    "addr:street":"Rue Clark",
    "iso:country":"CA",
    "sg:address":"7220 Rue Clark",
    "sg:city":"Montreal",
    "sg:classifiers":[
        {
            "category":"Manufacturing",
            "subcategory":"Furniture",
            "type":"Manufacturing & Wholesale Goods"
        }
    ],
    "sg:phone":"+1 514 272 5787",
    "sg:postcode":"H2R 2Y3",
    "sg:province":"QC",
    "sg:tags":[
        "shelving"
    ],
    "wof:name":"Hopkins Specialties Mfg CO Ltd",
    "wof:placetype":"venue"
},
  "geometry": {"coordinates":[-73.61943100000001,45.534187],"type":"Point"}
}