{
  "type": "Feature",
  "properties": {
    "addr:full":"10160 108 St Grande Prairie AB T8V 7B1",
    "addr:housenumber":"10160",
    "addr:postcode":"t8v 7b1",
    "addr:street":"108 St",
    "iso:country":"CA",
    "sg:address":"10160 108 St",
    "sg:city":"Grande Prairie",
    "sg:classifiers":[
        {
            "category":"Shopping",
            "subcategory":"Stationery & Office Supplies",
            "type":"Retail Goods"
        }
    ],
    "sg:phone":"+1 780 814 6020",
    "sg:postcode":"T8V 7B1",
    "sg:province":"AB",
    "wof:name":"Staples Business Depot",
    "wof:placetype":"venue"
},
  "geometry": {"coordinates":[-118.820602417,55.181186676],"type":"Point"}
}