{
  "type": "Feature",
  "properties": {
    "iso:country":"CA",
    "sg:city":"Southampton",
    "sg:classifiers":[
        {
            "category":"Home & Garden",
            "subcategory":"Household Appliances",
            "type":"Retail Goods"
        }
    ],
    "sg:phone":"+1 519 797 3905",
    "sg:postcode":"N0H 2L0",
    "sg:province":"ON",
    "wof:name":"Square Deal Neil's Tv & Appl",
    "wof:placetype":"venue"
},
  "geometry": {"coordinates":[-81.37567901609999,44.4855728149],"type":"Point"}
}