{
  "type": "Feature",
  "properties": {
    "addr:full":"2718 Station Rd River John NS B0K 1N0",
    "addr:housenumber":"2718",
    "addr:postcode":"b0k 1n0",
    "addr:street":"Station Rd",
    "iso:country":"CA",
    "sg:address":"2718 Station Rd",
    "sg:city":"River John",
    "sg:classifiers":[
        {
            "category":"Health Services",
            "subcategory":"Doctor",
            "type":"Services"
        }
    ],
    "sg:phone":"+1 902 351 3083",
    "sg:postcode":"B0K 1N0",
    "sg:province":"NS",
    "sg:tags":[
        "physician",
        "surgeon"
    ],
    "wof:name":"Bush, Rob MD",
    "wof:placetype":"venue"
},
  "geometry": {"coordinates":[-63.0590324402,45.7513961792],"type":"Point"}
}