{
  "type": "Feature",
  "properties": {
    "addr:full":"12400 Boul Industriel Pointe-Aux-Trembles QC H1B 5M5",
    "addr:housenumber":"12400",
    "addr:postcode":"h1b 5m5",
    "addr:street":"Boul Industriel",
    "iso:country":"CA",
    "sg:address":"12400 Boul Industriel",
    "sg:city":"Pointe-Aux-Trembles",
    "sg:classifiers":[
        {
            "category":"Manufacturing",
            "subcategory":"Metals",
            "type":"Manufacturing & Wholesale Goods"
        }
    ],
    "sg:phone":"+1 514 640 6936",
    "sg:postcode":"H1B 5M5",
    "sg:province":"QC",
    "sg:tags":[
        "steel"
    ],
    "wof:name":"Industrie Inox Pro Inc",
    "wof:placetype":"venue"
},
  "geometry": {"coordinates":[-73.517685,45.650227],"type":"Point"}
}