{
  "type": "Feature",
  "properties": {
    "addr:full":"Fonthill ON L0S 1E6",
    "addr:postcode":"l0s 1e6",
    "iso:country":"CA",
    "sg:city":"Fonthill",
    "sg:classifiers":[
        {
            "category":"Building & Trades",
            "subcategory":"Plumbing",
            "type":"Services"
        }
    ],
    "sg:phone":"+1 905 684 2719",
    "sg:postcode":"L0S 1E6",
    "sg:province":"ON",
    "sg:tags":[
        "heating",
        "contractor"
    ],
    "wof:name":"Mannell Heating Svc",
    "wof:placetype":"venue"
},
  "geometry": {"coordinates":[-79.28182200000001,43.044098],"type":"Point"}
}