{
  "type": "Feature",
  "properties": {
    "addr:full":"1st Ave Wollaston Lake SK S0J 3C0",
    "addr:postcode":"s0j 3c0",
    "addr:street":"1St Ave",
    "iso:country":"CA",
    "sg:address":"1st Ave",
    "sg:city":"Wollaston Lake",
    "sg:classifiers":[
        {
            "category":"Government",
            "subcategory":"Office",
            "type":"Public Place"
        }
    ],
    "sg:phone":"+1 306 633 5560",
    "sg:postcode":"S0J 3C0",
    "sg:province":"SK",
    "wof:name":"Saskatchewan Conservation Ofc",
    "wof:placetype":"venue"
},
  "geometry": {"coordinates":[-103.161781311,58.1029663086],"type":"Point"}
}