{
  "type": "Feature",
  "properties": {
    "addr:full":"13527 Hwy 4 Wentworth NS B0M 1Z0",
    "addr:housenumber":"13527",
    "addr:postcode":"b0m 1z0",
    "addr:street":"Hwy 4",
    "iso:country":"CA",
    "sg:address":"13527 Hwy 4",
    "sg:city":"Wentworth",
    "sg:classifiers":[
        {
            "category":"Personal",
            "subcategory":"Beauty Salon",
            "type":"Services"
        }
    ],
    "sg:phone":"+1 902 548 2084",
    "sg:postcode":"B0M 1Z0",
    "sg:province":"NS",
    "wof:name":"Country Style Hair Design",
    "wof:placetype":"venue"
},
  "geometry": {"coordinates":[-63.5497703552,45.6615638733],"type":"Point"}
}