{
  "type": "Feature",
  "properties": {
    "iso:country":"CA",
    "sg:address":"1455 Rue Michelin",
    "sg:city":"Laval",
    "sg:classifiers":[
        {
            "category":"Professional",
            "subcategory":"Engineering",
            "type":"Services"
        }
    ],
    "sg:phone":"+1 450 967 1515",
    "sg:postcode":"H7L 4S2",
    "sg:province":"QC",
    "sg:tags":[
        "technical",
        "expertise",
        "analysis",
        "engineer"
    ],
    "wof:name":"Pyrotech Bei Inc",
    "wof:placetype":"venue"
},
  "geometry": {"coordinates":[-73.745834,45.591125],"type":"Point"}
}