{
  "type": "Feature",
  "properties": {
    "addr:full":"Milton ON L9T 4H8",
    "addr:postcode":"l9t 4h8",
    "iso:country":"CA",
    "sg:city":"Milton",
    "sg:classifiers":[
        {
            "category":"Shopping",
            "type":"Retail Goods"
        }
    ],
    "sg:phone":"+1 905 876 0873",
    "sg:postcode":"L9T 4H8",
    "sg:province":"ON",
    "sg:tags":[
        "orthopedic",
        "appliance"
    ],
    "wof:name":"C Turner Medical Ltd",
    "wof:placetype":"venue"
},
  "geometry": {"coordinates":[-79.868752,43.526657],"type":"Point"}
}