{
  "type": "Feature",
  "properties": {
    "addr:full":"Saint-Hyacinthe QC J2S 6E9",
    "addr:postcode":"j2s 6e9",
    "iso:country":"CA",
    "sg:city":"Saint-Hyacinthe",
    "sg:classifiers":[
        {
            "category":"Professional",
            "subcategory":"Business Services",
            "type":"Services"
        }
    ],
    "sg:phone":"+1 450 774 0990",
    "sg:postcode":"J2S 6E9",
    "sg:province":"QC",
    "sg:tags":[
        "notary"
    ],
    "wof:name":"Deslandes, Francois",
    "wof:placetype":"venue"
},
  "geometry": {"coordinates":[-72.960114,45.623333],"type":"Point"}
}