{
  "type": "Feature",
  "properties": {
    "addr:full":"244 Wilkins St London ON N6C 5C6",
    "addr:housenumber":"244",
    "addr:postcode":"n6c 5c6",
    "addr:street":"Wilkins St",
    "iso:country":"CA",
    "sg:address":"244 Wilkins St",
    "sg:city":"London",
    "sg:classifiers":[
        {
            "category":"Health Services",
            "subcategory":"Health Practitioner",
            "type":"Services"
        }
    ],
    "sg:phone":"+1 519 649 6617",
    "sg:postcode":"N6C 5C6",
    "sg:province":"ON",
    "sg:tags":[
        "acupuncture",
        "shiatsu",
        "therapy"
    ],
    "wof:name":"Shiatsu Healing Ctr",
    "wof:placetype":"venue"
},
  "geometry": {"coordinates":[-81.236794,42.948635],"type":"Point"}
}