{
  "type": "Feature",
  "properties": {
    "addr:full":"221 Southshore Rd Pointe-Au-Baril-Station ON P0G 1K0",
    "addr:housenumber":"221",
    "addr:postcode":"p0g 1k0",
    "addr:street":"Southshore Rd",
    "iso:country":"CA",
    "sg:address":"221 Southshore Rd",
    "sg:city":"Pointe-Au-Baril-Station",
    "sg:classifiers":[
        {
            "category":"Travel",
            "subcategory":"Hotels & Motels",
            "type":"Entertainment"
        }
    ],
    "sg:phone":"+1 705 366 2265",
    "sg:postcode":"P0G 1K0",
    "sg:province":"ON",
    "sg:tags":[
        "resort"
    ],
    "wof:name":"Leisure Bay Holiday Resort",
    "wof:placetype":"venue"
},
  "geometry": {"coordinates":[-80.377167,45.600288],"type":"Point"}
}