{
  "type": "Feature",
  "properties": {
    "addr:full":"26 Garden Ave Stoney Creek ON L8E 2Y9",
    "addr:housenumber":"26",
    "addr:postcode":"l8e 2y9",
    "addr:street":"Garden Ave",
    "iso:country":"CA",
    "sg:address":"26 Garden Ave",
    "sg:city":"Stoney Creek",
    "sg:classifiers":[
        {
            "category":"Wholesale",
            "subcategory":"Machinery & Supplies",
            "type":"Manufacturing & Wholesale Goods"
        }
    ],
    "sg:phone":"+1 905 664 9531",
    "sg:postcode":"L8E 2Y9",
    "sg:province":"ON",
    "sg:tags":[
        "tool"
    ],
    "wof:name":"Carbide Concepts Inc",
    "wof:placetype":"venue"
},
  "geometry": {"coordinates":[-79.734413147,43.2366333008],"type":"Point"}
}