{
  "type": "Feature",
  "properties": {
    "addr:full":"Farm Eston SK S0L 1A0",
    "addr:postcode":"s0l 1a0",
    "iso:country":"CA",
    "sg:address":"Farm",
    "sg:city":"Eston",
    "sg:classifiers":[
        {
            "category":"Farming",
            "subcategory":"Farm & Veterinary Services",
            "type":"Manufacturing & Wholesale Goods"
        }
    ],
    "sg:phone":"+1 306 962 3500",
    "sg:postcode":"S0L 1A0",
    "sg:province":"SK",
    "sg:tags":[
        "seed",
        "grain",
        "cleaning"
    ],
    "wof:name":"Jackson Seed Farm Shop",
    "wof:placetype":"venue"
},
  "geometry": {"coordinates":[-108.754707,51.153706],"type":"Point"}
}