{
  "type": "Feature",
  "properties": {
    "addr:full":"8755 170 St NW Edmonton AB T5R 5Y6",
    "addr:housenumber":"8755",
    "addr:postcode":"t5r 5y6",
    "addr:street":"170 St Nw",
    "iso:country":"CA",
    "sg:address":"8755 170 St NW",
    "sg:city":"Edmonton",
    "sg:classifiers":[
        {
            "category":"Education",
            "subcategory":"School",
            "type":"Public Place"
        }
    ],
    "sg:phone":"+1 780 930 5502",
    "sg:postcode":"T5R 5Y6",
    "sg:province":"AB",
    "wof:name":"Aurora School",
    "wof:placetype":"venue"
},
  "geometry": {"coordinates":[-113.61495208700001,53.522151947],"type":"Point"}
}