{
  "type": "Feature",
  "properties": {
    "addr:full":"Burlington ON L7R 3N2",
    "addr:postcode":"l7r 3n2",
    "iso:country":"CA",
    "sg:city":"Burlington",
    "sg:classifiers":[
        {
            "category":"Shopping",
            "subcategory":"Clothing, Apparel, & Fashions",
            "type":"Retail Goods"
        }
    ],
    "sg:phone":"+1 905 632 6633",
    "sg:postcode":"L7R 3N2",
    "sg:province":"ON",
    "wof:name":"Fairweather",
    "wof:placetype":"venue"
},
  "geometry": {"coordinates":[-79.796143,43.346584],"type":"Point"}
}