{
  "type": "Feature",
  "properties": {
    "addr:full":"1403 29 St NW #G33 Calgary AB T2N 2T9",
    "addr:housenumber":"1403",
    "addr:postcode":"t2n 2t9",
    "addr:street":"29 St Nw # G33",
    "iso:country":"CA",
    "sg:address":"1403 29 St NW #G33",
    "sg:city":"Calgary",
    "sg:classifiers":[
        {
            "category":"Health Services",
            "subcategory":"Doctor",
            "type":"Services"
        }
    ],
    "sg:phone":"+1 403 944 8258",
    "sg:postcode":"T2N 2T9",
    "sg:province":"AB",
    "sg:tags":[
        "physician",
        "surgeon"
    ],
    "wof:name":"Graham, Andrew J MD",
    "wof:placetype":"venue"
},
  "geometry": {"coordinates":[-114.130867004,51.0647583008],"type":"Point"}
}