{
  "type": "Feature",
  "properties": {
    "addr:full":"21 Charlotte St Port Colborne ON L3K 3C7",
    "addr:housenumber":"21",
    "addr:postcode":"l3k 3c7",
    "addr:street":"Charlotte St",
    "iso:country":"CA",
    "sg:address":"21 Charlotte St",
    "sg:city":"Port Colborne",
    "sg:classifiers":[
        {
            "category":"Insurance",
            "subcategory":"Insurance Agent",
            "type":"Services"
        }
    ],
    "sg:phone":"+1 905 834 4510",
    "sg:postcode":"L3K 3C7",
    "sg:province":"ON",
    "wof:name":"A G Richardson Insurance Brkrs",
    "wof:placetype":"venue"
},
  "geometry": {"coordinates":[-79.25056499999999,42.885307],"type":"Point"}
}