{
  "type": "Feature",
  "properties": {
    "addr:full":"11 Main St E Ashern MB R0C 0E0",
    "addr:housenumber":"11",
    "addr:postcode":"r0c 0e0",
    "addr:street":"Main St E Ashern",
    "iso:country":"CA",
    "sg:address":"11 Main St E",
    "sg:city":"Ashern",
    "sg:classifiers":[
        {
            "category":"Travel",
            "subcategory":"Travel Agent",
            "type":"Entertainment"
        }
    ],
    "sg:phone":"+1 204 768 2237",
    "sg:postcode":"R0C 0E0",
    "sg:province":"MB",
    "sg:tags":[
        "agency",
        "bureau"
    ],
    "wof:name":"Lake Shore Handivan Assn Ltd",
    "wof:placetype":"venue"
},
  "geometry": {"coordinates":[-98.350266,51.180805],"type":"Point"}
}