{
  "type": "Feature",
  "properties": {
    "iso:country":"CA",
    "sg:address":"233 Carlaw Ave",
    "sg:city":"Toronto",
    "sg:classifiers":[
        {
            "category":"Food & Beverages",
            "subcategory":"Meat & Fish",
            "type":"Retail Goods"
        }
    ],
    "sg:phone":"+1 416 463 5936",
    "sg:postcode":"M4M 3N6",
    "sg:province":"ON",
    "sg:tags":[
        "seafood"
    ],
    "wof:name":"So Wing Hing Trading Corp",
    "wof:placetype":"venue"
},
  "geometry": {"coordinates":[-79.3403625488,43.6621742249],"type":"Point"}
}