{
  "type": "Feature",
  "properties": {
    "addr:full":"122 Shediac Rd Moncton NB E1A 2R9",
    "addr:housenumber":"122",
    "addr:postcode":"e1a 2r9",
    "addr:street":"Shediac Rd",
    "iso:country":"CA",
    "sg:address":"122 Shediac Rd",
    "sg:city":"Moncton",
    "sg:classifiers":[
        {
            "category":"Manufacturing",
            "subcategory":"Food",
            "type":"Manufacturing & Wholesale Goods"
        }
    ],
    "sg:phone":"+1 506 858 1117",
    "sg:postcode":"E1A 2R9",
    "sg:province":"NB",
    "sg:tags":[
        "baker",
        "product",
        "manufacturer"
    ],
    "wof:name":"Mc Buns Bakery",
    "wof:placetype":"venue"
},
  "geometry": {"coordinates":[-64.76223,46.103588],"type":"Point"}
}