{
  "type": "Feature",
  "properties": {
    "addr:full":"4615 Boul Industriel Sherbrooke QC J1L 2W3",
    "addr:housenumber":"4615",
    "addr:postcode":"j1l 2w3",
    "addr:street":"Boul Industriel",
    "iso:country":"CA",
    "sg:address":"4615 Boul Industriel",
    "sg:city":"Sherbrooke",
    "sg:classifiers":[
        {
            "category":"Retail",
            "subcategory":"Auto Repair",
            "type":"Services"
        }
    ],
    "sg:phone":"+1 819 566 5806",
    "sg:postcode":"J1L 2W3",
    "sg:province":"QC",
    "sg:tags":[
        "body",
        "automobile",
        "painting"
    ],
    "wof:name":"Garage Mg Leclerc Enr",
    "wof:placetype":"venue"
},
  "geometry": {"coordinates":[-71.97924,45.395699],"type":"Point"}
}