{
  "type": "Feature",
  "properties": {
    "addr:full":"7826 Howard Rd Mcgregor ON N0R 1J0",
    "addr:housenumber":"7826",
    "addr:postcode":"n0r 1j0",
    "addr:street":"Howard Rd",
    "iso:country":"CA",
    "sg:address":"7826 Howard Rd",
    "sg:city":"Mcgregor",
    "sg:classifiers":[
        {
            "category":"Building & Trades",
            "subcategory":"Construction",
            "type":"Services"
        }
    ],
    "sg:phone":"+1 519 726 4774",
    "sg:postcode":"N0R 1J0",
    "sg:province":"ON",
    "sg:tags":[
        "paving",
        "stone",
        "interlocking",
        "contractor"
    ],
    "wof:name":"Lavin Interlock & Landscaping",
    "wof:placetype":"venue"
},
  "geometry": {"coordinates":[-83.0019683838,42.1626281738],"type":"Point"}
}