{
  "type": "Feature",
  "properties": {
    "addr:full":"569 Hwy 105 Vermilion Bay ON P0V 2V0",
    "addr:housenumber":"569",
    "addr:postcode":"p0v 2v0",
    "addr:street":"Hwy 105",
    "iso:country":"CA",
    "sg:address":"569 Hwy 105",
    "sg:city":"Vermilion Bay",
    "sg:classifiers":[
        {
            "category":"Freight",
            "type":"Transportation"
        }
    ],
    "sg:phone":"+1 807 227 2057",
    "sg:postcode":"P0V 2V0",
    "sg:province":"ON",
    "sg:tags":[
        "trucking"
    ],
    "wof:name":"Kindelane Enterprises Ltd",
    "wof:placetype":"venue"
},
  "geometry": {"coordinates":[-93.3837432861,49.8584823608],"type":"Point"}
}