{
  "type": "Feature",
  "properties": {
    "addr:full":"16 John St N Harriston ON N0G 1Z0",
    "addr:housenumber":"16",
    "addr:postcode":"n0g 1z0",
    "addr:street":"John St N",
    "iso:country":"CA",
    "sg:address":"16 John St N",
    "sg:city":"Harriston",
    "sg:classifiers":[
        {
            "category":"Health Services",
            "subcategory":"Doctor",
            "type":"Services"
        }
    ],
    "sg:phone":"+1 519 338 2922",
    "sg:postcode":"N0G 1Z0",
    "sg:province":"ON",
    "sg:tags":[
        "physician",
        "surgeon"
    ],
    "wof:name":"Lions Medical Centre",
    "wof:placetype":"venue"
},
  "geometry": {"coordinates":[-80.87359600000001,43.912285],"type":"Point"}
}