{
  "type": "Feature",
  "properties": {
    "addr:full":"238 Winderheights Pl Waterloo ON N2T 1P1",
    "addr:housenumber":"238",
    "addr:postcode":"n2t 1p1",
    "addr:street":"Winderheights Pl",
    "iso:country":"CA",
    "sg:address":"238 Winderheights Pl",
    "sg:city":"Waterloo",
    "sg:classifiers":[
        {
            "category":"Professional",
            "subcategory":"Research",
            "type":"Services"
        }
    ],
    "sg:phone":"+1 519 885 2520",
    "sg:postcode":"N2T 1P1",
    "sg:province":"ON",
    "sg:tags":[
        "environmental",
        "ecological"
    ],
    "wof:name":"Radiation Environmental Mgmt",
    "wof:placetype":"venue"
},
  "geometry": {"coordinates":[-80.56378173829999,43.4618339539],"type":"Point"}
}