{
  "type": "Feature",
  "properties": {
    "iso:country":"CA",
    "sg:city":"Morrisburg",
    "sg:classifiers":[
        {
            "category":"Retail",
            "subcategory":"Auto Repair",
            "type":"Services"
        }
    ],
    "sg:phone":"+1 613 543 2156",
    "sg:postcode":"K0C 1X0",
    "sg:province":"ON",
    "sg:tags":[
        "repairing",
        "automobile"
    ],
    "wof:name":"Gary's Automotive",
    "wof:placetype":"venue"
},
  "geometry": {"coordinates":[-75.187171936,44.8998298645],"type":"Point"}
}