{
  "type": "Feature",
  "properties": {
    "addr:full":"Vancouver BC V6A 4C7",
    "addr:postcode":"v6a 4c7",
    "iso:country":"CA",
    "sg:city":"Vancouver",
    "sg:classifiers":[
        {
            "category":"Restaurant",
            "type":"Food & Drink"
        }
    ],
    "sg:phone":"+1 604 718 1130",
    "sg:postcode":"V6A 4C7",
    "sg:province":"BC",
    "wof:name":"Mc Donald's",
    "wof:placetype":"venue"
},
  "geometry": {"coordinates":[-123.098221,49.274311],"type":"Point"}
}