{
  "type": "Feature",
  "properties": {
    "addr:full":"96 Rg 3 E Trois-Pistoles QC G0L 4K0",
    "addr:housenumber":"96;3 e",
    "addr:postcode":"g0l 4k0",
    "addr:street":"Rg",
    "iso:country":"CA",
    "sg:address":"96 Rg 3 E",
    "sg:city":"Trois-Pistoles",
    "sg:classifiers":[
        {
            "category":"Farming",
            "subcategory":"Farm",
            "type":"Manufacturing & Wholesale Goods"
        }
    ],
    "sg:phone":"+1 418 851 2209",
    "sg:postcode":"G0L 4K0",
    "sg:province":"QC",
    "wof:name":"Ferme Luron Enr",
    "wof:placetype":"venue"
},
  "geometry": {"coordinates":[-69.17487335209999,48.1250190735],"type":"Point"}
}