{
  "type": "Feature",
  "properties": {
    "addr:full":"1433 17 Ave SW Calgary AB T2T 0E1",
    "addr:housenumber":"1433",
    "addr:postcode":"t2t 0e1",
    "addr:street":"17 Ave Sw",
    "iso:country":"CA",
    "sg:address":"1433 17 Ave SW",
    "sg:city":"Calgary",
    "sg:classifiers":[
        {
            "category":"Personal",
            "subcategory":"Beauty Salon",
            "type":"Services"
        }
    ],
    "sg:phone":"+1 403 229 2901",
    "sg:postcode":"T2T 0E1",
    "sg:province":"AB",
    "wof:name":"K & J Creative Hair Design",
    "wof:placetype":"venue"
},
  "geometry": {"coordinates":[-114.094955,51.037689],"type":"Point"}
}