{
  "type": "Feature",
  "properties": {
    "addr:full":"Montreal QC H3H 2N4",
    "addr:postcode":"h3h 2n4",
    "iso:country":"CA",
    "sg:city":"Montreal",
    "sg:classifiers":[
        {
            "category":"Real Estate",
            "subcategory":"Real Estate Agent",
            "type":"Services"
        }
    ],
    "sg:phone":"+1 514 931 8821",
    "sg:postcode":"H3H 2N4",
    "sg:province":"QC",
    "sg:tags":[
        "management"
    ],
    "wof:name":"Chatel",
    "wof:placetype":"venue"
},
  "geometry": {"coordinates":[-73.5546722412,45.5224723816],"type":"Point"}
}