{
  "type": "Feature",
  "properties": {
    "addr:full":"61 Alness St # 216 North York ON M3J 2H2",
    "addr:housenumber":"61",
    "addr:postcode":"m3j 2h2",
    "addr:street":"Alness St # 216",
    "iso:country":"CA",
    "sg:address":"61 Alness St # 216",
    "sg:city":"North York",
    "sg:classifiers":[
        {
            "category":"Manufacturing",
            "subcategory":"Printing",
            "type":"Manufacturing & Wholesale Goods"
        }
    ],
    "sg:phone":"+1 416 663 9229",
    "sg:postcode":"M3J 2H2",
    "sg:province":"ON",
    "sg:tags":[
        "publisher"
    ],
    "wof:name":"Toys & Games Magazine",
    "wof:placetype":"venue"
},
  "geometry": {"coordinates":[-79.472649,43.773022],"type":"Point"}
}