{
  "type": "Feature",
  "properties": {
    "addr:full":"39 Brandon Lane Ingonish NS B0C 1K0",
    "addr:housenumber":"39",
    "addr:postcode":"b0c 1k0",
    "addr:street":"Brandon Lane",
    "iso:country":"CA",
    "sg:address":"39 Brandon Lane",
    "sg:city":"Ingonish",
    "sg:classifiers":[
        {
            "category":"Education",
            "subcategory":"School",
            "type":"Public Place"
        }
    ],
    "sg:phone":"+1 902 285 2638",
    "sg:postcode":"B0C 1K0",
    "sg:province":"NS",
    "wof:name":"Cape Smokey Elementary School",
    "wof:placetype":"venue"
},
  "geometry": {"coordinates":[-60.368423,46.691711],"type":"Point"}
}