{
  "type": "Feature",
  "properties": {
    "addr:full":"528 Upper Sherman Ave Hamilton ON L8V 3M1",
    "addr:housenumber":"528",
    "addr:postcode":"l8v 3m1",
    "addr:street":"Upper Sherman Ave",
    "iso:country":"CA",
    "sg:address":"528 Upper Sherman Ave",
    "sg:city":"Hamilton",
    "sg:classifiers":[
        {
            "category":"Professional",
            "subcategory":"Accounting & Tax Preparation",
            "type":"Services"
        }
    ],
    "sg:phone":"+1 905 547 4425",
    "sg:postcode":"L8V 3M1",
    "sg:province":"ON",
    "sg:tags":[
        "return",
        "filing"
    ],
    "wof:name":"F B Accomando Business Svc",
    "wof:placetype":"venue"
},
  "geometry": {"coordinates":[-79.847565,43.231998],"type":"Point"}
}