{
  "type": "Feature",
  "properties": {
    "iso:country":"CA",
    "sg:city":"Victoriaville",
    "sg:classifiers":[
        {
            "category":"Arts & Performance",
            "subcategory":"Theater",
            "type":"Entertainment"
        }
    ],
    "sg:phone":"+1 819 352 3915",
    "sg:postcode":"G6S 1G1",
    "sg:province":"QC",
    "sg:tags":[
        "clown"
    ],
    "wof:name":"Fou Fou Le Clown",
    "wof:placetype":"venue"
},
  "geometry": {"coordinates":[-71.9225616455,46.05626297],"type":"Point"}
}