{
  "type": "Feature",
  "properties": {
    "addr:full":"6803 Melmack Cres Prince George BC V2M 7C9",
    "addr:housenumber":"6803",
    "addr:postcode":"v2m 7c9",
    "addr:street":"Melmack Cres",
    "iso:country":"CA",
    "sg:address":"6803 Melmack Cres",
    "sg:city":"Prince George",
    "sg:classifiers":[
        {
            "category":"Building & Trades",
            "subcategory":"Construction",
            "type":"Services"
        }
    ],
    "sg:phone":"+1 250 564 7674",
    "sg:postcode":"V2M 7C9",
    "sg:province":"BC",
    "sg:tags":[
        "masonry",
        "contractor"
    ],
    "wof:name":"Cranbrook Hill Masonry Ltd",
    "wof:placetype":"venue"
},
  "geometry": {"coordinates":[-122.84831200000001,53.937382],"type":"Point"}
}