{
  "type": "Feature",
  "properties": {
    "addr:full":"1920 Ellesmere Rd #305 Scarborough ON M1H 2V6",
    "addr:housenumber":"1920",
    "addr:postcode":"m1h 2v6",
    "addr:street":"Ellesmere Rd # 305",
    "iso:country":"CA",
    "sg:address":"1920 Ellesmere Rd #305",
    "sg:city":"Scarborough",
    "sg:classifiers":[
        {
            "category":"Professional",
            "subcategory":"Lawyer & Legal Services",
            "type":"Services"
        }
    ],
    "sg:phone":"+1 416 431 5870",
    "sg:postcode":"M1H 2V6",
    "sg:province":"ON",
    "sg:tags":[
        "attorney"
    ],
    "wof:name":"Petropoulos, Peter",
    "wof:placetype":"venue"
},
  "geometry": {"coordinates":[-79.24050099999999,43.774696],"type":"Point"}
}