{
  "type": "Feature",
  "properties": {
    "iso:country":"CA",
    "sg:address":"1260 Lakeshore Rd E",
    "sg:city":"Mississauga",
    "sg:classifiers":[
        {
            "category":"Freight",
            "type":"Transportation"
        }
    ],
    "sg:phone":"+1 905 274 1234",
    "sg:postcode":"L5E 3B8",
    "sg:province":"ON",
    "sg:tags":[
        "warehouse",
        "self",
        "storage"
    ],
    "wof:name":"Mc Kenna's Warehouse & Distr",
    "wof:placetype":"venue"
},
  "geometry": {"coordinates":[-79.55307769780001,43.5820465088],"type":"Point"}
}