{
  "type": "Feature",
  "properties": {
    "addr:full":"22709 Hwy 7 Sheet Harbour NS B0J 3B0",
    "addr:housenumber":"22709",
    "addr:postcode":"b0j 3b0",
    "addr:street":"Hwy 7",
    "iso:country":"CA",
    "sg:address":"22709 Hwy 7",
    "sg:city":"Sheet Harbour",
    "sg:classifiers":[
        {
            "category":"Organizations",
            "subcategory":"Membership Organization",
            "type":"Services"
        }
    ],
    "sg:phone":"+1 902 885 2668",
    "sg:postcode":"B0J 3B0",
    "sg:province":"NS",
    "wof:name":"Lea Place",
    "wof:placetype":"venue"
},
  "geometry": {"coordinates":[-62.530884,44.919815],"type":"Point"}
}