{
  "type": "Feature",
  "properties": {
    "addr:full":"286 Stephen St Morden MB R6M 1T4",
    "addr:housenumber":"286",
    "addr:postcode":"r6m 1t4",
    "addr:street":"Stephen St",
    "iso:country":"CA",
    "sg:address":"286 Stephen St",
    "sg:city":"Morden",
    "sg:classifiers":[
        {
            "category":"Professional",
            "subcategory":"Accounting & Tax Preparation",
            "type":"Services"
        }
    ],
    "sg:phone":"+1 204 822 6204",
    "sg:postcode":"R6M 1T4",
    "sg:province":"MB",
    "sg:tags":[
        "accountant"
    ],
    "wof:name":"Krahn & Friesen",
    "wof:placetype":"venue"
},
  "geometry": {"coordinates":[-98.0995635986,49.189781189],"type":"Point"}
}