{
  "type": "Feature",
  "properties": {
    "addr:full":"914 10th Ave S Golden BC V0A 1H0",
    "addr:housenumber":"914",
    "addr:postcode":"v0a 1h0",
    "addr:street":"10Th Ave S",
    "iso:country":"CA",
    "sg:address":"914 10th Ave S",
    "sg:city":"Golden",
    "sg:classifiers":[
        {
            "category":"Home & Garden",
            "subcategory":"Hardware",
            "type":"Retail Goods"
        }
    ],
    "sg:phone":"+1 250 344 5714",
    "sg:postcode":"V0A 1H0",
    "sg:province":"BC",
    "wof:name":"Mac Leod's-True Value Hardware",
    "wof:placetype":"venue"
},
  "geometry": {"coordinates":[-116.961235,51.295952],"type":"Point"}
}