{
  "type": "Feature",
  "properties": {
    "addr:full":"150 Interchange Way Concord ON L4K 5P7",
    "addr:housenumber":"150",
    "addr:postcode":"l4k 5p7",
    "addr:street":"Interchange Way",
    "iso:country":"CA",
    "sg:address":"150 Interchange Way",
    "sg:city":"Concord",
    "sg:classifiers":[
        {
            "category":"Travel",
            "subcategory":"Hotels & Motels",
            "type":"Entertainment"
        }
    ],
    "sg:phone":"+1 905 660 9938",
    "sg:postcode":"L4K 5P7",
    "sg:province":"ON",
    "wof:name":"Courtyard By Marriott",
    "wof:placetype":"venue"
},
  "geometry": {"coordinates":[-79.53141021730001,43.7883453369],"type":"Point"}
}