{
  "type": "Feature",
  "properties": {
    "addr:full":"Thetford Mines QC G6G 6N7",
    "addr:postcode":"g6g 6n7",
    "iso:country":"CA",
    "sg:city":"Thetford Mines",
    "sg:classifiers":[
        {
            "category":"Restaurant",
            "type":"Food & Drink"
        }
    ],
    "sg:phone":"+1 418 335 9127",
    "sg:postcode":"G6G 6N7",
    "sg:province":"QC",
    "wof:name":"Mc Donald's",
    "wof:placetype":"venue"
},
  "geometry": {"coordinates":[-71.30791499999999,46.088676],"type":"Point"}
}