{
  "type": "Feature",
  "properties": {
    "addr:full":"Edmonton AB T5J 3G2",
    "addr:postcode":"t5j 3g2",
    "iso:country":"CA",
    "sg:city":"Edmonton",
    "sg:classifiers":[
        {
            "category":"Real Estate",
            "subcategory":"Developer",
            "type":"Services"
        }
    ],
    "sg:phone":"+1 780 421 1207",
    "sg:postcode":"T5J 3G2",
    "sg:province":"AB",
    "wof:name":"Guaranty Properties Ltd",
    "wof:placetype":"venue"
},
  "geometry": {"coordinates":[-113.491005,53.542377],"type":"Point"}
}