{
  "type": "Feature",
  "properties": {
    "addr:full":"857 Pembroke St E Pembroke ON K8A 3M3",
    "addr:housenumber":"857",
    "addr:postcode":"k8a 3m3",
    "addr:street":"Pembroke St E",
    "iso:country":"CA",
    "sg:address":"857 Pembroke St E",
    "sg:city":"Pembroke",
    "sg:classifiers":[
        {
            "category":"Retail",
            "subcategory":"Auto Repair",
            "type":"Services"
        }
    ],
    "sg:phone":"+1 613 735 4139",
    "sg:postcode":"K8A 3M3",
    "sg:province":"ON",
    "sg:tags":[
        "repairing",
        "automobile"
    ],
    "wof:name":"OK Tire Stores",
    "wof:placetype":"venue"
},
  "geometry": {"coordinates":[-77.0902938843,45.8257255554],"type":"Point"}
}