{
  "type": "Feature",
  "properties": {
    "addr:full":"18 Main St Hyas SK S0A 1K0",
    "addr:housenumber":"18",
    "addr:postcode":"s0a 1k0",
    "addr:street":"Main St",
    "iso:country":"CA",
    "sg:address":"18 Main St",
    "sg:city":"Hyas",
    "sg:classifiers":[
        {
            "category":"Travel",
            "subcategory":"Hotels & Motels",
            "type":"Entertainment"
        }
    ],
    "sg:phone":"+1 306 594 2840",
    "sg:postcode":"S0A 1K0",
    "sg:province":"SK",
    "wof:name":"Hyas Hotel",
    "wof:placetype":"venue"
},
  "geometry": {"coordinates":[-102.26020813,51.8931922913],"type":"Point"}
}