{
  "type": "Feature",
  "properties": {
    "addr:full":"491 4th St Courtenay BC V9N 1G9",
    "addr:housenumber":"491",
    "addr:postcode":"v9n 1g9",
    "addr:street":"4Th St",
    "iso:country":"CA",
    "sg:address":"491 4th St",
    "sg:city":"Courtenay",
    "sg:classifiers":[
        {
            "category":"Organizations",
            "subcategory":"Political Organization",
            "type":"Services"
        }
    ],
    "sg:phone":"+1 250 334 3434",
    "sg:postcode":"V9N 1G9",
    "sg:province":"BC",
    "wof:name":"New Democrats",
    "wof:placetype":"venue"
},
  "geometry": {"coordinates":[-125.00196838399999,49.6908760071],"type":"Point"}
}