{
  "type": "Feature",
  "properties": {
    "iso:country":"CA",
    "sg:address":"4358 Roger St",
    "sg:city":"Port Alberni",
    "sg:classifiers":[
        {
            "category":"Organizations",
            "subcategory":"Professional Association",
            "type":"Services"
        }
    ],
    "sg:phone":"+1 250 723 9921",
    "sg:postcode":"V9Y 3Z6",
    "sg:province":"BC",
    "wof:name":"Oddfellows & Rebekah's Hall",
    "wof:placetype":"venue"
},
  "geometry": {"coordinates":[-124.79881286600001,49.2538642883],"type":"Point"}
}