{
  "type": "Feature",
  "properties": {
    "addr:full":"1090 Fairfield Rd Victoria BC V8V 3A5",
    "addr:housenumber":"1090",
    "addr:postcode":"v8v 3a5",
    "addr:street":"Fairfield Rd",
    "iso:country":"CA",
    "sg:address":"1090 Fairfield Rd",
    "sg:city":"Victoria",
    "sg:classifiers":[
        {
            "category":"Retail",
            "subcategory":"Auto Repair",
            "type":"Services"
        }
    ],
    "sg:phone":"+1 250 385 6371",
    "sg:postcode":"V8V 3A5",
    "sg:province":"BC",
    "sg:tags":[
        "repairing",
        "automobile"
    ],
    "wof:name":"Fairfield Shell",
    "wof:placetype":"venue"
},
  "geometry": {"coordinates":[-123.355873,48.418209],"type":"Point"}
}