{
  "type": "Feature",
  "properties": {
    "addr:full":"1090 Coverdale Rd Riverview NB E1B 5G5",
    "addr:housenumber":"1090",
    "addr:postcode":"e1b 5g5",
    "addr:street":"Coverdale Rd",
    "iso:country":"CA",
    "sg:address":"1090 Coverdale Rd",
    "sg:city":"Riverview",
    "sg:classifiers":[
        {
            "category":"Real Estate",
            "subcategory":"Surveying",
            "type":"Services"
        }
    ],
    "sg:phone":"+1 506 387 4073",
    "sg:postcode":"E1B 5G5",
    "sg:province":"NB",
    "sg:tags":[
        "surveyor"
    ],
    "wof:name":"Daigle Surveys Ltd",
    "wof:placetype":"venue"
},
  "geometry": {"coordinates":[-64.8565750122,46.0473823547],"type":"Point"}
}