{
  "type": "Feature",
  "properties": {
    "addr:full":"258 Rue Saint-Edouard Saint-Germain-DE-Grantham QC J0C 1K0",
    "addr:housenumber":"258",
    "addr:postcode":"j0c 1k0",
    "addr:street":"Rue Saint-Edouard",
    "iso:country":"CA",
    "sg:address":"258 Rue Saint-Edouard",
    "sg:city":"Saint-Germain-DE-Grantham",
    "sg:classifiers":[
        {
            "category":"Wholesale",
            "subcategory":"Farm Supplies",
            "type":"Manufacturing & Wholesale Goods"
        }
    ],
    "sg:phone":"+1 819 395 2557",
    "sg:postcode":"J0C 1K0",
    "sg:province":"QC",
    "sg:tags":[
        "salt"
    ],
    "wof:name":"Sel Drummond Enr",
    "wof:placetype":"venue"
},
  "geometry": {"coordinates":[-72.568665,45.839798],"type":"Point"}
}