{
  "type": "Feature",
  "properties": {
    "addr:full":"651 Burlington St E Hamilton ON L8L 4J5",
    "addr:housenumber":"651",
    "addr:postcode":"l8l 4j5",
    "addr:street":"Burlington St E",
    "iso:country":"CA",
    "sg:address":"651 Burlington St E",
    "sg:city":"Hamilton",
    "sg:classifiers":[
        {
            "category":"Manufacturing",
            "subcategory":"Glass & Minerals",
            "type":"Manufacturing & Wholesale Goods"
        }
    ],
    "sg:phone":"+1 905 312 9152",
    "sg:postcode":"L8L 4J5",
    "sg:province":"ON",
    "sg:tags":[
        "fabricator",
        "fiber"
    ],
    "wof:name":"Fibre Laminations Ltd",
    "wof:placetype":"venue"
},
  "geometry": {"coordinates":[-79.8357162476,43.2665061951],"type":"Point"}
}