{
  "type": "Feature",
  "properties": {
    "addr:full":"510 Home St W Moose Jaw SK S6H 7P4",
    "addr:housenumber":"510",
    "addr:postcode":"s6h 7p4",
    "addr:street":"Home St W",
    "iso:country":"CA",
    "sg:address":"510 Home St W",
    "sg:city":"Moose Jaw",
    "sg:classifiers":[
        {
            "category":"Sports & Exercise",
            "subcategory":"Bowling",
            "type":"Entertainment"
        }
    ],
    "sg:phone":"+1 306 693 0955",
    "sg:postcode":"S6H 7P4",
    "sg:province":"SK",
    "sg:tags":[
        "center"
    ],
    "wof:name":"South Hill Bowling Ctr",
    "wof:placetype":"venue"
},
  "geometry": {"coordinates":[-105.54750824,50.3853721619],"type":"Point"}
}