{
  "type": "Feature",
  "properties": {
    "addr:full":"1125 Richter St Kelowna BC V1Y 2K6",
    "addr:housenumber":"1125",
    "addr:postcode":"v1y 2k6",
    "addr:street":"Richter St",
    "iso:country":"CA",
    "sg:address":"1125 Richter St",
    "sg:city":"Kelowna",
    "sg:classifiers":[
        {
            "category":"Manufacturing",
            "subcategory":"Food",
            "type":"Manufacturing & Wholesale Goods"
        }
    ],
    "sg:phone":"+1 250 762 9144",
    "sg:postcode":"V1Y 2K6",
    "sg:province":"BC",
    "sg:tags":[
        "winery"
    ],
    "wof:name":"Calona Vineyards",
    "wof:placetype":"venue"
},
  "geometry": {"coordinates":[-119.488274,49.894955],"type":"Point"}
}