{
  "type": "Feature",
  "properties": {
    "addr:full":"66 Leeper St St Catharines ON L2S 2N2",
    "addr:housenumber":"66",
    "addr:postcode":"l2s 2n2",
    "addr:street":"Leeper St",
    "iso:country":"CA",
    "sg:address":"66 Leeper St",
    "sg:city":"St Catharines",
    "sg:classifiers":[
        {
            "category":"Professional",
            "subcategory":"Business Services",
            "type":"Services"
        }
    ],
    "sg:phone":"+1 905 684 6132",
    "sg:postcode":"L2S 2N2",
    "sg:province":"ON",
    "sg:tags":[
        "interior",
        "consultant",
        "design",
        "decorator"
    ],
    "wof:name":"Academy Decorators Ent Inc",
    "wof:placetype":"venue"
},
  "geometry": {"coordinates":[-79.25235000000001,43.143929],"type":"Point"}
}