{
  "type": "Feature",
  "properties": {
    "addr:full":"736 Marion St Winnipeg MB R2J 0K4",
    "addr:housenumber":"736",
    "addr:postcode":"r2j 0k4",
    "addr:street":"Marion St",
    "iso:country":"CA",
    "sg:address":"736 Marion St",
    "sg:city":"Winnipeg",
    "sg:classifiers":[
        {
            "category":"Retail",
            "subcategory":"Auto Repair",
            "type":"Services"
        }
    ],
    "sg:phone":"+1 204 233 4924",
    "sg:postcode":"R2J 0K4",
    "sg:province":"MB",
    "sg:tags":[
        "automobile",
        "co",
        "drive",
        "transporter"
    ],
    "wof:name":"Allied Systems",
    "wof:placetype":"venue"
},
  "geometry": {"coordinates":[-97.0904541016,49.8817634583],"type":"Point"}
}