{
  "type": "Feature",
  "properties": {
    "addr:full":"2275 10th Ave W Vancouver BC V6K 2J1",
    "addr:housenumber":"2275",
    "addr:postcode":"v6k 2j1",
    "addr:street":"10Th Ave W",
    "iso:country":"CA",
    "sg:address":"2275 10th Ave W",
    "sg:city":"Vancouver",
    "sg:classifiers":[
        {
            "category":"Wholesale",
            "subcategory":"Durable Goods & Equipment",
            "type":"Manufacturing & Wholesale Goods"
        }
    ],
    "sg:phone":"+1 604 732 3414",
    "sg:postcode":"V6K 2J1",
    "sg:province":"BC",
    "sg:tags":[
        "exporter"
    ],
    "wof:name":"Awa Intl",
    "wof:placetype":"venue"
},
  "geometry": {"coordinates":[-123.156921,49.263111],"type":"Point"}
}