{
  "type": "Feature",
  "properties": {
    "addr:full":"35 Longworth Ave Charlottetown PE C1A 5A3",
    "addr:housenumber":"35",
    "addr:postcode":"c1a 5a3",
    "addr:street":"Longworth Ave",
    "iso:country":"CA",
    "sg:address":"35 Longworth Ave",
    "sg:city":"Charlottetown",
    "sg:classifiers":[
        {
            "category":"Retail",
            "subcategory":"Funeral Services",
            "type":"Services"
        }
    ],
    "sg:phone":"+1 902 894 4321",
    "sg:postcode":"C1A 5A3",
    "sg:province":"PE",
    "sg:tags":[
        "director"
    ],
    "wof:name":"Hennessey Funeral Home",
    "wof:placetype":"venue"
},
  "geometry": {"coordinates":[-63.124973,46.242012],"type":"Point"}
}