{
  "type": "Feature",
  "properties": {
    "iso:country":"CA",
    "sg:address":"4621 Boul Saint-Laurent",
    "sg:city":"Montreal",
    "sg:classifiers":[
        {
            "category":"Professional",
            "subcategory":"Art Services",
            "type":"Services"
        }
    ],
    "sg:phone":"+1 514 285 1577",
    "sg:postcode":"H2T 1R2",
    "sg:province":"QC",
    "sg:tags":[
        "calligrapher"
    ],
    "wof:name":"Calligrafia",
    "wof:placetype":"venue"
},
  "geometry": {"coordinates":[-73.58749389650001,45.5207977295],"type":"Point"}
}