{
  "type": "Feature",
  "properties": {
    "addr:full":"Saint-Lucien QC J0C 1N0",
    "addr:postcode":"j0c 1n0",
    "iso:country":"CA",
    "sg:city":"Saint-Lucien",
    "sg:classifiers":[
        {
            "category":"Farming",
            "subcategory":"Farm & Veterinary Services",
            "type":"Manufacturing & Wholesale Goods"
        }
    ],
    "sg:phone":"+1 819 397 4531",
    "sg:postcode":"J0C 1N0",
    "sg:province":"QC",
    "wof:name":"L & S Cranberry L-P",
    "wof:placetype":"venue"
},
  "geometry": {"coordinates":[-72.2692565918,45.8750839233],"type":"Point"}
}