{
  "type": "Feature",
  "properties": {
    "addr:full":"469 Boul Adelard-Savoie Dieppe NB E1A 7E7",
    "addr:housenumber":"469",
    "addr:postcode":"e1a 7e7",
    "addr:street":"Boul Adelard-Savoie",
    "iso:country":"CA",
    "sg:address":"469 Boul Adelard-Savoie",
    "sg:city":"Dieppe",
    "sg:classifiers":[
        {
            "category":"Building & Trades",
            "subcategory":"Landscaping Services",
            "type":"Services"
        }
    ],
    "sg:phone":"+1 506 859 1214",
    "sg:postcode":"E1A 7E7",
    "sg:province":"NB",
    "sg:tags":[
        "landscape",
        "contractor"
    ],
    "wof:name":"East Green Landscaping Ltd",
    "wof:placetype":"venue"
},
  "geometry": {"coordinates":[-64.7038192749,46.1081123352],"type":"Point"}
}