{
  "type": "Feature",
  "properties": {
    "addr:full":"50 Mandalay Dr Winnipeg MB R2X 2Z2",
    "addr:housenumber":"50",
    "addr:postcode":"r2x 2z2",
    "addr:street":"Mandalay Dr",
    "iso:country":"CA",
    "sg:address":"50 Mandalay Dr",
    "sg:city":"Winnipeg",
    "sg:classifiers":[
        {
            "category":"Wholesale",
            "subcategory":"Hardware",
            "type":"Manufacturing & Wholesale Goods"
        }
    ],
    "sg:phone":"+1 204 633 9179",
    "sg:postcode":"R2X 2Z2",
    "sg:province":"MB",
    "sg:tags":[
        "fastener"
    ],
    "wof:name":"Ykk Canada Inc",
    "wof:placetype":"venue"
},
  "geometry": {"coordinates":[-97.18280799999999,49.947186],"type":"Point"}
}