{
  "type": "Feature",
  "properties": {
    "addr:full":"1701 Rue Notre-Dame Est Sainte-Marthe-Du-Cap QC G8T 8B2",
    "addr:housenumber":"1701",
    "addr:postcode":"g8t 8b2",
    "addr:street":"Rue Notre-Dame Est",
    "iso:country":"CA",
    "sg:address":"1701 Rue Notre-Dame Est",
    "sg:city":"Sainte-Marthe-Du-Cap",
    "sg:classifiers":[
        {
            "category":"Recreation",
            "type":"Entertainment"
        }
    ],
    "sg:phone":"+1 819 373 3666",
    "sg:postcode":"G8T 8B2",
    "sg:province":"QC",
    "sg:tags":[
        "center",
        "association"
    ],
    "wof:name":"Petanque Amis Ste-Marthe",
    "wof:placetype":"venue"
},
  "geometry": {"coordinates":[-72.481247,46.384357],"type":"Point"}
}