{
  "type": "Feature",
  "properties": {
    "addr:full":"1831 King St E Hamilton ON L8K 1V8",
    "addr:housenumber":"1831",
    "addr:postcode":"l8k 1v8",
    "addr:street":"King St E",
    "iso:country":"CA",
    "sg:address":"1831 King St E",
    "sg:city":"Hamilton",
    "sg:classifiers":[
        {
            "category":"Organizations",
            "subcategory":"Religious Organization",
            "type":"Services"
        }
    ],
    "sg:phone":"+1 905 549 4335",
    "sg:postcode":"L8K 1V8",
    "sg:province":"ON",
    "sg:tags":[
        "church"
    ],
    "wof:name":"St Mary's Anglican Church",
    "wof:placetype":"venue"
},
  "geometry": {"coordinates":[-79.809967,43.232193],"type":"Point"}
}