{
  "type": "Feature",
  "properties": {
    "addr:full":"5909 6 St SE Calgary AB T2H 1L8",
    "addr:housenumber":"5909 6",
    "addr:postcode":"t2h 1l8",
    "addr:street":"St Se",
    "iso:country":"CA",
    "sg:address":"5909 6 St SE",
    "sg:city":"Calgary",
    "sg:classifiers":[
        {
            "category":"Manufacturing",
            "subcategory":"Motor Vehicles & Parts",
            "type":"Manufacturing & Wholesale Goods"
        }
    ],
    "sg:phone":"+1 403 253 7555",
    "sg:postcode":"T2H 1L8",
    "sg:province":"AB",
    "sg:tags":[
        "equipment",
        "truck"
    ],
    "wof:name":"Greatwest Kenworth Ltd",
    "wof:placetype":"venue"
},
  "geometry": {"coordinates":[-114.050346,50.998825],"type":"Point"}
}