{
  "type": "Feature",
  "properties": {
    "iso:country":"CA",
    "sg:address":"387 Boul DE Mortagne",
    "sg:city":"Boucherville",
    "sg:classifiers":[
        {
            "category":"Professional",
            "subcategory":"Business Services",
            "type":"Services"
        }
    ],
    "sg:phone":"+1 450 449 0500",
    "sg:postcode":"J4B 1B7",
    "sg:province":"QC",
    "sg:tags":[
        "interior",
        "consultant",
        "design",
        "decorator"
    ],
    "wof:name":"Peinture & Decor DE Mortagne",
    "wof:placetype":"venue"
},
  "geometry": {"coordinates":[-73.43897247309999,45.5901374817],"type":"Point"}
}