{
  "type": "Feature",
  "properties": {
    "addr:full":"2 Ruskin Ave Toronto ON M6P 3P8",
    "addr:housenumber":"2",
    "addr:postcode":"m6p 3p8",
    "addr:street":"Ruskin Ave",
    "iso:country":"CA",
    "sg:address":"2 Ruskin Ave",
    "sg:city":"Toronto",
    "sg:classifiers":[
        {
            "category":"Education",
            "subcategory":"School",
            "type":"Public Place"
        }
    ],
    "sg:phone":"+1 416 393 5370",
    "sg:postcode":"M6P 3P8",
    "sg:province":"ON",
    "wof:name":"Saint Luigi",
    "wof:placetype":"venue"
},
  "geometry": {"coordinates":[-79.451561,43.662785],"type":"Point"}
}