{
  "type": "Feature",
  "properties": {
    "addr:full":"3167 North Service Rd Burlington ON L7N 3G2",
    "addr:housenumber":"3167",
    "addr:postcode":"l7n 3g2",
    "addr:street":"North Service Rd",
    "iso:country":"CA",
    "sg:address":"3167 North Service Rd",
    "sg:city":"Burlington",
    "sg:classifiers":[
        {
            "category":"Home & Garden",
            "subcategory":"Furniture",
            "type":"Retail Goods"
        }
    ],
    "sg:phone":"+1 905 335 1811",
    "sg:postcode":"L7N 3G2",
    "sg:province":"ON",
    "wof:name":"Leon's Furniture Warehouse",
    "wof:placetype":"venue"
},
  "geometry": {"coordinates":[-79.798355,43.357834],"type":"Point"}
}