{
  "type": "Feature",
  "properties": {
    "addr:full":"297 Betty Ann Dr North York ON M2R 1A9",
    "addr:housenumber":"297",
    "addr:postcode":"m2r 1a9",
    "addr:street":"Betty Ann Dr",
    "iso:country":"CA",
    "sg:address":"297 Betty Ann Dr",
    "sg:city":"North York",
    "sg:classifiers":[
        {
            "category":"Real Estate",
            "subcategory":"Real Estate Agent",
            "type":"Services"
        }
    ],
    "sg:phone":"+1 416 730 9590",
    "sg:postcode":"M2R 1A9",
    "sg:province":"ON",
    "wof:name":"Alan Moses Real Estate Ltd",
    "wof:placetype":"venue"
},
  "geometry": {"coordinates":[-79.434631,43.765244],"type":"Point"}
}