{
  "type": "Feature",
  "properties": {
    "addr:full":"71 Macdonald Ave Macdiarmid ON P0T 2B0",
    "addr:housenumber":"71",
    "addr:postcode":"p0t 2b0",
    "addr:street":"Macdonald Ave",
    "iso:country":"CA",
    "sg:address":"71 Macdonald Ave",
    "sg:city":"Macdiarmid",
    "sg:classifiers":[
        {
            "category":"Education",
            "subcategory":"School",
            "type":"Public Place"
        }
    ],
    "sg:phone":"+1 807 885 3265",
    "sg:postcode":"P0T 2B0",
    "sg:province":"ON",
    "wof:name":"Rocky Bay School",
    "wof:placetype":"venue"
},
  "geometry": {"coordinates":[-88.1290130615,49.4356918335],"type":"Point"}
}