{
  "type": "Feature",
  "properties": {
    "addr:full":"329 George St Sydney NS B1P 1J7",
    "addr:housenumber":"329",
    "addr:postcode":"b1p 1j7",
    "addr:street":"George St",
    "iso:country":"CA",
    "sg:address":"329 George St",
    "sg:city":"Sydney",
    "sg:classifiers":[
        {
            "category":"Organizations",
            "subcategory":"Non-profit Organization",
            "type":"Services"
        }
    ],
    "sg:phone":"+1 902 564 8263",
    "sg:postcode":"B1P 1J7",
    "sg:province":"NS",
    "sg:tags":[
        "charitable",
        "institution"
    ],
    "wof:name":"Canadian Cancer Society",
    "wof:placetype":"venue"
},
  "geometry": {"coordinates":[-60.1929092407,46.1399230957],"type":"Point"}
}