{
  "type": "Feature",
  "properties": {
    "addr:full":"Grande Prairie AB T8V 4H2",
    "addr:postcode":"t8v 4h2",
    "iso:country":"CA",
    "sg:city":"Grande Prairie",
    "sg:classifiers":[
        {
            "category":"Wholesale",
            "subcategory":"Machinery & Supplies",
            "type":"Manufacturing & Wholesale Goods"
        }
    ],
    "sg:phone":"+1 780 532 7133",
    "sg:postcode":"T8V 4H2",
    "sg:province":"AB",
    "sg:tags":[
        "janitor"
    ],
    "wof:name":"Distributors North",
    "wof:placetype":"venue"
},
  "geometry": {"coordinates":[-118.793953,55.194443],"type":"Point"}
}