{
  "type": "Feature",
  "properties": {
    "addr:full":"1600 Bedford Hwy Bedford NS B4A 1E8",
    "addr:housenumber":"1600",
    "addr:postcode":"b4a 1e8",
    "addr:street":"Bedford Hwy",
    "iso:country":"CA",
    "sg:address":"1600 Bedford Hwy",
    "sg:city":"Bedford",
    "sg:classifiers":[
        {
            "category":"Banks & Credit Unions",
            "subcategory":"Bank",
            "type":"Services"
        }
    ],
    "sg:phone":"+1 902 428 4712",
    "sg:postcode":"B4A 1E8",
    "sg:province":"NS",
    "wof:name":"Cibc",
    "wof:placetype":"venue"
},
  "geometry": {"coordinates":[-63.655506134,44.7347297668],"type":"Point"}
}