{
  "type": "Feature",
  "properties": {
    "addr:full":"Truro NS B2N 4B1",
    "addr:postcode":"b2n 4b1",
    "iso:country":"CA",
    "sg:city":"Truro",
    "sg:classifiers":[
        {
            "category":"Education",
            "subcategory":"College",
            "type":"Public Place"
        }
    ],
    "sg:phone":"+1 902 895 2464",
    "sg:postcode":"B2N 4B1",
    "sg:province":"NS",
    "sg:tags":[
        "academic",
        "school"
    ],
    "wof:name":"Colchester Adult Learning Assn",
    "wof:placetype":"venue"
},
  "geometry": {"coordinates":[-63.273178,45.364159],"type":"Point"}
}