{
  "type": "Feature",
  "properties": {
    "addr:full":"Waterloo ON N2L 4C9",
    "addr:postcode":"n2l 4c9",
    "iso:country":"CA",
    "sg:city":"Waterloo",
    "sg:classifiers":[
        {
            "category":"Wholesale",
            "subcategory":"Machinery & Supplies",
            "type":"Manufacturing & Wholesale Goods"
        }
    ],
    "sg:phone":"+1 519 888 9500",
    "sg:postcode":"N2L 4C9",
    "sg:province":"ON",
    "sg:tags":[
        "bearing"
    ],
    "wof:name":"Excel Bearings & Industrial",
    "wof:placetype":"venue"
},
  "geometry": {"coordinates":[-80.535004,43.495876],"type":"Point"}
}