{
  "type": "Feature",
  "properties": {
    "addr:full":"2300 Ryan Rd Courtenay BC V9N 8N6",
    "addr:housenumber":"2300",
    "addr:postcode":"v9n 8n6",
    "addr:street":"Ryan Rd",
    "iso:country":"CA",
    "sg:address":"2300 Ryan Rd",
    "sg:city":"Courtenay",
    "sg:classifiers":[
        {
            "category":"Education",
            "subcategory":"College",
            "type":"Public Place"
        }
    ],
    "sg:phone":"+1 250 334 5200",
    "sg:postcode":"V9N 8N6",
    "sg:province":"BC",
    "sg:tags":[
        "academic",
        "school"
    ],
    "wof:name":"North Island College Comox Vly",
    "wof:placetype":"venue"
},
  "geometry": {"coordinates":[-124.97141999999999,49.707485],"type":"Point"}
}