{
  "type": "Feature",
  "properties": {
    "iso:country":"CA",
    "sg:address":"637 Av Boivin",
    "sg:city":"Roberval",
    "sg:classifiers":[
        {
            "category":"Organizations",
            "subcategory":"Professional Association",
            "type":"Services"
        }
    ],
    "sg:phone":"+1 418 275 5298",
    "sg:postcode":"G8H 1E4",
    "sg:province":"QC",
    "wof:name":"Diabete Lac St-Jean",
    "wof:placetype":"venue"
},
  "geometry": {"coordinates":[-72.2280883789,48.5079498291],"type":"Point"}
}