{
  "type": "Feature",
  "properties": {
    "addr:full":"80 Bullock Dr # 10 Markham ON L3P 3P7",
    "addr:housenumber":"80",
    "addr:postcode":"l3p 3p7",
    "addr:street":"Bullock Dr # 10",
    "iso:country":"CA",
    "sg:address":"80 Bullock Dr # 10",
    "sg:city":"Markham",
    "sg:classifiers":[
        {
            "category":"Wholesale",
            "subcategory":"Metals & Minerals",
            "type":"Manufacturing & Wholesale Goods"
        }
    ],
    "sg:phone":"+1 905 471 6050",
    "sg:postcode":"L3P 3P7",
    "sg:province":"ON",
    "sg:tags":[
        "specialty"
    ],
    "wof:name":"Das Metal Products Inc",
    "wof:placetype":"venue"
},
  "geometry": {"coordinates":[-79.269707,43.877838],"type":"Point"}
}