{
  "type": "Feature",
  "properties": {
    "addr:full":"893 Bancroft Dr Sudbury ON P3B 1P8",
    "addr:housenumber":"893",
    "addr:postcode":"p3b 1p8",
    "addr:street":"Bancroft Dr",
    "iso:country":"CA",
    "sg:address":"893 Bancroft Dr",
    "sg:city":"Sudbury",
    "sg:classifiers":[
        {
            "category":"Health Services",
            "subcategory":"Doctor",
            "type":"Services"
        }
    ],
    "sg:phone":"+1 705 566 0950",
    "sg:postcode":"P3B 1P8",
    "sg:province":"ON",
    "sg:tags":[
        "dentist"
    ],
    "wof:name":"Buba Jr, M DDS",
    "wof:placetype":"venue"
},
  "geometry": {"coordinates":[-80.962952,46.498775],"type":"Point"}
}