{
  "type": "Feature",
  "properties": {
    "addr:full":"Kitchener ON N2G 1G5",
    "addr:postcode":"n2g 1g5",
    "iso:country":"CA",
    "sg:city":"Kitchener",
    "sg:classifiers":[
        {
            "category":"Health Services",
            "subcategory":"Doctor",
            "type":"Services"
        }
    ],
    "sg:phone":"+1 519 578 6960",
    "sg:postcode":"N2G 1G5",
    "sg:province":"ON",
    "sg:tags":[
        "physician",
        "surgeon"
    ],
    "wof:name":"Rao, V B S MD",
    "wof:placetype":"venue"
},
  "geometry": {"coordinates":[-80.51206207280001,43.4574813843],"type":"Point"}
}