{
  "type": "Feature",
  "properties": {
    "addr:full":"376 Millard Ave Newmarket ON L3Y 1Z7",
    "addr:housenumber":"376",
    "addr:postcode":"l3y 1z7",
    "addr:street":"Millard Ave",
    "iso:country":"CA",
    "sg:address":"376 Millard Ave",
    "sg:city":"Newmarket",
    "sg:classifiers":[
        {
            "category":"Professional",
            "subcategory":"Business Services",
            "type":"Services"
        }
    ],
    "sg:phone":"+1 905 895 2755",
    "sg:postcode":"L3Y 1Z7",
    "sg:province":"ON",
    "sg:tags":[
        "interior",
        "consultant",
        "design",
        "decorator"
    ],
    "wof:name":"Faye Longhurst Designs",
    "wof:placetype":"venue"
},
  "geometry": {"coordinates":[-79.4620666504,44.0537872314],"type":"Point"}
}