{
  "type": "Feature",
  "properties": {
    "addr:full":"3093 Rue Prince-Albert LA Baie QC G7B 1A4",
    "addr:housenumber":"3093",
    "addr:postcode":"g7b 1a4",
    "addr:street":"Rue Prince-Albert",
    "iso:country":"CA",
    "sg:address":"3093 Rue Prince-Albert",
    "sg:city":"LA Baie",
    "sg:classifiers":[
        {
            "category":"Health Services",
            "subcategory":"Nursing And Care Facility",
            "type":"Services"
        }
    ],
    "sg:phone":"+1 418 544 4866",
    "sg:postcode":"G7B 1A4",
    "sg:province":"QC",
    "sg:tags":[
        "home",
        "retirement",
        "community"
    ],
    "wof:name":"Residence DE LA Grande-Baie",
    "wof:placetype":"venue"
},
  "geometry": {"coordinates":[-70.855705,48.313877],"type":"Point"}
}