{
  "type": "Feature",
  "properties": {
    "iso:country":"CA",
    "sg:city":"Montreal",
    "sg:classifiers":[
        {
            "category":"Professional",
            "subcategory":"Computer Services",
            "type":"Services"
        }
    ],
    "sg:phone":"+1 514 844 4994",
    "sg:postcode":"H2W 1Z5",
    "sg:province":"QC",
    "sg:tags":[
        "graphics"
    ],
    "wof:name":"Produits Logiques Lop Lop",
    "wof:placetype":"venue"
},
  "geometry": {"coordinates":[-73.5851898193,45.5194282532],"type":"Point"}
}