{
  "type": "Feature",
  "properties": {
    "iso:country":"CA",
    "sg:address":"14 Rue Principale S",
    "sg:city":"Notre-Dame-Du-Nord",
    "sg:classifiers":[
        {
            "category":"Restaurant",
            "type":"Food & Drink"
        }
    ],
    "sg:phone":"+1 819 723 2292",
    "sg:postcode":"J0Z 3B0",
    "sg:province":"QC",
    "wof:name":"Pizza Mario",
    "wof:placetype":"venue"
},
  "geometry": {"coordinates":[-79.4843215942,47.5924186707],"type":"Point"}
}