{
  "type": "Feature",
  "properties": {
    "addr:full":"Sherridon MB R0B 1L0",
    "addr:postcode":"r0b 1l0",
    "iso:country":"CA",
    "sg:city":"Sherridon",
    "sg:classifiers":[
        {
            "category":"Health Services",
            "subcategory":"Hospital",
            "type":"Services"
        }
    ],
    "sg:phone":"+1 204 468 2012",
    "sg:postcode":"R0B 1L0",
    "sg:province":"MB",
    "wof:name":"Sherridon Nursing Station",
    "wof:placetype":"venue"
},
  "geometry": {"coordinates":[-101.085686,55.122387],"type":"Point"}
}