{
  "type": "Feature",
  "properties": {
    "iso:country":"CA",
    "sg:city":"Quebec",
    "sg:classifiers":[
        {
            "category":"Home & Garden",
            "subcategory":"Furniture",
            "type":"Retail Goods"
        }
    ],
    "sg:phone":"+1 418 877 1433",
    "sg:postcode":"G2E 5E2",
    "sg:province":"QC",
    "wof:name":"Meubles Barnabe Inc",
    "wof:placetype":"venue"
},
  "geometry": {"coordinates":[-71.3295211792,46.8019332886],"type":"Point"}
}