{
  "type": "Feature",
  "properties": {
    "addr:full":"220 Rue Principale Leeds Village QC G0N 1J0",
    "addr:housenumber":"220",
    "addr:postcode":"g0n 1j0",
    "addr:street":"Rue Principale Leeds Village",
    "iso:country":"CA",
    "sg:address":"220 Rue Principale",
    "sg:city":"Leeds Village",
    "sg:classifiers":[
        {
            "category":"Government",
            "subcategory":"Office",
            "type":"Public Place"
        }
    ],
    "sg:phone":"+1 418 424 3181",
    "sg:postcode":"G0N 1J0",
    "sg:province":"QC",
    "sg:tags":[
        "village"
    ],
    "wof:name":"St-Jacques DE Leeds Comite",
    "wof:placetype":"venue"
},
  "geometry": {"coordinates":[-71.338211,46.28791],"type":"Point"}
}