{
  "type": "Feature",
  "properties": {
    "addr:full":"18 Arthur St N Elmira ON N3B 1Z7",
    "addr:housenumber":"18",
    "addr:postcode":"n3b 1z7",
    "addr:street":"Arthur St N",
    "iso:country":"CA",
    "sg:address":"18 Arthur St N",
    "sg:city":"Elmira",
    "sg:classifiers":[
        {
            "category":"Farming",
            "subcategory":"Poultry Farm",
            "type":"Manufacturing & Wholesale Goods"
        }
    ],
    "sg:phone":"+1 519 669 2561",
    "sg:postcode":"N3B 1Z7",
    "sg:province":"ON",
    "wof:name":"Bonnie's Chick Hatchery Ltd",
    "wof:placetype":"venue"
},
  "geometry": {"coordinates":[-80.556358,43.601952],"type":"Point"}
}