{
  "type": "Feature",
  "properties": {
    "addr:full":"5 Cameron Lake Rd Tobermory ON N0H 2R0",
    "addr:housenumber":"5",
    "addr:postcode":"n0h 2r0",
    "addr:street":"Cameron Lake Rd",
    "iso:country":"CA",
    "sg:address":"5 Cameron Lake Rd",
    "sg:city":"Tobermory",
    "sg:classifiers":[
        {
            "category":"Restaurant",
            "type":"Food & Drink"
        }
    ],
    "sg:phone":"+1 519 596 2222",
    "sg:postcode":"N0H 2R0",
    "sg:province":"ON",
    "wof:name":"Cameron Lake Restaurant",
    "wof:placetype":"venue"
},
  "geometry": {"coordinates":[-81.665092,45.253826],"type":"Point"}
}