{
  "type": "Feature",
  "properties": {
    "iso:country":"CA",
    "sg:address":"5264 Boal Rd",
    "sg:city":"Duncan",
    "sg:classifiers":[
        {
            "category":"Retail",
            "subcategory":"Repair Shop",
            "type":"Services"
        }
    ],
    "sg:phone":"+1 250 748 0016",
    "sg:postcode":"V9L 6W3",
    "sg:province":"BC",
    "sg:tags":[
        "welding"
    ],
    "wof:name":"Ron's Welding Ltd",
    "wof:placetype":"venue"
},
  "geometry": {"coordinates":[-123.70738220200001,48.779094696],"type":"Point"}
}