{
  "type": "Feature",
  "properties": {
    "iso:country":"CA",
    "sg:address":"737 Kingsway Garden Mall NW",
    "sg:city":"Edmonton",
    "sg:classifiers":[
        {
            "category":"Shopping",
            "type":"Retail Goods"
        }
    ],
    "sg:phone":"+1 780 479 0397",
    "sg:postcode":"T5G 3E6",
    "sg:province":"AB",
    "sg:tags":[
        "miscellaneous",
        "store"
    ],
    "wof:name":"Love Boutique",
    "wof:placetype":"venue"
},
  "geometry": {"coordinates":[-113.490371704,53.5462188721],"type":"Point"}
}