{
  "type": "Feature",
  "properties": {
    "addr:full":"Brampton ON L6T 5K7",
    "addr:postcode":"l6t 5k7",
    "iso:country":"CA",
    "sg:city":"Brampton",
    "sg:classifiers":[
        {
            "category":"Freight",
            "type":"Transportation"
        }
    ],
    "sg:phone":"+1 905 790 2400",
    "sg:postcode":"L6T 5K7",
    "sg:province":"ON",
    "wof:name":"Zap Cargo Svc Inc",
    "wof:placetype":"venue"
},
  "geometry": {"coordinates":[-79.68018341059999,43.7335357666],"type":"Point"}
}