{
  "type": "Feature",
  "properties": {
    "addr:full":"5 Main St S Grand Valley ON L0N 1G0",
    "addr:housenumber":"5",
    "addr:postcode":"l0n 1g0",
    "addr:street":"Main St S Grand Valley",
    "iso:country":"CA",
    "sg:address":"5 Main St S",
    "sg:city":"Grand Valley",
    "sg:classifiers":[
        {
            "category":"Food & Beverages",
            "subcategory":"Groceries & Convenience Stores",
            "type":"Retail Goods"
        }
    ],
    "sg:phone":"+1 519 928 5282",
    "sg:postcode":"L0N 1G0",
    "sg:province":"ON",
    "sg:tags":[
        "grocer"
    ],
    "wof:name":"Hinds Foods",
    "wof:placetype":"venue"
},
  "geometry": {"coordinates":[-80.315048,43.898823],"type":"Point"}
}