{
  "type": "Feature",
  "properties": {
    "addr:full":"311 Black St Whitehorse YT Y1A 2N1",
    "addr:housenumber":"311",
    "addr:postcode":"y1a 2n1",
    "addr:street":"Black St",
    "iso:country":"CA",
    "sg:address":"311 Black St",
    "sg:city":"Whitehorse",
    "sg:classifiers":[
        {
            "category":"Wholesale",
            "subcategory":"Electrical",
            "type":"Manufacturing & Wholesale Goods"
        }
    ],
    "sg:phone":"+1 867 668 5175",
    "sg:postcode":"Y1A 2N1",
    "sg:province":"YT",
    "sg:tags":[
        "communication",
        "radio",
        "telephone",
        "cellular"
    ],
    "wof:name":"Total North Communications Ltd",
    "wof:placetype":"venue"
},
  "geometry": {"coordinates":[-135.05818176299999,60.7236747742],"type":"Point"}
}