{
  "type": "Feature",
  "properties": {
    "iso:country":"CA",
    "sg:address":"61 Rue Roy",
    "sg:city":"Ormstown",
    "sg:classifiers":[
        {
            "category":"Food & Beverages",
            "subcategory":"Groceries & Convenience Stores",
            "type":"Retail Goods"
        }
    ],
    "sg:phone":"+1 450 829 3879",
    "sg:postcode":"J0S 1K0",
    "sg:province":"QC",
    "wof:name":"Depanneur Bouchard Enr",
    "wof:placetype":"venue"
},
  "geometry": {"coordinates":[-73.99002075200001,45.1220550537],"type":"Point"}
}