{
  "type": "Feature",
  "properties": {
    "addr:full":"Montreal QC H3A 3G5",
    "addr:postcode":"h3a 3g5",
    "iso:country":"CA",
    "sg:city":"Montreal",
    "sg:classifiers":[
        {
            "category":"Insurance",
            "subcategory":"Hazard Insurance",
            "type":"Services"
        }
    ],
    "sg:phone":"+1 514 288 8725",
    "sg:postcode":"H3A 3G5",
    "sg:province":"QC",
    "sg:tags":[
        "casualty"
    ],
    "wof:name":"Optimum General Inc",
    "wof:placetype":"venue"
},
  "geometry": {"coordinates":[-73.5617218018,45.5147743225],"type":"Point"}
}