{
  "type": "Feature",
  "properties": {
    "addr:full":"Thetford Mines QC G6G 6H1",
    "addr:postcode":"g6g 6h1",
    "iso:country":"CA",
    "sg:city":"Thetford Mines",
    "sg:classifiers":[
        {
            "category":"Professional",
            "subcategory":"Business Services",
            "type":"Services"
        }
    ],
    "sg:phone":"+1 418 338 2113",
    "sg:postcode":"G6G 6H1",
    "sg:province":"QC",
    "sg:tags":[
        "product",
        "consultant",
        "ceramic",
        "design",
        "interior",
        "decorator"
    ],
    "wof:name":"Couture Lucien & Fils Inc",
    "wof:placetype":"venue"
},
  "geometry": {"coordinates":[-71.299263,46.090576],"type":"Point"}
}