{
  "type": "Feature",
  "properties": {
    "addr:full":"636 New Maryland Hwy New Maryland NB E3C 1K1",
    "addr:housenumber":"636",
    "addr:postcode":"e3c 1k1",
    "addr:street":"New Maryland Hwy",
    "iso:country":"CA",
    "sg:address":"636 New Maryland Hwy",
    "sg:city":"New Maryland",
    "sg:classifiers":[
        {
            "category":"Shopping",
            "subcategory":"Pharmacy",
            "type":"Retail Goods"
        }
    ],
    "sg:phone":"+1 506 459 8787",
    "sg:postcode":"E3C 1K1",
    "sg:province":"NB",
    "wof:name":"New Maryland Pharmacy",
    "wof:placetype":"venue"
},
  "geometry": {"coordinates":[-66.6849060059,45.8908462524],"type":"Point"}
}