{
  "type": "Feature",
  "properties": {
    "addr:full":"PO Box 434 Schomberg ON L0G 1T0",
    "addr:housenumber":"po",
    "addr:postcode":"l0g 1t0",
    "addr:street":"Box 434",
    "iso:country":"CA",
    "sg:address":"PO Box 434",
    "sg:city":"Schomberg",
    "sg:classifiers":[
        {
            "category":"Wholesale",
            "subcategory":"Durable Goods & Equipment",
            "type":"Manufacturing & Wholesale Goods"
        }
    ],
    "sg:phone":"+1 905 939 2867",
    "sg:postcode":"L0G 1T0",
    "sg:province":"ON",
    "sg:tags":[
        "engineering",
        "supply"
    ],
    "wof:name":"Ikb Engineering",
    "wof:placetype":"venue"
},
  "geometry": {"coordinates":[-79.6841049194,44.0028152466],"type":"Point"}
}