{
  "type": "Feature",
  "properties": {
    "addr:full":"26 Welkin Cres Nepean ON K2E 5M5",
    "addr:housenumber":"26",
    "addr:postcode":"k2e 5m5",
    "addr:street":"Welkin Cres",
    "iso:country":"CA",
    "sg:address":"26 Welkin Cres",
    "sg:city":"Nepean",
    "sg:classifiers":[
        {
            "category":"Professional",
            "subcategory":"Management & Consulting",
            "type":"Services"
        }
    ],
    "sg:phone":"+1 613 228 2634",
    "sg:postcode":"K2E 5M5",
    "sg:province":"ON",
    "sg:tags":[
        "consultant",
        "business"
    ],
    "wof:name":"Gls & Assoc",
    "wof:placetype":"venue"
},
  "geometry": {"coordinates":[-75.7232971191,45.3547401428],"type":"Point"}
}