{
  "type": "Feature",
  "properties": {
    "addr:full":"32 Perry St Woodstock ON N4S 3C3",
    "addr:housenumber":"32",
    "addr:postcode":"n4s 3c3",
    "addr:street":"Perry St",
    "iso:country":"CA",
    "sg:address":"32 Perry St",
    "sg:city":"Woodstock",
    "sg:classifiers":[
        {
            "category":"Taxi",
            "type":"Transportation"
        }
    ],
    "sg:phone":"+1 519 537 2345",
    "sg:postcode":"N4S 3C3",
    "sg:province":"ON",
    "sg:tags":[
        "taxicab"
    ],
    "wof:name":"Kendall Cab CO",
    "wof:placetype":"venue"
},
  "geometry": {"coordinates":[-80.75908699999999,43.12851],"type":"Point"}
}