{
  "type": "Feature",
  "properties": {
    "iso:country":"CA",
    "sg:address":"250 Centrum Blvd",
    "sg:city":"Orleans",
    "sg:classifiers":[
        {
            "category":"Cinema",
            "subcategory":"Movie Theater",
            "type":"Entertainment"
        }
    ],
    "sg:phone":"+1 613 834 0666",
    "sg:postcode":"K1E 3J1",
    "sg:province":"ON",
    "wof:name":"Cineplex Odeon Corp",
    "wof:placetype":"venue"
},
  "geometry": {"coordinates":[-75.51026153559999,45.4804573059],"type":"Point"}
}