{
  "type": "Feature",
  "properties": {
    "addr:full":"1540 Park St Hwy 20 Fonthill ON L0S 1E0",
    "addr:housenumber":"1540",
    "addr:postcode":"l0s 1e0",
    "addr:street":"Park St Hwy 20 Fonthill",
    "iso:country":"CA",
    "sg:address":"1540 Park St Hwy 20",
    "sg:city":"Fonthill",
    "sg:classifiers":[
        {
            "category":"Wholesale",
            "subcategory":"Construction Materials",
            "type":"Manufacturing & Wholesale Goods"
        }
    ],
    "sg:phone":"+1 905 892 2686",
    "sg:postcode":"L0S 1E0",
    "sg:province":"ON",
    "sg:tags":[
        "sand",
        "gravel"
    ],
    "wof:name":"Lafarge Canada",
    "wof:placetype":"venue"
},
  "geometry": {"coordinates":[-79.28182200000001,43.044098],"type":"Point"}
}