{
  "type": "Feature",
  "properties": {
    "addr:full":"140 Boul Greber Gatineau QC J8T 6H5",
    "addr:housenumber":"140",
    "addr:postcode":"j8t 6h5",
    "addr:street":"Boul Greber",
    "iso:country":"CA",
    "sg:address":"140 Boul Greber",
    "sg:city":"Gatineau",
    "sg:classifiers":[
        {
            "category":"Shopping",
            "subcategory":"Bicycles & Sporting Goods",
            "type":"Retail Goods"
        }
    ],
    "sg:phone":"+1 819 243 8108",
    "sg:postcode":"J8T 6H5",
    "sg:province":"QC",
    "wof:name":"En Equilibre",
    "wof:placetype":"venue"
},
  "geometry": {"coordinates":[-75.70089,45.468929],"type":"Point"}
}