{
  "type": "Feature",
  "properties": {
    "addr:full":"1909 Main St Westville NS B0K 2A0",
    "addr:housenumber":"1909",
    "addr:postcode":"b0k 2a0",
    "addr:street":"Main St",
    "iso:country":"CA",
    "sg:address":"1909 Main St",
    "sg:city":"Westville",
    "sg:classifiers":[
        {
            "category":"Food & Beverages",
            "subcategory":"Liquor & Beverages",
            "type":"Retail Goods"
        }
    ],
    "sg:phone":"+1 902 396 5180",
    "sg:postcode":"B0K 2A0",
    "sg:province":"NS",
    "sg:tags":[
        "store"
    ],
    "wof:name":"Nova Scotia Liquor Commission",
    "wof:placetype":"venue"
},
  "geometry": {"coordinates":[-62.711517,45.560188],"type":"Point"}
}