{
  "type": "Feature",
  "properties": {
    "addr:full":"7866 Shackleton Dr Richmond BC V7C 5G9",
    "addr:housenumber":"7866",
    "addr:postcode":"v7c 5g9",
    "addr:street":"Shackleton Dr",
    "iso:country":"CA",
    "sg:address":"7866 Shackleton Dr",
    "sg:city":"Richmond",
    "sg:classifiers":[
        {
            "category":"Professional",
            "subcategory":"Business Services",
            "type":"Services"
        }
    ],
    "sg:phone":"+1 604 448 8872",
    "sg:postcode":"V7C 5G9",
    "sg:province":"BC",
    "sg:tags":[
        "event"
    ],
    "wof:name":"Wow Productions",
    "wof:placetype":"venue"
},
  "geometry": {"coordinates":[-123.176163,49.157539],"type":"Point"}
}