{
  "type": "Feature",
  "properties": {
    "iso:country":"CA",
    "sg:address":"2760 Day St",
    "sg:city":"Springfield",
    "sg:classifiers":[
        {
            "category":"Retail",
            "subcategory":"Auto Repair",
            "type":"Services"
        }
    ],
    "sg:phone":"+1 204 222 6663",
    "sg:postcode":"R2C 2Z2",
    "sg:province":"MB",
    "sg:tags":[
        "automobile",
        "painting"
    ],
    "wof:name":"Ground Up Restorations Ltd",
    "wof:placetype":"venue"
},
  "geometry": {"coordinates":[-96.9959106445,49.9221115112],"type":"Point"}
}