{
  "type": "Feature",
  "properties": {
    "addr:full":"65 Rue Larouche Roberval QC G8H 3M9",
    "addr:housenumber":"65",
    "addr:postcode":"g8h 3m9",
    "addr:street":"Rue Larouche",
    "iso:country":"CA",
    "sg:address":"65 Rue Larouche",
    "sg:city":"Roberval",
    "sg:classifiers":[
        {
            "category":"Building & Trades",
            "subcategory":"Plumbing",
            "type":"Services"
        }
    ],
    "sg:phone":"+1 418 275 6703",
    "sg:postcode":"G8H 3M9",
    "sg:province":"QC",
    "sg:tags":[
        "contractor"
    ],
    "wof:name":"Plomberie Regent Inc",
    "wof:placetype":"venue"
},
  "geometry": {"coordinates":[-72.23629800000001,48.510887],"type":"Point"}
}