{
  "type": "Feature",
  "properties": {
    "addr:full":"84 Morley Ave Winnipeg MB R3L 0X5",
    "addr:housenumber":"84",
    "addr:postcode":"r3l 0x5",
    "addr:street":"Morley Ave",
    "iso:country":"CA",
    "sg:address":"84 Morley Ave",
    "sg:city":"Winnipeg",
    "sg:classifiers":[
        {
            "category":"Building & Trades",
            "subcategory":"Cleaning & Sanitation",
            "type":"Services"
        }
    ],
    "sg:phone":"+1 204 452 4449",
    "sg:postcode":"R3L 0X5",
    "sg:province":"MB",
    "sg:tags":[
        "snow",
        "removal"
    ],
    "wof:name":"Greater City Snow Removal",
    "wof:placetype":"venue"
},
  "geometry": {"coordinates":[-97.1262207031,49.8676986694],"type":"Point"}
}