{
  "type": "Feature",
  "properties": {
    "addr:full":"99 Boul Saint-Jean-Baptiste Chateauguay QC J6J 3H9",
    "addr:housenumber":"99",
    "addr:postcode":"j6j 3h9",
    "addr:street":"Boul Saint-Jean-Baptiste",
    "iso:country":"CA",
    "sg:address":"99 Boul Saint-Jean-Baptiste",
    "sg:city":"Chateauguay",
    "sg:classifiers":[
        {
            "category":"Restaurant",
            "type":"Food & Drink"
        }
    ],
    "sg:phone":"+1 450 692 3359",
    "sg:postcode":"J6J 3H9",
    "sg:province":"QC",
    "wof:name":"Pizza Hut",
    "wof:placetype":"venue"
},
  "geometry": {"coordinates":[-73.715248,45.360062],"type":"Point"}
}