{
  "type": "Feature",
  "properties": {
    "iso:country":"CA",
    "sg:address":"4450 Corporate Dr",
    "sg:city":"Burlington",
    "sg:classifiers":[
        {
            "category":"Manufacturing",
            "subcategory":"Tools & Machinery",
            "type":"Manufacturing & Wholesale Goods"
        }
    ],
    "sg:phone":"+1 905 332 8952",
    "sg:postcode":"L7L 5R3",
    "sg:province":"ON",
    "sg:tags":[
        "machine",
        "die",
        "maker",
        "shop"
    ],
    "wof:name":"C Guenther Industries Inc",
    "wof:placetype":"venue"
},
  "geometry": {"coordinates":[-79.7877044678,43.3882751465],"type":"Point"}
}