{
  "type": "Feature",
  "properties": {
    "addr:full":"2275 Av Desaulniers Saint-Hyacinthe QC J2S 6B7",
    "addr:housenumber":"2275",
    "addr:postcode":"j2s 6b7",
    "addr:street":"Av Desaulniers",
    "iso:country":"CA",
    "sg:address":"2275 Av Desaulniers",
    "sg:city":"Saint-Hyacinthe",
    "sg:classifiers":[
        {
            "category":"Organizations",
            "subcategory":"Professional Association",
            "type":"Services"
        }
    ],
    "sg:phone":"+1 450 774 6303",
    "sg:postcode":"J2S 6B7",
    "sg:province":"QC",
    "wof:name":"Philharmonique Societe",
    "wof:placetype":"venue"
},
  "geometry": {"coordinates":[-72.96114300000001,45.62545],"type":"Point"}
}