{
  "type": "Feature",
  "properties": {
    "addr:full":"2700 Rue Du Mont-Joli Sainte-Foy QC G1V 1C8",
    "addr:housenumber":"2700",
    "addr:postcode":"g1v 1c8",
    "addr:street":"Rue Du Mont-Joli",
    "iso:country":"CA",
    "sg:address":"2700 Rue Du Mont-Joli",
    "sg:city":"Sainte-Foy",
    "sg:classifiers":[
        {
            "category":"Manufacturing",
            "subcategory":"Printing",
            "type":"Manufacturing & Wholesale Goods"
        }
    ],
    "sg:phone":"+1 418 658 7177",
    "sg:postcode":"G1V 1C8",
    "sg:province":"QC",
    "sg:tags":[
        "publisher"
    ],
    "wof:name":"White Rock Publishing Inc",
    "wof:placetype":"venue"
},
  "geometry": {"coordinates":[-71.301857,46.783779],"type":"Point"}
}