{
  "type": "Feature",
  "properties": {
    "addr:full":"226 Elizabeth St Vulcan AB T0L 2B0",
    "addr:housenumber":"226",
    "addr:postcode":"t0l 2b0",
    "addr:street":"Elizabeth St",
    "iso:country":"CA",
    "sg:address":"226 Elizabeth St",
    "sg:city":"Vulcan",
    "sg:classifiers":[
        {
            "category":"Building & Trades",
            "subcategory":"Plumbing",
            "type":"Services"
        }
    ],
    "sg:phone":"+1 403 485 6633",
    "sg:postcode":"T0L 2B0",
    "sg:province":"AB",
    "sg:tags":[
        "septic"
    ],
    "wof:name":"Justinick Septic Tank Svc",
    "wof:placetype":"venue"
},
  "geometry": {"coordinates":[-113.271453857,50.3975296021],"type":"Point"}
}