{
  "type": "Feature",
  "properties": {
    "addr:full":"PO Box 316 Nampa AB T0H 2R0",
    "addr:housenumber":"po",
    "addr:postcode":"t0h 2r0",
    "addr:street":"Box 316",
    "iso:country":"CA",
    "sg:address":"PO Box 316",
    "sg:city":"Nampa",
    "sg:classifiers":[
        {
            "category":"Farming",
            "subcategory":"Dairy Farm",
            "type":"Manufacturing & Wholesale Goods"
        }
    ],
    "sg:phone":"+1 780 322 2386",
    "sg:postcode":"T0H 2R0",
    "sg:province":"AB",
    "wof:name":"Baars Dairy",
    "wof:placetype":"venue"
},
  "geometry": {"coordinates":[-117.134315491,56.0387992859],"type":"Point"}
}