{
  "type": "Feature",
  "properties": {
    "addr:full":"22 Boul DE L'Aeroport Bromont QC J2L 1S6",
    "addr:housenumber":"22",
    "addr:postcode":"j2l 1s6",
    "addr:street":"Boul De L'Aeroport",
    "iso:country":"CA",
    "sg:address":"22 Boul DE L'Aeroport",
    "sg:city":"Bromont",
    "sg:classifiers":[
        {
            "category":"Wholesale",
            "subcategory":"Metals & Minerals",
            "type":"Manufacturing & Wholesale Goods"
        }
    ],
    "sg:phone":"+1 450 534 2032",
    "sg:postcode":"J2L 1S6",
    "sg:province":"QC",
    "sg:tags":[
        "tubing"
    ],
    "wof:name":"Quail-T-Tube Inc",
    "wof:placetype":"venue"
},
  "geometry": {"coordinates":[-72.72700500489999,45.2991752625],"type":"Point"}
}