{
  "type": "Feature",
  "properties": {
    "addr:full":"Cottam ON N0R 1B0",
    "addr:postcode":"n0r 1b0",
    "iso:country":"CA",
    "sg:city":"Cottam",
    "sg:classifiers":[
        {
            "category":"Building & Trades",
            "subcategory":"Construction",
            "type":"Services"
        }
    ],
    "sg:phone":"+1 519 839 5130",
    "sg:postcode":"N0R 1B0",
    "sg:province":"ON",
    "sg:tags":[
        "roofing",
        "contractor"
    ],
    "wof:name":"Kingsville Roofing Ltd",
    "wof:placetype":"venue"
},
  "geometry": {"coordinates":[-82.7465515137,42.1271209717],"type":"Point"}
}