{
  "type": "Feature",
  "properties": {
    "addr:full":"999 Upper Wentworth St # 200 Hamilton ON L9A 4X5",
    "addr:housenumber":"999;200",
    "addr:postcode":"l9a 4x5",
    "addr:street":"Upper Wentworth St #",
    "iso:country":"CA",
    "sg:address":"999 Upper Wentworth St # 200",
    "sg:city":"Hamilton",
    "sg:classifiers":[
        {
            "category":"Restaurant",
            "type":"Food & Drink"
        }
    ],
    "sg:phone":"+1 905 385 4481",
    "sg:postcode":"L9A 4X5",
    "sg:province":"ON",
    "wof:name":"New York Fries",
    "wof:placetype":"venue"
},
  "geometry": {"coordinates":[-79.8644485474,43.2167167664],"type":"Point"}
}