{
  "type": "Feature",
  "properties": {
    "addr:full":"450 Main St Vancouver BC V6A 2T4",
    "addr:housenumber":"450",
    "addr:postcode":"v6a 2t4",
    "addr:street":"Main St",
    "iso:country":"CA",
    "sg:address":"450 Main St",
    "sg:city":"Vancouver",
    "sg:classifiers":[
        {
            "category":"Banks & Credit Unions",
            "subcategory":"Bank",
            "type":"Services"
        }
    ],
    "sg:phone":"+1 604 682 6701",
    "sg:postcode":"V6A 2T4",
    "sg:province":"BC",
    "wof:name":"Td Canada Trust",
    "wof:placetype":"venue"
},
  "geometry": {"coordinates":[-123.099586,49.280785],"type":"Point"}
}