{
  "type": "Feature",
  "properties": {
    "addr:full":"1270 Boul Wallberg Dolbeau-Mistassini QC G8L 1H1",
    "addr:housenumber":"1270",
    "addr:postcode":"g8l 1h1",
    "addr:street":"Boul Wallberg",
    "iso:country":"CA",
    "sg:address":"1270 Boul Wallberg",
    "sg:city":"Dolbeau-Mistassini",
    "sg:classifiers":[
        {
            "category":"Insurance",
            "subcategory":"Insurance Agent",
            "type":"Services"
        }
    ],
    "sg:phone":"+1 418 276 3694",
    "sg:postcode":"G8L 1H1",
    "sg:province":"QC",
    "wof:name":"Riverin Girard & Assoc Inc",
    "wof:placetype":"venue"
},
  "geometry": {"coordinates":[-72.2277145386,48.877696991],"type":"Point"}
}