{
  "type": "Feature",
  "properties": {
    "addr:full":"181 Rue Charlotte Sorel-Tracy QC J3P 1H9",
    "addr:housenumber":"181",
    "addr:postcode":"j3p 1h9",
    "addr:street":"Rue Charlotte",
    "iso:country":"CA",
    "sg:address":"181 Rue Charlotte",
    "sg:city":"Sorel-Tracy",
    "sg:classifiers":[
        {
            "category":"Personal",
            "subcategory":"Barber",
            "type":"Services"
        }
    ],
    "sg:phone":"+1 450 743 8787",
    "sg:postcode":"J3P 1H9",
    "sg:province":"QC",
    "wof:name":"Salon Tonio",
    "wof:placetype":"venue"
},
  "geometry": {"coordinates":[-73.10588799999999,46.045208],"type":"Point"}
}