{
  "type": "Feature",
  "properties": {
    "addr:full":"1083 Rue Saint-Denis Montreal QC H2X 3J3",
    "addr:housenumber":"1083",
    "addr:postcode":"h2x 3j3",
    "addr:street":"Rue Saint-Denis",
    "iso:country":"CA",
    "sg:address":"1083 Rue Saint-Denis",
    "sg:city":"Montreal",
    "sg:classifiers":[
        {
            "category":"Personal",
            "type":"Services"
        }
    ],
    "sg:phone":"+1 514 985 2424",
    "sg:postcode":"H2X 3J3",
    "sg:province":"QC",
    "sg:tags":[
        "dating"
    ],
    "wof:name":"Tele-Contact",
    "wof:placetype":"venue"
},
  "geometry": {"coordinates":[-73.557289,45.512447],"type":"Point"}
}