{
  "type": "Feature",
  "properties": {
    "addr:full":"Vancouver BC V6Z 1G3",
    "addr:postcode":"v6z 1g3",
    "iso:country":"CA",
    "sg:city":"Vancouver",
    "sg:classifiers":[
        {
            "category":"Health Services",
            "subcategory":"Doctor",
            "type":"Services"
        }
    ],
    "sg:phone":"+1 604 688 3561",
    "sg:postcode":"V6Z 1G3",
    "sg:province":"BC",
    "sg:tags":[
        "physician",
        "surgeon"
    ],
    "wof:name":"Albert Ho Yee Inc",
    "wof:placetype":"venue"
},
  "geometry": {"coordinates":[-123.118607,49.281956],"type":"Point"}
}