{
  "type": "Feature",
  "properties": {
    "addr:full":"4101 No. 5 Rd Richmond BC V6X 2T9",
    "addr:postcode":"4101;v6x 2t9",
    "addr:street":"5 Rd",
    "iso:country":"CA",
    "sg:address":"4101 No. 5 Rd",
    "sg:city":"Richmond",
    "sg:classifiers":[
        {
            "category":"Building & Trades",
            "subcategory":"Cleaning & Sanitation",
            "type":"Services"
        }
    ],
    "sg:phone":"+1 604 244 1719",
    "sg:postcode":"V6X 2T9",
    "sg:province":"BC",
    "sg:tags":[
        "janitor"
    ],
    "wof:name":"Esk Enterprises Ltd",
    "wof:placetype":"venue"
},
  "geometry": {"coordinates":[-123.091736,49.18391],"type":"Point"}
}