{
  "type": "Feature",
  "properties": {
    "addr:full":"5445 Roblin Blvd Winnipeg MB R3R 0G8",
    "addr:housenumber":"5445",
    "addr:postcode":"r3r 0g8",
    "addr:street":"Roblin Blvd",
    "iso:country":"CA",
    "sg:address":"5445 Roblin Blvd",
    "sg:city":"Winnipeg",
    "sg:classifiers":[
        {
            "category":"Health Services",
            "subcategory":"Nursing And Care Facility",
            "type":"Services"
        }
    ],
    "sg:phone":"+1 204 832 9229",
    "sg:postcode":"R3R 0G8",
    "sg:province":"MB",
    "sg:tags":[
        "home",
        "retirement",
        "community"
    ],
    "wof:name":"Vasa Lund Estates Inc",
    "wof:placetype":"venue"
},
  "geometry": {"coordinates":[-97.292198,49.85955],"type":"Point"}
}