{
  "type": "Feature",
  "properties": {
    "addr:full":"PO Box 80 Riske Creek BC V0L 1T0",
    "addr:housenumber":"po box 80",
    "addr:postcode":"v0l 1t0",
    "iso:country":"CA",
    "sg:address":"PO Box 80",
    "sg:city":"Riske Creek",
    "sg:classifiers":[
        {
            "category":"Organizations",
            "subcategory":"Community Association",
            "type":"Services"
        }
    ],
    "sg:phone":"+1 250 659 5650",
    "sg:postcode":"V0L 1T0",
    "sg:province":"BC",
    "sg:tags":[
        "native"
    ],
    "wof:name":"Tossey Ban Chilcotin Plateau",
    "wof:placetype":"venue"
},
  "geometry": {"coordinates":[-122.52873200000001,51.966454],"type":"Point"}
}