{
  "type": "Feature",
  "properties": {
    "addr:full":"10 Rue Papineau Joliette QC J6E 2K4",
    "addr:housenumber":"10",
    "addr:postcode":"j6e 2k4",
    "addr:street":"Rue Papineau",
    "iso:country":"CA",
    "sg:address":"10 Rue Papineau",
    "sg:city":"Joliette",
    "sg:classifiers":[
        {
            "category":"Cinema",
            "subcategory":"Movie Rental",
            "type":"Entertainment"
        }
    ],
    "sg:phone":"+1 450 752 5252",
    "sg:postcode":"J6E 2K4",
    "sg:province":"QC",
    "sg:tags":[
        "leasing",
        "video",
        "disc",
        "tape"
    ],
    "wof:name":"Superclub Videotron",
    "wof:placetype":"venue"
},
  "geometry": {"coordinates":[-73.44219200000001,46.036167],"type":"Point"}
}