{
  "type": "Feature",
  "properties": {
    "iso:country":"CA",
    "sg:address":"905 Fort St",
    "sg:city":"Victoria",
    "sg:classifiers":[
        {
            "category":"Shopping",
            "type":"Retail Goods"
        }
    ],
    "sg:phone":"+1 250 385 9786",
    "sg:postcode":"V8V 3K3",
    "sg:province":"BC",
    "sg:tags":[
        "picture",
        "printer"
    ],
    "wof:name":"Island Blue Print CO Ltd",
    "wof:placetype":"venue"
},
  "geometry": {"coordinates":[-123.35935974100001,48.4238395691],"type":"Point"}
}