{
  "type": "Feature",
  "properties": {
    "addr:full":"Calgary AB T2P 1C2",
    "addr:postcode":"t2p 1c2",
    "iso:country":"CA",
    "sg:city":"Calgary",
    "sg:classifiers":[
        {
            "category":"Professional",
            "subcategory":"Lawyer & Legal Services",
            "type":"Services"
        }
    ],
    "sg:phone":"+1 403 777 1400",
    "sg:postcode":"T2P 1C2",
    "sg:province":"AB",
    "sg:tags":[
        "attorney"
    ],
    "wof:name":"Meyers & CO",
    "wof:placetype":"venue"
},
  "geometry": {"coordinates":[-114.068268,51.045826],"type":"Point"}
}