{
  "type": "Feature",
  "properties": {
    "addr:full":"7052 Rue Saint-Hubert Montreal QC H2S 2M9",
    "addr:housenumber":"7052",
    "addr:postcode":"h2s 2m9",
    "addr:street":"Rue Saint-Hubert",
    "iso:country":"CA",
    "sg:address":"7052 Rue Saint-Hubert",
    "sg:city":"Montreal",
    "sg:classifiers":[
        {
            "category":"Shopping",
            "subcategory":"Jewelry",
            "type":"Retail Goods"
        }
    ],
    "sg:phone":"+1 514 272 3547",
    "sg:postcode":"H2S 2M9",
    "sg:province":"QC",
    "sg:tags":[
        "jeweler"
    ],
    "wof:name":"Bijouterie Esmeralda",
    "wof:placetype":"venue"
},
  "geometry": {"coordinates":[-73.612335,45.540188],"type":"Point"}
}