{
  "type": "Feature",
  "properties": {
    "addr:full":"Kitchener ON N2G 1E5",
    "addr:postcode":"n2g 1e5",
    "iso:country":"CA",
    "sg:city":"Kitchener",
    "sg:classifiers":[
        {
            "category":"Health Services",
            "subcategory":"Doctor",
            "type":"Services"
        }
    ],
    "sg:phone":"+1 519 744 3503",
    "sg:postcode":"N2G 1E5",
    "sg:province":"ON",
    "sg:tags":[
        "physician",
        "surgeon"
    ],
    "wof:name":"Hamilton, Ronald W MD",
    "wof:placetype":"venue"
},
  "geometry": {"coordinates":[-80.507294,43.455597],"type":"Point"}
}