{
  "type": "Feature",
  "properties": {
    "addr:full":"2396 Coldstream Dr Burlington ON L7P 3Z9",
    "addr:housenumber":"2396",
    "addr:postcode":"l7p 3z9",
    "addr:street":"Coldstream Dr",
    "iso:country":"CA",
    "sg:address":"2396 Coldstream Dr",
    "sg:city":"Burlington",
    "sg:classifiers":[
        {
            "category":"Organizations",
            "subcategory":"Religious Organization",
            "type":"Services"
        }
    ],
    "sg:phone":"+1 905 335 1528",
    "sg:postcode":"L7P 3Z9",
    "sg:province":"ON",
    "sg:tags":[
        "church"
    ],
    "wof:name":"Jewish Community of Burlington",
    "wof:placetype":"venue"
},
  "geometry": {"coordinates":[-79.84516906739999,43.3661842346],"type":"Point"}
}