{
  "type": "Feature",
  "properties": {
    "addr:full":"282 Main St Selkirk MB R1A 2P3",
    "addr:housenumber":"282",
    "addr:postcode":"r1a 2p3",
    "addr:street":"Main St",
    "iso:country":"CA",
    "sg:address":"282 Main St",
    "sg:city":"Selkirk",
    "sg:classifiers":[
        {
            "category":"Banks & Credit Unions",
            "subcategory":"Bank",
            "type":"Services"
        }
    ],
    "sg:phone":"+1 204 482 1810",
    "sg:postcode":"R1A 2P3",
    "sg:province":"MB",
    "wof:name":"Cambrian Credit Union Ltd",
    "wof:placetype":"venue"
},
  "geometry": {"coordinates":[-96.87912799999999,50.139626],"type":"Point"}
}