{
  "type": "Feature",
  "properties": {
    "addr:full":"454 Weldrick Rd E Richmond Hill ON L4B 2M3",
    "addr:housenumber":"454",
    "addr:postcode":"l4b 2m3",
    "addr:street":"Weldrick Rd E",
    "iso:country":"CA",
    "sg:address":"454 Weldrick Rd E",
    "sg:city":"Richmond Hill",
    "sg:classifiers":[
        {
            "category":"Wholesale",
            "subcategory":"Machinery & Supplies",
            "type":"Manufacturing & Wholesale Goods"
        }
    ],
    "sg:phone":"+1 416 747 1088",
    "sg:postcode":"L4B 2M3",
    "sg:province":"ON",
    "sg:tags":[
        "equipment",
        "printing",
        "furniture"
    ],
    "wof:name":"Tristar Business Systems",
    "wof:placetype":"venue"
},
  "geometry": {"coordinates":[-79.405281,43.870342],"type":"Point"}
}