{
  "type": "Feature",
  "properties": {
    "addr:full":"102 Hucknall Rd North York ON M3J 1V8",
    "addr:housenumber":"102",
    "addr:postcode":"m3j 1v8",
    "addr:street":"Hucknall Rd",
    "iso:country":"CA",
    "sg:address":"102 Hucknall Rd",
    "sg:city":"North York",
    "sg:classifiers":[
        {
            "category":"Shopping",
            "subcategory":"Discount & Variety Stores",
            "type":"Retail Goods"
        }
    ],
    "sg:phone":"+1 416 638 4420",
    "sg:postcode":"M3J 1V8",
    "sg:province":"ON",
    "wof:name":"University Colony Variety",
    "wof:placetype":"venue"
},
  "geometry": {"coordinates":[-79.49791,43.756584],"type":"Point"}
}