{
  "type": "Feature",
  "properties": {
    "addr:full":"9282 Sherbrook Hwy Thorburn NS B0K 1W0",
    "addr:housenumber":"9282",
    "addr:postcode":"b0k 1w0",
    "addr:street":"Sherbrook Hwy",
    "iso:country":"CA",
    "sg:address":"9282 Sherbrook Hwy",
    "sg:city":"Thorburn",
    "sg:classifiers":[
        {
            "category":"Building & Trades",
            "subcategory":"Construction",
            "type":"Services"
        }
    ],
    "sg:phone":"+1 902 922 2280",
    "sg:postcode":"B0K 1W0",
    "sg:province":"NS",
    "sg:tags":[
        "well",
        "drilling"
    ],
    "wof:name":"E D Stewart Ltd",
    "wof:placetype":"venue"
},
  "geometry": {"coordinates":[-62.555073,45.561798],"type":"Point"}
}