{
  "type": "Feature",
  "properties": {
    "addr:full":"815 Buchanan Blvd #K2 Winnipeg MB R2Y 1N1",
    "addr:housenumber":"815",
    "addr:postcode":"r2y 1n1",
    "addr:street":"Buchanan Blvd # K2",
    "iso:country":"CA",
    "sg:address":"815 Buchanan Blvd #K2",
    "sg:city":"Winnipeg",
    "sg:classifiers":[
        {
            "category":"Social Services",
            "subcategory":"Child Care",
            "type":"Services"
        }
    ],
    "sg:phone":"+1 204 885 4701",
    "sg:postcode":"R2Y 1N1",
    "sg:province":"MB",
    "wof:name":"Sigfusson Nursery School",
    "wof:placetype":"venue"
},
  "geometry": {"coordinates":[-97.31588000000001,49.88728],"type":"Point"}
}