{
  "type": "Feature",
  "properties": {
    "addr:full":"46 Iona Ave Rothesay NB E2E 3J6",
    "addr:housenumber":"46",
    "addr:postcode":"e2e 3j6",
    "addr:street":"Iona Ave",
    "iso:country":"CA",
    "sg:address":"46 Iona Ave",
    "sg:city":"Rothesay",
    "sg:classifiers":[
        {
            "category":"Personal",
            "subcategory":"Beauty Salon",
            "type":"Services"
        }
    ],
    "sg:phone":"+1 506 847 2022",
    "sg:postcode":"E2E 3J6",
    "sg:province":"NB",
    "wof:name":"Jane's Hair Design",
    "wof:placetype":"venue"
},
  "geometry": {"coordinates":[-65.9757843018,45.3923988342],"type":"Point"}
}