{
  "type": "Feature",
  "properties": {
    "addr:full":"1507 Stones Bay Rd Fort St James BC V0J 1P0",
    "addr:housenumber":"1507",
    "addr:postcode":"v0j 1p0",
    "addr:street":"Stones Bay Rd",
    "iso:country":"CA",
    "sg:address":"1507 Stones Bay Rd",
    "sg:city":"Fort St James",
    "sg:classifiers":[
        {
            "category":"Bars & Pubs",
            "type":"Food & Drink"
        }
    ],
    "sg:phone":"+1 250 996 7684",
    "sg:postcode":"V0J 1P0",
    "sg:province":"BC",
    "wof:name":"Eagle Crest Pub",
    "wof:placetype":"venue"
},
  "geometry": {"coordinates":[-124.294121,54.457973],"type":"Point"}
}