{
  "type": "Feature",
  "properties": {
    "addr:full":"Vancouver BC V6M 2G5",
    "addr:postcode":"v6m 2g5",
    "iso:country":"CA",
    "sg:city":"Vancouver",
    "sg:classifiers":[
        {
            "category":"Wholesale",
            "subcategory":"Durable Goods & Equipment",
            "type":"Manufacturing & Wholesale Goods"
        }
    ],
    "sg:phone":"+1 604 261 8820",
    "sg:postcode":"V6M 2G5",
    "sg:province":"BC",
    "sg:tags":[
        "representative",
        "manufacturer"
    ],
    "wof:name":"Alpha Omega Marketing Ltd",
    "wof:placetype":"venue"
},
  "geometry": {"coordinates":[-123.15646362299999,49.2319564819],"type":"Point"}
}