{
  "type": "Feature",
  "properties": {
    "addr:full":"1950 Rue Martel Saint-Hyacinthe QC J2T 1X8",
    "addr:housenumber":"1950",
    "addr:postcode":"j2t 1x8",
    "addr:street":"Rue Martel",
    "iso:country":"CA",
    "sg:address":"1950 Rue Martel",
    "sg:city":"Saint-Hyacinthe",
    "sg:classifiers":[
        {
            "category":"Wholesale",
            "subcategory":"Fruits & Vegetables",
            "type":"Manufacturing & Wholesale Goods"
        }
    ],
    "sg:phone":"+1 450 773 2583",
    "sg:postcode":"J2T 1X8",
    "sg:province":"QC",
    "wof:name":"Fruits Maska Inc",
    "wof:placetype":"venue"
},
  "geometry": {"coordinates":[-72.9449539185,45.6189231873],"type":"Point"}
}