{
  "type": "Feature",
  "properties": {
    "addr:full":"2255 Rue Bellefeuille Trois-Rivieres QC G9A 3Z1",
    "addr:housenumber":"2255",
    "addr:postcode":"g9a 3z1",
    "addr:street":"Rue Bellefeuille Trois-Rivieres",
    "iso:country":"CA",
    "sg:address":"2255 Rue Bellefeuille",
    "sg:city":"Trois-Rivieres",
    "sg:classifiers":[
        {
            "category":"Real Estate",
            "subcategory":"Real Estate Agent",
            "type":"Services"
        }
    ],
    "sg:phone":"+1 819 375 1363",
    "sg:postcode":"G9A 3Z1",
    "sg:province":"QC",
    "sg:tags":[
        "tool",
        "agency",
        "rental"
    ],
    "wof:name":"Centre DE Location Trois-Riv",
    "wof:placetype":"venue"
},
  "geometry": {"coordinates":[-72.55278,46.337383],"type":"Point"}
}