{
  "type": "Feature",
  "properties": {
    "addr:full":"RR 1 Lowbanks ON N0A 1K0",
    "addr:postcode":"n0a 1k0",
    "addr:street":"Rr 1",
    "iso:country":"CA",
    "sg:address":"RR 1",
    "sg:city":"Lowbanks",
    "sg:classifiers":[
        {
            "category":"Building & Trades",
            "subcategory":"Construction",
            "type":"Services"
        }
    ],
    "sg:phone":"+1 905 899 2300",
    "sg:postcode":"N0A 1K0",
    "sg:province":"ON",
    "sg:tags":[
        "excavating",
        "contractor"
    ],
    "wof:name":"Wassink Excavating Ltd",
    "wof:placetype":"venue"
},
  "geometry": {"coordinates":[-79.4529724121,42.8749542236],"type":"Point"}
}