{
  "type": "Feature",
  "properties": {
    "addr:full":"1909 20th St Didsbury AB T0M 0W0",
    "addr:housenumber":"1909",
    "addr:postcode":"t0m 0w0",
    "addr:street":"20Th St",
    "iso:country":"CA",
    "sg:address":"1909 20th St",
    "sg:city":"Didsbury",
    "sg:classifiers":[
        {
            "category":"Personal",
            "subcategory":"Beauty Salon",
            "type":"Services"
        }
    ],
    "sg:phone":"+1 403 335 3888",
    "sg:postcode":"T0M 0W0",
    "sg:province":"AB",
    "wof:name":"House of Hair",
    "wof:placetype":"venue"
},
  "geometry": {"coordinates":[-114.137283325,51.6601333618],"type":"Point"}
}