{
  "type": "Feature",
  "properties": {
    "addr:full":"129 Rue DE LA Montagne Saint-Gabriel-DE-Brandon QC J0K 2N0",
    "addr:housenumber":"129",
    "addr:postcode":"j0k 2n0",
    "addr:street":"Rue De La Montagne",
    "iso:country":"CA",
    "sg:address":"129 Rue DE LA Montagne",
    "sg:city":"Saint-Gabriel-DE-Brandon",
    "sg:classifiers":[
        {
            "category":"Retail",
            "subcategory":"Auto Repair",
            "type":"Services"
        }
    ],
    "sg:phone":"+1 450 835 1897",
    "sg:postcode":"J0K 2N0",
    "sg:province":"QC",
    "sg:tags":[
        "repairing",
        "automobile"
    ],
    "wof:name":"Garage Alain Brousseau Enr",
    "wof:placetype":"venue"
},
  "geometry": {"coordinates":[-73.37557983400001,46.2948074341],"type":"Point"}
}