{
  "type": "Feature",
  "properties": {
    "addr:full":"365 Boul Fiset Sorel-Tracy QC J3P 3R3",
    "addr:housenumber":"365",
    "addr:postcode":"j3p 3r3",
    "addr:street":"Boul Fiset",
    "iso:country":"CA",
    "sg:address":"365 Boul Fiset",
    "sg:city":"Sorel-Tracy",
    "sg:classifiers":[
        {
            "category":"Professional",
            "subcategory":"Accounting & Tax Preparation",
            "type":"Services"
        }
    ],
    "sg:phone":"+1 450 743 2752",
    "sg:postcode":"J3P 3R3",
    "sg:province":"QC",
    "sg:tags":[
        "accountant"
    ],
    "wof:name":"Verrier Paquin Hebert",
    "wof:placetype":"venue"
},
  "geometry": {"coordinates":[-73.0939788818,46.0364990234],"type":"Point"}
}