{
  "type": "Feature",
  "properties": {
    "iso:country":"CA",
    "sg:address":"78 Emma St",
    "sg:city":"Guelph",
    "sg:classifiers":[
        {
            "category":"Building & Trades",
            "subcategory":"Construction",
            "type":"Services"
        }
    ],
    "sg:phone":"+1 519 836 3305",
    "sg:postcode":"N1E 1T8",
    "sg:province":"ON",
    "sg:tags":[
        "roofing",
        "contractor"
    ],
    "wof:name":"B & A Roofing Guelph",
    "wof:placetype":"venue"
},
  "geometry": {"coordinates":[-80.259216,43.560352],"type":"Point"}
}