{
  "type": "Feature",
  "properties": {
    "addr:full":"4813 Route 134 Cocagne NB E4R 2Y2",
    "addr:housenumber":"4813",
    "addr:postcode":"e4r 2y2",
    "addr:street":"Route 134",
    "iso:country":"CA",
    "sg:address":"4813 Route 134",
    "sg:city":"Cocagne",
    "sg:classifiers":[
        {
            "category":"Food & Beverages",
            "subcategory":"Liquor & Beverages",
            "type":"Retail Goods"
        }
    ],
    "sg:phone":"+1 506 576 8620",
    "sg:postcode":"E4R 2Y2",
    "sg:province":"NB",
    "sg:tags":[
        "store"
    ],
    "wof:name":"N B Liquor Corp",
    "wof:placetype":"venue"
},
  "geometry": {"coordinates":[-64.6198272705,46.3403816223],"type":"Point"}
}