{
  "type": "Feature",
  "properties": {
    "iso:country":"CA",
    "sg:address":"1150 Boul Saint-Joseph E # 304",
    "sg:city":"Montreal",
    "sg:classifiers":[
        {
            "category":"Health Services",
            "subcategory":"Health Practitioner",
            "type":"Services"
        }
    ],
    "sg:phone":"+1 514 598 5945",
    "sg:postcode":"H2J 1L5",
    "sg:province":"QC",
    "sg:tags":[
        "psychologist"
    ],
    "wof:name":"Gilbert & Harvey",
    "wof:placetype":"venue"
},
  "geometry": {"coordinates":[-73.58358,45.530552],"type":"Point"}
}