{
  "type": "Feature",
  "properties": {
    "addr:full":"7227 Rue DE Lisieux Saint-Leonard QC H1S 2G5",
    "addr:housenumber":"7227",
    "addr:postcode":"h1s 2g5",
    "addr:street":"Rue De Lisieux",
    "iso:country":"CA",
    "sg:address":"7227 Rue DE Lisieux",
    "sg:city":"Saint-Leonard",
    "sg:classifiers":[
        {
            "category":"Retail",
            "subcategory":"Portrait Studio",
            "type":"Services"
        }
    ],
    "sg:phone":"+1 514 593 9080",
    "sg:postcode":"H1S 2G5",
    "sg:province":"QC",
    "sg:tags":[
        "photographer"
    ],
    "wof:name":"Dominic Fuizzotto Photography",
    "wof:placetype":"venue"
},
  "geometry": {"coordinates":[-73.58065795900001,45.5790214539],"type":"Point"}
}