{
  "type": "Feature",
  "properties": {
    "iso:country":"CA",
    "sg:address":"13315 89 St NW",
    "sg:city":"Edmonton",
    "sg:classifiers":[
        {
            "category":"Social Services",
            "subcategory":"Child Care",
            "type":"Services"
        }
    ],
    "sg:phone":"+1 780 478 4691",
    "sg:postcode":"T5E 3K3",
    "sg:province":"AB",
    "wof:name":"Glengarry Child Care Society",
    "wof:placetype":"venue"
},
  "geometry": {"coordinates":[-113.476928711,53.5940246582],"type":"Point"}
}