{
  "type": "Feature",
  "properties": {
    "addr:full":"PO Box 1828 Fort Macleod AB T0L 0Z0",
    "addr:housenumber":"po",
    "addr:postcode":"t0l 0z0",
    "addr:street":"Box 1828 Fort",
    "iso:country":"CA",
    "sg:address":"PO Box 1828",
    "sg:city":"Fort Macleod",
    "sg:classifiers":[
        {
            "category":"Retail",
            "subcategory":"Animal Services",
            "type":"Services"
        }
    ],
    "sg:phone":"+1 403 553 2362",
    "sg:postcode":"T0L 0Z0",
    "sg:province":"AB",
    "sg:tags":[
        "horse",
        "training"
    ],
    "wof:name":"S R Training",
    "wof:placetype":"venue"
},
  "geometry": {"coordinates":[-113.395584,49.726074],"type":"Point"}
}