{
  "type": "Feature",
  "properties": {
    "addr:full":"364 Logan Ave Toronto ON M4M 2N7",
    "addr:housenumber":"364",
    "addr:postcode":"m4m 2n7",
    "addr:street":"Logan Ave",
    "iso:country":"CA",
    "sg:address":"364 Logan Ave",
    "sg:city":"Toronto",
    "sg:classifiers":[
        {
            "category":"Building & Trades",
            "subcategory":"Construction",
            "type":"Services"
        }
    ],
    "sg:phone":"+1 416 465 1089",
    "sg:postcode":"M4M 2N7",
    "sg:province":"ON",
    "sg:tags":[
        "roofing",
        "contractor"
    ],
    "wof:name":"Cann Topp Roofing",
    "wof:placetype":"venue"
},
  "geometry": {"coordinates":[-79.343704,43.663445],"type":"Point"}
}