{
  "type": "Feature",
  "properties": {
    "addr:full":"2736 Rte Principale Val-Des-Monts QC J8N 2H7",
    "addr:housenumber":"2736",
    "addr:postcode":"j8n 2h7",
    "addr:street":"Rte Principale",
    "iso:country":"CA",
    "sg:address":"2736 Rte Principale",
    "sg:city":"Val-Des-Monts",
    "sg:classifiers":[
        {
            "category":"Retail",
            "subcategory":"Auto Repair",
            "type":"Services"
        }
    ],
    "sg:phone":"+1 819 457 2546",
    "sg:postcode":"J8N 2H7",
    "sg:province":"QC",
    "sg:tags":[
        "repairing",
        "automobile"
    ],
    "wof:name":"Garage Mahar",
    "wof:placetype":"venue"
},
  "geometry": {"coordinates":[-75.71126599999999,45.789986],"type":"Point"}
}