{
  "type": "Feature",
  "properties": {
    "iso:country":"CA",
    "sg:address":"NW 1 3 5W",
    "sg:city":"Winkler",
    "sg:classifiers":[
        {
            "category":"Museum",
            "type":"Entertainment"
        }
    ],
    "sg:phone":"+1 204 325 7497",
    "sg:postcode":"R6W 4B2",
    "sg:province":"MB",
    "wof:name":"Pembina Thresherman Museum Inc",
    "wof:placetype":"venue"
},
  "geometry": {"coordinates":[-97.93840026860001,49.1777038574],"type":"Point"}
}