{
  "type": "Feature",
  "properties": {
    "iso:country":"CA",
    "sg:address":"1250 Yonge St",
    "sg:city":"Toronto",
    "sg:classifiers":[
        {
            "category":"Food & Beverages",
            "subcategory":"Groceries & Convenience Stores",
            "type":"Retail Goods"
        }
    ],
    "sg:phone":"+1 416 923 4727",
    "sg:postcode":"M4T 1W5",
    "sg:province":"ON",
    "sg:tags":[
        "grocer"
    ],
    "wof:name":"Skippy Food Fair",
    "wof:placetype":"venue"
},
  "geometry": {"coordinates":[-79.3922424316,43.6832046509],"type":"Point"}
}