{
  "type": "Feature",
  "properties": {
    "iso:country":"CA",
    "sg:address":"6024 Spruce Cres",
    "sg:city":"Stettler",
    "sg:classifiers":[
        {
            "category":"Building & Trades",
            "subcategory":"Cleaning & Sanitation",
            "type":"Services"
        }
    ],
    "sg:phone":"+1 403 742 0987",
    "sg:postcode":"T0C 2L1",
    "sg:province":"AB",
    "sg:tags":[
        "janitor"
    ],
    "wof:name":"Sunset Cleaners",
    "wof:placetype":"venue"
},
  "geometry": {"coordinates":[-112.723556519,52.3125495911],"type":"Point"}
}