{
  "type": "Feature",
  "properties": {
    "iso:country":"CA",
    "sg:address":"536 4th St",
    "sg:city":"Courtenay",
    "sg:classifiers":[
        {
            "category":"Personal",
            "subcategory":"Beauty Salon",
            "type":"Services"
        }
    ],
    "sg:phone":"+1 250 334 0205",
    "sg:postcode":"V9N 1H2",
    "sg:province":"BC",
    "wof:name":"Dreamshapers Hair Studio",
    "wof:placetype":"venue"
},
  "geometry": {"coordinates":[-125.002853,49.690262],"type":"Point"}
}