{
  "type": "Feature",
  "properties": {
    "addr:full":"5762 Rue Sherbrooke O Montreal QC H4A 1X1",
    "addr:housenumber":"5762",
    "addr:postcode":"h4a 1x1",
    "addr:street":"Rue Sherbrooke O",
    "iso:country":"CA",
    "sg:address":"5762 Rue Sherbrooke O",
    "sg:city":"Montreal",
    "sg:classifiers":[
        {
            "category":"Shopping",
            "subcategory":"Used Merchandise",
            "type":"Retail Goods"
        }
    ],
    "sg:phone":"+1 514 488 8714",
    "sg:postcode":"H4A 1X1",
    "sg:province":"QC",
    "sg:tags":[
        "second",
        "store",
        "hand"
    ],
    "wof:name":"Salvation Army",
    "wof:placetype":"venue"
},
  "geometry": {"coordinates":[-73.5481262207,45.5742378235],"type":"Point"}
}