{
  "type": "Feature",
  "properties": {
    "addr:full":"295 Weber St N Waterloo ON N2J 3H8",
    "addr:housenumber":"295",
    "addr:postcode":"n2j 3h8",
    "addr:street":"Weber St N",
    "iso:country":"CA",
    "sg:address":"295 Weber St N",
    "sg:city":"Waterloo",
    "sg:classifiers":[
        {
            "category":"Professional",
            "subcategory":"Lawyer & Legal Services",
            "type":"Services"
        }
    ],
    "sg:phone":"+1 519 886 1204",
    "sg:postcode":"N2J 3H8",
    "sg:province":"ON",
    "sg:tags":[
        "attorney"
    ],
    "wof:name":"Petker & Assocs",
    "wof:placetype":"venue"
},
  "geometry": {"coordinates":[-80.52215576170001,43.4803695679],"type":"Point"}
}