{
  "type": "Feature",
  "properties": {
    "addr:full":"9097 Old Ridge Rd St Stephen NB E3L 2X2",
    "addr:housenumber":"9097",
    "addr:postcode":"e3l 2x2",
    "addr:street":"Old Ridge Rd",
    "iso:country":"CA",
    "sg:address":"9097 Old Ridge Rd",
    "sg:city":"St Stephen",
    "sg:classifiers":[
        {
            "category":"Shopping",
            "type":"Retail Goods"
        }
    ],
    "sg:phone":"+1 506 466 2110",
    "sg:postcode":"E3L 2X2",
    "sg:province":"NB",
    "sg:tags":[
        "monument"
    ],
    "wof:name":"Smet Monuments",
    "wof:placetype":"venue"
},
  "geometry": {"coordinates":[-67.2752914429,45.1945533752],"type":"Point"}
}