{
  "type": "Feature",
  "properties": {
    "addr:full":"4951 Haynes Rd Vernon BC V1B 3J6",
    "addr:housenumber":"4951",
    "addr:postcode":"v1b 3j6",
    "addr:street":"Haynes Rd",
    "iso:country":"CA",
    "sg:address":"4951 Haynes Rd",
    "sg:city":"Vernon",
    "sg:classifiers":[
        {
            "category":"Building & Trades",
            "subcategory":"Equipment Rental",
            "type":"Services"
        }
    ],
    "sg:phone":"+1 250 545 3886",
    "sg:postcode":"V1B 3J6",
    "sg:province":"BC",
    "sg:tags":[
        "yard",
        "welding"
    ],
    "wof:name":"Weldtec",
    "wof:placetype":"venue"
},
  "geometry": {"coordinates":[-119.273803711,50.2656860352],"type":"Point"}
}