{
  "type": "Feature",
  "properties": {
    "iso:country":"CA",
    "sg:address":"1 Av DE L'Eglise # 1",
    "sg:city":"Saint-Antoine",
    "sg:classifiers":[
        {
            "category":"Shopping",
            "subcategory":"Pharmacy",
            "type":"Retail Goods"
        }
    ],
    "sg:phone":"+1 506 525 2525",
    "sg:postcode":"E4V 1L6",
    "sg:province":"NB",
    "wof:name":"Pharmacie DE Saint-Antoine Inc",
    "wof:placetype":"venue"
},
  "geometry": {"coordinates":[-64.7523117065,46.3625106812],"type":"Point"}
}