{
  "type": "Feature",
  "properties": {
    "addr:full":"Bracebridge ON P1L 1Z6",
    "addr:postcode":"p1l 1z6",
    "iso:country":"CA",
    "sg:city":"Bracebridge",
    "sg:classifiers":[
        {
            "category":"Wholesale",
            "subcategory":"Electrical",
            "type":"Manufacturing & Wholesale Goods"
        }
    ],
    "sg:phone":"+1 705 645 7200",
    "sg:postcode":"P1L 1Z6",
    "sg:province":"ON",
    "sg:tags":[
        "equipment",
        "electric",
        "supply"
    ],
    "wof:name":"Nedco",
    "wof:placetype":"venue"
},
  "geometry": {"coordinates":[-79.31540699999999,45.015606],"type":"Point"}
}