{
  "type": "Feature",
  "properties": {
    "addr:full":"362 Ripley St New Waterford NS B1H 2Z6",
    "addr:housenumber":"362",
    "addr:postcode":"b1h 2z6",
    "addr:street":"Ripley St",
    "iso:country":"CA",
    "sg:address":"362 Ripley St",
    "sg:city":"New Waterford",
    "sg:classifiers":[
        {
            "category":"Freight",
            "type":"Transportation"
        }
    ],
    "sg:phone":"+1 902 862 6168",
    "sg:postcode":"B1H 2Z6",
    "sg:province":"NS",
    "sg:tags":[
        "trucking"
    ],
    "wof:name":"Connell's Trucking",
    "wof:placetype":"venue"
},
  "geometry": {"coordinates":[-60.09441,46.253304],"type":"Point"}
}