{
  "type": "Feature",
  "properties": {
    "addr:full":"2135 Dundas St W Toronto ON M6R 1X1",
    "addr:housenumber":"2135",
    "addr:postcode":"m6r 1x1",
    "addr:street":"Dundas St W",
    "iso:country":"CA",
    "sg:address":"2135 Dundas St W",
    "sg:city":"Toronto",
    "sg:classifiers":[
        {
            "category":"Food & Beverages",
            "subcategory":"Liquor & Beverages",
            "type":"Retail Goods"
        }
    ],
    "sg:phone":"+1 416 531 6512",
    "sg:postcode":"M6R 1X1",
    "sg:province":"ON",
    "sg:tags":[
        "beer",
        "ale"
    ],
    "wof:name":"Beer Store",
    "wof:placetype":"venue"
},
  "geometry": {"coordinates":[-79.449699,43.652725],"type":"Point"}
}