{
  "type": "Feature",
  "properties": {
    "addr:full":"40 Ironside Cres Scarborough ON M1X 1G4",
    "addr:housenumber":"40",
    "addr:postcode":"m1x 1g4",
    "addr:street":"Ironside Cres",
    "iso:country":"CA",
    "sg:address":"40 Ironside Cres",
    "sg:city":"Scarborough",
    "sg:classifiers":[
        {
            "category":"Manufacturing",
            "subcategory":"Tools & Machinery",
            "type":"Manufacturing & Wholesale Goods"
        }
    ],
    "sg:phone":"+1 416 412 2009",
    "sg:postcode":"M1X 1G4",
    "sg:province":"ON",
    "sg:tags":[
        "equipment",
        "hospital",
        "supply"
    ],
    "wof:name":"Norpak Mfg",
    "wof:placetype":"venue"
},
  "geometry": {"coordinates":[-79.24698600000001,43.825985],"type":"Point"}
}