{
  "type": "Feature",
  "properties": {
    "addr:full":"3300 2nd St E Cornwall ON K6H 6J8",
    "addr:housenumber":"3300",
    "addr:postcode":"k6h 6j8",
    "addr:street":"2Nd St E",
    "iso:country":"CA",
    "sg:address":"3300 2nd St E",
    "sg:city":"Cornwall",
    "sg:classifiers":[
        {
            "category":"Wholesale",
            "subcategory":"Vending Machines",
            "type":"Manufacturing & Wholesale Goods"
        }
    ],
    "sg:phone":"+1 613 933 5555",
    "sg:postcode":"K6H 6J8",
    "sg:province":"ON",
    "sg:tags":[
        "break",
        "coffee",
        "supply"
    ],
    "wof:name":"Glen Fine Foods",
    "wof:placetype":"venue"
},
  "geometry": {"coordinates":[-74.6853027344,45.0346717834],"type":"Point"}
}