{
  "type": "Feature",
  "properties": {
    "iso:country":"CA",
    "sg:address":"8545 Boul DE LA Rive-Sud",
    "sg:city":"Levis",
    "sg:classifiers":[
        {
            "category":"Manufacturing",
            "subcategory":"Metals",
            "type":"Manufacturing & Wholesale Goods"
        }
    ],
    "sg:phone":"+1 418 837 6170",
    "sg:postcode":"G6V 8V7",
    "sg:province":"QC",
    "sg:tags":[
        "shelter",
        "garage",
        "canopy",
        "temporary",
        "awning"
    ],
    "wof:name":"Atelier DE Toile Levis",
    "wof:placetype":"venue"
},
  "geometry": {"coordinates":[-71.13223266599999,46.8205413818],"type":"Point"}
}