{
  "type": "Feature",
  "properties": {
    "iso:country":"CA",
    "sg:address":"78 Rue Provost",
    "sg:city":"Chateauguay",
    "sg:classifiers":[
        {
            "category":"Manufacturing",
            "subcategory":"Tools & Machinery",
            "type":"Manufacturing & Wholesale Goods"
        }
    ],
    "sg:phone":"+1 450 698 1923",
    "sg:postcode":"J6J 2Y5",
    "sg:province":"QC",
    "sg:tags":[
        "lubricating",
        "system",
        "devices"
    ],
    "wof:name":"Chateauguay Pompes & Rsrvrs",
    "wof:placetype":"venue"
},
  "geometry": {"coordinates":[-73.75871276860001,45.3717041016],"type":"Point"}
}