{
  "type": "Feature",
  "properties": {
    "iso:country":"CA",
    "sg:city":"Salaberry-DE-Valleyfield",
    "sg:classifiers":[
        {
            "category":"Insurance",
            "subcategory":"Life Insurance",
            "type":"Services"
        }
    ],
    "sg:phone":"+1 450 371 2528",
    "sg:postcode":"J6T 2C9",
    "sg:province":"QC",
    "sg:tags":[
        "accountant"
    ],
    "wof:name":"Nelson Robert Courtier D'Asrnc",
    "wof:placetype":"venue"
},
  "geometry": {"coordinates":[-74.127022,45.254356],"type":"Point"}
}