{
  "type": "Feature",
  "properties": {
    "iso:country":"CA",
    "sg:address":"35 Eglinton Sq",
    "sg:city":"Scarborough",
    "sg:classifiers":[
        {
            "category":"Personal",
            "subcategory":"Beauty Salon",
            "type":"Services"
        }
    ],
    "sg:phone":"+1 416 757 8708",
    "sg:postcode":"M1L 2K1",
    "sg:province":"ON",
    "wof:name":"Creative Concepts in Hair Dsgn",
    "wof:placetype":"venue"
},
  "geometry": {"coordinates":[-79.3016281128,43.7234764099],"type":"Point"}
}