{
  "type": "Feature",
  "properties": {
    "addr:full":"1562 Queen St W Toronto ON M6R 1A6",
    "addr:housenumber":"1562",
    "addr:postcode":"m6r 1a6",
    "addr:street":"Queen St W",
    "iso:country":"CA",
    "sg:address":"1562 Queen St W",
    "sg:city":"Toronto",
    "sg:classifiers":[
        {
            "category":"Home & Garden",
            "subcategory":"Carpets & Floor Coverings",
            "type":"Retail Goods"
        }
    ],
    "sg:phone":"+1 416 536 7875",
    "sg:postcode":"M6R 1A6",
    "sg:province":"ON",
    "sg:tags":[
        "dealer",
        "rug"
    ],
    "wof:name":"M & M Carpets",
    "wof:placetype":"venue"
},
  "geometry": {"coordinates":[-79.44032300000001,43.639999],"type":"Point"}
}