{
  "type": "Feature",
  "properties": {
    "addr:full":"2553 Severn Ave Ottawa ON K2B 7V8",
    "addr:housenumber":"2553",
    "addr:postcode":"k2b 7v8",
    "addr:street":"Severn Ave",
    "iso:country":"CA",
    "sg:address":"2553 Severn Ave",
    "sg:city":"Ottawa",
    "sg:classifiers":[
        {
            "category":"Education",
            "subcategory":"School",
            "type":"Public Place"
        }
    ],
    "sg:phone":"+1 613 829 8082",
    "sg:postcode":"K2B 7V8",
    "sg:province":"ON",
    "wof:name":"Severn Avenue Public School",
    "wof:placetype":"venue"
},
  "geometry": {"coordinates":[-75.783073,45.356945],"type":"Point"}
}