{
  "type": "Feature",
  "properties": {
    "addr:full":"1014 Main St Saskatoon SK S7H 0K7",
    "addr:housenumber":"1014",
    "addr:postcode":"s7h 0k7",
    "addr:street":"Main St",
    "iso:country":"CA",
    "sg:address":"1014 Main St",
    "sg:city":"Saskatoon",
    "sg:classifiers":[
        {
            "category":"Wholesale",
            "subcategory":"Machinery & Supplies",
            "type":"Manufacturing & Wholesale Goods"
        }
    ],
    "sg:phone":"+1 306 343 9434",
    "sg:postcode":"S7H 0K7",
    "sg:province":"SK",
    "sg:tags":[
        "contractor"
    ],
    "wof:name":"Maverick Heaters",
    "wof:placetype":"venue"
},
  "geometry": {"coordinates":[-106.645927,52.116482],"type":"Point"}
}