{
  "type": "Feature",
  "properties": {
    "addr:full":"1072 2E Av Pointe-Aux-Trembles QC H1B 4R5",
    "addr:housenumber":"1072",
    "addr:postcode":"h1b 4r5",
    "addr:street":"2E Av",
    "iso:country":"CA",
    "sg:address":"1072 2E Av",
    "sg:city":"Pointe-Aux-Trembles",
    "sg:classifiers":[
        {
            "category":"Building & Trades",
            "subcategory":"Construction",
            "type":"Services"
        }
    ],
    "sg:phone":"+1 514 645 3734",
    "sg:postcode":"H1B 4R5",
    "sg:province":"QC",
    "sg:tags":[
        "roofing",
        "contractor"
    ],
    "wof:name":"A R Super Couvreur Inc",
    "wof:placetype":"venue"
},
  "geometry": {"coordinates":[-73.50084699999999,45.635441],"type":"Point"}
}