{
  "type": "Feature",
  "properties": {
    "iso:country":"CA",
    "sg:city":"Cochrane",
    "sg:classifiers":[
        {
            "category":"Wholesale",
            "subcategory":"Machinery & Supplies",
            "type":"Manufacturing & Wholesale Goods"
        }
    ],
    "sg:phone":"+1 705 272 4008",
    "sg:postcode":"P0L 1C0",
    "sg:province":"ON",
    "sg:tags":[
        "farm",
        "equipment"
    ],
    "wof:name":"Cochrane Farm & Ind Equipment",
    "wof:placetype":"venue"
},
  "geometry": {"coordinates":[-81.02895355219999,49.0652198792],"type":"Point"}
}