{
  "type": "Feature",
  "properties": {
    "addr:full":"2970 Rue Omer-Ravary Montreal QC H1W 3Z6",
    "addr:housenumber":"2970",
    "addr:postcode":"h1w 3z6",
    "addr:street":"Rue Omer-Ravary",
    "iso:country":"CA",
    "sg:address":"2970 Rue Omer-Ravary",
    "sg:city":"Montreal",
    "sg:classifiers":[
        {
            "category":"Manufacturing",
            "subcategory":"Rubber & Plastics",
            "type":"Manufacturing & Wholesale Goods"
        }
    ],
    "sg:phone":"+1 514 528 8608",
    "sg:postcode":"H1W 3Z6",
    "sg:province":"QC",
    "sg:tags":[
        "recreational",
        "surface"
    ],
    "wof:name":"Groupe Belea Inc",
    "wof:placetype":"venue"
},
  "geometry": {"coordinates":[-73.544724,45.53669],"type":"Point"}
}