{
  "type": "Feature",
  "properties": {
    "addr:full":"2936 Bloor St W Etobicoke ON M8X 1B6",
    "addr:housenumber":"2936",
    "addr:postcode":"m8x 1b6",
    "addr:street":"Bloor St W",
    "iso:country":"CA",
    "sg:address":"2936 Bloor St W",
    "sg:city":"Etobicoke",
    "sg:classifiers":[
        {
            "category":"Restaurant",
            "type":"Food & Drink"
        }
    ],
    "sg:phone":"+1 416 239 3812",
    "sg:postcode":"M8X 1B6",
    "sg:province":"ON",
    "wof:name":"Old Sod Pub",
    "wof:placetype":"venue"
},
  "geometry": {"coordinates":[-79.50750732420001,43.6483802795],"type":"Point"}
}