{
  "type": "Feature",
  "properties": {
    "addr:full":"25907 Woodbine Ave Keswick ON L4P 3E9",
    "addr:housenumber":"25907",
    "addr:postcode":"l4p 3e9",
    "addr:street":"Woodbine Ave",
    "iso:country":"CA",
    "sg:address":"25907 Woodbine Ave",
    "sg:city":"Keswick",
    "sg:classifiers":[
        {
            "category":"Retail",
            "subcategory":"Auto Repair",
            "type":"Services"
        }
    ],
    "sg:phone":"+1 905 476 7795",
    "sg:postcode":"L4P 3E9",
    "sg:province":"ON",
    "sg:tags":[
        "repairing",
        "automobile",
        "tire"
    ],
    "wof:name":"Dave's Custom Exhaust & Auto",
    "wof:placetype":"venue"
},
  "geometry": {"coordinates":[-79.4586181641,44.2742538452],"type":"Point"}
}