{
  "type": "Feature",
  "properties": {
    "addr:full":"Surrey BC V3S 6J8",
    "addr:postcode":"v3s 6j8",
    "iso:country":"CA",
    "sg:city":"Surrey",
    "sg:classifiers":[
        {
            "category":"Wholesale",
            "subcategory":"Auto Parts",
            "type":"Manufacturing & Wholesale Goods"
        }
    ],
    "sg:phone":"+1 604 530 5622",
    "sg:postcode":"V3S 6J8",
    "sg:province":"BC",
    "sg:tags":[
        "body",
        "paint",
        "shop",
        "automobile"
    ],
    "wof:name":"Valley Carcolor Inc",
    "wof:placetype":"venue"
},
  "geometry": {"coordinates":[-122.688682556,49.1079406738],"type":"Point"}
}