{
  "type": "Feature",
  "properties": {
    "iso:country":"CA",
    "sg:address":"284 Queen St E",
    "sg:city":"Brampton",
    "sg:classifiers":[
        {
            "category":"Professional",
            "subcategory":"Employment Agencies",
            "type":"Services"
        }
    ],
    "sg:phone":"+1 905 454 4972",
    "sg:postcode":"L6V 1C2",
    "sg:province":"ON",
    "sg:tags":[
        "help",
        "contractor"
    ],
    "wof:name":"Aimco Labour Lease Inc",
    "wof:placetype":"venue"
},
  "geometry": {"coordinates":[-79.7455215454,43.6993598938],"type":"Point"}
}