{
  "type": "Feature",
  "properties": {
    "addr:full":"635 Danforth Ave Toronto ON M4K 1R2",
    "addr:housenumber":"635",
    "addr:postcode":"m4k 1r2",
    "addr:street":"Danforth Ave",
    "iso:country":"CA",
    "sg:address":"635 Danforth Ave",
    "sg:city":"Toronto",
    "sg:classifiers":[
        {
            "category":"Banks & Credit Unions",
            "subcategory":"Investment Brokerage",
            "type":"Services"
        }
    ],
    "sg:phone":"+1 416 405 8003",
    "sg:postcode":"M4K 1R2",
    "sg:province":"ON",
    "sg:tags":[
        "cafe"
    ],
    "wof:name":"Palladium Bar Grill & Catering",
    "wof:placetype":"venue"
},
  "geometry": {"coordinates":[-79.3453674316,43.6786422729],"type":"Point"}
}