{
  "type": "Feature",
  "properties": {
    "addr:full":"Marshall SK S0M 1R0",
    "addr:postcode":"s0m 1r0",
    "addr:street":"Marshall",
    "iso:country":"CA",
    "sg:city":"Marshall",
    "sg:classifiers":[
        {
            "category":"Mining & Drilling",
            "type":"Manufacturing & Wholesale Goods"
        }
    ],
    "sg:phone":"+1 306 387 6264",
    "sg:postcode":"S0M 1R0",
    "sg:province":"SK",
    "sg:tags":[
        "splicing",
        "oil",
        "installation",
        "cable",
        "well",
        "detection"
    ],
    "wof:name":"Line Finders Ltd",
    "wof:placetype":"venue"
},
  "geometry": {"coordinates":[-109.78119700000001,53.191864],"type":"Point"}
}