{
  "type": "Feature",
  "properties": {
    "iso:country":"CA",
    "sg:address":"4515 Gateway Blvd NW",
    "sg:city":"Edmonton",
    "sg:classifiers":[
        {
            "category":"Utilities",
            "subcategory":"Mobile Phone",
            "type":"Services"
        }
    ],
    "sg:phone":"+1 780 437 0888",
    "sg:postcode":"T6H 5C3",
    "sg:province":"AB",
    "sg:tags":[
        "telephone",
        "cellular"
    ],
    "wof:name":"Tac Mobility",
    "wof:placetype":"venue"
},
  "geometry": {"coordinates":[-113.49140167199999,53.4835357666],"type":"Point"}
}