{
  "type": "Feature",
  "properties": {
    "addr:full":"9149 Webster Rd Glencairn ON L0M 1K0",
    "addr:housenumber":"9149",
    "addr:postcode":"l0m 1k0",
    "addr:street":"Webster Rd",
    "iso:country":"CA",
    "sg:address":"9149 Webster Rd",
    "sg:city":"Glencairn",
    "sg:classifiers":[
        {
            "category":"Manufacturing",
            "subcategory":"Glass & Minerals",
            "type":"Manufacturing & Wholesale Goods"
        }
    ],
    "sg:phone":"+1 705 466 2908",
    "sg:postcode":"L0M 1K0",
    "sg:province":"ON",
    "sg:tags":[
        "refractory"
    ],
    "wof:name":"Stayner Precast & Supplies",
    "wof:placetype":"venue"
},
  "geometry": {"coordinates":[-80.0305175781,44.3056716919],"type":"Point"}
}