{
  "type": "Feature",
  "properties": {
    "addr:full":"Quebec QC G1K 4K1",
    "addr:postcode":"g1k 4k1",
    "iso:country":"CA",
    "sg:city":"Quebec",
    "sg:classifiers":[
        {
            "category":"Government",
            "subcategory":"Office",
            "type":"Public Place"
        }
    ],
    "sg:phone":"+1 418 648 3111",
    "sg:postcode":"G1K 4K1",
    "sg:province":"QC",
    "wof:name":"Canada Protection Civile",
    "wof:placetype":"venue"
},
  "geometry": {"coordinates":[-71.222092,46.79504],"type":"Point"}
}