{
  "type": "Feature",
  "properties": {
    "addr:full":"20 Archibald Ave North Sydney NS B2A 2W3",
    "addr:housenumber":"20",
    "addr:postcode":"b2a 2w3",
    "addr:street":"Archibald Ave",
    "iso:country":"CA",
    "sg:address":"20 Archibald Ave",
    "sg:city":"North Sydney",
    "sg:classifiers":[
        {
            "category":"Retail",
            "subcategory":"Laundry & Dry Cleaning",
            "type":"Services"
        }
    ],
    "sg:phone":"+1 902 794 2312",
    "sg:postcode":"B2A 2W3",
    "sg:province":"NS",
    "sg:tags":[
        "cleaners"
    ],
    "wof:name":"Cameron Cleaners",
    "wof:placetype":"venue"
},
  "geometry": {"coordinates":[-60.250069,46.209858],"type":"Point"}
}