{
  "type": "Feature",
  "properties": {
    "addr:full":"35 Joseph St Parry Sound ON P2A 2G3",
    "addr:housenumber":"35",
    "addr:postcode":"p2a 2g3",
    "addr:street":"Joseph St",
    "iso:country":"CA",
    "sg:address":"35 Joseph St",
    "sg:city":"Parry Sound",
    "sg:classifiers":[
        {
            "category":"Retail",
            "subcategory":"Veterinary Services",
            "type":"Services"
        }
    ],
    "sg:phone":"+1 705 746 9884",
    "sg:postcode":"P2A 2G3",
    "sg:province":"ON",
    "sg:tags":[
        "veterinarian"
    ],
    "wof:name":"Parry Sound Animal Hospital",
    "wof:placetype":"venue"
},
  "geometry": {"coordinates":[-80.039047,45.357731],"type":"Point"}
}