{
  "type": "Feature",
  "properties": {
    "addr:full":"83 Woodgreen Dr SW Calgary AB T2W 4G6",
    "addr:housenumber":"83",
    "addr:postcode":"t2w 4g6",
    "addr:street":"Woodgreen Dr Sw",
    "iso:country":"CA",
    "sg:address":"83 Woodgreen Dr SW",
    "sg:city":"Calgary",
    "sg:classifiers":[
        {
            "category":"Shopping",
            "type":"Retail Goods"
        }
    ],
    "sg:phone":"+1 403 251 6475",
    "sg:postcode":"T2W 4G6",
    "sg:province":"AB",
    "sg:tags":[
        "stamp",
        "collector",
        "for"
    ],
    "wof:name":"R D Miner Philatelics",
    "wof:placetype":"venue"
},
  "geometry": {"coordinates":[-114.107597,50.938213],"type":"Point"}
}