{
  "type": "Feature",
  "properties": {
    "addr:full":"20 Forest Trail Gormley ON L0H 1G0",
    "addr:housenumber":"20",
    "addr:postcode":"l0h 1g0",
    "addr:street":"Forest Trail",
    "iso:country":"CA",
    "sg:address":"20 Forest Trail",
    "sg:city":"Gormley",
    "sg:classifiers":[
        {
            "category":"Wholesale",
            "subcategory":"Machinery & Supplies",
            "type":"Manufacturing & Wholesale Goods"
        }
    ],
    "sg:phone":"+1 905 726 3116",
    "sg:postcode":"L0H 1G0",
    "sg:province":"ON",
    "sg:tags":[
        "equipment",
        "irrigation",
        "system",
        "sprinkler"
    ],
    "wof:name":"Solujan Irrigation Inc",
    "wof:placetype":"venue"
},
  "geometry": {"coordinates":[-79.37786865229999,44.0072364807],"type":"Point"}
}