{
  "type": "Feature",
  "properties": {
    "iso:country":"CA",
    "sg:address":"764 Rue Principale",
    "sg:city":"Neguac",
    "sg:classifiers":[
        {
            "category":"Manufacturing",
            "subcategory":"Food",
            "type":"Manufacturing & Wholesale Goods"
        }
    ],
    "sg:phone":"+1 506 776 3050",
    "sg:postcode":"E9G 1N5",
    "sg:province":"NB",
    "sg:tags":[
        "product",
        "seafood",
        "fish",
        "prepared"
    ],
    "wof:name":"Neguac Seafoods",
    "wof:placetype":"venue"
},
  "geometry": {"coordinates":[-65.082382,47.244549],"type":"Point"}
}