{
  "type": "Feature",
  "properties": {
    "addr:full":"185 Somerset St W #201B Ottawa ON K2P 0J2",
    "addr:housenumber":"185",
    "addr:postcode":"k2p 0j2",
    "addr:street":"Somerset St W # 201B",
    "iso:country":"CA",
    "sg:address":"185 Somerset St W #201B",
    "sg:city":"Ottawa",
    "sg:classifiers":[
        {
            "category":"Real Estate",
            "subcategory":"Real Estate Agent",
            "type":"Services"
        }
    ],
    "sg:phone":"+1 613 233 8188",
    "sg:postcode":"K2P 0J2",
    "sg:province":"ON",
    "wof:name":"Shaker Realty Ltd",
    "wof:placetype":"venue"
},
  "geometry": {"coordinates":[-75.6909332275,45.4177894592],"type":"Point"}
}