{
  "type": "Feature",
  "properties": {
    "iso:country":"CA",
    "sg:city":"Winnipeg",
    "sg:classifiers":[
        {
            "category":"Government",
            "subcategory":"Office",
            "type":"Public Place"
        }
    ],
    "sg:phone":"+1 204 945 3096",
    "sg:postcode":"R2H 0C4",
    "sg:province":"MB",
    "wof:name":"Manitoba Translation Svc",
    "wof:placetype":"venue"
},
  "geometry": {"coordinates":[-97.121841,49.894367],"type":"Point"}
}