{
  "type": "Feature",
  "properties": {
    "addr:full":"3435 Ninth St St Catharines ON L2R 6P7",
    "addr:housenumber":"3435",
    "addr:postcode":"l2r 6p7",
    "addr:street":"Ninth St",
    "iso:country":"CA",
    "sg:address":"3435 Ninth St",
    "sg:city":"St Catharines",
    "sg:classifiers":[
        {
            "category":"Manufacturing",
            "subcategory":"Tools & Machinery",
            "type":"Manufacturing & Wholesale Goods"
        }
    ],
    "sg:phone":"+1 905 682 6586",
    "sg:postcode":"L2R 6P7",
    "sg:province":"ON",
    "sg:tags":[
        "machine",
        "shop"
    ],
    "wof:name":"Rockway Precision Machine",
    "wof:placetype":"venue"
},
  "geometry": {"coordinates":[-79.24867248539999,43.1563339233],"type":"Point"}
}