{
  "type": "Feature",
  "properties": {
    "addr:full":"Pickering ON L1V 4G6",
    "addr:postcode":"l1v 4g6",
    "iso:country":"CA",
    "sg:city":"Pickering",
    "sg:classifiers":[
        {
            "category":"Personal",
            "subcategory":"Shoe Repair & Shine",
            "type":"Services"
        }
    ],
    "sg:phone":"+1 905 831 6479",
    "sg:postcode":"L1V 4G6",
    "sg:province":"ON",
    "sg:tags":[
        "repairing",
        "boot"
    ],
    "wof:name":"Shoe Doctor Quality Shoe Rpr",
    "wof:placetype":"venue"
},
  "geometry": {"coordinates":[-79.089668,43.833164],"type":"Point"}
}