{
  "type": "Feature",
  "properties": {
    "addr:full":"4820 3rd Ave Edson AB T7E 1T8",
    "addr:housenumber":"4820",
    "addr:postcode":"t7e 1t8",
    "addr:street":"3Rd Ave",
    "iso:country":"CA",
    "sg:address":"4820 3rd Ave",
    "sg:city":"Edson",
    "sg:classifiers":[
        {
            "category":"Manufacturing",
            "subcategory":"Printing",
            "type":"Manufacturing & Wholesale Goods"
        }
    ],
    "sg:phone":"+1 780 723 3301",
    "sg:postcode":"T7E 1T8",
    "sg:province":"AB",
    "sg:tags":[
        "newspaper"
    ],
    "wof:name":"Edson Leader",
    "wof:placetype":"venue"
},
  "geometry": {"coordinates":[-116.427177,53.583427],"type":"Point"}
}