{
  "type": "Feature",
  "properties": {
    "addr:full":"1414 Rue Shefford Bromont QC J2L 1E1",
    "addr:housenumber":"1414",
    "addr:postcode":"j2l 1e1",
    "addr:street":"Rue Shefford",
    "iso:country":"CA",
    "sg:address":"1414 Rue Shefford",
    "sg:city":"Bromont",
    "sg:classifiers":[
        {
            "category":"Manufacturing",
            "subcategory":"Signs",
            "type":"Manufacturing & Wholesale Goods"
        }
    ],
    "sg:phone":"+1 450 534 3119",
    "sg:postcode":"J2L 1E1",
    "sg:province":"QC",
    "wof:name":"Enseignes Choquette Enr",
    "wof:placetype":"venue"
},
  "geometry": {"coordinates":[-72.684578,45.302807],"type":"Point"}
}