{
  "type": "Feature",
  "properties": {
    "addr:full":"16 Evergreen Dr Dartmouth NS B2W 4A7",
    "addr:housenumber":"16",
    "addr:postcode":"b2w 4a7",
    "addr:street":"Evergreen Dr",
    "iso:country":"CA",
    "sg:address":"16 Evergreen Dr",
    "sg:city":"Dartmouth",
    "sg:classifiers":[
        {
            "category":"Education",
            "subcategory":"School",
            "type":"Public Place"
        }
    ],
    "sg:phone":"+1 902 464 5140",
    "sg:postcode":"B2W 4A7",
    "sg:province":"NS",
    "wof:name":"Sir Robert Borden Jr High Schl",
    "wof:placetype":"venue"
},
  "geometry": {"coordinates":[-63.497192,44.674973],"type":"Point"}
}