{
  "type": "Feature",
  "properties": {
    "addr:full":"3915 Rue DE Rouen Montreal QC H1W 1N2",
    "addr:housenumber":"3915",
    "addr:postcode":"h1w 1n2",
    "addr:street":"Rue De Rouen",
    "iso:country":"CA",
    "sg:address":"3915 Rue DE Rouen",
    "sg:city":"Montreal",
    "sg:classifiers":[
        {
            "category":"Retail",
            "subcategory":"Auto Repair",
            "type":"Services"
        }
    ],
    "sg:phone":"+1 514 990 1400",
    "sg:postcode":"H1W 1N2",
    "sg:province":"QC",
    "sg:tags":[
        "repairing",
        "exhaust",
        "tire",
        "automobile",
        "system",
        "muffler"
    ],
    "wof:name":"Monsieur Muffler",
    "wof:placetype":"venue"
},
  "geometry": {"coordinates":[-73.546211,45.549576],"type":"Point"}
}