{
  "type": "Feature",
  "properties": {
    "addr:full":"6607 Line 66 Monkton ON N0K 1P0",
    "addr:housenumber":"6607",
    "addr:postcode":"n0k 1p0",
    "addr:street":"Line 66",
    "iso:country":"CA",
    "sg:address":"6607 Line 66",
    "sg:city":"Monkton",
    "sg:classifiers":[
        {
            "category":"Wholesale",
            "subcategory":"Auto Parts",
            "type":"Manufacturing & Wholesale Goods"
        }
    ],
    "sg:phone":"+1 519 887 9401",
    "sg:postcode":"N0K 1P0",
    "sg:province":"ON",
    "sg:tags":[
        "automobile",
        "rebuilt"
    ],
    "wof:name":"C J Truck & Auto Parts Ltd",
    "wof:placetype":"venue"
},
  "geometry": {"coordinates":[-81.07435599999999,43.634041],"type":"Point"}
}