{
  "type": "Feature",
  "properties": {
    "addr:full":"245 Rue Commerciale E Chandler QC G0C 1K0",
    "addr:housenumber":"245",
    "addr:postcode":"g0c 1k0",
    "addr:street":"Rue Commerciale E",
    "iso:country":"CA",
    "sg:address":"245 Rue Commerciale E",
    "sg:city":"Chandler",
    "sg:classifiers":[
        {
            "category":"Manufacturing",
            "subcategory":"Tools & Machinery",
            "type":"Manufacturing & Wholesale Goods"
        }
    ],
    "sg:phone":"+1 418 689 3401",
    "sg:postcode":"G0C 1K0",
    "sg:province":"QC",
    "sg:tags":[
        "machine",
        "shop",
        "welding"
    ],
    "wof:name":"Usinage Micron",
    "wof:placetype":"venue"
},
  "geometry": {"coordinates":[-64.665054,48.349041],"type":"Point"}
}