{
  "type": "Feature",
  "properties": {
    "addr:full":"13547 67A Ave Surrey BC V3W 2C1",
    "addr:housenumber":"13547",
    "addr:postcode":"v3w 2c1",
    "addr:street":"67A Ave",
    "iso:country":"CA",
    "sg:address":"13547 67A Ave",
    "sg:city":"Surrey",
    "sg:classifiers":[
        {
            "category":"Wholesale",
            "subcategory":"Office Equipment",
            "type":"Manufacturing & Wholesale Goods"
        }
    ],
    "sg:phone":"+1 604 599 0477",
    "sg:postcode":"V3W 2C1",
    "sg:province":"BC",
    "sg:tags":[
        "scanning",
        "code",
        "bar"
    ],
    "wof:name":"Western Bar Code Industries",
    "wof:placetype":"venue"
},
  "geometry": {"coordinates":[-122.830215454,49.105178833],"type":"Point"}
}