{
  "type": "Feature",
  "properties": {
    "iso:country":"CA",
    "sg:city":"Courtenay",
    "sg:classifiers":[
        {
            "category":"Retail",
            "subcategory":"Laundry & Dry Cleaning",
            "type":"Services"
        }
    ],
    "sg:phone":"+1 250 334 4772",
    "sg:postcode":"V9N 3R6",
    "sg:province":"BC",
    "sg:tags":[
        "cleaners"
    ],
    "wof:name":"Comox Valley Cleaners",
    "wof:placetype":"venue"
},
  "geometry": {"coordinates":[-124.987388611,49.6986656189],"type":"Point"}
}