{
  "type": "Feature",
  "properties": {
    "addr:full":"Burlington ON L7L 6M6",
    "addr:postcode":"l7l 6m6",
    "iso:country":"CA",
    "sg:city":"Burlington",
    "sg:classifiers":[
        {
            "category":"Health Services",
            "subcategory":"Doctor",
            "type":"Services"
        }
    ],
    "sg:phone":"+1 905 315 9888",
    "sg:postcode":"L7L 6M6",
    "sg:province":"ON",
    "sg:tags":[
        "dentist"
    ],
    "wof:name":"Millcroft Dental Care",
    "wof:placetype":"venue"
},
  "geometry": {"coordinates":[-79.7913513184,43.394405365],"type":"Point"}
}