{
  "type": "Feature",
  "properties": {
    "addr:full":"4128 Industrial Ave Onoway AB T0E 1V0",
    "addr:housenumber":"4128",
    "addr:postcode":"t0e 1v0",
    "addr:street":"Industrial Ave",
    "iso:country":"CA",
    "sg:address":"4128 Industrial Ave",
    "sg:city":"Onoway",
    "sg:classifiers":[
        {
            "category":"Food & Beverages",
            "subcategory":"Specialty",
            "type":"Retail Goods"
        }
    ],
    "sg:phone":"+1 780 967 6868",
    "sg:postcode":"T0E 1V0",
    "sg:province":"AB",
    "sg:tags":[
        "health",
        "diet"
    ],
    "wof:name":"Generations Packaging & Distr",
    "wof:placetype":"venue"
},
  "geometry": {"coordinates":[-114.1743927,53.7073860168],"type":"Point"}
}