{
  "type": "Feature",
  "properties": {
    "addr:full":"216 1 Ave S Lethbridge AB T1J 0A4",
    "addr:housenumber":"216",
    "addr:postcode":"t1j 0a4",
    "addr:street":"1 Ave S",
    "iso:country":"CA",
    "sg:address":"216 1 Ave S",
    "sg:city":"Lethbridge",
    "sg:classifiers":[
        {
            "category":"Restaurant",
            "type":"Food & Drink"
        }
    ],
    "sg:phone":"+1 403 320 8702",
    "sg:postcode":"T1J 0A4",
    "sg:province":"AB",
    "wof:name":"Arby's",
    "wof:placetype":"venue"
},
  "geometry": {"coordinates":[-112.84439086899999,49.6974716187],"type":"Point"}
}