{
  "type": "Feature",
  "properties": {
    "addr:full":"465 Bord Du Lac Dorval QC H9S 2A9",
    "addr:housenumber":"465",
    "addr:postcode":"h9s 2a9",
    "addr:street":"Bord Du Lac",
    "iso:country":"CA",
    "sg:address":"465 Bord Du Lac",
    "sg:city":"Dorval",
    "sg:classifiers":[
        {
            "category":"Personal",
            "type":"Services"
        }
    ],
    "sg:phone":"+1 514 631 4757",
    "sg:postcode":"H9S 2A9",
    "sg:province":"QC",
    "sg:tags":[
        "electrolysis"
    ],
    "wof:name":"Angele Flibotte Esthetique",
    "wof:placetype":"venue"
},
  "geometry": {"coordinates":[-73.7312545776,45.440788269],"type":"Point"}
}