{
  "type": "Feature",
  "properties": {
    "addr:full":"607 Queen St W Toronto ON M5V 2B7",
    "addr:housenumber":"607",
    "addr:postcode":"m5v 2b7",
    "addr:street":"Queen St W",
    "iso:country":"CA",
    "sg:address":"607 Queen St W",
    "sg:city":"Toronto",
    "sg:classifiers":[
        {
            "category":"Restaurant",
            "type":"Food & Drink"
        }
    ],
    "sg:phone":"+1 416 504 2269",
    "sg:postcode":"M5V 2B7",
    "sg:province":"ON",
    "wof:name":"Ali Baba's Restaurant",
    "wof:placetype":"venue"
},
  "geometry": {"coordinates":[-79.402168,43.647423],"type":"Point"}
}