{
  "type": "Feature",
  "properties": {
    "iso:country":"CA",
    "sg:address":"4589 Rue Sainte-Catherine E",
    "sg:city":"Montreal",
    "sg:classifiers":[
        {
            "category":"Social Services",
            "type":"Services"
        }
    ],
    "sg:phone":"+1 514 255 8444",
    "sg:postcode":"H1V 1Y8",
    "sg:province":"QC",
    "sg:tags":[
        "organization",
        "welfare",
        "crisis",
        "intervention"
    ],
    "wof:name":"Carre Inc",
    "wof:placetype":"venue"
},
  "geometry": {"coordinates":[-73.53244,45.553486],"type":"Point"}
}