{
  "type": "Feature",
  "properties": {
    "addr:full":"194 Highland St Haliburton ON K0M 1S0",
    "addr:housenumber":"194",
    "addr:postcode":"k0m 1s0",
    "addr:street":"Highland St",
    "iso:country":"CA",
    "sg:address":"194 Highland St",
    "sg:city":"Haliburton",
    "sg:classifiers":[
        {
            "category":"Banks & Credit Unions",
            "subcategory":"Bank",
            "type":"Services"
        }
    ],
    "sg:phone":"+1 705 457 1240",
    "sg:postcode":"K0M 1S0",
    "sg:province":"ON",
    "wof:name":"Bank of Montreal",
    "wof:placetype":"venue"
},
  "geometry": {"coordinates":[-78.5088424683,45.0463104248],"type":"Point"}
}