{
  "type": "Feature",
  "properties": {
    "addr:full":"80 Av Laurier E Montreal QC H2T 1E5",
    "addr:postcode":"h2t 1e5",
    "addr:street":"80 Av Laurier E",
    "iso:country":"CA",
    "sg:address":"80 Av Laurier E",
    "sg:city":"Montreal",
    "sg:classifiers":[
        {
            "category":"Real Estate",
            "subcategory":"Real Estate Agent",
            "type":"Services"
        }
    ],
    "sg:phone":"+1 514 278 1135",
    "sg:postcode":"H2T 1E5",
    "sg:province":"QC",
    "sg:tags":[
        "management"
    ],
    "wof:name":"Franamarc Inc",
    "wof:placetype":"venue"
},
  "geometry": {"coordinates":[-73.59195699999999,45.523769],"type":"Point"}
}