{
  "type": "Feature",
  "properties": {
    "addr:full":"53 Main St S Seaforth ON N0K 1W0",
    "addr:housenumber":"53",
    "addr:postcode":"n0k 1w0",
    "addr:street":"Main St S Seaforth",
    "iso:country":"CA",
    "sg:address":"53 Main St S",
    "sg:city":"Seaforth",
    "sg:classifiers":[
        {
            "category":"Home & Garden",
            "subcategory":"Carpets & Floor Coverings",
            "type":"Retail Goods"
        }
    ],
    "sg:phone":"+1 519 527 1728",
    "sg:postcode":"N0K 1W0",
    "sg:province":"ON",
    "sg:tags":[
        "material",
        "rug"
    ],
    "wof:name":"Bluewater Interiors",
    "wof:placetype":"venue"
},
  "geometry": {"coordinates":[-81.39464599999999,43.552174],"type":"Point"}
}