{
  "type": "Feature",
  "properties": {
    "addr:full":"2310 Av Benny Montreal QC H4B 2R4",
    "addr:housenumber":"2310",
    "addr:postcode":"h4b 2r4",
    "addr:street":"Av Benny",
    "iso:country":"CA",
    "sg:address":"2310 Av Benny",
    "sg:city":"Montreal",
    "sg:classifiers":[
        {
            "category":"Professional",
            "type":"Services"
        }
    ],
    "sg:phone":"+1 514 489 6116",
    "sg:postcode":"H4B 2R4",
    "sg:province":"QC",
    "sg:tags":[
        "cigarette",
        "cigar",
        "establishment",
        "dealer",
        "tobacco"
    ],
    "wof:name":"George Weiner Inc",
    "wof:placetype":"venue"
},
  "geometry": {"coordinates":[-73.6241531372,45.4635620117],"type":"Point"}
}