{
  "type": "Feature",
  "properties": {
    "iso:country":"CA",
    "sg:address":"1465 Lecaron Ave",
    "sg:city":"Sarnia",
    "sg:classifiers":[
        {
            "category":"Organizations",
            "subcategory":"Religious Organization",
            "type":"Services"
        }
    ],
    "sg:phone":"+1 519 344 2992",
    "sg:postcode":"N7V 3J4",
    "sg:province":"ON",
    "sg:tags":[
        "church"
    ],
    "wof:name":"Sacred Heart Rectory",
    "wof:placetype":"venue"
},
  "geometry": {"coordinates":[-82.389694,43.007603],"type":"Point"}
}