{
  "type": "Feature",
  "properties": {
    "addr:full":"West Vancouver BC V7T 2W4",
    "addr:postcode":"v7t 2w4",
    "iso:country":"CA",
    "sg:city":"West Vancouver",
    "sg:classifiers":[
        {
            "category":"Professional",
            "subcategory":"Management & Consulting",
            "type":"Services"
        }
    ],
    "sg:phone":"+1 604 921 1350",
    "sg:postcode":"V7T 2W4",
    "sg:province":"BC",
    "sg:tags":[
        "consultant",
        "telecommunication"
    ],
    "wof:name":"Canada Inc",
    "wof:placetype":"venue"
},
  "geometry": {"coordinates":[-123.140136719,49.3245506287],"type":"Point"}
}