{
  "type": "Feature",
  "properties": {
    "addr:full":"5025 Orbitor Dr Mississauga ON L4W 4Y5",
    "addr:housenumber":"5025",
    "addr:postcode":"l4w 4y5",
    "addr:street":"Orbitor Dr",
    "iso:country":"CA",
    "sg:address":"5025 Orbitor Dr",
    "sg:city":"Mississauga",
    "sg:classifiers":[
        {
            "category":"Professional",
            "subcategory":"Computer Services",
            "type":"Services"
        }
    ],
    "sg:phone":"+1 905 629 7775",
    "sg:postcode":"L4W 4Y5",
    "sg:province":"ON",
    "sg:tags":[
        "consultant"
    ],
    "wof:name":"Meta Logic Consulting Inc",
    "wof:placetype":"venue"
},
  "geometry": {"coordinates":[-79.59886899999999,43.656281],"type":"Point"}
}