{
  "type": "Feature",
  "properties": {
    "addr:full":"822 Millwood Rd East York ON M4G 1W4",
    "addr:housenumber":"822",
    "addr:postcode":"m4g 1w4",
    "addr:street":"Millwood Rd",
    "iso:country":"CA",
    "sg:address":"822 Millwood Rd",
    "sg:city":"East York",
    "sg:classifiers":[
        {
            "category":"Organizations",
            "subcategory":"Religious Organization",
            "type":"Services"
        }
    ],
    "sg:phone":"+1 416 425 1253",
    "sg:postcode":"M4G 1W4",
    "sg:province":"ON",
    "sg:tags":[
        "church"
    ],
    "wof:name":"Leaside United Church",
    "wof:placetype":"venue"
},
  "geometry": {"coordinates":[-79.3687133789,43.7050323486],"type":"Point"}
}