{
  "type": "Feature",
  "properties": {
    "iso:country":"CA",
    "sg:address":"134 Kempt",
    "sg:city":"St-Octave",
    "sg:classifiers":[
        {
            "category":"Organizations",
            "subcategory":"Professional Association",
            "type":"Services"
        }
    ],
    "sg:phone":"+1 418 775 2925",
    "sg:postcode":"G0J 3B0",
    "sg:province":"QC",
    "wof:name":"Centre Recreatif",
    "wof:placetype":"venue"
},
  "geometry": {"coordinates":[-68.079788208,48.600818634],"type":"Point"}
}