{
  "type": "Feature",
  "properties": {
    "addr:full":"Mackenzie BC V0J 2C0",
    "addr:postcode":"v0j 2c0",
    "iso:country":"CA",
    "sg:city":"Mackenzie",
    "sg:classifiers":[
        {
            "category":"Building & Trades",
            "subcategory":"Plumbing",
            "type":"Services"
        }
    ],
    "sg:phone":"+1 250 997 3345",
    "sg:postcode":"V0J 2C0",
    "sg:province":"BC",
    "sg:tags":[
        "mechanical",
        "contractor"
    ],
    "wof:name":"Doyon Aero Systems",
    "wof:placetype":"venue"
},
  "geometry": {"coordinates":[-123.12597656200001,55.3116531372],"type":"Point"}
}