{
  "type": "Feature",
  "properties": {
    "addr:full":"4141 Rue King O Sherbrooke QC J1L 1P5",
    "addr:housenumber":"4141",
    "addr:postcode":"j1l 1p5",
    "addr:street":"Rue King O",
    "iso:country":"CA",
    "sg:address":"4141 Rue King O",
    "sg:city":"Sherbrooke",
    "sg:classifiers":[
        {
            "category":"Autos & Motor Vehicles",
            "subcategory":"Automobile Sales",
            "type":"Retail Goods"
        }
    ],
    "sg:phone":"+1 819 563 4466",
    "sg:postcode":"J1L 1P5",
    "sg:province":"QC",
    "sg:tags":[
        "car",
        "dealer"
    ],
    "wof:name":"Automobiles Val Estrie Inc",
    "wof:placetype":"venue"
},
  "geometry": {"coordinates":[-71.96099100000001,45.387306],"type":"Point"}
}