{
  "type": "Feature",
  "properties": {
    "addr:full":"Carleton QC G0C 1J0",
    "addr:postcode":"g0c 1j0",
    "iso:country":"CA",
    "sg:city":"Carleton",
    "sg:classifiers":[
        {
            "category":"Building & Trades",
            "subcategory":"Landscaping Services",
            "type":"Services"
        }
    ],
    "sg:phone":"+1 418 364 6167",
    "sg:postcode":"G0C 1J0",
    "sg:province":"QC",
    "sg:tags":[
        "landscape",
        "contractor"
    ],
    "wof:name":"Amenagements D'Avignon Inc",
    "wof:placetype":"venue"
},
  "geometry": {"coordinates":[-66.1413803101,48.110080719],"type":"Point"}
}