{
  "type": "Feature",
  "properties": {
    "iso:country":"CA",
    "sg:address":"356 Rue Julie",
    "sg:city":"Saint-Eustache",
    "sg:classifiers":[
        {
            "category":"Professional",
            "subcategory":"Engineering",
            "type":"Services"
        }
    ],
    "sg:phone":"+1 514 983 5045",
    "sg:postcode":"J7P 4G9",
    "sg:province":"QC",
    "sg:tags":[
        "vibration",
        "measurement"
    ],
    "wof:name":"Paul Gilles Vibrations Inc",
    "wof:placetype":"venue"
},
  "geometry": {"coordinates":[-73.86818695069999,45.5788002014],"type":"Point"}
}