{
  "type": "Feature",
  "properties": {
    "addr:full":"Calgary AB T2E 7G6",
    "addr:postcode":"t2e 7g6",
    "iso:country":"CA",
    "sg:city":"Calgary",
    "sg:classifiers":[
        {
            "category":"Airport",
            "type":"Transportation"
        }
    ],
    "sg:phone":"+1 403 250 3032",
    "sg:postcode":"T2E 7G6",
    "sg:province":"AB",
    "sg:tags":[
        "aircraft",
        "maintenance"
    ],
    "wof:name":"Condor Aircraft Accessories",
    "wof:placetype":"venue"
},
  "geometry": {"coordinates":[-114.015136719,51.0969963074],"type":"Point"}
}