{
  "type": "Feature",
  "properties": {
    "iso:country":"CA",
    "sg:address":"85 Thorburn Rd",
    "sg:city":"St. John's",
    "sg:classifiers":[
        {
            "category":"Insurance",
            "subcategory":"Insurance Agent",
            "type":"Services"
        }
    ],
    "sg:phone":"+1 709 739 4475",
    "sg:postcode":"A1B 3M2",
    "sg:province":"NL",
    "wof:name":"Pottle, Walter",
    "wof:placetype":"venue"
},
  "geometry": {"coordinates":[-52.758724,47.563213],"type":"Point"}
}