{
  "type": "Feature",
  "properties": {
    "addr:full":"Winnipeg MB R3C 0C4",
    "addr:postcode":"r3c 0c4",
    "iso:country":"CA",
    "sg:city":"Winnipeg",
    "sg:classifiers":[
        {
            "category":"Government",
            "subcategory":"Office",
            "type":"Public Place"
        }
    ],
    "sg:phone":"+1 204 945 2638",
    "sg:postcode":"R3C 0C4",
    "sg:province":"MB",
    "wof:name":"Manitoba Cemetery Operators",
    "wof:placetype":"venue"
},
  "geometry": {"coordinates":[-97.14473,49.892998],"type":"Point"}
}