{
  "type": "Feature",
  "properties": {
    "addr:full":"8 Monrow St Lax Kw'Alaams BC V0V 1H0",
    "addr:housenumber":"8",
    "addr:postcode":"v0v 1h0",
    "addr:street":"Monrow St",
    "iso:country":"CA",
    "sg:address":"8 Monrow St",
    "sg:city":"Lax Kw'Alaams",
    "sg:classifiers":[
        {
            "category":"Organizations",
            "subcategory":"Professional Association",
            "type":"Services"
        }
    ],
    "sg:phone":"+1 250 625 3297",
    "sg:postcode":"V0V 1H0",
    "sg:province":"BC",
    "wof:name":"Allied Tsimshian Tribes Assn",
    "wof:placetype":"venue"
},
  "geometry": {"coordinates":[-126.555511,54.485668],"type":"Point"}
}