{
  "type": "Feature",
  "properties": {
    "iso:country":"CA",
    "sg:city":"London",
    "sg:classifiers":[
        {
            "category":"Insurance",
            "subcategory":"Insurance Agent",
            "type":"Services"
        }
    ],
    "sg:phone":"+1 519 672 6063",
    "sg:postcode":"N6A 5R8",
    "sg:province":"ON",
    "wof:name":"Standard Life Assurance CO",
    "wof:placetype":"venue"
},
  "geometry": {"coordinates":[-81.246635,42.985855],"type":"Point"}
}