{
  "type": "Feature",
  "properties": {
    "addr:full":"31221 Peardonville Rd Abbotsford BC V2T 6K9",
    "addr:housenumber":"31221",
    "addr:postcode":"v2t 6k9",
    "addr:street":"Peardonville Rd",
    "iso:country":"CA",
    "sg:address":"31221 Peardonville Rd",
    "sg:city":"Abbotsford",
    "sg:classifiers":[
        {
            "category":"Restaurant",
            "type":"Food & Drink"
        }
    ],
    "sg:phone":"+1 604 850 5997",
    "sg:postcode":"V2T 6K9",
    "sg:province":"BC",
    "wof:name":"Subway Sandwiches & Salads",
    "wof:placetype":"venue"
},
  "geometry": {"coordinates":[-122.359336853,49.0460281372],"type":"Point"}
}