{
  "type": "Feature",
  "properties": {
    "addr:full":"154 Rue Principale Cowansville QC J2K 1J2",
    "addr:housenumber":"154",
    "addr:postcode":"j2k 1j2",
    "addr:street":"Rue Principale",
    "iso:country":"CA",
    "sg:address":"154 Rue Principale",
    "sg:city":"Cowansville",
    "sg:classifiers":[
        {
            "category":"Organizations",
            "subcategory":"Professional Association",
            "type":"Services"
        }
    ],
    "sg:phone":"+1 450 263 7470",
    "sg:postcode":"J2K 1J2",
    "sg:province":"QC",
    "wof:name":"Club DE L'Age D'Or",
    "wof:placetype":"venue"
},
  "geometry": {"coordinates":[-72.7457580566,45.2077026367],"type":"Point"}
}