{
  "type": "Feature",
  "properties": {
    "addr:full":"8130 Rue Pascal-Gagnon Saint-Leonard QC H1P 1Y4",
    "addr:housenumber":"8130",
    "addr:postcode":"h1p 1y4",
    "addr:street":"Rue Pascal-Gagnon",
    "iso:country":"CA",
    "sg:address":"8130 Rue Pascal-Gagnon",
    "sg:city":"Saint-Leonard",
    "sg:classifiers":[
        {
            "category":"Building & Trades",
            "subcategory":"Cleaning & Sanitation",
            "type":"Services"
        }
    ],
    "sg:phone":"+1 514 326 6818",
    "sg:postcode":"H1P 1Y4",
    "sg:province":"QC",
    "sg:tags":[
        "snow",
        "removal"
    ],
    "wof:name":"Kanda Equipements Ltd",
    "wof:placetype":"venue"
},
  "geometry": {"coordinates":[-73.580612,45.599022],"type":"Point"}
}