{
  "type": "Feature",
  "properties": {
    "addr:full":"316 Ross Ave The Pas MB R9A 1K4",
    "addr:housenumber":"316",
    "addr:postcode":"r9a 1k4",
    "addr:street":"Ross Ave",
    "iso:country":"CA",
    "sg:address":"316 Ross Ave",
    "sg:city":"The Pas",
    "sg:classifiers":[
        {
            "category":"Organizations",
            "subcategory":"Religious Organization",
            "type":"Services"
        }
    ],
    "sg:phone":"+1 204 623 1275",
    "sg:postcode":"R9A 1K4",
    "sg:province":"MB",
    "sg:tags":[
        "church"
    ],
    "wof:name":"Bible Baptist Church",
    "wof:placetype":"venue"
},
  "geometry": {"coordinates":[-101.24862670900001,53.824306488],"type":"Point"}
}