{
  "type": "Feature",
  "properties": {
    "addr:full":"10 Fernview Crt Stoney Creek ON L8G 4W2",
    "addr:housenumber":"10",
    "addr:postcode":"l8g 4w2",
    "addr:street":"Fernview Crt",
    "iso:country":"CA",
    "sg:address":"10 Fernview Crt",
    "sg:city":"Stoney Creek",
    "sg:classifiers":[
        {
            "category":"Building & Trades",
            "subcategory":"Construction",
            "type":"Services"
        }
    ],
    "sg:phone":"+1 905 664 9495",
    "sg:postcode":"L8G 4W2",
    "sg:province":"ON",
    "sg:tags":[
        "contractor"
    ],
    "wof:name":"Di Carlo Custom Homes Ltd",
    "wof:placetype":"venue"
},
  "geometry": {"coordinates":[-79.717674,43.210117],"type":"Point"}
}