{
  "type": "Feature",
  "properties": {
    "addr:full":"33496 South Fraser Way Abbotsford BC V2S 2B5",
    "addr:housenumber":"33496",
    "addr:postcode":"v2s 2b5",
    "addr:street":"South Fraser Way",
    "iso:country":"CA",
    "sg:address":"33496 South Fraser Way",
    "sg:city":"Abbotsford",
    "sg:classifiers":[
        {
            "category":"Shopping",
            "subcategory":"Florist",
            "type":"Retail Goods"
        }
    ],
    "sg:phone":"+1 604 853 3251",
    "sg:postcode":"V2S 2B5",
    "sg:province":"BC",
    "wof:name":"Windsong Florist",
    "wof:placetype":"venue"
},
  "geometry": {"coordinates":[-122.296181,49.04929],"type":"Point"}
}