{
  "type": "Feature",
  "properties": {
    "addr:full":"30 Mill Rd Egmondville ON N0K 1G0",
    "addr:housenumber":"30",
    "addr:postcode":"n0k 1g0",
    "addr:street":"Mill Rd",
    "iso:country":"CA",
    "sg:address":"30 Mill Rd",
    "sg:city":"Egmondville",
    "sg:classifiers":[
        {
            "category":"Freight",
            "type":"Transportation"
        }
    ],
    "sg:phone":"+1 519 522 1043",
    "sg:postcode":"N0K 1G0",
    "sg:province":"ON",
    "sg:tags":[
        "commercial",
        "storage"
    ],
    "wof:name":"Seaforth Mini Storage",
    "wof:placetype":"venue"
},
  "geometry": {"coordinates":[-81.41001900000001,43.537361],"type":"Point"}
}