{
  "type": "Feature",
  "properties": {
    "addr:full":"344 Boul Du Havre Salaberry-DE-Valleyfield QC J6S 1S6",
    "addr:housenumber":"344",
    "addr:postcode":"j6s 1s6",
    "addr:street":"Boul Du Havre",
    "iso:country":"CA",
    "sg:address":"344 Boul Du Havre",
    "sg:city":"Salaberry-DE-Valleyfield",
    "sg:classifiers":[
        {
            "category":"Shopping",
            "subcategory":"Clothing, Apparel, & Fashions",
            "type":"Retail Goods"
        }
    ],
    "sg:phone":"+1 450 377 0614",
    "sg:postcode":"J6S 1S6",
    "sg:province":"QC",
    "sg:tags":[
        "item",
        "boutique"
    ],
    "wof:name":"Boutique Du Havre",
    "wof:placetype":"venue"
},
  "geometry": {"coordinates":[-74.134995,45.262669],"type":"Point"}
}