{
  "type": "Feature",
  "properties": {
    "addr:full":"Springfield ON N0L 2J0",
    "addr:postcode":"n0l 2j0",
    "iso:country":"CA",
    "sg:city":"Springfield",
    "sg:classifiers":[
        {
            "category":"Restaurant",
            "type":"Food & Drink"
        }
    ],
    "sg:phone":"+1 519 765 2530",
    "sg:postcode":"N0L 2J0",
    "sg:province":"ON",
    "wof:name":"Cravings Pizza",
    "wof:placetype":"venue"
},
  "geometry": {"coordinates":[-80.93971999999999,42.828949],"type":"Point"}
}