{
  "type": "Feature",
  "properties": {
    "addr:full":"Bindloss AB T0J 0H0",
    "addr:postcode":"t0j 0h0",
    "iso:country":"CA",
    "sg:city":"Bindloss",
    "sg:classifiers":[
        {
            "category":"Wholesale",
            "subcategory":"Petroleum",
            "type":"Manufacturing & Wholesale Goods"
        }
    ],
    "sg:phone":"+1 403 379 3963",
    "sg:postcode":"T0J 0H0",
    "sg:province":"AB",
    "sg:tags":[
        "pipe",
        "line",
        "company"
    ],
    "wof:name":"Trans Canada Pipe Lines Ltd",
    "wof:placetype":"venue"
},
  "geometry": {"coordinates":[-110.27568100000001,50.8792],"type":"Point"}
}