{
  "type": "Feature",
  "properties": {
    "addr:full":"1401 Rockland Ave Victoria BC V8S 1V9",
    "addr:housenumber":"1401",
    "addr:postcode":"v8s 1v9",
    "addr:street":"Rockland Ave",
    "iso:country":"CA",
    "sg:address":"1401 Rockland Ave",
    "sg:city":"Victoria",
    "sg:classifiers":[
        {
            "category":"Government",
            "subcategory":"Office",
            "type":"Public Place"
        }
    ],
    "sg:phone":"+1 250 387 2080",
    "sg:postcode":"V8S 1V9",
    "sg:province":"BC",
    "wof:name":"BC Government House",
    "wof:placetype":"venue"
},
  "geometry": {"coordinates":[-123.343307495,48.4194946289],"type":"Point"}
}