{
  "type": "Feature",
  "properties": {
    "addr:full":"Edmonton AB T5P 4J5",
    "addr:postcode":"t5p 4j5",
    "iso:country":"CA",
    "sg:city":"Edmonton",
    "sg:classifiers":[
        {
            "category":"Health Services",
            "subcategory":"Medical Lab",
            "type":"Services"
        }
    ],
    "sg:phone":"+1 780 484 9965",
    "sg:postcode":"T5P 4J5",
    "sg:province":"AB",
    "sg:tags":[
        "laboratory"
    ],
    "wof:name":"Dynacare Kasper Medical Lab",
    "wof:placetype":"venue"
},
  "geometry": {"coordinates":[-113.59005000000001,53.531738],"type":"Point"}
}