{
  "type": "Feature",
  "properties": {
    "addr:full":"1453 Church Ave Winnipeg MB R2X 2X9",
    "addr:housenumber":"1453",
    "addr:postcode":"r2x 2x9",
    "addr:street":"Church Ave",
    "iso:country":"CA",
    "sg:address":"1453 Church Ave",
    "sg:city":"Winnipeg",
    "sg:classifiers":[
        {
            "category":"Wholesale",
            "subcategory":"Machinery & Supplies",
            "type":"Manufacturing & Wholesale Goods"
        }
    ],
    "sg:phone":"+1 204 697 0006",
    "sg:postcode":"R2X 2X9",
    "sg:province":"MB",
    "sg:tags":[
        "janitor"
    ],
    "wof:name":"Wood Wyant Inc",
    "wof:placetype":"venue"
},
  "geometry": {"coordinates":[-97.1769104004,49.9385070801],"type":"Point"}
}