{
  "type": "Feature",
  "properties": {
    "addr:full":"117 Keewatin St N Oshawa ON L1G 6N2",
    "addr:housenumber":"117",
    "addr:postcode":"l1g 6n2",
    "addr:street":"Keewatin St N",
    "iso:country":"CA",
    "sg:address":"117 Keewatin St N",
    "sg:city":"Oshawa",
    "sg:classifiers":[
        {
            "category":"Personal",
            "type":"Services"
        }
    ],
    "sg:phone":"+1 905 728 8235",
    "sg:postcode":"L1G 6N2",
    "sg:province":"ON",
    "sg:tags":[
        "program",
        "physical",
        "exercise",
        "fitness"
    ],
    "wof:name":"Formula 1 Training",
    "wof:placetype":"venue"
},
  "geometry": {"coordinates":[-78.82740020750001,43.9083023071],"type":"Point"}
}