{
  "type": "Feature",
  "properties": {
    "addr:full":"17077 Highway 12 Midland ON L4R 4K3",
    "addr:housenumber":"17077",
    "addr:postcode":"l4r 4k3",
    "addr:street":"Highway 12",
    "iso:country":"CA",
    "sg:address":"17077 Highway 12",
    "sg:city":"Midland",
    "sg:classifiers":[
        {
            "category":"Freight",
            "type":"Transportation"
        }
    ],
    "sg:phone":"+1 705 526 2161",
    "sg:postcode":"L4R 4K3",
    "sg:province":"ON",
    "sg:tags":[
        "trucking"
    ],
    "wof:name":"Ken Archer Transport",
    "wof:placetype":"venue"
},
  "geometry": {"coordinates":[-79.88851200000001,44.749905],"type":"Point"}
}