{
  "type": "Feature",
  "properties": {
    "addr:full":"723 Balmoral Dr Brampton ON L6T 1X5",
    "addr:housenumber":"723",
    "addr:postcode":"l6t 1x5",
    "addr:street":"Balmoral Dr",
    "iso:country":"CA",
    "sg:address":"723 Balmoral Dr",
    "sg:city":"Brampton",
    "sg:classifiers":[
        {
            "category":"Organizations",
            "subcategory":"Religious Organization",
            "type":"Services"
        }
    ],
    "sg:phone":"+1 905 792 2279",
    "sg:postcode":"L6T 1X5",
    "sg:province":"ON",
    "sg:tags":[
        "church"
    ],
    "wof:name":"St Paul's Presbyterian Church",
    "wof:placetype":"venue"
},
  "geometry": {"coordinates":[-79.6937179565,43.719291687],"type":"Point"}
}