{
  "type": "Feature",
  "properties": {
    "addr:full":"4902 51st Ave Bonnyville AB T9N 2J1",
    "addr:housenumber":"4902",
    "addr:postcode":"t9n 2j1",
    "addr:street":"51St Ave",
    "iso:country":"CA",
    "sg:address":"4902 51st Ave",
    "sg:city":"Bonnyville",
    "sg:classifiers":[
        {
            "category":"Retail",
            "subcategory":"Auto Rental",
            "type":"Services"
        }
    ],
    "sg:phone":"+1 780 826 3278",
    "sg:postcode":"T9N 2J1",
    "sg:province":"AB",
    "sg:tags":[
        "renting",
        "automobile",
        "dealer"
    ],
    "wof:name":"Ducharme Rentals",
    "wof:placetype":"venue"
},
  "geometry": {"coordinates":[-110.737510681,54.2687530518],"type":"Point"}
}