{
  "type": "Feature",
  "properties": {
    "addr:full":"Burnaby BC V5C 5W7",
    "addr:postcode":"v5c 5w7",
    "iso:country":"CA",
    "sg:city":"Burnaby",
    "sg:classifiers":[
        {
            "category":"Autos & Motor Vehicles",
            "subcategory":"Auto Supplies",
            "type":"Retail Goods"
        }
    ],
    "sg:phone":"+1 604 294 3788",
    "sg:postcode":"V5C 5W7",
    "sg:province":"BC",
    "sg:tags":[
        "tire"
    ],
    "wof:name":"National Tire Wholesale",
    "wof:placetype":"venue"
},
  "geometry": {"coordinates":[-122.98479461700001,49.261428833],"type":"Point"}
}