{
  "type": "Feature",
  "properties": {
    "addr:full":"360 Boul Marcel-Laurin Saint-Laurent QC H4M 2L4",
    "addr:housenumber":"360",
    "addr:postcode":"h4m 2l4",
    "addr:street":"Boul Marcel-Laurin",
    "iso:country":"CA",
    "sg:address":"360 Boul Marcel-Laurin",
    "sg:city":"Saint-Laurent",
    "sg:classifiers":[
        {
            "category":"Retail",
            "subcategory":"Car Wash",
            "type":"Services"
        }
    ],
    "sg:phone":"+1 514 744 7358",
    "sg:postcode":"H4M 2L4",
    "sg:province":"QC",
    "sg:tags":[
        "automobile",
        "detail",
        "clean"
    ],
    "wof:name":"Lave Auto Marcel Laurin",
    "wof:placetype":"venue"
},
  "geometry": {"coordinates":[-73.67671199999999,45.50391],"type":"Point"}
}