{
  "type": "Feature",
  "properties": {
    "iso:country":"CA",
    "sg:city":"London",
    "sg:classifiers":[
        {
            "category":"Shopping",
            "subcategory":"Clothing, Apparel, & Fashions",
            "type":"Retail Goods"
        }
    ],
    "sg:phone":"+1 519 451 7455",
    "sg:postcode":"N5Y 1A8",
    "sg:province":"ON",
    "sg:tags":[
        "furnishing"
    ],
    "wof:name":"Nice Wear",
    "wof:placetype":"venue"
},
  "geometry": {"coordinates":[-81.215469,43.01952],"type":"Point"}
}