{
  "type": "Feature",
  "properties": {
    "addr:full":"New Westminster BC V3L 3C4",
    "addr:postcode":"v3l 3c4",
    "iso:country":"CA",
    "sg:city":"New Westminster",
    "sg:classifiers":[
        {
            "category":"Health Services",
            "subcategory":"Doctor",
            "type":"Services"
        }
    ],
    "sg:phone":"+1 604 522 5242",
    "sg:postcode":"V3L 3C4",
    "sg:province":"BC",
    "sg:tags":[
        "dentist"
    ],
    "wof:name":"Agar, Lyle DDS",
    "wof:placetype":"venue"
},
  "geometry": {"coordinates":[-122.92132599999999,49.213745],"type":"Point"}
}