{
  "type": "Feature",
  "properties": {
    "addr:full":"5245 Selma Park Rd Sechelt BC V0N 3A2",
    "addr:housenumber":"5245",
    "addr:postcode":"v0n 3a2",
    "addr:street":"Selma Park Rd",
    "iso:country":"CA",
    "sg:address":"5245 Selma Park Rd",
    "sg:city":"Sechelt",
    "sg:classifiers":[
        {
            "category":"Home & Garden",
            "subcategory":"Garden Supply",
            "type":"Retail Goods"
        }
    ],
    "sg:phone":"+1 604 885 4841",
    "sg:postcode":"V0N 3A2",
    "sg:province":"BC",
    "sg:tags":[
        "center"
    ],
    "wof:name":"Dahlias Galore",
    "wof:placetype":"venue"
},
  "geometry": {"coordinates":[-123.73263549799999,49.4644393921],"type":"Point"}
}