{
  "type": "Feature",
  "properties": {
    "addr:full":"85 Wildcat Rd North York ON M3J 2P5",
    "addr:housenumber":"85",
    "addr:postcode":"m3j 2p5",
    "addr:street":"Wildcat Rd",
    "iso:country":"CA",
    "sg:address":"85 Wildcat Rd",
    "sg:city":"North York",
    "sg:classifiers":[
        {
            "category":"Manufacturing",
            "subcategory":"Furniture",
            "type":"Manufacturing & Wholesale Goods"
        }
    ],
    "sg:phone":"+1 416 665 1057",
    "sg:postcode":"M3J 2P5",
    "sg:province":"ON",
    "sg:tags":[
        "chair"
    ],
    "wof:name":"Abs Woodworking",
    "wof:placetype":"venue"
},
  "geometry": {"coordinates":[-79.4866638184,43.7784996033],"type":"Point"}
}