{
  "type": "Feature",
  "properties": {
    "iso:country":"CA",
    "sg:address":"2675 Rue Sicotte",
    "sg:city":"Saint-Hyacinthe",
    "sg:classifiers":[
        {
            "category":"Home & Garden",
            "subcategory":"Household Appliances",
            "type":"Retail Goods"
        }
    ],
    "sg:phone":"+1 450 773 2043",
    "sg:postcode":"J2S 2L3",
    "sg:province":"QC",
    "sg:tags":[
        "equipment",
        "supply",
        "electric",
        "vacuum"
    ],
    "wof:name":"Fournitures Elec Maskoutaines",
    "wof:placetype":"venue"
},
  "geometry": {"coordinates":[-72.95830535890001,45.6225738525],"type":"Point"}
}