{
  "type": "Feature",
  "properties": {
    "addr:full":"55 Joanith Dr East York ON M4B 1S8",
    "addr:housenumber":"55",
    "addr:postcode":"m4b 1s8",
    "addr:street":"Joanith Dr",
    "iso:country":"CA",
    "sg:address":"55 Joanith Dr",
    "sg:city":"East York",
    "sg:classifiers":[
        {
            "category":"Building & Trades",
            "subcategory":"Plumbing",
            "type":"Services"
        }
    ],
    "sg:phone":"+1 416 755 9504",
    "sg:postcode":"M4B 1S8",
    "sg:province":"ON",
    "sg:tags":[
        "conditioning",
        "air",
        "system",
        "contractor"
    ],
    "wof:name":"Harvey's Refrigeration & Ac",
    "wof:placetype":"venue"
},
  "geometry": {"coordinates":[-79.307495,43.707245],"type":"Point"}
}