{
  "type": "Feature",
  "properties": {
    "addr:full":"4826 50 St Alix AB T0C 0B0",
    "addr:housenumber":"4826",
    "addr:postcode":"t0c 0b0",
    "addr:street":"50 St",
    "iso:country":"CA",
    "sg:address":"4826 50 St",
    "sg:city":"Alix",
    "sg:classifiers":[
        {
            "category":"Government",
            "subcategory":"Office",
            "type":"Public Place"
        }
    ],
    "sg:phone":"+1 403 747 2929",
    "sg:postcode":"T0C 0B0",
    "sg:province":"AB",
    "sg:tags":[
        "village"
    ],
    "wof:name":"Alix Village Shop",
    "wof:placetype":"venue"
},
  "geometry": {"coordinates":[-113.19429,52.398037],"type":"Point"}
}