{
  "type": "Feature",
  "properties": {
    "addr:full":"Petersburg ON N0B 2H0",
    "addr:postcode":"n0b 2h0",
    "iso:country":"CA",
    "sg:city":"Petersburg",
    "sg:classifiers":[
        {
            "category":"Professional",
            "subcategory":"Computer Services",
            "type":"Services"
        }
    ],
    "sg:phone":"+1 519 576 0451",
    "sg:postcode":"N0B 2H0",
    "sg:province":"ON",
    "sg:tags":[
        "repair"
    ],
    "wof:name":"Compair Systems",
    "wof:placetype":"venue"
},
  "geometry": {"coordinates":[-80.6027832031,43.4138717651],"type":"Point"}
}