{
  "type": "Feature",
  "properties": {
    "addr:full":"343 Rue Racine E Chicoutimi QC G7H 1S8",
    "addr:housenumber":"343",
    "addr:postcode":"g7h 1s8",
    "addr:street":"Rue Racine E",
    "iso:country":"CA",
    "sg:address":"343 Rue Racine E",
    "sg:city":"Chicoutimi",
    "sg:classifiers":[
        {
            "category":"Health Services",
            "subcategory":"Doctor",
            "type":"Services"
        }
    ],
    "sg:phone":"+1 418 543 4137",
    "sg:postcode":"G7H 1S8",
    "sg:province":"QC",
    "sg:tags":[
        "clinic"
    ],
    "wof:name":"Clinique Richard Ouellet",
    "wof:placetype":"venue"
},
  "geometry": {"coordinates":[-71.058044,48.427654],"type":"Point"}
}