{
  "type": "Feature",
  "properties": {
    "addr:full":"330 Metcalfe St Ottawa ON K2P 1S4",
    "addr:housenumber":"330",
    "addr:postcode":"k2p 1s4",
    "addr:street":"Metcalfe St",
    "iso:country":"CA",
    "sg:address":"330 Metcalfe St",
    "sg:city":"Ottawa",
    "sg:classifiers":[
        {
            "category":"Real Estate",
            "subcategory":"Real Estate Operator",
            "type":"Services"
        }
    ],
    "sg:phone":"+1 613 235 4087",
    "sg:postcode":"K2P 1S4",
    "sg:province":"ON",
    "sg:tags":[
        "apartment"
    ],
    "wof:name":"Governor Metcalfe Apartments",
    "wof:placetype":"venue"
},
  "geometry": {"coordinates":[-75.69023900000001,45.414333],"type":"Point"}
}