{
  "type": "Feature",
  "properties": {
    "addr:full":"7180 Rue Saint-Hubert Montreal QC H2R 2N1",
    "addr:housenumber":"7180",
    "addr:postcode":"h2r 2n1",
    "addr:street":"Rue Saint-Hubert",
    "iso:country":"CA",
    "sg:address":"7180 Rue Saint-Hubert",
    "sg:city":"Montreal",
    "sg:classifiers":[
        {
            "category":"Restaurant",
            "type":"Food & Drink"
        }
    ],
    "sg:phone":"+1 514 271 5261",
    "sg:postcode":"H2R 2N1",
    "sg:province":"QC",
    "wof:name":"Restaurant Chalimar",
    "wof:placetype":"venue"
},
  "geometry": {"coordinates":[-73.61377,45.540848],"type":"Point"}
}