{
  "type": "Feature",
  "properties": {
    "addr:full":"Saint-Eustache QC J7P 1W8",
    "addr:postcode":"j7p 1w8",
    "iso:country":"CA",
    "sg:city":"Saint-Eustache",
    "sg:classifiers":[
        {
            "category":"Manufacturing",
            "subcategory":"Food",
            "type":"Manufacturing & Wholesale Goods"
        }
    ],
    "sg:phone":"+1 450 473 1304",
    "sg:postcode":"J7P 1W8",
    "sg:province":"QC",
    "sg:tags":[
        "baker",
        "supply",
        "chocolate"
    ],
    "wof:name":"Fantaisies Culinaires",
    "wof:placetype":"venue"
},
  "geometry": {"coordinates":[-73.89164700000001,45.567444],"type":"Point"}
}