{
  "type": "Feature",
  "properties": {
    "iso:country":"CA",
    "sg:address":"121 Pippin Rd",
    "sg:city":"Concord",
    "sg:classifiers":[
        {
            "category":"Manufacturing",
            "subcategory":"Chemicals & Compounds",
            "type":"Manufacturing & Wholesale Goods"
        }
    ],
    "sg:phone":"+1 905 761 8529",
    "sg:postcode":"L4K 4J9",
    "sg:province":"ON",
    "sg:tags":[
        "plastic"
    ],
    "wof:name":"Royal Plastics Inc",
    "wof:placetype":"venue"
},
  "geometry": {"coordinates":[-79.523193,43.809807],"type":"Point"}
}