{
  "type": "Feature",
  "properties": {
    "iso:country":"CA",
    "sg:address":"100 Ferry Rd",
    "sg:city":"Winnipeg",
    "sg:classifiers":[
        {
            "category":"Organizations",
            "subcategory":"Professional Association",
            "type":"Services"
        }
    ],
    "sg:phone":"+1 204 888 1599",
    "sg:postcode":"R3J 1V7",
    "sg:province":"MB",
    "sg:tags":[
        "club"
    ],
    "wof:name":"Bourkevale Community Ctr",
    "wof:placetype":"venue"
},
  "geometry": {"coordinates":[-97.2193450928,49.8759040833],"type":"Point"}
}