{
  "type": "Feature",
  "properties": {
    "addr:full":"2045 Ch Du Sault Saint-Romuald QC G6W 2K7",
    "addr:postcode":"2045;g6w 2k7",
    "addr:street":"Ch Du Sault",
    "iso:country":"CA",
    "sg:address":"2045 Ch Du Sault",
    "sg:city":"Saint-Romuald",
    "sg:classifiers":[
        {
            "category":"Education",
            "subcategory":"School",
            "type":"Public Place"
        }
    ],
    "sg:phone":"+1 418 839 9451",
    "sg:postcode":"G6W 2K7",
    "sg:province":"QC",
    "wof:name":"Maria Dominique Ecole",
    "wof:placetype":"venue"
},
  "geometry": {"coordinates":[-71.239082,46.754234],"type":"Point"}
}