{
  "type": "Feature",
  "properties": {
    "iso:country":"CA",
    "sg:city":"Richmond",
    "sg:classifiers":[
        {
            "category":"Personal",
            "subcategory":"Beauty Salon",
            "type":"Services"
        }
    ],
    "sg:phone":"+1 604 273 6798",
    "sg:postcode":"V6X 3X9",
    "sg:province":"BC",
    "wof:name":"Danger Figure Ctr",
    "wof:placetype":"venue"
},
  "geometry": {"coordinates":[-123.134002685,49.1848106384],"type":"Point"}
}