{
  "type": "Feature",
  "properties": {
    "addr:full":"Cambridge ON N1R 7L6",
    "addr:postcode":"n1r 7l6",
    "iso:country":"CA",
    "sg:city":"Cambridge",
    "sg:classifiers":[
        {
            "category":"Professional",
            "subcategory":"Lawyer & Legal Services",
            "type":"Services"
        }
    ],
    "sg:phone":"+1 519 623 4799",
    "sg:postcode":"N1R 7L6",
    "sg:province":"ON",
    "sg:tags":[
        "attorney"
    ],
    "wof:name":"Copp & Cosman",
    "wof:placetype":"venue"
},
  "geometry": {"coordinates":[-80.315178,43.361755],"type":"Point"}
}