{
  "type": "Feature",
  "properties": {
    "addr:full":"125 King St E Bowmanville ON L1C 1N6",
    "addr:housenumber":"125",
    "addr:postcode":"l1c 1n6",
    "addr:street":"King St",
    "iso:country":"CA",
    "sg:address":"125 King St E",
    "sg:city":"Bowmanville",
    "sg:classifiers":[
        {
            "category":"Shopping",
            "type":"Retail Goods"
        }
    ],
    "sg:phone":"+1 905 623 4844",
    "sg:postcode":"L1C 1N6",
    "sg:province":"ON",
    "sg:tags":[
        "spa",
        "hot",
        "tub"
    ],
    "wof:name":"King Street Spas & Pool Spls",
    "wof:placetype":"venue"
},
  "geometry": {"coordinates":[-78.68428,43.910847],"type":"Point"}
}