{
  "type": "Feature",
  "properties": {
    "iso:country":"CA",
    "sg:address":"388 Ottawa St S",
    "sg:city":"Kitchener",
    "sg:classifiers":[
        {
            "category":"Organizations",
            "subcategory":"Religious Organization",
            "type":"Services"
        }
    ],
    "sg:phone":"+1 519 570 2199",
    "sg:postcode":"N2M 3P4",
    "sg:province":"ON",
    "sg:tags":[
        "church"
    ],
    "wof:name":"St Mary's Coptic Orthodox Chr",
    "wof:placetype":"venue"
},
  "geometry": {"coordinates":[-80.479271,43.432915],"type":"Point"}
}