{
  "type": "Feature",
  "properties": {
    "addr:full":"4163 View Ridge South Slocan BC V0G 2G0",
    "addr:housenumber":"4163",
    "addr:postcode":"v0g 2g0",
    "addr:street":"View",
    "iso:country":"CA",
    "sg:address":"4163 View Ridge",
    "sg:city":"South Slocan",
    "sg:classifiers":[
        {
            "category":"Building & Trades",
            "subcategory":"Construction",
            "type":"Services"
        }
    ],
    "sg:phone":"+1 250 359 2930",
    "sg:postcode":"V0G 2G0",
    "sg:province":"BC",
    "sg:tags":[
        "contractor"
    ],
    "wof:name":"Asc Construction Ltd",
    "wof:placetype":"venue"
},
  "geometry": {"coordinates":[-117.462898254,49.7624511719],"type":"Point"}
}