{
  "type": "Feature",
  "properties": {
    "iso:country":"CA",
    "sg:address":"318 Saskatchewan Ave W",
    "sg:city":"Outlook",
    "sg:classifiers":[
        {
            "category":"Shopping",
            "subcategory":"Jewelry",
            "type":"Retail Goods"
        }
    ],
    "sg:phone":"+1 306 867 8242",
    "sg:postcode":"S0L 2N0",
    "sg:province":"SK",
    "sg:tags":[
        "jeweler"
    ],
    "wof:name":"Golden Tuch Jewellers",
    "wof:placetype":"venue"
},
  "geometry": {"coordinates":[-107.05581665,51.4882087708],"type":"Point"}
}