{
  "type": "Feature",
  "properties": {
    "addr:full":"Gaspe QC G4X 1T5",
    "addr:postcode":"g4x 1t5",
    "iso:country":"CA",
    "sg:city":"Gaspe",
    "sg:classifiers":[
        {
            "category":"Professional",
            "subcategory":"Business Services",
            "type":"Services"
        }
    ],
    "sg:phone":"+1 418 368 2525",
    "sg:postcode":"G4X 1T5",
    "sg:province":"QC",
    "sg:tags":[
        "notary"
    ],
    "wof:name":"Gagne, Raymond",
    "wof:placetype":"venue"
},
  "geometry": {"coordinates":[-64.4845046997,48.8289642334],"type":"Point"}
}