{
  "type": "Feature",
  "properties": {
    "addr:full":"379 Queen St W Toronto ON M5V 2A5",
    "addr:housenumber":"379",
    "addr:postcode":"m5v 2a5",
    "addr:street":"Queen St W",
    "iso:country":"CA",
    "sg:address":"379 Queen St W",
    "sg:city":"Toronto",
    "sg:classifiers":[
        {
            "category":"Professional",
            "subcategory":"Research",
            "type":"Services"
        }
    ],
    "sg:phone":"+1 416 596 1799",
    "sg:postcode":"M5V 2A5",
    "sg:province":"ON",
    "sg:tags":[
        "foundation",
        "philanthropic"
    ],
    "wof:name":"Change Canada Charitable Fndtn",
    "wof:placetype":"venue"
},
  "geometry": {"coordinates":[-79.394012,43.649101],"type":"Point"}
}