{
  "type": "Feature",
  "properties": {
    "addr:full":"100 Place Charles-Le Moyne Longueuil QC J4K 2T4",
    "addr:housenumber":"100",
    "addr:postcode":"j4k 2t4",
    "addr:street":"Place Charles-Le Moyne",
    "iso:country":"CA",
    "sg:address":"100 Place Charles-Le Moyne",
    "sg:city":"Longueuil",
    "sg:classifiers":[
        {
            "category":"Shopping",
            "subcategory":"Florist",
            "type":"Retail Goods"
        }
    ],
    "sg:phone":"+1 450 463 0164",
    "sg:postcode":"J4K 2T4",
    "sg:province":"QC",
    "wof:name":"Au Cachet Fleuri",
    "wof:placetype":"venue"
},
  "geometry": {"coordinates":[-73.52253,45.525345],"type":"Point"}
}