{
  "type": "Feature",
  "properties": {
    "addr:full":"3500 27 St Vernon BC V1T 9P1",
    "addr:housenumber":"3500",
    "addr:postcode":"v1t 9p1",
    "addr:street":"27 St",
    "iso:country":"CA",
    "sg:address":"3500 27 St",
    "sg:city":"Vernon",
    "sg:classifiers":[
        {
            "category":"Autos & Motor Vehicles",
            "subcategory":"Automobile Sales",
            "type":"Retail Goods"
        }
    ],
    "sg:phone":"+1 250 545 2206",
    "sg:postcode":"V1T 9P1",
    "sg:province":"BC",
    "sg:tags":[
        "repairing",
        "car",
        "parts",
        "supply"
    ],
    "wof:name":"Walthers Pontiac Buick Gmc Ltd",
    "wof:placetype":"venue"
},
  "geometry": {"coordinates":[-119.26676940900001,50.2674865723],"type":"Point"}
}