{
  "type": "Feature",
  "properties": {
    "addr:full":"325 Munro St # 502 Bathurst NB E2A 3Y4",
    "addr:housenumber":"325",
    "addr:postcode":"e2a 3y4",
    "addr:street":"Munro St # 502",
    "iso:country":"CA",
    "sg:address":"325 Munro St # 502",
    "sg:city":"Bathurst",
    "sg:classifiers":[
        {
            "category":"Real Estate",
            "subcategory":"Real Estate Operator",
            "type":"Services"
        }
    ],
    "sg:phone":"+1 506 548 8054",
    "sg:postcode":"E2A 3Y4",
    "sg:province":"NB",
    "sg:tags":[
        "apartment"
    ],
    "wof:name":"Vienneau Apartments Ltd",
    "wof:placetype":"venue"
},
  "geometry": {"coordinates":[-65.647728,47.615002],"type":"Point"}
}