{
  "type": "Feature",
  "properties": {
    "addr:full":"Simcoe ON N3Y 4K4",
    "addr:postcode":"n3y 4k4",
    "iso:country":"CA",
    "sg:city":"Simcoe",
    "sg:classifiers":[
        {
            "category":"Wholesale",
            "subcategory":"Fruits & Vegetables",
            "type":"Manufacturing & Wholesale Goods"
        }
    ],
    "sg:phone":"+1 519 587 3260",
    "sg:postcode":"N3Y 4K4",
    "sg:province":"ON",
    "wof:name":"Sun Choice Produce",
    "wof:placetype":"venue"
},
  "geometry": {"coordinates":[-80.351890564,42.837600708],"type":"Point"}
}