{
  "type": "Feature",
  "properties": {
    "addr:full":"Smooth Rock Falls ON P0L 2B0",
    "addr:postcode":"p0l 2b0",
    "iso:country":"CA",
    "sg:city":"Smooth Rock Falls",
    "sg:classifiers":[
        {
            "category":"Building & Trades",
            "subcategory":"Electrical",
            "type":"Services"
        }
    ],
    "sg:phone":"+1 705 338 2834",
    "sg:postcode":"P0L 2B0",
    "sg:province":"ON",
    "sg:tags":[
        "electric",
        "contractor"
    ],
    "wof:name":"Denis Chevalier Electric",
    "wof:placetype":"venue"
},
  "geometry": {"coordinates":[-81.6323547363,49.2760353088],"type":"Point"}
}