{
  "type": "Feature",
  "properties": {
    "addr:full":"985 Bloor St W Toronto ON M6H 1M1",
    "addr:housenumber":"985",
    "addr:postcode":"m6h 1m1",
    "addr:street":"Bloor St W",
    "iso:country":"CA",
    "sg:address":"985 Bloor St W",
    "sg:city":"Toronto",
    "sg:classifiers":[
        {
            "category":"Restaurant",
            "type":"Food & Drink"
        }
    ],
    "sg:phone":"+1 416 531 3705",
    "sg:postcode":"M6H 1M1",
    "sg:province":"ON",
    "wof:name":"Jankie's Restaurant & Bar",
    "wof:placetype":"venue"
},
  "geometry": {"coordinates":[-79.429642,43.660915],"type":"Point"}
}