{
  "type": "Feature",
  "properties": {
    "addr:full":"PO Box 8 Sturgeon Landing SK S0P 0H0",
    "addr:housenumber":"po;8",
    "addr:postcode":"s0p 0h0",
    "addr:street":"Box;Sturgeon Landing",
    "iso:country":"CA",
    "sg:address":"PO Box 8",
    "sg:city":"Sturgeon Landing",
    "sg:classifiers":[
        {
            "category":"Health Services",
            "subcategory":"Clinic",
            "type":"Services"
        }
    ],
    "sg:phone":"+1 306 688 4510",
    "sg:postcode":"S0P 0H0",
    "sg:province":"SK",
    "wof:name":"Sturgeon Landing Health Clnc",
    "wof:placetype":"venue"
},
  "geometry": {"coordinates":[-101.81603200000001,54.282696],"type":"Point"}
}