{
  "type": "Feature",
  "properties": {
    "addr:full":"60 Foleys Cove Rd Pennfield NB E5H 2A3",
    "addr:housenumber":"60",
    "addr:postcode":"e5h 2a3",
    "addr:street":"Foleys Cove Rd",
    "iso:country":"CA",
    "sg:address":"60 Foleys Cove Rd",
    "sg:city":"Pennfield",
    "sg:classifiers":[
        {
            "category":"Farming",
            "subcategory":"Aquatic Farm",
            "type":"Manufacturing & Wholesale Goods"
        }
    ],
    "sg:phone":"+1 506 456 2223",
    "sg:postcode":"E5H 2A3",
    "sg:province":"NB",
    "sg:tags":[
        "hatchery",
        "fish"
    ],
    "wof:name":"Scotia Salmon Farms Ltd",
    "wof:placetype":"venue"
},
  "geometry": {"coordinates":[-66.7103424072,45.0869865417],"type":"Point"}
}