{
  "type": "Feature",
  "properties": {
    "addr:full":"Saint-Ludger-DE-Milot QC G0W 2B0",
    "addr:postcode":"g0w 2b0",
    "iso:country":"CA",
    "sg:city":"Saint-Ludger-DE-Milot",
    "sg:classifiers":[
        {
            "category":"Freight",
            "type":"Transportation"
        }
    ],
    "sg:phone":"+1 418 373 2067",
    "sg:postcode":"G0W 2B0",
    "sg:province":"QC",
    "sg:tags":[
        "trucking"
    ],
    "wof:name":"Entreprises Alain Michaud Inc",
    "wof:placetype":"venue"
},
  "geometry": {"coordinates":[-71.82054100000001,48.897587],"type":"Point"}
}