{
  "type": "Feature",
  "properties": {
    "addr:full":"329 Rue Gardenville Longueuil QC J4H 2H4",
    "addr:housenumber":"329",
    "addr:postcode":"j4h 2h4",
    "addr:street":"Rue Gardenville",
    "iso:country":"CA",
    "sg:address":"329 Rue Gardenville",
    "sg:city":"Longueuil",
    "sg:classifiers":[
        {
            "category":"Professional",
            "type":"Services"
        }
    ],
    "sg:phone":"+1 450 679 6783",
    "sg:postcode":"J4H 2H4",
    "sg:province":"QC",
    "sg:tags":[
        "general",
        "establishment",
        "contractor"
    ],
    "wof:name":"Navexperts Inc",
    "wof:placetype":"venue"
},
  "geometry": {"coordinates":[-73.5124130249,45.5302085876],"type":"Point"}
}