{
  "type": "Feature",
  "properties": {
    "addr:full":"213 3E Av Quebec QC G1L 2V7",
    "addr:housenumber":"213",
    "addr:postcode":"g1l 2v7",
    "addr:street":"3E Av",
    "iso:country":"CA",
    "sg:address":"213 3E Av",
    "sg:city":"Quebec",
    "sg:classifiers":[
        {
            "category":"Home & Garden",
            "subcategory":"Household Appliances",
            "type":"Retail Goods"
        }
    ],
    "sg:phone":"+1 418 529 8479",
    "sg:postcode":"G1L 2V7",
    "sg:province":"QC",
    "wof:name":"Quebec Service DE Laveuses Inc",
    "wof:placetype":"venue"
},
  "geometry": {"coordinates":[-71.2253570557,46.8212738037],"type":"Point"}
}