{
  "type": "Feature",
  "properties": {
    "addr:full":"177 Thames St S Ingersoll ON N5C 2T6",
    "addr:housenumber":"177",
    "addr:postcode":"n5c 2t6",
    "addr:street":"Thames St S",
    "iso:country":"CA",
    "sg:address":"177 Thames St S",
    "sg:city":"Ingersoll",
    "sg:classifiers":[
        {
            "category":"Health Services",
            "subcategory":"Doctor",
            "type":"Services"
        }
    ],
    "sg:phone":"+1 519 485 4141",
    "sg:postcode":"N5C 2T6",
    "sg:province":"ON",
    "sg:tags":[
        "dentist"
    ],
    "wof:name":"Berg, Dace DDS",
    "wof:placetype":"venue"
},
  "geometry": {"coordinates":[-80.8815689087,43.0374298096],"type":"Point"}
}