{
  "type": "Feature",
  "properties": {
    "iso:country":"CA",
    "sg:city":"Calgary",
    "sg:classifiers":[
        {
            "category":"Professional",
            "subcategory":"Engineering",
            "type":"Services"
        }
    ],
    "sg:phone":"+1 403 247 1777",
    "sg:postcode":"T3B 0H3",
    "sg:province":"AB",
    "sg:tags":[
        "engineer"
    ],
    "wof:name":"J K Engineering Ltd",
    "wof:placetype":"venue"
},
  "geometry": {"coordinates":[-114.200974,51.089153],"type":"Point"}
}