{
  "type": "Feature",
  "properties": {
    "addr:full":"Montreal QC H2R 2J4",
    "addr:postcode":"h2r 2j4",
    "iso:country":"CA",
    "sg:city":"Montreal",
    "sg:classifiers":[
        {
            "category":"Wholesale",
            "subcategory":"Metals & Minerals",
            "type":"Manufacturing & Wholesale Goods"
        }
    ],
    "sg:phone":"+1 514 990 1915",
    "sg:postcode":"H2R 2J4",
    "sg:province":"QC",
    "sg:tags":[
        "iron",
        "welding"
    ],
    "wof:name":"Abc Acier",
    "wof:placetype":"venue"
},
  "geometry": {"coordinates":[-73.6230545044,45.5422172546],"type":"Point"}
}