{
  "type": "Feature",
  "properties": {
    "iso:country":"CA",
    "sg:address":"152 Fairholme Ave",
    "sg:city":"North York",
    "sg:classifiers":[
        {
            "category":"Building & Trades",
            "subcategory":"Construction",
            "type":"Services"
        }
    ],
    "sg:phone":"+1 416 783 0308",
    "sg:postcode":"M6B 2X2",
    "sg:province":"ON",
    "sg:tags":[
        "masonry",
        "contractor",
        "general"
    ],
    "wof:name":"DE Rose General Contracting",
    "wof:placetype":"venue"
},
  "geometry": {"coordinates":[-79.44255065919999,43.7157897949],"type":"Point"}
}