{
  "type": "Feature",
  "properties": {
    "addr:full":"222 Grenfell Hts Grand Falls-Windsor NL A2A 2J2",
    "addr:housenumber":"222",
    "addr:postcode":"a2a 2j2",
    "addr:street":"Grenfell Hts",
    "iso:country":"CA",
    "sg:address":"222 Grenfell Hts",
    "sg:city":"Grand Falls-Windsor",
    "sg:classifiers":[
        {
            "category":"Food & Beverages",
            "subcategory":"Groceries & Convenience Stores",
            "type":"Retail Goods"
        }
    ],
    "sg:phone":"+1 709 489 8898",
    "sg:postcode":"A2A 2J2",
    "sg:province":"NL",
    "wof:name":"Neighbours K & K",
    "wof:placetype":"venue"
},
  "geometry": {"coordinates":[-55.6254348755,48.9483604431],"type":"Point"}
}