{
  "type": "Feature",
  "properties": {
    "iso:country":"CA",
    "sg:address":"193 Homestead Cres",
    "sg:city":"London",
    "sg:classifiers":[
        {
            "category":"Social Services",
            "subcategory":"Child Care",
            "type":"Services"
        }
    ],
    "sg:phone":"+1 519 471 9920",
    "sg:postcode":"N6G 2E6",
    "sg:province":"ON",
    "sg:tags":[
        "kindergarten",
        "academic",
        "school"
    ],
    "wof:name":"Montessori House of Children",
    "wof:placetype":"venue"
},
  "geometry": {"coordinates":[-81.306488,43.008114],"type":"Point"}
}