{
  "type": "Feature",
  "properties": {
    "addr:full":"4454 10th Ave W Vancouver BC V6R 2H9",
    "addr:housenumber":"4454",
    "addr:postcode":"v6r 2h9",
    "addr:street":"10Th Ave W",
    "iso:country":"CA",
    "sg:address":"4454 10th Ave W",
    "sg:city":"Vancouver",
    "sg:classifiers":[
        {
            "category":"Shopping",
            "subcategory":"Jewelry",
            "type":"Retail Goods"
        }
    ],
    "sg:phone":"+1 604 222 1505",
    "sg:postcode":"V6R 2H9",
    "sg:province":"BC",
    "sg:tags":[
        "establishment",
        "clothing"
    ],
    "wof:name":"Changes Consignment Clothing",
    "wof:placetype":"venue"
},
  "geometry": {"coordinates":[-123.207718,49.26368],"type":"Point"}
}