{
  "type": "Feature",
  "properties": {
    "addr:full":"43 Powell St Vancouver BC V6A 1E9",
    "addr:housenumber":"43",
    "addr:postcode":"v6a 1e9",
    "addr:street":"Powell St",
    "iso:country":"CA",
    "sg:address":"43 Powell St",
    "sg:city":"Vancouver",
    "sg:classifiers":[
        {
            "category":"Real Estate",
            "subcategory":"Real Estate Operator",
            "type":"Services"
        }
    ],
    "sg:phone":"+1 604 689 5161",
    "sg:postcode":"V6A 1E9",
    "sg:province":"BC",
    "sg:tags":[
        "apartment"
    ],
    "wof:name":"Europe Hotel Apartments",
    "wof:placetype":"venue"
},
  "geometry": {"coordinates":[-123.103218079,49.2834281921],"type":"Point"}
}