{
  "type": "Feature",
  "properties": {
    "addr:full":"401 7th St E Cornwall ON K6H 2S1",
    "addr:housenumber":"401",
    "addr:postcode":"k6h 2s1",
    "addr:street":"7Th St E",
    "iso:country":"CA",
    "sg:address":"401 7th St E",
    "sg:city":"Cornwall",
    "sg:classifiers":[
        {
            "category":"Food & Beverages",
            "subcategory":"Groceries & Convenience Stores",
            "type":"Retail Goods"
        }
    ],
    "sg:phone":"+1 613 933 8767",
    "sg:postcode":"K6H 2S1",
    "sg:province":"ON",
    "wof:name":"Mado's",
    "wof:placetype":"venue"
},
  "geometry": {"coordinates":[-74.724442,45.028309],"type":"Point"}
}