{
  "type": "Feature",
  "properties": {
    "addr:full":"Penticton BC V2A 5H3",
    "addr:postcode":"v2a 5h3",
    "iso:country":"CA",
    "sg:city":"Penticton",
    "sg:classifiers":[
        {
            "category":"Health Services",
            "subcategory":"Doctor",
            "type":"Services"
        }
    ],
    "sg:phone":"+1 250 492 8911",
    "sg:postcode":"V2A 5H3",
    "sg:province":"BC",
    "sg:tags":[
        "dentist"
    ],
    "wof:name":"Newman, Joanna DDS",
    "wof:placetype":"venue"
},
  "geometry": {"coordinates":[-119.583733,49.478054],"type":"Point"}
}