{
  "type": "Feature",
  "properties": {
    "addr:full":"595 Columbia St W Kamloops BC V2C 1K7",
    "addr:housenumber":"595",
    "addr:postcode":"bc v2c 1k7",
    "addr:street":"Columbia St W",
    "iso:country":"CA",
    "sg:address":"595 Columbia St W",
    "sg:city":"Kamloops",
    "sg:classifiers":[
        {
            "category":"Health Services",
            "subcategory":"Doctor",
            "type":"Services"
        }
    ],
    "sg:phone":"+1 250 828 2771",
    "sg:postcode":"V2C 1K7",
    "sg:province":"BC",
    "sg:tags":[
        "physician",
        "surgeon"
    ],
    "wof:name":"Mia, Raziya MD",
    "wof:placetype":"venue"
},
  "geometry": {"coordinates":[-120.352867,50.67239],"type":"Point"}
}