{
  "type": "Feature",
  "properties": {
    "addr:full":"Ahtahkakoop Reserve Canwood SK S0J 0K0",
    "addr:postcode":"s0j 0k0",
    "iso:country":"CA",
    "sg:address":"Ahtahkakoop Reserve",
    "sg:city":"Canwood",
    "sg:classifiers":[
        {
            "category":"Professional",
            "subcategory":"Management & Consulting",
            "type":"Services"
        }
    ],
    "sg:phone":"+1 306 468 2533",
    "sg:postcode":"S0J 0K0",
    "sg:province":"SK",
    "sg:tags":[
        "consultant",
        "business"
    ],
    "wof:name":"Nra & Assoc",
    "wof:placetype":"venue"
},
  "geometry": {"coordinates":[-106.604812622,53.3596763611],"type":"Point"}
}