{
  "type": "Feature",
  "properties": {
    "addr:full":"15150 Longwoods Rd Bothwell ON N0P 1C0",
    "addr:housenumber":"15150",
    "addr:postcode":"n0p 1c0",
    "addr:street":"Longwoods Rd",
    "iso:country":"CA",
    "sg:address":"15150 Longwoods Rd",
    "sg:city":"Bothwell",
    "sg:classifiers":[
        {
            "category":"Professional",
            "subcategory":"Accounting & Tax Preparation",
            "type":"Services"
        }
    ],
    "sg:phone":"+1 519 695 3425",
    "sg:postcode":"N0P 1C0",
    "sg:province":"ON",
    "sg:tags":[
        "return",
        "filing"
    ],
    "wof:name":"C K Tax & Accounting",
    "wof:placetype":"venue"
},
  "geometry": {"coordinates":[-81.8846206665,42.6010780334],"type":"Point"}
}