{
  "type": "Feature",
  "properties": {
    "iso:country":"CA",
    "sg:address":"15 Cedar Pointe Dr",
    "sg:city":"Barrie",
    "sg:classifiers":[
        {
            "category":"Government",
            "subcategory":"Office",
            "type":"Public Place"
        }
    ],
    "sg:phone":"+1 705 725 7215",
    "sg:postcode":"L4N 5R7",
    "sg:province":"ON",
    "sg:tags":[
        "village"
    ],
    "wof:name":"South Simcoe & Barrie Housing",
    "wof:placetype":"venue"
},
  "geometry": {"coordinates":[-79.713486,44.38015],"type":"Point"}
}