{
  "type": "Feature",
  "properties": {
    "addr:full":"2827 Dundas St W Toronto ON M6P 1Y6",
    "addr:housenumber":"2827",
    "addr:postcode":"m6p 1y6",
    "addr:street":"Dundas St W",
    "iso:country":"CA",
    "sg:address":"2827 Dundas St W",
    "sg:city":"Toronto",
    "sg:classifiers":[
        {
            "category":"Recreation",
            "type":"Entertainment"
        }
    ],
    "sg:phone":"+1 416 762 7097",
    "sg:postcode":"M6P 1Y6",
    "sg:province":"ON",
    "sg:tags":[
        "parlor",
        "billiard"
    ],
    "wof:name":"Shoxs Billiard Lounge",
    "wof:placetype":"venue"
},
  "geometry": {"coordinates":[-79.46363100000001,43.665215],"type":"Point"}
}