{
  "type": "Feature",
  "properties": {
    "addr:full":"PO Box 1 Wildwood AB T0E 2M0",
    "addr:housenumber":"po;1",
    "addr:postcode":"t0e 2m0",
    "addr:street":"Box",
    "iso:country":"CA",
    "sg:address":"PO Box 1",
    "sg:city":"Wildwood",
    "sg:classifiers":[
        {
            "category":"Freight",
            "type":"Transportation"
        }
    ],
    "sg:phone":"+1 780 325 3795",
    "sg:postcode":"T0E 2M0",
    "sg:province":"AB",
    "sg:tags":[
        "cartage"
    ],
    "wof:name":"Dee Jay's Trucking",
    "wof:placetype":"venue"
},
  "geometry": {"coordinates":[-115.236083984,53.6040916443],"type":"Point"}
}