{
  "type": "Feature",
  "properties": {
    "addr:full":"26 Erie St Stratford ON N5A 2M4",
    "addr:housenumber":"26",
    "addr:postcode":"n5a 2m4",
    "addr:street":"Erie St",
    "iso:country":"CA",
    "sg:address":"26 Erie St",
    "sg:city":"Stratford",
    "sg:classifiers":[
        {
            "category":"Restaurant",
            "type":"Food & Drink"
        }
    ],
    "sg:phone":"+1 519 275 3147",
    "sg:postcode":"N5A 2M4",
    "sg:province":"ON",
    "wof:name":"Boomers Gourmet Fries",
    "wof:placetype":"venue"
},
  "geometry": {"coordinates":[-80.98342132569999,43.3709373474],"type":"Point"}
}