{
  "type": "Feature",
  "properties": {
    "addr:full":"529 Mckay Ave North Bay ON P1B 7V7",
    "addr:housenumber":"529",
    "addr:postcode":"p1b 7v7",
    "addr:street":"Mckay Ave",
    "iso:country":"CA",
    "sg:address":"529 Mckay Ave",
    "sg:city":"North Bay",
    "sg:classifiers":[
        {
            "category":"Organizations",
            "subcategory":"Religious Organization",
            "type":"Services"
        }
    ],
    "sg:phone":"+1 705 494 9710",
    "sg:postcode":"P1B 7V7",
    "sg:province":"ON",
    "sg:tags":[
        "church"
    ],
    "wof:name":"Wesleyan Methodist Church",
    "wof:placetype":"venue"
},
  "geometry": {"coordinates":[-79.437134,46.322109],"type":"Point"}
}