{
  "type": "Feature",
  "properties": {
    "addr:full":"25 Rue Hill Edmundston NB E3V 1H7",
    "addr:housenumber":"25",
    "addr:postcode":"e3v 1h7",
    "addr:street":"Rue Hill",
    "iso:country":"CA",
    "sg:address":"25 Rue Hill",
    "sg:city":"Edmundston",
    "sg:classifiers":[
        {
            "category":"Retail",
            "subcategory":"Repair Shop",
            "type":"Services"
        }
    ],
    "sg:phone":"+1 506 735 4073",
    "sg:postcode":"E3V 1H7",
    "sg:province":"NB",
    "sg:tags":[
        "radio",
        "television",
        "electronic",
        "equipment"
    ],
    "wof:name":"Data Electronic Inc",
    "wof:placetype":"venue"
},
  "geometry": {"coordinates":[-68.3282241821,47.3629264832],"type":"Point"}
}