{
  "type": "Feature",
  "properties": {
    "addr:full":"205 Simeon St Kitchener ON N2H 1S9",
    "addr:housenumber":"205",
    "addr:postcode":"n2h 1s9",
    "addr:street":"Simeon St",
    "iso:country":"CA",
    "sg:address":"205 Simeon St",
    "sg:city":"Kitchener",
    "sg:classifiers":[
        {
            "category":"Building & Trades",
            "subcategory":"Construction",
            "type":"Services"
        }
    ],
    "sg:phone":"+1 519 570 1225",
    "sg:postcode":"N2H 1S9",
    "sg:province":"ON",
    "sg:tags":[
        "home",
        "improvement"
    ],
    "wof:name":"Mc Lead Woodcraft",
    "wof:placetype":"venue"
},
  "geometry": {"coordinates":[-80.474739,43.449158],"type":"Point"}
}