{
  "type": "Feature",
  "properties": {
    "addr:full":"417 Montrose Rd Belleville ON K8R 1B2",
    "addr:housenumber":"417",
    "addr:postcode":"k8r 1b2",
    "addr:street":"Montrose Rd",
    "iso:country":"CA",
    "sg:address":"417 Montrose Rd",
    "sg:city":"Belleville",
    "sg:classifiers":[
        {
            "category":"Health Services",
            "subcategory":"Clinic",
            "type":"Services"
        }
    ],
    "sg:phone":"+1 613 962 7933",
    "sg:postcode":"K8R 1B2",
    "sg:province":"ON",
    "sg:tags":[
        "aid",
        "first"
    ],
    "wof:name":"St John Ambulance",
    "wof:placetype":"venue"
},
  "geometry": {"coordinates":[-77.38189697270001,44.1610450745],"type":"Point"}
}