{
  "type": "Feature",
  "properties": {
    "iso:country":"CA",
    "sg:address":"769 Rue Jean-Talon O",
    "sg:city":"Montreal",
    "sg:classifiers":[
        {
            "category":"Food & Beverages",
            "subcategory":"Bakery",
            "type":"Retail Goods"
        }
    ],
    "sg:phone":"+1 514 271 2432",
    "sg:postcode":"H3N 1S3",
    "sg:province":"QC",
    "sg:tags":[
        "baker"
    ],
    "wof:name":"Patisserie Boulangerie Mimosa",
    "wof:placetype":"venue"
},
  "geometry": {"coordinates":[-73.613441,45.540543],"type":"Point"}
}