{
  "type": "Feature",
  "properties": {
    "iso:country":"CA",
    "sg:address":"764 Sheppard Ave W",
    "sg:city":"North York",
    "sg:classifiers":[
        {
            "category":"Organizations",
            "subcategory":"Religious Organization",
            "type":"Services"
        }
    ],
    "sg:phone":"+1 416 636 1045",
    "sg:postcode":"M3H 2S8",
    "sg:province":"ON",
    "sg:tags":[
        "church"
    ],
    "wof:name":"Toronto Jewish Mission",
    "wof:placetype":"venue"
},
  "geometry": {"coordinates":[-79.4478378296,43.7536964417],"type":"Point"}
}