{
  "type": "Feature",
  "properties": {
    "addr:full":"162 Rue Des Saules Shippagan NB E8S 1K5",
    "addr:housenumber":"162",
    "addr:postcode":"e8s 1k5",
    "addr:street":"Rue Des Saules",
    "iso:country":"CA",
    "sg:address":"162 Rue Des Saules",
    "sg:city":"Shippagan",
    "sg:classifiers":[
        {
            "category":"Autos & Motor Vehicles",
            "subcategory":"Motorcycle Sales",
            "type":"Retail Goods"
        }
    ],
    "sg:phone":"+1 506 336 8718",
    "sg:postcode":"E8S 1K5",
    "sg:province":"NB",
    "sg:tags":[
        "scooter"
    ],
    "wof:name":"Mallet Sport",
    "wof:placetype":"venue"
},
  "geometry": {"coordinates":[-64.709755,47.739544],"type":"Point"}
}