{
  "type": "Feature",
  "properties": {
    "iso:country":"CA",
    "sg:address":"892 Rue Bernard-Pilon",
    "sg:city":"Mcmasterville",
    "sg:classifiers":[
        {
            "category":"Social Services",
            "type":"Services"
        }
    ],
    "sg:phone":"+1 450 446 9058",
    "sg:postcode":"J3G 5W8",
    "sg:province":"QC",
    "sg:tags":[
        "organization",
        "welfare"
    ],
    "wof:name":"Centre Professionnel-Patriotes",
    "wof:placetype":"venue"
},
  "geometry": {"coordinates":[-73.227303,45.554417],"type":"Point"}
}