{
  "type": "Feature",
  "properties": {
    "iso:country":"CA",
    "sg:address":"23 Prospect Ave",
    "sg:city":"Kirkland Lake",
    "sg:classifiers":[
        {
            "category":"Personal",
            "subcategory":"Beauty Salon",
            "type":"Services"
        }
    ],
    "sg:phone":"+1 705 567 7575",
    "sg:postcode":"P2N 2V3",
    "sg:province":"ON",
    "wof:name":"Lasting Impressions Hair Dsgn",
    "wof:placetype":"venue"
},
  "geometry": {"coordinates":[-80.0341949463,48.150302887],"type":"Point"}
}