{
  "type": "Feature",
  "properties": {
    "addr:full":"1324 Blundell Rd Mississauga ON L4Y 1M5",
    "addr:housenumber":"1324",
    "addr:postcode":"l4y 1m5",
    "addr:street":"Blundell Rd",
    "iso:country":"CA",
    "sg:address":"1324 Blundell Rd",
    "sg:city":"Mississauga",
    "sg:classifiers":[
        {
            "category":"Autos & Motor Vehicles",
            "subcategory":"Auto Supplies",
            "type":"Retail Goods"
        }
    ],
    "sg:phone":"+1 905 615 8620",
    "sg:postcode":"L4Y 1M5",
    "sg:province":"ON",
    "sg:tags":[
        "equipment",
        "air",
        "conditioning",
        "automobile"
    ],
    "wof:name":"U View Ultraviolet Systems Inc",
    "wof:placetype":"venue"
},
  "geometry": {"coordinates":[-79.5810470581,43.6063995361],"type":"Point"}
}