{
  "type": "Feature",
  "properties": {
    "iso:country":"CA",
    "sg:city":"Calgary",
    "sg:classifiers":[
        {
            "category":"Shopping",
            "subcategory":"Clothing, Apparel, & Fashions",
            "type":"Retail Goods"
        }
    ],
    "sg:phone":"+1 403 246 8855",
    "sg:postcode":"T3C 1S2",
    "sg:province":"AB",
    "sg:tags":[
        "alteration"
    ],
    "wof:name":"Sue Alterations & Repair",
    "wof:placetype":"venue"
},
  "geometry": {"coordinates":[-114.140923,51.041351],"type":"Point"}
}