{
  "type": "Feature",
  "properties": {
    "addr:full":"676 Memorial Ave Thunder Bay ON P7B 3Z5",
    "addr:housenumber":"676",
    "addr:postcode":"p7b 3z5",
    "addr:street":"Memorial Ave",
    "iso:country":"CA",
    "sg:address":"676 Memorial Ave",
    "sg:city":"Thunder Bay",
    "sg:classifiers":[
        {
            "category":"Manufacturing",
            "subcategory":"Metals",
            "type":"Manufacturing & Wholesale Goods"
        }
    ],
    "sg:phone":"+1 807 344 2469",
    "sg:postcode":"P7B 3Z5",
    "sg:province":"ON",
    "sg:tags":[
        "coating"
    ],
    "wof:name":"Glidden Paints",
    "wof:placetype":"venue"
},
  "geometry": {"coordinates":[-89.24243199999999,48.415588],"type":"Point"}
}