{
  "type": "Feature",
  "properties": {
    "addr:full":"SW 15-6-23 Hartney MB R0M 0X0",
    "addr:postcode":"15-6-23;r0m 0x0",
    "addr:street":"Sw",
    "iso:country":"CA",
    "sg:address":"SW 15-6-23",
    "sg:city":"Hartney",
    "sg:classifiers":[
        {
            "category":"Government",
            "subcategory":"Office",
            "type":"Public Place"
        }
    ],
    "sg:phone":"+1 204 858 2614",
    "sg:postcode":"R0M 0X0",
    "sg:province":"MB",
    "wof:name":"Manitoba Maintenance Yard",
    "wof:placetype":"venue"
},
  "geometry": {"coordinates":[-100.528015,49.477478],"type":"Point"}
}