{
  "type": "Feature",
  "properties": {
    "addr:full":"45 Boul Laurier Mcmasterville QC J3G 1P7",
    "addr:housenumber":"45",
    "addr:postcode":"j3g 1p7",
    "addr:street":"Boul Laurier",
    "iso:country":"CA",
    "sg:address":"45 Boul Laurier",
    "sg:city":"Mcmasterville",
    "sg:classifiers":[
        {
            "category":"Retail",
            "subcategory":"Repair Shop",
            "type":"Services"
        }
    ],
    "sg:phone":"+1 450 467 3478",
    "sg:postcode":"J3G 1P7",
    "sg:province":"QC",
    "sg:tags":[
        "lock",
        "locksmith"
    ],
    "wof:name":"Atelier DE Serrures Fabris",
    "wof:placetype":"venue"
},
  "geometry": {"coordinates":[-73.221581,45.549133],"type":"Point"}
}