{
  "type": "Feature",
  "properties": {
    "addr:full":"Mission BC V2V 6M7",
    "addr:postcode":"v2v 6m7",
    "iso:country":"CA",
    "sg:city":"Mission",
    "sg:classifiers":[
        {
            "category":"Shopping",
            "subcategory":"Clothing, Apparel, & Fashions",
            "type":"Retail Goods"
        }
    ],
    "sg:phone":"+1 604 814 2291",
    "sg:postcode":"V2V 6M7",
    "sg:province":"BC",
    "sg:tags":[
        "jean"
    ],
    "wof:name":"Warehouse One the Jeans Store",
    "wof:placetype":"venue"
},
  "geometry": {"coordinates":[-122.317642212,49.1289710999],"type":"Point"}
}