{
  "type": "Feature",
  "properties": {
    "iso:country":"CA",
    "sg:address":"229 Pearl St",
    "sg:city":"Thunder Bay",
    "sg:classifiers":[
        {
            "category":"Professional",
            "subcategory":"Management & Consulting",
            "type":"Services"
        }
    ],
    "sg:phone":"+1 807 344 1959",
    "sg:postcode":"P7B 1E3",
    "sg:province":"ON",
    "sg:tags":[
        "development",
        "economic",
        "agency"
    ],
    "wof:name":"Axxis Development Inc",
    "wof:placetype":"venue"
},
  "geometry": {"coordinates":[-89.2227935791,48.4332542419],"type":"Point"}
}