{
  "type": "Feature",
  "properties": {
    "addr:full":"290 Shuter St Toronto ON M5A 1W7",
    "addr:housenumber":"290",
    "addr:postcode":"m5a 1w7",
    "addr:street":"Shuter St",
    "iso:country":"CA",
    "sg:address":"290 Shuter St",
    "sg:city":"Toronto",
    "sg:classifiers":[
        {
            "category":"Shopping",
            "subcategory":"Photographic Equipment",
            "type":"Retail Goods"
        }
    ],
    "sg:phone":"+1 416 466 9600",
    "sg:postcode":"M5A 1W7",
    "sg:province":"ON",
    "sg:tags":[
        "supply"
    ],
    "wof:name":"Headshots Rentals Inc",
    "wof:placetype":"venue"
},
  "geometry": {"coordinates":[-79.365562,43.656872],"type":"Point"}
}