{
  "type": "Feature",
  "properties": {
    "addr:full":"111 W 2nd St Revelstoke BC V0E 2S0",
    "addr:housenumber":"111",
    "addr:postcode":"v0e 2s0",
    "addr:street":"W 2Nd St",
    "iso:country":"CA",
    "sg:address":"111 W 2nd St",
    "sg:city":"Revelstoke",
    "sg:classifiers":[
        {
            "category":"Health Services",
            "subcategory":"Doctor",
            "type":"Services"
        }
    ],
    "sg:phone":"+1 250 837 6231",
    "sg:postcode":"V0E 2S0",
    "sg:province":"BC",
    "sg:tags":[
        "dentist"
    ],
    "wof:name":"Revelstoke Dental Ctr",
    "wof:placetype":"venue"
},
  "geometry": {"coordinates":[-118.19641900000001,50.998199],"type":"Point"}
}