{
  "type": "Feature",
  "properties": {
    "addr:full":"49 River St W Prince Albert SK S6V 2Y9",
    "addr:housenumber":"49",
    "addr:postcode":"s6v 2y9",
    "addr:street":"River St",
    "iso:country":"CA",
    "sg:address":"49 River St W",
    "sg:city":"Prince Albert",
    "sg:classifiers":[
        {
            "category":"Shopping",
            "subcategory":"Used Merchandise",
            "type":"Retail Goods"
        }
    ],
    "sg:phone":"+1 306 763 6600",
    "sg:postcode":"S6V 2Y9",
    "sg:province":"SK",
    "sg:tags":[
        "pawnbroker"
    ],
    "wof:name":"Riverside Pawn & Second Hand",
    "wof:placetype":"venue"
},
  "geometry": {"coordinates":[-105.755424499,53.205116272],"type":"Point"}
}