{
  "type": "Feature",
  "properties": {
    "addr:full":"PO Box 150 Salmon Cove Bdv NL A0A 3S0",
    "addr:housenumber":"po",
    "addr:postcode":"a0a 3s0",
    "addr:street":"Box 150 Salmon Cove",
    "iso:country":"CA",
    "sg:address":"PO Box 150",
    "sg:city":"Salmon Cove Bdv",
    "sg:classifiers":[
        {
            "category":"Retail",
            "subcategory":"Auto Repair",
            "type":"Services"
        }
    ],
    "sg:phone":"+1 709 596 5852",
    "sg:postcode":"A0A 3S0",
    "sg:province":"NL",
    "sg:tags":[
        "repairing",
        "automobile"
    ],
    "wof:name":"Slade's Garage",
    "wof:placetype":"venue"
},
  "geometry": {"coordinates":[-53.175121,47.781971],"type":"Point"}
}