{
  "type": "Feature",
  "properties": {
    "iso:country":"CA",
    "sg:city":"Vancouver",
    "sg:classifiers":[
        {
            "category":"Real Estate",
            "subcategory":"Real Estate Agent",
            "type":"Services"
        }
    ],
    "sg:phone":"+1 604 733 1804",
    "sg:postcode":"V6H 1M2",
    "sg:province":"BC",
    "sg:tags":[
        "management"
    ],
    "wof:name":"Rendora Apartments",
    "wof:placetype":"venue"
},
  "geometry": {"coordinates":[-123.13584136999999,49.2609062195],"type":"Point"}
}