{
  "type": "Feature",
  "properties": {
    "addr:full":"33 Isabella St Toronto ON M4Y 2P7",
    "addr:housenumber":"33",
    "addr:postcode":"m4y 2p7",
    "addr:street":"Isabella St",
    "iso:country":"CA",
    "sg:address":"33 Isabella St",
    "sg:city":"Toronto",
    "sg:classifiers":[
        {
            "category":"Building & Trades",
            "subcategory":"Cleaning & Sanitation",
            "type":"Services"
        }
    ],
    "sg:phone":"+1 416 929 8073",
    "sg:postcode":"M4Y 2P7",
    "sg:province":"ON",
    "sg:tags":[
        "property",
        "maintenance"
    ],
    "wof:name":"Salford Properties",
    "wof:placetype":"venue"
},
  "geometry": {"coordinates":[-79.383865,43.667786],"type":"Point"}
}