{
  "type": "Feature",
  "properties": {
    "addr:full":"Joliette QC J6E 6X6",
    "addr:postcode":"j6e 6x6",
    "iso:country":"CA",
    "sg:city":"Joliette",
    "sg:classifiers":[
        {
            "category":"Recreation",
            "type":"Entertainment"
        }
    ],
    "sg:phone":"+1 450 753 5118",
    "sg:postcode":"J6E 6X6",
    "sg:province":"QC",
    "sg:tags":[
        "lottery",
        "agent"
    ],
    "wof:name":"Kiosque Loto Quebec",
    "wof:placetype":"venue"
},
  "geometry": {"coordinates":[-73.426109314,46.0338401794],"type":"Point"}
}