{
  "type": "Feature",
  "properties": {
    "addr:full":"4658 Montee Gagnon RR 40 Terrebonne QC J6Y 1J4",
    "addr:housenumber":"40",
    "addr:postcode":"4658;j6y 1j4",
    "addr:street":"Montee Gagnon Rr",
    "iso:country":"CA",
    "sg:address":"4658 Montee Gagnon RR 40",
    "sg:city":"Terrebonne",
    "sg:classifiers":[
        {
            "category":"Building & Trades",
            "subcategory":"Plumbing",
            "type":"Services"
        }
    ],
    "sg:phone":"+1 450 433 3852",
    "sg:postcode":"J6Y 1J4",
    "sg:province":"QC",
    "sg:tags":[
        "refrigeration",
        "contractor"
    ],
    "wof:name":"Entreprises Rg",
    "wof:placetype":"venue"
},
  "geometry": {"coordinates":[-73.8194732666,45.7125854492],"type":"Point"}
}