{
  "type": "Feature",
  "properties": {
    "iso:country":"CA",
    "sg:city":"Chilliwack",
    "sg:classifiers":[
        {
            "category":"Retail",
            "subcategory":"Auto Repair",
            "type":"Services"
        }
    ],
    "sg:phone":"+1 604 792 6919",
    "sg:postcode":"V2P 6H4",
    "sg:province":"BC",
    "sg:tags":[
        "wrecker"
    ],
    "wof:name":"Cheap Towing",
    "wof:placetype":"venue"
},
  "geometry": {"coordinates":[-121.888671875,49.182975769],"type":"Point"}
}