{
  "type": "Feature",
  "properties": {
    "iso:country":"CA",
    "sg:address":"2131 Av Laurier E",
    "sg:city":"Montreal",
    "sg:classifiers":[
        {
            "category":"Retail",
            "subcategory":"Laundry & Dry Cleaning",
            "type":"Services"
        }
    ],
    "sg:phone":"+1 514 522 4944",
    "sg:postcode":"H2H 1C1",
    "sg:province":"QC",
    "sg:tags":[
        "cleaners"
    ],
    "wof:name":"Nettoyeur Dumont Laurier Enr",
    "wof:placetype":"venue"
},
  "geometry": {"coordinates":[-73.578232,45.538422],"type":"Point"}
}