{
  "type": "Feature",
  "properties": {
    "addr:full":"417 Dufferin Ave London ON N6B 1Z7",
    "addr:housenumber":"417",
    "addr:postcode":"n6b 1z7",
    "addr:street":"Dufferin Ave",
    "iso:country":"CA",
    "sg:address":"417 Dufferin Ave",
    "sg:city":"London",
    "sg:classifiers":[
        {
            "category":"Health Services",
            "subcategory":"Health Practitioner",
            "type":"Services"
        }
    ],
    "sg:phone":"+1 519 439 3902",
    "sg:postcode":"N6B 1Z7",
    "sg:province":"ON",
    "sg:tags":[
        "psychologist"
    ],
    "wof:name":"Judith Schachter & Assoc",
    "wof:placetype":"venue"
},
  "geometry": {"coordinates":[-81.24020400000001,42.989162],"type":"Point"}
}