{
  "type": "Feature",
  "properties": {
    "addr:full":"1255 Rue Amherst Montreal QC H2L 3K9",
    "addr:housenumber":"1255",
    "addr:postcode":"h2l 3k9",
    "addr:street":"Rue Amherst",
    "iso:country":"CA",
    "sg:address":"1255 Rue Amherst",
    "sg:city":"Montreal",
    "sg:classifiers":[
        {
            "category":"Retail",
            "subcategory":"Repair Shop",
            "type":"Services"
        }
    ],
    "sg:phone":"+1 514 522 2278",
    "sg:postcode":"H2L 3K9",
    "sg:province":"QC",
    "sg:tags":[
        "jeweler"
    ],
    "wof:name":"Bijouterie D'Epargne Enrg",
    "wof:placetype":"venue"
},
  "geometry": {"coordinates":[-73.55549600000001,45.516911],"type":"Point"}
}