{
  "type": "Feature",
  "properties": {
    "addr:full":"3660 18th Ave Prince George BC V2N 1A9",
    "addr:housenumber":"3660",
    "addr:postcode":"v2n 1a9",
    "addr:street":"18Th Ave",
    "iso:country":"CA",
    "sg:address":"3660 18th Ave",
    "sg:city":"Prince George",
    "sg:classifiers":[
        {
            "category":"Retail",
            "subcategory":"Repair Shop",
            "type":"Services"
        }
    ],
    "sg:phone":"+1 250 562 8833",
    "sg:postcode":"V2N 1A9",
    "sg:province":"BC",
    "sg:tags":[
        "tool",
        "parts"
    ],
    "wof:name":"Accurate Tool & Repair",
    "wof:placetype":"venue"
},
  "geometry": {"coordinates":[-122.787659,53.907429],"type":"Point"}
}