{
  "type": "Feature",
  "properties": {
    "iso:country":"CA",
    "sg:address":"40 Rue Du Loup",
    "sg:city":"Wendake",
    "sg:classifiers":[
        {
            "category":"Health Services",
            "subcategory":"Health Practitioner",
            "type":"Services"
        }
    ],
    "sg:phone":"+1 418 847 2161",
    "sg:postcode":"G0A 4V0",
    "sg:province":"QC",
    "sg:tags":[
        "physician"
    ],
    "wof:name":"Clinique Richard Assinuuk",
    "wof:placetype":"venue"
},
  "geometry": {"coordinates":[-71.362159729,46.8678970337],"type":"Point"}
}