{
  "type": "Feature",
  "properties": {
    "addr:full":"1919 Rang 3 Howick QC J0S 1G0",
    "addr:housenumber":"1919;3",
    "addr:postcode":"j0s 1g0",
    "addr:street":"Rang",
    "iso:country":"CA",
    "sg:address":"1919 Rang 3",
    "sg:city":"Howick",
    "sg:classifiers":[
        {
            "category":"Wholesale",
            "subcategory":"Machinery & Supplies",
            "type":"Manufacturing & Wholesale Goods"
        }
    ],
    "sg:phone":"+1 450 825 2286",
    "sg:postcode":"J0S 1G0",
    "sg:province":"QC",
    "sg:tags":[
        "farm",
        "equipment",
        "lawn",
        "garden"
    ],
    "wof:name":"Equipement Albert Billette Enr",
    "wof:placetype":"venue"
},
  "geometry": {"coordinates":[-73.856667,45.19368],"type":"Point"}
}