{
  "type": "Feature",
  "properties": {
    "iso:country":"CA",
    "sg:city":"Saint-Cyprien",
    "sg:classifiers":[
        {
            "category":"Building & Trades",
            "subcategory":"Plumbing",
            "type":"Services"
        }
    ],
    "sg:phone":"+1 418 963 2737",
    "sg:postcode":"G0L 2P0",
    "sg:province":"QC",
    "sg:tags":[
        "contractor"
    ],
    "wof:name":"Plomberie Lionel Lagace",
    "wof:placetype":"venue"
},
  "geometry": {"coordinates":[-69.0200576782,47.8965377808],"type":"Point"}
}