{
  "type": "Feature",
  "properties": {
    "iso:country":"CA",
    "sg:city":"Edmonton",
    "sg:classifiers":[
        {
            "category":"Education",
            "subcategory":"School",
            "type":"Public Place"
        }
    ],
    "sg:phone":"+1 780 477 8152",
    "sg:postcode":"T5B 0A1",
    "sg:province":"AB",
    "wof:name":"Virginia Park Elementary Schl",
    "wof:placetype":"venue"
},
  "geometry": {"coordinates":[-113.448486328,53.5601882935],"type":"Point"}
}