{
  "type": "Feature",
  "properties": {
    "iso:country":"CA",
    "sg:address":"344 Rue Drean",
    "sg:city":"Chicoutimi",
    "sg:classifiers":[
        {
            "category":"Manufacturing",
            "subcategory":"Food",
            "type":"Manufacturing & Wholesale Goods"
        }
    ],
    "sg:phone":"+1 418 693 8057",
    "sg:postcode":"G7J 3K4",
    "sg:province":"QC",
    "sg:tags":[
        "cocoa",
        "candy",
        "chocolate"
    ],
    "wof:name":"Confiserie Aux P'Tits Delices",
    "wof:placetype":"venue"
},
  "geometry": {"coordinates":[-71.0774,48.427193],"type":"Point"}
}