{
  "type": "Feature",
  "properties": {
    "addr:full":"1355 Kingston Rd #133 Pickering ON L1V 1B8",
    "addr:housenumber":"1355",
    "addr:postcode":"l1v 1b8",
    "addr:street":"Kingston Rd # 133",
    "iso:country":"CA",
    "sg:address":"1355 Kingston Rd #133",
    "sg:city":"Pickering",
    "sg:classifiers":[
        {
            "category":"Shopping",
            "subcategory":"Luggage & Leather Goods",
            "type":"Retail Goods"
        }
    ],
    "sg:phone":"+1 905 831 4105",
    "sg:postcode":"L1V 1B8",
    "sg:province":"ON",
    "wof:name":"Bentley Leathers Inc",
    "wof:placetype":"venue"
},
  "geometry": {"coordinates":[-79.0872421265,43.8379707336],"type":"Point"}
}