{
  "type": "Feature",
  "properties": {
    "addr:full":"4214 Rue Jean-Talon E Saint-Leonard QC H1S 1J7",
    "addr:housenumber":"4214",
    "addr:postcode":"h1s 1j7",
    "addr:street":"Rue Jean-Talon E",
    "iso:country":"CA",
    "sg:address":"4214 Rue Jean-Talon E",
    "sg:city":"Saint-Leonard",
    "sg:classifiers":[
        {
            "category":"Shopping",
            "subcategory":"Clothing, Apparel, & Fashions",
            "type":"Retail Goods"
        }
    ],
    "sg:phone":"+1 514 376 1275",
    "sg:postcode":"H1S 1J7",
    "sg:province":"QC",
    "sg:tags":[
        "item",
        "boutique"
    ],
    "wof:name":"Wan Arts Oriental",
    "wof:placetype":"venue"
},
  "geometry": {"coordinates":[-73.59024047849999,45.567779541],"type":"Point"}
}