{
  "type": "Feature",
  "properties": {
    "iso:country":"CA",
    "sg:city":"Mississauga",
    "sg:classifiers":[
        {
            "category":"Manufacturing",
            "subcategory":"Food",
            "type":"Manufacturing & Wholesale Goods"
        }
    ],
    "sg:phone":"+1 905 568 3099",
    "sg:postcode":"L4Z 1R5",
    "sg:province":"ON",
    "sg:tags":[
        "frozen",
        "grocer",
        "fruit"
    ],
    "wof:name":"Supreme Pierogies Inc",
    "wof:placetype":"venue"
},
  "geometry": {"coordinates":[-79.6566543579,43.6253814697],"type":"Point"}
}