{
  "type": "Feature",
  "properties": {
    "addr:full":"1770 Boul Talbot Stoneham QC G0A 4P0",
    "addr:housenumber":"1770",
    "addr:postcode":"g0a 4p0",
    "addr:street":"Boul Talbot",
    "iso:country":"CA",
    "sg:address":"1770 Boul Talbot",
    "sg:city":"Stoneham",
    "sg:classifiers":[
        {
            "category":"Health Services",
            "subcategory":"Nursing And Care Facility",
            "type":"Services"
        }
    ],
    "sg:phone":"+1 418 848 0148",
    "sg:postcode":"G0A 4P0",
    "sg:province":"QC",
    "sg:tags":[
        "home",
        "retirement",
        "community",
        "rest"
    ],
    "wof:name":"Residence D'Accueil Le Manoir",
    "wof:placetype":"venue"
},
  "geometry": {"coordinates":[-71.360146,46.994301],"type":"Point"}
}