{
  "type": "Feature",
  "properties": {
    "addr:full":"Montreal QC H2N 1P3",
    "addr:postcode":"h2n 1p3",
    "iso:country":"CA",
    "sg:city":"Montreal",
    "sg:classifiers":[
        {
            "category":"Wholesale",
            "subcategory":"Apparel",
            "type":"Manufacturing & Wholesale Goods"
        }
    ],
    "sg:phone":"+1 514 383 4422",
    "sg:postcode":"H2N 1P3",
    "sg:province":"QC",
    "sg:tags":[
        "sportswear"
    ],
    "wof:name":"Lana-Lee Fashions Inc",
    "wof:placetype":"venue"
},
  "geometry": {"coordinates":[-73.65277862550001,45.5447845459],"type":"Point"}
}