{
  "type": "Feature",
  "properties": {
    "addr:full":"1400 Ch Du Lac-Aux-Quenouilles Lac-Superieur QC J0T 1J0",
    "addr:housenumber":"1400",
    "addr:postcode":"j0t 1j0",
    "addr:street":"Ch Du Lac-Aux-Quenouilles Lac-Superieur",
    "iso:country":"CA",
    "sg:address":"1400 Ch Du Lac-Aux-Quenouilles",
    "sg:city":"Lac-Superieur",
    "sg:classifiers":[
        {
            "category":"Travel",
            "subcategory":"Hotels & Motels",
            "type":"Entertainment"
        }
    ],
    "sg:phone":"+1 819 326 4281",
    "sg:postcode":"J0T 1J0",
    "sg:province":"QC",
    "sg:tags":[
        "outing",
        "facility"
    ],
    "wof:name":"Auberge Le Petit Bonheur",
    "wof:placetype":"venue"
},
  "geometry": {"coordinates":[-74.39171600340001,46.1519241333],"type":"Point"}
}