{
  "type": "Feature",
  "properties": {
    "addr:full":"Scarborough ON M1R 4E2",
    "addr:postcode":"m1r 4e2",
    "iso:country":"CA",
    "sg:city":"Scarborough",
    "sg:classifiers":[
        {
            "category":"Personal",
            "subcategory":"Beauty Salon",
            "type":"Services"
        }
    ],
    "sg:phone":"+1 416 449 6262",
    "sg:postcode":"M1R 4E2",
    "sg:province":"ON",
    "wof:name":"Hair & Now Hair Design",
    "wof:placetype":"venue"
},
  "geometry": {"coordinates":[-79.303574,43.760414],"type":"Point"}
}