{
  "type": "Feature",
  "properties": {
    "addr:full":"63 William Stephenson Dr Whitby ON L1N 8R9",
    "addr:housenumber":"63",
    "addr:postcode":"l1n 8r9",
    "addr:street":"William Stephenson Dr",
    "iso:country":"CA",
    "sg:address":"63 William Stephenson Dr",
    "sg:city":"Whitby",
    "sg:classifiers":[
        {
            "category":"Wholesale",
            "subcategory":"Office Equipment",
            "type":"Manufacturing & Wholesale Goods"
        }
    ],
    "sg:phone":"+1 905 430 8615",
    "sg:postcode":"L1N 8R9",
    "sg:province":"ON",
    "sg:tags":[
        "register",
        "cash",
        "supply"
    ],
    "wof:name":"K & K Kostronik Inc",
    "wof:placetype":"venue"
},
  "geometry": {"coordinates":[-78.9268493652,43.9002342224],"type":"Point"}
}