{
  "type": "Feature",
  "properties": {
    "iso:country":"CA",
    "sg:address":"700 Av Jenkins",
    "sg:city":"Dorval",
    "sg:classifiers":[
        {
            "category":"Wholesale",
            "subcategory":"Machinery & Supplies",
            "type":"Manufacturing & Wholesale Goods"
        }
    ],
    "sg:phone":"+1 514 633 1231",
    "sg:postcode":"H9P 1A1",
    "sg:province":"QC",
    "sg:tags":[
        "equipment",
        "mining"
    ],
    "wof:name":"Tech Pro Heavy Ind Inc",
    "wof:placetype":"venue"
},
  "geometry": {"coordinates":[-73.73021697999999,45.4619026184],"type":"Point"}
}