{
  "type": "Feature",
  "properties": {
    "addr:full":"Port Lambton ON N0P 2B0",
    "addr:postcode":"n0p 2b0",
    "addr:street":"Port",
    "iso:country":"CA",
    "sg:city":"Port Lambton",
    "sg:classifiers":[
        {
            "category":"Building & Trades",
            "subcategory":"Construction",
            "type":"Services"
        }
    ],
    "sg:phone":"+1 519 892 3254",
    "sg:postcode":"N0P 2B0",
    "sg:province":"ON",
    "sg:tags":[
        "excavating",
        "contractor"
    ],
    "wof:name":"Slims Bulldozing",
    "wof:placetype":"venue"
},
  "geometry": {"coordinates":[-82.48644256590001,42.6933326721],"type":"Point"}
}