{
  "type": "Feature",
  "properties": {
    "addr:full":"425 Alliford Bay Sandspit BC V0T 1T0",
    "addr:housenumber":"425",
    "addr:postcode":"v0t 1t0",
    "addr:street":"Alliford Bay",
    "iso:country":"CA",
    "sg:address":"425 Alliford Bay",
    "sg:city":"Sandspit",
    "sg:classifiers":[
        {
            "category":"Manufacturing",
            "subcategory":"Lumber",
            "type":"Manufacturing & Wholesale Goods"
        }
    ],
    "sg:phone":"+1 250 637 5656",
    "sg:postcode":"V0T 1T0",
    "sg:province":"BC",
    "sg:tags":[
        "company",
        "logging"
    ],
    "wof:name":"Hi-Blade Contracting",
    "wof:placetype":"venue"
},
  "geometry": {"coordinates":[-131.838348,53.238579],"type":"Point"}
}