{
  "type": "Feature",
  "properties": {
    "addr:full":"3301 Garnet St Regina SK S4S 1X8",
    "addr:housenumber":"3301",
    "addr:postcode":"s4s 1x8",
    "addr:street":"Garnet St",
    "iso:country":"CA",
    "sg:address":"3301 Garnet St",
    "sg:city":"Regina",
    "sg:classifiers":[
        {
            "category":"Social Services",
            "subcategory":"Child Care",
            "type":"Services"
        }
    ],
    "sg:phone":"+1 306 586 1455",
    "sg:postcode":"S4S 1X8",
    "sg:province":"SK",
    "sg:tags":[
        "kindergarten",
        "academic",
        "school"
    ],
    "wof:name":"Mes Amis En Francais",
    "wof:placetype":"venue"
},
  "geometry": {"coordinates":[-104.626617,50.426334],"type":"Point"}
}