{
  "type": "Feature",
  "properties": {
    "addr:full":"105 Rue Principale O Sainte-Henedine QC G0S 2R0",
    "addr:housenumber":"105",
    "addr:postcode":"g0s 2r0",
    "addr:street":"Rue Principale O Sainte-Henedine",
    "iso:country":"CA",
    "sg:address":"105 Rue Principale O",
    "sg:city":"Sainte-Henedine",
    "sg:classifiers":[
        {
            "category":"Food & Beverages",
            "subcategory":"Groceries & Convenience Stores",
            "type":"Retail Goods"
        }
    ],
    "sg:phone":"+1 418 935 3438",
    "sg:postcode":"G0S 2R0",
    "sg:province":"QC",
    "sg:tags":[
        "grocer"
    ],
    "wof:name":"Depanneur L'Essence-Ciel",
    "wof:placetype":"venue"
},
  "geometry": {"coordinates":[-70.9842834473,46.5582237244],"type":"Point"}
}