{
  "type": "Feature",
  "properties": {
    "addr:full":"2990 Place Industrielle LA Tuque QC G9X 4T1",
    "addr:housenumber":"2990",
    "addr:postcode":"g9x 4t1",
    "addr:street":"Place Industrielle",
    "iso:country":"CA",
    "sg:address":"2990 Place Industrielle",
    "sg:city":"LA Tuque",
    "sg:classifiers":[
        {
            "category":"Building & Trades",
            "subcategory":"Equipment Rental",
            "type":"Services"
        }
    ],
    "sg:phone":"+1 819 523 7179",
    "sg:postcode":"G9X 4T1",
    "sg:province":"QC",
    "sg:tags":[
        "excavating",
        "contractor"
    ],
    "wof:name":"Betonniere LA Tuque",
    "wof:placetype":"venue"
},
  "geometry": {"coordinates":[-72.787415,47.396626],"type":"Point"}
}