{
  "type": "Feature",
  "properties": {
    "addr:full":"35 First Ave N Yorkton SK S3N 1J3",
    "addr:housenumber":"35",
    "addr:postcode":"s3n 1j3",
    "addr:street":"First Ave N",
    "iso:country":"CA",
    "sg:address":"35 First Ave N",
    "sg:city":"Yorkton",
    "sg:classifiers":[
        {
            "category":"Freight",
            "type":"Transportation"
        }
    ],
    "sg:phone":"+1 306 782 2355",
    "sg:postcode":"S3N 1J3",
    "sg:province":"SK",
    "sg:tags":[
        "bus",
        "line",
        "courier"
    ],
    "wof:name":"Greyhound Canada",
    "wof:placetype":"venue"
},
  "geometry": {"coordinates":[-102.46249400000001,51.211117],"type":"Point"}
}