{
  "type": "Feature",
  "properties": {
    "addr:full":"PO Box 1387 STN Main St Catharines ON L2R 7J8",
    "addr:housenumber":"po",
    "addr:postcode":"1387;l2r 7j8",
    "addr:street":"Box;Stn Main St",
    "iso:country":"CA",
    "sg:address":"PO Box 1387 STN Main",
    "sg:city":"St Catharines",
    "sg:classifiers":[
        {
            "category":"Social Services",
            "type":"Services"
        }
    ],
    "sg:phone":"+1 905 684 8331",
    "sg:postcode":"L2R 7J8",
    "sg:province":"ON",
    "sg:tags":[
        "organization",
        "welfare",
        "crisis",
        "intervention"
    ],
    "wof:name":"Women's Place Inc",
    "wof:placetype":"venue"
},
  "geometry": {"coordinates":[-79.24867248539999,43.1563339233],"type":"Point"}
}