{
  "type": "Feature",
  "properties": {
    "addr:full":"626 East Main St Welland ON L3B 3Y2",
    "addr:housenumber":"626",
    "addr:postcode":"l3b 3y2",
    "addr:street":"East Main St",
    "iso:country":"CA",
    "sg:address":"626 East Main St",
    "sg:city":"Welland",
    "sg:classifiers":[
        {
            "category":"Government",
            "subcategory":"Post Office",
            "type":"Public Place"
        }
    ],
    "sg:phone":"+1 905 735 0856",
    "sg:postcode":"L3B 3Y2",
    "sg:province":"ON",
    "wof:name":"East Main Post Office",
    "wof:placetype":"venue"
},
  "geometry": {"coordinates":[-79.23374938960001,42.9935798645],"type":"Point"}
}