{
  "type": "Feature",
  "properties": {
    "addr:full":"2535 Drew Rd Mississauga ON L4T 1G1",
    "addr:housenumber":"2535",
    "addr:postcode":"l4t 1g1",
    "addr:street":"Drew Rd",
    "iso:country":"CA",
    "sg:address":"2535 Drew Rd",
    "sg:city":"Mississauga",
    "sg:classifiers":[
        {
            "category":"Building & Trades",
            "subcategory":"Construction",
            "type":"Services"
        }
    ],
    "sg:phone":"+1 905 672 9992",
    "sg:postcode":"L4T 1G1",
    "sg:province":"ON",
    "sg:tags":[
        "roofing",
        "contractor"
    ],
    "wof:name":"Roof Tile Mgmt Inc",
    "wof:placetype":"venue"
},
  "geometry": {"coordinates":[-79.65766143800001,43.7010650635],"type":"Point"}
}