{
  "type": "Feature",
  "properties": {
    "addr:full":"3321 Cambourne Cres Mississauga ON L5N 5P8",
    "addr:housenumber":"3321",
    "addr:postcode":"l5n 5p8",
    "addr:street":"Cambourne Cres",
    "iso:country":"CA",
    "sg:address":"3321 Cambourne Cres",
    "sg:city":"Mississauga",
    "sg:classifiers":[
        {
            "category":"Professional",
            "subcategory":"Computer Services",
            "type":"Services"
        }
    ],
    "sg:phone":"+1 905 824 1989",
    "sg:postcode":"L5N 5P8",
    "sg:province":"ON",
    "sg:tags":[
        "internet"
    ],
    "wof:name":"Can Horizon Inc",
    "wof:placetype":"venue"
},
  "geometry": {"coordinates":[-79.777756,43.585823],"type":"Point"}
}