{
  "type": "Feature",
  "properties": {
    "addr:full":"RR 2 STN Main Trenton ON K8V 5P5",
    "addr:postcode":"k8v 5p5",
    "addr:street":"Rr 2 Stn Main",
    "iso:country":"CA",
    "sg:address":"RR 2 STN Main",
    "sg:city":"Trenton",
    "sg:classifiers":[
        {
            "category":"Shopping",
            "subcategory":"Computers & Home Electronics",
            "type":"Retail Goods"
        }
    ],
    "sg:phone":"+1 613 392 5379",
    "sg:postcode":"K8V 5P5",
    "sg:province":"ON",
    "wof:name":"Raines Computers",
    "wof:placetype":"venue"
},
  "geometry": {"coordinates":[-77.57630899999999,44.101139],"type":"Point"}
}