{
  "type": "Feature",
  "properties": {
    "addr:full":"Calgary AB T2A 6M6",
    "addr:postcode":"t2a 6m6",
    "iso:country":"CA",
    "sg:city":"Calgary",
    "sg:classifiers":[
        {
            "category":"Restaurant",
            "type":"Food & Drink"
        }
    ],
    "sg:phone":"+1 403 248 0882",
    "sg:postcode":"T2A 6M6",
    "sg:province":"AB",
    "wof:name":"Jenny's Restaurant & Lounge",
    "wof:placetype":"venue"
},
  "geometry": {"coordinates":[-113.98612199999999,51.058414],"type":"Point"}
}