{
  "type": "Feature",
  "properties": {
    "addr:full":"Calgary AB T2G 5M4",
    "addr:postcode":"t2g 5m4",
    "iso:country":"CA",
    "sg:city":"Calgary",
    "sg:classifiers":[
        {
            "category":"Wholesale",
            "subcategory":"Vending Machines",
            "type":"Manufacturing & Wholesale Goods"
        }
    ],
    "sg:phone":"+1 403 271 2856",
    "sg:postcode":"T2G 5M4",
    "sg:province":"AB",
    "wof:name":"AAA Vending Supplies Ltd",
    "wof:placetype":"venue"
},
  "geometry": {"coordinates":[-114.03254699999999,51.006729],"type":"Point"}
}