{
  "type": "Feature",
  "properties": {
    "addr:full":"248 Rue Des Erables Brownsburg-Chatham QC J8G 3C4",
    "addr:housenumber":"248",
    "addr:postcode":"j8g 3c4",
    "addr:street":"Rue Des Erables",
    "iso:country":"CA",
    "sg:address":"248 Rue Des Erables",
    "sg:city":"Brownsburg-Chatham",
    "sg:classifiers":[
        {
            "category":"Retail",
            "subcategory":"Auto Repair",
            "type":"Services"
        }
    ],
    "sg:phone":"+1 450 533 4571",
    "sg:postcode":"J8G 3C4",
    "sg:province":"QC",
    "sg:tags":[
        "repairing",
        "automobile"
    ],
    "wof:name":"Williams Inc",
    "wof:placetype":"venue"
},
  "geometry": {"coordinates":[-74.40295399999999,45.682461],"type":"Point"}
}