{
  "type": "Feature",
  "properties": {
    "addr:full":"PO Box 401 STN Lcd 1 Hamilton ON L8L 7W2",
    "addr:housenumber":"po;1",
    "addr:postcode":"l8l 7w2",
    "addr:street":"Box 401;Lcd",
    "iso:country":"CA",
    "sg:address":"PO Box 401 STN Lcd 1",
    "sg:city":"Hamilton",
    "sg:classifiers":[
        {
            "category":"Building & Trades",
            "subcategory":"Cleaning & Sanitation",
            "type":"Services"
        }
    ],
    "sg:phone":"+1 905 527 8663",
    "sg:postcode":"L8L 7W2",
    "sg:province":"ON",
    "sg:tags":[
        "window"
    ],
    "wof:name":"J & L Master Window Cleaning",
    "wof:placetype":"venue"
},
  "geometry": {"coordinates":[-79.888451,43.26099],"type":"Point"}
}