{
  "type": "Feature",
  "properties": {
    "iso:country":"CA",
    "sg:address":"12140 Av Fernand-Gauthier",
    "sg:city":"Montreal",
    "sg:classifiers":[
        {
            "category":"Health Services",
            "subcategory":"Doctor",
            "type":"Services"
        }
    ],
    "sg:phone":"+1 514 494 7654",
    "sg:postcode":"H1E 6T2",
    "sg:province":"QC",
    "sg:tags":[
        "physician",
        "surgeon"
    ],
    "wof:name":"M'Seffar, Abdel Magid MD",
    "wof:placetype":"venue"
},
  "geometry": {"coordinates":[-73.598396,45.630146],"type":"Point"}
}