{
  "type": "Feature",
  "properties": {
    "addr:full":"1453 Thorburn Rd Portugal Cove-St Philips NL A1M 1J6",
    "addr:housenumber":"1453",
    "addr:postcode":"a1m 1j6",
    "addr:street":"Thorburn Rd",
    "iso:country":"CA",
    "sg:address":"1453 Thorburn Rd",
    "sg:city":"Portugal Cove-St Philips",
    "sg:classifiers":[
        {
            "category":"Home & Garden",
            "subcategory":"Building Materials",
            "type":"Retail Goods"
        }
    ],
    "sg:phone":"+1 709 895 5097",
    "sg:postcode":"A1M 1J6",
    "sg:province":"NL",
    "sg:tags":[
        "glass",
        "leaded"
    ],
    "wof:name":"Sunhound Glassworks",
    "wof:placetype":"venue"
},
  "geometry": {"coordinates":[-52.877853,47.584339],"type":"Point"}
}