{
  "type": "Feature",
  "properties": {
    "iso:country":"CA",
    "sg:address":"206 Carling St",
    "sg:city":"St Marys",
    "sg:classifiers":[
        {
            "category":"Wholesale",
            "subcategory":"Scrap",
            "type":"Manufacturing & Wholesale Goods"
        }
    ],
    "sg:phone":"+1 519 284 2800",
    "sg:postcode":"N4X 1B8",
    "sg:province":"ON",
    "sg:tags":[
        "metal",
        "iron"
    ],
    "wof:name":"Robson Scrap Metals Ltd",
    "wof:placetype":"venue"
},
  "geometry": {"coordinates":[-81.1309051514,43.2706680298],"type":"Point"}
}