{
  "type": "Feature",
  "properties": {
    "addr:full":"698 Saskatchewan Ave E Melfort SK S0E 1A0",
    "addr:housenumber":"698",
    "addr:postcode":"s0e 1a0",
    "addr:street":"Saskatchewan Ave E Melfort",
    "iso:country":"CA",
    "sg:address":"698 Saskatchewan Ave E",
    "sg:city":"Melfort",
    "sg:classifiers":[
        {
            "category":"Home & Garden",
            "subcategory":"Building Materials",
            "type":"Retail Goods"
        }
    ],
    "sg:phone":"+1 306 752 3366",
    "sg:postcode":"S0E 1A0",
    "sg:province":"SK",
    "sg:tags":[
        "lumber"
    ],
    "wof:name":"Northland Lumber Ltd",
    "wof:placetype":"venue"
},
  "geometry": {"coordinates":[-104.596558,52.856594],"type":"Point"}
}