{
  "type": "Feature",
  "properties": {
    "addr:full":"4801 1 St SE Calgary AB T2G 2L2",
    "addr:housenumber":"4801 1",
    "addr:postcode":"t2g 2l2",
    "addr:street":"St Se",
    "iso:country":"CA",
    "sg:address":"4801 1 St SE",
    "sg:city":"Calgary",
    "sg:classifiers":[
        {
            "category":"Professional",
            "subcategory":"Management & Consulting",
            "type":"Services"
        }
    ],
    "sg:phone":"+1 403 266 3907",
    "sg:postcode":"T2G 2L2",
    "sg:province":"AB",
    "sg:tags":[
        "supply",
        "equipment",
        "planning",
        "theatrical",
        "party"
    ],
    "wof:name":"Gaps the Prop Shop",
    "wof:placetype":"venue"
},
  "geometry": {"coordinates":[-114.06234741199999,51.011264801],"type":"Point"}
}