{
  "type": "Feature",
  "properties": {
    "addr:full":"3 Ave & 4 St W Foremost AB T0K 0X0",
    "addr:postcode":"t0k 0x0",
    "addr:street":"3 Ave & 4 St W Foremost",
    "iso:country":"CA",
    "sg:address":"3 Ave & 4 St W",
    "sg:city":"Foremost",
    "sg:classifiers":[
        {
            "category":"Organizations",
            "subcategory":"Religious Organization",
            "type":"Services"
        }
    ],
    "sg:phone":"+1 403 867 3849",
    "sg:postcode":"T0K 0X0",
    "sg:province":"AB",
    "sg:tags":[
        "church"
    ],
    "wof:name":"Church of Jesus Christ of Lds",
    "wof:placetype":"venue"
},
  "geometry": {"coordinates":[-111.441436768,49.4790763855],"type":"Point"}
}