{
  "type": "Feature",
  "properties": {
    "addr:full":"Mont-Laurier QC J9L 3X4",
    "addr:postcode":"j9l 3x4",
    "iso:country":"CA",
    "sg:city":"Mont-Laurier",
    "sg:classifiers":[
        {
            "category":"Professional",
            "subcategory":"Testing Lab",
            "type":"Services"
        }
    ],
    "sg:phone":"+1 819 623 5511",
    "sg:postcode":"J9L 3X4",
    "sg:province":"QC",
    "sg:tags":[
        "soil"
    ],
    "wof:name":"Fondex Des Hautes Rivieres",
    "wof:placetype":"venue"
},
  "geometry": {"coordinates":[-75.487289,46.540562],"type":"Point"}
}