{
  "type": "Feature",
  "properties": {
    "addr:full":"3146 Rue DE Miniac Saint-Laurent QC H4S 1N5",
    "addr:housenumber":"3146",
    "addr:postcode":"h4s 1n5",
    "addr:street":"Rue De Miniac",
    "iso:country":"CA",
    "sg:address":"3146 Rue DE Miniac",
    "sg:city":"Saint-Laurent",
    "sg:classifiers":[
        {
            "category":"Manufacturing",
            "subcategory":"Tools & Machinery",
            "type":"Manufacturing & Wholesale Goods"
        }
    ],
    "sg:phone":"+1 514 335 0976",
    "sg:postcode":"H4S 1N5",
    "sg:province":"QC",
    "sg:tags":[
        "machine",
        "shop"
    ],
    "wof:name":"Traf Industrial Products Inc",
    "wof:placetype":"venue"
},
  "geometry": {"coordinates":[-73.752251,45.495979],"type":"Point"}
}