{
  "type": "Feature",
  "properties": {
    "addr:full":"Richmond Hill ON L4C 9M7",
    "addr:postcode":"l4c 9m7",
    "iso:country":"CA",
    "sg:city":"Richmond Hill",
    "sg:classifiers":[
        {
            "category":"Health Services",
            "subcategory":"Optometrist",
            "type":"Services"
        }
    ],
    "sg:phone":"+1 905 883 5617",
    "sg:postcode":"L4C 9M7",
    "sg:province":"ON",
    "wof:name":"Woo, Sharon OD",
    "wof:placetype":"venue"
},
  "geometry": {"coordinates":[-79.448425293,43.8682174683],"type":"Point"}
}