{
  "type": "Feature",
  "properties": {
    "addr:full":"11908 West Coast Rd Jordan River BC V0S 1L0",
    "addr:housenumber":"11908",
    "addr:postcode":"v0s 1l0",
    "addr:street":"West Coast Rd",
    "iso:country":"CA",
    "sg:address":"11908 West Coast Rd",
    "sg:city":"Jordan River",
    "sg:classifiers":[
        {
            "category":"Restaurant",
            "type":"Food & Drink"
        }
    ],
    "sg:phone":"+1 250 646 2184",
    "sg:postcode":"V0S 1L0",
    "sg:province":"BC",
    "wof:name":"Shakie's Drive-In",
    "wof:placetype":"venue"
},
  "geometry": {"coordinates":[-124.069328,48.431404],"type":"Point"}
}