{
  "type": "Feature",
  "properties": {
    "addr:full":"90 3E Av Quebec QC G1L 2V4",
    "addr:housenumber":"90",
    "addr:postcode":"g1l 2v4",
    "addr:street":"3E Av",
    "iso:country":"CA",
    "sg:address":"90 3E Av",
    "sg:city":"Quebec",
    "sg:classifiers":[
        {
            "category":"Retail",
            "subcategory":"Auto Repair",
            "type":"Services"
        }
    ],
    "sg:phone":"+1 418 525 7269",
    "sg:postcode":"G1L 2V4",
    "sg:province":"QC",
    "sg:tags":[
        "repairing",
        "automobile"
    ],
    "wof:name":"Jean Fina Svc",
    "wof:placetype":"venue"
},
  "geometry": {"coordinates":[-71.224358,46.820499],"type":"Point"}
}