{
  "type": "Feature",
  "properties": {
    "addr:full":"5812 176 St Surrey BC V3S 4E2",
    "addr:housenumber":"5812",
    "addr:postcode":"v3s 4e2",
    "addr:street":"176 St",
    "iso:country":"CA",
    "sg:address":"5812 176 St",
    "sg:city":"Surrey",
    "sg:classifiers":[
        {
            "category":"Retail",
            "subcategory":"Auto Repair",
            "type":"Services"
        }
    ],
    "sg:phone":"+1 604 574 4661",
    "sg:postcode":"V3S 4E2",
    "sg:province":"BC",
    "sg:tags":[
        "body",
        "automobile",
        "painting"
    ],
    "wof:name":"Cloverdale Auto Body",
    "wof:placetype":"venue"
},
  "geometry": {"coordinates":[-122.734909058,49.103969574],"type":"Point"}
}