{
  "type": "Feature",
  "properties": {
    "addr:full":"Vancouver BC V6B 2S2",
    "addr:postcode":"v6b 2s2",
    "iso:country":"CA",
    "sg:city":"Vancouver",
    "sg:classifiers":[
        {
            "category":"Professional",
            "subcategory":"Advertising",
            "type":"Services"
        }
    ],
    "sg:phone":"+1 604 688 0200",
    "sg:postcode":"V6B 2S2",
    "sg:province":"BC",
    "sg:tags":[
        "counselor"
    ],
    "wof:name":"Halloran Etcetera Advertising",
    "wof:placetype":"venue"
},
  "geometry": {"coordinates":[-123.12137603799999,49.2755661011],"type":"Point"}
}