{
  "type": "Feature",
  "properties": {
    "iso:country":"CA",
    "sg:address":"6340 Kingsway",
    "sg:city":"Burnaby",
    "sg:classifiers":[
        {
            "category":"Shopping",
            "type":"Retail Goods"
        }
    ],
    "sg:phone":"+1 604 439 8483",
    "sg:postcode":"V5E 1C5",
    "sg:province":"BC",
    "sg:tags":[
        "equipment",
        "beer",
        "supply"
    ],
    "wof:name":"Chateau Vino Wine Cellar",
    "wof:placetype":"venue"
},
  "geometry": {"coordinates":[-122.97137499999999,49.219669],"type":"Point"}
}