{
  "type": "Feature",
  "properties": {
    "addr:full":"2385 Rue Sicotte Saint-Hyacinthe QC J2S 2K7",
    "addr:housenumber":"2385",
    "addr:postcode":"j2s 2k7",
    "addr:street":"Rue Sicotte",
    "iso:country":"CA",
    "sg:address":"2385 Rue Sicotte",
    "sg:city":"Saint-Hyacinthe",
    "sg:classifiers":[
        {
            "category":"Professional",
            "subcategory":"Accounting & Tax Preparation",
            "type":"Services"
        }
    ],
    "sg:phone":"+1 450 773 7550",
    "sg:postcode":"J2S 2K7",
    "sg:province":"QC",
    "sg:tags":[
        "accountant"
    ],
    "wof:name":"Laplante & Assoc",
    "wof:placetype":"venue"
},
  "geometry": {"coordinates":[-72.955246,45.62458],"type":"Point"}
}