{
  "type": "Feature",
  "properties": {
    "iso:country":"CA",
    "sg:city":"Vancouver",
    "sg:classifiers":[
        {
            "category":"Organizations",
            "subcategory":"Professional Association",
            "type":"Services"
        }
    ],
    "sg:phone":"+1 604 737 3126",
    "sg:postcode":"V6H 4A7",
    "sg:province":"BC",
    "wof:name":"B C Sailing",
    "wof:placetype":"venue"
},
  "geometry": {"coordinates":[-123.135223389,49.2635955811],"type":"Point"}
}