{
  "type": "Feature",
  "properties": {
    "addr:full":"Woodbridge ON L4L 8H2",
    "addr:postcode":"l4l 8h2",
    "iso:country":"CA",
    "sg:city":"Woodbridge",
    "sg:classifiers":[
        {
            "category":"Manufacturing",
            "subcategory":"Printing",
            "type":"Manufacturing & Wholesale Goods"
        }
    ],
    "sg:phone":"+1 905 851 7222",
    "sg:postcode":"L4L 8H2",
    "sg:province":"ON",
    "sg:tags":[
        "printer"
    ],
    "wof:name":"Print Tech 2000",
    "wof:placetype":"venue"
},
  "geometry": {"coordinates":[-79.547028,43.786282],"type":"Point"}
}