{
  "type": "Feature",
  "properties": {
    "iso:country":"CA",
    "sg:address":"134 Queensville Side Rd",
    "sg:city":"River Drive Park",
    "sg:classifiers":[
        {
            "category":"Autos & Motor Vehicles",
            "subcategory":"Boat Sales",
            "type":"Retail Goods"
        }
    ],
    "sg:phone":"+1 905 953 0193",
    "sg:postcode":"L9N 1A7",
    "sg:province":"ON",
    "sg:tags":[
        "marina",
        "dealer"
    ],
    "wof:name":"Soldiers Bay Marine Ltd",
    "wof:placetype":"venue"
},
  "geometry": {"coordinates":[-79.50736999510001,44.1267814636],"type":"Point"}
}