{
  "type": "Feature",
  "properties": {
    "addr:full":"5207 49 St High Prairie AB T0G 1E0",
    "addr:housenumber":"5207",
    "addr:postcode":"t0g 1e0",
    "addr:street":"49 St",
    "iso:country":"CA",
    "sg:address":"5207 49 St",
    "sg:city":"High Prairie",
    "sg:classifiers":[
        {
            "category":"Health Services",
            "subcategory":"Medical Lab",
            "type":"Services"
        }
    ],
    "sg:phone":"+1 780 523 3204",
    "sg:postcode":"T0G 1E0",
    "sg:province":"AB",
    "wof:name":"High Prairie Denture Clinic",
    "wof:placetype":"venue"
},
  "geometry": {"coordinates":[-116.49170684800001,55.4321594238],"type":"Point"}
}