{
  "type": "Feature",
  "properties": {
    "addr:full":"3290 Rue Gisele Sainte-Marthe-Sur-Le-Lac QC J0N 1P0",
    "addr:housenumber":"3290",
    "addr:postcode":"j0n 1p0",
    "addr:street":"Rue Gisele",
    "iso:country":"CA",
    "sg:address":"3290 Rue Gisele",
    "sg:city":"Sainte-Marthe-Sur-Le-Lac",
    "sg:classifiers":[
        {
            "category":"Health Services",
            "subcategory":"Nursing And Care Facility",
            "type":"Services"
        }
    ],
    "sg:phone":"+1 450 623 7170",
    "sg:postcode":"J0N 1P0",
    "sg:province":"QC",
    "sg:tags":[
        "home",
        "retirement",
        "community"
    ],
    "wof:name":"Paradis Du Lac Enr",
    "wof:placetype":"venue"
},
  "geometry": {"coordinates":[-73.932365,45.529251],"type":"Point"}
}