{
  "type": "Feature",
  "properties": {
    "iso:country":"CA",
    "sg:address":"2148 Sooke Rd",
    "sg:city":"Victoria",
    "sg:classifiers":[
        {
            "category":"Autos & Motor Vehicles",
            "subcategory":"Fuel & Gas Station",
            "type":"Retail Goods"
        }
    ],
    "sg:phone":"+1 250 478 9383",
    "sg:postcode":"V9B 1W6",
    "sg:province":"BC",
    "sg:tags":[
        "oil"
    ],
    "wof:name":"Mountainview Shell",
    "wof:placetype":"venue"
},
  "geometry": {"coordinates":[-123.364517,48.428314],"type":"Point"}
}