{
  "type": "Feature",
  "properties": {
    "addr:full":"7 Seacliff Dr W Leamington ON N8H 2L5",
    "addr:housenumber":"7",
    "addr:postcode":"n8h 2l5",
    "addr:street":"Seacliff Dr W",
    "iso:country":"CA",
    "sg:address":"7 Seacliff Dr W",
    "sg:city":"Leamington",
    "sg:classifiers":[
        {
            "category":"Manufacturing",
            "subcategory":"Signs",
            "type":"Manufacturing & Wholesale Goods"
        }
    ],
    "sg:phone":"+1 519 322 2998",
    "sg:postcode":"N8H 2L5",
    "sg:province":"ON",
    "wof:name":"Chapman Signs",
    "wof:placetype":"venue"
},
  "geometry": {"coordinates":[-82.6019668579,42.0340614319],"type":"Point"}
}