{
  "type": "Feature",
  "properties": {
    "addr:full":"8870 Lundy's Lane Niagara Falls ON L2H 1H4",
    "addr:housenumber":"8870",
    "addr:postcode":"l2h 1h4",
    "addr:street":"Lundy'S Lane",
    "iso:country":"CA",
    "sg:address":"8870 Lundy's Lane",
    "sg:city":"Niagara Falls",
    "sg:classifiers":[
        {
            "category":"Bars & Pubs",
            "type":"Food & Drink"
        }
    ],
    "sg:phone":"+1 905 358 9124",
    "sg:postcode":"L2H 1H4",
    "sg:province":"ON",
    "sg:tags":[
        "club",
        "night"
    ],
    "wof:name":"Sundowner Inn",
    "wof:placetype":"venue"
},
  "geometry": {"coordinates":[-77.565369,45.042416],"type":"Point"}
}