{
  "type": "Feature",
  "properties": {
    "addr:full":"4462 Willingdon Ave Powell River BC V8A 2M6",
    "addr:housenumber":"4462",
    "addr:postcode":"v8a 2m6",
    "addr:street":"Willingdon Ave Powell",
    "iso:country":"CA",
    "sg:address":"4462 Willingdon Ave",
    "sg:city":"Powell River",
    "sg:classifiers":[
        {
            "category":"Autos & Motor Vehicles",
            "subcategory":"Boat Sales",
            "type":"Retail Goods"
        }
    ],
    "sg:phone":"+1 604 485 5616",
    "sg:postcode":"V8A 2M6",
    "sg:province":"BC",
    "sg:tags":[
        "equipment",
        "marine",
        "dealer",
        "supply"
    ],
    "wof:name":"Les Koleszar Svc Ltd",
    "wof:placetype":"venue"
},
  "geometry": {"coordinates":[-124.52838897700001,49.8370704651],"type":"Point"}
}