{
  "type": "Feature",
  "properties": {
    "addr:full":"28115 Huntingdon Rd Abbotsford BC V4X 1A8",
    "addr:housenumber":"28115",
    "addr:postcode":"v4x 1a8",
    "addr:street":"Huntingdon Rd",
    "iso:country":"CA",
    "sg:address":"28115 Huntingdon Rd",
    "sg:city":"Abbotsford",
    "sg:classifiers":[
        {
            "category":"Professional",
            "subcategory":"Business Services",
            "type":"Services"
        }
    ],
    "sg:phone":"+1 604 856 4384",
    "sg:postcode":"V4X 1A8",
    "sg:province":"BC",
    "wof:name":"Central Composting Ltd",
    "wof:placetype":"venue"
},
  "geometry": {"coordinates":[-122.44399300000001,49.017372],"type":"Point"}
}