{
  "type": "Feature",
  "properties": {
    "addr:full":"3977 Albert St Burnaby BC V5C 2E2",
    "addr:housenumber":"3977",
    "addr:postcode":"v5c 2e2",
    "addr:street":"Albert St",
    "iso:country":"CA",
    "sg:address":"3977 Albert St",
    "sg:city":"Burnaby",
    "sg:classifiers":[
        {
            "category":"Organizations",
            "subcategory":"Religious Organization",
            "type":"Services"
        }
    ],
    "sg:phone":"+1 604 298 3013",
    "sg:postcode":"V5C 2E2",
    "sg:province":"BC",
    "sg:tags":[
        "church"
    ],
    "wof:name":"Burnaby North Baptist Church",
    "wof:placetype":"venue"
},
  "geometry": {"coordinates":[-123.016784668,49.2821502686],"type":"Point"}
}