{
  "type": "Feature",
  "properties": {
    "iso:country":"CA",
    "sg:city":"Winnipeg",
    "sg:classifiers":[
        {
            "category":"Health Services",
            "subcategory":"Medical Lab",
            "type":"Services"
        }
    ],
    "sg:phone":"+1 204 895 8952",
    "sg:postcode":"R3M 0W4",
    "sg:province":"MB",
    "wof:name":"Aesthetic Dental Biomimetics",
    "wof:placetype":"venue"
},
  "geometry": {"coordinates":[-97.151382,49.871593],"type":"Point"}
}