{
  "type": "Feature",
  "properties": {
    "iso:country":"CA",
    "sg:address":"491 Bank St",
    "sg:city":"Ottawa",
    "sg:classifiers":[
        {
            "category":"Professional",
            "subcategory":"Business Services",
            "type":"Services"
        }
    ],
    "sg:phone":"+1 613 277 6675",
    "sg:postcode":"K2P 1Z2",
    "sg:province":"ON",
    "sg:tags":[
        "interior",
        "consultant",
        "design",
        "decorator"
    ],
    "wof:name":"Wardrop/Langlois",
    "wof:placetype":"venue"
},
  "geometry": {"coordinates":[-75.692558,45.410664],"type":"Point"}
}