{
  "type": "Feature",
  "properties": {
    "iso:country":"CA",
    "sg:address":"850 Boul Vanier",
    "sg:city":"Laval",
    "sg:classifiers":[
        {
            "category":"Government",
            "subcategory":"Office",
            "type":"Public Place"
        }
    ],
    "sg:phone":"+1 450 661 2008",
    "sg:postcode":"H7C 2M7",
    "sg:province":"QC",
    "wof:name":"Urgence Environnement",
    "wof:placetype":"venue"
},
  "geometry": {"coordinates":[-73.651833,45.604572],"type":"Point"}
}