{
  "type": "Feature",
  "properties": {
    "iso:country":"CA",
    "sg:address":"8520 Boul DE LA Rive-Sud",
    "sg:city":"Levis",
    "sg:classifiers":[
        {
            "category":"Travel",
            "subcategory":"Hotels & Motels",
            "type":"Entertainment"
        }
    ],
    "sg:phone":"+1 418 837 6667",
    "sg:postcode":"G6V 8V7",
    "sg:province":"QC",
    "wof:name":"Motel Le Lauzonnais",
    "wof:placetype":"venue"
},
  "geometry": {"coordinates":[-71.13344573969999,46.8198661804],"type":"Point"}
}