{
  "type": "Feature",
  "properties": {
    "addr:full":"3050 Boul Rosemont Montreal QC H1Y 1M2",
    "addr:housenumber":"3050",
    "addr:postcode":"h1y 1m2",
    "addr:street":"Boul Rosemont",
    "iso:country":"CA",
    "sg:address":"3050 Boul Rosemont",
    "sg:city":"Montreal",
    "sg:classifiers":[
        {
            "category":"Organizations",
            "subcategory":"Religious Organization",
            "type":"Services"
        }
    ],
    "sg:phone":"+1 514 721 1830",
    "sg:postcode":"H1Y 1M2",
    "sg:province":"QC",
    "sg:tags":[
        "church"
    ],
    "wof:name":"Trinity United Church",
    "wof:placetype":"venue"
},
  "geometry": {"coordinates":[-73.58196258540001,45.551158905],"type":"Point"}
}