{
  "type": "Feature",
  "properties": {
    "addr:full":"45010 Stratford Pl Chilliwack BC V2R 2Z2",
    "addr:housenumber":"45010",
    "addr:postcode":"v2r 2z2",
    "addr:street":"Stratford Pl",
    "iso:country":"CA",
    "sg:address":"45010 Stratford Pl",
    "sg:city":"Chilliwack",
    "sg:classifiers":[
        {
            "category":"Building & Trades",
            "subcategory":"Plumbing",
            "type":"Services"
        }
    ],
    "sg:phone":"+1 604 858 8786",
    "sg:postcode":"V2R 2Z2",
    "sg:province":"BC",
    "sg:tags":[
        "contractor"
    ],
    "wof:name":"Dave Reimer Plumbing & Heating",
    "wof:placetype":"venue"
},
  "geometry": {"coordinates":[-121.979584,49.109295],"type":"Point"}
}