{
  "type": "Feature",
  "properties": {
    "addr:full":"7336 36 St NW Edmonton AB T6B 3E8",
    "addr:housenumber":"7336",
    "addr:postcode":"t6b 3e8",
    "addr:street":"36 St Nw",
    "iso:country":"CA",
    "sg:address":"7336 36 St NW",
    "sg:city":"Edmonton",
    "sg:classifiers":[
        {
            "category":"Retail",
            "subcategory":"Repair Shop",
            "type":"Services"
        }
    ],
    "sg:phone":"+1 780 461 0041",
    "sg:postcode":"T6B 3E8",
    "sg:province":"AB",
    "sg:tags":[
        "welding"
    ],
    "wof:name":"Plasma-Tec Industries Ltd",
    "wof:placetype":"venue"
},
  "geometry": {"coordinates":[-113.39746100000001,53.509144],"type":"Point"}
}