{
  "type": "Feature",
  "properties": {
    "addr:full":"108 3 Ave Warner AB T0K 2L0",
    "addr:housenumber":"108",
    "addr:postcode":"t0k 2l0",
    "addr:street":"3 Ave",
    "iso:country":"CA",
    "sg:address":"108 3 Ave",
    "sg:city":"Warner",
    "sg:classifiers":[
        {
            "category":"Government",
            "subcategory":"Office",
            "type":"Public Place"
        }
    ],
    "sg:phone":"+1 403 642 3608",
    "sg:postcode":"T0K 2L0",
    "sg:province":"AB",
    "sg:tags":[
        "village"
    ],
    "wof:name":"Village of Warner",
    "wof:placetype":"venue"
},
  "geometry": {"coordinates":[-112.203186035,49.2821617126],"type":"Point"}
}