{
  "type": "Feature",
  "properties": {
    "addr:full":"Montreal QC H1Z 2H8",
    "addr:postcode":"h1z 2h8",
    "iso:country":"CA",
    "sg:city":"Montreal",
    "sg:classifiers":[
        {
            "category":"Professional",
            "subcategory":"Business Services",
            "type":"Services"
        }
    ],
    "sg:phone":"+1 514 721 4238",
    "sg:postcode":"H1Z 2H8",
    "sg:province":"QC",
    "sg:tags":[
        "embroidery"
    ],
    "wof:name":"Broderie Lina Enr",
    "wof:placetype":"venue"
},
  "geometry": {"coordinates":[-73.60585,45.564079],"type":"Point"}
}