{
  "type": "Feature",
  "properties": {
    "iso:country":"CA",
    "sg:address":"319 Boul St-Pierre O",
    "sg:city":"Caraquet",
    "sg:classifiers":[
        {
            "category":"Freight",
            "type":"Transportation"
        }
    ],
    "sg:phone":"+1 506 727 3503",
    "sg:postcode":"E1W 1A3",
    "sg:province":"NB",
    "sg:tags":[
        "building",
        "house",
        "mover",
        "septic"
    ],
    "wof:name":"R P Cormier Ltee",
    "wof:placetype":"venue"
},
  "geometry": {"coordinates":[-64.8875045776,47.798576355],"type":"Point"}
}