{
  "type": "Feature",
  "properties": {
    "iso:country":"CA",
    "sg:address":"1356 Rue Saint-Laurent",
    "sg:city":"Saint-Nicolas",
    "sg:classifiers":[
        {
            "category":"Professional",
            "subcategory":"Engineering",
            "type":"Services"
        }
    ],
    "sg:phone":"+1 418 836 0315",
    "sg:postcode":"G7A 4K3",
    "sg:province":"QC",
    "sg:tags":[
        "engineer"
    ],
    "wof:name":"Camtech Consultants",
    "wof:placetype":"venue"
},
  "geometry": {"coordinates":[-71.396301,46.703758],"type":"Point"}
}