{
  "type": "Feature",
  "properties": {
    "addr:full":"1106 2 Ave S Lethbridge AB T1J 0E2",
    "addr:housenumber":"1106",
    "addr:postcode":"t1j 0e2",
    "addr:street":"2 Ave S",
    "iso:country":"CA",
    "sg:address":"1106 2 Ave S",
    "sg:city":"Lethbridge",
    "sg:classifiers":[
        {
            "category":"Home & Garden",
            "subcategory":"Building Materials",
            "type":"Retail Goods"
        }
    ],
    "sg:phone":"+1 403 328 3443",
    "sg:postcode":"T1J 0E2",
    "sg:province":"AB",
    "sg:tags":[
        "glass",
        "window",
        "plate"
    ],
    "wof:name":"Quality Glass & Aluminum Ltd",
    "wof:placetype":"venue"
},
  "geometry": {"coordinates":[-112.83066599999999,49.697124],"type":"Point"}
}