{
  "type": "Feature",
  "properties": {
    "addr:full":"61A Paradise Lake St Lucknow ON N0G 2H0",
    "addr:housenumber":"61a",
    "addr:postcode":"n0g 2h0",
    "addr:street":"Paradise Lake St",
    "iso:country":"CA",
    "sg:address":"61A Paradise Lake St",
    "sg:city":"Lucknow",
    "sg:classifiers":[
        {
            "category":"Professional",
            "subcategory":"Accounting & Tax Preparation",
            "type":"Services"
        }
    ],
    "sg:phone":"+1 519 528 5115",
    "sg:postcode":"N0G 2H0",
    "sg:province":"ON",
    "sg:tags":[
        "accountant"
    ],
    "wof:name":"Gary Gehiere & Assoc Inc",
    "wof:placetype":"venue"
},
  "geometry": {"coordinates":[-81.516068,43.961304],"type":"Point"}
}