{
  "type": "Feature",
  "properties": {
    "iso:country":"CA",
    "sg:address":"1644 Merrittville Hwy",
    "sg:city":"Welland",
    "sg:classifiers":[
        {
            "category":"Restaurant",
            "type":"Food & Drink"
        }
    ],
    "sg:phone":"+1 905 384 0786",
    "sg:postcode":"L3B 5N5",
    "sg:province":"ON",
    "wof:name":"Tulky's Sports Bar & Grill Inc",
    "wof:placetype":"venue"
},
  "geometry": {"coordinates":[-79.2392425537,42.9934501648],"type":"Point"}
}