{
  "type": "Feature",
  "properties": {
    "addr:full":"81 Francis St W Mitchell ON N0K 1N0",
    "addr:housenumber":"81",
    "addr:postcode":"n0k 1n0",
    "addr:street":"Francis St W",
    "iso:country":"CA",
    "sg:address":"81 Francis St W",
    "sg:city":"Mitchell",
    "sg:classifiers":[
        {
            "category":"Recreation",
            "type":"Entertainment"
        }
    ],
    "sg:phone":"+1 519 348 8991",
    "sg:postcode":"N0K 1N0",
    "sg:province":"ON",
    "sg:tags":[
        "course",
        "golf"
    ],
    "wof:name":"Mitchell Golf Club Inc",
    "wof:placetype":"venue"
},
  "geometry": {"coordinates":[-81.188828,43.474964],"type":"Point"}
}