{
  "type": "Feature",
  "properties": {
    "addr:full":"649 Welham Rd Barrie ON L4N 0B7",
    "addr:housenumber":"649",
    "addr:postcode":"l4n 0b7",
    "addr:street":"Welham Rd",
    "iso:country":"CA",
    "sg:address":"649 Welham Rd",
    "sg:city":"Barrie",
    "sg:classifiers":[
        {
            "category":"Wholesale",
            "subcategory":"Durable Goods & Equipment",
            "type":"Manufacturing & Wholesale Goods"
        }
    ],
    "sg:phone":"+1 705 730 0850",
    "sg:postcode":"L4N 0B7",
    "sg:province":"ON",
    "sg:tags":[
        "representative",
        "manufacturer"
    ],
    "wof:name":"J O Bernt Bernt & Assoc",
    "wof:placetype":"venue"
},
  "geometry": {"coordinates":[-79.668892,44.335957],"type":"Point"}
}