{
  "type": "Feature",
  "properties": {
    "addr:full":"2346 Av Larue Beauport QC G1C 1K9",
    "addr:housenumber":"2346",
    "addr:postcode":"qc g1c 1k9",
    "addr:street":"Av Larue",
    "iso:country":"CA",
    "sg:address":"2346 Av Larue",
    "sg:city":"Beauport",
    "sg:classifiers":[
        {
            "category":"Restaurant",
            "type":"Food & Drink"
        }
    ],
    "sg:phone":"+1 418 660 2223",
    "sg:postcode":"G1C 1K9",
    "sg:province":"QC",
    "wof:name":"Casse-Croute Checkers",
    "wof:placetype":"venue"
},
  "geometry": {"coordinates":[-71.154915,46.888973],"type":"Point"}
}