{
  "type": "Feature",
  "properties": {
    "addr:full":"1847 Riverside Dr Timmins ON P4N 7C3",
    "addr:housenumber":"1847",
    "addr:postcode":"p4n 7c3",
    "addr:street":"Riverside Dr",
    "iso:country":"CA",
    "sg:address":"1847 Riverside Dr",
    "sg:city":"Timmins",
    "sg:classifiers":[
        {
            "category":"Retail",
            "subcategory":"Auto Repair",
            "type":"Services"
        }
    ],
    "sg:phone":"+1 705 268 6199",
    "sg:postcode":"P4N 7C3",
    "sg:province":"ON",
    "sg:tags":[
        "truck"
    ],
    "wof:name":"Timmins International",
    "wof:placetype":"venue"
},
  "geometry": {"coordinates":[-81.391869,48.472313],"type":"Point"}
}