{
  "type": "Feature",
  "properties": {
    "addr:full":"745 Clark Dr Vancouver BC V5L 3J3",
    "addr:housenumber":"745",
    "addr:postcode":"v5l 3j3",
    "addr:street":"Clark Dr",
    "iso:country":"CA",
    "sg:address":"745 Clark Dr",
    "sg:city":"Vancouver",
    "sg:classifiers":[
        {
            "category":"Manufacturing",
            "subcategory":"Textiles",
            "type":"Manufacturing & Wholesale Goods"
        }
    ],
    "sg:phone":"+1 604 255 7447",
    "sg:postcode":"V5L 3J3",
    "sg:province":"BC",
    "sg:tags":[
        "rug",
        "carpet"
    ],
    "wof:name":"Interface Flooring Systems Inc",
    "wof:placetype":"venue"
},
  "geometry": {"coordinates":[-123.07740800000001,49.278156],"type":"Point"}
}