{
  "type": "Feature",
  "properties": {
    "addr:full":"324 Main St Penticton BC V2A 5C3",
    "addr:housenumber":"324",
    "addr:postcode":"v2a 5c3",
    "addr:street":"Main St",
    "iso:country":"CA",
    "sg:address":"324 Main St",
    "sg:city":"Penticton",
    "sg:classifiers":[
        {
            "category":"Shopping",
            "subcategory":"Tobacco",
            "type":"Retail Goods"
        }
    ],
    "sg:phone":"+1 250 492 8704",
    "sg:postcode":"V2A 5C3",
    "sg:province":"BC",
    "sg:tags":[
        "cigarette",
        "cigar",
        "dealer"
    ],
    "wof:name":"D J's Convenience Store",
    "wof:placetype":"venue"
},
  "geometry": {"coordinates":[-119.592071533,49.4984588623],"type":"Point"}
}