{
  "type": "Feature",
  "properties": {
    "addr:full":"355 Blake St E Listowel ON N4W 2W1",
    "addr:housenumber":"355",
    "addr:postcode":"n4w 2w1",
    "addr:street":"Blake St E",
    "iso:country":"CA",
    "sg:address":"355 Blake St E",
    "sg:city":"Listowel",
    "sg:classifiers":[
        {
            "category":"Personal",
            "subcategory":"Beauty Salon",
            "type":"Services"
        }
    ],
    "sg:phone":"+1 519 291 9774",
    "sg:postcode":"N4W 2W1",
    "sg:province":"ON",
    "wof:name":"Hair Shop By Cecilia",
    "wof:placetype":"venue"
},
  "geometry": {"coordinates":[-80.944534,43.736347],"type":"Point"}
}