{
  "type": "Feature",
  "properties": {
    "addr:full":"487 Av Royale Beauport QC G1E 1Y2",
    "addr:postcode":"qc g1e 1y2",
    "addr:street":"487 Av Royale",
    "iso:country":"CA",
    "sg:address":"487 Av Royale",
    "sg:city":"Beauport",
    "sg:classifiers":[
        {
            "category":"Retail",
            "subcategory":"Auto Repair",
            "type":"Services"
        }
    ],
    "sg:phone":"+1 418 661 6462",
    "sg:postcode":"G1E 1Y2",
    "sg:province":"QC",
    "sg:tags":[
        "repairing",
        "automobile"
    ],
    "wof:name":"Garage Roch Guillot Inc",
    "wof:placetype":"venue"
},
  "geometry": {"coordinates":[-71.1963348389,46.857006073],"type":"Point"}
}