{
  "type": "Feature",
  "properties": {
    "addr:full":"264 Welland Ave St Catharines ON L2R 2P8",
    "addr:housenumber":"264",
    "addr:postcode":"l2r 2p8",
    "addr:street":"Welland Ave",
    "iso:country":"CA",
    "sg:address":"264 Welland Ave",
    "sg:city":"St Catharines",
    "sg:classifiers":[
        {
            "category":"Manufacturing",
            "subcategory":"Motor Vehicles & Parts",
            "type":"Manufacturing & Wholesale Goods"
        }
    ],
    "sg:phone":"+1 905 984 4000",
    "sg:postcode":"L2R 2P8",
    "sg:province":"ON",
    "sg:tags":[
        "equipment",
        "truck"
    ],
    "wof:name":"Moss Ats Mfg Inc",
    "wof:placetype":"venue"
},
  "geometry": {"coordinates":[-79.232826,43.168224],"type":"Point"}
}