{
  "type": "Feature",
  "properties": {
    "addr:full":"18 Milner Gate Thornhill ON L4J 2N4",
    "addr:housenumber":"18",
    "addr:postcode":"l4j 2n4",
    "addr:street":"Milner Gate",
    "iso:country":"CA",
    "sg:address":"18 Milner Gate",
    "sg:city":"Thornhill",
    "sg:classifiers":[
        {
            "category":"Professional",
            "subcategory":"Accounting & Tax Preparation",
            "type":"Services"
        }
    ],
    "sg:phone":"+1 905 886 9766",
    "sg:postcode":"L4J 2N4",
    "sg:province":"ON",
    "sg:tags":[
        "accountant"
    ],
    "wof:name":"Thansingh, Aneal R",
    "wof:placetype":"venue"
},
  "geometry": {"coordinates":[-79.4481964111,43.7994003296],"type":"Point"}
}