{
  "type": "Feature",
  "properties": {
    "iso:country":"CA",
    "sg:address":"Suite 250, 13571 Commerce Parkway",
    "sg:city":"Richmond, BC",
    "sg:classifiers":[
        {
            "category":"Manufacturing",
            "subcategory":"Electronics",
            "type":"Manufacturing & Wholesale Goods"
        }
    ],
    "sg:postcode":"V6V 2R2",
    "sg:website":"http://www.zeugmasystems.com",
    "wof:name":"Zeugma Systems",
    "wof:placetype":"venue"
},
  "geometry": {"coordinates":[-123.07175100000001,49.1739359],"type":"Point"}
}