{
  "type": "Feature",
  "properties": {
    "addr:full":"Surrey BC V3W 2W3",
    "addr:postcode":"v3w 2w3",
    "iso:country":"CA",
    "sg:city":"Surrey",
    "sg:classifiers":[
        {
            "category":"Social Services",
            "subcategory":"Job Training",
            "type":"Services"
        }
    ],
    "sg:phone":"+1 604 592 9119",
    "sg:postcode":"V3W 2W3",
    "sg:province":"BC",
    "sg:tags":[
        "physiotherapist",
        "rehabilitation"
    ],
    "wof:name":"Rehabmax Physiotherapy & Sport",
    "wof:placetype":"venue"
},
  "geometry": {"coordinates":[-122.846603394,49.1409835815],"type":"Point"}
}