{
  "type": "Feature",
  "properties": {
    "addr:full":"4186 Orkney Beach Rd Orillia ON L3V 6H7",
    "addr:housenumber":"4186",
    "addr:postcode":"l3v 6h7",
    "addr:street":"Orkney Beach Rd",
    "iso:country":"CA",
    "sg:address":"4186 Orkney Beach Rd",
    "sg:city":"Orillia",
    "sg:classifiers":[
        {
            "category":"Manufacturing",
            "subcategory":"Tools & Machinery",
            "type":"Manufacturing & Wholesale Goods"
        }
    ],
    "sg:phone":"+1 705 327 2089",
    "sg:postcode":"L3V 6H7",
    "sg:province":"ON",
    "sg:tags":[
        "compressor"
    ],
    "wof:name":"Jpf Industries",
    "wof:placetype":"venue"
},
  "geometry": {"coordinates":[-79.41822814939999,44.606590271],"type":"Point"}
}