{
  "type": "Feature",
  "properties": {
    "iso:country":"CA",
    "sg:address":"1943 Millstream Rd",
    "sg:city":"Victoria",
    "sg:classifiers":[
        {
            "category":"Wholesale",
            "subcategory":"Scrap",
            "type":"Manufacturing & Wholesale Goods"
        }
    ],
    "sg:phone":"+1 250 478 9886",
    "sg:postcode":"V9B 6E2",
    "sg:province":"BC",
    "sg:tags":[
        "waste"
    ],
    "wof:name":"Highwest Waste Recycler",
    "wof:placetype":"venue"
},
  "geometry": {"coordinates":[-123.364517212,48.428314209],"type":"Point"}
}