{
  "type": "Feature",
  "properties": {
    "addr:full":"666 Water St E Summerside PE C1N 4J1",
    "addr:housenumber":"666",
    "addr:postcode":"c1n 4j1",
    "addr:street":"Water St E",
    "iso:country":"CA",
    "sg:address":"666 Water St E",
    "sg:city":"Summerside",
    "sg:classifiers":[
        {
            "category":"Autos & Motor Vehicles",
            "subcategory":"Automobile Sales",
            "type":"Retail Goods"
        }
    ],
    "sg:phone":"+1 902 436 4289",
    "sg:postcode":"C1N 4J1",
    "sg:province":"PE",
    "sg:tags":[
        "car",
        "dealer"
    ],
    "wof:name":"City Motors",
    "wof:placetype":"venue"
},
  "geometry": {"coordinates":[-63.763882,46.396351],"type":"Point"}
}