{
  "type": "Feature",
  "properties": {
    "addr:full":"14610 116 Ave NW Edmonton AB T5M 3E9",
    "addr:housenumber":"14610",
    "addr:postcode":"t5m 3e9",
    "addr:street":"116 Ave Nw",
    "iso:country":"CA",
    "sg:address":"14610 116 Ave NW",
    "sg:city":"Edmonton",
    "sg:classifiers":[
        {
            "category":"Wholesale",
            "subcategory":"Electrical",
            "type":"Manufacturing & Wholesale Goods"
        }
    ],
    "sg:phone":"+1 780 452 3330",
    "sg:postcode":"T5M 3E9",
    "sg:province":"AB",
    "sg:tags":[
        "meter"
    ],
    "wof:name":"Capital Meter Svc Ltd",
    "wof:placetype":"venue"
},
  "geometry": {"coordinates":[-113.57240299999999,53.568027],"type":"Point"}
}