{
  "type": "Feature",
  "properties": {
    "addr:full":"310 Rue Hebert Deauville QC J1N 3L5",
    "addr:housenumber":"310",
    "addr:postcode":"j1n 3l5",
    "addr:street":"Rue Hebert",
    "iso:country":"CA",
    "sg:address":"310 Rue Hebert",
    "sg:city":"Deauville",
    "sg:classifiers":[
        {
            "category":"Building & Trades",
            "subcategory":"Construction",
            "type":"Services"
        }
    ],
    "sg:phone":"+1 819 864 9572",
    "sg:postcode":"J1N 3L5",
    "sg:province":"QC",
    "sg:tags":[
        "painter"
    ],
    "wof:name":"Plante Jean Peintre Enr",
    "wof:placetype":"venue"
},
  "geometry": {"coordinates":[-72.03851299999999,45.342304],"type":"Point"}
}