{
  "type": "Feature",
  "properties": {
    "addr:full":"424 26E Av Deux-Montagnes QC J7R 5P6",
    "addr:housenumber":"424",
    "addr:postcode":"j7r 5p6",
    "addr:street":"26E Av Deux-Montagnes",
    "iso:country":"CA",
    "sg:address":"424 26E Av",
    "sg:city":"Deux-Montagnes",
    "sg:classifiers":[
        {
            "category":"Wholesale",
            "subcategory":"Durable Goods & Equipment",
            "type":"Manufacturing & Wholesale Goods"
        }
    ],
    "sg:phone":"+1 450 472 9918",
    "sg:postcode":"J7R 5P6",
    "sg:province":"QC",
    "sg:tags":[
        "representative",
        "manufacturer"
    ],
    "wof:name":"Rfm Electro",
    "wof:placetype":"venue"
},
  "geometry": {"coordinates":[-73.9155502319,45.5384979248],"type":"Point"}
}