{
  "type": "Feature",
  "properties": {
    "addr:full":"358 Rideau St Ottawa ON K1N 5Y8",
    "addr:housenumber":"358",
    "addr:postcode":"k1n 5y8",
    "addr:street":"Rideau St",
    "iso:country":"CA",
    "sg:address":"358 Rideau St",
    "sg:city":"Ottawa",
    "sg:classifiers":[
        {
            "category":"Professional",
            "subcategory":"Printing & Photocopies",
            "type":"Services"
        }
    ],
    "sg:phone":"+1 613 241 7150",
    "sg:postcode":"K1N 5Y8",
    "sg:province":"ON",
    "sg:tags":[
        "duplicating",
        "copying"
    ],
    "wof:name":"Budget Copy & Printing",
    "wof:placetype":"venue"
},
  "geometry": {"coordinates":[-75.6835784912,45.4295310974],"type":"Point"}
}