{
  "type": "Feature",
  "properties": {
    "addr:full":"Surrey BC V3W 0H9",
    "addr:postcode":"v3w 0h9",
    "iso:country":"CA",
    "sg:city":"Surrey",
    "sg:classifiers":[
        {
            "category":"Restaurant",
            "type":"Food & Drink"
        }
    ],
    "sg:phone":"+1 604 599 8877",
    "sg:postcode":"V3W 0H9",
    "sg:province":"BC",
    "wof:name":"Boston Pizza",
    "wof:placetype":"venue"
},
  "geometry": {"coordinates":[-122.845688,49.140831],"type":"Point"}
}