{
  "type": "Feature",
  "properties": {
    "addr:full":"407 Lindsay Rd 5 Lions Head ON N0H 1W0",
    "addr:housenumber":"407;5",
    "addr:postcode":"n0h 1w0",
    "addr:street":"Lindsay Rd;Lions Head",
    "iso:country":"CA",
    "sg:address":"407 Lindsay Rd 5",
    "sg:city":"Lions Head",
    "sg:classifiers":[
        {
            "category":"Building & Trades",
            "subcategory":"Construction",
            "type":"Services"
        }
    ],
    "sg:phone":"+1 519 793 4467",
    "sg:postcode":"N0H 1W0",
    "sg:province":"ON",
    "sg:tags":[
        "excavating",
        "contractor"
    ],
    "wof:name":"Bridge Excavating",
    "wof:placetype":"venue"
},
  "geometry": {"coordinates":[-81.25420379640001,44.986579895],"type":"Point"}
}