{
  "type": "Feature",
  "properties": {
    "addr:full":"540 114E Rue Shawinigan-Sud QC G9P 2X8",
    "addr:housenumber":"540",
    "addr:postcode":"g9p 2x8",
    "addr:street":"114E Rue Shawinigan-Sud",
    "iso:country":"CA",
    "sg:address":"540 114E Rue",
    "sg:city":"Shawinigan-Sud",
    "sg:classifiers":[
        {
            "category":"Retail",
            "subcategory":"Auto Repair",
            "type":"Services"
        }
    ],
    "sg:phone":"+1 819 536 4337",
    "sg:postcode":"G9P 2X8",
    "sg:province":"QC",
    "sg:tags":[
        "repairing",
        "automobile",
        "welding"
    ],
    "wof:name":"Garage Berrouard",
    "wof:placetype":"venue"
},
  "geometry": {"coordinates":[-72.750626,46.523197],"type":"Point"}
}