{
  "type": "Feature",
  "properties": {
    "addr:full":"803 Johnson St Kingston ON K7L 2B6",
    "addr:housenumber":"803",
    "addr:postcode":"k7l 2b6",
    "addr:street":"Johnson St",
    "iso:country":"CA",
    "sg:address":"803 Johnson St",
    "sg:city":"Kingston",
    "sg:classifiers":[
        {
            "category":"Building & Trades",
            "subcategory":"Landscaping Services",
            "type":"Services"
        }
    ],
    "sg:phone":"+1 613 542 3393",
    "sg:postcode":"K7L 2B6",
    "sg:province":"ON",
    "sg:tags":[
        "designer",
        "landscape"
    ],
    "wof:name":"Carl Bray & Assoc Ltd",
    "wof:placetype":"venue"
},
  "geometry": {"coordinates":[-76.51010100000001,44.231281],"type":"Point"}
}