{
  "type": "Feature",
  "properties": {
    "addr:full":"1408 Gordon St Guelph ON N1L 1C8",
    "addr:housenumber":"1408",
    "addr:postcode":"n1l 1c8",
    "addr:street":"Gordon St",
    "iso:country":"CA",
    "sg:address":"1408 Gordon St",
    "sg:city":"Guelph",
    "sg:classifiers":[
        {
            "category":"Wholesale",
            "subcategory":"Meat",
            "type":"Manufacturing & Wholesale Goods"
        }
    ],
    "sg:phone":"+1 519 824 2579",
    "sg:postcode":"N1L 1C8",
    "sg:province":"ON",
    "sg:tags":[
        "butchering"
    ],
    "wof:name":"DE Vos Quality Meats",
    "wof:placetype":"venue"
},
  "geometry": {"coordinates":[-80.1974105835,43.5124053955],"type":"Point"}
}