{
  "type": "Feature",
  "properties": {
    "addr:full":"Richmond Hill ON L4C 9M5",
    "addr:postcode":"l4c 9m5",
    "iso:country":"CA",
    "sg:city":"Richmond Hill",
    "sg:classifiers":[
        {
            "category":"Professional",
            "subcategory":"Lawyer & Legal Services",
            "type":"Services"
        }
    ],
    "sg:phone":"+1 905 883 1803",
    "sg:postcode":"L4C 9M5",
    "sg:province":"ON",
    "sg:tags":[
        "attorney"
    ],
    "wof:name":"Mendlowicz, Lisa",
    "wof:placetype":"venue"
},
  "geometry": {"coordinates":[-79.4344406128,43.8599510193],"type":"Point"}
}