{
  "type": "Feature",
  "properties": {
    "iso:country":"CA",
    "sg:address":"29 Woodland Dr",
    "sg:city":"Cambridge",
    "sg:classifiers":[
        {
            "category":"Personal",
            "type":"Services"
        }
    ],
    "sg:phone":"+1 519 622 1271",
    "sg:postcode":"N1R 2X7",
    "sg:province":"ON",
    "sg:tags":[
        "pet",
        "boarding",
        "bureau",
        "sitting"
    ],
    "wof:name":"Pause 4 Paws",
    "wof:placetype":"venue"
},
  "geometry": {"coordinates":[-80.307343,43.34156],"type":"Point"}
}