{
  "type": "Feature",
  "properties": {
    "iso:country":"CA",
    "sg:address":"250 Harmony Rd S",
    "sg:city":"Oshawa",
    "sg:classifiers":[
        {
            "category":"Education",
            "subcategory":"School",
            "type":"Public Place"
        }
    ],
    "sg:phone":"+1 905 728 7315",
    "sg:postcode":"L1H 6T9",
    "sg:province":"ON",
    "wof:name":"F J Donevan Collegiate Inst",
    "wof:placetype":"venue"
},
  "geometry": {"coordinates":[-78.8309173584,43.8971710205],"type":"Point"}
}