{
  "type": "Feature",
  "properties": {
    "iso:country":"CA",
    "sg:address":"610 Thornhill St",
    "sg:city":"Morden",
    "sg:classifiers":[
        {
            "category":"Restaurant",
            "type":"Food & Drink"
        }
    ],
    "sg:phone":"+1 204 822 9566",
    "sg:postcode":"R6M 1E8",
    "sg:province":"MB",
    "wof:name":"King Ho Chinese Food Ltd",
    "wof:placetype":"venue"
},
  "geometry": {"coordinates":[-98.09973144529999,49.1921615601],"type":"Point"}
}