{
  "type": "Feature",
  "properties": {
    "addr:full":"4125 Boul Des Forges # F9 Trois-Rivieres QC G8Y 1W1",
    "addr:housenumber":"4125",
    "addr:postcode":"g8y 1w1",
    "addr:street":"Boul Des Forges # F9 Trois-Rivieres",
    "iso:country":"CA",
    "sg:address":"4125 Boul Des Forges # F9",
    "sg:city":"Trois-Rivieres",
    "sg:classifiers":[
        {
            "category":"Restaurant",
            "type":"Food & Drink"
        }
    ],
    "sg:phone":"+1 819 693 1297",
    "sg:postcode":"G8Y 1W1",
    "sg:province":"QC",
    "wof:name":"Valentine Restaurant",
    "wof:placetype":"venue"
},
  "geometry": {"coordinates":[-72.5862503052,46.3563957214],"type":"Point"}
}