{
  "type": "Feature",
  "properties": {
    "addr:full":"115 Kirkpatrick St Kingston ON K7K 2P4",
    "addr:housenumber":"115",
    "addr:postcode":"k7k 2p4",
    "addr:street":"Kirkpatrick St",
    "iso:country":"CA",
    "sg:address":"115 Kirkpatrick St",
    "sg:city":"Kingston",
    "sg:classifiers":[
        {
            "category":"Education",
            "subcategory":"Library",
            "type":"Public Place"
        }
    ],
    "sg:phone":"+1 613 546 0698",
    "sg:postcode":"K7K 2P4",
    "sg:province":"ON",
    "wof:name":"Kingscourt Branch Library",
    "wof:placetype":"venue"
},
  "geometry": {"coordinates":[-76.500298,44.253437],"type":"Point"}
}