{
  "type": "Feature",
  "properties": {
    "iso:country":"CA",
    "sg:address":"115 Kirkpatrick St",
    "sg:city":"Kingston",
    "sg:classifiers":[
        {
            "category":"Education",
            "subcategory":"Library",
            "type":"Public Place"
        }
    ],
    "sg:phone":"+1 613 546 0698",
    "sg:postcode":"K7K 2P4",
    "sg:province":"ON",
    "wof:name":"Kingscourt Branch Library",
    "wof:placetype":"venue"
},
  "geometry": {"coordinates":[-76.500298,44.253437],"type":"Point"}
}