{
  "type": "Feature",
  "properties": {
    "addr:full":"1039 Dundas St Woodstock ON N4S 1H5",
    "addr:housenumber":"1039",
    "addr:postcode":"n4s 1h5",
    "addr:street":"Dundas St",
    "iso:country":"CA",
    "sg:address":"1039 Dundas St",
    "sg:city":"Woodstock",
    "sg:classifiers":[
        {
            "category":"Professional",
            "subcategory":"Business Services",
            "type":"Services"
        }
    ],
    "sg:phone":"+1 519 539 3330",
    "sg:postcode":"N4S 1H5",
    "sg:province":"ON",
    "sg:tags":[
        "packaging",
        "machinery"
    ],
    "wof:name":"Sertapak Inc",
    "wof:placetype":"venue"
},
  "geometry": {"coordinates":[-80.727897644,43.1344642639],"type":"Point"}
}