{
  "type": "Feature",
  "properties": {
    "iso:country":"CA",
    "sg:address":"319 James St",
    "sg:city":"Delhi",
    "sg:classifiers":[
        {
            "category":"Restaurant",
            "type":"Food & Drink"
        }
    ],
    "sg:phone":"+1 519 582 0323",
    "sg:postcode":"N4B 2B3",
    "sg:province":"ON",
    "sg:tags":[
        "parlor",
        "ice",
        "cream"
    ],
    "wof:name":"Delhi Dairy Freeze",
    "wof:placetype":"venue"
},
  "geometry": {"coordinates":[-80.4931106567,42.852973938],"type":"Point"}
}