{
  "type": "Feature",
  "properties": {
    "addr:full":"73 Sackville Cross Rd Lower Sackville NS B4C 2M2",
    "addr:housenumber":"73",
    "addr:postcode":"b4c 2m2",
    "addr:street":"Sackville Cross Rd",
    "iso:country":"CA",
    "sg:address":"73 Sackville Cross Rd",
    "sg:city":"Lower Sackville",
    "sg:classifiers":[
        {
            "category":"Retail",
            "subcategory":"Auto Repair",
            "type":"Services"
        }
    ],
    "sg:phone":"+1 902 864 9466",
    "sg:postcode":"B4C 2M2",
    "sg:province":"NS",
    "sg:tags":[
        "repairing",
        "automobile"
    ],
    "wof:name":"Corbin's Automotive",
    "wof:placetype":"venue"
},
  "geometry": {"coordinates":[-63.686989,44.765171],"type":"Point"}
}