{
  "type": "Feature",
  "properties": {
    "addr:full":"54 Queen St N Kitchener ON N2H 2H2",
    "addr:housenumber":"54",
    "addr:postcode":"n2h 2h2",
    "addr:street":"Queen St N",
    "iso:country":"CA",
    "sg:address":"54 Queen St N",
    "sg:city":"Kitchener",
    "sg:classifiers":[
        {
            "category":"Organizations",
            "subcategory":"Religious Organization",
            "type":"Services"
        }
    ],
    "sg:phone":"+1 519 578 4430",
    "sg:postcode":"N2H 2H2",
    "sg:province":"ON",
    "sg:tags":[
        "church"
    ],
    "wof:name":"St Andrew's Presbyterian Chr",
    "wof:placetype":"venue"
},
  "geometry": {"coordinates":[-80.48751068120001,43.4521141052],"type":"Point"}
}