{
  "type": "Feature",
  "properties": {
    "addr:full":"38 Metropolitan Rd Scarborough ON M1R 2T6",
    "addr:housenumber":"38",
    "addr:postcode":"m1r 2t6",
    "addr:street":"Metropolitan Rd",
    "iso:country":"CA",
    "sg:address":"38 Metropolitan Rd",
    "sg:city":"Scarborough",
    "sg:classifiers":[
        {
            "category":"Wholesale",
            "subcategory":"Apparel",
            "type":"Manufacturing & Wholesale Goods"
        }
    ],
    "sg:phone":"+1 416 754 2300",
    "sg:postcode":"M1R 2T6",
    "sg:province":"ON",
    "sg:tags":[
        "clothing"
    ],
    "wof:name":"Wing Son Garments",
    "wof:placetype":"venue"
},
  "geometry": {"coordinates":[-79.3009262085,43.7677536011],"type":"Point"}
}