{
  "type": "Feature",
  "properties": {
    "addr:full":"7161 Victoria Dr Vancouver BC V5P 3Y9",
    "addr:housenumber":"7161",
    "addr:postcode":"v5p 3y9",
    "addr:street":"Victoria Dr",
    "iso:country":"CA",
    "sg:address":"7161 Victoria Dr",
    "sg:city":"Vancouver",
    "sg:classifiers":[
        {
            "category":"Home & Garden",
            "subcategory":"Furniture",
            "type":"Retail Goods"
        }
    ],
    "sg:phone":"+1 604 325 7946",
    "sg:postcode":"V5P 3Y9",
    "sg:province":"BC",
    "wof:name":"Guardian Interiors Ltd",
    "wof:placetype":"venue"
},
  "geometry": {"coordinates":[-123.066216,49.219162],"type":"Point"}
}