{
  "type": "Feature",
  "properties": {
    "addr:full":"322 Kintyre Pvt Ottawa ON K2C 3M6",
    "addr:housenumber":"322",
    "addr:postcode":"k2c 3m6",
    "addr:street":"Kintyre Pvt",
    "iso:country":"CA",
    "sg:address":"322 Kintyre Pvt",
    "sg:city":"Ottawa",
    "sg:classifiers":[
        {
            "category":"Health Services",
            "subcategory":"Health Practitioner",
            "type":"Services"
        }
    ],
    "sg:phone":"+1 613 224 0445",
    "sg:postcode":"K2C 3M6",
    "sg:province":"ON",
    "sg:tags":[
        "psychotherapist"
    ],
    "wof:name":"Sereinity Counselling Addctn",
    "wof:placetype":"venue"
},
  "geometry": {"coordinates":[-75.709129,45.364761],"type":"Point"}
}