{
  "type": "Feature",
  "properties": {
    "iso:country":"CA",
    "sg:address":"1433 4E Av",
    "sg:city":"Quebec",
    "sg:classifiers":[
        {
            "category":"Professional",
            "subcategory":"Business Services",
            "type":"Services"
        }
    ],
    "sg:phone":"+1 418 525 5738",
    "sg:postcode":"G1J 3B9",
    "sg:province":"QC",
    "sg:tags":[
        "notary"
    ],
    "wof:name":"Bureau Marcel Poulin",
    "wof:placetype":"venue"
},
  "geometry": {"coordinates":[-71.230698,46.830048],"type":"Point"}
}