{
  "type": "Feature",
  "properties": {
    "addr:full":"3451 Av Connaught Montreal QC H4B 1X4",
    "addr:housenumber":"3451",
    "addr:postcode":"h4b 1x4",
    "addr:street":"Av Connaught",
    "iso:country":"CA",
    "sg:address":"3451 Av Connaught",
    "sg:city":"Montreal",
    "sg:classifiers":[
        {
            "category":"Professional",
            "subcategory":"Art Services",
            "type":"Services"
        }
    ],
    "sg:phone":"+1 514 489 4883",
    "sg:postcode":"H4B 1X4",
    "sg:province":"QC",
    "sg:tags":[
        "graphic",
        "designer"
    ],
    "wof:name":"R H Design",
    "wof:placetype":"venue"
},
  "geometry": {"coordinates":[-73.64347100000001,45.454556],"type":"Point"}
}