{
  "type": "Feature",
  "properties": {
    "iso:country":"CA",
    "sg:address":"210 Rue Roland-Jeanneau",
    "sg:city":"Verdun",
    "sg:classifiers":[
        {
            "category":"Shopping",
            "subcategory":"Computers & Home Electronics",
            "type":"Retail Goods"
        }
    ],
    "sg:phone":"+1 514 769 3533",
    "sg:postcode":"H3E 1R5",
    "sg:province":"QC",
    "sg:tags":[
        "publishing"
    ],
    "wof:name":"Communiplex Marketing Inc",
    "wof:placetype":"venue"
},
  "geometry": {"coordinates":[-73.571762,45.459019],"type":"Point"}
}