{
  "type": "Feature",
  "properties": {
    "addr:full":"546 Belmont Ave W Kitchener ON N2M 5E3",
    "addr:housenumber":"546",
    "addr:postcode":"n2m 5e3",
    "addr:street":"Belmont Ave W",
    "iso:country":"CA",
    "sg:address":"546 Belmont Ave W",
    "sg:city":"Kitchener",
    "sg:classifiers":[
        {
            "category":"Real Estate",
            "subcategory":"Architect",
            "type":"Services"
        }
    ],
    "sg:phone":"+1 519 576 2150",
    "sg:postcode":"N2M 5E3",
    "sg:province":"ON",
    "sg:tags":[
        "engineer"
    ],
    "wof:name":"Walter Fedy Partnership",
    "wof:placetype":"venue"
},
  "geometry": {"coordinates":[-80.5146331787,43.4484176636],"type":"Point"}
}