{
  "type": "Feature",
  "properties": {
    "iso:country":"CA",
    "sg:address":"213 Vine St",
    "sg:city":"St Catharines",
    "sg:classifiers":[
        {
            "category":"Retail",
            "subcategory":"Portrait Studio",
            "type":"Services"
        }
    ],
    "sg:phone":"+1 905 935 1690",
    "sg:postcode":"L2M 4S7",
    "sg:province":"ON",
    "sg:tags":[
        "photographer"
    ],
    "wof:name":"Cheryl Thiessen Photography",
    "wof:placetype":"venue"
},
  "geometry": {"coordinates":[-79.23059082029999,43.1755714417],"type":"Point"}
}