{
  "type": "Feature",
  "properties": {
    "iso:country":"CA",
    "sg:address":"1654 Tryon Rd",
    "sg:city":"Sharbot Lake",
    "sg:classifiers":[
        {
            "category":"Retail",
            "subcategory":"Repair Shop",
            "type":"Services"
        }
    ],
    "sg:phone":"+1 613 279 3033",
    "sg:postcode":"K0H 2P0",
    "sg:province":"ON",
    "sg:tags":[
        "valve"
    ],
    "wof:name":"Process & Steam Specialties",
    "wof:placetype":"venue"
},
  "geometry": {"coordinates":[-76.6874008179,44.7715492249],"type":"Point"}
}