{
  "type": "Feature",
  "properties": {
    "addr:full":"129 Clifton Rd Toronto ON M4T 2G5",
    "addr:housenumber":"129",
    "addr:postcode":"m4t 2g5",
    "addr:street":"Clifton Rd",
    "iso:country":"CA",
    "sg:address":"129 Clifton Rd",
    "sg:city":"Toronto",
    "sg:classifiers":[
        {
            "category":"Building & Trades",
            "subcategory":"Landscaping Services",
            "type":"Services"
        }
    ],
    "sg:phone":"+1 416 638 5004",
    "sg:postcode":"M4T 2G5",
    "sg:province":"ON",
    "sg:tags":[
        "lawn",
        "contractor",
        "landscape",
        "maintenance",
        "grounds"
    ],
    "wof:name":"Greensward Gardening & Lndscpg",
    "wof:placetype":"venue"
},
  "geometry": {"coordinates":[-79.38537599999999,43.692265],"type":"Point"}
}