{
  "type": "Feature",
  "properties": {
    "addr:full":"200 Memorial Ave N Russell MB R0J 1W0",
    "addr:housenumber":"200",
    "addr:postcode":"r0j 1w0",
    "addr:street":"Memorial Ave N",
    "iso:country":"CA",
    "sg:address":"200 Memorial Ave N",
    "sg:city":"Russell",
    "sg:classifiers":[
        {
            "category":"Organizations",
            "subcategory":"Religious Organization",
            "type":"Services"
        }
    ],
    "sg:phone":"+1 204 773 2071",
    "sg:postcode":"R0J 1W0",
    "sg:province":"MB",
    "sg:tags":[
        "church"
    ],
    "wof:name":"United Church of Canada",
    "wof:placetype":"venue"
},
  "geometry": {"coordinates":[-101.288269,50.773129],"type":"Point"}
}