{
  "type": "Feature",
  "properties": {
    "addr:full":"7585 Boul Lacordaire Saint-Leonard QC H1S 2A6",
    "addr:housenumber":"7585",
    "addr:postcode":"h1s 2a6",
    "addr:street":"Boul Lacordaire",
    "iso:country":"CA",
    "sg:address":"7585 Boul Lacordaire",
    "sg:city":"Saint-Leonard",
    "sg:classifiers":[
        {
            "category":"Wholesale",
            "subcategory":"Machinery & Supplies",
            "type":"Manufacturing & Wholesale Goods"
        }
    ],
    "sg:phone":"+1 514 721 3281",
    "sg:postcode":"H1S 2A6",
    "sg:province":"QC",
    "sg:tags":[
        "machine",
        "sewing"
    ],
    "wof:name":"Veillet, Jean-Marie",
    "wof:placetype":"venue"
},
  "geometry": {"coordinates":[-73.5839996338,45.5823516846],"type":"Point"}
}