{
  "type": "Feature",
  "properties": {
    "iso:country":"CA",
    "sg:address":"80 Ch Tobique",
    "sg:city":"Grand Falls",
    "sg:classifiers":[
        {
            "category":"Restaurant",
            "type":"Food & Drink"
        }
    ],
    "sg:phone":"+1 506 473 3713",
    "sg:postcode":"E3Y 1B9",
    "sg:province":"NB",
    "sg:tags":[
        "pizza"
    ],
    "wof:name":"Pizza Boy",
    "wof:placetype":"venue"
},
  "geometry": {"coordinates":[-67.7342834473,47.0513648987],"type":"Point"}
}