{
  "type": "Feature",
  "properties": {
    "addr:full":"91 Erickson Rd Campbell River BC V9W 1S6",
    "addr:housenumber":"91",
    "addr:postcode":"v9w 1s6",
    "addr:street":"Erickson Rd",
    "iso:country":"CA",
    "sg:address":"91 Erickson Rd",
    "sg:city":"Campbell River",
    "sg:classifiers":[
        {
            "category":"Manufacturing",
            "subcategory":"Watercraft",
            "type":"Manufacturing & Wholesale Goods"
        }
    ],
    "sg:phone":"+1 250 923 1790",
    "sg:postcode":"V9W 1S6",
    "sg:province":"BC",
    "sg:tags":[
        "boat"
    ],
    "wof:name":"Eagle Leasing Ltd",
    "wof:placetype":"venue"
},
  "geometry": {"coordinates":[-125.210052,49.966152],"type":"Point"}
}