{
  "type": "Feature",
  "properties": {
    "addr:full":"326 Queenston Rd Hamilton ON L8K 1H6",
    "addr:housenumber":"326",
    "addr:postcode":"l8k 1h6",
    "addr:street":"Queenston Rd",
    "iso:country":"CA",
    "sg:address":"326 Queenston Rd",
    "sg:city":"Hamilton",
    "sg:classifiers":[
        {
            "category":"Personal",
            "subcategory":"Beauty Salon",
            "type":"Services"
        }
    ],
    "sg:phone":"+1 905 547 5009",
    "sg:postcode":"L8K 1H6",
    "sg:province":"ON",
    "wof:name":"Sylvana's Hair Salon",
    "wof:placetype":"venue"
},
  "geometry": {"coordinates":[-79.78977966310001,43.2335777283],"type":"Point"}
}