{
  "type": "Feature",
  "properties": {
    "iso:country":"CA",
    "sg:address":"PO Box 1260 STN Main",
    "sg:city":"Whitecourt",
    "sg:classifiers":[
        {
            "category":"Freight",
            "type":"Transportation"
        }
    ],
    "sg:phone":"+1 780 778 4192",
    "sg:postcode":"T7S 1P2",
    "sg:province":"AB",
    "sg:tags":[
        "trucking"
    ],
    "wof:name":"Bruce Boyce Trucking Ltd",
    "wof:placetype":"venue"
},
  "geometry": {"coordinates":[-115.70787811300001,54.1394348145],"type":"Point"}
}