{
  "type": "Feature",
  "properties": {
    "addr:full":"2655 Liruma Rd Mississauga ON L5K 1Y8",
    "addr:housenumber":"2655",
    "addr:postcode":"l5k 1y8",
    "addr:street":"Liruma Rd",
    "iso:country":"CA",
    "sg:address":"2655 Liruma Rd",
    "sg:city":"Mississauga",
    "sg:classifiers":[
        {
            "category":"Personal",
            "subcategory":"Beauty Salon",
            "type":"Services"
        }
    ],
    "sg:phone":"+1 905 855 9048",
    "sg:postcode":"L5K 1Y8",
    "sg:province":"ON",
    "wof:name":"Unique Nails",
    "wof:placetype":"venue"
},
  "geometry": {"coordinates":[-79.6718826294,43.5305213928],"type":"Point"}
}