{
  "type": "Feature",
  "properties": {
    "addr:full":"458 Av Saint-Charles Vaudreuil-Dorion QC J7V 2N5",
    "addr:postcode":"j7v 2n5",
    "addr:street":"458 Av Saint-Charles",
    "iso:country":"CA",
    "sg:address":"458 Av Saint-Charles",
    "sg:city":"Vaudreuil-Dorion",
    "sg:classifiers":[
        {
            "category":"Personal",
            "type":"Services"
        }
    ],
    "sg:phone":"+1 450 424 9141",
    "sg:postcode":"J7V 2N5",
    "sg:province":"QC",
    "sg:tags":[
        "control",
        "weight"
    ],
    "wof:name":"Clinique Diete-Equilib",
    "wof:placetype":"venue"
},
  "geometry": {"coordinates":[-74.0291442871,45.4014892578],"type":"Point"}
}