{
  "type": "Feature",
  "properties": {
    "addr:full":"Sainte-Foy QC G1N 4L5",
    "addr:postcode":"g1n 4l5",
    "iso:country":"CA",
    "sg:city":"Sainte-Foy",
    "sg:classifiers":[
        {
            "category":"Shopping",
            "subcategory":"Computers & Home Electronics",
            "type":"Retail Goods"
        }
    ],
    "sg:phone":"+1 418 687 1171",
    "sg:postcode":"G1N 4L5",
    "sg:province":"QC",
    "sg:tags":[
        "battery",
        "equipment",
        "electronic"
    ],
    "wof:name":"Corbel Limitee",
    "wof:placetype":"venue"
},
  "geometry": {"coordinates":[-71.2724,46.797314],"type":"Point"}
}