{
  "type": "Feature",
  "properties": {
    "addr:full":"9 Valerie St Stittsville ON K2S 1L2",
    "addr:housenumber":"9",
    "addr:postcode":"k2s 1l2",
    "addr:street":"Valerie St",
    "iso:country":"CA",
    "sg:address":"9 Valerie St",
    "sg:city":"Stittsville",
    "sg:classifiers":[
        {
            "category":"Building & Trades",
            "subcategory":"Construction",
            "type":"Services"
        }
    ],
    "sg:phone":"+1 613 836 6888",
    "sg:postcode":"K2S 1L2",
    "sg:province":"ON",
    "sg:tags":[
        "contractor"
    ],
    "wof:name":"Wigney Homes",
    "wof:placetype":"venue"
},
  "geometry": {"coordinates":[-75.927177,45.278858],"type":"Point"}
}