{
  "type": "Feature",
  "properties": {
    "iso:country":"CA",
    "sg:address":"800 4E Rue",
    "sg:city":"Chibougamau",
    "sg:classifiers":[
        {
            "category":"Education",
            "subcategory":"School",
            "type":"Public Place"
        }
    ],
    "sg:phone":"+1 418 748 3228",
    "sg:postcode":"G8P 1S8",
    "sg:province":"QC",
    "wof:name":"Ecole Bon-Pasteur",
    "wof:placetype":"venue"
},
  "geometry": {"coordinates":[-74.3761520386,49.9125061035],"type":"Point"}
}