{
  "type": "Feature",
  "properties": {
    "addr:full":"230 29th St E Saskatoon SK S7L 6Y6",
    "addr:housenumber":"230",
    "addr:postcode":"s7l 6y6",
    "addr:street":"29Th St E",
    "iso:country":"CA",
    "sg:address":"230 29th St E",
    "sg:city":"Saskatoon",
    "sg:classifiers":[
        {
            "category":"Retail",
            "subcategory":"Auto Repair",
            "type":"Services"
        }
    ],
    "sg:phone":"+1 306 242 7644",
    "sg:postcode":"S7L 6Y6",
    "sg:province":"SK",
    "sg:tags":[
        "truck"
    ],
    "wof:name":"Saskatoon Diesel Svc Ltd",
    "wof:placetype":"venue"
},
  "geometry": {"coordinates":[-106.666336,52.138607],"type":"Point"}
}