{
  "type": "Feature",
  "properties": {
    "addr:full":"237 12A St NE Calgary AB T2E 4R6",
    "addr:housenumber":"12a",
    "addr:postcode":"t2e 4r6",
    "addr:street":"237;St Ne",
    "iso:country":"CA",
    "sg:address":"237 12A St NE",
    "sg:city":"Calgary",
    "sg:classifiers":[
        {
            "category":"Professional",
            "subcategory":"Research",
            "type":"Services"
        }
    ],
    "sg:phone":"+1 403 283 8833",
    "sg:postcode":"T2E 4R6",
    "sg:province":"AB",
    "sg:tags":[
        "market",
        "analysis"
    ],
    "wof:name":"Site-Check Location Evaluation",
    "wof:placetype":"venue"
},
  "geometry": {"coordinates":[-114.032661,51.054008],"type":"Point"}
}