{
  "type": "Feature",
  "properties": {
    "addr:full":"Mont-Saint-Hilaire QC J3H 3P1",
    "addr:postcode":"j3h 3p1",
    "iso:country":"CA",
    "sg:city":"Mont-Saint-Hilaire",
    "sg:classifiers":[
        {
            "category":"Education",
            "subcategory":"Special Training",
            "type":"Public Place"
        }
    ],
    "sg:phone":"+1 450 446 7999",
    "sg:postcode":"J3H 3P1",
    "sg:province":"QC",
    "sg:tags":[
        "instruction",
        "driving"
    ],
    "wof:name":"Ecole DE Conduite Technic",
    "wof:placetype":"venue"
},
  "geometry": {"coordinates":[-73.187386,45.563244],"type":"Point"}
}