{
  "type": "Feature",
  "properties": {
    "addr:full":"577 25E Av Saint-Eustache QC J7R 4K3",
    "addr:housenumber":"577",
    "addr:postcode":"j7r 4k3",
    "addr:street":"25E Av Saint-Eustache",
    "iso:country":"CA",
    "sg:address":"577 25E Av",
    "sg:city":"Saint-Eustache",
    "sg:classifiers":[
        {
            "category":"Building & Trades",
            "subcategory":"Construction",
            "type":"Services"
        }
    ],
    "sg:phone":"+1 450 491 1541",
    "sg:postcode":"J7R 4K3",
    "sg:province":"QC",
    "sg:tags":[
        "siding",
        "aluminum",
        "contractor"
    ],
    "wof:name":"Aluminium 25 Ieme Inc",
    "wof:placetype":"venue"
},
  "geometry": {"coordinates":[-73.8889007568,45.5580482483],"type":"Point"}
}