{
  "type": "Feature",
  "properties": {
    "addr:full":"159 Roxborough Dr Toronto ON M4W 1X7",
    "addr:housenumber":"159",
    "addr:postcode":"m4w 1x7",
    "addr:street":"Roxborough Dr",
    "iso:country":"CA",
    "sg:address":"159 Roxborough Dr",
    "sg:city":"Toronto",
    "sg:classifiers":[
        {
            "category":"Education",
            "subcategory":"Dance Studio",
            "type":"Public Place"
        }
    ],
    "sg:phone":"+1 416 423 2866",
    "sg:postcode":"M4W 1X7",
    "sg:province":"ON",
    "sg:tags":[
        "instruction",
        "dancing"
    ],
    "wof:name":"Metropolitan School of Arts",
    "wof:placetype":"venue"
},
  "geometry": {"coordinates":[-79.37138400000001,43.684551],"type":"Point"}
}