{
  "type": "Feature",
  "properties": {
    "addr:full":"200 Centre St Assiniboia SK S0H 0B0",
    "addr:housenumber":"200",
    "addr:postcode":"s0h 0b0",
    "addr:street":"Centre St",
    "iso:country":"CA",
    "sg:address":"200 Centre St",
    "sg:city":"Assiniboia",
    "sg:classifiers":[
        {
            "category":"Insurance",
            "subcategory":"Insurance Agent",
            "type":"Services"
        }
    ],
    "sg:phone":"+1 306 642 7100",
    "sg:postcode":"S0H 0B0",
    "sg:province":"SK",
    "wof:name":"Great-West Life Assurance CO",
    "wof:placetype":"venue"
},
  "geometry": {"coordinates":[-105.992188,49.632633],"type":"Point"}
}