{
  "type": "Feature",
  "properties": {
    "addr:full":"Macklin SK S0L 2C0",
    "addr:postcode":"s0l 2c0",
    "addr:street":"Macklin",
    "iso:country":"CA",
    "sg:city":"Macklin",
    "sg:classifiers":[
        {
            "category":"Organizations",
            "subcategory":"Religious Organization",
            "type":"Services"
        }
    ],
    "sg:phone":"+1 306 753 2395",
    "sg:postcode":"S0L 2C0",
    "sg:province":"SK",
    "sg:tags":[
        "church"
    ],
    "wof:name":"St Anthony's Convent",
    "wof:placetype":"venue"
},
  "geometry": {"coordinates":[-109.935890198,52.3328132629],"type":"Point"}
}