{
  "type": "Feature",
  "properties": {
    "addr:full":"3889 Rue Jean-Talon E Montreal QC H2A 1Y6",
    "addr:housenumber":"3889",
    "addr:postcode":"h2a 1y6",
    "addr:street":"Rue Jean-Talon E",
    "iso:country":"CA",
    "sg:address":"3889 Rue Jean-Talon E",
    "sg:city":"Montreal",
    "sg:classifiers":[
        {
            "category":"Retail",
            "subcategory":"Auto Repair",
            "type":"Services"
        }
    ],
    "sg:phone":"+1 514 728 1394",
    "sg:postcode":"H2A 1Y6",
    "sg:province":"QC",
    "sg:tags":[
        "repairing",
        "automobile"
    ],
    "wof:name":"Csa Automobiles Inc",
    "wof:placetype":"venue"
},
  "geometry": {"coordinates":[-73.5927658081,45.5652732849],"type":"Point"}
}