{
  "type": "Feature",
  "properties": {
    "addr:full":"Prince George BC V2L 2Y8",
    "addr:postcode":"v2l 2y8",
    "iso:country":"CA",
    "sg:city":"Prince George",
    "sg:classifiers":[
        {
            "category":"Retail",
            "subcategory":"Auto Repair",
            "type":"Services"
        }
    ],
    "sg:phone":"+1 250 564 5149",
    "sg:postcode":"V2L 2Y8",
    "sg:province":"BC",
    "sg:tags":[
        "repairing",
        "automobile"
    ],
    "wof:name":"Simba Motors",
    "wof:placetype":"venue"
},
  "geometry": {"coordinates":[-122.753441,53.921307],"type":"Point"}
}