{
  "type": "Feature",
  "properties": {
    "iso:country":"CA",
    "sg:city":"Hay River",
    "sg:classifiers":[
        {
            "category":"Shopping",
            "subcategory":"Department Store",
            "type":"Retail Goods"
        }
    ],
    "sg:phone":"+1 867 874 6892",
    "sg:postcode":"X0E 1G1",
    "sg:province":"NT",
    "wof:name":"Fields Stores",
    "wof:placetype":"venue"
},
  "geometry": {"coordinates":[-115.79094696,60.8071136475],"type":"Point"}
}