{
  "type": "Feature",
  "properties": {
    "addr:full":"369 Logan Ave Winnipeg MB R3A 0P8",
    "addr:housenumber":"369",
    "addr:postcode":"r3a 0p8",
    "addr:street":"Logan Ave",
    "iso:country":"CA",
    "sg:address":"369 Logan Ave",
    "sg:city":"Winnipeg",
    "sg:classifiers":[
        {
            "category":"Home & Garden",
            "subcategory":"Building Materials",
            "type":"Retail Goods"
        }
    ],
    "sg:phone":"+1 204 947 0986",
    "sg:postcode":"R3A 0P8",
    "sg:province":"MB",
    "sg:tags":[
        "plumbing",
        "fixture",
        "bathroom",
        "remodeling"
    ],
    "wof:name":"Dynasty Bath & Kitchen Ctr",
    "wof:placetype":"venue"
},
  "geometry": {"coordinates":[-97.1409912109,49.9044189453],"type":"Point"}
}