{
  "type": "Feature",
  "properties": {
    "addr:full":"2596 Edinburgh Pl Ottawa ON K1B 5M1",
    "addr:housenumber":"2596",
    "addr:postcode":"k1b 5m1",
    "addr:street":"Edinburgh Pl",
    "iso:country":"CA",
    "sg:address":"2596 Edinburgh Pl",
    "sg:city":"Ottawa",
    "sg:classifiers":[
        {
            "category":"Manufacturing",
            "subcategory":"Printing",
            "type":"Manufacturing & Wholesale Goods"
        }
    ],
    "sg:phone":"+1 613 745 3224",
    "sg:postcode":"K1B 5M1",
    "sg:province":"ON",
    "sg:tags":[
        "printer"
    ],
    "wof:name":"Mastergraph Printing",
    "wof:placetype":"venue"
},
  "geometry": {"coordinates":[-75.6133346558,45.4039001465],"type":"Point"}
}