{
  "type": "Feature",
  "properties": {
    "addr:full":"Cache Creek BC V0K 1H0",
    "addr:postcode":"v0k 1h0",
    "iso:country":"CA",
    "sg:city":"Cache Creek",
    "sg:classifiers":[
        {
            "category":"Personal",
            "subcategory":"Beauty Salon",
            "type":"Services"
        }
    ],
    "sg:phone":"+1 250 457 6778",
    "sg:postcode":"V0K 1H0",
    "sg:province":"BC",
    "wof:name":"Billie's Hair Salon",
    "wof:placetype":"venue"
},
  "geometry": {"coordinates":[-121.316856,50.789642],"type":"Point"}
}