{
  "type": "Feature",
  "properties": {
    "addr:full":"315 10 Ave SE Calgary AB T2G 0W2",
    "addr:postcode":"t2g 0w2",
    "addr:street":"315 10 Ave Se",
    "iso:country":"CA",
    "sg:address":"315 10 Ave SE",
    "sg:city":"Calgary",
    "sg:classifiers":[
        {
            "category":"Education",
            "subcategory":"School",
            "type":"Public Place"
        }
    ],
    "sg:phone":"+1 403 268 3265",
    "sg:postcode":"T2G 0W2",
    "sg:province":"AB",
    "wof:name":"Discovering Choices",
    "wof:placetype":"venue"
},
  "geometry": {"coordinates":[-114.05775451700001,51.0430183411],"type":"Point"}
}