{
  "type": "Feature",
  "properties": {
    "addr:full":"5008 50 St Ponoka AB T4J 1R7",
    "addr:housenumber":"5008",
    "addr:postcode":"t4j 1r7",
    "addr:street":"50 St",
    "iso:country":"CA",
    "sg:address":"5008 50 St",
    "sg:city":"Ponoka",
    "sg:classifiers":[
        {
            "category":"Shopping",
            "subcategory":"Discount & Variety Stores",
            "type":"Retail Goods"
        }
    ],
    "sg:phone":"+1 403 783 2100",
    "sg:postcode":"T4J 1R7",
    "sg:province":"AB",
    "wof:name":"Great Canadian Dollar Store",
    "wof:placetype":"venue"
},
  "geometry": {"coordinates":[-113.576187,52.676231],"type":"Point"}
}