{
  "type": "Feature",
  "properties": {
    "addr:full":"101 Enderby Rd Toronto ON M4E 2S6",
    "addr:housenumber":"101",
    "addr:postcode":"m4e 2s6",
    "addr:street":"Enderby Rd",
    "iso:country":"CA",
    "sg:address":"101 Enderby Rd",
    "sg:city":"Toronto",
    "sg:classifiers":[
        {
            "category":"Real Estate",
            "subcategory":"Real Estate Operator",
            "type":"Services"
        }
    ],
    "sg:phone":"+1 416 699 9627",
    "sg:postcode":"M4E 2S6",
    "sg:province":"ON",
    "sg:tags":[
        "boarding",
        "house"
    ],
    "wof:name":"Enderby Manor",
    "wof:placetype":"venue"
},
  "geometry": {"coordinates":[-79.30159,43.684326],"type":"Point"}
}