{
  "type": "Feature",
  "properties": {
    "addr:full":"Fauquier ON P0L 1G0",
    "addr:postcode":"p0l 1g0",
    "iso:country":"CA",
    "sg:city":"Fauquier",
    "sg:classifiers":[
        {
            "category":"Health Services",
            "subcategory":"Doctor",
            "type":"Services"
        }
    ],
    "sg:phone":"+1 705 339 6341",
    "sg:postcode":"P0L 1G0",
    "sg:province":"ON",
    "sg:tags":[
        "clinic"
    ],
    "wof:name":"Corporation Du Canton Fauquier",
    "wof:placetype":"venue"
},
  "geometry": {"coordinates":[-82.03961200000001,49.312866],"type":"Point"}
}