{
  "type": "Feature",
  "properties": {
    "addr:full":"2209 Av Royale Beauport QC G1C 1P3",
    "addr:housenumber":"2209",
    "addr:postcode":"qc g1c 1p3",
    "addr:street":"Av Royale",
    "iso:country":"CA",
    "sg:address":"2209 Av Royale",
    "sg:city":"Beauport",
    "sg:classifiers":[
        {
            "category":"Building & Trades",
            "subcategory":"Cleaning & Sanitation",
            "type":"Services"
        }
    ],
    "sg:phone":"+1 418 660 6888",
    "sg:postcode":"G1C 1P3",
    "sg:province":"QC",
    "sg:tags":[
        "venetian",
        "blind"
    ],
    "wof:name":"Distribution Yvette Laroche",
    "wof:placetype":"venue"
},
  "geometry": {"coordinates":[-71.16143798829999,46.8823356628],"type":"Point"}
}