{
  "type": "Feature",
  "properties": {
    "addr:full":"440 Av Principale Degelis QC G5T 1M8",
    "addr:housenumber":"440",
    "addr:postcode":"g5t 1m8",
    "addr:street":"Av Principale",
    "iso:country":"CA",
    "sg:address":"440 Av Principale",
    "sg:city":"Degelis",
    "sg:classifiers":[
        {
            "category":"Personal",
            "subcategory":"Beauty Salon",
            "type":"Services"
        }
    ],
    "sg:phone":"+1 418 853 3618",
    "sg:postcode":"G5T 1M8",
    "sg:province":"QC",
    "wof:name":"Salon D'Esthetique Au Teint",
    "wof:placetype":"venue"
},
  "geometry": {"coordinates":[-68.642471,47.546844],"type":"Point"}
}