{
  "type": "Feature",
  "properties": {
    "addr:full":"19810 57A Ave Langley BC V3A 6G6",
    "addr:housenumber":"19810",
    "addr:postcode":"v3a 6g6",
    "addr:street":"57A Ave",
    "iso:country":"CA",
    "sg:address":"19810 57A Ave",
    "sg:city":"Langley",
    "sg:classifiers":[
        {
            "category":"Manufacturing",
            "subcategory":"Tools & Machinery",
            "type":"Manufacturing & Wholesale Goods"
        }
    ],
    "sg:phone":"+1 604 530 9646",
    "sg:postcode":"V3A 6G6",
    "sg:province":"BC",
    "sg:tags":[
        "machine",
        "shop"
    ],
    "wof:name":"United Machining Inc",
    "wof:placetype":"venue"
},
  "geometry": {"coordinates":[-122.65657043500001,49.1041221619],"type":"Point"}
}