{
  "type": "Feature",
  "properties": {
    "addr:full":"619 Central Ave Kingston NS B0P 1R0",
    "addr:housenumber":"619",
    "addr:postcode":"b0p 1r0",
    "addr:street":"Central Ave",
    "iso:country":"CA",
    "sg:address":"619 Central Ave",
    "sg:city":"Kingston",
    "sg:classifiers":[
        {
            "category":"Restaurant",
            "type":"Food & Drink"
        }
    ],
    "sg:phone":"+1 902 765 0535",
    "sg:postcode":"B0P 1R0",
    "sg:province":"NS",
    "wof:name":"Jessica's Cafe",
    "wof:placetype":"venue"
},
  "geometry": {"coordinates":[-64.9493560791,44.9874382019],"type":"Point"}
}