{
  "type": "Feature",
  "properties": {
    "addr:full":"175 Yonge St Midland ON L4R 2A7",
    "addr:housenumber":"175",
    "addr:postcode":"l4r 2a7",
    "addr:street":"Yonge St",
    "iso:country":"CA",
    "sg:address":"175 Yonge St",
    "sg:city":"Midland",
    "sg:classifiers":[
        {
            "category":"Organizations",
            "subcategory":"Professional Association",
            "type":"Services"
        }
    ],
    "sg:phone":"+1 705 526 5589",
    "sg:postcode":"L4R 2A7",
    "sg:province":"ON",
    "sg:tags":[
        "native"
    ],
    "wof:name":"Georgian Bay Native Friendship",
    "wof:placetype":"venue"
},
  "geometry": {"coordinates":[-79.86943817140001,44.752368927],"type":"Point"}
}