{
  "type": "Feature",
  "properties": {
    "addr:full":"Belleville ON K8P 5A5",
    "addr:postcode":"k8p 5a5",
    "iso:country":"CA",
    "sg:city":"Belleville",
    "sg:classifiers":[
        {
            "category":"Health Services",
            "subcategory":"Clinic",
            "type":"Services"
        }
    ],
    "sg:phone":"+1 613 962 9121",
    "sg:postcode":"K8P 5A5",
    "sg:province":"ON",
    "sg:tags":[
        "home"
    ],
    "wof:name":"Canadian Red Cross Society",
    "wof:placetype":"venue"
},
  "geometry": {"coordinates":[-77.395859,44.187622],"type":"Point"}
}