{
  "type": "Feature",
  "properties": {
    "addr:full":"174 Spadina Rd Toronto ON M5R 2T8",
    "addr:housenumber":"174",
    "addr:postcode":"m5r 2t8",
    "addr:street":"Spadina Rd",
    "iso:country":"CA",
    "sg:address":"174 Spadina Rd",
    "sg:city":"Toronto",
    "sg:classifiers":[
        {
            "category":"Arts & Performance",
            "subcategory":"Theater",
            "type":"Entertainment"
        }
    ],
    "sg:phone":"+1 416 504 0019",
    "sg:postcode":"M5R 2T8",
    "sg:province":"ON",
    "wof:name":"Theatre Columbus",
    "wof:placetype":"venue"
},
  "geometry": {"coordinates":[-79.40703600000001,43.674183],"type":"Point"}
}