{
  "type": "Feature",
  "properties": {
    "addr:full":"5 Garfield St Charlottetown PE C1A 6A4",
    "addr:housenumber":"5",
    "addr:postcode":"c1a 6a4",
    "addr:street":"Garfield St",
    "iso:country":"CA",
    "sg:address":"5 Garfield St",
    "sg:city":"Charlottetown",
    "sg:classifiers":[
        {
            "category":"Manufacturing",
            "subcategory":"Metals",
            "type":"Manufacturing & Wholesale Goods"
        }
    ],
    "sg:phone":"+1 902 566 4115",
    "sg:postcode":"C1A 6A4",
    "sg:province":"PE",
    "sg:tags":[
        "fastener",
        "bolt"
    ],
    "wof:name":"Atlantic Warehousing Ltd",
    "wof:placetype":"venue"
},
  "geometry": {"coordinates":[-63.111415863,46.2520980835],"type":"Point"}
}