{
  "type": "Feature",
  "properties": {
    "addr:full":"Toronto ON M5T 3K5",
    "addr:postcode":"m5t 3k5",
    "iso:country":"CA",
    "sg:city":"Toronto",
    "sg:classifiers":[
        {
            "category":"Restaurant",
            "type":"Food & Drink"
        }
    ],
    "sg:phone":"+1 416 598 1650",
    "sg:postcode":"M5T 3K5",
    "sg:province":"ON",
    "wof:name":"Gypsy Hungarian Restaurant",
    "wof:placetype":"venue"
},
  "geometry": {"coordinates":[-79.391029,43.653812],"type":"Point"}
}