{
  "type": "Feature",
  "properties": {
    "addr:full":"25 Advance Blvd Brampton ON L6T 4H8",
    "addr:housenumber":"25",
    "addr:postcode":"l6t 4h8",
    "addr:street":"Advance Blvd",
    "iso:country":"CA",
    "sg:address":"25 Advance Blvd",
    "sg:city":"Brampton",
    "sg:classifiers":[
        {
            "category":"Freight",
            "type":"Transportation"
        }
    ],
    "sg:phone":"+1 905 791 3077",
    "sg:postcode":"L6T 4H8",
    "sg:province":"ON",
    "sg:tags":[
        "box",
        "commercial"
    ],
    "wof:name":"Public Storage",
    "wof:placetype":"venue"
},
  "geometry": {"coordinates":[-79.69607499999999,43.697731],"type":"Point"}
}