{
  "type": "Feature",
  "properties": {
    "iso:country":"CA",
    "sg:address":"34 Martin Ross Ave",
    "sg:city":"North York",
    "sg:classifiers":[
        {
            "category":"Building & Trades",
            "subcategory":"Construction",
            "type":"Services"
        }
    ],
    "sg:phone":"+1 416 246 2730",
    "sg:postcode":"M3J 2K8",
    "sg:province":"ON",
    "sg:tags":[
        "skylight"
    ],
    "wof:name":"Aluplex Skylights Inc",
    "wof:placetype":"venue"
},
  "geometry": {"coordinates":[-79.47179412840001,43.7746734619],"type":"Point"}
}