{
  "type": "Feature",
  "properties": {
    "addr:full":"Barrie ON L4N 5R7",
    "addr:postcode":"l4n 5r7",
    "iso:country":"CA",
    "sg:city":"Barrie",
    "sg:classifiers":[
        {
            "category":"Manufacturing",
            "subcategory":"Jewelry",
            "type":"Manufacturing & Wholesale Goods"
        }
    ],
    "sg:phone":"+1 705 726 0893",
    "sg:postcode":"L4N 5R7",
    "sg:province":"ON",
    "sg:tags":[
        "craftsman"
    ],
    "wof:name":"Hake Jewellers",
    "wof:placetype":"venue"
},
  "geometry": {"coordinates":[-79.711967,44.382446],"type":"Point"}
}