{
  "type": "Feature",
  "properties": {
    "addr:full":"491 Rue Scott Roberval QC G8H 2E6",
    "addr:housenumber":"491",
    "addr:postcode":"g8h 2e6",
    "addr:street":"Rue Scott",
    "iso:country":"CA",
    "sg:address":"491 Rue Scott",
    "sg:city":"Roberval",
    "sg:classifiers":[
        {
            "category":"Food & Beverages",
            "subcategory":"Groceries & Convenience Stores",
            "type":"Retail Goods"
        }
    ],
    "sg:phone":"+1 418 275 2142",
    "sg:postcode":"G8H 2E6",
    "sg:province":"QC",
    "wof:name":"Depanneur Chez Claude",
    "wof:placetype":"venue"
},
  "geometry": {"coordinates":[-72.222672,48.50909],"type":"Point"}
}