{
  "type": "Feature",
  "properties": {
    "addr:full":"10158 97 Ave NW Edmonton AB T5K 2T5",
    "addr:housenumber":"10158",
    "addr:postcode":"t5k 2t5",
    "addr:street":"97 Ave Nw",
    "iso:country":"CA",
    "sg:address":"10158 97 Ave NW",
    "sg:city":"Edmonton",
    "sg:classifiers":[
        {
            "category":"Building & Trades",
            "subcategory":"Construction",
            "type":"Services"
        }
    ],
    "sg:phone":"+1 780 423 1683",
    "sg:postcode":"T5K 2T5",
    "sg:province":"AB",
    "sg:tags":[
        "general",
        "contractor"
    ],
    "wof:name":"Synergy Projects Ltd",
    "wof:placetype":"venue"
},
  "geometry": {"coordinates":[-113.49479700000001,53.534298],"type":"Point"}
}