{
  "type": "Feature",
  "properties": {
    "addr:full":"504 Av Saint-Charles Vaudreuil-Dorion QC J7V 2N7",
    "addr:postcode":"j7v 2n7",
    "addr:street":"504 Av Saint-Charles",
    "iso:country":"CA",
    "sg:address":"504 Av Saint-Charles",
    "sg:city":"Vaudreuil-Dorion",
    "sg:classifiers":[
        {
            "category":"Retail",
            "subcategory":"Auto Repair",
            "type":"Services"
        }
    ],
    "sg:phone":"+1 450 455 4221",
    "sg:postcode":"J7V 2N7",
    "sg:province":"QC",
    "sg:tags":[
        "repairing",
        "automobile"
    ],
    "wof:name":"Station Jean Pierre",
    "wof:placetype":"venue"
},
  "geometry": {"coordinates":[-74.031998,45.404484],"type":"Point"}
}