{
  "type": "Feature",
  "properties": {
    "iso:country":"CA",
    "sg:address":"324 Governors Rd E",
    "sg:city":"Paris",
    "sg:classifiers":[
        {
            "category":"Building & Trades",
            "subcategory":"Construction",
            "type":"Services"
        }
    ],
    "sg:phone":"+1 519 753 0324",
    "sg:postcode":"N3L 3E1",
    "sg:province":"ON",
    "sg:tags":[
        "control",
        "erosion"
    ],
    "wof:name":"Filtrexx Canada Inc",
    "wof:placetype":"venue"
},
  "geometry": {"coordinates":[-80.38164500000001,43.190681],"type":"Point"}
}