{
  "type": "Feature",
  "properties": {
    "addr:full":"12409 107 Ave NW Edmonton AB T5M 1Z2",
    "addr:housenumber":"12409",
    "addr:postcode":"t5m 1z2",
    "addr:street":"107 Ave Nw",
    "iso:country":"CA",
    "sg:address":"12409 107 Ave NW",
    "sg:city":"Edmonton",
    "sg:classifiers":[
        {
            "category":"Food & Beverages",
            "subcategory":"Groceries & Convenience Stores",
            "type":"Retail Goods"
        }
    ],
    "sg:phone":"+1 780 482 3813",
    "sg:postcode":"T5M 1Z2",
    "sg:province":"AB",
    "sg:tags":[
        "grocer"
    ],
    "wof:name":"Maple Grocery",
    "wof:placetype":"venue"
},
  "geometry": {"coordinates":[-113.536178589,53.550693512],"type":"Point"}
}