{
  "type": "Feature",
  "properties": {
    "addr:full":"1028 Aberdeen Bala ON P0C 1A0",
    "addr:housenumber":"1028",
    "addr:postcode":"p0c 1a0",
    "addr:street":"Aberdeen Bala",
    "iso:country":"CA",
    "sg:address":"1028 Aberdeen",
    "sg:city":"Bala",
    "sg:classifiers":[
        {
            "category":"Building & Trades",
            "subcategory":"Landscaping Services",
            "type":"Services"
        }
    ],
    "sg:phone":"+1 705 762 1554",
    "sg:postcode":"P0C 1A0",
    "sg:province":"ON",
    "sg:tags":[
        "tree"
    ],
    "wof:name":"Pineneedle Tree Svc",
    "wof:placetype":"venue"
},
  "geometry": {"coordinates":[-79.61615,45.018822],"type":"Point"}
}