{
  "type": "Feature",
  "properties": {
    "addr:full":"92 Metro Rd S Keswick ON L4P 1W2",
    "addr:housenumber":"92",
    "addr:postcode":"l4p 1w2",
    "addr:street":"Metro Rd S",
    "iso:country":"CA",
    "sg:address":"92 Metro Rd S",
    "sg:city":"Keswick",
    "sg:classifiers":[
        {
            "category":"Building & Trades",
            "subcategory":"Cleaning & Sanitation",
            "type":"Services"
        }
    ],
    "sg:phone":"+1 905 989 1103",
    "sg:postcode":"L4P 1W2",
    "sg:province":"ON",
    "sg:tags":[
        "window"
    ],
    "wof:name":"Dorset Park Window Cleaning",
    "wof:placetype":"venue"
},
  "geometry": {"coordinates":[-79.470924,44.237839],"type":"Point"}
}