{
  "type": "Feature",
  "properties": {
    "addr:full":"196 Warren Ave E Penticton BC V2A 3L8",
    "addr:housenumber":"196",
    "addr:postcode":"v2a 3l8",
    "addr:street":"Warren Ave E",
    "iso:country":"CA",
    "sg:address":"196 Warren Ave E",
    "sg:city":"Penticton",
    "sg:classifiers":[
        {
            "category":"Retail",
            "subcategory":"Veterinary Services",
            "type":"Services"
        }
    ],
    "sg:phone":"+1 250 492 8126",
    "sg:postcode":"V2A 3L8",
    "sg:province":"BC",
    "sg:tags":[
        "veterinarian"
    ],
    "wof:name":"Animal Medical Clinic",
    "wof:placetype":"venue"
},
  "geometry": {"coordinates":[-119.579399,49.475338],"type":"Point"}
}