{
  "type": "Feature",
  "properties": {
    "iso:country":"CA",
    "sg:address":"2930 Rue Desmarteau",
    "sg:city":"Montreal",
    "sg:classifiers":[
        {
            "category":"Manufacturing",
            "subcategory":"Printing",
            "type":"Manufacturing & Wholesale Goods"
        }
    ],
    "sg:phone":"+1 514 351 5224",
    "sg:postcode":"H1L 4N7",
    "sg:province":"QC",
    "sg:tags":[
        "newspaper"
    ],
    "wof:name":"Quebec Quilles",
    "wof:placetype":"venue"
},
  "geometry": {"coordinates":[-73.5230560303,45.6064414978],"type":"Point"}
}