{
  "type": "Feature",
  "properties": {
    "addr:full":"50 Millwick Dr North York ON M9L 1Y3",
    "addr:housenumber":"50",
    "addr:postcode":"m9l 1y3",
    "addr:street":"Millwick Dr",
    "iso:country":"CA",
    "sg:address":"50 Millwick Dr",
    "sg:city":"North York",
    "sg:classifiers":[
        {
            "category":"Utilities",
            "subcategory":"Refuse",
            "type":"Services"
        }
    ],
    "sg:phone":"+1 416 743 7379",
    "sg:postcode":"M9L 1Y3",
    "sg:province":"ON",
    "sg:tags":[
        "garbage",
        "collection"
    ],
    "wof:name":"Wellington Waste Disposal",
    "wof:placetype":"venue"
},
  "geometry": {"coordinates":[-79.561050415,43.7588500977],"type":"Point"}
}