{
  "type": "Feature",
  "properties": {
    "addr:full":"East Margaree Rd Margaree Harbour NS B0E 2B0",
    "addr:postcode":"b0e 2b0",
    "addr:street":"East Margaree Rd",
    "iso:country":"CA",
    "sg:address":"East Margaree Rd",
    "sg:city":"Margaree Harbour",
    "sg:classifiers":[
        {
            "category":"Organizations",
            "subcategory":"Professional Association",
            "type":"Services"
        }
    ],
    "sg:phone":"+1 902 235 2532",
    "sg:postcode":"B0E 2B0",
    "sg:province":"NS",
    "sg:tags":[
        "club"
    ],
    "wof:name":"Margaree Kinsmen",
    "wof:placetype":"venue"
},
  "geometry": {"coordinates":[-61.110809,46.435024],"type":"Point"}
}