{
  "type": "Feature",
  "properties": {
    "addr:full":"215 Carlton St Toronto ON M5A 2K9",
    "addr:housenumber":"215",
    "addr:postcode":"m5a 2k9",
    "addr:street":"Carlton St",
    "iso:country":"CA",
    "sg:address":"215 Carlton St",
    "sg:city":"Toronto",
    "sg:classifiers":[
        {
            "category":"Professional",
            "subcategory":"Management & Consulting",
            "type":"Services"
        }
    ],
    "sg:phone":"+1 416 924 9948",
    "sg:postcode":"M5A 2K9",
    "sg:province":"ON",
    "sg:tags":[
        "promotion",
        "sales"
    ],
    "wof:name":"Hausner Consultants Inc",
    "wof:placetype":"venue"
},
  "geometry": {"coordinates":[-79.369484,43.663807],"type":"Point"}
}