{
  "type": "Feature",
  "properties": {
    "addr:full":"4599 Tillicum St Burnaby BC V5J 3J9",
    "addr:housenumber":"4599",
    "addr:postcode":"v5j 3j9",
    "addr:street":"Tillicum St",
    "iso:country":"CA",
    "sg:address":"4599 Tillicum St",
    "sg:city":"Burnaby",
    "sg:classifiers":[
        {
            "category":"Professional",
            "subcategory":"Engineering",
            "type":"Services"
        }
    ],
    "sg:phone":"+1 604 659 3335",
    "sg:postcode":"V5J 3J9",
    "sg:province":"BC",
    "sg:tags":[
        "engineer"
    ],
    "wof:name":"Veco Canada Ltd",
    "wof:placetype":"venue"
},
  "geometry": {"coordinates":[-122.99047899999999,49.189045],"type":"Point"}
}