{
  "type": "Feature",
  "properties": {
    "addr:full":"4172 Petrolia Line Petrolia ON N0N 1R0",
    "addr:housenumber":"4172",
    "addr:postcode":"n0n 1r0",
    "addr:street":"Petrolia Line",
    "iso:country":"CA",
    "sg:address":"4172 Petrolia Line",
    "sg:city":"Petrolia",
    "sg:classifiers":[
        {
            "category":"Building & Trades",
            "subcategory":"Plumbing",
            "type":"Services"
        }
    ],
    "sg:phone":"+1 519 882 2544",
    "sg:postcode":"N0N 1R0",
    "sg:province":"ON",
    "sg:tags":[
        "contractor"
    ],
    "wof:name":"B & R Plumbing",
    "wof:placetype":"venue"
},
  "geometry": {"coordinates":[-82.14804077150001,42.8820762634],"type":"Point"}
}