{
  "type": "Feature",
  "properties": {
    "addr:full":"562 3rd Ave Fernie BC V0B 1M0",
    "addr:housenumber":"562",
    "addr:postcode":"bc v0b 1m0",
    "addr:street":"3Rd Ave",
    "iso:country":"CA",
    "sg:address":"562 3rd Ave",
    "sg:city":"Fernie",
    "sg:classifiers":[
        {
            "category":"Social Services",
            "type":"Services"
        }
    ],
    "sg:phone":"+1 250 423 3312",
    "sg:postcode":"V0B 1M0",
    "sg:province":"BC",
    "sg:tags":[
        "senior",
        "citizen"
    ],
    "wof:name":"Senior Citizens Drop in Ctr",
    "wof:placetype":"venue"
},
  "geometry": {"coordinates":[-115.062042236,49.5039176941],"type":"Point"}
}