{
  "type": "Feature",
  "properties": {
    "addr:full":"1403 Ch Des Pionniers O Cap-Saint-Ignace QC G0R 1H0",
    "addr:housenumber":"1403",
    "addr:postcode":"g0r 1h0",
    "addr:street":"Ch Des Pionniers O",
    "iso:country":"CA",
    "sg:address":"1403 Ch Des Pionniers O",
    "sg:city":"Cap-Saint-Ignace",
    "sg:classifiers":[
        {
            "category":"Manufacturing",
            "subcategory":"Printing",
            "type":"Manufacturing & Wholesale Goods"
        }
    ],
    "sg:phone":"+1 418 248 6965",
    "sg:postcode":"G0R 1H0",
    "sg:province":"QC",
    "sg:tags":[
        "printer"
    ],
    "wof:name":"Impression Rive-Sud Inc",
    "wof:placetype":"venue"
},
  "geometry": {"coordinates":[-70.432365,47.07856],"type":"Point"}
}