{
  "type": "Feature",
  "properties": {
    "addr:full":"2111 110 St NW Edmonton AB T6J 6P6",
    "addr:housenumber":"2111",
    "addr:postcode":"t6j 6p6",
    "addr:street":"110 St Nw",
    "iso:country":"CA",
    "sg:address":"2111 110 St NW",
    "sg:city":"Edmonton",
    "sg:classifiers":[
        {
            "category":"Retail",
            "subcategory":"Veterinary Services",
            "type":"Services"
        }
    ],
    "sg:phone":"+1 780 436 7688",
    "sg:postcode":"T6J 6P6",
    "sg:province":"AB",
    "sg:tags":[
        "veterinarian"
    ],
    "wof:name":"Heritage Animal Clinic",
    "wof:placetype":"venue"
},
  "geometry": {"coordinates":[-113.512901306,53.4528617859],"type":"Point"}
}