{
  "type": "Feature",
  "properties": {
    "addr:full":"76 Smoketree Cres Stittsville ON K2S 2B9",
    "addr:housenumber":"76",
    "addr:postcode":"k2s 2b9",
    "addr:street":"Smoketree Cres",
    "iso:country":"CA",
    "sg:address":"76 Smoketree Cres",
    "sg:city":"Stittsville",
    "sg:classifiers":[
        {
            "category":"Building & Trades",
            "subcategory":"Construction",
            "type":"Services"
        }
    ],
    "sg:phone":"+1 613 831 3711",
    "sg:postcode":"K2S 2B9",
    "sg:province":"ON",
    "sg:tags":[
        "contractor"
    ],
    "wof:name":"Holitzner Homes Ltd",
    "wof:placetype":"venue"
},
  "geometry": {"coordinates":[-75.944641,45.263157],"type":"Point"}
}