{
  "type": "Feature",
  "properties": {
    "addr:full":"7200 Boul Ste Anne DE Bellevue Montreal QC H4B 1T4",
    "addr:housenumber":"7200",
    "addr:postcode":"h4b 1t4",
    "addr:street":"Boul Ste;De Bellevue",
    "iso:country":"CA",
    "sg:address":"7200 Boul Ste Anne DE Bellevue",
    "sg:city":"Montreal",
    "sg:classifiers":[
        {
            "category":"Autos & Motor Vehicles",
            "subcategory":"Auto Supplies",
            "type":"Retail Goods"
        }
    ],
    "sg:phone":"+1 514 483 0810",
    "sg:postcode":"H4B 1T4",
    "sg:province":"QC",
    "sg:tags":[
        "repairing",
        "automobile",
        "parts"
    ],
    "wof:name":"Canadian Tire",
    "wof:placetype":"venue"
},
  "geometry": {"coordinates":[-73.6315155029,45.455291748],"type":"Point"}
}