{
  "type": "Feature",
  "properties": {
    "iso:country":"CA",
    "sg:address":"46 Russet Crt",
    "sg:city":"Stoney Creek",
    "sg:classifiers":[
        {
            "category":"Building & Trades",
            "subcategory":"Construction",
            "type":"Services"
        }
    ],
    "sg:phone":"+1 905 662 9524",
    "sg:postcode":"L8E 3Z5",
    "sg:province":"ON",
    "sg:tags":[
        "painter"
    ],
    "wof:name":"D C Painting & Decorating",
    "wof:placetype":"venue"
},
  "geometry": {"coordinates":[-79.7176361084,43.2201499939],"type":"Point"}
}