{
  "type": "Feature",
  "properties": {
    "addr:full":"673 Warren Rd London ON N6H 2V6",
    "addr:housenumber":"673",
    "addr:postcode":"n6h 2v6",
    "addr:street":"Warren Rd",
    "iso:country":"CA",
    "sg:address":"673 Warren Rd",
    "sg:city":"London",
    "sg:phone":"+1 519 471 8956",
    "sg:postcode":"N6H 2V6",
    "sg:province":"ON",
    "sg:tags":[
        "scale"
    ],
    "wof:name":"Riddell Scales",
    "wof:placetype":"venue"
},
  "geometry": {"coordinates":[-81.29504394529999,42.9735527039],"type":"Point"}
}