{
  "type": "Feature",
  "properties": {
    "addr:full":"1675 Av Fournier Plessisville QC G6L 2G5",
    "addr:housenumber":"1675",
    "addr:postcode":"g6l 2g5",
    "addr:street":"Av Fournier",
    "iso:country":"CA",
    "sg:address":"1675 Av Fournier",
    "sg:city":"Plessisville",
    "sg:classifiers":[
        {
            "category":"Real Estate",
            "subcategory":"Real Estate Agent",
            "type":"Services"
        }
    ],
    "sg:phone":"+1 819 362 8795",
    "sg:postcode":"G6L 2G5",
    "sg:province":"QC",
    "sg:tags":[
        "authorities",
        "housing"
    ],
    "wof:name":"Office Municipal D'Habitation",
    "wof:placetype":"venue"
},
  "geometry": {"coordinates":[-71.777084,46.218773],"type":"Point"}
}