{
  "type": "Feature",
  "properties": {
    "addr:full":"4914 Victoria Ave Niagara Falls ON L2E 4C6",
    "addr:housenumber":"4914",
    "addr:postcode":"l2e 4c6",
    "addr:street":"Victoria Ave",
    "iso:country":"CA",
    "sg:address":"4914 Victoria Ave",
    "sg:city":"Niagara Falls",
    "sg:classifiers":[
        {
            "category":"Restaurant",
            "type":"Food & Drink"
        }
    ],
    "sg:phone":"+1 905 374 2222",
    "sg:postcode":"L2E 4C6",
    "sg:province":"ON",
    "sg:tags":[
        "pizza"
    ],
    "wof:name":"Pete's Pizza",
    "wof:placetype":"venue"
},
  "geometry": {"coordinates":[-79.072906,43.102985],"type":"Point"}
}