{
  "type": "Feature",
  "properties": {
    "addr:full":"Victoria BC V8W 3C8",
    "addr:postcode":"v8w 3c8",
    "iso:country":"CA",
    "sg:city":"Victoria",
    "sg:classifiers":[
        {
            "category":"Government",
            "subcategory":"Office",
            "type":"Public Place"
        }
    ],
    "sg:phone":"+1 250 952 1502",
    "sg:postcode":"V8W 3C8",
    "sg:province":"BC",
    "wof:name":"BC Board of Hearing Aid",
    "wof:placetype":"venue"
},
  "geometry": {"coordinates":[-123.361504,48.427933],"type":"Point"}
}