{
  "type": "Feature",
  "properties": {
    "addr:full":"1782 Midland Ave Scarborough ON M1P 3C2",
    "addr:housenumber":"1782",
    "addr:postcode":"m1p 3c2",
    "addr:street":"Midland Ave",
    "iso:country":"CA",
    "sg:address":"1782 Midland Ave",
    "sg:city":"Scarborough",
    "sg:classifiers":[
        {
            "category":"Shopping",
            "subcategory":"Gifts & Souvenirs",
            "type":"Retail Goods"
        }
    ],
    "sg:phone":"+1 416 288 1977",
    "sg:postcode":"M1P 3C2",
    "sg:province":"ON",
    "sg:tags":[
        "party",
        "supply"
    ],
    "wof:name":"Gns Party Rentals",
    "wof:placetype":"venue"
},
  "geometry": {"coordinates":[-79.269081,43.761658],"type":"Point"}
}