{
  "type": "Feature",
  "properties": {
    "iso:country":"CA",
    "sg:address":"216 Merritt St",
    "sg:city":"St Catharines",
    "sg:classifiers":[
        {
            "category":"Wholesale",
            "subcategory":"Electrical",
            "type":"Manufacturing & Wholesale Goods"
        }
    ],
    "sg:phone":"+1 905 680 8255",
    "sg:postcode":"L2T 1J6",
    "sg:province":"ON",
    "sg:tags":[
        "communication",
        "radio",
        "telephone",
        "cellular"
    ],
    "wof:name":"Talk Wireless Inc",
    "wof:placetype":"venue"
},
  "geometry": {"coordinates":[-79.20983886720001,43.135597229],"type":"Point"}
}