{
  "type": "Feature",
  "properties": {
    "addr:full":"942 Hyde St Pincher Creek AB T0K 1W0",
    "addr:housenumber":"942",
    "addr:postcode":"t0k 1w0",
    "addr:street":"Hyde St",
    "iso:country":"CA",
    "sg:address":"942 Hyde St",
    "sg:city":"Pincher Creek",
    "sg:classifiers":[
        {
            "category":"Sports & Exercise",
            "subcategory":"Gym",
            "type":"Entertainment"
        }
    ],
    "sg:phone":"+1 403 627 4471",
    "sg:postcode":"T0K 1W0",
    "sg:province":"AB",
    "sg:tags":[
        "club",
        "health",
        "studio",
        "gymnasium"
    ],
    "wof:name":"Joe's Weight Training-Fitness",
    "wof:placetype":"venue"
},
  "geometry": {"coordinates":[-113.938903809,49.4824829102],"type":"Point"}
}