{
  "type": "Feature",
  "properties": {
    "addr:full":"268 Garyray Dr North York ON M9L 1P1",
    "addr:housenumber":"268",
    "addr:postcode":"m9l 1p1",
    "addr:street":"Garyray Dr",
    "iso:country":"CA",
    "sg:address":"268 Garyray Dr",
    "sg:city":"North York",
    "sg:classifiers":[
        {
            "category":"Retail",
            "subcategory":"Repair Shop",
            "type":"Services"
        }
    ],
    "sg:phone":"+1 416 746 7310",
    "sg:postcode":"M9L 1P1",
    "sg:province":"ON",
    "sg:tags":[
        "refinishing",
        "furniture"
    ],
    "wof:name":"Lanciano Furniture Refinishing",
    "wof:placetype":"venue"
},
  "geometry": {"coordinates":[-79.539124,43.769222],"type":"Point"}
}