{
  "type": "Feature",
  "properties": {
    "addr:full":"92 Harber Ave Kitchener ON N2C 1Z2",
    "addr:housenumber":"92",
    "addr:postcode":"n2c 1z2",
    "addr:street":"Harber Ave",
    "iso:country":"CA",
    "sg:address":"92 Harber Ave",
    "sg:city":"Kitchener",
    "sg:classifiers":[
        {
            "category":"Retail",
            "subcategory":"Auto Repair",
            "type":"Services"
        }
    ],
    "sg:phone":"+1 519 748 1648",
    "sg:postcode":"N2C 1Z2",
    "sg:province":"ON",
    "sg:tags":[
        "automobile",
        "top",
        "upholstery"
    ],
    "wof:name":"Upholsteries By Dixie Inc",
    "wof:placetype":"venue"
},
  "geometry": {"coordinates":[-80.45640563960001,43.4247322083],"type":"Point"}
}