{
  "type": "Feature",
  "properties": {
    "addr:full":"Salmon Arm BC V1E 1T3",
    "addr:postcode":"v1e 1t3",
    "iso:country":"CA",
    "sg:city":"Salmon Arm",
    "sg:classifiers":[
        {
            "category":"Shopping",
            "subcategory":"Books",
            "type":"Retail Goods"
        }
    ],
    "sg:phone":"+1 250 832 3948",
    "sg:postcode":"V1E 1T3",
    "sg:province":"BC",
    "sg:tags":[
        "dealer"
    ],
    "wof:name":"Bookingham Palace Bookstore",
    "wof:placetype":"venue"
},
  "geometry": {"coordinates":[-119.298667908,50.6927261353],"type":"Point"}
}