{
  "type": "Feature",
  "properties": {
    "iso:country":"CA",
    "sg:address":"4643 Boul Samson",
    "sg:city":"Laval",
    "sg:classifiers":[
        {
            "category":"Travel",
            "subcategory":"Travel Agent",
            "type":"Entertainment"
        }
    ],
    "sg:phone":"+1 450 686 7575",
    "sg:postcode":"H7W 2H5",
    "sg:province":"QC",
    "sg:tags":[
        "agency",
        "bureau"
    ],
    "wof:name":"Voyage En Directe",
    "wof:placetype":"venue"
},
  "geometry": {"coordinates":[-73.75808,45.528927],"type":"Point"}
}