{
  "type": "Feature",
  "properties": {
    "addr:full":"119 St Clair St Chatham ON N7L 3J2",
    "addr:housenumber":"119",
    "addr:postcode":"n7l 3j2",
    "addr:street":"St Clair St",
    "iso:country":"CA",
    "sg:address":"119 St Clair St",
    "sg:city":"Chatham",
    "sg:classifiers":[
        {
            "category":"Health Services",
            "subcategory":"Optometrist",
            "type":"Services"
        }
    ],
    "sg:phone":"+1 519 351 3707",
    "sg:postcode":"N7L 3J2",
    "sg:province":"ON",
    "wof:name":"Parks, John OD",
    "wof:placetype":"venue"
},
  "geometry": {"coordinates":[-82.192284,42.409023],"type":"Point"}
}