{
  "type": "Feature",
  "properties": {
    "iso:country":"CA",
    "sg:address":"57 Rue Monfette",
    "sg:city":"Victoriaville",
    "sg:classifiers":[
        {
            "category":"Education",
            "subcategory":"School",
            "type":"Public Place"
        }
    ],
    "sg:phone":"+1 819 752 9756",
    "sg:postcode":"G6P 1J8",
    "sg:province":"QC",
    "wof:name":"Jph Massicotte",
    "wof:placetype":"venue"
},
  "geometry": {"coordinates":[-71.96607971189999,46.0613670349],"type":"Point"}
}