{
  "type": "Feature",
  "properties": {
    "addr:full":"1225 Nelson Ave Hope BC V0X 1L4",
    "addr:housenumber":"1225",
    "addr:postcode":"v0x 1l4",
    "addr:street":"Nelson Ave",
    "iso:country":"CA",
    "sg:address":"1225 Nelson Ave",
    "sg:city":"Hope",
    "sg:classifiers":[
        {
            "category":"Government",
            "subcategory":"Office",
            "type":"Public Place"
        }
    ],
    "sg:phone":"+1 604 869 2333",
    "sg:postcode":"V0X 1L4",
    "sg:province":"BC",
    "sg:tags":[
        "village"
    ],
    "wof:name":"Hope Public Works Office",
    "wof:placetype":"venue"
},
  "geometry": {"coordinates":[-121.43582916299999,49.3747253418],"type":"Point"}
}