{
  "type": "Feature",
  "properties": {
    "addr:full":"1885 Huron St London ON N5V 3A5",
    "addr:housenumber":"1885",
    "addr:postcode":"n5v 3a5",
    "addr:street":"Huron St",
    "iso:country":"CA",
    "sg:address":"1885 Huron St",
    "sg:city":"London",
    "sg:classifiers":[
        {
            "category":"Autos & Motor Vehicles",
            "subcategory":"Fuel & Gas Station",
            "type":"Retail Goods"
        }
    ],
    "sg:phone":"+1 519 452 3580",
    "sg:postcode":"N5V 3A5",
    "sg:province":"ON",
    "sg:tags":[
        "oil"
    ],
    "wof:name":"Pioneer Petroleum",
    "wof:placetype":"venue"
},
  "geometry": {"coordinates":[-81.1890792847,43.0273475647],"type":"Point"}
}