{
  "type": "Feature",
  "properties": {
    "addr:full":"PO Box 2488 Pincher Creek AB T0K 1W0",
    "addr:housenumber":"po",
    "addr:postcode":"t0k 1w0",
    "addr:street":"Box 2488 Pincher Creek",
    "iso:country":"CA",
    "sg:address":"PO Box 2488",
    "sg:city":"Pincher Creek",
    "sg:classifiers":[
        {
            "category":"Building & Trades",
            "subcategory":"Landscaping Services",
            "type":"Services"
        }
    ],
    "sg:phone":"+1 403 627 4589",
    "sg:postcode":"T0K 1W0",
    "sg:province":"AB",
    "sg:tags":[
        "landscape",
        "contractor"
    ],
    "wof:name":"Grumpy's Greenhouses & Gardens",
    "wof:placetype":"venue"
},
  "geometry": {"coordinates":[-113.95009613000001,49.4856681824],"type":"Point"}
}