{
  "type": "Feature",
  "properties": {
    "addr:full":"Edmonton AB T6E 6A5",
    "addr:postcode":"t6e 6a5",
    "iso:country":"CA",
    "sg:city":"Edmonton",
    "sg:classifiers":[
        {
            "category":"Professional",
            "subcategory":"Research",
            "type":"Services"
        }
    ],
    "sg:phone":"+1 780 438 1460",
    "sg:postcode":"T6E 6A5",
    "sg:province":"AB",
    "sg:tags":[
        "environmental",
        "ecological",
        "engineer"
    ],
    "wof:name":"Thurber Engineering Ltd",
    "wof:placetype":"venue"
},
  "geometry": {"coordinates":[-113.477448,53.488396],"type":"Point"}
}