{
  "type": "Feature",
  "properties": {
    "addr:full":"6424 Hwy 1 Cambridge Station NS B0P 1G0",
    "addr:housenumber":"6424",
    "addr:postcode":"b0p 1g0",
    "addr:street":"Hwy 1 Cambridge",
    "iso:country":"CA",
    "sg:address":"6424 Hwy 1",
    "sg:city":"Cambridge Station",
    "sg:classifiers":[
        {
            "category":"Organizations",
            "subcategory":"Religious Organization",
            "type":"Services"
        }
    ],
    "sg:phone":"+1 902 679 7196",
    "sg:postcode":"B0P 1G0",
    "sg:province":"NS",
    "sg:tags":[
        "church"
    ],
    "wof:name":"New Covenant Community Church",
    "wof:placetype":"venue"
},
  "geometry": {"coordinates":[-64.64434799999999,45.055843],"type":"Point"}
}