{
  "type": "Feature",
  "properties": {
    "addr:full":"6205 Boul Wilfrid-Hamel L'Ancienne-Lorette QC G2E 5G8",
    "addr:housenumber":"6205",
    "addr:postcode":"g2e 5g8",
    "addr:street":"Boul Wilfrid-Hamel",
    "iso:country":"CA",
    "sg:address":"6205 Boul Wilfrid-Hamel",
    "sg:city":"L'Ancienne-Lorette",
    "sg:classifiers":[
        {
            "category":"Freight",
            "type":"Transportation"
        }
    ],
    "sg:phone":"+1 418 681 6246",
    "sg:postcode":"G2E 5G8",
    "sg:province":"QC",
    "sg:tags":[
        "trucking"
    ],
    "wof:name":"Tst Overland Express Inc",
    "wof:placetype":"venue"
},
  "geometry": {"coordinates":[-71.3456878662,46.7972602844],"type":"Point"}
}