{
  "type": "Feature",
  "properties": {
    "addr:full":"2 Bloor St W #L23 Toronto ON M4W 3E2",
    "addr:housenumber":"2",
    "addr:postcode":"m4w 3e2",
    "addr:street":"Bloor St W # L23",
    "iso:country":"CA",
    "sg:address":"2 Bloor St W #L23",
    "sg:city":"Toronto",
    "sg:classifiers":[
        {
            "category":"Retail",
            "subcategory":"Photofinishing",
            "type":"Services"
        }
    ],
    "sg:phone":"+1 416 923 6888",
    "sg:postcode":"M4W 3E2",
    "sg:province":"ON",
    "sg:tags":[
        "photo",
        "finishing"
    ],
    "wof:name":"Photo Imaging Plus",
    "wof:placetype":"venue"
},
  "geometry": {"coordinates":[-79.3874130249,43.6702346802],"type":"Point"}
}