{
  "type": "Feature",
  "properties": {
    "iso:country":"CA",
    "sg:address":"324 Wharncliffe Rd N",
    "sg:city":"London",
    "sg:classifiers":[
        {
            "category":"Shopping",
            "subcategory":"Discount & Variety Stores",
            "type":"Retail Goods"
        }
    ],
    "sg:phone":"+1 519 673 3076",
    "sg:postcode":"N6G 1E3",
    "sg:province":"ON",
    "wof:name":"Ben's Variety Inc",
    "wof:placetype":"venue"
},
  "geometry": {"coordinates":[-81.266556,42.994995],"type":"Point"}
}