{
  "type": "Feature",
  "properties": {
    "addr:full":"324 Wharncliffe Rd N London ON N6G 1E3",
    "addr:housenumber":"324",
    "addr:postcode":"n6g 1e3",
    "addr:street":"Wharncliffe Rd N",
    "iso:country":"CA",
    "sg:address":"324 Wharncliffe Rd N",
    "sg:city":"London",
    "sg:classifiers":[
        {
            "category":"Shopping",
            "subcategory":"Discount & Variety Stores",
            "type":"Retail Goods"
        }
    ],
    "sg:phone":"+1 519 673 3076",
    "sg:postcode":"N6G 1E3",
    "sg:province":"ON",
    "wof:name":"Ben's Variety Inc",
    "wof:placetype":"venue"
},
  "geometry": {"coordinates":[-81.26655599999999,42.994995],"type":"Point"}
}