{
  "type": "Feature",
  "properties": {
    "addr:full":"4117 98 St NW Edmonton AB T6E 5N5",
    "addr:housenumber":"4117",
    "addr:postcode":"t6e 5n5",
    "addr:street":"98 St Nw",
    "iso:country":"CA",
    "sg:address":"4117 98 St NW",
    "sg:city":"Edmonton",
    "sg:classifiers":[
        {
            "category":"Manufacturing",
            "subcategory":"Metals",
            "type":"Manufacturing & Wholesale Goods"
        }
    ],
    "sg:phone":"+1 780 461 7288",
    "sg:postcode":"T6E 5N5",
    "sg:province":"AB",
    "sg:tags":[
        "valve"
    ],
    "wof:name":"Alberta Compressor Valve CO",
    "wof:placetype":"venue"
},
  "geometry": {"coordinates":[-113.481956,53.476997],"type":"Point"}
}