{
  "type": "Feature",
  "properties": {
    "addr:full":"2417 West River Rd Hinton AB T7V 1Z1",
    "addr:housenumber":"2417",
    "addr:postcode":"t7v 1z1",
    "addr:street":"West River Rd",
    "iso:country":"CA",
    "sg:address":"2417 West River Rd",
    "sg:city":"Hinton",
    "sg:classifiers":[
        {
            "category":"Food & Beverages",
            "subcategory":"Specialty",
            "type":"Retail Goods"
        }
    ],
    "sg:phone":"+1 780 817 2552",
    "sg:postcode":"T7V 1Z1",
    "sg:province":"AB",
    "sg:tags":[
        "water",
        "bulk",
        "company"
    ],
    "wof:name":"Mountain Lite Spring Water",
    "wof:placetype":"venue"
},
  "geometry": {"coordinates":[-117.632843018,53.3877220154],"type":"Point"}
}