{
  "type": "Feature",
  "properties": {
    "addr:full":"Orono ON L0B 1M0",
    "addr:postcode":"l0b 1m0",
    "iso:country":"CA",
    "sg:city":"Orono",
    "sg:classifiers":[
        {
            "category":"Autos & Motor Vehicles",
            "subcategory":"Fuel & Gas Station",
            "type":"Retail Goods"
        }
    ],
    "sg:phone":"+1 905 983 9742",
    "sg:postcode":"L0B 1M0",
    "sg:province":"ON",
    "sg:tags":[
        "oil"
    ],
    "wof:name":"Jun's Esso",
    "wof:placetype":"venue"
},
  "geometry": {"coordinates":[-78.6182479858,44.0449790955],"type":"Point"}
}