{
  "type": "Feature",
  "properties": {
    "addr:full":"36 Main St Kenora ON P9N 3E6",
    "addr:housenumber":"36",
    "addr:postcode":"p9n 3e6",
    "addr:street":"Main St",
    "iso:country":"CA",
    "sg:address":"36 Main St",
    "sg:city":"Kenora",
    "sg:classifiers":[
        {
            "category":"Building & Trades",
            "subcategory":"Construction",
            "type":"Services"
        }
    ],
    "sg:phone":"+1 807 468 9088",
    "sg:postcode":"P9N 3E6",
    "sg:province":"ON",
    "sg:tags":[
        "contractor",
        "sewer",
        "general"
    ],
    "wof:name":"Wayne Canfield Backhoe",
    "wof:placetype":"venue"
},
  "geometry": {"coordinates":[-94.4850769043,49.7760620117],"type":"Point"}
}