{
  "type": "Feature",
  "properties": {
    "addr:full":"Borden ON L0M 1C0",
    "addr:postcode":"l0m 1c0",
    "iso:country":"CA",
    "sg:city":"Borden",
    "sg:classifiers":[
        {
            "category":"Organizations",
            "subcategory":"Professional Association",
            "type":"Services"
        }
    ],
    "sg:phone":"+1 705 424 9635",
    "sg:postcode":"L0M 1C0",
    "sg:province":"ON",
    "wof:name":"Union of National Defense",
    "wof:placetype":"venue"
},
  "geometry": {"coordinates":[-79.8947219849,44.2841491699],"type":"Point"}
}