{
  "type": "Feature",
  "properties": {
    "addr:full":"3550 Boul Losch Saint-Hubert QC J3Y 5T6",
    "addr:housenumber":"3550",
    "addr:postcode":"j3y 5t6",
    "addr:street":"Boul Losch",
    "iso:country":"CA",
    "sg:address":"3550 Boul Losch",
    "sg:city":"Saint-Hubert",
    "sg:classifiers":[
        {
            "category":"Retail",
            "subcategory":"Auto Repair",
            "type":"Services"
        }
    ],
    "sg:phone":"+1 450 676 1151",
    "sg:postcode":"J3Y 5T6",
    "sg:province":"QC",
    "sg:tags":[
        "body",
        "automobile",
        "painting"
    ],
    "wof:name":"Garage Le Cabriolet Inc",
    "wof:placetype":"venue"
},
  "geometry": {"coordinates":[-73.44395400000001,45.499958],"type":"Point"}
}