{
  "type": "Feature",
  "properties": {
    "addr:full":"666 Rue Caron Chicoutimi QC G7J 2Z4",
    "addr:housenumber":"666",
    "addr:postcode":"g7j 2z4",
    "addr:street":"Rue Caron",
    "iso:country":"CA",
    "sg:address":"666 Rue Caron",
    "sg:city":"Chicoutimi",
    "sg:classifiers":[
        {
            "category":"Food & Beverages",
            "subcategory":"Groceries & Convenience Stores",
            "type":"Retail Goods"
        }
    ],
    "sg:phone":"+1 418 549 1655",
    "sg:postcode":"G7J 2Z4",
    "sg:province":"QC",
    "sg:tags":[
        "butchering"
    ],
    "wof:name":"Alimentation Robert Blackburn",
    "wof:placetype":"venue"
},
  "geometry": {"coordinates":[-71.07391357420001,48.4201164246],"type":"Point"}
}