{
  "type": "Feature",
  "properties": {
    "addr:full":"11401 100 Ave Grande Prairie AB T8V 5M6",
    "addr:housenumber":"11401",
    "addr:postcode":"t8v 5m6",
    "addr:street":"100 Ave",
    "iso:country":"CA",
    "sg:address":"11401 100 Ave",
    "sg:city":"Grande Prairie",
    "sg:classifiers":[
        {
            "category":"Travel",
            "subcategory":"Hotels & Motels",
            "type":"Entertainment"
        }
    ],
    "sg:phone":"+1 780 539 5678",
    "sg:postcode":"T8V 5M6",
    "sg:province":"AB",
    "wof:name":"Stanford Inn",
    "wof:placetype":"venue"
},
  "geometry": {"coordinates":[-118.84066,55.170376],"type":"Point"}
}