{
  "type": "Feature",
  "properties": {
    "addr:full":"Vaughan ON L6A 1T1",
    "addr:postcode":"l6a 1t1",
    "iso:country":"CA",
    "sg:city":"Vaughan",
    "sg:classifiers":[
        {
            "category":"Government",
            "subcategory":"Office",
            "type":"Public Place"
        }
    ],
    "sg:phone":"+1 905 832 8511",
    "sg:postcode":"L6A 1T1",
    "sg:province":"ON",
    "sg:tags":[
        "village"
    ],
    "wof:name":"Vaughan Building Standards",
    "wof:placetype":"venue"
},
  "geometry": {"coordinates":[-79.508102417,43.8564186096],"type":"Point"}
}