{
  "type": "Feature",
  "properties": {
    "addr:full":"1800 Boul Saint Alexis Saint-Maurice QC G0X 2X0",
    "addr:housenumber":"1800",
    "addr:postcode":"g0x 2x0",
    "addr:street":"Boul Saint Alexis",
    "iso:country":"CA",
    "sg:address":"1800 Boul Saint Alexis",
    "sg:city":"Saint-Maurice",
    "sg:classifiers":[
        {
            "category":"Home & Garden",
            "subcategory":"Furniture",
            "type":"Retail Goods"
        }
    ],
    "sg:phone":"+1 819 374 4466",
    "sg:postcode":"G0X 2X0",
    "sg:province":"QC",
    "sg:tags":[
        "equipment",
        "kitchen",
        "cabinet"
    ],
    "wof:name":"Ateliers Rm Inc",
    "wof:placetype":"venue"
},
  "geometry": {"coordinates":[-72.53829956049999,46.432975769],"type":"Point"}
}