{
  "type": "Feature",
  "properties": {
    "iso:country":"CA",
    "sg:address":"1400 Rue Sauve O",
    "sg:city":"Montreal",
    "sg:classifiers":[
        {
            "category":"Building & Trades",
            "subcategory":"Landscaping Services",
            "type":"Services"
        }
    ],
    "sg:phone":"+1 514 832 0011",
    "sg:postcode":"H4N 1C5",
    "sg:province":"QC",
    "sg:tags":[
        "program",
        "maintenance"
    ],
    "wof:name":"Docteur Graffiti",
    "wof:placetype":"venue"
},
  "geometry": {"coordinates":[-73.6653671265,45.535358429],"type":"Point"}
}