{
  "type": "Feature",
  "properties": {
    "addr:full":"955 Brock Rd Pickering ON L1W 2X9",
    "addr:housenumber":"955",
    "addr:postcode":"l1w 2x9",
    "addr:street":"Brock Rd",
    "iso:country":"CA",
    "sg:address":"955 Brock Rd",
    "sg:city":"Pickering",
    "sg:classifiers":[
        {
            "category":"Manufacturing",
            "subcategory":"Tools & Machinery",
            "type":"Manufacturing & Wholesale Goods"
        }
    ],
    "sg:phone":"+1 905 420 3955",
    "sg:postcode":"L1W 2X9",
    "sg:province":"ON",
    "sg:tags":[
        "material",
        "truck",
        "handling"
    ],
    "wof:name":"Electric Lift Truck CO Ltd",
    "wof:placetype":"venue"
},
  "geometry": {"coordinates":[-79.0659561157,43.8302116394],"type":"Point"}
}