{
  "type": "Feature",
  "properties": {
    "addr:full":"2332 11th Ave # 230 Regina SK S4P 0K1",
    "addr:housenumber":"2332",
    "addr:postcode":"s4p 0k1",
    "addr:street":"11Th Ave # 230",
    "iso:country":"CA",
    "sg:address":"2332 11th Ave # 230",
    "sg:city":"Regina",
    "sg:classifiers":[
        {
            "category":"Professional",
            "subcategory":"Accounting & Tax Preparation",
            "type":"Services"
        }
    ],
    "sg:phone":"+1 306 924 4375",
    "sg:postcode":"S4P 0K1",
    "sg:province":"SK",
    "sg:tags":[
        "consultant",
        "accountant"
    ],
    "wof:name":"Padgett Business Svc",
    "wof:placetype":"venue"
},
  "geometry": {"coordinates":[-104.614204407,50.4505462646],"type":"Point"}
}