{
  "type": "Feature",
  "properties": {
    "addr:full":"5004 Meridian St NW Edmonton AB T6P 1R3",
    "addr:housenumber":"5004",
    "addr:postcode":"t6p 1r3",
    "addr:street":"Meridian St Nw",
    "iso:country":"CA",
    "sg:address":"5004 Meridian St NW",
    "sg:city":"Edmonton",
    "sg:classifiers":[
        {
            "category":"Real Estate",
            "subcategory":"Developer",
            "type":"Services"
        }
    ],
    "sg:phone":"+1 780 496 6983",
    "sg:postcode":"T6P 1R3",
    "sg:province":"AB",
    "sg:tags":[
        "cemetery",
        "government"
    ],
    "wof:name":"South Haven Cemetery",
    "wof:placetype":"venue"
},
  "geometry": {"coordinates":[-113.344581604,53.4910392761],"type":"Point"}
}