{
  "type": "Feature",
  "properties": {
    "addr:full":"1944 10 Ave SW Calgary AB T3C 0J8",
    "addr:housenumber":"1944",
    "addr:postcode":"t3c 0j8",
    "addr:street":"10 Ave Sw",
    "iso:country":"CA",
    "sg:address":"1944 10 Ave SW",
    "sg:city":"Calgary",
    "sg:classifiers":[
        {
            "category":"Real Estate",
            "subcategory":"Surveying",
            "type":"Services"
        }
    ],
    "sg:phone":"+1 403 244 2131",
    "sg:postcode":"T3C 0J8",
    "sg:province":"AB",
    "sg:tags":[
        "field",
        "oil"
    ],
    "wof:name":"All-Can Engineering & Surveys",
    "wof:placetype":"venue"
},
  "geometry": {"coordinates":[-114.104858398,51.0446128845],"type":"Point"}
}