{
  "type": "Feature",
  "properties": {
    "addr:full":"5960 LA Grande-Allee Saint-Hubert QC J3Y 1B3",
    "addr:housenumber":"5960",
    "addr:postcode":"j3y 1b3",
    "addr:street":"La Grande-Allee",
    "iso:country":"CA",
    "sg:address":"5960 LA Grande-Allee",
    "sg:city":"Saint-Hubert",
    "sg:classifiers":[
        {
            "category":"Retail",
            "subcategory":"Auto Repair",
            "type":"Services"
        }
    ],
    "sg:phone":"+1 450 678 5256",
    "sg:postcode":"J3Y 1B3",
    "sg:province":"QC",
    "sg:tags":[
        "repairing",
        "automobile"
    ],
    "wof:name":"Autopro Garage Max Enr",
    "wof:placetype":"venue"
},
  "geometry": {"coordinates":[-73.43570699999999,45.469948],"type":"Point"}
}