{
  "type": "Feature",
  "properties": {
    "iso:country":"CA",
    "sg:address":"1742 Springfield Rd # 2",
    "sg:city":"Kelowna",
    "sg:classifiers":[
        {
            "category":"Manufacturing",
            "subcategory":"Apparel",
            "type":"Manufacturing & Wholesale Goods"
        }
    ],
    "sg:phone":"+1 250 860 1728",
    "sg:postcode":"V1Y 5V6",
    "sg:province":"BC",
    "sg:tags":[
        "flag",
        "sign"
    ],
    "wof:name":"Access Signs",
    "wof:placetype":"venue"
},
  "geometry": {"coordinates":[-119.459083557,49.8769416809],"type":"Point"}
}