{
  "type": "Feature",
  "properties": {
    "iso:country":"CA",
    "sg:address":"414 Rue DE LA Riviere",
    "sg:city":"Cowansville",
    "sg:classifiers":[
        {
            "category":"Manufacturing",
            "subcategory":"Tools & Machinery",
            "type":"Manufacturing & Wholesale Goods"
        }
    ],
    "sg:phone":"+1 450 266 0744",
    "sg:postcode":"J2K 1N3",
    "sg:province":"QC",
    "sg:tags":[
        "engine"
    ],
    "wof:name":"Apm Diesel",
    "wof:placetype":"venue"
},
  "geometry": {"coordinates":[-72.7662811279,45.2099075317],"type":"Point"}
}