{
  "type": "Feature",
  "properties": {
    "addr:full":"1982 Islington Ave Etobicoke ON M9P 3N5",
    "addr:housenumber":"1982",
    "addr:postcode":"m9p 3n5",
    "addr:street":"Islington Ave",
    "iso:country":"CA",
    "sg:address":"1982 Islington Ave",
    "sg:city":"Etobicoke",
    "sg:classifiers":[
        {
            "category":"Manufacturing",
            "subcategory":"Printing",
            "type":"Manufacturing & Wholesale Goods"
        }
    ],
    "sg:phone":"+1 416 621 2077",
    "sg:postcode":"M9P 3N5",
    "sg:province":"ON",
    "sg:tags":[
        "publisher",
        "guide"
    ],
    "wof:name":"Mc Intyre & Assoc",
    "wof:placetype":"venue"
},
  "geometry": {"coordinates":[-79.54602050779999,43.6951637268],"type":"Point"}
}