{
  "type": "Feature",
  "properties": {
    "addr:full":"131 Queen St Eganville ON K0J 1T0",
    "addr:housenumber":"131",
    "addr:postcode":"k0j 1t0",
    "addr:street":"Queen St",
    "iso:country":"CA",
    "sg:address":"131 Queen St",
    "sg:city":"Eganville",
    "sg:classifiers":[
        {
            "category":"Restaurant",
            "type":"Food & Drink"
        }
    ],
    "sg:phone":"+1 613 628 2468",
    "sg:postcode":"K0J 1T0",
    "sg:province":"ON",
    "wof:name":"Country Rose Restaurant",
    "wof:placetype":"venue"
},
  "geometry": {"coordinates":[-77.09765625,45.5362243652],"type":"Point"}
}