{
  "type": "Feature",
  "properties": {
    "addr:full":"32 Calkin Dr Kentville NS B4N 3V7",
    "addr:housenumber":"32",
    "addr:postcode":"b4n 3v7",
    "addr:street":"Calkin Dr",
    "iso:country":"CA",
    "sg:address":"32 Calkin Dr",
    "sg:city":"Kentville",
    "sg:classifiers":[
        {
            "category":"Manufacturing",
            "subcategory":"Tools & Machinery",
            "type":"Manufacturing & Wholesale Goods"
        }
    ],
    "sg:phone":"+1 902 678 1354",
    "sg:postcode":"B4N 3V7",
    "sg:province":"NS",
    "sg:tags":[
        "machine",
        "shop"
    ],
    "wof:name":"Heritage Machining Svc",
    "wof:placetype":"venue"
},
  "geometry": {"coordinates":[-64.5484542847,45.065864563],"type":"Point"}
}