{
  "type": "Feature",
  "properties": {
    "addr:full":"Halifax NS B3M 3K5",
    "addr:postcode":"b3m 3k5",
    "iso:country":"CA",
    "sg:city":"Halifax",
    "sg:classifiers":[
        {
            "category":"Real Estate",
            "subcategory":"Real Estate Operator",
            "type":"Services"
        }
    ],
    "sg:phone":"+1 902 443 4827",
    "sg:postcode":"B3M 3K5",
    "sg:province":"NS",
    "sg:tags":[
        "apartment"
    ],
    "wof:name":"Stoneybrook Manor",
    "wof:placetype":"venue"
},
  "geometry": {"coordinates":[-63.637913,44.661934],"type":"Point"}
}