{
  "type": "Feature",
  "properties": {
    "iso:country":"CA",
    "sg:address":"19 Metcalfe Dr",
    "sg:city":"Sarnia",
    "sg:classifiers":[
        {
            "category":"Building & Trades",
            "subcategory":"Plumbing",
            "type":"Services"
        }
    ],
    "sg:phone":"+1 519 542 0333",
    "sg:postcode":"N7X 1A3",
    "sg:province":"ON",
    "sg:tags":[
        "conditioning",
        "air",
        "system",
        "contractor"
    ],
    "wof:name":"Sarnia Commercial & Ind Refrig",
    "wof:placetype":"venue"
},
  "geometry": {"coordinates":[-82.34089660639999,43.0153846741],"type":"Point"}
}