{
  "type": "Feature",
  "properties": {
    "addr:full":"45 Place D'Argenteuil Laval QC H7N 1P4",
    "addr:housenumber":"45",
    "addr:postcode":"h7n 1p4",
    "addr:street":"Place D'Argenteuil",
    "iso:country":"CA",
    "sg:address":"45 Place D'Argenteuil",
    "sg:city":"Laval",
    "sg:classifiers":[
        {
            "category":"Professional",
            "subcategory":"Detective & Security Services",
            "type":"Services"
        }
    ],
    "sg:phone":"+1 450 978 4332",
    "sg:postcode":"H7N 1P4",
    "sg:province":"QC",
    "sg:tags":[
        "investigator"
    ],
    "wof:name":"Investigations Bonaventure Inc",
    "wof:placetype":"venue"
},
  "geometry": {"coordinates":[-73.713768,45.55497],"type":"Point"}
}