{
  "type": "Feature",
  "properties": {
    "addr:full":"Victoria BC V9A 3B8",
    "addr:postcode":"v9a 3b8",
    "iso:country":"CA",
    "sg:city":"Victoria",
    "sg:classifiers":[
        {
            "category":"Shopping",
            "type":"Retail Goods"
        }
    ],
    "sg:phone":"+1 250 384 8484",
    "sg:postcode":"V9A 3B8",
    "sg:province":"BC",
    "sg:tags":[
        "equipment",
        "beer",
        "supply"
    ],
    "wof:name":"West Coast Brew Shop-U-Brew",
    "wof:placetype":"venue"
},
  "geometry": {"coordinates":[-123.382431,48.434521],"type":"Point"}
}