{
  "type": "Feature",
  "properties": {
    "addr:full":"816 Black Rd Sault Ste Marie ON P6A 6J8",
    "addr:housenumber":"816",
    "addr:postcode":"p6a 6j8",
    "addr:street":"Black Rd",
    "iso:country":"CA",
    "sg:address":"816 Black Rd",
    "sg:city":"Sault Ste Marie",
    "sg:classifiers":[
        {
            "category":"Retail",
            "subcategory":"Veterinary Services",
            "type":"Services"
        }
    ],
    "sg:phone":"+1 705 253 7831",
    "sg:postcode":"P6A 6J8",
    "sg:province":"ON",
    "sg:tags":[
        "veterinarian"
    ],
    "wof:name":"Black Road Veterinary Svc",
    "wof:placetype":"venue"
},
  "geometry": {"coordinates":[-84.287575,46.545967],"type":"Point"}
}