{
  "type": "Feature",
  "properties": {
    "addr:full":"Calgary AB T2E 8A2",
    "addr:postcode":"t2e 8a2",
    "iso:country":"CA",
    "sg:city":"Calgary",
    "sg:classifiers":[
        {
            "category":"Professional",
            "subcategory":"Advertising",
            "type":"Services"
        }
    ],
    "sg:phone":"+1 403 262 5900",
    "sg:postcode":"T2E 8A2",
    "sg:province":"AB",
    "sg:tags":[
        "designer",
        "display",
        "producer"
    ],
    "wof:name":"Displayco Canada Inc",
    "wof:placetype":"venue"
},
  "geometry": {"coordinates":[-114.04330400000001,51.120564],"type":"Point"}
}