{
  "type": "Feature",
  "properties": {
    "addr:full":"Ottawa ON K2P 1L5",
    "addr:postcode":"k2p 1l5",
    "iso:country":"CA",
    "sg:city":"Ottawa",
    "sg:classifiers":[
        {
            "category":"Professional",
            "subcategory":"Lawyer & Legal Services",
            "type":"Services"
        }
    ],
    "sg:phone":"+1 613 236 0662",
    "sg:postcode":"K2P 1L5",
    "sg:province":"ON",
    "sg:tags":[
        "attorney"
    ],
    "wof:name":"Blaney, Gary K",
    "wof:placetype":"venue"
},
  "geometry": {"coordinates":[-75.69169599999999,45.41922],"type":"Point"}
}