{
  "type": "Feature",
  "properties": {
    "addr:full":"186 Rue Saint-Georges LA Prairie QC J5R 2M4",
    "addr:housenumber":"186",
    "addr:postcode":"j5r 2m4",
    "addr:street":"Rue Saint-Georges",
    "iso:country":"CA",
    "sg:address":"186 Rue Saint-Georges",
    "sg:city":"LA Prairie",
    "sg:classifiers":[
        {
            "category":"Social Services",
            "subcategory":"Child Care",
            "type":"Services"
        }
    ],
    "sg:phone":"+1 450 659 3030",
    "sg:postcode":"J5R 2M4",
    "sg:province":"QC",
    "wof:name":"Garderie Le Soleil En Soi",
    "wof:placetype":"venue"
},
  "geometry": {"coordinates":[-73.4954986572,45.4188041687],"type":"Point"}
}