{
  "type": "Feature",
  "properties": {
    "iso:country":"CA",
    "sg:city":"Bothwell",
    "sg:classifiers":[
        {
            "category":"Recreation",
            "subcategory":"Marina",
            "type":"Entertainment"
        }
    ],
    "sg:phone":"+1 519 695 5900",
    "sg:postcode":"N0P 1C0",
    "sg:province":"ON",
    "sg:tags":[
        "repairing",
        "boat"
    ],
    "wof:name":"Marsh Recreation",
    "wof:placetype":"venue"
},
  "geometry": {"coordinates":[-81.8715515137,42.6304512024],"type":"Point"}
}