{
  "type": "Feature",
  "properties": {
    "addr:full":"551 Regent Ave W Winnipeg MB R2C 1R9",
    "addr:housenumber":"551",
    "addr:postcode":"r2c 1r9",
    "addr:street":"Regent Ave W",
    "iso:country":"CA",
    "sg:address":"551 Regent Ave W",
    "sg:city":"Winnipeg",
    "sg:classifiers":[
        {
            "category":"Health Services",
            "subcategory":"Medical Lab",
            "type":"Services"
        }
    ],
    "sg:phone":"+1 204 224 8800",
    "sg:postcode":"R2C 1R9",
    "sg:province":"MB",
    "wof:name":"Regent Denture Clinic",
    "wof:placetype":"venue"
},
  "geometry": {"coordinates":[-97.01786800000001,49.89537],"type":"Point"}
}