{
  "type": "Feature",
  "properties": {
    "addr:full":"2525 County Rd 50 Loretto ON L0G 1L0",
    "addr:housenumber":"2525;50",
    "addr:postcode":"l0g 1l0",
    "addr:street":"County Rd",
    "iso:country":"CA",
    "sg:address":"2525 County Rd 50",
    "sg:city":"Loretto",
    "sg:classifiers":[
        {
            "category":"Building & Trades",
            "subcategory":"Construction",
            "type":"Services"
        }
    ],
    "sg:phone":"+1 905 936 2050",
    "sg:postcode":"L0G 1L0",
    "sg:province":"ON",
    "sg:tags":[
        "home",
        "siding",
        "material",
        "improvement"
    ],
    "wof:name":"Metro Wide Siding Ltd",
    "wof:placetype":"venue"
},
  "geometry": {"coordinates":[-79.8904800415,44.0491065979],"type":"Point"}
}