{
  "type": "Feature",
  "properties": {
    "addr:full":"Lebel-Sur-Quevillon QC J0Y 1X0",
    "addr:postcode":"j0y 1x0",
    "iso:country":"CA",
    "sg:city":"Lebel-Sur-Quevillon",
    "sg:classifiers":[
        {
            "category":"Food & Beverages",
            "subcategory":"Liquor & Beverages",
            "type":"Retail Goods"
        }
    ],
    "sg:phone":"+1 819 755 4372",
    "sg:postcode":"J0Y 1X0",
    "sg:province":"QC",
    "sg:tags":[
        "store"
    ],
    "wof:name":"Saq",
    "wof:placetype":"venue"
},
  "geometry": {"coordinates":[-76.9776763916,49.0519371033],"type":"Point"}
}