{
  "type": "Feature",
  "properties": {
    "addr:full":"4620 Boul Thimens Saint-Laurent QC H4R 2B2",
    "addr:housenumber":"4620",
    "addr:postcode":"h4r 2b2",
    "addr:street":"Boul Thimens",
    "iso:country":"CA",
    "sg:address":"4620 Boul Thimens",
    "sg:city":"Saint-Laurent",
    "sg:classifiers":[
        {
            "category":"Manufacturing",
            "subcategory":"Food",
            "type":"Manufacturing & Wholesale Goods"
        }
    ],
    "sg:phone":"+1 514 333 8540",
    "sg:postcode":"H4R 2B2",
    "sg:province":"QC",
    "sg:tags":[
        "cocoa",
        "chocolate"
    ],
    "wof:name":"Chocolat Jean-Talon",
    "wof:placetype":"venue"
},
  "geometry": {"coordinates":[-73.7247161865,45.4948425293],"type":"Point"}
}