{
  "type": "Feature",
  "properties": {
    "addr:full":"46126 Yale Rd Chilliwack BC V2P 2P1",
    "addr:housenumber":"46126",
    "addr:postcode":"v2p 2p1",
    "addr:street":"Yale Rd",
    "iso:country":"CA",
    "sg:address":"46126 Yale Rd",
    "sg:city":"Chilliwack",
    "sg:classifiers":[
        {
            "category":"Manufacturing",
            "subcategory":"Metals",
            "type":"Manufacturing & Wholesale Goods"
        }
    ],
    "sg:phone":"+1 604 793 9400",
    "sg:postcode":"V2P 2P1",
    "sg:province":"BC",
    "sg:tags":[
        "cashing",
        "mail",
        "check"
    ],
    "wof:name":"Money Mart",
    "wof:placetype":"venue"
},
  "geometry": {"coordinates":[-121.95192,49.171131],"type":"Point"}
}