{
  "type": "Feature",
  "properties": {
    "addr:full":"95 Centennial Dr Port Hope ON L1A 3X3",
    "addr:housenumber":"95",
    "addr:postcode":"l1a 3x3",
    "addr:street":"Centennial Dr",
    "iso:country":"CA",
    "sg:address":"95 Centennial Dr",
    "sg:city":"Port Hope",
    "sg:classifiers":[
        {
            "category":"Real Estate",
            "subcategory":"Real Estate Agent",
            "type":"Services"
        }
    ],
    "sg:phone":"+1 905 885 8073",
    "sg:postcode":"L1A 3X3",
    "sg:province":"ON",
    "sg:tags":[
        "appraiser"
    ],
    "wof:name":"Darce Campbell Real Estate Ltd",
    "wof:placetype":"venue"
},
  "geometry": {"coordinates":[-78.30766300000001,43.965546],"type":"Point"}
}