{
  "type": "Feature",
  "properties": {
    "addr:full":"11204 27 St SW Calgary AB T2W 2Z6",
    "addr:housenumber":"11204",
    "addr:postcode":"t2w 2z6",
    "addr:street":"27 St Sw",
    "iso:country":"CA",
    "sg:address":"11204 27 St SW",
    "sg:city":"Calgary",
    "sg:classifiers":[
        {
            "category":"Real Estate",
            "subcategory":"Real Estate Operator",
            "type":"Services"
        }
    ],
    "sg:phone":"+1 403 238 6576",
    "sg:postcode":"T2W 2Z6",
    "sg:province":"AB",
    "sg:tags":[
        "apartment"
    ],
    "wof:name":"Sikome Rise Housing CO-OP Ltd",
    "wof:placetype":"venue"
},
  "geometry": {"coordinates":[-114.12342099999999,50.953732],"type":"Point"}
}