{
  "type": "Feature",
  "properties": {
    "addr:full":"Toronto ON M4Y 1R7",
    "addr:postcode":"m4y 1r7",
    "iso:country":"CA",
    "sg:city":"Toronto",
    "sg:classifiers":[
        {
            "category":"Real Estate",
            "subcategory":"Real Estate Agent",
            "type":"Services"
        }
    ],
    "sg:phone":"+1 416 922 8900",
    "sg:postcode":"M4Y 1R7",
    "sg:province":"ON",
    "wof:name":"Amso Realty Corp",
    "wof:placetype":"venue"
},
  "geometry": {"coordinates":[-79.387856,43.668503],"type":"Point"}
}