{
  "type": "Feature",
  "properties": {
    "addr:full":"121 Limestone Cres. Toronto M3J 2R1",
    "addr:housenumber":"121",
    "addr:postcode":"m3j 2r1",
    "addr:street":"Limestone Cres.",
    "iso:country":"CA",
    "sg:address":"121 Limestone Cres.",
    "sg:city":"Toronto",
    "sg:classifiers":[
        {
            "category":"Professional",
            "subcategory":"Research",
            "type":"Services"
        }
    ],
    "sg:postcode":"M3J 2R1",
    "sg:tags":[
        "green-hosting",
        "green-energy",
        "climate-change",
        "global-warming",
        "carbon-offset",
        "website",
        "internet",
        "cleantech"
    ],
    "sg:website":"http://www.greenscroll.org/",
    "wof:name":"Greenscroll",
    "wof:placetype":"venue"
},
  "geometry": {"coordinates":[-79.4886401,43.7800889],"type":"Point"}
}