{
  "type": "Feature",
  "properties": {
    "addr:full":"Laval QC H7X 3S5",
    "addr:postcode":"h7x 3s5",
    "iso:country":"CA",
    "sg:city":"Laval",
    "sg:classifiers":[
        {
            "category":"Health Services",
            "subcategory":"Chiropractor",
            "type":"Services"
        }
    ],
    "sg:phone":"+1 450 689 1223",
    "sg:postcode":"H7X 3S5",
    "sg:province":"QC",
    "wof:name":"Clinique Chiropratique",
    "wof:placetype":"venue"
},
  "geometry": {"coordinates":[-73.7870101929,45.5222053528],"type":"Point"}
}