{
  "type": "Feature",
  "properties": {
    "addr:full":"104 Av Champlain Val-D'Or QC J9P 2A6",
    "addr:postcode":"j9p 2a6",
    "addr:street":"104 Av Champlain",
    "iso:country":"CA",
    "sg:address":"104 Av Champlain",
    "sg:city":"Val-D'Or",
    "sg:classifiers":[
        {
            "category":"Building & Trades",
            "subcategory":"Construction",
            "type":"Services"
        }
    ],
    "sg:phone":"+1 819 825 2040",
    "sg:postcode":"J9P 2A6",
    "sg:province":"QC",
    "sg:tags":[
        "repairing",
        "contractor",
        "remodeling",
        "general"
    ],
    "wof:name":"Renovation Champlain Val D'Or",
    "wof:placetype":"venue"
},
  "geometry": {"coordinates":[-71.0033187866,45.3835067749],"type":"Point"}
}