{
  "type": "Feature",
  "properties": {
    "iso:country":"CA",
    "sg:address":"12425 Boul Industriel",
    "sg:city":"Pointe-Aux-Trembles",
    "sg:classifiers":[
        {
            "category":"Manufacturing",
            "subcategory":"Rubber & Plastics",
            "type":"Manufacturing & Wholesale Goods"
        }
    ],
    "sg:phone":"+1 514 645 4258",
    "sg:postcode":"H1B 5M7",
    "sg:province":"QC",
    "sg:tags":[
        "mold",
        "maker"
    ],
    "wof:name":"Rondi Industries Inc",
    "wof:placetype":"venue"
},
  "geometry": {"coordinates":[-73.5186,45.648537],"type":"Point"}
}