{
  "type": "Feature",
  "properties": {
    "addr:full":"Le Gardeur QC J5Z 4W8",
    "addr:postcode":"j5z 4w8",
    "addr:street":"Le Gardeur",
    "iso:country":"CA",
    "sg:city":"Le Gardeur",
    "sg:classifiers":[
        {
            "category":"Building & Trades",
            "subcategory":"Construction",
            "type":"Services"
        }
    ],
    "sg:phone":"+1 450 657 2000",
    "sg:postcode":"J5Z 4W8",
    "sg:province":"QC",
    "sg:tags":[
        "fiber",
        "optics"
    ],
    "wof:name":"Tel Tech 2000 Inc",
    "wof:placetype":"venue"
},
  "geometry": {"coordinates":[-73.484131,45.756271],"type":"Point"}
}