{
  "type": "Feature",
  "properties": {
    "iso:country":"CA",
    "sg:city":"Vancouver",
    "sg:classifiers":[
        {
            "category":"Wholesale",
            "subcategory":"Farm Supplies",
            "type":"Manufacturing & Wholesale Goods"
        }
    ],
    "sg:phone":"+1 604 669 7212",
    "sg:postcode":"V6G 1B3",
    "sg:province":"BC",
    "sg:tags":[
        "feed"
    ],
    "wof:name":"Westhawk Traders Ltd",
    "wof:placetype":"venue"
},
  "geometry": {"coordinates":[-123.13482666,49.2922973633],"type":"Point"}
}