{
  "type": "Feature",
  "properties": {
    "addr:full":"7 Hillside Cres Sherwood Park AB T8A 5E2",
    "addr:housenumber":"7",
    "addr:postcode":"t8a 5e2",
    "addr:street":"Hillside Cres",
    "iso:country":"CA",
    "sg:address":"7 Hillside Cres",
    "sg:city":"Sherwood Park",
    "sg:classifiers":[
        {
            "category":"Utilities",
            "subcategory":"Fuel Oil & Lpg",
            "type":"Services"
        }
    ],
    "sg:phone":"+1 780 417 6969",
    "sg:postcode":"T8A 5E2",
    "sg:province":"AB",
    "sg:tags":[
        "propane",
        "gas"
    ],
    "wof:name":"Bo Li Enterprises Inc",
    "wof:placetype":"venue"
},
  "geometry": {"coordinates":[-113.255798,53.538113],"type":"Point"}
}