{
  "type": "Feature",
  "properties": {
    "addr:full":"16 Main St St Walburg SK S0M 2T0",
    "addr:housenumber":"16",
    "addr:postcode":"s0m 2t0",
    "addr:street":"Main St St",
    "iso:country":"CA",
    "sg:address":"16 Main St",
    "sg:city":"St Walburg",
    "sg:classifiers":[
        {
            "category":"Education",
            "subcategory":"School",
            "type":"Public Place"
        }
    ],
    "sg:phone":"+1 306 248 3288",
    "sg:postcode":"S0M 2T0",
    "sg:province":"SK",
    "wof:name":"North West Regional College",
    "wof:placetype":"venue"
},
  "geometry": {"coordinates":[-109.200080872,53.6347236633],"type":"Point"}
}