{
  "type": "Feature",
  "properties": {
    "iso:country":"CA",
    "sg:address":"21 Micmac Dr",
    "sg:city":"Dartmouth",
    "sg:classifiers":[
        {
            "category":"Shopping",
            "subcategory":"Clothing, Apparel, & Fashions",
            "type":"Retail Goods"
        }
    ],
    "sg:phone":"+1 902 465 3754",
    "sg:postcode":"B2X 2H4",
    "sg:province":"NS",
    "sg:tags":[
        "furnishing"
    ],
    "wof:name":"Le Chateau",
    "wof:placetype":"venue"
},
  "geometry": {"coordinates":[-63.5445976257,44.6948623657],"type":"Point"}
}