{
  "type": "Feature",
  "properties": {
    "addr:full":"Beauport QC G1B 3G3",
    "addr:postcode":"g1b 3g3",
    "iso:country":"CA",
    "sg:city":"Beauport",
    "sg:classifiers":[
        {
            "category":"Health Services",
            "subcategory":"Doctor",
            "type":"Services"
        }
    ],
    "sg:phone":"+1 418 663 3333",
    "sg:postcode":"G1B 3G3",
    "sg:province":"QC",
    "sg:tags":[
        "dentist"
    ],
    "wof:name":"Centre Dentaire Lecours & Assc",
    "wof:placetype":"venue"
},
  "geometry": {"coordinates":[-71.1906585693,46.8983383179],"type":"Point"}
}