{
  "type": "Feature",
  "properties": {
    "addr:full":"5456 Av Westminster Cote Saint-Luc QC H4X 2A5",
    "addr:housenumber":"5456",
    "addr:postcode":"h4x 2a5",
    "addr:street":"Av Westminster Cote",
    "iso:country":"CA",
    "sg:address":"5456 Av Westminster",
    "sg:city":"Cote Saint-Luc",
    "sg:classifiers":[
        {
            "category":"Retail",
            "subcategory":"Repair Shop",
            "type":"Services"
        }
    ],
    "sg:phone":"+1 514 484 0284",
    "sg:postcode":"H4X 2A5",
    "sg:province":"QC",
    "sg:tags":[
        "lock",
        "locksmith"
    ],
    "wof:name":"Serrurier M Greene Locksmith",
    "wof:placetype":"venue"
},
  "geometry": {"coordinates":[-73.661293,45.4589],"type":"Point"}
}