{
  "type": "Feature",
  "properties": {
    "addr:full":"Surrey BC V3R 8P7",
    "addr:postcode":"v3r 8p7",
    "iso:country":"CA",
    "sg:city":"Surrey",
    "sg:classifiers":[
        {
            "category":"Professional",
            "subcategory":"Lawyer & Legal Services",
            "type":"Services"
        }
    ],
    "sg:phone":"+1 604 588 5344",
    "sg:postcode":"V3R 8P7",
    "sg:province":"BC",
    "sg:tags":[
        "attorney"
    ],
    "wof:name":"Sanderson, Kent",
    "wof:placetype":"venue"
},
  "geometry": {"coordinates":[-122.80310799999999,49.186329],"type":"Point"}
}