{
  "type": "Feature",
  "properties": {
    "iso:country":"CA",
    "sg:address":"1476 Ouellette Ave",
    "sg:city":"Windsor",
    "sg:classifiers":[
        {
            "category":"Retail",
            "subcategory":"Laundry & Dry Cleaning",
            "type":"Services"
        }
    ],
    "sg:phone":"+1 519 977 9880",
    "sg:postcode":"N8X 1K3",
    "sg:province":"ON",
    "sg:tags":[
        "cleaners"
    ],
    "wof:name":"Highland Dry Cleaners",
    "wof:placetype":"venue"
},
  "geometry": {"coordinates":[-83.028229,42.301025],"type":"Point"}
}