{
  "type": "Feature",
  "properties": {
    "addr:full":"10 Rideau St Ottawa ON K1N 9J1",
    "addr:housenumber":"10",
    "addr:postcode":"k1n 9j1",
    "addr:street":"Rideau St",
    "iso:country":"CA",
    "sg:address":"10 Rideau St",
    "sg:city":"Ottawa",
    "sg:classifiers":[
        {
            "category":"Government",
            "subcategory":"Office",
            "type":"Public Place"
        }
    ],
    "sg:phone":"+1 613 234 1188",
    "sg:postcode":"K1N 9J1",
    "sg:province":"ON",
    "wof:name":"Ontario Developmentally Hndcp",
    "wof:placetype":"venue"
},
  "geometry": {"coordinates":[-75.6921081543,45.4445495605],"type":"Point"}
}