{
  "type": "Feature",
  "properties": {
    "iso:country":"CA",
    "sg:city":"Brampton",
    "sg:classifiers":[
        {
            "category":"Manufacturing",
            "subcategory":"Metals",
            "type":"Manufacturing & Wholesale Goods"
        }
    ],
    "sg:phone":"+1 905 874 0533",
    "sg:postcode":"L6T 4Z5",
    "sg:province":"ON",
    "sg:tags":[
        "steel"
    ],
    "wof:name":"Sacramento Welding & Mfg",
    "wof:placetype":"venue"
},
  "geometry": {"coordinates":[-79.698555,43.690849],"type":"Point"}
}