{
  "type": "Feature",
  "properties": {
    "iso:country":"CA",
    "sg:address":"186 Boul Laurier",
    "sg:city":"Laurier-Station",
    "sg:classifiers":[
        {
            "category":"Government",
            "subcategory":"Office",
            "type":"Public Place"
        }
    ],
    "sg:phone":"+1 418 728 3564",
    "sg:postcode":"G0S 1N0",
    "sg:province":"QC",
    "wof:name":"Quebec Loisir Chasse Et Peche",
    "wof:placetype":"venue"
},
  "geometry": {"coordinates":[-71.625305,46.543247],"type":"Point"}
}