{
  "type": "Feature",
  "properties": {
    "addr:full":"Calgary AB T2G 5M2",
    "addr:postcode":"t2g 5m2",
    "iso:country":"CA",
    "sg:city":"Calgary",
    "sg:classifiers":[
        {
            "category":"Retail",
            "subcategory":"Repair Shop",
            "type":"Services"
        }
    ],
    "sg:phone":"+1 403 243 2291",
    "sg:postcode":"T2G 5M2",
    "sg:province":"AB",
    "sg:tags":[
        "upholsterer"
    ],
    "wof:name":"M T Svc & Upholstery",
    "wof:placetype":"venue"
},
  "geometry": {"coordinates":[-114.035355,51.010548],"type":"Point"}
}