{
  "type": "Feature",
  "properties": {
    "iso:country":"CA",
    "sg:address":"300 Donlin Ave",
    "sg:city":"Newmarket",
    "sg:classifiers":[
        {
            "category":"Shopping",
            "type":"Retail Goods"
        }
    ],
    "sg:phone":"+1 905 895 6291",
    "sg:postcode":"L3Y 4T6",
    "sg:province":"ON",
    "sg:tags":[
        "trophy",
        "engraver",
        "medal",
        "award"
    ],
    "wof:name":"Keith Davis Engravers & Awards",
    "wof:placetype":"venue"
},
  "geometry": {"coordinates":[-79.474045,44.046223],"type":"Point"}
}