{
  "type": "Feature",
  "properties": {
    "addr:full":"4771 Vanguard Rd Richmond BC V6X 2P7",
    "addr:housenumber":"4771",
    "addr:postcode":"v6x 2p7",
    "addr:street":"Vanguard Rd",
    "iso:country":"CA",
    "sg:address":"4771 Vanguard Rd",
    "sg:city":"Richmond",
    "sg:classifiers":[
        {
            "category":"Shopping",
            "subcategory":"Stationery & Office Supplies",
            "type":"Retail Goods"
        }
    ],
    "sg:phone":"+1 604 273 0761",
    "sg:postcode":"V6X 2P7",
    "sg:province":"BC",
    "sg:tags":[
        "envelope"
    ],
    "wof:name":"Pioneer Envelopes Ltd",
    "wof:placetype":"venue"
},
  "geometry": {"coordinates":[-123.101036072,49.1785316467],"type":"Point"}
}