{
  "type": "Feature",
  "properties": {
    "iso:country":"CA",
    "sg:address":"1 Ch Arthur Doyon",
    "sg:city":"Preissac",
    "sg:classifiers":[
        {
            "category":"Organizations",
            "subcategory":"Labor Organization",
            "type":"Services"
        }
    ],
    "sg:phone":"+1 819 759 3538",
    "sg:postcode":"J0Y 2E0",
    "sg:province":"QC",
    "wof:name":"Syndicat Des Metallos Local",
    "wof:placetype":"venue"
},
  "geometry": {"coordinates":[-78.542350769,48.2579154968],"type":"Point"}
}