{
  "type": "Feature",
  "properties": {
    "addr:full":"8228 East Blvd Vancouver BC V6P 5R6",
    "addr:housenumber":"8228",
    "addr:postcode":"v6p 5r6",
    "addr:street":"East Blvd",
    "iso:country":"CA",
    "sg:address":"8228 East Blvd",
    "sg:city":"Vancouver",
    "sg:classifiers":[
        {
            "category":"Health Services",
            "subcategory":"Health Practitioner",
            "type":"Services"
        }
    ],
    "sg:phone":"+1 604 266 6924",
    "sg:postcode":"V6P 5R6",
    "sg:province":"BC",
    "sg:tags":[
        "psychologist"
    ],
    "wof:name":"Newman & Grigg Psychological",
    "wof:placetype":"venue"
},
  "geometry": {"coordinates":[-123.145523,49.211845],"type":"Point"}
}