{
  "type": "Feature",
  "properties": {
    "addr:full":"1400 Rue Montplaisir Drummondville QC J2B 7T5",
    "addr:housenumber":"1400",
    "addr:postcode":"j2b 7t5",
    "addr:street":"Rue Montplaisir",
    "iso:country":"CA",
    "sg:address":"1400 Rue Montplaisir",
    "sg:city":"Drummondville",
    "sg:classifiers":[
        {
            "category":"Organizations",
            "subcategory":"Religious Organization",
            "type":"Services"
        }
    ],
    "sg:phone":"+1 819 472 5449",
    "sg:postcode":"J2B 7T5",
    "sg:province":"QC",
    "wof:name":"Maison Marie Reine DE Coeurs",
    "wof:placetype":"venue"
},
  "geometry": {"coordinates":[-72.483437,45.889748],"type":"Point"}
}