{
  "type": "Feature",
  "properties": {
    "addr:full":"601 Agnes St New Westminster BC V3M 1G9",
    "addr:housenumber":"601",
    "addr:postcode":"v3m 1g9",
    "addr:street":"Agnes St",
    "iso:country":"CA",
    "sg:address":"601 Agnes St",
    "sg:city":"New Westminster",
    "sg:classifiers":[
        {
            "category":"Restaurant",
            "type":"Food & Drink"
        }
    ],
    "sg:phone":"+1 604 520 1808",
    "sg:postcode":"V3M 1G9",
    "sg:province":"BC",
    "wof:name":"New Richman Restaurant",
    "wof:placetype":"venue"
},
  "geometry": {"coordinates":[-122.91007999999999,49.204792],"type":"Point"}
}