{
  "type": "Feature",
  "properties": {
    "addr:full":"RR 4 STN Main Listowel ON N4W 3G9",
    "addr:postcode":"n4w 3g9",
    "addr:street":"Rr 4 Stn Main",
    "iso:country":"CA",
    "sg:address":"RR 4 STN Main",
    "sg:city":"Listowel",
    "sg:classifiers":[
        {
            "category":"Organizations",
            "subcategory":"Religious Organization",
            "type":"Services"
        }
    ],
    "sg:phone":"+1 519 595 4961",
    "sg:postcode":"N4W 3G9",
    "sg:province":"ON",
    "sg:tags":[
        "church"
    ],
    "wof:name":"St Mary's Catholic Church",
    "wof:placetype":"venue"
},
  "geometry": {"coordinates":[-80.9537887573,43.7318191528],"type":"Point"}
}