{
  "type": "Feature",
  "properties": {
    "addr:full":"4174 15th Ave New Hazelton BC V0J 2J0",
    "addr:housenumber":"4174",
    "addr:postcode":"v0j 2j0",
    "addr:street":"15Th Ave",
    "iso:country":"CA",
    "sg:address":"4174 15th Ave",
    "sg:city":"New Hazelton",
    "sg:classifiers":[
        {
            "category":"Government",
            "subcategory":"Office",
            "type":"Public Place"
        }
    ],
    "sg:phone":"+1 250 842 6177",
    "sg:postcode":"V0J 2J0",
    "sg:province":"BC",
    "sg:tags":[
        "village"
    ],
    "wof:name":"New Hazelton Public Works",
    "wof:placetype":"venue"
},
  "geometry": {"coordinates":[-127.589493,55.242287],"type":"Point"}
}