{
  "type": "Feature",
  "properties": {
    "addr:full":"6 Rue DE L'Eglise Saint-Honore-DE-Temiscouata QC G0L 3K0",
    "addr:housenumber":"6",
    "addr:postcode":"g0l 3k0",
    "addr:street":"Rue De L'Eglise Saint-Honore-De-Temiscouata",
    "iso:country":"CA",
    "sg:address":"6 Rue DE L'Eglise",
    "sg:city":"Saint-Honore-DE-Temiscouata",
    "sg:classifiers":[
        {
            "category":"Education",
            "subcategory":"School",
            "type":"Public Place"
        }
    ],
    "sg:phone":"+1 418 497 3996",
    "sg:postcode":"G0L 3K0",
    "sg:province":"QC",
    "wof:name":"Moussaillons Ecole",
    "wof:placetype":"venue"
},
  "geometry": {"coordinates":[-69.1318435669,47.7253913879],"type":"Point"}
}