{
  "type": "Feature",
  "properties": {
    "addr:full":"1181 Rue Commerciale Saint-Jean-Chrysostome QC G6Z 3E7",
    "addr:housenumber":"1181",
    "addr:postcode":"g6z 3e7",
    "addr:street":"Rue Commerciale Saint-Jean-Chrysostome",
    "iso:country":"CA",
    "sg:address":"1181 Rue Commerciale",
    "sg:city":"Saint-Jean-Chrysostome",
    "sg:classifiers":[
        {
            "category":"Building & Trades",
            "subcategory":"Construction",
            "type":"Services"
        }
    ],
    "sg:phone":"+1 418 839 4681",
    "sg:postcode":"G6Z 3E7",
    "sg:province":"QC",
    "sg:tags":[
        "acoustical",
        "contractor"
    ],
    "wof:name":"Grenier Acoustique Inc",
    "wof:placetype":"venue"
},
  "geometry": {"coordinates":[-71.1867904663,46.7064247131],"type":"Point"}
}