{
  "type": "Feature",
  "properties": {
    "addr:full":"Normandin QC G8M 3X5",
    "addr:postcode":"g8m 3x5",
    "iso:country":"CA",
    "sg:city":"Normandin",
    "sg:classifiers":[
        {
            "category":"Personal",
            "subcategory":"Beauty Salon",
            "type":"Services"
        }
    ],
    "sg:phone":"+1 418 274 2881",
    "sg:postcode":"G8M 3X5",
    "sg:province":"QC",
    "wof:name":"Coiffure Perfection",
    "wof:placetype":"venue"
},
  "geometry": {"coordinates":[-72.51840199999999,48.84166],"type":"Point"}
}