{
  "type": "Feature",
  "properties": {
    "addr:full":"125 Bell St Ingersoll ON N5C 2N9",
    "addr:housenumber":"125",
    "addr:postcode":"n5c 2n9",
    "addr:street":"Bell St",
    "iso:country":"CA",
    "sg:address":"125 Bell St",
    "sg:city":"Ingersoll",
    "sg:classifiers":[
        {
            "category":"Autos & Motor Vehicles",
            "subcategory":"Automobile Sales",
            "type":"Retail Goods"
        }
    ],
    "sg:phone":"+1 519 485 2921",
    "sg:postcode":"N5C 2N9",
    "sg:province":"ON",
    "sg:tags":[
        "car",
        "dealer"
    ],
    "wof:name":"Midtown Motors",
    "wof:placetype":"venue"
},
  "geometry": {"coordinates":[-80.8919906616,43.0409812927],"type":"Point"}
}