{
  "type": "Feature",
  "properties": {
    "addr:full":"1450 North End Rd Salt Spring Island BC V8K 1M5",
    "addr:housenumber":"1450",
    "addr:postcode":"v8k 1m5",
    "addr:street":"North End Rd",
    "iso:country":"CA",
    "sg:address":"1450 North End Rd",
    "sg:city":"Salt Spring Island",
    "sg:classifiers":[
        {
            "category":"Travel",
            "subcategory":"Hotels & Motels",
            "type":"Entertainment"
        }
    ],
    "sg:phone":"+1 250 537 5773",
    "sg:postcode":"V8K 1M5",
    "sg:province":"BC",
    "sg:tags":[
        "resort"
    ],
    "wof:name":"Lakeside Gardens",
    "wof:placetype":"venue"
},
  "geometry": {"coordinates":[-123.535698,48.897564],"type":"Point"}
}