{
  "type": "Feature",
  "properties": {
    "iso:country":"CA",
    "sg:address":"6484 Rue Sherbrooke O",
    "sg:city":"Montreal",
    "sg:classifiers":[
        {
            "category":"Professional",
            "subcategory":"Business Services",
            "type":"Services"
        }
    ],
    "sg:phone":"+1 514 486 3680",
    "sg:postcode":"H4B 1N2",
    "sg:province":"QC",
    "sg:tags":[
        "notary"
    ],
    "wof:name":"Labreche & Assoc",
    "wof:placetype":"venue"
},
  "geometry": {"coordinates":[-73.543877,45.5811],"type":"Point"}
}