{
  "type": "Feature",
  "properties": {
    "addr:full":"801 11 St SW Calgary AB T2P 2C4",
    "addr:housenumber":"801 11",
    "addr:postcode":"t2p 2c4",
    "addr:street":"St Sw",
    "iso:country":"CA",
    "sg:address":"801 11 St SW",
    "sg:city":"Calgary",
    "sg:classifiers":[
        {
            "category":"Organizations",
            "subcategory":"Professional Association",
            "type":"Services"
        }
    ],
    "sg:phone":"+1 403 263 0300",
    "sg:postcode":"T2P 2C4",
    "sg:province":"AB",
    "wof:name":"Royal Canadian Air Cadets",
    "wof:placetype":"venue"
},
  "geometry": {"coordinates":[-114.088768,51.046169],"type":"Point"}
}