{
  "type": "Feature",
  "properties": {
    "addr:full":"5261 Coldham Rd Peachland BC V0H 1X2",
    "addr:housenumber":"5261",
    "addr:postcode":"v0h 1x2",
    "addr:street":"Coldham Rd",
    "iso:country":"CA",
    "sg:address":"5261 Coldham Rd",
    "sg:city":"Peachland",
    "sg:classifiers":[
        {
            "category":"Building & Trades",
            "subcategory":"Electrical",
            "type":"Services"
        }
    ],
    "sg:phone":"+1 250 767 3149",
    "sg:postcode":"V0H 1X2",
    "sg:province":"BC",
    "sg:tags":[
        "electric",
        "contractor"
    ],
    "wof:name":"Inter-Valley Electric",
    "wof:placetype":"venue"
},
  "geometry": {"coordinates":[-119.712524,49.7934],"type":"Point"}
}