{
  "type": "Feature",
  "properties": {
    "addr:full":"1600 Sherbrooke St W RR 3 Peterborough ON K9J 6X4",
    "addr:housenumber":"1600",
    "addr:postcode":"k9j 6x4",
    "addr:street":"Sherbrooke St W Rr 3",
    "iso:country":"CA",
    "sg:address":"1600 Sherbrooke St W RR 3",
    "sg:city":"Peterborough",
    "sg:classifiers":[
        {
            "category":"Organizations",
            "subcategory":"Religious Organization",
            "type":"Services"
        }
    ],
    "sg:phone":"+1 705 742 4338",
    "sg:postcode":"K9J 6X4",
    "sg:province":"ON",
    "sg:tags":[
        "church"
    ],
    "wof:name":"Immanuel Alliance Church",
    "wof:placetype":"venue"
},
  "geometry": {"coordinates":[-78.3709564209,44.2898902893],"type":"Point"}
}