{
  "type": "Feature",
  "properties": {
    "addr:full":"100 Place Walter Baker Kanata ON K2V 1A2",
    "addr:housenumber":"100",
    "addr:postcode":"k2v 1a2",
    "addr:street":"Place Walter Baker",
    "iso:country":"CA",
    "sg:address":"100 Place Walter Baker",
    "sg:city":"Kanata",
    "sg:classifiers":[
        {
            "category":"Arena",
            "subcategory":"Sports Club",
            "type":"Entertainment"
        }
    ],
    "sg:phone":"+1 613 580 2424",
    "sg:postcode":"K2V 1A2",
    "sg:province":"ON",
    "sg:tags":[
        "athletic",
        "fields",
        "stadium",
        "government"
    ],
    "wof:name":"Complexe Recreatif DE Kanata",
    "wof:placetype":"venue"
},
  "geometry": {"coordinates":[-75.90134399999999,45.295681],"type":"Point"}
}