{
  "type": "Feature",
  "properties": {
    "addr:full":"1 Callender St Toronto ON M6R 2H2",
    "addr:housenumber":"1",
    "addr:postcode":"m6r 2h2",
    "addr:street":"Callender St",
    "iso:country":"CA",
    "sg:address":"1 Callender St",
    "sg:city":"Toronto",
    "sg:classifiers":[
        {
            "category":"Health Services",
            "subcategory":"Doctor",
            "type":"Services"
        }
    ],
    "sg:phone":"+1 416 535 1477",
    "sg:postcode":"M6R 2H2",
    "sg:province":"ON",
    "sg:tags":[
        "dentist"
    ],
    "wof:name":"Vojnovic, Zoran DDS",
    "wof:placetype":"venue"
},
  "geometry": {"coordinates":[-79.44208500000001,43.639694],"type":"Point"}
}