{
  "type": "Feature",
  "properties": {
    "addr:full":"Cliff St Bella Coola BC V0T 1C0",
    "addr:postcode":"v0t 1c0",
    "addr:street":"Cliff St",
    "iso:country":"CA",
    "sg:address":"Cliff St",
    "sg:city":"Bella Coola",
    "sg:classifiers":[
        {
            "category":"Government",
            "subcategory":"Office",
            "type":"Public Place"
        }
    ],
    "sg:phone":"+1 250 799 5395",
    "sg:postcode":"V0T 1C0",
    "sg:province":"BC",
    "wof:name":"BC Social Services District",
    "wof:placetype":"venue"
},
  "geometry": {"coordinates":[-126.74625399999999,52.372021],"type":"Point"}
}