{
  "type": "Feature",
  "properties": {
    "addr:full":"99 Portland St #206 Dartmouth NS B2Y 1H5",
    "addr:housenumber":"99",
    "addr:postcode":"b2y 1h5",
    "addr:street":"Portland St # 206",
    "iso:country":"CA",
    "sg:address":"99 Portland St #206",
    "sg:city":"Dartmouth",
    "sg:classifiers":[
        {
            "category":"Professional",
            "subcategory":"Accounting & Tax Preparation",
            "type":"Services"
        }
    ],
    "sg:phone":"+1 902 463 9571",
    "sg:postcode":"B2Y 1H5",
    "sg:province":"NS",
    "sg:tags":[
        "accountant"
    ],
    "wof:name":"Rector, Kim CA",
    "wof:placetype":"venue"
},
  "geometry": {"coordinates":[-63.566154,44.666164],"type":"Point"}
}