{
  "type": "Feature",
  "properties": {
    "addr:full":"Richmond BC V7A 5G8",
    "addr:postcode":"v7a 5g8",
    "iso:country":"CA",
    "sg:city":"Richmond",
    "sg:classifiers":[
        {
            "category":"Manufacturing",
            "subcategory":"Textiles",
            "type":"Manufacturing & Wholesale Goods"
        }
    ],
    "sg:phone":"+1 604 275 3279",
    "sg:postcode":"V7A 5G8",
    "sg:province":"BC",
    "sg:tags":[
        "equipment",
        "motel",
        "hotel"
    ],
    "wof:name":"Chun Chung Intl Trading Ltd",
    "wof:placetype":"venue"
},
  "geometry": {"coordinates":[-123.09663399999999,49.131428],"type":"Point"}
}