{
  "type": "Feature",
  "properties": {
    "addr:full":"23 Duke St St Catharines ON L2R 5W1",
    "addr:housenumber":"23",
    "addr:postcode":"l2r 5w1",
    "addr:street":"Duke St",
    "iso:country":"CA",
    "sg:address":"23 Duke St",
    "sg:city":"St Catharines",
    "sg:classifiers":[
        {
            "category":"Wholesale",
            "subcategory":"Jewelry",
            "type":"Manufacturing & Wholesale Goods"
        }
    ],
    "sg:phone":"+1 905 685 1183",
    "sg:postcode":"L2R 5W1",
    "sg:province":"ON",
    "sg:tags":[
        "beads"
    ],
    "wof:name":"Serendipity on Duke",
    "wof:placetype":"venue"
},
  "geometry": {"coordinates":[-79.2494735718,43.1595497131],"type":"Point"}
}