{
  "type": "Feature",
  "properties": {
    "addr:full":"3814 Victoria Park Ave North York ON M2H 3H7",
    "addr:housenumber":"3814",
    "addr:postcode":"m2h 3h7",
    "addr:street":"Victoria Park Ave",
    "iso:country":"CA",
    "sg:address":"3814 Victoria Park Ave",
    "sg:city":"North York",
    "sg:classifiers":[
        {
            "category":"Wholesale",
            "subcategory":"Furniture",
            "type":"Manufacturing & Wholesale Goods"
        }
    ],
    "sg:phone":"+1 416 494 6600",
    "sg:postcode":"M2H 3H7",
    "sg:province":"ON",
    "wof:name":"Addmore Office Furniture",
    "wof:placetype":"venue"
},
  "geometry": {"coordinates":[-79.3397140503,43.8114204407],"type":"Point"}
}