{
  "type": "Feature",
  "properties": {
    "iso:country":"CA",
    "sg:city":"Vancouver",
    "sg:classifiers":[
        {
            "category":"Professional",
            "subcategory":"Engineering",
            "type":"Services"
        }
    ],
    "sg:phone":"+1 604 638 3000",
    "sg:postcode":"V6B 5T1",
    "sg:province":"BC",
    "sg:tags":[
        "engineer"
    ],
    "wof:name":"Planet Works",
    "wof:placetype":"venue"
},
  "geometry": {"coordinates":[-123.125435,49.274044],"type":"Point"}
}