{
  "type": "Feature",
  "properties": {
    "addr:full":"Scarborough ON M1T 3J7",
    "addr:postcode":"m1t 3j7",
    "iso:country":"CA",
    "sg:city":"Scarborough",
    "sg:classifiers":[
        {
            "category":"Personal",
            "subcategory":"Beauty Salon",
            "type":"Services"
        }
    ],
    "sg:phone":"+1 416 493 1635",
    "sg:postcode":"M1T 3J7",
    "sg:province":"ON",
    "sg:tags":[
        "barber"
    ],
    "wof:name":"Tony's Hairstyling For Men",
    "wof:placetype":"venue"
},
  "geometry": {"coordinates":[-79.31733699999999,43.776447],"type":"Point"}
}