{
  "type": "Feature",
  "properties": {
    "addr:full":"382 Rue Notre-Dame Est Cap-DE-LA-Madeleine QC G8T 4E2",
    "addr:housenumber":"382",
    "addr:postcode":"g8t 4e2",
    "addr:street":"Rue Notre-Dame Est",
    "iso:country":"CA",
    "sg:address":"382 Rue Notre-Dame Est",
    "sg:city":"Cap-DE-LA-Madeleine",
    "sg:classifiers":[
        {
            "category":"Travel",
            "subcategory":"Hotels & Motels",
            "type":"Entertainment"
        }
    ],
    "sg:phone":"+1 819 374 7997",
    "sg:postcode":"G8T 4E2",
    "sg:province":"QC",
    "sg:tags":[
        "breakfast",
        "accommodation",
        "bed"
    ],
    "wof:name":"Gite Du Chemin Du Roy",
    "wof:placetype":"venue"
},
  "geometry": {"coordinates":[-72.50527954099999,46.3607254028],"type":"Point"}
}