{
  "type": "Feature",
  "properties": {
    "addr:full":"1 Ch DE LA Beauce Beauharnois QC J6N 2L8",
    "addr:housenumber":"1",
    "addr:postcode":"j6n 2l8",
    "addr:street":"Ch De La Beauce",
    "iso:country":"CA",
    "sg:address":"1 Ch DE LA Beauce",
    "sg:city":"Beauharnois",
    "sg:classifiers":[
        {
            "category":"Autos & Motor Vehicles",
            "subcategory":"Automobile Sales",
            "type":"Retail Goods"
        }
    ],
    "sg:phone":"+1 450 225 5278",
    "sg:postcode":"J6N 2L8",
    "sg:province":"QC",
    "sg:tags":[
        "car",
        "dealer"
    ],
    "wof:name":"Automobiles Julien Inc",
    "wof:placetype":"venue"
},
  "geometry": {"coordinates":[-73.87146799999999,45.315907],"type":"Point"}
}