{
  "type": "Feature",
  "properties": {
    "addr:full":"449 Boul Provencher Winnipeg MB R2J 0B8",
    "addr:housenumber":"449",
    "addr:postcode":"r2j 0b8",
    "addr:street":"Boul Provencher",
    "iso:country":"CA",
    "sg:address":"449 Boul Provencher",
    "sg:city":"Winnipeg",
    "sg:classifiers":[
        {
            "category":"Professional",
            "subcategory":"Management & Consulting",
            "type":"Services"
        }
    ],
    "sg:phone":"+1 204 231 3537",
    "sg:postcode":"R2J 0B8",
    "sg:province":"MB",
    "sg:tags":[
        "consultant",
        "business"
    ],
    "wof:name":"Mid-West Training Assoc Ltd",
    "wof:placetype":"venue"
},
  "geometry": {"coordinates":[-97.109016,49.89563],"type":"Point"}
}