{
  "type": "Feature",
  "properties": {
    "addr:full":"33439 Rainbow Ave Abbotsford BC V2S 1E6",
    "addr:housenumber":"33439",
    "addr:postcode":"v2s 1e6",
    "addr:street":"Rainbow Ave",
    "iso:country":"CA",
    "sg:address":"33439 Rainbow Ave",
    "sg:city":"Abbotsford",
    "sg:classifiers":[
        {
            "category":"Insurance",
            "subcategory":"Insurance Agent",
            "type":"Services"
        }
    ],
    "sg:phone":"+1 604 852 4788",
    "sg:postcode":"V2S 1E6",
    "sg:province":"BC",
    "wof:name":"Harry Coleman Life & Health",
    "wof:placetype":"venue"
},
  "geometry": {"coordinates":[-122.297523498,49.0370559692],"type":"Point"}
}