{
  "type": "Feature",
  "properties": {
    "addr:full":"8120 Boul Metropolitain E Anjou QC H1K 1A1",
    "addr:housenumber":"8120",
    "addr:postcode":"h1k 1a1",
    "addr:street":"Boul Metropolitain E",
    "iso:country":"CA",
    "sg:address":"8120 Boul Metropolitain E",
    "sg:city":"Anjou",
    "sg:classifiers":[
        {
            "category":"Wholesale",
            "subcategory":"Machinery & Supplies",
            "type":"Manufacturing & Wholesale Goods"
        }
    ],
    "sg:phone":"+1 514 352 6112",
    "sg:postcode":"H1K 1A1",
    "sg:province":"QC",
    "sg:tags":[
        "equipment",
        "labeling"
    ],
    "wof:name":"Label-Com Tech Inc",
    "wof:placetype":"venue"
},
  "geometry": {"coordinates":[-73.5618896484,45.6092987061],"type":"Point"}
}