{
  "type": "Feature",
  "properties": {
    "addr:full":"Montreal QC H1E 6V1",
    "addr:postcode":"h1e 6v1",
    "iso:country":"CA",
    "sg:city":"Montreal",
    "sg:classifiers":[
        {
            "category":"Building & Trades",
            "subcategory":"Construction",
            "type":"Services"
        }
    ],
    "sg:phone":"+1 514 648 7884",
    "sg:postcode":"H1E 6V1",
    "sg:province":"QC",
    "sg:tags":[
        "paving",
        "landscape",
        "contractor"
    ],
    "wof:name":"Pavages & Paysagiste Delta",
    "wof:placetype":"venue"
},
  "geometry": {"coordinates":[-73.5738983154,45.6527023315],"type":"Point"}
}