{
  "type": "Feature",
  "properties": {
    "addr:full":"8715 44 St SE Calgary AB T2C 2P5",
    "addr:housenumber":"8715",
    "addr:postcode":"t2c 2p5",
    "addr:street":"44 St Se",
    "iso:country":"CA",
    "sg:address":"8715 44 St SE",
    "sg:city":"Calgary",
    "sg:classifiers":[
        {
            "category":"Freight",
            "type":"Transportation"
        }
    ],
    "sg:phone":"+1 403 720 3657",
    "sg:postcode":"T2C 2P5",
    "sg:province":"AB",
    "sg:tags":[
        "trucking"
    ],
    "wof:name":"Trical Trucking Ltd",
    "wof:placetype":"venue"
},
  "geometry": {"coordinates":[-113.97016143800001,50.9764709473],"type":"Point"}
}