{
  "type": "Feature",
  "properties": {
    "addr:full":"Ottawa ON K2P 2G3",
    "addr:postcode":"k2p 2g3",
    "iso:country":"CA",
    "sg:city":"Ottawa",
    "sg:classifiers":[
        {
            "category":"Professional",
            "subcategory":"Employment Agencies",
            "type":"Services"
        }
    ],
    "sg:phone":"+1 613 567 8886",
    "sg:postcode":"K2P 2G3",
    "sg:province":"ON",
    "sg:tags":[
        "opportunity"
    ],
    "wof:name":"Dynamic Personnel Consultants",
    "wof:placetype":"venue"
},
  "geometry": {"coordinates":[-75.6915512085,45.4172172546],"type":"Point"}
}