{
  "type": "Feature",
  "properties": {
    "iso:country":"CA",
    "sg:address":"109 Merit Cres",
    "sg:city":"West St Paul",
    "sg:classifiers":[
        {
            "category":"Building & Trades",
            "subcategory":"Plumbing",
            "type":"Services"
        }
    ],
    "sg:phone":"+1 204 940 1060",
    "sg:postcode":"R2P 2W5",
    "sg:province":"MB",
    "sg:tags":[
        "sheet",
        "work",
        "metal",
        "contractor"
    ],
    "wof:name":"D B Stainless Products",
    "wof:placetype":"venue"
},
  "geometry": {"coordinates":[-97.1153182983,49.9828910828],"type":"Point"}
}