{
  "type": "Feature",
  "properties": {
    "addr:full":"340 Cockburn St N Winnipeg MB R3M 2P5",
    "addr:housenumber":"340",
    "addr:postcode":"r3m 2p5",
    "addr:street":"Cockburn St N",
    "iso:country":"CA",
    "sg:address":"340 Cockburn St N",
    "sg:city":"Winnipeg",
    "sg:classifiers":[
        {
            "category":"Social Services",
            "subcategory":"Child Care",
            "type":"Services"
        }
    ],
    "sg:phone":"+1 204 453 6566",
    "sg:postcode":"R3M 2P5",
    "sg:province":"MB",
    "wof:name":"Earl Grey Childrens Ctr Inc",
    "wof:placetype":"venue"
},
  "geometry": {"coordinates":[-97.15057400000001,49.867836],"type":"Point"}
}