{
  "type": "Feature",
  "properties": {
    "addr:full":"251 5th Ave W Shaunavon SK S0N 2M0",
    "addr:housenumber":"251",
    "addr:postcode":"s0n 2m0",
    "addr:street":"5Th Ave W Shaunavon",
    "iso:country":"CA",
    "sg:address":"251 5th Ave W",
    "sg:city":"Shaunavon",
    "sg:classifiers":[
        {
            "category":"Education",
            "subcategory":"School",
            "type":"Public Place"
        }
    ],
    "sg:phone":"+1 306 297 2751",
    "sg:postcode":"S0N 2M0",
    "sg:province":"SK",
    "wof:name":"Shaunavon Public School",
    "wof:placetype":"venue"
},
  "geometry": {"coordinates":[-108.413979,49.647755],"type":"Point"}
}