{
  "type": "Feature",
  "properties": {
    "addr:full":"1613 Rue Royale Trois-Rivieres QC G9A 4K2",
    "addr:housenumber":"1613",
    "addr:postcode":"g9a 4k2",
    "addr:street":"Rue Royale",
    "iso:country":"CA",
    "sg:address":"1613 Rue Royale",
    "sg:city":"Trois-Rivieres",
    "sg:classifiers":[
        {
            "category":"Food & Beverages",
            "subcategory":"Groceries & Convenience Stores",
            "type":"Retail Goods"
        }
    ],
    "sg:phone":"+1 819 378 8333",
    "sg:postcode":"G9A 4K2",
    "sg:province":"QC",
    "sg:tags":[
        "grocer"
    ],
    "wof:name":"Depanneur Yogi",
    "wof:placetype":"venue"
},
  "geometry": {"coordinates":[-72.5447921753,46.3411254883],"type":"Point"}
}