{
  "type": "Feature",
  "properties": {
    "addr:full":"136 Dome Ave South Porcupine ON P0N 1H0",
    "addr:housenumber":"136",
    "addr:postcode":"p0n 1h0",
    "addr:street":"Dome Ave South",
    "iso:country":"CA",
    "sg:address":"136 Dome Ave",
    "sg:city":"South Porcupine",
    "sg:classifiers":[
        {
            "category":"Building & Trades",
            "subcategory":"Plumbing",
            "type":"Services"
        }
    ],
    "sg:phone":"+1 705 235 5825",
    "sg:postcode":"P0N 1H0",
    "sg:province":"ON",
    "sg:tags":[
        "air",
        "conditioning",
        "contractor",
        "system",
        "heating"
    ],
    "wof:name":"Canzio's Heating & Air Cond",
    "wof:placetype":"venue"
},
  "geometry": {"coordinates":[-81.207573,48.480167],"type":"Point"}
}