{
  "type": "Feature",
  "properties": {
    "addr:full":"6173 Bligh Rd Sechelt BC V0N 3A7",
    "addr:housenumber":"6173",
    "addr:postcode":"v0n 3a7",
    "addr:street":"Bligh Rd",
    "iso:country":"CA",
    "sg:address":"6173 Bligh Rd",
    "sg:city":"Sechelt",
    "sg:classifiers":[
        {
            "category":"Real Estate",
            "subcategory":"Real Estate Agent",
            "type":"Services"
        }
    ],
    "sg:phone":"+1 604 885 9683",
    "sg:postcode":"V0N 3A7",
    "sg:province":"BC",
    "wof:name":"Suncoast Estates",
    "wof:placetype":"venue"
},
  "geometry": {"coordinates":[-123.784767,49.46928],"type":"Point"}
}