{
  "type": "Feature",
  "properties": {
    "addr:full":"989 Bloor St W Toronto ON M6H 1M1",
    "addr:housenumber":"989",
    "addr:postcode":"m6h 1m1",
    "addr:street":"Bloor St W",
    "iso:country":"CA",
    "sg:address":"989 Bloor St W",
    "sg:city":"Toronto",
    "sg:classifiers":[
        {
            "category":"Home & Garden",
            "subcategory":"Furniture",
            "type":"Retail Goods"
        }
    ],
    "sg:phone":"+1 416 531 7552",
    "sg:postcode":"M6H 1M1",
    "sg:province":"ON",
    "wof:name":"Regal Furniture",
    "wof:placetype":"venue"
},
  "geometry": {"coordinates":[-79.429771,43.660889],"type":"Point"}
}