{
  "type": "Feature",
  "properties": {
    "addr:full":"3988 Still Creek Ave Burnaby BC V5C 6N9",
    "addr:housenumber":"3988",
    "addr:postcode":"v5c 6n9",
    "addr:street":"Still Creek Ave",
    "iso:country":"CA",
    "sg:address":"3988 Still Creek Ave",
    "sg:city":"Burnaby",
    "sg:classifiers":[
        {
            "category":"Manufacturing",
            "subcategory":"Printing",
            "type":"Manufacturing & Wholesale Goods"
        }
    ],
    "sg:phone":"+1 604 437 5800",
    "sg:postcode":"V5C 6N9",
    "sg:province":"BC",
    "sg:tags":[
        "printer"
    ],
    "wof:name":"Trade Business Forms Ltd",
    "wof:placetype":"venue"
},
  "geometry": {"coordinates":[-123.016197205,49.2607154846],"type":"Point"}
}