{
  "type": "Feature",
  "properties": {
    "iso:country":"CA",
    "sg:city":"Mississauga",
    "sg:classifiers":[
        {
            "category":"Professional",
            "subcategory":"Accounting & Tax Preparation",
            "type":"Services"
        }
    ],
    "sg:phone":"+1 905 282 8100",
    "sg:postcode":"L4W 4Y2",
    "sg:province":"ON",
    "sg:tags":[
        "payroll"
    ],
    "wof:name":"Ceridian Canada Ltd",
    "wof:placetype":"venue"
},
  "geometry": {"coordinates":[-79.610443,43.659924],"type":"Point"}
}