{
  "type": "Feature",
  "properties": {
    "iso:country":"CA",
    "sg:address":"640 Cathcart Blvd",
    "sg:city":"Sarnia",
    "sg:classifiers":[
        {
            "category":"Personal",
            "subcategory":"Beauty Salon",
            "type":"Services"
        }
    ],
    "sg:phone":"+1 519 344 2216",
    "sg:postcode":"N7V 2N4",
    "sg:province":"ON",
    "wof:name":"Maestro's Hair Studio",
    "wof:placetype":"venue"
},
  "geometry": {"coordinates":[-82.3890838623,43.0043334961],"type":"Point"}
}