{
  "type": "Feature",
  "properties": {
    "iso:country":"CA",
    "sg:address":"4497 Progress Dr",
    "sg:city":"Petrolia",
    "sg:classifiers":[
        {
            "category":"Freight",
            "type":"Transportation"
        }
    ],
    "sg:phone":"+1 519 882 3080",
    "sg:postcode":"N0N 1R0",
    "sg:province":"ON",
    "sg:tags":[
        "lumber",
        "commercial"
    ],
    "wof:name":"Lumberjack Building Ctr",
    "wof:placetype":"venue"
},
  "geometry": {"coordinates":[-82.1243438721,42.8874778748],"type":"Point"}
}