{
  "type": "Feature",
  "properties": {
    "addr:full":"5478 Av Westminster Cote Saint-Luc QC H4X 2A5",
    "addr:housenumber":"5478",
    "addr:postcode":"h4x 2a5",
    "addr:street":"Av Westminster Cote",
    "iso:country":"CA",
    "sg:address":"5478 Av Westminster",
    "sg:city":"Cote Saint-Luc",
    "sg:classifiers":[
        {
            "category":"Food & Beverages",
            "subcategory":"Fruits & Vegetables",
            "type":"Retail Goods"
        }
    ],
    "sg:phone":"+1 514 486 5771",
    "sg:postcode":"H4X 2A5",
    "sg:province":"QC",
    "sg:tags":[
        "produce"
    ],
    "wof:name":"M K Fruiticana",
    "wof:placetype":"venue"
},
  "geometry": {"coordinates":[-73.661682,45.459053],"type":"Point"}
}