{
  "type": "Feature",
  "properties": {
    "addr:full":"319 Brookmere Rd SW Calgary AB T2W 2P4",
    "addr:housenumber":"319",
    "addr:postcode":"t2w 2p4",
    "addr:street":"Brookmere Rd Sw",
    "iso:country":"CA",
    "sg:address":"319 Brookmere Rd SW",
    "sg:city":"Calgary",
    "sg:classifiers":[
        {
            "category":"Retail",
            "subcategory":"Repair Shop",
            "type":"Services"
        }
    ],
    "sg:phone":"+1 403 560 9095",
    "sg:postcode":"T2W 2P4",
    "sg:province":"AB",
    "sg:tags":[
        "basket",
        "bag",
        "shopping",
        "cart"
    ],
    "wof:name":"West Coast Sales & Svc Ltd",
    "wof:placetype":"venue"
},
  "geometry": {"coordinates":[-114.110596,50.959076],"type":"Point"}
}