{
  "type": "Feature",
  "properties": {
    "addr:full":"2740 Rue Notre-Dame E Montreal QC H1W 2H4",
    "addr:housenumber":"2740",
    "addr:postcode":"h1w 2h4",
    "addr:street":"Rue Notre-Dame E",
    "iso:country":"CA",
    "sg:address":"2740 Rue Notre-Dame E",
    "sg:city":"Montreal",
    "sg:classifiers":[
        {
            "category":"Wholesale",
            "subcategory":"Machinery & Supplies",
            "type":"Manufacturing & Wholesale Goods"
        }
    ],
    "sg:phone":"+1 514 526 4997",
    "sg:postcode":"H1W 2H4",
    "sg:province":"QC",
    "sg:tags":[
        "machine",
        "sewing"
    ],
    "wof:name":"New Williams CO Ltd",
    "wof:placetype":"venue"
},
  "geometry": {"coordinates":[-73.542343,45.533703],"type":"Point"}
}