{
  "type": "Feature",
  "properties": {
    "addr:full":"318 Rue Lafontaine Riviere-Du-Loup QC G5R 3B1",
    "addr:housenumber":"318",
    "addr:postcode":"g5r 3b1",
    "addr:street":"Rue Lafontaine",
    "iso:country":"CA",
    "sg:address":"318 Rue Lafontaine",
    "sg:city":"Riviere-Du-Loup",
    "sg:classifiers":[
        {
            "category":"Shopping",
            "subcategory":"Used Merchandise",
            "type":"Retail Goods"
        }
    ],
    "sg:phone":"+1 418 860 3232",
    "sg:postcode":"G5R 3B1",
    "sg:province":"QC",
    "sg:tags":[
        "flea",
        "market"
    ],
    "wof:name":"Achetons-Vendons",
    "wof:placetype":"venue"
},
  "geometry": {"coordinates":[-69.53681899999999,47.832375],"type":"Point"}
}