{
  "type": "Feature",
  "properties": {
    "addr:full":"3814 55 Ave Red Deer AB T4N 4N3",
    "addr:housenumber":"3814",
    "addr:postcode":"t4n 4n3",
    "addr:street":"55 Ave",
    "iso:country":"CA",
    "sg:address":"3814 55 Ave",
    "sg:city":"Red Deer",
    "sg:classifiers":[
        {
            "category":"Social Services",
            "type":"Services"
        }
    ],
    "sg:phone":"+1 403 341 3661",
    "sg:postcode":"T4N 4N3",
    "sg:province":"AB",
    "sg:tags":[
        "counseling"
    ],
    "wof:name":"Family-School Wellness Program",
    "wof:placetype":"venue"
},
  "geometry": {"coordinates":[-113.825935364,52.2586860657],"type":"Point"}
}