{
  "type": "Feature",
  "properties": {
    "addr:full":"3926 Roseland Dr W Windsor ON N9G 1Z5",
    "addr:housenumber":"3926",
    "addr:postcode":"n9g 1z5",
    "addr:street":"Roseland Dr W",
    "iso:country":"CA",
    "sg:address":"3926 Roseland Dr W",
    "sg:city":"Windsor",
    "sg:classifiers":[
        {
            "category":"Manufacturing",
            "subcategory":"Printing",
            "type":"Manufacturing & Wholesale Goods"
        }
    ],
    "sg:phone":"+1 519 966 4110",
    "sg:postcode":"N9G 1Z5",
    "sg:province":"ON",
    "sg:tags":[
        "printer"
    ],
    "wof:name":"Charterhouse Printing Svc",
    "wof:placetype":"venue"
},
  "geometry": {"coordinates":[-83.010323,42.254234],"type":"Point"}
}