{
  "type": "Feature",
  "properties": {
    "addr:full":"2097 Old Lakeshore Rd Burlington ON L7R 1A4",
    "addr:housenumber":"2097",
    "addr:postcode":"l7r 1a4",
    "addr:street":"Old Lakeshore Rd",
    "iso:country":"CA",
    "sg:address":"2097 Old Lakeshore Rd",
    "sg:city":"Burlington",
    "sg:classifiers":[
        {
            "category":"Personal",
            "subcategory":"Beauty Salon",
            "type":"Services"
        }
    ],
    "sg:phone":"+1 905 637 1041",
    "sg:postcode":"L7R 1A4",
    "sg:province":"ON",
    "wof:name":"Eclipse Salon",
    "wof:placetype":"venue"
},
  "geometry": {"coordinates":[-79.792053,43.326107],"type":"Point"}
}