{
  "type": "Feature",
  "properties": {
    "addr:full":"3223 Woodsdale Rd Winfield BC V4V 1X7",
    "addr:housenumber":"3223",
    "addr:postcode":"v4v 1x7",
    "addr:street":"Woodsdale Rd",
    "iso:country":"CA",
    "sg:address":"3223 Woodsdale Rd",
    "sg:city":"Winfield",
    "sg:classifiers":[
        {
            "category":"Home & Garden",
            "subcategory":"Building Materials",
            "type":"Retail Goods"
        }
    ],
    "sg:phone":"+1 250 766 2118",
    "sg:postcode":"V4V 1X7",
    "sg:province":"BC",
    "wof:name":"Lake Country Builders Mart",
    "wof:placetype":"venue"
},
  "geometry": {"coordinates":[-119.405601502,50.0245361328],"type":"Point"}
}