{
  "type": "Feature",
  "properties": {
    "addr:full":"1205 King St W Toronto ON M6K 1G2",
    "addr:housenumber":"1205",
    "addr:postcode":"m6k 1g2",
    "addr:street":"King St W",
    "iso:country":"CA",
    "sg:address":"1205 King St W",
    "sg:city":"Toronto",
    "sg:classifiers":[
        {
            "category":"Shopping",
            "subcategory":"Computers & Home Electronics",
            "type":"Retail Goods"
        }
    ],
    "sg:phone":"+1 416 344 4825",
    "sg:postcode":"M6K 1G2",
    "sg:province":"ON",
    "sg:tags":[
        "publishing"
    ],
    "wof:name":"Digital Depot",
    "wof:placetype":"venue"
},
  "geometry": {"coordinates":[-79.4269104004,43.6389007568],"type":"Point"}
}