{
  "type": "Feature",
  "properties": {
    "iso:country":"CA",
    "sg:address":"180 Rue Saint-Ignace",
    "sg:city":"Montmagny",
    "sg:classifiers":[
        {
            "category":"Retail",
            "subcategory":"Funeral Services",
            "type":"Services"
        }
    ],
    "sg:phone":"+1 418 248 4548",
    "sg:postcode":"G5V 1R9",
    "sg:province":"QC",
    "sg:tags":[
        "director"
    ],
    "wof:name":"Normand Laurent Inc",
    "wof:placetype":"venue"
},
  "geometry": {"coordinates":[-70.5506362915,46.9799537659],"type":"Point"}
}