{
  "type": "Feature",
  "properties": {
    "iso:country":"CA",
    "sg:address":"960 Franklyn Rd",
    "sg:city":"Kelowna",
    "sg:classifiers":[
        {
            "category":"Retail",
            "subcategory":"Repair Shop",
            "type":"Services"
        }
    ],
    "sg:phone":"+1 250 765 6104",
    "sg:postcode":"V1X 3V1",
    "sg:province":"BC",
    "sg:tags":[
        "appliance"
    ],
    "wof:name":"Abs Appliance Repairs",
    "wof:placetype":"venue"
},
  "geometry": {"coordinates":[-119.401215,49.900436],"type":"Point"}
}