{
  "type": "Feature",
  "properties": {
    "addr:full":"5040 Boul Samson Laval QC H7W 2J1",
    "addr:housenumber":"5040",
    "addr:postcode":"h7w 2j1",
    "addr:street":"Boul Samson",
    "iso:country":"CA",
    "sg:address":"5040 Boul Samson",
    "sg:city":"Laval",
    "sg:classifiers":[
        {
            "category":"Real Estate",
            "subcategory":"Real Estate Agent",
            "type":"Services"
        }
    ],
    "sg:phone":"+1 450 688 7371",
    "sg:postcode":"H7W 2J1",
    "sg:province":"QC",
    "wof:name":"Ram Courtier Immobilier Agree",
    "wof:placetype":"venue"
},
  "geometry": {"coordinates":[-73.76705200000001,45.526398],"type":"Point"}
}