{
  "type": "Feature",
  "properties": {
    "addr:full":"Calgary AB T2G 4G5",
    "addr:postcode":"t2g 4g5",
    "iso:country":"CA",
    "sg:city":"Calgary",
    "sg:classifiers":[
        {
            "category":"Real Estate",
            "subcategory":"Real Estate Agent",
            "type":"Services"
        }
    ],
    "sg:phone":"+1 403 264 6615",
    "sg:postcode":"T2G 4G5",
    "sg:province":"AB",
    "sg:tags":[
        "housing",
        "cooperative"
    ],
    "wof:name":"Ramsay Heights CO-OP Hsng Ltd",
    "wof:placetype":"venue"
},
  "geometry": {"coordinates":[-114.041481,51.036072],"type":"Point"}
}