{
  "type": "Feature",
  "properties": {
    "addr:full":"8878 60 Ave NW Edmonton AB T6E 6A6",
    "addr:housenumber":"8878",
    "addr:postcode":"t6e 6a6",
    "addr:street":"60 Ave Nw",
    "iso:country":"CA",
    "sg:address":"8878 60 Ave NW",
    "sg:city":"Edmonton",
    "sg:classifiers":[
        {
            "category":"Wholesale",
            "subcategory":"Auto Parts",
            "type":"Manufacturing & Wholesale Goods"
        }
    ],
    "sg:phone":"+1 780 448 0036",
    "sg:postcode":"T6E 6A6",
    "sg:province":"AB",
    "sg:tags":[
        "warranty",
        "automobile",
        "processing"
    ],
    "wof:name":"Corryn Distributors Ltd",
    "wof:placetype":"venue"
},
  "geometry": {"coordinates":[-113.463486,53.496033],"type":"Point"}
}