{
  "type": "Feature",
  "properties": {
    "addr:full":"2281 Lac Seguin Grand-Remous QC J0W 1E0",
    "addr:housenumber":"2281",
    "addr:postcode":"j0w 1e0",
    "addr:street":"Lac Seguin",
    "iso:country":"CA",
    "sg:address":"2281 Lac Seguin",
    "sg:city":"Grand-Remous",
    "sg:classifiers":[
        {
            "category":"Travel",
            "subcategory":"Campground",
            "type":"Entertainment"
        }
    ],
    "sg:phone":"+1 819 449 3285",
    "sg:postcode":"J0W 1E0",
    "sg:province":"QC",
    "sg:tags":[
        "camp",
        "fishing"
    ],
    "wof:name":"Domaine Shannon Inc",
    "wof:placetype":"venue"
},
  "geometry": {"coordinates":[-75.8990859985,46.6039848328],"type":"Point"}
}