{
  "type": "Feature",
  "properties": {
    "addr:full":"17 Rue Laurier Hull QC J8X 4C1",
    "addr:housenumber":"17",
    "addr:postcode":"j8x 4c1",
    "addr:street":"Rue Laurier",
    "iso:country":"CA",
    "sg:address":"17 Rue Laurier",
    "sg:city":"Hull",
    "sg:classifiers":[
        {
            "category":"Government",
            "subcategory":"Office",
            "type":"Public Place"
        }
    ],
    "sg:phone":"+1 819 776 8111",
    "sg:postcode":"J8X 4C1",
    "sg:province":"QC",
    "wof:name":"Quebec Substitut-Procureur",
    "wof:placetype":"venue"
},
  "geometry": {"coordinates":[-75.710854,45.427162],"type":"Point"}
}