{
  "type": "Feature",
  "properties": {
    "addr:full":"1548 Dean Park Rd North Saanich BC V8L 5E5",
    "addr:housenumber":"1548",
    "addr:postcode":"v8l 5e5",
    "addr:street":"Dean Park Rd",
    "iso:country":"CA",
    "sg:address":"1548 Dean Park Rd",
    "sg:city":"North Saanich",
    "sg:classifiers":[
        {
            "category":"Building & Trades",
            "subcategory":"Construction",
            "type":"Services"
        }
    ],
    "sg:phone":"+1 250 655 4766",
    "sg:postcode":"V8L 5E5",
    "sg:province":"BC",
    "sg:tags":[
        "concrete",
        "contractor"
    ],
    "wof:name":"Frank's Concrete",
    "wof:placetype":"venue"
},
  "geometry": {"coordinates":[-123.435081482,48.6190299988],"type":"Point"}
}