{
  "type": "Feature",
  "properties": {
    "addr:full":"562 Hillcrest Dr Fredericton NB E3A 2X7",
    "addr:housenumber":"562",
    "addr:postcode":"e3a 2x7",
    "addr:street":"Hillcrest Dr",
    "iso:country":"CA",
    "sg:address":"562 Hillcrest Dr",
    "sg:city":"Fredericton",
    "sg:classifiers":[
        {
            "category":"Real Estate",
            "subcategory":"Architect",
            "type":"Services"
        }
    ],
    "sg:phone":"+1 506 452 1993",
    "sg:postcode":"E3A 2X7",
    "sg:province":"NB",
    "wof:name":"Robertson, Ian",
    "wof:placetype":"venue"
},
  "geometry": {"coordinates":[-66.6270828247,45.9725189209],"type":"Point"}
}