{
  "type": "Feature",
  "properties": {
    "addr:full":"173 Broadway St Treherne MB R0G 2V0",
    "addr:housenumber":"173",
    "addr:postcode":"r0g 2v0",
    "addr:street":"Broadway St",
    "iso:country":"CA",
    "sg:address":"173 Broadway St",
    "sg:city":"Treherne",
    "sg:classifiers":[
        {
            "category":"Government",
            "subcategory":"Post Office",
            "type":"Public Place"
        }
    ],
    "sg:phone":"+1 204 723 2262",
    "sg:postcode":"R0G 2V0",
    "sg:province":"MB",
    "wof:name":"Canada Post Corp",
    "wof:placetype":"venue"
},
  "geometry": {"coordinates":[-98.6977157593,49.6279449463],"type":"Point"}
}