{
  "type": "Feature",
  "properties": {
    "addr:full":"1101 Cumberland St Cornwall ON K6J 4K3",
    "addr:housenumber":"1101",
    "addr:postcode":"k6j 4k3",
    "addr:street":"Cumberland St",
    "iso:country":"CA",
    "sg:address":"1101 Cumberland St",
    "sg:city":"Cornwall",
    "sg:classifiers":[
        {
            "category":"Shopping",
            "type":"Retail Goods"
        }
    ],
    "sg:phone":"+1 613 932 5712",
    "sg:postcode":"K6J 4K3",
    "sg:province":"ON",
    "sg:tags":[
        "monument"
    ],
    "wof:name":"Leclair Monuments",
    "wof:placetype":"venue"
},
  "geometry": {"coordinates":[-74.743706,45.027653],"type":"Point"}
}