{
  "type": "Feature",
  "properties": {
    "addr:full":"242 3 Ave E Drumheller AB T0J 0Y4",
    "addr:housenumber":"242",
    "addr:postcode":"t0j 0y4",
    "addr:street":"3 Ave E",
    "iso:country":"CA",
    "sg:address":"242 3 Ave E",
    "sg:city":"Drumheller",
    "sg:classifiers":[
        {
            "category":"Insurance",
            "subcategory":"Insurance Agent",
            "type":"Services"
        }
    ],
    "sg:phone":"+1 403 823 6133",
    "sg:postcode":"T0J 0Y4",
    "sg:province":"AB",
    "wof:name":"CO-Operators General Insurance",
    "wof:placetype":"venue"
},
  "geometry": {"coordinates":[-112.70425415,51.4639968872],"type":"Point"}
}