{
  "type": "Feature",
  "properties": {
    "addr:full":"35 Goldbrook Cres Richmond Hill ON L4S 1V4",
    "addr:housenumber":"35",
    "addr:postcode":"l4s 1v4",
    "addr:street":"Goldbrook Cres",
    "iso:country":"CA",
    "sg:address":"35 Goldbrook Cres",
    "sg:city":"Richmond Hill",
    "sg:classifiers":[
        {
            "category":"Building & Trades",
            "subcategory":"Construction",
            "type":"Services"
        }
    ],
    "sg:phone":"+1 905 780 8343",
    "sg:postcode":"L4S 1V4",
    "sg:province":"ON",
    "sg:tags":[
        "splicing",
        "installation",
        "electric",
        "cable",
        "contractor",
        "detection"
    ],
    "wof:name":"Energize Electric",
    "wof:placetype":"venue"
},
  "geometry": {"coordinates":[-79.41680100000001,43.88332],"type":"Point"}
}