{
  "type": "Feature",
  "properties": {
    "addr:full":"1288 42 Ave SE # 2 Calgary AB T2G 5P4",
    "addr:housenumber":"1288",
    "addr:postcode":"t2g 5p4",
    "addr:street":"42 Ave Se # 2",
    "iso:country":"CA",
    "sg:address":"1288 42 Ave SE # 2",
    "sg:city":"Calgary",
    "sg:classifiers":[
        {
            "category":"Home & Garden",
            "subcategory":"Building Materials",
            "type":"Retail Goods"
        }
    ],
    "sg:phone":"+1 403 262 7777",
    "sg:postcode":"T2G 5P4",
    "sg:province":"AB",
    "sg:tags":[
        "door"
    ],
    "wof:name":"Overhead Door CO of Calgary",
    "wof:placetype":"venue"
},
  "geometry": {"coordinates":[-114.03712463399999,51.0160446167],"type":"Point"}
}