{
  "type": "Feature",
  "properties": {
    "iso:country":"CA",
    "sg:city":"Timmins",
    "sg:classifiers":[
        {
            "category":"Manufacturing",
            "subcategory":"Tools & Machinery",
            "type":"Manufacturing & Wholesale Goods"
        }
    ],
    "sg:phone":"+1 705 267 1445",
    "sg:postcode":"P4N 7W7",
    "sg:province":"ON",
    "sg:tags":[
        "machine",
        "shop"
    ],
    "wof:name":"Rlp Machine & Steel Fabricator",
    "wof:placetype":"venue"
},
  "geometry": {"coordinates":[-81.3393936157,48.4712295532],"type":"Point"}
}