{
  "type": "Feature",
  "properties": {
    "addr:full":"118 Rue Principale E Sainte-Agathe-Des-Monts QC J8C 1K1",
    "addr:housenumber":"118",
    "addr:postcode":"j8c 1k1",
    "addr:street":"Rue Principale E Sainte-Agathe-Des-Monts",
    "iso:country":"CA",
    "sg:address":"118 Rue Principale E",
    "sg:city":"Sainte-Agathe-Des-Monts",
    "sg:classifiers":[
        {
            "category":"Insurance",
            "subcategory":"Insurance Agent",
            "type":"Services"
        }
    ],
    "sg:phone":"+1 819 326 7626",
    "sg:postcode":"J8C 1K1",
    "sg:province":"QC",
    "wof:name":"Assurance Wawanesa",
    "wof:placetype":"venue"
},
  "geometry": {"coordinates":[-74.28248600000001,46.046291],"type":"Point"}
}