{
  "type": "Feature",
  "properties": {
    "iso:country":"CA",
    "sg:address":"100 Rue Price O",
    "sg:city":"Alma",
    "sg:classifiers":[
        {
            "category":"Education",
            "subcategory":"Library",
            "type":"Public Place"
        }
    ],
    "sg:phone":"+1 418 662 6425",
    "sg:postcode":"G8B 4S1",
    "sg:province":"QC",
    "wof:name":"Centre Regional DE Svc Aux",
    "wof:placetype":"venue"
},
  "geometry": {"coordinates":[-71.6380233765,48.5513648987],"type":"Point"}
}