{
  "type": "Feature",
  "properties": {
    "addr:full":"755 Boul Saint-Jean Pointe-Claire QC H9R 5M9",
    "addr:housenumber":"755",
    "addr:postcode":"h9r 5m9",
    "addr:street":"Boul Saint-Jean",
    "iso:country":"CA",
    "sg:address":"755 Boul Saint-Jean",
    "sg:city":"Pointe-Claire",
    "sg:classifiers":[
        {
            "category":"Banks & Credit Unions",
            "subcategory":"Investment Brokerage",
            "type":"Services"
        }
    ],
    "sg:phone":"+1 514 426 1165",
    "sg:postcode":"H9R 5M9",
    "sg:province":"QC",
    "sg:tags":[
        "consultant",
        "planning",
        "financial"
    ],
    "wof:name":"Ron Barbara Financial Svc",
    "wof:placetype":"venue"
},
  "geometry": {"coordinates":[-73.8283996582,45.4671859741],"type":"Point"}
}