{
  "type": "Feature",
  "properties": {
    "addr:full":"Carleton Place ON K7C 3P2",
    "addr:postcode":"k7c 3p2",
    "iso:country":"CA",
    "sg:city":"Carleton Place",
    "sg:classifiers":[
        {
            "category":"Home & Garden",
            "subcategory":"Building Materials",
            "type":"Retail Goods"
        }
    ],
    "sg:phone":"+1 613 253 2364",
    "sg:postcode":"K7C 3P2",
    "sg:province":"ON",
    "wof:name":"Mjs Supplies",
    "wof:placetype":"venue"
},
  "geometry": {"coordinates":[-76.146812,45.14045],"type":"Point"}
}