{
  "type": "Feature",
  "properties": {
    "addr:full":"7800 Boul Taschereau # 125 Brossard QC J4X 1V7",
    "addr:housenumber":"7800",
    "addr:postcode":"j4x 1v7",
    "addr:street":"Boul Taschereau # 125",
    "iso:country":"CA",
    "sg:address":"7800 Boul Taschereau # 125",
    "sg:city":"Brossard",
    "sg:classifiers":[
        {
            "category":"Restaurant",
            "type":"Food & Drink"
        }
    ],
    "sg:phone":"+1 450 465 6010",
    "sg:postcode":"J4X 1V7",
    "sg:province":"QC",
    "sg:tags":[
        "delicatessen"
    ],
    "wof:name":"Charcuterie Fromagerie-Marche",
    "wof:placetype":"venue"
},
  "geometry": {"coordinates":[-73.46635437010001,45.4535217285],"type":"Point"}
}