{
  "type": "Feature",
  "properties": {
    "iso:country":"CA",
    "sg:city":"Scarborough",
    "sg:classifiers":[
        {
            "category":"Personal",
            "subcategory":"Beauty Salon",
            "type":"Services"
        }
    ],
    "sg:phone":"+1 416 493 7441",
    "sg:postcode":"M1W 3G5",
    "sg:province":"ON",
    "wof:name":"Modern Hair Place",
    "wof:placetype":"venue"
},
  "geometry": {"coordinates":[-79.3065490723,43.7998123169],"type":"Point"}
}