{
  "type": "Feature",
  "properties": {
    "addr:full":"Montreal QC H3B 4G7",
    "addr:postcode":"h3b 4g7",
    "iso:country":"CA",
    "sg:city":"Montreal",
    "sg:classifiers":[
        {
            "category":"Professional",
            "subcategory":"Management & Consulting",
            "type":"Services"
        }
    ],
    "sg:phone":"+1 514 879 1656",
    "sg:postcode":"H3B 4G7",
    "sg:province":"QC",
    "sg:tags":[
        "textile",
        "consultant"
    ],
    "wof:name":"Agence DE Textile Sarfa Inc",
    "wof:placetype":"venue"
},
  "geometry": {"coordinates":[-73.5703964233,45.5014419556],"type":"Point"}
}