{
  "type": "Feature",
  "properties": {
    "addr:full":"2070 Dugald Rd Winnipeg MB R2C 3G7",
    "addr:postcode":"2070;r2c 3g7",
    "addr:street":"Dugald Rd",
    "iso:country":"CA",
    "sg:address":"2070 Dugald Rd",
    "sg:city":"Winnipeg",
    "sg:classifiers":[
        {
            "category":"Recreation",
            "type":"Entertainment"
        }
    ],
    "sg:phone":"+1 204 222 1640",
    "sg:postcode":"R2C 3G7",
    "sg:province":"MB",
    "sg:tags":[
        "caterer",
        "hall",
        "auditorium"
    ],
    "wof:name":"Transcona Country Club",
    "wof:placetype":"venue"
},
  "geometry": {"coordinates":[-97.02542099999999,49.88583],"type":"Point"}
}