{
  "type": "Feature",
  "properties": {
    "addr:full":"4510 Beedie St Burnaby BC V5J 5L2",
    "addr:housenumber":"4510",
    "addr:postcode":"v5j 5l2",
    "addr:street":"Beedie St",
    "iso:country":"CA",
    "sg:address":"4510 Beedie St",
    "sg:city":"Burnaby",
    "sg:classifiers":[
        {
            "category":"Manufacturing",
            "subcategory":"Electronics",
            "type":"Manufacturing & Wholesale Goods"
        }
    ],
    "sg:phone":"+1 604 439 1099",
    "sg:postcode":"V5J 5L2",
    "sg:province":"BC",
    "sg:tags":[
        "equipment",
        "electronic",
        "supply"
    ],
    "wof:name":"Dna Data Networking",
    "wof:placetype":"venue"
},
  "geometry": {"coordinates":[-122.995476,49.190144],"type":"Point"}
}