{
  "type": "Feature",
  "properties": {
    "addr:full":"Calgary AB T2J 5N8",
    "addr:postcode":"t2j 5n8",
    "iso:country":"CA",
    "sg:city":"Calgary",
    "sg:classifiers":[
        {
            "category":"Professional",
            "subcategory":"Management & Consulting",
            "type":"Services"
        }
    ],
    "sg:phone":"+1 403 225 1064",
    "sg:postcode":"T2J 5N8",
    "sg:province":"AB",
    "sg:tags":[
        "party",
        "planning"
    ],
    "wof:name":"Happenings Special Events",
    "wof:placetype":"venue"
},
  "geometry": {"coordinates":[-114.071281433,50.9569091797],"type":"Point"}
}