{
  "type": "Feature",
  "properties": {
    "addr:full":"Les Eboulements QC G0A 2M0",
    "addr:postcode":"g0a 2m0",
    "iso:country":"CA",
    "sg:city":"Les Eboulements",
    "sg:classifiers":[
        {
            "category":"Farming",
            "subcategory":"Farm",
            "type":"Manufacturing & Wholesale Goods"
        }
    ],
    "sg:phone":"+1 418 635 2682",
    "sg:postcode":"G0A 2M0",
    "sg:province":"QC",
    "wof:name":"Ferme Eboulmontaise",
    "wof:placetype":"venue"
},
  "geometry": {"coordinates":[-70.30363464360001,47.4859886169],"type":"Point"}
}