{
  "type": "Feature",
  "properties": {
    "addr:full":"832 Boul Des Acadiens Bertrand NB E1W 1H3",
    "addr:housenumber":"832",
    "addr:postcode":"e1w 1h3",
    "addr:street":"Boul Des Acadiens Bertrand",
    "iso:country":"CA",
    "sg:address":"832 Boul Des Acadiens",
    "sg:city":"Bertrand",
    "sg:classifiers":[
        {
            "category":"Home & Garden",
            "subcategory":"Carpets & Floor Coverings",
            "type":"Retail Goods"
        }
    ],
    "sg:phone":"+1 506 727 2171",
    "sg:postcode":"E1W 1H3",
    "sg:province":"NB",
    "sg:tags":[
        "dealer",
        "rug"
    ],
    "wof:name":"Maison Du Tapis Ltee",
    "wof:placetype":"venue"
},
  "geometry": {"coordinates":[-65.057434082,47.760723114],"type":"Point"}
}