{
  "type": "Feature",
  "properties": {
    "addr:full":"102 Av Allion # A Lasalle QC H8P 2C5",
    "addr:postcode":"h8p 2c5",
    "addr:street":"102 Av Allion # A",
    "iso:country":"CA",
    "sg:address":"102 Av Allion # A",
    "sg:city":"Lasalle",
    "sg:classifiers":[
        {
            "category":"Building & Trades",
            "subcategory":"Electrical",
            "type":"Services"
        }
    ],
    "sg:phone":"+1 514 366 5484",
    "sg:postcode":"H8P 2C5",
    "sg:province":"QC",
    "sg:tags":[
        "electric",
        "contractor"
    ],
    "wof:name":"Maurice Electric",
    "wof:placetype":"venue"
},
  "geometry": {"coordinates":[-73.58931,45.433357],"type":"Point"}
}