{
  "type": "Feature",
  "properties": {
    "addr:full":"105 Richvale Dr N Brampton ON L6Z 1Y6",
    "addr:housenumber":"105",
    "addr:postcode":"l6z 1y6",
    "addr:street":"Richvale Dr N",
    "iso:country":"CA",
    "sg:address":"105 Richvale Dr N",
    "sg:city":"Brampton",
    "sg:classifiers":[
        {
            "category":"Education",
            "subcategory":"School",
            "type":"Public Place"
        }
    ],
    "sg:phone":"+1 905 846 0576",
    "sg:postcode":"L6Z 1Y6",
    "sg:province":"ON",
    "wof:name":"Robert H Lagerquist Pub School",
    "wof:placetype":"venue"
},
  "geometry": {"coordinates":[-79.79529599999999,43.731861],"type":"Point"}
}