{
  "type": "Feature",
  "properties": {
    "iso:country":"CA",
    "sg:address":"50 Park Bay St",
    "sg:city":"New Bothwell",
    "sg:classifiers":[
        {
            "category":"Organizations",
            "subcategory":"Professional Association",
            "type":"Services"
        }
    ],
    "sg:phone":"+1 204 388 4271",
    "sg:postcode":"R0A 1C0",
    "sg:province":"MB",
    "sg:tags":[
        "club"
    ],
    "wof:name":"New Bothwell Community Club",
    "wof:placetype":"venue"
},
  "geometry": {"coordinates":[-96.88916778559999,49.5896034241],"type":"Point"}
}