{
  "type": "Feature",
  "properties": {
    "addr:full":"Saint-Raphael QC G0R 4C0",
    "addr:postcode":"g0r 4c0",
    "iso:country":"CA",
    "sg:city":"Saint-Raphael",
    "sg:classifiers":[
        {
            "category":"Wholesale",
            "subcategory":"Construction Materials",
            "type":"Manufacturing & Wholesale Goods"
        }
    ],
    "sg:phone":"+1 418 243 2109",
    "sg:postcode":"G0R 4C0",
    "sg:province":"QC",
    "sg:tags":[
        "concrete",
        "sand",
        "gravel"
    ],
    "wof:name":"Unibeton",
    "wof:placetype":"venue"
},
  "geometry": {"coordinates":[-70.76494599999999,46.802242],"type":"Point"}
}