{
  "type": "Feature",
  "properties": {
    "iso:country":"CA",
    "sg:address":"Grand Bay West Rd",
    "sg:city":"Channel-Port-Aux-Basques",
    "sg:classifiers":[
        {
            "category":"Organizations",
            "subcategory":"Professional Association",
            "type":"Services"
        }
    ],
    "sg:phone":"+1 709 695 3153",
    "sg:postcode":"A0M 1C0",
    "sg:province":"NL",
    "sg:tags":[
        "club"
    ],
    "wof:name":"Kinsmen Club-Port Aux Basques",
    "wof:placetype":"venue"
},
  "geometry": {"coordinates":[-59.1847496033,47.5932884216],"type":"Point"}
}