{
  "type": "Feature",
  "properties": {
    "iso:country":"CA",
    "sg:address":"1149 King Rd",
    "sg:city":"Burlington",
    "sg:classifiers":[
        {
            "category":"Retail",
            "subcategory":"Car Wash",
            "type":"Services"
        }
    ],
    "sg:phone":"+1 905 681 7688",
    "sg:postcode":"L7R 3X5",
    "sg:province":"ON",
    "sg:tags":[
        "polishing",
        "washing",
        "cleaning"
    ],
    "wof:name":"Sparklewash",
    "wof:placetype":"venue"
},
  "geometry": {"coordinates":[-79.8379898071,43.3258514404],"type":"Point"}
}