{
  "type": "Feature",
  "properties": {
    "iso:country":"CA",
    "sg:address":"10044 108 St NW",
    "sg:city":"Edmonton",
    "sg:classifiers":[
        {
            "category":"Professional",
            "type":"Services"
        }
    ],
    "sg:phone":"+1 780 412 0149",
    "sg:postcode":"T5J 3S7",
    "sg:province":"AB",
    "sg:tags":[
        "establishment"
    ],
    "wof:name":"Trammell Crow Corporate Svc",
    "wof:placetype":"venue"
},
  "geometry": {"coordinates":[-113.506821,53.539795],"type":"Point"}
}