{
  "type": "Feature",
  "properties": {
    "addr:full":"6267 Amherst Shore Northport NS B0L 1E0",
    "addr:housenumber":"6267",
    "addr:postcode":"b0l 1e0",
    "addr:street":"Amherst",
    "iso:country":"CA",
    "sg:address":"6267 Amherst Shore",
    "sg:city":"Northport",
    "sg:classifiers":[
        {
            "category":"Building & Trades",
            "subcategory":"Electrical",
            "type":"Services"
        }
    ],
    "sg:phone":"+1 902 661 0107",
    "sg:postcode":"B0L 1E0",
    "sg:province":"NS",
    "sg:tags":[
        "electric",
        "contractor"
    ],
    "wof:name":"Shore Line Electric",
    "wof:placetype":"venue"
},
  "geometry": {"coordinates":[-63.8635597229,45.9311904907],"type":"Point"}
}