{
  "type": "Feature",
  "properties": {
    "iso:country":"CA",
    "sg:city":"Thornhill",
    "sg:classifiers":[
        {
            "category":"Retail",
            "subcategory":"Veterinary Services",
            "type":"Services"
        }
    ],
    "sg:phone":"+1 905 771 9855",
    "sg:postcode":"L4J 7Y3",
    "sg:province":"ON",
    "sg:tags":[
        "veterinarian"
    ],
    "wof:name":"Centre Street Animal Hospital",
    "wof:placetype":"venue"
},
  "geometry": {"coordinates":[-79.449944,43.810097],"type":"Point"}
}