{
  "type": "Feature",
  "properties": {
    "addr:full":"2660 Rue Sabourin Saint-Laurent QC H4S 1M2",
    "addr:housenumber":"2660",
    "addr:postcode":"h4s 1m2",
    "addr:street":"Rue Sabourin",
    "iso:country":"CA",
    "sg:address":"2660 Rue Sabourin",
    "sg:city":"Saint-Laurent",
    "sg:classifiers":[
        {
            "category":"Home & Garden",
            "subcategory":"Home Furnishings",
            "type":"Retail Goods"
        }
    ],
    "sg:phone":"+1 514 339 9595",
    "sg:postcode":"H4S 1M2",
    "sg:province":"QC",
    "sg:tags":[
        "venetian",
        "blind",
        "supply"
    ],
    "wof:name":"Irotex Inc",
    "wof:placetype":"venue"
},
  "geometry": {"coordinates":[-73.7507553101,45.4935417175],"type":"Point"}
}