{
  "type": "Feature",
  "properties": {
    "iso:country":"CA",
    "sg:city":"Simcoe",
    "sg:classifiers":[
        {
            "category":"Retail",
            "subcategory":"Repair Shop",
            "type":"Services"
        }
    ],
    "sg:phone":"+1 519 426 6804",
    "sg:postcode":"N3Y 4K3",
    "sg:province":"ON",
    "sg:tags":[
        "upholsterer"
    ],
    "wof:name":"Joe's Upholstery",
    "wof:placetype":"venue"
},
  "geometry": {"coordinates":[-80.28940582280001,42.8613815308],"type":"Point"}
}