{
  "type": "Feature",
  "properties": {
    "addr:full":"863 Red River Rd Thunder Bay ON P7B 1K3",
    "addr:housenumber":"863",
    "addr:postcode":"p7b 1k3",
    "addr:street":"Red River Rd",
    "iso:country":"CA",
    "sg:address":"863 Red River Rd",
    "sg:city":"Thunder Bay",
    "sg:classifiers":[
        {
            "category":"Restaurant",
            "type":"Food & Drink"
        }
    ],
    "sg:phone":"+1 807 767 2181",
    "sg:postcode":"P7B 1K3",
    "sg:province":"ON",
    "wof:name":"Eddy Lee's Chinese Restaurant",
    "wof:placetype":"venue"
},
  "geometry": {"coordinates":[-89.24865,48.446274],"type":"Point"}
}