{
  "type": "Feature",
  "properties": {
    "addr:full":"3200 Dundas St W Toronto ON M6P 2A3",
    "addr:housenumber":"3200",
    "addr:postcode":"m6p 2a3",
    "addr:street":"Dundas St W",
    "iso:country":"CA",
    "sg:address":"3200 Dundas St W",
    "sg:city":"Toronto",
    "sg:classifiers":[
        {
            "category":"Organizations",
            "subcategory":"Religious Organization",
            "type":"Services"
        }
    ],
    "sg:phone":"+1 416 767 5086",
    "sg:postcode":"M6P 2A3",
    "sg:province":"ON",
    "sg:tags":[
        "church"
    ],
    "wof:name":"Church of God of Prophecy",
    "wof:placetype":"venue"
},
  "geometry": {"coordinates":[-79.4767913818,43.6656799316],"type":"Point"}
}