{
  "type": "Feature",
  "properties": {
    "addr:full":"60 Gray Rd Stoney Creek ON L8G 2X5",
    "addr:housenumber":"60",
    "addr:postcode":"l8g 2x5",
    "addr:street":"Gray Rd",
    "iso:country":"CA",
    "sg:address":"60 Gray Rd",
    "sg:city":"Stoney Creek",
    "sg:classifiers":[
        {
            "category":"Education",
            "subcategory":"School",
            "type":"Public Place"
        }
    ],
    "sg:phone":"+1 905 664 4854",
    "sg:postcode":"L8G 2X5",
    "sg:province":"ON",
    "wof:name":"St Martin of Tours School",
    "wof:placetype":"venue"
},
  "geometry": {"coordinates":[-79.747108,43.215488],"type":"Point"}
}