{
  "type": "Feature",
  "properties": {
    "addr:full":"1040 Coxwell Ave East York ON M4C 3G5",
    "addr:housenumber":"1040",
    "addr:postcode":"m4c 3g5",
    "addr:street":"Coxwell Ave",
    "iso:country":"CA",
    "sg:address":"1040 Coxwell Ave",
    "sg:city":"East York",
    "sg:classifiers":[
        {
            "category":"Food & Beverages",
            "subcategory":"Bakery",
            "type":"Retail Goods"
        }
    ],
    "sg:phone":"+1 416 422 3700",
    "sg:postcode":"M4C 3G5",
    "sg:province":"ON",
    "sg:tags":[
        "baker"
    ],
    "wof:name":"Sweet Indulgence",
    "wof:placetype":"venue"
},
  "geometry": {"coordinates":[-79.329308,43.696827],"type":"Point"}
}