{
  "type": "Feature",
  "properties": {
    "iso:country":"CA",
    "sg:address":"Main St #1",
    "sg:city":"Manning",
    "sg:classifiers":[
        {
            "category":"Building & Trades",
            "subcategory":"Equipment Rental",
            "type":"Services"
        }
    ],
    "sg:phone":"+1 780 836 3940",
    "sg:postcode":"T0H 2M0",
    "sg:province":"AB",
    "sg:tags":[
        "player",
        "recorder",
        "video"
    ],
    "wof:name":"Movietown",
    "wof:placetype":"venue"
},
  "geometry": {"coordinates":[-117.62454200000001,56.929913],"type":"Point"}
}