{
  "type": "Feature",
  "properties": {
    "iso:country":"CA",
    "sg:address":"120 Montee Saint-Regis",
    "sg:city":"Saint-Constant",
    "sg:classifiers":[
        {
            "category":"Manufacturing",
            "subcategory":"Tools & Machinery",
            "type":"Manufacturing & Wholesale Goods"
        }
    ],
    "sg:phone":"+1 450 638 4050",
    "sg:postcode":"J5A 2E7",
    "sg:province":"QC",
    "sg:tags":[
        "truck"
    ],
    "wof:name":"Diesels Mp Inc",
    "wof:placetype":"venue"
},
  "geometry": {"coordinates":[-73.58242797849999,45.3692207336],"type":"Point"}
}