{
  "type": "Feature",
  "properties": {
    "addr:full":"4265 Lougheed Hwy Burnaby BC V5C 3Y6",
    "addr:housenumber":"4265",
    "addr:postcode":"v5c 3y6",
    "addr:street":"Lougheed Hwy",
    "iso:country":"CA",
    "sg:address":"4265 Lougheed Hwy",
    "sg:city":"Burnaby",
    "sg:classifiers":[
        {
            "category":"Shopping",
            "subcategory":"Stationery & Office Supplies",
            "type":"Retail Goods"
        }
    ],
    "sg:phone":"+1 604 320 6800",
    "sg:postcode":"V5C 3Y6",
    "sg:province":"BC",
    "wof:name":"Staples",
    "wof:placetype":"venue"
},
  "geometry": {"coordinates":[-123.009811,49.26659],"type":"Point"}
}