{
  "type": "Feature",
  "properties": {
    "addr:full":"Abbotsford BC V2S 6Y5",
    "addr:postcode":"v2s 6y5",
    "iso:country":"CA",
    "sg:city":"Abbotsford",
    "sg:classifiers":[
        {
            "category":"Home & Garden",
            "subcategory":"Building Materials",
            "type":"Retail Goods"
        }
    ],
    "sg:phone":"+1 604 852 5925",
    "sg:postcode":"V2S 6Y5",
    "sg:province":"BC",
    "sg:tags":[
        "type",
        "door"
    ],
    "wof:name":"Superior Door Svc",
    "wof:placetype":"venue"
},
  "geometry": {"coordinates":[-122.27694700000001,49.038788],"type":"Point"}
}