{
  "type": "Feature",
  "properties": {
    "addr:full":"721 King George Hwy Miramichi NB E1V 1P5",
    "addr:housenumber":"721",
    "addr:postcode":"e1v 1p5",
    "addr:street":"King George Hwy",
    "iso:country":"CA",
    "sg:address":"721 King George Hwy",
    "sg:city":"Miramichi",
    "sg:classifiers":[
        {
            "category":"Personal",
            "subcategory":"Beauty Salon",
            "type":"Services"
        }
    ],
    "sg:phone":"+1 506 624 9313",
    "sg:postcode":"E1V 1P5",
    "sg:province":"NB",
    "wof:name":"Shirley's Hair Haven",
    "wof:placetype":"venue"
},
  "geometry": {"coordinates":[-65.56285095210001,47.0096244812],"type":"Point"}
}