{
  "type": "Feature",
  "properties": {
    "addr:full":"5836 Dunn St Niagara Falls ON L2G 2N7",
    "addr:housenumber":"5836",
    "addr:postcode":"l2g 2n7",
    "addr:street":"Dunn St",
    "iso:country":"CA",
    "sg:address":"5836 Dunn St",
    "sg:city":"Niagara Falls",
    "sg:classifiers":[
        {
            "category":"Building & Trades",
            "subcategory":"Plumbing",
            "type":"Services"
        }
    ],
    "sg:phone":"+1 905 354 9032",
    "sg:postcode":"L2G 2N7",
    "sg:province":"ON",
    "sg:tags":[
        "contractor"
    ],
    "wof:name":"Metro Plumbing & Heating",
    "wof:placetype":"venue"
},
  "geometry": {"coordinates":[-79.089355,43.078819],"type":"Point"}
}