{
  "type": "Feature",
  "properties": {
    "addr:full":"163 Main St Woodstock ON N4S 1T1",
    "addr:housenumber":"163",
    "addr:postcode":"n4s 1t1",
    "addr:street":"Main St",
    "iso:country":"CA",
    "sg:address":"163 Main St",
    "sg:city":"Woodstock",
    "sg:classifiers":[
        {
            "category":"Building & Trades",
            "subcategory":"Construction",
            "type":"Services"
        }
    ],
    "sg:phone":"+1 519 537 3404",
    "sg:postcode":"N4S 1T1",
    "sg:province":"ON",
    "sg:tags":[
        "general",
        "contractor"
    ],
    "wof:name":"James A Vance Construction Ltd",
    "wof:placetype":"venue"
},
  "geometry": {"coordinates":[-80.7686920166,43.1259651184],"type":"Point"}
}