{
  "type": "Feature",
  "properties": {
    "addr:full":"5449 Ladner Trunk Rd Delta BC V4K 1W6",
    "addr:housenumber":"5449",
    "addr:postcode":"v4k 1w6",
    "addr:street":"Ladner Trunk Rd",
    "iso:country":"CA",
    "sg:address":"5449 Ladner Trunk Rd",
    "sg:city":"Delta",
    "sg:classifiers":[
        {
            "category":"Food & Beverages",
            "subcategory":"Liquor & Beverages",
            "type":"Retail Goods"
        }
    ],
    "sg:phone":"+1 604 946 2038",
    "sg:postcode":"V4K 1W6",
    "sg:province":"BC",
    "sg:tags":[
        "pub"
    ],
    "wof:name":"Landing Pub & Grill",
    "wof:placetype":"venue"
},
  "geometry": {"coordinates":[-123.07270813,49.0903205872],"type":"Point"}
}