{
  "type": "Feature",
  "properties": {
    "addr:full":"1005 Kensington Ave Burnaby BC V5B 4B8",
    "addr:housenumber":"1005",
    "addr:postcode":"v5b 4b8",
    "addr:street":"Kensington Ave",
    "iso:country":"CA",
    "sg:address":"1005 Kensington Ave",
    "sg:city":"Burnaby",
    "sg:classifiers":[
        {
            "category":"Organizations",
            "subcategory":"Religious Organization",
            "type":"Services"
        }
    ],
    "sg:phone":"+1 604 299 3915",
    "sg:postcode":"V5B 4B8",
    "sg:province":"BC",
    "sg:tags":[
        "church"
    ],
    "wof:name":"Faith Lutheran Church Preschl",
    "wof:placetype":"venue"
},
  "geometry": {"coordinates":[-122.970100403,49.2750358582],"type":"Point"}
}