{
  "type": "Feature",
  "properties": {
    "addr:full":"200 Adam St Belleville ON K8N 5S4",
    "addr:housenumber":"200",
    "addr:postcode":"k8n 5s4",
    "addr:street":"Adam St",
    "iso:country":"CA",
    "sg:address":"200 Adam St",
    "sg:city":"Belleville",
    "sg:classifiers":[
        {
            "category":"Retail",
            "subcategory":"Auto Repair",
            "type":"Services"
        }
    ],
    "sg:phone":"+1 613 966 1017",
    "sg:postcode":"K8N 5S4",
    "sg:province":"ON",
    "sg:tags":[
        "fuel",
        "equipment",
        "injection"
    ],
    "wof:name":"First Diesel Injection Svc Ltd",
    "wof:placetype":"venue"
},
  "geometry": {"coordinates":[-77.37977600000001,44.191875],"type":"Point"}
}