{
  "type": "Feature",
  "properties": {
    "addr:full":"1055 Rue Laurier Rockland ON K4K 1E3",
    "addr:housenumber":"1055",
    "addr:postcode":"k4k 1e3",
    "addr:street":"Rue Laurier",
    "iso:country":"CA",
    "sg:address":"1055 Rue Laurier",
    "sg:city":"Rockland",
    "sg:classifiers":[
        {
            "category":"Food & Beverages",
            "subcategory":"Groceries & Convenience Stores",
            "type":"Retail Goods"
        }
    ],
    "sg:phone":"+1 613 446 5444",
    "sg:postcode":"K4K 1E3",
    "sg:province":"ON",
    "wof:name":"Mac's Convenience Stores Ltd",
    "wof:placetype":"venue"
},
  "geometry": {"coordinates":[-75.2804107666,45.5538253784],"type":"Point"}
}