{
  "type": "Feature",
  "properties": {
    "addr:full":"11004 205 St NW Edmonton AB T5S 1Z4",
    "addr:housenumber":"11004",
    "addr:postcode":"t5s 1z4",
    "addr:street":"205 St Nw",
    "iso:country":"CA",
    "sg:address":"11004 205 St NW",
    "sg:city":"Edmonton",
    "sg:classifiers":[
        {
            "category":"Wholesale",
            "subcategory":"Construction Materials",
            "type":"Manufacturing & Wholesale Goods"
        }
    ],
    "sg:phone":"+1 780 453 2400",
    "sg:postcode":"T5S 1Z4",
    "sg:province":"AB",
    "sg:tags":[
        "lumber"
    ],
    "wof:name":"Mayfair Lumber Sales Ltd",
    "wof:placetype":"venue"
},
  "geometry": {"coordinates":[-113.67390399999999,53.556984],"type":"Point"}
}