{
  "type": "Feature",
  "properties": {
    "addr:full":"Brandon MB R7A 5A8",
    "addr:postcode":"r7a 5a8",
    "iso:country":"CA",
    "sg:city":"Brandon",
    "sg:classifiers":[
        {
            "category":"Health Services",
            "subcategory":"Optometrist",
            "type":"Services"
        }
    ],
    "sg:phone":"+1 204 727 5438",
    "sg:postcode":"R7A 5A8",
    "sg:province":"MB",
    "wof:name":"Varsity Eye Ctr",
    "wof:placetype":"venue"
},
  "geometry": {"coordinates":[-99.96166229249999,49.8449516296],"type":"Point"}
}