{
  "type": "Feature",
  "properties": {
    "addr:full":"527 Bronson Ave Ottawa ON K1R 6K1",
    "addr:housenumber":"527",
    "addr:postcode":"k1r 6k1",
    "addr:street":"Bronson Ave",
    "iso:country":"CA",
    "sg:address":"527 Bronson Ave",
    "sg:city":"Ottawa",
    "sg:classifiers":[
        {
            "category":"Shopping",
            "subcategory":"Discount & Variety Stores",
            "type":"Retail Goods"
        }
    ],
    "sg:phone":"+1 613 236 3254",
    "sg:postcode":"K1R 6K1",
    "sg:province":"ON",
    "wof:name":"Variety Food Mart",
    "wof:placetype":"venue"
},
  "geometry": {"coordinates":[-75.70251500000001,45.406097],"type":"Point"}
}