{
  "type": "Feature",
  "properties": {
    "iso:country":"CA",
    "sg:address":"1065 Main St",
    "sg:city":"Smithers",
    "sg:classifiers":[
        {
            "category":"Shopping",
            "subcategory":"Used Merchandise",
            "type":"Retail Goods"
        }
    ],
    "sg:phone":"+1 250 847 1501",
    "sg:postcode":"V0J 2N0",
    "sg:province":"BC",
    "sg:tags":[
        "shop",
        "thrift"
    ],
    "wof:name":"Salvation Army Thrift Store",
    "wof:placetype":"venue"
},
  "geometry": {"coordinates":[-127.173866272,54.7789421082],"type":"Point"}
}