{
  "type": "Feature",
  "properties": {
    "iso:country":"CA",
    "sg:address":"1822 Dundas St",
    "sg:city":"London",
    "sg:classifiers":[
        {
            "category":"Insurance",
            "subcategory":"Insurance Agent",
            "type":"Services"
        }
    ],
    "sg:phone":"+1 519 453 4572",
    "sg:postcode":"N5W 3E8",
    "sg:province":"ON",
    "wof:name":"State Farm Insurance CO",
    "wof:placetype":"venue"
},
  "geometry": {"coordinates":[-81.180489,43.003544],"type":"Point"}
}