{
  "type": "Feature",
  "properties": {
    "addr:full":"10608 107 Ave NW Edmonton AB T5H 0W4",
    "addr:housenumber":"10608",
    "addr:postcode":"t5h 0w4",
    "addr:street":"107 Ave Nw",
    "iso:country":"CA",
    "sg:address":"10608 107 Ave NW",
    "sg:city":"Edmonton",
    "sg:classifiers":[
        {
            "category":"Autos & Motor Vehicles",
            "subcategory":"Fuel & Gas Station",
            "type":"Retail Goods"
        }
    ],
    "sg:phone":"+1 780 421 8696",
    "sg:postcode":"T5H 0W4",
    "sg:province":"AB",
    "sg:tags":[
        "oil"
    ],
    "wof:name":"Churchill Husky",
    "wof:placetype":"venue"
},
  "geometry": {"coordinates":[-113.50322,53.551556],"type":"Point"}
}