{
  "type": "Feature",
  "properties": {
    "addr:full":"390 Topsail Rd St. John's NL A1E 2B8",
    "addr:housenumber":"390",
    "addr:postcode":"a1e 2b8",
    "addr:street":"Topsail Rd",
    "iso:country":"CA",
    "sg:address":"390 Topsail Rd",
    "sg:city":"St. John's",
    "sg:classifiers":[
        {
            "category":"Autos & Motor Vehicles",
            "subcategory":"Fuel & Gas Station",
            "type":"Retail Goods"
        }
    ],
    "sg:phone":"+1 709 364 5824",
    "sg:postcode":"A1E 2B8",
    "sg:province":"NL",
    "sg:tags":[
        "oil"
    ],
    "wof:name":"Canadian Tire Petroleum",
    "wof:placetype":"venue"
},
  "geometry": {"coordinates":[-52.744781,47.535496],"type":"Point"}
}