{
  "type": "Feature",
  "properties": {
    "addr:full":"3257 Rue Masson Montreal QC H1X 1R3",
    "addr:housenumber":"3257",
    "addr:postcode":"h1x 1r3",
    "addr:street":"Rue Masson",
    "iso:country":"CA",
    "sg:address":"3257 Rue Masson",
    "sg:city":"Montreal",
    "sg:classifiers":[
        {
            "category":"Health Services",
            "subcategory":"Optometrist",
            "type":"Services"
        }
    ],
    "sg:phone":"+1 514 376 1039",
    "sg:postcode":"H1X 1R3",
    "sg:province":"QC",
    "wof:name":"Clinique Optometrique DE Rsmt",
    "wof:placetype":"venue"
},
  "geometry": {"coordinates":[-73.57312011720001,45.5510826111],"type":"Point"}
}