{
  "type": "Feature",
  "properties": {
    "addr:full":"10416 Lakeshore Rd W Port Colborne ON L3K 5V4",
    "addr:housenumber":"10416",
    "addr:postcode":"l3k 5v4",
    "addr:street":"Lakeshore Rd W",
    "iso:country":"CA",
    "sg:address":"10416 Lakeshore Rd W",
    "sg:city":"Port Colborne",
    "sg:classifiers":[
        {
            "category":"Restaurant",
            "type":"Food & Drink"
        }
    ],
    "sg:phone":"+1 905 834 0586",
    "sg:postcode":"L3K 5V4",
    "sg:province":"ON",
    "wof:name":"Sugar's Too Fish & Grill House",
    "wof:placetype":"venue"
},
  "geometry": {"coordinates":[-79.280266,42.873859],"type":"Point"}
}