{
  "type": "Feature",
  "properties": {
    "addr:full":"2037 4th Ave W Vancouver BC V6J 1N3",
    "addr:housenumber":"2037",
    "addr:postcode":"v6j 1n3",
    "addr:street":"4Th Ave W",
    "iso:country":"CA",
    "sg:address":"2037 4th Ave W",
    "sg:city":"Vancouver",
    "sg:classifiers":[
        {
            "category":"Manufacturing",
            "subcategory":"Food",
            "type":"Manufacturing & Wholesale Goods"
        }
    ],
    "sg:phone":"+1 604 739 0475",
    "sg:postcode":"V6J 1N3",
    "sg:province":"BC",
    "sg:tags":[
        "cocoa",
        "chocolate"
    ],
    "wof:name":"Chocolate Arts",
    "wof:placetype":"venue"
},
  "geometry": {"coordinates":[-123.151276,49.268269],"type":"Point"}
}