{
  "type": "Feature",
  "properties": {
    "addr:full":"1972 Rue Tillemont Montreal QC H2E 1E1",
    "addr:housenumber":"1972",
    "addr:postcode":"h2e 1e1",
    "addr:street":"Rue Tillemont",
    "iso:country":"CA",
    "sg:address":"1972 Rue Tillemont",
    "sg:city":"Montreal",
    "sg:classifiers":[
        {
            "category":"Personal",
            "subcategory":"Beauty Salon",
            "type":"Services"
        }
    ],
    "sg:phone":"+1 514 728 1521",
    "sg:postcode":"H2E 1E1",
    "sg:province":"QC",
    "wof:name":"Salon Nasseau",
    "wof:placetype":"venue"
},
  "geometry": {"coordinates":[-73.6147232056,45.553401947],"type":"Point"}
}