{
  "type": "Feature",
  "properties": {
    "iso:country":"CA",
    "sg:address":"58 Boul Greber",
    "sg:city":"Gatineau",
    "sg:classifiers":[
        {
            "category":"Shopping",
            "subcategory":"Jewelry",
            "type":"Retail Goods"
        }
    ],
    "sg:phone":"+1 819 561 2400",
    "sg:postcode":"J8T 3P8",
    "sg:province":"QC",
    "sg:tags":[
        "jeweler"
    ],
    "wof:name":"Bijoutiere Lamoureux",
    "wof:placetype":"venue"
},
  "geometry": {"coordinates":[-75.700081,45.462025],"type":"Point"}
}