{
  "type": "Feature",
  "properties": {
    "addr:full":"6835 Boul Gouin E Montreal-Nord QC H1G 6M4",
    "addr:housenumber":"6835",
    "addr:postcode":"h1g 6m4",
    "addr:street":"Boul Gouin E",
    "iso:country":"CA",
    "sg:address":"6835 Boul Gouin E",
    "sg:city":"Montreal-Nord",
    "sg:classifiers":[
        {
            "category":"Health Services",
            "subcategory":"Nursing And Care Facility",
            "type":"Services"
        }
    ],
    "sg:phone":"+1 514 329 5434",
    "sg:postcode":"H1G 6M4",
    "sg:province":"QC",
    "sg:tags":[
        "home",
        "rest"
    ],
    "wof:name":"Soins Infirmiers Lsc Inc",
    "wof:placetype":"venue"
},
  "geometry": {"coordinates":[-73.6214981079,45.6277923584],"type":"Point"}
}