{
  "type": "Feature",
  "properties": {
    "iso:country":"CA",
    "sg:address":"2561 Rue Lacordaire",
    "sg:city":"Montreal",
    "sg:classifiers":[
        {
            "category":"Building & Trades",
            "subcategory":"Plumbing",
            "type":"Services"
        }
    ],
    "sg:phone":"+1 514 257 1086",
    "sg:postcode":"H1N 2M3",
    "sg:province":"QC",
    "sg:tags":[
        "contractor"
    ],
    "wof:name":"Plomberie Daniel Leonard",
    "wof:placetype":"venue"
},
  "geometry": {"coordinates":[-73.538101,45.571568],"type":"Point"}
}