{
  "type": "Feature",
  "properties": {
    "iso:country":"CA",
    "sg:city":"Radisson",
    "sg:classifiers":[
        {
            "category":"Food & Beverages",
            "subcategory":"Groceries & Convenience Stores",
            "type":"Retail Goods"
        }
    ],
    "sg:phone":"+1 819 638 7255",
    "sg:postcode":"J0Y 2X0",
    "sg:province":"QC",
    "sg:tags":[
        "grocer"
    ],
    "wof:name":"Distributions Radis-Nord Inc",
    "wof:placetype":"venue"
},
  "geometry": {"coordinates":[-77.66571044920001,53.7306251526],"type":"Point"}
}