{
  "type": "Feature",
  "properties": {
    "addr:full":"Scarborough ON M1S 3Y6",
    "addr:postcode":"m1s 3y6",
    "iso:country":"CA",
    "sg:city":"Scarborough",
    "sg:classifiers":[
        {
            "category":"Professional",
            "subcategory":"Accounting & Tax Preparation",
            "type":"Services"
        }
    ],
    "sg:phone":"+1 416 297 5552",
    "sg:postcode":"M1S 3Y6",
    "sg:province":"ON",
    "sg:tags":[
        "accountant"
    ],
    "wof:name":"Mak, Sophia F",
    "wof:placetype":"venue"
},
  "geometry": {"coordinates":[-79.260864,43.795101],"type":"Point"}
}