{
  "type": "Feature",
  "properties": {
    "addr:full":"PO Box 804 High Level AB T0H 1Z0",
    "addr:housenumber":"po;804",
    "addr:postcode":"t0h 1z0",
    "addr:street":"Box",
    "iso:country":"CA",
    "sg:address":"PO Box 804",
    "sg:city":"High Level",
    "sg:classifiers":[
        {
            "category":"Building & Trades",
            "subcategory":"Construction",
            "type":"Services"
        }
    ],
    "sg:phone":"+1 780 928 2587",
    "sg:postcode":"T0H 1Z0",
    "sg:province":"AB",
    "sg:tags":[
        "painter"
    ],
    "wof:name":"Pete's Painting & Maintenance",
    "wof:placetype":"venue"
},
  "geometry": {"coordinates":[-117.126091003,58.5167198181],"type":"Point"}
}