{
  "type": "Feature",
  "properties": {
    "addr:full":"Calgary AB T2H 1Z8",
    "addr:postcode":"t2h 1z8",
    "iso:country":"CA",
    "sg:city":"Calgary",
    "sg:classifiers":[
        {
            "category":"Building & Trades",
            "subcategory":"Construction",
            "type":"Services"
        }
    ],
    "sg:phone":"+1 403 253 1988",
    "sg:postcode":"T2H 1Z8",
    "sg:province":"AB",
    "sg:tags":[
        "siding",
        "contractor"
    ],
    "wof:name":"Mitten Vinyl Inc",
    "wof:placetype":"venue"
},
  "geometry": {"coordinates":[-114.0438,51.005302],"type":"Point"}
}