{
  "type": "Feature",
  "properties": {
    "addr:full":"300 Piccadilly St London ON N6A 1S5",
    "addr:housenumber":"300",
    "addr:postcode":"n6a 1s5",
    "addr:street":"Piccadilly St",
    "iso:country":"CA",
    "sg:address":"300 Piccadilly St",
    "sg:city":"London",
    "sg:classifiers":[
        {
            "category":"Health Services",
            "subcategory":"Health Practitioner",
            "type":"Services"
        }
    ],
    "sg:phone":"+1 519 858 2493",
    "sg:postcode":"N6A 1S5",
    "sg:province":"ON",
    "sg:tags":[
        "psychologist"
    ],
    "wof:name":"Woodson, Anna E",
    "wof:placetype":"venue"
},
  "geometry": {"coordinates":[-81.2492675781,42.9955329895],"type":"Point"}
}