{
  "type": "Feature",
  "properties": {
    "addr:full":"1575 Lawrence Ave W North York ON M6L 1C3",
    "addr:housenumber":"1575",
    "addr:postcode":"m6l 1c3",
    "addr:street":"Lawrence Ave W",
    "iso:country":"CA",
    "sg:address":"1575 Lawrence Ave W",
    "sg:city":"North York",
    "sg:classifiers":[
        {
            "category":"Personal",
            "subcategory":"Beauty Salon",
            "type":"Services"
        }
    ],
    "sg:phone":"+1 416 249 3111",
    "sg:postcode":"M6L 1C3",
    "sg:province":"ON",
    "wof:name":"Studio Hairstyling",
    "wof:placetype":"venue"
},
  "geometry": {"coordinates":[-79.488106,43.706154],"type":"Point"}
}