{
  "type": "Feature",
  "properties": {
    "iso:country":"CA",
    "sg:address":"PO Box 334",
    "sg:city":"Cardinal",
    "sg:classifiers":[
        {
            "category":"Organizations",
            "subcategory":"Religious Organization",
            "type":"Services"
        }
    ],
    "sg:phone":"+1 613 657 1317",
    "sg:postcode":"K0E 1E0",
    "sg:province":"ON",
    "sg:tags":[
        "church"
    ],
    "wof:name":"Cardinal Free Methodist Church",
    "wof:placetype":"venue"
},
  "geometry": {"coordinates":[-75.3848114014,44.7873153687],"type":"Point"}
}