{
  "type": "Feature",
  "properties": {
    "addr:full":"1275 Queen St E Toronto ON M4L 1C2",
    "addr:housenumber":"1275",
    "addr:postcode":"m4l 1c2",
    "addr:street":"Queen St E",
    "iso:country":"CA",
    "sg:address":"1275 Queen St E",
    "sg:city":"Toronto",
    "sg:classifiers":[
        {
            "category":"Shopping",
            "subcategory":"Discount & Variety Stores",
            "type":"Retail Goods"
        }
    ],
    "sg:phone":"+1 416 466 3015",
    "sg:postcode":"M4L 1C2",
    "sg:province":"ON",
    "wof:name":"Queen Street Variety",
    "wof:placetype":"venue"
},
  "geometry": {"coordinates":[-79.3286895752,43.6634674072],"type":"Point"}
}