{
  "type": "Feature",
  "properties": {
    "addr:full":"4439 Dallyn St NW Calgary AB T3A 1K2",
    "addr:housenumber":"4439",
    "addr:postcode":"t3a 1k2",
    "addr:street":"Dallyn St Nw",
    "iso:country":"CA",
    "sg:address":"4439 Dallyn St NW",
    "sg:city":"Calgary",
    "sg:classifiers":[
        {
            "category":"Shopping",
            "subcategory":"Computers & Home Electronics",
            "type":"Retail Goods"
        }
    ],
    "sg:phone":"+1 403 247 9525",
    "sg:postcode":"T3A 1K2",
    "sg:province":"AB",
    "sg:tags":[
        "publishing"
    ],
    "wof:name":"By Design Svc",
    "wof:placetype":"venue"
},
  "geometry": {"coordinates":[-114.151207,51.105774],"type":"Point"}
}