{
  "type": "Feature",
  "properties": {
    "addr:full":"Cap-DE-LA-Madeleine QC G8T 3R4",
    "addr:postcode":"g8t 3r4",
    "iso:country":"CA",
    "sg:city":"Cap-DE-LA-Madeleine",
    "sg:classifiers":[
        {
            "category":"Insurance",
            "subcategory":"Insurance Agent",
            "type":"Services"
        }
    ],
    "sg:phone":"+1 819 379 1488",
    "sg:postcode":"G8T 3R4",
    "sg:province":"QC",
    "sg:tags":[
        "advisory",
        "financial"
    ],
    "wof:name":"Securitel Canada",
    "wof:placetype":"venue"
},
  "geometry": {"coordinates":[-72.50147247309999,46.3704833984],"type":"Point"}
}