{
  "type": "Feature",
  "properties": {
    "addr:full":"130 Kingsmere Pl Saskatoon SK S7J 3V7",
    "addr:housenumber":"130",
    "addr:postcode":"s7j 3v7",
    "addr:street":"Kingsmere Pl",
    "iso:country":"CA",
    "sg:address":"130 Kingsmere Pl",
    "sg:city":"Saskatoon",
    "sg:classifiers":[
        {
            "category":"Organizations",
            "subcategory":"Religious Organization",
            "type":"Services"
        }
    ],
    "sg:phone":"+1 306 374 6556",
    "sg:postcode":"S7J 3V7",
    "sg:province":"SK",
    "sg:tags":[
        "church"
    ],
    "wof:name":"Lakeview Free Methodist Church",
    "wof:placetype":"venue"
},
  "geometry": {"coordinates":[-106.598083,52.103195],"type":"Point"}
}