{
  "type": "Feature",
  "properties": {
    "addr:full":"135 Peter St Port Hope ON L1A 1C5",
    "addr:housenumber":"135",
    "addr:postcode":"l1a 1c5",
    "addr:street":"Peter St",
    "iso:country":"CA",
    "sg:address":"135 Peter St",
    "sg:city":"Port Hope",
    "sg:classifiers":[
        {
            "category":"Shopping",
            "subcategory":"Pharmacy",
            "type":"Retail Goods"
        }
    ],
    "sg:phone":"+1 905 885 8191",
    "sg:postcode":"L1A 1C5",
    "sg:province":"ON",
    "wof:name":"York Super Pharmacy",
    "wof:placetype":"venue"
},
  "geometry": {"coordinates":[-78.28239440919999,43.9500808716],"type":"Point"}
}