{
  "type": "Feature",
  "properties": {
    "addr:full":"3675 Boul DE LA Grande-Allee Boisbriand QC J7H 1H5",
    "addr:housenumber":"3675",
    "addr:postcode":"j7h 1h5",
    "addr:street":"Boul De La Grande-Allee",
    "iso:country":"CA",
    "sg:address":"3675 Boul DE LA Grande-Allee",
    "sg:city":"Boisbriand",
    "sg:classifiers":[
        {
            "category":"Manufacturing",
            "subcategory":"Tools & Machinery",
            "type":"Manufacturing & Wholesale Goods"
        }
    ],
    "sg:phone":"+1 450 435 2121",
    "sg:postcode":"J7H 1H5",
    "sg:province":"QC",
    "sg:tags":[
        "equipment",
        "sawmill",
        "supply"
    ],
    "wof:name":"Comact Optimisation Inc",
    "wof:placetype":"venue"
},
  "geometry": {"coordinates":[-73.86070251460001,45.6301574707],"type":"Point"}
}