{
  "type": "Feature",
  "properties": {
    "addr:full":"5405 Av Hemard Saint-Hubert QC J3Y 3G8",
    "addr:housenumber":"5405",
    "addr:postcode":"j3y 3g8",
    "addr:street":"Av Hemard",
    "iso:country":"CA",
    "sg:address":"5405 Av Hemard",
    "sg:city":"Saint-Hubert",
    "sg:classifiers":[
        {
            "category":"Organizations",
            "subcategory":"Religious Organization",
            "type":"Services"
        }
    ],
    "sg:phone":"+1 450 676 2661",
    "sg:postcode":"J3Y 3G8",
    "sg:province":"QC",
    "sg:tags":[
        "church"
    ],
    "wof:name":"Immaculee Conception",
    "wof:placetype":"venue"
},
  "geometry": {"coordinates":[-73.4256973267,45.4918365479],"type":"Point"}
}