{
  "type": "Feature",
  "properties": {
    "iso:country":"CA",
    "sg:address":"95 Main St",
    "sg:city":"Erin",
    "sg:classifiers":[
        {
            "category":"Retail",
            "subcategory":"Auto Repair",
            "type":"Services"
        }
    ],
    "sg:phone":"+1 519 833 2330",
    "sg:postcode":"N0B 1T0",
    "sg:province":"ON",
    "sg:tags":[
        "repairing",
        "automobile"
    ],
    "wof:name":"Scott's Main Street Station",
    "wof:placetype":"venue"
},
  "geometry": {"coordinates":[-80.063339,43.77002],"type":"Point"}
}