{
  "type": "Feature",
  "properties": {
    "addr:full":"Pointe-Aux-Trembles QC H1B 4A5",
    "addr:postcode":"h1b 4a5",
    "iso:country":"CA",
    "sg:city":"Pointe-Aux-Trembles",
    "sg:classifiers":[
        {
            "category":"Social Services",
            "subcategory":"Job Training",
            "type":"Services"
        }
    ],
    "sg:phone":"+1 514 640 4700",
    "sg:postcode":"H1B 4A5",
    "sg:province":"QC",
    "sg:tags":[
        "employment"
    ],
    "wof:name":"Carrefour Jeunesse-Emploi",
    "wof:placetype":"venue"
},
  "geometry": {"coordinates":[-73.50312,45.641926],"type":"Point"}
}