{
  "type": "Feature",
  "properties": {
    "addr:full":"450 Rue Saint-Thomas Joliette QC J6E 3R1",
    "addr:housenumber":"450",
    "addr:postcode":"j6e 3r1",
    "addr:street":"Rue Saint-Thomas",
    "iso:country":"CA",
    "sg:address":"450 Rue Saint-Thomas",
    "sg:city":"Joliette",
    "sg:classifiers":[
        {
            "category":"Travel",
            "subcategory":"Hotels & Motels",
            "type":"Entertainment"
        }
    ],
    "sg:phone":"+1 450 752 2525",
    "sg:postcode":"J6E 3R1",
    "sg:province":"QC",
    "wof:name":"Hotel Chateau Joliette",
    "wof:placetype":"venue"
},
  "geometry": {"coordinates":[-73.433151,46.024357],"type":"Point"}
}