{
  "type": "Feature",
  "properties": {
    "iso:country":"CA",
    "sg:city":"Scarborough",
    "sg:classifiers":[
        {
            "category":"Shopping",
            "subcategory":"Pharmacy",
            "type":"Retail Goods"
        }
    ],
    "sg:phone":"+1 416 321 3978",
    "sg:postcode":"M1P 2W6",
    "sg:province":"ON",
    "wof:name":"Fairlane Drug Mart",
    "wof:placetype":"venue"
},
  "geometry": {"coordinates":[-79.28238677980001,43.7656784058],"type":"Point"}
}