{
  "type": "Feature",
  "properties": {
    "addr:full":"Stayner ON L0M 1S0",
    "addr:postcode":"l0m 1s0",
    "iso:country":"CA",
    "sg:city":"Stayner",
    "sg:classifiers":[
        {
            "category":"Manufacturing",
            "subcategory":"Printing",
            "type":"Manufacturing & Wholesale Goods"
        }
    ],
    "sg:phone":"+1 705 428 6515",
    "sg:postcode":"L0M 1S0",
    "sg:province":"ON",
    "sg:tags":[
        "lithographer",
        "printer"
    ],
    "wof:name":"Gowan Printing Svc",
    "wof:placetype":"venue"
},
  "geometry": {"coordinates":[-80.08818100000001,44.420052],"type":"Point"}
}