{
  "type": "Feature",
  "properties": {
    "addr:full":"101 Ridgevalley Rd Crooked Creek AB T0H 0Y0",
    "addr:housenumber":"101",
    "addr:postcode":"t0h 0y0",
    "addr:street":"Ridgevalley Rd",
    "iso:country":"CA",
    "sg:address":"101 Ridgevalley Rd",
    "sg:city":"Crooked Creek",
    "sg:classifiers":[
        {
            "category":"Retail",
            "subcategory":"Auto Repair",
            "type":"Services"
        }
    ],
    "sg:phone":"+1 780 957 2255",
    "sg:postcode":"T0H 0Y0",
    "sg:province":"AB",
    "sg:tags":[
        "body",
        "automobile",
        "painting"
    ],
    "wof:name":"Star Autobody Ltd",
    "wof:placetype":"venue"
},
  "geometry": {"coordinates":[-117.834824,55.155975],"type":"Point"}
}