{
  "type": "Feature",
  "properties": {
    "addr:full":"117 Emery St W London ON N6J 1R9",
    "addr:housenumber":"117",
    "addr:postcode":"n6j 1r9",
    "addr:street":"Emery St W",
    "iso:country":"CA",
    "sg:address":"117 Emery St W",
    "sg:city":"London",
    "sg:classifiers":[
        {
            "category":"Arts & Performance",
            "subcategory":"Theater",
            "type":"Entertainment"
        }
    ],
    "sg:phone":"+1 519 679 0971",
    "sg:postcode":"N6J 1R9",
    "sg:province":"ON",
    "sg:tags":[
        "bureau"
    ],
    "wof:name":"Active Talent Agency",
    "wof:placetype":"venue"
},
  "geometry": {"coordinates":[-81.27093499999999,42.963425],"type":"Point"}
}