{
  "type": "Feature",
  "properties": {
    "addr:full":"415 the Westway # 7 Etobicoke ON M9R 1H5",
    "addr:housenumber":"415;# 7",
    "addr:postcode":"m9r 1h5",
    "addr:street":"The Westway",
    "iso:country":"CA",
    "sg:address":"415 the Westway # 7",
    "sg:city":"Etobicoke",
    "sg:classifiers":[
        {
            "category":"Restaurant",
            "type":"Food & Drink"
        }
    ],
    "sg:phone":"+1 416 241 7347",
    "sg:postcode":"M9R 1H5",
    "sg:province":"ON",
    "wof:name":"Martinway Restaurant & Tavern",
    "wof:placetype":"venue"
},
  "geometry": {"coordinates":[-79.5650405884,43.6836357117],"type":"Point"}
}