{
  "type": "Feature",
  "properties": {
    "addr:full":"1110 Dundas St W Toronto ON M6J 1X2",
    "addr:housenumber":"1110",
    "addr:postcode":"m6j 1x2",
    "addr:street":"Dundas St W",
    "iso:country":"CA",
    "sg:address":"1110 Dundas St W",
    "sg:city":"Toronto",
    "sg:classifiers":[
        {
            "category":"Banks & Credit Unions",
            "subcategory":"Bank",
            "type":"Services"
        }
    ],
    "sg:phone":"+1 416 538 7111",
    "sg:postcode":"M6J 1X2",
    "sg:province":"ON",
    "wof:name":"Banco Totta & Acores",
    "wof:placetype":"venue"
},
  "geometry": {"coordinates":[-79.4198684692,43.649646759],"type":"Point"}
}