{
  "type": "Feature",
  "properties": {
    "addr:full":"850 Hurontario St Hwy 24 Collingwood ON L9Y 3Z1",
    "addr:housenumber":"850",
    "addr:postcode":"l9y 3z1",
    "addr:street":"Hurontario St Hwy 24",
    "iso:country":"CA",
    "sg:address":"850 Hurontario St Hwy 24",
    "sg:city":"Collingwood",
    "sg:classifiers":[
        {
            "category":"Retail",
            "subcategory":"Auto Repair",
            "type":"Services"
        }
    ],
    "sg:phone":"+1 705 444 2497",
    "sg:postcode":"L9Y 3Z1",
    "sg:province":"ON",
    "sg:tags":[
        "control",
        "automobile",
        "corrosion",
        "rustproofing",
        "undercoating"
    ],
    "wof:name":"Rust Check",
    "wof:placetype":"venue"
},
  "geometry": {"coordinates":[-80.213165,44.48106],"type":"Point"}
}