{
  "type": "Feature",
  "properties": {
    "addr:full":"3453 Casorso Rd Kelowna BC V1W 3J6",
    "addr:housenumber":"3453",
    "addr:postcode":"v1w 3j6",
    "addr:street":"Casorso Rd",
    "iso:country":"CA",
    "sg:address":"3453 Casorso Rd",
    "sg:city":"Kelowna",
    "sg:classifiers":[
        {
            "category":"Building & Trades",
            "subcategory":"Construction",
            "type":"Services"
        }
    ],
    "sg:phone":"+1 250 763 9027",
    "sg:postcode":"V1W 3J6",
    "sg:province":"BC",
    "sg:tags":[
        "cabinet",
        "maker",
        "furniture"
    ],
    "wof:name":"Canadiana Antiquities of Today",
    "wof:placetype":"venue"
},
  "geometry": {"coordinates":[-119.485207,49.856857],"type":"Point"}
}