{
  "type": "Feature",
  "properties": {
    "iso:country":"CA",
    "sg:address":"2500 Don Mills Rd",
    "sg:city":"North York",
    "sg:classifiers":[
        {
            "category":"Restaurant",
            "type":"Food & Drink"
        }
    ],
    "sg:phone":"+1 416 495 0092",
    "sg:postcode":"M2J 3B3",
    "sg:province":"ON",
    "sg:tags":[
        "shop",
        "tea",
        "coffee"
    ],
    "wof:name":"Tim Hortons",
    "wof:placetype":"venue"
},
  "geometry": {"coordinates":[-79.34726,43.775211],"type":"Point"}
}