{
  "type": "Feature",
  "properties": {
    "addr:full":"950 Jefferson Ave Winnipeg MB R2P 1W1",
    "addr:housenumber":"950",
    "addr:postcode":"r2p 1w1",
    "addr:street":"Jefferson Ave",
    "iso:country":"CA",
    "sg:address":"950 Jefferson Ave",
    "sg:city":"Winnipeg",
    "sg:classifiers":[
        {
            "category":"Autos & Motor Vehicles",
            "subcategory":"Fuel & Gas Station",
            "type":"Retail Goods"
        }
    ],
    "sg:phone":"+1 204 632 9779",
    "sg:postcode":"R2P 1W1",
    "sg:province":"MB",
    "sg:tags":[
        "oil"
    ],
    "wof:name":"Jefferson Esso",
    "wof:placetype":"venue"
},
  "geometry": {"coordinates":[-97.15735599999999,49.945728],"type":"Point"}
}