{
  "type": "Feature",
  "properties": {
    "addr:full":"585 Wallace St Wallaceburg ON N8A 1K9",
    "addr:housenumber":"585",
    "addr:postcode":"n8a 1k9",
    "addr:street":"Wallace St",
    "iso:country":"CA",
    "sg:address":"585 Wallace St",
    "sg:city":"Wallaceburg",
    "sg:classifiers":[
        {
            "category":"Personal",
            "subcategory":"Beauty Salon",
            "type":"Services"
        }
    ],
    "sg:phone":"+1 519 627 8111",
    "sg:postcode":"N8A 1K9",
    "sg:province":"ON",
    "wof:name":"B J's Hairstyling",
    "wof:placetype":"venue"
},
  "geometry": {"coordinates":[-82.38083648680001,42.5937957764],"type":"Point"}
}