{
  "type": "Feature",
  "properties": {
    "addr:full":"254 Bartley Dr North York ON M4A 1G1",
    "addr:housenumber":"254",
    "addr:postcode":"m4a 1g1",
    "addr:street":"Bartley Dr",
    "iso:country":"CA",
    "sg:address":"254 Bartley Dr",
    "sg:city":"North York",
    "sg:classifiers":[
        {
            "category":"Wholesale",
            "subcategory":"Sporting Goods",
            "type":"Manufacturing & Wholesale Goods"
        }
    ],
    "sg:phone":"+1 416 752 8985",
    "sg:postcode":"M4A 1G1",
    "sg:province":"ON",
    "sg:tags":[
        "equipment",
        "pool",
        "swimming"
    ],
    "wof:name":"Kenloch CO",
    "wof:placetype":"venue"
},
  "geometry": {"coordinates":[-79.316238,43.718334],"type":"Point"}
}