{
  "type": "Feature",
  "properties": {
    "addr:full":"438 King St W Oshawa ON L1J 2K9",
    "addr:housenumber":"438",
    "addr:postcode":"l1j 2k9",
    "addr:street":"King St W",
    "iso:country":"CA",
    "sg:address":"438 King St W",
    "sg:city":"Oshawa",
    "sg:classifiers":[
        {
            "category":"Autos & Motor Vehicles",
            "subcategory":"Auto Supplies",
            "type":"Retail Goods"
        }
    ],
    "sg:phone":"+1 905 576 0030",
    "sg:postcode":"L1J 2K9",
    "sg:province":"ON",
    "sg:tags":[
        "automobile",
        "stereo",
        "radio"
    ],
    "wof:name":"Ultimate Car Audio",
    "wof:placetype":"venue"
},
  "geometry": {"coordinates":[-78.8802108765,43.8939247131],"type":"Point"}
}