{
  "type": "Feature",
  "properties": {
    "iso:country":"CA",
    "sg:city":"Etobicoke",
    "sg:classifiers":[
        {
            "category":"Shopping",
            "subcategory":"Shoes",
            "type":"Retail Goods"
        }
    ],
    "sg:phone":"+1 416 234 1164",
    "sg:postcode":"M9B 3Y8",
    "sg:province":"ON",
    "wof:name":"Star Shoes",
    "wof:placetype":"venue"
},
  "geometry": {"coordinates":[-79.554649353,43.6326751709],"type":"Point"}
}