{
  "type": "Feature",
  "properties": {
    "iso:country":"CA",
    "sg:city":"Mississauga",
    "sg:classifiers":[
        {
            "category":"Professional",
            "subcategory":"Business Services",
            "type":"Services"
        }
    ],
    "sg:phone":"+1 905 279 4000",
    "sg:postcode":"L5C 1T7",
    "sg:province":"ON",
    "sg:tags":[
        "recording",
        "studio"
    ],
    "wof:name":"Metalworks Studios Inc",
    "wof:placetype":"venue"
},
  "geometry": {"coordinates":[-79.649239,43.577656],"type":"Point"}
}