{
  "type": "Feature",
  "properties": {
    "addr:full":"Scarborough ON M1S 4Z6",
    "addr:postcode":"m1s 4z6",
    "iso:country":"CA",
    "sg:city":"Scarborough",
    "sg:classifiers":[
        {
            "category":"Wholesale",
            "subcategory":"Durable Goods & Equipment",
            "type":"Manufacturing & Wholesale Goods"
        }
    ],
    "sg:phone":"+1 416 332 0030",
    "sg:postcode":"M1S 4Z6",
    "sg:province":"ON",
    "sg:tags":[
        "fire",
        "extinguisher",
        "protection"
    ],
    "wof:name":"Steadfast Fire Extinguishers",
    "wof:placetype":"venue"
},
  "geometry": {"coordinates":[-79.256828,43.810177],"type":"Point"}
}