{
  "type": "Feature",
  "properties": {
    "addr:full":"20300 Logan Ave Langley BC V3A 4L7",
    "addr:housenumber":"20300",
    "addr:postcode":"v3a 4l7",
    "addr:street":"Logan Ave",
    "iso:country":"CA",
    "sg:address":"20300 Logan Ave",
    "sg:city":"Langley",
    "sg:classifiers":[
        {
            "category":"Wholesale",
            "subcategory":"Sporting Goods",
            "type":"Manufacturing & Wholesale Goods"
        }
    ],
    "sg:phone":"+1 604 533 1251",
    "sg:postcode":"V3A 4L7",
    "sg:province":"BC",
    "sg:tags":[
        "equipment",
        "pool",
        "swimming"
    ],
    "wof:name":"English & Le Page Ltd",
    "wof:placetype":"venue"
},
  "geometry": {"coordinates":[-122.65992,49.108574],"type":"Point"}
}