{
  "type": "Feature",
  "properties": {
    "addr:full":"328 Speedvale Ave E #24 Guelph ON N1E 1N5",
    "addr:housenumber":"328",
    "addr:postcode":"n1e 1n5",
    "addr:street":"Speedvale Ave E # 24",
    "iso:country":"CA",
    "sg:address":"328 Speedvale Ave E #24",
    "sg:city":"Guelph",
    "sg:classifiers":[
        {
            "category":"Retail",
            "subcategory":"Veterinary Services",
            "type":"Services"
        }
    ],
    "sg:phone":"+1 519 763 1082",
    "sg:postcode":"N1E 1N5",
    "sg:province":"ON",
    "sg:tags":[
        "veterinarian"
    ],
    "wof:name":"Cornell Animal Hospital",
    "wof:placetype":"venue"
},
  "geometry": {"coordinates":[-80.25769805909999,43.566280365],"type":"Point"}
}