{
  "type": "Feature",
  "properties": {
    "addr:full":"424 Brandon Ave Winnipeg MB R3L 0T6",
    "addr:housenumber":"424",
    "addr:postcode":"r3l 0t6",
    "addr:street":"Brandon Ave",
    "iso:country":"CA",
    "sg:address":"424 Brandon Ave",
    "sg:city":"Winnipeg",
    "sg:classifiers":[
        {
            "category":"Organizations",
            "subcategory":"Religious Organization",
            "type":"Services"
        }
    ],
    "sg:phone":"+1 204 477 1211",
    "sg:postcode":"R3L 0T6",
    "sg:province":"MB",
    "sg:tags":[
        "church"
    ],
    "wof:name":"Sacre-Coeur Paroisse",
    "wof:placetype":"venue"
},
  "geometry": {"coordinates":[-97.13562,49.868008],"type":"Point"}
}