{
  "type": "Feature",
  "properties": {
    "iso:country":"CA",
    "sg:city":"Prescott",
    "sg:classifiers":[
        {
            "category":"Health Services",
            "subcategory":"Optometrist",
            "type":"Services"
        }
    ],
    "sg:phone":"+1 613 925 5186",
    "sg:postcode":"K0E 1T0",
    "sg:province":"ON",
    "wof:name":"Holmes, James A OD",
    "wof:placetype":"venue"
},
  "geometry": {"coordinates":[-75.51397705079999,44.7098770142],"type":"Point"}
}