{
  "type": "Feature",
  "properties": {
    "addr:full":"322 Duchess St Saskatoon SK S7K 0R1",
    "addr:housenumber":"322",
    "addr:postcode":"s7k 0r1",
    "addr:street":"Duchess St",
    "iso:country":"CA",
    "sg:address":"322 Duchess St",
    "sg:city":"Saskatoon",
    "sg:classifiers":[
        {
            "category":"Wholesale",
            "subcategory":"Construction Materials",
            "type":"Manufacturing & Wholesale Goods"
        }
    ],
    "sg:phone":"+1 306 955 2883",
    "sg:postcode":"S7K 0R1",
    "sg:province":"SK",
    "sg:tags":[
        "sand",
        "gravel"
    ],
    "wof:name":"L & L Gravel & Ranching CO",
    "wof:placetype":"venue"
},
  "geometry": {"coordinates":[-106.657814026,52.1426620483],"type":"Point"}
}