{
  "type": "Feature",
  "properties": {
    "addr:full":"1015 Main Ave E Sundre AB T0M 1X0",
    "addr:housenumber":"1015",
    "addr:postcode":"t0m 1x0",
    "addr:street":"Main Ave E",
    "iso:country":"CA",
    "sg:address":"1015 Main Ave E",
    "sg:city":"Sundre",
    "sg:classifiers":[
        {
            "category":"Shopping",
            "type":"Retail Goods"
        }
    ],
    "sg:phone":"+1 403 638 3959",
    "sg:postcode":"T0M 1X0",
    "sg:province":"AB",
    "sg:tags":[
        "pet",
        "food",
        "supply"
    ],
    "wof:name":"Sundre Livestock & Farm Supply",
    "wof:placetype":"venue"
},
  "geometry": {"coordinates":[-114.623611,51.794891],"type":"Point"}
}