{
  "type": "Feature",
  "properties": {
    "addr:full":"Mississauga ON L5N 6J1",
    "addr:postcode":"l5n 6j1",
    "iso:country":"CA",
    "sg:city":"Mississauga",
    "sg:classifiers":[
        {
            "category":"Real Estate",
            "subcategory":"Architect",
            "type":"Services"
        }
    ],
    "sg:phone":"+1 905 858 8644",
    "sg:postcode":"L5N 6J1",
    "sg:province":"ON",
    "wof:name":"Rsm Architecture Inc",
    "wof:placetype":"venue"
},
  "geometry": {"coordinates":[-79.735893,43.603184],"type":"Point"}
}