{
  "type": "Feature",
  "properties": {
    "addr:full":"1235 Boul Monseigneur-Langlois Grande-Ile QC J6S 1C1",
    "addr:housenumber":"1235",
    "addr:postcode":"j6s 1c1",
    "addr:street":"Boul Monseigneur-Langlois Grande-Ile",
    "iso:country":"CA",
    "sg:address":"1235 Boul Monseigneur-Langlois",
    "sg:city":"Grande-Ile",
    "sg:classifiers":[
        {
            "category":"Retail",
            "subcategory":"Auto Repair",
            "type":"Services"
        }
    ],
    "sg:phone":"+1 450 371 4281",
    "sg:postcode":"J6S 1C1",
    "sg:province":"QC",
    "sg:tags":[
        "repairing",
        "automobile",
        "muffler",
        "system",
        "exhaust"
    ],
    "wof:name":"Monsieur Muffler",
    "wof:placetype":"venue"
},
  "geometry": {"coordinates":[-74.1348953247,45.2703170776],"type":"Point"}
}