{
  "type": "Feature",
  "properties": {
    "addr:full":"2019 19th Ave Nanton AB T0L 1R0",
    "addr:housenumber":"2019",
    "addr:postcode":"t0l 1r0",
    "addr:street":"19Th Ave",
    "iso:country":"CA",
    "sg:address":"2019 19th Ave",
    "sg:city":"Nanton",
    "sg:classifiers":[
        {
            "category":"Manufacturing",
            "subcategory":"Chemicals & Compounds",
            "type":"Manufacturing & Wholesale Goods"
        }
    ],
    "sg:phone":"+1 403 646 2566",
    "sg:postcode":"T0L 1R0",
    "sg:province":"AB",
    "sg:tags":[
        "fertilizer"
    ],
    "wof:name":"Mac Killop Fertilizer & Feed",
    "wof:placetype":"venue"
},
  "geometry": {"coordinates":[-113.769341,50.348362],"type":"Point"}
}