{
  "type": "Feature",
  "properties": {
    "addr:full":"49 Main St Stephenville NL A2N 1H7",
    "addr:housenumber":"49",
    "addr:postcode":"a2n 1h7",
    "addr:street":"Main St",
    "iso:country":"CA",
    "sg:address":"49 Main St",
    "sg:city":"Stephenville",
    "sg:classifiers":[
        {
            "category":"Professional",
            "subcategory":"Accounting & Tax Preparation",
            "type":"Services"
        }
    ],
    "sg:phone":"+1 709 643 5873",
    "sg:postcode":"A2N 1H7",
    "sg:province":"NL",
    "sg:tags":[
        "return",
        "filing"
    ],
    "wof:name":"H & R Block Canada Inc",
    "wof:placetype":"venue"
},
  "geometry": {"coordinates":[-58.5834655762,48.5473861694],"type":"Point"}
}