{
  "type": "Feature",
  "properties": {
    "iso:country":"CA",
    "sg:address":"11735 156 St NW",
    "sg:city":"Edmonton",
    "sg:classifiers":[
        {
            "category":"Retail",
            "subcategory":"Repair Shop",
            "type":"Services"
        }
    ],
    "sg:phone":"+1 780 447 5625",
    "sg:postcode":"T5M 3N4",
    "sg:province":"AB",
    "sg:tags":[
        "lock",
        "locksmith"
    ],
    "wof:name":"All-Lock-Rescue Ltd",
    "wof:placetype":"venue"
},
  "geometry": {"coordinates":[-113.590179443,53.5686531067],"type":"Point"}
}