{
  "type": "Feature",
  "properties": {
    "addr:full":"2943 Route 560 Williamstown Carleton CO NB E7K 2A6",
    "addr:housenumber":"2943",
    "addr:postcode":"e7k 2a6",
    "addr:street":"Route 560",
    "iso:country":"CA",
    "sg:address":"2943 Route 560",
    "sg:city":"Williamstown Carleton CO",
    "sg:classifiers":[
        {
            "category":"Organizations",
            "subcategory":"Religious Organization",
            "type":"Services"
        }
    ],
    "sg:phone":"+1 506 276 1999",
    "sg:postcode":"E7K 2A6",
    "sg:province":"NB",
    "sg:tags":[
        "church"
    ],
    "wof:name":"St John Valley Mennonite Chr",
    "wof:placetype":"venue"
},
  "geometry": {"coordinates":[-67.701431,46.38612],"type":"Point"}
}