{
  "type": "Feature",
  "properties": {
    "addr:full":"1474 Rue Jean-Talon E Montreal QC H2E 1S7",
    "addr:housenumber":"1474",
    "addr:postcode":"h2e 1s7",
    "addr:street":"Rue Jean-Talon E",
    "iso:country":"CA",
    "sg:address":"1474 Rue Jean-Talon E",
    "sg:city":"Montreal",
    "sg:classifiers":[
        {
            "category":"Wholesale",
            "subcategory":"Durable Goods & Equipment",
            "type":"Manufacturing & Wholesale Goods"
        }
    ],
    "sg:phone":"+1 514 721 0082",
    "sg:postcode":"H2E 1S7",
    "sg:province":"QC",
    "sg:tags":[
        "compact",
        "record",
        "disc",
        "tape"
    ],
    "wof:name":"Leon Vellone Enrg",
    "wof:placetype":"venue"
},
  "geometry": {"coordinates":[-73.60836,45.546268],"type":"Point"}
}