{
  "type": "Feature",
  "properties": {
    "iso:country":"CA",
    "sg:address":"340 Richmond Rd",
    "sg:city":"Ottawa",
    "sg:classifiers":[
        {
            "category":"Shopping",
            "subcategory":"Pharmacy",
            "type":"Retail Goods"
        }
    ],
    "sg:phone":"+1 613 722 7896",
    "sg:postcode":"K2A 0E8",
    "sg:province":"ON",
    "sg:tags":[
        "post"
    ],
    "wof:name":"Westboro Pharmasave",
    "wof:placetype":"venue"
},
  "geometry": {"coordinates":[-75.754196167,45.391784668],"type":"Point"}
}