{
  "type": "Feature",
  "properties": {
    "addr:full":"312 Woolgar Ave Yellowknife NT X1A 3B5",
    "addr:housenumber":"312",
    "addr:postcode":"x1a 3b5",
    "addr:street":"Woolgar Ave",
    "iso:country":"CA",
    "sg:address":"312 Woolgar Ave",
    "sg:city":"Yellowknife",
    "sg:classifiers":[
        {
            "category":"Building & Trades",
            "subcategory":"Plumbing",
            "type":"Services"
        }
    ],
    "sg:phone":"+1 867 873 2392",
    "sg:postcode":"X1A 3B5",
    "sg:province":"NT",
    "sg:tags":[
        "contractor"
    ],
    "wof:name":"J & R Mechanical Ltd",
    "wof:placetype":"venue"
},
  "geometry": {"coordinates":[-114.40825700000001,62.443836],"type":"Point"}
}