{
  "type": "Feature",
  "properties": {
    "addr:full":"Cambridge ON N1T 1A3",
    "addr:postcode":"n1t 1a3",
    "iso:country":"CA",
    "sg:city":"Cambridge",
    "sg:classifiers":[
        {
            "category":"Retail",
            "subcategory":"Auto Repair",
            "type":"Services"
        }
    ],
    "sg:phone":"+1 519 621 2660",
    "sg:postcode":"N1T 1A3",
    "sg:province":"ON",
    "sg:tags":[
        "alternator",
        "automobile",
        "electric",
        "starter"
    ],
    "wof:name":"Mitchell Generator Starter",
    "wof:placetype":"venue"
},
  "geometry": {"coordinates":[-80.30315400000001,43.406761],"type":"Point"}
}