{
  "type": "Feature",
  "properties": {
    "addr:full":"Sudbury ON P3C 1S8",
    "addr:postcode":"p3c 1s8",
    "iso:country":"CA",
    "sg:city":"Sudbury",
    "sg:classifiers":[
        {
            "category":"Travel",
            "subcategory":"Travel Agent",
            "type":"Entertainment"
        }
    ],
    "sg:phone":"+1 705 675 1977",
    "sg:postcode":"P3C 1S8",
    "sg:province":"ON",
    "sg:tags":[
        "agency",
        "bureau"
    ],
    "wof:name":"Thomas Cook Travel",
    "wof:placetype":"venue"
},
  "geometry": {"coordinates":[-80.9923171997,46.4932518005],"type":"Point"}
}