{
  "type": "Feature",
  "properties": {
    "addr:full":"17560 60 Ave Surrey BC V3S 1T8",
    "addr:housenumber":"17560",
    "addr:postcode":"v3s 1t8",
    "addr:street":"60 Ave",
    "iso:country":"CA",
    "sg:address":"17560 60 Ave",
    "sg:city":"Surrey",
    "sg:classifiers":[
        {
            "category":"Social Services",
            "subcategory":"Child Care",
            "type":"Services"
        }
    ],
    "sg:phone":"+1 604 574 5057",
    "sg:postcode":"V3S 1T8",
    "sg:province":"BC",
    "wof:name":"Cloverdale Nursery School",
    "wof:placetype":"venue"
},
  "geometry": {"coordinates":[-122.75664500000001,49.111542],"type":"Point"}
}