{
  "type": "Feature",
  "properties": {
    "iso:country":"CA",
    "sg:address":"153 Kelsey Blvd",
    "sg:city":"Churchill",
    "sg:classifiers":[
        {
            "category":"Travel",
            "subcategory":"Hotels & Motels",
            "type":"Entertainment"
        }
    ],
    "sg:phone":"+1 204 675 8878",
    "sg:postcode":"R0B 0E0",
    "sg:province":"MB",
    "wof:name":"Polar Inn",
    "wof:placetype":"venue"
},
  "geometry": {"coordinates":[-94.1679534912,58.7691192627],"type":"Point"}
}