{
  "type": "Feature",
  "properties": {
    "addr:full":"21 Macdonald Cres Swift Current SK S9H 3Y8",
    "addr:housenumber":"21",
    "addr:postcode":"s9h 3y8",
    "addr:street":"Macdonald Cres",
    "iso:country":"CA",
    "sg:address":"21 Macdonald Cres",
    "sg:city":"Swift Current",
    "sg:classifiers":[
        {
            "category":"Insurance",
            "subcategory":"Insurance Agent",
            "type":"Services"
        }
    ],
    "sg:phone":"+1 306 778 2674",
    "sg:postcode":"S9H 3Y8",
    "sg:province":"SK",
    "sg:tags":[
        "investment"
    ],
    "wof:name":"Kolskog Financial Svc",
    "wof:placetype":"venue"
},
  "geometry": {"coordinates":[-107.77016399999999,50.29311],"type":"Point"}
}