{
  "type": "Feature",
  "properties": {
    "addr:full":"Yorkton SK S3N 2X3",
    "addr:postcode":"s3n 2x3",
    "iso:country":"CA",
    "sg:city":"Yorkton",
    "sg:classifiers":[
        {
            "category":"Travel",
            "subcategory":"Campground",
            "type":"Entertainment"
        }
    ],
    "sg:phone":"+1 306 782 7080",
    "sg:postcode":"S3N 2X3",
    "sg:province":"SK",
    "wof:name":"York Lake Regional Park",
    "wof:placetype":"venue"
},
  "geometry": {"coordinates":[-102.441452,51.224876],"type":"Point"}
}