{
  "type": "Feature",
  "properties": {
    "addr:full":"22 Dixon Ave Toronto ON M4L 1N3",
    "addr:housenumber":"22",
    "addr:postcode":"m4l 1n3",
    "addr:street":"Dixon Ave",
    "iso:country":"CA",
    "sg:address":"22 Dixon Ave",
    "sg:city":"Toronto",
    "sg:classifiers":[
        {
            "category":"Shopping",
            "type":"Retail Goods"
        }
    ],
    "sg:phone":"+1 416 246 1656",
    "sg:postcode":"M4L 1N3",
    "sg:province":"ON",
    "sg:tags":[
        "telephone",
        "cellular"
    ],
    "wof:name":"Call Jeff Communications Inc",
    "wof:placetype":"venue"
},
  "geometry": {"coordinates":[-79.3102722168,43.6698875427],"type":"Point"}
}