{
  "type": "Feature",
  "properties": {
    "iso:country":"CA",
    "sg:address":"531 Beaurepaire Dr",
    "sg:city":"Beaconsfield",
    "sg:classifiers":[
        {
            "category":"Professional",
            "subcategory":"Advertising",
            "type":"Services"
        }
    ],
    "sg:phone":"+1 514 428 1060",
    "sg:postcode":"H9W 3C9",
    "sg:province":"QC",
    "sg:tags":[
        "publicity"
    ],
    "wof:name":"Groupe Paquet Marketing Inc",
    "wof:placetype":"venue"
},
  "geometry": {"coordinates":[-73.889831543,45.4255828857],"type":"Point"}
}