{
  "type": "Feature",
  "properties": {
    "iso:country":"CA",
    "sg:address":"836 Willow St",
    "sg:city":"Truro",
    "sg:classifiers":[
        {
            "category":"Food & Beverages",
            "subcategory":"Groceries & Convenience Stores",
            "type":"Retail Goods"
        }
    ],
    "sg:phone":"+1 902 895 4828",
    "sg:postcode":"B2N 6N7",
    "sg:province":"NS",
    "wof:name":"Jason's Convenience Stores",
    "wof:placetype":"venue"
},
  "geometry": {"coordinates":[-63.2931671143,45.3356704712],"type":"Point"}
}