{
  "type": "Feature",
  "properties": {
    "addr:full":"5409 47th St Castor AB T0C 0X0",
    "addr:housenumber":"5409",
    "addr:postcode":"t0c 0x0",
    "addr:street":"47Th St",
    "iso:country":"CA",
    "sg:address":"5409 47th St",
    "sg:city":"Castor",
    "sg:classifiers":[
        {
            "category":"Education",
            "subcategory":"School",
            "type":"Public Place"
        }
    ],
    "sg:phone":"+1 403 882 3309",
    "sg:postcode":"T0C 0X0",
    "sg:province":"AB",
    "wof:name":"Theresetta Catholic School",
    "wof:placetype":"venue"
},
  "geometry": {"coordinates":[-111.906745911,52.2235183716],"type":"Point"}
}