{
  "type": "Feature",
  "properties": {
    "addr:full":"5702 75 St NW Edmonton AB T6E 5X6",
    "addr:housenumber":"5702",
    "addr:postcode":"t6e 5x6",
    "addr:street":"75 St Nw",
    "iso:country":"CA",
    "sg:address":"5702 75 St NW",
    "sg:city":"Edmonton",
    "sg:classifiers":[
        {
            "category":"Restaurant",
            "type":"Food & Drink"
        }
    ],
    "sg:phone":"+1 780 469 8713",
    "sg:postcode":"T6E 5X6",
    "sg:province":"AB",
    "wof:name":"Kfc",
    "wof:placetype":"venue"
},
  "geometry": {"coordinates":[-113.442863,53.493221],"type":"Point"}
}