{
  "type": "Feature",
  "properties": {
    "addr:full":"Saint-Modeste QC G0L 3W0",
    "addr:postcode":"g0l 3w0",
    "iso:country":"CA",
    "sg:city":"Saint-Modeste",
    "sg:classifiers":[
        {
            "category":"Government",
            "subcategory":"Office",
            "type":"Public Place"
        }
    ],
    "sg:phone":"+1 418 862 0890",
    "sg:postcode":"G0L 3W0",
    "sg:province":"QC",
    "sg:tags":[
        "village"
    ],
    "wof:name":"St-Modeste Garage Municipal",
    "wof:placetype":"venue"
},
  "geometry": {"coordinates":[-69.402985,47.832966],"type":"Point"}
}