{
  "type": "Feature",
  "properties": {
    "addr:full":"5199 Rue Sherbrooke E # 3172 Montreal QC H1T 3X2",
    "addr:housenumber":"5199",
    "addr:postcode":"h1t 3x2",
    "addr:street":"Rue Sherbrooke E # 3172",
    "iso:country":"CA",
    "sg:address":"5199 Rue Sherbrooke E # 3172",
    "sg:city":"Montreal",
    "sg:classifiers":[
        {
            "category":"Health Services",
            "subcategory":"Podiatrist",
            "type":"Services"
        }
    ],
    "sg:phone":"+1 514 251 5433",
    "sg:postcode":"H1T 3X2",
    "sg:province":"QC",
    "sg:tags":[
        "clinic"
    ],
    "wof:name":"Clinique En Soins Des Pieds",
    "wof:placetype":"venue"
},
  "geometry": {"coordinates":[-73.552772522,45.5683364868],"type":"Point"}
}