{
  "type": "Feature",
  "properties": {
    "addr:full":"661 3E Rue O Barraute QC J0Y 1A0",
    "addr:housenumber":"661",
    "addr:postcode":"j0y 1a0",
    "addr:street":"3E Rue O",
    "iso:country":"CA",
    "sg:address":"661 3E Rue O",
    "sg:city":"Barraute",
    "sg:classifiers":[
        {
            "category":"Retail",
            "subcategory":"Animal Services",
            "type":"Services"
        }
    ],
    "sg:phone":"+1 819 734 6306",
    "sg:postcode":"J0Y 1A0",
    "sg:province":"QC",
    "sg:tags":[
        "pet",
        "grooming",
        "washing"
    ],
    "wof:name":"Compagnon Des Chiens",
    "wof:placetype":"venue"
},
  "geometry": {"coordinates":[-77.6404953003,48.4329071045],"type":"Point"}
}