{
  "type": "Feature",
  "properties": {
    "addr:full":"89 Dupont St Toronto ON M5R 1V4",
    "addr:housenumber":"89",
    "addr:postcode":"m5r 1v4",
    "addr:street":"Dupont St",
    "iso:country":"CA",
    "sg:address":"89 Dupont St",
    "sg:city":"Toronto",
    "sg:classifiers":[
        {
            "category":"Building & Trades",
            "subcategory":"Landscaping Services",
            "type":"Services"
        }
    ],
    "sg:phone":"+1 416 515 1686",
    "sg:postcode":"M5R 1V4",
    "sg:province":"ON",
    "sg:tags":[
        "lawn",
        "contractor",
        "landscape",
        "maintenance",
        "grounds"
    ],
    "wof:name":"Canlawn Landscape Maintenance",
    "wof:placetype":"venue"
},
  "geometry": {"coordinates":[-79.400909,43.676117],"type":"Point"}
}