{
  "type": "Feature",
  "properties": {
    "iso:country":"CA",
    "sg:address":"3065 Cawthra Rd",
    "sg:city":"Mississauga",
    "sg:classifiers":[
        {
            "category":"Organizations",
            "subcategory":"Religious Organization",
            "type":"Services"
        }
    ],
    "sg:phone":"+1 905 277 1620",
    "sg:postcode":"L5A 2X4",
    "sg:province":"ON",
    "sg:tags":[
        "church"
    ],
    "wof:name":"Dixie Presbyterian Church",
    "wof:placetype":"venue"
},
  "geometry": {"coordinates":[-79.6020736694,43.5961875916],"type":"Point"}
}