{
  "type": "Feature",
  "properties": {
    "iso:country":"CA",
    "sg:address":"289 Lakeview Crt",
    "sg:city":"Cobourg",
    "sg:classifiers":[
        {
            "category":"Professional",
            "subcategory":"Lawyer & Legal Services",
            "type":"Services"
        }
    ],
    "sg:phone":"+1 905 373 0589",
    "sg:postcode":"K9A 5C3",
    "sg:province":"ON",
    "sg:tags":[
        "attorney"
    ],
    "wof:name":"Ember Leigh Hamilton Law Ofc",
    "wof:placetype":"venue"
},
  "geometry": {"coordinates":[-78.153679,43.959927],"type":"Point"}
}