{
  "type": "Feature",
  "properties": {
    "addr:full":"Edmonton AB T5Z 2Y7",
    "addr:postcode":"t5z 2y7",
    "iso:country":"CA",
    "sg:city":"Edmonton",
    "sg:classifiers":[
        {
            "category":"Shopping",
            "subcategory":"Clothing, Apparel, & Fashions",
            "type":"Retail Goods"
        }
    ],
    "sg:phone":"+1 780 489 1985",
    "sg:postcode":"T5Z 2Y7",
    "sg:province":"AB",
    "sg:tags":[
        "infant",
        "wear"
    ],
    "wof:name":"Gap Kids",
    "wof:placetype":"venue"
},
  "geometry": {"coordinates":[-113.476799,53.63129],"type":"Point"}
}