{
  "type": "Feature",
  "properties": {
    "addr:full":"224 19th St W North Vancouver BC V7M 1X5",
    "addr:housenumber":"224",
    "addr:postcode":"v7m 1x5",
    "addr:street":"19Th St W",
    "iso:country":"CA",
    "sg:address":"224 19th St W",
    "sg:city":"North Vancouver",
    "sg:classifiers":[
        {
            "category":"Health Services",
            "subcategory":"Health Practitioner",
            "type":"Services"
        }
    ],
    "sg:phone":"+1 604 988 5221",
    "sg:postcode":"V7M 1X5",
    "sg:province":"BC",
    "sg:tags":[
        "physiotherapist"
    ],
    "wof:name":"19th Street Physiotherapy Clnc",
    "wof:placetype":"venue"
},
  "geometry": {"coordinates":[-123.07628631599999,49.3263931274],"type":"Point"}
}