{
  "type": "Feature",
  "properties": {
    "addr:full":"60 Riviera Dr Markham ON L3R 5M1",
    "addr:housenumber":"60",
    "addr:postcode":"l3r 5m1",
    "addr:street":"Riviera Dr",
    "iso:country":"CA",
    "sg:address":"60 Riviera Dr",
    "sg:city":"Markham",
    "sg:classifiers":[
        {
            "category":"Retail",
            "subcategory":"Laundry & Dry Cleaning",
            "type":"Services"
        }
    ],
    "sg:phone":"+1 905 475 5353",
    "sg:postcode":"L3R 5M1",
    "sg:province":"ON",
    "sg:tags":[
        "cleaners",
        "rug",
        "carpet"
    ],
    "wof:name":"Mac Eachern's Deep Steam",
    "wof:placetype":"venue"
},
  "geometry": {"coordinates":[-79.3437805176,43.8323173523],"type":"Point"}
}