{
  "type": "Feature",
  "properties": {
    "addr:full":"287 Main St Arborg MB R0C 0A0",
    "addr:housenumber":"287",
    "addr:postcode":"r0c 0a0",
    "addr:street":"Main St",
    "iso:country":"CA",
    "sg:address":"287 Main St",
    "sg:city":"Arborg",
    "sg:classifiers":[
        {
            "category":"Travel",
            "subcategory":"Hotels & Motels",
            "type":"Entertainment"
        }
    ],
    "sg:phone":"+1 204 376 9301",
    "sg:postcode":"R0C 0A0",
    "sg:province":"MB",
    "wof:name":"Arborg Hotel",
    "wof:placetype":"venue"
},
  "geometry": {"coordinates":[-97.21845999999999,50.908337],"type":"Point"}
}