{
  "type": "Feature",
  "properties": {
    "addr:full":"Anola MB R0E 0A0",
    "addr:postcode":"r0e 0a0",
    "iso:country":"CA",
    "sg:city":"Anola",
    "sg:classifiers":[
        {
            "category":"Food & Beverages",
            "subcategory":"Specialty",
            "type":"Retail Goods"
        }
    ],
    "sg:phone":"+1 204 866 2672",
    "sg:postcode":"R0E 0A0",
    "sg:province":"MB",
    "sg:tags":[
        "vitamin"
    ],
    "wof:name":"Diane South Watkins Products",
    "wof:placetype":"venue"
},
  "geometry": {"coordinates":[-96.6410903931,49.8850631714],"type":"Point"}
}