{
  "type": "Feature",
  "properties": {
    "addr:full":"Winnipeg MB R3L 2A8",
    "addr:postcode":"r3l 2a8",
    "iso:country":"CA",
    "sg:city":"Winnipeg",
    "sg:classifiers":[
        {
            "category":"Building & Trades",
            "subcategory":"Construction",
            "type":"Services"
        }
    ],
    "sg:phone":"+1 204 452 3478",
    "sg:postcode":"R3L 2A8",
    "sg:province":"MB",
    "sg:tags":[
        "cleaning",
        "steam"
    ],
    "wof:name":"Blast All Power Washing",
    "wof:placetype":"venue"
},
  "geometry": {"coordinates":[-97.136100769,49.8669548035],"type":"Point"}
}