{
  "type": "Feature",
  "properties": {
    "addr:full":"3975 Rue Saint-Ambroise Montreal QC H4C 2E1",
    "addr:housenumber":"3975",
    "addr:postcode":"h4c 2e1",
    "addr:street":"Rue Saint-Ambroise",
    "iso:country":"CA",
    "sg:address":"3975 Rue Saint-Ambroise",
    "sg:city":"Montreal",
    "sg:classifiers":[
        {
            "category":"Restaurant",
            "type":"Food & Drink"
        }
    ],
    "sg:phone":"+1 514 933 0939",
    "sg:postcode":"H4C 2E1",
    "sg:province":"QC",
    "sg:tags":[
        "grocer"
    ],
    "wof:name":"Distribution Alimentaire Aubut",
    "wof:placetype":"venue"
},
  "geometry": {"coordinates":[-73.58026099999999,45.475864],"type":"Point"}
}