{
  "type": "Feature",
  "properties": {
    "addr:full":"285 Princess St Kingston ON K7L 1B4",
    "addr:housenumber":"285",
    "addr:postcode":"k7l 1b4",
    "addr:street":"Princess St",
    "iso:country":"CA",
    "sg:address":"285 Princess St",
    "sg:city":"Kingston",
    "sg:classifiers":[
        {
            "category":"Restaurant",
            "type":"Food & Drink"
        }
    ],
    "sg:phone":"+1 613 549 3999",
    "sg:postcode":"K7L 1B4",
    "sg:province":"ON",
    "wof:name":"Mc Donald's",
    "wof:placetype":"venue"
},
  "geometry": {"coordinates":[-76.4884185791,44.2325973511],"type":"Point"}
}