{
  "type": "Feature",
  "properties": {
    "addr:full":"Aylmer ON N5H 1K9",
    "addr:postcode":"n5h 1k9",
    "iso:country":"CA",
    "sg:city":"Aylmer",
    "sg:classifiers":[
        {
            "category":"Health Services",
            "subcategory":"Chiropractor",
            "type":"Services"
        }
    ],
    "sg:phone":"+1 519 765 2565",
    "sg:postcode":"N5H 1K9",
    "sg:province":"ON",
    "wof:name":"Oswell Chiropractic Ctr",
    "wof:placetype":"venue"
},
  "geometry": {"coordinates":[-80.994392,42.773018],"type":"Point"}
}