{
  "type": "Feature",
  "properties": {
    "addr:full":"10339 Av Du Parc-Georges Montreal-Nord QC H1H 4Y4",
    "addr:postcode":"h1h 4y4",
    "addr:street":"Av Du Parc-Georges",
    "iso:country":"CA",
    "sg:address":"10339 Av Du Parc-Georges",
    "sg:city":"Montreal-Nord",
    "sg:classifiers":[
        {
            "category":"Education",
            "subcategory":"School",
            "type":"Public Place"
        }
    ],
    "sg:phone":"+1 514 321 2642",
    "sg:postcode":"H1H 4Y4",
    "sg:province":"QC",
    "sg:tags":[
        "academic",
        "special"
    ],
    "wof:name":"Centre Academique Fournier Inc",
    "wof:placetype":"venue"
},
  "geometry": {"coordinates":[-73.6407241821,45.5820808411],"type":"Point"}
}