{
  "type": "Feature",
  "properties": {
    "addr:full":"1515 Idylwyld Dr N Saskatoon SK S7L 1A9",
    "addr:housenumber":"1515",
    "addr:postcode":"s7l 1a9",
    "addr:street":"Idylwyld Dr N",
    "iso:country":"CA",
    "sg:address":"1515 Idylwyld Dr N",
    "sg:city":"Saskatoon",
    "sg:classifiers":[
        {
            "category":"Home & Garden",
            "subcategory":"Household Appliances",
            "type":"Retail Goods"
        }
    ],
    "sg:phone":"+1 306 244 2336",
    "sg:postcode":"S7L 1A9",
    "sg:province":"SK",
    "sg:tags":[
        "cleaners",
        "vacuum"
    ],
    "wof:name":"Speedy Vacuum Svc",
    "wof:placetype":"venue"
},
  "geometry": {"coordinates":[-106.670532227,52.148853302],"type":"Point"}
}