{
  "type": "Feature",
  "properties": {
    "addr:full":"550 Wellington St London ON N6A 3P9",
    "addr:housenumber":"550",
    "addr:postcode":"n6a 3p9",
    "addr:street":"Wellington St",
    "iso:country":"CA",
    "sg:address":"550 Wellington St",
    "sg:city":"London",
    "sg:classifiers":[
        {
            "category":"Government",
            "subcategory":"Office",
            "type":"Public Place"
        }
    ],
    "sg:phone":"+1 519 672 1967",
    "sg:postcode":"N6A 3P9",
    "sg:province":"ON",
    "sg:tags":[
        "village"
    ],
    "wof:name":"London Centennial Hall",
    "wof:placetype":"venue"
},
  "geometry": {"coordinates":[-81.24737548829999,42.9894943237],"type":"Point"}
}