{
  "type": "Feature",
  "properties": {
    "addr:full":"Mississauga ON L4W 4N8",
    "addr:postcode":"l4w 4n8",
    "iso:country":"CA",
    "sg:city":"Mississauga",
    "sg:classifiers":[
        {
            "category":"Manufacturing",
            "subcategory":"Tools & Machinery",
            "type":"Manufacturing & Wholesale Goods"
        }
    ],
    "sg:phone":"+1 905 670 7717",
    "sg:postcode":"L4W 4N8",
    "sg:province":"ON",
    "sg:tags":[
        "machine",
        "shop"
    ],
    "wof:name":"Poly Precision Ltd",
    "wof:placetype":"venue"
},
  "geometry": {"coordinates":[-79.6374282837,43.6549606323],"type":"Point"}
}