{
  "type": "Feature",
  "properties": {
    "iso:country":"CA",
    "sg:city":"Montreal",
    "sg:classifiers":[
        {
            "category":"Food & Beverages",
            "subcategory":"Groceries & Convenience Stores",
            "type":"Retail Goods"
        }
    ],
    "sg:phone":"+1 514 336 8313",
    "sg:postcode":"H4J 1E8",
    "sg:province":"QC",
    "wof:name":"Depanneur Nouveau Gouin Inc",
    "wof:placetype":"venue"
},
  "geometry": {"coordinates":[-73.72217559809999,45.5305671692],"type":"Point"}
}