{
  "type": "Feature",
  "properties": {
    "iso:country":"CA",
    "sg:address":"Hwy 18",
    "sg:city":"Killarney",
    "sg:classifiers":[
        {
            "category":"Wholesale",
            "subcategory":"Farm Supplies",
            "type":"Manufacturing & Wholesale Goods"
        }
    ],
    "sg:phone":"+1 204 523 3333",
    "sg:postcode":"R0K 1G0",
    "sg:province":"MB",
    "sg:tags":[
        "feed"
    ],
    "wof:name":"Feedmax",
    "wof:placetype":"venue"
},
  "geometry": {"coordinates":[-99.65715026860001,49.1804351807],"type":"Point"}
}