{
  "type": "Feature",
  "properties": {
    "iso:country":"CA",
    "sg:address":"RR 5 STN Main",
    "sg:city":"Kincardine",
    "sg:classifiers":[
        {
            "category":"Manufacturing",
            "subcategory":"Lumber",
            "type":"Manufacturing & Wholesale Goods"
        }
    ],
    "sg:phone":"+1 519 396 5493",
    "sg:postcode":"N2Z 2X6",
    "sg:province":"ON",
    "sg:tags":[
        "company",
        "logging"
    ],
    "wof:name":"Bruce County Sawing & Lumber",
    "wof:placetype":"venue"
},
  "geometry": {"coordinates":[-81.6317367554,44.1816139221],"type":"Point"}
}