{
  "type": "Feature",
  "properties": {
    "addr:full":"11689 Route 144 St Leonard NB E7E 2M4",
    "addr:housenumber":"11689",
    "addr:postcode":"e7e 2m4",
    "addr:street":"Route 144 St",
    "iso:country":"CA",
    "sg:address":"11689 Route 144",
    "sg:city":"St Leonard",
    "sg:classifiers":[
        {
            "category":"Personal",
            "subcategory":"Beauty Salon",
            "type":"Services"
        }
    ],
    "sg:phone":"+1 506 423 7591",
    "sg:postcode":"E7E 2M4",
    "sg:province":"NB",
    "wof:name":"Salon Ladi-Dy",
    "wof:placetype":"venue"
},
  "geometry": {"coordinates":[-67.922157,47.160114],"type":"Point"}
}