{
  "type": "Feature",
  "properties": {
    "iso:country":"CA",
    "sg:address":"19 Millfield Dr",
    "sg:city":"Winnipeg",
    "sg:classifiers":[
        {
            "category":"Wholesale",
            "subcategory":"Meat",
            "type":"Manufacturing & Wholesale Goods"
        }
    ],
    "sg:phone":"+1 204 231 4144",
    "sg:postcode":"R2M 2N9",
    "sg:province":"MB",
    "wof:name":"Frostland Meats",
    "wof:placetype":"venue"
},
  "geometry": {"coordinates":[-97.126427,49.821037],"type":"Point"}
}