{
  "type": "Feature",
  "properties": {
    "addr:full":"1450 Ski Club Rd North Bay ON P1B 8E6",
    "addr:postcode":"1450;p1b 8e6",
    "addr:street":"Ski Club Rd",
    "iso:country":"CA",
    "sg:address":"1450 Ski Club Rd",
    "sg:city":"North Bay",
    "sg:classifiers":[
        {
            "category":"Organizations",
            "subcategory":"Professional Association",
            "type":"Services"
        }
    ],
    "sg:phone":"+1 705 497 0373",
    "sg:postcode":"P1B 8E6",
    "sg:province":"ON",
    "wof:name":"Northwatch",
    "wof:placetype":"venue"
},
  "geometry": {"coordinates":[-79.41533699999999,46.329033],"type":"Point"}
}