{
  "type": "Feature",
  "properties": {
    "addr:full":"317 Millwood Rd Toronto ON M4S 1J9",
    "addr:housenumber":"317",
    "addr:postcode":"m4s 1j9",
    "addr:street":"Millwood Rd",
    "iso:country":"CA",
    "sg:address":"317 Millwood Rd",
    "sg:city":"Toronto",
    "sg:classifiers":[
        {
            "category":"Building & Trades",
            "subcategory":"Cleaning & Sanitation",
            "type":"Services"
        }
    ],
    "sg:phone":"+1 416 489 7447",
    "sg:postcode":"M4S 1J9",
    "sg:province":"ON",
    "sg:tags":[
        "butler",
        "maid",
        "house"
    ],
    "wof:name":"Merry Maids",
    "wof:placetype":"venue"
},
  "geometry": {"coordinates":[-79.3868942261,43.7016181946],"type":"Point"}
}