{
  "type": "Feature",
  "properties": {
    "iso:country":"CA",
    "sg:city":"Baie-Des-Sables",
    "sg:classifiers":[
        {
            "category":"Recreation",
            "type":"Entertainment"
        }
    ],
    "sg:phone":"+1 418 772 6260",
    "sg:postcode":"G0J 1C0",
    "sg:province":"QC",
    "sg:tags":[
        "center",
        "government"
    ],
    "wof:name":"Baie Des Sables Ctr Des Loisir",
    "wof:placetype":"venue"
},
  "geometry": {"coordinates":[-67.8719863892,48.7299995422],"type":"Point"}
}