{
  "type": "Feature",
  "properties": {
    "addr:full":"27 Oak St W Leamington ON N8H 2B1",
    "addr:housenumber":"27",
    "addr:postcode":"n8h 2b1",
    "addr:street":"Oak St W",
    "iso:country":"CA",
    "sg:address":"27 Oak St W",
    "sg:city":"Leamington",
    "sg:classifiers":[
        {
            "category":"Retail",
            "subcategory":"Car Wash",
            "type":"Services"
        }
    ],
    "sg:phone":"+1 519 322 2205",
    "sg:postcode":"N8H 2B1",
    "sg:province":"ON",
    "sg:tags":[
        "polishing",
        "washing"
    ],
    "wof:name":"Wash Around the Clock",
    "wof:placetype":"venue"
},
  "geometry": {"coordinates":[-82.60460662840001,42.0468635559],"type":"Point"}
}