{
  "type": "Feature",
  "properties": {
    "addr:full":"2905 Island Hwy Campbell River BC V9W 2H4",
    "addr:housenumber":"2905",
    "addr:postcode":"v9w 2h4",
    "addr:street":"Island Hwy",
    "iso:country":"CA",
    "sg:address":"2905 Island Hwy",
    "sg:city":"Campbell River",
    "sg:classifiers":[
        {
            "category":"Recreation",
            "type":"Entertainment"
        }
    ],
    "sg:phone":"+1 250 287 3246",
    "sg:postcode":"V9W 2H4",
    "sg:province":"BC",
    "sg:tags":[
        "hall",
        "auditorium"
    ],
    "wof:name":"Masonic Lodge",
    "wof:placetype":"venue"
},
  "geometry": {"coordinates":[-125.268829346,50.0460166931],"type":"Point"}
}