{
  "type": "Feature",
  "properties": {
    "addr:full":"4 Cooper Rd Victoria BC V9A 4K2",
    "addr:housenumber":"4",
    "addr:postcode":"v9a 4k2",
    "addr:street":"Cooper Rd",
    "iso:country":"CA",
    "sg:address":"4 Cooper Rd",
    "sg:city":"Victoria",
    "sg:classifiers":[
        {
            "category":"Retail",
            "subcategory":"Auto Repair",
            "type":"Services"
        }
    ],
    "sg:phone":"+1 250 360 0543",
    "sg:postcode":"V9A 4K2",
    "sg:province":"BC",
    "sg:tags":[
        "repairing",
        "automobile"
    ],
    "wof:name":"Lekwammen Auto",
    "wof:placetype":"venue"
},
  "geometry": {"coordinates":[-123.36451700000001,48.428314],"type":"Point"}
}