{
  "type": "Feature",
  "properties": {
    "iso:country":"CA",
    "sg:address":"4685 Caulfeild Dr",
    "sg:city":"West Vancouver",
    "sg:classifiers":[
        {
            "category":"Recreation",
            "type":"Entertainment"
        }
    ],
    "sg:phone":"+1 604 926 5179",
    "sg:postcode":"V7W 1E9",
    "sg:province":"BC",
    "sg:tags":[
        "club",
        "hockey"
    ],
    "wof:name":"West Vancouver Minor Hockey",
    "wof:placetype":"venue"
},
  "geometry": {"coordinates":[-123.247550964,49.3472709656],"type":"Point"}
}