{
  "type": "Feature",
  "properties": {
    "addr:full":"7 Caithness Ave Toronto ON M4J 3X6",
    "addr:housenumber":"7",
    "addr:postcode":"m4j 3x6",
    "addr:street":"Caithness Ave",
    "iso:country":"CA",
    "sg:address":"7 Caithness Ave",
    "sg:city":"Toronto",
    "sg:classifiers":[
        {
            "category":"Personal",
            "subcategory":"Beauty Salon",
            "type":"Services"
        }
    ],
    "sg:phone":"+1 416 466 7062",
    "sg:postcode":"M4J 3X6",
    "sg:province":"ON",
    "wof:name":"International Beauty Ctr",
    "wof:placetype":"venue"
},
  "geometry": {"coordinates":[-79.3347320557,43.6811485291],"type":"Point"}
}