{
  "type": "Feature",
  "properties": {
    "addr:full":"72 Miles Canyon Rd Whitehorse YT Y1A 6L4",
    "addr:housenumber":"72",
    "addr:postcode":"y1a 6l4",
    "addr:street":"Miles Canyon Rd",
    "iso:country":"CA",
    "sg:address":"72 Miles Canyon Rd",
    "sg:city":"Whitehorse",
    "sg:classifiers":[
        {
            "category":"Building & Trades",
            "subcategory":"Equipment Rental",
            "type":"Services"
        }
    ],
    "sg:phone":"+1 867 668 7761",
    "sg:postcode":"Y1A 6L4",
    "sg:province":"YT",
    "sg:tags":[
        "aircraft",
        "leasing",
        "charter"
    ],
    "wof:name":"Black Sheep Aviation",
    "wof:placetype":"venue"
},
  "geometry": {"coordinates":[-135.05316199999999,60.720871],"type":"Point"}
}