{
  "type": "Feature",
  "properties": {
    "iso:country":"CA",
    "sg:city":"Barrie",
    "sg:classifiers":[
        {
            "category":"Building & Trades",
            "subcategory":"Construction",
            "type":"Services"
        }
    ],
    "sg:phone":"+1 705 733 2641",
    "sg:postcode":"L4N 9P5",
    "sg:province":"ON",
    "sg:tags":[
        "maker",
        "cabinet"
    ],
    "wof:name":"Barlow Cabinet Works Ltd",
    "wof:placetype":"venue"
},
  "geometry": {"coordinates":[-79.678001,44.333069],"type":"Point"}
}