{
  "type": "Feature",
  "properties": {
    "addr:full":"17283 County Rd 18 St Andrews West ON K0C 2A0",
    "addr:housenumber":"17283;18",
    "addr:postcode":"k0c 2a0",
    "addr:street":"County Rd;St Andrews West",
    "iso:country":"CA",
    "sg:address":"17283 County Rd 18",
    "sg:city":"St Andrews West",
    "sg:classifiers":[
        {
            "category":"Education",
            "subcategory":"School",
            "type":"Public Place"
        }
    ],
    "sg:phone":"+1 613 932 6592",
    "sg:postcode":"K0C 2A0",
    "sg:province":"ON",
    "wof:name":"Ecole St Andrew's",
    "wof:placetype":"venue"
},
  "geometry": {"coordinates":[-74.800224,45.09539],"type":"Point"}
}