{
  "type": "Feature",
  "properties": {
    "addr:full":"1915 Lawrence Ave W York ON M9N 1G8",
    "addr:housenumber":"1915",
    "addr:postcode":"m9n 1g8",
    "addr:street":"Lawrence Ave W",
    "iso:country":"CA",
    "sg:address":"1915 Lawrence Ave W",
    "sg:city":"York",
    "sg:classifiers":[
        {
            "category":"Professional",
            "subcategory":"Accounting & Tax Preparation",
            "type":"Services"
        }
    ],
    "sg:phone":"+1 416 247 5582",
    "sg:postcode":"M9N 1G8",
    "sg:province":"ON",
    "sg:tags":[
        "bookkeeping",
        "return",
        "system",
        "filing"
    ],
    "wof:name":"B & H Assoc",
    "wof:placetype":"venue"
},
  "geometry": {"coordinates":[-79.504654,43.702667],"type":"Point"}
}