{
  "type": "Feature",
  "properties": {
    "addr:full":"1177 Boul Saint-Paul Chicoutimi QC G7J 3Y2",
    "addr:housenumber":"1177",
    "addr:postcode":"g7j 3y2",
    "addr:street":"Boul Saint-Paul",
    "iso:country":"CA",
    "sg:address":"1177 Boul Saint-Paul",
    "sg:city":"Chicoutimi",
    "sg:classifiers":[
        {
            "category":"Wholesale",
            "subcategory":"Construction Materials",
            "type":"Manufacturing & Wholesale Goods"
        }
    ],
    "sg:phone":"+1 418 696 1416",
    "sg:postcode":"G7J 3Y2",
    "sg:province":"QC",
    "sg:tags":[
        "fence"
    ],
    "wof:name":"Cloturex Inc",
    "wof:placetype":"venue"
},
  "geometry": {"coordinates":[-71.0888824463,48.4104042053],"type":"Point"}
}