{
  "type": "Feature",
  "properties": {
    "addr:full":"412 Rue Heriot Drummondville QC J2B 1B5",
    "addr:housenumber":"412",
    "addr:postcode":"j2b 1b5",
    "addr:street":"Rue Heriot",
    "iso:country":"CA",
    "sg:address":"412 Rue Heriot",
    "sg:city":"Drummondville",
    "sg:classifiers":[
        {
            "category":"Restaurant",
            "type":"Food & Drink"
        }
    ],
    "sg:phone":"+1 819 477 3191",
    "sg:postcode":"J2B 1B5",
    "sg:province":"QC",
    "sg:tags":[
        "register",
        "cash",
        "supply"
    ],
    "wof:name":"Fournitures DE Bureau R David",
    "wof:placetype":"venue"
},
  "geometry": {"coordinates":[-72.4832458496,45.8821907043],"type":"Point"}
}