{
  "type": "Feature",
  "properties": {
    "iso:country":"CA",
    "sg:address":"936 Elgin St",
    "sg:city":"Newmarket",
    "sg:classifiers":[
        {
            "category":"Professional",
            "subcategory":"Engineering",
            "type":"Services"
        }
    ],
    "sg:phone":"+1 905 898 3859",
    "sg:postcode":"L3Y 3C1",
    "sg:province":"ON",
    "sg:tags":[
        "engineer"
    ],
    "wof:name":"G Dewinne Management Inc",
    "wof:placetype":"venue"
},
  "geometry": {"coordinates":[-79.440071,44.072037],"type":"Point"}
}