{
  "type": "Feature",
  "properties": {
    "addr:full":"131 Archibald St N Thunder Bay ON P7C 3X7",
    "addr:housenumber":"131",
    "addr:postcode":"p7c 3x7",
    "addr:street":"Archibald St N",
    "iso:country":"CA",
    "sg:address":"131 Archibald St N",
    "sg:city":"Thunder Bay",
    "sg:classifiers":[
        {
            "category":"Professional",
            "subcategory":"Accounting & Tax Preparation",
            "type":"Services"
        }
    ],
    "sg:phone":"+1 807 623 8461",
    "sg:postcode":"P7C 3X7",
    "sg:province":"ON",
    "sg:tags":[
        "accountant"
    ],
    "wof:name":"Buset, Dennis L",
    "wof:placetype":"venue"
},
  "geometry": {"coordinates":[-89.249092,48.384693],"type":"Point"}
}