{
  "type": "Feature",
  "properties": {
    "addr:full":"5001 Windsor Ave Coronation AB T0C 1C0",
    "addr:housenumber":"5001",
    "addr:postcode":"t0c 1c0",
    "addr:street":"Windsor Ave",
    "iso:country":"CA",
    "sg:address":"5001 Windsor Ave",
    "sg:city":"Coronation",
    "sg:classifiers":[
        {
            "category":"Personal",
            "subcategory":"Beauty Salon",
            "type":"Services"
        }
    ],
    "sg:phone":"+1 403 578 4200",
    "sg:postcode":"T0C 1C0",
    "sg:province":"AB",
    "wof:name":"Permanent Attractions",
    "wof:placetype":"venue"
},
  "geometry": {"coordinates":[-111.44882200000001,52.093578],"type":"Point"}
}