{
  "type": "Feature",
  "properties": {
    "iso:country":"CA",
    "sg:city":"Vancouver",
    "sg:classifiers":[
        {
            "category":"Professional",
            "subcategory":"Employment Agencies",
            "type":"Services"
        }
    ],
    "sg:phone":"+1 604 683 1705",
    "sg:postcode":"V6C 1J9",
    "sg:province":"BC",
    "sg:tags":[
        "opportunity"
    ],
    "wof:name":"Olidan Search Partners Inc",
    "wof:placetype":"venue"
},
  "geometry": {"coordinates":[-123.116653,49.285728],"type":"Point"}
}