{
  "type": "Feature",
  "properties": {
    "addr:full":"1310 11 St SW Calgary AB T2R 1G6",
    "addr:housenumber":"1310",
    "addr:postcode":"t2r 1g6",
    "addr:street":"11 St Sw",
    "iso:country":"CA",
    "sg:address":"1310 11 St SW",
    "sg:city":"Calgary",
    "sg:classifiers":[
        {
            "category":"Professional",
            "type":"Services"
        }
    ],
    "sg:phone":"+1 403 777 9901",
    "sg:postcode":"T2R 1G6",
    "sg:province":"AB",
    "sg:tags":[
        "motion",
        "picture",
        "establishment",
        "studio",
        "producer"
    ],
    "wof:name":"Bradshaw Mac Leod & Assoc Ltd",
    "wof:placetype":"venue"
},
  "geometry": {"coordinates":[-114.08875999999999,51.041023],"type":"Point"}
}