{
  "type": "Feature",
  "properties": {
    "iso:country":"CA",
    "sg:address":"608 22 Ave",
    "sg:city":"Nisku",
    "sg:classifiers":[
        {
            "category":"Wholesale",
            "subcategory":"Machinery & Supplies",
            "type":"Manufacturing & Wholesale Goods"
        }
    ],
    "sg:phone":"+1 780 955 3500",
    "sg:postcode":"T9E 7X6",
    "sg:province":"AB",
    "sg:tags":[
        "contractor"
    ],
    "wof:name":"Dan-Mar Equipment Sales & Svc",
    "wof:placetype":"venue"
},
  "geometry": {"coordinates":[-113.526161194,53.3432159424],"type":"Point"}
}