{
  "type": "Feature",
  "properties": {
    "iso:country":"CA",
    "sg:city":"Nepean",
    "sg:classifiers":[
        {
            "category":"Education",
            "subcategory":"College",
            "type":"Public Place"
        }
    ],
    "sg:phone":"+1 613 224 8973",
    "sg:postcode":"K2G 3H8",
    "sg:province":"ON",
    "sg:tags":[
        "academic",
        "training",
        "computer"
    ],
    "wof:name":"Academy of Learning",
    "wof:placetype":"venue"
},
  "geometry": {"coordinates":[-75.73937225340001,45.3604850769],"type":"Point"}
}