{
  "type": "Feature",
  "properties": {
    "addr:full":"738 Clearwater Village Rd Clearwater BC V0E 1N0",
    "addr:housenumber":"738",
    "addr:postcode":"v0e 1n0",
    "addr:street":"Clearwater Village Rd",
    "iso:country":"CA",
    "sg:address":"738 Clearwater Village Rd",
    "sg:city":"Clearwater",
    "sg:classifiers":[
        {
            "category":"Utilities",
            "subcategory":"Refuse",
            "type":"Services"
        }
    ],
    "sg:phone":"+1 250 674 3086",
    "sg:postcode":"V0E 1N0",
    "sg:province":"BC",
    "sg:tags":[
        "garbage",
        "collection",
        "trucking"
    ],
    "wof:name":"Raymav Enterprises",
    "wof:placetype":"venue"
},
  "geometry": {"coordinates":[-120.012794,51.646557],"type":"Point"}
}