{
  "type": "Feature",
  "properties": {
    "addr:full":"12455 97 St NW Edmonton AB T5G 1Z6",
    "addr:housenumber":"12455",
    "addr:postcode":"t5g 1z6",
    "addr:street":"97 St Nw",
    "iso:country":"CA",
    "sg:address":"12455 97 St NW",
    "sg:city":"Edmonton",
    "sg:classifiers":[
        {
            "category":"Shopping",
            "subcategory":"Florist",
            "type":"Retail Goods"
        }
    ],
    "sg:phone":"+1 780 413 0707",
    "sg:postcode":"T5G 1Z6",
    "sg:province":"AB",
    "wof:name":"Flowers By Janice",
    "wof:placetype":"venue"
},
  "geometry": {"coordinates":[-113.491622925,53.5802841187],"type":"Point"}
}