{
  "type": "Feature",
  "properties": {
    "addr:full":"Revelstoke BC V0E 2S0",
    "addr:postcode":"v0e 2s0",
    "iso:country":"CA",
    "sg:city":"Revelstoke",
    "sg:classifiers":[
        {
            "category":"Shopping",
            "subcategory":"Shoes",
            "type":"Retail Goods"
        }
    ],
    "sg:phone":"+1 250 837 3855",
    "sg:postcode":"V0E 2S0",
    "sg:province":"BC",
    "wof:name":"Universal Foot Wear Ltd",
    "wof:placetype":"venue"
},
  "geometry": {"coordinates":[-118.19278,50.993423],"type":"Point"}
}