{
  "type": "Feature",
  "properties": {
    "iso:country":"CA",
    "sg:city":"Saint-Laurent",
    "sg:classifiers":[
        {
            "category":"Personal",
            "subcategory":"Beauty Salon",
            "type":"Services"
        }
    ],
    "sg:phone":"+1 514 747 4954",
    "sg:postcode":"H4L 3L3",
    "sg:province":"QC",
    "wof:name":"Salon DE Coiffure Sam",
    "wof:placetype":"venue"
},
  "geometry": {"coordinates":[-73.677925,45.511459],"type":"Point"}
}