{
  "type": "Feature",
  "properties": {
    "addr:full":"408 Raynor Ave Victoria BC V9A 3A6",
    "addr:housenumber":"408",
    "addr:postcode":"v9a 3a6",
    "addr:street":"Raynor Ave",
    "iso:country":"CA",
    "sg:address":"408 Raynor Ave",
    "sg:city":"Victoria",
    "sg:classifiers":[
        {
            "category":"Home & Garden",
            "subcategory":"Furniture",
            "type":"Retail Goods"
        }
    ],
    "sg:phone":"+1 250 595 4272",
    "sg:postcode":"V9A 3A6",
    "sg:province":"BC",
    "sg:tags":[
        "builder",
        "custom"
    ],
    "wof:name":"Inwood Designs",
    "wof:placetype":"venue"
},
  "geometry": {"coordinates":[-123.386292,48.436283],"type":"Point"}
}