{
  "type": "Feature",
  "properties": {
    "addr:full":"Hamilton ON L8M 1K2",
    "addr:postcode":"l8m 1k2",
    "iso:country":"CA",
    "sg:city":"Hamilton",
    "sg:classifiers":[
        {
            "category":"Professional",
            "subcategory":"Accounting & Tax Preparation",
            "type":"Services"
        }
    ],
    "sg:phone":"+1 905 547 6668",
    "sg:postcode":"L8M 1K2",
    "sg:province":"ON",
    "sg:tags":[
        "accountant"
    ],
    "wof:name":"Flumiani, Ennio CA",
    "wof:placetype":"venue"
},
  "geometry": {"coordinates":[-79.843025,43.248425],"type":"Point"}
}