{
  "type": "Feature",
  "properties": {
    "addr:full":"10116 101 Ave Lac LA Biche AB T0A 2C0",
    "addr:housenumber":"10116",
    "addr:postcode":"t0a 2c0",
    "addr:street":"101 Ave",
    "iso:country":"CA",
    "sg:address":"10116 101 Ave",
    "sg:city":"Lac LA Biche",
    "sg:classifiers":[
        {
            "category":"Insurance",
            "subcategory":"Insurance Agent",
            "type":"Services"
        }
    ],
    "sg:phone":"+1 780 623 4314",
    "sg:postcode":"T0A 2C0",
    "sg:province":"AB",
    "wof:name":"CO-Operators General Insurance",
    "wof:placetype":"venue"
},
  "geometry": {"coordinates":[-111.976539612,54.770488739],"type":"Point"}
}