{
  "type": "Feature",
  "properties": {
    "iso:country":"CA",
    "sg:address":"2305 Bloor St W",
    "sg:city":"Toronto",
    "sg:classifiers":[
        {
            "category":"Organizations",
            "subcategory":"Religious Organization",
            "type":"Services"
        }
    ],
    "sg:phone":"+1 416 767 1859",
    "sg:postcode":"M6S 1P1",
    "sg:province":"ON",
    "sg:tags":[
        "church"
    ],
    "wof:name":"St Pius X Church",
    "wof:placetype":"venue"
},
  "geometry": {"coordinates":[-79.47937774659999,43.6503067017],"type":"Point"}
}