{
  "type": "Feature",
  "properties": {
    "addr:full":"975 Rue Richelieu LA Malbaie QC G5A 2X8",
    "addr:housenumber":"975",
    "addr:postcode":"g5a 2x8",
    "addr:street":"Rue Richelieu",
    "iso:country":"CA",
    "sg:address":"975 Rue Richelieu",
    "sg:city":"LA Malbaie",
    "sg:classifiers":[
        {
            "category":"Building & Trades",
            "subcategory":"Construction",
            "type":"Services"
        }
    ],
    "sg:phone":"+1 418 665 8181",
    "sg:postcode":"G5A 2X8",
    "sg:province":"QC",
    "sg:tags":[
        "contractor",
        "general"
    ],
    "wof:name":"Construction Belley Francois",
    "wof:placetype":"venue"
},
  "geometry": {"coordinates":[-70.143219,47.634083],"type":"Point"}
}