{
  "type": "Feature",
  "properties": {
    "addr:full":"111 Main St S Kenora ON P9N 1T1",
    "addr:housenumber":"111",
    "addr:postcode":"p9n 1t1",
    "addr:street":"Main St S",
    "iso:country":"CA",
    "sg:address":"111 Main St S",
    "sg:city":"Kenora",
    "sg:classifiers":[
        {
            "category":"Banks & Credit Unions",
            "subcategory":"Bank",
            "type":"Services"
        }
    ],
    "sg:phone":"+1 807 468 8933",
    "sg:postcode":"P9N 1T1",
    "sg:province":"ON",
    "wof:name":"Cibc",
    "wof:placetype":"venue"
},
  "geometry": {"coordinates":[-94.4900512695,49.7674102783],"type":"Point"}
}