{
  "type": "Feature",
  "properties": {
    "iso:country":"CA",
    "sg:address":"1st St S",
    "sg:city":"Turtleford",
    "sg:classifiers":[
        {
            "category":"Health Services",
            "subcategory":"Doctor",
            "type":"Services"
        }
    ],
    "sg:phone":"+1 306 845 2277",
    "sg:postcode":"S0M 2Y0",
    "sg:province":"SK",
    "sg:tags":[
        "physician",
        "clinic",
        "surgeon"
    ],
    "wof:name":"Riverside Medical Clinic",
    "wof:placetype":"venue"
},
  "geometry": {"coordinates":[-108.95655059800001,53.3879508972],"type":"Point"}
}