{
  "type": "Feature",
  "properties": {
    "addr:full":"905 Millwood Rd East York ON M4G 1X2",
    "addr:housenumber":"905",
    "addr:postcode":"m4g 1x2",
    "addr:street":"Millwood Rd",
    "iso:country":"CA",
    "sg:address":"905 Millwood Rd",
    "sg:city":"East York",
    "sg:classifiers":[
        {
            "category":"Professional",
            "subcategory":"Management & Consulting",
            "type":"Services"
        }
    ],
    "sg:phone":"+1 416 424 4194",
    "sg:postcode":"M4G 1X2",
    "sg:province":"ON",
    "sg:tags":[
        "supply",
        "equipment",
        "planning",
        "wine",
        "party"
    ],
    "wof:name":"Millwood Wine Works",
    "wof:placetype":"venue"
},
  "geometry": {"coordinates":[-79.36378479,43.7031745911],"type":"Point"}
}