{
  "type": "Feature",
  "properties": {
    "addr:full":"425 Rue Principale S Sainte-Perpetue-DE-L'Islet QC G0R 3Z0",
    "addr:housenumber":"425",
    "addr:postcode":"g0r 3z0",
    "addr:street":"Rue Principale S Sainte-Perpetue-De-L'Islet",
    "iso:country":"CA",
    "sg:address":"425 Rue Principale S",
    "sg:city":"Sainte-Perpetue-DE-L'Islet",
    "sg:classifiers":[
        {
            "category":"Government",
            "subcategory":"Office",
            "type":"Public Place"
        }
    ],
    "sg:phone":"+1 418 359 3501",
    "sg:postcode":"G0R 3Z0",
    "sg:province":"QC",
    "sg:tags":[
        "village"
    ],
    "wof:name":"Ste Perpetue Garage",
    "wof:placetype":"venue"
},
  "geometry": {"coordinates":[-70.331535,47.089802],"type":"Point"}
}