{
  "type": "Feature",
  "properties": {
    "addr:full":"2094 Davis Rd Peterborough ON K9J 6X4",
    "addr:housenumber":"2094",
    "addr:postcode":"k9j 6x4",
    "addr:street":"Davis Rd",
    "iso:country":"CA",
    "sg:address":"2094 Davis Rd",
    "sg:city":"Peterborough",
    "sg:classifiers":[
        {
            "category":"Building & Trades",
            "subcategory":"Construction",
            "type":"Services"
        }
    ],
    "sg:phone":"+1 705 742 2267",
    "sg:postcode":"K9J 6X4",
    "sg:province":"ON",
    "sg:tags":[
        "plastering",
        "painter",
        "contractor"
    ],
    "wof:name":"A J DE Carlo Construction",
    "wof:placetype":"venue"
},
  "geometry": {"coordinates":[-78.32131200000001,44.300732],"type":"Point"}
}