{
  "type": "Feature",
  "properties": {
    "addr:full":"2318 Keele St North York ON M6M 3Z8",
    "addr:housenumber":"2318",
    "addr:postcode":"m6m 3z8",
    "addr:street":"Keele St",
    "iso:country":"CA",
    "sg:address":"2318 Keele St",
    "sg:city":"North York",
    "sg:classifiers":[
        {
            "category":"Restaurant",
            "type":"Food & Drink"
        }
    ],
    "sg:phone":"+1 416 248 9919",
    "sg:postcode":"M6M 3Z8",
    "sg:province":"ON",
    "wof:name":"Mr Sub",
    "wof:placetype":"venue"
},
  "geometry": {"coordinates":[-79.4771194458,43.7038345337],"type":"Point"}
}