{
  "type": "Feature",
  "properties": {
    "iso:country":"CA",
    "sg:city":"Peace River",
    "sg:classifiers":[
        {
            "category":"Real Estate",
            "subcategory":"Real Estate Operator",
            "type":"Services"
        }
    ],
    "sg:phone":"+1 780 624 8683",
    "sg:postcode":"T8S 1B9",
    "sg:province":"AB",
    "sg:tags":[
        "apartment"
    ],
    "wof:name":"Northern Lites Apartments",
    "wof:placetype":"venue"
},
  "geometry": {"coordinates":[-117.291847229,56.2546195984],"type":"Point"}
}