{
  "type": "Feature",
  "properties": {
    "addr:full":"PO Box 1505 Mississippi Station ON K0H 2C0",
    "addr:housenumber":"po",
    "addr:postcode":"k0h 2c0",
    "addr:street":"Box 1505;Station",
    "iso:country":"CA",
    "sg:address":"PO Box 1505",
    "sg:city":"Mississippi Station",
    "sg:classifiers":[
        {
            "category":"Organizations",
            "subcategory":"Religious Organization",
            "type":"Services"
        }
    ],
    "sg:phone":"+1 613 279 2528",
    "sg:postcode":"K0H 2C0",
    "sg:province":"ON",
    "sg:tags":[
        "church"
    ],
    "wof:name":"Free Methodist Church",
    "wof:placetype":"venue"
},
  "geometry": {"coordinates":[-76.677628,44.923183],"type":"Point"}
}