{
  "type": "Feature",
  "properties": {
    "addr:full":"680 Boul Barrette Val-D'Or QC J9P 7G6",
    "addr:housenumber":"680",
    "addr:postcode":"j9p 7g6",
    "addr:street":"Boul Barrette",
    "iso:country":"CA",
    "sg:address":"680 Boul Barrette",
    "sg:city":"Val-D'Or",
    "sg:classifiers":[
        {
            "category":"Food & Beverages",
            "subcategory":"Groceries & Convenience Stores",
            "type":"Retail Goods"
        }
    ],
    "sg:phone":"+1 819 825 5000",
    "sg:postcode":"J9P 7G6",
    "sg:province":"QC",
    "sg:tags":[
        "grocer"
    ],
    "wof:name":"Loblaws",
    "wof:placetype":"venue"
},
  "geometry": {"coordinates":[-71.0033187866,45.3835067749],"type":"Point"}
}