{
  "type": "Feature",
  "properties": {
    "addr:full":"538 St Clair Ave W Toronto ON M6C 1A4",
    "addr:housenumber":"538",
    "addr:postcode":"m6c 1a4",
    "addr:street":"St Clair Ave W",
    "iso:country":"CA",
    "sg:address":"538 St Clair Ave W",
    "sg:city":"Toronto",
    "sg:classifiers":[
        {
            "category":"Retail",
            "subcategory":"Laundry & Dry Cleaning",
            "type":"Services"
        }
    ],
    "sg:phone":"+1 416 654 4779",
    "sg:postcode":"M6C 1A4",
    "sg:province":"ON",
    "sg:tags":[
        "cleaners",
        "rug",
        "carpet"
    ],
    "wof:name":"Persian & Oriental Rug Svc",
    "wof:placetype":"venue"
},
  "geometry": {"coordinates":[-79.4199066162,43.6829681396],"type":"Point"}
}