{
  "type": "Feature",
  "properties": {
    "addr:full":"675 Ch Du Golf O Drummondville QC J2B 8A8",
    "addr:housenumber":"675",
    "addr:postcode":"j2b 8a8",
    "addr:street":"Ch Du Golf O",
    "iso:country":"CA",
    "sg:address":"675 Ch Du Golf O",
    "sg:city":"Drummondville",
    "sg:classifiers":[
        {
            "category":"Professional",
            "subcategory":"Management & Consulting",
            "type":"Services"
        }
    ],
    "sg:phone":"+1 819 478 6092",
    "sg:postcode":"J2B 8A8",
    "sg:province":"QC",
    "sg:tags":[
        "personnel",
        "consultant"
    ],
    "wof:name":"Manpower Service DE Personnel",
    "wof:placetype":"venue"
},
  "geometry": {"coordinates":[-72.504051,45.905315],"type":"Point"}
}