{
  "type": "Feature",
  "properties": {
    "addr:full":"46 Milltown Blvd St Stephen NB E3L 1G3",
    "addr:housenumber":"46",
    "addr:postcode":"e3l 1g3",
    "addr:street":"Milltown Blvd",
    "iso:country":"CA",
    "sg:address":"46 Milltown Blvd",
    "sg:city":"St Stephen",
    "sg:classifiers":[
        {
            "category":"Professional",
            "subcategory":"Lawyer & Legal Services",
            "type":"Services"
        }
    ],
    "sg:phone":"+1 506 466 2338",
    "sg:postcode":"E3L 1G3",
    "sg:province":"NB",
    "sg:tags":[
        "attorney"
    ],
    "wof:name":"Nicholson, G Fred QC",
    "wof:placetype":"venue"
},
  "geometry": {"coordinates":[-67.277176,45.192505],"type":"Point"}
}