{
  "type": "Feature",
  "properties": {
    "addr:full":"41 Woodward Dr Whitby ON L1N 8X4",
    "addr:housenumber":"41",
    "addr:postcode":"l1n 8x4",
    "addr:street":"Woodward Dr",
    "iso:country":"CA",
    "sg:address":"41 Woodward Dr",
    "sg:city":"Whitby",
    "sg:classifiers":[
        {
            "category":"Professional",
            "subcategory":"Research",
            "type":"Services"
        }
    ],
    "sg:phone":"+1 905 666 7287",
    "sg:postcode":"L1N 8X4",
    "sg:province":"ON",
    "sg:tags":[
        "environmental",
        "ecological"
    ],
    "wof:name":"Aquaphyte Remediation Inc",
    "wof:placetype":"venue"
},
  "geometry": {"coordinates":[-78.936272,43.899288],"type":"Point"}
}