{
  "type": "Feature",
  "properties": {
    "iso:country":"CA",
    "sg:address":"632 Mckay St",
    "sg:city":"Kingston",
    "sg:classifiers":[
        {
            "category":"Health Services",
            "subcategory":"Health Practitioner",
            "type":"Services"
        }
    ],
    "sg:phone":"+1 613 384 3114",
    "sg:postcode":"K7M 5V9",
    "sg:province":"ON",
    "sg:tags":[
        "psychologist"
    ],
    "wof:name":"Nogrady, Heather PhD",
    "wof:placetype":"venue"
},
  "geometry": {"coordinates":[-76.57708740229999,44.243724823],"type":"Point"}
}