{
  "type": "Feature",
  "properties": {
    "addr:full":"92 DE Rose Ave Bolton ON L7E 1A8",
    "addr:postcode":"l7e 1a8",
    "addr:street":"92 De Rose Ave",
    "iso:country":"CA",
    "sg:address":"92 DE Rose Ave",
    "sg:city":"Bolton",
    "sg:classifiers":[
        {
            "category":"Building & Trades",
            "subcategory":"Cleaning & Sanitation",
            "type":"Services"
        }
    ],
    "sg:phone":"+1 905 857 7867",
    "sg:postcode":"L7E 1A8",
    "sg:province":"ON",
    "sg:tags":[
        "janitor"
    ],
    "wof:name":"Keys Janitorial Svc",
    "wof:placetype":"venue"
},
  "geometry": {"coordinates":[-79.7509,43.873783],"type":"Point"}
}