{
  "type": "Feature",
  "properties": {
    "addr:full":"15 Polson St Toronto ON M5A 1A4",
    "addr:housenumber":"15",
    "addr:postcode":"m5a 1a4",
    "addr:street":"Polson St",
    "iso:country":"CA",
    "sg:address":"15 Polson St",
    "sg:city":"Toronto",
    "sg:classifiers":[
        {
            "category":"Wholesale",
            "subcategory":"Apparel",
            "type":"Manufacturing & Wholesale Goods"
        }
    ],
    "sg:phone":"+1 416 461 9888",
    "sg:postcode":"M5A 1A4",
    "sg:province":"ON",
    "sg:tags":[
        "textile"
    ],
    "wof:name":"Momentum Group Inc",
    "wof:placetype":"venue"
},
  "geometry": {"coordinates":[-79.353882,43.641499],"type":"Point"}
}