{
  "type": "Feature",
  "properties": {
    "iso:country":"CA",
    "sg:address":"37 2E Ave",
    "sg:city":"Forestville",
    "sg:classifiers":[
        {
            "category":"Shopping",
            "subcategory":"Tobacco",
            "type":"Retail Goods"
        }
    ],
    "sg:phone":"+1 418 587 2803",
    "sg:postcode":"G0T 1E0",
    "sg:province":"QC",
    "sg:tags":[
        "cigarette",
        "cigar",
        "dealer"
    ],
    "wof:name":"Tabagie Depanneur Duchesne Enr",
    "wof:placetype":"venue"
},
  "geometry": {"coordinates":[-69.08145141599999,48.7389831543],"type":"Point"}
}