{
  "type": "Feature",
  "properties": {
    "addr:full":"11 Wilson St Bethany ON L0A 1A0",
    "addr:housenumber":"11",
    "addr:postcode":"l0a 1a0",
    "addr:street":"Wilson St",
    "iso:country":"CA",
    "sg:address":"11 Wilson St",
    "sg:city":"Bethany",
    "sg:classifiers":[
        {
            "category":"Building & Trades",
            "subcategory":"Construction",
            "type":"Services"
        }
    ],
    "sg:phone":"+1 705 277 3638",
    "sg:postcode":"L0A 1A0",
    "sg:province":"ON",
    "sg:tags":[
        "dry wall",
        "contractor"
    ],
    "wof:name":"Curtis D Drywall",
    "wof:placetype":"venue"
},
  "geometry": {"coordinates":[-78.567795,44.181152],"type":"Point"}
}