{
  "type": "Feature",
  "properties": {
    "addr:full":"240 Rue Saint-Michel Oka QC J0N 1E0",
    "addr:housenumber":"240",
    "addr:postcode":"j0n 1e0",
    "addr:street":"Rue Saint-Michel",
    "iso:country":"CA",
    "sg:address":"240 Rue Saint-Michel",
    "sg:city":"Oka",
    "sg:classifiers":[
        {
            "category":"Organizations",
            "subcategory":"Religious Organization",
            "type":"Services"
        }
    ],
    "sg:phone":"+1 514 479 6317",
    "sg:postcode":"J0N 1E0",
    "sg:province":"QC",
    "sg:tags":[
        "church"
    ],
    "wof:name":"Oka United Church",
    "wof:placetype":"venue"
},
  "geometry": {"coordinates":[-74.093025,45.461388],"type":"Point"}
}