{
  "type": "Feature",
  "properties": {
    "iso:country":"CA",
    "sg:address":"5 Stover St S",
    "sg:city":"Norwich",
    "sg:classifiers":[
        {
            "category":"Home & Garden",
            "subcategory":"Carpets & Floor Coverings",
            "type":"Retail Goods"
        }
    ],
    "sg:phone":"+1 519 863 3555",
    "sg:postcode":"N0J 1P0",
    "sg:province":"ON",
    "sg:tags":[
        "material",
        "dealer",
        "rug"
    ],
    "wof:name":"Verne's Carpet One",
    "wof:placetype":"venue"
},
  "geometry": {"coordinates":[-80.5970916748,42.9869804382],"type":"Point"}
}