{
  "type": "Feature",
  "properties": {
    "iso:country":"CA",
    "sg:address":"1105 Roland St",
    "sg:city":"Thunder Bay",
    "sg:classifiers":[
        {
            "category":"Wholesale",
            "subcategory":"Machinery & Supplies",
            "type":"Manufacturing & Wholesale Goods"
        }
    ],
    "sg:phone":"+1 807 625 5556",
    "sg:postcode":"P7B 5M5",
    "sg:province":"ON",
    "sg:tags":[
        "engine",
        "equipment",
        "hydraulic"
    ],
    "wof:name":"Lakeside Injection & Turbo Ltd",
    "wof:placetype":"venue"
},
  "geometry": {"coordinates":[-89.257004,48.402561],"type":"Point"}
}