{
  "type": "Feature",
  "properties": {
    "addr:full":"2711 Old Norwood Rd Peterborough ON K9J 6X8",
    "addr:housenumber":"2711",
    "addr:postcode":"k9j 6x8",
    "addr:street":"Old Norwood Rd",
    "iso:country":"CA",
    "sg:address":"2711 Old Norwood Rd",
    "sg:city":"Peterborough",
    "sg:classifiers":[
        {
            "category":"Building & Trades",
            "subcategory":"Construction",
            "type":"Services"
        }
    ],
    "sg:phone":"+1 705 742 4914",
    "sg:postcode":"K9J 6X8",
    "sg:province":"ON",
    "sg:tags":[
        "maker",
        "cabinet"
    ],
    "wof:name":"Will Kloosterman Cabinetry",
    "wof:placetype":"venue"
},
  "geometry": {"coordinates":[-78.28969600000001,44.315289],"type":"Point"}
}