{
  "type": "Feature",
  "properties": {
    "addr:full":"8250 Sabre Rd Lantzville BC V0R 2H0",
    "addr:housenumber":"8250",
    "addr:postcode":"v0r 2h0",
    "addr:street":"Sabre Rd",
    "iso:country":"CA",
    "sg:address":"8250 Sabre Rd",
    "sg:city":"Lantzville",
    "sg:classifiers":[
        {
            "category":"Shopping",
            "subcategory":"Bicycles & Sporting Goods",
            "type":"Retail Goods"
        }
    ],
    "sg:phone":"+1 250 390 4000",
    "sg:postcode":"V0R 2H0",
    "sg:province":"BC",
    "sg:tags":[
        "equipment",
        "golf"
    ],
    "wof:name":"Riverside Golf Ctr",
    "wof:placetype":"venue"
},
  "geometry": {"coordinates":[-124.132362366,49.251499176],"type":"Point"}
}