{
  "type": "Feature",
  "properties": {
    "iso:country":"CA",
    "sg:address":"8250 Sabre Rd",
    "sg:city":"Lantzville",
    "sg:classifiers":[
        {
            "category":"Shopping",
            "subcategory":"Bicycles & Sporting Goods",
            "type":"Retail Goods"
        }
    ],
    "sg:phone":"+1 250 390 4000",
    "sg:postcode":"V0R 2H0",
    "sg:province":"BC",
    "sg:tags":[
        "equipment",
        "golf"
    ],
    "wof:name":"Riverside Golf Ctr",
    "wof:placetype":"venue"
},
  "geometry": {"coordinates":[-124.132362366,49.251499176],"type":"Point"}
}