{
  "type": "Feature",
  "properties": {
    "addr:full":"4315 County Road 1 Yarker ON K0K 3N0",
    "addr:housenumber":"4315",
    "addr:postcode":"k0k 3n0",
    "addr:street":"County Road 1 Yarker",
    "iso:country":"CA",
    "sg:address":"4315 County Road 1",
    "sg:city":"Yarker",
    "sg:classifiers":[
        {
            "category":"Education",
            "subcategory":"School",
            "type":"Public Place"
        }
    ],
    "sg:phone":"+1 613 377 6714",
    "sg:postcode":"K0K 3N0",
    "sg:province":"ON",
    "wof:name":"Yarker Public School",
    "wof:placetype":"venue"
},
  "geometry": {"coordinates":[-76.771103,44.371746],"type":"Point"}
}