{
  "type": "Feature",
  "properties": {
    "addr:full":"Calgary AB T2S 2T6",
    "addr:postcode":"t2s 2t6",
    "iso:country":"CA",
    "sg:city":"Calgary",
    "sg:classifiers":[
        {
            "category":"Personal",
            "type":"Services"
        }
    ],
    "sg:phone":"+1 403 243 6610",
    "sg:postcode":"T2S 2T6",
    "sg:province":"AB",
    "sg:tags":[
        "therapist",
        "massage"
    ],
    "wof:name":"Britannia Body Work Ctr",
    "wof:placetype":"venue"
},
  "geometry": {"coordinates":[-114.08151245099999,51.0094604492],"type":"Point"}
}