{
  "type": "Feature",
  "properties": {
    "addr:full":"335 Lake St St Catharines ON L2N 4H5",
    "addr:housenumber":"335",
    "addr:postcode":"l2n 4h5",
    "addr:street":"Lake St",
    "iso:country":"CA",
    "sg:address":"335 Lake St",
    "sg:city":"St Catharines",
    "sg:classifiers":[
        {
            "category":"Retail",
            "subcategory":"Auto Repair",
            "type":"Services"
        }
    ],
    "sg:phone":"+1 905 934 6624",
    "sg:postcode":"L2N 4H5",
    "sg:province":"ON",
    "sg:tags":[
        "repairing",
        "automobile"
    ],
    "wof:name":"More Than Tires",
    "wof:placetype":"venue"
},
  "geometry": {"coordinates":[-79.2517318726,43.1815032959],"type":"Point"}
}