{
  "type": "Feature",
  "properties": {
    "addr:full":"1055 Georgia St W #1600 Vancouver BC V6E 3P3",
    "addr:housenumber":"1055",
    "addr:postcode":"v6e 3p3",
    "addr:street":"Georgia St W # 1600",
    "iso:country":"CA",
    "sg:address":"1055 Georgia St W #1600",
    "sg:city":"Vancouver",
    "sg:classifiers":[
        {
            "category":"Real Estate",
            "subcategory":"Real Estate Operator",
            "type":"Services"
        }
    ],
    "sg:phone":"+1 604 689 1711",
    "sg:postcode":"V6E 3P3",
    "sg:province":"BC",
    "sg:tags":[
        "building",
        "mall",
        "shopping",
        "center",
        "parks"
    ],
    "wof:name":"Royal Centre",
    "wof:placetype":"venue"
},
  "geometry": {"coordinates":[-123.122124,49.285271],"type":"Point"}
}