{
  "type": "Feature",
  "properties": {
    "addr:full":"3867 Marpole St Port Alberni BC V9Y 6Y3",
    "addr:housenumber":"3867",
    "addr:postcode":"v9y 6y3",
    "addr:street":"Marpole St",
    "iso:country":"CA",
    "sg:address":"3867 Marpole St",
    "sg:city":"Port Alberni",
    "sg:classifiers":[
        {
            "category":"Education",
            "subcategory":"School",
            "type":"Public Place"
        }
    ],
    "sg:phone":"+1 250 723 7521",
    "sg:postcode":"V9Y 6Y3",
    "sg:province":"BC",
    "wof:name":"John Howitt Elementary School",
    "wof:placetype":"venue"
},
  "geometry": {"coordinates":[-124.79354858400001,49.2712669373],"type":"Point"}
}