{
  "type": "Feature",
  "properties": {
    "addr:full":"5910 Rue DE Marseille Montreal QC H1N 1K3",
    "addr:housenumber":"5910",
    "addr:postcode":"h1n 1k3",
    "addr:street":"Rue De Marseille",
    "iso:country":"CA",
    "sg:address":"5910 Rue DE Marseille",
    "sg:city":"Montreal",
    "sg:classifiers":[
        {
            "category":"Wholesale",
            "subcategory":"Electrical",
            "type":"Manufacturing & Wholesale Goods"
        }
    ],
    "sg:phone":"+1 514 251 9152",
    "sg:postcode":"H1N 1K3",
    "sg:province":"QC",
    "sg:tags":[
        "control",
        "burglary",
        "security",
        "protective",
        "robbery"
    ],
    "wof:name":"Leduc Securite",
    "wof:placetype":"venue"
},
  "geometry": {"coordinates":[-73.542252,45.574245],"type":"Point"}
}