{
  "type": "Feature",
  "properties": {
    "addr:full":"35 Cambridge St Cambridge ON N1R 3R8",
    "addr:housenumber":"35",
    "addr:postcode":"n1r 3r8",
    "addr:street":"Cambridge St",
    "iso:country":"CA",
    "sg:address":"35 Cambridge St",
    "sg:city":"Cambridge",
    "sg:classifiers":[
        {
            "category":"Professional",
            "subcategory":"Lawyer & Legal Services",
            "type":"Services"
        }
    ],
    "sg:phone":"+1 519 621 7779",
    "sg:postcode":"N1R 3R8",
    "sg:province":"ON",
    "sg:tags":[
        "attorney"
    ],
    "wof:name":"Clement, Gregory J",
    "wof:placetype":"venue"
},
  "geometry": {"coordinates":[-80.3125,43.362255],"type":"Point"}
}