{
  "type": "Feature",
  "properties": {
    "addr:full":"1805 Wilson Ave North York ON M9M 1A2",
    "addr:housenumber":"1805",
    "addr:postcode":"m9m 1a2",
    "addr:street":"Wilson Ave",
    "iso:country":"CA",
    "sg:address":"1805 Wilson Ave",
    "sg:city":"North York",
    "sg:classifiers":[
        {
            "category":"Shopping",
            "type":"Retail Goods"
        }
    ],
    "sg:phone":"+1 416 742 4111",
    "sg:postcode":"M9M 1A2",
    "sg:province":"ON",
    "sg:tags":[
        "equipment",
        "telephone",
        "supply"
    ],
    "wof:name":"Balcom Systems Ltd",
    "wof:placetype":"venue"
},
  "geometry": {"coordinates":[-79.5221405029,43.7177772522],"type":"Point"}
}