{
  "type": "Feature",
  "properties": {
    "addr:full":"358 Guelph St Georgetown ON L7G 4B5",
    "addr:housenumber":"358",
    "addr:postcode":"l7g 4b5",
    "addr:street":"Guelph St",
    "iso:country":"CA",
    "sg:address":"358 Guelph St",
    "sg:city":"Georgetown",
    "sg:classifiers":[
        {
            "category":"Autos & Motor Vehicles",
            "subcategory":"Fuel & Gas Station",
            "type":"Retail Goods"
        }
    ],
    "sg:phone":"+1 905 873 2425",
    "sg:postcode":"L7G 4B5",
    "sg:province":"ON",
    "sg:tags":[
        "oil"
    ],
    "wof:name":"Cango Gas Bar",
    "wof:placetype":"venue"
},
  "geometry": {"coordinates":[-79.881783,43.648968],"type":"Point"}
}