{
  "type": "Feature",
  "properties": {
    "addr:full":"London ON N6K 1E1",
    "addr:postcode":"n6k 1e1",
    "iso:country":"CA",
    "sg:city":"London",
    "sg:classifiers":[
        {
            "category":"Insurance",
            "subcategory":"Insurance Agent",
            "type":"Services"
        }
    ],
    "sg:phone":"+1 519 473 7000",
    "sg:postcode":"N6K 1E1",
    "sg:province":"ON",
    "wof:name":"Madan Insurance Brokers",
    "wof:placetype":"venue"
},
  "geometry": {"coordinates":[-81.333893,42.959919],"type":"Point"}
}