{
  "type": "Feature",
  "properties": {
    "addr:full":"182 Golf Course Rd Huntsville ON P1H 1N7",
    "addr:housenumber":"182",
    "addr:postcode":"p1h 1n7",
    "addr:street":"Golf Course Rd",
    "iso:country":"CA",
    "sg:address":"182 Golf Course Rd",
    "sg:city":"Huntsville",
    "sg:classifiers":[
        {
            "category":"Recreation",
            "type":"Entertainment"
        }
    ],
    "sg:phone":"+1 705 789 1000",
    "sg:postcode":"P1H 1N7",
    "sg:province":"ON",
    "sg:tags":[
        "course",
        "golf"
    ],
    "wof:name":"Huntsville Downs Golf",
    "wof:placetype":"venue"
},
  "geometry": {"coordinates":[-79.215279,45.360165],"type":"Point"}
}