{
  "type": "Feature",
  "properties": {
    "addr:full":"109 Lone Rock Rd Lone Rock SK S0M 1K0",
    "addr:housenumber":"109",
    "addr:postcode":"s0m 1k0",
    "addr:street":"Lone Rock Rd",
    "iso:country":"CA",
    "sg:address":"109 Lone Rock Rd",
    "sg:city":"Lone Rock",
    "sg:classifiers":[
        {
            "category":"Home & Garden",
            "subcategory":"Building Materials",
            "type":"Retail Goods"
        }
    ],
    "sg:phone":"+1 306 387 6835",
    "sg:postcode":"S0M 1K0",
    "sg:province":"SK",
    "sg:tags":[
        "glass",
        "leaded"
    ],
    "wof:name":"Debbie Anderson Stained Glass",
    "wof:placetype":"venue"
},
  "geometry": {"coordinates":[-109.881561279,53.0501899719],"type":"Point"}
}