{
  "type": "Feature",
  "properties": {
    "iso:country":"CA",
    "sg:address":"130 3rd St",
    "sg:city":"Dalmeny",
    "sg:classifiers":[
        {
            "category":"Shopping",
            "subcategory":"Pharmacy",
            "type":"Retail Goods"
        }
    ],
    "sg:phone":"+1 306 254 2144",
    "sg:postcode":"S0K 1E0",
    "sg:province":"SK",
    "wof:name":"Dalmeny Buy N'Save Drug Mart",
    "wof:placetype":"venue"
},
  "geometry": {"coordinates":[-106.77663421600001,52.3392868042],"type":"Point"}
}