{
  "type": "Feature",
  "properties": {
    "addr:full":"225 2nd Ave E Vancouver BC V5T 1B6",
    "addr:housenumber":"225",
    "addr:postcode":"v5t 1b6",
    "addr:street":"2Nd Ave E",
    "iso:country":"CA",
    "sg:address":"225 2nd Ave E",
    "sg:city":"Vancouver",
    "sg:classifiers":[
        {
            "category":"Retail",
            "subcategory":"Auto Repair",
            "type":"Services"
        }
    ],
    "sg:phone":"+1 604 877 1588",
    "sg:postcode":"V5T 1B6",
    "sg:province":"BC",
    "sg:tags":[
        "body",
        "automobile",
        "painting"
    ],
    "wof:name":"Rudy & Peter Body Shop Ltd",
    "wof:placetype":"venue"
},
  "geometry": {"coordinates":[-123.100074768,49.268989563],"type":"Point"}
}