{
  "type": "Feature",
  "properties": {
    "iso:country":"CA",
    "sg:address":"7598 Yonge St",
    "sg:city":"Thornhill",
    "sg:classifiers":[
        {
            "category":"Retail",
            "subcategory":"Laundry & Dry Cleaning",
            "type":"Services"
        }
    ],
    "sg:phone":"+1 905 881 0554",
    "sg:postcode":"L4J 1V9",
    "sg:province":"ON",
    "sg:tags":[
        "cleaners"
    ],
    "wof:name":"Thornhill Carpet Cleaning",
    "wof:placetype":"venue"
},
  "geometry": {"coordinates":[-79.423859,43.812691],"type":"Point"}
}