{
  "type": "Feature",
  "properties": {
    "addr:full":"SW 19 26 26W Roblin MB R0L 1P0",
    "addr:housenumber":"26 26w roblin",
    "addr:postcode":"r0l 1p0",
    "addr:street":"Sw 19",
    "iso:country":"CA",
    "sg:address":"SW 19 26 26W",
    "sg:city":"Roblin",
    "sg:classifiers":[
        {
            "category":"Government",
            "subcategory":"Office",
            "type":"Public Place"
        }
    ],
    "sg:phone":"+1 204 937 4704",
    "sg:postcode":"R0L 1P0",
    "sg:province":"MB",
    "wof:name":"Canada Community Pastures",
    "wof:placetype":"venue"
},
  "geometry": {"coordinates":[-101.352851868,51.2281532288],"type":"Point"}
}