{
  "type": "Feature",
  "properties": {
    "addr:full":"3636 Dartmouth Rd SE Calgary AB T2G 4A6",
    "addr:housenumber":"3636",
    "addr:postcode":"t2g 4a6",
    "addr:street":"Dartmouth Rd Se",
    "iso:country":"CA",
    "sg:address":"3636 Dartmouth Rd SE",
    "sg:city":"Calgary",
    "sg:classifiers":[
        {
            "category":"Retail",
            "subcategory":"Auto Repair",
            "type":"Services"
        }
    ],
    "sg:phone":"+1 403 245 1955",
    "sg:postcode":"T2G 4A6",
    "sg:province":"AB",
    "sg:tags":[
        "automobile",
        "top",
        "upholstery"
    ],
    "wof:name":"DE Greeve Auto Upholstery Inc",
    "wof:placetype":"venue"
},
  "geometry": {"coordinates":[-114.05130800000001,51.022408],"type":"Point"}
}