{
  "type": "Feature",
  "properties": {
    "iso:country":"CA",
    "sg:address":"325 Wallinger Ave",
    "sg:city":"Kimberley",
    "sg:classifiers":[
        {
            "category":"Restaurant",
            "type":"Food & Drink"
        }
    ],
    "sg:phone":"+1 250 427 5227",
    "sg:postcode":"V1A 1Z3",
    "sg:province":"BC",
    "sg:tags":[
        "pizza"
    ],
    "wof:name":"Grubstake Pizza",
    "wof:placetype":"venue"
},
  "geometry": {"coordinates":[-115.982887268,49.6850662231],"type":"Point"}
}