{
  "type": "Feature",
  "properties": {
    "addr:full":"513 Rue Simard Saint-Ambroise QC G7P 2S6",
    "addr:housenumber":"513",
    "addr:postcode":"g7p 2s6",
    "addr:street":"Rue Simard",
    "iso:country":"CA",
    "sg:address":"513 Rue Simard",
    "sg:city":"Saint-Ambroise",
    "sg:classifiers":[
        {
            "category":"Insurance",
            "subcategory":"Insurance Agent",
            "type":"Services"
        }
    ],
    "sg:phone":"+1 418 672 2211",
    "sg:postcode":"G7P 2S6",
    "sg:province":"QC",
    "wof:name":"Assurances Groupe Cantin Inc",
    "wof:placetype":"venue"
},
  "geometry": {"coordinates":[-71.323853,48.557384],"type":"Point"}
}