{
  "type": "Feature",
  "properties": {
    "addr:full":"1825 Boul Rene-Levesque O Montreal QC H3H 1R4",
    "addr:housenumber":"1825",
    "addr:postcode":"h3h 1r4",
    "addr:street":"Boul Rene-Levesque O",
    "iso:country":"CA",
    "sg:address":"1825 Boul Rene-Levesque O",
    "sg:city":"Montreal",
    "sg:classifiers":[
        {
            "category":"Real Estate",
            "subcategory":"Architect",
            "type":"Services"
        }
    ],
    "sg:phone":"+1 514 937 6168",
    "sg:postcode":"H3H 1R4",
    "sg:province":"QC",
    "wof:name":"Order Des Architectes Quebec",
    "wof:placetype":"venue"
},
  "geometry": {"coordinates":[-73.5492782593,45.5223197937],"type":"Point"}
}