{
  "type": "Feature",
  "properties": {
    "addr:full":"60 Humber Blvd York ON M6N 2H3",
    "addr:housenumber":"60",
    "addr:postcode":"m6n 2h3",
    "addr:street":"Humber Blvd",
    "iso:country":"CA",
    "sg:address":"60 Humber Blvd",
    "sg:city":"York",
    "sg:classifiers":[
        {
            "category":"Professional",
            "subcategory":"Computer Services",
            "type":"Services"
        }
    ],
    "sg:phone":"+1 416 638 8444",
    "sg:postcode":"M6N 2H3",
    "sg:province":"ON",
    "sg:tags":[
        "consultant"
    ],
    "wof:name":"Olhm Info Sys Consultants",
    "wof:placetype":"venue"
},
  "geometry": {"coordinates":[-79.48184999999999,43.681297],"type":"Point"}
}