{
  "type": "Feature",
  "properties": {
    "iso:country":"CA",
    "sg:address":"2650 Boul Lafleche",
    "sg:city":"Baie-Comeau",
    "sg:classifiers":[
        {
            "category":"Personal",
            "subcategory":"Beauty Salon",
            "type":"Services"
        }
    ],
    "sg:phone":"+1 418 589 4434",
    "sg:postcode":"G5C 1E4",
    "sg:province":"QC",
    "wof:name":"Salon DE Coiffure Andreanne",
    "wof:placetype":"venue"
},
  "geometry": {"coordinates":[-68.2966079712,49.1931037903],"type":"Point"}
}