{
  "type": "Feature",
  "properties": {
    "addr:full":"9018 Royal St Langley BC V1M 2R5",
    "addr:housenumber":"9018",
    "addr:postcode":"v1m 2r5",
    "addr:street":"Royal St",
    "iso:country":"CA",
    "sg:address":"9018 Royal St",
    "sg:city":"Langley",
    "sg:classifiers":[
        {
            "category":"Retail",
            "subcategory":"Repair Shop",
            "type":"Services"
        }
    ],
    "sg:phone":"+1 604 888 9577",
    "sg:postcode":"V1M 2R5",
    "sg:province":"BC",
    "sg:tags":[
        "lock",
        "locksmith"
    ],
    "wof:name":"Fort Locksmith",
    "wof:placetype":"venue"
},
  "geometry": {"coordinates":[-122.57474499999999,49.166653],"type":"Point"}
}