{
  "type": "Feature",
  "properties": {
    "addr:full":"797 Adelaide St N London ON N5Y 2L8",
    "addr:housenumber":"797",
    "addr:postcode":"n5y 2l8",
    "addr:street":"Adelaide St N",
    "iso:country":"CA",
    "sg:address":"797 Adelaide St N",
    "sg:city":"London",
    "sg:classifiers":[
        {
            "category":"Personal",
            "type":"Services"
        }
    ],
    "sg:phone":"+1 519 673 3007",
    "sg:postcode":"N5Y 2L8",
    "sg:province":"ON",
    "sg:tags":[
        "therapist",
        "massage"
    ],
    "wof:name":"London Massage Therapy Ctr",
    "wof:placetype":"venue"
},
  "geometry": {"coordinates":[-81.2379989624,43.0014457703],"type":"Point"}
}