{
  "type": "Feature",
  "properties": {
    "addr:full":"139 Rue Saint-Paul O Montreal QC H2Y 1Z5",
    "addr:housenumber":"139",
    "addr:postcode":"h2y 1z5",
    "addr:street":"Rue Saint-Paul O",
    "iso:country":"CA",
    "sg:address":"139 Rue Saint-Paul O",
    "sg:city":"Montreal",
    "sg:classifiers":[
        {
            "category":"Restaurant",
            "type":"Food & Drink"
        }
    ],
    "sg:phone":"+1 514 843 7432",
    "sg:postcode":"H2Y 1Z5",
    "sg:province":"QC",
    "wof:name":"Petit-Moulinsart",
    "wof:placetype":"venue"
},
  "geometry": {"coordinates":[-73.55289459230001,45.5070495605],"type":"Point"}
}