{
  "type": "Feature",
  "properties": {
    "addr:full":"480 Boul Strathmore Dorval QC H9S 2J4",
    "addr:housenumber":"480",
    "addr:postcode":"h9s 2j4",
    "addr:street":"Boul Strathmore",
    "iso:country":"CA",
    "sg:address":"480 Boul Strathmore",
    "sg:city":"Dorval",
    "sg:classifiers":[
        {
            "category":"Restaurant",
            "type":"Food & Drink"
        }
    ],
    "sg:phone":"+1 514 633 8770",
    "sg:postcode":"H9S 2J4",
    "sg:province":"QC",
    "sg:tags":[
        "cafe"
    ],
    "wof:name":"Cafe Bord Du Lac",
    "wof:placetype":"venue"
},
  "geometry": {"coordinates":[-73.777145,45.448654],"type":"Point"}
}