{
  "type": "Feature",
  "properties": {
    "addr:full":"310 3rd Ave Chaplin SK S0H 0V0",
    "addr:housenumber":"310",
    "addr:postcode":"s0h 0v0",
    "addr:street":"3Rd Ave",
    "iso:country":"CA",
    "sg:address":"310 3rd Ave",
    "sg:city":"Chaplin",
    "sg:classifiers":[
        {
            "category":"Retail",
            "subcategory":"Auto Repair",
            "type":"Services"
        }
    ],
    "sg:phone":"+1 306 395 2205",
    "sg:postcode":"S0H 0V0",
    "sg:province":"SK",
    "sg:tags":[
        "repairing",
        "automobile"
    ],
    "wof:name":"Loeppky Repair",
    "wof:placetype":"venue"
},
  "geometry": {"coordinates":[-106.656593323,50.4620513916],"type":"Point"}
}