{
  "type": "Feature",
  "properties": {
    "addr:full":"2120 Rue DE L'Aeroport Saint-Mathieu-DE-Beloeil QC J3G 4S5",
    "addr:housenumber":"2120",
    "addr:postcode":"j3g 4s5",
    "addr:street":"Rue De L'Aeroport",
    "iso:country":"CA",
    "sg:address":"2120 Rue DE L'Aeroport",
    "sg:city":"Saint-Mathieu-DE-Beloeil",
    "sg:classifiers":[
        {
            "category":"Retail",
            "subcategory":"Auto Repair",
            "type":"Services"
        }
    ],
    "sg:phone":"+1 450 467 0614",
    "sg:postcode":"J3G 4S5",
    "sg:province":"QC",
    "sg:tags":[
        "body",
        "automobile",
        "painting"
    ],
    "wof:name":"Carrosserie P Tremblay Inc",
    "wof:placetype":"venue"
},
  "geometry": {"coordinates":[-73.23925,45.589924],"type":"Point"}
}