{
  "type": "Feature",
  "properties": {
    "iso:country":"CA",
    "sg:city":"Roblin",
    "sg:classifiers":[
        {
            "category":"Manufacturing",
            "subcategory":"Metals",
            "type":"Manufacturing & Wholesale Goods"
        }
    ],
    "sg:phone":"+1 204 937 4403",
    "sg:postcode":"R0L 1P0",
    "sg:province":"MB",
    "sg:tags":[
        "steel"
    ],
    "wof:name":"Kenco Industries",
    "wof:placetype":"venue"
},
  "geometry": {"coordinates":[-101.352851868,51.2281532288],"type":"Point"}
}