{
  "type": "Feature",
  "properties": {
    "addr:full":"10150 Pine Valley Dr Nobleton ON L0G 1N0",
    "addr:housenumber":"10150",
    "addr:postcode":"l0g 1n0",
    "addr:street":"Pine Valley Dr",
    "iso:country":"CA",
    "sg:address":"10150 Pine Valley Dr",
    "sg:city":"Nobleton",
    "sg:classifiers":[
        {
            "category":"Organizations",
            "subcategory":"Religious Organization",
            "type":"Services"
        }
    ],
    "sg:phone":"+1 905 832 8918",
    "sg:postcode":"L0G 1N0",
    "sg:province":"ON",
    "sg:tags":[
        "church"
    ],
    "wof:name":"St Paul's Presbyterian Church",
    "wof:placetype":"venue"
},
  "geometry": {"coordinates":[-79.652878,43.902885],"type":"Point"}
}