{
  "type": "Feature",
  "properties": {
    "addr:full":"2100 Av Laurier E Montreal QC H2H 1B9",
    "addr:housenumber":"2100",
    "addr:postcode":"h2h 1b9",
    "addr:street":"Av Laurier E",
    "iso:country":"CA",
    "sg:address":"2100 Av Laurier E",
    "sg:city":"Montreal",
    "sg:classifiers":[
        {
            "category":"Restaurant",
            "type":"Food & Drink"
        }
    ],
    "sg:phone":"+1 514 524 2325",
    "sg:postcode":"H2H 1B9",
    "sg:province":"QC",
    "wof:name":"Laurier Deli",
    "wof:placetype":"venue"
},
  "geometry": {"coordinates":[-73.578278,45.538006],"type":"Point"}
}