{
  "type": "Feature",
  "properties": {
    "addr:full":"39 King St Saint John NB E2L 4W3",
    "addr:housenumber":"39",
    "addr:postcode":"nb e2l 4w3",
    "addr:street":"King St",
    "iso:country":"CA",
    "sg:address":"39 King St",
    "sg:city":"Saint John",
    "sg:classifiers":[
        {
            "category":"Shopping",
            "subcategory":"Books",
            "type":"Retail Goods"
        }
    ],
    "sg:phone":"+1 506 658 9114",
    "sg:postcode":"E2L 4W3",
    "sg:province":"NB",
    "sg:tags":[
        "dealer"
    ],
    "wof:name":"Coles",
    "wof:placetype":"venue"
},
  "geometry": {"coordinates":[-66.060875,45.273251],"type":"Point"}
}