{
  "type": "Feature",
  "properties": {
    "addr:full":"1532 Marine Dr West Vancouver BC V7V 1H8",
    "addr:housenumber":"1532",
    "addr:postcode":"v7v 1h8",
    "addr:street":"Marine Dr",
    "iso:country":"CA",
    "sg:address":"1532 Marine Dr",
    "sg:city":"West Vancouver",
    "sg:classifiers":[
        {
            "category":"Restaurant",
            "type":"Food & Drink"
        }
    ],
    "sg:phone":"+1 604 922 2605",
    "sg:postcode":"V7V 1H8",
    "sg:province":"BC",
    "wof:name":"Yomi's Sushi & Noodle",
    "wof:placetype":"venue"
},
  "geometry": {"coordinates":[-123.157585,49.328289],"type":"Point"}
}