{
  "type": "Feature",
  "properties": {
    "addr:full":"36 Regent St Lakefield ON K0L 2H0",
    "addr:housenumber":"36",
    "addr:postcode":"k0l 2h0",
    "addr:street":"Regent St",
    "iso:country":"CA",
    "sg:address":"36 Regent St",
    "sg:city":"Lakefield",
    "sg:classifiers":[
        {
            "category":"Organizations",
            "subcategory":"Religious Organization",
            "type":"Services"
        }
    ],
    "sg:phone":"+1 705 652 8056",
    "sg:postcode":"K0L 2H0",
    "sg:province":"ON",
    "sg:tags":[
        "church"
    ],
    "wof:name":"Lakefield Baptist Church",
    "wof:placetype":"venue"
},
  "geometry": {"coordinates":[-78.270554,44.424061],"type":"Point"}
}