{
  "type": "Feature",
  "properties": {
    "addr:full":"475 Conception Bay Hwy Brigus NL A0A 1K0",
    "addr:housenumber":"475",
    "addr:postcode":"a0a 1k0",
    "addr:street":"Conception Bay Hwy",
    "iso:country":"CA",
    "sg:address":"475 Conception Bay Hwy",
    "sg:city":"Brigus",
    "sg:classifiers":[
        {
            "category":"Restaurant",
            "type":"Food & Drink"
        }
    ],
    "sg:phone":"+1 709 528 4281",
    "sg:postcode":"A0A 1K0",
    "sg:province":"NL",
    "wof:name":"E & E Drive in",
    "wof:placetype":"venue"
},
  "geometry": {"coordinates":[-53.242409,47.528835],"type":"Point"}
}