{
  "type": "Feature",
  "properties": {
    "iso:country":"CA",
    "sg:address":"246 Rue Saint-Gabriel",
    "sg:city":"Saint-Gabriel-DE-Brandon",
    "sg:classifiers":[
        {
            "category":"Professional",
            "subcategory":"Accounting & Tax Preparation",
            "type":"Services"
        }
    ],
    "sg:phone":"+1 450 835 4723",
    "sg:postcode":"J0K 2N0",
    "sg:province":"QC",
    "sg:tags":[
        "accountant"
    ],
    "wof:name":"Laporte, Pierre CA",
    "wof:placetype":"venue"
},
  "geometry": {"coordinates":[-73.3773727417,46.2901191711],"type":"Point"}
}