{
  "type": "Feature",
  "properties": {
    "addr:full":"404 34 St SW Edmonton AB T6X 1A5",
    "addr:housenumber":"34",
    "addr:postcode":"t6x 1a5",
    "addr:street":"404;St Sw",
    "iso:country":"CA",
    "sg:address":"404 34 St SW",
    "sg:city":"Edmonton",
    "sg:classifiers":[
        {
            "category":"Sports & Exercise",
            "subcategory":"Golf",
            "type":"Entertainment"
        }
    ],
    "sg:phone":"+1 780 988 8375",
    "sg:postcode":"T6X 1A5",
    "sg:province":"AB",
    "sg:tags":[
        "course"
    ],
    "wof:name":"Pioneer Meadows Golf Course",
    "wof:placetype":"venue"
},
  "geometry": {"coordinates":[-113.393784,53.429665],"type":"Point"}
}