{
  "type": "Feature",
  "properties": {
    "addr:full":"785 Trafalgar St London ON N5Z 1E6",
    "addr:housenumber":"785",
    "addr:postcode":"n5z 1e6",
    "addr:street":"Trafalgar St",
    "iso:country":"CA",
    "sg:address":"785 Trafalgar St",
    "sg:city":"London",
    "sg:classifiers":[
        {
            "category":"Education",
            "subcategory":"School",
            "type":"Public Place"
        }
    ],
    "sg:phone":"+1 519 452 2880",
    "sg:postcode":"N5Z 1E6",
    "sg:province":"ON",
    "wof:name":"Thames Secondary School",
    "wof:placetype":"venue"
},
  "geometry": {"coordinates":[-81.21942901609999,42.9782180786],"type":"Point"}
}