{
  "type": "Feature",
  "properties": {
    "addr:full":"1696 Hwy 3 Ruthven ON N0P 2G0",
    "addr:housenumber":"1696",
    "addr:postcode":"n0p 2g0",
    "addr:street":"Hwy 3 Ruthven",
    "iso:country":"CA",
    "sg:address":"1696 Hwy 3",
    "sg:city":"Ruthven",
    "sg:classifiers":[
        {
            "category":"Freight",
            "type":"Transportation"
        }
    ],
    "sg:phone":"+1 519 322 2394",
    "sg:postcode":"N0P 2G0",
    "sg:province":"ON",
    "sg:tags":[
        "vegetable",
        "fruit",
        "storage"
    ],
    "wof:name":"K & L Sales Inc",
    "wof:placetype":"venue"
},
  "geometry": {"coordinates":[-82.67202,42.051914],"type":"Point"}
}