{
  "type": "Feature",
  "properties": {
    "iso:country":"CA",
    "sg:address":"10520 Yonge St # 211",
    "sg:city":"Richmond Hill",
    "sg:classifiers":[
        {
            "category":"Shopping",
            "subcategory":"Clothing, Apparel, & Fashions",
            "type":"Retail Goods"
        }
    ],
    "sg:phone":"+1 905 770 8754",
    "sg:postcode":"L4C 3C7",
    "sg:province":"ON",
    "wof:name":"Winners Apparel Ltd",
    "wof:placetype":"venue"
},
  "geometry": {"coordinates":[-79.440369,43.883972],"type":"Point"}
}