{
  "type": "Feature",
  "properties": {
    "addr:full":"651 10E Av Senneterre QC J0Y 2M0",
    "addr:housenumber":"651",
    "addr:postcode":"j0y 2m0",
    "addr:street":"10E Av",
    "iso:country":"CA",
    "sg:address":"651 10E Av",
    "sg:city":"Senneterre",
    "sg:classifiers":[
        {
            "category":"Home & Garden",
            "subcategory":"Hardware",
            "type":"Retail Goods"
        }
    ],
    "sg:phone":"+1 819 737 8336",
    "sg:postcode":"J0Y 2M0",
    "sg:province":"QC",
    "wof:name":"Centre D'Outillage Aml Inc",
    "wof:placetype":"venue"
},
  "geometry": {"coordinates":[-77.243645,48.390335],"type":"Point"}
}