{
  "type": "Feature",
  "properties": {
    "iso:country":"CA",
    "sg:address":"730 Industrial Ave",
    "sg:city":"Ottawa",
    "sg:classifiers":[
        {
            "category":"Retail",
            "subcategory":"Auto Repair",
            "type":"Services"
        }
    ],
    "sg:phone":"+1 613 737 9717",
    "sg:postcode":"K1G 0Y9",
    "sg:province":"ON",
    "sg:tags":[
        "repairing",
        "automobile"
    ],
    "wof:name":"Eagle Automotive",
    "wof:placetype":"venue"
},
  "geometry": {"coordinates":[-75.637077,45.409573],"type":"Point"}
}