{
  "type": "Feature",
  "properties": {
    "addr:full":"102 Scollard St Toronto ON M5R 1G2",
    "addr:housenumber":"102",
    "addr:postcode":"m5r 1g2",
    "addr:street":"Scollard St",
    "iso:country":"CA",
    "sg:address":"102 Scollard St",
    "sg:city":"Toronto",
    "sg:classifiers":[
        {
            "category":"Personal",
            "subcategory":"Beauty Salon",
            "type":"Services"
        }
    ],
    "sg:phone":"+1 416 934 1817",
    "sg:postcode":"M5R 1G2",
    "sg:province":"ON",
    "wof:name":"Shagg Salon",
    "wof:placetype":"venue"
},
  "geometry": {"coordinates":[-79.39241800000001,43.671864],"type":"Point"}
}