{
  "type": "Feature",
  "properties": {
    "addr:full":"Scarborough ON M1J 3M5",
    "addr:postcode":"m1j 3m5",
    "iso:country":"CA",
    "sg:city":"Scarborough",
    "sg:classifiers":[
        {
            "category":"Retail",
            "subcategory":"Laundry & Dry Cleaning",
            "type":"Services"
        }
    ],
    "sg:phone":"+1 416 261 5422",
    "sg:postcode":"M1J 3M5",
    "sg:province":"ON",
    "sg:tags":[
        "cleaners"
    ],
    "wof:name":"Cadet Cleaners",
    "wof:placetype":"venue"
},
  "geometry": {"coordinates":[-79.215149,43.743923],"type":"Point"}
}