{
  "type": "Feature",
  "properties": {
    "addr:full":"8564 Fraser St Vancouver BC V5X 3Y3",
    "addr:housenumber":"8564",
    "addr:postcode":"v5x 3y3",
    "addr:street":"Fraser St",
    "iso:country":"CA",
    "sg:address":"8564 Fraser St",
    "sg:city":"Vancouver",
    "sg:classifiers":[
        {
            "category":"Wholesale",
            "subcategory":"Durable Goods & Equipment",
            "type":"Manufacturing & Wholesale Goods"
        }
    ],
    "sg:phone":"+1 604 324 7273",
    "sg:postcode":"V5X 3Y3",
    "sg:province":"BC",
    "sg:tags":[
        "importer"
    ],
    "wof:name":"Peekay Enterprises Ltd",
    "wof:placetype":"venue"
},
  "geometry": {"coordinates":[-123.090935,49.207317],"type":"Point"}
}