{
  "type": "Feature",
  "properties": {
    "addr:full":"1580 Laperriere Ave Ottawa ON K1Z 7T2",
    "addr:housenumber":"1580",
    "addr:postcode":"k1z 7t2",
    "addr:street":"Laperriere Ave",
    "iso:country":"CA",
    "sg:address":"1580 Laperriere Ave",
    "sg:city":"Ottawa",
    "sg:classifiers":[
        {
            "category":"Manufacturing",
            "subcategory":"Tools & Machinery",
            "type":"Manufacturing & Wholesale Goods"
        }
    ],
    "sg:phone":"+1 613 728 3778",
    "sg:postcode":"K1Z 7T2",
    "sg:province":"ON",
    "sg:tags":[
        "spraying",
        "equipment"
    ],
    "wof:name":"Devilbiss Ransburg Spray Equip",
    "wof:placetype":"venue"
},
  "geometry": {"coordinates":[-75.7453536987,45.3764686584],"type":"Point"}
}