{
  "type": "Feature",
  "properties": {
    "addr:full":"28 Rue Main O Coaticook QC J1A 1P2",
    "addr:housenumber":"28",
    "addr:postcode":"j1a 1p2",
    "addr:street":"Rue Main O",
    "iso:country":"CA",
    "sg:address":"28 Rue Main O",
    "sg:city":"Coaticook",
    "sg:classifiers":[
        {
            "category":"Real Estate",
            "subcategory":"Surveying",
            "type":"Services"
        }
    ],
    "sg:phone":"+1 819 849 4100",
    "sg:postcode":"J1A 1P2",
    "sg:province":"QC",
    "sg:tags":[
        "surveyor"
    ],
    "wof:name":"Parent, Daniel",
    "wof:placetype":"venue"
},
  "geometry": {"coordinates":[-71.80485534669999,45.1324386597],"type":"Point"}
}