{
  "type": "Feature",
  "properties": {
    "addr:full":"635 Southdale Rd E London ON N6E 3W6",
    "addr:housenumber":"635",
    "addr:postcode":"n6e 3w6",
    "addr:street":"Southdale Rd E",
    "iso:country":"CA",
    "sg:address":"635 Southdale Rd E",
    "sg:city":"London",
    "sg:classifiers":[
        {
            "category":"Retail",
            "subcategory":"Laundry & Dry Cleaning",
            "type":"Services"
        }
    ],
    "sg:phone":"+1 519 668 0931",
    "sg:postcode":"N6E 3W6",
    "sg:province":"ON",
    "sg:tags":[
        "cleaners"
    ],
    "wof:name":"Dry Cleaner",
    "wof:placetype":"venue"
},
  "geometry": {"coordinates":[-81.23053741459999,42.9429244995],"type":"Point"}
}