{
  "type": "Feature",
  "properties": {
    "addr:full":"9896 Cherry Ave W Taylor BC V0C 2K0",
    "addr:housenumber":"9896",
    "addr:postcode":"bc v0c 2k0",
    "addr:street":"Cherry Ave W",
    "iso:country":"CA",
    "sg:address":"9896 Cherry Ave W",
    "sg:city":"Taylor",
    "sg:classifiers":[
        {
            "category":"Government",
            "subcategory":"Office",
            "type":"Public Place"
        }
    ],
    "sg:phone":"+1 250 789 3333",
    "sg:postcode":"V0C 2K0",
    "sg:province":"BC",
    "sg:tags":[
        "village"
    ],
    "wof:name":"Taylor Community Hall",
    "wof:placetype":"venue"
},
  "geometry": {"coordinates":[-120.689438,56.159721],"type":"Point"}
}