{
  "type": "Feature",
  "properties": {
    "addr:full":"205 5 Ave SW #3500 Calgary AB T2P 2V7",
    "addr:housenumber":"205",
    "addr:postcode":"t2p 2v7",
    "addr:street":"5 Ave Sw # 3500",
    "iso:country":"CA",
    "sg:address":"205 5 Ave SW #3500",
    "sg:city":"Calgary",
    "sg:classifiers":[
        {
            "category":"Building & Trades",
            "subcategory":"Electrical",
            "type":"Services"
        }
    ],
    "sg:phone":"+1 403 205 3880",
    "sg:postcode":"T2P 2V7",
    "sg:province":"AB",
    "sg:tags":[
        "electric",
        "contractor"
    ],
    "wof:name":"Pyramid Corp",
    "wof:placetype":"venue"
},
  "geometry": {"coordinates":[-114.065575,51.048267],"type":"Point"}
}