{
  "type": "Feature",
  "properties": {
    "addr:full":"280 Hurontario St Collingwood ON L9Y 2M3",
    "addr:housenumber":"280",
    "addr:postcode":"l9y 2m3",
    "addr:street":"Hurontario St",
    "iso:country":"CA",
    "sg:address":"280 Hurontario St",
    "sg:city":"Collingwood",
    "sg:classifiers":[
        {
            "category":"Banks & Credit Unions",
            "subcategory":"Bank",
            "type":"Services"
        }
    ],
    "sg:phone":"+1 705 446 3000",
    "sg:postcode":"L9Y 2M3",
    "sg:province":"ON",
    "wof:name":"Royal Bank Financial Group",
    "wof:placetype":"venue"
},
  "geometry": {"coordinates":[-80.216286,44.496002],"type":"Point"}
}