{
  "type": "Feature",
  "properties": {
    "addr:full":"Winnipeg MB R2R 1S5",
    "addr:postcode":"r2r 1s5",
    "iso:country":"CA",
    "sg:city":"Winnipeg",
    "sg:classifiers":[
        {
            "category":"Food & Beverages",
            "subcategory":"Specialty",
            "type":"Retail Goods"
        }
    ],
    "sg:phone":"+1 204 632 7123",
    "sg:postcode":"R2R 1S5",
    "sg:province":"MB",
    "sg:tags":[
        "water",
        "bulk",
        "company"
    ],
    "wof:name":"Donmids Distilled Water",
    "wof:placetype":"venue"
},
  "geometry": {"coordinates":[-97.195908,49.93512],"type":"Point"}
}