{
  "type": "Feature",
  "properties": {
    "addr:full":"25 Main St Big Valley AB T0J 0G0",
    "addr:housenumber":"25",
    "addr:postcode":"t0j 0g0",
    "addr:street":"Main St",
    "iso:country":"CA",
    "sg:address":"25 Main St",
    "sg:city":"Big Valley",
    "sg:classifiers":[
        {
            "category":"Food & Beverages",
            "subcategory":"Groceries & Convenience Stores",
            "type":"Retail Goods"
        }
    ],
    "sg:phone":"+1 403 876 2275",
    "sg:postcode":"T0J 0G0",
    "sg:province":"AB",
    "sg:tags":[
        "grocer"
    ],
    "wof:name":"Frontier General Store",
    "wof:placetype":"venue"
},
  "geometry": {"coordinates":[-112.751305,52.034908],"type":"Point"}
}