{
  "type": "Feature",
  "properties": {
    "iso:country":"CA",
    "sg:address":"15659 109 Ave",
    "sg:city":"Surrey",
    "sg:classifiers":[
        {
            "category":"Building & Trades",
            "subcategory":"Landscaping Services",
            "type":"Services"
        }
    ],
    "sg:phone":"+1 604 951 3500",
    "sg:postcode":"V4N 4T5",
    "sg:province":"BC",
    "sg:tags":[
        "lawn",
        "tree",
        "maintenance",
        "grounds"
    ],
    "wof:name":"Western Weed & Tree Care",
    "wof:placetype":"venue"
},
  "geometry": {"coordinates":[-122.787971497,49.2007675171],"type":"Point"}
}