{
  "type": "Feature",
  "properties": {
    "addr:full":"Hwy 49 W Preeceville SK S0A 3B0",
    "addr:postcode":"s0a 3b0",
    "addr:street":"Hwy 49 W Preeceville",
    "iso:country":"CA",
    "sg:address":"Hwy 49 W",
    "sg:city":"Preeceville",
    "sg:classifiers":[
        {
            "category":"Freight",
            "type":"Transportation"
        }
    ],
    "sg:phone":"+1 306 547 4430",
    "sg:postcode":"S0A 3B0",
    "sg:province":"SK",
    "sg:tags":[
        "trucking"
    ],
    "wof:name":"M & M Alberts Trucking Ltd",
    "wof:placetype":"venue"
},
  "geometry": {"coordinates":[-102.666877747,51.9542350769],"type":"Point"}
}