{
  "type": "Feature",
  "properties": {
    "addr:full":"8050 Rue Hochelaga Montreal QC H1L 2L1",
    "addr:housenumber":"8050",
    "addr:postcode":"h1l 2l1",
    "addr:street":"Rue Hochelaga",
    "iso:country":"CA",
    "sg:address":"8050 Rue Hochelaga",
    "sg:city":"Montreal",
    "sg:classifiers":[
        {
            "category":"Home & Garden",
            "subcategory":"Home Furnishings",
            "type":"Retail Goods"
        }
    ],
    "sg:phone":"+1 514 355 3454",
    "sg:postcode":"H1L 2L1",
    "sg:province":"QC",
    "sg:tags":[
        "curtain",
        "made",
        "drapery"
    ],
    "wof:name":"Draperies DE L'Est M Lessard",
    "wof:placetype":"venue"
},
  "geometry": {"coordinates":[-73.523293,45.594765],"type":"Point"}
}