{
  "type": "Feature",
  "properties": {
    "addr:full":"Lindsay ON K9V 4R4",
    "addr:postcode":"k9v 4r4",
    "iso:country":"CA",
    "sg:city":"Lindsay",
    "sg:classifiers":[
        {
            "category":"Real Estate",
            "subcategory":"Real Estate Operator",
            "type":"Services"
        }
    ],
    "sg:phone":"+1 705 324 1655",
    "sg:postcode":"K9V 4R4",
    "sg:province":"ON",
    "sg:tags":[
        "mobile",
        "campground",
        "community"
    ],
    "wof:name":"Riverwood Park Campgrounds",
    "wof:placetype":"venue"
},
  "geometry": {"coordinates":[-78.7231216431,44.3233413696],"type":"Point"}
}