{
  "type": "Feature",
  "properties": {
    "iso:country":"CA",
    "sg:address":"75 Martha St",
    "sg:city":"Winnipeg",
    "sg:classifiers":[
        {
            "category":"Organizations",
            "subcategory":"Non-profit Organization",
            "type":"Services"
        }
    ],
    "sg:phone":"+1 204 982 8240",
    "sg:postcode":"R3B 1A4",
    "sg:province":"MB",
    "sg:tags":[
        "information",
        "welfare",
        "treatment",
        "alcoholism",
        "social"
    ],
    "wof:name":"Main Street Project",
    "wof:placetype":"venue"
},
  "geometry": {"coordinates":[-97.133812,49.902599],"type":"Point"}
}