{
  "type": "Feature",
  "properties": {
    "addr:full":"1390 2nd St E Cornwall ON K6H 5T4",
    "addr:housenumber":"1390",
    "addr:postcode":"k6h 5t4",
    "addr:street":"2Nd St E",
    "iso:country":"CA",
    "sg:address":"1390 2nd St E",
    "sg:city":"Cornwall",
    "sg:classifiers":[
        {
            "category":"Home & Garden",
            "subcategory":"Furniture",
            "type":"Retail Goods"
        }
    ],
    "sg:phone":"+1 613 938 2229",
    "sg:postcode":"K6H 5T4",
    "sg:province":"ON",
    "wof:name":"United Furniture Warehouse",
    "wof:placetype":"venue"
},
  "geometry": {"coordinates":[-74.702072,45.02755],"type":"Point"}
}