{
  "type": "Feature",
  "properties": {
    "addr:full":"147 Bertrand Saint-Bruno-Lac-Saint-Jean QC G0W 2L0",
    "addr:housenumber":"147",
    "addr:postcode":"g0w 2l0",
    "addr:street":"Bertrand Saint-Bruno-Lac-Saint-Jean",
    "iso:country":"CA",
    "sg:address":"147 Bertrand",
    "sg:city":"Saint-Bruno-Lac-Saint-Jean",
    "sg:classifiers":[
        {
            "category":"Building & Trades",
            "subcategory":"Construction",
            "type":"Services"
        }
    ],
    "sg:phone":"+1 418 343 2933",
    "sg:postcode":"G0W 2L0",
    "sg:province":"QC",
    "sg:tags":[
        "marking",
        "parking",
        "signal",
        "maintenance",
        "system"
    ],
    "wof:name":"Signalisation Audet Inc",
    "wof:placetype":"venue"
},
  "geometry": {"coordinates":[-70.8897018433,46.9212303162],"type":"Point"}
}