{
  "type": "Feature",
  "properties": {
    "addr:full":"60 DE Baets St Winnipeg MB R2J 3S9",
    "addr:postcode":"r2j 3s9",
    "addr:street":"60;St",
    "iso:country":"CA",
    "sg:address":"60 DE Baets St",
    "sg:city":"Winnipeg",
    "sg:classifiers":[
        {
            "category":"Professional",
            "type":"Services"
        }
    ],
    "sg:phone":"+1 204 940 1410",
    "sg:postcode":"R2J 3S9",
    "sg:province":"MB",
    "sg:tags":[
        "grocer",
        "establishment"
    ],
    "wof:name":"Goodlife Foods",
    "wof:placetype":"venue"
},
  "geometry": {"coordinates":[-97.04606628419999,49.8840026855],"type":"Point"}
}