{
  "type": "Feature",
  "properties": {
    "addr:full":"London ON N6B 1N8",
    "addr:postcode":"n6b 1n8",
    "iso:country":"CA",
    "sg:city":"London",
    "sg:classifiers":[
        {
            "category":"Wholesale",
            "subcategory":"Groceries",
            "type":"Manufacturing & Wholesale Goods"
        }
    ],
    "sg:phone":"+1 519 667 7709",
    "sg:postcode":"N6B 1N8",
    "sg:province":"ON",
    "sg:tags":[
        "grocer"
    ],
    "wof:name":"Parmalat Canada",
    "wof:placetype":"venue"
},
  "geometry": {"coordinates":[-81.25145721440001,42.9790153503],"type":"Point"}
}