{
  "type": "Feature",
  "properties": {
    "addr:full":"1495 Marine Dr West Vancouver BC V7T 1B8",
    "addr:housenumber":"1495",
    "addr:postcode":"v7t 1b8",
    "addr:street":"Marine Dr",
    "iso:country":"CA",
    "sg:address":"1495 Marine Dr",
    "sg:city":"West Vancouver",
    "sg:classifiers":[
        {
            "category":"Restaurant",
            "type":"Food & Drink"
        }
    ],
    "sg:phone":"+1 604 921 1311",
    "sg:postcode":"V7T 1B8",
    "sg:province":"BC",
    "wof:name":"Caspian Restaurant",
    "wof:placetype":"venue"
},
  "geometry": {"coordinates":[-123.1563797,49.3283882141],"type":"Point"}
}