{
  "type": "Feature",
  "properties": {
    "iso:country":"CA",
    "sg:address":"40 Railway Ave",
    "sg:city":"Redvers",
    "sg:classifiers":[
        {
            "category":"Organizations",
            "subcategory":"Professional Association",
            "type":"Services"
        }
    ],
    "sg:phone":"+1 306 452 3231",
    "sg:postcode":"S0C 2H0",
    "sg:province":"SK",
    "sg:tags":[
        "club"
    ],
    "wof:name":"Royal Canadian Legion Redvers",
    "wof:placetype":"venue"
},
  "geometry": {"coordinates":[-101.699142456,49.5762710571],"type":"Point"}
}