{
  "type": "Feature",
  "properties": {
    "addr:full":"214 Kingsway Garden Mall NW Edmonton AB T5G 3A6",
    "addr:housenumber":"214",
    "addr:postcode":"t5g 3a6",
    "addr:street":"Kingsway Garden Mall Nw",
    "iso:country":"CA",
    "sg:address":"214 Kingsway Garden Mall NW",
    "sg:city":"Edmonton",
    "sg:classifiers":[
        {
            "category":"Personal",
            "subcategory":"Beauty Salon",
            "type":"Services"
        }
    ],
    "sg:phone":"+1 780 477 8886",
    "sg:postcode":"T5G 3A6",
    "sg:province":"AB",
    "wof:name":"Altimo Hair Group",
    "wof:placetype":"venue"
},
  "geometry": {"coordinates":[-113.490371704,53.5462188721],"type":"Point"}
}