{
  "type": "Feature",
  "properties": {
    "iso:country":"CA",
    "sg:address":"2359 Calais Rd",
    "sg:city":"Duncan",
    "sg:classifiers":[
        {
            "category":"Organizations",
            "subcategory":"Religious Organization",
            "type":"Services"
        }
    ],
    "sg:phone":"+1 604 748 2232",
    "sg:postcode":"V9L 5V5",
    "sg:province":"BC",
    "sg:tags":[
        "church"
    ],
    "wof:name":"St Clare's Monastery",
    "wof:placetype":"venue"
},
  "geometry": {"coordinates":[-123.70738220200001,48.779094696],"type":"Point"}
}