{
  "type": "Feature",
  "properties": {
    "iso:country":"CA",
    "sg:city":"Montreal",
    "sg:classifiers":[
        {
            "category":"Manufacturing",
            "subcategory":"Tobacco Products",
            "type":"Manufacturing & Wholesale Goods"
        }
    ],
    "sg:phone":"+1 514 875 5571",
    "sg:postcode":"H3B 1A2",
    "sg:province":"QC",
    "sg:tags":[
        "cigarette",
        "cigar"
    ],
    "wof:name":"G Hiltebrandt CO",
    "wof:placetype":"venue"
},
  "geometry": {"coordinates":[-73.5605316162,45.5133514404],"type":"Point"}
}