{
  "type": "Feature",
  "properties": {
    "addr:full":"1225 Newmarket St Ottawa ON K1B 5N6",
    "addr:housenumber":"1225",
    "addr:postcode":"k1b 5n6",
    "addr:street":"Newmarket St",
    "iso:country":"CA",
    "sg:address":"1225 Newmarket St",
    "sg:city":"Ottawa",
    "sg:classifiers":[
        {
            "category":"Building & Trades",
            "subcategory":"Plumbing",
            "type":"Services"
        }
    ],
    "sg:phone":"+1 613 748 7277",
    "sg:postcode":"K1B 5N6",
    "sg:province":"ON",
    "sg:tags":[
        "ventilating",
        "sheet",
        "work",
        "metal",
        "contractor"
    ],
    "wof:name":"S K Sheet Metal Ltd",
    "wof:placetype":"venue"
},
  "geometry": {"coordinates":[-75.61968231199999,45.4112548828],"type":"Point"}
}