{
  "type": "Feature",
  "properties": {
    "addr:full":"9441 120 St Delta BC V4C 6S2",
    "addr:housenumber":"9441",
    "addr:postcode":"v4c 6s2",
    "addr:street":"120 St",
    "iso:country":"CA",
    "sg:address":"9441 120 St",
    "sg:city":"Delta",
    "sg:classifiers":[
        {
            "category":"Restaurant",
            "type":"Food & Drink"
        }
    ],
    "sg:phone":"+1 604 582 6698",
    "sg:postcode":"V4C 6S2",
    "sg:province":"BC",
    "wof:name":"Jim the Greek Taverna",
    "wof:placetype":"venue"
},
  "geometry": {"coordinates":[-122.890427,49.174568],"type":"Point"}
}