{
  "type": "Feature",
  "properties": {
    "iso:country":"CA",
    "sg:city":"Vancouver",
    "sg:classifiers":[
        {
            "category":"Food & Beverages",
            "subcategory":"Specialty",
            "type":"Retail Goods"
        }
    ],
    "sg:phone":"+1 604 251 6060",
    "sg:postcode":"V5M 4N8",
    "sg:province":"BC",
    "sg:tags":[
        "health",
        "diet"
    ],
    "wof:name":"Wing Shing Medical CO",
    "wof:placetype":"venue"
},
  "geometry": {"coordinates":[-123.046669,49.269272],"type":"Point"}
}