{
  "type": "Feature",
  "properties": {
    "iso:country":"CA",
    "sg:address":"118 Cedar Crest St",
    "sg:city":"Kitchener",
    "sg:classifiers":[
        {
            "category":"Building & Trades",
            "subcategory":"Cleaning & Sanitation",
            "type":"Services"
        }
    ],
    "sg:phone":"+1 519 749 1140",
    "sg:postcode":"N2N 2A9",
    "sg:province":"ON",
    "sg:tags":[
        "janitor"
    ],
    "wof:name":"Ideal Touch Janitorial Svc",
    "wof:placetype":"venue"
},
  "geometry": {"coordinates":[-80.5409317017,43.4132881165],"type":"Point"}
}