{
  "type": "Feature",
  "properties": {
    "addr:full":"Quesnel BC V2J 2T1",
    "addr:postcode":"v2j 2t1",
    "iso:country":"CA",
    "sg:city":"Quesnel",
    "sg:classifiers":[
        {
            "category":"Real Estate",
            "subcategory":"Surveying",
            "type":"Services"
        }
    ],
    "sg:phone":"+1 250 992 2265",
    "sg:postcode":"V2J 2T1",
    "sg:province":"BC",
    "sg:tags":[
        "surveyor"
    ],
    "wof:name":"Wiles & Cindric Survey Bcls",
    "wof:placetype":"venue"
},
  "geometry": {"coordinates":[-122.49240899999999,52.978184],"type":"Point"}
}