{
  "type": "Feature",
  "properties": {
    "addr:full":"3119 Route 535 Cocagne NB E4R 3E3",
    "addr:housenumber":"3119",
    "addr:postcode":"e4r 3e3",
    "addr:street":"Route 535",
    "iso:country":"CA",
    "sg:address":"3119 Route 535",
    "sg:city":"Cocagne",
    "sg:classifiers":[
        {
            "category":"Manufacturing",
            "subcategory":"Signs",
            "type":"Manufacturing & Wholesale Goods"
        }
    ],
    "sg:phone":"+1 506 576 8224",
    "sg:postcode":"E4R 3E3",
    "sg:province":"NB",
    "wof:name":"Rogers Mobile Sign Rental",
    "wof:placetype":"venue"
},
  "geometry": {"coordinates":[-64.61432647709999,46.3338050842],"type":"Point"}
}