{
  "type": "Feature",
  "properties": {
    "iso:country":"CA",
    "sg:address":"9503 93 Ave",
    "sg:city":"Fort St John",
    "sg:classifiers":[
        {
            "category":"Retail",
            "subcategory":"Car Wash",
            "type":"Services"
        }
    ],
    "sg:phone":"+1 250 261 5558",
    "sg:postcode":"V1J 7A1",
    "sg:province":"BC",
    "sg:tags":[
        "polishing",
        "washing"
    ],
    "wof:name":"Wash Zone Enterprises Inc",
    "wof:placetype":"venue"
},
  "geometry": {"coordinates":[-120.837882996,56.238948822],"type":"Point"}
}