{
  "type": "Feature",
  "properties": {
    "addr:full":"11 Rue O T J Audet QC G0Y 1A0",
    "addr:housenumber":"11",
    "addr:postcode":"g0y 1a0",
    "addr:street":"Rue O",
    "iso:country":"CA",
    "sg:address":"11 Rue O T J",
    "sg:city":"Audet",
    "sg:classifiers":[
        {
            "category":"Home & Garden",
            "subcategory":"Building Materials",
            "type":"Retail Goods"
        }
    ],
    "sg:phone":"+1 819 583 3635",
    "sg:postcode":"G0Y 1A0",
    "sg:province":"QC",
    "sg:tags":[
        "hardware"
    ],
    "wof:name":"Ferronnerie LA Vieille Forge",
    "wof:placetype":"venue"
},
  "geometry": {"coordinates":[-70.7380905151,45.6589775085],"type":"Point"}
}