{
  "type": "Feature",
  "properties": {
    "addr:full":"211 Rue Amherst Amherst QC J0T 2L0",
    "addr:housenumber":"211",
    "addr:postcode":"j0t 2l0",
    "addr:street":"Rue Amherst",
    "iso:country":"CA",
    "sg:address":"211 Rue Amherst",
    "sg:city":"Amherst",
    "sg:classifiers":[
        {
            "category":"Travel",
            "subcategory":"Hotels & Motels",
            "type":"Entertainment"
        }
    ],
    "sg:phone":"+1 819 687 3113",
    "sg:postcode":"J0T 2L0",
    "sg:province":"QC",
    "wof:name":"Hotel Chez Maurice",
    "wof:placetype":"venue"
},
  "geometry": {"coordinates":[-74.76313,46.008896],"type":"Point"}
}