{
  "type": "Feature",
  "properties": {
    "iso:country":"CA",
    "sg:address":"175 Rue Laurier",
    "sg:city":"Saint-Jean-Sur-Richelieu",
    "sg:classifiers":[
        {
            "category":"Personal",
            "type":"Services"
        }
    ],
    "sg:phone":"+1 450 346 5331",
    "sg:postcode":"J3B 6K5",
    "sg:province":"QC",
    "sg:tags":[
        "therapist",
        "massage"
    ],
    "wof:name":"Ouellette, Dianne",
    "wof:placetype":"venue"
},
  "geometry": {"coordinates":[-73.2559585571,45.3047103882],"type":"Point"}
}