{
  "type": "Feature",
  "properties": {
    "iso:country":"CA",
    "sg:city":"Delta",
    "sg:classifiers":[
        {
            "category":"Manufacturing",
            "subcategory":"Tools & Machinery",
            "type":"Manufacturing & Wholesale Goods"
        }
    ],
    "sg:phone":"+1 604 522 8303",
    "sg:postcode":"V3M 6M5",
    "sg:province":"BC",
    "sg:tags":[
        "equipment",
        "laboratory",
        "supply"
    ],
    "wof:name":"Innovatek Medical Inc",
    "wof:placetype":"venue"
},
  "geometry": {"coordinates":[-122.965187,49.161453],"type":"Point"}
}