{
  "type": "Feature",
  "properties": {
    "addr:full":"507 Rue Adoncour Longueuil QC J4G 2M6",
    "addr:housenumber":"507",
    "addr:postcode":"j4g 2m6",
    "addr:street":"Rue Adoncour",
    "iso:country":"CA",
    "sg:address":"507 Rue Adoncour",
    "sg:city":"Longueuil",
    "sg:classifiers":[
        {
            "category":"Health Services",
            "subcategory":"Medical Lab",
            "type":"Services"
        }
    ],
    "sg:phone":"+1 450 679 8105",
    "sg:postcode":"J4G 2M6",
    "sg:province":"QC",
    "wof:name":"Deschamps, Patrice",
    "wof:placetype":"venue"
},
  "geometry": {"coordinates":[-73.484131,45.555019],"type":"Point"}
}