{
  "type": "Feature",
  "properties": {
    "addr:full":"1464 Portugal Cove Rd Portugal Cove-St Philips NL A1M 3P3",
    "addr:housenumber":"1464",
    "addr:postcode":"a1m 3p3",
    "addr:street":"Portugal Cove Rd",
    "iso:country":"CA",
    "sg:address":"1464 Portugal Cove Rd",
    "sg:city":"Portugal Cove-St Philips",
    "sg:classifiers":[
        {
            "category":"Restaurant",
            "type":"Food & Drink"
        }
    ],
    "sg:phone":"+1 709 895 6585",
    "sg:postcode":"A1M 3P3",
    "sg:province":"NL",
    "sg:tags":[
        "convention",
        "meeting",
        "rooms",
        "banquet",
        "facility"
    ],
    "wof:name":"Murray's Pond Club",
    "wof:placetype":"venue"
},
  "geometry": {"coordinates":[-52.849174,47.628063],"type":"Point"}
}