{
  "type": "Feature",
  "properties": {
    "addr:full":"137 Milvan Dr North York ON M9L 1Z8",
    "addr:housenumber":"137",
    "addr:postcode":"m9l 1z8",
    "addr:street":"Milvan Dr",
    "iso:country":"CA",
    "sg:address":"137 Milvan Dr",
    "sg:city":"North York",
    "sg:classifiers":[
        {
            "category":"Building & Trades",
            "subcategory":"Construction",
            "type":"Services"
        }
    ],
    "sg:phone":"+1 905 660 6022",
    "sg:postcode":"M9L 1Z8",
    "sg:province":"ON",
    "sg:tags":[
        "woodworker"
    ],
    "wof:name":"Woodworking CO",
    "wof:placetype":"venue"
},
  "geometry": {"coordinates":[-79.5623092651,43.7572402954],"type":"Point"}
}