{
  "type": "Feature",
  "properties": {
    "addr:full":"1123 Broadview Ave East York ON M4K 2S6",
    "addr:housenumber":"1123",
    "addr:postcode":"m4k 2s6",
    "addr:street":"Broadview Ave",
    "iso:country":"CA",
    "sg:address":"1123 Broadview Ave",
    "sg:city":"East York",
    "sg:classifiers":[
        {
            "category":"Retail",
            "subcategory":"Laundry & Dry Cleaning",
            "type":"Services"
        }
    ],
    "sg:phone":"+1 416 425 0888",
    "sg:postcode":"M4K 2S6",
    "sg:province":"ON",
    "sg:tags":[
        "cleaners"
    ],
    "wof:name":"Royal Dry Cleaners",
    "wof:placetype":"venue"
},
  "geometry": {"coordinates":[-79.355659,43.687153],"type":"Point"}
}