{
  "type": "Feature",
  "properties": {
    "addr:full":"235 Boul DE LA Cote-Vertu Saint-Laurent QC H4N 1C8",
    "addr:housenumber":"235",
    "addr:postcode":"h4n 1c8",
    "addr:street":"Boul De La Cote-Vertu",
    "iso:country":"CA",
    "sg:address":"235 Boul DE LA Cote-Vertu",
    "sg:city":"Saint-Laurent",
    "sg:classifiers":[
        {
            "category":"Personal",
            "subcategory":"Beauty Salon",
            "type":"Services"
        }
    ],
    "sg:phone":"+1 514 332 7780",
    "sg:postcode":"H4N 1C8",
    "sg:province":"QC",
    "wof:name":"X-Pert Coiffure Unisexe Inc",
    "wof:placetype":"venue"
},
  "geometry": {"coordinates":[-73.66951,45.528343],"type":"Point"}
}