{
  "type": "Feature",
  "properties": {
    "addr:full":"735 Fernlea Rd Delhi ON N4B 2W6",
    "addr:housenumber":"735",
    "addr:postcode":"n4b 2w6",
    "addr:street":"Fernlea Rd",
    "iso:country":"CA",
    "sg:address":"735 Fernlea Rd",
    "sg:city":"Delhi",
    "sg:classifiers":[
        {
            "category":"Retail",
            "subcategory":"Animal Services",
            "type":"Services"
        }
    ],
    "sg:phone":"+1 519 582 0111",
    "sg:postcode":"N4B 2W6",
    "sg:province":"ON",
    "sg:tags":[
        "pet",
        "boarding",
        "sitting"
    ],
    "wof:name":"Fernlea Boarding Kennel",
    "wof:placetype":"venue"
},
  "geometry": {"coordinates":[-80.5864028931,42.8432121277],"type":"Point"}
}