{
  "type": "Feature",
  "properties": {
    "addr:full":"20 Aiton Cres Hartland NB E7P 2H2",
    "addr:housenumber":"20",
    "addr:postcode":"e7p 2h2",
    "addr:street":"Aiton Cres",
    "iso:country":"CA",
    "sg:address":"20 Aiton Cres",
    "sg:city":"Hartland",
    "sg:classifiers":[
        {
            "category":"Wholesale",
            "subcategory":"Drugs",
            "type":"Manufacturing & Wholesale Goods"
        }
    ],
    "sg:phone":"+1 506 375 4469",
    "sg:postcode":"E7P 2H2",
    "sg:province":"NB",
    "sg:tags":[
        "pharmaceutical",
        "product"
    ],
    "wof:name":"Aiton Drug CO Ltd",
    "wof:placetype":"venue"
},
  "geometry": {"coordinates":[-67.51741790769999,46.2983665466],"type":"Point"}
}