{
  "type": "Feature",
  "properties": {
    "addr:full":"Trail BC V1R 3V1",
    "addr:postcode":"bc v1r 3v1",
    "addr:street":"Trail",
    "iso:country":"CA",
    "sg:city":"Trail",
    "sg:classifiers":[
        {
            "category":"Professional",
            "subcategory":"Lawyer & Legal Services",
            "type":"Services"
        }
    ],
    "sg:phone":"+1 250 368 3327",
    "sg:postcode":"V1R 3V1",
    "sg:province":"BC",
    "sg:tags":[
        "attorney"
    ],
    "wof:name":"Brown, Robert G P",
    "wof:placetype":"venue"
},
  "geometry": {"coordinates":[-117.70906829800001,49.0969047546],"type":"Point"}
}