{
  "type": "Feature",
  "properties": {
    "addr:full":"75 Tillsley Dr Kitchener ON N2E 3T1",
    "addr:housenumber":"75",
    "addr:postcode":"n2e 3t1",
    "addr:street":"Tillsley Dr",
    "iso:country":"CA",
    "sg:address":"75 Tillsley Dr",
    "sg:city":"Kitchener",
    "sg:classifiers":[
        {
            "category":"Organizations",
            "subcategory":"Religious Organization",
            "type":"Services"
        }
    ],
    "sg:phone":"+1 519 745 3351",
    "sg:postcode":"N2E 3T1",
    "sg:province":"ON",
    "sg:tags":[
        "church"
    ],
    "wof:name":"Salvation Army",
    "wof:placetype":"venue"
},
  "geometry": {"coordinates":[-80.4981918335,43.408870697],"type":"Point"}
}