{
  "type": "Feature",
  "properties": {
    "addr:full":"North York ON M2J 4Y1",
    "addr:postcode":"m2j 4y1",
    "iso:country":"CA",
    "sg:city":"North York",
    "sg:classifiers":[
        {
            "category":"Professional",
            "subcategory":"Accounting & Tax Preparation",
            "type":"Services"
        }
    ],
    "sg:phone":"+1 416 502 1682",
    "sg:postcode":"M2J 4Y1",
    "sg:province":"ON",
    "sg:tags":[
        "accountant"
    ],
    "wof:name":"Murad, Nalbandian CA",
    "wof:placetype":"venue"
},
  "geometry": {"coordinates":[-79.329285,43.774719],"type":"Point"}
}