{
  "type": "Feature",
  "properties": {
    "iso:country":"CA",
    "sg:address":"2881 Pasqua St",
    "sg:city":"Regina",
    "sg:classifiers":[
        {
            "category":"Manufacturing",
            "subcategory":"Metals",
            "type":"Manufacturing & Wholesale Goods"
        }
    ],
    "sg:phone":"+1 306 775 3611",
    "sg:postcode":"S4S 2H4",
    "sg:province":"SK",
    "sg:tags":[
        "scrap",
        "iron"
    ],
    "wof:name":"Wheat City Metals",
    "wof:placetype":"venue"
},
  "geometry": {"coordinates":[-104.64067840600001,50.434223175],"type":"Point"}
}