{
  "type": "Feature",
  "properties": {
    "addr:full":"Surrey BC V3R 4H2",
    "addr:postcode":"v3r 4h2",
    "iso:country":"CA",
    "sg:city":"Surrey",
    "sg:classifiers":[
        {
            "category":"Arts & Performance",
            "subcategory":"Theater",
            "type":"Entertainment"
        }
    ],
    "sg:phone":"+1 604 588 8739",
    "sg:postcode":"V3R 4H2",
    "sg:province":"BC",
    "sg:tags":[
        "live",
        "music"
    ],
    "wof:name":"Night Hawks Music Svc",
    "wof:placetype":"venue"
},
  "geometry": {"coordinates":[-122.80062100000001,49.199417],"type":"Point"}
}