{
  "type": "Feature",
  "properties": {
    "iso:country":"CA",
    "sg:address":"85 Chain Lake Dr",
    "sg:city":"Halifax",
    "sg:classifiers":[
        {
            "category":"Retail",
            "subcategory":"Auto Repair",
            "type":"Services"
        }
    ],
    "sg:phone":"+1 902 450 5100",
    "sg:postcode":"B3S 1A3",
    "sg:province":"NS",
    "sg:tags":[
        "body",
        "automobile",
        "painting"
    ],
    "wof:name":"Coachworks Limited",
    "wof:placetype":"venue"
},
  "geometry": {"coordinates":[-63.6714477539,44.6386756897],"type":"Point"}
}