{
  "type": "Feature",
  "properties": {
    "addr:full":"525 Mowat Ave Fort Frances ON P9A 1Z1",
    "addr:housenumber":"525",
    "addr:postcode":"p9a 1z1",
    "addr:street":"Mowat Ave",
    "iso:country":"CA",
    "sg:address":"525 Mowat Ave",
    "sg:city":"Fort Frances",
    "sg:classifiers":[
        {
            "category":"Retail",
            "subcategory":"Repair Shop",
            "type":"Services"
        }
    ],
    "sg:phone":"+1 807 274 9728",
    "sg:postcode":"P9A 1Z1",
    "sg:province":"ON",
    "sg:tags":[
        "upholsterer"
    ],
    "wof:name":"Quality Custom Swng & Uphlstry",
    "wof:placetype":"venue"
},
  "geometry": {"coordinates":[-93.39883399999999,48.610283],"type":"Point"}
}