{
  "type": "Feature",
  "properties": {
    "addr:full":"7344 Blues Mills Whycocomagh NS B0E 3M0",
    "addr:housenumber":"7344",
    "addr:postcode":"b0e 3m0",
    "iso:country":"CA",
    "sg:address":"7344 Blues Mills",
    "sg:city":"Whycocomagh",
    "sg:classifiers":[
        {
            "category":"Restaurant",
            "type":"Food & Drink"
        }
    ],
    "sg:phone":"+1 902 756 3600",
    "sg:postcode":"B0E 3M0",
    "sg:province":"NS",
    "sg:tags":[
        "delicatessen"
    ],
    "wof:name":"Paradise Meat",
    "wof:placetype":"venue"
},
  "geometry": {"coordinates":[-61.125492,45.975029],"type":"Point"}
}