{
  "type": "Feature",
  "properties": {
    "addr:full":"2175 Av Saint-Clement Beauport QC G1E 6X6",
    "addr:housenumber":"2175",
    "addr:postcode":"qc g1e 6x6",
    "addr:street":"Av Saint-Clement",
    "iso:country":"CA",
    "sg:address":"2175 Av Saint-Clement",
    "sg:city":"Beauport",
    "sg:classifiers":[
        {
            "category":"Recreation",
            "type":"Entertainment"
        }
    ],
    "sg:phone":"+1 418 666 2177",
    "sg:postcode":"G1E 6X6",
    "sg:province":"QC",
    "sg:tags":[
        "government",
        "hall",
        "auditorium"
    ],
    "wof:name":"Beauport Sportif Alexis-Berube",
    "wof:placetype":"venue"
},
  "geometry": {"coordinates":[-71.21225,46.850536],"type":"Point"}
}