{
  "type": "Feature",
  "properties": {
    "addr:full":"264 1st Ave E Regina SK S4N 5H2",
    "addr:housenumber":"264",
    "addr:postcode":"s4n 5h2",
    "addr:street":"1St Ave E",
    "iso:country":"CA",
    "sg:address":"264 1st Ave E",
    "sg:city":"Regina",
    "sg:classifiers":[
        {
            "category":"Wholesale",
            "subcategory":"Electrical",
            "type":"Manufacturing & Wholesale Goods"
        }
    ],
    "sg:phone":"+1 306 721 2500",
    "sg:postcode":"S4N 5H2",
    "sg:province":"SK",
    "sg:tags":[
        "equipment",
        "electric",
        "supply"
    ],
    "wof:name":"Westburne Electric",
    "wof:placetype":"venue"
},
  "geometry": {"coordinates":[-104.579216003,50.4678192139],"type":"Point"}
}