{
  "type": "Feature",
  "properties": {
    "addr:full":"19 Macaulays Dr Sydney NS B1P 3Z8",
    "addr:housenumber":"19",
    "addr:postcode":"b1p 3z8",
    "addr:street":"Macaulays Dr",
    "iso:country":"CA",
    "sg:address":"19 Macaulays Dr",
    "sg:city":"Sydney",
    "sg:classifiers":[
        {
            "category":"Shopping",
            "subcategory":"Bicycles & Sporting Goods",
            "type":"Retail Goods"
        }
    ],
    "sg:phone":"+1 902 564 0077",
    "sg:postcode":"B1P 3Z8",
    "sg:province":"NS",
    "sg:tags":[
        "gun",
        "gunsmith"
    ],
    "wof:name":"Russell Firearms Ltd",
    "wof:placetype":"venue"
},
  "geometry": {"coordinates":[-60.163647,46.139202],"type":"Point"}
}