{
  "type": "Feature",
  "properties": {
    "addr:full":"3375 Kirk Rd Denman Island BC V0R 1T0",
    "addr:housenumber":"3375",
    "addr:postcode":"v0r 1t0",
    "addr:street":"Kirk Rd",
    "iso:country":"CA",
    "sg:address":"3375 Kirk Rd",
    "sg:city":"Denman Island",
    "sg:classifiers":[
        {
            "category":"Travel",
            "subcategory":"Hotels & Motels",
            "type":"Entertainment"
        }
    ],
    "sg:phone":"+1 250 335 0905",
    "sg:postcode":"V0R 1T0",
    "sg:province":"BC",
    "sg:tags":[
        "breakfast",
        "accommodation",
        "bed"
    ],
    "wof:name":"Hawthorn House Bed & Breakfast",
    "wof:placetype":"venue"
},
  "geometry": {"coordinates":[-124.808303833,49.5366821289],"type":"Point"}
}