{
  "type": "Feature",
  "properties": {
    "iso:country":"CA",
    "sg:address":"1040 Rue Saint-Aubin",
    "sg:city":"Saint-Laurent",
    "sg:classifiers":[
        {
            "category":"Building & Trades",
            "subcategory":"Landscaping Services",
            "type":"Services"
        }
    ],
    "sg:phone":"+1 514 332 6055",
    "sg:postcode":"H4R 1T3",
    "sg:province":"QC",
    "sg:tags":[
        "landscape",
        "contractor"
    ],
    "wof:name":"L J Ottoni Inc",
    "wof:placetype":"venue"
},
  "geometry": {"coordinates":[-73.6898574829,45.5092697144],"type":"Point"}
}