{
  "type": "Feature",
  "properties": {
    "addr:full":"3640 52 St SE Calgary AB T2B 3H1",
    "addr:housenumber":"3640",
    "addr:postcode":"t2b 3h1",
    "addr:street":"52 St Se",
    "iso:country":"CA",
    "sg:address":"3640 52 St SE",
    "sg:city":"Calgary",
    "sg:classifiers":[
        {
            "category":"Wholesale",
            "subcategory":"Construction Materials",
            "type":"Manufacturing & Wholesale Goods"
        }
    ],
    "sg:phone":"+1 403 569 0388",
    "sg:postcode":"T2B 3H1",
    "sg:province":"AB",
    "sg:tags":[
        "sand",
        "gravel",
        "landscape",
        "contractor"
    ],
    "wof:name":"Superior Loam Svc",
    "wof:placetype":"venue"
},
  "geometry": {"coordinates":[-113.958221435,51.0228424072],"type":"Point"}
}