{
  "type": "Feature",
  "properties": {
    "addr:full":"511 3rd Ave S Wapella SK S0G 4Z0",
    "addr:housenumber":"511",
    "addr:postcode":"s0g 4z0",
    "addr:street":"3Rd Ave S",
    "iso:country":"CA",
    "sg:address":"511 3rd Ave S",
    "sg:city":"Wapella",
    "sg:classifiers":[
        {
            "category":"Building & Trades",
            "subcategory":"Construction",
            "type":"Services"
        }
    ],
    "sg:phone":"+1 306 532 4330",
    "sg:postcode":"S0G 4Z0",
    "sg:province":"SK",
    "sg:tags":[
        "company",
        "general",
        "contractor"
    ],
    "wof:name":"Lynco Construction Ltd",
    "wof:placetype":"venue"
},
  "geometry": {"coordinates":[-101.96998600000001,50.260963],"type":"Point"}
}