{
  "type": "Feature",
  "properties": {
    "iso:country":"CA",
    "sg:address":"385 Rue Du Pont",
    "sg:city":"Mont-Laurier",
    "sg:classifiers":[
        {
            "category":"Education",
            "subcategory":"Library",
            "type":"Public Place"
        }
    ],
    "sg:phone":"+1 819 623 1833",
    "sg:postcode":"J9L 2R5",
    "sg:province":"QC",
    "wof:name":"Mont-Laurier Bibliotheque",
    "wof:placetype":"venue"
},
  "geometry": {"coordinates":[-75.4986038208,46.5502510071],"type":"Point"}
}