{
  "type": "Feature",
  "properties": {
    "iso:country":"CA",
    "sg:address":"41 King St",
    "sg:city":"North Sydney",
    "sg:classifiers":[
        {
            "category":"Health Services",
            "subcategory":"Medical Lab",
            "type":"Services"
        }
    ],
    "sg:phone":"+1 902 794 4242",
    "sg:postcode":"B2A 2S7",
    "sg:province":"NS",
    "wof:name":"Mac Donald's Denture Clinic",
    "wof:placetype":"venue"
},
  "geometry": {"coordinates":[-60.2539558411,46.2095565796],"type":"Point"}
}