{
  "type": "Feature",
  "properties": {
    "addr:full":"45 Rue Main O Coaticook QC J1A 1P3",
    "addr:housenumber":"45",
    "addr:postcode":"j1a 1p3",
    "addr:street":"Rue Main O",
    "iso:country":"CA",
    "sg:address":"45 Rue Main O",
    "sg:city":"Coaticook",
    "sg:classifiers":[
        {
            "category":"Home & Garden",
            "subcategory":"Furniture",
            "type":"Retail Goods"
        }
    ],
    "sg:phone":"+1 819 849 6337",
    "sg:postcode":"J1A 1P3",
    "sg:province":"QC",
    "wof:name":"Dupuis & Fils Inc",
    "wof:placetype":"venue"
},
  "geometry": {"coordinates":[-71.804878,45.132607],"type":"Point"}
}