{
  "type": "Feature",
  "properties": {
    "iso:country":"CA",
    "sg:city":"High Level",
    "sg:classifiers":[
        {
            "category":"Retail",
            "subcategory":"Laundry & Dry Cleaning",
            "type":"Services"
        }
    ],
    "sg:phone":"+1 780 926 4644",
    "sg:postcode":"T0H 1Z0",
    "sg:province":"AB",
    "sg:tags":[
        "cleaners"
    ],
    "wof:name":"High'n Dry Cleaners Ltd",
    "wof:placetype":"venue"
},
  "geometry": {"coordinates":[-117.129997253,58.5180358887],"type":"Point"}
}