{
  "type": "Feature",
  "properties": {
    "addr:full":"PO Box 808 Carstairs AB T0M 0N0",
    "addr:housenumber":"po",
    "addr:postcode":"t0m 0n0",
    "addr:street":"Box 808",
    "iso:country":"CA",
    "sg:address":"PO Box 808",
    "sg:city":"Carstairs",
    "sg:classifiers":[
        {
            "category":"Organizations",
            "subcategory":"Religious Organization",
            "type":"Services"
        }
    ],
    "sg:phone":"+1 403 337 3312",
    "sg:postcode":"T0M 0N0",
    "sg:province":"AB",
    "sg:tags":[
        "church"
    ],
    "wof:name":"Inter Act Ministries-Canada",
    "wof:placetype":"venue"
},
  "geometry": {"coordinates":[-114.095428,51.562595],"type":"Point"}
}