{
  "type": "Feature",
  "properties": {
    "addr:full":"625 Seneca Hill Dr North York ON M2J 2W6",
    "addr:housenumber":"625",
    "addr:postcode":"m2j 2w6",
    "addr:street":"Seneca Hill Dr",
    "iso:country":"CA",
    "sg:address":"625 Seneca Hill Dr",
    "sg:city":"North York",
    "sg:classifiers":[
        {
            "category":"Education",
            "subcategory":"School",
            "type":"Public Place"
        }
    ],
    "sg:phone":"+1 416 395 2840",
    "sg:postcode":"M2J 2W6",
    "sg:province":"ON",
    "wof:name":"Seneca Hill Public School",
    "wof:placetype":"venue"
},
  "geometry": {"coordinates":[-79.35105900000001,43.790768],"type":"Point"}
}