{
  "type": "Feature",
  "properties": {
    "addr:full":"190 Industrial Ave Carleton Place ON K7C 3T2",
    "addr:housenumber":"190",
    "addr:postcode":"k7c 3t2",
    "addr:street":"Industrial Ave",
    "iso:country":"CA",
    "sg:address":"190 Industrial Ave",
    "sg:city":"Carleton Place",
    "sg:classifiers":[
        {
            "category":"Freight",
            "type":"Transportation"
        }
    ],
    "sg:phone":"+1 613 257 1454",
    "sg:postcode":"K7C 3T2",
    "sg:province":"ON",
    "sg:tags":[
        "warehouse",
        "self",
        "storage"
    ],
    "wof:name":"Norwalk Warehouse",
    "wof:placetype":"venue"
},
  "geometry": {"coordinates":[-76.146423,45.153111],"type":"Point"}
}