{
  "type": "Feature",
  "properties": {
    "addr:full":"Fergus ON N1M 3T8",
    "addr:postcode":"n1m 3t8",
    "iso:country":"CA",
    "sg:city":"Fergus",
    "sg:classifiers":[
        {
            "category":"Home & Garden",
            "subcategory":"Building Materials",
            "type":"Retail Goods"
        }
    ],
    "sg:phone":"+1 519 787 1393",
    "sg:postcode":"N1M 3T8",
    "sg:province":"ON",
    "sg:tags":[
        "paint"
    ],
    "wof:name":"Colour Your World",
    "wof:placetype":"venue"
},
  "geometry": {"coordinates":[-80.37814299999999,43.705444],"type":"Point"}
}