{
  "type": "Feature",
  "properties": {
    "addr:full":"16 Market St Fenelon Falls ON K0M 1N0",
    "addr:housenumber":"16",
    "addr:postcode":"k0m 1n0",
    "addr:street":"Market St",
    "iso:country":"CA",
    "sg:address":"16 Market St",
    "sg:city":"Fenelon Falls",
    "sg:classifiers":[
        {
            "category":"Retail",
            "subcategory":"Laundry & Dry Cleaning",
            "type":"Services"
        }
    ],
    "sg:phone":"+1 705 887 2472",
    "sg:postcode":"K0M 1N0",
    "sg:province":"ON",
    "sg:tags":[
        "cleaners"
    ],
    "wof:name":"Fenelon Cleaners & Laundromat",
    "wof:placetype":"venue"
},
  "geometry": {"coordinates":[-78.7377319336,44.537902832],"type":"Point"}
}