{
  "type": "Feature",
  "properties": {
    "addr:full":"Mississauga ON L5T 1M1",
    "addr:postcode":"l5t 1m1",
    "iso:country":"CA",
    "sg:city":"Mississauga",
    "sg:classifiers":[
        {
            "category":"Wholesale",
            "subcategory":"Chemicals & Plastics",
            "type":"Manufacturing & Wholesale Goods"
        }
    ],
    "sg:phone":"+1 905 795 1766",
    "sg:postcode":"L5T 1M1",
    "sg:province":"ON",
    "sg:tags":[
        "zinc"
    ],
    "wof:name":"Zincaloy Inc",
    "wof:placetype":"venue"
},
  "geometry": {"coordinates":[-79.651268,43.660328],"type":"Point"}
}