{
  "type": "Feature",
  "properties": {
    "iso:country":"CA",
    "sg:address":"90 Banting Ave",
    "sg:city":"Oshawa",
    "sg:classifiers":[
        {
            "category":"Wholesale",
            "subcategory":"Electrical",
            "type":"Manufacturing & Wholesale Goods"
        }
    ],
    "sg:phone":"+1 905 438 8933",
    "sg:postcode":"L1H 2M2",
    "sg:province":"ON",
    "sg:tags":[
        "battery",
        "equipment",
        "charging"
    ],
    "wof:name":"Yortech",
    "wof:placetype":"venue"
},
  "geometry": {"coordinates":[-78.856277,43.890137],"type":"Point"}
}