{
  "type": "Feature",
  "properties": {
    "iso:country":"CA",
    "sg:address":"137 Niagara St",
    "sg:city":"St Catharines",
    "sg:classifiers":[
        {
            "category":"Autos & Motor Vehicles",
            "subcategory":"Automobile Sales",
            "type":"Retail Goods"
        }
    ],
    "sg:phone":"+1 905 687 9066",
    "sg:postcode":"L2R 4L6",
    "sg:province":"ON",
    "sg:tags":[
        "car",
        "dealer"
    ],
    "wof:name":"A V Motors",
    "wof:placetype":"venue"
},
  "geometry": {"coordinates":[-79.23487091059999,43.1694984436],"type":"Point"}
}