{
  "type": "Feature",
  "properties": {
    "iso:country":"CA",
    "sg:city":"London",
    "sg:classifiers":[
        {
            "category":"Health Services",
            "subcategory":"Health Practitioner",
            "type":"Services"
        }
    ],
    "sg:phone":"+1 519 661 2021",
    "sg:postcode":"N6G 1H1",
    "sg:province":"ON",
    "sg:tags":[
        "pathologist",
        "speech"
    ],
    "wof:name":"Uwo Speech & Hearing Clinic",
    "wof:placetype":"venue"
},
  "geometry": {"coordinates":[-81.246216,42.986897],"type":"Point"}
}