{
  "type": "Feature",
  "properties": {
    "addr:full":"661 Fortune Dr Kamloops BC V2B 2K7",
    "addr:housenumber":"661",
    "addr:postcode":"bc v2b 2k7",
    "addr:street":"Fortune Dr",
    "iso:country":"CA",
    "sg:address":"661 Fortune Dr",
    "sg:city":"Kamloops",
    "sg:classifiers":[
        {
            "category":"Restaurant",
            "type":"Food & Drink"
        }
    ],
    "sg:phone":"+1 250 376 0222",
    "sg:postcode":"V2B 2K7",
    "sg:province":"BC",
    "wof:name":"Mc Donald's",
    "wof:placetype":"venue"
},
  "geometry": {"coordinates":[-120.35660553,50.6958007812],"type":"Point"}
}