{
  "type": "Feature",
  "properties": {
    "addr:full":"Calgary AB T2C 2G5",
    "addr:postcode":"t2c 2g5",
    "iso:country":"CA",
    "sg:city":"Calgary",
    "sg:classifiers":[
        {
            "category":"Building & Trades",
            "subcategory":"Construction",
            "type":"Services"
        }
    ],
    "sg:phone":"+1 403 255 5000",
    "sg:postcode":"T2C 2G5",
    "sg:province":"AB",
    "sg:tags":[
        "dry wall",
        "contractor"
    ],
    "wof:name":"Excel Interior Contracting",
    "wof:placetype":"venue"
},
  "geometry": {"coordinates":[-113.97145080599999,50.9893875122],"type":"Point"}
}