{
  "type": "Feature",
  "properties": {
    "addr:full":"Allowance E RR 1 Marquette MB R0H 0V0",
    "addr:postcode":"r0h 0v0",
    "addr:street":"Rr 1",
    "iso:country":"CA",
    "sg:address":"Allowance E RR 1",
    "sg:city":"Marquette",
    "sg:classifiers":[
        {
            "category":"Banks & Credit Unions",
            "subcategory":"Bank",
            "type":"Services"
        }
    ],
    "sg:phone":"+1 204 375 6646",
    "sg:postcode":"R0H 0V0",
    "sg:province":"MB",
    "wof:name":"Caisse Populaire D'Elie",
    "wof:placetype":"venue"
},
  "geometry": {"coordinates":[-97.7204742432,50.0617408752],"type":"Point"}
}