{
  "type": "Feature",
  "properties": {
    "addr:full":"3596 44 Ave SE Calgary AB T2B 3J9",
    "addr:housenumber":"3596",
    "addr:postcode":"t2b 3j9",
    "addr:street":"44 Ave Se",
    "iso:country":"CA",
    "sg:address":"3596 44 Ave SE",
    "sg:city":"Calgary",
    "sg:classifiers":[
        {
            "category":"Retail",
            "subcategory":"Auto Repair",
            "type":"Services"
        }
    ],
    "sg:phone":"+1 403 273 8600",
    "sg:postcode":"T2B 3J9",
    "sg:province":"AB",
    "sg:tags":[
        "body",
        "automobile",
        "painting"
    ],
    "wof:name":"White Knight Auto Body Ltd",
    "wof:placetype":"venue"
},
  "geometry": {"coordinates":[-113.981803894,51.014125824],"type":"Point"}
}