{
  "type": "Feature",
  "properties": {
    "iso:country":"CA",
    "sg:address":"1791 Boul Saint-Martin O",
    "sg:city":"Laval",
    "sg:classifiers":[
        {
            "category":"Shopping",
            "type":"Retail Goods"
        }
    ],
    "sg:phone":"+1 450 687 6325",
    "sg:postcode":"H7S 1N2",
    "sg:province":"QC",
    "sg:tags":[
        "pet",
        "shop"
    ],
    "wof:name":"Centre D'Animaux Nature",
    "wof:placetype":"venue"
},
  "geometry": {"coordinates":[-73.72982,45.567089],"type":"Point"}
}