{
  "type": "Feature",
  "properties": {
    "addr:full":"20109 107 Ave NW Edmonton AB T5S 1W4",
    "addr:housenumber":"20109",
    "addr:postcode":"t5s 1w4",
    "addr:street":"107 Ave Nw",
    "iso:country":"CA",
    "sg:address":"20109 107 Ave NW",
    "sg:city":"Edmonton",
    "sg:classifiers":[
        {
            "category":"Retail",
            "subcategory":"Repair Shop",
            "type":"Services"
        }
    ],
    "sg:phone":"+1 780 447 3077",
    "sg:postcode":"T5S 1W4",
    "sg:province":"AB",
    "sg:tags":[
        "welding"
    ],
    "wof:name":"Pigford Welding Ltd",
    "wof:placetype":"venue"
},
  "geometry": {"coordinates":[-113.669296,53.5509],"type":"Point"}
}