{
  "type": "Feature",
  "properties": {
    "addr:full":"3273 Montague St Regina SK S4S 1Z8",
    "addr:housenumber":"3273",
    "addr:postcode":"s4s 1z8",
    "addr:street":"Montague St",
    "iso:country":"CA",
    "sg:address":"3273 Montague St",
    "sg:city":"Regina",
    "sg:classifiers":[
        {
            "category":"Organizations",
            "subcategory":"Religious Organization",
            "type":"Services"
        }
    ],
    "sg:phone":"+1 306 585 0090",
    "sg:postcode":"S4S 1Z8",
    "sg:province":"SK",
    "sg:tags":[
        "church"
    ],
    "wof:name":"Islamic Assn-Saskatchewan Inc",
    "wof:placetype":"venue"
},
  "geometry": {"coordinates":[-104.629486,50.427254],"type":"Point"}
}