{
  "type": "Feature",
  "properties": {
    "addr:full":"251 Av DE LA Colline Aylmer QC J9J 1T1",
    "addr:postcode":"j9j 1t1",
    "addr:street":"251 Av De La Colline",
    "iso:country":"CA",
    "sg:address":"251 Av DE LA Colline",
    "sg:city":"Aylmer",
    "sg:classifiers":[
        {
            "category":"Personal",
            "type":"Services"
        }
    ],
    "sg:phone":"+1 819 684 7242",
    "sg:postcode":"J9J 1T1",
    "sg:province":"QC",
    "sg:tags":[
        "medicine",
        "orthopedic",
        "therapist",
        "massage"
    ],
    "wof:name":"Clinique Ortho Sante",
    "wof:placetype":"venue"
},
  "geometry": {"coordinates":[-75.829842,45.40097],"type":"Point"}
}