{
  "type": "Feature",
  "properties": {
    "addr:full":"Carstairs AB T0M 0N0",
    "addr:postcode":"t0m 0n0",
    "iso:country":"CA",
    "sg:city":"Carstairs",
    "sg:classifiers":[
        {
            "category":"Insurance",
            "subcategory":"Insurance Agent",
            "type":"Services"
        }
    ],
    "sg:phone":"+1 403 337 3244",
    "sg:postcode":"T0M 0N0",
    "sg:province":"AB",
    "wof:name":"Amalgamated Insurance Spclsts",
    "wof:placetype":"venue"
},
  "geometry": {"coordinates":[-114.098457,51.563942],"type":"Point"}
}