{
  "type": "Feature",
  "properties": {
    "addr:full":"107 Central Ave E Linden AB T0M 1J0",
    "addr:housenumber":"107",
    "addr:postcode":"t0m 1j0",
    "addr:street":"Central Ave E",
    "iso:country":"CA",
    "sg:address":"107 Central Ave E",
    "sg:city":"Linden",
    "sg:classifiers":[
        {
            "category":"Personal",
            "subcategory":"Beauty Salon",
            "type":"Services"
        }
    ],
    "sg:phone":"+1 403 546 4146",
    "sg:postcode":"T0M 1J0",
    "sg:province":"AB",
    "wof:name":"Village Barber",
    "wof:placetype":"venue"
},
  "geometry": {"coordinates":[-113.48474899999999,51.590546],"type":"Point"}
}