{
  "type": "Feature",
  "properties": {
    "addr:full":"Les Eboulements QC G0A 2M0",
    "addr:postcode":"g0a 2m0",
    "iso:country":"CA",
    "sg:city":"Les Eboulements",
    "sg:classifiers":[
        {
            "category":"Retail",
            "subcategory":"Auto Repair",
            "type":"Services"
        }
    ],
    "sg:phone":"+1 418 635 2468",
    "sg:postcode":"G0A 2M0",
    "sg:province":"QC",
    "sg:tags":[
        "repairing",
        "automobile"
    ],
    "wof:name":"Garage Edmond Bradet Inc",
    "wof:placetype":"venue"
},
  "geometry": {"coordinates":[-70.32521820069999,47.4787330627],"type":"Point"}
}