{
  "type": "Feature",
  "properties": {
    "addr:full":"2310 Avenue C N Saskatoon SK S7L 5X5",
    "addr:housenumber":"2310",
    "addr:postcode":"s7l 5x5",
    "addr:street":"Avenue;N",
    "iso:country":"CA",
    "sg:address":"2310 Avenue C N",
    "sg:city":"Saskatoon",
    "sg:classifiers":[
        {
            "category":"Home & Garden",
            "subcategory":"Household Appliances",
            "type":"Retail Goods"
        }
    ],
    "sg:phone":"+1 306 373 2400",
    "sg:postcode":"S7L 5X5",
    "sg:province":"SK",
    "wof:name":"Mr Appliance",
    "wof:placetype":"venue"
},
  "geometry": {"coordinates":[-106.673995972,52.1619300842],"type":"Point"}
}