{
  "type": "Feature",
  "properties": {
    "addr:full":"5255 Hwy 10 New Germany NS B0R 1E0",
    "addr:housenumber":"5255",
    "addr:postcode":"b0r 1e0",
    "addr:street":"Hwy 10",
    "iso:country":"CA",
    "sg:address":"5255 Hwy 10",
    "sg:city":"New Germany",
    "sg:classifiers":[
        {
            "category":"Shopping",
            "subcategory":"Gifts & Souvenirs",
            "type":"Retail Goods"
        }
    ],
    "sg:phone":"+1 902 644 2829",
    "sg:postcode":"B0R 1E0",
    "sg:province":"NS",
    "sg:tags":[
        "shop",
        "video",
        "disc",
        "tape"
    ],
    "wof:name":"New Germany Video",
    "wof:placetype":"venue"
},
  "geometry": {"coordinates":[-64.7177200317,44.5440406799],"type":"Point"}
}