{
  "type": "Feature",
  "properties": {
    "addr:full":"21 Dundas Sq # 303 Toronto ON M5B 1B7",
    "addr:housenumber":"21",
    "addr:postcode":"m5b 1b7",
    "addr:street":"Dundas Sq # 303",
    "iso:country":"CA",
    "sg:address":"21 Dundas Sq # 303",
    "sg:city":"Toronto",
    "sg:classifiers":[
        {
            "category":"Manufacturing",
            "subcategory":"Jewelry",
            "type":"Manufacturing & Wholesale Goods"
        }
    ],
    "sg:phone":"+1 416 362 0865",
    "sg:postcode":"M5B 1B7",
    "sg:province":"ON",
    "wof:name":"Fame Jewellers",
    "wof:placetype":"venue"
},
  "geometry": {"coordinates":[-79.37989,43.655834],"type":"Point"}
}