{
  "type": "Feature",
  "properties": {
    "addr:full":"1 King St E Hamilton ON L8N 1A1",
    "addr:housenumber":"1",
    "addr:postcode":"l8n 1a1",
    "addr:street":"King St E",
    "iso:country":"CA",
    "sg:address":"1 King St E",
    "sg:city":"Hamilton",
    "sg:classifiers":[
        {
            "category":"Food & Beverages",
            "subcategory":"Groceries & Convenience Stores",
            "type":"Retail Goods"
        }
    ],
    "sg:phone":"+1 905 525 2262",
    "sg:postcode":"L8N 1A1",
    "sg:province":"ON",
    "wof:name":"King & James Convenience",
    "wof:placetype":"venue"
},
  "geometry": {"coordinates":[-79.8689041138,43.2567176819],"type":"Point"}
}