{
  "type": "Feature",
  "properties": {
    "addr:full":"63 Rue Ambroise-Fafard Baie-Saint-Paul QC G3Z 2J7",
    "addr:housenumber":"63",
    "addr:postcode":"g3z 2j7",
    "addr:street":"Rue Ambroise-Fafard",
    "iso:country":"CA",
    "sg:address":"63 Rue Ambroise-Fafard",
    "sg:city":"Baie-Saint-Paul",
    "sg:classifiers":[
        {
            "category":"Organizations",
            "subcategory":"Religious Organization",
            "type":"Services"
        }
    ],
    "sg:phone":"+1 418 435 3520",
    "sg:postcode":"G3Z 2J7",
    "sg:province":"QC",
    "wof:name":"Petites Franciscaines DE Marie",
    "wof:placetype":"venue"
},
  "geometry": {"coordinates":[-70.507355,47.43692],"type":"Point"}
}