{
  "type": "Feature",
  "properties": {
    "iso:country":"CA",
    "sg:city":"Winnipeg",
    "sg:classifiers":[
        {
            "category":"Professional",
            "subcategory":"Lawyer & Legal Services",
            "type":"Services"
        }
    ],
    "sg:phone":"+1 204 985 8550",
    "sg:postcode":"R3C 0B9",
    "sg:province":"MB",
    "sg:tags":[
        "attorney"
    ],
    "wof:name":"Grafton, B",
    "wof:placetype":"venue"
},
  "geometry": {"coordinates":[-97.142746,49.893661],"type":"Point"}
}