{
  "type": "Feature",
  "properties": {
    "addr:full":"Calgary AB T2P 3P8",
    "addr:postcode":"t2p 3p8",
    "iso:country":"CA",
    "sg:city":"Calgary",
    "sg:classifiers":[
        {
            "category":"Mining & Drilling",
            "type":"Manufacturing & Wholesale Goods"
        }
    ],
    "sg:phone":"+1 403 262 4880",
    "sg:postcode":"T2P 3P8",
    "sg:province":"AB",
    "sg:tags":[
        "field",
        "oil"
    ],
    "wof:name":"Expro Group Canada Inc",
    "wof:placetype":"venue"
},
  "geometry": {"coordinates":[-114.077179,51.047016],"type":"Point"}
}