{
  "type": "Feature",
  "properties": {
    "addr:full":"455 German School Rd Paris ON N3L 3E1",
    "addr:housenumber":"455",
    "addr:postcode":"n3l 3e1",
    "addr:street":"German School Rd",
    "iso:country":"CA",
    "sg:address":"455 German School Rd",
    "sg:city":"Paris",
    "sg:classifiers":[
        {
            "category":"Manufacturing",
            "subcategory":"Pottery",
            "type":"Manufacturing & Wholesale Goods"
        }
    ],
    "sg:phone":"+1 519 442 4641",
    "sg:postcode":"N3L 3E1",
    "sg:province":"ON",
    "sg:tags":[
        "top",
        "counter",
        "bathroom"
    ],
    "wof:name":"H & M Mfg",
    "wof:placetype":"venue"
},
  "geometry": {"coordinates":[-80.31203499999999,43.219158],"type":"Point"}
}