{
  "type": "Feature",
  "properties": {
    "addr:full":"381 Rue Principale Melocheville QC J0S 1J0",
    "addr:housenumber":"381",
    "addr:postcode":"j0s 1j0",
    "addr:street":"Rue Principale",
    "iso:country":"CA",
    "sg:address":"381 Rue Principale",
    "sg:city":"Melocheville",
    "sg:classifiers":[
        {
            "category":"Wholesale",
            "subcategory":"Apparel",
            "type":"Manufacturing & Wholesale Goods"
        }
    ],
    "sg:phone":"+1 450 429 3953",
    "sg:postcode":"J0S 1J0",
    "sg:province":"QC",
    "sg:tags":[
        "equipment",
        "safety",
        "clothing"
    ],
    "wof:name":"Klondike Safety Equipment",
    "wof:placetype":"venue"
},
  "geometry": {"coordinates":[-73.94691467289999,45.3168563843],"type":"Point"}
}