{
  "type": "Feature",
  "properties": {
    "addr:full":"89 Pender St E Vancouver BC V6A 1S9",
    "addr:housenumber":"89",
    "addr:postcode":"v6a 1s9",
    "addr:street":"Pender St E",
    "iso:country":"CA",
    "sg:address":"89 Pender St E",
    "sg:city":"Vancouver",
    "sg:classifiers":[
        {
            "category":"Manufacturing",
            "subcategory":"Food",
            "type":"Manufacturing & Wholesale Goods"
        }
    ],
    "sg:phone":"+1 604 684 2770",
    "sg:postcode":"V6A 1S9",
    "sg:province":"BC",
    "sg:tags":[
        "product",
        "manufacturer"
    ],
    "wof:name":"Beijing Trading CO Ltd",
    "wof:placetype":"venue"
},
  "geometry": {"coordinates":[-123.102531,49.280571],"type":"Point"}
}