{
  "type": "Feature",
  "properties": {
    "addr:full":"167 Cornelius Pky North York ON M6L 2K8",
    "addr:housenumber":"167",
    "addr:postcode":"m6l 2k8",
    "addr:street":"Cornelius Pky",
    "iso:country":"CA",
    "sg:address":"167 Cornelius Pky",
    "sg:city":"North York",
    "sg:classifiers":[
        {
            "category":"Building & Trades",
            "subcategory":"Cleaning & Sanitation",
            "type":"Services"
        }
    ],
    "sg:phone":"+1 416 244 7747",
    "sg:postcode":"M6L 2K8",
    "sg:province":"ON",
    "sg:tags":[
        "janitor"
    ],
    "wof:name":"Vintage Landscaping",
    "wof:placetype":"venue"
},
  "geometry": {"coordinates":[-79.475075,43.71981],"type":"Point"}
}