{
  "type": "Feature",
  "properties": {
    "addr:full":"425 Jim Young Rd South River ON P0A 1X0",
    "addr:housenumber":"425",
    "addr:postcode":"p0a 1x0",
    "addr:street":"Jim Young Rd",
    "iso:country":"CA",
    "sg:address":"425 Jim Young Rd",
    "sg:city":"South River",
    "sg:classifiers":[
        {
            "category":"Travel",
            "subcategory":"Hotels & Motels",
            "type":"Entertainment"
        }
    ],
    "sg:phone":"+1 705 386 7764",
    "sg:postcode":"P0A 1X0",
    "sg:province":"ON",
    "sg:tags":[
        "breakfast",
        "accommodation",
        "bed"
    ],
    "wof:name":"Eagle Lake Bed & Breakfast",
    "wof:placetype":"venue"
},
  "geometry": {"coordinates":[-79.3818359375,45.8405189514],"type":"Point"}
}