{
  "type": "Feature",
  "properties": {
    "addr:full":"Greenfield NB E7L 3E4",
    "addr:postcode":"e7l 3e4",
    "iso:country":"CA",
    "sg:city":"Greenfield",
    "sg:classifiers":[
        {
            "category":"Retail",
            "subcategory":"Auto Repair",
            "type":"Services"
        }
    ],
    "sg:phone":"+1 506 392 5589",
    "sg:postcode":"E7L 3E4",
    "sg:province":"NB",
    "sg:tags":[
        "repairing",
        "automobile"
    ],
    "wof:name":"Carlisle Repair Shop",
    "wof:placetype":"venue"
},
  "geometry": {"coordinates":[-67.659943,46.462879],"type":"Point"}
}