{
  "type": "Feature",
  "properties": {
    "addr:full":"727 Grandview Bench Rd Salmon Arm BC V1E 2X9",
    "addr:housenumber":"727",
    "addr:postcode":"v1e 2x9",
    "addr:street":"Grandview Bench Rd",
    "iso:country":"CA",
    "sg:address":"727 Grandview Bench Rd",
    "sg:city":"Salmon Arm",
    "sg:classifiers":[
        {
            "category":"Retail",
            "subcategory":"Repair Shop",
            "type":"Services"
        }
    ],
    "sg:phone":"+1 250 832 7216",
    "sg:postcode":"V1E 2X9",
    "sg:province":"BC",
    "sg:tags":[
        "blacksmith",
        "welding"
    ],
    "wof:name":"Rupp Metalworks",
    "wof:placetype":"venue"
},
  "geometry": {"coordinates":[-119.271888733,50.7022285461],"type":"Point"}
}