{
  "type": "Feature",
  "properties": {
    "addr:full":"701 Herbert Ave Herbert SK S0H 2A0",
    "addr:housenumber":"701",
    "addr:postcode":"s0h 2a0",
    "addr:street":"Herbert Ave Herbert",
    "iso:country":"CA",
    "sg:address":"701 Herbert Ave",
    "sg:city":"Herbert",
    "sg:classifiers":[
        {
            "category":"Personal",
            "subcategory":"Beauty Salon",
            "type":"Services"
        }
    ],
    "sg:phone":"+1 306 784 7710",
    "sg:postcode":"S0H 2A0",
    "sg:province":"SK",
    "wof:name":"Kelly's Kuts & Kurls",
    "wof:placetype":"venue"
},
  "geometry": {"coordinates":[-107.219177246,50.4265098572],"type":"Point"}
}