{
  "type": "Feature",
  "properties": {
    "iso:country":"CA",
    "sg:address":"78 Dundas St E",
    "sg:city":"Toronto",
    "sg:classifiers":[
        {
            "category":"Restaurant",
            "type":"Food & Drink"
        }
    ],
    "sg:phone":"+1 416 591 2191",
    "sg:postcode":"M5B 1C9",
    "sg:province":"ON",
    "wof:name":"Subway Sandwiches & Salads",
    "wof:placetype":"venue"
},
  "geometry": {"coordinates":[-79.3781280518,43.6563873291],"type":"Point"}
}