{
  "type": "Feature",
  "properties": {
    "addr:full":"18 Garibaldi St Guelph ON N1E 5P2",
    "addr:housenumber":"18",
    "addr:postcode":"n1e 5p2",
    "addr:street":"Garibaldi St",
    "iso:country":"CA",
    "sg:address":"18 Garibaldi St",
    "sg:city":"Guelph",
    "sg:classifiers":[
        {
            "category":"Shopping",
            "subcategory":"Used Merchandise",
            "type":"Retail Goods"
        }
    ],
    "sg:phone":"+1 519 822 0704",
    "sg:postcode":"N1E 5P2",
    "sg:province":"ON",
    "sg:tags":[
        "appliance"
    ],
    "wof:name":"Al's Appliances",
    "wof:placetype":"venue"
},
  "geometry": {"coordinates":[-80.2328796387,43.5542640686],"type":"Point"}
}