{
  "type": "Feature",
  "properties": {
    "addr:full":"128 Atlantic Ave Toronto ON M6K 1X9",
    "addr:housenumber":"128",
    "addr:postcode":"m6k 1x9",
    "addr:street":"Atlantic Ave",
    "iso:country":"CA",
    "sg:address":"128 Atlantic Ave",
    "sg:city":"Toronto",
    "sg:classifiers":[
        {
            "category":"Shopping",
            "subcategory":"Computers & Home Electronics",
            "type":"Retail Goods"
        }
    ],
    "sg:phone":"+1 416 537 2611",
    "sg:postcode":"M6K 1X9",
    "sg:province":"ON",
    "sg:tags":[
        "equipment",
        "dealer"
    ],
    "wof:name":"System Builders Inc",
    "wof:placetype":"venue"
},
  "geometry": {"coordinates":[-79.4212799072,43.6396980286],"type":"Point"}
}