{
  "type": "Feature",
  "properties": {
    "iso:country":"CA",
    "sg:city":"Richmond Hill",
    "sg:classifiers":[
        {
            "category":"Professional",
            "subcategory":"Computer Services",
            "type":"Services"
        }
    ],
    "sg:phone":"+1 905 709 8061",
    "sg:postcode":"L4C 9S6",
    "sg:province":"ON",
    "sg:tags":[
        "consultant"
    ],
    "wof:name":"Xonitek Systems Ltd",
    "wof:placetype":"venue"
},
  "geometry": {"coordinates":[-79.431923,43.847813],"type":"Point"}
}