{
  "type": "Feature",
  "properties": {
    "addr:full":"Penticton BC V2A 5E9",
    "addr:postcode":"v2a 5e9",
    "iso:country":"CA",
    "sg:city":"Penticton",
    "sg:classifiers":[
        {
            "category":"Restaurant",
            "type":"Food & Drink"
        }
    ],
    "sg:phone":"+1 250 492 7466",
    "sg:postcode":"V2A 5E9",
    "sg:province":"BC",
    "wof:name":"Wendy's",
    "wof:placetype":"venue"
},
  "geometry": {"coordinates":[-119.586494446,49.4849815369],"type":"Point"}
}