{
  "type": "Feature",
  "properties": {
    "addr:full":"596 Arvin Ave Stoney Creek ON L8E 5P1",
    "addr:housenumber":"596",
    "addr:postcode":"l8e 5p1",
    "addr:street":"Arvin Ave",
    "iso:country":"CA",
    "sg:address":"596 Arvin Ave",
    "sg:city":"Stoney Creek",
    "sg:classifiers":[
        {
            "category":"Manufacturing",
            "subcategory":"Tools & Machinery",
            "type":"Manufacturing & Wholesale Goods"
        }
    ],
    "sg:phone":"+1 905 643 0101",
    "sg:postcode":"L8E 5P1",
    "sg:province":"ON",
    "sg:tags":[
        "machine",
        "shop"
    ],
    "wof:name":"Bsb Mfg Ltd",
    "wof:placetype":"venue"
},
  "geometry": {"coordinates":[-79.702011,43.226082],"type":"Point"}
}