{
  "type": "Feature",
  "properties": {
    "addr:full":"57 Rte 125 Saint-Esprit QC J0K 2L0",
    "addr:housenumber":"57",
    "addr:postcode":"j0k 2l0",
    "addr:street":"Rte 125",
    "iso:country":"CA",
    "sg:address":"57 Rte 125",
    "sg:city":"Saint-Esprit",
    "sg:classifiers":[
        {
            "category":"Restaurant",
            "type":"Food & Drink"
        }
    ],
    "sg:phone":"+1 450 839 6271",
    "sg:postcode":"J0K 2L0",
    "sg:province":"QC",
    "sg:tags":[
        "lounge",
        "cocktail"
    ],
    "wof:name":"Scoop Resto Bar",
    "wof:placetype":"venue"
},
  "geometry": {"coordinates":[-73.68169399999999,45.915012],"type":"Point"}
}