{
  "type": "Feature",
  "properties": {
    "addr:full":"119 5th Ave E Prince Rupert BC V8J 1R4",
    "addr:housenumber":"119",
    "addr:postcode":"v8j 1r4",
    "addr:street":"5Th Ave E",
    "iso:country":"CA",
    "sg:address":"119 5th Ave E",
    "sg:city":"Prince Rupert",
    "sg:classifiers":[
        {
            "category":"Education",
            "subcategory":"Dance Studio",
            "type":"Public Place"
        }
    ],
    "sg:phone":"+1 250 624 3457",
    "sg:postcode":"V8J 1R4",
    "sg:province":"BC",
    "sg:tags":[
        "organization",
        "instruction",
        "fraternal",
        "dancing"
    ],
    "wof:name":"Dance Adademy of Prince Rupert",
    "wof:placetype":"venue"
},
  "geometry": {"coordinates":[-130.31866500000001,54.314148],"type":"Point"}
}