{
  "type": "Feature",
  "properties": {
    "iso:country":"CA",
    "sg:address":"255 Midwest Rd",
    "sg:city":"Scarborough",
    "sg:classifiers":[
        {
            "category":"Wholesale",
            "subcategory":"Electrical",
            "type":"Manufacturing & Wholesale Goods"
        }
    ],
    "sg:phone":"+1 416 757 3008",
    "sg:postcode":"M1P 3A6",
    "sg:province":"ON",
    "sg:tags":[
        "equipment",
        "electric",
        "supply"
    ],
    "wof:name":"Powertrade Electric Ltd",
    "wof:placetype":"venue"
},
  "geometry": {"coordinates":[-79.2702407837,43.7587623596],"type":"Point"}
}