{
  "type": "Feature",
  "properties": {
    "addr:full":"76 Front St Emo ON P0W 1E0",
    "addr:housenumber":"76",
    "addr:postcode":"p0w 1e0",
    "addr:street":"Front St",
    "iso:country":"CA",
    "sg:address":"76 Front St",
    "sg:city":"Emo",
    "sg:classifiers":[
        {
            "category":"Shopping",
            "subcategory":"Catalog Store",
            "type":"Retail Goods"
        }
    ],
    "sg:phone":"+1 807 482 2400",
    "sg:postcode":"P0W 1E0",
    "sg:province":"ON",
    "sg:tags":[
        "mail",
        "order",
        "internet"
    ],
    "wof:name":"Sears Canada Inc",
    "wof:placetype":"venue"
},
  "geometry": {"coordinates":[-93.83599100000001,48.629345],"type":"Point"}
}