{
  "type": "Feature",
  "properties": {
    "addr:full":"Concord ON L4K 4A3",
    "addr:postcode":"l4k 4a3",
    "iso:country":"CA",
    "sg:city":"Concord",
    "sg:classifiers":[
        {
            "category":"Home & Garden",
            "subcategory":"Building Materials",
            "type":"Retail Goods"
        }
    ],
    "sg:phone":"+1 905 738 9231",
    "sg:postcode":"L4K 4A3",
    "sg:province":"ON",
    "sg:tags":[
        "type",
        "door"
    ],
    "wof:name":"Maple Overhead Garage Doors",
    "wof:placetype":"venue"
},
  "geometry": {"coordinates":[-79.49773399999999,43.815823],"type":"Point"}
}