{
  "type": "Feature",
  "properties": {
    "addr:full":"3569 Rue Principale Baker Brook NB E7A 1T8",
    "addr:housenumber":"3569",
    "addr:postcode":"e7a 1t8",
    "addr:street":"Rue Principale",
    "iso:country":"CA",
    "sg:address":"3569 Rue Principale",
    "sg:city":"Baker Brook",
    "sg:classifiers":[
        {
            "category":"Home & Garden",
            "subcategory":"Home Furnishings",
            "type":"Retail Goods"
        }
    ],
    "sg:phone":"+1 506 258 6318",
    "sg:postcode":"E7A 1T8",
    "sg:province":"NB",
    "sg:tags":[
        "equipment",
        "accessory",
        "kitchen",
        "cabinet"
    ],
    "wof:name":"Armoire DE Cuisine Real Soucy",
    "wof:placetype":"venue"
},
  "geometry": {"coordinates":[-68.50251799999999,47.303207],"type":"Point"}
}