{
  "type": "Feature",
  "properties": {
    "addr:full":"786 King St E Hamilton ON L8M 1A6",
    "addr:housenumber":"786",
    "addr:postcode":"l8m 1a6",
    "addr:street":"King St E",
    "iso:country":"CA",
    "sg:address":"786 King St E",
    "sg:city":"Hamilton",
    "sg:classifiers":[
        {
            "category":"Professional",
            "subcategory":"Engineering",
            "type":"Services"
        }
    ],
    "sg:phone":"+1 905 523 1988",
    "sg:postcode":"L8M 1A6",
    "sg:province":"ON",
    "sg:tags":[
        "engineer"
    ],
    "wof:name":"Atkinson Engineering Inc",
    "wof:placetype":"venue"
},
  "geometry": {"coordinates":[-79.8437652588,43.2513961792],"type":"Point"}
}