{
  "type": "Feature",
  "properties": {
    "iso:country":"CA",
    "sg:address":"354 King St N",
    "sg:city":"Waterloo",
    "sg:classifiers":[
        {
            "category":"Health Services",
            "subcategory":"Optometrist",
            "type":"Services"
        }
    ],
    "sg:phone":"+1 519 885 2574",
    "sg:postcode":"N2J 2Z2",
    "sg:province":"ON",
    "wof:name":"Mac Donald, Derek OD",
    "wof:placetype":"venue"
},
  "geometry": {"coordinates":[-80.525787,43.481033],"type":"Point"}
}