{
  "type": "Feature",
  "properties": {
    "addr:full":"7219 Summit Dr Canim Lake BC V0K 1J0",
    "addr:housenumber":"7219",
    "addr:postcode":"v0k 1j0",
    "addr:street":"Summit Dr Canim",
    "iso:country":"CA",
    "sg:address":"7219 Summit Dr",
    "sg:city":"Canim Lake",
    "sg:classifiers":[
        {
            "category":"Building & Trades",
            "subcategory":"Cleaning & Sanitation",
            "type":"Services"
        }
    ],
    "sg:phone":"+1 250 397 2019",
    "sg:postcode":"V0K 1J0",
    "sg:province":"BC",
    "sg:tags":[
        "janitor"
    ],
    "wof:name":"Kristal Kleaning",
    "wof:placetype":"venue"
},
  "geometry": {"coordinates":[-120.910027,51.768406],"type":"Point"}
}