{
  "type": "Feature",
  "properties": {
    "iso:country":"CA",
    "sg:city":"Edmonton",
    "sg:classifiers":[
        {
            "category":"Personal",
            "subcategory":"Barber",
            "type":"Services"
        }
    ],
    "sg:phone":"+1 780 473 0709",
    "sg:postcode":"T5E 6A9",
    "sg:province":"AB",
    "wof:name":"Dickinsfield Barber Shop",
    "wof:placetype":"venue"
},
  "geometry": {"coordinates":[-113.490372,53.546219],"type":"Point"}
}