{
  "type": "Feature",
  "properties": {
    "iso:country":"CA",
    "sg:city":"Windsor",
    "sg:classifiers":[
        {
            "category":"Shopping",
            "subcategory":"Clothing, Apparel, & Fashions",
            "type":"Retail Goods"
        }
    ],
    "sg:phone":"+1 519 250 3463",
    "sg:postcode":"N8X 3Y8",
    "sg:province":"ON",
    "sg:tags":[
        "infant",
        "wear"
    ],
    "wof:name":"Gymboree",
    "wof:placetype":"venue"
},
  "geometry": {"coordinates":[-83.0047836304,42.2739982605],"type":"Point"}
}