{
  "type": "Feature",
  "properties": {
    "addr:full":"180 Josephine St Wingham ON N0G 2W0",
    "addr:housenumber":"180",
    "addr:postcode":"n0g 2w0",
    "addr:street":"Josephine St",
    "iso:country":"CA",
    "sg:address":"180 Josephine St",
    "sg:city":"Wingham",
    "sg:classifiers":[
        {
            "category":"Shopping",
            "subcategory":"Clothing, Apparel, & Fashions",
            "type":"Retail Goods"
        }
    ],
    "sg:phone":"+1 519 357 4503",
    "sg:postcode":"N0G 2W0",
    "sg:province":"ON",
    "sg:tags":[
        "work"
    ],
    "wof:name":"Workshop",
    "wof:placetype":"venue"
},
  "geometry": {"coordinates":[-81.314117,43.885098],"type":"Point"}
}