{
  "type": "Feature",
  "properties": {
    "addr:full":"Hanna AB T0J 1P0",
    "addr:postcode":"t0j 1p0",
    "iso:country":"CA",
    "sg:city":"Hanna",
    "sg:classifiers":[
        {
            "category":"Retail",
            "subcategory":"Veterinary Services",
            "type":"Services"
        }
    ],
    "sg:phone":"+1 403 854 3463",
    "sg:postcode":"T0J 1P0",
    "sg:province":"AB",
    "sg:tags":[
        "veterinarian"
    ],
    "wof:name":"Valley Veterinary Clinic",
    "wof:placetype":"venue"
},
  "geometry": {"coordinates":[-111.920357,51.645378],"type":"Point"}
}