{
  "type": "Feature",
  "properties": {
    "addr:full":"Vancouver BC V5R 5K6",
    "addr:postcode":"v5r 5k6",
    "iso:country":"CA",
    "sg:city":"Vancouver",
    "sg:classifiers":[
        {
            "category":"Shopping",
            "subcategory":"Clothing, Apparel, & Fashions",
            "type":"Retail Goods"
        }
    ],
    "sg:phone":"+1 604 431 1838",
    "sg:postcode":"V5R 5K6",
    "sg:province":"BC",
    "sg:tags":[
        "item",
        "boutique"
    ],
    "wof:name":"Something Special",
    "wof:placetype":"venue"
},
  "geometry": {"coordinates":[-123.035293579,49.2340087891],"type":"Point"}
}