{
  "type": "Feature",
  "properties": {
    "iso:country":"CA",
    "sg:address":"4255 Rue Wellington # 900",
    "sg:city":"Verdun",
    "sg:classifiers":[
        {
            "category":"Banks & Credit Unions",
            "subcategory":"Financial Services",
            "type":"Services"
        }
    ],
    "sg:phone":"+1 514 932 4115",
    "sg:postcode":"H4G 1V9",
    "sg:province":"QC",
    "sg:tags":[
        "bankruptcy",
        "trustee"
    ],
    "wof:name":"Appel & Cie Inc",
    "wof:placetype":"venue"
},
  "geometry": {"coordinates":[-73.567375,45.461411],"type":"Point"}
}