{
  "type": "Feature",
  "properties": {
    "addr:full":"50 Kensington Ave Toronto ON M5T 2K1",
    "addr:housenumber":"50",
    "addr:postcode":"m5t 2k1",
    "addr:street":"Kensington Ave",
    "iso:country":"CA",
    "sg:address":"50 Kensington Ave",
    "sg:city":"Toronto",
    "sg:classifiers":[
        {
            "category":"Shopping",
            "subcategory":"Gifts & Souvenirs",
            "type":"Retail Goods"
        }
    ],
    "sg:phone":"+1 416 596 7612",
    "sg:postcode":"M5T 2K1",
    "sg:province":"ON",
    "sg:tags":[
        "shop"
    ],
    "wof:name":"Far East Arts CO",
    "wof:placetype":"venue"
},
  "geometry": {"coordinates":[-79.4005432129,43.6541137695],"type":"Point"}
}