{
  "type": "Feature",
  "properties": {
    "addr:full":"Hwy 17 Verner ON P0H 2M0",
    "addr:postcode":"p0h 2m0",
    "addr:street":"Hwy 17 Verner",
    "iso:country":"CA",
    "sg:address":"Hwy 17",
    "sg:city":"Verner",
    "sg:classifiers":[
        {
            "category":"Wholesale",
            "subcategory":"Construction Materials",
            "type":"Manufacturing & Wholesale Goods"
        }
    ],
    "sg:phone":"+1 705 594 2358",
    "sg:postcode":"P0H 2M0",
    "sg:province":"ON",
    "sg:tags":[
        "sand",
        "gravel"
    ],
    "wof:name":"Beauparlant Francois Trucking",
    "wof:placetype":"venue"
},
  "geometry": {"coordinates":[-80.123688,46.410355],"type":"Point"}
}