{
  "type": "Feature",
  "properties": {
    "iso:country":"CA",
    "sg:address":"47 Dawson Rd",
    "sg:city":"Ste Anne",
    "sg:classifiers":[
        {
            "category":"Wholesale",
            "subcategory":"Groceries",
            "type":"Manufacturing & Wholesale Goods"
        }
    ],
    "sg:phone":"+1 204 422 5149",
    "sg:postcode":"R5H 1B7",
    "sg:province":"MB",
    "sg:tags":[
        "confectionery",
        "candy"
    ],
    "wof:name":"Penn-Essy Distributors Ltd",
    "wof:placetype":"venue"
},
  "geometry": {"coordinates":[-96.5484466553,49.6582221985],"type":"Point"}
}