{
  "type": "Feature",
  "properties": {
    "addr:full":"1657 Barrington St # 218 Halifax NS B3J 2A1",
    "addr:housenumber":"1657",
    "addr:postcode":"ns b3j 2a1",
    "addr:street":"Barrington St # 218",
    "iso:country":"CA",
    "sg:address":"1657 Barrington St # 218",
    "sg:city":"Halifax",
    "sg:classifiers":[
        {
            "category":"Communications",
            "subcategory":"Film & Video Production",
            "type":"Services"
        }
    ],
    "sg:phone":"+1 902 429 5398",
    "sg:postcode":"B3J 2A1",
    "sg:province":"NS",
    "sg:tags":[
        "taping"
    ],
    "wof:name":"Kimberlee Mc Taggart Editing",
    "wof:placetype":"venue"
},
  "geometry": {"coordinates":[-63.573654,44.646854],"type":"Point"}
}