{
  "type": "Feature",
  "properties": {
    "addr:full":"67 2nd St NE # 200 Altona MB R0G 0B0",
    "addr:housenumber":"67",
    "addr:postcode":"r0g 0b0",
    "addr:street":"2Nd St Ne # 200",
    "iso:country":"CA",
    "sg:address":"67 2nd St NE # 200",
    "sg:city":"Altona",
    "sg:classifiers":[
        {
            "category":"Professional",
            "subcategory":"Accounting & Tax Preparation",
            "type":"Services"
        }
    ],
    "sg:phone":"+1 204 324 1313",
    "sg:postcode":"R0G 0B0",
    "sg:province":"MB",
    "sg:tags":[
        "consultant"
    ],
    "wof:name":"Wayne Irvine Tax Svc",
    "wof:placetype":"venue"
},
  "geometry": {"coordinates":[-97.55549600000001,49.107059],"type":"Point"}
}