{
  "type": "Feature",
  "properties": {
    "addr:full":"1565 Hillside Dr London ON N6G 4M6",
    "addr:housenumber":"1565",
    "addr:postcode":"n6g 4m6",
    "addr:street":"Hillside Dr",
    "iso:country":"CA",
    "sg:address":"1565 Hillside Dr",
    "sg:city":"London",
    "sg:classifiers":[
        {
            "category":"Wholesale",
            "subcategory":"Electrical",
            "type":"Manufacturing & Wholesale Goods"
        }
    ],
    "sg:phone":"+1 416 236 4898",
    "sg:postcode":"N6G 4M6",
    "sg:province":"ON",
    "sg:tags":[
        "sound",
        "equipment",
        "system"
    ],
    "wof:name":"Supportive Hearing Systems Inc",
    "wof:placetype":"venue"
},
  "geometry": {"coordinates":[-81.28385900000001,43.01889],"type":"Point"}
}