{
  "type": "Feature",
  "properties": {
    "addr:full":"Abbotsford BC V2T 4C6",
    "addr:postcode":"v2t 4c6",
    "iso:country":"CA",
    "sg:city":"Abbotsford",
    "sg:classifiers":[
        {
            "category":"Retail",
            "subcategory":"Auto Repair",
            "type":"Services"
        }
    ],
    "sg:phone":"+1 604 850 7406",
    "sg:postcode":"V2T 4C6",
    "sg:province":"BC",
    "sg:tags":[
        "repairing",
        "automobile"
    ],
    "wof:name":"Esau Auto Repairs",
    "wof:placetype":"venue"
},
  "geometry": {"coordinates":[-122.34909057599999,49.0458183289],"type":"Point"}
}