{
  "type": "Feature",
  "properties": {
    "addr:full":"Courtenay BC V9N 9V7",
    "addr:postcode":"v9n 9v7",
    "iso:country":"CA",
    "sg:city":"Courtenay",
    "sg:classifiers":[
        {
            "category":"Shopping",
            "type":"Retail Goods"
        }
    ],
    "sg:phone":"+1 250 338 2686",
    "sg:postcode":"V9N 9V7",
    "sg:province":"BC",
    "sg:tags":[
        "equipment",
        "beer",
        "supply"
    ],
    "wof:name":"Wine Cottage",
    "wof:placetype":"venue"
},
  "geometry": {"coordinates":[-124.982788,49.702011],"type":"Point"}
}