{
  "type": "Feature",
  "properties": {
    "addr:full":"1201 Britannia Rd W Mississauga ON L5V 1N2",
    "addr:housenumber":"1201",
    "addr:postcode":"l5v 1n2",
    "addr:street":"Britannia Rd W",
    "iso:country":"CA",
    "sg:address":"1201 Britannia Rd W",
    "sg:city":"Mississauga",
    "sg:classifiers":[
        {
            "category":"Health Services",
            "subcategory":"Doctor",
            "type":"Services"
        }
    ],
    "sg:phone":"+1 905 542 9009",
    "sg:postcode":"L5V 1N2",
    "sg:province":"ON",
    "sg:tags":[
        "clinic",
        "rehabilitation"
    ],
    "wof:name":"Act Health Group Corp",
    "wof:placetype":"venue"
},
  "geometry": {"coordinates":[-79.7058258057,43.6033325195],"type":"Point"}
}