{
  "type": "Feature",
  "properties": {
    "addr:full":"1531 Grafton St Halifax NS B3J 2B9",
    "addr:housenumber":"1531",
    "addr:postcode":"ns b3j 2b9",
    "addr:street":"Grafton St",
    "iso:country":"CA",
    "sg:address":"1531 Grafton St",
    "sg:city":"Halifax",
    "sg:classifiers":[
        {
            "category":"Organizations",
            "subcategory":"Religious Organization",
            "type":"Services"
        }
    ],
    "sg:phone":"+1 902 422 8428",
    "sg:postcode":"B3J 2B9",
    "sg:province":"NS",
    "sg:tags":[
        "church"
    ],
    "wof:name":"Development & Peace",
    "wof:placetype":"venue"
},
  "geometry": {"coordinates":[-63.573982,44.644463],"type":"Point"}
}