{
  "type": "Feature",
  "properties": {
    "addr:full":"81 Batteaux Rd Collingwood ON L9Y 3Z1",
    "addr:housenumber":"81",
    "addr:postcode":"l9y 3z1",
    "addr:street":"Batteaux Rd",
    "iso:country":"CA",
    "sg:address":"81 Batteaux Rd",
    "sg:city":"Collingwood",
    "sg:classifiers":[
        {
            "category":"Education",
            "subcategory":"School",
            "type":"Public Place"
        }
    ],
    "sg:phone":"+1 705 445 1827",
    "sg:postcode":"L9Y 3Z1",
    "sg:province":"ON",
    "wof:name":"Nottawa Elementary School",
    "wof:placetype":"venue"
},
  "geometry": {"coordinates":[-80.21682699999999,44.499889],"type":"Point"}
}