{
  "type": "Feature",
  "properties": {
    "addr:full":"43 Loring Cres Stoney Creek ON L8E 3X2",
    "addr:housenumber":"43",
    "addr:postcode":"l8e 3x2",
    "addr:street":"Loring Cres",
    "iso:country":"CA",
    "sg:address":"43 Loring Cres",
    "sg:city":"Stoney Creek",
    "sg:classifiers":[
        {
            "category":"Building & Trades",
            "subcategory":"Construction",
            "type":"Services"
        }
    ],
    "sg:phone":"+1 905 574 7711",
    "sg:postcode":"L8E 3X2",
    "sg:province":"ON",
    "sg:tags":[
        "general",
        "contractor"
    ],
    "wof:name":"D Chase Contracting Inc",
    "wof:placetype":"venue"
},
  "geometry": {"coordinates":[-79.716881,43.22216],"type":"Point"}
}