{
  "type": "Feature",
  "properties": {
    "addr:full":"15660 Boul Des Acadiens Becancour QC G9H 1K8",
    "addr:housenumber":"15660",
    "addr:postcode":"g9h 1k8",
    "addr:street":"Boul Des Acadiens Becancour",
    "iso:country":"CA",
    "sg:address":"15660 Boul Des Acadiens",
    "sg:city":"Becancour",
    "sg:classifiers":[
        {
            "category":"Building & Trades",
            "subcategory":"Construction",
            "type":"Services"
        }
    ],
    "sg:phone":"+1 819 233 2876",
    "sg:postcode":"G9H 1K8",
    "sg:province":"QC",
    "sg:tags":[
        "excavating",
        "contractor"
    ],
    "wof:name":"Excavation Pierre Bergeron",
    "wof:placetype":"venue"
},
  "geometry": {"coordinates":[-72.495392,46.280121],"type":"Point"}
}