{
  "type": "Feature",
  "properties": {
    "iso:country":"CA",
    "sg:address":"1000 Ch DE LA Montagne-Coupee",
    "sg:city":"Saint-Jean-DE-Matha",
    "sg:classifiers":[
        {
            "category":"Travel",
            "subcategory":"Hotels & Motels",
            "type":"Entertainment"
        }
    ],
    "sg:phone":"+1 450 886 3891",
    "sg:postcode":"J0K 2S0",
    "sg:province":"QC",
    "wof:name":"Auberge DE LA Montagne Coupee",
    "wof:placetype":"venue"
},
  "geometry": {"coordinates":[-73.5015487671,46.1975440979],"type":"Point"}
}