{
  "type": "Feature",
  "properties": {
    "addr:full":"12417 67 St NW Edmonton AB T5B 1N2",
    "addr:housenumber":"12417",
    "addr:postcode":"t5b 1n2",
    "addr:street":"67 St Nw",
    "iso:country":"CA",
    "sg:address":"12417 67 St NW",
    "sg:city":"Edmonton",
    "sg:classifiers":[
        {
            "category":"Building & Trades",
            "subcategory":"Construction",
            "type":"Services"
        }
    ],
    "sg:phone":"+1 780 471 2357",
    "sg:postcode":"T5B 1N2",
    "sg:province":"AB",
    "sg:tags":[
        "fabricator",
        "work",
        "metal",
        "sheet",
        "contractor"
    ],
    "wof:name":"Mar-Ko Metal Products Inc",
    "wof:placetype":"venue"
},
  "geometry": {"coordinates":[-113.444351196,53.5801239014],"type":"Point"}
}