{
  "type": "Feature",
  "properties": {
    "iso:country":"CA",
    "sg:address":"568 Upper Wellington St",
    "sg:city":"Hamilton",
    "sg:classifiers":[
        {
            "category":"Retail",
            "subcategory":"Auto Repair",
            "type":"Services"
        }
    ],
    "sg:phone":"+1 905 383 2432",
    "sg:postcode":"L9A 3P9",
    "sg:province":"ON",
    "sg:tags":[
        "repairing",
        "automobile"
    ],
    "wof:name":"Whitwell Brothers Svc Ctr",
    "wof:placetype":"venue"
},
  "geometry": {"coordinates":[-79.86675262449999,43.238910675],"type":"Point"}
}