{
  "type": "Feature",
  "properties": {
    "addr:full":"4021 Melfort Cres Mississauga ON L5L 4K9",
    "addr:housenumber":"4021",
    "addr:postcode":"l5l 4k9",
    "addr:street":"Melfort Cres",
    "iso:country":"CA",
    "sg:address":"4021 Melfort Cres",
    "sg:city":"Mississauga",
    "sg:classifiers":[
        {
            "category":"Wholesale",
            "subcategory":"Machinery & Supplies",
            "type":"Manufacturing & Wholesale Goods"
        }
    ],
    "sg:phone":"+1 519 925 1944",
    "sg:postcode":"L5L 4K9",
    "sg:province":"ON",
    "sg:tags":[
        "equipment",
        "laundry"
    ],
    "wof:name":"Dane's Washer Svc",
    "wof:placetype":"venue"
},
  "geometry": {"coordinates":[-79.706215,43.531857],"type":"Point"}
}