{
  "type": "Feature",
  "properties": {
    "addr:full":"79 Talbot St W Aylmer ON N5H 1J6",
    "addr:housenumber":"79",
    "addr:postcode":"n5h 1j6",
    "addr:street":"Talbot St W",
    "iso:country":"CA",
    "sg:address":"79 Talbot St W",
    "sg:city":"Aylmer",
    "sg:classifiers":[
        {
            "category":"Shopping",
            "subcategory":"Catalog Store",
            "type":"Retail Goods"
        }
    ],
    "sg:phone":"+1 519 773 5372",
    "sg:postcode":"N5H 1J6",
    "sg:province":"ON",
    "sg:tags":[
        "mail",
        "order",
        "internet"
    ],
    "wof:name":"Sears Canada Inc",
    "wof:placetype":"venue"
},
  "geometry": {"coordinates":[-80.984664917,42.7731895447],"type":"Point"}
}