{
  "type": "Feature",
  "properties": {
    "addr:full":"4424 49 St Wetaskiwin AB T9A 1G9",
    "addr:housenumber":"4424",
    "addr:postcode":"t9a 1g9",
    "addr:street":"49 St",
    "iso:country":"CA",
    "sg:address":"4424 49 St",
    "sg:city":"Wetaskiwin",
    "sg:classifiers":[
        {
            "category":"Retail",
            "subcategory":"Auto Repair",
            "type":"Services"
        }
    ],
    "sg:phone":"+1 780 352 0495",
    "sg:postcode":"T9A 1G9",
    "sg:province":"AB",
    "sg:tags":[
        "repairing",
        "automobile",
        "muffler",
        "system",
        "exhaust"
    ],
    "wof:name":"Wizzard Custom Exhaust",
    "wof:placetype":"venue"
},
  "geometry": {"coordinates":[-113.374062,52.964352],"type":"Point"}
}