{
  "type": "Feature",
  "properties": {
    "addr:full":"277 Rue DE Liege E Montreal QC H2P 1J3",
    "addr:housenumber":"277",
    "addr:postcode":"h2p 1j3",
    "addr:street":"Rue De Liege E",
    "iso:country":"CA",
    "sg:address":"277 Rue DE Liege E",
    "sg:city":"Montreal",
    "sg:classifiers":[
        {
            "category":"Professional",
            "subcategory":"Research",
            "type":"Services"
        }
    ],
    "sg:phone":"+1 514 385 9081",
    "sg:postcode":"H2P 1J3",
    "sg:province":"QC",
    "sg:tags":[
        "environmental",
        "ecological"
    ],
    "wof:name":"Comite Des Citoyens D'Octave",
    "wof:placetype":"venue"
},
  "geometry": {"coordinates":[-73.636375,45.542992],"type":"Point"}
}