{
  "type": "Feature",
  "properties": {
    "addr:full":"3831 48 Ave Camrose AB T4V 2Y9",
    "addr:housenumber":"3831",
    "addr:postcode":"t4v 2y9",
    "addr:street":"48 Ave",
    "iso:country":"CA",
    "sg:address":"3831 48 Ave",
    "sg:city":"Camrose",
    "sg:classifiers":[
        {
            "category":"Autos & Motor Vehicles",
            "subcategory":"Auto Supplies",
            "type":"Retail Goods"
        }
    ],
    "sg:phone":"+1 780 672 5531",
    "sg:postcode":"T4V 2Y9",
    "sg:province":"AB",
    "sg:tags":[
        "automobile",
        "parts"
    ],
    "wof:name":"Strebs Auto & Ind Supply",
    "wof:placetype":"venue"
},
  "geometry": {"coordinates":[-112.804832,53.017803],"type":"Point"}
}