{
  "type": "Feature",
  "properties": {
    "addr:full":"34 Lee Ave North Bay ON P1A 2J6",
    "addr:housenumber":"34",
    "addr:postcode":"p1a 2j6",
    "addr:street":"Lee Ave",
    "iso:country":"CA",
    "sg:address":"34 Lee Ave",
    "sg:city":"North Bay",
    "sg:classifiers":[
        {
            "category":"Wholesale",
            "subcategory":"Durable Goods & Equipment",
            "type":"Manufacturing & Wholesale Goods"
        }
    ],
    "sg:phone":"+1 705 474 1216",
    "sg:postcode":"P1A 2J6",
    "sg:province":"ON",
    "sg:tags":[
        "representative",
        "manufacturer"
    ],
    "wof:name":"G & S Ind Sales Ltd",
    "wof:placetype":"venue"
},
  "geometry": {"coordinates":[-79.453712,46.295574],"type":"Point"}
}