{
  "type": "Feature",
  "properties": {
    "iso:country":"CA",
    "sg:address":"66 Norfinch Dr",
    "sg:city":"North York",
    "sg:classifiers":[
        {
            "category":"Travel",
            "subcategory":"Hotels & Motels",
            "type":"Entertainment"
        }
    ],
    "sg:phone":"+1 416 736 4700",
    "sg:postcode":"M3N 1X1",
    "sg:province":"ON",
    "wof:name":"Comfort Inn",
    "wof:placetype":"venue"
},
  "geometry": {"coordinates":[-79.5285415649,43.7575912476],"type":"Point"}
}