{
  "type": "Feature",
  "properties": {
    "addr:full":"333 Elgin St N Cambridge ON N1R 7H9",
    "addr:housenumber":"333",
    "addr:postcode":"n1r 7h9",
    "addr:street":"Elgin St N",
    "iso:country":"CA",
    "sg:address":"333 Elgin St N",
    "sg:city":"Cambridge",
    "sg:classifiers":[
        {
            "category":"Retail",
            "subcategory":"Auto Repair",
            "type":"Services"
        }
    ],
    "sg:phone":"+1 519 740 8787",
    "sg:postcode":"N1R 7H9",
    "sg:province":"ON",
    "sg:tags":[
        "body",
        "automobile",
        "painting"
    ],
    "wof:name":"Sera Motors",
    "wof:placetype":"venue"
},
  "geometry": {"coordinates":[-80.305733,43.377453],"type":"Point"}
}