{
  "type": "Feature",
  "properties": {
    "iso:country":"CA",
    "sg:city":"Saint-Hubert",
    "sg:classifiers":[
        {
            "category":"Shopping",
            "subcategory":"Jewelry",
            "type":"Retail Goods"
        }
    ],
    "sg:phone":"+1 450 443 4090",
    "sg:postcode":"J3Y 8Y5",
    "sg:province":"QC",
    "sg:tags":[
        "clocks"
    ],
    "wof:name":"Paul Hofer Inc",
    "wof:placetype":"venue"
},
  "geometry": {"coordinates":[-73.3907623291,45.4785766602],"type":"Point"}
}