{
  "type": "Feature",
  "properties": {
    "iso:country":"CA",
    "sg:address":"7622 Keele St",
    "sg:city":"Concord",
    "sg:classifiers":[
        {
            "category":"Wholesale",
            "subcategory":"Drugs",
            "type":"Manufacturing & Wholesale Goods"
        }
    ],
    "sg:phone":"+1 905 660 7622",
    "sg:postcode":"L4K 2R5",
    "sg:province":"ON",
    "sg:tags":[
        "pharmaceutical",
        "product"
    ],
    "wof:name":"Kohl & Frisch Ltd",
    "wof:placetype":"venue"
},
  "geometry": {"coordinates":[-79.498848,43.797115],"type":"Point"}
}