{
  "type": "Feature",
  "properties": {
    "addr:full":"Oakville ON L6J 7V7",
    "addr:postcode":"l6j 7v7",
    "iso:country":"CA",
    "sg:city":"Oakville",
    "sg:classifiers":[
        {
            "category":"Health Services",
            "subcategory":"Doctor",
            "type":"Services"
        }
    ],
    "sg:phone":"+1 905 337 9606",
    "sg:postcode":"L6J 7V7",
    "sg:province":"ON",
    "sg:tags":[
        "clinic",
        "dentist"
    ],
    "wof:name":"Family Dental Clinic",
    "wof:placetype":"venue"
},
  "geometry": {"coordinates":[-79.65130600000001,43.488518],"type":"Point"}
}