{
  "type": "Feature",
  "properties": {
    "addr:full":"137 Woodward Ave London ON N6H 2H1",
    "addr:housenumber":"137",
    "addr:postcode":"n6h 2h1",
    "addr:street":"Woodward Ave",
    "iso:country":"CA",
    "sg:address":"137 Woodward Ave",
    "sg:city":"London",
    "sg:classifiers":[
        {
            "category":"Social Services",
            "type":"Services"
        }
    ],
    "sg:phone":"+1 519 858 3017",
    "sg:postcode":"N6H 2H1",
    "sg:province":"ON",
    "sg:tags":[
        "counselor",
        "marriage",
        "family"
    ],
    "wof:name":"Wilkinson, Claire",
    "wof:placetype":"venue"
},
  "geometry": {"coordinates":[-81.270203,42.987923],"type":"Point"}
}