{
  "type": "Feature",
  "properties": {
    "addr:full":"132 Mississaga St E #A Orillia ON L3V 1V7",
    "addr:housenumber":"132",
    "addr:postcode":"l3v 1v7",
    "addr:street":"Mississaga St E # A",
    "iso:country":"CA",
    "sg:address":"132 Mississaga St E #A",
    "sg:city":"Orillia",
    "sg:classifiers":[
        {
            "category":"Shopping",
            "subcategory":"Clothing, Apparel, & Fashions",
            "type":"Retail Goods"
        }
    ],
    "sg:phone":"+1 705 325 1052",
    "sg:postcode":"L3V 1V7",
    "sg:province":"ON",
    "wof:name":"Just Elaine's",
    "wof:placetype":"venue"
},
  "geometry": {"coordinates":[-79.4165878296,44.6096992493],"type":"Point"}
}