{
  "type": "Feature",
  "properties": {
    "iso:country":"CA",
    "sg:address":"262 338 Rte",
    "sg:city":"Les Coteaux",
    "sg:classifiers":[
        {
            "category":"Health Services",
            "subcategory":"Doctor",
            "type":"Services"
        }
    ],
    "sg:phone":"+1 450 267 9008",
    "sg:postcode":"J7X 1A2",
    "sg:province":"QC",
    "sg:tags":[
        "clinic"
    ],
    "wof:name":"Centre Dentaire Menard Daoust",
    "wof:placetype":"venue"
},
  "geometry": {"coordinates":[-74.2141799927,45.2578811646],"type":"Point"}
}