{
  "type": "Feature",
  "properties": {
    "addr:full":"1001 1 St SE High River AB T1V 1E6",
    "addr:housenumber":"1001 1",
    "addr:postcode":"t1v 1e6",
    "addr:street":"St Se",
    "iso:country":"CA",
    "sg:address":"1001 1 St SE",
    "sg:city":"High River",
    "sg:classifiers":[
        {
            "category":"Retail",
            "subcategory":"Auto Repair",
            "type":"Services"
        }
    ],
    "sg:phone":"+1 403 652 1164",
    "sg:postcode":"T1V 1E6",
    "sg:province":"AB",
    "sg:tags":[
        "repairing",
        "automobile"
    ],
    "wof:name":"Allister's Auto Svc Ltd",
    "wof:placetype":"venue"
},
  "geometry": {"coordinates":[-113.86854599999999,50.573647],"type":"Point"}
}