{
  "type": "Feature",
  "properties": {
    "addr:full":"19501 Av Clark-Graham Baie-D'Urfe QC H9X 3T1",
    "addr:housenumber":"19501",
    "addr:postcode":"h9x 3t1",
    "addr:street":"Av Clark-Graham Baie-D'Urfe",
    "iso:country":"CA",
    "sg:address":"19501 Av Clark-Graham",
    "sg:city":"Baie-D'Urfe",
    "sg:classifiers":[
        {
            "category":"Freight",
            "type":"Transportation"
        }
    ],
    "sg:phone":"+1 514 457 2550",
    "sg:postcode":"H9X 3T1",
    "sg:province":"QC",
    "sg:tags":[
        "trucking"
    ],
    "wof:name":"Camionnage Cp Inc",
    "wof:placetype":"venue"
},
  "geometry": {"coordinates":[-71.495659,46.980713],"type":"Point"}
}