{
  "type": "Feature",
  "properties": {
    "iso:country":"CA",
    "sg:city":"Surrey",
    "sg:classifiers":[
        {
            "category":"Banks & Credit Unions",
            "subcategory":"Bank",
            "type":"Services"
        }
    ],
    "sg:phone":"+1 604 581 8866",
    "sg:postcode":"V3R 1M7",
    "sg:province":"BC",
    "sg:tags":[
        "loan",
        "real estate"
    ],
    "wof:name":"Pro-Mor Investment Svc Ltd",
    "wof:placetype":"venue"
},
  "geometry": {"coordinates":[-122.80872345,49.1913604736],"type":"Point"}
}