{
  "type": "Feature",
  "properties": {
    "addr:full":"3769 Boul Harvey Jonquiere QC G7X 3A4",
    "addr:housenumber":"3769",
    "addr:postcode":"g7x 3a4",
    "addr:street":"Boul Harvey",
    "iso:country":"CA",
    "sg:address":"3769 Boul Harvey",
    "sg:city":"Jonquiere",
    "sg:classifiers":[
        {
            "category":"Insurance",
            "subcategory":"Insurance Agent",
            "type":"Services"
        }
    ],
    "sg:phone":"+1 418 547 5000",
    "sg:postcode":"G7X 3A4",
    "sg:province":"QC",
    "wof:name":"Assurances 5000 Inc",
    "wof:placetype":"venue"
},
  "geometry": {"coordinates":[-71.24334,48.412796],"type":"Point"}
}