{
  "type": "Feature",
  "properties": {
    "addr:full":"135 Hartzell Rd St Catharines ON L2P 1N6",
    "addr:housenumber":"135",
    "addr:postcode":"l2p 1n6",
    "addr:street":"Hartzell Rd",
    "iso:country":"CA",
    "sg:address":"135 Hartzell Rd",
    "sg:city":"St Catharines",
    "sg:classifiers":[
        {
            "category":"Retail",
            "subcategory":"Auto Repair",
            "type":"Services"
        }
    ],
    "sg:phone":"+1 905 688 6011",
    "sg:postcode":"L2P 1N6",
    "sg:province":"ON",
    "sg:tags":[
        "repairing",
        "automobile"
    ],
    "wof:name":"Midas Auto Svc Experts",
    "wof:placetype":"venue"
},
  "geometry": {"coordinates":[-79.214455,43.150578],"type":"Point"}
}