{
  "type": "Feature",
  "properties": {
    "addr:full":"41 Main St Saint John NB E2K 1G9",
    "addr:housenumber":"41",
    "addr:postcode":"e2k 1g9",
    "addr:street":"Main St",
    "iso:country":"CA",
    "sg:address":"41 Main St",
    "sg:city":"Saint John",
    "sg:classifiers":[
        {
            "category":"Wholesale",
            "subcategory":"Hardware",
            "type":"Manufacturing & Wholesale Goods"
        }
    ],
    "sg:phone":"+1 506 634 7577",
    "sg:postcode":"E2K 1G9",
    "sg:province":"NB",
    "sg:tags":[
        "contractor"
    ],
    "wof:name":"Standard Machinery & Equip Ltd",
    "wof:placetype":"venue"
},
  "geometry": {"coordinates":[-66.087135,45.274899],"type":"Point"}
}