{
  "type": "Feature",
  "properties": {
    "addr:full":"308 Station Rd Shoal Lake MB R0J 1Z0",
    "addr:housenumber":"308",
    "addr:postcode":"r0j 1z0",
    "addr:street":"Station Rd",
    "iso:country":"CA",
    "sg:address":"308 Station Rd",
    "sg:city":"Shoal Lake",
    "sg:classifiers":[
        {
            "category":"Home & Garden",
            "subcategory":"Hardware",
            "type":"Retail Goods"
        }
    ],
    "sg:phone":"+1 204 759 3308",
    "sg:postcode":"R0J 1Z0",
    "sg:province":"MB",
    "wof:name":"True Value Hardware",
    "wof:placetype":"venue"
},
  "geometry": {"coordinates":[-100.590721,50.43692],"type":"Point"}
}