{
  "type": "Feature",
  "properties": {
    "addr:full":"2093 Rue Bellefeuille Trois-Rivieres QC G9A 3Y7",
    "addr:housenumber":"2093",
    "addr:postcode":"g9a 3y7",
    "addr:street":"Rue Bellefeuille Trois-Rivieres",
    "iso:country":"CA",
    "sg:address":"2093 Rue Bellefeuille",
    "sg:city":"Trois-Rivieres",
    "sg:classifiers":[
        {
            "category":"Home & Garden",
            "subcategory":"Building Materials",
            "type":"Retail Goods"
        }
    ],
    "sg:phone":"+1 819 374 4604",
    "sg:postcode":"G9A 3Y7",
    "sg:province":"QC",
    "sg:tags":[
        "lumber"
    ],
    "wof:name":"Leopold Duplessis Ltee",
    "wof:placetype":"venue"
},
  "geometry": {"coordinates":[-72.55229199999999,46.338287],"type":"Point"}
}