{
  "type": "Feature",
  "properties": {
    "addr:full":"238 Rue Racine Loretteville QC G2B 1E6",
    "addr:housenumber":"238",
    "addr:postcode":"g2b 1e6",
    "addr:street":"Rue Racine",
    "iso:country":"CA",
    "sg:address":"238 Rue Racine",
    "sg:city":"Loretteville",
    "sg:classifiers":[
        {
            "category":"Professional",
            "subcategory":"Accounting & Tax Preparation",
            "type":"Services"
        }
    ],
    "sg:phone":"+1 418 847 3638",
    "sg:postcode":"G2B 1E6",
    "sg:province":"QC",
    "sg:tags":[
        "accountant"
    ],
    "wof:name":"Centre DE Comptabilite Info",
    "wof:placetype":"venue"
},
  "geometry": {"coordinates":[-71.35881000000001,46.852329],"type":"Point"}
}