{
  "type": "Feature",
  "properties": {
    "addr:full":"1650 1E Av Quebec QC G1L 3L6",
    "addr:housenumber":"1650",
    "addr:postcode":"g1l 3l6",
    "addr:street":"1E Av",
    "iso:country":"CA",
    "sg:address":"1650 1E Av",
    "sg:city":"Quebec",
    "sg:classifiers":[
        {
            "category":"Restaurant",
            "type":"Food & Drink"
        }
    ],
    "sg:phone":"+1 418 522 6012",
    "sg:postcode":"G1L 3L6",
    "sg:province":"QC",
    "wof:name":"Cafe Cam Ranh",
    "wof:placetype":"venue"
},
  "geometry": {"coordinates":[-71.23642700000001,46.829208],"type":"Point"}
}