{
  "type": "Feature",
  "properties": {
    "addr:full":"2850 5E Av Shawinigan-Sud QC G9P 1R2",
    "addr:housenumber":"2850",
    "addr:postcode":"g9p 1r2",
    "addr:street":"5E Av Shawinigan-Sud",
    "iso:country":"CA",
    "sg:address":"2850 5E Av",
    "sg:city":"Shawinigan-Sud",
    "sg:classifiers":[
        {
            "category":"Health Services",
            "subcategory":"Nursing And Care Facility",
            "type":"Services"
        }
    ],
    "sg:phone":"+1 819 537 3558",
    "sg:postcode":"G9P 1R2",
    "sg:province":"QC",
    "sg:tags":[
        "home",
        "retirement",
        "community"
    ],
    "wof:name":"Residence Du Boise Ensoleille",
    "wof:placetype":"venue"
},
  "geometry": {"coordinates":[-72.740784,46.516651],"type":"Point"}
}