{
  "type": "Feature",
  "properties": {
    "iso:country":"CA",
    "sg:address":"280 Boul Pie-Xii",
    "sg:city":"Saint-Timothee",
    "sg:classifiers":[
        {
            "category":"Building & Trades",
            "subcategory":"Construction",
            "type":"Services"
        }
    ],
    "sg:phone":"+1 514 642 4274",
    "sg:postcode":"J6S 6P7",
    "sg:province":"QC",
    "sg:tags":[
        "excavating",
        "contractor"
    ],
    "wof:name":"Excavation Loiselle & Freres",
    "wof:placetype":"venue"
},
  "geometry": {"coordinates":[-74.03718566889999,45.2858390808],"type":"Point"}
}