{
  "type": "Feature",
  "properties": {
    "addr:full":"533 Rodney Dr North Bay ON P1A 2X4",
    "addr:housenumber":"533",
    "addr:postcode":"p1a 2x4",
    "addr:street":"Rodney Dr",
    "iso:country":"CA",
    "sg:address":"533 Rodney Dr",
    "sg:city":"North Bay",
    "sg:classifiers":[
        {
            "category":"Organizations",
            "subcategory":"Non-profit Organization",
            "type":"Services"
        }
    ],
    "sg:phone":"+1 705 472 0335",
    "sg:postcode":"P1A 2X4",
    "sg:province":"ON",
    "sg:tags":[
        "disability",
        "elevator"
    ],
    "wof:name":"Cambrian Elevator Ltd",
    "wof:placetype":"venue"
},
  "geometry": {"coordinates":[-79.4219818115,46.3194313049],"type":"Point"}
}