{
  "type": "Feature",
  "properties": {
    "addr:full":"9680 Boul Sainte-Anne Sainte-Anne-DE-Beaupre QC G0A 3C0",
    "addr:housenumber":"9680",
    "addr:postcode":"g0a 3c0",
    "addr:street":"Boul Sainte-Anne Sainte-Anne-De-Beaupre",
    "iso:country":"CA",
    "sg:address":"9680 Boul Sainte-Anne",
    "sg:city":"Sainte-Anne-DE-Beaupre",
    "sg:classifiers":[
        {
            "category":"Travel",
            "subcategory":"Hotels & Motels",
            "type":"Entertainment"
        }
    ],
    "sg:phone":"+1 418 827 2484",
    "sg:postcode":"G0A 3C0",
    "sg:province":"QC",
    "wof:name":"Motel Des Berges",
    "wof:placetype":"venue"
},
  "geometry": {"coordinates":[-70.888496,47.04887],"type":"Point"}
}