{
  "type": "Feature",
  "properties": {
    "addr:full":"Orono ON L0B 1M0",
    "addr:postcode":"l0b 1m0",
    "iso:country":"CA",
    "sg:city":"Orono",
    "sg:classifiers":[
        {
            "category":"Recreation",
            "subcategory":"Marina",
            "type":"Entertainment"
        }
    ],
    "sg:phone":"+1 905 983 3474",
    "sg:postcode":"L0B 1M0",
    "sg:province":"ON",
    "sg:tags":[
        "dealer",
        "boat",
        "sales"
    ],
    "wof:name":"Boatland Canada",
    "wof:placetype":"venue"
},
  "geometry": {"coordinates":[-78.61648599999999,43.97723],"type":"Point"}
}