{
  "type": "Feature",
  "properties": {
    "iso:country":"CA",
    "sg:address":"60 Mcnaughton Ave",
    "sg:city":"Wallaceburg",
    "sg:classifiers":[
        {
            "category":"Real Estate",
            "subcategory":"Real Estate Operator",
            "type":"Services"
        }
    ],
    "sg:phone":"+1 519 628 5411",
    "sg:postcode":"N8A 1R9",
    "sg:province":"ON",
    "sg:tags":[
        "mall",
        "shopping",
        "center"
    ],
    "wof:name":"Wallaceburg County Fair Mall",
    "wof:placetype":"venue"
},
  "geometry": {"coordinates":[-82.3839416504,42.5865287781],"type":"Point"}
}