{
  "type": "Feature",
  "properties": {
    "addr:full":"3555 Boul Harvey Jonquiere QC G7X 3B7",
    "addr:housenumber":"3555",
    "addr:postcode":"g7x 3b7",
    "addr:street":"Boul Harvey",
    "iso:country":"CA",
    "sg:address":"3555 Boul Harvey",
    "sg:city":"Jonquiere",
    "sg:classifiers":[
        {
            "category":"Insurance",
            "subcategory":"Insurance Agent",
            "type":"Services"
        }
    ],
    "sg:phone":"+1 418 695 5518",
    "sg:postcode":"G7X 3B7",
    "sg:province":"QC",
    "wof:name":"Allstate Du Canada CO",
    "wof:placetype":"venue"
},
  "geometry": {"coordinates":[-71.229973,48.41275],"type":"Point"}
}