{
  "type": "Feature",
  "properties": {
    "addr:full":"North Saanich BC V8L 5X8",
    "addr:postcode":"v8l 5x8",
    "iso:country":"CA",
    "sg:city":"North Saanich",
    "sg:classifiers":[
        {
            "category":"Shopping",
            "subcategory":"Clothing, Apparel, & Fashions",
            "type":"Retail Goods"
        }
    ],
    "sg:phone":"+1 250 655 8239",
    "sg:postcode":"V8L 5X8",
    "sg:province":"BC",
    "sg:tags":[
        "t"
    ],
    "wof:name":"Harlequin Nature Graphics Ltd",
    "wof:placetype":"venue"
},
  "geometry": {"coordinates":[-123.41707599999999,48.656059],"type":"Point"}
}