{
  "type": "Feature",
  "properties": {
    "addr:full":"892 Rte 132 O Perce QC G0C 2L0",
    "addr:housenumber":"892",
    "addr:postcode":"g0c 2l0",
    "addr:street":"Rte 132 O Perce",
    "iso:country":"CA",
    "sg:address":"892 Rte 132 O",
    "sg:city":"Perce",
    "sg:classifiers":[
        {
            "category":"Restaurant",
            "type":"Food & Drink"
        }
    ],
    "sg:phone":"+1 418 782 5054",
    "sg:postcode":"G0C 2L0",
    "sg:province":"QC",
    "wof:name":"Resto DE L'Anse",
    "wof:placetype":"venue"
},
  "geometry": {"coordinates":[-64.308983,48.617775],"type":"Point"}
}