{
  "type": "Feature",
  "properties": {
    "iso:country":"CA",
    "sg:city":"Bothwell",
    "sg:classifiers":[
        {
            "category":"Manufacturing",
            "subcategory":"Tools & Machinery",
            "type":"Manufacturing & Wholesale Goods"
        }
    ],
    "sg:phone":"+1 519 695 2031",
    "sg:postcode":"N0P 1C0",
    "sg:province":"ON",
    "sg:tags":[
        "machine",
        "shop"
    ],
    "wof:name":"Gws Tube Forming Solutions Inc",
    "wof:placetype":"venue"
},
  "geometry": {"coordinates":[-81.86637899999999,42.62989],"type":"Point"}
}