{
  "type": "Feature",
  "properties": {
    "addr:full":"1877 Queensway Prince George BC V2L 1L9",
    "addr:housenumber":"1877",
    "addr:postcode":"v2l 1l9",
    "addr:street":"Queensway",
    "iso:country":"CA",
    "sg:address":"1877 Queensway",
    "sg:city":"Prince George",
    "sg:classifiers":[
        {
            "category":"Professional",
            "subcategory":"Engineering",
            "type":"Services"
        }
    ],
    "sg:phone":"+1 250 563 9964",
    "sg:postcode":"V2L 1L9",
    "sg:province":"BC",
    "sg:tags":[
        "engineer"
    ],
    "wof:name":"Woodpro Engineering Ltd",
    "wof:placetype":"venue"
},
  "geometry": {"coordinates":[-122.74243927000001,53.9068374634],"type":"Point"}
}