{
  "type": "Feature",
  "properties": {
    "addr:full":"7260 Boul Cloutier # 33 Charlesbourg QC G1H 3E8",
    "addr:housenumber":"7260",
    "addr:postcode":"g1h 3e8",
    "addr:street":"Boul Cloutier # 33",
    "iso:country":"CA",
    "sg:address":"7260 Boul Cloutier # 33",
    "sg:city":"Charlesbourg",
    "sg:classifiers":[
        {
            "category":"Social Services",
            "type":"Services"
        }
    ],
    "sg:phone":"+1 418 623 7192",
    "sg:postcode":"G1H 3E8",
    "sg:province":"QC",
    "sg:tags":[
        "organization",
        "welfare"
    ],
    "wof:name":"Popote DE Charlesbourg Inc",
    "wof:placetype":"venue"
},
  "geometry": {"coordinates":[-71.273628,46.85384],"type":"Point"}
}