{
  "type": "Feature",
  "properties": {
    "addr:full":"52 Sixth St New Westminster BC V3L 2Z2",
    "addr:housenumber":"52",
    "addr:postcode":"v3l 2z2",
    "addr:street":"Sixth St",
    "iso:country":"CA",
    "sg:address":"52 Sixth St",
    "sg:city":"New Westminster",
    "sg:classifiers":[
        {
            "category":"Wholesale",
            "subcategory":"Chemicals & Plastics",
            "type":"Manufacturing & Wholesale Goods"
        }
    ],
    "sg:phone":"+1 604 521 7670",
    "sg:postcode":"V3L 2Z2",
    "sg:province":"BC",
    "sg:tags":[
        "aromatherapy"
    ],
    "wof:name":"Scents of Comfort",
    "wof:placetype":"venue"
},
  "geometry": {"coordinates":[-122.90918000000001,49.204079],"type":"Point"}
}