{
  "type": "Feature",
  "properties": {
    "addr:full":"6777 Morrison St Niagara Falls ON L2E 2G5",
    "addr:housenumber":"6777",
    "addr:postcode":"l2e 2g5",
    "addr:street":"Morrison St",
    "iso:country":"CA",
    "sg:address":"6777 Morrison St",
    "sg:city":"Niagara Falls",
    "sg:classifiers":[
        {
            "category":"Shopping",
            "type":"Retail Goods"
        }
    ],
    "sg:phone":"+1 905 356 6751",
    "sg:postcode":"L2E 2G5",
    "sg:province":"ON",
    "sg:tags":[
        "pet",
        "food",
        "supply"
    ],
    "wof:name":"Paulmac's Pet Food",
    "wof:placetype":"venue"
},
  "geometry": {"coordinates":[-79.10791,43.104416],"type":"Point"}
}