{
  "type": "Feature",
  "properties": {
    "addr:full":"2105 Victoria Ave Windsor ON N8X 1P8",
    "addr:housenumber":"2105",
    "addr:postcode":"n8x 1p8",
    "addr:street":"Victoria Ave",
    "iso:country":"CA",
    "sg:address":"2105 Victoria Ave",
    "sg:city":"Windsor",
    "sg:classifiers":[
        {
            "category":"Professional",
            "subcategory":"Lawyer & Legal Services",
            "type":"Services"
        }
    ],
    "sg:phone":"+1 519 254 4878",
    "sg:postcode":"N8X 1P8",
    "sg:province":"ON",
    "sg:tags":[
        "attorney"
    ],
    "wof:name":"Wylupek, David J",
    "wof:placetype":"venue"
},
  "geometry": {"coordinates":[-83.0276107788,42.2956886292],"type":"Point"}
}