{
  "type": "Feature",
  "properties": {
    "addr:full":"Emo ON P0W 1E0",
    "addr:postcode":"p0w 1e0",
    "iso:country":"CA",
    "sg:city":"Emo",
    "sg:classifiers":[
        {
            "category":"Food & Beverages",
            "subcategory":"Groceries & Convenience Stores",
            "type":"Retail Goods"
        }
    ],
    "sg:phone":"+1 807 482 2975",
    "sg:postcode":"P0W 1E0",
    "sg:province":"ON",
    "wof:name":"J D Junction",
    "wof:placetype":"venue"
},
  "geometry": {"coordinates":[-93.362335,48.6278],"type":"Point"}
}