{
  "type": "Feature",
  "properties": {
    "addr:full":"330 Tometary Dr Howie Center NS B1L 1G4",
    "addr:housenumber":"330",
    "addr:postcode":"b1l 1g4",
    "addr:street":"Tometary Dr",
    "iso:country":"CA",
    "sg:address":"330 Tometary Dr",
    "sg:city":"Howie Center",
    "sg:classifiers":[
        {
            "category":"Organizations",
            "subcategory":"Religious Organization",
            "type":"Services"
        }
    ],
    "sg:phone":"+1 902 567 9830",
    "sg:postcode":"B1L 1G4",
    "sg:province":"NS",
    "sg:tags":[
        "church"
    ],
    "wof:name":"Cape Breton Christian Fllshp",
    "wof:placetype":"venue"
},
  "geometry": {"coordinates":[-60.276173,46.071079],"type":"Point"}
}