{
  "type": "Feature",
  "properties": {
    "addr:full":"426 Shelley St Winnipeg MB R3K 1G3",
    "addr:housenumber":"426",
    "addr:postcode":"r3k 1g3",
    "addr:street":"Shelley St",
    "iso:country":"CA",
    "sg:address":"426 Shelley St",
    "sg:city":"Winnipeg",
    "sg:classifiers":[
        {
            "category":"Building & Trades",
            "subcategory":"Plumbing",
            "type":"Services"
        }
    ],
    "sg:phone":"+1 204 832 9949",
    "sg:postcode":"R3K 1G3",
    "sg:province":"MB",
    "sg:tags":[
        "drain",
        "cleaning",
        "sewer",
        "contractor"
    ],
    "wof:name":"Gary's Drain Svc",
    "wof:placetype":"venue"
},
  "geometry": {"coordinates":[-97.2919006348,49.8769798279],"type":"Point"}
}