{
  "type": "Feature",
  "properties": {
    "addr:full":"320 Touchwood Hills Ave Lestock SK S0A 2G0",
    "addr:housenumber":"320",
    "addr:postcode":"s0a 2g0",
    "addr:street":"Touchwood Hills Ave",
    "iso:country":"CA",
    "sg:address":"320 Touchwood Hills Ave",
    "sg:city":"Lestock",
    "sg:classifiers":[
        {
            "category":"Government",
            "subcategory":"Office",
            "type":"Public Place"
        }
    ],
    "sg:phone":"+1 306 274 2277",
    "sg:postcode":"S0A 2G0",
    "sg:province":"SK",
    "sg:tags":[
        "municipality"
    ],
    "wof:name":"Lestock Village Office",
    "wof:placetype":"venue"
},
  "geometry": {"coordinates":[-103.98625199999999,51.312473],"type":"Point"}
}