{
  "type": "Feature",
  "properties": {
    "addr:full":"Leamington ON N8H 3L1",
    "addr:postcode":"n8h 3l1",
    "iso:country":"CA",
    "sg:city":"Leamington",
    "sg:classifiers":[
        {
            "category":"Real Estate",
            "subcategory":"Real Estate Operator",
            "type":"Services"
        }
    ],
    "sg:phone":"+1 519 326 0320",
    "sg:postcode":"N8H 3L1",
    "sg:province":"ON",
    "sg:tags":[
        "apartment"
    ],
    "wof:name":"Country Court Apartments",
    "wof:placetype":"venue"
},
  "geometry": {"coordinates":[-82.605469,42.037525],"type":"Point"}
}