{
  "type": "Feature",
  "properties": {
    "addr:full":"2500 Campeau Dr Kanata ON K2K 2W3",
    "addr:housenumber":"2500",
    "addr:postcode":"k2k 2w3",
    "addr:street":"Campeau Dr",
    "iso:country":"CA",
    "sg:address":"2500 Campeau Dr",
    "sg:city":"Kanata",
    "sg:classifiers":[
        {
            "category":"Recreation",
            "type":"Entertainment"
        }
    ],
    "sg:phone":"+1 613 592 6269",
    "sg:postcode":"K2K 2W3",
    "sg:province":"ON",
    "sg:tags":[
        "tennis",
        "court"
    ],
    "wof:name":"March Tennis Club",
    "wof:placetype":"venue"
},
  "geometry": {"coordinates":[-75.89561500000001,45.320175],"type":"Point"}
}