{
  "type": "Feature",
  "properties": {
    "addr:full":"2337 Ch Des Patriotes Saint-Ours QC J0G 1P0",
    "addr:postcode":"2337;j0g 1p0",
    "addr:street":"Ch Des Patriotes",
    "iso:country":"CA",
    "sg:address":"2337 Ch Des Patriotes",
    "sg:city":"Saint-Ours",
    "sg:classifiers":[
        {
            "category":"Home & Garden",
            "subcategory":"Building Materials",
            "type":"Retail Goods"
        }
    ],
    "sg:phone":"+1 450 785 2474",
    "sg:postcode":"J0G 1P0",
    "sg:province":"QC",
    "sg:tags":[
        "door"
    ],
    "wof:name":"Vitrerie Vitrotec Inc",
    "wof:placetype":"venue"
},
  "geometry": {"coordinates":[-73.147408,45.902958],"type":"Point"}
}