{
  "type": "Feature",
  "properties": {
    "iso:country":"CA",
    "sg:address":"444 Ouellette Ave",
    "sg:city":"Windsor",
    "sg:classifiers":[
        {
            "category":"Food & Beverages",
            "subcategory":"Groceries & Convenience Stores",
            "type":"Retail Goods"
        }
    ],
    "sg:phone":"+1 519 253 9272",
    "sg:postcode":"N9A 1B2",
    "sg:province":"ON",
    "wof:name":"Ouellette Convenience Store",
    "wof:placetype":"venue"
},
  "geometry": {"coordinates":[-83.0374908447,42.3154678345],"type":"Point"}
}