{
  "type": "Feature",
  "properties": {
    "addr:full":"Caplan QC G0C 1H0",
    "addr:postcode":"g0c 1h0",
    "iso:country":"CA",
    "sg:city":"Caplan",
    "sg:classifiers":[
        {
            "category":"Retail",
            "subcategory":"Auto Repair",
            "type":"Services"
        }
    ],
    "sg:phone":"+1 418 388 5044",
    "sg:postcode":"G0C 1H0",
    "sg:province":"QC",
    "sg:tags":[
        "repairing",
        "automobile"
    ],
    "wof:name":"Garage Robert Boissonneault",
    "wof:placetype":"venue"
},
  "geometry": {"coordinates":[-65.655128,48.094498],"type":"Point"}
}