{
  "type": "Feature",
  "properties": {
    "iso:country":"CA",
    "sg:address":"64 Carmine Cres",
    "sg:city":"Cambridge",
    "sg:classifiers":[
        {
            "category":"Shopping",
            "subcategory":"Computers & Home Electronics",
            "type":"Retail Goods"
        }
    ],
    "sg:phone":"+1 519 658 0134",
    "sg:postcode":"N3C 3Z4",
    "sg:province":"ON",
    "sg:tags":[
        "equipment",
        "dealer"
    ],
    "wof:name":"Mac Donald Technologies",
    "wof:placetype":"venue"
},
  "geometry": {"coordinates":[-80.2921295166,43.4209098816],"type":"Point"}
}