{
  "type": "Feature",
  "properties": {
    "addr:full":"1185 Rue DE L'Acadie Victoriaville QC G6T 1W4",
    "addr:housenumber":"1185",
    "addr:postcode":"g6t 1w4",
    "addr:street":"Rue De L'Acadie",
    "iso:country":"CA",
    "sg:address":"1185 Rue DE L'Acadie",
    "sg:city":"Victoriaville",
    "sg:classifiers":[
        {
            "category":"Autos & Motor Vehicles",
            "subcategory":"Automobile Sales",
            "type":"Retail Goods"
        }
    ],
    "sg:phone":"+1 819 758 8984",
    "sg:postcode":"G6T 1W4",
    "sg:province":"QC",
    "sg:tags":[
        "truck"
    ],
    "wof:name":"Camions Gb Enr",
    "wof:placetype":"venue"
},
  "geometry": {"coordinates":[-71.94678500000001,46.073669],"type":"Point"}
}