{
  "type": "Feature",
  "properties": {
    "addr:full":"3007 57 Ave SE Calgary AB T2C 0B2",
    "addr:housenumber":"3007",
    "addr:postcode":"t2c 0b2",
    "addr:street":"57 Ave Se",
    "iso:country":"CA",
    "sg:address":"3007 57 Ave SE",
    "sg:city":"Calgary",
    "sg:classifiers":[
        {
            "category":"Local Transit",
            "type":"Transportation"
        }
    ],
    "sg:phone":"+1 403 262 5647",
    "sg:postcode":"T2C 0B2",
    "sg:province":"AB",
    "sg:tags":[
        "consultant"
    ],
    "wof:name":"Motor Transport Consultants",
    "wof:placetype":"venue"
},
  "geometry": {"coordinates":[-113.993522644,51.0034980774],"type":"Point"}
}