{
  "type": "Feature",
  "properties": {
    "iso:country":"CA",
    "sg:city":"Sudbury",
    "sg:classifiers":[
        {
            "category":"Shopping",
            "subcategory":"Clothing, Apparel, & Fashions",
            "type":"Retail Goods"
        }
    ],
    "sg:phone":"+1 705 523 1205",
    "sg:postcode":"P3E 6K4",
    "sg:province":"ON",
    "sg:tags":[
        "tailor"
    ],
    "wof:name":"Izabel's Tailoring",
    "wof:placetype":"venue"
},
  "geometry": {"coordinates":[-81.0100097656,46.4622383118],"type":"Point"}
}