{
  "type": "Feature",
  "properties": {
    "addr:full":"71 King St Saint John NB E2L 1G5",
    "addr:housenumber":"71",
    "addr:postcode":"nb e2l 1g5",
    "addr:street":"King St",
    "iso:country":"CA",
    "sg:address":"71 King St",
    "sg:city":"Saint John",
    "sg:classifiers":[
        {
            "category":"Banks & Credit Unions",
            "subcategory":"Bank",
            "type":"Services"
        }
    ],
    "sg:phone":"+1 506 634 1234",
    "sg:postcode":"E2L 1G5",
    "sg:province":"NB",
    "wof:name":"National Bank of Canada",
    "wof:placetype":"venue"
},
  "geometry": {"coordinates":[-66.059898,45.273411],"type":"Point"}
}