{
  "type": "Feature",
  "properties": {
    "addr:full":"2491 St Joseph Blvd Orleans ON K1C 1G2",
    "addr:housenumber":"2491",
    "addr:postcode":"k1c 1g2",
    "addr:street":"St Joseph Blvd",
    "iso:country":"CA",
    "sg:address":"2491 St Joseph Blvd",
    "sg:city":"Orleans",
    "sg:classifiers":[
        {
            "category":"Restaurant",
            "type":"Food & Drink"
        }
    ],
    "sg:phone":"+1 613 834 4549",
    "sg:postcode":"K1C 1G2",
    "sg:province":"ON",
    "wof:name":"Rangoli Indian Cuisine & Sweet",
    "wof:placetype":"venue"
},
  "geometry": {"coordinates":[-75.526993,45.470226],"type":"Point"}
}