{
  "type": "Feature",
  "properties": {
    "addr:full":"1975 50 Ave Red Deer AB T4R 1Z4",
    "addr:housenumber":"1975",
    "addr:postcode":"t4r 1z4",
    "addr:street":"50 Ave",
    "iso:country":"CA",
    "sg:address":"1975 50 Ave",
    "sg:city":"Red Deer",
    "sg:classifiers":[
        {
            "category":"Autos & Motor Vehicles",
            "subcategory":"Auto Supplies",
            "type":"Retail Goods"
        }
    ],
    "sg:phone":"+1 403 347 5501",
    "sg:postcode":"T4R 1Z4",
    "sg:province":"AB",
    "sg:tags":[
        "tire"
    ],
    "wof:name":"Don's Tire & Automotive Repair",
    "wof:placetype":"venue"
},
  "geometry": {"coordinates":[-113.81332399999999,52.234016],"type":"Point"}
}