{
  "type": "Feature",
  "properties": {
    "addr:full":"Toronto City Ctr Arpt # Hng 1 Toronto ON M5V 1A1",
    "addr:housenumber":"1",
    "addr:postcode":"m5v 1a1",
    "iso:country":"CA",
    "sg:address":"Toronto City Ctr Arpt # Hng 1",
    "sg:city":"Toronto",
    "sg:classifiers":[
        {
            "category":"Building & Trades",
            "subcategory":"Equipment Rental",
            "type":"Services"
        }
    ],
    "sg:phone":"+1 416 203 1144",
    "sg:postcode":"M5V 1A1",
    "sg:province":"ON",
    "sg:tags":[
        "aircraft",
        "charter",
        "leasing",
        "company",
        "airline"
    ],
    "wof:name":"Trans Capital Air Ltd",
    "wof:placetype":"venue"
},
  "geometry": {"coordinates":[-79.37629699999999,43.65049],"type":"Point"}
}