{
  "type": "Feature",
  "properties": {
    "addr:full":"13811 Wireless Way Richmond BC V6V 3A4",
    "addr:housenumber":"13811",
    "addr:postcode":"v6v 3a4",
    "addr:street":"Wireless Way",
    "iso:country":"CA",
    "sg:address":"13811 Wireless Way",
    "sg:city":"Richmond",
    "sg:classifiers":[
        {
            "category":"Manufacturing",
            "subcategory":"Electronics",
            "type":"Manufacturing & Wholesale Goods"
        }
    ],
    "sg:phone":"+1 604 231 1100",
    "sg:postcode":"V6V 3A4",
    "sg:province":"BC",
    "sg:tags":[
        "equipment",
        "electronic",
        "supply"
    ],
    "wof:name":"Sierra Wireless Inc",
    "wof:placetype":"venue"
},
  "geometry": {"coordinates":[-123.07074,49.171837],"type":"Point"}
}