{
  "type": "Feature",
  "properties": {
    "addr:full":"102 3rd St SE Portage LA Prairie MB R1N 1M5",
    "addr:housenumber":"102",
    "addr:postcode":"r1n 1m5",
    "addr:street":"3Rd St Se",
    "iso:country":"CA",
    "sg:address":"102 3rd St SE",
    "sg:city":"Portage LA Prairie",
    "sg:classifiers":[
        {
            "category":"Organizations",
            "subcategory":"Religious Organization",
            "type":"Services"
        }
    ],
    "sg:phone":"+1 204 857 6380",
    "sg:postcode":"R1N 1M5",
    "sg:province":"MB",
    "sg:tags":[
        "church"
    ],
    "wof:name":"First Baptist Church",
    "wof:placetype":"venue"
},
  "geometry": {"coordinates":[-98.2860488892,49.9707679749],"type":"Point"}
}