{
  "type": "Feature",
  "properties": {
    "addr:full":"508 4E Av Saint-Paul-DE-Montminy QC G0R 3Y0",
    "addr:housenumber":"508",
    "addr:postcode":"g0r 3y0",
    "addr:street":"4E Av Saint-Paul-De-Montminy",
    "iso:country":"CA",
    "sg:address":"508 4E Av",
    "sg:city":"Saint-Paul-DE-Montminy",
    "sg:classifiers":[
        {
            "category":"Home & Garden",
            "subcategory":"Building Materials",
            "type":"Retail Goods"
        }
    ],
    "sg:phone":"+1 418 469 2112",
    "sg:postcode":"G0R 3Y0",
    "sg:province":"QC",
    "sg:tags":[
        "cooperative"
    ],
    "wof:name":"Centre DE Renovation St-Paul",
    "wof:placetype":"venue"
},
  "geometry": {"coordinates":[-70.360435,46.730865],"type":"Point"}
}