{
  "type": "Feature",
  "properties": {
    "iso:country":"CA",
    "sg:address":"2620 Royal Windsor Dr",
    "sg:city":"Mississauga",
    "sg:classifiers":[
        {
            "category":"Manufacturing",
            "subcategory":"Chemicals & Compounds",
            "type":"Manufacturing & Wholesale Goods"
        }
    ],
    "sg:phone":"+1 905 823 1800",
    "sg:postcode":"L5J 4E7",
    "sg:province":"ON",
    "wof:name":"Ashland Canada Corp",
    "wof:placetype":"venue"
},
  "geometry": {"coordinates":[-79.6422653198,43.4993972778],"type":"Point"}
}