{
  "type": "Feature",
  "properties": {
    "iso:country":"CA",
    "sg:address":"740 Rue Saint-Maurice",
    "sg:city":"Montreal",
    "sg:classifiers":[
        {
            "category":"Utilities",
            "subcategory":"Refuse",
            "type":"Services"
        }
    ],
    "sg:phone":"+1 514 878 0727",
    "sg:postcode":"H3C 1L5",
    "sg:province":"QC",
    "sg:tags":[
        "equipment",
        "recycling",
        "system"
    ],
    "wof:name":"Tirex",
    "wof:placetype":"venue"
},
  "geometry": {"coordinates":[-73.55961600000001,45.499031],"type":"Point"}
}