{
  "type": "Feature",
  "properties": {
    "addr:full":"RR 1 Legal AB T0G 1L0",
    "addr:postcode":"t0g 1l0",
    "addr:street":"Rr 1",
    "iso:country":"CA",
    "sg:address":"RR 1",
    "sg:city":"Legal",
    "sg:classifiers":[
        {
            "category":"Retail",
            "subcategory":"Laundry & Dry Cleaning",
            "type":"Services"
        }
    ],
    "sg:phone":"+1 780 961 3064",
    "sg:postcode":"T0G 1L0",
    "sg:province":"AB",
    "sg:tags":[
        "cleaners",
        "excavating",
        "contractor",
        "rug",
        "carpet"
    ],
    "wof:name":"Rene's Vacuum Svc Inc",
    "wof:placetype":"venue"
},
  "geometry": {"coordinates":[-113.594337463,53.9480209351],"type":"Point"}
}