{
  "type": "Feature",
  "properties": {
    "addr:full":"48 Ellen Ave Hamilton ON L8G 5B4",
    "addr:housenumber":"48",
    "addr:postcode":"l8g 5b4",
    "addr:street":"Ellen Ave",
    "iso:country":"CA",
    "sg:address":"48 Ellen Ave",
    "sg:city":"Hamilton",
    "sg:classifiers":[
        {
            "category":"Building & Trades",
            "subcategory":"Construction",
            "type":"Services"
        }
    ],
    "sg:phone":"+1 905 578 5442",
    "sg:postcode":"L8G 5B4",
    "sg:province":"ON",
    "sg:tags":[
        "home",
        "improvement"
    ],
    "wof:name":"Mike's Painting & Decorating",
    "wof:placetype":"venue"
},
  "geometry": {"coordinates":[-79.776718,43.21513],"type":"Point"}
}