{
  "type": "Feature",
  "properties": {
    "addr:full":"3850 Boul Dagenais O Laval QC H7P 1W1",
    "addr:housenumber":"3850",
    "addr:postcode":"h7p 1w1",
    "addr:street":"Boul Dagenais O",
    "iso:country":"CA",
    "sg:address":"3850 Boul Dagenais O",
    "sg:city":"Laval",
    "sg:classifiers":[
        {
            "category":"Food & Beverages",
            "subcategory":"Groceries & Convenience Stores",
            "type":"Retail Goods"
        }
    ],
    "sg:phone":"+1 450 628 8143",
    "sg:postcode":"H7P 1W1",
    "sg:province":"QC",
    "sg:tags":[
        "grocer"
    ],
    "wof:name":"Super C",
    "wof:placetype":"venue"
},
  "geometry": {"coordinates":[-73.8210525513,45.5710334778],"type":"Point"}
}