{
  "type": "Feature",
  "properties": {
    "addr:full":"Essex Rd Kenora ON P9N 3W7",
    "addr:postcode":"p9n 3w7",
    "addr:street":"Essex Rd",
    "iso:country":"CA",
    "sg:address":"Essex Rd",
    "sg:city":"Kenora",
    "sg:classifiers":[
        {
            "category":"Building & Trades",
            "subcategory":"Construction",
            "type":"Services"
        }
    ],
    "sg:phone":"+1 807 548 4398",
    "sg:postcode":"P9N 3W7",
    "sg:province":"ON",
    "sg:tags":[
        "general",
        "contractor"
    ],
    "wof:name":"Ivor Hulmes & Sons Contr Ltd",
    "wof:placetype":"venue"
},
  "geometry": {"coordinates":[-94.37651062010001,49.8148536682],"type":"Point"}
}