{
  "type": "Feature",
  "properties": {
    "addr:full":"427 Academy Rd Winnipeg MB R3N 0C2",
    "addr:housenumber":"427",
    "addr:postcode":"r3n 0c2",
    "addr:street":"Academy Rd",
    "iso:country":"CA",
    "sg:address":"427 Academy Rd",
    "sg:city":"Winnipeg",
    "sg:classifiers":[
        {
            "category":"Personal",
            "subcategory":"Beauty Salon",
            "type":"Services"
        }
    ],
    "sg:phone":"+1 204 489 9775",
    "sg:postcode":"R3N 0C2",
    "sg:province":"MB",
    "wof:name":"Academy Hair Studio",
    "wof:placetype":"venue"
},
  "geometry": {"coordinates":[-97.1852645874,49.8739471436],"type":"Point"}
}