{
  "type": "Feature",
  "properties": {
    "addr:full":"411 Dundas St W Toronto ON M5T 1G6",
    "addr:housenumber":"411",
    "addr:postcode":"m5t 1g6",
    "addr:street":"Dundas St W",
    "iso:country":"CA",
    "sg:address":"411 Dundas St W",
    "sg:city":"Toronto",
    "sg:classifiers":[
        {
            "category":"Real Estate",
            "subcategory":"Real Estate Agent",
            "type":"Services"
        }
    ],
    "sg:phone":"+1 416 977 6617",
    "sg:postcode":"M5T 1G6",
    "sg:province":"ON",
    "wof:name":"Tradeworld Realty Inc",
    "wof:placetype":"venue"
},
  "geometry": {"coordinates":[-79.39506530760001,43.6534194946],"type":"Point"}
}