{
  "type": "Feature",
  "properties": {
    "addr:full":"7555 Edgar Industrial Dr Red Deer AB T4P 3R2",
    "addr:housenumber":"7555",
    "addr:postcode":"t4p 3r2",
    "addr:street":"Edgar Industrial Dr",
    "iso:country":"CA",
    "sg:address":"7555 Edgar Industrial Dr",
    "sg:city":"Red Deer",
    "sg:classifiers":[
        {
            "category":"Mining & Drilling",
            "type":"Manufacturing & Wholesale Goods"
        }
    ],
    "sg:phone":"+1 403 343 1110",
    "sg:postcode":"T4P 3R2",
    "sg:province":"AB",
    "sg:tags":[
        "field",
        "oil"
    ],
    "wof:name":"Midfield Supply Ltd",
    "wof:placetype":"venue"
},
  "geometry": {"coordinates":[-113.855721,52.302601],"type":"Point"}
}