{
  "type": "Feature",
  "properties": {
    "iso:country":"CA",
    "sg:address":"175 Macdonald Cres",
    "sg:city":"Fort Mcmurray",
    "sg:classifiers":[
        {
            "category":"Manufacturing",
            "subcategory":"Tools & Machinery",
            "type":"Manufacturing & Wholesale Goods"
        }
    ],
    "sg:phone":"+1 780 791 1445",
    "sg:postcode":"T9H 4B3",
    "sg:province":"AB",
    "sg:tags":[
        "machine",
        "shop"
    ],
    "wof:name":"Lemax Machine & Welding Ltd",
    "wof:placetype":"venue"
},
  "geometry": {"coordinates":[-111.336921692,56.6631278992],"type":"Point"}
}