{
  "type": "Feature",
  "properties": {
    "iso:country":"CA",
    "sg:address":"411 Kootenay St",
    "sg:city":"Nelson",
    "sg:classifiers":[
        {
            "category":"Shopping",
            "subcategory":"Books",
            "type":"Retail Goods"
        }
    ],
    "sg:phone":"+1 250 354 4722",
    "sg:postcode":"V1L 1K7",
    "sg:province":"BC",
    "sg:tags":[
        "compact",
        "record",
        "disc",
        "tape"
    ],
    "wof:name":"Pack Rat Annie's",
    "wof:placetype":"venue"
},
  "geometry": {"coordinates":[-117.297111511,49.4916915894],"type":"Point"}
}