{
  "type": "Feature",
  "properties": {
    "iso:country":"CA",
    "sg:address":"166 Rue Des Lilas",
    "sg:city":"Thetford Mines",
    "sg:classifiers":[
        {
            "category":"Arts & Performance",
            "subcategory":"Theater",
            "type":"Entertainment"
        }
    ],
    "sg:phone":"+1 418 335 2024",
    "sg:postcode":"G6G 1A4",
    "sg:province":"QC",
    "sg:tags":[
        "mobile",
        "discotheque"
    ],
    "wof:name":"Sonorisation Tm",
    "wof:placetype":"venue"
},
  "geometry": {"coordinates":[-71.3154602051,46.1095352173],"type":"Point"}
}