{
  "type": "Feature",
  "properties": {
    "addr:full":"2 Alsask Alsask SK S0L 0A0",
    "addr:housenumber":"2",
    "addr:postcode":"s0l 0a0",
    "addr:street":"Alsask Alsask",
    "iso:country":"CA",
    "sg:address":"2 Alsask",
    "sg:city":"Alsask",
    "sg:classifiers":[
        {
            "category":"Manufacturing",
            "subcategory":"Pet Food",
            "type":"Manufacturing & Wholesale Goods"
        }
    ],
    "sg:phone":"+1 306 968 2201",
    "sg:postcode":"S0L 0A0",
    "sg:province":"SK",
    "sg:tags":[
        "flour",
        "mills"
    ],
    "wof:name":"Nunweiler's Flour CO",
    "wof:placetype":"venue"
},
  "geometry": {"coordinates":[-109.988693,51.379581],"type":"Point"}
}