{
  "type": "Feature",
  "properties": {
    "addr:full":"552 University Park Dr Regina SK S4V 2Z3",
    "addr:housenumber":"552",
    "addr:postcode":"s4v 2z3",
    "addr:street":"University Park Dr",
    "iso:country":"CA",
    "sg:address":"552 University Park Dr",
    "sg:city":"Regina",
    "sg:classifiers":[
        {
            "category":"Health Services",
            "subcategory":"Doctor",
            "type":"Services"
        }
    ],
    "sg:phone":"+1 306 565 3500",
    "sg:postcode":"S4V 2Z3",
    "sg:province":"SK",
    "sg:tags":[
        "dentist"
    ],
    "wof:name":"West Landing Dental Ctr",
    "wof:placetype":"venue"
},
  "geometry": {"coordinates":[-104.549781799,50.4395904541],"type":"Point"}
}