{
  "type": "Feature",
  "properties": {
    "addr:full":"1070 Kingsway Sudbury ON P3B 2E5",
    "addr:housenumber":"1070",
    "addr:postcode":"p3b 2e5",
    "addr:street":"Kingsway",
    "iso:country":"CA",
    "sg:address":"1070 Kingsway",
    "sg:city":"Sudbury",
    "sg:classifiers":[
        {
            "category":"Restaurant",
            "type":"Food & Drink"
        }
    ],
    "sg:phone":"+1 705 560 6888",
    "sg:postcode":"P3B 2E5",
    "sg:province":"ON",
    "wof:name":"Casey's Kingsway",
    "wof:placetype":"venue"
},
  "geometry": {"coordinates":[-80.9618,46.50098],"type":"Point"}
}