{
  "type": "Feature",
  "properties": {
    "addr:full":"1006 Rue Craig Richmond QC J0B 2H0",
    "addr:housenumber":"1006",
    "addr:postcode":"j0b 2h0",
    "addr:street":"Rue Craig",
    "iso:country":"CA",
    "sg:address":"1006 Rue Craig",
    "sg:city":"Richmond",
    "sg:classifiers":[
        {
            "category":"Wholesale",
            "subcategory":"Machinery & Supplies",
            "type":"Manufacturing & Wholesale Goods"
        }
    ],
    "sg:phone":"+1 819 826 3707",
    "sg:postcode":"J0B 2H0",
    "sg:province":"QC",
    "sg:tags":[
        "farm",
        "equipment"
    ],
    "wof:name":"Agritex-Richmond",
    "wof:placetype":"venue"
},
  "geometry": {"coordinates":[-72.12906646730001,45.6680793762],"type":"Point"}
}