{
  "type": "Feature",
  "properties": {
    "iso:country":"CA",
    "sg:address":"5492 Hurst Crt",
    "sg:city":"Mississauga",
    "sg:classifiers":[
        {
            "category":"Education",
            "subcategory":"School",
            "type":"Public Place"
        }
    ],
    "sg:phone":"+1 905 826 7400",
    "sg:postcode":"L5V 2C8",
    "sg:province":"ON",
    "wof:name":"Tutoring Wonders",
    "wof:placetype":"venue"
},
  "geometry": {"coordinates":[-79.6900558472,43.5945968628],"type":"Point"}
}