{
  "type": "Feature",
  "properties": {
    "addr:full":"17 Fourth Ave S Williams Lake BC V2G 1J6",
    "addr:housenumber":"17",
    "addr:postcode":"v2g 1j6",
    "addr:street":"Fourth Ave S Williams",
    "iso:country":"CA",
    "sg:address":"17 Fourth Ave S",
    "sg:city":"Williams Lake",
    "sg:classifiers":[
        {
            "category":"Social Services",
            "type":"Services"
        }
    ],
    "sg:phone":"+1 250 392 5730",
    "sg:postcode":"V2G 1J6",
    "sg:province":"BC",
    "sg:tags":[
        "youth",
        "organization",
        "center"
    ],
    "wof:name":"Boys & Girls Club",
    "wof:placetype":"venue"
},
  "geometry": {"coordinates":[-122.14060974100001,52.1280097961],"type":"Point"}
}