{
  "type": "Feature",
  "properties": {
    "iso:country":"CA",
    "sg:address":"89 Humber College Blvd # 112",
    "sg:city":"Etobicoke",
    "sg:classifiers":[
        {
            "category":"Health Services",
            "subcategory":"Doctor",
            "type":"Services"
        }
    ],
    "sg:phone":"+1 416 746 1617",
    "sg:postcode":"M9V 4B8",
    "sg:province":"ON",
    "sg:tags":[
        "physician",
        "surgeon"
    ],
    "wof:name":"Kravetz, Arnold I MD",
    "wof:placetype":"venue"
},
  "geometry": {"coordinates":[-79.5982131958,43.731010437],"type":"Point"}
}