{
  "type": "Feature",
  "properties": {
    "addr:full":"337 King St E Gananoque ON K7G 1G6",
    "addr:housenumber":"337",
    "addr:postcode":"k7g 1g6",
    "addr:street":"King St E",
    "iso:country":"CA",
    "sg:address":"337 King St E",
    "sg:city":"Gananoque",
    "sg:classifiers":[
        {
            "category":"Retail",
            "subcategory":"Auto Repair",
            "type":"Services"
        }
    ],
    "sg:phone":"+1 613 382 7566",
    "sg:postcode":"K7G 1G6",
    "sg:province":"ON",
    "sg:tags":[
        "repairing",
        "automobile",
        "wrecker"
    ],
    "wof:name":"Gananoque Auto Svc",
    "wof:placetype":"venue"
},
  "geometry": {"coordinates":[-76.1578826904,44.3323974609],"type":"Point"}
}