{
  "type": "Feature",
  "properties": {
    "iso:country":"CA",
    "sg:city":"Dollard-Des-Ormeaux",
    "sg:classifiers":[
        {
            "category":"Freight",
            "type":"Transportation"
        }
    ],
    "sg:phone":"+1 514 620 5805",
    "sg:postcode":"H9H 4A6",
    "sg:province":"QC",
    "sg:tags":[
        "trucking"
    ],
    "wof:name":"Fero Transport Inc",
    "wof:placetype":"venue"
},
  "geometry": {"coordinates":[-73.845406,45.483295],"type":"Point"}
}