{
  "type": "Feature",
  "properties": {
    "addr:full":"1590 Willow Cres Kelowna BC V1Y 4K3",
    "addr:housenumber":"1590",
    "addr:postcode":"v1y 4k3",
    "addr:street":"Willow Cres",
    "iso:country":"CA",
    "sg:address":"1590 Willow Cres",
    "sg:city":"Kelowna",
    "sg:classifiers":[
        {
            "category":"Building & Trades",
            "subcategory":"Plumbing",
            "type":"Services"
        }
    ],
    "sg:phone":"+1 250 860 5981",
    "sg:postcode":"V1Y 4K3",
    "sg:province":"BC",
    "sg:tags":[
        "contractor"
    ],
    "wof:name":"Progress Plumbing & Heating",
    "wof:placetype":"venue"
},
  "geometry": {"coordinates":[-119.462501526,49.8929214478],"type":"Point"}
}