{
  "type": "Feature",
  "properties": {
    "addr:full":"25 2 Second Ave Wabush NL A0R 1B0",
    "addr:housenumber":"2",
    "addr:postcode":"a0r 1b0",
    "addr:street":"25;Second Ave",
    "iso:country":"CA",
    "sg:address":"25 2 Second Ave",
    "sg:city":"Wabush",
    "sg:classifiers":[
        {
            "category":"Wholesale",
            "subcategory":"Machinery & Supplies",
            "type":"Manufacturing & Wholesale Goods"
        }
    ],
    "sg:phone":"+1 709 282 3626",
    "sg:postcode":"A0R 1B0",
    "sg:province":"NL",
    "sg:tags":[
        "equipment",
        "mining"
    ],
    "wof:name":"Wajax Industries Ltd",
    "wof:placetype":"venue"
},
  "geometry": {"coordinates":[-66.868637085,52.8973655701],"type":"Point"}
}