{
  "type": "Feature",
  "properties": {
    "addr:full":"Calgary AB T2A 6T7",
    "addr:postcode":"t2a 6t7",
    "iso:country":"CA",
    "sg:city":"Calgary",
    "sg:classifiers":[
        {
            "category":"Professional",
            "subcategory":"Computer Services",
            "type":"Services"
        }
    ],
    "sg:phone":"+1 403 248 6700",
    "sg:postcode":"T2A 6T7",
    "sg:province":"AB",
    "sg:tags":[
        "repair"
    ],
    "wof:name":"Care Factor Computer Svc Inc",
    "wof:placetype":"venue"
},
  "geometry": {"coordinates":[-113.991974,51.054623],"type":"Point"}
}