{
  "type": "Feature",
  "properties": {
    "addr:full":"78 Fullarton St London ON N6A 1K1",
    "addr:housenumber":"78",
    "addr:postcode":"n6a 1k1",
    "addr:street":"Fullarton St",
    "iso:country":"CA",
    "sg:address":"78 Fullarton St",
    "sg:city":"London",
    "sg:classifiers":[
        {
            "category":"Parking",
            "type":"Transportation"
        }
    ],
    "sg:phone":"+1 519 432 3350",
    "sg:postcode":"N6A 1K1",
    "sg:province":"ON",
    "sg:tags":[
        "garage"
    ],
    "wof:name":"Metro Park Svc Inc",
    "wof:placetype":"venue"
},
  "geometry": {"coordinates":[-81.2535858154,42.9847946167],"type":"Point"}
}