{
  "type": "Feature",
  "properties": {
    "iso:country":"CA",
    "sg:address":"240 Rue Manville O",
    "sg:city":"Asbestos",
    "sg:classifiers":[
        {
            "category":"Building & Trades",
            "subcategory":"Construction",
            "type":"Services"
        }
    ],
    "sg:phone":"+1 819 879 0738",
    "sg:postcode":"J1T 1G7",
    "sg:province":"QC",
    "sg:tags":[
        "contractor"
    ],
    "wof:name":"Services Rme Inc",
    "wof:placetype":"venue"
},
  "geometry": {"coordinates":[-71.967415,45.776779],"type":"Point"}
}