{
  "type": "Feature",
  "properties": {
    "iso:country":"CA",
    "sg:address":"6400 Ch Saint-Francois",
    "sg:city":"Saint-Laurent",
    "sg:classifiers":[
        {
            "category":"Wholesale",
            "subcategory":"Auto Parts",
            "type":"Manufacturing & Wholesale Goods"
        }
    ],
    "sg:phone":"+1 514 333 5133",
    "sg:postcode":"H4S 1B7",
    "sg:province":"QC",
    "sg:tags":[
        "truck",
        "refrigeration",
        "equipment"
    ],
    "wof:name":"Refrigeration Thermo King",
    "wof:placetype":"venue"
},
  "geometry": {"coordinates":[-73.742332,45.48439],"type":"Point"}
}