{
  "type": "Feature",
  "properties": {
    "addr:full":"Guelph ON N1K 1S5",
    "addr:postcode":"n1k 1s5",
    "iso:country":"CA",
    "sg:city":"Guelph",
    "sg:classifiers":[
        {
            "category":"Real Estate",
            "subcategory":"Developer",
            "type":"Services"
        }
    ],
    "sg:phone":"+1 519 822 0141",
    "sg:postcode":"N1K 1S5",
    "sg:province":"ON",
    "wof:name":"Cernuik Construction Ltd",
    "wof:placetype":"venue"
},
  "geometry": {"coordinates":[-80.306183,43.532726],"type":"Point"}
}