{
  "type": "Feature",
  "properties": {
    "addr:full":"358 Church St E Delhi ON N4B 1V1",
    "addr:housenumber":"358",
    "addr:postcode":"n4b 1v1",
    "addr:street":"Church St E",
    "iso:country":"CA",
    "sg:address":"358 Church St E",
    "sg:city":"Delhi",
    "sg:classifiers":[
        {
            "category":"Building & Trades",
            "subcategory":"Plumbing",
            "type":"Services"
        }
    ],
    "sg:phone":"+1 519 582 1137",
    "sg:postcode":"N4B 1V1",
    "sg:province":"ON",
    "sg:tags":[
        "contractor"
    ],
    "wof:name":"Jim's Plumbing",
    "wof:placetype":"venue"
},
  "geometry": {"coordinates":[-80.480469,42.855659],"type":"Point"}
}