{
  "type": "Feature",
  "properties": {
    "addr:full":"5091 Continental Way Prince George BC V2N 5S5",
    "addr:housenumber":"5091",
    "addr:postcode":"v2n 5s5",
    "addr:street":"Continental Way",
    "iso:country":"CA",
    "sg:address":"5091 Continental Way",
    "sg:city":"Prince George",
    "sg:classifiers":[
        {
            "category":"Wholesale",
            "subcategory":"Machinery & Supplies",
            "type":"Manufacturing & Wholesale Goods"
        }
    ],
    "sg:phone":"+1 250 564 9714",
    "sg:postcode":"V2N 5S5",
    "sg:province":"BC",
    "sg:tags":[
        "equipment",
        "log",
        "splitting"
    ],
    "wof:name":"Bryer Machinery Corp",
    "wof:placetype":"venue"
},
  "geometry": {"coordinates":[-122.734154,53.872841],"type":"Point"}
}