{
  "type": "Feature",
  "properties": {
    "addr:full":"12612 Highway 50 Bolton ON L7E 1T6",
    "addr:housenumber":"12612",
    "addr:postcode":"l7e 1t6",
    "addr:street":"Highway 50",
    "iso:country":"CA",
    "sg:address":"12612 Highway 50",
    "sg:city":"Bolton",
    "sg:classifiers":[
        {
            "category":"Real Estate",
            "subcategory":"Real Estate Agent",
            "type":"Services"
        }
    ],
    "sg:phone":"+1 905 857 7353",
    "sg:postcode":"L7E 1T6",
    "sg:province":"ON",
    "wof:name":"Northwest Holdings",
    "wof:placetype":"venue"
},
  "geometry": {"coordinates":[-79.73943300000001,43.880852],"type":"Point"}
}