{
  "type": "Feature",
  "properties": {
    "addr:full":"2848 Laurier St # 3 Rockland ON K4K 1A3",
    "addr:housenumber":"2848",
    "addr:postcode":"k4k 1a3",
    "addr:street":"Laurier St # 3",
    "iso:country":"CA",
    "sg:address":"2848 Laurier St # 3",
    "sg:city":"Rockland",
    "sg:classifiers":[
        {
            "category":"Shopping",
            "type":"Retail Goods"
        }
    ],
    "sg:phone":"+1 613 446 7452",
    "sg:postcode":"K4K 1A3",
    "sg:province":"ON",
    "sg:tags":[
        "equipment",
        "wine",
        "supply"
    ],
    "wof:name":"Passion Wines",
    "wof:placetype":"venue"
},
  "geometry": {"coordinates":[-75.3023986816,45.5404396057],"type":"Point"}
}