{
  "type": "Feature",
  "properties": {
    "iso:country":"CA",
    "sg:address":"674 Boul Graham",
    "sg:city":"Mont-Royal",
    "sg:classifiers":[
        {
            "category":"Building & Trades",
            "subcategory":"Cleaning & Sanitation",
            "type":"Services"
        }
    ],
    "sg:phone":"+1 514 273 8787",
    "sg:postcode":"H3P 2E5",
    "sg:province":"QC",
    "sg:tags":[
        "janitor"
    ],
    "wof:name":"Lepont 2000 Inc",
    "wof:placetype":"venue"
},
  "geometry": {"coordinates":[-73.632866,45.519073],"type":"Point"}
}