{
  "type": "Feature",
  "properties": {
    "addr:full":"402 Boul Rene-Levesque O Montreal QC H2Z 1Z6",
    "addr:housenumber":"402",
    "addr:postcode":"h2z 1z6",
    "addr:street":"Boul Rene-Levesque O",
    "iso:country":"CA",
    "sg:address":"402 Boul Rene-Levesque O",
    "sg:city":"Montreal",
    "sg:classifiers":[
        {
            "category":"Restaurant",
            "type":"Food & Drink"
        }
    ],
    "sg:phone":"+1 514 861 1115",
    "sg:postcode":"H2Z 1Z6",
    "sg:province":"QC",
    "wof:name":"Cafe Bistro LA Tour",
    "wof:placetype":"venue"
},
  "geometry": {"coordinates":[-73.55798299999999,45.512714],"type":"Point"}
}