{
  "type": "Feature",
  "properties": {
    "addr:full":"4761 Nelles Cres Windermere BC V0B 2L0",
    "addr:housenumber":"4761",
    "addr:postcode":"bc v0b 2l0",
    "addr:street":"Nelles Cres",
    "iso:country":"CA",
    "sg:address":"4761 Nelles Cres",
    "sg:city":"Windermere",
    "sg:classifiers":[
        {
            "category":"Building & Trades",
            "subcategory":"Construction",
            "type":"Services"
        }
    ],
    "sg:phone":"+1 250 342 6805",
    "sg:postcode":"V0B 2L0",
    "sg:province":"BC",
    "sg:tags":[
        "excavating",
        "contractor"
    ],
    "wof:name":"Sholinder & Mac Kay Excavating",
    "wof:placetype":"venue"
},
  "geometry": {"coordinates":[-115.975571,50.465527],"type":"Point"}
}