{
  "type": "Feature",
  "properties": {
    "addr:full":"203 Katherine Ave N Porcupine Plain SK S0E 1H0",
    "addr:housenumber":"203",
    "addr:postcode":"s0e 1h0",
    "addr:street":"Katherine Ave N Porcupine Plain",
    "iso:country":"CA",
    "sg:address":"203 Katherine Ave N",
    "sg:city":"Porcupine Plain",
    "sg:classifiers":[
        {
            "category":"Autos & Motor Vehicles",
            "subcategory":"Auto Supplies",
            "type":"Retail Goods"
        }
    ],
    "sg:phone":"+1 306 278 2162",
    "sg:postcode":"S0E 1H0",
    "sg:province":"SK",
    "sg:tags":[
        "tire"
    ],
    "wof:name":"Porcupine Tire Ctr",
    "wof:placetype":"venue"
},
  "geometry": {"coordinates":[-103.254333,52.598064],"type":"Point"}
}