{
  "type": "Feature",
  "properties": {
    "iso:country":"CA",
    "sg:address":"36 George St",
    "sg:city":"Barrie",
    "sg:classifiers":[
        {
            "category":"Social Services",
            "subcategory":"Job Training",
            "type":"Services"
        }
    ],
    "sg:phone":"+1 705 727 1688",
    "sg:postcode":"L4N 5N3",
    "sg:province":"ON",
    "sg:tags":[
        "rehabilitation"
    ],
    "wof:name":"Workable Centres",
    "wof:placetype":"venue"
},
  "geometry": {"coordinates":[-79.7056732178,44.3799819946],"type":"Point"}
}