{
  "type": "Feature",
  "properties": {
    "addr:full":"219 King St Port Colborne ON L3K 4G6",
    "addr:housenumber":"219",
    "addr:postcode":"l3k 4g6",
    "addr:street":"King St",
    "iso:country":"CA",
    "sg:address":"219 King St",
    "sg:city":"Port Colborne",
    "sg:classifiers":[
        {
            "category":"Home & Garden",
            "subcategory":"Household Appliances",
            "type":"Retail Goods"
        }
    ],
    "sg:phone":"+1 905 835 2216",
    "sg:postcode":"L3K 4G6",
    "sg:province":"ON",
    "sg:tags":[
        "cleaners",
        "vacuum"
    ],
    "wof:name":"Alliance Vacuum Shop",
    "wof:placetype":"venue"
},
  "geometry": {"coordinates":[-79.25109863279999,42.8855667114],"type":"Point"}
}