{
  "type": "Feature",
  "properties": {
    "iso:country":"CA",
    "sg:city":"Sainte-Foy",
    "sg:classifiers":[
        {
            "category":"Health Services",
            "subcategory":"Doctor",
            "type":"Services"
        }
    ],
    "sg:phone":"+1 418 653 3249",
    "sg:postcode":"G1V 3M7",
    "sg:province":"QC",
    "sg:tags":[
        "dentist"
    ],
    "wof:name":"Lemieux, Brigitte DDS",
    "wof:placetype":"venue"
},
  "geometry": {"coordinates":[-71.28796386720001,46.7693939209],"type":"Point"}
}