{
  "type": "Feature",
  "properties": {
    "addr:full":"PO Box 3234 Nipawin SK S0E 1E0",
    "addr:housenumber":"po",
    "addr:postcode":"s0e 1e0",
    "addr:street":"Box 3234",
    "iso:country":"CA",
    "sg:address":"PO Box 3234",
    "sg:city":"Nipawin",
    "sg:classifiers":[
        {
            "category":"Building & Trades",
            "subcategory":"Plumbing",
            "type":"Services"
        }
    ],
    "sg:phone":"+1 306 862 4794",
    "sg:postcode":"S0E 1E0",
    "sg:province":"SK",
    "sg:tags":[
        "tank",
        "septic"
    ],
    "wof:name":"Town & Country Septic Svc",
    "wof:placetype":"venue"
},
  "geometry": {"coordinates":[-104.026283264,53.3567428589],"type":"Point"}
}