{
  "type": "Feature",
  "properties": {
    "addr:full":"PO Box 5361 STN Main Lacombe AB T4L 1X1",
    "addr:housenumber":"po",
    "addr:postcode":"t4l 1x1",
    "addr:street":"Box 5361 Stn Main",
    "iso:country":"CA",
    "sg:address":"PO Box 5361 STN Main",
    "sg:city":"Lacombe",
    "sg:classifiers":[
        {
            "category":"Manufacturing",
            "subcategory":"Glass & Minerals",
            "type":"Manufacturing & Wholesale Goods"
        }
    ],
    "sg:phone":"+1 403 782 6767",
    "sg:postcode":"T4L 1X1",
    "sg:province":"AB",
    "sg:tags":[
        "tank",
        "system",
        "septic"
    ],
    "wof:name":"Vans Concrete Ltd",
    "wof:placetype":"venue"
},
  "geometry": {"coordinates":[-113.73670199999999,52.463112],"type":"Point"}
}