{
  "type": "Feature",
  "properties": {
    "addr:full":"Vancouver BC V6G 1N6",
    "addr:postcode":"v6g 1n6",
    "iso:country":"CA",
    "sg:city":"Vancouver",
    "sg:classifiers":[
        {
            "category":"Real Estate",
            "subcategory":"Real Estate Operator",
            "type":"Services"
        }
    ],
    "sg:phone":"+1 604 682 2932",
    "sg:postcode":"V6G 1N6",
    "sg:province":"BC",
    "sg:tags":[
        "apartment"
    ],
    "wof:name":"Silhouette Apartments",
    "wof:placetype":"venue"
},
  "geometry": {"coordinates":[-123.142433,49.291641],"type":"Point"}
}