{
  "type": "Feature",
  "properties": {
    "addr:full":"560 Boul Cure-Labelle Sainte-Rose QC H7L 4V6",
    "addr:housenumber":"560",
    "addr:postcode":"h7l 4v6",
    "addr:street":"Boul Cure-Labelle",
    "iso:country":"CA",
    "sg:address":"560 Boul Cure-Labelle",
    "sg:city":"Sainte-Rose",
    "sg:classifiers":[
        {
            "category":"Banks & Credit Unions",
            "subcategory":"Bank",
            "type":"Services"
        }
    ],
    "sg:phone":"+1 450 625 2300",
    "sg:postcode":"H7L 4V6",
    "sg:province":"QC",
    "wof:name":"Banque Royale",
    "wof:placetype":"venue"
},
  "geometry": {"coordinates":[-73.78625488279999,45.5909004211],"type":"Point"}
}