{
  "type": "Feature",
  "properties": {
    "addr:full":"1000 Rue DE Bar-Le-Duc Sainte-Foy QC G1W 4X6",
    "addr:housenumber":"1000",
    "addr:postcode":"g1w 4x6",
    "addr:street":"Rue De Bar-Le-Duc",
    "iso:country":"CA",
    "sg:address":"1000 Rue DE Bar-Le-Duc",
    "sg:city":"Sainte-Foy",
    "sg:classifiers":[
        {
            "category":"Recreation",
            "type":"Entertainment"
        }
    ],
    "sg:phone":"+1 418 654 4304",
    "sg:postcode":"G1W 4X6",
    "sg:province":"QC",
    "sg:tags":[
        "center"
    ],
    "wof:name":"Centre DE Loisirs Saint",
    "wof:placetype":"venue"
},
  "geometry": {"coordinates":[-71.306274,46.766434],"type":"Point"}
}