{
  "type": "Feature",
  "properties": {
    "iso:country":"CA",
    "sg:city":"Ottawa",
    "sg:classifiers":[
        {
            "category":"Shopping",
            "subcategory":"Department Store",
            "type":"Retail Goods"
        }
    ],
    "sg:phone":"+1 613 521 8350",
    "sg:postcode":"K1V 9S1",
    "sg:province":"ON",
    "sg:tags":[
        "shop"
    ],
    "wof:name":"Discount King",
    "wof:placetype":"venue"
},
  "geometry": {"coordinates":[-75.67028,45.351223],"type":"Point"}
}