{
  "type": "Feature",
  "properties": {
    "addr:full":"4779 49 St Red Deer AB T4N 1T6",
    "addr:housenumber":"4779",
    "addr:postcode":"t4n 1t6",
    "addr:street":"49 St",
    "iso:country":"CA",
    "sg:address":"4779 49 St",
    "sg:city":"Red Deer",
    "sg:classifiers":[
        {
            "category":"Retail",
            "subcategory":"Funeral Services",
            "type":"Services"
        }
    ],
    "sg:phone":"+1 403 341 5181",
    "sg:postcode":"T4N 1T6",
    "sg:province":"AB",
    "sg:tags":[
        "director"
    ],
    "wof:name":"Personal Alternative Funeral",
    "wof:placetype":"venue"
},
  "geometry": {"coordinates":[-113.80793799999999,52.267849],"type":"Point"}
}