{
  "type": "Feature",
  "properties": {
    "addr:full":"21 Newhaven St Nepean ON K2G 0X7",
    "addr:housenumber":"21",
    "addr:postcode":"k2g 0x7",
    "addr:street":"Newhaven St",
    "iso:country":"CA",
    "sg:address":"21 Newhaven St",
    "sg:city":"Nepean",
    "sg:classifiers":[
        {
            "category":"Building & Trades",
            "subcategory":"Construction",
            "type":"Services"
        }
    ],
    "sg:phone":"+1 613 727 9574",
    "sg:postcode":"K2G 0X7",
    "sg:province":"ON",
    "sg:tags":[
        "home",
        "improvement"
    ],
    "wof:name":"Unique Construction",
    "wof:placetype":"venue"
},
  "geometry": {"coordinates":[-75.76128387449999,45.3269882202],"type":"Point"}
}