{
  "type": "Feature",
  "properties": {
    "addr:full":"Montreal QC H1Z 2Z8",
    "addr:postcode":"h1z 2z8",
    "iso:country":"CA",
    "sg:city":"Montreal",
    "sg:classifiers":[
        {
            "category":"Professional",
            "subcategory":"Advertising",
            "type":"Services"
        }
    ],
    "sg:phone":"+1 514 259 6647",
    "sg:postcode":"H1Z 2Z8",
    "sg:province":"QC",
    "wof:name":"Creation William",
    "wof:placetype":"venue"
},
  "geometry": {"coordinates":[-73.6215209961,45.5673370361],"type":"Point"}
}