{
  "type": "Feature",
  "properties": {
    "iso:country":"CA",
    "sg:address":"6158 Rue Vezina",
    "sg:city":"Saint-Emile",
    "sg:classifiers":[
        {
            "category":"Retail",
            "subcategory":"Auto Repair",
            "type":"Services"
        }
    ],
    "sg:phone":"+1 418 842 2255",
    "sg:postcode":"G3E 1P3",
    "sg:province":"QC",
    "sg:tags":[
        "repairing",
        "automobile"
    ],
    "wof:name":"Garage Jean-Yves Giguere Inc",
    "wof:placetype":"venue"
},
  "geometry": {"coordinates":[-71.343414,46.881298],"type":"Point"}
}