{
  "type": "Feature",
  "properties": {
    "addr:full":"2233 41st Ave W Vancouver BC V6M 2A3",
    "addr:housenumber":"2233",
    "addr:postcode":"v6m 2a3",
    "addr:street":"41St Ave W",
    "iso:country":"CA",
    "sg:address":"2233 41st Ave W",
    "sg:city":"Vancouver",
    "sg:classifiers":[
        {
            "category":"Food & Beverages",
            "subcategory":"Meat & Fish",
            "type":"Retail Goods"
        }
    ],
    "sg:phone":"+1 604 266 6911",
    "sg:postcode":"V6M 2A3",
    "sg:province":"BC",
    "wof:name":"Shaughnessy Fine Meats Ltd",
    "wof:placetype":"venue"
},
  "geometry": {"coordinates":[-123.158920288,49.2347450256],"type":"Point"}
}