{
  "type": "Feature",
  "properties": {
    "addr:full":"802 Ida Lane Kamloops BC V2B 6V1",
    "addr:housenumber":"802",
    "addr:postcode":"bc v2b 6v1",
    "addr:street":"Ida Lane",
    "iso:country":"CA",
    "sg:address":"802 Ida Lane",
    "sg:city":"Kamloops",
    "sg:classifiers":[
        {
            "category":"Manufacturing",
            "subcategory":"Printing",
            "type":"Manufacturing & Wholesale Goods"
        }
    ],
    "sg:phone":"+1 250 579 8214",
    "sg:postcode":"V2B 6V1",
    "sg:province":"BC",
    "sg:tags":[
        "screen"
    ],
    "wof:name":"Cannibal Screen Printing",
    "wof:placetype":"venue"
},
  "geometry": {"coordinates":[-120.340553,50.775986],"type":"Point"}
}