{
  "type": "Feature",
  "properties": {
    "addr:full":"Lachine QC H8R 1A3",
    "addr:postcode":"h8r 1a3",
    "iso:country":"CA",
    "sg:city":"Lachine",
    "sg:classifiers":[
        {
            "category":"Retail",
            "subcategory":"Auto Repair",
            "type":"Services"
        }
    ],
    "sg:phone":"+1 514 481 8835",
    "sg:postcode":"H8R 1A3",
    "sg:province":"QC",
    "sg:tags":[
        "repairing",
        "automobile",
        "body"
    ],
    "wof:name":"Carrosserie Camo",
    "wof:placetype":"venue"
},
  "geometry": {"coordinates":[-73.66275,45.448196],"type":"Point"}
}