{
  "type": "Feature",
  "properties": {
    "addr:full":"80 Plaza Dr Dundas ON L9H 4H4",
    "addr:housenumber":"80",
    "addr:postcode":"l9h 4h4",
    "addr:street":"Plaza Dr",
    "iso:country":"CA",
    "sg:address":"80 Plaza Dr",
    "sg:city":"Dundas",
    "sg:classifiers":[
        {
            "category":"Shopping",
            "subcategory":"Hobbies, Toys, & Games",
            "type":"Retail Goods"
        }
    ],
    "sg:phone":"+1 905 627 8909",
    "sg:postcode":"L9H 4H4",
    "sg:province":"ON",
    "wof:name":"Turtle Pond Toys",
    "wof:placetype":"venue"
},
  "geometry": {"coordinates":[-79.9431381226,43.2586288452],"type":"Point"}
}