{
  "type": "Feature",
  "properties": {
    "addr:full":"Coquitlam BC V3K 1A9",
    "addr:postcode":"v3k 1a9",
    "iso:country":"CA",
    "sg:city":"Coquitlam",
    "sg:classifiers":[
        {
            "category":"Manufacturing",
            "subcategory":"Signs",
            "type":"Manufacturing & Wholesale Goods"
        }
    ],
    "sg:phone":"+1 604 521 2254",
    "sg:postcode":"V3K 1A9",
    "sg:province":"BC",
    "wof:name":"Screenguild Signs Ltd",
    "wof:placetype":"venue"
},
  "geometry": {"coordinates":[-122.871994019,49.2359237671],"type":"Point"}
}