{
  "type": "Feature",
  "properties": {
    "addr:full":"5 Main St N Jarvis ON N0A 1J0",
    "addr:housenumber":"5",
    "addr:postcode":"n0a 1j0",
    "addr:street":"Main St N Jarvis",
    "iso:country":"CA",
    "sg:address":"5 Main St N",
    "sg:city":"Jarvis",
    "sg:classifiers":[
        {
            "category":"Restaurant",
            "type":"Food & Drink"
        }
    ],
    "sg:phone":"+1 519 587 2501",
    "sg:postcode":"N0A 1J0",
    "sg:province":"ON",
    "wof:name":"Golden Cactus Restaurant",
    "wof:placetype":"venue"
},
  "geometry": {"coordinates":[-80.11404400000001,42.884808],"type":"Point"}
}