{
  "type": "Feature",
  "properties": {
    "addr:full":"1500 Rue Raoul-Charette Joliette QC J6E 8S7",
    "addr:housenumber":"1500",
    "addr:postcode":"j6e 8s7",
    "addr:street":"Rue Raoul-Charette",
    "iso:country":"CA",
    "sg:address":"1500 Rue Raoul-Charette",
    "sg:city":"Joliette",
    "sg:classifiers":[
        {
            "category":"Autos & Motor Vehicles",
            "subcategory":"Automobile Sales",
            "type":"Retail Goods"
        }
    ],
    "sg:phone":"+1 450 759 0666",
    "sg:postcode":"J6E 8S7",
    "sg:province":"QC",
    "sg:tags":[
        "parts",
        "snowmobile",
        "accessory"
    ],
    "wof:name":"Jolautim Inc",
    "wof:placetype":"venue"
},
  "geometry": {"coordinates":[-73.446457,46.005768],"type":"Point"}
}