{
  "type": "Feature",
  "properties": {
    "iso:country":"CA",
    "sg:city":"Prince George",
    "sg:classifiers":[
        {
            "category":"Airline",
            "type":"Transportation"
        }
    ],
    "sg:phone":"+1 250 963 9611",
    "sg:postcode":"V2N 4M6",
    "sg:province":"BC",
    "sg:tags":[
        "aircraft",
        "rental",
        "charter",
        "leasing",
        "company"
    ],
    "wof:name":"Northern Thunderbird Air Inc",
    "wof:placetype":"venue"
},
  "geometry": {"coordinates":[-122.67692565900001,53.8800468445],"type":"Point"}
}