{
  "type": "Feature",
  "properties": {
    "iso:country":"CA",
    "sg:city":"Ottawa",
    "sg:classifiers":[
        {
            "category":"Health Services",
            "subcategory":"Health Practitioner",
            "type":"Services"
        }
    ],
    "sg:phone":"+1 613 247 1245",
    "sg:postcode":"K1V 1A4",
    "sg:province":"ON",
    "sg:tags":[
        "physiotherapist"
    ],
    "wof:name":"Hunt Club Physiotherapy Clinic",
    "wof:placetype":"venue"
},
  "geometry": {"coordinates":[-75.6464920044,45.3534927368],"type":"Point"}
}