{
  "type": "Feature",
  "properties": {
    "addr:full":"31 Ch DE Brebeuf Mont-Tremblant QC J8E 3B1",
    "addr:housenumber":"31",
    "addr:postcode":"j8e 3b1",
    "addr:street":"Ch De Brebeuf",
    "iso:country":"CA",
    "sg:address":"31 Ch DE Brebeuf",
    "sg:city":"Mont-Tremblant",
    "sg:classifiers":[
        {
            "category":"Recreation",
            "type":"Entertainment"
        }
    ],
    "sg:phone":"+1 819 425 8663",
    "sg:postcode":"J8E 3B1",
    "sg:province":"QC",
    "sg:tags":[
        "hall",
        "auditorium"
    ],
    "wof:name":"Centre DE Quilles St-Jovite",
    "wof:placetype":"venue"
},
  "geometry": {"coordinates":[-74.605003,46.11731],"type":"Point"}
}