{
  "type": "Feature",
  "properties": {
    "iso:country":"CA",
    "sg:address":"656 Front St",
    "sg:city":"Trenton",
    "sg:classifiers":[
        {
            "category":"Organizations",
            "subcategory":"Religious Organization",
            "type":"Services"
        }
    ],
    "sg:phone":"+1 613 392 0407",
    "sg:postcode":"K8V 4R8",
    "sg:province":"ON",
    "sg:tags":[
        "church"
    ],
    "wof:name":"North Trenton United Church",
    "wof:placetype":"venue"
},
  "geometry": {"coordinates":[-77.5964889526,44.1127357483],"type":"Point"}
}