{
  "type": "Feature",
  "properties": {
    "addr:full":"2060 Walkley Rd Ottawa ON K1G 3P5",
    "addr:housenumber":"2060",
    "addr:postcode":"k1g 3p5",
    "addr:street":"Walkley Rd",
    "iso:country":"CA",
    "sg:address":"2060 Walkley Rd",
    "sg:city":"Ottawa",
    "sg:classifiers":[
        {
            "category":"Professional",
            "subcategory":"Detective & Security Services",
            "type":"Services"
        }
    ],
    "sg:phone":"+1 613 238 5424",
    "sg:postcode":"K1G 3P5",
    "sg:province":"ON",
    "sg:tags":[
        "remote",
        "sensing",
        "analysis"
    ],
    "wof:name":"Radarsat International Inc",
    "wof:placetype":"venue"
},
  "geometry": {"coordinates":[-75.6273651123,45.3847236633],"type":"Point"}
}