{
  "type": "Feature",
  "properties": {
    "addr:full":"13 Rue Agincourt Kirkland QC H9J 2K3",
    "addr:housenumber":"13",
    "addr:postcode":"h9j 2k3",
    "addr:street":"Rue Agincourt",
    "iso:country":"CA",
    "sg:address":"13 Rue Agincourt",
    "sg:city":"Kirkland",
    "sg:classifiers":[
        {
            "category":"Manufacturing",
            "subcategory":"Printing",
            "type":"Manufacturing & Wholesale Goods"
        }
    ],
    "sg:phone":"+1 514 697 4352",
    "sg:postcode":"H9J 2K3",
    "sg:province":"QC",
    "sg:tags":[
        "publisher"
    ],
    "wof:name":"Communication Famille Inc",
    "wof:placetype":"venue"
},
  "geometry": {"coordinates":[-73.87767791749999,45.4390029907],"type":"Point"}
}