{
  "type": "Feature",
  "properties": {
    "addr:full":"Vanier QC G1M 3M2",
    "addr:postcode":"g1m 3m2",
    "iso:country":"CA",
    "sg:city":"Vanier",
    "sg:classifiers":[
        {
            "category":"Wholesale",
            "subcategory":"Electrical",
            "type":"Manufacturing & Wholesale Goods"
        }
    ],
    "sg:phone":"+1 418 527 8855",
    "sg:postcode":"G1M 3M2",
    "sg:province":"QC",
    "sg:tags":[
        "equipment",
        "electric",
        "supply"
    ],
    "wof:name":"Wesco Distribution-Canada Inc",
    "wof:placetype":"venue"
},
  "geometry": {"coordinates":[-71.2720336914,46.8274345398],"type":"Point"}
}