{
  "type": "Feature",
  "properties": {
    "addr:full":"174 Elgin St E Madoc ON K0K 2K0",
    "addr:housenumber":"174",
    "addr:postcode":"k0k 2k0",
    "addr:street":"Elgin St E",
    "iso:country":"CA",
    "sg:address":"174 Elgin St E",
    "sg:city":"Madoc",
    "sg:classifiers":[
        {
            "category":"Taxi",
            "type":"Transportation"
        }
    ],
    "sg:phone":"+1 613 473 4244",
    "sg:postcode":"K0K 2K0",
    "sg:province":"ON",
    "sg:tags":[
        "taxicab"
    ],
    "wof:name":"Don's Taxi",
    "wof:placetype":"venue"
},
  "geometry": {"coordinates":[-77.46569100000001,44.506115],"type":"Point"}
}