{
  "type": "Feature",
  "properties": {
    "addr:full":"2842 Main St Hillsborough NB E4H 2Y7",
    "addr:housenumber":"2842",
    "addr:postcode":"e4h 2y7",
    "addr:street":"Main St",
    "iso:country":"CA",
    "sg:address":"2842 Main St",
    "sg:city":"Hillsborough",
    "sg:classifiers":[
        {
            "category":"Shopping",
            "subcategory":"Catalog Store",
            "type":"Retail Goods"
        }
    ],
    "sg:phone":"+1 506 734 2936",
    "sg:postcode":"E4H 2Y7",
    "sg:province":"NB",
    "sg:tags":[
        "mail",
        "order",
        "internet"
    ],
    "wof:name":"Sears Canada Inc",
    "wof:placetype":"venue"
},
  "geometry": {"coordinates":[-64.647018,45.92506],"type":"Point"}
}