{
  "type": "Feature",
  "properties": {
    "addr:full":"7343 Tecumseh Rd E Pointe Aux Roches ON N0R 1N0",
    "addr:housenumber":"7343",
    "addr:postcode":"n0r 1n0",
    "addr:street":"Tecumseh Rd E Pointe Aux Roches",
    "iso:country":"CA",
    "sg:address":"7343 Tecumseh Rd E",
    "sg:city":"Pointe Aux Roches",
    "sg:classifiers":[
        {
            "category":"Education",
            "subcategory":"School",
            "type":"Public Place"
        }
    ],
    "sg:phone":"+1 519 798 3117",
    "sg:postcode":"N0R 1N0",
    "sg:province":"ON",
    "wof:name":"Our Lady of Annunciation",
    "wof:placetype":"venue"
},
  "geometry": {"coordinates":[-82.5452880859,42.3044891357],"type":"Point"}
}