{
  "type": "Feature",
  "properties": {
    "iso:country":"CA",
    "sg:address":"1745 St Laurent Blvd",
    "sg:city":"Ottawa",
    "sg:classifiers":[
        {
            "category":"Personal",
            "subcategory":"Beauty Salon",
            "type":"Services"
        }
    ],
    "sg:phone":"+1 613 738 0061",
    "sg:postcode":"K1G 3V4",
    "sg:province":"ON",
    "wof:name":"Freda's Family Hair Styling",
    "wof:placetype":"venue"
},
  "geometry": {"coordinates":[-75.6263961792,45.4052047729],"type":"Point"}
}