{
  "type": "Feature",
  "properties": {
    "addr:full":"330 Rue Principale Cowansville QC J2K 1J5",
    "addr:housenumber":"330",
    "addr:postcode":"j2k 1j5",
    "addr:street":"Rue Principale",
    "iso:country":"CA",
    "sg:address":"330 Rue Principale",
    "sg:city":"Cowansville",
    "sg:classifiers":[
        {
            "category":"Personal",
            "subcategory":"Beauty Salon",
            "type":"Services"
        }
    ],
    "sg:phone":"+1 450 266 5473",
    "sg:postcode":"J2K 1J5",
    "sg:province":"QC",
    "wof:name":"Coiffure Lise Unisex",
    "wof:placetype":"venue"
},
  "geometry": {"coordinates":[-72.73596999999999,45.209244],"type":"Point"}
}