{
  "type": "Feature",
  "properties": {
    "addr:full":"2404 46E Av Lachine QC H8T 2P3",
    "addr:housenumber":"2404",
    "addr:postcode":"h8t 2p3",
    "addr:street":"46E Av",
    "iso:country":"CA",
    "sg:address":"2404 46E Av",
    "sg:city":"Lachine",
    "sg:classifiers":[
        {
            "category":"Home & Garden",
            "subcategory":"Building Materials",
            "type":"Retail Goods"
        }
    ],
    "sg:phone":"+1 514 631 7210",
    "sg:postcode":"H8T 2P3",
    "sg:province":"QC",
    "sg:tags":[
        "type",
        "door"
    ],
    "wof:name":"Richard Stanver Ltee",
    "wof:placetype":"venue"
},
  "geometry": {"coordinates":[-73.719673,45.462547],"type":"Point"}
}