{
  "type": "Feature",
  "properties": {
    "addr:full":"566 Mcintosh Dr Prince Albert SK S6V 6T2",
    "addr:housenumber":"566",
    "addr:postcode":"s6v 6t2",
    "addr:street":"Mcintosh Dr",
    "iso:country":"CA",
    "sg:address":"566 Mcintosh Dr",
    "sg:city":"Prince Albert",
    "sg:classifiers":[
        {
            "category":"Education",
            "subcategory":"School",
            "type":"Public Place"
        }
    ],
    "sg:phone":"+1 306 763 7404",
    "sg:postcode":"S6V 6T2",
    "sg:province":"SK",
    "wof:name":"W J Berezowsky School",
    "wof:placetype":"venue"
},
  "geometry": {"coordinates":[-105.702461,53.204037],"type":"Point"}
}