{
  "type": "Feature",
  "properties": {
    "addr:full":"1002 14 St SW Calgary AB T3C 1B9",
    "addr:housenumber":"1002",
    "addr:postcode":"t3c 1b9",
    "addr:street":"14 St Sw",
    "iso:country":"CA",
    "sg:address":"1002 14 St SW",
    "sg:city":"Calgary",
    "sg:classifiers":[
        {
            "category":"Home & Garden",
            "subcategory":"Home Furnishings",
            "type":"Retail Goods"
        }
    ],
    "sg:phone":"+1 403 245 3396",
    "sg:postcode":"T3C 1B9",
    "sg:province":"AB",
    "sg:tags":[
        "lighting",
        "appliance"
    ],
    "wof:name":"Lighting Centre",
    "wof:placetype":"venue"
},
  "geometry": {"coordinates":[-114.09459699999999,51.04409],"type":"Point"}
}