{
  "type": "Feature",
  "properties": {
    "addr:full":"Saint-Joseph-Du-Lac QC J0N 1M0",
    "addr:postcode":"j0n 1m0",
    "iso:country":"CA",
    "sg:city":"Saint-Joseph-Du-Lac",
    "sg:classifiers":[
        {
            "category":"Organizations",
            "subcategory":"Professional Association",
            "type":"Services"
        }
    ],
    "sg:phone":"+1 450 473 2440",
    "sg:postcode":"J0N 1M0",
    "sg:province":"QC",
    "wof:name":"Comite D'Action Sociale",
    "wof:placetype":"venue"
},
  "geometry": {"coordinates":[-73.9790649414,45.5143089294],"type":"Point"}
}