{
  "type": "Feature",
  "properties": {
    "addr:full":"48 Southworth St N Welland ON L3B 1Y2",
    "addr:housenumber":"48",
    "addr:postcode":"l3b 1y2",
    "addr:street":"Southworth St N",
    "iso:country":"CA",
    "sg:address":"48 Southworth St N",
    "sg:city":"Welland",
    "sg:classifiers":[
        {
            "category":"Shopping",
            "subcategory":"Discount & Variety Stores",
            "type":"Retail Goods"
        }
    ],
    "sg:phone":"+1 905 732 7154",
    "sg:postcode":"L3B 1Y2",
    "sg:province":"ON",
    "wof:name":"Jerry's Place",
    "wof:placetype":"venue"
},
  "geometry": {"coordinates":[-79.23606872560001,42.9819564819],"type":"Point"}
}