{
  "type": "Feature",
  "properties": {
    "addr:full":"Onanole MB R0J 1N0",
    "addr:postcode":"r0j 1n0",
    "iso:country":"CA",
    "sg:city":"Onanole",
    "sg:classifiers":[
        {
            "category":"Travel",
            "subcategory":"Hotels & Motels",
            "type":"Entertainment"
        }
    ],
    "sg:phone":"+1 204 848 8428",
    "sg:postcode":"R0J 1N0",
    "sg:province":"MB",
    "sg:tags":[
        "breakfast",
        "accommodation",
        "bed"
    ],
    "wof:name":"Millennianne Eden Garden Inc",
    "wof:placetype":"venue"
},
  "geometry": {"coordinates":[-99.968597,50.622791],"type":"Point"}
}