{
  "type": "Feature",
  "properties": {
    "addr:full":"Calgary AB T3A 2L9",
    "addr:postcode":"t3a 2l9",
    "iso:country":"CA",
    "sg:city":"Calgary",
    "sg:classifiers":[
        {
            "category":"Restaurant",
            "type":"Food & Drink"
        }
    ],
    "sg:phone":"+1 403 288 7928",
    "sg:postcode":"T3A 2L9",
    "sg:province":"AB",
    "sg:tags":[
        "pizza"
    ],
    "wof:name":"Varsity Pizza",
    "wof:placetype":"venue"
},
  "geometry": {"coordinates":[-114.152596,51.093102],"type":"Point"}
}