{
  "type": "Feature",
  "properties": {
    "addr:full":"615 Taku Rd Heriot Bay BC V0P 1H0",
    "addr:housenumber":"615",
    "addr:postcode":"v0p 1h0",
    "addr:street":"Taku Rd",
    "iso:country":"CA",
    "sg:address":"615 Taku Rd",
    "sg:city":"Heriot Bay",
    "sg:classifiers":[
        {
            "category":"Shopping",
            "subcategory":"Bicycles & Sporting Goods",
            "type":"Retail Goods"
        }
    ],
    "sg:phone":"+1 250 285 3627",
    "sg:postcode":"V0P 1H0",
    "sg:province":"BC",
    "wof:name":"Island Cycle",
    "wof:placetype":"venue"
},
  "geometry": {"coordinates":[-125.201438904,50.094367981],"type":"Point"}
}