{
  "type": "Feature",
  "properties": {
    "addr:full":"752 Kingsway Vancouver BC V5V 3C1",
    "addr:housenumber":"752",
    "addr:postcode":"v5v 3c1",
    "addr:street":"Kingsway",
    "iso:country":"CA",
    "sg:address":"752 Kingsway",
    "sg:city":"Vancouver",
    "sg:classifiers":[
        {
            "category":"Real Estate",
            "subcategory":"Real Estate Operator",
            "type":"Services"
        }
    ],
    "sg:phone":"+1 604 708 2283",
    "sg:postcode":"V5V 3C1",
    "sg:province":"BC",
    "sg:tags":[
        "apartment"
    ],
    "wof:name":"Kingsgate Manor",
    "wof:placetype":"venue"
},
  "geometry": {"coordinates":[-123.088356018,49.2558364868],"type":"Point"}
}