{
  "type": "Feature",
  "properties": {
    "iso:country":"CA",
    "sg:address":"3350 Langstaff Rd",
    "sg:city":"Concord",
    "sg:classifiers":[
        {
            "category":"Home & Garden",
            "subcategory":"Building Materials",
            "type":"Retail Goods"
        }
    ],
    "sg:phone":"+1 905 669 9335",
    "sg:postcode":"L4K 4Z6",
    "sg:province":"ON",
    "sg:tags":[
        "door"
    ],
    "wof:name":"Dsh",
    "wof:placetype":"venue"
},
  "geometry": {"coordinates":[-79.5387268066,43.8104400635],"type":"Point"}
}