{
  "type": "Feature",
  "properties": {
    "iso:country":"CA",
    "sg:city":"Saskatoon",
    "sg:classifiers":[
        {
            "category":"Health Services",
            "subcategory":"Medical Lab",
            "type":"Services"
        }
    ],
    "sg:phone":"+1 306 244 2078",
    "sg:postcode":"S7K 1L8",
    "sg:province":"SK",
    "wof:name":"Acry-Dent Total Denture Svc",
    "wof:placetype":"venue"
},
  "geometry": {"coordinates":[-106.662765503,52.127532959],"type":"Point"}
}