{
  "type": "Feature",
  "properties": {
    "addr:full":"2355 Nicholson St S Prince George BC V2N 1W1",
    "addr:housenumber":"2355",
    "addr:postcode":"v2n 1w1",
    "addr:street":"Nicholson St S",
    "iso:country":"CA",
    "sg:address":"2355 Nicholson St S",
    "sg:city":"Prince George",
    "sg:classifiers":[
        {
            "category":"Retail",
            "subcategory":"Repair Shop",
            "type":"Services"
        }
    ],
    "sg:phone":"+1 250 563 4414",
    "sg:postcode":"V2N 1W1",
    "sg:province":"BC",
    "sg:tags":[
        "lock",
        "locksmith"
    ],
    "wof:name":"Trident Mobile Locksmiths Ltd",
    "wof:placetype":"venue"
},
  "geometry": {"coordinates":[-122.789031982,53.9002723694],"type":"Point"}
}