{
  "type": "Feature",
  "properties": {
    "iso:country":"CA",
    "sg:address":"67 Lakeshore Rd W",
    "sg:city":"Oakville",
    "sg:classifiers":[
        {
            "category":"Real Estate",
            "subcategory":"Real Estate Agent",
            "type":"Services"
        }
    ],
    "sg:phone":"+1 905 338 9000",
    "sg:postcode":"L6K 1C9",
    "sg:province":"ON",
    "wof:name":"Aboutowne Realty Corp",
    "wof:placetype":"venue"
},
  "geometry": {"coordinates":[-79.674118042,43.4404792786],"type":"Point"}
}