{
  "type": "Feature",
  "properties": {
    "addr:full":"10114 101st St Lac LA Biche AB T0A 2C0",
    "addr:housenumber":"10114",
    "addr:postcode":"t0a 2c0",
    "addr:street":"101St St;La Biche",
    "iso:country":"CA",
    "sg:address":"10114 101st St",
    "sg:city":"Lac LA Biche",
    "sg:classifiers":[
        {
            "category":"Food & Beverages",
            "subcategory":"Bakery",
            "type":"Retail Goods"
        }
    ],
    "sg:phone":"+1 780 623 4234",
    "sg:postcode":"T0A 2C0",
    "sg:province":"AB",
    "sg:tags":[
        "grocer"
    ],
    "wof:name":"Lac LA Biche Iga Foods Store",
    "wof:placetype":"venue"
},
  "geometry": {"coordinates":[-111.976395,54.770874],"type":"Point"}
}