{
  "type": "Feature",
  "properties": {
    "addr:full":"131 Shoemaker St Kitchener ON N2E 3B5",
    "addr:housenumber":"131",
    "addr:postcode":"n2e 3b5",
    "addr:street":"Shoemaker St",
    "iso:country":"CA",
    "sg:address":"131 Shoemaker St",
    "sg:city":"Kitchener",
    "sg:classifiers":[
        {
            "category":"Wholesale",
            "subcategory":"Books, Periodicals, & Newspapers",
            "type":"Manufacturing & Wholesale Goods"
        }
    ],
    "sg:phone":"+1 519 746 4420",
    "sg:postcode":"N2E 3B5",
    "sg:province":"ON",
    "sg:tags":[
        "dealer"
    ],
    "wof:name":"Library Services Ctr",
    "wof:placetype":"venue"
},
  "geometry": {"coordinates":[-80.469673,43.406887],"type":"Point"}
}