{
  "type": "Feature",
  "properties": {
    "addr:full":"4172 Dundas St W Etobicoke ON M8X 1X3",
    "addr:housenumber":"4172",
    "addr:postcode":"m8x 1x3",
    "addr:street":"Dundas St W",
    "iso:country":"CA",
    "sg:address":"4172 Dundas St W",
    "sg:city":"Etobicoke",
    "sg:classifiers":[
        {
            "category":"Professional",
            "subcategory":"Engineering",
            "type":"Services"
        }
    ],
    "sg:phone":"+1 416 239 7632",
    "sg:postcode":"M8X 1X3",
    "sg:province":"ON",
    "sg:tags":[
        "engineer"
    ],
    "wof:name":"Fletcher Associates",
    "wof:placetype":"venue"
},
  "geometry": {"coordinates":[-79.50939200000001,43.661121],"type":"Point"}
}