{
  "type": "Feature",
  "properties": {
    "addr:full":"101 Rue Du Ciel Bromont QC J2L 2X4",
    "addr:housenumber":"101",
    "addr:postcode":"j2l 2x4",
    "addr:street":"Rue Du Ciel",
    "iso:country":"CA",
    "sg:address":"101 Rue Du Ciel",
    "sg:city":"Bromont",
    "sg:classifiers":[
        {
            "category":"Professional",
            "subcategory":"Engineering",
            "type":"Services"
        }
    ],
    "sg:phone":"+1 450 534 0622",
    "sg:postcode":"J2L 2X4",
    "sg:province":"QC",
    "sg:tags":[
        "engineer"
    ],
    "wof:name":"Laboratoire Richelieu-Estrie",
    "wof:placetype":"venue"
},
  "geometry": {"coordinates":[-72.73056800000001,45.296547],"type":"Point"}
}