{
  "type": "Feature",
  "properties": {
    "iso:country":"CA",
    "sg:address":"92 Merit Cres",
    "sg:city":"West St Paul",
    "sg:classifiers":[
        {
            "category":"Building & Trades",
            "subcategory":"Construction",
            "type":"Services"
        }
    ],
    "sg:phone":"+1 204 334 4715",
    "sg:postcode":"R2P 2W5",
    "sg:province":"MB",
    "sg:tags":[
        "maker",
        "cabinet"
    ],
    "wof:name":"Commercial Specialties",
    "wof:placetype":"venue"
},
  "geometry": {"coordinates":[-97.1159286499,49.982837677],"type":"Point"}
}