{
  "type": "Feature",
  "properties": {
    "addr:full":"2177 Ch DE Chambly Longueuil QC J4J 3Z2",
    "addr:housenumber":"2177",
    "addr:postcode":"j4j 3z2",
    "addr:street":"Ch De Chambly",
    "iso:country":"CA",
    "sg:address":"2177 Ch DE Chambly",
    "sg:city":"Longueuil",
    "sg:classifiers":[
        {
            "category":"Restaurant",
            "type":"Food & Drink"
        }
    ],
    "sg:phone":"+1 450 468 7000",
    "sg:postcode":"J4J 3Z2",
    "sg:province":"QC",
    "sg:tags":[
        "pizza"
    ],
    "wof:name":"Allo Pizza",
    "wof:placetype":"venue"
},
  "geometry": {"coordinates":[-73.476028,45.527145],"type":"Point"}
}