{
  "type": "Feature",
  "properties": {
    "addr:full":"5810 99 St NW Edmonton AB T6E 3N9",
    "addr:housenumber":"5810",
    "addr:postcode":"t6e 3n9",
    "addr:street":"99 St Nw",
    "iso:country":"CA",
    "sg:address":"5810 99 St NW",
    "sg:city":"Edmonton",
    "sg:classifiers":[
        {
            "category":"Retail",
            "subcategory":"Auto Repair",
            "type":"Services"
        }
    ],
    "sg:phone":"+1 780 435 3896",
    "sg:postcode":"T6E 3N9",
    "sg:province":"AB",
    "sg:tags":[
        "repairing",
        "tire"
    ],
    "wof:name":"Kal Tire",
    "wof:placetype":"venue"
},
  "geometry": {"coordinates":[-113.486434937,53.4940223694],"type":"Point"}
}