{
  "type": "Feature",
  "properties": {
    "iso:country":"CA",
    "sg:city":"Scarborough",
    "sg:classifiers":[
        {
            "category":"Health Services",
            "subcategory":"Health Practitioner",
            "type":"Services"
        }
    ],
    "sg:phone":"+1 416 284 8973",
    "sg:postcode":"M1B 5M5",
    "sg:province":"ON",
    "sg:tags":[
        "physiotherapist"
    ],
    "wof:name":"Rylander Physiotherapy Ctr",
    "wof:placetype":"venue"
},
  "geometry": {"coordinates":[-79.152206,43.797829],"type":"Point"}
}