{
  "type": "Feature",
  "properties": {
    "iso:country":"CA",
    "sg:address":"973 Boul Hamel",
    "sg:city":"Saint-Felicien",
    "sg:classifiers":[
        {
            "category":"Government",
            "subcategory":"Office",
            "type":"Public Place"
        }
    ],
    "sg:phone":"+1 418 679 0252",
    "sg:postcode":"G8K 2E3",
    "sg:province":"QC",
    "sg:tags":[
        "village"
    ],
    "wof:name":"St-Felicien Garage Municipal",
    "wof:placetype":"venue"
},
  "geometry": {"coordinates":[-72.4479293823,48.6424255371],"type":"Point"}
}