{
  "type": "Feature",
  "properties": {
    "addr:full":"2 Montee Des Bouleaux Saint-Constant QC J5A 2N5",
    "addr:housenumber":"2",
    "addr:postcode":"j5a 2n5",
    "addr:street":"Montee Des Bouleaux",
    "iso:country":"CA",
    "sg:address":"2 Montee Des Bouleaux",
    "sg:city":"Saint-Constant",
    "sg:classifiers":[
        {
            "category":"Recreation",
            "type":"Entertainment"
        }
    ],
    "sg:phone":"+1 450 635 9591",
    "sg:postcode":"J5A 2N5",
    "sg:province":"QC",
    "sg:tags":[
        "martial",
        "arts",
        "instruction"
    ],
    "wof:name":"Centre DE Karate Kjs",
    "wof:placetype":"venue"
},
  "geometry": {"coordinates":[-73.5640029907,45.3791503906],"type":"Point"}
}