{
  "type": "Feature",
  "properties": {
    "iso:country":"CA",
    "sg:city":"Richmond",
    "sg:classifiers":[
        {
            "category":"Retail",
            "subcategory":"Auto Repair",
            "type":"Services"
        }
    ],
    "sg:phone":"+1 604 273 2961",
    "sg:postcode":"V6X 2P9",
    "sg:province":"BC",
    "sg:tags":[
        "repairing",
        "cylinder"
    ],
    "wof:name":"N W Engineering Ltd",
    "wof:placetype":"venue"
},
  "geometry": {"coordinates":[-123.098907471,49.1956634521],"type":"Point"}
}