{
  "type": "Feature",
  "properties": {
    "addr:full":"Concord ON L4K 2Z7",
    "addr:postcode":"l4k 2z7",
    "iso:country":"CA",
    "sg:city":"Concord",
    "sg:classifiers":[
        {
            "category":"Retail",
            "subcategory":"Auto Repair",
            "type":"Services"
        }
    ],
    "sg:phone":"+1 905 738 7011",
    "sg:postcode":"L4K 2Z7",
    "sg:province":"ON",
    "sg:tags":[
        "repairing",
        "automobile"
    ],
    "wof:name":"Staffern Auto Repair",
    "wof:placetype":"venue"
},
  "geometry": {"coordinates":[-79.4852676392,43.8232345581],"type":"Point"}
}