{
  "type": "Feature",
  "properties": {
    "addr:full":"West Vancouver BC V7V 1H9",
    "addr:postcode":"v7v 1h9",
    "iso:country":"CA",
    "sg:city":"West Vancouver",
    "sg:classifiers":[
        {
            "category":"Retail",
            "subcategory":"Veterinary Services",
            "type":"Services"
        }
    ],
    "sg:phone":"+1 604 922 2604",
    "sg:postcode":"V7V 1H9",
    "sg:province":"BC",
    "sg:tags":[
        "veterinarian"
    ],
    "wof:name":"Cat Hospital",
    "wof:placetype":"venue"
},
  "geometry": {"coordinates":[-123.15818786600001,49.3286705017],"type":"Point"}
}