{
  "type": "Feature",
  "properties": {
    "addr:full":"299 Rue Principale Ange-Gardien QC J0E 1E0",
    "addr:housenumber":"299",
    "addr:postcode":"j0e 1e0",
    "addr:street":"Rue Principale",
    "iso:country":"CA",
    "sg:address":"299 Rue Principale",
    "sg:city":"Ange-Gardien",
    "sg:classifiers":[
        {
            "category":"Professional",
            "subcategory":"Accounting & Tax Preparation",
            "type":"Services"
        }
    ],
    "sg:phone":"+1 450 293 5483",
    "sg:postcode":"J0E 1E0",
    "sg:province":"QC",
    "sg:tags":[
        "consultant",
        "accountant"
    ],
    "wof:name":"Beaudry Levesque",
    "wof:placetype":"venue"
},
  "geometry": {"coordinates":[-72.9361190796,45.354675293],"type":"Point"}
}