{
  "type": "Feature",
  "properties": {
    "addr:full":"137 Avenue C S Saskatoon SK S7M 1M9",
    "addr:housenumber":"137",
    "addr:postcode":"s7m 1m9",
    "addr:street":"Avenue",
    "iso:country":"CA",
    "sg:address":"137 Avenue C S",
    "sg:city":"Saskatoon",
    "sg:classifiers":[
        {
            "category":"Retail",
            "subcategory":"Auto Repair",
            "type":"Services"
        }
    ],
    "sg:phone":"+1 306 244 6088",
    "sg:postcode":"S7M 1M9",
    "sg:province":"SK",
    "sg:tags":[
        "repairing",
        "automobile"
    ],
    "wof:name":"Import Auto Svc Ltd",
    "wof:placetype":"venue"
},
  "geometry": {"coordinates":[-106.673683166,52.1286239624],"type":"Point"}
}