{
  "type": "Feature",
  "properties": {
    "iso:country":"CA",
    "sg:address":"39 Main St",
    "sg:city":"Corner Brook",
    "sg:classifiers":[
        {
            "category":"Building & Trades",
            "subcategory":"Plumbing",
            "type":"Services"
        }
    ],
    "sg:phone":"+1 709 634 7715",
    "sg:postcode":"A2H 1C5",
    "sg:province":"NL",
    "sg:tags":[
        "heat",
        "pump",
        "exchanger"
    ],
    "wof:name":"Furnace Man Ltd",
    "wof:placetype":"venue"
},
  "geometry": {"coordinates":[-57.9463844299,48.9521408081],"type":"Point"}
}