{
  "type": "Feature",
  "properties": {
    "addr:full":"1408 7 St Nisku AB T9E 7P9",
    "addr:housenumber":"1408 7",
    "addr:postcode":"t9e 7p9",
    "addr:street":"St",
    "iso:country":"CA",
    "sg:address":"1408 7 St",
    "sg:city":"Nisku",
    "sg:classifiers":[
        {
            "category":"Manufacturing",
            "subcategory":"Rubber & Plastics",
            "type":"Manufacturing & Wholesale Goods"
        }
    ],
    "sg:phone":"+1 780 955 3525",
    "sg:postcode":"T9E 7P9",
    "sg:province":"AB",
    "wof:name":"Wood Composite Technologies",
    "wof:placetype":"venue"
},
  "geometry": {"coordinates":[-113.521805,53.317997],"type":"Point"}
}