{
  "type": "Feature",
  "properties": {
    "addr:full":"115 Hussey Dr St. John's NL A1A 4Y6",
    "addr:housenumber":"115",
    "addr:postcode":"a1a 4y6",
    "addr:street":"Hussey Dr",
    "iso:country":"CA",
    "sg:address":"115 Hussey Dr",
    "sg:city":"St. John's",
    "sg:classifiers":[
        {
            "category":"Building & Trades",
            "subcategory":"Construction",
            "type":"Services"
        }
    ],
    "sg:phone":"+1 709 722 9576",
    "sg:postcode":"A1A 4Y6",
    "sg:province":"NL",
    "sg:tags":[
        "janitor",
        "contractor"
    ],
    "wof:name":"Bursey Cleaners Ltd",
    "wof:placetype":"venue"
},
  "geometry": {"coordinates":[-52.7278060913,47.6136741638],"type":"Point"}
}