{
  "type": "Feature",
  "properties": {
    "addr:full":"120 Rue Du Roy #A Deschambault QC G0A 1S0",
    "addr:housenumber":"120",
    "addr:postcode":"g0a 1s0",
    "addr:street":"Rue Du Roy # A Deschambault",
    "iso:country":"CA",
    "sg:address":"120 Rue Du Roy #A",
    "sg:city":"Deschambault",
    "sg:classifiers":[
        {
            "category":"Farming",
            "subcategory":"Farm & Veterinary Services",
            "type":"Manufacturing & Wholesale Goods"
        }
    ],
    "sg:phone":"+1 418 286 4789",
    "sg:postcode":"G0A 1S0",
    "sg:province":"QC",
    "sg:tags":[
        "breeder",
        "livestock"
    ],
    "wof:name":"Centre DE Developpement Du",
    "wof:placetype":"venue"
},
  "geometry": {"coordinates":[-71.785439,46.671844],"type":"Point"}
}