{
  "type": "Feature",
  "properties": {
    "addr:full":"Calgary AB T3A 5R8",
    "addr:postcode":"t3a 5r8",
    "iso:country":"CA",
    "sg:city":"Calgary",
    "sg:classifiers":[
        {
            "category":"Shopping",
            "subcategory":"Musical Instruments",
            "type":"Retail Goods"
        }
    ],
    "sg:phone":"+1 403 202 2414",
    "sg:postcode":"T3A 5R8",
    "sg:province":"AB",
    "sg:tags":[
        "music",
        "dealer"
    ],
    "wof:name":"Rideau Music Ltd",
    "wof:placetype":"venue"
},
  "geometry": {"coordinates":[-114.159065247,51.106464386],"type":"Point"}
}