{
  "type": "Feature",
  "properties": {
    "addr:full":"54 Sykes St S Meaford ON N4L 1E3",
    "addr:housenumber":"54",
    "addr:postcode":"n4l 1e3",
    "addr:street":"Sykes St S",
    "iso:country":"CA",
    "sg:address":"54 Sykes St S",
    "sg:city":"Meaford",
    "sg:classifiers":[
        {
            "category":"Professional",
            "subcategory":"Lawyer & Legal Services",
            "type":"Services"
        }
    ],
    "sg:phone":"+1 519 538 9929",
    "sg:postcode":"N4L 1E3",
    "sg:province":"ON",
    "sg:tags":[
        "attorney"
    ],
    "wof:name":"Allen, Carol",
    "wof:placetype":"venue"
},
  "geometry": {"coordinates":[-80.590919,44.604736],"type":"Point"}
}