{
  "type": "Feature",
  "properties": {
    "addr:full":"Fort Nelson BC V0C 1R0",
    "addr:postcode":"bc v0c 1r0",
    "iso:country":"CA",
    "sg:city":"Fort Nelson",
    "sg:classifiers":[
        {
            "category":"Freight",
            "type":"Transportation"
        }
    ],
    "sg:phone":"+1 250 774 7403",
    "sg:postcode":"V0C 1R0",
    "sg:province":"BC",
    "sg:tags":[
        "trucking"
    ],
    "wof:name":"Old Fort Svc",
    "wof:placetype":"venue"
},
  "geometry": {"coordinates":[-122.70848100000001,58.800217],"type":"Point"}
}