{
  "type": "Feature",
  "properties": {
    "addr:full":"Burnaby BC V5J 3N3",
    "addr:postcode":"v5j 3n3",
    "iso:country":"CA",
    "sg:city":"Burnaby",
    "sg:classifiers":[
        {
            "category":"Wholesale",
            "subcategory":"Plants",
            "type":"Manufacturing & Wholesale Goods"
        }
    ],
    "sg:phone":"+1 604 435 3755",
    "sg:postcode":"V5J 3N3",
    "sg:province":"BC",
    "sg:tags":[
        "florist"
    ],
    "wof:name":"Five Star Flower Wholesale Ltd",
    "wof:placetype":"venue"
},
  "geometry": {"coordinates":[-123.01496899999999,49.207222],"type":"Point"}
}