{
  "type": "Feature",
  "properties": {
    "addr:full":"2272 Lawrence Ave E Scarborough ON M1P 2P9",
    "addr:housenumber":"2272",
    "addr:postcode":"m1p 2p9",
    "addr:street":"Lawrence Ave E",
    "iso:country":"CA",
    "sg:address":"2272 Lawrence Ave E",
    "sg:city":"Scarborough",
    "sg:classifiers":[
        {
            "category":"Restaurant",
            "type":"Food & Drink"
        }
    ],
    "sg:phone":"+1 416 751 1200",
    "sg:postcode":"M1P 2P9",
    "sg:province":"ON",
    "wof:name":"Pizza Nova Dining Rooms",
    "wof:placetype":"venue"
},
  "geometry": {"coordinates":[-79.2784729004,43.7489509583],"type":"Point"}
}