{
  "type": "Feature",
  "properties": {
    "addr:full":"184 Rue Principale Grenville QC J0V 1J0",
    "addr:housenumber":"184",
    "addr:postcode":"j0v 1j0",
    "addr:street":"Rue Principale",
    "iso:country":"CA",
    "sg:address":"184 Rue Principale",
    "sg:city":"Grenville",
    "sg:classifiers":[
        {
            "category":"Education",
            "subcategory":"School",
            "type":"Public Place"
        }
    ],
    "sg:phone":"+1 819 242 2852",
    "sg:postcode":"J0V 1J0",
    "sg:province":"QC",
    "wof:name":"Sir Wilfrid Laurier School Brd",
    "wof:placetype":"venue"
},
  "geometry": {"coordinates":[-74.599251,45.632088],"type":"Point"}
}