{
  "type": "Feature",
  "properties": {
    "addr:full":"40 Rue Saint-Sacrement O # 201 Alma QC G8B 4N3",
    "addr:housenumber":"40",
    "addr:postcode":"g8b 4n3",
    "addr:street":"Rue Saint-Sacrement O # 201",
    "iso:country":"CA",
    "sg:address":"40 Rue Saint-Sacrement O # 201",
    "sg:city":"Alma",
    "sg:classifiers":[
        {
            "category":"Health Services",
            "subcategory":"Doctor",
            "type":"Services"
        }
    ],
    "sg:phone":"+1 418 668 3484",
    "sg:postcode":"G8B 4N3",
    "sg:province":"QC",
    "sg:tags":[
        "dentist"
    ],
    "wof:name":"Beaumont, Christian DDS",
    "wof:placetype":"venue"
},
  "geometry": {"coordinates":[-71.639557,48.552784],"type":"Point"}
}