{
  "type": "Feature",
  "properties": {
    "iso:country":"CA",
    "sg:city":"London",
    "sg:classifiers":[
        {
            "category":"Shopping",
            "subcategory":"Shoes",
            "type":"Retail Goods"
        }
    ],
    "sg:phone":"+1 519 657 5019",
    "sg:postcode":"N6K 1M6",
    "sg:province":"ON",
    "wof:name":"Kidz Feet",
    "wof:placetype":"venue"
},
  "geometry": {"coordinates":[-81.289536,42.948803],"type":"Point"}
}