{
  "type": "Feature",
  "properties": {
    "addr:full":"130 Principale Saint-Cleophas QC G0J 3N0",
    "addr:housenumber":"130",
    "addr:postcode":"g0j 3n0",
    "addr:street":"Principale Saint-Cleophas",
    "iso:country":"CA",
    "sg:address":"130 Principale",
    "sg:city":"Saint-Cleophas",
    "sg:classifiers":[
        {
            "category":"Building & Trades",
            "subcategory":"Construction",
            "type":"Services"
        }
    ],
    "sg:phone":"+1 418 536 3098",
    "sg:postcode":"G0J 3N0",
    "sg:province":"QC",
    "sg:tags":[
        "general",
        "contractor"
    ],
    "wof:name":"Boulanger Clement",
    "wof:placetype":"venue"
},
  "geometry": {"coordinates":[-67.764107,48.479191],"type":"Point"}
}