{
  "type": "Feature",
  "properties": {
    "addr:full":"3016 Arlington Ave Saskatoon SK S7J 2J9",
    "addr:housenumber":"3016",
    "addr:postcode":"s7j 2j9",
    "addr:street":"Arlington Ave",
    "iso:country":"CA",
    "sg:address":"3016 Arlington Ave",
    "sg:city":"Saskatoon",
    "sg:classifiers":[
        {
            "category":"Restaurant",
            "type":"Food & Drink"
        }
    ],
    "sg:phone":"+1 306 374 7525",
    "sg:postcode":"S7J 2J9",
    "sg:province":"SK",
    "wof:name":"Kelly's Kafe",
    "wof:placetype":"venue"
},
  "geometry": {"coordinates":[-106.61425781200001,52.0945510864],"type":"Point"}
}