{
  "type": "Feature",
  "properties": {
    "addr:full":"1769 Britannia Rd E # 6 Mississauga ON L4W 4E2",
    "addr:housenumber":"1769",
    "addr:postcode":"l4w 4e2",
    "addr:street":"Britannia Rd E # 6",
    "iso:country":"CA",
    "sg:address":"1769 Britannia Rd E # 6",
    "sg:city":"Mississauga",
    "sg:classifiers":[
        {
            "category":"Wholesale",
            "subcategory":"Auto Parts",
            "type":"Manufacturing & Wholesale Goods"
        }
    ],
    "sg:phone":"+1 905 670 9011",
    "sg:postcode":"L4W 4E2",
    "sg:province":"ON",
    "sg:tags":[
        "automobile",
        "rebuilt"
    ],
    "wof:name":"C V Joints Rebuilding",
    "wof:placetype":"venue"
},
  "geometry": {"coordinates":[-79.6404342651,43.6618995667],"type":"Point"}
}