{
  "type": "Feature",
  "properties": {
    "addr:full":"41805 Winthrop Rd Londesborough ON N0M 2H0",
    "addr:housenumber":"41805",
    "addr:postcode":"n0m 2h0",
    "addr:street":"Winthrop Rd",
    "iso:country":"CA",
    "sg:address":"41805 Winthrop Rd",
    "sg:city":"Londesborough",
    "sg:classifiers":[
        {
            "category":"Manufacturing",
            "subcategory":"Motor Vehicles & Parts",
            "type":"Manufacturing & Wholesale Goods"
        }
    ],
    "sg:phone":"+1 519 527 0078",
    "sg:postcode":"N0M 2H0",
    "sg:province":"ON",
    "sg:tags":[
        "automobile",
        "wrecking"
    ],
    "wof:name":"Anderson Salvage",
    "wof:placetype":"venue"
},
  "geometry": {"coordinates":[-81.47942399999999,43.699009],"type":"Point"}
}