{
  "type": "Feature",
  "properties": {
    "iso:country":"CA",
    "sg:city":"Hagersville",
    "sg:classifiers":[
        {
            "category":"Education",
            "subcategory":"School",
            "type":"Public Place"
        }
    ],
    "sg:phone":"+1 905 768 3222",
    "sg:postcode":"N0A 1H0",
    "sg:province":"ON",
    "wof:name":"Lloyd S King Elementary School",
    "wof:placetype":"venue"
},
  "geometry": {"coordinates":[-80.05113220210001,42.9626541138],"type":"Point"}
}