{
  "type": "Feature",
  "properties": {
    "addr:full":"2350 Stevenage Dr # 23 Ottawa ON K1G 3W3",
    "addr:housenumber":"2350",
    "addr:postcode":"k1g 3w3",
    "addr:street":"Stevenage Dr # 23",
    "iso:country":"CA",
    "sg:address":"2350 Stevenage Dr # 23",
    "sg:city":"Ottawa",
    "sg:classifiers":[
        {
            "category":"Retail",
            "subcategory":"Auto Repair",
            "type":"Services"
        }
    ],
    "sg:phone":"+1 613 738 2233",
    "sg:postcode":"K1G 3W3",
    "sg:province":"ON",
    "sg:tags":[
        "repairing",
        "automobile"
    ],
    "wof:name":"Tokoyo Joe Automotive",
    "wof:placetype":"venue"
},
  "geometry": {"coordinates":[-75.60876500000001,45.379948],"type":"Point"}
}