{
  "type": "Feature",
  "properties": {
    "addr:full":"5767 Boul Des Grandes-Prairies Saint-Leonard QC H1R 1B3",
    "addr:housenumber":"5767",
    "addr:postcode":"h1r 1b3",
    "addr:street":"Boul Des Grandes-Prairies",
    "iso:country":"CA",
    "sg:address":"5767 Boul Des Grandes-Prairies",
    "sg:city":"Saint-Leonard",
    "sg:classifiers":[
        {
            "category":"Freight",
            "type":"Transportation"
        }
    ],
    "sg:phone":"+1 514 323 5514",
    "sg:postcode":"H1R 1B3",
    "sg:province":"QC",
    "sg:tags":[
        "courier"
    ],
    "wof:name":"Purolator Courrier Ltee",
    "wof:placetype":"venue"
},
  "geometry": {"coordinates":[-73.6129150391,45.5979995728],"type":"Point"}
}