{
  "type": "Feature",
  "properties": {
    "addr:full":"185 Av Godefroy Becancour QC G9H 1S1",
    "addr:housenumber":"185",
    "addr:postcode":"g9h 1s1",
    "addr:street":"Av Godefroy Becancour",
    "iso:country":"CA",
    "sg:address":"185 Av Godefroy",
    "sg:city":"Becancour",
    "sg:classifiers":[
        {
            "category":"Personal",
            "type":"Services"
        }
    ],
    "sg:phone":"+1 819 233 4231",
    "sg:postcode":"G9H 1S1",
    "sg:province":"QC",
    "sg:tags":[
        "therapist",
        "massage"
    ],
    "wof:name":"Centre DE Massotherapie Sylvie",
    "wof:placetype":"venue"
},
  "geometry": {"coordinates":[-72.54368599999999,46.30785],"type":"Point"}
}