{
  "type": "Feature",
  "properties": {
    "iso:country":"CA",
    "sg:city":"Ottawa",
    "sg:classifiers":[
        {
            "category":"Organizations",
            "subcategory":"Non-profit Organization",
            "type":"Services"
        }
    ],
    "sg:phone":"+1 613 723 1900",
    "sg:postcode":"K2C 3N6",
    "sg:province":"ON",
    "sg:tags":[
        "addiction",
        "treatment",
        "center"
    ],
    "wof:name":"Bruce Johnston Addiction Cnsln",
    "wof:placetype":"venue"
},
  "geometry": {"coordinates":[-75.7026596069,45.3698425293],"type":"Point"}
}