{
  "type": "Feature",
  "properties": {
    "addr:full":"75 Rue Saint-Paul Quebec QC G1K 3V8",
    "addr:housenumber":"75",
    "addr:postcode":"g1k 3v8",
    "addr:street":"Rue Saint-Paul",
    "iso:country":"CA",
    "sg:address":"75 Rue Saint-Paul",
    "sg:city":"Quebec",
    "sg:classifiers":[
        {
            "category":"Restaurant",
            "type":"Food & Drink"
        }
    ],
    "sg:phone":"+1 418 692 2004",
    "sg:postcode":"G1K 3V8",
    "sg:province":"QC",
    "wof:name":"Cafe Le St-Malo",
    "wof:placetype":"venue"
},
  "geometry": {"coordinates":[-71.2041549683,46.816192627],"type":"Point"}
}