{
  "type": "Feature",
  "properties": {
    "addr:full":"6524 Rue Saint-Hubert Montreal QC H2S 2M3",
    "addr:housenumber":"6524",
    "addr:postcode":"h2s 2m3",
    "addr:street":"Rue Saint-Hubert",
    "iso:country":"CA",
    "sg:address":"6524 Rue Saint-Hubert",
    "sg:city":"Montreal",
    "sg:classifiers":[
        {
            "category":"Home & Garden",
            "subcategory":"Hardware",
            "type":"Retail Goods"
        }
    ],
    "sg:phone":"+1 514 274 3521",
    "sg:postcode":"H2S 2M3",
    "sg:province":"QC",
    "wof:name":"Lambert Quincaillerie Inc",
    "wof:placetype":"venue"
},
  "geometry": {"coordinates":[-73.60382080079999,45.5363502502],"type":"Point"}
}