{
  "type": "Feature",
  "properties": {
    "addr:full":"7145 Boul Henri-Bourassa Charlesbourg QC G1H 3E3",
    "addr:housenumber":"7145",
    "addr:postcode":"g1h 3e3",
    "addr:street":"Boul Henri-Bourassa",
    "iso:country":"CA",
    "sg:address":"7145 Boul Henri-Bourassa",
    "sg:city":"Charlesbourg",
    "sg:classifiers":[
        {
            "category":"Retail",
            "subcategory":"Auto Repair",
            "type":"Services"
        }
    ],
    "sg:phone":"+1 418 626 6626",
    "sg:postcode":"G1H 3E3",
    "sg:province":"QC",
    "sg:tags":[
        "repairing",
        "automobile"
    ],
    "wof:name":"Auto Technique Lapointe Inc",
    "wof:placetype":"venue"
},
  "geometry": {"coordinates":[-71.262489,46.857868],"type":"Point"}
}