{
  "type": "Feature",
  "properties": {
    "addr:full":"Calgary AB T3E 6K5",
    "addr:postcode":"t3e 6k5",
    "iso:country":"CA",
    "sg:city":"Calgary",
    "sg:classifiers":[
        {
            "category":"Personal",
            "subcategory":"Beauty Salon",
            "type":"Services"
        }
    ],
    "sg:phone":"+1 403 246 2848",
    "sg:postcode":"T3E 6K5",
    "sg:province":"AB",
    "wof:name":"Misty Hair Design",
    "wof:placetype":"venue"
},
  "geometry": {"coordinates":[-114.125427246,51.0377082825],"type":"Point"}
}