{
  "type": "Feature",
  "properties": {
    "addr:full":"3001 14 St SW Calgary AB T2T 3V6",
    "addr:housenumber":"3001",
    "addr:postcode":"t2t 3v6",
    "addr:street":"14 St Sw",
    "iso:country":"CA",
    "sg:address":"3001 14 St SW",
    "sg:city":"Calgary",
    "sg:classifiers":[
        {
            "category":"Retail",
            "subcategory":"Auto Repair",
            "type":"Services"
        }
    ],
    "sg:phone":"+1 403 229 0771",
    "sg:postcode":"T2T 3V6",
    "sg:province":"AB",
    "sg:tags":[
        "repairing",
        "automobile"
    ],
    "wof:name":"Mechanic's",
    "wof:placetype":"venue"
},
  "geometry": {"coordinates":[-114.09479522700001,51.0275840759],"type":"Point"}
}