{
  "type": "Feature",
  "properties": {
    "addr:full":"Etobicoke ON M8Z 5T6",
    "addr:postcode":"m8z 5t6",
    "iso:country":"CA",
    "sg:city":"Etobicoke",
    "sg:classifiers":[
        {
            "category":"Manufacturing",
            "subcategory":"Printing",
            "type":"Manufacturing & Wholesale Goods"
        }
    ],
    "sg:phone":"+1 416 251 3326",
    "sg:postcode":"M8Z 5T6",
    "sg:province":"ON",
    "sg:tags":[
        "printer"
    ],
    "wof:name":"Silverhaze Graphics Inc",
    "wof:placetype":"venue"
},
  "geometry": {"coordinates":[-79.5129623413,43.6128234863],"type":"Point"}
}