{
  "type": "Feature",
  "properties": {
    "addr:full":"Victoria BC V8V 4A1",
    "addr:postcode":"v8v 4a1",
    "iso:country":"CA",
    "sg:city":"Victoria",
    "sg:classifiers":[
        {
            "category":"Health Services",
            "subcategory":"Doctor",
            "type":"Services"
        }
    ],
    "sg:phone":"+1 250 385 8754",
    "sg:postcode":"V8V 4A1",
    "sg:province":"BC",
    "sg:tags":[
        "physician",
        "surgeon"
    ],
    "wof:name":"Mawdsley, Michael MD",
    "wof:placetype":"venue"
},
  "geometry": {"coordinates":[-123.353782654,48.42395401],"type":"Point"}
}