{
  "type": "Feature",
  "properties": {
    "iso:country":"CA",
    "sg:address":"750 Wharncliffe Rd S",
    "sg:city":"London",
    "sg:classifiers":[
        {
            "category":"Home & Garden",
            "subcategory":"Furniture",
            "type":"Retail Goods"
        }
    ],
    "sg:phone":"+1 519 681 8897",
    "sg:postcode":"N6J 2N4",
    "sg:province":"ON",
    "sg:tags":[
        "mattress"
    ],
    "wof:name":"In Between Dreams",
    "wof:placetype":"venue"
},
  "geometry": {"coordinates":[-81.2577209473,42.9459877014],"type":"Point"}
}