{
  "type": "Feature",
  "properties": {
    "addr:full":"1202 Boul Laure Sept-Iles QC G4S 1C5",
    "addr:housenumber":"1202",
    "addr:postcode":"g4s 1c5",
    "addr:street":"Boul Laure Sept-Iles",
    "iso:country":"CA",
    "sg:address":"1202 Boul Laure",
    "sg:city":"Sept-Iles",
    "sg:classifiers":[
        {
            "category":"Insurance",
            "subcategory":"Insurance Agent",
            "type":"Services"
        }
    ],
    "sg:phone":"+1 418 962 9744",
    "sg:postcode":"G4S 1C5",
    "sg:province":"QC",
    "wof:name":"Assurances Cusin & Pelletier",
    "wof:placetype":"venue"
},
  "geometry": {"coordinates":[-66.394783,50.234989],"type":"Point"}
}