{
  "type": "Feature",
  "properties": {
    "addr:full":"2131 North Nechako Rd Prince George BC V2K 4N2",
    "addr:housenumber":"2131",
    "addr:postcode":"v2k 4n2",
    "addr:street":"North Nechako Rd",
    "iso:country":"CA",
    "sg:address":"2131 North Nechako Rd",
    "sg:city":"Prince George",
    "sg:classifiers":[
        {
            "category":"Professional",
            "subcategory":"Accounting & Tax Preparation",
            "type":"Services"
        }
    ],
    "sg:phone":"+1 250 563 7265",
    "sg:postcode":"V2K 4N2",
    "sg:province":"BC",
    "sg:tags":[
        "accountant"
    ],
    "wof:name":"B B & A Svc",
    "wof:placetype":"venue"
},
  "geometry": {"coordinates":[-122.794960022,53.9449462891],"type":"Point"}
}