{
  "type": "Feature",
  "properties": {
    "addr:full":"51056 Range Road 204 Sherwood Park AB T8G 1E5",
    "addr:housenumber":"51056",
    "addr:postcode":"t8g 1e5",
    "addr:street":"Range Road 204;Park",
    "iso:country":"CA",
    "sg:address":"51056 Range Road 204",
    "sg:city":"Sherwood Park",
    "sg:classifiers":[
        {
            "category":"Farming",
            "subcategory":"Nursery",
            "type":"Manufacturing & Wholesale Goods"
        }
    ],
    "sg:phone":"+1 780 662 2494",
    "sg:postcode":"T8G 1E5",
    "sg:province":"AB",
    "sg:tags":[
        "greenhouse"
    ],
    "wof:name":"Hastings Lake Gardens",
    "wof:placetype":"venue"
},
  "geometry": {"coordinates":[-113.295738,53.526402],"type":"Point"}
}