{
  "type": "Feature",
  "properties": {
    "iso:country":"CA",
    "sg:address":"PO Box 342",
    "sg:city":"Berens River",
    "sg:classifiers":[
        {
            "category":"Social Services",
            "subcategory":"Child Care",
            "type":"Services"
        }
    ],
    "sg:phone":"+1 204 382 2907",
    "sg:postcode":"R0B 0A0",
    "sg:province":"MB",
    "wof:name":"Abinochiasak Day Ctr",
    "wof:placetype":"venue"
},
  "geometry": {"coordinates":[-100.23764,50.029285],"type":"Point"}
}