{
  "type": "Feature",
  "properties": {
    "addr:full":"Edmonton AB T5J 2G9",
    "addr:postcode":"t5j 2g9",
    "iso:country":"CA",
    "sg:city":"Edmonton",
    "sg:classifiers":[
        {
            "category":"Autos & Motor Vehicles",
            "subcategory":"Automobile Sales",
            "type":"Retail Goods"
        }
    ],
    "sg:phone":"+1 780 447 1264",
    "sg:postcode":"T5J 2G9",
    "sg:province":"AB",
    "sg:tags":[
        "car",
        "dealer"
    ],
    "wof:name":"Bargain Auto Ctr",
    "wof:placetype":"venue"
},
  "geometry": {"coordinates":[-113.587746,53.599602],"type":"Point"}
}