{
  "type": "Feature",
  "properties": {
    "addr:full":"2016 21 Ave NW Calgary AB T2M 1M8",
    "addr:housenumber":"2016",
    "addr:postcode":"t2m 1m8",
    "addr:street":"21 Ave Nw",
    "iso:country":"CA",
    "sg:address":"2016 21 Ave NW",
    "sg:city":"Calgary",
    "sg:classifiers":[
        {
            "category":"Food & Beverages",
            "subcategory":"Specialty",
            "type":"Retail Goods"
        }
    ],
    "sg:phone":"+1 403 210 0732",
    "sg:postcode":"T2M 1M8",
    "sg:province":"AB",
    "sg:tags":[
        "health",
        "diet"
    ],
    "wof:name":"Usana Independent Distr",
    "wof:placetype":"venue"
},
  "geometry": {"coordinates":[-114.10674299999999,51.071552],"type":"Point"}
}