{
  "type": "Feature",
  "properties": {
    "addr:full":"1385 Rue Ontario E Montreal QC H2L 1S2",
    "addr:housenumber":"1385",
    "addr:postcode":"h2l 1s2",
    "addr:street":"Rue Ontario E",
    "iso:country":"CA",
    "sg:address":"1385 Rue Ontario E",
    "sg:city":"Montreal",
    "sg:classifiers":[
        {
            "category":"Retail",
            "subcategory":"Funeral Services",
            "type":"Services"
        }
    ],
    "sg:phone":"+1 514 735 2025",
    "sg:postcode":"H2L 1S2",
    "sg:province":"QC",
    "sg:tags":[
        "director"
    ],
    "wof:name":"Urgel Bourgie Ltee",
    "wof:placetype":"venue"
},
  "geometry": {"coordinates":[-73.561317,45.523235],"type":"Point"}
}