{
  "type": "Feature",
  "properties": {
    "addr:full":"431 St Mary's Rd Winnipeg MB R2M 3K5",
    "addr:housenumber":"431",
    "addr:postcode":"r2m 3k5",
    "addr:street":"St Mary'S Rd",
    "iso:country":"CA",
    "sg:address":"431 St Mary's Rd",
    "sg:city":"Winnipeg",
    "sg:classifiers":[
        {
            "category":"Farming",
            "subcategory":"Nursery",
            "type":"Manufacturing & Wholesale Goods"
        }
    ],
    "sg:phone":"+1 204 237 1651",
    "sg:postcode":"R2M 3K5",
    "sg:province":"MB",
    "sg:tags":[
        "greenhouse"
    ],
    "wof:name":"Paul's Greenhouses & Florist",
    "wof:placetype":"venue"
},
  "geometry": {"coordinates":[-97.1489639282,49.8891487122],"type":"Point"}
}