{
  "type": "Feature",
  "properties": {
    "addr:full":"Waterloo ON N2K 4C9",
    "addr:postcode":"n2k 4c9",
    "iso:country":"CA",
    "sg:city":"Waterloo",
    "sg:classifiers":[
        {
            "category":"Retail",
            "subcategory":"Laundry & Dry Cleaning",
            "type":"Services"
        }
    ],
    "sg:phone":"+1 519 742 0983",
    "sg:postcode":"N2K 4C9",
    "sg:province":"ON",
    "sg:tags":[
        "cleaners",
        "tailor"
    ],
    "wof:name":"Kaiser's Tailor",
    "wof:placetype":"venue"
},
  "geometry": {"coordinates":[-80.491867,43.490757],"type":"Point"}
}