{
  "type": "Feature",
  "properties": {
    "addr:full":"2048 Mccaffrey Rd Agassiz BC V0M 1A1",
    "addr:housenumber":"2048",
    "addr:postcode":"v0m 1a1",
    "addr:street":"Mccaffrey Rd",
    "iso:country":"CA",
    "sg:address":"2048 Mccaffrey Rd",
    "sg:city":"Agassiz",
    "sg:classifiers":[
        {
            "category":"Building & Trades",
            "subcategory":"Construction",
            "type":"Services"
        }
    ],
    "sg:phone":"+1 604 796 3620",
    "sg:postcode":"V0M 1A1",
    "sg:province":"BC",
    "sg:tags":[
        "road",
        "contractor"
    ],
    "wof:name":"Kerrnsons Contracting Ltd",
    "wof:placetype":"venue"
},
  "geometry": {"coordinates":[-121.773414612,49.2410507202],"type":"Point"}
}