{
  "type": "Feature",
  "properties": {
    "addr:full":"357 Bay St Toronto ON M5H 2T7",
    "addr:housenumber":"357",
    "addr:postcode":"m5h 2t7",
    "addr:street":"Bay St",
    "iso:country":"CA",
    "sg:address":"357 Bay St",
    "sg:city":"Toronto",
    "sg:classifiers":[
        {
            "category":"Banks & Credit Unions",
            "subcategory":"Investment Brokerage",
            "type":"Services"
        }
    ],
    "sg:phone":"+1 416 368 5255",
    "sg:postcode":"M5H 2T7",
    "sg:province":"ON",
    "sg:tags":[
        "establishment",
        "financial",
        "advisory"
    ],
    "wof:name":"Cougar Global Investment Ltd",
    "wof:placetype":"venue"
},
  "geometry": {"coordinates":[-79.380959,43.650768],"type":"Point"}
}