{
  "type": "Feature",
  "properties": {
    "iso:country":"CA",
    "sg:address":"447 Ferry Rd",
    "sg:city":"Winnipeg",
    "sg:classifiers":[
        {
            "category":"Personal",
            "subcategory":"Beauty Salon",
            "type":"Services"
        }
    ],
    "sg:phone":"+1 204 888 9283",
    "sg:postcode":"R3J 1W3",
    "sg:province":"MB",
    "wof:name":"Silver Scissors",
    "wof:placetype":"venue"
},
  "geometry": {"coordinates":[-97.217903,49.887474],"type":"Point"}
}