{
  "type": "Feature",
  "properties": {
    "addr:full":"447 Ferry Rd Winnipeg MB R3J 1W3",
    "addr:housenumber":"447",
    "addr:postcode":"r3j 1w3",
    "addr:street":"Ferry Rd",
    "iso:country":"CA",
    "sg:address":"447 Ferry Rd",
    "sg:city":"Winnipeg",
    "sg:classifiers":[
        {
            "category":"Personal",
            "subcategory":"Beauty Salon",
            "type":"Services"
        }
    ],
    "sg:phone":"+1 204 888 9283",
    "sg:postcode":"R3J 1W3",
    "sg:province":"MB",
    "wof:name":"Silver Scissors",
    "wof:placetype":"venue"
},
  "geometry": {"coordinates":[-97.21790300000001,49.887474],"type":"Point"}
}