{
  "type": "Feature",
  "properties": {
    "addr:full":"Nanton AB T0L 1R0",
    "addr:postcode":"t0l 1r0",
    "iso:country":"CA",
    "sg:city":"Nanton",
    "sg:classifiers":[
        {
            "category":"Government",
            "subcategory":"Office",
            "type":"Public Place"
        }
    ],
    "sg:phone":"+1 403 646 2485",
    "sg:postcode":"T0L 1R0",
    "sg:province":"AB",
    "sg:tags":[
        "village"
    ],
    "wof:name":"Nanton Ems Administration",
    "wof:placetype":"venue"
},
  "geometry": {"coordinates":[-113.773849,50.349819],"type":"Point"}
}