{
  "type": "Feature",
  "properties": {
    "addr:full":"Toronto ON M6S 4W4",
    "addr:postcode":"m6s 4w4",
    "iso:country":"CA",
    "sg:city":"Toronto",
    "sg:classifiers":[
        {
            "category":"Health Services",
            "subcategory":"Doctor",
            "type":"Services"
        }
    ],
    "sg:phone":"+1 416 767 6626",
    "sg:postcode":"M6S 4W4",
    "sg:province":"ON",
    "sg:tags":[
        "dentist"
    ],
    "wof:name":"Kondracki, M L DDS",
    "wof:placetype":"venue"
},
  "geometry": {"coordinates":[-79.48365783689999,43.6493682861],"type":"Point"}
}