{
  "type": "Feature",
  "properties": {
    "iso:country":"CA",
    "sg:address":"1254 Ch DE Chambly",
    "sg:city":"Longueuil",
    "sg:classifiers":[
        {
            "category":"Personal",
            "subcategory":"Beauty Salon",
            "type":"Services"
        }
    ],
    "sg:phone":"+1 450 651 1208",
    "sg:postcode":"J4J 3W6",
    "sg:province":"QC",
    "wof:name":"Salon Coiffure Millenium",
    "wof:placetype":"venue"
},
  "geometry": {"coordinates":[-73.489075,45.53233],"type":"Point"}
}