{
  "type": "Feature",
  "properties": {
    "addr:full":"22328 119 Ave Maple Ridge BC V2X 2Z3",
    "addr:housenumber":"22328",
    "addr:postcode":"v2x 2z3",
    "addr:street":"119 Ave",
    "iso:country":"CA",
    "sg:address":"22328 119 Ave",
    "sg:city":"Maple Ridge",
    "sg:classifiers":[
        {
            "category":"Manufacturing",
            "subcategory":"Printing",
            "type":"Manufacturing & Wholesale Goods"
        }
    ],
    "sg:phone":"+1 604 467 1122",
    "sg:postcode":"V2X 2Z3",
    "sg:province":"BC",
    "sg:tags":[
        "newspaper"
    ],
    "wof:name":"Maple Ridge Pitt Meadows News",
    "wof:placetype":"venue"
},
  "geometry": {"coordinates":[-122.603607,49.21841],"type":"Point"}
}