{
  "type": "Feature",
  "properties": {
    "addr:full":"Montreal QC H2B 3C8",
    "addr:postcode":"h2b 3c8",
    "iso:country":"CA",
    "sg:city":"Montreal",
    "sg:classifiers":[
        {
            "category":"Manufacturing",
            "subcategory":"Apparel",
            "type":"Manufacturing & Wholesale Goods"
        }
    ],
    "sg:phone":"+1 514 387 9522",
    "sg:postcode":"H2B 3C8",
    "sg:province":"QC",
    "sg:tags":[
        "boy",
        "clothing",
        "furnishing"
    ],
    "wof:name":"9100-8581 Quebec Inc",
    "wof:placetype":"venue"
},
  "geometry": {"coordinates":[-73.645309,45.564838],"type":"Point"}
}