{
  "type": "Feature",
  "properties": {
    "addr:full":"Terrace BC V8G 4E1",
    "addr:postcode":"v8g 4e1",
    "iso:country":"CA",
    "sg:city":"Terrace",
    "sg:classifiers":[
        {
            "category":"Government",
            "subcategory":"Office",
            "type":"Public Place"
        }
    ],
    "sg:phone":"+1 250 615 6100",
    "sg:postcode":"V8G 4E1",
    "sg:province":"BC",
    "sg:tags":[
        "village"
    ],
    "wof:name":"Kitimat-Stikine Regional Distr",
    "wof:placetype":"venue"
},
  "geometry": {"coordinates":[-128.58413696299999,54.5170555115],"type":"Point"}
}