{
  "type": "Feature",
  "properties": {
    "addr:full":"436 Aberdeen St Fredericton NB E3B 1S1",
    "addr:housenumber":"436",
    "addr:postcode":"e3b 1s1",
    "addr:street":"Aberdeen St",
    "iso:country":"CA",
    "sg:address":"436 Aberdeen St",
    "sg:city":"Fredericton",
    "sg:classifiers":[
        {
            "category":"Home & Garden",
            "subcategory":"Household Appliances",
            "type":"Retail Goods"
        }
    ],
    "sg:phone":"+1 506 457 2777",
    "sg:postcode":"E3B 1S1",
    "sg:province":"NB",
    "wof:name":"Aberdeen Service Ctr",
    "wof:placetype":"venue"
},
  "geometry": {"coordinates":[-66.647255,45.956882],"type":"Point"}
}