{
  "type": "Feature",
  "properties": {
    "addr:full":"350 Shawville Blvd SE # 260 Calgary AB T2Y 3S4",
    "addr:housenumber":"350",
    "addr:postcode":"t2y 3s4",
    "addr:street":"Shawville Blvd Se # 260",
    "iso:country":"CA",
    "sg:address":"350 Shawville Blvd SE # 260",
    "sg:city":"Calgary",
    "sg:classifiers":[
        {
            "category":"Restaurant",
            "type":"Food & Drink"
        }
    ],
    "sg:phone":"+1 403 201 1116",
    "sg:postcode":"T2Y 3S4",
    "sg:province":"AB",
    "wof:name":"Subway Sandwiches & Salads",
    "wof:placetype":"venue"
},
  "geometry": {"coordinates":[-114.06234741199999,50.8980865479],"type":"Point"}
}