{
  "type": "Feature",
  "properties": {
    "addr:full":"189 Asher Rd Kelowna BC V1X 3H5",
    "addr:housenumber":"189",
    "addr:postcode":"v1x 3h5",
    "addr:street":"Asher Rd",
    "iso:country":"CA",
    "sg:address":"189 Asher Rd",
    "sg:city":"Kelowna",
    "sg:classifiers":[
        {
            "category":"Personal",
            "subcategory":"Barber",
            "type":"Services"
        }
    ],
    "sg:phone":"+1 250 765 8488",
    "sg:postcode":"V1X 3H5",
    "sg:province":"BC",
    "wof:name":"Lipka's Barber Shop",
    "wof:placetype":"venue"
},
  "geometry": {"coordinates":[-119.390991,49.890129],"type":"Point"}
}