{
  "type": "Feature",
  "properties": {
    "iso:country":"CA",
    "sg:city":"Mississauga",
    "sg:classifiers":[
        {
            "category":"Insurance",
            "subcategory":"Insurance Agent",
            "type":"Services"
        }
    ],
    "sg:phone":"+1 905 568 3430",
    "sg:postcode":"L4Z 3L3",
    "sg:province":"ON",
    "wof:name":"Insurance Unlimited Ins Broker",
    "wof:placetype":"venue"
},
  "geometry": {"coordinates":[-79.670898,43.626282],"type":"Point"}
}