{
  "type": "Feature",
  "properties": {
    "addr:full":"9275 Nowell St Chilliwack BC V2P 7G7",
    "addr:housenumber":"9275",
    "addr:postcode":"v2p 7g7",
    "addr:street":"Nowell St",
    "iso:country":"CA",
    "sg:address":"9275 Nowell St",
    "sg:city":"Chilliwack",
    "sg:classifiers":[
        {
            "category":"Professional",
            "subcategory":"Computer Services",
            "type":"Services"
        }
    ],
    "sg:phone":"+1 604 793 9944",
    "sg:postcode":"V2P 7G7",
    "sg:province":"BC",
    "sg:tags":[
        "internet"
    ],
    "wof:name":"Shaw Home High Speed Internet",
    "wof:placetype":"venue"
},
  "geometry": {"coordinates":[-121.94996643099999,49.1705741882],"type":"Point"}
}