{
  "type": "Feature",
  "properties": {
    "addr:full":"11638 87 Ave NW Edmonton AB T6G 0Y2",
    "addr:housenumber":"11638",
    "addr:postcode":"t6g 0y2",
    "addr:street":"87 Ave Nw",
    "iso:country":"CA",
    "sg:address":"11638 87 Ave NW",
    "sg:city":"Edmonton",
    "sg:classifiers":[
        {
            "category":"Food & Beverages",
            "subcategory":"Groceries & Convenience Stores",
            "type":"Retail Goods"
        }
    ],
    "sg:phone":"+1 780 433 2389",
    "sg:postcode":"T6G 0Y2",
    "sg:province":"AB",
    "wof:name":"Mac's Convenience Stores Ltd",
    "wof:placetype":"venue"
},
  "geometry": {"coordinates":[-113.531395,53.523079],"type":"Point"}
}