{
  "type": "Feature",
  "properties": {
    "iso:country":"CA",
    "sg:address":"198 King St W",
    "sg:city":"Brockville",
    "sg:classifiers":[
        {
            "category":"Shopping",
            "subcategory":"Bicycles & Sporting Goods",
            "type":"Retail Goods"
        }
    ],
    "sg:phone":"+1 613 342 5543",
    "sg:postcode":"K6V 3R5",
    "sg:province":"ON",
    "wof:name":"Q J Johnny",
    "wof:placetype":"venue"
},
  "geometry": {"coordinates":[-75.6878585815,44.5877532959],"type":"Point"}
}