{
  "type": "Feature",
  "properties": {
    "iso:country":"CA",
    "sg:address":"1410 16th Ave",
    "sg:city":"Campbell River",
    "sg:classifiers":[
        {
            "category":"Farming",
            "subcategory":"Fish & Marine Products",
            "type":"Manufacturing & Wholesale Goods"
        }
    ],
    "sg:phone":"+1 250 287 4735",
    "sg:postcode":"V9W 2E3",
    "sg:province":"BC",
    "sg:tags":[
        "fisherman"
    ],
    "wof:name":"R A Roberts Fishing CO Ltd",
    "wof:placetype":"venue"
},
  "geometry": {"coordinates":[-125.250190735,50.0306472778],"type":"Point"}
}