{
  "type": "Feature",
  "properties": {
    "addr:full":"Sherwood Park AB T8A 4R2",
    "addr:postcode":"t8a 4r2",
    "iso:country":"CA",
    "sg:city":"Sherwood Park",
    "sg:classifiers":[
        {
            "category":"Retail",
            "subcategory":"Repair Shop",
            "type":"Services"
        }
    ],
    "sg:phone":"+1 780 922 6602",
    "sg:postcode":"T8A 4R2",
    "sg:province":"AB",
    "sg:tags":[
        "taxidermist"
    ],
    "wof:name":"Taxidermy By Richard Page",
    "wof:placetype":"venue"
},
  "geometry": {"coordinates":[-113.295738,53.526402],"type":"Point"}
}