{
  "type": "Feature",
  "properties": {
    "iso:country":"CA",
    "sg:address":"PO Box 250",
    "sg:city":"Cando",
    "sg:classifiers":[
        {
            "category":"Education",
            "subcategory":"School",
            "type":"Public Place"
        }
    ],
    "sg:phone":"+1 306 937 3934",
    "sg:postcode":"S0K 0V0",
    "sg:province":"SK",
    "wof:name":"Cando Central School",
    "wof:placetype":"venue"
},
  "geometry": {"coordinates":[-108.215538,52.373615],"type":"Point"}
}