{
  "type": "Feature",
  "properties": {
    "addr:full":"Saskatoon SK S7H 5M3",
    "addr:postcode":"s7h 5m3",
    "iso:country":"CA",
    "sg:city":"Saskatoon",
    "sg:classifiers":[
        {
            "category":"Restaurant",
            "type":"Food & Drink"
        }
    ],
    "sg:phone":"+1 306 955 4467",
    "sg:postcode":"S7H 5M3",
    "sg:province":"SK",
    "wof:name":"Mrs Vanelli's Restaurant",
    "wof:placetype":"venue"
},
  "geometry": {"coordinates":[-106.60267639200001,52.1144218445],"type":"Point"}
}