{
  "type": "Feature",
  "properties": {
    "addr:full":"72 Copernicus Blvd Brantford ON N3P 1K5",
    "addr:housenumber":"72",
    "addr:postcode":"n3p 1k5",
    "addr:street":"Copernicus Blvd",
    "iso:country":"CA",
    "sg:address":"72 Copernicus Blvd",
    "sg:city":"Brantford",
    "sg:classifiers":[
        {
            "category":"Manufacturing",
            "subcategory":"Textiles",
            "type":"Manufacturing & Wholesale Goods"
        }
    ],
    "sg:phone":"+1 519 759 4242",
    "sg:postcode":"N3P 1K5",
    "sg:province":"ON",
    "sg:tags":[
        "knit"
    ],
    "wof:name":"Great Lakes Knitting Mills Ltd",
    "wof:placetype":"venue"
},
  "geometry": {"coordinates":[-80.240166,43.179466],"type":"Point"}
}