{
  "type": "Feature",
  "properties": {
    "iso:country":"CA",
    "sg:address":"1005 2 St SW",
    "sg:city":"Calgary",
    "sg:classifiers":[
        {
            "category":"Retail",
            "subcategory":"Laundry & Dry Cleaning",
            "type":"Services"
        }
    ],
    "sg:phone":"+1 403 264 3433",
    "sg:postcode":"T2R 1R4",
    "sg:province":"AB",
    "sg:tags":[
        "cleaners",
        "fur"
    ],
    "wof:name":"R C Intl Furs Ltd",
    "wof:placetype":"venue"
},
  "geometry": {"coordinates":[-114.068252563,51.0433158875],"type":"Point"}
}