{
  "type": "Feature",
  "properties": {
    "addr:full":"395 Grand Ave W Chatham ON N7L 1C4",
    "addr:housenumber":"395",
    "addr:postcode":"n7l 1c4",
    "addr:street":"Grand Ave W",
    "iso:country":"CA",
    "sg:address":"395 Grand Ave W",
    "sg:city":"Chatham",
    "sg:classifiers":[
        {
            "category":"Restaurant",
            "type":"Food & Drink"
        }
    ],
    "sg:phone":"+1 519 360 9800",
    "sg:postcode":"N7L 1C4",
    "sg:province":"ON",
    "wof:name":"Crabby Joe's Tap & Grill",
    "wof:placetype":"venue"
},
  "geometry": {"coordinates":[-82.2035980225,42.4017448425],"type":"Point"}
}