{
  "type": "Feature",
  "properties": {
    "addr:full":"470 Highland Rd W Kitchener ON N2M 3C7",
    "addr:housenumber":"470",
    "addr:postcode":"n2m 3c7",
    "addr:street":"Highland Rd W",
    "iso:country":"CA",
    "sg:address":"470 Highland Rd W",
    "sg:city":"Kitchener",
    "sg:classifiers":[
        {
            "category":"Restaurant",
            "type":"Food & Drink"
        }
    ],
    "sg:phone":"+1 519 576 6800",
    "sg:postcode":"N2M 3C7",
    "sg:province":"ON",
    "wof:name":"Mr Submarine",
    "wof:placetype":"venue"
},
  "geometry": {"coordinates":[-80.51397705079999,43.4361915588],"type":"Point"}
}