{
  "type": "Feature",
  "properties": {
    "addr:full":"148 Rue Principale Frampton QC G0R 1M0",
    "addr:housenumber":"148",
    "addr:postcode":"g0r 1m0",
    "addr:street":"Rue Principale",
    "iso:country":"CA",
    "sg:address":"148 Rue Principale",
    "sg:city":"Frampton",
    "sg:classifiers":[
        {
            "category":"Health Services",
            "subcategory":"Nursing And Care Facility",
            "type":"Services"
        }
    ],
    "sg:phone":"+1 418 479 2970",
    "sg:postcode":"G0R 1M0",
    "sg:province":"QC",
    "sg:tags":[
        "home",
        "retirement",
        "community",
        "rest"
    ],
    "wof:name":"Foyer Frampton",
    "wof:placetype":"venue"
},
  "geometry": {"coordinates":[-70.80952499999999,46.462543],"type":"Point"}
}