{
  "type": "Feature",
  "properties": {
    "iso:country":"CA",
    "sg:address":"207 Rang Saint-Edouard",
    "sg:city":"Saint-Jean-Sur-Richelieu",
    "sg:classifiers":[
        {
            "category":"Manufacturing",
            "subcategory":"Tools & Machinery",
            "type":"Manufacturing & Wholesale Goods"
        }
    ],
    "sg:phone":"+1 450 346 7227",
    "sg:postcode":"J2X 5T9",
    "sg:province":"QC",
    "sg:tags":[
        "machine",
        "shop",
        "mold"
    ],
    "wof:name":"Moules Hsm Inc",
    "wof:placetype":"venue"
},
  "geometry": {"coordinates":[-73.236458,45.335045],"type":"Point"}
}