{
  "type": "Feature",
  "properties": {
    "addr:full":"300 Rue Des Campeurs Sainte-Melanie QC J0K 3A0",
    "addr:housenumber":"300",
    "addr:postcode":"j0k 3a0",
    "addr:street":"Rue Des Campeurs Sainte-Melanie",
    "iso:country":"CA",
    "sg:address":"300 Rue Des Campeurs",
    "sg:city":"Sainte-Melanie",
    "sg:classifiers":[
        {
            "category":"Travel",
            "subcategory":"Hotels & Motels",
            "type":"Entertainment"
        }
    ],
    "sg:phone":"+1 450 889 2336",
    "sg:postcode":"J0K 3A0",
    "sg:province":"QC",
    "sg:tags":[
        "resort"
    ],
    "wof:name":"Camping Nadeau",
    "wof:placetype":"venue"
},
  "geometry": {"coordinates":[-73.51638,46.132809],"type":"Point"}
}