{
  "type": "Feature",
  "properties": {
    "addr:full":"St Catharines ON L2R 7P3",
    "addr:postcode":"l2r 7p3",
    "iso:country":"CA",
    "sg:city":"St Catharines",
    "sg:classifiers":[
        {
            "category":"Health Services",
            "subcategory":"Doctor",
            "type":"Services"
        }
    ],
    "sg:phone":"+1 905 641 3423",
    "sg:postcode":"L2R 7P3",
    "sg:province":"ON",
    "sg:tags":[
        "physician",
        "surgeon"
    ],
    "wof:name":"Josefchak, R G MD",
    "wof:placetype":"venue"
},
  "geometry": {"coordinates":[-79.230019,43.171703],"type":"Point"}
}