{
  "type": "Feature",
  "properties": {
    "iso:country":"CA",
    "sg:address":"205 Victoria St S",
    "sg:city":"Kitchener",
    "sg:classifiers":[
        {
            "category":"Real Estate",
            "subcategory":"Real Estate Operator",
            "type":"Services"
        }
    ],
    "sg:phone":"+1 519 749 2420",
    "sg:postcode":"N2G 4Z6",
    "sg:province":"ON",
    "sg:tags":[
        "apartment"
    ],
    "wof:name":"Drewlo Holdings Inc",
    "wof:placetype":"venue"
},
  "geometry": {"coordinates":[-80.50421142579999,43.4466667175],"type":"Point"}
}