{
  "type": "Feature",
  "properties": {
    "iso:country":"CA",
    "sg:city":"Vancouver",
    "sg:classifiers":[
        {
            "category":"Professional",
            "subcategory":"Advertising",
            "type":"Services"
        }
    ],
    "sg:phone":"+1 604 683 3987",
    "sg:postcode":"V6C 2B3",
    "sg:province":"BC",
    "sg:tags":[
        "counselor"
    ],
    "wof:name":"Canam Media Intl Inc",
    "wof:placetype":"venue"
},
  "geometry": {"coordinates":[-123.11560821499999,49.285572052],"type":"Point"}
}