{
  "type": "Feature",
  "properties": {
    "iso:country":"CA",
    "sg:address":"2630 Labieux Rd",
    "sg:city":"Nanaimo",
    "sg:classifiers":[
        {
            "category":"Health Services",
            "subcategory":"Clinic",
            "type":"Services"
        }
    ],
    "sg:phone":"+1 250 756 3008",
    "sg:postcode":"V9T 3N1",
    "sg:province":"BC",
    "sg:tags":[
        "home",
        "convalescent",
        "nursing"
    ],
    "wof:name":"Dwelling Place",
    "wof:placetype":"venue"
},
  "geometry": {"coordinates":[-124.015159607,49.1997642517],"type":"Point"}
}