{
  "type": "Feature",
  "properties": {
    "addr:full":"Saint-Denis-DE-Brompton QC J0B 2P0",
    "addr:postcode":"j0b 2p0",
    "iso:country":"CA",
    "sg:city":"Saint-Denis-DE-Brompton",
    "sg:classifiers":[
        {
            "category":"Manufacturing",
            "subcategory":"Tools & Machinery",
            "type":"Manufacturing & Wholesale Goods"
        }
    ],
    "sg:phone":"+1 819 846 0313",
    "sg:postcode":"J0B 2P0",
    "sg:province":"QC",
    "sg:tags":[
        "built",
        "designed"
    ],
    "wof:name":"Maquina Inc",
    "wof:placetype":"venue"
},
  "geometry": {"coordinates":[-72.05647277830001,45.4450836182],"type":"Point"}
}