{
  "type": "Feature",
  "properties": {
    "iso:country":"CA",
    "sg:address":"50 Principale O",
    "sg:city":"Cookshire",
    "sg:classifiers":[
        {
            "category":"Building & Trades",
            "subcategory":"Construction",
            "type":"Services"
        }
    ],
    "sg:phone":"+1 819 875 3869",
    "sg:postcode":"J0B 1M0",
    "sg:province":"QC",
    "sg:tags":[
        "painter"
    ],
    "wof:name":"Gagnon, Felix",
    "wof:placetype":"venue"
},
  "geometry": {"coordinates":[-71.6283035278,45.4124565125],"type":"Point"}
}