{
  "type": "Feature",
  "properties": {
    "iso:country":"CA",
    "sg:address":"34 Marr Rd",
    "sg:city":"Rothesay",
    "sg:phone":"+1 506 847 1044",
    "sg:postcode":"E2E 2R5",
    "sg:province":"NB",
    "sg:tags":[
        "equipment",
        "supply"
    ],
    "wof:name":"Milneco Limited",
    "wof:placetype":"venue"
},
  "geometry": {"coordinates":[-65.9780502319,45.3943824768],"type":"Point"}
}