{
  "type": "Feature",
  "properties": {
    "addr:full":"Calgary AB T2P 2Y5",
    "addr:postcode":"t2p 2y5",
    "iso:country":"CA",
    "sg:city":"Calgary",
    "sg:classifiers":[
        {
            "category":"Mining & Drilling",
            "type":"Manufacturing & Wholesale Goods"
        }
    ],
    "sg:phone":"+1 403 266 0085",
    "sg:postcode":"T2P 2Y5",
    "sg:province":"AB",
    "sg:tags":[
        "development",
        "gas",
        "oil",
        "exploration"
    ],
    "wof:name":"Slate Energy",
    "wof:placetype":"venue"
},
  "geometry": {"coordinates":[-114.074608,51.047615],"type":"Point"}
}