{
  "type": "Feature",
  "properties": {
    "iso:country":"CA",
    "sg:address":"30 Arthur St S",
    "sg:city":"Elmira",
    "sg:classifiers":[
        {
            "category":"Bars & Pubs",
            "type":"Food & Drink"
        }
    ],
    "sg:phone":"+1 519 669 9028",
    "sg:postcode":"N3B 2M7",
    "sg:province":"ON",
    "wof:name":"Central Tavern",
    "wof:placetype":"venue"
},
  "geometry": {"coordinates":[-80.55852508540001,43.5991973877],"type":"Point"}
}