{
  "type": "Feature",
  "properties": {
    "addr:full":"8144 Pinellas Park Dr Niagara Falls ON L2H 3B1",
    "addr:housenumber":"8144",
    "addr:postcode":"l2h 3b1",
    "addr:street":"Pinellas Park Dr",
    "iso:country":"CA",
    "sg:address":"8144 Pinellas Park Dr",
    "sg:city":"Niagara Falls",
    "sg:classifiers":[
        {
            "category":"Shopping",
            "subcategory":"Bicycles & Sporting Goods",
            "type":"Retail Goods"
        }
    ],
    "sg:phone":"+1 905 357 1311",
    "sg:postcode":"L2H 3B1",
    "sg:province":"ON",
    "sg:tags":[
        "equipment",
        "playground"
    ],
    "wof:name":"Henderson Recreation Equipment",
    "wof:placetype":"venue"
},
  "geometry": {"coordinates":[-79.133895874,43.105255127],"type":"Point"}
}