{
  "type": "Feature",
  "properties": {
    "iso:country":"CA",
    "sg:address":"3316 Old Coach Rd",
    "sg:city":"Burlington",
    "sg:classifiers":[
        {
            "category":"Building & Trades",
            "subcategory":"Electrical",
            "type":"Services"
        }
    ],
    "sg:phone":"+1 905 681 2714",
    "sg:postcode":"L7N 3P7",
    "sg:province":"ON",
    "sg:tags":[
        "electric",
        "contractor"
    ],
    "wof:name":"Ken Sisler Electric Ltd",
    "wof:placetype":"venue"
},
  "geometry": {"coordinates":[-79.777794,43.34808],"type":"Point"}
}