{
  "type": "Feature",
  "properties": {
    "addr:full":"1646 Victoria Park Ave North York ON M1R 1P7",
    "addr:housenumber":"1646",
    "addr:postcode":"m1r 1p7",
    "addr:street":"Victoria Park Ave",
    "iso:country":"CA",
    "sg:address":"1646 Victoria Park Ave",
    "sg:city":"North York",
    "sg:classifiers":[
        {
            "category":"Professional",
            "subcategory":"Detective & Security Services",
            "type":"Services"
        }
    ],
    "sg:phone":"+1 416 757 1503",
    "sg:postcode":"M1R 1P7",
    "sg:province":"ON",
    "sg:tags":[
        "investigator"
    ],
    "wof:name":"International Investigation",
    "wof:placetype":"venue"
},
  "geometry": {"coordinates":[-79.30566399999999,43.731564],"type":"Point"}
}