{
  "type": "Feature",
  "properties": {
    "addr:full":"333 Denison St Markham ON L3R 2Z4",
    "addr:housenumber":"333",
    "addr:postcode":"l3r 2z4",
    "addr:street":"Denison St",
    "iso:country":"CA",
    "sg:address":"333 Denison St",
    "sg:city":"Markham",
    "sg:classifiers":[
        {
            "category":"Professional",
            "subcategory":"Business Services",
            "type":"Services"
        }
    ],
    "sg:phone":"+1 905 479 3317",
    "sg:postcode":"L3R 2Z4",
    "sg:province":"ON",
    "sg:tags":[
        "interior",
        "consultant",
        "design",
        "decorator"
    ],
    "wof:name":"Plan Three Interiors",
    "wof:placetype":"venue"
},
  "geometry": {"coordinates":[-79.34889221189999,43.8222618103],"type":"Point"}
}