{
  "type": "Feature",
  "properties": {
    "iso:country":"CA",
    "sg:address":"1359 Boul Saint-Paul",
    "sg:city":"Chicoutimi",
    "sg:classifiers":[
        {
            "category":"Building & Trades",
            "subcategory":"Construction",
            "type":"Services"
        }
    ],
    "sg:phone":"+1 418 693 1521",
    "sg:postcode":"G7J 3Y3",
    "sg:province":"QC",
    "sg:tags":[
        "designer",
        "supply",
        "equipment",
        "billiard",
        "dealer",
        "pool",
        "swimming"
    ],
    "wof:name":"Piscines Soleil Plus Enr",
    "wof:placetype":"venue"
},
  "geometry": {"coordinates":[-71.09346,48.407017],"type":"Point"}
}