{
  "type": "Feature",
  "properties": {
    "addr:full":"Spruce View AB T0M 1V0",
    "addr:postcode":"t0m 1v0",
    "addr:street":"Spruce",
    "iso:country":"CA",
    "sg:city":"Spruce View",
    "sg:classifiers":[
        {
            "category":"Restaurant",
            "type":"Food & Drink"
        }
    ],
    "sg:phone":"+1 403 728 3555",
    "sg:postcode":"T0M 1V0",
    "sg:province":"AB",
    "wof:name":"Tivoli Garden Cafe",
    "wof:placetype":"venue"
},
  "geometry": {"coordinates":[-114.335655,52.086239],"type":"Point"}
}