{
  "type": "Feature",
  "properties": {
    "addr:full":"2500 Don Mills Rd North York ON M2J 3B3",
    "addr:housenumber":"2500",
    "addr:postcode":"m2j 3b3",
    "addr:street":"Don Mills Rd",
    "iso:country":"CA",
    "sg:address":"2500 Don Mills Rd",
    "sg:city":"North York",
    "sg:classifiers":[
        {
            "category":"Autos & Motor Vehicles",
            "subcategory":"Fuel & Gas Station",
            "type":"Retail Goods"
        }
    ],
    "sg:phone":"+1 416 494 6000",
    "sg:postcode":"M2J 3B3",
    "sg:province":"ON",
    "sg:tags":[
        "oil"
    ],
    "wof:name":"Sean's Esso",
    "wof:placetype":"venue"
},
  "geometry": {"coordinates":[-79.34725952150001,43.7752113342],"type":"Point"}
}