{
  "type": "Feature",
  "properties": {
    "addr:full":"656 Dundas St Woodstock ON N4S 1E3",
    "addr:housenumber":"656",
    "addr:postcode":"n4s 1e3",
    "addr:street":"Dundas St",
    "iso:country":"CA",
    "sg:address":"656 Dundas St",
    "sg:city":"Woodstock",
    "sg:classifiers":[
        {
            "category":"Shopping",
            "type":"Retail Goods"
        }
    ],
    "sg:phone":"+1 519 539 3426",
    "sg:postcode":"N4S 1E3",
    "sg:province":"ON",
    "sg:tags":[
        "pet",
        "shop"
    ],
    "wof:name":"Ruffin's Pet Ctr",
    "wof:placetype":"venue"
},
  "geometry": {"coordinates":[-80.749229,43.131042],"type":"Point"}
}