{
  "type": "Feature",
  "properties": {
    "addr:full":"265 Ponto Rd Kelowna BC V1X 2G2",
    "addr:housenumber":"265",
    "addr:postcode":"v1x 2g2",
    "addr:street":"Ponto Rd",
    "iso:country":"CA",
    "sg:address":"265 Ponto Rd",
    "sg:city":"Kelowna",
    "sg:classifiers":[
        {
            "category":"Building & Trades",
            "subcategory":"Construction",
            "type":"Services"
        }
    ],
    "sg:phone":"+1 250 765 8789",
    "sg:postcode":"V1X 2G2",
    "sg:province":"BC",
    "sg:tags":[
        "insulation",
        "heat",
        "stucco",
        "contractor"
    ],
    "wof:name":"Nelson Stucco",
    "wof:placetype":"venue"
},
  "geometry": {"coordinates":[-119.390182,49.893234],"type":"Point"}
}