{
  "type": "Feature",
  "properties": {
    "addr:full":"10550 82 Ave NW Edmonton AB T6E 2A4",
    "addr:housenumber":"10550",
    "addr:postcode":"t6e 2a4",
    "addr:street":"82 Ave Nw",
    "iso:country":"CA",
    "sg:address":"10550 82 Ave NW",
    "sg:city":"Edmonton",
    "sg:classifiers":[
        {
            "category":"Shopping",
            "subcategory":"Musical Instruments",
            "type":"Retail Goods"
        }
    ],
    "sg:phone":"+1 780 448 4827",
    "sg:postcode":"T6E 2A4",
    "sg:province":"AB",
    "sg:tags":[
        "music",
        "dealer"
    ],
    "wof:name":"Avenue Guitars",
    "wof:placetype":"venue"
},
  "geometry": {"coordinates":[-113.501991,53.518307],"type":"Point"}
}