{
  "type": "Feature",
  "properties": {
    "addr:full":"Vanier QC G1M 2V3",
    "addr:postcode":"g1m 2v3",
    "iso:country":"CA",
    "sg:city":"Vanier",
    "sg:classifiers":[
        {
            "category":"Wholesale",
            "subcategory":"Groceries",
            "type":"Manufacturing & Wholesale Goods"
        }
    ],
    "sg:phone":"+1 418 687 2322",
    "sg:postcode":"G1M 2V3",
    "sg:province":"QC",
    "sg:tags":[
        "grocer"
    ],
    "wof:name":"Metro Richelieu Inc",
    "wof:placetype":"venue"
},
  "geometry": {"coordinates":[-71.27668799999999,46.824566],"type":"Point"}
}