{
  "type": "Feature",
  "properties": {
    "iso:country":"CA",
    "sg:address":"33 Rue Richardson",
    "sg:city":"Beauharnois",
    "sg:classifiers":[
        {
            "category":"Government",
            "subcategory":"Fire Station",
            "type":"Public Place"
        }
    ],
    "sg:phone":"+1 ",
    "sg:postcode":"J6N 2T4",
    "sg:province":"QC",
    "sg:tags":[
        "department"
    ],
    "wof:name":"Beauharnois Feu",
    "wof:placetype":"venue"
},
  "geometry": {"coordinates":[-73.87603,45.313717],"type":"Point"}
}