{
  "type": "Feature",
  "properties": {
    "addr:full":"614 Broadway W Vancouver BC V5Z 1G1",
    "addr:housenumber":"614",
    "addr:postcode":"v5z 1g1",
    "addr:street":"Broadway W",
    "iso:country":"CA",
    "sg:address":"614 Broadway W",
    "sg:city":"Vancouver",
    "sg:classifiers":[
        {
            "category":"Restaurant",
            "type":"Food & Drink"
        }
    ],
    "sg:phone":"+1 604 879 1889",
    "sg:postcode":"V5Z 1G1",
    "sg:province":"BC",
    "wof:name":"Fu Loi Restaurant",
    "wof:placetype":"venue"
},
  "geometry": {"coordinates":[-123.11829376199999,49.2631416321],"type":"Point"}
}