{
  "type": "Feature",
  "properties": {
    "addr:full":"3741 Lawrence Ave E Scarborough ON M1G 1P7",
    "addr:housenumber":"3741",
    "addr:postcode":"m1g 1p7",
    "addr:street":"Lawrence Ave E",
    "iso:country":"CA",
    "sg:address":"3741 Lawrence Ave E",
    "sg:city":"Scarborough",
    "sg:classifiers":[
        {
            "category":"Restaurant",
            "type":"Food & Drink"
        }
    ],
    "sg:phone":"+1 416 289 3350",
    "sg:postcode":"M1G 1P7",
    "sg:province":"ON",
    "wof:name":"Mr Submarine",
    "wof:placetype":"venue"
},
  "geometry": {"coordinates":[-79.2168807983,43.7614784241],"type":"Point"}
}