{
  "type": "Feature",
  "properties": {
    "addr:full":"Boyle AB T0A 0M0",
    "addr:postcode":"t0a 0m0",
    "iso:country":"CA",
    "sg:city":"Boyle",
    "sg:classifiers":[
        {
            "category":"Professional",
            "subcategory":"Lawyer & Legal Services",
            "type":"Services"
        }
    ],
    "sg:phone":"+1 780 689 5054",
    "sg:postcode":"T0A 0M0",
    "sg:province":"AB",
    "sg:tags":[
        "attorney"
    ],
    "wof:name":"Polack Neindersma Liddell",
    "wof:placetype":"venue"
},
  "geometry": {"coordinates":[-112.80905199999999,54.59008],"type":"Point"}
}