{
  "type": "Feature",
  "properties": {
    "iso:country":"CA",
    "sg:city":"Edmonton",
    "sg:classifiers":[
        {
            "category":"Shopping",
            "subcategory":"Jewelry",
            "type":"Retail Goods"
        }
    ],
    "sg:phone":"+1 780 424 8539",
    "sg:postcode":"T5J 0G5",
    "sg:province":"AB",
    "wof:name":"Silversmith Jewellery Designs",
    "wof:placetype":"venue"
},
  "geometry": {"coordinates":[-113.49176788299999,53.5445365906],"type":"Point"}
}