{
  "type": "Feature",
  "properties": {
    "addr:full":"Ladysmith QC J0X 2A0",
    "addr:postcode":"j0x 2a0",
    "iso:country":"CA",
    "sg:city":"Ladysmith",
    "sg:classifiers":[
        {
            "category":"Government",
            "subcategory":"Office",
            "type":"Public Place"
        }
    ],
    "sg:phone":"+1 819 647 3206",
    "sg:postcode":"J0X 2A0",
    "sg:province":"QC",
    "sg:tags":[
        "village"
    ],
    "wof:name":"Thorne Municipality",
    "wof:placetype":"venue"
},
  "geometry": {"coordinates":[-76.385971,45.761032],"type":"Point"}
}