{
  "type": "Feature",
  "properties": {
    "addr:full":"Ottawa ON K1Z 7L2",
    "addr:postcode":"k1z 7l2",
    "iso:country":"CA",
    "sg:city":"Ottawa",
    "sg:classifiers":[
        {
            "category":"Organizations",
            "subcategory":"Professional Association",
            "type":"Services"
        }
    ],
    "sg:phone":"+1 613 232 0727",
    "sg:postcode":"K1Z 7L2",
    "sg:province":"ON",
    "wof:name":"Help the Aged",
    "wof:placetype":"venue"
},
  "geometry": {"coordinates":[-75.73419199999999,45.385803],"type":"Point"}
}