{
  "type": "Feature",
  "properties": {
    "addr:full":"2096 Petawawa Blvd Pembroke ON K8A 7G9",
    "addr:housenumber":"2096",
    "addr:postcode":"k8a 7g9",
    "addr:street":"Petawawa Blvd",
    "iso:country":"CA",
    "sg:address":"2096 Petawawa Blvd",
    "sg:city":"Pembroke",
    "sg:classifiers":[
        {
            "category":"Home & Garden",
            "subcategory":"Home Furnishings",
            "type":"Retail Goods"
        }
    ],
    "sg:phone":"+1 613 732 4789",
    "sg:postcode":"K8A 7G9",
    "sg:province":"ON",
    "sg:tags":[
        "machine",
        "sewing",
        "quilting"
    ],
    "wof:name":"Algonquin Sewing Ctr",
    "wof:placetype":"venue"
},
  "geometry": {"coordinates":[-77.112213,45.826481],"type":"Point"}
}