{
  "type": "Feature",
  "properties": {
    "addr:full":"PO Box 366 Arviat NU X0C 0E0",
    "addr:housenumber":"po",
    "addr:postcode":"x0c 0e0",
    "addr:street":"Box 366",
    "iso:country":"CA",
    "sg:address":"PO Box 366",
    "sg:city":"Arviat",
    "sg:classifiers":[
        {
            "category":"Shopping",
            "subcategory":"Hobbies, Toys, & Games",
            "type":"Retail Goods"
        }
    ],
    "sg:phone":"+1 867 857 2713",
    "sg:postcode":"X0C 0E0",
    "sg:province":"NU",
    "sg:tags":[
        "craft",
        "supply"
    ],
    "wof:name":"Kiluk Limited",
    "wof:placetype":"venue"
},
  "geometry": {"coordinates":[-94.058998,61.109707],"type":"Point"}
}