{
  "type": "Feature",
  "properties": {
    "addr:full":"26 16th Ave Hanover ON N4N 3V5",
    "addr:housenumber":"26",
    "addr:postcode":"n4n 3v5",
    "addr:street":"16Th Ave",
    "iso:country":"CA",
    "sg:address":"26 16th Ave",
    "sg:city":"Hanover",
    "sg:classifiers":[
        {
            "category":"Manufacturing",
            "subcategory":"Furniture",
            "type":"Manufacturing & Wholesale Goods"
        }
    ],
    "sg:phone":"+1 519 364 4455",
    "sg:postcode":"N4N 3V5",
    "sg:province":"ON",
    "wof:name":"Arbour Hill Custom Furniture",
    "wof:placetype":"venue"
},
  "geometry": {"coordinates":[-81.01416778559999,44.1417350769],"type":"Point"}
}