{
  "type": "Feature",
  "properties": {
    "iso:country":"CA",
    "sg:address":"26 16th Ave",
    "sg:city":"Hanover",
    "sg:classifiers":[
        {
            "category":"Manufacturing",
            "subcategory":"Furniture",
            "type":"Manufacturing & Wholesale Goods"
        }
    ],
    "sg:phone":"+1 519 364 4455",
    "sg:postcode":"N4N 3V5",
    "sg:province":"ON",
    "wof:name":"Arbour Hill Custom Furniture",
    "wof:placetype":"venue"
},
  "geometry": {"coordinates":[-81.01416778559999,44.1417350769],"type":"Point"}
}