{
  "type": "Feature",
  "properties": {
    "iso:country":"CA",
    "sg:address":"1556 Lasalle Blvd",
    "sg:city":"Sudbury",
    "sg:classifiers":[
        {
            "category":"Restaurant",
            "type":"Food & Drink"
        }
    ],
    "sg:phone":"+1 705 674 0703",
    "sg:postcode":"P3A 1Z7",
    "sg:province":"ON",
    "wof:name":"Mr Toppers Pizza Ltd",
    "wof:placetype":"venue"
},
  "geometry": {"coordinates":[-80.94017791749999,46.5221786499],"type":"Point"}
}