{
  "type": "Feature",
  "properties": {
    "addr:full":"357 Eveline St Selkirk MB R1A 1N2",
    "addr:housenumber":"357",
    "addr:postcode":"r1a 1n2",
    "addr:street":"Eveline St",
    "iso:country":"CA",
    "sg:address":"357 Eveline St",
    "sg:city":"Selkirk",
    "sg:classifiers":[
        {
            "category":"Manufacturing",
            "subcategory":"Printing",
            "type":"Manufacturing & Wholesale Goods"
        }
    ],
    "sg:phone":"+1 204 482 5438",
    "sg:postcode":"R1A 1N2",
    "sg:province":"MB",
    "sg:tags":[
        "printer"
    ],
    "wof:name":"Daerwood Press Ltd",
    "wof:placetype":"venue"
},
  "geometry": {"coordinates":[-96.870705,50.142555],"type":"Point"}
}