{
  "type": "Feature",
  "properties": {
    "addr:full":"27 Rue Perrault Sainte-Anne-DE-Bellevue QC H9X 2E1",
    "addr:housenumber":"27",
    "addr:postcode":"h9x 2e1",
    "addr:street":"Rue Perrault",
    "iso:country":"CA",
    "sg:address":"27 Rue Perrault",
    "sg:city":"Sainte-Anne-DE-Bellevue",
    "sg:classifiers":[
        {
            "category":"Manufacturing",
            "subcategory":"Tools & Machinery",
            "type":"Manufacturing & Wholesale Goods"
        }
    ],
    "sg:phone":"+1 514 457 3236",
    "sg:postcode":"H9X 2E1",
    "sg:province":"QC",
    "sg:tags":[
        "water",
        "equipment",
        "works",
        "landscape",
        "contractor"
    ],
    "wof:name":"Aux Rythmes Des Saisons Inc",
    "wof:placetype":"venue"
},
  "geometry": {"coordinates":[-73.946434,45.405293],"type":"Point"}
}