{
  "type": "Feature",
  "properties": {
    "addr:full":"170 Rue Des Champs-Elysees Chicoutimi QC G7H 2V6",
    "addr:housenumber":"170",
    "addr:postcode":"g7h 2v6",
    "addr:street":"Rue Des Champs-Elysees",
    "iso:country":"CA",
    "sg:address":"170 Rue Des Champs-Elysees",
    "sg:city":"Chicoutimi",
    "sg:classifiers":[
        {
            "category":"Food & Beverages",
            "subcategory":"Groceries & Convenience Stores",
            "type":"Retail Goods"
        }
    ],
    "sg:phone":"+1 418 545 2644",
    "sg:postcode":"G7H 2V6",
    "sg:province":"QC",
    "wof:name":"Couche Tard",
    "wof:placetype":"venue"
},
  "geometry": {"coordinates":[-71.063774,48.415562],"type":"Point"}
}