{
  "type": "Feature",
  "properties": {
    "addr:full":"500 Ch Des Anciens Deux-Montagnes QC J7R 6A7",
    "addr:housenumber":"500",
    "addr:postcode":"j7r 6a7",
    "addr:street":"Ch Des Anciens",
    "iso:country":"CA",
    "sg:address":"500 Ch Des Anciens",
    "sg:city":"Deux-Montagnes",
    "sg:classifiers":[
        {
            "category":"Banks & Credit Unions",
            "subcategory":"Bank",
            "type":"Services"
        }
    ],
    "sg:phone":"+1 450 473 6798",
    "sg:postcode":"J7R 6A7",
    "sg:province":"QC",
    "wof:name":"Caisse D'Economie Deux-Mntgns",
    "wof:placetype":"venue"
},
  "geometry": {"coordinates":[-73.908524,45.545815],"type":"Point"}
}