{
  "type": "Feature",
  "properties": {
    "addr:full":"516 172 Rte W St-Nazaire-Du-Lac-St-Jean QC G0W 2V0",
    "addr:housenumber":"172",
    "addr:postcode":"g0w 2v0",
    "addr:street":"Rte W St-Nazaire-Du-Lac-St-Jean",
    "iso:country":"CA",
    "sg:address":"516 172 Rte W",
    "sg:city":"St-Nazaire-Du-Lac-St-Jean",
    "sg:classifiers":[
        {
            "category":"Wholesale",
            "subcategory":"Machinery & Supplies",
            "type":"Manufacturing & Wholesale Goods"
        }
    ],
    "sg:phone":"+1 418 668 0757",
    "sg:postcode":"G0W 2V0",
    "sg:province":"QC",
    "sg:tags":[
        "forestry",
        "machine",
        "shop",
        "timber"
    ],
    "wof:name":"Produits Forestiers Munger Inc",
    "wof:placetype":"venue"
},
  "geometry": {"coordinates":[-71.48893,48.575619],"type":"Point"}
}