{
  "type": "Feature",
  "properties": {
    "addr:full":"12875 16 Ave Surrey BC V4A 1N5",
    "addr:housenumber":"12875",
    "addr:postcode":"v4a 1n5",
    "addr:street":"16 Ave",
    "iso:country":"CA",
    "sg:address":"12875 16 Ave",
    "sg:city":"Surrey",
    "sg:classifiers":[
        {
            "category":"Retail",
            "subcategory":"Repair Shop",
            "type":"Services"
        }
    ],
    "sg:phone":"+1 604 538 9600",
    "sg:postcode":"V4A 1N5",
    "sg:province":"BC",
    "sg:tags":[
        "appliance"
    ],
    "wof:name":"Ranger's Ocean Park Appliance",
    "wof:placetype":"venue"
},
  "geometry": {"coordinates":[-122.86488300000001,49.03141],"type":"Point"}
}