{
  "type": "Feature",
  "properties": {
    "addr:full":"1105 Rue Hains Drummondville QC J2C 6G6",
    "addr:housenumber":"1105",
    "addr:postcode":"j2c 6g6",
    "addr:street":"Rue Hains",
    "iso:country":"CA",
    "sg:address":"1105 Rue Hains",
    "sg:city":"Drummondville",
    "sg:classifiers":[
        {
            "category":"Shopping",
            "subcategory":"Computers & Home Electronics",
            "type":"Retail Goods"
        }
    ],
    "sg:phone":"+1 819 472 3770",
    "sg:postcode":"J2C 6G6",
    "sg:province":"QC",
    "sg:tags":[
        "software"
    ],
    "wof:name":"Siga Informatique Inc",
    "wof:placetype":"venue"
},
  "geometry": {"coordinates":[-72.525002,45.897465],"type":"Point"}
}