{
  "type": "Feature",
  "properties": {
    "addr:full":"442 Trans Canada Hwy Duncan BC V9L 3R6",
    "addr:housenumber":"442",
    "addr:postcode":"v9l 3r6",
    "addr:street":"Trans Canada Hwy",
    "iso:country":"CA",
    "sg:address":"442 Trans Canada Hwy",
    "sg:city":"Duncan",
    "sg:classifiers":[
        {
            "category":"Personal",
            "subcategory":"Beauty Salon",
            "type":"Services"
        }
    ],
    "sg:phone":"+1 250 746 8283",
    "sg:postcode":"V9L 3R6",
    "sg:province":"BC",
    "wof:name":"Tran's Haircuts",
    "wof:placetype":"venue"
},
  "geometry": {"coordinates":[-123.698677,48.779263],"type":"Point"}
}