{
  "type": "Feature",
  "properties": {
    "addr:full":"96 Hodgson Rd Fredericton NB E3C 2G4",
    "addr:housenumber":"96",
    "addr:postcode":"e3c 2g4",
    "addr:street":"Hodgson Rd",
    "iso:country":"CA",
    "sg:address":"96 Hodgson Rd",
    "sg:city":"Fredericton",
    "sg:classifiers":[
        {
            "category":"Wholesale",
            "subcategory":"Construction Materials",
            "type":"Manufacturing & Wholesale Goods"
        }
    ],
    "sg:phone":"+1 506 462 7248",
    "sg:postcode":"E3C 2G4",
    "sg:province":"NB",
    "sg:tags":[
        "lumber"
    ],
    "wof:name":"Pro Lumber Inc",
    "wof:placetype":"venue"
},
  "geometry": {"coordinates":[-66.621864,45.913883],"type":"Point"}
}