{
  "type": "Feature",
  "properties": {
    "addr:full":"Quebec QC G1K 3J4",
    "addr:postcode":"g1k 3j4",
    "iso:country":"CA",
    "sg:city":"Quebec",
    "sg:phone":"+1 418 521 4544",
    "sg:postcode":"G1K 3J4",
    "sg:province":"QC",
    "sg:tags":[
        "oil",
        "gasoline"
    ],
    "wof:name":"Petroles Cadrin Inc",
    "wof:placetype":"venue"
},
  "geometry": {"coordinates":[-71.2213439941,46.8145599365],"type":"Point"}
}