{
  "type": "Feature",
  "properties": {
    "iso:country":"CA",
    "sg:address":"111 Rue DE L'Eglise",
    "sg:city":"Edmundston",
    "sg:classifiers":[
        {
            "category":"Shopping",
            "subcategory":"Clothing, Apparel, & Fashions",
            "type":"Retail Goods"
        }
    ],
    "sg:phone":"+1 506 739 8444",
    "sg:postcode":"E3V 1J9",
    "sg:province":"NB",
    "wof:name":"Boutique Marie Claire Inc",
    "wof:placetype":"venue"
},
  "geometry": {"coordinates":[-68.326775,47.366554],"type":"Point"}
}