{
  "type": "Feature",
  "properties": {
    "addr:full":"Scarborough ON M1B 1Y4",
    "addr:postcode":"m1b 1y4",
    "iso:country":"CA",
    "sg:city":"Scarborough",
    "sg:classifiers":[
        {
            "category":"Shopping",
            "subcategory":"Bicycles & Sporting Goods",
            "type":"Retail Goods"
        }
    ],
    "sg:phone":"+1 416 298 7724",
    "sg:postcode":"M1B 1Y4",
    "sg:province":"ON",
    "sg:tags":[
        "snowboard"
    ],
    "wof:name":"Kuu Sport Mfg Ltd",
    "wof:placetype":"venue"
},
  "geometry": {"coordinates":[-79.2356872559,43.8107795715],"type":"Point"}
}