{
  "type": "Feature",
  "properties": {
    "iso:country":"CA",
    "sg:city":"Montreal",
    "sg:classifiers":[
        {
            "category":"Shopping",
            "type":"Retail Goods"
        }
    ],
    "sg:phone":"+1 514 845 0063",
    "sg:postcode":"H2L 4H2",
    "sg:province":"QC",
    "sg:tags":[
        "art",
        "gallery",
        "dealer"
    ],
    "wof:name":"Dazibao Centre D'Animation",
    "wof:placetype":"venue"
},
  "geometry": {"coordinates":[-73.573921,45.521446],"type":"Point"}
}