{
  "type": "Feature",
  "properties": {
    "addr:full":"5520 7th Ave Regina SK S4T 0S7",
    "addr:housenumber":"5520",
    "addr:postcode":"s4t 0s7",
    "addr:street":"7Th Ave",
    "iso:country":"CA",
    "sg:address":"5520 7th Ave",
    "sg:city":"Regina",
    "sg:classifiers":[
        {
            "category":"Personal",
            "subcategory":"Beauty Salon",
            "type":"Services"
        }
    ],
    "sg:phone":"+1 306 949 0720",
    "sg:postcode":"S4T 0S7",
    "sg:province":"SK",
    "wof:name":"Styles on 7th",
    "wof:placetype":"venue"
},
  "geometry": {"coordinates":[-104.660087585,50.4585189819],"type":"Point"}
}