{
  "type": "Feature",
  "properties": {
    "addr:full":"5213 1st Ave Boyle AB T0A 0M0",
    "addr:housenumber":"5213",
    "addr:postcode":"t0a 0m0",
    "addr:street":"1St Ave",
    "iso:country":"CA",
    "sg:address":"5213 1st Ave",
    "sg:city":"Boyle",
    "sg:classifiers":[
        {
            "category":"Retail",
            "subcategory":"Laundry & Dry Cleaning",
            "type":"Services"
        }
    ],
    "sg:phone":"+1 780 689 4257",
    "sg:postcode":"T0A 0M0",
    "sg:province":"AB",
    "sg:tags":[
        "cleaners",
        "rug",
        "carpet"
    ],
    "wof:name":"K'N's Karpet Cleaning",
    "wof:placetype":"venue"
},
  "geometry": {"coordinates":[-112.80835,54.58791],"type":"Point"}
}