{
  "type": "Feature",
  "properties": {
    "addr:full":"274 St Clair Blvd Corunna ON N0N 1G0",
    "addr:housenumber":"274",
    "addr:postcode":"n0n 1g0",
    "addr:street":"St Clair Blvd",
    "iso:country":"CA",
    "sg:address":"274 St Clair Blvd",
    "sg:city":"Corunna",
    "sg:classifiers":[
        {
            "category":"Education",
            "subcategory":"School",
            "type":"Public Place"
        }
    ],
    "sg:phone":"+1 519 862 1089",
    "sg:postcode":"N0N 1G0",
    "sg:province":"ON",
    "wof:name":"Sir John Moore Community Schl",
    "wof:placetype":"venue"
},
  "geometry": {"coordinates":[-82.447098,42.878082],"type":"Point"}
}