{
  "type": "Feature",
  "properties": {
    "iso:country":"CA",
    "sg:address":"821 the Queensway",
    "sg:city":"Etobicoke",
    "sg:classifiers":[
        {
            "category":"Professional",
            "subcategory":"Lawyer & Legal Services",
            "type":"Services"
        }
    ],
    "sg:phone":"+1 416 253 1223",
    "sg:postcode":"M8Z 1N6",
    "sg:province":"ON",
    "sg:tags":[
        "attorney"
    ],
    "wof:name":"Di Iorio Law Offices",
    "wof:placetype":"venue"
},
  "geometry": {"coordinates":[-79.508148,43.624973],"type":"Point"}
}