{
  "type": "Feature",
  "properties": {
    "addr:full":"111 Hunt St Ajax ON L1S 1P3",
    "addr:housenumber":"111",
    "addr:postcode":"l1s 1p3",
    "addr:street":"Hunt St",
    "iso:country":"CA",
    "sg:address":"111 Hunt St",
    "sg:city":"Ajax",
    "sg:classifiers":[
        {
            "category":"Organizations",
            "subcategory":"Community Association",
            "type":"Services"
        }
    ],
    "sg:phone":"+1 905 683 7811",
    "sg:postcode":"L1S 1P3",
    "sg:province":"ON",
    "sg:tags":[
        "club"
    ],
    "wof:name":"Royal Canadian Legion",
    "wof:placetype":"venue"
},
  "geometry": {"coordinates":[-79.02323150629999,43.8465538025],"type":"Point"}
}