{
  "type": "Feature",
  "properties": {
    "addr:full":"8400 Huntington Rd Woodbridge ON L4L 1A5",
    "addr:housenumber":"8400",
    "addr:postcode":"l4l 1a5",
    "addr:street":"Huntington Rd",
    "iso:country":"CA",
    "sg:address":"8400 Huntington Rd",
    "sg:city":"Woodbridge",
    "sg:classifiers":[
        {
            "category":"Farming",
            "subcategory":"Farm",
            "type":"Manufacturing & Wholesale Goods"
        }
    ],
    "sg:phone":"+1 905 851 3892",
    "sg:postcode":"L4L 1A5",
    "sg:province":"ON",
    "wof:name":"Quality Farms",
    "wof:placetype":"venue"
},
  "geometry": {"coordinates":[-79.65070299999999,43.784153],"type":"Point"}
}