{
  "type": "Feature",
  "properties": {
    "iso:country":"CA",
    "sg:address":"8400 Huntington Rd",
    "sg:city":"Woodbridge",
    "sg:classifiers":[
        {
            "category":"Farming",
            "subcategory":"Farm",
            "type":"Manufacturing & Wholesale Goods"
        }
    ],
    "sg:phone":"+1 905 851 3892",
    "sg:postcode":"L4L 1A5",
    "sg:province":"ON",
    "wof:name":"Quality Farms",
    "wof:placetype":"venue"
},
  "geometry": {"coordinates":[-79.650703,43.784153],"type":"Point"}
}