{
  "type": "Feature",
  "properties": {
    "addr:full":"910 4 Ave S Lethbridge AB T1J 0P6",
    "addr:housenumber":"910",
    "addr:postcode":"t1j 0p6",
    "addr:street":"4 Ave S",
    "iso:country":"CA",
    "sg:address":"910 4 Ave S",
    "sg:city":"Lethbridge",
    "sg:classifiers":[
        {
            "category":"Government",
            "subcategory":"Office",
            "type":"Public Place"
        }
    ],
    "sg:phone":"+1 403 320 3950",
    "sg:postcode":"T1J 0P6",
    "sg:province":"AB",
    "sg:tags":[
        "village"
    ],
    "wof:name":"Lethbridge Assessment & Tax",
    "wof:placetype":"venue"
},
  "geometry": {"coordinates":[-112.833519,49.694458],"type":"Point"}
}