{
  "type": "Feature",
  "properties": {
    "addr:full":"296 Av Lafleur Lasalle QC H8R 3H5",
    "addr:postcode":"h8r 3h5",
    "addr:street":"296 Av Lafleur",
    "iso:country":"CA",
    "sg:address":"296 Av Lafleur",
    "sg:city":"Lasalle",
    "sg:classifiers":[
        {
            "category":"Retail",
            "subcategory":"Car Wash",
            "type":"Services"
        }
    ],
    "sg:phone":"+1 514 595 8345",
    "sg:postcode":"H8R 3H5",
    "sg:province":"QC",
    "sg:tags":[
        "polishing",
        "washing"
    ],
    "wof:name":"Lave Auto Lafleur Ltee",
    "wof:placetype":"venue"
},
  "geometry": {"coordinates":[-73.6483078003,45.4287261963],"type":"Point"}
}