{
  "type": "Feature",
  "properties": {
    "addr:full":"4247 Rue Saint-Felix Cap-Rouge QC G1Y 1X6",
    "addr:housenumber":"4247",
    "addr:postcode":"g1y 1x6",
    "addr:street":"Rue Saint-Felix",
    "iso:country":"CA",
    "sg:address":"4247 Rue Saint-Felix",
    "sg:city":"Cap-Rouge",
    "sg:classifiers":[
        {
            "category":"Retail",
            "subcategory":"Auto Repair",
            "type":"Services"
        }
    ],
    "sg:phone":"+1 418 653 3043",
    "sg:postcode":"G1Y 1X6",
    "sg:province":"QC",
    "sg:tags":[
        "brake"
    ],
    "wof:name":"Garage Michel Roberge",
    "wof:placetype":"venue"
},
  "geometry": {"coordinates":[-71.3455963135,46.7479629517],"type":"Point"}
}