{
  "type": "Feature",
  "properties": {
    "addr:full":"62 2nd Ave Gimli MB R0C 1B0",
    "addr:housenumber":"62",
    "addr:postcode":"r0c 1b0",
    "addr:street":"2Nd Ave",
    "iso:country":"CA",
    "sg:address":"62 2nd Ave",
    "sg:city":"Gimli",
    "sg:classifiers":[
        {
            "category":"Government",
            "subcategory":"Office",
            "type":"Public Place"
        }
    ],
    "sg:phone":"+1 204 642 6020",
    "sg:postcode":"R0C 1B0",
    "sg:province":"MB",
    "wof:name":"Manitoba Education & Training",
    "wof:placetype":"venue"
},
  "geometry": {"coordinates":[-96.9870834351,50.6344032288],"type":"Point"}
}