{
  "type": "Feature",
  "properties": {
    "addr:full":"Fort Vermilion AB T0H 1N0",
    "addr:postcode":"t0h 1n0",
    "addr:street":"Fort",
    "iso:country":"CA",
    "sg:city":"Fort Vermilion",
    "sg:classifiers":[
        {
            "category":"Organizations",
            "subcategory":"Professional Association",
            "type":"Services"
        }
    ],
    "sg:phone":"+1 780 927 3727",
    "sg:postcode":"T0H 1N0",
    "sg:province":"AB",
    "wof:name":"Tallcree Band Administration",
    "wof:placetype":"venue"
},
  "geometry": {"coordinates":[-110.858520508,53.3516693115],"type":"Point"}
}