{
  "type": "Feature",
  "properties": {
    "addr:full":"102 Rue Prince-Arthur E Montreal QC H2X 1B5",
    "addr:housenumber":"102",
    "addr:postcode":"h2x 1b5",
    "addr:street":"Rue Prince-Arthur E",
    "iso:country":"CA",
    "sg:address":"102 Rue Prince-Arthur E",
    "sg:city":"Montreal",
    "sg:classifiers":[
        {
            "category":"Restaurant",
            "type":"Food & Drink"
        }
    ],
    "sg:phone":"+1 514 849 0122",
    "sg:postcode":"H2X 1B5",
    "sg:province":"QC",
    "wof:name":"Cabane Grecque Restaurant",
    "wof:placetype":"venue"
},
  "geometry": {"coordinates":[-73.5716018677,45.5148887634],"type":"Point"}
}