{
  "type": "Feature",
  "properties": {
    "addr:full":"PO Box 75 Grise Fiord NU X0A 0J0",
    "addr:housenumber":"po box 75",
    "addr:postcode":"x0a 0j0",
    "iso:country":"CA",
    "sg:address":"PO Box 75",
    "sg:city":"Grise Fiord",
    "sg:classifiers":[
        {
            "category":"Education",
            "subcategory":"School",
            "type":"Public Place"
        }
    ],
    "sg:phone":"+1 867 980 9921",
    "sg:postcode":"X0A 0J0",
    "sg:province":"NU",
    "wof:name":"Umimmak School",
    "wof:placetype":"venue"
},
  "geometry": {"coordinates":[-82.905136,76.418396],"type":"Point"}
}