{
  "type": "Feature",
  "properties": {
    "addr:full":"177 Cross Ave Oakville ON L6J 2W7",
    "addr:housenumber":"177",
    "addr:postcode":"l6j 2w7",
    "addr:street":"Cross Ave",
    "iso:country":"CA",
    "sg:address":"177 Cross Ave",
    "sg:city":"Oakville",
    "sg:classifiers":[
        {
            "category":"Government",
            "subcategory":"Office",
            "type":"Public Place"
        }
    ],
    "sg:phone":"+1 905 845 0451",
    "sg:postcode":"L6J 2W7",
    "sg:province":"ON",
    "wof:name":"Ontario Transportation Mnstry",
    "wof:placetype":"venue"
},
  "geometry": {"coordinates":[-79.684853,43.455627],"type":"Point"}
}