{
  "type": "Feature",
  "properties": {
    "addr:full":"4045 Ch Du Moulin Sainte-Adele QC J8B 2H9",
    "addr:postcode":"4045;j8b 2h9",
    "addr:street":"Ch Du Moulin Sainte-Adele",
    "iso:country":"CA",
    "sg:address":"4045 Ch Du Moulin",
    "sg:city":"Sainte-Adele",
    "sg:classifiers":[
        {
            "category":"Building & Trades",
            "subcategory":"Plumbing",
            "type":"Services"
        }
    ],
    "sg:phone":"+1 450 229 3433",
    "sg:postcode":"J8B 2H9",
    "sg:province":"QC",
    "sg:tags":[
        "excavating",
        "tank",
        "septic",
        "contractor"
    ],
    "wof:name":"Excavations R Gauthier Inc",
    "wof:placetype":"venue"
},
  "geometry": {"coordinates":[-74.17802399999999,45.978058],"type":"Point"}
}