{
  "type": "Feature",
  "properties": {
    "iso:country":"CA",
    "sg:address":"650 1st St E",
    "sg:city":"Canwood",
    "sg:classifiers":[
        {
            "category":"Recreation",
            "type":"Entertainment"
        }
    ],
    "sg:phone":"+1 306 468 2200",
    "sg:postcode":"S0J 0K0",
    "sg:province":"SK",
    "sg:tags":[
        "skating",
        "rink"
    ],
    "wof:name":"Canwood Skating Rink",
    "wof:placetype":"venue"
},
  "geometry": {"coordinates":[-106.60481299999999,53.359676],"type":"Point"}
}