{
  "type": "Feature",
  "properties": {
    "iso:country":"CA",
    "sg:city":"St Catharines",
    "sg:classifiers":[
        {
            "category":"Health Services",
            "subcategory":"Doctor",
            "type":"Services"
        }
    ],
    "sg:phone":"+1 905 704 1449",
    "sg:postcode":"L2S 3W2",
    "sg:province":"ON",
    "sg:tags":[
        "dentist"
    ],
    "wof:name":"Kostandoff, J DDS",
    "wof:placetype":"venue"
},
  "geometry": {"coordinates":[-79.274483,43.176708],"type":"Point"}
}