{
  "type": "Feature",
  "properties": {
    "addr:full":"1602 Fort St Victoria BC V8R 1H9",
    "addr:housenumber":"1602",
    "addr:postcode":"v8r 1h9",
    "addr:street":"Fort St",
    "iso:country":"CA",
    "sg:address":"1602 Fort St",
    "sg:city":"Victoria",
    "sg:classifiers":[
        {
            "category":"Retail",
            "subcategory":"Laundry & Dry Cleaning",
            "type":"Services"
        }
    ],
    "sg:phone":"+1 250 595 4141",
    "sg:postcode":"V8R 1H9",
    "sg:province":"BC",
    "sg:tags":[
        "cleaners"
    ],
    "wof:name":"Individual Dry Cleaners Ltd",
    "wof:placetype":"venue"
},
  "geometry": {"coordinates":[-123.336609,48.426762],"type":"Point"}
}