{
  "type": "Feature",
  "properties": {
    "addr:full":"1082 Woodland Dr Bathurst NB E2A 5V6",
    "addr:housenumber":"1082",
    "addr:postcode":"e2a 5v6",
    "addr:street":"Woodland Dr",
    "iso:country":"CA",
    "sg:address":"1082 Woodland Dr",
    "sg:city":"Bathurst",
    "sg:classifiers":[
        {
            "category":"Shopping",
            "subcategory":"Hobbies, Toys, & Games",
            "type":"Retail Goods"
        }
    ],
    "sg:phone":"+1 506 548 8706",
    "sg:postcode":"E2A 5V6",
    "sg:province":"NB",
    "sg:tags":[
        "craft",
        "supply"
    ],
    "wof:name":"Stitching Post",
    "wof:placetype":"venue"
},
  "geometry": {"coordinates":[-65.61414337159999,47.6240501404],"type":"Point"}
}