{
  "type": "Feature",
  "properties": {
    "iso:country":"CA",
    "sg:address":"1363 King St N",
    "sg:city":"St Jacobs",
    "sg:classifiers":[
        {
            "category":"Home & Garden",
            "subcategory":"Home Furnishings",
            "type":"Retail Goods"
        }
    ],
    "sg:phone":"+1 519 664 1192",
    "sg:postcode":"N0B 2N0",
    "sg:province":"ON",
    "sg:tags":[
        "linen"
    ],
    "wof:name":"Mary Catherine's Linen & Lace",
    "wof:placetype":"venue"
},
  "geometry": {"coordinates":[-80.5540847778,43.5372047424],"type":"Point"}
}