{
  "type": "Feature",
  "properties": {
    "addr:full":"21 Belmont St Moncton NB E1C 6X3",
    "addr:housenumber":"21",
    "addr:postcode":"e1c 6x3",
    "addr:street":"Belmont St",
    "iso:country":"CA",
    "sg:address":"21 Belmont St",
    "sg:city":"Moncton",
    "sg:classifiers":[
        {
            "category":"Building & Trades",
            "subcategory":"Landscaping Services",
            "type":"Services"
        }
    ],
    "sg:phone":"+1 506 853 0910",
    "sg:postcode":"E1C 6X3",
    "sg:province":"NB",
    "sg:tags":[
        "machinery",
        "landscape",
        "contractor"
    ],
    "wof:name":"City Backhoe Svc Ltd",
    "wof:placetype":"venue"
},
  "geometry": {"coordinates":[-64.801399,46.096272],"type":"Point"}
}