{
  "type": "Feature",
  "properties": {
    "addr:full":"933 15E Av Laval QC H7R 5J6",
    "addr:housenumber":"933",
    "addr:postcode":"h7r 5j6",
    "addr:street":"15E Av",
    "iso:country":"CA",
    "sg:address":"933 15E Av",
    "sg:city":"Laval",
    "sg:classifiers":[
        {
            "category":"Manufacturing",
            "subcategory":"Pottery",
            "type":"Manufacturing & Wholesale Goods"
        }
    ],
    "sg:phone":"+1 450 627 2552",
    "sg:postcode":"H7R 5J6",
    "sg:province":"QC",
    "wof:name":"Sam-Fra",
    "wof:placetype":"venue"
},
  "geometry": {"coordinates":[-73.8552474976,45.5595817566],"type":"Point"}
}