{
  "type": "Feature",
  "properties": {
    "iso:country":"CA",
    "sg:city":"Calgary",
    "sg:classifiers":[
        {
            "category":"Mining & Drilling",
            "type":"Manufacturing & Wholesale Goods"
        }
    ],
    "sg:phone":"+1 403 266 6291",
    "sg:postcode":"T2P 0J1",
    "sg:province":"AB",
    "sg:tags":[
        "company",
        "oil"
    ],
    "wof:name":"Adeco Exploration CO Ltd",
    "wof:placetype":"venue"
},
  "geometry": {"coordinates":[-114.068947,51.04932],"type":"Point"}
}