{
  "type": "Feature",
  "properties": {
    "iso:country":"CA",
    "sg:address":"61 Ainslie St S",
    "sg:city":"Cambridge",
    "sg:classifiers":[
        {
            "category":"Sports & Exercise",
            "subcategory":"Bowling",
            "type":"Entertainment"
        }
    ],
    "sg:phone":"+1 519 621 6100",
    "sg:postcode":"N1R 3K4",
    "sg:province":"ON",
    "sg:tags":[
        "center"
    ],
    "wof:name":"Dickson Bowl",
    "wof:placetype":"venue"
},
  "geometry": {"coordinates":[-80.3137512207,43.3563652039],"type":"Point"}
}