{
  "type": "Feature",
  "properties": {
    "addr:full":"523 Island View Rd #10 Roseneath ON K0K 2X0",
    "addr:housenumber":"523",
    "addr:postcode":"k0k 2x0",
    "addr:street":"Island View Rd # 10",
    "iso:country":"CA",
    "sg:address":"523 Island View Rd #10",
    "sg:city":"Roseneath",
    "sg:classifiers":[
        {
            "category":"Travel",
            "subcategory":"Hotels & Motels",
            "type":"Entertainment"
        }
    ],
    "sg:phone":"+1 905 352 2181",
    "sg:postcode":"K0K 2X0",
    "sg:province":"ON",
    "sg:tags":[
        "cottage",
        "cabin"
    ],
    "wof:name":"Glengarry Tourist Cottages",
    "wof:placetype":"venue"
},
  "geometry": {"coordinates":[-78.057236,44.193539],"type":"Point"}
}