{
  "type": "Feature",
  "properties": {
    "addr:full":"715 Rue DE Maskinonge Sainte-Foy QC G1X 2N5",
    "addr:housenumber":"715",
    "addr:postcode":"g1x 2n5",
    "addr:street":"Rue De Maskinonge",
    "iso:country":"CA",
    "sg:address":"715 Rue DE Maskinonge",
    "sg:city":"Sainte-Foy",
    "sg:classifiers":[
        {
            "category":"Professional",
            "subcategory":"Business Services",
            "type":"Services"
        }
    ],
    "sg:phone":"+1 418 666 6666",
    "sg:postcode":"G1X 2N5",
    "sg:province":"QC",
    "sg:tags":[
        "information",
        "referral"
    ],
    "wof:name":"Interactivites",
    "wof:placetype":"venue"
},
  "geometry": {"coordinates":[-71.3152923584,46.7802314758],"type":"Point"}
}