{
  "type": "Feature",
  "properties": {
    "addr:full":"307 Sheppard Ave W North York ON M2N 1N6",
    "addr:housenumber":"307",
    "addr:postcode":"m2n 1n6",
    "addr:street":"Sheppard Ave W",
    "iso:country":"CA",
    "sg:address":"307 Sheppard Ave W",
    "sg:city":"North York",
    "sg:classifiers":[
        {
            "category":"Health Services",
            "subcategory":"Doctor",
            "type":"Services"
        }
    ],
    "sg:phone":"+1 416 221 1177",
    "sg:postcode":"M2N 1N6",
    "sg:province":"ON",
    "sg:tags":[
        "physician",
        "surgeon"
    ],
    "wof:name":"Kosoy, Martin H MD",
    "wof:placetype":"venue"
},
  "geometry": {"coordinates":[-79.425819,43.758148],"type":"Point"}
}