{
  "type": "Feature",
  "properties": {
    "addr:full":"3270 50E Av Grand-Mere QC G9T 1A3",
    "addr:housenumber":"3270",
    "addr:postcode":"g9t 1a3",
    "addr:street":"50E Av Grand-Mere",
    "iso:country":"CA",
    "sg:address":"3270 50E Av",
    "sg:city":"Grand-Mere",
    "sg:classifiers":[
        {
            "category":"Food & Beverages",
            "subcategory":"Groceries & Convenience Stores",
            "type":"Retail Goods"
        }
    ],
    "sg:phone":"+1 819 538 2032",
    "sg:postcode":"G9T 1A3",
    "sg:province":"QC",
    "sg:tags":[
        "grocer"
    ],
    "wof:name":"Depanneur Ste-Flore",
    "wof:placetype":"venue"
},
  "geometry": {"coordinates":[-72.73619100000001,46.615383],"type":"Point"}
}