{
  "type": "Feature",
  "properties": {
    "addr:full":"104 Rue Bruce Cowansville QC J2K 3A6",
    "addr:housenumber":"104",
    "addr:postcode":"j2k 3a6",
    "addr:street":"Rue Bruce",
    "iso:country":"CA",
    "sg:address":"104 Rue Bruce",
    "sg:city":"Cowansville",
    "sg:classifiers":[
        {
            "category":"Organizations",
            "subcategory":"Religious Organization",
            "type":"Services"
        }
    ],
    "sg:phone":"+1 514 263 2662",
    "sg:postcode":"J2K 3A6",
    "sg:province":"QC",
    "sg:tags":[
        "church"
    ],
    "wof:name":"Trinity Anglican Church",
    "wof:placetype":"venue"
},
  "geometry": {"coordinates":[-72.752617,45.208473],"type":"Point"}
}