{
  "type": "Feature",
  "properties": {
    "addr:full":"3060 105 Hwy Vermilion Bay ON P0V 2V0",
    "addr:housenumber":"3060",
    "addr:postcode":"p0v 2v0",
    "addr:street":"105 Hwy Vermilion",
    "iso:country":"CA",
    "sg:address":"3060 105 Hwy",
    "sg:city":"Vermilion Bay",
    "sg:phone":"+1 807 227 2669",
    "sg:postcode":"P0V 2V0",
    "sg:province":"ON",
    "sg:tags":[
        "oil"
    ],
    "wof:name":"Steve Struk Ltd",
    "wof:placetype":"venue"
},
  "geometry": {"coordinates":[-93.383743,49.858482],"type":"Point"}
}