{
  "type": "Feature",
  "properties": {
    "iso:country":"CA",
    "sg:address":"677 King St E",
    "sg:city":"Hamilton",
    "sg:classifiers":[
        {
            "category":"Restaurant",
            "type":"Food & Drink"
        }
    ],
    "sg:phone":"+1 905 528 8882",
    "sg:postcode":"L8M 1A1",
    "sg:province":"ON",
    "sg:tags":[
        "out",
        "pizza"
    ],
    "wof:name":"King Pizza",
    "wof:placetype":"venue"
},
  "geometry": {"coordinates":[-79.84847259519999,43.2521438599],"type":"Point"}
}