{
  "type": "Feature",
  "properties": {
    "addr:full":"5333 Aspen Dr West Vancouver BC V7W 3C8",
    "addr:housenumber":"5333",
    "addr:postcode":"v7w 3c8",
    "addr:street":"Aspen Dr",
    "iso:country":"CA",
    "sg:address":"5333 Aspen Dr",
    "sg:city":"West Vancouver",
    "sg:classifiers":[
        {
            "category":"Wholesale",
            "subcategory":"Metals & Minerals",
            "type":"Manufacturing & Wholesale Goods"
        }
    ],
    "sg:phone":"+1 604 922 9101",
    "sg:postcode":"V7W 3C8",
    "sg:province":"BC",
    "sg:tags":[
        "product",
        "laminated",
        "structural"
    ],
    "wof:name":"Timber Systems Ltd",
    "wof:placetype":"venue"
},
  "geometry": {"coordinates":[-123.25598100000001,49.352852],"type":"Point"}
}