{
  "type": "Feature",
  "properties": {
    "iso:country":"CA",
    "sg:city":"Scarborough",
    "sg:classifiers":[
        {
            "category":"Shopping",
            "subcategory":"Pharmacy",
            "type":"Retail Goods"
        }
    ],
    "sg:phone":"+1 416 438 6501",
    "sg:postcode":"M1P 2V1",
    "sg:province":"ON",
    "wof:name":"Axis 3000 Medical Pharmacy",
    "wof:placetype":"venue"
},
  "geometry": {"coordinates":[-79.24881744379999,43.7550010681],"type":"Point"}
}