{
  "type": "Feature",
  "properties": {
    "addr:full":"376 Boul Tessier Lachute QC J8H 1C7",
    "addr:housenumber":"376",
    "addr:postcode":"j8h 1c7",
    "addr:street":"Boul Tessier",
    "iso:country":"CA",
    "sg:address":"376 Boul Tessier",
    "sg:city":"Lachute",
    "sg:classifiers":[
        {
            "category":"Insurance",
            "subcategory":"Insurance Agent",
            "type":"Services"
        }
    ],
    "sg:phone":"+1 450 562 8833",
    "sg:postcode":"J8H 1C7",
    "sg:province":"QC",
    "wof:name":"Assurance Promutuel Deux",
    "wof:placetype":"venue"
},
  "geometry": {"coordinates":[-74.3368988037,45.648727417],"type":"Point"}
}