{
  "type": "Feature",
  "properties": {
    "addr:full":"70 Milner Ave Scarborough ON M1S 3P8",
    "addr:housenumber":"70",
    "addr:postcode":"m1s 3p8",
    "addr:street":"Milner Ave",
    "iso:country":"CA",
    "sg:address":"70 Milner Ave",
    "sg:city":"Scarborough",
    "sg:classifiers":[
        {
            "category":"Building & Trades",
            "subcategory":"Construction",
            "type":"Services"
        }
    ],
    "sg:phone":"+1 416 292 7100",
    "sg:postcode":"M1S 3P8",
    "sg:province":"ON",
    "sg:tags":[
        "contractor"
    ],
    "wof:name":"Tradeworks Interiors Canada",
    "wof:placetype":"venue"
},
  "geometry": {"coordinates":[-79.251183,43.784294],"type":"Point"}
}