{
  "type": "Feature",
  "properties": {
    "addr:full":"Coldwater ON L0K 1E0",
    "addr:postcode":"l0k 1e0",
    "iso:country":"CA",
    "sg:city":"Coldwater",
    "sg:classifiers":[
        {
            "category":"Government",
            "subcategory":"Office",
            "type":"Public Place"
        }
    ],
    "sg:phone":"+1 705 686 7267",
    "sg:postcode":"L0K 1E0",
    "sg:province":"ON",
    "sg:tags":[
        "village"
    ],
    "wof:name":"Matchedash Twp Roads Dept",
    "wof:placetype":"venue"
},
  "geometry": {"coordinates":[-79.644363,44.710224],"type":"Point"}
}