{
  "type": "Feature",
  "properties": {
    "iso:country":"CA",
    "sg:address":"196 Rue Richelieu",
    "sg:city":"Beloeil",
    "sg:classifiers":[
        {
            "category":"Health Services",
            "subcategory":"Nursing And Care Facility",
            "type":"Services"
        }
    ],
    "sg:phone":"+1 450 467 3491",
    "sg:postcode":"J3G 4P1",
    "sg:province":"QC",
    "sg:tags":[
        "home",
        "retirement",
        "community"
    ],
    "wof:name":"Domaine Du Bel Accueil",
    "wof:placetype":"venue"
},
  "geometry": {"coordinates":[-73.2113418579,45.5500907898],"type":"Point"}
}