{
  "type": "Feature",
  "properties": {
    "addr:full":"4949 Rue Clark Montreal QC H2T 2T6",
    "addr:housenumber":"4949",
    "addr:postcode":"h2t 2t6",
    "addr:street":"Rue Clark",
    "iso:country":"CA",
    "sg:address":"4949 Rue Clark",
    "sg:city":"Montreal",
    "sg:classifiers":[
        {
            "category":"Cinema",
            "subcategory":"Movie Theater",
            "type":"Entertainment"
        }
    ],
    "sg:phone":"+1 514 845 7272",
    "sg:postcode":"H2T 2T6",
    "sg:province":"QC",
    "wof:name":"Theatre Petit A Petit",
    "wof:placetype":"venue"
},
  "geometry": {"coordinates":[-73.591042,45.521687],"type":"Point"}
}