{
  "type": "Feature",
  "properties": {
    "addr:full":"128 Ch Du Tremblay Boucherville QC J4B 6Z6",
    "addr:housenumber":"128",
    "addr:postcode":"j4b 6z6",
    "addr:street":"Ch Du Tremblay",
    "iso:country":"CA",
    "sg:address":"128 Ch Du Tremblay",
    "sg:city":"Boucherville",
    "sg:classifiers":[
        {
            "category":"Freight",
            "type":"Transportation"
        }
    ],
    "sg:phone":"+1 450 449 2511",
    "sg:postcode":"J4B 6Z6",
    "sg:province":"QC",
    "sg:tags":[
        "trucking"
    ],
    "wof:name":"Teamrep Logistique Intl Inc",
    "wof:placetype":"venue"
},
  "geometry": {"coordinates":[-73.426422,45.560368],"type":"Point"}
}