{
  "type": "Feature",
  "properties": {
    "addr:full":"Harris Dr Marystown NL A0E 2M0",
    "addr:postcode":"a0e 2m0",
    "addr:street":"Harris",
    "iso:country":"CA",
    "sg:address":"Harris Dr",
    "sg:city":"Marystown",
    "sg:classifiers":[
        {
            "category":"Social Services",
            "subcategory":"Child Care",
            "type":"Services"
        }
    ],
    "sg:phone":"+1 709 279 5300",
    "sg:postcode":"A0E 2M0",
    "sg:province":"NL",
    "wof:name":"Explore & Discover Pre School",
    "wof:placetype":"venue"
},
  "geometry": {"coordinates":[-55.165783,47.165718],"type":"Point"}
}