{
  "type": "Feature",
  "properties": {
    "addr:full":"Toronto ON M5V 1M6",
    "addr:postcode":"m5v 1m6",
    "iso:country":"CA",
    "sg:city":"Toronto",
    "sg:classifiers":[
        {
            "category":"Retail",
            "subcategory":"Auto Repair",
            "type":"Services"
        }
    ],
    "sg:phone":"+1 416 504 7554",
    "sg:postcode":"M5V 1M6",
    "sg:province":"ON",
    "sg:tags":[
        "body",
        "automobile",
        "painting"
    ],
    "wof:name":"Bianchi Brothers Auto Body",
    "wof:placetype":"venue"
},
  "geometry": {"coordinates":[-79.40074199999999,43.644367],"type":"Point"}
}