{
  "type": "Feature",
  "properties": {
    "iso:country":"CA",
    "sg:address":"8525 Mccowan Rd # 205",
    "sg:city":"Markham",
    "sg:classifiers":[
        {
            "category":"Health Services",
            "subcategory":"Doctor",
            "type":"Services"
        }
    ],
    "sg:phone":"+1 905 471 3292",
    "sg:postcode":"L3P 5E5",
    "sg:province":"ON",
    "sg:tags":[
        "dentist"
    ],
    "wof:name":"Ingles, John L DDS",
    "wof:placetype":"venue"
},
  "geometry": {"coordinates":[-79.284538269,43.8680076599],"type":"Point"}
}