{
  "type": "Feature",
  "properties": {
    "addr:full":"456 Rue Principale O Magog QC J1X 2A9",
    "addr:housenumber":"456",
    "addr:postcode":"j1x 2a9",
    "addr:street":"Rue Principale O",
    "iso:country":"CA",
    "sg:address":"456 Rue Principale O",
    "sg:city":"Magog",
    "sg:classifiers":[
        {
            "category":"Shopping",
            "subcategory":"Clothing, Apparel, & Fashions",
            "type":"Retail Goods"
        }
    ],
    "sg:phone":"+1 819 843 9244",
    "sg:postcode":"J1X 2A9",
    "sg:province":"QC",
    "sg:tags":[
        "wig",
        "toupee",
        "hairpiece"
    ],
    "wof:name":"Chez Le Barbier",
    "wof:placetype":"venue"
},
  "geometry": {"coordinates":[-72.13555100000001,45.261024],"type":"Point"}
}