{
  "type": "Feature",
  "properties": {
    "iso:country":"CA",
    "sg:address":"54 Upper Centennial Pky",
    "sg:city":"Stoney Creek",
    "sg:classifiers":[
        {
            "category":"Wholesale",
            "subcategory":"Auto Parts",
            "type":"Manufacturing & Wholesale Goods"
        }
    ],
    "sg:phone":"+1 905 385 9292",
    "sg:postcode":"L8J 2V8",
    "sg:province":"ON",
    "sg:tags":[
        "automobile",
        "rebuilt"
    ],
    "wof:name":"Barry Humphrey Enterprises Ltd",
    "wof:placetype":"venue"
},
  "geometry": {"coordinates":[-79.7746353149,43.1773109436],"type":"Point"}
}