{
  "type": "Feature",
  "properties": {
    "addr:full":"301 Ch Des Vaccanciers Des Ruisseaux QC J9L 3G6",
    "addr:housenumber":"301",
    "addr:postcode":"j9l 3g6",
    "addr:street":"Ch Des Vaccanciers Des Ruisseaux",
    "iso:country":"CA",
    "sg:address":"301 Ch Des Vaccanciers",
    "sg:city":"Des Ruisseaux",
    "sg:classifiers":[
        {
            "category":"Travel",
            "subcategory":"Campground",
            "type":"Entertainment"
        }
    ],
    "sg:phone":"+1 819 623 6093",
    "sg:postcode":"J9L 3G6",
    "sg:province":"QC",
    "wof:name":"Camping Du Baskatong",
    "wof:placetype":"venue"
},
  "geometry": {"coordinates":[-75.742836,46.646],"type":"Point"}
}