{
  "type": "Feature",
  "properties": {
    "addr:full":"3151 York St Port Coquitlam BC V3B 4A7",
    "addr:housenumber":"3151",
    "addr:postcode":"v3b 4a7",
    "addr:street":"York St",
    "iso:country":"CA",
    "sg:address":"3151 York St",
    "sg:city":"Port Coquitlam",
    "sg:classifiers":[
        {
            "category":"Organizations",
            "subcategory":"Religious Organization",
            "type":"Services"
        }
    ],
    "sg:phone":"+1 604 942 5322",
    "sg:postcode":"V3B 4A7",
    "sg:province":"BC",
    "sg:tags":[
        "church"
    ],
    "wof:name":"Hope Lutheran Church & School",
    "wof:placetype":"venue"
},
  "geometry": {"coordinates":[-122.764526,49.270306],"type":"Point"}
}