{
  "type": "Feature",
  "properties": {
    "addr:full":"1445 Gulf Shore Rd Hunter River PE C0A 1N0",
    "addr:housenumber":"1445",
    "addr:postcode":"c0a 1n0",
    "addr:street":"Gulf Shore Rd",
    "iso:country":"CA",
    "sg:address":"1445 Gulf Shore Rd",
    "sg:city":"Hunter River",
    "sg:classifiers":[
        {
            "category":"Travel",
            "subcategory":"Hotels & Motels",
            "type":"Entertainment"
        }
    ],
    "sg:phone":"+1 902 963 2025",
    "sg:postcode":"C0A 1N0",
    "sg:province":"PE",
    "sg:tags":[
        "cottage",
        "cabin"
    ],
    "wof:name":"Cavendish Beach Cottages",
    "wof:placetype":"venue"
},
  "geometry": {"coordinates":[-63.3431472778,46.3517608643],"type":"Point"}
}