{
  "type": "Feature",
  "properties": {
    "iso:country":"CA",
    "sg:address":"55 Standish Crt",
    "sg:city":"Mississauga",
    "sg:classifiers":[
        {
            "category":"Restaurant",
            "type":"Food & Drink"
        }
    ],
    "sg:phone":"+1 905 755 0021",
    "sg:postcode":"L5R 4A1",
    "sg:province":"ON",
    "sg:tags":[
        "caterer"
    ],
    "wof:name":"Select Sandwich Urban Kitchen",
    "wof:placetype":"venue"
},
  "geometry": {"coordinates":[-79.6837005615,43.62550354],"type":"Point"}
}