{
  "type": "Feature",
  "properties": {
    "addr:full":"34 Rue Flaubert Levis QC G6V 7N1",
    "addr:housenumber":"34",
    "addr:postcode":"g6v 7n1",
    "addr:street":"Rue Flaubert",
    "iso:country":"CA",
    "sg:address":"34 Rue Flaubert",
    "sg:city":"Levis",
    "sg:classifiers":[
        {
            "category":"Freight",
            "type":"Transportation"
        }
    ],
    "sg:phone":"+1 418 835 0010",
    "sg:postcode":"G6V 7N1",
    "sg:province":"QC",
    "sg:tags":[
        "courier"
    ],
    "wof:name":"Messagerie Nord-Sud Enr",
    "wof:placetype":"venue"
},
  "geometry": {"coordinates":[-71.16909800000001,46.785954],"type":"Point"}
}