{
  "type": "Feature",
  "properties": {
    "addr:full":"1273 Rue Blanchette Thetford Mines QC G6G 4H9",
    "addr:housenumber":"1273",
    "addr:postcode":"g6g 4h9",
    "addr:street":"Rue Blanchette",
    "iso:country":"CA",
    "sg:address":"1273 Rue Blanchette",
    "sg:city":"Thetford Mines",
    "sg:classifiers":[
        {
            "category":"Organizations",
            "subcategory":"Religious Organization",
            "type":"Services"
        }
    ],
    "sg:phone":"+1 418 335 2979",
    "sg:postcode":"G6G 4H9",
    "sg:province":"QC",
    "sg:tags":[
        "church"
    ],
    "wof:name":"Presbytere Ste-Marthe",
    "wof:placetype":"venue"
},
  "geometry": {"coordinates":[-71.3122177124,46.1079063416],"type":"Point"}
}