{
  "type": "Feature",
  "properties": {
    "addr:full":"12836 146 St NW Edmonton AB T5L 2H7",
    "addr:housenumber":"12836",
    "addr:postcode":"t5l 2h7",
    "addr:street":"146 St Nw",
    "iso:country":"CA",
    "sg:address":"12836 146 St NW",
    "sg:city":"Edmonton",
    "sg:classifiers":[
        {
            "category":"Building & Trades",
            "subcategory":"Construction",
            "type":"Services"
        }
    ],
    "sg:phone":"+1 780 454 3667",
    "sg:postcode":"T5L 2H7",
    "sg:province":"AB",
    "sg:tags":[
        "general",
        "contractor"
    ],
    "wof:name":"Churchill Corp",
    "wof:placetype":"venue"
},
  "geometry": {"coordinates":[-113.572014,53.585838],"type":"Point"}
}