{
  "type": "Feature",
  "properties": {
    "addr:full":"23985 Lougheed Hwy Maple Ridge BC V2W 1W1",
    "addr:housenumber":"23985",
    "addr:postcode":"v2w 1w1",
    "addr:street":"Lougheed Hwy",
    "iso:country":"CA",
    "sg:address":"23985 Lougheed Hwy",
    "sg:city":"Maple Ridge",
    "sg:classifiers":[
        {
            "category":"Autos & Motor Vehicles",
            "subcategory":"Fuel & Gas Station",
            "type":"Retail Goods"
        }
    ],
    "sg:phone":"+1 604 467 0933",
    "sg:postcode":"V2W 1W1",
    "sg:province":"BC",
    "sg:tags":[
        "oil"
    ],
    "wof:name":"Tempo Albion",
    "wof:placetype":"venue"
},
  "geometry": {"coordinates":[-122.559479,49.183624],"type":"Point"}
}