{
  "type": "Feature",
  "properties": {
    "addr:full":"43 Cormier Village Rd Grand-Barachois NB E4P 6Z8",
    "addr:housenumber":"43",
    "addr:postcode":"e4p 6z8",
    "addr:street":"Cormier Village Rd",
    "iso:country":"CA",
    "sg:address":"43 Cormier Village Rd",
    "sg:city":"Grand-Barachois",
    "sg:classifiers":[
        {
            "category":"Shopping",
            "subcategory":"Bicycles & Sporting Goods",
            "type":"Retail Goods"
        }
    ],
    "sg:phone":"+1 506 532 6308",
    "sg:postcode":"E4P 6Z8",
    "sg:province":"NB",
    "wof:name":"Seacoast Fishing Supplies Ltd",
    "wof:placetype":"venue"
},
  "geometry": {"coordinates":[-64.4224700928,46.2242889404],"type":"Point"}
}