{
  "type": "Feature",
  "properties": {
    "addr:full":"34 Saint Marie St Collingwood ON L9Y 3K1",
    "addr:housenumber":"34",
    "addr:postcode":"l9y 3k1",
    "addr:street":"Saint Marie St",
    "iso:country":"CA",
    "sg:address":"34 Saint Marie St",
    "sg:city":"Collingwood",
    "sg:classifiers":[
        {
            "category":"Health Services",
            "subcategory":"Chiropractor",
            "type":"Services"
        }
    ],
    "sg:phone":"+1 705 446 2203",
    "sg:postcode":"L9Y 3K1",
    "sg:province":"ON",
    "wof:name":"Hitchcock Family Chiropractic",
    "wof:placetype":"venue"
},
  "geometry": {"coordinates":[-80.2157745361,44.5016975403],"type":"Point"}
}