{
  "type": "Feature",
  "properties": {
    "addr:full":"830 Boul Charest E Quebec QC G1K 8H8",
    "addr:housenumber":"830",
    "addr:postcode":"g1k 8h8",
    "addr:street":"Boul Charest E",
    "iso:country":"CA",
    "sg:address":"830 Boul Charest E",
    "sg:city":"Quebec",
    "sg:classifiers":[
        {
            "category":"Restaurant",
            "type":"Food & Drink"
        }
    ],
    "sg:phone":"+1 418 648 0891",
    "sg:postcode":"G1K 8H8",
    "sg:province":"QC",
    "wof:name":"Chez Ashton",
    "wof:placetype":"venue"
},
  "geometry": {"coordinates":[-71.21835327150001,46.8156356812],"type":"Point"}
}