{
  "type": "Feature",
  "properties": {
    "addr:full":"320 Portage Ave Fort Frances ON P9A 3P9",
    "addr:housenumber":"320",
    "addr:postcode":"p9a 3p9",
    "addr:street":"Portage Ave",
    "iso:country":"CA",
    "sg:address":"320 Portage Ave",
    "sg:city":"Fort Frances",
    "sg:classifiers":[
        {
            "category":"Government",
            "subcategory":"Police Station",
            "type":"Public Place"
        }
    ],
    "sg:phone":"+1 807 274 3322",
    "sg:postcode":"P9A 3P9",
    "sg:province":"ON",
    "sg:tags":[
        "department"
    ],
    "wof:name":"Ontario Police",
    "wof:placetype":"venue"
},
  "geometry": {"coordinates":[-93.39543151860001,48.6081504822],"type":"Point"}
}