{
  "type": "Feature",
  "properties": {
    "addr:full":"Port Coquitlam BC V3C 6G5",
    "addr:postcode":"v3c 6g5",
    "iso:country":"CA",
    "sg:city":"Port Coquitlam",
    "sg:classifiers":[
        {
            "category":"Wholesale",
            "subcategory":"Machinery & Supplies",
            "type":"Manufacturing & Wholesale Goods"
        }
    ],
    "sg:phone":"+1 604 942 1645",
    "sg:postcode":"V3C 6G5",
    "sg:province":"BC",
    "sg:tags":[
        "plumbing",
        "contractor"
    ],
    "wof:name":"Westech Fire Protection System",
    "wof:placetype":"venue"
},
  "geometry": {"coordinates":[-122.756217956,49.2487411499],"type":"Point"}
}