{
  "type": "Feature",
  "properties": {
    "addr:full":"PO Box 10 Eden ON N0J 1H0",
    "addr:housenumber":"po box 10",
    "addr:postcode":"n0j 1h0",
    "iso:country":"CA",
    "sg:address":"PO Box 10",
    "sg:city":"Eden",
    "sg:classifiers":[
        {
            "category":"Organizations",
            "subcategory":"Religious Organization",
            "type":"Services"
        }
    ],
    "sg:phone":"+1 519 866 3686",
    "sg:postcode":"N0J 1H0",
    "sg:province":"ON",
    "sg:tags":[
        "church"
    ],
    "wof:name":"Eden Baptist Church",
    "wof:placetype":"venue"
},
  "geometry": {"coordinates":[-80.746185,42.793381],"type":"Point"}
}