{
  "type": "Feature",
  "properties": {
    "addr:full":"2900 Yonge St Toronto ON M4N 3N8",
    "addr:housenumber":"2900",
    "addr:postcode":"m4n 3n8",
    "addr:street":"Yonge St",
    "iso:country":"CA",
    "sg:address":"2900 Yonge St",
    "sg:city":"Toronto",
    "sg:classifiers":[
        {
            "category":"Social Services",
            "type":"Services"
        }
    ],
    "sg:phone":"+1 416 489 9960",
    "sg:postcode":"M4N 3N8",
    "sg:province":"ON",
    "sg:tags":[
        "counselor",
        "human",
        "relations"
    ],
    "wof:name":"Associates in Workplace",
    "wof:placetype":"venue"
},
  "geometry": {"coordinates":[-79.40164900000001,43.721382],"type":"Point"}
}