{
  "type": "Feature",
  "properties": {
    "addr:full":"441 Columbia St New Westminster BC V3L 1A9",
    "addr:housenumber":"441",
    "addr:postcode":"v3l 1a9",
    "addr:street":"Columbia",
    "iso:country":"CA",
    "sg:address":"441 Columbia St",
    "sg:city":"New Westminster",
    "sg:classifiers":[
        {
            "category":"Restaurant",
            "type":"Food & Drink"
        }
    ],
    "sg:phone":"+1 604 525 3473",
    "sg:postcode":"V3L 1A9",
    "sg:province":"BC",
    "wof:name":"Aldo's Pasta Bar Ltd",
    "wof:placetype":"venue"
},
  "geometry": {"coordinates":[-122.90593719500001,49.204334259],"type":"Point"}
}