{
  "type": "Feature",
  "properties": {
    "addr:full":"Laverlochere QC J0Z 2P0",
    "addr:postcode":"j0z 2p0",
    "iso:country":"CA",
    "sg:city":"Laverlochere",
    "sg:classifiers":[
        {
            "category":"Building & Trades",
            "subcategory":"Construction",
            "type":"Services"
        }
    ],
    "sg:phone":"+1 819 765 4111",
    "sg:postcode":"J0Z 2P0",
    "sg:province":"QC",
    "sg:tags":[
        "general",
        "contractor"
    ],
    "wof:name":"Transport Beaule Inc",
    "wof:placetype":"venue"
},
  "geometry": {"coordinates":[-79.35106658940001,47.4266166687],"type":"Point"}
}