{
  "type": "Feature",
  "properties": {
    "iso:country":"CA",
    "sg:city":"Mississauga",
    "sg:classifiers":[
        {
            "category":"Wholesale",
            "subcategory":"Machinery & Supplies",
            "type":"Manufacturing & Wholesale Goods"
        }
    ],
    "sg:phone":"+1 905 949 2741",
    "sg:postcode":"L5A 3P2",
    "sg:province":"ON",
    "sg:tags":[
        "equipment",
        "safety",
        "clothing"
    ],
    "wof:name":"Canadian Safety Equipment Inc",
    "wof:placetype":"venue"
},
  "geometry": {"coordinates":[-79.5960845947,43.5921554565],"type":"Point"}
}