{
  "type": "Feature",
  "properties": {
    "iso:country":"CA",
    "sg:address":"285 Balmoral St",
    "sg:city":"Winnipeg",
    "sg:classifiers":[
        {
            "category":"Personal",
            "subcategory":"Beauty Salon",
            "type":"Services"
        }
    ],
    "sg:phone":"+1 204 786 5655",
    "sg:postcode":"R3C 1X7",
    "sg:province":"MB",
    "wof:name":"Salon DE Seville",
    "wof:placetype":"venue"
},
  "geometry": {"coordinates":[-97.152863,49.888569],"type":"Point"}
}