{
  "type": "Feature",
  "properties": {
    "addr:full":"6787 Boul Milan Brossard QC J4Z 2B5",
    "addr:housenumber":"6787",
    "addr:postcode":"j4z 2b5",
    "addr:street":"Boul Milan",
    "iso:country":"CA",
    "sg:address":"6787 Boul Milan",
    "sg:city":"Brossard",
    "sg:classifiers":[
        {
            "category":"Personal",
            "subcategory":"Beauty Salon",
            "type":"Services"
        }
    ],
    "sg:phone":"+1 450 656 0925",
    "sg:postcode":"J4Z 2B5",
    "sg:province":"QC",
    "wof:name":"Salon DE Coiffure Elegance",
    "wof:placetype":"venue"
},
  "geometry": {"coordinates":[-73.4535827637,45.4661521912],"type":"Point"}
}