{
  "type": "Feature",
  "properties": {
    "addr:full":"2016 Sherwood Dr # 15 Sherwood Park AB T8A 3X3",
    "addr:housenumber":"2016;15",
    "addr:postcode":"t8a 3x3",
    "addr:street":"Sherwood Dr #;Park",
    "iso:country":"CA",
    "sg:address":"2016 Sherwood Dr # 15",
    "sg:city":"Sherwood Park",
    "sg:classifiers":[
        {
            "category":"Real Estate",
            "subcategory":"Real Estate Agent",
            "type":"Services"
        }
    ],
    "sg:phone":"+1 780 417 7383",
    "sg:postcode":"T8A 3X3",
    "sg:province":"AB",
    "sg:tags":[
        "desk",
        "space"
    ],
    "wof:name":"Sherwood Business Ctr",
    "wof:placetype":"venue"
},
  "geometry": {"coordinates":[-113.295418,53.52747],"type":"Point"}
}