{
  "type": "Feature",
  "properties": {
    "iso:country":"CA",
    "sg:city":"Campbell River",
    "sg:classifiers":[
        {
            "category":"Social Services",
            "type":"Services"
        }
    ],
    "sg:phone":"+1 250 923 1001",
    "sg:postcode":"V9W 6Y4",
    "sg:province":"BC",
    "sg:tags":[
        "youth",
        "organization",
        "center"
    ],
    "wof:name":"Royal Canadian Air Cadets",
    "wof:placetype":"venue"
},
  "geometry": {"coordinates":[-125.26981353799999,49.9539794922],"type":"Point"}
}