{
  "type": "Feature",
  "properties": {
    "addr:full":"7951 128 St Surrey BC V3W 4E7",
    "addr:housenumber":"7951",
    "addr:postcode":"v3w 4e7",
    "addr:street":"128 St",
    "iso:country":"CA",
    "sg:address":"7951 128 St",
    "sg:city":"Surrey",
    "sg:classifiers":[
        {
            "category":"Retail",
            "subcategory":"Auto Repair",
            "type":"Services"
        }
    ],
    "sg:phone":"+1 604 590 2151",
    "sg:postcode":"V3W 4E7",
    "sg:province":"BC",
    "sg:tags":[
        "body",
        "automobile",
        "painting"
    ],
    "wof:name":"Edelweiss Auto Repairs Ltd",
    "wof:placetype":"venue"
},
  "geometry": {"coordinates":[-122.86813354500001,49.1473274231],"type":"Point"}
}