{
  "type": "Feature",
  "properties": {
    "addr:full":"250 Galaxy Blvd Etobicoke ON M9W 5R8",
    "addr:housenumber":"250",
    "addr:postcode":"m9w 5r8",
    "addr:street":"Galaxy Blvd",
    "iso:country":"CA",
    "sg:address":"250 Galaxy Blvd",
    "sg:city":"Etobicoke",
    "sg:classifiers":[
        {
            "category":"Communications",
            "subcategory":"Film & Video Production",
            "type":"Services"
        }
    ],
    "sg:phone":"+1 416 213 0123",
    "sg:postcode":"M9W 5R8",
    "sg:province":"ON",
    "sg:tags":[
        "taping"
    ],
    "wof:name":"Debut Communications Inc",
    "wof:placetype":"venue"
},
  "geometry": {"coordinates":[-79.581039,43.678131],"type":"Point"}
}