{
  "type": "Feature",
  "properties": {
    "addr:full":"90 Farringford Dr Brantford ON N3R 6K9",
    "addr:housenumber":"90",
    "addr:postcode":"n3r 6k9",
    "addr:street":"Farringford Dr",
    "iso:country":"CA",
    "sg:address":"90 Farringford Dr",
    "sg:city":"Brantford",
    "sg:classifiers":[
        {
            "category":"Building & Trades",
            "subcategory":"Plumbing",
            "type":"Services"
        }
    ],
    "sg:phone":"+1 519 756 1476",
    "sg:postcode":"N3R 6K9",
    "sg:province":"ON",
    "sg:tags":[
        "contractor"
    ],
    "wof:name":"Mike Campbell Plumbing",
    "wof:placetype":"venue"
},
  "geometry": {"coordinates":[-80.25556182859999,43.1695137024],"type":"Point"}
}