{
  "type": "Feature",
  "properties": {
    "addr:full":"7042 Brisbin Rd Bewdley ON K0L 1E0",
    "addr:housenumber":"7042",
    "addr:postcode":"k0l 1e0",
    "addr:street":"Brisbin Rd",
    "iso:country":"CA",
    "sg:address":"7042 Brisbin Rd",
    "sg:city":"Bewdley",
    "sg:classifiers":[
        {
            "category":"Wholesale",
            "subcategory":"Construction Materials",
            "type":"Manufacturing & Wholesale Goods"
        }
    ],
    "sg:phone":"+1 905 797 2471",
    "sg:postcode":"K0L 1E0",
    "sg:province":"ON",
    "sg:tags":[
        "sand",
        "gravel"
    ],
    "wof:name":"Brisbin Sand & Gravel Ltd",
    "wof:placetype":"venue"
},
  "geometry": {"coordinates":[-78.32777400000001,44.089573],"type":"Point"}
}