{
  "type": "Feature",
  "properties": {
    "iso:country":"CA",
    "sg:address":"9 Christie Dr",
    "sg:city":"Brampton",
    "sg:classifiers":[
        {
            "category":"Wholesale",
            "subcategory":"Apparel",
            "type":"Manufacturing & Wholesale Goods"
        }
    ],
    "sg:phone":"+1 905 840 5518",
    "sg:postcode":"L6Z 3H6",
    "sg:province":"ON",
    "sg:tags":[
        "fireplace"
    ],
    "wof:name":"Creative Place",
    "wof:placetype":"venue"
},
  "geometry": {"coordinates":[-79.804329,43.738289],"type":"Point"}
}