{
  "type": "Feature",
  "properties": {
    "iso:country":"CA",
    "sg:city":"Richmond",
    "sg:classifiers":[
        {
            "category":"Home & Garden",
            "subcategory":"Garden Supply",
            "type":"Retail Goods"
        }
    ],
    "sg:phone":"+1 604 270 8202",
    "sg:postcode":"V6Y 1Z5",
    "sg:province":"BC",
    "sg:tags":[
        "sprinkler"
    ],
    "wof:name":"Knight Lawn Sprinkler Svc",
    "wof:placetype":"venue"
},
  "geometry": {"coordinates":[-123.140091,49.158005],"type":"Point"}
}