{
  "type": "Feature",
  "properties": {
    "iso:country":"CA",
    "sg:address":"522 King St W",
    "sg:city":"Brockville",
    "sg:classifiers":[
        {
            "category":"Personal",
            "subcategory":"Beauty Salon",
            "type":"Services"
        }
    ],
    "sg:phone":"+1 613 342 0900",
    "sg:postcode":"K6V 3T2",
    "sg:province":"ON",
    "wof:name":"Faces Plus",
    "wof:placetype":"venue"
},
  "geometry": {"coordinates":[-75.699814,44.580341],"type":"Point"}
}