{
  "type": "Feature",
  "properties": {
    "addr:full":"1922 Manawagonish Rd Saint John NB E2M 5H5",
    "addr:housenumber":"1922",
    "addr:postcode":"e2m 5h5",
    "addr:street":"Manawagonish Rd",
    "iso:country":"CA",
    "sg:address":"1922 Manawagonish Rd",
    "sg:city":"Saint John",
    "sg:classifiers":[
        {
            "category":"Retail",
            "subcategory":"Auto Rental",
            "type":"Services"
        }
    ],
    "sg:phone":"+1 506 635 1142",
    "sg:postcode":"E2M 5H5",
    "sg:province":"NB",
    "sg:tags":[
        "renting",
        "truck",
        "leasing"
    ],
    "wof:name":"U-Haul CO Ltd",
    "wof:placetype":"venue"
},
  "geometry": {"coordinates":[-66.13855743409999,45.2349815369],"type":"Point"}
}