{
  "type": "Feature",
  "properties": {
    "addr:full":"48 Argyle St Yorkton SK S3N 0P6",
    "addr:housenumber":"48",
    "addr:postcode":"s3n 0p6",
    "addr:street":"Argyle St",
    "iso:country":"CA",
    "sg:address":"48 Argyle St",
    "sg:city":"Yorkton",
    "sg:classifiers":[
        {
            "category":"Wholesale",
            "subcategory":"Machinery & Supplies",
            "type":"Manufacturing & Wholesale Goods"
        }
    ],
    "sg:phone":"+1 306 782 8888",
    "sg:postcode":"S3N 0P6",
    "sg:province":"SK",
    "sg:tags":[
        "agricultural",
        "implement"
    ],
    "wof:name":"Canadiana Agri-Motive CO Ltd",
    "wof:placetype":"venue"
},
  "geometry": {"coordinates":[-102.456497,51.209106],"type":"Point"}
}