{
  "type": "Feature",
  "properties": {
    "addr:full":"4920 Ch DE LA Cote-Des-Neiges Montreal QC H3V 1H2",
    "addr:postcode":"4920;h3v 1h2",
    "addr:street":"Ch De La Cote-Des-Neiges",
    "iso:country":"CA",
    "sg:address":"4920 Ch DE LA Cote-Des-Neiges",
    "sg:city":"Montreal",
    "sg:classifiers":[
        {
            "category":"Retail",
            "subcategory":"Veterinary Services",
            "type":"Services"
        }
    ],
    "sg:phone":"+1 514 737 6699",
    "sg:postcode":"H3V 1H2",
    "sg:province":"QC",
    "sg:tags":[
        "veterinarian"
    ],
    "wof:name":"Breton, M E DVM",
    "wof:placetype":"venue"
},
  "geometry": {"coordinates":[-73.616241,45.495098],"type":"Point"}
}