{
  "type": "Feature",
  "properties": {
    "addr:full":"216 Main St W Markdale ON N0C 1H0",
    "addr:housenumber":"216",
    "addr:postcode":"n0c 1h0",
    "addr:street":"Main St W",
    "iso:country":"CA",
    "sg:address":"216 Main St W",
    "sg:city":"Markdale",
    "sg:classifiers":[
        {
            "category":"Manufacturing",
            "subcategory":"Textiles",
            "type":"Manufacturing & Wholesale Goods"
        }
    ],
    "sg:phone":"+1 519 986 2072",
    "sg:postcode":"N0C 1H0",
    "sg:province":"ON",
    "sg:tags":[
        "label"
    ],
    "wof:name":"Medike Quality Labels",
    "wof:placetype":"venue"
},
  "geometry": {"coordinates":[-80.653656,44.314117],"type":"Point"}
}