{
  "type": "Feature",
  "properties": {
    "addr:full":"6522 4 St NE Calgary AB T2K 6H2",
    "addr:housenumber":"6522 4",
    "addr:postcode":"t2k 6h2",
    "addr:street":"St Ne",
    "iso:country":"CA",
    "sg:address":"6522 4 St NE",
    "sg:city":"Calgary",
    "sg:classifiers":[
        {
            "category":"Retail",
            "subcategory":"Laundry & Dry Cleaning",
            "type":"Services"
        }
    ],
    "sg:phone":"+1 403 274 6665",
    "sg:postcode":"T2K 6H2",
    "sg:province":"AB",
    "sg:tags":[
        "cleaners"
    ],
    "wof:name":"Care Cleaners",
    "wof:placetype":"venue"
},
  "geometry": {"coordinates":[-114.05652618400001,51.1110496521],"type":"Point"}
}