{
  "type": "Feature",
  "properties": {
    "iso:country":"CA",
    "sg:address":"235 Potterton Rd",
    "sg:city":"Kelowna",
    "sg:classifiers":[
        {
            "category":"Freight",
            "type":"Transportation"
        }
    ],
    "sg:phone":"+1 250 766 0724",
    "sg:postcode":"V4V 2K8",
    "sg:province":"BC",
    "sg:tags":[
        "warehouse",
        "public"
    ],
    "wof:name":"All BC Warehousing",
    "wof:placetype":"venue"
},
  "geometry": {"coordinates":[-119.388969421,50.0150604248],"type":"Point"}
}