{
  "type": "Feature",
  "properties": {
    "iso:country":"CA",
    "sg:address":"100 Golf Club Rd",
    "sg:city":"North Bay",
    "sg:classifiers":[
        {
            "category":"Retail",
            "subcategory":"Auto Repair",
            "type":"Services"
        }
    ],
    "sg:phone":"+1 705 494 7676",
    "sg:postcode":"P1B 9T8",
    "sg:province":"ON",
    "sg:tags":[
        "automobile",
        "lubrication"
    ],
    "wof:name":"Just Lubes",
    "wof:placetype":"venue"
},
  "geometry": {"coordinates":[-79.46318100000001,46.334938],"type":"Point"}
}