{
  "type": "Feature",
  "properties": {
    "addr:full":"25 Ch Du Golf Saint-Charles-Borromee QC J6E 2B5",
    "addr:housenumber":"25",
    "addr:postcode":"j6e 2b5",
    "addr:street":"Ch Du Golf Saint-Charles-Borromee",
    "iso:country":"CA",
    "sg:address":"25 Ch Du Golf",
    "sg:city":"Saint-Charles-Borromee",
    "sg:classifiers":[
        {
            "category":"Restaurant",
            "type":"Food & Drink"
        }
    ],
    "sg:phone":"+1 450 753 4124",
    "sg:postcode":"J6E 2B5",
    "sg:province":"QC",
    "wof:name":"Chaumiere DE Joliette Inc",
    "wof:placetype":"venue"
},
  "geometry": {"coordinates":[-73.4487686157,46.0433654785],"type":"Point"}
}