{
  "type": "Feature",
  "properties": {
    "iso:country":"CA",
    "sg:city":"Racine",
    "sg:classifiers":[
        {
            "category":"Restaurant",
            "type":"Food & Drink"
        }
    ],
    "sg:phone":"+1 450 532 5333",
    "sg:postcode":"J0E 1Y0",
    "sg:province":"QC",
    "wof:name":"Cantine Chez Jeff",
    "wof:placetype":"venue"
},
  "geometry": {"coordinates":[-72.2526550293,45.502494812],"type":"Point"}
}