{
  "type": "Feature",
  "properties": {
    "addr:full":"450 Mississauga Rd Niagara on the Lake ON L0S 1J0",
    "addr:housenumber":"450",
    "addr:postcode":"l0s 1j0",
    "addr:street":"Mississauga Rd;On",
    "iso:country":"CA",
    "sg:address":"450 Mississauga Rd",
    "sg:city":"Niagara on the Lake",
    "sg:classifiers":[
        {
            "category":"Restaurant",
            "type":"Food & Drink"
        }
    ],
    "sg:phone":"+1 905 468 4242",
    "sg:postcode":"L0S 1J0",
    "sg:province":"ON",
    "sg:tags":[
        "out",
        "pizza"
    ],
    "wof:name":"H D Pizza",
    "wof:placetype":"venue"
},
  "geometry": {"coordinates":[-79.0837554932,43.252822876],"type":"Point"}
}