{
  "type": "Feature",
  "properties": {
    "addr:full":"227 Steiger Cres Saskatoon SK S7N 4K1",
    "addr:housenumber":"227",
    "addr:postcode":"s7n 4k1",
    "addr:street":"Steiger Cres",
    "iso:country":"CA",
    "sg:address":"227 Steiger Cres",
    "sg:city":"Saskatoon",
    "sg:classifiers":[
        {
            "category":"Education",
            "subcategory":"Special Training",
            "type":"Public Place"
        }
    ],
    "sg:phone":"+1 306 955 8980",
    "sg:postcode":"S7N 4K1",
    "sg:province":"SK",
    "sg:tags":[
        "instruction",
        "speaking"
    ],
    "wof:name":"Christopher Leadership Courses",
    "wof:placetype":"venue"
},
  "geometry": {"coordinates":[-106.56407928500001,52.1421012878],"type":"Point"}
}