{
  "type": "Feature",
  "properties": {
    "addr:full":"3547 Av Swail Montreal QC H3T 1P5",
    "addr:housenumber":"3547",
    "addr:postcode":"h3t 1p5",
    "addr:street":"Av Swail",
    "iso:country":"CA",
    "sg:address":"3547 Av Swail",
    "sg:city":"Montreal",
    "sg:classifiers":[
        {
            "category":"Shopping",
            "subcategory":"Books",
            "type":"Retail Goods"
        }
    ],
    "sg:phone":"+1 514 736 0999",
    "sg:postcode":"H3T 1P5",
    "sg:province":"QC",
    "sg:tags":[
        "dealer"
    ],
    "wof:name":"Librairie Le Livre Voyageur",
    "wof:placetype":"venue"
},
  "geometry": {"coordinates":[-73.6199417114,45.49584198],"type":"Point"}
}