{
  "type": "Feature",
  "properties": {
    "addr:full":"7 Boul Des Iles Port-Cartier QC G5B 1V5",
    "addr:housenumber":"7",
    "addr:postcode":"g5b 1v5",
    "addr:street":"Boul Des Iles",
    "iso:country":"CA",
    "sg:address":"7 Boul Des Iles",
    "sg:city":"Port-Cartier",
    "sg:classifiers":[
        {
            "category":"Organizations",
            "subcategory":"Professional Association",
            "type":"Services"
        }
    ],
    "sg:phone":"+1 418 766 4355",
    "sg:postcode":"G5B 1V5",
    "sg:province":"QC",
    "wof:name":"Chevaliers DE Colomb",
    "wof:placetype":"venue"
},
  "geometry": {"coordinates":[-66.876572,50.021393],"type":"Point"}
}