{
  "type": "Feature",
  "properties": {
    "addr:full":"1 Main St Rabbit Lake SK S0M 2L0",
    "addr:housenumber":"1",
    "addr:postcode":"s0m 2l0",
    "addr:street":"Main St",
    "iso:country":"CA",
    "sg:address":"1 Main St",
    "sg:city":"Rabbit Lake",
    "sg:classifiers":[
        {
            "category":"Restaurant",
            "type":"Food & Drink"
        }
    ],
    "sg:phone":"+1 306 824 2142",
    "sg:postcode":"S0M 2L0",
    "sg:province":"SK",
    "sg:tags":[
        "tea",
        "rooms"
    ],
    "wof:name":"Rabbit Lake Store & Tea Room",
    "wof:placetype":"venue"
},
  "geometry": {"coordinates":[-107.77014200000001,53.142231],"type":"Point"}
}