{
  "type": "Feature",
  "properties": {
    "addr:full":"Burlington ON L7R 4B7",
    "addr:postcode":"l7r 4b7",
    "iso:country":"CA",
    "sg:city":"Burlington",
    "sg:classifiers":[
        {
            "category":"Local Transit",
            "type":"Transportation"
        }
    ],
    "sg:phone":"+1 905 637 2858",
    "sg:postcode":"L7R 4B7",
    "sg:province":"ON",
    "sg:tags":[
        "limousine"
    ],
    "wof:name":"Corporate Transportation Svc",
    "wof:placetype":"venue"
},
  "geometry": {"coordinates":[-79.8086242676,43.3329086304],"type":"Point"}
}