{
  "type": "Feature",
  "properties": {
    "iso:country":"CA",
    "sg:address":"2910 Carling Ave",
    "sg:city":"Ottawa",
    "sg:classifiers":[
        {
            "category":"Food & Beverages",
            "subcategory":"Groceries & Convenience Stores",
            "type":"Retail Goods"
        }
    ],
    "sg:phone":"+1 613 820 0266",
    "sg:postcode":"K2B 7J7",
    "sg:province":"ON",
    "wof:name":"Food Frenz",
    "wof:placetype":"venue"
},
  "geometry": {"coordinates":[-75.80098724370001,45.3566627502],"type":"Point"}
}