{
  "type": "Feature",
  "properties": {
    "iso:country":"CA",
    "sg:address":"1025 Marine Dr",
    "sg:city":"North Vancouver",
    "sg:classifiers":[
        {
            "category":"Shopping",
            "subcategory":"Books",
            "type":"Retail Goods"
        }
    ],
    "sg:phone":"+1 604 988 6681",
    "sg:postcode":"V7P 1S6",
    "sg:province":"BC",
    "sg:tags":[
        "dealer"
    ],
    "wof:name":"Indigo Books Music & More",
    "wof:placetype":"venue"
},
  "geometry": {"coordinates":[-123.102088928,49.3237495422],"type":"Point"}
}