{
  "type": "Feature",
  "properties": {
    "addr:full":"11 5th Ave SE High River AB T1V 1G2",
    "addr:housenumber":"11",
    "addr:postcode":"t1v 1g2",
    "addr:street":"5Th Ave Se",
    "iso:country":"CA",
    "sg:address":"11 5th Ave SE",
    "sg:city":"High River",
    "sg:classifiers":[
        {
            "category":"Communications",
            "subcategory":"Radio Station",
            "type":"Services"
        }
    ],
    "sg:phone":"+1 403 652 2472",
    "sg:postcode":"T1V 1G2",
    "sg:province":"AB",
    "sg:tags":[
        "company",
        "broadcasting"
    ],
    "wof:name":"am 1140 Radio Station",
    "wof:placetype":"venue"
},
  "geometry": {"coordinates":[-113.87045288100001,50.5783081055],"type":"Point"}
}