{
  "type": "Feature",
  "properties": {
    "iso:country":"CA",
    "sg:address":"235 Bayly St W",
    "sg:city":"Ajax",
    "sg:classifiers":[
        {
            "category":"Restaurant",
            "type":"Food & Drink"
        }
    ],
    "sg:phone":"+1 905 426 9535",
    "sg:postcode":"L1S 3K3",
    "sg:province":"ON",
    "wof:name":"Portly Piper",
    "wof:placetype":"venue"
},
  "geometry": {"coordinates":[-79.0261688232,43.8421287537],"type":"Point"}
}