{
  "type": "Feature",
  "properties": {
    "iso:country":"CA",
    "sg:address":"184 Rue Saint-Vallier O",
    "sg:city":"Quebec",
    "sg:classifiers":[
        {
            "category":"Restaurant",
            "type":"Food & Drink"
        }
    ],
    "sg:phone":"+1 418 649 9333",
    "sg:postcode":"G1K 1K1",
    "sg:province":"QC",
    "wof:name":"Restaurant Sol Latino",
    "wof:placetype":"venue"
},
  "geometry": {"coordinates":[-71.227745,46.811497],"type":"Point"}
}