{
  "type": "Feature",
  "properties": {
    "iso:country":"CA",
    "sg:address":"5029 Av Du Parc",
    "sg:city":"Montreal",
    "sg:classifiers":[
        {
            "category":"Food & Beverages",
            "subcategory":"Groceries & Convenience Stores",
            "type":"Retail Goods"
        }
    ],
    "sg:phone":"+1 514 273 8782",
    "sg:postcode":"H2V 4E9",
    "sg:province":"QC",
    "sg:tags":[
        "grocer"
    ],
    "wof:name":"P A Super Market Ltd",
    "wof:placetype":"venue"
},
  "geometry": {"coordinates":[-73.5948181152,45.5193328857],"type":"Point"}
}