{
  "type": "Feature",
  "properties": {
    "iso:country":"CA",
    "sg:address":"206 Rue DE L'Eglise",
    "sg:city":"Saint-Severin-DE-Beauce",
    "sg:classifiers":[
        {
            "category":"Food & Beverages",
            "subcategory":"Groceries & Convenience Stores",
            "type":"Retail Goods"
        }
    ],
    "sg:phone":"+1 418 426 5472",
    "sg:postcode":"G0N 1V0",
    "sg:province":"QC",
    "wof:name":"Nadeau, Jean-Guy",
    "wof:placetype":"venue"
},
  "geometry": {"coordinates":[-72.6519165039,45.3052368164],"type":"Point"}
}