{
  "type": "Feature",
  "properties": {
    "addr:full":"99 Glen Miller Rd Trenton ON K8V 5P8",
    "addr:housenumber":"99",
    "addr:postcode":"k8v 5p8",
    "addr:street":"Glen Miller Rd",
    "iso:country":"CA",
    "sg:address":"99 Glen Miller Rd",
    "sg:city":"Trenton",
    "sg:classifiers":[
        {
            "category":"Restaurant",
            "type":"Food & Drink"
        }
    ],
    "sg:phone":"+1 613 394 4855",
    "sg:postcode":"K8V 5P8",
    "sg:province":"ON",
    "wof:name":"Oscar's Seafood & Pasta House",
    "wof:placetype":"venue"
},
  "geometry": {"coordinates":[-77.58229799999999,44.131023],"type":"Point"}
}