{
  "type": "Feature",
  "properties": {
    "addr:full":"351 Place Des Jonquilles Sherbrooke QC J1E 3B3",
    "addr:housenumber":"351",
    "addr:postcode":"j1e 3b3",
    "addr:street":"Place Des Jonquilles",
    "iso:country":"CA",
    "sg:address":"351 Place Des Jonquilles",
    "sg:city":"Sherbrooke",
    "sg:classifiers":[
        {
            "category":"Real Estate",
            "subcategory":"Real Estate Agent",
            "type":"Services"
        }
    ],
    "sg:phone":"+1 819 346 7235",
    "sg:postcode":"J1E 3B3",
    "sg:province":"QC",
    "sg:tags":[
        "cooperative"
    ],
    "wof:name":"Cooperative D'Habitation",
    "wof:placetype":"venue"
},
  "geometry": {"coordinates":[-71.86650848390001,45.4143066406],"type":"Point"}
}