{
  "type": "Feature",
  "properties": {
    "addr:full":"715 Rue Meikle Lachute QC J8H 1V4",
    "addr:housenumber":"715",
    "addr:postcode":"j8h 1v4",
    "addr:street":"Rue Meikle",
    "iso:country":"CA",
    "sg:address":"715 Rue Meikle",
    "sg:city":"Lachute",
    "sg:classifiers":[
        {
            "category":"Organizations",
            "subcategory":"Religious Organization",
            "type":"Services"
        }
    ],
    "sg:phone":"+1 514 562 2917",
    "sg:postcode":"J8H 1V4",
    "sg:province":"QC",
    "sg:tags":[
        "church"
    ],
    "wof:name":"St Simon Anglican Church",
    "wof:placetype":"venue"
},
  "geometry": {"coordinates":[-74.3260192871,45.6593856812],"type":"Point"}
}