{
  "type": "Feature",
  "properties": {
    "addr:full":"3097 Boul Industriel Laval QC H7L 4P8",
    "addr:housenumber":"3097",
    "addr:postcode":"h7l 4p8",
    "addr:street":"Boul Industriel",
    "iso:country":"CA",
    "sg:address":"3097 Boul Industriel",
    "sg:city":"Laval",
    "sg:classifiers":[
        {
            "category":"Manufacturing",
            "subcategory":"Metals",
            "type":"Manufacturing & Wholesale Goods"
        }
    ],
    "sg:phone":"+1 450 629 8591",
    "sg:postcode":"H7L 4P8",
    "sg:province":"QC",
    "sg:tags":[
        "polishing",
        "buffing"
    ],
    "wof:name":"Polissage Cb",
    "wof:placetype":"venue"
},
  "geometry": {"coordinates":[-73.7422180176,45.5906143188],"type":"Point"}
}