{
  "type": "Feature",
  "properties": {
    "addr:full":"475 Provencher Winnipeg MB R2J 4A7",
    "addr:housenumber":"475",
    "addr:postcode":"r2j 4a7",
    "addr:street":"Provencher",
    "iso:country":"CA",
    "sg:address":"475 Provencher",
    "sg:city":"Winnipeg",
    "sg:classifiers":[
        {
            "category":"Health Services",
            "subcategory":"Medical Lab",
            "type":"Services"
        }
    ],
    "sg:phone":"+1 204 772 9144",
    "sg:postcode":"R2J 4A7",
    "sg:province":"MB",
    "sg:tags":[
        "laboratory"
    ],
    "wof:name":"Unicity Lab Svc",
    "wof:placetype":"venue"
},
  "geometry": {"coordinates":[-97.10763549799999,49.896030426],"type":"Point"}
}