{
  "type": "Feature",
  "properties": {
    "addr:full":"Sherwood Park AB T8H 1B5",
    "addr:postcode":"t8h 1b5",
    "iso:country":"CA",
    "sg:city":"Sherwood Park",
    "sg:classifiers":[
        {
            "category":"Building & Trades",
            "subcategory":"Equipment Rental",
            "type":"Services"
        }
    ],
    "sg:phone":"+1 780 467 7600",
    "sg:postcode":"T8H 1B5",
    "sg:province":"AB",
    "sg:tags":[
        "financing",
        "leasing"
    ],
    "wof:name":"Weststar Financial Inc",
    "wof:placetype":"venue"
},
  "geometry": {"coordinates":[-113.319641,53.565414],"type":"Point"}
}