{
  "type": "Feature",
  "properties": {
    "iso:country":"CA",
    "sg:city":"Kitchener",
    "sg:classifiers":[
        {
            "category":"Retail",
            "subcategory":"Veterinary Services",
            "type":"Services"
        }
    ],
    "sg:phone":"+1 519 748 6638",
    "sg:postcode":"N2A 3Y4",
    "sg:province":"ON",
    "sg:tags":[
        "veterinarian"
    ],
    "wof:name":"Cowper, Ellie DVM",
    "wof:placetype":"venue"
},
  "geometry": {"coordinates":[-80.420685,43.428493],"type":"Point"}
}