{
  "type": "Feature",
  "properties": {
    "addr:full":"Saint-Ferdinand QC G0N 1N0",
    "addr:postcode":"g0n 1n0",
    "iso:country":"CA",
    "sg:city":"Saint-Ferdinand",
    "sg:classifiers":[
        {
            "category":"Banks & Credit Unions",
            "subcategory":"Bank",
            "type":"Services"
        }
    ],
    "sg:phone":"+1 418 423 7501",
    "sg:postcode":"G0N 1N0",
    "sg:province":"QC",
    "wof:name":"Caisses Desjardins",
    "wof:placetype":"venue"
},
  "geometry": {"coordinates":[-71.573311,46.111706],"type":"Point"}
}