{
  "type": "Feature",
  "properties": {
    "addr:full":"22 Conception Bay Hwy Conception Bay South NL A1W 3A1",
    "addr:housenumber":"22",
    "addr:postcode":"a1w 3a1",
    "addr:street":"Conception Bay Hwy",
    "iso:country":"CA",
    "sg:address":"22 Conception Bay Hwy",
    "sg:city":"Conception Bay South",
    "sg:classifiers":[
        {
            "category":"Autos & Motor Vehicles",
            "subcategory":"Fuel & Gas Station",
            "type":"Retail Goods"
        }
    ],
    "sg:phone":"+1 709 834 9618",
    "sg:postcode":"A1W 3A1",
    "sg:province":"NL",
    "sg:tags":[
        "oil"
    ],
    "wof:name":"Manuels Irving Mainway",
    "wof:placetype":"venue"
},
  "geometry": {"coordinates":[-52.946712,47.520718],"type":"Point"}
}