{
  "type": "Feature",
  "properties": {
    "iso:country":"CA",
    "sg:city":"Lower Woods Harbour",
    "sg:classifiers":[
        {
            "category":"Restaurant",
            "type":"Food & Drink"
        }
    ],
    "sg:phone":"+1 902 723 0223",
    "sg:postcode":"B0W 2E0",
    "sg:province":"NS",
    "wof:name":"Captain Wayne's Cafe",
    "wof:placetype":"venue"
},
  "geometry": {"coordinates":[-65.7338256836,43.5277328491],"type":"Point"}
}