{
  "type": "Feature",
  "properties": {
    "addr:full":"Hwy 30 E Altona MB R0G 0B0",
    "addr:postcode":"r0g 0b0",
    "addr:street":"Hwy 30 E",
    "iso:country":"CA",
    "sg:address":"Hwy 30 E",
    "sg:city":"Altona",
    "sg:classifiers":[
        {
            "category":"Freight",
            "type":"Transportation"
        }
    ],
    "sg:phone":"+1 204 324 6778",
    "sg:postcode":"R0G 0B0",
    "sg:province":"MB",
    "sg:tags":[
        "trucking"
    ],
    "wof:name":"Renold's Transport",
    "wof:placetype":"venue"
},
  "geometry": {"coordinates":[-97.549621582,49.1226463318],"type":"Point"}
}