{
  "type": "Feature",
  "properties": {
    "iso:country":"CA",
    "sg:city":"Calgary",
    "sg:classifiers":[
        {
            "category":"Building & Trades",
            "subcategory":"Electrical",
            "type":"Services"
        }
    ],
    "sg:phone":"+1 403 243 0252",
    "sg:postcode":"T2G 3E5",
    "sg:province":"AB",
    "sg:tags":[
        "electric",
        "contractor"
    ],
    "wof:name":"Terakita Electric Ltd",
    "wof:placetype":"venue"
},
  "geometry": {"coordinates":[-114.03821563699999,51.0239334106],"type":"Point"}
}