{
  "type": "Feature",
  "properties": {
    "addr:full":"571 Sargent Ave Winnipeg MB R3B 1W6",
    "addr:housenumber":"571",
    "addr:postcode":"r3b 1w6",
    "addr:street":"Sargent Ave",
    "iso:country":"CA",
    "sg:address":"571 Sargent Ave",
    "sg:city":"Winnipeg",
    "sg:classifiers":[
        {
            "category":"Retail",
            "subcategory":"Auto Repair",
            "type":"Services"
        }
    ],
    "sg:phone":"+1 204 775 3961",
    "sg:postcode":"R3B 1W6",
    "sg:province":"MB",
    "sg:tags":[
        "repairing",
        "automobile"
    ],
    "wof:name":"Sargent Service",
    "wof:placetype":"venue"
},
  "geometry": {"coordinates":[-97.157471,49.89666],"type":"Point"}
}