{
  "type": "Feature",
  "properties": {
    "addr:full":"Concord ON L4K 4K9",
    "addr:postcode":"l4k 4k9",
    "iso:country":"CA",
    "sg:city":"Concord",
    "sg:classifiers":[
        {
            "category":"Professional",
            "subcategory":"Accounting & Tax Preparation",
            "type":"Services"
        }
    ],
    "sg:phone":"+1 905 760 9663",
    "sg:postcode":"L4K 4K9",
    "sg:province":"ON",
    "sg:tags":[
        "accountant"
    ],
    "wof:name":"Santangelo, Nino G CA",
    "wof:placetype":"venue"
},
  "geometry": {"coordinates":[-79.528137207,43.8004379272],"type":"Point"}
}