{
  "type": "Feature",
  "properties": {
    "addr:full":"401 Rue Germain Saint-Leonard-D'Aston QC J0C 1M0",
    "addr:housenumber":"401",
    "addr:postcode":"j0c 1m0",
    "addr:street":"Rue Germain Saint-Leonard-D'Aston",
    "iso:country":"CA",
    "sg:address":"401 Rue Germain",
    "sg:city":"Saint-Leonard-D'Aston",
    "sg:classifiers":[
        {
            "category":"Education",
            "subcategory":"School",
            "type":"Public Place"
        }
    ],
    "sg:phone":"+1 819 399 2122",
    "sg:postcode":"J0C 1M0",
    "sg:province":"QC",
    "wof:name":"Ecole Secondaire Decouverte",
    "wof:placetype":"venue"
},
  "geometry": {"coordinates":[-71.87023162840001,46.8514175415],"type":"Point"}
}