{
  "type": "Feature",
  "properties": {
    "addr:full":"212 Hendon Ave North York ON M2M 1B1",
    "addr:housenumber":"212",
    "addr:postcode":"m2m 1b1",
    "addr:street":"Hendon Ave",
    "iso:country":"CA",
    "sg:address":"212 Hendon Ave",
    "sg:city":"North York",
    "sg:classifiers":[
        {
            "category":"Building & Trades",
            "subcategory":"Plumbing",
            "type":"Services"
        }
    ],
    "sg:phone":"+1 416 651 0109",
    "sg:postcode":"M2M 1B1",
    "sg:province":"ON",
    "sg:tags":[
        "contractor",
        "drainage"
    ],
    "wof:name":"Acme Drain & Construction CO",
    "wof:placetype":"venue"
},
  "geometry": {"coordinates":[-79.42701,43.779305],"type":"Point"}
}