{
  "type": "Feature",
  "properties": {
    "addr:full":"6159 Curtis St Burnaby BC V5B 4X7",
    "addr:housenumber":"6159",
    "addr:postcode":"bc v5b 4x7",
    "addr:street":"Curtis St",
    "iso:country":"CA",
    "sg:address":"6159 Curtis St",
    "sg:city":"Burnaby",
    "sg:classifiers":[
        {
            "category":"Arena",
            "subcategory":"Sports Club",
            "type":"Entertainment"
        }
    ],
    "sg:phone":"+1 604 299 8354",
    "sg:postcode":"V5B 4X7",
    "sg:province":"BC",
    "sg:tags":[
        "skating",
        "athletic",
        "stadium",
        "rink",
        "fields"
    ],
    "wof:name":"Kensington Complex",
    "wof:placetype":"venue"
},
  "geometry": {"coordinates":[-122.974281311,49.27526474],"type":"Point"}
}