{
  "type": "Feature",
  "properties": {
    "addr:full":"22886 Hagerty Newbury ON N0L 1Z0",
    "addr:housenumber":"22886",
    "addr:postcode":"n0l 1z0",
    "addr:street":"Hagerty",
    "iso:country":"CA",
    "sg:address":"22886 Hagerty",
    "sg:city":"Newbury",
    "sg:classifiers":[
        {
            "category":"Banks & Credit Unions",
            "subcategory":"Bank",
            "type":"Services"
        }
    ],
    "sg:phone":"+1 519 693 4371",
    "sg:postcode":"N0L 1Z0",
    "sg:province":"ON",
    "wof:name":"Royal Bank Financial Group",
    "wof:placetype":"venue"
},
  "geometry": {"coordinates":[-81.79834,42.6842],"type":"Point"}
}