{
  "type": "Feature",
  "properties": {
    "addr:full":"Chilliwack BC V2R 5G1",
    "addr:postcode":"v2r 5g1",
    "iso:country":"CA",
    "sg:city":"Chilliwack",
    "sg:classifiers":[
        {
            "category":"Farming",
            "subcategory":"Dairy Farm",
            "type":"Manufacturing & Wholesale Goods"
        }
    ],
    "sg:phone":"+1 604 823 4201",
    "sg:postcode":"V2R 5G1",
    "sg:province":"BC",
    "wof:name":"Coast Mountain Dairy Ltd",
    "wof:placetype":"venue"
},
  "geometry": {"coordinates":[-122.070297,49.089214],"type":"Point"}
}