{
  "type": "Feature",
  "properties": {
    "iso:country":"CA",
    "sg:address":"3550 Boul DE LA Concorde E",
    "sg:city":"Laval",
    "sg:classifiers":[
        {
            "category":"Health Services",
            "subcategory":"Podiatrist",
            "type":"Services"
        }
    ],
    "sg:phone":"+1 450 664 7433",
    "sg:postcode":"H7E 2C7",
    "sg:province":"QC",
    "wof:name":"Sante Par Vos Pieds",
    "wof:placetype":"venue"
},
  "geometry": {"coordinates":[-73.66087341310001,45.5953025818],"type":"Point"}
}