{
  "type": "Feature",
  "properties": {
    "iso:country":"CA",
    "sg:address":"360 Merritt St",
    "sg:city":"St Catharines",
    "sg:classifiers":[
        {
            "category":"Building & Trades",
            "subcategory":"Construction",
            "type":"Services"
        }
    ],
    "sg:phone":"+1 905 227 5966",
    "sg:postcode":"L2T 1K8",
    "sg:province":"ON",
    "sg:tags":[
        "masonry",
        "contractor"
    ],
    "wof:name":"Creative Masonry Works",
    "wof:placetype":"venue"
},
  "geometry": {"coordinates":[-79.2138519287,43.1408195496],"type":"Point"}
}