{
  "type": "Feature",
  "properties": {
    "addr:full":"32 Av Holton Westmount QC H3Y 2E8",
    "addr:postcode":"h3y 2e8",
    "addr:street":"32 Av Holton",
    "iso:country":"CA",
    "sg:address":"32 Av Holton",
    "sg:city":"Westmount",
    "sg:classifiers":[
        {
            "category":"Wholesale",
            "subcategory":"Stationery",
            "type":"Manufacturing & Wholesale Goods"
        }
    ],
    "sg:phone":"+1 514 846 3445",
    "sg:postcode":"H3Y 2E8",
    "sg:province":"QC",
    "sg:tags":[
        "packaging",
        "material",
        "wrapping",
        "gift"
    ],
    "wof:name":"Zelick, Anne",
    "wof:placetype":"venue"
},
  "geometry": {"coordinates":[-73.592384,45.49036],"type":"Point"}
}