{
  "type": "Feature",
  "properties": {
    "iso:country":"CA",
    "sg:address":"709 Rue Garnier",
    "sg:city":"Marieville",
    "sg:classifiers":[
        {
            "category":"Personal",
            "subcategory":"Beauty Salon",
            "type":"Services"
        }
    ],
    "sg:phone":"+1 450 460 7617",
    "sg:postcode":"J3M 1G8",
    "sg:province":"QC",
    "wof:name":"Salon DE Coiffure Jacqueline",
    "wof:placetype":"venue"
},
  "geometry": {"coordinates":[-73.165397644,45.4305877686],"type":"Point"}
}