{
  "type": "Feature",
  "properties": {
    "addr:full":"6 Edgewood Pl W Lethbridge AB T1K 5Z7",
    "addr:housenumber":"6",
    "addr:postcode":"t1k 5z7",
    "addr:street":"Edgewood Pl W",
    "iso:country":"CA",
    "sg:address":"6 Edgewood Pl W",
    "sg:city":"Lethbridge",
    "sg:classifiers":[
        {
            "category":"Building & Trades",
            "subcategory":"Plumbing",
            "type":"Services"
        }
    ],
    "sg:phone":"+1 403 381 8077",
    "sg:postcode":"T1K 5Z7",
    "sg:province":"AB",
    "sg:tags":[
        "contractor"
    ],
    "wof:name":"Mike's Plumbing & Heating Ltd",
    "wof:placetype":"venue"
},
  "geometry": {"coordinates":[-112.88200378400001,49.6898345947],"type":"Point"}
}