{
  "type": "Feature",
  "properties": {
    "addr:full":"Vancouver BC V5L 1V8",
    "addr:postcode":"v5l 1v8",
    "iso:country":"CA",
    "sg:city":"Vancouver",
    "sg:classifiers":[
        {
            "category":"Retail",
            "subcategory":"Auto Repair",
            "type":"Services"
        }
    ],
    "sg:phone":"+1 604 255 4592",
    "sg:postcode":"V5L 1V8",
    "sg:province":"BC",
    "sg:tags":[
        "repairing",
        "automobile"
    ],
    "wof:name":"Zetta Automotive Svc",
    "wof:placetype":"venue"
},
  "geometry": {"coordinates":[-123.076599121,49.2801742554],"type":"Point"}
}