{
  "type": "Feature",
  "properties": {
    "addr:full":"1187 Rue Principale E Sainte-Agathe-Des-Monts QC J8C 1L7",
    "addr:housenumber":"1187",
    "addr:postcode":"j8c 1l7",
    "addr:street":"Rue Principale E Sainte-Agathe-Des-Monts",
    "iso:country":"CA",
    "sg:address":"1187 Rue Principale E",
    "sg:city":"Sainte-Agathe-Des-Monts",
    "sg:classifiers":[
        {
            "category":"Manufacturing",
            "subcategory":"Food",
            "type":"Manufacturing & Wholesale Goods"
        }
    ],
    "sg:phone":"+1 819 321 2225",
    "sg:postcode":"J8C 1L7",
    "sg:province":"QC",
    "sg:tags":[
        "grocer",
        "product",
        "manufacturer"
    ],
    "wof:name":"Nord Sud Produits Alimentaires",
    "wof:placetype":"venue"
},
  "geometry": {"coordinates":[-74.262062,46.04261],"type":"Point"}
}