{
  "type": "Feature",
  "properties": {
    "addr:full":"189 E Columbia Vanderhoof BC V0J 3A0",
    "addr:housenumber":"189",
    "addr:postcode":"v0j 3a0",
    "addr:street":"E Columbia",
    "iso:country":"CA",
    "sg:address":"189 E Columbia",
    "sg:city":"Vanderhoof",
    "sg:classifiers":[
        {
            "category":"Sports & Exercise",
            "subcategory":"Bowling",
            "type":"Entertainment"
        }
    ],
    "sg:phone":"+1 250 567 9333",
    "sg:postcode":"V0J 3A0",
    "sg:province":"BC",
    "sg:tags":[
        "center"
    ],
    "wof:name":"Vanderhoof Recreations",
    "wof:placetype":"venue"
},
  "geometry": {"coordinates":[-124.007729,54.016846],"type":"Point"}
}