{
  "type": "Feature",
  "properties": {
    "addr:full":"1104 Main St Saskatoon SK S7H 0K9",
    "addr:housenumber":"1104",
    "addr:postcode":"s7h 0k9",
    "addr:street":"Main St",
    "iso:country":"CA",
    "sg:address":"1104 Main St",
    "sg:city":"Saskatoon",
    "sg:classifiers":[
        {
            "category":"Social Services",
            "type":"Services"
        }
    ],
    "sg:phone":"+1 306 244 7950",
    "sg:postcode":"S7H 0K9",
    "sg:province":"SK",
    "sg:tags":[
        "counseling"
    ],
    "wof:name":"Changing Men Consulting",
    "wof:placetype":"venue"
},
  "geometry": {"coordinates":[-106.643630981,52.1165657043],"type":"Point"}
}