{
  "type": "Feature",
  "properties": {
    "addr:full":"11 Orkney Pl East St Paul MB R2E 0G9",
    "addr:housenumber":"11",
    "addr:postcode":"r2e 0g9",
    "addr:street":"Orkney Pl",
    "iso:country":"CA",
    "sg:address":"11 Orkney Pl",
    "sg:city":"East St Paul",
    "sg:classifiers":[
        {
            "category":"Travel",
            "subcategory":"Travel Agent",
            "type":"Entertainment"
        }
    ],
    "sg:phone":"+1 204 257 0574",
    "sg:postcode":"R2E 0G9",
    "sg:province":"MB",
    "sg:tags":[
        "agency",
        "bureau"
    ],
    "wof:name":"Interline Discount Travel",
    "wof:placetype":"venue"
},
  "geometry": {"coordinates":[-97.017815,49.97522],"type":"Point"}
}