{
  "type": "Feature",
  "properties": {
    "iso:country":"CA",
    "sg:city":"Bracebridge",
    "sg:classifiers":[
        {
            "category":"Professional",
            "subcategory":"Business Services",
            "type":"Services"
        }
    ],
    "sg:phone":"+1 705 645 4662",
    "sg:postcode":"P1L 1T8",
    "sg:province":"ON",
    "sg:tags":[
        "paralegal",
        "bailiff"
    ],
    "wof:name":"Commission Service Inc",
    "wof:placetype":"venue"
},
  "geometry": {"coordinates":[-79.309387207,45.0401306152],"type":"Point"}
}