{
  "type": "Feature",
  "properties": {
    "addr:full":"London ON N5X 3W1",
    "addr:postcode":"n5x 3w1",
    "iso:country":"CA",
    "sg:city":"London",
    "sg:classifiers":[
        {
            "category":"Personal",
            "subcategory":"Tanning Parlor",
            "type":"Services"
        }
    ],
    "sg:phone":"+1 519 850 7312",
    "sg:postcode":"N5X 3W1",
    "sg:province":"ON",
    "sg:tags":[
        "salon"
    ],
    "wof:name":"Euro Sun Tanning Salon Inc",
    "wof:placetype":"venue"
},
  "geometry": {"coordinates":[-81.27593231199999,43.0271377563],"type":"Point"}
}