{
  "type": "Feature",
  "properties": {
    "addr:full":"3410 Rue Griffith Saint-Laurent QC H4T 1A7",
    "addr:housenumber":"3410",
    "addr:postcode":"h4t 1a7",
    "addr:street":"Rue Griffith",
    "iso:country":"CA",
    "sg:address":"3410 Rue Griffith",
    "sg:city":"Saint-Laurent",
    "sg:classifiers":[
        {
            "category":"Wholesale",
            "subcategory":"Durable Goods & Equipment",
            "type":"Manufacturing & Wholesale Goods"
        }
    ],
    "sg:phone":"+1 514 342 5390",
    "sg:postcode":"H4T 1A7",
    "sg:province":"QC",
    "sg:tags":[
        "laboratory",
        "instrument",
        "scientific",
        "apparatus",
        "supply"
    ],
    "wof:name":"Fisher Scientifique Ltee",
    "wof:placetype":"venue"
},
  "geometry": {"coordinates":[-73.693321,45.488899],"type":"Point"}
}