{
  "type": "Feature",
  "properties": {
    "addr:full":"186 8th Ave W Vancouver BC V5Y 1N2",
    "addr:housenumber":"186",
    "addr:postcode":"v5y 1n2",
    "addr:street":"8Th Ave W",
    "iso:country":"CA",
    "sg:address":"186 8th Ave W",
    "sg:city":"Vancouver",
    "sg:classifiers":[
        {
            "category":"Manufacturing",
            "subcategory":"Metals",
            "type":"Manufacturing & Wholesale Goods"
        }
    ],
    "sg:phone":"+1 604 879 2974",
    "sg:postcode":"V5Y 1N2",
    "sg:province":"BC",
    "sg:tags":[
        "fitting",
        "hose",
        "coupling"
    ],
    "wof:name":"Lo-Rez Vibration Control Ltd",
    "wof:placetype":"venue"
},
  "geometry": {"coordinates":[-123.10891700000001,49.263699],"type":"Point"}
}