{
  "type": "Feature",
  "properties": {
    "addr:full":"8985 Fraserwood Crt Burnaby BC V5J 5E8",
    "addr:housenumber":"8985",
    "addr:postcode":"v5j 5e8",
    "addr:street":"Fraserwood Crt",
    "iso:country":"CA",
    "sg:address":"8985 Fraserwood Crt",
    "sg:city":"Burnaby",
    "sg:classifiers":[
        {
            "category":"Wholesale",
            "subcategory":"Machinery & Supplies",
            "type":"Manufacturing & Wholesale Goods"
        }
    ],
    "sg:phone":"+1 604 433 6711",
    "sg:postcode":"V5J 5E8",
    "sg:province":"BC",
    "sg:tags":[
        "bearing"
    ],
    "wof:name":"B C Bearing Engineers Ltd",
    "wof:placetype":"venue"
},
  "geometry": {"coordinates":[-123.018333,49.200539],"type":"Point"}
}