{
  "type": "Feature",
  "properties": {
    "addr:full":"3200 Rue King O Sherbrooke QC J1L 1C9",
    "addr:housenumber":"3200",
    "addr:postcode":"j1l 1c9",
    "addr:street":"Rue King O",
    "iso:country":"CA",
    "sg:address":"3200 Rue King O",
    "sg:city":"Sherbrooke",
    "sg:classifiers":[
        {
            "category":"Personal",
            "subcategory":"Beauty Salon",
            "type":"Services"
        }
    ],
    "sg:phone":"+1 819 562 7555",
    "sg:postcode":"J1L 1C9",
    "sg:province":"QC",
    "wof:name":"Beaute Coiffure Monalysa",
    "wof:placetype":"venue"
},
  "geometry": {"coordinates":[-71.94738769529999,45.3954391479],"type":"Point"}
}