{
  "type": "Feature",
  "properties": {
    "addr:full":"6251 Sooke Rd Sooke BC V0S 1N0",
    "addr:housenumber":"6251",
    "addr:postcode":"v0s 1n0",
    "addr:street":"Sooke Rd",
    "iso:country":"CA",
    "sg:address":"6251 Sooke Rd",
    "sg:city":"Sooke",
    "sg:classifiers":[
        {
            "category":"Organizations",
            "subcategory":"Religious Organization",
            "type":"Services"
        }
    ],
    "sg:phone":"+1 250 642 6661",
    "sg:postcode":"V0S 1N0",
    "sg:province":"BC",
    "sg:tags":[
        "church"
    ],
    "wof:name":"Juan DE Fuca Seventh Day Advnt",
    "wof:placetype":"venue"
},
  "geometry": {"coordinates":[-123.700974,48.387218],"type":"Point"}
}