{
  "type": "Feature",
  "properties": {
    "addr:full":"343 Ch Du Vallon Thetford Mines QC G6G 5R5",
    "addr:housenumber":"343",
    "addr:postcode":"g6g 5r5",
    "addr:street":"Ch Du Vallon",
    "iso:country":"CA",
    "sg:address":"343 Ch Du Vallon",
    "sg:city":"Thetford Mines",
    "sg:classifiers":[
        {
            "category":"Real Estate",
            "subcategory":"Real Estate Agent",
            "type":"Services"
        }
    ],
    "sg:phone":"+1 418 338 4220",
    "sg:postcode":"G6G 5R5",
    "sg:province":"QC",
    "wof:name":"Sutton-Pro",
    "wof:placetype":"venue"
},
  "geometry": {"coordinates":[-71.3039932251,46.1196365356],"type":"Point"}
}