{
  "type": "Feature",
  "properties": {
    "addr:full":"23 Rue Principale Saint-Camille-DE-Bellechasse QC G0R 2S0",
    "addr:housenumber":"23",
    "addr:postcode":"g0r 2s0",
    "addr:street":"Rue Principale",
    "iso:country":"CA",
    "sg:address":"23 Rue Principale",
    "sg:city":"Saint-Camille-DE-Bellechasse",
    "sg:classifiers":[
        {
            "category":"Restaurant",
            "type":"Food & Drink"
        }
    ],
    "sg:phone":"+1 418 595 2550",
    "sg:postcode":"G0R 2S0",
    "sg:province":"QC",
    "wof:name":"Casse-Croute Chez Hilda",
    "wof:placetype":"venue"
},
  "geometry": {"coordinates":[-70.2256698608,46.4852676392],"type":"Point"}
}