{
  "type": "Feature",
  "properties": {
    "addr:full":"7250 Boul Langelier Saint-Leonard QC H1S 2X6",
    "addr:housenumber":"7250",
    "addr:postcode":"h1s 2x6",
    "addr:street":"Boul Langelier",
    "iso:country":"CA",
    "sg:address":"7250 Boul Langelier",
    "sg:city":"Saint-Leonard",
    "sg:classifiers":[
        {
            "category":"Autos & Motor Vehicles",
            "subcategory":"Automobile Sales",
            "type":"Retail Goods"
        }
    ],
    "sg:phone":"+1 514 256 1010",
    "sg:postcode":"H1S 2X6",
    "sg:province":"QC",
    "sg:tags":[
        "car",
        "dealer"
    ],
    "wof:name":"Kia St-Leonard",
    "wof:placetype":"venue"
},
  "geometry": {"coordinates":[-73.570503,45.590851],"type":"Point"}
}