{
  "type": "Feature",
  "properties": {
    "addr:full":"145 King St W #1000 Toronto ON M5H 1J8",
    "addr:housenumber":"145",
    "addr:postcode":"m5h 1j8",
    "addr:street":"King St W # 1000",
    "iso:country":"CA",
    "sg:address":"145 King St W #1000",
    "sg:city":"Toronto",
    "sg:classifiers":[
        {
            "category":"Professional",
            "subcategory":"Employment Agencies",
            "type":"Services"
        }
    ],
    "sg:phone":"+1 416 863 9978",
    "sg:postcode":"M5H 1J8",
    "sg:province":"ON",
    "sg:tags":[
        "consultant",
        "search",
        "executive"
    ],
    "wof:name":"Schoales & Assoc Inc",
    "wof:placetype":"venue"
},
  "geometry": {"coordinates":[-79.384262085,43.6476211548],"type":"Point"}
}