{
  "type": "Feature",
  "properties": {
    "addr:full":"2174 Departure Bay Rd Nanaimo BC V9S 3V6",
    "addr:housenumber":"2174",
    "addr:postcode":"v9s 3v6",
    "addr:street":"Departure Bay Rd",
    "iso:country":"CA",
    "sg:address":"2174 Departure Bay Rd",
    "sg:city":"Nanaimo",
    "sg:classifiers":[
        {
            "category":"Organizations",
            "subcategory":"Religious Organization",
            "type":"Services"
        }
    ],
    "sg:phone":"+1 250 758 1232",
    "sg:postcode":"V9S 3V6",
    "sg:province":"BC",
    "sg:tags":[
        "church"
    ],
    "wof:name":"Lutheran Church Hope",
    "wof:placetype":"venue"
},
  "geometry": {"coordinates":[-123.967056274,49.1925201416],"type":"Point"}
}