{
  "type": "Feature",
  "properties": {
    "addr:full":"2031 Rue Frontenac Montreal QC H2K 2Z2",
    "addr:housenumber":"2031",
    "addr:postcode":"h2k 2z2",
    "addr:street":"Rue Frontenac",
    "iso:country":"CA",
    "sg:address":"2031 Rue Frontenac",
    "sg:city":"Montreal",
    "sg:classifiers":[
        {
            "category":"Restaurant",
            "type":"Food & Drink"
        }
    ],
    "sg:phone":"+1 514 526 2852",
    "sg:postcode":"H2K 2Z2",
    "sg:province":"QC",
    "wof:name":"Mambo Restaurant",
    "wof:placetype":"venue"
},
  "geometry": {"coordinates":[-73.5533218384,45.5334510803],"type":"Point"}
}