{
  "type": "Feature",
  "properties": {
    "addr:full":"2207 Boul Du Cure-Labelle Saint-Jerome QC J7Y 1T6",
    "addr:housenumber":"2207",
    "addr:postcode":"j7y 1t6",
    "addr:street":"Boul Du Cure-Labelle Saint-Jerome",
    "iso:country":"CA",
    "sg:address":"2207 Boul Du Cure-Labelle",
    "sg:city":"Saint-Jerome",
    "sg:classifiers":[
        {
            "category":"Building & Trades",
            "subcategory":"Plumbing",
            "type":"Services"
        }
    ],
    "sg:phone":"+1 450 436 4666",
    "sg:postcode":"J7Y 1T6",
    "sg:province":"QC",
    "sg:tags":[
        "ventilating",
        "conditioning",
        "contractor",
        "system",
        "air"
    ],
    "wof:name":"Entreprises-Refrig Locas",
    "wof:placetype":"venue"
},
  "geometry": {"coordinates":[-74.012489,45.805885],"type":"Point"}
}