{
  "type": "Feature",
  "properties": {
    "addr:full":"12783 248 St Maple Ridge BC V4R 1K4",
    "addr:housenumber":"12783",
    "addr:postcode":"bc v4r 1k4",
    "addr:street":"248 St",
    "iso:country":"CA",
    "sg:address":"12783 248 St",
    "sg:city":"Maple Ridge",
    "sg:classifiers":[
        {
            "category":"Shopping",
            "type":"Retail Goods"
        }
    ],
    "sg:phone":"+1 604 467 4417",
    "sg:postcode":"V4R 1K4",
    "sg:province":"BC",
    "sg:tags":[
        "awning",
        "canopy"
    ],
    "wof:name":"Primeline Industries",
    "wof:placetype":"venue"
},
  "geometry": {"coordinates":[-122.535362244,49.2343559265],"type":"Point"}
}