{
  "type": "Feature",
  "properties": {
    "addr:full":"1203 Dundas St W Toronto ON M6J 1X3",
    "addr:housenumber":"1203",
    "addr:postcode":"m6j 1x3",
    "addr:street":"Dundas St W",
    "iso:country":"CA",
    "sg:address":"1203 Dundas St W",
    "sg:city":"Toronto",
    "sg:classifiers":[
        {
            "category":"Shopping",
            "subcategory":"Clothing, Apparel, & Fashions",
            "type":"Retail Goods"
        }
    ],
    "sg:phone":"+1 416 533 6258",
    "sg:postcode":"M6J 1X3",
    "sg:province":"ON",
    "sg:tags":[
        "infant"
    ],
    "wof:name":"Jean Darlene Shoppe",
    "wof:placetype":"venue"
},
  "geometry": {"coordinates":[-79.4229812622,43.6492156982],"type":"Point"}
}