{
  "type": "Feature",
  "properties": {
    "iso:country":"CA",
    "sg:address":"86 Norfolk St # 101",
    "sg:city":"Guelph",
    "sg:classifiers":[
        {
            "category":"Health Services",
            "subcategory":"Chiropractor",
            "type":"Services"
        }
    ],
    "sg:phone":"+1 519 827 0040",
    "sg:postcode":"N1H 4J2",
    "sg:province":"ON",
    "wof:name":"Norfolk Chiropractic",
    "wof:placetype":"venue"
},
  "geometry": {"coordinates":[-80.25164794920001,43.5446395874],"type":"Point"}
}