{
  "type": "Feature",
  "properties": {
    "iso:country":"CA",
    "sg:address":"5699 Raleigh St",
    "sg:city":"Mississauga",
    "sg:classifiers":[
        {
            "category":"Professional",
            "subcategory":"Computer Services",
            "type":"Services"
        }
    ],
    "sg:phone":"+1 905 812 0051",
    "sg:postcode":"L5M 7E6",
    "sg:province":"ON",
    "sg:tags":[
        "consultant"
    ],
    "wof:name":"Computer Productivity Resource",
    "wof:placetype":"venue"
},
  "geometry": {"coordinates":[-79.742752,43.55645],"type":"Point"}
}