{
  "type": "Feature",
  "properties": {
    "addr:full":"General Delivery Pikangikum ON P0V 2L0",
    "addr:postcode":"p0v 2l0",
    "iso:country":"CA",
    "sg:address":"General Delivery",
    "sg:city":"Pikangikum",
    "sg:classifiers":[
        {
            "category":"Education",
            "subcategory":"School",
            "type":"Public Place"
        }
    ],
    "sg:phone":"+1 807 773 5561",
    "sg:postcode":"P0V 2L0",
    "sg:province":"ON",
    "wof:name":"Eenchokay Birchstick School",
    "wof:placetype":"venue"
},
  "geometry": {"coordinates":[-93.646683,51.736073],"type":"Point"}
}