{
  "type": "Feature",
  "properties": {
    "iso:country":"CA",
    "sg:address":"5101 Dugald Rd",
    "sg:city":"Winnipeg",
    "sg:classifiers":[
        {
            "category":"Shopping",
            "type":"Retail Goods"
        }
    ],
    "sg:phone":"+1 204 222 2485",
    "sg:postcode":"R2C 5K1",
    "sg:province":"MB",
    "sg:tags":[
        "monument"
    ],
    "wof:name":"Brier Estates Memorials",
    "wof:placetype":"venue"
},
  "geometry": {"coordinates":[-96.96495819090001,49.8861694336],"type":"Point"}
}