{
  "type": "Feature",
  "properties": {
    "addr:full":"Cannington ON L0E 1E0",
    "addr:postcode":"l0e 1e0",
    "iso:country":"CA",
    "sg:city":"Cannington",
    "sg:classifiers":[
        {
            "category":"Food & Beverages",
            "subcategory":"Groceries & Convenience Stores",
            "type":"Retail Goods"
        }
    ],
    "sg:phone":"+1 705 437 1010",
    "sg:postcode":"L0E 1E0",
    "sg:province":"ON",
    "wof:name":"New Port Bolster Convenience",
    "wof:placetype":"venue"
},
  "geometry": {"coordinates":[-79.0378952026,44.3503684998],"type":"Point"}
}