{
  "type": "Feature",
  "properties": {
    "addr:full":"Calgary AB T2E 6Z3",
    "addr:postcode":"t2e 6z3",
    "iso:country":"CA",
    "sg:city":"Calgary",
    "sg:classifiers":[
        {
            "category":"Wholesale",
            "subcategory":"Electrical",
            "type":"Manufacturing & Wholesale Goods"
        }
    ],
    "sg:phone":"+1 403 250 9065",
    "sg:postcode":"T2E 6Z3",
    "sg:province":"AB",
    "sg:tags":[
        "communication",
        "wire",
        "radio",
        "cable"
    ],
    "wof:name":"Alliance Cables Inc",
    "wof:placetype":"venue"
},
  "geometry": {"coordinates":[-114.01082599999999,51.081287],"type":"Point"}
}