{
  "type": "Feature",
  "properties": {
    "addr:full":"100 Edgebyne Cres NW Calgary AB T3A 4B3",
    "addr:housenumber":"100",
    "addr:postcode":"t3a 4b3",
    "addr:street":"Edgebyne Cres Nw",
    "iso:country":"CA",
    "sg:address":"100 Edgebyne Cres NW",
    "sg:city":"Calgary",
    "sg:classifiers":[
        {
            "category":"Building & Trades",
            "subcategory":"Construction",
            "type":"Services"
        }
    ],
    "sg:phone":"+1 403 239 7517",
    "sg:postcode":"T3A 4B3",
    "sg:province":"AB",
    "sg:tags":[
        "painter"
    ],
    "wof:name":"Cougar Painting",
    "wof:placetype":"venue"
},
  "geometry": {"coordinates":[-114.15371704099999,51.1281738281],"type":"Point"}
}