{
  "type": "Feature",
  "properties": {
    "addr:full":"Toronto ON M5B 1J3",
    "addr:postcode":"m5b 1j3",
    "iso:country":"CA",
    "sg:city":"Toronto",
    "sg:classifiers":[
        {
            "category":"Communications",
            "subcategory":"Film & Video Production",
            "type":"Services"
        }
    ],
    "sg:phone":"+1 416 977 8966",
    "sg:postcode":"M5B 1J3",
    "sg:province":"ON",
    "sg:tags":[
        "television",
        "producer"
    ],
    "wof:name":"Independent Production Fund",
    "wof:placetype":"venue"
},
  "geometry": {"coordinates":[-79.38266,43.661568],"type":"Point"}
}