{
  "type": "Feature",
  "properties": {
    "iso:country":"CA",
    "sg:address":"120 2nd St",
    "sg:city":"Hudson",
    "sg:classifiers":[
        {
            "category":"Professional",
            "type":"Services"
        }
    ],
    "sg:phone":"+1 807 582 3365",
    "sg:postcode":"P0V 1X0",
    "sg:province":"ON",
    "sg:tags":[
        "establishment"
    ],
    "wof:name":"Hudson Sporting Goods",
    "wof:placetype":"venue"
},
  "geometry": {"coordinates":[-92.169303894,50.090839386],"type":"Point"}
}