{
  "type": "Feature",
  "properties": {
    "addr:full":"1135 Red Head Rd Saint John NB E2P 1J9",
    "addr:housenumber":"1135",
    "addr:postcode":"e2p 1j9",
    "addr:street":"Red Head Rd",
    "iso:country":"CA",
    "sg:address":"1135 Red Head Rd",
    "sg:city":"Saint John",
    "sg:classifiers":[
        {
            "category":"Building & Trades",
            "subcategory":"Electrical",
            "type":"Services"
        }
    ],
    "sg:phone":"+1 506 647 6887",
    "sg:postcode":"E2P 1J9",
    "sg:province":"NB",
    "sg:tags":[
        "electric",
        "contractor"
    ],
    "wof:name":"Glenn Patrick Griffin Inc",
    "wof:placetype":"venue"
},
  "geometry": {"coordinates":[-66.01282500000001,45.256119],"type":"Point"}
}