{
  "type": "Feature",
  "properties": {
    "addr:full":"61 Rue Valin Saint-Fulgence QC G0V 1S0",
    "addr:housenumber":"61",
    "addr:postcode":"g0v 1s0",
    "addr:street":"Rue Valin",
    "iso:country":"CA",
    "sg:address":"61 Rue Valin",
    "sg:city":"Saint-Fulgence",
    "sg:classifiers":[
        {
            "category":"Manufacturing",
            "subcategory":"Printing",
            "type":"Manufacturing & Wholesale Goods"
        }
    ],
    "sg:phone":"+1 418 674 2379",
    "sg:postcode":"G0V 1S0",
    "sg:province":"QC",
    "sg:tags":[
        "bookbinder"
    ],
    "wof:name":"Reliure Apc Inc",
    "wof:placetype":"venue"
},
  "geometry": {"coordinates":[-70.98101043699999,48.4609260559],"type":"Point"}
}