{
  "type": "Feature",
  "properties": {
    "addr:full":"2146 Government St Penticton BC V2A 8B5",
    "addr:housenumber":"2146",
    "addr:postcode":"v2a 8b5",
    "addr:street":"Government St",
    "iso:country":"CA",
    "sg:address":"2146 Government St",
    "sg:city":"Penticton",
    "sg:classifiers":[
        {
            "category":"Retail",
            "subcategory":"Repair Shop",
            "type":"Services"
        }
    ],
    "sg:phone":"+1 250 492 7890",
    "sg:postcode":"V2A 8B5",
    "sg:province":"BC",
    "sg:tags":[
        "television",
        "radio"
    ],
    "wof:name":"Guzman Electronics",
    "wof:placetype":"venue"
},
  "geometry": {"coordinates":[-119.573853,49.475834],"type":"Point"}
}