{
  "type": "Feature",
  "properties": {
    "addr:full":"6160 6th Ave Whitehorse YT Y1A 1N6",
    "addr:housenumber":"6160",
    "addr:postcode":"y1a 1n6",
    "addr:street":"6Th Ave",
    "iso:country":"CA",
    "sg:address":"6160 6th Ave",
    "sg:city":"Whitehorse",
    "sg:classifiers":[
        {
            "category":"Shopping",
            "subcategory":"Clothing, Apparel, & Fashions",
            "type":"Retail Goods"
        }
    ],
    "sg:phone":"+1 867 667 6582",
    "sg:postcode":"Y1A 1N6",
    "sg:province":"YT",
    "sg:tags":[
        "dressmaker"
    ],
    "wof:name":"Helen's Sewing",
    "wof:placetype":"venue"
},
  "geometry": {"coordinates":[-135.06344604500001,60.7220916748],"type":"Point"}
}