{
  "type": "Feature",
  "properties": {
    "addr:full":"Ewen Ave Glen Ewen SK S0C 1C0",
    "addr:postcode":"s0c 1c0",
    "addr:street":"Ewen Ave Glen",
    "iso:country":"CA",
    "sg:address":"Ewen Ave",
    "sg:city":"Glen Ewen",
    "sg:classifiers":[
        {
            "category":"Recreation",
            "type":"Entertainment"
        }
    ],
    "sg:phone":"+1 306 925 2207",
    "sg:postcode":"S0C 1C0",
    "sg:province":"SK",
    "sg:tags":[
        "skating",
        "rink"
    ],
    "wof:name":"Glen Ewen Communiplex",
    "wof:placetype":"venue"
},
  "geometry": {"coordinates":[-102.019485,49.210342],"type":"Point"}
}