{
  "type": "Feature",
  "properties": {
    "addr:full":"1347 Johnston Rd White Rock BC V4B 3Z3",
    "addr:housenumber":"1347",
    "addr:postcode":"v4b 3z3",
    "addr:street":"Johnston Rd",
    "iso:country":"CA",
    "sg:address":"1347 Johnston Rd",
    "sg:city":"White Rock",
    "sg:classifiers":[
        {
            "category":"Restaurant",
            "type":"Food & Drink"
        }
    ],
    "sg:phone":"+1 604 536 3703",
    "sg:postcode":"V4B 3Z3",
    "sg:province":"BC",
    "wof:name":"Yucca Tree Cafe",
    "wof:placetype":"venue"
},
  "geometry": {"coordinates":[-122.801376,49.026543],"type":"Point"}
}