{
  "type": "Feature",
  "properties": {
    "iso:country":"CA",
    "sg:address":"607 Patricia St",
    "sg:city":"Jasper",
    "sg:classifiers":[
        {
            "category":"Retail",
            "subcategory":"Self-service Laundry",
            "type":"Services"
        }
    ],
    "sg:phone":"+1 780 852 3852",
    "sg:postcode":"T0E 1E0",
    "sg:province":"AB",
    "wof:name":"Coin Clean",
    "wof:placetype":"venue"
},
  "geometry": {"coordinates":[-118.081306458,52.8759422302],"type":"Point"}
}