{
  "type": "Feature",
  "properties": {
    "addr:full":"1346 Rue Bon-Air L'Ancienne-Lorette QC G2E 1H7",
    "addr:housenumber":"1346",
    "addr:postcode":"g2e 1h7",
    "addr:street":"Rue Bon-Air",
    "iso:country":"CA",
    "sg:address":"1346 Rue Bon-Air",
    "sg:city":"L'Ancienne-Lorette",
    "sg:classifiers":[
        {
            "category":"Building & Trades",
            "subcategory":"Construction",
            "type":"Services"
        }
    ],
    "sg:phone":"+1 418 877 3126",
    "sg:postcode":"G2E 1H7",
    "sg:province":"QC",
    "sg:tags":[
        "siding",
        "contractor"
    ],
    "wof:name":"Agregat Re Nor Inc",
    "wof:placetype":"venue"
},
  "geometry": {"coordinates":[-71.365135,46.809093],"type":"Point"}
}