{
  "type": "Feature",
  "properties": {
    "addr:full":"3007 Ch Chesham Milan QC G0Y 1E0",
    "addr:postcode":"3007;g0y 1e0",
    "addr:street":"Ch Chesham",
    "iso:country":"CA",
    "sg:address":"3007 Ch Chesham",
    "sg:city":"Milan",
    "sg:classifiers":[
        {
            "category":"Professional",
            "subcategory":"Business Services",
            "type":"Services"
        }
    ],
    "sg:phone":"+1 819 657 4702",
    "sg:postcode":"G0Y 1E0",
    "sg:province":"QC",
    "sg:tags":[
        "translator",
        "interpreter"
    ],
    "wof:name":"Dube, Lise",
    "wof:placetype":"venue"
},
  "geometry": {"coordinates":[-71.139252,45.59951],"type":"Point"}
}