{
  "type": "Feature",
  "properties": {
    "addr:full":"800 Westgate Rd Oakville ON L6L 5N2",
    "addr:housenumber":"800",
    "addr:postcode":"l6l 5n2",
    "addr:street":"Westgate Rd",
    "iso:country":"CA",
    "sg:address":"800 Westgate Rd",
    "sg:city":"Oakville",
    "sg:classifiers":[
        {
            "category":"Manufacturing",
            "subcategory":"Tools & Machinery",
            "type":"Manufacturing & Wholesale Goods"
        }
    ],
    "sg:phone":"+1 905 847 8092",
    "sg:postcode":"L6L 5N2",
    "sg:province":"ON",
    "sg:tags":[
        "equipment",
        "lighting"
    ],
    "wof:name":"Control Freqs Inc",
    "wof:placetype":"venue"
},
  "geometry": {"coordinates":[-79.73128509519999,43.4156227112],"type":"Point"}
}