{
  "type": "Feature",
  "properties": {
    "addr:full":"61 Elizabeth Dr Gander NL A1V 1G4",
    "addr:housenumber":"61",
    "addr:postcode":"a1v 1g4",
    "addr:street":"Elizabeth Dr",
    "iso:country":"CA",
    "sg:address":"61 Elizabeth Dr",
    "sg:city":"Gander",
    "sg:classifiers":[
        {
            "category":"Professional",
            "subcategory":"Lawyer & Legal Services",
            "type":"Services"
        }
    ],
    "sg:phone":"+1 709 256 4006",
    "sg:postcode":"A1V 1G4",
    "sg:province":"NL",
    "sg:tags":[
        "attorney"
    ],
    "wof:name":"Easton Facey Hillier & Lawrenc",
    "wof:placetype":"venue"
},
  "geometry": {"coordinates":[-54.606098,48.958042],"type":"Point"}
}