{
  "type": "Feature",
  "properties": {
    "addr:full":"5672 Victoria Dr Vancouver BC V5P 3W4",
    "addr:housenumber":"5672",
    "addr:postcode":"v5p 3w4",
    "addr:street":"Victoria Dr",
    "iso:country":"CA",
    "sg:address":"5672 Victoria Dr",
    "sg:city":"Vancouver",
    "sg:classifiers":[
        {
            "category":"Building & Trades",
            "subcategory":"Construction",
            "type":"Services"
        }
    ],
    "sg:phone":"+1 604 327 2908",
    "sg:postcode":"V5P 3W4",
    "sg:province":"BC",
    "sg:tags":[
        "roofing",
        "contractor"
    ],
    "wof:name":"A-G-Woodward Roofing",
    "wof:placetype":"venue"
},
  "geometry": {"coordinates":[-123.065292,49.233162],"type":"Point"}
}