{
  "type": "Feature",
  "properties": {
    "addr:full":"301 Alpine St Comox BC V9M 1G1",
    "addr:housenumber":"301",
    "addr:postcode":"v9m 1g1",
    "addr:street":"Alpine St",
    "iso:country":"CA",
    "sg:address":"301 Alpine St",
    "sg:city":"Comox",
    "sg:classifiers":[
        {
            "category":"Real Estate",
            "subcategory":"Real Estate Agent",
            "type":"Services"
        }
    ],
    "sg:phone":"+1 250 890 0125",
    "sg:postcode":"V9M 1G1",
    "sg:province":"BC",
    "sg:tags":[
        "management"
    ],
    "wof:name":"Comox Valley Condominium Svc",
    "wof:placetype":"venue"
},
  "geometry": {"coordinates":[-124.94355,49.676456],"type":"Point"}
}