{
  "type": "Feature",
  "properties": {
    "addr:full":"580 Adelaide St N London ON N6B 3J8",
    "addr:housenumber":"580",
    "addr:postcode":"n6b 3j8",
    "addr:street":"Adelaide St N",
    "iso:country":"CA",
    "sg:address":"580 Adelaide St N",
    "sg:city":"London",
    "sg:classifiers":[
        {
            "category":"Food & Beverages",
            "subcategory":"Bakery",
            "type":"Retail Goods"
        }
    ],
    "sg:phone":"+1 519 438 2315",
    "sg:postcode":"N6B 3J8",
    "sg:province":"ON",
    "sg:tags":[
        "baker"
    ],
    "wof:name":"Lusitana Bakery Shop",
    "wof:placetype":"venue"
},
  "geometry": {"coordinates":[-81.2340621948,42.9943237305],"type":"Point"}
}