{
  "type": "Feature",
  "properties": {
    "addr:full":"101 Huron St Toronto ON M5T 2A9",
    "addr:housenumber":"101",
    "addr:postcode":"m5t 2a9",
    "addr:street":"Huron St",
    "iso:country":"CA",
    "sg:address":"101 Huron St",
    "sg:city":"Toronto",
    "sg:classifiers":[
        {
            "category":"Organizations",
            "subcategory":"Religious Organization",
            "type":"Services"
        }
    ],
    "sg:phone":"+1 416 977 3508",
    "sg:postcode":"M5T 2A9",
    "sg:province":"ON",
    "sg:tags":[
        "church"
    ],
    "wof:name":"First Baptist Church",
    "wof:placetype":"venue"
},
  "geometry": {"coordinates":[-79.396423,43.654491],"type":"Point"}
}