{
  "type": "Feature",
  "properties": {
    "addr:full":"Winfield BC V4V 1P6",
    "addr:postcode":"v4v 1p6",
    "iso:country":"CA",
    "sg:city":"Winfield",
    "sg:classifiers":[
        {
            "category":"Cinema",
            "subcategory":"Movie Rental",
            "type":"Entertainment"
        }
    ],
    "sg:phone":"+1 250 766 2296",
    "sg:postcode":"V4V 1P6",
    "sg:province":"BC",
    "sg:tags":[
        "leasing",
        "video",
        "disc",
        "tape"
    ],
    "wof:name":"Video Express",
    "wof:placetype":"venue"
},
  "geometry": {"coordinates":[-119.405601502,50.0245361328],"type":"Point"}
}