{
  "type": "Feature",
  "properties": {
    "addr:full":"2234 Hastings St E Vancouver BC V5L 1V4",
    "addr:housenumber":"2234",
    "addr:postcode":"v5l 1v4",
    "addr:street":"Hastings St E",
    "iso:country":"CA",
    "sg:address":"2234 Hastings St E",
    "sg:city":"Vancouver",
    "sg:classifiers":[
        {
            "category":"Shopping",
            "subcategory":"Bicycles & Sporting Goods",
            "type":"Retail Goods"
        }
    ],
    "sg:phone":"+1 604 254 6910",
    "sg:postcode":"V5L 1V4",
    "sg:province":"BC",
    "sg:tags":[
        "equipment",
        "arts",
        "supply",
        "martial"
    ],
    "wof:name":"Golden Arrow Martial Arts",
    "wof:placetype":"venue"
},
  "geometry": {"coordinates":[-123.05901299999999,49.280983],"type":"Point"}
}