{
  "type": "Feature",
  "properties": {
    "addr:full":"Calgary AB T3K 4L2",
    "addr:postcode":"t3k 4l2",
    "iso:country":"CA",
    "sg:city":"Calgary",
    "sg:classifiers":[
        {
            "category":"Health Services",
            "subcategory":"Doctor",
            "type":"Services"
        }
    ],
    "sg:phone":"+1 403 275 3131",
    "sg:postcode":"T3K 4L2",
    "sg:province":"AB",
    "sg:tags":[
        "dentist"
    ],
    "wof:name":"Sandstone Dental Ctr",
    "wof:placetype":"venue"
},
  "geometry": {"coordinates":[-114.09935,51.133736],"type":"Point"}
}