{
  "type": "Feature",
  "properties": {
    "iso:country":"CA",
    "sg:address":"519 Westmorland Rd",
    "sg:city":"Saint John",
    "sg:classifiers":[
        {
            "category":"Restaurant",
            "type":"Food & Drink"
        }
    ],
    "sg:phone":"+1 506 633 2888",
    "sg:postcode":"E2J 3W9",
    "sg:province":"NB",
    "sg:tags":[
        "pizza"
    ],
    "wof:name":"Mrs Vanellis Italian Pizza",
    "wof:placetype":"venue"
},
  "geometry": {"coordinates":[-66.0164108276,45.3094291687],"type":"Point"}
}