{
  "type": "Feature",
  "properties": {
    "addr:full":"Peachland BC V0H 1X7",
    "addr:postcode":"v0h 1x7",
    "iso:country":"CA",
    "sg:city":"Peachland",
    "sg:classifiers":[
        {
            "category":"Banks & Credit Unions",
            "subcategory":"Investment Brokerage",
            "type":"Services"
        }
    ],
    "sg:phone":"+1 250 767 3358",
    "sg:postcode":"V0H 1X7",
    "sg:province":"BC",
    "sg:tags":[
        "stock",
        "broker",
        "bond"
    ],
    "wof:name":"Edward Jones",
    "wof:placetype":"venue"
},
  "geometry": {"coordinates":[-119.73751799999999,49.772636],"type":"Point"}
}