{
  "type": "Feature",
  "properties": {
    "iso:country":"CA",
    "sg:address":"29 Almont Rd",
    "sg:city":"North York",
    "sg:classifiers":[
        {
            "category":"Building & Trades",
            "subcategory":"Electrical",
            "type":"Services"
        }
    ],
    "sg:phone":"+1 416 633 6874",
    "sg:postcode":"M3H 3E4",
    "sg:province":"ON",
    "sg:tags":[
        "electric",
        "contractor"
    ],
    "wof:name":"Franton Electric Ltd",
    "wof:placetype":"venue"
},
  "geometry": {"coordinates":[-79.43604278559999,43.7392463684],"type":"Point"}
}