{
  "type": "Feature",
  "properties": {
    "addr:full":"311 Brock Ave Toronto ON M6K 2M5",
    "addr:housenumber":"311",
    "addr:postcode":"m6k 2m5",
    "addr:street":"Brock Ave",
    "iso:country":"CA",
    "sg:address":"311 Brock Ave",
    "sg:city":"Toronto",
    "sg:classifiers":[
        {
            "category":"Organizations",
            "subcategory":"Religious Organization",
            "type":"Services"
        }
    ],
    "sg:phone":"+1 416 537 1735",
    "sg:postcode":"M6K 2M5",
    "sg:province":"ON",
    "sg:tags":[
        "church"
    ],
    "wof:name":"Brock Avenue Gospel Hall",
    "wof:placetype":"venue"
},
  "geometry": {"coordinates":[-79.43568399999999,43.650414],"type":"Point"}
}