{
  "type": "Feature",
  "properties": {
    "iso:country":"CA",
    "sg:city":"Scarborough",
    "sg:classifiers":[
        {
            "category":"Education",
            "subcategory":"Special Training",
            "type":"Public Place"
        }
    ],
    "sg:phone":"+1 416 293 2582",
    "sg:postcode":"M1S 2B7",
    "sg:province":"ON",
    "sg:tags":[
        "tutoring"
    ],
    "wof:name":"Wonderkids Learning Ctr",
    "wof:placetype":"venue"
},
  "geometry": {"coordinates":[-79.27578,43.786694],"type":"Point"}
}