{
  "type": "Feature",
  "properties": {
    "addr:full":"3 Queen St Bridgetown NS B0S 1C0",
    "addr:housenumber":"3",
    "addr:postcode":"b0s 1c0",
    "addr:street":"Queen St",
    "iso:country":"CA",
    "sg:address":"3 Queen St",
    "sg:city":"Bridgetown",
    "sg:classifiers":[
        {
            "category":"Professional",
            "subcategory":"Lawyer & Legal Services",
            "type":"Services"
        }
    ],
    "sg:phone":"+1 902 665 4471",
    "sg:postcode":"B0S 1C0",
    "sg:province":"NS",
    "sg:tags":[
        "attorney"
    ],
    "wof:name":"Orlando & Hicks",
    "wof:placetype":"venue"
},
  "geometry": {"coordinates":[-65.291023,44.841393],"type":"Point"}
}