{
  "type": "Feature",
  "properties": {
    "addr:full":"115 Michigan Ave Blind River ON P0R 1B0",
    "addr:housenumber":"115",
    "addr:postcode":"p0r 1b0",
    "addr:street":"Michigan Ave",
    "iso:country":"CA",
    "sg:address":"115 Michigan Ave",
    "sg:city":"Blind River",
    "sg:classifiers":[
        {
            "category":"Building & Trades",
            "subcategory":"Electrical",
            "type":"Services"
        }
    ],
    "sg:phone":"+1 705 356 7176",
    "sg:postcode":"P0R 1B0",
    "sg:province":"ON",
    "sg:tags":[
        "electric",
        "contractor"
    ],
    "wof:name":"Mac Iver Electric",
    "wof:placetype":"venue"
},
  "geometry": {"coordinates":[-82.962479,46.182884],"type":"Point"}
}