{
  "type": "Feature",
  "properties": {
    "addr:full":"Cambridge Station NS B0P 1G0",
    "addr:postcode":"b0p 1g0",
    "addr:street":"Cambridge",
    "iso:country":"CA",
    "sg:city":"Cambridge Station",
    "sg:classifiers":[
        {
            "category":"Education",
            "subcategory":"School",
            "type":"Public Place"
        }
    ],
    "sg:phone":"+1 902 538 4680",
    "sg:postcode":"B0P 1G0",
    "sg:province":"NS",
    "wof:name":"Cambridge Elementary School",
    "wof:placetype":"venue"
},
  "geometry": {"coordinates":[-64.635651,45.057102],"type":"Point"}
}