{
  "type": "Feature",
  "properties": {
    "addr:full":"3075 Boul DE Portland Sherbrooke QC J1L 2Y7",
    "addr:housenumber":"3075",
    "addr:postcode":"j1l 2y7",
    "addr:street":"Boul De Portland",
    "iso:country":"CA",
    "sg:address":"3075 Boul DE Portland",
    "sg:city":"Sherbrooke",
    "sg:classifiers":[
        {
            "category":"Banks & Credit Unions",
            "subcategory":"Bank",
            "type":"Services"
        }
    ],
    "sg:phone":"+1 819 563 4011",
    "sg:postcode":"J1L 2Y7",
    "sg:province":"QC",
    "wof:name":"Banque Nationale",
    "wof:placetype":"venue"
},
  "geometry": {"coordinates":[-71.949966,45.403675],"type":"Point"}
}