{
  "type": "Feature",
  "properties": {
    "addr:full":"2637 Commercial Dr Vancouver BC V5N 4C3",
    "addr:housenumber":"2637",
    "addr:postcode":"v5n 4c3",
    "addr:street":"Commercial Dr",
    "iso:country":"CA",
    "sg:address":"2637 Commercial Dr",
    "sg:city":"Vancouver",
    "sg:classifiers":[
        {
            "category":"Shopping",
            "subcategory":"Discount & Variety Stores",
            "type":"Retail Goods"
        }
    ],
    "sg:phone":"+1 604 879 3196",
    "sg:postcode":"V5N 4C3",
    "sg:province":"BC",
    "sg:tags":[
        "housewares"
    ],
    "wof:name":"Superior Dollar Store",
    "wof:placetype":"venue"
},
  "geometry": {"coordinates":[-123.069923401,49.2610244751],"type":"Point"}
}