{
  "type": "Feature",
  "properties": {
    "addr:full":"10 Lewis Dr Island View NB E3E 1A1",
    "addr:housenumber":"10",
    "addr:postcode":"e3e 1a1",
    "addr:street":"Lewis Dr",
    "iso:country":"CA",
    "sg:address":"10 Lewis Dr",
    "sg:city":"Island View",
    "sg:classifiers":[
        {
            "category":"Building & Trades",
            "subcategory":"Construction",
            "type":"Services"
        }
    ],
    "sg:phone":"+1 506 459 7082",
    "sg:postcode":"E3E 1A1",
    "sg:province":"NB",
    "sg:tags":[
        "concrete",
        "contractor"
    ],
    "wof:name":"Capital Concrete Floors Ltd",
    "wof:placetype":"venue"
},
  "geometry": {"coordinates":[-66.8127746582,45.9640159607],"type":"Point"}
}