{
  "type": "Feature",
  "properties": {
    "addr:full":"9085 Rock Island Rd Prince George BC V2N 5T4",
    "addr:housenumber":"9085",
    "addr:postcode":"v2n 5t4",
    "addr:street":"Rock Island Rd",
    "iso:country":"CA",
    "sg:address":"9085 Rock Island Rd",
    "sg:city":"Prince George",
    "sg:classifiers":[
        {
            "category":"Retail",
            "subcategory":"Repair Shop",
            "type":"Services"
        }
    ],
    "sg:phone":"+1 250 564 0324",
    "sg:postcode":"V2N 5T4",
    "sg:province":"BC",
    "sg:tags":[
        "welding"
    ],
    "wof:name":"Northern Aluminum Tank Svc Ltd",
    "wof:placetype":"venue"
},
  "geometry": {"coordinates":[-122.733818054,53.8401641846],"type":"Point"}
}