{
  "type": "Feature",
  "properties": {
    "addr:full":"Calgary AB T2H 2L9",
    "addr:postcode":"t2h 2l9",
    "iso:country":"CA",
    "sg:city":"Calgary",
    "sg:classifiers":[
        {
            "category":"Wholesale",
            "subcategory":"Meat",
            "type":"Manufacturing & Wholesale Goods"
        }
    ],
    "sg:phone":"+1 403 213 3977",
    "sg:postcode":"T2H 2L9",
    "sg:province":"AB",
    "wof:name":"Precision Trading",
    "wof:placetype":"venue"
},
  "geometry": {"coordinates":[-114.078163,50.988476],"type":"Point"}
}