{
  "type": "Feature",
  "properties": {
    "addr:full":"118 Little Ave Barrie ON L4N 4X4",
    "addr:housenumber":"118",
    "addr:postcode":"l4n 4x4",
    "addr:street":"Little Ave",
    "iso:country":"CA",
    "sg:address":"118 Little Ave",
    "sg:city":"Barrie",
    "sg:classifiers":[
        {
            "category":"Autos & Motor Vehicles",
            "subcategory":"Auto Supplies",
            "type":"Retail Goods"
        }
    ],
    "sg:phone":"+1 705 722 3822",
    "sg:postcode":"L4N 4X4",
    "sg:province":"ON",
    "sg:tags":[
        "automobile",
        "parts"
    ],
    "wof:name":"Canadian Tire Gas Bar",
    "wof:placetype":"venue"
},
  "geometry": {"coordinates":[-79.68231201170001,44.3624305725],"type":"Point"}
}