{
  "type": "Feature",
  "properties": {
    "addr:full":"Brampton ON L6W 3P1",
    "addr:postcode":"l6w 3p1",
    "iso:country":"CA",
    "sg:city":"Brampton",
    "sg:classifiers":[
        {
            "category":"Professional",
            "subcategory":"Lawyer & Legal Services",
            "type":"Services"
        }
    ],
    "sg:phone":"+1 905 453 3629",
    "sg:postcode":"L6W 3P1",
    "sg:province":"ON",
    "sg:tags":[
        "attorney"
    ],
    "wof:name":"Ceci, Gina",
    "wof:placetype":"venue"
},
  "geometry": {"coordinates":[-79.7592468262,43.6863250732],"type":"Point"}
}