{
  "type": "Feature",
  "properties": {
    "addr:full":"3670 Hurontario St Mississauga ON L5B 1P3",
    "addr:housenumber":"3670",
    "addr:postcode":"l5b 1p3",
    "addr:street":"Hurontario St",
    "iso:country":"CA",
    "sg:address":"3670 Hurontario St",
    "sg:city":"Mississauga",
    "sg:classifiers":[
        {
            "category":"Restaurant",
            "type":"Food & Drink"
        }
    ],
    "sg:phone":"+1 905 803 6713",
    "sg:postcode":"L5B 1P3",
    "sg:province":"ON",
    "wof:name":"Cafe Nicole Bistro",
    "wof:placetype":"venue"
},
  "geometry": {"coordinates":[-79.6342468262,43.5927581787],"type":"Point"}
}