{
  "type": "Feature",
  "properties": {
    "addr:full":"3521 Mainway Burlington ON L7M 1A9",
    "addr:housenumber":"3521",
    "addr:postcode":"l7m 1a9",
    "addr:street":"Mainway",
    "iso:country":"CA",
    "sg:address":"3521 Mainway",
    "sg:city":"Burlington",
    "sg:classifiers":[
        {
            "category":"Recreation",
            "type":"Entertainment"
        }
    ],
    "sg:phone":"+1 905 637 8351",
    "sg:postcode":"L7M 1A9",
    "sg:province":"ON",
    "sg:tags":[
        "club",
        "hockey"
    ],
    "wof:name":"Burlington Oldtimers Hockey",
    "wof:placetype":"venue"
},
  "geometry": {"coordinates":[-79.7975616455,43.3703460693],"type":"Point"}
}