{
  "type": "Feature",
  "properties": {
    "iso:country":"CA",
    "sg:address":"1000 Ch Saint-Jose",
    "sg:city":"LA Prairie",
    "sg:classifiers":[
        {
            "category":"Freight",
            "type":"Transportation"
        }
    ],
    "sg:phone":"+1 450 444 2020",
    "sg:postcode":"J5R 6A9",
    "sg:province":"QC",
    "sg:tags":[
        "mover"
    ],
    "wof:name":"Demenagement & Entreposage",
    "wof:placetype":"venue"
},
  "geometry": {"coordinates":[-73.4934310913,45.4017105103],"type":"Point"}
}