{
  "type": "Feature",
  "properties": {
    "iso:country":"CA",
    "sg:address":"6359 Boul Leger",
    "sg:city":"Montreal-Nord",
    "sg:classifiers":[
        {
            "category":"Personal",
            "subcategory":"Beauty Salon",
            "type":"Services"
        }
    ],
    "sg:phone":"+1 514 322 5550",
    "sg:postcode":"H1G 1L4",
    "sg:province":"QC",
    "wof:name":"Salon Lyne Coiffure",
    "wof:placetype":"venue"
},
  "geometry": {"coordinates":[-73.623535,45.62278],"type":"Point"}
}