{
  "type": "Feature",
  "properties": {
    "iso:country":"CA",
    "sg:address":"444 5E Rue",
    "sg:city":"Shawinigan",
    "sg:classifiers":[
        {
            "category":"Real Estate",
            "subcategory":"Real Estate Operator",
            "type":"Services"
        }
    ],
    "sg:phone":"+1 819 537 9730",
    "sg:postcode":"G9N 1E6",
    "sg:province":"QC",
    "sg:tags":[
        "post",
        "shopping",
        "center",
        "mall"
    ],
    "wof:name":"Promenade Centre-Commercial",
    "wof:placetype":"venue"
},
  "geometry": {"coordinates":[-72.7484970093,46.5406532288],"type":"Point"}
}