{
  "type": "Feature",
  "properties": {
    "iso:country":"CA",
    "sg:address":"3035 Boul Le Carrefour # T1",
    "sg:city":"Laval",
    "sg:classifiers":[
        {
            "category":"Restaurant",
            "type":"Food & Drink"
        }
    ],
    "sg:phone":"+1 450 973 1791",
    "sg:postcode":"H7T 1C8",
    "sg:province":"QC",
    "wof:name":"Cafe Depot",
    "wof:placetype":"venue"
},
  "geometry": {"coordinates":[-73.750549,45.568085],"type":"Point"}
}