{
  "type": "Feature",
  "properties": {
    "addr:full":"3035 Boul Le Carrefour # T1 Laval QC H7T 1C8",
    "addr:housenumber":"3035;# t1",
    "addr:postcode":"h7t 1c8",
    "addr:street":"Boul Le Carrefour",
    "iso:country":"CA",
    "sg:address":"3035 Boul Le Carrefour # T1",
    "sg:city":"Laval",
    "sg:classifiers":[
        {
            "category":"Restaurant",
            "type":"Food & Drink"
        }
    ],
    "sg:phone":"+1 450 973 1791",
    "sg:postcode":"H7T 1C8",
    "sg:province":"QC",
    "wof:name":"Cafe Depot",
    "wof:placetype":"venue"
},
  "geometry": {"coordinates":[-73.75054900000001,45.568085],"type":"Point"}
}