{
  "type": "Feature",
  "properties": {
    "addr:full":"Anglican Rectory Eastport NL A0G 1Z0",
    "addr:postcode":"a0g 1z0",
    "iso:country":"CA",
    "sg:address":"Anglican Rectory",
    "sg:city":"Eastport",
    "sg:classifiers":[
        {
            "category":"Organizations",
            "subcategory":"Religious Organization",
            "type":"Services"
        }
    ],
    "sg:phone":"+1 709 677 2504",
    "sg:postcode":"A0G 1Z0",
    "sg:province":"NL",
    "sg:tags":[
        "church"
    ],
    "wof:name":"Holy Cross Anglican Church",
    "wof:placetype":"venue"
},
  "geometry": {"coordinates":[-53.761264801,48.652179718],"type":"Point"}
}