{
  "type": "Feature",
  "properties": {
    "addr:full":"700 Division St Kingston ON K7K 6N8",
    "addr:housenumber":"700",
    "addr:postcode":"k7k 6n8",
    "addr:street":"Division St",
    "iso:country":"CA",
    "sg:address":"700 Division St",
    "sg:city":"Kingston",
    "sg:classifiers":[
        {
            "category":"Real Estate",
            "subcategory":"Real Estate Agent",
            "type":"Services"
        }
    ],
    "sg:phone":"+1 613 544 8362",
    "sg:postcode":"K7K 6N8",
    "sg:province":"ON",
    "sg:tags":[
        "housing"
    ],
    "wof:name":"Porto Village",
    "wof:placetype":"venue"
},
  "geometry": {"coordinates":[-76.496437,44.250118],"type":"Point"}
}