{
  "type": "Feature",
  "properties": {
    "addr:full":"Varennes QC J3X 1P7",
    "addr:postcode":"j3x 1p7",
    "iso:country":"CA",
    "sg:city":"Varennes",
    "sg:classifiers":[
        {
            "category":"Wholesale",
            "subcategory":"Machinery & Supplies",
            "type":"Manufacturing & Wholesale Goods"
        }
    ],
    "sg:phone":"+1 450 652 2662",
    "sg:postcode":"J3X 1P7",
    "sg:province":"QC",
    "sg:tags":[
        "mechanical",
        "gas",
        "contractor"
    ],
    "wof:name":"Compresseur Plus Rg Inc",
    "wof:placetype":"venue"
},
  "geometry": {"coordinates":[-73.41842699999999,45.653843],"type":"Point"}
}