{
  "type": "Feature",
  "properties": {
    "addr:full":"Mission BC V2V 4J5",
    "addr:postcode":"v2v 4j5",
    "iso:country":"CA",
    "sg:city":"Mission",
    "sg:classifiers":[
        {
            "category":"Organizations",
            "subcategory":"Religious Organization",
            "type":"Services"
        }
    ],
    "sg:phone":"+1 604 820 4402",
    "sg:postcode":"V2V 4J5",
    "sg:province":"BC",
    "sg:tags":[
        "church"
    ],
    "wof:name":"New Heights Community Church",
    "wof:placetype":"venue"
},
  "geometry": {"coordinates":[-122.28280599999999,49.159996],"type":"Point"}
}