{
  "type": "Feature",
  "properties": {
    "addr:full":"1682 100th St North Battleford SK S9A 0W6",
    "addr:housenumber":"1682",
    "addr:postcode":"s9a 0w6",
    "addr:street":"100Th St",
    "iso:country":"CA",
    "sg:address":"1682 100th St",
    "sg:city":"North Battleford",
    "sg:classifiers":[
        {
            "category":"Professional",
            "subcategory":"Accounting & Tax Preparation",
            "type":"Services"
        }
    ],
    "sg:phone":"+1 306 445 7448",
    "sg:postcode":"S9A 0W6",
    "sg:province":"SK",
    "sg:tags":[
        "accountant"
    ],
    "wof:name":"Clements & Kwong",
    "wof:placetype":"venue"
},
  "geometry": {"coordinates":[-108.298797607,52.7823562622],"type":"Point"}
}