{
  "type": "Feature",
  "properties": {
    "addr:full":"Victoria BC V8X 1K1",
    "addr:postcode":"v8x 1k1",
    "iso:country":"CA",
    "sg:city":"Victoria",
    "sg:classifiers":[
        {
            "category":"Professional",
            "subcategory":"Accounting & Tax Preparation",
            "type":"Services"
        }
    ],
    "sg:phone":"+1 250 708 0070",
    "sg:postcode":"V8X 1K1",
    "sg:province":"BC",
    "sg:tags":[
        "payroll"
    ],
    "wof:name":"Paytrak Payroll Svc",
    "wof:placetype":"venue"
},
  "geometry": {"coordinates":[-123.36200714100001,48.448890686],"type":"Point"}
}