{
  "type": "Feature",
  "properties": {
    "addr:full":"4498 Rue Sainte-Catherine O Westmount QC H3Z 1R7",
    "addr:housenumber":"4498",
    "addr:postcode":"h3z 1r7",
    "addr:street":"Rue Sainte-Catherine O",
    "iso:country":"CA",
    "sg:address":"4498 Rue Sainte-Catherine O",
    "sg:city":"Westmount",
    "sg:classifiers":[
        {
            "category":"Food & Beverages",
            "subcategory":"Groceries & Convenience Stores",
            "type":"Retail Goods"
        }
    ],
    "sg:phone":"+1 514 932 1477",
    "sg:postcode":"H3Z 1R7",
    "sg:province":"QC",
    "sg:tags":[
        "grocer"
    ],
    "wof:name":"Clifford's Market",
    "wof:placetype":"venue"
},
  "geometry": {"coordinates":[-73.59367399999999,45.48074],"type":"Point"}
}