{
  "type": "Feature",
  "properties": {
    "iso:country":"CA",
    "sg:address":"4498 Rue Sainte-Catherine O",
    "sg:city":"Westmount",
    "sg:classifiers":[
        {
            "category":"Food & Beverages",
            "subcategory":"Groceries & Convenience Stores",
            "type":"Retail Goods"
        }
    ],
    "sg:phone":"+1 514 932 1477",
    "sg:postcode":"H3Z 1R7",
    "sg:province":"QC",
    "sg:tags":[
        "grocer"
    ],
    "wof:name":"Clifford's Market",
    "wof:placetype":"venue"
},
  "geometry": {"coordinates":[-73.593674,45.48074],"type":"Point"}
}