{
  "type": "Feature",
  "properties": {
    "addr:full":"4916 47th Ave Two Hills AB T0B 4K0",
    "addr:housenumber":"4916",
    "addr:postcode":"t0b 4k0",
    "addr:street":"47Th Ave",
    "iso:country":"CA",
    "sg:address":"4916 47th Ave",
    "sg:city":"Two Hills",
    "sg:classifiers":[
        {
            "category":"Banks & Credit Unions",
            "subcategory":"Bank",
            "type":"Services"
        }
    ],
    "sg:phone":"+1 780 657 3321",
    "sg:postcode":"T0B 4K0",
    "sg:province":"AB",
    "wof:name":"Battle River Credit Union Ltd",
    "wof:placetype":"venue"
},
  "geometry": {"coordinates":[-111.74279,53.709133],"type":"Point"}
}