{
  "type": "Feature",
  "properties": {
    "addr:full":"2885 Justice Way Abbotsford BC V2T 3P6",
    "addr:housenumber":"2885",
    "addr:postcode":"v2t 3p6",
    "addr:street":"Justice Way",
    "iso:country":"CA",
    "sg:address":"2885 Justice Way",
    "sg:city":"Abbotsford",
    "sg:classifiers":[
        {
            "category":"Professional",
            "subcategory":"Lawyer & Legal Services",
            "type":"Services"
        }
    ],
    "sg:phone":"+1 604 859 1377",
    "sg:postcode":"V2T 3P6",
    "sg:province":"BC",
    "sg:tags":[
        "attorney"
    ],
    "wof:name":"G Jack Harris Law Office",
    "wof:placetype":"venue"
},
  "geometry": {"coordinates":[-122.33105468799999,49.0545806885],"type":"Point"}
}