{
  "type": "Feature",
  "properties": {
    "addr:full":"27 Ryan Pl Brantford ON N3S 7S1",
    "addr:housenumber":"27",
    "addr:postcode":"n3s 7s1",
    "addr:street":"Ryan Pl",
    "iso:country":"CA",
    "sg:address":"27 Ryan Pl",
    "sg:city":"Brantford",
    "sg:classifiers":[
        {
            "category":"Wholesale",
            "subcategory":"Sporting Goods",
            "type":"Manufacturing & Wholesale Goods"
        }
    ],
    "sg:phone":"+1 519 758 1616",
    "sg:postcode":"N3S 7S1",
    "sg:province":"ON",
    "sg:tags":[
        "course",
        "golf",
        "equipment"
    ],
    "wof:name":"Ncm Golf Systems Inc",
    "wof:placetype":"venue"
},
  "geometry": {"coordinates":[-80.22607421879999,43.15284729],"type":"Point"}
}