{
  "type": "Feature",
  "properties": {
    "iso:country":"CA",
    "sg:city":"Montreal",
    "sg:classifiers":[
        {
            "category":"Professional",
            "subcategory":"Computer Services",
            "type":"Services"
        }
    ],
    "sg:phone":"+1 514 281 5100",
    "sg:postcode":"H3A 1V4",
    "sg:province":"QC",
    "sg:tags":[
        "internet",
        "software"
    ],
    "wof:name":"I-Network 101 Inc",
    "wof:placetype":"venue"
},
  "geometry": {"coordinates":[-73.5755691528,45.5015296936],"type":"Point"}
}