{
  "type": "Feature",
  "properties": {
    "addr:full":"395 Oakdale Rd North York ON M3N 1W7",
    "addr:housenumber":"395",
    "addr:postcode":"m3n 1w7",
    "addr:street":"Oakdale Rd",
    "iso:country":"CA",
    "sg:address":"395 Oakdale Rd",
    "sg:city":"North York",
    "sg:classifiers":[
        {
            "category":"Manufacturing",
            "subcategory":"Paper Products",
            "type":"Manufacturing & Wholesale Goods"
        }
    ],
    "sg:phone":"+1 416 742 8323",
    "sg:postcode":"M3N 1W7",
    "sg:province":"ON",
    "sg:tags":[
        "board"
    ],
    "wof:name":"Chipboard Connection",
    "wof:placetype":"venue"
},
  "geometry": {"coordinates":[-79.526596,43.748329],"type":"Point"}
}