{
  "type": "Feature",
  "properties": {
    "addr:full":"615 2nd St Humboldt SK S0K 2A0",
    "addr:housenumber":"615",
    "addr:postcode":"s0k 2a0",
    "addr:street":"2Nd St",
    "iso:country":"CA",
    "sg:address":"615 2nd St",
    "sg:city":"Humboldt",
    "sg:classifiers":[
        {
            "category":"Wholesale",
            "subcategory":"Machinery & Supplies",
            "type":"Manufacturing & Wholesale Goods"
        }
    ],
    "sg:phone":"+1 306 682 5404",
    "sg:postcode":"S0K 2A0",
    "sg:province":"SK",
    "sg:tags":[
        "bookbinder",
        "equipment"
    ],
    "wof:name":"Provincial Bindery Ltd",
    "wof:placetype":"venue"
},
  "geometry": {"coordinates":[-105.11396000000001,52.198044],"type":"Point"}
}