{
  "type": "Feature",
  "properties": {
    "iso:country":"CA",
    "sg:address":"38 Steeles Ave E",
    "sg:city":"Thornhill",
    "sg:classifiers":[
        {
            "category":"Professional",
            "subcategory":"Accounting & Tax Preparation",
            "type":"Services"
        }
    ],
    "sg:phone":"+1 905 881 3533",
    "sg:postcode":"L3T 1A2",
    "sg:province":"ON",
    "sg:tags":[
        "accountant"
    ],
    "wof:name":"Zeppieri & CO",
    "wof:placetype":"venue"
},
  "geometry": {"coordinates":[-79.4166564941,43.7988929749],"type":"Point"}
}