{
  "type": "Feature",
  "properties": {
    "iso:country":"CA",
    "sg:address":"29158 Hwy 7",
    "sg:city":"Arden",
    "sg:classifiers":[
        {
            "category":"Education",
            "subcategory":"School",
            "type":"Public Place"
        }
    ],
    "sg:phone":"+1 613 335 5617",
    "sg:postcode":"K0H 1B0",
    "sg:province":"ON",
    "wof:name":"Arden Court Children's Rsdnc",
    "wof:placetype":"venue"
},
  "geometry": {"coordinates":[-76.9240570068,44.7209091187],"type":"Point"}
}