{
  "type": "Feature",
  "properties": {
    "addr:full":"5002 Forrest Dr Yellowknife NT X1A 2A9",
    "addr:housenumber":"5002",
    "addr:postcode":"x1a 2a9",
    "addr:street":"Forrest Dr",
    "iso:country":"CA",
    "sg:address":"5002 Forrest Dr",
    "sg:city":"Yellowknife",
    "sg:classifiers":[
        {
            "category":"Communications",
            "subcategory":"Radio Station",
            "type":"Services"
        }
    ],
    "sg:phone":"+1 867 920 5400",
    "sg:postcode":"X1A 2A9",
    "sg:province":"NT",
    "sg:tags":[
        "television",
        "broadcasting",
        "co",
        "company"
    ],
    "wof:name":"Canadian Broadcasting Corp",
    "wof:placetype":"venue"
},
  "geometry": {"coordinates":[-114.38904599999999,62.446224],"type":"Point"}
}