{
  "type": "Feature",
  "properties": {
    "addr:full":"404 Main St Woodstock ON N4S 7X5",
    "addr:housenumber":"404",
    "addr:postcode":"n4s 7x5",
    "addr:street":"Main St",
    "iso:country":"CA",
    "sg:address":"404 Main St",
    "sg:city":"Woodstock",
    "sg:classifiers":[
        {
            "category":"Manufacturing",
            "subcategory":"Pet Food",
            "type":"Manufacturing & Wholesale Goods"
        }
    ],
    "sg:phone":"+1 519 539 8561",
    "sg:postcode":"N4S 7X5",
    "sg:province":"ON",
    "sg:tags":[
        "feed"
    ],
    "wof:name":"Agribrands Purina Canada Inc",
    "wof:placetype":"venue"
},
  "geometry": {"coordinates":[-80.759872,43.12624],"type":"Point"}
}