{
  "type": "Feature",
  "properties": {
    "addr:full":"271 Rue Principale Saint-Victor QC G0M 2B0",
    "addr:housenumber":"271",
    "addr:postcode":"g0m 2b0",
    "addr:street":"Rue Principale",
    "iso:country":"CA",
    "sg:address":"271 Rue Principale",
    "sg:city":"Saint-Victor",
    "sg:classifiers":[
        {
            "category":"Restaurant",
            "type":"Food & Drink"
        }
    ],
    "sg:phone":"+1 418 588 6600",
    "sg:postcode":"G0M 2B0",
    "sg:province":"QC",
    "wof:name":"Pizzeria Jean-Pierre",
    "wof:placetype":"venue"
},
  "geometry": {"coordinates":[-70.90630299999999,46.147438],"type":"Point"}
}