{
  "type": "Feature",
  "properties": {
    "addr:full":"356 Trunk Rd Duncan BC V9L 2P6",
    "addr:housenumber":"356",
    "addr:postcode":"v9l 2p6",
    "addr:street":"Trunk Rd",
    "iso:country":"CA",
    "sg:address":"356 Trunk Rd",
    "sg:city":"Duncan",
    "sg:classifiers":[
        {
            "category":"Shopping",
            "subcategory":"Shoes",
            "type":"Retail Goods"
        }
    ],
    "sg:phone":"+1 250 748 4033",
    "sg:postcode":"V9L 2P6",
    "sg:province":"BC",
    "wof:name":"Volume Shoes",
    "wof:placetype":"venue"
},
  "geometry": {"coordinates":[-123.701363,48.776688],"type":"Point"}
}