{
  "type": "Feature",
  "properties": {
    "iso:country":"CA",
    "sg:address":"515 Main St",
    "sg:city":"Asquith",
    "sg:classifiers":[
        {
            "category":"Organizations",
            "subcategory":"Professional Association",
            "type":"Services"
        }
    ],
    "sg:phone":"+1 306 329 4393",
    "sg:postcode":"S0K 0J0",
    "sg:province":"SK",
    "wof:name":"New Horizons",
    "wof:placetype":"venue"
},
  "geometry": {"coordinates":[-107.229431152,52.132724762],"type":"Point"}
}