{
  "type": "Feature",
  "properties": {
    "addr:full":"23505 Isle Pierre-Reid Lake Rd Prince George BC V2K 5P1",
    "addr:housenumber":"23505",
    "addr:postcode":"v2k 5p1",
    "addr:street":"Isle Pierre-Reid Lake Rd",
    "iso:country":"CA",
    "sg:address":"23505 Isle Pierre-Reid Lake Rd",
    "sg:city":"Prince George",
    "sg:classifiers":[
        {
            "category":"Organizations",
            "subcategory":"Professional Association",
            "type":"Services"
        }
    ],
    "sg:phone":"+1 250 967 4316",
    "sg:postcode":"V2K 5P1",
    "sg:province":"BC",
    "wof:name":"Reid Lake Community Assn",
    "wof:placetype":"venue"
},
  "geometry": {"coordinates":[-122.745087,53.91235],"type":"Point"}
}