{
  "type": "Feature",
  "properties": {
    "iso:country":"CA",
    "sg:address":"289 Lincoln Rd",
    "sg:city":"Waterloo",
    "sg:classifiers":[
        {
            "category":"Organizations",
            "subcategory":"Religious Organization",
            "type":"Services"
        }
    ],
    "sg:phone":"+1 519 885 4800",
    "sg:postcode":"N2J 2P6",
    "sg:province":"ON",
    "sg:tags":[
        "church"
    ],
    "wof:name":"Lincoln Heights Missionary Chr",
    "wof:placetype":"venue"
},
  "geometry": {"coordinates":[-80.505814,43.481731],"type":"Point"}
}