{
  "type": "Feature",
  "properties": {
    "addr:full":"1991 Des Pionniers Ave Balmoral NB E8E 1C2",
    "addr:housenumber":"1991",
    "addr:postcode":"e8e 1c2",
    "addr:street":"Des Pionniers Ave",
    "iso:country":"CA",
    "sg:address":"1991 Des Pionniers Ave",
    "sg:city":"Balmoral",
    "sg:classifiers":[
        {
            "category":"Communications",
            "subcategory":"Radio Station",
            "type":"Services"
        }
    ],
    "sg:phone":"+1 506 826 1040",
    "sg:postcode":"E8E 1C2",
    "sg:province":"NB",
    "sg:tags":[
        "company",
        "broadcasting"
    ],
    "wof:name":"Cims-FM",
    "wof:placetype":"venue"
},
  "geometry": {"coordinates":[-66.4906997681,47.9608573914],"type":"Point"}
}