{
  "type": "Feature",
  "properties": {
    "addr:full":"Etobicoke ON M9V 2L6",
    "addr:postcode":"m9v 2l6",
    "iso:country":"CA",
    "sg:city":"Etobicoke",
    "sg:classifiers":[
        {
            "category":"Food & Beverages",
            "subcategory":"Bakery",
            "type":"Retail Goods"
        }
    ],
    "sg:phone":"+1 416 743 4579",
    "sg:postcode":"M9V 2L6",
    "sg:province":"ON",
    "sg:tags":[
        "baker"
    ],
    "wof:name":"Canosa Bakery",
    "wof:placetype":"venue"
},
  "geometry": {"coordinates":[-79.607986,43.750149],"type":"Point"}
}