{
  "type": "Feature",
  "properties": {
    "addr:full":"Rock Forest QC J1N 3S5",
    "addr:postcode":"j1n 3s5",
    "iso:country":"CA",
    "sg:city":"Rock Forest",
    "sg:classifiers":[
        {
            "category":"Health Services",
            "subcategory":"Health Practitioner",
            "type":"Services"
        }
    ],
    "sg:phone":"+1 819 820 2673",
    "sg:postcode":"J1N 3S5",
    "sg:province":"QC",
    "sg:tags":[
        "psychologist"
    ],
    "wof:name":"Racicot, Helene",
    "wof:placetype":"venue"
},
  "geometry": {"coordinates":[-71.9869308472,45.3717155457],"type":"Point"}
}