{
  "type": "Feature",
  "properties": {
    "iso:country":"CA",
    "sg:address":"750 Wharncliffe Rd S",
    "sg:city":"London",
    "sg:classifiers":[
        {
            "category":"Home & Garden",
            "subcategory":"Carpets & Floor Coverings",
            "type":"Retail Goods"
        }
    ],
    "sg:phone":"+1 519 668 0404",
    "sg:postcode":"N6J 2N4",
    "sg:province":"ON",
    "sg:tags":[
        "material",
        "rug"
    ],
    "wof:name":"End of the Roll",
    "wof:placetype":"venue"
},
  "geometry": {"coordinates":[-81.2577209473,42.9459877014],"type":"Point"}
}