{
  "type": "Feature",
  "properties": {
    "addr:full":"5940 No 6 Rd # 410 Richmond BC V6V 1Z1",
    "addr:housenumber":"410",
    "addr:postcode":"5940;v6v 1z1",
    "addr:street":"No 6 Rd #",
    "iso:country":"CA",
    "sg:address":"5940 No 6 Rd # 410",
    "sg:city":"Richmond",
    "sg:classifiers":[
        {
            "category":"Wholesale",
            "subcategory":"Stationery",
            "type":"Manufacturing & Wholesale Goods"
        }
    ],
    "sg:phone":"+1 604 273 5408",
    "sg:postcode":"V6V 1Z1",
    "sg:province":"BC",
    "sg:tags":[
        "product",
        "paper"
    ],
    "wof:name":"Tierney's Wholesale",
    "wof:placetype":"venue"
},
  "geometry": {"coordinates":[-123.068985,49.171539],"type":"Point"}
}