{
  "type": "Feature",
  "properties": {
    "iso:country":"CA",
    "sg:address":"76 First St",
    "sg:city":"Collingwood",
    "sg:classifiers":[
        {
            "category":"Autos & Motor Vehicles",
            "subcategory":"Fuel & Gas Station",
            "type":"Retail Goods"
        }
    ],
    "sg:phone":"+1 705 445 3138",
    "sg:postcode":"L9Y 1A3",
    "sg:province":"ON",
    "sg:tags":[
        "oil"
    ],
    "wof:name":"Noco Gas Bar",
    "wof:placetype":"venue"
},
  "geometry": {"coordinates":[-80.22016143800001,44.5024261475],"type":"Point"}
}