{
  "type": "Feature",
  "properties": {
    "addr:full":"517 Bathurst St London ON N6B 1P5",
    "addr:housenumber":"517",
    "addr:postcode":"n6b 1p5",
    "addr:street":"Bathurst St",
    "iso:country":"CA",
    "sg:address":"517 Bathurst St",
    "sg:city":"London",
    "sg:phone":"+1 519 432 6311",
    "sg:postcode":"N6B 1P5",
    "sg:province":"ON",
    "sg:tags":[
        "equipment",
        "supply"
    ],
    "wof:name":"Russell Food Equipment Ltd",
    "wof:placetype":"venue"
},
  "geometry": {"coordinates":[-81.23337554930001,42.9839820862],"type":"Point"}
}