{
  "type": "Feature",
  "properties": {
    "addr:full":"8961 12E Av Montreal QC H1Z 3J5",
    "addr:housenumber":"8961",
    "addr:postcode":"h1z 3j5",
    "addr:street":"12E Av",
    "iso:country":"CA",
    "sg:address":"8961 12E Av",
    "sg:city":"Montreal",
    "sg:classifiers":[
        {
            "category":"Social Services",
            "type":"Services"
        }
    ],
    "sg:phone":"+1 514 326 4766",
    "sg:postcode":"H1Z 3J5",
    "sg:province":"QC",
    "sg:tags":[
        "organization",
        "welfare"
    ],
    "wof:name":"Centre Communautaire Patience",
    "wof:placetype":"venue"
},
  "geometry": {"coordinates":[-73.625107,45.571747],"type":"Point"}
}