{
  "type": "Feature",
  "properties": {
    "iso:country":"CA",
    "sg:address":"5144 75 St NW",
    "sg:city":"Edmonton",
    "sg:classifiers":[
        {
            "category":"Manufacturing",
            "subcategory":"Tools & Machinery",
            "type":"Manufacturing & Wholesale Goods"
        }
    ],
    "sg:phone":"+1 780 466 3388",
    "sg:postcode":"T6E 6W2",
    "sg:province":"AB",
    "sg:tags":[
        "model",
        "maker"
    ],
    "wof:name":"Great Hobbies Inc",
    "wof:placetype":"venue"
},
  "geometry": {"coordinates":[-113.44291687,53.4900016785],"type":"Point"}
}