{
  "type": "Feature",
  "properties": {
    "addr:full":"1567 Steeles Ave E North York ON M2M 3Y7",
    "addr:housenumber":"1567",
    "addr:postcode":"m2m 3y7",
    "addr:street":"Steeles Ave E",
    "iso:country":"CA",
    "sg:address":"1567 Steeles Ave E",
    "sg:city":"North York",
    "sg:classifiers":[
        {
            "category":"Restaurant",
            "type":"Food & Drink"
        }
    ],
    "sg:phone":"+1 416 225 7200",
    "sg:postcode":"M2M 3Y7",
    "sg:province":"ON",
    "sg:tags":[
        "shop",
        "coffee"
    ],
    "wof:name":"Second Cup",
    "wof:placetype":"venue"
},
  "geometry": {"coordinates":[-79.383698,43.805885],"type":"Point"}
}