{
  "type": "Feature",
  "properties": {
    "iso:country":"CA",
    "sg:address":"39 Crosby Ave # 101",
    "sg:city":"Richmond Hill",
    "sg:classifiers":[
        {
            "category":"Social Services",
            "type":"Services"
        }
    ],
    "sg:phone":"+1 905 770 1989",
    "sg:postcode":"L4C 0B1",
    "sg:province":"ON",
    "sg:tags":[
        "housing",
        "assistance"
    ],
    "wof:name":"Genesis Place",
    "wof:placetype":"venue"
},
  "geometry": {"coordinates":[-79.437538147,43.880607605],"type":"Point"}
}