{
  "type": "Feature",
  "properties": {
    "addr:full":"730 Concession St Hamilton ON L8V 1C1",
    "addr:housenumber":"730",
    "addr:postcode":"l8v 1c1",
    "addr:street":"Concession St",
    "iso:country":"CA",
    "sg:address":"730 Concession St",
    "sg:city":"Hamilton",
    "sg:classifiers":[
        {
            "category":"Health Services",
            "subcategory":"Doctor",
            "type":"Services"
        }
    ],
    "sg:phone":"+1 905 387 5543",
    "sg:postcode":"L8V 1C1",
    "sg:province":"ON",
    "sg:tags":[
        "physician",
        "surgeon"
    ],
    "wof:name":"Puksa, Serge MD",
    "wof:placetype":"venue"
},
  "geometry": {"coordinates":[-79.844833374,43.2389984131],"type":"Point"}
}