{
  "type": "Feature",
  "properties": {
    "iso:country":"CA",
    "sg:address":"2 Millwick Dr",
    "sg:city":"North York",
    "sg:phone":"+1 416 740 0999",
    "sg:postcode":"M9L 1Y3",
    "sg:province":"ON",
    "sg:tags":[
        "shelving"
    ],
    "wof:name":"Econo Storage Solutions Inc",
    "wof:placetype":"venue"
},
  "geometry": {"coordinates":[-79.55969238279999,43.7563896179],"type":"Point"}
}