{
  "type": "Feature",
  "properties": {
    "addr:full":"Etobicoke ON M9W 6J9",
    "addr:postcode":"m9w 6j9",
    "iso:country":"CA",
    "sg:city":"Etobicoke",
    "sg:classifiers":[
        {
            "category":"Restaurant",
            "type":"Food & Drink"
        }
    ],
    "sg:phone":"+1 416 674 0036",
    "sg:postcode":"M9W 6J9",
    "sg:province":"ON",
    "sg:tags":[
        "caterer",
        "rooms",
        "banquet"
    ],
    "wof:name":"Elite Banquet Halls",
    "wof:placetype":"venue"
},
  "geometry": {"coordinates":[-79.61657700000001,43.746059],"type":"Point"}
}