{
  "type": "Feature",
  "properties": {
    "addr:full":"857 Boul DE LA Montagne Saint-Casimir QC G0A 3L0",
    "addr:housenumber":"857",
    "addr:postcode":"g0a 3l0",
    "addr:street":"Boul De La Montagne",
    "iso:country":"CA",
    "sg:address":"857 Boul DE LA Montagne",
    "sg:city":"Saint-Casimir",
    "sg:classifiers":[
        {
            "category":"Retail",
            "subcategory":"Auto Repair",
            "type":"Services"
        }
    ],
    "sg:phone":"+1 418 339 3133",
    "sg:postcode":"G0A 3L0",
    "sg:province":"QC",
    "sg:tags":[
        "repairing",
        "automobile"
    ],
    "wof:name":"Garage Ghislain Tessier",
    "wof:placetype":"venue"
},
  "geometry": {"coordinates":[-72.16628300000001,46.666588],"type":"Point"}
}