{
  "type": "Feature",
  "properties": {
    "addr:full":"65 Howard Pl Kitchener ON N2K 2Z4",
    "addr:housenumber":"65",
    "addr:postcode":"n2k 2z4",
    "addr:street":"Howard Pl",
    "iso:country":"CA",
    "sg:address":"65 Howard Pl",
    "sg:city":"Kitchener",
    "sg:classifiers":[
        {
            "category":"Manufacturing",
            "subcategory":"Paper Products",
            "type":"Manufacturing & Wholesale Goods"
        }
    ],
    "sg:phone":"+1 519 578 8250",
    "sg:postcode":"N2K 2Z4",
    "sg:province":"ON",
    "sg:tags":[
        "box"
    ],
    "wof:name":"Schumacher Industries Ltd",
    "wof:placetype":"venue"
},
  "geometry": {"coordinates":[-80.464157,43.478973],"type":"Point"}
}