{
  "type": "Feature",
  "properties": {
    "addr:full":"686 Dundas St Woodstock ON N4S 1E6",
    "addr:housenumber":"686",
    "addr:postcode":"n4s 1e6",
    "addr:street":"Dundas St",
    "iso:country":"CA",
    "sg:address":"686 Dundas St",
    "sg:city":"Woodstock",
    "sg:classifiers":[
        {
            "category":"Shopping",
            "subcategory":"Clothing, Apparel, & Fashions",
            "type":"Retail Goods"
        }
    ],
    "sg:phone":"+1 519 421 2088",
    "sg:postcode":"N4S 1E6",
    "sg:province":"ON",
    "sg:tags":[
        "tailor"
    ],
    "wof:name":"V I P's",
    "wof:placetype":"venue"
},
  "geometry": {"coordinates":[-80.7478103638,43.1312561035],"type":"Point"}
}