{
  "type": "Feature",
  "properties": {
    "addr:full":"3102 30 Ave Vernon BC V1T 2C2",
    "addr:housenumber":"3102",
    "addr:postcode":"v1t 2c2",
    "addr:street":"30 Ave",
    "iso:country":"CA",
    "sg:address":"3102 30 Ave",
    "sg:city":"Vernon",
    "sg:classifiers":[
        {
            "category":"Restaurant",
            "type":"Food & Drink"
        }
    ],
    "sg:phone":"+1 250 503 2322",
    "sg:postcode":"V1T 2C2",
    "sg:province":"BC",
    "wof:name":"Queen's Garden Restaurant",
    "wof:placetype":"venue"
},
  "geometry": {"coordinates":[-119.27243,50.26366],"type":"Point"}
}