{
  "type": "Feature",
  "properties": {
    "addr:full":"22540 Dewdney Trunk Rd Maple Ridge BC V2X 3J9",
    "addr:housenumber":"22540",
    "addr:postcode":"v2x 3j9",
    "addr:street":"Dewdney Trunk Rd",
    "iso:country":"CA",
    "sg:address":"22540 Dewdney Trunk Rd",
    "sg:city":"Maple Ridge",
    "sg:classifiers":[
        {
            "category":"Shopping",
            "subcategory":"Optical Goods",
            "type":"Retail Goods"
        }
    ],
    "sg:phone":"+1 604 466 3937",
    "sg:postcode":"V2X 3J9",
    "sg:province":"BC",
    "sg:tags":[
        "hearing",
        "equipment",
        "supply",
        "optician",
        "impaired"
    ],
    "wof:name":"Crystal Vision One Hour Optcl",
    "wof:placetype":"venue"
},
  "geometry": {"coordinates":[-122.597244,49.220367],"type":"Point"}
}