{
  "type": "Feature",
  "properties": {
    "iso:country":"CA",
    "sg:address":"1626 6E Rue",
    "sg:city":"Trois-Rivieres",
    "sg:classifiers":[
        {
            "category":"Shopping",
            "subcategory":"Luggage & Leather Goods",
            "type":"Retail Goods"
        }
    ],
    "sg:phone":"+1 819 379 0488",
    "sg:postcode":"G8Y 5B8",
    "sg:province":"QC",
    "sg:tags":[
        "apparel"
    ],
    "wof:name":"Stock",
    "wof:placetype":"venue"
},
  "geometry": {"coordinates":[-72.5553283691,46.3517799377],"type":"Point"}
}