{
  "type": "Feature",
  "properties": {
    "addr:full":"Laval QC H7V 3Y4",
    "addr:postcode":"h7v 3y4",
    "iso:country":"CA",
    "sg:city":"Laval",
    "sg:classifiers":[
        {
            "category":"Building & Trades",
            "subcategory":"Construction",
            "type":"Services"
        }
    ],
    "sg:phone":"+1 450 682 1446",
    "sg:postcode":"H7V 3Y4",
    "sg:province":"QC",
    "sg:tags":[
        "general",
        "contractor"
    ],
    "wof:name":"Dargis Groupe",
    "wof:placetype":"venue"
},
  "geometry": {"coordinates":[-73.740273,45.545113],"type":"Point"}
}