{
  "type": "Feature",
  "properties": {
    "addr:full":"64 Cannon St E Hamilton ON L8L 1Z9",
    "addr:housenumber":"64",
    "addr:postcode":"l8l 1z9",
    "addr:street":"Cannon St E",
    "iso:country":"CA",
    "sg:address":"64 Cannon St E",
    "sg:city":"Hamilton",
    "sg:classifiers":[
        {
            "category":"Autos & Motor Vehicles",
            "subcategory":"Automobile Sales",
            "type":"Retail Goods"
        }
    ],
    "sg:phone":"+1 905 525 2795",
    "sg:postcode":"L8L 1Z9",
    "sg:province":"ON",
    "sg:tags":[
        "car",
        "dealer"
    ],
    "wof:name":"Trust Autosale",
    "wof:placetype":"venue"
},
  "geometry": {"coordinates":[-79.8643951416,43.2599143982],"type":"Point"}
}