{
  "type": "Feature",
  "properties": {
    "addr:full":"4700 Orange Point Rd Campbell River BC V9W 6Y4",
    "addr:housenumber":"4700",
    "addr:postcode":"v9w 6y4",
    "addr:street":"Orange Point Rd",
    "iso:country":"CA",
    "sg:address":"4700 Orange Point Rd",
    "sg:city":"Campbell River",
    "sg:classifiers":[
        {
            "category":"Mining & Drilling",
            "type":"Manufacturing & Wholesale Goods"
        }
    ],
    "sg:phone":"+1 250 286 1136",
    "sg:postcode":"V9W 6Y4",
    "sg:province":"BC",
    "sg:tags":[
        "company",
        "oil"
    ],
    "wof:name":"Chevron Canada Ltd",
    "wof:placetype":"venue"
},
  "geometry": {"coordinates":[-125.27658099999999,50.069492],"type":"Point"}
}