{
  "type": "Feature",
  "properties": {
    "iso:country":"CA",
    "sg:address":"3853 Royston Rd",
    "sg:city":"Royston",
    "sg:classifiers":[
        {
            "category":"Retail",
            "subcategory":"Repair Shop",
            "type":"Services"
        }
    ],
    "sg:phone":"+1 250 338 5883",
    "sg:postcode":"V0R 2V0",
    "sg:province":"BC",
    "sg:tags":[
        "equipment",
        "video"
    ],
    "wof:name":"Royston Electronics",
    "wof:placetype":"venue"
},
  "geometry": {"coordinates":[-124.948441,49.642933],"type":"Point"}
}