{
  "type": "Feature",
  "properties": {
    "addr:full":"849 Westport Cres Mississauga ON L5T 1E7",
    "addr:housenumber":"849",
    "addr:postcode":"l5t 1e7",
    "addr:street":"Westport Cres",
    "iso:country":"CA",
    "sg:address":"849 Westport Cres",
    "sg:city":"Mississauga",
    "sg:classifiers":[
        {
            "category":"Retail",
            "subcategory":"Auto Repair",
            "type":"Services"
        }
    ],
    "sg:phone":"+1 905 696 8228",
    "sg:postcode":"L5T 1E7",
    "sg:province":"ON",
    "sg:tags":[
        "repairing",
        "automobile",
        "body"
    ],
    "wof:name":"Care Auto Repairs",
    "wof:placetype":"venue"
},
  "geometry": {"coordinates":[-79.65625799999999,43.649975],"type":"Point"}
}