{
  "type": "Feature",
  "properties": {
    "addr:full":"211 Consumers Rd North York ON M2J 4G8",
    "addr:housenumber":"211",
    "addr:postcode":"m2j 4g8",
    "addr:street":"Consumers Rd",
    "iso:country":"CA",
    "sg:address":"211 Consumers Rd",
    "sg:city":"North York",
    "sg:classifiers":[
        {
            "category":"Real Estate",
            "subcategory":"Real Estate Agent",
            "type":"Services"
        }
    ],
    "sg:phone":"+1 416 494 8777",
    "sg:postcode":"M2J 4G8",
    "sg:province":"ON",
    "wof:name":"Royal Crest Realty",
    "wof:placetype":"venue"
},
  "geometry": {"coordinates":[-79.331924,43.772156],"type":"Point"}
}