{
  "type": "Feature",
  "properties": {
    "addr:full":"Winnipeg MB R3T 2G2",
    "addr:postcode":"r3t 2g2",
    "iso:country":"CA",
    "sg:city":"Winnipeg",
    "sg:classifiers":[
        {
            "category":"Manufacturing",
            "subcategory":"Tools & Machinery",
            "type":"Manufacturing & Wholesale Goods"
        }
    ],
    "sg:phone":"+1 204 254 4016",
    "sg:postcode":"R3T 2G2",
    "sg:province":"MB",
    "sg:tags":[
        "laboratory",
        "optical"
    ],
    "wof:name":"Lenspro Limited",
    "wof:placetype":"venue"
},
  "geometry": {"coordinates":[-97.15116119379999,49.8302268982],"type":"Point"}
}