{
  "type": "Feature",
  "properties": {
    "addr:full":"223 Rue Saint-Marcel Drummondville QC J2B 2E3",
    "addr:housenumber":"223",
    "addr:postcode":"j2b 2e3",
    "addr:street":"Rue Saint-Marcel",
    "iso:country":"CA",
    "sg:address":"223 Rue Saint-Marcel",
    "sg:city":"Drummondville",
    "sg:classifiers":[
        {
            "category":"Health Services",
            "subcategory":"Doctor",
            "type":"Services"
        }
    ],
    "sg:phone":"+1 819 477 2344",
    "sg:postcode":"J2B 2E3",
    "sg:province":"QC",
    "sg:tags":[
        "physician",
        "surgeon"
    ],
    "wof:name":"Soucy, Francois MD",
    "wof:placetype":"venue"
},
  "geometry": {"coordinates":[-72.48687700000001,45.874313],"type":"Point"}
}