{
  "type": "Feature",
  "properties": {
    "iso:country":"CA",
    "sg:address":"15534 95 Ave",
    "sg:city":"Surrey",
    "sg:classifiers":[
        {
            "category":"Retail",
            "subcategory":"Repair Shop",
            "type":"Services"
        }
    ],
    "sg:phone":"+1 604 802 2994",
    "sg:postcode":"V3R 8T9",
    "sg:province":"BC",
    "sg:tags":[
        "repairing",
        "piano",
        "refinishing"
    ],
    "wof:name":"Crescendo Piano Svc",
    "wof:placetype":"venue"
},
  "geometry": {"coordinates":[-122.79212188699999,49.1747093201],"type":"Point"}
}