{
  "type": "Feature",
  "properties": {
    "addr:full":"195 3 St W Drumheller AB T0J 0Y4",
    "addr:housenumber":"195 3",
    "addr:postcode":"t0j 0y4",
    "addr:street":"St W",
    "iso:country":"CA",
    "sg:address":"195 3 St W",
    "sg:city":"Drumheller",
    "sg:classifiers":[
        {
            "category":"Organizations",
            "subcategory":"Religious Organization",
            "type":"Services"
        }
    ],
    "sg:phone":"+1 403 823 2366",
    "sg:postcode":"T0J 0Y4",
    "sg:province":"AB",
    "sg:tags":[
        "church"
    ],
    "wof:name":"Knox United Church",
    "wof:placetype":"venue"
},
  "geometry": {"coordinates":[-112.712502,51.46553],"type":"Point"}
}