{
  "type": "Feature",
  "properties": {
    "iso:country":"CA",
    "sg:address":"539 Ben Jackson Rd",
    "sg:city":"Hantsport",
    "sg:classifiers":[
        {
            "category":"Professional",
            "subcategory":"Accounting & Tax Preparation",
            "type":"Services"
        }
    ],
    "sg:phone":"+1 902 684 0022",
    "sg:postcode":"B0P 1P0",
    "sg:province":"NS",
    "sg:tags":[
        "payroll"
    ],
    "wof:name":"J M Bookkeeping & Taxation",
    "wof:placetype":"venue"
},
  "geometry": {"coordinates":[-64.18389129640001,45.0649223328],"type":"Point"}
}