{
  "type": "Feature",
  "properties": {
    "addr:full":"3367 Lake Shore Blvd W Etobicoke ON M8W 1N1",
    "addr:housenumber":"3367",
    "addr:postcode":"m8w 1n1",
    "addr:street":"Lake Shore Blvd W",
    "iso:country":"CA",
    "sg:address":"3367 Lake Shore Blvd W",
    "sg:city":"Etobicoke",
    "sg:classifiers":[
        {
            "category":"Home & Garden",
            "subcategory":"Carpets & Floor Coverings",
            "type":"Retail Goods"
        }
    ],
    "sg:phone":"+1 416 251 6601",
    "sg:postcode":"M8W 1N1",
    "sg:province":"ON",
    "sg:tags":[
        "material",
        "rug"
    ],
    "wof:name":"Peacock Carpet & Tile Ltd",
    "wof:placetype":"venue"
},
  "geometry": {"coordinates":[-79.526726,43.595879],"type":"Point"}
}