{
  "type": "Feature",
  "properties": {
    "iso:country":"CA",
    "sg:address":"3750 Lawrence Ave E",
    "sg:city":"Scarborough",
    "sg:classifiers":[
        {
            "category":"Food & Beverages",
            "subcategory":"Groceries & Convenience Stores",
            "type":"Retail Goods"
        }
    ],
    "sg:phone":"+1 416 439 2500",
    "sg:postcode":"M1G 1R1",
    "sg:province":"ON",
    "sg:tags":[
        "grocer"
    ],
    "wof:name":"Iga",
    "wof:placetype":"venue"
},
  "geometry": {"coordinates":[-79.2153015137,43.7621002197],"type":"Point"}
}