{
  "type": "Feature",
  "properties": {
    "iso:country":"CA",
    "sg:city":"Brossard",
    "sg:classifiers":[
        {
            "category":"Education",
            "subcategory":"School",
            "type":"Public Place"
        }
    ],
    "sg:phone":"+1 450 676 1745",
    "sg:postcode":"J4Z 3P5",
    "sg:province":"QC",
    "wof:name":"Cegep St-Jean-Richelieu",
    "wof:placetype":"venue"
},
  "geometry": {"coordinates":[-73.4644851685,45.4679641724],"type":"Point"}
}