{
  "type": "Feature",
  "properties": {
    "addr:full":"2505 Rte Kennedy E Notre-Dame-Des-Pins QC G0M 1K0",
    "addr:housenumber":"2505",
    "addr:postcode":"g0m 1k0",
    "addr:street":"Rte Kennedy E Notre-Dame-Des-Pins",
    "iso:country":"CA",
    "sg:address":"2505 Rte Kennedy E",
    "sg:city":"Notre-Dame-Des-Pins",
    "sg:classifiers":[
        {
            "category":"Shopping",
            "subcategory":"Used Merchandise",
            "type":"Retail Goods"
        }
    ],
    "sg:phone":"+1 418 774 4441",
    "sg:postcode":"G0M 1K0",
    "sg:province":"QC",
    "sg:tags":[
        "flea",
        "market"
    ],
    "wof:name":"Marche Aux Puces Regional Enr",
    "wof:placetype":"venue"
},
  "geometry": {"coordinates":[-70.71086099999999,46.189419],"type":"Point"}
}