{
  "type": "Feature",
  "properties": {
    "addr:full":"6298 Main St Stouffville ON L4A 1G8",
    "addr:housenumber":"6298",
    "addr:postcode":"l4a 1g8",
    "addr:street":"Main St",
    "iso:country":"CA",
    "sg:address":"6298 Main St",
    "sg:city":"Stouffville",
    "sg:classifiers":[
        {
            "category":"Restaurant",
            "type":"Food & Drink"
        }
    ],
    "sg:phone":"+1 905 642 2122",
    "sg:postcode":"L4A 1G8",
    "sg:province":"ON",
    "wof:name":"Emerald Isle",
    "wof:placetype":"venue"
},
  "geometry": {"coordinates":[-79.2461013794,43.9715995789],"type":"Point"}
}