{
  "type": "Feature",
  "properties": {
    "addr:full":"9439 131A St Surrey BC V3V 6Z4",
    "addr:housenumber":"9439",
    "addr:postcode":"v3v 6z4",
    "addr:street":"131A St",
    "iso:country":"CA",
    "sg:address":"9439 131A St",
    "sg:city":"Surrey",
    "sg:classifiers":[
        {
            "category":"Home & Garden",
            "subcategory":"Building Materials",
            "type":"Retail Goods"
        }
    ],
    "sg:phone":"+1 604 930 6144",
    "sg:postcode":"V3V 6Z4",
    "sg:province":"BC",
    "sg:tags":[
        "windows"
    ],
    "wof:name":"Kensington",
    "wof:placetype":"venue"
},
  "geometry": {"coordinates":[-122.830215,49.105179],"type":"Point"}
}