{
  "type": "Feature",
  "properties": {
    "addr:full":"Richmond BC V6V 2R3",
    "addr:postcode":"v6v 2r3",
    "iso:country":"CA",
    "sg:city":"Richmond",
    "sg:classifiers":[
        {
            "category":"Wholesale",
            "subcategory":"Electrical",
            "type":"Manufacturing & Wholesale Goods"
        }
    ],
    "sg:phone":"+1 604 233 1868",
    "sg:postcode":"V6V 2R3",
    "sg:province":"BC",
    "sg:tags":[
        "equipment",
        "electronic",
        "supply"
    ],
    "wof:name":"Rich-Tech Electronic Component",
    "wof:placetype":"venue"
},
  "geometry": {"coordinates":[-123.080528,49.187687],"type":"Point"}
}