{
  "type": "Feature",
  "properties": {
    "iso:country":"CA",
    "sg:address":"124 Bridge Rd",
    "sg:city":"Miramichi",
    "sg:classifiers":[
        {
            "category":"Home & Garden",
            "subcategory":"Building Materials",
            "type":"Retail Goods"
        }
    ],
    "sg:phone":"+1 506 622 3820",
    "sg:postcode":"E1V 3H8",
    "sg:province":"NB",
    "sg:tags":[
        "lumber"
    ],
    "wof:name":"Beaver Lumber",
    "wof:placetype":"venue"
},
  "geometry": {"coordinates":[-65.55099487299999,46.996963501],"type":"Point"}
}