{
  "type": "Feature",
  "properties": {
    "addr:full":"4773 Piccadilly S West Vancouver BC V7W 1J8",
    "addr:housenumber":"4773",
    "addr:postcode":"v7w 1j8",
    "addr:street":"Piccadilly;West",
    "iso:country":"CA",
    "sg:address":"4773 Piccadilly S",
    "sg:city":"West Vancouver",
    "sg:classifiers":[
        {
            "category":"Organizations",
            "subcategory":"Religious Organization",
            "type":"Services"
        }
    ],
    "sg:phone":"+1 604 922 3531",
    "sg:postcode":"V7W 1J8",
    "sg:province":"BC",
    "sg:tags":[
        "church"
    ],
    "wof:name":"St Francis in the Wood",
    "wof:placetype":"venue"
},
  "geometry": {"coordinates":[-123.254791,49.339256],"type":"Point"}
}