{
  "type": "Feature",
  "properties": {
    "addr:full":"810 Boul Industriel Granby QC J2J 1A4",
    "addr:housenumber":"810",
    "addr:postcode":"j2j 1a4",
    "addr:street":"Boul Industriel",
    "iso:country":"CA",
    "sg:address":"810 Boul Industriel",
    "sg:city":"Granby",
    "sg:classifiers":[
        {
            "category":"Building & Trades",
            "subcategory":"Plumbing",
            "type":"Services"
        }
    ],
    "sg:phone":"+1 450 375 3429",
    "sg:postcode":"J2J 1A4",
    "sg:province":"QC",
    "sg:tags":[
        "conditioning",
        "air",
        "system",
        "contractor"
    ],
    "wof:name":"Refri Ozone Inc",
    "wof:placetype":"venue"
},
  "geometry": {"coordinates":[-72.759789,45.389305],"type":"Point"}
}