{
  "type": "Feature",
  "properties": {
    "iso:country":"CA",
    "sg:address":"16740 121 Ave NW",
    "sg:city":"Edmonton",
    "sg:classifiers":[
        {
            "category":"Retail",
            "subcategory":"Auto Repair",
            "type":"Services"
        }
    ],
    "sg:phone":"+1 780 484 4492",
    "sg:postcode":"T5V 1P6",
    "sg:province":"AB",
    "sg:tags":[
        "truck"
    ],
    "wof:name":"Edmonton Fleet Maintenance",
    "wof:placetype":"venue"
},
  "geometry": {"coordinates":[-113.60992400000001,53.572956],"type":"Point"}
}