{
  "type": "Feature",
  "properties": {
    "addr:full":"Erin ON N0B 1T0",
    "addr:postcode":"n0b 1t0",
    "iso:country":"CA",
    "sg:city":"Erin",
    "sg:classifiers":[
        {
            "category":"Manufacturing",
            "subcategory":"Printing",
            "type":"Manufacturing & Wholesale Goods"
        }
    ],
    "sg:phone":"+1 519 833 9603",
    "sg:postcode":"N0B 1T0",
    "sg:province":"ON",
    "sg:tags":[
        "newspaper"
    ],
    "wof:name":"Erin Advocate",
    "wof:placetype":"venue"
},
  "geometry": {"coordinates":[-80.07666778559999,43.7815246582],"type":"Point"}
}