{
  "type": "Feature",
  "properties": {
    "addr:full":"633 Rue DE Courcelle Montreal QC H4C 3C7",
    "addr:housenumber":"633",
    "addr:postcode":"h4c 3c7",
    "addr:street":"Rue De Courcelle",
    "iso:country":"CA",
    "sg:address":"633 Rue DE Courcelle",
    "sg:city":"Montreal",
    "sg:classifiers":[
        {
            "category":"Education",
            "subcategory":"School",
            "type":"Public Place"
        }
    ],
    "sg:phone":"+1 514 596 5670",
    "sg:postcode":"H4C 3C7",
    "sg:province":"QC",
    "wof:name":"Charlevoix Annexe DE Ludger",
    "wof:placetype":"venue"
},
  "geometry": {"coordinates":[-73.591042,45.473969],"type":"Point"}
}