{
  "type": "Feature",
  "properties": {
    "addr:full":"2825 Sheffield Rd Ottawa ON K1B 3V8",
    "addr:housenumber":"2825",
    "addr:postcode":"k1b 3v8",
    "addr:street":"Sheffield Rd",
    "iso:country":"CA",
    "sg:address":"2825 Sheffield Rd",
    "sg:city":"Ottawa",
    "sg:classifiers":[
        {
            "category":"Wholesale",
            "subcategory":"Vending Machines",
            "type":"Manufacturing & Wholesale Goods"
        }
    ],
    "sg:phone":"+1 613 742 5891",
    "sg:postcode":"K1B 3V8",
    "sg:province":"ON",
    "wof:name":"Five Star Vending",
    "wof:placetype":"venue"
},
  "geometry": {"coordinates":[-75.60144042970001,45.3975105286],"type":"Point"}
}