{
  "type": "Feature",
  "properties": {
    "addr:full":"NE 11 12 5 E Dugald MB R0E 0K0",
    "addr:housenumber":"12 5 e",
    "addr:postcode":"r0e 0k0",
    "addr:street":"Ne 11;Dugald",
    "iso:country":"CA",
    "sg:address":"NE 11 12 5 E",
    "sg:city":"Dugald",
    "sg:classifiers":[
        {
            "category":"Wholesale",
            "subcategory":"Machinery & Supplies",
            "type":"Manufacturing & Wholesale Goods"
        }
    ],
    "sg:phone":"+1 204 444 3931",
    "sg:postcode":"R0E 0K0",
    "sg:province":"MB",
    "sg:tags":[
        "equipment",
        "hydraulic"
    ],
    "wof:name":"A S Repair Sales & Svc",
    "wof:placetype":"venue"
},
  "geometry": {"coordinates":[-96.8401184082,49.8859062195],"type":"Point"}
}