{
  "type": "Feature",
  "properties": {
    "addr:full":"124 Main St Toronto ON M4E 2V8",
    "addr:housenumber":"124",
    "addr:postcode":"m4e 2v8",
    "addr:street":"Main St",
    "iso:country":"CA",
    "sg:address":"124 Main St",
    "sg:city":"Toronto",
    "sg:classifiers":[
        {
            "category":"Health Services",
            "subcategory":"Doctor",
            "type":"Services"
        }
    ],
    "sg:phone":"+1 416 699 0620",
    "sg:postcode":"M4E 2V8",
    "sg:province":"ON",
    "sg:tags":[
        "dentist"
    ],
    "wof:name":"Teodoro Tsang & Assoc",
    "wof:placetype":"venue"
},
  "geometry": {"coordinates":[-79.299919,43.682812],"type":"Point"}
}