{
  "type": "Feature",
  "properties": {
    "addr:full":"9420 100 St Peace River AB T8S 1H7",
    "addr:housenumber":"9420",
    "addr:postcode":"t8s 1h7",
    "addr:street":"100 St",
    "iso:country":"CA",
    "sg:address":"9420 100 St",
    "sg:city":"Peace River",
    "sg:classifiers":[
        {
            "category":"Retail",
            "subcategory":"Auto Repair",
            "type":"Services"
        }
    ],
    "sg:phone":"+1 780 624 8622",
    "sg:postcode":"T8S 1H7",
    "sg:province":"AB",
    "sg:tags":[
        "repairing",
        "automobile"
    ],
    "wof:name":"Tech One Mechanical Repair Ltd",
    "wof:placetype":"venue"
},
  "geometry": {"coordinates":[-117.291794,56.23848],"type":"Point"}
}