{
  "type": "Feature",
  "properties": {
    "addr:full":"620 Fourth Line Oakville ON L6L 5B2",
    "addr:housenumber":"620",
    "addr:postcode":"l6l 5b2",
    "addr:street":"Fourth Line",
    "iso:country":"CA",
    "sg:address":"620 Fourth Line",
    "sg:city":"Oakville",
    "sg:classifiers":[
        {
            "category":"Building & Trades",
            "subcategory":"Construction",
            "type":"Services"
        }
    ],
    "sg:phone":"+1 905 845 1114",
    "sg:postcode":"L6L 5B2",
    "sg:province":"ON",
    "sg:tags":[
        "roofing",
        "contractor"
    ],
    "wof:name":"Cherry & Hoyle Roofing Ltd",
    "wof:placetype":"venue"
},
  "geometry": {"coordinates":[-79.701431,43.432858],"type":"Point"}
}