{
  "type": "Feature",
  "properties": {
    "addr:full":"148 Broughton Ave Hamilton ON L8W 3S7",
    "addr:housenumber":"148",
    "addr:postcode":"l8w 3s7",
    "addr:street":"Broughton Ave",
    "iso:country":"CA",
    "sg:address":"148 Broughton Ave",
    "sg:city":"Hamilton",
    "sg:classifiers":[
        {
            "category":"Building & Trades",
            "subcategory":"Construction",
            "type":"Services"
        }
    ],
    "sg:phone":"+1 905 388 9099",
    "sg:postcode":"L8W 3S7",
    "sg:province":"ON",
    "sg:tags":[
        "painter"
    ],
    "wof:name":"Fine Line Painting & Decor",
    "wof:placetype":"venue"
},
  "geometry": {"coordinates":[-79.8536453247,43.1885795593],"type":"Point"}
}