{
  "type": "Feature",
  "properties": {
    "iso:country":"CA",
    "sg:address":"100 Bell St",
    "sg:city":"Faro",
    "sg:classifiers":[
        {
            "category":"Education",
            "subcategory":"School",
            "type":"Public Place"
        }
    ],
    "sg:phone":"+1 867 994 2760",
    "sg:postcode":"Y0B 1K0",
    "sg:province":"YT",
    "wof:name":"Del Van Gorder School",
    "wof:placetype":"venue"
},
  "geometry": {"coordinates":[-133.354812622,62.2291564941],"type":"Point"}
}