{
  "type": "Feature",
  "properties": {
    "addr:full":"1250 Rue Maisonneuve Magog QC J1X 2N9",
    "addr:housenumber":"1250",
    "addr:postcode":"j1x 2n9",
    "addr:street":"Rue Maisonneuve",
    "iso:country":"CA",
    "sg:address":"1250 Rue Maisonneuve",
    "sg:city":"Magog",
    "sg:classifiers":[
        {
            "category":"Professional",
            "subcategory":"Advertising",
            "type":"Services"
        }
    ],
    "sg:phone":"+1 819 847 3613",
    "sg:postcode":"J1X 2N9",
    "sg:province":"QC",
    "wof:name":"Promotions Db",
    "wof:placetype":"venue"
},
  "geometry": {"coordinates":[-72.137108,45.274853],"type":"Point"}
}