{
  "type": "Feature",
  "properties": {
    "addr:full":"Kelowna BC V1X 7L4",
    "addr:postcode":"v1x 7l4",
    "iso:country":"CA",
    "sg:city":"Kelowna",
    "sg:classifiers":[
        {
            "category":"Building & Trades",
            "subcategory":"Plumbing",
            "type":"Services"
        }
    ],
    "sg:phone":"+1 250 491 4600",
    "sg:postcode":"V1X 7L4",
    "sg:province":"BC",
    "sg:tags":[
        "conditioning",
        "air",
        "system",
        "contractor"
    ],
    "wof:name":"Trane British Columbia",
    "wof:placetype":"venue"
},
  "geometry": {"coordinates":[-119.384094238,49.9225845337],"type":"Point"}
}