{
  "type": "Feature",
  "properties": {
    "addr:full":"706 Pacific Ave Carnduff SK S0C 0S0",
    "addr:housenumber":"706",
    "addr:postcode":"s0c 0s0",
    "addr:street":"Pacific Ave",
    "iso:country":"CA",
    "sg:address":"706 Pacific Ave",
    "sg:city":"Carnduff",
    "sg:classifiers":[
        {
            "category":"Organizations",
            "subcategory":"Religious Organization",
            "type":"Services"
        }
    ],
    "sg:phone":"+1 306 482 3932",
    "sg:postcode":"S0C 0S0",
    "sg:province":"SK",
    "sg:tags":[
        "church"
    ],
    "wof:name":"United Church",
    "wof:placetype":"venue"
},
  "geometry": {"coordinates":[-101.799049377,49.1772232056],"type":"Point"}
}