{
  "type": "Feature",
  "properties": {
    "addr:full":"2301 Highway 311 Truro NS B2N 5B4",
    "addr:housenumber":"2301",
    "addr:postcode":"b2n 5b4",
    "addr:street":"Highway 311",
    "iso:country":"CA",
    "sg:address":"2301 Highway 311",
    "sg:city":"Truro",
    "sg:classifiers":[
        {
            "category":"Building & Trades",
            "subcategory":"Construction",
            "type":"Services"
        }
    ],
    "sg:phone":"+1 902 896 0045",
    "sg:postcode":"B2N 5B4",
    "sg:province":"NS",
    "sg:tags":[
        "excavating",
        "contractor"
    ],
    "wof:name":"All-Ways Excavation",
    "wof:placetype":"venue"
},
  "geometry": {"coordinates":[-63.2890396118,45.3660202026],"type":"Point"}
}