{
  "type": "Feature",
  "properties": {
    "addr:full":"6013 Yonge St North York ON M2M 3W2",
    "addr:housenumber":"6013",
    "addr:postcode":"m2m 3w2",
    "addr:street":"Yonge St",
    "iso:country":"CA",
    "sg:address":"6013 Yonge St",
    "sg:city":"North York",
    "sg:classifiers":[
        {
            "category":"Professional",
            "subcategory":"Accounting & Tax Preparation",
            "type":"Services"
        }
    ],
    "sg:phone":"+1 416 227 2300",
    "sg:postcode":"M2M 3W2",
    "sg:province":"ON",
    "sg:tags":[
        "bookkeeping",
        "general"
    ],
    "wof:name":"Razdar Accounting",
    "wof:placetype":"venue"
},
  "geometry": {"coordinates":[-79.417671,43.789196],"type":"Point"}
}