{
  "type": "Feature",
  "properties": {
    "addr:full":"7904 Yellowhead Trail NW Edmonton AB T5B 1G3",
    "addr:housenumber":"7904",
    "addr:postcode":"t5b 1g3",
    "addr:street":"Yellowhead Trail Nw",
    "iso:country":"CA",
    "sg:address":"7904 Yellowhead Trail NW",
    "sg:city":"Edmonton",
    "sg:classifiers":[
        {
            "category":"Freight",
            "type":"Transportation"
        }
    ],
    "sg:phone":"+1 780 474 7081",
    "sg:postcode":"T5B 1G3",
    "sg:province":"AB",
    "sg:tags":[
        "trucking"
    ],
    "wof:name":"H Hirsch Trucking",
    "wof:placetype":"venue"
},
  "geometry": {"coordinates":[-113.462311,53.582748],"type":"Point"}
}