{
  "type": "Feature",
  "properties": {
    "addr:full":"300 Sydney St S Kitchener ON N2G 3W1",
    "addr:housenumber":"300",
    "addr:postcode":"n2g 3w1",
    "addr:street":"Sydney St S",
    "iso:country":"CA",
    "sg:address":"300 Sydney St S",
    "sg:city":"Kitchener",
    "sg:classifiers":[
        {
            "category":"Building & Trades",
            "subcategory":"Pest Control",
            "type":"Services"
        }
    ],
    "sg:phone":"+1 519 576 6592",
    "sg:postcode":"N2G 3W1",
    "sg:province":"ON",
    "wof:name":"Safeway Pest Control Inc",
    "wof:placetype":"venue"
},
  "geometry": {"coordinates":[-80.475967,43.434753],"type":"Point"}
}