{
  "type": "Feature",
  "properties": {
    "addr:full":"Saint-Jean-DE-Matha QC J0K 2S0",
    "addr:postcode":"j0k 2s0",
    "iso:country":"CA",
    "sg:city":"Saint-Jean-DE-Matha",
    "sg:classifiers":[
        {
            "category":"Home & Garden",
            "subcategory":"Hardware",
            "type":"Retail Goods"
        }
    ],
    "sg:phone":"+1 450 886 2741",
    "sg:postcode":"J0K 2S0",
    "sg:province":"QC",
    "wof:name":"Luc Ducharme Ctr-Renovation",
    "wof:placetype":"venue"
},
  "geometry": {"coordinates":[-73.529968,46.235798],"type":"Point"}
}