{
  "type": "Feature",
  "properties": {
    "addr:full":"Winnipeg MB R2C 3A8",
    "addr:postcode":"r2c 3a8",
    "iso:country":"CA",
    "sg:city":"Winnipeg",
    "sg:classifiers":[
        {
            "category":"Retail",
            "subcategory":"Auto Rental",
            "type":"Services"
        }
    ],
    "sg:phone":"+1 204 668 0808",
    "sg:postcode":"R2C 3A8",
    "sg:province":"MB",
    "sg:tags":[
        "renting",
        "automobile"
    ],
    "wof:name":"A Enterprise Rent-A-Car",
    "wof:placetype":"venue"
},
  "geometry": {"coordinates":[-97.0416183472,49.8951072693],"type":"Point"}
}