{
  "type": "Feature",
  "properties": {
    "iso:country":"CA",
    "sg:address":"5225 Rue Berri",
    "sg:city":"Montreal",
    "sg:classifiers":[
        {
            "category":"Organizations",
            "subcategory":"Professional Association",
            "type":"Services"
        }
    ],
    "sg:phone":"+1 514 948 0505",
    "sg:postcode":"H2J 2S4",
    "sg:province":"QC",
    "wof:name":"Coalition Des Organismes",
    "wof:placetype":"venue"
},
  "geometry": {"coordinates":[-73.59039300000001,45.529221],"type":"Point"}
}