{
  "type": "Feature",
  "properties": {
    "iso:country":"CA",
    "sg:address":"1340 Rue DE LA Pointe-Aux-Liev",
    "sg:city":"Quebec",
    "sg:classifiers":[
        {
            "category":"Food & Beverages",
            "subcategory":"Groceries & Convenience Stores",
            "type":"Retail Goods"
        }
    ],
    "sg:phone":"+1 418 524 5959",
    "sg:postcode":"G1L 4M3",
    "sg:province":"QC",
    "sg:tags":[
        "grocer"
    ],
    "wof:name":"Epicerie Boutch",
    "wof:placetype":"venue"
},
  "geometry": {"coordinates":[-71.24249267579999,46.8225975037],"type":"Point"}
}