{
  "type": "Feature",
  "properties": {
    "addr:full":"730 Cheadle St W Swift Current SK S9H 0B9",
    "addr:housenumber":"730",
    "addr:postcode":"s9h 0b9",
    "addr:street":"Cheadle St W",
    "iso:country":"CA",
    "sg:address":"730 Cheadle St W",
    "sg:city":"Swift Current",
    "sg:classifiers":[
        {
            "category":"Retail",
            "subcategory":"Auto Repair",
            "type":"Services"
        }
    ],
    "sg:phone":"+1 306 773 5901",
    "sg:postcode":"S9H 0B9",
    "sg:province":"SK",
    "sg:tags":[
        "body",
        "automobile",
        "painting"
    ],
    "wof:name":"Klassen Autobody Ltd",
    "wof:placetype":"venue"
},
  "geometry": {"coordinates":[-107.80986785899999,50.2831230164],"type":"Point"}
}