{
  "type": "Feature",
  "properties": {
    "addr:full":"North York ON M3H 1T2",
    "addr:postcode":"m3h 1t2",
    "iso:country":"CA",
    "sg:city":"North York",
    "sg:classifiers":[
        {
            "category":"Real Estate",
            "subcategory":"Real Estate Agent",
            "type":"Services"
        }
    ],
    "sg:phone":"+1 416 630 6788",
    "sg:postcode":"M3H 1T2",
    "sg:province":"ON",
    "sg:tags":[
        "management"
    ],
    "wof:name":"Greatwise Developments Corp",
    "wof:placetype":"venue"
},
  "geometry": {"coordinates":[-79.4360580444,43.736831665],"type":"Point"}
}