{
  "type": "Feature",
  "properties": {
    "addr:full":"Mississauga ON L4Z 3M3",
    "addr:postcode":"l4z 3m3",
    "iso:country":"CA",
    "sg:city":"Mississauga",
    "sg:classifiers":[
        {
            "category":"Professional",
            "subcategory":"Employment Agencies",
            "type":"Services"
        }
    ],
    "sg:phone":"+1 905 273 4229",
    "sg:postcode":"L4Z 3M3",
    "sg:province":"ON",
    "sg:tags":[
        "opportunity"
    ],
    "wof:name":"Robert Half Finance & Acctng",
    "wof:placetype":"venue"
},
  "geometry": {"coordinates":[-79.63822937010001,43.5964622498],"type":"Point"}
}