{
  "type": "Feature",
  "properties": {
    "addr:full":"1962 Greenfield Rd Ayr ON N0B 1E0",
    "addr:housenumber":"1962",
    "addr:postcode":"n0b 1e0",
    "addr:street":"Greenfield Rd",
    "iso:country":"CA",
    "sg:address":"1962 Greenfield Rd",
    "sg:city":"Ayr",
    "sg:classifiers":[
        {
            "category":"Freight",
            "type":"Transportation"
        }
    ],
    "sg:phone":"+1 519 632 8533",
    "sg:postcode":"N0B 1E0",
    "sg:province":"ON",
    "sg:tags":[
        "cement",
        "trucking"
    ],
    "wof:name":"Bnk Transport Ltd",
    "wof:placetype":"venue"
},
  "geometry": {"coordinates":[-80.4318695068,43.3038902283],"type":"Point"}
}