{
  "type": "Feature",
  "properties": {
    "addr:full":"22 Evans Ave Leamington ON N8H 4X3",
    "addr:housenumber":"22",
    "addr:postcode":"n8h 4x3",
    "addr:street":"Evans Ave",
    "iso:country":"CA",
    "sg:address":"22 Evans Ave",
    "sg:city":"Leamington",
    "sg:classifiers":[
        {
            "category":"Freight",
            "type":"Transportation"
        }
    ],
    "sg:phone":"+1 519 322 0549",
    "sg:postcode":"N8H 4X3",
    "sg:province":"ON",
    "sg:tags":[
        "trucking"
    ],
    "wof:name":"Gino Trucking",
    "wof:placetype":"venue"
},
  "geometry": {"coordinates":[-82.5821762085,42.0452766418],"type":"Point"}
}