{
  "type": "Feature",
  "properties": {
    "addr:full":"Scarborough ON M1B 2W3",
    "addr:postcode":"m1b 2w3",
    "iso:country":"CA",
    "sg:city":"Scarborough",
    "sg:classifiers":[
        {
            "category":"Retail",
            "subcategory":"Auto Repair",
            "type":"Services"
        }
    ],
    "sg:phone":"+1 416 754 2128",
    "sg:postcode":"M1B 2W3",
    "sg:province":"ON",
    "sg:tags":[
        "automobile",
        "rustproofing",
        "undercoating"
    ],
    "wof:name":"Rust Check Ctr",
    "wof:placetype":"venue"
},
  "geometry": {"coordinates":[-79.24250000000001,43.811954],"type":"Point"}
}