{
  "type": "Feature",
  "properties": {
    "addr:full":"7954 Winston Churchill Blvd Hornby ON L0P 1E0",
    "addr:housenumber":"7954",
    "addr:postcode":"l0p 1e0",
    "addr:street":"Winston Churchill Blvd",
    "iso:country":"CA",
    "sg:address":"7954 Winston Churchill Blvd",
    "sg:city":"Hornby",
    "sg:classifiers":[
        {
            "category":"Freight",
            "type":"Transportation"
        }
    ],
    "sg:phone":"+1 905 567 5295",
    "sg:postcode":"L0P 1E0",
    "sg:province":"ON",
    "sg:tags":[
        "commercial",
        "storage"
    ],
    "wof:name":"A Safe Self Storage",
    "wof:placetype":"venue"
},
  "geometry": {"coordinates":[-79.837952,43.571579],"type":"Point"}
}