{
  "type": "Feature",
  "properties": {
    "addr:full":"94 Boul Renard O Gaspe QC G4X 5A1",
    "addr:housenumber":"94",
    "addr:postcode":"g4x 5a1",
    "addr:street":"Boul Renard O Gaspe",
    "iso:country":"CA",
    "sg:address":"94 Boul Renard O",
    "sg:city":"Gaspe",
    "sg:classifiers":[
        {
            "category":"Restaurant",
            "type":"Food & Drink"
        }
    ],
    "sg:phone":"+1 418 269 7273",
    "sg:postcode":"G4X 5A1",
    "sg:province":"QC",
    "wof:name":"Dixie Lee",
    "wof:placetype":"venue"
},
  "geometry": {"coordinates":[-64.3834686279,48.9919395447],"type":"Point"}
}