{
  "type": "Feature",
  "properties": {
    "addr:full":"355 Laurier St Bathurst NB E2A 3G9",
    "addr:housenumber":"355",
    "addr:postcode":"e2a 3g9",
    "addr:street":"Laurier St",
    "iso:country":"CA",
    "sg:address":"355 Laurier St",
    "sg:city":"Bathurst",
    "sg:classifiers":[
        {
            "category":"Health Services",
            "subcategory":"Health Practitioner",
            "type":"Services"
        }
    ],
    "sg:phone":"+1 506 548 4004",
    "sg:postcode":"E2A 3G9",
    "sg:province":"NB",
    "sg:tags":[
        "acupuncture",
        "physiotherapist"
    ],
    "wof:name":"Nor'East Physiotherapie Inc",
    "wof:placetype":"venue"
},
  "geometry": {"coordinates":[-65.668694,47.630489],"type":"Point"}
}