{
  "type": "Feature",
  "properties": {
    "addr:full":"670 Highway 7 E # 35 Richmond Hill ON L4B 3P2",
    "addr:housenumber":"670;35",
    "addr:postcode":"l4b 3p2",
    "addr:street":"Highway 7 E #",
    "iso:country":"CA",
    "sg:address":"670 Highway 7 E # 35",
    "sg:city":"Richmond Hill",
    "sg:classifiers":[
        {
            "category":"Shopping",
            "subcategory":"Discount & Variety Stores",
            "type":"Retail Goods"
        }
    ],
    "sg:phone":"+1 905 709 2076",
    "sg:postcode":"L4B 3P2",
    "sg:province":"ON",
    "wof:name":"Shoppes of the Parkway Variety",
    "wof:placetype":"venue"
},
  "geometry": {"coordinates":[-79.37847137449999,43.8465538025],"type":"Point"}
}