{
  "type": "Feature",
  "properties": {
    "addr:full":"2043 Rue DE Palerme Laval QC H7M 5J3",
    "addr:housenumber":"2043",
    "addr:postcode":"h7m 5j3",
    "addr:street":"Rue De Palerme",
    "iso:country":"CA",
    "sg:address":"2043 Rue DE Palerme",
    "sg:city":"Laval",
    "sg:classifiers":[
        {
            "category":"Wholesale",
            "subcategory":"Electrical",
            "type":"Manufacturing & Wholesale Goods"
        }
    ],
    "sg:phone":"+1 450 662 1379",
    "sg:postcode":"H7M 5J3",
    "sg:province":"QC",
    "sg:tags":[
        "control",
        "security",
        "system"
    ],
    "wof:name":"Secu-Pro Experts-Conseils",
    "wof:placetype":"venue"
},
  "geometry": {"coordinates":[-73.7241897583,45.6130180359],"type":"Point"}
}