{
  "type": "Feature",
  "properties": {
    "addr:full":"Barrhead AB T7N 1A4",
    "addr:postcode":"t7n 1a4",
    "iso:country":"CA",
    "sg:city":"Barrhead",
    "sg:classifiers":[
        {
            "category":"Restaurant",
            "type":"Food & Drink"
        }
    ],
    "sg:phone":"+1 780 674 3999",
    "sg:postcode":"T7N 1A4",
    "sg:province":"AB",
    "wof:name":"Frank Steakhouse & Pizza Ltd",
    "wof:placetype":"venue"
},
  "geometry": {"coordinates":[-114.402992,54.118076],"type":"Point"}
}