{
  "type": "Feature",
  "properties": {
    "addr:full":"151 Wentworth Rd Windsor NS B0N 2T0",
    "addr:housenumber":"151",
    "addr:postcode":"b0n 2t0",
    "addr:street":"Wentworth Rd",
    "iso:country":"CA",
    "sg:address":"151 Wentworth Rd",
    "sg:city":"Windsor",
    "sg:classifiers":[
        {
            "category":"Health Services",
            "subcategory":"Doctor",
            "type":"Services"
        }
    ],
    "sg:phone":"+1 902 798 2355",
    "sg:postcode":"B0N 2T0",
    "sg:province":"NS",
    "sg:tags":[
        "dentist"
    ],
    "wof:name":"Kevin Walsh Dentistry Inc",
    "wof:placetype":"venue"
},
  "geometry": {"coordinates":[-64.126914978,44.9909858704],"type":"Point"}
}