{
  "type": "Feature",
  "properties": {
    "iso:country":"CA",
    "sg:address":"6979 Yonge St # 207",
    "sg:city":"North York",
    "sg:classifiers":[
        {
            "category":"Health Services",
            "subcategory":"Doctor",
            "type":"Services"
        }
    ],
    "sg:phone":"+1 416 229 9597",
    "sg:postcode":"M2M 3X9",
    "sg:province":"ON",
    "sg:tags":[
        "dentist"
    ],
    "wof:name":"Midpoint Dental Office",
    "wof:placetype":"venue"
},
  "geometry": {"coordinates":[-79.4199752808,43.7980003357],"type":"Point"}
}