{
  "type": "Feature",
  "properties": {
    "addr:full":"350 Boul Cremazie E Montreal QC H2P 1E5",
    "addr:housenumber":"350",
    "addr:postcode":"h2p 1e5",
    "addr:street":"Boul Cremazie E",
    "iso:country":"CA",
    "sg:address":"350 Boul Cremazie E",
    "sg:city":"Montreal",
    "sg:classifiers":[
        {
            "category":"Autos & Motor Vehicles",
            "subcategory":"Auto Supplies",
            "type":"Retail Goods"
        }
    ],
    "sg:phone":"+1 514 384 5534",
    "sg:postcode":"H2P 1E5",
    "sg:province":"QC",
    "sg:tags":[
        "automobile",
        "parts"
    ],
    "wof:name":"Pieces D'Auto Cobra Inc",
    "wof:placetype":"venue"
},
  "geometry": {"coordinates":[-73.63897705079999,45.5446777344],"type":"Point"}
}