{
  "type": "Feature",
  "properties": {
    "addr:full":"550 Rundlehorn Cir NE Calgary AB T1Y 5T9",
    "addr:housenumber":"550",
    "addr:postcode":"t1y 5t9",
    "addr:street":"Rundlehorn Cir Ne",
    "iso:country":"CA",
    "sg:address":"550 Rundlehorn Cir NE",
    "sg:city":"Calgary",
    "sg:classifiers":[
        {
            "category":"Real Estate",
            "subcategory":"Real Estate Operator",
            "type":"Services"
        }
    ],
    "sg:phone":"+1 403 285 2063",
    "sg:postcode":"T1Y 5T9",
    "sg:province":"AB",
    "sg:tags":[
        "apartment"
    ],
    "wof:name":"Sunridge Village",
    "wof:placetype":"venue"
},
  "geometry": {"coordinates":[-113.980858,51.072754],"type":"Point"}
}