{
  "type": "Feature",
  "properties": {
    "iso:country":"CA",
    "sg:address":"402 English Bluff Rd",
    "sg:city":"Delta",
    "sg:classifiers":[
        {
            "category":"Social Services",
            "subcategory":"Child Care",
            "type":"Services"
        }
    ],
    "sg:phone":"+1 604 943 0525",
    "sg:postcode":"V4M 2N2",
    "sg:province":"BC",
    "wof:name":"Bilingual Montessori",
    "wof:placetype":"venue"
},
  "geometry": {"coordinates":[-123.089744568,49.0097465515],"type":"Point"}
}