{
  "type": "Feature",
  "properties": {
    "addr:full":"11130 149 St NW Edmonton AB T5M 1W4",
    "addr:housenumber":"11130",
    "addr:postcode":"t5m 1w4",
    "addr:street":"149 St Nw",
    "iso:country":"CA",
    "sg:address":"11130 149 St NW",
    "sg:city":"Edmonton",
    "sg:classifiers":[
        {
            "category":"Retail",
            "subcategory":"Auto Repair",
            "type":"Services"
        }
    ],
    "sg:phone":"+1 780 454 2341",
    "sg:postcode":"T5M 1W4",
    "sg:province":"AB",
    "sg:tags":[
        "body",
        "automobile",
        "painting"
    ],
    "wof:name":"Kingsway Lexus Toyota Auto",
    "wof:placetype":"venue"
},
  "geometry": {"coordinates":[-113.5783,53.559849],"type":"Point"}
}