{
  "type": "Feature",
  "properties": {
    "addr:full":"Woodbridge ON L4L 9G3",
    "addr:postcode":"l4l 9g3",
    "iso:country":"CA",
    "sg:city":"Woodbridge",
    "sg:classifiers":[
        {
            "category":"Building & Trades",
            "subcategory":"Construction",
            "type":"Services"
        }
    ],
    "sg:phone":"+1 416 213 7181",
    "sg:postcode":"L4L 9G3",
    "sg:province":"ON",
    "sg:tags":[
        "contractor"
    ],
    "wof:name":"Royal Pine Homes Ltd",
    "wof:placetype":"venue"
},
  "geometry": {"coordinates":[-79.54673,43.808899],"type":"Point"}
}