{
  "type": "Feature",
  "properties": {
    "addr:full":"20667 Langley Bypass Langley BC V3A 5E8",
    "addr:housenumber":"20667",
    "addr:postcode":"v3a 5e8",
    "addr:street":"Langley Bypass",
    "iso:country":"CA",
    "sg:address":"20667 Langley Bypass",
    "sg:city":"Langley",
    "sg:classifiers":[
        {
            "category":"Wholesale",
            "subcategory":"Hardware",
            "type":"Manufacturing & Wholesale Goods"
        }
    ],
    "sg:phone":"+1 604 533 2455",
    "sg:postcode":"V3A 5E8",
    "sg:province":"BC",
    "sg:tags":[
        "equipment",
        "heating",
        "system"
    ],
    "wof:name":"Meyers Sheet Metal",
    "wof:placetype":"venue"
},
  "geometry": {"coordinates":[-122.651093,49.113277],"type":"Point"}
}