{
  "type": "Feature",
  "properties": {
    "addr:full":"Mitchell & Hwy 518 E Emsdale ON P0A 1J0",
    "addr:postcode":"p0a 1j0",
    "addr:street":"Hwy 518 E",
    "iso:country":"CA",
    "sg:address":"Mitchell & Hwy 518 E",
    "sg:city":"Emsdale",
    "sg:classifiers":[
        {
            "category":"Freight",
            "type":"Transportation"
        }
    ],
    "sg:phone":"+1 705 636 0313",
    "sg:postcode":"P0A 1J0",
    "sg:province":"ON",
    "sg:tags":[
        "commercial",
        "storage"
    ],
    "wof:name":"A & J Storage",
    "wof:placetype":"venue"
},
  "geometry": {"coordinates":[-79.315468,45.529362],"type":"Point"}
}