{
  "type": "Feature",
  "properties": {
    "iso:country":"CA",
    "sg:city":"St. John's",
    "sg:classifiers":[
        {
            "category":"Manufacturing",
            "subcategory":"Printing",
            "type":"Manufacturing & Wholesale Goods"
        }
    ],
    "sg:phone":"+1 709 579 3350",
    "sg:postcode":"A1C 6K3",
    "sg:province":"NL",
    "sg:tags":[
        "printer"
    ],
    "wof:name":"Print Three",
    "wof:placetype":"venue"
},
  "geometry": {"coordinates":[-52.7127990723,47.560295105],"type":"Point"}
}