{
  "type": "Feature",
  "properties": {
    "iso:country":"CA",
    "sg:city":"Barrie",
    "sg:classifiers":[
        {
            "category":"Retail",
            "subcategory":"Animal Services",
            "type":"Services"
        }
    ],
    "sg:phone":"+1 705 792 0761",
    "sg:postcode":"L4N 4Y8",
    "sg:province":"ON",
    "sg:tags":[
        "pet",
        "training"
    ],
    "wof:name":"Barrie Canine Connection",
    "wof:placetype":"venue"
},
  "geometry": {"coordinates":[-79.6826705933,44.3584213257],"type":"Point"}
}