{
  "type": "Feature",
  "properties": {
    "addr:full":"421 Lahave St Bridgewater NS B4V 3A2",
    "addr:housenumber":"421",
    "addr:postcode":"b4v 3a2",
    "addr:street":"Lahave St",
    "iso:country":"CA",
    "sg:address":"421 Lahave St",
    "sg:city":"Bridgewater",
    "sg:classifiers":[
        {
            "category":"Shopping",
            "subcategory":"Books",
            "type":"Retail Goods"
        }
    ],
    "sg:phone":"+1 902 543 4773",
    "sg:postcode":"B4V 3A2",
    "sg:province":"NS",
    "sg:tags":[
        "dealer"
    ],
    "wof:name":"Coles",
    "wof:placetype":"venue"
},
  "geometry": {"coordinates":[-64.5143737793,44.3780212402],"type":"Point"}
}