{
  "type": "Feature",
  "properties": {
    "addr:full":"Dartmouth NS B3B 1M7",
    "addr:postcode":"b3b 1m7",
    "iso:country":"CA",
    "sg:city":"Dartmouth",
    "sg:classifiers":[
        {
            "category":"Wholesale",
            "subcategory":"Auto Parts",
            "type":"Manufacturing & Wholesale Goods"
        }
    ],
    "sg:phone":"+1 902 468 2555",
    "sg:postcode":"B3B 1M7",
    "sg:province":"NS",
    "sg:tags":[
        "equipment",
        "truck"
    ],
    "wof:name":"Ocean Truck Equipment Ltd",
    "wof:placetype":"venue"
},
  "geometry": {"coordinates":[-63.5979728699,44.7096061707],"type":"Point"}
}