{
  "type": "Feature",
  "properties": {
    "addr:full":"4141 98 St NW Edmonton AB T6E 5N5",
    "addr:housenumber":"4141",
    "addr:postcode":"t6e 5n5",
    "addr:street":"98 St Nw",
    "iso:country":"CA",
    "sg:address":"4141 98 St NW",
    "sg:city":"Edmonton",
    "sg:classifiers":[
        {
            "category":"Wholesale",
            "subcategory":"Jewelry",
            "type":"Manufacturing & Wholesale Goods"
        }
    ],
    "sg:phone":"+1 780 433 6465",
    "sg:postcode":"T6E 5N5",
    "sg:province":"AB",
    "sg:tags":[
        "jeweler"
    ],
    "wof:name":"Gastown Fashion Jwlry & Gifts",
    "wof:placetype":"venue"
},
  "geometry": {"coordinates":[-113.481956,53.477432],"type":"Point"}
}