{
  "type": "Feature",
  "properties": {
    "iso:country":"CA",
    "sg:address":"14 Indell Lane",
    "sg:city":"Brampton",
    "sg:classifiers":[
        {
            "category":"Retail",
            "subcategory":"Repair Shop",
            "type":"Services"
        }
    ],
    "sg:phone":"+1 905 789 0813",
    "sg:postcode":"L6T 3Y3",
    "sg:province":"ON",
    "sg:tags":[
        "lighting",
        "fixture"
    ],
    "wof:name":"Northern Light Technology Grp",
    "wof:placetype":"venue"
},
  "geometry": {"coordinates":[-79.689598,43.736668],"type":"Point"}
}