{
  "type": "Feature",
  "properties": {
    "iso:country":"CA",
    "sg:city":"North Vancouver",
    "sg:classifiers":[
        {
            "category":"Shopping",
            "type":"Retail Goods"
        }
    ],
    "sg:phone":"+1 604 988 8013",
    "sg:postcode":"V7M 2K2",
    "sg:province":"BC",
    "sg:tags":[
        "hearing",
        "equipment",
        "supply",
        "impaired"
    ],
    "wof:name":"Beltone Better Hearing Ctr",
    "wof:placetype":"venue"
},
  "geometry": {"coordinates":[-123.071990967,49.3266639709],"type":"Point"}
}