{
  "type": "Feature",
  "properties": {
    "addr:full":"361 Rue Blain Mont-Saint-Hilaire QC J3H 3B4",
    "addr:housenumber":"361",
    "addr:postcode":"j3h 3b4",
    "addr:street":"Rue Blain",
    "iso:country":"CA",
    "sg:address":"361 Rue Blain",
    "sg:city":"Mont-Saint-Hilaire",
    "sg:classifiers":[
        {
            "category":"Professional",
            "subcategory":"Business Services",
            "type":"Services"
        }
    ],
    "sg:phone":"+1 450 467 7996",
    "sg:postcode":"J3H 3B4",
    "sg:province":"QC",
    "sg:tags":[
        "consultant",
        "cabinet",
        "design",
        "interior",
        "maker",
        "decorator"
    ],
    "wof:name":"Ebenisterie Van DE Beken",
    "wof:placetype":"venue"
},
  "geometry": {"coordinates":[-73.1861343384,45.5652770996],"type":"Point"}
}