{
  "type": "Feature",
  "properties": {
    "addr:full":"3482 Petawawa Blvd Petawawa ON K8H 1X3",
    "addr:housenumber":"3482",
    "addr:postcode":"k8h 1x3",
    "addr:street":"Petawawa Blvd",
    "iso:country":"CA",
    "sg:address":"3482 Petawawa Blvd",
    "sg:city":"Petawawa",
    "sg:classifiers":[
        {
            "category":"Shopping",
            "subcategory":"Catalog Store",
            "type":"Retail Goods"
        }
    ],
    "sg:phone":"+1 613 687 5195",
    "sg:postcode":"K8H 1X3",
    "sg:province":"ON",
    "sg:tags":[
        "mail",
        "order",
        "internet"
    ],
    "wof:name":"Sears Canada Inc",
    "wof:placetype":"venue"
},
  "geometry": {"coordinates":[-77.28370700000001,45.899754],"type":"Point"}
}