{
  "type": "Feature",
  "properties": {
    "addr:full":"327 Cooper St Cambridge ON N3C 3X8",
    "addr:housenumber":"327",
    "addr:postcode":"n3c 3x8",
    "addr:street":"Cooper St",
    "iso:country":"CA",
    "sg:address":"327 Cooper St",
    "sg:city":"Cambridge",
    "sg:classifiers":[
        {
            "category":"Wholesale",
            "subcategory":"Electrical",
            "type":"Manufacturing & Wholesale Goods"
        }
    ],
    "sg:phone":"+1 519 651 2802",
    "sg:postcode":"N3C 3X8",
    "sg:province":"ON",
    "sg:tags":[
        "control"
    ],
    "wof:name":"Phoenix Controls Corp",
    "wof:placetype":"venue"
},
  "geometry": {"coordinates":[-80.294197,43.426044],"type":"Point"}
}