{
  "type": "Feature",
  "properties": {
    "addr:full":"4640 Byng Rd Port Hardy BC V0N 2P0",
    "addr:housenumber":"4640",
    "addr:postcode":"v0n 2p0",
    "addr:street":"Byng Rd",
    "iso:country":"CA",
    "sg:address":"4640 Byng Rd",
    "sg:city":"Port Hardy",
    "sg:classifiers":[
        {
            "category":"Education",
            "subcategory":"School",
            "type":"Public Place"
        }
    ],
    "sg:phone":"+1 250 949 8243",
    "sg:postcode":"V0N 2P0",
    "sg:province":"BC",
    "wof:name":"Avalon Adventist Jr Academy",
    "wof:placetype":"venue"
},
  "geometry": {"coordinates":[-127.398361206,50.6881713867],"type":"Point"}
}