{
  "type": "Feature",
  "properties": {
    "addr:full":"143 Sackville St Montague PE C0A 1R0",
    "addr:housenumber":"143",
    "addr:postcode":"c0a 1r0",
    "addr:street":"Sackville St",
    "iso:country":"CA",
    "sg:address":"143 Sackville St",
    "sg:city":"Montague",
    "sg:classifiers":[
        {
            "category":"Arena",
            "subcategory":"Sports Club",
            "type":"Entertainment"
        }
    ],
    "sg:phone":"+1 902 838 2724",
    "sg:postcode":"C0A 1R0",
    "sg:province":"PE",
    "sg:tags":[
        "athletic",
        "fields",
        "stadium"
    ],
    "wof:name":"Iceland Arena",
    "wof:placetype":"venue"
},
  "geometry": {"coordinates":[-62.648567,46.167236],"type":"Point"}
}