{
  "type": "Feature",
  "properties": {
    "iso:country":"CA",
    "sg:city":"Victoria",
    "sg:classifiers":[
        {
            "category":"Restaurant",
            "type":"Food & Drink"
        }
    ],
    "sg:phone":"+1 250 384 5622",
    "sg:postcode":"V8W 1E6",
    "sg:province":"BC",
    "wof:name":"J R's India Curry House",
    "wof:placetype":"venue"
},
  "geometry": {"coordinates":[-123.369674683,48.4251327515],"type":"Point"}
}