{
  "type": "Feature",
  "properties": {
    "addr:full":"PO Box 338 Manitouwadge ON P0T 2C0",
    "addr:housenumber":"po",
    "addr:postcode":"p0t 2c0",
    "addr:street":"Box 338",
    "iso:country":"CA",
    "sg:address":"PO Box 338",
    "sg:city":"Manitouwadge",
    "sg:classifiers":[
        {
            "category":"Organizations",
            "subcategory":"Professional Association",
            "type":"Services"
        }
    ],
    "sg:phone":"+1 807 826 4224",
    "sg:postcode":"P0T 2C0",
    "sg:province":"ON",
    "wof:name":"Marjorie House Outreach",
    "wof:placetype":"venue"
},
  "geometry": {"coordinates":[-85.83214599999999,49.12394],"type":"Point"}
}