{
  "type": "Feature",
  "properties": {
    "addr:full":"North York ON M2M 3W7",
    "addr:postcode":"m2m 3w7",
    "iso:country":"CA",
    "sg:city":"North York",
    "sg:classifiers":[
        {
            "category":"Professional",
            "subcategory":"Lawyer & Legal Services",
            "type":"Services"
        }
    ],
    "sg:phone":"+1 416 224 2272",
    "sg:postcode":"M2M 3W7",
    "sg:province":"ON",
    "sg:tags":[
        "attorney"
    ],
    "wof:name":"Kil Jang, Han",
    "wof:placetype":"venue"
},
  "geometry": {"coordinates":[-79.418648,43.791725],"type":"Point"}
}