{
  "type": "Feature",
  "properties": {
    "addr:full":"425 Av Des Cedres Shawinigan QC G9N 1N5",
    "addr:housenumber":"425",
    "addr:postcode":"g9n 1n5",
    "addr:street":"Av Des Cedres",
    "iso:country":"CA",
    "sg:address":"425 Av Des Cedres",
    "sg:city":"Shawinigan",
    "sg:classifiers":[
        {
            "category":"Wholesale",
            "subcategory":"Electrical",
            "type":"Manufacturing & Wholesale Goods"
        }
    ],
    "sg:phone":"+1 819 537 0000",
    "sg:postcode":"G9N 1N5",
    "sg:province":"QC",
    "sg:tags":[
        "communication",
        "radio",
        "system"
    ],
    "wof:name":"Reynolds Radio",
    "wof:placetype":"venue"
},
  "geometry": {"coordinates":[-72.746201,46.540154],"type":"Point"}
}