{
  "type": "Feature",
  "properties": {
    "addr:full":"3184 Birds Hill Rd East St Paul MB R2E 1H1",
    "addr:housenumber":"3184",
    "addr:postcode":"r2e 1h1",
    "addr:street":"Birds Hill Rd East",
    "iso:country":"CA",
    "sg:address":"3184 Birds Hill Rd",
    "sg:city":"East St Paul",
    "sg:classifiers":[
        {
            "category":"Restaurant",
            "type":"Food & Drink"
        }
    ],
    "sg:phone":"+1 204 668 8091",
    "sg:postcode":"R2E 1H1",
    "sg:province":"MB",
    "sg:tags":[
        "caterer"
    ],
    "wof:name":"Ludwick Catering Ltd",
    "wof:placetype":"venue"
},
  "geometry": {"coordinates":[-97.0064468384,49.9751701355],"type":"Point"}
}