{
  "type": "Feature",
  "properties": {
    "addr:full":"4760 Rue Hochelaga Montreal QC H1V 1E4",
    "addr:housenumber":"4760",
    "addr:postcode":"h1v 1e4",
    "addr:street":"Rue Hochelaga",
    "iso:country":"CA",
    "sg:address":"4760 Rue Hochelaga",
    "sg:city":"Montreal",
    "sg:classifiers":[
        {
            "category":"Organizations",
            "subcategory":"Religious Organization",
            "type":"Services"
        }
    ],
    "sg:phone":"+1 514 256 0735",
    "sg:postcode":"H1V 1E4",
    "sg:province":"QC",
    "sg:tags":[
        "church"
    ],
    "wof:name":"Ste Marie DE LA Medaille",
    "wof:placetype":"venue"
},
  "geometry": {"coordinates":[-73.543533,45.559448],"type":"Point"}
}