{
  "type": "Feature",
  "properties": {
    "addr:full":"38 Maida Vale Scarborough ON M1K 2X9",
    "addr:housenumber":"38",
    "addr:postcode":"m1k 2x9",
    "addr:street":"Maida Vale",
    "iso:country":"CA",
    "sg:address":"38 Maida Vale",
    "sg:city":"Scarborough",
    "sg:classifiers":[
        {
            "category":"Manufacturing",
            "subcategory":"Printing",
            "type":"Manufacturing & Wholesale Goods"
        }
    ],
    "sg:phone":"+1 416 285 1951",
    "sg:postcode":"M1K 2X9",
    "sg:province":"ON",
    "sg:tags":[
        "printer"
    ],
    "wof:name":"In Demand",
    "wof:placetype":"venue"
},
  "geometry": {"coordinates":[-79.27501700000001,43.733532],"type":"Point"}
}