{
  "type": "Feature",
  "properties": {
    "addr:full":"37 Rue Du Roi Sorel-Tracy QC J3P 4M6",
    "addr:housenumber":"37",
    "addr:postcode":"j3p 4m6",
    "addr:street":"Rue Du Roi",
    "iso:country":"CA",
    "sg:address":"37 Rue Du Roi",
    "sg:city":"Sorel-Tracy",
    "sg:classifiers":[
        {
            "category":"Shopping",
            "subcategory":"Clothing, Apparel, & Fashions",
            "type":"Retail Goods"
        }
    ],
    "sg:phone":"+1 450 746 0359",
    "sg:postcode":"J3P 4M6",
    "sg:province":"QC",
    "sg:tags":[
        "boutique",
        "jeweler"
    ],
    "wof:name":"Bijouterie Lyne Div",
    "wof:placetype":"venue"
},
  "geometry": {"coordinates":[-73.116333,46.045109],"type":"Point"}
}