{
  "type": "Feature",
  "properties": {
    "iso:country":"CA",
    "sg:city":"Saskatoon",
    "sg:classifiers":[
        {
            "category":"Real Estate",
            "subcategory":"Real Estate Operator",
            "type":"Services"
        }
    ],
    "sg:phone":"+1 306 242 7300",
    "sg:postcode":"S7K 6K3",
    "sg:province":"SK",
    "sg:tags":[
        "apartment"
    ],
    "wof:name":"Duchess Courts",
    "wof:placetype":"venue"
},
  "geometry": {"coordinates":[-106.648773193,52.1426124573],"type":"Point"}
}