{
  "type": "Feature",
  "properties": {
    "iso:country":"CA",
    "sg:address":"952 Main St",
    "sg:city":"Winnipeg",
    "sg:classifiers":[
        {
            "category":"Shopping",
            "subcategory":"Gifts & Souvenirs",
            "type":"Retail Goods"
        }
    ],
    "sg:phone":"+1 204 582 2832",
    "sg:postcode":"R2W 3P4",
    "sg:province":"MB",
    "sg:tags":[
        "shop"
    ],
    "wof:name":"Kalyna Ukrainian CO-OP Bk Str",
    "wof:placetype":"venue"
},
  "geometry": {"coordinates":[-97.133087,49.911289],"type":"Point"}
}