{
  "type": "Feature",
  "properties": {
    "addr:full":"2904 Bloor St W Etobicoke ON M8X 1B6",
    "addr:housenumber":"2904",
    "addr:postcode":"m8x 1b6",
    "addr:street":"Bloor St W",
    "iso:country":"CA",
    "sg:address":"2904 Bloor St W",
    "sg:city":"Etobicoke",
    "sg:classifiers":[
        {
            "category":"Personal",
            "subcategory":"Beauty Salon",
            "type":"Services"
        }
    ],
    "sg:phone":"+1 416 231 5932",
    "sg:postcode":"M8X 1B6",
    "sg:province":"ON",
    "wof:name":"Kingsway Hair Design For Men",
    "wof:placetype":"venue"
},
  "geometry": {"coordinates":[-79.5067825317,43.6484909058],"type":"Point"}
}