{
  "type": "Feature",
  "properties": {
    "iso:country":"CA",
    "sg:address":"1421 Highway 17 E",
    "sg:city":"Kenora",
    "sg:classifiers":[
        {
            "category":"Recreation",
            "type":"Entertainment"
        }
    ],
    "sg:phone":"+1 807 468 3483",
    "sg:postcode":"P9N 1M1",
    "sg:province":"ON",
    "sg:tags":[
        "diving",
        "instruction"
    ],
    "wof:name":"Sunset Diving",
    "wof:placetype":"venue"
},
  "geometry": {"coordinates":[-94.4893112183,49.7706260681],"type":"Point"}
}