{
  "type": "Feature",
  "properties": {
    "addr:full":"10821 96 St NW Edmonton AB T5H 2J8",
    "addr:housenumber":"10821",
    "addr:postcode":"t5h 2j8",
    "addr:street":"96 St Nw",
    "iso:country":"CA",
    "sg:address":"10821 96 St NW",
    "sg:city":"Edmonton",
    "sg:classifiers":[
        {
            "category":"Organizations",
            "subcategory":"Religious Organization",
            "type":"Services"
        }
    ],
    "sg:phone":"+1 780 422 3052",
    "sg:postcode":"T5H 2J8",
    "sg:province":"AB",
    "sg:tags":[
        "church"
    ],
    "wof:name":"Sacred Heart Roman Catholic",
    "wof:placetype":"venue"
},
  "geometry": {"coordinates":[-113.48717498800001,53.5547485352],"type":"Point"}
}