{
  "type": "Feature",
  "properties": {
    "iso:country":"CA",
    "sg:city":"Ottawa",
    "sg:classifiers":[
        {
            "category":"Professional",
            "subcategory":"Lawyer & Legal Services",
            "type":"Services"
        }
    ],
    "sg:phone":"+1 613 567 1431",
    "sg:postcode":"K2P 0C2",
    "sg:province":"ON",
    "sg:tags":[
        "attorney"
    ],
    "wof:name":"Parent Carr",
    "wof:placetype":"venue"
},
  "geometry": {"coordinates":[-75.6899795532,45.4196815491],"type":"Point"}
}