{
  "type": "Feature",
  "properties": {
    "iso:country":"CA",
    "sg:city":"Etobicoke",
    "sg:classifiers":[
        {
            "category":"Health Services",
            "subcategory":"Hospital",
            "type":"Services"
        }
    ],
    "sg:phone":"+1 416 207 5032",
    "sg:postcode":"M8X 1Y6",
    "sg:province":"ON",
    "sg:tags":[
        "mental"
    ],
    "wof:name":"Fame",
    "wof:placetype":"venue"
},
  "geometry": {"coordinates":[-79.5113372803,43.6604614258],"type":"Point"}
}