{
  "type": "Feature",
  "properties": {
    "iso:country":"CA",
    "sg:city":"Bearskin Lake",
    "sg:classifiers":[
        {
            "category":"Travel",
            "subcategory":"Hotels & Motels",
            "type":"Entertainment"
        }
    ],
    "sg:phone":"+1 807 363 2581",
    "sg:postcode":"P0V 1E0",
    "sg:province":"ON",
    "wof:name":"Michikan Lake Business Ctr",
    "wof:placetype":"venue"
},
  "geometry": {"coordinates":[-90.99156188960001,53.8995018005],"type":"Point"}
}