{
  "type": "Feature",
  "properties": {
    "addr:full":"North Vancouver BC V7M 3K1",
    "addr:postcode":"v7m 3k1",
    "iso:country":"CA",
    "sg:city":"North Vancouver",
    "sg:classifiers":[
        {
            "category":"Professional",
            "subcategory":"Lawyer & Legal Services",
            "type":"Services"
        }
    ],
    "sg:phone":"+1 604 988 6321",
    "sg:postcode":"V7M 3K1",
    "sg:province":"BC",
    "sg:tags":[
        "attorney"
    ],
    "wof:name":"Poyner Baxter",
    "wof:placetype":"venue"
},
  "geometry": {"coordinates":[-123.083817,49.310711],"type":"Point"}
}