{
  "type": "Feature",
  "properties": {
    "addr:full":"580 Yonge St Barrie ON L4N 4E4",
    "addr:housenumber":"580",
    "addr:postcode":"l4n 4e4",
    "addr:street":"Yonge St",
    "iso:country":"CA",
    "sg:address":"580 Yonge St",
    "sg:city":"Barrie",
    "sg:classifiers":[
        {
            "category":"Autos & Motor Vehicles",
            "subcategory":"Automobile Sales",
            "type":"Retail Goods"
        }
    ],
    "sg:phone":"+1 705 728 2801",
    "sg:postcode":"L4N 4E4",
    "sg:province":"ON",
    "sg:tags":[
        "car",
        "dealer"
    ],
    "wof:name":"Canadian Car Connections",
    "wof:placetype":"venue"
},
  "geometry": {"coordinates":[-79.6514663696,44.3583946228],"type":"Point"}
}