{
  "type": "Feature",
  "properties": {
    "addr:full":"450 Rue Saint-Georges Saint-Michel-Des-Saints QC J0K 3B0",
    "addr:housenumber":"450",
    "addr:postcode":"j0k 3b0",
    "addr:street":"Rue Saint-Georges",
    "iso:country":"CA",
    "sg:address":"450 Rue Saint-Georges",
    "sg:city":"Saint-Michel-Des-Saints",
    "sg:classifiers":[
        {
            "category":"Building & Trades",
            "subcategory":"Plumbing",
            "type":"Services"
        }
    ],
    "sg:phone":"+1 450 833 6902",
    "sg:postcode":"J0K 3B0",
    "sg:province":"QC",
    "sg:tags":[
        "contractor"
    ],
    "wof:name":"Gaston Beausoleil Plomberie",
    "wof:placetype":"venue"
},
  "geometry": {"coordinates":[-73.92306499999999,46.676392],"type":"Point"}
}