{
  "type": "Feature",
  "properties": {
    "addr:full":"4718 51 Ave Leduc AB T9E 6Y8",
    "addr:housenumber":"4718",
    "addr:postcode":"t9e 6y8",
    "addr:street":"51 Ave",
    "iso:country":"CA",
    "sg:address":"4718 51 Ave",
    "sg:city":"Leduc",
    "sg:classifiers":[
        {
            "category":"Wholesale",
            "subcategory":"Groceries",
            "type":"Manufacturing & Wholesale Goods"
        }
    ],
    "sg:phone":"+1 780 986 9363",
    "sg:postcode":"T9E 6Y8",
    "sg:province":"AB",
    "sg:tags":[
        "confectionery",
        "candy"
    ],
    "wof:name":"Candy Nut Kids Corp",
    "wof:placetype":"venue"
},
  "geometry": {"coordinates":[-113.548179627,53.2656478882],"type":"Point"}
}