{
  "type": "Feature",
  "properties": {
    "addr:full":"132 Beaconsfield Way NW Calgary AB T3K 1X1",
    "addr:housenumber":"132",
    "addr:postcode":"t3k 1x1",
    "addr:street":"Beaconsfield Way Nw",
    "iso:country":"CA",
    "sg:address":"132 Beaconsfield Way NW",
    "sg:city":"Calgary",
    "sg:classifiers":[
        {
            "category":"Building & Trades",
            "subcategory":"Construction",
            "type":"Services"
        }
    ],
    "sg:phone":"+1 403 275 4589",
    "sg:postcode":"T3K 1X1",
    "sg:province":"AB",
    "sg:tags":[
        "masonry",
        "contractor"
    ],
    "wof:name":"Bill's Masonry",
    "wof:placetype":"venue"
},
  "geometry": {"coordinates":[-114.105361938,51.1304588318],"type":"Point"}
}