{
  "type": "Feature",
  "properties": {
    "addr:full":"Baie-Saint-Paul QC G3Z 2P8",
    "addr:postcode":"g3z 2p8",
    "iso:country":"CA",
    "sg:city":"Baie-Saint-Paul",
    "sg:classifiers":[
        {
            "category":"Professional",
            "subcategory":"Business Services",
            "type":"Services"
        }
    ],
    "sg:phone":"+1 418 240 4000",
    "sg:postcode":"G3Z 2P8",
    "sg:province":"QC",
    "sg:tags":[
        "notary"
    ],
    "wof:name":"Bouchard & Gagnon Notaires",
    "wof:placetype":"venue"
},
  "geometry": {"coordinates":[-70.51750199999999,47.44754],"type":"Point"}
}