{
  "type": "Feature",
  "properties": {
    "addr:full":"1221 Rue Fleury E Montreal QC H2C 1R2",
    "addr:housenumber":"1221",
    "addr:postcode":"h2c 1r2",
    "addr:street":"Rue Fleury E",
    "iso:country":"CA",
    "sg:address":"1221 Rue Fleury E",
    "sg:city":"Montreal",
    "sg:classifiers":[
        {
            "category":"Shopping",
            "subcategory":"Pharmacy",
            "type":"Retail Goods"
        }
    ],
    "sg:phone":"+1 514 384 4990",
    "sg:postcode":"H2C 1R2",
    "sg:province":"QC",
    "wof:name":"Pharmacie Jean Coutu",
    "wof:placetype":"venue"
},
  "geometry": {"coordinates":[-73.658607,45.559299],"type":"Point"}
}