{
  "type": "Feature",
  "properties": {
    "addr:full":"71 Rue Des Grands-Lacs Saint-Augustin-DE-Desmaures QC G3A 1T5",
    "addr:housenumber":"71",
    "addr:postcode":"g3a 1t5",
    "addr:street":"Rue Des Grands-Lacs",
    "iso:country":"CA",
    "sg:address":"71 Rue Des Grands-Lacs",
    "sg:city":"Saint-Augustin-DE-Desmaures",
    "sg:classifiers":[
        {
            "category":"Manufacturing",
            "subcategory":"Printing",
            "type":"Manufacturing & Wholesale Goods"
        }
    ],
    "sg:phone":"+1 418 878 9499",
    "sg:postcode":"G3A 1T5",
    "sg:province":"QC",
    "sg:tags":[
        "printer"
    ],
    "wof:name":"Imprimerie Sociale Inc",
    "wof:placetype":"venue"
},
  "geometry": {"coordinates":[-71.44799,46.750233],"type":"Point"}
}