{
  "type": "Feature",
  "properties": {
    "iso:country":"CA",
    "sg:address":"259 Traders Blvd E #4",
    "sg:city":"Mississauga",
    "sg:classifiers":[
        {
            "category":"Wholesale",
            "subcategory":"Machinery & Supplies",
            "type":"Manufacturing & Wholesale Goods"
        }
    ],
    "sg:phone":"+1 905 712 9292",
    "sg:postcode":"L4Z 2E5",
    "sg:province":"ON",
    "sg:tags":[
        "abrasive"
    ],
    "wof:name":"Industrial Abrasives Inc",
    "wof:placetype":"venue"
},
  "geometry": {"coordinates":[-79.6689,43.628059],"type":"Point"}
}