{
  "type": "Feature",
  "properties": {
    "addr:full":"320 Main St Shawville QC J0X 2Y0",
    "addr:housenumber":"320",
    "addr:postcode":"j0x 2y0",
    "addr:street":"Main St",
    "iso:country":"CA",
    "sg:address":"320 Main St",
    "sg:city":"Shawville",
    "sg:classifiers":[
        {
            "category":"Health Services",
            "subcategory":"Doctor",
            "type":"Services"
        }
    ],
    "sg:phone":"+1 819 647 2218",
    "sg:postcode":"J0X 2Y0",
    "sg:province":"QC",
    "sg:tags":[
        "physician",
        "surgeon"
    ],
    "wof:name":"O'Neill, Thomas MD",
    "wof:placetype":"venue"
},
  "geometry": {"coordinates":[-76.490585,45.603249],"type":"Point"}
}