{
  "type": "Feature",
  "properties": {
    "addr:full":"11425 61E Av Montreal QC H1C 2B7",
    "addr:housenumber":"11425",
    "addr:postcode":"h1c 2b7",
    "addr:street":"61E Av",
    "iso:country":"CA",
    "sg:address":"11425 61E Av",
    "sg:city":"Montreal",
    "sg:classifiers":[
        {
            "category":"Restaurant",
            "type":"Food & Drink"
        }
    ],
    "sg:phone":"+1 514 881 7253",
    "sg:postcode":"H1C 2B7",
    "sg:province":"QC",
    "wof:name":"Cantines Francine Laurencelle",
    "wof:placetype":"venue"
},
  "geometry": {"coordinates":[-73.553619,45.645725],"type":"Point"}
}