{
  "type": "Feature",
  "properties": {
    "addr:full":"164 Av Proulx Vanier QC G1M 1W7",
    "addr:postcode":"g1m 1w7",
    "addr:street":"164 Av Proulx",
    "iso:country":"CA",
    "sg:address":"164 Av Proulx",
    "sg:city":"Vanier",
    "sg:classifiers":[
        {
            "category":"Social Services",
            "type":"Services"
        }
    ],
    "sg:phone":"+1 418 683 5023",
    "sg:postcode":"G1M 1W7",
    "sg:province":"QC",
    "sg:tags":[
        "youth",
        "organization",
        "center"
    ],
    "wof:name":"Maison Des Jeunes Parenthese",
    "wof:placetype":"venue"
},
  "geometry": {"coordinates":[-71.2571029663,46.8138809204],"type":"Point"}
}