{
  "type": "Feature",
  "properties": {
    "iso:country":"CA",
    "sg:city":"North York",
    "sg:classifiers":[
        {
            "category":"Professional",
            "subcategory":"Business Services",
            "type":"Services"
        }
    ],
    "sg:phone":"+1 416 736 4359",
    "sg:postcode":"M3J 2M5",
    "sg:province":"ON",
    "sg:tags":[
        "auctioneer"
    ],
    "wof:name":"Active Auction CO",
    "wof:placetype":"venue"
},
  "geometry": {"coordinates":[-79.476791,43.776428],"type":"Point"}
}