{
  "type": "Feature",
  "properties": {
    "addr:full":"531 Rue Principale Saint-Amable QC J0L 1N0",
    "addr:housenumber":"531",
    "addr:postcode":"j0l 1n0",
    "addr:street":"Rue Principale",
    "iso:country":"CA",
    "sg:address":"531 Rue Principale",
    "sg:city":"Saint-Amable",
    "sg:classifiers":[
        {
            "category":"Health Services",
            "subcategory":"Doctor",
            "type":"Services"
        }
    ],
    "sg:phone":"+1 450 649 5050",
    "sg:postcode":"J0L 1N0",
    "sg:province":"QC",
    "sg:tags":[
        "dentist"
    ],
    "wof:name":"Centre Dentaire Familial",
    "wof:placetype":"venue"
},
  "geometry": {"coordinates":[-73.30633544920001,45.6427154541],"type":"Point"}
}