{
  "type": "Feature",
  "properties": {
    "iso:country":"CA",
    "sg:address":"2730 Ailsa Cres",
    "sg:city":"North Vancouver",
    "sg:classifiers":[
        {
            "category":"Professional",
            "subcategory":"Lawyer & Legal Services",
            "type":"Services"
        }
    ],
    "sg:phone":"+1 604 980 4069",
    "sg:postcode":"V7K 2B2",
    "sg:province":"BC",
    "sg:tags":[
        "attorney"
    ],
    "wof:name":"Weisberg, Fred",
    "wof:placetype":"venue"
},
  "geometry": {"coordinates":[-123.047684,49.334007],"type":"Point"}
}