{
  "type": "Feature",
  "properties": {
    "iso:country":"CA",
    "sg:address":"NW 21 13 11E",
    "sg:city":"Seven Sisters Falls",
    "sg:classifiers":[
        {
            "category":"Home & Garden",
            "subcategory":"Garden Supply",
            "type":"Retail Goods"
        }
    ],
    "sg:phone":"+1 204 348 2386",
    "sg:postcode":"R0E 1Y0",
    "sg:province":"MB",
    "sg:tags":[
        "bulb",
        "seed"
    ],
    "wof:name":"P R Farms",
    "wof:placetype":"venue"
},
  "geometry": {"coordinates":[-96.0297012329,50.1053543091],"type":"Point"}
}