{
  "type": "Feature",
  "properties": {
    "addr:full":"PO Box 546 STN Main Edmonton AB T5J 2K8",
    "addr:housenumber":"po",
    "addr:postcode":"t5j 2k8",
    "addr:street":"Box 546 Stn",
    "iso:country":"CA",
    "sg:address":"PO Box 546 STN Main",
    "sg:city":"Edmonton",
    "sg:classifiers":[
        {
            "category":"Professional",
            "subcategory":"Business Services",
            "type":"Services"
        }
    ],
    "sg:phone":"+1 780 434 8384",
    "sg:postcode":"T5J 2K8",
    "sg:province":"AB",
    "sg:tags":[
        "translator",
        "interpreter"
    ],
    "wof:name":"Association of Translators",
    "wof:placetype":"venue"
},
  "geometry": {"coordinates":[-113.49037199999999,53.546219],"type":"Point"}
}