{
  "type": "Feature",
  "properties": {
    "iso:country":"CA",
    "sg:address":"PO Box 546 STN Main",
    "sg:city":"Edmonton",
    "sg:classifiers":[
        {
            "category":"Professional",
            "subcategory":"Business Services",
            "type":"Services"
        }
    ],
    "sg:phone":"+1 780 434 8384",
    "sg:postcode":"T5J 2K8",
    "sg:province":"AB",
    "sg:tags":[
        "translator",
        "interpreter"
    ],
    "wof:name":"Association of Translators",
    "wof:placetype":"venue"
},
  "geometry": {"coordinates":[-113.490372,53.546219],"type":"Point"}
}