{
  "type": "Feature",
  "properties": {
    "iso:country":"CA",
    "sg:address":"3894 Russell Rd",
    "sg:city":"Gloucester",
    "sg:classifiers":[
        {
            "category":"Building & Trades",
            "subcategory":"Landscaping Services",
            "type":"Services"
        }
    ],
    "sg:phone":"+1 613 521 8829",
    "sg:postcode":"K1G 3N2",
    "sg:province":"ON",
    "sg:tags":[
        "stone",
        "interlocking",
        "landscape",
        "contractor"
    ],
    "wof:name":"Mac Kinnon Reid & Assoc",
    "wof:placetype":"venue"
},
  "geometry": {"coordinates":[-75.581841,45.396011],"type":"Point"}
}