{
  "type": "Feature",
  "properties": {
    "addr:full":"North York ON M6A 3B5",
    "addr:postcode":"m6a 3b5",
    "iso:country":"CA",
    "sg:city":"North York",
    "sg:classifiers":[
        {
            "category":"Shopping",
            "type":"Retail Goods"
        }
    ],
    "sg:phone":"+1 416 787 8450",
    "sg:postcode":"M6A 3B5",
    "sg:province":"ON",
    "sg:tags":[
        "hearing",
        "equipment",
        "supply",
        "impaired"
    ],
    "wof:name":"Hearing Solutions",
    "wof:placetype":"venue"
},
  "geometry": {"coordinates":[-79.4579238892,43.7135772705],"type":"Point"}
}