{
  "type": "Feature",
  "properties": {
    "addr:full":"880 Colborne Rd #101 Sarnia ON N7V 3K3",
    "addr:housenumber":"880",
    "addr:postcode":"n7v 3k3",
    "addr:street":"Colborne Rd # 101",
    "iso:country":"CA",
    "sg:address":"880 Colborne Rd #101",
    "sg:city":"Sarnia",
    "sg:classifiers":[
        {
            "category":"Real Estate",
            "subcategory":"Real Estate Operator",
            "type":"Services"
        }
    ],
    "sg:phone":"+1 519 344 6467",
    "sg:postcode":"N7V 3K3",
    "sg:province":"ON",
    "sg:tags":[
        "apartment"
    ],
    "wof:name":"Regal Towers",
    "wof:placetype":"venue"
},
  "geometry": {"coordinates":[-82.3886642456,42.98802948],"type":"Point"}
}