{
  "type": "Feature",
  "properties": {
    "iso:country":"CA",
    "sg:address":"5000 Av Dornal",
    "sg:city":"Montreal",
    "sg:classifiers":[
        {
            "category":"Shopping",
            "type":"Retail Goods"
        }
    ],
    "sg:phone":"+1 514 343 9633",
    "sg:postcode":"H3W 1W2",
    "sg:province":"QC",
    "sg:tags":[
        "art",
        "gallery",
        "dealer"
    ],
    "wof:name":"Shayna Laing Art Intl Inc",
    "wof:placetype":"venue"
},
  "geometry": {"coordinates":[-73.627792,45.486423],"type":"Point"}
}