{
  "type": "Feature",
  "properties": {
    "addr:full":"Estevan SK S4A 2S7",
    "addr:postcode":"s4a 2s7",
    "iso:country":"CA",
    "sg:city":"Estevan",
    "sg:classifiers":[
        {
            "category":"Health Services",
            "subcategory":"Doctor",
            "type":"Services"
        }
    ],
    "sg:phone":"+1 306 634 2661",
    "sg:postcode":"S4A 2S7",
    "sg:province":"SK",
    "sg:tags":[
        "physician",
        "clinic",
        "surgeon"
    ],
    "wof:name":"Estevan Medical Clinic",
    "wof:placetype":"venue"
},
  "geometry": {"coordinates":[-103.011512756,49.1511116028],"type":"Point"}
}