{
  "type": "Feature",
  "properties": {
    "addr:full":"87 Av Mcculloch Outremont QC H2V 3L8",
    "addr:postcode":"h2v 3l8",
    "addr:street":"87 Av Mcculloch",
    "iso:country":"CA",
    "sg:address":"87 Av Mcculloch",
    "sg:city":"Outremont",
    "sg:classifiers":[
        {
            "category":"Professional",
            "subcategory":"Art Services",
            "type":"Services"
        }
    ],
    "sg:phone":"+1 514 495 4717",
    "sg:postcode":"H2V 3L8",
    "sg:province":"QC",
    "sg:tags":[
        "graphic",
        "designer"
    ],
    "wof:name":"Roy, Daniel",
    "wof:placetype":"venue"
},
  "geometry": {"coordinates":[-73.59934199999999,45.513847],"type":"Point"}
}