{
  "type": "Feature",
  "properties": {
    "addr:full":"Martensville SK S0K 2T0",
    "addr:postcode":"s0k 2t0",
    "iso:country":"CA",
    "sg:city":"Martensville",
    "sg:classifiers":[
        {
            "category":"Sports & Exercise",
            "subcategory":"Golf",
            "type":"Entertainment"
        }
    ],
    "sg:phone":"+1 306 934 3958",
    "sg:postcode":"S0K 2T0",
    "sg:province":"SK",
    "sg:tags":[
        "course"
    ],
    "wof:name":"Martensville Golf Course",
    "wof:placetype":"venue"
},
  "geometry": {"coordinates":[-106.67073059099999,52.2962646484],"type":"Point"}
}