{
  "type": "Feature",
  "properties": {
    "iso:country":"CA",
    "sg:address":"109 Rte 271 S",
    "sg:city":"Saint-Ephrem-DE-Beauce",
    "sg:classifiers":[
        {
            "category":"Manufacturing",
            "subcategory":"Building Materials",
            "type":"Manufacturing & Wholesale Goods"
        }
    ],
    "sg:phone":"+1 418 484 2978",
    "sg:postcode":"G0M 1R0",
    "sg:province":"QC",
    "sg:tags":[
        "truss"
    ],
    "wof:name":"Poutrelles Modernes Ltee",
    "wof:placetype":"venue"
},
  "geometry": {"coordinates":[-70.9426651001,46.0663299561],"type":"Point"}
}