{
  "type": "Feature",
  "properties": {
    "iso:country":"CA",
    "sg:city":"Vancouver",
    "sg:classifiers":[
        {
            "category":"Wholesale",
            "subcategory":"Furniture",
            "type":"Manufacturing & Wholesale Goods"
        }
    ],
    "sg:phone":"+1 604 683 8300",
    "sg:postcode":"V6E 2M6",
    "sg:province":"BC",
    "wof:name":"Herman Miller Workplace Rsrc",
    "wof:placetype":"venue"
},
  "geometry": {"coordinates":[-123.118797,49.28727],"type":"Point"}
}