{
  "type": "Feature",
  "properties": {
    "addr:full":"Kipling SK S0G 2S0",
    "addr:postcode":"s0g 2s0",
    "iso:country":"CA",
    "sg:city":"Kipling",
    "sg:classifiers":[
        {
            "category":"Food & Beverages",
            "subcategory":"Groceries & Convenience Stores",
            "type":"Retail Goods"
        }
    ],
    "sg:phone":"+1 306 736 2315",
    "sg:postcode":"S0G 2S0",
    "sg:province":"SK",
    "sg:tags":[
        "grocer"
    ],
    "wof:name":"Kipling CO-Operative Assn Ltd",
    "wof:placetype":"venue"
},
  "geometry": {"coordinates":[-102.63407135,50.1035690308],"type":"Point"}
}