{
  "type": "Feature",
  "properties": {
    "addr:full":"1804 Broadway W Vancouver BC V6J 1Y9",
    "addr:housenumber":"1804",
    "addr:postcode":"v6j 1y9",
    "addr:street":"Broadway W",
    "iso:country":"CA",
    "sg:address":"1804 Broadway W",
    "sg:city":"Vancouver",
    "sg:classifiers":[
        {
            "category":"Professional",
            "subcategory":"Detective & Security Services",
            "type":"Services"
        }
    ],
    "sg:phone":"+1 604 731 6662",
    "sg:postcode":"V6J 1Y9",
    "sg:province":"BC",
    "sg:tags":[
        "investigator"
    ],
    "wof:name":"Spy Store",
    "wof:placetype":"venue"
},
  "geometry": {"coordinates":[-123.146080017,49.2635993958],"type":"Point"}
}