{
  "type": "Feature",
  "properties": {
    "iso:country":"CA",
    "sg:address":"12117 100 St",
    "sg:city":"Grande Prairie",
    "sg:classifiers":[
        {
            "category":"Restaurant",
            "type":"Food & Drink"
        }
    ],
    "sg:phone":"+1 780 532 0310",
    "sg:postcode":"T8V 4H1",
    "sg:province":"AB",
    "wof:name":"Boston Pizza",
    "wof:placetype":"venue"
},
  "geometry": {"coordinates":[-118.793968201,55.1899337769],"type":"Point"}
}