{
  "type": "Feature",
  "properties": {
    "addr:full":"Swan Hills AB T0G 2C0",
    "addr:postcode":"t0g 2c0",
    "iso:country":"CA",
    "sg:city":"Swan Hills",
    "sg:classifiers":[
        {
            "category":"Retail",
            "subcategory":"Repair Shop",
            "type":"Services"
        }
    ],
    "sg:phone":"+1 780 333 2122",
    "sg:postcode":"T0G 2C0",
    "sg:province":"AB",
    "sg:tags":[
        "welding"
    ],
    "wof:name":"Eckert's Welding & Maintenance",
    "wof:placetype":"venue"
},
  "geometry": {"coordinates":[-115.396545,54.711033],"type":"Point"}
}