{
  "type": "Feature",
  "properties": {
    "addr:full":"439 Government St Dryden ON P8N 2P4",
    "addr:housenumber":"439",
    "addr:postcode":"p8n 2p4",
    "addr:street":"Government St",
    "iso:country":"CA",
    "sg:address":"439 Government St",
    "sg:city":"Dryden",
    "sg:classifiers":[
        {
            "category":"Health Services",
            "subcategory":"Chiropractor",
            "type":"Services"
        }
    ],
    "sg:phone":"+1 807 223 8833",
    "sg:postcode":"P8N 2P4",
    "sg:province":"ON",
    "wof:name":"Mc Leod Chiropractic",
    "wof:placetype":"venue"
},
  "geometry": {"coordinates":[-92.8292388916,49.7862930298],"type":"Point"}
}