{
  "type": "Feature",
  "properties": {
    "addr:full":"Churchill Falls NL A0R 1A0",
    "addr:postcode":"a0r 1a0",
    "addr:street":"Churchill",
    "iso:country":"CA",
    "sg:city":"Churchill Falls",
    "sg:classifiers":[
        {
            "category":"Government",
            "subcategory":"Police Station",
            "type":"Public Place"
        }
    ],
    "sg:phone":"+1 709 925 3524",
    "sg:postcode":"A0R 1A0",
    "sg:province":"NL",
    "sg:tags":[
        "department"
    ],
    "wof:name":"Churchill Falls Police Dept",
    "wof:placetype":"venue"
},
  "geometry": {"coordinates":[-64.00151824949999,53.5303649902],"type":"Point"}
}