{
  "type": "Feature",
  "properties": {
    "addr:full":"70 Church St W Delhi ON N4B 1V7",
    "addr:housenumber":"70",
    "addr:postcode":"n4b 1v7",
    "addr:street":"Church St W",
    "iso:country":"CA",
    "sg:address":"70 Church St W",
    "sg:city":"Delhi",
    "sg:classifiers":[
        {
            "category":"Insurance",
            "subcategory":"Insurance Agent",
            "type":"Services"
        }
    ],
    "sg:phone":"+1 519 875 2999",
    "sg:postcode":"N4B 1V7",
    "sg:province":"ON",
    "wof:name":"Thournout Insurance Brokers",
    "wof:placetype":"venue"
},
  "geometry": {"coordinates":[-80.4961853027,42.8537483215],"type":"Point"}
}