{
  "type": "Feature",
  "properties": {
    "addr:full":"Notre-Dame-Du-Laus QC J0X 2M0",
    "addr:postcode":"j0x 2m0",
    "iso:country":"CA",
    "sg:city":"Notre-Dame-Du-Laus",
    "sg:classifiers":[
        {
            "category":"Home & Garden",
            "subcategory":"Building Materials",
            "type":"Retail Goods"
        }
    ],
    "sg:phone":"+1 819 767 5005",
    "sg:postcode":"J0X 2M0",
    "sg:province":"QC",
    "wof:name":"Patio Du Laus",
    "wof:placetype":"venue"
},
  "geometry": {"coordinates":[-75.62627410890001,46.0780525208],"type":"Point"}
}