{
  "type": "Feature",
  "properties": {
    "addr:full":"327 Knowlton Rd Knowlton QC J0E 1V0",
    "addr:housenumber":"327",
    "addr:postcode":"j0e 1v0",
    "addr:street":"Knowlton Rd",
    "iso:country":"CA",
    "sg:address":"327 Knowlton Rd",
    "sg:city":"Knowlton",
    "sg:classifiers":[
        {
            "category":"Manufacturing",
            "subcategory":"Printing",
            "type":"Manufacturing & Wholesale Goods"
        }
    ],
    "sg:phone":"+1 450 242 2400",
    "sg:postcode":"J0E 1V0",
    "sg:province":"QC",
    "sg:tags":[
        "newspaper"
    ],
    "wof:name":"Tempo",
    "wof:placetype":"venue"
},
  "geometry": {"coordinates":[-72.513474,45.216503],"type":"Point"}
}