{
  "type": "Feature",
  "properties": {
    "iso:country":"CA",
    "sg:address":"74 Industrial Dr",
    "sg:city":"Hartland",
    "sg:classifiers":[
        {
            "category":"Autos & Motor Vehicles",
            "subcategory":"Auto Supplies",
            "type":"Retail Goods"
        }
    ],
    "sg:phone":"+1 506 375 4200",
    "sg:postcode":"E7P 2G8",
    "sg:province":"NB",
    "sg:tags":[
        "repairing",
        "automobile"
    ],
    "wof:name":"Valley Car Care & Tire Ltd",
    "wof:placetype":"venue"
},
  "geometry": {"coordinates":[-67.5195007324,46.297290802],"type":"Point"}
}