{
  "type": "Feature",
  "properties": {
    "addr:full":"492 Springbank Dr London ON N6J 1H1",
    "addr:housenumber":"492",
    "addr:postcode":"n6j 1h1",
    "addr:street":"Springbank Dr",
    "iso:country":"CA",
    "sg:address":"492 Springbank Dr",
    "sg:city":"London",
    "sg:classifiers":[
        {
            "category":"Real Estate",
            "subcategory":"Real Estate Operator",
            "type":"Services"
        }
    ],
    "sg:phone":"+1 519 472 2032",
    "sg:postcode":"N6J 1H1",
    "sg:province":"ON",
    "sg:tags":[
        "apartment"
    ],
    "wof:name":"Springbank Manor Apartments",
    "wof:placetype":"venue"
},
  "geometry": {"coordinates":[-81.28740692140001,42.9661865234],"type":"Point"}
}