{
  "type": "Feature",
  "properties": {
    "addr:full":"Waterloo ON N2J 4V2",
    "addr:postcode":"n2j 4v2",
    "iso:country":"CA",
    "sg:city":"Waterloo",
    "sg:classifiers":[
        {
            "category":"Personal",
            "subcategory":"Beauty Salon",
            "type":"Services"
        }
    ],
    "sg:phone":"+1 519 746 7171",
    "sg:postcode":"N2J 4V2",
    "sg:province":"ON",
    "wof:name":"Chameleon Hair Studio & Spa",
    "wof:placetype":"venue"
},
  "geometry": {"coordinates":[-80.52526899999999,43.47665],"type":"Point"}
}