{
  "type": "Feature",
  "properties": {
    "addr:full":"4059 New St Burlington ON L7L 1S8",
    "addr:housenumber":"4059",
    "addr:postcode":"l7l 1s8",
    "addr:street":"New St",
    "iso:country":"CA",
    "sg:address":"4059 New St",
    "sg:city":"Burlington",
    "sg:classifiers":[
        {
            "category":"Cinema",
            "subcategory":"Movie Rental",
            "type":"Entertainment"
        }
    ],
    "sg:phone":"+1 905 681 7551",
    "sg:postcode":"L7L 1S8",
    "sg:province":"ON",
    "sg:tags":[
        "leasing",
        "video",
        "disc",
        "tape"
    ],
    "wof:name":"Rogers Video",
    "wof:placetype":"venue"
},
  "geometry": {"coordinates":[-79.76805899999999,43.354385],"type":"Point"}
}