{
  "type": "Feature",
  "properties": {
    "addr:full":"180 123E Rue Saint-Georges QC G5Y 2Z1",
    "addr:housenumber":"180",
    "addr:postcode":"g5y 2z1",
    "addr:street":"123E Rue",
    "iso:country":"CA",
    "sg:address":"180 123E Rue",
    "sg:city":"Saint-Georges",
    "sg:classifiers":[
        {
            "category":"Shopping",
            "subcategory":"Jewelry",
            "type":"Retail Goods"
        }
    ],
    "sg:phone":"+1 418 228 8465",
    "sg:postcode":"G5Y 2Z1",
    "sg:province":"QC",
    "sg:tags":[
        "jeweler"
    ],
    "wof:name":"Bijouterie Du Patrimoine",
    "wof:placetype":"venue"
},
  "geometry": {"coordinates":[-70.67115020750001,46.1233482361],"type":"Point"}
}