{
  "type": "Feature",
  "properties": {
    "addr:full":"Gravenhurst ON P1P 1X2",
    "addr:postcode":"p1p 1x2",
    "iso:country":"CA",
    "sg:city":"Gravenhurst",
    "sg:classifiers":[
        {
            "category":"Taxi",
            "type":"Transportation"
        }
    ],
    "sg:phone":"+1 705 687 2246",
    "sg:postcode":"P1P 1X2",
    "sg:province":"ON",
    "sg:tags":[
        "taxicab"
    ],
    "wof:name":"Gravenhurst Taxi",
    "wof:placetype":"venue"
},
  "geometry": {"coordinates":[-79.3739929199,44.9201583862],"type":"Point"}
}