{
  "type": "Feature",
  "properties": {
    "iso:country":"CA",
    "sg:city":"Concord",
    "sg:classifiers":[
        {
            "category":"Home & Garden",
            "subcategory":"Household Appliances",
            "type":"Retail Goods"
        }
    ],
    "sg:phone":"+1 416 665 6951",
    "sg:postcode":"L4K 2S9",
    "sg:province":"ON",
    "wof:name":"York County Heating & Air Cond",
    "wof:placetype":"venue"
},
  "geometry": {"coordinates":[-79.494705,43.801533],"type":"Point"}
}