{
  "type": "Feature",
  "properties": {
    "iso:country":"CA",
    "sg:address":"1210 Meridian Rd NE",
    "sg:city":"Calgary",
    "sg:classifiers":[
        {
            "category":"Retail",
            "subcategory":"Auto Rental",
            "type":"Services"
        }
    ],
    "sg:phone":"+1 403 273 6800",
    "sg:postcode":"T2A 2N9",
    "sg:province":"AB",
    "sg:tags":[
        "renting",
        "automobile"
    ],
    "wof:name":"Rent-A-Wreck",
    "wof:placetype":"venue"
},
  "geometry": {"coordinates":[-114.000770569,51.0636405945],"type":"Point"}
}