{
  "type": "Feature",
  "properties": {
    "addr:full":"800 Ch St-Gerard Sainte-Marie-Salome QC J0K 2Z0",
    "addr:housenumber":"800",
    "addr:postcode":"j0k 2z0",
    "addr:street":"Ch St-Gerard Sainte-Marie-Salome",
    "iso:country":"CA",
    "sg:address":"800 Ch St-Gerard",
    "sg:city":"Sainte-Marie-Salome",
    "sg:classifiers":[
        {
            "category":"Wholesale",
            "subcategory":"Auto Parts",
            "type":"Manufacturing & Wholesale Goods"
        }
    ],
    "sg:phone":"+1 450 839 3002",
    "sg:postcode":"J0K 2Z0",
    "sg:province":"QC",
    "sg:tags":[
        "automobile",
        "rebuilt",
        "dealer"
    ],
    "wof:name":"Lepage Auto Enrg",
    "wof:placetype":"venue"
},
  "geometry": {"coordinates":[-73.464157,45.92281],"type":"Point"}
}