{
  "type": "Feature",
  "properties": {
    "iso:country":"CA",
    "sg:address":"297 Montee Des Pionniers",
    "sg:city":"Lachenaie",
    "sg:classifiers":[
        {
            "category":"Shopping",
            "subcategory":"Pharmacy",
            "type":"Retail Goods"
        }
    ],
    "sg:phone":"+1 450 582 1817",
    "sg:postcode":"J6V 1H4",
    "sg:province":"QC",
    "wof:name":"Uniprix P Bergeron",
    "wof:placetype":"venue"
},
  "geometry": {"coordinates":[-73.5124206543,45.7118759155],"type":"Point"}
}