{
  "type": "Feature",
  "properties": {
    "addr:full":"85 Ellesmere Rd Scarborough ON M1R 4B7",
    "addr:housenumber":"85",
    "addr:postcode":"m1r 4b7",
    "addr:street":"Ellesmere Rd",
    "iso:country":"CA",
    "sg:address":"85 Ellesmere Rd",
    "sg:city":"Scarborough",
    "sg:classifiers":[
        {
            "category":"Professional",
            "subcategory":"Accounting & Tax Preparation",
            "type":"Services"
        }
    ],
    "sg:phone":"+1 416 444 7505",
    "sg:postcode":"M1R 4B7",
    "sg:province":"ON",
    "sg:tags":[
        "return",
        "filing"
    ],
    "wof:name":"Liberty Tax Svc",
    "wof:placetype":"venue"
},
  "geometry": {"coordinates":[-79.313087,43.758244],"type":"Point"}
}