{
  "type": "Feature",
  "properties": {
    "addr:full":"1168 Seymour St Vancouver BC V6B 3N3",
    "addr:housenumber":"1168",
    "addr:postcode":"bc v6b 3n3",
    "addr:street":"Seymour St",
    "iso:country":"CA",
    "sg:address":"1168 Seymour St",
    "sg:city":"Vancouver",
    "sg:classifiers":[
        {
            "category":"Manufacturing",
            "subcategory":"Printing",
            "type":"Manufacturing & Wholesale Goods"
        }
    ],
    "sg:phone":"+1 604 684 3361",
    "sg:postcode":"V6B 3N3",
    "sg:province":"BC",
    "sg:tags":[
        "engraver"
    ],
    "wof:name":"North West Graphics Ltd",
    "wof:placetype":"venue"
},
  "geometry": {"coordinates":[-123.124527,49.276791],"type":"Point"}
}