{
  "type": "Feature",
  "properties": {
    "addr:full":"940 Ch Olivier Saint-Nicolas QC G7A 2N1",
    "addr:housenumber":"940",
    "addr:postcode":"g7a 2n1",
    "addr:street":"Ch Olivier",
    "iso:country":"CA",
    "sg:address":"940 Ch Olivier",
    "sg:city":"Saint-Nicolas",
    "sg:classifiers":[
        {
            "category":"Autos & Motor Vehicles",
            "subcategory":"Recreational Vehicle Sales",
            "type":"Retail Goods"
        }
    ],
    "sg:phone":"+1 418 831 3080",
    "sg:postcode":"G7A 2N1",
    "sg:province":"QC",
    "wof:name":"Roulottes Chaudiere Inc",
    "wof:placetype":"venue"
},
  "geometry": {"coordinates":[-71.32377624510001,46.6869773865],"type":"Point"}
}