{
  "type": "Feature",
  "properties": {
    "addr:full":"1314 11th Ave Regina SK S4P 0G7",
    "addr:housenumber":"1314",
    "addr:postcode":"s4p 0g7",
    "addr:street":"11Th Ave",
    "iso:country":"CA",
    "sg:address":"1314 11th Ave",
    "sg:city":"Regina",
    "sg:classifiers":[
        {
            "category":"Government",
            "subcategory":"Office",
            "type":"Public Place"
        }
    ],
    "sg:phone":"+1 306 780 5530",
    "sg:postcode":"S4P 0G7",
    "sg:province":"SK",
    "wof:name":"Oskana Centre",
    "wof:placetype":"venue"
},
  "geometry": {"coordinates":[-104.599441528,50.4505691528],"type":"Point"}
}