{
  "type": "Feature",
  "properties": {
    "addr:full":"Rainbow Lake AB T0H 2Y0",
    "addr:postcode":"t0h 2y0",
    "addr:street":"Rainbow",
    "iso:country":"CA",
    "sg:city":"Rainbow Lake",
    "sg:classifiers":[
        {
            "category":"Health Services",
            "subcategory":"Doctor",
            "type":"Services"
        }
    ],
    "sg:phone":"+1 780 956 2344",
    "sg:postcode":"T0H 2Y0",
    "sg:province":"AB",
    "sg:tags":[
        "dentist"
    ],
    "wof:name":"Rainbow Lake Dental Clinic",
    "wof:placetype":"venue"
},
  "geometry": {"coordinates":[-119.410247803,58.4995727539],"type":"Point"}
}