{
  "type": "Feature",
  "properties": {
    "addr:full":"1111 Tristar Dr #4B Mississauga ON L5T 1W5",
    "addr:housenumber":"1111",
    "addr:postcode":"l5t 1w5",
    "addr:street":"Tristar Dr # 4B",
    "iso:country":"CA",
    "sg:address":"1111 Tristar Dr #4B",
    "sg:city":"Mississauga",
    "sg:classifiers":[
        {
            "category":"Manufacturing",
            "subcategory":"Paper Products",
            "type":"Manufacturing & Wholesale Goods"
        }
    ],
    "sg:phone":"+1 905 795 0144",
    "sg:postcode":"L5T 1W5",
    "sg:province":"ON",
    "sg:tags":[
        "converter"
    ],
    "wof:name":"Regent Paper Converters Inc",
    "wof:placetype":"venue"
},
  "geometry": {"coordinates":[-79.6657714844,43.6547012329],"type":"Point"}
}