{
  "type": "Feature",
  "properties": {
    "addr:full":"151 Esna Park Dr # 16 Markham ON L3R 3B1",
    "addr:housenumber":"151",
    "addr:postcode":"l3r 3b1",
    "addr:street":"Esna Park Dr # 16",
    "iso:country":"CA",
    "sg:address":"151 Esna Park Dr # 16",
    "sg:city":"Markham",
    "sg:classifiers":[
        {
            "category":"Health Services",
            "subcategory":"Medical Lab",
            "type":"Services"
        }
    ],
    "sg:phone":"+1 905 477 5388",
    "sg:postcode":"L3R 3B1",
    "sg:province":"ON",
    "sg:tags":[
        "laboratory"
    ],
    "wof:name":"Club Dental Laboratories",
    "wof:placetype":"venue"
},
  "geometry": {"coordinates":[-79.339142,43.826672],"type":"Point"}
}