{
  "type": "Feature",
  "properties": {
    "addr:full":"Burnaby BC V5C 6P8",
    "addr:postcode":"v5c 6p8",
    "iso:country":"CA",
    "sg:city":"Burnaby",
    "sg:classifiers":[
        {
            "category":"Professional",
            "subcategory":"Computer Services",
            "type":"Services"
        }
    ],
    "sg:phone":"+1 604 205 5385",
    "sg:postcode":"V5C 6P8",
    "sg:province":"BC",
    "sg:tags":[
        "consultant",
        "designer"
    ],
    "wof:name":"Codex Technologies Inc",
    "wof:placetype":"venue"
},
  "geometry": {"coordinates":[-123.016693,49.264172],"type":"Point"}
}