{
  "type": "Feature",
  "properties": {
    "iso:country":"CA",
    "sg:address":"1200 5th Ave",
    "sg:city":"Valemount",
    "sg:classifiers":[
        {
            "category":"Food & Beverages",
            "subcategory":"Groceries & Convenience Stores",
            "type":"Retail Goods"
        }
    ],
    "sg:phone":"+1 250 566 4415",
    "sg:postcode":"V0E 2Z0",
    "sg:province":"BC",
    "sg:tags":[
        "grocer"
    ],
    "wof:name":"Shopeasy",
    "wof:placetype":"venue"
},
  "geometry": {"coordinates":[-119.25743866000001,52.8321075439],"type":"Point"}
}