{
  "type": "Feature",
  "properties": {
    "addr:full":"6557 Hart Hwy Prince George BC V2K 3A4",
    "addr:housenumber":"6557",
    "addr:postcode":"v2k 3a4",
    "addr:street":"Hart Hwy",
    "iso:country":"CA",
    "sg:address":"6557 Hart Hwy",
    "sg:city":"Prince George",
    "sg:classifiers":[
        {
            "category":"Personal",
            "subcategory":"Beauty Salon",
            "type":"Services"
        }
    ],
    "sg:phone":"+1 250 962 9262",
    "sg:postcode":"V2K 3A4",
    "sg:province":"BC",
    "wof:name":"Trend Setters Hair Studio",
    "wof:placetype":"venue"
},
  "geometry": {"coordinates":[-122.78610229500001,53.9889602661],"type":"Point"}
}