{
  "type": "Feature",
  "properties": {
    "iso:country":"CA",
    "sg:city":"Etobicoke",
    "sg:classifiers":[
        {
            "category":"Health Services",
            "subcategory":"Optometrist",
            "type":"Services"
        }
    ],
    "sg:phone":"+1 416 695 8206",
    "sg:postcode":"M9C 1B8",
    "sg:province":"ON",
    "wof:name":"Martin Traynor & Assoc",
    "wof:placetype":"venue"
},
  "geometry": {"coordinates":[-79.561203,43.610424],"type":"Point"}
}