{
  "type": "Feature",
  "properties": {
    "iso:country":"CA",
    "sg:address":"1330 Kingsway",
    "sg:city":"Vancouver",
    "sg:classifiers":[
        {
            "category":"Restaurant",
            "type":"Food & Drink"
        }
    ],
    "sg:phone":"+1 604 874 6969",
    "sg:postcode":"V5V 3E4",
    "sg:province":"BC",
    "wof:name":"Cheo Leo",
    "wof:placetype":"venue"
},
  "geometry": {"coordinates":[-123.077423,49.250668],"type":"Point"}
}