{
  "type": "Feature",
  "properties": {
    "addr:full":"2414 Vanier Dr Prince George BC V2N 1T7",
    "addr:housenumber":"2414",
    "addr:postcode":"v2n 1t7",
    "addr:street":"Vanier Dr",
    "iso:country":"CA",
    "sg:address":"2414 Vanier Dr",
    "sg:city":"Prince George",
    "sg:classifiers":[
        {
            "category":"Organizations",
            "subcategory":"Religious Organization",
            "type":"Services"
        }
    ],
    "sg:phone":"+1 250 563 2015",
    "sg:postcode":"V2N 1T7",
    "sg:province":"BC",
    "sg:tags":[
        "church"
    ],
    "wof:name":"Ukrainian St George's Catholic",
    "wof:placetype":"venue"
},
  "geometry": {"coordinates":[-122.78671300000001,53.899246],"type":"Point"}
}