{
  "type": "Feature",
  "properties": {
    "iso:country":"CA",
    "sg:address":"67 Wolverleigh Blvd",
    "sg:city":"Toronto",
    "sg:classifiers":[
        {
            "category":"Retail",
            "subcategory":"Repair Shop",
            "type":"Services"
        }
    ],
    "sg:phone":"+1 416 466 9619",
    "sg:postcode":"M4J 1R6",
    "sg:province":"ON",
    "sg:tags":[
        "instrument",
        "musical"
    ],
    "wof:name":"Davis, Philip",
    "wof:placetype":"venue"
},
  "geometry": {"coordinates":[-79.32810211180001,43.6840019226],"type":"Point"}
}