{
  "type": "Feature",
  "properties": {
    "addr:full":"251 Amber St Markham ON L3R 3J7",
    "addr:housenumber":"251",
    "addr:postcode":"l3r 3j7",
    "addr:street":"Amber St",
    "iso:country":"CA",
    "sg:address":"251 Amber St",
    "sg:city":"Markham",
    "sg:classifiers":[
        {
            "category":"Building & Trades",
            "subcategory":"Electrical",
            "type":"Services"
        }
    ],
    "sg:phone":"+1 905 477 0220",
    "sg:postcode":"L3R 3J7",
    "sg:province":"ON",
    "sg:tags":[
        "electric",
        "contractor"
    ],
    "wof:name":"Brothers & Wright Electrical",
    "wof:placetype":"venue"
},
  "geometry": {"coordinates":[-79.334129,43.827469],"type":"Point"}
}