{
  "type": "Feature",
  "properties": {
    "iso:country":"CA",
    "sg:address":"1104 Av Olier-Payette",
    "sg:city":"Laval",
    "sg:classifiers":[
        {
            "category":"Health Services",
            "subcategory":"Doctor",
            "type":"Services"
        }
    ],
    "sg:phone":"+1 450 628 8400",
    "sg:postcode":"H7L 5L2",
    "sg:province":"QC",
    "sg:tags":[
        "physician",
        "surgeon"
    ],
    "wof:name":"Muller Schneidesch, Mireille DO",
    "wof:placetype":"venue"
},
  "geometry": {"coordinates":[-73.775391,45.622452],"type":"Point"}
}