{
  "type": "Feature",
  "properties": {
    "addr:full":"56 Ontario St Burks Falls ON P0A 1C0",
    "addr:housenumber":"56",
    "addr:postcode":"p0a 1c0",
    "addr:street":"Ontario St",
    "iso:country":"CA",
    "sg:address":"56 Ontario St",
    "sg:city":"Burks Falls",
    "sg:classifiers":[
        {
            "category":"Real Estate",
            "subcategory":"Real Estate Agent",
            "type":"Services"
        }
    ],
    "sg:phone":"+1 705 382 2014",
    "sg:postcode":"P0A 1C0",
    "sg:province":"ON",
    "wof:name":"Bowes & Cocks Ltd",
    "wof:placetype":"venue"
},
  "geometry": {"coordinates":[-83.5637512207,46.2533493042],"type":"Point"}
}