{
  "type": "Feature",
  "properties": {
    "iso:country":"CA",
    "sg:address":"56 Ontario St",
    "sg:city":"Burks Falls",
    "sg:classifiers":[
        {
            "category":"Real Estate",
            "subcategory":"Real Estate Agent",
            "type":"Services"
        }
    ],
    "sg:phone":"+1 705 382 2014",
    "sg:postcode":"P0A 1C0",
    "sg:province":"ON",
    "wof:name":"Bowes & Cocks Ltd",
    "wof:placetype":"venue"
},
  "geometry": {"coordinates":[-83.5637512207,46.2533493042],"type":"Point"}
}