{
  "type": "Feature",
  "properties": {
    "addr:full":"104 Philip Ave North Vancouver BC V7P 2V6",
    "addr:housenumber":"104",
    "addr:postcode":"v7p 2v6",
    "addr:street":"Philip Ave",
    "iso:country":"CA",
    "sg:address":"104 Philip Ave",
    "sg:city":"North Vancouver",
    "sg:classifiers":[
        {
            "category":"Shopping",
            "type":"Retail Goods"
        }
    ],
    "sg:phone":"+1 604 985 0057",
    "sg:postcode":"V7P 2V6",
    "sg:province":"BC",
    "sg:tags":[
        "spa",
        "hot",
        "tub"
    ],
    "wof:name":"Crystalview Pool & Spa",
    "wof:placetype":"venue"
},
  "geometry": {"coordinates":[-123.113449,49.316738],"type":"Point"}
}