{
  "type": "Feature",
  "properties": {
    "addr:full":"13717 Golf Course Rd Charlie Lake BC V0C 1H0",
    "addr:housenumber":"13717",
    "addr:postcode":"bc v0c 1h0",
    "addr:street":"Golf Course Rd",
    "iso:country":"CA",
    "sg:address":"13717 Golf Course Rd",
    "sg:city":"Charlie Lake",
    "sg:classifiers":[
        {
            "category":"Recreation",
            "type":"Entertainment"
        }
    ],
    "sg:phone":"+1 250 785 5566",
    "sg:postcode":"V0C 1H0",
    "sg:province":"BC",
    "sg:tags":[
        "course",
        "golf"
    ],
    "wof:name":"Lake Point Golf & Country Club",
    "wof:placetype":"venue"
},
  "geometry": {"coordinates":[-120.964912415,56.2806358337],"type":"Point"}
}