{
  "type": "Feature",
  "properties": {
    "iso:country":"CA",
    "sg:address":"140 Orion Pl",
    "sg:city":"Cambridge",
    "sg:classifiers":[
        {
            "category":"Manufacturing",
            "subcategory":"Metals",
            "type":"Manufacturing & Wholesale Goods"
        }
    ],
    "sg:phone":"+1 519 621 5520",
    "sg:postcode":"N1T 1R9",
    "sg:province":"ON",
    "sg:tags":[
        "plumbing",
        "fixture",
        "supply"
    ],
    "wof:name":"Cambridge Brass",
    "wof:placetype":"venue"
},
  "geometry": {"coordinates":[-80.2828369141,43.3703308105],"type":"Point"}
}