{
  "type": "Feature",
  "properties": {
    "addr:full":"16995 Yonge St # 5 Newmarket ON L3Y 5Y1",
    "addr:housenumber":"16995",
    "addr:postcode":"l3y 5y1",
    "addr:street":"Yonge St # 5",
    "iso:country":"CA",
    "sg:address":"16995 Yonge St # 5",
    "sg:city":"Newmarket",
    "sg:classifiers":[
        {
            "category":"Retail",
            "subcategory":"Auto Repair",
            "type":"Services"
        }
    ],
    "sg:phone":"+1 905 898 5115",
    "sg:postcode":"L3Y 5Y1",
    "sg:province":"ON",
    "sg:tags":[
        "repairing",
        "automobile"
    ],
    "wof:name":"Firestone Tire & Auto Ctr",
    "wof:placetype":"venue"
},
  "geometry": {"coordinates":[-79.47718811039999,44.0421104431],"type":"Point"}
}