{
  "type": "Feature",
  "properties": {
    "addr:full":"510 Dundas St Woodstock ON N4S 1C5",
    "addr:housenumber":"510",
    "addr:postcode":"n4s 1c5",
    "addr:street":"Dundas St",
    "iso:country":"CA",
    "sg:address":"510 Dundas St",
    "sg:city":"Woodstock",
    "sg:classifiers":[
        {
            "category":"Restaurant",
            "type":"Food & Drink"
        }
    ],
    "sg:phone":"+1 519 537 5892",
    "sg:postcode":"N4S 1C5",
    "sg:province":"ON",
    "wof:name":"Dino's Dining Lounge",
    "wof:placetype":"venue"
},
  "geometry": {"coordinates":[-80.7558441162,43.1300697327],"type":"Point"}
}