{
  "type": "Feature",
  "properties": {
    "iso:country":"CA",
    "sg:address":"3155 Montee Saint-Hubert",
    "sg:city":"Saint-Hubert",
    "sg:classifiers":[
        {
            "category":"Wholesale",
            "subcategory":"Office Equipment",
            "type":"Manufacturing & Wholesale Goods"
        }
    ],
    "sg:phone":"+1 450 445 2980",
    "sg:postcode":"J3Y 4J4",
    "sg:province":"QC",
    "sg:tags":[
        "accounting",
        "bookkeeping",
        "system"
    ],
    "wof:name":"Falardeau, Ghislain",
    "wof:placetype":"venue"
},
  "geometry": {"coordinates":[-73.42496490480001,45.4992141724],"type":"Point"}
}