{
  "type": "Feature",
  "properties": {
    "addr:full":"75 Roseford Terr Acton ON L7J 2L2",
    "addr:housenumber":"75",
    "addr:postcode":"l7j 2l2",
    "addr:street":"Roseford Terr",
    "iso:country":"CA",
    "sg:address":"75 Roseford Terr",
    "sg:city":"Acton",
    "sg:classifiers":[
        {
            "category":"Wholesale",
            "subcategory":"Construction Materials",
            "type":"Manufacturing & Wholesale Goods"
        }
    ],
    "sg:phone":"+1 519 853 2020",
    "sg:postcode":"L7J 2L2",
    "sg:province":"ON",
    "sg:tags":[
        "fence"
    ],
    "wof:name":"Rothwell Construction",
    "wof:placetype":"venue"
},
  "geometry": {"coordinates":[-80.026321,43.634499],"type":"Point"}
}