{
  "type": "Feature",
  "properties": {
    "addr:full":"RR 2 Thorndale ON N0M 2P0",
    "addr:postcode":"n0m 2p0",
    "addr:street":"Rr 2",
    "iso:country":"CA",
    "sg:address":"RR 2",
    "sg:city":"Thorndale",
    "sg:classifiers":[
        {
            "category":"Wholesale",
            "subcategory":"Scrap",
            "type":"Manufacturing & Wholesale Goods"
        }
    ],
    "sg:phone":"+1 519 461 0449",
    "sg:postcode":"N0M 2P0",
    "sg:province":"ON",
    "sg:tags":[
        "product",
        "recycling",
        "metal",
        "center"
    ],
    "wof:name":"A & S Aluminum Recyclers",
    "wof:placetype":"venue"
},
  "geometry": {"coordinates":[-81.1135177612,43.0531692505],"type":"Point"}
}