{
  "type": "Feature",
  "properties": {
    "iso:country":"CA",
    "sg:city":"Welland",
    "sg:classifiers":[
        {
            "category":"Real Estate",
            "subcategory":"Real Estate Operator",
            "type":"Services"
        }
    ],
    "sg:phone":"+1 905 735 4051",
    "sg:postcode":"L3C 6T4",
    "sg:province":"ON",
    "sg:tags":[
        "apartment"
    ],
    "wof:name":"Parkway Village",
    "wof:placetype":"venue"
},
  "geometry": {"coordinates":[-79.2565536499,42.9871559143],"type":"Point"}
}