{
  "type": "Feature",
  "properties": {
    "addr:full":"511 Bank St Ottawa ON K2P 1Z5",
    "addr:housenumber":"511",
    "addr:postcode":"k2p 1z5",
    "addr:street":"Bank St",
    "iso:country":"CA",
    "sg:address":"511 Bank St",
    "sg:city":"Ottawa",
    "sg:classifiers":[
        {
            "category":"Restaurant",
            "type":"Food & Drink"
        }
    ],
    "sg:phone":"+1 613 567 2997",
    "sg:postcode":"K2P 1Z5",
    "sg:province":"ON",
    "wof:name":"Gina's Cafe",
    "wof:placetype":"venue"
},
  "geometry": {"coordinates":[-75.692322,45.41013],"type":"Point"}
}