{
  "type": "Feature",
  "properties": {
    "addr:full":"Saint-Anselme QC G0R 2N0",
    "addr:postcode":"g0r 2n0",
    "iso:country":"CA",
    "sg:city":"Saint-Anselme",
    "sg:classifiers":[
        {
            "category":"Retail",
            "subcategory":"Auto Repair",
            "type":"Services"
        }
    ],
    "sg:phone":"+1 418 885 9719",
    "sg:postcode":"G0R 2N0",
    "sg:province":"QC",
    "sg:tags":[
        "repairing",
        "automobile",
        "polishing",
        "washing",
        "car"
    ],
    "wof:name":"Garage St-Anselme Trans Auto",
    "wof:placetype":"venue"
},
  "geometry": {"coordinates":[-70.99271400000001,46.643661],"type":"Point"}
}