{
  "type": "Feature",
  "properties": {
    "iso:country":"CA",
    "sg:address":"355 Station Rd",
    "sg:city":"Shoal Lake",
    "sg:classifiers":[
        {
            "category":"Shopping",
            "subcategory":"Pharmacy",
            "type":"Retail Goods"
        }
    ],
    "sg:phone":"+1 204 759 2300",
    "sg:postcode":"R0J 1Z0",
    "sg:province":"MB",
    "wof:name":"Shoal Lake Pharmacy Ltd",
    "wof:placetype":"venue"
},
  "geometry": {"coordinates":[-100.59072113000001,50.436920166],"type":"Point"}
}