{
  "type": "Feature",
  "properties": {
    "addr:full":"324 Farnham Rd Belleville ON K8N 4Z5",
    "addr:housenumber":"324",
    "addr:postcode":"k8n 4z5",
    "addr:street":"Farnham Rd",
    "iso:country":"CA",
    "sg:address":"324 Farnham Rd",
    "sg:city":"Belleville",
    "sg:classifiers":[
        {
            "category":"Retail",
            "subcategory":"Repair Shop",
            "type":"Services"
        }
    ],
    "sg:phone":"+1 613 961 1105",
    "sg:postcode":"K8N 4Z5",
    "sg:province":"ON",
    "sg:tags":[
        "ironwork",
        "fence"
    ],
    "wof:name":"Tak Construction",
    "wof:placetype":"venue"
},
  "geometry": {"coordinates":[-77.3974304199,44.2106819153],"type":"Point"}
}