{
  "type": "Feature",
  "properties": {
    "addr:full":"877 Henderson Hwy Winnipeg MB R2K 2L8",
    "addr:housenumber":"877",
    "addr:postcode":"r2k 2l8",
    "addr:street":"Henderson Hwy",
    "iso:country":"CA",
    "sg:address":"877 Henderson Hwy",
    "sg:city":"Winnipeg",
    "sg:classifiers":[
        {
            "category":"Insurance",
            "subcategory":"Insurance Agent",
            "type":"Services"
        }
    ],
    "sg:phone":"+1 204 661 2446",
    "sg:postcode":"R2K 2L8",
    "sg:province":"MB",
    "wof:name":"Harbun Insurance Brokers Ltd",
    "wof:placetype":"venue"
},
  "geometry": {"coordinates":[-97.099655,49.931831],"type":"Point"}
}