{
  "type": "Feature",
  "properties": {
    "iso:country":"CA",
    "sg:address":"200 8 Ave SW",
    "sg:city":"Calgary",
    "sg:classifiers":[
        {
            "category":"Shopping",
            "subcategory":"Department Store",
            "type":"Retail Goods"
        }
    ],
    "sg:phone":"+1 403 262 0345",
    "sg:postcode":"T2P 1B5",
    "sg:province":"AB",
    "wof:name":"Bay",
    "wof:placetype":"venue"
},
  "geometry": {"coordinates":[-114.065734863,51.0457344055],"type":"Point"}
}