{
  "type": "Feature",
  "properties": {
    "iso:country":"CA",
    "sg:city":"Astorville",
    "sg:classifiers":[
        {
            "category":"Wholesale",
            "subcategory":"Electrical",
            "type":"Manufacturing & Wholesale Goods"
        }
    ],
    "sg:phone":"+1 705 752 4164",
    "sg:postcode":"P0H 1B0",
    "sg:province":"ON",
    "sg:tags":[
        "generator"
    ],
    "wof:name":"Val's Equipment Svc",
    "wof:placetype":"venue"
},
  "geometry": {"coordinates":[-79.2683258057,46.1852264404],"type":"Point"}
}