{
  "type": "Feature",
  "properties": {
    "addr:full":"221 Norseman St Etobicoke ON M8Z 2R5",
    "addr:housenumber":"221",
    "addr:postcode":"m8z 2r5",
    "addr:street":"Norseman St",
    "iso:country":"CA",
    "sg:address":"221 Norseman St",
    "sg:city":"Etobicoke",
    "sg:classifiers":[
        {
            "category":"Food & Beverages",
            "subcategory":"Specialty",
            "type":"Retail Goods"
        }
    ],
    "sg:phone":"+1 416 232 2346",
    "sg:postcode":"M8Z 2R5",
    "sg:province":"ON",
    "sg:tags":[
        "vitamin"
    ],
    "wof:name":"Trophic Canada",
    "wof:placetype":"venue"
},
  "geometry": {"coordinates":[-79.5225143433,43.633228302],"type":"Point"}
}