{
  "type": "Feature",
  "properties": {
    "addr:full":"Edmonton AB T5J 3S4",
    "addr:postcode":"t5j 3s4",
    "iso:country":"CA",
    "sg:city":"Edmonton",
    "sg:classifiers":[
        {
            "category":"Real Estate",
            "subcategory":"Real Estate Agent",
            "type":"Services"
        }
    ],
    "sg:phone":"+1 780 423 1772",
    "sg:postcode":"T5J 3S4",
    "sg:province":"AB",
    "sg:tags":[
        "desk",
        "space"
    ],
    "wof:name":"Executive Centre At Manulife",
    "wof:placetype":"venue"
},
  "geometry": {"coordinates":[-113.493934631,53.5425872803],"type":"Point"}
}