{
  "type": "Feature",
  "properties": {
    "addr:full":"Calgary AB T2C 4E8",
    "addr:postcode":"t2c 4e8",
    "iso:country":"CA",
    "sg:city":"Calgary",
    "sg:classifiers":[
        {
            "category":"Wholesale",
            "subcategory":"Stationery",
            "type":"Manufacturing & Wholesale Goods"
        }
    ],
    "sg:phone":"+1 403 287 3490",
    "sg:postcode":"T2C 4E8",
    "sg:province":"AB",
    "sg:tags":[
        "product",
        "paper"
    ],
    "wof:name":"Bunzl Distribution Inc",
    "wof:placetype":"venue"
},
  "geometry": {"coordinates":[-113.97035200000001,50.991779],"type":"Point"}
}