{
  "type": "Feature",
  "properties": {
    "iso:country":"CA",
    "sg:city":"Waterloo",
    "sg:classifiers":[
        {
            "category":"Professional",
            "subcategory":"Computer Services",
            "type":"Services"
        }
    ],
    "sg:phone":"+1 519 884 7200",
    "sg:postcode":"N2V 2C9",
    "sg:province":"ON",
    "sg:tags":[
        "internet"
    ],
    "wof:name":"Information Gateway Svc",
    "wof:placetype":"venue"
},
  "geometry": {"coordinates":[-80.52703857420001,43.5063476562],"type":"Point"}
}