{
  "type": "Feature",
  "properties": {
    "iso:country":"CA",
    "sg:city":"Montreal",
    "sg:classifiers":[
        {
            "category":"Health Services",
            "subcategory":"Doctor",
            "type":"Services"
        }
    ],
    "sg:phone":"+1 514 344 6654",
    "sg:postcode":"H3G 1W1",
    "sg:province":"QC",
    "sg:tags":[
        "physician",
        "surgeon"
    ],
    "wof:name":"Demirjian, Ari MD",
    "wof:placetype":"venue"
},
  "geometry": {"coordinates":[-73.5749053955,45.4988136292],"type":"Point"}
}