{
  "type": "Feature",
  "properties": {
    "addr:full":"501 Wellington Rd London ON N6C 4R3",
    "addr:housenumber":"501",
    "addr:postcode":"n6c 4r3",
    "addr:street":"Wellington Rd",
    "iso:country":"CA",
    "sg:address":"501 Wellington Rd",
    "sg:city":"London",
    "sg:classifiers":[
        {
            "category":"Health Services",
            "subcategory":"Doctor",
            "type":"Services"
        }
    ],
    "sg:phone":"+1 519 681 4020",
    "sg:postcode":"N6C 4R3",
    "sg:province":"ON",
    "sg:tags":[
        "dentist"
    ],
    "wof:name":"Kozoriz, John G DDS",
    "wof:placetype":"venue"
},
  "geometry": {"coordinates":[-81.229919,42.956226],"type":"Point"}
}