{
  "type": "Feature",
  "properties": {
    "iso:country":"CA",
    "sg:address":"35 Church St",
    "sg:city":"Toronto",
    "sg:classifiers":[
        {
            "category":"Restaurant",
            "type":"Food & Drink"
        }
    ],
    "sg:phone":"+1 416 366 7800",
    "sg:postcode":"M5E 1T3",
    "sg:province":"ON",
    "wof:name":"Hot House Cafe",
    "wof:placetype":"venue"
},
  "geometry": {"coordinates":[-79.373833,43.649052],"type":"Point"}
}