{
  "type": "Feature",
  "properties": {
    "addr:full":"6 Coronation Cres Dartmouth NS B2V 2M1",
    "addr:housenumber":"6",
    "addr:postcode":"b2v 2m1",
    "addr:street":"Coronation Cres",
    "iso:country":"CA",
    "sg:address":"6 Coronation Cres",
    "sg:city":"Dartmouth",
    "sg:classifiers":[
        {
            "category":"Building & Trades",
            "subcategory":"Construction",
            "type":"Services"
        }
    ],
    "sg:phone":"+1 902 462 4660",
    "sg:postcode":"B2V 2M1",
    "sg:province":"NS",
    "sg:tags":[
        "painter"
    ],
    "wof:name":"K & J Wentzell Painting Ltd",
    "wof:placetype":"venue"
},
  "geometry": {"coordinates":[-63.4989585876,44.6650543213],"type":"Point"}
}