{
  "type": "Feature",
  "properties": {
    "iso:country":"CA",
    "sg:address":"2620 Rte 209",
    "sg:city":"Saint-Antoine-Abbe",
    "sg:classifiers":[
        {
            "category":"Banks & Credit Unions",
            "subcategory":"Bank",
            "type":"Services"
        }
    ],
    "sg:phone":"+1 450 827 2542",
    "sg:postcode":"J0S 1N0",
    "sg:province":"QC",
    "wof:name":"Caisses Populaire Desjardins",
    "wof:placetype":"venue"
},
  "geometry": {"coordinates":[-73.88910675050001,45.0512542725],"type":"Point"}
}