{
  "type": "Feature",
  "properties": {
    "addr:full":"282 Main St S Carman MB R0G 0J0",
    "addr:housenumber":"282",
    "addr:postcode":"r0g 0j0",
    "addr:street":"Main St S",
    "iso:country":"CA",
    "sg:address":"282 Main St S",
    "sg:city":"Carman",
    "sg:classifiers":[
        {
            "category":"Building & Trades",
            "subcategory":"Electrical",
            "type":"Services"
        }
    ],
    "sg:phone":"+1 204 745 2628",
    "sg:postcode":"R0G 0J0",
    "sg:province":"MB",
    "sg:tags":[
        "electric",
        "contractor"
    ],
    "wof:name":"Bob Murray Electric Ltd",
    "wof:placetype":"venue"
},
  "geometry": {"coordinates":[-98.00185399999999,49.498028],"type":"Point"}
}