{
  "type": "Feature",
  "properties": {
    "addr:full":"1310 Nicholas-Denys Rd Saint-Laurent NB E8K 3K2",
    "addr:housenumber":"1310",
    "addr:postcode":"e8k 3k2",
    "addr:street":"Nicholas-Denys Rd",
    "iso:country":"CA",
    "sg:address":"1310 Nicholas-Denys Rd",
    "sg:city":"Saint-Laurent",
    "sg:classifiers":[
        {
            "category":"Freight",
            "type":"Transportation"
        }
    ],
    "sg:phone":"+1 506 783 2221",
    "sg:postcode":"E8K 3K2",
    "sg:province":"NB",
    "sg:tags":[
        "trucking"
    ],
    "wof:name":"Jmf Contractor DE Bois Ltee",
    "wof:placetype":"venue"
},
  "geometry": {"coordinates":[-65.78169250489999,47.739200592],"type":"Point"}
}