{
  "type": "Feature",
  "properties": {
    "addr:full":"31713 South Fraser Way Abbotsford BC V2T 1V1",
    "addr:housenumber":"31713",
    "addr:postcode":"v2t 1v1",
    "addr:street":"South Fraser Way",
    "iso:country":"CA",
    "sg:address":"31713 South Fraser Way",
    "sg:city":"Abbotsford",
    "sg:classifiers":[
        {
            "category":"Food & Beverages",
            "subcategory":"Groceries & Convenience Stores",
            "type":"Retail Goods"
        }
    ],
    "sg:phone":"+1 604 850 5680",
    "sg:postcode":"V2T 1V1",
    "sg:province":"BC",
    "sg:tags":[
        "grocer"
    ],
    "wof:name":"R & F Market",
    "wof:placetype":"venue"
},
  "geometry": {"coordinates":[-122.34530599999999,49.046883],"type":"Point"}
}