{
  "type": "Feature",
  "properties": {
    "addr:full":"Laval QC H7P 1T8",
    "addr:postcode":"h7p 1t8",
    "iso:country":"CA",
    "sg:city":"Laval",
    "sg:classifiers":[
        {
            "category":"Health Services",
            "subcategory":"Doctor",
            "type":"Services"
        }
    ],
    "sg:phone":"+1 450 622 8880",
    "sg:postcode":"H7P 1T8",
    "sg:province":"QC",
    "sg:tags":[
        "dentist"
    ],
    "wof:name":"Clinique Dentaire",
    "wof:placetype":"venue"
},
  "geometry": {"coordinates":[-73.795586,45.579109],"type":"Point"}
}