{
  "type": "Feature",
  "properties": {
    "iso:country":"CA",
    "sg:address":"510 Rue Belanger",
    "sg:city":"Montreal",
    "sg:classifiers":[
        {
            "category":"Personal",
            "type":"Services"
        }
    ],
    "sg:phone":"+1 514 276 4805",
    "sg:postcode":"H2S 1G4",
    "sg:province":"QC",
    "sg:tags":[
        "therapist",
        "massage"
    ],
    "wof:name":"Centre D'Esthetique Manon",
    "wof:placetype":"venue"
},
  "geometry": {"coordinates":[-73.610954,45.537987],"type":"Point"}
}