{
  "type": "Feature",
  "properties": {
    "addr:full":"Macamic QC J0Z 2S0",
    "addr:postcode":"j0z 2s0",
    "iso:country":"CA",
    "sg:city":"Macamic",
    "sg:classifiers":[
        {
            "category":"Manufacturing",
            "subcategory":"Tools & Machinery",
            "type":"Manufacturing & Wholesale Goods"
        }
    ],
    "sg:phone":"+1 819 782 4422",
    "sg:postcode":"J0Z 2S0",
    "sg:province":"QC",
    "sg:tags":[
        "machine",
        "shop"
    ],
    "wof:name":"Larose & Larose Inc",
    "wof:placetype":"venue"
},
  "geometry": {"coordinates":[-79.00221252439999,48.7553482056],"type":"Point"}
}