{
  "type": "Feature",
  "properties": {
    "iso:country":"CA",
    "sg:address":"2000 Rue Notre-Dame E",
    "sg:city":"Montreal",
    "sg:classifiers":[
        {
            "category":"Arts & Performance",
            "subcategory":"Theater",
            "type":"Entertainment"
        }
    ],
    "sg:phone":"+1 514 596 3872",
    "sg:postcode":"H2K 2N3",
    "sg:province":"QC",
    "sg:tags":[
        "scenery",
        "theatrical",
        "studio",
        "equipment",
        "supply"
    ],
    "wof:name":"Productions Double Effet Inc",
    "wof:placetype":"venue"
},
  "geometry": {"coordinates":[-73.546761,45.520508],"type":"Point"}
}