{
  "type": "Feature",
  "properties": {
    "iso:country":"CA",
    "sg:address":"418 Rue Caron",
    "sg:city":"Quebec",
    "sg:classifiers":[
        {
            "category":"Personal",
            "subcategory":"Beauty Salon",
            "type":"Services"
        }
    ],
    "sg:phone":"+1 418 523 6002",
    "sg:postcode":"G1K 5W7",
    "sg:province":"QC",
    "wof:name":"Salon Trouvailles D'Afrique",
    "wof:placetype":"venue"
},
  "geometry": {"coordinates":[-71.228439,46.812717],"type":"Point"}
}