{
  "type": "Feature",
  "properties": {
    "addr:full":"223 Rue Emile Laval QC H7N 4M1",
    "addr:housenumber":"223",
    "addr:postcode":"h7n 4m1",
    "addr:street":"Rue Emile",
    "iso:country":"CA",
    "sg:address":"223 Rue Emile",
    "sg:city":"Laval",
    "sg:classifiers":[
        {
            "category":"Building & Trades",
            "subcategory":"Construction",
            "type":"Services"
        }
    ],
    "sg:phone":"+1 450 224 3084",
    "sg:postcode":"H7N 4M1",
    "sg:province":"QC",
    "sg:tags":[
        "repairing",
        "contractor",
        "remodeling",
        "general"
    ],
    "wof:name":"Construction Andre Lachance",
    "wof:placetype":"venue"
},
  "geometry": {"coordinates":[-73.6881866455,45.5600891113],"type":"Point"}
}