{
  "type": "Feature",
  "properties": {
    "iso:country":"CA",
    "sg:address":"29 Gervais Dr",
    "sg:city":"North York",
    "sg:classifiers":[
        {
            "category":"Wholesale",
            "subcategory":"Scrap",
            "type":"Manufacturing & Wholesale Goods"
        }
    ],
    "sg:phone":"+1 416 443 0846",
    "sg:postcode":"M3C 1Y9",
    "sg:province":"ON",
    "sg:tags":[
        "recycling",
        "center"
    ],
    "wof:name":"Recycling Matters",
    "wof:placetype":"venue"
},
  "geometry": {"coordinates":[-79.33661651609999,43.7240066528],"type":"Point"}
}