{
  "type": "Feature",
  "properties": {
    "addr:full":"37150 Lougheed Hwy Dewdney BC V0M 1H0",
    "addr:housenumber":"37150",
    "addr:postcode":"v0m 1h0",
    "addr:street":"Lougheed Hwy",
    "iso:country":"CA",
    "sg:address":"37150 Lougheed Hwy",
    "sg:city":"Dewdney",
    "sg:classifiers":[
        {
            "category":"Shopping",
            "subcategory":"Discount & Variety Stores",
            "type":"Retail Goods"
        }
    ],
    "sg:phone":"+1 604 826 2776",
    "sg:postcode":"V0M 1H0",
    "sg:province":"BC",
    "sg:tags":[
        "merchandise",
        "general"
    ],
    "wof:name":"Dewdney Trading CO",
    "wof:placetype":"venue"
},
  "geometry": {"coordinates":[-122.194778442,49.163318634],"type":"Point"}
}