{
  "type": "Feature",
  "properties": {
    "addr:full":"930 Rue Pie-Xi Thetford Mines QC G6G 7M4",
    "addr:housenumber":"930",
    "addr:postcode":"g6g 7m4",
    "addr:street":"Rue Pie-Xi",
    "iso:country":"CA",
    "sg:address":"930 Rue Pie-Xi",
    "sg:city":"Thetford Mines",
    "sg:classifiers":[
        {
            "category":"Building & Trades",
            "subcategory":"Construction",
            "type":"Services"
        }
    ],
    "sg:phone":"+1 418 338 2323",
    "sg:postcode":"G6G 7M4",
    "sg:province":"QC",
    "sg:tags":[
        "insulation",
        "heat",
        "contractor"
    ],
    "wof:name":"Technologies Fibrox Ltee",
    "wof:placetype":"venue"
},
  "geometry": {"coordinates":[-71.316727,46.098038],"type":"Point"}
}