{
  "type": "Feature",
  "properties": {
    "addr:full":"2440 Bank St Ottawa ON K1V 8S1",
    "addr:housenumber":"2440",
    "addr:postcode":"k1v 8s1",
    "addr:street":"Bank St",
    "iso:country":"CA",
    "sg:address":"2440 Bank St",
    "sg:city":"Ottawa",
    "sg:classifiers":[
        {
            "category":"Shopping",
            "subcategory":"Computers & Home Electronics",
            "type":"Retail Goods"
        }
    ],
    "sg:phone":"+1 613 247 4263",
    "sg:postcode":"K1V 8S1",
    "sg:province":"ON",
    "sg:tags":[
        "game",
        "video"
    ],
    "wof:name":"Microplay Video Games",
    "wof:placetype":"venue"
},
  "geometry": {"coordinates":[-75.64877300000001,45.35387],"type":"Point"}
}