{
  "type": "Feature",
  "properties": {
    "addr:full":"7030 Woodbine Ave Markham ON L3R 6G2",
    "addr:housenumber":"7030",
    "addr:postcode":"l3r 6g2",
    "addr:street":"Woodbine Ave",
    "iso:country":"CA",
    "sg:address":"7030 Woodbine Ave",
    "sg:city":"Markham",
    "sg:classifiers":[
        {
            "category":"Wholesale",
            "subcategory":"Machinery & Supplies",
            "type":"Manufacturing & Wholesale Goods"
        }
    ],
    "sg:phone":"+1 905 479 7827",
    "sg:postcode":"L3R 6G2",
    "sg:province":"ON",
    "sg:tags":[
        "stock",
        "boards",
        "system",
        "quotation"
    ],
    "wof:name":"Cgi",
    "wof:placetype":"venue"
},
  "geometry": {"coordinates":[-79.349052,43.814854],"type":"Point"}
}