{
  "type": "Feature",
  "properties": {
    "addr:full":"Campbell River BC V9W 6H7",
    "addr:postcode":"v9w 6h7",
    "iso:country":"CA",
    "sg:city":"Campbell River",
    "sg:classifiers":[
        {
            "category":"Manufacturing",
            "subcategory":"Tools & Machinery",
            "type":"Manufacturing & Wholesale Goods"
        }
    ],
    "sg:phone":"+1 250 286 7262",
    "sg:postcode":"V9W 6H7",
    "sg:province":"BC",
    "sg:tags":[
        "machine",
        "shop"
    ],
    "wof:name":"Morgan Machine Works",
    "wof:placetype":"venue"
},
  "geometry": {"coordinates":[-125.270172,50.044888],"type":"Point"}
}