{
  "type": "Feature",
  "properties": {
    "iso:country":"CA",
    "sg:city":"Brampton",
    "sg:classifiers":[
        {
            "category":"Personal",
            "subcategory":"Tattoo Parlor",
            "type":"Services"
        }
    ],
    "sg:phone":"+1 905 793 4853",
    "sg:postcode":"L6T 3R5",
    "sg:province":"ON",
    "sg:tags":[
        "tattooing",
        "craft",
        "supply"
    ],
    "wof:name":"Little Mexico",
    "wof:placetype":"venue"
},
  "geometry": {"coordinates":[-79.723366,43.717297],"type":"Point"}
}