{
  "type": "Feature",
  "properties": {
    "addr:full":"150 Katimavik Rd Kanata ON K2L 2N2",
    "addr:housenumber":"150",
    "addr:postcode":"k2l 2n2",
    "addr:street":"Katimavik Rd",
    "iso:country":"CA",
    "sg:address":"150 Katimavik Rd",
    "sg:city":"Kanata",
    "sg:classifiers":[
        {
            "category":"Shopping",
            "subcategory":"Optical Goods",
            "type":"Retail Goods"
        }
    ],
    "sg:phone":"+1 613 592 1885",
    "sg:postcode":"K2L 2N2",
    "sg:province":"ON",
    "sg:tags":[
        "optician"
    ],
    "wof:name":"Kanata Opticians",
    "wof:placetype":"venue"
},
  "geometry": {"coordinates":[-75.8957366943,45.3111457825],"type":"Point"}
}