{
  "type": "Feature",
  "properties": {
    "addr:full":"2301 Royal Windsor Dr Mississauga ON L5J 1K5",
    "addr:housenumber":"2301",
    "addr:postcode":"l5j 1k5",
    "addr:street":"Royal Windsor Dr",
    "iso:country":"CA",
    "sg:address":"2301 Royal Windsor Dr",
    "sg:city":"Mississauga",
    "sg:classifiers":[
        {
            "category":"Freight",
            "type":"Transportation"
        }
    ],
    "sg:phone":"+1 905 336 1814",
    "sg:postcode":"L5J 1K5",
    "sg:province":"ON",
    "sg:tags":[
        "mover",
        "trucking"
    ],
    "wof:name":"Royal Moving & Storage Ltd",
    "wof:placetype":"venue"
},
  "geometry": {"coordinates":[-79.635628,43.505966],"type":"Point"}
}