{
  "type": "Feature",
  "properties": {
    "addr:full":"Montreal QC H3X 2H9",
    "addr:postcode":"h3x 2h9",
    "iso:country":"CA",
    "sg:city":"Montreal",
    "sg:classifiers":[
        {
            "category":"Professional",
            "subcategory":"Accounting & Tax Preparation",
            "type":"Services"
        }
    ],
    "sg:phone":"+1 514 488 8800",
    "sg:postcode":"H3X 2H9",
    "sg:province":"QC",
    "sg:tags":[
        "accountant"
    ],
    "wof:name":"Goodwin Neuhaus Stein",
    "wof:placetype":"venue"
},
  "geometry": {"coordinates":[-73.631668,45.484394],"type":"Point"}
}