{
  "type": "Feature",
  "properties": {
    "iso:country":"CA",
    "sg:address":"13524 25 St NW",
    "sg:city":"Edmonton",
    "sg:classifiers":[
        {
            "category":"Building & Trades",
            "subcategory":"Electrical",
            "type":"Services"
        }
    ],
    "sg:phone":"+1 780 478 1298",
    "sg:postcode":"T5A 3V6",
    "sg:province":"AB",
    "sg:tags":[
        "electric",
        "contractor"
    ],
    "wof:name":"G & G Electric Ltd",
    "wof:placetype":"venue"
},
  "geometry": {"coordinates":[-113.38080596899999,53.5973739624],"type":"Point"}
}