{
  "type": "Feature",
  "properties": {
    "addr:full":"4784 Av Van Horne Montreal QC H3W 1H7",
    "addr:housenumber":"4784",
    "addr:postcode":"h3w 1h7",
    "addr:street":"Av Van Horne",
    "iso:country":"CA",
    "sg:address":"4784 Av Van Horne",
    "sg:city":"Montreal",
    "sg:classifiers":[
        {
            "category":"Personal",
            "subcategory":"Beauty Salon",
            "type":"Services"
        }
    ],
    "sg:phone":"+1 514 344 9834",
    "sg:postcode":"H3W 1H7",
    "sg:province":"QC",
    "wof:name":"Coiffure Tysalina",
    "wof:placetype":"venue"
},
  "geometry": {"coordinates":[-73.63716100000001,45.494621],"type":"Point"}
}