{
  "type": "Feature",
  "properties": {
    "iso:country":"CA",
    "sg:address":"525 Rue DE LA Falaise",
    "sg:city":"Levis",
    "sg:classifiers":[
        {
            "category":"Wholesale",
            "subcategory":"Chemicals & Plastics",
            "type":"Manufacturing & Wholesale Goods"
        }
    ],
    "sg:phone":"+1 418 837 8638",
    "sg:postcode":"G6W 1A4",
    "sg:province":"QC",
    "sg:tags":[
        "cleaning",
        "compound"
    ],
    "wof:name":"Amway Produits Domestiques",
    "wof:placetype":"venue"
},
  "geometry": {"coordinates":[-71.1909866333,46.7923545837],"type":"Point"}
}