{
  "type": "Feature",
  "properties": {
    "addr:full":"Loring ON P0H 1S0",
    "addr:postcode":"p0h 1s0",
    "iso:country":"CA",
    "sg:city":"Loring",
    "sg:classifiers":[
        {
            "category":"Food & Beverages",
            "subcategory":"Groceries & Convenience Stores",
            "type":"Retail Goods"
        }
    ],
    "sg:phone":"+1 705 757 2366",
    "sg:postcode":"P0H 1S0",
    "sg:province":"ON",
    "sg:tags":[
        "grocer"
    ],
    "wof:name":"Loring General Store",
    "wof:placetype":"venue"
},
  "geometry": {"coordinates":[-79.9974899292,45.9322853088],"type":"Point"}
}