{
  "type": "Feature",
  "properties": {
    "addr:full":"4041 7 St SE Calgary AB T2G 2Y9",
    "addr:housenumber":"4041 7",
    "addr:postcode":"t2g 2y9",
    "addr:street":"St Se",
    "iso:country":"CA",
    "sg:address":"4041 7 St SE",
    "sg:city":"Calgary",
    "sg:classifiers":[
        {
            "category":"Wholesale",
            "subcategory":"Hardware",
            "type":"Manufacturing & Wholesale Goods"
        }
    ],
    "sg:phone":"+1 403 287 1310",
    "sg:postcode":"T2G 2Y9",
    "sg:province":"AB",
    "sg:tags":[
        "control",
        "equipment",
        "heating",
        "system"
    ],
    "wof:name":"Albert's Controls Ltd",
    "wof:placetype":"venue"
},
  "geometry": {"coordinates":[-114.045952,51.018528],"type":"Point"}
}