{
  "type": "Feature",
  "properties": {
    "addr:full":"577 2 St SE Medicine Hat AB T1A 0C5",
    "addr:housenumber":"577 2",
    "addr:postcode":"t1a 0c5",
    "addr:street":"St Se",
    "iso:country":"CA",
    "sg:address":"577 2 St SE",
    "sg:city":"Medicine Hat",
    "sg:classifiers":[
        {
            "category":"Professional",
            "subcategory":"Lawyer & Legal Services",
            "type":"Services"
        }
    ],
    "sg:phone":"+1 403 527 7736",
    "sg:postcode":"T1A 0C5",
    "sg:province":"AB",
    "sg:tags":[
        "attorney"
    ],
    "wof:name":"Roy E Link Law Offices",
    "wof:placetype":"venue"
},
  "geometry": {"coordinates":[-110.67684199999999,50.040253],"type":"Point"}
}