{
  "type": "Feature",
  "properties": {
    "iso:country":"CA",
    "sg:address":"Hwy 11",
    "sg:city":"Temagami",
    "sg:classifiers":[
        {
            "category":"Shopping",
            "subcategory":"Gifts & Souvenirs",
            "type":"Retail Goods"
        }
    ],
    "sg:phone":"+1 705 569 3311",
    "sg:postcode":"P0H 2H0",
    "sg:province":"ON",
    "sg:tags":[
        "shop"
    ],
    "wof:name":"Northland Traders",
    "wof:placetype":"venue"
},
  "geometry": {"coordinates":[-79.7899398804,47.0627212524],"type":"Point"}
}