{
  "type": "Feature",
  "properties": {
    "iso:country":"CA",
    "sg:address":"299 Frances St",
    "sg:city":"Strathroy",
    "sg:classifiers":[
        {
            "category":"Government",
            "subcategory":"Police Station",
            "type":"Public Place"
        }
    ],
    "sg:phone":"+1 519 245 1250",
    "sg:postcode":"N7G 4G9",
    "sg:province":"ON",
    "sg:tags":[
        "department"
    ],
    "wof:name":"Strathroy Caradoc Police Dept",
    "wof:placetype":"venue"
},
  "geometry": {"coordinates":[-81.6138000488,42.949848175],"type":"Point"}
}