{
  "type": "Feature",
  "properties": {
    "addr:full":"196 Rue Renault O Arntfield QC J0Z 1B0",
    "addr:housenumber":"196",
    "addr:postcode":"j0z 1b0",
    "addr:street":"Rue Renault;Arntfield",
    "iso:country":"CA",
    "sg:address":"196 Rue Renault O",
    "sg:city":"Arntfield",
    "sg:classifiers":[
        {
            "category":"Building & Trades",
            "subcategory":"Construction",
            "type":"Services"
        }
    ],
    "sg:phone":"+1 819 279 2399",
    "sg:postcode":"J0Z 1B0",
    "sg:province":"QC",
    "sg:tags":[
        "general",
        "contractor"
    ],
    "wof:name":"Excavation Renick Inc",
    "wof:placetype":"venue"
},
  "geometry": {"coordinates":[-79.21666,48.20779],"type":"Point"}
}