{
  "type": "Feature",
  "properties": {
    "addr:full":"230 2nd St E Debden SK S0J 0S0",
    "addr:housenumber":"230",
    "addr:postcode":"s0j 0s0",
    "addr:street":"2Nd St E Debden",
    "iso:country":"CA",
    "sg:address":"230 2nd St E",
    "sg:city":"Debden",
    "sg:classifiers":[
        {
            "category":"Recreation",
            "type":"Entertainment"
        }
    ],
    "sg:phone":"+1 306 724 2262",
    "sg:postcode":"S0J 0S0",
    "sg:province":"SK",
    "sg:tags":[
        "skating",
        "rink"
    ],
    "wof:name":"Debden Skating Rink",
    "wof:placetype":"venue"
},
  "geometry": {"coordinates":[-106.87822723399999,53.5272254944],"type":"Point"}
}