{
  "type": "Feature",
  "properties": {
    "addr:full":"403227 Robinson Rd Ingersoll ON N5C 3J7",
    "addr:housenumber":"403227",
    "addr:postcode":"n5c 3j7",
    "addr:street":"Robinson Rd",
    "iso:country":"CA",
    "sg:address":"403227 Robinson Rd",
    "sg:city":"Ingersoll",
    "sg:classifiers":[
        {
            "category":"Wholesale",
            "subcategory":"Auto Parts",
            "type":"Manufacturing & Wholesale Goods"
        }
    ],
    "sg:phone":"+1 519 485 4520",
    "sg:postcode":"N5C 3J7",
    "sg:province":"ON",
    "sg:tags":[
        "automobile",
        "wrecking"
    ],
    "wof:name":"Phillips Auto Wreckers",
    "wof:placetype":"venue"
},
  "geometry": {"coordinates":[-80.88385,43.038116],"type":"Point"}
}