{
  "type": "Feature",
  "properties": {
    "iso:country":"CA",
    "sg:address":"5805 Rue DE Prince-Rupert",
    "sg:city":"Laval",
    "sg:classifiers":[
        {
            "category":"Retail",
            "subcategory":"Repair Shop",
            "type":"Services"
        }
    ],
    "sg:phone":"+1 450 628 9712",
    "sg:postcode":"H7H 1C5",
    "sg:province":"QC",
    "sg:tags":[
        "lock",
        "locksmith"
    ],
    "wof:name":"Serrurier Lebel Enr",
    "wof:placetype":"venue"
},
  "geometry": {"coordinates":[-73.747101,45.633774],"type":"Point"}
}