{
  "type": "Feature",
  "properties": {
    "addr:full":"491 7th Ave Campbell River BC V9W 4A1",
    "addr:housenumber":"491",
    "addr:postcode":"v9w 4a1",
    "addr:street":"7Th Ave",
    "iso:country":"CA",
    "sg:address":"491 7th Ave",
    "sg:city":"Campbell River",
    "sg:classifiers":[
        {
            "category":"Food & Beverages",
            "subcategory":"Groceries & Convenience Stores",
            "type":"Retail Goods"
        }
    ],
    "sg:phone":"+1 250 287 3882",
    "sg:postcode":"V9W 4A1",
    "sg:province":"BC",
    "sg:tags":[
        "grocer"
    ],
    "wof:name":"Jolly Giant Stores",
    "wof:placetype":"venue"
},
  "geometry": {"coordinates":[-125.246032715,50.0197677612],"type":"Point"}
}