{
  "type": "Feature",
  "properties": {
    "addr:full":"31 Ch DE L'Ile-DE-Mai Boisbriand QC J7G 1R7",
    "addr:housenumber":"31",
    "addr:postcode":"j7g 1r7",
    "addr:street":"Ch De L'Ile-De-Mai",
    "iso:country":"CA",
    "sg:address":"31 Ch DE L'Ile-DE-Mai",
    "sg:city":"Boisbriand",
    "sg:classifiers":[
        {
            "category":"Wholesale",
            "subcategory":"Durable Goods & Equipment",
            "type":"Manufacturing & Wholesale Goods"
        }
    ],
    "sg:phone":"+1 450 435 2951",
    "sg:postcode":"J7G 1R7",
    "sg:province":"QC",
    "sg:tags":[
        "representative",
        "manufacturer"
    ],
    "wof:name":"Lessard, Jean",
    "wof:placetype":"venue"
},
  "geometry": {"coordinates":[-73.827095,45.606838],"type":"Point"}
}