{
  "type": "Feature",
  "properties": {
    "addr:full":"Montreal QC H1Z 4K6",
    "addr:postcode":"h1z 4k6",
    "iso:country":"CA",
    "sg:city":"Montreal",
    "sg:classifiers":[
        {
            "category":"Professional",
            "subcategory":"Management & Consulting",
            "type":"Services"
        }
    ],
    "sg:phone":"+1 514 727 0884",
    "sg:postcode":"H1Z 4K6",
    "sg:province":"QC",
    "sg:tags":[
        "consultant",
        "business"
    ],
    "wof:name":"Gestion Lf",
    "wof:placetype":"venue"
},
  "geometry": {"coordinates":[-73.60702514650001,45.566734314],"type":"Point"}
}