{
  "type": "Feature",
  "properties": {
    "addr:full":"610 Newman Rd Quesnel BC V2J 6Z8",
    "addr:housenumber":"610",
    "addr:postcode":"v2j 6z8",
    "addr:street":"Newman Rd",
    "iso:country":"CA",
    "sg:address":"610 Newman Rd",
    "sg:city":"Quesnel",
    "sg:classifiers":[
        {
            "category":"Restaurant",
            "type":"Food & Drink"
        }
    ],
    "sg:phone":"+1 250 747 4536",
    "sg:postcode":"V2J 6Z8",
    "sg:province":"BC",
    "wof:name":"Boston Pizza",
    "wof:placetype":"venue"
},
  "geometry": {"coordinates":[-122.441047669,52.9692649841],"type":"Point"}
}