{
  "type": "Feature",
  "properties": {
    "iso:country":"CA",
    "sg:city":"Montreal",
    "sg:classifiers":[
        {
            "category":"Food & Beverages",
            "subcategory":"Groceries & Convenience Stores",
            "type":"Retail Goods"
        }
    ],
    "sg:phone":"+1 514 844 6276",
    "sg:postcode":"H2Y 3X7",
    "sg:province":"QC",
    "wof:name":"Depanneur Beau-Soir",
    "wof:placetype":"venue"
},
  "geometry": {"coordinates":[-73.554413,45.510803],"type":"Point"}
}