{
  "type": "Feature",
  "properties": {
    "iso:country":"CA",
    "sg:address":"20 Rue Morris",
    "sg:city":"Sainte-Therese",
    "sg:classifiers":[
        {
            "category":"Professional",
            "subcategory":"Lawyer & Legal Services",
            "type":"Services"
        }
    ],
    "sg:phone":"+1 450 434 6884",
    "sg:postcode":"J7E 3L2",
    "sg:province":"QC",
    "sg:tags":[
        "attorney"
    ],
    "wof:name":"Masson, Richard",
    "wof:placetype":"venue"
},
  "geometry": {"coordinates":[-73.8465499878,45.6417007446],"type":"Point"}
}