{
  "type": "Feature",
  "properties": {
    "addr:full":"2948 Ch Sainte-Marie Mascouche QC J7K 1N7",
    "addr:housenumber":"2948",
    "addr:postcode":"j7k 1n7",
    "addr:street":"Ch Sainte-Marie",
    "iso:country":"CA",
    "sg:address":"2948 Ch Sainte-Marie",
    "sg:city":"Mascouche",
    "sg:classifiers":[
        {
            "category":"Shopping",
            "subcategory":"Florist",
            "type":"Retail Goods"
        }
    ],
    "sg:phone":"+1 450 474 2092",
    "sg:postcode":"J7K 1N7",
    "sg:province":"QC",
    "wof:name":"Fleuriste Le Panier DE Fleurs",
    "wof:placetype":"venue"
},
  "geometry": {"coordinates":[-73.60325622560001,45.748134613],"type":"Point"}
}