{
  "type": "Feature",
  "properties": {
    "addr:full":"Edmonton AB T6E 4E1",
    "addr:postcode":"t6e 4e1",
    "iso:country":"CA",
    "sg:city":"Edmonton",
    "sg:classifiers":[
        {
            "category":"Wholesale",
            "subcategory":"Groceries",
            "type":"Manufacturing & Wholesale Goods"
        }
    ],
    "sg:phone":"+1 780 439 3888",
    "sg:postcode":"T6E 4E1",
    "sg:province":"AB",
    "sg:tags":[
        "grocer"
    ],
    "wof:name":"Ching Wah Trading CO Ltd",
    "wof:placetype":"venue"
},
  "geometry": {"coordinates":[-113.497314453,53.5154037476],"type":"Point"}
}