{
  "type": "Feature",
  "properties": {
    "addr:full":"Winnipeg MB R3E 3H4",
    "addr:postcode":"r3e 3h4",
    "iso:country":"CA",
    "sg:city":"Winnipeg",
    "sg:classifiers":[
        {
            "category":"Organizations",
            "subcategory":"Religious Organization",
            "type":"Services"
        }
    ],
    "sg:phone":"+1 204 954 2900",
    "sg:postcode":"R3E 3H4",
    "sg:province":"MB",
    "sg:tags":[
        "church"
    ],
    "wof:name":"Winnipeg Presbytery United Chr",
    "wof:placetype":"venue"
},
  "geometry": {"coordinates":[-97.183159,49.913654],"type":"Point"}
}