{
  "type": "Feature",
  "properties": {
    "addr:full":"Rose Prairie BC V0C 2H0",
    "addr:postcode":"bc v0c 2h0",
    "iso:country":"CA",
    "sg:city":"Rose Prairie",
    "sg:classifiers":[
        {
            "category":"Building & Trades",
            "subcategory":"Construction",
            "type":"Services"
        }
    ],
    "sg:phone":"+1 250 827 3282",
    "sg:postcode":"V0C 2H0",
    "sg:province":"BC",
    "sg:tags":[
        "field",
        "oil",
        "general",
        "contractor"
    ],
    "wof:name":"Djc Contracting Ltd",
    "wof:placetype":"venue"
},
  "geometry": {"coordinates":[-120.806702,56.508266],"type":"Point"}
}