{
  "type": "Feature",
  "properties": {
    "addr:full":"258 Soudan Ave Toronto ON M4S 1W4",
    "addr:housenumber":"258",
    "addr:postcode":"m4s 1w4",
    "addr:street":"Soudan Ave",
    "iso:country":"CA",
    "sg:address":"258 Soudan Ave",
    "sg:city":"Toronto",
    "sg:classifiers":[
        {
            "category":"Personal",
            "subcategory":"Shoe Repair & Shine",
            "type":"Services"
        }
    ],
    "sg:phone":"+1 416 484 7200",
    "sg:postcode":"M4S 1W4",
    "sg:province":"ON",
    "sg:tags":[
        "repairing",
        "boot"
    ],
    "wof:name":"Louis Shoe Repair",
    "wof:placetype":"venue"
},
  "geometry": {"coordinates":[-79.3887557983,43.7063179016],"type":"Point"}
}