{
  "type": "Feature",
  "properties": {
    "addr:full":"1558 Barrington St Halifax NS B3J 1Z6",
    "addr:housenumber":"1558",
    "addr:postcode":"ns b3j 1z6",
    "addr:street":"Barrington St",
    "iso:country":"CA",
    "sg:address":"1558 Barrington St",
    "sg:city":"Halifax",
    "sg:classifiers":[
        {
            "category":"Restaurant",
            "type":"Food & Drink"
        }
    ],
    "sg:phone":"+1 902 425 8882",
    "sg:postcode":"B3J 1Z6",
    "sg:province":"NS",
    "sg:tags":[
        "pizza"
    ],
    "wof:name":"Venus Pizza",
    "wof:placetype":"venue"
},
  "geometry": {"coordinates":[-63.5733642578,44.6454353333],"type":"Point"}
}