{
  "type": "Feature",
  "properties": {
    "addr:full":"5958 Telford Rd Prince George BC V2K 1V6",
    "addr:housenumber":"5958",
    "addr:postcode":"v2k 1v6",
    "addr:street":"Telford Rd",
    "iso:country":"CA",
    "sg:address":"5958 Telford Rd",
    "sg:city":"Prince George",
    "sg:classifiers":[
        {
            "category":"Building & Trades",
            "subcategory":"Construction",
            "type":"Services"
        }
    ],
    "sg:phone":"+1 250 962 7138",
    "sg:postcode":"V2K 1V6",
    "sg:province":"BC",
    "sg:tags":[
        "excavating",
        "contractor",
        "general"
    ],
    "wof:name":"Lobol Enterprises Ltd",
    "wof:placetype":"venue"
},
  "geometry": {"coordinates":[-122.777000427,53.9832420349],"type":"Point"}
}