{
  "type": "Feature",
  "properties": {
    "addr:full":"1551 Rue Du Couvent Laval QC H7W 3A7",
    "addr:housenumber":"1551",
    "addr:postcode":"h7w 3a7",
    "addr:street":"Rue Du Couvent",
    "iso:country":"CA",
    "sg:address":"1551 Rue Du Couvent",
    "sg:city":"Laval",
    "sg:classifiers":[
        {
            "category":"Building & Trades",
            "subcategory":"Electrical",
            "type":"Services"
        }
    ],
    "sg:phone":"+1 450 687 2660",
    "sg:postcode":"H7W 3A7",
    "sg:province":"QC",
    "sg:tags":[
        "electric",
        "contractor"
    ],
    "wof:name":"Cac Entrepreneur Electricien",
    "wof:placetype":"venue"
},
  "geometry": {"coordinates":[-73.76039123539999,45.5482368469],"type":"Point"}
}