{
  "type": "Feature",
  "properties": {
    "iso:country":"CA",
    "sg:address":"431 Ch Des Rgs 2-3",
    "sg:city":"Mancebourg",
    "sg:classifiers":[
        {
            "category":"Shopping",
            "subcategory":"Bicycles & Sporting Goods",
            "type":"Retail Goods"
        }
    ],
    "sg:phone":"+1 819 333 4756",
    "sg:postcode":"J0Z 2T0",
    "sg:province":"QC",
    "sg:tags":[
        "bait",
        "fishing"
    ],
    "wof:name":"Epicerie Paquin Enr",
    "wof:placetype":"venue"
},
  "geometry": {"coordinates":[-79.3288116455,48.7504234314],"type":"Point"}
}