{
  "type": "Feature",
  "properties": {
    "iso:country":"CA",
    "sg:address":"134 Doncaster Ave",
    "sg:city":"Thornhill",
    "sg:classifiers":[
        {
            "category":"Retail",
            "subcategory":"Auto Repair",
            "type":"Services"
        }
    ],
    "sg:phone":"+1 905 771 7476",
    "sg:postcode":"L3T 1L3",
    "sg:province":"ON",
    "sg:tags":[
        "repairing",
        "automobile",
        "inspection"
    ],
    "wof:name":"Sum Kim Drive Clean",
    "wof:placetype":"venue"
},
  "geometry": {"coordinates":[-79.4106140137,43.8057899475],"type":"Point"}
}