{
  "type": "Feature",
  "properties": {
    "addr:full":"6404 30 St SE Calgary AB T2C 1V6",
    "addr:housenumber":"6404",
    "addr:postcode":"t2c 1v6",
    "addr:street":"30 St Se",
    "iso:country":"CA",
    "sg:address":"6404 30 St SE",
    "sg:city":"Calgary",
    "sg:classifiers":[
        {
            "category":"Building & Trades",
            "subcategory":"Construction",
            "type":"Services"
        }
    ],
    "sg:phone":"+1 403 279 2840",
    "sg:postcode":"T2C 1V6",
    "sg:province":"AB",
    "wof:name":"Ronaco Industries Ltd",
    "wof:placetype":"venue"
},
  "geometry": {"coordinates":[-113.985603333,50.9969444275],"type":"Point"}
}