{
  "type": "Feature",
  "properties": {
    "addr:full":"1540 Northmount Dr NW Calgary AB T2L 0G6",
    "addr:housenumber":"1540",
    "addr:postcode":"t2l 0g6",
    "addr:street":"Northmount Dr Nw",
    "iso:country":"CA",
    "sg:address":"1540 Northmount Dr NW",
    "sg:city":"Calgary",
    "sg:classifiers":[
        {
            "category":"Real Estate",
            "subcategory":"Real Estate Operator",
            "type":"Services"
        }
    ],
    "sg:phone":"+1 403 282 6565",
    "sg:postcode":"T2L 0G6",
    "sg:province":"AB",
    "sg:tags":[
        "apartment"
    ],
    "wof:name":"Carroll Place",
    "wof:placetype":"venue"
},
  "geometry": {"coordinates":[-114.139801025,51.0961227417],"type":"Point"}
}