{
  "type": "Feature",
  "properties": {
    "addr:full":"Calgary AB T3E 1K9",
    "addr:postcode":"t3e 1k9",
    "iso:country":"CA",
    "sg:city":"Calgary",
    "sg:classifiers":[
        {
            "category":"Building & Trades",
            "subcategory":"Construction",
            "type":"Services"
        }
    ],
    "sg:phone":"+1 403 287 9840",
    "sg:postcode":"T3E 1K9",
    "sg:province":"AB",
    "sg:tags":[
        "repairing",
        "remodeling",
        "contractor"
    ],
    "wof:name":"Appollo Carpentry Svc",
    "wof:placetype":"venue"
},
  "geometry": {"coordinates":[-114.110275,51.005772],"type":"Point"}
}