{
  "type": "Feature",
  "properties": {
    "addr:full":"8340 Rue Baillarge Montreal QC H1L 3C1",
    "addr:housenumber":"8340",
    "addr:postcode":"h1l 3c1",
    "addr:street":"Rue Baillarge",
    "iso:country":"CA",
    "sg:address":"8340 Rue Baillarge",
    "sg:city":"Montreal",
    "sg:classifiers":[
        {
            "category":"Building & Trades",
            "subcategory":"Construction",
            "type":"Services"
        }
    ],
    "sg:phone":"+1 514 353 3990",
    "sg:postcode":"H1L 3C1",
    "sg:province":"QC",
    "sg:tags":[
        "contractor"
    ],
    "wof:name":"Pharaons Construction",
    "wof:placetype":"venue"
},
  "geometry": {"coordinates":[-73.5149688721,45.5950889587],"type":"Point"}
}