{
  "type": "Feature",
  "properties": {
    "iso:country":"CA",
    "sg:address":"745 Mount Pleasant Rd",
    "sg:city":"Toronto",
    "sg:classifiers":[
        {
            "category":"Retail",
            "subcategory":"Animal Services",
            "type":"Services"
        }
    ],
    "sg:phone":"+1 416 483 5194",
    "sg:postcode":"M4S 2N4",
    "sg:province":"ON",
    "sg:tags":[
        "pet",
        "grooming",
        "washing"
    ],
    "wof:name":"Mount Pleasant Pet Grooming",
    "wof:placetype":"venue"
},
  "geometry": {"coordinates":[-79.38962554930001,43.7075157166],"type":"Point"}
}