{
  "type": "Feature",
  "properties": {
    "addr:full":"558 15 Hwy Lombardy ON K0G 1L0",
    "addr:postcode":"k0g 1l0",
    "addr:street":"558 15 Hwy",
    "iso:country":"CA",
    "sg:address":"558 15 Hwy",
    "sg:city":"Lombardy",
    "sg:classifiers":[
        {
            "category":"Building & Trades",
            "subcategory":"Construction",
            "type":"Services"
        }
    ],
    "sg:phone":"+1 613 283 6572",
    "sg:postcode":"K0G 1L0",
    "sg:province":"ON",
    "sg:tags":[
        "excavating",
        "contractor"
    ],
    "wof:name":"Howard Burns Equipment Rental",
    "wof:placetype":"venue"
},
  "geometry": {"coordinates":[-76.06716918950001,44.8396263123],"type":"Point"}
}