{
  "type": "Feature",
  "properties": {
    "addr:full":"Surrey BC V3R 7Z1",
    "addr:postcode":"v3r 7z1",
    "iso:country":"CA",
    "sg:city":"Surrey",
    "sg:classifiers":[
        {
            "category":"Restaurant",
            "type":"Food & Drink"
        }
    ],
    "sg:phone":"+1 604 589 1929",
    "sg:postcode":"V3R 7Z1",
    "sg:province":"BC",
    "wof:name":"Hara's Buffet",
    "wof:placetype":"venue"
},
  "geometry": {"coordinates":[-122.802238464,49.1863288879],"type":"Point"}
}