{
  "type": "Feature",
  "properties": {
    "iso:country":"CA",
    "sg:address":"38 Mary St",
    "sg:city":"Chatham",
    "sg:classifiers":[
        {
            "category":"Building & Trades",
            "subcategory":"Landscaping Services",
            "type":"Services"
        }
    ],
    "sg:phone":"+1 519 351 3438",
    "sg:postcode":"N7L 1A4",
    "sg:province":"ON",
    "sg:tags":[
        "landscape",
        "contractor"
    ],
    "wof:name":"Greg Balie Landscape",
    "wof:placetype":"venue"
},
  "geometry": {"coordinates":[-82.1947250366,42.4029846191],"type":"Point"}
}