{
  "type": "Feature",
  "properties": {
    "addr:full":"Richmond BC V6X 1B8",
    "addr:postcode":"v6x 1b8",
    "iso:country":"CA",
    "sg:city":"Richmond",
    "sg:classifiers":[
        {
            "category":"Restaurant",
            "type":"Food & Drink"
        }
    ],
    "sg:phone":"+1 604 273 2639",
    "sg:postcode":"V6X 1B8",
    "sg:province":"BC",
    "wof:name":"Bridge Bakery Cafe",
    "wof:placetype":"venue"
},
  "geometry": {"coordinates":[-123.142487,49.172165],"type":"Point"}
}