{
  "type": "Feature",
  "properties": {
    "iso:country":"CA",
    "sg:address":"1329 Bay St",
    "sg:city":"Toronto",
    "sg:classifiers":[
        {
            "category":"Professional",
            "subcategory":"Business Services",
            "type":"Services"
        }
    ],
    "sg:phone":"+1 416 926 8200",
    "sg:postcode":"M5R 2C4",
    "sg:province":"ON",
    "sg:tags":[
        "lecture",
        "bureau",
        "seminar"
    ],
    "wof:name":"American Conference Institute",
    "wof:placetype":"venue"
},
  "geometry": {"coordinates":[-79.3906784058,43.6727256775],"type":"Point"}
}