{
  "type": "Feature",
  "properties": {
    "addr:full":"1375 Rue Joliot-Curie Boucherville QC J4B 7M4",
    "addr:housenumber":"1375",
    "addr:postcode":"j4b 7m4",
    "addr:street":"Rue Joliot-Curie",
    "iso:country":"CA",
    "sg:address":"1375 Rue Joliot-Curie",
    "sg:city":"Boucherville",
    "sg:classifiers":[
        {
            "category":"Building & Trades",
            "subcategory":"Construction",
            "type":"Services"
        }
    ],
    "sg:phone":"+1 450 449 2633",
    "sg:postcode":"J4B 7M4",
    "sg:province":"QC",
    "sg:tags":[
        "pile",
        "driving"
    ],
    "wof:name":"Geopac Inc",
    "wof:placetype":"venue"
},
  "geometry": {"coordinates":[-73.435074,45.558342],"type":"Point"}
}