{
  "type": "Feature",
  "properties": {
    "iso:country":"CA",
    "sg:address":"3640 Reginald Ave",
    "sg:city":"Furdale",
    "sg:classifiers":[
        {
            "category":"Manufacturing",
            "subcategory":"Building Materials",
            "type":"Manufacturing & Wholesale Goods"
        }
    ],
    "sg:phone":"+1 306 931 8000",
    "sg:postcode":"S7T 1B1",
    "sg:province":"SK",
    "sg:tags":[
        "maker",
        "cabinet"
    ],
    "wof:name":"David Woodworkers",
    "wof:placetype":"venue"
},
  "geometry": {"coordinates":[-106.68347930900001,52.0808258057],"type":"Point"}
}