{
  "type": "Feature",
  "properties": {
    "addr:full":"5 George St Brockville ON K6V 3V3",
    "addr:housenumber":"5",
    "addr:postcode":"k6v 3v3",
    "addr:street":"George St",
    "iso:country":"CA",
    "sg:address":"5 George St",
    "sg:city":"Brockville",
    "sg:classifiers":[
        {
            "category":"Professional",
            "subcategory":"Accounting & Tax Preparation",
            "type":"Services"
        }
    ],
    "sg:phone":"+1 613 498 4149",
    "sg:postcode":"K6V 3V3",
    "sg:province":"ON",
    "sg:tags":[
        "accountant"
    ],
    "wof:name":"Duncan, Beverley J CA",
    "wof:placetype":"venue"
},
  "geometry": {"coordinates":[-75.68586000000001,44.589661],"type":"Point"}
}