{
  "type": "Feature",
  "properties": {
    "addr:full":"Bobcaygeon ON K0M 1A0",
    "addr:postcode":"k0m 1a0",
    "iso:country":"CA",
    "sg:city":"Bobcaygeon",
    "sg:classifiers":[
        {
            "category":"Building & Trades",
            "subcategory":"Construction",
            "type":"Services"
        }
    ],
    "sg:phone":"+1 705 738 5000",
    "sg:postcode":"K0M 1A0",
    "sg:province":"ON",
    "sg:tags":[
        "real estate",
        "contractor",
        "developer"
    ],
    "wof:name":"Coachlamp Homes",
    "wof:placetype":"venue"
},
  "geometry": {"coordinates":[-78.5225448608,44.5216598511],"type":"Point"}
}