{
  "type": "Feature",
  "properties": {
    "addr:full":"404 Main St Grandview MB R0L 0Y0",
    "addr:housenumber":"404",
    "addr:postcode":"r0l 0y0",
    "addr:street":"Main St",
    "iso:country":"CA",
    "sg:address":"404 Main St",
    "sg:city":"Grandview",
    "sg:classifiers":[
        {
            "category":"Shopping",
            "subcategory":"Pharmacy",
            "type":"Retail Goods"
        }
    ],
    "sg:phone":"+1 204 546 2626",
    "sg:postcode":"R0L 0Y0",
    "sg:province":"MB",
    "wof:name":"Cairns Pharmacy Ltd",
    "wof:placetype":"venue"
},
  "geometry": {"coordinates":[-100.6996,51.168411],"type":"Point"}
}