{
  "type": "Feature",
  "properties": {
    "addr:full":"7575 Cambie St Vancouver BC V6P 3H6",
    "addr:housenumber":"7575",
    "addr:postcode":"v6p 3h6",
    "addr:street":"Cambie St",
    "iso:country":"CA",
    "sg:address":"7575 Cambie St",
    "sg:city":"Vancouver",
    "sg:classifiers":[
        {
            "category":"Health Services",
            "subcategory":"Doctor",
            "type":"Services"
        }
    ],
    "sg:phone":"+1 604 266 9171",
    "sg:postcode":"V6P 3H6",
    "sg:province":"BC",
    "sg:tags":[
        "dentist"
    ],
    "wof:name":"Maltz, Nathan J DDS",
    "wof:placetype":"venue"
},
  "geometry": {"coordinates":[-123.11721799999999,49.216267],"type":"Point"}
}