{
  "type": "Feature",
  "properties": {
    "addr:full":"215 Robinson Ave Lundbreck AB T0K 1H0",
    "addr:housenumber":"215",
    "addr:postcode":"t0k 1h0",
    "addr:street":"Robinson Ave",
    "iso:country":"CA",
    "sg:address":"215 Robinson Ave",
    "sg:city":"Lundbreck",
    "sg:classifiers":[
        {
            "category":"Education",
            "subcategory":"School",
            "type":"Public Place"
        }
    ],
    "sg:phone":"+1 403 628 3897",
    "sg:postcode":"T0K 1H0",
    "sg:province":"AB",
    "wof:name":"Livingstone School",
    "wof:placetype":"venue"
},
  "geometry": {"coordinates":[-114.164017,49.586849],"type":"Point"}
}