{
  "type": "Feature",
  "properties": {
    "addr:full":"576 Danforth Ave Toronto ON M4K 1R1",
    "addr:housenumber":"576",
    "addr:postcode":"m4k 1r1",
    "addr:street":"Danforth Ave",
    "iso:country":"CA",
    "sg:address":"576 Danforth Ave",
    "sg:city":"Toronto",
    "sg:classifiers":[
        {
            "category":"Restaurant",
            "type":"Food & Drink"
        }
    ],
    "sg:phone":"+1 416 466 2931",
    "sg:postcode":"M4K 1R1",
    "sg:province":"ON",
    "wof:name":"IL Fornello Restaurants",
    "wof:placetype":"venue"
},
  "geometry": {"coordinates":[-79.346619,43.678703],"type":"Point"}
}