{
  "type": "Feature",
  "properties": {
    "iso:country":"CA",
    "sg:address":"257 Boul Cure-Labelle",
    "sg:city":"Sainte-Rose",
    "sg:classifiers":[
        {
            "category":"Retail",
            "subcategory":"Auto Repair",
            "type":"Services"
        }
    ],
    "sg:phone":"+1 450 625 5547",
    "sg:postcode":"H7L 2Z9",
    "sg:province":"QC",
    "sg:tags":[
        "machine",
        "automobile",
        "body",
        "shop"
    ],
    "wof:name":"Garage Andre Hebert Inc",
    "wof:placetype":"venue"
},
  "geometry": {"coordinates":[-73.78927612299999,45.5997390747],"type":"Point"}
}