{
  "type": "Feature",
  "properties": {
    "iso:country":"CA",
    "sg:address":"44 Main St",
    "sg:city":"Zurich",
    "sg:classifiers":[
        {
            "category":"Autos & Motor Vehicles",
            "subcategory":"Fuel & Gas Station",
            "type":"Retail Goods"
        }
    ],
    "sg:phone":"+1 519 236 7223",
    "sg:postcode":"N0M 2T0",
    "sg:province":"ON",
    "sg:tags":[
        "oil"
    ],
    "wof:name":"Zurich Gas Bar",
    "wof:placetype":"venue"
},
  "geometry": {"coordinates":[-81.6253356934,43.4212532043],"type":"Point"}
}