{
  "type": "Feature",
  "properties": {
    "iso:country":"CA",
    "sg:address":"6600 Aut Transcanadienne #615",
    "sg:city":"Pointe-Claire",
    "sg:classifiers":[
        {
            "category":"Wholesale",
            "subcategory":"Durable Goods & Equipment",
            "type":"Manufacturing & Wholesale Goods"
        }
    ],
    "sg:phone":"+1 514 697 1602",
    "sg:postcode":"H9R 4S2",
    "sg:province":"QC",
    "sg:tags":[
        "electronic",
        "representative"
    ],
    "wof:name":"Canadian Source Corp",
    "wof:placetype":"venue"
},
  "geometry": {"coordinates":[-73.838219,45.457832],"type":"Point"}
}