{
  "type": "Feature",
  "properties": {
    "addr:full":"200 Clinton St Toronto ON M6G 2Y5",
    "addr:housenumber":"200",
    "addr:postcode":"m6g 2y5",
    "addr:street":"Clinton St",
    "iso:country":"CA",
    "sg:address":"200 Clinton St",
    "sg:city":"Toronto",
    "sg:classifiers":[
        {
            "category":"Education",
            "subcategory":"Special Training",
            "type":"Public Place"
        }
    ],
    "sg:phone":"+1 416 531 9797",
    "sg:postcode":"M6G 2Y5",
    "sg:province":"ON",
    "sg:tags":[
        "management"
    ],
    "wof:name":"Call Consulting Group Inc",
    "wof:placetype":"venue"
},
  "geometry": {"coordinates":[-79.41567999999999,43.659409],"type":"Point"}
}