{
  "type": "Feature",
  "properties": {
    "addr:full":"785 Boul Industriel Mascouche QC J7K 2Z1",
    "addr:housenumber":"785",
    "addr:postcode":"j7k 2z1",
    "addr:street":"Boul Industriel",
    "iso:country":"CA",
    "sg:address":"785 Boul Industriel",
    "sg:city":"Mascouche",
    "sg:classifiers":[
        {
            "category":"Autos & Motor Vehicles",
            "subcategory":"Auto Supplies",
            "type":"Retail Goods"
        }
    ],
    "sg:phone":"+1 450 474 4163",
    "sg:postcode":"J7K 2Z1",
    "sg:province":"QC",
    "sg:tags":[
        "repairing",
        "automobile"
    ],
    "wof:name":"Pneu Lamater",
    "wof:placetype":"venue"
},
  "geometry": {"coordinates":[-73.591194,45.73856],"type":"Point"}
}