{
  "type": "Feature",
  "properties": {
    "addr:full":"100 Mile House BC V0K 2E0",
    "addr:postcode":"v0k 2e0",
    "iso:country":"CA",
    "sg:city":"100 Mile House",
    "sg:classifiers":[
        {
            "category":"Food & Beverages",
            "subcategory":"Bakery",
            "type":"Retail Goods"
        }
    ],
    "sg:phone":"+1 250 395 3444",
    "sg:postcode":"V0K 2E0",
    "sg:province":"BC",
    "sg:tags":[
        "baker"
    ],
    "wof:name":"Paninos Bakery & Cafe Ltd",
    "wof:placetype":"venue"
},
  "geometry": {"coordinates":[-121.391159,51.314026],"type":"Point"}
}