{
  "type": "Feature",
  "properties": {
    "addr:full":"2090 55E Av Dorval QC H9P 1H1",
    "addr:housenumber":"2090",
    "addr:postcode":"h9p 1h1",
    "addr:street":"55E Av",
    "iso:country":"CA",
    "sg:address":"2090 55E Av",
    "sg:city":"Dorval",
    "sg:classifiers":[
        {
            "category":"Manufacturing",
            "subcategory":"Tools & Machinery",
            "type":"Manufacturing & Wholesale Goods"
        }
    ],
    "sg:phone":"+1 514 631 3492",
    "sg:postcode":"H9P 1H1",
    "sg:province":"QC",
    "sg:tags":[
        "machine",
        "shop"
    ],
    "wof:name":"M G Lonic Inc",
    "wof:placetype":"venue"
},
  "geometry": {"coordinates":[-73.727852,45.463409],"type":"Point"}
}