{
  "type": "Feature",
  "properties": {
    "iso:country":"CA",
    "sg:city":"Saint-Leonard",
    "sg:classifiers":[
        {
            "category":"Professional",
            "subcategory":"Lawyer & Legal Services",
            "type":"Services"
        }
    ],
    "sg:phone":"+1 514 253 3338",
    "sg:postcode":"H1S 3E8",
    "sg:province":"QC",
    "sg:tags":[
        "attorney"
    ],
    "wof:name":"Doyon Izzi & Nivoix",
    "wof:placetype":"venue"
},
  "geometry": {"coordinates":[-73.575485,45.591808],"type":"Point"}
}