{
  "type": "Feature",
  "properties": {
    "addr:full":"16 F. Tribe Rd Perth-Andover NB E7H 3R6",
    "addr:housenumber":"16",
    "addr:postcode":"e7h 3r6",
    "addr:street":"F. Tribe Rd",
    "iso:country":"CA",
    "sg:address":"16 F. Tribe Rd",
    "sg:city":"Perth-Andover",
    "sg:classifiers":[
        {
            "category":"Food & Beverages",
            "subcategory":"Groceries & Convenience Stores",
            "type":"Retail Goods"
        }
    ],
    "sg:phone":"+1 506 273 2221",
    "sg:postcode":"E7H 3R6",
    "sg:province":"NB",
    "sg:tags":[
        "grocer"
    ],
    "wof:name":"Andover Perth United Farmers",
    "wof:placetype":"venue"
},
  "geometry": {"coordinates":[-67.7169342041,46.7491607666],"type":"Point"}
}