{
  "type": "Feature",
  "properties": {
    "addr:full":"875 St Clair Ave W Toronto ON M6C 1C4",
    "addr:housenumber":"875",
    "addr:postcode":"m6c 1c4",
    "addr:street":"St Clair Ave W",
    "iso:country":"CA",
    "sg:address":"875 St Clair Ave W",
    "sg:city":"Toronto",
    "sg:classifiers":[
        {
            "category":"Shopping",
            "subcategory":"Department Store",
            "type":"Retail Goods"
        }
    ],
    "sg:phone":"+1 416 651 4400",
    "sg:postcode":"M6C 1C4",
    "sg:province":"ON",
    "sg:tags":[
        "shop"
    ],
    "wof:name":"Dollar Club",
    "wof:placetype":"venue"
},
  "geometry": {"coordinates":[-79.43305206300001,43.6800193787],"type":"Point"}
}