{
  "type": "Feature",
  "properties": {
    "addr:full":"5402 47 St Red Deer AB T4N 6Z4",
    "addr:housenumber":"5402",
    "addr:postcode":"t4n 6z4",
    "addr:street":"47 St",
    "iso:country":"CA",
    "sg:address":"5402 47 St",
    "sg:city":"Red Deer",
    "sg:classifiers":[
        {
            "category":"Cinema",
            "subcategory":"Movie Theater",
            "type":"Entertainment"
        }
    ],
    "sg:phone":"+1 403 346 1300",
    "sg:postcode":"T4N 6Z4",
    "sg:province":"AB",
    "wof:name":"Carnival Cinemas",
    "wof:placetype":"venue"
},
  "geometry": {"coordinates":[-113.821991,52.267338],"type":"Point"}
}