{
  "type": "Feature",
  "properties": {
    "addr:full":"Winnipeg MB R2G 3G6",
    "addr:postcode":"r2g 3g6",
    "iso:country":"CA",
    "sg:city":"Winnipeg",
    "sg:classifiers":[
        {
            "category":"Personal",
            "subcategory":"Beauty Salon",
            "type":"Services"
        }
    ],
    "sg:phone":"+1 204 338 0434",
    "sg:postcode":"R2G 3G6",
    "sg:province":"MB",
    "wof:name":"Lina's Hair Studio",
    "wof:placetype":"venue"
},
  "geometry": {"coordinates":[-97.09243011469999,49.9371948242],"type":"Point"}
}