{
  "type": "Feature",
  "properties": {
    "addr:full":"408 Queen St S Blyth ON N0M 1H0",
    "addr:housenumber":"408",
    "addr:postcode":"n0m 1h0",
    "addr:street":"Queen St S",
    "iso:country":"CA",
    "sg:address":"408 Queen St S",
    "sg:city":"Blyth",
    "sg:classifiers":[
        {
            "category":"Shopping",
            "type":"Retail Goods"
        }
    ],
    "sg:phone":"+1 519 523 4944",
    "sg:postcode":"N0M 1H0",
    "sg:province":"ON",
    "sg:tags":[
        "picture",
        "frame",
        "art",
        "gallery",
        "dealer"
    ],
    "wof:name":"Green Gallery",
    "wof:placetype":"venue"
},
  "geometry": {"coordinates":[-81.429451,43.736053],"type":"Point"}
}