{
  "type": "Feature",
  "properties": {
    "addr:full":"369 Huron St Woodstock ON N4S 7A5",
    "addr:housenumber":"369",
    "addr:postcode":"n4s 7a5",
    "addr:street":"Huron St",
    "iso:country":"CA",
    "sg:address":"369 Huron St",
    "sg:city":"Woodstock",
    "sg:classifiers":[
        {
            "category":"Health Services",
            "subcategory":"Hospital",
            "type":"Services"
        }
    ],
    "sg:phone":"+1 519 537 8162",
    "sg:postcode":"N4S 7A5",
    "sg:province":"ON",
    "wof:name":"Woodstock Private Hospital",
    "wof:placetype":"venue"
},
  "geometry": {"coordinates":[-80.751389,43.142849],"type":"Point"}
}