{
  "type": "Feature",
  "properties": {
    "addr:full":"4475 Airfield Rd Barriere BC V0E 1E0",
    "addr:housenumber":"4475",
    "addr:postcode":"bc v0e 1e0",
    "addr:street":"Airfield Rd",
    "iso:country":"CA",
    "sg:address":"4475 Airfield Rd",
    "sg:city":"Barriere",
    "sg:classifiers":[
        {
            "category":"Education",
            "subcategory":"School",
            "type":"Public Place"
        }
    ],
    "sg:phone":"+1 250 672 9916",
    "sg:postcode":"V0E 1E0",
    "sg:province":"BC",
    "wof:name":"Barriere Elementary School",
    "wof:placetype":"venue"
},
  "geometry": {"coordinates":[-120.12840271,51.1827659607],"type":"Point"}
}