{
  "type": "Feature",
  "properties": {
    "addr:full":"2052 41st Ave W # 200 Vancouver BC V6M 1Y8",
    "addr:housenumber":"2052",
    "addr:postcode":"v6m 1y8",
    "addr:street":"41St Ave W # 200",
    "iso:country":"CA",
    "sg:address":"2052 41st Ave W # 200",
    "sg:city":"Vancouver",
    "sg:classifiers":[
        {
            "category":"Banks & Credit Unions",
            "subcategory":"Investment Brokerage",
            "type":"Services"
        }
    ],
    "sg:phone":"+1 604 228 7777",
    "sg:postcode":"V6M 1Y8",
    "sg:province":"BC",
    "sg:tags":[
        "consultant",
        "planning",
        "financial"
    ],
    "wof:name":"Investors Group Financial Svc",
    "wof:placetype":"venue"
},
  "geometry": {"coordinates":[-123.153503418,49.2343902588],"type":"Point"}
}