{
  "type": "Feature",
  "properties": {
    "iso:country":"CA",
    "sg:address":"8130 Silver Star Rd",
    "sg:city":"Vernon",
    "sg:classifiers":[
        {
            "category":"Retail",
            "subcategory":"Animal Services",
            "type":"Services"
        }
    ],
    "sg:phone":"+1 250 545 1620",
    "sg:postcode":"V1B 3N1",
    "sg:province":"BC",
    "sg:tags":[
        "pet",
        "grooming",
        "washing"
    ],
    "wof:name":"Pretty Pooch Dog Groom",
    "wof:placetype":"venue"
},
  "geometry": {"coordinates":[-119.209350586,50.3081283569],"type":"Point"}
}