{
  "type": "Feature",
  "properties": {
    "iso:country":"CA",
    "sg:address":"760 Notre Dame Ave",
    "sg:city":"Sudbury",
    "sg:classifiers":[
        {
            "category":"Shopping",
            "subcategory":"Used Merchandise",
            "type":"Retail Goods"
        }
    ],
    "sg:phone":"+1 705 525 5100",
    "sg:postcode":"P3A 2T4",
    "sg:province":"ON",
    "sg:tags":[
        "second",
        "wiping",
        "store",
        "hand"
    ],
    "wof:name":"Jarrett Value Ctr",
    "wof:placetype":"venue"
},
  "geometry": {"coordinates":[-80.98616027830001,46.5109672546],"type":"Point"}
}