{
  "type": "Feature",
  "properties": {
    "addr:full":"4925 51st Ave Barrhead AB T7N 1A2",
    "addr:housenumber":"4925",
    "addr:postcode":"t7n 1a2",
    "addr:street":"51St Ave",
    "iso:country":"CA",
    "sg:address":"4925 51st Ave",
    "sg:city":"Barrhead",
    "sg:classifiers":[
        {
            "category":"Organizations",
            "subcategory":"Non-profit Organization",
            "type":"Services"
        }
    ],
    "sg:phone":"+1 780 674 4944",
    "sg:postcode":"T7N 1A2",
    "sg:province":"AB",
    "sg:tags":[
        "disability"
    ],
    "wof:name":"Blue Heron Support Svc Assn",
    "wof:placetype":"venue"
},
  "geometry": {"coordinates":[-114.403885,54.12019],"type":"Point"}
}