{
  "type": "Feature",
  "properties": {
    "addr:full":"100 1E Rue N Thetford Mines QC G6G 4Y2",
    "addr:housenumber":"100",
    "addr:postcode":"g6g 4y2",
    "addr:street":"1E Rue N",
    "iso:country":"CA",
    "sg:address":"100 1E Rue N",
    "sg:city":"Thetford Mines",
    "sg:classifiers":[
        {
            "category":"Health Services",
            "subcategory":"Optometrist",
            "type":"Services"
        }
    ],
    "sg:phone":"+1 418 335 5600",
    "sg:postcode":"G6G 4Y2",
    "sg:province":"QC",
    "wof:name":"Acces A L'Optometrie Croteau",
    "wof:placetype":"venue"
},
  "geometry": {"coordinates":[-71.289383,46.099792],"type":"Point"}
}