{
  "type": "Feature",
  "properties": {
    "addr:full":"28 Glenridge Ave Bridgewater NS B4V 1T5",
    "addr:housenumber":"28",
    "addr:postcode":"b4v 1t5",
    "addr:street":"Glenridge Ave",
    "iso:country":"CA",
    "sg:address":"28 Glenridge Ave",
    "sg:city":"Bridgewater",
    "sg:classifiers":[
        {
            "category":"Building & Trades",
            "subcategory":"Construction",
            "type":"Services"
        }
    ],
    "sg:phone":"+1 902 543 1332",
    "sg:postcode":"B4V 1T5",
    "sg:province":"NS",
    "sg:tags":[
        "general",
        "contractor"
    ],
    "wof:name":"Dexter Construction Ltd",
    "wof:placetype":"venue"
},
  "geometry": {"coordinates":[-64.52694700000001,44.373756],"type":"Point"}
}