{
  "type": "Feature",
  "properties": {
    "addr:full":"101 Powell St Vancouver BC V6A 1G2",
    "addr:housenumber":"101",
    "addr:postcode":"v6a 1g2",
    "addr:street":"Powell St",
    "iso:country":"CA",
    "sg:address":"101 Powell St",
    "sg:city":"Vancouver",
    "sg:classifiers":[
        {
            "category":"Education",
            "subcategory":"School",
            "type":"Public Place"
        }
    ],
    "sg:phone":"+1 604 713 5760",
    "sg:postcode":"V6A 1G2",
    "sg:province":"BC",
    "wof:name":"Adult Education Ctr",
    "wof:placetype":"venue"
},
  "geometry": {"coordinates":[-123.10189800000001,49.28339],"type":"Point"}
}