{
  "type": "Feature",
  "properties": {
    "addr:full":"550 Berry St Winnipeg MB R3H 0R9",
    "addr:housenumber":"550",
    "addr:postcode":"r3h 0r9",
    "addr:street":"Berry St",
    "iso:country":"CA",
    "sg:address":"550 Berry St",
    "sg:city":"Winnipeg",
    "sg:classifiers":[
        {
            "category":"Professional",
            "subcategory":"Business Services",
            "type":"Services"
        }
    ],
    "sg:phone":"+1 204 786 7630",
    "sg:postcode":"R3H 0R9",
    "sg:province":"MB",
    "sg:tags":[
        "paging",
        "answering",
        "telemarketing"
    ],
    "wof:name":"Integrated Messaging Inc",
    "wof:placetype":"venue"
},
  "geometry": {"coordinates":[-97.2103805542,49.8921546936],"type":"Point"}
}