{
  "type": "Feature",
  "properties": {
    "addr:full":"Okotoks AB T1S 1A4",
    "addr:postcode":"t1s 1a4",
    "iso:country":"CA",
    "sg:city":"Okotoks",
    "sg:classifiers":[
        {
            "category":"Professional",
            "subcategory":"Business Services",
            "type":"Services"
        }
    ],
    "sg:phone":"+1 403 938 4855",
    "sg:postcode":"T1S 1A4",
    "sg:province":"AB",
    "sg:tags":[
        "blind",
        "consultant",
        "venetian",
        "design",
        "interior",
        "decorator"
    ],
    "wof:name":"Mc Laughlin Interiors",
    "wof:placetype":"venue"
},
  "geometry": {"coordinates":[-113.976868,50.725437],"type":"Point"}
}