{
  "type": "Feature",
  "properties": {
    "addr:full":"Brandon MB R7A 6X7",
    "addr:postcode":"r7a 6x7",
    "iso:country":"CA",
    "sg:city":"Brandon",
    "sg:classifiers":[
        {
            "category":"Shopping",
            "subcategory":"Clothing, Apparel, & Fashions",
            "type":"Retail Goods"
        }
    ],
    "sg:phone":"+1 204 725 1546",
    "sg:postcode":"R7A 6X7",
    "sg:province":"MB",
    "wof:name":"Warehouse One-the Jean Store",
    "wof:placetype":"venue"
},
  "geometry": {"coordinates":[-99.962204,49.829182],"type":"Point"}
}