{
  "type": "Feature",
  "properties": {
    "addr:full":"Brussels ON N0G 1H0",
    "addr:postcode":"n0g 1h0",
    "iso:country":"CA",
    "sg:city":"Brussels",
    "sg:classifiers":[
        {
            "category":"Wholesale",
            "subcategory":"Farm Supplies",
            "type":"Manufacturing & Wholesale Goods"
        }
    ],
    "sg:phone":"+1 519 887 6461",
    "sg:postcode":"N0G 1H0",
    "sg:province":"ON",
    "sg:tags":[
        "livestock"
    ],
    "wof:name":"Brussels Livestock",
    "wof:placetype":"venue"
},
  "geometry": {"coordinates":[-81.251663208,43.7418518066],"type":"Point"}
}