{
  "type": "Feature",
  "properties": {
    "addr:full":"1744 Rue William Montreal QC H3J 1R4",
    "addr:housenumber":"1744",
    "addr:postcode":"h3j 1r4",
    "addr:street":"Rue William",
    "iso:country":"CA",
    "sg:address":"1744 Rue William",
    "sg:city":"Montreal",
    "sg:classifiers":[
        {
            "category":"Professional",
            "subcategory":"Computer Services",
            "type":"Services"
        }
    ],
    "sg:phone":"+1 514 935 1155",
    "sg:postcode":"H3J 1R4",
    "sg:province":"QC",
    "sg:tags":[
        "consultant"
    ],
    "wof:name":"Procad Consultants",
    "wof:placetype":"venue"
},
  "geometry": {"coordinates":[-73.5662307739,45.4878540039],"type":"Point"}
}