{
  "type": "Feature",
  "properties": {
    "addr:full":"1380 Boul DE LA Cote-Vertu Saint-Laurent QC H4L 1Z4",
    "addr:housenumber":"1380",
    "addr:postcode":"h4l 1z4",
    "addr:street":"Boul De La Cote-Vertu",
    "iso:country":"CA",
    "sg:address":"1380 Boul DE LA Cote-Vertu",
    "sg:city":"Saint-Laurent",
    "sg:classifiers":[
        {
            "category":"Retail",
            "subcategory":"Auto Repair",
            "type":"Services"
        }
    ],
    "sg:phone":"+1 514 744 2256",
    "sg:postcode":"H4L 1Z4",
    "sg:province":"QC",
    "sg:tags":[
        "repairing",
        "automobile"
    ],
    "wof:name":"Garage Andre Beauregard",
    "wof:placetype":"venue"
},
  "geometry": {"coordinates":[-73.68096160890001,45.5154342651],"type":"Point"}
}