{
  "type": "Feature",
  "properties": {
    "iso:country":"CA",
    "sg:city":"Montreal",
    "sg:classifiers":[
        {
            "category":"Shopping",
            "type":"Retail Goods"
        }
    ],
    "sg:phone":"+1 514 374 3630",
    "sg:postcode":"H2A 1X4",
    "sg:province":"QC",
    "sg:tags":[
        "miscellaneous",
        "store"
    ],
    "wof:name":"Librairie Erotique",
    "wof:placetype":"venue"
},
  "geometry": {"coordinates":[-73.595421,45.562313],"type":"Point"}
}