{
  "type": "Feature",
  "properties": {
    "addr:full":"67 Rue Fusey Cap-DE-LA-Madeleine QC G8T 2T9",
    "addr:housenumber":"67",
    "addr:postcode":"g8t 2t9",
    "addr:street":"Rue Fusey",
    "iso:country":"CA",
    "sg:address":"67 Rue Fusey",
    "sg:city":"Cap-DE-LA-Madeleine",
    "sg:classifiers":[
        {
            "category":"Personal",
            "subcategory":"Barber",
            "type":"Services"
        }
    ],
    "sg:phone":"+1 819 376 7162",
    "sg:postcode":"G8T 2T9",
    "sg:province":"QC",
    "wof:name":"Salon DE Coiffure A Thibault",
    "wof:placetype":"venue"
},
  "geometry": {"coordinates":[-72.52795399999999,46.365131],"type":"Point"}
}