{
  "type": "Feature",
  "properties": {
    "addr:full":"Dollard-Des-Ormeaux QC H9H 3X4",
    "addr:postcode":"h9h 3x4",
    "iso:country":"CA",
    "sg:city":"Dollard-Des-Ormeaux",
    "sg:classifiers":[
        {
            "category":"Wholesale",
            "subcategory":"Office Equipment",
            "type":"Manufacturing & Wholesale Goods"
        }
    ],
    "sg:phone":"+1 514 626 4888",
    "sg:postcode":"H9H 3X4",
    "sg:province":"QC",
    "sg:tags":[
        "accounting",
        "bookkeeping",
        "system"
    ],
    "wof:name":"Wintax",
    "wof:placetype":"venue"
},
  "geometry": {"coordinates":[-73.842590332,45.4805107117],"type":"Point"}
}