{
  "type": "Feature",
  "properties": {
    "addr:full":"Melville SK S0A 2P0",
    "addr:postcode":"s0a 2p0",
    "iso:country":"CA",
    "sg:city":"Melville",
    "sg:classifiers":[
        {
            "category":"Freight",
            "type":"Transportation"
        }
    ],
    "sg:phone":"+1 306 728 5742",
    "sg:postcode":"S0A 2P0",
    "sg:province":"SK",
    "sg:tags":[
        "grain",
        "elevator"
    ],
    "wof:name":"Agricore United",
    "wof:placetype":"venue"
},
  "geometry": {"coordinates":[-102.79547100000001,50.923813],"type":"Point"}
}