{
  "type": "Feature",
  "properties": {
    "addr:full":"11000 Rue Saint-Denis Montreal QC H3L 2J9",
    "addr:housenumber":"11000",
    "addr:postcode":"h3l 2j9",
    "addr:street":"Rue Saint-Denis",
    "iso:country":"CA",
    "sg:address":"11000 Rue Saint-Denis",
    "sg:city":"Montreal",
    "sg:classifiers":[
        {
            "category":"Professional",
            "subcategory":"Computer Services",
            "type":"Services"
        }
    ],
    "sg:phone":"+1 514 385 0358",
    "sg:postcode":"H3L 2J9",
    "sg:province":"QC",
    "sg:tags":[
        "consultant"
    ],
    "wof:name":"Progiciel Marketing Inc",
    "wof:placetype":"venue"
},
  "geometry": {"coordinates":[-73.67377500000001,45.555161],"type":"Point"}
}