{
  "type": "Feature",
  "properties": {
    "addr:full":"50 Victoria S Southampton ON N0H 2L0",
    "addr:housenumber":"50",
    "addr:postcode":"n0h 2l0",
    "addr:street":"Victoria S",
    "iso:country":"CA",
    "sg:address":"50 Victoria S",
    "sg:city":"Southampton",
    "sg:classifiers":[
        {
            "category":"Government",
            "subcategory":"Fire Station",
            "type":"Public Place"
        }
    ],
    "sg:phone":"+1 ",
    "sg:postcode":"N0H 2L0",
    "sg:province":"ON",
    "sg:tags":[
        "department"
    ],
    "wof:name":"Southampton Fire Hall",
    "wof:placetype":"venue"
},
  "geometry": {"coordinates":[-81.3704528809,44.4932746887],"type":"Point"}
}