{
  "type": "Feature",
  "properties": {
    "addr:full":"26 Blevins Pl Toronto ON M5A 3M4",
    "addr:housenumber":"26",
    "addr:postcode":"m5a 3m4",
    "addr:street":"Blevins Pl",
    "iso:country":"CA",
    "sg:address":"26 Blevins Pl",
    "sg:city":"Toronto",
    "sg:classifiers":[
        {
            "category":"Social Services",
            "subcategory":"Child Care",
            "type":"Services"
        }
    ],
    "sg:phone":"+1 416 392 5517",
    "sg:postcode":"M5A 3M4",
    "sg:province":"ON",
    "sg:tags":[
        "government"
    ],
    "wof:name":"Toronto Child Care Ctr",
    "wof:placetype":"venue"
},
  "geometry": {"coordinates":[-79.359764,43.659138],"type":"Point"}
}