{
  "type": "Feature",
  "properties": {
    "iso:country":"CA",
    "sg:address":"RR 2",
    "sg:city":"Godfrey",
    "sg:classifiers":[
        {
            "category":"Food & Beverages",
            "subcategory":"Fruits & Vegetables",
            "type":"Retail Goods"
        }
    ],
    "sg:phone":"+1 613 273 7555",
    "sg:postcode":"K0H 1T0",
    "sg:province":"ON",
    "sg:tags":[
        "produce"
    ],
    "wof:name":"Burridge Market Garden & Chip",
    "wof:placetype":"venue"
},
  "geometry": {"coordinates":[-76.67906188960001,44.5431137085],"type":"Point"}
}