{
  "type": "Feature",
  "properties": {
    "addr:full":"2 Downes Ave Picton ON K0K 2T0",
    "addr:housenumber":"2",
    "addr:postcode":"k0k 2t0",
    "addr:street":"Downes Ave",
    "iso:country":"CA",
    "sg:address":"2 Downes Ave",
    "sg:city":"Picton",
    "sg:classifiers":[
        {
            "category":"Organizations",
            "subcategory":"Religious Organization",
            "type":"Services"
        }
    ],
    "sg:phone":"+1 613 476 2622",
    "sg:postcode":"K0K 2T0",
    "sg:province":"ON",
    "sg:tags":[
        "church"
    ],
    "wof:name":"Gilead Fellowship",
    "wof:placetype":"venue"
},
  "geometry": {"coordinates":[-77.14673614500001,44.0065155029],"type":"Point"}
}