{
  "type": "Feature",
  "properties": {
    "addr:full":"327 Ontario St St Catharines ON L2R 5L3",
    "addr:housenumber":"327",
    "addr:postcode":"l2r 5l3",
    "addr:street":"Ontario St",
    "iso:country":"CA",
    "sg:address":"327 Ontario St",
    "sg:city":"St Catharines",
    "sg:classifiers":[
        {
            "category":"Banks & Credit Unions",
            "subcategory":"Bank",
            "type":"Services"
        }
    ],
    "sg:phone":"+1 905 684 8333",
    "sg:postcode":"L2R 5L3",
    "sg:province":"ON",
    "wof:name":"Scotiabank",
    "wof:placetype":"venue"
},
  "geometry": {"coordinates":[-79.264679,43.170139],"type":"Point"}
}