{
  "type": "Feature",
  "properties": {
    "addr:full":"Mindemoya ON P0P 1S0",
    "addr:postcode":"p0p 1s0",
    "iso:country":"CA",
    "sg:city":"Mindemoya",
    "sg:classifiers":[
        {
            "category":"Travel",
            "subcategory":"Hotels & Motels",
            "type":"Entertainment"
        }
    ],
    "sg:phone":"+1 705 377 4075",
    "sg:postcode":"P0P 1S0",
    "sg:province":"ON",
    "sg:tags":[
        "tourist",
        "accommodation"
    ],
    "wof:name":"Maple Spring Cottages",
    "wof:placetype":"venue"
},
  "geometry": {"coordinates":[-82.14144899999999,45.741943],"type":"Point"}
}