{
  "type": "Feature",
  "properties": {
    "iso:country":"CA",
    "sg:city":"Brossard",
    "sg:classifiers":[
        {
            "category":"Social Services",
            "subcategory":"Job Training",
            "type":"Services"
        }
    ],
    "sg:phone":"+1 450 465 4078",
    "sg:postcode":"J4W 3J9",
    "sg:province":"QC",
    "sg:tags":[
        "career",
        "counseling",
        "employment",
        "vocational"
    ],
    "wof:name":"DE Soi A L'Emploi",
    "wof:placetype":"venue"
},
  "geometry": {"coordinates":[-73.474571,45.473835],"type":"Point"}
}