{
  "type": "Feature",
  "properties": {
    "addr:full":"1625 Wilson Ave North York ON M3L 1A5",
    "addr:housenumber":"1625",
    "addr:postcode":"m3l 1a5",
    "addr:street":"Wilson Ave",
    "iso:country":"CA",
    "sg:address":"1625 Wilson Ave",
    "sg:city":"North York",
    "sg:classifiers":[
        {
            "category":"Recreation",
            "type":"Entertainment"
        }
    ],
    "sg:phone":"+1 416 244 1984",
    "sg:postcode":"M3L 1A5",
    "sg:province":"ON",
    "sg:tags":[
        "parlor",
        "billiard"
    ],
    "wof:name":"Inside the Corner Pocket",
    "wof:placetype":"venue"
},
  "geometry": {"coordinates":[-79.5133514404,43.7197647095],"type":"Point"}
}