{
  "type": "Feature",
  "properties": {
    "addr:full":"14528 River Line Thamesville ON N0P 2K0",
    "addr:housenumber":"14528",
    "addr:postcode":"n0p 2k0",
    "addr:street":"River Line",
    "iso:country":"CA",
    "sg:address":"14528 River Line",
    "sg:city":"Thamesville",
    "sg:classifiers":[
        {
            "category":"Organizations",
            "subcategory":"Membership Organization",
            "type":"Services"
        }
    ],
    "sg:phone":"+1 519 692 4141",
    "sg:postcode":"N0P 2K0",
    "sg:province":"ON",
    "wof:name":"Centre For Indigenous",
    "wof:placetype":"venue"
},
  "geometry": {"coordinates":[-81.9830627441,42.5336608887],"type":"Point"}
}