{
  "type": "Feature",
  "properties": {
    "addr:full":"613 Rue Albert LA Baie QC G7B 3L6",
    "addr:housenumber":"613",
    "addr:postcode":"g7b 3l6",
    "addr:street":"Rue Albert",
    "iso:country":"CA",
    "sg:address":"613 Rue Albert",
    "sg:city":"LA Baie",
    "sg:classifiers":[
        {
            "category":"Shopping",
            "subcategory":"Clothing, Apparel, & Fashions",
            "type":"Retail Goods"
        }
    ],
    "sg:phone":"+1 418 544 2836",
    "sg:postcode":"G7B 3L6",
    "sg:province":"QC",
    "sg:tags":[
        "furnishing"
    ],
    "wof:name":"Odina Simard Ltee",
    "wof:placetype":"venue"
},
  "geometry": {"coordinates":[-70.8817520142,48.3405685425],"type":"Point"}
}