{
  "type": "Feature",
  "properties": {
    "iso:country":"CA",
    "sg:address":"633 Granville St",
    "sg:city":"Vancouver",
    "sg:classifiers":[
        {
            "category":"Shopping",
            "subcategory":"Clothing, Apparel, & Fashions",
            "type":"Retail Goods"
        }
    ],
    "sg:phone":"+1 604 681 3121",
    "sg:postcode":"V7Y 1E4",
    "sg:province":"BC",
    "wof:name":"Holt Renfrew & CO Ltd",
    "wof:placetype":"venue"
},
  "geometry": {"coordinates":[-123.117088318,49.28332901],"type":"Point"}
}