{
  "type": "Feature",
  "properties": {
    "addr:full":"1475 St Edward Blvd N Lethbridge AB T1H 2P9",
    "addr:housenumber":"1475",
    "addr:postcode":"t1h 2p9",
    "addr:street":"St Edward Blvd N",
    "iso:country":"CA",
    "sg:address":"1475 St Edward Blvd N",
    "sg:city":"Lethbridge",
    "sg:classifiers":[
        {
            "category":"Bars & Pubs",
            "type":"Food & Drink"
        }
    ],
    "sg:phone":"+1 403 327 2589",
    "sg:postcode":"T1H 2P9",
    "sg:province":"AB",
    "wof:name":"Pop's Pub",
    "wof:placetype":"venue"
},
  "geometry": {"coordinates":[-112.831108,49.718754],"type":"Point"}
}