{
  "type": "Feature",
  "properties": {
    "iso:country":"CA",
    "sg:address":"26 Aberdeen St",
    "sg:city":"Kentville",
    "sg:classifiers":[
        {
            "category":"Banks & Credit Unions",
            "subcategory":"Bank",
            "type":"Services"
        }
    ],
    "sg:phone":"+1 902 678 7303",
    "sg:postcode":"B4N 2N1",
    "sg:province":"NS",
    "wof:name":"Bank of Montreal",
    "wof:placetype":"venue"
},
  "geometry": {"coordinates":[-64.496391,45.07856],"type":"Point"}
}