{
  "type": "Feature",
  "properties": {
    "addr:full":"1571 Rue Du Berry Charlesbourg QC G1G 5G7",
    "addr:housenumber":"1571",
    "addr:postcode":"g1g 5g7",
    "addr:street":"Rue Du Berry",
    "iso:country":"CA",
    "sg:address":"1571 Rue Du Berry",
    "sg:city":"Charlesbourg",
    "sg:classifiers":[
        {
            "category":"Building & Trades",
            "subcategory":"Electrical",
            "type":"Services"
        }
    ],
    "sg:phone":"+1 418 623 0511",
    "sg:postcode":"G1G 5G7",
    "sg:province":"QC",
    "sg:tags":[
        "electric",
        "contractor"
    ],
    "wof:name":"Patrick Latulippe Inc",
    "wof:placetype":"venue"
},
  "geometry": {"coordinates":[-71.288315,46.868546],"type":"Point"}
}