{
  "type": "Feature",
  "properties": {
    "addr:full":"Whitehorse YT Y1A 1A3",
    "addr:postcode":"y1a 1a3",
    "iso:country":"CA",
    "sg:city":"Whitehorse",
    "sg:classifiers":[
        {
            "category":"Insurance",
            "subcategory":"Insurance Agent",
            "type":"Services"
        }
    ],
    "sg:phone":"+1 867 668 4888",
    "sg:postcode":"Y1A 1A3",
    "sg:province":"YT",
    "sg:tags":[
        "adjuster"
    ],
    "wof:name":"Alcan Adjusters Inc",
    "wof:placetype":"venue"
},
  "geometry": {"coordinates":[-135.050827,60.72039],"type":"Point"}
}