{
  "type": "Feature",
  "properties": {
    "addr:full":"1607 Boreale Havre-Saint-Pierre QC G0G 1P0",
    "addr:housenumber":"1607",
    "addr:postcode":"g0g 1p0",
    "addr:street":"Boreale",
    "iso:country":"CA",
    "sg:address":"1607 Boreale",
    "sg:city":"Havre-Saint-Pierre",
    "sg:classifiers":[
        {
            "category":"Personal",
            "subcategory":"Beauty Salon",
            "type":"Services"
        }
    ],
    "sg:phone":"+1 418 538 1380",
    "sg:postcode":"G0G 1P0",
    "sg:province":"QC",
    "wof:name":"Clinique D'Esthetique Sonia",
    "wof:placetype":"venue"
},
  "geometry": {"coordinates":[-63.576031,50.250664],"type":"Point"}
}