{
  "type": "Feature",
  "properties": {
    "addr:full":"9 Boul D'Anjou Chateauguay QC J6J 2P6",
    "addr:housenumber":"9",
    "addr:postcode":"j6j 2p6",
    "addr:street":"Boul D'Anjou",
    "iso:country":"CA",
    "sg:address":"9 Boul D'Anjou",
    "sg:city":"Chateauguay",
    "sg:classifiers":[
        {
            "category":"Health Services",
            "subcategory":"Doctor",
            "type":"Services"
        }
    ],
    "sg:phone":"+1 450 698 0480",
    "sg:postcode":"J6J 2P6",
    "sg:province":"QC",
    "sg:tags":[
        "clinic"
    ],
    "wof:name":"Clinique DE Denturologie",
    "wof:placetype":"venue"
},
  "geometry": {"coordinates":[-73.740112,45.361485],"type":"Point"}
}