{
  "type": "Feature",
  "properties": {
    "addr:full":"3875 Main St Tracadie-Sheila NB E1X 1G5",
    "addr:housenumber":"3875",
    "addr:postcode":"e1x 1g5",
    "addr:street":"Main St",
    "iso:country":"CA",
    "sg:address":"3875 Main St",
    "sg:city":"Tracadie-Sheila",
    "sg:classifiers":[
        {
            "category":"Retail",
            "subcategory":"Funeral Services",
            "type":"Services"
        }
    ],
    "sg:phone":"+1 506 776 3766",
    "sg:postcode":"E1X 1G5",
    "sg:province":"NB",
    "sg:tags":[
        "director"
    ],
    "wof:name":"Salon Funeraire C Robichaud",
    "wof:placetype":"venue"
},
  "geometry": {"coordinates":[-64.909691,47.511028],"type":"Point"}
}