{
  "type": "Feature",
  "properties": {
    "addr:full":"555 Wilson Ave North York ON M3H 5Y6",
    "addr:housenumber":"555",
    "addr:postcode":"m3h 5y6",
    "addr:street":"Wilson Ave",
    "iso:country":"CA",
    "sg:address":"555 Wilson Ave",
    "sg:city":"North York",
    "sg:classifiers":[
        {
            "category":"Insurance",
            "subcategory":"Insurance Agent",
            "type":"Services"
        }
    ],
    "sg:phone":"+1 416 636 3575",
    "sg:postcode":"M3H 5Y6",
    "sg:province":"ON",
    "wof:name":"Travel Secure Ltd",
    "wof:placetype":"venue"
},
  "geometry": {"coordinates":[-79.4478530884,43.7343025208],"type":"Point"}
}