{
  "type": "Feature",
  "properties": {
    "addr:full":"1098 Heritage Rd Burlington ON L7L 4X9",
    "addr:housenumber":"1098",
    "addr:postcode":"l7l 4x9",
    "addr:street":"Heritage Rd",
    "iso:country":"CA",
    "sg:address":"1098 Heritage Rd",
    "sg:city":"Burlington",
    "sg:classifiers":[
        {
            "category":"Professional",
            "subcategory":"Accounting & Tax Preparation",
            "type":"Services"
        }
    ],
    "sg:phone":"+1 905 335 4000",
    "sg:postcode":"L7L 4X9",
    "sg:province":"ON",
    "sg:tags":[
        "accountant"
    ],
    "wof:name":"Fox, Robert I CA",
    "wof:placetype":"venue"
},
  "geometry": {"coordinates":[-79.78443908689999,43.3751716614],"type":"Point"}
}