{
  "type": "Feature",
  "properties": {
    "addr:full":"1104 Corydon Ave Winnipeg MB R3M 0Y8",
    "addr:housenumber":"1104",
    "addr:postcode":"r3m 0y8",
    "addr:street":"Corydon Ave",
    "iso:country":"CA",
    "sg:address":"1104 Corydon Ave",
    "sg:city":"Winnipeg",
    "sg:classifiers":[
        {
            "category":"Home & Garden",
            "subcategory":"Household Appliances",
            "type":"Retail Goods"
        }
    ],
    "sg:phone":"+1 204 475 7717",
    "sg:postcode":"R3M 0Y8",
    "sg:province":"MB",
    "sg:tags":[
        "cleaners",
        "vacuum"
    ],
    "wof:name":"River Heights Vacuum",
    "wof:placetype":"venue"
},
  "geometry": {"coordinates":[-97.16727400000001,49.866024],"type":"Point"}
}