{
  "type": "Feature",
  "properties": {
    "iso:country":"CA",
    "sg:address":"587 Rue Stanley",
    "sg:city":"Roxton Pond",
    "sg:classifiers":[
        {
            "category":"Retail",
            "subcategory":"Auto Repair",
            "type":"Services"
        }
    ],
    "sg:phone":"+1 450 372 7465",
    "sg:postcode":"J0E 1Z0",
    "sg:province":"QC",
    "sg:tags":[
        "body",
        "automobile",
        "painting"
    ],
    "wof:name":"Garage Jean Michaud Inc",
    "wof:placetype":"venue"
},
  "geometry": {"coordinates":[-72.6609573364,45.4760398865],"type":"Point"}
}