{
  "type": "Feature",
  "properties": {
    "addr:full":"North York ON M2J 1V7",
    "addr:postcode":"m2j 1v7",
    "iso:country":"CA",
    "sg:city":"North York",
    "sg:classifiers":[
        {
            "category":"Real Estate",
            "subcategory":"Real Estate Agent",
            "type":"Services"
        }
    ],
    "sg:phone":"+1 416 491 7440",
    "sg:postcode":"M2J 1V7",
    "sg:province":"ON",
    "sg:tags":[
        "convenience",
        "management",
        "store"
    ],
    "wof:name":"Monarch Construction Ltd",
    "wof:placetype":"venue"
},
  "geometry": {"coordinates":[-79.33637237550001,43.7755584717],"type":"Point"}
}