{
  "type": "Feature",
  "properties": {
    "addr:full":"141 Rue St Philippe Saint-Alban QC G0A 3B0",
    "addr:housenumber":"141",
    "addr:postcode":"g0a 3b0",
    "addr:street":"Rue St Philippe",
    "iso:country":"CA",
    "sg:address":"141 Rue St Philippe",
    "sg:city":"Saint-Alban",
    "sg:classifiers":[
        {
            "category":"Retail",
            "subcategory":"Auto Repair",
            "type":"Services"
        }
    ],
    "sg:phone":"+1 418 268 5142",
    "sg:postcode":"G0A 3B0",
    "sg:province":"QC",
    "sg:tags":[
        "repairing",
        "automobile"
    ],
    "wof:name":"Garage Rene Lefebvre",
    "wof:placetype":"venue"
},
  "geometry": {"coordinates":[-72.083778,46.720161],"type":"Point"}
}