{
  "type": "Feature",
  "properties": {
    "addr:full":"1700 Aimco Blvd Mississauga ON L4W 1V1",
    "addr:housenumber":"1700",
    "addr:postcode":"l4w 1v1",
    "addr:street":"Aimco Blvd",
    "iso:country":"CA",
    "sg:address":"1700 Aimco Blvd",
    "sg:city":"Mississauga",
    "sg:classifiers":[
        {
            "category":"Professional",
            "type":"Services"
        }
    ],
    "sg:phone":"+1 905 602 6102",
    "sg:postcode":"L4W 1V1",
    "sg:province":"ON",
    "sg:tags":[
        "establishment",
        "baker",
        "cookie",
        "bakery"
    ],
    "wof:name":"Furaliani's Food Corp",
    "wof:placetype":"venue"
},
  "geometry": {"coordinates":[-79.6201477051,43.6429748535],"type":"Point"}
}