{
  "type": "Feature",
  "properties": {
    "addr:full":"495 Av Brochu Sept-Iles QC G4R 2X2",
    "addr:housenumber":"495",
    "addr:postcode":"g4r 2x2",
    "addr:street":"Av Brochu Sept-Iles",
    "iso:country":"CA",
    "sg:address":"495 Av Brochu",
    "sg:city":"Sept-Iles",
    "sg:classifiers":[
        {
            "category":"Restaurant",
            "type":"Food & Drink"
        }
    ],
    "sg:phone":"+1 418 962 9311",
    "sg:postcode":"G4R 2X2",
    "sg:province":"QC",
    "wof:name":"Cafe Du Port",
    "wof:placetype":"venue"
},
  "geometry": {"coordinates":[-66.386742,50.207321],"type":"Point"}
}