{
  "type": "Feature",
  "properties": {
    "iso:country":"CA",
    "sg:address":"22 2E Ave",
    "sg:city":"Chapais",
    "sg:classifiers":[
        {
            "category":"Organizations",
            "subcategory":"Religious Organization",
            "type":"Services"
        }
    ],
    "sg:phone":"+1 418 745 2211",
    "sg:postcode":"G0W 1H0",
    "sg:province":"QC",
    "sg:tags":[
        "church"
    ],
    "wof:name":"Presbyteres DE Chapais",
    "wof:placetype":"venue"
},
  "geometry": {"coordinates":[-74.855506897,49.7842216492],"type":"Point"}
}