{
  "type": "Feature",
  "properties": {
    "addr:full":"St Catharines ON L2N 7G4",
    "addr:postcode":"l2n 7g4",
    "iso:country":"CA",
    "sg:city":"St Catharines",
    "sg:classifiers":[
        {
            "category":"Food & Beverages",
            "subcategory":"Bakery",
            "type":"Retail Goods"
        }
    ],
    "sg:phone":"+1 905 935 1366",
    "sg:postcode":"L2N 7G4",
    "sg:province":"ON",
    "sg:tags":[
        "doughnut"
    ],
    "wof:name":"Tim Hortons",
    "wof:placetype":"venue"
},
  "geometry": {"coordinates":[-79.25179290769999,43.1827011108],"type":"Point"}
}