{
  "type": "Feature",
  "properties": {
    "addr:full":"135 Dieppe Rd St Catharines ON L2M 6R7",
    "addr:housenumber":"135",
    "addr:postcode":"l2m 6r7",
    "addr:street":"Dieppe Rd",
    "iso:country":"CA",
    "sg:address":"135 Dieppe Rd",
    "sg:city":"St Catharines",
    "sg:classifiers":[
        {
            "category":"Autos & Motor Vehicles",
            "subcategory":"Automobile Sales",
            "type":"Retail Goods"
        }
    ],
    "sg:phone":"+1 905 641 3421",
    "sg:postcode":"L2M 6R7",
    "sg:province":"ON",
    "sg:tags":[
        "car",
        "dealer"
    ],
    "wof:name":"Skyway Fine Cars",
    "wof:placetype":"venue"
},
  "geometry": {"coordinates":[-79.216583,43.170174],"type":"Point"}
}