{
  "type": "Feature",
  "properties": {
    "addr:full":"414 Pleasant Park Rd Ottawa ON K1H 5N1",
    "addr:housenumber":"414",
    "addr:postcode":"k1h 5n1",
    "addr:street":"Pleasant Park Rd",
    "iso:country":"CA",
    "sg:address":"414 Pleasant Park Rd",
    "sg:city":"Ottawa",
    "sg:classifiers":[
        {
            "category":"Organizations",
            "subcategory":"Religious Organization",
            "type":"Services"
        }
    ],
    "sg:phone":"+1 613 733 4886",
    "sg:postcode":"K1H 5N1",
    "sg:province":"ON",
    "sg:tags":[
        "church"
    ],
    "wof:name":"Pleasant Park Baptist Church",
    "wof:placetype":"venue"
},
  "geometry": {"coordinates":[-75.65409099999999,45.393513],"type":"Point"}
}