{
  "type": "Feature",
  "properties": {
    "addr:full":"794 Fort St Victoria BC V8W 1H2",
    "addr:housenumber":"794",
    "addr:postcode":"v8w 1h2",
    "addr:street":"Fort St",
    "iso:country":"CA",
    "sg:address":"794 Fort St",
    "sg:city":"Victoria",
    "sg:classifiers":[
        {
            "category":"Professional",
            "subcategory":"Detective & Security Services",
            "type":"Services"
        }
    ],
    "sg:phone":"+1 250 652 0541",
    "sg:postcode":"V8W 1H2",
    "sg:province":"BC",
    "sg:tags":[
        "adjuster",
        "insurance",
        "investigator"
    ],
    "wof:name":"Sterling Pacific Investigation",
    "wof:placetype":"venue"
},
  "geometry": {"coordinates":[-123.36286163299999,48.4243965149],"type":"Point"}
}