{
  "type": "Feature",
  "properties": {
    "addr:full":"2540 Rue Pine Hill Rawdon QC J0K 1S0",
    "addr:housenumber":"2540",
    "addr:postcode":"j0k 1s0",
    "addr:street":"Rue Pine Hill",
    "iso:country":"CA",
    "sg:address":"2540 Rue Pine Hill",
    "sg:city":"Rawdon",
    "sg:classifiers":[
        {
            "category":"Manufacturing",
            "subcategory":"Glass & Minerals",
            "type":"Manufacturing & Wholesale Goods"
        }
    ],
    "sg:phone":"+1 450 834 3177",
    "sg:postcode":"J0K 1S0",
    "sg:province":"QC",
    "wof:name":"Lukian Studios",
    "wof:placetype":"venue"
},
  "geometry": {"coordinates":[-73.71669799999999,46.030155],"type":"Point"}
}