{
  "type": "Feature",
  "properties": {
    "iso:country":"CA",
    "sg:address":"88 Av Ballantyne N",
    "sg:city":"Montreal-Ouest",
    "sg:classifiers":[
        {
            "category":"Organizations",
            "subcategory":"Religious Organization",
            "type":"Services"
        }
    ],
    "sg:phone":"+1 514 482 3210",
    "sg:postcode":"H4X 2B8",
    "sg:province":"QC",
    "sg:tags":[
        "church"
    ],
    "wof:name":"Montreal West United Church",
    "wof:placetype":"venue"
},
  "geometry": {"coordinates":[-73.64623260499999,45.453792572],"type":"Point"}
}