{
  "type": "Feature",
  "properties": {
    "addr:full":"1255 Aut Duplessis Sainte-Foy QC G2G 2B4",
    "addr:postcode":"1255;g2g 2b4",
    "addr:street":"Duplessis",
    "iso:country":"CA",
    "sg:address":"1255 Aut Duplessis",
    "sg:city":"Sainte-Foy",
    "sg:classifiers":[
        {
            "category":"Travel",
            "subcategory":"Hotels & Motels",
            "type":"Entertainment"
        }
    ],
    "sg:phone":"+1 418 872 5900",
    "sg:postcode":"G2G 2B4",
    "sg:province":"QC",
    "wof:name":"Comfort Inn",
    "wof:placetype":"venue"
},
  "geometry": {"coordinates":[-71.2952957153,46.7636909485],"type":"Point"}
}