{
  "type": "Feature",
  "properties": {
    "addr:full":"602 15A Ave Nisku AB T9E 7R9",
    "addr:housenumber":"602",
    "addr:postcode":"t9e 7r9",
    "addr:street":"15A Ave",
    "iso:country":"CA",
    "sg:address":"602 15A Ave",
    "sg:city":"Nisku",
    "sg:classifiers":[
        {
            "category":"Professional",
            "subcategory":"Testing Lab",
            "type":"Services"
        }
    ],
    "sg:phone":"+1 780 955 8601",
    "sg:postcode":"T9E 7R9",
    "sg:province":"AB",
    "sg:tags":[
        "x"
    ],
    "wof:name":"Canada Inspection Assoc",
    "wof:placetype":"venue"
},
  "geometry": {"coordinates":[-113.523712,53.322792],"type":"Point"}
}