{
  "type": "Feature",
  "properties": {
    "iso:country":"CA",
    "sg:city":"Ottawa",
    "sg:phone":"+1 613 745 2800",
    "sg:postcode":"K1B 4L2",
    "sg:province":"ON",
    "sg:tags":[
        "equipment",
        "supply"
    ],
    "wof:name":"Empire Crockery Canada Inc",
    "wof:placetype":"venue"
},
  "geometry": {"coordinates":[-75.623245,45.411106],"type":"Point"}
}