{
  "type": "Feature",
  "properties": {
    "addr:full":"Sherwood Park AB T8B 1K7",
    "addr:postcode":"t8b 1k7",
    "iso:country":"CA",
    "sg:city":"Sherwood Park",
    "sg:classifiers":[
        {
            "category":"Retail",
            "subcategory":"Animal Services",
            "type":"Services"
        }
    ],
    "sg:phone":"+1 780 449 5570",
    "sg:postcode":"T8B 1K7",
    "sg:province":"AB",
    "sg:tags":[
        "horse",
        "training"
    ],
    "wof:name":"Clover Leaf Stables Equestrian",
    "wof:placetype":"venue"
},
  "geometry": {"coordinates":[-113.270775,53.585606],"type":"Point"}
}