{
  "type": "Feature",
  "properties": {
    "iso:country":"CA",
    "sg:address":"33730 Enterprise Ave",
    "sg:city":"Abbotsford",
    "sg:classifiers":[
        {
            "category":"Home & Garden",
            "subcategory":"Building Materials",
            "type":"Retail Goods"
        }
    ],
    "sg:phone":"+1 604 853 0420",
    "sg:postcode":"V2S 7T9",
    "sg:province":"BC",
    "sg:tags":[
        "wood",
        "preserving"
    ],
    "wof:name":"North American Wood Treating",
    "wof:placetype":"venue"
},
  "geometry": {"coordinates":[-122.291679382,49.0604438782],"type":"Point"}
}