{
  "type": "Feature",
  "properties": {
    "iso:country":"CA",
    "sg:address":"6827 Campbell Settler Crt",
    "sg:city":"Mississauga",
    "sg:classifiers":[
        {
            "category":"Health Services",
            "subcategory":"Doctor",
            "type":"Services"
        }
    ],
    "sg:phone":"+1 905 671 9787",
    "sg:postcode":"L5W 1B3",
    "sg:province":"ON",
    "sg:tags":[
        "physician",
        "surgeon"
    ],
    "wof:name":"Singal, Sewa MD",
    "wof:placetype":"venue"
},
  "geometry": {"coordinates":[-79.72211456300001,43.6248054504],"type":"Point"}
}