{
  "type": "Feature",
  "properties": {
    "addr:full":"5582 Yonge St North York ON M2N 5S2",
    "addr:housenumber":"5582",
    "addr:postcode":"m2n 5s2",
    "addr:street":"Yonge St",
    "iso:country":"CA",
    "sg:address":"5582 Yonge St",
    "sg:city":"North York",
    "sg:classifiers":[
        {
            "category":"Professional",
            "subcategory":"Computer Services",
            "type":"Services"
        }
    ],
    "sg:phone":"+1 416 229 6923",
    "sg:postcode":"M2N 5S2",
    "sg:province":"ON",
    "sg:tags":[
        "internet"
    ],
    "wof:name":"Y K Internet Zone",
    "wof:placetype":"venue"
},
  "geometry": {"coordinates":[-79.4155426025,43.7789764404],"type":"Point"}
}