{
  "type": "Feature",
  "properties": {
    "iso:country":"CA",
    "sg:city":"Windsor",
    "sg:classifiers":[
        {
            "category":"Social Services",
            "type":"Services"
        }
    ],
    "sg:phone":"+1 519 972 7771",
    "sg:postcode":"N8X 4Y8",
    "sg:province":"ON",
    "sg:tags":[
        "senior",
        "citizen"
    ],
    "wof:name":"Retired Seniors Volunteer",
    "wof:placetype":"venue"
},
  "geometry": {"coordinates":[-83.0050582886,42.2734565735],"type":"Point"}
}