{
  "type": "Feature",
  "properties": {
    "addr:full":"Bowen Island BC V0N 1G0",
    "addr:postcode":"v0n 1g0",
    "iso:country":"CA",
    "sg:city":"Bowen Island",
    "sg:classifiers":[
        {
            "category":"Home & Garden",
            "subcategory":"Garden Supply",
            "type":"Retail Goods"
        }
    ],
    "sg:phone":"+1 604 947 2016",
    "sg:postcode":"V0N 1G0",
    "sg:province":"BC",
    "sg:tags":[
        "nurseryman"
    ],
    "wof:name":"Bowen Island Nursery",
    "wof:placetype":"venue"
},
  "geometry": {"coordinates":[-123.34191131599999,49.3798675537],"type":"Point"}
}