{
  "type": "Feature",
  "properties": {
    "addr:full":"1700 5th Conc Ruthven ON N0P 2G0",
    "addr:housenumber":"1700",
    "addr:postcode":"n0p 2g0",
    "addr:street":"5Th Conc",
    "iso:country":"CA",
    "sg:address":"1700 5th Conc",
    "sg:city":"Ruthven",
    "sg:classifiers":[
        {
            "category":"Wholesale",
            "subcategory":"Fruits & Vegetables",
            "type":"Manufacturing & Wholesale Goods"
        }
    ],
    "sg:phone":"+1 519 326 0082",
    "sg:postcode":"N0P 2G0",
    "sg:province":"ON",
    "sg:tags":[
        "farm",
        "shipper"
    ],
    "wof:name":"E & B Medel Orchards Ltd",
    "wof:placetype":"venue"
},
  "geometry": {"coordinates":[-82.67202,42.051914],"type":"Point"}
}