{
  "type": "Feature",
  "properties": {
    "addr:full":"Altario AB T0C 0E0",
    "addr:postcode":"t0c 0e0",
    "iso:country":"CA",
    "sg:city":"Altario",
    "sg:classifiers":[
        {
            "category":"Mining & Drilling",
            "type":"Manufacturing & Wholesale Goods"
        }
    ],
    "sg:phone":"+1 403 552 2115",
    "sg:postcode":"T0C 0E0",
    "sg:province":"AB",
    "sg:tags":[
        "company",
        "oil"
    ],
    "wof:name":"Penn West Petroleum Ltd",
    "wof:placetype":"venue"
},
  "geometry": {"coordinates":[-110.16250599999999,51.918774],"type":"Point"}
}