{
  "type": "Feature",
  "properties": {
    "addr:full":"860 Rue Saint-Germain Saint-Laurent QC H4L 3R8",
    "addr:housenumber":"860",
    "addr:postcode":"h4l 3r8",
    "addr:street":"Rue Saint-Germain",
    "iso:country":"CA",
    "sg:address":"860 Rue Saint-Germain",
    "sg:city":"Saint-Laurent",
    "sg:classifiers":[
        {
            "category":"Insurance",
            "subcategory":"Insurance Agent",
            "type":"Services"
        }
    ],
    "sg:phone":"+1 514 748 6374",
    "sg:postcode":"H4L 3R8",
    "sg:province":"QC",
    "wof:name":"Jasmin Hercules & Fils Ltee",
    "wof:placetype":"venue"
},
  "geometry": {"coordinates":[-73.678513,45.513138],"type":"Point"}
}