{
  "type": "Feature",
  "properties": {
    "addr:full":"2330 Benvoulin Rd Kelowna BC V1W 2C6",
    "addr:housenumber":"2330",
    "addr:postcode":"v1w 2c6",
    "addr:street":"Benvoulin Rd",
    "iso:country":"CA",
    "sg:address":"2330 Benvoulin Rd",
    "sg:city":"Kelowna",
    "sg:classifiers":[
        {
            "category":"Manufacturing",
            "subcategory":"Jewelry",
            "type":"Manufacturing & Wholesale Goods"
        }
    ],
    "sg:phone":"+1 250 860 3831",
    "sg:postcode":"V1W 2C6",
    "sg:province":"BC",
    "sg:tags":[
        "lapidary"
    ],
    "wof:name":"Tony's Rocks & Minerals",
    "wof:placetype":"venue"
},
  "geometry": {"coordinates":[-119.444786072,49.8721084595],"type":"Point"}
}