{
  "type": "Feature",
  "properties": {
    "addr:full":"Chilliwack BC V2R 4H3",
    "addr:postcode":"v2r 4h3",
    "iso:country":"CA",
    "sg:city":"Chilliwack",
    "sg:classifiers":[
        {
            "category":"Utilities",
            "subcategory":"Mobile Phone",
            "type":"Services"
        }
    ],
    "sg:phone":"+1 604 792 0323",
    "sg:postcode":"V2R 4H3",
    "sg:province":"BC",
    "sg:tags":[
        "telephone",
        "cellular"
    ],
    "wof:name":"Cel-Pak",
    "wof:placetype":"venue"
},
  "geometry": {"coordinates":[-121.95155334499999,49.1713676453],"type":"Point"}
}