{
  "type": "Feature",
  "properties": {
    "addr:full":"5670 Boul Des Forges Trois-Rivieres QC G8Y 1X7",
    "addr:housenumber":"5670",
    "addr:postcode":"g8y 1x7",
    "addr:street":"Boul Des Forges Trois-Rivieres",
    "iso:country":"CA",
    "sg:address":"5670 Boul Des Forges",
    "sg:city":"Trois-Rivieres",
    "sg:classifiers":[
        {
            "category":"Real Estate",
            "subcategory":"Surveying",
            "type":"Services"
        }
    ],
    "sg:phone":"+1 819 379 8081",
    "sg:postcode":"G8Y 1X7",
    "sg:province":"QC",
    "sg:tags":[
        "surveyor"
    ],
    "wof:name":"Plante, Michel",
    "wof:placetype":"venue"
},
  "geometry": {"coordinates":[-72.596817,46.364643],"type":"Point"}
}