{
  "type": "Feature",
  "properties": {
    "addr:full":"25 Lawson St Elmvale ON L0L 1P0",
    "addr:housenumber":"25",
    "addr:postcode":"l0l 1p0",
    "addr:street":"Lawson St",
    "iso:country":"CA",
    "sg:address":"25 Lawson St",
    "sg:city":"Elmvale",
    "sg:classifiers":[
        {
            "category":"Education",
            "subcategory":"School",
            "type":"Public Place"
        }
    ],
    "sg:phone":"+1 705 322 2201",
    "sg:postcode":"L0L 1P0",
    "sg:province":"ON",
    "wof:name":"Elmvale District High School",
    "wof:placetype":"venue"
},
  "geometry": {"coordinates":[-79.865257,44.579876],"type":"Point"}
}