{
  "type": "Feature",
  "properties": {
    "addr:full":"581 Sagamok Rd Massey ON P0P 1P0",
    "addr:housenumber":"581",
    "addr:postcode":"p0p 1p0",
    "addr:street":"Sagamok Rd",
    "iso:country":"CA",
    "sg:address":"581 Sagamok Rd",
    "sg:city":"Massey",
    "sg:classifiers":[
        {
            "category":"Autos & Motor Vehicles",
            "subcategory":"Fuel & Gas Station",
            "type":"Retail Goods"
        }
    ],
    "sg:phone":"+1 705 865 3066",
    "sg:postcode":"P0P 1P0",
    "sg:province":"ON",
    "sg:tags":[
        "oil"
    ],
    "wof:name":"Toulouse Grocery & Gas Bar",
    "wof:placetype":"venue"
},
  "geometry": {"coordinates":[-82.076218,46.212616],"type":"Point"}
}