{
  "type": "Feature",
  "properties": {
    "iso:country":"CA",
    "sg:address":"3195 Rue Lemieux",
    "sg:city":"Quebec",
    "sg:classifiers":[
        {
            "category":"Personal",
            "type":"Services"
        }
    ],
    "sg:phone":"+1 418 687 0313",
    "sg:postcode":"G1P 4N6",
    "sg:province":"QC",
    "sg:tags":[
        "therapist",
        "massage"
    ],
    "wof:name":"Beaudry & Bernier",
    "wof:placetype":"venue"
},
  "geometry": {"coordinates":[-71.3128890991,46.8141708374],"type":"Point"}
}