{
  "type": "Feature",
  "properties": {
    "addr:full":"74 Vienna Rd Tillsonburg ON N4G 3C8",
    "addr:housenumber":"74",
    "addr:postcode":"n4g 3c8",
    "addr:street":"Vienna Rd",
    "iso:country":"CA",
    "sg:address":"74 Vienna Rd",
    "sg:city":"Tillsonburg",
    "sg:classifiers":[
        {
            "category":"Autos & Motor Vehicles",
            "subcategory":"Auto Supplies",
            "type":"Retail Goods"
        }
    ],
    "sg:phone":"+1 519 688 7388",
    "sg:postcode":"N4G 3C8",
    "sg:province":"ON",
    "sg:tags":[
        "automobile",
        "parts"
    ],
    "wof:name":"Rad Shop",
    "wof:placetype":"venue"
},
  "geometry": {"coordinates":[-80.720833,42.85194],"type":"Point"}
}