{
  "type": "Feature",
  "properties": {
    "addr:full":"215 Drive in Rd Sault Ste Marie ON P6B 5X5",
    "addr:housenumber":"215",
    "addr:postcode":"p6b 5x5",
    "addr:street":"Drive In Rd",
    "iso:country":"CA",
    "sg:address":"215 Drive in Rd",
    "sg:city":"Sault Ste Marie",
    "sg:classifiers":[
        {
            "category":"Wholesale",
            "subcategory":"Metals & Minerals",
            "type":"Manufacturing & Wholesale Goods"
        }
    ],
    "sg:phone":"+1 705 256 7957",
    "sg:postcode":"P6B 5X5",
    "sg:province":"ON",
    "sg:tags":[
        "steel",
        "warehouse"
    ],
    "wof:name":"Traders Steel Warehouse",
    "wof:placetype":"venue"
},
  "geometry": {"coordinates":[-84.32283,46.547596],"type":"Point"}
}