{
  "type": "Feature",
  "properties": {
    "iso:country":"CA",
    "sg:address":"685 Rue Cathcart",
    "sg:city":"Montreal",
    "sg:classifiers":[
        {
            "category":"Government",
            "subcategory":"Office",
            "type":"Public Place"
        }
    ],
    "sg:phone":"+1 514 283 6086",
    "sg:postcode":"H3B 1M7",
    "sg:province":"QC",
    "wof:name":"Canada Verificateur General",
    "wof:placetype":"venue"
},
  "geometry": {"coordinates":[-73.569839,45.502087],"type":"Point"}
}