{
  "type": "Feature",
  "properties": {
    "addr:full":"North York ON M2N 6H7",
    "addr:postcode":"m2n 6h7",
    "iso:country":"CA",
    "sg:city":"North York",
    "sg:classifiers":[
        {
            "category":"Professional",
            "subcategory":"Business Services",
            "type":"Services"
        }
    ],
    "sg:phone":"+1 416 227 0722",
    "sg:postcode":"M2N 6H7",
    "sg:province":"ON",
    "sg:tags":[
        "paralegal"
    ],
    "wof:name":"Action Accident Benefits",
    "wof:placetype":"venue"
},
  "geometry": {"coordinates":[-79.388329,43.766697],"type":"Point"}
}