{
  "type": "Feature",
  "properties": {
    "addr:full":"24115 St Clair St Chatham ON N7M 5J7",
    "addr:housenumber":"24115",
    "addr:postcode":"n7m 5j7",
    "addr:street":"St Clair St",
    "iso:country":"CA",
    "sg:address":"24115 St Clair St",
    "sg:city":"Chatham",
    "sg:classifiers":[
        {
            "category":"Home & Garden",
            "subcategory":"Furniture",
            "type":"Retail Goods"
        }
    ],
    "sg:phone":"+1 519 351 4616",
    "sg:postcode":"N7M 5J7",
    "sg:province":"ON",
    "wof:name":"Leon's Furniture & Appliances",
    "wof:placetype":"venue"
},
  "geometry": {"coordinates":[-82.22291564939999,42.4336395264],"type":"Point"}
}