{
  "type": "Feature",
  "properties": {
    "addr:full":"Langley BC V3A 3Y7",
    "addr:postcode":"v3a 3y7",
    "iso:country":"CA",
    "sg:city":"Langley",
    "sg:classifiers":[
        {
            "category":"Insurance",
            "subcategory":"Hazard Insurance",
            "type":"Services"
        }
    ],
    "sg:phone":"+1 604 533 5144",
    "sg:postcode":"V3A 3Y7",
    "sg:province":"BC",
    "sg:tags":[
        "employee",
        "consultant",
        "compensation",
        "benefit",
        "plan"
    ],
    "wof:name":"R Spencer Mohart Insurance",
    "wof:placetype":"venue"
},
  "geometry": {"coordinates":[-122.659431,49.104248],"type":"Point"}
}