{
  "type": "Feature",
  "properties": {
    "iso:country":"CA",
    "sg:address":"103 Place Des Melezes",
    "sg:city":"Sainte-Helene-DE-Breakeyville",
    "sg:classifiers":[
        {
            "category":"Professional",
            "subcategory":"Detective & Security Services",
            "type":"Services"
        }
    ],
    "sg:phone":"+1 418 990 2678",
    "sg:postcode":"G0S 1E1",
    "sg:province":"QC",
    "sg:tags":[
        "investigator"
    ],
    "wof:name":"Bureau D'Enquetes Provincial",
    "wof:placetype":"venue"
},
  "geometry": {"coordinates":[-71.23480987550001,46.6943016052],"type":"Point"}
}