{
  "type": "Feature",
  "properties": {
    "addr:full":"Sainte-Foy QC G1W 2K7",
    "addr:postcode":"g1w 2k7",
    "iso:country":"CA",
    "sg:city":"Sainte-Foy",
    "sg:classifiers":[
        {
            "category":"Real Estate",
            "subcategory":"Real Estate Agent",
            "type":"Services"
        }
    ],
    "sg:phone":"+1 418 653 5353",
    "sg:postcode":"G1W 2K7",
    "sg:province":"QC",
    "wof:name":"Fortin Delage Inc",
    "wof:placetype":"venue"
},
  "geometry": {"coordinates":[-71.3090133667,46.7678565979],"type":"Point"}
}