{
  "type": "Feature",
  "properties": {
    "iso:country":"CA",
    "sg:city":"Richmond",
    "sg:classifiers":[
        {
            "category":"Retail",
            "subcategory":"Laundry & Dry Cleaning",
            "type":"Services"
        }
    ],
    "sg:phone":"+1 604 274 2711",
    "sg:postcode":"V7C 5J8",
    "sg:province":"BC",
    "sg:tags":[
        "cleaners"
    ],
    "wof:name":"Easy Care Cleaners",
    "wof:placetype":"venue"
},
  "geometry": {"coordinates":[-123.158775,49.154732],"type":"Point"}
}