{
  "type": "Feature",
  "properties": {
    "addr:full":"Parson BC V0A 1L0",
    "addr:postcode":"v0a 1l0",
    "addr:street":"Parson Bc",
    "iso:country":"CA",
    "sg:city":"Parson",
    "sg:classifiers":[
        {
            "category":"Manufacturing",
            "subcategory":"Lumber",
            "type":"Manufacturing & Wholesale Goods"
        }
    ],
    "sg:phone":"+1 250 348 2525",
    "sg:postcode":"V0A 1L0",
    "sg:province":"BC",
    "sg:tags":[
        "company",
        "logging"
    ],
    "wof:name":"B & C Logging",
    "wof:placetype":"venue"
},
  "geometry": {"coordinates":[-116.697883606,51.1016044617],"type":"Point"}
}