{
  "type": "Feature",
  "properties": {
    "iso:country":"CA",
    "sg:address":"1309 24 Ave",
    "sg:city":"Coaldale",
    "sg:classifiers":[
        {
            "category":"Health Services",
            "subcategory":"Health Practitioner",
            "type":"Services"
        }
    ],
    "sg:phone":"+1 403 345 6519",
    "sg:postcode":"T1M 1C9",
    "sg:province":"AB",
    "sg:tags":[
        "homeopath"
    ],
    "wof:name":"Gauthier, N",
    "wof:placetype":"venue"
},
  "geometry": {"coordinates":[-112.611999512,49.7210121155],"type":"Point"}
}