{
  "type": "Feature",
  "properties": {
    "addr:full":"Sherbrooke QC J1G 1A9",
    "addr:postcode":"j1g 1a9",
    "iso:country":"CA",
    "sg:city":"Sherbrooke",
    "sg:classifiers":[
        {
            "category":"Personal",
            "type":"Services"
        }
    ],
    "sg:phone":"+1 819 566 5525",
    "sg:postcode":"J1G 1A9",
    "sg:province":"QC",
    "sg:tags":[
        "control",
        "weight"
    ],
    "wof:name":"Clinique Poids Sante",
    "wof:placetype":"venue"
},
  "geometry": {"coordinates":[-71.88325500000001,45.406052],"type":"Point"}
}