{
  "type": "Feature",
  "properties": {
    "addr:full":"1591 Rue Principale E Sainte-Agathe-Des-Monts QC J8C 1M1",
    "addr:housenumber":"1591",
    "addr:postcode":"j8c 1m1",
    "addr:street":"Rue Principale E Sainte-Agathe-Des-Monts",
    "iso:country":"CA",
    "sg:address":"1591 Rue Principale E",
    "sg:city":"Sainte-Agathe-Des-Monts",
    "sg:classifiers":[
        {
            "category":"Travel",
            "subcategory":"Hotels & Motels",
            "type":"Entertainment"
        }
    ],
    "sg:phone":"+1 819 326 1444",
    "sg:postcode":"J8C 1M1",
    "sg:province":"QC",
    "wof:name":"Motel Clair-Mont",
    "wof:placetype":"venue"
},
  "geometry": {"coordinates":[-74.25476837159999,46.0418281555],"type":"Point"}
}