{
  "type": "Feature",
  "properties": {
    "addr:full":"1396 St. Margaret's Bay Rd Lakeside NS B3T 1A8",
    "addr:housenumber":"1396",
    "addr:postcode":"b3t 1a8",
    "addr:street":"St. Margaret'S Bay Rd",
    "iso:country":"CA",
    "sg:address":"1396 St. Margaret's Bay Rd",
    "sg:city":"Lakeside",
    "sg:classifiers":[
        {
            "category":"Building & Trades",
            "subcategory":"Plumbing",
            "type":"Services"
        }
    ],
    "sg:phone":"+1 902 876 2809",
    "sg:postcode":"B3T 1A8",
    "sg:province":"NS",
    "sg:tags":[
        "conditioning",
        "air",
        "system",
        "contractor"
    ],
    "wof:name":"Crescent Refrigeration",
    "wof:placetype":"venue"
},
  "geometry": {"coordinates":[-63.723133,44.649693],"type":"Point"}
}