{
  "type": "Feature",
  "properties": {
    "addr:full":"529 Boul Du Seminaire N Saint-Jean-Sur-Richelieu QC J3B 5L8",
    "addr:housenumber":"529",
    "addr:postcode":"j3b 5l8",
    "addr:street":"Boul Du Seminaire N",
    "iso:country":"CA",
    "sg:address":"529 Boul Du Seminaire N",
    "sg:city":"Saint-Jean-Sur-Richelieu",
    "sg:classifiers":[
        {
            "category":"Shopping",
            "subcategory":"Computers & Home Electronics",
            "type":"Retail Goods"
        }
    ],
    "sg:phone":"+1 450 348 1675",
    "sg:postcode":"J3B 5L8",
    "sg:province":"QC",
    "sg:tags":[
        "television",
        "radio"
    ],
    "wof:name":"Larose & Larose Image & Son",
    "wof:placetype":"venue"
},
  "geometry": {"coordinates":[-73.26406860349999,45.3168869019],"type":"Point"}
}