{
  "type": "Feature",
  "properties": {
    "addr:full":"289 Huron Rd Goderich ON N7A 3A1",
    "addr:housenumber":"289",
    "addr:postcode":"n7a 3a1",
    "addr:street":"Huron Rd",
    "iso:country":"CA",
    "sg:address":"289 Huron Rd",
    "sg:city":"Goderich",
    "sg:classifiers":[
        {
            "category":"Restaurant",
            "type":"Food & Drink"
        }
    ],
    "sg:phone":"+1 519 524 4849",
    "sg:postcode":"N7A 3A1",
    "sg:province":"ON",
    "wof:name":"Bluewater Restaurant",
    "wof:placetype":"venue"
},
  "geometry": {"coordinates":[-81.6974945068,43.7358283997],"type":"Point"}
}