{
  "type": "Feature",
  "properties": {
    "iso:country":"CA",
    "sg:address":"2900 44th Ave E",
    "sg:city":"Vancouver",
    "sg:classifiers":[
        {
            "category":"Education",
            "subcategory":"School",
            "type":"Public Place"
        }
    ],
    "sg:phone":"+1 604 713 4771",
    "sg:postcode":"V5R 3A8",
    "sg:province":"BC",
    "wof:name":"George M Weir Elementary Schl",
    "wof:placetype":"venue"
},
  "geometry": {"coordinates":[-123.045684815,49.2301025391],"type":"Point"}
}