{
  "type": "Feature",
  "properties": {
    "iso:country":"CA",
    "sg:address":"5902 104 St NW",
    "sg:city":"Edmonton",
    "sg:classifiers":[
        {
            "category":"Personal",
            "subcategory":"Beauty Salon",
            "type":"Services"
        }
    ],
    "sg:phone":"+1 780 438 3433",
    "sg:postcode":"T6H 2K3",
    "sg:province":"AB",
    "wof:name":"Karma",
    "wof:placetype":"venue"
},
  "geometry": {"coordinates":[-113.49783325200001,53.4961967468],"type":"Point"}
}