{
  "type": "Feature",
  "properties": {
    "addr:full":"280 Rue Sainte-Catherine O Montreal QC H2X 2A1",
    "addr:housenumber":"280",
    "addr:postcode":"h2x 2a1",
    "addr:street":"Rue Sainte-Catherine O",
    "iso:country":"CA",
    "sg:address":"280 Rue Sainte-Catherine O",
    "sg:city":"Montreal",
    "sg:classifiers":[
        {
            "category":"Shopping",
            "subcategory":"Shoes",
            "type":"Retail Goods"
        }
    ],
    "sg:phone":"+1 514 866 3111",
    "sg:postcode":"H2X 2A1",
    "sg:province":"QC",
    "wof:name":"Chaussures Stelly",
    "wof:placetype":"venue"
},
  "geometry": {"coordinates":[-73.5612945557,45.5124702454],"type":"Point"}
}