{
  "type": "Feature",
  "properties": {
    "addr:full":"255 Rue Saint-Charles E Longueuil QC J4H 1B3",
    "addr:housenumber":"255",
    "addr:postcode":"j4h 1b3",
    "addr:street":"Rue Saint-Charles E",
    "iso:country":"CA",
    "sg:address":"255 Rue Saint-Charles E",
    "sg:city":"Longueuil",
    "sg:classifiers":[
        {
            "category":"Organizations",
            "subcategory":"Professional Association",
            "type":"Services"
        }
    ],
    "sg:phone":"+1 450 674 0349",
    "sg:postcode":"J4H 1B3",
    "sg:province":"QC",
    "wof:name":"Societe D'Histoire-Longueuil",
    "wof:placetype":"venue"
},
  "geometry": {"coordinates":[-73.5062866211,45.5437545776],"type":"Point"}
}