{
  "type": "Feature",
  "properties": {
    "addr:full":"8098 Donaldson Dr Grand Forks BC V0H 1H2",
    "addr:housenumber":"8098",
    "addr:postcode":"v0h 1h2",
    "addr:street":"Donaldson Dr",
    "iso:country":"CA",
    "sg:address":"8098 Donaldson Dr",
    "sg:city":"Grand Forks",
    "sg:classifiers":[
        {
            "category":"Retail",
            "subcategory":"Car Wash",
            "type":"Services"
        }
    ],
    "sg:phone":"+1 250 442 2537",
    "sg:postcode":"V0H 1H2",
    "sg:province":"BC",
    "sg:tags":[
        "polishing",
        "washing"
    ],
    "wof:name":"Big Ed's Car Cleaning Svc",
    "wof:placetype":"venue"
},
  "geometry": {"coordinates":[-118.47331200000001,49.036304],"type":"Point"}
}