{
  "type": "Feature",
  "properties": {
    "addr:full":"201 Woodside Dr Orillia ON L3V 6T4",
    "addr:housenumber":"201",
    "addr:postcode":"l3v 6t4",
    "addr:street":"Woodside Dr",
    "iso:country":"CA",
    "sg:address":"201 Woodside Dr",
    "sg:city":"Orillia",
    "sg:classifiers":[
        {
            "category":"Restaurant",
            "type":"Food & Drink"
        }
    ],
    "sg:phone":"+1 705 326 7343",
    "sg:postcode":"L3V 6T4",
    "sg:province":"ON",
    "wof:name":"Mc Cabes Restaurant & Bar",
    "wof:placetype":"venue"
},
  "geometry": {"coordinates":[-79.440697,44.60817],"type":"Point"}
}