{
  "type": "Feature",
  "properties": {
    "iso:country":"CA",
    "sg:address":"120 Princess Ave",
    "sg:city":"Vancouver",
    "sg:classifiers":[
        {
            "category":"Retail",
            "subcategory":"Repair Shop",
            "type":"Services"
        }
    ],
    "sg:phone":"+1 604 253 2696",
    "sg:postcode":"V6A 3C3",
    "sg:province":"BC",
    "sg:tags":[
        "marine",
        "electric"
    ],
    "wof:name":"Van-Mar Electric Ltd",
    "wof:placetype":"venue"
},
  "geometry": {"coordinates":[-123.09108734100001,49.2837104797],"type":"Point"}
}