{
  "type": "Feature",
  "properties": {
    "iso:country":"CA",
    "sg:address":"178 John St S",
    "sg:city":"Hamilton",
    "sg:classifiers":[
        {
            "category":"Retail",
            "subcategory":"Auto Repair",
            "type":"Services"
        }
    ],
    "sg:phone":"+1 905 529 2833",
    "sg:postcode":"L8N 2C6",
    "sg:province":"ON",
    "sg:tags":[
        "repairing",
        "automobile"
    ],
    "wof:name":"Downtown Auto Specialist",
    "wof:placetype":"venue"
},
  "geometry": {"coordinates":[-79.8685760498,43.2513694763],"type":"Point"}
}