{
  "type": "Feature",
  "properties": {
    "iso:country":"CA",
    "sg:address":"3535 Laird Rd",
    "sg:city":"Mississauga",
    "sg:classifiers":[
        {
            "category":"Manufacturing",
            "subcategory":"Rubber & Plastics",
            "type":"Manufacturing & Wholesale Goods"
        }
    ],
    "sg:phone":"+1 905 569 3538",
    "sg:postcode":"L5L 5Y7",
    "sg:province":"ON",
    "wof:name":"Millennium Flexible Packaging",
    "wof:placetype":"venue"
},
  "geometry": {"coordinates":[-79.6992721558,43.5175170898],"type":"Point"}
}