{
  "type": "Feature",
  "properties": {
    "addr:full":"1490 Marine Dr West Vancouver BC V7T 1B7",
    "addr:housenumber":"1490",
    "addr:postcode":"v7t 1b7",
    "addr:street":"Marine Dr",
    "iso:country":"CA",
    "sg:address":"1490 Marine Dr",
    "sg:city":"West Vancouver",
    "sg:classifiers":[
        {
            "category":"Autos & Motor Vehicles",
            "subcategory":"Fuel & Gas Station",
            "type":"Retail Goods"
        }
    ],
    "sg:phone":"+1 604 926 3516",
    "sg:postcode":"V7T 1B7",
    "sg:province":"BC",
    "sg:tags":[
        "oil"
    ],
    "wof:name":"Ambleside Petro-Canada",
    "wof:placetype":"venue"
},
  "geometry": {"coordinates":[-123.156403,49.328114],"type":"Point"}
}