{
  "type": "Feature",
  "properties": {
    "addr:full":"235 Scott St Fort Frances ON P9A 1G8",
    "addr:housenumber":"235",
    "addr:postcode":"p9a 1g8",
    "addr:street":"Scott St",
    "iso:country":"CA",
    "sg:address":"235 Scott St",
    "sg:city":"Fort Frances",
    "sg:classifiers":[
        {
            "category":"Travel",
            "subcategory":"Hotels & Motels",
            "type":"Entertainment"
        }
    ],
    "sg:phone":"+1 807 274 5355",
    "sg:postcode":"P9A 1G8",
    "sg:province":"ON",
    "wof:name":"Rainy Lake Hotel",
    "wof:placetype":"venue"
},
  "geometry": {"coordinates":[-93.397491,48.609848],"type":"Point"}
}