{
  "type": "Feature",
  "properties": {
    "addr:full":"Lakeside NS B3T 1L7",
    "addr:postcode":"b3t 1l7",
    "iso:country":"CA",
    "sg:city":"Lakeside",
    "sg:classifiers":[
        {
            "category":"Organizations",
            "subcategory":"Professional Association",
            "type":"Services"
        }
    ],
    "sg:phone":"+1 902 876 0526",
    "sg:postcode":"B3T 1L7",
    "sg:province":"NS",
    "wof:name":"Insurance Brokers Assn of NS",
    "wof:placetype":"venue"
},
  "geometry": {"coordinates":[-63.68922,44.638287],"type":"Point"}
}