{
  "type": "Feature",
  "properties": {
    "addr:full":"721 Broadway Ave Saskatoon SK S7N 1B3",
    "addr:housenumber":"721",
    "addr:postcode":"s7n 1b3",
    "addr:street":"Broadway Ave",
    "iso:country":"CA",
    "sg:address":"721 Broadway Ave",
    "sg:city":"Saskatoon",
    "sg:classifiers":[
        {
            "category":"Restaurant",
            "type":"Food & Drink"
        }
    ],
    "sg:phone":"+1 306 665 7991",
    "sg:postcode":"S7N 1B3",
    "sg:province":"SK",
    "wof:name":"Calories Bakery & Restaurant",
    "wof:placetype":"venue"
},
  "geometry": {"coordinates":[-106.656532,52.118546],"type":"Point"}
}