{
  "type": "Feature",
  "properties": {
    "addr:full":"651 Main St Dartmouth NS B2W 3T6",
    "addr:housenumber":"651",
    "addr:postcode":"b2w 3t6",
    "addr:street":"Main St",
    "iso:country":"CA",
    "sg:address":"651 Main St",
    "sg:city":"Dartmouth",
    "sg:classifiers":[
        {
            "category":"Shopping",
            "subcategory":"Computers & Home Electronics",
            "type":"Retail Goods"
        }
    ],
    "sg:phone":"+1 902 434 3747",
    "sg:postcode":"B2W 3T6",
    "sg:province":"NS",
    "sg:tags":[
        "radio",
        "television",
        "video",
        "equipment"
    ],
    "wof:name":"Hodgins Tv Svc",
    "wof:placetype":"venue"
},
  "geometry": {"coordinates":[-63.496372,44.696064],"type":"Point"}
}