{
  "type": "Feature",
  "properties": {
    "addr:full":"9764 Willow St Chemainus BC V0R 1K0",
    "addr:housenumber":"9764",
    "addr:postcode":"v0r 1k0",
    "addr:street":"Willow St",
    "iso:country":"CA",
    "sg:address":"9764 Willow St",
    "sg:city":"Chemainus",
    "sg:classifiers":[
        {
            "category":"Cinema",
            "subcategory":"Movie Rental",
            "type":"Entertainment"
        }
    ],
    "sg:phone":"+1 250 246 9944",
    "sg:postcode":"V0R 1K0",
    "sg:province":"BC",
    "sg:tags":[
        "leasing",
        "video",
        "disc",
        "tape"
    ],
    "wof:name":"Pioneer's Video & Music",
    "wof:placetype":"venue"
},
  "geometry": {"coordinates":[-123.717453003,48.9222373962],"type":"Point"}
}