{
  "type": "Feature",
  "properties": {
    "addr:full":"530 Robson St Vancouver BC V6B 2B7",
    "addr:housenumber":"530",
    "addr:postcode":"bc v6b 2b7",
    "addr:street":"Robson St",
    "iso:country":"CA",
    "sg:address":"530 Robson St",
    "sg:city":"Vancouver",
    "sg:classifiers":[
        {
            "category":"Food & Beverages",
            "subcategory":"Groceries & Convenience Stores",
            "type":"Retail Goods"
        }
    ],
    "sg:phone":"+1 604 662 8454",
    "sg:postcode":"V6B 2B7",
    "sg:province":"BC",
    "sg:tags":[
        "grocer"
    ],
    "wof:name":"Iman Grocery Store",
    "wof:placetype":"venue"
},
  "geometry": {"coordinates":[-123.118286133,49.2802009583],"type":"Point"}
}