{
  "type": "Feature",
  "properties": {
    "addr:full":"366 Rang Du Domaine Lemieux QC G0X 1S0",
    "addr:housenumber":"366",
    "addr:postcode":"g0x 1s0",
    "addr:street":"Rang Du Domaine",
    "iso:country":"CA",
    "sg:address":"366 Rang Du Domaine",
    "sg:city":"Lemieux",
    "sg:classifiers":[
        {
            "category":"Building & Trades",
            "subcategory":"Construction",
            "type":"Services"
        }
    ],
    "sg:phone":"+1 819 283 2088",
    "sg:postcode":"G0X 1S0",
    "sg:province":"QC",
    "sg:tags":[
        "general",
        "contractor"
    ],
    "wof:name":"Transport Armand Blanchette",
    "wof:placetype":"venue"
},
  "geometry": {"coordinates":[-72.10701,46.327801],"type":"Point"}
}