{
  "type": "Feature",
  "properties": {
    "addr:full":"23 Rue Saint-Edouard Baie-Saint-Paul QC G3Z 1C9",
    "addr:housenumber":"23",
    "addr:postcode":"g3z 1c9",
    "addr:street":"Rue Saint-Edouard",
    "iso:country":"CA",
    "sg:address":"23 Rue Saint-Edouard",
    "sg:city":"Baie-Saint-Paul",
    "sg:classifiers":[
        {
            "category":"Retail",
            "subcategory":"Portrait Studio",
            "type":"Services"
        }
    ],
    "sg:phone":"+1 418 240 2604",
    "sg:postcode":"G3Z 1C9",
    "sg:province":"QC",
    "sg:tags":[
        "photographer"
    ],
    "wof:name":"Centre DE Traitement D'Image",
    "wof:placetype":"venue"
},
  "geometry": {"coordinates":[-70.51123,47.447819],"type":"Point"}
}