{
  "type": "Feature",
  "properties": {
    "addr:full":"18196 Claytonhill Dr Surrey BC V3S 7N5",
    "addr:housenumber":"18196",
    "addr:postcode":"v3s 7n5",
    "addr:street":"Claytonhill Dr",
    "iso:country":"CA",
    "sg:address":"18196 Claytonhill Dr",
    "sg:city":"Surrey",
    "sg:classifiers":[
        {
            "category":"Professional",
            "subcategory":"Accounting & Tax Preparation",
            "type":"Services"
        }
    ],
    "sg:phone":"+1 604 574 2844",
    "sg:postcode":"V3S 7N5",
    "sg:province":"BC",
    "sg:tags":[
        "accountant"
    ],
    "wof:name":"Davey, Jerry",
    "wof:placetype":"venue"
},
  "geometry": {"coordinates":[-122.718048,49.121784],"type":"Point"}
}