{
  "type": "Feature",
  "properties": {
    "addr:full":"9317 Huggard St Fort Mcmurray AB T9H 1C4",
    "addr:housenumber":"9317",
    "addr:postcode":"t9h 1c4",
    "addr:street":"Huggard St",
    "iso:country":"CA",
    "sg:address":"9317 Huggard St",
    "sg:city":"Fort Mcmurray",
    "sg:classifiers":[
        {
            "category":"Organizations",
            "subcategory":"Community Association",
            "type":"Services"
        }
    ],
    "sg:phone":"+1 780 743 2329",
    "sg:postcode":"T9H 1C4",
    "sg:province":"AB",
    "sg:tags":[
        "club"
    ],
    "wof:name":"Royal Canadian Legion",
    "wof:placetype":"venue"
},
  "geometry": {"coordinates":[-111.33879852299999,56.6984939575],"type":"Point"}
}