{
  "type": "Feature",
  "properties": {
    "addr:full":"2985 Ch Royal Beauport QC G1E 1T5",
    "addr:postcode":"2985;qc g1e 1t5",
    "addr:street":"Ch Royal",
    "iso:country":"CA",
    "sg:address":"2985 Ch Royal",
    "sg:city":"Beauport",
    "sg:classifiers":[
        {
            "category":"Restaurant",
            "type":"Food & Drink"
        }
    ],
    "sg:phone":"+1 418 663 6863",
    "sg:postcode":"G1E 1T5",
    "sg:province":"QC",
    "wof:name":"Buffet Royal",
    "wof:placetype":"venue"
},
  "geometry": {"coordinates":[-71.21337127690001,46.8482170105],"type":"Point"}
}