{
  "type": "Feature",
  "properties": {
    "addr:full":"713 Cavell St Creston BC V0B 1G4",
    "addr:housenumber":"713",
    "addr:postcode":"bc v0b 1g4",
    "addr:street":"Cavell St",
    "iso:country":"CA",
    "sg:address":"713 Cavell St",
    "sg:city":"Creston",
    "sg:classifiers":[
        {
            "category":"Organizations",
            "subcategory":"Religious Organization",
            "type":"Services"
        }
    ],
    "sg:phone":"+1 250 428 5214",
    "sg:postcode":"V0B 1G4",
    "sg:province":"BC",
    "sg:tags":[
        "church"
    ],
    "wof:name":"Seventh Day Adventist School",
    "wof:placetype":"venue"
},
  "geometry": {"coordinates":[-116.517433,49.104141],"type":"Point"}
}