{
  "type": "Feature",
  "properties": {
    "iso:country":"CA",
    "sg:address":"205 Rang Saint-Alexis",
    "sg:city":"Nicolet-Sud",
    "sg:classifiers":[
        {
            "category":"Communications",
            "subcategory":"Film & Video Production",
            "type":"Services"
        }
    ],
    "sg:phone":"+1 819 293 5791",
    "sg:postcode":"J3T 1T5",
    "sg:province":"QC",
    "sg:tags":[
        "taping"
    ],
    "wof:name":"Cpro Video Inc",
    "wof:placetype":"venue"
},
  "geometry": {"coordinates":[-72.62078857420001,46.221736908],"type":"Point"}
}