{
  "type": "Feature",
  "properties": {
    "addr:full":"Anjou QC H1K 4E4",
    "addr:postcode":"h1k 4e4",
    "iso:country":"CA",
    "sg:city":"Anjou",
    "sg:classifiers":[
        {
            "category":"Organizations",
            "subcategory":"Professional Association",
            "type":"Services"
        }
    ],
    "sg:phone":"+1 514 355 6190",
    "sg:postcode":"H1K 4E4",
    "sg:province":"QC",
    "wof:name":"Asp Construction",
    "wof:placetype":"venue"
},
  "geometry": {"coordinates":[-73.563545,45.605106],"type":"Point"}
}