{
  "type": "Feature",
  "properties": {
    "addr:full":"1100 Prince St Truro NS B2N 1J1",
    "addr:housenumber":"1100",
    "addr:postcode":"b2n 1j1",
    "addr:street":"Prince St",
    "iso:country":"CA",
    "sg:address":"1100 Prince St",
    "sg:city":"Truro",
    "sg:classifiers":[
        {
            "category":"Organizations",
            "subcategory":"Professional Association",
            "type":"Services"
        }
    ],
    "sg:phone":"+1 902 893 4773",
    "sg:postcode":"B2N 1J1",
    "sg:province":"NS",
    "wof:name":"Truro Lions Club",
    "wof:placetype":"venue"
},
  "geometry": {"coordinates":[-63.2664642334,45.3643989563],"type":"Point"}
}