{
  "type": "Feature",
  "properties": {
    "addr:full":"974 Rte 275 Saint-Benjamin QC G0M 1N0",
    "addr:housenumber":"974",
    "addr:postcode":"g0m 1n0",
    "addr:street":"Rte 275",
    "iso:country":"CA",
    "sg:address":"974 Rte 275",
    "sg:city":"Saint-Benjamin",
    "sg:classifiers":[
        {
            "category":"Retail",
            "subcategory":"Auto Repair",
            "type":"Services"
        }
    ],
    "sg:phone":"+1 418 594 8849",
    "sg:postcode":"G0M 1N0",
    "sg:province":"QC",
    "sg:tags":[
        "repairing",
        "automobile"
    ],
    "wof:name":"Centre DE L'Auto Rdr Inc",
    "wof:placetype":"venue"
},
  "geometry": {"coordinates":[-70.59522247309999,46.2857170105],"type":"Point"}
}