{
  "type": "Feature",
  "properties": {
    "addr:full":"Alma QC G8B 1N2",
    "addr:postcode":"g8b 1n2",
    "iso:country":"CA",
    "sg:city":"Alma",
    "sg:classifiers":[
        {
            "category":"Real Estate",
            "subcategory":"Real Estate Agent",
            "type":"Services"
        }
    ],
    "sg:phone":"+1 418 668 0168",
    "sg:postcode":"G8B 1N2",
    "sg:province":"QC",
    "sg:tags":[
        "appraiser"
    ],
    "wof:name":"Immobiliere Societe D'Evaluat",
    "wof:placetype":"venue"
},
  "geometry": {"coordinates":[-71.64913900000001,48.547989],"type":"Point"}
}