{
  "type": "Feature",
  "properties": {
    "iso:country":"CA",
    "sg:city":"Thunder Bay",
    "sg:classifiers":[
        {
            "category":"Banks & Credit Unions",
            "subcategory":"Bank",
            "type":"Services"
        }
    ],
    "sg:phone":"+1 807 623 8723",
    "sg:postcode":"P7C 4K3",
    "sg:province":"ON",
    "sg:tags":[
        "loan",
        "real estate"
    ],
    "wof:name":"Twinport Finance Ltd",
    "wof:placetype":"venue"
},
  "geometry": {"coordinates":[-89.260925293,48.3843765259],"type":"Point"}
}