{
  "type": "Feature",
  "properties": {
    "addr:full":"20 Edgewater Crt Moncton NB E1E 4H7",
    "addr:housenumber":"20",
    "addr:postcode":"e1e 4h7",
    "addr:street":"Edgewater Crt",
    "iso:country":"CA",
    "sg:address":"20 Edgewater Crt",
    "sg:city":"Moncton",
    "sg:classifiers":[
        {
            "category":"Personal",
            "subcategory":"Beauty Salon",
            "type":"Services"
        }
    ],
    "sg:phone":"+1 506 382 2087",
    "sg:postcode":"E1E 4H7",
    "sg:province":"NB",
    "wof:name":"Asthetik Marie-Marthe Bernier",
    "wof:placetype":"venue"
},
  "geometry": {"coordinates":[-64.83088684080001,46.0678405762],"type":"Point"}
}