{
  "type": "Feature",
  "properties": {
    "iso:country":"CA",
    "sg:address":"4503 Boul Saint-Jean # A",
    "sg:city":"Dollard-Des-Ormeaux",
    "sg:classifiers":[
        {
            "category":"Health Services",
            "subcategory":"Chiropractor",
            "type":"Services"
        }
    ],
    "sg:phone":"+1 514 626 1999",
    "sg:postcode":"H9H 2A4",
    "sg:province":"QC",
    "wof:name":"Clinique Chiropratique St-Jean",
    "wof:placetype":"venue"
},
  "geometry": {"coordinates":[-73.845642,45.484226],"type":"Point"}
}