{
  "type": "Feature",
  "properties": {
    "addr:full":"419 Rue Notre-Dame Joliette QC J6E 3H5",
    "addr:housenumber":"419",
    "addr:postcode":"j6e 3h5",
    "addr:street":"Rue Notre-Dame",
    "iso:country":"CA",
    "sg:address":"419 Rue Notre-Dame",
    "sg:city":"Joliette",
    "sg:classifiers":[
        {
            "category":"Shopping",
            "subcategory":"Clothing, Apparel, & Fashions",
            "type":"Retail Goods"
        }
    ],
    "sg:phone":"+1 450 755 2524",
    "sg:postcode":"J6E 3H5",
    "sg:province":"QC",
    "sg:tags":[
        "sportswear"
    ],
    "wof:name":"Brooklyn Hip Hop",
    "wof:placetype":"venue"
},
  "geometry": {"coordinates":[-73.43853799999999,46.024132],"type":"Point"}
}