{
  "type": "Feature",
  "properties": {
    "addr:full":"7700 Hurontario St Brampton ON L6Y 4M3",
    "addr:housenumber":"7700",
    "addr:postcode":"l6y 4m3",
    "addr:street":"Hurontario St",
    "iso:country":"CA",
    "sg:address":"7700 Hurontario St",
    "sg:city":"Brampton",
    "sg:classifiers":[
        {
            "category":"Government",
            "subcategory":"Office",
            "type":"Public Place"
        }
    ],
    "sg:phone":"+1 905 455 8288",
    "sg:postcode":"L6Y 4M3",
    "sg:province":"ON",
    "wof:name":"Canada Members of Parliament",
    "wof:placetype":"venue"
},
  "geometry": {"coordinates":[-79.7256011963,43.6600570679],"type":"Point"}
}