{
  "type": "Feature",
  "properties": {
    "addr:full":"208 1st Ave W Kelvington SK S0A 1W0",
    "addr:housenumber":"208",
    "addr:postcode":"s0a 1w0",
    "addr:street":"1St Ave W Kelvington",
    "iso:country":"CA",
    "sg:address":"208 1st Ave W",
    "sg:city":"Kelvington",
    "sg:classifiers":[
        {
            "category":"Organizations",
            "subcategory":"Professional Association",
            "type":"Services"
        }
    ],
    "sg:phone":"+1 306 327 5150",
    "sg:postcode":"S0A 1W0",
    "sg:province":"SK",
    "sg:tags":[
        "club"
    ],
    "wof:name":"Kelvington Legion Community",
    "wof:placetype":"venue"
},
  "geometry": {"coordinates":[-103.533646,52.165184],"type":"Point"}
}