{
  "type": "Feature",
  "properties": {
    "addr:full":"Wabasca AB T0G 2K0",
    "addr:postcode":"t0g 2k0",
    "iso:country":"CA",
    "sg:city":"Wabasca",
    "sg:classifiers":[
        {
            "category":"Health Services",
            "subcategory":"Clinic",
            "type":"Services"
        }
    ],
    "sg:phone":"+1 780 891 3640",
    "sg:postcode":"T0G 2K0",
    "sg:province":"AB",
    "wof:name":"Pee-Kis-Kwe-Tan Let's Talk Soc",
    "wof:placetype":"venue"
},
  "geometry": {"coordinates":[-113.823402405,55.948551178],"type":"Point"}
}