{
  "type": "Feature",
  "properties": {
    "iso:country":"CA",
    "sg:address":"31 Rue Academie",
    "sg:city":"Salaberry-DE-Valleyfield",
    "sg:classifiers":[
        {
            "category":"Food & Beverages",
            "subcategory":"Groceries & Convenience Stores",
            "type":"Retail Goods"
        }
    ],
    "sg:phone":"+1 450 377 9980",
    "sg:postcode":"J6T 4W4",
    "sg:province":"QC",
    "sg:tags":[
        "grocer"
    ],
    "wof:name":"Depanneur Academie Enr",
    "wof:placetype":"venue"
},
  "geometry": {"coordinates":[-74.127258,45.255314],"type":"Point"}
}