{
  "type": "Feature",
  "properties": {
    "iso:country":"CA",
    "sg:address":"1756 Alba Rd",
    "sg:city":"Okanagan Falls",
    "sg:classifiers":[
        {
            "category":"Manufacturing",
            "subcategory":"Tools & Machinery",
            "type":"Manufacturing & Wholesale Goods"
        }
    ],
    "sg:phone":"+1 250 497 8160",
    "sg:postcode":"V0H 1R0",
    "sg:province":"BC",
    "sg:tags":[
        "machine",
        "shop"
    ],
    "wof:name":"Vanholt Machine Works Ltd",
    "wof:placetype":"venue"
},
  "geometry": {"coordinates":[-119.57151794400001,49.3443832397],"type":"Point"}
}