{
  "type": "Feature",
  "properties": {
    "addr:full":"2111 Industrial Dr Regina SK S4P 3Y3",
    "addr:housenumber":"2111",
    "addr:postcode":"s4p 3y3",
    "addr:street":"Industrial Dr",
    "iso:country":"CA",
    "sg:address":"2111 Industrial Dr",
    "sg:city":"Regina",
    "sg:classifiers":[
        {
            "category":"Manufacturing",
            "subcategory":"Glass & Minerals",
            "type":"Manufacturing & Wholesale Goods"
        }
    ],
    "sg:phone":"+1 306 545 5677",
    "sg:postcode":"S4P 3Y3",
    "sg:province":"SK",
    "sg:tags":[
        "refractory"
    ],
    "wof:name":"Vesuvius Canada",
    "wof:placetype":"venue"
},
  "geometry": {"coordinates":[-104.595176697,50.4480133057],"type":"Point"}
}