{
  "type": "Feature",
  "properties": {
    "addr:full":"Rawdon QC J0K 1S0",
    "addr:postcode":"j0k 1s0",
    "iso:country":"CA",
    "sg:city":"Rawdon",
    "sg:classifiers":[
        {
            "category":"Shopping",
            "subcategory":"Clothing, Apparel, & Fashions",
            "type":"Retail Goods"
        }
    ],
    "sg:phone":"+1 450 834 1008",
    "sg:postcode":"J0K 1S0",
    "sg:province":"QC",
    "wof:name":"Boutik Kool",
    "wof:placetype":"venue"
},
  "geometry": {"coordinates":[-73.706917,46.042488],"type":"Point"}
}