{
  "type": "Feature",
  "properties": {
    "addr:full":"755 Wonderland Rd N London ON N6H 4L1",
    "addr:housenumber":"755",
    "addr:postcode":"n6h 4l1",
    "addr:street":"Wonderland Rd N",
    "iso:country":"CA",
    "sg:address":"755 Wonderland Rd N",
    "sg:city":"London",
    "sg:classifiers":[
        {
            "category":"Personal",
            "type":"Services"
        }
    ],
    "sg:phone":"+1 519 471 7181",
    "sg:postcode":"N6H 4L1",
    "sg:province":"ON",
    "sg:tags":[
        "program",
        "physical",
        "exercise",
        "fitness"
    ],
    "wof:name":"Athletic Club",
    "wof:placetype":"venue"
},
  "geometry": {"coordinates":[-81.2956619263,42.9900779724],"type":"Point"}
}