{
  "type": "Feature",
  "properties": {
    "addr:full":"Kitchener ON N2P 2A3",
    "addr:postcode":"n2p 2a3",
    "iso:country":"CA",
    "sg:city":"Kitchener",
    "sg:classifiers":[
        {
            "category":"Food & Beverages",
            "subcategory":"Bakery",
            "type":"Retail Goods"
        }
    ],
    "sg:phone":"+1 519 894 4545",
    "sg:postcode":"N2P 2A3",
    "sg:province":"ON",
    "sg:tags":[
        "tea",
        "coffee",
        "doughnut"
    ],
    "wof:name":"Tim Hortons",
    "wof:placetype":"venue"
},
  "geometry": {"coordinates":[-80.433128,43.394329],"type":"Point"}
}