{
  "type": "Feature",
  "properties": {
    "addr:full":"Ottawa ON K1P 6K7",
    "addr:postcode":"k1p 6k7",
    "iso:country":"CA",
    "sg:city":"Ottawa",
    "sg:classifiers":[
        {
            "category":"Real Estate",
            "subcategory":"Developer",
            "type":"Services"
        }
    ],
    "sg:phone":"+1 613 234 2296",
    "sg:postcode":"K1P 6K7",
    "sg:province":"ON",
    "wof:name":"Canril Corp",
    "wof:placetype":"venue"
},
  "geometry": {"coordinates":[-75.6958999634,45.4212379456],"type":"Point"}
}