{
  "type": "Feature",
  "properties": {
    "addr:full":"430 Pidard St Cleveland QC J0B 2H0",
    "addr:housenumber":"430",
    "addr:postcode":"j0b 2h0",
    "addr:street":"Pidard St",
    "iso:country":"CA",
    "sg:address":"430 Pidard St",
    "sg:city":"Cleveland",
    "sg:classifiers":[
        {
            "category":"Government",
            "subcategory":"Office",
            "type":"Public Place"
        }
    ],
    "sg:phone":"+1 819 826 5725",
    "sg:postcode":"J0B 2H0",
    "sg:province":"QC",
    "sg:tags":[
        "consultant",
        "recreation",
        "program",
        "village"
    ],
    "wof:name":"Loisirs DE Cleveland",
    "wof:placetype":"venue"
},
  "geometry": {"coordinates":[-72.10562896730001,45.7070465088],"type":"Point"}
}