{
  "type": "Feature",
  "properties": {
    "addr:full":"Saint-Felicien QC G8K 1S9",
    "addr:postcode":"g8k 1s9",
    "iso:country":"CA",
    "sg:city":"Saint-Felicien",
    "sg:classifiers":[
        {
            "category":"Retail",
            "subcategory":"Auto Repair",
            "type":"Services"
        }
    ],
    "sg:phone":"+1 418 679 4581",
    "sg:postcode":"G8K 1S9",
    "sg:province":"QC",
    "sg:tags":[
        "body",
        "automobile",
        "painting"
    ],
    "wof:name":"Garage Denis Menard Enr",
    "wof:placetype":"venue"
},
  "geometry": {"coordinates":[-72.41812896730001,48.6421432495],"type":"Point"}
}