{
  "type": "Feature",
  "properties": {
    "addr:full":"4926 49th St Redwater AB T0A 2W0",
    "addr:housenumber":"4926",
    "addr:postcode":"t0a 2w0",
    "addr:street":"49Th St",
    "iso:country":"CA",
    "sg:address":"4926 49th St",
    "sg:city":"Redwater",
    "sg:classifiers":[
        {
            "category":"Shopping",
            "subcategory":"Pharmacy",
            "type":"Retail Goods"
        }
    ],
    "sg:phone":"+1 780 942 3615",
    "sg:postcode":"T0A 2W0",
    "sg:province":"AB",
    "wof:name":"Terrene Pharmacy Ltd",
    "wof:placetype":"venue"
},
  "geometry": {"coordinates":[-113.108512878,53.9508705139],"type":"Point"}
}