{
  "type": "Feature",
  "properties": {
    "addr:full":"North York ON M2M 3V3",
    "addr:postcode":"m2m 3v3",
    "iso:country":"CA",
    "sg:city":"North York",
    "sg:classifiers":[
        {
            "category":"Professional",
            "subcategory":"Employment Agencies",
            "type":"Services"
        }
    ],
    "sg:phone":"+1 416 229 6868",
    "sg:postcode":"M2M 3V3",
    "sg:province":"ON",
    "sg:tags":[
        "consultant",
        "search",
        "executive"
    ],
    "wof:name":"Addmore Personnel Inc",
    "wof:placetype":"venue"
},
  "geometry": {"coordinates":[-79.4164733887,43.784324646],"type":"Point"}
}