{
  "type": "Feature",
  "properties": {
    "addr:full":"117 Main St Melfort SK S0E 1A0",
    "addr:housenumber":"117",
    "addr:postcode":"s0e 1a0",
    "addr:street":"Main St",
    "iso:country":"CA",
    "sg:address":"117 Main St",
    "sg:city":"Melfort",
    "sg:classifiers":[
        {
            "category":"Banks & Credit Unions",
            "subcategory":"Bank",
            "type":"Services"
        }
    ],
    "sg:phone":"+1 306 752 2881",
    "sg:postcode":"S0E 1A0",
    "sg:province":"SK",
    "wof:name":"Cibc",
    "wof:placetype":"venue"
},
  "geometry": {"coordinates":[-104.611435,52.859924],"type":"Point"}
}