{
  "type": "Feature",
  "properties": {
    "addr:full":"631 Dundas St W # B Belleville ON K8N 4Z2",
    "addr:housenumber":"631",
    "addr:postcode":"k8n 4z2",
    "addr:street":"Dundas St W # B",
    "iso:country":"CA",
    "sg:address":"631 Dundas St W # B",
    "sg:city":"Belleville",
    "sg:classifiers":[
        {
            "category":"Real Estate",
            "subcategory":"Developer",
            "type":"Services"
        }
    ],
    "sg:phone":"+1 613 962 8468",
    "sg:postcode":"K8N 4Z2",
    "sg:province":"ON",
    "sg:tags":[
        "cemetery"
    ],
    "wof:name":"Belleville Cemetery",
    "wof:placetype":"venue"
},
  "geometry": {"coordinates":[-77.412399292,44.1457939148],"type":"Point"}
}