{
  "type": "Feature",
  "properties": {
    "addr:full":"121 Columbia Dr Claresholm AB T0L 0T0",
    "addr:housenumber":"121",
    "addr:postcode":"t0l 0t0",
    "addr:street":"Columbia Dr",
    "iso:country":"CA",
    "sg:address":"121 Columbia Dr",
    "sg:city":"Claresholm",
    "sg:classifiers":[
        {
            "category":"Home & Garden",
            "subcategory":"Furniture",
            "type":"Retail Goods"
        }
    ],
    "sg:phone":"+1 403 625 3503",
    "sg:postcode":"T0L 0T0",
    "sg:province":"AB",
    "wof:name":"Gerto Cabinets & Furniture Ltd",
    "wof:placetype":"venue"
},
  "geometry": {"coordinates":[-113.589668274,50.0370140076],"type":"Point"}
}