{
  "type": "Feature",
  "properties": {
    "addr:full":"Repentigny QC J6A 2P4",
    "addr:postcode":"j6a 2p4",
    "iso:country":"CA",
    "sg:city":"Repentigny",
    "sg:classifiers":[
        {
            "category":"Shopping",
            "subcategory":"Clothing, Apparel, & Fashions",
            "type":"Retail Goods"
        }
    ],
    "sg:phone":"+1 450 581 4955",
    "sg:postcode":"J6A 2P4",
    "sg:province":"QC",
    "wof:name":"LA Cle Du Plaisir",
    "wof:placetype":"venue"
},
  "geometry": {"coordinates":[-73.470749,45.716702],"type":"Point"}
}