{
  "type": "Feature",
  "properties": {
    "iso:country":"CA",
    "sg:city":"Canso",
    "sg:classifiers":[
        {
            "category":"Travel",
            "subcategory":"Hotels & Motels",
            "type":"Entertainment"
        }
    ],
    "sg:phone":"+1 902 366 2400",
    "sg:postcode":"B0H 1H0",
    "sg:province":"NS",
    "wof:name":"Last Port Motel",
    "wof:placetype":"venue"
},
  "geometry": {"coordinates":[-60.996487,45.336113],"type":"Point"}
}