{
  "type": "Feature",
  "properties": {
    "addr:full":"Sainte-Anne-Des-Plaines QC J0N 1H0",
    "addr:postcode":"j0n 1h0",
    "iso:country":"CA",
    "sg:city":"Sainte-Anne-Des-Plaines",
    "sg:classifiers":[
        {
            "category":"Building & Trades",
            "subcategory":"Landscaping Services",
            "type":"Services"
        }
    ],
    "sg:phone":"+1 450 478 2222",
    "sg:postcode":"J0N 1H0",
    "sg:province":"QC",
    "sg:tags":[
        "sod",
        "sodding"
    ],
    "wof:name":"Fermes Michel Bastien Inc",
    "wof:placetype":"venue"
},
  "geometry": {"coordinates":[-73.76518249510001,45.7622795105],"type":"Point"}
}