{
  "type": "Feature",
  "properties": {
    "addr:full":"72 Steeles Ave W Thornhill ON L4J 1A1",
    "addr:housenumber":"72",
    "addr:postcode":"l4j 1a1",
    "addr:street":"Steeles Ave W",
    "iso:country":"CA",
    "sg:address":"72 Steeles Ave W",
    "sg:city":"Thornhill",
    "sg:classifiers":[
        {
            "category":"Manufacturing",
            "subcategory":"Food",
            "type":"Manufacturing & Wholesale Goods"
        }
    ],
    "sg:phone":"+1 905 881 7393",
    "sg:postcode":"L4J 1A1",
    "sg:province":"ON",
    "sg:tags":[
        "product",
        "manufacturer"
    ],
    "wof:name":"Nino D'Aversa Bakery Ltd",
    "wof:placetype":"venue"
},
  "geometry": {"coordinates":[-79.4228134155,43.7976074219],"type":"Point"}
}