{
  "type": "Feature",
  "properties": {
    "addr:full":"8042 Rue Saint-Denis Montreal QC H2R 2G1",
    "addr:housenumber":"8042",
    "addr:postcode":"h2r 2g1",
    "addr:street":"Rue Saint-Denis",
    "iso:country":"CA",
    "sg:address":"8042 Rue Saint-Denis",
    "sg:city":"Montreal",
    "sg:classifiers":[
        {
            "category":"Organizations",
            "subcategory":"Religious Organization",
            "type":"Services"
        }
    ],
    "sg:phone":"+1 514 388 2501",
    "sg:postcode":"H2R 2G1",
    "sg:province":"QC",
    "sg:tags":[
        "church"
    ],
    "wof:name":"Eglise Biblique Pierre",
    "wof:placetype":"venue"
},
  "geometry": {"coordinates":[-73.6282501221,45.542175293],"type":"Point"}
}