{
  "type": "Feature",
  "properties": {
    "addr:full":"204 Jane St Toronto ON M6S 3Y9",
    "addr:housenumber":"204",
    "addr:postcode":"m6s 3y9",
    "addr:street":"Jane St",
    "iso:country":"CA",
    "sg:address":"204 Jane St",
    "sg:city":"Toronto",
    "sg:classifiers":[
        {
            "category":"Food & Beverages",
            "subcategory":"Groceries & Convenience Stores",
            "type":"Retail Goods"
        }
    ],
    "sg:phone":"+1 416 763 2070",
    "sg:postcode":"M6S 3Y9",
    "sg:province":"ON",
    "sg:tags":[
        "grocer"
    ],
    "wof:name":"A's Variety",
    "wof:placetype":"venue"
},
  "geometry": {"coordinates":[-79.486633,43.654144],"type":"Point"}
}