{
  "type": "Feature",
  "properties": {
    "addr:full":"214 Center Ave Blumenort MB R0A 0C0",
    "addr:housenumber":"214",
    "addr:postcode":"r0a 0c0",
    "addr:street":"Center Ave",
    "iso:country":"CA",
    "sg:address":"214 Center Ave",
    "sg:city":"Blumenort",
    "sg:classifiers":[
        {
            "category":"Freight",
            "type":"Transportation"
        }
    ],
    "sg:phone":"+1 204 326 6380",
    "sg:postcode":"R0A 0C0",
    "sg:province":"MB",
    "sg:tags":[
        "hauling",
        "livestock",
        "trucking"
    ],
    "wof:name":"Steve's Livestock Transport",
    "wof:placetype":"venue"
},
  "geometry": {"coordinates":[-96.69016999999999,49.604256],"type":"Point"}
}