{
  "type": "Feature",
  "properties": {
    "addr:full":"5430 Boul Cousineau Saint-Hubert QC J3Y 7J8",
    "addr:housenumber":"5430",
    "addr:postcode":"j3y 7j8",
    "addr:street":"Boul Cousineau",
    "iso:country":"CA",
    "sg:address":"5430 Boul Cousineau",
    "sg:city":"Saint-Hubert",
    "sg:classifiers":[
        {
            "category":"Shopping",
            "subcategory":"Bicycles & Sporting Goods",
            "type":"Retail Goods"
        }
    ],
    "sg:phone":"+1 450 445 8356",
    "sg:postcode":"J3Y 7J8",
    "sg:province":"QC",
    "wof:name":"Velo",
    "wof:placetype":"venue"
},
  "geometry": {"coordinates":[-73.4199371338,45.5003738403],"type":"Point"}
}