{
  "type": "Feature",
  "properties": {
    "addr:full":"703 4th Ave Keremeos BC V0X 1N0",
    "addr:housenumber":"703",
    "addr:postcode":"v0x 1n0",
    "addr:street":"4Th Ave",
    "iso:country":"CA",
    "sg:address":"703 4th Ave",
    "sg:city":"Keremeos",
    "sg:classifiers":[
        {
            "category":"Recreation",
            "type":"Entertainment"
        }
    ],
    "sg:phone":"+1 250 499 5766",
    "sg:postcode":"V0X 1N0",
    "sg:province":"BC",
    "sg:tags":[
        "pool",
        "swimming"
    ],
    "wof:name":"Keremeos Swimming Pool",
    "wof:placetype":"venue"
},
  "geometry": {"coordinates":[-119.829437,49.206314],"type":"Point"}
}