{
  "type": "Feature",
  "properties": {
    "addr:full":"Whitewood SK S0G 5C0",
    "addr:postcode":"s0g 5c0",
    "iso:country":"CA",
    "sg:city":"Whitewood",
    "sg:classifiers":[
        {
            "category":"Autos & Motor Vehicles",
            "subcategory":"Fuel & Gas Station",
            "type":"Retail Goods"
        }
    ],
    "sg:phone":"+1 306 696 2527",
    "sg:postcode":"S0G 5C0",
    "sg:province":"SK",
    "sg:tags":[
        "oil"
    ],
    "wof:name":"Lloyd & Johnny's Gas Bar",
    "wof:placetype":"venue"
},
  "geometry": {"coordinates":[-102.25789642300001,50.3278312683],"type":"Point"}
}