{
  "type": "Feature",
  "properties": {
    "addr:full":"Knowlton QC J0E 1V0",
    "addr:postcode":"j0e 1v0",
    "addr:street":"Knowlton",
    "iso:country":"CA",
    "sg:city":"Knowlton",
    "sg:classifiers":[
        {
            "category":"Cinema",
            "subcategory":"Movie Rental",
            "type":"Entertainment"
        }
    ],
    "sg:phone":"+1 450 243 6700",
    "sg:postcode":"J0E 1V0",
    "sg:province":"QC",
    "sg:tags":[
        "leasing",
        "video",
        "disc",
        "tape"
    ],
    "wof:name":"Knowlton Video Enr",
    "wof:placetype":"venue"
},
  "geometry": {"coordinates":[-72.514168,45.216824],"type":"Point"}
}