{
  "type": "Feature",
  "properties": {
    "addr:full":"Coquitlam BC V3K 3P4",
    "addr:postcode":"v3k 3p4",
    "iso:country":"CA",
    "sg:city":"Coquitlam",
    "sg:classifiers":[
        {
            "category":"Professional",
            "subcategory":"Accounting & Tax Preparation",
            "type":"Services"
        }
    ],
    "sg:phone":"+1 604 936 4221",
    "sg:postcode":"V3K 3P4",
    "sg:province":"BC",
    "sg:tags":[
        "consultant",
        "return",
        "filing"
    ],
    "wof:name":"H & R Block Canada Inc",
    "wof:placetype":"venue"
},
  "geometry": {"coordinates":[-122.861473,49.249119],"type":"Point"}
}