{
  "type": "Feature",
  "properties": {
    "iso:country":"CA",
    "sg:address":"320 65 Ave SE # A",
    "sg:city":"Calgary",
    "sg:classifiers":[
        {
            "category":"Shopping",
            "type":"Retail Goods"
        }
    ],
    "sg:phone":"+1 403 252 0445",
    "sg:postcode":"T2H 0R8",
    "sg:province":"AB",
    "sg:tags":[
        "equipment",
        "church",
        "supply"
    ],
    "wof:name":"Campus Supply CO Ltd",
    "wof:placetype":"venue"
},
  "geometry": {"coordinates":[-114.05947113000001,50.9944190979],"type":"Point"}
}