{
  "type": "Feature",
  "properties": {
    "addr:full":"102 Inch Arran Ave Dalhousie NB E8C 1Y6",
    "addr:housenumber":"102",
    "addr:postcode":"e8c 1y6",
    "addr:street":"Inch Arran Ave",
    "iso:country":"CA",
    "sg:address":"102 Inch Arran Ave",
    "sg:city":"Dalhousie",
    "sg:classifiers":[
        {
            "category":"Food & Beverages",
            "subcategory":"Groceries & Convenience Stores",
            "type":"Retail Goods"
        }
    ],
    "sg:phone":"+1 506 684 2101",
    "sg:postcode":"E8C 1Y6",
    "sg:province":"NB",
    "wof:name":"Depanneur Bon Ami",
    "wof:placetype":"venue"
},
  "geometry": {"coordinates":[-66.3535308838,48.0599250793],"type":"Point"}
}