{
  "type": "Feature",
  "properties": {
    "addr:full":"Yamachiche QC G0X 3L0",
    "addr:postcode":"g0x 3l0",
    "iso:country":"CA",
    "sg:city":"Yamachiche",
    "sg:classifiers":[
        {
            "category":"Social Services",
            "type":"Services"
        }
    ],
    "sg:phone":"+1 819 296 3339",
    "sg:postcode":"G0X 3L0",
    "sg:province":"QC",
    "sg:tags":[
        "home",
        "senior",
        "retirement",
        "community",
        "citizen"
    ],
    "wof:name":"Maison Barthelemy-Caron",
    "wof:placetype":"venue"
},
  "geometry": {"coordinates":[-72.8317642212,46.2820014954],"type":"Point"}
}