{
  "type": "Feature",
  "properties": {
    "addr:full":"2894 Dufferin St North York ON M6B 3S6",
    "addr:housenumber":"2894",
    "addr:postcode":"m6b 3s6",
    "addr:street":"Dufferin St",
    "iso:country":"CA",
    "sg:address":"2894 Dufferin St",
    "sg:city":"North York",
    "sg:classifiers":[
        {
            "category":"Shopping",
            "subcategory":"Discount & Variety Stores",
            "type":"Retail Goods"
        }
    ],
    "sg:phone":"+1 416 782 8556",
    "sg:postcode":"M6B 3S6",
    "sg:province":"ON",
    "wof:name":"Astro Variety",
    "wof:placetype":"venue"
},
  "geometry": {"coordinates":[-79.45347599999999,43.707954],"type":"Point"}
}