{
  "type": "Feature",
  "properties": {
    "addr:full":"2449 Ch Lucerne Mont-Royal QC H3R 2K5",
    "addr:housenumber":"2449",
    "addr:postcode":"h3r 2k5",
    "addr:street":"Ch Lucerne",
    "iso:country":"CA",
    "sg:address":"2449 Ch Lucerne",
    "sg:city":"Mont-Royal",
    "sg:classifiers":[
        {
            "category":"Personal",
            "subcategory":"Beauty Salon",
            "type":"Services"
        }
    ],
    "sg:phone":"+1 514 737 5831",
    "sg:postcode":"H3R 2K5",
    "sg:province":"QC",
    "wof:name":"Salon Evolove",
    "wof:placetype":"venue"
},
  "geometry": {"coordinates":[-73.661766,45.507633],"type":"Point"}
}