{
  "type": "Feature",
  "properties": {
    "addr:full":"Concord ON L4K 4G1",
    "addr:postcode":"l4k 4g1",
    "iso:country":"CA",
    "sg:city":"Concord",
    "sg:classifiers":[
        {
            "category":"Building & Trades",
            "subcategory":"Construction",
            "type":"Services"
        }
    ],
    "sg:phone":"+1 905 660 5111",
    "sg:postcode":"L4K 4G1",
    "sg:province":"ON",
    "sg:tags":[
        "general",
        "contractor"
    ],
    "wof:name":"A M Citriniti & CO Ltd",
    "wof:placetype":"venue"
},
  "geometry": {"coordinates":[-79.5351715088,43.8039207458],"type":"Point"}
}