{
  "type": "Feature",
  "properties": {
    "addr:full":"Winnipeg MB R3M 0W7",
    "addr:postcode":"r3m 0w7",
    "iso:country":"CA",
    "sg:city":"Winnipeg",
    "sg:classifiers":[
        {
            "category":"Personal",
            "subcategory":"Beauty Salon",
            "type":"Services"
        }
    ],
    "sg:phone":"+1 204 477 0197",
    "sg:postcode":"R3M 0W7",
    "sg:province":"MB",
    "wof:name":"Ken Cori's Studio 103",
    "wof:placetype":"venue"
},
  "geometry": {"coordinates":[-97.15911102290001,49.8690338135],"type":"Point"}
}