{
  "type": "Feature",
  "properties": {
    "addr:full":"160 Main St Unionville ON L3R 2G9",
    "addr:housenumber":"160",
    "addr:postcode":"l3r 2g9",
    "addr:street":"Main St",
    "iso:country":"CA",
    "sg:address":"160 Main St",
    "sg:city":"Unionville",
    "sg:classifiers":[
        {
            "category":"Personal",
            "subcategory":"Beauty Salon",
            "type":"Services"
        }
    ],
    "sg:phone":"+1 905 946 1995",
    "sg:postcode":"L3R 2G9",
    "sg:province":"ON",
    "wof:name":"Blush Spa & Salon",
    "wof:placetype":"venue"
},
  "geometry": {"coordinates":[-79.3119735718,43.8667144775],"type":"Point"}
}