{
  "type": "Feature",
  "properties": {
    "addr:full":"Thornhill ON L3T 7P7",
    "addr:postcode":"l3t 7p7",
    "iso:country":"CA",
    "sg:city":"Thornhill",
    "sg:classifiers":[
        {
            "category":"Personal",
            "subcategory":"Beauty Salon",
            "type":"Services"
        }
    ],
    "sg:phone":"+1 905 764 7711",
    "sg:postcode":"L3T 7P7",
    "sg:province":"ON",
    "wof:name":"Bita Beauty",
    "wof:placetype":"venue"
},
  "geometry": {"coordinates":[-79.4009475708,43.8215332031],"type":"Point"}
}