{
  "type": "Feature",
  "properties": {
    "addr:full":"Orleans ON K1C 1T1",
    "addr:postcode":"k1c 1t1",
    "iso:country":"CA",
    "sg:city":"Orleans",
    "sg:classifiers":[
        {
            "category":"Building & Trades",
            "subcategory":"Landscaping Services",
            "type":"Services"
        }
    ],
    "sg:phone":"+1 613 830 0614",
    "sg:postcode":"K1C 1T1",
    "sg:province":"ON",
    "sg:tags":[
        "lawn",
        "maintenance",
        "grounds"
    ],
    "wof:name":"Servicemaster Lawncare",
    "wof:placetype":"venue"
},
  "geometry": {"coordinates":[-75.481842,45.488632],"type":"Point"}
}