{
  "type": "Feature",
  "properties": {
    "addr:full":"414 Spadina Rd Toronto ON M5P 2W2",
    "addr:housenumber":"414",
    "addr:postcode":"m5p 2w2",
    "addr:street":"Spadina Rd",
    "iso:country":"CA",
    "sg:address":"414 Spadina Rd",
    "sg:city":"Toronto",
    "sg:classifiers":[
        {
            "category":"Banks & Credit Unions",
            "subcategory":"Bank",
            "type":"Services"
        }
    ],
    "sg:phone":"+1 416 974 7170",
    "sg:postcode":"M5P 2W2",
    "sg:province":"ON",
    "wof:name":"Royal Bank Financial Group",
    "wof:placetype":"venue"
},
  "geometry": {"coordinates":[-79.412766,43.688534],"type":"Point"}
}