{
  "type": "Feature",
  "properties": {
    "iso:country":"CA",
    "sg:address":"1850 9th Ave NW",
    "sg:city":"Moose Jaw",
    "sg:classifiers":[
        {
            "category":"Freight",
            "type":"Transportation"
        }
    ],
    "sg:phone":"+1 306 693 7644",
    "sg:postcode":"S6H 7K7",
    "sg:province":"SK",
    "sg:tags":[
        "grain",
        "elevator",
        "trucking"
    ],
    "wof:name":"Ag Pro Grain",
    "wof:placetype":"venue"
},
  "geometry": {"coordinates":[-105.557579041,50.4093284607],"type":"Point"}
}