{
  "type": "Feature",
  "properties": {
    "addr:full":"6326 1st Ave N Regina SK S4T 7C3",
    "addr:housenumber":"6326",
    "addr:postcode":"s4t 7c3",
    "addr:street":"1St Ave N",
    "iso:country":"CA",
    "sg:address":"6326 1st Ave N",
    "sg:city":"Regina",
    "sg:classifiers":[
        {
            "category":"Retail",
            "subcategory":"Animal Services",
            "type":"Services"
        }
    ],
    "sg:phone":"+1 306 543 2226",
    "sg:postcode":"S4T 7C3",
    "sg:province":"SK",
    "sg:tags":[
        "pet",
        "grooming",
        "washing"
    ],
    "wof:name":"Doggone Pet Salon",
    "wof:placetype":"venue"
},
  "geometry": {"coordinates":[-104.67111199999999,50.47411],"type":"Point"}
}