{
  "type": "Feature",
  "properties": {
    "addr:full":"RR 1 Warburg AB T0C 2T0",
    "addr:postcode":"t0c 2t0",
    "addr:street":"Rr 1",
    "iso:country":"CA",
    "sg:address":"RR 1",
    "sg:city":"Warburg",
    "sg:classifiers":[
        {
            "category":"Farming",
            "subcategory":"Farm",
            "type":"Manufacturing & Wholesale Goods"
        }
    ],
    "sg:phone":"+1 780 848 2472",
    "sg:postcode":"T0C 2T0",
    "sg:province":"AB",
    "wof:name":"Oscar's Loader Svc Ltd",
    "wof:placetype":"venue"
},
  "geometry": {"coordinates":[-114.318642,53.181034],"type":"Point"}
}