{
  "type": "Feature",
  "properties": {
    "addr:full":"5900 Boul Etienne-Dallaire Levis QC G6V 8T3",
    "addr:housenumber":"5900",
    "addr:postcode":"g6v 8t3",
    "addr:street":"Boul Etienne-Dallaire",
    "iso:country":"CA",
    "sg:address":"5900 Boul Etienne-Dallaire",
    "sg:city":"Levis",
    "sg:classifiers":[
        {
            "category":"Food & Beverages",
            "subcategory":"Groceries & Convenience Stores",
            "type":"Retail Goods"
        }
    ],
    "sg:phone":"+1 418 838 9396",
    "sg:postcode":"G6V 8T3",
    "sg:province":"QC",
    "wof:name":"Depanneur Gestion Daniel Roy",
    "wof:placetype":"venue"
},
  "geometry": {"coordinates":[-71.1644668579,46.7935752869],"type":"Point"}
}