{
  "type": "Feature",
  "properties": {
    "addr:full":"91 Main St Sundridge ON P0A 1Z0",
    "addr:housenumber":"91",
    "addr:postcode":"p0a 1z0",
    "addr:street":"Main St",
    "iso:country":"CA",
    "sg:address":"91 Main St",
    "sg:city":"Sundridge",
    "sg:classifiers":[
        {
            "category":"Food & Beverages",
            "subcategory":"Groceries & Convenience Stores",
            "type":"Retail Goods"
        }
    ],
    "sg:phone":"+1 705 384 7025",
    "sg:postcode":"P0A 1Z0",
    "sg:province":"ON",
    "sg:tags":[
        "product"
    ],
    "wof:name":"Village Bins",
    "wof:placetype":"venue"
},
  "geometry": {"coordinates":[-79.39109000000001,45.770794],"type":"Point"}
}