{
  "type": "Feature",
  "properties": {
    "addr:full":"Hemmingford QC J0L 1H0",
    "addr:postcode":"j0l 1h0",
    "iso:country":"CA",
    "sg:city":"Hemmingford",
    "sg:classifiers":[
        {
            "category":"Real Estate",
            "subcategory":"Real Estate Agent",
            "type":"Services"
        }
    ],
    "sg:phone":"+1 450 247 2773",
    "sg:postcode":"J0L 1H0",
    "sg:province":"QC",
    "wof:name":"Remax",
    "wof:placetype":"venue"
},
  "geometry": {"coordinates":[-73.585426,45.0518],"type":"Point"}
}