{
  "type": "Feature",
  "properties": {
    "addr:full":"3105 Boul Rome Brossard QC J4Y 1R2",
    "addr:housenumber":"3105",
    "addr:postcode":"j4y 1r2",
    "addr:street":"Boul Rome",
    "iso:country":"CA",
    "sg:address":"3105 Boul Rome",
    "sg:city":"Brossard",
    "sg:classifiers":[
        {
            "category":"Organizations",
            "subcategory":"Community Association",
            "type":"Services"
        }
    ],
    "sg:phone":"+1 450 462 4019",
    "sg:postcode":"J4Y 1R2",
    "sg:province":"QC",
    "sg:tags":[
        "club"
    ],
    "wof:name":"Club DE Patinage Artistique",
    "wof:placetype":"venue"
},
  "geometry": {"coordinates":[-73.45566599999999,45.44994],"type":"Point"}
}