{
  "type": "Feature",
  "properties": {
    "addr:full":"Port Coquitlam BC V3C 4Z1",
    "addr:postcode":"v3c 4z1",
    "iso:country":"CA",
    "sg:city":"Port Coquitlam",
    "sg:classifiers":[
        {
            "category":"Home & Garden",
            "subcategory":"Building Materials",
            "type":"Retail Goods"
        }
    ],
    "sg:phone":"+1 604 944 7118",
    "sg:postcode":"V3C 4Z1",
    "sg:province":"BC",
    "sg:tags":[
        "bending",
        "glass",
        "drilling",
        "grinding"
    ],
    "wof:name":"Seabird Bent Glass",
    "wof:placetype":"venue"
},
  "geometry": {"coordinates":[-122.762398,49.250759],"type":"Point"}
}