{
  "type": "Feature",
  "properties": {
    "addr:full":"26 Carmel Rd Sault Ste Marie ON P6A 3N9",
    "addr:housenumber":"26",
    "addr:postcode":"p6a 3n9",
    "addr:street":"Carmel Rd",
    "iso:country":"CA",
    "sg:address":"26 Carmel Rd",
    "sg:city":"Sault Ste Marie",
    "sg:classifiers":[
        {
            "category":"Organizations",
            "subcategory":"Religious Organization",
            "type":"Services"
        }
    ],
    "sg:phone":"+1 705 949 1072",
    "sg:postcode":"P6A 3N9",
    "sg:province":"ON",
    "sg:tags":[
        "church"
    ],
    "wof:name":"St Jeromes Roman Catholic Chrh",
    "wof:placetype":"venue"
},
  "geometry": {"coordinates":[-84.293076,46.510563],"type":"Point"}
}