{
  "type": "Feature",
  "properties": {
    "addr:full":"240 Water St Summerside PE C1N 1B3",
    "addr:housenumber":"240",
    "addr:postcode":"c1n 1b3",
    "addr:street":"Water St",
    "iso:country":"CA",
    "sg:address":"240 Water St",
    "sg:city":"Summerside",
    "sg:classifiers":[
        {
            "category":"Shopping",
            "subcategory":"Books",
            "type":"Retail Goods"
        }
    ],
    "sg:phone":"+1 902 888 2665",
    "sg:postcode":"C1N 1B3",
    "sg:province":"PE",
    "sg:tags":[
        "dealer"
    ],
    "wof:name":"Avonlea Book Store",
    "wof:placetype":"venue"
},
  "geometry": {"coordinates":[-63.789764,46.391216],"type":"Point"}
}