{
  "type": "Feature",
  "properties": {
    "addr:full":"1187 Bank St Ottawa ON K1S 3X7",
    "addr:housenumber":"1187",
    "addr:postcode":"k1s 3x7",
    "addr:street":"Bank St",
    "iso:country":"CA",
    "sg:address":"1187 Bank St",
    "sg:city":"Ottawa",
    "sg:classifiers":[
        {
            "category":"Education",
            "subcategory":"Special Training",
            "type":"Public Place"
        }
    ],
    "sg:phone":"+1 613 730 3349",
    "sg:postcode":"K1S 3X7",
    "sg:province":"ON",
    "sg:tags":[
        "instruction",
        "driving"
    ],
    "wof:name":"Achievers Driving School",
    "wof:placetype":"venue"
},
  "geometry": {"coordinates":[-75.681496,45.39209],"type":"Point"}
}