{
  "type": "Feature",
  "properties": {
    "addr:full":"327 Boul LA Salle Baie-Comeau QC G4Z 2L5",
    "addr:housenumber":"327",
    "addr:postcode":"g4z 2l5",
    "addr:street":"Boul La",
    "iso:country":"CA",
    "sg:address":"327 Boul LA Salle",
    "sg:city":"Baie-Comeau",
    "sg:classifiers":[
        {
            "category":"Professional",
            "subcategory":"Business Services",
            "type":"Services"
        }
    ],
    "sg:phone":"+1 418 296 6063",
    "sg:postcode":"G4Z 2L5",
    "sg:province":"QC",
    "sg:tags":[
        "interior",
        "consultant",
        "design",
        "decorator",
        "paint"
    ],
    "wof:name":"Galerie Du Tapis",
    "wof:placetype":"venue"
},
  "geometry": {"coordinates":[-68.191795,49.214737],"type":"Point"}
}