{
  "type": "Feature",
  "properties": {
    "addr:full":"5009 47th Ave Pouce Coupe BC V0C 2C0",
    "addr:housenumber":"5009",
    "addr:postcode":"bc v0c 2c0",
    "addr:street":"47Th Ave",
    "iso:country":"CA",
    "sg:address":"5009 47th Ave",
    "sg:city":"Pouce Coupe",
    "sg:classifiers":[
        {
            "category":"Organizations",
            "subcategory":"Professional Association",
            "type":"Services"
        }
    ],
    "sg:phone":"+1 250 786 5144",
    "sg:postcode":"V0C 2C0",
    "sg:province":"BC",
    "wof:name":"Royal Canadian Legion",
    "wof:placetype":"venue"
},
  "geometry": {"coordinates":[-120.133712769,55.7128677368],"type":"Point"}
}