{
  "type": "Feature",
  "properties": {
    "addr:full":"77 Milliken Meadows Dr Markham ON L3R 0V5",
    "addr:housenumber":"77",
    "addr:postcode":"l3r 0v5",
    "addr:street":"Milliken Meadows Dr",
    "iso:country":"CA",
    "sg:address":"77 Milliken Meadows Dr",
    "sg:city":"Markham",
    "sg:classifiers":[
        {
            "category":"Organizations",
            "subcategory":"Religious Organization",
            "type":"Services"
        }
    ],
    "sg:phone":"+1 905 479 3322",
    "sg:postcode":"L3R 0V5",
    "sg:province":"ON",
    "sg:tags":[
        "church"
    ],
    "wof:name":"Markham Christian Community",
    "wof:placetype":"venue"
},
  "geometry": {"coordinates":[-79.3080062866,43.8360671997],"type":"Point"}
}