{
  "type": "Feature",
  "properties": {
    "iso:country":"CA",
    "sg:address":"472 Kirkfield St",
    "sg:city":"Winnipeg",
    "sg:classifiers":[
        {
            "category":"Organizations",
            "subcategory":"Religious Organization",
            "type":"Services"
        }
    ],
    "sg:phone":"+1 204 837 1017",
    "sg:postcode":"R3K 1E6",
    "sg:province":"MB",
    "sg:tags":[
        "church"
    ],
    "wof:name":"Kirkfield Park United Church",
    "wof:placetype":"venue"
},
  "geometry": {"coordinates":[-97.29048156739999,49.8781700134],"type":"Point"}
}