{
  "type": "Feature",
  "properties": {
    "iso:country":"CA",
    "sg:address":"470 Rue Ellice",
    "sg:city":"Beauharnois",
    "sg:classifiers":[
        {
            "category":"Shopping",
            "subcategory":"Clothing, Apparel, & Fashions",
            "type":"Retail Goods"
        }
    ],
    "sg:phone":"+1 450 429 4545",
    "sg:postcode":"J6N 1X7",
    "sg:province":"QC",
    "sg:tags":[
        "fur",
        "business"
    ],
    "wof:name":"Fourrures Laberge Inc",
    "wof:placetype":"venue"
},
  "geometry": {"coordinates":[-73.87525177000001,45.3140907288],"type":"Point"}
}