{
  "type": "Feature",
  "properties": {
    "iso:country":"CA",
    "sg:address":"196 19th Ave E",
    "sg:city":"Vancouver",
    "sg:classifiers":[
        {
            "category":"Professional",
            "subcategory":"Accounting & Tax Preparation",
            "type":"Services"
        }
    ],
    "sg:phone":"+1 604 708 9897",
    "sg:postcode":"V5V 1H9",
    "sg:province":"BC",
    "sg:tags":[
        "accountant"
    ],
    "wof:name":"Beltramello, Helen L",
    "wof:placetype":"venue"
},
  "geometry": {"coordinates":[-123.10105896,49.2536239624],"type":"Point"}
}