{
  "type": "Feature",
  "properties": {
    "addr:full":"7119 Tottington Dr Mississauga ON L5N 7S4",
    "addr:housenumber":"7119",
    "addr:postcode":"l5n 7s4",
    "addr:street":"Tottington Dr",
    "iso:country":"CA",
    "sg:address":"7119 Tottington Dr",
    "sg:city":"Mississauga",
    "sg:classifiers":[
        {
            "category":"Wholesale",
            "subcategory":"Durable Goods & Equipment",
            "type":"Manufacturing & Wholesale Goods"
        }
    ],
    "sg:phone":"+1 905 816 9333",
    "sg:postcode":"L5N 7S4",
    "sg:province":"ON",
    "sg:tags":[
        "exporter"
    ],
    "wof:name":"G S Overseas Canada Ltd",
    "wof:placetype":"venue"
},
  "geometry": {"coordinates":[-79.749641,43.616516],"type":"Point"}
}