{
  "type": "Feature",
  "properties": {
    "addr:full":"550 Rue Marie-DE-L'Incarnation Quebec QC G1N 3H4",
    "addr:housenumber":"550",
    "addr:postcode":"g1n 3h4",
    "addr:street":"Rue Marie-De-L'Incarnation",
    "iso:country":"CA",
    "sg:address":"550 Rue Marie-DE-L'Incarnation",
    "sg:city":"Quebec",
    "sg:classifiers":[
        {
            "category":"Building & Trades",
            "subcategory":"Construction",
            "type":"Services"
        }
    ],
    "sg:phone":"+1 418 529 7381",
    "sg:postcode":"G1N 3H4",
    "sg:province":"QC",
    "sg:tags":[
        "maker",
        "cabinet"
    ],
    "wof:name":"Atelier Alv Inc",
    "wof:placetype":"venue"
},
  "geometry": {"coordinates":[-71.419472,46.858582],"type":"Point"}
}