{
  "type": "Feature",
  "properties": {
    "addr:full":"930 Sheldon Crt Burlington ON L7L 5K6",
    "addr:housenumber":"930",
    "addr:postcode":"l7l 5k6",
    "addr:street":"Sheldon Crt",
    "iso:country":"CA",
    "sg:address":"930 Sheldon Crt",
    "sg:city":"Burlington",
    "sg:classifiers":[
        {
            "category":"Organizations",
            "subcategory":"Labor Organization",
            "type":"Services"
        }
    ],
    "sg:phone":"+1 905 631 8989",
    "sg:postcode":"L7L 5K6",
    "sg:province":"ON",
    "wof:name":"Ontario Pipe Trades Council",
    "wof:placetype":"venue"
},
  "geometry": {"coordinates":[-79.759201,43.386257],"type":"Point"}
}