{
  "type": "Feature",
  "properties": {
    "addr:full":"Scarborough ON M1K 5G8",
    "addr:postcode":"m1k 5g8",
    "iso:country":"CA",
    "sg:city":"Scarborough",
    "sg:classifiers":[
        {
            "category":"Social Services",
            "subcategory":"Job Training",
            "type":"Services"
        }
    ],
    "sg:phone":"+1 416 755 8938",
    "sg:postcode":"M1K 5G8",
    "sg:province":"ON",
    "sg:tags":[
        "rehabilitation"
    ],
    "wof:name":"Centre For Accident Rehab",
    "wof:placetype":"venue"
},
  "geometry": {"coordinates":[-79.2676773071,43.7321739197],"type":"Point"}
}