{
  "type": "Feature",
  "properties": {
    "addr:full":"811 Rue Des Ursulines Trois-Rivieres QC G9A 5B7",
    "addr:housenumber":"811",
    "addr:postcode":"g9a 5b7",
    "addr:street":"Rue Des Ursulines Trois-Rivieres",
    "iso:country":"CA",
    "sg:address":"811 Rue Des Ursulines",
    "sg:city":"Trois-Rivieres",
    "sg:classifiers":[
        {
            "category":"Organizations",
            "subcategory":"Religious Organization",
            "type":"Services"
        }
    ],
    "sg:phone":"+1 819 374 6010",
    "sg:postcode":"G9A 5B7",
    "sg:province":"QC",
    "sg:tags":[
        "church"
    ],
    "wof:name":"Anglican Church St-James",
    "wof:placetype":"venue"
},
  "geometry": {"coordinates":[-72.53680419920001,46.3436431885],"type":"Point"}
}