{
  "type": "Feature",
  "properties": {
    "addr:full":"601 Albert St Regina SK S4R 2P4",
    "addr:housenumber":"601",
    "addr:postcode":"s4r 2p4",
    "addr:street":"Albert St",
    "iso:country":"CA",
    "sg:address":"601 Albert St",
    "sg:city":"Regina",
    "sg:classifiers":[
        {
            "category":"Retail",
            "subcategory":"Auto Rental",
            "type":"Services"
        }
    ],
    "sg:phone":"+1 306 791 9139",
    "sg:postcode":"S4R 2P4",
    "sg:province":"SK",
    "sg:tags":[
        "renting",
        "automobile"
    ],
    "wof:name":"Hertz Rent A Car",
    "wof:placetype":"venue"
},
  "geometry": {"coordinates":[-104.617904663,50.4683685303],"type":"Point"}
}