{
  "type": "Feature",
  "properties": {
    "addr:full":"2492 98th St North Battleford SK S9A 4A2",
    "addr:housenumber":"2492",
    "addr:postcode":"s9a 4a2",
    "addr:street":"98Th St",
    "iso:country":"CA",
    "sg:address":"2492 98th St",
    "sg:city":"North Battleford",
    "sg:classifiers":[
        {
            "category":"Home & Garden",
            "subcategory":"Building Materials",
            "type":"Retail Goods"
        }
    ],
    "sg:phone":"+1 306 445 8867",
    "sg:postcode":"S9A 4A2",
    "sg:province":"SK",
    "sg:tags":[
        "windows",
        "plate",
        "window"
    ],
    "wof:name":"Alumi-Glass Svc Ltd",
    "wof:placetype":"venue"
},
  "geometry": {"coordinates":[-108.302825928,52.7949409485],"type":"Point"}
}