{
  "type": "Feature",
  "properties": {
    "iso:country":"CA",
    "sg:address":"2646 Islington Ave",
    "sg:city":"Etobicoke",
    "sg:classifiers":[
        {
            "category":"Restaurant",
            "type":"Food & Drink"
        }
    ],
    "sg:phone":"+1 416 745 4449",
    "sg:postcode":"M9V 2X5",
    "sg:province":"ON",
    "wof:name":"Brar Sweets & Restaurant",
    "wof:placetype":"venue"
},
  "geometry": {"coordinates":[-79.5659790039,43.7382545471],"type":"Point"}
}