{
  "type": "Feature",
  "properties": {
    "iso:country":"CA",
    "sg:address":"5 Rue Des Emeraudes",
    "sg:city":"Levis",
    "sg:classifiers":[
        {
            "category":"Wholesale",
            "subcategory":"Auto Parts",
            "type":"Manufacturing & Wholesale Goods"
        }
    ],
    "sg:phone":"+1 418 838 4442",
    "sg:postcode":"G6W 6Y7",
    "sg:province":"QC",
    "sg:tags":[
        "equipment",
        "truck"
    ],
    "wof:name":"Macpek Inc",
    "wof:placetype":"venue"
},
  "geometry": {"coordinates":[-71.1988143921,46.7714576721],"type":"Point"}
}