{
  "type": "Feature",
  "properties": {
    "addr:full":"13605 Rue Sherbrooke E Pointe-Aux-Trembles QC H1A 1C3",
    "addr:housenumber":"13605",
    "addr:postcode":"h1a 1c3",
    "addr:street":"Rue Sherbrooke E Pointe-Aux-Trembles",
    "iso:country":"CA",
    "sg:address":"13605 Rue Sherbrooke E",
    "sg:city":"Pointe-Aux-Trembles",
    "sg:classifiers":[
        {
            "category":"Health Services",
            "subcategory":"Health Practitioner",
            "type":"Services"
        }
    ],
    "sg:phone":"+1 514 498 4182",
    "sg:postcode":"H1A 1C3",
    "sg:province":"QC",
    "sg:tags":[
        "physiotherapist"
    ],
    "wof:name":"Clinique DE Physiotherapie",
    "wof:placetype":"venue"
},
  "geometry": {"coordinates":[-73.50748400000001,45.662922],"type":"Point"}
}