{
  "type": "Feature",
  "properties": {
    "iso:country":"CA",
    "sg:address":"13605 Rue Sherbrooke E",
    "sg:city":"Pointe-Aux-Trembles",
    "sg:classifiers":[
        {
            "category":"Health Services",
            "subcategory":"Health Practitioner",
            "type":"Services"
        }
    ],
    "sg:phone":"+1 514 498 4182",
    "sg:postcode":"H1A 1C3",
    "sg:province":"QC",
    "sg:tags":[
        "physiotherapist"
    ],
    "wof:name":"Clinique DE Physiotherapie",
    "wof:placetype":"venue"
},
  "geometry": {"coordinates":[-73.507484,45.662922],"type":"Point"}
}