{
  "type": "Feature",
  "properties": {
    "addr:full":"402 Garrison Sq SW Calgary AB T2T 6B4",
    "addr:housenumber":"402",
    "addr:postcode":"t2t 6b4",
    "addr:street":"Garrison Sq Sw",
    "iso:country":"CA",
    "sg:address":"402 Garrison Sq SW",
    "sg:city":"Calgary",
    "sg:classifiers":[
        {
            "category":"Professional",
            "subcategory":"Business Services",
            "type":"Services"
        }
    ],
    "sg:phone":"+1 403 261 3677",
    "sg:postcode":"T2T 6B4",
    "sg:province":"AB",
    "sg:tags":[
        "translator",
        "interpreter"
    ],
    "wof:name":"Thibaudeau Mac Leod Trnsltns",
    "wof:placetype":"venue"
},
  "geometry": {"coordinates":[-114.11354799999999,51.02124],"type":"Point"}
}