{
  "type": "Feature",
  "properties": {
    "addr:full":"290 Boul Harwood Vaudreuil-Dorion QC J7V 1Y5",
    "addr:housenumber":"290",
    "addr:postcode":"j7v 1y5",
    "addr:street":"Boul Harwood",
    "iso:country":"CA",
    "sg:address":"290 Boul Harwood",
    "sg:city":"Vaudreuil-Dorion",
    "sg:classifiers":[
        {
            "category":"Bars & Pubs",
            "type":"Food & Drink"
        }
    ],
    "sg:phone":"+1 450 424 8152",
    "sg:postcode":"J7V 1Y5",
    "sg:province":"QC",
    "sg:tags":[
        "lounge",
        "cafe",
        "cocktail"
    ],
    "wof:name":"Pit Stop",
    "wof:placetype":"venue"
},
  "geometry": {"coordinates":[-74.015846,45.38081],"type":"Point"}
}