{
  "type": "Feature",
  "properties": {
    "addr:full":"Burns Lake BC V0J 1E0",
    "addr:postcode":"bc v0j 1e0",
    "addr:street":"Burns Lake",
    "iso:country":"CA",
    "sg:city":"Burns Lake",
    "sg:classifiers":[
        {
            "category":"Shopping",
            "subcategory":"Florist",
            "type":"Retail Goods"
        }
    ],
    "sg:phone":"+1 250 692 2395",
    "sg:postcode":"V0J 1E0",
    "sg:province":"BC",
    "wof:name":"Burns Lake Flowers-All Occsn",
    "wof:placetype":"venue"
},
  "geometry": {"coordinates":[-125.75488281200001,54.2249908447],"type":"Point"}
}