{
  "type": "Feature",
  "properties": {
    "addr:full":"316 Saskatchewan Ave E Outlook SK S0L 2N0",
    "addr:housenumber":"316",
    "addr:postcode":"s0l 2n0",
    "addr:street":"Saskatchewan Ave E Outlook",
    "iso:country":"CA",
    "sg:address":"316 Saskatchewan Ave E",
    "sg:city":"Outlook",
    "sg:classifiers":[
        {
            "category":"Real Estate",
            "subcategory":"Real Estate Agent",
            "type":"Services"
        }
    ],
    "sg:phone":"+1 306 867 8687",
    "sg:postcode":"S0L 2N0",
    "sg:province":"SK",
    "sg:tags":[
        "cooperative"
    ],
    "wof:name":"Riverbend CO-OP Ltd",
    "wof:placetype":"venue"
},
  "geometry": {"coordinates":[-107.055832,51.488209],"type":"Point"}
}