{
  "type": "Feature",
  "properties": {
    "addr:full":"3219 31 Ave Vernon BC V1T 2H2",
    "addr:housenumber":"3219",
    "addr:postcode":"v1t 2h2",
    "addr:street":"31 Ave",
    "iso:country":"CA",
    "sg:address":"3219 31 Ave",
    "sg:city":"Vernon",
    "sg:classifiers":[
        {
            "category":"Shopping",
            "type":"Retail Goods"
        }
    ],
    "sg:phone":"+1 250 549 3222",
    "sg:postcode":"V1T 2H2",
    "sg:province":"BC",
    "sg:tags":[
        "pet",
        "shop"
    ],
    "wof:name":"A J's Pets & Things",
    "wof:placetype":"venue"
},
  "geometry": {"coordinates":[-119.27413199999999,50.264713],"type":"Point"}
}