{
  "type": "Feature",
  "properties": {
    "addr:full":"Yonge and Eglinton Toronto M4P1L5",
    "addr:postcode":"m4p1l5",
    "iso:country":"CA",
    "sg:address":"Yonge and Eglinton",
    "sg:city":"Toronto",
    "sg:classifiers":[
        {
            "category":"Professional",
            "subcategory":"Management & Consulting",
            "type":"Services"
        }
    ],
    "sg:postcode":"M4P1L5",
    "sg:tags":[
        "rethink",
        "seo",
        "consulting",
        "marketing",
        "online",
        "search",
        "engine",
        "optimization",
        "canada",
        "organic",
        "96robots"
    ],
    "sg:website":"http://96robots.com",
    "wof:name":"96Robots - SEO & Online Marketing",
    "wof:placetype":"venue"
},
  "geometry": {"coordinates":[-79.38926499999999,43.708686],"type":"Point"}
}