{
  "type": "Feature",
  "properties": {
    "addr:full":"1152 Kenaston St Gloucester ON K1B 3P5",
    "addr:housenumber":"1152",
    "addr:postcode":"k1b 3p5",
    "addr:street":"Kenaston St",
    "iso:country":"CA",
    "sg:address":"1152 Kenaston St",
    "sg:city":"Gloucester",
    "sg:classifiers":[
        {
            "category":"Professional",
            "subcategory":"Management & Consulting",
            "type":"Services"
        }
    ],
    "sg:phone":"+1 613 749 8000",
    "sg:postcode":"K1B 3P5",
    "sg:province":"ON",
    "sg:tags":[
        "garbage",
        "collection"
    ],
    "wof:name":"Waste Services Inc",
    "wof:placetype":"venue"
},
  "geometry": {"coordinates":[-75.62558,45.417503],"type":"Point"}
}