{
  "type": "Feature",
  "properties": {
    "addr:full":"Bonaventure QC G0C 1E0",
    "addr:postcode":"g0c 1e0",
    "iso:country":"CA",
    "sg:city":"Bonaventure",
    "sg:classifiers":[
        {
            "category":"Restaurant",
            "type":"Food & Drink"
        }
    ],
    "sg:phone":"+1 418 534 4276",
    "sg:postcode":"G0C 1E0",
    "sg:province":"QC",
    "wof:name":"Cafe Acadien Enr",
    "wof:placetype":"venue"
},
  "geometry": {"coordinates":[-65.489082,48.042709],"type":"Point"}
}