{
  "type": "Feature",
  "properties": {
    "addr:full":"Bow Island AB T0K 0G0",
    "addr:postcode":"t0k 0g0",
    "addr:street":"Bow",
    "iso:country":"CA",
    "sg:city":"Bow Island",
    "sg:classifiers":[
        {
            "category":"Home & Garden",
            "subcategory":"Hardware",
            "type":"Retail Goods"
        }
    ],
    "sg:phone":"+1 403 545 2020",
    "sg:postcode":"T0K 0G0",
    "sg:province":"AB",
    "wof:name":"Bow Island Hardware Ltd",
    "wof:placetype":"venue"
},
  "geometry": {"coordinates":[-111.381248474,49.8698005676],"type":"Point"}
}