{
  "type": "Feature",
  "properties": {
    "addr:full":"871 Rue Notre-Dame Saint-Alphonse-Rodriguez QC J0K 1W0",
    "addr:housenumber":"871",
    "addr:postcode":"j0k 1w0",
    "addr:street":"Rue Notre-Dame",
    "iso:country":"CA",
    "sg:address":"871 Rue Notre-Dame",
    "sg:city":"Saint-Alphonse-Rodriguez",
    "sg:classifiers":[
        {
            "category":"Manufacturing",
            "subcategory":"Leather Goods",
            "type":"Manufacturing & Wholesale Goods"
        }
    ],
    "sg:phone":"+1 450 883 8889",
    "sg:postcode":"J0K 1W0",
    "sg:province":"QC",
    "wof:name":"Cuirs Industriels",
    "wof:placetype":"venue"
},
  "geometry": {"coordinates":[-73.6912536621,46.1842803955],"type":"Point"}
}