{
  "type": "Feature",
  "properties": {
    "addr:full":"5500 Av DE Westbury Montreal QC H3W 2W8",
    "addr:housenumber":"5500",
    "addr:postcode":"h3w 2w8",
    "addr:street":"Av De Westbury",
    "iso:country":"CA",
    "sg:address":"5500 Av DE Westbury",
    "sg:city":"Montreal",
    "sg:classifiers":[
        {
            "category":"Sports & Exercise",
            "subcategory":"Gym",
            "type":"Entertainment"
        }
    ],
    "sg:phone":"+1 514 739 2632",
    "sg:postcode":"H3W 2W8",
    "sg:province":"QC",
    "sg:tags":[
        "club",
        "health",
        "studio",
        "gymnasium"
    ],
    "wof:name":"Get Fit Quick Inc",
    "wof:placetype":"venue"
},
  "geometry": {"coordinates":[-73.6342163086,45.4883842468],"type":"Point"}
}