{
  "type": "Feature",
  "properties": {
    "iso:country":"CA",
    "sg:address":"551 Duncan St",
    "sg:city":"Wallaceburg",
    "sg:classifiers":[
        {
            "category":"Building & Trades",
            "subcategory":"Construction",
            "type":"Services"
        }
    ],
    "sg:phone":"+1 519 627 6410",
    "sg:postcode":"N8A 4E9",
    "sg:province":"ON",
    "sg:tags":[
        "excavating",
        "contractor"
    ],
    "wof:name":"Rbm Contractors",
    "wof:placetype":"venue"
},
  "geometry": {"coordinates":[-82.38739776609999,42.5989875793],"type":"Point"}
}