{
  "type": "Feature",
  "properties": {
    "addr:full":"394 Melrose Ave North York ON M5M 1Z7",
    "addr:housenumber":"394",
    "addr:postcode":"m5m 1z7",
    "addr:street":"Melrose Ave",
    "iso:country":"CA",
    "sg:address":"394 Melrose Ave",
    "sg:city":"North York",
    "sg:classifiers":[
        {
            "category":"Retail",
            "subcategory":"Portrait Studio",
            "type":"Services"
        }
    ],
    "sg:phone":"+1 416 787 9585",
    "sg:postcode":"M5M 1Z7",
    "sg:province":"ON",
    "sg:tags":[
        "photographer"
    ],
    "wof:name":"Cavouk Portraits",
    "wof:placetype":"venue"
},
  "geometry": {"coordinates":[-79.42036437989999,43.7296485901],"type":"Point"}
}