{
  "type": "Feature",
  "properties": {
    "addr:full":"188 Renfrew St Pembroke ON K8A 6X1",
    "addr:housenumber":"188",
    "addr:postcode":"k8a 6x1",
    "addr:street":"Renfrew St",
    "iso:country":"CA",
    "sg:address":"188 Renfrew St",
    "sg:city":"Pembroke",
    "sg:classifiers":[
        {
            "category":"Organizations",
            "subcategory":"Religious Organization",
            "type":"Services"
        }
    ],
    "sg:phone":"+1 613 732 8513",
    "sg:postcode":"K8A 6X1",
    "sg:province":"ON",
    "sg:tags":[
        "church"
    ],
    "wof:name":"St Columbkille Cathedral",
    "wof:placetype":"venue"
},
  "geometry": {"coordinates":[-77.11655399999999,45.824085],"type":"Point"}
}