{
  "type": "Feature",
  "properties": {
    "iso:country":"CA",
    "sg:address":"388 Country Hills Dr NW",
    "sg:city":"Calgary",
    "sg:classifiers":[
        {
            "category":"Building & Trades",
            "subcategory":"Construction",
            "type":"Services"
        }
    ],
    "sg:phone":"+1 403 226 7501",
    "sg:postcode":"T3K 5A6",
    "sg:province":"AB",
    "sg:tags":[
        "home",
        "rental",
        "improvement"
    ],
    "wof:name":"Home Depot",
    "wof:placetype":"venue"
},
  "geometry": {"coordinates":[-114.06630699999999,51.147556],"type":"Point"}
}