{
  "type": "Feature",
  "properties": {
    "addr:full":"476 Rue Principale Saint-Ferdinand QC G0N 1N0",
    "addr:housenumber":"476",
    "addr:postcode":"g0n 1n0",
    "addr:street":"Rue Principale",
    "iso:country":"CA",
    "sg:address":"476 Rue Principale",
    "sg:city":"Saint-Ferdinand",
    "sg:classifiers":[
        {
            "category":"Home & Garden",
            "subcategory":"Hardware",
            "type":"Retail Goods"
        }
    ],
    "sg:phone":"+1 418 428 9830",
    "sg:postcode":"G0N 1N0",
    "sg:province":"QC",
    "wof:name":"Quincaillerie St-Ferdinand",
    "wof:placetype":"venue"
},
  "geometry": {"coordinates":[-71.57231899999999,46.109364],"type":"Point"}
}