{
  "type": "Feature",
  "properties": {
    "addr:full":"9360 Rue Charles-DE Latour Montreal QC H4N 1M2",
    "addr:housenumber":"9360",
    "addr:postcode":"h4n 1m2",
    "addr:street":"Rue Charles-De Latour",
    "iso:country":"CA",
    "sg:address":"9360 Rue Charles-DE Latour",
    "sg:city":"Montreal",
    "sg:classifiers":[
        {
            "category":"Wholesale",
            "subcategory":"Groceries",
            "type":"Manufacturing & Wholesale Goods"
        }
    ],
    "sg:phone":"+1 514 387 4568",
    "sg:postcode":"H4N 1M2",
    "sg:province":"QC",
    "sg:tags":[
        "food",
        "bulk"
    ],
    "wof:name":"Basse Freres Alimentation",
    "wof:placetype":"venue"
},
  "geometry": {"coordinates":[-73.65979799999999,45.531094],"type":"Point"}
}