{
  "type": "Feature",
  "properties": {
    "addr:full":"636 Point Pelee Dr Leamington ON N8H 3V4",
    "addr:housenumber":"636",
    "addr:postcode":"n8h 3v4",
    "addr:street":"Point Pelee Dr",
    "iso:country":"CA",
    "sg:address":"636 Point Pelee Dr",
    "sg:city":"Leamington",
    "sg:classifiers":[
        {
            "category":"Shopping",
            "subcategory":"Gifts & Souvenirs",
            "type":"Retail Goods"
        }
    ],
    "sg:phone":"+1 519 326 5193",
    "sg:postcode":"N8H 3V4",
    "sg:province":"ON",
    "sg:tags":[
        "shop"
    ],
    "wof:name":"Pelee Wings Nature Store",
    "wof:placetype":"venue"
},
  "geometry": {"coordinates":[-82.5500793457,41.9879302979],"type":"Point"}
}