{
  "type": "Feature",
  "properties": {
    "addr:full":"10086 Hurontario St Brampton ON L7A 1E5",
    "addr:housenumber":"10086",
    "addr:postcode":"l7a 1e5",
    "addr:street":"Hurontario St",
    "iso:country":"CA",
    "sg:address":"10086 Hurontario St",
    "sg:city":"Brampton",
    "sg:classifiers":[
        {
            "category":"Restaurant",
            "type":"Food & Drink"
        }
    ],
    "sg:phone":"+1 905 846 6199",
    "sg:postcode":"L7A 1E5",
    "sg:province":"ON",
    "sg:tags":[
        "grocer"
    ],
    "wof:name":"Asa Meats & West Indian Gro",
    "wof:placetype":"venue"
},
  "geometry": {"coordinates":[-79.78969600000001,43.707741],"type":"Point"}
}