{
  "type": "Feature",
  "properties": {
    "addr:full":"12 Rue Ernest-Veilleux Baie-Saint-Paul QC G3Z 1C7",
    "addr:housenumber":"12",
    "addr:postcode":"g3z 1c7",
    "addr:street":"Rue Ernest-Veilleux",
    "iso:country":"CA",
    "sg:address":"12 Rue Ernest-Veilleux",
    "sg:city":"Baie-Saint-Paul",
    "sg:classifiers":[
        {
            "category":"Building & Trades",
            "subcategory":"Construction",
            "type":"Services"
        }
    ],
    "sg:phone":"+1 418 435 3642",
    "sg:postcode":"G3Z 1C7",
    "sg:province":"QC",
    "sg:tags":[
        "repairing",
        "contractor",
        "remodeling",
        "general"
    ],
    "wof:name":"Construction Dufour Aluminium",
    "wof:placetype":"venue"
},
  "geometry": {"coordinates":[-70.513344,47.450642],"type":"Point"}
}