{
  "type": "Feature",
  "properties": {
    "addr:full":"136 Lake Adams Green SE Calgary AB T2J 3N4",
    "addr:housenumber":"136",
    "addr:postcode":"t2j 3n4",
    "addr:street":"Lake Adams Green Se",
    "iso:country":"CA",
    "sg:address":"136 Lake Adams Green SE",
    "sg:city":"Calgary",
    "sg:classifiers":[
        {
            "category":"Professional",
            "subcategory":"Management & Consulting",
            "type":"Services"
        }
    ],
    "sg:phone":"+1 403 225 2502",
    "sg:postcode":"T2J 3N4",
    "sg:province":"AB",
    "sg:tags":[
        "consultant",
        "business"
    ],
    "wof:name":"G F Murphy & Assoc",
    "wof:placetype":"venue"
},
  "geometry": {"coordinates":[-114.062798,50.943317],"type":"Point"}
}