{
  "type": "Feature",
  "properties": {
    "addr:full":"19 Rue Saint-Georges Riviere-Du-Loup QC G5R 1E5",
    "addr:housenumber":"19",
    "addr:postcode":"g5r 1e5",
    "addr:street":"Rue Saint-Georges Riviere-Du-Loup",
    "iso:country":"CA",
    "sg:address":"19 Rue Saint-Georges",
    "sg:city":"Riviere-Du-Loup",
    "sg:classifiers":[
        {
            "category":"Arts & Performance",
            "subcategory":"Theater",
            "type":"Entertainment"
        }
    ],
    "sg:phone":"+1 418 862 0736",
    "sg:postcode":"G5R 1E5",
    "sg:province":"QC",
    "sg:tags":[
        "talent",
        "agency",
        "casting"
    ],
    "wof:name":"Agence Guy Boucher Impresario",
    "wof:placetype":"venue"
},
  "geometry": {"coordinates":[-69.53633880620001,47.841758728],"type":"Point"}
}