{
  "type": "Feature",
  "properties": {
    "iso:country":"CA",
    "sg:city":"Englehart",
    "sg:classifiers":[
        {
            "category":"Social Services",
            "type":"Services"
        }
    ],
    "sg:phone":"+1 705 544 7565",
    "sg:postcode":"P0J 1H0",
    "sg:province":"ON",
    "sg:tags":[
        "organization",
        "welfare"
    ],
    "wof:name":"Temiskaming District Assmnt",
    "wof:placetype":"venue"
},
  "geometry": {"coordinates":[-79.87870025629999,47.8252639771],"type":"Point"}
}