{
  "type": "Feature",
  "properties": {
    "iso:country":"CA",
    "sg:city":"St Albert",
    "sg:classifiers":[
        {
            "category":"Personal",
            "subcategory":"Beauty Salon",
            "type":"Services"
        }
    ],
    "sg:phone":"+1 780 458 0107",
    "sg:postcode":"T8N 6K4",
    "sg:province":"AB",
    "wof:name":"Studio 107 Total Hair & Body",
    "wof:placetype":"venue"
},
  "geometry": {"coordinates":[-113.626480102,53.6516914368],"type":"Point"}
}