{
  "type": "Feature",
  "properties": {
    "addr:full":"PO Box 138 Port Au Port NL A0N 1T0",
    "addr:housenumber":"po",
    "addr:postcode":"a0n 1t0",
    "addr:street":"Box 138 Port Au Port",
    "iso:country":"CA",
    "sg:address":"PO Box 138",
    "sg:city":"Port Au Port",
    "sg:classifiers":[
        {
            "category":"Wholesale",
            "subcategory":"Auto Parts",
            "type":"Manufacturing & Wholesale Goods"
        }
    ],
    "sg:phone":"+1 709 644 2332",
    "sg:postcode":"A0N 1T0",
    "sg:province":"NL",
    "sg:tags":[
        "automobile",
        "rebuilt"
    ],
    "wof:name":"White's Enterprises Auto Slvge",
    "wof:placetype":"venue"
},
  "geometry": {"coordinates":[-58.710091,48.556732],"type":"Point"}
}