{
  "type": "Feature",
  "properties": {
    "addr:full":"63 Rosedale Ave St Catharines ON L2P 1Y6",
    "addr:housenumber":"63",
    "addr:postcode":"l2p 1y6",
    "addr:street":"Rosedale Ave",
    "iso:country":"CA",
    "sg:address":"63 Rosedale Ave",
    "sg:city":"St Catharines",
    "sg:classifiers":[
        {
            "category":"Shopping",
            "type":"Retail Goods"
        }
    ],
    "sg:phone":"+1 905 684 3060",
    "sg:postcode":"L2P 1Y6",
    "sg:province":"ON",
    "sg:tags":[
        "awning",
        "canopy"
    ],
    "wof:name":"B M Awnings",
    "wof:placetype":"venue"
},
  "geometry": {"coordinates":[-79.20500199999999,43.157627],"type":"Point"}
}