{
  "type": "Feature",
  "properties": {
    "iso:country":"CA",
    "sg:address":"63 Rosedale Ave",
    "sg:city":"St Catharines",
    "sg:classifiers":[
        {
            "category":"Shopping",
            "type":"Retail Goods"
        }
    ],
    "sg:phone":"+1 905 684 3060",
    "sg:postcode":"L2P 1Y6",
    "sg:province":"ON",
    "sg:tags":[
        "awning",
        "canopy"
    ],
    "wof:name":"B M Awnings",
    "wof:placetype":"venue"
},
  "geometry": {"coordinates":[-79.205002,43.157627],"type":"Point"}
}