{
  "type": "Feature",
  "properties": {
    "iso:country":"CA",
    "sg:city":"Saskatoon",
    "sg:classifiers":[
        {
            "category":"Real Estate",
            "subcategory":"Real Estate Operator",
            "type":"Services"
        }
    ],
    "sg:phone":"+1 306 384 6202",
    "sg:postcode":"S7L 6R9",
    "sg:province":"SK",
    "sg:tags":[
        "apartment"
    ],
    "wof:name":"Arbor Greens Apartments",
    "wof:placetype":"venue"
},
  "geometry": {"coordinates":[-106.743286133,52.1371841431],"type":"Point"}
}