{
  "type": "Feature",
  "properties": {
    "addr:full":"3648 Parkview St Penticton BC V2A 6H1",
    "addr:housenumber":"3648",
    "addr:postcode":"v2a 6h1",
    "addr:street":"Parkview St",
    "iso:country":"CA",
    "sg:address":"3648 Parkview St",
    "sg:city":"Penticton",
    "sg:classifiers":[
        {
            "category":"Travel",
            "subcategory":"Hotels & Motels",
            "type":"Entertainment"
        }
    ],
    "sg:phone":"+1 250 492 7114",
    "sg:postcode":"V2A 6H1",
    "sg:province":"BC",
    "sg:tags":[
        "resort"
    ],
    "wof:name":"Sunny Beach Motel",
    "wof:placetype":"venue"
},
  "geometry": {"coordinates":[-119.586486816,49.4549255371],"type":"Point"}
}