{
  "type": "Feature",
  "properties": {
    "addr:full":"1212 Boul Raymond Beauport QC G1B 2P3",
    "addr:housenumber":"1212",
    "addr:postcode":"g1b 2p3",
    "addr:street":"Boul Raymond",
    "iso:country":"CA",
    "sg:address":"1212 Boul Raymond",
    "sg:city":"Beauport",
    "sg:classifiers":[
        {
            "category":"Autos & Motor Vehicles",
            "subcategory":"Automobile Sales",
            "type":"Retail Goods"
        }
    ],
    "sg:phone":"+1 418 666 8277",
    "sg:postcode":"G1B 2P3",
    "sg:province":"QC",
    "sg:tags":[
        "car",
        "dealer"
    ],
    "wof:name":"Automobiles Del Sol",
    "wof:placetype":"venue"
},
  "geometry": {"coordinates":[-71.1934051514,46.912147522],"type":"Point"}
}