{
  "type": "Feature",
  "properties": {
    "addr:full":"326 Grey St Elbow SK S0H 1J0",
    "addr:housenumber":"326",
    "addr:postcode":"s0h 1j0",
    "addr:street":"Grey St",
    "iso:country":"CA",
    "sg:address":"326 Grey St",
    "sg:city":"Elbow",
    "sg:classifiers":[
        {
            "category":"Shopping",
            "subcategory":"Florist",
            "type":"Retail Goods"
        }
    ],
    "sg:phone":"+1 306 854 2233",
    "sg:postcode":"S0H 1J0",
    "sg:province":"SK",
    "wof:name":"Florist Shop By Larry Joel",
    "wof:placetype":"venue"
},
  "geometry": {"coordinates":[-106.594406128,51.1214065552],"type":"Point"}
}