{
  "type": "Feature",
  "properties": {
    "addr:full":"Calgary AB T2N 2A1",
    "addr:postcode":"t2n 2a1",
    "iso:country":"CA",
    "sg:city":"Calgary",
    "sg:classifiers":[
        {
            "category":"Health Services",
            "subcategory":"Health Practitioner",
            "type":"Services"
        }
    ],
    "sg:phone":"+1 403 289 0056",
    "sg:postcode":"T2N 2A1",
    "sg:province":"AB",
    "sg:tags":[
        "psychologist"
    ],
    "wof:name":"Mac Leod, M J",
    "wof:placetype":"venue"
},
  "geometry": {"coordinates":[-114.09496300000001,51.05685],"type":"Point"}
}