{
  "type": "Feature",
  "properties": {
    "addr:full":"653 William Ave Winnipeg MB R3A 0K1",
    "addr:housenumber":"653",
    "addr:postcode":"r3a 0k1",
    "addr:street":"William Ave",
    "iso:country":"CA",
    "sg:address":"653 William Ave",
    "sg:city":"Winnipeg",
    "sg:classifiers":[
        {
            "category":"Organizations",
            "subcategory":"Labor Organization",
            "type":"Services"
        }
    ],
    "sg:phone":"+1 204 783 4338",
    "sg:postcode":"R3A 0K1",
    "sg:province":"MB",
    "wof:name":"Health Sciences Ctr Nurses 10",
    "wof:placetype":"venue"
},
  "geometry": {"coordinates":[-97.155067,49.904148],"type":"Point"}
}