{
  "type": "Feature",
  "properties": {
    "addr:full":"2199 Rue Roussel Chicoutimi QC G7G 1W4",
    "addr:housenumber":"2199",
    "addr:postcode":"g7g 1w4",
    "addr:street":"Rue Roussel",
    "iso:country":"CA",
    "sg:address":"2199 Rue Roussel",
    "sg:city":"Chicoutimi",
    "sg:classifiers":[
        {
            "category":"Shopping",
            "subcategory":"Jewelry",
            "type":"Retail Goods"
        }
    ],
    "sg:phone":"+1 418 543 1959",
    "sg:postcode":"G7G 1W4",
    "sg:province":"QC",
    "sg:tags":[
        "jeweler"
    ],
    "wof:name":"Bijouterie Fortunat Gagnon",
    "wof:placetype":"venue"
},
  "geometry": {"coordinates":[-71.06563568120001,48.4371948242],"type":"Point"}
}