{
  "type": "Feature",
  "properties": {
    "addr:full":"269 Argyle St S Renfrew ON K7V 1T8",
    "addr:housenumber":"269",
    "addr:postcode":"k7v 1t8",
    "addr:street":"Argyle St S",
    "iso:country":"CA",
    "sg:address":"269 Argyle St S",
    "sg:city":"Renfrew",
    "sg:classifiers":[
        {
            "category":"Retail",
            "subcategory":"Animal Services",
            "type":"Services"
        }
    ],
    "sg:phone":"+1 613 432 2968",
    "sg:postcode":"K7V 1T8",
    "sg:province":"ON",
    "sg:tags":[
        "pet",
        "grooming",
        "washing"
    ],
    "wof:name":"Precious Pets",
    "wof:placetype":"venue"
},
  "geometry": {"coordinates":[-76.68341100000001,45.470467],"type":"Point"}
}