{
  "type": "Feature",
  "properties": {
    "addr:full":"1318 Rymal Rd E Hamilton ON L8W 3N1",
    "addr:housenumber":"1318",
    "addr:postcode":"l8w 3n1",
    "addr:street":"Rymal Rd E",
    "iso:country":"CA",
    "sg:address":"1318 Rymal Rd E",
    "sg:city":"Hamilton",
    "sg:classifiers":[
        {
            "category":"Manufacturing",
            "subcategory":"Metals",
            "type":"Manufacturing & Wholesale Goods"
        }
    ],
    "sg:phone":"+1 905 388 7111",
    "sg:postcode":"L8W 3N1",
    "sg:province":"ON",
    "sg:tags":[
        "steel"
    ],
    "wof:name":"Walters Inc",
    "wof:placetype":"venue"
},
  "geometry": {"coordinates":[-79.835067749,43.188129425],"type":"Point"}
}