{
  "type": "Feature",
  "properties": {
    "addr:full":"848 Boul Laure Sept-Iles QC G4R 1Y7",
    "addr:housenumber":"848",
    "addr:postcode":"g4r 1y7",
    "addr:street":"Boul Laure Sept-Iles",
    "iso:country":"CA",
    "sg:address":"848 Boul Laure",
    "sg:city":"Sept-Iles",
    "sg:classifiers":[
        {
            "category":"Real Estate",
            "subcategory":"Real Estate Agent",
            "type":"Services"
        }
    ],
    "sg:phone":"+1 418 968 3464",
    "sg:postcode":"G4R 1Y7",
    "sg:province":"QC",
    "wof:name":"Royal Le Page Cote-Nord",
    "wof:placetype":"venue"
},
  "geometry": {"coordinates":[-66.3895645142,50.2244491577],"type":"Point"}
}