{
  "type": "Feature",
  "properties": {
    "addr:full":"122 Scollard St Toronto ON M5R 1G2",
    "addr:housenumber":"122",
    "addr:postcode":"m5r 1g2",
    "addr:street":"Scollard St",
    "iso:country":"CA",
    "sg:address":"122 Scollard St",
    "sg:city":"Toronto",
    "sg:classifiers":[
        {
            "category":"Shopping",
            "type":"Retail Goods"
        }
    ],
    "sg:phone":"+1 416 324 5766",
    "sg:postcode":"M5R 1G2",
    "sg:province":"ON",
    "sg:tags":[
        "art",
        "gallery",
        "dealer"
    ],
    "wof:name":"Drabinsky Gallery",
    "wof:placetype":"venue"
},
  "geometry": {"coordinates":[-79.392601,43.671825],"type":"Point"}
}