{
  "type": "Feature",
  "properties": {
    "addr:full":"Saskatoon SK S7K 1M4",
    "addr:postcode":"s7k 1m4",
    "iso:country":"CA",
    "sg:city":"Saskatoon",
    "sg:classifiers":[
        {
            "category":"Arts & Performance",
            "subcategory":"Theater",
            "type":"Entertainment"
        }
    ],
    "sg:phone":"+1 306 664 2239",
    "sg:postcode":"S7K 1M4",
    "sg:province":"SK",
    "wof:name":"Twenty-Fifth Street Theatre",
    "wof:placetype":"venue"
},
  "geometry": {"coordinates":[-106.663375855,52.1262054443],"type":"Point"}
}