{
  "type": "Feature",
  "properties": {
    "addr:full":"Sherbrooke QC J1H 3X4",
    "addr:postcode":"j1h 3x4",
    "iso:country":"CA",
    "sg:city":"Sherbrooke",
    "sg:classifiers":[
        {
            "category":"Manufacturing",
            "subcategory":"Tools & Machinery",
            "type":"Manufacturing & Wholesale Goods"
        }
    ],
    "sg:phone":"+1 819 566 0556",
    "sg:postcode":"J1H 3X4",
    "sg:province":"QC",
    "sg:tags":[
        "seating",
        "company"
    ],
    "wof:name":"Tec Innovation Inc",
    "wof:placetype":"venue"
},
  "geometry": {"coordinates":[-71.89877300000001,45.395355],"type":"Point"}
}