{
  "type": "Feature",
  "properties": {
    "addr:full":"165 Colonnade Rd #2 Nepean ON K2E 7J4",
    "addr:housenumber":"165",
    "addr:postcode":"k2e 7j4",
    "addr:street":"Colonnade Rd # 2",
    "iso:country":"CA",
    "sg:address":"165 Colonnade Rd #2",
    "sg:city":"Nepean",
    "sg:classifiers":[
        {
            "category":"Professional",
            "subcategory":"Business Services",
            "type":"Services"
        }
    ],
    "sg:phone":"+1 613 226 8680",
    "sg:postcode":"K2E 7J4",
    "sg:province":"ON",
    "sg:tags":[
        "screen",
        "printing",
        "embroidery"
    ],
    "wof:name":"Daquin Sales",
    "wof:placetype":"venue"
},
  "geometry": {"coordinates":[-75.704926,45.34351],"type":"Point"}
}