{
  "type": "Feature",
  "properties": {
    "addr:full":"5385 Rue Des Jockeys Montreal QC H4P 2T8",
    "addr:housenumber":"5385",
    "addr:postcode":"h4p 2t8",
    "addr:street":"Rue Des Jockeys",
    "iso:country":"CA",
    "sg:address":"5385 Rue Des Jockeys",
    "sg:city":"Montreal",
    "sg:classifiers":[
        {
            "category":"Restaurant",
            "type":"Food & Drink"
        }
    ],
    "sg:phone":"+1 514 738 1616",
    "sg:postcode":"H4P 2T8",
    "sg:province":"QC",
    "wof:name":"Restaurant Baton Rouge",
    "wof:placetype":"venue"
},
  "geometry": {"coordinates":[-73.654922,45.493938],"type":"Point"}
}