{
  "type": "Feature",
  "properties": {
    "iso:country":"CA",
    "sg:address":"265 Edward St",
    "sg:city":"Aurora",
    "sg:classifiers":[
        {
            "category":"Autos & Motor Vehicles",
            "subcategory":"Auto Supplies",
            "type":"Retail Goods"
        }
    ],
    "sg:phone":"+1 905 751 0626",
    "sg:postcode":"L4G 3M7",
    "sg:province":"ON",
    "sg:tags":[
        "automobile",
        "stereo",
        "radio"
    ],
    "wof:name":"Noize Boyz",
    "wof:placetype":"venue"
},
  "geometry": {"coordinates":[-79.462097168,43.9870643616],"type":"Point"}
}