{
  "type": "Feature",
  "properties": {
    "iso:country":"CA",
    "sg:address":"550 Fennell Ave E",
    "sg:city":"Hamilton",
    "sg:classifiers":[
        {
            "category":"Shopping",
            "type":"Retail Goods"
        }
    ],
    "sg:phone":"+1 905 387 4040",
    "sg:postcode":"L8V 4S9",
    "sg:province":"ON",
    "sg:tags":[
        "cosmetic",
        "pharmacy"
    ],
    "wof:name":"Shoppers Drug Mart",
    "wof:placetype":"venue"
},
  "geometry": {"coordinates":[-79.85661315919999,43.2321548462],"type":"Point"}
}