{
  "type": "Feature",
  "properties": {
    "addr:full":"13022 Steven Ave Summerland BC V0H 1Z0",
    "addr:housenumber":"13022",
    "addr:postcode":"v0h 1z0",
    "addr:street":"Steven Ave",
    "iso:country":"CA",
    "sg:address":"13022 Steven Ave",
    "sg:city":"Summerland",
    "sg:classifiers":[
        {
            "category":"Home & Garden",
            "subcategory":"Garden Supply",
            "type":"Retail Goods"
        }
    ],
    "sg:phone":"+1 250 494 1070",
    "sg:postcode":"V0H 1Z0",
    "sg:province":"BC",
    "sg:tags":[
        "sprinkler"
    ],
    "wof:name":"Blue Waters Irrigation Ltd",
    "wof:placetype":"venue"
},
  "geometry": {"coordinates":[-119.674088,49.583546],"type":"Point"}
}