{
  "type": "Feature",
  "properties": {
    "addr:full":"251 Rue St-Louis Portneuf QC G0A 2Y0",
    "addr:housenumber":"251",
    "addr:postcode":"g0a 2y0",
    "addr:street":"Rue St-Louis",
    "iso:country":"CA",
    "sg:address":"251 Rue St-Louis",
    "sg:city":"Portneuf",
    "sg:classifiers":[
        {
            "category":"Retail",
            "subcategory":"Auto Repair",
            "type":"Services"
        }
    ],
    "sg:phone":"+1 418 286 6791",
    "sg:postcode":"G0A 2Y0",
    "sg:province":"QC",
    "sg:tags":[
        "repairing",
        "automobile"
    ],
    "wof:name":"Garage Gaston Martel Enr",
    "wof:placetype":"venue"
},
  "geometry": {"coordinates":[-71.885925,46.695641],"type":"Point"}
}