{
  "type": "Feature",
  "properties": {
    "iso:country":"CA",
    "sg:address":"5463 Rue Saint-Jacques",
    "sg:city":"Montreal",
    "sg:classifiers":[
        {
            "category":"Restaurant",
            "type":"Food & Drink"
        }
    ],
    "sg:phone":"+1 514 931 8814",
    "sg:postcode":"H4A 2E1",
    "sg:province":"QC",
    "sg:tags":[
        "caterer"
    ],
    "wof:name":"Catering By George Inc",
    "wof:placetype":"venue"
},
  "geometry": {"coordinates":[-73.604133606,45.4694213867],"type":"Point"}
}