{
  "type": "Feature",
  "properties": {
    "iso:country":"CA",
    "sg:address":"1989 Dundas St E",
    "sg:city":"Mississauga",
    "sg:classifiers":[
        {
            "category":"Retail",
            "subcategory":"Auto Repair",
            "type":"Services"
        }
    ],
    "sg:phone":"+1 905 629 1222",
    "sg:postcode":"L4X 1M1",
    "sg:province":"ON",
    "sg:tags":[
        "repairing",
        "automobile"
    ],
    "wof:name":"Master Mechanic",
    "wof:placetype":"venue"
},
  "geometry": {"coordinates":[-79.570412,43.622082],"type":"Point"}
}