{
  "type": "Feature",
  "properties": {
    "addr:full":"3901 Connaught Ave Windsor ON N9C 4H4",
    "addr:housenumber":"3901",
    "addr:postcode":"n9c 4h4",
    "addr:street":"Connaught Ave",
    "iso:country":"CA",
    "sg:address":"3901 Connaught Ave",
    "sg:city":"Windsor",
    "sg:classifiers":[
        {
            "category":"Recreation",
            "type":"Entertainment"
        }
    ],
    "sg:phone":"+1 519 257 5288",
    "sg:postcode":"N9C 4H4",
    "sg:province":"ON",
    "sg:tags":[
        "youth",
        "information",
        "activity",
        "center",
        "organization"
    ],
    "wof:name":"Windsor Regional Children's",
    "wof:placetype":"venue"
},
  "geometry": {"coordinates":[-83.063644,42.282806],"type":"Point"}
}