{
  "type": "Feature",
  "properties": {
    "addr:full":"3267 Parsons Rd NW Edmonton AB T6N 1B4",
    "addr:housenumber":"3267",
    "addr:postcode":"t6n 1b4",
    "addr:street":"Parsons Rd Nw",
    "iso:country":"CA",
    "sg:address":"3267 Parsons Rd NW",
    "sg:city":"Edmonton",
    "sg:classifiers":[
        {
            "category":"Wholesale",
            "subcategory":"Machinery & Supplies",
            "type":"Manufacturing & Wholesale Goods"
        }
    ],
    "sg:phone":"+1 780 490 5820",
    "sg:postcode":"T6N 1B4",
    "sg:province":"AB",
    "sg:tags":[
        "machine",
        "tool"
    ],
    "wof:name":"Steel Smith Supply Ltd",
    "wof:placetype":"venue"
},
  "geometry": {"coordinates":[-113.48575592,53.4652328491],"type":"Point"}
}