{
  "type": "Feature",
  "properties": {
    "addr:full":"Buckland QC G0R 1G0",
    "addr:postcode":"g0r 1g0",
    "addr:street":"Buckland",
    "iso:country":"CA",
    "sg:city":"Buckland",
    "sg:classifiers":[
        {
            "category":"Freight",
            "type":"Transportation"
        }
    ],
    "sg:phone":"+1 418 789 2384",
    "sg:postcode":"G0R 1G0",
    "sg:province":"QC",
    "sg:tags":[
        "trucking"
    ],
    "wof:name":"Transport M Belanger & Fils",
    "wof:placetype":"venue"
},
  "geometry": {"coordinates":[-70.545143,46.619625],"type":"Point"}
}