{
  "type": "Feature",
  "properties": {
    "addr:full":"35 Barrieau St Miramichi NB E1N 4T9",
    "addr:housenumber":"35",
    "addr:postcode":"e1n 4t9",
    "addr:street":"Barrieau St",
    "iso:country":"CA",
    "sg:address":"35 Barrieau St",
    "sg:city":"Miramichi",
    "sg:classifiers":[
        {
            "category":"Retail",
            "subcategory":"Auto Repair",
            "type":"Services"
        }
    ],
    "sg:phone":"+1 506 627 1482",
    "sg:postcode":"E1N 4T9",
    "sg:province":"NB",
    "sg:tags":[
        "repairing",
        "automobile",
        "painting"
    ],
    "wof:name":"Gerry's Auto Body",
    "wof:placetype":"venue"
},
  "geometry": {"coordinates":[-65.51445,46.989941],"type":"Point"}
}