{
  "type": "Feature",
  "properties": {
    "iso:country":"CA",
    "sg:address":"1737 Lasalle Blvd",
    "sg:city":"Sudbury",
    "sg:classifiers":[
        {
            "category":"Autos & Motor Vehicles",
            "subcategory":"Automobile Sales",
            "type":"Retail Goods"
        }
    ],
    "sg:phone":"+1 705 566 8111",
    "sg:postcode":"P3A 1Z8",
    "sg:province":"ON",
    "sg:tags":[
        "scooter",
        "parts",
        "motorcycle",
        "snowmobile"
    ],
    "wof:name":"Royal Distributing",
    "wof:placetype":"venue"
},
  "geometry": {"coordinates":[-80.9341888428,46.5219535828],"type":"Point"}
}