{
  "type": "Feature",
  "properties": {
    "addr:full":"Milton ON L9T 5A3",
    "addr:postcode":"l9t 5a3",
    "iso:country":"CA",
    "sg:city":"Milton",
    "sg:classifiers":[
        {
            "category":"Home & Garden",
            "subcategory":"Household Appliances",
            "type":"Retail Goods"
        }
    ],
    "sg:phone":"+1 905 875 0154",
    "sg:postcode":"L9T 5A3",
    "sg:province":"ON",
    "wof:name":"Appliance Depot",
    "wof:placetype":"venue"
},
  "geometry": {"coordinates":[-79.881134,43.503166],"type":"Point"}
}