{
  "type": "Feature",
  "properties": {
    "addr:full":"Calgary AB T2P 2W1",
    "addr:postcode":"t2p 2w1",
    "iso:country":"CA",
    "sg:city":"Calgary",
    "sg:classifiers":[
        {
            "category":"Organizations",
            "subcategory":"Professional Association",
            "type":"Services"
        }
    ],
    "sg:phone":"+1 403 264 8522",
    "sg:postcode":"T2P 2W1",
    "sg:province":"AB",
    "wof:name":"Isa-Calgary Section",
    "wof:placetype":"venue"
},
  "geometry": {"coordinates":[-114.067741394,51.0464859009],"type":"Point"}
}