{
  "type": "Feature",
  "properties": {
    "addr:full":"260 Dundas St E Toronto ON M5A 1Z6",
    "addr:housenumber":"260",
    "addr:postcode":"m5a 1z6",
    "addr:street":"Dundas St E",
    "iso:country":"CA",
    "sg:address":"260 Dundas St E",
    "sg:city":"Toronto",
    "sg:classifiers":[
        {
            "category":"Restaurant",
            "type":"Food & Drink"
        }
    ],
    "sg:phone":"+1 416 929 9116",
    "sg:postcode":"M5A 1Z6",
    "sg:province":"ON",
    "wof:name":"Piassa Ingera",
    "wof:placetype":"venue"
},
  "geometry": {"coordinates":[-79.37260437010001,43.6581916809],"type":"Point"}
}