{
  "type": "Feature",
  "properties": {
    "addr:full":"Toronto ON M5R 3P8",
    "addr:postcode":"m5r 3p8",
    "iso:country":"CA",
    "sg:city":"Toronto",
    "sg:classifiers":[
        {
            "category":"Real Estate",
            "subcategory":"Architect",
            "type":"Services"
        }
    ],
    "sg:phone":"+1 416 922 2040",
    "sg:postcode":"M5R 3P8",
    "sg:province":"ON",
    "wof:name":"Donald J Caunter Arch",
    "wof:placetype":"venue"
},
  "geometry": {"coordinates":[-79.398499,43.675373],"type":"Point"}
}