{
  "type": "Feature",
  "properties": {
    "addr:full":"Comber ON N0P 1J0",
    "addr:postcode":"n0p 1j0",
    "iso:country":"CA",
    "sg:city":"Comber",
    "sg:classifiers":[
        {
            "category":"Shopping",
            "subcategory":"Pharmacy",
            "type":"Retail Goods"
        }
    ],
    "sg:phone":"+1 519 687 3933",
    "sg:postcode":"N0P 1J0",
    "sg:province":"ON",
    "wof:name":"Comber Drug Store",
    "wof:placetype":"venue"
},
  "geometry": {"coordinates":[-82.55239899999999,42.234695],"type":"Point"}
}