{
  "type": "Feature",
  "properties": {
    "iso:country":"CA",
    "sg:address":"60 Colchester Sq",
    "sg:city":"Kanata",
    "sg:classifiers":[
        {
            "category":"Health Services",
            "subcategory":"Doctor",
            "type":"Services"
        }
    ],
    "sg:phone":"+1 613 599 5922",
    "sg:postcode":"K2K 2Z9",
    "sg:province":"ON",
    "sg:tags":[
        "dentist"
    ],
    "wof:name":"Village Green Dental Care",
    "wof:placetype":"venue"
},
  "geometry": {"coordinates":[-75.889709,45.321144],"type":"Point"}
}