{
  "type": "Feature",
  "properties": {
    "addr:full":"60 Colchester Sq Kanata ON K2K 2Z9",
    "addr:housenumber":"60",
    "addr:postcode":"k2k 2z9",
    "addr:street":"Colchester Sq",
    "iso:country":"CA",
    "sg:address":"60 Colchester Sq",
    "sg:city":"Kanata",
    "sg:classifiers":[
        {
            "category":"Health Services",
            "subcategory":"Doctor",
            "type":"Services"
        }
    ],
    "sg:phone":"+1 613 599 5922",
    "sg:postcode":"K2K 2Z9",
    "sg:province":"ON",
    "sg:tags":[
        "dentist"
    ],
    "wof:name":"Village Green Dental Care",
    "wof:placetype":"venue"
},
  "geometry": {"coordinates":[-75.889709,45.321144],"type":"Point"}
}