{
  "type": "Feature",
  "properties": {
    "iso:country":"CA",
    "sg:city":"Peterborough",
    "sg:classifiers":[
        {
            "category":"Manufacturing",
            "subcategory":"Paper Products",
            "type":"Manufacturing & Wholesale Goods"
        }
    ],
    "sg:phone":"+1 705 742 5888",
    "sg:postcode":"K9J 6X6",
    "sg:province":"ON",
    "sg:tags":[
        "corrugated",
        "box",
        "fiber",
        "solid",
        "material",
        "packaging"
    ],
    "wof:name":"Coyle Corrugated Containers",
    "wof:placetype":"venue"
},
  "geometry": {"coordinates":[-78.351379,44.262356],"type":"Point"}
}