{
  "type": "Feature",
  "properties": {
    "addr:full":"1925 Portage Ave Winnipeg MB R3J 0J5",
    "addr:housenumber":"1925",
    "addr:postcode":"r3j 0j5",
    "addr:street":"Portage Ave",
    "iso:country":"CA",
    "sg:address":"1925 Portage Ave",
    "sg:city":"Winnipeg",
    "sg:classifiers":[
        {
            "category":"Autos & Motor Vehicles",
            "subcategory":"Fuel & Gas Station",
            "type":"Retail Goods"
        }
    ],
    "sg:phone":"+1 204 888 8234",
    "sg:postcode":"R3J 0J5",
    "sg:province":"MB",
    "sg:tags":[
        "oil"
    ],
    "wof:name":"Red River CO-Operative Ltd",
    "wof:placetype":"venue"
},
  "geometry": {"coordinates":[-97.22265625,49.8787155151],"type":"Point"}
}