{
  "type": "Feature",
  "properties": {
    "addr:full":"5343 Route 11 Brantville NB E9H 1M7",
    "addr:housenumber":"5343",
    "addr:postcode":"e9h 1m7",
    "addr:street":"Route 11",
    "iso:country":"CA",
    "sg:address":"5343 Route 11",
    "sg:city":"Brantville",
    "sg:classifiers":[
        {
            "category":"Autos & Motor Vehicles",
            "subcategory":"Fuel & Gas Station",
            "type":"Retail Goods"
        }
    ],
    "sg:phone":"+1 506 395 9006",
    "sg:postcode":"E9H 1M7",
    "sg:province":"NB",
    "sg:tags":[
        "oil"
    ],
    "wof:name":"Hache Petro-Canada",
    "wof:placetype":"venue"
},
  "geometry": {"coordinates":[-65.016762,47.308434],"type":"Point"}
}