{
  "type": "Feature",
  "properties": {
    "addr:full":"30127 Brigden Rd Wallaceburg ON N8A 4L2",
    "addr:housenumber":"30127",
    "addr:postcode":"n8a 4l2",
    "addr:street":"Brigden Rd",
    "iso:country":"CA",
    "sg:address":"30127 Brigden Rd",
    "sg:city":"Wallaceburg",
    "sg:classifiers":[
        {
            "category":"Organizations",
            "subcategory":"Religious Organization",
            "type":"Services"
        }
    ],
    "sg:phone":"+1 519 627 4965",
    "sg:postcode":"N8A 4L2",
    "sg:province":"ON",
    "sg:tags":[
        "church"
    ],
    "wof:name":"Charlemont Free Meth Church",
    "wof:placetype":"venue"
},
  "geometry": {"coordinates":[-82.39503479,42.5929756165],"type":"Point"}
}