{
  "type": "Feature",
  "properties": {
    "iso:country":"CA",
    "sg:address":"55 Oakdale Ave",
    "sg:city":"St Catharines",
    "sg:classifiers":[
        {
            "category":"Wholesale",
            "subcategory":"Scrap",
            "type":"Manufacturing & Wholesale Goods"
        }
    ],
    "sg:phone":"+1 905 688 8896",
    "sg:postcode":"L2P 2L3",
    "sg:province":"ON",
    "sg:tags":[
        "recycling",
        "metal",
        "center",
        "iron"
    ],
    "wof:name":"Hydro Metal Recycling",
    "wof:placetype":"venue"
},
  "geometry": {"coordinates":[-79.21825408940001,43.1441383362],"type":"Point"}
}