{
  "type": "Feature",
  "properties": {
    "addr:full":"500 364 Rte Morin-Heights QC J0R 1H0",
    "addr:housenumber":"364",
    "addr:postcode":"j0r 1h0",
    "addr:street":"Rte Morin-Heights",
    "iso:country":"CA",
    "sg:address":"500 364 Rte",
    "sg:city":"Morin-Heights",
    "sg:classifiers":[
        {
            "category":"Travel",
            "subcategory":"Hotels & Motels",
            "type":"Entertainment"
        }
    ],
    "sg:phone":"+1 450 226 1796",
    "sg:postcode":"J0R 1H0",
    "sg:province":"QC",
    "sg:tags":[
        "inn",
        "hall",
        "auditorium"
    ],
    "wof:name":"Auberge Morin-Heights",
    "wof:placetype":"venue"
},
  "geometry": {"coordinates":[-74.23455,45.905979],"type":"Point"}
}