{
  "type": "Feature",
  "properties": {
    "addr:full":"254 Main St W Hawkesbury ON K6A 2H6",
    "addr:housenumber":"254",
    "addr:postcode":"k6a 2h6",
    "addr:street":"Main St W",
    "iso:country":"CA",
    "sg:address":"254 Main St W",
    "sg:city":"Hawkesbury",
    "sg:classifiers":[
        {
            "category":"Restaurant",
            "type":"Food & Drink"
        }
    ],
    "sg:phone":"+1 613 632 4473",
    "sg:postcode":"K6A 2H6",
    "sg:province":"ON",
    "wof:name":"Miss Hawkesbury",
    "wof:placetype":"venue"
},
  "geometry": {"coordinates":[-74.61782073969999,45.6100502014],"type":"Point"}
}