{
  "type": "Feature",
  "properties": {
    "addr:full":"20043 40A Ave Langley BC V3A 2Y6",
    "addr:housenumber":"20043",
    "addr:postcode":"v3a 2y6",
    "addr:street":"40A Ave",
    "iso:country":"CA",
    "sg:address":"20043 40A Ave",
    "sg:city":"Langley",
    "sg:classifiers":[
        {
            "category":"Cinema",
            "subcategory":"Movie Rental",
            "type":"Entertainment"
        }
    ],
    "sg:phone":"+1 604 530 3696",
    "sg:postcode":"V3A 2Y6",
    "sg:province":"BC",
    "sg:tags":[
        "leasing",
        "video",
        "disc",
        "tape"
    ],
    "wof:name":"Video World",
    "wof:placetype":"venue"
},
  "geometry": {"coordinates":[-122.65657,49.104122],"type":"Point"}
}