{
  "type": "Feature",
  "properties": {
    "addr:full":"Winnipeg MB R2R 2E2",
    "addr:postcode":"r2r 2e2",
    "iso:country":"CA",
    "sg:city":"Winnipeg",
    "sg:classifiers":[
        {
            "category":"Personal",
            "subcategory":"Beauty Salon",
            "type":"Services"
        }
    ],
    "sg:phone":"+1 204 694 5462",
    "sg:postcode":"R2R 2E2",
    "sg:province":"MB",
    "wof:name":"Magicuts",
    "wof:placetype":"venue"
},
  "geometry": {"coordinates":[-97.195457,49.94471],"type":"Point"}
}