{
  "type": "Feature",
  "properties": {
    "addr:full":"Scarborough ON M1X 1M1",
    "addr:postcode":"m1x 1m1",
    "iso:country":"CA",
    "sg:city":"Scarborough",
    "sg:classifiers":[
        {
            "category":"Wholesale",
            "subcategory":"Durable Goods & Equipment",
            "type":"Manufacturing & Wholesale Goods"
        }
    ],
    "sg:phone":"+1 416 299 0910",
    "sg:postcode":"M1X 1M1",
    "sg:province":"ON",
    "sg:tags":[
        "laboratory",
        "scientific",
        "apparatus",
        "supply"
    ],
    "wof:name":"Ajax Scientific Ltd",
    "wof:placetype":"venue"
},
  "geometry": {"coordinates":[-79.247467,43.828011],"type":"Point"}
}