{
  "type": "Feature",
  "properties": {
    "iso:country":"CA",
    "sg:address":"85 Rue Notre-Dame",
    "sg:city":"Notre-Dame-Des-Monts",
    "sg:classifiers":[
        {
            "category":"Education",
            "subcategory":"School",
            "type":"Public Place"
        }
    ],
    "sg:phone":"+1 418 439 2171",
    "sg:postcode":"G0T 1L0",
    "sg:province":"QC",
    "wof:name":"Ecole Fernand-Saindon",
    "wof:placetype":"venue"
},
  "geometry": {"coordinates":[-70.39032745359999,47.6647186279],"type":"Point"}
}