{
  "type": "Feature",
  "properties": {
    "iso:country":"CA",
    "sg:city":"High Prairie",
    "sg:classifiers":[
        {
            "category":"Shopping",
            "type":"Retail Goods"
        }
    ],
    "sg:phone":"+1 780 523 3424",
    "sg:postcode":"T0G 1E0",
    "sg:province":"AB",
    "sg:tags":[
        "ice"
    ],
    "wof:name":"D & L Party Ice",
    "wof:placetype":"venue"
},
  "geometry": {"coordinates":[-116.48042297400001,55.4328842163],"type":"Point"}
}