{
  "type": "Feature",
  "properties": {
    "addr:full":"46 St-Francois-Xavier E Boul Grande-Vallee QC G0E 1K0",
    "addr:housenumber":"46",
    "addr:postcode":"g0e 1k0",
    "addr:street":"St-Francois-Xavier E Boul Grande-Vallee",
    "iso:country":"CA",
    "sg:address":"46 St-Francois-Xavier E Boul",
    "sg:city":"Grande-Vallee",
    "sg:classifiers":[
        {
            "category":"Shopping",
            "subcategory":"Bicycles & Sporting Goods",
            "type":"Retail Goods"
        }
    ],
    "sg:phone":"+1 418 393 2766",
    "sg:postcode":"G0E 1K0",
    "sg:province":"QC",
    "wof:name":"Boulet Sports DE Grande Vallee",
    "wof:placetype":"venue"
},
  "geometry": {"coordinates":[-65.11531066889999,49.226852417],"type":"Point"}
}