{
  "type": "Feature",
  "properties": {
    "addr:full":"96 James St Parry Sound ON P2A 1T9",
    "addr:housenumber":"96",
    "addr:postcode":"p2a 1t9",
    "addr:street":"James St",
    "iso:country":"CA",
    "sg:address":"96 James St",
    "sg:city":"Parry Sound",
    "sg:classifiers":[
        {
            "category":"Shopping",
            "type":"Retail Goods"
        }
    ],
    "sg:phone":"+1 705 746 5495",
    "sg:postcode":"P2A 1T9",
    "sg:province":"ON",
    "sg:tags":[
        "ice"
    ],
    "wof:name":"Taylor's Ice & Bait",
    "wof:placetype":"venue"
},
  "geometry": {"coordinates":[-80.03385900000001,45.347641],"type":"Point"}
}