{
  "type": "Feature",
  "properties": {
    "addr:full":"PO Box 768 Onoway AB T0E 1V0",
    "addr:housenumber":"po",
    "addr:postcode":"t0e 1v0",
    "addr:street":"Box 768",
    "iso:country":"CA",
    "sg:address":"PO Box 768",
    "sg:city":"Onoway",
    "sg:classifiers":[
        {
            "category":"Freight",
            "type":"Transportation"
        }
    ],
    "sg:phone":"+1 780 967 3476",
    "sg:postcode":"T0E 1V0",
    "sg:province":"AB",
    "sg:tags":[
        "trucking"
    ],
    "wof:name":"4 Bar K Ranch",
    "wof:placetype":"venue"
},
  "geometry": {"coordinates":[-114.19152800000001,53.703018],"type":"Point"}
}