{
  "type": "Feature",
  "properties": {
    "addr:full":"2272 Rue Leon-Harmel Quebec QC G1N 4L2",
    "addr:housenumber":"2272",
    "addr:postcode":"g1n 4l2",
    "addr:street":"Rue Leon-Harmel",
    "iso:country":"CA",
    "sg:address":"2272 Rue Leon-Harmel",
    "sg:city":"Quebec",
    "sg:phone":"+1 418 682 2500",
    "sg:postcode":"G1N 4L2",
    "sg:province":"QC",
    "sg:tags":[
        "lubricant",
        "oil",
        "burner"
    ],
    "wof:name":"Thermoshell Inc",
    "wof:placetype":"venue"
},
  "geometry": {"coordinates":[-71.284569,46.799362],"type":"Point"}
}