{
  "type": "Feature",
  "properties": {
    "addr:full":"499 Dewe Ave Thunder Bay ON P7A 2H1",
    "addr:housenumber":"499",
    "addr:postcode":"p7a 2h1",
    "addr:street":"Dewe Ave",
    "iso:country":"CA",
    "sg:address":"499 Dewe Ave",
    "sg:city":"Thunder Bay",
    "sg:classifiers":[
        {
            "category":"Organizations",
            "subcategory":"Religious Organization",
            "type":"Services"
        }
    ],
    "sg:phone":"+1 807 683 6621",
    "sg:postcode":"P7A 2H1",
    "sg:province":"ON",
    "sg:tags":[
        "church"
    ],
    "wof:name":"Epiphany Lutheran Church",
    "wof:placetype":"venue"
},
  "geometry": {"coordinates":[-89.19091,48.469204],"type":"Point"}
}