{
  "type": "Feature",
  "properties": {
    "iso:country":"CA",
    "sg:address":"747 12th St W",
    "sg:city":"Prince Albert",
    "sg:classifiers":[
        {
            "category":"Shopping",
            "type":"Retail Goods"
        }
    ],
    "sg:phone":"+1 306 764 0869",
    "sg:postcode":"S6V 3C3",
    "sg:province":"SK",
    "sg:tags":[
        "dance",
        "music",
        "wedding",
        "recorded",
        "supply"
    ],
    "wof:name":"Cloud Nine Music Svc",
    "wof:placetype":"venue"
},
  "geometry": {"coordinates":[-105.77397918699999,53.2016716003],"type":"Point"}
}