{
  "type": "Feature",
  "properties": {
    "iso:country":"CA",
    "sg:address":"80 Elgin Ave",
    "sg:city":"Simcoe",
    "sg:classifiers":[
        {
            "category":"Education",
            "subcategory":"School",
            "type":"Public Place"
        }
    ],
    "sg:phone":"+1 519 426 4628",
    "sg:postcode":"N3Y 4A8",
    "sg:province":"ON",
    "wof:name":"Elgin Avenue Public School",
    "wof:placetype":"venue"
},
  "geometry": {"coordinates":[-80.313736,42.837181],"type":"Point"}
}