{
  "type": "Feature",
  "properties": {
    "addr:full":"5030 Canyon-Lister Rd Canyon BC V0B 1C1",
    "addr:housenumber":"5030",
    "addr:postcode":"bc v0b 1c1",
    "addr:street":"Canyon-Lister Rd",
    "iso:country":"CA",
    "sg:address":"5030 Canyon-Lister Rd",
    "sg:city":"Canyon",
    "sg:classifiers":[
        {
            "category":"Building & Trades",
            "subcategory":"Plumbing",
            "type":"Services"
        }
    ],
    "sg:phone":"+1 250 428 9626",
    "sg:postcode":"V0B 1C1",
    "sg:province":"BC",
    "sg:tags":[
        "heating",
        "contractor"
    ],
    "wof:name":"Custom Heating & Air Cond",
    "wof:placetype":"venue"
},
  "geometry": {"coordinates":[-116.44761657700001,49.054397583],"type":"Point"}
}