{
  "type": "Feature",
  "properties": {
    "addr:full":"3245 Harvester Rd #7 Burlington ON L7N 3T7",
    "addr:housenumber":"3245",
    "addr:postcode":"l7n 3t7",
    "addr:street":"Harvester Rd # 7",
    "iso:country":"CA",
    "sg:address":"3245 Harvester Rd #7",
    "sg:city":"Burlington",
    "sg:classifiers":[
        {
            "category":"Health Services",
            "subcategory":"Clinic",
            "type":"Services"
        }
    ],
    "sg:phone":"+1 905 631 6700",
    "sg:postcode":"L7N 3T7",
    "sg:province":"ON",
    "sg:tags":[
        "home"
    ],
    "wof:name":"Wheelchairs Etc & Home Health",
    "wof:placetype":"venue"
},
  "geometry": {"coordinates":[-79.79437299999999,43.355976],"type":"Point"}
}