{
  "type": "Feature",
  "properties": {
    "addr:full":"1865 N Talbot St Windsor ON N9A 6J3",
    "addr:housenumber":"1865",
    "addr:postcode":"n9a 6j3",
    "addr:street":"N Talbot St",
    "iso:country":"CA",
    "sg:address":"1865 N Talbot St",
    "sg:city":"Windsor",
    "sg:classifiers":[
        {
            "category":"Wholesale",
            "subcategory":"Machinery & Supplies",
            "type":"Manufacturing & Wholesale Goods"
        }
    ],
    "sg:phone":"+1 519 737 7711",
    "sg:postcode":"N9A 6J3",
    "sg:province":"ON",
    "sg:tags":[
        "tool"
    ],
    "wof:name":"Keyline Cutting Tools Inc",
    "wof:placetype":"venue"
},
  "geometry": {"coordinates":[-83.033913,42.317822],"type":"Point"}
}