{
  "type": "Feature",
  "properties": {
    "addr:full":"9508 120 St Surrey BC V3V 4C1",
    "addr:housenumber":"9508",
    "addr:postcode":"v3v 4c1",
    "addr:street":"120 St",
    "iso:country":"CA",
    "sg:address":"9508 120 St",
    "sg:city":"Surrey",
    "sg:classifiers":[
        {
            "category":"Shopping",
            "subcategory":"Optical Goods",
            "type":"Retail Goods"
        }
    ],
    "sg:phone":"+1 604 584 7577",
    "sg:postcode":"V3V 4C1",
    "sg:province":"BC",
    "sg:tags":[
        "optician"
    ],
    "wof:name":"Your Eyes Only Optical Ltd",
    "wof:placetype":"venue"
},
  "geometry": {"coordinates":[-122.890090942,49.1754570007],"type":"Point"}
}