{
  "type": "Feature",
  "properties": {
    "addr:full":"39 Ontario St N Grand Bend ON N0M 1T0",
    "addr:housenumber":"39",
    "addr:postcode":"n0m 1t0",
    "addr:street":"Ontario St N",
    "iso:country":"CA",
    "sg:address":"39 Ontario St N",
    "sg:city":"Grand Bend",
    "sg:classifiers":[
        {
            "category":"Food & Beverages",
            "subcategory":"Bakery",
            "type":"Retail Goods"
        }
    ],
    "sg:phone":"+1 519 238 1488",
    "sg:postcode":"N0M 1T0",
    "sg:province":"ON",
    "sg:tags":[
        "doughnut"
    ],
    "wof:name":"Tim Hortons",
    "wof:placetype":"venue"
},
  "geometry": {"coordinates":[-81.75502,43.314533],"type":"Point"}
}