{
  "type": "Feature",
  "properties": {
    "addr:full":"1155 101st St North Battleford SK S9A 0Z5",
    "addr:housenumber":"1155",
    "addr:postcode":"s9a 0z5",
    "addr:street":"101St St",
    "iso:country":"CA",
    "sg:address":"1155 101st St",
    "sg:city":"North Battleford",
    "sg:classifiers":[
        {
            "category":"Food & Beverages",
            "subcategory":"Bakery",
            "type":"Retail Goods"
        }
    ],
    "sg:phone":"+1 306 445 8711",
    "sg:postcode":"S9A 0Z5",
    "sg:province":"SK",
    "sg:tags":[
        "baker"
    ],
    "wof:name":"Danish Home Bakery",
    "wof:placetype":"venue"
},
  "geometry": {"coordinates":[-108.297783,52.77425],"type":"Point"}
}