{
  "type": "Feature",
  "properties": {
    "iso:country":"CA",
    "sg:address":"Hwy 9",
    "sg:city":"Carlyle",
    "sg:classifiers":[
        {
            "category":"Organizations",
            "subcategory":"Professional Association",
            "type":"Services"
        }
    ],
    "sg:phone":"+1 306 453 6722",
    "sg:postcode":"S0C 0R0",
    "sg:province":"SK",
    "sg:tags":[
        "club"
    ],
    "wof:name":"Carlyle Curling Club",
    "wof:placetype":"venue"
},
  "geometry": {"coordinates":[-102.257385254,49.6343002319],"type":"Point"}
}