{
  "type": "Feature",
  "properties": {
    "addr:full":"85 Kingsley Rd Christina Lake BC V0H 1E2",
    "addr:housenumber":"85",
    "addr:postcode":"v0h 1e2",
    "addr:street":"Kingsley Rd",
    "iso:country":"CA",
    "sg:address":"85 Kingsley Rd",
    "sg:city":"Christina Lake",
    "sg:classifiers":[
        {
            "category":"Travel",
            "subcategory":"Hotels & Motels",
            "type":"Entertainment"
        }
    ],
    "sg:phone":"+1 250 447 6626",
    "sg:postcode":"V0H 1E2",
    "sg:province":"BC",
    "sg:tags":[
        "resort"
    ],
    "wof:name":"Kingsley's Resort",
    "wof:placetype":"venue"
},
  "geometry": {"coordinates":[-118.22026099999999,49.059025],"type":"Point"}
}