{
  "type": "Feature",
  "properties": {
    "addr:full":"255 Rue Jean-Talon E Montreal QC H2R 1S9",
    "addr:housenumber":"255",
    "addr:postcode":"h2r 1s9",
    "addr:street":"Rue Jean-Talon E",
    "iso:country":"CA",
    "sg:address":"255 Rue Jean-Talon E",
    "sg:city":"Montreal",
    "sg:classifiers":[
        {
            "category":"Cinema",
            "subcategory":"Movie Rental",
            "type":"Entertainment"
        }
    ],
    "sg:phone":"+1 514 273 2184",
    "sg:postcode":"H2R 1S9",
    "sg:province":"QC",
    "sg:tags":[
        "leasing",
        "video",
        "disc",
        "tape"
    ],
    "wof:name":"Video Mansour",
    "wof:placetype":"venue"
},
  "geometry": {"coordinates":[-73.6159286499,45.5369567871],"type":"Point"}
}