{
  "type": "Feature",
  "properties": {
    "addr:full":"5225 Rue Saint-Joseph Trois-Rivieres-Ouest QC G8Z 4M5",
    "addr:housenumber":"5225",
    "addr:postcode":"g8z 4m5",
    "addr:street":"Rue Saint-Joseph Trois-Rivieres-Ouest",
    "iso:country":"CA",
    "sg:address":"5225 Rue Saint-Joseph",
    "sg:city":"Trois-Rivieres-Ouest",
    "sg:classifiers":[
        {
            "category":"Freight",
            "type":"Transportation"
        }
    ],
    "sg:phone":"+1 819 691 6996",
    "sg:postcode":"G8Z 4M5",
    "sg:province":"QC",
    "sg:tags":[
        "warehouse",
        "storage"
    ],
    "wof:name":"Distribution Transit-Mauricie",
    "wof:placetype":"venue"
},
  "geometry": {"coordinates":[-72.58440400000001,46.334606],"type":"Point"}
}