{
  "type": "Feature",
  "properties": {
    "iso:country":"CA",
    "sg:address":"922 Simcoe St N",
    "sg:city":"Oshawa",
    "sg:classifiers":[
        {
            "category":"Insurance",
            "subcategory":"Insurance Agent",
            "type":"Services"
        }
    ],
    "sg:phone":"+1 905 571 3380",
    "sg:postcode":"L1G 4W2",
    "sg:province":"ON",
    "sg:tags":[
        "consultant",
        "planning",
        "financial"
    ],
    "wof:name":"Primerica",
    "wof:placetype":"venue"
},
  "geometry": {"coordinates":[-78.8742980957,43.9220123291],"type":"Point"}
}