{
  "type": "Feature",
  "properties": {
    "iso:country":"CA",
    "sg:address":"100 Main St",
    "sg:city":"Englefeld",
    "sg:classifiers":[
        {
            "category":"Travel",
            "subcategory":"Hotels & Motels",
            "type":"Entertainment"
        }
    ],
    "sg:phone":"+1 306 287 3141",
    "sg:postcode":"S0K 1N0",
    "sg:province":"SK",
    "wof:name":"Englefeld Hotel",
    "wof:placetype":"venue"
},
  "geometry": {"coordinates":[-104.654396057,52.1589317322],"type":"Point"}
}