{
  "type": "Feature",
  "properties": {
    "addr:full":"8460 Boul Becancour Becancour QC G9H 3A5",
    "addr:housenumber":"8460",
    "addr:postcode":"g9h 3a5",
    "addr:street":"Boul Becancour Becancour",
    "iso:country":"CA",
    "sg:address":"8460 Boul Becancour",
    "sg:city":"Becancour",
    "sg:classifiers":[
        {
            "category":"Food & Beverages",
            "subcategory":"Groceries & Convenience Stores",
            "type":"Retail Goods"
        }
    ],
    "sg:phone":"+1 819 294 2585",
    "sg:postcode":"G9H 3A5",
    "sg:province":"QC",
    "wof:name":"Station DE Svc Relais Du Parc",
    "wof:placetype":"venue"
},
  "geometry": {"coordinates":[-72.4309082031,46.346622467],"type":"Point"}
}