{
  "type": "Feature",
  "properties": {
    "addr:full":"384 Peter St N Bothwell ON N0P 1C0",
    "addr:housenumber":"384",
    "addr:postcode":"n0p 1c0",
    "addr:street":"Peter St N",
    "iso:country":"CA",
    "sg:address":"384 Peter St N",
    "sg:city":"Bothwell",
    "sg:classifiers":[
        {
            "category":"Personal",
            "subcategory":"Beauty Salon",
            "type":"Services"
        }
    ],
    "sg:phone":"+1 519 695 2802",
    "sg:postcode":"N0P 1C0",
    "sg:province":"ON",
    "wof:name":"Fash'n Fair Beauty Studio",
    "wof:placetype":"venue"
},
  "geometry": {"coordinates":[-81.86932400000001,42.632973],"type":"Point"}
}