{
  "type": "Feature",
  "properties": {
    "addr:full":"108 Chestnut St Toronto ON M5G 1R3",
    "addr:housenumber":"108",
    "addr:postcode":"m5g 1r3",
    "addr:street":"Chestnut St",
    "iso:country":"CA",
    "sg:address":"108 Chestnut St",
    "sg:city":"Toronto",
    "sg:classifiers":[
        {
            "category":"Restaurant",
            "type":"Food & Drink"
        }
    ],
    "sg:phone":"+1 416 977 9899",
    "sg:postcode":"M5G 1R3",
    "sg:province":"ON",
    "wof:name":"Lai Wah Heen",
    "wof:placetype":"venue"
},
  "geometry": {"coordinates":[-79.386047,43.654881],"type":"Point"}
}