{
  "type": "Feature",
  "properties": {
    "addr:full":"2050 Clark Dr Vancouver BC V5N 3G7",
    "addr:housenumber":"2050",
    "addr:postcode":"v5n 3g7",
    "addr:street":"Clark Dr",
    "iso:country":"CA",
    "sg:address":"2050 Clark Dr",
    "sg:city":"Vancouver",
    "sg:classifiers":[
        {
            "category":"Home & Garden",
            "subcategory":"Carpets & Floor Coverings",
            "type":"Retail Goods"
        }
    ],
    "sg:phone":"+1 604 255 3852",
    "sg:postcode":"V5N 3G7",
    "sg:province":"BC",
    "sg:tags":[
        "dealer",
        "rug"
    ],
    "wof:name":"Adanac Carpet Ltd",
    "wof:placetype":"venue"
},
  "geometry": {"coordinates":[-123.077179,49.266567],"type":"Point"}
}