{
  "type": "Feature",
  "properties": {
    "iso:country":"CA",
    "sg:city":"Victoria",
    "sg:classifiers":[
        {
            "category":"Real Estate",
            "subcategory":"Real Estate Operator",
            "type":"Services"
        }
    ],
    "sg:phone":"+1 250 383 7628",
    "sg:postcode":"V8V 1L9",
    "sg:province":"BC",
    "sg:tags":[
        "apartment"
    ],
    "wof:name":"Marifield Park",
    "wof:placetype":"venue"
},
  "geometry": {"coordinates":[-123.37147521999999,48.4143753052],"type":"Point"}
}