{
  "type": "Feature",
  "properties": {
    "addr:full":"117 Brentwood Dr Bedford NS B4A 3S3",
    "addr:housenumber":"117",
    "addr:postcode":"b4a 3s3",
    "addr:street":"Brentwood Dr",
    "iso:country":"CA",
    "sg:address":"117 Brentwood Dr",
    "sg:city":"Bedford",
    "sg:classifiers":[
        {
            "category":"Professional",
            "subcategory":"Accounting & Tax Preparation",
            "type":"Services"
        }
    ],
    "sg:phone":"+1 902 456 1031",
    "sg:postcode":"B4A 3S3",
    "sg:province":"NS",
    "sg:tags":[
        "accountant"
    ],
    "wof:name":"David L Etter & Assoc",
    "wof:placetype":"venue"
},
  "geometry": {"coordinates":[-63.644539,44.730576],"type":"Point"}
}