{
  "type": "Feature",
  "properties": {
    "addr:full":"1632 Bowen Rd Nanaimo BC V9S 1G6",
    "addr:housenumber":"1632",
    "addr:postcode":"v9s 1g6",
    "addr:street":"Bowen Rd",
    "iso:country":"CA",
    "sg:address":"1632 Bowen Rd",
    "sg:city":"Nanaimo",
    "sg:classifiers":[
        {
            "category":"Education",
            "subcategory":"School",
            "type":"Public Place"
        }
    ],
    "sg:phone":"+1 250 754 6845",
    "sg:postcode":"V9S 1G6",
    "sg:province":"BC",
    "wof:name":"Quarterway School",
    "wof:placetype":"venue"
},
  "geometry": {"coordinates":[-123.975379944,49.179397583],"type":"Point"}
}