{
  "type": "Feature",
  "properties": {
    "addr:full":"Sainte-Genevieve QC H9H 1C1",
    "addr:postcode":"h9h 1c1",
    "addr:street":"Sainte-Genevieve",
    "iso:country":"CA",
    "sg:city":"Sainte-Genevieve",
    "sg:classifiers":[
        {
            "category":"Education",
            "subcategory":"Special Training",
            "type":"Public Place"
        }
    ],
    "sg:phone":"+1 514 696 3010",
    "sg:postcode":"H9H 1C1",
    "sg:province":"QC",
    "sg:tags":[
        "school",
        "music"
    ],
    "wof:name":"Ecole DE Musique Ste-Genevieve",
    "wof:placetype":"venue"
},
  "geometry": {"coordinates":[-73.866394043,45.4841079712],"type":"Point"}
}