{
  "type": "Feature",
  "properties": {
    "iso:country":"CA",
    "sg:city":"London",
    "sg:classifiers":[
        {
            "category":"Shopping",
            "subcategory":"Clothing, Apparel, & Fashions",
            "type":"Retail Goods"
        }
    ],
    "sg:phone":"+1 519 433 9499",
    "sg:postcode":"N6A 1S2",
    "sg:province":"ON",
    "sg:tags":[
        "tailor"
    ],
    "wof:name":"Ann's Tailoring & Design",
    "wof:placetype":"venue"
},
  "geometry": {"coordinates":[-81.2529220581,42.9942741394],"type":"Point"}
}