{
  "type": "Feature",
  "properties": {
    "addr:full":"2113 Otter Point Rd Sooke BC V0S 1N0",
    "addr:housenumber":"2113",
    "addr:postcode":"v0s 1n0",
    "addr:street":"Otter Point Rd",
    "iso:country":"CA",
    "sg:address":"2113 Otter Point Rd",
    "sg:city":"Sooke",
    "sg:classifiers":[
        {
            "category":"Health Services",
            "subcategory":"Clinic",
            "type":"Services"
        }
    ],
    "sg:phone":"+1 250 642 3790",
    "sg:postcode":"V0S 1N0",
    "sg:province":"BC",
    "wof:name":"Goodlife Wellness Ctr",
    "wof:placetype":"venue"
},
  "geometry": {"coordinates":[-123.725730896,48.3802833557],"type":"Point"}
}