{
  "type": "Feature",
  "properties": {
    "addr:full":"PO Box 65 Macoun SK S0C 1P0",
    "addr:housenumber":"po box 65",
    "addr:postcode":"s0c 1p0",
    "iso:country":"CA",
    "sg:address":"PO Box 65",
    "sg:city":"Macoun",
    "sg:classifiers":[
        {
            "category":"Organizations",
            "subcategory":"Religious Organization",
            "type":"Services"
        }
    ],
    "sg:phone":"+1 306 634 9284",
    "sg:postcode":"S0C 1P0",
    "sg:province":"SK",
    "sg:tags":[
        "church"
    ],
    "wof:name":"Macoun Evangelical Mssnry Chr",
    "wof:placetype":"venue"
},
  "geometry": {"coordinates":[-103.261971,49.313671],"type":"Point"}
}