{
  "type": "Feature",
  "properties": {
    "addr:full":"44 Rte Du President-Kennedy Levis QC G6V 6C5",
    "addr:housenumber":"44",
    "addr:postcode":"g6v 6c5",
    "addr:street":"Rte Du President-Kennedy",
    "iso:country":"CA",
    "sg:address":"44 Rte Du President-Kennedy",
    "sg:city":"Levis",
    "sg:classifiers":[
        {
            "category":"Sports & Exercise",
            "subcategory":"Bowling",
            "type":"Entertainment"
        }
    ],
    "sg:phone":"+1 418 837 2461",
    "sg:postcode":"G6V 6C5",
    "sg:province":"QC",
    "sg:tags":[
        "center"
    ],
    "wof:name":"Boule O-Drome Rive Sud Inc",
    "wof:placetype":"venue"
},
  "geometry": {"coordinates":[-71.1778793335,46.7959594727],"type":"Point"}
}