{
  "type": "Feature",
  "properties": {
    "addr:full":"1872 Angus St Regina SK S4T 1Z4",
    "addr:housenumber":"1872",
    "addr:postcode":"s4t 1z4",
    "addr:street":"Angus St",
    "iso:country":"CA",
    "sg:address":"1872 Angus St",
    "sg:city":"Regina",
    "sg:classifiers":[
        {
            "category":"Professional",
            "subcategory":"Lawyer & Legal Services",
            "type":"Services"
        }
    ],
    "sg:phone":"+1 306 789 7470",
    "sg:postcode":"S4T 1Z4",
    "sg:province":"SK",
    "sg:tags":[
        "attorney"
    ],
    "wof:name":"Mc Cannell Law Chambers",
    "wof:placetype":"venue"
},
  "geometry": {"coordinates":[-104.61983499999999,50.449306],"type":"Point"}
}