{
  "type": "Feature",
  "properties": {
    "iso:country":"CA",
    "sg:address":"3425 Laird Rd #5",
    "sg:city":"Mississauga",
    "sg:classifiers":[
        {
            "category":"Shopping",
            "type":"Retail Goods"
        }
    ],
    "sg:phone":"+1 905 760 0110",
    "sg:postcode":"L5L 5R8",
    "sg:province":"ON",
    "sg:tags":[
        "cosmetic",
        "perfume"
    ],
    "wof:name":"Faces Inc",
    "wof:placetype":"venue"
},
  "geometry": {"coordinates":[-79.695526,43.515694],"type":"Point"}
}