{
  "type": "Feature",
  "properties": {
    "addr:full":"30 Borden Ave Dartmouth NS B3B 1C8",
    "addr:housenumber":"30",
    "addr:postcode":"b3b 1c8",
    "addr:street":"Borden Ave",
    "iso:country":"CA",
    "sg:address":"30 Borden Ave",
    "sg:city":"Dartmouth",
    "sg:classifiers":[
        {
            "category":"Wholesale",
            "subcategory":"Hardware",
            "type":"Manufacturing & Wholesale Goods"
        }
    ],
    "sg:phone":"+1 902 468 7154",
    "sg:postcode":"B3B 1C8",
    "sg:province":"NS",
    "sg:tags":[
        "fastener"
    ],
    "wof:name":"Infasco",
    "wof:placetype":"venue"
},
  "geometry": {"coordinates":[-63.6015968323,44.7034263611],"type":"Point"}
}