{
  "type": "Feature",
  "properties": {
    "addr:full":"3 Rue Martin Saint-Philippe QC J0L 2K0",
    "addr:housenumber":"3",
    "addr:postcode":"j0l 2k0",
    "addr:street":"Rue Martin",
    "iso:country":"CA",
    "sg:address":"3 Rue Martin",
    "sg:city":"Saint-Philippe",
    "sg:classifiers":[
        {
            "category":"Retail",
            "subcategory":"Repair Shop",
            "type":"Services"
        }
    ],
    "sg:phone":"+1 450 659 8312",
    "sg:postcode":"J0L 2K0",
    "sg:province":"QC",
    "sg:tags":[
        "welding"
    ],
    "wof:name":"Soudure Aurele Dube Enr",
    "wof:placetype":"venue"
},
  "geometry": {"coordinates":[-73.4713134766,45.3480758667],"type":"Point"}
}