{
  "type": "Feature",
  "properties": {
    "iso:country":"CA",
    "sg:address":"959 Kamato Rd",
    "sg:city":"Mississauga",
    "sg:classifiers":[
        {
            "category":"Wholesale",
            "subcategory":"Sporting Goods",
            "type":"Manufacturing & Wholesale Goods"
        }
    ],
    "sg:phone":"+1 905 624 4022",
    "sg:postcode":"L4W 2R5",
    "sg:province":"ON",
    "sg:tags":[
        "equipment",
        "lane",
        "bowling"
    ],
    "wof:name":"Bowling Sales of Canada",
    "wof:placetype":"venue"
},
  "geometry": {"coordinates":[-79.6472702026,43.6360206604],"type":"Point"}
}