{
  "type": "Feature",
  "properties": {
    "addr:full":"200 Fitch St Welland ON L3C 4V9",
    "addr:housenumber":"200",
    "addr:postcode":"l3c 4v9",
    "addr:street":"Fitch St",
    "iso:country":"CA",
    "sg:address":"200 Fitch St",
    "sg:city":"Welland",
    "sg:classifiers":[
        {
            "category":"Shopping",
            "subcategory":"Department Store",
            "type":"Retail Goods"
        }
    ],
    "sg:phone":"+1 905 732 5121",
    "sg:postcode":"L3C 4V9",
    "sg:province":"ON",
    "sg:tags":[
        "shop"
    ],
    "wof:name":"Liquidation World Inc",
    "wof:placetype":"venue"
},
  "geometry": {"coordinates":[-79.2633972168,42.9945755005],"type":"Point"}
}