{
  "type": "Feature",
  "properties": {
    "addr:full":"PO Box 185 Duchess AB T0J 0Z0",
    "addr:housenumber":"po;185",
    "addr:postcode":"t0j 0z0",
    "addr:street":"Box",
    "iso:country":"CA",
    "sg:address":"PO Box 185",
    "sg:city":"Duchess",
    "sg:classifiers":[
        {
            "category":"Manufacturing",
            "subcategory":"Textiles",
            "type":"Manufacturing & Wholesale Goods"
        }
    ],
    "sg:phone":"+1 403 378 3069",
    "sg:postcode":"T0J 0Z0",
    "sg:province":"AB",
    "sg:tags":[
        "woolen",
        "wool",
        "mills"
    ],
    "wof:name":"Wool Mine Gift Gallery",
    "wof:placetype":"venue"
},
  "geometry": {"coordinates":[-111.904411,50.732498],"type":"Point"}
}