{
  "type": "Feature",
  "properties": {
    "addr:full":"10633 154 St NW Edmonton AB T5P 2J3",
    "addr:housenumber":"10633",
    "addr:postcode":"t5p 2j3",
    "addr:street":"154 St Nw",
    "iso:country":"CA",
    "sg:address":"10633 154 St NW",
    "sg:city":"Edmonton",
    "sg:classifiers":[
        {
            "category":"Organizations",
            "subcategory":"Non-profit Organization",
            "type":"Services"
        }
    ],
    "sg:phone":"+1 780 489 1349",
    "sg:postcode":"T5P 2J3",
    "sg:province":"AB",
    "sg:tags":[
        "charitable",
        "institution"
    ],
    "wof:name":"House Next Door 3/Interval",
    "wof:placetype":"venue"
},
  "geometry": {"coordinates":[-113.586617,53.550049],"type":"Point"}
}