{
  "type": "Feature",
  "properties": {
    "addr:full":"Toronto ON M6G 1L5",
    "addr:postcode":"m6g 1l5",
    "iso:country":"CA",
    "sg:city":"Toronto",
    "sg:classifiers":[
        {
            "category":"Social Services",
            "type":"Services"
        }
    ],
    "sg:phone":"+1 416 538 9412",
    "sg:postcode":"M6G 1L5",
    "sg:province":"ON",
    "sg:tags":[
        "organization",
        "welfare"
    ],
    "wof:name":"Korean Community Svc",
    "wof:placetype":"venue"
},
  "geometry": {"coordinates":[-79.41851800000001,43.663441],"type":"Point"}
}