{
  "type": "Feature",
  "properties": {
    "addr:full":"Emo ON P0W 1E0",
    "addr:postcode":"p0w 1e0",
    "iso:country":"CA",
    "sg:city":"Emo",
    "sg:classifiers":[
        {
            "category":"Insurance",
            "subcategory":"Insurance Agent",
            "type":"Services"
        }
    ],
    "sg:phone":"+1 807 482 2146",
    "sg:postcode":"P0W 1E0",
    "sg:province":"ON",
    "wof:name":"Gillons Insurance Brokers",
    "wof:placetype":"venue"
},
  "geometry": {"coordinates":[-93.83242799999999,48.627693],"type":"Point"}
}