{
  "type": "Feature",
  "properties": {
    "iso:country":"CA",
    "sg:address":"75 Peru Rd",
    "sg:city":"Milton",
    "sg:classifiers":[
        {
            "category":"Retail",
            "subcategory":"Auto Repair",
            "type":"Services"
        }
    ],
    "sg:phone":"+1 905 878 6951",
    "sg:postcode":"L9T 2V9",
    "sg:province":"ON",
    "sg:tags":[
        "repairing",
        "automobile"
    ],
    "wof:name":"Rego's Repair Svc",
    "wof:placetype":"venue"
},
  "geometry": {"coordinates":[-79.917168,43.519135],"type":"Point"}
}