{
  "type": "Feature",
  "properties": {
    "addr:full":"349 Rue Heriot Drummondville QC J2B 1B1",
    "addr:housenumber":"349",
    "addr:postcode":"j2b 1b1",
    "addr:street":"Rue Heriot",
    "iso:country":"CA",
    "sg:address":"349 Rue Heriot",
    "sg:city":"Drummondville",
    "sg:classifiers":[
        {
            "category":"Manufacturing",
            "subcategory":"Apparel",
            "type":"Manufacturing & Wholesale Goods"
        }
    ],
    "sg:phone":"+1 819 478 2535",
    "sg:postcode":"J2B 1B1",
    "sg:province":"QC",
    "sg:tags":[
        "fur",
        "business"
    ],
    "wof:name":"Laflamme Fourrures Drummond",
    "wof:placetype":"venue"
},
  "geometry": {"coordinates":[-72.484802,45.882874],"type":"Point"}
}