{
  "type": "Feature",
  "properties": {
    "addr:full":"1 Rue Auclair # A Sainte-Brigitte-DE-Laval QC G0A 3K0",
    "addr:housenumber":"1",
    "addr:postcode":"g0a 3k0",
    "addr:street":"Rue Auclair # A Sainte-Brigitte-De-Laval",
    "iso:country":"CA",
    "sg:address":"1 Rue Auclair # A",
    "sg:city":"Sainte-Brigitte-DE-Laval",
    "sg:classifiers":[
        {
            "category":"Recreation",
            "type":"Entertainment"
        }
    ],
    "sg:phone":"+1 418 825 1866",
    "sg:postcode":"G0A 3K0",
    "sg:province":"QC",
    "sg:tags":[
        "center"
    ],
    "wof:name":"Maison Des Jeunes Ste Brigitte",
    "wof:placetype":"venue"
},
  "geometry": {"coordinates":[-71.1944351196,47.0033073425],"type":"Point"}
}