{
  "type": "Feature",
  "properties": {
    "iso:country":"CA",
    "sg:address":"335 Spadina Ave",
    "sg:city":"Toronto",
    "sg:classifiers":[
        {
            "category":"Food & Beverages",
            "subcategory":"Liquor & Beverages",
            "type":"Retail Goods"
        }
    ],
    "sg:phone":"+1 416 597 0145",
    "sg:postcode":"M5T 2E9",
    "sg:province":"ON",
    "sg:tags":[
        "store"
    ],
    "wof:name":"Liquor Control Board of on",
    "wof:placetype":"venue"
},
  "geometry": {"coordinates":[-79.398689,43.654964],"type":"Point"}
}