{
  "type": "Feature",
  "properties": {
    "addr:full":"997 Boul Decarie # 209 Saint-Laurent QC H4L 3M7",
    "addr:housenumber":"997",
    "addr:postcode":"h4l 3m7",
    "addr:street":"Boul Decarie # 209 Saint-Laurent",
    "iso:country":"CA",
    "sg:address":"997 Boul Decarie # 209",
    "sg:city":"Saint-Laurent",
    "sg:classifiers":[
        {
            "category":"Shopping",
            "subcategory":"Computers & Home Electronics",
            "type":"Retail Goods"
        }
    ],
    "sg:phone":"+1 514 337 7479",
    "sg:postcode":"H4L 3M7",
    "sg:province":"QC",
    "sg:tags":[
        "equipment",
        "dealer"
    ],
    "wof:name":"Sam Echangeur Enrg",
    "wof:placetype":"venue"
},
  "geometry": {"coordinates":[-73.682434,45.51424],"type":"Point"}
}