{
  "type": "Feature",
  "properties": {
    "addr:full":"500 Av Marshall Dorval QC H9P 1C9",
    "addr:housenumber":"500",
    "addr:postcode":"h9p 1c9",
    "addr:street":"Av Marshall",
    "iso:country":"CA",
    "sg:address":"500 Av Marshall",
    "sg:city":"Dorval",
    "sg:classifiers":[
        {
            "category":"Retail",
            "subcategory":"Auto Repair",
            "type":"Services"
        }
    ],
    "sg:phone":"+1 514 636 1118",
    "sg:postcode":"H9P 1C9",
    "sg:province":"QC",
    "sg:tags":[
        "repairing",
        "automobile",
        "painting"
    ],
    "wof:name":"Carosserie Bel'Auto",
    "wof:placetype":"venue"
},
  "geometry": {"coordinates":[-73.73724365229999,45.4494895935],"type":"Point"}
}