{
  "type": "Feature",
  "properties": {
    "iso:country":"CA",
    "sg:city":"Calgary",
    "sg:classifiers":[
        {
            "category":"Arts & Performance",
            "subcategory":"Theater",
            "type":"Entertainment"
        }
    ],
    "sg:phone":"+1 403 230 3220",
    "sg:postcode":"T3E 7J4",
    "sg:province":"AB",
    "sg:tags":[
        "bureau"
    ],
    "wof:name":"Dagaz Talent",
    "wof:placetype":"venue"
},
  "geometry": {"coordinates":[-114.122123718,51.0174102783],"type":"Point"}
}