{
  "type": "Feature",
  "properties": {
    "addr:full":"1233 Glen Dr Vancouver BC V6A 3M8",
    "addr:housenumber":"1233",
    "addr:postcode":"v6a 3m8",
    "addr:street":"Glen Dr",
    "iso:country":"CA",
    "sg:address":"1233 Glen Dr",
    "sg:city":"Vancouver",
    "sg:classifiers":[
        {
            "category":"Food & Beverages",
            "subcategory":"Specialty",
            "type":"Retail Goods"
        }
    ],
    "sg:phone":"+1 604 254 3688",
    "sg:postcode":"V6A 3M8",
    "sg:province":"BC",
    "sg:tags":[
        "poultry"
    ],
    "wof:name":"Kum Sing Poultry",
    "wof:placetype":"venue"
},
  "geometry": {"coordinates":[-123.08165700000001,49.273815],"type":"Point"}
}