{
  "type": "Feature",
  "properties": {
    "addr:full":"542 Champlain St Dieppe NB E1A 1P4",
    "addr:housenumber":"542",
    "addr:postcode":"e1a 1p4",
    "addr:street":"Champlain St",
    "iso:country":"CA",
    "sg:address":"542 Champlain St",
    "sg:city":"Dieppe",
    "sg:classifiers":[
        {
            "category":"Wholesale",
            "subcategory":"Durable Goods & Equipment",
            "type":"Manufacturing & Wholesale Goods"
        }
    ],
    "sg:phone":"+1 506 859 8117",
    "sg:postcode":"E1A 1P4",
    "sg:province":"NB",
    "sg:tags":[
        "representative",
        "manufacturer"
    ],
    "wof:name":"Vision Sales & Marketing Ltd",
    "wof:placetype":"venue"
},
  "geometry": {"coordinates":[-64.7323684692,46.0985717773],"type":"Point"}
}