{
  "type": "Feature",
  "properties": {
    "addr:full":"8925 118 Ave NW Edmonton AB T5B 0T5",
    "addr:housenumber":"8925",
    "addr:postcode":"t5b 0t5",
    "addr:street":"118 Ave Nw",
    "iso:country":"CA",
    "sg:address":"8925 118 Ave NW",
    "sg:city":"Edmonton",
    "sg:classifiers":[
        {
            "category":"Health Services",
            "subcategory":"Doctor",
            "type":"Services"
        }
    ],
    "sg:phone":"+1 780 474 5471",
    "sg:postcode":"T5B 0T5",
    "sg:province":"AB",
    "sg:tags":[
        "physician",
        "surgeon"
    ],
    "wof:name":"Ma, James K S MD",
    "wof:placetype":"venue"
},
  "geometry": {"coordinates":[-113.478668,53.57029],"type":"Point"}
}