{
  "type": "Feature",
  "properties": {
    "addr:full":"1405 Gerrard St E Toronto ON M4L 1Z5",
    "addr:housenumber":"1405",
    "addr:postcode":"m4l 1z5",
    "addr:street":"Gerrard St E",
    "iso:country":"CA",
    "sg:address":"1405 Gerrard St E",
    "sg:city":"Toronto",
    "sg:classifiers":[
        {
            "category":"Food & Beverages",
            "subcategory":"Groceries & Convenience Stores",
            "type":"Retail Goods"
        }
    ],
    "sg:phone":"+1 416 778 8355",
    "sg:postcode":"M4L 1Z5",
    "sg:province":"ON",
    "sg:tags":[
        "grocer"
    ],
    "wof:name":"Toronto Cash & Carry",
    "wof:placetype":"venue"
},
  "geometry": {"coordinates":[-79.323471,43.671799],"type":"Point"}
}