{
  "type": "Feature",
  "properties": {
    "addr:full":"455 Montee Du Moulin Laval QC H7A 1Z2",
    "addr:housenumber":"455",
    "addr:postcode":"h7a 1z2",
    "addr:street":"Montee Du Moulin",
    "iso:country":"CA",
    "sg:address":"455 Montee Du Moulin",
    "sg:city":"Laval",
    "sg:classifiers":[
        {
            "category":"Social Services",
            "type":"Services"
        }
    ],
    "sg:phone":"+1 450 665 3049",
    "sg:postcode":"H7A 1Z2",
    "sg:province":"QC",
    "sg:tags":[
        "organization",
        "welfare"
    ],
    "wof:name":"Centre Defi-Jeunesse",
    "wof:placetype":"venue"
},
  "geometry": {"coordinates":[-73.5723953247,45.6670265198],"type":"Point"}
}