{
  "type": "Feature",
  "properties": {
    "addr:full":"5790 Beach Ave Peachland BC V0H 1X6",
    "addr:housenumber":"5790",
    "addr:postcode":"v0h 1x6",
    "addr:street":"Beach Ave",
    "iso:country":"CA",
    "sg:address":"5790 Beach Ave",
    "sg:city":"Peachland",
    "sg:classifiers":[
        {
            "category":"Restaurant",
            "type":"Food & Drink"
        }
    ],
    "sg:phone":"+1 250 767 6625",
    "sg:postcode":"V0H 1X6",
    "sg:province":"BC",
    "wof:name":"Gasthaus on the Lake",
    "wof:placetype":"venue"
},
  "geometry": {"coordinates":[-119.735817,49.774223],"type":"Point"}
}