{
  "type": "Feature",
  "properties": {
    "iso:country":"CA",
    "sg:city":"Timmins",
    "sg:classifiers":[
        {
            "category":"Professional",
            "subcategory":"Engineering",
            "type":"Services"
        }
    ],
    "sg:phone":"+1 705 360 5525",
    "sg:postcode":"P4N 2S7",
    "sg:province":"ON",
    "sg:tags":[
        "engineer"
    ],
    "wof:name":"Cma Engineering",
    "wof:placetype":"venue"
},
  "geometry": {"coordinates":[-81.33685302729999,48.4754867554],"type":"Point"}
}