{
  "type": "Feature",
  "properties": {
    "addr:full":"3600 Billings Crt #203 Burlington ON L7N 3N6",
    "addr:housenumber":"3600",
    "addr:postcode":"l7n 3n6",
    "addr:street":"Billings Crt # 203",
    "iso:country":"CA",
    "sg:address":"3600 Billings Crt #203",
    "sg:city":"Burlington",
    "sg:classifiers":[
        {
            "category":"Social Services",
            "type":"Services"
        }
    ],
    "sg:phone":"+1 905 681 6225",
    "sg:postcode":"L7N 3N6",
    "sg:province":"ON",
    "sg:tags":[
        "counselor",
        "marriage",
        "family"
    ],
    "wof:name":"Pieter Van Der Meulen & Assoc",
    "wof:placetype":"venue"
},
  "geometry": {"coordinates":[-79.789192,43.364029],"type":"Point"}
}