{
  "type": "Feature",
  "properties": {
    "addr:full":"Campbell River BC V9W 3G2",
    "addr:postcode":"v9w 3g2",
    "iso:country":"CA",
    "sg:city":"Campbell River",
    "sg:classifiers":[
        {
            "category":"Building & Trades",
            "subcategory":"Electrical",
            "type":"Services"
        }
    ],
    "sg:phone":"+1 250 830 0997",
    "sg:postcode":"V9W 3G2",
    "sg:province":"BC",
    "sg:tags":[
        "electric",
        "contractor"
    ],
    "wof:name":"Apple Electric Ltd",
    "wof:placetype":"venue"
},
  "geometry": {"coordinates":[-125.263870239,50.0319480896],"type":"Point"}
}