{
  "type": "Feature",
  "properties": {
    "iso:country":"CA",
    "sg:address":"128 Edgemont St S",
    "sg:city":"Hamilton",
    "sg:classifiers":[
        {
            "category":"Organizations",
            "subcategory":"Religious Organization",
            "type":"Services"
        }
    ],
    "sg:phone":"+1 905 544 2100",
    "sg:postcode":"L8K 2H8",
    "sg:province":"ON",
    "sg:tags":[
        "church"
    ],
    "wof:name":"St John the Baptist Rc Church",
    "wof:placetype":"venue"
},
  "geometry": {"coordinates":[-79.819534,43.238251],"type":"Point"}
}