{
  "type": "Feature",
  "properties": {
    "addr:full":"1010 Adelaide St N London ON N5Y 2M9",
    "addr:housenumber":"1010",
    "addr:postcode":"n5y 2m9",
    "addr:street":"Adelaide St N",
    "iso:country":"CA",
    "sg:address":"1010 Adelaide St N",
    "sg:city":"London",
    "sg:classifiers":[
        {
            "category":"Retail",
            "subcategory":"Car Wash",
            "type":"Services"
        }
    ],
    "sg:phone":"+1 519 439 9294",
    "sg:postcode":"N5Y 2M9",
    "sg:province":"ON",
    "sg:tags":[
        "polishing",
        "washing"
    ],
    "wof:name":"Shell Canada Ltd",
    "wof:placetype":"venue"
},
  "geometry": {"coordinates":[-81.24025726319999,43.0067825317],"type":"Point"}
}