{
  "type": "Feature",
  "properties": {
    "addr:full":"5175 Hennin St Oldcastle ON N0R 1L0",
    "addr:housenumber":"5175",
    "addr:postcode":"n0r 1l0",
    "addr:street":"Hennin St",
    "iso:country":"CA",
    "sg:address":"5175 Hennin St",
    "sg:city":"Oldcastle",
    "sg:classifiers":[
        {
            "category":"Manufacturing",
            "subcategory":"Tools & Machinery",
            "type":"Manufacturing & Wholesale Goods"
        }
    ],
    "sg:phone":"+1 519 737 6811",
    "sg:postcode":"N0R 1L0",
    "sg:province":"ON",
    "sg:tags":[
        "die",
        "maker"
    ],
    "wof:name":"Saturn Tool & Die Inc",
    "wof:placetype":"venue"
},
  "geometry": {"coordinates":[-82.956993,42.238235],"type":"Point"}
}