{
  "type": "Feature",
  "properties": {
    "addr:full":"842 56th St E Saskatoon SK S7K 5Y8",
    "addr:housenumber":"842",
    "addr:postcode":"s7k 5y8",
    "addr:street":"56Th St E",
    "iso:country":"CA",
    "sg:address":"842 56th St E",
    "sg:city":"Saskatoon",
    "sg:classifiers":[
        {
            "category":"Manufacturing",
            "subcategory":"Apparel",
            "type":"Manufacturing & Wholesale Goods"
        }
    ],
    "sg:phone":"+1 306 931 1122",
    "sg:postcode":"S7K 5Y8",
    "sg:province":"SK",
    "sg:tags":[
        "tarpaulin"
    ],
    "wof:name":"Inland Plastics Ltd",
    "wof:placetype":"venue"
},
  "geometry": {"coordinates":[-106.650368,52.18034],"type":"Point"}
}