{
  "type": "Feature",
  "properties": {
    "addr:full":"1711 Bishop St Cambridge ON N1T 1N5",
    "addr:housenumber":"1711",
    "addr:postcode":"n1t 1n5",
    "addr:street":"Bishop St",
    "iso:country":"CA",
    "sg:address":"1711 Bishop St",
    "sg:city":"Cambridge",
    "sg:classifiers":[
        {
            "category":"Building & Trades",
            "subcategory":"Electrical",
            "type":"Services"
        }
    ],
    "sg:phone":"+1 519 740 6666",
    "sg:postcode":"N1T 1N5",
    "sg:province":"ON",
    "sg:tags":[
        "equipment",
        "telecommunication"
    ],
    "wof:name":"Performed Line Products Ltd",
    "wof:placetype":"venue"
},
  "geometry": {"coordinates":[-80.30284899999999,43.398689],"type":"Point"}
}