{
  "type": "Feature",
  "properties": {
    "addr:full":"Saint-Pamphile QC G0R 3X0",
    "addr:postcode":"g0r 3x0",
    "iso:country":"CA",
    "sg:city":"Saint-Pamphile",
    "sg:classifiers":[
        {
            "category":"Freight",
            "type":"Transportation"
        }
    ],
    "sg:phone":"+1 418 356 3322",
    "sg:postcode":"G0R 3X0",
    "sg:province":"QC",
    "sg:tags":[
        "trucking"
    ],
    "wof:name":"Transport St-Pamphile Inc",
    "wof:placetype":"venue"
},
  "geometry": {"coordinates":[-69.7751464844,46.9597549438],"type":"Point"}
}