{
  "type": "Feature",
  "properties": {
    "addr:full":"1615 Rue DE Louvain O Montreal QC H4N 1G6",
    "addr:housenumber":"1615",
    "addr:postcode":"h4n 1g6",
    "addr:street":"Rue De Louvain O",
    "iso:country":"CA",
    "sg:address":"1615 Rue DE Louvain O",
    "sg:city":"Montreal",
    "sg:classifiers":[
        {
            "category":"Manufacturing",
            "subcategory":"Apparel",
            "type":"Manufacturing & Wholesale Goods"
        }
    ],
    "sg:phone":"+1 514 384 4741",
    "sg:postcode":"H4N 1G6",
    "sg:province":"QC",
    "sg:tags":[
        "clothing",
        "clothes"
    ],
    "wof:name":"Ufo Vetements Pour Enfants",
    "wof:placetype":"venue"
},
  "geometry": {"coordinates":[-73.6627197266,45.5314064026],"type":"Point"}
}