{
  "type": "Feature",
  "properties": {
    "addr:full":"16507 40 Ave Surrey BC V3S 0L2",
    "addr:housenumber":"16507",
    "addr:postcode":"v3s 0l2",
    "addr:street":"40 Ave",
    "iso:country":"CA",
    "sg:address":"16507 40 Ave",
    "sg:city":"Surrey",
    "sg:classifiers":[
        {
            "category":"Professional",
            "subcategory":"Research",
            "type":"Services"
        }
    ],
    "sg:phone":"+1 604 574 5477",
    "sg:postcode":"V3S 0L2",
    "sg:province":"BC",
    "sg:tags":[
        "environmental",
        "ecological"
    ],
    "wof:name":"Mud Bay Drilling CO Ltd",
    "wof:placetype":"venue"
},
  "geometry": {"coordinates":[-122.765419006,49.0750427246],"type":"Point"}
}