{
  "type": "Feature",
  "properties": {
    "addr:full":"53 Sixth Ave N Yorkton SK S3N 0X7",
    "addr:housenumber":"53",
    "addr:postcode":"s3n 0x7",
    "addr:street":"Sixth Ave N",
    "iso:country":"CA",
    "sg:address":"53 Sixth Ave N",
    "sg:city":"Yorkton",
    "sg:classifiers":[
        {
            "category":"Real Estate",
            "subcategory":"Real Estate Operator",
            "type":"Services"
        }
    ],
    "sg:phone":"+1 306 782 9464",
    "sg:postcode":"S3N 0X7",
    "sg:province":"SK",
    "sg:tags":[
        "shop",
        "mall",
        "shopping",
        "center",
        "coffee"
    ],
    "wof:name":"Zebra X-Ing",
    "wof:placetype":"venue"
},
  "geometry": {"coordinates":[-102.455635,51.212299],"type":"Point"}
}