{
  "type": "Feature",
  "properties": {
    "addr:full":"1160 Rymal Rd E Hamilton ON L8W 3N7",
    "addr:housenumber":"1160",
    "addr:postcode":"l8w 3n7",
    "addr:street":"Rymal Rd E",
    "iso:country":"CA",
    "sg:address":"1160 Rymal Rd E",
    "sg:city":"Hamilton",
    "sg:classifiers":[
        {
            "category":"Professional",
            "subcategory":"Business Services",
            "type":"Services"
        }
    ],
    "sg:phone":"+1 905 388 6233",
    "sg:postcode":"L8W 3N7",
    "sg:province":"ON",
    "sg:tags":[
        "designer",
        "dealer",
        "pool",
        "swimming"
    ],
    "wof:name":"Pioneer Family Pools",
    "wof:placetype":"venue"
},
  "geometry": {"coordinates":[-79.841759,43.189705],"type":"Point"}
}