{
  "type": "Feature",
  "properties": {
    "addr:full":"203 33rd St W Saskatoon SK S7L 0V2",
    "addr:housenumber":"203",
    "addr:postcode":"s7l 0v2",
    "addr:street":"33Rd St W",
    "iso:country":"CA",
    "sg:address":"203 33rd St W",
    "sg:city":"Saskatoon",
    "sg:classifiers":[
        {
            "category":"Home & Garden",
            "subcategory":"Hardware",
            "type":"Retail Goods"
        }
    ],
    "sg:phone":"+1 306 244 4884",
    "sg:postcode":"S7L 0V2",
    "sg:province":"SK",
    "wof:name":"Mayfair Hardware",
    "wof:placetype":"venue"
},
  "geometry": {"coordinates":[-106.67215,52.143734],"type":"Point"}
}