{
  "type": "Feature",
  "properties": {
    "addr:full":"1255 Boul Laird # 331 Mont-Royal QC H3P 2T1",
    "addr:housenumber":"1255",
    "addr:postcode":"h3p 2t1",
    "addr:street":"Boul Laird # 331 Mont-Royal",
    "iso:country":"CA",
    "sg:address":"1255 Boul Laird # 331",
    "sg:city":"Mont-Royal",
    "sg:classifiers":[
        {
            "category":"Real Estate",
            "subcategory":"Real Estate Operator",
            "type":"Services"
        }
    ],
    "sg:phone":"+1 514 731 6313",
    "sg:postcode":"H3P 2T1",
    "sg:province":"QC",
    "sg:tags":[
        "apartment"
    ],
    "wof:name":"Edifice Laird-Canora Inc",
    "wof:placetype":"venue"
},
  "geometry": {"coordinates":[-73.6439819336,45.5172538757],"type":"Point"}
}