{
  "type": "Feature",
  "properties": {
    "addr:full":"7707 Kingsway Burnaby BC V3N 3C9",
    "addr:housenumber":"7707",
    "addr:postcode":"v3n 3c9",
    "addr:street":"Kingsway",
    "iso:country":"CA",
    "sg:address":"7707 Kingsway",
    "sg:city":"Burnaby",
    "sg:classifiers":[
        {
            "category":"Retail",
            "subcategory":"Auto Repair",
            "type":"Services"
        }
    ],
    "sg:phone":"+1 604 525 8322",
    "sg:postcode":"V3N 3C9",
    "sg:province":"BC",
    "sg:tags":[
        "repairing",
        "automobile",
        "brake"
    ],
    "wof:name":"Edmonds Motors Ltd",
    "wof:placetype":"venue"
},
  "geometry": {"coordinates":[-122.940940857,49.2153358459],"type":"Point"}
}