{
  "type": "Feature",
  "properties": {
    "addr:full":"24492 56A Ave Langley BC V2Z 1G8",
    "addr:housenumber":"24492",
    "addr:postcode":"v2z 1g8",
    "addr:street":"56A Ave",
    "iso:country":"CA",
    "sg:address":"24492 56A Ave",
    "sg:city":"Langley",
    "sg:classifiers":[
        {
            "category":"Building & Trades",
            "subcategory":"Construction",
            "type":"Services"
        }
    ],
    "sg:phone":"+1 604 856 6790",
    "sg:postcode":"V2Z 1G8",
    "sg:province":"BC",
    "sg:tags":[
        "excavating",
        "contractor"
    ],
    "wof:name":"Western Star Contracting Ltd",
    "wof:placetype":"venue"
},
  "geometry": {"coordinates":[-122.65657043500001,49.1041221619],"type":"Point"}
}