{
  "type": "Feature",
  "properties": {
    "addr:full":"167 Queen St W Brampton ON L6Y 1M5",
    "addr:housenumber":"167",
    "addr:postcode":"l6y 1m5",
    "addr:street":"Queen St W",
    "iso:country":"CA",
    "sg:address":"167 Queen St W",
    "sg:city":"Brampton",
    "sg:classifiers":[
        {
            "category":"Health Services",
            "subcategory":"Doctor",
            "type":"Services"
        }
    ],
    "sg:phone":"+1 905 453 9366",
    "sg:postcode":"L6Y 1M5",
    "sg:province":"ON",
    "sg:tags":[
        "physician",
        "surgeon"
    ],
    "wof:name":"Paribello, Carlo MD",
    "wof:placetype":"venue"
},
  "geometry": {"coordinates":[-79.76384,43.682156],"type":"Point"}
}