{
  "type": "Feature",
  "properties": {
    "addr:full":"Rte Pennington Frampton QC G0R 1M0",
    "addr:postcode":"g0r 1m0",
    "addr:street":"Rte Pennington",
    "iso:country":"CA",
    "sg:address":"Rte Pennington",
    "sg:city":"Frampton",
    "sg:classifiers":[
        {
            "category":"Travel",
            "subcategory":"Campground",
            "type":"Entertainment"
        }
    ],
    "sg:phone":"+1 418 479 5415",
    "sg:postcode":"G0R 1M0",
    "sg:province":"QC",
    "sg:tags":[
        "camp",
        "fishing"
    ],
    "wof:name":"Club Chasse & Peche Ste-Marie",
    "wof:placetype":"venue"
},
  "geometry": {"coordinates":[-70.8080215454,46.4614982605],"type":"Point"}
}