{
  "type": "Feature",
  "properties": {
    "addr:full":"507 Mary St Wiarton ON N0H 2T0",
    "addr:housenumber":"507",
    "addr:postcode":"n0h 2t0",
    "addr:street":"Mary St",
    "iso:country":"CA",
    "sg:address":"507 Mary St",
    "sg:city":"Wiarton",
    "sg:classifiers":[
        {
            "category":"Retail",
            "subcategory":"Repair Shop",
            "type":"Services"
        }
    ],
    "sg:phone":"+1 519 534 3338",
    "sg:postcode":"N0H 2T0",
    "sg:province":"ON",
    "sg:tags":[
        "appliance"
    ],
    "wof:name":"Gavard Appliance & Refrig Svc",
    "wof:placetype":"venue"
},
  "geometry": {"coordinates":[-81.133957,44.738419],"type":"Point"}
}