{
  "type": "Feature",
  "properties": {
    "iso:country":"CA",
    "sg:address":"5245 Boul Cousineau # 188",
    "sg:city":"Saint-Hubert",
    "sg:classifiers":[
        {
            "category":"Shopping",
            "subcategory":"Clothing, Apparel, & Fashions",
            "type":"Retail Goods"
        }
    ],
    "sg:phone":"+1 450 462 8778",
    "sg:postcode":"J3Y 6J8",
    "sg:province":"QC",
    "wof:name":"Xmara",
    "wof:placetype":"venue"
},
  "geometry": {"coordinates":[-73.425148,45.501904],"type":"Point"}
}