{
  "type": "Feature",
  "properties": {
    "iso:country":"CA",
    "sg:address":"1175 Aut Chomedey",
    "sg:city":"Laval",
    "sg:classifiers":[
        {
            "category":"Home & Garden",
            "subcategory":"Home Furnishings",
            "type":"Retail Goods"
        }
    ],
    "sg:phone":"+1 450 687 3892",
    "sg:postcode":"H7W 5J8",
    "sg:province":"QC",
    "sg:tags":[
        "venetian",
        "blind",
        "made",
        "drapery"
    ],
    "wof:name":"Verti-Store Inc",
    "wof:placetype":"venue"
},
  "geometry": {"coordinates":[-73.78855896,45.5363044739],"type":"Point"}
}