{
  "type": "Feature",
  "properties": {
    "addr:full":"158 Rue Notre-Dame E Rimouski QC G5L 2A1",
    "addr:housenumber":"158",
    "addr:postcode":"g5l 2a1",
    "addr:street":"Rue Notre-Dame E",
    "iso:country":"CA",
    "sg:address":"158 Rue Notre-Dame E",
    "sg:city":"Rimouski",
    "sg:classifiers":[
        {
            "category":"Retail",
            "subcategory":"Portrait Studio",
            "type":"Services"
        }
    ],
    "sg:phone":"+1 418 723 9013",
    "sg:postcode":"G5L 2A1",
    "sg:province":"QC",
    "sg:tags":[
        "wedding",
        "supply"
    ],
    "wof:name":"Theriault, Roland",
    "wof:placetype":"venue"
},
  "geometry": {"coordinates":[-68.517021,48.451927],"type":"Point"}
}