{
  "type": "Feature",
  "properties": {
    "addr:full":"5108 50th Ave Daysland AB T0B 1A0",
    "addr:housenumber":"5108",
    "addr:postcode":"t0b 1a0",
    "addr:street":"50Th Ave",
    "iso:country":"CA",
    "sg:address":"5108 50th Ave",
    "sg:city":"Daysland",
    "sg:classifiers":[
        {
            "category":"Wholesale",
            "subcategory":"Machinery & Supplies",
            "type":"Manufacturing & Wholesale Goods"
        }
    ],
    "sg:phone":"+1 780 374 3786",
    "sg:postcode":"T0B 1A0",
    "sg:province":"AB",
    "sg:tags":[
        "farm",
        "equipment"
    ],
    "wof:name":"Daysland Auto & Farm Supply",
    "wof:placetype":"venue"
},
  "geometry": {"coordinates":[-112.263161,52.864449],"type":"Point"}
}