{
  "type": "Feature",
  "properties": {
    "addr:full":"2079 42nd Ave W Vancouver BC V6M 2B4",
    "addr:housenumber":"2079",
    "addr:postcode":"v6m 2b4",
    "addr:street":"42Nd Ave W",
    "iso:country":"CA",
    "sg:address":"2079 42nd Ave W",
    "sg:city":"Vancouver",
    "sg:classifiers":[
        {
            "category":"Shopping",
            "subcategory":"Pharmacy",
            "type":"Retail Goods"
        }
    ],
    "sg:phone":"+1 604 263 1811",
    "sg:postcode":"V6M 2B4",
    "sg:province":"BC",
    "wof:name":"London Drugs",
    "wof:placetype":"venue"
},
  "geometry": {"coordinates":[-123.154152,49.233696],"type":"Point"}
}