{
  "type": "Feature",
  "properties": {
    "addr:full":"4204 118 Ave NW Edmonton AB T5W 1A4",
    "addr:housenumber":"4204",
    "addr:postcode":"t5w 1a4",
    "addr:street":"118 Ave Nw",
    "iso:country":"CA",
    "sg:address":"4204 118 Ave NW",
    "sg:city":"Edmonton",
    "sg:classifiers":[
        {
            "category":"Food & Beverages",
            "subcategory":"Meat & Fish",
            "type":"Retail Goods"
        }
    ],
    "sg:phone":"+1 780 479 3247",
    "sg:postcode":"T5W 1A4",
    "sg:province":"AB",
    "wof:name":"Silver City Meats Ltd",
    "wof:placetype":"venue"
},
  "geometry": {"coordinates":[-113.406318665,53.5704879761],"type":"Point"}
}