{
  "type": "Feature",
  "properties": {
    "addr:full":"316 Principale Saint-Victor QC G0M 2B0",
    "addr:housenumber":"316",
    "addr:postcode":"g0m 2b0",
    "addr:street":"Principale",
    "iso:country":"CA",
    "sg:address":"316 Principale",
    "sg:city":"Saint-Victor",
    "sg:classifiers":[
        {
            "category":"Manufacturing",
            "subcategory":"Metals",
            "type":"Manufacturing & Wholesale Goods"
        }
    ],
    "sg:phone":"+1 418 588 3935",
    "sg:postcode":"G0M 2B0",
    "sg:province":"QC",
    "sg:tags":[
        "solder"
    ],
    "wof:name":"Soudure Mobile",
    "wof:placetype":"venue"
},
  "geometry": {"coordinates":[-70.902252,46.149887],"type":"Point"}
}