{
  "type": "Feature",
  "properties": {
    "addr:full":"8493 Av Du Chardonnet Anjou QC H1K 1B8",
    "addr:housenumber":"8493",
    "addr:postcode":"h1k 1b8",
    "addr:street":"Av Du Chardonnet",
    "iso:country":"CA",
    "sg:address":"8493 Av Du Chardonnet",
    "sg:city":"Anjou",
    "sg:classifiers":[
        {
            "category":"Building & Trades",
            "subcategory":"Plumbing",
            "type":"Services"
        }
    ],
    "sg:phone":"+1 514 354 0847",
    "sg:postcode":"H1K 1B8",
    "sg:province":"QC",
    "sg:tags":[
        "ventilating",
        "contractor"
    ],
    "wof:name":"Ven-T-Air Ducts Ltee",
    "wof:placetype":"venue"
},
  "geometry": {"coordinates":[-73.556847,45.612083],"type":"Point"}
}