{
  "type": "Feature",
  "properties": {
    "addr:full":"215 Rue Robinson S Granby QC J2G 7M4",
    "addr:housenumber":"215",
    "addr:postcode":"j2g 7m4",
    "addr:street":"Rue Robinson S Granby",
    "iso:country":"CA",
    "sg:address":"215 Rue Robinson S",
    "sg:city":"Granby",
    "sg:classifiers":[
        {
            "category":"Organizations",
            "subcategory":"Professional Association",
            "type":"Services"
        }
    ],
    "sg:phone":"+1 450 777 4233",
    "sg:postcode":"J2G 7M4",
    "sg:province":"QC",
    "wof:name":"Entraide St Eugene",
    "wof:placetype":"venue"
},
  "geometry": {"coordinates":[-72.74169158940001,45.4008331299],"type":"Point"}
}