{
  "type": "Feature",
  "properties": {
    "addr:full":"6447 2 St SE Calgary AB T2H 1J5",
    "addr:housenumber":"6447 2",
    "addr:postcode":"t2h 1j5",
    "addr:street":"St Se",
    "iso:country":"CA",
    "sg:address":"6447 2 St SE",
    "sg:city":"Calgary",
    "sg:classifiers":[
        {
            "category":"Manufacturing",
            "subcategory":"Tools & Machinery",
            "type":"Manufacturing & Wholesale Goods"
        }
    ],
    "sg:phone":"+1 403 252 8131",
    "sg:postcode":"T2H 1J5",
    "sg:province":"AB",
    "sg:tags":[
        "generator"
    ],
    "wof:name":"Simson-Maxwell",
    "wof:placetype":"venue"
},
  "geometry": {"coordinates":[-114.060142517,50.9952163696],"type":"Point"}
}