{
  "type": "Feature",
  "properties": {
    "addr:full":"5 Cornwall St Sault Ste Marie ON P6C 1C4",
    "addr:housenumber":"5",
    "addr:postcode":"p6c 1c4",
    "addr:street":"Cornwall St",
    "iso:country":"CA",
    "sg:address":"5 Cornwall St",
    "sg:city":"Sault Ste Marie",
    "sg:classifiers":[
        {
            "category":"Organizations",
            "subcategory":"Professional Association",
            "type":"Services"
        }
    ],
    "sg:phone":"+1 705 942 4794",
    "sg:postcode":"P6C 1C4",
    "sg:province":"ON",
    "wof:name":"Portuguese Canadian Assn",
    "wof:placetype":"venue"
},
  "geometry": {"coordinates":[-84.341095,46.525181],"type":"Point"}
}