{
  "type": "Feature",
  "properties": {
    "addr:full":"PO Box 3232 STN Terminal Vancouver BC V6B 3X8",
    "addr:housenumber":"po",
    "addr:postcode":"3232;bc v6b 3x8",
    "addr:street":"Box",
    "iso:country":"CA",
    "sg:address":"PO Box 3232 STN Terminal",
    "sg:city":"Vancouver",
    "sg:classifiers":[
        {
            "category":"Recreation",
            "type":"Entertainment"
        }
    ],
    "sg:phone":"+1 604 659 3474",
    "sg:postcode":"V6B 3X8",
    "sg:province":"BC",
    "sg:tags":[
        "amusement"
    ],
    "wof:name":"Vancouver Aquarium Marine",
    "wof:placetype":"venue"
},
  "geometry": {"coordinates":[-123.114037,49.260441],"type":"Point"}
}