{
  "type": "Feature",
  "properties": {
    "iso:country":"CA",
    "sg:address":"595 Boul Guimond",
    "sg:city":"Longueuil",
    "sg:classifiers":[
        {
            "category":"Manufacturing",
            "subcategory":"Paper Products",
            "type":"Manufacturing & Wholesale Goods"
        }
    ],
    "sg:phone":"+1 514 866 5494",
    "sg:postcode":"J4G 1L9",
    "sg:province":"QC",
    "sg:tags":[
        "bag"
    ],
    "wof:name":"Impressions Logobec Intl Ltee",
    "wof:placetype":"venue"
},
  "geometry": {"coordinates":[-73.469742,45.568451],"type":"Point"}
}