{
  "type": "Feature",
  "properties": {
    "addr:full":"27 King St E Brockville ON K6V 1A7",
    "addr:housenumber":"27",
    "addr:postcode":"k6v 1a7",
    "addr:street":"King St",
    "iso:country":"CA",
    "sg:address":"27 King St E",
    "sg:city":"Brockville",
    "sg:classifiers":[
        {
            "category":"Personal",
            "subcategory":"Barber",
            "type":"Services"
        }
    ],
    "sg:phone":"+1 613 345 5319",
    "sg:postcode":"K6V 1A7",
    "sg:province":"ON",
    "wof:name":"Jay's Barber Shop",
    "wof:placetype":"venue"
},
  "geometry": {"coordinates":[-75.6817855835,44.5910644531],"type":"Point"}
}