{
  "type": "Feature",
  "properties": {
    "addr:full":"901 Rue Lenoir Montreal QC H4C 2Z6",
    "addr:housenumber":"901",
    "addr:postcode":"h4c 2z6",
    "addr:street":"Rue Lenoir",
    "iso:country":"CA",
    "sg:address":"901 Rue Lenoir",
    "sg:city":"Montreal",
    "sg:classifiers":[
        {
            "category":"Shopping",
            "type":"Retail Goods"
        }
    ],
    "sg:phone":"+1 514 939 3038",
    "sg:postcode":"H4C 2Z6",
    "sg:province":"QC",
    "sg:tags":[
        "equipment",
        "sculptor",
        "supply"
    ],
    "wof:name":"Schupp, Olivier",
    "wof:placetype":"venue"
},
  "geometry": {"coordinates":[-73.5917816162,45.4764404297],"type":"Point"}
}