{
  "type": "Feature",
  "properties": {
    "addr:full":"10118 99th Ave Lac LA Biche AB T0A 2C0",
    "addr:housenumber":"10118",
    "addr:postcode":"t0a 2c0",
    "addr:street":"99Th Ave",
    "iso:country":"CA",
    "sg:address":"10118 99th Ave",
    "sg:city":"Lac LA Biche",
    "sg:classifiers":[
        {
            "category":"Utilities",
            "subcategory":"Natural Gas",
            "type":"Services"
        }
    ],
    "sg:phone":"+1 780 623 4266",
    "sg:postcode":"T0A 2C0",
    "sg:province":"AB",
    "sg:tags":[
        "company",
        "government"
    ],
    "wof:name":"Lac LA Biche Gas Office",
    "wof:placetype":"venue"
},
  "geometry": {"coordinates":[-111.975311,54.767632],"type":"Point"}
}