{
  "type": "Feature",
  "properties": {
    "addr:full":"67 Cedar St Sudbury ON P3E 1A7",
    "addr:housenumber":"67",
    "addr:postcode":"p3e 1a7",
    "addr:street":"Cedar St",
    "iso:country":"CA",
    "sg:address":"67 Cedar St",
    "sg:city":"Sudbury",
    "sg:classifiers":[
        {
            "category":"Shopping",
            "subcategory":"Clothing, Apparel, & Fashions",
            "type":"Retail Goods"
        }
    ],
    "sg:phone":"+1 705 674 7541",
    "sg:postcode":"P3E 1A7",
    "sg:province":"ON",
    "sg:tags":[
        "furnishing"
    ],
    "wof:name":"Joe Lesar Men's Wear & Tailor",
    "wof:placetype":"venue"
},
  "geometry": {"coordinates":[-80.994598,46.492046],"type":"Point"}
}