{
  "type": "Feature",
  "properties": {
    "addr:full":"9 Tavistock Crt Markham ON L3P 6H2",
    "addr:housenumber":"9",
    "addr:postcode":"l3p 6h2",
    "addr:street":"Tavistock Crt",
    "iso:country":"CA",
    "sg:address":"9 Tavistock Crt",
    "sg:city":"Markham",
    "sg:classifiers":[
        {
            "category":"Building & Trades",
            "subcategory":"Construction",
            "type":"Services"
        }
    ],
    "sg:phone":"+1 905 471 7124",
    "sg:postcode":"L3P 6H2",
    "sg:province":"ON",
    "sg:tags":[
        "masonry",
        "contractor"
    ],
    "wof:name":"Alfi Masonry",
    "wof:placetype":"venue"
},
  "geometry": {"coordinates":[-79.28173099999999,43.883343],"type":"Point"}
}