{
  "type": "Feature",
  "properties": {
    "iso:country":"CA",
    "sg:city":"Vancouver",
    "sg:classifiers":[
        {
            "category":"Real Estate",
            "subcategory":"Real Estate Operator",
            "type":"Services"
        }
    ],
    "sg:phone":"+1 604 872 7777",
    "sg:postcode":"V5Z 4B3",
    "sg:province":"BC",
    "sg:tags":[
        "apartment"
    ],
    "wof:name":"Moberly Apartments",
    "wof:placetype":"venue"
},
  "geometry": {"coordinates":[-123.119010925,49.2675094604],"type":"Point"}
}