{
  "type": "Feature",
  "properties": {
    "iso:country":"CA",
    "sg:address":"250 Place D'Youville # 200",
    "sg:city":"Montreal",
    "sg:classifiers":[
        {
            "category":"Professional",
            "subcategory":"Lawyer & Legal Services",
            "type":"Services"
        }
    ],
    "sg:phone":"+1 514 845 5457",
    "sg:postcode":"H2Y 2B6",
    "sg:province":"QC",
    "sg:tags":[
        "attorney"
    ],
    "wof:name":"Cleroux, Stephane",
    "wof:placetype":"venue"
},
  "geometry": {"coordinates":[-73.643867,45.547421],"type":"Point"}
}