{
  "type": "Feature",
  "properties": {
    "addr:full":"848 Rue St-Francois Verret NB E3V 4R2",
    "addr:housenumber":"848",
    "addr:postcode":"e3v 4r2",
    "addr:street":"Rue St-Francois",
    "iso:country":"CA",
    "sg:address":"848 Rue St-Francois",
    "sg:city":"Verret",
    "sg:classifiers":[
        {
            "category":"Retail",
            "subcategory":"Animal Services",
            "type":"Services"
        }
    ],
    "sg:phone":"+1 506 735 7982",
    "sg:postcode":"E3V 4R2",
    "sg:province":"NB",
    "sg:tags":[
        "pet",
        "grooming",
        "washing"
    ],
    "wof:name":"Studio Le Look Canin & Felin",
    "wof:placetype":"venue"
},
  "geometry": {"coordinates":[-68.376862,47.350147],"type":"Point"}
}