{
  "type": "Feature",
  "properties": {
    "addr:full":"Brampton ON L6W 3R7",
    "addr:postcode":"l6w 3r7",
    "iso:country":"CA",
    "sg:city":"Brampton",
    "sg:classifiers":[
        {
            "category":"Social Services",
            "type":"Services"
        }
    ],
    "sg:phone":"+1 905 452 0332",
    "sg:postcode":"L6W 3R7",
    "sg:province":"ON",
    "sg:tags":[
        "organization",
        "welfare"
    ],
    "wof:name":"Family Education Ctr",
    "wof:placetype":"venue"
},
  "geometry": {"coordinates":[-79.7411727905,43.689617157],"type":"Point"}
}