{
  "type": "Feature",
  "properties": {
    "iso:country":"CA",
    "sg:address":"20 Claireport Cres",
    "sg:city":"Etobicoke",
    "sg:classifiers":[
        {
            "category":"Manufacturing",
            "subcategory":"Signs",
            "type":"Manufacturing & Wholesale Goods"
        }
    ],
    "sg:phone":"+1 416 675 7775",
    "sg:postcode":"M9W 6P6",
    "sg:province":"ON",
    "wof:name":"Global Signs Inc",
    "wof:placetype":"venue"
},
  "geometry": {"coordinates":[-79.6324310303,43.7469787598],"type":"Point"}
}