{
  "type": "Feature",
  "properties": {
    "addr:full":"449 Mount Pleasant Rd Brantford ON N3T 5L5",
    "addr:housenumber":"449",
    "addr:postcode":"n3t 5l5",
    "addr:street":"Mount Pleasant Rd",
    "iso:country":"CA",
    "sg:address":"449 Mount Pleasant Rd",
    "sg:city":"Brantford",
    "sg:classifiers":[
        {
            "category":"Real Estate",
            "subcategory":"Architect",
            "type":"Services"
        }
    ],
    "sg:phone":"+1 519 752 1116",
    "sg:postcode":"N3T 5L5",
    "sg:province":"ON",
    "sg:tags":[
        "illustrator",
        "architectural"
    ],
    "wof:name":"Swanson Design",
    "wof:placetype":"venue"
},
  "geometry": {"coordinates":[-80.27648925779999,43.1145782471],"type":"Point"}
}