{
  "type": "Feature",
  "properties": {
    "addr:full":"1933 Rue Le Chatelier Laval QC H7L 5B3",
    "addr:housenumber":"1933",
    "addr:postcode":"h7l 5b3",
    "addr:street":"Rue Le Chatelier",
    "iso:country":"CA",
    "sg:address":"1933 Rue Le Chatelier",
    "sg:city":"Laval",
    "sg:classifiers":[
        {
            "category":"Manufacturing",
            "subcategory":"Printing",
            "type":"Manufacturing & Wholesale Goods"
        }
    ],
    "sg:phone":"+1 514 990 3221",
    "sg:postcode":"H7L 5B3",
    "sg:province":"QC",
    "sg:tags":[
        "printer"
    ],
    "wof:name":"Imprimerie Papeterie Gibralter",
    "wof:placetype":"venue"
},
  "geometry": {"coordinates":[-73.75759887700001,45.588104248],"type":"Point"}
}