{
  "type": "Feature",
  "properties": {
    "addr:full":"55 Josephine St Wingham ON N0G 2W0",
    "addr:housenumber":"55",
    "addr:postcode":"n0g 2w0",
    "addr:street":"Josephine St",
    "iso:country":"CA",
    "sg:address":"55 Josephine St",
    "sg:city":"Wingham",
    "sg:classifiers":[
        {
            "category":"Shopping",
            "type":"Retail Goods"
        }
    ],
    "sg:phone":"+1 519 357 3490",
    "sg:postcode":"N0G 2W0",
    "sg:province":"ON",
    "sg:tags":[
        "cosmetic",
        "perfume"
    ],
    "wof:name":"Pharma Plus Drugmart",
    "wof:placetype":"venue"
},
  "geometry": {"coordinates":[-81.31646728520001,43.8815994263],"type":"Point"}
}