{
  "type": "Feature",
  "properties": {
    "addr:full":"3 Russell St Leamington ON N8H 1T7",
    "addr:housenumber":"3",
    "addr:postcode":"n8h 1t7",
    "addr:street":"Russell St",
    "iso:country":"CA",
    "sg:address":"3 Russell St",
    "sg:city":"Leamington",
    "sg:classifiers":[
        {
            "category":"Professional",
            "subcategory":"Accounting & Tax Preparation",
            "type":"Services"
        }
    ],
    "sg:phone":"+1 519 325 0380",
    "sg:postcode":"N8H 1T7",
    "sg:province":"ON",
    "sg:tags":[
        "return",
        "filing"
    ],
    "wof:name":"H B Accounting Svc",
    "wof:placetype":"venue"
},
  "geometry": {"coordinates":[-82.600365,42.05143],"type":"Point"}
}