{
  "type": "Feature",
  "properties": {
    "addr:full":"Winnipeg MB R3C 4J9",
    "addr:postcode":"r3c 4j9",
    "iso:country":"CA",
    "sg:city":"Winnipeg",
    "sg:classifiers":[
        {
            "category":"Shopping",
            "subcategory":"Florist",
            "type":"Retail Goods"
        }
    ],
    "sg:phone":"+1 204 949 1579",
    "sg:postcode":"R3C 4J9",
    "sg:province":"MB",
    "wof:name":"Business Is Blooming",
    "wof:placetype":"venue"
},
  "geometry": {"coordinates":[-97.137062,49.887672],"type":"Point"}
}