{
  "type": "Feature",
  "properties": {
    "iso:country":"CA",
    "sg:address":"249 Sherk St",
    "sg:city":"Leamington",
    "sg:classifiers":[
        {
            "category":"Shopping",
            "subcategory":"Clothing, Apparel, & Fashions",
            "type":"Retail Goods"
        }
    ],
    "sg:phone":"+1 519 322 5186",
    "sg:postcode":"N8H 4X7",
    "sg:province":"ON",
    "sg:tags":[
        "sporting"
    ],
    "wof:name":"Bowman Pro Sports",
    "wof:placetype":"venue"
},
  "geometry": {"coordinates":[-82.6055145264,42.04114151],"type":"Point"}
}