{
  "type": "Feature",
  "properties": {
    "addr:full":"3180 American Dr Mississauga ON L4V 1B3",
    "addr:housenumber":"3180",
    "addr:postcode":"l4v 1b3",
    "addr:street":"American Dr",
    "iso:country":"CA",
    "sg:address":"3180 American Dr",
    "sg:city":"Mississauga",
    "sg:classifiers":[
        {
            "category":"Manufacturing",
            "subcategory":"Tools & Machinery",
            "type":"Manufacturing & Wholesale Goods"
        }
    ],
    "sg:phone":"+1 905 677 1571",
    "sg:postcode":"L4V 1B3",
    "sg:province":"ON",
    "sg:tags":[
        "boring",
        "drilling"
    ],
    "wof:name":"Brunner Canada Inc",
    "wof:placetype":"venue"
},
  "geometry": {"coordinates":[-79.617279,43.693012],"type":"Point"}
}