{
  "type": "Feature",
  "properties": {
    "iso:country":"CA",
    "sg:city":"Milton",
    "sg:classifiers":[
        {
            "category":"Building & Trades",
            "subcategory":"Plumbing",
            "type":"Services"
        }
    ],
    "sg:phone":"+1 905 876 1830",
    "sg:postcode":"L9T 3K5",
    "sg:province":"ON",
    "sg:tags":[
        "refrigeration",
        "refrigerating",
        "contractor"
    ],
    "wof:name":"B C Air Systems Ltd",
    "wof:placetype":"venue"
},
  "geometry": {"coordinates":[-79.8780670166,43.5012397766],"type":"Point"}
}