{
  "type": "Feature",
  "properties": {
    "addr:full":"1970 Ospika Blvd S Prince George BC V2N 4W5",
    "addr:housenumber":"1970",
    "addr:postcode":"v2n 4w5",
    "addr:street":"Ospika Blvd S",
    "iso:country":"CA",
    "sg:address":"1970 Ospika Blvd S",
    "sg:city":"Prince George",
    "sg:classifiers":[
        {
            "category":"Bars & Pubs",
            "type":"Food & Drink"
        }
    ],
    "sg:phone":"+1 250 562 0001",
    "sg:postcode":"V2N 4W5",
    "sg:province":"BC",
    "wof:name":"J J's Neighbourhood Pub",
    "wof:placetype":"venue"
},
  "geometry": {"coordinates":[-122.797104,53.906944],"type":"Point"}
}