{
  "type": "Feature",
  "properties": {
    "addr:full":"Saint-Jean-Sur-Richelieu QC J3A 1R7",
    "addr:postcode":"j3a 1r7",
    "iso:country":"CA",
    "sg:city":"Saint-Jean-Sur-Richelieu",
    "sg:classifiers":[
        {
            "category":"Professional",
            "subcategory":"Accounting & Tax Preparation",
            "type":"Services"
        }
    ],
    "sg:phone":"+1 450 359 9898",
    "sg:postcode":"J3A 1R7",
    "sg:province":"QC",
    "sg:tags":[
        "accountant"
    ],
    "wof:name":"90587064 Quebec Inc",
    "wof:placetype":"venue"
},
  "geometry": {"coordinates":[-73.2678146362,45.3365325928],"type":"Point"}
}