{
  "type": "Feature",
  "properties": {
    "addr:full":"1678 Bayview Ave Toronto ON M4G 3C3",
    "addr:housenumber":"1678",
    "addr:postcode":"m4g 3c3",
    "addr:street":"Bayview Ave",
    "iso:country":"CA",
    "sg:address":"1678 Bayview Ave",
    "sg:city":"Toronto",
    "sg:classifiers":[
        {
            "category":"Health Services",
            "subcategory":"Doctor",
            "type":"Services"
        }
    ],
    "sg:phone":"+1 416 489 8072",
    "sg:postcode":"M4G 3C3",
    "sg:province":"ON",
    "sg:tags":[
        "dentist"
    ],
    "wof:name":"Brown, David DDS",
    "wof:placetype":"venue"
},
  "geometry": {"coordinates":[-79.376266,43.708168],"type":"Point"}
}