{
  "type": "Feature",
  "properties": {
    "addr:full":"2070 46th Ave W Vancouver BC V6M 2K9",
    "addr:housenumber":"2070",
    "addr:postcode":"v6m 2k9",
    "addr:street":"46Th Ave W",
    "iso:country":"CA",
    "sg:address":"2070 46th Ave W",
    "sg:city":"Vancouver",
    "sg:classifiers":[
        {
            "category":"Education",
            "subcategory":"Dance Studio",
            "type":"Public Place"
        }
    ],
    "sg:phone":"+1 604 261 5918",
    "sg:postcode":"V6M 2K9",
    "sg:province":"BC",
    "sg:tags":[
        "instruction",
        "dancing"
    ],
    "wof:name":"Lorita Leunge Chinese Dance CO",
    "wof:placetype":"venue"
},
  "geometry": {"coordinates":[-123.154159546,49.2296905518],"type":"Point"}
}