{
  "type": "Feature",
  "properties": {
    "addr:full":"411 Richmond Street East Suite 208 Toronto M5A 3S5",
    "addr:housenumber":"411",
    "addr:postcode":"m5a 3s5",
    "addr:street":"Richmond Street East Suite 208",
    "iso:country":"CA",
    "sg:address":"411 Richmond Street East Suite 208",
    "sg:city":"Toronto",
    "sg:classifiers":[
        {
            "category":"Professional",
            "subcategory":"Computer Services",
            "type":"Services"
        }
    ],
    "sg:postcode":"M5A 3S5",
    "sg:website":"http://www.mdialog.com",
    "wof:name":"mDialog",
    "wof:placetype":"venue"
},
  "geometry": {"coordinates":[-79.364013,43.65455],"type":"Point"}
}