{
  "type": "Feature",
  "properties": {
    "addr:full":"Calgary AB T2P 1C9",
    "addr:postcode":"t2p 1c9",
    "iso:country":"CA",
    "sg:city":"Calgary",
    "sg:classifiers":[
        {
            "category":"Real Estate",
            "subcategory":"Real Estate Agent",
            "type":"Services"
        }
    ],
    "sg:phone":"+1 403 265 9180",
    "sg:postcode":"T2P 1C9",
    "sg:province":"AB",
    "sg:tags":[
        "management"
    ],
    "wof:name":"Colliers International Realty",
    "wof:placetype":"venue"
},
  "geometry": {"coordinates":[-114.06887817400001,51.0455741882],"type":"Point"}
}