{
  "type": "Feature",
  "properties": {
    "addr:full":"147 Simcoe St N Oshawa ON L1G 4S6",
    "addr:housenumber":"147",
    "addr:postcode":"l1g 4s6",
    "addr:street":"Simcoe St N",
    "iso:country":"CA",
    "sg:address":"147 Simcoe St N",
    "sg:city":"Oshawa",
    "sg:classifiers":[
        {
            "category":"Organizations",
            "subcategory":"Religious Organization",
            "type":"Services"
        }
    ],
    "sg:phone":"+1 905 728 8673",
    "sg:postcode":"L1G 4S6",
    "sg:province":"ON",
    "sg:tags":[
        "church"
    ],
    "wof:name":"Knox Presbyterian Church",
    "wof:placetype":"venue"
},
  "geometry": {"coordinates":[-78.865173,43.901455],"type":"Point"}
}