{
  "type": "Feature",
  "properties": {
    "addr:full":"3904 March Rd Carp ON K0A 1L0",
    "addr:housenumber":"3904",
    "addr:postcode":"k0a 1l0",
    "addr:street":"March Rd",
    "iso:country":"CA",
    "sg:address":"3904 March Rd",
    "sg:city":"Carp",
    "sg:classifiers":[
        {
            "category":"Retail",
            "subcategory":"Animal Services",
            "type":"Services"
        }
    ],
    "sg:phone":"+1 613 256 3649",
    "sg:postcode":"K0A 1L0",
    "sg:province":"ON",
    "sg:tags":[
        "pet",
        "grooming",
        "washing"
    ],
    "wof:name":"Bedrock Kennels Ltd",
    "wof:placetype":"venue"
},
  "geometry": {"coordinates":[-76.122528,45.270905],"type":"Point"}
}