{
  "type": "Feature",
  "properties": {
    "addr:full":"6910 Rue Marconi Montreal QC H2S 3K1",
    "addr:housenumber":"6910",
    "addr:postcode":"h2s 3k1",
    "addr:street":"Rue Marconi",
    "iso:country":"CA",
    "sg:address":"6910 Rue Marconi",
    "sg:city":"Montreal",
    "sg:classifiers":[
        {
            "category":"Wholesale",
            "subcategory":"Meat",
            "type":"Manufacturing & Wholesale Goods"
        }
    ],
    "sg:phone":"+1 514 274 9375",
    "sg:postcode":"H2S 3K1",
    "sg:province":"QC",
    "sg:tags":[
        "delicatessen",
        "product",
        "sausage"
    ],
    "wof:name":"Charcuterie Parisienne Inc",
    "wof:placetype":"venue"
},
  "geometry": {"coordinates":[-73.6174697876,45.5307197571],"type":"Point"}
}