{
  "type": "Feature",
  "properties": {
    "addr:full":"801 Central Ave Thunder Bay ON P7B 6P8",
    "addr:housenumber":"801",
    "addr:postcode":"p7b 6p8",
    "addr:street":"Central Ave",
    "iso:country":"CA",
    "sg:address":"801 Central Ave",
    "sg:city":"Thunder Bay",
    "sg:classifiers":[
        {
            "category":"Food & Beverages",
            "subcategory":"Bakery",
            "type":"Retail Goods"
        }
    ],
    "sg:phone":"+1 807 344 3382",
    "sg:postcode":"P7B 6P8",
    "sg:province":"ON",
    "sg:tags":[
        "doughnut"
    ],
    "wof:name":"Robin's Donuts",
    "wof:placetype":"venue"
},
  "geometry": {"coordinates":[-89.264931,48.410847],"type":"Point"}
}