{
  "type": "Feature",
  "properties": {
    "addr:full":"1096 Victoria Rd S Guelph ON N1H 6H8",
    "addr:housenumber":"1096",
    "addr:postcode":"n1h 6h8",
    "addr:street":"Victoria Rd",
    "iso:country":"CA",
    "sg:address":"1096 Victoria Rd S",
    "sg:city":"Guelph",
    "sg:classifiers":[
        {
            "category":"Recreation",
            "type":"Entertainment"
        }
    ],
    "sg:phone":"+1 519 821 2211",
    "sg:postcode":"N1H 6H8",
    "sg:province":"ON",
    "sg:tags":[
        "course",
        "golf"
    ],
    "wof:name":"Victoria Park Golf Club East",
    "wof:placetype":"venue"
},
  "geometry": {"coordinates":[-80.220482,43.549469],"type":"Point"}
}