{
  "type": "Feature",
  "properties": {
    "addr:full":"2001 Second Ave N Williams Lake BC V2G 1Y1",
    "addr:housenumber":"2001",
    "addr:postcode":"v2g 1y1",
    "addr:street":"Second Ave N",
    "iso:country":"CA",
    "sg:address":"2001 Second Ave N",
    "sg:city":"Williams Lake",
    "sg:classifiers":[
        {
            "category":"Autos & Motor Vehicles",
            "subcategory":"Motorcycle Sales",
            "type":"Retail Goods"
        }
    ],
    "sg:phone":"+1 250 392 1010",
    "sg:postcode":"V2G 1Y1",
    "sg:province":"BC",
    "sg:tags":[
        "scooter"
    ],
    "wof:name":"Sonic Cycles",
    "wof:placetype":"venue"
},
  "geometry": {"coordinates":[-122.163398743,52.1470108032],"type":"Point"}
}