{
  "type": "Feature",
  "properties": {
    "addr:full":"108 138 Rte Les Escoumins QC G0T 1K0",
    "addr:housenumber":"138",
    "addr:postcode":"g0t 1k0",
    "addr:street":"Rte",
    "iso:country":"CA",
    "sg:address":"108 138 Rte",
    "sg:city":"Les Escoumins",
    "sg:classifiers":[
        {
            "category":"Home & Garden",
            "subcategory":"Hardware",
            "type":"Retail Goods"
        }
    ],
    "sg:phone":"+1 418 233 2550",
    "sg:postcode":"G0T 1K0",
    "sg:province":"QC",
    "wof:name":"Louis-Philippe Lepage Inc",
    "wof:placetype":"venue"
},
  "geometry": {"coordinates":[-69.4141159058,48.3289833069],"type":"Point"}
}