{
  "type": "Feature",
  "properties": {
    "addr:full":"Boileau QC J0V 1N0",
    "addr:postcode":"j0v 1n0",
    "iso:country":"CA",
    "sg:city":"Boileau",
    "sg:classifiers":[
        {
            "category":"Retail",
            "subcategory":"Repair Shop",
            "type":"Services"
        }
    ],
    "sg:phone":"+1 819 522 6518",
    "sg:postcode":"J0V 1N0",
    "sg:province":"QC",
    "sg:tags":[
        "welding"
    ],
    "wof:name":"Gauthier Soudure",
    "wof:placetype":"venue"
},
  "geometry": {"coordinates":[-74.77294158940001,45.9007835388],"type":"Point"}
}