{
  "type": "Feature",
  "properties": {
    "addr:full":"Edmonton AB T5J 3S9",
    "addr:postcode":"t5j 3s9",
    "iso:country":"CA",
    "sg:city":"Edmonton",
    "sg:classifiers":[
        {
            "category":"Professional",
            "subcategory":"Lawyer & Legal Services",
            "type":"Services"
        }
    ],
    "sg:phone":"+1 780 423 8905",
    "sg:postcode":"T5J 3S9",
    "sg:province":"AB",
    "sg:tags":[
        "attorney"
    ],
    "wof:name":"Ackroyd Piasta Roth & Day",
    "wof:placetype":"venue"
},
  "geometry": {"coordinates":[-113.504059,53.540802],"type":"Point"}
}