{
  "type": "Feature",
  "properties": {
    "addr:full":"Waterloo ON N2J 3H8",
    "addr:postcode":"n2j 3h8",
    "iso:country":"CA",
    "sg:city":"Waterloo",
    "sg:classifiers":[
        {
            "category":"Professional",
            "subcategory":"Accounting & Tax Preparation",
            "type":"Services"
        }
    ],
    "sg:phone":"+1 519 747 0958",
    "sg:postcode":"N2J 3H8",
    "sg:province":"ON",
    "sg:tags":[
        "accountant"
    ],
    "wof:name":"Mc Kerlie Accounting Svc",
    "wof:placetype":"venue"
},
  "geometry": {"coordinates":[-80.521896,43.480057],"type":"Point"}
}