{
  "type": "Feature",
  "properties": {
    "addr:full":"3092 Dominion Rd Ridgeway ON L0S 1N0",
    "addr:housenumber":"3092",
    "addr:postcode":"l0s 1n0",
    "addr:street":"Dominion Rd",
    "iso:country":"CA",
    "sg:address":"3092 Dominion Rd",
    "sg:city":"Ridgeway",
    "sg:classifiers":[
        {
            "category":"Personal",
            "subcategory":"Beauty Salon",
            "type":"Services"
        }
    ],
    "sg:phone":"+1 905 894 5024",
    "sg:postcode":"L0S 1N0",
    "sg:province":"ON",
    "wof:name":"Roots Hair Design",
    "wof:placetype":"venue"
},
  "geometry": {"coordinates":[-79.030739,42.88538],"type":"Point"}
}