{
  "type": "Feature",
  "properties": {
    "addr:full":"19 Rue Morin Sainte-Adele QC J8B 2P5",
    "addr:housenumber":"19",
    "addr:postcode":"j8b 2p5",
    "addr:street":"Rue Morin",
    "iso:country":"CA",
    "sg:address":"19 Rue Morin",
    "sg:city":"Sainte-Adele",
    "sg:classifiers":[
        {
            "category":"Shopping",
            "subcategory":"Tobacco",
            "type":"Retail Goods"
        }
    ],
    "sg:phone":"+1 450 229 2724",
    "sg:postcode":"J8B 2P5",
    "sg:province":"QC",
    "sg:tags":[
        "cigarette",
        "cigar",
        "dealer"
    ],
    "wof:name":"Calumet",
    "wof:placetype":"venue"
},
  "geometry": {"coordinates":[-74.136177,45.951637],"type":"Point"}
}