{
  "type": "Feature",
  "properties": {
    "iso:country":"CA",
    "sg:address":"149 Hwy 132 O",
    "sg:city":"Caplan",
    "sg:classifiers":[
        {
            "category":"Health Services",
            "subcategory":"Doctor",
            "type":"Services"
        }
    ],
    "sg:phone":"+1 418 388 2201",
    "sg:postcode":"G0C 1H0",
    "sg:province":"QC",
    "sg:tags":[
        "clinic"
    ],
    "wof:name":"Clinique Medicale Caplan Inc",
    "wof:placetype":"venue"
},
  "geometry": {"coordinates":[-65.67924499510001,48.1011810303],"type":"Point"}
}