{
  "type": "Feature",
  "properties": {
    "addr:full":"45 Rue Notre-Dame O Cap-Chat QC G0J 1E0",
    "addr:housenumber":"45",
    "addr:postcode":"g0j 1e0",
    "addr:street":"Rue Notre-Dame O",
    "iso:country":"CA",
    "sg:address":"45 Rue Notre-Dame O",
    "sg:city":"Cap-Chat",
    "sg:classifiers":[
        {
            "category":"Professional",
            "subcategory":"Business Services",
            "type":"Services"
        }
    ],
    "sg:phone":"+1 418 786 2040",
    "sg:postcode":"G0J 1E0",
    "sg:province":"QC",
    "sg:tags":[
        "notary"
    ],
    "wof:name":"Bernier St-Laurent Bouffard",
    "wof:placetype":"venue"
},
  "geometry": {"coordinates":[-66.687210083,49.0974578857],"type":"Point"}
}