{
  "type": "Feature",
  "properties": {
    "addr:full":"3159 Rue Laval Lac-Megantic QC G6B 1A5",
    "addr:housenumber":"3159",
    "addr:postcode":"g6b 1a5",
    "addr:street":"Rue Laval Lac-Megantic",
    "iso:country":"CA",
    "sg:address":"3159 Rue Laval",
    "sg:city":"Lac-Megantic",
    "sg:classifiers":[
        {
            "category":"Organizations",
            "subcategory":"Professional Association",
            "type":"Services"
        }
    ],
    "sg:phone":"+1 819 583 4333",
    "sg:postcode":"G6B 1A5",
    "sg:province":"QC",
    "wof:name":"Ordre Loyal Des Moose Loge",
    "wof:placetype":"venue"
},
  "geometry": {"coordinates":[-70.9115219116,45.5929069519],"type":"Point"}
}