{
  "type": "Feature",
  "properties": {
    "iso:country":"CA",
    "sg:address":"2270 Braeside Ave",
    "sg:city":"Ottawa",
    "sg:classifiers":[
        {
            "category":"Social Services",
            "type":"Services"
        }
    ],
    "sg:phone":"+1 613 521 5151",
    "sg:postcode":"K1H 7J7",
    "sg:province":"ON",
    "sg:tags":[
        "senior",
        "citizen"
    ],
    "wof:name":"Ellwood House",
    "wof:placetype":"venue"
},
  "geometry": {"coordinates":[-75.660622,45.384167],"type":"Point"}
}