{
  "type": "Feature",
  "properties": {
    "addr:full":"Edmonton AB T5G 2W3",
    "addr:postcode":"t5g 2w3",
    "iso:country":"CA",
    "sg:city":"Edmonton",
    "sg:classifiers":[
        {
            "category":"Manufacturing",
            "subcategory":"Metals",
            "type":"Manufacturing & Wholesale Goods"
        }
    ],
    "sg:phone":"+1 780 477 5400",
    "sg:postcode":"T5G 2W3",
    "sg:province":"AB",
    "sg:tags":[
        "downspouts",
        "barrels",
        "gutter",
        "drum"
    ],
    "wof:name":"Alberta Eavestroughing Ltd",
    "wof:placetype":"venue"
},
  "geometry": {"coordinates":[-113.53310399999999,53.568192],"type":"Point"}
}