{
  "type": "Feature",
  "properties": {
    "addr:full":"Surrey BC V3R 0V7",
    "addr:postcode":"v3r 0v7",
    "iso:country":"CA",
    "sg:city":"Surrey",
    "sg:classifiers":[
        {
            "category":"Health Services",
            "subcategory":"Doctor",
            "type":"Services"
        }
    ],
    "sg:phone":"+1 604 589 7272",
    "sg:postcode":"V3R 0V7",
    "sg:province":"BC",
    "sg:tags":[
        "dentist"
    ],
    "wof:name":"Kaeley, Manbinder DDS",
    "wof:placetype":"venue"
},
  "geometry": {"coordinates":[-122.830215454,49.105178833],"type":"Point"}
}