{
  "type": "Feature",
  "properties": {
    "addr:full":"228 Division St N Kingsville ON N9Y 1E4",
    "addr:housenumber":"228",
    "addr:postcode":"n9y 1e4",
    "addr:street":"Division St N",
    "iso:country":"CA",
    "sg:address":"228 Division St N",
    "sg:city":"Kingsville",
    "sg:classifiers":[
        {
            "category":"Retail",
            "subcategory":"Veterinary Services",
            "type":"Services"
        }
    ],
    "sg:phone":"+1 519 733 5450",
    "sg:postcode":"N9Y 1E4",
    "sg:province":"ON",
    "sg:tags":[
        "veterinarian"
    ],
    "wof:name":"Kingsville Animal Clinic",
    "wof:placetype":"venue"
},
  "geometry": {"coordinates":[-82.739143,42.045658],"type":"Point"}
}