{
  "type": "Feature",
  "properties": {
    "addr:full":"Brigden ON N0N 1B0",
    "addr:postcode":"n0n 1b0",
    "iso:country":"CA",
    "sg:city":"Brigden",
    "sg:classifiers":[
        {
            "category":"Personal",
            "subcategory":"Beauty Salon",
            "type":"Services"
        }
    ],
    "sg:phone":"+1 519 864 4122",
    "sg:postcode":"N0N 1B0",
    "sg:province":"ON",
    "wof:name":"Madeleine's Hair Ctr",
    "wof:placetype":"venue"
},
  "geometry": {"coordinates":[-82.28271484379999,42.8136291504],"type":"Point"}
}