{
  "type": "Feature",
  "properties": {
    "addr:full":"80 King St E Dundas ON L9H 1C2",
    "addr:housenumber":"80",
    "addr:postcode":"l9h 1c2",
    "addr:street":"King St E",
    "iso:country":"CA",
    "sg:address":"80 King St E",
    "sg:city":"Dundas",
    "sg:classifiers":[
        {
            "category":"Building & Trades",
            "subcategory":"Landscaping Services",
            "type":"Services"
        }
    ],
    "sg:phone":"+1 905 627 8424",
    "sg:postcode":"L9H 1C2",
    "sg:province":"ON",
    "sg:tags":[
        "landscape",
        "contractor"
    ],
    "wof:name":"Owens Landscaping Svc",
    "wof:placetype":"venue"
},
  "geometry": {"coordinates":[-79.948532,43.265774],"type":"Point"}
}