{
  "type": "Feature",
  "properties": {
    "addr:full":"Toronto ON M4P 1E4",
    "addr:postcode":"m4p 1e4",
    "iso:country":"CA",
    "sg:city":"Toronto",
    "sg:classifiers":[
        {
            "category":"Banks & Credit Unions",
            "subcategory":"Investment Brokerage",
            "type":"Services"
        }
    ],
    "sg:phone":"+1 416 945 4840",
    "sg:postcode":"M4P 1E4",
    "sg:province":"ON",
    "wof:name":"Scotia Mc Leod Inc",
    "wof:placetype":"venue"
},
  "geometry": {"coordinates":[-79.3986663818,43.7072372437],"type":"Point"}
}