{
  "type": "Feature",
  "properties": {
    "addr:full":"Duncan BC V9L 1N8",
    "addr:postcode":"v9l 1n8",
    "iso:country":"CA",
    "sg:city":"Duncan",
    "sg:classifiers":[
        {
            "category":"Social Services",
            "type":"Services"
        }
    ],
    "sg:phone":"+1 250 748 2447",
    "sg:postcode":"V9L 1N8",
    "sg:province":"BC",
    "sg:tags":[
        "organization",
        "welfare"
    ],
    "wof:name":"Big Brothers Big Sisters",
    "wof:placetype":"venue"
},
  "geometry": {"coordinates":[-123.709023,48.7794],"type":"Point"}
}