{
  "type": "Feature",
  "properties": {
    "iso:country":"CA",
    "sg:city":"Windsor",
    "sg:classifiers":[
        {
            "category":"Manufacturing",
            "subcategory":"Furniture",
            "type":"Manufacturing & Wholesale Goods"
        }
    ],
    "sg:phone":"+1 519 944 5730",
    "sg:postcode":"N8W 5R8",
    "sg:province":"ON",
    "wof:name":"International Seating & Decor",
    "wof:placetype":"venue"
},
  "geometry": {"coordinates":[-82.95812225340001,42.2847709656],"type":"Point"}
}