{
  "type": "Feature",
  "properties": {
    "addr:full":"1009 5th Ave Beaverlodge AB T0H 0C0",
    "addr:housenumber":"1009",
    "addr:postcode":"t0h 0c0",
    "addr:street":"5Th Ave",
    "iso:country":"CA",
    "sg:address":"1009 5th Ave",
    "sg:city":"Beaverlodge",
    "sg:classifiers":[
        {
            "category":"Education",
            "subcategory":"School",
            "type":"Public Place"
        }
    ],
    "sg:phone":"+1 780 354 2446",
    "sg:postcode":"T0H 0C0",
    "sg:province":"AB",
    "wof:name":"Beaverlodge Elementary School",
    "wof:placetype":"venue"
},
  "geometry": {"coordinates":[-119.423286,55.212254],"type":"Point"}
}