{
  "type": "Feature",
  "properties": {
    "addr:full":"1901 Stisted Rd N Sprucedale ON P0A 1Y0",
    "addr:housenumber":"1901",
    "addr:postcode":"p0a 1y0",
    "addr:street":"Stisted Rd N Sprucedale",
    "iso:country":"CA",
    "sg:address":"1901 Stisted Rd N",
    "sg:city":"Sprucedale",
    "sg:classifiers":[
        {
            "category":"Retail",
            "subcategory":"Auto Repair",
            "type":"Services"
        }
    ],
    "sg:phone":"+1 705 685 7242",
    "sg:postcode":"P0A 1Y0",
    "sg:province":"ON",
    "sg:tags":[
        "repairing",
        "automobile"
    ],
    "wof:name":"Sharwood Transportation Ltd",
    "wof:placetype":"venue"
},
  "geometry": {"coordinates":[-79.464088,45.491779],"type":"Point"}
}