{
  "type": "Feature",
  "properties": {
    "addr:full":"195 Boul Hymus Pointe-Claire QC H9R 1E9",
    "addr:housenumber":"195",
    "addr:postcode":"h9r 1e9",
    "addr:street":"Boul Hymus",
    "iso:country":"CA",
    "sg:address":"195 Boul Hymus",
    "sg:city":"Pointe-Claire",
    "sg:classifiers":[
        {
            "category":"Shopping",
            "subcategory":"Department Store",
            "type":"Retail Goods"
        }
    ],
    "sg:phone":"+1 514 694 5990",
    "sg:postcode":"H9R 1E9",
    "sg:province":"QC",
    "wof:name":"Zellers",
    "wof:placetype":"venue"
},
  "geometry": {"coordinates":[-73.81925964360001,45.4607086182],"type":"Point"}
}