{
  "type": "Feature",
  "properties": {
    "iso:country":"CA",
    "sg:address":"999 Upper Wentworth St",
    "sg:city":"Hamilton",
    "sg:classifiers":[
        {
            "category":"Shopping",
            "type":"Retail Goods"
        }
    ],
    "sg:phone":"+1 905 575 9900",
    "sg:postcode":"L9A 4X5",
    "sg:province":"ON",
    "sg:tags":[
        "telephone",
        "cellular"
    ],
    "wof:name":"Bell World",
    "wof:placetype":"venue"
},
  "geometry": {"coordinates":[-79.8644485474,43.2167167664],"type":"Point"}
}