{
  "type": "Feature",
  "properties": {
    "iso:country":"CA",
    "sg:city":"Nepean",
    "sg:classifiers":[
        {
            "category":"Food & Beverages",
            "subcategory":"Groceries & Convenience Stores",
            "type":"Retail Goods"
        }
    ],
    "sg:phone":"+1 613 820 3896",
    "sg:postcode":"K2H 5H2",
    "sg:province":"ON",
    "wof:name":"Crystal Liu Grocery Store",
    "wof:placetype":"venue"
},
  "geometry": {"coordinates":[-75.709022522,45.3146705627],"type":"Point"}
}