{
  "type": "Feature",
  "properties": {
    "addr:full":"26 Rowland Cres St Albert AB T8N 5B3",
    "addr:housenumber":"26",
    "addr:postcode":"t8n 5b3",
    "addr:street":"Rowland Cres",
    "iso:country":"CA",
    "sg:address":"26 Rowland Cres",
    "sg:city":"St Albert",
    "sg:classifiers":[
        {
            "category":"Home & Garden",
            "subcategory":"Furniture",
            "type":"Retail Goods"
        }
    ],
    "sg:phone":"+1 780 418 1528",
    "sg:postcode":"T8N 5B3",
    "sg:province":"AB",
    "sg:tags":[
        "builder",
        "custom"
    ],
    "wof:name":"Eas Inc",
    "wof:placetype":"venue"
},
  "geometry": {"coordinates":[-113.644356,53.617928],"type":"Point"}
}