{
  "type": "Feature",
  "properties": {
    "addr:full":"814 Michel Rd #7 Elkford BC V0B 1H0",
    "addr:housenumber":"814",
    "addr:postcode":"bc v0b 1h0",
    "addr:street":"Michel Rd # 7",
    "iso:country":"CA",
    "sg:address":"814 Michel Rd #7",
    "sg:city":"Elkford",
    "sg:classifiers":[
        {
            "category":"Health Services",
            "subcategory":"Doctor",
            "type":"Services"
        }
    ],
    "sg:phone":"+1 250 865 4344",
    "sg:postcode":"V0B 1H0",
    "sg:province":"BC",
    "sg:tags":[
        "dentist"
    ],
    "wof:name":"Elkford Dental Ctr",
    "wof:placetype":"venue"
},
  "geometry": {"coordinates":[-114.920158,50.024826],"type":"Point"}
}