{
  "type": "Feature",
  "properties": {
    "addr:full":"62 St. Peters Rd Charlottetown PE C1A 5N8",
    "addr:housenumber":"62",
    "addr:postcode":"c1a 5n8",
    "addr:street":"St. Peters Rd",
    "iso:country":"CA",
    "sg:address":"62 St. Peters Rd",
    "sg:city":"Charlottetown",
    "sg:classifiers":[
        {
            "category":"Wholesale",
            "subcategory":"Seafood",
            "type":"Manufacturing & Wholesale Goods"
        }
    ],
    "sg:phone":"+1 902 628 6674",
    "sg:postcode":"C1A 5N8",
    "sg:province":"PE",
    "wof:name":"Maritime Marketing Svc",
    "wof:placetype":"venue"
},
  "geometry": {"coordinates":[-63.1215515137,46.2513389587],"type":"Point"}
}