{
  "type": "Feature",
  "properties": {
    "iso:country":"CA",
    "sg:address":"655 Colborne St",
    "sg:city":"Brantford",
    "sg:classifiers":[
        {
            "category":"Food & Beverages",
            "subcategory":"Groceries & Convenience Stores",
            "type":"Retail Goods"
        }
    ],
    "sg:phone":"+1 519 751 9128",
    "sg:postcode":"N3S 3M8",
    "sg:province":"ON",
    "sg:tags":[
        "grocer"
    ],
    "wof:name":"Price Chopper",
    "wof:placetype":"venue"
},
  "geometry": {"coordinates":[-80.238129,43.140907],"type":"Point"}
}