{
  "type": "Feature",
  "properties": {
    "addr:full":"446 King Rd Richmond Hill ON L4E 2Y8",
    "addr:housenumber":"446",
    "addr:postcode":"l4e 2y8",
    "addr:street":"King Rd",
    "iso:country":"CA",
    "sg:address":"446 King Rd",
    "sg:city":"Richmond Hill",
    "sg:classifiers":[
        {
            "category":"Retail",
            "subcategory":"Repair Shop",
            "type":"Services"
        }
    ],
    "sg:phone":"+1 905 773 3911",
    "sg:postcode":"L4E 2Y8",
    "sg:province":"ON",
    "sg:tags":[
        "upholsterer"
    ],
    "wof:name":"Top Quality Interiors",
    "wof:placetype":"venue"
},
  "geometry": {"coordinates":[-79.4711761475,43.9412536621],"type":"Point"}
}