{
  "type": "Feature",
  "properties": {
    "addr:full":"5130 60th Ave NE Canoe BC V0E 1K0",
    "addr:housenumber":"5130",
    "addr:postcode":"v0e 1k0",
    "addr:street":"60Th Ave Ne",
    "iso:country":"CA",
    "sg:address":"5130 60th Ave NE",
    "sg:city":"Canoe",
    "sg:classifiers":[
        {
            "category":"Autos & Motor Vehicles",
            "subcategory":"Boat Sales",
            "type":"Retail Goods"
        }
    ],
    "sg:phone":"+1 250 832 1054",
    "sg:postcode":"V0E 1K0",
    "sg:province":"BC",
    "sg:tags":[
        "dealer"
    ],
    "wof:name":"Randy's Marine Svc",
    "wof:placetype":"venue"
},
  "geometry": {"coordinates":[-119.078903,50.789959],"type":"Point"}
}