{
  "type": "Feature",
  "properties": {
    "addr:full":"1020 Ch Olivier Saint-Nicolas QC G7A 2M7",
    "addr:postcode":"1020;g7a 2m7",
    "addr:street":"Ch Olivier",
    "iso:country":"CA",
    "sg:address":"1020 Ch Olivier",
    "sg:city":"Saint-Nicolas",
    "sg:classifiers":[
        {
            "category":"Home & Garden",
            "subcategory":"Building Materials",
            "type":"Retail Goods"
        }
    ],
    "sg:phone":"+1 418 836 4826",
    "sg:postcode":"G7A 2M7",
    "sg:province":"QC",
    "sg:tags":[
        "floor"
    ],
    "wof:name":"Groupe Materiaux A Bas Prix",
    "wof:placetype":"venue"
},
  "geometry": {"coordinates":[-71.328613,46.684582],"type":"Point"}
}