{
  "type": "Feature",
  "properties": {
    "addr:full":"Hubley Plaza St Margaret Village NS B0C 1R0",
    "addr:postcode":"b0c 1r0",
    "addr:street":"Plaza St",
    "iso:country":"CA",
    "sg:address":"Hubley Plaza",
    "sg:city":"St Margaret Village",
    "sg:classifiers":[
        {
            "category":"Personal",
            "type":"Services"
        }
    ],
    "sg:phone":"+1 902 876 1099",
    "sg:postcode":"B0C 1R0",
    "sg:province":"NS",
    "sg:tags":[
        "electrolysis"
    ],
    "wof:name":"First Impressions Electrolysis",
    "wof:placetype":"venue"
},
  "geometry": {"coordinates":[-60.4704475403,46.9865150452],"type":"Point"}
}