{
  "type": "Feature",
  "properties": {
    "addr:full":"435 Quebec St Prince George BC V2L 1W5",
    "addr:housenumber":"435",
    "addr:postcode":"v2l 1w5",
    "addr:street":"Quebec St",
    "iso:country":"CA",
    "sg:address":"435 Quebec St",
    "sg:city":"Prince George",
    "sg:classifiers":[
        {
            "category":"Personal",
            "type":"Services"
        }
    ],
    "sg:phone":"+1 250 562 7800",
    "sg:postcode":"V2L 1W5",
    "sg:province":"BC",
    "sg:tags":[
        "therapist",
        "massage"
    ],
    "wof:name":"Cryderman, Jim",
    "wof:placetype":"venue"
},
  "geometry": {"coordinates":[-122.747108459,53.9159965515],"type":"Point"}
}