{
  "type": "Feature",
  "properties": {
    "addr:full":"45 Jarvis St Fort Erie ON L2A 2S3",
    "addr:housenumber":"45",
    "addr:postcode":"l2a 2s3",
    "addr:street":"Jarvis St",
    "iso:country":"CA",
    "sg:address":"45 Jarvis St",
    "sg:city":"Fort Erie",
    "sg:classifiers":[
        {
            "category":"Professional",
            "subcategory":"Management & Consulting",
            "type":"Services"
        }
    ],
    "sg:phone":"+1 905 871 7331",
    "sg:postcode":"L2A 2S3",
    "sg:province":"ON",
    "sg:tags":[
        "consultant",
        "business"
    ],
    "wof:name":"Business Development Ctr",
    "wof:placetype":"venue"
},
  "geometry": {"coordinates":[-78.91651899999999,42.929665],"type":"Point"}
}