{
  "type": "Feature",
  "properties": {
    "addr:full":"257 Rue Queen Lennoxville QC J1M 1K7",
    "addr:housenumber":"257",
    "addr:postcode":"j1m 1k7",
    "addr:street":"Rue Queen",
    "iso:country":"CA",
    "sg:address":"257 Rue Queen",
    "sg:city":"Lennoxville",
    "sg:classifiers":[
        {
            "category":"Social Services",
            "subcategory":"Job Training",
            "type":"Services"
        }
    ],
    "sg:phone":"+1 819 566 2422",
    "sg:postcode":"J1M 1K7",
    "sg:province":"QC",
    "sg:tags":[
        "employment"
    ],
    "wof:name":"Job Links",
    "wof:placetype":"venue"
},
  "geometry": {"coordinates":[-71.8617019653,45.3746833801],"type":"Point"}
}