{
  "type": "Feature",
  "properties": {
    "addr:full":"22 Lincoln Rd Grand Falls-Windsor NL A2A 1M8",
    "addr:housenumber":"22",
    "addr:postcode":"a2a 1m8",
    "addr:street":"Lincoln Rd",
    "iso:country":"CA",
    "sg:address":"22 Lincoln Rd",
    "sg:city":"Grand Falls-Windsor",
    "sg:classifiers":[
        {
            "category":"Restaurant",
            "type":"Food & Drink"
        }
    ],
    "sg:phone":"+1 709 489 9899",
    "sg:postcode":"A2A 1M8",
    "sg:province":"NL",
    "wof:name":"King City Restaurant",
    "wof:placetype":"venue"
},
  "geometry": {"coordinates":[-55.666321,48.943695],"type":"Point"}
}