{
  "type": "Feature",
  "properties": {
    "addr:full":"225 Davis St Sarnia ON N7T 1B2",
    "addr:housenumber":"225",
    "addr:postcode":"n7t 1b2",
    "addr:street":"Davis St",
    "iso:country":"CA",
    "sg:address":"225 Davis St",
    "sg:city":"Sarnia",
    "sg:classifiers":[
        {
            "category":"Health Services",
            "subcategory":"Health Practitioner",
            "type":"Services"
        }
    ],
    "sg:phone":"+1 519 344 7581",
    "sg:postcode":"N7T 1B2",
    "sg:province":"ON",
    "sg:tags":[
        "physiotherapist"
    ],
    "wof:name":"Sam Shuqair Physiotherapy",
    "wof:placetype":"venue"
},
  "geometry": {"coordinates":[-82.40264129640001,42.9705314636],"type":"Point"}
}