{
  "type": "Feature",
  "properties": {
    "addr:full":"205 Centre St Meadow Lake SK S9X 1L5",
    "addr:housenumber":"205",
    "addr:postcode":"s9x 1l5",
    "addr:street":"Centre St",
    "iso:country":"CA",
    "sg:address":"205 Centre St",
    "sg:city":"Meadow Lake",
    "sg:classifiers":[
        {
            "category":"Recreation",
            "type":"Entertainment"
        }
    ],
    "sg:phone":"+1 306 236 3766",
    "sg:postcode":"S9X 1L5",
    "sg:province":"SK",
    "sg:tags":[
        "center"
    ],
    "wof:name":"North West Friendship Ctr",
    "wof:placetype":"venue"
},
  "geometry": {"coordinates":[-108.432197571,54.1199455261],"type":"Point"}
}