{
  "type": "Feature",
  "properties": {
    "iso:country":"CA",
    "sg:address":"4612 95 St NW",
    "sg:city":"Edmonton",
    "sg:classifiers":[
        {
            "category":"Building & Trades",
            "subcategory":"Equipment Rental",
            "type":"Services"
        }
    ],
    "sg:phone":"+1 780 448 2088",
    "sg:postcode":"T6E 5Z6",
    "sg:province":"AB",
    "sg:tags":[
        "leasing"
    ],
    "wof:name":"Next To New Leasing Ltd",
    "wof:placetype":"venue"
},
  "geometry": {"coordinates":[-113.47598266599999,53.484375],"type":"Point"}
}