{
  "type": "Feature",
  "properties": {
    "addr:full":"951 Gordon St # 3 Guelph ON N1G 4S1",
    "addr:housenumber":"951",
    "addr:postcode":"n1g 4s1",
    "addr:street":"Gordon St # 3",
    "iso:country":"CA",
    "sg:address":"951 Gordon St # 3",
    "sg:city":"Guelph",
    "sg:classifiers":[
        {
            "category":"Travel",
            "subcategory":"Travel Agent",
            "type":"Entertainment"
        }
    ],
    "sg:phone":"+1 519 836 0061",
    "sg:postcode":"N1G 4S1",
    "sg:province":"ON",
    "sg:tags":[
        "agency",
        "bureau"
    ],
    "wof:name":"Frederick Travel",
    "wof:placetype":"venue"
},
  "geometry": {"coordinates":[-80.21389000000001,43.522514],"type":"Point"}
}