{
  "type": "Feature",
  "properties": {
    "addr:full":"2434 Rue Saint-Cesaire Marieville QC J3M 1N2",
    "addr:housenumber":"2434",
    "addr:postcode":"j3m 1n2",
    "addr:street":"Rue Saint-Cesaire",
    "iso:country":"CA",
    "sg:address":"2434 Rue Saint-Cesaire",
    "sg:city":"Marieville",
    "sg:classifiers":[
        {
            "category":"Wholesale",
            "subcategory":"Hardware",
            "type":"Manufacturing & Wholesale Goods"
        }
    ],
    "sg:phone":"+1 450 460 7241",
    "sg:postcode":"J3M 1N2",
    "sg:province":"QC",
    "sg:tags":[
        "refrigerating"
    ],
    "wof:name":"Refrigeration Lacoste Inc",
    "wof:placetype":"venue"
},
  "geometry": {"coordinates":[-73.13408699999999,45.432606],"type":"Point"}
}