{
  "type": "Feature",
  "properties": {
    "addr:full":"1577 Lawrence Ave W North York ON M6L 1C4",
    "addr:housenumber":"1577",
    "addr:postcode":"m6l 1c4",
    "addr:street":"Lawrence Ave W",
    "iso:country":"CA",
    "sg:address":"1577 Lawrence Ave W",
    "sg:city":"North York",
    "sg:classifiers":[
        {
            "category":"Real Estate",
            "subcategory":"Real Estate Operator",
            "type":"Services"
        }
    ],
    "sg:phone":"+1 416 614 8104",
    "sg:postcode":"M6L 1C4",
    "sg:province":"ON",
    "sg:tags":[
        "apartment"
    ],
    "wof:name":"Wynn Family Properties",
    "wof:placetype":"venue"
},
  "geometry": {"coordinates":[-79.48820499999999,43.706131],"type":"Point"}
}