{
  "type": "Feature",
  "properties": {
    "iso:country":"CA",
    "sg:address":"301 Durham St E",
    "sg:city":"Walkerton",
    "sg:classifiers":[
        {
            "category":"Travel",
            "subcategory":"Travel Agent",
            "type":"Entertainment"
        }
    ],
    "sg:phone":"+1 519 881 3120",
    "sg:postcode":"N0G 2V0",
    "sg:province":"ON",
    "sg:tags":[
        "agency",
        "bureau"
    ],
    "wof:name":"Wide World Travel & Tour Svc",
    "wof:placetype":"venue"
},
  "geometry": {"coordinates":[-81.1484298706,44.1329994202],"type":"Point"}
}