{
  "type": "Feature",
  "properties": {
    "addr:full":"15802 111 Ave NW Edmonton AB T5M 2R8",
    "addr:housenumber":"15802",
    "addr:postcode":"t5m 2r8",
    "addr:street":"111 Ave Nw",
    "iso:country":"CA",
    "sg:address":"15802 111 Ave NW",
    "sg:city":"Edmonton",
    "sg:classifiers":[
        {
            "category":"Autos & Motor Vehicles",
            "subcategory":"Auto Supplies",
            "type":"Retail Goods"
        }
    ],
    "sg:phone":"+1 780 454 2223",
    "sg:postcode":"T5M 2R8",
    "sg:province":"AB",
    "sg:tags":[
        "automobile",
        "accessory"
    ],
    "wof:name":"Four Wheel Parts Performance",
    "wof:placetype":"venue"
},
  "geometry": {"coordinates":[-113.594742,53.559303],"type":"Point"}
}