{
  "type": "Feature",
  "properties": {
    "iso:country":"CA",
    "sg:address":"767 Rue Paul-Desruisseaux",
    "sg:city":"Sherbrooke",
    "sg:classifiers":[
        {
            "category":"Professional",
            "subcategory":"Accounting & Tax Preparation",
            "type":"Services"
        }
    ],
    "sg:phone":"+1 819 564 1432",
    "sg:postcode":"J1J 4L9",
    "sg:province":"QC",
    "sg:tags":[
        "bookkeeping",
        "return",
        "filing",
        "general"
    ],
    "wof:name":"Services Financiers-L'Estrie",
    "wof:placetype":"venue"
},
  "geometry": {"coordinates":[-71.9312667847,45.4098129272],"type":"Point"}
}