{
  "type": "Feature",
  "properties": {
    "iso:country":"CA",
    "sg:address":"400 Esna Park Dr # 4",
    "sg:city":"Markham",
    "sg:classifiers":[
        {
            "category":"Wholesale",
            "subcategory":"Apparel",
            "type":"Manufacturing & Wholesale Goods"
        }
    ],
    "sg:phone":"+1 905 940 2307",
    "sg:postcode":"L3R 3K2",
    "sg:province":"ON",
    "sg:tags":[
        "textile"
    ],
    "wof:name":"N N Intl",
    "wof:placetype":"venue"
},
  "geometry": {"coordinates":[-79.33558654789999,43.8221054077],"type":"Point"}
}