{
  "type": "Feature",
  "properties": {
    "addr:full":"423 Rue DE LA Riviere Cowansville QC J2K 1N4",
    "addr:housenumber":"423",
    "addr:postcode":"j2k 1n4",
    "addr:street":"Rue De La Riviere",
    "iso:country":"CA",
    "sg:address":"423 Rue DE LA Riviere",
    "sg:city":"Cowansville",
    "sg:classifiers":[
        {
            "category":"Recreation",
            "type":"Entertainment"
        }
    ],
    "sg:phone":"+1 450 263 3553",
    "sg:postcode":"J2K 1N4",
    "sg:province":"QC",
    "sg:tags":[
        "parlor",
        "billiard"
    ],
    "wof:name":"Bar Salon Billard-Cowansville",
    "wof:placetype":"venue"
},
  "geometry": {"coordinates":[-72.76823400000001,45.210182],"type":"Point"}
}