{
  "type": "Feature",
  "properties": {
    "addr:full":"234 Rue Dufferin Sherbrooke QC J1H 4M2",
    "addr:housenumber":"234",
    "addr:postcode":"j1h 4m2",
    "addr:street":"Rue Dufferin",
    "iso:country":"CA",
    "sg:address":"234 Rue Dufferin",
    "sg:city":"Sherbrooke",
    "sg:classifiers":[
        {
            "category":"Health Services",
            "subcategory":"Doctor",
            "type":"Services"
        }
    ],
    "sg:phone":"+1 819 821 2297",
    "sg:postcode":"J1H 4M2",
    "sg:province":"QC",
    "sg:tags":[
        "physician",
        "surgeon",
        "attorney"
    ],
    "wof:name":"Clinqiue Medico-Legale",
    "wof:placetype":"venue"
},
  "geometry": {"coordinates":[-71.89408899999999,45.405159],"type":"Point"}
}