{
  "type": "Feature",
  "properties": {
    "addr:full":"9200 Rue DE L'Innovation Anjou QC H1J 2X9",
    "addr:housenumber":"9200",
    "addr:postcode":"h1j 2x9",
    "addr:street":"Rue De L'Innovation",
    "iso:country":"CA",
    "sg:address":"9200 Rue DE L'Innovation",
    "sg:city":"Anjou",
    "sg:classifiers":[
        {
            "category":"Education",
            "subcategory":"School",
            "type":"Public Place"
        }
    ],
    "sg:phone":"+1 514 353 0801",
    "sg:postcode":"H1J 2X9",
    "sg:province":"QC",
    "wof:name":"Centre DE Formation Des Metier",
    "wof:placetype":"venue"
},
  "geometry": {"coordinates":[-73.55801391599999,45.6191482544],"type":"Point"}
}