{
  "type": "Feature",
  "properties": {
    "addr:full":"808 Michel Rd Elkford BC V0B 1H0",
    "addr:housenumber":"808",
    "addr:postcode":"bc v0b 1h0",
    "addr:street":"Michel Rd",
    "iso:country":"CA",
    "sg:address":"808 Michel Rd",
    "sg:city":"Elkford",
    "sg:classifiers":[
        {
            "category":"Travel",
            "subcategory":"Hotels & Motels",
            "type":"Entertainment"
        }
    ],
    "sg:phone":"+1 250 865 2211",
    "sg:postcode":"V0B 1H0",
    "sg:province":"BC",
    "wof:name":"Elkford Motor Inn",
    "wof:placetype":"venue"
},
  "geometry": {"coordinates":[-114.919479,50.024956],"type":"Point"}
}