{
  "type": "Feature",
  "properties": {
    "addr:full":"Vancouver BC V6M 4H3",
    "addr:postcode":"v6m 4h3",
    "iso:country":"CA",
    "sg:city":"Vancouver",
    "sg:classifiers":[
        {
            "category":"Real Estate",
            "subcategory":"Real Estate Agent",
            "type":"Services"
        }
    ],
    "sg:phone":"+1 604 263 1433",
    "sg:postcode":"V6M 4H3",
    "sg:province":"BC",
    "wof:name":"Sutton Group Heritage West",
    "wof:placetype":"venue"
},
  "geometry": {"coordinates":[-123.155731,49.236351],"type":"Point"}
}