{
  "type": "Feature",
  "properties": {
    "iso:country":"CA",
    "sg:address":"19 Glendinning Ave",
    "sg:city":"Scarborough",
    "sg:classifiers":[
        {
            "category":"Food & Beverages",
            "subcategory":"Groceries & Convenience Stores",
            "type":"Retail Goods"
        }
    ],
    "sg:phone":"+1 416 496 2294",
    "sg:postcode":"M1W 3E2",
    "sg:province":"ON",
    "wof:name":"Mac's Convenience Stores Ltd",
    "wof:placetype":"venue"
},
  "geometry": {"coordinates":[-79.33350372309999,43.811756134],"type":"Point"}
}