{
  "type": "Feature",
  "properties": {
    "addr:full":"305 Industrial Pky S # 10 Aurora ON L4G 6X7",
    "addr:housenumber":"305",
    "addr:postcode":"l4g 6x7",
    "addr:street":"Industrial Pky S # 10",
    "iso:country":"CA",
    "sg:address":"305 Industrial Pky S # 10",
    "sg:city":"Aurora",
    "sg:classifiers":[
        {
            "category":"Shopping",
            "subcategory":"Clothing, Apparel, & Fashions",
            "type":"Retail Goods"
        }
    ],
    "sg:phone":"+1 905 841 3768",
    "sg:postcode":"L4G 6X7",
    "sg:province":"ON",
    "sg:tags":[
        "riding",
        "equipment"
    ],
    "wof:name":"Ssg Gloves",
    "wof:placetype":"venue"
},
  "geometry": {"coordinates":[-79.45347595210001,43.9876708984],"type":"Point"}
}