{
  "type": "Feature",
  "properties": {
    "addr:full":"650 Fortune Cres Kingston ON K7P 2T3",
    "addr:housenumber":"650",
    "addr:postcode":"k7p 2t3",
    "addr:street":"Fortune Cres",
    "iso:country":"CA",
    "sg:address":"650 Fortune Cres",
    "sg:city":"Kingston",
    "sg:classifiers":[
        {
            "category":"Utilities",
            "type":"Services"
        }
    ],
    "sg:phone":"+1 613 966 1491",
    "sg:postcode":"K7P 2T3",
    "sg:province":"ON",
    "sg:tags":[
        "sweeping",
        "cleaning"
    ],
    "wof:name":"Scott Industrial Svc",
    "wof:placetype":"venue"
},
  "geometry": {"coordinates":[-76.565445,44.27174],"type":"Point"}
}