{
  "type": "Feature",
  "properties": {
    "addr:full":"Parksville BC V9P 1R6",
    "addr:postcode":"v9p 1r6",
    "iso:country":"CA",
    "sg:city":"Parksville",
    "sg:classifiers":[
        {
            "category":"Personal",
            "subcategory":"Beauty Salon",
            "type":"Services"
        }
    ],
    "sg:phone":"+1 250 248 3231",
    "sg:postcode":"V9P 1R6",
    "sg:province":"BC",
    "wof:name":"Cut & Curl Salon",
    "wof:placetype":"venue"
},
  "geometry": {"coordinates":[-124.311913,49.32],"type":"Point"}
}