{
  "type": "Feature",
  "properties": {
    "addr:full":"6135 Okanagan Landing Rd Vernon BC V1H 1M3",
    "addr:housenumber":"6135",
    "addr:postcode":"v1h 1m3",
    "addr:street":"Okanagan Landing Rd",
    "iso:country":"CA",
    "sg:address":"6135 Okanagan Landing Rd",
    "sg:city":"Vernon",
    "sg:classifiers":[
        {
            "category":"Wholesale",
            "subcategory":"Fruits & Vegetables",
            "type":"Manufacturing & Wholesale Goods"
        }
    ],
    "sg:phone":"+1 250 542 6723",
    "sg:postcode":"V1H 1M3",
    "sg:province":"BC",
    "wof:name":"Okanagan Produce Plus",
    "wof:placetype":"venue"
},
  "geometry": {"coordinates":[-119.322113,50.247513],"type":"Point"}
}