{
  "type": "Feature",
  "properties": {
    "addr:full":"125 Waterloo St S Cambridge ON N3H 1N3",
    "addr:housenumber":"125",
    "addr:postcode":"n3h 1n3",
    "addr:street":"Waterloo St S",
    "iso:country":"CA",
    "sg:address":"125 Waterloo St S",
    "sg:city":"Cambridge",
    "sg:classifiers":[
        {
            "category":"Shopping",
            "type":"Retail Goods"
        }
    ],
    "sg:phone":"+1 519 653 1994",
    "sg:postcode":"N3H 1N3",
    "sg:province":"ON",
    "sg:tags":[
        "wheel",
        "home",
        "chair",
        "health",
        "scooter"
    ],
    "wof:name":"Preston Medical Pharmacy",
    "wof:placetype":"venue"
},
  "geometry": {"coordinates":[-80.36119100000001,43.396896],"type":"Point"}
}