{
  "type": "Feature",
  "properties": {
    "addr:full":"30 Sewells Rd Scarborough ON M1B 3G5",
    "addr:housenumber":"30",
    "addr:postcode":"m1b 3g5",
    "addr:street":"Sewells Rd",
    "iso:country":"CA",
    "sg:address":"30 Sewells Rd",
    "sg:city":"Scarborough",
    "sg:classifiers":[
        {
            "category":"Government",
            "subcategory":"Office",
            "type":"Public Place"
        }
    ],
    "sg:phone":"+1 416 396 4054",
    "sg:postcode":"M1B 3G5",
    "sg:province":"ON",
    "sg:tags":[
        "tennis",
        "court",
        "village"
    ],
    "wof:name":"Malvern Community Rec Ctr",
    "wof:placetype":"venue"
},
  "geometry": {"coordinates":[-79.21608000000001,43.807743],"type":"Point"}
}