{
  "type": "Feature",
  "properties": {
    "addr:full":"653 241 Rte Saint-Joachim-DE-Shefford QC J0E 2G0",
    "addr:housenumber":"241",
    "addr:postcode":"j0e 2g0",
    "addr:street":"Rte Saint-Joachim-De-Shefford",
    "iso:country":"CA",
    "sg:address":"653 241 Rte",
    "sg:city":"Saint-Joachim-DE-Shefford",
    "sg:classifiers":[
        {
            "category":"Organizations",
            "subcategory":"Religious Organization",
            "type":"Services"
        }
    ],
    "sg:phone":"+1 514 539 1255",
    "sg:postcode":"J0E 2G0",
    "sg:province":"QC",
    "sg:tags":[
        "church"
    ],
    "wof:name":"Eglise Catholique",
    "wof:placetype":"venue"
},
  "geometry": {"coordinates":[-72.47403,45.332138],"type":"Point"}
}