{
  "type": "Feature",
  "properties": {
    "addr:full":"489 College St # 500 Toronto ON M6G 1A5",
    "addr:housenumber":"489",
    "addr:postcode":"m6g 1a5",
    "addr:street":"College St # 500",
    "iso:country":"CA",
    "sg:address":"489 College St # 500",
    "sg:city":"Toronto",
    "sg:classifiers":[
        {
            "category":"Organizations",
            "subcategory":"Professional Association",
            "type":"Services"
        }
    ],
    "sg:phone":"+1 416 920 9567",
    "sg:postcode":"M6G 1A5",
    "sg:province":"ON",
    "wof:name":"Pasan",
    "wof:placetype":"venue"
},
  "geometry": {"coordinates":[-79.40935500000001,43.656036],"type":"Point"}
}