{
  "type": "Feature",
  "properties": {
    "addr:full":"37 Saskatchewan Ave Quill Lake SK S0A 3E0",
    "addr:housenumber":"37",
    "addr:postcode":"s0a 3e0",
    "addr:street":"Saskatchewan Ave",
    "iso:country":"CA",
    "sg:address":"37 Saskatchewan Ave",
    "sg:city":"Quill Lake",
    "sg:classifiers":[
        {
            "category":"Personal",
            "subcategory":"Beauty Salon",
            "type":"Services"
        }
    ],
    "sg:phone":"+1 306 383 2202",
    "sg:postcode":"S0A 3E0",
    "sg:province":"SK",
    "wof:name":"Barb's Beauty Salon",
    "wof:placetype":"venue"
},
  "geometry": {"coordinates":[-104.256980896,52.069934845],"type":"Point"}
}