{
  "type": "Feature",
  "properties": {
    "addr:full":"Mont-Royal QC H4N 2P7",
    "addr:postcode":"h4n 2p7",
    "iso:country":"CA",
    "sg:city":"Mont-Royal",
    "sg:classifiers":[
        {
            "category":"Professional",
            "subcategory":"Accounting & Tax Preparation",
            "type":"Services"
        }
    ],
    "sg:phone":"+1 514 735 4818",
    "sg:postcode":"H4N 2P7",
    "sg:province":"QC",
    "sg:tags":[
        "accountant"
    ],
    "wof:name":"Cardilli, Anna CA",
    "wof:placetype":"venue"
},
  "geometry": {"coordinates":[-73.66422300000001,45.505013],"type":"Point"}
}