{
  "type": "Feature",
  "properties": {
    "addr:full":"130 Rue Jean-Proulx Hull QC J8Z 1V3",
    "addr:housenumber":"130",
    "addr:postcode":"j8z 1v3",
    "addr:street":"Rue Jean-Proulx",
    "iso:country":"CA",
    "sg:address":"130 Rue Jean-Proulx",
    "sg:city":"Hull",
    "sg:classifiers":[
        {
            "category":"Manufacturing",
            "subcategory":"Metals",
            "type":"Manufacturing & Wholesale Goods"
        }
    ],
    "sg:phone":"+1 819 770 7110",
    "sg:postcode":"J8Z 1V3",
    "sg:province":"QC",
    "sg:tags":[
        "plumbing",
        "fixture",
        "supply"
    ],
    "wof:name":"Boone Plumbing & Heating Spply",
    "wof:placetype":"venue"
},
  "geometry": {"coordinates":[-75.7340545654,45.46616745],"type":"Point"}
}