{
  "type": "Feature",
  "properties": {
    "iso:country":"CA",
    "sg:address":"9 Madeira Cres",
    "sg:city":"Dartmouth",
    "sg:classifiers":[
        {
            "category":"Professional",
            "subcategory":"Accounting & Tax Preparation",
            "type":"Services"
        }
    ],
    "sg:phone":"+1 902 462 2094",
    "sg:postcode":"B2W 6G6",
    "sg:province":"NS",
    "sg:tags":[
        "bookkeeping",
        "general"
    ],
    "wof:name":"Mac Leod & Assoc Software Inc",
    "wof:placetype":"venue"
},
  "geometry": {"coordinates":[-63.4884567261,44.6923751831],"type":"Point"}
}