{
  "type": "Feature",
  "properties": {
    "addr:full":"19 Seneca Hill Dr North York ON M2J 2W3",
    "addr:housenumber":"19",
    "addr:postcode":"m2j 2w3",
    "addr:street":"Seneca Hill Dr",
    "iso:country":"CA",
    "sg:address":"19 Seneca Hill Dr",
    "sg:city":"North York",
    "sg:classifiers":[
        {
            "category":"Building & Trades",
            "subcategory":"Electrical",
            "type":"Services"
        }
    ],
    "sg:phone":"+1 416 491 4454",
    "sg:postcode":"M2J 2W3",
    "sg:province":"ON",
    "sg:tags":[
        "electric",
        "contractor"
    ],
    "wof:name":"Treadman Electric CO Ltd",
    "wof:placetype":"venue"
},
  "geometry": {"coordinates":[-79.36254099999999,43.785957],"type":"Point"}
}