{
  "type": "Feature",
  "properties": {
    "addr:full":"15 Wallingford Rd North York ON M3A 2V1",
    "addr:housenumber":"15",
    "addr:postcode":"m3a 2v1",
    "addr:street":"Wallingford Rd",
    "iso:country":"CA",
    "sg:address":"15 Wallingford Rd",
    "sg:city":"North York",
    "sg:classifiers":[
        {
            "category":"Education",
            "subcategory":"School",
            "type":"Public Place"
        }
    ],
    "sg:phone":"+1 416 395 3510",
    "sg:postcode":"M3A 2V1",
    "sg:province":"ON",
    "wof:name":"Victoria Park Secondary School",
    "wof:placetype":"venue"
},
  "geometry": {"coordinates":[-79.32191467289999,43.7553672791],"type":"Point"}
}