{
  "type": "Feature",
  "properties": {
    "addr:full":"454 Okaview Rd Kelowna BC V1W 4L4",
    "addr:housenumber":"454",
    "addr:postcode":"v1w 4l4",
    "addr:street":"Okaview Rd",
    "iso:country":"CA",
    "sg:address":"454 Okaview Rd",
    "sg:city":"Kelowna",
    "sg:classifiers":[
        {
            "category":"Building & Trades",
            "subcategory":"Construction",
            "type":"Services"
        }
    ],
    "sg:phone":"+1 250 764 5200",
    "sg:postcode":"V1W 4L4",
    "sg:province":"BC",
    "sg:tags":[
        "contractor",
        "general"
    ],
    "wof:name":"Stonebridge Design & Build",
    "wof:placetype":"venue"
},
  "geometry": {"coordinates":[-119.508301,49.800098],"type":"Point"}
}