{
  "type": "Feature",
  "properties": {
    "addr:full":"60 5E Av Boisbriand QC J7G 1Y9",
    "addr:housenumber":"60",
    "addr:postcode":"j7g 1y9",
    "addr:street":"5E Av",
    "iso:country":"CA",
    "sg:address":"60 5E Av",
    "sg:city":"Boisbriand",
    "sg:classifiers":[
        {
            "category":"Building & Trades",
            "subcategory":"Construction",
            "type":"Services"
        }
    ],
    "sg:phone":"+1 450 437 3650",
    "sg:postcode":"J7G 1Y9",
    "sg:province":"QC",
    "sg:tags":[
        "masonry",
        "contractor"
    ],
    "wof:name":"Maconnerie Julien Lepage Inc",
    "wof:placetype":"venue"
},
  "geometry": {"coordinates":[-73.81722259519999,45.6182441711],"type":"Point"}
}