{
  "type": "Feature",
  "properties": {
    "iso:country":"CA",
    "sg:address":"1180 Mountain Rd",
    "sg:city":"Moncton",
    "sg:classifiers":[
        {
            "category":"Restaurant",
            "type":"Food & Drink"
        }
    ],
    "sg:phone":"+1 506 855 4255",
    "sg:postcode":"E1C 2T6",
    "sg:province":"NB",
    "wof:name":"Dixie Lee",
    "wof:placetype":"venue"
},
  "geometry": {"coordinates":[-64.82502746580001,46.1071510315],"type":"Point"}
}