{
  "type": "Feature",
  "properties": {
    "addr:full":"Edmonton AB T5N 4A3",
    "addr:postcode":"t5n 4a3",
    "iso:country":"CA",
    "sg:city":"Edmonton",
    "sg:classifiers":[
        {
            "category":"Personal",
            "subcategory":"Beauty Salon",
            "type":"Services"
        }
    ],
    "sg:phone":"+1 780 482 4857",
    "sg:postcode":"T5N 4A3",
    "sg:province":"AB",
    "wof:name":"Martino Hair Group",
    "wof:placetype":"venue"
},
  "geometry": {"coordinates":[-113.536140442,53.5433883667],"type":"Point"}
}