{
  "type": "Feature",
  "properties": {
    "addr:full":"14 Rue Dubo Victoriaville QC G6P 6V3",
    "addr:housenumber":"14",
    "addr:postcode":"g6p 6v3",
    "addr:street":"Rue Dubo",
    "iso:country":"CA",
    "sg:address":"14 Rue Dubo",
    "sg:city":"Victoriaville",
    "sg:classifiers":[
        {
            "category":"Social Services",
            "type":"Services"
        }
    ],
    "sg:phone":"+1 819 751 2088",
    "sg:postcode":"G6P 6V3",
    "sg:province":"QC",
    "sg:tags":[
        "organization",
        "welfare"
    ],
    "wof:name":"Centre DE Svc En Deficience",
    "wof:placetype":"venue"
},
  "geometry": {"coordinates":[-71.9786224365,46.06690979],"type":"Point"}
}