{
  "type": "Feature",
  "properties": {
    "addr:full":"1171 Kossuth Rd Cambridge ON N3C 2V3",
    "addr:housenumber":"1171",
    "addr:postcode":"n3c 2v3",
    "addr:street":"Kossuth Rd",
    "iso:country":"CA",
    "sg:address":"1171 Kossuth Rd",
    "sg:city":"Cambridge",
    "sg:classifiers":[
        {
            "category":"Shopping",
            "subcategory":"Bicycles & Sporting Goods",
            "type":"Retail Goods"
        }
    ],
    "sg:phone":"+1 519 658 9764",
    "sg:postcode":"N3C 2V3",
    "sg:province":"ON",
    "wof:name":"Beaverdale Golf Club",
    "wof:placetype":"venue"
},
  "geometry": {"coordinates":[-80.315331,43.361408],"type":"Point"}
}