{
  "type": "Feature",
  "properties": {
    "addr:full":"Nepean ON K2E 6T8",
    "addr:postcode":"k2e 6t8",
    "iso:country":"CA",
    "sg:city":"Nepean",
    "sg:classifiers":[
        {
            "category":"Building & Trades",
            "subcategory":"Construction",
            "type":"Services"
        }
    ],
    "sg:phone":"+1 613 224 9252",
    "sg:postcode":"K2E 6T8",
    "sg:province":"ON",
    "sg:tags":[
        "tile",
        "dealer"
    ],
    "wof:name":"Tempest Tile Ltd",
    "wof:placetype":"venue"
},
  "geometry": {"coordinates":[-75.7183227539,45.3332061768],"type":"Point"}
}