{
  "type": "Feature",
  "properties": {
    "iso:country":"CA",
    "sg:address":"5608 Imperial St",
    "sg:city":"Burnaby",
    "sg:classifiers":[
        {
            "category":"Retail",
            "subcategory":"Auto Repair",
            "type":"Services"
        }
    ],
    "sg:phone":"+1 604 437 5420",
    "sg:postcode":"V5J 1E9",
    "sg:province":"BC",
    "sg:tags":[
        "body",
        "automobile",
        "painting"
    ],
    "wof:name":"Boyd Autobody & Glass",
    "wof:placetype":"venue"
},
  "geometry": {"coordinates":[-122.982681274,49.2217254639],"type":"Point"}
}