{
  "type": "Feature",
  "properties": {
    "iso:country":"CA",
    "sg:address":"1501 Carling Ave",
    "sg:city":"Ottawa",
    "sg:classifiers":[
        {
            "category":"Manufacturing",
            "subcategory":"Signs",
            "type":"Manufacturing & Wholesale Goods"
        }
    ],
    "sg:phone":"+1 613 728 5979",
    "sg:postcode":"K1Z 7M1",
    "sg:province":"ON",
    "wof:name":"Eventgraphics",
    "wof:placetype":"venue"
},
  "geometry": {"coordinates":[-75.7422027588,45.3834075928],"type":"Point"}
}