{
  "type": "Feature",
  "properties": {
    "iso:country":"CA",
    "sg:city":"Edmonton",
    "sg:classifiers":[
        {
            "category":"Professional",
            "subcategory":"Accounting & Tax Preparation",
            "type":"Services"
        }
    ],
    "sg:phone":"+1 780 468 7232",
    "sg:postcode":"T6E 6A8",
    "sg:province":"AB",
    "sg:tags":[
        "accountant"
    ],
    "wof:name":"Yaremchuk & Annicchiarico",
    "wof:placetype":"venue"
},
  "geometry": {"coordinates":[-113.45629119900001,53.4878921509],"type":"Point"}
}