{
  "type": "Feature",
  "properties": {
    "addr:full":"968 2nd Ave W Owen Sound ON N4K 4M7",
    "addr:housenumber":"968",
    "addr:postcode":"n4k 4m7",
    "addr:street":"2Nd Ave W",
    "iso:country":"CA",
    "sg:address":"968 2nd Ave W",
    "sg:city":"Owen Sound",
    "sg:classifiers":[
        {
            "category":"Shopping",
            "subcategory":"Optical Goods",
            "type":"Retail Goods"
        }
    ],
    "sg:phone":"+1 519 376 4242",
    "sg:postcode":"N4K 4M7",
    "sg:province":"ON",
    "sg:tags":[
        "sun",
        "goggles",
        "sunglasses",
        "optician"
    ],
    "wof:name":"R J Campbell Opticians Ltd",
    "wof:placetype":"venue"
},
  "geometry": {"coordinates":[-80.946198,44.566689],"type":"Point"}
}