{
  "type": "Feature",
  "properties": {
    "iso:country":"CA",
    "sg:address":"176 Golden Dr",
    "sg:city":"Coquitlam",
    "sg:classifiers":[
        {
            "category":"Autos & Motor Vehicles",
            "subcategory":"Fuel & Gas Station",
            "type":"Retail Goods"
        }
    ],
    "sg:phone":"+1 604 464 5040",
    "sg:postcode":"V3K 6J1",
    "sg:province":"BC",
    "sg:tags":[
        "oil"
    ],
    "wof:name":"Mayfair Petro-Canada",
    "wof:placetype":"venue"
},
  "geometry": {"coordinates":[-122.820236206,49.2330551147],"type":"Point"}
}