{
  "type": "Feature",
  "properties": {
    "addr:full":"Castlegar BC V1N 2M1",
    "addr:postcode":"v1n 2m1",
    "iso:country":"CA",
    "sg:city":"Castlegar",
    "sg:classifiers":[
        {
            "category":"Real Estate",
            "subcategory":"Real Estate Agent",
            "type":"Services"
        }
    ],
    "sg:phone":"+1 250 365 2677",
    "sg:postcode":"V1N 2M1",
    "sg:province":"BC",
    "sg:tags":[
        "authorities",
        "housing"
    ],
    "wof:name":"Woodland Park Housing CO-OP",
    "wof:placetype":"venue"
},
  "geometry": {"coordinates":[-117.65473938,49.3020401001],"type":"Point"}
}