{
  "type": "Feature",
  "properties": {
    "addr:full":"7284 Cypress St Vancouver BC V6P 5M3",
    "addr:housenumber":"7284",
    "addr:postcode":"v6p 5m3",
    "addr:street":"Cypress St",
    "iso:country":"CA",
    "sg:address":"7284 Cypress St",
    "sg:city":"Vancouver",
    "sg:classifiers":[
        {
            "category":"Organizations",
            "subcategory":"Religious Organization",
            "type":"Services"
        }
    ],
    "sg:phone":"+1 604 266 8011",
    "sg:postcode":"V6P 5M3",
    "sg:province":"BC",
    "sg:tags":[
        "church"
    ],
    "wof:name":"St Faith's Church",
    "wof:placetype":"venue"
},
  "geometry": {"coordinates":[-123.149399,49.21983],"type":"Point"}
}