{
  "type": "Feature",
  "properties": {
    "addr:full":"315 Ch Knowlton Rd Knowlton QC J0E 1V0",
    "addr:housenumber":"315",
    "addr:postcode":"j0e 1v0",
    "addr:street":"Ch Knowlton Rd",
    "iso:country":"CA",
    "sg:address":"315 Ch Knowlton Rd",
    "sg:city":"Knowlton",
    "sg:classifiers":[
        {
            "category":"Professional",
            "subcategory":"Business Services",
            "type":"Services"
        }
    ],
    "sg:phone":"+1 450 243 6161",
    "sg:postcode":"J0E 1V0",
    "sg:province":"QC",
    "sg:tags":[
        "packaging"
    ],
    "wof:name":"Emballages Knowlton Inc",
    "wof:placetype":"venue"
},
  "geometry": {"coordinates":[-72.51280199999999,45.216454],"type":"Point"}
}