{
  "type": "Feature",
  "properties": {
    "addr:full":"587 Rue Principale Petit-Rocher NB E8J 1H6",
    "addr:housenumber":"587",
    "addr:postcode":"e8j 1h6",
    "addr:street":"Rue Principale",
    "iso:country":"CA",
    "sg:address":"587 Rue Principale",
    "sg:city":"Petit-Rocher",
    "sg:classifiers":[
        {
            "category":"Travel",
            "subcategory":"Hotels & Motels",
            "type":"Entertainment"
        }
    ],
    "sg:phone":"+1 506 783 0587",
    "sg:postcode":"E8J 1H6",
    "sg:province":"NB",
    "sg:tags":[
        "breakfast",
        "inn",
        "bed",
        "accommodation"
    ],
    "wof:name":"Auberge D'Anjou",
    "wof:placetype":"venue"
},
  "geometry": {"coordinates":[-65.71798699999999,47.782974],"type":"Point"}
}