{
  "type": "Feature",
  "properties": {
    "addr:full":"Montreal QC H3C 4J3",
    "addr:postcode":"h3c 4j3",
    "iso:country":"CA",
    "sg:city":"Montreal",
    "sg:classifiers":[
        {
            "category":"Professional",
            "subcategory":"Business Services",
            "type":"Services"
        }
    ],
    "sg:phone":"+1 514 861 0609",
    "sg:postcode":"H3C 4J3",
    "sg:province":"QC",
    "sg:tags":[
        "interior",
        "consultant",
        "design",
        "decorator"
    ],
    "wof:name":"Realisations Conceptum Intl",
    "wof:placetype":"venue"
},
  "geometry": {"coordinates":[-73.56359863279999,45.4972038269],"type":"Point"}
}