{
  "type": "Feature",
  "properties": {
    "addr:full":"939 Algonquin Blvd E Timmins ON P4N 7J5",
    "addr:housenumber":"939",
    "addr:postcode":"p4n 7j5",
    "addr:street":"Algonquin Blvd E",
    "iso:country":"CA",
    "sg:address":"939 Algonquin Blvd E",
    "sg:city":"Timmins",
    "sg:classifiers":[
        {
            "category":"Travel",
            "subcategory":"Hotels & Motels",
            "type":"Entertainment"
        }
    ],
    "sg:phone":"+1 705 264 9474",
    "sg:postcode":"P4N 7J5",
    "sg:province":"ON",
    "wof:name":"Comfort Inn",
    "wof:placetype":"venue"
},
  "geometry": {"coordinates":[-81.314789,48.47662],"type":"Point"}
}