{
  "type": "Feature",
  "properties": {
    "addr:full":"437 Queen St W Toronto ON M5V 2A5",
    "addr:housenumber":"437",
    "addr:postcode":"m5v 2a5",
    "addr:street":"Queen St W",
    "iso:country":"CA",
    "sg:address":"437 Queen St W",
    "sg:city":"Toronto",
    "sg:classifiers":[
        {
            "category":"Shopping",
            "subcategory":"Shoes",
            "type":"Retail Goods"
        }
    ],
    "sg:phone":"+1 416 593 5598",
    "sg:postcode":"M5V 2A5",
    "sg:province":"ON",
    "wof:name":"Get Out Side",
    "wof:placetype":"venue"
},
  "geometry": {"coordinates":[-79.395775,43.64872],"type":"Point"}
}