{
  "type": "Feature",
  "properties": {
    "addr:full":"2155 Leanne Blvd # 6 Mississauga ON L5K 2K8",
    "addr:housenumber":"2155",
    "addr:postcode":"l5k 2k8",
    "addr:street":"Leanne Blvd # 6",
    "iso:country":"CA",
    "sg:address":"2155 Leanne Blvd # 6",
    "sg:city":"Mississauga",
    "sg:classifiers":[
        {
            "category":"Restaurant",
            "type":"Food & Drink"
        }
    ],
    "sg:phone":"+1 905 822 2040",
    "sg:postcode":"L5K 2K8",
    "sg:province":"ON",
    "sg:tags":[
        "chicken",
        "dinner"
    ],
    "wof:name":"Swiss Chalet Rotisserie/Grill",
    "wof:placetype":"venue"
},
  "geometry": {"coordinates":[-79.65308400000001,43.526199],"type":"Point"}
}