{
  "type": "Feature",
  "properties": {
    "addr:full":"PO Box 426 Blackfalds AB T0M 0J0",
    "addr:housenumber":"po",
    "addr:postcode":"t0m 0j0",
    "addr:street":"Box 426",
    "iso:country":"CA",
    "sg:address":"PO Box 426",
    "sg:city":"Blackfalds",
    "sg:classifiers":[
        {
            "category":"Mining & Drilling",
            "type":"Manufacturing & Wholesale Goods"
        }
    ],
    "sg:phone":"+1 403 844 2154",
    "sg:postcode":"T0M 0J0",
    "sg:province":"AB",
    "sg:tags":[
        "field",
        "oil",
        "transportation"
    ],
    "wof:name":"Heck's Trucking & Oilfield",
    "wof:placetype":"venue"
},
  "geometry": {"coordinates":[-113.79022999999999,52.38015],"type":"Point"}
}