{
  "type": "Feature",
  "properties": {
    "addr:full":"125 Pownal St Charlottetown PE C1A 3W4",
    "addr:housenumber":"125",
    "addr:postcode":"c1a 3w4",
    "addr:street":"Pownal St",
    "iso:country":"CA",
    "sg:address":"125 Pownal St",
    "sg:city":"Charlottetown",
    "sg:classifiers":[
        {
            "category":"Insurance",
            "subcategory":"Insurance Agent",
            "type":"Services"
        }
    ],
    "sg:phone":"+1 902 566 5666",
    "sg:postcode":"C1A 3W4",
    "sg:province":"PE",
    "wof:name":"Cooke, Charlie",
    "wof:placetype":"venue"
},
  "geometry": {"coordinates":[-63.129517,46.233185],"type":"Point"}
}