{
  "type": "Feature",
  "properties": {
    "iso:country":"CA",
    "sg:address":"360 Bay St #200",
    "sg:city":"Toronto",
    "sg:classifiers":[
        {
            "category":"Manufacturing",
            "subcategory":"Printing",
            "type":"Manufacturing & Wholesale Goods"
        }
    ],
    "sg:phone":"+1 416 368 9296",
    "sg:postcode":"M5H 2V6",
    "sg:province":"ON",
    "sg:tags":[
        "printer"
    ],
    "wof:name":"City Centre Copy Printing",
    "wof:placetype":"venue"
},
  "geometry": {"coordinates":[-79.381332,43.65073],"type":"Point"}
}