{
  "type": "Feature",
  "properties": {
    "addr:full":"360 Bay St #200 Toronto ON M5H 2V6",
    "addr:housenumber":"360",
    "addr:postcode":"m5h 2v6",
    "addr:street":"Bay St # 200",
    "iso:country":"CA",
    "sg:address":"360 Bay St #200",
    "sg:city":"Toronto",
    "sg:classifiers":[
        {
            "category":"Manufacturing",
            "subcategory":"Printing",
            "type":"Manufacturing & Wholesale Goods"
        }
    ],
    "sg:phone":"+1 416 368 9296",
    "sg:postcode":"M5H 2V6",
    "sg:province":"ON",
    "sg:tags":[
        "printer"
    ],
    "wof:name":"City Centre Copy Printing",
    "wof:placetype":"venue"
},
  "geometry": {"coordinates":[-79.381332,43.65073],"type":"Point"}
}