{
  "type": "Feature",
  "properties": {
    "addr:full":"Winnipeg MB R2H 0G9",
    "addr:postcode":"r2h 0g9",
    "iso:country":"CA",
    "sg:city":"Winnipeg",
    "sg:classifiers":[
        {
            "category":"Organizations",
            "subcategory":"Professional Association",
            "type":"Services"
        }
    ],
    "sg:phone":"+1 204 237 8947",
    "sg:postcode":"R2H 0G9",
    "sg:province":"MB",
    "wof:name":"Conseil Jeunesse Provincial",
    "wof:placetype":"venue"
},
  "geometry": {"coordinates":[-97.113243103,49.8945732117],"type":"Point"}
}