{
  "type": "Feature",
  "properties": {
    "iso:country":"CA",
    "sg:address":"2300 Boul Industriel",
    "sg:city":"Chambly",
    "sg:classifiers":[
        {
            "category":"Manufacturing",
            "subcategory":"Toys & Sporting Goods",
            "type":"Manufacturing & Wholesale Goods"
        }
    ],
    "sg:phone":"+1 450 658 7587",
    "sg:postcode":"J3L 4V2",
    "sg:province":"QC",
    "sg:tags":[
        "athletic"
    ],
    "wof:name":"Production Passau Inc",
    "wof:placetype":"venue"
},
  "geometry": {"coordinates":[-73.27513885499999,45.432849884],"type":"Point"}
}