{
  "type": "Feature",
  "properties": {
    "addr:full":"103 Morgans Rd Huntsville ON P1H 1A2",
    "addr:housenumber":"103",
    "addr:postcode":"p1h 1a2",
    "addr:street":"Morgans Rd",
    "iso:country":"CA",
    "sg:address":"103 Morgans Rd",
    "sg:city":"Huntsville",
    "sg:classifiers":[
        {
            "category":"Real Estate",
            "subcategory":"Architect",
            "type":"Services"
        }
    ],
    "sg:phone":"+1 705 789 6960",
    "sg:postcode":"P1H 1A2",
    "sg:province":"ON",
    "sg:tags":[
        "course",
        "golf"
    ],
    "wof:name":"John F Robinson & Assoc Ltd",
    "wof:placetype":"venue"
},
  "geometry": {"coordinates":[-79.1307220459,45.3639221191],"type":"Point"}
}