{
  "type": "Feature",
  "properties": {
    "addr:full":"6332 Travois Cres NW Calgary AB T2K 3S7",
    "addr:housenumber":"6332",
    "addr:postcode":"t2k 3s7",
    "addr:street":"Travois Cres Nw",
    "iso:country":"CA",
    "sg:address":"6332 Travois Cres NW",
    "sg:city":"Calgary",
    "sg:classifiers":[
        {
            "category":"Building & Trades",
            "subcategory":"Construction",
            "type":"Services"
        }
    ],
    "sg:phone":"+1 403 274 6171",
    "sg:postcode":"T2K 3S7",
    "sg:province":"AB",
    "sg:tags":[
        "excavating",
        "contractor"
    ],
    "wof:name":"Tole Trucking & Bobcat Ltd",
    "wof:placetype":"venue"
},
  "geometry": {"coordinates":[-114.063721,51.109001],"type":"Point"}
}