{
  "type": "Feature",
  "properties": {
    "addr:full":"1618 Wilson Ave North York ON M3L 1A3",
    "addr:housenumber":"1618",
    "addr:postcode":"m3l 1a3",
    "addr:street":"Wilson Ave",
    "iso:country":"CA",
    "sg:address":"1618 Wilson Ave",
    "sg:city":"North York",
    "sg:classifiers":[
        {
            "category":"Food & Beverages",
            "subcategory":"Liquor & Beverages",
            "type":"Retail Goods"
        }
    ],
    "sg:phone":"+1 416 241 3018",
    "sg:postcode":"M3L 1A3",
    "sg:province":"ON",
    "sg:tags":[
        "store"
    ],
    "wof:name":"Ontario Liquor Store",
    "wof:placetype":"venue"
},
  "geometry": {"coordinates":[-79.5102310181,43.7207527161],"type":"Point"}
}