{
  "type": "Feature",
  "properties": {
    "addr:full":"12333 Arbour St Windsor ON N8N 1P1",
    "addr:housenumber":"12333",
    "addr:postcode":"n8n 1p1",
    "addr:street":"Arbour St",
    "iso:country":"CA",
    "sg:address":"12333 Arbour St",
    "sg:city":"Windsor",
    "sg:classifiers":[
        {
            "category":"Retail",
            "subcategory":"Auto Repair",
            "type":"Services"
        }
    ],
    "sg:phone":"+1 519 735 5812",
    "sg:postcode":"N8N 1P1",
    "sg:province":"ON",
    "sg:tags":[
        "machine",
        "automobile",
        "shop"
    ],
    "wof:name":"Mountain Cylinder & Head Mach",
    "wof:placetype":"venue"
},
  "geometry": {"coordinates":[-83.033913,42.317822],"type":"Point"}
}