{
  "type": "Feature",
  "properties": {
    "addr:full":"11 Romko Crt St Catharines ON L2N 7A1",
    "addr:housenumber":"11",
    "addr:postcode":"l2n 7a1",
    "addr:street":"Romko Crt",
    "iso:country":"CA",
    "sg:address":"11 Romko Crt",
    "sg:city":"St Catharines",
    "sg:classifiers":[
        {
            "category":"Wholesale",
            "subcategory":"Non-durable Goods",
            "type":"Manufacturing & Wholesale Goods"
        }
    ],
    "sg:phone":"+1 905 938 8022",
    "sg:postcode":"L2N 7A1",
    "sg:province":"ON",
    "sg:tags":[
        "advertising"
    ],
    "wof:name":"Shirt Design",
    "wof:placetype":"venue"
},
  "geometry": {"coordinates":[-79.255852,43.184532],"type":"Point"}
}