{
  "type": "Feature",
  "properties": {
    "addr:full":"150 Rue Heriot Drummondville QC J2C 1J8",
    "addr:housenumber":"150",
    "addr:postcode":"j2c 1j8",
    "addr:street":"Rue Heriot",
    "iso:country":"CA",
    "sg:address":"150 Rue Heriot",
    "sg:city":"Drummondville",
    "sg:classifiers":[
        {
            "category":"Banks & Credit Unions",
            "subcategory":"Financial Services",
            "type":"Services"
        }
    ],
    "sg:phone":"+1 819 475 0182",
    "sg:postcode":"J2C 1J8",
    "sg:province":"QC",
    "sg:tags":[
        "bankruptcy",
        "trustee"
    ],
    "wof:name":"Roy Metivier Roberge Syndics",
    "wof:placetype":"venue"
},
  "geometry": {"coordinates":[-72.49060799999999,45.88633],"type":"Point"}
}