{
  "type": "Feature",
  "properties": {
    "addr:full":"868 Lyons Creek Rd Welland ON L3B 5N4",
    "addr:housenumber":"868",
    "addr:postcode":"l3b 5n4",
    "addr:street":"Lyons Creek Rd",
    "iso:country":"CA",
    "sg:address":"868 Lyons Creek Rd",
    "sg:city":"Welland",
    "sg:classifiers":[
        {
            "category":"Organizations",
            "subcategory":"Religious Organization",
            "type":"Services"
        }
    ],
    "sg:phone":"+1 905 732 3116",
    "sg:postcode":"L3B 5N4",
    "sg:province":"ON",
    "sg:tags":[
        "church"
    ],
    "wof:name":"Jehovah's Witness Kingdom Hall",
    "wof:placetype":"venue"
},
  "geometry": {"coordinates":[-79.1764907837,42.9974212646],"type":"Point"}
}