{
  "type": "Feature",
  "properties": {
    "addr:full":"2840 13 Ave SW Salmon Arm BC V1E 3K1",
    "addr:housenumber":"2840",
    "addr:postcode":"v1e 3k1",
    "addr:street":"13 Ave Sw",
    "iso:country":"CA",
    "sg:address":"2840 13 Ave SW",
    "sg:city":"Salmon Arm",
    "sg:classifiers":[
        {
            "category":"Wholesale",
            "subcategory":"Scrap",
            "type":"Manufacturing & Wholesale Goods"
        }
    ],
    "sg:phone":"+1 250 832 6630",
    "sg:postcode":"V1E 3K1",
    "sg:province":"BC",
    "sg:tags":[
        "recycling",
        "center"
    ],
    "wof:name":"Bill's Bottle Depot Ltd",
    "wof:placetype":"venue"
},
  "geometry": {"coordinates":[-119.316368,50.690361],"type":"Point"}
}