{
  "type": "Feature",
  "properties": {
    "addr:full":"RR 2 Sexsmith AB T0H 3C0",
    "addr:postcode":"t0h 3c0",
    "addr:street":"Rr 2",
    "iso:country":"CA",
    "sg:address":"RR 2",
    "sg:city":"Sexsmith",
    "sg:classifiers":[
        {
            "category":"Wholesale",
            "subcategory":"Machinery & Supplies",
            "type":"Manufacturing & Wholesale Goods"
        }
    ],
    "sg:phone":"+1 780 568 4100",
    "sg:postcode":"T0H 3C0",
    "sg:province":"AB",
    "sg:tags":[
        "farm",
        "equipment"
    ],
    "wof:name":"Sexsmith Used Farm Parts",
    "wof:placetype":"venue"
},
  "geometry": {"coordinates":[-118.780761719,55.3451118469],"type":"Point"}
}