{
  "type": "Feature",
  "properties": {
    "addr:full":"55 Bernier Terr Kanata ON K2L 2V1",
    "addr:housenumber":"55",
    "addr:postcode":"k2l 2v1",
    "addr:street":"Bernier Terr",
    "iso:country":"CA",
    "sg:address":"55 Bernier Terr",
    "sg:city":"Kanata",
    "sg:classifiers":[
        {
            "category":"Professional",
            "subcategory":"Business Services",
            "type":"Services"
        }
    ],
    "sg:phone":"+1 613 592 3103",
    "sg:postcode":"K2L 2V1",
    "sg:province":"ON",
    "sg:tags":[
        "interior",
        "consultant",
        "design",
        "decorator"
    ],
    "wof:name":"Shiva Interiors",
    "wof:placetype":"venue"
},
  "geometry": {"coordinates":[-75.89444,45.306007],"type":"Point"}
}