{
  "type": "Feature",
  "properties": {
    "addr:full":"26 Symonds Ave St. John's NL A1E 3A3",
    "addr:housenumber":"26",
    "addr:postcode":"a1e 3a3",
    "addr:street":"Symonds Ave",
    "iso:country":"CA",
    "sg:address":"26 Symonds Ave",
    "sg:city":"St. John's",
    "sg:classifiers":[
        {
            "category":"Shopping",
            "subcategory":"Catalog Store",
            "type":"Retail Goods"
        }
    ],
    "sg:phone":"+1 709 738 3435",
    "sg:postcode":"A1E 3A3",
    "sg:province":"NL",
    "sg:tags":[
        "mail",
        "order",
        "internet"
    ],
    "wof:name":"Tidespoint.com",
    "wof:placetype":"venue"
},
  "geometry": {"coordinates":[-52.7289619446,47.5510139465],"type":"Point"}
}