{
  "type": "Feature",
  "properties": {
    "addr:full":"Gimli MB R0C 1B0",
    "addr:postcode":"r0c 1b0",
    "iso:country":"CA",
    "sg:city":"Gimli",
    "sg:classifiers":[
        {
            "category":"Shopping",
            "type":"Retail Goods"
        }
    ],
    "sg:phone":"+1 204 642 8217",
    "sg:postcode":"R0C 1B0",
    "sg:province":"MB",
    "sg:tags":[
        "art",
        "gallery",
        "dealer"
    ],
    "wof:name":"Gimli Art Club",
    "wof:placetype":"venue"
},
  "geometry": {"coordinates":[-96.9941482544,50.6319503784],"type":"Point"}
}