{
  "type": "Feature",
  "properties": {
    "iso:country":"CA",
    "sg:city":"Chatham",
    "sg:classifiers":[
        {
            "category":"Health Services",
            "subcategory":"Doctor",
            "type":"Services"
        }
    ],
    "sg:phone":"+1 519 354 7778",
    "sg:postcode":"N7L 4T1",
    "sg:province":"ON",
    "sg:tags":[
        "physician",
        "surgeon"
    ],
    "wof:name":"Parry, Park MD",
    "wof:placetype":"venue"
},
  "geometry": {"coordinates":[-82.215088,42.394314],"type":"Point"}
}