{
  "type": "Feature",
  "properties": {
    "addr:full":"880 Boul Du Royaume O Chicoutimi QC G7H 5B1",
    "addr:housenumber":"880",
    "addr:postcode":"g7h 5b1",
    "addr:street":"Boul Du Royaume O",
    "iso:country":"CA",
    "sg:address":"880 Boul Du Royaume O",
    "sg:city":"Chicoutimi",
    "sg:classifiers":[
        {
            "category":"Freight",
            "type":"Transportation"
        }
    ],
    "sg:phone":"+1 418 698 3400",
    "sg:postcode":"G7H 5B1",
    "sg:province":"QC",
    "sg:tags":[
        "trucking"
    ],
    "wof:name":"Transport Saguelac Inc",
    "wof:placetype":"venue"
},
  "geometry": {"coordinates":[-71.10182189939999,48.3843536377],"type":"Point"}
}