{
  "type": "Feature",
  "properties": {
    "addr:full":"Caplan QC G0C 1H0",
    "addr:postcode":"g0c 1h0",
    "iso:country":"CA",
    "sg:city":"Caplan",
    "sg:classifiers":[
        {
            "category":"Travel",
            "subcategory":"Hotels & Motels",
            "type":"Entertainment"
        }
    ],
    "sg:phone":"+1 418 388 5286",
    "sg:postcode":"G0C 1H0",
    "sg:province":"QC",
    "wof:name":"Motel Ruisselet",
    "wof:placetype":"venue"
},
  "geometry": {"coordinates":[-65.67924499510001,48.1011810303],"type":"Point"}
}