{
  "type": "Feature",
  "properties": {
    "addr:full":"162 Lipton St Winnipeg MB R3G 2G7",
    "addr:housenumber":"162",
    "addr:postcode":"r3g 2g7",
    "addr:street":"Lipton St",
    "iso:country":"CA",
    "sg:address":"162 Lipton St",
    "sg:city":"Winnipeg",
    "sg:classifiers":[
        {
            "category":"Shopping",
            "type":"Retail Goods"
        }
    ],
    "sg:phone":"+1 204 775 7096",
    "sg:postcode":"R3G 2G7",
    "sg:province":"MB",
    "sg:tags":[
        "craft",
        "gallery",
        "dealer"
    ],
    "wof:name":"Lipton Street Studio",
    "wof:placetype":"venue"
},
  "geometry": {"coordinates":[-97.1741104126,49.8823928833],"type":"Point"}
}