{
  "type": "Feature",
  "properties": {
    "addr:full":"1305 Rue Bishop Sainte-Foy QC G1W 3E4",
    "addr:housenumber":"1305",
    "addr:postcode":"g1w 3e4",
    "addr:street":"Rue Bishop",
    "iso:country":"CA",
    "sg:address":"1305 Rue Bishop",
    "sg:city":"Sainte-Foy",
    "sg:classifiers":[
        {
            "category":"Professional",
            "subcategory":"Employment Agencies",
            "type":"Services"
        }
    ],
    "sg:phone":"+1 418 650 0509",
    "sg:postcode":"G1W 3E4",
    "sg:province":"QC",
    "sg:tags":[
        "consultant",
        "search",
        "executive"
    ],
    "wof:name":"Parrot Recherche DE Cadres Inc",
    "wof:placetype":"venue"
},
  "geometry": {"coordinates":[-71.2759475708,46.7695159912],"type":"Point"}
}