{
  "type": "Feature",
  "properties": {
    "iso:country":"CA",
    "sg:city":"Brampton",
    "sg:classifiers":[
        {
            "category":"Wholesale",
            "subcategory":"Hardware",
            "type":"Manufacturing & Wholesale Goods"
        }
    ],
    "sg:phone":"+1 905 454 1742",
    "sg:postcode":"L6W 3R6",
    "sg:province":"ON",
    "sg:tags":[
        "heating"
    ],
    "wof:name":"Klimatrol Environmental Systs",
    "wof:placetype":"venue"
},
  "geometry": {"coordinates":[-79.7161483765,43.6839942932],"type":"Point"}
}