{
  "type": "Feature",
  "properties": {
    "addr:full":"7032 Ch Sainte-Marguerite Trois-Rivieres-Ouest QC G9A 5C9",
    "addr:postcode":"7032;g9a 5c9",
    "addr:street":"Ch Sainte-Marguerite Trois-Rivieres-Ouest",
    "iso:country":"CA",
    "sg:address":"7032 Ch Sainte-Marguerite",
    "sg:city":"Trois-Rivieres-Ouest",
    "sg:classifiers":[
        {
            "category":"Building & Trades",
            "subcategory":"Plumbing",
            "type":"Services"
        }
    ],
    "sg:phone":"+1 819 377 4304",
    "sg:postcode":"G9A 5C9",
    "sg:province":"QC",
    "sg:tags":[
        "ventilating",
        "contractor"
    ],
    "wof:name":"Int'Air Cite Ventilation",
    "wof:placetype":"venue"
},
  "geometry": {"coordinates":[-72.601257,46.324036],"type":"Point"}
}