{
  "type": "Feature",
  "properties": {
    "iso:country":"CA",
    "sg:address":"135 Rang 6",
    "sg:city":"Saint-Rosaire",
    "sg:classifiers":[
        {
            "category":"Retail",
            "subcategory":"Auto Repair",
            "type":"Services"
        }
    ],
    "sg:phone":"+1 819 752 4197",
    "sg:postcode":"G0Z 1K0",
    "sg:province":"QC",
    "sg:tags":[
        "repairing",
        "automobile"
    ],
    "wof:name":"Garage Romeo Lariviere",
    "wof:placetype":"venue"
},
  "geometry": {"coordinates":[-72.0563964844,46.1584701538],"type":"Point"}
}