{
  "type": "Feature",
  "properties": {
    "addr:full":"3661 48 Ave SE Calgary AB T2B 3N8",
    "addr:housenumber":"3661",
    "addr:postcode":"t2b 3n8",
    "addr:street":"48 Ave Se",
    "iso:country":"CA",
    "sg:address":"3661 48 Ave SE",
    "sg:city":"Calgary",
    "sg:classifiers":[
        {
            "category":"Freight",
            "type":"Transportation"
        }
    ],
    "sg:phone":"+1 403 236 7758",
    "sg:postcode":"T2B 3N8",
    "sg:province":"AB",
    "sg:tags":[
        "trucking"
    ],
    "wof:name":"J & R Hall Transport Inc",
    "wof:placetype":"venue"
},
  "geometry": {"coordinates":[-113.97782135,51.0103530884],"type":"Point"}
}