{
  "type": "Feature",
  "properties": {
    "addr:full":"Kanata ON K2V 1A4",
    "addr:postcode":"k2v 1a4",
    "iso:country":"CA",
    "sg:city":"Kanata",
    "sg:classifiers":[
        {
            "category":"Professional",
            "subcategory":"Management & Consulting",
            "type":"Services"
        }
    ],
    "sg:phone":"+1 613 599 4646",
    "sg:postcode":"K2V 1A4",
    "sg:province":"ON",
    "sg:tags":[
        "consultant",
        "sport"
    ],
    "wof:name":"Inside Edge Sports Consultants",
    "wof:placetype":"venue"
},
  "geometry": {"coordinates":[-75.9253540039,45.2963905334],"type":"Point"}
}