{
  "type": "Feature",
  "properties": {
    "addr:full":"5 York St London ON N6A 1A1",
    "addr:housenumber":"5",
    "addr:postcode":"n6a 1a1",
    "addr:street":"York St",
    "iso:country":"CA",
    "sg:address":"5 York St",
    "sg:city":"London",
    "sg:classifiers":[
        {
            "category":"Home & Garden",
            "subcategory":"Home Furnishings",
            "type":"Retail Goods"
        }
    ],
    "sg:phone":"+1 519 438 6165",
    "sg:postcode":"N6A 1A1",
    "sg:province":"ON",
    "sg:tags":[
        "equipment",
        "fireplace"
    ],
    "wof:name":"Guildwood Fireside",
    "wof:placetype":"venue"
},
  "geometry": {"coordinates":[-81.25507399999999,42.979382],"type":"Point"}
}