{
  "type": "Feature",
  "properties": {
    "iso:country":"CA",
    "sg:address":"36 Toronto St",
    "sg:city":"Toronto",
    "sg:classifiers":[
        {
            "category":"Travel",
            "subcategory":"Travel Agent",
            "type":"Entertainment"
        }
    ],
    "sg:phone":"+1 416 364 2363",
    "sg:postcode":"M5C 2C5",
    "sg:province":"ON",
    "sg:tags":[
        "agency",
        "bureau"
    ],
    "wof:name":"Clarke Way Travel",
    "wof:placetype":"venue"
},
  "geometry": {"coordinates":[-79.3764266968,43.6502990723],"type":"Point"}
}