{
  "type": "Feature",
  "properties": {
    "iso:country":"CA",
    "sg:address":"13853 102 Ave",
    "sg:city":"Surrey",
    "sg:classifiers":[
        {
            "category":"Health Services",
            "subcategory":"Nursing And Care Facility",
            "type":"Services"
        }
    ],
    "sg:phone":"+1 604 581 1555",
    "sg:postcode":"V3T 5P6",
    "sg:province":"BC",
    "sg:tags":[
        "home",
        "retirement",
        "community"
    ],
    "wof:name":"Imperial Place",
    "wof:placetype":"venue"
},
  "geometry": {"coordinates":[-122.838661194,49.1879005432],"type":"Point"}
}