{
  "type": "Feature",
  "properties": {
    "addr:full":"365 Boul Sir-Wilfrid-Laurier Saint-Basile-Le-Grand QC J3N 1M2",
    "addr:housenumber":"365",
    "addr:postcode":"j3n 1m2",
    "addr:street":"Boul Sir-Wilfrid-Laurier",
    "iso:country":"CA",
    "sg:address":"365 Boul Sir-Wilfrid-Laurier",
    "sg:city":"Saint-Basile-Le-Grand",
    "sg:classifiers":[
        {
            "category":"Travel",
            "subcategory":"Hotels & Motels",
            "type":"Entertainment"
        }
    ],
    "sg:phone":"+1 450 461 1571",
    "sg:postcode":"J3N 1M2",
    "sg:province":"QC",
    "wof:name":"Motel Le Pavillon",
    "wof:placetype":"venue"
},
  "geometry": {"coordinates":[-73.307434082,45.523525238],"type":"Point"}
}