{
  "type": "Feature",
  "properties": {
    "addr:full":"5853 Peer St Niagara Falls ON L2G 1X4",
    "addr:postcode":"5853;l2g 1x4",
    "addr:street":"Peer St",
    "iso:country":"CA",
    "sg:address":"5853 Peer St",
    "sg:city":"Niagara Falls",
    "sg:classifiers":[
        {
            "category":"Professional",
            "subcategory":"Employment Agencies",
            "type":"Services"
        }
    ],
    "sg:phone":"+1 905 353 1873",
    "sg:postcode":"L2G 1X4",
    "sg:province":"ON",
    "sg:tags":[
        "opportunity"
    ],
    "wof:name":"Job Finding Club",
    "wof:placetype":"venue"
},
  "geometry": {"coordinates":[-79.0914840698,43.0877075195],"type":"Point"}
}