{
  "type": "Feature",
  "properties": {
    "addr:full":"113 Mccabe Cres Thornhill ON L4J 2S6",
    "addr:housenumber":"113",
    "addr:postcode":"l4j 2s6",
    "addr:street":"Mccabe Cres",
    "iso:country":"CA",
    "sg:address":"113 Mccabe Cres",
    "sg:city":"Thornhill",
    "sg:classifiers":[
        {
            "category":"Social Services",
            "type":"Services"
        }
    ],
    "sg:phone":"+1 905 738 4601",
    "sg:postcode":"L4J 2S6",
    "sg:province":"ON",
    "sg:tags":[
        "counselor",
        "marriage",
        "family"
    ],
    "wof:name":"Sivkin, Dorete",
    "wof:placetype":"venue"
},
  "geometry": {"coordinates":[-79.462715,43.789993],"type":"Point"}
}