{
  "type": "Feature",
  "properties": {
    "addr:full":"636 Colby Dr Waterloo ON N2V 1A2",
    "addr:housenumber":"636",
    "addr:postcode":"n2v 1a2",
    "addr:street":"Colby Dr",
    "iso:country":"CA",
    "sg:address":"636 Colby Dr",
    "sg:city":"Waterloo",
    "sg:classifiers":[
        {
            "category":"Retail",
            "subcategory":"Auto Repair",
            "type":"Services"
        }
    ],
    "sg:phone":"+1 519 886 7264",
    "sg:postcode":"N2V 1A2",
    "sg:province":"ON",
    "sg:tags":[
        "body",
        "automobile",
        "painting"
    ],
    "wof:name":"Automotive Refinishing",
    "wof:placetype":"venue"
},
  "geometry": {"coordinates":[-80.5404281616,43.5059318542],"type":"Point"}
}