{
  "type": "Feature",
  "properties": {
    "addr:full":"Main St Delisle SK S0L 0P0",
    "addr:postcode":"s0l 0p0",
    "addr:street":"Main St",
    "iso:country":"CA",
    "sg:address":"Main St",
    "sg:city":"Delisle",
    "sg:classifiers":[
        {
            "category":"Government",
            "subcategory":"Office",
            "type":"Public Place"
        }
    ],
    "sg:phone":"+1 306 493 2972",
    "sg:postcode":"S0L 0P0",
    "sg:province":"SK",
    "sg:tags":[
        "village"
    ],
    "wof:name":"Delisle Workshop",
    "wof:placetype":"venue"
},
  "geometry": {"coordinates":[-107.13343811,51.9232139587],"type":"Point"}
}