{
  "type": "Feature",
  "properties": {
    "iso:country":"CA",
    "sg:address":"4500 50 Ave",
    "sg:city":"Olds",
    "sg:classifiers":[
        {
            "category":"Social Services",
            "subcategory":"Adult Care",
            "type":"Services"
        }
    ],
    "sg:phone":"+1 403 556 1987",
    "sg:postcode":"T4H 1X5",
    "sg:province":"AB",
    "sg:tags":[
        "senior",
        "housing",
        "citizen"
    ],
    "wof:name":"Legacy Villages",
    "wof:placetype":"venue"
},
  "geometry": {"coordinates":[-114.102867127,51.796749115],"type":"Point"}
}