{
  "type": "Feature",
  "properties": {
    "addr:full":"Vancouver BC V6B 2T5",
    "addr:postcode":"v6b 2t5",
    "iso:country":"CA",
    "sg:city":"Vancouver",
    "sg:classifiers":[
        {
            "category":"Shopping",
            "subcategory":"Clothing, Apparel, & Fashions",
            "type":"Retail Goods"
        }
    ],
    "sg:phone":"+1 604 688 7672",
    "sg:postcode":"V6B 2T5",
    "sg:province":"BC",
    "sg:tags":[
        "shop",
        "bridal"
    ],
    "wof:name":"Yaletown Wedding Gallery",
    "wof:placetype":"venue"
},
  "geometry": {"coordinates":[-123.119164,49.276299],"type":"Point"}
}