{
  "type": "Feature",
  "properties": {
    "addr:full":"Calgary AB T2G 5C3",
    "addr:postcode":"t2g 5c3",
    "iso:country":"CA",
    "sg:city":"Calgary",
    "sg:classifiers":[
        {
            "category":"Real Estate",
            "subcategory":"Architect",
            "type":"Services"
        }
    ],
    "sg:phone":"+1 403 264 2070",
    "sg:postcode":"T2G 5C3",
    "sg:province":"AB",
    "wof:name":"Johnston Sport Architecture",
    "wof:placetype":"venue"
},
  "geometry": {"coordinates":[-114.059585571,51.0452919006],"type":"Point"}
}