{
  "type": "Feature",
  "properties": {
    "iso:country":"CA",
    "sg:address":"3501 Trout Lake Rd",
    "sg:city":"North Bay",
    "sg:classifiers":[
        {
            "category":"Restaurant",
            "type":"Food & Drink"
        }
    ],
    "sg:phone":"+1 705 474 1982",
    "sg:postcode":"P1B 8G4",
    "sg:province":"ON",
    "wof:name":"Average Joe's",
    "wof:placetype":"venue"
},
  "geometry": {"coordinates":[-79.40785217289999,46.3295898438],"type":"Point"}
}