{
  "type": "Feature",
  "properties": {
    "addr:full":"520 Mountainview Rd Mcbride BC V0J 2E0",
    "addr:housenumber":"520",
    "addr:postcode":"v0j 2e0",
    "addr:street":"Mountainview Rd",
    "iso:country":"CA",
    "sg:address":"520 Mountainview Rd",
    "sg:city":"Mcbride",
    "sg:classifiers":[
        {
            "category":"Building & Trades",
            "subcategory":"Construction",
            "type":"Services"
        }
    ],
    "sg:phone":"+1 250 569 2493",
    "sg:postcode":"V0J 2E0",
    "sg:province":"BC",
    "sg:tags":[
        "general",
        "contractor"
    ],
    "wof:name":"R B Hatchard Construction Ltd",
    "wof:placetype":"venue"
},
  "geometry": {"coordinates":[-120.16211699999999,53.30442],"type":"Point"}
}