{
  "type": "Feature",
  "properties": {
    "addr:full":"8999 Conc 5 Uxbridge ON L9P 1R1",
    "addr:housenumber":"8999;5",
    "addr:postcode":"l9p 1r1",
    "addr:street":"Conc",
    "iso:country":"CA",
    "sg:address":"8999 Conc 5",
    "sg:city":"Uxbridge",
    "sg:classifiers":[
        {
            "category":"Manufacturing",
            "subcategory":"Motor Vehicles & Parts",
            "type":"Manufacturing & Wholesale Goods"
        }
    ],
    "sg:phone":"+1 905 852 9711",
    "sg:postcode":"L9P 1R1",
    "sg:province":"ON",
    "sg:tags":[
        "designer",
        "trailer"
    ],
    "wof:name":"L B Moore CO Ltd",
    "wof:placetype":"venue"
},
  "geometry": {"coordinates":[-79.186295,44.138603],"type":"Point"}
}