{
  "type": "Feature",
  "properties": {
    "addr:full":"2672 Lancaster Rd Ottawa ON K1B 4T7",
    "addr:housenumber":"2672",
    "addr:postcode":"k1b 4t7",
    "addr:street":"Lancaster Rd",
    "iso:country":"CA",
    "sg:address":"2672 Lancaster Rd",
    "sg:city":"Ottawa",
    "sg:classifiers":[
        {
            "category":"Manufacturing",
            "subcategory":"Rubber & Plastics",
            "type":"Manufacturing & Wholesale Goods"
        }
    ],
    "sg:phone":"+1 613 523 8051",
    "sg:postcode":"K1B 4T7",
    "sg:province":"ON",
    "sg:tags":[
        "equipment",
        "bookbinder",
        "laminating",
        "supply"
    ],
    "wof:name":"Gbc Canada Inc",
    "wof:placetype":"venue"
},
  "geometry": {"coordinates":[-75.6099395752,45.3981742859],"type":"Point"}
}