{
  "type": "Feature",
  "properties": {
    "addr:full":"1498 Fairburn St Sudbury ON P3A 1N7",
    "addr:housenumber":"1498",
    "addr:postcode":"p3a 1n7",
    "addr:street":"Fairburn St",
    "iso:country":"CA",
    "sg:address":"1498 Fairburn St",
    "sg:city":"Sudbury",
    "sg:classifiers":[
        {
            "category":"Wholesale",
            "subcategory":"Machinery & Supplies",
            "type":"Manufacturing & Wholesale Goods"
        }
    ],
    "sg:phone":"+1 705 566 0909",
    "sg:postcode":"P3A 1N7",
    "sg:province":"ON",
    "sg:tags":[
        "salon",
        "beauty"
    ],
    "wof:name":"Carpi Beauty Supplies",
    "wof:placetype":"venue"
},
  "geometry": {"coordinates":[-80.9420547485,46.5175704956],"type":"Point"}
}