{
  "type": "Feature",
  "properties": {
    "addr:full":"785 Westney Rd S Ajax ON L1S 7G1",
    "addr:housenumber":"785",
    "addr:postcode":"l1s 7g1",
    "addr:street":"Westney Rd",
    "iso:country":"CA",
    "sg:address":"785 Westney Rd S",
    "sg:city":"Ajax",
    "sg:classifiers":[
        {
            "category":"Building & Trades",
            "subcategory":"Plumbing",
            "type":"Services"
        }
    ],
    "sg:phone":"+1 905 428 6581",
    "sg:postcode":"L1S 7G1",
    "sg:province":"ON",
    "sg:tags":[
        "contractor"
    ],
    "wof:name":"Southwood Plumbing & Heating",
    "wof:placetype":"venue"
},
  "geometry": {"coordinates":[-79.023888,43.829403],"type":"Point"}
}