{
  "type": "Feature",
  "properties": {
    "addr:full":"Cp 255 Succ Bureau-Chef Salaberry-DE-Valleyfield QC J6S 4V6",
    "addr:postcode":"j6s 4v6",
    "addr:street":"Bureau-Chef",
    "iso:country":"CA",
    "sg:address":"Cp 255 Succ Bureau-Chef",
    "sg:city":"Salaberry-DE-Valleyfield",
    "sg:classifiers":[
        {
            "category":"Organizations",
            "subcategory":"Religious Organization",
            "type":"Services"
        }
    ],
    "sg:phone":"+1 450 377 7610",
    "sg:postcode":"J6S 4V6",
    "sg:province":"QC",
    "sg:tags":[
        "church"
    ],
    "wof:name":"Emmanuel DE Pentecote",
    "wof:placetype":"venue"
},
  "geometry": {"coordinates":[-74.13246154789999,45.2564163208],"type":"Point"}
}