{
  "type": "Feature",
  "properties": {
    "addr:full":"26 Oriole Ave Mississauga ON L5G 1V2",
    "addr:housenumber":"26",
    "addr:postcode":"l5g 1v2",
    "addr:street":"Oriole Ave",
    "iso:country":"CA",
    "sg:address":"26 Oriole Ave",
    "sg:city":"Mississauga",
    "sg:classifiers":[
        {
            "category":"Banks & Credit Unions",
            "subcategory":"Bank",
            "type":"Services"
        }
    ],
    "sg:phone":"+1 905 891 8600",
    "sg:postcode":"L5G 1V2",
    "sg:province":"ON",
    "sg:tags":[
        "financing",
        "loan"
    ],
    "wof:name":"Forward Capital Corp",
    "wof:placetype":"venue"
},
  "geometry": {"coordinates":[-79.586601,43.558506],"type":"Point"}
}