{
  "type": "Feature",
  "properties": {
    "addr:full":"1292 Plank Rd Sarnia ON N7T 7H3",
    "addr:housenumber":"1292",
    "addr:postcode":"n7t 7h3",
    "addr:street":"Plank Rd",
    "iso:country":"CA",
    "sg:address":"1292 Plank Rd",
    "sg:city":"Sarnia",
    "sg:classifiers":[
        {
            "category":"Wholesale",
            "subcategory":"Metals & Minerals",
            "type":"Manufacturing & Wholesale Goods"
        }
    ],
    "sg:phone":"+1 519 336 1556",
    "sg:postcode":"N7T 7H3",
    "sg:province":"ON",
    "sg:tags":[
        "steel",
        "warehouse"
    ],
    "wof:name":"Huron Alloys Inc",
    "wof:placetype":"venue"
},
  "geometry": {"coordinates":[-82.370209,42.952221],"type":"Point"}
}