{
  "type": "Feature",
  "properties": {
    "addr:full":"6400 Valley Way Niagara Falls ON L2E 7E3",
    "addr:housenumber":"6400",
    "addr:postcode":"l2e 7e3",
    "addr:street":"Valley Way",
    "iso:country":"CA",
    "sg:address":"6400 Valley Way",
    "sg:city":"Niagara Falls",
    "sg:classifiers":[
        {
            "category":"Health Services",
            "subcategory":"Nursing And Care Facility",
            "type":"Services"
        }
    ],
    "sg:phone":"+1 905 358 3277",
    "sg:postcode":"L2E 7E3",
    "sg:province":"ON",
    "sg:tags":[
        "home",
        "convalescent"
    ],
    "wof:name":"Valley Park Lodge",
    "wof:placetype":"venue"
},
  "geometry": {"coordinates":[-79.101501,43.098156],"type":"Point"}
}