{
  "type": "Feature",
  "properties": {
    "addr:full":"507 Rue Marquis Saint-Celestin QC J0C 1G0",
    "addr:housenumber":"507",
    "addr:postcode":"j0c 1g0",
    "addr:street":"Rue Marquis Saint-Celestin",
    "iso:country":"CA",
    "sg:address":"507 Rue Marquis",
    "sg:city":"Saint-Celestin",
    "sg:classifiers":[
        {
            "category":"Autos & Motor Vehicles",
            "subcategory":"Fuel & Gas Station",
            "type":"Retail Goods"
        }
    ],
    "sg:phone":"+1 819 229 3450",
    "sg:postcode":"J0C 1G0",
    "sg:province":"QC",
    "sg:tags":[
        "oil"
    ],
    "wof:name":"Garage Roy Et Dionne Inc",
    "wof:placetype":"venue"
},
  "geometry": {"coordinates":[-72.4322891235,46.2132797241],"type":"Point"}
}