{
  "type": "Feature",
  "properties": {
    "addr:full":"102 Ch D'Aigremont Lorraine QC J6Z 4P2",
    "addr:housenumber":"102",
    "addr:postcode":"j6z 4p2",
    "addr:street":"Ch D'Aigremont",
    "iso:country":"CA",
    "sg:address":"102 Ch D'Aigremont",
    "sg:city":"Lorraine",
    "sg:classifiers":[
        {
            "category":"Building & Trades",
            "subcategory":"Cleaning & Sanitation",
            "type":"Services"
        }
    ],
    "sg:phone":"+1 450 965 8111",
    "sg:postcode":"J6Z 4P2",
    "sg:province":"QC",
    "sg:tags":[
        "window"
    ],
    "wof:name":"Lavexpert Inc",
    "wof:placetype":"venue"
},
  "geometry": {"coordinates":[-73.778946,45.67252],"type":"Point"}
}