{
  "type": "Feature",
  "properties": {
    "addr:full":"21 Rue Gourd Amos QC J9T 3V3",
    "addr:housenumber":"21",
    "addr:postcode":"j9t 3v3",
    "addr:street":"Rue Gourd Amos",
    "iso:country":"CA",
    "sg:address":"21 Rue Gourd",
    "sg:city":"Amos",
    "sg:classifiers":[
        {
            "category":"Retail",
            "subcategory":"Veterinary Services",
            "type":"Services"
        }
    ],
    "sg:phone":"+1 819 732 2124",
    "sg:postcode":"J9T 3V3",
    "sg:province":"QC",
    "sg:tags":[
        "veterinarian"
    ],
    "wof:name":"Gervais, Paul DVM",
    "wof:placetype":"venue"
},
  "geometry": {"coordinates":[-78.129456,48.577759],"type":"Point"}
}