{
  "type": "Feature",
  "properties": {
    "addr:full":"3773 Strandherd Dr Nepean ON K2J 4B1",
    "addr:housenumber":"3773",
    "addr:postcode":"k2j 4b1",
    "addr:street":"Strandherd Dr",
    "iso:country":"CA",
    "sg:address":"3773 Strandherd Dr",
    "sg:city":"Nepean",
    "sg:classifiers":[
        {
            "category":"Restaurant",
            "type":"Food & Drink"
        }
    ],
    "sg:phone":"+1 613 823 7838",
    "sg:postcode":"K2J 4B1",
    "sg:province":"ON",
    "wof:name":"Mc Donald's",
    "wof:placetype":"venue"
},
  "geometry": {"coordinates":[-75.7477645874,45.2698287964],"type":"Point"}
}