{
  "type": "Feature",
  "properties": {
    "addr:full":"Montreal QC H3G 1N2",
    "addr:postcode":"h3g 1n2",
    "iso:country":"CA",
    "sg:city":"Montreal",
    "sg:classifiers":[
        {
            "category":"Real Estate",
            "subcategory":"Real Estate Agent",
            "type":"Services"
        }
    ],
    "sg:phone":"+1 514 846 1610",
    "sg:postcode":"H3G 1N2",
    "sg:province":"QC",
    "sg:tags":[
        "investment"
    ],
    "wof:name":"Kemor Properties",
    "wof:placetype":"venue"
},
  "geometry": {"coordinates":[-73.5551452637,45.5215492249],"type":"Point"}
}