{
  "type": "Feature",
  "properties": {
    "addr:full":"154 Rue Laurent Granby QC J2J 1V1",
    "addr:housenumber":"154",
    "addr:postcode":"j2j 1v1",
    "addr:street":"Rue Laurent",
    "iso:country":"CA",
    "sg:address":"154 Rue Laurent",
    "sg:city":"Granby",
    "sg:classifiers":[
        {
            "category":"Real Estate",
            "subcategory":"Real Estate Agent",
            "type":"Services"
        }
    ],
    "sg:phone":"+1 450 378 4347",
    "sg:postcode":"J2J 1V1",
    "sg:province":"QC",
    "wof:name":"Immeubles Jean-Paul Roy Inc",
    "wof:placetype":"venue"
},
  "geometry": {"coordinates":[-72.7565612793,45.4026107788],"type":"Point"}
}