{
  "type": "Feature",
  "properties": {
    "addr:full":"Montreal QC H2N 2E3",
    "addr:postcode":"h2n 2e3",
    "iso:country":"CA",
    "sg:city":"Montreal",
    "sg:classifiers":[
        {
            "category":"Travel",
            "subcategory":"Travel Agent",
            "type":"Entertainment"
        }
    ],
    "sg:phone":"+1 514 385 3885",
    "sg:postcode":"H2N 2E3",
    "sg:province":"QC",
    "sg:tags":[
        "agency",
        "bureau"
    ],
    "wof:name":"Voyages Lindberg",
    "wof:placetype":"venue"
},
  "geometry": {"coordinates":[-73.660141,45.53886],"type":"Point"}
}