{
  "type": "Feature",
  "properties": {
    "addr:full":"238 Durham St E Walkerton ON N0G 2V0",
    "addr:housenumber":"238",
    "addr:postcode":"n0g 2v0",
    "addr:street":"Durham St E Walkerton",
    "iso:country":"CA",
    "sg:address":"238 Durham St E",
    "sg:city":"Walkerton",
    "sg:classifiers":[
        {
            "category":"Shopping",
            "subcategory":"Jewelry",
            "type":"Retail Goods"
        }
    ],
    "sg:phone":"+1 519 881 1700",
    "sg:postcode":"N0G 2V0",
    "sg:province":"ON",
    "sg:tags":[
        "jeweler"
    ],
    "wof:name":"Victor Lair Jeweller",
    "wof:placetype":"venue"
},
  "geometry": {"coordinates":[-81.149406,44.133415],"type":"Point"}
}