{
  "type": "Feature",
  "properties": {
    "iso:country":"CA",
    "sg:city":"Montreal",
    "sg:classifiers":[
        {
            "category":"Wholesale",
            "subcategory":"Durable Goods & Equipment",
            "type":"Manufacturing & Wholesale Goods"
        }
    ],
    "sg:phone":"+1 514 270 3933",
    "sg:postcode":"H2N 1C8",
    "sg:province":"QC",
    "sg:tags":[
        "importer"
    ],
    "wof:name":"Billion Star Inc",
    "wof:placetype":"venue"
},
  "geometry": {"coordinates":[-73.652618,45.54213],"type":"Point"}
}