{
  "type": "Feature",
  "properties": {
    "addr:full":"28 Northside Rd Nepean ON K2H 5Z3",
    "addr:housenumber":"28",
    "addr:postcode":"k2h 5z3",
    "addr:street":"Northside Rd",
    "iso:country":"CA",
    "sg:address":"28 Northside Rd",
    "sg:city":"Nepean",
    "sg:classifiers":[
        {
            "category":"Professional",
            "subcategory":"Lawyer & Legal Services",
            "type":"Services"
        }
    ],
    "sg:phone":"+1 613 829 7171",
    "sg:postcode":"K2H 5Z3",
    "sg:province":"ON",
    "sg:tags":[
        "attorney"
    ],
    "wof:name":"Ferris, J Patrick",
    "wof:placetype":"venue"
},
  "geometry": {"coordinates":[-75.814278,45.329517],"type":"Point"}
}