{
  "type": "Feature",
  "properties": {
    "iso:country":"CA",
    "sg:address":"170 Boul Maisonneuve",
    "sg:city":"Hull",
    "sg:classifiers":[
        {
            "category":"Building & Trades",
            "subcategory":"Construction",
            "type":"Services"
        }
    ],
    "sg:phone":"+1 819 771 9362",
    "sg:postcode":"J8X 3N4",
    "sg:province":"QC",
    "sg:tags":[
        "roofing",
        "contractor"
    ],
    "wof:name":"Construction Crawford Inc",
    "wof:placetype":"venue"
},
  "geometry": {"coordinates":[-75.71282196040001,45.4310531616],"type":"Point"}
}