{
  "type": "Feature",
  "properties": {
    "iso:country":"CA",
    "sg:address":"1440 Glenora Dr",
    "sg:city":"London",
    "sg:classifiers":[
        {
            "category":"Education",
            "subcategory":"School",
            "type":"Public Place"
        }
    ],
    "sg:phone":"+1 519 433 2828",
    "sg:postcode":"N5X 1V2",
    "sg:province":"ON",
    "wof:name":"St Mark School",
    "wof:placetype":"venue"
},
  "geometry": {"coordinates":[-81.2366027832,43.0352096558],"type":"Point"}
}