{
  "type": "Feature",
  "properties": {
    "addr:full":"33 Isabella St #102 Toronto ON M4Y 2P7",
    "addr:housenumber":"33",
    "addr:postcode":"m4y 2p7",
    "addr:street":"Isabella St # 102",
    "iso:country":"CA",
    "sg:address":"33 Isabella St #102",
    "sg:city":"Toronto",
    "sg:classifiers":[
        {
            "category":"Shopping",
            "subcategory":"Computers & Home Electronics",
            "type":"Retail Goods"
        }
    ],
    "sg:phone":"+1 416 929 0511",
    "sg:postcode":"M4Y 2P7",
    "sg:province":"ON",
    "sg:tags":[
        "software"
    ],
    "wof:name":"Notarianni & Assoc",
    "wof:placetype":"venue"
},
  "geometry": {"coordinates":[-79.383865,43.667786],"type":"Point"}
}