{
  "type": "Feature",
  "properties": {
    "addr:full":"903 Pape Ave East York ON M4K 3V1",
    "addr:housenumber":"903",
    "addr:postcode":"m4k 3v1",
    "addr:street":"Pape Ave",
    "iso:country":"CA",
    "sg:address":"903 Pape Ave",
    "sg:city":"East York",
    "sg:classifiers":[
        {
            "category":"Building & Trades",
            "subcategory":"Construction",
            "type":"Services"
        }
    ],
    "sg:phone":"+1 416 465 5615",
    "sg:postcode":"M4K 3V1",
    "sg:province":"ON",
    "sg:tags":[
        "roofing",
        "contractor"
    ],
    "wof:name":"Blue Jay Roofing Ltd",
    "wof:placetype":"venue"
},
  "geometry": {"coordinates":[-79.346962,43.684803],"type":"Point"}
}