{
  "type": "Feature",
  "properties": {
    "addr:full":"420 Queen St Charlottetown PE C1A 4E6",
    "addr:housenumber":"420",
    "addr:postcode":"c1a 4e6",
    "addr:street":"Queen St",
    "iso:country":"CA",
    "sg:address":"420 Queen St",
    "sg:city":"Charlottetown",
    "sg:classifiers":[
        {
            "category":"Autos & Motor Vehicles",
            "subcategory":"Auto Supplies",
            "type":"Retail Goods"
        }
    ],
    "sg:phone":"+1 902 566 4555",
    "sg:postcode":"C1A 4E6",
    "sg:province":"PE",
    "sg:tags":[
        "automobile",
        "parts"
    ],
    "wof:name":"Napa Auto Parts",
    "wof:placetype":"venue"
},
  "geometry": {"coordinates":[-63.135479,46.241558],"type":"Point"}
}