{
  "type": "Feature",
  "properties": {
    "iso:country":"CA",
    "sg:address":"305 Franklin St",
    "sg:city":"Outlook",
    "sg:classifiers":[
        {
            "category":"Health Services",
            "subcategory":"Doctor",
            "type":"Services"
        }
    ],
    "sg:phone":"+1 306 867 8226",
    "sg:postcode":"S0L 2N0",
    "sg:province":"SK",
    "sg:tags":[
        "dentist"
    ],
    "wof:name":"Outlook Dental Clinic",
    "wof:placetype":"venue"
},
  "geometry": {"coordinates":[-107.053855896,51.4848327637],"type":"Point"}
}