{
  "type": "Feature",
  "properties": {
    "addr:full":"4371 Mayberry St # 100 Burnaby BC V5H 4H8",
    "addr:housenumber":"4371",
    "addr:postcode":"v5h 4h8",
    "addr:street":"Mayberry St # 100",
    "iso:country":"CA",
    "sg:address":"4371 Mayberry St # 100",
    "sg:city":"Burnaby",
    "sg:classifiers":[
        {
            "category":"Real Estate",
            "subcategory":"Real Estate Agent",
            "type":"Services"
        }
    ],
    "sg:phone":"+1 604 432 9801",
    "sg:postcode":"V5H 4H8",
    "sg:province":"BC",
    "sg:tags":[
        "cooperative"
    ],
    "wof:name":"Andras Place Housing CO-OP",
    "wof:placetype":"venue"
},
  "geometry": {"coordinates":[-123.009841919,49.2254905701],"type":"Point"}
}