{
  "type": "Feature",
  "properties": {
    "addr:full":"4904 49 St Consort AB T0C 1B0",
    "addr:housenumber":"4904",
    "addr:postcode":"t0c 1b0",
    "addr:street":"49 St",
    "iso:country":"CA",
    "sg:address":"4904 49 St",
    "sg:city":"Consort",
    "sg:classifiers":[
        {
            "category":"Building & Trades",
            "subcategory":"Electrical",
            "type":"Services"
        }
    ],
    "sg:phone":"+1 403 577 2632",
    "sg:postcode":"T0C 1B0",
    "sg:province":"AB",
    "sg:tags":[
        "electric",
        "contractor"
    ],
    "wof:name":"D A Electric Ltd",
    "wof:placetype":"venue"
},
  "geometry": {"coordinates":[-110.774032593,52.0073661804],"type":"Point"}
}