{
  "type": "Feature",
  "properties": {
    "addr:full":"42 Glendale Ave Lower Sackville NS B4C 3M1",
    "addr:housenumber":"42",
    "addr:postcode":"b4c 3m1",
    "addr:street":"Glendale Ave",
    "iso:country":"CA",
    "sg:address":"42 Glendale Ave",
    "sg:city":"Lower Sackville",
    "sg:classifiers":[
        {
            "category":"Freight",
            "type":"Transportation"
        }
    ],
    "sg:phone":"+1 902 450 5656",
    "sg:postcode":"B4C 3M1",
    "sg:province":"NS",
    "sg:tags":[
        "mover",
        "commercial"
    ],
    "wof:name":"Metro Self Storage",
    "wof:placetype":"venue"
},
  "geometry": {"coordinates":[-63.6569061279,44.7589988708],"type":"Point"}
}