{
  "type": "Feature",
  "properties": {
    "addr:full":"Dunnville ON N1A 2W7",
    "addr:postcode":"n1a 2w7",
    "iso:country":"CA",
    "sg:city":"Dunnville",
    "sg:classifiers":[
        {
            "category":"Manufacturing",
            "subcategory":"Printing",
            "type":"Manufacturing & Wholesale Goods"
        }
    ],
    "sg:phone":"+1 905 774 6934",
    "sg:postcode":"N1A 2W7",
    "sg:province":"ON",
    "sg:tags":[
        "printer"
    ],
    "wof:name":"Dunnville Printery",
    "wof:placetype":"venue"
},
  "geometry": {"coordinates":[-79.666634,42.941685],"type":"Point"}
}