{
  "type": "Feature",
  "properties": {
    "iso:country":"CA",
    "sg:address":"425 Locust St",
    "sg:city":"Burlington",
    "sg:classifiers":[
        {
            "category":"Personal",
            "subcategory":"Beauty Salon",
            "type":"Services"
        }
    ],
    "sg:phone":"+1 905 637 2325",
    "sg:postcode":"L7S 1T8",
    "sg:province":"ON",
    "wof:name":"Chiarelli Hair Design",
    "wof:placetype":"venue"
},
  "geometry": {"coordinates":[-79.79763793950001,43.3244476318],"type":"Point"}
}