{
  "type": "Feature",
  "properties": {
    "addr:full":"4810 Calgary Trail NW Edmonton AB T6H 5H5",
    "addr:housenumber":"4810",
    "addr:postcode":"t6h 5h5",
    "addr:street":"Calgary Trail Nw",
    "iso:country":"CA",
    "sg:address":"4810 Calgary Trail NW",
    "sg:city":"Edmonton",
    "sg:classifiers":[
        {
            "category":"Restaurant",
            "type":"Food & Drink"
        }
    ],
    "sg:phone":"+1 780 437 5616",
    "sg:postcode":"T6H 5H5",
    "sg:province":"AB",
    "wof:name":"Moose Factory",
    "wof:placetype":"venue"
},
  "geometry": {"coordinates":[-113.49511699999999,53.48584],"type":"Point"}
}