{
  "type": "Feature",
  "properties": {
    "addr:full":"PO Box 25025 Rpo Hiway Kitchener ON N2A 4A5",
    "addr:housenumber":"po box",
    "addr:postcode":"25025;n2a 4a5",
    "addr:street":"Hiway",
    "iso:country":"CA",
    "sg:address":"PO Box 25025 Rpo Hiway",
    "sg:city":"Kitchener",
    "sg:classifiers":[
        {
            "category":"Wholesale",
            "subcategory":"Electrical",
            "type":"Manufacturing & Wholesale Goods"
        }
    ],
    "sg:phone":"+1 519 576 5350",
    "sg:postcode":"N2A 4A5",
    "sg:province":"ON",
    "sg:tags":[
        "transformer"
    ],
    "wof:name":"Colitran Technology Inc",
    "wof:placetype":"venue"
},
  "geometry": {"coordinates":[-80.49304962159999,43.4512290955],"type":"Point"}
}