{
  "type": "Feature",
  "properties": {
    "iso:country":"CA",
    "sg:address":"207 Keefer Rd",
    "sg:city":"Thorold",
    "sg:classifiers":[
        {
            "category":"Personal",
            "subcategory":"Beauty Salon",
            "type":"Services"
        }
    ],
    "sg:phone":"+1 905 227 3111",
    "sg:postcode":"L2V 4N3",
    "sg:province":"ON",
    "wof:name":"Solace Hair Esthetics",
    "wof:placetype":"venue"
},
  "geometry": {"coordinates":[-79.217834,43.109634],"type":"Point"}
}