{
  "type": "Feature",
  "properties": {
    "iso:country":"CA",
    "sg:city":"Calgary",
    "sg:classifiers":[
        {
            "category":"Education",
            "subcategory":"Dance Studio",
            "type":"Public Place"
        }
    ],
    "sg:phone":"+1 403 281 8922",
    "sg:postcode":"T2W 4J3",
    "sg:province":"AB",
    "sg:tags":[
        "instruction",
        "dancing"
    ],
    "wof:name":"Elite Dance Academy",
    "wof:placetype":"venue"
},
  "geometry": {"coordinates":[-114.109207,50.940907],"type":"Point"}
}