{
  "type": "Feature",
  "properties": {
    "addr:full":"Gatineau QC J8T 8G5",
    "addr:postcode":"j8t 8g5",
    "iso:country":"CA",
    "sg:city":"Gatineau",
    "sg:classifiers":[
        {
            "category":"Retail",
            "subcategory":"Auto Repair",
            "type":"Services"
        }
    ],
    "sg:phone":"+1 819 243 7461",
    "sg:postcode":"J8T 8G5",
    "sg:province":"QC",
    "sg:tags":[
        "repairing",
        "automobile"
    ],
    "wof:name":"Auto Xtrem Inc",
    "wof:placetype":"venue"
},
  "geometry": {"coordinates":[-75.70768700000001,45.490181],"type":"Point"}
}