{
  "type": "Feature",
  "properties": {
    "iso:country":"CA",
    "sg:address":"1435 Rue Provancher",
    "sg:city":"Cap-Rouge",
    "sg:classifiers":[
        {
            "category":"Recreation",
            "type":"Entertainment"
        }
    ],
    "sg:phone":"+1 418 650 7785",
    "sg:postcode":"G1Y 1R9",
    "sg:province":"QC",
    "sg:tags":[
        "center",
        "hall",
        "auditorium"
    ],
    "wof:name":"Cap-Rouge Maison Provancher",
    "wof:placetype":"venue"
},
  "geometry": {"coordinates":[-71.343613,46.750916],"type":"Point"}
}