{
  "type": "Feature",
  "properties": {
    "addr:full":"2716 Rue Lapierre Lasalle QC H8N 2W9",
    "addr:housenumber":"2716",
    "addr:postcode":"h8n 2w9",
    "addr:street":"Rue Lapierre",
    "iso:country":"CA",
    "sg:address":"2716 Rue Lapierre",
    "sg:city":"Lasalle",
    "sg:classifiers":[
        {
            "category":"Professional",
            "subcategory":"Business Services",
            "type":"Services"
        }
    ],
    "sg:phone":"+1 514 368 3032",
    "sg:postcode":"H8N 2W9",
    "sg:province":"QC",
    "sg:tags":[
        "interior",
        "consultant",
        "design",
        "decorator"
    ],
    "wof:name":"H Chernoff Design",
    "wof:placetype":"venue"
},
  "geometry": {"coordinates":[-73.6314468384,45.4434547424],"type":"Point"}
}