{
  "type": "Feature",
  "properties": {
    "iso:country":"CA",
    "sg:address":"370 Rang 4",
    "sg:city":"Saint-Hilarion",
    "sg:classifiers":[
        {
            "category":"Wholesale",
            "subcategory":"Meat",
            "type":"Manufacturing & Wholesale Goods"
        }
    ],
    "sg:phone":"+1 418 457 3532",
    "sg:postcode":"G0A 3V0",
    "sg:province":"QC",
    "sg:tags":[
        "product"
    ],
    "wof:name":"Charcuterie Det Inc",
    "wof:placetype":"venue"
},
  "geometry": {"coordinates":[-70.36306762700001,47.6002120972],"type":"Point"}
}