{
  "type": "Feature",
  "properties": {
    "addr:full":"41 Elora Rd Alma ON N0B 1A0",
    "addr:housenumber":"41",
    "addr:postcode":"n0b 1a0",
    "addr:street":"Elora Rd",
    "iso:country":"CA",
    "sg:address":"41 Elora Rd",
    "sg:city":"Alma",
    "sg:classifiers":[
        {
            "category":"Recreation",
            "type":"Entertainment"
        }
    ],
    "sg:phone":"+1 519 846 8991",
    "sg:postcode":"N0B 1A0",
    "sg:province":"ON",
    "sg:tags":[
        "center"
    ],
    "wof:name":"Alma Community Hall",
    "wof:placetype":"venue"
},
  "geometry": {"coordinates":[-80.504425,43.731838],"type":"Point"}
}