{
  "type": "Feature",
  "properties": {
    "iso:country":"CA",
    "sg:address":"6082 Ch DE Chambly",
    "sg:city":"Saint-Hubert",
    "sg:classifiers":[
        {
            "category":"Retail",
            "subcategory":"Laundry & Dry Cleaning",
            "type":"Services"
        }
    ],
    "sg:phone":"+1 450 656 8421",
    "sg:postcode":"J3Y 3R5",
    "sg:province":"QC",
    "sg:tags":[
        "cleaners"
    ],
    "wof:name":"J L Martel Inc",
    "wof:placetype":"venue"
},
  "geometry": {"coordinates":[-73.404655,45.497669],"type":"Point"}
}