{
  "type": "Feature",
  "properties": {
    "addr:full":"949 Woodlawn Rd W Guelph ON N1K 1C9",
    "addr:housenumber":"949",
    "addr:postcode":"n1k 1c9",
    "addr:street":"Woodlawn Rd W",
    "iso:country":"CA",
    "sg:address":"949 Woodlawn Rd W",
    "sg:city":"Guelph",
    "sg:classifiers":[
        {
            "category":"Autos & Motor Vehicles",
            "subcategory":"Automobile Sales",
            "type":"Retail Goods"
        }
    ],
    "sg:phone":"+1 519 837 3020",
    "sg:postcode":"N1K 1C9",
    "sg:province":"ON",
    "sg:tags":[
        "car",
        "dealer"
    ],
    "wof:name":"Guelph City Mazda",
    "wof:placetype":"venue"
},
  "geometry": {"coordinates":[-80.320808,43.533791],"type":"Point"}
}