{
  "type": "Feature",
  "properties": {
    "addr:full":"6 John St Newboro ON K0G 1P0",
    "addr:housenumber":"6",
    "addr:postcode":"k0g 1p0",
    "addr:street":"John St",
    "iso:country":"CA",
    "sg:address":"6 John St",
    "sg:city":"Newboro",
    "sg:classifiers":[
        {
            "category":"Health Services",
            "subcategory":"Doctor",
            "type":"Services"
        }
    ],
    "sg:phone":"+1 613 272 2500",
    "sg:postcode":"K0G 1P0",
    "sg:province":"ON",
    "sg:tags":[
        "physician",
        "surgeon"
    ],
    "wof:name":"Rideau Medical Ctr",
    "wof:placetype":"venue"
},
  "geometry": {"coordinates":[-76.31759643549999,44.6533432007],"type":"Point"}
}