{
  "type": "Feature",
  "properties": {
    "addr:full":"249 Rue John-Nairne # 110 LA Malbaie QC G5A 1M4",
    "addr:housenumber":"249",
    "addr:postcode":"g5a 1m4",
    "addr:street":"Rue John-Nairne # 110",
    "iso:country":"CA",
    "sg:address":"249 Rue John-Nairne # 110",
    "sg:city":"LA Malbaie",
    "sg:classifiers":[
        {
            "category":"Manufacturing",
            "subcategory":"Printing",
            "type":"Manufacturing & Wholesale Goods"
        }
    ],
    "sg:phone":"+1 418 665 6121",
    "sg:postcode":"G5A 1M4",
    "sg:province":"QC",
    "sg:tags":[
        "newspaper"
    ],
    "wof:name":"Journal Plein Jour Inc",
    "wof:placetype":"venue"
},
  "geometry": {"coordinates":[-70.1509017944,47.6537704468],"type":"Point"}
}