{
  "type": "Feature",
  "properties": {
    "addr:full":"Chilliwack BC V2P 2N1",
    "addr:postcode":"v2p 2n1",
    "iso:country":"CA",
    "sg:city":"Chilliwack",
    "sg:classifiers":[
        {
            "category":"Autos & Motor Vehicles",
            "subcategory":"Auto Supplies",
            "type":"Retail Goods"
        }
    ],
    "sg:phone":"+1 604 792 0490",
    "sg:postcode":"V2P 2N1",
    "sg:province":"BC",
    "sg:tags":[
        "tire"
    ],
    "wof:name":"Abbsry Used Tires",
    "wof:placetype":"venue"
},
  "geometry": {"coordinates":[-121.96369199999999,49.152821],"type":"Point"}
}