{
  "type": "Feature",
  "properties": {
    "iso:country":"CA",
    "sg:city":"Black Lake",
    "sg:classifiers":[
        {
            "category":"Building & Trades",
            "subcategory":"Construction",
            "type":"Services"
        }
    ],
    "sg:phone":"+1 418 423 4395",
    "sg:postcode":"G6H 2M2",
    "sg:province":"QC",
    "sg:tags":[
        "excavating",
        "contractor"
    ],
    "wof:name":"Excavation Marcel Guerard Inc",
    "wof:placetype":"venue"
},
  "geometry": {"coordinates":[-71.392539978,46.0489082336],"type":"Point"}
}