{
  "type": "Feature",
  "properties": {
    "addr:full":"134 Main St Benito MB R0L 0C0",
    "addr:housenumber":"134",
    "addr:postcode":"r0l 0c0",
    "addr:street":"Main St",
    "iso:country":"CA",
    "sg:address":"134 Main St",
    "sg:city":"Benito",
    "sg:classifiers":[
        {
            "category":"Food & Beverages",
            "subcategory":"Specialty",
            "type":"Retail Goods"
        }
    ],
    "sg:phone":"+1 204 539 2659",
    "sg:postcode":"R0L 0C0",
    "sg:province":"MB",
    "sg:tags":[
        "health",
        "diet"
    ],
    "wof:name":"J K Borcz Health & Hobby Shop",
    "wof:placetype":"venue"
},
  "geometry": {"coordinates":[-101.55149078399999,51.917263031],"type":"Point"}
}