{
  "type": "Feature",
  "properties": {
    "addr:full":"69 Hamptons Dr NW Calgary AB T3A 5H7",
    "addr:housenumber":"69",
    "addr:postcode":"t3a 5h7",
    "addr:street":"Hamptons Dr Nw",
    "iso:country":"CA",
    "sg:address":"69 Hamptons Dr NW",
    "sg:city":"Calgary",
    "sg:classifiers":[
        {
            "category":"Recreation",
            "type":"Entertainment"
        }
    ],
    "sg:phone":"+1 403 239 1455",
    "sg:postcode":"T3A 5H7",
    "sg:province":"AB",
    "sg:tags":[
        "course",
        "golf"
    ],
    "wof:name":"Country Club of the Hamptons",
    "wof:placetype":"venue"
},
  "geometry": {"coordinates":[-114.146560669,51.1486282349],"type":"Point"}
}