{
  "type": "Feature",
  "properties": {
    "addr:full":"573 Goderich Port Elgin ON N0H 2C0",
    "addr:housenumber":"573",
    "addr:postcode":"n0h 2c0",
    "addr:street":"Goderich Port",
    "iso:country":"CA",
    "sg:address":"573 Goderich",
    "sg:city":"Port Elgin",
    "sg:classifiers":[
        {
            "category":"Health Services",
            "subcategory":"Optometrist",
            "type":"Services"
        }
    ],
    "sg:phone":"+1 519 832 9191",
    "sg:postcode":"N0H 2C0",
    "sg:province":"ON",
    "wof:name":"Thiel, R OD",
    "wof:placetype":"venue"
},
  "geometry": {"coordinates":[-81.3894577026,44.4352073669],"type":"Point"}
}