{
  "type": "Feature",
  "properties": {
    "iso:country":"CA",
    "sg:address":"255 Glen Miller Rd # 2",
    "sg:city":"Trenton",
    "sg:classifiers":[
        {
            "category":"Shopping",
            "type":"Retail Goods"
        }
    ],
    "sg:phone":"+1 613 394 0894",
    "sg:postcode":"K8V 5P8",
    "sg:province":"ON",
    "sg:tags":[
        "trophy",
        "sporting",
        "medal",
        "award"
    ],
    "wof:name":"Pegasus Sports & Trophies",
    "wof:placetype":"venue"
},
  "geometry": {"coordinates":[-77.58493804930001,44.1391792297],"type":"Point"}
}