{
  "type": "Feature",
  "properties": {
    "addr:full":"499 Seventh St Nanaimo BC V9R 1E6",
    "addr:housenumber":"499",
    "addr:postcode":"v9r 1e6",
    "addr:street":"Seventh St",
    "iso:country":"CA",
    "sg:address":"499 Seventh St",
    "sg:city":"Nanaimo",
    "sg:classifiers":[
        {
            "category":"Food & Beverages",
            "subcategory":"Groceries & Convenience Stores",
            "type":"Retail Goods"
        }
    ],
    "sg:phone":"+1 250 753 1229",
    "sg:postcode":"V9R 1E6",
    "sg:province":"BC",
    "sg:tags":[
        "grocer"
    ],
    "wof:name":"Ye Olde Corner Store",
    "wof:placetype":"venue"
},
  "geometry": {"coordinates":[-123.949295044,49.1475105286],"type":"Point"}
}