{
  "type": "Feature",
  "properties": {
    "addr:full":"100 Birchmount St London ON N6K 4K5",
    "addr:housenumber":"100",
    "addr:postcode":"n6k 4k5",
    "addr:street":"Birchmount St",
    "iso:country":"CA",
    "sg:address":"100 Birchmount St",
    "sg:city":"London",
    "sg:classifiers":[
        {
            "category":"Building & Trades",
            "subcategory":"Construction",
            "type":"Services"
        }
    ],
    "sg:phone":"+1 519 474 7453",
    "sg:postcode":"N6K 4K5",
    "sg:province":"ON",
    "sg:tags":[
        "contractor"
    ],
    "wof:name":"Vander Molen Homes",
    "wof:placetype":"venue"
},
  "geometry": {"coordinates":[-81.30554199220001,42.9396896362],"type":"Point"}
}