{
  "type": "Feature",
  "properties": {
    "addr:full":"Davidson SK S0G 1A0",
    "addr:postcode":"s0g 1a0",
    "iso:country":"CA",
    "sg:city":"Davidson",
    "sg:classifiers":[
        {
            "category":"Insurance",
            "subcategory":"Insurance Agent",
            "type":"Services"
        }
    ],
    "sg:phone":"+1 306 567 2101",
    "sg:postcode":"S0G 1A0",
    "sg:province":"SK",
    "wof:name":"Frier Agencies Ltd",
    "wof:placetype":"venue"
},
  "geometry": {"coordinates":[-105.990669,51.263474],"type":"Point"}
}