{
  "type": "Feature",
  "properties": {
    "addr:full":"Vancouver BC V6A 1H9",
    "addr:postcode":"v6a 1h9",
    "iso:country":"CA",
    "sg:city":"Vancouver",
    "sg:classifiers":[
        {
            "category":"Building & Trades",
            "subcategory":"Construction",
            "type":"Services"
        }
    ],
    "sg:phone":"+1 604 251 6565",
    "sg:postcode":"V6A 1H9",
    "sg:province":"BC",
    "sg:tags":[
        "concrete",
        "contractor"
    ],
    "wof:name":"Pro-Crete West",
    "wof:placetype":"venue"
},
  "geometry": {"coordinates":[-123.08332799999999,49.282722],"type":"Point"}
}