{
  "type": "Feature",
  "properties": {
    "addr:full":"277 Bering Ave Etobicoke ON M8Z 3A5",
    "addr:housenumber":"277",
    "addr:postcode":"m8z 3a5",
    "addr:street":"Bering Ave",
    "iso:country":"CA",
    "sg:address":"277 Bering Ave",
    "sg:city":"Etobicoke",
    "sg:classifiers":[
        {
            "category":"Building & Trades",
            "subcategory":"Plumbing",
            "type":"Services"
        }
    ],
    "sg:phone":"+1 416 239 6000",
    "sg:postcode":"M8Z 3A5",
    "sg:province":"ON",
    "sg:tags":[
        "contractor"
    ],
    "wof:name":"Niagara Water Svc",
    "wof:placetype":"venue"
},
  "geometry": {"coordinates":[-79.52597,43.638142],"type":"Point"}
}