{
  "type": "Feature",
  "properties": {
    "addr:full":"3951 Rue Des Peupliers LA Dore QC G8J 1E4",
    "addr:housenumber":"3951",
    "addr:postcode":"g8j 1e4",
    "addr:street":"Rue Des Peupliers La Dore",
    "iso:country":"CA",
    "sg:address":"3951 Rue Des Peupliers",
    "sg:city":"LA Dore",
    "sg:classifiers":[
        {
            "category":"Organizations",
            "subcategory":"Professional Association",
            "type":"Services"
        }
    ],
    "sg:phone":"+1 418 256 3821",
    "sg:postcode":"G8J 1E4",
    "sg:province":"QC",
    "wof:name":"Corporation Du Moulin Eau",
    "wof:placetype":"venue"
},
  "geometry": {"coordinates":[-72.63748168950001,48.7030448914],"type":"Point"}
}