{
  "type": "Feature",
  "properties": {
    "iso:country":"CA",
    "sg:address":"1195 Courtneypark Dr E",
    "sg:city":"Mississauga",
    "sg:classifiers":[
        {
            "category":"Home & Garden",
            "subcategory":"Garden Supply",
            "type":"Retail Goods"
        }
    ],
    "sg:phone":"+1 905 565 0265",
    "sg:postcode":"L5T 1R1",
    "sg:province":"ON",
    "sg:tags":[
        "lawn",
        "mower"
    ],
    "wof:name":"Murray Canada Inc",
    "wof:placetype":"venue"
},
  "geometry": {"coordinates":[-79.6634521484,43.6589775085],"type":"Point"}
}