{
  "type": "Feature",
  "properties": {
    "addr:full":"93 Hemlo Dr Marathon ON P0T 2E0",
    "addr:housenumber":"93",
    "addr:postcode":"p0t 2e0",
    "addr:street":"Hemlo Dr",
    "iso:country":"CA",
    "sg:address":"93 Hemlo Dr",
    "sg:city":"Marathon",
    "sg:classifiers":[
        {
            "category":"Retail",
            "subcategory":"Repair Shop",
            "type":"Services"
        }
    ],
    "sg:phone":"+1 807 229 1459",
    "sg:postcode":"P0T 2E0",
    "sg:province":"ON",
    "sg:tags":[
        "lock",
        "locksmith"
    ],
    "wof:name":"Peter Courchesne Locksmith",
    "wof:placetype":"venue"
},
  "geometry": {"coordinates":[-86.378593,48.705517],"type":"Point"}
}