{
  "type": "Feature",
  "properties": {
    "addr:full":"295 Rue Cockburn Drummondville QC J2C 5X6",
    "addr:housenumber":"295",
    "addr:postcode":"j2c 5x6",
    "addr:street":"Rue Cockburn",
    "iso:country":"CA",
    "sg:address":"295 Rue Cockburn",
    "sg:city":"Drummondville",
    "sg:classifiers":[
        {
            "category":"Government",
            "subcategory":"Office",
            "type":"Public Place"
        }
    ],
    "sg:phone":"+1 819 474 1227",
    "sg:postcode":"J2C 5X6",
    "sg:province":"QC",
    "sg:tags":[
        "city",
        "hall"
    ],
    "wof:name":"Office Municipal D'Habitation",
    "wof:placetype":"venue"
},
  "geometry": {"coordinates":[-72.493431,45.883022],"type":"Point"}
}