{
  "type": "Feature",
  "properties": {
    "addr:full":"1st St & Church Ave Grouard AB T0G 1C0",
    "addr:postcode":"t0g 1c0",
    "addr:street":"1St St & Church Ave",
    "iso:country":"CA",
    "sg:address":"1st St & Church Ave",
    "sg:city":"Grouard",
    "sg:classifiers":[
        {
            "category":"Education",
            "subcategory":"School",
            "type":"Public Place"
        }
    ],
    "sg:phone":"+1 780 751 3772",
    "sg:postcode":"T0G 1C0",
    "sg:province":"AB",
    "wof:name":"Grouard Northland School",
    "wof:placetype":"venue"
},
  "geometry": {"coordinates":[-116.148582,55.525387],"type":"Point"}
}