{
  "type": "Feature",
  "properties": {
    "addr:full":"266 King Rd Nanaimo BC V9R 6H9",
    "addr:housenumber":"266",
    "addr:postcode":"v9r 6h9",
    "addr:street":"King Rd",
    "iso:country":"CA",
    "sg:address":"266 King Rd",
    "sg:city":"Nanaimo",
    "sg:classifiers":[
        {
            "category":"Manufacturing",
            "subcategory":"Tools & Machinery",
            "type":"Manufacturing & Wholesale Goods"
        }
    ],
    "sg:phone":"+1 250 754 1010",
    "sg:postcode":"V9R 6H9",
    "sg:province":"BC",
    "sg:tags":[
        "polishing",
        "equipment",
        "station",
        "washing",
        "car"
    ],
    "wof:name":"Westech Maintenance & Repairs",
    "wof:placetype":"venue"
},
  "geometry": {"coordinates":[-123.982543945,49.1641082764],"type":"Point"}
}