{
  "type": "Feature",
  "properties": {
    "addr:full":"1720 Bow Valley Trail Canmore AB T1W 2X3",
    "addr:housenumber":"1720",
    "addr:postcode":"t1w 2x3",
    "addr:street":"Bow Valley Trail",
    "iso:country":"CA",
    "sg:address":"1720 Bow Valley Trail",
    "sg:city":"Canmore",
    "sg:classifiers":[
        {
            "category":"Personal",
            "type":"Services"
        }
    ],
    "sg:phone":"+1 403 678 6699",
    "sg:postcode":"T1W 2X3",
    "sg:province":"AB",
    "sg:tags":[
        "reservation",
        "motel",
        "therapist",
        "massage",
        "hotel"
    ],
    "wof:name":"Quality Resort-Chateau Canmore",
    "wof:placetype":"venue"
},
  "geometry": {"coordinates":[-115.359528,51.09885],"type":"Point"}
}