{
  "type": "Feature",
  "properties": {
    "iso:country":"CA",
    "sg:address":"89 Toll Rd",
    "sg:city":"Holland Landing",
    "sg:classifiers":[
        {
            "category":"Home & Garden",
            "subcategory":"Household Appliances",
            "type":"Retail Goods"
        }
    ],
    "sg:phone":"+1 905 836 1331",
    "sg:postcode":"L9N 1G7",
    "sg:province":"ON",
    "wof:name":"Andy's Appliance Repair Svc",
    "wof:placetype":"venue"
},
  "geometry": {"coordinates":[-79.506362915,44.1036224365],"type":"Point"}
}