{
  "type": "Feature",
  "properties": {
    "iso:country":"CA",
    "sg:address":"709 Topsail Rd",
    "sg:city":"Mount Pearl",
    "sg:classifiers":[
        {
            "category":"Retail",
            "subcategory":"Auto Rental",
            "type":"Services"
        }
    ],
    "sg:phone":"+1 709 748 2105",
    "sg:postcode":"A1N 3N4",
    "sg:province":"NL",
    "sg:tags":[
        "renting",
        "automobile"
    ],
    "wof:name":"Discount Car & Truck Rental",
    "wof:placetype":"venue"
},
  "geometry": {"coordinates":[-52.7773361206,47.5229454041],"type":"Point"}
}