{
  "type": "Feature",
  "properties": {
    "addr:full":"39 Woodman's Chart Markham ON L3R 6K8",
    "addr:housenumber":"39",
    "addr:postcode":"l3r 6k8",
    "addr:street":"Woodman'S Chart",
    "iso:country":"CA",
    "sg:address":"39 Woodman's Chart",
    "sg:city":"Markham",
    "sg:classifiers":[
        {
            "category":"Insurance",
            "subcategory":"Insurance Agent",
            "type":"Services"
        }
    ],
    "sg:phone":"+1 905 305 1144",
    "sg:postcode":"L3R 6K8",
    "sg:province":"ON",
    "wof:name":"J L Kucher Financial Ins Svc",
    "wof:placetype":"venue"
},
  "geometry": {"coordinates":[-79.33992000000001,43.85603],"type":"Point"}
}