{
  "type": "Feature",
  "properties": {
    "addr:full":"815 Boul DE LA Cote-Vertu Saint-Laurent QC H4L 1Y6",
    "addr:housenumber":"815",
    "addr:postcode":"h4l 1y6",
    "addr:street":"Boul De La Cote-Vertu",
    "iso:country":"CA",
    "sg:address":"815 Boul DE LA Cote-Vertu",
    "sg:city":"Saint-Laurent",
    "sg:classifiers":[
        {
            "category":"Health Services",
            "subcategory":"Doctor",
            "type":"Services"
        }
    ],
    "sg:phone":"+1 514 748 0251",
    "sg:postcode":"H4L 1Y6",
    "sg:province":"QC",
    "sg:tags":[
        "clinic"
    ],
    "wof:name":"Gestion Avicienne",
    "wof:placetype":"venue"
},
  "geometry": {"coordinates":[-73.6754074097,45.5201263428],"type":"Point"}
}