{
  "type": "Feature",
  "properties": {
    "iso:country":"CA",
    "sg:city":"Calgary",
    "sg:classifiers":[
        {
            "category":"Wholesale",
            "subcategory":"Office Equipment",
            "type":"Manufacturing & Wholesale Goods"
        }
    ],
    "sg:phone":"+1 403 264 5851",
    "sg:postcode":"T2P 1B7",
    "sg:province":"AB",
    "sg:tags":[
        "register",
        "cash",
        "supply"
    ],
    "wof:name":"General Cash Registers",
    "wof:placetype":"venue"
},
  "geometry": {"coordinates":[-114.066154,51.045479],"type":"Point"}
}