{
  "type": "Feature",
  "properties": {
    "addr:full":"1481 Rue Denault Sherbrooke QC J1H 2R1",
    "addr:housenumber":"1481",
    "addr:postcode":"j1h 2r1",
    "addr:street":"Rue Denault",
    "iso:country":"CA",
    "sg:address":"1481 Rue Denault",
    "sg:city":"Sherbrooke",
    "sg:classifiers":[
        {
            "category":"Retail",
            "subcategory":"Auto Repair",
            "type":"Services"
        }
    ],
    "sg:phone":"+1 819 569 4410",
    "sg:postcode":"J1H 2R1",
    "sg:province":"QC",
    "sg:tags":[
        "repairing",
        "automobile"
    ],
    "wof:name":"Claude Silencieux Enr",
    "wof:placetype":"venue"
},
  "geometry": {"coordinates":[-71.9122467041,45.3890419006],"type":"Point"}
}