{
  "type": "Feature",
  "properties": {
    "addr:full":"4861 Boul Des Sources Pierrefonds QC H8Y 3C8",
    "addr:housenumber":"4861",
    "addr:postcode":"h8y 3c8",
    "addr:street":"Boul Des Sources",
    "iso:country":"CA",
    "sg:address":"4861 Boul Des Sources",
    "sg:city":"Pierrefonds",
    "sg:classifiers":[
        {
            "category":"Health Services",
            "subcategory":"Doctor",
            "type":"Services"
        }
    ],
    "sg:phone":"+1 514 683 6425",
    "sg:postcode":"H8Y 3C8",
    "sg:province":"QC",
    "sg:tags":[
        "clinic",
        "dentist"
    ],
    "wof:name":"Bertrand Daoust Dental Office",
    "wof:placetype":"venue"
},
  "geometry": {"coordinates":[-73.81785600000001,45.505093],"type":"Point"}
}