{
  "type": "Feature",
  "properties": {
    "addr:full":"Hardisty AB T0B 1V0",
    "addr:postcode":"t0b 1v0",
    "iso:country":"CA",
    "sg:city":"Hardisty",
    "sg:classifiers":[
        {
            "category":"Insurance",
            "subcategory":"Insurance Agent",
            "type":"Services"
        }
    ],
    "sg:phone":"+1 780 888 3738",
    "sg:postcode":"T0B 1V0",
    "sg:province":"AB",
    "wof:name":"Hardisty Insurance Svc",
    "wof:placetype":"venue"
},
  "geometry": {"coordinates":[-111.303451538,52.6759300232],"type":"Point"}
}