{
  "type": "Feature",
  "properties": {
    "addr:full":"400 Sandwich St S Amherstburg ON N9V 3L4",
    "addr:housenumber":"400",
    "addr:postcode":"n9v 3l4",
    "addr:street":"Sandwich St S",
    "iso:country":"CA",
    "sg:address":"400 Sandwich St S",
    "sg:city":"Amherstburg",
    "sg:classifiers":[
        {
            "category":"Professional",
            "subcategory":"Accounting & Tax Preparation",
            "type":"Services"
        }
    ],
    "sg:phone":"+1 519 736 2191",
    "sg:postcode":"N9V 3L4",
    "sg:province":"ON",
    "sg:tags":[
        "return",
        "filing"
    ],
    "wof:name":"H & R Block Canada Inc",
    "wof:placetype":"venue"
},
  "geometry": {"coordinates":[-83.108284,42.097134],"type":"Point"}
}