{
  "type": "Feature",
  "properties": {
    "addr:full":"61 Linacre Rd Winnipeg MB R3T 3G7",
    "addr:housenumber":"61",
    "addr:postcode":"r3t 3g7",
    "addr:street":"Linacre Rd",
    "iso:country":"CA",
    "sg:address":"61 Linacre Rd",
    "sg:city":"Winnipeg",
    "sg:classifiers":[
        {
            "category":"Real Estate",
            "subcategory":"Developer",
            "type":"Services"
        }
    ],
    "sg:phone":"+1 204 269 4119",
    "sg:postcode":"R3T 3G7",
    "sg:province":"MB",
    "sg:tags":[
        "cemetery"
    ],
    "wof:name":"Mennonite Memorial Gardens",
    "wof:placetype":"venue"
},
  "geometry": {"coordinates":[-97.1397018433,49.7945175171],"type":"Point"}
}