{
  "type": "Feature",
  "properties": {
    "addr:full":"176 Edendale Way NW Calgary AB T3A 3X2",
    "addr:housenumber":"176",
    "addr:postcode":"t3a 3x2",
    "addr:street":"Edendale Way Nw",
    "iso:country":"CA",
    "sg:address":"176 Edendale Way NW",
    "sg:city":"Calgary",
    "sg:classifiers":[
        {
            "category":"Mining & Drilling",
            "type":"Manufacturing & Wholesale Goods"
        }
    ],
    "sg:phone":"+1 403 265 1770",
    "sg:postcode":"T3A 3X2",
    "sg:province":"AB",
    "sg:tags":[
        "consultant",
        "oil",
        "gas"
    ],
    "wof:name":"Nrc Consulting Ltd",
    "wof:placetype":"venue"
},
  "geometry": {"coordinates":[-114.14643859900001,51.1245002747],"type":"Point"}
}