{
  "type": "Feature",
  "properties": {
    "addr:full":"800 Arrow Rd North York ON M9M 2Z8",
    "addr:housenumber":"800",
    "addr:postcode":"m9m 2z8",
    "addr:street":"Arrow Rd",
    "iso:country":"CA",
    "sg:address":"800 Arrow Rd",
    "sg:city":"North York",
    "sg:classifiers":[
        {
            "category":"Building & Trades",
            "subcategory":"Construction",
            "type":"Services"
        }
    ],
    "sg:phone":"+1 416 743 7666",
    "sg:postcode":"M9M 2Z8",
    "sg:province":"ON",
    "sg:tags":[
        "dry wall",
        "contractor"
    ],
    "wof:name":"Little Brothers Drywall CO",
    "wof:placetype":"venue"
},
  "geometry": {"coordinates":[-79.531288,43.748123],"type":"Point"}
}