{
  "type": "Feature",
  "properties": {
    "addr:full":"3150 American Dr Mississauga ON L4V 1B4",
    "addr:housenumber":"3150",
    "addr:postcode":"l4v 1b4",
    "addr:street":"American Dr",
    "iso:country":"CA",
    "sg:address":"3150 American Dr",
    "sg:city":"Mississauga",
    "sg:classifiers":[
        {
            "category":"Wholesale",
            "subcategory":"Machinery & Supplies",
            "type":"Manufacturing & Wholesale Goods"
        }
    ],
    "sg:phone":"+1 905 677 3270",
    "sg:postcode":"L4V 1B4",
    "sg:province":"ON",
    "sg:tags":[
        "truck"
    ],
    "wof:name":"Liftow Limited",
    "wof:placetype":"venue"
},
  "geometry": {"coordinates":[-79.617836,43.692513],"type":"Point"}
}