{
  "type": "Feature",
  "properties": {
    "addr:full":"Guelph ON N1G 2X6",
    "addr:postcode":"n1g 2x6",
    "iso:country":"CA",
    "sg:city":"Guelph",
    "sg:classifiers":[
        {
            "category":"Food & Beverages",
            "subcategory":"Bakery",
            "type":"Retail Goods"
        }
    ],
    "sg:phone":"+1 519 837 3060",
    "sg:postcode":"N1G 2X6",
    "sg:province":"ON",
    "sg:tags":[
        "tea",
        "coffee",
        "doughnut"
    ],
    "wof:name":"Tim Hortons",
    "wof:placetype":"venue"
},
  "geometry": {"coordinates":[-80.2378158569,43.5170860291],"type":"Point"}
}