{
  "type": "Feature",
  "properties": {
    "addr:full":"10873 Oxbow Dr Komoka ON N0L 1R0",
    "addr:housenumber":"10873",
    "addr:postcode":"n0l 1r0",
    "addr:street":"Oxbow Dr",
    "iso:country":"CA",
    "sg:address":"10873 Oxbow Dr",
    "sg:city":"Komoka",
    "sg:classifiers":[
        {
            "category":"Building & Trades",
            "subcategory":"Electrical",
            "type":"Services"
        }
    ],
    "sg:phone":"+1 519 471 2130",
    "sg:postcode":"N0L 1R0",
    "sg:province":"ON",
    "sg:tags":[
        "electric",
        "contractor"
    ],
    "wof:name":"W P Osborne Elec London Ltd",
    "wof:placetype":"venue"
},
  "geometry": {"coordinates":[-81.401550293,42.9843292236],"type":"Point"}
}