{
  "type": "Feature",
  "properties": {
    "addr:full":"1392 Ch DE Chambly Longueuil QC J4J 3X3",
    "addr:postcode":"1392;j4j 3x3",
    "addr:street":"Ch De Chambly",
    "iso:country":"CA",
    "sg:address":"1392 Ch DE Chambly",
    "sg:city":"Longueuil",
    "sg:classifiers":[
        {
            "category":"Home & Garden",
            "subcategory":"Carpets & Floor Coverings",
            "type":"Retail Goods"
        }
    ],
    "sg:phone":"+1 450 677 2032",
    "sg:postcode":"J4J 3X3",
    "sg:province":"QC",
    "sg:tags":[
        "dealer",
        "rug"
    ],
    "wof:name":"Lamoureux & Frere Inc",
    "wof:placetype":"venue"
},
  "geometry": {"coordinates":[-73.48690000000001,45.531425],"type":"Point"}
}