{
  "type": "Feature",
  "properties": {
    "addr:full":"601 Wellington St N Kitchener ON N2H 5L6",
    "addr:housenumber":"601",
    "addr:postcode":"n2h 5l6",
    "addr:street":"Wellington St N",
    "iso:country":"CA",
    "sg:address":"601 Wellington St N",
    "sg:city":"Kitchener",
    "sg:classifiers":[
        {
            "category":"Organizations",
            "subcategory":"Professional Association",
            "type":"Services"
        }
    ],
    "sg:phone":"+1 519 742 7003",
    "sg:postcode":"N2H 5L6",
    "sg:province":"ON",
    "wof:name":"Canadian Legion",
    "wof:placetype":"venue"
},
  "geometry": {"coordinates":[-80.4786148071,43.4628219604],"type":"Point"}
}