{
  "type": "Feature",
  "properties": {
    "addr:full":"201 King George Hwy Miramichi NB E1V 1K8",
    "addr:housenumber":"201",
    "addr:postcode":"e1v 1k8",
    "addr:street":"King George Hwy",
    "iso:country":"CA",
    "sg:address":"201 King George Hwy",
    "sg:city":"Miramichi",
    "sg:classifiers":[
        {
            "category":"Home & Garden",
            "subcategory":"Carpets & Floor Coverings",
            "type":"Retail Goods"
        }
    ],
    "sg:phone":"+1 506 622 2363",
    "sg:postcode":"E1V 1K8",
    "sg:province":"NB",
    "sg:tags":[
        "dealer",
        "rug"
    ],
    "wof:name":"Carpet Man Ltd",
    "wof:placetype":"venue"
},
  "geometry": {"coordinates":[-65.5845489502,46.9775543213],"type":"Point"}
}