{
  "type": "Feature",
  "properties": {
    "addr:full":"675 Av Marguerite-Bourgeoys Quebec QC G1S 3V8",
    "addr:housenumber":"675",
    "addr:postcode":"g1s 3v8",
    "addr:street":"Av Marguerite-Bourgeoys",
    "iso:country":"CA",
    "sg:address":"675 Av Marguerite-Bourgeoys",
    "sg:city":"Quebec",
    "sg:classifiers":[
        {
            "category":"Recreation",
            "type":"Entertainment"
        }
    ],
    "sg:phone":"+1 418 656 4233",
    "sg:postcode":"G1S 3V8",
    "sg:province":"QC",
    "sg:tags":[
        "instruction",
        "yoga"
    ],
    "wof:name":"Lotus-Centre DE Yoga",
    "wof:placetype":"venue"
},
  "geometry": {"coordinates":[-71.25708770750001,46.7952575684],"type":"Point"}
}