{
  "type": "Feature",
  "properties": {
    "iso:country":"CA",
    "sg:city":"Brossard",
    "sg:classifiers":[
        {
            "category":"Wholesale",
            "subcategory":"Machinery & Supplies",
            "type":"Manufacturing & Wholesale Goods"
        }
    ],
    "sg:phone":"+1 450 923 1117",
    "sg:postcode":"J4X 1Z6",
    "sg:province":"QC",
    "sg:tags":[
        "equipment",
        "industrial"
    ],
    "wof:name":"Inspection Prevention Pro",
    "wof:placetype":"venue"
},
  "geometry": {"coordinates":[-73.490234,45.454742],"type":"Point"}
}