{
  "type": "Feature",
  "properties": {
    "addr:full":"505 Rue Notre-Dame # 124 Repentigny QC J6A 8K5",
    "addr:housenumber":"505",
    "addr:postcode":"j6a 8k5",
    "addr:street":"Rue Notre-Dame # 124",
    "iso:country":"CA",
    "sg:address":"505 Rue Notre-Dame # 124",
    "sg:city":"Repentigny",
    "sg:classifiers":[
        {
            "category":"Health Services",
            "subcategory":"Nursing And Care Facility",
            "type":"Services"
        }
    ],
    "sg:phone":"+1 450 582 9200",
    "sg:postcode":"J6A 8K5",
    "sg:province":"QC",
    "sg:tags":[
        "home",
        "retirement",
        "community"
    ],
    "wof:name":"Residence Le Notre-Dame",
    "wof:placetype":"venue"
},
  "geometry": {"coordinates":[-73.4426727295,45.7416152954],"type":"Point"}
}