{
  "type": "Feature",
  "properties": {
    "addr:full":"116 Carry Dr SE Medicine Hat AB T1B 3Z8",
    "addr:housenumber":"116",
    "addr:postcode":"t1b 3z8",
    "addr:street":"Carry Dr Se",
    "iso:country":"CA",
    "sg:address":"116 Carry Dr SE",
    "sg:city":"Medicine Hat",
    "sg:classifiers":[
        {
            "category":"Health Services",
            "subcategory":"Doctor",
            "type":"Services"
        }
    ],
    "sg:phone":"+1 403 528 3568",
    "sg:postcode":"T1B 3Z8",
    "sg:province":"AB",
    "sg:tags":[
        "physician",
        "surgeon"
    ],
    "wof:name":"Ruzycki, W A MD",
    "wof:placetype":"venue"
},
  "geometry": {"coordinates":[-110.643913,50.008034],"type":"Point"}
}