{
  "type": "Feature",
  "properties": {
    "addr:full":"Calgary AB T2E 8X2",
    "addr:postcode":"t2e 8x2",
    "iso:country":"CA",
    "sg:city":"Calgary",
    "sg:classifiers":[
        {
            "category":"Freight",
            "type":"Transportation"
        }
    ],
    "sg:phone":"+1 403 735 0560",
    "sg:postcode":"T2E 8X2",
    "sg:province":"AB",
    "sg:tags":[
        "broker",
        "customs"
    ],
    "wof:name":"Russell A Farrow Ltd",
    "wof:placetype":"venue"
},
  "geometry": {"coordinates":[-114.041359,51.12014],"type":"Point"}
}