{
  "type": "Feature",
  "properties": {
    "iso:country":"CA",
    "sg:address":"PO Box 33 STN Main",
    "sg:city":"Barrie",
    "sg:classifiers":[
        {
            "category":"Building & Trades",
            "subcategory":"Construction",
            "type":"Services"
        }
    ],
    "sg:phone":"+1 705 721 4336",
    "sg:postcode":"L4M 4S9",
    "sg:province":"ON",
    "sg:tags":[
        "general",
        "contractor"
    ],
    "wof:name":"Gilby Construction Ltd",
    "wof:placetype":"venue"
},
  "geometry": {"coordinates":[-79.6863250732,44.3893013],"type":"Point"}
}