{
  "type": "Feature",
  "properties": {
    "addr:full":"1762 Thrums Rd Castlegar BC V1N 4N4",
    "addr:housenumber":"1762",
    "addr:postcode":"v1n 4n4",
    "addr:street":"Thrums Rd",
    "iso:country":"CA",
    "sg:address":"1762 Thrums Rd",
    "sg:city":"Castlegar",
    "sg:classifiers":[
        {
            "category":"Home & Garden",
            "subcategory":"Furniture",
            "type":"Retail Goods"
        }
    ],
    "sg:phone":"+1 250 399 0030",
    "sg:postcode":"V1N 4N4",
    "sg:province":"BC",
    "sg:tags":[
        "windows",
        "kitchen",
        "cabinet"
    ],
    "wof:name":"Boardwalk Enterprises",
    "wof:placetype":"venue"
},
  "geometry": {"coordinates":[-117.65418243400001,49.2962532043],"type":"Point"}
}