{
  "type": "Feature",
  "properties": {
    "addr:full":"Ladysmith BC V9G 1A7",
    "addr:postcode":"v9g 1a7",
    "iso:country":"CA",
    "sg:city":"Ladysmith",
    "sg:classifiers":[
        {
            "category":"Real Estate",
            "subcategory":"Real Estate Agent",
            "type":"Services"
        }
    ],
    "sg:phone":"+1 250 245 3700",
    "sg:postcode":"V9G 1A7",
    "sg:province":"BC",
    "wof:name":"Re/Max Ocean Point Realty",
    "wof:placetype":"venue"
},
  "geometry": {"coordinates":[-123.82029724100001,48.9951019287],"type":"Point"}
}