{
  "type": "Feature",
  "properties": {
    "iso:country":"CA",
    "sg:address":"201 9E Rue",
    "sg:city":"Val-D'Or",
    "sg:classifiers":[
        {
            "category":"Organizations",
            "subcategory":"Community Association",
            "type":"Services"
        }
    ],
    "sg:phone":"+1 819 825 7135",
    "sg:postcode":"J9P 3K5",
    "sg:province":"QC",
    "sg:tags":[
        "club"
    ],
    "wof:name":"Club Des Handicapes",
    "wof:placetype":"venue"
},
  "geometry": {"coordinates":[-65.2350387573,48.0378379822],"type":"Point"}
}