{
  "type": "Feature",
  "properties": {
    "addr:full":"1091 102nd St # B North Battleford SK S9A 1E5",
    "addr:housenumber":"1091",
    "addr:postcode":"s9a 1e5",
    "addr:street":"102Nd St # B",
    "iso:country":"CA",
    "sg:address":"1091 102nd St # B",
    "sg:city":"North Battleford",
    "sg:classifiers":[
        {
            "category":"Banks & Credit Unions",
            "subcategory":"Bank",
            "type":"Services"
        }
    ],
    "sg:phone":"+1 306 445 5444",
    "sg:postcode":"S9A 1E5",
    "sg:province":"SK",
    "sg:tags":[
        "cashing",
        "check"
    ],
    "wof:name":"Cashplan",
    "wof:placetype":"venue"
},
  "geometry": {"coordinates":[-108.29631000000001,52.773144],"type":"Point"}
}