{
  "type": "Feature",
  "properties": {
    "iso:country":"CA",
    "sg:address":"3355 Ch Saint-Charles",
    "sg:city":"Lachenaie",
    "sg:classifiers":[
        {
            "category":"Government",
            "subcategory":"Office",
            "type":"Public Place"
        }
    ],
    "sg:phone":"+1 450 471 2424",
    "sg:postcode":"J6V 1A2",
    "sg:province":"QC",
    "sg:tags":[
        "city",
        "hall"
    ],
    "wof:name":"Centre Ludovic Laurier",
    "wof:placetype":"venue"
},
  "geometry": {"coordinates":[-73.5511856079,45.7013816833],"type":"Point"}
}