{
  "type": "Feature",
  "properties": {
    "addr:full":"215 Stafford St Winnipeg MB R3M 2X1",
    "addr:housenumber":"215",
    "addr:postcode":"r3m 2x1",
    "addr:street":"Stafford St",
    "iso:country":"CA",
    "sg:address":"215 Stafford St",
    "sg:city":"Winnipeg",
    "sg:classifiers":[
        {
            "category":"Shopping",
            "subcategory":"Clothing, Apparel, & Fashions",
            "type":"Retail Goods"
        }
    ],
    "sg:phone":"+1 204 475 0063",
    "sg:postcode":"R3M 2X1",
    "sg:province":"MB",
    "sg:tags":[
        "furnishing"
    ],
    "wof:name":"Lionetti Clothier & Custom Tlr",
    "wof:placetype":"venue"
},
  "geometry": {"coordinates":[-97.16264343260001,49.8693733215],"type":"Point"}
}