{
  "type": "Feature",
  "properties": {
    "addr:full":"820 Av Ogilvy Montreal QC H3N 1N8",
    "addr:housenumber":"820",
    "addr:postcode":"h3n 1n8",
    "addr:street":"Av Ogilvy",
    "iso:country":"CA",
    "sg:address":"820 Av Ogilvy",
    "sg:city":"Montreal",
    "sg:classifiers":[
        {
            "category":"Organizations",
            "subcategory":"Professional Association",
            "type":"Services"
        }
    ],
    "sg:phone":"+1 514 274 1335",
    "sg:postcode":"H3N 1N8",
    "sg:province":"QC",
    "wof:name":"Sykea Society of Canada",
    "wof:placetype":"venue"
},
  "geometry": {"coordinates":[-73.6265335083,45.5265464783],"type":"Point"}
}