{
  "type": "Feature",
  "properties": {
    "addr:full":"100 Mayfield Common NW Edmonton AB T5P 4B3",
    "addr:housenumber":"100",
    "addr:postcode":"t5p 4b3",
    "addr:street":"Mayfield Common Nw",
    "iso:country":"CA",
    "sg:address":"100 Mayfield Common NW",
    "sg:city":"Edmonton",
    "sg:classifiers":[
        {
            "category":"Wholesale",
            "subcategory":"Hardware",
            "type":"Manufacturing & Wholesale Goods"
        }
    ],
    "sg:phone":"+1 780 944 9600",
    "sg:postcode":"T5P 4B3",
    "sg:province":"AB",
    "sg:tags":[
        "compressor",
        "tool"
    ],
    "wof:name":"House of Tools",
    "wof:placetype":"venue"
},
  "geometry": {"coordinates":[-113.615432739,53.5435295105],"type":"Point"}
}