{
  "type": "Feature",
  "properties": {
    "addr:full":"4066 Drummond Rd Niagara Falls ON L2E 6B9",
    "addr:housenumber":"4066",
    "addr:postcode":"l2e 6b9",
    "addr:street":"Drummond Rd",
    "iso:country":"CA",
    "sg:address":"4066 Drummond Rd",
    "sg:city":"Niagara Falls",
    "sg:classifiers":[
        {
            "category":"Real Estate",
            "subcategory":"Real Estate Agent",
            "type":"Services"
        }
    ],
    "sg:phone":"+1 905 374 7170",
    "sg:postcode":"L2E 6B9",
    "sg:province":"ON",
    "sg:tags":[
        "management"
    ],
    "wof:name":"Stamford Realty Ltd",
    "wof:placetype":"venue"
},
  "geometry": {"coordinates":[-79.09912109379999,43.1144828796],"type":"Point"}
}