{
  "type": "Feature",
  "properties": {
    "iso:country":"CA",
    "sg:address":"230 42 Ave SE",
    "sg:city":"Calgary",
    "sg:classifiers":[
        {
            "category":"Home & Garden",
            "subcategory":"Building Materials",
            "type":"Retail Goods"
        }
    ],
    "sg:phone":"+1 403 243 6500",
    "sg:postcode":"T2G 1Y4",
    "sg:province":"AB",
    "sg:tags":[
        "lumber"
    ],
    "wof:name":"Timbertown Building Ctr Ltd",
    "wof:placetype":"venue"
},
  "geometry": {"coordinates":[-114.059890747,51.016078949],"type":"Point"}
}