{
  "type": "Feature",
  "properties": {
    "addr:full":"4242 Boul Saint-Laurent Montreal QC H2W 1Z3",
    "addr:housenumber":"4242",
    "addr:postcode":"h2w 1z3",
    "addr:street":"Boul Saint-Laurent",
    "iso:country":"CA",
    "sg:address":"4242 Boul Saint-Laurent",
    "sg:city":"Montreal",
    "sg:classifiers":[
        {
            "category":"Professional",
            "subcategory":"Business Services",
            "type":"Services"
        }
    ],
    "sg:phone":"+1 514 843 5626",
    "sg:postcode":"H2W 1Z3",
    "sg:province":"QC",
    "sg:tags":[
        "notary"
    ],
    "wof:name":"Bernardo, Lucien",
    "wof:placetype":"venue"
},
  "geometry": {"coordinates":[-73.582741,45.518353],"type":"Point"}
}