{
  "type": "Feature",
  "properties": {
    "addr:full":"RR 1 St Williams ON N0E 1P0",
    "addr:postcode":"n0e 1p0",
    "addr:street":"Rr 1 St",
    "iso:country":"CA",
    "sg:address":"RR 1",
    "sg:city":"St Williams",
    "sg:classifiers":[
        {
            "category":"Shopping",
            "subcategory":"Discount & Variety Stores",
            "type":"Retail Goods"
        }
    ],
    "sg:phone":"+1 519 586 3703",
    "sg:postcode":"N0E 1P0",
    "sg:province":"ON",
    "wof:name":"Pine Needle",
    "wof:placetype":"venue"
},
  "geometry": {"coordinates":[-80.415527,42.667858],"type":"Point"}
}