{
  "type": "Feature",
  "properties": {
    "addr:full":"84 Ruth St Sault Ste Marie ON P6C 2E6",
    "addr:housenumber":"84",
    "addr:postcode":"p6c 2e6",
    "addr:street":"Ruth St",
    "iso:country":"CA",
    "sg:address":"84 Ruth St",
    "sg:city":"Sault Ste Marie",
    "sg:classifiers":[
        {
            "category":"Social Services",
            "subcategory":"Child Care",
            "type":"Services"
        }
    ],
    "sg:phone":"+1 705 759 4691",
    "sg:postcode":"P6C 2E6",
    "sg:province":"ON",
    "wof:name":"Jessie Irving Children's Ctr",
    "wof:placetype":"venue"
},
  "geometry": {"coordinates":[-84.3561096191,46.5357894897],"type":"Point"}
}