{
  "type": "Feature",
  "properties": {
    "addr:full":"2909 Pasqua St #8 Regina SK S4S 2H4",
    "addr:housenumber":"2909",
    "addr:postcode":"s4s 2h4",
    "addr:street":"Pasqua St # 8",
    "iso:country":"CA",
    "sg:address":"2909 Pasqua St #8",
    "sg:city":"Regina",
    "sg:classifiers":[
        {
            "category":"Building & Trades",
            "subcategory":"Construction",
            "type":"Services"
        }
    ],
    "sg:phone":"+1 306 586 9538",
    "sg:postcode":"S4S 2H4",
    "sg:province":"SK",
    "sg:tags":[
        "pipe",
        "line",
        "contractor"
    ],
    "wof:name":"Abs Pipeliners",
    "wof:placetype":"venue"
},
  "geometry": {"coordinates":[-104.6407547,50.43359375],"type":"Point"}
}