{
  "type": "Feature",
  "properties": {
    "addr:full":"135 Wexford Rd Brampton ON L6Z 2T5",
    "addr:housenumber":"135",
    "addr:postcode":"l6z 2t5",
    "addr:street":"Wexford Rd",
    "iso:country":"CA",
    "sg:address":"135 Wexford Rd",
    "sg:city":"Brampton",
    "sg:classifiers":[
        {
            "category":"Professional",
            "subcategory":"Secretarial Services",
            "type":"Services"
        }
    ],
    "sg:phone":"+1 905 840 7648",
    "sg:postcode":"L6Z 2T5",
    "sg:province":"ON",
    "sg:tags":[
        "transcription",
        "medical",
        "processing",
        "word"
    ],
    "wof:name":"Eal Ventures",
    "wof:placetype":"venue"
},
  "geometry": {"coordinates":[-79.7839508057,43.7151069641],"type":"Point"}
}