{
  "type": "Feature",
  "properties": {
    "addr:full":"61 West Deane Park Dr Etobicoke ON M9B 2S1",
    "addr:housenumber":"61",
    "addr:postcode":"m9b 2s1",
    "addr:street":"West Deane Park Dr",
    "iso:country":"CA",
    "sg:address":"61 West Deane Park Dr",
    "sg:city":"Etobicoke",
    "sg:classifiers":[
        {
            "category":"Organizations",
            "subcategory":"Religious Organization",
            "type":"Services"
        }
    ],
    "sg:phone":"+1 416 622 5577",
    "sg:postcode":"M9B 2S1",
    "sg:province":"ON",
    "sg:tags":[
        "church"
    ],
    "wof:name":"St Philip's Ev Lutheran Church",
    "wof:placetype":"venue"
},
  "geometry": {"coordinates":[-79.563835,43.658173],"type":"Point"}
}