{
  "type": "Feature",
  "properties": {
    "iso:country":"CA",
    "sg:address":"5960 Shawson Dr",
    "sg:city":"Mississauga",
    "sg:classifiers":[
        {
            "category":"Manufacturing",
            "subcategory":"Textiles",
            "type":"Manufacturing & Wholesale Goods"
        }
    ],
    "sg:phone":"+1 905 696 9329",
    "sg:postcode":"L4W 3W5",
    "sg:province":"ON",
    "sg:tags":[
        "mills",
        "yarn"
    ],
    "wof:name":"Amtex Manufacturing Inc",
    "wof:placetype":"venue"
},
  "geometry": {"coordinates":[-79.654221,43.647564],"type":"Point"}
}