{
  "type": "Feature",
  "properties": {
    "iso:country":"CA",
    "sg:address":"41 Maple Ave",
    "sg:city":"Tatamagouche",
    "sg:classifiers":[
        {
            "category":"Personal",
            "subcategory":"Beauty Salon",
            "type":"Services"
        }
    ],
    "sg:phone":"+1 902 657 3611",
    "sg:postcode":"B0K 1V0",
    "sg:province":"NS",
    "wof:name":"Mary's Beauty Salon",
    "wof:placetype":"venue"
},
  "geometry": {"coordinates":[-63.2919540405,45.7101593018],"type":"Point"}
}