{
  "type": "Feature",
  "properties": {
    "addr:full":"111 Rue Saint-Pierre Quebec QC G1K 4A6",
    "addr:housenumber":"111",
    "addr:postcode":"g1k 4a6",
    "addr:street":"Rue Saint-Pierre",
    "iso:country":"CA",
    "sg:address":"111 Rue Saint-Pierre",
    "sg:city":"Quebec",
    "sg:classifiers":[
        {
            "category":"Real Estate",
            "subcategory":"Architect",
            "type":"Services"
        }
    ],
    "sg:phone":"+1 418 694 1010",
    "sg:postcode":"G1K 4A6",
    "sg:province":"QC",
    "wof:name":"Lemay & Michaud Design Inc",
    "wof:placetype":"venue"
},
  "geometry": {"coordinates":[-71.203278,46.815578],"type":"Point"}
}