{
  "type": "Feature",
  "properties": {
    "addr:full":"LA Baie QC G7B 3N8",
    "addr:postcode":"g7b 3n8",
    "iso:country":"CA",
    "sg:city":"LA Baie",
    "sg:classifiers":[
        {
            "category":"Professional",
            "subcategory":"Business Services",
            "type":"Services"
        }
    ],
    "sg:phone":"+1 418 697 6738",
    "sg:postcode":"G7B 3N8",
    "sg:province":"QC",
    "wof:name":"Recuperation Du Saguenay",
    "wof:placetype":"venue"
},
  "geometry": {"coordinates":[-70.93055,48.365406],"type":"Point"}
}