{
  "type": "Feature",
  "properties": {
    "addr:full":"1573 Bloor St W Toronto ON M6P 1A6",
    "addr:housenumber":"1573",
    "addr:postcode":"m6p 1a6",
    "addr:street":"Bloor St W",
    "iso:country":"CA",
    "sg:address":"1573 Bloor St W",
    "sg:city":"Toronto",
    "sg:classifiers":[
        {
            "category":"Banks & Credit Unions",
            "subcategory":"Bank",
            "type":"Services"
        }
    ],
    "sg:phone":"+1 416 532 1149",
    "sg:postcode":"M6P 1A6",
    "sg:province":"ON",
    "wof:name":"Parama Lithuanian Credit Union",
    "wof:placetype":"venue"
},
  "geometry": {"coordinates":[-79.4541931152,43.6559638977],"type":"Point"}
}