{
  "type": "Feature",
  "properties": {
    "addr:full":"Toronto ON M6N 1H8",
    "addr:postcode":"m6n 1h8",
    "iso:country":"CA",
    "sg:city":"Toronto",
    "sg:classifiers":[
        {
            "category":"Food & Beverages",
            "subcategory":"Fruits & Vegetables",
            "type":"Retail Goods"
        }
    ],
    "sg:phone":"+1 416 653 0007",
    "sg:postcode":"M6N 1H8",
    "sg:province":"ON",
    "sg:tags":[
        "grocer"
    ],
    "wof:name":"Boston Variety Fish & Fruit",
    "wof:placetype":"venue"
},
  "geometry": {"coordinates":[-79.4002914429,43.6869773865],"type":"Point"}
}