{
  "type": "Feature",
  "properties": {
    "addr:full":"203 Vavenby Bridge Rd Vavenby BC V0E 3A0",
    "addr:housenumber":"203",
    "addr:postcode":"v0e 3a0",
    "addr:street":"Vavenby Bridge Rd",
    "iso:country":"CA",
    "sg:address":"203 Vavenby Bridge Rd",
    "sg:city":"Vavenby",
    "sg:classifiers":[
        {
            "category":"Freight",
            "type":"Transportation"
        }
    ],
    "sg:phone":"+1 250 676 9233",
    "sg:postcode":"V0E 3A0",
    "sg:province":"BC",
    "sg:tags":[
        "bus",
        "line",
        "courier"
    ],
    "wof:name":"Greyhound Lines of Canada Ltd",
    "wof:placetype":"venue"
},
  "geometry": {"coordinates":[-119.72782100000001,51.587269],"type":"Point"}
}