{
  "type": "Feature",
  "properties": {
    "addr:full":"Sudbury ON P3E 5P5",
    "addr:postcode":"p3e 5p5",
    "iso:country":"CA",
    "sg:city":"Sudbury",
    "sg:classifiers":[
        {
            "category":"Building & Trades",
            "subcategory":"Construction",
            "type":"Services"
        }
    ],
    "sg:phone":"+1 705 522 1133",
    "sg:postcode":"P3E 5P5",
    "sg:province":"ON",
    "sg:tags":[
        "insulation",
        "heat",
        "contractor"
    ],
    "wof:name":"Thermotek Insulations Inc",
    "wof:placetype":"venue"
},
  "geometry": {"coordinates":[-81.029556,46.464733],"type":"Point"}
}