{
  "type": "Feature",
  "properties": {
    "iso:country":"CA",
    "sg:address":"633 Colborne St",
    "sg:city":"London",
    "sg:classifiers":[
        {
            "category":"Shopping",
            "subcategory":"Computers & Home Electronics",
            "type":"Retail Goods"
        }
    ],
    "sg:phone":"+1 519 433 0076",
    "sg:postcode":"N6B 2V3",
    "sg:province":"ON",
    "sg:tags":[
        "software"
    ],
    "wof:name":"Keigan System Inc",
    "wof:placetype":"venue"
},
  "geometry": {"coordinates":[-81.243492,42.993511],"type":"Point"}
}