{
  "type": "Feature",
  "properties": {
    "addr:full":"Surrey BC V3T 2X2",
    "addr:postcode":"v3t 2x2",
    "iso:country":"CA",
    "sg:city":"Surrey",
    "sg:classifiers":[
        {
            "category":"Professional",
            "subcategory":"Accounting & Tax Preparation",
            "type":"Services"
        }
    ],
    "sg:phone":"+1 604 589 7661",
    "sg:postcode":"V3T 2X2",
    "sg:province":"BC",
    "sg:tags":[
        "accountant"
    ],
    "wof:name":"Brian W Davis Inc",
    "wof:placetype":"venue"
},
  "geometry": {"coordinates":[-122.84529113799999,49.1916389465],"type":"Point"}
}