{
  "type": "Feature",
  "properties": {
    "iso:country":"CA",
    "sg:address":"7542 178 St NW",
    "sg:city":"Edmonton",
    "sg:classifiers":[
        {
            "category":"Autos & Motor Vehicles",
            "subcategory":"Fuel & Gas Station",
            "type":"Retail Goods"
        }
    ],
    "sg:phone":"+1 780 481 6903",
    "sg:postcode":"T5T 2Y5",
    "sg:province":"AB",
    "sg:tags":[
        "oil"
    ],
    "wof:name":"Esso Imperial Oil",
    "wof:placetype":"venue"
},
  "geometry": {"coordinates":[-113.63080596899999,53.5084686279],"type":"Point"}
}