{
  "type": "Feature",
  "properties": {
    "iso:country":"CA",
    "sg:address":"8901 Woodbine Ave # 223",
    "sg:city":"Markham",
    "sg:classifiers":[
        {
            "category":"Professional",
            "subcategory":"Accounting & Tax Preparation",
            "type":"Services"
        }
    ],
    "sg:phone":"+1 905 947 4388",
    "sg:postcode":"L3R 9Y4",
    "sg:province":"ON",
    "sg:tags":[
        "accountant"
    ],
    "wof:name":"Lott Business Advisory Corp",
    "wof:placetype":"venue"
},
  "geometry": {"coordinates":[-79.3627624512,43.867931366],"type":"Point"}
}