{
  "type": "Feature",
  "properties": {
    "addr:full":"950 Grand Rang Rte 159 Saint-Tite QC G0X 3H0",
    "addr:housenumber":"950",
    "addr:postcode":"g0x 3h0",
    "addr:street":"Grand Rang Rte 159",
    "iso:country":"CA",
    "sg:address":"950 Grand Rang Rte 159",
    "sg:city":"Saint-Tite",
    "sg:classifiers":[
        {
            "category":"Manufacturing",
            "subcategory":"Tools & Machinery",
            "type":"Manufacturing & Wholesale Goods"
        }
    ],
    "sg:phone":"+1 418 365 5867",
    "sg:postcode":"G0X 3H0",
    "sg:province":"QC",
    "sg:tags":[
        "machine",
        "shop",
        "solder"
    ],
    "wof:name":"Machineries AB Enr",
    "wof:placetype":"venue"
},
  "geometry": {"coordinates":[-72.5495223999,46.7094726562],"type":"Point"}
}