{
  "type": "Feature",
  "properties": {
    "addr:full":"916 Rue Du Ruisseau Saint-Jerome QC J7Z 6R7",
    "addr:housenumber":"916",
    "addr:postcode":"j7z 6r7",
    "addr:street":"Rue Du Ruisseau Saint-Jerome",
    "iso:country":"CA",
    "sg:address":"916 Rue Du Ruisseau",
    "sg:city":"Saint-Jerome",
    "sg:classifiers":[
        {
            "category":"Social Services",
            "subcategory":"Child Care",
            "type":"Services"
        }
    ],
    "sg:phone":"+1 450 565 9480",
    "sg:postcode":"J7Z 6R7",
    "sg:province":"QC",
    "wof:name":"Garderie Educative L'Envolee",
    "wof:placetype":"venue"
},
  "geometry": {"coordinates":[-73.981506,45.765614],"type":"Point"}
}