{
  "type": "Feature",
  "properties": {
    "iso:country":"CA",
    "sg:address":"320 Marwood Dr",
    "sg:city":"Oshawa",
    "sg:classifiers":[
        {
            "category":"Wholesale",
            "subcategory":"Hardware",
            "type":"Manufacturing & Wholesale Goods"
        }
    ],
    "sg:phone":"+1 905 720 1099",
    "sg:postcode":"L1H 8B4",
    "sg:province":"ON",
    "sg:tags":[
        "plumbing",
        "fixture",
        "supply"
    ],
    "wof:name":"Noble Trade Plumbing Supl Ltd",
    "wof:placetype":"venue"
},
  "geometry": {"coordinates":[-78.8325042725,43.8767166138],"type":"Point"}
}