{
  "type": "Feature",
  "properties": {
    "addr:full":"3180 Bathurst St North York ON M6A 2A9",
    "addr:housenumber":"3180",
    "addr:postcode":"m6a 2a9",
    "addr:street":"Bathurst St",
    "iso:country":"CA",
    "sg:address":"3180 Bathurst St",
    "sg:city":"North York",
    "sg:classifiers":[
        {
            "category":"Organizations",
            "subcategory":"Religious Organization",
            "type":"Services"
        }
    ],
    "sg:phone":"+1 416 783 6503",
    "sg:postcode":"M6A 2A9",
    "sg:province":"ON",
    "sg:tags":[
        "church"
    ],
    "wof:name":"Asbury & West United Church",
    "wof:placetype":"venue"
},
  "geometry": {"coordinates":[-79.4307479858,43.7227058411],"type":"Point"}
}