{
  "type": "Feature",
  "properties": {
    "addr:full":"4 Rue Pelletier Cabano QC G0L 1E0",
    "addr:housenumber":"4",
    "addr:postcode":"g0l 1e0",
    "addr:street":"Rue Pelletier",
    "iso:country":"CA",
    "sg:address":"4 Rue Pelletier",
    "sg:city":"Cabano",
    "sg:classifiers":[
        {
            "category":"Shopping",
            "subcategory":"Jewelry",
            "type":"Retail Goods"
        }
    ],
    "sg:phone":"+1 418 854 2306",
    "sg:postcode":"G0L 1E0",
    "sg:province":"QC",
    "sg:tags":[
        "jeweler"
    ],
    "wof:name":"Bijouterie Cabano Enr",
    "wof:placetype":"venue"
},
  "geometry": {"coordinates":[-68.877304,47.681805],"type":"Point"}
}