{
  "type": "Feature",
  "properties": {
    "addr:full":"869 Upper James St Hamilton ON L9C 3A3",
    "addr:housenumber":"869",
    "addr:postcode":"l9c 3a3",
    "addr:street":"Upper James St",
    "iso:country":"CA",
    "sg:address":"869 Upper James St",
    "sg:city":"Hamilton",
    "sg:classifiers":[
        {
            "category":"Restaurant",
            "type":"Food & Drink"
        }
    ],
    "sg:phone":"+1 905 388 9238",
    "sg:postcode":"L9C 3A3",
    "sg:province":"ON",
    "wof:name":"Wendy's",
    "wof:placetype":"venue"
},
  "geometry": {"coordinates":[-79.882271,43.22691],"type":"Point"}
}