{
  "type": "Feature",
  "properties": {
    "addr:full":"19 Fraser St Lakefield ON K0L 2H0",
    "addr:housenumber":"19",
    "addr:postcode":"k0l 2h0",
    "addr:street":"Fraser St",
    "iso:country":"CA",
    "sg:address":"19 Fraser St",
    "sg:city":"Lakefield",
    "sg:classifiers":[
        {
            "category":"Health Services",
            "subcategory":"Nursing And Care Facility",
            "type":"Services"
        }
    ],
    "sg:phone":"+1 705 652 7112",
    "sg:postcode":"K0L 2H0",
    "sg:province":"ON",
    "sg:tags":[
        "home",
        "convalescent"
    ],
    "wof:name":"Extendicare Lakefield",
    "wof:placetype":"venue"
},
  "geometry": {"coordinates":[-78.2802886963,44.4235191345],"type":"Point"}
}