{
  "type": "Feature",
  "properties": {
    "addr:full":"12 Talbot St E Jarvis ON N0A 1J0",
    "addr:housenumber":"12",
    "addr:postcode":"n0a 1j0",
    "addr:street":"Talbot St E Jarvis",
    "iso:country":"CA",
    "sg:address":"12 Talbot St E",
    "sg:city":"Jarvis",
    "sg:classifiers":[
        {
            "category":"Banks & Credit Unions",
            "subcategory":"Bank",
            "type":"Services"
        }
    ],
    "sg:phone":"+1 519 587 2253",
    "sg:postcode":"N0A 1J0",
    "sg:province":"ON",
    "wof:name":"Cibc",
    "wof:placetype":"venue"
},
  "geometry": {"coordinates":[-80.112579,42.884781],"type":"Point"}
}