{
  "type": "Feature",
  "properties": {
    "iso:country":"CA",
    "sg:address":"321 Clarence St",
    "sg:city":"Brampton",
    "sg:classifiers":[
        {
            "category":"Freight",
            "type":"Transportation"
        }
    ],
    "sg:phone":"+1 905 453 8350",
    "sg:postcode":"L6W 1T6",
    "sg:province":"ON",
    "sg:tags":[
        "trucking"
    ],
    "wof:name":"York Transportation Group",
    "wof:placetype":"venue"
},
  "geometry": {"coordinates":[-79.7305526733,43.6916465759],"type":"Point"}
}