{
  "type": "Feature",
  "properties": {
    "addr:full":"347 10th St W Owen Sound ON N4K 3R4",
    "addr:housenumber":"347",
    "addr:postcode":"n4k 3r4",
    "addr:street":"10Th St W",
    "iso:country":"CA",
    "sg:address":"347 10th St W",
    "sg:city":"Owen Sound",
    "sg:classifiers":[
        {
            "category":"Health Services",
            "subcategory":"Doctor",
            "type":"Services"
        }
    ],
    "sg:phone":"+1 519 372 2329",
    "sg:postcode":"N4K 3R4",
    "sg:province":"ON",
    "sg:tags":[
        "physician",
        "surgeon"
    ],
    "wof:name":"Wright, J A MD",
    "wof:placetype":"venue"
},
  "geometry": {"coordinates":[-80.94857,44.566975],"type":"Point"}
}