{
  "type": "Feature",
  "properties": {
    "addr:full":"600 Ferguson Ave N Hamilton ON L8L 4Z9",
    "addr:housenumber":"600",
    "addr:postcode":"l8l 4z9",
    "addr:street":"Ferguson Ave N",
    "iso:country":"CA",
    "sg:address":"600 Ferguson Ave N",
    "sg:city":"Hamilton",
    "sg:classifiers":[
        {
            "category":"Banks & Credit Unions",
            "subcategory":"Bank",
            "type":"Services"
        }
    ],
    "sg:phone":"+1 905 523 7385",
    "sg:postcode":"L8L 4Z9",
    "sg:province":"ON",
    "wof:name":"Canadian Transportation",
    "wof:placetype":"venue"
},
  "geometry": {"coordinates":[-79.853409,43.27343],"type":"Point"}
}