{
  "type": "Feature",
  "properties": {
    "addr:full":"256 Rue Principale Saint-Alexis-DE-Montcalm QC J0K 1T0",
    "addr:housenumber":"256",
    "addr:postcode":"j0k 1t0",
    "addr:street":"Rue Principale",
    "iso:country":"CA",
    "sg:address":"256 Rue Principale",
    "sg:city":"Saint-Alexis-DE-Montcalm",
    "sg:classifiers":[
        {
            "category":"Banks & Credit Unions",
            "subcategory":"Bank",
            "type":"Services"
        }
    ],
    "sg:phone":"+1 450 839 3609",
    "sg:postcode":"J0K 1T0",
    "sg:province":"QC",
    "wof:name":"Caisses Populaires Desjardins",
    "wof:placetype":"venue"
},
  "geometry": {"coordinates":[-73.6132659912,45.932964325],"type":"Point"}
}