{
  "type": "Feature",
  "properties": {
    "iso:country":"CA",
    "sg:address":"RR 2",
    "sg:city":"Bancroft",
    "sg:classifiers":[
        {
            "category":"Banks & Credit Unions",
            "subcategory":"Investment Brokerage",
            "type":"Services"
        }
    ],
    "sg:phone":"+1 613 332 4063",
    "sg:postcode":"K0L 1C0",
    "sg:province":"ON",
    "wof:name":"Bryson, Bill",
    "wof:placetype":"venue"
},
  "geometry": {"coordinates":[-77.85334777830001,45.0565414429],"type":"Point"}
}