{
  "type": "Feature",
  "properties": {
    "addr:full":"Medicine Hat AB T1B 3R2",
    "addr:postcode":"t1b 3r2",
    "iso:country":"CA",
    "sg:city":"Medicine Hat",
    "sg:classifiers":[
        {
            "category":"Professional",
            "subcategory":"Accounting & Tax Preparation",
            "type":"Services"
        }
    ],
    "sg:phone":"+1 403 526 8776",
    "sg:postcode":"T1B 3R2",
    "sg:province":"AB",
    "sg:tags":[
        "return",
        "filing"
    ],
    "wof:name":"Liberty Tax Svc",
    "wof:placetype":"venue"
},
  "geometry": {"coordinates":[-110.64619399999999,50.007725],"type":"Point"}
}