{
  "type": "Feature",
  "properties": {
    "addr:full":"2448 Danforth Ave Toronto ON M4C 1K9",
    "addr:housenumber":"2448",
    "addr:postcode":"m4c 1k9",
    "addr:street":"Danforth Ave",
    "iso:country":"CA",
    "sg:address":"2448 Danforth Ave",
    "sg:city":"Toronto",
    "sg:classifiers":[
        {
            "category":"Education",
            "subcategory":"Dance Studio",
            "type":"Public Place"
        }
    ],
    "sg:phone":"+1 416 406 4222",
    "sg:postcode":"M4C 1K9",
    "sg:province":"ON",
    "sg:tags":[
        "instruction",
        "dancing"
    ],
    "wof:name":"Dancing At Twilight Inc",
    "wof:placetype":"venue"
},
  "geometry": {"coordinates":[-79.304131,43.68779],"type":"Point"}
}