{
  "type": "Feature",
  "properties": {
    "addr:full":"291 Ste Catherine Saint-Polycarpe QC J0P 1X0",
    "addr:housenumber":"291",
    "addr:postcode":"j0p 1x0",
    "addr:street":"Ste Catherine",
    "iso:country":"CA",
    "sg:address":"291 Ste Catherine",
    "sg:city":"Saint-Polycarpe",
    "sg:classifiers":[
        {
            "category":"Social Services",
            "subcategory":"Child Care",
            "type":"Services"
        }
    ],
    "sg:phone":"+1 450 265 3437",
    "sg:postcode":"J0P 1X0",
    "sg:province":"QC",
    "wof:name":"Garderie Educative Enfant Enr",
    "wof:placetype":"venue"
},
  "geometry": {"coordinates":[-74.315727,45.294472],"type":"Point"}
}