{
  "type": "Feature",
  "properties": {
    "addr:full":"Springfield ON N0L 2J0",
    "addr:postcode":"n0l 2j0",
    "iso:country":"CA",
    "sg:city":"Springfield",
    "sg:classifiers":[
        {
            "category":"Real Estate",
            "subcategory":"Real Estate Operator",
            "type":"Services"
        }
    ],
    "sg:phone":"+1 519 765 4111",
    "sg:postcode":"N0L 2J0",
    "sg:province":"ON",
    "sg:tags":[
        "mobile",
        "home",
        "community"
    ],
    "wof:name":"1060021 Ontario Inc",
    "wof:placetype":"venue"
},
  "geometry": {"coordinates":[-80.936378,42.829491],"type":"Point"}
}