{
  "type": "Feature",
  "properties": {
    "iso:country":"CA",
    "sg:address":"131 Hwy 64",
    "sg:city":"Noelville",
    "sg:classifiers":[
        {
            "category":"Home & Garden",
            "subcategory":"Building Materials",
            "type":"Retail Goods"
        }
    ],
    "sg:phone":"+1 705 898 2248",
    "sg:postcode":"P0M 2N0",
    "sg:province":"ON",
    "sg:tags":[
        "lumber"
    ],
    "wof:name":"Nadon Lumber Ltd",
    "wof:placetype":"venue"
},
  "geometry": {"coordinates":[-80.4316253662,46.1329574585],"type":"Point"}
}