{
  "type": "Feature",
  "properties": {
    "addr:full":"1037 Boul Lafleche Baie-Comeau QC G5C 1C8",
    "addr:housenumber":"1037",
    "addr:postcode":"g5c 1c8",
    "addr:street":"Boul Lafleche",
    "iso:country":"CA",
    "sg:address":"1037 Boul Lafleche",
    "sg:city":"Baie-Comeau",
    "sg:classifiers":[
        {
            "category":"Shopping",
            "type":"Retail Goods"
        }
    ],
    "sg:phone":"+1 418 589 2321",
    "sg:postcode":"G5C 1C8",
    "sg:province":"QC",
    "sg:tags":[
        "hearing",
        "equipment",
        "supply",
        "impaired"
    ],
    "wof:name":"Groupe Forget-Parent",
    "wof:placetype":"venue"
},
  "geometry": {"coordinates":[-68.262894,49.196873],"type":"Point"}
}