{
  "type": "Feature",
  "properties": {
    "iso:country":"CA",
    "sg:city":"Kazabazua",
    "sg:classifiers":[
        {
            "category":"Retail",
            "subcategory":"Auto Repair",
            "type":"Services"
        }
    ],
    "sg:phone":"+1 819 467 2810",
    "sg:postcode":"J0X 1X0",
    "sg:province":"QC",
    "sg:tags":[
        "body",
        "automobile",
        "painting"
    ],
    "wof:name":"Eldon Mc Cambley Auto Ctr",
    "wof:placetype":"venue"
},
  "geometry": {"coordinates":[-76.0172653198,45.9195251465],"type":"Point"}
}