{
  "type": "Feature",
  "properties": {
    "addr:full":"Chilliwack BC V2P 2M3",
    "addr:postcode":"v2p 2m3",
    "iso:country":"CA",
    "sg:city":"Chilliwack",
    "sg:classifiers":[
        {
            "category":"Restaurant",
            "type":"Food & Drink"
        }
    ],
    "sg:phone":"+1 604 792 5310",
    "sg:postcode":"V2P 2M3",
    "sg:province":"BC",
    "wof:name":"Friendly Banners Restaurant",
    "wof:placetype":"venue"
},
  "geometry": {"coordinates":[-121.957504273,49.1680831909],"type":"Point"}
}