{
  "type": "Feature",
  "properties": {
    "addr:full":"3103 27 St Vernon BC V1T 4W4",
    "addr:housenumber":"3103",
    "addr:postcode":"v1t 4w4",
    "addr:street":"27 St",
    "iso:country":"CA",
    "sg:address":"3103 27 St",
    "sg:city":"Vernon",
    "sg:classifiers":[
        {
            "category":"Health Services",
            "subcategory":"Doctor",
            "type":"Services"
        }
    ],
    "sg:phone":"+1 250 503 1558",
    "sg:postcode":"V1T 4W4",
    "sg:province":"BC",
    "sg:tags":[
        "physician",
        "surgeon"
    ],
    "wof:name":"Mustard Seed Clinic",
    "wof:placetype":"venue"
},
  "geometry": {"coordinates":[-119.26649500000001,50.264557],"type":"Point"}
}