{
  "type": "Feature",
  "properties": {
    "addr:full":"35 Highgate Dr Markham ON L3R 3R5",
    "addr:housenumber":"35",
    "addr:postcode":"l3r 3r5",
    "addr:street":"Highgate Dr",
    "iso:country":"CA",
    "sg:address":"35 Highgate Dr",
    "sg:city":"Markham",
    "sg:classifiers":[
        {
            "category":"Education",
            "subcategory":"School",
            "type":"Public Place"
        }
    ],
    "sg:phone":"+1 905 477 1019",
    "sg:postcode":"L3R 3R5",
    "sg:province":"ON",
    "wof:name":"Highgate Public School",
    "wof:placetype":"venue"
},
  "geometry": {"coordinates":[-79.3154373169,43.8281135559],"type":"Point"}
}