{
  "type": "Feature",
  "properties": {
    "iso:country":"CA",
    "sg:address":"3385 Old Homestead Rd",
    "sg:city":"Sutton West",
    "sg:classifiers":[
        {
            "category":"Retail",
            "subcategory":"Auto Repair",
            "type":"Services"
        }
    ],
    "sg:phone":"+1 905 476 7037",
    "sg:postcode":"L0E 1R0",
    "sg:province":"ON",
    "sg:tags":[
        "repairing",
        "automobile"
    ],
    "wof:name":"Prosser's Garage",
    "wof:placetype":"venue"
},
  "geometry": {"coordinates":[-79.3612365723,44.3048667908],"type":"Point"}
}