{
  "type": "Feature",
  "properties": {
    "addr:full":"1914 Ch DE LA Reserve Chicoutimi QC G7H 5B3",
    "addr:postcode":"1914;g7h 5b3",
    "addr:street":"Ch De La Reserve",
    "iso:country":"CA",
    "sg:address":"1914 Ch DE LA Reserve",
    "sg:city":"Chicoutimi",
    "sg:classifiers":[
        {
            "category":"Manufacturing",
            "subcategory":"Furniture",
            "type":"Manufacturing & Wholesale Goods"
        }
    ],
    "sg:phone":"+1 418 696 4750",
    "sg:postcode":"G7H 5B3",
    "sg:province":"QC",
    "sg:tags":[
        "planning",
        "remodeling",
        "kitchen"
    ],
    "wof:name":"Armoires & Cuisines Modernes",
    "wof:placetype":"venue"
},
  "geometry": {"coordinates":[-71.1391906738,48.3994636536],"type":"Point"}
}