{
  "type": "Feature",
  "properties": {
    "addr:full":"1750 Main St Winnipeg MB R2V 1Z7",
    "addr:housenumber":"1750",
    "addr:postcode":"r2v 1z7",
    "addr:street":"Main St",
    "iso:country":"CA",
    "sg:address":"1750 Main St",
    "sg:city":"Winnipeg",
    "sg:classifiers":[
        {
            "category":"Shopping",
            "subcategory":"Pharmacy",
            "type":"Retail Goods"
        }
    ],
    "sg:phone":"+1 204 339 2025",
    "sg:postcode":"R2V 1Z7",
    "sg:province":"MB",
    "wof:name":"West Kildonan Pharmacy",
    "wof:placetype":"venue"
},
  "geometry": {"coordinates":[-97.118256,49.936333],"type":"Point"}
}