{
  "type": "Feature",
  "properties": {
    "addr:full":"Kelowna BC V1V 1S1",
    "addr:postcode":"v1v 1s1",
    "iso:country":"CA",
    "sg:city":"Kelowna",
    "sg:classifiers":[
        {
            "category":"Government",
            "subcategory":"Office",
            "type":"Public Place"
        }
    ],
    "sg:phone":"+1 250 491 3700",
    "sg:postcode":"V1V 1S1",
    "sg:province":"BC",
    "wof:name":"Canada Transport",
    "wof:placetype":"venue"
},
  "geometry": {"coordinates":[-119.382149,49.952663],"type":"Point"}
}