{
  "type": "Feature",
  "properties": {
    "addr:full":"127 Yonge St #202 Toronto ON M5C 1W4",
    "addr:housenumber":"127",
    "addr:postcode":"m5c 1w4",
    "addr:street":"Yonge St # 202",
    "iso:country":"CA",
    "sg:address":"127 Yonge St #202",
    "sg:city":"Toronto",
    "sg:classifiers":[
        {
            "category":"Retail",
            "subcategory":"Portrait Studio",
            "type":"Services"
        }
    ],
    "sg:phone":"+1 416 366 4301",
    "sg:postcode":"M5C 1W4",
    "sg:province":"ON",
    "sg:tags":[
        "photographer"
    ],
    "wof:name":"Photo CO",
    "wof:placetype":"venue"
},
  "geometry": {"coordinates":[-79.378471,43.650944],"type":"Point"}
}