{
  "type": "Feature",
  "properties": {
    "addr:full":"Surrey BC V3W 4G2",
    "addr:postcode":"v3w 4g2",
    "iso:country":"CA",
    "sg:city":"Surrey",
    "sg:classifiers":[
        {
            "category":"Wholesale",
            "subcategory":"Metals & Minerals",
            "type":"Manufacturing & Wholesale Goods"
        }
    ],
    "sg:phone":"+1 604 597 1217",
    "sg:postcode":"V3W 4G2",
    "sg:province":"BC",
    "sg:tags":[
        "aluminum"
    ],
    "wof:name":"Modern Time Aluminum CO",
    "wof:placetype":"venue"
},
  "geometry": {"coordinates":[-122.867813,49.152809],"type":"Point"}
}