{
  "type": "Feature",
  "properties": {
    "addr:full":"North Battleford SK S9A 3T5",
    "addr:postcode":"s9a 3t5",
    "iso:country":"CA",
    "sg:city":"North Battleford",
    "sg:classifiers":[
        {
            "category":"Building & Trades",
            "subcategory":"Landscaping Services",
            "type":"Services"
        }
    ],
    "sg:phone":"+1 306 445 1499",
    "sg:postcode":"S9A 3T5",
    "sg:province":"SK",
    "sg:tags":[
        "grounds",
        "lawn",
        "general",
        "maintenance",
        "contractor"
    ],
    "wof:name":"D W Lawn Care",
    "wof:placetype":"venue"
},
  "geometry": {"coordinates":[-108.30519104,52.7931518555],"type":"Point"}
}