{
  "type": "Feature",
  "properties": {
    "addr:full":"Kelowna BC V1Y 6G1",
    "addr:postcode":"v1y 6g1",
    "iso:country":"CA",
    "sg:city":"Kelowna",
    "sg:classifiers":[
        {
            "category":"Real Estate",
            "subcategory":"Real Estate Agent",
            "type":"Services"
        }
    ],
    "sg:phone":"+1 250 868 6595",
    "sg:postcode":"V1Y 6G1",
    "sg:province":"BC",
    "wof:name":"Hasenhuendl, Eric",
    "wof:placetype":"venue"
},
  "geometry": {"coordinates":[-119.463898,49.881729],"type":"Point"}
}