{
  "type": "Feature",
  "properties": {
    "addr:full":"Delta BC V4L 2M1",
    "addr:postcode":"v4l 2m1",
    "iso:country":"CA",
    "sg:city":"Delta",
    "sg:classifiers":[
        {
            "category":"Education",
            "subcategory":"Special Training",
            "type":"Public Place"
        }
    ],
    "sg:phone":"+1 604 943 6022",
    "sg:postcode":"V4L 2M1",
    "sg:province":"BC",
    "sg:tags":[
        "tutoring"
    ],
    "wof:name":"Sylvan Learning Ctr",
    "wof:placetype":"venue"
},
  "geometry": {"coordinates":[-123.068909,49.037605],"type":"Point"}
}