{
  "type": "Feature",
  "properties": {
    "iso:country":"CA",
    "sg:city":"Port Greville",
    "sg:classifiers":[
        {
            "category":"Shopping",
            "subcategory":"Used Merchandise",
            "type":"Retail Goods"
        }
    ],
    "sg:phone":"+1 902 348 2245",
    "sg:postcode":"B0M 1T0",
    "sg:province":"NS",
    "sg:tags":[
        "antique"
    ],
    "wof:name":"Shaw Country Market",
    "wof:placetype":"venue"
},
  "geometry": {"coordinates":[-64.5495223999,45.4078369141],"type":"Point"}
}