{
  "type": "Feature",
  "properties": {
    "iso:country":"CA",
    "sg:city":"Calgary",
    "sg:classifiers":[
        {
            "category":"Shopping",
            "type":"Retail Goods"
        }
    ],
    "sg:phone":"+1 403 225 2418",
    "sg:postcode":"T2J 0N3",
    "sg:province":"AB",
    "sg:tags":[
        "picture",
        "frame"
    ],
    "wof:name":"You Name It We Can Frame It",
    "wof:placetype":"venue"
},
  "geometry": {"coordinates":[-114.04814148,50.943687439],"type":"Point"}
}