{
  "type": "Feature",
  "properties": {
    "addr:full":"1211 Winnipeg St Regina SK S4R 1K1",
    "addr:housenumber":"1211",
    "addr:postcode":"s4r 1k1",
    "addr:street":"Winnipeg St",
    "iso:country":"CA",
    "sg:address":"1211 Winnipeg St",
    "sg:city":"Regina",
    "sg:classifiers":[
        {
            "category":"Food & Beverages",
            "subcategory":"Meat & Fish",
            "type":"Retail Goods"
        }
    ],
    "sg:phone":"+1 306 546 4600",
    "sg:postcode":"S4R 1K1",
    "sg:province":"SK",
    "wof:name":"Tendercut Meats Tc 20000 Inc",
    "wof:placetype":"venue"
},
  "geometry": {"coordinates":[-104.595031738,50.4595527649],"type":"Point"}
}