{
  "type": "Feature",
  "properties": {
    "addr:full":"485 Eglinton Ave E # 107 Toronto ON M4P 1N2",
    "addr:housenumber":"485",
    "addr:postcode":"m4p 1n2",
    "addr:street":"Eglinton Ave E # 107",
    "iso:country":"CA",
    "sg:address":"485 Eglinton Ave E # 107",
    "sg:city":"Toronto",
    "sg:classifiers":[
        {
            "category":"Shopping",
            "subcategory":"Clothing, Apparel, & Fashions",
            "type":"Retail Goods"
        }
    ],
    "sg:phone":"+1 416 487 3711",
    "sg:postcode":"M4P 1N2",
    "sg:province":"ON",
    "sg:tags":[
        "dressmaker"
    ],
    "wof:name":"Doreen's Dress Making",
    "wof:placetype":"venue"
},
  "geometry": {"coordinates":[-79.381561,43.710026],"type":"Point"}
}