{
  "type": "Feature",
  "properties": {
    "iso:country":"CA",
    "sg:city":"Terrace",
    "sg:classifiers":[
        {
            "category":"Building & Trades",
            "subcategory":"Equipment Rental",
            "type":"Services"
        }
    ],
    "sg:phone":"+1 250 635 2430",
    "sg:postcode":"V8G 4V2",
    "sg:province":"BC",
    "sg:tags":[
        "helicopter",
        "aircraft",
        "leasing",
        "charter"
    ],
    "wof:name":"Canadian Helicopters Ltd",
    "wof:placetype":"venue"
},
  "geometry": {"coordinates":[-128.602172852,54.5158576965],"type":"Point"}
}