{
  "type": "Feature",
  "properties": {
    "addr:full":"1143 Rue Saint-Jean Quebec QC G1R 1S3",
    "addr:housenumber":"1143",
    "addr:postcode":"g1r 1s3",
    "addr:street":"Rue Saint-Jean",
    "iso:country":"CA",
    "sg:address":"1143 Rue Saint-Jean",
    "sg:city":"Quebec",
    "sg:classifiers":[
        {
            "category":"Shopping",
            "type":"Retail Goods"
        }
    ],
    "sg:phone":"+1 418 694 9292",
    "sg:postcode":"G1R 1S3",
    "sg:province":"QC",
    "sg:tags":[
        "candle"
    ],
    "wof:name":"Chandelles & Cie",
    "wof:placetype":"venue"
},
  "geometry": {"coordinates":[-71.2100982666,46.8139839172],"type":"Point"}
}