{
  "type": "Feature",
  "properties": {
    "addr:full":"Langley BC V1M 3E6",
    "addr:postcode":"v1m 3e6",
    "iso:country":"CA",
    "sg:city":"Langley",
    "sg:classifiers":[
        {
            "category":"Building & Trades",
            "subcategory":"Construction",
            "type":"Services"
        }
    ],
    "sg:phone":"+1 604 888 4000",
    "sg:postcode":"V1M 3E6",
    "sg:province":"BC",
    "sg:tags":[
        "excavating",
        "contractor"
    ],
    "wof:name":"Backhoes Unlimited",
    "wof:placetype":"venue"
},
  "geometry": {"coordinates":[-122.67610168500001,49.1791725159],"type":"Point"}
}