{
  "type": "Feature",
  "properties": {
    "addr:full":"409 Patricia St Jasper AB T0E 1E0",
    "addr:housenumber":"409",
    "addr:postcode":"t0e 1e0",
    "addr:street":"Patricia St",
    "iso:country":"CA",
    "sg:address":"409 Patricia St",
    "sg:city":"Jasper",
    "sg:classifiers":[
        {
            "category":"Organizations",
            "subcategory":"Professional Association",
            "type":"Services"
        }
    ],
    "sg:phone":"+1 780 852 3858",
    "sg:postcode":"T0E 1E0",
    "sg:province":"AB",
    "wof:name":"Jasper Chamber of Commerce",
    "wof:placetype":"venue"
},
  "geometry": {"coordinates":[-118.080276,52.879498],"type":"Point"}
}