{
  "type": "Feature",
  "properties": {
    "addr:full":"199 Rte Du Long-Sault Saint-Andre-D'Argenteuil QC J0V 1X0",
    "addr:housenumber":"199",
    "addr:postcode":"j0v 1x0",
    "addr:street":"Rte Du Long-Sault Saint-Andre-D'Argenteuil",
    "iso:country":"CA",
    "sg:address":"199 Rte Du Long-Sault",
    "sg:city":"Saint-Andre-D'Argenteuil",
    "sg:classifiers":[
        {
            "category":"Bars & Pubs",
            "type":"Food & Drink"
        }
    ],
    "sg:phone":"+1 450 537 3719",
    "sg:postcode":"J0V 1X0",
    "sg:province":"QC",
    "sg:tags":[
        "lounge",
        "tourist",
        "cocktail",
        "accommodation"
    ],
    "wof:name":"Bar Riverside",
    "wof:placetype":"venue"
},
  "geometry": {"coordinates":[-74.3527297974,45.557434082],"type":"Point"}
}