{
  "type": "Feature",
  "properties": {
    "addr:full":"Abbotsford BC V2T 4C6",
    "addr:postcode":"v2t 4c6",
    "iso:country":"CA",
    "sg:city":"Abbotsford",
    "sg:classifiers":[
        {
            "category":"Retail",
            "subcategory":"Repair Shop",
            "type":"Services"
        }
    ],
    "sg:phone":"+1 604 855 1558",
    "sg:postcode":"V2T 4C6",
    "sg:province":"BC",
    "sg:tags":[
        "sharpening"
    ],
    "wof:name":"Tru-Cut Sharpening",
    "wof:placetype":"venue"
},
  "geometry": {"coordinates":[-122.349251,49.045807],"type":"Point"}
}