{
  "type": "Feature",
  "properties": {
    "addr:full":"7120 98 Ave NW Edmonton AB T6A 0A7",
    "addr:housenumber":"7120",
    "addr:postcode":"t6a 0a7",
    "addr:street":"98 Ave Nw",
    "iso:country":"CA",
    "sg:address":"7120 98 Ave NW",
    "sg:city":"Edmonton",
    "sg:classifiers":[
        {
            "category":"Organizations",
            "subcategory":"Religious Organization",
            "type":"Services"
        }
    ],
    "sg:phone":"+1 780 463 3415",
    "sg:postcode":"T6A 0A7",
    "sg:province":"AB",
    "sg:tags":[
        "church"
    ],
    "wof:name":"Mar Thoma Syrian Anglican Ch",
    "wof:placetype":"venue"
},
  "geometry": {"coordinates":[-113.43801116900001,53.5379142761],"type":"Point"}
}