{
  "type": "Feature",
  "properties": {
    "addr:full":"19 King St E Hagersville ON N0A 1H0",
    "addr:housenumber":"19",
    "addr:postcode":"n0a 1h0",
    "addr:street":"King St E",
    "iso:country":"CA",
    "sg:address":"19 King St E",
    "sg:city":"Hagersville",
    "sg:classifiers":[
        {
            "category":"Shopping",
            "subcategory":"Stationery & Office Supplies",
            "type":"Retail Goods"
        }
    ],
    "sg:phone":"+1 905 768 5860",
    "sg:postcode":"N0A 1H0",
    "sg:province":"ON",
    "wof:name":"Art Service Office Supply",
    "wof:placetype":"venue"
},
  "geometry": {"coordinates":[-80.0494384766,42.9612731934],"type":"Point"}
}