{
  "type": "Feature",
  "properties": {
    "iso:country":"CA",
    "sg:address":"1304 Rue Saint-Alphonse O",
    "sg:city":"Thetford Mines",
    "sg:classifiers":[
        {
            "category":"Personal",
            "subcategory":"Beauty Salon",
            "type":"Services"
        }
    ],
    "sg:phone":"+1 418 335 7181",
    "sg:postcode":"G6G 3Y1",
    "sg:province":"QC",
    "wof:name":"Salon Le Viscaya Enr",
    "wof:placetype":"venue"
},
  "geometry": {"coordinates":[-71.28448486329999,46.0772590637],"type":"Point"}
}