{
  "type": "Feature",
  "properties": {
    "addr:full":"54 Six Point Rd Etobicoke ON M8Z 2X2",
    "addr:housenumber":"54",
    "addr:postcode":"m8z 2x2",
    "addr:street":"Six Point Rd",
    "iso:country":"CA",
    "sg:address":"54 Six Point Rd",
    "sg:city":"Etobicoke",
    "sg:classifiers":[
        {
            "category":"Manufacturing",
            "subcategory":"Building Materials",
            "type":"Manufacturing & Wholesale Goods"
        }
    ],
    "sg:phone":"+1 416 232 0522",
    "sg:postcode":"M8Z 2X2",
    "sg:province":"ON",
    "sg:tags":[
        "equipment",
        "boat",
        "supply"
    ],
    "wof:name":"Noah's Boat Building Supplies",
    "wof:placetype":"venue"
},
  "geometry": {"coordinates":[-79.52546700000001,43.636021],"type":"Point"}
}