{
  "type": "Feature",
  "properties": {
    "addr:full":"Somerville NB E7P 2S6",
    "addr:postcode":"e7p 2s6",
    "iso:country":"CA",
    "sg:city":"Somerville",
    "sg:classifiers":[
        {
            "category":"Autos & Motor Vehicles",
            "subcategory":"Auto Supplies",
            "type":"Retail Goods"
        }
    ],
    "sg:phone":"+1 506 375 4585",
    "sg:postcode":"E7P 2S6",
    "sg:province":"NB",
    "sg:tags":[
        "automobile",
        "parts"
    ],
    "wof:name":"M & A Automotive Ltd",
    "wof:placetype":"venue"
},
  "geometry": {"coordinates":[-67.54523500000001,46.295601],"type":"Point"}
}