{
  "type": "Feature",
  "properties": {
    "addr:full":"Delta BC V4E 2A6",
    "addr:postcode":"v4e 2a6",
    "iso:country":"CA",
    "sg:city":"Delta",
    "sg:classifiers":[
        {
            "category":"Personal",
            "subcategory":"Beauty Salon",
            "type":"Services"
        }
    ],
    "sg:phone":"+1 604 572 6317",
    "sg:postcode":"V4E 2A6",
    "sg:province":"BC",
    "wof:name":"Groove the Hair Studio",
    "wof:placetype":"venue"
},
  "geometry": {"coordinates":[-122.890587,49.118145],"type":"Point"}
}