{
  "type": "Feature",
  "properties": {
    "addr:full":"4340 Highway 12 Lacombe AB T4L 1A4",
    "addr:housenumber":"4340",
    "addr:postcode":"t4l 1a4",
    "addr:street":"Highway 12",
    "iso:country":"CA",
    "sg:address":"4340 Highway 12",
    "sg:city":"Lacombe",
    "sg:classifiers":[
        {
            "category":"Autos & Motor Vehicles",
            "subcategory":"Recreational Vehicle Sales",
            "type":"Retail Goods"
        }
    ],
    "sg:phone":"+1 403 782 7715",
    "sg:postcode":"T4L 1A4",
    "sg:province":"AB",
    "wof:name":"Barb's Rv Place",
    "wof:placetype":"venue"
},
  "geometry": {"coordinates":[-113.722176,52.468479],"type":"Point"}
}