{
  "type": "Feature",
  "properties": {
    "addr:full":"438 Rue DE LA Madone Mont-Laurier QC J9L 1S3",
    "addr:housenumber":"438",
    "addr:postcode":"j9l 1s3",
    "addr:street":"Rue De La Madone",
    "iso:country":"CA",
    "sg:address":"438 Rue DE LA Madone",
    "sg:city":"Mont-Laurier",
    "sg:classifiers":[
        {
            "category":"Professional",
            "subcategory":"Accounting & Tax Preparation",
            "type":"Services"
        }
    ],
    "sg:phone":"+1 819 623 6550",
    "sg:postcode":"J9L 1S3",
    "sg:province":"QC",
    "sg:tags":[
        "accountant"
    ],
    "wof:name":"Sirard, Rejean CA",
    "wof:placetype":"venue"
},
  "geometry": {"coordinates":[-75.500298,46.551571],"type":"Point"}
}