{
  "type": "Feature",
  "properties": {
    "iso:country":"CA",
    "sg:city":"Toronto",
    "sg:classifiers":[
        {
            "category":"Banks & Credit Unions",
            "subcategory":"Bank",
            "type":"Services"
        }
    ],
    "sg:phone":"+1 416 975 1161",
    "sg:postcode":"M4V 3A1",
    "sg:province":"ON",
    "sg:tags":[
        "loan",
        "real estate"
    ],
    "wof:name":"Kopas & Burrit Financial",
    "wof:placetype":"venue"
},
  "geometry": {"coordinates":[-79.395699,43.687901],"type":"Point"}
}