{
  "type": "Feature",
  "properties": {
    "addr:full":"311 Railway Ave Wawota SK S0G 5A0",
    "addr:housenumber":"311",
    "addr:postcode":"s0g 5a0",
    "addr:street":"Railway Ave",
    "iso:country":"CA",
    "sg:address":"311 Railway Ave",
    "sg:city":"Wawota",
    "sg:classifiers":[
        {
            "category":"Retail",
            "subcategory":"Auto Repair",
            "type":"Services"
        }
    ],
    "sg:phone":"+1 306 739 2303",
    "sg:postcode":"S0G 5A0",
    "sg:province":"SK",
    "sg:tags":[
        "repairing",
        "automobile"
    ],
    "wof:name":"Drumm's Garage Ltd",
    "wof:placetype":"venue"
},
  "geometry": {"coordinates":[-102.02818298299999,49.9032096863],"type":"Point"}
}