{
  "type": "Feature",
  "properties": {
    "addr:full":"Saint-Pie QC J0H 1W0",
    "addr:postcode":"j0h 1w0",
    "iso:country":"CA",
    "sg:city":"Saint-Pie",
    "sg:classifiers":[
        {
            "category":"Manufacturing",
            "subcategory":"Metals",
            "type":"Manufacturing & Wholesale Goods"
        }
    ],
    "sg:phone":"+1 450 772 6613",
    "sg:postcode":"J0H 1W0",
    "sg:province":"QC",
    "sg:tags":[
        "stamping",
        "finisher"
    ],
    "wof:name":"Quefer Inc",
    "wof:placetype":"venue"
},
  "geometry": {"coordinates":[-72.896919,45.504269],"type":"Point"}
}