{
  "type": "Feature",
  "properties": {
    "addr:full":"245 Rue Cyr N Thetford Mines QC G6G 4E5",
    "addr:housenumber":"245",
    "addr:postcode":"g6g 4e5",
    "addr:street":"Rue Cyr N",
    "iso:country":"CA",
    "sg:address":"245 Rue Cyr N",
    "sg:city":"Thetford Mines",
    "sg:classifiers":[
        {
            "category":"Health Services",
            "subcategory":"Nursing And Care Facility",
            "type":"Services"
        }
    ],
    "sg:phone":"+1 418 335 7301",
    "sg:postcode":"G6G 4E5",
    "sg:province":"QC",
    "sg:tags":[
        "home",
        "retirement",
        "community"
    ],
    "wof:name":"Residence Notre Dame",
    "wof:placetype":"venue"
},
  "geometry": {"coordinates":[-71.300613,46.096195],"type":"Point"}
}