{
  "type": "Feature",
  "properties": {
    "addr:full":"Montreal QC H3G 1T7",
    "addr:postcode":"h3g 1t7",
    "iso:country":"CA",
    "sg:city":"Montreal",
    "sg:classifiers":[
        {
            "category":"Recreation",
            "type":"Entertainment"
        }
    ],
    "sg:phone":"+1 514 878 1331",
    "sg:postcode":"H3G 1T7",
    "sg:province":"QC",
    "sg:tags":[
        "ticket"
    ],
    "wof:name":"Academie Des Billets Inc",
    "wof:placetype":"venue"
},
  "geometry": {"coordinates":[-73.551796,45.519581],"type":"Point"}
}