{
  "type": "Feature",
  "properties": {
    "addr:full":"Toronto ON M4R 1A7",
    "addr:postcode":"m4r 1a7",
    "iso:country":"CA",
    "sg:city":"Toronto",
    "sg:classifiers":[
        {
            "category":"Manufacturing",
            "subcategory":"Lumber",
            "type":"Manufacturing & Wholesale Goods"
        }
    ],
    "sg:phone":"+1 416 483 5152",
    "sg:postcode":"M4R 1A7",
    "sg:province":"ON",
    "sg:tags":[
        "forester"
    ],
    "wof:name":"Outland Reforestation",
    "wof:placetype":"venue"
},
  "geometry": {"coordinates":[-79.406479,43.705132],"type":"Point"}
}