{
  "type": "Feature",
  "properties": {
    "iso:country":"CA",
    "sg:address":"455 Rue Sherbrooke O",
    "sg:city":"Montreal",
    "sg:classifiers":[
        {
            "category":"Travel",
            "subcategory":"Hotels & Motels",
            "type":"Entertainment"
        }
    ],
    "sg:phone":"+1 514 284 3634",
    "sg:postcode":"H3A 1B7",
    "sg:province":"QC",
    "wof:name":"Appartement Hotel",
    "wof:placetype":"venue"
},
  "geometry": {"coordinates":[-73.567398,45.517479],"type":"Point"}
}