{
  "type": "Feature",
  "properties": {
    "addr:full":"393 Portage Ave Winnipeg MB R3B 3H6",
    "addr:housenumber":"393",
    "addr:postcode":"r3b 3h6",
    "addr:street":"Portage Ave",
    "iso:country":"CA",
    "sg:address":"393 Portage Ave",
    "sg:city":"Winnipeg",
    "sg:classifiers":[
        {
            "category":"Shopping",
            "subcategory":"Clothing, Apparel, & Fashions",
            "type":"Retail Goods"
        }
    ],
    "sg:phone":"+1 204 947 3838",
    "sg:postcode":"R3B 3H6",
    "sg:province":"MB",
    "wof:name":"Laura Petites",
    "wof:placetype":"venue"
},
  "geometry": {"coordinates":[-97.14814800000001,49.892204],"type":"Point"}
}