{
  "type": "Feature",
  "properties": {
    "addr:full":"4525 Railway Ave Elk Point AB T0A 1A0",
    "addr:housenumber":"4525",
    "addr:postcode":"t0a 1a0",
    "addr:street":"Railway Ave",
    "iso:country":"CA",
    "sg:address":"4525 Railway Ave",
    "sg:city":"Elk Point",
    "sg:classifiers":[
        {
            "category":"Wholesale",
            "subcategory":"Petroleum",
            "type":"Manufacturing & Wholesale Goods"
        }
    ],
    "sg:phone":"+1 780 724 3944",
    "sg:postcode":"T0A 1A0",
    "sg:province":"AB",
    "sg:tags":[
        "bulk",
        "oil",
        "gasoline"
    ],
    "wof:name":"United Farmers of Alberta",
    "wof:placetype":"venue"
},
  "geometry": {"coordinates":[-110.892532,53.896221],"type":"Point"}
}