{
  "type": "Feature",
  "properties": {
    "addr:full":"842 Boul Laure Sept-Iles QC G4R 1Y7",
    "addr:housenumber":"842",
    "addr:postcode":"g4r 1y7",
    "addr:street":"Boul Laure Sept-Iles",
    "iso:country":"CA",
    "sg:address":"842 Boul Laure",
    "sg:city":"Sept-Iles",
    "sg:classifiers":[
        {
            "category":"Travel",
            "subcategory":"Hotels & Motels",
            "type":"Entertainment"
        }
    ],
    "sg:phone":"+1 418 962 9427",
    "sg:postcode":"G4R 1Y7",
    "sg:province":"QC",
    "wof:name":"Mouettes Hotel Motel",
    "wof:placetype":"venue"
},
  "geometry": {"coordinates":[-66.389145,50.224117],"type":"Point"}
}