{
  "type": "Feature",
  "properties": {
    "addr:full":"1970 Anderton Rd Comox BC V9M 4B1",
    "addr:housenumber":"1970",
    "addr:postcode":"v9m 4b1",
    "addr:street":"Anderton Rd",
    "iso:country":"CA",
    "sg:address":"1970 Anderton Rd",
    "sg:city":"Comox",
    "sg:classifiers":[
        {
            "category":"Retail",
            "subcategory":"Animal Services",
            "type":"Services"
        }
    ],
    "sg:phone":"+1 250 339 2955",
    "sg:postcode":"V9M 4B1",
    "sg:province":"BC",
    "sg:tags":[
        "pet",
        "boarding",
        "grooming",
        "washing",
        "sitting"
    ],
    "wof:name":"House of Dogs Boarding Kennels",
    "wof:placetype":"venue"
},
  "geometry": {"coordinates":[-124.93483000000001,49.689152],"type":"Point"}
}