{
  "type": "Feature",
  "properties": {
    "addr:full":"28 Av Du Chemin DE Fer E LA Sarre QC J9Z 1N1",
    "addr:postcode":"j9z 1n1",
    "addr:street":"28 Av Du Chemin De Fer E La Sarre",
    "iso:country":"CA",
    "sg:address":"28 Av Du Chemin DE Fer E",
    "sg:city":"LA Sarre",
    "sg:classifiers":[
        {
            "category":"Health Services",
            "subcategory":"Hospital",
            "type":"Services"
        }
    ],
    "sg:phone":"+1 819 333 3628",
    "sg:postcode":"J9Z 1N1",
    "sg:province":"QC",
    "sg:tags":[
        "mental"
    ],
    "wof:name":"Trait D'Union",
    "wof:placetype":"venue"
},
  "geometry": {"coordinates":[-79.203644,48.802353],"type":"Point"}
}