{
  "type": "Feature",
  "properties": {
    "addr:full":"1945 Rue Fullum Montreal QC H2K 3N3",
    "addr:housenumber":"1945",
    "addr:postcode":"h2k 3n3",
    "addr:street":"Rue Fullum",
    "iso:country":"CA",
    "sg:address":"1945 Rue Fullum",
    "sg:city":"Montreal",
    "sg:classifiers":[
        {
            "category":"Cinema",
            "subcategory":"Movie Theater",
            "type":"Entertainment"
        }
    ],
    "sg:phone":"+1 514 521 4199",
    "sg:postcode":"H2K 3N3",
    "sg:province":"QC",
    "wof:name":"Nouveau Theatre Experimental",
    "wof:placetype":"venue"
},
  "geometry": {"coordinates":[-73.5544204712,45.5301895142],"type":"Point"}
}