{
  "type": "Feature",
  "properties": {
    "addr:full":"41 Milner Ave Scarborough ON M1S 3P6",
    "addr:housenumber":"41",
    "addr:postcode":"m1s 3p6",
    "addr:street":"Milner Ave",
    "iso:country":"CA",
    "sg:address":"41 Milner Ave",
    "sg:city":"Scarborough",
    "sg:classifiers":[
        {
            "category":"Restaurant",
            "type":"Food & Drink"
        }
    ],
    "sg:phone":"+1 416 321 5684",
    "sg:postcode":"M1S 3P6",
    "sg:province":"ON",
    "wof:name":"Montana's Cookhouse Saloon",
    "wof:placetype":"venue"
},
  "geometry": {"coordinates":[-79.253212,43.78413],"type":"Point"}
}