{
  "type": "Feature",
  "properties": {
    "addr:full":"Surrey BC V4N 4E6",
    "addr:postcode":"v4n 4e6",
    "iso:country":"CA",
    "sg:city":"Surrey",
    "sg:classifiers":[
        {
            "category":"Building & Trades",
            "subcategory":"Construction",
            "type":"Services"
        }
    ],
    "sg:phone":"+1 604 882 8933",
    "sg:postcode":"V4N 4E6",
    "sg:province":"BC",
    "sg:tags":[
        "balancing"
    ],
    "wof:name":"Western Vibration & Machine",
    "wof:placetype":"venue"
},
  "geometry": {"coordinates":[-122.68536400000001,49.173756],"type":"Point"}
}