{
  "type": "Feature",
  "properties": {
    "addr:full":"51 Parkside Dr Mcgregor ON N0R 1J0",
    "addr:housenumber":"51",
    "addr:postcode":"n0r 1j0",
    "addr:street":"Parkside Dr",
    "iso:country":"CA",
    "sg:address":"51 Parkside Dr",
    "sg:city":"Mcgregor",
    "sg:classifiers":[
        {
            "category":"Food & Beverages",
            "subcategory":"Groceries & Convenience Stores",
            "type":"Retail Goods"
        }
    ],
    "sg:phone":"+1 519 726 5103",
    "sg:postcode":"N0R 1J0",
    "sg:province":"ON",
    "wof:name":"Parkside Variety",
    "wof:placetype":"venue"
},
  "geometry": {"coordinates":[-82.961426,42.147507],"type":"Point"}
}