{
  "type": "Feature",
  "properties": {
    "addr:full":"5854 69 St Dr Red Deer AB T4P 1C4",
    "addr:housenumber":"5854",
    "addr:postcode":"t4p 1c4",
    "addr:street":"69 St Dr",
    "iso:country":"CA",
    "sg:address":"5854 69 St Dr",
    "sg:city":"Red Deer",
    "sg:classifiers":[
        {
            "category":"Building & Trades",
            "subcategory":"Construction",
            "type":"Services"
        }
    ],
    "sg:phone":"+1 403 588 1581",
    "sg:postcode":"T4P 1C4",
    "sg:province":"AB",
    "sg:tags":[
        "concrete",
        "contractor"
    ],
    "wof:name":"Kristian's Concrete Fndtns",
    "wof:placetype":"venue"
},
  "geometry": {"coordinates":[-113.830055237,52.293258667],"type":"Point"}
}