{
  "type": "Feature",
  "properties": {
    "addr:full":"294 Spadina Ave Toronto ON M5T 2E7",
    "addr:housenumber":"294",
    "addr:postcode":"m5t 2e7",
    "addr:street":"Spadina Ave",
    "iso:country":"CA",
    "sg:address":"294 Spadina Ave",
    "sg:city":"Toronto",
    "sg:classifiers":[
        {
            "category":"Travel",
            "subcategory":"Travel Agent",
            "type":"Entertainment"
        }
    ],
    "sg:phone":"+1 416 977 2778",
    "sg:postcode":"M5T 2E7",
    "sg:province":"ON",
    "sg:tags":[
        "agency",
        "bureau"
    ],
    "wof:name":"New Golden Horse Tours Canada",
    "wof:placetype":"venue"
},
  "geometry": {"coordinates":[-79.39841461180001,43.6530609131],"type":"Point"}
}