{
  "type": "Feature",
  "properties": {
    "addr:full":"Guelph ON N1E 2X7",
    "addr:postcode":"n1e 2x7",
    "iso:country":"CA",
    "sg:city":"Guelph",
    "sg:classifiers":[
        {
            "category":"Professional",
            "subcategory":"Art Services",
            "type":"Services"
        }
    ],
    "sg:phone":"+1 519 767 2250",
    "sg:postcode":"N1E 2X7",
    "sg:province":"ON",
    "sg:tags":[
        "graphic",
        "designer",
        "sign"
    ],
    "wof:name":"Sign Art Ctr",
    "wof:placetype":"venue"
},
  "geometry": {"coordinates":[-80.230957,43.555218],"type":"Point"}
}