{
  "type": "Feature",
  "properties": {
    "addr:full":"1002 Pigeon Lake Peterborough ON K9J 6X2",
    "addr:housenumber":"1002",
    "addr:postcode":"k9j 6x2",
    "addr:street":"Pigeon Lake",
    "iso:country":"CA",
    "sg:address":"1002 Pigeon Lake",
    "sg:city":"Peterborough",
    "sg:classifiers":[
        {
            "category":"Travel",
            "subcategory":"Campground",
            "type":"Entertainment"
        }
    ],
    "sg:phone":"+1 705 657 8571",
    "sg:postcode":"K9J 6X2",
    "sg:province":"ON",
    "sg:tags":[
        "camp"
    ],
    "wof:name":"Camp Maple Leaf Inc",
    "wof:placetype":"venue"
},
  "geometry": {"coordinates":[-78.32131195069999,44.3007316589],"type":"Point"}
}