{
  "type": "Feature",
  "properties": {
    "addr:full":"324 Young St Winnipeg MB R3B 2S4",
    "addr:housenumber":"324",
    "addr:postcode":"r3b 2s4",
    "addr:street":"Young St",
    "iso:country":"CA",
    "sg:address":"324 Young St",
    "sg:city":"Winnipeg",
    "sg:classifiers":[
        {
            "category":"Professional",
            "subcategory":"Business Services",
            "type":"Services"
        }
    ],
    "sg:phone":"+1 204 786 4061",
    "sg:postcode":"R3B 2S4",
    "sg:province":"MB",
    "sg:tags":[
        "auctioneer"
    ],
    "wof:name":"Peter's Auction Sales Ltd",
    "wof:placetype":"venue"
},
  "geometry": {"coordinates":[-97.15537999999999,49.890278],"type":"Point"}
}