{
  "type": "Feature",
  "properties": {
    "addr:full":"22368 Dewdney Trunk Rd Maple Ridge BC V2X 3J2",
    "addr:housenumber":"22368",
    "addr:postcode":"v2x 3j2",
    "addr:street":"Dewdney Trunk Rd",
    "iso:country":"CA",
    "sg:address":"22368 Dewdney Trunk Rd",
    "sg:city":"Maple Ridge",
    "sg:classifiers":[
        {
            "category":"Personal",
            "type":"Services"
        }
    ],
    "sg:phone":"+1 604 467 3567",
    "sg:postcode":"V2X 3J2",
    "sg:province":"BC",
    "sg:tags":[
        "therapist",
        "massage"
    ],
    "wof:name":"Uptown Massage Therapy Clinic",
    "wof:placetype":"venue"
},
  "geometry": {"coordinates":[-122.602501,49.220367],"type":"Point"}
}