{
  "type": "Feature",
  "properties": {
    "addr:full":"10128 127 Ave NW Edmonton AB T5E 0B7",
    "addr:housenumber":"10128",
    "addr:postcode":"t5e 0b7",
    "addr:street":"127 Ave Nw",
    "iso:country":"CA",
    "sg:address":"10128 127 Ave NW",
    "sg:city":"Edmonton",
    "sg:classifiers":[
        {
            "category":"Retail",
            "subcategory":"Car Wash",
            "type":"Services"
        }
    ],
    "sg:phone":"+1 780 475 0999",
    "sg:postcode":"T5E 0B7",
    "sg:province":"AB",
    "sg:tags":[
        "automobile",
        "rustproofing",
        "undercoating",
        "detail"
    ],
    "wof:name":"Detail Plus Tires",
    "wof:placetype":"venue"
},
  "geometry": {"coordinates":[-113.494590759,53.5849380493],"type":"Point"}
}