{
  "type": "Feature",
  "properties": {
    "iso:country":"CA",
    "sg:city":"Sainte-Sophie-D'Halifax",
    "sg:classifiers":[
        {
            "category":"Home & Garden",
            "subcategory":"Furniture",
            "type":"Retail Goods"
        }
    ],
    "sg:phone":"+1 819 362 8655",
    "sg:postcode":"G0P 1L0",
    "sg:province":"QC",
    "wof:name":"Patios & Planchers Gl Inc",
    "wof:placetype":"venue"
},
  "geometry": {"coordinates":[-68.8511581421,48.8680152893],"type":"Point"}
}