{
  "type": "Feature",
  "properties": {
    "iso:country":"CA",
    "sg:city":"Surrey",
    "sg:classifiers":[
        {
            "category":"Professional",
            "subcategory":"Research",
            "type":"Services"
        }
    ],
    "sg:phone":"+1 604 584 8889",
    "sg:postcode":"V3R 8P8",
    "sg:province":"BC",
    "sg:tags":[
        "development",
        "laboratory"
    ],
    "wof:name":"Study Centre",
    "wof:placetype":"venue"
},
  "geometry": {"coordinates":[-122.80036163299999,49.1684608459],"type":"Point"}
}