{
  "type": "Feature",
  "properties": {
    "addr:full":"31 Rue Coursol Ripon QC J0V 1V0",
    "addr:housenumber":"31",
    "addr:postcode":"j0v 1v0",
    "addr:street":"Rue Coursol",
    "iso:country":"CA",
    "sg:address":"31 Rue Coursol",
    "sg:city":"Ripon",
    "sg:classifiers":[
        {
            "category":"Education",
            "subcategory":"Library",
            "type":"Public Place"
        }
    ],
    "sg:phone":"+1 819 983 2000",
    "sg:postcode":"J0V 1V0",
    "sg:province":"QC",
    "wof:name":"Ripon Bibliotheque Municipale",
    "wof:placetype":"venue"
},
  "geometry": {"coordinates":[-75.1004867554,45.7827796936],"type":"Point"}
}