{
  "type": "Feature",
  "properties": {
    "addr:full":"529288 Osprey-the Blue Mtns Singhampton ON N0C 1M0",
    "addr:housenumber":"529288",
    "addr:postcode":"n0c 1m0",
    "addr:street":"Osprey-The",
    "iso:country":"CA",
    "sg:address":"529288 Osprey-the Blue Mtns",
    "sg:city":"Singhampton",
    "sg:classifiers":[
        {
            "category":"Manufacturing",
            "subcategory":"Buildings",
            "type":"Manufacturing & Wholesale Goods"
        }
    ],
    "sg:phone":"+1 519 922 2836",
    "sg:postcode":"N0C 1M0",
    "sg:province":"ON",
    "sg:tags":[
        "home",
        "log",
        "cabin",
        "contractor"
    ],
    "wof:name":"Pioneer Logs Ltd",
    "wof:placetype":"venue"
},
  "geometry": {"coordinates":[-80.2511520386,44.3505744934],"type":"Point"}
}