{
  "type": "Feature",
  "properties": {
    "addr:full":"7520 104 St NW Edmonton AB T6E 6J4",
    "addr:housenumber":"7520",
    "addr:postcode":"t6e 6j4",
    "addr:street":"104 St Nw",
    "iso:country":"CA",
    "sg:address":"7520 104 St NW",
    "sg:city":"Edmonton",
    "sg:classifiers":[
        {
            "category":"Autos & Motor Vehicles",
            "subcategory":"Fuel & Gas Station",
            "type":"Retail Goods"
        }
    ],
    "sg:phone":"+1 780 433 0164",
    "sg:postcode":"T6E 6J4",
    "sg:province":"AB",
    "sg:tags":[
        "oil"
    ],
    "wof:name":"Husky",
    "wof:placetype":"venue"
},
  "geometry": {"coordinates":[-113.497840881,53.5118637085],"type":"Point"}
}