{
  "type": "Feature",
  "properties": {
    "iso:country":"CA",
    "sg:address":"13570 140 St NW",
    "sg:city":"Edmonton",
    "sg:classifiers":[
        {
            "category":"Health Services",
            "subcategory":"Clinic",
            "type":"Services"
        }
    ],
    "sg:phone":"+1 780 944 0067",
    "sg:postcode":"T5L 2E6",
    "sg:province":"AB",
    "wof:name":"Dynamic Quality Health Care",
    "wof:placetype":"venue"
},
  "geometry": {"coordinates":[-113.562065124,53.5971717834],"type":"Point"}
}