{
  "type": "Feature",
  "properties": {
    "addr:full":"Zurich ON N0M 2T0",
    "addr:postcode":"n0m 2t0",
    "iso:country":"CA",
    "sg:city":"Zurich",
    "sg:classifiers":[
        {
            "category":"Home & Garden",
            "subcategory":"Home Furnishings",
            "type":"Retail Goods"
        }
    ],
    "sg:phone":"+1 519 236 4793",
    "sg:postcode":"N0M 2T0",
    "sg:province":"ON",
    "sg:tags":[
        "curtain",
        "made",
        "drapery"
    ],
    "wof:name":"Plantations Vintage Interiors",
    "wof:placetype":"venue"
},
  "geometry": {"coordinates":[-81.624756,43.42186],"type":"Point"}
}