{
  "type": "Feature",
  "properties": {
    "iso:country":"CA",
    "sg:address":"1575 3E Av",
    "sg:city":"Quebec",
    "sg:classifiers":[
        {
            "category":"Organizations",
            "subcategory":"Professional Association",
            "type":"Services"
        }
    ],
    "sg:phone":"+1 418 648 6480",
    "sg:postcode":"G1L 2Y4",
    "sg:province":"QC",
    "sg:tags":[
        "psychologist"
    ],
    "wof:name":"Autonhommie Centre-Ressources",
    "wof:placetype":"venue"
},
  "geometry": {"coordinates":[-71.233376,46.830097],"type":"Point"}
}