{
  "type": "Feature",
  "properties": {
    "addr:full":"1 Rue Langlois Sainte-Luce QC G0K 1P0",
    "addr:housenumber":"1",
    "addr:postcode":"g0k 1p0",
    "addr:street":"Rue Langlois",
    "iso:country":"CA",
    "sg:address":"1 Rue Langlois",
    "sg:city":"Sainte-Luce",
    "sg:classifiers":[
        {
            "category":"Government",
            "subcategory":"Fire Station",
            "type":"Public Place"
        }
    ],
    "sg:phone":"+1 ",
    "sg:postcode":"G0K 1P0",
    "sg:province":"QC",
    "sg:tags":[
        "department"
    ],
    "wof:name":"Ste-Luce Incendie",
    "wof:placetype":"venue"
},
  "geometry": {"coordinates":[-68.391746521,48.5466766357],"type":"Point"}
}