{
  "type": "Feature",
  "properties": {
    "iso:country":"CA",
    "sg:address":"2159 Hwy 31",
    "sg:city":"Winchester",
    "sg:classifiers":[
        {
            "category":"Restaurant",
            "type":"Food & Drink"
        }
    ],
    "sg:phone":"+1 613 774 2417",
    "sg:postcode":"K0C 2K0",
    "sg:province":"ON",
    "wof:name":"Country Kitchen Dining Lounge",
    "wof:placetype":"venue"
},
  "geometry": {"coordinates":[-75.377342,45.089046],"type":"Point"}
}