{
  "type": "Feature",
  "properties": {
    "addr:full":"9370 Alaska Way Delta BC V4C 4R8",
    "addr:housenumber":"9370",
    "addr:postcode":"v4c 4r8",
    "addr:street":"Alaska Way",
    "iso:country":"CA",
    "sg:address":"9370 Alaska Way",
    "sg:city":"Delta",
    "sg:classifiers":[
        {
            "category":"Retail",
            "subcategory":"Repair Shop",
            "type":"Services"
        }
    ],
    "sg:phone":"+1 604 583 2411",
    "sg:postcode":"V4C 4R8",
    "sg:province":"BC",
    "sg:tags":[
        "welding"
    ],
    "wof:name":"Uniweld Services Ltd",
    "wof:placetype":"venue"
},
  "geometry": {"coordinates":[-122.921737671,49.1719703674],"type":"Point"}
}