{
  "type": "Feature",
  "properties": {
    "addr:full":"1427 Boul Pie-Ix Montreal QC H1V 2C2",
    "addr:housenumber":"1427",
    "addr:postcode":"h1v 2c2",
    "addr:street":"Boul Pie-Ix",
    "iso:country":"CA",
    "sg:address":"1427 Boul Pie-Ix",
    "sg:city":"Montreal",
    "sg:classifiers":[
        {
            "category":"Health Services",
            "subcategory":"Doctor",
            "type":"Services"
        }
    ],
    "sg:phone":"+1 514 523 0858",
    "sg:postcode":"H1V 2C2",
    "sg:province":"QC",
    "sg:tags":[
        "dentist"
    ],
    "wof:name":"Clinique Dentaires Chau",
    "wof:placetype":"venue"
},
  "geometry": {"coordinates":[-73.5357284546,45.5487480164],"type":"Point"}
}