{
  "type": "Feature",
  "properties": {
    "addr:full":"1237 Beach Dr Victoria BC V8S 2N4",
    "addr:housenumber":"1237",
    "addr:postcode":"v8s 2n4",
    "addr:street":"Beach Dr",
    "iso:country":"CA",
    "sg:address":"1237 Beach Dr",
    "sg:city":"Victoria",
    "sg:classifiers":[
        {
            "category":"Organizations",
            "subcategory":"Religious Organization",
            "type":"Services"
        }
    ],
    "sg:phone":"+1 250 598 5180",
    "sg:postcode":"V8S 2N4",
    "sg:province":"BC",
    "sg:tags":[
        "church"
    ],
    "wof:name":"Life of Victory Family Church",
    "wof:placetype":"venue"
},
  "geometry": {"coordinates":[-123.36451700000001,48.428314],"type":"Point"}
}