{
  "type": "Feature",
  "properties": {
    "addr:full":"56 Bolsover Rd Bolsover ON K0M 1B0",
    "addr:housenumber":"56",
    "addr:postcode":"k0m 1b0",
    "addr:street":"Bolsover Rd",
    "iso:country":"CA",
    "sg:address":"56 Bolsover Rd",
    "sg:city":"Bolsover",
    "sg:classifiers":[
        {
            "category":"Recreation",
            "type":"Entertainment"
        }
    ],
    "sg:phone":"+1 705 426 9940",
    "sg:postcode":"K0M 1B0",
    "sg:province":"ON",
    "sg:tags":[
        "course",
        "golf"
    ],
    "wof:name":"Western Trent Golf Club",
    "wof:placetype":"venue"
},
  "geometry": {"coordinates":[-79.0658416748,44.5311813354],"type":"Point"}
}