{
  "type": "Feature",
  "properties": {
    "iso:country":"CA",
    "sg:address":"12057 230 St",
    "sg:city":"Maple Ridge",
    "sg:classifiers":[
        {
            "category":"Professional",
            "subcategory":"Accounting & Tax Preparation",
            "type":"Services"
        }
    ],
    "sg:phone":"+1 604 467 9757",
    "sg:postcode":"V2X 6R4",
    "sg:province":"BC",
    "sg:tags":[
        "consultant"
    ],
    "wof:name":"William F Barker & Assoc",
    "wof:placetype":"venue"
},
  "geometry": {"coordinates":[-122.585091,49.221443],"type":"Point"}
}