{
  "type": "Feature",
  "properties": {
    "addr:full":"295 Rue Gauthier Saint-Marc-Des-Carrieres QC G0A 4B0",
    "addr:housenumber":"295",
    "addr:postcode":"g0a 4b0",
    "addr:street":"Rue Gauthier Saint-Marc-Des-Carrieres",
    "iso:country":"CA",
    "sg:address":"295 Rue Gauthier",
    "sg:city":"Saint-Marc-Des-Carrieres",
    "sg:classifiers":[
        {
            "category":"Real Estate",
            "subcategory":"Surveying",
            "type":"Services"
        }
    ],
    "sg:phone":"+1 418 268 5669",
    "sg:postcode":"G0A 4B0",
    "sg:province":"QC",
    "sg:tags":[
        "surveyor"
    ],
    "wof:name":"Champagne, Maurice",
    "wof:placetype":"venue"
},
  "geometry": {"coordinates":[-72.04892700000001,46.680145],"type":"Point"}
}