{
  "type": "Feature",
  "properties": {
    "addr:full":"Saint-Joseph-Du-Lac QC J0N 1M0",
    "addr:postcode":"j0n 1m0",
    "iso:country":"CA",
    "sg:city":"Saint-Joseph-Du-Lac",
    "sg:classifiers":[
        {
            "category":"Retail",
            "subcategory":"Veterinary Services",
            "type":"Services"
        }
    ],
    "sg:phone":"+1 450 974 1453",
    "sg:postcode":"J0N 1M0",
    "sg:province":"QC",
    "sg:tags":[
        "veterinarian"
    ],
    "wof:name":"Clinique Veterinaire-St-Joseph",
    "wof:placetype":"venue"
},
  "geometry": {"coordinates":[-73.9723739624,45.5196304321],"type":"Point"}
}