{
  "type": "Feature",
  "properties": {
    "addr:full":"120 Rue Ryan Dollard-Des-Ormeaux QC H9A 3C4",
    "addr:housenumber":"120",
    "addr:postcode":"h9a 3c4",
    "addr:street":"Rue Ryan",
    "iso:country":"CA",
    "sg:address":"120 Rue Ryan",
    "sg:city":"Dollard-Des-Ormeaux",
    "sg:classifiers":[
        {
            "category":"Travel",
            "subcategory":"Travel Agent",
            "type":"Entertainment"
        }
    ],
    "sg:phone":"+1 514 624 0410",
    "sg:postcode":"H9A 3C4",
    "sg:province":"QC",
    "sg:tags":[
        "agency",
        "bureau"
    ],
    "wof:name":"Weigensberg, Elayne",
    "wof:placetype":"venue"
},
  "geometry": {"coordinates":[-73.83358,45.488476],"type":"Point"}
}