{
  "type": "Feature",
  "properties": {
    "iso:country":"CA",
    "sg:address":"1591 Bowser Ave",
    "sg:city":"North Vancouver",
    "sg:classifiers":[
        {
            "category":"Building & Trades",
            "subcategory":"Construction",
            "type":"Services"
        }
    ],
    "sg:phone":"+1 604 986 4494",
    "sg:postcode":"V7P 2Y4",
    "sg:province":"BC",
    "sg:tags":[
        "general",
        "contractor"
    ],
    "wof:name":"Jdg Construction Mgmt Ltd",
    "wof:placetype":"venue"
},
  "geometry": {"coordinates":[-123.11634063699999,49.3237190247],"type":"Point"}
}