{
  "type": "Feature",
  "properties": {
    "iso:country":"CA",
    "sg:address":"570 Clarke Rd",
    "sg:city":"London",
    "sg:classifiers":[
        {
            "category":"Manufacturing",
            "subcategory":"Metals",
            "type":"Manufacturing & Wholesale Goods"
        }
    ],
    "sg:phone":"+1 519 453 4738",
    "sg:postcode":"N5V 3K5",
    "sg:province":"ON",
    "sg:tags":[
        "fastener"
    ],
    "wof:name":"Ctf Supply",
    "wof:placetype":"venue"
},
  "geometry": {"coordinates":[-81.179535,43.012611],"type":"Point"}
}