{
  "type": "Feature",
  "properties": {
    "addr:full":"252 Algonquin Blvd W Timmins ON P4N 2R7",
    "addr:housenumber":"252",
    "addr:postcode":"p4n 2r7",
    "addr:street":"Algonquin Blvd W",
    "iso:country":"CA",
    "sg:address":"252 Algonquin Blvd W",
    "sg:city":"Timmins",
    "sg:classifiers":[
        {
            "category":"Retail",
            "subcategory":"Veterinary Services",
            "type":"Services"
        }
    ],
    "sg:phone":"+1 705 268 7387",
    "sg:postcode":"P4N 2R7",
    "sg:province":"ON",
    "sg:tags":[
        "veterinarian"
    ],
    "wof:name":"Hampton Veterinary Hospital",
    "wof:placetype":"venue"
},
  "geometry": {"coordinates":[-81.342102,48.476212],"type":"Point"}
}