{
  "type": "Feature",
  "properties": {
    "iso:country":"CA",
    "sg:address":"1695 the Collegeway",
    "sg:city":"Mississauga",
    "sg:classifiers":[
        {
            "category":"Restaurant",
            "type":"Food & Drink"
        }
    ],
    "sg:phone":"+1 905 828 7449",
    "sg:postcode":"L5L 3S7",
    "sg:province":"ON",
    "wof:name":"Thatchers Restaurant",
    "wof:placetype":"venue"
},
  "geometry": {"coordinates":[-79.6654586792,43.5435791016],"type":"Point"}
}