{
  "type": "Feature",
  "properties": {
    "addr:full":"12270 Av Armand-Chaput Montreal QC H1C 1J1",
    "addr:housenumber":"12270",
    "addr:postcode":"h1c 1j1",
    "addr:street":"Av Armand-Chaput",
    "iso:country":"CA",
    "sg:address":"12270 Av Armand-Chaput",
    "sg:city":"Montreal",
    "sg:phone":"+1 514 643 3132",
    "sg:postcode":"H1C 1J1",
    "sg:province":"QC",
    "sg:tags":[
        "transmission",
        "facsimile",
        "electronic",
        "mail"
    ],
    "wof:name":"Viafax Enr",
    "wof:placetype":"venue"
},
  "geometry": {"coordinates":[-73.537537,45.667747],"type":"Point"}
}