{
  "type": "Feature",
  "properties": {
    "addr:full":"Airport Rd Kenora ON P9N 3W7",
    "addr:postcode":"p9n 3w7",
    "addr:street":"Airport Rd",
    "iso:country":"CA",
    "sg:address":"Airport Rd",
    "sg:city":"Kenora",
    "sg:classifiers":[
        {
            "category":"Shopping",
            "subcategory":"Used Merchandise",
            "type":"Retail Goods"
        }
    ],
    "sg:phone":"+1 807 548 2258",
    "sg:postcode":"P9N 3W7",
    "sg:province":"ON",
    "sg:tags":[
        "second",
        "store",
        "hand"
    ],
    "wof:name":"Salvation Army Sorting Ctr",
    "wof:placetype":"venue"
},
  "geometry": {"coordinates":[-94.365112,49.793522],"type":"Point"}
}