{
  "type": "Feature",
  "properties": {
    "addr:full":"PO Box 877 STN Main Grande Prairie AB T8V 3R5",
    "addr:housenumber":"po",
    "addr:postcode":"t8v 3r5",
    "addr:street":"Box 877 Stn Main",
    "iso:country":"CA",
    "sg:address":"PO Box 877 STN Main",
    "sg:city":"Grande Prairie",
    "sg:classifiers":[
        {
            "category":"Building & Trades",
            "subcategory":"Construction",
            "type":"Services"
        }
    ],
    "sg:phone":"+1 780 532 2610",
    "sg:postcode":"T8V 3R5",
    "sg:province":"AB",
    "sg:tags":[
        "contractor"
    ],
    "wof:name":"4 Season Contractors",
    "wof:placetype":"venue"
},
  "geometry": {"coordinates":[-118.79489100000001,55.171162],"type":"Point"}
}