{
  "type": "Feature",
  "properties": {
    "addr:full":"2495 Rue Lavallee Longueuil QC J4L 1R5",
    "addr:housenumber":"2495",
    "addr:postcode":"j4l 1r5",
    "addr:street":"Rue Lavallee",
    "iso:country":"CA",
    "sg:address":"2495 Rue Lavallee",
    "sg:city":"Longueuil",
    "sg:classifiers":[
        {
            "category":"Professional",
            "subcategory":"Business Services",
            "type":"Services"
        }
    ],
    "sg:phone":"+1 450 348 4144",
    "sg:postcode":"J4L 1R5",
    "sg:province":"QC",
    "sg:tags":[
        "inspection"
    ],
    "wof:name":"Qualite Inspection",
    "wof:placetype":"venue"
},
  "geometry": {"coordinates":[-73.46644592289999,45.5293083191],"type":"Point"}
}