{
  "type": "Feature",
  "properties": {
    "iso:country":"CA",
    "sg:address":"621 John St",
    "sg:city":"Victoria",
    "sg:classifiers":[
        {
            "category":"Restaurant",
            "type":"Food & Drink"
        }
    ],
    "sg:phone":"+1 250 388 7333",
    "sg:postcode":"V8T 1T8",
    "sg:province":"BC",
    "sg:tags":[
        "caterer"
    ],
    "wof:name":"Goldstream Catering Ltd",
    "wof:placetype":"venue"
},
  "geometry": {"coordinates":[-123.368804932,48.4368209839],"type":"Point"}
}