{
  "type": "Feature",
  "properties": {
    "addr:full":"6138 90 Ave NW Edmonton AB T6B 0P2",
    "addr:housenumber":"6138",
    "addr:postcode":"t6b 0p2",
    "addr:street":"90 Ave Nw",
    "iso:country":"CA",
    "sg:address":"6138 90 Ave NW",
    "sg:city":"Edmonton",
    "sg:classifiers":[
        {
            "category":"Health Services",
            "subcategory":"Doctor",
            "type":"Services"
        }
    ],
    "sg:phone":"+1 780 469 5533",
    "sg:postcode":"T6B 0P2",
    "sg:province":"AB",
    "sg:tags":[
        "physician",
        "surgeon"
    ],
    "wof:name":"Blais, Guy R MD",
    "wof:placetype":"venue"
},
  "geometry": {"coordinates":[-113.42697099999999,53.524574],"type":"Point"}
}