{
  "type": "Feature",
  "properties": {
    "addr:full":"1535 Ch Sainte-Foy Quebec QC G1S 2P1",
    "addr:postcode":"1535;g1s 2p1",
    "addr:street":"Ch Sainte-Foy",
    "iso:country":"CA",
    "sg:address":"1535 Ch Sainte-Foy",
    "sg:city":"Quebec",
    "sg:classifiers":[
        {
            "category":"Organizations",
            "subcategory":"Religious Organization",
            "type":"Services"
        }
    ],
    "sg:phone":"+1 418 683 6825",
    "sg:postcode":"G1S 2P1",
    "sg:province":"QC",
    "sg:tags":[
        "church"
    ],
    "wof:name":"Clarte-Dieu",
    "wof:placetype":"venue"
},
  "geometry": {"coordinates":[-71.25852966310001,46.7926902771],"type":"Point"}
}