{
  "type": "Feature",
  "properties": {
    "addr:full":"Dundas ON L9H 6X4",
    "addr:postcode":"l9h 6x4",
    "iso:country":"CA",
    "sg:city":"Dundas",
    "sg:classifiers":[
        {
            "category":"Shopping",
            "type":"Retail Goods"
        }
    ],
    "sg:phone":"+1 905 627 1911",
    "sg:postcode":"L9H 6X4",
    "sg:province":"ON",
    "sg:tags":[
        "picture",
        "frame",
        "art",
        "gallery",
        "dealer"
    ],
    "wof:name":"Framing & Art Ctr",
    "wof:placetype":"venue"
},
  "geometry": {"coordinates":[-79.94169599999999,43.259007],"type":"Point"}
}