{
  "type": "Feature",
  "properties": {
    "addr:full":"Woodbridge ON L4L 5Y5",
    "addr:postcode":"l4l 5y5",
    "iso:country":"CA",
    "sg:city":"Woodbridge",
    "sg:classifiers":[
        {
            "category":"Wholesale",
            "subcategory":"Electrical",
            "type":"Manufacturing & Wholesale Goods"
        }
    ],
    "sg:phone":"+1 905 856 2992",
    "sg:postcode":"L4L 5Y5",
    "sg:province":"ON",
    "sg:tags":[
        "equipment",
        "electronic",
        "supply"
    ],
    "wof:name":"Ryantronics Sales & Importing",
    "wof:placetype":"venue"
},
  "geometry": {"coordinates":[-79.5650939941,43.7807579041],"type":"Point"}
}