{
  "type": "Feature",
  "properties": {
    "addr:full":"112 Newkirk Rd Richmond Hill ON L4C 3G3",
    "addr:housenumber":"112",
    "addr:postcode":"l4c 3g3",
    "addr:street":"Newkirk Rd",
    "iso:country":"CA",
    "sg:address":"112 Newkirk Rd",
    "sg:city":"Richmond Hill",
    "sg:classifiers":[
        {
            "category":"Shopping",
            "subcategory":"Musical Instruments",
            "type":"Retail Goods"
        }
    ],
    "sg:phone":"+1 905 770 5222",
    "sg:postcode":"L4C 3G3",
    "sg:province":"ON",
    "sg:tags":[
        "music",
        "dealer"
    ],
    "wof:name":"Cosmo Music Warehouse Ltd",
    "wof:placetype":"venue"
},
  "geometry": {"coordinates":[-79.42871100000001,43.881554],"type":"Point"}
}