{
  "type": "Feature",
  "properties": {
    "addr:full":"PO Box 168 Millarville AB T0L 1K0",
    "addr:housenumber":"po",
    "addr:postcode":"t0l 1k0",
    "addr:street":"Box 168 Millarville",
    "iso:country":"CA",
    "sg:address":"PO Box 168",
    "sg:city":"Millarville",
    "sg:classifiers":[
        {
            "category":"Professional",
            "subcategory":"Management & Consulting",
            "type":"Services"
        }
    ],
    "sg:phone":"+1 403 931 2779",
    "sg:postcode":"T0L 1K0",
    "sg:province":"AB",
    "sg:tags":[
        "consultant",
        "business"
    ],
    "wof:name":"Goodman Mc Dougall & Assoc Ltd",
    "wof:placetype":"venue"
},
  "geometry": {"coordinates":[-114.334732,50.760174],"type":"Point"}
}