{
  "type": "Feature",
  "properties": {
    "addr:full":"3708 44 Ave NE Calgary AB T1Y 5V8",
    "addr:housenumber":"3708",
    "addr:postcode":"t1y 5v8",
    "addr:street":"44 Ave Ne",
    "iso:country":"CA",
    "sg:address":"3708 44 Ave NE",
    "sg:city":"Calgary",
    "sg:classifiers":[
        {
            "category":"Social Services",
            "subcategory":"Child Care",
            "type":"Services"
        }
    ],
    "sg:phone":"+1 403 590 0814",
    "sg:postcode":"T1Y 5V8",
    "sg:province":"AB",
    "wof:name":"Whitehorn Playcare",
    "wof:placetype":"venue"
},
  "geometry": {"coordinates":[-113.98122406,51.0913467407],"type":"Point"}
}