{
  "type": "Feature",
  "properties": {
    "iso:country":"CA",
    "sg:address":"PO Box 55070 Rpo Temple",
    "sg:city":"Calgary",
    "sg:classifiers":[
        {
            "category":"Building & Trades",
            "subcategory":"Plumbing",
            "type":"Services"
        }
    ],
    "sg:phone":"+1 403 293 9422",
    "sg:postcode":"T1Y 6R6",
    "sg:province":"AB",
    "sg:tags":[
        "mobile",
        "system",
        "air",
        "conditioning",
        "home",
        "contractor"
    ],
    "wof:name":"Shur Fire Mh Svc",
    "wof:placetype":"venue"
},
  "geometry": {"coordinates":[-114.063194,51.045074],"type":"Point"}
}