{
  "type": "Feature",
  "properties": {
    "addr:full":"Barnesville NB E5N 3M2",
    "addr:postcode":"e5n 3m2",
    "iso:country":"CA",
    "sg:city":"Barnesville",
    "sg:classifiers":[
        {
            "category":"Food & Beverages",
            "subcategory":"Groceries & Convenience Stores",
            "type":"Retail Goods"
        }
    ],
    "sg:phone":"+1 506 832 3227",
    "sg:postcode":"E5N 3M2",
    "sg:province":"NB",
    "wof:name":"Kathy's Convenience Store",
    "wof:placetype":"venue"
},
  "geometry": {"coordinates":[-65.73053,45.443947],"type":"Point"}
}