{
  "type": "Feature",
  "properties": {
    "addr:full":"465 Regent St Fredericton NB E3B 3X6",
    "addr:housenumber":"465",
    "addr:postcode":"e3b 3x6",
    "addr:street":"Regent St",
    "iso:country":"CA",
    "sg:address":"465 Regent St",
    "sg:city":"Fredericton",
    "sg:phone":"+1 506 458 0015",
    "sg:postcode":"E3B 3X6",
    "sg:province":"NB",
    "sg:tags":[
        "oil"
    ],
    "wof:name":"Fundy Energy Ltd",
    "wof:placetype":"venue"
},
  "geometry": {"coordinates":[-66.645324707,45.9537506104],"type":"Point"}
}