{
  "type": "Feature",
  "properties": {
    "addr:full":"10016 107 St Westlock AB T7P 2K8",
    "addr:housenumber":"10016",
    "addr:postcode":"t7p 2k8",
    "addr:street":"107 St",
    "iso:country":"CA",
    "sg:address":"10016 107 St",
    "sg:city":"Westlock",
    "sg:classifiers":[
        {
            "category":"Shopping",
            "subcategory":"Florist",
            "type":"Retail Goods"
        }
    ],
    "sg:phone":"+1 780 349 5454",
    "sg:postcode":"T7P 2K8",
    "sg:province":"AB",
    "wof:name":"Flower Barn",
    "wof:placetype":"venue"
},
  "geometry": {"coordinates":[-113.861816,54.156059],"type":"Point"}
}