{
  "type": "Feature",
  "properties": {
    "addr:full":"10123 95 Ave Fort St John BC V1J 1H9",
    "addr:housenumber":"10123",
    "addr:postcode":"v1j 1h9",
    "addr:street":"95 Ave",
    "iso:country":"CA",
    "sg:address":"10123 95 Ave",
    "sg:city":"Fort St John",
    "sg:classifiers":[
        {
            "category":"Wholesale",
            "subcategory":"Electrical",
            "type":"Manufacturing & Wholesale Goods"
        }
    ],
    "sg:phone":"+1 250 785 4374",
    "sg:postcode":"V1J 1H9",
    "sg:province":"BC",
    "sg:tags":[
        "instrument"
    ],
    "wof:name":"Dalco Instrument & Measurement",
    "wof:placetype":"venue"
},
  "geometry": {"coordinates":[-120.84953299999999,56.24131],"type":"Point"}
}