{
  "type": "Feature",
  "properties": {
    "addr:full":"176 Cardigan St Guelph ON N1H 3Z9",
    "addr:housenumber":"176",
    "addr:postcode":"n1h 3z9",
    "addr:street":"Cardigan St",
    "iso:country":"CA",
    "sg:address":"176 Cardigan St",
    "sg:city":"Guelph",
    "sg:classifiers":[
        {
            "category":"Retail",
            "subcategory":"Auto Repair",
            "type":"Services"
        }
    ],
    "sg:phone":"+1 519 836 3799",
    "sg:postcode":"N1H 3Z9",
    "sg:province":"ON",
    "sg:tags":[
        "wrecker"
    ],
    "wof:name":"Pelc Moto Motori",
    "wof:placetype":"venue"
},
  "geometry": {"coordinates":[-80.25657653810001,43.552280426],"type":"Point"}
}