{
  "type": "Feature",
  "properties": {
    "iso:country":"CA",
    "sg:address":"6895 Rue Joncaire",
    "sg:city":"Montreal",
    "sg:classifiers":[
        {
            "category":"Manufacturing",
            "subcategory":"Metals",
            "type":"Manufacturing & Wholesale Goods"
        }
    ],
    "sg:phone":"+1 514 253 8498",
    "sg:postcode":"H1M 3H1",
    "sg:province":"QC",
    "sg:tags":[
        "fire",
        "hydrant"
    ],
    "wof:name":"Hydra-Tech",
    "wof:placetype":"venue"
},
  "geometry": {"coordinates":[-73.5665969849,45.59425354],"type":"Point"}
}