{
  "type": "Feature",
  "properties": {
    "iso:country":"CA",
    "sg:city":"Windsor",
    "sg:classifiers":[
        {
            "category":"Freight",
            "type":"Transportation"
        }
    ],
    "sg:phone":"+1 519 256 8244",
    "sg:postcode":"N8X 4W6",
    "sg:province":"ON",
    "sg:tags":[
        "broker",
        "customs"
    ],
    "wof:name":"Russell A Farrow Ltd",
    "wof:placetype":"venue"
},
  "geometry": {"coordinates":[-83.0220031738,42.2995796204],"type":"Point"}
}