{
  "type": "Feature",
  "properties": {
    "iso:country":"CA",
    "sg:address":"22 James St",
    "sg:city":"Timberlea",
    "sg:classifiers":[
        {
            "category":"Education",
            "subcategory":"School",
            "type":"Public Place"
        }
    ],
    "sg:phone":"+1 902 876 3236",
    "sg:postcode":"B3T 1G9",
    "sg:province":"NS",
    "wof:name":"Beechville Lakeside Timberlea",
    "wof:placetype":"venue"
},
  "geometry": {"coordinates":[-63.7426452637,44.6587905884],"type":"Point"}
}