{
  "type": "Feature",
  "properties": {
    "addr:full":"2540 Ouellette Ave Windsor ON N8X 1L7",
    "addr:housenumber":"2540",
    "addr:postcode":"n8x 1l7",
    "addr:street":"Ouellette Ave",
    "iso:country":"CA",
    "sg:address":"2540 Ouellette Ave",
    "sg:city":"Windsor",
    "sg:classifiers":[
        {
            "category":"Food & Beverages",
            "subcategory":"Bakery",
            "type":"Retail Goods"
        }
    ],
    "sg:phone":"+1 519 966 9880",
    "sg:postcode":"N8X 1L7",
    "sg:province":"ON",
    "sg:tags":[
        "doughnut"
    ],
    "wof:name":"Tim Hortons",
    "wof:placetype":"venue"
},
  "geometry": {"coordinates":[-83.01960800000001,42.287685],"type":"Point"}
}