{
  "type": "Feature",
  "properties": {
    "iso:country":"CA",
    "sg:address":"1637 5A Ave",
    "sg:city":"Wainwright",
    "sg:classifiers":[
        {
            "category":"Building & Trades",
            "subcategory":"Electrical",
            "type":"Services"
        }
    ],
    "sg:phone":"+1 780 842 3303",
    "sg:postcode":"T9W 1J5",
    "sg:province":"AB",
    "sg:tags":[
        "electric",
        "contractor"
    ],
    "wof:name":"Owl Electric",
    "wof:placetype":"venue"
},
  "geometry": {"coordinates":[-110.84575653100001,52.833732605],"type":"Point"}
}