{
  "type": "Feature",
  "properties": {
    "addr:full":"13 Lemarchant Rd St. John's NL A1C 2G4",
    "addr:housenumber":"13",
    "addr:postcode":"a1c 2g4",
    "addr:street":"Lemarchant Rd",
    "iso:country":"CA",
    "sg:address":"13 Lemarchant Rd",
    "sg:city":"St. John's",
    "sg:classifiers":[
        {
            "category":"Restaurant",
            "type":"Food & Drink"
        }
    ],
    "sg:phone":"+1 709 726 4811",
    "sg:postcode":"A1C 2G4",
    "sg:province":"NL",
    "wof:name":"Loong Wah Restaurant",
    "wof:placetype":"venue"
},
  "geometry": {"coordinates":[-52.714802,47.563873],"type":"Point"}
}