{
  "type": "Feature",
  "properties": {
    "addr:full":"93 Glencoe Dr Mount Pearl NL A1N 4S7",
    "addr:housenumber":"93",
    "addr:postcode":"a1n 4s7",
    "addr:street":"Glencoe Dr",
    "iso:country":"CA",
    "sg:address":"93 Glencoe Dr",
    "sg:city":"Mount Pearl",
    "sg:classifiers":[
        {
            "category":"Wholesale",
            "subcategory":"Groceries",
            "type":"Manufacturing & Wholesale Goods"
        }
    ],
    "sg:phone":"+1 709 368 8336",
    "sg:postcode":"A1N 4S7",
    "sg:province":"NL",
    "sg:tags":[
        "food",
        "broker"
    ],
    "wof:name":"Concord National Inc",
    "wof:placetype":"venue"
},
  "geometry": {"coordinates":[-52.8467636108,47.518371582],"type":"Point"}
}