{
  "type": "Feature",
  "properties": {
    "addr:full":"78 Hathaway Lane Lacombe AB T4L 1T4",
    "addr:housenumber":"78",
    "addr:postcode":"t4l 1t4",
    "addr:street":"Hathaway Lane",
    "iso:country":"CA",
    "sg:address":"78 Hathaway Lane",
    "sg:city":"Lacombe",
    "sg:classifiers":[
        {
            "category":"Building & Trades",
            "subcategory":"Electrical",
            "type":"Services"
        }
    ],
    "sg:phone":"+1 403 782 6429",
    "sg:postcode":"T4L 1T4",
    "sg:province":"AB",
    "sg:tags":[
        "electric",
        "contractor"
    ],
    "wof:name":"Halliday Electric",
    "wof:placetype":"venue"
},
  "geometry": {"coordinates":[-113.71906300000001,52.481091],"type":"Point"}
}