{
  "type": "Feature",
  "properties": {
    "addr:full":"6909 Antrim Ave Burnaby BC V5J 4M5",
    "addr:housenumber":"6909",
    "addr:postcode":"v5j 4m5",
    "addr:street":"Antrim Ave",
    "iso:country":"CA",
    "sg:address":"6909 Antrim Ave",
    "sg:city":"Burnaby",
    "sg:classifiers":[
        {
            "category":"Wholesale",
            "subcategory":"Sporting Goods",
            "type":"Manufacturing & Wholesale Goods"
        }
    ],
    "sg:phone":"+1 604 437 4717",
    "sg:postcode":"V5J 4M5",
    "sg:province":"BC",
    "sg:tags":[
        "equipment",
        "steam",
        "bath"
    ],
    "wof:name":"Leisure Baths Ltd",
    "wof:placetype":"venue"
},
  "geometry": {"coordinates":[-122.985069275,49.2206726074],"type":"Point"}
}