{
  "type": "Feature",
  "properties": {
    "iso:country":"CA",
    "sg:address":"39 Jarlan Terr",
    "sg:city":"Kanata",
    "sg:classifiers":[
        {
            "category":"Insurance",
            "subcategory":"Insurance Agent",
            "type":"Services"
        }
    ],
    "sg:phone":"+1 613 592 9882",
    "sg:postcode":"K2L 3L7",
    "sg:province":"ON",
    "wof:name":"Garry Linttell Insurance Brkrs",
    "wof:placetype":"venue"
},
  "geometry": {"coordinates":[-75.90604400629999,45.3019332886],"type":"Point"}
}