{
  "type": "Feature",
  "properties": {
    "addr:full":"666 Boul Saint-Joseph Hull QC J8Y 4A8",
    "addr:housenumber":"666",
    "addr:postcode":"j8y 4a8",
    "addr:street":"Boul Saint-Joseph",
    "iso:country":"CA",
    "sg:address":"666 Boul Saint-Joseph",
    "sg:city":"Hull",
    "sg:classifiers":[
        {
            "category":"Shopping",
            "subcategory":"Florist",
            "type":"Retail Goods"
        }
    ],
    "sg:phone":"+1 819 770 3456",
    "sg:postcode":"J8Y 4A8",
    "sg:province":"QC",
    "wof:name":"Fleuriste Une Douce Pensee",
    "wof:placetype":"venue"
},
  "geometry": {"coordinates":[-75.73931899999999,45.453053],"type":"Point"}
}