{
  "type": "Feature",
  "properties": {
    "iso:country":"CA",
    "sg:address":"NE 23-17-22W",
    "sg:city":"Strathclair",
    "sg:classifiers":[
        {
            "category":"Manufacturing",
            "subcategory":"Tools & Machinery",
            "type":"Manufacturing & Wholesale Goods"
        }
    ],
    "sg:phone":"+1 204 365 5374",
    "sg:postcode":"R0J 2C0",
    "sg:province":"MB",
    "sg:tags":[
        "farm",
        "equipment"
    ],
    "wof:name":"Vern's Custom Agro",
    "wof:placetype":"venue"
},
  "geometry": {"coordinates":[-100.392189026,50.4036064148],"type":"Point"}
}