{
  "type": "Feature",
  "properties": {
    "addr:full":"Berthierville QC J0K 1A0",
    "addr:postcode":"j0k 1a0",
    "iso:country":"CA",
    "sg:city":"Berthierville",
    "sg:classifiers":[
        {
            "category":"Manufacturing",
            "subcategory":"Tools & Machinery",
            "type":"Manufacturing & Wholesale Goods"
        }
    ],
    "sg:phone":"+1 450 836 3721",
    "sg:postcode":"J0K 1A0",
    "sg:province":"QC",
    "sg:tags":[
        "steel"
    ],
    "wof:name":"Acier Hason Inc",
    "wof:placetype":"venue"
},
  "geometry": {"coordinates":[-73.1776351929,46.0876197815],"type":"Point"}
}