{
  "type": "Feature",
  "properties": {
    "addr:full":"426 Albert St Waterloo ON N2L 3V3",
    "addr:housenumber":"426",
    "addr:postcode":"n2l 3v3",
    "addr:street":"Albert St",
    "iso:country":"CA",
    "sg:address":"426 Albert St",
    "sg:city":"Waterloo",
    "sg:classifiers":[
        {
            "category":"Building & Trades",
            "subcategory":"Landscaping Services",
            "type":"Services"
        }
    ],
    "sg:phone":"+1 519 746 2848",
    "sg:postcode":"N2L 3V3",
    "sg:province":"ON",
    "sg:tags":[
        "landscape",
        "contractor"
    ],
    "wof:name":"Artistic Landscaping Inc",
    "wof:placetype":"venue"
},
  "geometry": {"coordinates":[-80.538155,43.482975],"type":"Point"}
}