{
  "type": "Feature",
  "properties": {
    "addr:full":"188 Isabel St Winnipeg MB R3A 1G7",
    "addr:housenumber":"188",
    "addr:postcode":"r3a 1g7",
    "addr:street":"Isabel St",
    "iso:country":"CA",
    "sg:address":"188 Isabel St",
    "sg:city":"Winnipeg",
    "sg:classifiers":[
        {
            "category":"Food & Beverages",
            "subcategory":"Meat & Fish",
            "type":"Retail Goods"
        }
    ],
    "sg:phone":"+1 204 774 2451",
    "sg:postcode":"R3A 1G7",
    "sg:province":"MB",
    "sg:tags":[
        "grocer"
    ],
    "wof:name":"Riediger's Supermarket Ltd",
    "wof:placetype":"venue"
},
  "geometry": {"coordinates":[-97.14881099999999,49.903584],"type":"Point"}
}