{
  "type": "Feature",
  "properties": {
    "addr:full":"1010 80E Rue E # 340 Charlesbourg QC G1H 6P2",
    "addr:housenumber":"1010",
    "addr:postcode":"g1h 6p2",
    "addr:street":"80E Rue E # 340",
    "iso:country":"CA",
    "sg:address":"1010 80E Rue E # 340",
    "sg:city":"Charlesbourg",
    "sg:classifiers":[
        {
            "category":"Health Services",
            "subcategory":"Doctor",
            "type":"Services"
        }
    ],
    "sg:phone":"+1 418 624 1644",
    "sg:postcode":"G1H 6P2",
    "sg:province":"QC",
    "sg:tags":[
        "dentist"
    ],
    "wof:name":"Clinique Dentaire C Blais",
    "wof:placetype":"venue"
},
  "geometry": {"coordinates":[-71.25116,46.845718],"type":"Point"}
}