{
  "type": "Feature",
  "properties": {
    "addr:full":"180 Leacock St Blind River ON P0R 1B0",
    "addr:housenumber":"180",
    "addr:postcode":"p0r 1b0",
    "addr:street":"Leacock St",
    "iso:country":"CA",
    "sg:address":"180 Leacock St",
    "sg:city":"Blind River",
    "sg:classifiers":[
        {
            "category":"Museum",
            "type":"Entertainment"
        }
    ],
    "sg:phone":"+1 705 356 7544",
    "sg:postcode":"P0R 1B0",
    "sg:province":"ON",
    "sg:tags":[
        "government"
    ],
    "wof:name":"Timber Village Museum",
    "wof:placetype":"venue"
},
  "geometry": {"coordinates":[-82.945564,46.18523],"type":"Point"}
}