{
  "type": "Feature",
  "properties": {
    "addr:full":"Spruce Grove AB T7X 4G2",
    "addr:postcode":"t7x 4g2",
    "iso:country":"CA",
    "sg:city":"Spruce Grove",
    "sg:classifiers":[
        {
            "category":"Recreation",
            "type":"Entertainment"
        }
    ],
    "sg:phone":"+1 780 962 5350",
    "sg:postcode":"T7X 4G2",
    "sg:province":"AB",
    "sg:tags":[
        "instruction",
        "gymnastic"
    ],
    "wof:name":"Spruce Grove Aerials Gymnstcs",
    "wof:placetype":"venue"
},
  "geometry": {"coordinates":[-113.88909099999999,53.539417],"type":"Point"}
}