{
  "type": "Feature",
  "properties": {
    "iso:country":"CA",
    "sg:address":"16 Rose Ave",
    "sg:city":"Orillia",
    "sg:classifiers":[
        {
            "category":"Organizations",
            "subcategory":"Community Association",
            "type":"Services"
        }
    ],
    "sg:phone":"+1 705 325 8366",
    "sg:postcode":"L3V 6Y5",
    "sg:province":"ON",
    "sg:tags":[
        "club"
    ],
    "wof:name":"Moose Lodge",
    "wof:placetype":"venue"
},
  "geometry": {"coordinates":[-79.42584991459999,44.5954933167],"type":"Point"}
}