{
  "type": "Feature",
  "properties": {
    "addr:full":"915 23 Ave SE Calgary AB T2G 1P1",
    "addr:housenumber":"915",
    "addr:postcode":"t2g 1p1",
    "addr:street":"23 Ave Se",
    "iso:country":"CA",
    "sg:address":"915 23 Ave SE",
    "sg:city":"Calgary",
    "sg:classifiers":[
        {
            "category":"Manufacturing",
            "subcategory":"Tools & Machinery",
            "type":"Manufacturing & Wholesale Goods"
        }
    ],
    "sg:phone":"+1 403 263 4200",
    "sg:postcode":"T2G 1P1",
    "sg:province":"AB",
    "sg:tags":[
        "equipment",
        "nurseryman",
        "greenhouse",
        "supply"
    ],
    "wof:name":"Professional Gardener CO Ltd",
    "wof:placetype":"venue"
},
  "geometry": {"coordinates":[-114.040672302,51.0327911377],"type":"Point"}
}