{
  "type": "Feature",
  "properties": {
    "addr:full":"48 Mill Rd Wellington Station PE C0B 2E0",
    "addr:housenumber":"48",
    "addr:postcode":"c0b 2e0",
    "addr:street":"Mill Rd",
    "iso:country":"CA",
    "sg:address":"48 Mill Rd",
    "sg:city":"Wellington Station",
    "sg:classifiers":[
        {
            "category":"Government",
            "subcategory":"Office",
            "type":"Public Place"
        }
    ],
    "sg:phone":"+1 902 854 2083",
    "sg:postcode":"C0B 2E0",
    "sg:province":"PE",
    "wof:name":"Canada Human Resource Ctrs",
    "wof:placetype":"venue"
},
  "geometry": {"coordinates":[-64.0004501343,46.4499511719],"type":"Point"}
}