{
  "type": "Feature",
  "properties": {
    "addr:full":"6858 West Coast Rd Sooke BC V0S 1N0",
    "addr:housenumber":"6858",
    "addr:postcode":"v0s 1n0",
    "addr:street":"West Coast Rd",
    "iso:country":"CA",
    "sg:address":"6858 West Coast Rd",
    "sg:city":"Sooke",
    "sg:classifiers":[
        {
            "category":"Bars & Pubs",
            "type":"Food & Drink"
        }
    ],
    "sg:phone":"+1 250 642 3333",
    "sg:postcode":"V0S 1N0",
    "sg:province":"BC",
    "wof:name":"Buffy's Pub",
    "wof:placetype":"venue"
},
  "geometry": {"coordinates":[-123.729103088,48.3699874878],"type":"Point"}
}