{
  "type": "Feature",
  "properties": {
    "addr:full":"Chemainus BC V0R 1K0",
    "addr:postcode":"v0r 1k0",
    "iso:country":"CA",
    "sg:city":"Chemainus",
    "sg:classifiers":[
        {
            "category":"Professional",
            "subcategory":"Computer Services",
            "type":"Services"
        }
    ],
    "sg:phone":"+1 250 246 4322",
    "sg:postcode":"V0R 1K0",
    "sg:province":"BC",
    "sg:tags":[
        "internet"
    ],
    "wof:name":"Shaw Home High Speed Internet",
    "wof:placetype":"venue"
},
  "geometry": {"coordinates":[-123.730361938,48.9306793213],"type":"Point"}
}