{
  "type": "Feature",
  "properties": {
    "iso:country":"CA",
    "sg:address":"241 Rue Nadeau",
    "sg:city":"Repentigny",
    "sg:classifiers":[
        {
            "category":"Building & Trades",
            "subcategory":"Electrical",
            "type":"Services"
        }
    ],
    "sg:phone":"+1 450 654 8306",
    "sg:postcode":"J5Y 3J4",
    "sg:province":"QC",
    "sg:tags":[
        "electric",
        "contractor"
    ],
    "wof:name":"Entreprises D'Electricite",
    "wof:placetype":"venue"
},
  "geometry": {"coordinates":[-73.42501799999999,45.779667],"type":"Point"}
}