{
  "type": "Feature",
  "properties": {
    "iso:country":"CA",
    "sg:city":"Perth",
    "sg:classifiers":[
        {
            "category":"Home & Garden",
            "subcategory":"Garden Supply",
            "type":"Retail Goods"
        }
    ],
    "sg:phone":"+1 613 267 7053",
    "sg:postcode":"K7H 3C8",
    "sg:province":"ON",
    "sg:tags":[
        "engine",
        "lawn",
        "mower"
    ],
    "wof:name":"Pete's Lawn & Marine",
    "wof:placetype":"venue"
},
  "geometry": {"coordinates":[-76.2594985962,44.912979126],"type":"Point"}
}