{
  "type": "Feature",
  "properties": {
    "addr:full":"Trinity Tb NL A0C 2S0",
    "addr:postcode":"a0c 2s0",
    "iso:country":"CA",
    "sg:city":"Trinity Tb",
    "sg:classifiers":[
        {
            "category":"Professional",
            "subcategory":"Research",
            "type":"Services"
        }
    ],
    "sg:phone":"+1 709 464 3700",
    "sg:postcode":"A0C 2S0",
    "sg:province":"NL",
    "sg:tags":[
        "development",
        "laboratory"
    ],
    "wof:name":"Ceta Research",
    "wof:placetype":"venue"
},
  "geometry": {"coordinates":[-53.359711,48.369068],"type":"Point"}
}