{
  "type": "Feature",
  "properties": {
    "addr:full":"3015 Boul DE Maisonneuve O Montreal QC H3Z 1J8",
    "addr:housenumber":"3015",
    "addr:postcode":"h3z 1j8",
    "addr:street":"Boul De Maisonneuve O",
    "iso:country":"CA",
    "sg:address":"3015 Boul DE Maisonneuve O",
    "sg:city":"Montreal",
    "sg:classifiers":[
        {
            "category":"Shopping",
            "subcategory":"Tobacco",
            "type":"Retail Goods"
        }
    ],
    "sg:phone":"+1 514 931 7693",
    "sg:postcode":"H3Z 1J8",
    "sg:province":"QC",
    "sg:tags":[
        "cigarette",
        "cigar",
        "dealer"
    ],
    "wof:name":"Tabagie Metro Atwater",
    "wof:placetype":"venue"
},
  "geometry": {"coordinates":[-73.58599100000001,45.49007],"type":"Point"}
}