{
  "type": "Feature",
  "properties": {
    "iso:country":"CA",
    "sg:address":"1515 Boul Du Tricentenaire",
    "sg:city":"Montreal",
    "sg:classifiers":[
        {
            "category":"Organizations",
            "subcategory":"Professional Association",
            "type":"Services"
        }
    ],
    "sg:phone":"+1 514 642 2168",
    "sg:postcode":"H1B 3A9",
    "sg:province":"QC",
    "wof:name":"L'Assn Du Hockey Mineur-Pat",
    "wof:placetype":"venue"
},
  "geometry": {"coordinates":[-73.4991760254,45.6512184143],"type":"Point"}
}