{
  "type": "Feature",
  "properties": {
    "addr:full":"5825 Riverside Dr E Windsor ON N8S 1B4",
    "addr:housenumber":"5825",
    "addr:postcode":"n8s 1b4",
    "addr:street":"Riverside Dr E",
    "iso:country":"CA",
    "sg:address":"5825 Riverside Dr E",
    "sg:city":"Windsor",
    "sg:classifiers":[
        {
            "category":"Real Estate",
            "subcategory":"Real Estate Agent",
            "type":"Services"
        }
    ],
    "sg:phone":"+1 519 945 6633",
    "sg:postcode":"N8S 1B4",
    "sg:province":"ON",
    "wof:name":"O'Brien Real Estate",
    "wof:placetype":"venue"
},
  "geometry": {"coordinates":[-82.968559,42.331631],"type":"Point"}
}