{
  "type": "Feature",
  "properties": {
    "addr:full":"55 Village Centre Pl Mississauga ON L4Z 1V9",
    "addr:housenumber":"55",
    "addr:postcode":"l4z 1v9",
    "addr:street":"Village Centre Pl",
    "iso:country":"CA",
    "sg:address":"55 Village Centre Pl",
    "sg:city":"Mississauga",
    "sg:classifiers":[
        {
            "category":"Social Services",
            "subcategory":"Child Care",
            "type":"Services"
        }
    ],
    "sg:phone":"+1 905 279 4869",
    "sg:postcode":"L4Z 1V9",
    "sg:province":"ON",
    "sg:tags":[
        "consultant",
        "search",
        "executive"
    ],
    "wof:name":"Care Match Inc",
    "wof:placetype":"venue"
},
  "geometry": {"coordinates":[-79.641029,43.600811],"type":"Point"}
}