{
  "type": "Feature",
  "properties": {
    "addr:full":"Calgary AB T2P 4H4",
    "addr:postcode":"t2p 4h4",
    "iso:country":"CA",
    "sg:city":"Calgary",
    "sg:classifiers":[
        {
            "category":"Banks & Credit Unions",
            "subcategory":"Investment Brokerage",
            "type":"Services"
        }
    ],
    "sg:phone":"+1 403 517 8880",
    "sg:postcode":"T2P 4H4",
    "sg:province":"AB",
    "sg:tags":[
        "consultant",
        "planning",
        "financial"
    ],
    "wof:name":"Twc Financial Corp",
    "wof:placetype":"venue"
},
  "geometry": {"coordinates":[-114.06617,51.0495],"type":"Point"}
}