{
  "type": "Feature",
  "properties": {
    "addr:full":"2308 96 St NW Edmonton AB T6N 1J8",
    "addr:housenumber":"2308",
    "addr:postcode":"t6n 1j8",
    "addr:street":"96 St Nw",
    "iso:country":"CA",
    "sg:address":"2308 96 St NW",
    "sg:city":"Edmonton",
    "sg:classifiers":[
        {
            "category":"Health Services",
            "subcategory":"Podiatrist",
            "type":"Services"
        }
    ],
    "sg:phone":"+1 780 444 3668",
    "sg:postcode":"T6N 1J8",
    "sg:province":"AB",
    "wof:name":"Foot Institute Inc",
    "wof:placetype":"venue"
},
  "geometry": {"coordinates":[-113.475677,53.452747],"type":"Point"}
}