{
  "type": "Feature",
  "properties": {
    "addr:full":"187 Boul Greber Gatineau QC J8T 3R1",
    "addr:housenumber":"187",
    "addr:postcode":"j8t 3r1",
    "addr:street":"Boul Greber",
    "iso:country":"CA",
    "sg:address":"187 Boul Greber",
    "sg:city":"Gatineau",
    "sg:classifiers":[
        {
            "category":"Wholesale",
            "subcategory":"Office Equipment",
            "type":"Manufacturing & Wholesale Goods"
        }
    ],
    "sg:phone":"+1 819 243 3349",
    "sg:postcode":"J8T 3R1",
    "sg:province":"QC",
    "sg:tags":[
        "return",
        "tax",
        "system",
        "preparation",
        "accounting",
        "bookkeeping",
        "filing"
    ],
    "wof:name":"Impot Direct Richard Beaulieu",
    "wof:placetype":"venue"
},
  "geometry": {"coordinates":[-75.70095825200001,45.472328186],"type":"Point"}
}