{
  "type": "Feature",
  "properties": {
    "addr:full":"5632 Logan Rd Niagara Falls ON L2E 6S6",
    "addr:housenumber":"5632",
    "addr:postcode":"l2e 6s6",
    "addr:street":"Logan Rd",
    "iso:country":"CA",
    "sg:address":"5632 Logan Rd",
    "sg:city":"Niagara Falls",
    "sg:classifiers":[
        {
            "category":"Building & Trades",
            "subcategory":"Plumbing",
            "type":"Services"
        }
    ],
    "sg:phone":"+1 905 295 4421",
    "sg:postcode":"L2E 6S6",
    "sg:province":"ON",
    "sg:tags":[
        "septic"
    ],
    "wof:name":"Brown's Septic Svc",
    "wof:placetype":"venue"
},
  "geometry": {"coordinates":[-79.088638,43.029686],"type":"Point"}
}