{
  "type": "Feature",
  "properties": {
    "iso:country":"CA",
    "sg:address":"4860 Dundas St W",
    "sg:city":"Etobicoke",
    "sg:classifiers":[
        {
            "category":"Banks & Credit Unions",
            "subcategory":"Bank",
            "type":"Services"
        }
    ],
    "sg:phone":"+1 416 239 8175",
    "sg:postcode":"M9A 1B5",
    "sg:province":"ON",
    "wof:name":"Royal Bank Financial Group",
    "wof:placetype":"venue"
},
  "geometry": {"coordinates":[-79.527603,43.650261],"type":"Point"}
}