{
  "type": "Feature",
  "properties": {
    "addr:full":"Vancouver BC V5Z 3X7",
    "addr:postcode":"v5z 3x7",
    "iso:country":"CA",
    "sg:city":"Vancouver",
    "sg:classifiers":[
        {
            "category":"Shopping",
            "subcategory":"Clothing, Apparel, & Fashions",
            "type":"Retail Goods"
        }
    ],
    "sg:phone":"+1 604 264 8558",
    "sg:postcode":"V5Z 3X7",
    "sg:province":"BC",
    "sg:tags":[
        "tailor"
    ],
    "wof:name":"Parker's Alteration Shop",
    "wof:placetype":"venue"
},
  "geometry": {"coordinates":[-123.11403656,49.2604408264],"type":"Point"}
}