{
  "type": "Feature",
  "properties": {
    "iso:country":"CA",
    "sg:address":"26 Dufferin St",
    "sg:city":"Lunenburg",
    "sg:classifiers":[
        {
            "category":"Travel",
            "subcategory":"Hotels & Motels",
            "type":"Entertainment"
        }
    ],
    "sg:phone":"+1 902 634 3963",
    "sg:postcode":"B0J 2C0",
    "sg:province":"NS",
    "sg:tags":[
        "inn"
    ],
    "wof:name":"Lunenburg Inn",
    "wof:placetype":"venue"
},
  "geometry": {"coordinates":[-64.3178939819,44.3789863586],"type":"Point"}
}