{
  "type": "Feature",
  "properties": {
    "iso:country":"CA",
    "sg:address":"718 Centre St N",
    "sg:city":"Whitby",
    "sg:classifiers":[
        {
            "category":"Building & Trades",
            "subcategory":"Landscaping Services",
            "type":"Services"
        }
    ],
    "sg:phone":"+1 905 666 3187",
    "sg:postcode":"L1N 9A9",
    "sg:province":"ON",
    "sg:tags":[
        "lawn",
        "maintenance",
        "grounds"
    ],
    "wof:name":"Weed Man",
    "wof:placetype":"venue"
},
  "geometry": {"coordinates":[-78.9483337402,43.8874092102],"type":"Point"}
}