{
  "type": "Feature",
  "properties": {
    "addr:full":"1047 Simcoe St S Oshawa ON L1H 4L4",
    "addr:housenumber":"1047",
    "addr:postcode":"l1h 4l4",
    "addr:street":"Simcoe St S",
    "iso:country":"CA",
    "sg:address":"1047 Simcoe St S",
    "sg:city":"Oshawa",
    "sg:classifiers":[
        {
            "category":"Food & Beverages",
            "subcategory":"Bakery",
            "type":"Retail Goods"
        }
    ],
    "sg:phone":"+1 905 723 6020",
    "sg:postcode":"L1H 4L4",
    "sg:province":"ON",
    "sg:tags":[
        "doughnut"
    ],
    "wof:name":"Coffee Time Donuts",
    "wof:placetype":"venue"
},
  "geometry": {"coordinates":[-78.844612,43.8741],"type":"Point"}
}