{
  "type": "Feature",
  "properties": {
    "addr:full":"1845 Eglinton Ave W York ON M6E 2J3",
    "addr:housenumber":"1845",
    "addr:postcode":"m6e 2j3",
    "addr:street":"Eglinton Ave W",
    "iso:country":"CA",
    "sg:address":"1845 Eglinton Ave W",
    "sg:city":"York",
    "sg:classifiers":[
        {
            "category":"Shopping",
            "subcategory":"Department Store",
            "type":"Retail Goods"
        }
    ],
    "sg:phone":"+1 416 787 2276",
    "sg:postcode":"M6E 2J3",
    "sg:province":"ON",
    "sg:tags":[
        "shop"
    ],
    "wof:name":"Super Bargain & Cigar Store",
    "wof:placetype":"venue"
},
  "geometry": {"coordinates":[-79.4509735107,43.6954650879],"type":"Point"}
}