{
  "type": "Feature",
  "properties": {
    "addr:full":"6784A Perth Line 88 Gowanstown ON N0G 1Y0",
    "addr:housenumber":"6784a",
    "addr:postcode":"n0g 1y0",
    "addr:street":"Perth Line 88",
    "iso:country":"CA",
    "sg:address":"6784A Perth Line 88",
    "sg:city":"Gowanstown",
    "sg:classifiers":[
        {
            "category":"Organizations",
            "subcategory":"Religious Organization",
            "type":"Services"
        }
    ],
    "sg:phone":"+1 519 291 1165",
    "sg:postcode":"N0G 1Y0",
    "sg:province":"ON",
    "sg:tags":[
        "church"
    ],
    "wof:name":"Trinity Lutheran Church",
    "wof:placetype":"venue"
},
  "geometry": {"coordinates":[-80.93966674799999,43.7817802429],"type":"Point"}
}