{
  "type": "Feature",
  "properties": {
    "addr:full":"91 Chapel St Nanaimo BC V9R 5H3",
    "addr:housenumber":"91",
    "addr:postcode":"v9r 5h3",
    "addr:street":"Chapel St",
    "iso:country":"CA",
    "sg:address":"91 Chapel St",
    "sg:city":"Nanaimo",
    "sg:classifiers":[
        {
            "category":"Cinema",
            "subcategory":"Movie Theater",
            "type":"Entertainment"
        }
    ],
    "sg:phone":"+1 250 754 3585",
    "sg:postcode":"V9R 5H3",
    "sg:province":"BC",
    "wof:name":"Bay Theatre",
    "wof:placetype":"venue"
},
  "geometry": {"coordinates":[-123.938118,49.168221],"type":"Point"}
}