{
  "type": "Feature",
  "properties": {
    "addr:full":"5035 Boul DE Maisonneuve O Montreal QC H4A 1Y5",
    "addr:housenumber":"5035",
    "addr:postcode":"h4a 1y5",
    "addr:street":"Boul De Maisonneuve O",
    "iso:country":"CA",
    "sg:address":"5035 Boul DE Maisonneuve O",
    "sg:city":"Montreal",
    "sg:classifiers":[
        {
            "category":"Organizations",
            "subcategory":"Religious Organization",
            "type":"Services"
        }
    ],
    "sg:phone":"+1 514 485 9933",
    "sg:postcode":"H4A 1Y5",
    "sg:province":"QC",
    "sg:tags":[
        "church"
    ],
    "wof:name":"Unitarian Church of Montreal",
    "wof:placetype":"venue"
},
  "geometry": {"coordinates":[-73.6028060913,45.4755134583],"type":"Point"}
}