{
  "type": "Feature",
  "properties": {
    "addr:full":"1388 272 St Aldergrove BC V4W 2P9",
    "addr:housenumber":"1388",
    "addr:postcode":"v4w 2p9",
    "addr:street":"272 St",
    "iso:country":"CA",
    "sg:address":"1388 272 St",
    "sg:city":"Aldergrove",
    "sg:classifiers":[
        {
            "category":"Organizations",
            "subcategory":"Professional Association",
            "type":"Services"
        }
    ],
    "sg:phone":"+1 604 856 6170",
    "sg:postcode":"V4W 2P9",
    "sg:province":"BC",
    "wof:name":"Fraser Valley Hunt",
    "wof:placetype":"venue"
},
  "geometry": {"coordinates":[-122.47067300000001,49.045849],"type":"Point"}
}