{
  "type": "Feature",
  "properties": {
    "addr:full":"4329 Buchanan St Burnaby BC V5C 3X7",
    "addr:housenumber":"4329",
    "addr:postcode":"v5c 3x7",
    "addr:street":"Buchanan St",
    "iso:country":"CA",
    "sg:address":"4329 Buchanan St",
    "sg:city":"Burnaby",
    "sg:classifiers":[
        {
            "category":"Building & Trades",
            "subcategory":"Construction",
            "type":"Services"
        }
    ],
    "sg:phone":"+1 604 299 6131",
    "sg:postcode":"V5C 3X7",
    "sg:province":"BC",
    "sg:tags":[
        "balancing"
    ],
    "wof:name":"High Performance Engines Ltd",
    "wof:placetype":"venue"
},
  "geometry": {"coordinates":[-123.00798,49.267597],"type":"Point"}
}