{
  "type": "Feature",
  "properties": {
    "addr:full":"Calgary AB T2P 5L3",
    "addr:postcode":"t2p 5l3",
    "iso:country":"CA",
    "sg:city":"Calgary",
    "sg:classifiers":[
        {
            "category":"Professional",
            "subcategory":"Accounting & Tax Preparation",
            "type":"Services"
        }
    ],
    "sg:phone":"+1 403 509 7500",
    "sg:postcode":"T2P 5L3",
    "sg:province":"AB",
    "sg:tags":[
        "accountant"
    ],
    "wof:name":"Price Waterhouse Coopers Llp",
    "wof:placetype":"venue"
},
  "geometry": {"coordinates":[-114.06338501,51.0482215881],"type":"Point"}
}