{
  "type": "Feature",
  "properties": {
    "addr:full":"2494 Kildare Rd Windsor ON N8W 2Y3",
    "addr:housenumber":"2494",
    "addr:postcode":"n8w 2y3",
    "addr:street":"Kildare Rd",
    "iso:country":"CA",
    "sg:address":"2494 Kildare Rd",
    "sg:city":"Windsor",
    "sg:classifiers":[
        {
            "category":"Building & Trades",
            "subcategory":"Construction",
            "type":"Services"
        }
    ],
    "sg:phone":"+1 519 252 7670",
    "sg:postcode":"N8W 2Y3",
    "sg:province":"ON",
    "sg:tags":[
        "painter"
    ],
    "wof:name":"Jackie's Painting & Decorating",
    "wof:placetype":"venue"
},
  "geometry": {"coordinates":[-82.994354,42.293861],"type":"Point"}
}