{
  "type": "Feature",
  "properties": {
    "iso:country":"CA",
    "sg:address":"4050 Rue Brodeur",
    "sg:city":"Sherbrooke",
    "sg:classifiers":[
        {
            "category":"Manufacturing",
            "subcategory":"Tools & Machinery",
            "type":"Manufacturing & Wholesale Goods"
        }
    ],
    "sg:phone":"+1 819 566 0066",
    "sg:postcode":"J1L 1V9",
    "sg:province":"QC",
    "sg:tags":[
        "machine",
        "shop"
    ],
    "wof:name":"Industries Ge Gilbert Inc",
    "wof:placetype":"venue"
},
  "geometry": {"coordinates":[-71.9642715454,45.3913612366],"type":"Point"}
}