{
  "type": "Feature",
  "properties": {
    "iso:country":"CA",
    "sg:address":"207 St. Paul St W",
    "sg:city":"St Catharines",
    "sg:classifiers":[
        {
            "category":"Building & Trades",
            "subcategory":"Cleaning & Sanitation",
            "type":"Services"
        }
    ],
    "sg:phone":"+1 905 684 1242",
    "sg:postcode":"L2S 2E1",
    "sg:province":"ON",
    "sg:tags":[
        "janitor"
    ],
    "wof:name":"Niagara Peninsula Janitor Svc",
    "wof:placetype":"venue"
},
  "geometry": {"coordinates":[-79.25689697270001,43.145942688],"type":"Point"}
}