{
  "type": "Feature",
  "properties": {
    "iso:country":"CA",
    "sg:address":"5 Rue Saint-Jean-Baptiste",
    "sg:city":"L'Anse-Saint-Jean",
    "sg:classifiers":[
        {
            "category":"Travel",
            "subcategory":"Hotels & Motels",
            "type":"Entertainment"
        }
    ],
    "sg:phone":"+1 418 272 3359",
    "sg:postcode":"G0V 1J0",
    "sg:province":"QC",
    "wof:name":"Auberge Du Mont-Edouard",
    "wof:placetype":"venue"
},
  "geometry": {"coordinates":[-70.244140625,48.1977157593],"type":"Point"}
}