{
  "type": "Feature",
  "properties": {
    "addr:full":"Barrie ON L4N 3K4",
    "addr:postcode":"l4n 3k4",
    "iso:country":"CA",
    "sg:city":"Barrie",
    "sg:classifiers":[
        {
            "category":"Food & Beverages",
            "subcategory":"Groceries & Convenience Stores",
            "type":"Retail Goods"
        }
    ],
    "sg:phone":"+1 705 737 4774",
    "sg:postcode":"L4N 3K4",
    "sg:province":"ON",
    "wof:name":"Allandale Jug City",
    "wof:placetype":"venue"
},
  "geometry": {"coordinates":[-79.6908187866,44.374042511],"type":"Point"}
}