{
  "type": "Feature",
  "properties": {
    "addr:full":"100 Sparks St # 1001 Ottawa ON K1P 5B7",
    "addr:housenumber":"100",
    "addr:postcode":"k1p 5b7",
    "addr:street":"Sparks St # 1001",
    "iso:country":"CA",
    "sg:address":"100 Sparks St # 1001",
    "sg:city":"Ottawa",
    "sg:classifiers":[
        {
            "category":"Professional",
            "subcategory":"Research",
            "type":"Services"
        }
    ],
    "sg:phone":"+1 613 234 4666",
    "sg:postcode":"K1P 5B7",
    "sg:province":"ON",
    "sg:tags":[
        "laboratory",
        "market",
        "analysis"
    ],
    "wof:name":"Ses Canada Research Inc",
    "wof:placetype":"venue"
},
  "geometry": {"coordinates":[-75.6976470947,45.4226074219],"type":"Point"}
}