{
  "type": "Feature",
  "properties": {
    "addr:full":"805 Gilmore Ave Burnaby BC V5C 4R9",
    "addr:housenumber":"805",
    "addr:postcode":"v5c 4r9",
    "addr:street":"Gilmore Ave",
    "iso:country":"CA",
    "sg:address":"805 Gilmore Ave",
    "sg:city":"Burnaby",
    "sg:classifiers":[
        {
            "category":"Food & Beverages",
            "subcategory":"Groceries & Convenience Stores",
            "type":"Retail Goods"
        }
    ],
    "sg:phone":"+1 604 299 7022",
    "sg:postcode":"V5C 4R9",
    "sg:province":"BC",
    "sg:tags":[
        "grocer"
    ],
    "wof:name":"Glenburn Grocery",
    "wof:placetype":"venue"
},
  "geometry": {"coordinates":[-123.01432,49.27737],"type":"Point"}
}