{
  "type": "Feature",
  "properties": {
    "addr:full":"51 Rue Deziel Levis QC G6V 3T7",
    "addr:housenumber":"51",
    "addr:postcode":"g6v 3t7",
    "addr:street":"Rue Deziel",
    "iso:country":"CA",
    "sg:address":"51 Rue Deziel",
    "sg:city":"Levis",
    "sg:classifiers":[
        {
            "category":"Education",
            "subcategory":"School",
            "type":"Public Place"
        }
    ],
    "sg:phone":"+1 418 833 7691",
    "sg:postcode":"G6V 3T7",
    "sg:province":"QC",
    "wof:name":"Marcelle Mallet",
    "wof:placetype":"venue"
},
  "geometry": {"coordinates":[-71.184929,46.809731],"type":"Point"}
}