{
  "type": "Feature",
  "properties": {
    "addr:full":"32068 King Rd Abbotsford BC V2T 5Z5",
    "addr:housenumber":"32068",
    "addr:postcode":"v2t 5z5",
    "addr:street":"King Rd",
    "iso:country":"CA",
    "sg:address":"32068 King Rd",
    "sg:city":"Abbotsford",
    "sg:classifiers":[
        {
            "category":"Organizations",
            "subcategory":"Religious Organization",
            "type":"Services"
        }
    ],
    "sg:phone":"+1 604 864 0030",
    "sg:postcode":"V2T 5Z5",
    "sg:province":"BC",
    "sg:tags":[
        "church"
    ],
    "wof:name":"King Road Mennonite Brethren",
    "wof:placetype":"venue"
},
  "geometry": {"coordinates":[-122.33387,49.030754],"type":"Point"}
}