{
  "type": "Feature",
  "properties": {
    "iso:country":"CA",
    "sg:address":"441 Rue Sauvageau",
    "sg:city":"Thetford Mines",
    "sg:classifiers":[
        {
            "category":"Retail",
            "subcategory":"Auto Repair",
            "type":"Services"
        }
    ],
    "sg:phone":"+1 418 335 5343",
    "sg:postcode":"G6G 2H1",
    "sg:province":"QC",
    "sg:tags":[
        "repairing",
        "automobile"
    ],
    "wof:name":"Garage Camille Jacques Inc",
    "wof:placetype":"venue"
},
  "geometry": {"coordinates":[-71.29527282710001,46.099105835],"type":"Point"}
}