{
  "type": "Feature",
  "properties": {
    "iso:country":"CA",
    "sg:city":"Kanata",
    "sg:classifiers":[
        {
            "category":"Health Services",
            "subcategory":"Doctor",
            "type":"Services"
        }
    ],
    "sg:phone":"+1 613 599 8555",
    "sg:postcode":"K2L 4B6",
    "sg:province":"ON",
    "sg:tags":[
        "dentist"
    ],
    "wof:name":"Whyte, R J DDS",
    "wof:placetype":"venue"
},
  "geometry": {"coordinates":[-75.904655,45.299355],"type":"Point"}
}