{
  "type": "Feature",
  "properties": {
    "addr:full":"St Leonard NB E7E 1Y1",
    "addr:postcode":"e7e 1y1",
    "addr:street":"St",
    "iso:country":"CA",
    "sg:city":"St Leonard",
    "sg:classifiers":[
        {
            "category":"Insurance",
            "subcategory":"Insurance Agent",
            "type":"Services"
        }
    ],
    "sg:phone":"+1 506 423 1122",
    "sg:postcode":"E7E 1Y1",
    "sg:province":"NB",
    "wof:name":"Assurance Laurent Beaupre Inc",
    "wof:placetype":"venue"
},
  "geometry": {"coordinates":[-67.930008,47.159828],"type":"Point"}
}