{
  "type": "Feature",
  "properties": {
    "iso:country":"CA",
    "sg:address":"1233 Donald St",
    "sg:city":"Gloucester",
    "sg:classifiers":[
        {
            "category":"Wholesale",
            "subcategory":"Non-durable Goods",
            "type":"Manufacturing & Wholesale Goods"
        }
    ],
    "sg:phone":"+1 613 744 3982",
    "sg:postcode":"K1J 8W3",
    "sg:province":"ON",
    "sg:tags":[
        "interior",
        "curtain",
        "drapery"
    ],
    "wof:name":"A-1 Bou Clair Inc",
    "wof:placetype":"venue"
},
  "geometry": {"coordinates":[-75.63755,45.42918],"type":"Point"}
}