{
  "type": "Feature",
  "properties": {
    "addr:full":"610 Evergreen Rd Campbell River BC V9W 3R8",
    "addr:housenumber":"610",
    "addr:postcode":"v9w 3r8",
    "addr:street":"Evergreen Rd",
    "iso:country":"CA",
    "sg:address":"610 Evergreen Rd",
    "sg:city":"Campbell River",
    "sg:classifiers":[
        {
            "category":"Health Services",
            "subcategory":"Podiatrist",
            "type":"Services"
        }
    ],
    "sg:phone":"+1 250 286 1660",
    "sg:postcode":"V9W 3R8",
    "sg:province":"BC",
    "wof:name":"Behrens, Bret A DPM",
    "wof:placetype":"venue"
},
  "geometry": {"coordinates":[-125.247787476,50.0077171326],"type":"Point"}
}