{
  "type": "Feature",
  "properties": {
    "addr:full":"185 Williams Rd Hinton AB T7V 1Z1",
    "addr:housenumber":"185",
    "addr:postcode":"t7v 1z1",
    "addr:street":"Williams Rd",
    "iso:country":"CA",
    "sg:address":"185 Williams Rd",
    "sg:city":"Hinton",
    "sg:classifiers":[
        {
            "category":"Shopping",
            "subcategory":"Clothing, Apparel, & Fashions",
            "type":"Retail Goods"
        }
    ],
    "sg:phone":"+1 780 865 3544",
    "sg:postcode":"T7V 1Z1",
    "sg:province":"AB",
    "sg:tags":[
        "salvage",
        "surplus",
        "merchandise"
    ],
    "wof:name":"Rocky Mountain Salvage",
    "wof:placetype":"venue"
},
  "geometry": {"coordinates":[-117.60562899999999,53.399223],"type":"Point"}
}