{
  "type": "Feature",
  "properties": {
    "addr:full":"6848 Av Christophe-Colomb Montreal QC H2S 2H2",
    "addr:housenumber":"6848",
    "addr:postcode":"h2s 2h2",
    "addr:street":"Av Christophe-Colomb",
    "iso:country":"CA",
    "sg:address":"6848 Av Christophe-Colomb",
    "sg:city":"Montreal",
    "sg:classifiers":[
        {
            "category":"Organizations",
            "subcategory":"Professional Association",
            "type":"Services"
        }
    ],
    "sg:phone":"+1 514 495 3494",
    "sg:postcode":"H2S 2H2",
    "sg:province":"QC",
    "wof:name":"Groupe D'Entraide Maternelle",
    "wof:placetype":"venue"
},
  "geometry": {"coordinates":[-73.607093811,45.5401496887],"type":"Point"}
}