{
  "type": "Feature",
  "properties": {
    "addr:full":"15 Rue DE Colbert Gatineau QC J8T 8B4",
    "addr:housenumber":"15",
    "addr:postcode":"j8t 8b4",
    "addr:street":"Rue De Colbert",
    "iso:country":"CA",
    "sg:address":"15 Rue DE Colbert",
    "sg:city":"Gatineau",
    "sg:classifiers":[
        {
            "category":"Retail",
            "subcategory":"Repair Shop",
            "type":"Services"
        }
    ],
    "sg:phone":"+1 819 243 1424",
    "sg:postcode":"J8T 8B4",
    "sg:province":"QC",
    "sg:tags":[
        "repairing",
        "piano",
        "refinishing"
    ],
    "wof:name":"Charette, Yves",
    "wof:placetype":"venue"
},
  "geometry": {"coordinates":[-75.737831,45.479725],"type":"Point"}
}