{
  "type": "Feature",
  "properties": {
    "addr:full":"111 Kemp Cres Prince Albert SK S6V 6G9",
    "addr:housenumber":"111",
    "addr:postcode":"s6v 6g9",
    "addr:street":"Kemp Cres",
    "iso:country":"CA",
    "sg:address":"111 Kemp Cres",
    "sg:city":"Prince Albert",
    "sg:classifiers":[
        {
            "category":"Retail",
            "subcategory":"Repair Shop",
            "type":"Services"
        }
    ],
    "sg:phone":"+1 306 764 6333",
    "sg:postcode":"S6V 6G9",
    "sg:province":"SK",
    "sg:tags":[
        "lock",
        "locksmith"
    ],
    "wof:name":"A 1 Locksmithing",
    "wof:placetype":"venue"
},
  "geometry": {"coordinates":[-105.703552,53.20697],"type":"Point"}
}