{
  "type": "Feature",
  "properties": {
    "addr:full":"6025 Boul Metropolitain E Saint-Leonard QC H1P 1X5",
    "addr:housenumber":"6025",
    "addr:postcode":"h1p 1x5",
    "addr:street":"Boul Metropolitain E",
    "iso:country":"CA",
    "sg:address":"6025 Boul Metropolitain E",
    "sg:city":"Saint-Leonard",
    "sg:classifiers":[
        {
            "category":"Government",
            "subcategory":"Office",
            "type":"Public Place"
        }
    ],
    "sg:phone":"+1 514 328 8300",
    "sg:postcode":"H1P 1X5",
    "sg:province":"QC",
    "sg:tags":[
        "village"
    ],
    "wof:name":"St-Leonard Travaux Publics",
    "wof:placetype":"venue"
},
  "geometry": {"coordinates":[-73.583496,45.589001],"type":"Point"}
}