{
  "type": "Feature",
  "properties": {
    "addr:full":"410 Sherbourne St Toronto ON M4X 1K2",
    "addr:housenumber":"410",
    "addr:postcode":"m4x 1k2",
    "addr:street":"Sherbourne St",
    "iso:country":"CA",
    "sg:address":"410 Sherbourne St",
    "sg:city":"Toronto",
    "sg:classifiers":[
        {
            "category":"Health Services",
            "subcategory":"Doctor",
            "type":"Services"
        }
    ],
    "sg:phone":"+1 416 867 3728",
    "sg:postcode":"M4X 1K2",
    "sg:province":"ON",
    "sg:tags":[
        "physician",
        "surgeon"
    ],
    "wof:name":"Glazier, Richard MD",
    "wof:placetype":"venue"
},
  "geometry": {"coordinates":[-79.3737945557,43.6645126343],"type":"Point"}
}