{
  "type": "Feature",
  "properties": {
    "addr:full":"15 Wertheim Crt Richmond Hill ON L4B 3H7",
    "addr:housenumber":"15",
    "addr:postcode":"l4b 3h7",
    "addr:street":"Wertheim Crt",
    "iso:country":"CA",
    "sg:address":"15 Wertheim Crt",
    "sg:city":"Richmond Hill",
    "sg:classifiers":[
        {
            "category":"Health Services",
            "subcategory":"Optometrist",
            "type":"Services"
        }
    ],
    "sg:phone":"+1 905 882 0329",
    "sg:postcode":"L4B 3H7",
    "sg:province":"ON",
    "wof:name":"Szemere, Kathy J M OD",
    "wof:placetype":"venue"
},
  "geometry": {"coordinates":[-79.386436,43.845062],"type":"Point"}
}