{
  "type": "Feature",
  "properties": {
    "addr:full":"37 Alma St Ingersoll ON N5C 1N1",
    "addr:housenumber":"37",
    "addr:postcode":"n5c 1n1",
    "addr:street":"Alma St",
    "iso:country":"CA",
    "sg:address":"37 Alma St",
    "sg:city":"Ingersoll",
    "sg:classifiers":[
        {
            "category":"Professional",
            "subcategory":"Employment Agencies",
            "type":"Services"
        }
    ],
    "sg:phone":"+1 519 485 6088",
    "sg:postcode":"N5C 1N1",
    "sg:province":"ON",
    "sg:tags":[
        "opportunity"
    ],
    "wof:name":"Ingersoll Learning & Employ",
    "wof:placetype":"venue"
},
  "geometry": {"coordinates":[-80.888397,43.044769],"type":"Point"}
}