{
  "type": "Feature",
  "properties": {
    "iso:country":"CA",
    "sg:city":"Barrie",
    "sg:classifiers":[
        {
            "category":"Health Services",
            "subcategory":"Doctor",
            "type":"Services"
        }
    ],
    "sg:phone":"+1 705 737 5111",
    "sg:postcode":"L4N 8A8",
    "sg:province":"ON",
    "sg:tags":[
        "dentist"
    ],
    "wof:name":"Wheeler, Art DDS",
    "wof:placetype":"venue"
},
  "geometry": {"coordinates":[-79.659645,44.354553],"type":"Point"}
}