{
  "type": "Feature",
  "properties": {
    "addr:full":"PO Box 5350 Haines Junction YT Y0B 1L0",
    "addr:housenumber":"po;5350",
    "addr:postcode":"y0b 1l0",
    "addr:street":"Box",
    "iso:country":"CA",
    "sg:address":"PO Box 5350",
    "sg:city":"Haines Junction",
    "sg:classifiers":[
        {
            "category":"Education",
            "subcategory":"Library",
            "type":"Public Place"
        }
    ],
    "sg:phone":"+1 867 634 2215",
    "sg:postcode":"Y0B 1L0",
    "sg:province":"YT",
    "wof:name":"Haines Junction Public Library",
    "wof:placetype":"venue"
},
  "geometry": {"coordinates":[-137.51068115199999,60.7533988953],"type":"Point"}
}