{
  "type": "Feature",
  "properties": {
    "iso:country":"CA",
    "sg:address":"406 13 St N",
    "sg:city":"Lethbridge",
    "sg:classifiers":[
        {
            "category":"Shopping",
            "subcategory":"Jewelry",
            "type":"Retail Goods"
        }
    ],
    "sg:phone":"+1 403 327 7610",
    "sg:postcode":"T1H 2S2",
    "sg:province":"AB",
    "sg:tags":[
        "jeweler"
    ],
    "wof:name":"Higa's Jewellry Ltd",
    "wof:placetype":"venue"
},
  "geometry": {"coordinates":[-112.82427215600001,49.7048187256],"type":"Point"}
}