{
  "type": "Feature",
  "properties": {
    "addr:full":"39 Queen St N Tilbury ON N0P 2L0",
    "addr:housenumber":"39",
    "addr:postcode":"n0p 2l0",
    "addr:street":"Queen St N",
    "iso:country":"CA",
    "sg:address":"39 Queen St N",
    "sg:city":"Tilbury",
    "sg:classifiers":[
        {
            "category":"Shopping",
            "subcategory":"Computers & Home Electronics",
            "type":"Retail Goods"
        }
    ],
    "sg:phone":"+1 519 682 0111",
    "sg:postcode":"N0P 2L0",
    "sg:province":"ON",
    "sg:tags":[
        "equipment",
        "satellite",
        "system"
    ],
    "wof:name":"Video Scan",
    "wof:placetype":"venue"
},
  "geometry": {"coordinates":[-82.43222045900001,42.2606506348],"type":"Point"}
}