{
  "type": "Feature",
  "properties": {
    "addr:full":"210 King St W Chatham ON N7M 1E5",
    "addr:housenumber":"210",
    "addr:postcode":"n7m 1e5",
    "addr:street":"King St W",
    "iso:country":"CA",
    "sg:address":"210 King St W",
    "sg:city":"Chatham",
    "sg:classifiers":[
        {
            "category":"Shopping",
            "subcategory":"Clothing, Apparel, & Fashions",
            "type":"Retail Goods"
        }
    ],
    "sg:phone":"+1 519 352 0244",
    "sg:postcode":"N7M 1E5",
    "sg:province":"ON",
    "sg:tags":[
        "furnishing"
    ],
    "wof:name":"Lionel's Men's Wear",
    "wof:placetype":"venue"
},
  "geometry": {"coordinates":[-82.18795799999999,42.405247],"type":"Point"}
}