{
  "type": "Feature",
  "properties": {
    "iso:country":"CA",
    "sg:address":"117 Rue DE LA Villa",
    "sg:city":"Les Mechins",
    "sg:classifiers":[
        {
            "category":"Real Estate",
            "subcategory":"Real Estate Operator",
            "type":"Services"
        }
    ],
    "sg:phone":"+1 418 729 3635",
    "sg:postcode":"G0J 1T0",
    "sg:province":"QC",
    "sg:tags":[
        "apartment"
    ],
    "wof:name":"Office Municipal D'Habitation",
    "wof:placetype":"venue"
},
  "geometry": {"coordinates":[-66.9726715088,48.9999923706],"type":"Point"}
}