{
  "type": "Feature",
  "properties": {
    "addr:full":"117 Rue DE LA Villa Les Mechins QC G0J 1T0",
    "addr:housenumber":"117",
    "addr:postcode":"g0j 1t0",
    "addr:street":"Rue De La Villa Les Mechins",
    "iso:country":"CA",
    "sg:address":"117 Rue DE LA Villa",
    "sg:city":"Les Mechins",
    "sg:classifiers":[
        {
            "category":"Real Estate",
            "subcategory":"Real Estate Operator",
            "type":"Services"
        }
    ],
    "sg:phone":"+1 418 729 3635",
    "sg:postcode":"G0J 1T0",
    "sg:province":"QC",
    "sg:tags":[
        "apartment"
    ],
    "wof:name":"Office Municipal D'Habitation",
    "wof:placetype":"venue"
},
  "geometry": {"coordinates":[-66.9726715088,48.9999923706],"type":"Point"}
}