{
  "type": "Feature",
  "properties": {
    "addr:full":"5611 4 St NW Calgary AB T2K 1B3",
    "addr:housenumber":"5611 4",
    "addr:postcode":"t2k 1b3",
    "addr:street":"St Nw",
    "iso:country":"CA",
    "sg:address":"5611 4 St NW",
    "sg:city":"Calgary",
    "sg:classifiers":[
        {
            "category":"Shopping",
            "subcategory":"Pharmacy",
            "type":"Retail Goods"
        }
    ],
    "sg:phone":"+1 403 275 1222",
    "sg:postcode":"T2K 1B3",
    "sg:province":"AB",
    "wof:name":"Shoppers Drug Mart",
    "wof:placetype":"venue"
},
  "geometry": {"coordinates":[-114.071662903,51.1014442444],"type":"Point"}
}