{
  "type": "Feature",
  "properties": {
    "addr:full":"Pointe-Claire QC H9R 4S3",
    "addr:postcode":"h9r 4s3",
    "iso:country":"CA",
    "sg:city":"Pointe-Claire",
    "sg:classifiers":[
        {
            "category":"Shopping",
            "type":"Retail Goods"
        }
    ],
    "sg:phone":"+1 514 697 8868",
    "sg:postcode":"H9R 4S3",
    "sg:province":"QC",
    "sg:tags":[
        "equipment",
        "hospital",
        "orthopedic",
        "appliance",
        "supply"
    ],
    "wof:name":"Medequip",
    "wof:placetype":"venue"
},
  "geometry": {"coordinates":[-73.8331985474,45.4503555298],"type":"Point"}
}