{
  "type": "Feature",
  "properties": {
    "addr:full":"Norwood ON K0L 2V0",
    "addr:postcode":"k0l 2v0",
    "iso:country":"CA",
    "sg:city":"Norwood",
    "sg:classifiers":[
        {
            "category":"Banks & Credit Unions",
            "subcategory":"Bank",
            "type":"Services"
        }
    ],
    "sg:phone":"+1 705 639 5371",
    "sg:postcode":"K0L 2V0",
    "sg:province":"ON",
    "wof:name":"Royal Bank Financial Group",
    "wof:placetype":"venue"
},
  "geometry": {"coordinates":[-77.979133606,44.3830337524],"type":"Point"}
}