{
  "type": "Feature",
  "properties": {
    "iso:country":"CA",
    "sg:address":"106 Metcalfe St E",
    "sg:city":"Strathroy",
    "sg:classifiers":[
        {
            "category":"Autos & Motor Vehicles",
            "subcategory":"Auto Supplies",
            "type":"Retail Goods"
        }
    ],
    "sg:phone":"+1 519 245 7656",
    "sg:postcode":"N7G 1P3",
    "sg:province":"ON",
    "sg:tags":[
        "equipment",
        "racing",
        "car",
        "automobile"
    ],
    "wof:name":"Gary's Automotive Performance",
    "wof:placetype":"venue"
},
  "geometry": {"coordinates":[-81.6187744141,42.9581718445],"type":"Point"}
}