{
  "type": "Feature",
  "properties": {
    "addr:full":"411 Boul Saint-Joseph O Outremont QC H2V 2P3",
    "addr:housenumber":"411",
    "addr:postcode":"h2v 2p3",
    "addr:street":"Boul Saint-Joseph O",
    "iso:country":"CA",
    "sg:address":"411 Boul Saint-Joseph O",
    "sg:city":"Outremont",
    "sg:classifiers":[
        {
            "category":"Health Services",
            "subcategory":"Doctor",
            "type":"Services"
        }
    ],
    "sg:phone":"+1 514 274 9730",
    "sg:postcode":"H2V 2P3",
    "sg:province":"QC",
    "sg:tags":[
        "dentist"
    ],
    "wof:name":"Durand, Claude DDS",
    "wof:placetype":"venue"
},
  "geometry": {"coordinates":[-73.595848,45.517612],"type":"Point"}
}