{
  "type": "Feature",
  "properties": {
    "addr:full":"4910 50th Ave Vegreville AB T9C 1R4",
    "addr:housenumber":"4910",
    "addr:postcode":"t9c 1r4",
    "addr:street":"50Th Ave",
    "iso:country":"CA",
    "sg:address":"4910 50th Ave",
    "sg:city":"Vegreville",
    "sg:classifiers":[
        {
            "category":"Utilities",
            "subcategory":"Mobile Phone",
            "type":"Services"
        }
    ],
    "sg:phone":"+1 780 632 6649",
    "sg:postcode":"T9C 1R4",
    "sg:province":"AB",
    "sg:tags":[
        "telephone",
        "cellular"
    ],
    "wof:name":"A Plus Cellular",
    "wof:placetype":"venue"
},
  "geometry": {"coordinates":[-112.050605774,53.4940223694],"type":"Point"}
}