{
  "type": "Feature",
  "properties": {
    "addr:full":"Sainte-Foy QC G1V 2M2",
    "addr:postcode":"g1v 2m2",
    "iso:country":"CA",
    "sg:city":"Sainte-Foy",
    "sg:classifiers":[
        {
            "category":"Banks & Credit Unions",
            "subcategory":"Investment Brokerage",
            "type":"Services"
        }
    ],
    "sg:phone":"+1 418 656 1212",
    "sg:postcode":"G1V 2M2",
    "sg:province":"QC",
    "wof:name":"Mac Dougall Mac Dougall",
    "wof:placetype":"venue"
},
  "geometry": {"coordinates":[-71.2896194458,46.7663269043],"type":"Point"}
}