{
  "type": "Feature",
  "properties": {
    "iso:country":"CA",
    "sg:address":"35 Boul Du Plateau",
    "sg:city":"Hull",
    "sg:classifiers":[
        {
            "category":"Shopping",
            "subcategory":"Pharmacy",
            "type":"Retail Goods"
        }
    ],
    "sg:phone":"+1 819 772 0197",
    "sg:postcode":"J9A 3G1",
    "sg:province":"QC",
    "wof:name":"Pharmacie Paul Tousignant",
    "wof:placetype":"venue"
},
  "geometry": {"coordinates":[-75.7715301514,45.4364051819],"type":"Point"}
}