{
  "type": "Feature",
  "properties": {
    "addr:full":"279 Hillside Dr S Elliot Lake ON P5A 1N7",
    "addr:housenumber":"279",
    "addr:postcode":"p5a 1n7",
    "addr:street":"Hillside Dr S",
    "iso:country":"CA",
    "sg:address":"279 Hillside Dr S",
    "sg:city":"Elliot Lake",
    "sg:classifiers":[
        {
            "category":"Food & Beverages",
            "subcategory":"Groceries & Convenience Stores",
            "type":"Retail Goods"
        }
    ],
    "sg:phone":"+1 705 848 6575",
    "sg:postcode":"P5A 1N7",
    "sg:province":"ON",
    "wof:name":"Hillside Shop & Save",
    "wof:placetype":"venue"
},
  "geometry": {"coordinates":[-82.659683,46.380291],"type":"Point"}
}