{
  "type": "Feature",
  "properties": {
    "addr:full":"2575 75th Ave Grand Forks BC V0H 1H2",
    "addr:housenumber":"2575",
    "addr:postcode":"v0h 1h2",
    "addr:street":"75Th Ave",
    "iso:country":"CA",
    "sg:address":"2575 75th Ave",
    "sg:city":"Grand Forks",
    "sg:classifiers":[
        {
            "category":"Education",
            "subcategory":"School",
            "type":"Public Place"
        }
    ],
    "sg:phone":"+1 250 442 8275",
    "sg:postcode":"V0H 1H2",
    "sg:province":"BC",
    "wof:name":"John A Hutton Elementary",
    "wof:placetype":"venue"
},
  "geometry": {"coordinates":[-118.47007000000001,49.025818],"type":"Point"}
}