{
  "type": "Feature",
  "properties": {
    "addr:full":"14 W Cameron Rd Essex ON N8M 2X5",
    "addr:housenumber":"14",
    "addr:postcode":"n8m 2x5",
    "addr:street":"W Cameron Rd",
    "iso:country":"CA",
    "sg:address":"14 W Cameron Rd",
    "sg:city":"Essex",
    "sg:classifiers":[
        {
            "category":"Manufacturing",
            "subcategory":"Rubber & Plastics",
            "type":"Manufacturing & Wholesale Goods"
        }
    ],
    "sg:phone":"+1 519 839 4120",
    "sg:postcode":"N8M 2X5",
    "sg:province":"ON",
    "sg:tags":[
        "mold",
        "maker"
    ],
    "wof:name":"Northridge Plastics Ltd",
    "wof:placetype":"venue"
},
  "geometry": {"coordinates":[-82.823257,42.176418],"type":"Point"}
}