{
  "type": "Feature",
  "properties": {
    "addr:full":"1245 Rue Du Square-Phillips Montreal QC H3B 3E9",
    "addr:housenumber":"1245",
    "addr:postcode":"h3b 3e9",
    "addr:street":"Rue Du Square-Phillips",
    "iso:country":"CA",
    "sg:address":"1245 Rue Du Square-Phillips",
    "sg:city":"Montreal",
    "sg:classifiers":[
        {
            "category":"Restaurant",
            "type":"Food & Drink"
        }
    ],
    "sg:phone":"+1 514 282 8388",
    "sg:postcode":"H3B 3E9",
    "sg:province":"QC",
    "wof:name":"Soupebol Nouillerie",
    "wof:placetype":"venue"
},
  "geometry": {"coordinates":[-73.55438995359999,45.5122871399],"type":"Point"}
}