{
  "type": "Feature",
  "properties": {
    "addr:full":"270 Rue Du Parc Mont-Saint-Hilaire QC J3H 2Y3",
    "addr:housenumber":"270",
    "addr:postcode":"j3h 2y3",
    "addr:street":"Rue Du Parc",
    "iso:country":"CA",
    "sg:address":"270 Rue Du Parc",
    "sg:city":"Mont-Saint-Hilaire",
    "sg:classifiers":[
        {
            "category":"Building & Trades",
            "subcategory":"Construction",
            "type":"Services"
        }
    ],
    "sg:phone":"+1 450 446 5589",
    "sg:postcode":"J3H 2Y3",
    "sg:province":"QC",
    "sg:tags":[
        "repairing",
        "remodeling",
        "contractor"
    ],
    "wof:name":"Adam Denis Construction Inc",
    "wof:placetype":"venue"
},
  "geometry": {"coordinates":[-73.1901626587,45.5613937378],"type":"Point"}
}