{
  "type": "Feature",
  "properties": {
    "addr:full":"110 3rd St Cochrane ON P0L 1C0",
    "addr:housenumber":"110",
    "addr:postcode":"p0l 1c0",
    "addr:street":"3Rd St",
    "iso:country":"CA",
    "sg:address":"110 3rd St",
    "sg:city":"Cochrane",
    "sg:classifiers":[
        {
            "category":"Insurance",
            "subcategory":"Insurance Agent",
            "type":"Services"
        }
    ],
    "sg:phone":"+1 705 272 4315",
    "sg:postcode":"P0L 1C0",
    "sg:province":"ON",
    "wof:name":"Paul Ayotte Insurance Brokers",
    "wof:placetype":"venue"
},
  "geometry": {"coordinates":[-81.0289306641,49.0617637634],"type":"Point"}
}