{
  "type": "Feature",
  "properties": {
    "addr:full":"7925 Seeker Rd Brockville ON K6V 5T2",
    "addr:housenumber":"7925",
    "addr:postcode":"k6v 5t2",
    "addr:street":"Seeker Rd",
    "iso:country":"CA",
    "sg:address":"7925 Seeker Rd",
    "sg:city":"Brockville",
    "sg:classifiers":[
        {
            "category":"Manufacturing",
            "subcategory":"Building Materials",
            "type":"Manufacturing & Wholesale Goods"
        }
    ],
    "sg:phone":"+1 613 926 2106",
    "sg:postcode":"K6V 5T2",
    "sg:province":"ON",
    "sg:tags":[
        "woodworker"
    ],
    "wof:name":"Custom Trim & Millwork",
    "wof:placetype":"venue"
},
  "geometry": {"coordinates":[-75.68301391599999,44.5903892517],"type":"Point"}
}