{
  "type": "Feature",
  "properties": {
    "addr:full":"10435 10A Ave NW Edmonton AB T6J 6G4",
    "addr:housenumber":"10435",
    "addr:postcode":"t6j 6g4",
    "addr:street":"10A Ave Nw",
    "iso:country":"CA",
    "sg:address":"10435 10A Ave NW",
    "sg:city":"Edmonton",
    "sg:classifiers":[
        {
            "category":"Home & Garden",
            "subcategory":"Building Materials",
            "type":"Retail Goods"
        }
    ],
    "sg:phone":"+1 780 420 0900",
    "sg:postcode":"T6J 6G4",
    "sg:province":"AB",
    "sg:tags":[
        "energy",
        "conservation",
        "prod"
    ],
    "wof:name":"Eco Systems Inc",
    "wof:placetype":"venue"
},
  "geometry": {"coordinates":[-113.495193,53.441277],"type":"Point"}
}