{
  "type": "Feature",
  "properties": {
    "iso:country":"CA",
    "sg:address":"6669 Boul Pontbriand",
    "sg:city":"Rawdon",
    "sg:classifiers":[
        {
            "category":"Recreation",
            "type":"Entertainment"
        }
    ],
    "sg:phone":"+1 450 834 4149",
    "sg:postcode":"J0K 1S0",
    "sg:province":"QC",
    "sg:tags":[
        "provincial",
        "parks",
        "government"
    ],
    "wof:name":"Rawdon Parc Des Cascades",
    "wof:placetype":"venue"
},
  "geometry": {"coordinates":[-73.8162155151,46.053276062],"type":"Point"}
}