{
  "type": "Feature",
  "properties": {
    "addr:full":"1149 Rue Dufault Laval QC H7E 4S7",
    "addr:housenumber":"1149",
    "addr:postcode":"h7e 4s7",
    "addr:street":"Rue Dufault",
    "iso:country":"CA",
    "sg:address":"1149 Rue Dufault",
    "sg:city":"Laval",
    "sg:classifiers":[
        {
            "category":"Manufacturing",
            "subcategory":"Lumber",
            "type":"Manufacturing & Wholesale Goods"
        }
    ],
    "sg:phone":"+1 450 661 8419",
    "sg:postcode":"H7E 4S7",
    "sg:province":"QC",
    "sg:tags":[
        "consultant",
        "instructional"
    ],
    "wof:name":"Centre Nord-Americain DE",
    "wof:placetype":"venue"
},
  "geometry": {"coordinates":[-73.66746500000001,45.604893],"type":"Point"}
}