{
  "type": "Feature",
  "properties": {
    "addr:full":"190 Rue Montcalm Joliette QC J6E 5G4",
    "addr:housenumber":"190",
    "addr:postcode":"j6e 5g4",
    "addr:street":"Rue Montcalm",
    "iso:country":"CA",
    "sg:address":"190 Rue Montcalm",
    "sg:city":"Joliette",
    "sg:classifiers":[
        {
            "category":"Organizations",
            "subcategory":"Labor Organization",
            "type":"Services"
        }
    ],
    "sg:phone":"+1 450 759 1316",
    "sg:postcode":"J6E 5G4",
    "sg:province":"QC",
    "wof:name":"Csn Construction",
    "wof:placetype":"venue"
},
  "geometry": {"coordinates":[-73.436798,46.022335],"type":"Point"}
}