{
  "type": "Feature",
  "properties": {
    "addr:full":"5121 26 St Vernon BC V1T 8G4",
    "addr:housenumber":"5121",
    "addr:postcode":"v1t 8g4",
    "addr:street":"26 St",
    "iso:country":"CA",
    "sg:address":"5121 26 St",
    "sg:city":"Vernon",
    "sg:classifiers":[
        {
            "category":"Travel",
            "subcategory":"Hotels & Motels",
            "type":"Entertainment"
        }
    ],
    "sg:phone":"+1 250 549 2224",
    "sg:postcode":"V1T 8G4",
    "sg:province":"BC",
    "wof:name":"Best Western Villager Mtr Inn",
    "wof:placetype":"venue"
},
  "geometry": {"coordinates":[-119.26636499999999,50.283661],"type":"Point"}
}