{
  "type": "Feature",
  "properties": {
    "addr:full":"1616 Dupont St Toronto ON M6P 3S7",
    "addr:housenumber":"1616",
    "addr:postcode":"m6p 3s7",
    "addr:street":"Dupont St",
    "iso:country":"CA",
    "sg:address":"1616 Dupont St",
    "sg:city":"Toronto",
    "sg:classifiers":[
        {
            "category":"Personal",
            "subcategory":"Beauty Salon",
            "type":"Services"
        }
    ],
    "sg:phone":"+1 416 762 2304",
    "sg:postcode":"M6P 3S7",
    "sg:province":"ON",
    "wof:name":"Helen's Beauty Salon",
    "wof:placetype":"venue"
},
  "geometry": {"coordinates":[-79.45491790769999,43.6651191711],"type":"Point"}
}