{
  "type": "Feature",
  "properties": {
    "addr:full":"408 Rue Dufresne Joliette QC J6E 6C5",
    "addr:housenumber":"408",
    "addr:postcode":"j6e 6c5",
    "addr:street":"Rue Dufresne",
    "iso:country":"CA",
    "sg:address":"408 Rue Dufresne",
    "sg:city":"Joliette",
    "sg:classifiers":[
        {
            "category":"Professional",
            "subcategory":"Engineering",
            "type":"Services"
        }
    ],
    "sg:phone":"+1 450 759 2409",
    "sg:postcode":"J6E 6C5",
    "sg:province":"QC",
    "sg:tags":[
        "engineer"
    ],
    "wof:name":"Ramonage Professional Enr",
    "wof:placetype":"venue"
},
  "geometry": {"coordinates":[-73.45696258540001,46.0228652954],"type":"Point"}
}