{
  "type": "Feature",
  "properties": {
    "iso:country":"CA",
    "sg:city":"Saint-Jerome",
    "sg:classifiers":[
        {
            "category":"Health Services",
            "subcategory":"Doctor",
            "type":"Services"
        }
    ],
    "sg:phone":"+1 450 602 8868",
    "sg:postcode":"J7Z 3B8",
    "sg:province":"QC",
    "sg:tags":[
        "physician",
        "surgeon"
    ],
    "wof:name":"Forest, Nathalie DO",
    "wof:placetype":"venue"
},
  "geometry": {"coordinates":[-73.989265,45.761112],"type":"Point"}
}