{
  "type": "Feature",
  "properties": {
    "addr:full":"2720 College Ave # 103 Regina SK S4T 1T9",
    "addr:housenumber":"2720",
    "addr:postcode":"s4t 1t9",
    "addr:street":"College Ave # 103",
    "iso:country":"CA",
    "sg:address":"2720 College Ave # 103",
    "sg:city":"Regina",
    "sg:classifiers":[
        {
            "category":"Real Estate",
            "subcategory":"Real Estate Operator",
            "type":"Services"
        }
    ],
    "sg:phone":"+1 306 522 7167",
    "sg:postcode":"S4T 1T9",
    "sg:province":"SK",
    "sg:tags":[
        "apartment"
    ],
    "wof:name":"Davin Place",
    "wof:placetype":"venue"
},
  "geometry": {"coordinates":[-104.620033264,50.4409675598],"type":"Point"}
}