{
  "type": "Feature",
  "properties": {
    "addr:full":"150 Canada St Hamilton ON L8P 1P5",
    "addr:housenumber":"150",
    "addr:postcode":"l8p 1p5",
    "addr:street":"Canada St",
    "iso:country":"CA",
    "sg:address":"150 Canada St",
    "sg:city":"Hamilton",
    "sg:classifiers":[
        {
            "category":"Retail",
            "subcategory":"Repair Shop",
            "type":"Services"
        }
    ],
    "sg:phone":"+1 905 526 9133",
    "sg:postcode":"L8P 1P5",
    "sg:province":"ON",
    "sg:tags":[
        "antique",
        "restoring"
    ],
    "wof:name":"Klotz Antique Restoration",
    "wof:placetype":"venue"
},
  "geometry": {"coordinates":[-79.8861236572,43.2577934265],"type":"Point"}
}