{
  "type": "Feature",
  "properties": {
    "addr:full":"Edmonton AB T6B 3A1",
    "addr:postcode":"t6b 3a1",
    "iso:country":"CA",
    "sg:city":"Edmonton",
    "sg:classifiers":[
        {
            "category":"Manufacturing",
            "subcategory":"Printing",
            "type":"Manufacturing & Wholesale Goods"
        }
    ],
    "sg:phone":"+1 780 468 0100",
    "sg:postcode":"T6B 3A1",
    "sg:province":"AB",
    "sg:tags":[
        "newspaper"
    ],
    "wof:name":"Edmonton Sun",
    "wof:placetype":"venue"
},
  "geometry": {"coordinates":[-113.417519,53.526882],"type":"Point"}
}