{
  "type": "Feature",
  "properties": {
    "addr:full":"1330 Rue Bersimis Chicoutimi QC G7K 1A5",
    "addr:housenumber":"1330",
    "addr:postcode":"g7k 1a5",
    "addr:street":"Rue Bersimis",
    "iso:country":"CA",
    "sg:address":"1330 Rue Bersimis",
    "sg:city":"Chicoutimi",
    "sg:classifiers":[
        {
            "category":"Travel",
            "subcategory":"Travel Agent",
            "type":"Entertainment"
        }
    ],
    "sg:phone":"+1 418 545 3683",
    "sg:postcode":"G7K 1A5",
    "sg:province":"QC",
    "sg:tags":[
        "bus",
        "transit",
        "agency",
        "line"
    ],
    "wof:name":"Corporation Intermunicipale",
    "wof:placetype":"venue"
},
  "geometry": {"coordinates":[-71.11328899999999,48.395962],"type":"Point"}
}