{
  "type": "Feature",
  "properties": {
    "addr:full":"1195 Cote DE Terrebonne Terrebonne QC J6Y 1G5",
    "addr:housenumber":"1195",
    "addr:postcode":"j6y 1g5",
    "addr:street":"Cote De Terrebonne",
    "iso:country":"CA",
    "sg:address":"1195 Cote DE Terrebonne",
    "sg:city":"Terrebonne",
    "sg:classifiers":[
        {
            "category":"Building & Trades",
            "subcategory":"Construction",
            "type":"Services"
        }
    ],
    "sg:phone":"+1 450 492 5547",
    "sg:postcode":"J6Y 1G5",
    "sg:province":"QC",
    "sg:tags":[
        "glass",
        "glazier"
    ],
    "wof:name":"Vitrerie Action Enr",
    "wof:placetype":"venue"
},
  "geometry": {"coordinates":[-73.72411346440001,45.6845779419],"type":"Point"}
}