{
  "type": "Feature",
  "properties": {
    "addr:full":"Vaudreuil-Dorion QC J7V 8P2",
    "addr:postcode":"j7v 8p2",
    "iso:country":"CA",
    "sg:city":"Vaudreuil-Dorion",
    "sg:classifiers":[
        {
            "category":"Shopping",
            "subcategory":"Clothing, Apparel, & Fashions",
            "type":"Retail Goods"
        }
    ],
    "sg:phone":"+1 450 455 3552",
    "sg:postcode":"J7V 8P2",
    "sg:province":"QC",
    "wof:name":"Escada Fashion Outlet",
    "wof:placetype":"venue"
},
  "geometry": {"coordinates":[-74.1101989746,45.4290313721],"type":"Point"}
}