{
  "type": "Feature",
  "properties": {
    "iso:country":"CA",
    "sg:address":"1604 Cedar Rd",
    "sg:city":"Nanaimo",
    "sg:classifiers":[
        {
            "category":"Travel",
            "subcategory":"Hotels & Motels",
            "type":"Entertainment"
        }
    ],
    "sg:phone":"+1 250 722 3112",
    "sg:postcode":"V9X 1L2",
    "sg:province":"BC",
    "wof:name":"Cranberry Arms Ventures Ltd",
    "wof:placetype":"venue"
},
  "geometry": {"coordinates":[-123.878730774,49.1153411865],"type":"Point"}
}