{
  "type": "Feature",
  "properties": {
    "iso:country":"CA",
    "sg:address":"3086 Pembina Hwy",
    "sg:city":"Winnipeg",
    "sg:classifiers":[
        {
            "category":"Food & Beverages",
            "subcategory":"Groceries & Convenience Stores",
            "type":"Retail Goods"
        }
    ],
    "sg:phone":"+1 204 269 5309",
    "sg:postcode":"R3T 2J2",
    "sg:province":"MB",
    "wof:name":"Shell Food Store",
    "wof:placetype":"venue"
},
  "geometry": {"coordinates":[-97.1565704346,49.7815589905],"type":"Point"}
}