{
  "type": "Feature",
  "properties": {
    "iso:country":"CA",
    "sg:address":"89 Kirkpatrick St",
    "sg:city":"Kingston",
    "sg:classifiers":[
        {
            "category":"Organizations",
            "subcategory":"Religious Organization",
            "type":"Services"
        }
    ],
    "sg:phone":"+1 613 548 3914",
    "sg:postcode":"K7K 7G4",
    "sg:province":"ON",
    "sg:tags":[
        "church"
    ],
    "wof:name":"Church of the Redeemer Hall",
    "wof:placetype":"venue"
},
  "geometry": {"coordinates":[-76.49872589109999,44.2534866333],"type":"Point"}
}