{
  "type": "Feature",
  "properties": {
    "addr:full":"975 Wallace Ave N Listowel ON N4W 1M6",
    "addr:housenumber":"975",
    "addr:postcode":"n4w 1m6",
    "addr:street":"Wallace Ave N",
    "iso:country":"CA",
    "sg:address":"975 Wallace Ave N",
    "sg:city":"Listowel",
    "sg:classifiers":[
        {
            "category":"Food & Beverages",
            "subcategory":"Groceries & Convenience Stores",
            "type":"Retail Goods"
        }
    ],
    "sg:phone":"+1 519 291 3330",
    "sg:postcode":"N4W 1M6",
    "sg:province":"ON",
    "sg:tags":[
        "grocer"
    ],
    "wof:name":"M & M Meat Shops",
    "wof:placetype":"venue"
},
  "geometry": {"coordinates":[-80.9460678101,43.7407989502],"type":"Point"}
}