{
  "type": "Feature",
  "properties": {
    "addr:full":"Inuvik NT X0E 0T0",
    "addr:postcode":"x0e 0t0",
    "iso:country":"CA",
    "sg:city":"Inuvik",
    "sg:classifiers":[
        {
            "category":"Education",
            "subcategory":"College",
            "type":"Public Place"
        }
    ],
    "sg:phone":"+1 867 777 5879",
    "sg:postcode":"X0E 0T0",
    "sg:province":"NT",
    "sg:tags":[
        "academic",
        "school"
    ],
    "wof:name":"University of Alaska",
    "wof:placetype":"venue"
},
  "geometry": {"coordinates":[-133.734939575,68.3610534668],"type":"Point"}
}