{
  "type": "Feature",
  "properties": {
    "addr:full":"1565 St Georges St Orleans ON K1E 1R2",
    "addr:housenumber":"1565",
    "addr:postcode":"k1e 1r2",
    "addr:street":"St Georges St",
    "iso:country":"CA",
    "sg:address":"1565 St Georges St",
    "sg:city":"Orleans",
    "sg:classifiers":[
        {
            "category":"Education",
            "subcategory":"School",
            "type":"Public Place"
        }
    ],
    "sg:phone":"+1 613 824 9700",
    "sg:postcode":"K1E 1R2",
    "sg:province":"ON",
    "wof:name":"Our Lady of Wisdom Catholic",
    "wof:placetype":"venue"
},
  "geometry": {"coordinates":[-75.50193023680001,45.4675369263],"type":"Point"}
}