{
  "type": "Feature",
  "properties": {
    "addr:full":"4 Rue Charlevoix Saint-Charles-Borromee QC J6E 7Y8",
    "addr:housenumber":"4",
    "addr:postcode":"j6e 7y8",
    "addr:street":"Rue Charlevoix Saint-Charles-Borromee",
    "iso:country":"CA",
    "sg:address":"4 Rue Charlevoix",
    "sg:city":"Saint-Charles-Borromee",
    "sg:classifiers":[
        {
            "category":"Wholesale",
            "subcategory":"Electrical",
            "type":"Manufacturing & Wholesale Goods"
        }
    ],
    "sg:phone":"+1 450 752 8833",
    "sg:postcode":"J6E 7Y8",
    "sg:province":"QC",
    "sg:tags":[
        "operated",
        "equipment",
        "telephone",
        "card",
        "supply"
    ],
    "wof:name":"Afx Communications",
    "wof:placetype":"venue"
},
  "geometry": {"coordinates":[-73.4857330322,46.0655326843],"type":"Point"}
}