{
  "type": "Feature",
  "properties": {
    "iso:country":"CA",
    "sg:address":"12210 Boul DE Pierrefonds # 100",
    "sg:city":"Pierrefonds",
    "sg:classifiers":[
        {
            "category":"Real Estate",
            "subcategory":"Real Estate Operator",
            "type":"Services"
        }
    ],
    "sg:phone":"+1 514 683 4372",
    "sg:postcode":"H9A 2X6",
    "sg:province":"QC",
    "sg:tags":[
        "apartment"
    ],
    "wof:name":"Crestview Garden",
    "wof:placetype":"venue"
},
  "geometry": {"coordinates":[-73.826088,45.504257],"type":"Point"}
}