{
  "type": "Feature",
  "properties": {
    "addr:full":"2180 Av DE LA Rotonde Charny QC G6X 2L8",
    "addr:housenumber":"2180",
    "addr:postcode":"g6x 2l8",
    "addr:street":"Av De La Rotonde",
    "iso:country":"CA",
    "sg:address":"2180 Av DE LA Rotonde",
    "sg:city":"Charny",
    "sg:classifiers":[
        {
            "category":"Building & Trades",
            "subcategory":"Construction",
            "type":"Services"
        }
    ],
    "sg:phone":"+1 418 832 7632",
    "sg:postcode":"G6X 2L8",
    "sg:province":"QC",
    "sg:tags":[
        "downspouts",
        "fabricator",
        "gutter",
        "aluminum"
    ],
    "wof:name":"Alu-Rex Inc",
    "wof:placetype":"venue"
},
  "geometry": {"coordinates":[-71.269119,46.706932],"type":"Point"}
}