{
  "type": "Feature",
  "properties": {
    "addr:full":"Richmond BC V6V 2X8",
    "addr:postcode":"v6v 2x8",
    "iso:country":"CA",
    "sg:city":"Richmond",
    "sg:classifiers":[
        {
            "category":"Professional",
            "subcategory":"Engineering",
            "type":"Services"
        }
    ],
    "sg:phone":"+1 604 214 9248",
    "sg:postcode":"V6V 2X8",
    "sg:province":"BC",
    "sg:tags":[
        "engineer"
    ],
    "wof:name":"Universal Dynamics Ltd",
    "wof:placetype":"venue"
},
  "geometry": {"coordinates":[-123.071502685,49.1735343933],"type":"Point"}
}