{
  "type": "Feature",
  "properties": {
    "addr:full":"11211 142 St NW Edmonton AB T5M 4A1",
    "addr:housenumber":"11211",
    "addr:postcode":"t5m 4a1",
    "addr:street":"142 St Nw",
    "iso:country":"CA",
    "sg:address":"11211 142 St NW",
    "sg:city":"Edmonton",
    "sg:classifiers":[
        {
            "category":"Cinema",
            "subcategory":"Movie Theater",
            "type":"Entertainment"
        }
    ],
    "sg:phone":"+1 780 451 3344",
    "sg:postcode":"T5M 4A1",
    "sg:province":"AB",
    "wof:name":"Imax Theatre",
    "wof:placetype":"venue"
},
  "geometry": {"coordinates":[-113.56556701700001,53.5608291626],"type":"Point"}
}