{
  "type": "Feature",
  "properties": {
    "iso:country":"CA",
    "sg:city":"Kamloops",
    "sg:classifiers":[
        {
            "category":"Insurance",
            "subcategory":"Insurance Agent",
            "type":"Services"
        }
    ],
    "sg:phone":"+1 250 314 6217",
    "sg:postcode":"V2C 2E5",
    "sg:province":"BC",
    "wof:name":"Barton Black & Robertson Ins",
    "wof:placetype":"venue"
},
  "geometry": {"coordinates":[-120.336280823,50.6750831604],"type":"Point"}
}