{
  "type": "Feature",
  "properties": {
    "addr:full":"7042 Airport Rd Mississauga ON L4T 2G8",
    "addr:housenumber":"7042",
    "addr:postcode":"l4t 2g8",
    "addr:street":"Airport Rd",
    "iso:country":"CA",
    "sg:address":"7042 Airport Rd",
    "sg:city":"Mississauga",
    "sg:classifiers":[
        {
            "category":"Personal",
            "subcategory":"Hair Removal",
            "type":"Services"
        }
    ],
    "sg:phone":"+1 905 677 8886",
    "sg:postcode":"L4T 2G8",
    "sg:province":"ON",
    "sg:tags":[
        "removing",
        "salon",
        "beauty"
    ],
    "wof:name":"Maqi's Beauty & Skin Care Ctr",
    "wof:placetype":"venue"
},
  "geometry": {"coordinates":[-79.643272,43.704136],"type":"Point"}
}