{
  "type": "Feature",
  "properties": {
    "addr:full":"North York ON M3N 2V6",
    "addr:postcode":"m3n 2v6",
    "iso:country":"CA",
    "sg:city":"North York",
    "sg:classifiers":[
        {
            "category":"Shopping",
            "type":"Retail Goods"
        }
    ],
    "sg:phone":"+1 416 410 0440",
    "sg:postcode":"M3N 2V6",
    "sg:province":"ON",
    "sg:tags":[
        "hearing",
        "equipment",
        "supply",
        "impaired"
    ],
    "wof:name":"Sheridan Hearing Svc",
    "wof:placetype":"venue"
},
  "geometry": {"coordinates":[-79.525398,43.755466],"type":"Point"}
}