{
  "type": "Feature",
  "properties": {
    "addr:full":"Courtenay BC V9N 3P1",
    "addr:postcode":"v9n 3p1",
    "iso:country":"CA",
    "sg:city":"Courtenay",
    "sg:classifiers":[
        {
            "category":"Health Services",
            "subcategory":"Health Practitioner",
            "type":"Services"
        }
    ],
    "sg:phone":"+1 250 334 0655",
    "sg:postcode":"V9N 3P1",
    "sg:province":"BC",
    "sg:tags":[
        "physician"
    ],
    "wof:name":"Braidwood Naturopathic Clinic",
    "wof:placetype":"venue"
},
  "geometry": {"coordinates":[-124.99115,49.699512],"type":"Point"}
}