{
  "type": "Feature",
  "properties": {
    "addr:full":"645 Gardiners Rd Kingston ON K7M 8K2",
    "addr:housenumber":"645",
    "addr:postcode":"k7m 8k2",
    "addr:street":"Gardiners Rd",
    "iso:country":"CA",
    "sg:address":"645 Gardiners Rd",
    "sg:city":"Kingston",
    "sg:classifiers":[
        {
            "category":"Home & Garden",
            "subcategory":"Home Furnishings",
            "type":"Retail Goods"
        }
    ],
    "sg:phone":"+1 613 389 2223",
    "sg:postcode":"K7M 8K2",
    "sg:province":"ON",
    "sg:tags":[
        "shop",
        "fabric",
        "quilting"
    ],
    "wof:name":"Perfect Stitch Workshop",
    "wof:placetype":"venue"
},
  "geometry": {"coordinates":[-76.568085,44.24408],"type":"Point"}
}