{
  "type": "Feature",
  "properties": {
    "iso:country":"CA",
    "sg:address":"16895 Boul Hymus",
    "sg:city":"Kirkland",
    "sg:classifiers":[
        {
            "category":"Manufacturing",
            "subcategory":"Lumber",
            "type":"Manufacturing & Wholesale Goods"
        }
    ],
    "sg:phone":"+1 514 630 9663",
    "sg:postcode":"H9H 3L4",
    "sg:province":"QC",
    "sg:tags":[
        "equipment",
        "material",
        "stair",
        "floor"
    ],
    "wof:name":"Bois Franc Steve Lavallee Inc",
    "wof:placetype":"venue"
},
  "geometry": {"coordinates":[-73.85368347169999,45.4501724243],"type":"Point"}
}