{
  "type": "Feature",
  "properties": {
    "iso:country":"CA",
    "sg:address":"6 Ivanhoe Rd",
    "sg:city":"Brantford",
    "sg:classifiers":[
        {
            "category":"Building & Trades",
            "subcategory":"Electrical",
            "type":"Services"
        }
    ],
    "sg:phone":"+1 519 759 4026",
    "sg:postcode":"N3R 5T8",
    "sg:province":"ON",
    "sg:tags":[
        "electric",
        "contractor"
    ],
    "wof:name":"Merrill Electric Inc",
    "wof:placetype":"venue"
},
  "geometry": {"coordinates":[-80.264877,43.184128],"type":"Point"}
}