{
  "type": "Feature",
  "properties": {
    "addr:full":"Thunder Bay ON P7B 6M9",
    "addr:postcode":"p7b 6m9",
    "iso:country":"CA",
    "sg:city":"Thunder Bay",
    "sg:classifiers":[
        {
            "category":"Banks & Credit Unions",
            "subcategory":"Bank",
            "type":"Services"
        }
    ],
    "sg:phone":"+1 807 346 1780",
    "sg:postcode":"P7B 6M9",
    "sg:province":"ON",
    "wof:name":"Business Development Bank",
    "wof:placetype":"venue"
},
  "geometry": {"coordinates":[-89.258675,48.408886],"type":"Point"}
}