{
  "type": "Feature",
  "properties": {
    "addr:full":"383 Main St Selkirk MB R1A 1T7",
    "addr:housenumber":"383",
    "addr:postcode":"r1a 1t7",
    "addr:street":"Main St",
    "iso:country":"CA",
    "sg:address":"383 Main St",
    "sg:city":"Selkirk",
    "sg:classifiers":[
        {
            "category":"Restaurant",
            "type":"Food & Drink"
        }
    ],
    "sg:phone":"+1 204 482 3838",
    "sg:postcode":"R1A 1T7",
    "sg:province":"MB",
    "wof:name":"Ocean Palace",
    "wof:placetype":"venue"
},
  "geometry": {"coordinates":[-96.87414550779999,50.1443748474],"type":"Point"}
}