{
  "type": "Feature",
  "properties": {
    "iso:country":"CA",
    "sg:address":"330 Av Ranger",
    "sg:city":"Vaudreuil-Dorion",
    "sg:classifiers":[
        {
            "category":"Shopping",
            "subcategory":"Clothing, Apparel, & Fashions",
            "type":"Retail Goods"
        }
    ],
    "sg:phone":"+1 450 455 9339",
    "sg:postcode":"J7V 2X2",
    "sg:province":"QC",
    "sg:tags":[
        "fur",
        "business"
    ],
    "wof:name":"Emile Sarrazin Inc",
    "wof:placetype":"venue"
},
  "geometry": {"coordinates":[-74.016373,45.378567],"type":"Point"}
}