{
  "type": "Feature",
  "properties": {
    "iso:country":"CA",
    "sg:address":"848 18th St",
    "sg:city":"Brandon",
    "sg:classifiers":[
        {
            "category":"Retail",
            "subcategory":"Photofinishing",
            "type":"Services"
        }
    ],
    "sg:phone":"+1 204 727 3263",
    "sg:postcode":"R7A 5B7",
    "sg:province":"MB",
    "sg:tags":[
        "photographer",
        "photo"
    ],
    "wof:name":"Brandon Photographics",
    "wof:placetype":"venue"
},
  "geometry": {"coordinates":[-99.9622039795,49.8369789124],"type":"Point"}
}