{
  "type": "Feature",
  "properties": {
    "addr:full":"Sault Ste Marie ON P6A 3C7",
    "addr:postcode":"p6a 3c7",
    "iso:country":"CA",
    "sg:city":"Sault Ste Marie",
    "sg:classifiers":[
        {
            "category":"Real Estate",
            "subcategory":"Architect",
            "type":"Services"
        }
    ],
    "sg:phone":"+1 705 942 9494",
    "sg:postcode":"P6A 3C7",
    "sg:province":"ON",
    "wof:name":"Mgp Architects",
    "wof:placetype":"venue"
},
  "geometry": {"coordinates":[-84.327583,46.508125],"type":"Point"}
}