{
  "type": "Feature",
  "properties": {
    "addr:full":"100 Martin St Penticton BC V2A 5K1",
    "addr:housenumber":"100",
    "addr:postcode":"v2a 5k1",
    "addr:street":"Martin St",
    "iso:country":"CA",
    "sg:address":"100 Martin St",
    "sg:city":"Penticton",
    "sg:classifiers":[
        {
            "category":"Retail",
            "subcategory":"Laundry & Dry Cleaning",
            "type":"Services"
        }
    ],
    "sg:phone":"+1 250 492 4341",
    "sg:postcode":"V2A 5K1",
    "sg:province":"BC",
    "sg:tags":[
        "linen",
        "supply",
        "cleaners"
    ],
    "wof:name":"Star Cleaners",
    "wof:placetype":"venue"
},
  "geometry": {"coordinates":[-119.594764709,49.501209259],"type":"Point"}
}