{
  "type": "Feature",
  "properties": {
    "iso:country":"CA",
    "sg:address":"33 Rue Bridge",
    "sg:city":"Ormstown",
    "sg:classifiers":[
        {
            "category":"Bars & Pubs",
            "type":"Food & Drink"
        }
    ],
    "sg:phone":"+1 450 829 9805",
    "sg:postcode":"J0S 1K0",
    "sg:province":"QC",
    "sg:tags":[
        "lounge",
        "cocktail"
    ],
    "wof:name":"Bar Au Vieux Moulin",
    "wof:placetype":"venue"
},
  "geometry": {"coordinates":[-73.9921722412,45.1235466003],"type":"Point"}
}