{
  "type": "Feature",
  "properties": {
    "iso:country":"CA",
    "sg:city":"North York",
    "sg:classifiers":[
        {
            "category":"Health Services",
            "subcategory":"Doctor",
            "type":"Services"
        }
    ],
    "sg:phone":"+1 416 226 4030",
    "sg:postcode":"M2K 2W1",
    "sg:province":"ON",
    "sg:tags":[
        "dentist"
    ],
    "wof:name":"Tocchio, Claudio DDS",
    "wof:placetype":"venue"
},
  "geometry": {"coordinates":[-79.36869812010001,43.7710990906],"type":"Point"}
}