{
  "type": "Feature",
  "properties": {
    "iso:country":"CA",
    "sg:address":"2820 Av Du Port",
    "sg:city":"LA Baie",
    "sg:classifiers":[
        {
            "category":"Food & Beverages",
            "subcategory":"Groceries & Convenience Stores",
            "type":"Retail Goods"
        }
    ],
    "sg:phone":"+1 418 544 3612",
    "sg:postcode":"G7B 1W4",
    "sg:province":"QC",
    "wof:name":"Depanneur Andre Potvin",
    "wof:placetype":"venue"
},
  "geometry": {"coordinates":[-70.89875,48.330368],"type":"Point"}
}