{
  "type": "Feature",
  "properties": {
    "addr:full":"7 Inglewood Dr # A St Albert AB T8N 5E2",
    "addr:housenumber":"7",
    "addr:postcode":"t8n 5e2",
    "addr:street":"Inglewood Dr # A St",
    "iso:country":"CA",
    "sg:address":"7 Inglewood Dr # A",
    "sg:city":"St Albert",
    "sg:classifiers":[
        {
            "category":"Home & Garden",
            "subcategory":"Household Appliances",
            "type":"Retail Goods"
        }
    ],
    "sg:phone":"+1 780 459 4702",
    "sg:postcode":"T8N 5E2",
    "sg:province":"AB",
    "wof:name":"Sears Canada Inc",
    "wof:placetype":"venue"
},
  "geometry": {"coordinates":[-113.62346599999999,53.646999],"type":"Point"}
}