{
  "type": "Feature",
  "properties": {
    "addr:full":"730 Yonge St # 226 Toronto ON M4Y 2B7",
    "addr:housenumber":"730",
    "addr:postcode":"m4y 2b7",
    "addr:street":"Yonge St # 226",
    "iso:country":"CA",
    "sg:address":"730 Yonge St # 226",
    "sg:city":"Toronto",
    "sg:classifiers":[
        {
            "category":"Health Services",
            "subcategory":"Health Practitioner",
            "type":"Services"
        }
    ],
    "sg:phone":"+1 416 961 0487",
    "sg:postcode":"M4Y 2B7",
    "sg:province":"ON",
    "sg:tags":[
        "psychologist"
    ],
    "wof:name":"Hays, Kate PhD",
    "wof:placetype":"venue"
},
  "geometry": {"coordinates":[-79.3862457275,43.6687927246],"type":"Point"}
}