{
  "type": "Feature",
  "properties": {
    "iso:country":"CA",
    "sg:city":"Etobicoke",
    "sg:classifiers":[
        {
            "category":"Wholesale",
            "subcategory":"Meat",
            "type":"Manufacturing & Wholesale Goods"
        }
    ],
    "sg:phone":"+1 416 742 6333",
    "sg:postcode":"M9V 5G6",
    "sg:province":"ON",
    "sg:tags":[
        "butchering"
    ],
    "wof:name":"Rowntree Meats Ltd",
    "wof:placetype":"venue"
},
  "geometry": {"coordinates":[-79.585327,43.750484],"type":"Point"}
}