{
  "type": "Feature",
  "properties": {
    "addr:full":"Etobicoke ON M9V 5G6",
    "addr:postcode":"m9v 5g6",
    "iso:country":"CA",
    "sg:city":"Etobicoke",
    "sg:classifiers":[
        {
            "category":"Wholesale",
            "subcategory":"Meat",
            "type":"Manufacturing & Wholesale Goods"
        }
    ],
    "sg:phone":"+1 416 742 6333",
    "sg:postcode":"M9V 5G6",
    "sg:province":"ON",
    "sg:tags":[
        "butchering"
    ],
    "wof:name":"Rowntree Meats Ltd",
    "wof:placetype":"venue"
},
  "geometry": {"coordinates":[-79.58532700000001,43.750484],"type":"Point"}
}