{
  "type": "Feature",
  "properties": {
    "addr:full":"20 Smith St Petitcodiac NB E4Z 4W1",
    "addr:housenumber":"20",
    "addr:postcode":"e4z 4w1",
    "addr:street":"Smith St",
    "iso:country":"CA",
    "sg:address":"20 Smith St",
    "sg:city":"Petitcodiac",
    "sg:classifiers":[
        {
            "category":"Freight",
            "type":"Transportation"
        }
    ],
    "sg:phone":"+1 506 756 2250",
    "sg:postcode":"E4Z 4W1",
    "sg:province":"NB",
    "sg:tags":[
        "trucking"
    ],
    "wof:name":"Burgess Contracting Ltd",
    "wof:placetype":"venue"
},
  "geometry": {"coordinates":[-65.1700210571,45.9318656921],"type":"Point"}
}