{
  "type": "Feature",
  "properties": {
    "iso:country":"CA",
    "sg:address":"6144 Old Summit Lake Rd",
    "sg:city":"Prince George",
    "sg:classifiers":[
        {
            "category":"Education",
            "subcategory":"School",
            "type":"Public Place"
        }
    ],
    "sg:phone":"+1 250 962 9249",
    "sg:postcode":"V2K 5R2",
    "sg:province":"BC",
    "wof:name":"Shady Valley Elementary School",
    "wof:placetype":"venue"
},
  "geometry": {"coordinates":[-122.725769043,53.9884643555],"type":"Point"}
}