{
  "type": "Feature",
  "properties": {
    "addr:full":"583 Alfred St Kingston ON K7K 4J6",
    "addr:housenumber":"583",
    "addr:postcode":"k7k 4j6",
    "addr:street":"Alfred St",
    "iso:country":"CA",
    "sg:address":"583 Alfred St",
    "sg:city":"Kingston",
    "sg:classifiers":[
        {
            "category":"Food & Beverages",
            "subcategory":"Groceries & Convenience Stores",
            "type":"Retail Goods"
        }
    ],
    "sg:phone":"+1 613 542 4171",
    "sg:postcode":"K7K 4J6",
    "sg:province":"ON",
    "sg:tags":[
        "grocer"
    ],
    "wof:name":"Medeiros Imported Foods",
    "wof:placetype":"venue"
},
  "geometry": {"coordinates":[-76.4980773926,44.2433166504],"type":"Point"}
}