{
  "type": "Feature",
  "properties": {
    "addr:full":"Kelowna BC V1Y 8B3",
    "addr:postcode":"v1y 8b3",
    "iso:country":"CA",
    "sg:city":"Kelowna",
    "sg:classifiers":[
        {
            "category":"Real Estate",
            "subcategory":"Real Estate Operator",
            "type":"Services"
        }
    ],
    "sg:phone":"+1 250 860 3112",
    "sg:postcode":"V1Y 8B3",
    "sg:province":"BC",
    "sg:tags":[
        "apartment"
    ],
    "wof:name":"Okanagan Place II",
    "wof:placetype":"venue"
},
  "geometry": {"coordinates":[-119.47148132300001,49.8793067932],"type":"Point"}
}