{
  "type": "Feature",
  "properties": {
    "addr:full":"309 St. Patrick St Bathurst NB E2A 1E2",
    "addr:housenumber":"309",
    "addr:postcode":"e2a 1e2",
    "addr:street":"St. Patrick St",
    "iso:country":"CA",
    "sg:address":"309 St. Patrick St",
    "sg:city":"Bathurst",
    "sg:classifiers":[
        {
            "category":"Education",
            "subcategory":"College",
            "type":"Public Place"
        }
    ],
    "sg:phone":"+1 506 548 3503",
    "sg:postcode":"E2A 1E2",
    "sg:province":"NB",
    "sg:tags":[
        "academic",
        "school"
    ],
    "wof:name":"Bathurst Adult Learning Ctr",
    "wof:placetype":"venue"
},
  "geometry": {"coordinates":[-65.64859771730001,47.6176567078],"type":"Point"}
}