{
  "type": "Feature",
  "properties": {
    "addr:full":"112 Snidercroft Rd Concord ON L4K 2K1",
    "addr:housenumber":"112",
    "addr:postcode":"l4k 2k1",
    "addr:street":"Snidercroft Rd",
    "iso:country":"CA",
    "sg:address":"112 Snidercroft Rd",
    "sg:city":"Concord",
    "sg:classifiers":[
        {
            "category":"Manufacturing",
            "subcategory":"Chemicals & Compounds",
            "type":"Manufacturing & Wholesale Goods"
        }
    ],
    "sg:phone":"+1 905 738 2220",
    "sg:postcode":"L4K 2K1",
    "sg:province":"ON",
    "sg:tags":[
        "lithographing",
        "ink"
    ],
    "wof:name":"Ganho Inks & Chemicals Ltd",
    "wof:placetype":"venue"
},
  "geometry": {"coordinates":[-79.50016784669999,43.7886772156],"type":"Point"}
}