{
  "type": "Feature",
  "properties": {
    "addr:full":"Scarborough ON M1X 1E7",
    "addr:postcode":"m1x 1e7",
    "iso:country":"CA",
    "sg:city":"Scarborough",
    "sg:classifiers":[
        {
            "category":"Wholesale",
            "subcategory":"Photographic Equipment",
            "type":"Manufacturing & Wholesale Goods"
        }
    ],
    "sg:phone":"+1 416 299 5577",
    "sg:postcode":"M1X 1E7",
    "sg:province":"ON",
    "sg:tags":[
        "audio"
    ],
    "wof:name":"Best Video & Av",
    "wof:placetype":"venue"
},
  "geometry": {"coordinates":[-79.24387400000001,43.827248],"type":"Point"}
}