{
  "type": "Feature",
  "properties": {
    "addr:full":"Waterford ON N0E 1Y0",
    "addr:postcode":"n0e 1y0",
    "iso:country":"CA",
    "sg:city":"Waterford",
    "sg:classifiers":[
        {
            "category":"Building & Trades",
            "subcategory":"Construction",
            "type":"Services"
        }
    ],
    "sg:phone":"+1 519 443 7519",
    "sg:postcode":"N0E 1Y0",
    "sg:province":"ON",
    "sg:tags":[
        "excavating",
        "contractor",
        "drainage"
    ],
    "wof:name":"D C Steel Farm Drainage Ltd",
    "wof:placetype":"venue"
},
  "geometry": {"coordinates":[-80.288605,42.925114],"type":"Point"}
}