{
  "type": "Feature",
  "properties": {
    "iso:country":"CA",
    "sg:address":"210 Railway Ave E",
    "sg:city":"Margo",
    "sg:classifiers":[
        {
            "category":"Professional",
            "subcategory":"Accounting & Tax Preparation",
            "type":"Services"
        }
    ],
    "sg:phone":"+1 306 324 4521",
    "sg:postcode":"S0A 2M0",
    "sg:province":"SK",
    "sg:tags":[
        "bookkeeping",
        "general"
    ],
    "wof:name":"Give Yourself A Break Bkpng",
    "wof:placetype":"venue"
},
  "geometry": {"coordinates":[-103.335472107,51.8273010254],"type":"Point"}
}