{
  "type": "Feature",
  "properties": {
    "iso:country":"CA",
    "sg:city":"Dsl DE Saint-Andre",
    "sg:classifiers":[
        {
            "category":"Manufacturing",
            "subcategory":"Tools & Machinery",
            "type":"Manufacturing & Wholesale Goods"
        }
    ],
    "sg:phone":"+1 506 473 3439",
    "sg:postcode":"E3Y 3H6",
    "sg:province":"NB",
    "sg:tags":[
        "potato"
    ],
    "wof:name":"Valley Sales & Svc Ltd",
    "wof:placetype":"venue"
},
  "geometry": {"coordinates":[-67.75946044920001,47.105758667],"type":"Point"}
}