{
  "type": "Feature",
  "properties": {
    "addr:full":"1218 Ch Du Gouvernement Sainte-Julienne QC J0K 2T0",
    "addr:housenumber":"1218",
    "addr:postcode":"j0k 2t0",
    "addr:street":"Ch Du Gouvernement",
    "iso:country":"CA",
    "sg:address":"1218 Ch Du Gouvernement",
    "sg:city":"Sainte-Julienne",
    "sg:classifiers":[
        {
            "category":"Home & Garden",
            "subcategory":"Building Materials",
            "type":"Retail Goods"
        }
    ],
    "sg:phone":"+1 450 831 2823",
    "sg:postcode":"J0K 2T0",
    "sg:province":"QC",
    "sg:tags":[
        "windows",
        "door"
    ],
    "wof:name":"H Varin & Fils Inc",
    "wof:placetype":"venue"
},
  "geometry": {"coordinates":[-73.70793914790001,45.9585075378],"type":"Point"}
}