{
  "type": "Feature",
  "properties": {
    "addr:full":"1891 Av Saint-Alfred Plessisville QC G6L 2G2",
    "addr:housenumber":"1891",
    "addr:postcode":"g6l 2g2",
    "addr:street":"Av Saint-Alfred",
    "iso:country":"CA",
    "sg:address":"1891 Av Saint-Alfred",
    "sg:city":"Plessisville",
    "sg:classifiers":[
        {
            "category":"Home & Garden",
            "subcategory":"Garden Supply",
            "type":"Retail Goods"
        }
    ],
    "sg:phone":"+1 819 362 3742",
    "sg:postcode":"G6L 2G2",
    "sg:province":"QC",
    "sg:tags":[
        "nurseryman"
    ],
    "wof:name":"Pepiniere LA Samare Enr",
    "wof:placetype":"venue"
},
  "geometry": {"coordinates":[-71.78038787840001,46.2201461792],"type":"Point"}
}