{
  "type": "Feature",
  "properties": {
    "iso:country":"CA",
    "sg:address":"PO Box 10",
    "sg:city":"Trout Lake",
    "sg:classifiers":[
        {
            "category":"Government",
            "subcategory":"Office",
            "type":"Public Place"
        }
    ],
    "sg:phone":"+1 867 206 2848",
    "sg:postcode":"X0E 1Z0",
    "sg:province":"NT",
    "wof:name":"Nwt Trout Lake 2-Bay Garage",
    "wof:placetype":"venue"
},
  "geometry": {"coordinates":[-121.23843383800001,60.4382514954],"type":"Point"}
}