{
  "type": "Feature",
  "properties": {
    "addr:full":"124 Crescent St Sackville NB E4L 3V4",
    "addr:housenumber":"124",
    "addr:postcode":"e4l 3v4",
    "addr:street":"Crescent St",
    "iso:country":"CA",
    "sg:address":"124 Crescent St",
    "sg:city":"Sackville",
    "sg:classifiers":[
        {
            "category":"Autos & Motor Vehicles",
            "subcategory":"Auto Supplies",
            "type":"Retail Goods"
        }
    ],
    "sg:phone":"+1 506 536 3330",
    "sg:postcode":"E4L 3V4",
    "sg:province":"NB",
    "sg:tags":[
        "automobile",
        "parts"
    ],
    "wof:name":"Crescent Automotive & Ind",
    "wof:placetype":"venue"
},
  "geometry": {"coordinates":[-64.355316,45.889301],"type":"Point"}
}