{
  "type": "Feature",
  "properties": {
    "addr:full":"595 Rue Gilles Laval QC H7P 2V8",
    "addr:housenumber":"595",
    "addr:postcode":"h7p 2v8",
    "addr:street":"Rue Gilles",
    "iso:country":"CA",
    "sg:address":"595 Rue Gilles",
    "sg:city":"Laval",
    "sg:classifiers":[
        {
            "category":"Retail",
            "subcategory":"Auto Repair",
            "type":"Services"
        }
    ],
    "sg:phone":"+1 450 625 0449",
    "sg:postcode":"H7P 2V8",
    "sg:province":"QC",
    "sg:tags":[
        "repairing",
        "automobile"
    ],
    "wof:name":"Certigard",
    "wof:placetype":"venue"
},
  "geometry": {"coordinates":[-73.79335,45.582596],"type":"Point"}
}