{
  "type": "Feature",
  "properties": {
    "iso:country":"CA",
    "sg:address":"8188 Yonge St",
    "sg:city":"Thornhill",
    "sg:classifiers":[
        {
            "category":"Health Services",
            "subcategory":"Doctor",
            "type":"Services"
        }
    ],
    "sg:phone":"+1 905 889 2222",
    "sg:postcode":"L4J 1W5",
    "sg:province":"ON",
    "sg:tags":[
        "physician",
        "surgeon"
    ],
    "wof:name":"Magee, Gary MD",
    "wof:placetype":"venue"
},
  "geometry": {"coordinates":[-79.4271621704,43.8269119263],"type":"Point"}
}