{
  "type": "Feature",
  "properties": {
    "addr:full":"Abbotsford BC V2S 3P3",
    "addr:postcode":"v2s 3p3",
    "iso:country":"CA",
    "sg:city":"Abbotsford",
    "sg:classifiers":[
        {
            "category":"Health Services",
            "subcategory":"Doctor",
            "type":"Services"
        }
    ],
    "sg:phone":"+1 604 853 5757",
    "sg:postcode":"V2S 3P3",
    "sg:province":"BC",
    "sg:tags":[
        "dentist"
    ],
    "wof:name":"Mc Callum Place Dental Ctr",
    "wof:placetype":"venue"
},
  "geometry": {"coordinates":[-122.293335,49.041874],"type":"Point"}
}