{
  "type": "Feature",
  "properties": {
    "addr:full":"1701 Lac Labrecque Labrecque QC G0W 2S0",
    "addr:housenumber":"1701",
    "addr:postcode":"g0w 2s0",
    "addr:street":"Lac Labrecque",
    "iso:country":"CA",
    "sg:address":"1701 Lac Labrecque",
    "sg:city":"Labrecque",
    "sg:classifiers":[
        {
            "category":"Government",
            "subcategory":"Office",
            "type":"Public Place"
        }
    ],
    "sg:phone":"+1 418 481 2947",
    "sg:postcode":"G0W 2S0",
    "sg:province":"QC",
    "sg:tags":[
        "village"
    ],
    "wof:name":"Chalet Municipal DE St-Leon",
    "wof:placetype":"venue"
},
  "geometry": {"coordinates":[-71.523796,48.674847],"type":"Point"}
}