{
  "type": "Feature",
  "properties": {
    "addr:full":"Natashquan QC G0G 2E0",
    "addr:postcode":"g0g 2e0",
    "iso:country":"CA",
    "sg:city":"Natashquan",
    "sg:classifiers":[
        {
            "category":"Professional",
            "subcategory":"Computer Services",
            "type":"Services"
        }
    ],
    "sg:phone":"+1 418 726 3572",
    "sg:postcode":"G0G 2E0",
    "sg:province":"QC",
    "sg:tags":[
        "information",
        "system",
        "consultant"
    ],
    "wof:name":"Services Informatiques Jjl",
    "wof:placetype":"venue"
},
  "geometry": {"coordinates":[-61.828693,50.192654],"type":"Point"}
}