{
  "type": "Feature",
  "properties": {
    "addr:full":"303 Beaconsfield Blvd Beaconsfield QC H9W 4A7",
    "addr:housenumber":"303",
    "addr:postcode":"h9w 4a7",
    "addr:street":"Beaconsfield Blvd",
    "iso:country":"CA",
    "sg:address":"303 Beaconsfield Blvd",
    "sg:city":"Beaconsfield",
    "sg:classifiers":[
        {
            "category":"Education",
            "subcategory":"Library",
            "type":"Public Place"
        }
    ],
    "sg:phone":"+1 514 428 4470",
    "sg:postcode":"H9W 4A7",
    "sg:province":"QC",
    "sg:tags":[
        "government"
    ],
    "wof:name":"Beaconsfield Bibliotheque",
    "wof:placetype":"venue"
},
  "geometry": {"coordinates":[-73.8648681641,45.424785614],"type":"Point"}
}