{
  "type": "Feature",
  "properties": {
    "addr:full":"650 West Georgia Street, Suite 1300 650 West Georgia Street, PO Box 11582 Vancouver V6B 4N8",
    "addr:housenumber":"650;650;box",
    "addr:postcode":"11582;v6b 4n8",
    "addr:street":"West Georgia Street Suite 1300;West Georgia Street Po",
    "iso:country":"CA",
    "sg:address":"650 West Georgia Street, Suite 1300 650 West Georgia Street, PO Box 11582",
    "sg:city":"Vancouver",
    "sg:classifiers":[
        {
            "category":"Professional",
            "subcategory":"Research",
            "type":"Services"
        }
    ],
    "sg:postcode":"V6B 4N8",
    "sg:website":"http://www.nexterra.ca",
    "wof:name":"Nexterra",
    "wof:placetype":"venue"
},
  "geometry": {"coordinates":[-123.11764959999999,49.282159],"type":"Point"}
}