{
  "type": "Feature",
  "properties": {
    "iso:country":"CA",
    "sg:address":"650 Kingston Rd",
    "sg:city":"Toronto",
    "sg:classifiers":[
        {
            "category":"Retail",
            "subcategory":"Auto Repair",
            "type":"Services"
        }
    ],
    "sg:phone":"+1 416 691 6955",
    "sg:postcode":"M4E 1P9",
    "sg:province":"ON",
    "sg:tags":[
        "repairing",
        "automobile"
    ],
    "wof:name":"L & L Beckwith Garage",
    "wof:placetype":"venue"
},
  "geometry": {"coordinates":[-79.298324585,43.6789588928],"type":"Point"}
}