{
  "type": "Feature",
  "properties": {
    "addr:full":"158 Beech St Clinton ON N0M 1L0",
    "addr:housenumber":"158",
    "addr:postcode":"n0m 1l0",
    "addr:street":"Beech St",
    "iso:country":"CA",
    "sg:address":"158 Beech St",
    "sg:city":"Clinton",
    "sg:classifiers":[
        {
            "category":"Retail",
            "subcategory":"Laundry & Dry Cleaning",
            "type":"Services"
        }
    ],
    "sg:phone":"+1 519 482 7064",
    "sg:postcode":"N0M 1L0",
    "sg:province":"ON",
    "sg:tags":[
        "cleaners"
    ],
    "wof:name":"Clinton Dry Cleaners",
    "wof:placetype":"venue"
},
  "geometry": {"coordinates":[-81.536957,43.621552],"type":"Point"}
}