{
  "type": "Feature",
  "properties": {
    "addr:full":"1964 Victoria Park Ave North York ON M1R 5G7",
    "addr:housenumber":"1964",
    "addr:postcode":"m1r 5g7",
    "addr:street":"Victoria Park Ave",
    "iso:country":"CA",
    "sg:address":"1964 Victoria Park Ave",
    "sg:city":"North York",
    "sg:classifiers":[
        {
            "category":"Retail",
            "subcategory":"Auto Repair",
            "type":"Services"
        }
    ],
    "sg:phone":"+1 416 444 5766",
    "sg:postcode":"M1R 5G7",
    "sg:province":"ON",
    "sg:tags":[
        "automobile",
        "lubrication"
    ],
    "wof:name":"Mr Lube",
    "wof:placetype":"venue"
},
  "geometry": {"coordinates":[-79.312157,43.748447],"type":"Point"}
}