{
  "type": "Feature",
  "properties": {
    "addr:full":"2711 Battleford Ave SW Calgary AB T3E 7L4",
    "addr:housenumber":"2711",
    "addr:postcode":"t3e 7l4",
    "addr:street":"Battleford Ave Sw",
    "iso:country":"CA",
    "sg:address":"2711 Battleford Ave SW",
    "sg:city":"Calgary",
    "sg:classifiers":[
        {
            "category":"Communications",
            "subcategory":"Film & Video Production",
            "type":"Services"
        }
    ],
    "sg:phone":"+1 403 205 4747",
    "sg:postcode":"T3E 7L4",
    "sg:province":"AB",
    "sg:tags":[
        "motion",
        "picture",
        "studio",
        "producer"
    ],
    "wof:name":"Calgary Society-Independent",
    "wof:placetype":"venue"
},
  "geometry": {"coordinates":[-114.12358856199999,51.0172615051],"type":"Point"}
}