{
  "type": "Feature",
  "properties": {
    "addr:full":"9940 Warren Rd SE Calgary AB T2J 1G7",
    "addr:housenumber":"9940",
    "addr:postcode":"t2j 1g7",
    "addr:street":"Warren Rd Se",
    "iso:country":"CA",
    "sg:address":"9940 Warren Rd SE",
    "sg:city":"Calgary",
    "sg:classifiers":[
        {
            "category":"Building & Trades",
            "subcategory":"Electrical",
            "type":"Services"
        }
    ],
    "sg:phone":"+1 403 278 3973",
    "sg:postcode":"T2J 1G7",
    "sg:province":"AB",
    "sg:tags":[
        "electric",
        "contractor"
    ],
    "wof:name":"Har-Tech Electric",
    "wof:placetype":"venue"
},
  "geometry": {"coordinates":[-114.061172,50.963085],"type":"Point"}
}