{
  "type": "Feature",
  "properties": {
    "addr:full":"145 King St E Toronto ON M5C 2Y7",
    "addr:housenumber":"145",
    "addr:postcode":"m5c 2y7",
    "addr:street":"King St E",
    "iso:country":"CA",
    "sg:address":"145 King St E",
    "sg:city":"Toronto",
    "sg:classifiers":[
        {
            "category":"Wholesale",
            "subcategory":"Machinery & Supplies",
            "type":"Manufacturing & Wholesale Goods"
        }
    ],
    "sg:phone":"+1 416 363 5577",
    "sg:postcode":"M5C 2Y7",
    "sg:province":"ON",
    "sg:tags":[
        "environmental",
        "ecological"
    ],
    "wof:name":"Green Ware Environmental",
    "wof:placetype":"venue"
},
  "geometry": {"coordinates":[-79.37255096440001,43.6501693726],"type":"Point"}
}