{
  "type": "Feature",
  "properties": {
    "addr:full":"2721 Jane St North York ON M3L 1S3",
    "addr:housenumber":"2721",
    "addr:postcode":"m3l 1s3",
    "addr:street":"Jane St",
    "iso:country":"CA",
    "sg:address":"2721 Jane St",
    "sg:city":"North York",
    "sg:classifiers":[
        {
            "category":"Shopping",
            "subcategory":"Crafts & Fabrics",
            "type":"Retail Goods"
        }
    ],
    "sg:phone":"+1 416 741 8560",
    "sg:postcode":"M3L 1S3",
    "sg:province":"ON",
    "sg:tags":[
        "shop"
    ],
    "wof:name":"Fashion World",
    "wof:placetype":"venue"
},
  "geometry": {"coordinates":[-79.51329800000001,43.740517],"type":"Point"}
}