{
  "type": "Feature",
  "properties": {
    "addr:full":"43 Rue Lavoie Victoriaville QC G6T 1M8",
    "addr:housenumber":"43",
    "addr:postcode":"g6t 1m8",
    "addr:street":"Rue Lavoie",
    "iso:country":"CA",
    "sg:address":"43 Rue Lavoie",
    "sg:city":"Victoriaville",
    "sg:classifiers":[
        {
            "category":"Building & Trades",
            "subcategory":"Construction",
            "type":"Services"
        }
    ],
    "sg:phone":"+1 819 752 4874",
    "sg:postcode":"G6T 1M8",
    "sg:province":"QC",
    "sg:tags":[
        "masonry",
        "contractor"
    ],
    "wof:name":"Raymond Champagne Maconnerie",
    "wof:placetype":"venue"
},
  "geometry": {"coordinates":[-72.0208435059,46.0598564148],"type":"Point"}
}