{
  "type": "Feature",
  "properties": {
    "iso:country":"CA",
    "sg:city":"Port Moody",
    "sg:classifiers":[
        {
            "category":"Wholesale",
            "subcategory":"Groceries",
            "type":"Manufacturing & Wholesale Goods"
        }
    ],
    "sg:phone":"+1 604 461 7880",
    "sg:postcode":"V3H 5C8",
    "sg:province":"BC",
    "sg:tags":[
        "food",
        "product"
    ],
    "wof:name":"Daly's Food Svc",
    "wof:placetype":"venue"
},
  "geometry": {"coordinates":[-122.839737,49.27676],"type":"Point"}
}