{
  "type": "Feature",
  "properties": {
    "addr:full":"Scarborough ON M1X 1L9",
    "addr:postcode":"m1x 1l9",
    "iso:country":"CA",
    "sg:city":"Scarborough",
    "sg:classifiers":[
        {
            "category":"Shopping",
            "subcategory":"Computers & Home Electronics",
            "type":"Retail Goods"
        }
    ],
    "sg:phone":"+1 416 321 9085",
    "sg:postcode":"M1X 1L9",
    "sg:province":"ON",
    "sg:tags":[
        "equipment",
        "dealer"
    ],
    "wof:name":"Acrotech International",
    "wof:placetype":"venue"
},
  "geometry": {"coordinates":[-79.2502365112,43.8302612305],"type":"Point"}
}