{
  "type": "Feature",
  "properties": {
    "addr:full":"Saint-Jerome QC J7Z 4Z1",
    "addr:postcode":"j7z 4z1",
    "iso:country":"CA",
    "sg:city":"Saint-Jerome",
    "sg:classifiers":[
        {
            "category":"Restaurant",
            "type":"Food & Drink"
        }
    ],
    "sg:phone":"+1 450 431 1440",
    "sg:postcode":"J7Z 4Z1",
    "sg:province":"QC",
    "wof:name":"Restaurant Villa D'Estee",
    "wof:placetype":"venue"
},
  "geometry": {"coordinates":[-74.000664,45.768089],"type":"Point"}
}