{
  "type": "Feature",
  "properties": {
    "addr:full":"154 Mark St London ON N5V 2G9",
    "addr:housenumber":"154",
    "addr:postcode":"n5v 2g9",
    "addr:street":"Mark St",
    "iso:country":"CA",
    "sg:address":"154 Mark St",
    "sg:city":"London",
    "sg:classifiers":[
        {
            "category":"Organizations",
            "subcategory":"Religious Organization",
            "type":"Services"
        }
    ],
    "sg:phone":"+1 519 461 0675",
    "sg:postcode":"N5V 2G9",
    "sg:province":"ON",
    "sg:tags":[
        "church"
    ],
    "wof:name":"St George Anglican Church",
    "wof:placetype":"venue"
},
  "geometry": {"coordinates":[-81.2087020874,43.0197677612],"type":"Point"}
}