{
  "type": "Feature",
  "properties": {
    "addr:full":"9 Queen St # 200 Niagara on the Lake ON L0S 1J0",
    "addr:housenumber":"9",
    "addr:postcode":"l0s 1j0",
    "addr:street":"Queen St # 200;On",
    "iso:country":"CA",
    "sg:address":"9 Queen St # 200",
    "sg:city":"Niagara on the Lake",
    "sg:classifiers":[
        {
            "category":"Banks & Credit Unions",
            "subcategory":"Investment Brokerage",
            "type":"Services"
        }
    ],
    "sg:phone":"+1 905 468 0655",
    "sg:postcode":"L0S 1J0",
    "sg:province":"ON",
    "wof:name":"Caldwell Securities Ltd",
    "wof:placetype":"venue"
},
  "geometry": {"coordinates":[-79.071091,43.255135],"type":"Point"}
}