{
  "type": "Feature",
  "properties": {
    "addr:full":"208 Fifth Ave Ottawa ON K1S 2N2",
    "addr:housenumber":"208",
    "addr:postcode":"k1s 2n2",
    "addr:street":"Fifth Ave",
    "iso:country":"CA",
    "sg:address":"208 Fifth Ave",
    "sg:city":"Ottawa",
    "sg:classifiers":[
        {
            "category":"Professional",
            "subcategory":"Management & Consulting",
            "type":"Services"
        }
    ],
    "sg:phone":"+1 613 863 3090",
    "sg:postcode":"K1S 2N2",
    "sg:province":"ON",
    "sg:tags":[
        "marketing",
        "consultant"
    ],
    "wof:name":"Temple Marketing",
    "wof:placetype":"venue"
},
  "geometry": {"coordinates":[-75.69107099999999,45.400093],"type":"Point"}
}