{
  "type": "Feature",
  "properties": {
    "addr:full":"1155 Henderson Hwy Winnipeg MB R2G 1L5",
    "addr:housenumber":"1155",
    "addr:postcode":"r2g 1l5",
    "addr:street":"Henderson Hwy",
    "iso:country":"CA",
    "sg:address":"1155 Henderson Hwy",
    "sg:city":"Winnipeg",
    "sg:classifiers":[
        {
            "category":"Manufacturing",
            "subcategory":"Apparel",
            "type":"Manufacturing & Wholesale Goods"
        }
    ],
    "sg:phone":"+1 204 339 1943",
    "sg:postcode":"R2G 1L5",
    "sg:province":"MB",
    "sg:tags":[
        "fur",
        "business"
    ],
    "wof:name":"Chut Furs",
    "wof:placetype":"venue"
},
  "geometry": {"coordinates":[-97.091796875,49.9387054443],"type":"Point"}
}