{
  "type": "Feature",
  "properties": {
    "addr:full":"575 Rue Sacre-Coeur O Alma QC G8B 1M4",
    "addr:housenumber":"575",
    "addr:postcode":"g8b 1m4",
    "addr:street":"Rue Sacre-Coeur O",
    "iso:country":"CA",
    "sg:address":"575 Rue Sacre-Coeur O",
    "sg:city":"Alma",
    "sg:classifiers":[
        {
            "category":"Shopping",
            "subcategory":"Clothing, Apparel, & Fashions",
            "type":"Retail Goods"
        }
    ],
    "sg:phone":"+1 418 662 5949",
    "sg:postcode":"G8B 1M4",
    "sg:province":"QC",
    "wof:name":"Magasin Rex",
    "wof:placetype":"venue"
},
  "geometry": {"coordinates":[-71.63191223139999,48.5433197021],"type":"Point"}
}