{
  "type": "Feature",
  "properties": {
    "addr:full":"317 Rue Monseigneur-Nadeau Sorel-Tracy QC J3P 7C4",
    "addr:housenumber":"317",
    "addr:postcode":"j3p 7c4",
    "addr:street":"Rue Monseigneur-Nadeau",
    "iso:country":"CA",
    "sg:address":"317 Rue Monseigneur-Nadeau",
    "sg:city":"Sorel-Tracy",
    "sg:classifiers":[
        {
            "category":"Food & Beverages",
            "subcategory":"Groceries & Convenience Stores",
            "type":"Retail Goods"
        }
    ],
    "sg:phone":"+1 450 746 5627",
    "sg:postcode":"J3P 7C4",
    "sg:province":"QC",
    "wof:name":"Depanneur Rene Enr",
    "wof:placetype":"venue"
},
  "geometry": {"coordinates":[-73.1126327515,46.042388916],"type":"Point"}
}