{
  "type": "Feature",
  "properties": {
    "addr:full":"4446 Main St Baie Verte NL A0K 1B0",
    "addr:housenumber":"4446",
    "addr:postcode":"a0k 1b0",
    "addr:street":"Main St",
    "iso:country":"CA",
    "sg:address":"4446 Main St",
    "sg:city":"Baie Verte",
    "sg:classifiers":[
        {
            "category":"Food & Beverages",
            "subcategory":"Groceries & Convenience Stores",
            "type":"Retail Goods"
        }
    ],
    "sg:phone":"+1 709 532 4258",
    "sg:postcode":"A0K 1B0",
    "sg:province":"NL",
    "wof:name":"Central Convenience & Elecs",
    "wof:placetype":"venue"
},
  "geometry": {"coordinates":[-56.1923103333,49.9394645691],"type":"Point"}
}