{
  "type": "Feature",
  "properties": {
    "addr:full":"29 North Main St Deer Lake NL A8A 1W8",
    "addr:housenumber":"29",
    "addr:postcode":"a8a 1w8",
    "addr:street":"North Main St",
    "iso:country":"CA",
    "sg:address":"29 North Main St",
    "sg:city":"Deer Lake",
    "sg:classifiers":[
        {
            "category":"Personal",
            "subcategory":"Beauty Salon",
            "type":"Services"
        }
    ],
    "sg:phone":"+1 709 635 7678",
    "sg:postcode":"A8A 1W8",
    "sg:province":"NL",
    "wof:name":"Cutting Post",
    "wof:placetype":"venue"
},
  "geometry": {"coordinates":[-57.423664,49.175339],"type":"Point"}
}