{
  "type": "Feature",
  "properties": {
    "addr:full":"218 Heise Cres Saskatoon SK S7M 4Y8",
    "addr:housenumber":"218",
    "addr:postcode":"s7m 4y8",
    "addr:street":"Heise Cres",
    "iso:country":"CA",
    "sg:address":"218 Heise Cres",
    "sg:city":"Saskatoon",
    "sg:classifiers":[
        {
            "category":"Freight",
            "type":"Transportation"
        }
    ],
    "sg:phone":"+1 306 683 6402",
    "sg:postcode":"S7M 4Y8",
    "sg:province":"SK",
    "sg:tags":[
        "mobile",
        "home"
    ],
    "wof:name":"Allan Cey-Mobile Home Moving",
    "wof:placetype":"venue"
},
  "geometry": {"coordinates":[-106.744415,52.125435],"type":"Point"}
}