{
  "type": "Feature",
  "properties": {
    "addr:full":"Vancouver BC V6E 1T7",
    "addr:postcode":"v6e 1t7",
    "iso:country":"CA",
    "sg:city":"Vancouver",
    "sg:classifiers":[
        {
            "category":"Professional",
            "subcategory":"Lawyer & Legal Services",
            "type":"Services"
        }
    ],
    "sg:phone":"+1 604 685 7317",
    "sg:postcode":"V6E 1T7",
    "sg:province":"BC",
    "sg:tags":[
        "attorney"
    ],
    "wof:name":"Nelson, Barbara J QC",
    "wof:placetype":"venue"
},
  "geometry": {"coordinates":[-123.13407100000001,49.276066],"type":"Point"}
}