{
  "type": "Feature",
  "properties": {
    "iso:country":"CA",
    "sg:address":"1475 Rue DE L'Industrie",
    "sg:city":"Beloeil",
    "sg:classifiers":[
        {
            "category":"Building & Trades",
            "subcategory":"Construction",
            "type":"Services"
        }
    ],
    "sg:phone":"+1 450 464 6084",
    "sg:postcode":"J3G 4S5",
    "sg:province":"QC",
    "sg:tags":[
        "equipment",
        "builder",
        "parts",
        "truck",
        "deck"
    ],
    "wof:name":"Entreprises Paul Maranda Inc",
    "wof:placetype":"venue"
},
  "geometry": {"coordinates":[-73.207619,45.57486],"type":"Point"}
}