{
  "type": "Feature",
  "properties": {
    "addr:full":"10 Rue Brooks Sherbrooke QC J1H 4X6",
    "addr:housenumber":"10",
    "addr:postcode":"j1h 4x6",
    "addr:street":"Rue Brooks",
    "iso:country":"CA",
    "sg:address":"10 Rue Brooks",
    "sg:city":"Sherbrooke",
    "sg:classifiers":[
        {
            "category":"Health Services",
            "subcategory":"Nursing And Care Facility",
            "type":"Services"
        }
    ],
    "sg:phone":"+1 819 346 0423",
    "sg:postcode":"J1H 4X6",
    "sg:province":"QC",
    "sg:tags":[
        "home",
        "retirement",
        "community",
        "rest"
    ],
    "wof:name":"Auberge Brooks",
    "wof:placetype":"venue"
},
  "geometry": {"coordinates":[-71.89166299999999,45.400215],"type":"Point"}
}