{
  "type": "Feature",
  "properties": {
    "addr:full":"Southend SK S0J 2L0",
    "addr:postcode":"s0j 2l0",
    "addr:street":"Southend",
    "iso:country":"CA",
    "sg:city":"Southend",
    "sg:classifiers":[
        {
            "category":"Education",
            "subcategory":"School",
            "type":"Public Place"
        }
    ],
    "sg:phone":"+1 306 758 2025",
    "sg:postcode":"S0J 2L0",
    "sg:province":"SK",
    "wof:name":"Reindeer Lake High School",
    "wof:placetype":"venue"
},
  "geometry": {"coordinates":[-103.242004395,56.3293762207],"type":"Point"}
}