{
  "type": "Feature",
  "properties": {
    "addr:full":"3440 56 Ave SE Calgary AB T2C 2C3",
    "addr:housenumber":"3440",
    "addr:postcode":"t2c 2c3",
    "addr:street":"56 Ave Se",
    "iso:country":"CA",
    "sg:address":"3440 56 Ave SE",
    "sg:city":"Calgary",
    "sg:classifiers":[
        {
            "category":"Wholesale",
            "subcategory":"Meat",
            "type":"Manufacturing & Wholesale Goods"
        }
    ],
    "sg:phone":"+1 403 279 2555",
    "sg:postcode":"T2C 2C3",
    "sg:province":"AB",
    "sg:tags":[
        "packer"
    ],
    "wof:name":"Lucerne Foods Ltd",
    "wof:placetype":"venue"
},
  "geometry": {"coordinates":[-113.984832764,51.0021896362],"type":"Point"}
}