{
  "type": "Feature",
  "properties": {
    "addr:full":"3 Cloud Dr Roddickton NL A0K 4P0",
    "addr:housenumber":"3",
    "addr:postcode":"a0k 4p0",
    "addr:street":"Cloud Dr",
    "iso:country":"CA",
    "sg:address":"3 Cloud Dr",
    "sg:city":"Roddickton",
    "sg:classifiers":[
        {
            "category":"Shopping",
            "subcategory":"Pharmacy",
            "type":"Retail Goods"
        }
    ],
    "sg:phone":"+1 709 457 2774",
    "sg:postcode":"A0K 4P0",
    "sg:province":"NL",
    "wof:name":"Roddickton Pharmacy Ltd",
    "wof:placetype":"venue"
},
  "geometry": {"coordinates":[-56.121704,50.872356],"type":"Point"}
}