{
  "type": "Feature",
  "properties": {
    "addr:full":"25 Rue Des Cedres Sainte-Aurelie QC G0M 1M0",
    "addr:housenumber":"25",
    "addr:postcode":"g0m 1m0",
    "addr:street":"Rue Des Cedres Sainte-Aurelie",
    "iso:country":"CA",
    "sg:address":"25 Rue Des Cedres",
    "sg:city":"Sainte-Aurelie",
    "sg:classifiers":[
        {
            "category":"Professional",
            "subcategory":"Advertising",
            "type":"Services"
        }
    ],
    "sg:phone":"+1 418 593 3470",
    "sg:postcode":"G0M 1M0",
    "sg:province":"QC",
    "wof:name":"Alizee Inc",
    "wof:placetype":"venue"
},
  "geometry": {"coordinates":[-70.355934,46.177216],"type":"Point"}
}