{
  "type": "Feature",
  "properties": {
    "addr:full":"5065 Rue Saint-Denis Montreal QC H2J 2L9",
    "addr:housenumber":"5065",
    "addr:postcode":"h2j 2l9",
    "addr:street":"Rue Saint-Denis",
    "iso:country":"CA",
    "sg:address":"5065 Rue Saint-Denis",
    "sg:city":"Montreal",
    "sg:classifiers":[
        {
            "category":"Banks & Credit Unions",
            "subcategory":"Bank",
            "type":"Services"
        }
    ],
    "sg:phone":"+1 514 908 2274",
    "sg:postcode":"H2J 2L9",
    "sg:province":"QC",
    "sg:tags":[
        "cashing",
        "check"
    ],
    "wof:name":"Rapide Cheque",
    "wof:placetype":"venue"
},
  "geometry": {"coordinates":[-73.588829,45.526794],"type":"Point"}
}