{
  "type": "Feature",
  "properties": {
    "addr:full":"1648 1st Ave E Vancouver BC V5N 1A7",
    "addr:housenumber":"1648",
    "addr:postcode":"v5n 1a7",
    "addr:street":"1St Ave E",
    "iso:country":"CA",
    "sg:address":"1648 1st Ave E",
    "sg:city":"Vancouver",
    "sg:classifiers":[
        {
            "category":"Organizations",
            "subcategory":"Religious Organization",
            "type":"Services"
        }
    ],
    "sg:phone":"+1 604 253 3631",
    "sg:postcode":"V5N 1A7",
    "sg:province":"BC",
    "sg:tags":[
        "church"
    ],
    "wof:name":"Salvation Army",
    "wof:placetype":"venue"
},
  "geometry": {"coordinates":[-123.07066345200001,49.2694664001],"type":"Point"}
}