{
  "type": "Feature",
  "properties": {
    "addr:full":"580 Rue Papineau Boisbriand QC J7G 2T7",
    "addr:housenumber":"580",
    "addr:postcode":"j7g 2t7",
    "addr:street":"Rue Papineau",
    "iso:country":"CA",
    "sg:address":"580 Rue Papineau",
    "sg:city":"Boisbriand",
    "sg:classifiers":[
        {
            "category":"Home & Garden",
            "subcategory":"Building Materials",
            "type":"Retail Goods"
        }
    ],
    "sg:phone":"+1 450 434 0499",
    "sg:postcode":"J7G 2T7",
    "sg:province":"QC",
    "sg:tags":[
        "door"
    ],
    "wof:name":"Fenetres Concept Inc",
    "wof:placetype":"venue"
},
  "geometry": {"coordinates":[-73.826965,45.623413],"type":"Point"}
}