{
  "type": "Feature",
  "properties": {
    "iso:country":"CA",
    "sg:city":"Trois-Rivieres",
    "sg:classifiers":[
        {
            "category":"Autos & Motor Vehicles",
            "subcategory":"Auto Supplies",
            "type":"Retail Goods"
        }
    ],
    "sg:phone":"+1 819 374 6209",
    "sg:postcode":"G9A 2V9",
    "sg:province":"QC",
    "sg:tags":[
        "automobile",
        "parts"
    ],
    "wof:name":"Helie'n Sport",
    "wof:placetype":"venue"
},
  "geometry": {"coordinates":[-72.550072,46.332306],"type":"Point"}
}