{
  "type": "Feature",
  "properties": {
    "iso:country":"CA",
    "sg:address":"64 Dunlop St E",
    "sg:city":"Barrie",
    "sg:classifiers":[
        {
            "category":"Banks & Credit Unions",
            "subcategory":"Bank",
            "type":"Services"
        }
    ],
    "sg:phone":"+1 705 726 9311",
    "sg:postcode":"L4M 1A3",
    "sg:province":"ON",
    "wof:name":"National Bank",
    "wof:placetype":"venue"
},
  "geometry": {"coordinates":[-79.687851,44.389309],"type":"Point"}
}