{
  "type": "Feature",
  "properties": {
    "addr:full":"675 Rue Farrell Drummondville QC J2C 6E2",
    "addr:housenumber":"675",
    "addr:postcode":"j2c 6e2",
    "addr:street":"Rue Farrell",
    "iso:country":"CA",
    "sg:address":"675 Rue Farrell",
    "sg:city":"Drummondville",
    "sg:classifiers":[
        {
            "category":"Manufacturing",
            "subcategory":"Signs",
            "type":"Manufacturing & Wholesale Goods"
        }
    ],
    "sg:phone":"+1 819 474 4044",
    "sg:postcode":"J2C 6E2",
    "sg:province":"QC",
    "wof:name":"Enseignes Leco Ltee",
    "wof:placetype":"venue"
},
  "geometry": {"coordinates":[-72.51947021479999,45.8860588074],"type":"Point"}
}