{
  "type": "Feature",
  "properties": {
    "addr:full":"17671 56 Ave Surrey BC V3S 1C9",
    "addr:housenumber":"17671",
    "addr:postcode":"v3s 1c9",
    "addr:street":"56 Ave",
    "iso:country":"CA",
    "sg:address":"17671 56 Ave",
    "sg:city":"Surrey",
    "sg:classifiers":[
        {
            "category":"Government",
            "subcategory":"Office",
            "type":"Public Place"
        }
    ],
    "sg:phone":"+1 604 574 8133",
    "sg:postcode":"V3S 1C9",
    "sg:province":"BC",
    "sg:tags":[
        "village"
    ],
    "wof:name":"Cloverdal Senior Ctr",
    "wof:placetype":"venue"
},
  "geometry": {"coordinates":[-122.732704,49.104301],"type":"Point"}
}