{
  "type": "Feature",
  "properties": {
    "addr:full":"Saint-Calixte QC J0K 1Z0",
    "addr:postcode":"j0k 1z0",
    "iso:country":"CA",
    "sg:city":"Saint-Calixte",
    "sg:classifiers":[
        {
            "category":"Building & Trades",
            "subcategory":"Construction",
            "type":"Services"
        }
    ],
    "sg:phone":"+1 450 222 2211",
    "sg:postcode":"J0K 1Z0",
    "sg:province":"QC",
    "sg:tags":[
        "excavating",
        "contractor"
    ],
    "wof:name":"Regimbald, Fernand",
    "wof:placetype":"venue"
},
  "geometry": {"coordinates":[-73.8505554199,45.9520759583],"type":"Point"}
}