{
  "type": "Feature",
  "properties": {
    "addr:full":"85 Rue DE Martigny O Saint-Jerome QC J7Y 3R8",
    "addr:housenumber":"85",
    "addr:postcode":"j7y 3r8",
    "addr:street":"Rue De Martigny O Saint-Jerome",
    "iso:country":"CA",
    "sg:address":"85 Rue DE Martigny O",
    "sg:city":"Saint-Jerome",
    "sg:classifiers":[
        {
            "category":"Government",
            "subcategory":"Office",
            "type":"Public Place"
        }
    ],
    "sg:phone":"+1 450 569 3075",
    "sg:postcode":"J7Y 3R8",
    "sg:province":"QC",
    "wof:name":"Quebec Securite Du Revenu",
    "wof:placetype":"venue"
},
  "geometry": {"coordinates":[-74.001228,45.780514],"type":"Point"}
}