{
  "type": "Feature",
  "properties": {
    "addr:full":"240 Rue Principale E Farnham QC J2N 1L6",
    "addr:housenumber":"240",
    "addr:postcode":"j2n 1l6",
    "addr:street":"Rue Principale E",
    "iso:country":"CA",
    "sg:address":"240 Rue Principale E",
    "sg:city":"Farnham",
    "sg:classifiers":[
        {
            "category":"Restaurant",
            "type":"Food & Drink"
        }
    ],
    "sg:phone":"+1 450 293 7029",
    "sg:postcode":"J2N 1L6",
    "sg:province":"QC",
    "sg:tags":[
        "lounge",
        "cafe",
        "cocktail"
    ],
    "wof:name":"P'Tit Bar",
    "wof:placetype":"venue"
},
  "geometry": {"coordinates":[-72.9775924683,45.2843475342],"type":"Point"}
}