{
  "type": "Feature",
  "properties": {
    "addr:full":"127 Point West Dr Winnipeg MB R3T 5J5",
    "addr:housenumber":"127",
    "addr:postcode":"r3t 5j5",
    "addr:street":"Point West Dr",
    "iso:country":"CA",
    "sg:address":"127 Point West Dr",
    "sg:city":"Winnipeg",
    "sg:classifiers":[
        {
            "category":"Building & Trades",
            "subcategory":"Landscaping Services",
            "type":"Services"
        }
    ],
    "sg:phone":"+1 204 269 7858",
    "sg:postcode":"R3T 5J5",
    "sg:province":"MB",
    "sg:tags":[
        "landscape",
        "contractor"
    ],
    "wof:name":"Professional Tree Svc",
    "wof:placetype":"venue"
},
  "geometry": {"coordinates":[-97.171104,49.774395],"type":"Point"}
}