{
  "type": "Feature",
  "properties": {
    "iso:country":"CA",
    "sg:address":"2584 Agricola St",
    "sg:city":"Halifax",
    "sg:classifiers":[
        {
            "category":"Professional",
            "subcategory":"Advertising",
            "type":"Services"
        }
    ],
    "sg:phone":"+1 902 429 8463",
    "sg:postcode":"B3K 4C6",
    "sg:province":"NS",
    "sg:tags":[
        "counselor"
    ],
    "wof:name":"Time & Space Media",
    "wof:placetype":"venue"
},
  "geometry": {"coordinates":[-63.5935249329,44.655128479],"type":"Point"}
}