{
  "type": "Feature",
  "properties": {
    "iso:country":"CA",
    "sg:address":"168 Majors Path",
    "sg:city":"St. John's",
    "sg:classifiers":[
        {
            "category":"Wholesale",
            "subcategory":"Machinery & Supplies",
            "type":"Manufacturing & Wholesale Goods"
        }
    ],
    "sg:phone":"+1 709 576 6591",
    "sg:postcode":"A1A 5A1",
    "sg:province":"NL",
    "sg:tags":[
        "equipment",
        "industrial"
    ],
    "wof:name":"Consolidated Continental CO",
    "wof:placetype":"venue"
},
  "geometry": {"coordinates":[-52.7310066223,47.6087036133],"type":"Point"}
}