{
  "type": "Feature",
  "properties": {
    "iso:country":"CA",
    "sg:address":"435 Limeridge Rd E",
    "sg:city":"Hamilton",
    "sg:classifiers":[
        {
            "category":"Recreation",
            "type":"Entertainment"
        }
    ],
    "sg:phone":"+1 905 385 3733",
    "sg:postcode":"L9A 2S8",
    "sg:province":"ON",
    "sg:tags":[
        "caterer",
        "hall",
        "auditorium"
    ],
    "wof:name":"Royal Canadian Legion",
    "wof:placetype":"venue"
},
  "geometry": {"coordinates":[-79.8664779663,43.2153205872],"type":"Point"}
}