{
  "type": "Feature",
  "properties": {
    "addr:full":"Toronto ON M4J 1L4",
    "addr:postcode":"m4j 1l4",
    "iso:country":"CA",
    "sg:city":"Toronto",
    "sg:classifiers":[
        {
            "category":"Education",
            "subcategory":"Special Training",
            "type":"Public Place"
        }
    ],
    "sg:phone":"+1 416 733 8208",
    "sg:postcode":"M4J 1L4",
    "sg:province":"ON",
    "sg:tags":[
        "instruction",
        "driving"
    ],
    "wof:name":"Young Drivers of Canada",
    "wof:placetype":"venue"
},
  "geometry": {"coordinates":[-79.3424072266,43.6792984009],"type":"Point"}
}