{
  "type": "Feature",
  "properties": {
    "addr:full":"419 Boul Jessop # 685 Rimouski QC G5L 7Y5",
    "addr:housenumber":"419",
    "addr:postcode":"g5l 7y5",
    "addr:street":"Boul Jessop # 685",
    "iso:country":"CA",
    "sg:address":"419 Boul Jessop # 685",
    "sg:city":"Rimouski",
    "sg:classifiers":[
        {
            "category":"Shopping",
            "subcategory":"Clothing, Apparel, & Fashions",
            "type":"Retail Goods"
        }
    ],
    "sg:phone":"+1 418 722 9755",
    "sg:postcode":"G5L 7Y5",
    "sg:province":"QC",
    "sg:tags":[
        "item",
        "boutique"
    ],
    "wof:name":"Emotions",
    "wof:placetype":"venue"
},
  "geometry": {"coordinates":[-68.51559399999999,48.468117],"type":"Point"}
}