{
  "type": "Feature",
  "properties": {
    "addr:full":"2245 Park Cres Coquitlam BC V3J 6T1",
    "addr:housenumber":"2245",
    "addr:postcode":"v3j 6t1",
    "addr:street":"Park Cres",
    "iso:country":"CA",
    "sg:address":"2245 Park Cres",
    "sg:city":"Coquitlam",
    "sg:classifiers":[
        {
            "category":"Arts & Performance",
            "subcategory":"Theater",
            "type":"Entertainment"
        }
    ],
    "sg:phone":"+1 604 469 4991",
    "sg:postcode":"V3J 6T1",
    "sg:province":"BC",
    "sg:tags":[
        "talent",
        "agency",
        "casting"
    ],
    "wof:name":"Shooting Stars Agency",
    "wof:placetype":"venue"
},
  "geometry": {"coordinates":[-122.83161163299999,49.2710266113],"type":"Point"}
}