{
  "type": "Feature",
  "properties": {
    "addr:full":"468 Rue Principale Lachute QC J8H 1Y3",
    "addr:housenumber":"468",
    "addr:postcode":"j8h 1y3",
    "addr:street":"Rue Principale",
    "iso:country":"CA",
    "sg:address":"468 Rue Principale",
    "sg:city":"Lachute",
    "sg:classifiers":[
        {
            "category":"Health Services",
            "subcategory":"Optometrist",
            "type":"Services"
        }
    ],
    "sg:phone":"+1 450 562 4934",
    "sg:postcode":"J8H 1Y3",
    "sg:province":"QC",
    "sg:tags":[
        "optician"
    ],
    "wof:name":"Optique Clin D'Oeil",
    "wof:placetype":"venue"
},
  "geometry": {"coordinates":[-74.33612100000001,45.656425],"type":"Point"}
}