{
  "type": "Feature",
  "properties": {
    "addr:full":"33 Rue Rouillier Saint-Philippe QC J0L 2K0",
    "addr:housenumber":"33",
    "addr:postcode":"j0l 2k0",
    "addr:street":"Rue Rouillier",
    "iso:country":"CA",
    "sg:address":"33 Rue Rouillier",
    "sg:city":"Saint-Philippe",
    "sg:classifiers":[
        {
            "category":"Building & Trades",
            "subcategory":"Construction",
            "type":"Services"
        }
    ],
    "sg:phone":"+1 450 659 4914",
    "sg:postcode":"J0L 2K0",
    "sg:province":"QC",
    "sg:tags":[
        "insulation",
        "heat",
        "contractor"
    ],
    "wof:name":"Isolations Claude Gariepy Enr",
    "wof:placetype":"venue"
},
  "geometry": {"coordinates":[-73.46719360349999,45.3816184998],"type":"Point"}
}