{
  "type": "Feature",
  "properties": {
    "addr:full":"Surrey BC V3V 4B5",
    "addr:postcode":"v3v 4b5",
    "iso:country":"CA",
    "sg:city":"Surrey",
    "sg:classifiers":[
        {
            "category":"Building & Trades",
            "subcategory":"Electrical",
            "type":"Services"
        }
    ],
    "sg:phone":"+1 604 594 3209",
    "sg:postcode":"V3V 4B5",
    "sg:province":"BC",
    "sg:tags":[
        "electric",
        "contractor"
    ],
    "wof:name":"Sira Electric 1997 Ltd",
    "wof:placetype":"venue"
},
  "geometry": {"coordinates":[-122.89008331300001,49.1700248718],"type":"Point"}
}