{
  "type": "Feature",
  "properties": {
    "iso:country":"CA",
    "sg:address":"2001 Highway 15",
    "sg:city":"Kingston",
    "sg:classifiers":[
        {
            "category":"Insurance",
            "subcategory":"Insurance Agent",
            "type":"Services"
        }
    ],
    "sg:phone":"+1 613 542 6573",
    "sg:postcode":"K7L 4V3",
    "sg:province":"ON",
    "wof:name":"Earl Shaw Insurance Brokers",
    "wof:placetype":"venue"
},
  "geometry": {"coordinates":[-76.47933197019999,44.2315368652],"type":"Point"}
}