{
  "type": "Feature",
  "properties": {
    "iso:country":"CA",
    "sg:address":"309 100 Ave",
    "sg:city":"Dawson Creek",
    "sg:classifiers":[
        {
            "category":"Mining & Drilling",
            "type":"Manufacturing & Wholesale Goods"
        }
    ],
    "sg:phone":"+1 250 782 4416",
    "sg:postcode":"V1G 1V4",
    "sg:province":"BC",
    "sg:tags":[
        "field",
        "oil",
        "steam",
        "cleaning"
    ],
    "wof:name":"A & F Mobile Steam Cleaning",
    "wof:placetype":"venue"
},
  "geometry": {"coordinates":[-120.214805603,55.7611198425],"type":"Point"}
}