{
  "type": "Feature",
  "properties": {
    "addr:full":"171 Main St Liverpool NS B0T 1K0",
    "addr:housenumber":"171",
    "addr:postcode":"b0t 1k0",
    "addr:street":"Main St",
    "iso:country":"CA",
    "sg:address":"171 Main St",
    "sg:city":"Liverpool",
    "sg:classifiers":[
        {
            "category":"Professional",
            "subcategory":"Lawyer & Legal Services",
            "type":"Services"
        }
    ],
    "sg:phone":"+1 902 354 5756",
    "sg:postcode":"B0T 1K0",
    "sg:province":"NS",
    "sg:tags":[
        "attorney"
    ],
    "wof:name":"Tutty & Dipersio",
    "wof:placetype":"venue"
},
  "geometry": {"coordinates":[-64.714027,44.039574],"type":"Point"}
}