{
  "type": "Feature",
  "properties": {
    "iso:country":"CA",
    "sg:city":"LA Salle",
    "sg:classifiers":[
        {
            "category":"Shopping",
            "subcategory":"Gifts & Souvenirs",
            "type":"Retail Goods"
        }
    ],
    "sg:phone":"+1 204 736 3026",
    "sg:postcode":"R0G 1B0",
    "sg:province":"MB",
    "sg:tags":[
        "shop"
    ],
    "wof:name":"Country Imports",
    "wof:placetype":"venue"
},
  "geometry": {"coordinates":[-97.2642211914,49.6934738159],"type":"Point"}
}