{
  "type": "Feature",
  "properties": {
    "addr:full":"358 Rue Notre-Dame Repentigny QC J6A 2S5",
    "addr:housenumber":"358",
    "addr:postcode":"j6a 2s5",
    "addr:street":"Rue Notre-Dame",
    "iso:country":"CA",
    "sg:address":"358 Rue Notre-Dame",
    "sg:city":"Repentigny",
    "sg:classifiers":[
        {
            "category":"Food & Beverages",
            "subcategory":"Bakery",
            "type":"Retail Goods"
        }
    ],
    "sg:phone":"+1 450 582 7642",
    "sg:postcode":"J6A 2S5",
    "sg:province":"QC",
    "sg:tags":[
        "baker"
    ],
    "wof:name":"Patisserie LA Praline",
    "wof:placetype":"venue"
},
  "geometry": {"coordinates":[-73.45318603520001,45.7326507568],"type":"Point"}
}