{
  "type": "Feature",
  "properties": {
    "addr:full":"285 Service Rd N Vulcan AB T0L 2B0",
    "addr:housenumber":"285",
    "addr:postcode":"t0l 2b0",
    "addr:street":"Service Rd N Vulcan",
    "iso:country":"CA",
    "sg:address":"285 Service Rd N",
    "sg:city":"Vulcan",
    "sg:classifiers":[
        {
            "category":"Home & Garden",
            "subcategory":"Garden Supply",
            "type":"Retail Goods"
        }
    ],
    "sg:phone":"+1 403 485 2140",
    "sg:postcode":"T0L 2B0",
    "sg:province":"AB",
    "sg:tags":[
        "chemical",
        "agricultural"
    ],
    "wof:name":"Agricore United",
    "wof:placetype":"venue"
},
  "geometry": {"coordinates":[-113.25645400000001,50.405834],"type":"Point"}
}