{
  "type": "Feature",
  "properties": {
    "iso:country":"CA",
    "sg:address":"2704 125 Rte",
    "sg:city":"Sainte-Julienne",
    "sg:classifiers":[
        {
            "category":"Building & Trades",
            "subcategory":"Construction",
            "type":"Services"
        }
    ],
    "sg:phone":"+1 450 834 2755",
    "sg:postcode":"J0K 2T0",
    "sg:province":"QC",
    "sg:tags":[
        "water",
        "well",
        "drilling"
    ],
    "wof:name":"Antoine Langlois Inc",
    "wof:placetype":"venue"
},
  "geometry": {"coordinates":[-73.7198104858,45.9952850342],"type":"Point"}
}