{
  "type": "Feature",
  "properties": {
    "addr:full":"8025 156 St Surrey BC V3S 3R4",
    "addr:housenumber":"8025",
    "addr:postcode":"v3s 3r4",
    "addr:street":"156 St",
    "iso:country":"CA",
    "sg:address":"8025 156 St",
    "sg:city":"Surrey",
    "sg:classifiers":[
        {
            "category":"Building & Trades",
            "subcategory":"Construction",
            "type":"Services"
        }
    ],
    "sg:phone":"+1 604 597 3388",
    "sg:postcode":"V3S 3R4",
    "sg:province":"BC",
    "sg:tags":[
        "steel",
        "erectors"
    ],
    "wof:name":"Pfc Steel Management Svc Inc",
    "wof:placetype":"venue"
},
  "geometry": {"coordinates":[-122.790176,49.148743],"type":"Point"}
}