{
  "type": "Feature",
  "properties": {
    "addr:full":"Nanticoke ON N0A 1L0",
    "addr:postcode":"n0a 1l0",
    "addr:street":"Nanticoke",
    "iso:country":"CA",
    "sg:city":"Nanticoke",
    "sg:classifiers":[
        {
            "category":"Building & Trades",
            "subcategory":"Construction",
            "type":"Services"
        }
    ],
    "sg:phone":"+1 519 587 5544",
    "sg:postcode":"N0A 1L0",
    "sg:province":"ON",
    "sg:tags":[
        "control",
        "erosion",
        "designer",
        "marine",
        "contractor"
    ],
    "wof:name":"Wilkinson Erosion Control Ltd",
    "wof:placetype":"venue"
},
  "geometry": {"coordinates":[-80.07197600000001,42.810741],"type":"Point"}
}