{
  "type": "Feature",
  "properties": {
    "addr:full":"Harrow ON N0R 1G0",
    "addr:postcode":"n0r 1g0",
    "iso:country":"CA",
    "sg:city":"Harrow",
    "sg:classifiers":[
        {
            "category":"Utilities",
            "subcategory":"Refuse",
            "type":"Services"
        }
    ],
    "sg:phone":"+1 519 736 5643",
    "sg:postcode":"N0R 1G0",
    "sg:province":"ON",
    "sg:tags":[
        "garbage",
        "collection"
    ],
    "wof:name":"D W Crowder Trucking",
    "wof:placetype":"venue"
},
  "geometry": {"coordinates":[-82.91790771479999,42.0355262756],"type":"Point"}
}