{
  "type": "Feature",
  "properties": {
    "addr:full":"Deacon Lake Deep River ON K0J 1P0",
    "addr:postcode":"k0j 1p0",
    "addr:street":"Deacon Lake",
    "iso:country":"CA",
    "sg:address":"Deacon Lake",
    "sg:city":"Deep River",
    "sg:classifiers":[
        {
            "category":"Organizations",
            "subcategory":"Professional Association",
            "type":"Services"
        }
    ],
    "sg:phone":"+1 613 584 1342",
    "sg:postcode":"K0J 1P0",
    "sg:province":"ON",
    "sg:tags":[
        "club"
    ],
    "wof:name":"Wedgewood Club",
    "wof:placetype":"venue"
},
  "geometry": {"coordinates":[-77.492653,46.098076],"type":"Point"}
}