{
  "type": "Feature",
  "properties": {
    "addr:full":"1149 8th St E Saskatoon SK S7H 0S3",
    "addr:housenumber":"1149",
    "addr:postcode":"s7h 0s3",
    "addr:street":"8Th St E",
    "iso:country":"CA",
    "sg:address":"1149 8th St E",
    "sg:city":"Saskatoon",
    "sg:classifiers":[
        {
            "category":"Real Estate",
            "subcategory":"Real Estate Agent",
            "type":"Services"
        }
    ],
    "sg:phone":"+1 306 244 4453",
    "sg:postcode":"S7H 0S3",
    "sg:province":"SK",
    "wof:name":"Saskatoon Real Estate Board",
    "wof:placetype":"venue"
},
  "geometry": {"coordinates":[-106.642753601,52.114944458],"type":"Point"}
}