{
  "type": "Feature",
  "properties": {
    "addr:full":"Sainte-Croix QC G0S 2H0",
    "addr:postcode":"g0s 2h0",
    "iso:country":"CA",
    "sg:city":"Sainte-Croix",
    "sg:classifiers":[
        {
            "category":"Insurance",
            "subcategory":"Insurance Agent",
            "type":"Services"
        }
    ],
    "sg:phone":"+1 418 926 2042",
    "sg:postcode":"G0S 2H0",
    "sg:province":"QC",
    "wof:name":"Assurances-Voyages Gb",
    "wof:placetype":"venue"
},
  "geometry": {"coordinates":[-71.73570251460001,46.6228561401],"type":"Point"}
}