{
  "type": "Feature",
  "properties": {
    "addr:full":"PO Box 601 STN Main Cold Lake AB T9M 1P2",
    "addr:housenumber":"po;601",
    "addr:postcode":"t9m 1p2",
    "addr:street":"Box;Stn Main",
    "iso:country":"CA",
    "sg:address":"PO Box 601 STN Main",
    "sg:city":"Cold Lake",
    "sg:classifiers":[
        {
            "category":"Building & Trades",
            "subcategory":"Construction",
            "type":"Services"
        }
    ],
    "sg:phone":"+1 780 639 3059",
    "sg:postcode":"T9M 1P2",
    "sg:province":"AB",
    "sg:tags":[
        "general",
        "contractor"
    ],
    "wof:name":"T-Square Contracting Inc",
    "wof:placetype":"venue"
},
  "geometry": {"coordinates":[-110.17379,54.465027],"type":"Point"}
}