{
  "type": "Feature",
  "properties": {
    "addr:full":"60 Inglis St Ayr ON N0B 1E0",
    "addr:housenumber":"60",
    "addr:postcode":"n0b 1e0",
    "addr:street":"Inglis St",
    "iso:country":"CA",
    "sg:address":"60 Inglis St",
    "sg:city":"Ayr",
    "sg:classifiers":[
        {
            "category":"Manufacturing",
            "subcategory":"Metals",
            "type":"Manufacturing & Wholesale Goods"
        }
    ],
    "sg:phone":"+1 519 632 7456",
    "sg:postcode":"N0B 1E0",
    "sg:province":"ON",
    "sg:tags":[
        "stamping"
    ],
    "wof:name":"Premier Spring & Mfg Ltd",
    "wof:placetype":"venue"
},
  "geometry": {"coordinates":[-80.45370483400001,43.2914123535],"type":"Point"}
}