{
  "type": "Feature",
  "properties": {
    "addr:full":"2645 Royal Windsor Dr Mississauga ON L5J 1K9",
    "addr:housenumber":"2645",
    "addr:postcode":"l5j 1k9",
    "addr:street":"Royal Windsor Dr",
    "iso:country":"CA",
    "sg:address":"2645 Royal Windsor Dr",
    "sg:city":"Mississauga",
    "sg:classifiers":[
        {
            "category":"Wholesale",
            "subcategory":"Electrical",
            "type":"Manufacturing & Wholesale Goods"
        }
    ],
    "sg:phone":"+1 905 855 4610",
    "sg:postcode":"L5J 1K9",
    "sg:province":"ON",
    "sg:tags":[
        "equipment",
        "tool",
        "electronic"
    ],
    "wof:name":"Electrovaya Inc",
    "wof:placetype":"venue"
},
  "geometry": {"coordinates":[-79.64247899999999,43.49963],"type":"Point"}
}