{
  "type": "Feature",
  "properties": {
    "iso:country":"CA",
    "sg:address":"2645 Royal Windsor Dr",
    "sg:city":"Mississauga",
    "sg:classifiers":[
        {
            "category":"Wholesale",
            "subcategory":"Electrical",
            "type":"Manufacturing & Wholesale Goods"
        }
    ],
    "sg:phone":"+1 905 855 4610",
    "sg:postcode":"L5J 1K9",
    "sg:province":"ON",
    "sg:tags":[
        "equipment",
        "tool",
        "electronic"
    ],
    "wof:name":"Electrovaya Inc",
    "wof:placetype":"venue"
},
  "geometry": {"coordinates":[-79.642479,43.49963],"type":"Point"}
}