{
  "type": "Feature",
  "properties": {
    "addr:full":"532 Benoit Ave New Liskeard ON P0J 1P0",
    "addr:housenumber":"532",
    "addr:postcode":"p0j 1p0",
    "addr:street":"Benoit Ave",
    "iso:country":"CA",
    "sg:address":"532 Benoit Ave",
    "sg:city":"New Liskeard",
    "sg:classifiers":[
        {
            "category":"Building & Trades",
            "subcategory":"Construction",
            "type":"Services"
        }
    ],
    "sg:phone":"+1 705 647 6609",
    "sg:postcode":"P0J 1P0",
    "sg:province":"ON",
    "sg:tags":[
        "pole",
        "line",
        "contractor"
    ],
    "wof:name":"Cote's Pole Line",
    "wof:placetype":"venue"
},
  "geometry": {"coordinates":[-79.67366790769999,47.5085792542],"type":"Point"}
}