{
  "type": "Feature",
  "properties": {
    "addr:full":"20 Glebe Rd E Toronto ON M4S 1N6",
    "addr:housenumber":"20",
    "addr:postcode":"m4s 1n6",
    "addr:street":"Glebe Rd E",
    "iso:country":"CA",
    "sg:address":"20 Glebe Rd E",
    "sg:city":"Toronto",
    "sg:classifiers":[
        {
            "category":"Organizations",
            "subcategory":"Religious Organization",
            "type":"Services"
        }
    ],
    "sg:phone":"+1 416 484 6849",
    "sg:postcode":"M4S 1N6",
    "sg:province":"ON",
    "sg:tags":[
        "church"
    ],
    "wof:name":"German United Church",
    "wof:placetype":"venue"
},
  "geometry": {"coordinates":[-79.396767,43.701363],"type":"Point"}
}