{
  "type": "Feature",
  "properties": {
    "addr:full":"1544 Fifth Louth Ave St Catharines ON L2R 6P7",
    "addr:housenumber":"1544",
    "addr:postcode":"l2r 6p7",
    "addr:street":"Fifth Louth Ave",
    "iso:country":"CA",
    "sg:address":"1544 Fifth Louth Ave",
    "sg:city":"St Catharines",
    "sg:classifiers":[
        {
            "category":"Building & Trades",
            "subcategory":"Construction",
            "type":"Services"
        }
    ],
    "sg:phone":"+1 905 685 4424",
    "sg:postcode":"L2R 6P7",
    "sg:province":"ON",
    "sg:tags":[
        "roofing",
        "contractor"
    ],
    "wof:name":"Ed Christensen Roofing Ltd",
    "wof:placetype":"venue"
},
  "geometry": {"coordinates":[-79.24867248539999,43.1563339233],"type":"Point"}
}