{
  "type": "Feature",
  "properties": {
    "iso:country":"CA",
    "sg:address":"606 Rue Cathcart",
    "sg:city":"Montreal",
    "sg:classifiers":[
        {
            "category":"Professional",
            "subcategory":"Management & Consulting",
            "type":"Services"
        }
    ],
    "sg:phone":"+1 514 394 9449",
    "sg:postcode":"H3B 1K9",
    "sg:province":"QC",
    "sg:tags":[
        "consultant",
        "business"
    ],
    "wof:name":"Akera Inc",
    "wof:placetype":"venue"
},
  "geometry": {"coordinates":[-73.567978,45.50354],"type":"Point"}
}