{
  "type": "Feature",
  "properties": {
    "addr:full":"349 Rue Des Chevaliers Rimouski QC G5L 1X3",
    "addr:housenumber":"349",
    "addr:postcode":"g5l 1x3",
    "addr:street":"Rue Des Chevaliers",
    "iso:country":"CA",
    "sg:address":"349 Rue Des Chevaliers",
    "sg:city":"Rimouski",
    "sg:classifiers":[
        {
            "category":"Building & Trades",
            "subcategory":"Plumbing",
            "type":"Services"
        }
    ],
    "sg:phone":"+1 418 724 7711",
    "sg:postcode":"G5L 1X3",
    "sg:province":"QC",
    "sg:tags":[
        "conditioning",
        "air",
        "system",
        "refrigerating",
        "contractor"
    ],
    "wof:name":"Refrigeration Grl Inc",
    "wof:placetype":"venue"
},
  "geometry": {"coordinates":[-68.5078582764,48.459186554],"type":"Point"}
}