{
  "type": "Feature",
  "properties": {
    "addr:full":"87 Wallbridge Cres Belleville ON K8P 1Z5",
    "addr:housenumber":"87",
    "addr:postcode":"k8p 1z5",
    "addr:street":"Wallbridge Cres",
    "iso:country":"CA",
    "sg:address":"87 Wallbridge Cres",
    "sg:city":"Belleville",
    "sg:classifiers":[
        {
            "category":"Freight",
            "type":"Transportation"
        }
    ],
    "sg:phone":"+1 613 962 9557",
    "sg:postcode":"K8P 1Z5",
    "sg:province":"ON",
    "sg:tags":[
        "mover"
    ],
    "wof:name":"Lapalm Moving",
    "wof:placetype":"venue"
},
  "geometry": {"coordinates":[-77.39464599999999,44.17028],"type":"Point"}
}