{
  "type": "Feature",
  "properties": {
    "addr:full":"284 Rang Saint-Joseph Sainte-Beatrix QC J0K 1Y0",
    "addr:housenumber":"284",
    "addr:postcode":"j0k 1y0",
    "addr:street":"Rang Saint-Joseph Sainte-Beatrix",
    "iso:country":"CA",
    "sg:address":"284 Rang Saint-Joseph",
    "sg:city":"Sainte-Beatrix",
    "sg:classifiers":[
        {
            "category":"Home & Garden",
            "subcategory":"Carpets & Floor Coverings",
            "type":"Retail Goods"
        }
    ],
    "sg:phone":"+1 450 883 2381",
    "sg:postcode":"J0K 1Y0",
    "sg:province":"QC",
    "sg:tags":[
        "dealer",
        "rug"
    ],
    "wof:name":"Roi Du Tapis Enrg",
    "wof:placetype":"venue"
},
  "geometry": {"coordinates":[-73.600082,46.178261],"type":"Point"}
}