{
  "type": "Feature",
  "properties": {
    "addr:full":"100 Boul Brien # 14 Repentigny QC J6A 5N4",
    "addr:housenumber":"100",
    "addr:postcode":"j6a 5n4",
    "addr:street":"Boul Brien # 14",
    "iso:country":"CA",
    "sg:address":"100 Boul Brien # 14",
    "sg:city":"Repentigny",
    "sg:classifiers":[
        {
            "category":"Shopping",
            "subcategory":"Clothing, Apparel, & Fashions",
            "type":"Retail Goods"
        }
    ],
    "sg:phone":"+1 450 581 8354",
    "sg:postcode":"J6A 5N4",
    "sg:province":"QC",
    "sg:tags":[
        "shop",
        "boutique",
        "gift"
    ],
    "wof:name":"Ardene",
    "wof:placetype":"venue"
},
  "geometry": {"coordinates":[-73.455147,45.744362],"type":"Point"}
}