{
  "type": "Feature",
  "properties": {
    "addr:full":"Grand-Mere QC G9T 2P7",
    "addr:postcode":"g9t 2p7",
    "iso:country":"CA",
    "sg:city":"Grand-Mere",
    "sg:classifiers":[
        {
            "category":"Manufacturing",
            "subcategory":"Retail Goods",
            "type":"Manufacturing & Wholesale Goods"
        }
    ],
    "sg:phone":"+1 819 538 1745",
    "sg:postcode":"G9T 2P7",
    "sg:province":"QC",
    "sg:tags":[
        "spool"
    ],
    "wof:name":"Bobines Mauriciennes Enr",
    "wof:placetype":"venue"
},
  "geometry": {"coordinates":[-72.71028099999999,46.600674],"type":"Point"}
}