{
  "type": "Feature",
  "properties": {
    "iso:country":"CA",
    "sg:address":"319 North Rd",
    "sg:city":"Coquitlam",
    "sg:classifiers":[
        {
            "category":"Travel",
            "subcategory":"Hotels & Motels",
            "type":"Entertainment"
        }
    ],
    "sg:phone":"+1 604 931 9011",
    "sg:postcode":"V3K 3V8",
    "sg:province":"BC",
    "wof:name":"Best Western Coquitlam Inn",
    "wof:placetype":"venue"
},
  "geometry": {"coordinates":[-122.892417908,49.2428779602],"type":"Point"}
}