{
  "type": "Feature",
  "properties": {
    "addr:full":"1260 Grant St Victoria BC V8T 1C2",
    "addr:housenumber":"1260",
    "addr:postcode":"v8t 1c2",
    "addr:street":"Grant St",
    "iso:country":"CA",
    "sg:address":"1260 Grant St",
    "sg:city":"Victoria",
    "sg:classifiers":[
        {
            "category":"Education",
            "subcategory":"School",
            "type":"Public Place"
        }
    ],
    "sg:phone":"+1 250 388 5456",
    "sg:postcode":"V8T 1C2",
    "sg:province":"BC",
    "wof:name":"Victoria High",
    "wof:placetype":"venue"
},
  "geometry": {"coordinates":[-123.347359,48.428875],"type":"Point"}
}