{
  "type": "Feature",
  "properties": {
    "addr:full":"Montreal QC H3H 2R2",
    "addr:postcode":"h3h 2r2",
    "iso:country":"CA",
    "sg:city":"Montreal",
    "sg:classifiers":[
        {
            "category":"Professional",
            "subcategory":"Management & Consulting",
            "type":"Services"
        }
    ],
    "sg:phone":"+1 514 933 9898",
    "sg:postcode":"H3H 2R2",
    "sg:province":"QC",
    "sg:tags":[
        "marketing",
        "consultant"
    ],
    "wof:name":"Consultants Cfs Inc",
    "wof:placetype":"venue"
},
  "geometry": {"coordinates":[-73.588745,45.493927],"type":"Point"}
}