{
  "type": "Feature",
  "properties": {
    "addr:full":"72 Water St Stratford ON N5A 3C1",
    "addr:housenumber":"72",
    "addr:postcode":"n5a 3c1",
    "addr:street":"Water St",
    "iso:country":"CA",
    "sg:address":"72 Water St",
    "sg:city":"Stratford",
    "sg:classifiers":[
        {
            "category":"Organizations",
            "subcategory":"Professional Association",
            "type":"Services"
        }
    ],
    "sg:phone":"+1 519 271 1633",
    "sg:postcode":"N5A 3C1",
    "sg:province":"ON",
    "sg:tags":[
        "club"
    ],
    "wof:name":"Stratford Optimist Hall",
    "wof:placetype":"venue"
},
  "geometry": {"coordinates":[-80.9771347046,43.3730735779],"type":"Point"}
}