{
  "type": "Feature",
  "properties": {
    "addr:full":"Laval QC H7V 1S1",
    "addr:postcode":"h7v 1s1",
    "iso:country":"CA",
    "sg:city":"Laval",
    "sg:classifiers":[
        {
            "category":"Professional",
            "subcategory":"Business Services",
            "type":"Services"
        }
    ],
    "sg:phone":"+1 450 681 2577",
    "sg:postcode":"H7V 1S1",
    "sg:province":"QC",
    "sg:tags":[
        "notary"
    ],
    "wof:name":"Vinet & Vinet",
    "wof:placetype":"venue"
},
  "geometry": {"coordinates":[-73.74737548829999,45.541229248],"type":"Point"}
}