{
  "type": "Feature",
  "properties": {
    "addr:full":"2035 Campbell Rd Kelowna BC V1Z 1S9",
    "addr:housenumber":"2035",
    "addr:postcode":"v1z 1s9",
    "addr:street":"Campbell Rd",
    "iso:country":"CA",
    "sg:address":"2035 Campbell Rd",
    "sg:city":"Kelowna",
    "sg:classifiers":[
        {
            "category":"Bars & Pubs",
            "type":"Food & Drink"
        }
    ],
    "sg:phone":"+1 250 769 7066",
    "sg:postcode":"V1Z 1S9",
    "sg:province":"BC",
    "wof:name":"Pier Marina Pub & Grill",
    "wof:placetype":"venue"
},
  "geometry": {"coordinates":[-119.52474975600001,49.8780937195],"type":"Point"}
}