{
  "type": "Feature",
  "properties": {
    "addr:full":"894 Logan Ave Toronto ON M4K 3E1",
    "addr:housenumber":"894",
    "addr:postcode":"m4k 3e1",
    "addr:street":"Logan Ave",
    "iso:country":"CA",
    "sg:address":"894 Logan Ave",
    "sg:city":"Toronto",
    "sg:classifiers":[
        {
            "category":"Retail",
            "subcategory":"Laundry & Dry Cleaning",
            "type":"Services"
        }
    ],
    "sg:phone":"+1 416 778 1253",
    "sg:postcode":"M4K 3E1",
    "sg:province":"ON",
    "sg:tags":[
        "cleaners"
    ],
    "wof:name":"Logan Cleaners",
    "wof:placetype":"venue"
},
  "geometry": {"coordinates":[-79.349754,43.677757],"type":"Point"}
}