{
  "type": "Feature",
  "properties": {
    "addr:full":"13959 Rue Pierre-Brion Montreal QC H1A 4K1",
    "addr:housenumber":"13959",
    "addr:postcode":"h1a 4k1",
    "addr:street":"Rue Pierre-Brion",
    "iso:country":"CA",
    "sg:address":"13959 Rue Pierre-Brion",
    "sg:city":"Montreal",
    "sg:classifiers":[
        {
            "category":"Building & Trades",
            "subcategory":"Pest Control",
            "type":"Services"
        }
    ],
    "sg:phone":"+1 514 642 6099",
    "sg:postcode":"H1A 4K1",
    "sg:province":"QC",
    "wof:name":"Extermination Techni-Bec Enr",
    "wof:placetype":"venue"
},
  "geometry": {"coordinates":[-73.50932299999999,45.668156],"type":"Point"}
}