{
  "type": "Feature",
  "properties": {
    "iso:country":"CA",
    "sg:address":"155 Rue Jules-Leger",
    "sg:city":"Boucherville",
    "sg:classifiers":[
        {
            "category":"Building & Trades",
            "subcategory":"Construction",
            "type":"Services"
        }
    ],
    "sg:phone":"+1 450 641 1737",
    "sg:postcode":"J4B 7K8",
    "sg:province":"QC",
    "sg:tags":[
        "maker",
        "cabinet"
    ],
    "wof:name":"Ebenisterie Norclair Inc",
    "wof:placetype":"venue"
},
  "geometry": {"coordinates":[-73.451813,45.576687],"type":"Point"}
}