{
  "type": "Feature",
  "properties": {
    "addr:full":"1026 3 Ave S Lethbridge AB T1J 0J4",
    "addr:housenumber":"1026",
    "addr:postcode":"t1j 0j4",
    "addr:street":"3 Ave S",
    "iso:country":"CA",
    "sg:address":"1026 3 Ave S",
    "sg:city":"Lethbridge",
    "sg:classifiers":[
        {
            "category":"Home & Garden",
            "subcategory":"Building Materials",
            "type":"Retail Goods"
        }
    ],
    "sg:phone":"+1 403 328 9221",
    "sg:postcode":"T1J 0J4",
    "sg:province":"AB",
    "sg:tags":[
        "paint"
    ],
    "wof:name":"General Paint Ltd",
    "wof:placetype":"venue"
},
  "geometry": {"coordinates":[-112.831886,49.696018],"type":"Point"}
}