{
  "type": "Feature",
  "properties": {
    "addr:full":"180 Yamaska Saint-Hugues QC J0H 1N0",
    "addr:housenumber":"180",
    "addr:postcode":"j0h 1n0",
    "addr:street":"Yamaska",
    "iso:country":"CA",
    "sg:address":"180 Yamaska",
    "sg:city":"Saint-Hugues",
    "sg:classifiers":[
        {
            "category":"Building & Trades",
            "subcategory":"Electrical",
            "type":"Services"
        }
    ],
    "sg:phone":"+1 450 791 2512",
    "sg:postcode":"J0H 1N0",
    "sg:province":"QC",
    "sg:tags":[
        "electric",
        "contractor"
    ],
    "wof:name":"Martin Pierre Yves Entr Elect",
    "wof:placetype":"venue"
},
  "geometry": {"coordinates":[-72.86698150629999,45.7898979187],"type":"Point"}
}