{
  "type": "Feature",
  "properties": {
    "addr:full":"405 Rue Des Oblats Maniwaki QC J9E 1H1",
    "addr:housenumber":"405",
    "addr:postcode":"j9e 1h1",
    "addr:street":"Rue Des Oblats",
    "iso:country":"CA",
    "sg:address":"405 Rue Des Oblats",
    "sg:city":"Maniwaki",
    "sg:classifiers":[
        {
            "category":"Personal",
            "subcategory":"Beauty Salon",
            "type":"Services"
        }
    ],
    "sg:phone":"+1 819 449 7316",
    "sg:postcode":"J9E 1H1",
    "sg:province":"QC",
    "wof:name":"Salon Josee Coulombe Coiffure",
    "wof:placetype":"venue"
},
  "geometry": {"coordinates":[-75.968307,46.381046],"type":"Point"}
}