{
  "type": "Feature",
  "properties": {
    "addr:full":"2890 Rue Bergeron Saint-Paulin QC J0K 3G0",
    "addr:housenumber":"2890",
    "addr:postcode":"j0k 3g0",
    "addr:street":"Rue Bergeron",
    "iso:country":"CA",
    "sg:address":"2890 Rue Bergeron",
    "sg:city":"Saint-Paulin",
    "sg:classifiers":[
        {
            "category":"Professional",
            "subcategory":"Business Services",
            "type":"Services"
        }
    ],
    "sg:phone":"+1 819 268 2683",
    "sg:postcode":"J0K 3G0",
    "sg:province":"QC",
    "sg:tags":[
        "notary"
    ],
    "wof:name":"Michaud, Luc",
    "wof:placetype":"venue"
},
  "geometry": {"coordinates":[-73.013977,46.420162],"type":"Point"}
}