{
  "type": "Feature",
  "properties": {
    "addr:full":"2048 Rue Marie-Anne O Carignan QC J3L 4G2",
    "addr:housenumber":"2048",
    "addr:postcode":"j3l 4g2",
    "addr:street":"Rue Marie-Anne O",
    "iso:country":"CA",
    "sg:address":"2048 Rue Marie-Anne O",
    "sg:city":"Carignan",
    "sg:classifiers":[
        {
            "category":"Building & Trades",
            "subcategory":"Electrical",
            "type":"Services"
        }
    ],
    "sg:phone":"+1 450 658 7621",
    "sg:postcode":"J3L 4G2",
    "sg:province":"QC",
    "sg:tags":[
        "electric",
        "contractor"
    ],
    "wof:name":"Zelenko Electrique Enrg",
    "wof:placetype":"venue"
},
  "geometry": {"coordinates":[-73.33000199999999,45.449722],"type":"Point"}
}