{
  "type": "Feature",
  "properties": {
    "addr:full":"73 Starrs Rd Yarmouth NS B5A 2T6",
    "addr:housenumber":"73",
    "addr:postcode":"b5a 2t6",
    "addr:street":"Starrs Rd",
    "iso:country":"CA",
    "sg:address":"73 Starrs Rd",
    "sg:city":"Yarmouth",
    "sg:classifiers":[
        {
            "category":"Recreation",
            "type":"Entertainment"
        }
    ],
    "sg:phone":"+1 902 742 5464",
    "sg:postcode":"B5A 2T6",
    "sg:province":"NS",
    "sg:tags":[
        "parlor",
        "billiard"
    ],
    "wof:name":"King's Billiards",
    "wof:placetype":"venue"
},
  "geometry": {"coordinates":[-66.0966796875,43.8403663635],"type":"Point"}
}