{
  "type": "Feature",
  "properties": {
    "iso:country":"CA",
    "sg:address":"4552 N Access",
    "sg:city":"Chetwynd",
    "sg:classifiers":[
        {
            "category":"Government",
            "subcategory":"Office",
            "type":"Public Place"
        }
    ],
    "sg:phone":"+1 250 788 1862",
    "sg:postcode":"V0C 1J0",
    "sg:province":"BC",
    "sg:tags":[
        "village"
    ],
    "wof:name":"Peace River Area E Economic",
    "wof:placetype":"venue"
},
  "geometry": {"coordinates":[-121.611717224,55.6943588257],"type":"Point"}
}