{
  "type": "Feature",
  "properties": {
    "addr:full":"316 Oxford St W #309 London ON N6H 4L2",
    "addr:housenumber":"316",
    "addr:postcode":"n6h 4l2",
    "addr:street":"Oxford St W # 309",
    "iso:country":"CA",
    "sg:address":"316 Oxford St W #309",
    "sg:city":"London",
    "sg:classifiers":[
        {
            "category":"Recreation",
            "type":"Entertainment"
        }
    ],
    "sg:phone":"+1 519 433 5930",
    "sg:postcode":"N6H 4L2",
    "sg:province":"ON",
    "sg:tags":[
        "paint",
        "game",
        "ball",
        "sport"
    ],
    "wof:name":"Regiment Air Soft",
    "wof:placetype":"venue"
},
  "geometry": {"coordinates":[-81.2777557373,42.9880752563],"type":"Point"}
}