{
  "type": "Feature",
  "properties": {
    "addr:full":"4 Rue Main O Coaticook QC J1A 1P2",
    "addr:housenumber":"4",
    "addr:postcode":"j1a 1p2",
    "addr:street":"Rue Main O",
    "iso:country":"CA",
    "sg:address":"4 Rue Main O",
    "sg:city":"Coaticook",
    "sg:classifiers":[
        {
            "category":"Education",
            "subcategory":"Special Training",
            "type":"Public Place"
        }
    ],
    "sg:phone":"+1 819 849 6161",
    "sg:postcode":"J1A 1P2",
    "sg:province":"QC",
    "sg:tags":[
        "instruction",
        "driving"
    ],
    "wof:name":"Ecole DE Conduite Tecnic",
    "wof:placetype":"venue"
},
  "geometry": {"coordinates":[-71.805222,45.13245],"type":"Point"}
}