{
  "type": "Feature",
  "properties": {
    "iso:country":"CA",
    "sg:address":"PO Box 7",
    "sg:city":"Langdon",
    "sg:classifiers":[
        {
            "category":"Organizations",
            "subcategory":"Religious Organization",
            "type":"Services"
        }
    ],
    "sg:phone":"+1 403 936 5974",
    "sg:postcode":"T0J 1X0",
    "sg:province":"AB",
    "sg:tags":[
        "church"
    ],
    "wof:name":"Langdon Baptist Church",
    "wof:placetype":"venue"
},
  "geometry": {"coordinates":[-113.679519653,50.9691200256],"type":"Point"}
}