{
  "type": "Feature",
  "properties": {
    "addr:full":"Tring-Jonction QC G0N 1X0",
    "addr:postcode":"g0n 1x0",
    "iso:country":"CA",
    "sg:city":"Tring-Jonction",
    "sg:classifiers":[
        {
            "category":"Building & Trades",
            "subcategory":"Construction",
            "type":"Services"
        }
    ],
    "sg:phone":"+1 418 426 2947",
    "sg:postcode":"G0N 1X0",
    "sg:province":"QC",
    "sg:tags":[
        "excavating",
        "contractor"
    ],
    "wof:name":"Lvl Constructions Inc",
    "wof:placetype":"venue"
},
  "geometry": {"coordinates":[-70.99225616459999,46.2721977234],"type":"Point"}
}