{
  "type": "Feature",
  "properties": {
    "iso:country":"CA",
    "sg:address":"112 Peel St",
    "sg:city":"New Hamburg",
    "sg:classifiers":[
        {
            "category":"Food & Beverages",
            "subcategory":"Groceries & Convenience Stores",
            "type":"Retail Goods"
        }
    ],
    "sg:phone":"+1 519 662 2611",
    "sg:postcode":"N3A 1E3",
    "sg:province":"ON",
    "wof:name":"Little Short Stop Stores Ltd",
    "wof:placetype":"venue"
},
  "geometry": {"coordinates":[-80.709351,43.377895],"type":"Point"}
}