{
  "type": "Feature",
  "properties": {
    "addr:full":"460 Copenhagen Rd Thunder Bay ON P7B 6B3",
    "addr:housenumber":"460",
    "addr:postcode":"p7b 6b3",
    "addr:street":"Copenhagen Rd",
    "iso:country":"CA",
    "sg:address":"460 Copenhagen Rd",
    "sg:city":"Thunder Bay",
    "sg:classifiers":[
        {
            "category":"Building & Trades",
            "subcategory":"Construction",
            "type":"Services"
        }
    ],
    "sg:phone":"+1 807 683 8007",
    "sg:postcode":"P7B 6B3",
    "sg:province":"ON",
    "sg:tags":[
        "home",
        "solarium",
        "improvement"
    ],
    "wof:name":"Dave's Sunrooms & Solariums",
    "wof:placetype":"venue"
},
  "geometry": {"coordinates":[-89.18277,48.544014],"type":"Point"}
}