{
  "type": "Feature",
  "properties": {
    "addr:full":"2875 St. George St Vancouver BC V5T 3R8",
    "addr:housenumber":"2875",
    "addr:postcode":"v5t 3r8",
    "addr:street":"St. George St",
    "iso:country":"CA",
    "sg:address":"2875 St. George St",
    "sg:city":"Vancouver",
    "sg:classifiers":[
        {
            "category":"Government",
            "subcategory":"Office",
            "type":"Public Place"
        }
    ],
    "sg:phone":"+1 604 879 8853",
    "sg:postcode":"V5T 3R8",
    "sg:province":"BC",
    "sg:tags":[
        "organization",
        "social",
        "welfare"
    ],
    "wof:name":"Odyssey II",
    "wof:placetype":"venue"
},
  "geometry": {"coordinates":[-123.09303300000001,49.259083],"type":"Point"}
}