{
  "type": "Feature",
  "properties": {
    "addr:full":"7576 Duncan St Powell River BC V8A 1W7",
    "addr:housenumber":"7576",
    "addr:postcode":"v8a 1w7",
    "addr:street":"Duncan St",
    "iso:country":"CA",
    "sg:address":"7576 Duncan St",
    "sg:city":"Powell River",
    "sg:classifiers":[
        {
            "category":"Building & Trades",
            "subcategory":"Equipment Rental",
            "type":"Services"
        }
    ],
    "sg:phone":"+1 604 483 2107",
    "sg:postcode":"V8A 1W7",
    "sg:province":"BC",
    "sg:tags":[
        "aircraft",
        "leasing",
        "charter"
    ],
    "wof:name":"Pacific Coastal Airlines Ltd",
    "wof:placetype":"venue"
},
  "geometry": {"coordinates":[-124.494262695,49.836769104],"type":"Point"}
}