{
  "type": "Feature",
  "properties": {
    "iso:country":"CA",
    "sg:address":"8208 106 St NW",
    "sg:city":"Edmonton",
    "sg:classifiers":[
        {
            "category":"Travel",
            "subcategory":"Hotels & Motels",
            "type":"Entertainment"
        }
    ],
    "sg:phone":"+1 780 434 6111",
    "sg:postcode":"T6E 6R9",
    "sg:province":"AB",
    "wof:name":"Varscona Hotel",
    "wof:placetype":"venue"
},
  "geometry": {"coordinates":[-113.5037,53.518253],"type":"Point"}
}