{
  "type": "Feature",
  "properties": {
    "addr:full":"6640 Royal Ave West Vancouver BC V7W 2B9",
    "addr:housenumber":"6640",
    "addr:postcode":"v7w 2b9",
    "addr:street":"Royal Ave",
    "iso:country":"CA",
    "sg:address":"6640 Royal Ave",
    "sg:city":"West Vancouver",
    "sg:classifiers":[
        {
            "category":"Restaurant",
            "type":"Food & Drink"
        }
    ],
    "sg:phone":"+1 604 921 8865",
    "sg:postcode":"V7W 2B9",
    "sg:province":"BC",
    "wof:name":"Greenhouse",
    "wof:placetype":"venue"
},
  "geometry": {"coordinates":[-123.274429321,49.3739280701],"type":"Point"}
}