{
  "type": "Feature",
  "properties": {
    "addr:full":"3265 Geddes Rd Prince George BC V2K 5G3",
    "addr:housenumber":"3265",
    "addr:postcode":"v2k 5g3",
    "addr:street":"Geddes Rd",
    "iso:country":"CA",
    "sg:address":"3265 Geddes Rd",
    "sg:city":"Prince George",
    "sg:classifiers":[
        {
            "category":"Building & Trades",
            "subcategory":"Electrical",
            "type":"Services"
        }
    ],
    "sg:phone":"+1 250 963 1318",
    "sg:postcode":"V2K 5G3",
    "sg:province":"BC",
    "sg:tags":[
        "electric",
        "contractor"
    ],
    "wof:name":"Milltron Electric Inc",
    "wof:placetype":"venue"
},
  "geometry": {"coordinates":[-122.745087,53.91235],"type":"Point"}
}