{
  "type": "Feature",
  "properties": {
    "addr:full":"Glen Robertson ON K0B 1H0",
    "addr:postcode":"k0b 1h0",
    "addr:street":"Glen Robertson",
    "iso:country":"CA",
    "sg:city":"Glen Robertson",
    "sg:classifiers":[
        {
            "category":"Food & Beverages",
            "subcategory":"Groceries & Convenience Stores",
            "type":"Retail Goods"
        }
    ],
    "sg:phone":"+1 613 874 1094",
    "sg:postcode":"K0B 1H0",
    "sg:province":"ON",
    "sg:tags":[
        "grocer"
    ],
    "wof:name":"Basic Needs",
    "wof:placetype":"venue"
},
  "geometry": {"coordinates":[-74.50190000000001,45.360134],"type":"Point"}
}