{
  "type": "Feature",
  "properties": {
    "iso:country":"CA",
    "sg:address":"1278 Confederation Dr",
    "sg:city":"Port Coquitlam",
    "sg:classifiers":[
        {
            "category":"Social Services",
            "subcategory":"Child Care",
            "type":"Services"
        }
    ],
    "sg:phone":"+1 604 942 2118",
    "sg:postcode":"V3C 6L9",
    "sg:province":"BC",
    "wof:name":"Rainbow Bridge Preschool Ltd",
    "wof:placetype":"venue"
},
  "geometry": {"coordinates":[-122.783241272,49.2380180359],"type":"Point"}
}