{
  "type": "Feature",
  "properties": {
    "iso:country":"CA",
    "sg:address":"504 Fenwick Pl",
    "sg:city":"Burlington",
    "sg:classifiers":[
        {
            "category":"Professional",
            "subcategory":"Art Services",
            "type":"Services"
        }
    ],
    "sg:phone":"+1 905 634 6100",
    "sg:postcode":"L7N 2W8",
    "sg:province":"ON",
    "sg:tags":[
        "graphic",
        "designer"
    ],
    "wof:name":"Jim Haynes Designer",
    "wof:placetype":"venue"
},
  "geometry": {"coordinates":[-79.77964782710001,43.3461494446],"type":"Point"}
}