{
  "type": "Feature",
  "properties": {
    "addr:full":"236 Nepean St Ottawa ON K2P 0B8",
    "addr:housenumber":"236",
    "addr:postcode":"k2p 0b8",
    "addr:street":"Nepean St",
    "iso:country":"CA",
    "sg:address":"236 Nepean St",
    "sg:city":"Ottawa",
    "sg:classifiers":[
        {
            "category":"Shopping",
            "type":"Retail Goods"
        }
    ],
    "sg:phone":"+1 613 230 2799",
    "sg:postcode":"K2P 0B8",
    "sg:province":"ON",
    "sg:tags":[
        "art",
        "gallery",
        "dealer"
    ],
    "wof:name":"Galerie 101 Gallery",
    "wof:placetype":"venue"
},
  "geometry": {"coordinates":[-75.6993713379,45.4165992737],"type":"Point"}
}