{
  "type": "Feature",
  "properties": {
    "iso:country":"CA",
    "sg:address":"236 Nepean St",
    "sg:city":"Ottawa",
    "sg:classifiers":[
        {
            "category":"Shopping",
            "type":"Retail Goods"
        }
    ],
    "sg:phone":"+1 613 230 2799",
    "sg:postcode":"K2P 0B8",
    "sg:province":"ON",
    "sg:tags":[
        "art",
        "gallery",
        "dealer"
    ],
    "wof:name":"Galerie 101 Gallery",
    "wof:placetype":"venue"
},
  "geometry": {"coordinates":[-75.6993713379,45.4165992737],"type":"Point"}
}