{
  "type": "Feature",
  "properties": {
    "addr:full":"50 Blue Springs Dr Waterloo ON N2J 4M4",
    "addr:housenumber":"50",
    "addr:postcode":"n2j 4m4",
    "addr:street":"Blue Springs Dr",
    "iso:country":"CA",
    "sg:address":"50 Blue Springs Dr",
    "sg:city":"Waterloo",
    "sg:classifiers":[
        {
            "category":"Real Estate",
            "subcategory":"Real Estate Operator",
            "type":"Services"
        }
    ],
    "sg:phone":"+1 519 725 5335",
    "sg:postcode":"N2J 4M4",
    "sg:province":"ON",
    "sg:tags":[
        "condominium"
    ],
    "wof:name":"Waterloo Condo 65",
    "wof:placetype":"venue"
},
  "geometry": {"coordinates":[-80.52407100000001,43.488075],"type":"Point"}
}