{
  "type": "Feature",
  "properties": {
    "addr:full":"23 Rte 125 E Saint-Esprit QC J0K 2L0",
    "addr:housenumber":"23",
    "addr:postcode":"j0k 2l0",
    "addr:street":"Rte 125 E",
    "iso:country":"CA",
    "sg:address":"23 Rte 125 E",
    "sg:city":"Saint-Esprit",
    "sg:classifiers":[
        {
            "category":"Professional",
            "subcategory":"Business Services",
            "type":"Services"
        }
    ],
    "sg:phone":"+1 450 588 2939",
    "sg:postcode":"J0K 2L0",
    "sg:province":"QC",
    "sg:tags":[
        "hardware",
        "water",
        "treatment"
    ],
    "wof:name":"Centre DE Pompes Villemaire",
    "wof:placetype":"venue"
},
  "geometry": {"coordinates":[-73.67320251460001,45.9115600586],"type":"Point"}
}