{
  "type": "Feature",
  "properties": {
    "addr:full":"11 Varsity Estates View NW Calgary AB T3B 5G5",
    "addr:housenumber":"11",
    "addr:postcode":"t3b 5g5",
    "addr:street":"Varsity Estates View Nw",
    "iso:country":"CA",
    "sg:address":"11 Varsity Estates View NW",
    "sg:city":"Calgary",
    "sg:classifiers":[
        {
            "category":"Real Estate",
            "subcategory":"Real Estate Operator",
            "type":"Services"
        }
    ],
    "sg:phone":"+1 403 286 7402",
    "sg:postcode":"T3B 5G5",
    "sg:province":"AB",
    "sg:tags":[
        "apartment"
    ],
    "wof:name":"Cathedral Manor Estates",
    "wof:placetype":"venue"
},
  "geometry": {"coordinates":[-114.169021606,51.1052818298],"type":"Point"}
}