{
  "type": "Feature",
  "properties": {
    "addr:full":"1680 Rte Kennedy N Sainte-Marie QC G6E 3P7",
    "addr:housenumber":"1680",
    "addr:postcode":"g6e 3p7",
    "addr:street":"Rte Kennedy N",
    "iso:country":"CA",
    "sg:address":"1680 Rte Kennedy N",
    "sg:city":"Sainte-Marie",
    "sg:classifiers":[
        {
            "category":"Autos & Motor Vehicles",
            "subcategory":"Automobile Sales",
            "type":"Retail Goods"
        }
    ],
    "sg:phone":"+1 418 387 2746",
    "sg:postcode":"G6E 3P7",
    "sg:province":"QC",
    "sg:tags":[
        "car",
        "dealer"
    ],
    "wof:name":"Garage Simard & Freres Auto",
    "wof:placetype":"venue"
},
  "geometry": {"coordinates":[-65.98382599999999,48.172626],"type":"Point"}
}