{
  "type": "Feature",
  "properties": {
    "iso:country":"CA",
    "sg:address":"1405 Glenview Ave",
    "sg:city":"Kelowna",
    "sg:classifiers":[
        {
            "category":"Utilities",
            "subcategory":"Refuse",
            "type":"Services"
        }
    ],
    "sg:phone":"+1 250 868 2424",
    "sg:postcode":"V1Y 3P5",
    "sg:province":"BC",
    "sg:tags":[
        "garbage",
        "collection"
    ],
    "wof:name":"Orchard Valley Disposal",
    "wof:placetype":"venue"
},
  "geometry": {"coordinates":[-119.466186523,49.8931388855],"type":"Point"}
}