{
  "type": "Feature",
  "properties": {
    "addr:full":"117 Richmond Ave N Plumas MB R0J 1P0",
    "addr:housenumber":"117",
    "addr:postcode":"r0j 1p0",
    "addr:street":"Richmond Ave N",
    "iso:country":"CA",
    "sg:address":"117 Richmond Ave N",
    "sg:city":"Plumas",
    "sg:classifiers":[
        {
            "category":"Education",
            "subcategory":"School",
            "type":"Public Place"
        }
    ],
    "sg:phone":"+1 204 386 2250",
    "sg:postcode":"R0J 1P0",
    "sg:province":"MB",
    "wof:name":"Plumas Elementary School",
    "wof:placetype":"venue"
},
  "geometry": {"coordinates":[-99.0863647461,50.3846168518],"type":"Point"}
}