{
  "type": "Feature",
  "properties": {
    "addr:full":"10828 147 St NW Edmonton AB T5N 3E2",
    "addr:housenumber":"10828",
    "addr:postcode":"t5n 3e2",
    "addr:street":"147 St Nw",
    "iso:country":"CA",
    "sg:address":"10828 147 St NW",
    "sg:city":"Edmonton",
    "sg:classifiers":[
        {
            "category":"Social Services",
            "type":"Services"
        }
    ],
    "sg:phone":"+1 780 453 3251",
    "sg:postcode":"T5N 3E2",
    "sg:province":"AB",
    "sg:tags":[
        "counselor",
        "marriage",
        "family"
    ],
    "wof:name":"Community Outreach",
    "wof:placetype":"venue"
},
  "geometry": {"coordinates":[-113.574653626,53.5542144775],"type":"Point"}
}