{
  "type": "Feature",
  "properties": {
    "addr:full":"Montreal QC H4P 2H2",
    "addr:postcode":"h4p 2h2",
    "iso:country":"CA",
    "sg:city":"Montreal",
    "sg:classifiers":[
        {
            "category":"Real Estate",
            "subcategory":"Architect",
            "type":"Services"
        }
    ],
    "sg:phone":"+1 514 344 9411",
    "sg:postcode":"H4P 2H2",
    "sg:province":"QC",
    "wof:name":"Somerset Development Ltd",
    "wof:placetype":"venue"
},
  "geometry": {"coordinates":[-73.65715789790001,45.4974937439],"type":"Point"}
}