{
  "type": "Feature",
  "properties": {
    "addr:full":"1020 12th Ave SW Moose Jaw SK S6H 5X8",
    "addr:housenumber":"1020",
    "addr:postcode":"s6h 5x8",
    "addr:street":"12Th Ave Sw",
    "iso:country":"CA",
    "sg:address":"1020 12th Ave SW",
    "sg:city":"Moose Jaw",
    "sg:classifiers":[
        {
            "category":"Education",
            "subcategory":"School",
            "type":"Public Place"
        }
    ],
    "sg:phone":"+1 306 694 1622",
    "sg:postcode":"S6H 5X8",
    "sg:province":"SK",
    "wof:name":"Sacred Heart School",
    "wof:placetype":"venue"
},
  "geometry": {"coordinates":[-105.568832398,50.3789596558],"type":"Point"}
}