{
  "type": "Feature",
  "properties": {
    "iso:country":"CA",
    "sg:city":"Vancouver",
    "sg:classifiers":[
        {
            "category":"Professional",
            "subcategory":"Business Services",
            "type":"Services"
        }
    ],
    "sg:phone":"+1 604 876 4786",
    "sg:postcode":"V5Y 3T7",
    "sg:province":"BC",
    "sg:tags":[
        "foreground",
        "music"
    ],
    "wof:name":"Isun Music Svc",
    "wof:placetype":"venue"
},
  "geometry": {"coordinates":[-123.113418579,49.2683296204],"type":"Point"}
}