{
  "type": "Feature",
  "properties": {
    "addr:full":"PO Box 205 Irricana AB T0M 1B0",
    "addr:housenumber":"po",
    "addr:postcode":"t0m 1b0",
    "addr:street":"Box 205 Irricana",
    "iso:country":"CA",
    "sg:address":"PO Box 205",
    "sg:city":"Irricana",
    "sg:classifiers":[
        {
            "category":"Home & Garden",
            "subcategory":"Furniture",
            "type":"Retail Goods"
        }
    ],
    "sg:phone":"+1 403 935 4338",
    "sg:postcode":"T0M 1B0",
    "sg:province":"AB",
    "sg:tags":[
        "equipment",
        "kitchen",
        "cabinet"
    ],
    "wof:name":"Kitchen Visions",
    "wof:placetype":"venue"
},
  "geometry": {"coordinates":[-113.591415,51.325047],"type":"Point"}
}