{
  "type": "Feature",
  "properties": {
    "addr:full":"891 Rue Principale # 101 Saint-Amable QC J0L 1N0",
    "addr:housenumber":"891",
    "addr:postcode":"j0l 1n0",
    "addr:street":"Rue Principale # 101",
    "iso:country":"CA",
    "sg:address":"891 Rue Principale # 101",
    "sg:city":"Saint-Amable",
    "sg:classifiers":[
        {
            "category":"Restaurant",
            "type":"Food & Drink"
        }
    ],
    "sg:phone":"+1 450 649 0554",
    "sg:postcode":"J0L 1N0",
    "sg:province":"QC",
    "wof:name":"Casse-Croute Ladine",
    "wof:placetype":"venue"
},
  "geometry": {"coordinates":[-73.2980422974,45.6502418518],"type":"Point"}
}