{
  "type": "Feature",
  "properties": {
    "addr:full":"2212 Island Hwy E Nanoose Bay BC V9P 9A8",
    "addr:housenumber":"2212",
    "addr:postcode":"v9p 9a8",
    "addr:street":"Island Hwy E",
    "iso:country":"CA",
    "sg:address":"2212 Island Hwy E",
    "sg:city":"Nanoose Bay",
    "sg:classifiers":[
        {
            "category":"Travel",
            "subcategory":"Campground",
            "type":"Entertainment"
        }
    ],
    "sg:phone":"+1 250 468 7186",
    "sg:postcode":"V9P 9A8",
    "sg:province":"BC",
    "wof:name":"Nanoose Creek Campground",
    "wof:placetype":"venue"
},
  "geometry": {"coordinates":[-124.203217,49.263474],"type":"Point"}
}