{
  "type": "Feature",
  "properties": {
    "addr:full":"3504 Granton Rd New Glasgow NS B2H 5C6",
    "addr:housenumber":"3504",
    "addr:postcode":"b2h 5c6",
    "addr:street":"Granton Rd",
    "iso:country":"CA",
    "sg:address":"3504 Granton Rd",
    "sg:city":"New Glasgow",
    "sg:classifiers":[
        {
            "category":"Retail",
            "subcategory":"Animal Services",
            "type":"Services"
        }
    ],
    "sg:phone":"+1 902 396 3595",
    "sg:postcode":"B2H 5C6",
    "sg:province":"NS",
    "sg:tags":[
        "pet",
        "boarding",
        "sitting"
    ],
    "wof:name":"Spca Shelter",
    "wof:placetype":"venue"
},
  "geometry": {"coordinates":[-62.643414,45.591839],"type":"Point"}
}