{
  "type": "Feature",
  "properties": {
    "addr:full":"3596 Av Barclay Montreal QC H3S 1K4",
    "addr:housenumber":"3596",
    "addr:postcode":"h3s 1k4",
    "addr:street":"Av Barclay",
    "iso:country":"CA",
    "sg:address":"3596 Av Barclay",
    "sg:city":"Montreal",
    "sg:classifiers":[
        {
            "category":"Food & Beverages",
            "subcategory":"Groceries & Convenience Stores",
            "type":"Retail Goods"
        }
    ],
    "sg:phone":"+1 514 737 0612",
    "sg:postcode":"H3S 1K4",
    "sg:province":"QC",
    "sg:tags":[
        "grocer"
    ],
    "wof:name":"Marche Alexandre",
    "wof:placetype":"venue"
},
  "geometry": {"coordinates":[-73.635017,45.502995],"type":"Point"}
}