{
  "type": "Feature",
  "properties": {
    "addr:full":"110 Dowty Rd Ajax ON L1S 2G4",
    "addr:housenumber":"110",
    "addr:postcode":"l1s 2g4",
    "addr:street":"Dowty Rd",
    "iso:country":"CA",
    "sg:address":"110 Dowty Rd",
    "sg:city":"Ajax",
    "sg:classifiers":[
        {
            "category":"Bars & Pubs",
            "type":"Food & Drink"
        }
    ],
    "sg:phone":"+1 905 683 3587",
    "sg:postcode":"L1S 2G4",
    "sg:province":"ON",
    "sg:tags":[
        "club",
        "night"
    ],
    "wof:name":"Chameleon Cafe",
    "wof:placetype":"venue"
},
  "geometry": {"coordinates":[-79.0289382935,43.8478050232],"type":"Point"}
}