{
  "type": "Feature",
  "properties": {
    "addr:full":"1085 St Mary's Rd Winnipeg MB R2M 3T2",
    "addr:housenumber":"1085",
    "addr:postcode":"r2m 3t2",
    "addr:street":"St Mary'S Rd",
    "iso:country":"CA",
    "sg:address":"1085 St Mary's Rd",
    "sg:city":"Winnipeg",
    "sg:classifiers":[
        {
            "category":"Sports & Exercise",
            "subcategory":"Bowling",
            "type":"Entertainment"
        }
    ],
    "sg:phone":"+1 204 256 7333",
    "sg:postcode":"R2M 3T2",
    "sg:province":"MB",
    "sg:tags":[
        "center"
    ],
    "wof:name":"Dakota Bowling Ltd",
    "wof:placetype":"venue"
},
  "geometry": {"coordinates":[-97.112419,49.836533],"type":"Point"}
}