{
  "type": "Feature",
  "properties": {
    "addr:full":"59 Queen St Langton ON N0E 1G0",
    "addr:housenumber":"59",
    "addr:postcode":"n0e 1g0",
    "addr:street":"Queen St",
    "iso:country":"CA",
    "sg:address":"59 Queen St",
    "sg:city":"Langton",
    "sg:classifiers":[
        {
            "category":"Wholesale",
            "subcategory":"Machinery & Supplies",
            "type":"Manufacturing & Wholesale Goods"
        }
    ],
    "sg:phone":"+1 519 875 4439",
    "sg:postcode":"N0E 1G0",
    "sg:province":"ON",
    "sg:tags":[
        "farm",
        "equipment",
        "lawn",
        "mower"
    ],
    "wof:name":"Sinnaeve Equipment Ctr",
    "wof:placetype":"venue"
},
  "geometry": {"coordinates":[-80.579781,42.744827],"type":"Point"}
}