{
  "type": "Feature",
  "properties": {
    "addr:full":"4809 50 Ave Wetaskiwin AB T9A 0S1",
    "addr:housenumber":"4809",
    "addr:postcode":"t9a 0s1",
    "addr:street":"50 Ave",
    "iso:country":"CA",
    "sg:address":"4809 50 Ave",
    "sg:city":"Wetaskiwin",
    "sg:classifiers":[
        {
            "category":"Home & Garden",
            "subcategory":"Household Appliances",
            "type":"Retail Goods"
        }
    ],
    "sg:phone":"+1 780 352 6511",
    "sg:postcode":"T9A 0S1",
    "sg:province":"AB",
    "sg:tags":[
        "cleaners",
        "vacuum"
    ],
    "wof:name":"Wetaskiwin Delux Vacuum",
    "wof:placetype":"venue"
},
  "geometry": {"coordinates":[-113.37153600000001,52.969234],"type":"Point"}
}