{
  "type": "Feature",
  "properties": {
    "addr:full":"4230 Rue Notre-Dame Est Sainte-Marthe-Du-Cap QC G8V 1Z2",
    "addr:housenumber":"4230",
    "addr:postcode":"g8v 1z2",
    "addr:street":"Rue Notre-Dame Est",
    "iso:country":"CA",
    "sg:address":"4230 Rue Notre-Dame Est",
    "sg:city":"Sainte-Marthe-Du-Cap",
    "sg:classifiers":[
        {
            "category":"Retail",
            "subcategory":"Auto Repair",
            "type":"Services"
        }
    ],
    "sg:phone":"+1 819 374 8420",
    "sg:postcode":"G8V 1Z2",
    "sg:province":"QC",
    "sg:tags":[
        "repairing",
        "automobile"
    ],
    "wof:name":"Normandin E & Fils",
    "wof:placetype":"venue"
},
  "geometry": {"coordinates":[-72.430161,46.406414],"type":"Point"}
}