{
  "type": "Feature",
  "properties": {
    "addr:full":"Chicoutimi QC G7H 6B9",
    "addr:postcode":"g7h 6b9",
    "iso:country":"CA",
    "sg:city":"Chicoutimi",
    "sg:classifiers":[
        {
            "category":"Health Services",
            "subcategory":"Doctor",
            "type":"Services"
        }
    ],
    "sg:phone":"+1 418 549 3573",
    "sg:postcode":"G7H 6B9",
    "sg:province":"QC",
    "sg:tags":[
        "clinic",
        "dentist"
    ],
    "wof:name":"Clinique Dentaire Mc Nicoll",
    "wof:placetype":"venue"
},
  "geometry": {"coordinates":[-71.11171,48.306122],"type":"Point"}
}