{
  "type": "Feature",
  "properties": {
    "addr:full":"492 Kipawa Temiscaming QC J0Z 3R0",
    "addr:housenumber":"492",
    "addr:postcode":"j0z 3r0",
    "addr:street":"Kipawa Temiscaming",
    "iso:country":"CA",
    "sg:address":"492 Kipawa",
    "sg:city":"Temiscaming",
    "sg:classifiers":[
        {
            "category":"Professional",
            "subcategory":"Computer Services",
            "type":"Services"
        }
    ],
    "sg:phone":"+1 819 627 9090",
    "sg:postcode":"J0Z 3R0",
    "sg:province":"QC",
    "sg:tags":[
        "television",
        "internet"
    ],
    "wof:name":"Cablevision Du Norde DE Quebec",
    "wof:placetype":"venue"
},
  "geometry": {"coordinates":[-79.0946884155,46.7227554321],"type":"Point"}
}