{
  "type": "Feature",
  "properties": {
    "addr:full":"400 1st St N Wakaw SK S0K 4P0",
    "addr:housenumber":"400",
    "addr:postcode":"s0k 4p0",
    "addr:street":"1St St N",
    "iso:country":"CA",
    "sg:address":"400 1st St N",
    "sg:city":"Wakaw",
    "sg:classifiers":[
        {
            "category":"Health Services",
            "subcategory":"Nursing And Care Facility",
            "type":"Services"
        }
    ],
    "sg:phone":"+1 306 233 4621",
    "sg:postcode":"S0K 4P0",
    "sg:province":"SK",
    "sg:tags":[
        "home",
        "convalescent"
    ],
    "wof:name":"Lakeview Pioneer Lodge",
    "wof:placetype":"venue"
},
  "geometry": {"coordinates":[-105.74270629900001,52.6529502869],"type":"Point"}
}