{
  "type": "Feature",
  "properties": {
    "addr:full":"Mississauga ON L5L 5Z3",
    "addr:postcode":"l5l 5z3",
    "iso:country":"CA",
    "sg:city":"Mississauga",
    "sg:classifiers":[
        {
            "category":"Wholesale",
            "subcategory":"Machinery & Supplies",
            "type":"Manufacturing & Wholesale Goods"
        }
    ],
    "sg:phone":"+1 905 828 9900",
    "sg:postcode":"L5L 5Z3",
    "sg:province":"ON",
    "sg:tags":[
        "valve"
    ],
    "wof:name":"Process & Steam Specialties",
    "wof:placetype":"venue"
},
  "geometry": {"coordinates":[-79.7191390991,43.5276298523],"type":"Point"}
}