{
  "type": "Feature",
  "properties": {
    "addr:full":"72 Main St Rexton NB E4W 2B2",
    "addr:housenumber":"72",
    "addr:postcode":"e4w 2b2",
    "addr:street":"Main St",
    "iso:country":"CA",
    "sg:address":"72 Main St",
    "sg:city":"Rexton",
    "sg:classifiers":[
        {
            "category":"Food & Beverages",
            "subcategory":"Groceries & Convenience Stores",
            "type":"Retail Goods"
        }
    ],
    "sg:phone":"+1 506 523 4219",
    "sg:postcode":"E4W 2B2",
    "sg:province":"NB",
    "sg:tags":[
        "grocer"
    ],
    "wof:name":"Foodland",
    "wof:placetype":"venue"
},
  "geometry": {"coordinates":[-64.87754099999999,46.657318],"type":"Point"}
}