{
  "type": "Feature",
  "properties": {
    "addr:full":"9881 Hwy 1 Saulnierville NS B0W 2Z0",
    "addr:housenumber":"9881",
    "addr:postcode":"b0w 2z0",
    "addr:street":"Hwy 1",
    "iso:country":"CA",
    "sg:address":"9881 Hwy 1",
    "sg:city":"Saulnierville",
    "sg:classifiers":[
        {
            "category":"Food & Beverages",
            "subcategory":"Specialty",
            "type":"Retail Goods"
        }
    ],
    "sg:phone":"+1 902 769 3199",
    "sg:postcode":"B0W 2Z0",
    "sg:province":"NS",
    "sg:tags":[
        "health",
        "diet"
    ],
    "wof:name":"Supernutrition",
    "wof:placetype":"venue"
},
  "geometry": {"coordinates":[-66.1291885376,44.254650116],"type":"Point"}
}