{
  "type": "Feature",
  "properties": {
    "addr:full":"310 Alexander St # B Whitehorse YT Y1A 2L6",
    "addr:housenumber":"310",
    "addr:postcode":"y1a 2l6",
    "addr:street":"Alexander St # B",
    "iso:country":"CA",
    "sg:address":"310 Alexander St # B",
    "sg:city":"Whitehorse",
    "sg:classifiers":[
        {
            "category":"Home & Garden",
            "subcategory":"Household Appliances",
            "type":"Retail Goods"
        }
    ],
    "sg:phone":"+1 867 668 3592",
    "sg:postcode":"Y1A 2L6",
    "sg:province":"YT",
    "wof:name":"Mobile Domestic Appliance Rpr",
    "wof:placetype":"venue"
},
  "geometry": {"coordinates":[-135.05766299999999,60.723156],"type":"Point"}
}