{
  "type": "Feature",
  "properties": {
    "iso:country":"CA",
    "sg:city":"Two Hills",
    "sg:classifiers":[
        {
            "category":"Autos & Motor Vehicles",
            "subcategory":"Auto Supplies",
            "type":"Retail Goods"
        }
    ],
    "sg:phone":"+1 780 657 0087",
    "sg:postcode":"T0B 4K0",
    "sg:province":"AB",
    "sg:tags":[
        "tire"
    ],
    "wof:name":"Two Hills Tire & Mechanical",
    "wof:placetype":"venue"
},
  "geometry": {"coordinates":[-111.746437073,53.7073364258],"type":"Point"}
}