{
  "type": "Feature",
  "properties": {
    "addr:full":"840 Sloane St Woodstock ON N4S 7V3",
    "addr:housenumber":"840",
    "addr:postcode":"n4s 7v3",
    "addr:street":"Sloane St",
    "iso:country":"CA",
    "sg:address":"840 Sloane St",
    "sg:city":"Woodstock",
    "sg:classifiers":[
        {
            "category":"Education",
            "subcategory":"School",
            "type":"Public Place"
        }
    ],
    "sg:phone":"+1 519 537 2642",
    "sg:postcode":"N4S 7V3",
    "sg:province":"ON",
    "wof:name":"Hillcrest Public School",
    "wof:placetype":"venue"
},
  "geometry": {"coordinates":[-80.74205000000001,43.140858],"type":"Point"}
}