{
  "type": "Feature",
  "properties": {
    "addr:full":"640 Albert St Regina SK S4R 2P3",
    "addr:housenumber":"640",
    "addr:postcode":"s4r 2p3",
    "addr:street":"Albert St",
    "iso:country":"CA",
    "sg:address":"640 Albert St",
    "sg:city":"Regina",
    "sg:classifiers":[
        {
            "category":"Building & Trades",
            "subcategory":"Construction",
            "type":"Services"
        }
    ],
    "sg:phone":"+1 306 757 4775",
    "sg:postcode":"S4R 2P3",
    "sg:province":"SK",
    "sg:tags":[
        "refinishing",
        "supply",
        "floor",
        "laying",
        "resurfacing",
        "party"
    ],
    "wof:name":"Prairieland Rental Ctr",
    "wof:placetype":"venue"
},
  "geometry": {"coordinates":[-104.618438721,50.4686737061],"type":"Point"}
}