{
  "type": "Feature",
  "properties": {
    "iso:country":"CA",
    "sg:address":"1485 Portage Ave",
    "sg:city":"Winnipeg",
    "sg:classifiers":[
        {
            "category":"Shopping",
            "subcategory":"Computers & Home Electronics",
            "type":"Retail Goods"
        }
    ],
    "sg:phone":"+1 204 774 0554",
    "sg:postcode":"R3G 0W4",
    "sg:province":"MB",
    "sg:tags":[
        "equipment",
        "dealer"
    ],
    "wof:name":"Island Ink-Jet",
    "wof:placetype":"venue"
},
  "geometry": {"coordinates":[-97.19825,49.88102],"type":"Point"}
}