{
  "type": "Feature",
  "properties": {
    "iso:country":"CA",
    "sg:city":"Grande Cache",
    "sg:classifiers":[
        {
            "category":"Social Services",
            "type":"Services"
        }
    ],
    "sg:phone":"+1 780 827 3800",
    "sg:postcode":"T0E 0Y0",
    "sg:province":"AB",
    "sg:tags":[
        "organization",
        "welfare"
    ],
    "wof:name":"Native Counselling Svc-Alberta",
    "wof:placetype":"venue"
},
  "geometry": {"coordinates":[-119.112548828,53.8888053894],"type":"Point"}
}