{
  "type": "Feature",
  "properties": {
    "addr:full":"7400 132 St Surrey BC V3W 4M7",
    "addr:housenumber":"7400",
    "addr:postcode":"v3w 4m7",
    "addr:street":"132 St",
    "iso:country":"CA",
    "sg:address":"7400 132 St",
    "sg:city":"Surrey",
    "sg:classifiers":[
        {
            "category":"Manufacturing",
            "subcategory":"Food",
            "type":"Manufacturing & Wholesale Goods"
        }
    ],
    "sg:phone":"+1 604 590 5757",
    "sg:postcode":"V3W 4M7",
    "sg:province":"BC",
    "sg:tags":[
        "product",
        "manufacturer"
    ],
    "wof:name":"Campac",
    "wof:placetype":"venue"
},
  "geometry": {"coordinates":[-122.85675000000001,49.140961],"type":"Point"}
}