{
  "type": "Feature",
  "properties": {
    "addr:full":"Brossard QC J4W 2S8",
    "addr:postcode":"j4w 2s8",
    "iso:country":"CA",
    "sg:city":"Brossard",
    "sg:classifiers":[
        {
            "category":"Personal",
            "subcategory":"Beauty Salon",
            "type":"Services"
        }
    ],
    "sg:phone":"+1 450 923 3823",
    "sg:postcode":"J4W 2S8",
    "sg:province":"QC",
    "wof:name":"G Classique Coiffure Inc",
    "wof:placetype":"venue"
},
  "geometry": {"coordinates":[-73.46979522709999,45.4669418335],"type":"Point"}
}