{
  "type": "Feature",
  "properties": {
    "iso:country":"CA",
    "sg:address":"101 Public Rd W",
    "sg:city":"Mariapolis",
    "sg:classifiers":[
        {
            "category":"Travel",
            "subcategory":"Hotels & Motels",
            "type":"Entertainment"
        }
    ],
    "sg:phone":"+1 204 836 2758",
    "sg:postcode":"R0K 1K0",
    "sg:province":"MB",
    "wof:name":"Mariapolis Motor Hotel",
    "wof:placetype":"venue"
},
  "geometry": {"coordinates":[-98.9888839722,49.3619499207],"type":"Point"}
}