{
  "type": "Feature",
  "properties": {
    "addr:full":"180 Rue Saint-Charles O Longueuil QC J4H 1C9",
    "addr:housenumber":"180",
    "addr:postcode":"j4h 1c9",
    "addr:street":"Rue Saint-Charles O",
    "iso:country":"CA",
    "sg:address":"180 Rue Saint-Charles O",
    "sg:city":"Longueuil",
    "sg:classifiers":[
        {
            "category":"Retail",
            "subcategory":"Laundry & Dry Cleaning",
            "type":"Services"
        }
    ],
    "sg:phone":"+1 450 928 9055",
    "sg:postcode":"J4H 1C9",
    "sg:province":"QC",
    "sg:tags":[
        "cleaners"
    ],
    "wof:name":"Nettoyeur Excellence",
    "wof:placetype":"venue"
},
  "geometry": {"coordinates":[-73.50664500000001,45.542721],"type":"Point"}
}