{
  "type": "Feature",
  "properties": {
    "addr:full":"49 Dunlop St W Barrie ON L4N 1A3",
    "addr:housenumber":"49",
    "addr:postcode":"l4n 1a3",
    "addr:street":"Dunlop St W",
    "iso:country":"CA",
    "sg:address":"49 Dunlop St W",
    "sg:city":"Barrie",
    "sg:classifiers":[
        {
            "category":"Personal",
            "subcategory":"Barber",
            "type":"Services"
        }
    ],
    "sg:phone":"+1 705 728 2642",
    "sg:postcode":"L4N 1A3",
    "sg:province":"ON",
    "wof:name":"Mike's Barbershop & Styling",
    "wof:placetype":"venue"
},
  "geometry": {"coordinates":[-79.691597,44.388466],"type":"Point"}
}