{
  "type": "Feature",
  "properties": {
    "addr:full":"4412 10th Ave New Hazelton BC V0J 2J0",
    "addr:housenumber":"4412",
    "addr:postcode":"v0j 2j0",
    "addr:street":"10Th Ave",
    "iso:country":"CA",
    "sg:address":"4412 10th Ave",
    "sg:city":"New Hazelton",
    "sg:classifiers":[
        {
            "category":"Restaurant",
            "type":"Food & Drink"
        }
    ],
    "sg:phone":"+1 250 842 6767",
    "sg:postcode":"V0J 2J0",
    "sg:province":"BC",
    "wof:name":"Totem Cafe",
    "wof:placetype":"venue"
},
  "geometry": {"coordinates":[-127.586037,55.246452],"type":"Point"}
}