{
  "type": "Feature",
  "properties": {
    "iso:country":"CA",
    "sg:address":"205 Erie Ave",
    "sg:city":"Brantford",
    "sg:classifiers":[
        {
            "category":"Food & Beverages",
            "subcategory":"Groceries & Convenience Stores",
            "type":"Retail Goods"
        }
    ],
    "sg:phone":"+1 519 752 1001",
    "sg:postcode":"N3S 2H1",
    "sg:province":"ON",
    "wof:name":"Mac's Convenience Stores Ltd",
    "wof:placetype":"venue"
},
  "geometry": {"coordinates":[-80.25582900000001,43.126667],"type":"Point"}
}