{
  "type": "Feature",
  "properties": {
    "addr:full":"424 Esplanade W North Vancouver BC V7M 1A7",
    "addr:housenumber":"424",
    "addr:postcode":"v7m 1a7",
    "addr:street":"Esplanade W",
    "iso:country":"CA",
    "sg:address":"424 Esplanade W",
    "sg:city":"North Vancouver",
    "sg:classifiers":[
        {
            "category":"Organizations",
            "subcategory":"Religious Organization",
            "type":"Services"
        }
    ],
    "sg:phone":"+1 604 984 6709",
    "sg:postcode":"V7M 1A7",
    "sg:province":"BC",
    "sg:tags":[
        "church"
    ],
    "wof:name":"St Paul's Indian Catholic Chr",
    "wof:placetype":"venue"
},
  "geometry": {"coordinates":[-123.087845,49.315521],"type":"Point"}
}