{
  "type": "Feature",
  "properties": {
    "iso:country":"CA",
    "sg:address":"740 Dufferin St",
    "sg:city":"Toronto",
    "sg:classifiers":[
        {
            "category":"Food & Beverages",
            "subcategory":"Groceries & Convenience Stores",
            "type":"Retail Goods"
        }
    ],
    "sg:phone":"+1 416 535 1087",
    "sg:postcode":"M6H 3K6",
    "sg:province":"ON",
    "wof:name":"Starbank Convenience",
    "wof:placetype":"venue"
},
  "geometry": {"coordinates":[-79.4327163696,43.6526298523],"type":"Point"}
}