{
  "type": "Feature",
  "properties": {
    "addr:full":"Winnipeg MB R2M 5G8",
    "addr:postcode":"r2m 5g8",
    "iso:country":"CA",
    "sg:city":"Winnipeg",
    "sg:classifiers":[
        {
            "category":"Cinema",
            "subcategory":"Movie Rental",
            "type":"Entertainment"
        }
    ],
    "sg:phone":"+1 204 257 1234",
    "sg:postcode":"R2M 5G8",
    "sg:province":"MB",
    "sg:tags":[
        "video",
        "game",
        "tape",
        "leasing"
    ],
    "wof:name":"Rogers Video",
    "wof:placetype":"venue"
},
  "geometry": {"coordinates":[-97.1101074219,49.8262252808],"type":"Point"}
}