{
  "type": "Feature",
  "properties": {
    "iso:country":"CA",
    "sg:address":"10 Hoover St",
    "sg:city":"Lanigan",
    "sg:classifiers":[
        {
            "category":"Government",
            "subcategory":"Office",
            "type":"Public Place"
        }
    ],
    "sg:phone":"+1 306 365 3260",
    "sg:postcode":"S0K 2M0",
    "sg:province":"SK",
    "sg:tags":[
        "village"
    ],
    "wof:name":"Lanigan Water Treatment Plant",
    "wof:placetype":"venue"
},
  "geometry": {"coordinates":[-105.02878570599999,51.851650238],"type":"Point"}
}