{
  "type": "Feature",
  "properties": {
    "iso:country":"CA",
    "sg:address":"4145 Burnside Line",
    "sg:city":"Orillia",
    "sg:classifiers":[
        {
            "category":"Real Estate",
            "subcategory":"Surveying",
            "type":"Services"
        }
    ],
    "sg:phone":"+1 705 329 0765",
    "sg:postcode":"L3V 6H4",
    "sg:province":"ON",
    "sg:tags":[
        "surveyor"
    ],
    "wof:name":"C T Strongman Surveying Ltd",
    "wof:placetype":"venue"
},
  "geometry": {"coordinates":[-79.435043335,44.6268310547],"type":"Point"}
}