{
  "type": "Feature",
  "properties": {
    "addr:full":"747 7th Ave W Owen Sound ON N4K 5J8",
    "addr:housenumber":"747",
    "addr:postcode":"n4k 5j8",
    "addr:street":"7Th Ave W",
    "iso:country":"CA",
    "sg:address":"747 7th Ave W",
    "sg:city":"Owen Sound",
    "sg:classifiers":[
        {
            "category":"Building & Trades",
            "subcategory":"Electrical",
            "type":"Services"
        }
    ],
    "sg:phone":"+1 519 371 7257",
    "sg:postcode":"N4K 5J8",
    "sg:province":"ON",
    "sg:tags":[
        "electric",
        "contractor"
    ],
    "wof:name":"Dunn's Electric",
    "wof:placetype":"venue"
},
  "geometry": {"coordinates":[-80.953979,44.5616],"type":"Point"}
}