{
  "type": "Feature",
  "properties": {
    "addr:full":"3215 Ch Sainte-Foy Sainte-Foy QC G1X 1R6",
    "addr:postcode":"3215;g1x 1r6",
    "addr:street":"Ch Sainte-Foy",
    "iso:country":"CA",
    "sg:address":"3215 Ch Sainte-Foy",
    "sg:city":"Sainte-Foy",
    "sg:classifiers":[
        {
            "category":"Home & Garden",
            "subcategory":"Building Materials",
            "type":"Retail Goods"
        }
    ],
    "sg:phone":"+1 418 653 2777",
    "sg:postcode":"G1X 1R6",
    "sg:province":"QC",
    "sg:tags":[
        "glass",
        "window",
        "plate"
    ],
    "wof:name":"Docteur Du Pare-Brise",
    "wof:placetype":"venue"
},
  "geometry": {"coordinates":[-71.2917633057,46.7692108154],"type":"Point"}
}