{
  "type": "Feature",
  "properties": {
    "addr:full":"2151 Boul Lapiniere #A6 Brossard QC J4W 2T5",
    "addr:housenumber":"2151",
    "addr:postcode":"j4w 2t5",
    "addr:street":"Boul Lapiniere # A6",
    "iso:country":"CA",
    "sg:address":"2151 Boul Lapiniere #A6",
    "sg:city":"Brossard",
    "sg:classifiers":[
        {
            "category":"Shopping",
            "subcategory":"Clothing, Apparel, & Fashions",
            "type":"Retail Goods"
        }
    ],
    "sg:phone":"+1 450 465 6474",
    "sg:postcode":"J4W 2T5",
    "sg:province":"QC",
    "sg:tags":[
        "item",
        "boutique"
    ],
    "wof:name":"Boutique USA",
    "wof:placetype":"venue"
},
  "geometry": {"coordinates":[-73.4703216553,45.4733963013],"type":"Point"}
}