{
  "type": "Feature",
  "properties": {
    "addr:full":"5 Brookshire Crt Bedford NS B4A 4E2",
    "addr:housenumber":"5",
    "addr:postcode":"b4a 4e2",
    "addr:street":"Brookshire Crt",
    "iso:country":"CA",
    "sg:address":"5 Brookshire Crt",
    "sg:city":"Bedford",
    "sg:classifiers":[
        {
            "category":"Education",
            "subcategory":"School",
            "type":"Public Place"
        }
    ],
    "sg:phone":"+1 902 835 2384",
    "sg:postcode":"B4A 4E2",
    "sg:province":"NS",
    "wof:name":"Bedford Elementary Academy",
    "wof:placetype":"venue"
},
  "geometry": {"coordinates":[-63.6875495911,44.7211799622],"type":"Point"}
}