{
  "type": "Feature",
  "properties": {
    "addr:full":"168 Chapel St Cobourg ON K9A 1J3",
    "addr:housenumber":"168",
    "addr:postcode":"k9a 1j3",
    "addr:street":"Chapel St",
    "iso:country":"CA",
    "sg:address":"168 Chapel St",
    "sg:city":"Cobourg",
    "sg:classifiers":[
        {
            "category":"Social Services",
            "type":"Services"
        }
    ],
    "sg:phone":"+1 905 373 4842",
    "sg:postcode":"K9A 1J3",
    "sg:province":"ON",
    "sg:tags":[
        "counselor",
        "marriage",
        "family"
    ],
    "wof:name":"Tranquility Place Counselling",
    "wof:placetype":"venue"
},
  "geometry": {"coordinates":[-78.1602935791,43.9630775452],"type":"Point"}
}