{
  "type": "Feature",
  "properties": {
    "iso:country":"CA",
    "sg:address":"550 Boul Cure-Labelle",
    "sg:city":"Sainte-Rose",
    "sg:classifiers":[
        {
            "category":"Restaurant",
            "type":"Food & Drink"
        }
    ],
    "sg:phone":"+1 450 967 9905",
    "sg:postcode":"H7L 4V6",
    "sg:province":"QC",
    "sg:tags":[
        "out"
    ],
    "wof:name":"Domino's Pizza",
    "wof:placetype":"venue"
},
  "geometry": {"coordinates":[-73.786385,45.591366],"type":"Point"}
}