{
  "type": "Feature",
  "properties": {
    "addr:full":"401 Kincardine Ave Kincardine ON N2Z 2V5",
    "addr:housenumber":"401",
    "addr:postcode":"n2z 2v5",
    "addr:street":"Kincardine Ave",
    "iso:country":"CA",
    "sg:address":"401 Kincardine Ave",
    "sg:city":"Kincardine",
    "sg:classifiers":[
        {
            "category":"Restaurant",
            "type":"Food & Drink"
        }
    ],
    "sg:phone":"+1 519 396 4233",
    "sg:postcode":"N2Z 2V5",
    "sg:province":"ON",
    "wof:name":"Cuyler's Family Restaurant",
    "wof:placetype":"venue"
},
  "geometry": {"coordinates":[-81.640472,44.164425],"type":"Point"}
}