{
  "type": "Feature",
  "properties": {
    "addr:full":"Range Rd 232 & Township Rd 584 Thorhild AB T0A 3J0",
    "addr:postcode":"t0a 3j0",
    "addr:street":"Range Rd 232 & Township Rd 584",
    "iso:country":"CA",
    "sg:address":"Range Rd 232 & Township Rd 584",
    "sg:city":"Thorhild",
    "sg:classifiers":[
        {
            "category":"Organizations",
            "subcategory":"Labor Organization",
            "type":"Services"
        }
    ],
    "sg:phone":"+1 780 942 2050",
    "sg:postcode":"T0A 3J0",
    "sg:province":"AB",
    "wof:name":"Operating Engineers Training",
    "wof:placetype":"venue"
},
  "geometry": {"coordinates":[-113.322647,54.036236],"type":"Point"}
}