{
  "type": "Feature",
  "properties": {
    "addr:full":"2501 Guelph Line # 6 Burlington ON L7M 2A3",
    "addr:housenumber":"2501",
    "addr:postcode":"l7m 2a3",
    "addr:street":"Guelph Line # 6",
    "iso:country":"CA",
    "sg:address":"2501 Guelph Line # 6",
    "sg:city":"Burlington",
    "sg:classifiers":[
        {
            "category":"Restaurant",
            "type":"Food & Drink"
        }
    ],
    "sg:phone":"+1 905 332 6203",
    "sg:postcode":"L7M 2A3",
    "sg:province":"ON",
    "wof:name":"Boston Fish & Chips",
    "wof:placetype":"venue"
},
  "geometry": {"coordinates":[-79.839752,43.37772],"type":"Point"}
}