{
  "type": "Feature",
  "properties": {
    "iso:country":"CA",
    "sg:address":"215 Cayley",
    "sg:city":"Walkerton",
    "sg:classifiers":[
        {
            "category":"Government",
            "subcategory":"Office",
            "type":"Public Place"
        }
    ],
    "sg:phone":"+1 519 881 0432",
    "sg:postcode":"N0G 2V0",
    "sg:province":"ON",
    "wof:name":"Ontario Crown Attorney",
    "wof:placetype":"venue"
},
  "geometry": {"coordinates":[-81.15045166020001,44.1310806274],"type":"Point"}
}