{
  "type": "Feature",
  "properties": {
    "addr:full":"1929 8 Line Rd Metcalfe ON K0A 2P0",
    "addr:housenumber":"1929",
    "addr:postcode":"k0a 2p0",
    "addr:street":"8 Line Rd",
    "iso:country":"CA",
    "sg:address":"1929 8 Line Rd",
    "sg:city":"Metcalfe",
    "sg:classifiers":[
        {
            "category":"Manufacturing",
            "subcategory":"Metals",
            "type":"Manufacturing & Wholesale Goods"
        }
    ],
    "sg:phone":"+1 613 821 3102",
    "sg:postcode":"K0A 2P0",
    "sg:province":"ON",
    "sg:tags":[
        "fence"
    ],
    "wof:name":"Cheslock & Sons Construction",
    "wof:placetype":"venue"
},
  "geometry": {"coordinates":[-75.481697,45.253239],"type":"Point"}
}