{
  "type": "Feature",
  "properties": {
    "addr:full":"PO Box 7082 STN Sandwich Windsor ON N9C 3Y6",
    "addr:housenumber":"po",
    "addr:postcode":"7082;n9c 3y6",
    "addr:street":"Box;Sandwich",
    "iso:country":"CA",
    "sg:address":"PO Box 7082 STN Sandwich",
    "sg:city":"Windsor",
    "sg:classifiers":[
        {
            "category":"Home & Garden",
            "subcategory":"Building Materials",
            "type":"Retail Goods"
        }
    ],
    "sg:phone":"+1 519 967 0520",
    "sg:postcode":"N9C 3Y6",
    "sg:province":"ON",
    "sg:tags":[
        "door"
    ],
    "wof:name":"Pcs Automation Svc Inc",
    "wof:placetype":"venue"
},
  "geometry": {"coordinates":[-83.033913,42.317822],"type":"Point"}
}