{
  "type": "Feature",
  "properties": {
    "addr:full":"2245 Rue Viau Montreal QC H1V 3H6",
    "addr:housenumber":"2245",
    "addr:postcode":"h1v 3h6",
    "addr:street":"Rue Viau",
    "iso:country":"CA",
    "sg:address":"2245 Rue Viau",
    "sg:city":"Montreal",
    "sg:classifiers":[
        {
            "category":"Manufacturing",
            "subcategory":"Tools & Machinery",
            "type":"Manufacturing & Wholesale Goods"
        }
    ],
    "sg:phone":"+1 514 878 3999",
    "sg:postcode":"H1V 3H6",
    "sg:province":"QC",
    "sg:tags":[
        "machine",
        "shop"
    ],
    "wof:name":"Titanium Era",
    "wof:placetype":"venue"
},
  "geometry": {"coordinates":[-73.538376,45.560314],"type":"Point"}
}