{
  "type": "Feature",
  "properties": {
    "addr:full":"PO Box 763 STN Main Cochrane AB T4C 1A8",
    "addr:housenumber":"po",
    "addr:postcode":"t4c 1a8",
    "addr:street":"Box 763 Stn Main",
    "iso:country":"CA",
    "sg:address":"PO Box 763 STN Main",
    "sg:city":"Cochrane",
    "sg:classifiers":[
        {
            "category":"Wholesale",
            "subcategory":"Farm Supplies",
            "type":"Manufacturing & Wholesale Goods"
        }
    ],
    "sg:phone":"+1 403 932 5345",
    "sg:postcode":"T4C 1A8",
    "sg:province":"AB",
    "sg:tags":[
        "hide"
    ],
    "wof:name":"Southern Hides Ltd",
    "wof:placetype":"venue"
},
  "geometry": {"coordinates":[-114.46800231900001,51.190826416],"type":"Point"}
}