{
  "type": "Feature",
  "properties": {
    "iso:country":"CA",
    "sg:address":"1072 Rue Dulcinee",
    "sg:city":"Havre-Saint-Pierre",
    "sg:classifiers":[
        {
            "category":"Banks & Credit Unions",
            "subcategory":"Bank",
            "type":"Services"
        }
    ],
    "sg:phone":"+1 418 538 2123",
    "sg:postcode":"G0G 1P0",
    "sg:province":"QC",
    "wof:name":"Caisse Desjardins Havre Pierre",
    "wof:placetype":"venue"
},
  "geometry": {"coordinates":[-63.6028900146,50.2437171936],"type":"Point"}
}