{
  "type": "Feature",
  "properties": {
    "addr:full":"Saint-Hubert QC J3Y 5T6",
    "addr:postcode":"j3y 5t6",
    "iso:country":"CA",
    "sg:city":"Saint-Hubert",
    "sg:classifiers":[
        {
            "category":"Wholesale",
            "subcategory":"Construction Materials",
            "type":"Manufacturing & Wholesale Goods"
        }
    ],
    "sg:phone":"+1 450 443 6535",
    "sg:postcode":"J3Y 5T6",
    "sg:province":"QC",
    "sg:tags":[
        "building"
    ],
    "wof:name":"Senneco Inc",
    "wof:placetype":"venue"
},
  "geometry": {"coordinates":[-73.4433898926,45.5007553101],"type":"Point"}
}