{
  "type": "Feature",
  "properties": {
    "addr:full":"10843 82 Ave NW Edmonton AB T6E 2B2",
    "addr:housenumber":"10843",
    "addr:postcode":"t6e 2b2",
    "addr:street":"82 Ave Nw",
    "iso:country":"CA",
    "sg:address":"10843 82 Ave NW",
    "sg:city":"Edmonton",
    "sg:classifiers":[
        {
            "category":"Banks & Credit Unions",
            "subcategory":"Bank",
            "type":"Services"
        }
    ],
    "sg:phone":"+1 780 448 6900",
    "sg:postcode":"T6E 2B2",
    "sg:province":"AB",
    "wof:name":"Royal Bank Financial Group",
    "wof:placetype":"venue"
},
  "geometry": {"coordinates":[-113.510536194,53.5178337097],"type":"Point"}
}