{
  "type": "Feature",
  "properties": {
    "addr:full":"940 Main St Selkirk MB R1A 2A7",
    "addr:housenumber":"940",
    "addr:postcode":"r1a 2a7",
    "addr:street":"Main St",
    "iso:country":"CA",
    "sg:address":"940 Main St",
    "sg:city":"Selkirk",
    "sg:classifiers":[
        {
            "category":"Building & Trades",
            "subcategory":"Plumbing",
            "type":"Services"
        }
    ],
    "sg:phone":"+1 204 482 4159",
    "sg:postcode":"R1A 2A7",
    "sg:province":"MB",
    "sg:tags":[
        "contractor"
    ],
    "wof:name":"Tnt Plumbing & Heating",
    "wof:placetype":"venue"
},
  "geometry": {"coordinates":[-96.86721,50.165409],"type":"Point"}
}