{
  "type": "Feature",
  "properties": {
    "iso:country":"CA",
    "sg:address":"3055 Preston Ave",
    "sg:city":"Saskatoon",
    "sg:classifiers":[
        {
            "category":"Health Services",
            "subcategory":"Nursing And Care Facility",
            "type":"Services"
        }
    ],
    "sg:phone":"+1 306 955 4800",
    "sg:postcode":"S7T 1C3",
    "sg:province":"SK",
    "sg:tags":[
        "home",
        "convalescent"
    ],
    "wof:name":"Circle Drive Special Care Home",
    "wof:placetype":"venue"
},
  "geometry": {"coordinates":[-106.622436523,52.0874061584],"type":"Point"}
}