{
  "type": "Feature",
  "properties": {
    "addr:full":"311 Harrison Dr Sudbury ON P3E 5E1",
    "addr:housenumber":"311",
    "addr:postcode":"p3e 5e1",
    "addr:street":"Harrison Dr",
    "iso:country":"CA",
    "sg:address":"311 Harrison Dr",
    "sg:city":"Sudbury",
    "sg:classifiers":[
        {
            "category":"Building & Trades",
            "subcategory":"Construction",
            "type":"Services"
        }
    ],
    "sg:phone":"+1 705 522 9240",
    "sg:postcode":"P3E 5E1",
    "sg:province":"ON",
    "sg:tags":[
        "general",
        "contractor"
    ],
    "wof:name":"J N Construction Ltd",
    "wof:placetype":"venue"
},
  "geometry": {"coordinates":[-81.00649300000001,46.439533],"type":"Point"}
}