{
  "type": "Feature",
  "properties": {
    "addr:full":"Whistler BC V0N 1B4",
    "addr:postcode":"v0n 1b4",
    "iso:country":"CA",
    "sg:city":"Whistler",
    "sg:classifiers":[
        {
            "category":"Bars & Pubs",
            "type":"Food & Drink"
        }
    ],
    "sg:phone":"+1 604 932 2323",
    "sg:postcode":"V0N 1B4",
    "sg:province":"BC",
    "sg:tags":[
        "club",
        "cabaret",
        "night"
    ],
    "wof:name":"Garfinkel's",
    "wof:placetype":"venue"
},
  "geometry": {"coordinates":[-122.956504822,50.1169013977],"type":"Point"}
}