{
  "type": "Feature",
  "properties": {
    "addr:full":"137 Yonge St # 116 Toronto ON M5C 1W6",
    "addr:housenumber":"137",
    "addr:postcode":"m5c 1w6",
    "addr:street":"Yonge St # 116",
    "iso:country":"CA",
    "sg:address":"137 Yonge St # 116",
    "sg:city":"Toronto",
    "sg:classifiers":[
        {
            "category":"Shopping",
            "subcategory":"Computers & Home Electronics",
            "type":"Retail Goods"
        }
    ],
    "sg:phone":"+1 416 862 9595",
    "sg:postcode":"M5C 1W6",
    "sg:province":"ON",
    "wof:name":"Ask Used Computers 'N Parts",
    "wof:placetype":"venue"
},
  "geometry": {"coordinates":[-79.3785934448,43.6512794495],"type":"Point"}
}