{
  "type": "Feature",
  "properties": {
    "addr:full":"685 32E Ave Lachine QC H8T 3G6",
    "addr:housenumber":"685",
    "addr:postcode":"h8t 3g6",
    "addr:street":"32E Ave",
    "iso:country":"CA",
    "sg:address":"685 32E Ave",
    "sg:city":"Lachine",
    "sg:classifiers":[
        {
            "category":"Food & Beverages",
            "subcategory":"Groceries & Convenience Stores",
            "type":"Retail Goods"
        }
    ],
    "sg:phone":"+1 514 634 1708",
    "sg:postcode":"H8T 3G6",
    "sg:province":"QC",
    "wof:name":"Couche-Tard",
    "wof:placetype":"venue"
},
  "geometry": {"coordinates":[-73.6928482056,45.4415855408],"type":"Point"}
}