{
  "type": "Feature",
  "properties": {
    "addr:full":"310 Shaw Chase BC V0E 1M0",
    "addr:housenumber":"310",
    "addr:postcode":"bc v0e 1m0",
    "addr:street":"Shaw Chase",
    "iso:country":"CA",
    "sg:address":"310 Shaw",
    "sg:city":"Chase",
    "sg:classifiers":[
        {
            "category":"Education",
            "subcategory":"School",
            "type":"Public Place"
        }
    ],
    "sg:phone":"+1 250 679 3207",
    "sg:postcode":"V0E 1M0",
    "sg:province":"BC",
    "wof:name":"Chase Elementary School",
    "wof:placetype":"venue"
},
  "geometry": {"coordinates":[-119.684837,50.82209],"type":"Point"}
}