{
  "type": "Feature",
  "properties": {
    "iso:country":"CA",
    "sg:address":"220 University Ave",
    "sg:city":"Charlottetown",
    "sg:classifiers":[
        {
            "category":"Shopping",
            "subcategory":"Books",
            "type":"Retail Goods"
        }
    ],
    "sg:phone":"+1 902 892 6931",
    "sg:postcode":"C1A 4L5",
    "sg:province":"PE",
    "sg:tags":[
        "dealer"
    ],
    "wof:name":"Canadian Bible Society",
    "wof:placetype":"venue"
},
  "geometry": {"coordinates":[-63.1298675537,46.2382125854],"type":"Point"}
}