{
  "type": "Feature",
  "properties": {
    "addr:full":"278 Old Kingston Rd Scarborough ON M1C 1B5",
    "addr:housenumber":"278",
    "addr:postcode":"m1c 1b5",
    "addr:street":"Old Kingston Rd",
    "iso:country":"CA",
    "sg:address":"278 Old Kingston Rd",
    "sg:city":"Scarborough",
    "sg:classifiers":[
        {
            "category":"Retail",
            "subcategory":"Auto Repair",
            "type":"Services"
        }
    ],
    "sg:phone":"+1 416 282 5731",
    "sg:postcode":"M1C 1B5",
    "sg:province":"ON",
    "sg:tags":[
        "repairing",
        "automobile"
    ],
    "wof:name":"Mulhall's Service Ctr",
    "wof:placetype":"venue"
},
  "geometry": {"coordinates":[-79.1720962524,43.7825622559],"type":"Point"}
}