{
  "type": "Feature",
  "properties": {
    "addr:full":"78 Boul Sainte-Anne Sainte-Anne-Des-Plaines QC J0N 1H0",
    "addr:housenumber":"78",
    "addr:postcode":"j0n 1h0",
    "addr:street":"Boul Sainte-Anne",
    "iso:country":"CA",
    "sg:address":"78 Boul Sainte-Anne",
    "sg:city":"Sainte-Anne-Des-Plaines",
    "sg:classifiers":[
        {
            "category":"Home & Garden",
            "subcategory":"Building Materials",
            "type":"Retail Goods"
        }
    ],
    "sg:phone":"+1 450 478 4575",
    "sg:postcode":"J0N 1H0",
    "sg:province":"QC",
    "sg:tags":[
        "windows",
        "glass"
    ],
    "wof:name":"Vitrerie Ste Anne Enr",
    "wof:placetype":"venue"
},
  "geometry": {"coordinates":[-73.81444500000001,45.760204],"type":"Point"}
}