{
  "type": "Feature",
  "properties": {
    "addr:full":"Toronto ON M4Y 1T1",
    "addr:postcode":"m4y 1t1",
    "iso:country":"CA",
    "sg:city":"Toronto",
    "sg:classifiers":[
        {
            "category":"Health Services",
            "subcategory":"Health Practitioner",
            "type":"Services"
        }
    ],
    "sg:phone":"+1 416 921 9670",
    "sg:postcode":"M4Y 1T1",
    "sg:province":"ON",
    "sg:tags":[
        "control",
        "psychotherapist",
        "weight"
    ],
    "wof:name":"Patricia Kelly & Assoc",
    "wof:placetype":"venue"
},
  "geometry": {"coordinates":[-79.383522,43.669308],"type":"Point"}
}