{
  "type": "Feature",
  "properties": {
    "iso:country":"CA",
    "sg:address":"1571 Boul Saint-Jean-Baptiste",
    "sg:city":"Chicoutimi",
    "sg:classifiers":[
        {
            "category":"Sports & Exercise",
            "subcategory":"Golf",
            "type":"Entertainment"
        }
    ],
    "sg:phone":"+1 418 693 8221",
    "sg:postcode":"G7H 7T9",
    "sg:province":"QC",
    "sg:tags":[
        "course"
    ],
    "wof:name":"Club DE Golf Le Ricochet",
    "wof:placetype":"venue"
},
  "geometry": {"coordinates":[-71.021721,48.410606],"type":"Point"}
}