{
  "type": "Feature",
  "properties": {
    "addr:full":"502 Park Ave Moosomin SK S0G 3N0",
    "addr:housenumber":"502",
    "addr:postcode":"s0g 3n0",
    "addr:street":"Park Ave",
    "iso:country":"CA",
    "sg:address":"502 Park Ave",
    "sg:city":"Moosomin",
    "sg:classifiers":[
        {
            "category":"Autos & Motor Vehicles",
            "subcategory":"Fuel & Gas Station",
            "type":"Retail Goods"
        }
    ],
    "sg:phone":"+1 306 435 2335",
    "sg:postcode":"S0G 3N0",
    "sg:province":"SK",
    "sg:tags":[
        "oil"
    ],
    "wof:name":"Esso",
    "wof:placetype":"venue"
},
  "geometry": {"coordinates":[-101.667946,50.150467],"type":"Point"}
}