{
  "type": "Feature",
  "properties": {
    "addr:full":"4379 Kingston Rd Scarborough ON M1E 2M9",
    "addr:housenumber":"4379",
    "addr:postcode":"m1e 2m9",
    "addr:street":"Kingston Rd",
    "iso:country":"CA",
    "sg:address":"4379 Kingston Rd",
    "sg:city":"Scarborough",
    "sg:classifiers":[
        {
            "category":"Food & Beverages",
            "subcategory":"Groceries & Convenience Stores",
            "type":"Retail Goods"
        }
    ],
    "sg:phone":"+1 416 281 3244",
    "sg:postcode":"M1E 2M9",
    "sg:province":"ON",
    "wof:name":"Let's Convenience Plus",
    "wof:placetype":"venue"
},
  "geometry": {"coordinates":[-79.19021600000001,43.766636],"type":"Point"}
}