{
  "type": "Feature",
  "properties": {
    "iso:country":"CA",
    "sg:address":"621 Patricia St",
    "sg:city":"Jasper",
    "sg:classifiers":[
        {
            "category":"Shopping",
            "subcategory":"Gifts & Souvenirs",
            "type":"Retail Goods"
        }
    ],
    "sg:phone":"+1 780 852 5575",
    "sg:postcode":"T0E 1E0",
    "sg:province":"AB",
    "sg:tags":[
        "shop"
    ],
    "wof:name":"Rocky Mountain Christmas",
    "wof:placetype":"venue"
},
  "geometry": {"coordinates":[-118.081413269,52.8756713867],"type":"Point"}
}