{
  "type": "Feature",
  "properties": {
    "addr:full":"1031 Rue Principale Saint-Agapit QC G0S 1Z0",
    "addr:housenumber":"1031",
    "addr:postcode":"g0s 1z0",
    "addr:street":"Rue Principale",
    "iso:country":"CA",
    "sg:address":"1031 Rue Principale",
    "sg:city":"Saint-Agapit",
    "sg:classifiers":[
        {
            "category":"Autos & Motor Vehicles",
            "subcategory":"Auto Supplies",
            "type":"Retail Goods"
        }
    ],
    "sg:phone":"+1 418 888 3929",
    "sg:postcode":"G0S 1Z0",
    "sg:province":"QC",
    "sg:tags":[
        "tire"
    ],
    "wof:name":"Centre DE L'Auto Lotbiniere",
    "wof:placetype":"venue"
},
  "geometry": {"coordinates":[-71.424232,46.565079],"type":"Point"}
}