{
  "type": "Feature",
  "properties": {
    "addr:full":"31 Gimli St Trenton ON K8V 6V4",
    "addr:housenumber":"31",
    "addr:postcode":"k8v 6v4",
    "addr:street":"Gimli St",
    "iso:country":"CA",
    "sg:address":"31 Gimli St",
    "sg:city":"Trenton",
    "sg:classifiers":[
        {
            "category":"Education",
            "subcategory":"School",
            "type":"Public Place"
        }
    ],
    "sg:phone":"+1 613 394 1394",
    "sg:postcode":"K8V 6V4",
    "sg:province":"ON",
    "wof:name":"Breadner Elementary School",
    "wof:placetype":"venue"
},
  "geometry": {"coordinates":[-77.5581207275,44.1151580811],"type":"Point"}
}