{
  "type": "Feature",
  "properties": {
    "addr:full":"215 Boul DE LA Concorde E Laval QC H7G 2C9",
    "addr:housenumber":"215",
    "addr:postcode":"qc h7g 2c9",
    "addr:street":"Boul De La Concorde E",
    "iso:country":"CA",
    "sg:address":"215 Boul DE LA Concorde E",
    "sg:city":"Laval",
    "sg:classifiers":[
        {
            "category":"Insurance",
            "subcategory":"Insurance Agent",
            "type":"Services"
        }
    ],
    "sg:phone":"+1 450 662 8686",
    "sg:postcode":"H7G 2C9",
    "sg:province":"QC",
    "wof:name":"Assurance Sante Sud",
    "wof:placetype":"venue"
},
  "geometry": {"coordinates":[-73.6833190918,45.575378418],"type":"Point"}
}