{
  "type": "Feature",
  "properties": {
    "iso:country":"CA",
    "sg:address":"456 Montcalm Ave",
    "sg:city":"Sarnia",
    "sg:classifiers":[
        {
            "category":"Retail",
            "subcategory":"Repair Shop",
            "type":"Services"
        }
    ],
    "sg:phone":"+1 519 344 4900",
    "sg:postcode":"N7S 2P9",
    "sg:province":"ON",
    "sg:tags":[
        "refinishing",
        "furniture"
    ],
    "wof:name":"Furniture Doctor",
    "wof:placetype":"venue"
},
  "geometry": {"coordinates":[-82.374779,42.973675],"type":"Point"}
}