{
  "type": "Feature",
  "properties": {
    "addr:full":"808 1 Ave S Lethbridge AB T1J 4T1",
    "addr:housenumber":"808",
    "addr:postcode":"t1j 4t1",
    "addr:street":"1 Ave S",
    "iso:country":"CA",
    "sg:address":"808 1 Ave S",
    "sg:city":"Lethbridge",
    "sg:classifiers":[
        {
            "category":"Shopping",
            "subcategory":"Optical Goods",
            "type":"Retail Goods"
        }
    ],
    "sg:phone":"+1 403 327 3444",
    "sg:postcode":"T1J 4T1",
    "sg:province":"AB",
    "sg:tags":[
        "sun",
        "goggles",
        "sunglasses",
        "optician"
    ],
    "wof:name":"Professional Optical Ltd",
    "wof:placetype":"venue"
},
  "geometry": {"coordinates":[-112.83548,49.69788],"type":"Point"}
}