{
  "type": "Feature",
  "properties": {
    "addr:full":"2585 8E Rue Saint-Prosper-DE-Dorchester QC G0M 1Y0",
    "addr:housenumber":"2585",
    "addr:postcode":"g0m 1y0",
    "addr:street":"8E Rue Saint-Prosper-De-Dorchester",
    "iso:country":"CA",
    "sg:address":"2585 8E Rue",
    "sg:city":"Saint-Prosper-DE-Dorchester",
    "sg:classifiers":[
        {
            "category":"Autos & Motor Vehicles",
            "subcategory":"Recreational Vehicle Sales",
            "type":"Retail Goods"
        }
    ],
    "sg:phone":"+1 418 594 5070",
    "sg:postcode":"G0M 1Y0",
    "sg:province":"QC",
    "sg:tags":[
        "all",
        "terrain"
    ],
    "wof:name":"Argos Laurent Gilbert Inc",
    "wof:placetype":"venue"
},
  "geometry": {"coordinates":[-70.497749,46.221554],"type":"Point"}
}