{
  "type": "Feature",
  "properties": {
    "addr:full":"122 Surgeoner Cres Newmarket ON L3X 2L2",
    "addr:housenumber":"122",
    "addr:postcode":"l3x 2l2",
    "addr:street":"Surgeoner Cres",
    "iso:country":"CA",
    "sg:address":"122 Surgeoner Cres",
    "sg:city":"Newmarket",
    "sg:classifiers":[
        {
            "category":"Retail",
            "subcategory":"Laundry & Dry Cleaning",
            "type":"Services"
        }
    ],
    "sg:phone":"+1 905 853 5848",
    "sg:postcode":"L3X 2L2",
    "sg:province":"ON",
    "sg:tags":[
        "cleaners",
        "rug",
        "carpet"
    ],
    "wof:name":"Roto Static Carpet & Uphlstry",
    "wof:placetype":"venue"
},
  "geometry": {"coordinates":[-79.4849243164,44.0375709534],"type":"Point"}
}