{
  "type": "Feature",
  "properties": {
    "addr:full":"31 Arthur St S Elmira ON N3B 2M4",
    "addr:housenumber":"31",
    "addr:postcode":"n3b 2m4",
    "addr:street":"Arthur St S",
    "iso:country":"CA",
    "sg:address":"31 Arthur St S",
    "sg:city":"Elmira",
    "sg:classifiers":[
        {
            "category":"Retail",
            "subcategory":"Repair Shop",
            "type":"Services"
        }
    ],
    "sg:phone":"+1 519 669 3384",
    "sg:postcode":"N3B 2M4",
    "sg:province":"ON",
    "sg:tags":[
        "jewelry"
    ],
    "wof:name":"Hartman Jewellers",
    "wof:placetype":"venue"
},
  "geometry": {"coordinates":[-80.5579452515,43.5994224548],"type":"Point"}
}