{
  "type": "Feature",
  "properties": {
    "iso:country":"CA",
    "sg:city":"London",
    "sg:classifiers":[
        {
            "category":"Banks & Credit Unions",
            "subcategory":"Bank",
            "type":"Services"
        }
    ],
    "sg:phone":"+1 519 649 6545",
    "sg:postcode":"N6C 5Z3",
    "sg:province":"ON",
    "sg:tags":[
        "loan",
        "real estate"
    ],
    "wof:name":"Mortgage Centre",
    "wof:placetype":"venue"
},
  "geometry": {"coordinates":[-81.260132,42.956722],"type":"Point"}
}