{
  "type": "Feature",
  "properties": {
    "addr:full":"33038 Second Ave Mission BC V2V 1J8",
    "addr:housenumber":"33038",
    "addr:postcode":"v2v 1j8",
    "addr:street":"Second Ave",
    "iso:country":"CA",
    "sg:address":"33038 Second Ave",
    "sg:city":"Mission",
    "sg:classifiers":[
        {
            "category":"Health Services",
            "subcategory":"Doctor",
            "type":"Services"
        }
    ],
    "sg:phone":"+1 604 826 2960",
    "sg:postcode":"V2V 1J8",
    "sg:province":"BC",
    "sg:tags":[
        "dentist"
    ],
    "wof:name":"Germain, Diana DDS",
    "wof:placetype":"venue"
},
  "geometry": {"coordinates":[-122.30850982699999,49.1350746155],"type":"Point"}
}