{
  "type": "Feature",
  "properties": {
    "addr:full":"586 Rang 5 S Packington QC G0L 1Z0",
    "addr:housenumber":"586",
    "addr:postcode":"g0l 1z0",
    "addr:street":"Rang 5 S",
    "iso:country":"CA",
    "sg:address":"586 Rang 5 S",
    "sg:city":"Packington",
    "sg:classifiers":[
        {
            "category":"Manufacturing",
            "subcategory":"Lumber",
            "type":"Manufacturing & Wholesale Goods"
        }
    ],
    "sg:phone":"+1 418 853 2385",
    "sg:postcode":"G0L 1Z0",
    "sg:province":"QC",
    "sg:tags":[
        "syrup",
        "maple",
        "sugar"
    ],
    "wof:name":"Erabliere Valcourt",
    "wof:placetype":"venue"
},
  "geometry": {"coordinates":[-68.806648,47.428734],"type":"Point"}
}