{
  "type": "Feature",
  "properties": {
    "iso:country":"CA",
    "sg:city":"Toronto",
    "sg:classifiers":[
        {
            "category":"Professional",
            "subcategory":"Management & Consulting",
            "type":"Services"
        }
    ],
    "sg:phone":"+1 416 961 6611",
    "sg:postcode":"M5R 1C1",
    "sg:province":"ON",
    "sg:tags":[
        "consultant",
        "government"
    ],
    "wof:name":"Sussex Strategy Group",
    "wof:placetype":"venue"
},
  "geometry": {"coordinates":[-79.3922119141,43.6707801819],"type":"Point"}
}