{
  "type": "Feature",
  "properties": {
    "iso:country":"CA",
    "sg:city":"Digby",
    "sg:classifiers":[
        {
            "category":"Home & Garden",
            "subcategory":"Garden Supply",
            "type":"Retail Goods"
        }
    ],
    "sg:phone":"+1 902 245 5422",
    "sg:postcode":"B0V 1A0",
    "sg:province":"NS",
    "sg:tags":[
        "lawn",
        "mower",
        "terrain",
        "all",
        "vehicle"
    ],
    "wof:name":"Gates Power Equipment Ltd",
    "wof:placetype":"venue"
},
  "geometry": {"coordinates":[-66.1154174805,44.3339080811],"type":"Point"}
}