{
  "type": "Feature",
  "properties": {
    "addr:full":"1488 Chancellor Dr Winnipeg MB R3T 4H6",
    "addr:housenumber":"1488",
    "addr:postcode":"r3t 4h6",
    "addr:street":"Chancellor Dr",
    "iso:country":"CA",
    "sg:address":"1488 Chancellor Dr",
    "sg:city":"Winnipeg",
    "sg:classifiers":[
        {
            "category":"Professional",
            "subcategory":"Computer Services",
            "type":"Services"
        }
    ],
    "sg:phone":"+1 204 292 2323",
    "sg:postcode":"R3T 4H6",
    "sg:province":"MB",
    "sg:tags":[
        "website",
        "multimedia",
        "design"
    ],
    "wof:name":"Majestic Productions",
    "wof:placetype":"venue"
},
  "geometry": {"coordinates":[-97.16864,49.803444],"type":"Point"}
}