{
  "type": "Feature",
  "properties": {
    "addr:full":"Val-D'Or QC J9P 7B1",
    "addr:postcode":"j9p 7b1",
    "iso:country":"CA",
    "sg:city":"Val-D'Or",
    "sg:classifiers":[
        {
            "category":"Retail",
            "subcategory":"Portrait Studio",
            "type":"Services"
        }
    ],
    "sg:phone":"+1 819 824 6368",
    "sg:postcode":"J9P 7B1",
    "sg:province":"QC",
    "sg:tags":[
        "photographer"
    ],
    "wof:name":"Photo Rejean Massicotte Enr",
    "wof:placetype":"venue"
},
  "geometry": {"coordinates":[-68.42929077150001,53.89012146],"type":"Point"}
}