{
  "type": "Feature",
  "properties": {
    "addr:full":"810 6th Ave Ladysmith BC V9G 1A2",
    "addr:housenumber":"810",
    "addr:postcode":"v9g 1a2",
    "addr:street":"6Th Ave",
    "iso:country":"CA",
    "sg:address":"810 6th Ave",
    "sg:city":"Ladysmith",
    "sg:classifiers":[
        {
            "category":"Recreation",
            "type":"Entertainment"
        }
    ],
    "sg:phone":"+1 250 245 6424",
    "sg:postcode":"V9G 1A2",
    "sg:province":"BC",
    "sg:tags":[
        "provincial",
        "center",
        "parks"
    ],
    "wof:name":"Frank Jameson Community Ctr",
    "wof:placetype":"venue"
},
  "geometry": {"coordinates":[-123.827057,48.991077],"type":"Point"}
}