{
  "type": "Feature",
  "properties": {
    "addr:full":"534 Park St Kenora ON P9N 1A1",
    "addr:housenumber":"534",
    "addr:postcode":"p9n 1a1",
    "addr:street":"Park St",
    "iso:country":"CA",
    "sg:address":"534 Park St",
    "sg:city":"Kenora",
    "sg:classifiers":[
        {
            "category":"Personal",
            "subcategory":"Beauty Salon",
            "type":"Services"
        }
    ],
    "sg:phone":"+1 807 468 4795",
    "sg:postcode":"P9N 1A1",
    "sg:province":"ON",
    "wof:name":"Magicuts",
    "wof:placetype":"venue"
},
  "geometry": {"coordinates":[-94.48421500000001,49.767033],"type":"Point"}
}