{
  "type": "Feature",
  "properties": {
    "addr:full":"221 Evans Ave Etobicoke ON M8Z 1J5",
    "addr:housenumber":"221",
    "addr:postcode":"m8z 1j5",
    "addr:street":"Evans Ave",
    "iso:country":"CA",
    "sg:address":"221 Evans Ave",
    "sg:city":"Etobicoke",
    "sg:classifiers":[
        {
            "category":"Professional",
            "type":"Services"
        }
    ],
    "sg:phone":"+1 416 251 8154",
    "sg:postcode":"M8Z 1J5",
    "sg:province":"ON",
    "sg:tags":[
        "establishment",
        "uniform"
    ],
    "wof:name":"Sportsphere",
    "wof:placetype":"venue"
},
  "geometry": {"coordinates":[-79.51638800000001,43.617367],"type":"Point"}
}