{
  "type": "Feature",
  "properties": {
    "iso:country":"CA",
    "sg:address":"394 4E Rue",
    "sg:city":"Quebec",
    "sg:classifiers":[
        {
            "category":"Building & Trades",
            "subcategory":"Construction",
            "type":"Services"
        }
    ],
    "sg:phone":"+1 418 529 1912",
    "sg:postcode":"G1L 2S5",
    "sg:province":"QC",
    "sg:tags":[
        "repairing",
        "contractor",
        "remodeling",
        "general"
    ],
    "wof:name":"Laurent Labbe & Fils Inc",
    "wof:placetype":"venue"
},
  "geometry": {"coordinates":[-71.224442,46.823215],"type":"Point"}
}