{
  "type": "Feature",
  "properties": {
    "addr:full":"1039 Pape Ave East York ON M4K 3W1",
    "addr:housenumber":"1039",
    "addr:postcode":"m4k 3w1",
    "addr:street":"Pape Ave",
    "iso:country":"CA",
    "sg:address":"1039 Pape Ave",
    "sg:city":"East York",
    "sg:classifiers":[
        {
            "category":"Restaurant",
            "type":"Food & Drink"
        }
    ],
    "sg:phone":"+1 416 421 1686",
    "sg:postcode":"M4K 3W1",
    "sg:province":"ON",
    "wof:name":"East York Restaurant Ltd",
    "wof:placetype":"venue"
},
  "geometry": {"coordinates":[-79.3485412598,43.689239502],"type":"Point"}
}