{
  "type": "Feature",
  "properties": {
    "addr:full":"1621 Irricana Rd NE Airdrie AB T4A 2G7",
    "addr:housenumber":"1621",
    "addr:postcode":"t4a 2g7",
    "addr:street":"Irricana Rd Ne",
    "iso:country":"CA",
    "sg:address":"1621 Irricana Rd NE",
    "sg:city":"Airdrie",
    "sg:classifiers":[
        {
            "category":"Professional",
            "subcategory":"Business Services",
            "type":"Services"
        }
    ],
    "sg:phone":"+1 403 912 4400",
    "sg:postcode":"T4A 2G7",
    "sg:province":"AB",
    "sg:tags":[
        "auctioneer"
    ],
    "wof:name":"Adesa Calgary",
    "wof:placetype":"venue"
},
  "geometry": {"coordinates":[-113.981422424,51.2996330261],"type":"Point"}
}