{
  "type": "Feature",
  "properties": {
    "addr:full":"Ragueneau QC G0H 1S0",
    "addr:postcode":"g0h 1s0",
    "iso:country":"CA",
    "sg:city":"Ragueneau",
    "sg:classifiers":[
        {
            "category":"Building & Trades",
            "subcategory":"Construction",
            "type":"Services"
        }
    ],
    "sg:phone":"+1 418 567 4843",
    "sg:postcode":"G0H 1S0",
    "sg:province":"QC",
    "sg:tags":[
        "excavating",
        "contractor"
    ],
    "wof:name":"Location Excavation Rsmf",
    "wof:placetype":"venue"
},
  "geometry": {"coordinates":[-68.4857788086,49.0703392029],"type":"Point"}
}