{
  "type": "Feature",
  "properties": {
    "addr:full":"268 Lakeshore Rd E Mississauga ON L5G 1H1",
    "addr:housenumber":"268",
    "addr:postcode":"l5g 1h1",
    "addr:street":"Lakeshore Rd E",
    "iso:country":"CA",
    "sg:address":"268 Lakeshore Rd E",
    "sg:city":"Mississauga",
    "sg:classifiers":[
        {
            "category":"Banks & Credit Unions",
            "subcategory":"Bank",
            "type":"Services"
        }
    ],
    "sg:phone":"+1 905 274 4494",
    "sg:postcode":"L5G 1H1",
    "sg:province":"ON",
    "sg:tags":[
        "loan"
    ],
    "wof:name":"Confidential Cash Inc",
    "wof:placetype":"venue"
},
  "geometry": {"coordinates":[-79.5765533447,43.5603294373],"type":"Point"}
}