{
  "type": "Feature",
  "properties": {
    "addr:full":"6247 Boul Leger Montreal-Nord QC H1G 6K8",
    "addr:housenumber":"6247",
    "addr:postcode":"h1g 6k8",
    "addr:street":"Boul Leger",
    "iso:country":"CA",
    "sg:address":"6247 Boul Leger",
    "sg:city":"Montreal-Nord",
    "sg:classifiers":[
        {
            "category":"Restaurant",
            "type":"Food & Drink"
        }
    ],
    "sg:phone":"+1 514 326 1000",
    "sg:postcode":"H1G 6K8",
    "sg:province":"QC",
    "wof:name":"Apelia Restaurant",
    "wof:placetype":"venue"
},
  "geometry": {"coordinates":[-73.624985,45.621826],"type":"Point"}
}