{
  "type": "Feature",
  "properties": {
    "addr:full":"71 Melanie St Eganville ON K0J 1T0",
    "addr:housenumber":"71",
    "addr:postcode":"k0j 1t0",
    "addr:street":"Melanie St",
    "iso:country":"CA",
    "sg:address":"71 Melanie St",
    "sg:city":"Eganville",
    "sg:classifiers":[
        {
            "category":"Building & Trades",
            "subcategory":"Construction",
            "type":"Services"
        }
    ],
    "sg:phone":"+1 613 628 2646",
    "sg:postcode":"K0J 1T0",
    "sg:province":"ON",
    "sg:tags":[
        "roofing",
        "contractor"
    ],
    "wof:name":"Schiron Construction",
    "wof:placetype":"venue"
},
  "geometry": {"coordinates":[-77.09535217289999,45.5336494446],"type":"Point"}
}