{
  "type": "Feature",
  "properties": {
    "addr:full":"2 Buffalo St Tuxford SK S0H 4C0",
    "addr:housenumber":"2",
    "addr:postcode":"s0h 4c0",
    "addr:street":"Buffalo St",
    "iso:country":"CA",
    "sg:address":"2 Buffalo St",
    "sg:city":"Tuxford",
    "sg:classifiers":[
        {
            "category":"Building & Trades",
            "subcategory":"Construction",
            "type":"Services"
        }
    ],
    "sg:phone":"+1 306 693 5610",
    "sg:postcode":"S0H 4C0",
    "sg:province":"SK",
    "sg:tags":[
        "general",
        "contractor"
    ],
    "wof:name":"Double K Excavating Ltd",
    "wof:placetype":"venue"
},
  "geometry": {"coordinates":[-105.58174099999999,50.575504],"type":"Point"}
}