{
  "type": "Feature",
  "properties": {
    "addr:full":"1419 Mallek Cres Victoria BC V8T 2R3",
    "addr:housenumber":"1419",
    "addr:postcode":"v8t 2r3",
    "addr:street":"Mallek Cres",
    "iso:country":"CA",
    "sg:address":"1419 Mallek Cres",
    "sg:city":"Victoria",
    "sg:classifiers":[
        {
            "category":"Organizations",
            "subcategory":"Professional Association",
            "type":"Services"
        }
    ],
    "sg:phone":"+1 250 595 3133",
    "sg:postcode":"V8T 2R3",
    "sg:province":"BC",
    "sg:tags":[
        "club"
    ],
    "wof:name":"Kiwanis Club of Victoria",
    "wof:placetype":"venue"
},
  "geometry": {"coordinates":[-123.348022,48.445309],"type":"Point"}
}