{
  "type": "Feature",
  "properties": {
    "iso:country":"CA",
    "sg:address":"3600 Billings Crt",
    "sg:city":"Burlington",
    "sg:classifiers":[
        {
            "category":"Professional",
            "subcategory":"Research",
            "type":"Services"
        }
    ],
    "sg:phone":"+1 905 631 6290",
    "sg:postcode":"L7N 3N6",
    "sg:province":"ON",
    "sg:tags":[
        "economic",
        "analysis"
    ],
    "wof:name":"Econometric Research Ltd",
    "wof:placetype":"venue"
},
  "geometry": {"coordinates":[-79.789192,43.364029],"type":"Point"}
}