{
  "type": "Feature",
  "properties": {
    "addr:full":"169 Rue Saint-Damase Drummondville QC J2B 6G8",
    "addr:housenumber":"169",
    "addr:postcode":"j2b 6g8",
    "addr:street":"Rue Saint-Damase",
    "iso:country":"CA",
    "sg:address":"169 Rue Saint-Damase",
    "sg:city":"Drummondville",
    "sg:classifiers":[
        {
            "category":"Home & Garden",
            "subcategory":"Household Appliances",
            "type":"Retail Goods"
        }
    ],
    "sg:phone":"+1 819 475 3136",
    "sg:postcode":"J2B 6G8",
    "sg:province":"QC",
    "sg:tags":[
        "cleaners",
        "vacuum"
    ],
    "wof:name":"Royaume DE L'Aspirateur",
    "wof:placetype":"venue"
},
  "geometry": {"coordinates":[-72.49276733400001,45.872467041],"type":"Point"}
}