{
  "type": "Feature",
  "properties": {
    "addr:full":"230 Main St S Redcliff AB T0J 2P0",
    "addr:housenumber":"230",
    "addr:postcode":"t0j 2p0",
    "addr:street":"Main St S Redcliff",
    "iso:country":"CA",
    "sg:address":"230 Main St S",
    "sg:city":"Redcliff",
    "sg:classifiers":[
        {
            "category":"Recreation",
            "type":"Entertainment"
        }
    ],
    "sg:phone":"+1 403 548 9242",
    "sg:postcode":"T0J 2P0",
    "sg:province":"AB",
    "sg:tags":[
        "pool",
        "swimming"
    ],
    "wof:name":"Redcliff Pool Aquatic Ctr",
    "wof:placetype":"venue"
},
  "geometry": {"coordinates":[-110.789413,50.074844],"type":"Point"}
}