{
  "type": "Feature",
  "properties": {
    "iso:country":"CA",
    "sg:address":"822 11 Ave SW",
    "sg:city":"Calgary",
    "sg:classifiers":[
        {
            "category":"Restaurant",
            "type":"Food & Drink"
        }
    ],
    "sg:phone":"+1 403 264 7241",
    "sg:postcode":"T2R 0E5",
    "sg:province":"AB",
    "wof:name":"King & I Thai Cuisine",
    "wof:placetype":"venue"
},
  "geometry": {"coordinates":[-114.079689,51.04295],"type":"Point"}
}