{
  "type": "Feature",
  "properties": {
    "iso:country":"CA",
    "sg:address":"702 Boul Adolphe-Chapleau",
    "sg:city":"Bois-Des-Filion",
    "sg:classifiers":[
        {
            "category":"Restaurant",
            "type":"Food & Drink"
        }
    ],
    "sg:phone":"+1 450 621 6464",
    "sg:postcode":"J6Z 1L8",
    "sg:province":"QC",
    "wof:name":"Mr Burger",
    "wof:placetype":"venue"
},
  "geometry": {"coordinates":[-73.770935,45.656105],"type":"Point"}
}