{
  "type": "Feature",
  "properties": {
    "addr:full":"Calgary AB T2E 7B2",
    "addr:postcode":"t2e 7b2",
    "iso:country":"CA",
    "sg:city":"Calgary",
    "sg:classifiers":[
        {
            "category":"Food & Beverages",
            "subcategory":"Meat & Fish",
            "type":"Retail Goods"
        }
    ],
    "sg:phone":"+1 403 250 7727",
    "sg:postcode":"T2E 7B2",
    "sg:province":"AB",
    "wof:name":"Ryan's Meat Processors Ltd",
    "wof:placetype":"venue"
},
  "geometry": {"coordinates":[-114.013885,51.079811],"type":"Point"}
}