{
  "type": "Feature",
  "properties": {
    "iso:country":"CA",
    "sg:address":"4500 Boul Henri-Bourassa",
    "sg:city":"Charlesbourg",
    "sg:classifiers":[
        {
            "category":"Wholesale",
            "subcategory":"Medical Equipment & Supplies",
            "type":"Manufacturing & Wholesale Goods"
        }
    ],
    "sg:phone":"+1 418 622 1195",
    "sg:postcode":"G1H 3A5",
    "sg:province":"QC",
    "sg:tags":[
        "dental"
    ],
    "wof:name":"Brasseler Canada Inc",
    "wof:placetype":"venue"
},
  "geometry": {"coordinates":[-71.2408065796,46.848941803],"type":"Point"}
}