{
  "type": "Feature",
  "properties": {
    "addr:full":"1596 Rte Marie-Victorin O Deschaillons-Sur-Saint-Laurent QC G0S 1G0",
    "addr:housenumber":"1596",
    "addr:postcode":"g0s 1g0",
    "addr:street":"Rte Marie-Victorin O",
    "iso:country":"CA",
    "sg:address":"1596 Rte Marie-Victorin O",
    "sg:city":"Deschaillons-Sur-Saint-Laurent",
    "sg:classifiers":[
        {
            "category":"Cinema",
            "subcategory":"Movie Rental",
            "type":"Entertainment"
        }
    ],
    "sg:phone":"+1 819 292 3393",
    "sg:postcode":"G0S 1G0",
    "sg:province":"QC",
    "sg:tags":[
        "leasing",
        "video",
        "disc",
        "tape"
    ],
    "wof:name":"Club Video Son Et Couleur Enr",
    "wof:placetype":"venue"
},
  "geometry": {"coordinates":[-72.1276473999,46.5500526428],"type":"Point"}
}