{
  "type": "Feature",
  "properties": {
    "addr:full":"2505 Boul Des Entreprises Terrebonne QC J6X 5S5",
    "addr:housenumber":"2505",
    "addr:postcode":"j6x 5s5",
    "addr:street":"Boul Des Entreprises",
    "iso:country":"CA",
    "sg:address":"2505 Boul Des Entreprises",
    "sg:city":"Terrebonne",
    "sg:classifiers":[
        {
            "category":"Organizations",
            "subcategory":"Labor Organization",
            "type":"Services"
        }
    ],
    "sg:phone":"+1 450 477 7304",
    "sg:postcode":"J6X 5S5",
    "sg:province":"QC",
    "wof:name":"Syndicat Des Enseignantes",
    "wof:placetype":"venue"
},
  "geometry": {"coordinates":[-73.70504,45.722],"type":"Point"}
}