{
  "type": "Feature",
  "properties": {
    "addr:full":"5303 Nauvoo Rd Watford ON N0M 2S0",
    "addr:housenumber":"5303",
    "addr:postcode":"n0m 2s0",
    "addr:street":"Nauvoo Rd",
    "iso:country":"CA",
    "sg:address":"5303 Nauvoo Rd",
    "sg:city":"Watford",
    "sg:classifiers":[
        {
            "category":"Autos & Motor Vehicles",
            "subcategory":"Auto Supplies",
            "type":"Retail Goods"
        }
    ],
    "sg:phone":"+1 519 876 2733",
    "sg:postcode":"N0M 2S0",
    "sg:province":"ON",
    "sg:tags":[
        "automobile",
        "parts"
    ],
    "wof:name":"Watford Auto Parts",
    "wof:placetype":"venue"
},
  "geometry": {"coordinates":[-81.880211,42.948414],"type":"Point"}
}