{
  "type": "Feature",
  "properties": {
    "addr:full":"369 Rue Ouimet Saint-Laurent QC H4L 5M5",
    "addr:housenumber":"369",
    "addr:postcode":"h4l 5m5",
    "addr:street":"Rue Ouimet",
    "iso:country":"CA",
    "sg:address":"369 Rue Ouimet",
    "sg:city":"Saint-Laurent",
    "sg:classifiers":[
        {
            "category":"Education",
            "subcategory":"Special Training",
            "type":"Public Place"
        }
    ],
    "sg:phone":"+1 514 855 4949",
    "sg:postcode":"H4L 5M5",
    "sg:province":"QC",
    "sg:tags":[
        "instrument",
        "music",
        "musical"
    ],
    "wof:name":"Mr DO Re MI",
    "wof:placetype":"venue"
},
  "geometry": {"coordinates":[-73.67143249510001,45.5087890625],"type":"Point"}
}