{
  "type": "Feature",
  "properties": {
    "addr:full":"5165 Dixie Rd Mississauga ON L4W 4G1",
    "addr:housenumber":"5165",
    "addr:postcode":"l4w 4g1",
    "addr:street":"Dixie Rd",
    "iso:country":"CA",
    "sg:address":"5165 Dixie Rd",
    "sg:city":"Mississauga",
    "sg:classifiers":[
        {
            "category":"Professional",
            "subcategory":"Business Services",
            "type":"Services"
        }
    ],
    "sg:phone":"+1 905 624 4009",
    "sg:postcode":"L4W 4G1",
    "sg:province":"ON",
    "sg:tags":[
        "convention",
        "meeting",
        "rooms",
        "banquet",
        "facility"
    ],
    "wof:name":"Pavilion Royale Inc",
    "wof:placetype":"venue"
},
  "geometry": {"coordinates":[-79.625221,43.639278],"type":"Point"}
}