{
  "type": "Feature",
  "properties": {
    "addr:full":"1153 Ch DE Villebois Alma QC G8B 5V2",
    "addr:housenumber":"1153",
    "addr:postcode":"g8b 5v2",
    "addr:street":"Ch De Villebois",
    "iso:country":"CA",
    "sg:address":"1153 Ch DE Villebois",
    "sg:city":"Alma",
    "sg:classifiers":[
        {
            "category":"Social Services",
            "type":"Services"
        }
    ],
    "sg:phone":"+1 418 668 6411",
    "sg:postcode":"G8B 5V2",
    "sg:province":"QC",
    "sg:tags":[
        "organization",
        "welfare"
    ],
    "wof:name":"Havre DE L'Hospitalite Inc",
    "wof:placetype":"venue"
},
  "geometry": {"coordinates":[-71.61432647709999,48.5354652405],"type":"Point"}
}