{
  "type": "Feature",
  "properties": {
    "addr:full":"19 1st Ave Schumacher ON P0N 1G0",
    "addr:housenumber":"19",
    "addr:postcode":"p0n 1g0",
    "addr:street":"1St Ave",
    "iso:country":"CA",
    "sg:address":"19 1st Ave",
    "sg:city":"Schumacher",
    "sg:classifiers":[
        {
            "category":"Shopping",
            "subcategory":"Bicycles & Sporting Goods",
            "type":"Retail Goods"
        }
    ],
    "sg:phone":"+1 705 268 8069",
    "sg:postcode":"P0N 1G0",
    "sg:province":"ON",
    "sg:tags":[
        "tackle",
        "fishing"
    ],
    "wof:name":"Pro Tackle CO",
    "wof:placetype":"venue"
},
  "geometry": {"coordinates":[-81.297302,48.47691],"type":"Point"}
}