{
  "type": "Feature",
  "properties": {
    "iso:country":"CA",
    "sg:address":"5232 Rue Saint-Andre",
    "sg:city":"Montreal",
    "sg:classifiers":[
        {
            "category":"Building & Trades",
            "subcategory":"Plumbing",
            "type":"Services"
        }
    ],
    "sg:phone":"+1 514 270 7145",
    "sg:postcode":"H2J 3A7",
    "sg:province":"QC",
    "sg:tags":[
        "contractor"
    ],
    "wof:name":"Plomberie Julien Morin",
    "wof:placetype":"venue"
},
  "geometry": {"coordinates":[-73.589058,45.530109],"type":"Point"}
}