{
  "type": "Feature",
  "properties": {
    "addr:full":"334 Twelfth St New Westminster BC V3M 4H6",
    "addr:housenumber":"334",
    "addr:postcode":"v3m 4h6",
    "addr:street":"Twelfth St",
    "iso:country":"CA",
    "sg:address":"334 Twelfth St",
    "sg:city":"New Westminster",
    "sg:classifiers":[
        {
            "category":"Manufacturing",
            "subcategory":"Printing",
            "type":"Manufacturing & Wholesale Goods"
        }
    ],
    "sg:phone":"+1 604 521 1295",
    "sg:postcode":"V3M 4H6",
    "sg:province":"BC",
    "sg:tags":[
        "printer"
    ],
    "wof:name":"Spectrum Graphics",
    "wof:placetype":"venue"
},
  "geometry": {"coordinates":[-122.92579650899999,49.2036361694],"type":"Point"}
}