{
  "type": "Feature",
  "properties": {
    "iso:country":"CA",
    "sg:address":"2827 Shaughnessy St",
    "sg:city":"Port Coquitlam",
    "sg:classifiers":[
        {
            "category":"Retail",
            "subcategory":"Laundry & Dry Cleaning",
            "type":"Services"
        }
    ],
    "sg:phone":"+1 604 942 8037",
    "sg:postcode":"V3C 3H1",
    "sg:province":"BC",
    "sg:tags":[
        "cleaners"
    ],
    "wof:name":"Busy Bee Cleaners & Laundromat",
    "wof:placetype":"venue"
},
  "geometry": {"coordinates":[-122.778274536,49.2658538818],"type":"Point"}
}