{
  "type": "Feature",
  "properties": {
    "addr:full":"RR 4 Rockwood ON N0B 2K0",
    "addr:postcode":"n0b 2k0",
    "addr:street":"Rr 4",
    "iso:country":"CA",
    "sg:address":"RR 4",
    "sg:city":"Rockwood",
    "sg:classifiers":[
        {
            "category":"Shopping",
            "subcategory":"Bicycles & Sporting Goods",
            "type":"Retail Goods"
        }
    ],
    "sg:phone":"+1 519 856 4168",
    "sg:postcode":"N0B 2K0",
    "sg:province":"ON",
    "sg:tags":[
        "music",
        "dealer"
    ],
    "wof:name":"Acton Musicland",
    "wof:placetype":"venue"
},
  "geometry": {"coordinates":[-80.143806,43.618542],"type":"Point"}
}