{
  "type": "Feature",
  "properties": {
    "addr:full":"Edmonton AB T6E 5Y4",
    "addr:postcode":"t6e 5y4",
    "iso:country":"CA",
    "sg:city":"Edmonton",
    "sg:classifiers":[
        {
            "category":"Organizations",
            "subcategory":"Labor Organization",
            "type":"Services"
        }
    ],
    "sg:phone":"+1 780 485 1922",
    "sg:postcode":"T6E 5Y4",
    "sg:province":"AB",
    "wof:name":"Brotherhood of Locomotive Engr",
    "wof:placetype":"venue"
},
  "geometry": {"coordinates":[-113.477791,53.479031],"type":"Point"}
}