{
  "type": "Feature",
  "properties": {
    "addr:full":"186 3rd Ave Benito MB R0L 0C0",
    "addr:housenumber":"186",
    "addr:postcode":"r0l 0c0",
    "addr:street":"3Rd Ave",
    "iso:country":"CA",
    "sg:address":"186 3rd Ave",
    "sg:city":"Benito",
    "sg:classifiers":[
        {
            "category":"Building & Trades",
            "subcategory":"Construction",
            "type":"Services"
        }
    ],
    "sg:phone":"+1 204 539 2017",
    "sg:postcode":"R0L 0C0",
    "sg:province":"MB",
    "sg:tags":[
        "general",
        "contractor"
    ],
    "wof:name":"Yaknovich, Ed",
    "wof:placetype":"venue"
},
  "geometry": {"coordinates":[-101.549911499,51.9155082703],"type":"Point"}
}