{
  "type": "Feature",
  "properties": {
    "addr:full":"Ajax ON L1S 6W4",
    "addr:postcode":"l1s 6w4",
    "iso:country":"CA",
    "sg:city":"Ajax",
    "sg:classifiers":[
        {
            "category":"Wholesale",
            "subcategory":"Electrical",
            "type":"Manufacturing & Wholesale Goods"
        }
    ],
    "sg:phone":"+1 905 426 7682",
    "sg:postcode":"L1S 6W4",
    "sg:province":"ON",
    "sg:tags":[
        "equipment",
        "electric",
        "supply"
    ],
    "wof:name":"Westburne Ruddy Electric",
    "wof:placetype":"venue"
},
  "geometry": {"coordinates":[-79.0327529907,43.8312225342],"type":"Point"}
}