{
  "type": "Feature",
  "properties": {
    "addr:full":"Saint-Pamphile QC G0R 3X0",
    "addr:postcode":"g0r 3x0",
    "iso:country":"CA",
    "sg:city":"Saint-Pamphile",
    "sg:classifiers":[
        {
            "category":"Health Services",
            "subcategory":"Nursing And Care Facility",
            "type":"Services"
        }
    ],
    "sg:phone":"+1 418 356 2504",
    "sg:postcode":"G0R 3X0",
    "sg:province":"QC",
    "sg:tags":[
        "home",
        "retirement",
        "community"
    ],
    "wof:name":"Habitations Saint-Pamphile",
    "wof:placetype":"venue"
},
  "geometry": {"coordinates":[-69.782234,46.960751],"type":"Point"}
}