{
  "type": "Feature",
  "properties": {
    "addr:full":"80 Rideout Rd Lower Brighton NB E7P 2G3",
    "addr:housenumber":"80",
    "addr:postcode":"e7p 2g3",
    "addr:street":"Rideout Rd",
    "iso:country":"CA",
    "sg:address":"80 Rideout Rd",
    "sg:city":"Lower Brighton",
    "sg:classifiers":[
        {
            "category":"Wholesale",
            "subcategory":"Scrap",
            "type":"Manufacturing & Wholesale Goods"
        }
    ],
    "sg:phone":"+1 506 375 6188",
    "sg:postcode":"E7P 2G3",
    "sg:province":"NB",
    "sg:tags":[
        "garbage",
        "recycling",
        "center",
        "collection"
    ],
    "wof:name":"Rideout's Sanitation & Recycle",
    "wof:placetype":"venue"
},
  "geometry": {"coordinates":[-67.420181,46.363632],"type":"Point"}
}