{
  "type": "Feature",
  "properties": {
    "addr:full":"9919 106 St NW Edmonton AB T5K 1E2",
    "addr:housenumber":"9919",
    "addr:postcode":"t5k 1e2",
    "addr:street":"106 St Nw",
    "iso:country":"CA",
    "sg:address":"9919 106 St NW",
    "sg:city":"Edmonton",
    "sg:classifiers":[
        {
            "category":"Organizations",
            "subcategory":"Political Organization",
            "type":"Services"
        }
    ],
    "sg:phone":"+1 780 423 1624",
    "sg:postcode":"T5K 1E2",
    "sg:province":"AB",
    "wof:name":"Progressive Conservative Assn",
    "wof:placetype":"venue"
},
  "geometry": {"coordinates":[-113.50271600000001,53.53764],"type":"Point"}
}