{
  "type": "Feature",
  "properties": {
    "addr:full":"698 Gustavus St Port Elgin ON N0H 2C0",
    "addr:housenumber":"698",
    "addr:postcode":"n0h 2c0",
    "addr:street":"Gustavus St",
    "iso:country":"CA",
    "sg:address":"698 Gustavus St",
    "sg:city":"Port Elgin",
    "sg:classifiers":[
        {
            "category":"Shopping",
            "type":"Retail Goods"
        }
    ],
    "sg:phone":"+1 519 832 6052",
    "sg:postcode":"N0H 2C0",
    "sg:province":"ON",
    "sg:tags":[
        "trophy",
        "medal",
        "award"
    ],
    "wof:name":"First Place Trophies",
    "wof:placetype":"venue"
},
  "geometry": {"coordinates":[-81.385925,44.434383],"type":"Point"}
}