{
  "type": "Feature",
  "properties": {
    "addr:full":"Toronto ON M5T 1S6",
    "addr:postcode":"m5t 1s6",
    "iso:country":"CA",
    "sg:city":"Toronto",
    "sg:classifiers":[
        {
            "category":"Health Services",
            "subcategory":"Doctor",
            "type":"Services"
        }
    ],
    "sg:phone":"+1 416 924 5871",
    "sg:postcode":"M5T 1S6",
    "sg:province":"ON",
    "sg:tags":[
        "physician",
        "surgeon"
    ],
    "wof:name":"Noronha, Luis MD",
    "wof:placetype":"venue"
},
  "geometry": {"coordinates":[-79.4042663574,43.6572647095],"type":"Point"}
}