{
  "type": "Feature",
  "properties": {
    "addr:full":"210 Atwood Ave Rainy River ON P0W 1L0",
    "addr:housenumber":"210",
    "addr:postcode":"p0w 1l0",
    "addr:street":"Atwood Ave",
    "iso:country":"CA",
    "sg:address":"210 Atwood Ave",
    "sg:city":"Rainy River",
    "sg:classifiers":[
        {
            "category":"Social Services",
            "type":"Services"
        }
    ],
    "sg:phone":"+1 807 852 3268",
    "sg:postcode":"P0W 1L0",
    "sg:province":"ON",
    "sg:tags":[
        "organization",
        "welfare"
    ],
    "wof:name":"Northwestern Health Unit",
    "wof:placetype":"venue"
},
  "geometry": {"coordinates":[-94.568016,48.721996],"type":"Point"}
}