{
  "type": "Feature",
  "properties": {
    "addr:full":"407 Mcdermot Ave Winnipeg MB R3A 0A8",
    "addr:housenumber":"407",
    "addr:postcode":"r3a 0a8",
    "addr:street":"Mcdermot Ave",
    "iso:country":"CA",
    "sg:address":"407 Mcdermot Ave",
    "sg:city":"Winnipeg",
    "sg:classifiers":[
        {
            "category":"Manufacturing",
            "subcategory":"Signs",
            "type":"Manufacturing & Wholesale Goods"
        }
    ],
    "sg:phone":"+1 204 943 1262",
    "sg:postcode":"R3A 0A8",
    "sg:province":"MB",
    "wof:name":"Contempra Signs Ltd",
    "wof:placetype":"venue"
},
  "geometry": {"coordinates":[-97.14702606199999,49.899356842],"type":"Point"}
}