{
  "type": "Feature",
  "properties": {
    "addr:full":"622 9th St Gretna MB R0G 0V0",
    "addr:housenumber":"622",
    "addr:postcode":"r0g 0v0",
    "addr:street":"9Th St",
    "iso:country":"CA",
    "sg:address":"622 9th St",
    "sg:city":"Gretna",
    "sg:classifiers":[
        {
            "category":"Education",
            "subcategory":"School",
            "type":"Public Place"
        }
    ],
    "sg:phone":"+1 204 327 5344",
    "sg:postcode":"R0G 0V0",
    "sg:province":"MB",
    "wof:name":"Gretna School",
    "wof:placetype":"venue"
},
  "geometry": {"coordinates":[-97.560997,49.007931],"type":"Point"}
}