{
  "type": "Feature",
  "properties": {
    "addr:full":"1114 Victoria Ave E Thunder Bay ON P7C 1B8",
    "addr:housenumber":"1114",
    "addr:postcode":"p7c 1b8",
    "addr:street":"Victoria Ave E",
    "iso:country":"CA",
    "sg:address":"1114 Victoria Ave E",
    "sg:city":"Thunder Bay",
    "sg:classifiers":[
        {
            "category":"Personal",
            "subcategory":"Beauty Salon",
            "type":"Services"
        }
    ],
    "sg:phone":"+1 807 622 7221",
    "sg:postcode":"P7C 1B8",
    "sg:province":"ON",
    "wof:name":"Continental Hair Stylists",
    "wof:placetype":"venue"
},
  "geometry": {"coordinates":[-89.252876,48.383999],"type":"Point"}
}