{
  "type": "Feature",
  "properties": {
    "iso:country":"CA",
    "sg:address":"12070 88 Ave",
    "sg:city":"Surrey",
    "sg:classifiers":[
        {
            "category":"Building & Trades",
            "subcategory":"Construction",
            "type":"Services"
        }
    ],
    "sg:phone":"+1 604 502 6152",
    "sg:postcode":"V3W 3J2",
    "sg:province":"BC",
    "sg:tags":[
        "resurfacing",
        "laying",
        "refinishing",
        "floor"
    ],
    "wof:name":"King of Floors",
    "wof:placetype":"venue"
},
  "geometry": {"coordinates":[-122.888718,49.163033],"type":"Point"}
}