{
  "type": "Feature",
  "properties": {
    "addr:full":"4301 38 St Camrose AB T4V 3P9",
    "addr:housenumber":"4301",
    "addr:postcode":"t4v 3p9",
    "addr:street":"38 St",
    "iso:country":"CA",
    "sg:address":"4301 38 St",
    "sg:city":"Camrose",
    "sg:classifiers":[
        {
            "category":"Health Services",
            "subcategory":"Clinic",
            "type":"Services"
        }
    ],
    "sg:phone":"+1 780 672 3204",
    "sg:postcode":"T4V 3P9",
    "sg:province":"AB",
    "sg:tags":[
        "information",
        "program",
        "referral"
    ],
    "wof:name":"Take Care Mobility",
    "wof:placetype":"venue"
},
  "geometry": {"coordinates":[-112.802567,53.008564],"type":"Point"}
}