{
  "type": "Feature",
  "properties": {
    "addr:full":"1055 Bay St Toronto ON M5S 3A3",
    "addr:housenumber":"1055",
    "addr:postcode":"m5s 3a3",
    "addr:street":"Bay St",
    "iso:country":"CA",
    "sg:address":"1055 Bay St",
    "sg:city":"Toronto",
    "sg:classifiers":[
        {
            "category":"Shopping",
            "subcategory":"Books",
            "type":"Retail Goods"
        }
    ],
    "sg:phone":"+1 416 485 5316",
    "sg:postcode":"M5S 3A3",
    "sg:province":"ON",
    "sg:tags":[
        "dealer"
    ],
    "wof:name":"Golf Gap",
    "wof:placetype":"venue"
},
  "geometry": {"coordinates":[-79.38804626460001,43.6666145325],"type":"Point"}
}