{
  "type": "Feature",
  "properties": {
    "addr:full":"13203 66 St NW Edmonton AB T5C 0B2",
    "addr:housenumber":"13203",
    "addr:postcode":"t5c 0b2",
    "addr:street":"66 St Nw",
    "iso:country":"CA",
    "sg:address":"13203 66 St NW",
    "sg:city":"Edmonton",
    "sg:classifiers":[
        {
            "category":"Autos & Motor Vehicles",
            "subcategory":"Fuel & Gas Station",
            "type":"Retail Goods"
        }
    ],
    "sg:phone":"+1 780 478 4071",
    "sg:postcode":"T5C 0B2",
    "sg:province":"AB",
    "sg:tags":[
        "oil"
    ],
    "wof:name":"Belvedere Chicken Bakery-Deli",
    "wof:placetype":"venue"
},
  "geometry": {"coordinates":[-113.442687988,53.5924453735],"type":"Point"}
}