{
  "type": "Feature",
  "properties": {
    "addr:full":"Surrey BC V4P 1H5",
    "addr:postcode":"v4p 1h5",
    "iso:country":"CA",
    "sg:city":"Surrey",
    "sg:classifiers":[
        {
            "category":"Recreation",
            "type":"Entertainment"
        }
    ],
    "sg:phone":"+1 604 531 3410",
    "sg:postcode":"V4P 1H5",
    "sg:province":"BC",
    "sg:tags":[
        "martial",
        "arts",
        "instruction"
    ],
    "wof:name":"Executive Club",
    "wof:placetype":"venue"
},
  "geometry": {"coordinates":[-122.794250488,49.0463294983],"type":"Point"}
}