{
  "type": "Feature",
  "properties": {
    "addr:full":"376 Mary St Niagara on the Lake ON L0S 1J0",
    "addr:housenumber":"376",
    "addr:postcode":"l0s 1j0",
    "addr:street":"Mary St;On",
    "iso:country":"CA",
    "sg:address":"376 Mary St",
    "sg:city":"Niagara on the Lake",
    "sg:classifiers":[
        {
            "category":"Personal",
            "subcategory":"Beauty Salon",
            "type":"Services"
        }
    ],
    "sg:phone":"+1 905 468 2503",
    "sg:postcode":"L0S 1J0",
    "sg:province":"ON",
    "wof:name":"Rapunzel's",
    "wof:placetype":"venue"
},
  "geometry": {"coordinates":[-79.08792099999999,43.254704],"type":"Point"}
}