{
  "type": "Feature",
  "properties": {
    "addr:full":"616 Trounce Alley Victoria BC V8W 1K3",
    "addr:housenumber":"616",
    "addr:postcode":"v8w 1k3",
    "addr:street":"Trounce Alley",
    "iso:country":"CA",
    "sg:address":"616 Trounce Alley",
    "sg:city":"Victoria",
    "sg:classifiers":[
        {
            "category":"Shopping",
            "subcategory":"Gifts & Souvenirs",
            "type":"Retail Goods"
        }
    ],
    "sg:phone":"+1 250 383 1883",
    "sg:postcode":"V8W 1K3",
    "sg:province":"BC",
    "sg:tags":[
        "shop"
    ],
    "wof:name":"All in Bloom",
    "wof:placetype":"venue"
},
  "geometry": {"coordinates":[-123.367386,48.425915],"type":"Point"}
}