{
  "type": "Feature",
  "properties": {
    "addr:full":"Edmonton AB T6H 2K3",
    "addr:postcode":"t6h 2k3",
    "iso:country":"CA",
    "sg:city":"Edmonton",
    "sg:classifiers":[
        {
            "category":"Autos & Motor Vehicles",
            "subcategory":"Fuel & Gas Station",
            "type":"Retail Goods"
        }
    ],
    "sg:phone":"+1 780 437 2220",
    "sg:postcode":"T6H 2K3",
    "sg:province":"AB",
    "sg:tags":[
        "oil"
    ],
    "wof:name":"South Side Shell Self Svc",
    "wof:placetype":"venue"
},
  "geometry": {"coordinates":[-113.49789428699999,53.4954605103],"type":"Point"}
}