{
  "type": "Feature",
  "properties": {
    "addr:full":"5985 Rodeo Dr Mississauga ON L5R 3X8",
    "addr:housenumber":"5985",
    "addr:postcode":"l5r 3x8",
    "addr:street":"Rodeo Dr",
    "iso:country":"CA",
    "sg:address":"5985 Rodeo Dr",
    "sg:city":"Mississauga",
    "sg:classifiers":[
        {
            "category":"Shopping",
            "subcategory":"Clothing, Apparel, & Fashions",
            "type":"Retail Goods"
        }
    ],
    "sg:phone":"+1 905 502 8169",
    "sg:postcode":"L5R 3X8",
    "sg:province":"ON",
    "sg:tags":[
        "boutique",
        "accessory"
    ],
    "wof:name":"Tristan & America",
    "wof:placetype":"venue"
},
  "geometry": {"coordinates":[-79.69135300000001,43.614239],"type":"Point"}
}