{
  "type": "Feature",
  "properties": {
    "iso:country":"CA",
    "sg:address":"120 Rue Dollard",
    "sg:city":"Saint-Jean-Sur-Richelieu",
    "sg:classifiers":[
        {
            "category":"Organizations",
            "subcategory":"Religious Organization",
            "type":"Services"
        }
    ],
    "sg:phone":"+1 450 346 9785",
    "sg:postcode":"J3B 5G5",
    "sg:province":"QC",
    "sg:tags":[
        "church"
    ],
    "wof:name":"Presbytere St Lucien",
    "wof:placetype":"venue"
},
  "geometry": {"coordinates":[-73.2695159912,45.3031005859],"type":"Point"}
}