{
  "type": "Feature",
  "properties": {
    "iso:country":"CA",
    "sg:address":"4020 Boul DE Portland",
    "sg:city":"Sherbrooke",
    "sg:classifiers":[
        {
            "category":"Communications",
            "subcategory":"Radio Station",
            "type":"Services"
        }
    ],
    "sg:phone":"+1 819 563 6363",
    "sg:postcode":"J1L 2V6",
    "sg:province":"QC",
    "sg:tags":[
        "company",
        "broadcasting"
    ],
    "wof:name":"Chlt",
    "wof:placetype":"venue"
},
  "geometry": {"coordinates":[-71.964684,45.402603],"type":"Point"}
}