{
  "type": "Feature",
  "properties": {
    "addr:full":"4020 Boul DE Portland Sherbrooke QC J1L 2V6",
    "addr:housenumber":"4020",
    "addr:postcode":"j1l 2v6",
    "addr:street":"Boul De Portland",
    "iso:country":"CA",
    "sg:address":"4020 Boul DE Portland",
    "sg:city":"Sherbrooke",
    "sg:classifiers":[
        {
            "category":"Communications",
            "subcategory":"Radio Station",
            "type":"Services"
        }
    ],
    "sg:phone":"+1 819 563 6363",
    "sg:postcode":"J1L 2V6",
    "sg:province":"QC",
    "sg:tags":[
        "company",
        "broadcasting"
    ],
    "wof:name":"Chlt",
    "wof:placetype":"venue"
},
  "geometry": {"coordinates":[-71.96468400000001,45.402603],"type":"Point"}
}