{
  "type": "Feature",
  "properties": {
    "addr:full":"Etobicoke ON M9A 3T7",
    "addr:postcode":"m9a 3t7",
    "iso:country":"CA",
    "sg:city":"Etobicoke",
    "sg:classifiers":[
        {
            "category":"Health Services",
            "subcategory":"Doctor",
            "type":"Services"
        }
    ],
    "sg:phone":"+1 416 239 6958",
    "sg:postcode":"M9A 3T7",
    "sg:province":"ON",
    "sg:tags":[
        "dentist"
    ],
    "wof:name":"Humbertown Dental Ctr",
    "wof:placetype":"venue"
},
  "geometry": {"coordinates":[-79.52010300000001,43.662872],"type":"Point"}
}