{
  "type": "Feature",
  "properties": {
    "iso:country":"CA",
    "sg:address":"1490 Av DE L'Eglise",
    "sg:city":"Montreal",
    "sg:classifiers":[
        {
            "category":"Autos & Motor Vehicles",
            "subcategory":"Fuel & Gas Station",
            "type":"Retail Goods"
        }
    ],
    "sg:phone":"+1 514 768 0397",
    "sg:postcode":"H4E 1G2",
    "sg:province":"QC",
    "sg:tags":[
        "oil"
    ],
    "wof:name":"Sonic Super Svc",
    "wof:placetype":"venue"
},
  "geometry": {"coordinates":[-73.58093261720001,45.4634246826],"type":"Point"}
}