{
  "type": "Feature",
  "properties": {
    "addr:full":"PO Box 1013 Rosetown SK S0L 2V0",
    "addr:housenumber":"po",
    "addr:postcode":"s0l 2v0",
    "addr:street":"Box 1013",
    "iso:country":"CA",
    "sg:address":"PO Box 1013",
    "sg:city":"Rosetown",
    "sg:classifiers":[
        {
            "category":"Sports & Exercise",
            "subcategory":"Golf",
            "type":"Entertainment"
        }
    ],
    "sg:phone":"+1 306 882 3001",
    "sg:postcode":"S0L 2V0",
    "sg:province":"SK",
    "sg:tags":[
        "course"
    ],
    "wof:name":"Rosetown Golf & Country Club",
    "wof:placetype":"venue"
},
  "geometry": {"coordinates":[-107.986946,51.550285],"type":"Point"}
}