{
  "type": "Feature",
  "properties": {
    "addr:full":"405 3E Rue Quebec QC G1J 2T9",
    "addr:housenumber":"405",
    "addr:postcode":"g1j 2t9",
    "addr:street":"3E Rue Quebec",
    "iso:country":"CA",
    "sg:address":"405 3E Rue",
    "sg:city":"Quebec",
    "sg:classifiers":[
        {
            "category":"Communications",
            "subcategory":"Radio Station",
            "type":"Services"
        }
    ],
    "sg:phone":"+1 418 640 2575",
    "sg:postcode":"G1J 2T9",
    "sg:province":"QC",
    "sg:tags":[
        "company",
        "broadcasting"
    ],
    "wof:name":"Ckrl-FM",
    "wof:placetype":"venue"
},
  "geometry": {"coordinates":[-71.22363300000001,46.822884],"type":"Point"}
}