{
  "type": "Feature",
  "properties": {
    "addr:full":"Sunnyside NL A0B 3J0",
    "addr:postcode":"a0b 3j0",
    "iso:country":"CA",
    "sg:city":"Sunnyside",
    "sg:classifiers":[
        {
            "category":"Personal",
            "subcategory":"Beauty Salon",
            "type":"Services"
        }
    ],
    "sg:phone":"+1 709 472 4405",
    "sg:postcode":"A0B 3J0",
    "sg:province":"NL",
    "wof:name":"Karen's Hair Shop",
    "wof:placetype":"venue"
},
  "geometry": {"coordinates":[-53.9495048523,47.8950691223],"type":"Point"}
}