{
  "type": "Feature",
  "properties": {
    "addr:full":"390 Steeles Ave W # 6 Thornhill ON L4J 6X2",
    "addr:housenumber":"390",
    "addr:postcode":"l4j 6x2",
    "addr:street":"Steeles Ave W # 6",
    "iso:country":"CA",
    "sg:address":"390 Steeles Ave W # 6",
    "sg:city":"Thornhill",
    "sg:classifiers":[
        {
            "category":"Restaurant",
            "type":"Food & Drink"
        }
    ],
    "sg:phone":"+1 905 764 6440",
    "sg:postcode":"L4J 6X2",
    "sg:province":"ON",
    "wof:name":"Sababa Restaurant",
    "wof:placetype":"venue"
},
  "geometry": {"coordinates":[-79.433601,43.795212],"type":"Point"}
}