{
  "type": "Feature",
  "properties": {
    "addr:full":"132 Browns Line Etobicoke ON M8W 3T2",
    "addr:housenumber":"132",
    "addr:postcode":"m8w 3t2",
    "addr:street":"Browns Line",
    "iso:country":"CA",
    "sg:address":"132 Browns Line",
    "sg:city":"Etobicoke",
    "sg:classifiers":[
        {
            "category":"Home & Garden",
            "subcategory":"Building Materials",
            "type":"Retail Goods"
        }
    ],
    "sg:phone":"+1 416 259 2100",
    "sg:postcode":"M8W 3T2",
    "sg:province":"ON",
    "sg:tags":[
        "glass",
        "window",
        "plate"
    ],
    "wof:name":"Shells Glass",
    "wof:placetype":"venue"
},
  "geometry": {"coordinates":[-79.5429229736,43.5961532593],"type":"Point"}
}