{
  "type": "Feature",
  "properties": {
    "addr:full":"2481 39 Ave NE Calgary AB T2E 8V8",
    "addr:housenumber":"2481",
    "addr:postcode":"t2e 8v8",
    "addr:street":"39 Ave Ne",
    "iso:country":"CA",
    "sg:address":"2481 39 Ave NE",
    "sg:city":"Calgary",
    "sg:classifiers":[
        {
            "category":"Travel",
            "subcategory":"Hotels & Motels",
            "type":"Entertainment"
        }
    ],
    "sg:phone":"+1 403 250 1800",
    "sg:postcode":"T2E 8V8",
    "sg:province":"AB",
    "wof:name":"Country Inn & Suites",
    "wof:placetype":"venue"
},
  "geometry": {"coordinates":[-114.00314299999999,51.088089],"type":"Point"}
}