{
  "type": "Feature",
  "properties": {
    "addr:full":"267 Main Ave Plum Coulee MB R0G 1R0",
    "addr:housenumber":"267",
    "addr:postcode":"r0g 1r0",
    "addr:street":"Main Ave",
    "iso:country":"CA",
    "sg:address":"267 Main Ave",
    "sg:city":"Plum Coulee",
    "sg:classifiers":[
        {
            "category":"Restaurant",
            "type":"Food & Drink"
        }
    ],
    "sg:phone":"+1 204 829 3281",
    "sg:postcode":"R0G 1R0",
    "sg:province":"MB",
    "sg:tags":[
        "shop",
        "coffee"
    ],
    "wof:name":"Plum Coulee New Horizon",
    "wof:placetype":"venue"
},
  "geometry": {"coordinates":[-97.76720400000001,49.189449],"type":"Point"}
}