{
  "type": "Feature",
  "properties": {
    "iso:country":"CA",
    "sg:address":"2605 Stagecoach Rd",
    "sg:city":"Osgoode",
    "sg:classifiers":[
        {
            "category":"Autos & Motor Vehicles",
            "subcategory":"Auto Supplies",
            "type":"Retail Goods"
        }
    ],
    "sg:phone":"+1 613 821 2953",
    "sg:postcode":"K0A 2W0",
    "sg:province":"ON",
    "sg:tags":[
        "tire"
    ],
    "wof:name":"Osgoode Tire Sales",
    "wof:placetype":"venue"
},
  "geometry": {"coordinates":[-75.567527771,45.1954116821],"type":"Point"}
}