{
  "type": "Feature",
  "properties": {
    "addr:full":"4513 Lakeshore Dr Sylvan Lake AB T4S 1C3",
    "addr:housenumber":"4513",
    "addr:postcode":"t4s 1c3",
    "addr:street":"Lakeshore Dr",
    "iso:country":"CA",
    "sg:address":"4513 Lakeshore Dr",
    "sg:city":"Sylvan Lake",
    "sg:classifiers":[
        {
            "category":"Restaurant",
            "type":"Food & Drink"
        }
    ],
    "sg:phone":"+1 403 887 5675",
    "sg:postcode":"T4S 1C3",
    "sg:province":"AB",
    "wof:name":"Kfc",
    "wof:placetype":"venue"
},
  "geometry": {"coordinates":[-114.09219400000001,52.311836],"type":"Point"}
}