{
  "type": "Feature",
  "properties": {
    "addr:full":"5619 Boul Des Laurentides Laval QC H7K 2K4",
    "addr:housenumber":"5619",
    "addr:postcode":"qc h7k 2k4",
    "addr:street":"Boul Des Laurentides",
    "iso:country":"CA",
    "sg:address":"5619 Boul Des Laurentides",
    "sg:city":"Laval",
    "sg:classifiers":[
        {
            "category":"Social Services",
            "subcategory":"Child Care",
            "type":"Services"
        }
    ],
    "sg:phone":"+1 450 622 8839",
    "sg:postcode":"H7K 2K4",
    "sg:province":"QC",
    "wof:name":"Garderie Le Petit Monde",
    "wof:placetype":"venue"
},
  "geometry": {"coordinates":[-73.7515258789,45.6274757385],"type":"Point"}
}