{
  "type": "Feature",
  "properties": {
    "addr:full":"962 Park Royal S # A West Vancouver BC V7T 1A1",
    "addr:housenumber":"962",
    "addr:postcode":"v7t 1a1",
    "addr:street":"Park Royal S # A",
    "iso:country":"CA",
    "sg:address":"962 Park Royal S # A",
    "sg:city":"West Vancouver",
    "sg:classifiers":[
        {
            "category":"Shopping",
            "type":"Retail Goods"
        }
    ],
    "sg:phone":"+1 604 925 2070",
    "sg:postcode":"V7T 1A1",
    "sg:province":"BC",
    "sg:tags":[
        "coin",
        "dealer",
        "supply"
    ],
    "wof:name":"Balmoral Coins & Stamps",
    "wof:placetype":"venue"
},
  "geometry": {"coordinates":[-123.140396,49.32584],"type":"Point"}
}