{
  "type": "Feature",
  "properties": {
    "addr:full":"151 Toryork Dr North York ON M9L 1X9",
    "addr:housenumber":"151",
    "addr:postcode":"m9l 1x9",
    "addr:street":"Toryork Dr",
    "iso:country":"CA",
    "sg:address":"151 Toryork Dr",
    "sg:city":"North York",
    "sg:classifiers":[
        {
            "category":"Retail",
            "subcategory":"Auto Repair",
            "type":"Services"
        }
    ],
    "sg:phone":"+1 416 745 1285",
    "sg:postcode":"M9L 1X9",
    "sg:province":"ON",
    "sg:tags":[
        "repairing",
        "automobile"
    ],
    "wof:name":"Westside Automotive Svc",
    "wof:placetype":"venue"
},
  "geometry": {"coordinates":[-79.554649,43.757812],"type":"Point"}
}