{
  "type": "Feature",
  "properties": {
    "addr:full":"10210 Centennial Dr Fort Mcmurray AB T9H 1Y5",
    "addr:housenumber":"10210",
    "addr:postcode":"t9h 1y5",
    "addr:street":"Centennial Dr",
    "iso:country":"CA",
    "sg:address":"10210 Centennial Dr",
    "sg:city":"Fort Mcmurray",
    "sg:classifiers":[
        {
            "category":"Insurance",
            "subcategory":"Insurance Agent",
            "type":"Services"
        }
    ],
    "sg:phone":"+1 780 790 0090",
    "sg:postcode":"T9H 1Y5",
    "sg:province":"AB",
    "sg:tags":[
        "adjuster"
    ],
    "wof:name":"Shumka Craig & Moore Adjusters",
    "wof:placetype":"venue"
},
  "geometry": {"coordinates":[-111.35002899200001,56.7181243896],"type":"Point"}
}