{
  "type": "Feature",
  "properties": {
    "addr:full":"10077 Yonge St Richmond Hill ON L4C 1T7",
    "addr:housenumber":"10077",
    "addr:postcode":"l4c 1t7",
    "addr:street":"Yonge St",
    "iso:country":"CA",
    "sg:address":"10077 Yonge St",
    "sg:city":"Richmond Hill",
    "sg:classifiers":[
        {
            "category":"Education",
            "subcategory":"School",
            "type":"Public Place"
        }
    ],
    "sg:phone":"+1 905 884 8850",
    "sg:postcode":"L4C 1T7",
    "sg:province":"ON",
    "sg:tags":[
        "instruction",
        "dancing"
    ],
    "wof:name":"C B Dance Academy",
    "wof:placetype":"venue"
},
  "geometry": {"coordinates":[-79.4374160767,43.873046875],"type":"Point"}
}