{
  "type": "Feature",
  "properties": {
    "addr:full":"Conception Bay South NL A1W 5C6",
    "addr:postcode":"a1w 5c6",
    "iso:country":"CA",
    "sg:city":"Conception Bay South",
    "sg:classifiers":[
        {
            "category":"Organizations",
            "subcategory":"Religious Organization",
            "type":"Services"
        }
    ],
    "sg:phone":"+1 709 834 2336",
    "sg:postcode":"A1W 5C6",
    "sg:province":"NL",
    "sg:tags":[
        "church"
    ],
    "wof:name":"St John the Evangelist",
    "wof:placetype":"venue"
},
  "geometry": {"coordinates":[-52.938328,47.536739],"type":"Point"}
}