{
  "type": "Feature",
  "properties": {
    "iso:country":"CA",
    "sg:city":"Edmonton",
    "sg:classifiers":[
        {
            "category":"Government",
            "subcategory":"Office",
            "type":"Public Place"
        }
    ],
    "sg:phone":"+1 780 414 1328",
    "sg:postcode":"T5E 4C2",
    "sg:province":"AB",
    "wof:name":"Edmonton Glengarry",
    "wof:placetype":"venue"
},
  "geometry": {"coordinates":[-113.491844177,53.5879173279],"type":"Point"}
}