{
  "type": "Feature",
  "properties": {
    "addr:full":"160 Av Du Sacre-Coeur Quebec QC G1N 2W2",
    "addr:housenumber":"160",
    "addr:postcode":"g1n 2w2",
    "addr:street":"Av Du Sacre-Coeur",
    "iso:country":"CA",
    "sg:address":"160 Av Du Sacre-Coeur",
    "sg:city":"Quebec",
    "sg:classifiers":[
        {
            "category":"Sports & Exercise",
            "subcategory":"Bowling",
            "type":"Entertainment"
        }
    ],
    "sg:phone":"+1 418 523 2973",
    "sg:postcode":"G1N 2W2",
    "sg:province":"QC",
    "sg:tags":[
        "center"
    ],
    "wof:name":"Salle DE Quilles Montmartre",
    "wof:placetype":"venue"
},
  "geometry": {"coordinates":[-71.244347,46.810944],"type":"Point"}
}