{
  "type": "Feature",
  "properties": {
    "iso:country":"CA",
    "sg:address":"10 Christopher Crt",
    "sg:city":"Saint John",
    "sg:classifiers":[
        {
            "category":"Real Estate",
            "subcategory":"Real Estate Operator",
            "type":"Services"
        }
    ],
    "sg:phone":"+1 506 658 1132",
    "sg:postcode":"E2K 4L5",
    "sg:province":"NB",
    "sg:tags":[
        "apartment"
    ],
    "wof:name":"Cedar Glen Apartments",
    "wof:placetype":"venue"
},
  "geometry": {"coordinates":[-66.08709,45.296776],"type":"Point"}
}