{
  "type": "Feature",
  "properties": {
    "addr:full":"359 Wheelabrator Way Milton ON L9T 3C1",
    "addr:housenumber":"359",
    "addr:postcode":"l9t 3c1",
    "addr:street":"Wheelabrator Way",
    "iso:country":"CA",
    "sg:address":"359 Wheelabrator Way",
    "sg:city":"Milton",
    "sg:classifiers":[
        {
            "category":"Home & Garden",
            "subcategory":"Building Materials",
            "type":"Retail Goods"
        }
    ],
    "sg:phone":"+1 905 876 1290",
    "sg:postcode":"L9T 3C1",
    "sg:province":"ON",
    "sg:tags":[
        "door"
    ],
    "wof:name":"Elton Manufacturing",
    "wof:placetype":"venue"
},
  "geometry": {"coordinates":[-79.892906189,43.5257606506],"type":"Point"}
}