{
  "type": "Feature",
  "properties": {
    "addr:full":"9150 Rue Edison Anjou QC H1J 1T1",
    "addr:housenumber":"9150",
    "addr:postcode":"h1j 1t1",
    "addr:street":"Rue Edison",
    "iso:country":"CA",
    "sg:address":"9150 Rue Edison",
    "sg:city":"Anjou",
    "sg:classifiers":[
        {
            "category":"Wholesale",
            "subcategory":"Home Furnishings",
            "type":"Manufacturing & Wholesale Goods"
        }
    ],
    "sg:phone":"+1 514 354 1971",
    "sg:postcode":"H1J 1T1",
    "sg:province":"QC",
    "sg:tags":[
        "rug",
        "carpet"
    ],
    "wof:name":"Tapis Beaver Carpets Ltee",
    "wof:placetype":"venue"
},
  "geometry": {"coordinates":[-73.56857299799999,45.6121292114],"type":"Point"}
}