{
  "type": "Feature",
  "properties": {
    "addr:full":"150 Main St N Morris MB R0G 1K0",
    "addr:housenumber":"150",
    "addr:postcode":"r0g 1k0",
    "addr:street":"Main St N",
    "iso:country":"CA",
    "sg:address":"150 Main St N",
    "sg:city":"Morris",
    "sg:classifiers":[
        {
            "category":"Shopping",
            "subcategory":"Catalog Store",
            "type":"Retail Goods"
        }
    ],
    "sg:phone":"+1 204 746 2389",
    "sg:postcode":"R0G 1K0",
    "sg:province":"MB",
    "sg:tags":[
        "mail",
        "order",
        "internet"
    ],
    "wof:name":"Sears Canada Inc",
    "wof:placetype":"venue"
},
  "geometry": {"coordinates":[-97.36421199999999,49.355774],"type":"Point"}
}