{
  "type": "Feature",
  "properties": {
    "addr:full":"75 8E Rue Laval QC H7N 2C5",
    "addr:housenumber":"75",
    "addr:postcode":"h7n 2c5",
    "addr:street":"8E Rue",
    "iso:country":"CA",
    "sg:address":"75 8E Rue",
    "sg:city":"Laval",
    "sg:classifiers":[
        {
            "category":"Personal",
            "subcategory":"Barber",
            "type":"Services"
        }
    ],
    "sg:phone":"+1 450 629 5033",
    "sg:postcode":"H7N 2C5",
    "sg:province":"QC",
    "wof:name":"Salon DE Barbier Tony",
    "wof:placetype":"venue"
},
  "geometry": {"coordinates":[-73.770966,45.641132],"type":"Point"}
}