{
  "type": "Feature",
  "properties": {
    "addr:full":"800 Grand Lake Rd Sydney NS B1P 6S9",
    "addr:housenumber":"800",
    "addr:postcode":"b1p 6s9",
    "addr:street":"Grand Lake Rd",
    "iso:country":"CA",
    "sg:address":"800 Grand Lake Rd",
    "sg:city":"Sydney",
    "sg:classifiers":[
        {
            "category":"Shopping",
            "subcategory":"Clothing, Apparel, & Fashions",
            "type":"Retail Goods"
        }
    ],
    "sg:phone":"+1 902 539 1988",
    "sg:postcode":"B1P 6S9",
    "sg:province":"NS",
    "wof:name":"City Streets",
    "wof:placetype":"venue"
},
  "geometry": {"coordinates":[-60.1285591125,46.153339386],"type":"Point"}
}