{
  "type": "Feature",
  "properties": {
    "addr:full":"Campbell River BC V9W 2W3",
    "addr:postcode":"v9w 2w3",
    "iso:country":"CA",
    "sg:city":"Campbell River",
    "sg:classifiers":[
        {
            "category":"Real Estate",
            "subcategory":"Real Estate Operator",
            "type":"Services"
        }
    ],
    "sg:phone":"+1 250 287 7763",
    "sg:postcode":"V9W 2W3",
    "sg:province":"BC",
    "sg:tags":[
        "apartment"
    ],
    "wof:name":"Terrace View Apartments",
    "wof:placetype":"venue"
},
  "geometry": {"coordinates":[-125.246529,50.024117],"type":"Point"}
}