{
  "type": "Feature",
  "properties": {
    "addr:full":"110 69th Ave E Vancouver BC V5X 4K6",
    "addr:housenumber":"110",
    "addr:postcode":"v5x 4k6",
    "addr:street":"69Th Ave E",
    "iso:country":"CA",
    "sg:address":"110 69th Ave E",
    "sg:city":"Vancouver",
    "sg:classifiers":[
        {
            "category":"Wholesale",
            "subcategory":"Scrap",
            "type":"Manufacturing & Wholesale Goods"
        }
    ],
    "sg:phone":"+1 604 327 5052",
    "sg:postcode":"V5X 4K6",
    "sg:province":"BC",
    "sg:tags":[
        "recycling",
        "center"
    ],
    "wof:name":"Urban Woodwaste Recyclers Ltd",
    "wof:placetype":"venue"
},
  "geometry": {"coordinates":[-123.10430145300001,49.2092666626],"type":"Point"}
}