{
  "type": "Feature",
  "properties": {
    "addr:full":"32 Tidefall Dr Scarborough ON M1W 1J2",
    "addr:housenumber":"32",
    "addr:postcode":"m1w 1j2",
    "addr:street":"Tidefall Dr",
    "iso:country":"CA",
    "sg:address":"32 Tidefall Dr",
    "sg:city":"Scarborough",
    "sg:classifiers":[
        {
            "category":"Real Estate",
            "subcategory":"Real Estate Agent",
            "type":"Services"
        }
    ],
    "sg:phone":"+1 416 499 4994",
    "sg:postcode":"M1W 1J2",
    "sg:province":"ON",
    "wof:name":"Red Roof Realty Inc",
    "wof:placetype":"venue"
},
  "geometry": {"coordinates":[-79.320358,43.78373],"type":"Point"}
}