{
  "type": "Feature",
  "properties": {
    "addr:full":"4856 48 Ave Delta BC V4K 1V1",
    "addr:housenumber":"4856",
    "addr:postcode":"v4k 1v1",
    "addr:street":"48 Ave",
    "iso:country":"CA",
    "sg:address":"4856 48 Ave",
    "sg:city":"Delta",
    "sg:classifiers":[
        {
            "category":"Restaurant",
            "type":"Food & Drink"
        }
    ],
    "sg:phone":"+1 604 946 7717",
    "sg:postcode":"V4K 1V1",
    "sg:province":"BC",
    "wof:name":"Belle Auberge Restaurant",
    "wof:placetype":"venue"
},
  "geometry": {"coordinates":[-123.089088,49.090031],"type":"Point"}
}