{
  "type": "Feature",
  "properties": {
    "addr:full":"2020 Rue Royale Trois-Rivieres QC G9A 4L2",
    "addr:housenumber":"2020",
    "addr:postcode":"g9a 4l2",
    "addr:street":"Rue Royale",
    "iso:country":"CA",
    "sg:address":"2020 Rue Royale",
    "sg:city":"Trois-Rivieres",
    "sg:classifiers":[
        {
            "category":"Retail",
            "subcategory":"Auto Repair",
            "type":"Services"
        }
    ],
    "sg:phone":"+1 819 373 9736",
    "sg:postcode":"G9A 4L2",
    "sg:province":"QC",
    "sg:tags":[
        "repairing",
        "automobile",
        "dealer"
    ],
    "wof:name":"Deziel Auto Inc",
    "wof:placetype":"venue"
},
  "geometry": {"coordinates":[-72.547302,46.337261],"type":"Point"}
}