{
  "type": "Feature",
  "properties": {
    "iso:country":"CA",
    "sg:address":"49 Silver Birch Dr",
    "sg:city":"Brandon",
    "sg:classifiers":[
        {
            "category":"Education",
            "subcategory":"School",
            "type":"Public Place"
        }
    ],
    "sg:phone":"+1 204 729 3260",
    "sg:postcode":"R7B 1A8",
    "sg:province":"MB",
    "wof:name":"Linden Lanes School",
    "wof:placetype":"venue"
},
  "geometry": {"coordinates":[-99.979355,49.830097],"type":"Point"}
}