{
  "type": "Feature",
  "properties": {
    "addr:full":"Pth 6 & PR 513 St Martin MB R0C 2T0",
    "addr:housenumber":"513",
    "addr:postcode":"r0c 2t0",
    "addr:street":"Pth 6 & Pr",
    "iso:country":"CA",
    "sg:address":"Pth 6 & PR 513",
    "sg:city":"St Martin",
    "sg:classifiers":[
        {
            "category":"Insurance",
            "subcategory":"Insurance Agent",
            "type":"Services"
        }
    ],
    "sg:phone":"+1 204 659 5226",
    "sg:postcode":"R0C 2T0",
    "sg:province":"MB",
    "wof:name":"Turman's Agency",
    "wof:placetype":"venue"
},
  "geometry": {"coordinates":[-98.6894454956,51.718585968],"type":"Point"}
}