{
  "type": "Feature",
  "properties": {
    "iso:country":"CA",
    "sg:address":"34 Maple View Cres",
    "sg:city":"Nepean",
    "sg:classifiers":[
        {
            "category":"Professional",
            "subcategory":"Business Services",
            "type":"Services"
        }
    ],
    "sg:phone":"+1 613 799 2010",
    "sg:postcode":"K2G 5J4",
    "sg:province":"ON",
    "sg:tags":[
        "party",
        "planning"
    ],
    "wof:name":"Picture Perfect Planners",
    "wof:placetype":"venue"
},
  "geometry": {"coordinates":[-75.7629394531,45.3367271423],"type":"Point"}
}