{
  "type": "Feature",
  "properties": {
    "addr:full":"Surrey BC V3S 2V8",
    "addr:postcode":"v3s 2v8",
    "iso:country":"CA",
    "sg:city":"Surrey",
    "sg:classifiers":[
        {
            "category":"Home & Garden",
            "subcategory":"Carpets & Floor Coverings",
            "type":"Retail Goods"
        }
    ],
    "sg:phone":"+1 604 589 9696",
    "sg:postcode":"V3S 2V8",
    "sg:province":"BC",
    "sg:tags":[
        "dealer",
        "rug"
    ],
    "wof:name":"Carpet Centre Factory Direct",
    "wof:placetype":"venue"
},
  "geometry": {"coordinates":[-122.79089399999999,49.162189],"type":"Point"}
}