{
  "type": "Feature",
  "properties": {
    "iso:country":"CA",
    "sg:address":"70 Raglan Rd",
    "sg:city":"Kingston",
    "sg:classifiers":[
        {
            "category":"Personal",
            "subcategory":"Beauty Salon",
            "type":"Services"
        }
    ],
    "sg:phone":"+1 613 544 5138",
    "sg:postcode":"K7K 1K8",
    "sg:province":"ON",
    "wof:name":"Blaney's Anti Aging Spa",
    "wof:placetype":"venue"
},
  "geometry": {"coordinates":[-76.48565673829999,44.2376174927],"type":"Point"}
}