{
  "type": "Feature",
  "properties": {
    "addr:full":"120 Boul DE L'Hopital # 155 Gatineau QC J8T 8M2",
    "addr:housenumber":"120",
    "addr:postcode":"j8t 8m2",
    "addr:street":"Boul De L'Hopital # 155",
    "iso:country":"CA",
    "sg:address":"120 Boul DE L'Hopital # 155",
    "sg:city":"Gatineau",
    "sg:classifiers":[
        {
            "category":"Health Services",
            "subcategory":"Doctor",
            "type":"Services"
        }
    ],
    "sg:phone":"+1 819 561 0002",
    "sg:postcode":"J8T 8M2",
    "sg:province":"QC",
    "sg:tags":[
        "clinic"
    ],
    "wof:name":"Polyclinique DE L'Oreille",
    "wof:placetype":"venue"
},
  "geometry": {"coordinates":[-75.6874465942,45.4796981812],"type":"Point"}
}