{
  "type": "Feature",
  "properties": {
    "addr:full":"562 Knowlton Rd Knowlton QC J0E 1V0",
    "addr:housenumber":"562",
    "addr:postcode":"j0e 1v0",
    "addr:street":"Knowlton Rd",
    "iso:country":"CA",
    "sg:address":"562 Knowlton Rd",
    "sg:city":"Knowlton",
    "sg:classifiers":[
        {
            "category":"Restaurant",
            "type":"Food & Drink"
        }
    ],
    "sg:phone":"+1 450 243 5532",
    "sg:postcode":"J0E 1V0",
    "sg:province":"QC",
    "wof:name":"Belle Escapade",
    "wof:placetype":"venue"
},
  "geometry": {"coordinates":[-72.536316,45.213043],"type":"Point"}
}