{
  "type": "Feature",
  "properties": {
    "addr:full":"Calgary AB T2Z 3Z4",
    "addr:postcode":"t2z 3z4",
    "iso:country":"CA",
    "sg:city":"Calgary",
    "sg:classifiers":[
        {
            "category":"Manufacturing",
            "subcategory":"Paper Products",
            "type":"Manufacturing & Wholesale Goods"
        }
    ],
    "sg:phone":"+1 403 236 0232",
    "sg:postcode":"T2Z 3Z4",
    "sg:province":"AB",
    "sg:tags":[
        "bag"
    ],
    "wof:name":"Alpine Plastics Ltd",
    "wof:placetype":"venue"
},
  "geometry": {"coordinates":[-113.974281,50.946907],"type":"Point"}
}