{
  "type": "Feature",
  "properties": {
    "addr:full":"Pointe-Claire QC H9S 4K9",
    "addr:postcode":"h9s 4k9",
    "iso:country":"CA",
    "sg:city":"Pointe-Claire",
    "sg:classifiers":[
        {
            "category":"Home & Garden",
            "subcategory":"Building Materials",
            "type":"Retail Goods"
        }
    ],
    "sg:phone":"+1 514 426 8588",
    "sg:postcode":"H9S 4K9",
    "sg:province":"QC",
    "sg:tags":[
        "windows",
        "door"
    ],
    "wof:name":"Portes & Fenetres DE L'Ouest",
    "wof:placetype":"venue"
},
  "geometry": {"coordinates":[-73.77800000000001,45.445068],"type":"Point"}
}