{
  "type": "Feature",
  "properties": {
    "addr:full":"37 Prince Arthur Ave Toronto ON M5R 1B2",
    "addr:housenumber":"37",
    "addr:postcode":"m5r 1b2",
    "addr:street":"Prince Arthur Ave",
    "iso:country":"CA",
    "sg:address":"37 Prince Arthur Ave",
    "sg:city":"Toronto",
    "sg:classifiers":[
        {
            "category":"Professional",
            "subcategory":"Lawyer & Legal Services",
            "type":"Services"
        }
    ],
    "sg:phone":"+1 416 601 1515",
    "sg:postcode":"M5R 1B2",
    "sg:province":"ON",
    "sg:tags":[
        "attorney"
    ],
    "wof:name":"David W Locke Law Offices",
    "wof:placetype":"venue"
},
  "geometry": {"coordinates":[-79.39682769780001,43.6693153381],"type":"Point"}
}