{
  "type": "Feature",
  "properties": {
    "addr:full":"Toronto ON M6R 3A6",
    "addr:postcode":"m6r 3a6",
    "iso:country":"CA",
    "sg:city":"Toronto",
    "sg:classifiers":[
        {
            "category":"Health Services",
            "subcategory":"Doctor",
            "type":"Services"
        }
    ],
    "sg:phone":"+1 416 535 6009",
    "sg:postcode":"M6R 3A6",
    "sg:province":"ON",
    "sg:tags":[
        "physician",
        "surgeon"
    ],
    "wof:name":"Klodas, S Maciej MD",
    "wof:placetype":"venue"
},
  "geometry": {"coordinates":[-79.45255299999999,43.656002],"type":"Point"}
}