{
  "type": "Feature",
  "properties": {
    "addr:full":"Vancouver BC V5Z 2N6",
    "addr:postcode":"v5z 2n6",
    "iso:country":"CA",
    "sg:city":"Vancouver",
    "sg:classifiers":[
        {
            "category":"Health Services",
            "subcategory":"Doctor",
            "type":"Services"
        }
    ],
    "sg:phone":"+1 604 261 6454",
    "sg:postcode":"V5Z 2N6",
    "sg:province":"BC",
    "sg:tags":[
        "physician",
        "surgeon"
    ],
    "wof:name":"Solyom, I Elizabeth MD",
    "wof:placetype":"venue"
},
  "geometry": {"coordinates":[-123.12437439,49.2340164185],"type":"Point"}
}