{
  "type": "Feature",
  "properties": {
    "addr:full":"Lethbridge AB T1J 2B6",
    "addr:postcode":"t1j 2b6",
    "iso:country":"CA",
    "sg:city":"Lethbridge",
    "sg:classifiers":[
        {
            "category":"Professional",
            "subcategory":"Lawyer & Legal Services",
            "type":"Services"
        }
    ],
    "sg:phone":"+1 403 328 9300",
    "sg:postcode":"T1J 2B6",
    "sg:province":"AB",
    "sg:tags":[
        "attorney"
    ],
    "wof:name":"Lamont, Barbara G",
    "wof:placetype":"venue"
},
  "geometry": {"coordinates":[-112.83989715600001,49.6938285828],"type":"Point"}
}