{
  "type": "Feature",
  "properties": {
    "addr:full":"76 Wentworth St S Hamilton ON L8N 2Y9",
    "addr:housenumber":"76",
    "addr:postcode":"l8n 2y9",
    "addr:street":"Wentworth St S",
    "iso:country":"CA",
    "sg:address":"76 Wentworth St S",
    "sg:city":"Hamilton",
    "sg:classifiers":[
        {
            "category":"Home & Garden",
            "subcategory":"Home Furnishings",
            "type":"Retail Goods"
        }
    ],
    "sg:phone":"+1 905 527 1688",
    "sg:postcode":"L8N 2Y9",
    "sg:province":"ON",
    "sg:tags":[
        "lighting",
        "fixture"
    ],
    "wof:name":"Yorkshire Lighting",
    "wof:placetype":"venue"
},
  "geometry": {"coordinates":[-79.85008999999999,43.249954],"type":"Point"}
}