{
  "type": "Feature",
  "properties": {
    "addr:full":"Montreal QC H3A 2A5",
    "addr:postcode":"h3a 2a5",
    "iso:country":"CA",
    "sg:city":"Montreal",
    "sg:classifiers":[
        {
            "category":"Banks & Credit Unions",
            "subcategory":"Investment Brokerage",
            "type":"Services"
        }
    ],
    "sg:phone":"+1 514 842 2685",
    "sg:postcode":"H3A 2A5",
    "sg:province":"QC",
    "wof:name":"Disnat",
    "wof:placetype":"venue"
},
  "geometry": {"coordinates":[-73.57186889650001,45.504070282],"type":"Point"}
}