{
  "type": "Feature",
  "properties": {
    "addr:full":"128 Morrell St Brantford ON N3T 4J8",
    "addr:housenumber":"128",
    "addr:postcode":"n3t 4j8",
    "addr:street":"Morrell St",
    "iso:country":"CA",
    "sg:address":"128 Morrell St",
    "sg:city":"Brantford",
    "sg:classifiers":[
        {
            "category":"Food & Beverages",
            "subcategory":"Groceries & Convenience Stores",
            "type":"Retail Goods"
        }
    ],
    "sg:phone":"+1 519 751 0405",
    "sg:postcode":"N3T 4J8",
    "sg:province":"ON",
    "wof:name":"Holmedale Mini Mart",
    "wof:placetype":"venue"
},
  "geometry": {"coordinates":[-80.287964,43.145359],"type":"Point"}
}