{
  "type": "Feature",
  "properties": {
    "addr:full":"712 East Lake Rise NE Airdrie AB T4A 2H9",
    "addr:housenumber":"712",
    "addr:postcode":"t4a 2h9",
    "addr:street":"East Lake Rise Ne",
    "iso:country":"CA",
    "sg:address":"712 East Lake Rise NE",
    "sg:city":"Airdrie",
    "sg:classifiers":[
        {
            "category":"Building & Trades",
            "subcategory":"Landscaping Services",
            "type":"Services"
        }
    ],
    "sg:phone":"+1 403 948 5116",
    "sg:postcode":"T4A 2H9",
    "sg:province":"AB",
    "sg:tags":[
        "landscape",
        "contractor"
    ],
    "wof:name":"Land Care Landscaping",
    "wof:placetype":"venue"
},
  "geometry": {"coordinates":[-113.99762,51.289989],"type":"Point"}
}