{
  "type": "Feature",
  "properties": {
    "addr:full":"2670 Plymouth Dr Oakville ON L6H 5R6",
    "addr:housenumber":"2670",
    "addr:postcode":"l6h 5r6",
    "addr:street":"Plymouth Dr",
    "iso:country":"CA",
    "sg:address":"2670 Plymouth Dr",
    "sg:city":"Oakville",
    "sg:classifiers":[
        {
            "category":"Shopping",
            "subcategory":"Stationery & Office Supplies",
            "type":"Retail Goods"
        }
    ],
    "sg:phone":"+1 905 829 5051",
    "sg:postcode":"L6H 5R6",
    "sg:province":"ON",
    "wof:name":"Sanford Canada",
    "wof:placetype":"venue"
},
  "geometry": {"coordinates":[-79.67999267579999,43.5060691833],"type":"Point"}
}