{
  "type": "Feature",
  "properties": {
    "addr:full":"Ottawa ON K1Z 6X3",
    "addr:postcode":"k1z 6x3",
    "iso:country":"CA",
    "sg:city":"Ottawa",
    "sg:classifiers":[
        {
            "category":"Building & Trades",
            "subcategory":"Plumbing",
            "type":"Services"
        }
    ],
    "sg:phone":"+1 613 794 6163",
    "sg:postcode":"K1Z 6X3",
    "sg:province":"ON",
    "sg:tags":[
        "conditioning",
        "air",
        "system",
        "contractor"
    ],
    "wof:name":"Blair's Mechanical Inc",
    "wof:placetype":"venue"
},
  "geometry": {"coordinates":[-75.7527923584,45.392742157],"type":"Point"}
}