{
  "type": "Feature",
  "properties": {
    "addr:full":"11444 119 St NW Edmonton AB T5G 2X6",
    "addr:housenumber":"11444",
    "addr:postcode":"t5g 2x6",
    "addr:street":"119 St Nw",
    "iso:country":"CA",
    "sg:address":"11444 119 St NW",
    "sg:city":"Edmonton",
    "sg:classifiers":[
        {
            "category":"Freight",
            "type":"Transportation"
        }
    ],
    "sg:phone":"+1 780 451 5252",
    "sg:postcode":"T5G 2X6",
    "sg:province":"AB",
    "sg:tags":[
        "commercial",
        "storage"
    ],
    "wof:name":"Sentinel Self-Storage",
    "wof:placetype":"venue"
},
  "geometry": {"coordinates":[-113.52724499999999,53.565155],"type":"Point"}
}