{
  "type": "Feature",
  "properties": {
    "addr:full":"130 Government Rd S Black Diamond AB T0L 0H0",
    "addr:housenumber":"130",
    "addr:postcode":"t0l 0h0",
    "addr:street":"Government Rd S",
    "iso:country":"CA",
    "sg:address":"130 Government Rd S",
    "sg:city":"Black Diamond",
    "sg:classifiers":[
        {
            "category":"Shopping",
            "subcategory":"Gifts & Souvenirs",
            "type":"Retail Goods"
        }
    ],
    "sg:phone":"+1 403 933 2347",
    "sg:postcode":"T0L 0H0",
    "sg:province":"AB",
    "sg:tags":[
        "shop"
    ],
    "wof:name":"Wonders",
    "wof:placetype":"venue"
},
  "geometry": {"coordinates":[-114.23240699999999,50.687984],"type":"Point"}
}