{
  "type": "Feature",
  "properties": {
    "iso:country":"CA",
    "sg:address":"22 Main St W",
    "sg:city":"Grimsby",
    "sg:classifiers":[
        {
            "category":"Banks & Credit Unions",
            "subcategory":"Bank",
            "type":"Services"
        }
    ],
    "sg:phone":"+1 905 309 9743",
    "sg:postcode":"L3M 1R4",
    "sg:province":"ON",
    "sg:tags":[
        "loan",
        "real estate"
    ],
    "wof:name":"Main Street Mortgage Svc Ltd",
    "wof:placetype":"venue"
},
  "geometry": {"coordinates":[-79.561287,43.193596],"type":"Point"}
}