{
  "type": "Feature",
  "properties": {
    "addr:full":"219 Colonnade Rd Nepean ON K2E 7K3",
    "addr:housenumber":"219",
    "addr:postcode":"k2e 7k3",
    "addr:street":"Colonnade Rd",
    "iso:country":"CA",
    "sg:address":"219 Colonnade Rd",
    "sg:city":"Nepean",
    "sg:classifiers":[
        {
            "category":"Recreation",
            "type":"Entertainment"
        }
    ],
    "sg:phone":"+1 613 225 6781",
    "sg:postcode":"K2E 7K3",
    "sg:province":"ON",
    "sg:tags":[
        "tours",
        "boat",
        "sightseeing"
    ],
    "wof:name":"Paul's Boat Lines Ltd",
    "wof:placetype":"venue"
},
  "geometry": {"coordinates":[-75.7126235962,45.3417701721],"type":"Point"}
}