{
  "type": "Feature",
  "properties": {
    "addr:full":"2500 Lawrence Ave E Scarborough ON M1P 2R7",
    "addr:housenumber":"2500",
    "addr:postcode":"m1p 2r7",
    "addr:street":"Lawrence Ave E",
    "iso:country":"CA",
    "sg:address":"2500 Lawrence Ave E",
    "sg:city":"Scarborough",
    "sg:classifiers":[
        {
            "category":"Professional",
            "subcategory":"Business Services",
            "type":"Services"
        }
    ],
    "sg:phone":"+1 416 288 1018",
    "sg:postcode":"M1P 2R7",
    "sg:province":"ON",
    "sg:tags":[
        "trade",
        "exposition",
        "fair",
        "show"
    ],
    "wof:name":"Elite Show Svc",
    "wof:placetype":"venue"
},
  "geometry": {"coordinates":[-79.26808200000001,43.751343],"type":"Point"}
}