{
  "type": "Feature",
  "properties": {
    "iso:country":"CA",
    "sg:address":"18 Car Saint-Louis",
    "sg:city":"Chateauguay",
    "sg:classifiers":[
        {
            "category":"Manufacturing",
            "subcategory":"Printing",
            "type":"Manufacturing & Wholesale Goods"
        }
    ],
    "sg:phone":"+1 450 691 7333",
    "sg:postcode":"J6K 2E8",
    "sg:province":"QC",
    "sg:tags":[
        "accounting",
        "printer",
        "system",
        "bookkeeping"
    ],
    "wof:name":"Uniscript",
    "wof:placetype":"venue"
},
  "geometry": {"coordinates":[-73.766838,45.354858],"type":"Point"}
}