{
  "type": "Feature",
  "properties": {
    "iso:country":"CA",
    "sg:address":"1200 Rue Bernier",
    "sg:city":"Drummondville",
    "sg:classifiers":[
        {
            "category":"Real Estate",
            "subcategory":"Real Estate Operator",
            "type":"Services"
        }
    ],
    "sg:phone":"+1 819 471 6516",
    "sg:postcode":"J2C 7A8",
    "sg:province":"QC",
    "sg:tags":[
        "apartment"
    ],
    "wof:name":"Appartments St-Hubert",
    "wof:placetype":"venue"
},
  "geometry": {"coordinates":[-72.52751159669999,45.8971786499],"type":"Point"}
}