{
  "type": "Feature",
  "properties": {
    "iso:country":"CA",
    "sg:address":"899 Kingsway",
    "sg:city":"Vancouver",
    "sg:classifiers":[
        {
            "category":"Home & Garden",
            "subcategory":"Building Materials",
            "type":"Retail Goods"
        }
    ],
    "sg:phone":"+1 604 879 0486",
    "sg:postcode":"V5V 3C2",
    "sg:province":"BC",
    "sg:tags":[
        "plate",
        "window",
        "upholsterer"
    ],
    "wof:name":"Broco Auto Glass & Upholstery",
    "wof:placetype":"venue"
},
  "geometry": {"coordinates":[-123.085548401,49.2548866272],"type":"Point"}
}