{
  "type": "Feature",
  "properties": {
    "addr:full":"Saint-Jean-DE-Matha QC J0K 2S0",
    "addr:postcode":"j0k 2s0",
    "iso:country":"CA",
    "sg:city":"Saint-Jean-DE-Matha",
    "sg:classifiers":[
        {
            "category":"Wholesale",
            "subcategory":"Meat",
            "type":"Manufacturing & Wholesale Goods"
        }
    ],
    "sg:phone":"+1 450 886 2913",
    "sg:postcode":"J0K 2S0",
    "sg:province":"QC",
    "sg:tags":[
        "butchering"
    ],
    "wof:name":"Viandes Gadoury Enr",
    "wof:placetype":"venue"
},
  "geometry": {"coordinates":[-73.5295333862,46.2307167053],"type":"Point"}
}