{
  "type": "Feature",
  "properties": {
    "addr:full":"354 Glenashton Dr Oakville ON L6H 4V9",
    "addr:housenumber":"354",
    "addr:postcode":"l6h 4v9",
    "addr:street":"Glenashton Dr",
    "iso:country":"CA",
    "sg:address":"354 Glenashton Dr",
    "sg:city":"Oakville",
    "sg:classifiers":[
        {
            "category":"Wholesale",
            "subcategory":"Medical Equipment & Supplies",
            "type":"Manufacturing & Wholesale Goods"
        }
    ],
    "sg:phone":"+1 905 849 5904",
    "sg:postcode":"L6H 4V9",
    "sg:province":"ON",
    "sg:tags":[
        "physician",
        "surgeon"
    ],
    "wof:name":"Fareesco International",
    "wof:placetype":"venue"
},
  "geometry": {"coordinates":[-79.7082824707,43.481464386],"type":"Point"}
}