{
  "type": "Feature",
  "properties": {
    "addr:full":"Scarborough ON M1H 3G3",
    "addr:postcode":"m1h 3g3",
    "iso:country":"CA",
    "sg:city":"Scarborough",
    "sg:classifiers":[
        {
            "category":"Health Services",
            "subcategory":"Doctor",
            "type":"Services"
        }
    ],
    "sg:phone":"+1 416 439 4080",
    "sg:postcode":"M1H 3G3",
    "sg:province":"ON",
    "sg:tags":[
        "dentist"
    ],
    "wof:name":"Tsai, Damon DDS",
    "wof:placetype":"venue"
},
  "geometry": {"coordinates":[-79.2361755371,43.7811508179],"type":"Point"}
}