{
  "type": "Feature",
  "properties": {
    "addr:full":"11903 Boul Sainte-Gertrude Montreal-Nord QC H1G 5R1",
    "addr:housenumber":"11903",
    "addr:postcode":"h1g 5r1",
    "addr:street":"Boul Sainte-Gertrude",
    "iso:country":"CA",
    "sg:address":"11903 Boul Sainte-Gertrude",
    "sg:city":"Montreal-Nord",
    "sg:classifiers":[
        {
            "category":"Professional",
            "subcategory":"Lawyer & Legal Services",
            "type":"Services"
        }
    ],
    "sg:phone":"+1 514 327 1201",
    "sg:postcode":"H1G 5R1",
    "sg:province":"QC",
    "sg:tags":[
        "attorney"
    ],
    "wof:name":"Cayer, Victor",
    "wof:placetype":"venue"
},
  "geometry": {"coordinates":[-73.635391,45.60564],"type":"Point"}
}