{
  "type": "Feature",
  "properties": {
    "addr:full":"160 Spring St Sault Ste Marie ON P6A 3A5",
    "addr:housenumber":"160",
    "addr:postcode":"p6a 3a5",
    "addr:street":"Spring St",
    "iso:country":"CA",
    "sg:address":"160 Spring St",
    "sg:city":"Sault Ste Marie",
    "sg:classifiers":[
        {
            "category":"Organizations",
            "subcategory":"Religious Organization",
            "type":"Services"
        }
    ],
    "sg:phone":"+1 705 253 3264",
    "sg:postcode":"P6A 3A5",
    "sg:province":"ON",
    "sg:tags":[
        "church"
    ],
    "wof:name":"Central United Church",
    "wof:placetype":"venue"
},
  "geometry": {"coordinates":[-84.329574585,46.5111122131],"type":"Point"}
}