{
  "type": "Feature",
  "properties": {
    "iso:country":"CA",
    "sg:city":"Arborg",
    "sg:classifiers":[
        {
            "category":"Manufacturing",
            "subcategory":"Furniture",
            "type":"Manufacturing & Wholesale Goods"
        }
    ],
    "sg:phone":"+1 204 364 2442",
    "sg:postcode":"R0C 0A0",
    "sg:province":"MB",
    "sg:tags":[
        "material",
        "fixture",
        "display"
    ],
    "wof:name":"Vidir Machine Inc",
    "wof:placetype":"venue"
},
  "geometry": {"coordinates":[-97.20436096189999,50.9053459167],"type":"Point"}
}