{
  "type": "Feature",
  "properties": {
    "addr:full":"Maria QC G0C 1Y0",
    "addr:postcode":"g0c 1y0",
    "addr:street":"Maria",
    "iso:country":"CA",
    "sg:city":"Maria",
    "sg:classifiers":[
        {
            "category":"Organizations",
            "subcategory":"Professional Association",
            "type":"Services"
        }
    ],
    "sg:phone":"+1 418 759 3016",
    "sg:postcode":"G0C 1Y0",
    "sg:province":"QC",
    "wof:name":"Mesure Alternative Jeunesse",
    "wof:placetype":"venue"
},
  "geometry": {"coordinates":[-65.9806594849,48.1769256592],"type":"Point"}
}