{
  "type": "Feature",
  "properties": {
    "addr:full":"710 Wayne Pl Prince Rupert BC V8J 3V6",
    "addr:housenumber":"710",
    "addr:postcode":"v8j 3v6",
    "addr:street":"Wayne Pl",
    "iso:country":"CA",
    "sg:address":"710 Wayne Pl",
    "sg:city":"Prince Rupert",
    "sg:classifiers":[
        {
            "category":"Restaurant",
            "type":"Food & Drink"
        }
    ],
    "sg:phone":"+1 250 624 2621",
    "sg:postcode":"V8J 3V6",
    "sg:province":"BC",
    "wof:name":"Gondola Dining Room",
    "wof:placetype":"venue"
},
  "geometry": {"coordinates":[-130.32913199999999,54.312725],"type":"Point"}
}