{
  "type": "Feature",
  "properties": {
    "iso:country":"CA",
    "sg:address":"4575 Tillicum St",
    "sg:city":"Burnaby",
    "sg:classifiers":[
        {
            "category":"Building & Trades",
            "subcategory":"Construction",
            "type":"Services"
        }
    ],
    "sg:phone":"+1 604 437 3377",
    "sg:postcode":"V5J 5K9",
    "sg:province":"BC",
    "sg:tags":[
        "skylight"
    ],
    "wof:name":"Columbia Manufacturing CO Ltd",
    "wof:placetype":"venue"
},
  "geometry": {"coordinates":[-122.99105835,49.1887130737],"type":"Point"}
}