{
  "type": "Feature",
  "properties": {
    "iso:country":"CA",
    "sg:address":"41 Bayview Dr",
    "sg:city":"Port Clements",
    "sg:classifiers":[
        {
            "category":"Building & Trades",
            "subcategory":"Construction",
            "type":"Services"
        }
    ],
    "sg:phone":"+1 250 557 2025",
    "sg:postcode":"V0T 1R0",
    "sg:province":"BC",
    "sg:tags":[
        "general",
        "contractor"
    ],
    "wof:name":"Kumdis Enterprises Ltd",
    "wof:placetype":"venue"
},
  "geometry": {"coordinates":[-132.18499755900001,53.6884040833],"type":"Point"}
}