{
  "type": "Feature",
  "properties": {
    "addr:full":"Vancouver BC V6B 4M9",
    "addr:postcode":"v6b 4m9",
    "iso:country":"CA",
    "sg:city":"Vancouver",
    "sg:classifiers":[
        {
            "category":"Banks & Credit Unions",
            "subcategory":"Bank",
            "type":"Services"
        }
    ],
    "sg:phone":"+1 604 687 6444",
    "sg:postcode":"V6B 4M9",
    "sg:province":"BC",
    "sg:tags":[
        "loan",
        "real estate"
    ],
    "wof:name":"Argent Realty Inc",
    "wof:placetype":"venue"
},
  "geometry": {"coordinates":[-123.115631103,49.281124115],"type":"Point"}
}