{
  "type": "Feature",
  "properties": {
    "addr:full":"45 Bonaventure Ave St. John's NL A1C 3Z3",
    "addr:housenumber":"45",
    "addr:postcode":"a1c 3z3",
    "addr:street":"Bonaventure Ave",
    "iso:country":"CA",
    "sg:address":"45 Bonaventure Ave",
    "sg:city":"St. John's",
    "sg:classifiers":[
        {
            "category":"Recreation",
            "type":"Entertainment"
        }
    ],
    "sg:phone":"+1 709 753 5782",
    "sg:postcode":"A1C 3Z3",
    "sg:province":"NL",
    "sg:tags":[
        "skating",
        "rink"
    ],
    "wof:name":"O'Hehir Arena Inc",
    "wof:placetype":"venue"
},
  "geometry": {"coordinates":[-52.7165298462,47.5697097778],"type":"Point"}
}