{
  "type": "Feature",
  "properties": {
    "addr:full":"Calgary AB T2R 0C9",
    "addr:postcode":"t2r 0c9",
    "iso:country":"CA",
    "sg:city":"Calgary",
    "sg:classifiers":[
        {
            "category":"Government",
            "subcategory":"Office",
            "type":"Public Place"
        }
    ],
    "sg:phone":"+1 403 297 8418",
    "sg:postcode":"T2R 0C9",
    "sg:province":"AB",
    "wof:name":"Alberta Community Dev Svc",
    "wof:placetype":"venue"
},
  "geometry": {"coordinates":[-114.07225800000001,51.042503],"type":"Point"}
}