{
  "type": "Feature",
  "properties": {
    "addr:full":"640 Markham Rd Scarborough ON M1H 2A7",
    "addr:housenumber":"640",
    "addr:postcode":"m1h 2a7",
    "addr:street":"Markham Rd",
    "iso:country":"CA",
    "sg:address":"640 Markham Rd",
    "sg:city":"Scarborough",
    "sg:phone":"+1 416 438 1523",
    "sg:postcode":"M1H 2A7",
    "sg:province":"ON",
    "wof:name":"Shell Canada Products Ltd",
    "wof:placetype":"venue"
},
  "geometry": {"coordinates":[-79.225883,43.760777],"type":"Point"}
}