{
  "type": "Feature",
  "properties": {
    "addr:full":"Penticton BC V2A 6W6",
    "addr:postcode":"v2a 6w6",
    "iso:country":"CA",
    "sg:city":"Penticton",
    "sg:classifiers":[
        {
            "category":"Shopping",
            "subcategory":"Books",
            "type":"Retail Goods"
        }
    ],
    "sg:phone":"+1 250 493 2517",
    "sg:postcode":"V2A 6W6",
    "sg:province":"BC",
    "sg:tags":[
        "dealer"
    ],
    "wof:name":"Coles",
    "wof:placetype":"venue"
},
  "geometry": {"coordinates":[-119.583015442,49.4747161865],"type":"Point"}
}