{
  "type": "Feature",
  "properties": {
    "addr:full":"3512 Happy Valley Rd Victoria BC V9C 2Y3",
    "addr:housenumber":"3512",
    "addr:postcode":"bc v9c 2y3",
    "addr:street":"Happy Valley Rd",
    "iso:country":"CA",
    "sg:address":"3512 Happy Valley Rd",
    "sg:city":"Victoria",
    "sg:classifiers":[
        {
            "category":"Shopping",
            "type":"Retail Goods"
        }
    ],
    "sg:phone":"+1 250 478 8279",
    "sg:postcode":"V9C 2Y3",
    "sg:province":"BC",
    "sg:tags":[
        "trophy",
        "medal",
        "award"
    ],
    "wof:name":"Girard Games & Awards",
    "wof:placetype":"venue"
},
  "geometry": {"coordinates":[-123.364517212,48.428314209],"type":"Point"}
}