{
  "type": "Feature",
  "properties": {
    "iso:country":"CA",
    "sg:city":"Concord",
    "sg:classifiers":[
        {
            "category":"Wholesale",
            "subcategory":"Stationery",
            "type":"Manufacturing & Wholesale Goods"
        }
    ],
    "sg:phone":"+1 905 669 6770",
    "sg:postcode":"L4K 4N6",
    "sg:province":"ON",
    "sg:tags":[
        "packaging",
        "material"
    ],
    "wof:name":"Heat Sealing Equipment CO",
    "wof:placetype":"venue"
},
  "geometry": {"coordinates":[-79.5250701904,43.8094940186],"type":"Point"}
}