{
  "type": "Feature",
  "properties": {
    "addr:full":"41 Hatfield Point Loop Rd Hatfield Point NB E5T 2S3",
    "addr:housenumber":"41",
    "addr:postcode":"e5t 2s3",
    "addr:street":"Hatfield Point Loop Rd",
    "iso:country":"CA",
    "sg:address":"41 Hatfield Point Loop Rd",
    "sg:city":"Hatfield Point",
    "sg:classifiers":[
        {
            "category":"Organizations",
            "subcategory":"Religious Organization",
            "type":"Services"
        }
    ],
    "sg:phone":"+1 506 485 2088",
    "sg:postcode":"E5T 2S3",
    "sg:province":"NB",
    "sg:tags":[
        "church"
    ],
    "wof:name":"Hatfield Point Baptist Church",
    "wof:placetype":"venue"
},
  "geometry": {"coordinates":[-65.860153,45.650234],"type":"Point"}
}