{
  "type": "Feature",
  "properties": {
    "addr:full":"L'Epiphanie QC J5X 3L4",
    "addr:postcode":"j5x 3l4",
    "iso:country":"CA",
    "sg:city":"L'Epiphanie",
    "sg:classifiers":[
        {
            "category":"Retail",
            "subcategory":"Auto Repair",
            "type":"Services"
        }
    ],
    "sg:phone":"+1 450 588 5860",
    "sg:postcode":"J5X 3L4",
    "sg:province":"QC",
    "sg:tags":[
        "automobile",
        "electric"
    ],
    "wof:name":"Garage Daniel Enr",
    "wof:placetype":"venue"
},
  "geometry": {"coordinates":[-73.48378,45.849998],"type":"Point"}
}