{
  "type": "Feature",
  "properties": {
    "iso:country":"CA",
    "sg:address":"775 Dundas St W",
    "sg:city":"Toronto",
    "sg:classifiers":[
        {
            "category":"Recreation",
            "type":"Entertainment"
        }
    ],
    "sg:phone":"+1 416 603 3030",
    "sg:postcode":"M6J 1V2",
    "sg:province":"ON",
    "sg:tags":[
        "parlor",
        "billiard"
    ],
    "wof:name":"Portuguese Billiards & Snack",
    "wof:placetype":"venue"
},
  "geometry": {"coordinates":[-79.4073562622,43.6519241333],"type":"Point"}
}