{
  "type": "Feature",
  "properties": {
    "addr:full":"Angus ON L0M 1B0",
    "addr:postcode":"l0m 1b0",
    "iso:country":"CA",
    "sg:city":"Angus",
    "sg:classifiers":[
        {
            "category":"Organizations",
            "subcategory":"Religious Organization",
            "type":"Services"
        }
    ],
    "sg:phone":"+1 705 424 1551",
    "sg:postcode":"L0M 1B0",
    "sg:province":"ON",
    "sg:tags":[
        "church"
    ],
    "wof:name":"Our Lady of Grace",
    "wof:placetype":"venue"
},
  "geometry": {"coordinates":[-79.87195587159999,44.3242683411],"type":"Point"}
}