{
  "type": "Feature",
  "properties": {
    "addr:full":"Saint-Henri-DE-Levis QC G0R 3E0",
    "addr:postcode":"g0r 3e0",
    "iso:country":"CA",
    "sg:city":"Saint-Henri-DE-Levis",
    "sg:classifiers":[
        {
            "category":"Personal",
            "subcategory":"Beauty Salon",
            "type":"Services"
        }
    ],
    "sg:phone":"+1 418 882 1978",
    "sg:postcode":"G0R 3E0",
    "sg:province":"QC",
    "wof:name":"Esthetique Reflet Beaute",
    "wof:placetype":"venue"
},
  "geometry": {"coordinates":[-71.068138,46.693275],"type":"Point"}
}