{
  "type": "Feature",
  "properties": {
    "addr:full":"Scarborough ON M1V 5J6",
    "addr:postcode":"m1v 5j6",
    "iso:country":"CA",
    "sg:city":"Scarborough",
    "sg:classifiers":[
        {
            "category":"Shopping",
            "subcategory":"Clothing, Apparel, & Fashions",
            "type":"Retail Goods"
        }
    ],
    "sg:phone":"+1 416 299 7383",
    "sg:postcode":"M1V 5J6",
    "sg:province":"ON",
    "wof:name":"Sartaj Fashions",
    "wof:placetype":"venue"
},
  "geometry": {"coordinates":[-79.261932,43.820305],"type":"Point"}
}