{
  "type": "Feature",
  "properties": {
    "addr:full":"8 Ch Saint-Francois-Xavier Candiac QC J5R 1A2",
    "addr:housenumber":"8",
    "addr:postcode":"j5r 1a2",
    "addr:street":"Saint-Francois-Xavier",
    "iso:country":"CA",
    "sg:address":"8 Ch Saint-Francois-Xavier",
    "sg:city":"Candiac",
    "sg:classifiers":[
        {
            "category":"Social Services",
            "type":"Services"
        }
    ],
    "sg:phone":"+1 450 659 9651",
    "sg:postcode":"J5R 1A2",
    "sg:province":"QC",
    "sg:tags":[
        "organization",
        "welfare"
    ],
    "wof:name":"Centre DE Benevolat DE LA Rive",
    "wof:placetype":"venue"
},
  "geometry": {"coordinates":[-73.52873200000001,45.39743],"type":"Point"}
}