{
  "type": "Feature",
  "properties": {
    "addr:full":"106 Crowfoot Terr NW Calgary AB T3G 4J8",
    "addr:housenumber":"106",
    "addr:postcode":"t3g 4j8",
    "addr:street":"Crowfoot Terr Nw",
    "iso:country":"CA",
    "sg:address":"106 Crowfoot Terr NW",
    "sg:city":"Calgary",
    "sg:classifiers":[
        {
            "category":"Shopping",
            "subcategory":"Gifts & Souvenirs",
            "type":"Retail Goods"
        }
    ],
    "sg:phone":"+1 403 239 3555",
    "sg:postcode":"T3G 4J8",
    "sg:province":"AB",
    "sg:tags":[
        "shop"
    ],
    "wof:name":"Rafters",
    "wof:placetype":"venue"
},
  "geometry": {"coordinates":[-114.20224,51.126919],"type":"Point"}
}