{
  "type": "Feature",
  "properties": {
    "addr:full":"12 Hawthorne Cres Aylmer ON N5H 3C3",
    "addr:housenumber":"12",
    "addr:postcode":"n5h 3c3",
    "addr:street":"Hawthorne Cres",
    "iso:country":"CA",
    "sg:address":"12 Hawthorne Cres",
    "sg:city":"Aylmer",
    "sg:classifiers":[
        {
            "category":"Building & Trades",
            "subcategory":"Construction",
            "type":"Services"
        }
    ],
    "sg:phone":"+1 519 773 8592",
    "sg:postcode":"N5H 3C3",
    "sg:province":"ON",
    "sg:tags":[
        "home",
        "improvement"
    ],
    "wof:name":"Southwest Ultimate Imprvmnts",
    "wof:placetype":"venue"
},
  "geometry": {"coordinates":[-80.990967,42.77879],"type":"Point"}
}