{
  "type": "Feature",
  "properties": {
    "addr:full":"7819 Rue Des Muguets Sorel-Tracy QC J3R 5J5",
    "addr:housenumber":"7819",
    "addr:postcode":"j3r 5j5",
    "addr:street":"Rue Des Muguets",
    "iso:country":"CA",
    "sg:address":"7819 Rue Des Muguets",
    "sg:city":"Sorel-Tracy",
    "sg:classifiers":[
        {
            "category":"Building & Trades",
            "subcategory":"Construction",
            "type":"Services"
        }
    ],
    "sg:phone":"+1 450 742 0712",
    "sg:postcode":"J3R 5J5",
    "sg:province":"QC",
    "sg:tags":[
        "general",
        "contractor"
    ],
    "wof:name":"Construction Novy",
    "wof:placetype":"venue"
},
  "geometry": {"coordinates":[-73.1410293579,46.0150108337],"type":"Point"}
}