{
  "type": "Feature",
  "properties": {
    "addr:full":"Port Hawkesbury NS B9A 2B4",
    "addr:postcode":"b9a 2b4",
    "iso:country":"CA",
    "sg:city":"Port Hawkesbury",
    "sg:classifiers":[
        {
            "category":"Professional",
            "subcategory":"Engineering",
            "type":"Services"
        }
    ],
    "sg:phone":"+1 902 625 3631",
    "sg:postcode":"B9A 2B4",
    "sg:province":"NS",
    "sg:tags":[
        "engineer"
    ],
    "wof:name":"Strait Engineering Ltd",
    "wof:placetype":"venue"
},
  "geometry": {"coordinates":[-61.3580665588,45.6183815002],"type":"Point"}
}