{
  "type": "Feature",
  "properties": {
    "addr:full":"Burnaby BC V5C 2K4",
    "addr:postcode":"v5c 2k4",
    "iso:country":"CA",
    "sg:city":"Burnaby",
    "sg:classifiers":[
        {
            "category":"Professional",
            "subcategory":"Accounting & Tax Preparation",
            "type":"Services"
        }
    ],
    "sg:phone":"+1 604 294 1423",
    "sg:postcode":"V5C 2K4",
    "sg:province":"BC",
    "sg:tags":[
        "accountant"
    ],
    "wof:name":"George Clarke Ltd",
    "wof:placetype":"venue"
},
  "geometry": {"coordinates":[-123.00206,49.280869],"type":"Point"}
}