{
  "type": "Feature",
  "properties": {
    "addr:full":"453 Cochrane St # A Sudbury ON P3B 2C8",
    "addr:housenumber":"453",
    "addr:postcode":"p3b 2c8",
    "addr:street":"Cochrane St # A",
    "iso:country":"CA",
    "sg:address":"453 Cochrane St # A",
    "sg:city":"Sudbury",
    "sg:classifiers":[
        {
            "category":"Home & Garden",
            "subcategory":"Building Materials",
            "type":"Retail Goods"
        }
    ],
    "sg:phone":"+1 705 671 2839",
    "sg:postcode":"P3B 2C8",
    "sg:province":"ON",
    "sg:tags":[
        "glass",
        "window",
        "plate"
    ],
    "wof:name":"Tint Vision Auto Glass",
    "wof:placetype":"venue"
},
  "geometry": {"coordinates":[-80.982193,46.494274],"type":"Point"}
}