{
  "type": "Feature",
  "properties": {
    "addr:full":"1837 Rue DE L'Isere Val-Belair QC G3K 1M1",
    "addr:housenumber":"1837",
    "addr:postcode":"g3k 1m1",
    "addr:street":"Rue De L'Isere Val-Belair",
    "iso:country":"CA",
    "sg:address":"1837 Rue DE L'Isere",
    "sg:city":"Val-Belair",
    "sg:classifiers":[
        {
            "category":"Wholesale",
            "subcategory":"Auto Parts",
            "type":"Manufacturing & Wholesale Goods"
        }
    ],
    "sg:phone":"+1 418 845 1111",
    "sg:postcode":"G3K 1M1",
    "sg:province":"QC",
    "sg:tags":[
        "automobile"
    ],
    "wof:name":"Latulippe, Rosaire",
    "wof:placetype":"venue"
},
  "geometry": {"coordinates":[-71.41439800000001,46.860577],"type":"Point"}
}