{
  "type": "Feature",
  "properties": {
    "addr:full":"72 Lemon St Guelph ON N1E 2H5",
    "addr:housenumber":"72",
    "addr:postcode":"n1e 2h5",
    "addr:street":"Lemon St",
    "iso:country":"CA",
    "sg:address":"72 Lemon St",
    "sg:city":"Guelph",
    "sg:classifiers":[
        {
            "category":"Education",
            "subcategory":"School",
            "type":"Public Place"
        }
    ],
    "sg:phone":"+1 519 822 1911",
    "sg:postcode":"N1E 2H5",
    "sg:province":"ON",
    "wof:name":"King George Public School",
    "wof:placetype":"venue"
},
  "geometry": {"coordinates":[-80.24706999999999,43.55426],"type":"Point"}
}