{
  "type": "Feature",
  "properties": {
    "addr:full":"864 Hurontario St Collingwood ON L9Y 3Z4",
    "addr:housenumber":"864",
    "addr:postcode":"l9y 3z4",
    "addr:street":"Hurontario St",
    "iso:country":"CA",
    "sg:address":"864 Hurontario St",
    "sg:city":"Collingwood",
    "sg:classifiers":[
        {
            "category":"Manufacturing",
            "subcategory":"Toys & Sporting Goods",
            "type":"Manufacturing & Wholesale Goods"
        }
    ],
    "sg:phone":"+1 705 445 7133",
    "sg:postcode":"L9Y 3Z4",
    "sg:province":"ON",
    "sg:tags":[
        "athletic"
    ],
    "wof:name":"John Brown Custom Sprtng Equip",
    "wof:placetype":"venue"
},
  "geometry": {"coordinates":[-80.21305084230001,44.4805908203],"type":"Point"}
}