{
  "type": "Feature",
  "properties": {
    "addr:full":"10201 101 St LA Crete AB T0H 2H0",
    "addr:housenumber":"10201",
    "addr:postcode":"t0h 2h0",
    "addr:street":"101 St",
    "iso:country":"CA",
    "sg:address":"10201 101 St",
    "sg:city":"LA Crete",
    "sg:classifiers":[
        {
            "category":"Building & Trades",
            "subcategory":"Electrical",
            "type":"Services"
        }
    ],
    "sg:phone":"+1 780 928 2644",
    "sg:postcode":"T0H 2H0",
    "sg:province":"AB",
    "sg:tags":[
        "electric",
        "contractor"
    ],
    "wof:name":"Redline Electric Ltd",
    "wof:placetype":"venue"
},
  "geometry": {"coordinates":[-116.409637,58.211105],"type":"Point"}
}