{
  "type": "Feature",
  "properties": {
    "addr:full":"30 Mapleport Cres Sauble Beach ON N0H 2G0",
    "addr:housenumber":"30",
    "addr:postcode":"n0h 2g0",
    "addr:street":"Mapleport Cres",
    "iso:country":"CA",
    "sg:address":"30 Mapleport Cres",
    "sg:city":"Sauble Beach",
    "sg:classifiers":[
        {
            "category":"Building & Trades",
            "subcategory":"Construction",
            "type":"Services"
        }
    ],
    "sg:phone":"+1 519 422 1747",
    "sg:postcode":"N0H 2G0",
    "sg:province":"ON",
    "sg:tags":[
        "dry wall",
        "contractor"
    ],
    "wof:name":"Coblentz & Brown Drywall",
    "wof:placetype":"venue"
},
  "geometry": {"coordinates":[-81.26913500000001,44.604927],"type":"Point"}
}