{
  "type": "Feature",
  "properties": {
    "iso:country":"CA",
    "sg:city":"Lachine",
    "sg:classifiers":[
        {
            "category":"Shopping",
            "subcategory":"Bicycles & Sporting Goods",
            "type":"Retail Goods"
        }
    ],
    "sg:phone":"+1 514 637 0016",
    "sg:postcode":"H8S 3S2",
    "sg:province":"QC",
    "sg:tags":[
        "development",
        "electronic",
        "research"
    ],
    "wof:name":"Biosig Instruments Inc",
    "wof:placetype":"venue"
},
  "geometry": {"coordinates":[-73.68109893800001,45.4362487793],"type":"Point"}
}