{
  "type": "Feature",
  "properties": {
    "addr:full":"Montreal QC H3A 1T5",
    "addr:postcode":"h3a 1t5",
    "iso:country":"CA",
    "sg:city":"Montreal",
    "sg:classifiers":[
        {
            "category":"Shopping",
            "subcategory":"Pharmacy",
            "type":"Retail Goods"
        }
    ],
    "sg:phone":"+1 514 843 7117",
    "sg:postcode":"H3A 1T5",
    "sg:province":"QC",
    "wof:name":"Uniprix",
    "wof:placetype":"venue"
},
  "geometry": {"coordinates":[-73.5735702515,45.500453949],"type":"Point"}
}