{
  "type": "Feature",
  "properties": {
    "addr:full":"Abbotsford BC V2T 2Y6",
    "addr:postcode":"v2t 2y6",
    "iso:country":"CA",
    "sg:city":"Abbotsford",
    "sg:classifiers":[
        {
            "category":"Manufacturing",
            "subcategory":"Food",
            "type":"Manufacturing & Wholesale Goods"
        }
    ],
    "sg:phone":"+1 604 854 5673",
    "sg:postcode":"V2T 2Y6",
    "sg:province":"BC",
    "sg:tags":[
        "baker",
        "product",
        "manufacturer"
    ],
    "wof:name":"Fraser Ridge Bakery",
    "wof:placetype":"venue"
},
  "geometry": {"coordinates":[-122.33777600000001,49.05196],"type":"Point"}
}