{
  "type": "Feature",
  "properties": {
    "addr:full":"525 Portage Ave Fort Frances ON P9A 2A2",
    "addr:housenumber":"525",
    "addr:postcode":"p9a 2a2",
    "addr:street":"Portage Ave",
    "iso:country":"CA",
    "sg:address":"525 Portage Ave",
    "sg:city":"Fort Frances",
    "sg:classifiers":[
        {
            "category":"Travel",
            "subcategory":"Hotels & Motels",
            "type":"Entertainment"
        }
    ],
    "sg:phone":"+1 807 274 9805",
    "sg:postcode":"P9A 2A2",
    "sg:province":"ON",
    "wof:name":"Reid's Voyageur Inn Motel",
    "wof:placetype":"venue"
},
  "geometry": {"coordinates":[-93.39576700000001,48.610897],"type":"Point"}
}