{
  "type": "Feature",
  "properties": {
    "addr:full":"1380 Birch St Pemberton BC V0N 2L0",
    "addr:housenumber":"1380",
    "addr:postcode":"v0n 2l0",
    "addr:street":"Birch St",
    "iso:country":"CA",
    "sg:address":"1380 Birch St",
    "sg:city":"Pemberton",
    "sg:classifiers":[
        {
            "category":"Shopping",
            "subcategory":"Bicycles & Sporting Goods",
            "type":"Retail Goods"
        }
    ],
    "sg:phone":"+1 604 894 6630",
    "sg:postcode":"V0N 2L0",
    "sg:province":"BC",
    "wof:name":"Spud Valley Sporting Goods Ltd",
    "wof:placetype":"venue"
},
  "geometry": {"coordinates":[-122.80701446499999,50.3223152161],"type":"Point"}
}