{
  "type": "Feature",
  "properties": {
    "addr:full":"2406 Ch Des Quatre-Bourgeois Sainte-Foy QC G1V 1W5",
    "addr:postcode":"2406;g1v 1w5",
    "addr:street":"Ch Des Quatre-Bourgeois",
    "iso:country":"CA",
    "sg:address":"2406 Ch Des Quatre-Bourgeois",
    "sg:city":"Sainte-Foy",
    "sg:classifiers":[
        {
            "category":"Health Services",
            "subcategory":"Health Practitioner",
            "type":"Services"
        }
    ],
    "sg:phone":"+1 418 659 7000",
    "sg:postcode":"G1V 1W5",
    "sg:province":"QC",
    "sg:tags":[
        "accountant",
        "psychologist"
    ],
    "wof:name":"Reseau Psychotech Inc",
    "wof:placetype":"venue"
},
  "geometry": {"coordinates":[-71.2822723389,46.7853507996],"type":"Point"}
}