{
  "type": "Feature",
  "properties": {
    "addr:full":"Hse 515001 Norway House MB R0B 1B0",
    "addr:postcode":"515001;r0b 1b0",
    "addr:street":"Hse",
    "iso:country":"CA",
    "sg:address":"Hse 515001",
    "sg:city":"Norway House",
    "sg:classifiers":[
        {
            "category":"Shopping",
            "subcategory":"Bicycles & Sporting Goods",
            "type":"Retail Goods"
        }
    ],
    "sg:phone":"+1 204 359 6463",
    "sg:postcode":"R0B 1B0",
    "sg:province":"MB",
    "sg:tags":[
        "equipment",
        "trapping",
        "supply"
    ],
    "wof:name":"Norway House Trappers Assn",
    "wof:placetype":"venue"
},
  "geometry": {"coordinates":[-97.76863098139999,53.9951553345],"type":"Point"}
}