{
  "type": "Feature",
  "properties": {
    "addr:full":"685 Walkley Rd Ottawa ON K1V 6R8",
    "addr:housenumber":"685",
    "addr:postcode":"k1v 6r8",
    "addr:street":"Walkley Rd",
    "iso:country":"CA",
    "sg:address":"685 Walkley Rd",
    "sg:city":"Ottawa",
    "sg:classifiers":[
        {
            "category":"Organizations",
            "subcategory":"Religious Organization",
            "type":"Services"
        }
    ],
    "sg:phone":"+1 613 731 7834",
    "sg:postcode":"K1V 6R8",
    "sg:province":"ON",
    "sg:tags":[
        "church"
    ],
    "wof:name":"Holy Cross Church",
    "wof:placetype":"venue"
},
  "geometry": {"coordinates":[-75.684372,45.361912],"type":"Point"}
}