{
  "type": "Feature",
  "properties": {
    "addr:full":"131 Greenbank Rd Nepean ON K2H 8R1",
    "addr:housenumber":"131",
    "addr:postcode":"k2h 8r1",
    "addr:street":"Greenbank Rd",
    "iso:country":"CA",
    "sg:address":"131 Greenbank Rd",
    "sg:city":"Nepean",
    "sg:classifiers":[
        {
            "category":"Education",
            "subcategory":"School",
            "type":"Public Place"
        }
    ],
    "sg:phone":"+1 613 829 5320",
    "sg:postcode":"K2H 8R1",
    "sg:province":"ON",
    "wof:name":"Sir Robert Borden High School",
    "wof:placetype":"venue"
},
  "geometry": {"coordinates":[-75.78263099999999,45.332123],"type":"Point"}
}