{
  "type": "Feature",
  "properties": {
    "iso:country":"CA",
    "sg:address":"809 Bank St",
    "sg:city":"Ottawa",
    "sg:classifiers":[
        {
            "category":"Shopping",
            "subcategory":"Hobbies, Toys, & Games",
            "type":"Retail Goods"
        }
    ],
    "sg:phone":"+1 613 234 3836",
    "sg:postcode":"K1S 3V7",
    "sg:province":"ON",
    "wof:name":"Mrs Tiggy Winkle's",
    "wof:placetype":"venue"
},
  "geometry": {"coordinates":[-75.6879501343,45.4026870728],"type":"Point"}
}