{
  "type": "Feature",
  "properties": {
    "addr:full":"261 Whitney Ave Hamilton ON L8S 2G9",
    "addr:housenumber":"261",
    "addr:postcode":"l8s 2g9",
    "addr:street":"Whitney Ave",
    "iso:country":"CA",
    "sg:address":"261 Whitney Ave",
    "sg:city":"Hamilton",
    "sg:classifiers":[
        {
            "category":"Organizations",
            "subcategory":"Religious Organization",
            "type":"Services"
        }
    ],
    "sg:phone":"+1 905 529 5756",
    "sg:postcode":"L8S 2G9",
    "sg:province":"ON",
    "sg:tags":[
        "church"
    ],
    "wof:name":"Westside Baptist Church",
    "wof:placetype":"venue"
},
  "geometry": {"coordinates":[-79.930069,43.252518],"type":"Point"}
}