{
  "type": "Feature",
  "properties": {
    "addr:full":"692 Queensway W Simcoe ON N3Y 4J9",
    "addr:housenumber":"692",
    "addr:postcode":"n3y 4j9",
    "addr:street":"Queensway W",
    "iso:country":"CA",
    "sg:address":"692 Queensway W",
    "sg:city":"Simcoe",
    "sg:classifiers":[
        {
            "category":"Organizations",
            "subcategory":"Religious Organization",
            "type":"Services"
        }
    ],
    "sg:phone":"+1 519 428 3100",
    "sg:postcode":"N3Y 4J9",
    "sg:province":"ON",
    "sg:tags":[
        "church"
    ],
    "wof:name":"Jehovah's Witnesses",
    "wof:placetype":"venue"
},
  "geometry": {"coordinates":[-80.347054,42.838219],"type":"Point"}
}