{
  "type": "Feature",
  "properties": {
    "addr:full":"45 Slack Rd Nepean ON K2G 0B7",
    "addr:housenumber":"45",
    "addr:postcode":"k2g 0b7",
    "addr:street":"Slack Rd",
    "iso:country":"CA",
    "sg:address":"45 Slack Rd",
    "sg:city":"Nepean",
    "sg:classifiers":[
        {
            "category":"Wholesale",
            "subcategory":"Machinery & Supplies",
            "type":"Manufacturing & Wholesale Goods"
        }
    ],
    "sg:phone":"+1 613 225 0555",
    "sg:postcode":"K2G 0B7",
    "sg:province":"ON",
    "sg:tags":[
        "farm",
        "equipment",
        "rental"
    ],
    "wof:name":"B & T Mac Farlane Ottawa Ltd",
    "wof:placetype":"venue"
},
  "geometry": {"coordinates":[-75.72374000000001,45.324299],"type":"Point"}
}