{
  "type": "Feature",
  "properties": {
    "addr:full":"399 10th St Hanover ON N4N 1P7",
    "addr:housenumber":"399",
    "addr:postcode":"n4n 1p7",
    "addr:street":"10Th St",
    "iso:country":"CA",
    "sg:address":"399 10th St",
    "sg:city":"Hanover",
    "sg:classifiers":[
        {
            "category":"Personal",
            "subcategory":"Beauty Salon",
            "type":"Services"
        }
    ],
    "sg:phone":"+1 519 364 3854",
    "sg:postcode":"N4N 1P7",
    "sg:province":"ON",
    "wof:name":"My Scissors & I",
    "wof:placetype":"venue"
},
  "geometry": {"coordinates":[-81.024353,44.152454],"type":"Point"}
}