{
  "type": "Feature",
  "properties": {
    "addr:full":"9831 Fourth St Sidney BC V8L 2Z2",
    "addr:housenumber":"9831",
    "addr:postcode":"v8l 2z2",
    "addr:street":"Fourth St",
    "iso:country":"CA",
    "sg:address":"9831 Fourth St",
    "sg:city":"Sidney",
    "sg:classifiers":[
        {
            "category":"Organizations",
            "subcategory":"Community Association",
            "type":"Services"
        }
    ],
    "sg:phone":"+1 250 656 3777",
    "sg:postcode":"V8L 2Z2",
    "sg:province":"BC",
    "sg:tags":[
        "club",
        "military"
    ],
    "wof:name":"Army Navy & Air Force Veterans",
    "wof:placetype":"venue"
},
  "geometry": {"coordinates":[-123.398819,48.649693],"type":"Point"}
}