{
  "type": "Feature",
  "properties": {
    "addr:full":"156 Front St W #305 Toronto ON M5J 2L6",
    "addr:housenumber":"156",
    "addr:postcode":"m5j 2l6",
    "addr:street":"Front St W # 305",
    "iso:country":"CA",
    "sg:address":"156 Front St W #305",
    "sg:city":"Toronto",
    "sg:classifiers":[
        {
            "category":"Professional",
            "subcategory":"Computer Services",
            "type":"Services"
        }
    ],
    "sg:phone":"+1 416 593 8886",
    "sg:postcode":"M5J 2L6",
    "sg:province":"ON",
    "sg:tags":[
        "consultant"
    ],
    "wof:name":"Phoenix Information Systems",
    "wof:placetype":"venue"
},
  "geometry": {"coordinates":[-79.384331,43.64502],"type":"Point"}
}