{
  "type": "Feature",
  "properties": {
    "addr:full":"14 Simpson Cres Saskatoon SK S7H 3C6",
    "addr:housenumber":"14",
    "addr:postcode":"s7h 3c6",
    "addr:street":"Simpson Cres",
    "iso:country":"CA",
    "sg:address":"14 Simpson Cres",
    "sg:city":"Saskatoon",
    "sg:classifiers":[
        {
            "category":"Banks & Credit Unions",
            "subcategory":"Financial Services",
            "type":"Services"
        }
    ],
    "sg:phone":"+1 306 244 8636",
    "sg:postcode":"S7H 3C6",
    "sg:province":"SK",
    "sg:tags":[
        "company",
        "holding"
    ],
    "wof:name":"Sadownick Enterprises Ltd",
    "wof:placetype":"venue"
},
  "geometry": {"coordinates":[-106.61041299999999,52.120045],"type":"Point"}
}