{
  "type": "Feature",
  "properties": {
    "iso:country":"CA",
    "sg:city":"Burlington",
    "sg:classifiers":[
        {
            "category":"Building & Trades",
            "subcategory":"Construction",
            "type":"Services"
        }
    ],
    "sg:phone":"+1 905 634 8400",
    "sg:postcode":"L7M 3T4",
    "sg:province":"ON",
    "sg:tags":[
        "sandblasting"
    ],
    "wof:name":"Burlington Sandblasting",
    "wof:placetype":"venue"
},
  "geometry": {"coordinates":[-79.7984542847,43.3657302856],"type":"Point"}
}