{
  "type": "Feature",
  "properties": {
    "addr:full":"3600 Av Barclay Montreal QC H3S 1K5",
    "addr:housenumber":"3600",
    "addr:postcode":"h3s 1k5",
    "addr:street":"Av Barclay",
    "iso:country":"CA",
    "sg:address":"3600 Av Barclay",
    "sg:city":"Montreal",
    "sg:classifiers":[
        {
            "category":"Real Estate",
            "subcategory":"Real Estate Operator",
            "type":"Services"
        }
    ],
    "sg:phone":"+1 514 737 2268",
    "sg:postcode":"H3S 1K5",
    "sg:province":"QC",
    "sg:tags":[
        "apartment"
    ],
    "wof:name":"Fdl Compagnie Ltee",
    "wof:placetype":"venue"
},
  "geometry": {"coordinates":[-73.6350326538,45.5029716492],"type":"Point"}
}