{
  "type": "Feature",
  "properties": {
    "addr:full":"817 High St W Moose Jaw SK S6H 6L7",
    "addr:housenumber":"817",
    "addr:postcode":"s6h 6l7",
    "addr:street":"High St W",
    "iso:country":"CA",
    "sg:address":"817 High St W",
    "sg:city":"Moose Jaw",
    "sg:classifiers":[
        {
            "category":"Real Estate",
            "subcategory":"Real Estate Agent",
            "type":"Services"
        }
    ],
    "sg:phone":"+1 306 692 8958",
    "sg:postcode":"S6H 6L7",
    "sg:province":"SK",
    "wof:name":"L J Agencies Ltd",
    "wof:placetype":"venue"
},
  "geometry": {"coordinates":[-105.55510700000001,50.391388],"type":"Point"}
}