{
  "type": "Feature",
  "properties": {
    "addr:full":"1512 Niagara Stone Rd Virgil ON L0S 1T0",
    "addr:housenumber":"1512",
    "addr:postcode":"l0s 1t0",
    "addr:street":"Niagara Stone Rd",
    "iso:country":"CA",
    "sg:address":"1512 Niagara Stone Rd",
    "sg:city":"Virgil",
    "sg:classifiers":[
        {
            "category":"Banks & Credit Unions",
            "subcategory":"Investment Brokerage",
            "type":"Services"
        }
    ],
    "sg:phone":"+1 905 468 2232",
    "sg:postcode":"L0S 1T0",
    "sg:province":"ON",
    "sg:tags":[
        "consultant",
        "planning",
        "financial"
    ],
    "wof:name":"Quantum Financial Group",
    "wof:placetype":"venue"
},
  "geometry": {"coordinates":[-79.12200900000001,43.22224],"type":"Point"}
}