{
  "type": "Feature",
  "properties": {
    "iso:country":"CA",
    "sg:city":"Mission",
    "sg:classifiers":[
        {
            "category":"Banks & Credit Unions",
            "subcategory":"Bank",
            "type":"Services"
        }
    ],
    "sg:phone":"+1 604 826 3644",
    "sg:postcode":"V2V 7B8",
    "sg:province":"BC",
    "wof:name":"Prospera Credit Union",
    "wof:placetype":"venue"
},
  "geometry": {"coordinates":[-122.327393,49.133045],"type":"Point"}
}