{
  "type": "Feature",
  "properties": {
    "addr:full":"3932 29 St NE Calgary AB T1Y 6B6",
    "addr:housenumber":"3932",
    "addr:postcode":"t1y 6b6",
    "addr:street":"29 St Ne",
    "iso:country":"CA",
    "sg:address":"3932 29 St NE",
    "sg:city":"Calgary",
    "sg:classifiers":[
        {
            "category":"Wholesale",
            "subcategory":"Apparel",
            "type":"Manufacturing & Wholesale Goods"
        }
    ],
    "sg:phone":"+1 403 291 4494",
    "sg:postcode":"T1Y 6B6",
    "sg:province":"AB",
    "sg:tags":[
        "notion"
    ],
    "wof:name":"Cansew Inc",
    "wof:placetype":"venue"
},
  "geometry": {"coordinates":[-113.991569519,51.0880737305],"type":"Point"}
}