{
  "type": "Feature",
  "properties": {
    "addr:full":"2360 Naramata Rd Naramata BC V0H 1N0",
    "addr:housenumber":"2360",
    "addr:postcode":"v0h 1n0",
    "addr:street":"Naramata Rd",
    "iso:country":"CA",
    "sg:address":"2360 Naramata Rd",
    "sg:city":"Naramata",
    "sg:classifiers":[
        {
            "category":"Wholesale",
            "subcategory":"Machinery & Supplies",
            "type":"Manufacturing & Wholesale Goods"
        }
    ],
    "sg:phone":"+1 250 496 5338",
    "sg:postcode":"V0H 1N0",
    "sg:province":"BC",
    "sg:tags":[
        "farm",
        "equipment"
    ],
    "wof:name":"Zeller & Son Enterprises Ltd",
    "wof:placetype":"venue"
},
  "geometry": {"coordinates":[-119.578506,49.570808],"type":"Point"}
}