{
  "type": "Feature",
  "properties": {
    "addr:full":"1605 18 St NE Calgary AB T2E 4W2",
    "addr:housenumber":"1605",
    "addr:postcode":"t2e 4w2",
    "addr:street":"18 St Ne",
    "iso:country":"CA",
    "sg:address":"1605 18 St NE",
    "sg:city":"Calgary",
    "sg:classifiers":[
        {
            "category":"Restaurant",
            "type":"Food & Drink"
        }
    ],
    "sg:phone":"+1 403 277 3342",
    "sg:postcode":"T2E 4W2",
    "sg:province":"AB",
    "wof:name":"Zack's Pizza Parlor",
    "wof:placetype":"venue"
},
  "geometry": {"coordinates":[-114.01635,51.065517],"type":"Point"}
}