{
  "type": "Feature",
  "properties": {
    "addr:full":"1658 Rue Saint-Denis Trois-Rivieres QC G9A 4A2",
    "addr:housenumber":"1658",
    "addr:postcode":"g9a 4a2",
    "addr:street":"Rue Saint-Denis",
    "iso:country":"CA",
    "sg:address":"1658 Rue Saint-Denis",
    "sg:city":"Trois-Rivieres",
    "sg:classifiers":[
        {
            "category":"Building & Trades",
            "subcategory":"Construction",
            "type":"Services"
        }
    ],
    "sg:phone":"+1 819 373 6701",
    "sg:postcode":"G9A 4A2",
    "sg:province":"QC",
    "sg:tags":[
        "general",
        "contractor"
    ],
    "wof:name":"Entreprises Denis Beaudry",
    "wof:placetype":"venue"
},
  "geometry": {"coordinates":[-72.548531,46.341721],"type":"Point"}
}