{
  "type": "Feature",
  "properties": {
    "addr:full":"250 Caron St St Jean Baptiste MB R0G 2B0",
    "addr:housenumber":"250",
    "addr:postcode":"r0g 2b0",
    "addr:street":"Caron St",
    "iso:country":"CA",
    "sg:address":"250 Caron St",
    "sg:city":"St Jean Baptiste",
    "sg:classifiers":[
        {
            "category":"Wholesale",
            "subcategory":"Farm Supplies",
            "type":"Manufacturing & Wholesale Goods"
        }
    ],
    "sg:phone":"+1 204 758 3597",
    "sg:postcode":"R0G 2B0",
    "sg:province":"MB",
    "sg:tags":[
        "bulb",
        "seed"
    ],
    "wof:name":"Roy Legumex Inc",
    "wof:placetype":"venue"
},
  "geometry": {"coordinates":[-97.327286,49.221802],"type":"Point"}
}