{
  "type": "Feature",
  "properties": {
    "addr:full":"70 Joseph St Parry Sound ON P2A 2G5",
    "addr:housenumber":"70",
    "addr:postcode":"p2a 2g5",
    "addr:street":"Joseph St",
    "iso:country":"CA",
    "sg:address":"70 Joseph St",
    "sg:city":"Parry Sound",
    "sg:classifiers":[
        {
            "category":"Manufacturing",
            "subcategory":"Printing",
            "type":"Manufacturing & Wholesale Goods"
        }
    ],
    "sg:phone":"+1 705 746 6434",
    "sg:postcode":"P2A 2G5",
    "sg:province":"ON",
    "sg:tags":[
        "newspaper",
        "lottery",
        "agent"
    ],
    "wof:name":"International News",
    "wof:placetype":"venue"
},
  "geometry": {"coordinates":[-80.040237,45.359016],"type":"Point"}
}