{
  "type": "Feature",
  "properties": {
    "addr:full":"Lake of the Woods Kenora ON P9N 3X3",
    "addr:postcode":"p9n 3x3",
    "iso:country":"CA",
    "sg:address":"Lake of the Woods",
    "sg:city":"Kenora",
    "sg:classifiers":[
        {
            "category":"Travel",
            "subcategory":"Hotels & Motels",
            "type":"Entertainment"
        }
    ],
    "sg:phone":"+1 807 543 4001",
    "sg:postcode":"P9N 3X3",
    "sg:province":"ON",
    "sg:tags":[
        "resort"
    ],
    "wof:name":"Crow Rock Camp",
    "wof:placetype":"venue"
},
  "geometry": {"coordinates":[-94.489311,49.770626],"type":"Point"}
}