{
  "type": "Feature",
  "properties": {
    "addr:full":"2550 Montee Saint-Francois Laval QC H7E 4P2",
    "addr:postcode":"2550;h7e 4p2",
    "addr:street":"Montee Saint-Francois",
    "iso:country":"CA",
    "sg:address":"2550 Montee Saint-Francois",
    "sg:city":"Laval",
    "sg:classifiers":[
        {
            "category":"Retail",
            "subcategory":"Auto Repair",
            "type":"Services"
        }
    ],
    "sg:phone":"+1 514 323 8713",
    "sg:postcode":"H7E 4P2",
    "sg:province":"QC",
    "sg:tags":[
        "truck"
    ],
    "wof:name":"Garage Metrop Inc",
    "wof:placetype":"venue"
},
  "geometry": {"coordinates":[-73.676804,45.645622],"type":"Point"}
}