{
  "type": "Feature",
  "properties": {
    "iso:country":"CA",
    "sg:address":"361 East River Rd",
    "sg:city":"New Glasgow",
    "sg:classifiers":[
        {
            "category":"Organizations",
            "subcategory":"Labor Organization",
            "type":"Services"
        }
    ],
    "sg:phone":"+1 902 752 3178",
    "sg:postcode":"B2H 3P8",
    "sg:province":"NS",
    "wof:name":"Caw",
    "wof:placetype":"venue"
},
  "geometry": {"coordinates":[-62.6454658508,45.5835342407],"type":"Point"}
}