{
  "type": "Feature",
  "properties": {
    "addr:full":"3015 Lake Shore Blvd W Etobicoke ON M8V 1K2",
    "addr:housenumber":"3015",
    "addr:postcode":"m8v 1k2",
    "addr:street":"Lake Shore Blvd W",
    "iso:country":"CA",
    "sg:address":"3015 Lake Shore Blvd W",
    "sg:city":"Etobicoke",
    "sg:classifiers":[
        {
            "category":"Personal",
            "subcategory":"Beauty Salon",
            "type":"Services"
        }
    ],
    "sg:phone":"+1 416 259 0461",
    "sg:postcode":"M8V 1K2",
    "sg:province":"ON",
    "wof:name":"Neisha Hair Styling",
    "wof:placetype":"venue"
},
  "geometry": {"coordinates":[-79.50814800000001,43.60001],"type":"Point"}
}