{
  "type": "Feature",
  "properties": {
    "addr:full":"36 Stornoway Cres Thornhill ON L3T 3X7",
    "addr:housenumber":"36",
    "addr:postcode":"l3t 3x7",
    "addr:street":"Stornoway Cres",
    "iso:country":"CA",
    "sg:address":"36 Stornoway Cres",
    "sg:city":"Thornhill",
    "sg:classifiers":[
        {
            "category":"Education",
            "subcategory":"School",
            "type":"Public Place"
        }
    ],
    "sg:phone":"+1 905 889 9535",
    "sg:postcode":"L3T 3X7",
    "sg:province":"ON",
    "wof:name":"Stornoway Crescent Public Schl",
    "wof:placetype":"venue"
},
  "geometry": {"coordinates":[-79.411072,43.829304],"type":"Point"}
}