{
  "type": "Feature",
  "properties": {
    "addr:full":"Mcbride BC V0J 2E0",
    "addr:postcode":"v0j 2e0",
    "iso:country":"CA",
    "sg:city":"Mcbride",
    "sg:classifiers":[
        {
            "category":"Shopping",
            "subcategory":"Bicycles & Sporting Goods",
            "type":"Retail Goods"
        }
    ],
    "sg:phone":"+1 250 569 0320",
    "sg:postcode":"V0J 2E0",
    "sg:province":"BC",
    "sg:tags":[
        "paint",
        "ball",
        "sport"
    ],
    "wof:name":"Wahoo Enterprises",
    "wof:placetype":"venue"
},
  "geometry": {"coordinates":[-120.168190002,53.3010101318],"type":"Point"}
}