{
  "type": "Feature",
  "properties": {
    "addr:full":"163 James Bay Jct Rd Parry Sound ON P2A 2W8",
    "addr:housenumber":"163",
    "addr:postcode":"p2a 2w8",
    "addr:street":"James Bay Jct Rd",
    "iso:country":"CA",
    "sg:address":"163 James Bay Jct Rd",
    "sg:city":"Parry Sound",
    "sg:classifiers":[
        {
            "category":"Building & Trades",
            "subcategory":"Construction",
            "type":"Services"
        }
    ],
    "sg:phone":"+1 705 378 1065",
    "sg:postcode":"P2A 2W8",
    "sg:province":"ON",
    "sg:tags":[
        "general",
        "contractor"
    ],
    "wof:name":"Badger Construction Ltd",
    "wof:placetype":"venue"
},
  "geometry": {"coordinates":[-80.0363616943,45.3447685242],"type":"Point"}
}