{
  "type": "Feature",
  "properties": {
    "addr:full":"208 Water St Exten Campbellton NB E3N 1B2",
    "addr:housenumber":"208",
    "addr:postcode":"e3n 1b2",
    "addr:street":"Water St Exten",
    "iso:country":"CA",
    "sg:address":"208 Water St Exten",
    "sg:city":"Campbellton",
    "sg:classifiers":[
        {
            "category":"Freight",
            "type":"Transportation"
        }
    ],
    "sg:phone":"+1 506 759 8744",
    "sg:postcode":"E3N 1B2",
    "sg:province":"NB",
    "sg:tags":[
        "trucking"
    ],
    "wof:name":"Armour Transport Inc",
    "wof:placetype":"venue"
},
  "geometry": {"coordinates":[-66.6672210693,47.9954986572],"type":"Point"}
}