{
  "type": "Feature",
  "properties": {
    "iso:country":"CA",
    "sg:address":"186 Steel St",
    "sg:city":"Barrie",
    "sg:classifiers":[
        {
            "category":"Banks & Credit Unions",
            "subcategory":"Investment Brokerage",
            "type":"Services"
        }
    ],
    "sg:phone":"+1 705 739 9092",
    "sg:postcode":"L4M 2G4",
    "sg:province":"ON",
    "sg:tags":[
        "consultant",
        "financing"
    ],
    "wof:name":"Jensen Financial Consultants",
    "wof:placetype":"venue"
},
  "geometry": {"coordinates":[-79.65667,44.401237],"type":"Point"}
}