{
  "type": "Feature",
  "properties": {
    "addr:full":"460 Finley Ave Ajax ON L1S 2E3",
    "addr:housenumber":"460",
    "addr:postcode":"l1s 2e3",
    "addr:street":"Finley Ave",
    "iso:country":"CA",
    "sg:address":"460 Finley Ave",
    "sg:city":"Ajax",
    "sg:classifiers":[
        {
            "category":"Manufacturing",
            "subcategory":"Rubber & Plastics",
            "type":"Manufacturing & Wholesale Goods"
        }
    ],
    "sg:phone":"+1 905 428 6197",
    "sg:postcode":"L1S 2E3",
    "sg:province":"ON",
    "sg:tags":[
        "producer"
    ],
    "wof:name":"Vinyl Distributors",
    "wof:placetype":"venue"
},
  "geometry": {"coordinates":[-79.0290985107,43.8371162415],"type":"Point"}
}