{
  "type": "Feature",
  "properties": {
    "iso:country":"CA",
    "sg:address":"8649 Boul Viau",
    "sg:city":"Saint-Leonard",
    "sg:classifiers":[
        {
            "category":"Shopping",
            "subcategory":"Tobacco",
            "type":"Retail Goods"
        }
    ],
    "sg:phone":"+1 514 321 4583",
    "sg:postcode":"H1R 2T9",
    "sg:province":"QC",
    "sg:tags":[
        "cigarette",
        "cigar",
        "dealer"
    ],
    "wof:name":"Depanneur Solita Enr",
    "wof:placetype":"venue"
},
  "geometry": {"coordinates":[-73.6050643921,45.5845336914],"type":"Point"}
}