{
  "type": "Feature",
  "properties": {
    "addr:full":"38 Rue Des Trembles Saint-Luc QC J2W 1B1",
    "addr:housenumber":"38",
    "addr:postcode":"j2w 1b1",
    "addr:street":"Rue Des Trembles",
    "iso:country":"CA",
    "sg:address":"38 Rue Des Trembles",
    "sg:city":"Saint-Luc",
    "sg:classifiers":[
        {
            "category":"Communications",
            "subcategory":"Film & Video Production",
            "type":"Services"
        }
    ],
    "sg:phone":"+1 450 359 0131",
    "sg:postcode":"J2W 1B1",
    "sg:province":"QC",
    "sg:tags":[
        "taping"
    ],
    "wof:name":"Production MD Inc",
    "wof:placetype":"venue"
},
  "geometry": {"coordinates":[-73.367538,45.380856],"type":"Point"}
}