{
  "type": "Feature",
  "properties": {
    "iso:country":"CA",
    "sg:address":"238 11 Ave SE",
    "sg:city":"Calgary",
    "sg:classifiers":[
        {
            "category":"Wholesale",
            "subcategory":"Computers",
            "type":"Manufacturing & Wholesale Goods"
        }
    ],
    "sg:phone":"+1 403 261 3026",
    "sg:postcode":"T2G 0X8",
    "sg:province":"AB",
    "sg:tags":[
        "equipment",
        "scanning",
        "graphics"
    ],
    "wof:name":"Accumedia Technologies Ltd",
    "wof:placetype":"venue"
},
  "geometry": {"coordinates":[-114.059776306,51.0423927307],"type":"Point"}
}