{
  "type": "Feature",
  "properties": {
    "addr:full":"223 Principale Saint-Clet QC J0P 1S0",
    "addr:housenumber":"223",
    "addr:postcode":"j0p 1s0",
    "addr:street":"Principale",
    "iso:country":"CA",
    "sg:address":"223 Principale",
    "sg:city":"Saint-Clet",
    "sg:classifiers":[
        {
            "category":"Organizations",
            "subcategory":"Religious Organization",
            "type":"Services"
        }
    ],
    "sg:phone":"+1 514 456 3284",
    "sg:postcode":"J0P 1S0",
    "sg:province":"QC",
    "sg:tags":[
        "church"
    ],
    "wof:name":"Eglise St Clet Catholic Church",
    "wof:placetype":"venue"
},
  "geometry": {"coordinates":[-74.22073399999999,45.351608],"type":"Point"}
}