{
  "type": "Feature",
  "properties": {
    "iso:country":"CA",
    "sg:address":"130 Waddell Ave",
    "sg:city":"Dominion City",
    "sg:classifiers":[
        {
            "category":"Banks & Credit Unions",
            "subcategory":"Bank",
            "type":"Services"
        }
    ],
    "sg:phone":"+1 204 427 2119",
    "sg:postcode":"R0A 0H0",
    "sg:province":"MB",
    "wof:name":"Cibc",
    "wof:placetype":"venue"
},
  "geometry": {"coordinates":[-97.1622467041,49.1334648132],"type":"Point"}
}