{
  "type": "Feature",
  "properties": {
    "addr:full":"11030 River Rd Delta BC V4C 2S2",
    "addr:housenumber":"11030",
    "addr:postcode":"v4c 2s2",
    "addr:street":"River Rd",
    "iso:country":"CA",
    "sg:address":"11030 River Rd",
    "sg:city":"Delta",
    "sg:classifiers":[
        {
            "category":"Health Services",
            "subcategory":"Nursing And Care Facility",
            "type":"Services"
        }
    ],
    "sg:phone":"+1 604 584 2223",
    "sg:postcode":"V4C 2S2",
    "sg:province":"BC",
    "sg:tags":[
        "home",
        "retirement",
        "community"
    ],
    "wof:name":"Abbeyfield House Annieville",
    "wof:placetype":"venue"
},
  "geometry": {"coordinates":[-122.915130615,49.170173645],"type":"Point"}
}