{
  "type": "Feature",
  "properties": {
    "addr:full":"16135 114 Ave NW Edmonton AB T5M 2Z3",
    "addr:housenumber":"16135",
    "addr:postcode":"t5m 2z3",
    "addr:street":"114 Ave Nw",
    "iso:country":"CA",
    "sg:address":"16135 114 Ave NW",
    "sg:city":"Edmonton",
    "sg:classifiers":[
        {
            "category":"Wholesale",
            "subcategory":"Machinery & Supplies",
            "type":"Manufacturing & Wholesale Goods"
        }
    ],
    "sg:phone":"+1 780 453 3718",
    "sg:postcode":"T5M 2Z3",
    "sg:province":"AB",
    "sg:tags":[
        "insulation",
        "packaging",
        "material"
    ],
    "wof:name":"Plasti-Fab",
    "wof:placetype":"venue"
},
  "geometry": {"coordinates":[-113.599746704,53.5627822876],"type":"Point"}
}