{
  "type": "Feature",
  "properties": {
    "iso:country":"CA",
    "sg:address":"PO Box 8",
    "sg:city":"Chesterfield Inlet",
    "sg:classifiers":[
        {
            "category":"Building & Trades",
            "subcategory":"Construction",
            "type":"Services"
        }
    ],
    "sg:phone":"+1 867 898 9175",
    "sg:postcode":"X0C 0B0",
    "sg:province":"NU",
    "sg:tags":[
        "general",
        "contractor"
    ],
    "wof:name":"Aulajug Limited",
    "wof:placetype":"venue"
},
  "geometry": {"coordinates":[-90.70715332029999,63.339641571],"type":"Point"}
}