{
  "type": "Feature",
  "properties": {
    "addr:full":"Montreal QC H3M 3E2",
    "addr:postcode":"h3m 3e2",
    "iso:country":"CA",
    "sg:city":"Montreal",
    "sg:classifiers":[
        {
            "category":"Professional",
            "subcategory":"Engineering",
            "type":"Services"
        }
    ],
    "sg:phone":"+1 514 337 6662",
    "sg:postcode":"H3M 3E2",
    "sg:province":"QC",
    "sg:tags":[
        "engineer"
    ],
    "wof:name":"Groupe Progima",
    "wof:placetype":"venue"
},
  "geometry": {"coordinates":[-73.678719,45.5368],"type":"Point"}
}