{
  "type": "Feature",
  "properties": {
    "addr:full":"4811 Niven Rd NW Calgary AB T2K 6B7",
    "addr:housenumber":"4811",
    "addr:postcode":"t2k 6b7",
    "addr:street":"Niven Rd Nw",
    "iso:country":"CA",
    "sg:address":"4811 Niven Rd NW",
    "sg:city":"Calgary",
    "sg:classifiers":[
        {
            "category":"Real Estate",
            "subcategory":"Real Estate Operator",
            "type":"Services"
        }
    ],
    "sg:phone":"+1 403 282 5762",
    "sg:postcode":"T2K 6B7",
    "sg:province":"AB",
    "sg:tags":[
        "senior",
        "apartment",
        "housing",
        "citizen"
    ],
    "wof:name":"Cambrian Manor",
    "wof:placetype":"venue"
},
  "geometry": {"coordinates":[-114.09258270300001,51.0975112915],"type":"Point"}
}