{
  "type": "Feature",
  "properties": {
    "iso:country":"CA",
    "sg:address":"375 Rue DE Courcelette # 900",
    "sg:city":"Sherbrooke",
    "sg:classifiers":[
        {
            "category":"Professional",
            "type":"Services"
        }
    ],
    "sg:phone":"+1 819 347 1111",
    "sg:postcode":"J1H 3X4",
    "sg:province":"QC",
    "sg:tags":[
        "assistance",
        "program",
        "technology"
    ],
    "wof:name":"Enerkem Technologie Inc",
    "wof:placetype":"venue"
},
  "geometry": {"coordinates":[-71.898773,45.395355],"type":"Point"}
}