{
  "type": "Feature",
  "properties": {
    "addr:full":"275 Elm Ave Beaconsfield QC H9W 2E4",
    "addr:housenumber":"275",
    "addr:postcode":"h9w 2e4",
    "addr:street":"Elm Ave",
    "iso:country":"CA",
    "sg:address":"275 Elm Ave",
    "sg:city":"Beaconsfield",
    "sg:classifiers":[
        {
            "category":"Personal",
            "subcategory":"Beauty Salon",
            "type":"Services"
        }
    ],
    "sg:phone":"+1 514 694 8317",
    "sg:postcode":"H9W 2E4",
    "sg:province":"QC",
    "wof:name":"Revolution Hair Studio",
    "wof:placetype":"venue"
},
  "geometry": {"coordinates":[-73.864571,45.43132],"type":"Point"}
}