{
  "type": "Feature",
  "properties": {
    "iso:country":"CA",
    "sg:address":"325 Lambton St",
    "sg:city":"Kincardine",
    "sg:classifiers":[
        {
            "category":"Real Estate",
            "subcategory":"Real Estate Agent",
            "type":"Services"
        }
    ],
    "sg:phone":"+1 519 396 1221",
    "sg:postcode":"N2Z 2Y1",
    "sg:province":"ON",
    "sg:tags":[
        "management"
    ],
    "wof:name":"Princes Grand Estate",
    "wof:placetype":"venue"
},
  "geometry": {"coordinates":[-81.6317367554,44.1816139221],"type":"Point"}
}