{
  "type": "Feature",
  "properties": {
    "addr:full":"1198 Government St Penticton BC V2A 4V1",
    "addr:housenumber":"1198",
    "addr:postcode":"v2a 4v1",
    "addr:street":"Government St",
    "iso:country":"CA",
    "sg:address":"1198 Government St",
    "sg:city":"Penticton",
    "sg:classifiers":[
        {
            "category":"Autos & Motor Vehicles",
            "subcategory":"Fuel & Gas Station",
            "type":"Retail Goods"
        }
    ],
    "sg:phone":"+1 250 492 8606",
    "sg:postcode":"V2A 4V1",
    "sg:province":"BC",
    "sg:tags":[
        "oil"
    ],
    "wof:name":"Lake City Svc",
    "wof:placetype":"venue"
},
  "geometry": {"coordinates":[-119.578873,49.4879],"type":"Point"}
}