{
  "type": "Feature",
  "properties": {
    "addr:full":"Saint-Isidore-DE-Clifton QC J0B 2X0",
    "addr:postcode":"j0b 2x0",
    "iso:country":"CA",
    "sg:city":"Saint-Isidore-DE-Clifton",
    "sg:classifiers":[
        {
            "category":"Retail",
            "subcategory":"Auto Repair",
            "type":"Services"
        }
    ],
    "sg:phone":"+1 819 658 2161",
    "sg:postcode":"J0B 2X0",
    "sg:province":"QC",
    "sg:tags":[
        "repairing",
        "automobile"
    ],
    "wof:name":"Garage Fortier Daniel",
    "wof:placetype":"venue"
},
  "geometry": {"coordinates":[-71.528458,45.268421],"type":"Point"}
}