{
  "type": "Feature",
  "properties": {
    "iso:country":"CA",
    "sg:address":"3355 the Collegeway # 15",
    "sg:city":"Mississauga",
    "sg:classifiers":[
        {
            "category":"Food & Beverages",
            "subcategory":"Groceries & Convenience Stores",
            "type":"Retail Goods"
        }
    ],
    "sg:phone":"+1 905 607 6222",
    "sg:postcode":"L5L 5T3",
    "sg:province":"ON",
    "sg:tags":[
        "grocer"
    ],
    "wof:name":"Jeanie's Market Place",
    "wof:placetype":"venue"
},
  "geometry": {"coordinates":[-79.70365905760001,43.5241394043],"type":"Point"}
}