{
  "type": "Feature",
  "properties": {
    "addr:full":"9649 94 Ave # 100 Grande Prairie AB T8V 6H3",
    "addr:housenumber":"9649",
    "addr:postcode":"t8v 6h3",
    "addr:street":"94 Ave # 100",
    "iso:country":"CA",
    "sg:address":"9649 94 Ave # 100",
    "sg:city":"Grande Prairie",
    "sg:classifiers":[
        {
            "category":"Real Estate",
            "subcategory":"Real Estate Operator",
            "type":"Services"
        }
    ],
    "sg:phone":"+1 780 539 4560",
    "sg:postcode":"T8V 6H3",
    "sg:province":"AB",
    "sg:tags":[
        "apartment"
    ],
    "wof:name":"Prairie Sunrise Towers Ltd",
    "wof:placetype":"venue"
},
  "geometry": {"coordinates":[-118.78521000000001,55.165146],"type":"Point"}
}