{
  "type": "Feature",
  "properties": {
    "addr:full":"625 Rue Du Pont Saint-Gedeon QC G0W 2P0",
    "addr:housenumber":"625",
    "addr:postcode":"g0w 2p0",
    "addr:street":"Rue Du Pont Saint-Gedeon",
    "iso:country":"CA",
    "sg:address":"625 Rue Du Pont",
    "sg:city":"Saint-Gedeon",
    "sg:classifiers":[
        {
            "category":"Retail",
            "subcategory":"Repair Shop",
            "type":"Services"
        }
    ],
    "sg:phone":"+1 418 345 8991",
    "sg:postcode":"G0W 2P0",
    "sg:province":"QC",
    "sg:tags":[
        "tool",
        "parts",
        "grinding"
    ],
    "wof:name":"Outilleurs Guy Girard",
    "wof:placetype":"venue"
},
  "geometry": {"coordinates":[-71.79084,48.479027],"type":"Point"}
}