{
  "type": "Feature",
  "properties": {
    "addr:full":"PO Box 78 STN Main Duncan BC V9L 3X1",
    "addr:housenumber":"po box 78",
    "addr:postcode":"v9l 3x1",
    "addr:street":"Stn Main",
    "iso:country":"CA",
    "sg:address":"PO Box 78 STN Main",
    "sg:city":"Duncan",
    "sg:classifiers":[
        {
            "category":"Building & Trades",
            "subcategory":"Construction",
            "type":"Services"
        }
    ],
    "sg:phone":"+1 250 746 3653",
    "sg:postcode":"V9L 3X1",
    "sg:province":"BC",
    "sg:tags":[
        "general",
        "contractor"
    ],
    "wof:name":"Chris Clement Construction",
    "wof:placetype":"venue"
},
  "geometry": {"coordinates":[-123.70738220200001,48.779094696],"type":"Point"}
}