{
  "type": "Feature",
  "properties": {
    "iso:country":"CA",
    "sg:address":"7450 Boul Taschereau",
    "sg:city":"Brossard",
    "sg:classifiers":[
        {
            "category":"Restaurant",
            "type":"Food & Drink"
        }
    ],
    "sg:phone":"+1 450 466 7040",
    "sg:postcode":"J4W 1M9",
    "sg:province":"QC",
    "wof:name":"Mc Donald's",
    "wof:placetype":"venue"
},
  "geometry": {"coordinates":[-73.46534,45.45726],"type":"Point"}
}