{
  "type": "Feature",
  "properties": {
    "addr:full":"16531 106 St NW Edmonton AB T5X 1W4",
    "addr:housenumber":"16531",
    "addr:postcode":"t5x 1w4",
    "addr:street":"106 St Nw",
    "iso:country":"CA",
    "sg:address":"16531 106 St NW",
    "sg:city":"Edmonton",
    "sg:classifiers":[
        {
            "category":"Shopping",
            "subcategory":"Bicycles & Sporting Goods",
            "type":"Retail Goods"
        }
    ],
    "sg:phone":"+1 780 457 0988",
    "sg:postcode":"T5X 1W4",
    "sg:province":"AB",
    "sg:tags":[
        "equipment",
        "playground"
    ],
    "wof:name":"Childspace Playgrounds/Rocky",
    "wof:placetype":"venue"
},
  "geometry": {"coordinates":[-113.504875183,53.6274185181],"type":"Point"}
}