{
  "type": "Feature",
  "properties": {
    "iso:country":"CA",
    "sg:address":"675 Kildare Ave E",
    "sg:city":"Winnipeg",
    "sg:classifiers":[
        {
            "category":"Shopping",
            "type":"Retail Goods"
        }
    ],
    "sg:phone":"+1 204 224 4992",
    "sg:postcode":"R2C 0P9",
    "sg:province":"MB",
    "sg:tags":[
        "mail",
        "catalog",
        "miscellaneous",
        "store",
        "order"
    ],
    "wof:name":"Giggles & Toys Canada",
    "wof:placetype":"venue"
},
  "geometry": {"coordinates":[-96.98471832280001,49.9009895325],"type":"Point"}
}