{
  "type": "Feature",
  "properties": {
    "addr:full":"113 Central Ave E Linden AB T0M 1J0",
    "addr:housenumber":"113",
    "addr:postcode":"t0m 1j0",
    "addr:street":"Central Ave E",
    "iso:country":"CA",
    "sg:address":"113 Central Ave E",
    "sg:city":"Linden",
    "sg:classifiers":[
        {
            "category":"Shopping",
            "subcategory":"Crafts & Fabrics",
            "type":"Retail Goods"
        }
    ],
    "sg:phone":"+1 403 546 3882",
    "sg:postcode":"T0M 1J0",
    "sg:province":"AB",
    "sg:tags":[
        "shop"
    ],
    "wof:name":"Jo-Al Styles & Fabrics",
    "wof:placetype":"venue"
},
  "geometry": {"coordinates":[-113.48468,51.590519],"type":"Point"}
}