{
  "type": "Feature",
  "properties": {
    "addr:full":"502 King St W Toronto ON M5V 1L7",
    "addr:housenumber":"502",
    "addr:postcode":"m5v 1l7",
    "addr:street":"King St W",
    "iso:country":"CA",
    "sg:address":"502 King St W",
    "sg:city":"Toronto",
    "sg:classifiers":[
        {
            "category":"Professional",
            "subcategory":"Research",
            "type":"Services"
        }
    ],
    "sg:phone":"+1 416 922 9414",
    "sg:postcode":"M5V 1L7",
    "sg:province":"ON",
    "sg:tags":[
        "market",
        "analysis"
    ],
    "wof:name":"Impact Research",
    "wof:placetype":"venue"
},
  "geometry": {"coordinates":[-79.39643100000001,43.645329],"type":"Point"}
}