{
  "type": "Feature",
  "properties": {
    "addr:full":"29 Bingham Dr Moncton NB E1E 2M8",
    "addr:housenumber":"29",
    "addr:postcode":"e1e 2m8",
    "addr:street":"Bingham Dr",
    "iso:country":"CA",
    "sg:address":"29 Bingham Dr",
    "sg:city":"Moncton",
    "sg:classifiers":[
        {
            "category":"Personal",
            "type":"Services"
        }
    ],
    "sg:phone":"+1 506 857 4263",
    "sg:postcode":"E1E 2M8",
    "sg:province":"NB",
    "sg:tags":[
        "therapist",
        "massage"
    ],
    "wof:name":"Professional Massage Clinic",
    "wof:placetype":"venue"
},
  "geometry": {"coordinates":[-64.84206399999999,46.09547],"type":"Point"}
}