{
  "type": "Feature",
  "properties": {
    "addr:full":"10 Edgewood Gdns Toronto ON M4L 3H5",
    "addr:housenumber":"10",
    "addr:postcode":"m4l 3h5",
    "addr:street":"Edgewood Gdns",
    "iso:country":"CA",
    "sg:address":"10 Edgewood Gdns",
    "sg:city":"Toronto",
    "sg:classifiers":[
        {
            "category":"Professional",
            "subcategory":"Art Services",
            "type":"Services"
        }
    ],
    "sg:phone":"+1 416 410 8666",
    "sg:postcode":"M4L 3H5",
    "sg:province":"ON",
    "sg:tags":[
        "photographer"
    ],
    "wof:name":"Richard Bell & Assoc",
    "wof:placetype":"venue"
},
  "geometry": {"coordinates":[-79.3138961792,43.6731834412],"type":"Point"}
}