{
  "type": "Feature",
  "properties": {
    "iso:country":"CA",
    "sg:address":"35110 Delair Rd",
    "sg:city":"Abbotsford",
    "sg:classifiers":[
        {
            "category":"Retail",
            "subcategory":"Portrait Studio",
            "type":"Services"
        }
    ],
    "sg:phone":"+1 604 853 6599",
    "sg:postcode":"V4X 2B1",
    "sg:province":"BC",
    "sg:tags":[
        "photographer"
    ],
    "wof:name":"Frank Stadnyk Photographer",
    "wof:placetype":"venue"
},
  "geometry": {"coordinates":[-122.25273132300001,49.0340499878],"type":"Point"}
}