{
  "type": "Feature",
  "properties": {
    "addr:full":"3456 Av Du Parc Montreal QC H2X 2H5",
    "addr:housenumber":"3456",
    "addr:postcode":"h2x 2h5",
    "addr:street":"Av Du Parc",
    "iso:country":"CA",
    "sg:address":"3456 Av Du Parc",
    "sg:city":"Montreal",
    "sg:classifiers":[
        {
            "category":"Restaurant",
            "type":"Food & Drink"
        }
    ],
    "sg:phone":"+1 514 849 2030",
    "sg:postcode":"H2X 2H5",
    "sg:province":"QC",
    "wof:name":"Bodega Cafe Restaurant",
    "wof:placetype":"venue"
},
  "geometry": {"coordinates":[-73.57274627690001,45.5088882446],"type":"Point"}
}