{
  "type": "Feature",
  "properties": {
    "addr:full":"Oakville ON L6L 5W8",
    "addr:postcode":"l6l 5w8",
    "iso:country":"CA",
    "sg:city":"Oakville",
    "sg:classifiers":[
        {
            "category":"Retail",
            "subcategory":"Veterinary Services",
            "type":"Services"
        }
    ],
    "sg:phone":"+1 905 825 2100",
    "sg:postcode":"L6L 5W8",
    "sg:province":"ON",
    "sg:tags":[
        "veterinarian"
    ],
    "wof:name":"Bronte Road Animal Hospital",
    "wof:placetype":"venue"
},
  "geometry": {"coordinates":[-79.7293014526,43.4048614502],"type":"Point"}
}