{
  "type": "Feature",
  "properties": {
    "addr:full":"Fort Smith NT X0E 0P0",
    "addr:postcode":"x0e 0p0",
    "iso:country":"CA",
    "sg:city":"Fort Smith",
    "sg:classifiers":[
        {
            "category":"Government",
            "subcategory":"Office",
            "type":"Public Place"
        }
    ],
    "sg:phone":"+1 867 872 7310",
    "sg:postcode":"X0E 0P0",
    "sg:province":"NT",
    "wof:name":"N T Human Resources Clerk",
    "wof:placetype":"venue"
},
  "geometry": {"coordinates":[-111.90263400000001,60.000095],"type":"Point"}
}