{
  "type": "Feature",
  "properties": {
    "addr:full":"555 Marlee Ave North York ON M6B 3J6",
    "addr:housenumber":"555",
    "addr:postcode":"m6b 3j6",
    "addr:street":"Marlee Ave",
    "iso:country":"CA",
    "sg:address":"555 Marlee Ave",
    "sg:city":"North York",
    "sg:classifiers":[
        {
            "category":"Personal",
            "subcategory":"Beauty Salon",
            "type":"Services"
        }
    ],
    "sg:phone":"+1 416 787 0299",
    "sg:postcode":"M6B 3J6",
    "sg:province":"ON",
    "wof:name":"Tammy' Spa",
    "wof:placetype":"venue"
},
  "geometry": {"coordinates":[-79.44368,43.709175],"type":"Point"}
}