{
  "type": "Feature",
  "properties": {
    "addr:full":"144 Rue Principale Leclercville QC G0S 2K0",
    "addr:housenumber":"144",
    "addr:postcode":"g0s 2k0",
    "addr:street":"Rue Principale",
    "iso:country":"CA",
    "sg:address":"144 Rue Principale",
    "sg:city":"Leclercville",
    "sg:classifiers":[
        {
            "category":"Shopping",
            "subcategory":"Discount & Variety Stores",
            "type":"Retail Goods"
        }
    ],
    "sg:phone":"+1 819 292 2220",
    "sg:postcode":"G0S 2K0",
    "sg:province":"QC",
    "sg:tags":[
        "merchandise",
        "general"
    ],
    "wof:name":"C E Beaudet Inc",
    "wof:placetype":"venue"
},
  "geometry": {"coordinates":[-71.999191,46.571159],"type":"Point"}
}