{
  "type": "Feature",
  "properties": {
    "addr:full":"455 Grand Ave E Chatham ON N7L 1X4",
    "addr:housenumber":"455",
    "addr:postcode":"n7l 1x4",
    "addr:street":"Grand Ave E",
    "iso:country":"CA",
    "sg:address":"455 Grand Ave E",
    "sg:city":"Chatham",
    "sg:classifiers":[
        {
            "category":"Personal",
            "type":"Services"
        }
    ],
    "sg:phone":"+1 519 355 0330",
    "sg:postcode":"N7L 1X4",
    "sg:province":"ON",
    "sg:tags":[
        "control",
        "weight"
    ],
    "wof:name":"Herbal One Weight Management",
    "wof:placetype":"venue"
},
  "geometry": {"coordinates":[-82.1746520996,42.4185295105],"type":"Point"}
}