{
  "type": "Feature",
  "properties": {
    "addr:full":"4 Hemlock Ave Corner Brook NL A2H 3C8",
    "addr:housenumber":"4",
    "addr:postcode":"a2h 3c8",
    "addr:street":"Hemlock Ave",
    "iso:country":"CA",
    "sg:address":"4 Hemlock Ave",
    "sg:city":"Corner Brook",
    "sg:classifiers":[
        {
            "category":"Manufacturing",
            "subcategory":"Tools & Machinery",
            "type":"Manufacturing & Wholesale Goods"
        }
    ],
    "sg:phone":"+1 709 634 4870",
    "sg:postcode":"A2H 3C8",
    "sg:province":"NL",
    "sg:tags":[
        "equipment",
        "electric",
        "motor",
        "infrared"
    ],
    "wof:name":"Locke's Motor Svc",
    "wof:placetype":"venue"
},
  "geometry": {"coordinates":[-57.9144248962,48.9548606873],"type":"Point"}
}