{
  "type": "Feature",
  "properties": {
    "addr:full":"502 Sharpe St New Westminster BC V3M 4R2",
    "addr:housenumber":"502",
    "addr:postcode":"v3m 4r2",
    "addr:street":"Sharpe St",
    "iso:country":"CA",
    "sg:address":"502 Sharpe St",
    "sg:city":"New Westminster",
    "sg:classifiers":[
        {
            "category":"Building & Trades",
            "subcategory":"Construction",
            "type":"Services"
        }
    ],
    "sg:phone":"+1 604 526 9922",
    "sg:postcode":"V3M 4R2",
    "sg:province":"BC",
    "sg:tags":[
        "painter"
    ],
    "wof:name":"Royal City Decorators Ltd",
    "wof:placetype":"venue"
},
  "geometry": {"coordinates":[-122.933151,49.203972],"type":"Point"}
}