{
  "type": "Feature",
  "properties": {
    "addr:full":"160 Boul Saint-Rene O Gatineau QC J8P 2V4",
    "addr:housenumber":"160",
    "addr:postcode":"j8p 2v4",
    "addr:street":"Boul Saint-Rene O",
    "iso:country":"CA",
    "sg:address":"160 Boul Saint-Rene O",
    "sg:city":"Gatineau",
    "sg:classifiers":[
        {
            "category":"Personal",
            "subcategory":"Tanning Parlor",
            "type":"Services"
        }
    ],
    "sg:phone":"+1 819 643 3030",
    "sg:postcode":"J8P 2V4",
    "sg:province":"QC",
    "sg:tags":[
        "salon"
    ],
    "wof:name":"Salon DE Bronzage Flamingo",
    "wof:placetype":"venue"
},
  "geometry": {"coordinates":[-75.651207,45.492111],"type":"Point"}
}