{
  "type": "Feature",
  "properties": {
    "addr:full":"158 8th St Brandon MB R7A 3X1",
    "addr:housenumber":"158",
    "addr:postcode":"r7a 3x1",
    "addr:street":"8Th St",
    "iso:country":"CA",
    "sg:address":"158 8th St",
    "sg:city":"Brandon",
    "sg:classifiers":[
        {
            "category":"Real Estate",
            "subcategory":"Architect",
            "type":"Services"
        }
    ],
    "sg:phone":"+1 204 727 8853",
    "sg:postcode":"R7A 3X1",
    "sg:province":"MB",
    "wof:name":"Mcm Architects Inc",
    "wof:placetype":"venue"
},
  "geometry": {"coordinates":[-99.9488525391,49.8472328186],"type":"Point"}
}