{
  "type": "Feature",
  "properties": {
    "addr:full":"1098 Wilson Ave North York ON M3M 1G7",
    "addr:housenumber":"1098",
    "addr:postcode":"m3m 1g7",
    "addr:street":"Wilson Ave",
    "iso:country":"CA",
    "sg:address":"1098 Wilson Ave",
    "sg:city":"North York",
    "sg:classifiers":[
        {
            "category":"Banks & Credit Unions",
            "subcategory":"Bank",
            "type":"Services"
        }
    ],
    "sg:phone":"+1 416 633 9156",
    "sg:postcode":"M3M 1G7",
    "sg:province":"ON",
    "wof:name":"Cibc",
    "wof:placetype":"venue"
},
  "geometry": {"coordinates":[-79.482315,43.72673],"type":"Point"}
}