{
  "type": "Feature",
  "properties": {
    "addr:full":"4679 Kingsway Burnaby BC V5H 2B3",
    "addr:housenumber":"4679",
    "addr:postcode":"v5h 2b3",
    "addr:street":"Kingsway",
    "iso:country":"CA",
    "sg:address":"4679 Kingsway",
    "sg:city":"Burnaby",
    "sg:classifiers":[
        {
            "category":"Restaurant",
            "type":"Food & Drink"
        }
    ],
    "sg:phone":"+1 604 435 1111",
    "sg:postcode":"V5H 2B3",
    "sg:province":"BC",
    "wof:name":"Canadian 2 For 1 Pizza",
    "wof:placetype":"venue"
},
  "geometry": {"coordinates":[-123.000069,49.228798],"type":"Point"}
}