{
  "type": "Feature",
  "properties": {
    "addr:full":"Rawdon QC J0K 1S0",
    "addr:postcode":"j0k 1s0",
    "iso:country":"CA",
    "sg:city":"Rawdon",
    "sg:classifiers":[
        {
            "category":"Health Services",
            "subcategory":"Clinic",
            "type":"Services"
        }
    ],
    "sg:phone":"+1 450 834 5801",
    "sg:postcode":"J0K 1S0",
    "sg:province":"QC",
    "sg:tags":[
        "home"
    ],
    "wof:name":"Soins Prn Lanaudiere",
    "wof:placetype":"venue"
},
  "geometry": {"coordinates":[-73.7019195557,46.0506629944],"type":"Point"}
}