{
  "type": "Feature",
  "properties": {
    "addr:full":"5532 51 Ave Killam AB T0B 2L0",
    "addr:housenumber":"5532",
    "addr:postcode":"t0b 2l0",
    "addr:street":"51 Ave",
    "iso:country":"CA",
    "sg:address":"5532 51 Ave",
    "sg:city":"Killam",
    "sg:classifiers":[
        {
            "category":"Home & Garden",
            "subcategory":"Building Materials",
            "type":"Retail Goods"
        }
    ],
    "sg:phone":"+1 780 385 3664",
    "sg:postcode":"T0B 2L0",
    "sg:province":"AB",
    "sg:tags":[
        "windows",
        "glass",
        "window",
        "plate"
    ],
    "wof:name":"Holbies Glass Ltd",
    "wof:placetype":"venue"
},
  "geometry": {"coordinates":[-111.8629,52.79261],"type":"Point"}
}