{
  "type": "Feature",
  "properties": {
    "addr:full":"1390 Rue Sherbrooke O Montreal QC H3G 1J5",
    "addr:housenumber":"1390",
    "addr:postcode":"h3g 1j5",
    "addr:street":"Rue Sherbrooke O",
    "iso:country":"CA",
    "sg:address":"1390 Rue Sherbrooke O",
    "sg:city":"Montreal",
    "sg:classifiers":[
        {
            "category":"Shopping",
            "type":"Retail Goods"
        }
    ],
    "sg:phone":"+1 514 285 1611",
    "sg:postcode":"H3G 1J5",
    "sg:province":"QC",
    "sg:tags":[
        "art",
        "gallery",
        "dealer"
    ],
    "wof:name":"Galerie D'Art Du Musee Beaux",
    "wof:placetype":"venue"
},
  "geometry": {"coordinates":[-73.5646286011,45.5251655579],"type":"Point"}
}