{
  "type": "Feature",
  "properties": {
    "addr:full":"320 Airport Blvd Gander NL A1V 1X5",
    "addr:housenumber":"320",
    "addr:postcode":"a1v 1x5",
    "addr:street":"Airport Blvd",
    "iso:country":"CA",
    "sg:address":"320 Airport Blvd",
    "sg:city":"Gander",
    "sg:classifiers":[
        {
            "category":"Restaurant",
            "type":"Food & Drink"
        }
    ],
    "sg:phone":"+1 709 651 2200",
    "sg:postcode":"A1V 1X5",
    "sg:province":"NL",
    "wof:name":"Mc Donald's",
    "wof:placetype":"venue"
},
  "geometry": {"coordinates":[-54.6019668579,48.9540138245],"type":"Point"}
}