{
  "type": "Feature",
  "properties": {
    "addr:full":"7900 Av Casgrain Montreal QC H2R 1Z3",
    "addr:housenumber":"7900",
    "addr:postcode":"h2r 1z3",
    "addr:street":"Av Casgrain",
    "iso:country":"CA",
    "sg:address":"7900 Av Casgrain",
    "sg:city":"Montreal",
    "sg:classifiers":[
        {
            "category":"Wholesale",
            "subcategory":"Hardware",
            "type":"Manufacturing & Wholesale Goods"
        }
    ],
    "sg:phone":"+1 514 382 7900",
    "sg:postcode":"H2R 1Z3",
    "sg:province":"QC",
    "wof:name":"Acl Quincaillerie Inc",
    "wof:placetype":"venue"
},
  "geometry": {"coordinates":[-73.6279754639,45.5391921997],"type":"Point"}
}