{
  "type": "Feature",
  "properties": {
    "addr:full":"30 Rue Saint-Mathieu Beloeil QC J3G 6N7",
    "addr:housenumber":"30",
    "addr:postcode":"j3g 6n7",
    "addr:street":"Rue Saint-Mathieu",
    "iso:country":"CA",
    "sg:address":"30 Rue Saint-Mathieu",
    "sg:city":"Beloeil",
    "sg:classifiers":[
        {
            "category":"Personal",
            "subcategory":"Beauty Salon",
            "type":"Services"
        }
    ],
    "sg:phone":"+1 450 464 1228",
    "sg:postcode":"J3G 6N7",
    "sg:province":"QC",
    "wof:name":"Salon Studio DE Coiffure Les",
    "wof:placetype":"venue"
},
  "geometry": {"coordinates":[-73.199654,45.570339],"type":"Point"}
}