{
  "type": "Feature",
  "properties": {
    "addr:full":"2660 Albert Way Abbotsford BC V2T 2R2",
    "addr:housenumber":"2660",
    "addr:postcode":"v2t 2r2",
    "addr:street":"Albert Way",
    "iso:country":"CA",
    "sg:address":"2660 Albert Way",
    "sg:city":"Abbotsford",
    "sg:classifiers":[
        {
            "category":"Wholesale",
            "subcategory":"Construction Materials",
            "type":"Manufacturing & Wholesale Goods"
        }
    ],
    "sg:phone":"+1 604 850 8708",
    "sg:postcode":"V2T 2R2",
    "sg:province":"BC",
    "sg:tags":[
        "fence"
    ],
    "wof:name":"B & R Metalworks Inc",
    "wof:placetype":"venue"
},
  "geometry": {"coordinates":[-122.34678599999999,49.05056],"type":"Point"}
}