{
  "type": "Feature",
  "properties": {
    "addr:full":"7471 Boul Wilfrid-Hamel Sainte-Foy QC G2G 1C2",
    "addr:housenumber":"7471",
    "addr:postcode":"g2g 1c2",
    "addr:street":"Boul Wilfrid-Hamel",
    "iso:country":"CA",
    "sg:address":"7471 Boul Wilfrid-Hamel",
    "sg:city":"Sainte-Foy",
    "sg:classifiers":[
        {
            "category":"Retail",
            "subcategory":"Auto Repair",
            "type":"Services"
        }
    ],
    "sg:phone":"+1 418 871 3257",
    "sg:postcode":"G2G 1C2",
    "sg:province":"QC",
    "sg:tags":[
        "repairing",
        "automobile"
    ],
    "wof:name":"Garage Michel & Daniel",
    "wof:placetype":"venue"
},
  "geometry": {"coordinates":[-71.372467,46.77673],"type":"Point"}
}