{
  "type": "Feature",
  "properties": {
    "iso:country":"CA",
    "sg:address":"304 11th St W",
    "sg:city":"Cornwall",
    "sg:classifiers":[
        {
            "category":"Home & Garden",
            "subcategory":"Building Materials",
            "type":"Retail Goods"
        }
    ],
    "sg:phone":"+1 613 933 2286",
    "sg:postcode":"K6J 3B2",
    "sg:province":"ON",
    "sg:tags":[
        "glass",
        "window",
        "plate"
    ],
    "wof:name":"Rolland A Paquette Ltd",
    "wof:placetype":"venue"
},
  "geometry": {"coordinates":[-74.74184417719999,45.0280761719],"type":"Point"}
}