{
  "type": "Feature",
  "properties": {
    "iso:country":"CA",
    "sg:address":"934 Rue Monseigneur-DE Laval",
    "sg:city":"Beloeil",
    "sg:classifiers":[
        {
            "category":"Shopping",
            "subcategory":"Gifts & Souvenirs",
            "type":"Retail Goods"
        }
    ],
    "sg:phone":"+1 450 446 5777",
    "sg:postcode":"J3G 4E7",
    "sg:province":"QC",
    "sg:tags":[
        "shop"
    ],
    "wof:name":"L'Antilope",
    "wof:placetype":"venue"
},
  "geometry": {"coordinates":[-73.203049,45.567131],"type":"Point"}
}