{
  "type": "Feature",
  "properties": {
    "addr:full":"934 Rue Monseigneur-DE Laval Beloeil QC J3G 4E7",
    "addr:housenumber":"934",
    "addr:postcode":"j3g 4e7",
    "addr:street":"Rue Monseigneur-De Laval",
    "iso:country":"CA",
    "sg:address":"934 Rue Monseigneur-DE Laval",
    "sg:city":"Beloeil",
    "sg:classifiers":[
        {
            "category":"Shopping",
            "subcategory":"Gifts & Souvenirs",
            "type":"Retail Goods"
        }
    ],
    "sg:phone":"+1 450 446 5777",
    "sg:postcode":"J3G 4E7",
    "sg:province":"QC",
    "sg:tags":[
        "shop"
    ],
    "wof:name":"L'Antilope",
    "wof:placetype":"venue"
},
  "geometry": {"coordinates":[-73.20304899999999,45.567131],"type":"Point"}
}