{
  "type": "Feature",
  "properties": {
    "addr:full":"5014 50th St Yellowknife NT X1A 2N3",
    "addr:housenumber":"5014",
    "addr:postcode":"x1a 2n3",
    "addr:street":"50Th St",
    "iso:country":"CA",
    "sg:address":"5014 50th St",
    "sg:city":"Yellowknife",
    "sg:classifiers":[
        {
            "category":"Shopping",
            "subcategory":"Clothing, Apparel, & Fashions",
            "type":"Retail Goods"
        }
    ],
    "sg:phone":"+1 867 873 5940",
    "sg:postcode":"X1A 2N3",
    "sg:province":"NT",
    "sg:tags":[
        "furnishing"
    ],
    "wof:name":"For Men Only",
    "wof:placetype":"venue"
},
  "geometry": {"coordinates":[-114.371368,62.453686],"type":"Point"}
}