{
  "type": "Feature",
  "properties": {
    "addr:full":"Whitecourt AB T7S 1N6",
    "addr:postcode":"t7s 1n6",
    "iso:country":"CA",
    "sg:city":"Whitecourt",
    "sg:classifiers":[
        {
            "category":"Shopping",
            "subcategory":"Clothing, Apparel, & Fashions",
            "type":"Retail Goods"
        }
    ],
    "sg:phone":"+1 780 778 4465",
    "sg:postcode":"T7S 1N6",
    "sg:province":"AB",
    "wof:name":"Warehouse One the Jean Store",
    "wof:placetype":"venue"
},
  "geometry": {"coordinates":[-115.682129,54.140415],"type":"Point"}
}