{
  "type": "Feature",
  "properties": {
    "addr:full":"3710 Main St Vancouver BC V5V 3N7",
    "addr:housenumber":"3710",
    "addr:postcode":"v5v 3n7",
    "addr:street":"Main St",
    "iso:country":"CA",
    "sg:address":"3710 Main St",
    "sg:city":"Vancouver",
    "sg:classifiers":[
        {
            "category":"Restaurant",
            "type":"Food & Drink"
        }
    ],
    "sg:phone":"+1 604 872 4872",
    "sg:postcode":"V5V 3N7",
    "sg:province":"BC",
    "wof:name":"Pho Thang Long",
    "wof:placetype":"venue"
},
  "geometry": {"coordinates":[-123.100769043,49.2519416809],"type":"Point"}
}