{
  "type": "Feature",
  "properties": {
    "iso:country":"CA",
    "sg:address":"101 Edward Ave",
    "sg:city":"Richmond Hill",
    "sg:classifiers":[
        {
            "category":"Professional",
            "subcategory":"Business Services",
            "type":"Services"
        }
    ],
    "sg:phone":"+1 905 884 9110",
    "sg:postcode":"L4C 5E5",
    "sg:province":"ON",
    "sg:tags":[
        "packaging"
    ],
    "wof:name":"Bright Ideas Custom Packaging",
    "wof:placetype":"venue"
},
  "geometry": {"coordinates":[-79.4274902344,43.8940925598],"type":"Point"}
}