{
  "type": "Feature",
  "properties": {
    "addr:full":"Powerview MB R0E 1P0",
    "addr:postcode":"r0e 1p0",
    "iso:country":"CA",
    "sg:city":"Powerview",
    "sg:classifiers":[
        {
            "category":"Home & Garden",
            "subcategory":"Furniture",
            "type":"Retail Goods"
        }
    ],
    "sg:phone":"+1 204 367 2460",
    "sg:postcode":"R0E 1P0",
    "sg:province":"MB",
    "wof:name":"Dave's Used Furniture Store",
    "wof:placetype":"venue"
},
  "geometry": {"coordinates":[-96.1982574463,50.5672912598],"type":"Point"}
}