{
  "type": "Feature",
  "properties": {
    "iso:country":"CA",
    "sg:address":"561 11 Rg",
    "sg:city":"Sainte-Francoise",
    "sg:classifiers":[
        {
            "category":"Organizations",
            "subcategory":"Religious Organization",
            "type":"Services"
        }
    ],
    "sg:phone":"+1 418 287 5921",
    "sg:postcode":"G0L 3B0",
    "sg:province":"QC",
    "sg:tags":[
        "church"
    ],
    "wof:name":"Presbytere Ste Francois",
    "wof:placetype":"venue"
},
  "geometry": {"coordinates":[-71.9983673096,46.4544639587],"type":"Point"}
}