{
  "type": "Feature",
  "properties": {
    "addr:full":"4125 Boul Des Forges Trois-Rivieres QC G8Y 1W1",
    "addr:housenumber":"4125",
    "addr:postcode":"g8y 1w1",
    "addr:street":"Boul Des Forges Trois-Rivieres",
    "iso:country":"CA",
    "sg:address":"4125 Boul Des Forges",
    "sg:city":"Trois-Rivieres",
    "sg:classifiers":[
        {
            "category":"Shopping",
            "subcategory":"Clothing, Apparel, & Fashions",
            "type":"Retail Goods"
        }
    ],
    "sg:phone":"+1 819 379 3011",
    "sg:postcode":"G8Y 1W1",
    "sg:province":"QC",
    "wof:name":"Suzy Shier",
    "wof:placetype":"venue"
},
  "geometry": {"coordinates":[-72.58625000000001,46.356396],"type":"Point"}
}