{
  "type": "Feature",
  "properties": {
    "iso:country":"CA",
    "sg:city":"Kamloops",
    "sg:classifiers":[
        {
            "category":"Shopping",
            "type":"Retail Goods"
        }
    ],
    "sg:phone":"+1 250 376 0018",
    "sg:postcode":"V2B 8A7",
    "sg:province":"BC",
    "sg:tags":[
        "trophy",
        "engraver",
        "medal",
        "award"
    ],
    "wof:name":"Winners Awards & More",
    "wof:placetype":"venue"
},
  "geometry": {"coordinates":[-120.37283325200001,50.705745697],"type":"Point"}
}