{
  "type": "Feature",
  "properties": {
    "addr:full":"396 Furby St Winnipeg MB R3B 2V5",
    "addr:housenumber":"396",
    "addr:postcode":"r3b 2v5",
    "addr:street":"Furby St",
    "iso:country":"CA",
    "sg:address":"396 Furby St",
    "sg:city":"Winnipeg",
    "sg:classifiers":[
        {
            "category":"Building & Trades",
            "subcategory":"Construction",
            "type":"Services"
        }
    ],
    "sg:phone":"+1 204 772 5041",
    "sg:postcode":"R3B 2V5",
    "sg:province":"MB",
    "sg:tags":[
        "concrete",
        "contractor",
        "general"
    ],
    "wof:name":"Forum Construction Svc Ltd",
    "wof:placetype":"venue"
},
  "geometry": {"coordinates":[-97.15772200000001,49.890533],"type":"Point"}
}