{
  "type": "Feature",
  "properties": {
    "addr:full":"2725 Belisle Dr Val Caron ON P3N 1B3",
    "addr:housenumber":"2725",
    "addr:postcode":"p3n 1b3",
    "addr:street":"Belisle Dr",
    "iso:country":"CA",
    "sg:address":"2725 Belisle Dr",
    "sg:city":"Val Caron",
    "sg:classifiers":[
        {
            "category":"Building & Trades",
            "subcategory":"Construction",
            "type":"Services"
        }
    ],
    "sg:phone":"+1 705 897 4971",
    "sg:postcode":"P3N 1B3",
    "sg:province":"ON",
    "sg:tags":[
        "demolition",
        "contractor"
    ],
    "wof:name":"Consbec Inc",
    "wof:placetype":"venue"
},
  "geometry": {"coordinates":[-81.02879299999999,46.602943],"type":"Point"}
}