{
  "type": "Feature",
  "properties": {
    "addr:full":"7 Bishop Ave North York ON M2M 4J4",
    "addr:housenumber":"7",
    "addr:postcode":"m2m 4j4",
    "addr:street":"Bishop Ave",
    "iso:country":"CA",
    "sg:address":"7 Bishop Ave",
    "sg:city":"North York",
    "sg:classifiers":[
        {
            "category":"Organizations",
            "subcategory":"Professional Association",
            "type":"Services"
        }
    ],
    "sg:phone":"+1 416 730 8350",
    "sg:postcode":"M2M 4J4",
    "sg:province":"ON",
    "wof:name":"Canadian Friends of Finland",
    "wof:placetype":"venue"
},
  "geometry": {"coordinates":[-79.4152374268,43.7816543579],"type":"Point"}
}