{
  "type": "Feature",
  "properties": {
    "addr:full":"550 Cornwall St Regina SK S4R 2H2",
    "addr:housenumber":"550",
    "addr:postcode":"s4r 2h2",
    "addr:street":"Cornwall St",
    "iso:country":"CA",
    "sg:address":"550 Cornwall St",
    "sg:city":"Regina",
    "sg:classifiers":[
        {
            "category":"Mining & Drilling",
            "type":"Manufacturing & Wholesale Goods"
        }
    ],
    "sg:phone":"+1 306 949 8700",
    "sg:postcode":"S4R 2H2",
    "sg:province":"SK",
    "sg:tags":[
        "jacking",
        "concrete",
        "contractor",
        "mud"
    ],
    "wof:name":"Slab Master",
    "wof:placetype":"venue"
},
  "geometry": {"coordinates":[-104.612487793,50.470249176],"type":"Point"}
}