{
  "type": "Feature",
  "properties": {
    "addr:full":"Brampton ON L6W 3J5",
    "addr:postcode":"l6w 3j5",
    "iso:country":"CA",
    "sg:city":"Brampton",
    "sg:classifiers":[
        {
            "category":"Manufacturing",
            "subcategory":"Tools & Machinery",
            "type":"Manufacturing & Wholesale Goods"
        }
    ],
    "sg:phone":"+1 905 459 1865",
    "sg:postcode":"L6W 3J5",
    "sg:province":"ON",
    "sg:tags":[
        "die",
        "maker"
    ],
    "wof:name":"G B Mutch Precision Stamping",
    "wof:placetype":"venue"
},
  "geometry": {"coordinates":[-79.733841,43.695419],"type":"Point"}
}