{
  "type": "Feature",
  "properties": {
    "addr:full":"100 Arden St Moncton NB E1C 4B7",
    "addr:housenumber":"100",
    "addr:postcode":"e1c 4b7",
    "addr:street":"Arden St",
    "iso:country":"CA",
    "sg:address":"100 Arden St",
    "sg:city":"Moncton",
    "sg:classifiers":[
        {
            "category":"Health Services",
            "subcategory":"Doctor",
            "type":"Services"
        }
    ],
    "sg:phone":"+1 506 383 2992",
    "sg:postcode":"E1C 4B7",
    "sg:province":"NB",
    "sg:tags":[
        "physician",
        "surgeon"
    ],
    "wof:name":"Laser Care Dr Warren Giberson",
    "wof:placetype":"venue"
},
  "geometry": {"coordinates":[-64.805008,46.106339],"type":"Point"}
}