{
  "type": "Feature",
  "properties": {
    "addr:full":"2495 Av Dollard Lasalle QC H8N 1S2",
    "addr:housenumber":"2495",
    "addr:postcode":"h8n 1s2",
    "addr:street":"Av Dollard",
    "iso:country":"CA",
    "sg:address":"2495 Av Dollard",
    "sg:city":"Lasalle",
    "sg:classifiers":[
        {
            "category":"Building & Trades",
            "subcategory":"Construction",
            "type":"Services"
        }
    ],
    "sg:phone":"+1 514 365 3233",
    "sg:postcode":"H8N 1S2",
    "sg:province":"QC",
    "sg:tags":[
        "contractor",
        "general"
    ],
    "wof:name":"Constructions Gaetani Inc",
    "wof:placetype":"venue"
},
  "geometry": {"coordinates":[-73.638901,45.434467],"type":"Point"}
}