{
  "type": "Feature",
  "properties": {
    "addr:full":"912 Vancouver St Victoria BC V8V 3V7",
    "addr:housenumber":"912",
    "addr:postcode":"v8v 3v7",
    "addr:street":"Vancouver St",
    "iso:country":"CA",
    "sg:address":"912 Vancouver St",
    "sg:city":"Victoria",
    "sg:classifiers":[
        {
            "category":"Education",
            "subcategory":"School",
            "type":"Public Place"
        }
    ],
    "sg:phone":"+1 250 383 5125",
    "sg:postcode":"V8V 3V7",
    "sg:province":"BC",
    "sg:tags":[
        "church"
    ],
    "wof:name":"Christ Church Cathedral School",
    "wof:placetype":"venue"
},
  "geometry": {"coordinates":[-123.357567,48.421776],"type":"Point"}
}