{
  "type": "Feature",
  "properties": {
    "addr:full":"100 Westmore Dr Etobicoke ON M9V 5C3",
    "addr:housenumber":"100",
    "addr:postcode":"m9v 5c3",
    "addr:street":"Westmore Dr",
    "iso:country":"CA",
    "sg:address":"100 Westmore Dr",
    "sg:city":"Etobicoke",
    "sg:classifiers":[
        {
            "category":"Wholesale",
            "subcategory":"Apparel",
            "type":"Manufacturing & Wholesale Goods"
        }
    ],
    "sg:phone":"+1 416 749 8737",
    "sg:postcode":"M9V 5C3",
    "sg:province":"ON",
    "sg:tags":[
        "sportswear"
    ],
    "wof:name":"Morina Sports Screening",
    "wof:placetype":"venue"
},
  "geometry": {"coordinates":[-79.60219600000001,43.736897],"type":"Point"}
}