{
  "type": "Feature",
  "properties": {
    "iso:country":"CA",
    "sg:city":"Winkler",
    "sg:classifiers":[
        {
            "category":"Wholesale",
            "subcategory":"Electrical",
            "type":"Manufacturing & Wholesale Goods"
        }
    ],
    "sg:phone":"+1 204 325 6464",
    "sg:postcode":"R6W 4B9",
    "sg:province":"MB",
    "sg:tags":[
        "equipment",
        "electric",
        "supply"
    ],
    "wof:name":"Eecol Electric Ltd",
    "wof:placetype":"venue"
},
  "geometry": {"coordinates":[-97.9373245239,49.1869544983],"type":"Point"}
}