{
  "type": "Feature",
  "properties": {
    "addr:full":"1315 Rue Gay-Lussac Boucherville QC J4B 7K1",
    "addr:housenumber":"1315",
    "addr:postcode":"j4b 7k1",
    "addr:street":"Rue Gay-Lussac",
    "iso:country":"CA",
    "sg:address":"1315 Rue Gay-Lussac",
    "sg:city":"Boucherville",
    "sg:classifiers":[
        {
            "category":"Shopping",
            "type":"Retail Goods"
        }
    ],
    "sg:phone":"+1 450 449 1224",
    "sg:postcode":"J4B 7K1",
    "sg:province":"QC",
    "sg:tags":[
        "equipment",
        "wine",
        "supply"
    ],
    "wof:name":"Produits Paklab Products Inc",
    "wof:placetype":"venue"
},
  "geometry": {"coordinates":[-73.428963,45.571541],"type":"Point"}
}