{
  "type": "Feature",
  "properties": {
    "addr:full":"Calgary AB T2P 3H5",
    "addr:postcode":"t2p 3h5",
    "iso:country":"CA",
    "sg:city":"Calgary",
    "sg:classifiers":[
        {
            "category":"Mining & Drilling",
            "type":"Manufacturing & Wholesale Goods"
        }
    ],
    "sg:phone":"+1 403 265 0088",
    "sg:postcode":"T2P 3H5",
    "sg:province":"AB",
    "sg:tags":[
        "development",
        "gas",
        "oil",
        "exploration"
    ],
    "wof:name":"Velvet Exploration Ltd",
    "wof:placetype":"venue"
},
  "geometry": {"coordinates":[-114.073975,51.048546],"type":"Point"}
}