{
  "type": "Feature",
  "properties": {
    "addr:full":"1240 Rue Lachaine Laval QC H7C 2N7",
    "addr:housenumber":"1240",
    "addr:postcode":"h7c 2n7",
    "addr:street":"Rue Lachaine",
    "iso:country":"CA",
    "sg:address":"1240 Rue Lachaine",
    "sg:city":"Laval",
    "sg:classifiers":[
        {
            "category":"Manufacturing",
            "subcategory":"Signs",
            "type":"Manufacturing & Wholesale Goods"
        }
    ],
    "sg:phone":"+1 450 664 2761",
    "sg:postcode":"H7C 2N7",
    "sg:province":"QC",
    "wof:name":"Enseignes Jacques Villeneuve",
    "wof:placetype":"venue"
},
  "geometry": {"coordinates":[-73.65804290769999,45.6168136597],"type":"Point"}
}