{
  "type": "Feature",
  "properties": {
    "addr:full":"230 Rue Brebeuf Beloeil QC J3G 5P3",
    "addr:housenumber":"230",
    "addr:postcode":"j3g 5p3",
    "addr:street":"Rue Brebeuf",
    "iso:country":"CA",
    "sg:address":"230 Rue Brebeuf",
    "sg:city":"Beloeil",
    "sg:classifiers":[
        {
            "category":"Government",
            "subcategory":"Office",
            "type":"Public Place"
        }
    ],
    "sg:phone":"+1 450 467 0840",
    "sg:postcode":"J3G 5P3",
    "sg:province":"QC",
    "wof:name":"Quebec Mandataires",
    "wof:placetype":"venue"
},
  "geometry": {"coordinates":[-73.2072525024,45.564666748],"type":"Point"}
}