{
  "type": "Feature",
  "properties": {
    "addr:full":"15 Pullman Crt Scarborough ON M1X 1E4",
    "addr:housenumber":"15",
    "addr:postcode":"m1x 1e4",
    "addr:street":"Pullman Crt",
    "iso:country":"CA",
    "sg:address":"15 Pullman Crt",
    "sg:city":"Scarborough",
    "sg:classifiers":[
        {
            "category":"Building & Trades",
            "subcategory":"Construction",
            "type":"Services"
        }
    ],
    "sg:phone":"+1 416 321 2275",
    "sg:postcode":"M1X 1E4",
    "sg:province":"ON",
    "sg:tags":[
        "tile",
        "dealer"
    ],
    "wof:name":"Douglas Flooring Ltd",
    "wof:placetype":"venue"
},
  "geometry": {"coordinates":[-79.237892,43.820713],"type":"Point"}
}