{
  "type": "Feature",
  "properties": {
    "addr:full":"302 West St Herschel SK S0L 1L0",
    "addr:housenumber":"302",
    "addr:postcode":"s0l 1l0",
    "addr:street":"West St",
    "iso:country":"CA",
    "sg:address":"302 West St",
    "sg:city":"Herschel",
    "sg:classifiers":[
        {
            "category":"Manufacturing",
            "subcategory":"Apparel",
            "type":"Manufacturing & Wholesale Goods"
        }
    ],
    "sg:phone":"+1 306 377 4404",
    "sg:postcode":"S0L 1L0",
    "sg:province":"SK",
    "sg:tags":[
        "clothing"
    ],
    "wof:name":"Verlor Fab-Tech",
    "wof:placetype":"venue"
},
  "geometry": {"coordinates":[-108.35534699999999,51.637581],"type":"Point"}
}