{
  "type": "Feature",
  "properties": {
    "iso:country":"CA",
    "sg:address":"7040 68 Ave NW",
    "sg:city":"Edmonton",
    "sg:classifiers":[
        {
            "category":"Manufacturing",
            "subcategory":"Paper Products",
            "type":"Manufacturing & Wholesale Goods"
        }
    ],
    "sg:phone":"+1 780 465 0637",
    "sg:postcode":"T6B 3C5",
    "sg:province":"AB",
    "sg:tags":[
        "janitor"
    ],
    "wof:name":"C F Rotex",
    "wof:placetype":"venue"
},
  "geometry": {"coordinates":[-113.435188294,53.5051651001],"type":"Point"}
}