{
  "type": "Feature",
  "properties": {
    "addr:full":"1403 Central Ave Prince Albert SK S6V 7J4",
    "addr:housenumber":"1403",
    "addr:postcode":"s6v 7j4",
    "addr:street":"Central Ave",
    "iso:country":"CA",
    "sg:address":"1403 Central Ave",
    "sg:city":"Prince Albert",
    "sg:classifiers":[
        {
            "category":"Shopping",
            "subcategory":"Gifts & Souvenirs",
            "type":"Retail Goods"
        }
    ],
    "sg:phone":"+1 306 922 6336",
    "sg:postcode":"S6V 7J4",
    "sg:province":"SK",
    "sg:tags":[
        "cards",
        "greeting"
    ],
    "wof:name":"Carlton Cards",
    "wof:placetype":"venue"
},
  "geometry": {"coordinates":[-105.754501,53.199947],"type":"Point"}
}