{
  "type": "Feature",
  "properties": {
    "addr:full":"36413 Dawson Rd Abbotsford BC V3G 2L1",
    "addr:housenumber":"36413",
    "addr:postcode":"v3g 2l1",
    "addr:street":"Dawson Rd",
    "iso:country":"CA",
    "sg:address":"36413 Dawson Rd",
    "sg:city":"Abbotsford",
    "sg:classifiers":[
        {
            "category":"Building & Trades",
            "subcategory":"Construction",
            "type":"Services"
        }
    ],
    "sg:phone":"+1 604 852 4221",
    "sg:postcode":"V3G 2L1",
    "sg:province":"BC",
    "sg:tags":[
        "general",
        "contractor"
    ],
    "wof:name":"D & M Bricklaying Ltd",
    "wof:placetype":"venue"
},
  "geometry": {"coordinates":[-122.215065,49.089542],"type":"Point"}
}