{
  "type": "Feature",
  "properties": {
    "addr:full":"105 Main St W Atikokan ON P0T 1C0",
    "addr:housenumber":"105",
    "addr:postcode":"p0t 1c0",
    "addr:street":"Main St W Atikokan",
    "iso:country":"CA",
    "sg:address":"105 Main St W",
    "sg:city":"Atikokan",
    "sg:classifiers":[
        {
            "category":"Shopping",
            "subcategory":"Gifts & Souvenirs",
            "type":"Retail Goods"
        }
    ],
    "sg:phone":"+1 807 597 4488",
    "sg:postcode":"P0T 1C0",
    "sg:province":"ON",
    "sg:tags":[
        "shop"
    ],
    "wof:name":"Wild Wood Country",
    "wof:placetype":"venue"
},
  "geometry": {"coordinates":[-91.62202499999999,48.757393],"type":"Point"}
}