{
  "type": "Feature",
  "properties": {
    "addr:full":"1333 Sheppard Ave E #300 North York ON M2J 1V1",
    "addr:housenumber":"1333",
    "addr:postcode":"m2j 1v1",
    "addr:street":"Sheppard Ave E # 300",
    "iso:country":"CA",
    "sg:address":"1333 Sheppard Ave E #300",
    "sg:city":"North York",
    "sg:classifiers":[
        {
            "category":"Health Services",
            "subcategory":"Doctor",
            "type":"Services"
        }
    ],
    "sg:phone":"+1 416 494 7424",
    "sg:postcode":"M2J 1V1",
    "sg:province":"ON",
    "sg:tags":[
        "physician",
        "surgeon"
    ],
    "wof:name":"Reicher, Agnes E MD",
    "wof:placetype":"venue"
},
  "geometry": {"coordinates":[-79.3622894287,43.7717437744],"type":"Point"}
}