{
  "type": "Feature",
  "properties": {
    "addr:full":"72 Rue Chouinard Pointe-Lebel QC G0H 1N0",
    "addr:housenumber":"72",
    "addr:postcode":"g0h 1n0",
    "addr:street":"Rue Chouinard",
    "iso:country":"CA",
    "sg:address":"72 Rue Chouinard",
    "sg:city":"Pointe-Lebel",
    "sg:classifiers":[
        {
            "category":"Travel",
            "subcategory":"Campground",
            "type":"Entertainment"
        }
    ],
    "sg:phone":"+1 418 589 6576",
    "sg:postcode":"G0H 1N0",
    "sg:province":"QC",
    "wof:name":"Camping DE LA Mer",
    "wof:placetype":"venue"
},
  "geometry": {"coordinates":[-68.18486799999999,49.155502],"type":"Point"}
}