{
  "type": "Feature",
  "properties": {
    "addr:full":"Sioux Lookout ON P8T 1A8",
    "addr:postcode":"p8t 1a8",
    "iso:country":"CA",
    "sg:city":"Sioux Lookout",
    "sg:classifiers":[
        {
            "category":"Organizations",
            "subcategory":"Non-profit Organization",
            "type":"Services"
        }
    ],
    "sg:phone":"+1 807 737 4506",
    "sg:postcode":"P8T 1A8",
    "sg:province":"ON",
    "sg:tags":[
        "addiction",
        "treatment",
        "center"
    ],
    "wof:name":"Community Counselling",
    "wof:placetype":"venue"
},
  "geometry": {"coordinates":[-91.91759500000001,50.098946],"type":"Point"}
}