{
  "type": "Feature",
  "properties": {
    "addr:full":"3350 Fairview St # 199 Burlington ON L7N 3L5",
    "addr:housenumber":"3350",
    "addr:postcode":"l7n 3l5",
    "addr:street":"Fairview St # 199",
    "iso:country":"CA",
    "sg:address":"3350 Fairview St # 199",
    "sg:city":"Burlington",
    "sg:classifiers":[
        {
            "category":"Wholesale",
            "subcategory":"Home Furnishings",
            "type":"Manufacturing & Wholesale Goods"
        }
    ],
    "sg:phone":"+1 905 333 1322",
    "sg:postcode":"L7N 3L5",
    "sg:province":"ON",
    "sg:tags":[
        "closet",
        "accessory"
    ],
    "wof:name":"Space Age Shelving",
    "wof:placetype":"venue"
},
  "geometry": {"coordinates":[-79.7853546143,43.3542022705],"type":"Point"}
}