{
  "type": "Feature",
  "properties": {
    "addr:full":"Vancouver BC V6H 4B4",
    "addr:postcode":"v6h 4b4",
    "iso:country":"CA",
    "sg:city":"Vancouver",
    "sg:classifiers":[
        {
            "category":"Professional",
            "subcategory":"Management & Consulting",
            "type":"Services"
        }
    ],
    "sg:phone":"+1 604 731 9663",
    "sg:postcode":"V6H 4B4",
    "sg:province":"BC",
    "sg:tags":[
        "marketing",
        "consultant"
    ],
    "wof:name":"Cosmos Pacific Investment",
    "wof:placetype":"venue"
},
  "geometry": {"coordinates":[-123.138412,49.262352],"type":"Point"}
}