{
  "type": "Feature",
  "properties": {
    "addr:full":"1231 Guelph Line Burlington ON L7P 2T1",
    "addr:housenumber":"1231",
    "addr:postcode":"l7p 2t1",
    "addr:street":"Guelph Line",
    "iso:country":"CA",
    "sg:address":"1231 Guelph Line",
    "sg:city":"Burlington",
    "sg:classifiers":[
        {
            "category":"Retail",
            "subcategory":"Veterinary Services",
            "type":"Services"
        }
    ],
    "sg:phone":"+1 905 335 3515",
    "sg:postcode":"L7P 2T1",
    "sg:province":"ON",
    "sg:tags":[
        "veterinarian"
    ],
    "wof:name":"Burlington Animal Hospital",
    "wof:placetype":"venue"
},
  "geometry": {"coordinates":[-79.81196594239999,43.3579826355],"type":"Point"}
}