{
  "type": "Feature",
  "properties": {
    "iso:country":"CA",
    "sg:address":"317 Rue Dagenais",
    "sg:city":"Le Gardeur",
    "sg:classifiers":[
        {
            "category":"Building & Trades",
            "subcategory":"Construction",
            "type":"Services"
        }
    ],
    "sg:phone":"+1 450 581 4924",
    "sg:postcode":"J5Z 4Y9",
    "sg:province":"QC",
    "sg:tags":[
        "roofing",
        "contractor"
    ],
    "wof:name":"Toiture Brousseau Inc",
    "wof:placetype":"venue"
},
  "geometry": {"coordinates":[-73.474007,45.77037],"type":"Point"}
}