{
  "type": "Feature",
  "properties": {
    "addr:full":"2654 Norris Rd Kelowna BC V1X 7L9",
    "addr:housenumber":"2654",
    "addr:postcode":"v1x 7l9",
    "addr:street":"Norris Rd",
    "iso:country":"CA",
    "sg:address":"2654 Norris Rd",
    "sg:city":"Kelowna",
    "sg:classifiers":[
        {
            "category":"Building & Trades",
            "subcategory":"Construction",
            "type":"Services"
        }
    ],
    "sg:phone":"+1 250 765 1411",
    "sg:postcode":"V1X 7L9",
    "sg:province":"BC",
    "sg:tags":[
        "contractor",
        "road",
        "general"
    ],
    "wof:name":"Geddes Construction Ltd",
    "wof:placetype":"venue"
},
  "geometry": {"coordinates":[-119.381362915,49.9236831665],"type":"Point"}
}