{
  "type": "Feature",
  "properties": {
    "iso:country":"CA",
    "sg:address":"198 Walnut Ave",
    "sg:city":"Toronto",
    "sg:classifiers":[
        {
            "category":"Professional",
            "subcategory":"Management & Consulting",
            "type":"Services"
        }
    ],
    "sg:phone":"+1 416 536 9307",
    "sg:postcode":"M6J 2N6",
    "sg:province":"ON",
    "sg:tags":[
        "marketing",
        "consultant"
    ],
    "wof:name":"Ground Control Marketing",
    "wof:placetype":"venue"
},
  "geometry": {"coordinates":[-79.411315918,43.6454963684],"type":"Point"}
}