{
  "type": "Feature",
  "properties": {
    "addr:full":"55 Yonge St #800 Toronto ON M5E 1J4",
    "addr:housenumber":"55",
    "addr:postcode":"m5e 1j4",
    "addr:street":"Yonge St # 800",
    "iso:country":"CA",
    "sg:address":"55 Yonge St #800",
    "sg:city":"Toronto",
    "sg:classifiers":[
        {
            "category":"Wholesale",
            "subcategory":"Petroleum",
            "type":"Manufacturing & Wholesale Goods"
        }
    ],
    "sg:phone":"+1 416 869 2111",
    "sg:postcode":"M5E 1J4",
    "sg:province":"ON",
    "sg:tags":[
        "pipe",
        "line",
        "company"
    ],
    "wof:name":"Trans Canada Pipe Lines Ltd",
    "wof:placetype":"venue"
},
  "geometry": {"coordinates":[-79.37729644780001,43.6482124329],"type":"Point"}
}