{
  "type": "Feature",
  "properties": {
    "addr:full":"1020 Boul Hamel Saint-Felicien QC G8K 1X9",
    "addr:housenumber":"1020",
    "addr:postcode":"g8k 1x9",
    "addr:street":"Boul Hamel Saint-Felicien",
    "iso:country":"CA",
    "sg:address":"1020 Boul Hamel",
    "sg:city":"Saint-Felicien",
    "sg:classifiers":[
        {
            "category":"Retail",
            "subcategory":"Auto Rental",
            "type":"Services"
        }
    ],
    "sg:phone":"+1 418 679 8445",
    "sg:postcode":"G8K 1X9",
    "sg:province":"QC",
    "sg:tags":[
        "renting",
        "automobile"
    ],
    "wof:name":"Location Sauvageau",
    "wof:placetype":"venue"
},
  "geometry": {"coordinates":[-72.45129394529999,48.6458702087],"type":"Point"}
}