{
  "type": "Feature",
  "properties": {
    "addr:full":"1081 Canada Ave Duncan BC V9L 1V2",
    "addr:housenumber":"1081",
    "addr:postcode":"v9l 1v2",
    "addr:street":"Canada Ave",
    "iso:country":"CA",
    "sg:address":"1081 Canada Ave",
    "sg:city":"Duncan",
    "sg:classifiers":[
        {
            "category":"Professional",
            "subcategory":"Engineering",
            "type":"Services"
        }
    ],
    "sg:phone":"+1 250 746 5545",
    "sg:postcode":"V9L 1V2",
    "sg:province":"BC",
    "sg:tags":[
        "environmental",
        "ecological"
    ],
    "wof:name":"Madrone Environmental Svc Ltd",
    "wof:placetype":"venue"
},
  "geometry": {"coordinates":[-123.709091,48.785488],"type":"Point"}
}