{
  "type": "Feature",
  "properties": {
    "iso:country":"CA",
    "sg:address":"497 Victoria St E",
    "sg:city":"Alliston",
    "sg:classifiers":[
        {
            "category":"Travel",
            "subcategory":"Hotels & Motels",
            "type":"Entertainment"
        }
    ],
    "sg:phone":"+1 705 435 4381",
    "sg:postcode":"L9R 1J8",
    "sg:province":"ON",
    "wof:name":"Red Pine Motor Inn",
    "wof:placetype":"venue"
},
  "geometry": {"coordinates":[-79.84417,44.15913],"type":"Point"}
}