{
  "type": "Feature",
  "properties": {
    "addr:full":"Surrey BC V4A 4N7",
    "addr:postcode":"v4a 4n7",
    "iso:country":"CA",
    "sg:city":"Surrey",
    "sg:classifiers":[
        {
            "category":"Professional",
            "subcategory":"Lawyer & Legal Services",
            "type":"Services"
        }
    ],
    "sg:phone":"+1 604 531 1041",
    "sg:postcode":"V4A 4N7",
    "sg:province":"BC",
    "sg:tags":[
        "attorney"
    ],
    "wof:name":"Green, Ross Hart",
    "wof:placetype":"venue"
},
  "geometry": {"coordinates":[-122.801376,49.040169],"type":"Point"}
}