{
  "type": "Feature",
  "properties": {
    "addr:full":"Penetanguishene ON L9M 1M2",
    "addr:postcode":"l9m 1m2",
    "iso:country":"CA",
    "sg:city":"Penetanguishene",
    "sg:classifiers":[
        {
            "category":"Real Estate",
            "subcategory":"Real Estate Operator",
            "type":"Services"
        }
    ],
    "sg:phone":"+1 705 549 4641",
    "sg:postcode":"L9M 1M2",
    "sg:province":"ON",
    "sg:tags":[
        "mall",
        "shopping",
        "center"
    ],
    "wof:name":"Village Square Mall",
    "wof:placetype":"venue"
},
  "geometry": {"coordinates":[-79.933044,44.7673],"type":"Point"}
}