{
  "type": "Feature",
  "properties": {
    "addr:full":"1099 Rue Daillon Baie-Comeau QC G5C 2S5",
    "addr:housenumber":"1099",
    "addr:postcode":"g5c 2s5",
    "addr:street":"Rue Daillon",
    "iso:country":"CA",
    "sg:address":"1099 Rue Daillon",
    "sg:city":"Baie-Comeau",
    "sg:classifiers":[
        {
            "category":"Building & Trades",
            "subcategory":"Cleaning & Sanitation",
            "type":"Services"
        }
    ],
    "sg:phone":"+1 418 589 2646",
    "sg:postcode":"G5C 2S5",
    "sg:province":"QC",
    "sg:tags":[
        "fireplace",
        "chimney"
    ],
    "wof:name":"Entreprise MB",
    "wof:placetype":"venue"
},
  "geometry": {"coordinates":[-68.30774700000001,49.190002],"type":"Point"}
}