{
  "type": "Feature",
  "properties": {
    "iso:country":"CA",
    "sg:address":"Yellowhead Highway 16 W",
    "sg:city":"Mcbride",
    "sg:classifiers":[
        {
            "category":"Restaurant",
            "type":"Food & Drink"
        }
    ],
    "sg:phone":"+1 250 569 0007",
    "sg:postcode":"V0J 2E0",
    "sg:province":"BC",
    "wof:name":"Sun Valley Restaurant",
    "wof:placetype":"venue"
},
  "geometry": {"coordinates":[-120.171646118,53.3074874878],"type":"Point"}
}