{
  "type": "Feature",
  "properties": {
    "addr:full":"Winnipeg MB R3C 0E2",
    "addr:postcode":"r3c 0e2",
    "iso:country":"CA",
    "sg:city":"Winnipeg",
    "sg:classifiers":[
        {
            "category":"Shopping",
            "subcategory":"Clothing, Apparel, & Fashions",
            "type":"Retail Goods"
        }
    ],
    "sg:phone":"+1 204 943 9177",
    "sg:postcode":"R3C 0E2",
    "sg:province":"MB",
    "sg:tags":[
        "breast",
        "artificial",
        "brassiere"
    ],
    "wof:name":"Allure By Ruth Inc",
    "wof:placetype":"venue"
},
  "geometry": {"coordinates":[-97.148788,49.891483],"type":"Point"}
}