{
  "type": "Feature",
  "properties": {
    "addr:full":"20 Carden St Guelph ON N1H 3A2",
    "addr:housenumber":"20",
    "addr:postcode":"n1h 3a2",
    "addr:street":"Carden St",
    "iso:country":"CA",
    "sg:address":"20 Carden St",
    "sg:city":"Guelph",
    "sg:classifiers":[
        {
            "category":"Shopping",
            "subcategory":"Musical Instruments",
            "type":"Retail Goods"
        }
    ],
    "sg:phone":"+1 519 836 3199",
    "sg:postcode":"N1H 3A2",
    "sg:province":"ON",
    "wof:name":"Guelph Music",
    "wof:placetype":"venue"
},
  "geometry": {"coordinates":[-80.24897,43.543873],"type":"Point"}
}