{
  "type": "Feature",
  "properties": {
    "addr:full":"859 Westminster Ave Winnipeg MB R3G 1B1",
    "addr:housenumber":"859",
    "addr:postcode":"r3g 1b1",
    "addr:street":"Westminster Ave",
    "iso:country":"CA",
    "sg:address":"859 Westminster Ave",
    "sg:city":"Winnipeg",
    "sg:classifiers":[
        {
            "category":"Food & Beverages",
            "subcategory":"Bakery",
            "type":"Retail Goods"
        }
    ],
    "sg:phone":"+1 204 783 5097",
    "sg:postcode":"R3G 1B1",
    "sg:province":"MB",
    "sg:tags":[
        "baker"
    ],
    "wof:name":"Tall Grass Prairie Bread CO",
    "wof:placetype":"venue"
},
  "geometry": {"coordinates":[-97.168755,49.88171],"type":"Point"}
}