{
  "type": "Feature",
  "properties": {
    "iso:country":"CA",
    "sg:address":"536 Rue Lafontaine",
    "sg:city":"Riviere-Du-Loup",
    "sg:classifiers":[
        {
            "category":"Shopping",
            "subcategory":"Tobacco",
            "type":"Retail Goods"
        }
    ],
    "sg:phone":"+1 418 862 2574",
    "sg:postcode":"G5R 3C4",
    "sg:province":"QC",
    "sg:tags":[
        "cigarette",
        "cigar",
        "dealer"
    ],
    "wof:name":"G D Nouvelles",
    "wof:placetype":"venue"
},
  "geometry": {"coordinates":[-69.53020477290001,47.8275222778],"type":"Point"}
}