{
  "type": "Feature",
  "properties": {
    "addr:full":"10256 154 St Surrey BC V3R 5Y7",
    "addr:housenumber":"10256",
    "addr:postcode":"v3r 5y7",
    "addr:street":"154 St",
    "iso:country":"CA",
    "sg:address":"10256 154 St",
    "sg:city":"Surrey",
    "sg:classifiers":[
        {
            "category":"Health Services",
            "subcategory":"Clinic",
            "type":"Services"
        }
    ],
    "sg:phone":"+1 604 583 1017",
    "sg:postcode":"V3R 5Y7",
    "sg:province":"BC",
    "sg:tags":[
        "childbirth",
        "education"
    ],
    "wof:name":"Healthiest Babies Possible",
    "wof:placetype":"venue"
},
  "geometry": {"coordinates":[-122.795151,49.188297],"type":"Point"}
}