{
  "type": "Feature",
  "properties": {
    "addr:full":"North York ON M2M 4J5",
    "addr:postcode":"m2m 4j5",
    "iso:country":"CA",
    "sg:city":"North York",
    "sg:classifiers":[
        {
            "category":"Health Services",
            "subcategory":"Doctor",
            "type":"Services"
        }
    ],
    "sg:phone":"+1 416 229 4179",
    "sg:postcode":"M2M 4J5",
    "sg:province":"ON",
    "sg:tags":[
        "physician",
        "surgeon"
    ],
    "wof:name":"Schiffer, L MD",
    "wof:placetype":"venue"
},
  "geometry": {"coordinates":[-79.393387,43.790325],"type":"Point"}
}