{
  "type": "Feature",
  "properties": {
    "addr:full":"8 Rue Greenlay N Windsor QC J1S 2K2",
    "addr:housenumber":"8",
    "addr:postcode":"j1s 2k2",
    "addr:street":"Rue Greenlay N",
    "iso:country":"CA",
    "sg:address":"8 Rue Greenlay N",
    "sg:city":"Windsor",
    "sg:classifiers":[
        {
            "category":"Home & Garden",
            "subcategory":"Household Appliances",
            "type":"Retail Goods"
        }
    ],
    "sg:phone":"+1 819 820 9340",
    "sg:postcode":"J1S 2K2",
    "sg:province":"QC",
    "sg:tags":[
        "machine",
        "sewing"
    ],
    "wof:name":"Machines A Coudre Y Gillis",
    "wof:placetype":"venue"
},
  "geometry": {"coordinates":[-72.01095581049999,45.5678863525],"type":"Point"}
}