{
  "type": "Feature",
  "properties": {
    "addr:full":"4046 78 St Cres Red Deer AB T4P 3E3",
    "addr:housenumber":"4046",
    "addr:postcode":"t4p 3e3",
    "addr:street":"78 St",
    "iso:country":"CA",
    "sg:address":"4046 78 St Cres",
    "sg:city":"Red Deer",
    "sg:classifiers":[
        {
            "category":"Mining & Drilling",
            "type":"Manufacturing & Wholesale Goods"
        }
    ],
    "sg:phone":"+1 403 342 4884",
    "sg:postcode":"T4P 3E3",
    "sg:province":"AB",
    "sg:tags":[
        "equipment",
        "field",
        "oil",
        "well",
        "supply"
    ],
    "wof:name":"Rialta Supply Ltd",
    "wof:placetype":"venue"
},
  "geometry": {"coordinates":[-113.817436,52.262302],"type":"Point"}
}