{
  "type": "Feature",
  "properties": {
    "addr:full":"207 Caversham Ave Cadogan AB T0B 0T0",
    "addr:housenumber":"207",
    "addr:postcode":"t0b 0t0",
    "addr:street":"Caversham Ave",
    "iso:country":"CA",
    "sg:address":"207 Caversham Ave",
    "sg:city":"Cadogan",
    "sg:classifiers":[
        {
            "category":"Retail",
            "subcategory":"Auto Repair",
            "type":"Services"
        }
    ],
    "sg:phone":"+1 780 753 6546",
    "sg:postcode":"T0B 0T0",
    "sg:province":"AB",
    "sg:tags":[
        "repairing",
        "automobile"
    ],
    "wof:name":"K & B Svc",
    "wof:placetype":"venue"
},
  "geometry": {"coordinates":[-110.45017199999999,52.319698],"type":"Point"}
}