{
  "type": "Feature",
  "properties": {
    "addr:full":"7 Rue Fournier Saint-Quentin NB E8A 1M9",
    "addr:housenumber":"7",
    "addr:postcode":"e8a 1m9",
    "addr:street":"Rue Fournier",
    "iso:country":"CA",
    "sg:address":"7 Rue Fournier",
    "sg:city":"Saint-Quentin",
    "sg:classifiers":[
        {
            "category":"Real Estate",
            "subcategory":"Real Estate Agent",
            "type":"Services"
        }
    ],
    "sg:phone":"+1 506 235 2688",
    "sg:postcode":"E8A 1M9",
    "sg:province":"NB",
    "sg:tags":[
        "agency",
        "rental"
    ],
    "wof:name":"Leblanc Rentals",
    "wof:placetype":"venue"
},
  "geometry": {"coordinates":[-67.39247899999999,47.521236],"type":"Point"}
}