{
  "type": "Feature",
  "properties": {
    "addr:full":"325 Boul Chomedey Laval QC H7V 3S7",
    "addr:housenumber":"325",
    "addr:postcode":"h7v 3s7",
    "addr:street":"Boul Chomedey",
    "iso:country":"CA",
    "sg:address":"325 Boul Chomedey",
    "sg:city":"Laval",
    "sg:classifiers":[
        {
            "category":"Utilities",
            "subcategory":"Fuel Oil & Lpg",
            "type":"Services"
        }
    ],
    "sg:phone":"+1 450 681 7531",
    "sg:postcode":"H7V 3S7",
    "sg:province":"QC",
    "wof:name":"Petroles Bertrand",
    "wof:placetype":"venue"
},
  "geometry": {"coordinates":[-73.73393249510001,45.539150238],"type":"Point"}
}