{
  "type": "Feature",
  "properties": {
    "addr:full":"407 Railway St Kipling SK S0G 2S0",
    "addr:housenumber":"407",
    "addr:postcode":"s0g 2s0",
    "addr:street":"Railway St",
    "iso:country":"CA",
    "sg:address":"407 Railway St",
    "sg:city":"Kipling",
    "sg:classifiers":[
        {
            "category":"Home & Garden",
            "subcategory":"Garden Supply",
            "type":"Retail Goods"
        }
    ],
    "sg:phone":"+1 306 736 8140",
    "sg:postcode":"S0G 2S0",
    "sg:province":"SK",
    "sg:tags":[
        "engine",
        "lawn"
    ],
    "wof:name":"Baker's Small Engine Repair",
    "wof:placetype":"venue"
},
  "geometry": {"coordinates":[-102.62749481199999,50.1023788452],"type":"Point"}
}