{
  "type": "Feature",
  "properties": {
    "addr:full":"855 College Manor Dr Newmarket ON L3Y 8G7",
    "addr:housenumber":"855",
    "addr:postcode":"l3y 8g7",
    "addr:street":"College Manor Dr",
    "iso:country":"CA",
    "sg:address":"855 College Manor Dr",
    "sg:city":"Newmarket",
    "sg:classifiers":[
        {
            "category":"Education",
            "subcategory":"School",
            "type":"Public Place"
        }
    ],
    "sg:phone":"+1 905 836 8041",
    "sg:postcode":"L3Y 8G7",
    "sg:province":"ON",
    "wof:name":"Bogart Public School",
    "wof:placetype":"venue"
},
  "geometry": {"coordinates":[-79.43879699999999,44.048298],"type":"Point"}
}