{
  "type": "Feature",
  "properties": {
    "addr:full":"Williams Lake BC V2G 2X9",
    "addr:postcode":"bc v2g 2x9",
    "iso:country":"CA",
    "sg:city":"Williams Lake",
    "sg:classifiers":[
        {
            "category":"Insurance",
            "subcategory":"Insurance Agent",
            "type":"Services"
        }
    ],
    "sg:phone":"+1 250 398 6761",
    "sg:postcode":"V2G 2X9",
    "sg:province":"BC",
    "wof:name":"Insurance Corp of BC",
    "wof:placetype":"venue"
},
  "geometry": {"coordinates":[-122.13427,52.136147],"type":"Point"}
}