{
  "type": "Feature",
  "properties": {
    "addr:full":"4500 Stewart Rd W Kelowna BC V1W 4N5",
    "addr:housenumber":"4500",
    "addr:postcode":"v1w 4n5",
    "addr:street":"Stewart Rd W",
    "iso:country":"CA",
    "sg:address":"4500 Stewart Rd W",
    "sg:city":"Kelowna",
    "sg:classifiers":[
        {
            "category":"Wholesale",
            "subcategory":"Plants",
            "type":"Manufacturing & Wholesale Goods"
        }
    ],
    "sg:phone":"+1 250 764 2121",
    "sg:postcode":"V1W 4N5",
    "sg:province":"BC",
    "sg:tags":[
        "nursery",
        "tree"
    ],
    "wof:name":"Stewart Brothers Nurseries Ltd",
    "wof:placetype":"venue"
},
  "geometry": {"coordinates":[-119.455124,49.819958],"type":"Point"}
}