{
  "type": "Feature",
  "properties": {
    "addr:full":"Burritts Rapids ON K0G 1B0",
    "addr:postcode":"k0g 1b0",
    "iso:country":"CA",
    "sg:city":"Burritts Rapids",
    "sg:classifiers":[
        {
            "category":"Government",
            "subcategory":"Jail",
            "type":"Public Place"
        }
    ],
    "sg:phone":"+1 613 269 4771",
    "sg:postcode":"K0G 1B0",
    "sg:province":"ON",
    "sg:tags":[
        "provincial",
        "institution"
    ],
    "wof:name":"Ontario Correctional Svc",
    "wof:placetype":"venue"
},
  "geometry": {"coordinates":[-75.7986068726,44.9834518433],"type":"Point"}
}