{
  "type": "Feature",
  "properties": {
    "addr:full":"1519 Main St Stittsville ON K2S 1A7",
    "addr:housenumber":"1519",
    "addr:postcode":"k2s 1a7",
    "addr:street":"Main St",
    "iso:country":"CA",
    "sg:address":"1519 Main St",
    "sg:city":"Stittsville",
    "sg:classifiers":[
        {
            "category":"Home & Garden",
            "subcategory":"Building Materials",
            "type":"Retail Goods"
        }
    ],
    "sg:phone":"+1 613 831 4080",
    "sg:postcode":"K2S 1A7",
    "sg:province":"ON",
    "sg:tags":[
        "glass",
        "window",
        "plate"
    ],
    "wof:name":"Stittsville Glass & Sign",
    "wof:placetype":"venue"
},
  "geometry": {"coordinates":[-75.9272155762,45.2638549805],"type":"Point"}
}