{
  "type": "Feature",
  "properties": {
    "iso:country":"CA",
    "sg:city":"Merrickville",
    "sg:classifiers":[
        {
            "category":"Home & Garden",
            "subcategory":"Garden Supply",
            "type":"Retail Goods"
        }
    ],
    "sg:phone":"+1 613 269 3785",
    "sg:postcode":"K0G 1N0",
    "sg:province":"ON",
    "sg:tags":[
        "lawn",
        "mower"
    ],
    "wof:name":"Lyle Small Engines",
    "wof:placetype":"venue"
},
  "geometry": {"coordinates":[-75.83683776860001,44.9157409668],"type":"Point"}
}