{
  "type": "Feature",
  "properties": {
    "iso:country":"CA",
    "sg:address":"5232 Portage Ave",
    "sg:city":"Headingley",
    "sg:classifiers":[
        {
            "category":"Professional",
            "subcategory":"Accounting & Tax Preparation",
            "type":"Services"
        }
    ],
    "sg:phone":"+1 204 889 8862",
    "sg:postcode":"R4H 1E1",
    "sg:province":"MB",
    "sg:tags":[
        "accountant",
        "bookkeeping",
        "general"
    ],
    "wof:name":"Ritchie Accounting",
    "wof:placetype":"venue"
},
  "geometry": {"coordinates":[-97.3963394165,49.8754234314],"type":"Point"}
}