{
  "type": "Feature",
  "properties": {
    "addr:full":"22222 Lougheed Hwy Maple Ridge BC V2X 2T2",
    "addr:housenumber":"22222",
    "addr:postcode":"v2x 2t2",
    "addr:street":"Lougheed Hwy",
    "iso:country":"CA",
    "sg:address":"22222 Lougheed Hwy",
    "sg:city":"Maple Ridge",
    "sg:classifiers":[
        {
            "category":"Travel",
            "subcategory":"Hotels & Motels",
            "type":"Entertainment"
        }
    ],
    "sg:phone":"+1 604 467 3944",
    "sg:postcode":"V2X 2T2",
    "sg:province":"BC",
    "wof:name":"Haney Motor Hotel Ltd",
    "wof:placetype":"venue"
},
  "geometry": {"coordinates":[-122.606369,49.216709],"type":"Point"}
}