{
  "type": "Feature",
  "properties": {
    "iso:country":"CA",
    "sg:city":"Saint-Felicien",
    "sg:classifiers":[
        {
            "category":"Wholesale",
            "subcategory":"Groceries",
            "type":"Manufacturing & Wholesale Goods"
        }
    ],
    "sg:phone":"+1 418 679 2623",
    "sg:postcode":"G8K 1T1",
    "sg:province":"QC",
    "sg:tags":[
        "food",
        "grocer",
        "product"
    ],
    "wof:name":"Saputo Bakery Division",
    "wof:placetype":"venue"
},
  "geometry": {"coordinates":[-72.4123458862,48.6416397095],"type":"Point"}
}