{
  "type": "Feature",
  "properties": {
    "addr:full":"Red Deer County AB T4S 2A3",
    "addr:postcode":"t4s 2a3",
    "iso:country":"CA",
    "sg:city":"Red Deer County",
    "sg:classifiers":[
        {
            "category":"Manufacturing",
            "subcategory":"Buildings",
            "type":"Manufacturing & Wholesale Goods"
        }
    ],
    "sg:phone":"+1 403 346 3800",
    "sg:postcode":"T4S 2A3",
    "sg:province":"AB",
    "sg:tags":[
        "prefab"
    ],
    "wof:name":"Chiles Homes Ltd",
    "wof:placetype":"venue"
},
  "geometry": {"coordinates":[-113.870483398,52.2853431702],"type":"Point"}
}