{
  "type": "Feature",
  "properties": {
    "addr:full":"132 Patrick View SW Calgary AB T3H 3J4",
    "addr:housenumber":"132",
    "addr:postcode":"t3h 3j4",
    "addr:street":"Patrick View Sw",
    "iso:country":"CA",
    "sg:address":"132 Patrick View SW",
    "sg:city":"Calgary",
    "sg:classifiers":[
        {
            "category":"Professional",
            "subcategory":"Business Services",
            "type":"Services"
        }
    ],
    "sg:phone":"+1 403 278 9412",
    "sg:postcode":"T3H 3J4",
    "sg:province":"AB",
    "sg:tags":[
        "arbitration"
    ],
    "wof:name":"Hornung, Richard I",
    "wof:placetype":"venue"
},
  "geometry": {"coordinates":[-114.178978,51.067833],"type":"Point"}
}