{
  "type": "Feature",
  "properties": {
    "addr:full":"Brockville ON K6V 7L2",
    "addr:postcode":"k6v 7l2",
    "iso:country":"CA",
    "sg:city":"Brockville",
    "sg:classifiers":[
        {
            "category":"Government",
            "subcategory":"Office",
            "type":"Public Place"
        }
    ],
    "sg:phone":"+1 613 345 3269",
    "sg:postcode":"K6V 7L2",
    "sg:province":"ON",
    "sg:tags":[
        "village"
    ],
    "wof:name":"Brockville Downtown Board Mgmt",
    "wof:placetype":"venue"
},
  "geometry": {"coordinates":[-75.68287658689999,44.5903053284],"type":"Point"}
}