{
  "type": "Feature",
  "properties": {
    "addr:full":"261 Pleasant St Dartmouth NS B2Y 3S1",
    "addr:housenumber":"261",
    "addr:postcode":"b2y 3s1",
    "addr:street":"Pleasant St",
    "iso:country":"CA",
    "sg:address":"261 Pleasant St",
    "sg:city":"Dartmouth",
    "sg:classifiers":[
        {
            "category":"Health Services",
            "subcategory":"Doctor",
            "type":"Services"
        }
    ],
    "sg:phone":"+1 902 464 4646",
    "sg:postcode":"B2Y 3S1",
    "sg:province":"NS",
    "sg:tags":[
        "physician",
        "surgeon"
    ],
    "wof:name":"Muthu, M Saravana MD",
    "wof:placetype":"venue"
},
  "geometry": {"coordinates":[-63.5500297546,44.6568107605],"type":"Point"}
}