{
  "type": "Feature",
  "properties": {
    "iso:country":"CA",
    "sg:address":"1077 Rue Saint-Denis",
    "sg:city":"Montreal",
    "sg:classifiers":[
        {
            "category":"Social Services",
            "subcategory":"Job Training",
            "type":"Services"
        }
    ],
    "sg:phone":"+1 514 281 1030",
    "sg:postcode":"H2X 3J3",
    "sg:province":"QC",
    "sg:tags":[
        "employment"
    ],
    "wof:name":"Operation Placement Jeunesse",
    "wof:placetype":"venue"
},
  "geometry": {"coordinates":[-73.557236,45.512424],"type":"Point"}
}