{
  "type": "Feature",
  "properties": {
    "addr:full":"2288 2nd Ave Whitehorse YT Y1A 1C8",
    "addr:housenumber":"2288",
    "addr:postcode":"y1a 1c8",
    "addr:street":"2Nd Ave",
    "iso:country":"CA",
    "sg:address":"2288 2nd Ave",
    "sg:city":"Whitehorse",
    "sg:classifiers":[
        {
            "category":"Travel",
            "subcategory":"Hotels & Motels",
            "type":"Entertainment"
        }
    ],
    "sg:phone":"+1 867 668 4747",
    "sg:postcode":"Y1A 1C8",
    "sg:province":"YT",
    "wof:name":"Westmark Klondike Inn",
    "wof:placetype":"venue"
},
  "geometry": {"coordinates":[-135.06582599999999,60.72871],"type":"Point"}
}