{
  "type": "Feature",
  "properties": {
    "iso:country":"CA",
    "sg:address":"31 Cliff St",
    "sg:city":"Saint John",
    "sg:classifiers":[
        {
            "category":"Organizations",
            "subcategory":"Religious Organization",
            "type":"Services"
        }
    ],
    "sg:phone":"+1 506 634 4970",
    "sg:postcode":"E2L 3A9",
    "sg:province":"NB",
    "wof:name":"Sisters of Charity",
    "wof:placetype":"venue"
},
  "geometry": {"coordinates":[-66.057975769,45.2778930664],"type":"Point"}
}