{
  "type": "Feature",
  "properties": {
    "addr:full":"4840 Hammond Bay Rd Nanaimo BC V9T 5B4",
    "addr:housenumber":"4840",
    "addr:postcode":"v9t 5b4",
    "addr:street":"Hammond Bay Rd",
    "iso:country":"CA",
    "sg:address":"4840 Hammond Bay Rd",
    "sg:city":"Nanaimo",
    "sg:classifiers":[
        {
            "category":"Organizations",
            "subcategory":"Professional Association",
            "type":"Services"
        }
    ],
    "sg:phone":"+1 250 756 2410",
    "sg:postcode":"V9T 5B4",
    "sg:province":"BC",
    "sg:tags":[
        "club"
    ],
    "wof:name":"Hungarian Cultural Society",
    "wof:placetype":"venue"
},
  "geometry": {"coordinates":[-123.984116,49.231232],"type":"Point"}
}