{
  "type": "Feature",
  "properties": {
    "addr:full":"1170 Burnhamthorpe Rd W #27 Mississauga ON L5C 4E6",
    "addr:housenumber":"1170",
    "addr:postcode":"l5c 4e6",
    "addr:street":"Burnhamthorpe Rd W # 27",
    "iso:country":"CA",
    "sg:address":"1170 Burnhamthorpe Rd W #27",
    "sg:city":"Mississauga",
    "sg:classifiers":[
        {
            "category":"Retail",
            "subcategory":"Repair Shop",
            "type":"Services"
        }
    ],
    "sg:phone":"+1 905 276 0251",
    "sg:postcode":"L5C 4E6",
    "sg:province":"ON",
    "sg:tags":[
        "repairing",
        "piano",
        "refinishing"
    ],
    "wof:name":"Pianos Plus Music Ctr",
    "wof:placetype":"venue"
},
  "geometry": {"coordinates":[-79.6631698608,43.5690078735],"type":"Point"}
}