{
  "type": "Feature",
  "properties": {
    "iso:country":"CA",
    "sg:address":"2585 216 St",
    "sg:city":"Langley",
    "sg:classifiers":[
        {
            "category":"Food & Beverages",
            "subcategory":"Meat & Fish",
            "type":"Retail Goods"
        }
    ],
    "sg:phone":"+1 604 530 6493",
    "sg:postcode":"V2Z 1P4",
    "sg:province":"BC",
    "wof:name":"Saunders Meats",
    "wof:placetype":"venue"
},
  "geometry": {"coordinates":[-122.625183105,49.0492324829],"type":"Point"}
}