{
  "type": "Feature",
  "properties": {
    "addr:full":"4891 Rue Sherbrooke O Westmount QC H3Z 1G9",
    "addr:housenumber":"4891",
    "addr:postcode":"h3z 1g9",
    "addr:street":"Rue Sherbrooke O",
    "iso:country":"CA",
    "sg:address":"4891 Rue Sherbrooke O",
    "sg:city":"Westmount",
    "sg:classifiers":[
        {
            "category":"Personal",
            "subcategory":"Beauty Salon",
            "type":"Services"
        }
    ],
    "sg:phone":"+1 514 482 5824",
    "sg:postcode":"H3Z 1G9",
    "sg:province":"QC",
    "wof:name":"Fanny of Westmount Inc",
    "wof:placetype":"venue"
},
  "geometry": {"coordinates":[-73.604263,45.478443],"type":"Point"}
}