{
  "type": "Feature",
  "properties": {
    "iso:country":"CA",
    "sg:address":"185 Balliol St",
    "sg:city":"Toronto",
    "sg:classifiers":[
        {
            "category":"Recreation",
            "type":"Entertainment"
        }
    ],
    "sg:phone":"+1 416 487 1507",
    "sg:postcode":"M4S 1C2",
    "sg:province":"ON",
    "sg:tags":[
        "tennis",
        "court"
    ],
    "wof:name":"Greenwin Tennis Club",
    "wof:placetype":"venue"
},
  "geometry": {"coordinates":[-79.391121,43.698341],"type":"Point"}
}