{
  "type": "Feature",
  "properties": {
    "addr:full":"59 Salls St Red Rock ON P0T 2P0",
    "addr:housenumber":"59",
    "addr:postcode":"p0t 2p0",
    "addr:street":"Salls St",
    "iso:country":"CA",
    "sg:address":"59 Salls St",
    "sg:city":"Red Rock",
    "sg:classifiers":[
        {
            "category":"Food & Beverages",
            "subcategory":"Groceries & Convenience Stores",
            "type":"Retail Goods"
        }
    ],
    "sg:phone":"+1 807 886 2630",
    "sg:postcode":"P0T 2P0",
    "sg:province":"ON",
    "sg:tags":[
        "grocer"
    ],
    "wof:name":"Saunders Foodland",
    "wof:placetype":"venue"
},
  "geometry": {"coordinates":[-88.25862100000001,48.939835],"type":"Point"}
}