{
  "type": "Feature",
  "properties": {
    "addr:full":"1174 Queen St W Toronto ON M6J 1J5",
    "addr:housenumber":"1174",
    "addr:postcode":"m6j 1j5",
    "addr:street":"Queen St W",
    "iso:country":"CA",
    "sg:address":"1174 Queen St W",
    "sg:city":"Toronto",
    "sg:classifiers":[
        {
            "category":"Shopping",
            "type":"Retail Goods"
        }
    ],
    "sg:phone":"+1 416 516 2581",
    "sg:postcode":"M6J 1J5",
    "sg:province":"ON",
    "sg:tags":[
        "art",
        "gallery",
        "dealer"
    ],
    "wof:name":"Loop Gallery",
    "wof:placetype":"venue"
},
  "geometry": {"coordinates":[-79.4255828857,43.6429748535],"type":"Point"}
}