{
  "type": "Feature",
  "properties": {
    "addr:full":"12424 Elbow Dr SW Calgary AB T2W 1H2",
    "addr:housenumber":"12424",
    "addr:postcode":"t2w 1h2",
    "addr:street":"Elbow Dr Sw",
    "iso:country":"CA",
    "sg:address":"12424 Elbow Dr SW",
    "sg:city":"Calgary",
    "sg:classifiers":[
        {
            "category":"Education",
            "subcategory":"School",
            "type":"Public Place"
        }
    ],
    "sg:phone":"+1 403 777 7690",
    "sg:postcode":"T2W 1H2",
    "sg:province":"AB",
    "wof:name":"Robert Warren Jr High School",
    "wof:placetype":"venue"
},
  "geometry": {"coordinates":[-114.08538799999999,50.942406],"type":"Point"}
}