{
  "type": "Feature",
  "properties": {
    "iso:country":"CA",
    "sg:city":"Richmond",
    "sg:classifiers":[
        {
            "category":"Professional",
            "subcategory":"Accounting & Tax Preparation",
            "type":"Services"
        }
    ],
    "sg:phone":"+1 604 278 2851",
    "sg:postcode":"V6X 2W2",
    "sg:province":"BC",
    "sg:tags":[
        "accountant"
    ],
    "wof:name":"Eva Y Lee Inc",
    "wof:placetype":"venue"
},
  "geometry": {"coordinates":[-123.102951,49.186001],"type":"Point"}
}