{
  "type": "Feature",
  "properties": {
    "addr:full":"Calgary AB T2E 2W7",
    "addr:postcode":"t2e 2w7",
    "iso:country":"CA",
    "sg:city":"Calgary",
    "sg:classifiers":[
        {
            "category":"Banks & Credit Unions",
            "subcategory":"Financial Services",
            "type":"Services"
        }
    ],
    "sg:phone":"+1 403 250 8757",
    "sg:postcode":"T2E 2W7",
    "sg:province":"AB",
    "sg:tags":[
        "company",
        "holding"
    ],
    "wof:name":"Beaumont Select Corp Inc",
    "wof:placetype":"venue"
},
  "geometry": {"coordinates":[-114.036552,51.095024],"type":"Point"}
}