{
  "type": "Feature",
  "properties": {
    "addr:full":"150 Karl Clark Rd NW Edmonton AB T6N 1E2",
    "addr:housenumber":"150",
    "addr:postcode":"t6n 1e2",
    "addr:street":"Karl Clark Rd Nw",
    "iso:country":"CA",
    "sg:address":"150 Karl Clark Rd NW",
    "sg:city":"Edmonton",
    "sg:classifiers":[
        {
            "category":"Wholesale",
            "subcategory":"Durable Goods & Equipment",
            "type":"Manufacturing & Wholesale Goods"
        }
    ],
    "sg:phone":"+1 780 450 4400",
    "sg:postcode":"T6N 1E2",
    "sg:province":"AB",
    "sg:tags":[
        "electronic",
        "representative"
    ],
    "wof:name":"Logi Can Technologies Inc",
    "wof:placetype":"venue"
},
  "geometry": {"coordinates":[-113.4766922,53.4494628906],"type":"Point"}
}