{
  "type": "Feature",
  "properties": {
    "iso:country":"CA",
    "sg:city":"Vancouver",
    "sg:classifiers":[
        {
            "category":"Wholesale",
            "subcategory":"Durable Goods & Equipment",
            "type":"Manufacturing & Wholesale Goods"
        }
    ],
    "sg:phone":"+1 604 876 9878",
    "sg:postcode":"V5Y 1N5",
    "sg:province":"BC",
    "sg:tags":[
        "importer"
    ],
    "wof:name":"Aironware Enterprise Ltd",
    "wof:placetype":"venue"
},
  "geometry": {"coordinates":[-123.110671997,49.2637290955],"type":"Point"}
}