{
  "type": "Feature",
  "properties": {
    "addr:full":"315 Montreal Rd Cornwall ON K6H 1B6",
    "addr:housenumber":"315",
    "addr:postcode":"k6h 1b6",
    "addr:street":"Montreal Rd",
    "iso:country":"CA",
    "sg:address":"315 Montreal Rd",
    "sg:city":"Cornwall",
    "sg:classifiers":[
        {
            "category":"Restaurant",
            "type":"Food & Drink"
        }
    ],
    "sg:phone":"+1 613 932 4944",
    "sg:postcode":"K6H 1B6",
    "sg:province":"ON",
    "wof:name":"New Garden Restaurant",
    "wof:placetype":"venue"
},
  "geometry": {"coordinates":[-74.711494,45.018368],"type":"Point"}
}