{
  "type": "Feature",
  "properties": {
    "iso:country":"CA",
    "sg:address":"4720 Jane St",
    "sg:city":"North York",
    "sg:classifiers":[
        {
            "category":"Banks & Credit Unions",
            "subcategory":"Bank",
            "type":"Services"
        }
    ],
    "sg:phone":"+1 416 661 6363",
    "sg:postcode":"M3N 2L2",
    "sg:province":"ON",
    "wof:name":"Royal Bank Financial Group",
    "wof:placetype":"venue"
},
  "geometry": {"coordinates":[-79.520927,43.770298],"type":"Point"}
}