{
  "type": "Feature",
  "properties": {
    "addr:full":"4720 Jane St North York ON M3N 2L2",
    "addr:housenumber":"4720",
    "addr:postcode":"m3n 2l2",
    "addr:street":"Jane St",
    "iso:country":"CA",
    "sg:address":"4720 Jane St",
    "sg:city":"North York",
    "sg:classifiers":[
        {
            "category":"Banks & Credit Unions",
            "subcategory":"Bank",
            "type":"Services"
        }
    ],
    "sg:phone":"+1 416 661 6363",
    "sg:postcode":"M3N 2L2",
    "sg:province":"ON",
    "wof:name":"Royal Bank Financial Group",
    "wof:placetype":"venue"
},
  "geometry": {"coordinates":[-79.520927,43.770298],"type":"Point"}
}