{
  "type": "Feature",
  "properties": {
    "addr:full":"1672 12th Ave E Vancouver BC V5N 2A3",
    "addr:housenumber":"1672",
    "addr:postcode":"v5n 2a3",
    "addr:street":"12Th Ave E",
    "iso:country":"CA",
    "sg:address":"1672 12th Ave E",
    "sg:city":"Vancouver",
    "sg:classifiers":[
        {
            "category":"Retail",
            "subcategory":"Laundry & Dry Cleaning",
            "type":"Services"
        }
    ],
    "sg:phone":"+1 604 873 3365",
    "sg:postcode":"V5N 2A3",
    "sg:province":"BC",
    "sg:tags":[
        "cleaners"
    ],
    "wof:name":"Highland Coin Laundry & Clean",
    "wof:placetype":"venue"
},
  "geometry": {"coordinates":[-123.07058000000001,49.259445],"type":"Point"}
}