{
  "type": "Feature",
  "properties": {
    "addr:full":"1 Rue Principale N Notre-Dame-Du-Nord QC J0Z 3B0",
    "addr:housenumber":"1",
    "addr:postcode":"j0z 3b0",
    "addr:street":"Rue Principale N",
    "iso:country":"CA",
    "sg:address":"1 Rue Principale N",
    "sg:city":"Notre-Dame-Du-Nord",
    "sg:classifiers":[
        {
            "category":"Restaurant",
            "type":"Food & Drink"
        }
    ],
    "sg:phone":"+1 819 723 2738",
    "sg:postcode":"J0Z 3B0",
    "sg:province":"QC",
    "wof:name":"Restaurant Maxime Steak House",
    "wof:placetype":"venue"
},
  "geometry": {"coordinates":[-79.483757,47.593384],"type":"Point"}
}