{
  "type": "Feature",
  "properties": {
    "iso:country":"CA",
    "sg:city":"North York",
    "sg:classifiers":[
        {
            "category":"Shopping",
            "subcategory":"Shoes",
            "type":"Retail Goods"
        }
    ],
    "sg:phone":"+1 416 492 2007",
    "sg:postcode":"M2J 5A7",
    "sg:province":"ON",
    "wof:name":"Feet First",
    "wof:placetype":"venue"
},
  "geometry": {"coordinates":[-79.3453674316,43.7756156921],"type":"Point"}
}