{
  "type": "Feature",
  "properties": {
    "addr:full":"14900 Deer Ridge Dr SE Calgary AB T2J 7G1",
    "addr:housenumber":"14900",
    "addr:postcode":"t2j 7g1",
    "addr:street":"Deer Ridge Dr Se",
    "iso:country":"CA",
    "sg:address":"14900 Deer Ridge Dr SE",
    "sg:city":"Calgary",
    "sg:classifiers":[
        {
            "category":"Restaurant",
            "type":"Food & Drink"
        }
    ],
    "sg:phone":"+1 403 215 1005",
    "sg:postcode":"T2J 7G1",
    "sg:province":"AB",
    "wof:name":"Burger King",
    "wof:placetype":"venue"
},
  "geometry": {"coordinates":[-114.027519226,50.9302635193],"type":"Point"}
}