{
  "type": "Feature",
  "properties": {
    "addr:full":"2504 Bristol Cir Oakville ON L6H 5S1",
    "addr:housenumber":"2504",
    "addr:postcode":"l6h 5s1",
    "addr:street":"Bristol Cir",
    "iso:country":"CA",
    "sg:address":"2504 Bristol Cir",
    "sg:city":"Oakville",
    "sg:classifiers":[
        {
            "category":"Organizations",
            "subcategory":"Professional Association",
            "type":"Services"
        }
    ],
    "sg:phone":"+1 905 829 2331",
    "sg:postcode":"L6H 5S1",
    "sg:province":"ON",
    "wof:name":"Mississauga Italian Canadian",
    "wof:placetype":"venue"
},
  "geometry": {"coordinates":[-79.681725,43.519333],"type":"Point"}
}