{
  "type": "Feature",
  "properties": {
    "addr:full":"183 St Clair Ave W Toronto ON M4V 1P7",
    "addr:housenumber":"183",
    "addr:postcode":"m4v 1p7",
    "addr:street":"St Clair Ave W",
    "iso:country":"CA",
    "sg:address":"183 St Clair Ave W",
    "sg:city":"Toronto",
    "sg:classifiers":[
        {
            "category":"Health Services",
            "subcategory":"Health Practitioner",
            "type":"Services"
        }
    ],
    "sg:phone":"+1 416 967 4530",
    "sg:postcode":"M4V 1P7",
    "sg:province":"ON",
    "sg:tags":[
        "psychologist"
    ],
    "wof:name":"Cohen, N J",
    "wof:placetype":"venue"
},
  "geometry": {"coordinates":[-79.4033355713,43.686126709],"type":"Point"}
}