{
  "type": "Feature",
  "properties": {
    "addr:full":"4136 53rd Ave High Prairie AB T0G 1E0",
    "addr:housenumber":"4136",
    "addr:postcode":"t0g 1e0",
    "addr:street":"53Rd Ave",
    "iso:country":"CA",
    "sg:address":"4136 53rd Ave",
    "sg:city":"High Prairie",
    "sg:classifiers":[
        {
            "category":"Wholesale",
            "subcategory":"Petroleum",
            "type":"Manufacturing & Wholesale Goods"
        }
    ],
    "sg:phone":"+1 780 523 3205",
    "sg:postcode":"T0G 1E0",
    "sg:province":"AB",
    "sg:tags":[
        "bulk",
        "oil",
        "gasoline"
    ],
    "wof:name":"United Farmers of Alberta",
    "wof:placetype":"venue"
},
  "geometry": {"coordinates":[-116.46923099999999,55.431526],"type":"Point"}
}