{
  "type": "Feature",
  "properties": {
    "addr:full":"544 Rue Bagot Quebec QC G1N 2A4",
    "addr:housenumber":"544",
    "addr:postcode":"g1n 2a4",
    "addr:street":"Rue Bagot",
    "iso:country":"CA",
    "sg:address":"544 Rue Bagot",
    "sg:city":"Quebec",
    "sg:classifiers":[
        {
            "category":"Building & Trades",
            "subcategory":"Construction",
            "type":"Services"
        }
    ],
    "sg:phone":"+1 418 523 3405",
    "sg:postcode":"G1N 2A4",
    "sg:province":"QC",
    "sg:tags":[
        "painter",
        "pointing"
    ],
    "wof:name":"Entreprises Harbour Inc",
    "wof:placetype":"venue"
},
  "geometry": {"coordinates":[-71.2384109497,46.8081817627],"type":"Point"}
}