{
  "type": "Feature",
  "properties": {
    "addr:full":"Kingston ON K7L 1G8",
    "addr:postcode":"k7l 1g8",
    "iso:country":"CA",
    "sg:city":"Kingston",
    "sg:classifiers":[
        {
            "category":"Health Services",
            "subcategory":"Health Practitioner",
            "type":"Services"
        }
    ],
    "sg:phone":"+1 613 549 2195",
    "sg:postcode":"K7L 1G8",
    "sg:province":"ON",
    "sg:tags":[
        "psychologist"
    ],
    "wof:name":"Folsom, Jean PhD",
    "wof:placetype":"venue"
},
  "geometry": {"coordinates":[-76.5090332031,44.2402076721],"type":"Point"}
}