{
  "type": "Feature",
  "properties": {
    "iso:country":"CA",
    "sg:address":"161 Grant St",
    "sg:city":"Morden",
    "sg:classifiers":[
        {
            "category":"Manufacturing",
            "subcategory":"Glass & Minerals",
            "type":"Manufacturing & Wholesale Goods"
        }
    ],
    "sg:phone":"+1 204 822 9668",
    "sg:postcode":"R6M 1Y4",
    "sg:province":"MB",
    "sg:tags":[
        "insulation"
    ],
    "wof:name":"North Star Fibre Inc",
    "wof:placetype":"venue"
},
  "geometry": {"coordinates":[-98.1035308838,49.1838798523],"type":"Point"}
}