{
  "type": "Feature",
  "properties": {
    "addr:full":"419 Muskrat St Banff AB T1L 1B9",
    "addr:housenumber":"419",
    "addr:postcode":"t1l 1b9",
    "addr:street":"Muskrat St",
    "iso:country":"CA",
    "sg:address":"419 Muskrat St",
    "sg:city":"Banff",
    "sg:classifiers":[
        {
            "category":"Local Transit",
            "type":"Transportation"
        }
    ],
    "sg:phone":"+1 403 762 5558",
    "sg:postcode":"T1L 1B9",
    "sg:province":"AB",
    "sg:tags":[
        "limousine"
    ],
    "wof:name":"Alpine Limousine & Tours",
    "wof:placetype":"venue"
},
  "geometry": {"coordinates":[-115.565231,51.180614],"type":"Point"}
}