{
  "type": "Feature",
  "properties": {
    "addr:full":"12 Rue Principale Saint-Modeste QC G0L 3W0",
    "addr:housenumber":"12",
    "addr:postcode":"g0l 3w0",
    "addr:street":"Rue Principale",
    "iso:country":"CA",
    "sg:address":"12 Rue Principale",
    "sg:city":"Saint-Modeste",
    "sg:classifiers":[
        {
            "category":"Professional",
            "subcategory":"Engineering",
            "type":"Services"
        }
    ],
    "sg:phone":"+1 418 867 2145",
    "sg:postcode":"G0L 3W0",
    "sg:province":"QC",
    "sg:tags":[
        "environmental",
        "ecological",
        "engineer"
    ],
    "wof:name":"Jean-Paul Roy Ingeniere Consei",
    "wof:placetype":"venue"
},
  "geometry": {"coordinates":[-69.4365692139,47.7944107056],"type":"Point"}
}