{
  "type": "Feature",
  "properties": {
    "addr:full":"Montreal QC H2R 3A8",
    "addr:postcode":"h2r 3a8",
    "iso:country":"CA",
    "sg:city":"Montreal",
    "sg:classifiers":[
        {
            "category":"Retail",
            "subcategory":"Laundry & Dry Cleaning",
            "type":"Services"
        }
    ],
    "sg:phone":"+1 514 272 3312",
    "sg:postcode":"H2R 3A8",
    "sg:province":"QC",
    "sg:tags":[
        "cleaners"
    ],
    "wof:name":"Nettoyeur 60 Minutes",
    "wof:placetype":"venue"
},
  "geometry": {"coordinates":[-73.61346399999999,45.539661],"type":"Point"}
}