{
  "type": "Feature",
  "properties": {
    "addr:full":"211 Victoria Ave E Regina SK S4N 0P4",
    "addr:housenumber":"211",
    "addr:postcode":"s4n 0p4",
    "addr:street":"Victoria Ave E",
    "iso:country":"CA",
    "sg:address":"211 Victoria Ave E",
    "sg:city":"Regina",
    "sg:classifiers":[
        {
            "category":"Personal",
            "subcategory":"Beauty Salon",
            "type":"Services"
        }
    ],
    "sg:phone":"+1 306 352 6144",
    "sg:postcode":"S4N 0P4",
    "sg:province":"SK",
    "wof:name":"Teazers Hair Designs",
    "wof:placetype":"venue"
},
  "geometry": {"coordinates":[-104.584023,50.446987],"type":"Point"}
}