{
  "type": "Feature",
  "properties": {
    "addr:full":"252 Chippewa St Sarnia ON N7T 8A9",
    "addr:housenumber":"252",
    "addr:postcode":"n7t 8a9",
    "addr:street":"Chippewa St",
    "iso:country":"CA",
    "sg:address":"252 Chippewa St",
    "sg:city":"Sarnia",
    "sg:classifiers":[
        {
            "category":"Professional",
            "subcategory":"Management & Consulting",
            "type":"Services"
        }
    ],
    "sg:phone":"+1 519 344 0026",
    "sg:postcode":"N7T 8A9",
    "sg:province":"ON",
    "sg:tags":[
        "consultant",
        "safety"
    ],
    "wof:name":"Lambton Safe Community Council",
    "wof:placetype":"venue"
},
  "geometry": {"coordinates":[-82.412209,42.955109],"type":"Point"}
}