{
  "type": "Feature",
  "properties": {
    "iso:country":"CA",
    "sg:city":"Westbank",
    "sg:classifiers":[
        {
            "category":"Travel",
            "subcategory":"Travel Agent",
            "type":"Entertainment"
        }
    ],
    "sg:phone":"+1 250 768 4567",
    "sg:postcode":"V4T 2G2",
    "sg:province":"BC",
    "sg:tags":[
        "agency",
        "bureau"
    ],
    "wof:name":"United Travel Ltd",
    "wof:placetype":"venue"
},
  "geometry": {"coordinates":[-119.63005065900001,49.8297805786],"type":"Point"}
}