{
  "type": "Feature",
  "properties": {
    "addr:full":"Winnipeg MB R2C 4J2",
    "addr:postcode":"r2c 4j2",
    "iso:country":"CA",
    "sg:city":"Winnipeg",
    "sg:classifiers":[
        {
            "category":"Restaurant",
            "type":"Food & Drink"
        }
    ],
    "sg:phone":"+1 204 661 6244",
    "sg:postcode":"R2C 4J2",
    "sg:province":"MB",
    "sg:tags":[
        "cocoa",
        "parlor",
        "chocolate",
        "ice",
        "cream"
    ],
    "wof:name":"Laura Secord",
    "wof:placetype":"venue"
},
  "geometry": {"coordinates":[-97.061829,49.897278],"type":"Point"}
}