{
  "type": "Feature",
  "properties": {
    "addr:full":"3668 Rue Leclerc Lac-Megantic QC G6B 2V6",
    "addr:housenumber":"3668",
    "addr:postcode":"g6b 2v6",
    "addr:street":"Rue Leclerc",
    "iso:country":"CA",
    "sg:address":"3668 Rue Leclerc",
    "sg:city":"Lac-Megantic",
    "sg:classifiers":[
        {
            "category":"Professional",
            "subcategory":"Accounting & Tax Preparation",
            "type":"Services"
        }
    ],
    "sg:phone":"+1 819 583 2382",
    "sg:postcode":"G6B 2V6",
    "sg:province":"QC",
    "sg:tags":[
        "return",
        "filing"
    ],
    "wof:name":"Servicomtaxes Enr",
    "wof:placetype":"venue"
},
  "geometry": {"coordinates":[-70.9040145874,45.5875930786],"type":"Point"}
}