{
  "type": "Feature",
  "properties": {
    "addr:full":"Mississauga ON L5S 1A5",
    "addr:postcode":"l5s 1a5",
    "iso:country":"CA",
    "sg:city":"Mississauga",
    "sg:classifiers":[
        {
            "category":"Manufacturing",
            "subcategory":"Metals",
            "type":"Manufacturing & Wholesale Goods"
        }
    ],
    "sg:phone":"+1 905 677 8803",
    "sg:postcode":"L5S 1A5",
    "sg:province":"ON",
    "sg:tags":[
        "steel"
    ],
    "wof:name":"M S Magnum Mfg Inc",
    "wof:placetype":"venue"
},
  "geometry": {"coordinates":[-79.664108,43.700371],"type":"Point"}
}