{
  "type": "Feature",
  "properties": {
    "addr:full":"22330 Dewdney Trunk Rd Maple Ridge BC V2X 3J2",
    "addr:housenumber":"22330",
    "addr:postcode":"v2x 3j2",
    "addr:street":"Dewdney Trunk Rd",
    "iso:country":"CA",
    "sg:address":"22330 Dewdney Trunk Rd",
    "sg:city":"Maple Ridge",
    "sg:classifiers":[
        {
            "category":"Shopping",
            "subcategory":"Books",
            "type":"Retail Goods"
        }
    ],
    "sg:phone":"+1 604 467 4913",
    "sg:postcode":"V2X 3J2",
    "sg:province":"BC",
    "sg:tags":[
        "comic",
        "dealer"
    ],
    "wof:name":"Haney Books",
    "wof:placetype":"venue"
},
  "geometry": {"coordinates":[-122.603714,49.220367],"type":"Point"}
}