{
  "type": "Feature",
  "properties": {
    "addr:full":"137 Eagle Way Ucluelet BC V0R 3A0",
    "addr:housenumber":"137",
    "addr:postcode":"bc v0r 3a0",
    "addr:street":"Eagle Way",
    "iso:country":"CA",
    "sg:address":"137 Eagle Way",
    "sg:city":"Ucluelet",
    "sg:classifiers":[
        {
            "category":"Professional",
            "subcategory":"Art Services",
            "type":"Services"
        }
    ],
    "sg:phone":"+1 250 726 7481",
    "sg:postcode":"V0R 3A0",
    "sg:province":"BC",
    "sg:tags":[
        "graphic",
        "designer"
    ],
    "wof:name":"Schramm Design",
    "wof:placetype":"venue"
},
  "geometry": {"coordinates":[-125.54261,48.938026],"type":"Point"}
}