{
  "type": "Feature",
  "properties": {
    "iso:country":"CA",
    "sg:address":"1136 Centre St",
    "sg:city":"Thornhill",
    "sg:classifiers":[
        {
            "category":"Wholesale",
            "subcategory":"Metals & Minerals",
            "type":"Manufacturing & Wholesale Goods"
        }
    ],
    "sg:phone":"+1 905 763 7513",
    "sg:postcode":"L4J 3M8",
    "sg:province":"ON",
    "sg:tags":[
        "steel",
        "warehouse"
    ],
    "wof:name":"Lorimar Steel Sales",
    "wof:placetype":"venue"
},
  "geometry": {"coordinates":[-79.4619293213,43.8085021973],"type":"Point"}
}