{
  "type": "Feature",
  "properties": {
    "addr:full":"751 St Andrew St W Fergus ON N1M 3H2",
    "addr:housenumber":"751",
    "addr:postcode":"n1m 3h2",
    "addr:street":"St Andrew St W",
    "iso:country":"CA",
    "sg:address":"751 St Andrew St W",
    "sg:city":"Fergus",
    "sg:classifiers":[
        {
            "category":"Personal",
            "subcategory":"Beauty Salon",
            "type":"Services"
        }
    ],
    "sg:phone":"+1 519 843 1984",
    "sg:postcode":"N1M 3H2",
    "sg:province":"ON",
    "wof:name":"Basin Street Hair Design",
    "wof:placetype":"venue"
},
  "geometry": {"coordinates":[-80.385193,43.696342],"type":"Point"}
}