{
  "type": "Feature",
  "properties": {
    "iso:country":"CA",
    "sg:address":"3901 Hwy 97 N",
    "sg:city":"Quesnel",
    "sg:classifiers":[
        {
            "category":"Building & Trades",
            "subcategory":"Construction",
            "type":"Services"
        }
    ],
    "sg:phone":"+1 250 992 7383",
    "sg:postcode":"V2J 6W6",
    "sg:province":"BC",
    "sg:tags":[
        "excavating",
        "contractor"
    ],
    "wof:name":"N Purmal Contracting",
    "wof:placetype":"venue"
},
  "geometry": {"coordinates":[-122.49508667000001,53.0151901245],"type":"Point"}
}