{
  "type": "Feature",
  "properties": {
    "addr:full":"14204 25 St NW Edmonton AB T5Y 1G5",
    "addr:housenumber":"14204",
    "addr:postcode":"t5y 1g5",
    "addr:street":"25 St Nw",
    "iso:country":"CA",
    "sg:address":"14204 25 St NW",
    "sg:city":"Edmonton",
    "sg:classifiers":[
        {
            "category":"Organizations",
            "subcategory":"Religious Organization",
            "type":"Services"
        }
    ],
    "sg:phone":"+1 780 476 3762",
    "sg:postcode":"T5Y 1G5",
    "sg:province":"AB",
    "sg:tags":[
        "church"
    ],
    "wof:name":"Bethel Christian Reformed Chr",
    "wof:placetype":"venue"
},
  "geometry": {"coordinates":[-113.38173675500001,53.6058883667],"type":"Point"}
}