{
  "type": "Feature",
  "properties": {
    "addr:full":"170 Kortright Rd W Guelph ON N1G 4V7",
    "addr:housenumber":"170",
    "addr:postcode":"n1g 4v7",
    "addr:street":"Kortright Rd W",
    "iso:country":"CA",
    "sg:address":"170 Kortright Rd W",
    "sg:city":"Guelph",
    "sg:classifiers":[
        {
            "category":"Banks & Credit Unions",
            "subcategory":"Bank",
            "type":"Services"
        }
    ],
    "sg:phone":"+1 519 821 2030",
    "sg:postcode":"N1G 4V7",
    "sg:province":"ON",
    "wof:name":"Scotiabank",
    "wof:placetype":"venue"
},
  "geometry": {"coordinates":[-80.21957399999999,43.514343],"type":"Point"}
}