{
  "type": "Feature",
  "properties": {
    "addr:full":"121 Colborne St Brantford ON N3T 2G7",
    "addr:housenumber":"121",
    "addr:postcode":"n3t 2g7",
    "addr:street":"Colborne St",
    "iso:country":"CA",
    "sg:address":"121 Colborne St",
    "sg:city":"Brantford",
    "sg:classifiers":[
        {
            "category":"Food & Beverages",
            "subcategory":"Groceries & Convenience Stores",
            "type":"Retail Goods"
        }
    ],
    "sg:phone":"+1 519 756 8481",
    "sg:postcode":"N3T 2G7",
    "sg:province":"ON",
    "sg:tags":[
        "grocer"
    ],
    "wof:name":"Mac's Convenience Stores Ltd",
    "wof:placetype":"venue"
},
  "geometry": {"coordinates":[-80.2652206421,43.1382598877],"type":"Point"}
}