{
  "type": "Feature",
  "properties": {
    "addr:full":"2005 Finch Ave W North York ON M3N 2V3",
    "addr:housenumber":"2005",
    "addr:postcode":"m3n 2v3",
    "addr:street":"Finch Ave W",
    "iso:country":"CA",
    "sg:address":"2005 Finch Ave W",
    "sg:city":"North York",
    "sg:classifiers":[
        {
            "category":"Food & Beverages",
            "subcategory":"Liquor & Beverages",
            "type":"Retail Goods"
        }
    ],
    "sg:phone":"+1 416 745 3047",
    "sg:postcode":"M3N 2V3",
    "sg:province":"ON",
    "sg:tags":[
        "beer",
        "ale"
    ],
    "wof:name":"Beer Store",
    "wof:placetype":"venue"
},
  "geometry": {"coordinates":[-79.520073,43.756752],"type":"Point"}
}