{
  "type": "Feature",
  "properties": {
    "addr:full":"Williams Lake BC V2G 1N6",
    "addr:postcode":"bc v2g 1n6",
    "iso:country":"CA",
    "sg:city":"Williams Lake",
    "sg:classifiers":[
        {
            "category":"Government",
            "subcategory":"Office",
            "type":"Public Place"
        }
    ],
    "sg:phone":"+1 250 398 4909",
    "sg:postcode":"V2G 1N6",
    "sg:province":"BC",
    "wof:name":"BC Social Svc",
    "wof:placetype":"venue"
},
  "geometry": {"coordinates":[-122.147667,52.131901],"type":"Point"}
}