{
  "type": "Feature",
  "properties": {
    "addr:full":"Saint-Basile-Le-Grand QC J3N 1A9",
    "addr:postcode":"j3n 1a9",
    "iso:country":"CA",
    "sg:city":"Saint-Basile-Le-Grand",
    "sg:classifiers":[
        {
            "category":"Arena",
            "subcategory":"Sports Club",
            "type":"Entertainment"
        }
    ],
    "sg:phone":"+1 450 653 8248",
    "sg:postcode":"J3N 1A9",
    "sg:province":"QC",
    "sg:tags":[
        "manager",
        "recruiter",
        "association",
        "promoter"
    ],
    "wof:name":"Assn Reg Kin-Ball Rsm",
    "wof:placetype":"venue"
},
  "geometry": {"coordinates":[-73.280655,45.531509],"type":"Point"}
}