{
  "type": "Feature",
  "properties": {
    "addr:full":"501 Stewart Ave Nanaimo BC V9S 4C8",
    "addr:housenumber":"501",
    "addr:postcode":"v9s 4c8",
    "addr:street":"Stewart Ave",
    "iso:country":"CA",
    "sg:address":"501 Stewart Ave",
    "sg:city":"Nanaimo",
    "sg:classifiers":[
        {
            "category":"Professional",
            "subcategory":"Lawyer & Legal Services",
            "type":"Services"
        }
    ],
    "sg:phone":"+1 250 753 9180",
    "sg:postcode":"V9S 4C8",
    "sg:province":"BC",
    "sg:tags":[
        "attorney"
    ],
    "wof:name":"Stephen Taylor Law Office",
    "wof:placetype":"venue"
},
  "geometry": {"coordinates":[-123.944855,49.177998],"type":"Point"}
}