{
  "type": "Feature",
  "properties": {
    "addr:full":"Concord ON L4K 4C6",
    "addr:postcode":"l4k 4c6",
    "iso:country":"CA",
    "sg:city":"Concord",
    "sg:classifiers":[
        {
            "category":"Manufacturing",
            "subcategory":"Tools & Machinery",
            "type":"Manufacturing & Wholesale Goods"
        }
    ],
    "sg:phone":"+1 905 761 8822",
    "sg:postcode":"L4K 4C6",
    "sg:province":"ON",
    "sg:tags":[
        "cleaning",
        "steam"
    ],
    "wof:name":"Hpw Inc",
    "wof:placetype":"venue"
},
  "geometry": {"coordinates":[-79.4923171997,43.8267745972],"type":"Point"}
}