{
  "type": "Feature",
  "properties": {
    "addr:full":"391 Av Gamache Sept-Iles QC G4R 2H6",
    "addr:postcode":"g4r 2h6",
    "addr:street":"391 Av Gamache Sept-Iles",
    "iso:country":"CA",
    "sg:address":"391 Av Gamache",
    "sg:city":"Sept-Iles",
    "sg:classifiers":[
        {
            "category":"Wholesale",
            "subcategory":"Machinery & Supplies",
            "type":"Manufacturing & Wholesale Goods"
        }
    ],
    "sg:phone":"+1 418 962 0494",
    "sg:postcode":"G4R 2H6",
    "sg:province":"QC",
    "sg:tags":[
        "salon",
        "beauty"
    ],
    "wof:name":"Cantin Beaute Ltee",
    "wof:placetype":"venue"
},
  "geometry": {"coordinates":[-66.377701,50.207306],"type":"Point"}
}