{
  "type": "Feature",
  "properties": {
    "iso:country":"CA",
    "sg:city":"Watson Lake",
    "sg:classifiers":[
        {
            "category":"Building & Trades",
            "subcategory":"Equipment Rental",
            "type":"Services"
        }
    ],
    "sg:phone":"+1 867 536 2611",
    "sg:postcode":"Y0A 1C0",
    "sg:province":"YT",
    "sg:tags":[
        "contractor"
    ],
    "wof:name":"Jedway Enterprises Ltd",
    "wof:placetype":"venue"
},
  "geometry": {"coordinates":[-128.714157105,60.0629348755],"type":"Point"}
}