{
  "type": "Feature",
  "properties": {
    "addr:full":"4277 46A Ave Red Deer AB T4N 6T6",
    "addr:housenumber":"4277",
    "addr:postcode":"t4n 6t6",
    "addr:street":"46A Ave",
    "iso:country":"CA",
    "sg:address":"4277 46A Ave",
    "sg:city":"Red Deer",
    "sg:classifiers":[
        {
            "category":"Social Services",
            "subcategory":"Adult Care",
            "type":"Services"
        }
    ],
    "sg:phone":"+1 403 343 0688",
    "sg:postcode":"T4N 6T6",
    "sg:province":"AB",
    "sg:tags":[
        "senior",
        "housing",
        "citizen"
    ],
    "wof:name":"Parkvale Lodge",
    "wof:placetype":"venue"
},
  "geometry": {"coordinates":[-113.803978,52.261581],"type":"Point"}
}