{
  "type": "Feature",
  "properties": {
    "addr:full":"1147 Ontario St E Stratford ON N5A 6S5",
    "addr:housenumber":"1147",
    "addr:postcode":"n5a 6s5",
    "addr:street":"Ontario St E",
    "iso:country":"CA",
    "sg:address":"1147 Ontario St E",
    "sg:city":"Stratford",
    "sg:classifiers":[
        {
            "category":"Autos & Motor Vehicles",
            "subcategory":"Automobile Sales",
            "type":"Retail Goods"
        }
    ],
    "sg:phone":"+1 519 271 2651",
    "sg:postcode":"N5A 6S5",
    "sg:province":"ON",
    "sg:tags":[
        "truck"
    ],
    "wof:name":"Festival City Motors Ltd",
    "wof:placetype":"venue"
},
  "geometry": {"coordinates":[-80.942261,43.370708],"type":"Point"}
}