{
  "type": "Feature",
  "properties": {
    "addr:full":"Hull QC J8Y 6N5",
    "addr:postcode":"j8y 6n5",
    "iso:country":"CA",
    "sg:city":"Hull",
    "sg:classifiers":[
        {
            "category":"Professional",
            "subcategory":"Accounting & Tax Preparation",
            "type":"Services"
        }
    ],
    "sg:phone":"+1 819 770 9833",
    "sg:postcode":"J8Y 6N5",
    "sg:province":"QC",
    "sg:tags":[
        "accountant"
    ],
    "wof:name":"Raymond Chabot Grant Thornton",
    "wof:placetype":"venue"
},
  "geometry": {"coordinates":[-75.7338256836,45.4435958862],"type":"Point"}
}