{
  "type": "Feature",
  "properties": {
    "addr:full":"34 Maddison St E Monkton ON N0K 1P0",
    "addr:housenumber":"34",
    "addr:postcode":"n0k 1p0",
    "addr:street":"Maddison St E",
    "iso:country":"CA",
    "sg:address":"34 Maddison St E",
    "sg:city":"Monkton",
    "sg:classifiers":[
        {
            "category":"Organizations",
            "subcategory":"Religious Organization",
            "type":"Services"
        }
    ],
    "sg:phone":"+1 519 347 2130",
    "sg:postcode":"N0K 1P0",
    "sg:province":"ON",
    "sg:tags":[
        "church"
    ],
    "wof:name":"Knox Presbyterian Church",
    "wof:placetype":"venue"
},
  "geometry": {"coordinates":[-81.080833,43.586521],"type":"Point"}
}