{
  "type": "Feature",
  "properties": {
    "iso:country":"CA",
    "sg:address":"1328 Government St",
    "sg:city":"Victoria",
    "sg:classifiers":[
        {
            "category":"Shopping",
            "subcategory":"Gifts & Souvenirs",
            "type":"Retail Goods"
        }
    ],
    "sg:phone":"+1 250 383 0321",
    "sg:postcode":"V8W 1Y8",
    "sg:province":"BC",
    "sg:tags":[
        "shop"
    ],
    "wof:name":"Cowichan Trading CO",
    "wof:placetype":"venue"
},
  "geometry": {"coordinates":[-123.367675781,48.4268951416],"type":"Point"}
}