{
  "type": "Feature",
  "properties": {
    "addr:full":"Saint-Joseph-Du-Lac QC J0N 1M0",
    "addr:postcode":"j0n 1m0",
    "iso:country":"CA",
    "sg:city":"Saint-Joseph-Du-Lac",
    "sg:classifiers":[
        {
            "category":"Retail",
            "subcategory":"Auto Repair",
            "type":"Services"
        }
    ],
    "sg:phone":"+1 450 473 0768",
    "sg:postcode":"J0N 1M0",
    "sg:province":"QC",
    "sg:tags":[
        "body",
        "automobile",
        "painting"
    ],
    "wof:name":"Classique Auto Mc",
    "wof:placetype":"venue"
},
  "geometry": {"coordinates":[-73.96742999999999,45.521454],"type":"Point"}
}