{
  "type": "Feature",
  "properties": {
    "addr:full":"Chatham ON N7M 5J5",
    "addr:postcode":"n7m 5j5",
    "iso:country":"CA",
    "sg:city":"Chatham",
    "sg:classifiers":[
        {
            "category":"Manufacturing",
            "subcategory":"Tools & Machinery",
            "type":"Manufacturing & Wholesale Goods"
        }
    ],
    "sg:phone":"+1 519 352 5637",
    "sg:postcode":"N7M 5J5",
    "sg:province":"ON",
    "sg:tags":[
        "machine",
        "shop"
    ],
    "wof:name":"Thames Machine & Tool CO Ltd",
    "wof:placetype":"venue"
},
  "geometry": {"coordinates":[-82.2236709595,42.3904838562],"type":"Point"}
}