{
  "type": "Feature",
  "properties": {
    "addr:full":"2575 Sooke River Rd Sooke BC V0S 1N0",
    "addr:housenumber":"2575",
    "addr:postcode":"v0s 1n0",
    "addr:street":"Sooke River Rd",
    "iso:country":"CA",
    "sg:address":"2575 Sooke River Rd",
    "sg:city":"Sooke",
    "sg:classifiers":[
        {
            "category":"Autos & Motor Vehicles",
            "subcategory":"Motorcycle Sales",
            "type":"Retail Goods"
        }
    ],
    "sg:phone":"+1 250 642 3924",
    "sg:postcode":"V0S 1N0",
    "sg:province":"BC",
    "sg:tags":[
        "scooter"
    ],
    "wof:name":"Kenco Motorcycle & Salvage",
    "wof:placetype":"venue"
},
  "geometry": {"coordinates":[-123.69899700000001,48.402397],"type":"Point"}
}