{
  "type": "Feature",
  "properties": {
    "addr:full":"Bancroft ON K0L 1C0",
    "addr:postcode":"k0l 1c0",
    "iso:country":"CA",
    "sg:city":"Bancroft",
    "sg:classifiers":[
        {
            "category":"Wholesale",
            "subcategory":"Hardware",
            "type":"Manufacturing & Wholesale Goods"
        }
    ],
    "sg:phone":"+1 613 332 2427",
    "sg:postcode":"K0L 1C0",
    "sg:province":"ON",
    "sg:tags":[
        "equipment",
        "energy",
        "solar"
    ],
    "wof:name":"Wes Crafts",
    "wof:placetype":"venue"
},
  "geometry": {"coordinates":[-77.85269927980001,45.0573272705],"type":"Point"}
}