{
  "type": "Feature",
  "properties": {
    "addr:full":"Montpellier QC J0V 1M0",
    "addr:postcode":"j0v 1m0",
    "iso:country":"CA",
    "sg:city":"Montpellier",
    "sg:classifiers":[
        {
            "category":"Government",
            "subcategory":"Office",
            "type":"Public Place"
        }
    ],
    "sg:phone":"+1 819 428 3663",
    "sg:postcode":"J0V 1M0",
    "sg:province":"QC",
    "sg:tags":[
        "village"
    ],
    "wof:name":"Montpellier Municipal Bureau",
    "wof:placetype":"venue"
},
  "geometry": {"coordinates":[-75.165024,45.854446],"type":"Point"}
}