{
  "type": "Feature",
  "properties": {
    "addr:full":"1894 Bolt Ave Comox BC V9M 2J4",
    "addr:housenumber":"1894",
    "addr:postcode":"v9m 2j4",
    "addr:street":"Bolt Ave",
    "iso:country":"CA",
    "sg:address":"1894 Bolt Ave",
    "sg:city":"Comox",
    "sg:classifiers":[
        {
            "category":"Taxi",
            "type":"Transportation"
        }
    ],
    "sg:phone":"+1 250 339 0997",
    "sg:postcode":"V9M 2J4",
    "sg:province":"BC",
    "sg:tags":[
        "taxicab"
    ],
    "wof:name":"Designated Drivers",
    "wof:placetype":"venue"
},
  "geometry": {"coordinates":[-124.93254899999999,49.684628],"type":"Point"}
}