{
  "type": "Feature",
  "properties": {
    "addr:full":"North Vancouver BC V7L 1B3",
    "addr:postcode":"v7l 1b3",
    "iso:country":"CA",
    "sg:city":"North Vancouver",
    "sg:classifiers":[
        {
            "category":"Organizations",
            "subcategory":"Professional Association",
            "type":"Services"
        }
    ],
    "sg:phone":"+1 604 988 3484",
    "sg:postcode":"V7L 1B3",
    "sg:province":"BC",
    "wof:name":"Operation Eyesight Universal",
    "wof:placetype":"venue"
},
  "geometry": {"coordinates":[-123.07386779799999,49.3099708557],"type":"Point"}
}