{
  "type": "Feature",
  "properties": {
    "addr:full":"2177 Rue Masson # 205 Montreal QC H2H 1B1",
    "addr:housenumber":"2177",
    "addr:postcode":"h2h 1b1",
    "addr:street":"Rue Masson # 205",
    "iso:country":"CA",
    "sg:address":"2177 Rue Masson # 205",
    "sg:city":"Montreal",
    "sg:classifiers":[
        {
            "category":"Organizations",
            "subcategory":"Professional Association",
            "type":"Services"
        }
    ],
    "sg:phone":"+1 514 521 9671",
    "sg:postcode":"H2H 1B1",
    "sg:province":"QC",
    "wof:name":"Aqppt",
    "wof:placetype":"venue"
},
  "geometry": {"coordinates":[-73.580879,45.540764],"type":"Point"}
}