{
  "type": "Feature",
  "properties": {
    "addr:full":"408 Rue Saint-Sulpice Montreal QC H2Y 2V5",
    "addr:housenumber":"408",
    "addr:postcode":"h2y 2v5",
    "addr:street":"Rue Saint-Sulpice",
    "iso:country":"CA",
    "sg:address":"408 Rue Saint-Sulpice",
    "sg:city":"Montreal",
    "sg:classifiers":[
        {
            "category":"Professional",
            "subcategory":"Management & Consulting",
            "type":"Services"
        }
    ],
    "sg:phone":"+1 514 286 2866",
    "sg:postcode":"H2Y 2V5",
    "sg:province":"QC",
    "sg:tags":[
        "communications",
        "consultant"
    ],
    "wof:name":"Boite DE Comm",
    "wof:placetype":"venue"
},
  "geometry": {"coordinates":[-73.55490899999999,45.50433],"type":"Point"}
}