{
  "type": "Feature",
  "properties": {
    "iso:country":"CA",
    "sg:city":"Kitchener",
    "sg:classifiers":[
        {
            "category":"Social Services",
            "type":"Services"
        }
    ],
    "sg:phone":"+1 519 745 4215",
    "sg:postcode":"N2M 2C8",
    "sg:province":"ON",
    "sg:tags":[
        "organization",
        "welfare"
    ],
    "wof:name":"Salvation Army Kitchener Fmly",
    "wof:placetype":"venue"
},
  "geometry": {"coordinates":[-80.517189,43.446144],"type":"Point"}
}