{
  "type": "Feature",
  "properties": {
    "iso:country":"CA",
    "sg:address":"43615 Yale Rd",
    "sg:city":"Chilliwack",
    "sg:classifiers":[
        {
            "category":"Manufacturing",
            "subcategory":"Pet Food",
            "type":"Manufacturing & Wholesale Goods"
        }
    ],
    "sg:phone":"+1 604 823 5543",
    "sg:postcode":"V2R 4J6",
    "sg:province":"BC",
    "sg:tags":[
        "flour",
        "mills"
    ],
    "wof:name":"Anita's Organic Grain & Flour",
    "wof:placetype":"venue"
},
  "geometry": {"coordinates":[-122.01464843799999,49.1443214417],"type":"Point"}
}