{
  "type": "Feature",
  "properties": {
    "addr:full":"461 the Queensway S Keswick ON L4P 2C9",
    "addr:housenumber":"461",
    "addr:postcode":"l4p 2c9",
    "addr:street":"The Queensway S",
    "iso:country":"CA",
    "sg:address":"461 the Queensway S",
    "sg:city":"Keswick",
    "sg:classifiers":[
        {
            "category":"Manufacturing",
            "subcategory":"Printing",
            "type":"Manufacturing & Wholesale Goods"
        }
    ],
    "sg:phone":"+1 905 476 7753",
    "sg:postcode":"L4P 2C9",
    "sg:province":"ON",
    "sg:tags":[
        "newspaper"
    ],
    "wof:name":"Georgian Advocate Newspaper",
    "wof:placetype":"venue"
},
  "geometry": {"coordinates":[-79.4646530151,44.2131462097],"type":"Point"}
}