{
  "type": "Feature",
  "properties": {
    "addr:full":"190 Chain Lake Dr Halifax NS B3S 1C5",
    "addr:housenumber":"190",
    "addr:postcode":"b3s 1c5",
    "addr:street":"Chain Lake Dr",
    "iso:country":"CA",
    "sg:address":"190 Chain Lake Dr",
    "sg:city":"Halifax",
    "sg:classifiers":[
        {
            "category":"Cinema",
            "subcategory":"Movie Theater",
            "type":"Entertainment"
        }
    ],
    "sg:phone":"+1 902 876 4800",
    "sg:postcode":"B3S 1C5",
    "sg:province":"NS",
    "wof:name":"Empire 18 Cinemas Bayers Lake",
    "wof:placetype":"venue"
},
  "geometry": {"coordinates":[-63.674904,44.648903],"type":"Point"}
}