{
  "type": "Feature",
  "properties": {
    "addr:full":"22 Citadel Mesa Close NW Calgary AB T3G 5K8",
    "addr:housenumber":"22",
    "addr:postcode":"t3g 5k8",
    "addr:street":"Citadel Mesa Close Nw",
    "iso:country":"CA",
    "sg:address":"22 Citadel Mesa Close NW",
    "sg:city":"Calgary",
    "sg:classifiers":[
        {
            "category":"Professional",
            "subcategory":"Secretarial Services",
            "type":"Services"
        }
    ],
    "sg:phone":"+1 403 243 2387",
    "sg:postcode":"T3G 5K8",
    "sg:province":"AB",
    "sg:tags":[
        "reporting",
        "court"
    ],
    "wof:name":"Lexis Reporting Group",
    "wof:placetype":"venue"
},
  "geometry": {"coordinates":[-114.190269,51.148067],"type":"Point"}
}