{
  "type": "Feature",
  "properties": {
    "addr:full":"2209 Lorraine Dr Peterborough ON K9L 1X5",
    "addr:housenumber":"2209",
    "addr:postcode":"k9l 1x5",
    "addr:street":"Lorraine Dr",
    "iso:country":"CA",
    "sg:address":"2209 Lorraine Dr",
    "sg:city":"Peterborough",
    "sg:classifiers":[
        {
            "category":"Retail",
            "subcategory":"Repair Shop",
            "type":"Services"
        }
    ],
    "sg:phone":"+1 705 745 7845",
    "sg:postcode":"K9L 1X5",
    "sg:province":"ON",
    "sg:tags":[
        "lock",
        "locksmith",
        "furniture"
    ],
    "wof:name":"First Quality Office Repair",
    "wof:placetype":"venue"
},
  "geometry": {"coordinates":[-78.304192,44.353306],"type":"Point"}
}