{
  "type": "Feature",
  "properties": {
    "addr:full":"2119 Av Du Mont-Royal E Montreal QC H2H 1J9",
    "addr:housenumber":"2119",
    "addr:postcode":"h2h 1j9",
    "addr:street":"Av Du Mont-Royal E",
    "iso:country":"CA",
    "sg:address":"2119 Av Du Mont-Royal E",
    "sg:city":"Montreal",
    "sg:classifiers":[
        {
            "category":"Shopping",
            "subcategory":"Department Store",
            "type":"Retail Goods"
        }
    ],
    "sg:phone":"+1 514 526 8291",
    "sg:postcode":"H2H 1J9",
    "sg:province":"QC",
    "sg:tags":[
        "shop"
    ],
    "wof:name":"Dollarmania",
    "wof:placetype":"venue"
},
  "geometry": {"coordinates":[-73.5723571777,45.5354881287],"type":"Point"}
}