{
  "type": "Feature",
  "properties": {
    "iso:country":"CA",
    "sg:address":"4 Central Ave E",
    "sg:city":"Brockville",
    "sg:classifiers":[
        {
            "category":"Personal",
            "subcategory":"Beauty Salon",
            "type":"Services"
        }
    ],
    "sg:phone":"+1 613 342 4012",
    "sg:postcode":"K6V 1W4",
    "sg:province":"ON",
    "wof:name":"Coiffure",
    "wof:placetype":"venue"
},
  "geometry": {"coordinates":[-75.6900405884,44.6018028259],"type":"Point"}
}