{
  "type": "Feature",
  "properties": {
    "addr:full":"342 Scott St Fort Frances ON P9A 1G9",
    "addr:housenumber":"342",
    "addr:postcode":"p9a 1g9",
    "addr:street":"Scott St",
    "iso:country":"CA",
    "sg:address":"342 Scott St",
    "sg:city":"Fort Frances",
    "sg:classifiers":[
        {
            "category":"Manufacturing",
            "subcategory":"Printing",
            "type":"Manufacturing & Wholesale Goods"
        }
    ],
    "sg:phone":"+1 807 274 3233",
    "sg:postcode":"P9A 1G9",
    "sg:province":"ON",
    "sg:tags":[
        "printer"
    ],
    "wof:name":"Good Impressions Printing",
    "wof:placetype":"venue"
},
  "geometry": {"coordinates":[-93.394272,48.610203],"type":"Point"}
}