{
  "type": "Feature",
  "properties": {
    "addr:full":"605 Av DE LA Station Shawinigan QC G9N 1V9",
    "addr:postcode":"g9n 1v9",
    "addr:street":"605 Av De La Station",
    "iso:country":"CA",
    "sg:address":"605 Av DE LA Station",
    "sg:city":"Shawinigan",
    "sg:classifiers":[
        {
            "category":"Government",
            "subcategory":"Office",
            "type":"Public Place"
        }
    ],
    "sg:phone":"+1 819 537 7273",
    "sg:postcode":"G9N 1V9",
    "sg:province":"QC",
    "wof:name":"Quebec Protection DE LA Faune",
    "wof:placetype":"venue"
},
  "geometry": {"coordinates":[-72.752396,46.540916],"type":"Point"}
}