{
  "type": "Feature",
  "properties": {
    "addr:full":"112 Centennial Sq Thunder Bay ON P7E 1H3",
    "addr:housenumber":"112",
    "addr:postcode":"p7e 1h3",
    "addr:street":"Centennial Sq",
    "iso:country":"CA",
    "sg:address":"112 Centennial Sq",
    "sg:city":"Thunder Bay",
    "sg:classifiers":[
        {
            "category":"Restaurant",
            "type":"Food & Drink"
        }
    ],
    "sg:phone":"+1 807 622 5211",
    "sg:postcode":"P7E 1H3",
    "sg:province":"ON",
    "wof:name":"J J's Family Restaurant",
    "wof:placetype":"venue"
},
  "geometry": {"coordinates":[-89.19554100000001,48.471485],"type":"Point"}
}