{
  "type": "Feature",
  "properties": {
    "addr:full":"156 Rue Gaudreault Saint-Ambroise QC G7P 2J9",
    "addr:housenumber":"156",
    "addr:postcode":"g7p 2j9",
    "addr:street":"Rue Gaudreault",
    "iso:country":"CA",
    "sg:address":"156 Rue Gaudreault",
    "sg:city":"Saint-Ambroise",
    "sg:classifiers":[
        {
            "category":"Government",
            "subcategory":"Office",
            "type":"Public Place"
        }
    ],
    "sg:phone":"+1 418 672 2253",
    "sg:postcode":"G7P 2J9",
    "sg:province":"QC",
    "sg:tags":[
        "village"
    ],
    "wof:name":"Complexe Socio-Culturel",
    "wof:placetype":"venue"
},
  "geometry": {"coordinates":[-71.30689239500001,48.5551300049],"type":"Point"}
}