{
  "type": "Feature",
  "properties": {
    "addr:full":"98 Elm St Valemount BC V0E 2Z0",
    "addr:housenumber":"98",
    "addr:postcode":"v0e 2z0",
    "addr:street":"Elm St",
    "iso:country":"CA",
    "sg:address":"98 Elm St",
    "sg:city":"Valemount",
    "sg:classifiers":[
        {
            "category":"Recreation",
            "type":"Entertainment"
        }
    ],
    "sg:phone":"+1 250 566 4740",
    "sg:postcode":"V0E 2Z0",
    "sg:province":"BC",
    "sg:tags":[
        "center"
    ],
    "wof:name":"Canoe Valley Recreation Ctr",
    "wof:placetype":"venue"
},
  "geometry": {"coordinates":[-119.27022599999999,52.829891],"type":"Point"}
}