{
  "type": "Feature",
  "properties": {
    "iso:country":"CA",
    "sg:address":"212 5th St",
    "sg:city":"Courtenay",
    "sg:classifiers":[
        {
            "category":"Professional",
            "subcategory":"Lawyer & Legal Services",
            "type":"Services"
        }
    ],
    "sg:phone":"+1 250 334 4155",
    "sg:postcode":"V9N 1J6",
    "sg:province":"BC",
    "sg:tags":[
        "attorney"
    ],
    "wof:name":"Yeo, Robert",
    "wof:placetype":"venue"
},
  "geometry": {"coordinates":[-124.997436523,49.6912307739],"type":"Point"}
}