{
  "type": "Feature",
  "properties": {
    "addr:full":"268 Main St Point Leamington NL A0H 1Z0",
    "addr:housenumber":"268",
    "addr:postcode":"a0h 1z0",
    "addr:street":"Main St Point",
    "iso:country":"CA",
    "sg:address":"268 Main St",
    "sg:city":"Point Leamington",
    "sg:classifiers":[
        {
            "category":"Shopping",
            "subcategory":"Clothing, Apparel, & Fashions",
            "type":"Retail Goods"
        }
    ],
    "sg:phone":"+1 709 484 3596",
    "sg:postcode":"A0H 1Z0",
    "sg:province":"NL",
    "sg:tags":[
        "industrial",
        "glove"
    ],
    "wof:name":"Superior Glove Works Ltd",
    "wof:placetype":"venue"
},
  "geometry": {"coordinates":[-55.406029,49.319309],"type":"Point"}
}