{
  "type": "Feature",
  "properties": {
    "addr:full":"50 Boul St. Charles Beaconsfield QC H9W 2X3",
    "addr:housenumber":"50",
    "addr:postcode":"h9w 2x3",
    "addr:street":"Boul St. Charles",
    "iso:country":"CA",
    "sg:address":"50 Boul St. Charles",
    "sg:city":"Beaconsfield",
    "sg:classifiers":[
        {
            "category":"Personal",
            "subcategory":"Beauty Salon",
            "type":"Services"
        }
    ],
    "sg:phone":"+1 514 693 3585",
    "sg:postcode":"H9W 2X3",
    "sg:province":"QC",
    "sg:tags":[
        "manicuring"
    ],
    "wof:name":"Ongle Beaconsfield",
    "wof:placetype":"venue"
},
  "geometry": {"coordinates":[-73.8467636108,45.4326210022],"type":"Point"}
}