{
  "type": "Feature",
  "properties": {
    "iso:country":"CA",
    "sg:address":"3200 Boul Laframboise",
    "sg:city":"Saint-Hyacinthe",
    "sg:classifiers":[
        {
            "category":"Shopping",
            "subcategory":"Clothing, Apparel, & Fashions",
            "type":"Retail Goods"
        }
    ],
    "sg:phone":"+1 450 774 3621",
    "sg:postcode":"J2S 4Z5",
    "sg:province":"QC",
    "sg:tags":[
        "cleaners",
        "work"
    ],
    "wof:name":"Antonio Moreau Ltee",
    "wof:placetype":"venue"
},
  "geometry": {"coordinates":[-72.9673080444,45.6367378235],"type":"Point"}
}