{
  "type": "Feature",
  "properties": {
    "addr:full":"628 Main St Humboldt SK S0K 2A0",
    "addr:housenumber":"628",
    "addr:postcode":"s0k 2a0",
    "addr:street":"Main St",
    "iso:country":"CA",
    "sg:address":"628 Main St",
    "sg:city":"Humboldt",
    "sg:classifiers":[
        {
            "category":"Shopping",
            "subcategory":"Computers & Home Electronics",
            "type":"Retail Goods"
        }
    ],
    "sg:phone":"+1 306 682 2282",
    "sg:postcode":"S0K 2A0",
    "sg:province":"SK",
    "sg:tags":[
        "equipment",
        "dealer"
    ],
    "wof:name":"Country Corner Computers",
    "wof:placetype":"venue"
},
  "geometry": {"coordinates":[-105.122711,52.199333],"type":"Point"}
}