{
  "type": "Feature",
  "properties": {
    "addr:full":"Aurora ON L4G 1M1",
    "addr:postcode":"l4g 1m1",
    "iso:country":"CA",
    "sg:city":"Aurora",
    "sg:classifiers":[
        {
            "category":"Health Services",
            "subcategory":"Doctor",
            "type":"Services"
        }
    ],
    "sg:phone":"+1 905 727 1917",
    "sg:postcode":"L4G 1M1",
    "sg:province":"ON",
    "sg:tags":[
        "dentist"
    ],
    "wof:name":"Weingarten, Harry DDS",
    "wof:placetype":"venue"
},
  "geometry": {"coordinates":[-79.466881,43.997566],"type":"Point"}
}