{
  "type": "Feature",
  "properties": {
    "iso:country":"CA",
    "sg:address":"6605 Ch DE LA Cote-Des-Neiges",
    "sg:city":"Montreal",
    "sg:classifiers":[
        {
            "category":"Shopping",
            "subcategory":"Pharmacy",
            "type":"Retail Goods"
        }
    ],
    "sg:phone":"+1 514 739 8884",
    "sg:postcode":"H3S 2B3",
    "sg:province":"QC",
    "wof:name":"Pharmaprix",
    "wof:placetype":"venue"
},
  "geometry": {"coordinates":[-73.635773,45.502598],"type":"Point"}
}