{
  "type": "Feature",
  "properties": {
    "addr:full":"1116 Mainland St Vancouver BC V6B 2T9",
    "addr:housenumber":"1116",
    "addr:postcode":"bc v6b 2t9",
    "addr:street":"Mainland St",
    "iso:country":"CA",
    "sg:address":"1116 Mainland St",
    "sg:city":"Vancouver",
    "sg:classifiers":[
        {
            "category":"Restaurant",
            "type":"Food & Drink"
        }
    ],
    "sg:phone":"+1 604 687 1116",
    "sg:postcode":"V6B 2T9",
    "sg:province":"BC",
    "wof:name":"Circolo Restaurant",
    "wof:placetype":"venue"
},
  "geometry": {"coordinates":[-123.12077331499999,49.275226593],"type":"Point"}
}