{
  "type": "Feature",
  "properties": {
    "iso:country":"CA",
    "sg:address":"15 Rue Des Pins",
    "sg:city":"St-Joachim-DE-Montmorency",
    "sg:classifiers":[
        {
            "category":"Building & Trades",
            "subcategory":"Construction",
            "type":"Services"
        }
    ],
    "sg:phone":"+1 418 827 4778",
    "sg:postcode":"G0A 3X0",
    "sg:province":"QC",
    "sg:tags":[
        "contractor"
    ],
    "wof:name":"Rodia Construction Enr",
    "wof:placetype":"venue"
},
  "geometry": {"coordinates":[-70.8658981323,47.0648880005],"type":"Point"}
}