{
  "type": "Feature",
  "properties": {
    "addr:full":"Campbell River BC V9W 5P7",
    "addr:postcode":"v9w 5p7",
    "iso:country":"CA",
    "sg:city":"Campbell River",
    "sg:classifiers":[
        {
            "category":"Government",
            "subcategory":"Office",
            "type":"Public Place"
        }
    ],
    "sg:phone":"+1 250 830 6520",
    "sg:postcode":"V9W 5P7",
    "sg:province":"BC",
    "wof:name":"Campbell River Alcohol & Drug",
    "wof:placetype":"venue"
},
  "geometry": {"coordinates":[-125.25520299999999,50.026581],"type":"Point"}
}