{
  "type": "Feature",
  "properties": {
    "addr:full":"158 Mcgonigal St W Arnprior ON K7S 1M6",
    "addr:housenumber":"158",
    "addr:postcode":"k7s 1m6",
    "addr:street":"Mcgonigal St W",
    "iso:country":"CA",
    "sg:address":"158 Mcgonigal St W",
    "sg:city":"Arnprior",
    "sg:classifiers":[
        {
            "category":"Freight",
            "type":"Transportation"
        }
    ],
    "sg:phone":"+1 613 623 3923",
    "sg:postcode":"K7S 1M6",
    "sg:province":"ON",
    "sg:tags":[
        "trucking"
    ],
    "wof:name":"Dupuis Transfer",
    "wof:placetype":"venue"
},
  "geometry": {"coordinates":[-76.3592834473,45.4354820251],"type":"Point"}
}