{
  "type": "Feature",
  "properties": {
    "addr:full":"165 Cedar Island Rd Orillia ON L3V 1S9",
    "addr:housenumber":"165",
    "addr:postcode":"l3v 1s9",
    "addr:street":"Cedar Island Rd",
    "iso:country":"CA",
    "sg:address":"165 Cedar Island Rd",
    "sg:city":"Orillia",
    "sg:classifiers":[
        {
            "category":"Professional",
            "type":"Services"
        }
    ],
    "sg:phone":"+1 705 326 7554",
    "sg:postcode":"L3V 1S9",
    "sg:province":"ON",
    "sg:tags":[
        "water",
        "establishment",
        "well",
        "drilling"
    ],
    "wof:name":"Walter Howell & Sons Ltd",
    "wof:placetype":"venue"
},
  "geometry": {"coordinates":[-79.4067,44.608589],"type":"Point"}
}