{
  "type": "Feature",
  "properties": {
    "addr:full":"21 Rue Des Oblats S Ville-Marie QC J9V 1K1",
    "addr:housenumber":"21",
    "addr:postcode":"j9v 1k1",
    "addr:street":"Rue Des Oblats S",
    "iso:country":"CA",
    "sg:address":"21 Rue Des Oblats S",
    "sg:city":"Ville-Marie",
    "sg:classifiers":[
        {
            "category":"Restaurant",
            "type":"Food & Drink"
        }
    ],
    "sg:phone":"+1 819 622 1188",
    "sg:postcode":"J9V 1K1",
    "sg:province":"QC",
    "sg:tags":[
        "parlor",
        "ice",
        "cream"
    ],
    "wof:name":"Glacier Enr",
    "wof:placetype":"venue"
},
  "geometry": {"coordinates":[-79.435822,47.330624],"type":"Point"}
}