{
  "type": "Feature",
  "properties": {
    "addr:full":"2015 Rue Peel # 450 Montreal QC H3A 1T8",
    "addr:housenumber":"2015",
    "addr:postcode":"h3a 1t8",
    "addr:street":"Rue Peel # 450",
    "iso:country":"CA",
    "sg:address":"2015 Rue Peel # 450",
    "sg:city":"Montreal",
    "sg:classifiers":[
        {
            "category":"Professional",
            "subcategory":"Lawyer & Legal Services",
            "type":"Services"
        }
    ],
    "sg:phone":"+1 514 288 9322",
    "sg:postcode":"H3A 1T8",
    "sg:province":"QC",
    "sg:tags":[
        "attorney"
    ],
    "wof:name":"Barza, Howard",
    "wof:placetype":"venue"
},
  "geometry": {"coordinates":[-73.574997,45.501228],"type":"Point"}
}