{
  "type": "Feature",
  "properties": {
    "addr:full":"11666 Laity St Maple Ridge BC V2X 5A3",
    "addr:housenumber":"11666",
    "addr:postcode":"v2x 5a3",
    "addr:street":"Laity St",
    "iso:country":"CA",
    "sg:address":"11666 Laity St",
    "sg:city":"Maple Ridge",
    "sg:classifiers":[
        {
            "category":"Government",
            "subcategory":"Office",
            "type":"Public Place"
        }
    ],
    "sg:phone":"+1 604 463 1822",
    "sg:postcode":"V2X 5A3",
    "sg:province":"BC",
    "sg:tags":[
        "organization",
        "hospital"
    ],
    "wof:name":"Ridge Meadows Hospital Fndtn",
    "wof:placetype":"venue"
},
  "geometry": {"coordinates":[-122.631919861,49.2147865295],"type":"Point"}
}