{
  "type": "Feature",
  "properties": {
    "addr:full":"453 Rhodes Ave Toronto ON M4L 3A6",
    "addr:housenumber":"453",
    "addr:postcode":"m4l 3a6",
    "addr:street":"Rhodes Ave",
    "iso:country":"CA",
    "sg:address":"453 Rhodes Ave",
    "sg:city":"Toronto",
    "sg:classifiers":[
        {
            "category":"Professional",
            "subcategory":"Computer Services",
            "type":"Services"
        }
    ],
    "sg:phone":"+1 416 465 5822",
    "sg:postcode":"M4L 3A6",
    "sg:province":"ON",
    "sg:tags":[
        "consultant"
    ],
    "wof:name":"Cjrk Computer Consulting",
    "wof:placetype":"venue"
},
  "geometry": {"coordinates":[-79.321754,43.676453],"type":"Point"}
}