{
  "type": "Feature",
  "properties": {
    "addr:full":"123 Rue Valvue # B Loretteville QC G2A 2G1",
    "addr:housenumber":"123;# b",
    "addr:postcode":"g2a 2g1",
    "addr:street":"Rue Valvue",
    "iso:country":"CA",
    "sg:address":"123 Rue Valvue # B",
    "sg:city":"Loretteville",
    "sg:classifiers":[
        {
            "category":"Insurance",
            "subcategory":"Insurance Agent",
            "type":"Services"
        }
    ],
    "sg:phone":"+1 418 845 5959",
    "sg:postcode":"G2A 2G1",
    "sg:province":"QC",
    "wof:name":"Services Financiers Primerica",
    "wof:placetype":"venue"
},
  "geometry": {"coordinates":[-71.34893035890001,46.8586730957],"type":"Point"}
}