{
  "type": "Feature",
  "properties": {
    "addr:full":"Ottawa ON K1S 3W2",
    "addr:postcode":"k1s 3w2",
    "iso:country":"CA",
    "sg:city":"Ottawa",
    "sg:classifiers":[
        {
            "category":"Building & Trades",
            "subcategory":"Construction",
            "type":"Services"
        }
    ],
    "sg:phone":"+1 613 565 4669",
    "sg:postcode":"K1S 3W2",
    "sg:province":"ON",
    "sg:tags":[
        "resurfacing",
        "laying",
        "refinishing",
        "floor"
    ],
    "wof:name":"Creative Floorworx Inc",
    "wof:placetype":"venue"
},
  "geometry": {"coordinates":[-75.687225,45.401421],"type":"Point"}
}