{
  "type": "Feature",
  "properties": {
    "addr:full":"961 Rue Legault Greenfield Park QC J4V 3C6",
    "addr:housenumber":"961",
    "addr:postcode":"j4v 3c6",
    "addr:street":"Rue Legault;Park",
    "iso:country":"CA",
    "sg:address":"961 Rue Legault",
    "sg:city":"Greenfield Park",
    "sg:classifiers":[
        {
            "category":"Real Estate",
            "subcategory":"Real Estate Operator",
            "type":"Services"
        }
    ],
    "sg:phone":"+1 450 676 9807",
    "sg:postcode":"J4V 3C6",
    "sg:province":"QC",
    "sg:tags":[
        "condominium"
    ],
    "wof:name":"Fairgreen Acres",
    "wof:placetype":"venue"
},
  "geometry": {"coordinates":[-73.4430465698,45.4930648804],"type":"Point"}
}