{
  "type": "Feature",
  "properties": {
    "addr:full":"Ottawa ON K1P 6A9",
    "addr:postcode":"k1p 6a9",
    "iso:country":"CA",
    "sg:city":"Ottawa",
    "sg:classifiers":[
        {
            "category":"Professional",
            "subcategory":"Lawyer & Legal Services",
            "type":"Services"
        }
    ],
    "sg:phone":"+1 613 567 3222",
    "sg:postcode":"K1P 6A9",
    "sg:province":"ON",
    "sg:tags":[
        "attorney"
    ],
    "wof:name":"Rail, Denis",
    "wof:placetype":"venue"
},
  "geometry": {"coordinates":[-75.700729,45.41993],"type":"Point"}
}