{
  "type": "Feature",
  "properties": {
    "addr:full":"789 Markham Rd Scarborough ON M1H 2Y1",
    "addr:housenumber":"789",
    "addr:postcode":"m1h 2y1",
    "addr:street":"Markham Rd",
    "iso:country":"CA",
    "sg:address":"789 Markham Rd",
    "sg:city":"Scarborough",
    "sg:classifiers":[
        {
            "category":"Banks & Credit Unions",
            "subcategory":"Bank",
            "type":"Services"
        }
    ],
    "sg:phone":"+1 416 439 3031",
    "sg:postcode":"M1H 2Y1",
    "sg:province":"ON",
    "wof:name":"Royal Bank Financial Group",
    "wof:placetype":"venue"
},
  "geometry": {"coordinates":[-79.22789,43.76696],"type":"Point"}
}