{
  "type": "Feature",
  "properties": {
    "iso:country":"CA",
    "sg:address":"200 Hwy 18 W",
    "sg:city":"Estevan",
    "sg:classifiers":[
        {
            "category":"Manufacturing",
            "subcategory":"Buildings",
            "type":"Manufacturing & Wholesale Goods"
        }
    ],
    "sg:phone":"+1 306 634 7255",
    "sg:postcode":"S4A 2A7",
    "sg:province":"SK",
    "sg:tags":[
        "mobile",
        "home"
    ],
    "wof:name":"Sri Homes Inc",
    "wof:placetype":"venue"
},
  "geometry": {"coordinates":[-102.975242615,49.1328392029],"type":"Point"}
}