{
  "type": "Feature",
  "properties": {
    "addr:full":"215 Chain Lake Dr Halifax NS B3S 1C9",
    "addr:housenumber":"215",
    "addr:postcode":"b3s 1c9",
    "addr:street":"Chain Lake Dr",
    "iso:country":"CA",
    "sg:address":"215 Chain Lake Dr",
    "sg:city":"Halifax",
    "sg:classifiers":[
        {
            "category":"Shopping",
            "subcategory":"Stationery & Office Supplies",
            "type":"Retail Goods"
        }
    ],
    "sg:phone":"+1 902 450 5241",
    "sg:postcode":"B3S 1C9",
    "sg:province":"NS",
    "wof:name":"Business Depot",
    "wof:placetype":"venue"
},
  "geometry": {"coordinates":[-63.6757621765,44.6502723694],"type":"Point"}
}