{
  "type": "Feature",
  "properties": {
    "addr:full":"1415 Rue Des Champs-Elysees # 300 Chicoutimi QC G7H 6J2",
    "addr:housenumber":"1415",
    "addr:postcode":"g7h 6j2",
    "addr:street":"Rue Des Champs-Elysees # 300",
    "iso:country":"CA",
    "sg:address":"1415 Rue Des Champs-Elysees # 300",
    "sg:city":"Chicoutimi",
    "sg:classifiers":[
        {
            "category":"Food & Beverages",
            "subcategory":"Specialty",
            "type":"Retail Goods"
        }
    ],
    "sg:phone":"+1 418 693 9320",
    "sg:postcode":"G7H 6J2",
    "sg:province":"QC",
    "wof:name":"Nature Sante",
    "wof:placetype":"venue"
},
  "geometry": {"coordinates":[-71.051612854,48.4038124084],"type":"Point"}
}