{
  "type": "Feature",
  "properties": {
    "addr:full":"3459 Sheppard Ave E # 202 Scarborough ON M1T 3K5",
    "addr:housenumber":"3459",
    "addr:postcode":"m1t 3k5",
    "addr:street":"Sheppard Ave E # 202",
    "iso:country":"CA",
    "sg:address":"3459 Sheppard Ave E # 202",
    "sg:city":"Scarborough",
    "sg:classifiers":[
        {
            "category":"Professional",
            "subcategory":"Lawyer & Legal Services",
            "type":"Services"
        }
    ],
    "sg:phone":"+1 416 292 2565",
    "sg:postcode":"M1T 3K5",
    "sg:province":"ON",
    "sg:tags":[
        "attorney"
    ],
    "wof:name":"Akai Seto",
    "wof:placetype":"venue"
},
  "geometry": {"coordinates":[-79.3052444458,43.7792282104],"type":"Point"}
}