{
  "type": "Feature",
  "properties": {
    "iso:country":"CA",
    "sg:address":"444 Albert St E",
    "sg:city":"Sault Ste Marie",
    "sg:classifiers":[
        {
            "category":"Social Services",
            "type":"Services"
        }
    ],
    "sg:phone":"+1 705 253 7343",
    "sg:postcode":"P6A 2J8",
    "sg:province":"ON",
    "sg:tags":[
        "organization",
        "welfare"
    ],
    "wof:name":"Summit Human Svc",
    "wof:placetype":"venue"
},
  "geometry": {"coordinates":[-84.33126068120001,46.5123558044],"type":"Point"}
}