{
  "type": "Feature",
  "properties": {
    "addr:full":"Gibsons BC V0N 1V0",
    "addr:postcode":"v0n 1v0",
    "iso:country":"CA",
    "sg:city":"Gibsons",
    "sg:classifiers":[
        {
            "category":"Personal",
            "subcategory":"Shoe Repair & Shine",
            "type":"Services"
        }
    ],
    "sg:phone":"+1 604 886 4622",
    "sg:postcode":"V0N 1V0",
    "sg:province":"BC",
    "sg:tags":[
        "repairing",
        "boot"
    ],
    "wof:name":"Trident Boots",
    "wof:placetype":"venue"
},
  "geometry": {"coordinates":[-123.505318,49.402206],"type":"Point"}
}