{
  "type": "Feature",
  "properties": {
    "addr:full":"37 Athabascan Ave #205 Sherwood Park AB T8A 4H3",
    "addr:housenumber":"37",
    "addr:postcode":"t8a 4h3",
    "addr:street":"Athabascan Ave # 205;Park",
    "iso:country":"CA",
    "sg:address":"37 Athabascan Ave #205",
    "sg:city":"Sherwood Park",
    "sg:classifiers":[
        {
            "category":"Real Estate",
            "subcategory":"Surveying",
            "type":"Services"
        }
    ],
    "sg:phone":"+1 780 417 4678",
    "sg:postcode":"T8A 4H3",
    "sg:province":"AB",
    "sg:tags":[
        "development",
        "consultant",
        "land"
    ],
    "wof:name":"Boreal Land Svc Ltd",
    "wof:placetype":"venue"
},
  "geometry": {"coordinates":[-113.321854,53.536282],"type":"Point"}
}