{
  "type": "Feature",
  "properties": {
    "addr:full":"13 Huron Dr Hammonds Plains NS B4B 1N1",
    "addr:housenumber":"13",
    "addr:postcode":"b4b 1n1",
    "addr:street":"Huron Dr",
    "iso:country":"CA",
    "sg:address":"13 Huron Dr",
    "sg:city":"Hammonds Plains",
    "sg:classifiers":[
        {
            "category":"Building & Trades",
            "subcategory":"Construction",
            "type":"Services"
        }
    ],
    "sg:phone":"+1 902 835 8716",
    "sg:postcode":"B4B 1N1",
    "sg:province":"NS",
    "sg:tags":[
        "contractor"
    ],
    "wof:name":"Keddy Construction Ltd",
    "wof:placetype":"venue"
},
  "geometry": {"coordinates":[-63.789406,44.744865],"type":"Point"}
}