{
  "type": "Feature",
  "properties": {
    "iso:country":"CA",
    "sg:address":"20 Park St W",
    "sg:city":"Sunderland",
    "sg:classifiers":[
        {
            "category":"Recreation",
            "type":"Entertainment"
        }
    ],
    "sg:phone":"+1 705 357 3338",
    "sg:postcode":"L0C 1H0",
    "sg:province":"ON",
    "sg:tags":[
        "skating",
        "hall",
        "rink",
        "auditorium"
    ],
    "wof:name":"Sunderland Memorial Arena",
    "wof:placetype":"venue"
},
  "geometry": {"coordinates":[-79.0671386719,44.2638282776],"type":"Point"}
}