{
  "type": "Feature",
  "properties": {
    "addr:full":"215 Villa Marie Dr Marystown NL A0E 2M0",
    "addr:housenumber":"215",
    "addr:postcode":"a0e 2m0",
    "addr:street":"Villa Marie Dr",
    "iso:country":"CA",
    "sg:address":"215 Villa Marie Dr",
    "sg:city":"Marystown",
    "sg:classifiers":[
        {
            "category":"Government",
            "subcategory":"Office",
            "type":"Public Place"
        }
    ],
    "sg:phone":"+1 709 279 3591",
    "sg:postcode":"A0E 2M0",
    "sg:province":"NL",
    "sg:tags":[
        "village"
    ],
    "wof:name":"Municipal Assessment Agency",
    "wof:placetype":"venue"
},
  "geometry": {"coordinates":[-55.15239,47.167347],"type":"Point"}
}