{
  "type": "Feature",
  "properties": {
    "addr:full":"134 John St Sault Ste Marie ON P6A 1P1",
    "addr:housenumber":"134",
    "addr:postcode":"p6a 1p1",
    "addr:street":"John St",
    "iso:country":"CA",
    "sg:address":"134 John St",
    "sg:city":"Sault Ste Marie",
    "sg:classifiers":[
        {
            "category":"Organizations",
            "subcategory":"Religious Organization",
            "type":"Services"
        }
    ],
    "sg:phone":"+1 705 253 3060",
    "sg:postcode":"P6A 1P1",
    "sg:province":"ON",
    "sg:tags":[
        "church"
    ],
    "wof:name":"St John Evangelist Epis Church",
    "wof:placetype":"venue"
},
  "geometry": {"coordinates":[-84.3445739746,46.5187988281],"type":"Point"}
}