{
  "type": "Feature",
  "properties": {
    "addr:full":"253 2nd Ave W Minitonas MB R0L 1G0",
    "addr:housenumber":"253",
    "addr:postcode":"r0l 1g0",
    "addr:street":"2Nd Ave W Minitonas",
    "iso:country":"CA",
    "sg:address":"253 2nd Ave W",
    "sg:city":"Minitonas",
    "sg:classifiers":[
        {
            "category":"Home & Garden",
            "subcategory":"Building Materials",
            "type":"Retail Goods"
        }
    ],
    "sg:phone":"+1 204 525 2440",
    "sg:postcode":"R0L 1G0",
    "sg:province":"MB",
    "wof:name":"Holmstead Furniture & Mfg",
    "wof:placetype":"venue"
},
  "geometry": {"coordinates":[-101.037147522,52.0865859985],"type":"Point"}
}