{
  "type": "Feature",
  "properties": {
    "addr:full":"Barrie ON L4M 3C1",
    "addr:postcode":"l4m 3c1",
    "iso:country":"CA",
    "sg:city":"Barrie",
    "sg:classifiers":[
        {
            "category":"Health Services",
            "subcategory":"Doctor",
            "type":"Services"
        }
    ],
    "sg:phone":"+1 705 722 3777",
    "sg:postcode":"L4M 3C1",
    "sg:province":"ON",
    "sg:tags":[
        "clinic",
        "dentist"
    ],
    "wof:name":"Bayfield Mall Dental Ctr",
    "wof:placetype":"venue"
},
  "geometry": {"coordinates":[-79.700996,44.401634],"type":"Point"}
}