{
  "type": "Feature",
  "properties": {
    "addr:full":"274 Av Labrosse Pointe-Claire QC H9R 5L8",
    "addr:postcode":"h9r 5l8",
    "addr:street":"274 Av Labrosse",
    "iso:country":"CA",
    "sg:address":"274 Av Labrosse",
    "sg:city":"Pointe-Claire",
    "sg:classifiers":[
        {
            "category":"Wholesale",
            "subcategory":"Machinery & Supplies",
            "type":"Manufacturing & Wholesale Goods"
        }
    ],
    "sg:phone":"+1 514 426 3030",
    "sg:postcode":"H9R 5L8",
    "sg:province":"QC",
    "sg:tags":[
        "converting",
        "paper",
        "converter"
    ],
    "wof:name":"Bobst Canada Inc",
    "wof:placetype":"venue"
},
  "geometry": {"coordinates":[-73.8283996582,45.4708251953],"type":"Point"}
}