{
  "type": "Feature",
  "properties": {
    "iso:country":"CA",
    "sg:address":"429 Dundas St",
    "sg:city":"Woodstock",
    "sg:classifiers":[
        {
            "category":"Home & Garden",
            "subcategory":"Furniture",
            "type":"Retail Goods"
        }
    ],
    "sg:phone":"+1 519 537 2397",
    "sg:postcode":"N4S 1B8",
    "sg:province":"ON",
    "wof:name":"Hudson's Furniture Store",
    "wof:placetype":"venue"
},
  "geometry": {"coordinates":[-80.75886535639999,43.1299285889],"type":"Point"}
}