{
  "type": "Feature",
  "properties": {
    "addr:full":"252 Ch Petit-Carey Six Roads NB E1X 3A6",
    "addr:housenumber":"252",
    "addr:postcode":"e1x 3a6",
    "addr:street":"Ch Petit-Carey;Roads",
    "iso:country":"CA",
    "sg:address":"252 Ch Petit-Carey",
    "sg:city":"Six Roads",
    "sg:classifiers":[
        {
            "category":"Wholesale",
            "subcategory":"Seafood",
            "type":"Manufacturing & Wholesale Goods"
        }
    ],
    "sg:phone":"+1 506 395 9013",
    "sg:postcode":"E1X 3A6",
    "sg:province":"NB",
    "wof:name":"R B Fruits DE Mers",
    "wof:placetype":"venue"
},
  "geometry": {"coordinates":[-64.86438800000001,47.62571],"type":"Point"}
}