{
  "type": "Feature",
  "properties": {
    "addr:full":"Main St Rose Valley SK S0E 1M0",
    "addr:postcode":"s0e 1m0",
    "addr:street":"Main St",
    "iso:country":"CA",
    "sg:address":"Main St",
    "sg:city":"Rose Valley",
    "sg:classifiers":[
        {
            "category":"Banks & Credit Unions",
            "subcategory":"Bank",
            "type":"Services"
        }
    ],
    "sg:phone":"+1 306 323 4519",
    "sg:postcode":"S0E 1M0",
    "sg:province":"SK",
    "wof:name":"St Front Credit Union",
    "wof:placetype":"venue"
},
  "geometry": {"coordinates":[-103.811226,52.289658],"type":"Point"}
}