{
  "type": "Feature",
  "properties": {
    "addr:full":"426 2nd Ave N Vauxhall AB T0K 2K0",
    "addr:housenumber":"426",
    "addr:postcode":"t0k 2k0",
    "addr:street":"2Nd Ave N",
    "iso:country":"CA",
    "sg:address":"426 2nd Ave N",
    "sg:city":"Vauxhall",
    "sg:classifiers":[
        {
            "category":"Banks & Credit Unions",
            "subcategory":"Bank",
            "type":"Services"
        }
    ],
    "sg:phone":"+1 403 654 2123",
    "sg:postcode":"T0K 2K0",
    "sg:province":"AB",
    "wof:name":"Cibc",
    "wof:placetype":"venue"
},
  "geometry": {"coordinates":[-112.103981,50.068378],"type":"Point"}
}