{
  "type": "Feature",
  "properties": {
    "addr:full":"7333 Place Des Roseraies # 100 Anjou QC H1M 2X6",
    "addr:housenumber":"7333",
    "addr:postcode":"h1m 2x6",
    "addr:street":"Place Des Roseraies # 100",
    "iso:country":"CA",
    "sg:address":"7333 Place Des Roseraies # 100",
    "sg:city":"Anjou",
    "sg:classifiers":[
        {
            "category":"Professional",
            "subcategory":"Employment Agencies",
            "type":"Services"
        }
    ],
    "sg:phone":"+1 514 493 9993",
    "sg:postcode":"H1M 2X6",
    "sg:province":"QC",
    "sg:tags":[
        "opportunity"
    ],
    "wof:name":"Services Industriels Renfort",
    "wof:placetype":"venue"
},
  "geometry": {"coordinates":[-73.55991400000001,45.600571],"type":"Point"}
}