{
  "type": "Feature",
  "properties": {
    "iso:country":"CA",
    "sg:city":"Port Moody",
    "sg:classifiers":[
        {
            "category":"Professional",
            "subcategory":"Management & Consulting",
            "type":"Services"
        }
    ],
    "sg:phone":"+1 604 469 4099",
    "sg:postcode":"V3H 4W6",
    "sg:province":"BC",
    "sg:tags":[
        "consultant",
        "business"
    ],
    "wof:name":"Steps Business Development Grp",
    "wof:placetype":"venue"
},
  "geometry": {"coordinates":[-122.838981628,49.2924804688],"type":"Point"}
}