{
  "type": "Feature",
  "properties": {
    "addr:full":"930 Rue Principale Beresford NB E8K 3N5",
    "addr:housenumber":"930",
    "addr:postcode":"e8k 3n5",
    "addr:street":"Rue Principale",
    "iso:country":"CA",
    "sg:address":"930 Rue Principale",
    "sg:city":"Beresford",
    "sg:classifiers":[
        {
            "category":"Autos & Motor Vehicles",
            "subcategory":"Motorcycle Sales",
            "type":"Retail Goods"
        }
    ],
    "sg:phone":"+1 506 548 5190",
    "sg:postcode":"E8K 3N5",
    "sg:province":"NB",
    "sg:tags":[
        "scooter"
    ],
    "wof:name":"L R Custom Numero Un Ltd",
    "wof:placetype":"venue"
},
  "geometry": {"coordinates":[-65.7022323608,47.6942253113],"type":"Point"}
}