{
  "type": "Feature",
  "properties": {
    "addr:full":"3003 Englewood Dr Woss BC V0N 3P0",
    "addr:housenumber":"3003",
    "addr:postcode":"v0n 3p0",
    "addr:street":"Englewood Dr",
    "iso:country":"CA",
    "sg:address":"3003 Englewood Dr",
    "sg:city":"Woss",
    "sg:classifiers":[
        {
            "category":"Bars & Pubs",
            "type":"Food & Drink"
        }
    ],
    "sg:phone":"+1 250 281 2270",
    "sg:postcode":"V0N 3P0",
    "sg:province":"BC",
    "wof:name":"Lucky Logger Pub",
    "wof:placetype":"venue"
},
  "geometry": {"coordinates":[-126.60116600000001,50.210293],"type":"Point"}
}