{
  "type": "Feature",
  "properties": {
    "iso:country":"CA",
    "sg:address":"827 Sherbrooke St",
    "sg:city":"Peterborough",
    "sg:classifiers":[
        {
            "category":"Health Services",
            "subcategory":"Doctor",
            "type":"Services"
        }
    ],
    "sg:phone":"+1 705 743 0827",
    "sg:postcode":"K9J 2R2",
    "sg:province":"ON",
    "sg:tags":[
        "dentist"
    ],
    "wof:name":"Jeffrey, T J Gordon DDS",
    "wof:placetype":"venue"
},
  "geometry": {"coordinates":[-78.34562683110001,44.2954101562],"type":"Point"}
}