{
  "type": "Feature",
  "properties": {
    "addr:full":"502 8A St NE Calgary AB T2E 4J5",
    "addr:housenumber":"502",
    "addr:postcode":"t2e 4j5",
    "addr:street":"8A St Ne",
    "iso:country":"CA",
    "sg:address":"502 8A St NE",
    "sg:city":"Calgary",
    "sg:classifiers":[
        {
            "category":"Shopping",
            "subcategory":"Computers & Home Electronics",
            "type":"Retail Goods"
        }
    ],
    "sg:phone":"+1 403 228 1944",
    "sg:postcode":"T2E 4J5",
    "sg:province":"AB",
    "sg:tags":[
        "high",
        "fidelity",
        "stereophonic"
    ],
    "wof:name":"Future Technologies Ltd",
    "wof:placetype":"venue"
},
  "geometry": {"coordinates":[-114.041549683,51.0562934875],"type":"Point"}
}