{
  "type": "Feature",
  "properties": {
    "iso:country":"CA",
    "sg:address":"777 Mckay Rd",
    "sg:city":"Pickering",
    "sg:classifiers":[
        {
            "category":"Manufacturing",
            "subcategory":"Chemicals & Compounds",
            "type":"Manufacturing & Wholesale Goods"
        }
    ],
    "sg:phone":"+1 905 683 0411",
    "sg:postcode":"L1W 3A3",
    "sg:province":"ON",
    "sg:tags":[
        "paint"
    ],
    "wof:name":"Schwartz Chem of Canada Ltd",
    "wof:placetype":"venue"
},
  "geometry": {"coordinates":[-79.057465,43.819641],"type":"Point"}
}