{
  "type": "Feature",
  "properties": {
    "iso:country":"CA",
    "sg:address":"76 Talbot St E",
    "sg:city":"Leamington",
    "sg:classifiers":[
        {
            "category":"Cinema",
            "subcategory":"Movie Theater",
            "type":"Entertainment"
        }
    ],
    "sg:phone":"+1 519 322 2200",
    "sg:postcode":"N8H 1L3",
    "sg:province":"ON",
    "wof:name":"Star Theatre Inc",
    "wof:placetype":"venue"
},
  "geometry": {"coordinates":[-82.59748840330001,42.0535011292],"type":"Point"}
}