{
  "type": "Feature",
  "properties": {
    "addr:full":"170 Colonnade Rd Nepean ON K2E 7J5",
    "addr:housenumber":"170",
    "addr:postcode":"k2e 7j5",
    "addr:street":"Colonnade Rd",
    "iso:country":"CA",
    "sg:address":"170 Colonnade Rd",
    "sg:city":"Nepean",
    "sg:classifiers":[
        {
            "category":"Professional",
            "subcategory":"Business Services",
            "type":"Services"
        }
    ],
    "sg:phone":"+1 613 727 1044",
    "sg:postcode":"K2E 7J5",
    "sg:province":"ON",
    "sg:tags":[
        "convention",
        "meeting",
        "facility"
    ],
    "wof:name":"Centurion Conference & Event",
    "wof:placetype":"venue"
},
  "geometry": {"coordinates":[-75.7096481323,45.3424415588],"type":"Point"}
}