{
  "type": "Feature",
  "properties": {
    "addr:full":"125 Edilcan Dr Concord ON L4K 3S6",
    "addr:housenumber":"125",
    "addr:postcode":"l4k 3s6",
    "addr:street":"Edilcan Dr",
    "iso:country":"CA",
    "sg:address":"125 Edilcan Dr",
    "sg:city":"Concord",
    "sg:classifiers":[
        {
            "category":"Building & Trades",
            "subcategory":"Construction",
            "type":"Services"
        }
    ],
    "sg:phone":"+1 416 736 0277",
    "sg:postcode":"L4K 3S6",
    "sg:province":"ON",
    "sg:tags":[
        "concrete",
        "contractor"
    ],
    "wof:name":"Concord Concrete & Drain Inc",
    "wof:placetype":"venue"
},
  "geometry": {"coordinates":[-79.524818,43.816296],"type":"Point"}
}