{
  "type": "Feature",
  "properties": {
    "addr:full":"165 Rue Plessis Massueville QC J0G 1K0",
    "addr:housenumber":"165",
    "addr:postcode":"j0g 1k0",
    "addr:street":"Rue Plessis",
    "iso:country":"CA",
    "sg:address":"165 Rue Plessis",
    "sg:city":"Massueville",
    "sg:classifiers":[
        {
            "category":"Travel",
            "subcategory":"Campground",
            "type":"Entertainment"
        }
    ],
    "sg:phone":"+1 450 788 2680",
    "sg:postcode":"J0G 1K0",
    "sg:province":"QC",
    "wof:name":"Camping Quebecois",
    "wof:placetype":"venue"
},
  "geometry": {"coordinates":[-72.930397,45.90799],"type":"Point"}
}