{
  "type": "Feature",
  "properties": {
    "iso:country":"CA",
    "sg:address":"3700 Rue Berri",
    "sg:city":"Montreal",
    "sg:classifiers":[
        {
            "category":"Government",
            "subcategory":"Office",
            "type":"Public Place"
        }
    ],
    "sg:phone":"+1 514 873 1800",
    "sg:postcode":"H2L 4G9",
    "sg:province":"QC",
    "wof:name":"Quebec Comite Patronal DE",
    "wof:placetype":"venue"
},
  "geometry": {"coordinates":[-73.570618,45.519588],"type":"Point"}
}