{
  "type": "Feature",
  "properties": {
    "addr:full":"161 Ch DE L'Anse Rigaud QC J0P 1P0",
    "addr:housenumber":"161",
    "addr:postcode":"j0p 1p0",
    "addr:street":"Ch De L'Anse",
    "iso:country":"CA",
    "sg:address":"161 Ch DE L'Anse",
    "sg:city":"Rigaud",
    "sg:classifiers":[
        {
            "category":"Building & Trades",
            "subcategory":"Plumbing",
            "type":"Services"
        }
    ],
    "sg:phone":"+1 450 451 0767",
    "sg:postcode":"J0P 1P0",
    "sg:province":"QC",
    "sg:tags":[
        "contractor"
    ],
    "wof:name":"Plomberie Rigaud Inc",
    "wof:placetype":"venue"
},
  "geometry": {"coordinates":[-74.220482,45.481453],"type":"Point"}
}