{
  "type": "Feature",
  "properties": {
    "addr:full":"8350 77 Ave NW Edmonton AB T6C 0L4",
    "addr:housenumber":"8350",
    "addr:postcode":"t6c 0l4",
    "addr:street":"77 Ave Nw",
    "iso:country":"CA",
    "sg:address":"8350 77 Ave NW",
    "sg:city":"Edmonton",
    "sg:classifiers":[
        {
            "category":"Organizations",
            "subcategory":"Religious Organization",
            "type":"Services"
        }
    ],
    "sg:phone":"+1 780 461 7701",
    "sg:postcode":"T6C 0L4",
    "sg:province":"AB",
    "sg:tags":[
        "church"
    ],
    "wof:name":"St Jung Ha Sang",
    "wof:placetype":"venue"
},
  "geometry": {"coordinates":[-113.45607800000001,53.513466],"type":"Point"}
}