{
  "type": "Feature",
  "properties": {
    "addr:full":"275 Avenue Rd Kingston ON K7M 1C4",
    "addr:housenumber":"275",
    "addr:postcode":"k7m 1c4",
    "addr:street":"Avenue Rd",
    "iso:country":"CA",
    "sg:address":"275 Avenue Rd",
    "sg:city":"Kingston",
    "sg:classifiers":[
        {
            "category":"Real Estate",
            "subcategory":"Real Estate Agent",
            "type":"Services"
        }
    ],
    "sg:phone":"+1 613 544 2325",
    "sg:postcode":"K7M 1C4",
    "sg:province":"ON",
    "sg:tags":[
        "management"
    ],
    "wof:name":"Raven Realty Ltd Real Estate",
    "wof:placetype":"venue"
},
  "geometry": {"coordinates":[-76.518913,44.249847],"type":"Point"}
}