{
  "type": "Feature",
  "properties": {
    "addr:full":"3364 114 Ave SE Calgary AB T2Z 3V6",
    "addr:housenumber":"3364",
    "addr:postcode":"t2z 3v6",
    "addr:street":"114 Ave Se",
    "iso:country":"CA",
    "sg:address":"3364 114 Ave SE",
    "sg:city":"Calgary",
    "sg:classifiers":[
        {
            "category":"Manufacturing",
            "subcategory":"Tools & Machinery",
            "type":"Manufacturing & Wholesale Goods"
        }
    ],
    "sg:phone":"+1 403 253 7939",
    "sg:postcode":"T2Z 3V6",
    "sg:province":"AB",
    "sg:tags":[
        "control",
        "instrument"
    ],
    "wof:name":"Telematic Controls Inc",
    "wof:placetype":"venue"
},
  "geometry": {"coordinates":[-113.988754,50.949638],"type":"Point"}
}