{
  "type": "Feature",
  "properties": {
    "addr:full":"Vancouver BC V6E 1C9",
    "addr:postcode":"v6e 1c9",
    "iso:country":"CA",
    "sg:city":"Vancouver",
    "sg:classifiers":[
        {
            "category":"Professional",
            "subcategory":"Business Services",
            "type":"Services"
        }
    ],
    "sg:phone":"+1 604 685 5541",
    "sg:postcode":"V6E 1C9",
    "sg:province":"BC",
    "sg:tags":[
        "event"
    ],
    "wof:name":"Marquis Group",
    "wof:placetype":"venue"
},
  "geometry": {"coordinates":[-123.126862,49.284336],"type":"Point"}
}