{
  "type": "Feature",
  "properties": {
    "iso:country":"CA",
    "sg:address":"1401 Irricana Rd NE",
    "sg:city":"Airdrie",
    "sg:classifiers":[
        {
            "category":"Wholesale",
            "subcategory":"Petroleum",
            "type":"Manufacturing & Wholesale Goods"
        }
    ],
    "sg:phone":"+1 403 948 8111",
    "sg:postcode":"T4A 2G7",
    "sg:province":"AB",
    "sg:tags":[
        "pipe",
        "line",
        "company"
    ],
    "wof:name":"Transcanada Pipelines Ltd",
    "wof:placetype":"venue"
},
  "geometry": {"coordinates":[-113.986495972,51.2996826172],"type":"Point"}
}