{
  "type": "Feature",
  "properties": {
    "addr:full":"185 Union St Saint John NB E2L 1A9",
    "addr:housenumber":"185",
    "addr:postcode":"nb e2l 1a9",
    "addr:street":"Union St",
    "iso:country":"CA",
    "sg:address":"185 Union St",
    "sg:city":"Saint John",
    "sg:classifiers":[
        {
            "category":"Bars & Pubs",
            "type":"Food & Drink"
        }
    ],
    "sg:phone":"+1 506 652 4556",
    "sg:postcode":"E2L 1A9",
    "sg:province":"NB",
    "wof:name":"Iceberg Sports Pub",
    "wof:placetype":"venue"
},
  "geometry": {"coordinates":[-66.058716,45.275257],"type":"Point"}
}