{
  "type": "Feature",
  "properties": {
    "addr:full":"Winnipeg MB R3G 3P2",
    "addr:postcode":"r3g 3p2",
    "iso:country":"CA",
    "sg:city":"Winnipeg",
    "sg:classifiers":[
        {
            "category":"Government",
            "subcategory":"Office",
            "type":"Public Place"
        }
    ],
    "sg:phone":"+1 204 945 6586",
    "sg:postcode":"R3G 3P2",
    "sg:province":"MB",
    "wof:name":"Manitoba Mineral Exploration",
    "wof:placetype":"venue"
},
  "geometry": {"coordinates":[-97.19663238530001,49.8942451477],"type":"Point"}
}