{
  "type": "Feature",
  "properties": {
    "addr:full":"Nepean ON K2E 6T6",
    "addr:postcode":"k2e 6t6",
    "iso:country":"CA",
    "sg:city":"Nepean",
    "sg:classifiers":[
        {
            "category":"Wholesale",
            "subcategory":"Chemicals & Plastics",
            "type":"Manufacturing & Wholesale Goods"
        }
    ],
    "sg:phone":"+1 613 226 4228",
    "sg:postcode":"K2E 6T6",
    "sg:province":"ON",
    "sg:tags":[
        "instrument",
        "gas",
        "scientific",
        "apparatus"
    ],
    "wof:name":"Megs Specialty Gases & Equip",
    "wof:placetype":"venue"
},
  "geometry": {"coordinates":[-75.72133636469999,45.3340492249],"type":"Point"}
}