{
  "type": "Feature",
  "properties": {
    "addr:full":"457 Wellington St N Kitchener ON N2H 5L4",
    "addr:housenumber":"457",
    "addr:postcode":"n2h 5l4",
    "addr:street":"Wellington St N",
    "iso:country":"CA",
    "sg:address":"457 Wellington St N",
    "sg:city":"Kitchener",
    "sg:classifiers":[
        {
            "category":"Autos & Motor Vehicles",
            "subcategory":"Automobile Sales",
            "type":"Retail Goods"
        }
    ],
    "sg:phone":"+1 519 742 1511",
    "sg:postcode":"N2H 5L4",
    "sg:province":"ON",
    "sg:tags":[
        "body",
        "car"
    ],
    "wof:name":"Glm Auto Body Ltd",
    "wof:placetype":"venue"
},
  "geometry": {"coordinates":[-80.482269,43.461441],"type":"Point"}
}