{
  "type": "Feature",
  "properties": {
    "iso:country":"CA",
    "sg:address":"4308 50 Ave",
    "sg:city":"Innisfail",
    "sg:classifiers":[
        {
            "category":"Wholesale",
            "subcategory":"Farm Supplies",
            "type":"Manufacturing & Wholesale Goods"
        }
    ],
    "sg:phone":"+1 403 227 4999",
    "sg:postcode":"T4G 1M5",
    "sg:province":"AB",
    "sg:tags":[
        "chemical",
        "agricultural"
    ],
    "wof:name":"Innisfail CO-OP Agro Svc",
    "wof:placetype":"venue"
},
  "geometry": {"coordinates":[-113.95010376,52.0211448669],"type":"Point"}
}