{
  "type": "Feature",
  "properties": {
    "addr:full":"9412 120 St Surrey BC V3V 4B9",
    "addr:housenumber":"9412",
    "addr:postcode":"v3v 4b9",
    "addr:street":"120 St",
    "iso:country":"CA",
    "sg:address":"9412 120 St",
    "sg:city":"Surrey",
    "sg:classifiers":[
        {
            "category":"Restaurant",
            "type":"Food & Drink"
        }
    ],
    "sg:phone":"+1 604 581 7744",
    "sg:postcode":"V3V 4B9",
    "sg:province":"BC",
    "wof:name":"Wendy's",
    "wof:placetype":"venue"
},
  "geometry": {"coordinates":[-122.89007599999999,49.173923],"type":"Point"}
}