{
  "type": "Feature",
  "properties": {
    "addr:full":"5 Portage Rd Petawawa ON K8H 1T2",
    "addr:housenumber":"5",
    "addr:postcode":"k8h 1t2",
    "addr:street":"Portage Rd",
    "iso:country":"CA",
    "sg:address":"5 Portage Rd",
    "sg:city":"Petawawa",
    "sg:classifiers":[
        {
            "category":"Building & Trades",
            "subcategory":"Construction",
            "type":"Services"
        }
    ],
    "sg:phone":"+1 613 687 5479",
    "sg:postcode":"K8H 1T2",
    "sg:province":"ON",
    "sg:tags":[
        "general",
        "contractor"
    ],
    "wof:name":"Tcb Construction",
    "wof:placetype":"venue"
},
  "geometry": {"coordinates":[-77.28392028810001,45.8979873657],"type":"Point"}
}