{
  "type": "Feature",
  "properties": {
    "addr:full":"7615 Tecumseh Rd E Windsor ON N8T 3H1",
    "addr:housenumber":"7615",
    "addr:postcode":"n8t 3h1",
    "addr:street":"Tecumseh Rd E",
    "iso:country":"CA",
    "sg:address":"7615 Tecumseh Rd E",
    "sg:city":"Windsor",
    "sg:classifiers":[
        {
            "category":"Banks & Credit Unions",
            "subcategory":"Bank",
            "type":"Services"
        }
    ],
    "sg:phone":"+1 519 251 0871",
    "sg:postcode":"N8T 3H1",
    "sg:province":"ON",
    "sg:tags":[
        "cashing",
        "money",
        "check",
        "order"
    ],
    "wof:name":"Money Mart",
    "wof:placetype":"venue"
},
  "geometry": {"coordinates":[-82.93553199999999,42.313408],"type":"Point"}
}