{
  "type": "Feature",
  "properties": {
    "addr:full":"1005 Pasqua St Regina SK S4T 4K9",
    "addr:housenumber":"1005",
    "addr:postcode":"s4t 4k9",
    "addr:street":"Pasqua St",
    "iso:country":"CA",
    "sg:address":"1005 Pasqua St",
    "sg:city":"Regina",
    "sg:classifiers":[
        {
            "category":"Autos & Motor Vehicles",
            "subcategory":"Fuel & Gas Station",
            "type":"Retail Goods"
        }
    ],
    "sg:phone":"+1 306 791 6362",
    "sg:postcode":"S4T 4K9",
    "sg:province":"SK",
    "sg:tags":[
        "convenience",
        "oil",
        "store"
    ],
    "wof:name":"Klein's Food Mart",
    "wof:placetype":"venue"
},
  "geometry": {"coordinates":[-104.64078499999999,50.462765],"type":"Point"}
}