{
  "type": "Feature",
  "properties": {
    "addr:full":"24 Smith Ave Hamilton ON L8L 5P1",
    "addr:housenumber":"24",
    "addr:postcode":"l8l 5p1",
    "addr:street":"Smith Ave",
    "iso:country":"CA",
    "sg:address":"24 Smith Ave",
    "sg:city":"Hamilton",
    "sg:classifiers":[
        {
            "category":"Education",
            "subcategory":"School",
            "type":"Public Place"
        }
    ],
    "sg:phone":"+1 905 529 2848",
    "sg:postcode":"L8L 5P1",
    "sg:province":"ON",
    "wof:name":"St Brigid's School",
    "wof:placetype":"venue"
},
  "geometry": {"coordinates":[-79.8498,43.257519],"type":"Point"}
}