{
  "type": "Feature",
  "properties": {
    "addr:full":"Penticton BC V2A 3G6",
    "addr:postcode":"v2a 3g6",
    "iso:country":"CA",
    "sg:city":"Penticton",
    "sg:classifiers":[
        {
            "category":"Health Services",
            "subcategory":"Doctor",
            "type":"Services"
        }
    ],
    "sg:phone":"+1 250 493 0887",
    "sg:postcode":"V2A 3G6",
    "sg:province":"BC",
    "sg:tags":[
        "physician",
        "surgeon"
    ],
    "wof:name":"Walker, Shannon MD",
    "wof:placetype":"venue"
},
  "geometry": {"coordinates":[-119.57897186300001,49.4825286865],"type":"Point"}
}