{
  "type": "Feature",
  "properties": {
    "iso:country":"CA",
    "sg:address":"675 King St E",
    "sg:city":"Oshawa",
    "sg:classifiers":[
        {
            "category":"Health Services",
            "subcategory":"Doctor",
            "type":"Services"
        }
    ],
    "sg:phone":"+1 905 723 0950",
    "sg:postcode":"L1H 1G4",
    "sg:province":"ON",
    "sg:tags":[
        "dentist"
    ],
    "wof:name":"Dhillon, Mandeep DDS",
    "wof:placetype":"venue"
},
  "geometry": {"coordinates":[-78.8397979736,43.9029541016],"type":"Point"}
}