{
  "type": "Feature",
  "properties": {
    "addr:full":"Cap-DE-LA-Madeleine QC G8T 5R5",
    "addr:postcode":"g8t 5r5",
    "iso:country":"CA",
    "sg:city":"Cap-DE-LA-Madeleine",
    "sg:classifiers":[
        {
            "category":"Building & Trades",
            "subcategory":"Construction",
            "type":"Services"
        }
    ],
    "sg:phone":"+1 819 375 0196",
    "sg:postcode":"G8T 5R5",
    "sg:province":"QC",
    "sg:tags":[
        "acoustical",
        "ceiling",
        "contractor"
    ],
    "wof:name":"Systeme Interieur Mauricien",
    "wof:placetype":"venue"
},
  "geometry": {"coordinates":[-72.508652,46.364708],"type":"Point"}
}