{
  "type": "Feature",
  "properties": {
    "iso:country":"CA",
    "sg:address":"14 Mill St E",
    "sg:city":"Leamington",
    "sg:classifiers":[
        {
            "category":"Recreation",
            "type":"Entertainment"
        }
    ],
    "sg:phone":"+1 519 322 2251",
    "sg:postcode":"N8H 1R7",
    "sg:province":"ON",
    "sg:tags":[
        "bingo",
        "game"
    ],
    "wof:name":"Bingo Country",
    "wof:placetype":"venue"
},
  "geometry": {"coordinates":[-82.5986175537,42.0520210266],"type":"Point"}
}