{
  "type": "Feature",
  "properties": {
    "addr:full":"100 Main St Dysart SK S0G 1H0",
    "addr:housenumber":"100",
    "addr:postcode":"s0g 1h0",
    "addr:street":"Main St",
    "iso:country":"CA",
    "sg:address":"100 Main St",
    "sg:city":"Dysart",
    "sg:classifiers":[
        {
            "category":"Food & Beverages",
            "subcategory":"Groceries & Convenience Stores",
            "type":"Retail Goods"
        }
    ],
    "sg:phone":"+1 306 432 2132",
    "sg:postcode":"S0G 1H0",
    "sg:province":"SK",
    "sg:tags":[
        "meat"
    ],
    "wof:name":"Scrobe's Groceries",
    "wof:placetype":"venue"
},
  "geometry": {"coordinates":[-104.030845642,50.9448852539],"type":"Point"}
}