{
  "type": "Feature",
  "properties": {
    "iso:country":"CA",
    "sg:address":"19 Ashern Rd",
    "sg:city":"Winnipeg",
    "sg:classifiers":[
        {
            "category":"Building & Trades",
            "subcategory":"Plumbing",
            "type":"Services"
        }
    ],
    "sg:phone":"+1 204 832 4511",
    "sg:postcode":"R2Y 1H1",
    "sg:province":"MB",
    "sg:tags":[
        "contractor"
    ],
    "wof:name":"Sturgeon Creek Plumbing & Htg",
    "wof:placetype":"venue"
},
  "geometry": {"coordinates":[-97.30407,49.896507],"type":"Point"}
}