{
  "type": "Feature",
  "properties": {
    "addr:full":"26 Legend Crt Ancaster ON L9K 1J3",
    "addr:housenumber":"26",
    "addr:postcode":"l9k 1j3",
    "addr:street":"Legend Crt",
    "iso:country":"CA",
    "sg:address":"26 Legend Crt",
    "sg:city":"Ancaster",
    "sg:classifiers":[
        {
            "category":"Health Services",
            "subcategory":"Doctor",
            "type":"Services"
        }
    ],
    "sg:phone":"+1 905 304 6115",
    "sg:postcode":"L9K 1J3",
    "sg:province":"ON",
    "sg:tags":[
        "dentist"
    ],
    "wof:name":"Harnett, B E DDS",
    "wof:placetype":"venue"
},
  "geometry": {"coordinates":[-79.94821899999999,43.227505],"type":"Point"}
}