{
  "type": "Feature",
  "properties": {
    "iso:country":"CA",
    "sg:address":"144 6th St",
    "sg:city":"Brandon",
    "sg:classifiers":[
        {
            "category":"Health Services",
            "subcategory":"Doctor",
            "type":"Services"
        }
    ],
    "sg:phone":"+1 204 727 6451",
    "sg:postcode":"R7A 3N2",
    "sg:province":"MB",
    "sg:tags":[
        "physician",
        "surgeon"
    ],
    "wof:name":"Lindsay, G MD",
    "wof:placetype":"venue"
},
  "geometry": {"coordinates":[-99.9461898804,49.8477516174],"type":"Point"}
}