{
  "type": "Feature",
  "properties": {
    "addr:full":"904 George St Enderby BC V0E 1V0",
    "addr:housenumber":"904",
    "addr:postcode":"v0e 1v0",
    "addr:street":"George St",
    "iso:country":"CA",
    "sg:address":"904 George St",
    "sg:city":"Enderby",
    "sg:classifiers":[
        {
            "category":"Insurance",
            "subcategory":"Insurance Agent",
            "type":"Services"
        }
    ],
    "sg:phone":"+1 250 838 7333",
    "sg:postcode":"V0E 1V0",
    "sg:province":"BC",
    "wof:name":"Mc Leod Agencies Ltd",
    "wof:placetype":"venue"
},
  "geometry": {"coordinates":[-119.14031199999999,50.550407],"type":"Point"}
}