{
  "type": "Feature",
  "properties": {
    "addr:full":"2804 Sackville Dr Upper Sackville NS B4E 3C4",
    "addr:housenumber":"2804",
    "addr:postcode":"b4e 3c4",
    "addr:street":"Sackville Dr",
    "iso:country":"CA",
    "sg:address":"2804 Sackville Dr",
    "sg:city":"Upper Sackville",
    "sg:classifiers":[
        {
            "category":"Building & Trades",
            "subcategory":"Landscaping Services",
            "type":"Services"
        }
    ],
    "sg:phone":"+1 902 865 2676",
    "sg:postcode":"B4E 3C4",
    "sg:province":"NS",
    "sg:tags":[
        "landscape",
        "contractor"
    ],
    "wof:name":"Lockwood Water Gardens Design",
    "wof:placetype":"venue"
},
  "geometry": {"coordinates":[-63.776199,44.822342],"type":"Point"}
}