{
  "type": "Feature",
  "properties": {
    "addr:full":"Winchester ON K0C 2K0",
    "addr:postcode":"k0c 2k0",
    "iso:country":"CA",
    "sg:city":"Winchester",
    "sg:classifiers":[
        {
            "category":"Cinema",
            "subcategory":"Movie Rental",
            "type":"Entertainment"
        }
    ],
    "sg:phone":"+1 613 774 5858",
    "sg:postcode":"K0C 2K0",
    "sg:province":"ON",
    "sg:tags":[
        "leasing",
        "video",
        "disc",
        "tape"
    ],
    "wof:name":"Winchester Video",
    "wof:placetype":"venue"
},
  "geometry": {"coordinates":[-75.353638,45.092472],"type":"Point"}
}