{
  "type": "Feature",
  "properties": {
    "addr:full":"1504 Foster St White Rock BC V4B 3X8",
    "addr:housenumber":"1504",
    "addr:postcode":"v4b 3x8",
    "addr:street":"Foster St",
    "iso:country":"CA",
    "sg:address":"1504 Foster St",
    "sg:city":"White Rock",
    "sg:classifiers":[
        {
            "category":"Shopping",
            "subcategory":"Bicycles & Sporting Goods",
            "type":"Retail Goods"
        }
    ],
    "sg:phone":"+1 604 535 7287",
    "sg:postcode":"V4B 3X8",
    "sg:province":"BC",
    "wof:name":"Board Kennel",
    "wof:placetype":"venue"
},
  "geometry": {"coordinates":[-122.80358099999999,49.029598],"type":"Point"}
}