{
  "type": "Feature",
  "properties": {
    "iso:country":"CA",
    "sg:address":"91 Hart Dr",
    "sg:city":"Barrie",
    "sg:classifiers":[
        {
            "category":"Retail",
            "subcategory":"Auto Repair",
            "type":"Services"
        }
    ],
    "sg:phone":"+1 705 722 8600",
    "sg:postcode":"L4N 5M3",
    "sg:province":"ON",
    "sg:tags":[
        "truck"
    ],
    "wof:name":"Tri Truck Ctr Inc",
    "wof:placetype":"venue"
},
  "geometry": {"coordinates":[-79.71100616459999,44.3774642944],"type":"Point"}
}