{
  "type": "Feature",
  "properties": {
    "addr:full":"94 Rue Adrien-Robert Hull QC J8Y 3S2",
    "addr:housenumber":"94",
    "addr:postcode":"j8y 3s2",
    "addr:street":"Rue Adrien-Robert",
    "iso:country":"CA",
    "sg:address":"94 Rue Adrien-Robert",
    "sg:city":"Hull",
    "sg:classifiers":[
        {
            "category":"Manufacturing",
            "subcategory":"Food",
            "type":"Manufacturing & Wholesale Goods"
        }
    ],
    "sg:phone":"+1 819 777 6716",
    "sg:postcode":"J8Y 3S2",
    "sg:province":"QC",
    "sg:tags":[
        "health",
        "natural"
    ],
    "wof:name":"Soyarie",
    "wof:placetype":"venue"
},
  "geometry": {"coordinates":[-75.73455,45.457607],"type":"Point"}
}