{
  "type": "Feature",
  "properties": {
    "addr:full":"5720 198 St Langley BC V3A 7C7",
    "addr:housenumber":"5720",
    "addr:postcode":"v3a 7c7",
    "addr:street":"198 St",
    "iso:country":"CA",
    "sg:address":"5720 198 St",
    "sg:city":"Langley",
    "sg:classifiers":[
        {
            "category":"Manufacturing",
            "subcategory":"Metals",
            "type":"Manufacturing & Wholesale Goods"
        }
    ],
    "sg:phone":"+1 604 530 3154",
    "sg:postcode":"V3A 7C7",
    "sg:province":"BC",
    "sg:tags":[
        "plumbing",
        "fixture",
        "supply"
    ],
    "wof:name":"Fibrestone Mfg Inc",
    "wof:placetype":"venue"
},
  "geometry": {"coordinates":[-122.67318,49.106693],"type":"Point"}
}