{
  "type": "Feature",
  "properties": {
    "addr:full":"1269 Kingsway Sudbury ON P3B 2E9",
    "addr:housenumber":"1269",
    "addr:postcode":"p3b 2e9",
    "addr:street":"Kingsway",
    "iso:country":"CA",
    "sg:address":"1269 Kingsway",
    "sg:city":"Sudbury",
    "sg:classifiers":[
        {
            "category":"Manufacturing",
            "subcategory":"Glass & Minerals",
            "type":"Manufacturing & Wholesale Goods"
        }
    ],
    "sg:phone":"+1 705 566 9180",
    "sg:postcode":"P3B 2E9",
    "sg:province":"ON",
    "sg:tags":[
        "marble",
        "monument"
    ],
    "wof:name":"Artcraft Monumental Works Ltd",
    "wof:placetype":"venue"
},
  "geometry": {"coordinates":[-80.946281,46.504814],"type":"Point"}
}