{
  "type": "Feature",
  "properties": {
    "addr:full":"824 Wilson Ave North York ON M3K 1E5",
    "addr:housenumber":"824",
    "addr:postcode":"m3k 1e5",
    "addr:street":"Wilson Ave",
    "iso:country":"CA",
    "sg:address":"824 Wilson Ave",
    "sg:city":"North York",
    "sg:classifiers":[
        {
            "category":"Professional",
            "subcategory":"Employment Agencies",
            "type":"Services"
        }
    ],
    "sg:phone":"+1 416 789 5522",
    "sg:postcode":"M3K 1E5",
    "sg:province":"ON",
    "sg:tags":[
        "opportunity"
    ],
    "wof:name":"Adler Employment Agency Inc",
    "wof:placetype":"venue"
},
  "geometry": {"coordinates":[-79.46656,43.730835],"type":"Point"}
}