{
  "type": "Feature",
  "properties": {
    "addr:full":"208 Main St Semans SK S0A 3S0",
    "addr:housenumber":"208",
    "addr:postcode":"s0a 3s0",
    "addr:street":"Main St",
    "iso:country":"CA",
    "sg:address":"208 Main St",
    "sg:city":"Semans",
    "sg:classifiers":[
        {
            "category":"Travel",
            "subcategory":"Hotels & Motels",
            "type":"Entertainment"
        }
    ],
    "sg:phone":"+1 306 524 2210",
    "sg:postcode":"S0A 3S0",
    "sg:province":"SK",
    "wof:name":"Semans Hotel",
    "wof:placetype":"venue"
},
  "geometry": {"coordinates":[-104.725594,51.404812],"type":"Point"}
}