{
  "type": "Feature",
  "properties": {
    "iso:country":"CA",
    "sg:address":"5004 52 St",
    "sg:city":"Whitecourt",
    "sg:classifiers":[
        {
            "category":"Government",
            "subcategory":"Office",
            "type":"Public Place"
        }
    ],
    "sg:phone":"+1 780 778 2273",
    "sg:postcode":"T7S 1N2",
    "sg:province":"AB",
    "sg:tags":[
        "village"
    ],
    "wof:name":"Whitecourt Town Office",
    "wof:placetype":"venue"
},
  "geometry": {"coordinates":[-115.689086914,54.1416893005],"type":"Point"}
}