{
  "type": "Feature",
  "properties": {
    "iso:country":"CA",
    "sg:city":"Maple",
    "sg:classifiers":[
        {
            "category":"Building & Trades",
            "subcategory":"Landscaping Services",
            "type":"Services"
        }
    ],
    "sg:phone":"+1 905 832 6289",
    "sg:postcode":"L6A 1R3",
    "sg:province":"ON",
    "sg:tags":[
        "landscape",
        "contractor"
    ],
    "wof:name":"Sartor & Susin Erosion Control",
    "wof:placetype":"venue"
},
  "geometry": {"coordinates":[-79.509979,43.873325],"type":"Point"}
}