{
  "type": "Feature",
  "properties": {
    "addr:full":"148 Gurnett St Aurora ON L4G 1P8",
    "addr:housenumber":"148",
    "addr:postcode":"l4g 1p8",
    "addr:street":"Gurnett St",
    "iso:country":"CA",
    "sg:address":"148 Gurnett St",
    "sg:city":"Aurora",
    "sg:classifiers":[
        {
            "category":"Building & Trades",
            "subcategory":"Construction",
            "type":"Services"
        }
    ],
    "sg:phone":"+1 905 841 8103",
    "sg:postcode":"L4G 1P8",
    "sg:province":"ON",
    "sg:tags":[
        "painter"
    ],
    "wof:name":"Scott Dexter Painting & Decor",
    "wof:placetype":"venue"
},
  "geometry": {"coordinates":[-79.46468353269999,43.9938697815],"type":"Point"}
}