{
  "type": "Feature",
  "properties": {
    "addr:full":"255 Rue Principale E Magog QC J1X 1Y7",
    "addr:housenumber":"255",
    "addr:postcode":"j1x 1y7",
    "addr:street":"Rue Principale E",
    "iso:country":"CA",
    "sg:address":"255 Rue Principale E",
    "sg:city":"Magog",
    "sg:classifiers":[
        {
            "category":"Bars & Pubs",
            "type":"Food & Drink"
        }
    ],
    "sg:phone":"+1 819 843 2122",
    "sg:postcode":"J1X 1Y7",
    "sg:province":"QC",
    "sg:tags":[
        "lounge",
        "cocktail"
    ],
    "wof:name":"Bar DE L'Est",
    "wof:placetype":"venue"
},
  "geometry": {"coordinates":[-72.139771,45.263004],"type":"Point"}
}