{
  "type": "Feature",
  "properties": {
    "addr:full":"Head of Chezzetcook NS B0J 1N0",
    "addr:postcode":"b0j 1n0",
    "iso:country":"CA",
    "sg:city":"Head of Chezzetcook",
    "sg:classifiers":[
        {
            "category":"Home & Garden",
            "subcategory":"Carpets & Floor Coverings",
            "type":"Retail Goods"
        }
    ],
    "sg:phone":"+1 902 827 4417",
    "sg:postcode":"B0J 1N0",
    "sg:province":"NS",
    "sg:tags":[
        "material",
        "dealer",
        "rug"
    ],
    "wof:name":"Atlantic Carpet Concepts",
    "wof:placetype":"venue"
},
  "geometry": {"coordinates":[-63.237865448,44.7506942749],"type":"Point"}
}