{
  "type": "Feature",
  "properties": {
    "addr:full":"9494 Boul Saint-Laurent Montreal QC H2N 1P4",
    "addr:housenumber":"9494",
    "addr:postcode":"h2n 1p4",
    "addr:street":"Boul Saint-Laurent",
    "iso:country":"CA",
    "sg:address":"9494 Boul Saint-Laurent",
    "sg:city":"Montreal",
    "sg:classifiers":[
        {
            "category":"Real Estate",
            "subcategory":"Real Estate Agent",
            "type":"Services"
        }
    ],
    "sg:phone":"+1 514 389 6131",
    "sg:postcode":"H2N 1P4",
    "sg:province":"QC",
    "sg:tags":[
        "management"
    ],
    "wof:name":"Frankel Enterprises Ltd",
    "wof:placetype":"venue"
},
  "geometry": {"coordinates":[-73.654296875,45.5452651978],"type":"Point"}
}