{
  "type": "Feature",
  "properties": {
    "addr:full":"Mill Bay BC V0R 2P0",
    "addr:postcode":"v0r 2p0",
    "iso:country":"CA",
    "sg:city":"Mill Bay",
    "sg:classifiers":[
        {
            "category":"Organizations",
            "subcategory":"Professional Association",
            "type":"Services"
        }
    ],
    "sg:phone":"+1 250 743 7430",
    "sg:postcode":"V0R 2P0",
    "sg:province":"BC",
    "wof:name":"Malahat Te'Mexw",
    "wof:placetype":"venue"
},
  "geometry": {"coordinates":[-123.52821400000001,48.626877],"type":"Point"}
}