{
  "type": "Feature",
  "properties": {
    "addr:full":"Saskatoon SK S7M 2W5",
    "addr:postcode":"s7m 2w5",
    "iso:country":"CA",
    "sg:city":"Saskatoon",
    "sg:classifiers":[
        {
            "category":"Manufacturing",
            "subcategory":"Rubber & Plastics",
            "type":"Manufacturing & Wholesale Goods"
        }
    ],
    "sg:phone":"+1 306 683 1981",
    "sg:postcode":"S7M 2W5",
    "sg:province":"SK",
    "sg:tags":[
        "pipe"
    ],
    "wof:name":"Primary Containment Utilities",
    "wof:placetype":"venue"
},
  "geometry": {"coordinates":[-106.694297791,52.123664856],"type":"Point"}
}