{
  "type": "Feature",
  "properties": {
    "addr:full":"310 Main St Unity SK S0K 4L0",
    "addr:housenumber":"310",
    "addr:postcode":"s0k 4l0",
    "addr:street":"Main St",
    "iso:country":"CA",
    "sg:address":"310 Main St",
    "sg:city":"Unity",
    "sg:classifiers":[
        {
            "category":"Retail",
            "subcategory":"Laundry & Dry Cleaning",
            "type":"Services"
        }
    ],
    "sg:phone":"+1 306 228 2100",
    "sg:postcode":"S0K 4L0",
    "sg:province":"SK",
    "sg:tags":[
        "cleaners"
    ],
    "wof:name":"Fresh & Brite Drycleaners",
    "wof:placetype":"venue"
},
  "geometry": {"coordinates":[-109.15763099999999,52.443081],"type":"Point"}
}