{
  "type": "Feature",
  "properties": {
    "addr:full":"4055 Av Saint-Jean-Baptiste Quebec QC G2E 2K3",
    "addr:housenumber":"4055",
    "addr:postcode":"qc g2e 2k3",
    "addr:street":"Av Saint-Jean-Baptiste",
    "iso:country":"CA",
    "sg:address":"4055 Av Saint-Jean-Baptiste",
    "sg:city":"Quebec",
    "sg:classifiers":[
        {
            "category":"Shopping",
            "type":"Retail Goods"
        }
    ],
    "sg:phone":"+1 418 570 8650",
    "sg:postcode":"G2E 2K3",
    "sg:province":"QC",
    "sg:tags":[
        "art",
        "gallery",
        "dealer"
    ],
    "wof:name":"Galerie D'Art Rosart",
    "wof:placetype":"venue"
},
  "geometry": {"coordinates":[-71.340569,46.809681],"type":"Point"}
}