{
  "type": "Feature",
  "properties": {
    "addr:full":"869 Dundas St W Toronto ON M6J 1V6",
    "addr:housenumber":"869",
    "addr:postcode":"m6j 1v6",
    "addr:street":"Dundas St W",
    "iso:country":"CA",
    "sg:address":"869 Dundas St W",
    "sg:city":"Toronto",
    "sg:classifiers":[
        {
            "category":"Restaurant",
            "type":"Food & Drink"
        }
    ],
    "sg:phone":"+1 416 603 2515",
    "sg:postcode":"M6J 1V6",
    "sg:province":"ON",
    "wof:name":"Churrasqueira Vila Verdense",
    "wof:placetype":"venue"
},
  "geometry": {"coordinates":[-79.41059112550001,43.6512298584],"type":"Point"}
}