{
  "type": "Feature",
  "properties": {
    "addr:full":"646 Drum Rd Pontypool ON L0A 1K0",
    "addr:housenumber":"646",
    "addr:postcode":"l0a 1k0",
    "addr:street":"Drum Rd",
    "iso:country":"CA",
    "sg:address":"646 Drum Rd",
    "sg:city":"Pontypool",
    "sg:classifiers":[
        {
            "category":"Food & Beverages",
            "subcategory":"Liquor & Beverages",
            "type":"Retail Goods"
        }
    ],
    "sg:phone":"+1 705 277 3131",
    "sg:postcode":"L0A 1K0",
    "sg:province":"ON",
    "sg:tags":[
        "store"
    ],
    "wof:name":"Liquor Control Board of Ont",
    "wof:placetype":"venue"
},
  "geometry": {"coordinates":[-78.62841033940001,44.100479126],"type":"Point"}
}