{
  "type": "Feature",
  "properties": {
    "addr:full":"3853 Rue Colbert Jonquiere QC G7X 0E6",
    "addr:housenumber":"3853",
    "addr:postcode":"g7x 0e6",
    "addr:street":"Rue Colbert",
    "iso:country":"CA",
    "sg:address":"3853 Rue Colbert",
    "sg:city":"Jonquiere",
    "sg:classifiers":[
        {
            "category":"Building & Trades",
            "subcategory":"Electrical",
            "type":"Services"
        }
    ],
    "sg:phone":"+1 418 542 6941",
    "sg:postcode":"G7X 0E6",
    "sg:province":"QC",
    "sg:tags":[
        "electric",
        "contractor"
    ],
    "wof:name":"Econo-Watt Inc",
    "wof:placetype":"venue"
},
  "geometry": {"coordinates":[-71.252876,48.411381],"type":"Point"}
}