{
  "type": "Feature",
  "properties": {
    "addr:full":"8614 98 St Grande Prairie AB T8V 2C6",
    "addr:housenumber":"8614",
    "addr:postcode":"t8v 2c6",
    "addr:street":"98 St",
    "iso:country":"CA",
    "sg:address":"8614 98 St",
    "sg:city":"Grande Prairie",
    "sg:classifiers":[
        {
            "category":"Building & Trades",
            "subcategory":"Construction",
            "type":"Services"
        }
    ],
    "sg:phone":"+1 780 532 5226",
    "sg:postcode":"T8V 2C6",
    "sg:province":"AB",
    "sg:tags":[
        "masonry",
        "stucco",
        "contractor"
    ],
    "wof:name":"Contemporary Stucco Systems",
    "wof:placetype":"venue"
},
  "geometry": {"coordinates":[-118.789124,55.157597],"type":"Point"}
}