{
  "type": "Feature",
  "properties": {
    "addr:full":"7250 Boul Arthur-Sauve Laval QC H7R 3X9",
    "addr:housenumber":"7250",
    "addr:postcode":"h7r 3x9",
    "addr:street":"Boul Arthur-Sauve",
    "iso:country":"CA",
    "sg:address":"7250 Boul Arthur-Sauve",
    "sg:city":"Laval",
    "sg:classifiers":[
        {
            "category":"Building & Trades",
            "subcategory":"Plumbing",
            "type":"Services"
        }
    ],
    "sg:phone":"+1 450 627 4717",
    "sg:postcode":"H7R 3X9",
    "sg:province":"QC",
    "sg:tags":[
        "air",
        "cleaning",
        "contractor",
        "system",
        "conditioning"
    ],
    "wof:name":"James O'Brien & Fils Ltee",
    "wof:placetype":"venue"
},
  "geometry": {"coordinates":[-73.86247299999999,45.545456],"type":"Point"}
}