{
  "type": "Feature",
  "properties": {
    "iso:country":"CA",
    "sg:city":"Val-Morin",
    "sg:classifiers":[
        {
            "category":"Bars & Pubs",
            "type":"Food & Drink"
        }
    ],
    "sg:phone":"+1 819 322 5622",
    "sg:postcode":"J0T 2R0",
    "sg:province":"QC",
    "sg:tags":[
        "lounge",
        "cocktail"
    ],
    "wof:name":"Bar LA Source",
    "wof:placetype":"venue"
},
  "geometry": {"coordinates":[-74.1962509155,45.9917907715],"type":"Point"}
}