{
  "type": "Feature",
  "properties": {
    "addr:full":"261 Bethune Cres Goderich ON N7A 4M6",
    "addr:housenumber":"261",
    "addr:postcode":"n7a 4m6",
    "addr:street":"Bethune Cres",
    "iso:country":"CA",
    "sg:address":"261 Bethune Cres",
    "sg:city":"Goderich",
    "sg:classifiers":[
        {
            "category":"Health Services",
            "subcategory":"Nursing And Care Facility",
            "type":"Services"
        }
    ],
    "sg:phone":"+1 519 524 6161",
    "sg:postcode":"N7A 4M6",
    "sg:province":"ON",
    "sg:tags":[
        "home",
        "retirement",
        "general",
        "community",
        "contractor"
    ],
    "wof:name":"Southcove Developments Inc",
    "wof:placetype":"venue"
},
  "geometry": {"coordinates":[-81.722984314,43.7283248901],"type":"Point"}
}