{
  "type": "Feature",
  "properties": {
    "addr:full":"32 Heathrow Crt Markham ON L3R 3T8",
    "addr:housenumber":"32",
    "addr:postcode":"l3r 3t8",
    "addr:street":"Heathrow Crt",
    "iso:country":"CA",
    "sg:address":"32 Heathrow Crt",
    "sg:city":"Markham",
    "sg:classifiers":[
        {
            "category":"Professional",
            "subcategory":"Computer Services",
            "type":"Services"
        }
    ],
    "sg:phone":"+1 905 477 7243",
    "sg:postcode":"L3R 3T8",
    "sg:province":"ON",
    "sg:tags":[
        "consultant"
    ],
    "wof:name":"Tools Not Toys Technologies",
    "wof:placetype":"venue"
},
  "geometry": {"coordinates":[-79.3133850098,43.8325080872],"type":"Point"}
}