{
  "type": "Feature",
  "properties": {
    "addr:full":"65 Arthur St S Elmira ON N3B 2M6",
    "addr:housenumber":"65",
    "addr:postcode":"n3b 2m6",
    "addr:street":"Arthur St S",
    "iso:country":"CA",
    "sg:address":"65 Arthur St S",
    "sg:city":"Elmira",
    "sg:classifiers":[
        {
            "category":"Education",
            "subcategory":"Library",
            "type":"Public Place"
        }
    ],
    "sg:phone":"+1 519 669 5477",
    "sg:postcode":"N3B 2M6",
    "sg:province":"ON",
    "wof:name":"Elmira Branch Library",
    "wof:placetype":"venue"
},
  "geometry": {"coordinates":[-80.5588607788,43.5981788635],"type":"Point"}
}