{
  "type": "Feature",
  "properties": {
    "iso:country":"CA",
    "sg:address":"453 12th Ave W",
    "sg:city":"Vancouver",
    "sg:classifiers":[
        {
            "category":"Government",
            "subcategory":"Office",
            "type":"Public Place"
        }
    ],
    "sg:phone":"+1 604 873 7330",
    "sg:postcode":"V5Y 1V4",
    "sg:province":"BC",
    "sg:tags":[
        "village"
    ],
    "wof:name":"Vancouver Land Survey Info",
    "wof:placetype":"venue"
},
  "geometry": {"coordinates":[-123.114074707,49.2605743408],"type":"Point"}
}