{
  "type": "Feature",
  "properties": {
    "addr:full":"43 Rossland Ave Nepean ON K2G 2K5",
    "addr:housenumber":"43",
    "addr:postcode":"k2g 2k5",
    "addr:street":"Rossland Ave",
    "iso:country":"CA",
    "sg:address":"43 Rossland Ave",
    "sg:city":"Nepean",
    "sg:classifiers":[
        {
            "category":"Professional",
            "subcategory":"Business Services",
            "type":"Services"
        }
    ],
    "sg:phone":"+1 613 225 5345",
    "sg:postcode":"K2G 2K5",
    "sg:province":"ON",
    "sg:tags":[
        "water",
        "treatment"
    ],
    "wof:name":"Everpure Drinking Water System",
    "wof:placetype":"venue"
},
  "geometry": {"coordinates":[-75.7404556274,45.3529624939],"type":"Point"}
}