{
  "type": "Feature",
  "properties": {
    "addr:full":"572 Bloor St W Toronto ON M6G 1K1",
    "addr:housenumber":"572",
    "addr:postcode":"m6g 1k1",
    "addr:street":"Bloor St W",
    "iso:country":"CA",
    "sg:address":"572 Bloor St W",
    "sg:city":"Toronto",
    "sg:classifiers":[
        {
            "category":"Shopping",
            "subcategory":"Shoes",
            "type":"Retail Goods"
        }
    ],
    "sg:phone":"+1 416 537 0398",
    "sg:postcode":"M6G 1K1",
    "sg:province":"ON",
    "wof:name":"Payless Shoe Source",
    "wof:placetype":"venue"
},
  "geometry": {"coordinates":[-79.412064,43.665073],"type":"Point"}
}