{
  "type": "Feature",
  "properties": {
    "iso:country":"CA",
    "sg:address":"1019 Rang Chemin Gaudet",
    "sg:city":"Saint-Jacques",
    "sg:classifiers":[
        {
            "category":"Building & Trades",
            "subcategory":"Landscaping Services",
            "type":"Services"
        }
    ],
    "sg:phone":"+1 450 839 7634",
    "sg:postcode":"J0K 2R0",
    "sg:province":"QC",
    "sg:tags":[
        "grounds",
        "lawn",
        "general",
        "maintenance",
        "contractor"
    ],
    "wof:name":"Coutu, Roger",
    "wof:placetype":"venue"
},
  "geometry": {"coordinates":[-73.56908416749999,45.9470558167],"type":"Point"}
}