{
  "type": "Feature",
  "properties": {
    "iso:country":"CA",
    "sg:address":"250 Rue Saint-Thomas",
    "sg:city":"Salaberry-DE-Valleyfield",
    "sg:classifiers":[
        {
            "category":"Social Services",
            "subcategory":"Child Care",
            "type":"Services"
        }
    ],
    "sg:phone":"+1 450 371 2723",
    "sg:postcode":"J6T 6H6",
    "sg:province":"QC",
    "wof:name":"Cpe Citronnelle",
    "wof:placetype":"venue"
},
  "geometry": {"coordinates":[-74.128151,45.248268],"type":"Point"}
}