{
  "type": "Feature",
  "properties": {
    "addr:full":"1426 19 Ave NW Calgary AB T2M 1A6",
    "addr:housenumber":"1426",
    "addr:postcode":"t2m 1a6",
    "addr:street":"19 Ave Nw",
    "iso:country":"CA",
    "sg:address":"1426 19 Ave NW",
    "sg:city":"Calgary",
    "sg:classifiers":[
        {
            "category":"Health Services",
            "subcategory":"Doctor",
            "type":"Services"
        }
    ],
    "sg:phone":"+1 403 289 6161",
    "sg:postcode":"T2M 1A6",
    "sg:province":"AB",
    "sg:tags":[
        "physician",
        "surgeon"
    ],
    "wof:name":"Lad Clinic",
    "wof:placetype":"venue"
},
  "geometry": {"coordinates":[-114.092911,51.069824],"type":"Point"}
}