{
  "type": "Feature",
  "properties": {
    "addr:full":"Saint-Joseph-Du-Lac QC J0N 1M0",
    "addr:postcode":"j0n 1m0",
    "iso:country":"CA",
    "sg:city":"Saint-Joseph-Du-Lac",
    "sg:classifiers":[
        {
            "category":"Building & Trades",
            "subcategory":"Construction",
            "type":"Services"
        }
    ],
    "sg:phone":"+1 450 491 3039",
    "sg:postcode":"J0N 1M0",
    "sg:province":"QC",
    "sg:tags":[
        "repairing",
        "contractor",
        "remodeling",
        "general"
    ],
    "wof:name":"Construction Confort Inc",
    "wof:placetype":"venue"
},
  "geometry": {"coordinates":[-73.987747,45.523621],"type":"Point"}
}