{
  "type": "Feature",
  "properties": {
    "addr:full":"1840 Commercial Dr Vancouver BC V5N 4A5",
    "addr:housenumber":"1840",
    "addr:postcode":"v5n 4a5",
    "addr:street":"Commercial Dr",
    "iso:country":"CA",
    "sg:address":"1840 Commercial Dr",
    "sg:city":"Vancouver",
    "sg:classifiers":[
        {
            "category":"Personal",
            "subcategory":"Beauty Salon",
            "type":"Services"
        }
    ],
    "sg:phone":"+1 604 251 7187",
    "sg:postcode":"V5N 4A5",
    "sg:province":"BC",
    "wof:name":"Deja Vu Intl Hair Studio Inc",
    "wof:placetype":"venue"
},
  "geometry": {"coordinates":[-123.06955719,49.2683105469],"type":"Point"}
}