{
  "type": "Feature",
  "properties": {
    "addr:full":"LA Ronge SK S0J 1L0",
    "addr:postcode":"s0j 1l0",
    "iso:country":"CA",
    "sg:city":"LA Ronge",
    "sg:classifiers":[
        {
            "category":"Taxi",
            "type":"Transportation"
        }
    ],
    "sg:phone":"+1 306 425 3500",
    "sg:postcode":"S0J 1L0",
    "sg:province":"SK",
    "sg:tags":[
        "taxicab"
    ],
    "wof:name":"L A Family Taxi",
    "wof:placetype":"venue"
},
  "geometry": {"coordinates":[-105.295326233,55.1124954224],"type":"Point"}
}