{
  "type": "Feature",
  "properties": {
    "addr:full":"Angus ON L0M 1B0",
    "addr:postcode":"l0m 1b0",
    "iso:country":"CA",
    "sg:city":"Angus",
    "sg:classifiers":[
        {
            "category":"Food & Beverages",
            "subcategory":"Groceries & Convenience Stores",
            "type":"Retail Goods"
        }
    ],
    "sg:phone":"+1 705 424 6515",
    "sg:postcode":"L0M 1B0",
    "sg:province":"ON",
    "sg:tags":[
        "grocer"
    ],
    "wof:name":"Angus Variety",
    "wof:placetype":"venue"
},
  "geometry": {"coordinates":[-79.885277,44.316509],"type":"Point"}
}