{
  "type": "Feature",
  "properties": {
    "addr:full":"125 Av Saint-Charles Vaudreuil-Dorion QC J7V 2K7",
    "addr:housenumber":"125",
    "addr:postcode":"j7v 2k7",
    "addr:street":"Av Saint-Charles",
    "iso:country":"CA",
    "sg:address":"125 Av Saint-Charles",
    "sg:city":"Vaudreuil-Dorion",
    "sg:classifiers":[
        {
            "category":"Restaurant",
            "type":"Food & Drink"
        }
    ],
    "sg:phone":"+1 450 455 6421",
    "sg:postcode":"J7V 2K7",
    "sg:province":"QC",
    "wof:name":"Restauroute",
    "wof:placetype":"venue"
},
  "geometry": {"coordinates":[-74.0121688843,45.3866920471],"type":"Point"}
}