{
  "type": "Feature",
  "properties": {
    "addr:full":"Vancouver BC V5Z 1K1",
    "addr:postcode":"v5z 1k1",
    "iso:country":"CA",
    "sg:city":"Vancouver",
    "sg:classifiers":[
        {
            "category":"Health Services",
            "subcategory":"Doctor",
            "type":"Services"
        }
    ],
    "sg:phone":"+1 604 879 0661",
    "sg:postcode":"V5Z 1K1",
    "sg:province":"BC",
    "sg:tags":[
        "dentist"
    ],
    "wof:name":"Van Endo Group",
    "wof:placetype":"venue"
},
  "geometry": {"coordinates":[-123.122169,49.263489],"type":"Point"}
}