{
  "type": "Feature",
  "properties": {
    "addr:full":"High Level AB T0H 1Z0",
    "addr:postcode":"t0h 1z0",
    "iso:country":"CA",
    "sg:city":"High Level",
    "sg:classifiers":[
        {
            "category":"Health Services",
            "subcategory":"Hospital",
            "type":"Services"
        }
    ],
    "sg:phone":"+1 780 926 3791",
    "sg:postcode":"T0H 1Z0",
    "sg:province":"AB",
    "wof:name":"High Level General Hospital",
    "wof:placetype":"venue"
},
  "geometry": {"coordinates":[-117.141990662,58.5156326294],"type":"Point"}
}