{
  "type": "Feature",
  "properties": {
    "addr:full":"PO Box 1463 STN Main Cochrane AB T4C 1B4",
    "addr:housenumber":"po",
    "addr:postcode":"t4c 1b4",
    "addr:street":"Box 1463 Stn Main",
    "iso:country":"CA",
    "sg:address":"PO Box 1463 STN Main",
    "sg:city":"Cochrane",
    "sg:classifiers":[
        {
            "category":"Recreation",
            "type":"Entertainment"
        }
    ],
    "sg:phone":"+1 403 932 3299",
    "sg:postcode":"T4C 1B4",
    "sg:province":"AB",
    "sg:tags":[
        "stable"
    ],
    "wof:name":"Saddle Peak Trail Rides Ltd",
    "wof:placetype":"venue"
},
  "geometry": {"coordinates":[-114.46800231900001,51.190826416],"type":"Point"}
}