{
  "type": "Feature",
  "properties": {
    "addr:full":"1821 8th St E Saskatoon SK S7H 0T4",
    "addr:housenumber":"1821",
    "addr:postcode":"s7h 0t4",
    "addr:street":"8Th St E",
    "iso:country":"CA",
    "sg:address":"1821 8th St E",
    "sg:city":"Saskatoon",
    "sg:classifiers":[
        {
            "category":"Retail",
            "subcategory":"Auto Repair",
            "type":"Services"
        }
    ],
    "sg:phone":"+1 306 374 2425",
    "sg:postcode":"S7H 0T4",
    "sg:province":"SK",
    "sg:tags":[
        "repairing",
        "automobile"
    ],
    "wof:name":"Kal Tire",
    "wof:placetype":"venue"
},
  "geometry": {"coordinates":[-106.629013062,52.1150779724],"type":"Point"}
}