{
  "type": "Feature",
  "properties": {
    "addr:full":"Saint-Damien-DE-Buckland QC G0R 2Y0",
    "addr:postcode":"g0r 2y0",
    "iso:country":"CA",
    "sg:city":"Saint-Damien-DE-Buckland",
    "sg:classifiers":[
        {
            "category":"Education",
            "subcategory":"School",
            "type":"Public Place"
        }
    ],
    "sg:phone":"+1 418 789 2871",
    "sg:postcode":"G0R 2Y0",
    "sg:province":"QC",
    "wof:name":"Ecole Rayons DE Soleil",
    "wof:placetype":"venue"
},
  "geometry": {"coordinates":[-70.655449,46.622799],"type":"Point"}
}