{
  "type": "Feature",
  "properties": {
    "addr:full":"Oakville ON L6L 2X8",
    "addr:postcode":"l6l 2x8",
    "iso:country":"CA",
    "sg:city":"Oakville",
    "sg:classifiers":[
        {
            "category":"Manufacturing",
            "subcategory":"Metals",
            "type":"Manufacturing & Wholesale Goods"
        }
    ],
    "sg:phone":"+1 905 825 5151",
    "sg:postcode":"L6L 2X8",
    "sg:province":"ON",
    "sg:tags":[
        "door"
    ],
    "wof:name":"Englelake Limited",
    "wof:placetype":"venue"
},
  "geometry": {"coordinates":[-79.7212295532,43.4144325256],"type":"Point"}
}