{
  "type": "Feature",
  "properties": {
    "addr:full":"Vancouver BC V6J 1G5",
    "addr:postcode":"v6j 1g5",
    "iso:country":"CA",
    "sg:city":"Vancouver",
    "sg:classifiers":[
        {
            "category":"Real Estate",
            "subcategory":"Architect",
            "type":"Services"
        }
    ],
    "sg:phone":"+1 604 732 4545",
    "sg:postcode":"V6J 1G5",
    "sg:province":"BC",
    "wof:name":"Eric Stine Architects Inc",
    "wof:placetype":"venue"
},
  "geometry": {"coordinates":[-123.14705658,49.2704429626],"type":"Point"}
}