{
  "type": "Feature",
  "properties": {
    "addr:full":"36 Erin Meadow Green SE Calgary AB T2B 3G3",
    "addr:housenumber":"36",
    "addr:postcode":"t2b 3g3",
    "addr:street":"Erin Meadow Green Se",
    "iso:country":"CA",
    "sg:address":"36 Erin Meadow Green SE",
    "sg:city":"Calgary",
    "sg:classifiers":[
        {
            "category":"Professional",
            "subcategory":"Detective & Security Services",
            "type":"Services"
        }
    ],
    "sg:phone":"+1 403 248 5999",
    "sg:postcode":"T2B 3G3",
    "sg:province":"AB",
    "sg:tags":[
        "guard",
        "patrol"
    ],
    "wof:name":"Local Crew & Security Svc Inc",
    "wof:placetype":"venue"
},
  "geometry": {"coordinates":[-113.964989,51.02002],"type":"Point"}
}