{
  "type": "Feature",
  "properties": {
    "addr:full":"341 Av Lafleur Lasalle QC H8R 3H3",
    "addr:postcode":"h8r 3h3",
    "addr:street":"341 Av Lafleur",
    "iso:country":"CA",
    "sg:address":"341 Av Lafleur",
    "sg:city":"Lasalle",
    "sg:classifiers":[
        {
            "category":"Retail",
            "subcategory":"Auto Rental",
            "type":"Services"
        }
    ],
    "sg:phone":"+1 514 595 4479",
    "sg:postcode":"H8R 3H3",
    "sg:province":"QC",
    "sg:tags":[
        "renting",
        "truck",
        "leasing"
    ],
    "wof:name":"U-Haul Cie Ltee",
    "wof:placetype":"venue"
},
  "geometry": {"coordinates":[-73.647415,45.429794],"type":"Point"}
}