{
  "type": "Feature",
  "properties": {
    "addr:full":"5361 Glebe St # C Halifax NS B3K 2P9",
    "addr:housenumber":"5361",
    "addr:postcode":"b3k 2p9",
    "addr:street":"Glebe St # C",
    "iso:country":"CA",
    "sg:address":"5361 Glebe St # C",
    "sg:city":"Halifax",
    "sg:classifiers":[
        {
            "category":"Organizations",
            "subcategory":"Non-profit Organization",
            "type":"Services"
        }
    ],
    "sg:phone":"+1 902 492 3000",
    "sg:postcode":"B3K 2P9",
    "sg:province":"NS",
    "sg:tags":[
        "charitable",
        "institution"
    ],
    "wof:name":"Sisters of Svc",
    "wof:placetype":"venue"
},
  "geometry": {"coordinates":[-63.6091117859,44.6726264954],"type":"Point"}
}