{
  "type": "Feature",
  "properties": {
    "addr:full":"Bonaventure QC G0C 1E0",
    "addr:postcode":"g0c 1e0",
    "iso:country":"CA",
    "sg:city":"Bonaventure",
    "sg:classifiers":[
        {
            "category":"Government",
            "subcategory":"Office",
            "type":"Public Place"
        }
    ],
    "sg:phone":"+1 418 534 3246",
    "sg:postcode":"G0C 1E0",
    "sg:province":"QC",
    "sg:tags":[
        "municipality"
    ],
    "wof:name":"Municipalite DE Bonaventure",
    "wof:placetype":"venue"
},
  "geometry": {"coordinates":[-65.4898300171,48.0430984497],"type":"Point"}
}