{
  "type": "Feature",
  "properties": {
    "addr:full":"415 Mount Pleasant Rd Toronto ON M4S 2L5",
    "addr:housenumber":"415",
    "addr:postcode":"m4s 2l5",
    "addr:street":"Mount Pleasant Rd",
    "iso:country":"CA",
    "sg:address":"415 Mount Pleasant Rd",
    "sg:city":"Toronto",
    "sg:classifiers":[
        {
            "category":"Restaurant",
            "type":"Food & Drink"
        }
    ],
    "sg:phone":"+1 416 481 0900",
    "sg:postcode":"M4S 2L5",
    "sg:province":"ON",
    "wof:name":"Kfc",
    "wof:placetype":"venue"
},
  "geometry": {"coordinates":[-79.3864822388,43.699092865],"type":"Point"}
}