{
  "type": "Feature",
  "properties": {
    "addr:full":"221 Mary St Orillia ON L3V 3E5",
    "addr:housenumber":"221",
    "addr:postcode":"l3v 3e5",
    "addr:street":"Mary St",
    "iso:country":"CA",
    "sg:address":"221 Mary St",
    "sg:city":"Orillia",
    "sg:classifiers":[
        {
            "category":"Education",
            "subcategory":"Special Training",
            "type":"Public Place"
        }
    ],
    "sg:phone":"+1 705 329 0291",
    "sg:postcode":"L3V 3E5",
    "sg:province":"ON",
    "sg:tags":[
        "instruction",
        "driving"
    ],
    "wof:name":"Airdrie Driving Academy",
    "wof:placetype":"venue"
},
  "geometry": {"coordinates":[-79.428558,44.605621],"type":"Point"}
}