{
  "type": "Feature",
  "properties": {
    "addr:full":"22 Maple Way Sharon ON L0G 1V0",
    "addr:housenumber":"22",
    "addr:postcode":"l0g 1v0",
    "addr:street":"Maple Way",
    "iso:country":"CA",
    "sg:address":"22 Maple Way",
    "sg:city":"Sharon",
    "sg:classifiers":[
        {
            "category":"Building & Trades",
            "subcategory":"Construction",
            "type":"Services"
        }
    ],
    "sg:phone":"+1 905 478 1611",
    "sg:postcode":"L0G 1V0",
    "sg:province":"ON",
    "sg:tags":[
        "general",
        "contractor"
    ],
    "wof:name":"Krakatoa",
    "wof:placetype":"venue"
},
  "geometry": {"coordinates":[-79.436966,44.097084],"type":"Point"}
}