{
  "type": "Feature",
  "properties": {
    "addr:full":"642 Rue DE Courcelle Montreal QC H4C 3C5",
    "addr:housenumber":"642",
    "addr:postcode":"h4c 3c5",
    "addr:street":"Rue De Courcelle",
    "iso:country":"CA",
    "sg:address":"642 Rue DE Courcelle",
    "sg:city":"Montreal",
    "sg:classifiers":[
        {
            "category":"Wholesale",
            "subcategory":"Furniture",
            "type":"Manufacturing & Wholesale Goods"
        }
    ],
    "sg:phone":"+1 514 934 9274",
    "sg:postcode":"H4C 3C5",
    "sg:province":"QC",
    "wof:name":"Kiosk Design Inc",
    "wof:placetype":"venue"
},
  "geometry": {"coordinates":[-73.5916671753,45.473941803],"type":"Point"}
}