{
  "type": "Feature",
  "properties": {
    "addr:full":"9289 Boul Pie-Ix Montreal QC H1Z 3W4",
    "addr:housenumber":"9289",
    "addr:postcode":"h1z 3w4",
    "addr:street":"Boul Pie-Ix",
    "iso:country":"CA",
    "sg:address":"9289 Boul Pie-Ix",
    "sg:city":"Montreal",
    "sg:classifiers":[
        {
            "category":"Wholesale",
            "subcategory":"Meat",
            "type":"Manufacturing & Wholesale Goods"
        }
    ],
    "sg:phone":"+1 514 322 8000",
    "sg:postcode":"H1Z 3W4",
    "sg:province":"QC",
    "sg:tags":[
        "butchering"
    ],
    "wof:name":"Boucherie Fortin Inc",
    "wof:placetype":"venue"
},
  "geometry": {"coordinates":[-73.624863,45.581455],"type":"Point"}
}