{
  "type": "Feature",
  "properties": {
    "addr:full":"Merritt BC V1K 1B8",
    "addr:postcode":"v1k 1b8",
    "iso:country":"CA",
    "sg:city":"Merritt",
    "sg:classifiers":[
        {
            "category":"Manufacturing",
            "subcategory":"Printing",
            "type":"Manufacturing & Wholesale Goods"
        }
    ],
    "sg:phone":"+1 250 378 6808",
    "sg:postcode":"V1K 1B8",
    "sg:province":"BC",
    "sg:tags":[
        "printer"
    ],
    "wof:name":"Merritt Printing",
    "wof:placetype":"venue"
},
  "geometry": {"coordinates":[-120.78706359900001,50.1104164124],"type":"Point"}
}