{
  "type": "Feature",
  "properties": {
    "addr:full":"38 Tilley Rd Gagetown NB E5M 1A8",
    "addr:housenumber":"38",
    "addr:postcode":"e5m 1a8",
    "addr:street":"Tilley Rd",
    "iso:country":"CA",
    "sg:address":"38 Tilley Rd",
    "sg:city":"Gagetown",
    "sg:classifiers":[
        {
            "category":"Restaurant",
            "type":"Food & Drink"
        }
    ],
    "sg:phone":"+1 506 488 9806",
    "sg:postcode":"E5M 1A8",
    "sg:province":"NB",
    "wof:name":"Creek View",
    "wof:placetype":"venue"
},
  "geometry": {"coordinates":[-66.15239,45.778137],"type":"Point"}
}