{
  "type": "Feature",
  "properties": {
    "addr:full":"44 Av Glencoe Outremont QC H3T 1P9",
    "addr:postcode":"h3t 1p9",
    "addr:street":"44 Av Glencoe",
    "iso:country":"CA",
    "sg:address":"44 Av Glencoe",
    "sg:city":"Outremont",
    "sg:classifiers":[
        {
            "category":"Health Services",
            "subcategory":"Health Practitioner",
            "type":"Services"
        }
    ],
    "sg:phone":"+1 514 738 6061",
    "sg:postcode":"H3T 1P9",
    "sg:province":"QC",
    "sg:tags":[
        "psychologist"
    ],
    "wof:name":"Cuddihy, L Larose",
    "wof:placetype":"venue"
},
  "geometry": {"coordinates":[-73.61518100000001,45.510712],"type":"Point"}
}