{
  "type": "Feature",
  "properties": {
    "addr:full":"174 Mary St Port Perry ON L9L 1B7",
    "addr:housenumber":"174",
    "addr:postcode":"l9l 1b7",
    "addr:street":"Mary St",
    "iso:country":"CA",
    "sg:address":"174 Mary St",
    "sg:city":"Port Perry",
    "sg:classifiers":[
        {
            "category":"Banks & Credit Unions",
            "subcategory":"Bank",
            "type":"Services"
        }
    ],
    "sg:phone":"+1 905 985 4777",
    "sg:postcode":"L9L 1B7",
    "sg:province":"ON",
    "sg:tags":[
        "financing"
    ],
    "wof:name":"Venturetrend Management Inc",
    "wof:placetype":"venue"
},
  "geometry": {"coordinates":[-78.94293999999999,44.103851],"type":"Point"}
}