{
  "type": "Feature",
  "properties": {
    "addr:full":"340 Boul Cartier O Laval QC H7N 2J6",
    "addr:housenumber":"340",
    "addr:postcode":"h7n 2j6",
    "addr:street":"Boul Cartier O",
    "iso:country":"CA",
    "sg:address":"340 Boul Cartier O",
    "sg:city":"Laval",
    "sg:classifiers":[
        {
            "category":"Education",
            "subcategory":"Dance Studio",
            "type":"Public Place"
        }
    ],
    "sg:phone":"+1 450 663 1668",
    "sg:postcode":"H7N 2J6",
    "sg:province":"QC",
    "sg:tags":[
        "instruction",
        "dancing"
    ],
    "wof:name":"Maison DE Ballet Theatre",
    "wof:placetype":"venue"
},
  "geometry": {"coordinates":[-73.70766448969999,45.5518112183],"type":"Point"}
}