{
  "type": "Feature",
  "properties": {
    "addr:full":"1580 Rue Soucy Saint-Hubert QC J4T 1A3",
    "addr:housenumber":"1580",
    "addr:postcode":"j4t 1a3",
    "addr:street":"Rue Soucy",
    "iso:country":"CA",
    "sg:address":"1580 Rue Soucy",
    "sg:city":"Saint-Hubert",
    "sg:classifiers":[
        {
            "category":"Retail",
            "subcategory":"Repair Shop",
            "type":"Services"
        }
    ],
    "sg:phone":"+1 450 676 1321",
    "sg:postcode":"J4T 1A3",
    "sg:province":"QC",
    "sg:tags":[
        "upholsterer"
    ],
    "wof:name":"Abco Rembourrage Inc",
    "wof:placetype":"venue"
},
  "geometry": {"coordinates":[-73.4465560913,45.4975585938],"type":"Point"}
}