{
  "type": "Feature",
  "properties": {
    "addr:full":"201 St Laurent Ave Quesnel BC V2J 2C8",
    "addr:housenumber":"201",
    "addr:postcode":"v2j 2c8",
    "addr:street":"St Laurent Ave",
    "iso:country":"CA",
    "sg:address":"201 St Laurent Ave",
    "sg:city":"Quesnel",
    "sg:classifiers":[
        {
            "category":"Banks & Credit Unions",
            "subcategory":"Bank",
            "type":"Services"
        }
    ],
    "sg:phone":"+1 250 992 2127",
    "sg:postcode":"V2J 2C8",
    "sg:province":"BC",
    "wof:name":"Royal Bank Financial Group",
    "wof:placetype":"venue"
},
  "geometry": {"coordinates":[-122.498207092,52.9790153503],"type":"Point"}
}