{
  "type": "Feature",
  "properties": {
    "addr:full":"Macamic QC J0Z 2S0",
    "addr:postcode":"j0z 2s0",
    "iso:country":"CA",
    "sg:city":"Macamic",
    "sg:classifiers":[
        {
            "category":"Building & Trades",
            "subcategory":"Construction",
            "type":"Services"
        }
    ],
    "sg:phone":"+1 819 782 2304",
    "sg:postcode":"J0Z 2S0",
    "sg:province":"QC",
    "sg:tags":[
        "general",
        "contractor"
    ],
    "wof:name":"Gilles J Aubin Inc",
    "wof:placetype":"venue"
},
  "geometry": {"coordinates":[-78.999489,48.750568],"type":"Point"}
}