{
  "type": "Feature",
  "properties": {
    "addr:full":"Concord ON L4K 4M9",
    "addr:postcode":"l4k 4m9",
    "iso:country":"CA",
    "sg:city":"Concord",
    "sg:classifiers":[
        {
            "category":"Building & Trades",
            "subcategory":"Plumbing",
            "type":"Services"
        }
    ],
    "sg:phone":"+1 905 660 3647",
    "sg:postcode":"L4K 4M9",
    "sg:province":"ON",
    "sg:tags":[
        "contractor"
    ],
    "wof:name":"Creslan Plumbing Inc",
    "wof:placetype":"venue"
},
  "geometry": {"coordinates":[-79.52454400000001,43.809834],"type":"Point"}
}