{
  "type": "Feature",
  "properties": {
    "addr:full":"2750 Fairway Plaza Rd S Lethbridge AB T1K 6Z3",
    "addr:housenumber":"2750",
    "addr:postcode":"t1k 6z3",
    "addr:street":"Fairway Plaza Rd S",
    "iso:country":"CA",
    "sg:address":"2750 Fairway Plaza Rd S",
    "sg:city":"Lethbridge",
    "sg:classifiers":[
        {
            "category":"Banks & Credit Unions",
            "subcategory":"Bank",
            "type":"Services"
        }
    ],
    "sg:phone":"+1 403 317 7090",
    "sg:postcode":"T1K 6Z3",
    "sg:province":"AB",
    "wof:name":"Bank of Montreal",
    "wof:placetype":"venue"
},
  "geometry": {"coordinates":[-112.792419,49.668282],"type":"Point"}
}