{
  "type": "Feature",
  "properties": {
    "addr:full":"439 Rue Lafrance Gatineau QC J8P 6C1",
    "addr:housenumber":"439",
    "addr:postcode":"j8p 6c1",
    "addr:street":"Rue Lafrance",
    "iso:country":"CA",
    "sg:address":"439 Rue Lafrance",
    "sg:city":"Gatineau",
    "sg:classifiers":[
        {
            "category":"Building & Trades",
            "subcategory":"Pest Control",
            "type":"Services"
        }
    ],
    "sg:phone":"+1 819 663 8560",
    "sg:postcode":"J8P 6C1",
    "sg:province":"QC",
    "wof:name":"Extermination St-Michel Ltee",
    "wof:placetype":"venue"
},
  "geometry": {"coordinates":[-75.66699199999999,45.492325],"type":"Point"}
}