{
  "type": "Feature",
  "properties": {
    "iso:country":"CA",
    "sg:address":"452 Plains Rd E",
    "sg:city":"Burlington",
    "sg:classifiers":[
        {
            "category":"Health Services",
            "subcategory":"Health Practitioner",
            "type":"Services"
        }
    ],
    "sg:phone":"+1 905 333 8860",
    "sg:postcode":"L7T 2E1",
    "sg:province":"ON",
    "sg:tags":[
        "acupuncture",
        "chiropractor"
    ],
    "wof:name":"Kitchen, Richard C DC",
    "wof:placetype":"venue"
},
  "geometry": {"coordinates":[-79.8374633789,43.3180618286],"type":"Point"}
}