{
  "type": "Feature",
  "properties": {
    "iso:country":"CA",
    "sg:address":"6423 30 St SE",
    "sg:city":"Calgary",
    "sg:classifiers":[
        {
            "category":"Home & Garden",
            "subcategory":"Building Materials",
            "type":"Retail Goods"
        }
    ],
    "sg:phone":"+1 403 279 2797",
    "sg:postcode":"T2C 1R4",
    "sg:province":"AB",
    "sg:tags":[
        "windows"
    ],
    "wof:name":"Supreme Windows",
    "wof:placetype":"venue"
},
  "geometry": {"coordinates":[-113.985961914,50.9967575073],"type":"Point"}
}