{
  "type": "Feature",
  "properties": {
    "addr:full":"611 Commercial Ave Kitimat BC V8C 2J5",
    "addr:housenumber":"611",
    "addr:postcode":"bc v8c 2j5",
    "addr:street":"Commercial Ave",
    "iso:country":"CA",
    "sg:address":"611 Commercial Ave",
    "sg:city":"Kitimat",
    "sg:classifiers":[
        {
            "category":"Home & Garden",
            "subcategory":"Carpets & Floor Coverings",
            "type":"Retail Goods"
        }
    ],
    "sg:phone":"+1 250 632 3157",
    "sg:postcode":"V8C 2J5",
    "sg:province":"BC",
    "sg:tags":[
        "equipment",
        "supply",
        "rug",
        "electric"
    ],
    "wof:name":"Emporium Builders Supplies Ltd",
    "wof:placetype":"venue"
},
  "geometry": {"coordinates":[-128.685486,54.060272],"type":"Point"}
}