{
  "type": "Feature",
  "properties": {
    "addr:full":"152 Albert St Strathroy ON N7G 1V5",
    "addr:housenumber":"152",
    "addr:postcode":"n7g 1v5",
    "addr:street":"Albert St",
    "iso:country":"CA",
    "sg:address":"152 Albert St",
    "sg:city":"Strathroy",
    "sg:classifiers":[
        {
            "category":"Organizations",
            "subcategory":"Religious Organization",
            "type":"Services"
        }
    ],
    "sg:phone":"+1 519 245 2292",
    "sg:postcode":"N7G 1V5",
    "sg:province":"ON",
    "sg:tags":[
        "church"
    ],
    "wof:name":"St Andrew's Presbyterian Ch",
    "wof:placetype":"venue"
},
  "geometry": {"coordinates":[-81.62702899999999,42.955429],"type":"Point"}
}