{
  "type": "Feature",
  "properties": {
    "addr:full":"300 Notre Dame Ave # A Winnipeg MB R3B 1P4",
    "addr:housenumber":"300",
    "addr:postcode":"r3b 1p4",
    "addr:street":"Notre Dame Ave # A",
    "iso:country":"CA",
    "sg:address":"300 Notre Dame Ave # A",
    "sg:city":"Winnipeg",
    "sg:classifiers":[
        {
            "category":"Shopping",
            "subcategory":"Clothing, Apparel, & Fashions",
            "type":"Retail Goods"
        }
    ],
    "sg:phone":"+1 204 943 2788",
    "sg:postcode":"R3B 1P4",
    "sg:province":"MB",
    "sg:tags":[
        "tailor"
    ],
    "wof:name":"Angie Angie Fashion",
    "wof:placetype":"venue"
},
  "geometry": {"coordinates":[-97.143929,49.896454],"type":"Point"}
}