{
  "type": "Feature",
  "properties": {
    "addr:full":"3rd St Bredenbury SK S0A 0H0",
    "addr:postcode":"s0a 0h0",
    "addr:street":"3Rd St",
    "iso:country":"CA",
    "sg:address":"3rd St",
    "sg:city":"Bredenbury",
    "sg:classifiers":[
        {
            "category":"Education",
            "subcategory":"Library",
            "type":"Public Place"
        }
    ],
    "sg:phone":"+1 306 898 4683",
    "sg:postcode":"S0A 0H0",
    "sg:province":"SK",
    "sg:tags":[
        "government"
    ],
    "wof:name":"Bredenbury Town Library",
    "wof:placetype":"venue"
},
  "geometry": {"coordinates":[-102.05053700000001,50.939602],"type":"Point"}
}