{
  "type": "Feature",
  "properties": {
    "addr:full":"2501 Finch Ave W North York ON M9M 2G1",
    "addr:housenumber":"2501",
    "addr:postcode":"m9m 2g1",
    "addr:street":"Finch Ave W",
    "iso:country":"CA",
    "sg:address":"2501 Finch Ave W",
    "sg:city":"North York",
    "sg:classifiers":[
        {
            "category":"Restaurant",
            "type":"Food & Drink"
        }
    ],
    "sg:phone":"+1 416 740 9566",
    "sg:postcode":"M9M 2G1",
    "sg:province":"ON",
    "wof:name":"Bangali Sweet House",
    "wof:placetype":"venue"
},
  "geometry": {"coordinates":[-79.554924,43.749245],"type":"Point"}
}