{
  "type": "Feature",
  "properties": {
    "addr:full":"172 St. George St Toronto ON M5R 2M7",
    "addr:housenumber":"172",
    "addr:postcode":"m5r 2m7",
    "addr:street":"St. George St",
    "iso:country":"CA",
    "sg:address":"172 St. George St",
    "sg:city":"Toronto",
    "sg:classifiers":[
        {
            "category":"Real Estate",
            "subcategory":"Architect",
            "type":"Services"
        }
    ],
    "sg:phone":"+1 416 968 3522",
    "sg:postcode":"M5R 2M7",
    "sg:province":"ON",
    "wof:name":"Young & Wright Architects Inc",
    "wof:placetype":"venue"
},
  "geometry": {"coordinates":[-79.40016900000001,43.667889],"type":"Point"}
}