{
  "type": "Feature",
  "properties": {
    "addr:full":"2 Cedar Ave New Liskeard ON P0J 1P0",
    "addr:housenumber":"2",
    "addr:postcode":"p0j 1p0",
    "addr:street":"Cedar Ave",
    "iso:country":"CA",
    "sg:address":"2 Cedar Ave",
    "sg:city":"New Liskeard",
    "sg:classifiers":[
        {
            "category":"Restaurant",
            "type":"Food & Drink"
        }
    ],
    "sg:phone":"+1 705 647 9500",
    "sg:postcode":"P0J 1P0",
    "sg:province":"ON",
    "wof:name":"Rooster's Bar and Grill",
    "wof:placetype":"venue"
},
  "geometry": {"coordinates":[-79.6708526611,47.5065345764],"type":"Point"}
}