{
  "type": "Feature",
  "properties": {
    "addr:full":"57 E Church St Waterford ON N0E 1Y0",
    "addr:housenumber":"57",
    "addr:postcode":"n0e 1y0",
    "addr:street":"E Church St",
    "iso:country":"CA",
    "sg:address":"57 E Church St",
    "sg:city":"Waterford",
    "sg:classifiers":[
        {
            "category":"Health Services",
            "subcategory":"Doctor",
            "type":"Services"
        }
    ],
    "sg:phone":"+1 519 443 7241",
    "sg:postcode":"N0E 1Y0",
    "sg:province":"ON",
    "sg:tags":[
        "physician",
        "surgeon"
    ],
    "wof:name":"Peeris, S A MD",
    "wof:placetype":"venue"
},
  "geometry": {"coordinates":[-80.2877502441,42.9321098328],"type":"Point"}
}