{
  "type": "Feature",
  "properties": {
    "addr:full":"248 Boulton Ave Toronto ON M4M 2K1",
    "addr:housenumber":"248",
    "addr:postcode":"m4m 2k1",
    "addr:street":"Boulton Ave",
    "iso:country":"CA",
    "sg:address":"248 Boulton Ave",
    "sg:city":"Toronto",
    "sg:classifiers":[
        {
            "category":"Restaurant",
            "type":"Food & Drink"
        }
    ],
    "sg:phone":"+1 416 778 4038",
    "sg:postcode":"M4M 2K1",
    "sg:province":"ON",
    "wof:name":"Que Ling Restaurant",
    "wof:placetype":"venue"
},
  "geometry": {"coordinates":[-79.3493652344,43.6654968262],"type":"Point"}
}