{
  "type": "Feature",
  "properties": {
    "addr:full":"3000 Rue Viau Montreal QC H1V 3J3",
    "addr:housenumber":"3000",
    "addr:postcode":"h1v 3j3",
    "addr:street":"Rue Viau",
    "iso:country":"CA",
    "sg:address":"3000 Rue Viau",
    "sg:city":"Montreal",
    "sg:classifiers":[
        {
            "category":"Government",
            "subcategory":"Office",
            "type":"Public Place"
        }
    ],
    "sg:phone":"+1 514 872 6644",
    "sg:postcode":"H1V 3J3",
    "sg:province":"QC",
    "sg:tags":[
        "village"
    ],
    "wof:name":"Montreal Centres DE Sports",
    "wof:placetype":"venue"
},
  "geometry": {"coordinates":[-73.5490112305,45.5633773804],"type":"Point"}
}