{
  "type": "Feature",
  "properties": {
    "iso:country":"CA",
    "sg:address":"784 St Clair Ave W",
    "sg:city":"Toronto",
    "sg:classifiers":[
        {
            "category":"Shopping",
            "subcategory":"Florist",
            "type":"Retail Goods"
        }
    ],
    "sg:phone":"+1 416 653 4334",
    "sg:postcode":"M6C 1B6",
    "sg:province":"ON",
    "wof:name":"Alberta Flower's & Gifts",
    "wof:placetype":"venue"
},
  "geometry": {"coordinates":[-79.42933654789999,43.6811065674],"type":"Point"}
}