{
  "type": "Feature",
  "properties": {
    "addr:full":"60 Government Rd S Weyburn SK S4H 2A3",
    "addr:housenumber":"60",
    "addr:postcode":"s4h 2a3",
    "addr:street":"Government Rd",
    "iso:country":"CA",
    "sg:address":"60 Government Rd S",
    "sg:city":"Weyburn",
    "sg:classifiers":[
        {
            "category":"Local Transit",
            "type":"Transportation"
        }
    ],
    "sg:phone":"+1 306 842 2020",
    "sg:postcode":"S4H 2A3",
    "sg:province":"SK",
    "sg:tags":[
        "bus",
        "line"
    ],
    "wof:name":"Saskatchewan Transportation",
    "wof:placetype":"venue"
},
  "geometry": {"coordinates":[-103.858101,49.658607],"type":"Point"}
}