{
  "type": "Feature",
  "properties": {
    "addr:full":"Surrey BC V3W 1A2",
    "addr:postcode":"v3w 1a2",
    "iso:country":"CA",
    "sg:city":"Surrey",
    "sg:classifiers":[
        {
            "category":"Manufacturing",
            "subcategory":"Lumber",
            "type":"Manufacturing & Wholesale Goods"
        }
    ],
    "sg:phone":"+1 604 592 0500",
    "sg:postcode":"V3W 1A2",
    "sg:province":"BC",
    "sg:tags":[
        "ginseng"
    ],
    "wof:name":"American Wild Woodland Ginseng",
    "wof:placetype":"venue"
},
  "geometry": {"coordinates":[-122.830215,49.105179],"type":"Point"}
}