{
  "type": "Feature",
  "properties": {
    "addr:full":"312 Cumberland Crt Oshawa ON L1H 8E7",
    "addr:housenumber":"312",
    "addr:postcode":"l1h 8e7",
    "addr:street":"Cumberland Crt",
    "iso:country":"CA",
    "sg:address":"312 Cumberland Crt",
    "sg:city":"Oshawa",
    "sg:classifiers":[
        {
            "category":"Farming",
            "subcategory":"Dairy Farm",
            "type":"Manufacturing & Wholesale Goods"
        }
    ],
    "sg:phone":"+1 905 725 4360",
    "sg:postcode":"L1H 8E7",
    "sg:province":"ON",
    "wof:name":"Amey's Dairy Distributing",
    "wof:placetype":"venue"
},
  "geometry": {"coordinates":[-78.8183670044,43.8978652954],"type":"Point"}
}