{
  "type": "Feature",
  "properties": {
    "addr:full":"191 Trans Canada Hwy Woodstock NB E7M 6B5",
    "addr:housenumber":"191",
    "addr:postcode":"e7m 6b5",
    "addr:street":"Trans Canada Hwy",
    "iso:country":"CA",
    "sg:address":"191 Trans Canada Hwy",
    "sg:city":"Woodstock",
    "sg:phone":"+1 506 328 3243",
    "sg:postcode":"E7M 6B5",
    "sg:province":"NB",
    "sg:tags":[
        "oil"
    ],
    "wof:name":"Clark Oil CO Ltd",
    "wof:placetype":"venue"
},
  "geometry": {"coordinates":[-67.608879,46.14748],"type":"Point"}
}