{
  "type": "Feature",
  "properties": {
    "addr:full":"2803 Boul Mercure Saint-Nicephore QC J2A 3N9",
    "addr:housenumber":"2803",
    "addr:postcode":"j2a 3n9",
    "addr:street":"Boul Mercure Saint-Nicephore",
    "iso:country":"CA",
    "sg:address":"2803 Boul Mercure",
    "sg:city":"Saint-Nicephore",
    "sg:classifiers":[
        {
            "category":"Building & Trades",
            "subcategory":"Construction",
            "type":"Services"
        }
    ],
    "sg:phone":"+1 819 472 8400",
    "sg:postcode":"J2A 3N9",
    "sg:province":"QC",
    "sg:tags":[
        "excavating",
        "contractor",
        "general"
    ],
    "wof:name":"Serge Labbe Entrepreneur",
    "wof:placetype":"venue"
},
  "geometry": {"coordinates":[-72.40654754640001,45.8219947815],"type":"Point"}
}