{
  "type": "Feature",
  "properties": {
    "addr:full":"Cap-DE-LA-Madeleine QC G8T 7A6",
    "addr:postcode":"g8t 7a6",
    "iso:country":"CA",
    "sg:city":"Cap-DE-LA-Madeleine",
    "sg:classifiers":[
        {
            "category":"Education",
            "subcategory":"School",
            "type":"Public Place"
        }
    ],
    "sg:phone":"+1 819 375 8836",
    "sg:postcode":"G8T 7A6",
    "sg:province":"QC",
    "wof:name":"Ecole DE LA Ferte",
    "wof:placetype":"venue"
},
  "geometry": {"coordinates":[-72.551643,46.388172],"type":"Point"}
}