{
  "type": "Feature",
  "properties": {
    "addr:full":"Vermilion Bay ON P0V 2V0",
    "addr:postcode":"p0v 2v0",
    "addr:street":"Vermilion Bay",
    "iso:country":"CA",
    "sg:city":"Vermilion Bay",
    "sg:classifiers":[
        {
            "category":"Travel",
            "subcategory":"Hotels & Motels",
            "type":"Entertainment"
        }
    ],
    "sg:phone":"+1 807 529 6131",
    "sg:postcode":"P0V 2V0",
    "sg:province":"ON",
    "sg:tags":[
        "resort"
    ],
    "wof:name":"Sharpe's Cliff Lake Lodge",
    "wof:placetype":"venue"
},
  "geometry": {"coordinates":[-93.3837432861,49.8584823608],"type":"Point"}
}