{
  "type": "Feature",
  "properties": {
    "addr:full":"71st St E Saskatoon SK S7K 3J7",
    "addr:postcode":"s7k 3j7",
    "addr:street":"71St St E",
    "iso:country":"CA",
    "sg:address":"71st St E",
    "sg:city":"Saskatoon",
    "sg:classifiers":[
        {
            "category":"Freight",
            "type":"Transportation"
        }
    ],
    "sg:phone":"+1 306 933 2919",
    "sg:postcode":"S7K 3J7",
    "sg:province":"SK",
    "sg:tags":[
        "trucking"
    ],
    "wof:name":"Barry's Transport Ltd",
    "wof:placetype":"venue"
},
  "geometry": {"coordinates":[-106.62890625,52.2021331787],"type":"Point"}
}