{
  "type": "Feature",
  "properties": {
    "addr:full":"1110 Av Bernard Outremont QC H2V 1V3",
    "addr:housenumber":"1110",
    "addr:postcode":"h2v 1v3",
    "addr:street":"Av Bernard",
    "iso:country":"CA",
    "sg:address":"1110 Av Bernard",
    "sg:city":"Outremont",
    "sg:classifiers":[
        {
            "category":"Wholesale",
            "subcategory":"Home Furnishings",
            "type":"Manufacturing & Wholesale Goods"
        }
    ],
    "sg:phone":"+1 514 488 0584",
    "sg:postcode":"H2V 1V3",
    "sg:province":"QC",
    "sg:tags":[
        "closet",
        "accessory"
    ],
    "wof:name":"Au Printemps",
    "wof:placetype":"venue"
},
  "geometry": {"coordinates":[-73.607269,45.521488],"type":"Point"}
}