{
  "type": "Feature",
  "properties": {
    "addr:full":"Hawkesbury ON K6A 1A1",
    "addr:postcode":"k6a 1a1",
    "iso:country":"CA",
    "sg:city":"Hawkesbury",
    "sg:classifiers":[
        {
            "category":"Professional",
            "subcategory":"Lawyer & Legal Services",
            "type":"Services"
        }
    ],
    "sg:phone":"+1 613 632 8557",
    "sg:postcode":"K6A 1A1",
    "sg:province":"ON",
    "sg:tags":[
        "attorney"
    ],
    "wof:name":"Woods Parisien",
    "wof:placetype":"venue"
},
  "geometry": {"coordinates":[-74.610824585,45.6096878052],"type":"Point"}
}