{
  "type": "Feature",
  "properties": {
    "addr:full":"Waterton Park AB T0K 2M0",
    "addr:postcode":"t0k 2m0",
    "addr:street":"Waterton",
    "iso:country":"CA",
    "sg:city":"Waterton Park",
    "sg:classifiers":[
        {
            "category":"Shopping",
            "type":"Retail Goods"
        }
    ],
    "sg:phone":"+1 403 859 2294",
    "sg:postcode":"T0K 2M0",
    "sg:province":"AB",
    "sg:tags":[
        "stamp",
        "collector",
        "for"
    ],
    "wof:name":"Canada Post Corp",
    "wof:placetype":"venue"
},
  "geometry": {"coordinates":[-113.841079712,49.1131362915],"type":"Point"}
}