{
  "type": "Feature",
  "properties": {
    "addr:full":"1181 Rue Brissette Longueuil QC J4M 1J1",
    "addr:housenumber":"1181",
    "addr:postcode":"j4m 1j1",
    "addr:street":"Rue Brissette",
    "iso:country":"CA",
    "sg:address":"1181 Rue Brissette",
    "sg:city":"Longueuil",
    "sg:classifiers":[
        {
            "category":"Wholesale",
            "subcategory":"Machinery & Supplies",
            "type":"Manufacturing & Wholesale Goods"
        }
    ],
    "sg:phone":"+1 450 647 6636",
    "sg:postcode":"J4M 1J1",
    "sg:province":"QC",
    "sg:tags":[
        "equipment",
        "baker"
    ],
    "wof:name":"Cyrano Services Inc",
    "wof:placetype":"venue"
},
  "geometry": {"coordinates":[-73.447769165,45.5289764404],"type":"Point"}
}