{
  "type": "Feature",
  "properties": {
    "addr:full":"420 Victoria Ave Fort Frances ON P9A 2C3",
    "addr:housenumber":"420",
    "addr:postcode":"p9a 2c3",
    "addr:street":"Victoria Ave",
    "iso:country":"CA",
    "sg:address":"420 Victoria Ave",
    "sg:city":"Fort Frances",
    "sg:classifiers":[
        {
            "category":"Professional",
            "subcategory":"Lawyer & Legal Services",
            "type":"Services"
        }
    ],
    "sg:phone":"+1 807 274 9809",
    "sg:postcode":"P9A 2C3",
    "sg:province":"ON",
    "sg:tags":[
        "attorney"
    ],
    "wof:name":"Brunetta, Clare Allan",
    "wof:placetype":"venue"
},
  "geometry": {"coordinates":[-93.3923797607,48.6092300415],"type":"Point"}
}