{
  "type": "Feature",
  "properties": {
    "addr:full":"2010 Rg St Jean Saint-Maurice QC G0X 2X0",
    "addr:postcode":"2010;g0x 2x0",
    "addr:street":"Rg St",
    "iso:country":"CA",
    "sg:address":"2010 Rg St Jean",
    "sg:city":"Saint-Maurice",
    "sg:classifiers":[
        {
            "category":"Personal",
            "subcategory":"Beauty Salon",
            "type":"Services"
        }
    ],
    "sg:phone":"+1 819 378 8377",
    "sg:postcode":"G0X 2X0",
    "sg:province":"QC",
    "wof:name":"Bigoudi Coiffure Enr",
    "wof:placetype":"venue"
},
  "geometry": {"coordinates":[-72.548653,46.456093],"type":"Point"}
}