{
  "type": "Feature",
  "properties": {
    "iso:country":"CA",
    "sg:address":"3366 Harvester Rd",
    "sg:city":"Burlington",
    "sg:classifiers":[
        {
            "category":"Retail",
            "subcategory":"Auto Repair",
            "type":"Services"
        }
    ],
    "sg:phone":"+1 905 637 7303",
    "sg:postcode":"L7N 3M8",
    "sg:province":"ON",
    "sg:tags":[
        "repairing",
        "automobile"
    ],
    "wof:name":"Advanced Automotive",
    "wof:placetype":"venue"
},
  "geometry": {"coordinates":[-79.790199,43.358765],"type":"Point"}
}