{
  "type": "Feature",
  "properties": {
    "addr:full":"721 Garner Pl Estevan SK S4A 2G6",
    "addr:housenumber":"721",
    "addr:postcode":"s4a 2g6",
    "addr:street":"Garner Pl",
    "iso:country":"CA",
    "sg:address":"721 Garner Pl",
    "sg:city":"Estevan",
    "sg:classifiers":[
        {
            "category":"Building & Trades",
            "subcategory":"Landscaping Services",
            "type":"Services"
        }
    ],
    "sg:phone":"+1 306 634 7348",
    "sg:postcode":"S4A 2G6",
    "sg:province":"SK",
    "sg:tags":[
        "tree",
        "landscape",
        "contractor"
    ],
    "wof:name":"Southeast Tree Care",
    "wof:placetype":"venue"
},
  "geometry": {"coordinates":[-102.985687,49.153183],"type":"Point"}
}