{
  "type": "Feature",
  "properties": {
    "addr:full":"Municipal Rd Kincaid SK S0H 2J0",
    "addr:postcode":"s0h 2j0",
    "addr:street":"Municipal Rd",
    "iso:country":"CA",
    "sg:address":"Municipal Rd",
    "sg:city":"Kincaid",
    "sg:classifiers":[
        {
            "category":"Health Services",
            "subcategory":"Clinic",
            "type":"Services"
        }
    ],
    "sg:phone":"+1 306 264 3233",
    "sg:postcode":"S0H 2J0",
    "sg:province":"SK",
    "wof:name":"Kincaid Health Ctr",
    "wof:placetype":"venue"
},
  "geometry": {"coordinates":[-107.00393699999999,49.67223],"type":"Point"}
}