{
  "type": "Feature",
  "properties": {
    "addr:full":"635 Rue Lavoisier Repentigny QC J6A 7N2",
    "addr:housenumber":"635",
    "addr:postcode":"j6a 7n2",
    "addr:street":"Rue Lavoisier",
    "iso:country":"CA",
    "sg:address":"635 Rue Lavoisier",
    "sg:city":"Repentigny",
    "sg:classifiers":[
        {
            "category":"Retail",
            "subcategory":"Car Wash",
            "type":"Services"
        }
    ],
    "sg:phone":"+1 450 581 4715",
    "sg:postcode":"J6A 7N2",
    "sg:province":"QC",
    "sg:tags":[
        "polishing",
        "washing"
    ],
    "wof:name":"Halle Libre Svc Plus Enr",
    "wof:placetype":"venue"
},
  "geometry": {"coordinates":[-73.448013,45.755108],"type":"Point"}
}