{
  "type": "Feature",
  "properties": {
    "addr:full":"10 Princess Springhill NS B0M 1X0",
    "addr:housenumber":"10",
    "addr:postcode":"b0m 1x0",
    "addr:street":"Princess",
    "iso:country":"CA",
    "sg:address":"10 Princess",
    "sg:city":"Springhill",
    "sg:classifiers":[
        {
            "category":"Health Services",
            "subcategory":"Doctor",
            "type":"Services"
        }
    ],
    "sg:phone":"+1 902 597 8055",
    "sg:postcode":"B0M 1X0",
    "sg:province":"NS",
    "sg:tags":[
        "physician",
        "surgeon"
    ],
    "wof:name":"Begin, P MD",
    "wof:placetype":"venue"
},
  "geometry": {"coordinates":[-64.051811,45.650608],"type":"Point"}
}