{
  "type": "Feature",
  "properties": {
    "addr:full":"Winnipeg MB R3C 3R8",
    "addr:postcode":"r3c 3r8",
    "iso:country":"CA",
    "sg:city":"Winnipeg",
    "sg:classifiers":[
        {
            "category":"Government",
            "subcategory":"Office",
            "type":"Public Place"
        }
    ],
    "sg:phone":"+1 204 984 1575",
    "sg:postcode":"R3C 3R8",
    "sg:province":"MB",
    "wof:name":"Canada Aboriginal Policing",
    "wof:placetype":"venue"
},
  "geometry": {"coordinates":[-97.14255523680001,49.8896903992],"type":"Point"}
}