{
  "type": "Feature",
  "properties": {
    "addr:full":"5949 College St Halifax NS B3H 1X6",
    "addr:housenumber":"5949",
    "addr:postcode":"b3h 1x6",
    "addr:street":"College St",
    "iso:country":"CA",
    "sg:address":"5949 College St",
    "sg:city":"Halifax",
    "sg:classifiers":[
        {
            "category":"Professional",
            "type":"Services"
        }
    ],
    "sg:phone":"+1 902 429 2942",
    "sg:postcode":"B3H 1X6",
    "sg:province":"NS",
    "sg:tags":[
        "construction",
        "management",
        "establishment"
    ],
    "wof:name":"Dynacon Management Inc",
    "wof:placetype":"venue"
},
  "geometry": {"coordinates":[-63.5854568481,44.6397132874],"type":"Point"}
}