{
  "type": "Feature",
  "properties": {
    "iso:country":"CA",
    "sg:address":"18 Egbert St",
    "sg:city":"Saint John",
    "sg:classifiers":[
        {
            "category":"Wholesale",
            "subcategory":"Scrap",
            "type":"Manufacturing & Wholesale Goods"
        }
    ],
    "sg:phone":"+1 506 652 2918",
    "sg:postcode":"E2J 1X1",
    "sg:province":"NB",
    "sg:tags":[
        "depot",
        "recycling",
        "center",
        "bottle",
        "can"
    ],
    "wof:name":"Fundy Redemption Ctr",
    "wof:placetype":"venue"
},
  "geometry": {"coordinates":[-66.0454711914,45.2852058411],"type":"Point"}
}