{
  "type": "Feature",
  "properties": {
    "addr:full":"Vernon BC V1T 8L1",
    "addr:postcode":"v1t 8l1",
    "iso:country":"CA",
    "sg:city":"Vernon",
    "sg:classifiers":[
        {
            "category":"Health Services",
            "subcategory":"Doctor",
            "type":"Services"
        }
    ],
    "sg:phone":"+1 250 260 1739",
    "sg:postcode":"V1T 8L1",
    "sg:province":"BC",
    "sg:tags":[
        "physician",
        "surgeon"
    ],
    "wof:name":"Curran, T MD",
    "wof:placetype":"venue"
},
  "geometry": {"coordinates":[-119.269493,50.262337],"type":"Point"}
}