{
  "type": "Feature",
  "properties": {
    "addr:full":"Calgary AB T2E 2V5",
    "addr:postcode":"t2e 2v5",
    "iso:country":"CA",
    "sg:city":"Calgary",
    "sg:classifiers":[
        {
            "category":"Shopping",
            "subcategory":"Computers & Home Electronics",
            "type":"Retail Goods"
        }
    ],
    "sg:phone":"+1 403 276 1398",
    "sg:postcode":"T2E 2V5",
    "sg:province":"AB",
    "sg:tags":[
        "software"
    ],
    "wof:name":"Tymeware",
    "wof:placetype":"venue"
},
  "geometry": {"coordinates":[-114.062599182,51.0762138367],"type":"Point"}
}