{
  "type": "Feature",
  "properties": {
    "addr:full":"644 Hornby St Vancouver BC V6C 2G2",
    "addr:housenumber":"644",
    "addr:postcode":"bc v6c 2g2",
    "addr:street":"Hornby St",
    "iso:country":"CA",
    "sg:address":"644 Hornby St",
    "sg:city":"Vancouver",
    "sg:classifiers":[
        {
            "category":"Shopping",
            "subcategory":"Shoes",
            "type":"Retail Goods"
        }
    ],
    "sg:phone":"+1 604 669 3738",
    "sg:postcode":"V6C 2G2",
    "sg:province":"BC",
    "wof:name":"Tallcrest Shoes",
    "wof:placetype":"venue"
},
  "geometry": {"coordinates":[-123.11891199999999,49.284237],"type":"Point"}
}