{
  "type": "Feature",
  "properties": {
    "addr:full":"5524 Rue Saint-Patrick Montreal QC H4E 1A8",
    "addr:housenumber":"5524",
    "addr:postcode":"h4e 1a8",
    "addr:street":"Rue Saint-Patrick",
    "iso:country":"CA",
    "sg:address":"5524 Rue Saint-Patrick",
    "sg:city":"Montreal",
    "sg:classifiers":[
        {
            "category":"Manufacturing",
            "subcategory":"Printing",
            "type":"Manufacturing & Wholesale Goods"
        }
    ],
    "sg:phone":"+1 514 766 6162",
    "sg:postcode":"H4E 1A8",
    "sg:province":"QC",
    "sg:tags":[
        "multimedia"
    ],
    "wof:name":"Multi Media Interactif",
    "wof:placetype":"venue"
},
  "geometry": {"coordinates":[-73.596085,45.463802],"type":"Point"}
}