{
  "type": "Feature",
  "properties": {
    "addr:full":"5223 82 Ave NW Edmonton AB T6B 2J6",
    "addr:housenumber":"5223",
    "addr:postcode":"t6b 2j6",
    "addr:street":"82 Ave Nw",
    "iso:country":"CA",
    "sg:address":"5223 82 Ave NW",
    "sg:city":"Edmonton",
    "sg:classifiers":[
        {
            "category":"Manufacturing",
            "subcategory":"Printing",
            "type":"Manufacturing & Wholesale Goods"
        }
    ],
    "sg:phone":"+1 780 465 3936",
    "sg:postcode":"T6B 2J6",
    "sg:province":"AB",
    "sg:tags":[
        "printer"
    ],
    "wof:name":"Heron Printing Ltd",
    "wof:placetype":"venue"
},
  "geometry": {"coordinates":[-113.42027299999999,53.517899],"type":"Point"}
}