{
  "type": "Feature",
  "properties": {
    "addr:full":"Seven Sisters Falls MB R0E 1Y0",
    "addr:housenumber":"seven",
    "addr:postcode":"r0e 1y0",
    "iso:country":"CA",
    "sg:city":"Seven Sisters Falls",
    "sg:classifiers":[
        {
            "category":"Organizations",
            "subcategory":"Religious Organization",
            "type":"Services"
        }
    ],
    "sg:phone":"+1 204 348 2536",
    "sg:postcode":"R0E 1Y0",
    "sg:province":"MB",
    "sg:tags":[
        "church"
    ],
    "wof:name":"Whiteshell Baptist Church",
    "wof:placetype":"venue"
},
  "geometry": {"coordinates":[-96.02625274659999,50.1053504944],"type":"Point"}
}