{
  "type": "Feature",
  "properties": {
    "addr:full":"Scarborough ON M1S 5H6",
    "addr:postcode":"m1s 5h6",
    "iso:country":"CA",
    "sg:city":"Scarborough",
    "sg:classifiers":[
        {
            "category":"Health Services",
            "subcategory":"Doctor",
            "type":"Services"
        }
    ],
    "sg:phone":"+1 416 291 0051",
    "sg:postcode":"M1S 5H6",
    "sg:province":"ON",
    "sg:tags":[
        "physician",
        "surgeon"
    ],
    "wof:name":"Leung, Kevin MD",
    "wof:placetype":"venue"
},
  "geometry": {"coordinates":[-79.28815460209999,43.8034858704],"type":"Point"}
}