{
  "type": "Feature",
  "properties": {
    "addr:full":"1872 Kennedy Rd Scarborough ON M1P 2L8",
    "addr:housenumber":"1872",
    "addr:postcode":"m1p 2l8",
    "addr:street":"Kennedy Rd",
    "iso:country":"CA",
    "sg:address":"1872 Kennedy Rd",
    "sg:city":"Scarborough",
    "sg:classifiers":[
        {
            "category":"Food & Beverages",
            "subcategory":"Groceries & Convenience Stores",
            "type":"Retail Goods"
        }
    ],
    "sg:phone":"+1 416 293 4619",
    "sg:postcode":"M1P 2L8",
    "sg:province":"ON",
    "sg:tags":[
        "grocer"
    ],
    "wof:name":"R C West Indian Grocery",
    "wof:placetype":"venue"
},
  "geometry": {"coordinates":[-79.28136444090001,43.766204834],"type":"Point"}
}