{
  "type": "Feature",
  "properties": {
    "iso:country":"CA",
    "sg:address":"12282 Av Roch-Desjardins",
    "sg:city":"Montreal",
    "sg:classifiers":[
        {
            "category":"Professional",
            "subcategory":"Management & Consulting",
            "type":"Services"
        }
    ],
    "sg:phone":"+1 514 494 9926",
    "sg:postcode":"H1E 4P4",
    "sg:province":"QC",
    "sg:tags":[
        "food",
        "facility"
    ],
    "wof:name":"Distribution Marchica Inc",
    "wof:placetype":"venue"
},
  "geometry": {"coordinates":[-73.585892,45.641369],"type":"Point"}
}