{
  "type": "Feature",
  "properties": {
    "addr:full":"426 Dundas St Woodstock ON N4S 1C1",
    "addr:housenumber":"426",
    "addr:postcode":"n4s 1c1",
    "addr:street":"Dundas St",
    "iso:country":"CA",
    "sg:address":"426 Dundas St",
    "sg:city":"Woodstock",
    "sg:classifiers":[
        {
            "category":"Wholesale",
            "subcategory":"Apparel",
            "type":"Manufacturing & Wholesale Goods"
        }
    ],
    "sg:phone":"+1 519 537 6244",
    "sg:postcode":"N4S 1C1",
    "sg:province":"ON",
    "wof:name":"Imogene's",
    "wof:placetype":"venue"
},
  "geometry": {"coordinates":[-80.7590255737,43.1296310425],"type":"Point"}
}