{
  "type": "Feature",
  "properties": {
    "addr:full":"654 the Queensway Etobicoke ON M8Y 1K7",
    "addr:housenumber":"654",
    "addr:postcode":"m8y 1k7",
    "addr:street":"The Queensway",
    "iso:country":"CA",
    "sg:address":"654 the Queensway",
    "sg:city":"Etobicoke",
    "sg:classifiers":[
        {
            "category":"Wholesale",
            "subcategory":"Machinery & Supplies",
            "type":"Manufacturing & Wholesale Goods"
        }
    ],
    "sg:phone":"+1 416 503 1286",
    "sg:postcode":"M8Y 1K7",
    "sg:province":"ON",
    "sg:tags":[
        "janitor"
    ],
    "wof:name":"Protect Cleaning Supplies",
    "wof:placetype":"venue"
},
  "geometry": {"coordinates":[-79.497787,43.627567],"type":"Point"}
}