{
  "type": "Feature",
  "properties": {
    "addr:full":"105 Mccaul St # 29 Toronto ON M5T 2X4",
    "addr:housenumber":"105",
    "addr:postcode":"m5t 2x4",
    "addr:street":"Mccaul St # 29",
    "iso:country":"CA",
    "sg:address":"105 Mccaul St # 29",
    "sg:city":"Toronto",
    "sg:classifiers":[
        {
            "category":"Restaurant",
            "type":"Food & Drink"
        }
    ],
    "sg:phone":"+1 416 351 8722",
    "sg:postcode":"M5T 2X4",
    "sg:province":"ON",
    "wof:name":"Al's Fish & Chips",
    "wof:placetype":"venue"
},
  "geometry": {"coordinates":[-79.3909835815,43.6536941528],"type":"Point"}
}