{
  "type": "Feature",
  "properties": {
    "addr:full":"Ajax ON L1S 7G8",
    "addr:postcode":"l1s 7g8",
    "iso:country":"CA",
    "sg:city":"Ajax",
    "sg:classifiers":[
        {
            "category":"Retail",
            "subcategory":"Auto Repair",
            "type":"Services"
        }
    ],
    "sg:phone":"+1 905 427 0276",
    "sg:postcode":"L1S 7G8",
    "sg:province":"ON",
    "sg:tags":[
        "repairing",
        "automobile"
    ],
    "wof:name":"Elite Automotive",
    "wof:placetype":"venue"
},
  "geometry": {"coordinates":[-79.0325012207,43.8352394104],"type":"Point"}
}