{
  "type": "Feature",
  "properties": {
    "addr:full":"8700 Boul Champlain Lasalle QC H8P 3H7",
    "addr:housenumber":"8700",
    "addr:postcode":"h8p 3h7",
    "addr:street":"Boul Champlain",
    "iso:country":"CA",
    "sg:address":"8700 Boul Champlain",
    "sg:city":"Lasalle",
    "sg:classifiers":[
        {
            "category":"Education",
            "subcategory":"School",
            "type":"Public Place"
        }
    ],
    "sg:phone":"+1 514 367 8700",
    "sg:postcode":"H8P 3H7",
    "sg:province":"QC",
    "wof:name":"Commission Scolaire Marguerite",
    "wof:placetype":"venue"
},
  "geometry": {"coordinates":[-73.62191009519999,45.417678833],"type":"Point"}
}