{
  "type": "Feature",
  "properties": {
    "iso:country":"CA",
    "sg:address":"50 Claver Ave",
    "sg:city":"North York",
    "sg:classifiers":[
        {
            "category":"Education",
            "subcategory":"School",
            "type":"Public Place"
        }
    ],
    "sg:phone":"+1 416 393 5250",
    "sg:postcode":"M6B 2W1",
    "sg:province":"ON",
    "wof:name":"Saint Charles Elementary Schl",
    "wof:placetype":"venue"
},
  "geometry": {"coordinates":[-79.450553894,43.7132949829],"type":"Point"}
}