{
  "type": "Feature",
  "properties": {
    "addr:full":"Toronto ON M5A 1J2",
    "addr:postcode":"m5a 1j2",
    "iso:country":"CA",
    "sg:city":"Toronto",
    "sg:classifiers":[
        {
            "category":"Professional",
            "subcategory":"Management & Consulting",
            "type":"Services"
        }
    ],
    "sg:phone":"+1 416 362 7730",
    "sg:postcode":"M5A 1J2",
    "sg:province":"ON",
    "sg:tags":[
        "communications",
        "consultant"
    ],
    "wof:name":"Simplified Communications Grp",
    "wof:placetype":"venue"
},
  "geometry": {"coordinates":[-79.36489899999999,43.649731],"type":"Point"}
}