{
  "type": "Feature",
  "properties": {
    "addr:full":"Saskatoon SK S7K 2B2",
    "addr:postcode":"s7k 2b2",
    "iso:country":"CA",
    "sg:city":"Saskatoon",
    "sg:classifiers":[
        {
            "category":"Shopping",
            "type":"Retail Goods"
        }
    ],
    "sg:phone":"+1 306 242 8050",
    "sg:postcode":"S7K 2B2",
    "sg:province":"SK",
    "sg:tags":[
        "pottery",
        "art",
        "gallery",
        "dealer"
    ],
    "wof:name":"Prairie Pottery",
    "wof:placetype":"venue"
},
  "geometry": {"coordinates":[-106.66325399999999,52.129524],"type":"Point"}
}