{
  "type": "Feature",
  "properties": {
    "addr:full":"200 Ronson Dr Etobicoke ON M9W 5Z9",
    "addr:housenumber":"200",
    "addr:postcode":"m9w 5z9",
    "addr:street":"Ronson Dr",
    "iso:country":"CA",
    "sg:address":"200 Ronson Dr",
    "sg:city":"Etobicoke",
    "sg:classifiers":[
        {
            "category":"Travel",
            "subcategory":"Travel Agent",
            "type":"Entertainment"
        }
    ],
    "sg:phone":"+1 416 614 2887",
    "sg:postcode":"M9W 5Z9",
    "sg:province":"ON",
    "sg:tags":[
        "agency",
        "bureau"
    ],
    "wof:name":"Travel Cuts",
    "wof:placetype":"venue"
},
  "geometry": {"coordinates":[-79.5683441162,43.6943626404],"type":"Point"}
}