{
  "type": "Feature",
  "properties": {
    "addr:full":"60 Rue Perreault Cap-DE-LA-Madeleine QC G8T 9S2",
    "addr:housenumber":"60",
    "addr:postcode":"g8t 9s2",
    "addr:street":"Rue Perreault",
    "iso:country":"CA",
    "sg:address":"60 Rue Perreault",
    "sg:city":"Cap-DE-LA-Madeleine",
    "sg:classifiers":[
        {
            "category":"Health Services",
            "subcategory":"Nursing And Care Facility",
            "type":"Services"
        }
    ],
    "sg:phone":"+1 819 374 7683",
    "sg:postcode":"G8T 9S2",
    "sg:province":"QC",
    "sg:tags":[
        "home",
        "retirement",
        "community"
    ],
    "wof:name":"Residence Ste Famille",
    "wof:placetype":"venue"
},
  "geometry": {"coordinates":[-72.5278549194,46.3622207642],"type":"Point"}
}