{
  "type": "Feature",
  "properties": {
    "addr:full":"158 Rte Saint-Joseph Dosquet QC G0S 1H0",
    "addr:housenumber":"158",
    "addr:postcode":"g0s 1h0",
    "addr:street":"Rte Saint-Joseph",
    "iso:country":"CA",
    "sg:address":"158 Rte Saint-Joseph",
    "sg:city":"Dosquet",
    "sg:classifiers":[
        {
            "category":"Retail",
            "subcategory":"Auto Repair",
            "type":"Services"
        }
    ],
    "sg:phone":"+1 418 728 2620",
    "sg:postcode":"G0S 1H0",
    "sg:province":"QC",
    "sg:tags":[
        "repairing",
        "automobile"
    ],
    "wof:name":"Garage Fc Faucher Inc",
    "wof:placetype":"venue"
},
  "geometry": {"coordinates":[-71.5289230347,46.46692276],"type":"Point"}
}