{
  "type": "Feature",
  "properties": {
    "addr:full":"1244 Lawrence Ave E North York ON M3A 1C3",
    "addr:housenumber":"1244",
    "addr:postcode":"m3a 1c3",
    "addr:street":"Lawrence Ave E",
    "iso:country":"CA",
    "sg:address":"1244 Lawrence Ave E",
    "sg:city":"North York",
    "sg:classifiers":[
        {
            "category":"Food & Beverages",
            "subcategory":"Bakery",
            "type":"Retail Goods"
        }
    ],
    "sg:phone":"+1 416 444 0027",
    "sg:postcode":"M3A 1C3",
    "sg:province":"ON",
    "sg:tags":[
        "shop",
        "doughnut",
        "coffee"
    ],
    "wof:name":"Tim Hortons",
    "wof:placetype":"venue"
},
  "geometry": {"coordinates":[-79.318977356,43.741355896],"type":"Point"}
}