{
  "type": "Feature",
  "properties": {
    "addr:full":"1700 Queen's Blvd Kitchener ON N2N 3L6",
    "addr:housenumber":"1700",
    "addr:postcode":"n2n 3l6",
    "addr:street":"Queen'S Blvd",
    "iso:country":"CA",
    "sg:address":"1700 Queen's Blvd",
    "sg:city":"Kitchener",
    "sg:classifiers":[
        {
            "category":"Recreation",
            "type":"Entertainment"
        }
    ],
    "sg:phone":"+1 519 741 2621",
    "sg:postcode":"N2N 3L6",
    "sg:province":"ON",
    "sg:tags":[
        "government",
        "hall",
        "auditorium"
    ],
    "wof:name":"Kitchener Forest Heights Comm",
    "wof:placetype":"venue"
},
  "geometry": {"coordinates":[-80.50178527830001,43.4360847473],"type":"Point"}
}