{
  "type": "Feature",
  "properties": {
    "iso:country":"CA",
    "sg:city":"Vercheres",
    "sg:classifiers":[
        {
            "category":"Wholesale",
            "subcategory":"Groceries",
            "type":"Manufacturing & Wholesale Goods"
        }
    ],
    "sg:phone":"+1 450 583 2000",
    "sg:postcode":"J0L 2R0",
    "sg:province":"QC",
    "sg:tags":[
        "pet",
        "food"
    ],
    "wof:name":"Apc Nutrition Inc",
    "wof:placetype":"venue"
},
  "geometry": {"coordinates":[-73.354393,45.774395],"type":"Point"}
}