{
  "type": "Feature",
  "properties": {
    "iso:country":"CA",
    "sg:address":"305 3E Av",
    "sg:city":"Pintendre",
    "sg:classifiers":[
        {
            "category":"Recreation",
            "type":"Entertainment"
        }
    ],
    "sg:phone":"+1 418 838 6086",
    "sg:postcode":"G6C 1C6",
    "sg:province":"QC",
    "sg:tags":[
        "government",
        "hall",
        "auditorium"
    ],
    "wof:name":"Pintendre Centre Communautaire",
    "wof:placetype":"venue"
},
  "geometry": {"coordinates":[-71.12381744379999,46.7531967163],"type":"Point"}
}