{
  "type": "Feature",
  "properties": {
    "iso:country":"CA",
    "sg:address":"74 West St",
    "sg:city":"Corner Brook",
    "sg:classifiers":[
        {
            "category":"Food & Beverages",
            "subcategory":"Bakery",
            "type":"Retail Goods"
        }
    ],
    "sg:phone":"+1 709 634 4946",
    "sg:postcode":"A2H 2Z3",
    "sg:province":"NL",
    "sg:tags":[
        "tea",
        "coffee",
        "doughnut"
    ],
    "wof:name":"Tim Hortons",
    "wof:placetype":"venue"
},
  "geometry": {"coordinates":[-57.941196,48.951023],"type":"Point"}
}