{
  "type": "Feature",
  "properties": {
    "addr:full":"378 Boul Maloney E Gatineau QC J8P 1E6",
    "addr:housenumber":"378",
    "addr:postcode":"j8p 1e6",
    "addr:street":"Boul Maloney E",
    "iso:country":"CA",
    "sg:address":"378 Boul Maloney E",
    "sg:city":"Gatineau",
    "sg:classifiers":[
        {
            "category":"Cinema",
            "subcategory":"Movie Rental",
            "type":"Entertainment"
        }
    ],
    "sg:phone":"+1 819 663 7400",
    "sg:postcode":"J8P 1E6",
    "sg:province":"QC",
    "sg:tags":[
        "leasing",
        "video",
        "disc",
        "tape"
    ],
    "wof:name":"Video Super Choix",
    "wof:placetype":"venue"
},
  "geometry": {"coordinates":[-75.64147199999999,45.484447],"type":"Point"}
}