{
  "type": "Feature",
  "properties": {
    "addr:full":"5180 Rue Beaubien E Montreal QC H1T 1W1",
    "addr:housenumber":"5180",
    "addr:postcode":"h1t 1w1",
    "addr:street":"Rue Beaubien E",
    "iso:country":"CA",
    "sg:address":"5180 Rue Beaubien E",
    "sg:city":"Montreal",
    "sg:classifiers":[
        {
            "category":"Shopping",
            "subcategory":"Clothing, Apparel, & Fashions",
            "type":"Retail Goods"
        }
    ],
    "sg:phone":"+1 514 251 0208",
    "sg:postcode":"H1T 1W1",
    "sg:province":"QC",
    "wof:name":"Boutique Versatil",
    "wof:placetype":"venue"
},
  "geometry": {"coordinates":[-73.5701751709,45.5732803345],"type":"Point"}
}