{
  "type": "Feature",
  "properties": {
    "addr:full":"2710 Kaslo St Vancouver BC V5M 4J1",
    "addr:housenumber":"2710",
    "addr:postcode":"v5m 4j1",
    "addr:street":"Kaslo St",
    "iso:country":"CA",
    "sg:address":"2710 Kaslo St",
    "sg:city":"Vancouver",
    "sg:classifiers":[
        {
            "category":"Manufacturing",
            "subcategory":"Signs",
            "type":"Manufacturing & Wholesale Goods"
        }
    ],
    "sg:phone":"+1 604 215 5526",
    "sg:postcode":"V5M 4J1",
    "sg:province":"BC",
    "wof:name":"Pattison Sign Group",
    "wof:placetype":"venue"
},
  "geometry": {"coordinates":[-123.04689,49.259953],"type":"Point"}
}