{
  "type": "Feature",
  "properties": {
    "addr:full":"1550 Rue Prevert Laval QC H7R 3W4",
    "addr:housenumber":"1550",
    "addr:postcode":"h7r 3w4",
    "addr:street":"Rue Prevert",
    "iso:country":"CA",
    "sg:address":"1550 Rue Prevert",
    "sg:city":"Laval",
    "sg:classifiers":[
        {
            "category":"Personal",
            "subcategory":"Beauty Salon",
            "type":"Services"
        }
    ],
    "sg:phone":"+1 450 627 7051",
    "sg:postcode":"H7R 3W4",
    "sg:province":"QC",
    "wof:name":"Maniel Coiffure",
    "wof:placetype":"venue"
},
  "geometry": {"coordinates":[-73.872597,45.554333],"type":"Point"}
}