{
  "type": "Feature",
  "properties": {
    "addr:full":"84 Rte 125 Saint-Esprit QC J0K 2L0",
    "addr:housenumber":"84",
    "addr:postcode":"j0k 2l0",
    "addr:street":"Rte 125",
    "iso:country":"CA",
    "sg:address":"84 Rte 125",
    "sg:city":"Saint-Esprit",
    "sg:classifiers":[
        {
            "category":"Freight",
            "type":"Transportation"
        }
    ],
    "sg:phone":"+1 450 839 7399",
    "sg:postcode":"J0K 2L0",
    "sg:province":"QC",
    "sg:tags":[
        "trucking"
    ],
    "wof:name":"Solutions Transit Inc",
    "wof:placetype":"venue"
},
  "geometry": {"coordinates":[-73.68926999999999,45.915787],"type":"Point"}
}