{
  "type": "Feature",
  "properties": {
    "addr:full":"232 Arlington St Winnipeg MB R3G 1Y8",
    "addr:housenumber":"232",
    "addr:postcode":"r3g 1y8",
    "addr:street":"Arlington St",
    "iso:country":"CA",
    "sg:address":"232 Arlington St",
    "sg:city":"Winnipeg",
    "sg:classifiers":[
        {
            "category":"Health Services",
            "subcategory":"Chiropractor",
            "type":"Services"
        }
    ],
    "sg:phone":"+1 204 667 7463",
    "sg:postcode":"R3G 1Y8",
    "sg:province":"MB",
    "wof:name":"Jackson, Greg DC",
    "wof:placetype":"venue"
},
  "geometry": {"coordinates":[-97.169724,49.884201],"type":"Point"}
}