{
  "type": "Feature",
  "properties": {
    "addr:full":"224 Talbot St N Essex ON N8M 2C8",
    "addr:housenumber":"224",
    "addr:postcode":"n8m 2c8",
    "addr:street":"Talbot St N",
    "iso:country":"CA",
    "sg:address":"224 Talbot St N",
    "sg:city":"Essex",
    "sg:classifiers":[
        {
            "category":"Autos & Motor Vehicles",
            "subcategory":"Automobile Sales",
            "type":"Retail Goods"
        }
    ],
    "sg:phone":"+1 519 776 4222",
    "sg:postcode":"N8M 2C8",
    "sg:province":"ON",
    "sg:tags":[
        "car",
        "dealer"
    ],
    "wof:name":"Dave Hitchcock Chevrolet Olds",
    "wof:placetype":"venue"
},
  "geometry": {"coordinates":[-82.82763671879999,42.1791687012],"type":"Point"}
}