{
  "type": "Feature",
  "properties": {
    "iso:country":"CA",
    "sg:city":"Montreal",
    "sg:classifiers":[
        {
            "category":"Health Services",
            "subcategory":"Doctor",
            "type":"Services"
        }
    ],
    "sg:phone":"+1 514 332 4009",
    "sg:postcode":"H4J 2J6",
    "sg:province":"QC",
    "sg:tags":[
        "ophthalmologist"
    ],
    "wof:name":"Tardif, Denis",
    "wof:placetype":"venue"
},
  "geometry": {"coordinates":[-73.71825408940001,45.5312194824],"type":"Point"}
}