{
  "type": "Feature",
  "properties": {
    "addr:full":"191 Osborne St Winnipeg MB R3L 1Z2",
    "addr:housenumber":"191",
    "addr:postcode":"r3l 1z2",
    "addr:street":"Osborne St",
    "iso:country":"CA",
    "sg:address":"191 Osborne St",
    "sg:city":"Winnipeg",
    "sg:classifiers":[
        {
            "category":"Restaurant",
            "type":"Food & Drink"
        }
    ],
    "sg:phone":"+1 204 633 6907",
    "sg:postcode":"R3L 1Z2",
    "sg:province":"MB",
    "wof:name":"Sukhothai",
    "wof:placetype":"venue"
},
  "geometry": {"coordinates":[-97.14363899999999,49.876274],"type":"Point"}
}