{
  "type": "Feature",
  "properties": {
    "addr:full":"202 Rue Saint-Zotique O Montreal QC H2V 4S9",
    "addr:housenumber":"202",
    "addr:postcode":"h2v 4s9",
    "addr:street":"Rue Saint-Zotique O",
    "iso:country":"CA",
    "sg:address":"202 Rue Saint-Zotique O",
    "sg:city":"Montreal",
    "sg:classifiers":[
        {
            "category":"Freight",
            "type":"Transportation"
        }
    ],
    "sg:phone":"+1 514 278 4444",
    "sg:postcode":"H2V 4S9",
    "sg:province":"QC",
    "sg:tags":[
        "commercial",
        "storage"
    ],
    "wof:name":"Mini Entreposage LA Cite",
    "wof:placetype":"venue"
},
  "geometry": {"coordinates":[-73.610206604,45.5335350037],"type":"Point"}
}