{
  "type": "Feature",
  "properties": {
    "addr:full":"5 Rue Egan Quyon QC J0X 2V0",
    "addr:housenumber":"5",
    "addr:postcode":"j0x 2v0",
    "addr:street":"Rue Egan",
    "iso:country":"CA",
    "sg:address":"5 Rue Egan",
    "sg:city":"Quyon",
    "sg:classifiers":[
        {
            "category":"Wholesale",
            "subcategory":"Farm Supplies",
            "type":"Manufacturing & Wholesale Goods"
        }
    ],
    "sg:phone":"+1 819 458 2023",
    "sg:postcode":"J0X 2V0",
    "sg:province":"QC",
    "sg:tags":[
        "roofing",
        "material"
    ],
    "wof:name":"M & R Feed & Farm Supply",
    "wof:placetype":"venue"
},
  "geometry": {"coordinates":[-76.236732,45.520958],"type":"Point"}
}