{
  "type": "Feature",
  "properties": {
    "addr:full":"1445 St Matthews Ave Winnipeg MB R3G 0K7",
    "addr:housenumber":"1445",
    "addr:postcode":"r3g 0k7",
    "addr:street":"St Matthews Ave",
    "iso:country":"CA",
    "sg:address":"1445 St Matthews Ave",
    "sg:city":"Winnipeg",
    "sg:classifiers":[
        {
            "category":"Shopping",
            "subcategory":"Hobbies, Toys, & Games",
            "type":"Retail Goods"
        }
    ],
    "sg:phone":"+1 204 982 8697",
    "sg:postcode":"R3G 0K7",
    "sg:province":"MB",
    "wof:name":"Toys R US",
    "wof:placetype":"venue"
},
  "geometry": {"coordinates":[-97.196487,49.891026],"type":"Point"}
}