{
  "type": "Feature",
  "properties": {
    "addr:full":"2420 39 Ave NE Calgary AB T2E 6X1",
    "addr:housenumber":"2420",
    "addr:postcode":"t2e 6x1",
    "addr:street":"39 Ave Ne",
    "iso:country":"CA",
    "sg:address":"2420 39 Ave NE",
    "sg:city":"Calgary",
    "sg:classifiers":[
        {
            "category":"Manufacturing",
            "subcategory":"Metals",
            "type":"Manufacturing & Wholesale Goods"
        }
    ],
    "sg:phone":"+1 403 250 2000",
    "sg:postcode":"T2E 6X1",
    "sg:province":"AB",
    "sg:tags":[
        "door"
    ],
    "wof:name":"Stylecraft Door Mfg",
    "wof:placetype":"venue"
},
  "geometry": {"coordinates":[-114.004402,51.088364],"type":"Point"}
}