{
  "type": "Feature",
  "properties": {
    "addr:full":"6172 Quinpool Rd Halifax NS B3L 1A3",
    "addr:housenumber":"6172",
    "addr:postcode":"b3l 1a3",
    "addr:street":"Quinpool Rd",
    "iso:country":"CA",
    "sg:address":"6172 Quinpool Rd",
    "sg:city":"Halifax",
    "sg:classifiers":[
        {
            "category":"Shopping",
            "subcategory":"Florist",
            "type":"Retail Goods"
        }
    ],
    "sg:phone":"+1 902 423 7746",
    "sg:postcode":"B3L 1A3",
    "sg:province":"NS",
    "wof:name":"Charles & Vern's Flower Salon",
    "wof:placetype":"venue"
},
  "geometry": {"coordinates":[-63.595024,44.645859],"type":"Point"}
}