{
  "type": "Feature",
  "properties": {
    "addr:full":"2760 Rue Laval Nantes QC G6B 1A1",
    "addr:housenumber":"2760",
    "addr:postcode":"g6b 1a1",
    "addr:street":"Rue Laval",
    "iso:country":"CA",
    "sg:address":"2760 Rue Laval",
    "sg:city":"Nantes",
    "sg:classifiers":[
        {
            "category":"Autos & Motor Vehicles",
            "subcategory":"Motorcycle Sales",
            "type":"Retail Goods"
        }
    ],
    "sg:phone":"+1 819 583 5266",
    "sg:postcode":"G6B 1A1",
    "sg:province":"QC",
    "sg:tags":[
        "all",
        "terrain"
    ],
    "wof:name":"Garage Rejean Roy",
    "wof:placetype":"venue"
},
  "geometry": {"coordinates":[-70.917191,45.596546],"type":"Point"}
}