{
  "type": "Feature",
  "properties": {
    "addr:full":"1780 Albion Rd Etobicoke ON M9V 1C1",
    "addr:housenumber":"1780",
    "addr:postcode":"m9v 1c1",
    "addr:street":"Albion Rd",
    "iso:country":"CA",
    "sg:address":"1780 Albion Rd",
    "sg:city":"Etobicoke",
    "sg:classifiers":[
        {
            "category":"Retail",
            "subcategory":"Auto Repair",
            "type":"Services"
        }
    ],
    "sg:phone":"+1 416 740 1555",
    "sg:postcode":"M9V 1C1",
    "sg:province":"ON",
    "sg:tags":[
        "repairing",
        "automobile"
    ],
    "wof:name":"Gta Auto Ctr",
    "wof:placetype":"venue"
},
  "geometry": {"coordinates":[-79.6046905518,43.7439193726],"type":"Point"}
}