{
  "type": "Feature",
  "properties": {
    "addr:full":"36 Cleveland St Thorold ON L2V 3K4",
    "addr:housenumber":"36",
    "addr:postcode":"l2v 3k4",
    "addr:street":"Cleveland St",
    "iso:country":"CA",
    "sg:address":"36 Cleveland St",
    "sg:city":"Thorold",
    "sg:classifiers":[
        {
            "category":"Restaurant",
            "type":"Food & Drink"
        }
    ],
    "sg:phone":"+1 905 227 0121",
    "sg:postcode":"L2V 3K4",
    "sg:province":"ON",
    "sg:tags":[
        "banquet",
        "rooms"
    ],
    "wof:name":"Club Capri",
    "wof:placetype":"venue"
},
  "geometry": {"coordinates":[-79.20027899999999,43.118824],"type":"Point"}
}