{
  "type": "Feature",
  "properties": {
    "iso:country":"CA",
    "sg:address":"232 Combe Ave",
    "sg:city":"North York",
    "sg:classifiers":[
        {
            "category":"Professional",
            "type":"Services"
        }
    ],
    "sg:phone":"+1 416 630 2500",
    "sg:postcode":"M3H 4K7",
    "sg:province":"ON",
    "sg:tags":[
        "general",
        "establishment",
        "contractor"
    ],
    "wof:name":"Dufferin Dock & Door Ltd",
    "wof:placetype":"venue"
},
  "geometry": {"coordinates":[-79.46281433110001,43.7582168579],"type":"Point"}
}