{
  "type": "Feature",
  "properties": {
    "addr:full":"449 Dundas St Woodstock ON N4S 1C2",
    "addr:housenumber":"449",
    "addr:postcode":"n4s 1c2",
    "addr:street":"Dundas St",
    "iso:country":"CA",
    "sg:address":"449 Dundas St",
    "sg:city":"Woodstock",
    "sg:classifiers":[
        {
            "category":"Shopping",
            "subcategory":"Pharmacy",
            "type":"Retail Goods"
        }
    ],
    "sg:phone":"+1 519 537 3491",
    "sg:postcode":"N4S 1C2",
    "sg:province":"ON",
    "wof:name":"Parkes Shoppers Drug Mart",
    "wof:placetype":"venue"
},
  "geometry": {"coordinates":[-80.758247,43.130013],"type":"Point"}
}