{
  "type": "Feature",
  "properties": {
    "addr:full":"North York ON M3B 3J5",
    "addr:postcode":"m3b 3j5",
    "iso:country":"CA",
    "sg:city":"North York",
    "sg:classifiers":[
        {
            "category":"Shopping",
            "subcategory":"Computers & Home Electronics",
            "type":"Retail Goods"
        }
    ],
    "sg:phone":"+1 416 383 1010",
    "sg:postcode":"M3B 3J5",
    "sg:province":"ON",
    "sg:tags":[
        "software"
    ],
    "wof:name":"Kroll Computer Systems Inc",
    "wof:placetype":"venue"
},
  "geometry": {"coordinates":[-79.3519287109,43.7618484497],"type":"Point"}
}