{
  "type": "Feature",
  "properties": {
    "iso:country":"CA",
    "sg:address":"204 Av Dorval",
    "sg:city":"Dorval",
    "sg:classifiers":[
        {
            "category":"Cinema",
            "subcategory":"Movie Rental",
            "type":"Entertainment"
        }
    ],
    "sg:phone":"+1 514 631 5575",
    "sg:postcode":"H9S 3H3",
    "sg:province":"QC",
    "sg:tags":[
        "leasing",
        "video",
        "disc",
        "tape"
    ],
    "wof:name":"Mega Video",
    "wof:placetype":"venue"
},
  "geometry": {"coordinates":[-73.74044036870001,45.4415168762],"type":"Point"}
}