{
  "type": "Feature",
  "properties": {
    "addr:full":"7179 10th Ave Burnaby BC V3N 2R6",
    "addr:housenumber":"7179",
    "addr:postcode":"v3n 2r6",
    "addr:street":"10Th Ave",
    "iso:country":"CA",
    "sg:address":"7179 10th Ave",
    "sg:city":"Burnaby",
    "sg:classifiers":[
        {
            "category":"Building & Trades",
            "subcategory":"Electrical",
            "type":"Services"
        }
    ],
    "sg:phone":"+1 604 526 4774",
    "sg:postcode":"V3N 2R6",
    "sg:province":"BC",
    "sg:tags":[
        "home",
        "improvement",
        "electric",
        "contractor"
    ],
    "wof:name":"Rich-Mar Electric Ltd",
    "wof:placetype":"venue"
},
  "geometry": {"coordinates":[-122.94526672400001,49.209602356],"type":"Point"}
}