{
  "type": "Feature",
  "properties": {
    "addr:full":"59 Char St Kitimat BC V8C 2K6",
    "addr:housenumber":"59",
    "addr:postcode":"bc v8c 2k6",
    "addr:street":"Char St",
    "iso:country":"CA",
    "sg:address":"59 Char St",
    "sg:city":"Kitimat",
    "sg:classifiers":[
        {
            "category":"Building & Trades",
            "subcategory":"Electrical",
            "type":"Services"
        }
    ],
    "sg:phone":"+1 250 632 6825",
    "sg:postcode":"V8C 2K6",
    "sg:province":"BC",
    "sg:tags":[
        "electric",
        "contractor"
    ],
    "wof:name":"Orca Electric Ltd",
    "wof:placetype":"venue"
},
  "geometry": {"coordinates":[-128.60801699999999,54.09803],"type":"Point"}
}