{
  "type": "Feature",
  "properties": {
    "addr:full":"420 Elgin St Sudbury ON P3B 1B2",
    "addr:housenumber":"420",
    "addr:postcode":"p3b 1b2",
    "addr:street":"Elgin St",
    "iso:country":"CA",
    "sg:address":"420 Elgin St",
    "sg:city":"Sudbury",
    "sg:classifiers":[
        {
            "category":"Restaurant",
            "type":"Food & Drink"
        }
    ],
    "sg:phone":"+1 705 675 6916",
    "sg:postcode":"P3B 1B2",
    "sg:province":"ON",
    "wof:name":"Boomers",
    "wof:placetype":"venue"
},
  "geometry": {"coordinates":[-80.9880828857,46.4858665466],"type":"Point"}
}