{
  "type": "Feature",
  "properties": {
    "addr:full":"Waterloo ON N2J 3H4",
    "addr:postcode":"n2j 3h4",
    "iso:country":"CA",
    "sg:city":"Waterloo",
    "sg:classifiers":[
        {
            "category":"Retail",
            "subcategory":"Auto Repair",
            "type":"Services"
        }
    ],
    "sg:phone":"+1 519 886 2821",
    "sg:postcode":"N2J 3H4",
    "sg:province":"ON",
    "sg:tags":[
        "repairing",
        "automobile"
    ],
    "wof:name":"Terry Forler Automotive",
    "wof:placetype":"venue"
},
  "geometry": {"coordinates":[-80.5173873901,43.4753799438],"type":"Point"}
}