{
  "type": "Feature",
  "properties": {
    "iso:country":"CA",
    "sg:address":"1339 Rte Principale",
    "sg:city":"Tres-Saint-Redempteur",
    "sg:classifiers":[
        {
            "category":"Shopping",
            "subcategory":"Bicycles & Sporting Goods",
            "type":"Retail Goods"
        }
    ],
    "sg:phone":"+1 450 451 5581",
    "sg:postcode":"J0P 1P0",
    "sg:province":"QC",
    "sg:tags":[
        "equipment",
        "sauna",
        "supply"
    ],
    "wof:name":"Guy Guenette Sauna Select Inc",
    "wof:placetype":"venue"
},
  "geometry": {"coordinates":[-74.4216537476,45.4256896973],"type":"Point"}
}