{
  "type": "Feature",
  "properties": {
    "addr:full":"Saint-Hyacinthe QC J2S 4Z1",
    "addr:postcode":"j2s 4z1",
    "iso:country":"CA",
    "sg:city":"Saint-Hyacinthe",
    "sg:classifiers":[
        {
            "category":"Professional",
            "subcategory":"Management & Consulting",
            "type":"Services"
        }
    ],
    "sg:phone":"+1 450 771 6800",
    "sg:postcode":"J2S 4Z1",
    "sg:province":"QC",
    "sg:tags":[
        "farm",
        "agricultural",
        "consultant"
    ],
    "wof:name":"G Villeneuve Inc",
    "wof:placetype":"venue"
},
  "geometry": {"coordinates":[-72.96219600000001,45.634014],"type":"Point"}
}