{
  "type": "Feature",
  "properties": {
    "iso:country":"CA",
    "sg:address":"22 Stevenson Rd S",
    "sg:city":"Oshawa",
    "sg:classifiers":[
        {
            "category":"Shopping",
            "subcategory":"Clothing, Apparel, & Fashions",
            "type":"Retail Goods"
        }
    ],
    "sg:phone":"+1 905 432 7682",
    "sg:postcode":"L1J 5L9",
    "sg:province":"ON",
    "sg:tags":[
        "sportswear"
    ],
    "wof:name":"Official Sports Section Inc",
    "wof:placetype":"venue"
},
  "geometry": {"coordinates":[-78.88327,43.89246],"type":"Point"}
}