{
  "type": "Feature",
  "properties": {
    "iso:country":"CA",
    "sg:address":"116 Hurontario St",
    "sg:city":"Collingwood",
    "sg:classifiers":[
        {
            "category":"Shopping",
            "subcategory":"Photographic Equipment",
            "type":"Retail Goods"
        }
    ],
    "sg:phone":"+1 705 445 3611",
    "sg:postcode":"L9Y 2L8",
    "sg:province":"ON",
    "sg:tags":[
        "photo",
        "finishing"
    ],
    "wof:name":"Carmen's Foto Source",
    "wof:placetype":"venue"
},
  "geometry": {"coordinates":[-80.21700286870001,44.4998321533],"type":"Point"}
}