{
  "type": "Feature",
  "properties": {
    "addr:full":"Candiac QC J5R 3L5",
    "addr:postcode":"j5r 3l5",
    "iso:country":"CA",
    "sg:city":"Candiac",
    "sg:classifiers":[
        {
            "category":"Professional",
            "subcategory":"Lawyer & Legal Services",
            "type":"Services"
        }
    ],
    "sg:phone":"+1 450 444 1844",
    "sg:postcode":"J5R 3L5",
    "sg:province":"QC",
    "sg:tags":[
        "attorney"
    ],
    "wof:name":"Dessureault, Jacques",
    "wof:placetype":"venue"
},
  "geometry": {"coordinates":[-73.51551055909999,45.3920211792],"type":"Point"}
}