{
  "type": "Feature",
  "properties": {
    "iso:country":"CA",
    "sg:address":"3551 River Rd W",
    "sg:city":"Delta",
    "sg:classifiers":[
        {
            "category":"Autos & Motor Vehicles",
            "subcategory":"Recreational Vehicle Sales",
            "type":"Retail Goods"
        }
    ],
    "sg:phone":"+1 604 946 0033",
    "sg:postcode":"V4K 3N2",
    "sg:province":"BC",
    "sg:tags":[
        "canopy",
        "shell",
        "truck",
        "cap"
    ],
    "wof:name":"Fibermold Truck Canopys",
    "wof:placetype":"venue"
},
  "geometry": {"coordinates":[-123.125289917,49.0811195374],"type":"Point"}
}