{
  "type": "Feature",
  "properties": {
    "addr:full":"240 Catherine St Ottawa ON K2P 2G8",
    "addr:housenumber":"240",
    "addr:postcode":"k2p 2g8",
    "addr:street":"Catherine St",
    "iso:country":"CA",
    "sg:address":"240 Catherine St",
    "sg:city":"Ottawa",
    "sg:classifiers":[
        {
            "category":"Organizations",
            "subcategory":"Professional Association",
            "type":"Services"
        }
    ],
    "sg:phone":"+1 613 236 6451",
    "sg:postcode":"K2P 2G8",
    "sg:province":"ON",
    "wof:name":"Canadian Seed Institute",
    "wof:placetype":"venue"
},
  "geometry": {"coordinates":[-75.6932754517,45.4088249207],"type":"Point"}
}