{
  "type": "Feature",
  "properties": {
    "addr:full":"Vaudreuil-Dorion QC J7V 8P2",
    "addr:postcode":"j7v 8p2",
    "iso:country":"CA",
    "sg:city":"Vaudreuil-Dorion",
    "sg:classifiers":[
        {
            "category":"Shopping",
            "subcategory":"Clothing, Apparel, & Fashions",
            "type":"Retail Goods"
        }
    ],
    "sg:phone":"+1 450 458 7088",
    "sg:postcode":"J7V 8P2",
    "sg:province":"QC",
    "sg:tags":[
        "leather",
        "riding",
        "equipment"
    ],
    "wof:name":"Wilson Saddlery",
    "wof:placetype":"venue"
},
  "geometry": {"coordinates":[-74.1106185913,45.4295310974],"type":"Point"}
}