{
  "type": "Feature",
  "properties": {
    "addr:full":"320 Main St Aylesbury SK S0G 0B0",
    "addr:housenumber":"320",
    "addr:postcode":"s0g 0b0",
    "addr:street":"Main St",
    "iso:country":"CA",
    "sg:address":"320 Main St",
    "sg:city":"Aylesbury",
    "sg:classifiers":[
        {
            "category":"Travel",
            "subcategory":"Hotels & Motels",
            "type":"Entertainment"
        }
    ],
    "sg:phone":"+1 306 734 2928",
    "sg:postcode":"S0G 0B0",
    "sg:province":"SK",
    "wof:name":"Aylesbury Hotel",
    "wof:placetype":"venue"
},
  "geometry": {"coordinates":[-105.69396999999999,50.938984],"type":"Point"}
}