{
  "type": "Feature",
  "properties": {
    "addr:full":"829 5th Ave Prince George BC V2L 3K5",
    "addr:housenumber":"829",
    "addr:postcode":"v2l 3k5",
    "addr:street":"5Th Ave",
    "iso:country":"CA",
    "sg:address":"829 5th Ave",
    "sg:city":"Prince George",
    "sg:classifiers":[
        {
            "category":"Building & Trades",
            "subcategory":"Construction",
            "type":"Services"
        }
    ],
    "sg:phone":"+1 250 562 8747",
    "sg:postcode":"V2L 3K5",
    "sg:province":"BC",
    "sg:tags":[
        "roofing",
        "contractor"
    ],
    "wof:name":"Arctic Roofing Ltd",
    "wof:placetype":"venue"
},
  "geometry": {"coordinates":[-122.739799,53.913197],"type":"Point"}
}