{
  "type": "Feature",
  "properties": {
    "iso:country":"CA",
    "sg:address":"16 Rue Trempe",
    "sg:city":"Cadillac",
    "sg:classifiers":[
        {
            "category":"Manufacturing",
            "subcategory":"Furniture",
            "type":"Manufacturing & Wholesale Goods"
        }
    ],
    "sg:phone":"+1 819 759 4774",
    "sg:postcode":"J0Y 1C0",
    "sg:province":"QC",
    "sg:tags":[
        "exposition",
        "stand"
    ],
    "wof:name":"Exponord Inc",
    "wof:placetype":"venue"
},
  "geometry": {"coordinates":[-78.3884353638,48.2248954773],"type":"Point"}
}