{
  "type": "Feature",
  "properties": {
    "addr:full":"25 Centennial Lane Millbrook ON L0A 1G0",
    "addr:housenumber":"25",
    "addr:postcode":"l0a 1g0",
    "addr:street":"Centennial Lane",
    "iso:country":"CA",
    "sg:address":"25 Centennial Lane",
    "sg:city":"Millbrook",
    "sg:classifiers":[
        {
            "category":"Government",
            "subcategory":"Office",
            "type":"Public Place"
        }
    ],
    "sg:phone":"+1 705 932 2802",
    "sg:postcode":"L0A 1G0",
    "sg:province":"ON",
    "sg:tags":[
        "village"
    ],
    "wof:name":"Ontario Water Treatment Plant",
    "wof:placetype":"venue"
},
  "geometry": {"coordinates":[-78.44813499999999,44.155602],"type":"Point"}
}