{
  "type": "Feature",
  "properties": {
    "addr:full":"RR 2 Thorsby AB T0C 2P0",
    "addr:postcode":"t0c 2p0",
    "addr:street":"Rr 2",
    "iso:country":"CA",
    "sg:address":"RR 2",
    "sg:city":"Thorsby",
    "sg:classifiers":[
        {
            "category":"Retail",
            "subcategory":"Animal Services",
            "type":"Services"
        }
    ],
    "sg:phone":"+1 780 389 3737",
    "sg:postcode":"T0C 2P0",
    "sg:province":"AB",
    "sg:tags":[
        "breeder",
        "horse"
    ],
    "wof:name":"DE-Bon Enterprises Ltd",
    "wof:placetype":"venue"
},
  "geometry": {"coordinates":[-114.05059799999999,53.228065],"type":"Point"}
}