{
  "type": "Feature",
  "properties": {
    "addr:full":"314 Ellwood Cres Bobcaygeon ON K0M 1A0",
    "addr:housenumber":"314",
    "addr:postcode":"k0m 1a0",
    "addr:street":"Ellwood Cres",
    "iso:country":"CA",
    "sg:address":"314 Ellwood Cres",
    "sg:city":"Bobcaygeon",
    "sg:classifiers":[
        {
            "category":"Building & Trades",
            "subcategory":"Plumbing",
            "type":"Services"
        }
    ],
    "sg:phone":"+1 705 738 4384",
    "sg:postcode":"K0M 1A0",
    "sg:province":"ON",
    "sg:tags":[
        "contractor"
    ],
    "wof:name":"Junkin Murry Plumbing",
    "wof:placetype":"venue"
},
  "geometry": {"coordinates":[-78.53755187989999,44.5363006592],"type":"Point"}
}