{
  "type": "Feature",
  "properties": {
    "addr:full":"1883 Fort St Victoria BC V8R 1K1",
    "addr:housenumber":"1883",
    "addr:postcode":"v8r 1k1",
    "addr:street":"Fort St",
    "iso:country":"CA",
    "sg:address":"1883 Fort St",
    "sg:city":"Victoria",
    "sg:classifiers":[
        {
            "category":"Restaurant",
            "type":"Food & Drink"
        }
    ],
    "sg:phone":"+1 250 598 3228",
    "sg:postcode":"V8R 1K1",
    "sg:province":"BC",
    "sg:tags":[
        "caterer"
    ],
    "wof:name":"Cooks Day Off",
    "wof:placetype":"venue"
},
  "geometry": {"coordinates":[-123.327248,48.430859],"type":"Point"}
}