{
  "type": "Feature",
  "properties": {
    "addr:full":"33 Maple Valley Rd Corner Brook NL A2H 3C4",
    "addr:housenumber":"33",
    "addr:postcode":"a2h 3c4",
    "addr:street":"Maple Valley Rd",
    "iso:country":"CA",
    "sg:address":"33 Maple Valley Rd",
    "sg:city":"Corner Brook",
    "sg:classifiers":[
        {
            "category":"Retail",
            "subcategory":"Auto Repair",
            "type":"Services"
        }
    ],
    "sg:phone":"+1 709 632 7767",
    "sg:postcode":"A2H 3C4",
    "sg:province":"NL",
    "sg:tags":[
        "repairing",
        "automobile"
    ],
    "wof:name":"Corner Brook Autopro",
    "wof:placetype":"venue"
},
  "geometry": {"coordinates":[-57.916954,48.950653],"type":"Point"}
}