{
  "type": "Feature",
  "properties": {
    "addr:full":"503 Oakdale Rd North York ON M3N 1W7",
    "addr:housenumber":"503",
    "addr:postcode":"m3n 1w7",
    "addr:street":"Oakdale Rd",
    "iso:country":"CA",
    "sg:address":"503 Oakdale Rd",
    "sg:city":"North York",
    "sg:classifiers":[
        {
            "category":"Wholesale",
            "subcategory":"Apparel",
            "type":"Manufacturing & Wholesale Goods"
        }
    ],
    "sg:phone":"+1 416 742 1950",
    "sg:postcode":"M3N 1W7",
    "sg:province":"ON",
    "sg:tags":[
        "clothing"
    ],
    "wof:name":"Crossbar Athletic Wear Ltd",
    "wof:placetype":"venue"
},
  "geometry": {"coordinates":[-79.526543,43.750134],"type":"Point"}
}