{
  "type": "Feature",
  "properties": {
    "addr:full":"Winnipeg MB R3B 1G5",
    "addr:postcode":"r3b 1g5",
    "iso:country":"CA",
    "sg:city":"Winnipeg",
    "sg:classifiers":[
        {
            "category":"Manufacturing",
            "subcategory":"Printing",
            "type":"Manufacturing & Wholesale Goods"
        }
    ],
    "sg:phone":"+1 204 957 1519",
    "sg:postcode":"R3B 1G5",
    "sg:province":"MB",
    "sg:tags":[
        "publisher"
    ],
    "wof:name":"Canadian Dimension Magazine",
    "wof:placetype":"venue"
},
  "geometry": {"coordinates":[-97.139961,49.8974],"type":"Point"}
}