{
  "type": "Feature",
  "properties": {
    "iso:country":"CA",
    "sg:address":"2 Collier St",
    "sg:city":"Barrie",
    "sg:classifiers":[
        {
            "category":"Shopping",
            "subcategory":"Gifts & Souvenirs",
            "type":"Retail Goods"
        }
    ],
    "sg:phone":"+1 705 728 2395",
    "sg:postcode":"L4M 1G3",
    "sg:province":"ON",
    "sg:tags":[
        "shop",
        "glassware",
        "chinaware"
    ],
    "wof:name":"Steele's China & Gift Shop Ltd",
    "wof:placetype":"venue"
},
  "geometry": {"coordinates":[-79.6908798218,44.3904457092],"type":"Point"}
}