{
  "type": "Feature",
  "properties": {
    "addr:full":"349 Dunsmuir Bowser BC V0R 1G0",
    "addr:housenumber":"349",
    "addr:postcode":"v0r 1g0",
    "addr:street":"Dunsmuir",
    "iso:country":"CA",
    "sg:address":"349 Dunsmuir",
    "sg:city":"Bowser",
    "sg:classifiers":[
        {
            "category":"Social Services",
            "type":"Services"
        }
    ],
    "sg:phone":"+1 250 248 7273",
    "sg:postcode":"V0R 1G0",
    "sg:province":"BC",
    "sg:tags":[
        "organization",
        "welfare"
    ],
    "wof:name":"Alcoholics Anonymous",
    "wof:placetype":"venue"
},
  "geometry": {"coordinates":[-124.70038599999999,49.44511],"type":"Point"}
}