{
  "type": "Feature",
  "properties": {
    "addr:full":"Saint-Albert QC J0A 1E0",
    "addr:postcode":"j0a 1e0",
    "iso:country":"CA",
    "sg:city":"Saint-Albert",
    "sg:classifiers":[
        {
            "category":"Autos & Motor Vehicles",
            "subcategory":"Fuel & Gas Station",
            "type":"Retail Goods"
        }
    ],
    "sg:phone":"+1 819 353 2520",
    "sg:postcode":"J0A 1E0",
    "sg:province":"QC",
    "sg:tags":[
        "oil"
    ],
    "wof:name":"Station Service Astro Inc",
    "wof:placetype":"venue"
},
  "geometry": {"coordinates":[-72.086327,46.003563],"type":"Point"}
}