{
  "type": "Feature",
  "properties": {
    "addr:full":"Parksville BC V9P 2B7",
    "addr:postcode":"v9p 2b7",
    "iso:country":"CA",
    "sg:city":"Parksville",
    "sg:classifiers":[
        {
            "category":"Insurance",
            "subcategory":"Insurance Agent",
            "type":"Services"
        }
    ],
    "sg:phone":"+1 250 248 4351",
    "sg:postcode":"V9P 2B7",
    "sg:province":"BC",
    "wof:name":"Alder Insurance Svc Ltd",
    "wof:placetype":"venue"
},
  "geometry": {"coordinates":[-124.345870972,49.3324432373],"type":"Point"}
}