{
  "type": "Feature",
  "properties": {
    "addr:full":"3697 Boul Saint-Laurent Montreal QC H2X 2V7",
    "addr:housenumber":"3697",
    "addr:postcode":"h2x 2v7",
    "addr:street":"Boul Saint-Laurent",
    "iso:country":"CA",
    "sg:address":"3697 Boul Saint-Laurent",
    "sg:city":"Montreal",
    "sg:classifiers":[
        {
            "category":"Shopping",
            "subcategory":"Music",
            "type":"Retail Goods"
        }
    ],
    "sg:phone":"+1 514 985 9989",
    "sg:postcode":"H2X 2V7",
    "sg:province":"QC",
    "sg:tags":[
        "compact",
        "record",
        "disc",
        "tape"
    ],
    "wof:name":"Noize",
    "wof:placetype":"venue"
},
  "geometry": {"coordinates":[-73.574303,45.514816],"type":"Point"}
}