{
  "type": "Feature",
  "properties": {
    "addr:full":"33 Glenwood Dr Chatham ON N7L 3X1",
    "addr:housenumber":"33",
    "addr:postcode":"n7l 3x1",
    "addr:street":"Glenwood Dr",
    "iso:country":"CA",
    "sg:address":"33 Glenwood Dr",
    "sg:city":"Chatham",
    "sg:classifiers":[
        {
            "category":"Building & Trades",
            "subcategory":"Construction",
            "type":"Services"
        }
    ],
    "sg:phone":"+1 519 354 8928",
    "sg:postcode":"N7L 3X1",
    "sg:province":"ON",
    "sg:tags":[
        "contractor"
    ],
    "wof:name":"Multi Construction Ltd",
    "wof:placetype":"venue"
},
  "geometry": {"coordinates":[-82.1999282837,42.4175071716],"type":"Point"}
}