{
  "type": "Feature",
  "properties": {
    "addr:full":"114 Centennial Dr E Thompson MB R8N 1K1",
    "addr:housenumber":"114",
    "addr:postcode":"r8n 1k1",
    "addr:street":"Centennial Dr E Thompson",
    "iso:country":"CA",
    "sg:address":"114 Centennial Dr E",
    "sg:city":"Thompson",
    "sg:classifiers":[
        {
            "category":"Building & Trades",
            "subcategory":"Plumbing",
            "type":"Services"
        }
    ],
    "sg:phone":"+1 204 778 7206",
    "sg:postcode":"R8N 1K1",
    "sg:province":"MB",
    "sg:tags":[
        "contractor"
    ],
    "wof:name":"Thompson Plumbing & Heating",
    "wof:placetype":"venue"
},
  "geometry": {"coordinates":[-97.858543,55.733234],"type":"Point"}
}