{
  "type": "Feature",
  "properties": {
    "iso:country":"CA",
    "sg:address":"299 24th St",
    "sg:city":"West Vancouver",
    "sg:classifiers":[
        {
            "category":"Professional",
            "subcategory":"Business Services",
            "type":"Services"
        }
    ],
    "sg:phone":"+1 604 925 1332",
    "sg:postcode":"V7V 4G9",
    "sg:province":"BC",
    "sg:tags":[
        "interior",
        "consultant",
        "design",
        "decorator"
    ],
    "wof:name":"Mary Halliday Interior Design",
    "wof:placetype":"venue"
},
  "geometry": {"coordinates":[-123.179252624,49.3341064453],"type":"Point"}
}