{
  "type": "Feature",
  "properties": {
    "iso:country":"CA",
    "sg:address":"1921 Boul Keller",
    "sg:city":"Saint-Laurent",
    "sg:classifiers":[
        {
            "category":"Retail",
            "subcategory":"Laundry & Dry Cleaning",
            "type":"Services"
        }
    ],
    "sg:phone":"+1 514 332 2879",
    "sg:postcode":"H4K 2V6",
    "sg:province":"QC",
    "sg:tags":[
        "cleaners"
    ],
    "wof:name":"Keller Nettoyer",
    "wof:placetype":"venue"
},
  "geometry": {"coordinates":[-73.712761,45.524536],"type":"Point"}
}