{
  "type": "Feature",
  "properties": {
    "addr:full":"1533 Michael St Ottawa ON K1B 3T3",
    "addr:housenumber":"1533",
    "addr:postcode":"k1b 3t3",
    "addr:street":"Michael St",
    "iso:country":"CA",
    "sg:address":"1533 Michael St",
    "sg:city":"Ottawa",
    "sg:classifiers":[
        {
            "category":"Professional",
            "subcategory":"Business Services",
            "type":"Services"
        }
    ],
    "sg:phone":"+1 613 747 1927",
    "sg:postcode":"K1B 3T3",
    "sg:province":"ON",
    "sg:tags":[
        "embroidery"
    ],
    "wof:name":"Porter's House of Embroidery",
    "wof:placetype":"venue"
},
  "geometry": {"coordinates":[-75.62657900000001,45.412216],"type":"Point"}
}