{
  "type": "Feature",
  "properties": {
    "addr:full":"11850 54E Av Montreal QC H1E 2J3",
    "addr:housenumber":"11850",
    "addr:postcode":"h1e 2j3",
    "addr:street":"54E Av",
    "iso:country":"CA",
    "sg:address":"11850 54E Av",
    "sg:city":"Montreal",
    "sg:classifiers":[
        {
            "category":"Building & Trades",
            "subcategory":"Plumbing",
            "type":"Services"
        }
    ],
    "sg:phone":"+1 514 983 2982",
    "sg:postcode":"H1E 2J3",
    "sg:province":"QC",
    "sg:tags":[
        "contractor"
    ],
    "wof:name":"Tuyauteurs A1",
    "wof:placetype":"venue"
},
  "geometry": {"coordinates":[-73.56424713129999,45.6476325989],"type":"Point"}
}