{
  "type": "Feature",
  "properties": {
    "addr:full":"859 the Queensway Etobicoke ON M8Z 1N8",
    "addr:housenumber":"859",
    "addr:postcode":"m8z 1n8",
    "addr:street":"The Queensway",
    "iso:country":"CA",
    "sg:address":"859 the Queensway",
    "sg:city":"Etobicoke",
    "sg:classifiers":[
        {
            "category":"Autos & Motor Vehicles",
            "subcategory":"Auto Supplies",
            "type":"Retail Goods"
        }
    ],
    "sg:phone":"+1 416 255 0188",
    "sg:postcode":"M8Z 1N8",
    "sg:province":"ON",
    "sg:tags":[
        "tire"
    ],
    "wof:name":"Firestone Tire & Auto Ctr",
    "wof:placetype":"venue"
},
  "geometry": {"coordinates":[-79.5106124878,43.6244773865],"type":"Point"}
}