{
  "type": "Feature",
  "properties": {
    "iso:country":"CA",
    "sg:address":"36 Baxter St",
    "sg:city":"Brantford",
    "sg:classifiers":[
        {
            "category":"Education",
            "subcategory":"School",
            "type":"Public Place"
        }
    ],
    "sg:phone":"+1 519 753 2929",
    "sg:postcode":"N3R 2V8",
    "sg:province":"ON",
    "wof:name":"Braemar House School",
    "wof:placetype":"venue"
},
  "geometry": {"coordinates":[-80.2561798096,43.1690063477],"type":"Point"}
}