{
  "type": "Feature",
  "properties": {
    "addr:full":"434 10th St Hanover ON N4N 1P9",
    "addr:housenumber":"434",
    "addr:postcode":"n4n 1p9",
    "addr:street":"10Th St",
    "iso:country":"CA",
    "sg:address":"434 10th St",
    "sg:city":"Hanover",
    "sg:classifiers":[
        {
            "category":"Shopping",
            "type":"Retail Goods"
        }
    ],
    "sg:phone":"+1 519 364 6866",
    "sg:postcode":"N4N 1P9",
    "sg:province":"ON",
    "sg:tags":[
        "monument"
    ],
    "wof:name":"Hanover Monuments",
    "wof:placetype":"venue"
},
  "geometry": {"coordinates":[-81.0230484009,44.1529350281],"type":"Point"}
}