{
  "type": "Feature",
  "properties": {
    "addr:full":"9140 Boul Perras Montreal QC H1E 7E4",
    "addr:housenumber":"9140",
    "addr:postcode":"h1e 7e4",
    "addr:street":"Boul Perras",
    "iso:country":"CA",
    "sg:address":"9140 Boul Perras",
    "sg:city":"Montreal",
    "sg:classifiers":[
        {
            "category":"Government",
            "subcategory":"Office",
            "type":"Public Place"
        }
    ],
    "sg:phone":"+1 514 872 9814",
    "sg:postcode":"H1E 7E4",
    "sg:province":"QC",
    "sg:tags":[
        "village"
    ],
    "wof:name":"Montreal Maison DE LA Culture",
    "wof:placetype":"venue"
},
  "geometry": {"coordinates":[-73.5775527954,45.6502914429],"type":"Point"}
}