{
  "type": "Feature",
  "properties": {
    "addr:full":"Montreal QC H3G 1W7",
    "addr:postcode":"h3g 1w7",
    "iso:country":"CA",
    "sg:city":"Montreal",
    "sg:classifiers":[
        {
            "category":"Shopping",
            "subcategory":"Clothing, Apparel, & Fashions",
            "type":"Retail Goods"
        }
    ],
    "sg:phone":"+1 514 849 4073",
    "sg:postcode":"H3G 1W7",
    "sg:province":"QC",
    "sg:tags":[
        "dressmaker"
    ],
    "wof:name":"Carmen Alterations",
    "wof:placetype":"venue"
},
  "geometry": {"coordinates":[-73.57622499999999,45.499737],"type":"Point"}
}