{
  "type": "Feature",
  "properties": {
    "iso:country":"CA",
    "sg:address":"505 5th St",
    "sg:city":"Courtenay",
    "sg:classifiers":[
        {
            "category":"Professional",
            "subcategory":"Lawyer & Legal Services",
            "type":"Services"
        }
    ],
    "sg:phone":"+1 250 334 2416",
    "sg:postcode":"V9N 1K2",
    "sg:province":"BC",
    "sg:tags":[
        "attorney"
    ],
    "wof:name":"Ives, Paul R",
    "wof:placetype":"venue"
},
  "geometry": {"coordinates":[-125.00193786600001,49.6899642944],"type":"Point"}
}