{
  "type": "Feature",
  "properties": {
    "addr:full":"Trenton ON K8V 5P5",
    "addr:postcode":"k8v 5p5",
    "iso:country":"CA",
    "sg:city":"Trenton",
    "sg:classifiers":[
        {
            "category":"Shopping",
            "subcategory":"Florist",
            "type":"Retail Goods"
        }
    ],
    "sg:phone":"+1 613 394 3346",
    "sg:postcode":"K8V 5P5",
    "sg:province":"ON",
    "wof:name":"Kaye's Flowers & Gifts",
    "wof:placetype":"venue"
},
  "geometry": {"coordinates":[-77.57025146479999,44.1050796509],"type":"Point"}
}