{
  "type": "Feature",
  "properties": {
    "addr:full":"3333 Crowsnest Trail S Lethbridge AB T1J 4H1",
    "addr:housenumber":"3333",
    "addr:postcode":"t1j 4h1",
    "addr:street":"Crowsnest Trail S",
    "iso:country":"CA",
    "sg:address":"3333 Crowsnest Trail S",
    "sg:city":"Lethbridge",
    "sg:classifiers":[
        {
            "category":"Retail",
            "subcategory":"Animal Services",
            "type":"Services"
        }
    ],
    "sg:phone":"+1 403 328 9692",
    "sg:postcode":"T1J 4H1",
    "sg:province":"AB",
    "sg:tags":[
        "pet",
        "crematory",
        "cemetery"
    ],
    "wof:name":"Lhs Pet Care & Animal Svc",
    "wof:placetype":"venue"
},
  "geometry": {"coordinates":[-112.83374000000001,49.693836],"type":"Point"}
}