{
  "type": "Feature",
  "properties": {
    "addr:full":"2361 Main St London ON N6P 1A7",
    "addr:housenumber":"2361",
    "addr:postcode":"n6p 1a7",
    "addr:street":"Main St",
    "iso:country":"CA",
    "sg:address":"2361 Main St",
    "sg:city":"London",
    "sg:classifiers":[
        {
            "category":"Professional",
            "subcategory":"Management & Consulting",
            "type":"Services"
        }
    ],
    "sg:phone":"+1 519 652 2800",
    "sg:postcode":"N6P 1A7",
    "sg:province":"ON",
    "sg:tags":[
        "food"
    ],
    "wof:name":"Nutritional Management Svc",
    "wof:placetype":"venue"
},
  "geometry": {"coordinates":[-81.29361,42.911346],"type":"Point"}
}