{
  "type": "Feature",
  "properties": {
    "addr:full":"2085 Wallace Ave Comox BC V9M 1W4",
    "addr:housenumber":"2085",
    "addr:postcode":"v9m 1w4",
    "addr:street":"Wallace Ave",
    "iso:country":"CA",
    "sg:address":"2085 Wallace Ave",
    "sg:city":"Comox",
    "sg:classifiers":[
        {
            "category":"Education",
            "subcategory":"School",
            "type":"Public Place"
        }
    ],
    "sg:phone":"+1 250 339 4881",
    "sg:postcode":"V9M 1W4",
    "sg:province":"BC",
    "wof:name":"Comox Elementary School",
    "wof:placetype":"venue"
},
  "geometry": {"coordinates":[-124.938064575,49.677230835],"type":"Point"}
}