{
  "type": "Feature",
  "properties": {
    "addr:full":"474 Ouellette Ave Windsor ON N9A 1B2",
    "addr:housenumber":"474",
    "addr:postcode":"n9a 1b2",
    "addr:street":"Ouellette Ave",
    "iso:country":"CA",
    "sg:address":"474 Ouellette Ave",
    "sg:city":"Windsor",
    "sg:classifiers":[
        {
            "category":"Organizations",
            "subcategory":"Professional Association",
            "type":"Services"
        }
    ],
    "sg:phone":"+1 519 252 5723",
    "sg:postcode":"N9A 1B2",
    "sg:province":"ON",
    "wof:name":"City Centre Business Assn",
    "wof:placetype":"venue"
},
  "geometry": {"coordinates":[-83.0372390747,42.31508255],"type":"Point"}
}