{
  "type": "Feature",
  "properties": {
    "addr:full":"1186 King St Windsor NS B0N 2T0",
    "addr:housenumber":"1186",
    "addr:postcode":"b0n 2t0",
    "addr:street":"King St",
    "iso:country":"CA",
    "sg:address":"1186 King St",
    "sg:city":"Windsor",
    "sg:classifiers":[
        {
            "category":"Real Estate",
            "subcategory":"Developer",
            "type":"Services"
        }
    ],
    "sg:phone":"+1 902 798 9201",
    "sg:postcode":"B0N 2T0",
    "sg:province":"NS",
    "sg:tags":[
        "cemetery"
    ],
    "wof:name":"Maple Wood Cemetery",
    "wof:placetype":"venue"
},
  "geometry": {"coordinates":[-64.13130200000001,44.990593],"type":"Point"}
}