{
  "type": "Feature",
  "properties": {
    "addr:full":"21 7E Av E Riviere-Paspebiac QC G0C 2S0",
    "addr:housenumber":"21",
    "addr:postcode":"g0c 2s0",
    "addr:street":"7E Av E Riviere-Paspebiac",
    "iso:country":"CA",
    "sg:address":"21 7E Av E",
    "sg:city":"Riviere-Paspebiac",
    "sg:classifiers":[
        {
            "category":"Food & Beverages",
            "subcategory":"Groceries & Convenience Stores",
            "type":"Retail Goods"
        }
    ],
    "sg:phone":"+1 418 752 5256",
    "sg:postcode":"G0C 2S0",
    "sg:province":"QC",
    "sg:tags":[
        "grocer"
    ],
    "wof:name":"Parise, Gerald",
    "wof:placetype":"venue"
},
  "geometry": {"coordinates":[-65.25830841059999,48.0564041138],"type":"Point"}
}