{
  "type": "Feature",
  "properties": {
    "iso:country":"CA",
    "sg:address":"106 Rue Grande-Ile",
    "sg:city":"Salaberry-DE-Valleyfield",
    "sg:classifiers":[
        {
            "category":"Real Estate",
            "subcategory":"Real Estate Agent",
            "type":"Services"
        }
    ],
    "sg:phone":"+1 450 371 3000",
    "sg:postcode":"J6S 3M6",
    "sg:province":"QC",
    "wof:name":"Immeubles Mario Leger Inc",
    "wof:placetype":"venue"
},
  "geometry": {"coordinates":[-74.133255,45.264408],"type":"Point"}
}