{
  "type": "Feature",
  "properties": {
    "iso:country":"CA",
    "sg:city":"Edmonton",
    "sg:classifiers":[
        {
            "category":"Professional",
            "subcategory":"Management & Consulting",
            "type":"Services"
        }
    ],
    "sg:phone":"+1 780 413 4838",
    "sg:postcode":"T5G 2T8",
    "sg:province":"AB",
    "sg:tags":[
        "consultant",
        "business"
    ],
    "wof:name":"Business Assistance Inc",
    "wof:placetype":"venue"
},
  "geometry": {"coordinates":[-113.507789612,53.5692977905],"type":"Point"}
}