{
  "type": "Feature",
  "properties": {
    "iso:country":"CA",
    "sg:city":"Wadena",
    "sg:classifiers":[
        {
            "category":"Building & Trades",
            "subcategory":"Construction",
            "type":"Services"
        }
    ],
    "sg:phone":"+1 306 338 3436",
    "sg:postcode":"S0A 4J0",
    "sg:province":"SK",
    "sg:tags":[
        "downspouts",
        "gutter"
    ],
    "wof:name":"C R Eavestroughing",
    "wof:placetype":"venue"
},
  "geometry": {"coordinates":[-103.79473877,51.9426193237],"type":"Point"}
}