{
  "type": "Feature",
  "properties": {
    "iso:country":"CA",
    "sg:address":"1775 9th Line",
    "sg:city":"Innisfil",
    "sg:classifiers":[
        {
            "category":"Building & Trades",
            "subcategory":"Construction",
            "type":"Services"
        }
    ],
    "sg:phone":"+1 705 436 9579",
    "sg:postcode":"L9S 3Y3",
    "sg:province":"ON",
    "sg:tags":[
        "masonry",
        "contractor"
    ],
    "wof:name":"L Farr Masonry",
    "wof:placetype":"venue"
},
  "geometry": {"coordinates":[-79.5957489014,44.3171691895],"type":"Point"}
}