{
  "type": "Feature",
  "properties": {
    "addr:full":"131 14E Ave Saint-Ambroise-DE-Kildare QC J0K 1C0",
    "addr:housenumber":"131",
    "addr:postcode":"j0k 1c0",
    "addr:street":"14E Ave",
    "iso:country":"CA",
    "sg:address":"131 14E Ave",
    "sg:city":"Saint-Ambroise-DE-Kildare",
    "sg:classifiers":[
        {
            "category":"Personal",
            "subcategory":"Beauty Salon",
            "type":"Services"
        }
    ],
    "sg:phone":"+1 450 759 8505",
    "sg:postcode":"J0K 1C0",
    "sg:province":"QC",
    "wof:name":"Salon DE Coiffure Karo",
    "wof:placetype":"venue"
},
  "geometry": {"coordinates":[-73.554436,46.076778],"type":"Point"}
}