{
  "type": "Feature",
  "properties": {
    "addr:full":"7269 Silver Mead Rd NW Calgary AB T3B 3V1",
    "addr:housenumber":"7269",
    "addr:postcode":"t3b 3v1",
    "addr:street":"Silver Mead Rd Nw",
    "iso:country":"CA",
    "sg:address":"7269 Silver Mead Rd NW",
    "sg:city":"Calgary",
    "sg:classifiers":[
        {
            "category":"Professional",
            "subcategory":"Management & Consulting",
            "type":"Services"
        }
    ],
    "sg:phone":"+1 403 277 6767",
    "sg:postcode":"T3B 3V1",
    "sg:province":"AB",
    "sg:tags":[
        "consultant",
        "training"
    ],
    "wof:name":"Willmott Communication Svc",
    "wof:placetype":"venue"
},
  "geometry": {"coordinates":[-114.193359,51.106071],"type":"Point"}
}