{
  "type": "Feature",
  "properties": {
    "addr:full":"Pointe-Claire QC H9S 4H2",
    "addr:postcode":"h9s 4h2",
    "iso:country":"CA",
    "sg:city":"Pointe-Claire",
    "sg:classifiers":[
        {
            "category":"Real Estate",
            "subcategory":"Real Estate Operator",
            "type":"Services"
        }
    ],
    "sg:phone":"+1 514 695 9611",
    "sg:postcode":"H9S 4H2",
    "sg:province":"QC",
    "sg:tags":[
        "apartment"
    ],
    "wof:name":"Lakeshore Towers Apartments",
    "wof:placetype":"venue"
},
  "geometry": {"coordinates":[-73.78679700000001,45.448223],"type":"Point"}
}