{
  "type": "Feature",
  "properties": {
    "iso:country":"CA",
    "sg:city":"Toronto",
    "sg:classifiers":[
        {
            "category":"Organizations",
            "subcategory":"Professional Association",
            "type":"Services"
        }
    ],
    "sg:phone":"+1 416 961 6555",
    "sg:postcode":"M4W 1T1",
    "sg:province":"ON",
    "sg:tags":[
        "body",
        "dental",
        "governing"
    ],
    "wof:name":"Royal College of Dental Srgns",
    "wof:placetype":"venue"
},
  "geometry": {"coordinates":[-79.3892669678,43.6771316528],"type":"Point"}
}