{
  "type": "Feature",
  "properties": {
    "addr:full":"262 Old Homestead Rd Keswick ON L4P 3C8",
    "addr:housenumber":"262",
    "addr:postcode":"l4p 3c8",
    "addr:street":"Old Homestead Rd",
    "iso:country":"CA",
    "sg:address":"262 Old Homestead Rd",
    "sg:city":"Keswick",
    "sg:classifiers":[
        {
            "category":"Education",
            "subcategory":"School",
            "type":"Public Place"
        }
    ],
    "sg:phone":"+1 905 476 7784",
    "sg:postcode":"L4P 3C8",
    "sg:province":"ON",
    "wof:name":"St Thomas Aquinas School",
    "wof:placetype":"venue"
},
  "geometry": {"coordinates":[-79.48131600000001,44.249344],"type":"Point"}
}