{
  "type": "Feature",
  "properties": {
    "iso:country":"CA",
    "sg:address":"4725 Cote Rosemont",
    "sg:city":"Trois-Rivieres-Ouest",
    "sg:classifiers":[
        {
            "category":"Social Services",
            "subcategory":"Child Care",
            "type":"Services"
        }
    ],
    "sg:phone":"+1 819 374 2551",
    "sg:postcode":"G8Y 6R7",
    "sg:province":"QC",
    "wof:name":"Garderie LA Villa Des Petits",
    "wof:placetype":"venue"
},
  "geometry": {"coordinates":[-72.593269,46.332253],"type":"Point"}
}