{
  "type": "Feature",
  "properties": {
    "addr:full":"Ajax ON L1S 6L3",
    "addr:postcode":"l1s 6l3",
    "iso:country":"CA",
    "sg:city":"Ajax",
    "sg:classifiers":[
        {
            "category":"Personal",
            "subcategory":"Beauty Salon",
            "type":"Services"
        }
    ],
    "sg:phone":"+1 905 428 0600",
    "sg:postcode":"L1S 6L3",
    "sg:province":"ON",
    "wof:name":"Shoppe",
    "wof:placetype":"venue"
},
  "geometry": {"coordinates":[-79.0573806763,43.8530464172],"type":"Point"}
}