{
  "type": "Feature",
  "properties": {
    "addr:full":"1224 Rue Labelle Mont-Tremblant QC J8E 2N5",
    "addr:housenumber":"1224",
    "addr:postcode":"j8e 2n5",
    "addr:street":"Rue Labelle",
    "iso:country":"CA",
    "sg:address":"1224 Rue Labelle",
    "sg:city":"Mont-Tremblant",
    "sg:classifiers":[
        {
            "category":"Organizations",
            "subcategory":"Religious Organization",
            "type":"Services"
        }
    ],
    "sg:phone":"+1 819 425 9242",
    "sg:postcode":"J8E 2N5",
    "sg:province":"QC",
    "sg:tags":[
        "church"
    ],
    "wof:name":"Centre Evangelique Des Hautes",
    "wof:placetype":"venue"
},
  "geometry": {"coordinates":[-74.588745,46.137192],"type":"Point"}
}