{
  "type": "Feature",
  "properties": {
    "addr:full":"PO Box 718 Raymond AB T0K 2S0",
    "addr:housenumber":"po",
    "addr:postcode":"t0k 2s0",
    "addr:street":"Box 718 Raymond",
    "iso:country":"CA",
    "sg:address":"PO Box 718",
    "sg:city":"Raymond",
    "sg:classifiers":[
        {
            "category":"Building & Trades",
            "subcategory":"Construction",
            "type":"Services"
        }
    ],
    "sg:phone":"+1 403 752 3886",
    "sg:postcode":"T0K 2S0",
    "sg:province":"AB",
    "sg:tags":[
        "home",
        "builder",
        "general",
        "contractor"
    ],
    "wof:name":"Hirsche Construction Ltd",
    "wof:placetype":"venue"
},
  "geometry": {"coordinates":[-112.663887,49.465519],"type":"Point"}
}