{
  "type": "Feature",
  "properties": {
    "addr:full":"302 Lansdowne Ave S Arden MB R0J 0B0",
    "addr:housenumber":"302",
    "addr:postcode":"r0j 0b0",
    "addr:street":"Lansdowne Ave S",
    "iso:country":"CA",
    "sg:address":"302 Lansdowne Ave S",
    "sg:city":"Arden",
    "sg:classifiers":[
        {
            "category":"Government",
            "subcategory":"Office",
            "type":"Public Place"
        }
    ],
    "sg:phone":"+1 204 368 2202",
    "sg:postcode":"R0J 0B0",
    "sg:province":"MB",
    "sg:tags":[
        "village"
    ],
    "wof:name":"Lansdowne Rural Municipality",
    "wof:placetype":"venue"
},
  "geometry": {"coordinates":[-99.269402,50.276501],"type":"Point"}
}