{
  "type": "Feature",
  "properties": {
    "addr:full":"1120 Upper Sherman Ave Hamilton ON L8W 3W1",
    "addr:housenumber":"1120",
    "addr:postcode":"l8w 3w1",
    "addr:street":"Upper Sherman Ave",
    "iso:country":"CA",
    "sg:address":"1120 Upper Sherman Ave",
    "sg:city":"Hamilton",
    "sg:classifiers":[
        {
            "category":"Food & Beverages",
            "subcategory":"Groceries & Convenience Stores",
            "type":"Retail Goods"
        }
    ],
    "sg:phone":"+1 905 318 5522",
    "sg:postcode":"L8W 3W1",
    "sg:province":"ON",
    "wof:name":"Avondale Stores Ltd",
    "wof:placetype":"venue"
},
  "geometry": {"coordinates":[-79.85614776609999,43.2121658325],"type":"Point"}
}