{
  "type": "Feature",
  "properties": {
    "addr:full":"861 Danforth Ave Toronto ON M4J 1L8",
    "addr:housenumber":"861",
    "addr:postcode":"m4j 1l8",
    "addr:street":"Danforth Ave",
    "iso:country":"CA",
    "sg:address":"861 Danforth Ave",
    "sg:city":"Toronto",
    "sg:classifiers":[
        {
            "category":"Restaurant",
            "type":"Food & Drink"
        }
    ],
    "sg:phone":"+1 416 461 9238",
    "sg:postcode":"M4J 1L8",
    "sg:province":"ON",
    "wof:name":"Danforth Dragon Restaurant",
    "wof:placetype":"venue"
},
  "geometry": {"coordinates":[-79.33987399999999,43.679806],"type":"Point"}
}