{
  "type": "Feature",
  "properties": {
    "addr:full":"391 Rue Principale Saint-Vallier QC G0R 4J0",
    "addr:housenumber":"391",
    "addr:postcode":"g0r 4j0",
    "addr:street":"Rue Principale",
    "iso:country":"CA",
    "sg:address":"391 Rue Principale",
    "sg:city":"Saint-Vallier",
    "sg:classifiers":[
        {
            "category":"Professional",
            "subcategory":"Lawyer & Legal Services",
            "type":"Services"
        }
    ],
    "sg:phone":"+1 418 884 3659",
    "sg:postcode":"G0R 4J0",
    "sg:province":"QC",
    "sg:tags":[
        "attorney"
    ],
    "wof:name":"Corriveau Cloutier",
    "wof:placetype":"venue"
},
  "geometry": {"coordinates":[-70.8169250488,46.8954200745],"type":"Point"}
}