{
  "type": "Feature",
  "properties": {
    "addr:full":"Gibsons BC V0N 1V7",
    "addr:postcode":"v0n 1v7",
    "iso:country":"CA",
    "sg:city":"Gibsons",
    "sg:classifiers":[
        {
            "category":"Health Services",
            "subcategory":"Doctor",
            "type":"Services"
        }
    ],
    "sg:phone":"+1 604 886 7830",
    "sg:postcode":"V0N 1V7",
    "sg:province":"BC",
    "sg:tags":[
        "dentist"
    ],
    "wof:name":"Choy, Vineyard DDS",
    "wof:placetype":"venue"
},
  "geometry": {"coordinates":[-123.520820618,49.4068183899],"type":"Point"}
}