{
  "type": "Feature",
  "properties": {
    "addr:full":"Mississauga ON L5G 3X5",
    "addr:postcode":"l5g 3x5",
    "iso:country":"CA",
    "sg:city":"Mississauga",
    "sg:classifiers":[
        {
            "category":"Building & Trades",
            "subcategory":"Construction",
            "type":"Services"
        }
    ],
    "sg:phone":"+1 905 271 7491",
    "sg:postcode":"L5G 3X5",
    "sg:province":"ON",
    "sg:tags":[
        "resurfacing",
        "laying",
        "refinishing",
        "floor"
    ],
    "wof:name":"Floormasters Hardwood Flooring",
    "wof:placetype":"venue"
},
  "geometry": {"coordinates":[-79.57421100000001,43.562946],"type":"Point"}
}