{
  "type": "Feature",
  "properties": {
    "addr:full":"103 Baby Point Rd York ON M6S 2G6",
    "addr:housenumber":"103",
    "addr:postcode":"m6s 2g6",
    "addr:street":"Baby Point Rd",
    "iso:country":"CA",
    "sg:address":"103 Baby Point Rd",
    "sg:city":"York",
    "sg:classifiers":[
        {
            "category":"Professional",
            "subcategory":"Management & Consulting",
            "type":"Services"
        }
    ],
    "sg:phone":"+1 416 769 5552",
    "sg:postcode":"M6S 2G6",
    "sg:province":"ON",
    "sg:tags":[
        "consultant",
        "mining"
    ],
    "wof:name":"John David Mason Ltd",
    "wof:placetype":"venue"
},
  "geometry": {"coordinates":[-79.498795,43.65522],"type":"Point"}
}