{
  "type": "Feature",
  "properties": {
    "addr:full":"1353 Lawrence Ave W North York ON M6L 1A4",
    "addr:housenumber":"1353",
    "addr:postcode":"m6l 1a4",
    "addr:street":"Lawrence Ave W",
    "iso:country":"CA",
    "sg:address":"1353 Lawrence Ave W",
    "sg:city":"North York",
    "sg:classifiers":[
        {
            "category":"Shopping",
            "subcategory":"Gifts & Souvenirs",
            "type":"Retail Goods"
        }
    ],
    "sg:phone":"+1 416 249 6911",
    "sg:postcode":"M6L 1A4",
    "sg:province":"ON",
    "sg:tags":[
        "shop"
    ],
    "wof:name":"North Park Smokes & Gift Shop",
    "wof:placetype":"venue"
},
  "geometry": {"coordinates":[-79.47601299999999,43.709255],"type":"Point"}
}