{
  "type": "Feature",
  "properties": {
    "addr:full":"628 Sixth Ave # 600 New Westminster BC V3M 6Z1",
    "addr:housenumber":"628;600",
    "addr:postcode":"v3m 6z1",
    "addr:street":"Sixth Ave #",
    "iso:country":"CA",
    "sg:address":"628 Sixth Ave # 600",
    "sg:city":"New Westminster",
    "sg:classifiers":[
        {
            "category":"Professional",
            "subcategory":"Accounting & Tax Preparation",
            "type":"Services"
        }
    ],
    "sg:phone":"+1 604 521 3761",
    "sg:postcode":"V3M 6Z1",
    "sg:province":"BC",
    "sg:tags":[
        "accountant"
    ],
    "wof:name":"Grant Thornton",
    "wof:placetype":"venue"
},
  "geometry": {"coordinates":[-122.920692,49.212807],"type":"Point"}
}