{
  "type": "Feature",
  "properties": {
    "addr:full":"3765 Loggers Way Kinburn ON K0A 2H0",
    "addr:housenumber":"3765",
    "addr:postcode":"k0a 2h0",
    "addr:street":"Loggers Way",
    "iso:country":"CA",
    "sg:address":"3765 Loggers Way",
    "sg:city":"Kinburn",
    "sg:classifiers":[
        {
            "category":"Education",
            "subcategory":"School",
            "type":"Public Place"
        }
    ],
    "sg:phone":"+1 613 832 2821",
    "sg:postcode":"K0A 2H0",
    "sg:province":"ON",
    "wof:name":"Fitzroy Centennial School",
    "wof:placetype":"venue"
},
  "geometry": {"coordinates":[-76.1869354248,45.3902244568],"type":"Point"}
}