{
  "type": "Feature",
  "properties": {
    "addr:full":"290 Main St E Grimsby ON L3M 1P8",
    "addr:housenumber":"290",
    "addr:postcode":"l3m 1p8",
    "addr:street":"Main St E",
    "iso:country":"CA",
    "sg:address":"290 Main St E",
    "sg:city":"Grimsby",
    "sg:classifiers":[
        {
            "category":"Organizations",
            "subcategory":"Religious Organization",
            "type":"Services"
        }
    ],
    "sg:phone":"+1 905 945 0004",
    "sg:postcode":"L3M 1P8",
    "sg:province":"ON",
    "sg:tags":[
        "church"
    ],
    "wof:name":"Mountainview Christian Ref Ch",
    "wof:placetype":"venue"
},
  "geometry": {"coordinates":[-79.522087,43.184864],"type":"Point"}
}