{
  "type": "Feature",
  "properties": {
    "addr:full":"1207 Talbot St St Thomas ON N5P 1G8",
    "addr:housenumber":"1207",
    "addr:postcode":"n5p 1g8",
    "addr:street":"Talbot St",
    "iso:country":"CA",
    "sg:address":"1207 Talbot St",
    "sg:city":"St Thomas",
    "sg:classifiers":[
        {
            "category":"Autos & Motor Vehicles",
            "subcategory":"Automobile Sales",
            "type":"Retail Goods"
        }
    ],
    "sg:phone":"+1 519 633 0240",
    "sg:postcode":"N5P 1G8",
    "sg:province":"ON",
    "sg:tags":[
        "car",
        "dealer"
    ],
    "wof:name":"Bridgeview Motors",
    "wof:placetype":"venue"
},
  "geometry": {"coordinates":[-81.1569976807,42.779045105],"type":"Point"}
}