{
  "type": "Feature",
  "properties": {
    "addr:full":"2824 Victoria Ave E Thunder Bay ON P7C 1G3",
    "addr:housenumber":"2824",
    "addr:postcode":"p7c 1g3",
    "addr:street":"Victoria Ave E",
    "iso:country":"CA",
    "sg:address":"2824 Victoria Ave E",
    "sg:city":"Thunder Bay",
    "sg:classifiers":[
        {
            "category":"Building & Trades",
            "subcategory":"Cleaning & Sanitation",
            "type":"Services"
        }
    ],
    "sg:phone":"+1 807 626 9065",
    "sg:postcode":"P7C 1G3",
    "sg:province":"ON",
    "sg:tags":[
        "house",
        "janitor"
    ],
    "wof:name":"Quality Cleaners",
    "wof:placetype":"venue"
},
  "geometry": {"coordinates":[-89.277458,48.383984],"type":"Point"}
}