{
  "type": "Feature",
  "properties": {
    "iso:country":"CA",
    "sg:city":"Kanata",
    "sg:classifiers":[
        {
            "category":"Manufacturing",
            "subcategory":"Electronics",
            "type":"Manufacturing & Wholesale Goods"
        }
    ],
    "sg:phone":"+1 613 271 8649",
    "sg:postcode":"K2K 3A4",
    "sg:province":"ON",
    "sg:tags":[
        "semiconductor",
        "devices"
    ],
    "wof:name":"Texas Instruments Canada Ltd",
    "wof:placetype":"venue"
},
  "geometry": {"coordinates":[-75.9188156128,45.3439826965],"type":"Point"}
}