{
  "type": "Feature",
  "properties": {
    "iso:country":"CA",
    "sg:city":"Fort Saskatchewan",
    "sg:classifiers":[
        {
            "category":"Wholesale",
            "subcategory":"Metals & Minerals",
            "type":"Manufacturing & Wholesale Goods"
        }
    ],
    "sg:phone":"+1 780 992 7000",
    "sg:postcode":"T8L 2T3",
    "sg:province":"AB",
    "wof:name":"Sherritt International",
    "wof:placetype":"venue"
},
  "geometry": {"coordinates":[-113.19135284399999,53.7158851624],"type":"Point"}
}