{
  "type": "Feature",
  "properties": {
    "addr:full":"1477 Erin St Winnipeg MB R3E 2S9",
    "addr:housenumber":"1477",
    "addr:postcode":"r3e 2s9",
    "addr:street":"Erin St",
    "iso:country":"CA",
    "sg:address":"1477 Erin St",
    "sg:city":"Winnipeg",
    "sg:classifiers":[
        {
            "category":"Retail",
            "subcategory":"Auto Repair",
            "type":"Services"
        }
    ],
    "sg:phone":"+1 204 783 5876",
    "sg:postcode":"R3E 2S9",
    "sg:province":"MB",
    "sg:tags":[
        "body",
        "automobile",
        "painting"
    ],
    "wof:name":"Mac's Custom Painting Ltd",
    "wof:placetype":"venue"
},
  "geometry": {"coordinates":[-97.18347930909999,49.9031295776],"type":"Point"}
}