{
  "type": "Feature",
  "properties": {
    "iso:country":"CA",
    "sg:city":"Sedgewick",
    "sg:classifiers":[
        {
            "category":"Wholesale",
            "subcategory":"Machinery & Supplies",
            "type":"Manufacturing & Wholesale Goods"
        }
    ],
    "sg:phone":"+1 780 384 3601",
    "sg:postcode":"T0B 4C0",
    "sg:province":"AB",
    "sg:tags":[
        "equipment",
        "safety",
        "clothing"
    ],
    "wof:name":"Safety First Muirhead's Ltd",
    "wof:placetype":"venue"
},
  "geometry": {"coordinates":[-111.698753357,52.7761497498],"type":"Point"}
}