{
  "type": "Feature",
  "properties": {
    "addr:full":"26 Rue Saint-Nicolas Quebec QC G1K 6T2",
    "addr:housenumber":"26",
    "addr:postcode":"g1k 6t2",
    "addr:street":"Rue Saint-Nicolas",
    "iso:country":"CA",
    "sg:address":"26 Rue Saint-Nicolas",
    "sg:city":"Quebec",
    "sg:classifiers":[
        {
            "category":"Shopping",
            "subcategory":"Computers & Home Electronics",
            "type":"Retail Goods"
        }
    ],
    "sg:phone":"+1 418 692 2690",
    "sg:postcode":"G1K 6T2",
    "sg:province":"QC",
    "sg:tags":[
        "equipment",
        "dealer"
    ],
    "wof:name":"Virtuel Pc Mac",
    "wof:placetype":"venue"
},
  "geometry": {"coordinates":[-71.213089,46.816029],"type":"Point"}
}