{
  "type": "Feature",
  "properties": {
    "addr:full":"3466 Landmark Rd Burlington ON L7M 1S8",
    "addr:housenumber":"3466",
    "addr:postcode":"l7m 1s8",
    "addr:street":"Landmark Rd",
    "iso:country":"CA",
    "sg:address":"3466 Landmark Rd",
    "sg:city":"Burlington",
    "sg:classifiers":[
        {
            "category":"Manufacturing",
            "subcategory":"Rubber & Plastics",
            "type":"Manufacturing & Wholesale Goods"
        }
    ],
    "sg:phone":"+1 905 335 3711",
    "sg:postcode":"L7M 1S8",
    "sg:province":"ON",
    "wof:name":"L A Rubber Inc",
    "wof:placetype":"venue"
},
  "geometry": {"coordinates":[-79.796944,43.367306],"type":"Point"}
}