{
  "type": "Feature",
  "properties": {
    "addr:full":"96 Rue DE LA Pointe-Langlois Laval QC H7L 3M5",
    "addr:housenumber":"96",
    "addr:postcode":"h7l 3m5",
    "addr:street":"Rue De La Pointe-Langlois",
    "iso:country":"CA",
    "sg:address":"96 Rue DE LA Pointe-Langlois",
    "sg:city":"Laval",
    "sg:classifiers":[
        {
            "category":"Autos & Motor Vehicles",
            "subcategory":"Auto Supplies",
            "type":"Retail Goods"
        }
    ],
    "sg:phone":"+1 450 628 3000",
    "sg:postcode":"H7L 3M5",
    "sg:province":"QC",
    "sg:tags":[
        "grill",
        "guard",
        "bumper",
        "automobile"
    ],
    "wof:name":"Botec",
    "wof:placetype":"venue"
},
  "geometry": {"coordinates":[-73.8045043945,45.6046485901],"type":"Point"}
}