{
  "type": "Feature",
  "properties": {
    "addr:full":"Scott QC G0S 3G0",
    "addr:postcode":"g0s 3g0",
    "iso:country":"CA",
    "sg:city":"Scott",
    "sg:classifiers":[
        {
            "category":"Bars & Pubs",
            "type":"Food & Drink"
        }
    ],
    "sg:phone":"+1 418 387 5513",
    "sg:postcode":"G0S 3G0",
    "sg:province":"QC",
    "sg:tags":[
        "lounge",
        "cocktail"
    ],
    "wof:name":"Bar Le Zodiaque",
    "wof:placetype":"venue"
},
  "geometry": {"coordinates":[-71.07473,46.506287],"type":"Point"}
}