{
  "type": "Feature",
  "properties": {
    "iso:country":"CA",
    "sg:address":"3434 Rue Notre-Dame O",
    "sg:city":"Montreal",
    "sg:classifiers":[
        {
            "category":"Restaurant",
            "type":"Food & Drink"
        }
    ],
    "sg:phone":"+1 514 932 8027",
    "sg:postcode":"H4C 1P2",
    "sg:province":"QC",
    "wof:name":"Restaurant LA Place St Henri",
    "wof:placetype":"venue"
},
  "geometry": {"coordinates":[-73.537277,45.541187],"type":"Point"}
}