{
  "type": "Feature",
  "properties": {
    "iso:country":"CA",
    "sg:address":"207 St. Paul St W # 1",
    "sg:city":"St Catharines",
    "sg:classifiers":[
        {
            "category":"Retail",
            "subcategory":"Auto Repair",
            "type":"Services"
        }
    ],
    "sg:phone":"+1 905 685 7324",
    "sg:postcode":"L2S 2E1",
    "sg:province":"ON",
    "sg:tags":[
        "glass",
        "top",
        "upholstery",
        "automobile"
    ],
    "wof:name":"Tempest Auto Trim & Glass",
    "wof:placetype":"venue"
},
  "geometry": {"coordinates":[-79.25689697270001,43.145942688],"type":"Point"}
}