{
  "type": "Feature",
  "properties": {
    "addr:full":"2046 Av Chartier Dorval QC H9P 1H2",
    "addr:housenumber":"2046",
    "addr:postcode":"h9p 1h2",
    "addr:street":"Av Chartier",
    "iso:country":"CA",
    "sg:address":"2046 Av Chartier",
    "sg:city":"Dorval",
    "sg:classifiers":[
        {
            "category":"Manufacturing",
            "subcategory":"Tools & Machinery",
            "type":"Manufacturing & Wholesale Goods"
        }
    ],
    "sg:phone":"+1 514 633 9261",
    "sg:postcode":"H9P 1H2",
    "sg:province":"QC",
    "sg:tags":[
        "machine",
        "shop"
    ],
    "wof:name":"Industries Akal Inc",
    "wof:placetype":"venue"
},
  "geometry": {"coordinates":[-73.7252044678,45.4631500244],"type":"Point"}
}