{
  "type": "Feature",
  "properties": {
    "addr:full":"117 Mckellar St S Thunder Bay ON P7E 1H5",
    "addr:housenumber":"117",
    "addr:postcode":"p7e 1h5",
    "addr:street":"Mckellar St S",
    "iso:country":"CA",
    "sg:address":"117 Mckellar St S",
    "sg:city":"Thunder Bay",
    "sg:classifiers":[
        {
            "category":"Health Services",
            "subcategory":"Doctor",
            "type":"Services"
        }
    ],
    "sg:phone":"+1 807 626 1234",
    "sg:postcode":"P7E 1H5",
    "sg:province":"ON",
    "sg:tags":[
        "physician",
        "surgeon"
    ],
    "wof:name":"Almond, R MD",
    "wof:placetype":"venue"
},
  "geometry": {"coordinates":[-89.250145,48.383789],"type":"Point"}
}