{
  "type": "Feature",
  "properties": {
    "iso:country":"CA",
    "sg:address":"75 Breezehill Ave N #100",
    "sg:city":"Ottawa",
    "sg:classifiers":[
        {
            "category":"Professional",
            "subcategory":"Art Services",
            "type":"Services"
        }
    ],
    "sg:phone":"+1 613 728 1988",
    "sg:postcode":"K1Y 2H6",
    "sg:province":"ON",
    "sg:tags":[
        "photographer"
    ],
    "wof:name":"Headlight Inc",
    "wof:placetype":"venue"
},
  "geometry": {"coordinates":[-75.71872711180001,45.4060821533],"type":"Point"}
}