{
  "type": "Feature",
  "properties": {
    "addr:full":"6415 Dixie Rd Mississauga ON L5T 1A4",
    "addr:housenumber":"6415",
    "addr:postcode":"l5t 1a4",
    "addr:street":"Dixie Rd",
    "iso:country":"CA",
    "sg:address":"6415 Dixie Rd",
    "sg:city":"Mississauga",
    "sg:classifiers":[
        {
            "category":"Autos & Motor Vehicles",
            "subcategory":"Fuel & Gas Station",
            "type":"Retail Goods"
        }
    ],
    "sg:phone":"+1 905 670 2659",
    "sg:postcode":"L5T 1A4",
    "sg:province":"ON",
    "sg:tags":[
        "oil"
    ],
    "wof:name":"Esso Shop",
    "wof:placetype":"venue"
},
  "geometry": {"coordinates":[-79.6592102051,43.66431427],"type":"Point"}
}