{
  "type": "Feature",
  "properties": {
    "addr:full":"100 3 Ave S Lethbridge AB T1J 4L2",
    "addr:housenumber":"100",
    "addr:postcode":"t1j 4l2",
    "addr:street":"3 Ave S",
    "iso:country":"CA",
    "sg:address":"100 3 Ave S",
    "sg:city":"Lethbridge",
    "sg:classifiers":[
        {
            "category":"Travel",
            "subcategory":"Hotels & Motels",
            "type":"Entertainment"
        }
    ],
    "sg:phone":"+1 403 327 6000",
    "sg:postcode":"T1J 4L2",
    "sg:province":"AB",
    "wof:name":"Days Inn Lethbridge",
    "wof:placetype":"venue"
},
  "geometry": {"coordinates":[-112.846069,49.695595],"type":"Point"}
}