{
  "type": "Feature",
  "properties": {
    "addr:full":"1850 Boundary Rd Whitby ON L1N 8P8",
    "addr:housenumber":"1850",
    "addr:postcode":"l1n 8p8",
    "addr:street":"Boundary Rd",
    "iso:country":"CA",
    "sg:address":"1850 Boundary Rd",
    "sg:city":"Whitby",
    "sg:classifiers":[
        {
            "category":"Retail",
            "subcategory":"Auto Repair",
            "type":"Services"
        }
    ],
    "sg:phone":"+1 905 571 5886",
    "sg:postcode":"L1N 8P8",
    "sg:province":"ON",
    "sg:tags":[
        "automobile",
        "co",
        "drive",
        "transporter"
    ],
    "wof:name":"Leaseway Motocar Transport",
    "wof:placetype":"venue"
},
  "geometry": {"coordinates":[-78.88721466059999,43.8648338318],"type":"Point"}
}