{
  "type": "Feature",
  "properties": {
    "addr:full":"12122 163 St NW Edmonton AB T5V 1H4",
    "addr:housenumber":"12122",
    "addr:postcode":"t5v 1h4",
    "addr:street":"163 St Nw",
    "iso:country":"CA",
    "sg:address":"12122 163 St NW",
    "sg:city":"Edmonton",
    "sg:classifiers":[
        {
            "category":"Retail",
            "subcategory":"Auto Repair",
            "type":"Services"
        }
    ],
    "sg:phone":"+1 780 484 1194",
    "sg:postcode":"T5V 1H4",
    "sg:province":"AB",
    "sg:tags":[
        "repairing",
        "automobile"
    ],
    "wof:name":"Access Automotive Repair Ltd",
    "wof:placetype":"venue"
},
  "geometry": {"coordinates":[-113.603004,53.573105],"type":"Point"}
}