{
  "type": "Feature",
  "properties": {
    "addr:full":"3095 Boul Wilfrid-Hamel # 239 Quebec QC G1P 4C6",
    "addr:housenumber":"3095",
    "addr:postcode":"g1p 4c6",
    "addr:street":"Boul Wilfrid-Hamel # 239",
    "iso:country":"CA",
    "sg:address":"3095 Boul Wilfrid-Hamel # 239",
    "sg:city":"Quebec",
    "sg:classifiers":[
        {
            "category":"Freight",
            "type":"Transportation"
        }
    ],
    "sg:phone":"+1 418 877 0671",
    "sg:postcode":"G1P 4C6",
    "sg:province":"QC",
    "sg:tags":[
        "courier"
    ],
    "wof:name":"Messagerie Inter Cite",
    "wof:placetype":"venue"
},
  "geometry": {"coordinates":[-71.3058853149,46.8062324524],"type":"Point"}
}