{
  "type": "Feature",
  "properties": {
    "addr:full":"3268 Rue Marconi Mascouche QC J7K 3N6",
    "addr:housenumber":"3268",
    "addr:postcode":"j7k 3n6",
    "addr:street":"Rue Marconi",
    "iso:country":"CA",
    "sg:address":"3268 Rue Marconi",
    "sg:city":"Mascouche",
    "sg:classifiers":[
        {
            "category":"Manufacturing",
            "subcategory":"Metals",
            "type":"Manufacturing & Wholesale Goods"
        }
    ],
    "sg:phone":"+1 450 966 9070",
    "sg:postcode":"J7K 3N6",
    "sg:province":"QC",
    "sg:tags":[
        "polishing",
        "buffing"
    ],
    "wof:name":"Polissage Rive-Nord Enr",
    "wof:placetype":"venue"
},
  "geometry": {"coordinates":[-73.594116,45.738144],"type":"Point"}
}