{
  "type": "Feature",
  "properties": {
    "addr:full":"171 Av Orchard Lasalle QC H8R 3G3",
    "addr:postcode":"h8r 3g3",
    "addr:street":"171 Av Orchard",
    "iso:country":"CA",
    "sg:address":"171 Av Orchard",
    "sg:city":"Lasalle",
    "sg:classifiers":[
        {
            "category":"Education",
            "subcategory":"School",
            "type":"Public Place"
        }
    ],
    "sg:phone":"+1 514 366 2270",
    "sg:postcode":"H8R 3G3",
    "sg:province":"QC",
    "wof:name":"Cecil Newman Ecole Primaire",
    "wof:placetype":"venue"
},
  "geometry": {"coordinates":[-73.6472396851,45.4229736328],"type":"Point"}
}