{
  "type": "Feature",
  "properties": {
    "addr:full":"2286 Algonquin Rd Sudbury ON P3E 4Z6",
    "addr:housenumber":"2286",
    "addr:postcode":"p3e 4z6",
    "addr:street":"Algonquin Rd",
    "iso:country":"CA",
    "sg:address":"2286 Algonquin Rd",
    "sg:city":"Sudbury",
    "sg:classifiers":[
        {
            "category":"Manufacturing",
            "subcategory":"Metals",
            "type":"Manufacturing & Wholesale Goods"
        }
    ],
    "sg:phone":"+1 705 522 1305",
    "sg:postcode":"P3E 4Z6",
    "sg:province":"ON",
    "sg:tags":[
        "steel"
    ],
    "wof:name":"Sandro Steel Fabrication Ltd",
    "wof:placetype":"venue"
},
  "geometry": {"coordinates":[-80.995796,46.441986],"type":"Point"}
}