{
  "type": "Feature",
  "properties": {
    "addr:full":"12 Loyalist Dr Brighton ON K0K 1H0",
    "addr:housenumber":"12",
    "addr:postcode":"k0k 1h0",
    "addr:street":"Loyalist Dr",
    "iso:country":"CA",
    "sg:address":"12 Loyalist Dr",
    "sg:city":"Brighton",
    "sg:classifiers":[
        {
            "category":"Professional",
            "subcategory":"Research",
            "type":"Services"
        }
    ],
    "sg:phone":"+1 613 475 1878",
    "sg:postcode":"K0K 1H0",
    "sg:province":"ON",
    "sg:tags":[
        "environmental",
        "ecological"
    ],
    "wof:name":"Groundtrax Inc",
    "wof:placetype":"venue"
},
  "geometry": {"coordinates":[-77.729347,44.034798],"type":"Point"}
}