{
  "type": "Feature",
  "properties": {
    "addr:full":"933 Ramsey Lake Rd Sudbury ON P3E 6B5",
    "addr:housenumber":"933",
    "addr:postcode":"p3e 6b5",
    "addr:street":"Ramsey Lake Rd",
    "iso:country":"CA",
    "sg:address":"933 Ramsey Lake Rd",
    "sg:city":"Sudbury",
    "sg:classifiers":[
        {
            "category":"Professional",
            "subcategory":"Management & Consulting",
            "type":"Services"
        }
    ],
    "sg:phone":"+1 705 671 6360",
    "sg:postcode":"P3E 6B5",
    "sg:province":"ON",
    "sg:tags":[
        "consultant",
        "safety"
    ],
    "wof:name":"Mines & Aggregates Safety",
    "wof:placetype":"venue"
},
  "geometry": {"coordinates":[-80.97282409669999,46.4707527161],"type":"Point"}
}