{
  "type": "Feature",
  "properties": {
    "addr:full":"6306 Main St Stouffville ON L4A 1G8",
    "addr:housenumber":"6306",
    "addr:postcode":"l4a 1g8",
    "addr:street":"Main St",
    "iso:country":"CA",
    "sg:address":"6306 Main St",
    "sg:city":"Stouffville",
    "sg:classifiers":[
        {
            "category":"Sports & Exercise",
            "subcategory":"Gym",
            "type":"Entertainment"
        }
    ],
    "sg:phone":"+1 905 642 4392",
    "sg:postcode":"L4A 1G8",
    "sg:province":"ON",
    "sg:tags":[
        "control",
        "weight",
        "club",
        "gymnasium",
        "health",
        "studio"
    ],
    "wof:name":"Curves For Women",
    "wof:placetype":"venue"
},
  "geometry": {"coordinates":[-79.24572000000001,43.971733],"type":"Point"}
}