{
  "type": "Feature",
  "properties": {
    "addr:full":"Red Lake ON P0V 2M0",
    "addr:postcode":"p0v 2m0",
    "iso:country":"CA",
    "sg:city":"Red Lake",
    "sg:classifiers":[
        {
            "category":"Professional",
            "subcategory":"Accounting & Tax Preparation",
            "type":"Services"
        }
    ],
    "sg:phone":"+1 807 727 3425",
    "sg:postcode":"P0V 2M0",
    "sg:province":"ON",
    "sg:tags":[
        "return",
        "filing"
    ],
    "wof:name":"Davis' Tax Preparation",
    "wof:placetype":"venue"
},
  "geometry": {"coordinates":[-93.8356704712,51.0132408142],"type":"Point"}
}