{
  "type": "Feature",
  "properties": {
    "iso:country":"CA",
    "sg:address":"1645 Dundas St E",
    "sg:city":"Whitby",
    "sg:classifiers":[
        {
            "category":"Shopping",
            "subcategory":"Clothing, Apparel, & Fashions",
            "type":"Retail Goods"
        }
    ],
    "sg:phone":"+1 905 579 7676",
    "sg:postcode":"L1N 2K9",
    "sg:province":"ON",
    "sg:tags":[
        "infant",
        "wear"
    ],
    "wof:name":"Once Upon A Child",
    "wof:placetype":"venue"
},
  "geometry": {"coordinates":[-78.910805,43.886822],"type":"Point"}
}