{
  "type": "Feature",
  "properties": {
    "iso:country":"CA",
    "sg:address":"56 Lemarchant St",
    "sg:city":"Carbonear",
    "sg:classifiers":[
        {
            "category":"Organizations",
            "subcategory":"Religious Organization",
            "type":"Services"
        }
    ],
    "sg:phone":"+1 709 596 7654",
    "sg:postcode":"A1Y 1A9",
    "sg:province":"NL",
    "sg:tags":[
        "church"
    ],
    "wof:name":"Pentecostal Church",
    "wof:placetype":"venue"
},
  "geometry": {"coordinates":[-53.2294998169,47.7363815308],"type":"Point"}
}