{
  "type": "Feature",
  "properties": {
    "addr:full":"160 St Andrew St W Fergus ON N1M 1N5",
    "addr:housenumber":"160",
    "addr:postcode":"n1m 1n5",
    "addr:street":"St Andrew St W",
    "iso:country":"CA",
    "sg:address":"160 St Andrew St W",
    "sg:city":"Fergus",
    "sg:classifiers":[
        {
            "category":"Retail",
            "subcategory":"Repair Shop",
            "type":"Services"
        }
    ],
    "sg:phone":"+1 519 843 6540",
    "sg:postcode":"N1M 1N5",
    "sg:province":"ON",
    "sg:tags":[
        "interior",
        "consultant",
        "design",
        "decorator",
        "upholsterer"
    ],
    "wof:name":"Fergus Custom Upholstery",
    "wof:placetype":"venue"
},
  "geometry": {"coordinates":[-80.378151,43.705154],"type":"Point"}
}