{
  "type": "Feature",
  "properties": {
    "addr:full":"2109 Ottawa St Windsor ON N8Y 1R8",
    "addr:housenumber":"2109",
    "addr:postcode":"n8y 1r8",
    "addr:street":"Ottawa St",
    "iso:country":"CA",
    "sg:address":"2109 Ottawa St",
    "sg:city":"Windsor",
    "sg:classifiers":[
        {
            "category":"Restaurant",
            "type":"Food & Drink"
        }
    ],
    "sg:phone":"+1 519 256 7425",
    "sg:postcode":"N8Y 1R8",
    "sg:province":"ON",
    "wof:name":"Delila's Kitchen",
    "wof:placetype":"venue"
},
  "geometry": {"coordinates":[-83.003868103,42.3126907349],"type":"Point"}
}