{
  "type": "Feature",
  "properties": {
    "addr:full":"452 Rue Des Faconniers Rimouski QC G5M 1S8",
    "addr:housenumber":"452",
    "addr:postcode":"g5m 1s8",
    "addr:street":"Rue Des Faconniers",
    "iso:country":"CA",
    "sg:address":"452 Rue Des Faconniers",
    "sg:city":"Rimouski",
    "sg:classifiers":[
        {
            "category":"Freight",
            "type":"Transportation"
        }
    ],
    "sg:phone":"+1 418 723 2727",
    "sg:postcode":"G5M 1S8",
    "sg:province":"QC",
    "sg:tags":[
        "trucking"
    ],
    "wof:name":"Transport Morneau Inc",
    "wof:placetype":"venue"
},
  "geometry": {"coordinates":[-68.4979095459,48.4608459473],"type":"Point"}
}