{
  "type": "Feature",
  "properties": {
    "addr:full":"302 Bismark Ave Langenburg SK S0A 2A0",
    "addr:housenumber":"302",
    "addr:postcode":"s0a 2a0",
    "addr:street":"Bismark Ave",
    "iso:country":"CA",
    "sg:address":"302 Bismark Ave",
    "sg:city":"Langenburg",
    "sg:classifiers":[
        {
            "category":"Organizations",
            "subcategory":"Religious Organization",
            "type":"Services"
        }
    ],
    "sg:phone":"+1 306 743 5010",
    "sg:postcode":"S0A 2A0",
    "sg:province":"SK",
    "sg:tags":[
        "church"
    ],
    "wof:name":"Christ Lutheran Church",
    "wof:placetype":"venue"
},
  "geometry": {"coordinates":[-101.698746,50.843075],"type":"Point"}
}