{
  "type": "Feature",
  "properties": {
    "addr:full":"3948 Route 845 Kingston NB E5N 1E9",
    "addr:housenumber":"3948",
    "addr:postcode":"e5n 1e9",
    "addr:street":"Route 845",
    "iso:country":"CA",
    "sg:address":"3948 Route 845",
    "sg:city":"Kingston",
    "sg:classifiers":[
        {
            "category":"Organizations",
            "subcategory":"Religious Organization",
            "type":"Services"
        }
    ],
    "sg:phone":"+1 506 763 3183",
    "sg:postcode":"E5N 1E9",
    "sg:province":"NB",
    "sg:tags":[
        "church"
    ],
    "wof:name":"Parish of Kingston",
    "wof:placetype":"venue"
},
  "geometry": {"coordinates":[-65.97933197019999,45.5009346008],"type":"Point"}
}