{
  "type": "Feature",
  "properties": {
    "iso:country":"CA",
    "sg:address":"296 Brunswick Ave",
    "sg:city":"Toronto",
    "sg:classifiers":[
        {
            "category":"Restaurant",
            "type":"Food & Drink"
        }
    ],
    "sg:phone":"+1 416 929 3253",
    "sg:postcode":"M5S 2M7",
    "sg:province":"ON",
    "wof:name":"Green Room",
    "wof:placetype":"venue"
},
  "geometry": {"coordinates":[-79.4074554443,43.6654281616],"type":"Point"}
}