{
  "type": "Feature",
  "properties": {
    "iso:country":"CA",
    "sg:city":"Gypsumville",
    "sg:classifiers":[
        {
            "category":"Education",
            "subcategory":"School",
            "type":"Public Place"
        }
    ],
    "sg:phone":"+1 204 659 4475",
    "sg:postcode":"R0C 1J0",
    "sg:province":"MB",
    "wof:name":"Gypsumville School",
    "wof:placetype":"venue"
},
  "geometry": {"coordinates":[-98.6343917847,51.7704162598],"type":"Point"}
}