{
  "type": "Feature",
  "properties": {
    "addr:full":"13 Husseys Rd Portugal Cove-St Philips NL A1M 2V1",
    "addr:housenumber":"13",
    "addr:postcode":"a1m 2v1",
    "addr:street":"Husseys Rd",
    "iso:country":"CA",
    "sg:address":"13 Husseys Rd",
    "sg:city":"Portugal Cove-St Philips",
    "sg:classifiers":[
        {
            "category":"Manufacturing",
            "subcategory":"Rubber & Plastics",
            "type":"Manufacturing & Wholesale Goods"
        }
    ],
    "sg:phone":"+1 709 895 3132",
    "sg:postcode":"A1M 2V1",
    "sg:province":"NL",
    "wof:name":"R J Specialties Plastic",
    "wof:placetype":"venue"
},
  "geometry": {"coordinates":[-52.879562,47.599209],"type":"Point"}
}