{
  "type": "Feature",
  "properties": {
    "iso:country":"CA",
    "sg:address":"727 Rue Du Versant",
    "sg:city":"Rimouski",
    "sg:classifiers":[
        {
            "category":"Building & Trades",
            "subcategory":"Construction",
            "type":"Services"
        }
    ],
    "sg:phone":"+1 418 724 6399",
    "sg:postcode":"G5L 8C4",
    "sg:province":"QC",
    "sg:tags":[
        "contractor"
    ],
    "wof:name":"Lebel, Andre",
    "wof:placetype":"venue"
},
  "geometry": {"coordinates":[-68.5760650635,48.4295730591],"type":"Point"}
}