{
  "type": "Feature",
  "properties": {
    "iso:country":"CA",
    "sg:address":"2903 32 Ave",
    "sg:city":"Vernon",
    "sg:classifiers":[
        {
            "category":"Health Services",
            "subcategory":"Doctor",
            "type":"Services"
        }
    ],
    "sg:phone":"+1 250 545 2326",
    "sg:postcode":"V1T 2L6",
    "sg:province":"BC",
    "sg:tags":[
        "physician",
        "surgeon"
    ],
    "wof:name":"Smart, Gavin MD",
    "wof:placetype":"venue"
},
  "geometry": {"coordinates":[-119.270233154,50.2654533386],"type":"Point"}
}