{
  "type": "Feature",
  "properties": {
    "addr:full":"3812 Albrecht Naramata BC V0H 1N0",
    "addr:housenumber":"3812",
    "addr:postcode":"v0h 1n0",
    "addr:street":"Albrecht Naramata",
    "iso:country":"CA",
    "sg:address":"3812 Albrecht",
    "sg:city":"Naramata",
    "sg:classifiers":[
        {
            "category":"Autos & Motor Vehicles",
            "subcategory":"Motorcycle Sales",
            "type":"Retail Goods"
        }
    ],
    "sg:phone":"+1 250 496 5427",
    "sg:postcode":"V0H 1N0",
    "sg:province":"BC",
    "sg:tags":[
        "scooter"
    ],
    "wof:name":"Hunt Cycle",
    "wof:placetype":"venue"
},
  "geometry": {"coordinates":[-119.578773498,49.5962638855],"type":"Point"}
}