{
  "type": "Feature",
  "properties": {
    "addr:full":"199 King St E Hwy 26 Thornbury ON N0H 2P0",
    "addr:housenumber":"199",
    "addr:postcode":"n0h 2p0",
    "addr:street":"King St E Hwy 26",
    "iso:country":"CA",
    "sg:address":"199 King St E Hwy 26",
    "sg:city":"Thornbury",
    "sg:classifiers":[
        {
            "category":"Food & Beverages",
            "subcategory":"Groceries & Convenience Stores",
            "type":"Retail Goods"
        }
    ],
    "sg:phone":"+1 519 599 7118",
    "sg:postcode":"N0H 2P0",
    "sg:province":"ON",
    "wof:name":"Thornbury Mini Mart",
    "wof:placetype":"venue"
},
  "geometry": {"coordinates":[-80.440895,44.556553],"type":"Point"}
}