{
  "type": "Feature",
  "properties": {
    "addr:full":"22 Pleasantview Ave Paradise NL A1L 2Z1",
    "addr:housenumber":"22",
    "addr:postcode":"a1l 2z1",
    "addr:street":"Pleasantview Ave",
    "iso:country":"CA",
    "sg:address":"22 Pleasantview Ave",
    "sg:city":"Paradise",
    "sg:classifiers":[
        {
            "category":"Wholesale",
            "subcategory":"Meat",
            "type":"Manufacturing & Wholesale Goods"
        }
    ],
    "sg:phone":"+1 709 782 1142",
    "sg:postcode":"A1L 2Z1",
    "sg:province":"NL",
    "sg:tags":[
        "packer"
    ],
    "wof:name":"Quality Brand Meats Ltd",
    "wof:placetype":"venue"
},
  "geometry": {"coordinates":[-52.872906,47.536877],"type":"Point"}
}