{
  "type": "Feature",
  "properties": {
    "iso:country":"CA",
    "sg:address":"493 Ouellette Ave",
    "sg:city":"Windsor",
    "sg:classifiers":[
        {
            "category":"Shopping",
            "subcategory":"Clothing, Apparel, & Fashions",
            "type":"Retail Goods"
        }
    ],
    "sg:phone":"+1 519 253 2418",
    "sg:postcode":"N9A 4J2",
    "sg:province":"ON",
    "sg:tags":[
        "fur",
        "business"
    ],
    "wof:name":"Lazare's Furs",
    "wof:placetype":"venue"
},
  "geometry": {"coordinates":[-83.037415,42.314903],"type":"Point"}
}