{
  "type": "Feature",
  "properties": {
    "iso:country":"CA",
    "sg:address":"310 Av Dorval",
    "sg:city":"Dorval",
    "sg:classifiers":[
        {
            "category":"Food & Beverages",
            "subcategory":"Groceries & Convenience Stores",
            "type":"Retail Goods"
        }
    ],
    "sg:phone":"+1 514 631 6234",
    "sg:postcode":"H9S 3H7",
    "sg:province":"QC",
    "sg:tags":[
        "grocer"
    ],
    "wof:name":"Maxi",
    "wof:placetype":"venue"
},
  "geometry": {"coordinates":[-73.7410202026,45.443901062],"type":"Point"}
}