{
  "type": "Feature",
  "properties": {
    "addr:full":"8 Rue Des Ormes Riviere-Du-Loup QC G5R 4W7",
    "addr:housenumber":"8",
    "addr:postcode":"g5r 4w7",
    "addr:street":"Rue Des Ormes Riviere-Du-Loup",
    "iso:country":"CA",
    "sg:address":"8 Rue Des Ormes",
    "sg:city":"Riviere-Du-Loup",
    "sg:classifiers":[
        {
            "category":"Communications",
            "subcategory":"Film & Video Production",
            "type":"Services"
        }
    ],
    "sg:phone":"+1 418 860 2436",
    "sg:postcode":"G5R 4W7",
    "sg:province":"QC",
    "sg:tags":[
        "motion",
        "picture"
    ],
    "wof:name":"Entreprises Daniel Masse Inc",
    "wof:placetype":"venue"
},
  "geometry": {"coordinates":[-69.5470581055,47.8341293335],"type":"Point"}
}