{
  "type": "Feature",
  "properties": {
    "addr:full":"3671 Dundas St W York ON M6S 2T3",
    "addr:housenumber":"3671",
    "addr:postcode":"m6s 2t3",
    "addr:street":"Dundas St W",
    "iso:country":"CA",
    "sg:address":"3671 Dundas St W",
    "sg:city":"York",
    "sg:classifiers":[
        {
            "category":"Food & Beverages",
            "subcategory":"Groceries & Convenience Stores",
            "type":"Retail Goods"
        }
    ],
    "sg:phone":"+1 416 769 7171",
    "sg:postcode":"M6S 2T3",
    "sg:province":"ON",
    "sg:tags":[
        "grocer"
    ],
    "wof:name":"Loblaws Supermarkets Ltd",
    "wof:placetype":"venue"
},
  "geometry": {"coordinates":[-79.505661,43.66275],"type":"Point"}
}