{
  "type": "Feature",
  "properties": {
    "addr:full":"557 Lonsdale Ave North Vancouver BC V7M 2G6",
    "addr:housenumber":"557",
    "addr:postcode":"v7m 2g6",
    "addr:street":"Lonsdale Ave",
    "iso:country":"CA",
    "sg:address":"557 Lonsdale Ave",
    "sg:city":"North Vancouver",
    "sg:classifiers":[
        {
            "category":"Professional",
            "subcategory":"Business Services",
            "type":"Services"
        }
    ],
    "sg:phone":"+1 604 987 2911",
    "sg:postcode":"V7M 2G6",
    "sg:province":"BC",
    "sg:tags":[
        "interior",
        "consultant",
        "design",
        "decorator"
    ],
    "wof:name":"Ashton House Interior Design",
    "wof:placetype":"venue"
},
  "geometry": {"coordinates":[-123.07505,49.31567],"type":"Point"}
}