{
  "type": "Feature",
  "properties": {
    "addr:full":"Farm Lumsden SK S0G 3C0",
    "addr:postcode":"s0g 3c0",
    "iso:country":"CA",
    "sg:address":"Farm",
    "sg:city":"Lumsden",
    "sg:classifiers":[
        {
            "category":"Building & Trades",
            "subcategory":"Construction",
            "type":"Services"
        }
    ],
    "sg:phone":"+1 306 731 1491",
    "sg:postcode":"S0G 3C0",
    "sg:province":"SK",
    "sg:tags":[
        "contractor"
    ],
    "wof:name":"Laron Builders Ltd",
    "wof:placetype":"venue"
},
  "geometry": {"coordinates":[-104.87041473399999,50.6437911987],"type":"Point"}
}