{
  "type": "Feature",
  "properties": {
    "addr:full":"5008 50 St #A Sylvan Lake AB T4S 1M5",
    "addr:housenumber":"5008",
    "addr:postcode":"t4s 1m5",
    "addr:street":"50 St # A",
    "iso:country":"CA",
    "sg:address":"5008 50 St #A",
    "sg:city":"Sylvan Lake",
    "sg:classifiers":[
        {
            "category":"Personal",
            "subcategory":"Barber",
            "type":"Services"
        }
    ],
    "sg:phone":"+1 403 887 4112",
    "sg:postcode":"T4S 1M5",
    "sg:province":"AB",
    "wof:name":"Sylvan Lake Barber Shop",
    "wof:placetype":"venue"
},
  "geometry": {"coordinates":[-114.097488,52.308208],"type":"Point"}
}