{
  "type": "Feature",
  "properties": {
    "addr:full":"Sainte-Foy QC G1V 2L8",
    "addr:postcode":"g1v 2l8",
    "iso:country":"CA",
    "sg:city":"Sainte-Foy",
    "sg:classifiers":[
        {
            "category":"Shopping",
            "type":"Retail Goods"
        }
    ],
    "sg:phone":"+1 418 653 2332",
    "sg:postcode":"G1V 2L8",
    "sg:province":"QC",
    "sg:tags":[
        "picture",
        "frame"
    ],
    "wof:name":"Grif & Graf Inc",
    "wof:placetype":"venue"
},
  "geometry": {"coordinates":[-71.2840805054,46.7696647644],"type":"Point"}
}