{
  "type": "Feature",
  "properties": {
    "addr:full":"180 Esplanade W North Vancouver BC V7M 1A3",
    "addr:housenumber":"180",
    "addr:postcode":"v7m 1a3",
    "addr:street":"Esplanade W",
    "iso:country":"CA",
    "sg:address":"180 Esplanade W",
    "sg:city":"North Vancouver",
    "sg:classifiers":[
        {
            "category":"Restaurant",
            "type":"Food & Drink"
        }
    ],
    "sg:phone":"+1 604 987 9911",
    "sg:postcode":"V7M 1A3",
    "sg:province":"BC",
    "wof:name":"Thai House Restaurant Ltd",
    "wof:placetype":"venue"
},
  "geometry": {"coordinates":[-123.081809998,49.3122520447],"type":"Point"}
}