{
  "type": "Feature",
  "properties": {
    "iso:country":"CA",
    "sg:city":"Mississauga",
    "sg:classifiers":[
        {
            "category":"Professional",
            "subcategory":"Advertising",
            "type":"Services"
        }
    ],
    "sg:phone":"+1 905 569 1605",
    "sg:postcode":"L5L 5Y5",
    "sg:province":"ON",
    "sg:tags":[
        "designer",
        "display",
        "producer"
    ],
    "wof:name":"Mc Rae Imaging Inc",
    "wof:placetype":"venue"
},
  "geometry": {"coordinates":[-79.718964,43.527454],"type":"Point"}
}