{
  "type": "Feature",
  "properties": {
    "addr:full":"407 Industrial Road F Cranbrook BC V1C 6P1",
    "addr:housenumber":"407",
    "addr:postcode":"v1c 6p1",
    "addr:street":"Industrial Road F",
    "iso:country":"CA",
    "sg:address":"407 Industrial Road F",
    "sg:city":"Cranbrook",
    "sg:classifiers":[
        {
            "category":"Freight",
            "type":"Transportation"
        }
    ],
    "sg:phone":"+1 250 426 4297",
    "sg:postcode":"V1C 6P1",
    "sg:province":"BC",
    "sg:tags":[
        "trucking"
    ],
    "wof:name":"Optimistic Enterprises Ltd",
    "wof:placetype":"venue"
},
  "geometry": {"coordinates":[-115.760894775,49.5317459106],"type":"Point"}
}