{
  "type": "Feature",
  "properties": {
    "addr:full":"2530 Av Brassard Plessisville QC G6L 2R9",
    "addr:housenumber":"2530",
    "addr:postcode":"g6l 2r9",
    "addr:street":"Av Brassard",
    "iso:country":"CA",
    "sg:address":"2530 Av Brassard",
    "sg:city":"Plessisville",
    "sg:classifiers":[
        {
            "category":"Real Estate",
            "subcategory":"Surveying",
            "type":"Services"
        }
    ],
    "sg:phone":"+1 819 362 8085",
    "sg:postcode":"G6L 2R9",
    "sg:province":"QC",
    "sg:tags":[
        "surveyor"
    ],
    "wof:name":"Lemieux, Andre",
    "wof:placetype":"venue"
},
  "geometry": {"coordinates":[-71.781494,46.230099],"type":"Point"}
}