{
  "type": "Feature",
  "properties": {
    "addr:full":"350 Queen St Acton ON L7J 1R2",
    "addr:housenumber":"350",
    "addr:postcode":"l7j 1r2",
    "addr:street":"Queen St",
    "iso:country":"CA",
    "sg:address":"350 Queen St",
    "sg:city":"Acton",
    "sg:classifiers":[
        {
            "category":"Banks & Credit Unions",
            "subcategory":"Bank",
            "type":"Services"
        }
    ],
    "sg:phone":"+1 519 853 0911",
    "sg:postcode":"L7J 1R2",
    "sg:province":"ON",
    "wof:name":"Prosperity One Credit Union",
    "wof:placetype":"venue"
},
  "geometry": {"coordinates":[-80.02861799999999,43.636848],"type":"Point"}
}