{
  "type": "Feature",
  "properties": {
    "iso:country":"CA",
    "sg:address":"350 Queen St",
    "sg:city":"Acton",
    "sg:classifiers":[
        {
            "category":"Banks & Credit Unions",
            "subcategory":"Bank",
            "type":"Services"
        }
    ],
    "sg:phone":"+1 519 853 0911",
    "sg:postcode":"L7J 1R2",
    "sg:province":"ON",
    "wof:name":"Prosperity One Credit Union",
    "wof:placetype":"venue"
},
  "geometry": {"coordinates":[-80.028618,43.636848],"type":"Point"}
}