{
  "type": "Feature",
  "properties": {
    "addr:full":"Kamloops BC V2C 6K7",
    "addr:postcode":"bc v2c 6k7",
    "iso:country":"CA",
    "sg:city":"Kamloops",
    "sg:classifiers":[
        {
            "category":"Retail",
            "subcategory":"Repair Shop",
            "type":"Services"
        }
    ],
    "sg:phone":"+1 250 372 2400",
    "sg:postcode":"V2C 6K7",
    "sg:province":"BC",
    "sg:tags":[
        "welding"
    ],
    "wof:name":"Grizzly Welding",
    "wof:placetype":"venue"
},
  "geometry": {"coordinates":[-120.37641143800001,50.6740112305],"type":"Point"}
}