{
  "type": "Feature",
  "properties": {
    "addr:full":"1141 Emperor Ave Ottawa ON K1Z 8C3",
    "addr:housenumber":"1141",
    "addr:postcode":"k1z 8c3",
    "addr:street":"Emperor Ave",
    "iso:country":"CA",
    "sg:address":"1141 Emperor Ave",
    "sg:city":"Ottawa",
    "sg:classifiers":[
        {
            "category":"Building & Trades",
            "subcategory":"Plumbing",
            "type":"Services"
        }
    ],
    "sg:phone":"+1 613 728 4307",
    "sg:postcode":"K1Z 8C3",
    "sg:province":"ON",
    "sg:tags":[
        "contractor"
    ],
    "wof:name":"Kelly's Plumbing & Heating Ltd",
    "wof:placetype":"venue"
},
  "geometry": {"coordinates":[-75.7243652344,45.3811569214],"type":"Point"}
}