{
  "type": "Feature",
  "properties": {
    "addr:full":"2084 Rue Bossuet Montreal QC H1N 2R7",
    "addr:housenumber":"2084",
    "addr:postcode":"h1n 2r7",
    "addr:street":"Rue Bossuet",
    "iso:country":"CA",
    "sg:address":"2084 Rue Bossuet",
    "sg:city":"Montreal",
    "sg:classifiers":[
        {
            "category":"Home & Garden",
            "subcategory":"Carpets & Floor Coverings",
            "type":"Retail Goods"
        }
    ],
    "sg:phone":"+1 514 594 6043",
    "sg:postcode":"H1N 2R7",
    "sg:province":"QC",
    "sg:tags":[
        "dealer",
        "rug"
    ],
    "wof:name":"Couvre Plancher Serge Levesque",
    "wof:placetype":"venue"
},
  "geometry": {"coordinates":[-73.53020477290001,45.5705223083],"type":"Point"}
}