{
  "type": "Feature",
  "properties": {
    "addr:full":"1470 the Queensway Etobicoke ON M8Z 1T5",
    "addr:housenumber":"1470",
    "addr:postcode":"m8z 1t5",
    "addr:street":"The Queensway",
    "iso:country":"CA",
    "sg:address":"1470 the Queensway",
    "sg:city":"Etobicoke",
    "sg:classifiers":[
        {
            "category":"Banks & Credit Unions",
            "subcategory":"Investment Brokerage",
            "type":"Services"
        }
    ],
    "sg:phone":"+1 416 251 0477",
    "sg:postcode":"M8Z 1T5",
    "sg:province":"ON",
    "sg:tags":[
        "consultant",
        "planning",
        "financial"
    ],
    "wof:name":"Assaad Financial Svc",
    "wof:placetype":"venue"
},
  "geometry": {"coordinates":[-79.53426399999999,43.619335],"type":"Point"}
}