{
  "type": "Feature",
  "properties": {
    "addr:full":"Nobel ON P0G 1G0",
    "addr:postcode":"p0g 1g0",
    "iso:country":"CA",
    "sg:city":"Nobel",
    "sg:classifiers":[
        {
            "category":"Wholesale",
            "subcategory":"Construction Materials",
            "type":"Manufacturing & Wholesale Goods"
        }
    ],
    "sg:phone":"+1 705 342 5371",
    "sg:postcode":"P0G 1G0",
    "sg:province":"ON",
    "sg:tags":[
        "sand",
        "gravel"
    ],
    "wof:name":"William Konoval & Sons Constr",
    "wof:placetype":"venue"
},
  "geometry": {"coordinates":[-80.092300415,45.4146690369],"type":"Point"}
}