{
  "type": "Feature",
  "properties": {
    "iso:country":"CA",
    "sg:address":"9658 142 St NW",
    "sg:city":"Edmonton",
    "sg:classifiers":[
        {
            "category":"Food & Beverages",
            "subcategory":"Liquor & Beverages",
            "type":"Retail Goods"
        }
    ],
    "sg:phone":"+1 780 488 7800",
    "sg:postcode":"T5N 4B2",
    "sg:province":"AB",
    "sg:tags":[
        "wine"
    ],
    "wof:name":"Crestwood Fine Wines-Spirits",
    "wof:placetype":"venue"
},
  "geometry": {"coordinates":[-113.566001892,53.5340385437],"type":"Point"}
}