{
  "type": "Feature",
  "properties": {
    "addr:full":"6843 Dawson St Niagara Falls ON L2E 7B6",
    "addr:housenumber":"6843",
    "addr:postcode":"l2e 7b6",
    "addr:street":"Dawson St",
    "iso:country":"CA",
    "sg:address":"6843 Dawson St",
    "sg:city":"Niagara Falls",
    "sg:classifiers":[
        {
            "category":"Health Services",
            "subcategory":"Doctor",
            "type":"Services"
        }
    ],
    "sg:phone":"+1 905 356 1971",
    "sg:postcode":"L2E 7B6",
    "sg:province":"ON",
    "sg:tags":[
        "dentist"
    ],
    "wof:name":"Yamasaki, Thomas DDS",
    "wof:placetype":"venue"
},
  "geometry": {"coordinates":[-79.109955,43.100178],"type":"Point"}
}