{
  "type": "Feature",
  "properties": {
    "addr:full":"1225 Hyde Park Rd London ON N6H 5K6",
    "addr:housenumber":"1225",
    "addr:postcode":"n6h 5k6",
    "addr:street":"Hyde Park Rd",
    "iso:country":"CA",
    "sg:address":"1225 Hyde Park Rd",
    "sg:city":"London",
    "sg:classifiers":[
        {
            "category":"Retail",
            "subcategory":"Auto Repair",
            "type":"Services"
        }
    ],
    "sg:phone":"+1 519 472 6000",
    "sg:postcode":"N6H 5K6",
    "sg:province":"ON",
    "sg:tags":[
        "repairing",
        "automobile"
    ],
    "wof:name":"Rob Clarke Automotive",
    "wof:placetype":"venue"
},
  "geometry": {"coordinates":[-81.32759900000001,42.990028],"type":"Point"}
}