{
  "type": "Feature",
  "properties": {
    "addr:full":"17204 105 Ave NW Edmonton AB T5S 1G4",
    "addr:housenumber":"17204",
    "addr:postcode":"t5s 1g4",
    "addr:street":"105 Ave Nw",
    "iso:country":"CA",
    "sg:address":"17204 105 Ave NW",
    "sg:city":"Edmonton",
    "sg:classifiers":[
        {
            "category":"Retail",
            "subcategory":"Auto Rental",
            "type":"Services"
        }
    ],
    "sg:phone":"+1 780 483 0344",
    "sg:postcode":"T5S 1G4",
    "sg:province":"AB",
    "sg:tags":[
        "renting",
        "truck",
        "leasing"
    ],
    "wof:name":"Champion Truck Rentals Inc",
    "wof:placetype":"venue"
},
  "geometry": {"coordinates":[-113.618171692,53.5487518311],"type":"Point"}
}