{
  "type": "Feature",
  "properties": {
    "addr:full":"1729 Av Sainte-Famille Sainte-Foy QC G2G 1M2",
    "addr:housenumber":"1729",
    "addr:postcode":"g2g 1m2",
    "addr:street":"Av Sainte-Famille",
    "iso:country":"CA",
    "sg:address":"1729 Av Sainte-Famille",
    "sg:city":"Sainte-Foy",
    "sg:classifiers":[
        {
            "category":"Arts & Performance",
            "subcategory":"Theater",
            "type":"Entertainment"
        }
    ],
    "sg:phone":"+1 418 877 9218",
    "sg:postcode":"G2G 1M2",
    "sg:province":"QC",
    "sg:tags":[
        "talent",
        "agency",
        "casting"
    ],
    "wof:name":"Productions Andre Jacques",
    "wof:placetype":"venue"
},
  "geometry": {"coordinates":[-71.362679,46.781845],"type":"Point"}
}