{
  "type": "Feature",
  "properties": {
    "iso:country":"CA",
    "sg:city":"Vancouver",
    "sg:classifiers":[
        {
            "category":"Health Services",
            "subcategory":"Medical Lab",
            "type":"Services"
        }
    ],
    "sg:phone":"+1 604 325 6788",
    "sg:postcode":"V5X 4V9",
    "sg:province":"BC",
    "sg:tags":[
        "laboratory"
    ],
    "wof:name":"G A Orthodont Craft Lab Ltd",
    "wof:placetype":"venue"
},
  "geometry": {"coordinates":[-123.084892,49.208893],"type":"Point"}
}