{
  "type": "Feature",
  "properties": {
    "iso:country":"CA",
    "sg:address":"4585 Albert St",
    "sg:city":"Burnaby",
    "sg:classifiers":[
        {
            "category":"Social Services",
            "type":"Services"
        }
    ],
    "sg:phone":"+1 604 294 1936",
    "sg:postcode":"V5C 2G6",
    "sg:province":"BC",
    "sg:tags":[
        "senior",
        "citizen",
        "recreation",
        "center"
    ],
    "wof:name":"Confederation Community Ctr",
    "wof:placetype":"venue"
},
  "geometry": {"coordinates":[-123.00064086899999,49.2820968628],"type":"Point"}
}