{
  "type": "Feature",
  "properties": {
    "addr:full":"58 Westmount Bay Winnipeg MB R2J 1Y9",
    "addr:housenumber":"58",
    "addr:postcode":"r2j 1y9",
    "addr:street":"Westmount Bay",
    "iso:country":"CA",
    "sg:address":"58 Westmount Bay",
    "sg:city":"Winnipeg",
    "sg:classifiers":[
        {
            "category":"Wholesale",
            "subcategory":"Hardware",
            "type":"Manufacturing & Wholesale Goods"
        }
    ],
    "sg:phone":"+1 204 256 7283",
    "sg:postcode":"R2J 1Y9",
    "sg:province":"MB",
    "sg:tags":[
        "equipment",
        "energy",
        "solar"
    ],
    "wof:name":"Simply Solar",
    "wof:placetype":"venue"
},
  "geometry": {"coordinates":[-97.06549835209999,49.8626480103],"type":"Point"}
}