{
  "type": "Feature",
  "properties": {
    "iso:country":"CA",
    "sg:city":"Sainte-Foy",
    "sg:classifiers":[
        {
            "category":"Professional",
            "subcategory":"Business Services",
            "type":"Services"
        }
    ],
    "sg:phone":"+1 418 659 4812",
    "sg:postcode":"G1V 4P1",
    "sg:province":"QC",
    "sg:tags":[
        "interior",
        "consultant",
        "design",
        "decorator"
    ],
    "wof:name":"Giovanni Maur Designer Inc",
    "wof:placetype":"venue"
},
  "geometry": {"coordinates":[-71.295204,46.76598],"type":"Point"}
}