{
  "type": "Feature",
  "properties": {
    "iso:country":"CA",
    "sg:address":"159 Rue Saint-Damase",
    "sg:city":"Drummondville",
    "sg:classifiers":[
        {
            "category":"Health Services",
            "subcategory":"Medical Lab",
            "type":"Services"
        }
    ],
    "sg:phone":"+1 819 478 2030",
    "sg:postcode":"J2B 6G6",
    "sg:province":"QC",
    "wof:name":"Entreprise Mario Belhumeur",
    "wof:placetype":"venue"
},
  "geometry": {"coordinates":[-72.4921951294,45.8729133606],"type":"Point"}
}