{
  "type": "Feature",
  "properties": {
    "addr:full":"10400 Rue Renaude-Lapointe Anjou QC H1J 2V7",
    "addr:housenumber":"10400",
    "addr:postcode":"h1j 2v7",
    "addr:street":"Rue Renaude-Lapointe",
    "iso:country":"CA",
    "sg:address":"10400 Rue Renaude-Lapointe",
    "sg:city":"Anjou",
    "sg:classifiers":[
        {
            "category":"Shopping",
            "type":"Retail Goods"
        }
    ],
    "sg:phone":"+1 514 322 5300",
    "sg:postcode":"H1J 2V7",
    "sg:province":"QC",
    "sg:tags":[
        "pet",
        "food",
        "shop",
        "supply"
    ],
    "wof:name":"J E Mondou Ltee",
    "wof:placetype":"venue"
},
  "geometry": {"coordinates":[-73.5905380249,45.6117095947],"type":"Point"}
}