{
  "type": "Feature",
  "properties": {
    "addr:full":"9149 82 Ave NW Edmonton AB T6C 0Z4",
    "addr:housenumber":"9149",
    "addr:postcode":"t6c 0z4",
    "addr:street":"82 Ave Nw",
    "iso:country":"CA",
    "sg:address":"9149 82 Ave NW",
    "sg:city":"Edmonton",
    "sg:classifiers":[
        {
            "category":"Health Services",
            "subcategory":"Doctor",
            "type":"Services"
        }
    ],
    "sg:phone":"+1 780 463 9522",
    "sg:postcode":"T6C 0Z4",
    "sg:province":"AB",
    "sg:tags":[
        "dentist"
    ],
    "wof:name":"Millcreek Dental Care",
    "wof:placetype":"venue"
},
  "geometry": {"coordinates":[-113.46822400000001,53.517803],"type":"Point"}
}