{
  "type": "Feature",
  "properties": {
    "addr:full":"44 Windsor Dr Ajax ON L1T 2Z6",
    "addr:housenumber":"44",
    "addr:postcode":"l1t 2z6",
    "addr:street":"Windsor Dr",
    "iso:country":"CA",
    "sg:address":"44 Windsor Dr",
    "sg:city":"Ajax",
    "sg:classifiers":[
        {
            "category":"Manufacturing",
            "subcategory":"Metals",
            "type":"Manufacturing & Wholesale Goods"
        }
    ],
    "sg:phone":"+1 905 686 3234",
    "sg:postcode":"L1T 2Z6",
    "sg:province":"ON",
    "sg:tags":[
        "door"
    ],
    "wof:name":"Mac Fayden Windows",
    "wof:placetype":"venue"
},
  "geometry": {"coordinates":[-79.0605926514,43.8561897278],"type":"Point"}
}