{
  "type": "Feature",
  "properties": {
    "addr:full":"5008 Baysel Ave Swan Hills AB T0G 2C0",
    "addr:housenumber":"5008",
    "addr:postcode":"t0g 2c0",
    "addr:street":"Baysel Ave",
    "iso:country":"CA",
    "sg:address":"5008 Baysel Ave",
    "sg:city":"Swan Hills",
    "sg:classifiers":[
        {
            "category":"Professional",
            "subcategory":"Business Services",
            "type":"Services"
        }
    ],
    "sg:phone":"+1 780 333 4754",
    "sg:postcode":"T0G 2C0",
    "sg:province":"AB",
    "sg:tags":[
        "embroidery"
    ],
    "wof:name":"Little House Embroidery",
    "wof:placetype":"venue"
},
  "geometry": {"coordinates":[-115.413177,54.718685],"type":"Point"}
}