{
  "type": "Feature",
  "properties": {
    "addr:full":"89 King St E Toronto ON M5C 1G3",
    "addr:housenumber":"89",
    "addr:postcode":"m5c 1g3",
    "addr:street":"King St E",
    "iso:country":"CA",
    "sg:address":"89 King St E",
    "sg:city":"Toronto",
    "sg:classifiers":[
        {
            "category":"Retail",
            "subcategory":"Laundry & Dry Cleaning",
            "type":"Services"
        }
    ],
    "sg:phone":"+1 416 362 6713",
    "sg:postcode":"M5C 1G3",
    "sg:province":"ON",
    "sg:tags":[
        "cleaners",
        "carpet",
        "dealer",
        "rug"
    ],
    "wof:name":"Adourian's Rug Galleries Ltd",
    "wof:placetype":"venue"
},
  "geometry": {"coordinates":[-79.3747711182,43.6496925354],"type":"Point"}
}