{
  "type": "Feature",
  "properties": {
    "addr:full":"121 Rte 303 Otter Lake QC J0X 2P0",
    "addr:housenumber":"121",
    "addr:postcode":"j0x 2p0",
    "addr:street":"Rte 303",
    "iso:country":"CA",
    "sg:address":"121 Rte 303",
    "sg:city":"Otter Lake",
    "sg:classifiers":[
        {
            "category":"Home & Garden",
            "subcategory":"Hardware",
            "type":"Retail Goods"
        }
    ],
    "sg:phone":"+1 819 453 7621",
    "sg:postcode":"J0X 2P0",
    "sg:province":"QC",
    "sg:tags":[
        "building",
        "material"
    ],
    "wof:name":"Dale's Home Hardware & Bldg",
    "wof:placetype":"venue"
},
  "geometry": {"coordinates":[-76.3956375122,45.8421058655],"type":"Point"}
}