{
  "type": "Feature",
  "properties": {
    "addr:full":"Basin Head Rd Elmira PE C0A 1K0",
    "addr:postcode":"c0a 1k0",
    "addr:street":"Head Rd",
    "iso:country":"CA",
    "sg:address":"Basin Head Rd",
    "sg:city":"Elmira",
    "sg:classifiers":[
        {
            "category":"Recreation",
            "type":"Entertainment"
        }
    ],
    "sg:phone":"+1 902 357 7230",
    "sg:postcode":"C0A 1K0",
    "sg:province":"PE",
    "sg:tags":[
        "provincial",
        "parks"
    ],
    "wof:name":"Basin Head Park",
    "wof:placetype":"venue"
},
  "geometry": {"coordinates":[-62.065502,46.440529],"type":"Point"}
}