{
  "type": "Feature",
  "properties": {
    "addr:full":"1945 Queen St E Toronto ON M4L 1H7",
    "addr:housenumber":"1945",
    "addr:postcode":"m4l 1h7",
    "addr:street":"Queen St E",
    "iso:country":"CA",
    "sg:address":"1945 Queen St E",
    "sg:city":"Toronto",
    "sg:classifiers":[
        {
            "category":"Shopping",
            "type":"Retail Goods"
        }
    ],
    "sg:phone":"+1 416 694 9485",
    "sg:postcode":"M4L 1H7",
    "sg:province":"ON",
    "sg:tags":[
        "art",
        "gallery",
        "dealer"
    ],
    "wof:name":"Incurable Collector",
    "wof:placetype":"venue"
},
  "geometry": {"coordinates":[-79.302879,43.669266],"type":"Point"}
}