{
  "type": "Feature",
  "properties": {
    "addr:full":"425 St Mary Ave Winnipeg MB R3C 0N2",
    "addr:housenumber":"425",
    "addr:postcode":"r3c 0n2",
    "addr:street":"St Mary Ave",
    "iso:country":"CA",
    "sg:address":"425 St Mary Ave",
    "sg:city":"Winnipeg",
    "sg:classifiers":[
        {
            "category":"Health Services",
            "subcategory":"Doctor",
            "type":"Services"
        }
    ],
    "sg:phone":"+1 204 957 3235",
    "sg:postcode":"R3C 0N2",
    "sg:province":"MB",
    "sg:tags":[
        "physician",
        "surgeon"
    ],
    "wof:name":"Prodan, O MD",
    "wof:placetype":"venue"
},
  "geometry": {"coordinates":[-97.14888000000001,49.889172],"type":"Point"}
}