{
  "type": "Feature",
  "properties": {
    "addr:full":"362 Lacewood Dr Halifax NS B3S 1M7",
    "addr:housenumber":"362",
    "addr:postcode":"b3s 1m7",
    "addr:street":"Lacewood Dr",
    "iso:country":"CA",
    "sg:address":"362 Lacewood Dr",
    "sg:city":"Halifax",
    "sg:classifiers":[
        {
            "category":"Home & Garden",
            "subcategory":"Carpets & Floor Coverings",
            "type":"Retail Goods"
        }
    ],
    "sg:phone":"+1 902 445 6400",
    "sg:postcode":"B3S 1M7",
    "sg:province":"NS",
    "sg:tags":[
        "material",
        "rug"
    ],
    "wof:name":"Taylor Flooring",
    "wof:placetype":"venue"
},
  "geometry": {"coordinates":[-63.669769,44.658672],"type":"Point"}
}