{
  "type": "Feature",
  "properties": {
    "iso:country":"CA",
    "sg:address":"9251 Yonge St #200",
    "sg:city":"Richmond Hill",
    "sg:classifiers":[
        {
            "category":"Insurance",
            "subcategory":"Insurance Agent",
            "type":"Services"
        }
    ],
    "sg:phone":"+1 905 709 9808",
    "sg:postcode":"L4C 9T3",
    "sg:province":"ON",
    "wof:name":"Pinnacle General Insurance",
    "wof:placetype":"venue"
},
  "geometry": {"coordinates":[-79.4326629639,43.8523521423],"type":"Point"}
}