{
  "type": "Feature",
  "properties": {
    "addr:full":"2290 Rue Bruneau Quebec QC G1J 2J9",
    "addr:housenumber":"2290",
    "addr:postcode":"g1j 2j9",
    "addr:street":"Rue Bruneau",
    "iso:country":"CA",
    "sg:address":"2290 Rue Bruneau",
    "sg:city":"Quebec",
    "sg:classifiers":[
        {
            "category":"Food & Beverages",
            "subcategory":"Groceries & Convenience Stores",
            "type":"Retail Goods"
        }
    ],
    "sg:phone":"+1 418 663 6464",
    "sg:postcode":"G1J 2J9",
    "sg:province":"QC",
    "sg:tags":[
        "grocer"
    ],
    "wof:name":"Accommodation Rapide Inc",
    "wof:placetype":"venue"
},
  "geometry": {"coordinates":[-71.215851,46.840267],"type":"Point"}
}