{
  "type": "Feature",
  "properties": {
    "addr:full":"3130 Boul Dagenais O Laval QC H7P 1T9",
    "addr:housenumber":"3130",
    "addr:postcode":"h7p 1t9",
    "addr:street":"Boul Dagenais O",
    "iso:country":"CA",
    "sg:address":"3130 Boul Dagenais O",
    "sg:city":"Laval",
    "sg:classifiers":[
        {
            "category":"Restaurant",
            "type":"Food & Drink"
        }
    ],
    "sg:phone":"+1 450 625 6711",
    "sg:postcode":"H7P 1T9",
    "sg:province":"QC",
    "sg:tags":[
        "parlor",
        "ice",
        "cream"
    ],
    "wof:name":"Dairy Queen",
    "wof:placetype":"venue"
},
  "geometry": {"coordinates":[-73.7942199707,45.5787200928],"type":"Point"}
}