{
  "type": "Feature",
  "properties": {
    "addr:full":"Grande Prairie AB T8V 3Y2",
    "addr:postcode":"t8v 3y2",
    "iso:country":"CA",
    "sg:city":"Grande Prairie",
    "sg:classifiers":[
        {
            "category":"Restaurant",
            "type":"Food & Drink"
        }
    ],
    "sg:phone":"+1 780 538 3551",
    "sg:postcode":"T8V 3Y2",
    "sg:province":"AB",
    "wof:name":"Edo Japan-Grande Prairie",
    "wof:placetype":"venue"
},
  "geometry": {"coordinates":[-118.794456482,55.1868743896],"type":"Point"}
}