{
  "type": "Feature",
  "properties": {
    "addr:full":"56954 Eden Line Eden ON N0J 1H0",
    "addr:housenumber":"56954",
    "addr:postcode":"n0j 1h0",
    "addr:street":"Eden Line",
    "iso:country":"CA",
    "sg:address":"56954 Eden Line",
    "sg:city":"Eden",
    "sg:classifiers":[
        {
            "category":"Manufacturing",
            "subcategory":"Tools & Machinery",
            "type":"Manufacturing & Wholesale Goods"
        }
    ],
    "sg:phone":"+1 519 866 5677",
    "sg:postcode":"N0J 1H0",
    "sg:province":"ON",
    "sg:tags":[
        "equipment",
        "material",
        "handling"
    ],
    "wof:name":"Phil Mauer & Assoc Inc",
    "wof:placetype":"venue"
},
  "geometry": {"coordinates":[-80.75200700000001,42.794197],"type":"Point"}
}