{
  "type": "Feature",
  "properties": {
    "addr:full":"22078 Triad Rd Prespatou BC V0C 2S0",
    "addr:postcode":"22078;bc v0c 2s0",
    "addr:street":"Triad Rd",
    "iso:country":"CA",
    "sg:address":"22078 Triad Rd",
    "sg:city":"Prespatou",
    "sg:classifiers":[
        {
            "category":"Retail",
            "subcategory":"Auto Repair",
            "type":"Services"
        }
    ],
    "sg:phone":"+1 250 630 2334",
    "sg:postcode":"V0C 2S0",
    "sg:province":"BC",
    "sg:tags":[
        "repairing",
        "automobile"
    ],
    "wof:name":"Klassen Auto Repair",
    "wof:placetype":"venue"
},
  "geometry": {"coordinates":[-121.09728241000001,56.898235321],"type":"Point"}
}