{
  "type": "Feature",
  "properties": {
    "addr:full":"676 Elizabeth Rd Winnipeg MB R2J 1A4",
    "addr:housenumber":"676",
    "addr:postcode":"r2j 1a4",
    "addr:street":"Elizabeth Rd",
    "iso:country":"CA",
    "sg:address":"676 Elizabeth Rd",
    "sg:city":"Winnipeg",
    "sg:classifiers":[
        {
            "category":"Personal",
            "subcategory":"Beauty Salon",
            "type":"Services"
        }
    ],
    "sg:phone":"+1 204 255 4292",
    "sg:postcode":"R2J 1A4",
    "sg:province":"MB",
    "wof:name":"Peter's Hairstyling",
    "wof:placetype":"venue"
},
  "geometry": {"coordinates":[-97.08911895750001,49.8708572388],"type":"Point"}
}