{
  "type": "Feature",
  "properties": {
    "addr:full":"Mission BC V2V 5X9",
    "addr:postcode":"v2v 5x9",
    "iso:country":"CA",
    "sg:city":"Mission",
    "sg:classifiers":[
        {
            "category":"Building & Trades",
            "subcategory":"Construction",
            "type":"Services"
        }
    ],
    "sg:phone":"+1 604 820 4497",
    "sg:postcode":"V2V 5X9",
    "sg:province":"BC",
    "sg:tags":[
        "millwright"
    ],
    "wof:name":"Team Machinist & Millwright",
    "wof:placetype":"venue"
},
  "geometry": {"coordinates":[-122.31413999999999,49.13076],"type":"Point"}
}