{
  "type": "Feature",
  "properties": {
    "addr:full":"1230 Boul Saint-Antoine Saint-Jerome QC J7Z 7M2",
    "addr:housenumber":"1230",
    "addr:postcode":"j7z 7m2",
    "addr:street":"Boul Saint-Antoine",
    "iso:country":"CA",
    "sg:address":"1230 Boul Saint-Antoine",
    "sg:city":"Saint-Jerome",
    "sg:classifiers":[
        {
            "category":"Health Services",
            "subcategory":"Medical Lab",
            "type":"Services"
        }
    ],
    "sg:phone":"+1 450 432 8898",
    "sg:postcode":"J7Z 7M2",
    "sg:province":"QC",
    "wof:name":"Prud-Homme, Simon",
    "wof:placetype":"venue"
},
  "geometry": {"coordinates":[-73.97513600000001,45.768639],"type":"Point"}
}