{
  "type": "Feature",
  "properties": {
    "addr:full":"Sherwood Park AB T8A 2H6",
    "addr:postcode":"t8a 2h6",
    "iso:country":"CA",
    "sg:city":"Sherwood Park",
    "sg:classifiers":[
        {
            "category":"Retail",
            "subcategory":"Self-service Laundry",
            "type":"Services"
        }
    ],
    "sg:phone":"+1 780 417 2130",
    "sg:postcode":"T8A 2H6",
    "sg:province":"AB",
    "wof:name":"Maplewood Coin Laundry",
    "wof:placetype":"venue"
},
  "geometry": {"coordinates":[-113.295249939,53.5148963928],"type":"Point"}
}