{
  "type": "Feature",
  "properties": {
    "addr:full":"183 Little Narrows Rd Little Narrows NS B0E 1T0",
    "addr:housenumber":"183",
    "addr:postcode":"b0e 1t0",
    "addr:street":"Little Narrows Rd",
    "iso:country":"CA",
    "sg:address":"183 Little Narrows Rd",
    "sg:city":"Little Narrows",
    "sg:classifiers":[
        {
            "category":"Building & Trades",
            "subcategory":"Construction",
            "type":"Services"
        }
    ],
    "sg:phone":"+1 902 756 3033",
    "sg:postcode":"B0E 1T0",
    "sg:province":"NS",
    "sg:tags":[
        "general",
        "contractor"
    ],
    "wof:name":"D W Matheson & Contracting Ltd",
    "wof:placetype":"venue"
},
  "geometry": {"coordinates":[-60.9846763611,45.992515564],"type":"Point"}
}