{
  "type": "Feature",
  "properties": {
    "addr:full":"Calgary AB T2P 3N2",
    "addr:postcode":"t2p 3n2",
    "iso:country":"CA",
    "sg:city":"Calgary",
    "sg:classifiers":[
        {
            "category":"Professional",
            "subcategory":"Computer Services",
            "type":"Services"
        }
    ],
    "sg:phone":"+1 403 237 7750",
    "sg:postcode":"T2P 3N2",
    "sg:province":"AB",
    "wof:name":"Msi Systems Integration Ltd",
    "wof:placetype":"venue"
},
  "geometry": {"coordinates":[-114.063087463,51.0494346619],"type":"Point"}
}