{
  "type": "Feature",
  "properties": {
    "addr:full":"290 William Ave Winnipeg MB R3B 0R1",
    "addr:housenumber":"290",
    "addr:postcode":"r3b 0r1",
    "addr:street":"William Ave",
    "iso:country":"CA",
    "sg:address":"290 William Ave",
    "sg:city":"Winnipeg",
    "sg:classifiers":[
        {
            "category":"Professional",
            "subcategory":"Employment Agencies",
            "type":"Services"
        }
    ],
    "sg:phone":"+1 204 982 4600",
    "sg:postcode":"R3B 0R1",
    "sg:province":"MB",
    "sg:tags":[
        "opportunity"
    ],
    "wof:name":"Aactive Personnel Svc Ltd",
    "wof:placetype":"venue"
},
  "geometry": {"coordinates":[-97.140869,49.899315],"type":"Point"}
}