{
  "type": "Feature",
  "properties": {
    "addr:full":"74 Rue Principale Aylmer QC J9H 3L7",
    "addr:housenumber":"74",
    "addr:postcode":"j9h 3l7",
    "addr:street":"Rue Principale",
    "iso:country":"CA",
    "sg:address":"74 Rue Principale",
    "sg:city":"Aylmer",
    "sg:classifiers":[
        {
            "category":"Social Services",
            "type":"Services"
        }
    ],
    "sg:phone":"+1 819 682 4622",
    "sg:postcode":"J9H 3L7",
    "sg:province":"QC",
    "sg:tags":[
        "organization",
        "welfare"
    ],
    "wof:name":"Pavillon Du Parc Inc",
    "wof:placetype":"venue"
},
  "geometry": {"coordinates":[-75.8471908569,45.3946495056],"type":"Point"}
}