{
  "type": "Feature",
  "properties": {
    "addr:full":"745 Av D'Anvers Montreal QC H3N 1C8",
    "addr:postcode":"h3n 1c8",
    "addr:street":"745 Av D'Anvers",
    "iso:country":"CA",
    "sg:address":"745 Av D'Anvers",
    "sg:city":"Montreal",
    "sg:classifiers":[
        {
            "category":"Organizations",
            "subcategory":"Religious Organization",
            "type":"Services"
        }
    ],
    "sg:phone":"+1 514 272 2391",
    "sg:postcode":"H3N 1C8",
    "sg:province":"QC",
    "sg:tags":[
        "church"
    ],
    "wof:name":"Eglise Baptiste DE Siloe",
    "wof:placetype":"venue"
},
  "geometry": {"coordinates":[-73.63800000000001,45.533623],"type":"Point"}
}