{
  "type": "Feature",
  "properties": {
    "addr:full":"653 Mctavish St Regina SK S4T 3T6",
    "addr:housenumber":"653",
    "addr:postcode":"s4t 3t6",
    "addr:street":"Mctavish St",
    "iso:country":"CA",
    "sg:address":"653 Mctavish St",
    "sg:city":"Regina",
    "sg:classifiers":[
        {
            "category":"Building & Trades",
            "subcategory":"Plumbing",
            "type":"Services"
        }
    ],
    "sg:phone":"+1 306 525 9925",
    "sg:postcode":"S4T 3T6",
    "sg:province":"SK",
    "sg:tags":[
        "contractor"
    ],
    "wof:name":"A & P Mechanical",
    "wof:placetype":"venue"
},
  "geometry": {"coordinates":[-104.633850098,50.4684791565],"type":"Point"}
}