{
  "type": "Feature",
  "properties": {
    "addr:full":"10120 95 Ave Fort St John BC V1J 1J1",
    "addr:housenumber":"10120",
    "addr:postcode":"v1j 1j1",
    "addr:street":"95 Ave",
    "iso:country":"CA",
    "sg:address":"10120 95 Ave",
    "sg:city":"Fort St John",
    "sg:classifiers":[
        {
            "category":"Retail",
            "subcategory":"Auto Repair",
            "type":"Services"
        }
    ],
    "sg:phone":"+1 250 787 0648",
    "sg:postcode":"V1J 1J1",
    "sg:province":"BC",
    "sg:tags":[
        "repairing",
        "automobile"
    ],
    "wof:name":"W & C Automotive Ltd",
    "wof:placetype":"venue"
},
  "geometry": {"coordinates":[-120.849503,56.241581],"type":"Point"}
}