{
  "type": "Feature",
  "properties": {
    "addr:full":"1199 Topsail Rd Mount Pearl NL A1N 5G2",
    "addr:housenumber":"1199",
    "addr:postcode":"a1n 5g2",
    "addr:street":"Topsail Rd",
    "iso:country":"CA",
    "sg:address":"1199 Topsail Rd",
    "sg:city":"Mount Pearl",
    "sg:classifiers":[
        {
            "category":"Retail",
            "subcategory":"Auto Repair",
            "type":"Services"
        }
    ],
    "sg:phone":"+1 709 368 6300",
    "sg:postcode":"A1N 5G2",
    "sg:province":"NL",
    "sg:tags":[
        "repairing",
        "automobile"
    ],
    "wof:name":"Walsh's Automotive",
    "wof:placetype":"venue"
},
  "geometry": {"coordinates":[-52.826157,47.528465],"type":"Point"}
}