{
  "type": "Feature",
  "properties": {
    "addr:full":"100 Railway Ave Lucky Lake SK S0L 1Z0",
    "addr:housenumber":"100",
    "addr:postcode":"s0l 1z0",
    "addr:street":"Railway Ave",
    "iso:country":"CA",
    "sg:address":"100 Railway Ave",
    "sg:city":"Lucky Lake",
    "sg:classifiers":[
        {
            "category":"Home & Garden",
            "subcategory":"Building Materials",
            "type":"Retail Goods"
        }
    ],
    "sg:phone":"+1 306 858 2233",
    "sg:postcode":"S0L 1Z0",
    "sg:province":"SK",
    "sg:tags":[
        "lumber"
    ],
    "wof:name":"Ken's Lumber Sales",
    "wof:placetype":"venue"
},
  "geometry": {"coordinates":[-107.135559,50.979946],"type":"Point"}
}