{
  "type": "Feature",
  "properties": {
    "addr:full":"3025 Fir St Vancouver BC V6J 5K3",
    "addr:housenumber":"3025",
    "addr:postcode":"v6j 5k3",
    "addr:street":"Fir St",
    "iso:country":"CA",
    "sg:address":"3025 Fir St",
    "sg:city":"Vancouver",
    "sg:classifiers":[
        {
            "category":"Recreation",
            "type":"Entertainment"
        }
    ],
    "sg:phone":"+1 604 731 8422",
    "sg:postcode":"V6J 5K3",
    "sg:province":"BC",
    "sg:tags":[
        "amusement"
    ],
    "wof:name":"Granville Park Lawn Bowling",
    "wof:placetype":"venue"
},
  "geometry": {"coordinates":[-123.141373,49.258682],"type":"Point"}
}