{
  "type": "Feature",
  "properties": {
    "addr:full":"12208 Bonaventure Dr SE Calgary AB T2J 2V7",
    "addr:housenumber":"12208",
    "addr:postcode":"t2j 2v7",
    "addr:street":"Bonaventure Dr Se",
    "iso:country":"CA",
    "sg:address":"12208 Bonaventure Dr SE",
    "sg:city":"Calgary",
    "sg:classifiers":[
        {
            "category":"Building & Trades",
            "subcategory":"Electrical",
            "type":"Services"
        }
    ],
    "sg:phone":"+1 403 286 1822",
    "sg:postcode":"T2J 2V7",
    "sg:province":"AB",
    "sg:tags":[
        "electric",
        "contractor"
    ],
    "wof:name":"Bertram Electric Ltd",
    "wof:placetype":"venue"
},
  "geometry": {"coordinates":[-114.060379,50.943966],"type":"Point"}
}