{
  "type": "Feature",
  "properties": {
    "addr:full":"420 Rue Belvedere S Sherbrooke QC J1H 4B5",
    "addr:housenumber":"420",
    "addr:postcode":"j1h 4b5",
    "addr:street":"Rue Belvedere S",
    "iso:country":"CA",
    "sg:address":"420 Rue Belvedere S",
    "sg:city":"Sherbrooke",
    "sg:classifiers":[
        {
            "category":"Shopping",
            "subcategory":"Pharmacy",
            "type":"Retail Goods"
        }
    ],
    "sg:phone":"+1 819 566 6821",
    "sg:postcode":"J1H 4B5",
    "sg:province":"QC",
    "wof:name":"Pharmaprix",
    "wof:placetype":"venue"
},
  "geometry": {"coordinates":[-71.89592,45.395683],"type":"Point"}
}