{
  "type": "Feature",
  "properties": {
    "addr:full":"Waterloo ON N2J 4R4",
    "addr:postcode":"n2j 4r4",
    "iso:country":"CA",
    "sg:city":"Waterloo",
    "sg:classifiers":[
        {
            "category":"Building & Trades",
            "subcategory":"Plumbing",
            "type":"Services"
        }
    ],
    "sg:phone":"+1 519 885 2140",
    "sg:postcode":"N2J 4R4",
    "sg:province":"ON",
    "sg:tags":[
        "contractor"
    ],
    "wof:name":"Paton Brothers Ltd",
    "wof:placetype":"venue"
},
  "geometry": {"coordinates":[-80.51512146,43.4890670776],"type":"Point"}
}