{
  "type": "Feature",
  "properties": {
    "addr:full":"56 4th Ave Englehart ON P0J 1H0",
    "addr:housenumber":"56",
    "addr:postcode":"p0j 1h0",
    "addr:street":"4Th Ave",
    "iso:country":"CA",
    "sg:address":"56 4th Ave",
    "sg:city":"Englehart",
    "sg:classifiers":[
        {
            "category":"Government",
            "subcategory":"Office",
            "type":"Public Place"
        }
    ],
    "sg:phone":"+1 705 544 8050",
    "sg:postcode":"P0J 1H0",
    "sg:province":"ON",
    "wof:name":"Ontario Driver & Vehicle Agent",
    "wof:placetype":"venue"
},
  "geometry": {"coordinates":[-79.876015,47.824078],"type":"Point"}
}