{
  "type": "Feature",
  "properties": {
    "addr:full":"Toronto ON M5R 1A6",
    "addr:postcode":"m5r 1a6",
    "iso:country":"CA",
    "sg:city":"Toronto",
    "sg:classifiers":[
        {
            "category":"Health Services",
            "subcategory":"Doctor",
            "type":"Services"
        }
    ],
    "sg:phone":"+1 416 967 4212",
    "sg:postcode":"M5R 1A6",
    "sg:province":"ON",
    "sg:tags":[
        "dentist"
    ],
    "wof:name":"Sturm, Judy DDS",
    "wof:placetype":"venue"
},
  "geometry": {"coordinates":[-79.39193,43.670258],"type":"Point"}
}