{
  "type": "Feature",
  "properties": {
    "addr:full":"9615 102 St Grande Prairie AB T8V 2T8",
    "addr:housenumber":"9615",
    "addr:postcode":"t8v 2t8",
    "addr:street":"102 St",
    "iso:country":"CA",
    "sg:address":"9615 102 St",
    "sg:city":"Grande Prairie",
    "sg:classifiers":[
        {
            "category":"Organizations",
            "subcategory":"Religious Organization",
            "type":"Services"
        }
    ],
    "sg:phone":"+1 780 624 5980",
    "sg:postcode":"T8V 2T8",
    "sg:province":"AB",
    "sg:tags":[
        "church"
    ],
    "wof:name":"Salvation Army",
    "wof:placetype":"venue"
},
  "geometry": {"coordinates":[-118.80115499999999,55.167217],"type":"Point"}
}