{
  "type": "Feature",
  "properties": {
    "addr:full":"183 Ellesmere Rd Scarborough ON M1R 4C9",
    "addr:housenumber":"183",
    "addr:postcode":"m1r 4c9",
    "addr:street":"Ellesmere Rd",
    "iso:country":"CA",
    "sg:address":"183 Ellesmere Rd",
    "sg:city":"Scarborough",
    "sg:classifiers":[
        {
            "category":"Arts & Performance",
            "subcategory":"Theater",
            "type":"Entertainment"
        }
    ],
    "sg:phone":"+1 416 449 4514",
    "sg:postcode":"M1R 4C9",
    "sg:province":"ON",
    "sg:tags":[
        "live",
        "music"
    ],
    "wof:name":"Sounds Exclusive Pro Disc Jcky",
    "wof:placetype":"venue"
},
  "geometry": {"coordinates":[-79.30519099999999,43.760052],"type":"Point"}
}