{
  "type": "Feature",
  "properties": {
    "addr:full":"64 Powell Dr Carbonear NL A1Y 1A5",
    "addr:housenumber":"64",
    "addr:postcode":"a1y 1a5",
    "addr:street":"Powell Dr",
    "iso:country":"CA",
    "sg:address":"64 Powell Dr",
    "sg:city":"Carbonear",
    "sg:classifiers":[
        {
            "category":"Autos & Motor Vehicles",
            "subcategory":"Auto Supplies",
            "type":"Retail Goods"
        }
    ],
    "sg:phone":"+1 709 596 3932",
    "sg:postcode":"A1Y 1A5",
    "sg:province":"NL",
    "sg:tags":[
        "repairing",
        "automobile",
        "parts"
    ],
    "wof:name":"Park Automotive Supplies Ltd",
    "wof:placetype":"venue"
},
  "geometry": {"coordinates":[-53.2310333252,47.7300872803],"type":"Point"}
}