{
  "type": "Feature",
  "properties": {
    "addr:full":"40 Water St Windsor NS B0N 2T0",
    "addr:housenumber":"40",
    "addr:postcode":"b0n 2t0",
    "addr:street":"Water St",
    "iso:country":"CA",
    "sg:address":"40 Water St",
    "sg:city":"Windsor",
    "sg:classifiers":[
        {
            "category":"Shopping",
            "subcategory":"Computers & Home Electronics",
            "type":"Retail Goods"
        }
    ],
    "sg:phone":"+1 902 798 2025",
    "sg:postcode":"B0N 2T0",
    "sg:province":"NS",
    "sg:tags":[
        "equipment",
        "satellite",
        "telephone",
        "cellular"
    ],
    "wof:name":"Sam's Cellular Svc",
    "wof:placetype":"venue"
},
  "geometry": {"coordinates":[-64.138992,44.994869],"type":"Point"}
}