{
  "type": "Feature",
  "properties": {
    "addr:full":"60 Rosebank Dr Miramichi NB E1V 5M5",
    "addr:housenumber":"60",
    "addr:postcode":"e1v 5m5",
    "addr:street":"Rosebank Dr",
    "iso:country":"CA",
    "sg:address":"60 Rosebank Dr",
    "sg:city":"Miramichi",
    "sg:classifiers":[
        {
            "category":"Shopping",
            "subcategory":"Bicycles & Sporting Goods",
            "type":"Retail Goods"
        }
    ],
    "sg:phone":"+1 506 622 5050",
    "sg:postcode":"E1V 5M5",
    "sg:province":"NB",
    "wof:name":"Eddy Out Depot",
    "wof:placetype":"venue"
},
  "geometry": {"coordinates":[-65.52600099999999,47.021297],"type":"Point"}
}