{
  "type": "Feature",
  "properties": {
    "iso:country":"CA",
    "sg:city":"Saskatoon",
    "sg:classifiers":[
        {
            "category":"Health Services",
            "subcategory":"Doctor",
            "type":"Services"
        }
    ],
    "sg:phone":"+1 306 374 1551",
    "sg:postcode":"S7H 5J6",
    "sg:province":"SK",
    "sg:tags":[
        "physician",
        "surgeon"
    ],
    "wof:name":"Matthews, Peter C MD",
    "wof:placetype":"venue"
},
  "geometry": {"coordinates":[-106.634819,52.115078],"type":"Point"}
}