{
  "type": "Feature",
  "properties": {
    "addr:full":"Calgary AB T1Y 5E2",
    "addr:postcode":"t1y 5e2",
    "iso:country":"CA",
    "sg:city":"Calgary",
    "sg:classifiers":[
        {
            "category":"Building & Trades",
            "subcategory":"Plumbing",
            "type":"Services"
        }
    ],
    "sg:phone":"+1 403 291 3072",
    "sg:postcode":"T1Y 5E2",
    "sg:province":"AB",
    "sg:tags":[
        "air",
        "conditioning",
        "contractor",
        "system",
        "heating"
    ],
    "wof:name":"Tar Sands Sheet Metal Ltd",
    "wof:placetype":"venue"
},
  "geometry": {"coordinates":[-113.994613648,51.0830841064],"type":"Point"}
}