{
  "type": "Feature",
  "properties": {
    "iso:country":"CA",
    "sg:city":"Woodstock",
    "sg:classifiers":[
        {
            "category":"Restaurant",
            "type":"Food & Drink"
        }
    ],
    "sg:phone":"+1 506 328 6004",
    "sg:postcode":"E7M 5G9",
    "sg:province":"NB",
    "wof:name":"Kfc",
    "wof:placetype":"venue"
},
  "geometry": {"coordinates":[-67.59875488279999,46.1689910889],"type":"Point"}
}