{
  "type": "Feature",
  "properties": {
    "iso:country":"CA",
    "sg:city":"North Bay",
    "sg:classifiers":[
        {
            "category":"Health Services",
            "subcategory":"Doctor",
            "type":"Services"
        }
    ],
    "sg:phone":"+1 705 472 4782",
    "sg:postcode":"P1B 4Y3",
    "sg:province":"ON",
    "sg:tags":[
        "physician",
        "surgeon"
    ],
    "wof:name":"Kesty, Kenneth R MD",
    "wof:placetype":"venue"
},
  "geometry": {"coordinates":[-79.4663925171,46.3265342712],"type":"Point"}
}