{
  "type": "Feature",
  "properties": {
    "addr:full":"45107 Wells Rd Chilliwack BC V2R 1H6",
    "addr:housenumber":"45107",
    "addr:postcode":"v2r 1h6",
    "addr:street":"Wells Rd",
    "iso:country":"CA",
    "sg:address":"45107 Wells Rd",
    "sg:city":"Chilliwack",
    "sg:classifiers":[
        {
            "category":"Food & Beverages",
            "subcategory":"Groceries & Convenience Stores",
            "type":"Retail Goods"
        }
    ],
    "sg:phone":"+1 604 858 3401",
    "sg:postcode":"V2R 1H6",
    "sg:province":"BC",
    "sg:tags":[
        "grocer"
    ],
    "wof:name":"Wells Road Grocery",
    "wof:placetype":"venue"
},
  "geometry": {"coordinates":[-121.977050781,49.1349105835],"type":"Point"}
}