{
  "type": "Feature",
  "properties": {
    "iso:country":"CA",
    "sg:address":"45107 Wells Rd",
    "sg:city":"Chilliwack",
    "sg:classifiers":[
        {
            "category":"Food & Beverages",
            "subcategory":"Groceries & Convenience Stores",
            "type":"Retail Goods"
        }
    ],
    "sg:phone":"+1 604 858 3401",
    "sg:postcode":"V2R 1H6",
    "sg:province":"BC",
    "sg:tags":[
        "grocer"
    ],
    "wof:name":"Wells Road Grocery",
    "wof:placetype":"venue"
},
  "geometry": {"coordinates":[-121.977050781,49.1349105835],"type":"Point"}
}