{
  "type": "Feature",
  "properties": {
    "iso:country":"CA",
    "sg:city":"Ignace",
    "sg:classifiers":[
        {
            "category":"Utilities",
            "subcategory":"Sewage",
            "type":"Services"
        }
    ],
    "sg:phone":"+1 807 934 6427",
    "sg:postcode":"P0T 1T0",
    "sg:province":"ON",
    "sg:tags":[
        "disposal",
        "system"
    ],
    "wof:name":"Northwest Sewage",
    "wof:placetype":"venue"
},
  "geometry": {"coordinates":[-91.6600570679,49.4174156189],"type":"Point"}
}