{
  "type": "Feature",
  "properties": {
    "iso:country":"CA",
    "sg:address":"5350 Rue Sherbrooke E",
    "sg:city":"Montreal",
    "sg:classifiers":[
        {
            "category":"Restaurant",
            "type":"Food & Drink"
        }
    ],
    "sg:phone":"+1 514 255 6060",
    "sg:postcode":"H1V 1A1",
    "sg:province":"QC",
    "sg:tags":[
        "chicken",
        "dinner"
    ],
    "wof:name":"Score Rotisserie",
    "wof:placetype":"venue"
},
  "geometry": {"coordinates":[-73.551574707,45.5691642761],"type":"Point"}
}