{
  "type": "Feature",
  "properties": {
    "addr:full":"691 the Kingsway Peterborough ON K9J 6W5",
    "addr:housenumber":"691",
    "addr:postcode":"k9j 6w5",
    "addr:street":"The Kingsway",
    "iso:country":"CA",
    "sg:address":"691 the Kingsway",
    "sg:city":"Peterborough",
    "sg:classifiers":[
        {
            "category":"Building & Trades",
            "subcategory":"Cleaning & Sanitation",
            "type":"Services"
        }
    ],
    "sg:phone":"+1 705 743 7200",
    "sg:postcode":"K9J 6W5",
    "sg:province":"ON",
    "sg:tags":[
        "window"
    ],
    "wof:name":"Blue Diamond Window Cleaning",
    "wof:placetype":"venue"
},
  "geometry": {"coordinates":[-78.340309,44.277054],"type":"Point"}
}