{
  "type": "Feature",
  "properties": {
    "addr:full":"903 Giffard St Whitby ON L1N 2S3",
    "addr:housenumber":"903",
    "addr:postcode":"l1n 2s3",
    "addr:street":"Giffard St",
    "iso:country":"CA",
    "sg:address":"903 Giffard St",
    "sg:city":"Whitby",
    "sg:classifiers":[
        {
            "category":"Organizations",
            "subcategory":"Religious Organization",
            "type":"Services"
        }
    ],
    "sg:phone":"+1 905 668 3676",
    "sg:postcode":"L1N 2S3",
    "sg:province":"ON",
    "sg:tags":[
        "church"
    ],
    "wof:name":"St John Evangelist Rc Church",
    "wof:placetype":"venue"
},
  "geometry": {"coordinates":[-78.952721,43.879364],"type":"Point"}
}