{
  "type": "Feature",
  "properties": {
    "addr:full":"141 Kay Cres Winnipeg MB R2Y 1L1",
    "addr:housenumber":"141",
    "addr:postcode":"r2y 1l1",
    "addr:street":"Kay Cres",
    "iso:country":"CA",
    "sg:address":"141 Kay Cres",
    "sg:city":"Winnipeg",
    "sg:classifiers":[
        {
            "category":"Wholesale",
            "subcategory":"Non-durable Goods",
            "type":"Manufacturing & Wholesale Goods"
        }
    ],
    "sg:phone":"+1 204 897 2149",
    "sg:postcode":"R2Y 1L1",
    "sg:province":"MB",
    "sg:tags":[
        "advertising"
    ],
    "wof:name":"Armadillo Productions",
    "wof:placetype":"venue"
},
  "geometry": {"coordinates":[-97.3104476929,49.8924942017],"type":"Point"}
}