{
  "type": "Feature",
  "properties": {
    "addr:full":"124 Queensway Dr Moncton NB E1G 2L2",
    "addr:housenumber":"124",
    "addr:postcode":"e1g 2l2",
    "addr:street":"Queensway Dr",
    "iso:country":"CA",
    "sg:address":"124 Queensway Dr",
    "sg:city":"Moncton",
    "sg:classifiers":[
        {
            "category":"Shopping",
            "subcategory":"Hobbies, Toys, & Games",
            "type":"Retail Goods"
        }
    ],
    "sg:phone":"+1 506 384 1206",
    "sg:postcode":"E1G 2L2",
    "sg:province":"NB",
    "sg:tags":[
        "craft",
        "supply"
    ],
    "wof:name":"Cozy Corner Craft",
    "wof:placetype":"venue"
},
  "geometry": {"coordinates":[-64.8275756836,46.1313476562],"type":"Point"}
}