{
  "type": "Feature",
  "properties": {
    "addr:full":"620 Rue Notre-Dame O Victoriaville QC G6P 1T1",
    "addr:housenumber":"620",
    "addr:postcode":"g6p 1t1",
    "addr:street":"Rue Notre-Dame O",
    "iso:country":"CA",
    "sg:address":"620 Rue Notre-Dame O",
    "sg:city":"Victoriaville",
    "sg:classifiers":[
        {
            "category":"Restaurant",
            "type":"Food & Drink"
        }
    ],
    "sg:phone":"+1 819 758 3666",
    "sg:postcode":"G6P 1T1",
    "sg:province":"QC",
    "wof:name":"Kfc",
    "wof:placetype":"venue"
},
  "geometry": {"coordinates":[-71.9428482056,46.0627975464],"type":"Point"}
}