{
  "type": "Feature",
  "properties": {
    "addr:full":"London ON N6E 1P9",
    "addr:postcode":"n6e 1p9",
    "iso:country":"CA",
    "sg:city":"London",
    "sg:classifiers":[
        {
            "category":"Wholesale",
            "subcategory":"Machinery & Supplies",
            "type":"Manufacturing & Wholesale Goods"
        }
    ],
    "sg:phone":"+1 519 681 5640",
    "sg:postcode":"N6E 1P9",
    "sg:province":"ON",
    "sg:tags":[
        "automobile",
        "parts",
        "cleaning"
    ],
    "wof:name":"Monarch Rebuilding",
    "wof:placetype":"venue"
},
  "geometry": {"coordinates":[-81.211624,42.931019],"type":"Point"}
}