{
  "type": "Feature",
  "properties": {
    "iso:country":"CA",
    "sg:address":"PO Box 608",
    "sg:city":"Wembley",
    "sg:classifiers":[
        {
            "category":"Retail",
            "subcategory":"Repair Shop",
            "type":"Services"
        }
    ],
    "sg:phone":"+1 780 766 3315",
    "sg:postcode":"T0H 3S0",
    "sg:province":"AB",
    "sg:tags":[
        "welding"
    ],
    "wof:name":"Tonto's Portable Welding Ltd",
    "wof:placetype":"venue"
},
  "geometry": {"coordinates":[-119.139198303,55.1647949219],"type":"Point"}
}