{
  "type": "Feature",
  "properties": {
    "addr:full":"200 Glen Park Dr Gloucester ON K1B 5A3",
    "addr:housenumber":"200",
    "addr:postcode":"k1b 5a3",
    "addr:street":"Glen Park Dr",
    "iso:country":"CA",
    "sg:address":"200 Glen Park Dr",
    "sg:city":"Gloucester",
    "sg:classifiers":[
        {
            "category":"Arena",
            "subcategory":"Sports Club",
            "type":"Entertainment"
        }
    ],
    "sg:phone":"+1 613 824 5197",
    "sg:postcode":"K1B 5A3",
    "sg:province":"ON",
    "sg:tags":[
        "athletic",
        "fields",
        "stadium",
        "government"
    ],
    "wof:name":"Blackburn Hamlet Arena",
    "wof:placetype":"venue"
},
  "geometry": {"coordinates":[-75.56405639650001,45.4301147461],"type":"Point"}
}