{
  "type": "Feature",
  "properties": {
    "addr:full":"2 Avenue D Willow Bunch SK S0H 4K0",
    "addr:housenumber":"2",
    "addr:postcode":"s0h 4k0",
    "addr:street":"Avenue D",
    "iso:country":"CA",
    "sg:address":"2 Avenue D",
    "sg:city":"Willow Bunch",
    "sg:classifiers":[
        {
            "category":"Farming",
            "subcategory":"Nursery",
            "type":"Manufacturing & Wholesale Goods"
        }
    ],
    "sg:phone":"+1 306 473 2737",
    "sg:postcode":"S0H 4K0",
    "sg:province":"SK",
    "sg:tags":[
        "greenhouse"
    ],
    "wof:name":"Willow Bunch Greenhouse",
    "wof:placetype":"venue"
},
  "geometry": {"coordinates":[-105.638268,49.391815],"type":"Point"}
}