{
  "type": "Feature",
  "properties": {
    "addr:full":"Vancouver BC V5Z 1K3",
    "addr:postcode":"v5z 1k3",
    "iso:country":"CA",
    "sg:city":"Vancouver",
    "sg:classifiers":[
        {
            "category":"Personal",
            "type":"Services"
        }
    ],
    "sg:phone":"+1 604 730 1744",
    "sg:postcode":"V5Z 1K3",
    "sg:province":"BC",
    "sg:tags":[
        "hair",
        "replacement"
    ],
    "wof:name":"Micron Laboratories",
    "wof:placetype":"venue"
},
  "geometry": {"coordinates":[-123.125862122,49.2635345459],"type":"Point"}
}