{
  "type": "Feature",
  "properties": {
    "addr:full":"695 Bath Rd Kingston ON K7M 4X1",
    "addr:housenumber":"695",
    "addr:postcode":"k7m 4x1",
    "addr:street":"Bath Rd",
    "iso:country":"CA",
    "sg:address":"695 Bath Rd",
    "sg:city":"Kingston",
    "sg:classifiers":[
        {
            "category":"Farming",
            "subcategory":"Dairy Farm",
            "type":"Manufacturing & Wholesale Goods"
        }
    ],
    "sg:phone":"+1 613 389 8762",
    "sg:postcode":"K7M 4X1",
    "sg:province":"ON",
    "wof:name":"Reid's Dairy",
    "wof:placetype":"venue"
},
  "geometry": {"coordinates":[-76.541053772,44.2384262085],"type":"Point"}
}