{
  "type": "Feature",
  "properties": {
    "addr:full":"4035 Boul DE LA Rive-Sud Levis QC G6W 6M9",
    "addr:housenumber":"4035",
    "addr:postcode":"g6w 6m9",
    "addr:street":"Boul De La Rive-Sud",
    "iso:country":"CA",
    "sg:address":"4035 Boul DE LA Rive-Sud",
    "sg:city":"Levis",
    "sg:classifiers":[
        {
            "category":"Autos & Motor Vehicles",
            "subcategory":"Automobile Sales",
            "type":"Retail Goods"
        }
    ],
    "sg:phone":"+1 418 838 9897",
    "sg:postcode":"G6W 6M9",
    "sg:province":"QC",
    "sg:tags":[
        "car",
        "dealer"
    ],
    "wof:name":"Norm Auto Enr",
    "wof:placetype":"venue"
},
  "geometry": {"coordinates":[-71.19637299999999,46.775795],"type":"Point"}
}