{
  "type": "Feature",
  "properties": {
    "addr:full":"Austin MB R0H 0C0",
    "addr:postcode":"r0h 0c0",
    "iso:country":"CA",
    "sg:city":"Austin",
    "sg:classifiers":[
        {
            "category":"Farming",
            "subcategory":"Farm",
            "type":"Manufacturing & Wholesale Goods"
        }
    ],
    "sg:phone":"+1 204 385 2988",
    "sg:postcode":"R0H 0C0",
    "sg:province":"MB",
    "wof:name":"Delta Colony Farms Ltd",
    "wof:placetype":"venue"
},
  "geometry": {"coordinates":[-98.9363479614,49.9503746033],"type":"Point"}
}