{
  "type": "Feature",
  "properties": {
    "addr:full":"2500 Hurontario St Mississauga ON L5B 1N4",
    "addr:housenumber":"2500",
    "addr:postcode":"l5b 1n4",
    "addr:street":"Hurontario St",
    "iso:country":"CA",
    "sg:address":"2500 Hurontario St",
    "sg:city":"Mississauga",
    "sg:classifiers":[
        {
            "category":"Food & Beverages",
            "subcategory":"Groceries & Convenience Stores",
            "type":"Retail Goods"
        }
    ],
    "sg:phone":"+1 905 270 6823",
    "sg:postcode":"L5B 1N4",
    "sg:province":"ON",
    "sg:tags":[
        "grocer"
    ],
    "wof:name":"Price Chopper",
    "wof:placetype":"venue"
},
  "geometry": {"coordinates":[-79.614029,43.578384],"type":"Point"}
}