{
  "type": "Feature",
  "properties": {
    "iso:country":"CA",
    "sg:address":"100 West St",
    "sg:city":"Brampton",
    "sg:classifiers":[
        {
            "category":"Organizations",
            "subcategory":"Labor Organization",
            "type":"Services"
        }
    ],
    "sg:phone":"+1 905 874 0767",
    "sg:postcode":"L6X 1W2",
    "sg:province":"ON",
    "wof:name":"Aluminium Brick & Glass Wrkrs",
    "wof:placetype":"venue"
},
  "geometry": {"coordinates":[-79.7682189941,43.6847305298],"type":"Point"}
}