{
  "type": "Feature",
  "properties": {
    "addr:full":"79 Bywood Dr Etobicoke ON M9A 1M2",
    "addr:housenumber":"79",
    "addr:postcode":"m9a 1m2",
    "addr:street":"Bywood Dr",
    "iso:country":"CA",
    "sg:address":"79 Bywood Dr",
    "sg:city":"Etobicoke",
    "sg:classifiers":[
        {
            "category":"Professional",
            "subcategory":"Engineering",
            "type":"Services"
        }
    ],
    "sg:phone":"+1 416 239 0821",
    "sg:postcode":"M9A 1M2",
    "sg:province":"ON",
    "sg:tags":[
        "engineer"
    ],
    "wof:name":"Majm Corp Ltd",
    "wof:placetype":"venue"
},
  "geometry": {"coordinates":[-79.540848,43.65667],"type":"Point"}
}