{
  "type": "Feature",
  "properties": {
    "addr:full":"575 Rue Sainte-Rose LA Prairie QC J5R 1Z2",
    "addr:housenumber":"575",
    "addr:postcode":"j5r 1z2",
    "addr:street":"Rue Sainte-Rose",
    "iso:country":"CA",
    "sg:address":"575 Rue Sainte-Rose",
    "sg:city":"LA Prairie",
    "sg:classifiers":[
        {
            "category":"Retail",
            "subcategory":"Auto Repair",
            "type":"Services"
        }
    ],
    "sg:phone":"+1 450 444 3126",
    "sg:postcode":"J5R 1Z2",
    "sg:province":"QC",
    "sg:tags":[
        "body",
        "automobile",
        "painting"
    ],
    "wof:name":"Carrosserie Lepine Enrg",
    "wof:placetype":"venue"
},
  "geometry": {"coordinates":[-73.49086,45.41124],"type":"Point"}
}