{
  "type": "Feature",
  "properties": {
    "addr:full":"7712 Kent Blvd Brockville ON K6V 7H6",
    "addr:housenumber":"7712",
    "addr:postcode":"k6v 7h6",
    "addr:street":"Kent Blvd",
    "iso:country":"CA",
    "sg:address":"7712 Kent Blvd",
    "sg:city":"Brockville",
    "sg:classifiers":[
        {
            "category":"Shopping",
            "subcategory":"Musical Instruments",
            "type":"Retail Goods"
        }
    ],
    "sg:phone":"+1 613 342 7377",
    "sg:postcode":"K6V 7H6",
    "sg:province":"ON",
    "sg:tags":[
        "music",
        "dealer"
    ],
    "wof:name":"Mr C's Gift of Music",
    "wof:placetype":"venue"
},
  "geometry": {"coordinates":[-75.7066268921,44.5994682312],"type":"Point"}
}