{
  "type": "Feature",
  "properties": {
    "addr:full":"1900 Main St Vancouver BC V5T 3B9",
    "addr:housenumber":"1900",
    "addr:postcode":"v5t 3b9",
    "addr:street":"Main St",
    "iso:country":"CA",
    "sg:address":"1900 Main St",
    "sg:city":"Vancouver",
    "sg:classifiers":[
        {
            "category":"Retail",
            "subcategory":"Auto Repair",
            "type":"Services"
        }
    ],
    "sg:phone":"+1 604 873 3358",
    "sg:postcode":"V5T 3B9",
    "sg:province":"BC",
    "sg:tags":[
        "body",
        "automobile",
        "painting"
    ],
    "wof:name":"Craftsman Collision",
    "wof:placetype":"venue"
},
  "geometry": {"coordinates":[-123.100646973,49.2681312561],"type":"Point"}
}