{
  "type": "Feature",
  "properties": {
    "iso:country":"CA",
    "sg:address":"181 Place D'Youville",
    "sg:city":"Montreal",
    "sg:classifiers":[
        {
            "category":"Building & Trades",
            "subcategory":"Construction",
            "type":"Services"
        }
    ],
    "sg:phone":"+1 514 286 1409",
    "sg:postcode":"H2Y 2B2",
    "sg:province":"QC",
    "sg:tags":[
        "designer"
    ],
    "wof:name":"Hippo Design Inc",
    "wof:placetype":"venue"
},
  "geometry": {"coordinates":[-73.643867,45.547421],"type":"Point"}
}