{
  "type": "Feature",
  "properties": {
    "addr:full":"25 Southampton Pky Sauble Beach ON N0H 2G0",
    "addr:housenumber":"25",
    "addr:postcode":"n0h 2g0",
    "addr:street":"Southampton Pky",
    "iso:country":"CA",
    "sg:address":"25 Southampton Pky",
    "sg:city":"Sauble Beach",
    "sg:classifiers":[
        {
            "category":"Organizations",
            "subcategory":"Religious Organization",
            "type":"Services"
        }
    ],
    "sg:phone":"+1 519 422 1437",
    "sg:postcode":"N0H 2G0",
    "sg:province":"ON",
    "sg:tags":[
        "church"
    ],
    "wof:name":"Sauble Christian Fellowship",
    "wof:placetype":"venue"
},
  "geometry": {"coordinates":[-81.2646865845,44.6272583008],"type":"Point"}
}