{
  "type": "Feature",
  "properties": {
    "addr:full":"1972 Sturgeon Rd Dunsford ON K0M 1L0",
    "addr:housenumber":"1972",
    "addr:postcode":"k0m 1l0",
    "addr:street":"Sturgeon Rd",
    "iso:country":"CA",
    "sg:address":"1972 Sturgeon Rd",
    "sg:city":"Dunsford",
    "sg:classifiers":[
        {
            "category":"Food & Beverages",
            "subcategory":"Groceries & Convenience Stores",
            "type":"Retail Goods"
        }
    ],
    "sg:phone":"+1 705 793 1059",
    "sg:postcode":"K0M 1L0",
    "sg:province":"ON",
    "wof:name":"Mum's Mini Mart",
    "wof:placetype":"venue"
},
  "geometry": {"coordinates":[-78.642365,44.452061],"type":"Point"}
}