{
  "type": "Feature",
  "properties": {
    "addr:full":"Sainte-Melanie QC J0K 3A0",
    "addr:postcode":"j0k 3a0",
    "iso:country":"CA",
    "sg:city":"Sainte-Melanie",
    "sg:classifiers":[
        {
            "category":"Freight",
            "type":"Transportation"
        }
    ],
    "sg:phone":"+1 450 889 2196",
    "sg:postcode":"J0K 3A0",
    "sg:province":"QC",
    "sg:tags":[
        "trucking"
    ],
    "wof:name":"Transport & Laplante & Gilbert",
    "wof:placetype":"venue"
},
  "geometry": {"coordinates":[-73.51638,46.132809],"type":"Point"}
}