{
  "type": "Feature",
  "properties": {
    "addr:full":"1220 100th St Tisdale SK S0E 1T0",
    "addr:housenumber":"1220",
    "addr:postcode":"s0e 1t0",
    "addr:street":"100Th St",
    "iso:country":"CA",
    "sg:address":"1220 100th St",
    "sg:city":"Tisdale",
    "sg:classifiers":[
        {
            "category":"Retail",
            "subcategory":"Auto Repair",
            "type":"Services"
        }
    ],
    "sg:phone":"+1 306 873 5885",
    "sg:postcode":"S0E 1T0",
    "sg:province":"SK",
    "sg:tags":[
        "repairing",
        "automobile"
    ],
    "wof:name":"Tisdale Lube Svc",
    "wof:placetype":"venue"
},
  "geometry": {"coordinates":[-104.04505899999999,52.857021],"type":"Point"}
}