{
  "type": "Feature",
  "properties": {
    "addr:full":"7823 34 St NW Edmonton AB T6B 2V5",
    "addr:housenumber":"7823",
    "addr:postcode":"t6b 2v5",
    "addr:street":"34 St Nw",
    "iso:country":"CA",
    "sg:address":"7823 34 St NW",
    "sg:city":"Edmonton",
    "sg:classifiers":[
        {
            "category":"Freight",
            "type":"Transportation"
        }
    ],
    "sg:phone":"+1 780 465 0341",
    "sg:postcode":"T6B 2V5",
    "sg:province":"AB",
    "sg:tags":[
        "field",
        "oil"
    ],
    "wof:name":"Northern Industrial Carriers",
    "wof:placetype":"venue"
},
  "geometry": {"coordinates":[-113.39363899999999,53.514381],"type":"Point"}
}