{
  "type": "Feature",
  "properties": {
    "addr:full":"16 Strathearn Rd York ON M6C 1R3",
    "addr:housenumber":"16",
    "addr:postcode":"m6c 1r3",
    "addr:street":"Strathearn Rd",
    "iso:country":"CA",
    "sg:address":"16 Strathearn Rd",
    "sg:city":"York",
    "sg:classifiers":[
        {
            "category":"Education",
            "subcategory":"Special Training",
            "type":"Public Place"
        }
    ],
    "sg:phone":"+1 416 787 5555",
    "sg:postcode":"M6C 1R3",
    "sg:province":"ON",
    "sg:tags":[
        "management"
    ],
    "wof:name":"Coaching Clinic",
    "wof:placetype":"venue"
},
  "geometry": {"coordinates":[-79.423500061,43.6922798157],"type":"Point"}
}