{
  "type": "Feature",
  "properties": {
    "iso:country":"CA",
    "sg:address":"8781 Dale Rd # D",
    "sg:city":"Cobourg",
    "sg:classifiers":[
        {
            "category":"Building & Trades",
            "subcategory":"Plumbing",
            "type":"Services"
        }
    ],
    "sg:phone":"+1 905 377 0860",
    "sg:postcode":"K9A 4J7",
    "sg:province":"ON",
    "sg:tags":[
        "sheet",
        "work",
        "metal",
        "contractor"
    ],
    "wof:name":"C & K Fabrication",
    "wof:placetype":"venue"
},
  "geometry": {"coordinates":[-78.1677780151,43.9596061707],"type":"Point"}
}