{
  "type": "Feature",
  "properties": {
    "addr:full":"10 Parkside Dr St Jacobs ON N0B 2N0",
    "addr:housenumber":"10",
    "addr:postcode":"n0b 2n0",
    "addr:street":"Parkside Dr St",
    "iso:country":"CA",
    "sg:address":"10 Parkside Dr",
    "sg:city":"St Jacobs",
    "sg:classifiers":[
        {
            "category":"Health Services",
            "subcategory":"Doctor",
            "type":"Services"
        }
    ],
    "sg:phone":"+1 519 664 3794",
    "sg:postcode":"N0B 2N0",
    "sg:province":"ON",
    "sg:tags":[
        "physician",
        "surgeon"
    ],
    "wof:name":"Woolwich Community Health Ctr",
    "wof:placetype":"venue"
},
  "geometry": {"coordinates":[-80.5511550903,43.5440444946],"type":"Point"}
}