{
  "type": "Feature",
  "properties": {
    "addr:full":"10551 97 St NW Edmonton AB T5H 2L4",
    "addr:housenumber":"10551",
    "addr:postcode":"t5h 2l4",
    "addr:street":"97 St Nw",
    "iso:country":"CA",
    "sg:address":"10551 97 St NW",
    "sg:city":"Edmonton",
    "sg:classifiers":[
        {
            "category":"Personal",
            "subcategory":"Beauty Salon",
            "type":"Services"
        }
    ],
    "sg:phone":"+1 780 428 2668",
    "sg:postcode":"T5H 2L4",
    "sg:province":"AB",
    "wof:name":"Silvias Beauty Salon",
    "wof:placetype":"venue"
},
  "geometry": {"coordinates":[-113.488273621,53.5495834351],"type":"Point"}
}