{
  "type": "Feature",
  "properties": {
    "addr:full":"995 1E Rue Val-D'Or QC J9P 4E3",
    "addr:housenumber":"995",
    "addr:postcode":"j9p 4e3",
    "addr:street":"1E Rue",
    "iso:country":"CA",
    "sg:address":"995 1E Rue",
    "sg:city":"Val-D'Or",
    "sg:classifiers":[
        {
            "category":"Health Services",
            "subcategory":"Nursing And Care Facility",
            "type":"Services"
        }
    ],
    "sg:phone":"+1 819 825 3444",
    "sg:postcode":"J9P 4E3",
    "sg:province":"QC",
    "sg:tags":[
        "home",
        "retirement",
        "community"
    ],
    "wof:name":"Residence Au Coeur Du Rayon",
    "wof:placetype":"venue"
},
  "geometry": {"coordinates":[-71.667526,48.701248],"type":"Point"}
}