{
  "type": "Feature",
  "properties": {
    "addr:full":"1724 Queen St W Toronto ON M6R 1B3",
    "addr:housenumber":"1724",
    "addr:postcode":"m6r 1b3",
    "addr:street":"Queen St W",
    "iso:country":"CA",
    "sg:address":"1724 Queen St W",
    "sg:city":"Toronto",
    "sg:classifiers":[
        {
            "category":"Health Services",
            "subcategory":"Doctor",
            "type":"Services"
        }
    ],
    "sg:phone":"+1 416 532 7777",
    "sg:postcode":"M6R 1B3",
    "sg:province":"ON",
    "sg:tags":[
        "physician",
        "surgeon"
    ],
    "wof:name":"Dekany, Paul C MD",
    "wof:placetype":"venue"
},
  "geometry": {"coordinates":[-79.4458694458,43.6387939453],"type":"Point"}
}