{
  "type": "Feature",
  "properties": {
    "addr:full":"6985 Ch Des Sources Lachute QC J8H 2C5",
    "addr:housenumber":"6985",
    "addr:postcode":"j8h 2c5",
    "addr:street":"Ch Des Sources",
    "iso:country":"CA",
    "sg:address":"6985 Ch Des Sources",
    "sg:city":"Lachute",
    "sg:classifiers":[
        {
            "category":"Utilities",
            "subcategory":"Refuse",
            "type":"Services"
        }
    ],
    "sg:phone":"+1 450 562 7231",
    "sg:postcode":"J8H 2C5",
    "sg:province":"QC",
    "sg:tags":[
        "landfill"
    ],
    "wof:name":"Regie Intermunicipale Argntl",
    "wof:placetype":"venue"
},
  "geometry": {"coordinates":[-74.25170135499999,45.6060218811],"type":"Point"}
}