{
  "type": "Feature",
  "properties": {
    "iso:country":"CA",
    "sg:city":"Charlesbourg",
    "sg:classifiers":[
        {
            "category":"Personal",
            "subcategory":"Beauty Salon",
            "type":"Services"
        }
    ],
    "sg:phone":"+1 418 623 3334",
    "sg:postcode":"G1G 3Y6",
    "sg:province":"QC",
    "wof:name":"Salon Aquarelle Coiffure",
    "wof:placetype":"venue"
},
  "geometry": {"coordinates":[-71.2838592529,46.8773078918],"type":"Point"}
}