{
  "type": "Feature",
  "properties": {
    "iso:country":"CA",
    "sg:address":"80 Costa Rd",
    "sg:city":"Concord",
    "sg:classifiers":[
        {
            "category":"Manufacturing",
            "subcategory":"Tools & Machinery",
            "type":"Manufacturing & Wholesale Goods"
        }
    ],
    "sg:phone":"+1 905 738 6994",
    "sg:postcode":"L4K 1N2",
    "sg:province":"ON",
    "sg:tags":[
        "machine",
        "shop"
    ],
    "wof:name":"Satellite Welding & Machining",
    "wof:placetype":"venue"
},
  "geometry": {"coordinates":[-79.51467132569999,43.7946281433],"type":"Point"}
}