{
  "type": "Feature",
  "properties": {
    "iso:country":"CA",
    "sg:address":"91 Lakeshore Rd E",
    "sg:city":"Mississauga",
    "sg:classifiers":[
        {
            "category":"Restaurant",
            "type":"Food & Drink"
        }
    ],
    "sg:phone":"+1 905 891 8747",
    "sg:postcode":"L5G 1E2",
    "sg:province":"ON",
    "sg:tags":[
        "shop",
        "coffee"
    ],
    "wof:name":"Second Cup",
    "wof:placetype":"venue"
},
  "geometry": {"coordinates":[-79.58390808110001,43.5530891418],"type":"Point"}
}