{
  "type": "Feature",
  "properties": {
    "addr:full":"291 Rue Du Pont Quebec QC G1K 6L8",
    "addr:housenumber":"291",
    "addr:postcode":"g1k 6l8",
    "addr:street":"Rue Du Pont",
    "iso:country":"CA",
    "sg:address":"291 Rue Du Pont",
    "sg:city":"Quebec",
    "sg:classifiers":[
        {
            "category":"Arts & Performance",
            "subcategory":"Theater",
            "type":"Entertainment"
        }
    ],
    "sg:phone":"+1 418 524 3401",
    "sg:postcode":"G1K 6L8",
    "sg:province":"QC",
    "sg:tags":[
        "bureau"
    ],
    "wof:name":"Centre Des Danseuses Nues",
    "wof:placetype":"venue"
},
  "geometry": {"coordinates":[-71.221786499,46.8171577454],"type":"Point"}
}