{
  "type": "Feature",
  "properties": {
    "addr:full":"223 Ch Cyr New Richmond QC G0C 2B0",
    "addr:housenumber":"223",
    "addr:postcode":"g0c 2b0",
    "addr:street":"Ch Cyr",
    "iso:country":"CA",
    "sg:address":"223 Ch Cyr",
    "sg:city":"New Richmond",
    "sg:classifiers":[
        {
            "category":"Retail",
            "subcategory":"Auto Rental",
            "type":"Services"
        }
    ],
    "sg:phone":"+1 418 392 6737",
    "sg:postcode":"G0C 2B0",
    "sg:province":"QC",
    "sg:tags":[
        "renting",
        "truck",
        "leasing"
    ],
    "wof:name":"U-Haul CO Ltd",
    "wof:placetype":"venue"
},
  "geometry": {"coordinates":[-65.849564,48.173344],"type":"Point"}
}