{
  "type": "Feature",
  "properties": {
    "iso:country":"CA",
    "sg:address":"541 Granville St",
    "sg:city":"Vancouver",
    "sg:classifiers":[
        {
            "category":"Restaurant",
            "type":"Food & Drink"
        }
    ],
    "sg:phone":"+1 604 609 4450",
    "sg:postcode":"V6C 1X6",
    "sg:province":"BC",
    "wof:name":"Subway Sandwiches & Salads",
    "wof:placetype":"venue"
},
  "geometry": {"coordinates":[-123.11555481000001,49.2843132019],"type":"Point"}
}