{
  "type": "Feature",
  "properties": {
    "addr:full":"490 Dundas St E Waterdown ON L0R 2H1",
    "addr:housenumber":"490",
    "addr:postcode":"l0r 2h1",
    "addr:street":"Dundas St E",
    "iso:country":"CA",
    "sg:address":"490 Dundas St E",
    "sg:city":"Waterdown",
    "sg:classifiers":[
        {
            "category":"Utilities",
            "subcategory":"Fuel Oil & Lpg",
            "type":"Services"
        }
    ],
    "sg:phone":"+1 905 689 5155",
    "sg:postcode":"L0R 2H1",
    "sg:province":"ON",
    "sg:tags":[
        "propane",
        "gas"
    ],
    "wof:name":"Waterdown Gas Bar & Propane",
    "wof:placetype":"venue"
},
  "geometry": {"coordinates":[-79.87809753419999,43.3447952271],"type":"Point"}
}