{
  "type": "Feature",
  "properties": {
    "addr:full":"25 Rue Poulin Adstock QC G0N 1S0",
    "addr:housenumber":"25",
    "addr:postcode":"g0n 1s0",
    "addr:street":"Rue Poulin",
    "iso:country":"CA",
    "sg:address":"25 Rue Poulin",
    "sg:city":"Adstock",
    "sg:classifiers":[
        {
            "category":"Bus Charters",
            "type":"Transportation"
        }
    ],
    "sg:phone":"+1 418 422 2174",
    "sg:postcode":"G0N 1S0",
    "sg:province":"QC",
    "sg:tags":[
        "rental"
    ],
    "wof:name":"Plante, Marcel",
    "wof:placetype":"venue"
},
  "geometry": {"coordinates":[-71.074493,46.046906],"type":"Point"}
}