{
  "type": "Feature",
  "properties": {
    "iso:country":"CA",
    "sg:address":"2491 Lake Shore Blvd W",
    "sg:city":"Etobicoke",
    "sg:classifiers":[
        {
            "category":"Cinema",
            "subcategory":"Movie Rental",
            "type":"Entertainment"
        }
    ],
    "sg:phone":"+1 416 252 6600",
    "sg:postcode":"M8V 1C5",
    "sg:province":"ON",
    "sg:tags":[
        "leasing",
        "video",
        "disc",
        "tape"
    ],
    "wof:name":"Video Deal",
    "wof:placetype":"venue"
},
  "geometry": {"coordinates":[-79.48960876460001,43.612827301],"type":"Point"}
}