{
  "type": "Feature",
  "properties": {
    "addr:full":"200 Golf Course Rd Pembroke ON K8A 7B3",
    "addr:housenumber":"200",
    "addr:postcode":"k8a 7b3",
    "addr:street":"Golf Course Rd",
    "iso:country":"CA",
    "sg:address":"200 Golf Course Rd",
    "sg:city":"Pembroke",
    "sg:classifiers":[
        {
            "category":"Building & Trades",
            "subcategory":"Plumbing",
            "type":"Services"
        }
    ],
    "sg:phone":"+1 613 735 4446",
    "sg:postcode":"K8A 7B3",
    "sg:province":"ON",
    "sg:tags":[
        "heating",
        "contractor"
    ],
    "wof:name":"Oakridge Plumbing Heating",
    "wof:placetype":"venue"
},
  "geometry": {"coordinates":[-77.112213,45.826481],"type":"Point"}
}