{
  "type": "Feature",
  "properties": {
    "addr:full":"30 Mahonee Dr Winnipeg MB R2G 3S2",
    "addr:housenumber":"30",
    "addr:postcode":"r2g 3s2",
    "addr:street":"Mahonee Dr",
    "iso:country":"CA",
    "sg:address":"30 Mahonee Dr",
    "sg:city":"Winnipeg",
    "sg:classifiers":[
        {
            "category":"Building & Trades",
            "subcategory":"Construction",
            "type":"Services"
        }
    ],
    "sg:phone":"+1 204 668 4374",
    "sg:postcode":"R2G 3S2",
    "sg:province":"MB",
    "sg:tags":[
        "painter"
    ],
    "wof:name":"Atlas Painting Ltd",
    "wof:placetype":"venue"
},
  "geometry": {"coordinates":[-97.056602478,49.9300498962],"type":"Point"}
}