{
  "type": "Feature",
  "properties": {
    "addr:full":"6359 Rue Jean-Talon E Saint-Leonard QC H1S 3E7",
    "addr:housenumber":"6359",
    "addr:postcode":"h1s 3e7",
    "addr:street":"Rue Jean-Talon E",
    "iso:country":"CA",
    "sg:address":"6359 Rue Jean-Talon E",
    "sg:city":"Saint-Leonard",
    "sg:classifiers":[
        {
            "category":"Health Services",
            "subcategory":"Doctor",
            "type":"Services"
        }
    ],
    "sg:phone":"+1 514 254 5212",
    "sg:postcode":"H1S 3E7",
    "sg:province":"QC",
    "sg:tags":[
        "dentist"
    ],
    "wof:name":"Clinique D'Anesthesie Dentaire",
    "wof:placetype":"venue"
},
  "geometry": {"coordinates":[-73.57608,45.591156],"type":"Point"}
}