{
  "type": "Feature",
  "properties": {
    "addr:full":"850 Ch Olivier Saint-Nicolas QC G7A 2N1",
    "addr:housenumber":"850",
    "addr:postcode":"g7a 2n1",
    "addr:street":"Ch Olivier",
    "iso:country":"CA",
    "sg:address":"850 Ch Olivier",
    "sg:city":"Saint-Nicolas",
    "sg:classifiers":[
        {
            "category":"Retail",
            "subcategory":"Auto Repair",
            "type":"Services"
        }
    ],
    "sg:phone":"+1 418 831 2046",
    "sg:postcode":"G7A 2N1",
    "sg:province":"QC",
    "sg:tags":[
        "bus"
    ],
    "wof:name":"Prevost Car Inc",
    "wof:placetype":"venue"
},
  "geometry": {"coordinates":[-71.315186,46.691231],"type":"Point"}
}