{
  "type": "Feature",
  "properties": {
    "addr:full":"Calgary AB T2S 0J2",
    "addr:postcode":"t2s 0j2",
    "iso:country":"CA",
    "sg:city":"Calgary",
    "sg:classifiers":[
        {
            "category":"Health Services",
            "subcategory":"Doctor",
            "type":"Services"
        }
    ],
    "sg:phone":"+1 403 228 6899",
    "sg:postcode":"T2S 0J2",
    "sg:province":"AB",
    "sg:tags":[
        "physician",
        "surgeon"
    ],
    "wof:name":"Gladman, Donald J MD",
    "wof:placetype":"venue"
},
  "geometry": {"coordinates":[-114.06960296600001,51.0325469971],"type":"Point"}
}