{
  "type": "Feature",
  "properties": {
    "addr:full":"1 Thomson Crt Markham ON L3P 1M5",
    "addr:housenumber":"1",
    "addr:postcode":"l3p 1m5",
    "addr:street":"Thomson Crt",
    "iso:country":"CA",
    "sg:address":"1 Thomson Crt",
    "sg:city":"Markham",
    "sg:classifiers":[
        {
            "category":"Health Services",
            "subcategory":"Nursing And Care Facility",
            "type":"Services"
        }
    ],
    "sg:phone":"+1 905 294 9830",
    "sg:postcode":"L3P 1M5",
    "sg:province":"ON",
    "sg:tags":[
        "home",
        "retirement",
        "community"
    ],
    "wof:name":"Rougebank Foundation",
    "wof:placetype":"venue"
},
  "geometry": {"coordinates":[-79.260735,43.874851],"type":"Point"}
}