{
  "type": "Feature",
  "properties": {
    "addr:full":"90 Main St Sundridge ON P0A 1Z0",
    "addr:housenumber":"90",
    "addr:postcode":"p0a 1z0",
    "addr:street":"Main St",
    "iso:country":"CA",
    "sg:address":"90 Main St",
    "sg:city":"Sundridge",
    "sg:classifiers":[
        {
            "category":"Real Estate",
            "subcategory":"Real Estate Agent",
            "type":"Services"
        }
    ],
    "sg:phone":"+1 705 384 5262",
    "sg:postcode":"P0A 1Z0",
    "sg:province":"ON",
    "sg:tags":[
        "appraiser"
    ],
    "wof:name":"Near North Realty Ltd",
    "wof:placetype":"venue"
},
  "geometry": {"coordinates":[-79.3912811279,45.7710266113],"type":"Point"}
}