{
  "type": "Feature",
  "properties": {
    "addr:full":"55 Catherine St St Catharines ON L2R 5E9",
    "addr:housenumber":"55",
    "addr:postcode":"l2r 5e9",
    "addr:street":"Catherine St",
    "iso:country":"CA",
    "sg:address":"55 Catherine St",
    "sg:city":"St Catharines",
    "sg:classifiers":[
        {
            "category":"Wholesale",
            "subcategory":"Durable Goods & Equipment",
            "type":"Manufacturing & Wholesale Goods"
        }
    ],
    "sg:phone":"+1 905 682 6666",
    "sg:postcode":"L2R 5E9",
    "sg:province":"ON",
    "sg:tags":[
        "exporter"
    ],
    "wof:name":"Hamdani Textiles Ltd",
    "wof:placetype":"venue"
},
  "geometry": {"coordinates":[-79.245842,43.167484],"type":"Point"}
}