{
  "type": "Feature",
  "properties": {
    "addr:full":"Toronto ON M5S 2R4",
    "addr:postcode":"m5s 2r4",
    "iso:country":"CA",
    "sg:city":"Toronto",
    "sg:classifiers":[
        {
            "category":"Social Services",
            "type":"Services"
        }
    ],
    "sg:phone":"+1 416 516 9546",
    "sg:postcode":"M5S 2R4",
    "sg:province":"ON",
    "sg:tags":[
        "organization",
        "welfare"
    ],
    "wof:name":"Catalyst Centre",
    "wof:placetype":"venue"
},
  "geometry": {"coordinates":[-79.41063699999999,43.663239],"type":"Point"}
}