{
  "type": "Feature",
  "properties": {
    "addr:full":"Abbotsford BC V2S 5G3",
    "addr:postcode":"v2s 5g3",
    "iso:country":"CA",
    "sg:city":"Abbotsford",
    "sg:classifiers":[
        {
            "category":"Real Estate",
            "subcategory":"Real Estate Operator",
            "type":"Services"
        }
    ],
    "sg:phone":"+1 604 854 2377",
    "sg:postcode":"V2S 5G3",
    "sg:province":"BC",
    "sg:tags":[
        "apartment"
    ],
    "wof:name":"Bakerview Place",
    "wof:placetype":"venue"
},
  "geometry": {"coordinates":[-122.299789,49.0481],"type":"Point"}
}