{
  "type": "Feature",
  "properties": {
    "addr:full":"Toronto ON M5E 1W7",
    "addr:postcode":"m5e 1w7",
    "iso:country":"CA",
    "sg:city":"Toronto",
    "sg:classifiers":[
        {
            "category":"Real Estate",
            "subcategory":"Real Estate Agent",
            "type":"Services"
        }
    ],
    "sg:phone":"+1 416 865 1740",
    "sg:postcode":"M5E 1W7",
    "sg:province":"ON",
    "wof:name":"World Euro Corp Ltd",
    "wof:placetype":"venue"
},
  "geometry": {"coordinates":[-79.3745803833,43.6420516968],"type":"Point"}
}