{
  "type": "Feature",
  "properties": {
    "addr:full":"45 Bromley Ave Hanwell NB E3C 1M8",
    "addr:housenumber":"45",
    "addr:postcode":"e3c 1m8",
    "addr:street":"Bromley Ave",
    "iso:country":"CA",
    "sg:address":"45 Bromley Ave",
    "sg:city":"Hanwell",
    "sg:classifiers":[
        {
            "category":"Shopping",
            "type":"Retail Goods"
        }
    ],
    "sg:phone":"+1 506 455 5462",
    "sg:postcode":"E3C 1M8",
    "sg:province":"NB",
    "sg:tags":[
        "orthopedic",
        "appliance"
    ],
    "wof:name":"Biokinetic Prosthetics Inc",
    "wof:placetype":"venue"
},
  "geometry": {"coordinates":[-66.7954406738,45.8684844971],"type":"Point"}
}