{
  "type": "Feature",
  "properties": {
    "addr:full":"465 Kenmount Rd St. John's NL A1B 3P9",
    "addr:housenumber":"465",
    "addr:postcode":"a1b 3p9",
    "addr:street":"Kenmount Rd",
    "iso:country":"CA",
    "sg:address":"465 Kenmount Rd",
    "sg:city":"St. John's",
    "sg:classifiers":[
        {
            "category":"Autos & Motor Vehicles",
            "subcategory":"Motorcycle Sales",
            "type":"Retail Goods"
        }
    ],
    "sg:phone":"+1 709 739 6662",
    "sg:postcode":"A1B 3P9",
    "sg:province":"NL",
    "sg:tags":[
        "scooter"
    ],
    "wof:name":"Atlantic Recreation Ltd",
    "wof:placetype":"venue"
},
  "geometry": {"coordinates":[-52.7894821167,47.5459632874],"type":"Point"}
}