{
  "type": "Feature",
  "properties": {
    "iso:country":"CA",
    "sg:address":"1336 Rue Ontario E",
    "sg:city":"Montreal",
    "sg:classifiers":[
        {
            "category":"Shopping",
            "subcategory":"Jewelry",
            "type":"Retail Goods"
        }
    ],
    "sg:phone":"+1 514 526 3180",
    "sg:postcode":"H2L 1R9",
    "sg:province":"QC",
    "sg:tags":[
        "jeweler"
    ],
    "wof:name":"Bijouterie Johanne",
    "wof:placetype":"venue"
},
  "geometry": {"coordinates":[-73.561218,45.522682],"type":"Point"}
}