{
  "type": "Feature",
  "properties": {
    "addr:full":"600 Grandview Ave Saint John NB E2J 4M9",
    "addr:housenumber":"600",
    "addr:postcode":"e2j 4m9",
    "addr:street":"Grandview Ave",
    "iso:country":"CA",
    "sg:address":"600 Grandview Ave",
    "sg:city":"Saint John",
    "sg:classifiers":[
        {
            "category":"Manufacturing",
            "subcategory":"Metals",
            "type":"Manufacturing & Wholesale Goods"
        }
    ],
    "sg:phone":"+1 506 696 8336",
    "sg:postcode":"E2J 4M9",
    "sg:province":"NB",
    "sg:tags":[
        "welding"
    ],
    "wof:name":"Ready Arc Welding & Fab Inc",
    "wof:placetype":"venue"
},
  "geometry": {"coordinates":[-66.0040969849,45.2803077698],"type":"Point"}
}