{
  "type": "Feature",
  "properties": {
    "addr:full":"135 North Front St Belleville ON K8P 3B5",
    "addr:housenumber":"135",
    "addr:postcode":"k8p 3b5",
    "addr:street":"North Front St",
    "iso:country":"CA",
    "sg:address":"135 North Front St",
    "sg:city":"Belleville",
    "sg:classifiers":[
        {
            "category":"Shopping",
            "subcategory":"Computers & Home Electronics",
            "type":"Retail Goods"
        }
    ],
    "sg:phone":"+1 613 966 6201",
    "sg:postcode":"K8P 3B5",
    "sg:province":"ON",
    "sg:tags":[
        "equipment",
        "dealer"
    ],
    "wof:name":"Micro Age",
    "wof:placetype":"venue"
},
  "geometry": {"coordinates":[-77.3901062012,44.1761054993],"type":"Point"}
}