{
  "type": "Feature",
  "properties": {
    "addr:full":"110 Apex St Saskatoon SK S7R 1C8",
    "addr:housenumber":"110",
    "addr:postcode":"s7r 1c8",
    "addr:street":"Apex St",
    "iso:country":"CA",
    "sg:address":"110 Apex St",
    "sg:city":"Saskatoon",
    "sg:classifiers":[
        {
            "category":"Home & Garden",
            "subcategory":"Furniture",
            "type":"Retail Goods"
        }
    ],
    "sg:phone":"+1 306 242 7378",
    "sg:postcode":"S7R 1C8",
    "sg:province":"SK",
    "wof:name":"Sleepers Mattress Factory",
    "wof:placetype":"venue"
},
  "geometry": {"coordinates":[-106.67285156200001,52.1923980713],"type":"Point"}
}