{
  "type": "Feature",
  "properties": {
    "iso:country":"CA",
    "sg:address":"315 St Laurent Ave",
    "sg:city":"Quesnel",
    "sg:classifiers":[
        {
            "category":"Personal",
            "subcategory":"Beauty Salon",
            "type":"Services"
        }
    ],
    "sg:phone":"+1 250 992 5615",
    "sg:postcode":"V2J 2E1",
    "sg:province":"BC",
    "wof:name":"Hi-Fashion Hair Styling",
    "wof:placetype":"venue"
},
  "geometry": {"coordinates":[-122.49524688699999,52.9791755676],"type":"Point"}
}