{
  "type": "Feature",
  "properties": {
    "addr:full":"183 Hendershott Rd Hannon ON L0R 1P0",
    "addr:housenumber":"183",
    "addr:postcode":"l0r 1p0",
    "addr:street":"Hendershott Rd",
    "iso:country":"CA",
    "sg:address":"183 Hendershott Rd",
    "sg:city":"Hannon",
    "sg:classifiers":[
        {
            "category":"Manufacturing",
            "subcategory":"Rubber & Plastics",
            "type":"Manufacturing & Wholesale Goods"
        }
    ],
    "sg:phone":"+1 905 692 5404",
    "sg:postcode":"L0R 1P0",
    "sg:province":"ON",
    "wof:name":"Maljohn CO Ltd",
    "wof:placetype":"venue"
},
  "geometry": {"coordinates":[-79.837738,43.19854],"type":"Point"}
}