{
  "type": "Feature",
  "properties": {
    "iso:country":"CA",
    "sg:address":"42 Shaughnessy Blvd",
    "sg:city":"North York",
    "sg:classifiers":[
        {
            "category":"Building & Trades",
            "subcategory":"Construction",
            "type":"Services"
        }
    ],
    "sg:phone":"+1 416 494 3730",
    "sg:postcode":"M2J 1H5",
    "sg:province":"ON",
    "sg:tags":[
        "dry wall",
        "contractor"
    ],
    "wof:name":"Deltan Contractors Ltd",
    "wof:placetype":"venue"
},
  "geometry": {"coordinates":[-79.3517074585,43.7713356018],"type":"Point"}
}