{
  "type": "Feature",
  "properties": {
    "addr:full":"18 Queen St Charlottetown PE C1A 4A1",
    "addr:housenumber":"18",
    "addr:postcode":"c1a 4a1",
    "addr:street":"Queen St",
    "iso:country":"CA",
    "sg:address":"18 Queen St",
    "sg:city":"Charlottetown",
    "sg:classifiers":[
        {
            "category":"Shopping",
            "subcategory":"Gifts & Souvenirs",
            "type":"Retail Goods"
        }
    ],
    "sg:phone":"+1 902 892 8635",
    "sg:postcode":"C1A 4A1",
    "sg:province":"PE",
    "sg:tags":[
        "shop"
    ],
    "wof:name":"Skye Mac Gift Shop",
    "wof:placetype":"venue"
},
  "geometry": {"coordinates":[-63.1240653992,46.2315673828],"type":"Point"}
}