{
  "type": "Feature",
  "properties": {
    "addr:full":"58 Woodland Dr Hay River NT X0E 0R8",
    "addr:housenumber":"58",
    "addr:postcode":"x0e 0r8",
    "addr:street":"Woodland Dr",
    "iso:country":"CA",
    "sg:address":"58 Woodland Dr",
    "sg:city":"Hay River",
    "sg:classifiers":[
        {
            "category":"Education",
            "subcategory":"School",
            "type":"Public Place"
        }
    ],
    "sg:phone":"+1 867 874 3676",
    "sg:postcode":"X0E 0R8",
    "sg:province":"NT",
    "wof:name":"South Shore Education Council",
    "wof:placetype":"venue"
},
  "geometry": {"coordinates":[-115.786804,60.811718],"type":"Point"}
}