{
  "type": "Feature",
  "properties": {
    "addr:full":"Toronto ON M6S 4W1",
    "addr:postcode":"m6s 4w1",
    "iso:country":"CA",
    "sg:city":"Toronto",
    "sg:classifiers":[
        {
            "category":"Health Services",
            "subcategory":"Doctor",
            "type":"Services"
        }
    ],
    "sg:phone":"+1 416 604 0647",
    "sg:postcode":"M6S 4W1",
    "sg:province":"ON",
    "sg:tags":[
        "dentist"
    ],
    "wof:name":"Lukic, Gordana DDS",
    "wof:placetype":"venue"
},
  "geometry": {"coordinates":[-79.4799575806,43.650188446],"type":"Point"}
}