{
  "type": "Feature",
  "properties": {
    "iso:country":"CA",
    "sg:address":"222 Rogers St",
    "sg:city":"Peterborough",
    "sg:classifiers":[
        {
            "category":"Arts & Performance",
            "subcategory":"Theater",
            "type":"Entertainment"
        }
    ],
    "sg:phone":"+1 705 760 0826",
    "sg:postcode":"K9H 1W3",
    "sg:province":"ON",
    "sg:tags":[
        "live",
        "wedding",
        "music",
        "supply"
    ],
    "wof:name":"Bloton Disc Jockey Svc",
    "wof:placetype":"venue"
},
  "geometry": {"coordinates":[-78.304573,44.301441],"type":"Point"}
}