{
  "type": "Feature",
  "properties": {
    "addr:full":"4331 Rue Belanger Montreal QC H1T 1A8",
    "addr:housenumber":"4331",
    "addr:postcode":"h1t 1a8",
    "addr:street":"Rue Belanger",
    "iso:country":"CA",
    "sg:address":"4331 Rue Belanger",
    "sg:city":"Montreal",
    "sg:classifiers":[
        {
            "category":"Food & Beverages",
            "subcategory":"Specialty",
            "type":"Retail Goods"
        }
    ],
    "sg:phone":"+1 514 727 7902",
    "sg:postcode":"H1T 1A8",
    "sg:province":"QC",
    "wof:name":"Aliments DE Sante P Richer",
    "wof:placetype":"venue"
},
  "geometry": {"coordinates":[-73.585686,45.567154],"type":"Point"}
}