{
  "type": "Feature",
  "properties": {
    "addr:full":"9850 41 Ave NW Edmonton AB T6E 5L6",
    "addr:housenumber":"9850",
    "addr:postcode":"t6e 5l6",
    "addr:street":"41 Ave Nw",
    "iso:country":"CA",
    "sg:address":"9850 41 Ave NW",
    "sg:city":"Edmonton",
    "sg:classifiers":[
        {
            "category":"Building & Trades",
            "subcategory":"Electrical",
            "type":"Services"
        }
    ],
    "sg:phone":"+1 780 414 0980",
    "sg:postcode":"T6E 5L6",
    "sg:province":"AB",
    "sg:tags":[
        "electric",
        "contractor"
    ],
    "wof:name":"Muth Electrical Mgmt Inc",
    "wof:placetype":"venue"
},
  "geometry": {"coordinates":[-113.48422241199999,53.4765892029],"type":"Point"}
}