{
  "type": "Feature",
  "properties": {
    "addr:full":"Nipigon ON P0T 2J0",
    "addr:postcode":"p0t 2j0",
    "iso:country":"CA",
    "sg:city":"Nipigon",
    "sg:classifiers":[
        {
            "category":"Education",
            "subcategory":"Special Training",
            "type":"Public Place"
        }
    ],
    "sg:phone":"+1 807 887 3654",
    "sg:postcode":"P0T 2J0",
    "sg:province":"ON",
    "sg:tags":[
        "reading",
        "instruction",
        "improvement"
    ],
    "wof:name":"Superior North Literacy",
    "wof:placetype":"venue"
},
  "geometry": {"coordinates":[-88.269684,49.006828],"type":"Point"}
}