{
  "type": "Feature",
  "properties": {
    "addr:full":"355 Rue Turgeon Hebertville QC G8N 1S6",
    "addr:housenumber":"355",
    "addr:postcode":"g8n 1s6",
    "addr:street":"Rue Turgeon Hebertville",
    "iso:country":"CA",
    "sg:address":"355 Rue Turgeon",
    "sg:city":"Hebertville",
    "sg:classifiers":[
        {
            "category":"Government",
            "subcategory":"Office",
            "type":"Public Place"
        }
    ],
    "sg:phone":"+1 418 344 1500",
    "sg:postcode":"G8N 1S6",
    "sg:province":"QC",
    "sg:tags":[
        "village"
    ],
    "wof:name":"Hebertville Garage Municipal",
    "wof:placetype":"venue"
},
  "geometry": {"coordinates":[-71.6773223877,48.3950157166],"type":"Point"}
}