{
  "type": "Feature",
  "properties": {
    "addr:full":"1235 3E Av Val-D'Or QC J9P 6C3",
    "addr:housenumber":"1235",
    "addr:postcode":"j9p 6c3",
    "addr:street":"3E Av Val-D'Or",
    "iso:country":"CA",
    "sg:address":"1235 3E Av",
    "sg:city":"Val-D'Or",
    "sg:classifiers":[
        {
            "category":"Retail",
            "subcategory":"Funeral Services",
            "type":"Services"
        }
    ],
    "sg:phone":"+1 819 874 2511",
    "sg:postcode":"J9P 6C3",
    "sg:province":"QC",
    "sg:tags":[
        "director"
    ],
    "wof:name":"Residence Funeraire DE L'Abiti",
    "wof:placetype":"venue"
},
  "geometry": {"coordinates":[-68.42929077150001,53.89012146],"type":"Point"}
}