{
  "type": "Feature",
  "properties": {
    "iso:country":"CA",
    "sg:city":"Montreal",
    "sg:classifiers":[
        {
            "category":"Wholesale",
            "subcategory":"Apparel",
            "type":"Manufacturing & Wholesale Goods"
        }
    ],
    "sg:phone":"+1 514 278 8645",
    "sg:postcode":"H2V 4H8",
    "sg:province":"QC",
    "sg:tags":[
        "textile"
    ],
    "wof:name":"Sterling Woollens & Silks",
    "wof:placetype":"venue"
},
  "geometry": {"coordinates":[-73.6124343872,45.5267066956],"type":"Point"}
}