{
  "type": "Feature",
  "properties": {
    "iso:country":"CA",
    "sg:city":"Vancouver",
    "sg:classifiers":[
        {
            "category":"Health Services",
            "subcategory":"Doctor",
            "type":"Services"
        }
    ],
    "sg:phone":"+1 604 875 4682",
    "sg:postcode":"V5Z 4E8",
    "sg:province":"BC",
    "sg:tags":[
        "physician",
        "surgeon"
    ],
    "wof:name":"Rivers, Jason MD",
    "wof:placetype":"venue"
},
  "geometry": {"coordinates":[-123.122772217,49.2625312805],"type":"Point"}
}