{
  "type": "Feature",
  "properties": {
    "addr:full":"Calgary AB T2S 0B7",
    "addr:postcode":"t2s 0b7",
    "iso:country":"CA",
    "sg:city":"Calgary",
    "sg:classifiers":[
        {
            "category":"Travel",
            "subcategory":"Travel Agent",
            "type":"Entertainment"
        }
    ],
    "sg:phone":"+1 403 244 6334",
    "sg:postcode":"T2S 0B7",
    "sg:province":"AB",
    "sg:tags":[
        "agency",
        "bureau"
    ],
    "wof:name":"Mark Travel Ltd",
    "wof:placetype":"venue"
},
  "geometry": {"coordinates":[-114.077957,51.037949],"type":"Point"}
}