{
  "type": "Feature",
  "properties": {
    "addr:full":"78 Vaughan Rd York ON M6C 2L7",
    "addr:housenumber":"78",
    "addr:postcode":"m6c 2l7",
    "addr:street":"Vaughan Rd",
    "iso:country":"CA",
    "sg:address":"78 Vaughan Rd",
    "sg:city":"York",
    "sg:classifiers":[
        {
            "category":"Retail",
            "subcategory":"Auto Repair",
            "type":"Services"
        }
    ],
    "sg:phone":"+1 416 657 6262",
    "sg:postcode":"M6C 2L7",
    "sg:province":"ON",
    "sg:tags":[
        "repairing",
        "automobile"
    ],
    "wof:name":"Alex Auto Tech & Collision",
    "wof:placetype":"venue"
},
  "geometry": {"coordinates":[-79.4207,43.68309],"type":"Point"}
}