{
  "type": "Feature",
  "properties": {
    "addr:full":"114 Whalen St Miramichi NB E1V 3W5",
    "addr:housenumber":"114",
    "addr:postcode":"e1v 3w5",
    "addr:street":"Whalen St",
    "iso:country":"CA",
    "sg:address":"114 Whalen St",
    "sg:city":"Miramichi",
    "sg:classifiers":[
        {
            "category":"Manufacturing",
            "subcategory":"Metals",
            "type":"Manufacturing & Wholesale Goods"
        }
    ],
    "sg:phone":"+1 506 627 1220",
    "sg:postcode":"E1V 3W5",
    "sg:province":"NB",
    "sg:tags":[
        "steel"
    ],
    "wof:name":"Trac Industries Ltd",
    "wof:placetype":"venue"
},
  "geometry": {"coordinates":[-65.58628845210001,46.9987106323],"type":"Point"}
}