{
  "type": "Feature",
  "properties": {
    "addr:full":"65 Main St Twillingate NL A0G 4M0",
    "addr:housenumber":"65",
    "addr:postcode":"a0g 4m0",
    "addr:street":"Main St Twillingate",
    "iso:country":"CA",
    "sg:address":"65 Main St",
    "sg:city":"Twillingate",
    "sg:classifiers":[
        {
            "category":"Government",
            "subcategory":"Office",
            "type":"Public Place"
        }
    ],
    "sg:phone":"+1 709 884 2438",
    "sg:postcode":"A0G 4M0",
    "sg:province":"NL",
    "sg:tags":[
        "municipality"
    ],
    "wof:name":"Town of Twillingate Town Ofc",
    "wof:placetype":"venue"
},
  "geometry": {"coordinates":[-54.7759742737,49.6569213867],"type":"Point"}
}