{
  "type": "Feature",
  "properties": {
    "addr:full":"100 Donaghy Ave North Vancouver BC V7P 2L5",
    "addr:housenumber":"100",
    "addr:postcode":"v7p 2l5",
    "addr:street":"Donaghy Ave",
    "iso:country":"CA",
    "sg:address":"100 Donaghy Ave",
    "sg:city":"North Vancouver",
    "sg:classifiers":[
        {
            "category":"Retail",
            "subcategory":"Auto Repair",
            "type":"Services"
        }
    ],
    "sg:phone":"+1 604 984 2212",
    "sg:postcode":"V7P 2L5",
    "sg:province":"BC",
    "sg:tags":[
        "repairing",
        "automobile",
        "truck"
    ],
    "wof:name":"Husky Mobile Repair",
    "wof:placetype":"venue"
},
  "geometry": {"coordinates":[-123.096664,49.318283],"type":"Point"}
}