{
  "type": "Feature",
  "properties": {
    "addr:full":"452 View St Haileybury ON P0J 1K0",
    "addr:housenumber":"452",
    "addr:postcode":"p0j 1k0",
    "addr:street":"View St",
    "iso:country":"CA",
    "sg:address":"452 View St",
    "sg:city":"Haileybury",
    "sg:classifiers":[
        {
            "category":"Restaurant",
            "type":"Food & Drink"
        }
    ],
    "sg:phone":"+1 705 672 2511",
    "sg:postcode":"P0J 1K0",
    "sg:province":"ON",
    "wof:name":"King of Fries",
    "wof:placetype":"venue"
},
  "geometry": {"coordinates":[-79.63661999999999,47.444176],"type":"Point"}
}