{
  "type": "Feature",
  "properties": {
    "addr:full":"1312 Bedford Hwy Bedford NS B4A 1C8",
    "addr:housenumber":"1312",
    "addr:postcode":"b4a 1c8",
    "addr:street":"Bedford Hwy",
    "iso:country":"CA",
    "sg:address":"1312 Bedford Hwy",
    "sg:city":"Bedford",
    "sg:classifiers":[
        {
            "category":"Food & Beverages",
            "subcategory":"Groceries & Convenience Stores",
            "type":"Retail Goods"
        }
    ],
    "sg:phone":"+1 902 835 8244",
    "sg:postcode":"B4A 1C8",
    "sg:province":"NS",
    "sg:tags":[
        "grocer"
    ],
    "wof:name":"Bedford Discount Meat & Grcry",
    "wof:placetype":"venue"
},
  "geometry": {"coordinates":[-63.666721,44.726383],"type":"Point"}
}