{
  "type": "Feature",
  "properties": {
    "addr:full":"Burnaby BC V5B 1S9",
    "addr:postcode":"v5b 1s9",
    "iso:country":"CA",
    "sg:city":"Burnaby",
    "sg:classifiers":[
        {
            "category":"Building & Trades",
            "subcategory":"Construction",
            "type":"Services"
        }
    ],
    "sg:phone":"+1 604 294 9115",
    "sg:postcode":"V5B 1S9",
    "sg:province":"BC",
    "sg:tags":[
        "painter"
    ],
    "wof:name":"Korda Brothers Decorating Ltd",
    "wof:placetype":"venue"
},
  "geometry": {"coordinates":[-122.96064800000001,49.280243],"type":"Point"}
}