{
  "type": "Feature",
  "properties": {
    "addr:full":"High River AB T1V 1M7",
    "addr:postcode":"t1v 1m7",
    "iso:country":"CA",
    "sg:city":"High River",
    "sg:classifiers":[
        {
            "category":"Autos & Motor Vehicles",
            "subcategory":"Automobile Sales",
            "type":"Retail Goods"
        }
    ],
    "sg:phone":"+1 403 652 4949",
    "sg:postcode":"T1V 1M7",
    "sg:province":"AB",
    "sg:tags":[
        "car",
        "dealer"
    ],
    "wof:name":"Country Chrysler",
    "wof:placetype":"venue"
},
  "geometry": {"coordinates":[-113.84797668500001,50.5729370117],"type":"Point"}
}