{
  "type": "Feature",
  "properties": {
    "addr:full":"Richmond BC V6W 1H8",
    "addr:postcode":"v6w 1h8",
    "iso:country":"CA",
    "sg:city":"Richmond",
    "sg:classifiers":[
        {
            "category":"Manufacturing",
            "subcategory":"Tools & Machinery",
            "type":"Manufacturing & Wholesale Goods"
        }
    ],
    "sg:phone":"+1 604 270 4409",
    "sg:postcode":"V6W 1H8",
    "sg:province":"BC",
    "sg:tags":[
        "cylinder"
    ],
    "wof:name":"Hydraflow Technologies Ltd",
    "wof:placetype":"venue"
},
  "geometry": {"coordinates":[-122.98995208700001,49.1651306152],"type":"Point"}
}