{
  "type": "Feature",
  "properties": {
    "addr:full":"12922 82 St NW Edmonton AB T5E 2T2",
    "addr:housenumber":"12922",
    "addr:postcode":"t5e 2t2",
    "addr:street":"82 St Nw",
    "iso:country":"CA",
    "sg:address":"12922 82 St NW",
    "sg:city":"Edmonton",
    "sg:classifiers":[
        {
            "category":"Shopping",
            "subcategory":"Bicycles & Sporting Goods",
            "type":"Retail Goods"
        }
    ],
    "sg:phone":"+1 780 473 4498",
    "sg:postcode":"T5E 2T2",
    "sg:province":"AB",
    "sg:tags":[
        "tackle",
        "fishing"
    ],
    "wof:name":"Fishing Center",
    "wof:placetype":"venue"
},
  "geometry": {"coordinates":[-113.4674,53.587364],"type":"Point"}
}