{
  "type": "Feature",
  "properties": {
    "iso:country":"CA",
    "sg:address":"518 Fort William Rd",
    "sg:city":"Thunder Bay",
    "sg:classifiers":[
        {
            "category":"Recreation",
            "type":"Entertainment"
        }
    ],
    "sg:phone":"+1 807 345 1712",
    "sg:postcode":"P7B 2Z8",
    "sg:province":"ON",
    "sg:tags":[
        "hall",
        "auditorium"
    ],
    "wof:name":"St John Ambulance Ctr",
    "wof:placetype":"venue"
},
  "geometry": {"coordinates":[-89.2350616455,48.4184417725],"type":"Point"}
}