{
  "type": "Feature",
  "properties": {
    "addr:full":"9638 Cameron St Burnaby BC V3J 1M2",
    "addr:housenumber":"9638",
    "addr:postcode":"v3j 1m2",
    "addr:street":"Cameron St",
    "iso:country":"CA",
    "sg:address":"9638 Cameron St",
    "sg:city":"Burnaby",
    "sg:classifiers":[
        {
            "category":"Food & Beverages",
            "subcategory":"Liquor & Beverages",
            "type":"Retail Goods"
        }
    ],
    "sg:phone":"+1 604 660 7792",
    "sg:postcode":"V3J 1M2",
    "sg:province":"BC",
    "sg:tags":[
        "store"
    ],
    "wof:name":"Burnaby Liquor Stores-Govt",
    "wof:placetype":"venue"
},
  "geometry": {"coordinates":[-122.897872925,49.2533073425],"type":"Point"}
}