{
  "type": "Feature",
  "properties": {
    "addr:full":"196 Dalhousie St Brantford ON N3S 3T7",
    "addr:housenumber":"196",
    "addr:postcode":"n3s 3t7",
    "addr:street":"Dalhousie St",
    "iso:country":"CA",
    "sg:address":"196 Dalhousie St",
    "sg:city":"Brantford",
    "sg:classifiers":[
        {
            "category":"Food & Beverages",
            "subcategory":"Bakery",
            "type":"Retail Goods"
        }
    ],
    "sg:phone":"+1 519 754 0737",
    "sg:postcode":"N3S 3T7",
    "sg:province":"ON",
    "sg:tags":[
        "doughnut"
    ],
    "wof:name":"Mr Mugs Coffee & Donuts",
    "wof:placetype":"venue"
},
  "geometry": {"coordinates":[-80.2585906982,43.1398773193],"type":"Point"}
}