{
  "type": "Feature",
  "properties": {
    "addr:full":"795 Cote D'Abraham Quebec QC G1R 1A2",
    "addr:housenumber":"795",
    "addr:postcode":"g1r 1a2",
    "addr:street":"Cote D'Abraham",
    "iso:country":"CA",
    "sg:address":"795 Cote D'Abraham",
    "sg:city":"Quebec",
    "sg:classifiers":[
        {
            "category":"Wholesale",
            "subcategory":"Stationery",
            "type":"Manufacturing & Wholesale Goods"
        }
    ],
    "sg:phone":"+1 418 522 6600",
    "sg:postcode":"G1R 1A2",
    "sg:province":"QC",
    "sg:tags":[
        "cards",
        "greeting"
    ],
    "wof:name":"Editions Galerie L'Imagerie",
    "wof:placetype":"venue"
},
  "geometry": {"coordinates":[-71.289017,46.806496],"type":"Point"}
}