{
  "type": "Feature",
  "properties": {
    "addr:full":"608 Signal Rd Fort Mcmurray AB T9H 4Z4",
    "addr:housenumber":"608",
    "addr:postcode":"t9h 4z4",
    "addr:street":"Signal Rd",
    "iso:country":"CA",
    "sg:address":"608 Signal Rd",
    "sg:city":"Fort Mcmurray",
    "sg:classifiers":[
        {
            "category":"Retail",
            "subcategory":"Laundry & Dry Cleaning",
            "type":"Services"
        }
    ],
    "sg:phone":"+1 780 791 0552",
    "sg:postcode":"T9H 4Z4",
    "sg:province":"AB",
    "sg:tags":[
        "cleaners"
    ],
    "wof:name":"Style Ryte Cleaners",
    "wof:placetype":"venue"
},
  "geometry": {"coordinates":[-111.449150085,56.728969574],"type":"Point"}
}