{
  "type": "Feature",
  "properties": {
    "addr:full":"16 Glendale Ave Mount Pearl NL A1N 1M9",
    "addr:housenumber":"16",
    "addr:postcode":"a1n 1m9",
    "addr:street":"Glendale Ave",
    "iso:country":"CA",
    "sg:address":"16 Glendale Ave",
    "sg:city":"Mount Pearl",
    "sg:classifiers":[
        {
            "category":"Home & Garden",
            "subcategory":"Garden Supply",
            "type":"Retail Goods"
        }
    ],
    "sg:phone":"+1 709 368 5106",
    "sg:postcode":"A1N 1M9",
    "sg:province":"NL",
    "sg:tags":[
        "nurseryman"
    ],
    "wof:name":"Glendale Gardens",
    "wof:placetype":"venue"
},
  "geometry": {"coordinates":[-52.808559,47.521496],"type":"Point"}
}