{
  "type": "Feature",
  "properties": {
    "addr:full":"52 5E Av E LA Sarre QC J9Z 1K9",
    "addr:housenumber":"52",
    "addr:postcode":"j9z 1k9",
    "addr:street":"5E Av E La Sarre",
    "iso:country":"CA",
    "sg:address":"52 5E Av E",
    "sg:city":"LA Sarre",
    "sg:classifiers":[
        {
            "category":"Cinema",
            "subcategory":"Movie Rental",
            "type":"Entertainment"
        }
    ],
    "sg:phone":"+1 819 339 2463",
    "sg:postcode":"J9Z 1K9",
    "sg:province":"QC",
    "sg:tags":[
        "leasing",
        "video",
        "disc",
        "tape"
    ],
    "wof:name":"Cine Video Club LA Sarre",
    "wof:placetype":"venue"
},
  "geometry": {"coordinates":[-79.2023696899,48.8054695129],"type":"Point"}
}