{
  "type": "Feature",
  "properties": {
    "addr:full":"666 Rue Sherbrooke O Montreal QC H3A 1E7",
    "addr:housenumber":"666",
    "addr:postcode":"h3a 1e7",
    "addr:street":"Rue Sherbrooke O",
    "iso:country":"CA",
    "sg:address":"666 Rue Sherbrooke O",
    "sg:city":"Montreal",
    "sg:classifiers":[
        {
            "category":"Professional",
            "subcategory":"Computer Services",
            "type":"Services"
        }
    ],
    "sg:phone":"+1 514 876 9222",
    "sg:postcode":"H3A 1E7",
    "sg:province":"QC",
    "sg:tags":[
        "information",
        "system",
        "consultant"
    ],
    "wof:name":"Uniglobe Voyages",
    "wof:placetype":"venue"
},
  "geometry": {"coordinates":[-73.5664138794,45.5187644958],"type":"Point"}
}