{
  "type": "Feature",
  "properties": {
    "addr:full":"1951 Tillemont St Montreal QC H2E 1C9",
    "addr:housenumber":"1951",
    "addr:postcode":"h2e 1c9",
    "addr:street":"Tillemont St",
    "iso:country":"CA",
    "sg:address":"1951 Tillemont St",
    "sg:city":"Montreal",
    "sg:classifiers":[
        {
            "category":"Food & Beverages",
            "subcategory":"Fruits & Vegetables",
            "type":"Retail Goods"
        }
    ],
    "sg:phone":"+1 514 374 8234",
    "sg:postcode":"H2E 1C9",
    "sg:province":"QC",
    "sg:tags":[
        "produce"
    ],
    "wof:name":"Fruiterie Martin",
    "wof:placetype":"venue"
},
  "geometry": {"coordinates":[-73.61517333979999,45.5532913208],"type":"Point"}
}