{
  "type": "Feature",
  "properties": {
    "addr:full":"Richmond BC V6V 2H4",
    "addr:postcode":"v6v 2h4",
    "iso:country":"CA",
    "sg:city":"Richmond",
    "sg:classifiers":[
        {
            "category":"Manufacturing",
            "subcategory":"Food",
            "type":"Manufacturing & Wholesale Goods"
        }
    ],
    "sg:phone":"+1 604 323 8896",
    "sg:postcode":"V6V 2H4",
    "sg:province":"BC",
    "sg:tags":[
        "grocer",
        "product",
        "manufacturer"
    ],
    "wof:name":"Yau Sing Hong Enterprises",
    "wof:placetype":"venue"
},
  "geometry": {"coordinates":[-123.09483299999999,49.20208],"type":"Point"}
}