{
  "type": "Feature",
  "properties": {
    "iso:country":"CA",
    "sg:address":"5 King Edward Ave W",
    "sg:city":"Vancouver",
    "sg:classifiers":[
        {
            "category":"Organizations",
            "subcategory":"Religious Organization",
            "type":"Services"
        }
    ],
    "sg:phone":"+1 604 876 7814",
    "sg:postcode":"V5Y 2H6",
    "sg:province":"BC",
    "sg:tags":[
        "church"
    ],
    "wof:name":"Augustana Lutheran Church",
    "wof:placetype":"venue"
},
  "geometry": {"coordinates":[-123.105209,49.249046],"type":"Point"}
}