{
  "type": "Feature",
  "properties": {
    "addr:full":"2075 5E Av Shawinigan-Sud QC G9P 1N6",
    "addr:housenumber":"2075",
    "addr:postcode":"g9p 1n6",
    "addr:street":"5E Av Shawinigan-Sud",
    "iso:country":"CA",
    "sg:address":"2075 5E Av",
    "sg:city":"Shawinigan-Sud",
    "sg:classifiers":[
        {
            "category":"Travel",
            "subcategory":"Travel Agent",
            "type":"Entertainment"
        }
    ],
    "sg:phone":"+1 819 537 5757",
    "sg:postcode":"G9P 1N6",
    "sg:province":"QC",
    "sg:tags":[
        "agency",
        "bureau"
    ],
    "wof:name":"Voyages Arc-En-Ciel",
    "wof:placetype":"venue"
},
  "geometry": {"coordinates":[-72.74582700000001,46.52058],"type":"Point"}
}