{
  "type": "Feature",
  "properties": {
    "addr:full":"350 7 Ave SW # 2800 Calgary AB T2P 3N9",
    "addr:housenumber":"350",
    "addr:postcode":"t2p 3n9",
    "addr:street":"7 Ave Sw # 2800",
    "iso:country":"CA",
    "sg:address":"350 7 Ave SW # 2800",
    "sg:city":"Calgary",
    "sg:classifiers":[
        {
            "category":"Real Estate",
            "subcategory":"Real Estate Agent",
            "type":"Services"
        }
    ],
    "sg:phone":"+1 403 263 9604",
    "sg:postcode":"T2P 3N9",
    "sg:province":"AB",
    "sg:tags":[
        "desk",
        "space"
    ],
    "wof:name":"First Executive Ctr Ltd",
    "wof:placetype":"venue"
},
  "geometry": {"coordinates":[-114.069091797,51.0467605591],"type":"Point"}
}