{
  "type": "Feature",
  "properties": {
    "addr:full":"202353 Hwy 21 Owen Sound ON N4K 5N7",
    "addr:housenumber":"202353",
    "addr:postcode":"n4k 5n7",
    "addr:street":"Hwy 21",
    "iso:country":"CA",
    "sg:address":"202353 Hwy 21",
    "sg:city":"Owen Sound",
    "sg:classifiers":[
        {
            "category":"Home & Garden",
            "subcategory":"Garden Supply",
            "type":"Retail Goods"
        }
    ],
    "sg:phone":"+1 519 376 6521",
    "sg:postcode":"N4K 5N7",
    "sg:province":"ON",
    "sg:tags":[
        "center"
    ],
    "wof:name":"Westside Nurseries-Greenhouses",
    "wof:placetype":"venue"
},
  "geometry": {"coordinates":[-80.952927,44.566872],"type":"Point"}
}