{
  "type": "Feature",
  "properties": {
    "addr:full":"18 Carl Cres Waterdown ON L0R 2H4",
    "addr:housenumber":"18",
    "addr:postcode":"l0r 2h4",
    "addr:street":"Carl Cres",
    "iso:country":"CA",
    "sg:address":"18 Carl Cres",
    "sg:city":"Waterdown",
    "sg:classifiers":[
        {
            "category":"Manufacturing",
            "subcategory":"Tools & Machinery",
            "type":"Manufacturing & Wholesale Goods"
        }
    ],
    "sg:phone":"+1 905 689 6551",
    "sg:postcode":"L0R 2H4",
    "sg:province":"ON",
    "sg:tags":[
        "equipment",
        "system",
        "automation"
    ],
    "wof:name":"Pollex Enterprises Inc",
    "wof:placetype":"venue"
},
  "geometry": {"coordinates":[-79.892242,43.325428],"type":"Point"}
}