{
  "type": "Feature",
  "properties": {
    "iso:country":"CA",
    "sg:address":"18 Pte A LA Croix",
    "sg:city":"Port-Daniel",
    "sg:classifiers":[
        {
            "category":"Building & Trades",
            "subcategory":"Electrical",
            "type":"Services"
        }
    ],
    "sg:phone":"+1 418 396 5412",
    "sg:postcode":"G0C 2N0",
    "sg:province":"QC",
    "sg:tags":[
        "electric",
        "contractor"
    ],
    "wof:name":"Hachey Electrique",
    "wof:placetype":"venue"
},
  "geometry": {"coordinates":[-64.9660568237,48.1819915771],"type":"Point"}
}