{
  "type": "Feature",
  "properties": {
    "addr:full":"Dawson Creek BC V1G 2E1",
    "addr:postcode":"v1g 2e1",
    "iso:country":"CA",
    "sg:city":"Dawson Creek",
    "sg:classifiers":[
        {
            "category":"Professional",
            "subcategory":"Accounting & Tax Preparation",
            "type":"Services"
        }
    ],
    "sg:phone":"+1 250 782 3558",
    "sg:postcode":"V1G 2E1",
    "sg:province":"BC",
    "sg:tags":[
        "consultant",
        "return",
        "filing"
    ],
    "wof:name":"Liberty Tax Svc",
    "wof:placetype":"venue"
},
  "geometry": {"coordinates":[-120.241363525,55.7594070435],"type":"Point"}
}