{
  "type": "Feature",
  "properties": {
    "addr:full":"31 Bolland Cres Ajax ON L1S 3G8",
    "addr:housenumber":"31",
    "addr:postcode":"l1s 3g8",
    "addr:street":"Bolland Cres",
    "iso:country":"CA",
    "sg:address":"31 Bolland Cres",
    "sg:city":"Ajax",
    "sg:classifiers":[
        {
            "category":"Professional",
            "subcategory":"Art Services",
            "type":"Services"
        }
    ],
    "sg:phone":"+1 905 424 9768",
    "sg:postcode":"L1S 3G8",
    "sg:province":"ON",
    "sg:tags":[
        "photographer"
    ],
    "wof:name":"Alexander Robertson Phtgrphy",
    "wof:placetype":"venue"
},
  "geometry": {"coordinates":[-79.01737213129999,43.8235015869],"type":"Point"}
}