{
  "type": "Feature",
  "properties": {
    "addr:full":"Strathmore AB T1P 1R7",
    "addr:postcode":"t1p 1r7",
    "iso:country":"CA",
    "sg:city":"Strathmore",
    "sg:classifiers":[
        {
            "category":"Insurance",
            "subcategory":"Insurance Agent",
            "type":"Services"
        }
    ],
    "sg:phone":"+1 403 934 4503",
    "sg:postcode":"T1P 1R7",
    "sg:province":"AB",
    "sg:tags":[
        "investment"
    ],
    "wof:name":"Edward Jones",
    "wof:placetype":"venue"
},
  "geometry": {"coordinates":[-113.40007,51.055626],"type":"Point"}
}