{
  "type": "Feature",
  "properties": {
    "iso:country":"CA",
    "sg:address":"75 Rue Saint-Viateur O",
    "sg:city":"Montreal",
    "sg:classifiers":[
        {
            "category":"Restaurant",
            "type":"Food & Drink"
        }
    ],
    "sg:phone":"+1 514 276 0073",
    "sg:postcode":"H2T 2K9",
    "sg:province":"QC",
    "sg:tags":[
        "delicatessen"
    ],
    "wof:name":"Charcuterie Fromagerie Jose",
    "wof:placetype":"venue"
},
  "geometry": {"coordinates":[-73.5982208252,45.5268859863],"type":"Point"}
}