{
  "type": "Feature",
  "properties": {
    "iso:country":"CA",
    "sg:address":"4570 Av Arseneault",
    "sg:city":"Becancour",
    "sg:classifiers":[
        {
            "category":"Home & Garden",
            "subcategory":"Hardware",
            "type":"Retail Goods"
        }
    ],
    "sg:phone":"+1 819 233 2363",
    "sg:postcode":"G9H 1V8",
    "sg:province":"QC",
    "wof:name":"Acadien Bricoleur Inc",
    "wof:placetype":"venue"
},
  "geometry": {"coordinates":[-72.5071182251,46.2738037109],"type":"Point"}
}