{
  "type": "Feature",
  "properties": {
    "addr:full":"2 Macintosh Rd Port Hawkesbury NS B9A 3K5",
    "addr:housenumber":"2",
    "addr:postcode":"b9a 3k5",
    "addr:street":"Macintosh Rd",
    "iso:country":"CA",
    "sg:address":"2 Macintosh Rd",
    "sg:city":"Port Hawkesbury",
    "sg:classifiers":[
        {
            "category":"Wholesale",
            "subcategory":"Electrical",
            "type":"Manufacturing & Wholesale Goods"
        }
    ],
    "sg:phone":"+1 902 625 0127",
    "sg:postcode":"B9A 3K5",
    "sg:province":"NS",
    "sg:tags":[
        "communication",
        "radio",
        "system"
    ],
    "wof:name":"Highland Mobile Radio",
    "wof:placetype":"venue"
},
  "geometry": {"coordinates":[-61.3412017822,45.6132888794],"type":"Point"}
}