{
  "type": "Feature",
  "properties": {
    "iso:country":"CA",
    "sg:address":"108 Alfred St",
    "sg:city":"Kemptville",
    "sg:classifiers":[
        {
            "category":"Farming",
            "subcategory":"Farm & Veterinary Services",
            "type":"Manufacturing & Wholesale Goods"
        }
    ],
    "sg:phone":"+1 613 258 6155",
    "sg:postcode":"K0G 1J0",
    "sg:province":"ON",
    "sg:tags":[
        "management"
    ],
    "wof:name":"Dairypac Inc",
    "wof:placetype":"venue"
},
  "geometry": {"coordinates":[-75.65168,45.015736],"type":"Point"}
}