{
  "type": "Feature",
  "properties": {
    "addr:full":"1150 Central Ave N Swift Current SK S9H 0G1",
    "addr:housenumber":"1150",
    "addr:postcode":"s9h 0g1",
    "addr:street":"Central Ave N",
    "iso:country":"CA",
    "sg:address":"1150 Central Ave N",
    "sg:city":"Swift Current",
    "sg:classifiers":[
        {
            "category":"Home & Garden",
            "subcategory":"Carpets & Floor Coverings",
            "type":"Retail Goods"
        }
    ],
    "sg:phone":"+1 306 778 8883",
    "sg:postcode":"S9H 0G1",
    "sg:province":"SK",
    "sg:tags":[
        "plumbing",
        "rug",
        "contractor"
    ],
    "wof:name":"Pioneer CO-Operative Assn Ltd",
    "wof:placetype":"venue"
},
  "geometry": {"coordinates":[-107.796318054,50.3012237549],"type":"Point"}
}