{
  "type": "Feature",
  "properties": {
    "iso:country":"CA",
    "sg:address":"92 Banff Ave",
    "sg:city":"Banff",
    "sg:classifiers":[
        {
            "category":"Organizations",
            "subcategory":"Professional Association",
            "type":"Services"
        }
    ],
    "sg:phone":"+1 403 762 2550",
    "sg:postcode":"T1L 1A4",
    "sg:province":"AB",
    "wof:name":"Royal Canadian Legion",
    "wof:placetype":"venue"
},
  "geometry": {"coordinates":[-115.570877075,51.1740112305],"type":"Point"}
}