{
  "type": "Feature",
  "properties": {
    "addr:full":"417 Turenne St Winnipeg MB R2J 0S5",
    "addr:housenumber":"417",
    "addr:postcode":"r2j 0s5",
    "addr:street":"Turenne St",
    "iso:country":"CA",
    "sg:address":"417 Turenne St",
    "sg:city":"Winnipeg",
    "sg:classifiers":[
        {
            "category":"Wholesale",
            "subcategory":"Wine & Distilled Alcoholic Beverages",
            "type":"Manufacturing & Wholesale Goods"
        }
    ],
    "sg:phone":"+1 204 237 3333",
    "sg:postcode":"R2J 0S5",
    "sg:province":"MB",
    "sg:tags":[
        "equipment",
        "brewer",
        "supply"
    ],
    "wof:name":"Moonshiners Unlimited",
    "wof:placetype":"venue"
},
  "geometry": {"coordinates":[-97.078362,49.881908],"type":"Point"}
}