{
  "type": "Feature",
  "properties": {
    "addr:full":"1384 Boul Jacques-Cartier Mont-Joli QC G5H 2T7",
    "addr:housenumber":"1384",
    "addr:postcode":"g5h 2t7",
    "addr:street":"Boul Jacques-Cartier",
    "iso:country":"CA",
    "sg:address":"1384 Boul Jacques-Cartier",
    "sg:city":"Mont-Joli",
    "sg:classifiers":[
        {
            "category":"Retail",
            "subcategory":"Auto Repair",
            "type":"Services"
        }
    ],
    "sg:phone":"+1 418 775 5076",
    "sg:postcode":"G5H 2T7",
    "sg:province":"QC",
    "sg:tags":[
        "repairing",
        "automobile"
    ],
    "wof:name":"Garage Fournier & Fils Enr",
    "wof:placetype":"venue"
},
  "geometry": {"coordinates":[-68.194717,48.589973],"type":"Point"}
}