{
  "type": "Feature",
  "properties": {
    "addr:full":"1530 Albion Rd # 73 Etobicoke ON M9V 1B4",
    "addr:housenumber":"1530",
    "addr:postcode":"m9v 1b4",
    "addr:street":"Albion Rd # 73",
    "iso:country":"CA",
    "sg:address":"1530 Albion Rd # 73",
    "sg:city":"Etobicoke",
    "sg:classifiers":[
        {
            "category":"Shopping",
            "subcategory":"Jewelry",
            "type":"Retail Goods"
        }
    ],
    "sg:phone":"+1 416 744 9333",
    "sg:postcode":"M9V 1B4",
    "sg:province":"ON",
    "sg:tags":[
        "jeweler"
    ],
    "wof:name":"Liz Jewellery & Gifts",
    "wof:placetype":"venue"
},
  "geometry": {"coordinates":[-79.58191680909999,43.7400894165],"type":"Point"}
}