{
  "type": "Feature",
  "properties": {
    "addr:full":"Thornhill ON L4J 8G3",
    "addr:postcode":"l4j 8g3",
    "iso:country":"CA",
    "sg:city":"Thornhill",
    "sg:classifiers":[
        {
            "category":"Social Services",
            "subcategory":"Child Care",
            "type":"Services"
        }
    ],
    "sg:phone":"+1 905 882 9551",
    "sg:postcode":"L4J 8G3",
    "sg:province":"ON",
    "wof:name":"Butternut Children's Ctr",
    "wof:placetype":"venue"
},
  "geometry": {"coordinates":[-79.456604,43.814651],"type":"Point"}
}