{
  "type": "Feature",
  "properties": {
    "addr:full":"Louiseville QC J5V 2L4",
    "addr:postcode":"j5v 2l4",
    "iso:country":"CA",
    "sg:city":"Louiseville",
    "sg:classifiers":[
        {
            "category":"Manufacturing",
            "subcategory":"Furniture",
            "type":"Manufacturing & Wholesale Goods"
        }
    ],
    "sg:phone":"+1 819 228 8573",
    "sg:postcode":"J5V 2L4",
    "sg:province":"QC",
    "wof:name":"Entreprises Dnl Lacoursiere",
    "wof:placetype":"venue"
},
  "geometry": {"coordinates":[-72.8987579346,46.2610397339],"type":"Point"}
}