{
  "type": "Feature",
  "properties": {
    "addr:full":"572 Notre Dame St Belle River ON N0R 1A0",
    "addr:housenumber":"572",
    "addr:postcode":"n0r 1a0",
    "addr:street":"Notre Dame St",
    "iso:country":"CA",
    "sg:address":"572 Notre Dame St",
    "sg:city":"Belle River",
    "sg:classifiers":[
        {
            "category":"Retail",
            "subcategory":"Funeral Services",
            "type":"Services"
        }
    ],
    "sg:phone":"+1 519 728 1500",
    "sg:postcode":"N0R 1A0",
    "sg:province":"ON",
    "sg:tags":[
        "director"
    ],
    "wof:name":"Melady's Funeral Home",
    "wof:placetype":"venue"
},
  "geometry": {"coordinates":[-82.70948,42.293068],"type":"Point"}
}