{
  "type": "Feature",
  "properties": {
    "addr:full":"380 Kings Rd Sydney NS B1S 1A8",
    "addr:housenumber":"380",
    "addr:postcode":"b1s 1a8",
    "addr:street":"Kings Rd",
    "iso:country":"CA",
    "sg:address":"380 Kings Rd",
    "sg:city":"Sydney",
    "sg:classifiers":[
        {
            "category":"Banks & Credit Unions",
            "subcategory":"Bank",
            "type":"Services"
        }
    ],
    "sg:phone":"+1 902 564 4596",
    "sg:postcode":"B1S 1A8",
    "sg:province":"NS",
    "sg:tags":[
        "loan",
        "real estate"
    ],
    "wof:name":"Citi Financial Canada Inc",
    "wof:placetype":"venue"
},
  "geometry": {"coordinates":[-60.2008361816,46.1237030029],"type":"Point"}
}