{
  "type": "Feature",
  "properties": {
    "addr:full":"Vancouver BC V6B 2S2",
    "addr:postcode":"v6b 2s2",
    "iso:country":"CA",
    "sg:city":"Vancouver",
    "sg:classifiers":[
        {
            "category":"Professional",
            "subcategory":"Management & Consulting",
            "type":"Services"
        }
    ],
    "sg:phone":"+1 604 642 6765",
    "sg:postcode":"V6B 2S2",
    "sg:province":"BC",
    "sg:tags":[
        "marketing",
        "internet",
        "consultant"
    ],
    "wof:name":"6S Marketing Inc",
    "wof:placetype":"venue"
},
  "geometry": {"coordinates":[-123.12125399999999,49.275654],"type":"Point"}
}