{
  "type": "Feature",
  "properties": {
    "addr:full":"58 Rue DE Bresoles Montreal QC H2Y 1V5",
    "addr:housenumber":"58",
    "addr:postcode":"h2y 1v5",
    "addr:street":"Rue De Bresoles",
    "iso:country":"CA",
    "sg:address":"58 Rue DE Bresoles",
    "sg:city":"Montreal",
    "sg:classifiers":[
        {
            "category":"Professional",
            "subcategory":"Management & Consulting",
            "type":"Services"
        }
    ],
    "sg:phone":"+1 514 288 2000",
    "sg:postcode":"H2Y 1V5",
    "sg:province":"QC",
    "sg:tags":[
        "communications",
        "consultant"
    ],
    "wof:name":"Communications 2000 Ltee",
    "wof:placetype":"venue"
},
  "geometry": {"coordinates":[-73.555367,45.505009],"type":"Point"}
}