{
  "type": "Feature",
  "properties": {
    "addr:full":"135 Victoria Ave Belleville ON K8N 2B1",
    "addr:housenumber":"135",
    "addr:postcode":"k8n 2b1",
    "addr:street":"Victoria Ave",
    "iso:country":"CA",
    "sg:address":"135 Victoria Ave",
    "sg:city":"Belleville",
    "sg:classifiers":[
        {
            "category":"Health Services",
            "subcategory":"Nursing And Care Facility",
            "type":"Services"
        }
    ],
    "sg:phone":"+1 613 969 7407",
    "sg:postcode":"K8N 2B1",
    "sg:province":"ON",
    "sg:tags":[
        "personal"
    ],
    "wof:name":"Plainfield Community Home",
    "wof:placetype":"venue"
},
  "geometry": {"coordinates":[-77.377037,44.168324],"type":"Point"}
}