{
  "type": "Feature",
  "properties": {
    "iso:country":"CA",
    "sg:address":"4600 12E Av",
    "sg:city":"Shawinigan-Sud",
    "sg:classifiers":[
        {
            "category":"Manufacturing",
            "subcategory":"Metals",
            "type":"Manufacturing & Wholesale Goods"
        }
    ],
    "sg:phone":"+1 819 537 8881",
    "sg:postcode":"G9N 6T5",
    "sg:province":"QC",
    "sg:tags":[
        "caster",
        "glide"
    ],
    "wof:name":"Roues & Roulettes Ro-Ma",
    "wof:placetype":"venue"
},
  "geometry": {"coordinates":[-72.7186050415,46.49659729],"type":"Point"}
}