{
  "type": "Feature",
  "properties": {
    "addr:full":"75 Willoway Stouffville ON L4A 1K6",
    "addr:housenumber":"75",
    "addr:postcode":"l4a 1k6",
    "addr:street":"Willoway",
    "iso:country":"CA",
    "sg:address":"75 Willoway",
    "sg:city":"Stouffville",
    "sg:classifiers":[
        {
            "category":"Education",
            "subcategory":"Special Training",
            "type":"Public Place"
        }
    ],
    "sg:phone":"+1 905 642 2938",
    "sg:postcode":"L4A 1K6",
    "sg:province":"ON",
    "sg:tags":[
        "management"
    ],
    "wof:name":"Hutchison Group",
    "wof:placetype":"venue"
},
  "geometry": {"coordinates":[-79.2422943115,43.9768791199],"type":"Point"}
}