{
  "type": "Feature",
  "properties": {
    "addr:full":"2579 Yonge St Toronto ON M4P 2J1",
    "addr:housenumber":"2579",
    "addr:postcode":"m4p 2j1",
    "addr:street":"Yonge St",
    "iso:country":"CA",
    "sg:address":"2579 Yonge St",
    "sg:city":"Toronto",
    "sg:classifiers":[
        {
            "category":"Cinema",
            "subcategory":"Movie Rental",
            "type":"Entertainment"
        }
    ],
    "sg:phone":"+1 416 487 6221",
    "sg:postcode":"M4P 2J1",
    "sg:province":"ON",
    "sg:tags":[
        "leasing",
        "video",
        "disc",
        "tape"
    ],
    "wof:name":"Movies 4 You",
    "wof:placetype":"venue"
},
  "geometry": {"coordinates":[-79.3997268677,43.7140960693],"type":"Point"}
}