{
  "type": "Feature",
  "properties": {
    "addr:full":"Ottawa ON K1N 9J7",
    "addr:postcode":"k1n 9j7",
    "iso:country":"CA",
    "sg:city":"Ottawa",
    "sg:classifiers":[
        {
            "category":"Restaurant",
            "type":"Food & Drink"
        }
    ],
    "sg:phone":"+1 613 563 0433",
    "sg:postcode":"K1N 9J7",
    "sg:province":"ON",
    "wof:name":"Kfc",
    "wof:placetype":"venue"
},
  "geometry": {"coordinates":[-75.692314,45.425819],"type":"Point"}
}