{
  "type": "Feature",
  "properties": {
    "addr:full":"15302 Pacific Ave White Rock BC V4B 1P9",
    "addr:housenumber":"15302",
    "addr:postcode":"v4b 1p9",
    "addr:street":"Pacific Ave",
    "iso:country":"CA",
    "sg:address":"15302 Pacific Ave",
    "sg:city":"White Rock",
    "sg:classifiers":[
        {
            "category":"Recreation",
            "type":"Entertainment"
        }
    ],
    "sg:phone":"+1 604 531 4944",
    "sg:postcode":"V4B 1P9",
    "sg:province":"BC",
    "sg:tags":[
        "hall",
        "auditorium"
    ],
    "wof:name":"White Rock Masonic Society",
    "wof:placetype":"venue"
},
  "geometry": {"coordinates":[-122.79830200000001,49.022697],"type":"Point"}
}