{
  "type": "Feature",
  "properties": {
    "addr:full":"4 Vata Crt Aurora ON L4G 4B6",
    "addr:housenumber":"4",
    "addr:postcode":"l4g 4b6",
    "addr:street":"Vata Crt",
    "iso:country":"CA",
    "sg:address":"4 Vata Crt",
    "sg:city":"Aurora",
    "sg:classifiers":[
        {
            "category":"Building & Trades",
            "subcategory":"Plumbing",
            "type":"Services"
        }
    ],
    "sg:phone":"+1 905 713 6959",
    "sg:postcode":"L4G 4B6",
    "sg:province":"ON",
    "sg:tags":[
        "ventilating",
        "contractor"
    ],
    "wof:name":"Interior Climate Group",
    "wof:placetype":"venue"
},
  "geometry": {"coordinates":[-79.458190918,43.9882316589],"type":"Point"}
}