{
  "type": "Feature",
  "properties": {
    "addr:full":"1253 Walker St Mcgregor ON N0R 1J0",
    "addr:housenumber":"1253",
    "addr:postcode":"n0r 1j0",
    "addr:street":"Walker St",
    "iso:country":"CA",
    "sg:address":"1253 Walker St",
    "sg:city":"Mcgregor",
    "sg:classifiers":[
        {
            "category":"Manufacturing",
            "subcategory":"Tools & Machinery",
            "type":"Manufacturing & Wholesale Goods"
        }
    ],
    "sg:phone":"+1 519 726 6233",
    "sg:postcode":"N0R 1J0",
    "sg:province":"ON",
    "sg:tags":[
        "machine",
        "shop"
    ],
    "wof:name":"Alger Machine Shop",
    "wof:placetype":"venue"
},
  "geometry": {"coordinates":[-82.993637085,42.1623954773],"type":"Point"}
}