{
  "type": "Feature",
  "properties": {
    "iso:country":"CA",
    "sg:address":"835 Lorne Ave",
    "sg:city":"London",
    "sg:classifiers":[
        {
            "category":"Organizations",
            "subcategory":"Religious Organization",
            "type":"Services"
        }
    ],
    "sg:phone":"+1 519 672 4864",
    "sg:postcode":"N5W 3K9",
    "sg:province":"ON",
    "sg:tags":[
        "church"
    ],
    "wof:name":"Ambassador Baptist Church",
    "wof:placetype":"venue"
},
  "geometry": {"coordinates":[-81.225349,42.994061],"type":"Point"}
}