{
  "type": "Feature",
  "properties": {
    "iso:country":"CA",
    "sg:address":"1305 Ch Des Patriotes",
    "sg:city":"Otterburn Park",
    "sg:classifiers":[
        {
            "category":"Shopping",
            "subcategory":"Florist",
            "type":"Retail Goods"
        }
    ],
    "sg:phone":"+1 450 464 4746",
    "sg:postcode":"J3H 4K7",
    "sg:province":"QC",
    "wof:name":"Aux Floralies 5 Saisons Enr",
    "wof:placetype":"venue"
},
  "geometry": {"coordinates":[-73.227783,45.536686],"type":"Point"}
}