{
  "type": "Feature",
  "properties": {
    "addr:full":"1005 Westmount Ave Innisfil ON L9S 1T6",
    "addr:housenumber":"1005",
    "addr:postcode":"l9s 1t6",
    "addr:street":"Westmount Ave",
    "iso:country":"CA",
    "sg:address":"1005 Westmount Ave",
    "sg:city":"Innisfil",
    "sg:classifiers":[
        {
            "category":"Manufacturing",
            "subcategory":"Signs",
            "type":"Manufacturing & Wholesale Goods"
        }
    ],
    "sg:phone":"+1 705 436 2403",
    "sg:postcode":"L9S 1T6",
    "sg:province":"ON",
    "wof:name":"Nite Light Sign Svc",
    "wof:placetype":"venue"
},
  "geometry": {"coordinates":[-79.5476608276,44.3091850281],"type":"Point"}
}