{
  "type": "Feature",
  "properties": {
    "iso:country":"CA",
    "sg:address":"8015 Av Blaise-Pascal",
    "sg:city":"Montreal",
    "sg:classifiers":[
        {
            "category":"Personal",
            "subcategory":"Barber",
            "type":"Services"
        }
    ],
    "sg:phone":"+1 514 881 8727",
    "sg:postcode":"H1E 3X7",
    "sg:province":"QC",
    "wof:name":"Stars Salon DE Coiffure",
    "wof:placetype":"venue"
},
  "geometry": {"coordinates":[-73.5865249634,45.6295509338],"type":"Point"}
}