{
  "type": "Feature",
  "properties": {
    "iso:country":"CA",
    "sg:address":"83 Shaver Rd",
    "sg:city":"Brantford",
    "sg:classifiers":[
        {
            "category":"Building & Trades",
            "subcategory":"Construction",
            "type":"Services"
        }
    ],
    "sg:phone":"+1 519 752 0311",
    "sg:postcode":"N3T 5M1",
    "sg:province":"ON",
    "sg:tags":[
        "system",
        "blower"
    ],
    "wof:name":"Delhi Industries",
    "wof:placetype":"venue"
},
  "geometry": {"coordinates":[-80.30610656739999,43.1355514526],"type":"Point"}
}