{
  "type": "Feature",
  "properties": {
    "addr:full":"29 Hero Rd Shelburne NS B0T 1W0",
    "addr:housenumber":"29",
    "addr:postcode":"b0t 1w0",
    "addr:street":"Hero Rd",
    "iso:country":"CA",
    "sg:address":"29 Hero Rd",
    "sg:city":"Shelburne",
    "sg:classifiers":[
        {
            "category":"Manufacturing",
            "subcategory":"Watercraft",
            "type":"Manufacturing & Wholesale Goods"
        }
    ],
    "sg:phone":"+1 902 875 8100",
    "sg:postcode":"B0T 1W0",
    "sg:province":"NS",
    "sg:tags":[
        "builder",
        "ship",
        "repairer"
    ],
    "wof:name":"Shelburne Ship Repair",
    "wof:placetype":"venue"
},
  "geometry": {"coordinates":[-65.31564331049999,43.7656593323],"type":"Point"}
}