{
  "type": "Feature",
  "properties": {
    "addr:full":"Coquitlam BC V3K 6R2",
    "addr:postcode":"v3k 6r2",
    "iso:country":"CA",
    "sg:city":"Coquitlam",
    "sg:classifiers":[
        {
            "category":"Freight",
            "type":"Transportation"
        }
    ],
    "sg:phone":"+1 604 941 8802",
    "sg:postcode":"V3K 6R2",
    "sg:province":"BC",
    "wof:name":"Top Transportation Corp",
    "wof:placetype":"venue"
},
  "geometry": {"coordinates":[-122.824242,49.231503],"type":"Point"}
}