{
  "type": "Feature",
  "properties": {
    "addr:full":"Edgerton AB T0B 1K0",
    "addr:postcode":"t0b 1k0",
    "iso:country":"CA",
    "sg:city":"Edgerton",
    "sg:classifiers":[
        {
            "category":"Wholesale",
            "subcategory":"Chemicals & Plastics",
            "type":"Manufacturing & Wholesale Goods"
        }
    ],
    "sg:phone":"+1 780 755 3734",
    "sg:postcode":"T0B 1K0",
    "sg:province":"AB",
    "sg:tags":[
        "agricultural"
    ],
    "wof:name":"Agricore United",
    "wof:placetype":"venue"
},
  "geometry": {"coordinates":[-110.45450599999999,52.755741],"type":"Point"}
}