{
  "type": "Feature",
  "properties": {
    "iso:country":"CA",
    "sg:address":"4965 Boul Des Laurentides",
    "sg:city":"Laval",
    "sg:classifiers":[
        {
            "category":"Retail",
            "subcategory":"Animal Services",
            "type":"Services"
        }
    ],
    "sg:phone":"+1 450 963 2968",
    "sg:postcode":"H7K 2J6",
    "sg:province":"QC",
    "sg:tags":[
        "pet",
        "grooming",
        "washing"
    ],
    "wof:name":"Centre DE Beaute Animale",
    "wof:placetype":"venue"
},
  "geometry": {"coordinates":[-73.743973,45.619366],"type":"Point"}
}