{
  "type": "Feature",
  "properties": {
    "addr:full":"4726 45A Ave Delta BC V4K 1M6",
    "addr:housenumber":"4726",
    "addr:postcode":"v4k 1m6",
    "addr:street":"45A Ave",
    "iso:country":"CA",
    "sg:address":"4726 45A Ave",
    "sg:city":"Delta",
    "sg:classifiers":[
        {
            "category":"Farming",
            "subcategory":"Farm",
            "type":"Manufacturing & Wholesale Goods"
        }
    ],
    "sg:phone":"+1 604 940 2024",
    "sg:postcode":"V4K 1M6",
    "sg:province":"BC",
    "wof:name":"Delta Farmers Institute",
    "wof:placetype":"venue"
},
  "geometry": {"coordinates":[-123.05961600000001,49.084801],"type":"Point"}
}