{
  "type": "Feature",
  "properties": {
    "iso:country":"CA",
    "sg:address":"4726 45A Ave",
    "sg:city":"Delta",
    "sg:classifiers":[
        {
            "category":"Farming",
            "subcategory":"Farm",
            "type":"Manufacturing & Wholesale Goods"
        }
    ],
    "sg:phone":"+1 604 940 2024",
    "sg:postcode":"V4K 1M6",
    "sg:province":"BC",
    "wof:name":"Delta Farmers Institute",
    "wof:placetype":"venue"
},
  "geometry": {"coordinates":[-123.059616,49.084801],"type":"Point"}
}