{
  "type": "Feature",
  "properties": {
    "addr:full":"409 Centre St Assiniboia SK S0H 0B0",
    "addr:housenumber":"409",
    "addr:postcode":"s0h 0b0",
    "addr:street":"Centre St",
    "iso:country":"CA",
    "sg:address":"409 Centre St",
    "sg:city":"Assiniboia",
    "sg:classifiers":[
        {
            "category":"Home & Garden",
            "subcategory":"Building Materials",
            "type":"Retail Goods"
        }
    ],
    "sg:phone":"+1 306 642 3347",
    "sg:postcode":"S0H 0B0",
    "sg:province":"SK",
    "sg:tags":[
        "cooperative"
    ],
    "wof:name":"Southland CO-OP Assn Ltd",
    "wof:placetype":"venue"
},
  "geometry": {"coordinates":[-105.992431641,49.630821228],"type":"Point"}
}