{
  "type": "Feature",
  "properties": {
    "addr:full":"5200 Robinson St Niagara Falls ON L2G 2A2",
    "addr:housenumber":"5200",
    "addr:postcode":"l2g 2a2",
    "addr:street":"Robinson St",
    "iso:country":"CA",
    "sg:address":"5200 Robinson St",
    "sg:city":"Niagara Falls",
    "sg:classifiers":[
        {
            "category":"Restaurant",
            "type":"Food & Drink"
        }
    ],
    "sg:phone":"+1 905 356 2651",
    "sg:postcode":"L2G 2A2",
    "sg:province":"ON",
    "wof:name":"Skylon Tower",
    "wof:placetype":"venue"
},
  "geometry": {"coordinates":[-79.0797195435,43.0863990784],"type":"Point"}
}