{
  "type": "Feature",
  "properties": {
    "addr:full":"390 Brant St #402 Burlington ON L7R 4J4",
    "addr:housenumber":"390",
    "addr:postcode":"l7r 4j4",
    "addr:street":"Brant St # 402",
    "iso:country":"CA",
    "sg:address":"390 Brant St #402",
    "sg:city":"Burlington",
    "sg:classifiers":[
        {
            "category":"Insurance",
            "subcategory":"Insurance Agent",
            "type":"Services"
        }
    ],
    "sg:phone":"+1 905 631 0500",
    "sg:postcode":"L7R 4J4",
    "sg:province":"ON",
    "sg:tags":[
        "consultant"
    ],
    "wof:name":"Bauman Consulting Inc",
    "wof:placetype":"venue"
},
  "geometry": {"coordinates":[-79.79737854,43.3251838684],"type":"Point"}
}