{
  "type": "Feature",
  "properties": {
    "iso:country":"CA",
    "sg:address":"450 Edinburgh Dr",
    "sg:city":"Moncton",
    "sg:classifiers":[
        {
            "category":"Wholesale",
            "subcategory":"Books, Periodicals, & Newspapers",
            "type":"Manufacturing & Wholesale Goods"
        }
    ],
    "sg:phone":"+1 506 383 4191",
    "sg:postcode":"E1E 2L1",
    "sg:province":"NB",
    "sg:tags":[
        "magazine"
    ],
    "wof:name":"J Mc Nulty Weekley Inc",
    "wof:placetype":"venue"
},
  "geometry": {"coordinates":[-64.8394393921,46.0860671997],"type":"Point"}
}