{
  "type": "Feature",
  "properties": {
    "addr:full":"1100 Boul Cremazie E Montreal QC H2P 2X2",
    "addr:housenumber":"1100",
    "addr:postcode":"h2p 2x2",
    "addr:street":"Boul Cremazie E",
    "iso:country":"CA",
    "sg:address":"1100 Boul Cremazie E",
    "sg:city":"Montreal",
    "sg:classifiers":[
        {
            "category":"Professional",
            "subcategory":"Computer Services",
            "type":"Services"
        }
    ],
    "sg:phone":"+1 514 722 9333",
    "sg:postcode":"H2P 2X2",
    "sg:province":"QC",
    "sg:tags":[
        "information",
        "system",
        "consultant"
    ],
    "wof:name":"Os4 Techno",
    "wof:placetype":"venue"
},
  "geometry": {"coordinates":[-73.62911224370001,45.55027771],"type":"Point"}
}