{
  "type": "Feature",
  "properties": {
    "addr:full":"House 1148 Skownan MB R0L 1Y0",
    "addr:housenumber":"1148",
    "addr:postcode":"r0l 1y0",
    "addr:street":"Skownan",
    "iso:country":"CA",
    "sg:address":"House 1148",
    "sg:city":"Skownan",
    "sg:classifiers":[
        {
            "category":"Organizations",
            "subcategory":"Community Association",
            "type":"Services"
        }
    ],
    "sg:phone":"+1 204 628 3373",
    "sg:postcode":"R0L 1Y0",
    "sg:province":"MB",
    "sg:tags":[
        "native"
    ],
    "wof:name":"Skownan First Nation",
    "wof:placetype":"venue"
},
  "geometry": {"coordinates":[-99.5879058838,51.9892539978],"type":"Point"}
}