{
  "type": "Feature",
  "properties": {
    "addr:full":"7105 Nootka St Powell River BC V8A 5E3",
    "addr:postcode":"7105;v8a 5e3",
    "addr:street":"Nootka St",
    "iso:country":"CA",
    "sg:address":"7105 Nootka St",
    "sg:city":"Powell River",
    "sg:classifiers":[
        {
            "category":"Education",
            "subcategory":"School",
            "type":"Public Place"
        }
    ],
    "sg:phone":"+1 604 485 2756",
    "sg:postcode":"V8A 5E3",
    "sg:province":"BC",
    "wof:name":"Ocean View Middle School",
    "wof:placetype":"venue"
},
  "geometry": {"coordinates":[-124.518852,49.821472],"type":"Point"}
}