{
  "type": "Feature",
  "properties": {
    "addr:full":"4270 Boul Des Forges Trois-Rivieres QC G8Y 1W3",
    "addr:housenumber":"4270",
    "addr:postcode":"g8y 1w3",
    "addr:street":"Boul Des Forges Trois-Rivieres",
    "iso:country":"CA",
    "sg:address":"4270 Boul Des Forges",
    "sg:city":"Trois-Rivieres",
    "sg:classifiers":[
        {
            "category":"Autos & Motor Vehicles",
            "subcategory":"Fuel & Gas Station",
            "type":"Retail Goods"
        }
    ],
    "sg:phone":"+1 819 374 1828",
    "sg:postcode":"G8Y 1W3",
    "sg:province":"QC",
    "sg:tags":[
        "oil"
    ],
    "wof:name":"Olco",
    "wof:placetype":"venue"
},
  "geometry": {"coordinates":[-72.58719600000001,46.357525],"type":"Point"}
}