{
  "type": "Feature",
  "properties": {
    "addr:full":"20 Queens Sq Cambridge ON N1S 1H3",
    "addr:housenumber":"20",
    "addr:postcode":"n1s 1h3",
    "addr:street":"Queens Sq",
    "iso:country":"CA",
    "sg:address":"20 Queens Sq",
    "sg:city":"Cambridge",
    "sg:classifiers":[
        {
            "category":"Shopping",
            "subcategory":"Florist",
            "type":"Retail Goods"
        }
    ],
    "sg:phone":"+1 519 621 5220",
    "sg:postcode":"N1S 1H3",
    "sg:province":"ON",
    "wof:name":"Crosses Flowers Ltd",
    "wof:placetype":"venue"
},
  "geometry": {"coordinates":[-80.310081,43.43145],"type":"Point"}
}