{
  "type": "Feature",
  "properties": {
    "addr:full":"10 Terminal Ave Nanaimo BC V9R 5C3",
    "addr:housenumber":"10",
    "addr:postcode":"v9r 5c3",
    "addr:street":"Terminal Ave",
    "iso:country":"CA",
    "sg:address":"10 Terminal Ave",
    "sg:city":"Nanaimo",
    "sg:classifiers":[
        {
            "category":"Retail",
            "subcategory":"Auto Repair",
            "type":"Services"
        }
    ],
    "sg:phone":"+1 250 741 1700",
    "sg:postcode":"V9R 5C3",
    "sg:province":"BC",
    "sg:tags":[
        "repairing",
        "automobile"
    ],
    "wof:name":"Mr Lube",
    "wof:placetype":"venue"
},
  "geometry": {"coordinates":[-123.940628,49.169975],"type":"Point"}
}