{
  "type": "Feature",
  "properties": {
    "iso:country":"CA",
    "sg:address":"33759 Morey Ave # 1",
    "sg:city":"Abbotsford",
    "sg:classifiers":[
        {
            "category":"Building & Trades",
            "subcategory":"Construction",
            "type":"Services"
        }
    ],
    "sg:phone":"+1 604 859 1430",
    "sg:postcode":"V2S 2W5",
    "sg:province":"BC",
    "sg:tags":[
        "excavating",
        "contractor",
        "general"
    ],
    "wof:name":"Chet Construction Ltd",
    "wof:placetype":"venue"
},
  "geometry": {"coordinates":[-122.290290833,49.0547676086],"type":"Point"}
}