{
  "type": "Feature",
  "properties": {
    "iso:country":"CA",
    "sg:address":"RR 2",
    "sg:city":"Warkworth",
    "sg:classifiers":[
        {
            "category":"Wholesale",
            "subcategory":"Farm Supplies",
            "type":"Manufacturing & Wholesale Goods"
        }
    ],
    "sg:phone":"+1 705 924 3293",
    "sg:postcode":"K0K 3K0",
    "sg:province":"ON",
    "sg:tags":[
        "feed"
    ],
    "wof:name":"Young's Quality Feeds",
    "wof:placetype":"venue"
},
  "geometry": {"coordinates":[-77.8898468018,44.2007331848],"type":"Point"}
}