{
  "type": "Feature",
  "properties": {
    "addr:full":"582 Boul Du Seminaire N Saint-Jean-Sur-Richelieu QC J3B 7E3",
    "addr:housenumber":"582",
    "addr:postcode":"j3b 7e3",
    "addr:street":"Boul Du Seminaire N",
    "iso:country":"CA",
    "sg:address":"582 Boul Du Seminaire N",
    "sg:city":"Saint-Jean-Sur-Richelieu",
    "sg:classifiers":[
        {
            "category":"Home & Garden",
            "subcategory":"Home Furnishings",
            "type":"Retail Goods"
        }
    ],
    "sg:phone":"+1 450 348 4049",
    "sg:postcode":"J3B 7E3",
    "sg:province":"QC",
    "sg:tags":[
        "lighting",
        "fixture"
    ],
    "wof:name":"Eclairage Moderne Saran Inc",
    "wof:placetype":"venue"
},
  "geometry": {"coordinates":[-73.2644042969,45.3181114197],"type":"Point"}
}