{
  "type": "Feature",
  "properties": {
    "addr:full":"Trois-Rivieres QC G8Y 5N6",
    "addr:postcode":"g8y 5n6",
    "iso:country":"CA",
    "sg:city":"Trois-Rivieres",
    "sg:classifiers":[
        {
            "category":"Communications",
            "subcategory":"Television Station",
            "type":"Services"
        }
    ],
    "sg:phone":"+1 819 376 8880",
    "sg:postcode":"G8Y 5N6",
    "sg:province":"QC",
    "sg:tags":[
        "broadcasting",
        "co"
    ],
    "wof:name":"Poste Chem Tv Tele-8",
    "wof:placetype":"venue"
},
  "geometry": {"coordinates":[-72.5777511597,46.3546409607],"type":"Point"}
}