{
  "type": "Feature",
  "properties": {
    "addr:full":"52 Ramblewood Rd Winnipeg MB R3X 1W2",
    "addr:housenumber":"52",
    "addr:postcode":"r3x 1w2",
    "addr:street":"Ramblewood Rd",
    "iso:country":"CA",
    "sg:address":"52 Ramblewood Rd",
    "sg:city":"Winnipeg",
    "sg:classifiers":[
        {
            "category":"Building & Trades",
            "subcategory":"Construction",
            "type":"Services"
        }
    ],
    "sg:phone":"+1 204 255 4890",
    "sg:postcode":"R3X 1W2",
    "sg:province":"MB",
    "sg:tags":[
        "excavating",
        "contractor"
    ],
    "wof:name":"Gauthier Backhoe Svc Ltd",
    "wof:placetype":"venue"
},
  "geometry": {"coordinates":[-97.045502,49.802635],"type":"Point"}
}