{
  "type": "Feature",
  "properties": {
    "addr:full":"805 Main St Biggar SK S0K 0M0",
    "addr:housenumber":"805",
    "addr:postcode":"s0k 0m0",
    "addr:street":"Main St",
    "iso:country":"CA",
    "sg:address":"805 Main St",
    "sg:city":"Biggar",
    "sg:classifiers":[
        {
            "category":"Home & Garden",
            "subcategory":"Building Materials",
            "type":"Retail Goods"
        }
    ],
    "sg:phone":"+1 306 948 2248",
    "sg:postcode":"S0K 0M0",
    "sg:province":"SK",
    "sg:tags":[
        "lumber"
    ],
    "wof:name":"North American Lumber Ltd",
    "wof:placetype":"venue"
},
  "geometry": {"coordinates":[-107.98204,52.06049],"type":"Point"}
}