{
  "type": "Feature",
  "properties": {
    "addr:full":"670 Eglinton Ave E East York ON M4G 2K4",
    "addr:housenumber":"670",
    "addr:postcode":"m4g 2k4",
    "addr:street":"Eglinton Ave E",
    "iso:country":"CA",
    "sg:address":"670 Eglinton Ave E",
    "sg:city":"East York",
    "sg:classifiers":[
        {
            "category":"Organizations",
            "subcategory":"Religious Organization",
            "type":"Services"
        }
    ],
    "sg:phone":"+1 416 422 0510",
    "sg:postcode":"M4G 2K4",
    "sg:province":"ON",
    "sg:tags":[
        "church"
    ],
    "wof:name":"Leaside Presbyterian Church",
    "wof:placetype":"venue"
},
  "geometry": {"coordinates":[-79.372597,43.712139],"type":"Point"}
}