{
  "type": "Feature",
  "properties": {
    "addr:full":"Delta BC V4L 2A6",
    "addr:postcode":"v4l 2a6",
    "iso:country":"CA",
    "sg:city":"Delta",
    "sg:classifiers":[
        {
            "category":"Personal",
            "subcategory":"Beauty Salon",
            "type":"Services"
        }
    ],
    "sg:phone":"+1 604 943 1444",
    "sg:postcode":"V4L 2A6",
    "sg:province":"BC",
    "wof:name":"Fre-Joy of London",
    "wof:placetype":"venue"
},
  "geometry": {"coordinates":[-123.068817139,49.0267524719],"type":"Point"}
}