{
  "type": "Feature",
  "properties": {
    "iso:country":"CA",
    "sg:address":"409 Dundas St W",
    "sg:city":"Belleville",
    "sg:classifiers":[
        {
            "category":"Insurance",
            "subcategory":"Insurance Agent",
            "type":"Services"
        }
    ],
    "sg:phone":"+1 613 968 4576",
    "sg:postcode":"K8P 1B6",
    "sg:province":"ON",
    "wof:name":"Albert Van Reewyk Ins Brokers",
    "wof:placetype":"venue"
},
  "geometry": {"coordinates":[-77.4072570801,44.147228241],"type":"Point"}
}