{
  "type": "Feature",
  "properties": {
    "addr:full":"29 Vaughan Rd Welland ON L3B 5Z7",
    "addr:housenumber":"29",
    "addr:postcode":"l3b 5z7",
    "addr:street":"Vaughan Rd",
    "iso:country":"CA",
    "sg:address":"29 Vaughan Rd",
    "sg:city":"Welland",
    "sg:classifiers":[
        {
            "category":"Retail",
            "subcategory":"Laundry & Dry Cleaning",
            "type":"Services"
        }
    ],
    "sg:phone":"+1 905 732 4222",
    "sg:postcode":"L3B 5Z7",
    "sg:province":"ON",
    "wof:name":"Superior Dust Control & Lndry",
    "wof:placetype":"venue"
},
  "geometry": {"coordinates":[-79.264107,42.964245],"type":"Point"}
}