{
  "type": "Feature",
  "properties": {
    "addr:full":"Pointe-Aux-Outardes QC G0H 1M0",
    "addr:postcode":"g0h 1m0",
    "iso:country":"CA",
    "sg:city":"Pointe-Aux-Outardes",
    "sg:classifiers":[
        {
            "category":"Local Transit",
            "type":"Transportation"
        }
    ],
    "sg:phone":"+1 418 567 8261",
    "sg:postcode":"G0H 1M0",
    "sg:province":"QC",
    "sg:tags":[
        "bus",
        "line"
    ],
    "wof:name":"Autobus Boulay Inc",
    "wof:placetype":"venue"
},
  "geometry": {"coordinates":[-68.402664,49.07859],"type":"Point"}
}