{
  "type": "Feature",
  "properties": {
    "iso:country":"CA",
    "sg:address":"875 Hastings St W",
    "sg:city":"Vancouver",
    "sg:classifiers":[
        {
            "category":"Shopping",
            "subcategory":"Clothing, Apparel, & Fashions",
            "type":"Retail Goods"
        }
    ],
    "sg:phone":"+1 604 682 3991",
    "sg:postcode":"V6C 3N9",
    "sg:province":"BC",
    "sg:tags":[
        "lingerie"
    ],
    "wof:name":"J-Parfait",
    "wof:placetype":"venue"
},
  "geometry": {"coordinates":[-123.115272522,49.286491394],"type":"Point"}
}