{
  "type": "Feature",
  "properties": {
    "addr:full":"1099 Danforth Ave Toronto ON M4J 1M5",
    "addr:housenumber":"1099",
    "addr:postcode":"m4j 1m5",
    "addr:street":"Danforth Ave",
    "iso:country":"CA",
    "sg:address":"1099 Danforth Ave",
    "sg:city":"Toronto",
    "sg:classifiers":[
        {
            "category":"Organizations",
            "subcategory":"Religious Organization",
            "type":"Services"
        }
    ],
    "sg:phone":"+1 416 466 9433",
    "sg:postcode":"M4J 1M5",
    "sg:province":"ON",
    "sg:tags":[
        "church"
    ],
    "wof:name":"Saint Catherine of Siena",
    "wof:placetype":"venue"
},
  "geometry": {"coordinates":[-79.334892,43.680885],"type":"Point"}
}