{
  "type": "Feature",
  "properties": {
    "addr:full":"3940 Rang Saint-Malo Sainte-Marthe-Du-Cap QC G8V 1X9",
    "addr:housenumber":"3940",
    "addr:postcode":"g8v 1x9",
    "addr:street":"Rang Saint-Malo",
    "iso:country":"CA",
    "sg:address":"3940 Rang Saint-Malo",
    "sg:city":"Sainte-Marthe-Du-Cap",
    "sg:classifiers":[
        {
            "category":"Retail",
            "subcategory":"Auto Repair",
            "type":"Services"
        }
    ],
    "sg:phone":"+1 819 378 6391",
    "sg:postcode":"G8V 1X9",
    "sg:province":"QC",
    "sg:tags":[
        "body",
        "automobile",
        "painting"
    ],
    "wof:name":"Garage Medee & Fils Inc",
    "wof:placetype":"venue"
},
  "geometry": {"coordinates":[-72.456619,46.417248],"type":"Point"}
}