{
  "type": "Feature",
  "properties": {
    "addr:full":"6650 Perth Line 88 Gowanstown ON N0G 1Y0",
    "addr:housenumber":"6650",
    "addr:postcode":"n0g 1y0",
    "addr:street":"Perth Line 88",
    "iso:country":"CA",
    "sg:address":"6650 Perth Line 88",
    "sg:city":"Gowanstown",
    "sg:classifiers":[
        {
            "category":"Manufacturing",
            "subcategory":"Metals",
            "type":"Manufacturing & Wholesale Goods"
        }
    ],
    "sg:phone":"+1 519 291 4136",
    "sg:postcode":"N0G 1Y0",
    "sg:province":"ON",
    "sg:tags":[
        "steel"
    ],
    "wof:name":"Behrns Metal Fabricating",
    "wof:placetype":"venue"
},
  "geometry": {"coordinates":[-80.93966674799999,43.7817802429],"type":"Point"}
}