{
  "type": "Feature",
  "properties": {
    "addr:full":"1275 Rue Blanchette Saint-Hyacinthe QC J2S 1J9",
    "addr:housenumber":"1275",
    "addr:postcode":"j2s 1j9",
    "addr:street":"Rue Blanchette",
    "iso:country":"CA",
    "sg:address":"1275 Rue Blanchette",
    "sg:city":"Saint-Hyacinthe",
    "sg:classifiers":[
        {
            "category":"Professional",
            "subcategory":"Employment Agencies",
            "type":"Services"
        }
    ],
    "sg:phone":"+1 450 261 0101",
    "sg:postcode":"J2S 1J9",
    "sg:province":"QC",
    "sg:tags":[
        "opportunity"
    ],
    "wof:name":"Agence DE Placement Helene Roy",
    "wof:placetype":"venue"
},
  "geometry": {"coordinates":[-72.9582290649,45.6336593628],"type":"Point"}
}