{
  "type": "Feature",
  "properties": {
    "addr:full":"6631 Bank St Metcalfe ON K0A 2P0",
    "addr:housenumber":"6631",
    "addr:postcode":"k0a 2p0",
    "addr:street":"Bank St",
    "iso:country":"CA",
    "sg:address":"6631 Bank St",
    "sg:city":"Metcalfe",
    "sg:classifiers":[
        {
            "category":"Social Services",
            "subcategory":"Child Care",
            "type":"Services"
        }
    ],
    "sg:phone":"+1 613 821 5902",
    "sg:postcode":"K0A 2P0",
    "sg:province":"ON",
    "wof:name":"Greely Child Care Ctr",
    "wof:placetype":"venue"
},
  "geometry": {"coordinates":[-75.4986953735,45.231918335],"type":"Point"}
}