{
  "type": "Feature",
  "properties": {
    "iso:country":"CA",
    "sg:city":"Vancouver",
    "sg:classifiers":[
        {
            "category":"Wholesale",
            "subcategory":"Machinery & Supplies",
            "type":"Manufacturing & Wholesale Goods"
        }
    ],
    "sg:phone":"+1 604 688 6244",
    "sg:postcode":"V6C 2T7",
    "sg:province":"BC",
    "sg:tags":[
        "ship",
        "broker"
    ],
    "wof:name":"Simpson Spence & Young",
    "wof:placetype":"venue"
},
  "geometry": {"coordinates":[-123.115372,49.284935],"type":"Point"}
}