{
  "type": "Feature",
  "properties": {
    "iso:country":"CA",
    "sg:city":"Burlington",
    "sg:classifiers":[
        {
            "category":"Manufacturing",
            "subcategory":"Printing",
            "type":"Manufacturing & Wholesale Goods"
        }
    ],
    "sg:phone":"+1 905 333 4132",
    "sg:postcode":"L7L 5Y3",
    "sg:province":"ON",
    "sg:tags":[
        "printer"
    ],
    "wof:name":"Astra Graphics",
    "wof:placetype":"venue"
},
  "geometry": {"coordinates":[-79.76149,43.372913],"type":"Point"}
}