{
  "type": "Feature",
  "properties": {
    "addr:full":"525 London St Winnipeg MB R2K 2Z4",
    "addr:housenumber":"525",
    "addr:postcode":"r2k 2z4",
    "addr:street":"London St",
    "iso:country":"CA",
    "sg:address":"525 London St",
    "sg:city":"Winnipeg",
    "sg:classifiers":[
        {
            "category":"Shopping",
            "subcategory":"Pharmacy",
            "type":"Retail Goods"
        }
    ],
    "sg:phone":"+1 204 669 1267",
    "sg:postcode":"R2K 2Z4",
    "sg:province":"MB",
    "wof:name":"Munroe Pharmacy",
    "wof:placetype":"venue"
},
  "geometry": {"coordinates":[-97.0811462402,49.9117736816],"type":"Point"}
}