{
  "type": "Feature",
  "properties": {
    "addr:full":"683 St Clair Ave W Toronto ON M6C 1A7",
    "addr:housenumber":"683",
    "addr:postcode":"m6c 1a7",
    "addr:street":"St Clair Ave W",
    "iso:country":"CA",
    "sg:address":"683 St Clair Ave W",
    "sg:city":"Toronto",
    "sg:classifiers":[
        {
            "category":"Shopping",
            "subcategory":"Used Merchandise",
            "type":"Retail Goods"
        }
    ],
    "sg:phone":"+1 416 656 9969",
    "sg:postcode":"M6C 1A7",
    "sg:province":"ON",
    "sg:tags":[
        "shop",
        "second",
        "consignment",
        "store",
        "hand"
    ],
    "wof:name":"Twice As Nice",
    "wof:placetype":"venue"
},
  "geometry": {"coordinates":[-79.4254608154,43.6816291809],"type":"Point"}
}