{
  "type": "Feature",
  "properties": {
    "iso:country":"CA",
    "sg:address":"78 Lawrence St",
    "sg:city":"Lunenburg",
    "sg:classifiers":[
        {
            "category":"Shopping",
            "subcategory":"Shoes",
            "type":"Retail Goods"
        }
    ],
    "sg:phone":"+1 902 634 4772",
    "sg:postcode":"B0J 2C0",
    "sg:province":"NS",
    "wof:name":"Naturally Yours-Shoes Greta",
    "wof:placetype":"venue"
},
  "geometry": {"coordinates":[-64.3112411499,44.3795394897],"type":"Point"}
}