{
  "type": "Feature",
  "properties": {
    "iso:country":"CA",
    "sg:address":"5755 11 St SE",
    "sg:city":"Calgary",
    "sg:classifiers":[
        {
            "category":"Wholesale",
            "subcategory":"Machinery & Supplies",
            "type":"Manufacturing & Wholesale Goods"
        }
    ],
    "sg:phone":"+1 403 253 6463",
    "sg:postcode":"T2H 1M7",
    "sg:province":"AB",
    "sg:tags":[
        "equipment",
        "industrial"
    ],
    "wof:name":"Gregg Distributors Ltd",
    "wof:placetype":"venue"
},
  "geometry": {"coordinates":[-114.037475586,51.0040245056],"type":"Point"}
}