{
  "type": "Feature",
  "properties": {
    "addr:full":"1855 Leslie St North York ON M3B 2L9",
    "addr:housenumber":"1855",
    "addr:postcode":"m3b 2l9",
    "addr:street":"Leslie St",
    "iso:country":"CA",
    "sg:address":"1855 Leslie St",
    "sg:city":"North York",
    "sg:classifiers":[
        {
            "category":"Retail",
            "subcategory":"Veterinary Services",
            "type":"Services"
        }
    ],
    "sg:phone":"+1 416 447 8551",
    "sg:postcode":"M3B 2L9",
    "sg:province":"ON",
    "sg:tags":[
        "veterinarian"
    ],
    "wof:name":"Donohue, David DVM",
    "wof:placetype":"venue"
},
  "geometry": {"coordinates":[-79.359711,43.752689],"type":"Point"}
}