{
  "type": "Feature",
  "properties": {
    "addr:full":"134 17 Ave NE Calgary AB T2E 1L6",
    "addr:postcode":"t2e 1l6",
    "addr:street":"134 17 Ave Ne",
    "iso:country":"CA",
    "sg:address":"134 17 Ave NE",
    "sg:city":"Calgary",
    "sg:classifiers":[
        {
            "category":"Personal",
            "subcategory":"Barber",
            "type":"Services"
        }
    ],
    "sg:phone":"+1 403 277 2955",
    "sg:postcode":"T2E 1L6",
    "sg:province":"AB",
    "wof:name":"Blue & White Barber Shop",
    "wof:placetype":"venue"
},
  "geometry": {"coordinates":[-114.061531,51.067997],"type":"Point"}
}