{
  "type": "Feature",
  "properties": {
    "addr:full":"25 Arena St St Isidore ON K0C 2B0",
    "addr:housenumber":"25",
    "addr:postcode":"k0c 2b0",
    "addr:street":"Arena St St",
    "iso:country":"CA",
    "sg:address":"25 Arena St",
    "sg:city":"St Isidore",
    "sg:classifiers":[
        {
            "category":"Education",
            "subcategory":"Library",
            "type":"Public Place"
        }
    ],
    "sg:phone":"+1 613 524 2252",
    "sg:postcode":"K0C 2B0",
    "sg:province":"ON",
    "wof:name":"St Isidore Bibliotheque Pblq",
    "wof:placetype":"venue"
},
  "geometry": {"coordinates":[-74.9058303833,45.3857307434],"type":"Point"}
}