{
  "type": "Feature",
  "properties": {
    "iso:country":"CA",
    "sg:address":"821 17 St SW",
    "sg:city":"Medicine Hat",
    "sg:classifiers":[
        {
            "category":"Home & Garden",
            "subcategory":"Building Materials",
            "type":"Retail Goods"
        }
    ],
    "sg:phone":"+1 403 526 2222",
    "sg:postcode":"T1A 4X9",
    "sg:province":"AB",
    "sg:tags":[
        "mixed",
        "concrete"
    ],
    "wof:name":"Inland Concrete Ltd",
    "wof:placetype":"venue"
},
  "geometry": {"coordinates":[-110.70559692400001,50.0233001709],"type":"Point"}
}