{
  "type": "Feature",
  "properties": {
    "iso:country":"CA",
    "sg:city":"Beloeil",
    "sg:classifiers":[
        {
            "category":"Wholesale",
            "subcategory":"Electrical",
            "type":"Manufacturing & Wholesale Goods"
        }
    ],
    "sg:phone":"+1 450 464 4545",
    "sg:postcode":"J3G 4S5",
    "sg:province":"QC",
    "sg:tags":[
        "coil"
    ],
    "wof:name":"Enersol Inc",
    "wof:placetype":"venue"
},
  "geometry": {"coordinates":[-73.2076187134,45.5748596191],"type":"Point"}
}