{
  "type": "Feature",
  "properties": {
    "iso:country":"CA",
    "sg:city":"Vaudreuil-Dorion",
    "sg:classifiers":[
        {
            "category":"Retail",
            "subcategory":"Auto Repair",
            "type":"Services"
        }
    ],
    "sg:phone":"+1 450 455 1030",
    "sg:postcode":"J7V 2T8",
    "sg:province":"QC",
    "sg:tags":[
        "body",
        "automobile",
        "painting"
    ],
    "wof:name":"Procolor Prestige",
    "wof:placetype":"venue"
},
  "geometry": {"coordinates":[-74.011391,45.377285],"type":"Point"}
}