{
  "type": "Feature",
  "properties": {
    "addr:full":"621 Berford St Wiarton ON N0H 2T0",
    "addr:housenumber":"621",
    "addr:postcode":"n0h 2t0",
    "addr:street":"Berford St",
    "iso:country":"CA",
    "sg:address":"621 Berford St",
    "sg:city":"Wiarton",
    "sg:classifiers":[
        {
            "category":"Food & Beverages",
            "subcategory":"Liquor & Beverages",
            "type":"Retail Goods"
        }
    ],
    "sg:phone":"+1 519 534 5031",
    "sg:postcode":"N0H 2T0",
    "sg:province":"ON",
    "sg:tags":[
        "equipment",
        "beer",
        "wine",
        "supply"
    ],
    "wof:name":"Mister Beer",
    "wof:placetype":"venue"
},
  "geometry": {"coordinates":[-81.140778,44.743919],"type":"Point"}
}