{
  "type": "Feature",
  "properties": {
    "addr:full":"224 Gerrish St Windsor NS B0N 2T0",
    "addr:housenumber":"224",
    "addr:postcode":"b0n 2t0",
    "addr:street":"Gerrish St",
    "iso:country":"CA",
    "sg:address":"224 Gerrish St",
    "sg:city":"Windsor",
    "sg:classifiers":[
        {
            "category":"Restaurant",
            "type":"Food & Drink"
        }
    ],
    "sg:phone":"+1 902 798 4015",
    "sg:postcode":"B0N 2T0",
    "sg:province":"NS",
    "sg:tags":[
        "pizza"
    ],
    "wof:name":"Bella Roma Pizza & Subs",
    "wof:placetype":"venue"
},
  "geometry": {"coordinates":[-64.1326751709,44.9923667908],"type":"Point"}
}