{
  "type": "Feature",
  "properties": {
    "addr:full":"1633 Mountain Rd Moncton NB E1G 1A5",
    "addr:housenumber":"1633",
    "addr:postcode":"e1g 1a5",
    "addr:street":"Mountain Rd",
    "iso:country":"CA",
    "sg:address":"1633 Mountain Rd",
    "sg:city":"Moncton",
    "sg:classifiers":[
        {
            "category":"Building & Trades",
            "subcategory":"Construction",
            "type":"Services"
        }
    ],
    "sg:phone":"+1 506 851 5337",
    "sg:postcode":"E1G 1A5",
    "sg:province":"NB",
    "sg:tags":[
        "contractor"
    ],
    "wof:name":"Hamilton Homes",
    "wof:placetype":"venue"
},
  "geometry": {"coordinates":[-64.8411026001,46.1179847717],"type":"Point"}
}