{
  "type": "Feature",
  "properties": {
    "iso:country":"CA",
    "sg:address":"203 Mountain Rd",
    "sg:city":"Moncton",
    "sg:classifiers":[
        {
            "category":"Health Services",
            "subcategory":"Medical Lab",
            "type":"Services"
        }
    ],
    "sg:phone":"+1 506 858 9914",
    "sg:postcode":"E1C 2L5",
    "sg:province":"NB",
    "wof:name":"Moncton Denture Clinic",
    "wof:placetype":"venue"
},
  "geometry": {"coordinates":[-64.78341674799999,46.0948791504],"type":"Point"}
}