{
  "type": "Feature",
  "properties": {
    "addr:full":"3839 Albert St Regina SK S4S 3R4",
    "addr:housenumber":"3839",
    "addr:postcode":"s4s 3r4",
    "addr:street":"Albert St",
    "iso:country":"CA",
    "sg:address":"3839 Albert St",
    "sg:city":"Regina",
    "sg:classifiers":[
        {
            "category":"Shopping",
            "subcategory":"Clothing, Apparel, & Fashions",
            "type":"Retail Goods"
        }
    ],
    "sg:phone":"+1 306 584 5405",
    "sg:postcode":"S4S 3R4",
    "sg:province":"SK",
    "wof:name":"Rhodas Elegance Again Inc",
    "wof:placetype":"venue"
},
  "geometry": {"coordinates":[-104.617774963,50.4180641174],"type":"Point"}
}