{
  "type": "Feature",
  "properties": {
    "iso:country":"CA",
    "sg:address":"3225 Boul Pitfield",
    "sg:city":"Saint-Laurent",
    "sg:classifiers":[
        {
            "category":"Home & Garden",
            "subcategory":"Garden Supply",
            "type":"Retail Goods"
        }
    ],
    "sg:phone":"+1 514 333 0808",
    "sg:postcode":"H4S 1H3",
    "sg:province":"QC",
    "sg:tags":[
        "equipment",
        "irrigation",
        "system"
    ],
    "wof:name":"Waterwell Irrigation Inc",
    "wof:placetype":"venue"
},
  "geometry": {"coordinates":[-73.75177,45.50032],"type":"Point"}
}