{
  "type": "Feature",
  "properties": {
    "addr:full":"Mississauga ON L5T 2G3",
    "addr:postcode":"l5t 2g3",
    "iso:country":"CA",
    "sg:city":"Mississauga",
    "sg:classifiers":[
        {
            "category":"Banks & Credit Unions",
            "subcategory":"Bank",
            "type":"Services"
        }
    ],
    "sg:phone":"+1 905 670 8292",
    "sg:postcode":"L5T 2G3",
    "sg:province":"ON",
    "sg:tags":[
        "loan"
    ],
    "wof:name":"K P Financial Svc",
    "wof:placetype":"venue"
},
  "geometry": {"coordinates":[-79.669708,43.669182],"type":"Point"}
}