{
  "type": "Feature",
  "properties": {
    "addr:full":"Burnaby BC V5C 6A7",
    "addr:postcode":"v5c 6a7",
    "iso:country":"CA",
    "sg:city":"Burnaby",
    "sg:classifiers":[
        {
            "category":"Building & Trades",
            "subcategory":"Equipment Rental",
            "type":"Services"
        }
    ],
    "sg:phone":"+1 604 293 0202",
    "sg:postcode":"V5C 6A7",
    "sg:province":"BC",
    "sg:tags":[
        "renting",
        "automobile"
    ],
    "wof:name":"Travelers Financial Corp",
    "wof:placetype":"venue"
},
  "geometry": {"coordinates":[-123.011047,49.266106],"type":"Point"}
}