{
  "type": "Feature",
  "properties": {
    "addr:full":"185 Boul Des Cedres Quebec QC G1L 1M8",
    "addr:housenumber":"185",
    "addr:postcode":"g1l 1m8",
    "addr:street":"Boul Des Cedres",
    "iso:country":"CA",
    "sg:address":"185 Boul Des Cedres",
    "sg:city":"Quebec",
    "sg:classifiers":[
        {
            "category":"Manufacturing",
            "subcategory":"Printing",
            "type":"Manufacturing & Wholesale Goods"
        }
    ],
    "sg:phone":"+1 418 628 3606",
    "sg:postcode":"G1L 1M8",
    "sg:province":"QC",
    "sg:tags":[
        "printer"
    ],
    "wof:name":"Formules D'Affaires Modernes",
    "wof:placetype":"venue"
},
  "geometry": {"coordinates":[-71.24969482420001,46.8327026367],"type":"Point"}
}