{
  "type": "Feature",
  "properties": {
    "addr:full":"824 Tecumseh Rd E Windsor ON N8X 2S3",
    "addr:housenumber":"824",
    "addr:postcode":"n8x 2s3",
    "addr:street":"Tecumseh Rd E",
    "iso:country":"CA",
    "sg:address":"824 Tecumseh Rd E",
    "sg:city":"Windsor",
    "sg:classifiers":[
        {
            "category":"Shopping",
            "type":"Retail Goods"
        }
    ],
    "sg:phone":"+1 519 250 7998",
    "sg:postcode":"N8X 2S3",
    "sg:province":"ON",
    "sg:tags":[
        "telephone",
        "cellular"
    ],
    "wof:name":"Rogers At & T Wireless",
    "wof:placetype":"venue"
},
  "geometry": {"coordinates":[-83.0121688843,42.2990760803],"type":"Point"}
}