{
  "type": "Feature",
  "properties": {
    "addr:full":"1356 Fourth Ave St Catharines ON L2R 6P9",
    "addr:housenumber":"1356",
    "addr:postcode":"l2r 6p9",
    "addr:street":"Fourth Ave",
    "iso:country":"CA",
    "sg:address":"1356 Fourth Ave",
    "sg:city":"St Catharines",
    "sg:classifiers":[
        {
            "category":"Building & Trades",
            "subcategory":"Landscaping Services",
            "type":"Services"
        }
    ],
    "sg:phone":"+1 905 682 2260",
    "sg:postcode":"L2R 6P9",
    "sg:province":"ON",
    "sg:tags":[
        "landscape",
        "contractor"
    ],
    "wof:name":"Allcare Landscape",
    "wof:placetype":"venue"
},
  "geometry": {"coordinates":[-79.28876495359999,43.1547317505],"type":"Point"}
}