{
  "type": "Feature",
  "properties": {
    "addr:full":"Hamilton ON L8R 2M1",
    "addr:postcode":"l8r 2m1",
    "iso:country":"CA",
    "sg:city":"Hamilton",
    "sg:classifiers":[
        {
            "category":"Organizations",
            "subcategory":"Community Association",
            "type":"Services"
        }
    ],
    "sg:phone":"+1 905 527 1000",
    "sg:postcode":"L8R 2M1",
    "sg:province":"ON",
    "sg:tags":[
        "club"
    ],
    "wof:name":"Hamilton Army & Navy Veterans",
    "wof:placetype":"venue"
},
  "geometry": {"coordinates":[-79.86348,43.27343],"type":"Point"}
}