{
  "type": "Feature",
  "properties": {
    "addr:full":"5125 50 St Yellowknife NT X1A 1S1",
    "addr:housenumber":"5125",
    "addr:postcode":"x1a 1s1",
    "addr:street":"50 St",
    "iso:country":"CA",
    "sg:address":"5125 50 St",
    "sg:city":"Yellowknife",
    "sg:classifiers":[
        {
            "category":"Government",
            "subcategory":"Office",
            "type":"Public Place"
        }
    ],
    "sg:phone":"+1 867 873 3492",
    "sg:postcode":"X1A 1S1",
    "sg:province":"NT",
    "wof:name":"Aboriginal Business Canada",
    "wof:placetype":"venue"
},
  "geometry": {"coordinates":[-114.367904663,62.4524917603],"type":"Point"}
}