{
  "type": "Feature",
  "properties": {
    "addr:full":"16037 Rang Ste-Marguerite Saint-Antoine QC J7Z 5T4",
    "addr:housenumber":"16037",
    "addr:postcode":"j7z 5t4",
    "addr:street":"Rang Ste-Marguerite Saint-Antoine",
    "iso:country":"CA",
    "sg:address":"16037 Rang Ste-Marguerite",
    "sg:city":"Saint-Antoine",
    "sg:classifiers":[
        {
            "category":"Building & Trades",
            "subcategory":"Construction",
            "type":"Services"
        }
    ],
    "sg:phone":"+1 450 436 5100",
    "sg:postcode":"J7Z 5T4",
    "sg:province":"QC",
    "sg:tags":[
        "concrete",
        "contractor"
    ],
    "wof:name":"Beton Cellulaire Inc",
    "wof:placetype":"venue"
},
  "geometry": {"coordinates":[-73.98266599999999,45.764172],"type":"Point"}
}