{
  "type": "Feature",
  "properties": {
    "addr:full":"3181 Ch Sainte-Foy Sainte-Foy QC G1X 1R3",
    "addr:postcode":"3181;g1x 1r3",
    "addr:street":"Ch Sainte-Foy",
    "iso:country":"CA",
    "sg:address":"3181 Ch Sainte-Foy",
    "sg:city":"Sainte-Foy",
    "sg:classifiers":[
        {
            "category":"Real Estate",
            "subcategory":"Real Estate Agent",
            "type":"Services"
        }
    ],
    "sg:phone":"+1 418 658 5893",
    "sg:postcode":"G1X 1R3",
    "sg:province":"QC",
    "sg:tags":[
        "management"
    ],
    "wof:name":"Fologex Limitee",
    "wof:placetype":"venue"
},
  "geometry": {"coordinates":[-71.291763,46.769211],"type":"Point"}
}