{
  "type": "Feature",
  "properties": {
    "addr:full":"2041 Rue Du Rail Charny QC G6X 1X8",
    "addr:housenumber":"2041",
    "addr:postcode":"g6x 1x8",
    "addr:street":"Rue Du Rail",
    "iso:country":"CA",
    "sg:address":"2041 Rue Du Rail",
    "sg:city":"Charny",
    "sg:classifiers":[
        {
            "category":"Retail",
            "subcategory":"Repair Shop",
            "type":"Services"
        }
    ],
    "sg:phone":"+1 418 832 7549",
    "sg:postcode":"G6X 1X8",
    "sg:province":"QC",
    "sg:tags":[
        "welding"
    ],
    "wof:name":"Soudure Mobile Lb",
    "wof:placetype":"venue"
},
  "geometry": {"coordinates":[-71.276222,46.70845],"type":"Point"}
}