{
  "type": "Feature",
  "properties": {
    "iso:country":"CA",
    "sg:address":"209 Abalone Pl NE",
    "sg:city":"Calgary",
    "sg:classifiers":[
        {
            "category":"Building & Trades",
            "subcategory":"Landscaping Services",
            "type":"Services"
        }
    ],
    "sg:phone":"+1 403 248 5886",
    "sg:postcode":"T2A 6S2",
    "sg:province":"AB",
    "sg:tags":[
        "lawn",
        "maintenance",
        "grounds"
    ],
    "wof:name":"S & J Lawn Care",
    "wof:placetype":"venue"
},
  "geometry": {"coordinates":[-113.928032,51.055607],"type":"Point"}
}