{
  "type": "Feature",
  "properties": {
    "addr:full":"103 Rue Du Foyer N Saint-Pamphile QC G0R 3X0",
    "addr:housenumber":"103",
    "addr:postcode":"g0r 3x0",
    "addr:street":"Rue Du Foyer N",
    "iso:country":"CA",
    "sg:address":"103 Rue Du Foyer N",
    "sg:city":"Saint-Pamphile",
    "sg:classifiers":[
        {
            "category":"Social Services",
            "type":"Services"
        }
    ],
    "sg:phone":"+1 418 356 3399",
    "sg:postcode":"G0R 3X0",
    "sg:province":"QC",
    "sg:tags":[
        "organization",
        "welfare"
    ],
    "wof:name":"Info-Sante Clsc",
    "wof:placetype":"venue"
},
  "geometry": {"coordinates":[-69.78299,46.961025],"type":"Point"}
}