{
  "type": "Feature",
  "properties": {
    "addr:full":"Calgary AB T2P 4K1",
    "addr:postcode":"t2p 4k1",
    "iso:country":"CA",
    "sg:city":"Calgary",
    "sg:classifiers":[
        {
            "category":"Shopping",
            "subcategory":"Clothing, Apparel, & Fashions",
            "type":"Retail Goods"
        }
    ],
    "sg:phone":"+1 403 234 8585",
    "sg:postcode":"T2P 4K1",
    "sg:province":"AB",
    "sg:tags":[
        "furnishing"
    ],
    "wof:name":"Henry Singer Men's Wear",
    "wof:placetype":"venue"
},
  "geometry": {"coordinates":[-114.068489075,51.0455627441],"type":"Point"}
}