{
  "type": "Feature",
  "properties": {
    "addr:full":"257 279 Rte Saint-Lazare-DE-Bellechasse QC G0R 3J0",
    "addr:housenumber":"279",
    "addr:postcode":"g0r 3j0",
    "addr:street":"Rte Saint-Lazare-De-Bellechasse",
    "iso:country":"CA",
    "sg:address":"257 279 Rte",
    "sg:city":"Saint-Lazare-DE-Bellechasse",
    "sg:classifiers":[
        {
            "category":"Manufacturing",
            "subcategory":"Tools & Machinery",
            "type":"Manufacturing & Wholesale Goods"
        }
    ],
    "sg:phone":"+1 418 883 5158",
    "sg:postcode":"G0R 3J0",
    "sg:province":"QC",
    "sg:tags":[
        "maple",
        "sugar"
    ],
    "wof:name":"Equipements D'Erabliere Cdl",
    "wof:placetype":"venue"
},
  "geometry": {"coordinates":[-70.80521400000001,46.654324],"type":"Point"}
}