{
  "type": "Feature",
  "properties": {
    "addr:full":"750 16E Av Pointe-Aux-Trembles QC H1B 3M7",
    "addr:housenumber":"750",
    "addr:postcode":"h1b 3m7",
    "addr:street":"16E Av Pointe-Aux-Trembles",
    "iso:country":"CA",
    "sg:address":"750 16E Av",
    "sg:city":"Pointe-Aux-Trembles",
    "sg:classifiers":[
        {
            "category":"Professional",
            "subcategory":"Accounting & Tax Preparation",
            "type":"Services"
        }
    ],
    "sg:phone":"+1 514 498 2131",
    "sg:postcode":"H1B 3M7",
    "sg:province":"QC",
    "sg:tags":[
        "accountant"
    ],
    "wof:name":"St-Onge, Robert CA",
    "wof:placetype":"venue"
},
  "geometry": {"coordinates":[-73.493011,45.643795],"type":"Point"}
}