{
  "type": "Feature",
  "properties": {
    "addr:full":"North York ON M3J 3K4",
    "addr:postcode":"m3j 3k4",
    "iso:country":"CA",
    "sg:city":"North York",
    "sg:classifiers":[
        {
            "category":"Home & Garden",
            "subcategory":"Garden Supply",
            "type":"Retail Goods"
        }
    ],
    "sg:phone":"+1 416 739 7484",
    "sg:postcode":"M3J 3K4",
    "sg:province":"ON",
    "sg:tags":[
        "sprinkler"
    ],
    "wof:name":"Maple Leaf Irrigation Inc",
    "wof:placetype":"venue"
},
  "geometry": {"coordinates":[-79.48862457280001,43.7784194946],"type":"Point"}
}