{
  "type": "Feature",
  "properties": {
    "addr:full":"126 Scott St Hinton AB T7V 1H2",
    "addr:housenumber":"126",
    "addr:postcode":"t7v 1h2",
    "addr:street":"Scott St",
    "iso:country":"CA",
    "sg:address":"126 Scott St",
    "sg:city":"Hinton",
    "sg:classifiers":[
        {
            "category":"Manufacturing",
            "subcategory":"Tools & Machinery",
            "type":"Manufacturing & Wholesale Goods"
        }
    ],
    "sg:phone":"+1 780 865 4032",
    "sg:postcode":"T7V 1H2",
    "sg:province":"AB",
    "sg:tags":[
        "machine",
        "shop"
    ],
    "wof:name":"Dann's Welding & Machining",
    "wof:placetype":"venue"
},
  "geometry": {"coordinates":[-117.584602356,53.4046897888],"type":"Point"}
}