{
  "type": "Feature",
  "properties": {
    "addr:full":"1061 343 Rte Saint-Ambroise-DE-Kildare QC J0K 1C0",
    "addr:housenumber":"1061",
    "addr:postcode":"j0k 1c0",
    "addr:street":"343 Rte",
    "iso:country":"CA",
    "sg:address":"1061 343 Rte",
    "sg:city":"Saint-Ambroise-DE-Kildare",
    "sg:classifiers":[
        {
            "category":"Autos & Motor Vehicles",
            "subcategory":"Motorcycle Sales",
            "type":"Retail Goods"
        }
    ],
    "sg:phone":"+1 450 756 0069",
    "sg:postcode":"J0K 1C0",
    "sg:province":"QC",
    "sg:tags":[
        "scooter"
    ],
    "wof:name":"Moto Performance Enr",
    "wof:placetype":"venue"
},
  "geometry": {"coordinates":[-73.55443572999999,46.0767784119],"type":"Point"}
}