{
  "type": "Feature",
  "properties": {
    "addr:full":"Cap-Saint-Ignace QC G0R 1H0",
    "addr:postcode":"g0r 1h0",
    "iso:country":"CA",
    "sg:city":"Cap-Saint-Ignace",
    "sg:classifiers":[
        {
            "category":"Restaurant",
            "type":"Food & Drink"
        }
    ],
    "sg:phone":"+1 418 246 5551",
    "sg:postcode":"G0R 1H0",
    "sg:province":"QC",
    "wof:name":"Restaurant Bar 51",
    "wof:placetype":"venue"
},
  "geometry": {"coordinates":[-70.45831298829999,47.038394928],"type":"Point"}
}