{
  "type": "Feature",
  "properties": {
    "addr:full":"Red Deer AB T4N 4H5",
    "addr:postcode":"t4n 4h5",
    "iso:country":"CA",
    "sg:city":"Red Deer",
    "sg:classifiers":[
        {
            "category":"Real Estate",
            "subcategory":"Real Estate Agent",
            "type":"Services"
        }
    ],
    "sg:phone":"+1 403 347 0751",
    "sg:postcode":"T4N 4H5",
    "sg:province":"AB",
    "wof:name":"Berday, Duane",
    "wof:placetype":"venue"
},
  "geometry": {"coordinates":[-113.81609344500001,52.2690925598],"type":"Point"}
}