{
  "type": "Feature",
  "properties": {
    "addr:full":"Vancouver BC V5S 4W2",
    "addr:postcode":"v5s 4w2",
    "iso:country":"CA",
    "sg:city":"Vancouver",
    "sg:classifiers":[
        {
            "category":"Restaurant",
            "type":"Food & Drink"
        }
    ],
    "sg:phone":"+1 604 327 7720",
    "sg:postcode":"V5S 4W2",
    "sg:province":"BC",
    "wof:name":"Tasty Wok",
    "wof:placetype":"venue"
},
  "geometry": {"coordinates":[-123.04119900000001,49.218422],"type":"Point"}
}