{
  "type": "Feature",
  "properties": {
    "addr:full":"1730 Lakeshore Rd W Mississauga ON L5J 1J5",
    "addr:housenumber":"1730",
    "addr:postcode":"l5j 1j5",
    "addr:street":"Lakeshore Rd W",
    "iso:country":"CA",
    "sg:address":"1730 Lakeshore Rd W",
    "sg:city":"Mississauga",
    "sg:classifiers":[
        {
            "category":"Banks & Credit Unions",
            "subcategory":"Bank",
            "type":"Services"
        }
    ],
    "sg:phone":"+1 905 822 1648",
    "sg:postcode":"L5J 1J5",
    "sg:province":"ON",
    "wof:name":"Royal Bank Financial Group",
    "wof:placetype":"venue"
},
  "geometry": {"coordinates":[-79.62262,43.517536],"type":"Point"}
}