{
  "type": "Feature",
  "properties": {
    "addr:full":"605 Av Saint-Louis Saint-Raymond QC G3L 3T7",
    "addr:postcode":"g3l 3t7",
    "addr:street":"605 Av Saint-Louis",
    "iso:country":"CA",
    "sg:address":"605 Av Saint-Louis",
    "sg:city":"Saint-Raymond",
    "sg:classifiers":[
        {
            "category":"Building & Trades",
            "subcategory":"Construction",
            "type":"Services"
        }
    ],
    "sg:phone":"+1 418 337 6842",
    "sg:postcode":"G3L 3T7",
    "sg:province":"QC",
    "sg:tags":[
        "excavating",
        "contractor"
    ],
    "wof:name":"Entreprises Victorin Noreau",
    "wof:placetype":"venue"
},
  "geometry": {"coordinates":[-71.82830800000001,46.893429],"type":"Point"}
}