{
  "type": "Feature",
  "properties": {
    "iso:country":"CA",
    "sg:city":"Richmond",
    "sg:classifiers":[
        {
            "category":"Autos & Motor Vehicles",
            "subcategory":"Auto Supplies",
            "type":"Retail Goods"
        }
    ],
    "sg:phone":"+1 604 278 7986",
    "sg:postcode":"V6V 2W3",
    "sg:province":"BC",
    "sg:tags":[
        "automobile",
        "parts"
    ],
    "wof:name":"Deutsch Tech Motors-Dtm CO",
    "wof:placetype":"venue"
},
  "geometry": {"coordinates":[-122.992622376,49.1692047119],"type":"Point"}
}