{
  "type": "Feature",
  "properties": {
    "addr:full":"Quebec QC G2K 2E4",
    "addr:postcode":"g2k 2e4",
    "iso:country":"CA",
    "sg:city":"Quebec",
    "sg:classifiers":[
        {
            "category":"Parking",
            "type":"Transportation"
        }
    ],
    "sg:phone":"+1 418 628 6852",
    "sg:postcode":"G2K 2E4",
    "sg:province":"QC",
    "sg:tags":[
        "garage"
    ],
    "wof:name":"Gestiparc Inc",
    "wof:placetype":"venue"
},
  "geometry": {"coordinates":[-71.296783,46.83548],"type":"Point"}
}