{
  "type": "Feature",
  "properties": {
    "addr:full":"6276 Hwy 325 RR 5 Bridgewater NS B4V 2W4",
    "addr:housenumber":"6276",
    "addr:postcode":"b4v 2w4",
    "addr:street":"Hwy 325 Rr 5",
    "iso:country":"CA",
    "sg:address":"6276 Hwy 325 RR 5",
    "sg:city":"Bridgewater",
    "sg:classifiers":[
        {
            "category":"Building & Trades",
            "subcategory":"Construction",
            "type":"Services"
        }
    ],
    "sg:phone":"+1 902 685 2974",
    "sg:postcode":"B4V 2W4",
    "sg:province":"NS",
    "sg:tags":[
        "excavating",
        "contractor"
    ],
    "wof:name":"Larry J Beck Excavating Ltd",
    "wof:placetype":"venue"
},
  "geometry": {"coordinates":[-64.523033,44.380497],"type":"Point"}
}