{
  "type": "Feature",
  "properties": {
    "iso:country":"CA",
    "sg:city":"Scarborough",
    "sg:classifiers":[
        {
            "category":"Restaurant",
            "type":"Food & Drink"
        }
    ],
    "sg:phone":"+1 416 291 3892",
    "sg:postcode":"M1V 5B5",
    "sg:province":"ON",
    "wof:name":"South Asia Malaysian Cuisine",
    "wof:placetype":"venue"
},
  "geometry": {"coordinates":[-79.289932,43.809143],"type":"Point"}
}