{
  "type": "Feature",
  "properties": {
    "addr:full":"3119 Muskoka Rd 169 Bala ON P0C 1A0",
    "addr:housenumber":"3119;169",
    "addr:postcode":"p0c 1a0",
    "addr:street":"Muskoka Rd",
    "iso:country":"CA",
    "sg:address":"3119 Muskoka Rd 169",
    "sg:city":"Bala",
    "sg:classifiers":[
        {
            "category":"Shopping",
            "subcategory":"Clothing, Apparel, & Fashions",
            "type":"Retail Goods"
        }
    ],
    "sg:phone":"+1 705 762 0111",
    "sg:postcode":"P0C 1A0",
    "sg:province":"ON",
    "wof:name":"Bala Shoppe",
    "wof:placetype":"venue"
},
  "geometry": {"coordinates":[-79.61457799999999,45.009609],"type":"Point"}
}