{
  "type": "Feature",
  "properties": {
    "addr:full":"1749 Caledonia Ave North Vancouver BC V7G 1T5",
    "addr:housenumber":"1749",
    "addr:postcode":"v7g 1t5",
    "addr:street":"Caledonia Ave",
    "iso:country":"CA",
    "sg:address":"1749 Caledonia Ave",
    "sg:city":"North Vancouver",
    "sg:classifiers":[
        {
            "category":"Banks & Credit Unions",
            "subcategory":"Bank",
            "type":"Services"
        }
    ],
    "sg:phone":"+1 604 871 1007",
    "sg:postcode":"V7G 1T5",
    "sg:province":"BC",
    "sg:tags":[
        "financing"
    ],
    "wof:name":"Westcoast Financing",
    "wof:placetype":"venue"
},
  "geometry": {"coordinates":[-122.952209,49.322411],"type":"Point"}
}