{
  "type": "Feature",
  "properties": {
    "addr:full":"5135 10E Av Montreal QC H1Y 2G5",
    "addr:housenumber":"5135",
    "addr:postcode":"h1y 2g5",
    "addr:street":"10E Av",
    "iso:country":"CA",
    "sg:address":"5135 10E Av",
    "sg:city":"Montreal",
    "sg:classifiers":[
        {
            "category":"Shopping",
            "type":"Retail Goods"
        }
    ],
    "sg:phone":"+1 514 521 5071",
    "sg:postcode":"H1Y 2G5",
    "sg:province":"QC",
    "sg:tags":[
        "orthopedic",
        "appliance"
    ],
    "wof:name":"Ortho Dynamic Inc",
    "wof:placetype":"venue"
},
  "geometry": {"coordinates":[-73.5692825317,45.5492248535],"type":"Point"}
}