{
  "type": "Feature",
  "properties": {
    "addr:full":"230 Av Saint-Jerome Matane QC G4W 3A2",
    "addr:housenumber":"230",
    "addr:postcode":"g4w 3a2",
    "addr:street":"Av Saint-Jerome",
    "iso:country":"CA",
    "sg:address":"230 Av Saint-Jerome",
    "sg:city":"Matane",
    "sg:classifiers":[
        {
            "category":"Restaurant",
            "type":"Food & Drink"
        }
    ],
    "sg:phone":"+1 418 562 7717",
    "sg:postcode":"G4W 3A2",
    "sg:province":"QC",
    "wof:name":"Cantine Des Iles Paul-Andre",
    "wof:placetype":"venue"
},
  "geometry": {"coordinates":[-67.53136444090001,48.8427047729],"type":"Point"}
}