{
  "type": "Feature",
  "properties": {
    "iso:country":"CA",
    "sg:city":"Toronto",
    "sg:classifiers":[
        {
            "category":"Restaurant",
            "type":"Food & Drink"
        }
    ],
    "sg:phone":"+1 416 535 8234",
    "sg:postcode":"M6R 2L6",
    "sg:province":"ON",
    "wof:name":"Ace Restaurant",
    "wof:placetype":"venue"
},
  "geometry": {"coordinates":[-79.4485626221,43.6456031799],"type":"Point"}
}