{
  "type": "Feature",
  "properties": {
    "addr:full":"1341 Billie Bear Rd Huntsville ON P1H 2J6",
    "addr:housenumber":"1341",
    "addr:postcode":"p1h 2j6",
    "addr:street":"Billie Bear Rd",
    "iso:country":"CA",
    "sg:address":"1341 Billie Bear Rd",
    "sg:city":"Huntsville",
    "sg:classifiers":[
        {
            "category":"Travel",
            "subcategory":"Hotels & Motels",
            "type":"Entertainment"
        }
    ],
    "sg:phone":"+1 705 635 1330",
    "sg:postcode":"P1H 2J6",
    "sg:province":"ON",
    "sg:tags":[
        "resort"
    ],
    "wof:name":"Billie Bear Lakeside Community",
    "wof:placetype":"venue"
},
  "geometry": {"coordinates":[-79.218002,45.326565],"type":"Point"}
}