{
  "type": "Feature",
  "properties": {
    "addr:full":"107 1st Ave E Oyen AB T0J 2J0",
    "addr:housenumber":"107",
    "addr:postcode":"t0j 2j0",
    "addr:street":"1St Ave E Oyen",
    "iso:country":"CA",
    "sg:address":"107 1st Ave E",
    "sg:city":"Oyen",
    "sg:classifiers":[
        {
            "category":"Food & Beverages",
            "subcategory":"Groceries & Convenience Stores",
            "type":"Retail Goods"
        }
    ],
    "sg:phone":"+1 403 664 3945",
    "sg:postcode":"T0J 2J0",
    "sg:province":"AB",
    "sg:tags":[
        "grocer"
    ],
    "wof:name":"Oyen Shop Easy",
    "wof:placetype":"venue"
},
  "geometry": {"coordinates":[-110.48326900000001,51.354721],"type":"Point"}
}