{
  "type": "Feature",
  "properties": {
    "addr:full":"543 Front St Quesnel BC V2J 2K7",
    "addr:housenumber":"543",
    "addr:postcode":"v2j 2k7",
    "addr:street":"Front St",
    "iso:country":"CA",
    "sg:address":"543 Front St",
    "sg:city":"Quesnel",
    "sg:classifiers":[
        {
            "category":"Health Services",
            "subcategory":"Clinic",
            "type":"Services"
        }
    ],
    "sg:phone":"+1 250 992 1002",
    "sg:postcode":"V2J 2K7",
    "sg:province":"BC",
    "wof:name":"Lifeline",
    "wof:placetype":"venue"
},
  "geometry": {"coordinates":[-122.49891700000001,52.980972],"type":"Point"}
}