{
  "type": "Feature",
  "properties": {
    "addr:full":"1200 Boul Firestone Joliette QC J6E 2W5",
    "addr:housenumber":"1200",
    "addr:postcode":"j6e 2w5",
    "addr:street":"Boul Firestone",
    "iso:country":"CA",
    "sg:address":"1200 Boul Firestone",
    "sg:city":"Joliette",
    "sg:classifiers":[
        {
            "category":"Building & Trades",
            "subcategory":"Construction",
            "type":"Services"
        }
    ],
    "sg:phone":"+1 450 759 1666",
    "sg:postcode":"J6E 2W5",
    "sg:province":"QC",
    "sg:tags":[
        "contractor",
        "general",
        "mechanical"
    ],
    "wof:name":"Mecanique Bec Inc",
    "wof:placetype":"venue"
},
  "geometry": {"coordinates":[-73.4226760864,46.0345077515],"type":"Point"}
}