{
  "type": "Feature",
  "properties": {
    "addr:full":"10447 Yonge St Richmond Hill ON L4C 3C2",
    "addr:housenumber":"10447",
    "addr:postcode":"l4c 3c2",
    "addr:street":"Yonge St",
    "iso:country":"CA",
    "sg:address":"10447 Yonge St",
    "sg:city":"Richmond Hill",
    "sg:classifiers":[
        {
            "category":"Restaurant",
            "type":"Food & Drink"
        }
    ],
    "sg:phone":"+1 905 884 3017",
    "sg:postcode":"L4C 3C2",
    "sg:province":"ON",
    "sg:tags":[
        "sandwich"
    ],
    "wof:name":"Mr Submarine",
    "wof:placetype":"venue"
},
  "geometry": {"coordinates":[-79.439598,43.882263],"type":"Point"}
}