{
  "type": "Feature",
  "properties": {
    "iso:country":"CA",
    "sg:city":"Woodbridge",
    "sg:classifiers":[
        {
            "category":"Health Services",
            "subcategory":"Doctor",
            "type":"Services"
        }
    ],
    "sg:phone":"+1 905 850 9099",
    "sg:postcode":"L4L 5X4",
    "sg:province":"ON",
    "sg:tags":[
        "dentist"
    ],
    "wof:name":"Today's Family Dental Ctr",
    "wof:placetype":"venue"
},
  "geometry": {"coordinates":[-79.5667266846,43.7843399048],"type":"Point"}
}