{
  "type": "Feature",
  "properties": {
    "iso:country":"CA",
    "sg:address":"21 Mobile Dr",
    "sg:city":"North York",
    "sg:classifiers":[
        {
            "category":"Retail",
            "subcategory":"Laundry & Dry Cleaning",
            "type":"Services"
        }
    ],
    "sg:phone":"+1 416 751 7676",
    "sg:postcode":"M4A 1H5",
    "sg:province":"ON",
    "sg:tags":[
        "cleaners",
        "rug",
        "carpet"
    ],
    "wof:name":"Babayan's",
    "wof:placetype":"venue"
},
  "geometry": {"coordinates":[-79.3157577515,43.7249183655],"type":"Point"}
}