{
  "type": "Feature",
  "properties": {
    "addr:full":"97 King St Woodville ON K0M 2T0",
    "addr:housenumber":"97",
    "addr:postcode":"k0m 2t0",
    "addr:street":"King St",
    "iso:country":"CA",
    "sg:address":"97 King St",
    "sg:city":"Woodville",
    "sg:classifiers":[
        {
            "category":"Restaurant",
            "type":"Food & Drink"
        }
    ],
    "sg:phone":"+1 705 439 2723",
    "sg:postcode":"K0M 2T0",
    "sg:province":"ON",
    "wof:name":"Brick Oven",
    "wof:placetype":"venue"
},
  "geometry": {"coordinates":[-78.99025726319999,44.3978805542],"type":"Point"}
}