{
  "type": "Feature",
  "properties": {
    "addr:full":"161 6 Ave Cochrane ON P0L 1C0",
    "addr:housenumber":"161",
    "addr:postcode":"p0l 1c0",
    "addr:street":"6 Ave",
    "iso:country":"CA",
    "sg:address":"161 6 Ave",
    "sg:city":"Cochrane",
    "sg:classifiers":[
        {
            "category":"Education",
            "subcategory":"Special Training",
            "type":"Public Place"
        }
    ],
    "sg:phone":"+1 705 272 3513",
    "sg:postcode":"P0L 1C0",
    "sg:province":"ON",
    "sg:tags":[
        "program"
    ],
    "wof:name":"Au Pied DE LA Lettre",
    "wof:placetype":"venue"
},
  "geometry": {"coordinates":[-81.02514600000001,49.062786],"type":"Point"}
}