{
  "type": "Feature",
  "properties": {
    "iso:country":"CA",
    "sg:address":"5 Russell St",
    "sg:city":"Binscarth",
    "sg:classifiers":[
        {
            "category":"Travel",
            "subcategory":"Hotels & Motels",
            "type":"Entertainment"
        }
    ],
    "sg:phone":"+1 204 532 2459",
    "sg:postcode":"R0J 0G0",
    "sg:province":"MB",
    "wof:name":"Binscarth 580 Hotel",
    "wof:placetype":"venue"
},
  "geometry": {"coordinates":[-101.27755737299999,50.6236915588],"type":"Point"}
}