{
  "type": "Feature",
  "properties": {
    "addr:full":"459 Ch Pierre-Peladeau Sainte-Adele QC J8B 1Z3",
    "addr:housenumber":"459",
    "addr:postcode":"j8b 1z3",
    "addr:street":"Ch Pierre-Peladeau Sainte-Adele",
    "iso:country":"CA",
    "sg:address":"459 Ch Pierre-Peladeau",
    "sg:city":"Sainte-Adele",
    "sg:classifiers":[
        {
            "category":"Manufacturing",
            "subcategory":"Pet Food",
            "type":"Manufacturing & Wholesale Goods"
        }
    ],
    "sg:phone":"+1 450 229 3030",
    "sg:postcode":"J8B 1Z3",
    "sg:province":"QC",
    "sg:tags":[
        "cat",
        "dog",
        "supply"
    ],
    "wof:name":"Moulees Du Nord Inc",
    "wof:placetype":"venue"
},
  "geometry": {"coordinates":[-74.133759,45.952869],"type":"Point"}
}