{
  "type": "Feature",
  "properties": {
    "iso:country":"CA",
    "sg:address":"4032 Rue Arthur-Champoux",
    "sg:city":"Montreal-Nord",
    "sg:classifiers":[
        {
            "category":"Social Services",
            "subcategory":"Child Care",
            "type":"Services"
        }
    ],
    "sg:phone":"+1 514 322 4314",
    "sg:postcode":"H1H 1S1",
    "sg:province":"QC",
    "wof:name":"Garderie Les Hirondelles Inc",
    "wof:placetype":"venue"
},
  "geometry": {"coordinates":[-73.6411743164,45.5929908752],"type":"Point"}
}