{
  "type": "Feature",
  "properties": {
    "addr:full":"555 90E Rue Saint-Georges QC G5Y 3L1",
    "addr:housenumber":"555",
    "addr:postcode":"g5y 3l1",
    "addr:street":"90E Rue",
    "iso:country":"CA",
    "sg:address":"555 90E Rue",
    "sg:city":"Saint-Georges",
    "sg:classifiers":[
        {
            "category":"Shopping",
            "subcategory":"Clothing, Apparel, & Fashions",
            "type":"Retail Goods"
        }
    ],
    "sg:phone":"+1 418 227 0499",
    "sg:postcode":"G5Y 3L1",
    "sg:province":"QC",
    "sg:tags":[
        "item",
        "boutique"
    ],
    "wof:name":"Boutique Nuance Bjs Inc",
    "wof:placetype":"venue"
},
  "geometry": {"coordinates":[-70.693459,46.132408],"type":"Point"}
}