{
  "type": "Feature",
  "properties": {
    "addr:full":"PO Box 46 Mine Centre ON P0W 1H0",
    "addr:housenumber":"po box 46",
    "addr:postcode":"p0w 1h0",
    "iso:country":"CA",
    "sg:address":"PO Box 46",
    "sg:city":"Mine Centre",
    "sg:classifiers":[
        {
            "category":"Building & Trades",
            "subcategory":"Construction",
            "type":"Services"
        }
    ],
    "sg:phone":"+1 807 599 2770",
    "sg:postcode":"P0W 1H0",
    "sg:province":"ON",
    "sg:tags":[
        "contractor"
    ],
    "wof:name":"Mine Centre Builders",
    "wof:placetype":"venue"
},
  "geometry": {"coordinates":[-92.640602,48.760971],"type":"Point"}
}