{
  "type": "Feature",
  "properties": {
    "addr:full":"72 Orphans Home Rd Bridgewater NS B4V 3J5",
    "addr:housenumber":"72",
    "addr:postcode":"b4v 3j5",
    "addr:street":"Orphans Home Rd",
    "iso:country":"CA",
    "sg:address":"72 Orphans Home Rd",
    "sg:city":"Bridgewater",
    "sg:classifiers":[
        {
            "category":"Freight",
            "type":"Transportation"
        }
    ],
    "sg:phone":"+1 902 543 2586",
    "sg:postcode":"B4V 3J5",
    "sg:province":"NS",
    "sg:tags":[
        "trucking"
    ],
    "wof:name":"Leroy Whynot General Trucking",
    "wof:placetype":"venue"
},
  "geometry": {"coordinates":[-64.523033,44.380497],"type":"Point"}
}