{
  "type": "Feature",
  "properties": {
    "iso:country":"CA",
    "sg:city":"Dryden",
    "sg:classifiers":[
        {
            "category":"Restaurant",
            "type":"Food & Drink"
        }
    ],
    "sg:phone":"+1 807 223 7411",
    "sg:postcode":"P8N 1Z3",
    "sg:province":"ON",
    "wof:name":"Hong Kong House",
    "wof:placetype":"venue"
},
  "geometry": {"coordinates":[-92.8390579224,49.7839279175],"type":"Point"}
}