{
  "type": "Feature",
  "properties": {
    "addr:full":"1 Cotter's Drung Carbonear NL A1Y 1A1",
    "addr:housenumber":"1",
    "addr:postcode":"a1y 1a1",
    "addr:street":"Cotter'S Drung",
    "iso:country":"CA",
    "sg:address":"1 Cotter's Drung",
    "sg:city":"Carbonear",
    "sg:classifiers":[
        {
            "category":"Building & Trades",
            "subcategory":"Construction",
            "type":"Services"
        }
    ],
    "sg:phone":"+1 709 596 2084",
    "sg:postcode":"A1Y 1A1",
    "sg:province":"NL",
    "sg:tags":[
        "roofing",
        "contractor",
        "general"
    ],
    "wof:name":"Conception Bay Roofing Ltd",
    "wof:placetype":"venue"
},
  "geometry": {"coordinates":[-53.2295,47.736382],"type":"Point"}
}