{
  "type": "Feature",
  "properties": {
    "addr:full":"Mississauga ON L5T 1X3",
    "addr:postcode":"l5t 1x3",
    "iso:country":"CA",
    "sg:city":"Mississauga",
    "sg:classifiers":[
        {
            "category":"Professional",
            "subcategory":"Art Services",
            "type":"Services"
        }
    ],
    "sg:phone":"+1 905 795 9025",
    "sg:postcode":"L5T 1X3",
    "sg:province":"ON",
    "sg:tags":[
        "graphic",
        "designer"
    ],
    "wof:name":"Dpi Graphics Group Inc",
    "wof:placetype":"venue"
},
  "geometry": {"coordinates":[-79.66289500000001,43.64946],"type":"Point"}
}