{
  "type": "Feature",
  "properties": {
    "addr:full":"84 1st Ave S Chesley ON N0G 1L0",
    "addr:housenumber":"84",
    "addr:postcode":"n0g 1l0",
    "addr:street":"1St Ave S Chesley",
    "iso:country":"CA",
    "sg:address":"84 1st Ave S",
    "sg:city":"Chesley",
    "sg:classifiers":[
        {
            "category":"Professional",
            "subcategory":"Lawyer & Legal Services",
            "type":"Services"
        }
    ],
    "sg:phone":"+1 519 363 3223",
    "sg:postcode":"N0G 1L0",
    "sg:province":"ON",
    "sg:tags":[
        "attorney"
    ],
    "wof:name":"Loucks, Peter E",
    "wof:placetype":"venue"
},
  "geometry": {"coordinates":[-81.095444,44.298103],"type":"Point"}
}