{
  "type": "Feature",
  "properties": {
    "addr:full":"31 Craig St Brampton ON L6Y 1J2",
    "addr:housenumber":"31",
    "addr:postcode":"l6y 1j2",
    "addr:street":"Craig St",
    "iso:country":"CA",
    "sg:address":"31 Craig St",
    "sg:city":"Brampton",
    "sg:classifiers":[
        {
            "category":"Education",
            "subcategory":"School",
            "type":"Public Place"
        }
    ],
    "sg:phone":"+1 905 451 2515",
    "sg:postcode":"L6Y 1J2",
    "sg:province":"ON",
    "wof:name":"Mc Hugh Public School",
    "wof:placetype":"venue"
},
  "geometry": {"coordinates":[-79.759079,43.680317],"type":"Point"}
}