{
  "type": "Feature",
  "properties": {
    "addr:full":"431 Brant St Burlington ON L7R 2G3",
    "addr:housenumber":"431",
    "addr:postcode":"l7r 2g3",
    "addr:street":"Brant St",
    "iso:country":"CA",
    "sg:address":"431 Brant St",
    "sg:city":"Burlington",
    "sg:classifiers":[
        {
            "category":"Insurance",
            "subcategory":"Insurance Agent",
            "type":"Services"
        }
    ],
    "sg:phone":"+1 905 634 5549",
    "sg:postcode":"L7R 2G3",
    "sg:province":"ON",
    "wof:name":"Russell, Bruce",
    "wof:placetype":"venue"
},
  "geometry": {"coordinates":[-79.798439,43.326294],"type":"Point"}
}