{
  "type": "Feature",
  "properties": {
    "iso:country":"CA",
    "sg:city":"Saint-Guillaume",
    "sg:classifiers":[
        {
            "category":"Home & Garden",
            "subcategory":"Building Materials",
            "type":"Retail Goods"
        }
    ],
    "sg:phone":"+1 819 396 2279",
    "sg:postcode":"J0C 1L0",
    "sg:province":"QC",
    "sg:tags":[
        "door"
    ],
    "wof:name":"Menuiserie Victorienne",
    "wof:placetype":"venue"
},
  "geometry": {"coordinates":[-72.7613601685,45.8855133057],"type":"Point"}
}