{
  "type": "Feature",
  "properties": {
    "iso:country":"CA",
    "sg:city":"London",
    "sg:classifiers":[
        {
            "category":"Professional",
            "subcategory":"Computer Services",
            "type":"Services"
        }
    ],
    "sg:phone":"+1 519 641 3881",
    "sg:postcode":"N6H 5L7",
    "sg:province":"ON",
    "wof:name":"Bolen Distributing Inc",
    "wof:placetype":"venue"
},
  "geometry": {"coordinates":[-81.335464,42.999569],"type":"Point"}
}