{
  "type": "Feature",
  "properties": {
    "addr:full":"58 Mcguiness Dr Brantford ON N3T 6N5",
    "addr:housenumber":"58",
    "addr:postcode":"n3t 6n5",
    "addr:street":"Mcguiness Dr",
    "iso:country":"CA",
    "sg:address":"58 Mcguiness Dr",
    "sg:city":"Brantford",
    "sg:classifiers":[
        {
            "category":"Building & Trades",
            "subcategory":"Cleaning & Sanitation",
            "type":"Services"
        }
    ],
    "sg:phone":"+1 519 756 6672",
    "sg:postcode":"N3T 6N5",
    "sg:province":"ON",
    "sg:tags":[
        "janitor"
    ],
    "wof:name":"Your Way Out Cleaning Svc",
    "wof:placetype":"venue"
},
  "geometry": {"coordinates":[-80.29866,43.125538],"type":"Point"}
}