{
  "type": "Feature",
  "properties": {
    "iso:country":"CA",
    "sg:address":"1933 Regent St",
    "sg:city":"Sudbury",
    "sg:classifiers":[
        {
            "category":"Shopping",
            "subcategory":"Clothing, Apparel, & Fashions",
            "type":"Retail Goods"
        }
    ],
    "sg:phone":"+1 705 522 2314",
    "sg:postcode":"P3E 5R2",
    "sg:province":"ON",
    "wof:name":"Smart Set",
    "wof:placetype":"venue"
},
  "geometry": {"coordinates":[-81.001572,46.450874],"type":"Point"}
}