{
  "type": "Feature",
  "properties": {
    "iso:country":"CA",
    "sg:address":"6580 Rue Magloire",
    "sg:city":"Saint-Leonard",
    "sg:classifiers":[
        {
            "category":"Manufacturing",
            "subcategory":"Tools & Machinery",
            "type":"Manufacturing & Wholesale Goods"
        }
    ],
    "sg:phone":"+1 514 323 2470",
    "sg:postcode":"H1P 1N9",
    "sg:province":"QC",
    "sg:tags":[
        "machine",
        "shop"
    ],
    "wof:name":"J E Poulin Inc",
    "wof:placetype":"venue"
},
  "geometry": {"coordinates":[-73.585251,45.597942],"type":"Point"}
}