{
  "type": "Feature",
  "properties": {
    "addr:full":"70 Montreal Rd Vanier ON K1L 6E7",
    "addr:housenumber":"70",
    "addr:postcode":"k1l 6e7",
    "addr:street":"Montreal Rd",
    "iso:country":"CA",
    "sg:address":"70 Montreal Rd",
    "sg:city":"Vanier",
    "sg:classifiers":[
        {
            "category":"Recreation",
            "type":"Entertainment"
        }
    ],
    "sg:phone":"+1 613 747 6878",
    "sg:postcode":"K1L 6E7",
    "sg:province":"ON",
    "sg:tags":[
        "bingo",
        "game"
    ],
    "wof:name":"Friends' Bingo Hall",
    "wof:placetype":"venue"
},
  "geometry": {"coordinates":[-75.66785400000001,45.433517],"type":"Point"}
}