{
  "type": "Feature",
  "properties": {
    "iso:country":"CA",
    "sg:address":"70 Montreal Rd",
    "sg:city":"Vanier",
    "sg:classifiers":[
        {
            "category":"Recreation",
            "type":"Entertainment"
        }
    ],
    "sg:phone":"+1 613 747 6878",
    "sg:postcode":"K1L 6E7",
    "sg:province":"ON",
    "sg:tags":[
        "bingo",
        "game"
    ],
    "wof:name":"Friends' Bingo Hall",
    "wof:placetype":"venue"
},
  "geometry": {"coordinates":[-75.667854,45.433517],"type":"Point"}
}