{
  "type": "Feature",
  "properties": {
    "addr:full":"39450 Equity Mine Rd Houston BC V0J 1Z0",
    "addr:housenumber":"39450",
    "addr:postcode":"v0j 1z0",
    "addr:street":"Equity Mine Rd",
    "iso:country":"CA",
    "sg:address":"39450 Equity Mine Rd",
    "sg:city":"Houston",
    "sg:classifiers":[
        {
            "category":"Mining & Drilling",
            "type":"Manufacturing & Wholesale Goods"
        }
    ],
    "sg:phone":"+1 250 845 7799",
    "sg:postcode":"V0J 1Z0",
    "sg:province":"BC",
    "sg:tags":[
        "company"
    ],
    "wof:name":"Equity Silver Mines Ltd",
    "wof:placetype":"venue"
},
  "geometry": {"coordinates":[-126.61245,54.381798],"type":"Point"}
}