{
  "type": "Feature",
  "properties": {
    "addr:full":"1976 Northwest Rd Block House NS B0J 1E0",
    "addr:housenumber":"1976",
    "addr:postcode":"ns b0j 1e0",
    "addr:street":"Northwest Rd Block",
    "iso:country":"CA",
    "sg:address":"1976 Northwest Rd",
    "sg:city":"Block House",
    "sg:classifiers":[
        {
            "category":"Building & Trades",
            "subcategory":"Construction",
            "type":"Services"
        }
    ],
    "sg:phone":"+1 902 624 9844",
    "sg:postcode":"B0J 1E0",
    "sg:province":"NS",
    "sg:tags":[
        "excavating",
        "contractor"
    ],
    "wof:name":"Langille's Excavation Ltd",
    "wof:placetype":"venue"
},
  "geometry": {"coordinates":[-64.413177,44.447639],"type":"Point"}
}