{
  "type": "Feature",
  "properties": {
    "addr:full":"24 Ch DE LA Savane Gatineau QC J8T 1P7",
    "addr:housenumber":"24",
    "addr:postcode":"j8t 1p7",
    "addr:street":"Ch De La Savane",
    "iso:country":"CA",
    "sg:address":"24 Ch DE LA Savane",
    "sg:city":"Gatineau",
    "sg:classifiers":[
        {
            "category":"Food & Beverages",
            "subcategory":"Groceries & Convenience Stores",
            "type":"Retail Goods"
        }
    ],
    "sg:phone":"+1 819 561 2194",
    "sg:postcode":"J8T 1P7",
    "sg:province":"QC",
    "sg:tags":[
        "grocer"
    ],
    "wof:name":"Wooherta Canada Inc",
    "wof:placetype":"venue"
},
  "geometry": {"coordinates":[-75.704697,45.47353],"type":"Point"}
}