{
  "type": "Feature",
  "properties": {
    "addr:full":"116 Leonard Dr Sussex NB E4E 2R1",
    "addr:housenumber":"116",
    "addr:postcode":"e4e 2r1",
    "addr:street":"Leonard Dr",
    "iso:country":"CA",
    "sg:address":"116 Leonard Dr",
    "sg:city":"Sussex",
    "sg:classifiers":[
        {
            "category":"Autos & Motor Vehicles",
            "subcategory":"Auto Supplies",
            "type":"Retail Goods"
        }
    ],
    "sg:phone":"+1 506 433 2166",
    "sg:postcode":"E4E 2R1",
    "sg:province":"NB",
    "sg:tags":[
        "tire"
    ],
    "wof:name":"Sussex Tire Svc Ltd",
    "wof:placetype":"venue"
},
  "geometry": {"coordinates":[-65.494865,45.725739],"type":"Point"}
}