{
  "type": "Feature",
  "properties": {
    "addr:full":"822 Main St E Hamilton ON L8M 1L6",
    "addr:housenumber":"822",
    "addr:postcode":"l8m 1l6",
    "addr:street":"Main St E",
    "iso:country":"CA",
    "sg:address":"822 Main St E",
    "sg:city":"Hamilton",
    "sg:classifiers":[
        {
            "category":"Retail",
            "subcategory":"Laundry & Dry Cleaning",
            "type":"Services"
        }
    ],
    "sg:phone":"+1 905 545 3911",
    "sg:postcode":"L8M 1L6",
    "sg:province":"ON",
    "sg:tags":[
        "cleaners"
    ],
    "wof:name":"Hicks Furs Ltd",
    "wof:placetype":"venue"
},
  "geometry": {"coordinates":[-79.836730957,43.2467193604],"type":"Point"}
}