{
  "type": "Feature",
  "properties": {
    "addr:full":"3986 Rue Saint-Urbain Montreal QC H2W 1T7",
    "addr:housenumber":"3986",
    "addr:postcode":"h2w 1t7",
    "addr:street":"Rue Saint-Urbain",
    "iso:country":"CA",
    "sg:address":"3986 Rue Saint-Urbain",
    "sg:city":"Montreal",
    "sg:classifiers":[
        {
            "category":"Professional",
            "subcategory":"Research",
            "type":"Services"
        }
    ],
    "sg:phone":"+1 514 288 1402",
    "sg:postcode":"H2W 1T7",
    "sg:province":"QC",
    "sg:tags":[
        "environmental",
        "ecological",
        "association"
    ],
    "wof:name":"Eco-Quartier Jeanne Mance",
    "wof:placetype":"venue"
},
  "geometry": {"coordinates":[-73.58010101319999,45.5154190063],"type":"Point"}
}