{
  "type": "Feature",
  "properties": {
    "addr:full":"388 Coxe Blvd Milton ON L9T 4J5",
    "addr:housenumber":"388",
    "addr:postcode":"l9t 4j5",
    "addr:street":"Coxe Blvd",
    "iso:country":"CA",
    "sg:address":"388 Coxe Blvd",
    "sg:city":"Milton",
    "sg:classifiers":[
        {
            "category":"Professional",
            "subcategory":"Computer Services",
            "type":"Services"
        }
    ],
    "sg:phone":"+1 905 875 2895",
    "sg:postcode":"L9T 4J5",
    "sg:province":"ON",
    "sg:tags":[
        "consultant",
        "designer"
    ],
    "wof:name":"R Caswell & Assoc Inc",
    "wof:placetype":"venue"
},
  "geometry": {"coordinates":[-79.859627,43.51815],"type":"Point"}
}