{
  "type": "Feature",
  "properties": {
    "addr:full":"1509 Burger Rd Christina Lake BC V0H 1E0",
    "addr:housenumber":"1509",
    "addr:postcode":"v0h 1e0",
    "addr:street":"Burger Rd",
    "iso:country":"CA",
    "sg:address":"1509 Burger Rd",
    "sg:city":"Christina Lake",
    "sg:classifiers":[
        {
            "category":"Professional",
            "subcategory":"Engineering",
            "type":"Services"
        }
    ],
    "sg:phone":"+1 250 447 6272",
    "sg:postcode":"V0H 1E0",
    "sg:province":"BC",
    "sg:tags":[
        "engineer"
    ],
    "wof:name":"Arbortec Design Svc Ltd",
    "wof:placetype":"venue"
},
  "geometry": {"coordinates":[-118.21767425500001,49.0364532471],"type":"Point"}
}