{
  "type": "Feature",
  "properties": {
    "iso:country":"CA",
    "sg:address":"4637 2nd Ave N",
    "sg:city":"Regina",
    "sg:classifiers":[
        {
            "category":"Food & Beverages",
            "subcategory":"Groceries & Convenience Stores",
            "type":"Retail Goods"
        }
    ],
    "sg:phone":"+1 306 543 4778",
    "sg:postcode":"S4R 0Y6",
    "sg:province":"SK",
    "sg:tags":[
        "grocer"
    ],
    "wof:name":"Manna Confectionery",
    "wof:placetype":"venue"
},
  "geometry": {"coordinates":[-104.647308,50.472179],"type":"Point"}
}