{
  "type": "Feature",
  "properties": {
    "iso:country":"CA",
    "sg:city":"Quesnel",
    "sg:classifiers":[
        {
            "category":"Restaurant",
            "type":"Food & Drink"
        }
    ],
    "sg:phone":"+1 250 992 6868",
    "sg:postcode":"V2J 5K2",
    "sg:province":"BC",
    "wof:name":"Mc Donald's",
    "wof:placetype":"venue"
},
  "geometry": {"coordinates":[-122.469940185,52.9840126038],"type":"Point"}
}