{
  "type": "Feature",
  "properties": {
    "addr:full":"172 Argyle St N Caledonia ON N3W 2J7",
    "addr:housenumber":"172",
    "addr:postcode":"n3w 2j7",
    "addr:street":"Argyle St N",
    "iso:country":"CA",
    "sg:address":"172 Argyle St N",
    "sg:city":"Caledonia",
    "sg:classifiers":[
        {
            "category":"Banks & Credit Unions",
            "subcategory":"Investment Brokerage",
            "type":"Services"
        }
    ],
    "sg:phone":"+1 905 765 5000",
    "sg:postcode":"N3W 2J7",
    "sg:province":"ON",
    "sg:tags":[
        "consultant",
        "planning",
        "financial"
    ],
    "wof:name":"Farm Mutual Financial Svc",
    "wof:placetype":"venue"
},
  "geometry": {"coordinates":[-79.9500045776,43.0773239136],"type":"Point"}
}