{
  "type": "Feature",
  "properties": {
    "iso:country":"CA",
    "sg:address":"75580 Wildwood Line",
    "sg:city":"Bayfield",
    "sg:classifiers":[
        {
            "category":"Wholesale",
            "subcategory":"Electrical",
            "type":"Manufacturing & Wholesale Goods"
        }
    ],
    "sg:phone":"+1 519 565 5500",
    "sg:postcode":"N0M 1G0",
    "sg:province":"ON",
    "sg:tags":[
        "supply",
        "sign"
    ],
    "wof:name":"Canadian Signcrafters Supply",
    "wof:placetype":"venue"
},
  "geometry": {"coordinates":[-81.696434021,43.5613822937],"type":"Point"}
}