{
  "type": "Feature",
  "properties": {
    "addr:full":"2534 Dougall Ave Windsor ON N8X 1T6",
    "addr:housenumber":"2534",
    "addr:postcode":"n8x 1t6",
    "addr:street":"Dougall Ave",
    "iso:country":"CA",
    "sg:address":"2534 Dougall Ave",
    "sg:city":"Windsor",
    "sg:classifiers":[
        {
            "category":"Personal",
            "subcategory":"Beauty Salon",
            "type":"Services"
        }
    ],
    "sg:phone":"+1 519 972 6452",
    "sg:postcode":"N8X 1T6",
    "sg:province":"ON",
    "wof:name":"Exclusiv Aesthetics By Tammy",
    "wof:placetype":"venue"
},
  "geometry": {"coordinates":[-83.02137,42.284851],"type":"Point"}
}