{
  "type": "Feature",
  "properties": {
    "addr:full":"350 Bloor St E Toronto ON M4W 1H4",
    "addr:housenumber":"350",
    "addr:postcode":"m4w 1h4",
    "addr:street":"Bloor St E",
    "iso:country":"CA",
    "sg:address":"350 Bloor St E",
    "sg:city":"Toronto",
    "sg:classifiers":[
        {
            "category":"Professional",
            "subcategory":"Business Services",
            "type":"Services"
        }
    ],
    "sg:phone":"+1 416 932 0487",
    "sg:postcode":"M4W 1H4",
    "sg:province":"ON",
    "sg:tags":[
        "telemarketing"
    ],
    "wof:name":"Sitel Teleservices Canada Inc",
    "wof:placetype":"venue"
},
  "geometry": {"coordinates":[-79.3785858154,43.6721305847],"type":"Point"}
}