{
  "type": "Feature",
  "properties": {
    "iso:country":"CA",
    "sg:address":"285 Av Duquesne",
    "sg:city":"Saint-Hyacinthe",
    "sg:classifiers":[
        {
            "category":"Wholesale",
            "subcategory":"Office Equipment",
            "type":"Manufacturing & Wholesale Goods"
        }
    ],
    "sg:phone":"+1 450 774 3918",
    "sg:postcode":"J2S 7M4",
    "sg:province":"QC",
    "sg:tags":[
        "accounting",
        "bookkeeping",
        "system"
    ],
    "wof:name":"C L Gestion Enr",
    "wof:placetype":"venue"
},
  "geometry": {"coordinates":[-72.97847,45.5956],"type":"Point"}
}