{
  "type": "Feature",
  "properties": {
    "addr:full":"10295 Av Papineau Montreal QC H2B 2A1",
    "addr:housenumber":"10295",
    "addr:postcode":"h2b 2a1",
    "addr:street":"Av Papineau",
    "iso:country":"CA",
    "sg:address":"10295 Av Papineau",
    "sg:city":"Montreal",
    "sg:classifiers":[
        {
            "category":"Bars & Pubs",
            "type":"Food & Drink"
        }
    ],
    "sg:phone":"+1 514 383 9780",
    "sg:postcode":"H2B 2A1",
    "sg:province":"QC",
    "wof:name":"Brasserie Tonneau D'Or Inc",
    "wof:placetype":"venue"
},
  "geometry": {"coordinates":[-73.65295399999999,45.568192],"type":"Point"}
}