{
  "type": "Feature",
  "properties": {
    "addr:full":"859 Chestnut Cres Sudbury ON P3A 5B3",
    "addr:housenumber":"859",
    "addr:postcode":"p3a 5b3",
    "addr:street":"Chestnut Cres",
    "iso:country":"CA",
    "sg:address":"859 Chestnut Cres",
    "sg:city":"Sudbury",
    "sg:classifiers":[
        {
            "category":"Wholesale",
            "subcategory":"Vending Machines",
            "type":"Manufacturing & Wholesale Goods"
        }
    ],
    "sg:phone":"+1 705 524 3532",
    "sg:postcode":"P3A 5B3",
    "sg:province":"ON",
    "wof:name":"R & D Vending",
    "wof:placetype":"venue"
},
  "geometry": {"coordinates":[-80.9565811157,46.5300865173],"type":"Point"}
}