{
  "type": "Feature",
  "properties": {
    "iso:country":"CA",
    "sg:address":"1007 1 St SW",
    "sg:city":"Calgary",
    "sg:classifiers":[
        {
            "category":"Shopping",
            "subcategory":"Used Merchandise",
            "type":"Retail Goods"
        }
    ],
    "sg:phone":"+1 403 264 5009",
    "sg:postcode":"T2R 0T8",
    "sg:province":"AB",
    "sg:tags":[
        "pawnbroker"
    ],
    "wof:name":"Prestige Pawnbrokers",
    "wof:placetype":"venue"
},
  "geometry": {"coordinates":[-114.06582641599999,51.0432281494],"type":"Point"}
}