{
  "type": "Feature",
  "properties": {
    "iso:country":"CA",
    "sg:city":"Montreal",
    "sg:classifiers":[
        {
            "category":"Manufacturing",
            "subcategory":"Printing",
            "type":"Manufacturing & Wholesale Goods"
        }
    ],
    "sg:phone":"+1 514 598 8547",
    "sg:postcode":"H2L 1H9",
    "sg:province":"QC",
    "sg:tags":[
        "publisher"
    ],
    "wof:name":"Editions Du Cram Inc",
    "wof:placetype":"venue"
},
  "geometry": {"coordinates":[-73.566757,45.5215],"type":"Point"}
}