{
  "type": "Feature",
  "properties": {
    "addr:full":"6291 Nicolle Pl Richmond BC V7C 4V7",
    "addr:housenumber":"6291",
    "addr:postcode":"v7c 4v7",
    "addr:street":"Nicolle Pl",
    "iso:country":"CA",
    "sg:address":"6291 Nicolle Pl",
    "sg:city":"Richmond",
    "sg:classifiers":[
        {
            "category":"Wholesale",
            "subcategory":"Apparel",
            "type":"Manufacturing & Wholesale Goods"
        }
    ],
    "sg:phone":"+1 604 275 2134",
    "sg:postcode":"V7C 4V7",
    "sg:province":"BC",
    "sg:tags":[
        "lingerie"
    ],
    "wof:name":"Doug Stuckey Agencies",
    "wof:placetype":"venue"
},
  "geometry": {"coordinates":[-123.179756165,49.1667518616],"type":"Point"}
}