{
  "type": "Feature",
  "properties": {
    "iso:country":"CA",
    "sg:city":"Lloydminster",
    "sg:classifiers":[
        {
            "category":"Education",
            "subcategory":"School",
            "type":"Public Place"
        }
    ],
    "sg:phone":"+1 780 875 3600",
    "sg:postcode":"T9V 2Z4",
    "sg:province":"AB",
    "wof:name":"Holy Rosary High School",
    "wof:placetype":"venue"
},
  "geometry": {"coordinates":[-110.0078125,53.2779998779],"type":"Point"}
}