{
  "type": "Feature",
  "properties": {
    "addr:full":"4291 Kevin Dr Niagara Falls ON L2H 3B4",
    "addr:housenumber":"4291",
    "addr:postcode":"l2h 3b4",
    "addr:street":"Kevin Dr",
    "iso:country":"CA",
    "sg:address":"4291 Kevin Dr",
    "sg:city":"Niagara Falls",
    "sg:classifiers":[
        {
            "category":"Wholesale",
            "subcategory":"Groceries",
            "type":"Manufacturing & Wholesale Goods"
        }
    ],
    "sg:phone":"+1 905 356 0428",
    "sg:postcode":"L2H 3B4",
    "sg:province":"ON",
    "sg:tags":[
        "food",
        "product"
    ],
    "wof:name":"Quality Bar Foods",
    "wof:placetype":"venue"
},
  "geometry": {"coordinates":[-79.127762,43.110439],"type":"Point"}
}