{
  "type": "Feature",
  "properties": {
    "addr:full":"5068 Imperial St Burnaby BC V5J 1C8",
    "addr:housenumber":"5068",
    "addr:postcode":"v5j 1c8",
    "addr:street":"Imperial St",
    "iso:country":"CA",
    "sg:address":"5068 Imperial St",
    "sg:city":"Burnaby",
    "sg:classifiers":[
        {
            "category":"Retail",
            "subcategory":"Auto Repair",
            "type":"Services"
        }
    ],
    "sg:phone":"+1 604 434 1324",
    "sg:postcode":"V5J 1C8",
    "sg:province":"BC",
    "sg:tags":[
        "repairing",
        "automobile"
    ],
    "wof:name":"Max's Auto Frame Repair Ltd",
    "wof:placetype":"venue"
},
  "geometry": {"coordinates":[-122.991096,49.221745],"type":"Point"}
}