{
  "type": "Feature",
  "properties": {
    "addr:full":"Toronto ON M5J 2W4",
    "addr:postcode":"m5j 2w4",
    "iso:country":"CA",
    "sg:city":"Toronto",
    "sg:classifiers":[
        {
            "category":"Mining & Drilling",
            "type":"Manufacturing & Wholesale Goods"
        }
    ],
    "sg:phone":"+1 416 386 0342",
    "sg:postcode":"M5J 2W4",
    "sg:province":"ON",
    "sg:tags":[
        "company"
    ],
    "wof:name":"Tintina Mines Ltd",
    "wof:placetype":"venue"
},
  "geometry": {"coordinates":[-79.380089,43.647743],"type":"Point"}
}