{
  "type": "Feature",
  "properties": {
    "addr:full":"1010 Sandhill Rd Coldwater ON L0K 1E0",
    "addr:housenumber":"1010",
    "addr:postcode":"l0k 1e0",
    "addr:street":"Sandhill Rd",
    "iso:country":"CA",
    "sg:address":"1010 Sandhill Rd",
    "sg:city":"Coldwater",
    "sg:classifiers":[
        {
            "category":"Home & Garden",
            "subcategory":"Building Materials",
            "type":"Retail Goods"
        }
    ],
    "sg:phone":"+1 705 686 7996",
    "sg:postcode":"L0K 1E0",
    "sg:province":"ON",
    "sg:tags":[
        "windows"
    ],
    "wof:name":"O'Connor Windows",
    "wof:placetype":"venue"
},
  "geometry": {"coordinates":[-79.64436340330001,44.7102241516],"type":"Point"}
}