{
  "type": "Feature",
  "properties": {
    "addr:full":"41 Regent St Richmond Hill ON L4C 9E2",
    "addr:housenumber":"41",
    "addr:postcode":"l4c 9e2",
    "addr:street":"Regent St",
    "iso:country":"CA",
    "sg:address":"41 Regent St",
    "sg:city":"Richmond Hill",
    "sg:classifiers":[
        {
            "category":"Professional",
            "subcategory":"Business Services",
            "type":"Services"
        }
    ],
    "sg:phone":"+1 905 737 9747",
    "sg:postcode":"L4C 9E2",
    "sg:province":"ON",
    "sg:tags":[
        "paralegal"
    ],
    "wof:name":"Judi Simms Paralegal & Assoc",
    "wof:placetype":"venue"
},
  "geometry": {"coordinates":[-79.461227417,43.8791618347],"type":"Point"}
}