{
  "type": "Feature",
  "properties": {
    "addr:full":"434 Av Saint-Charles Vaudreuil-Dorion QC J7V 2N1",
    "addr:postcode":"j7v 2n1",
    "addr:street":"434 Av Saint-Charles",
    "iso:country":"CA",
    "sg:address":"434 Av Saint-Charles",
    "sg:city":"Vaudreuil-Dorion",
    "sg:classifiers":[
        {
            "category":"Shopping",
            "subcategory":"Clothing, Apparel, & Fashions",
            "type":"Retail Goods"
        }
    ],
    "sg:phone":"+1 450 455 9930",
    "sg:postcode":"J7V 2N1",
    "sg:province":"QC",
    "sg:tags":[
        "item",
        "boutique"
    ],
    "wof:name":"Boutique Helen",
    "wof:placetype":"venue"
},
  "geometry": {"coordinates":[-74.0280456543,45.4004898071],"type":"Point"}
}