{
  "type": "Feature",
  "properties": {
    "addr:full":"346 Orenda Rd Brampton ON L6T 1G1",
    "addr:housenumber":"346",
    "addr:postcode":"l6t 1g1",
    "addr:street":"Orenda Rd",
    "iso:country":"CA",
    "sg:address":"346 Orenda Rd",
    "sg:city":"Brampton",
    "sg:classifiers":[
        {
            "category":"Manufacturing",
            "subcategory":"Tools & Machinery",
            "type":"Manufacturing & Wholesale Goods"
        }
    ],
    "sg:phone":"+1 905 458 5341",
    "sg:postcode":"L6T 1G1",
    "sg:province":"ON",
    "sg:tags":[
        "machine",
        "shop"
    ],
    "wof:name":"Systematic Tool & Die",
    "wof:placetype":"venue"
},
  "geometry": {"coordinates":[-79.70014999999999,43.701866],"type":"Point"}
}