{
  "type": "Feature",
  "properties": {
    "addr:full":"Red Deer AB T4P 1X6",
    "addr:postcode":"t4p 1x6",
    "iso:country":"CA",
    "sg:city":"Red Deer",
    "sg:classifiers":[
        {
            "category":"Education",
            "subcategory":"Special Training",
            "type":"Public Place"
        }
    ],
    "sg:phone":"+1 403 341 4711",
    "sg:postcode":"T4P 1X6",
    "sg:province":"AB",
    "sg:tags":[
        "instruction",
        "driving"
    ],
    "wof:name":"Cameron Driver Education Ltd",
    "wof:placetype":"venue"
},
  "geometry": {"coordinates":[-113.80880000000001,52.300823],"type":"Point"}
}