{
  "type": "Feature",
  "properties": {
    "addr:full":"293 Bay St #L8 Sault Ste Marie ON P6A 1X3",
    "addr:housenumber":"293;# l8",
    "addr:postcode":"p6a 1x3",
    "addr:street":"Bay St",
    "iso:country":"CA",
    "sg:address":"293 Bay St #L8",
    "sg:city":"Sault Ste Marie",
    "sg:classifiers":[
        {
            "category":"Personal",
            "subcategory":"Beauty Salon",
            "type":"Services"
        }
    ],
    "sg:phone":"+1 705 945 9494",
    "sg:postcode":"P6A 1X3",
    "sg:province":"ON",
    "wof:name":"Regis Salon",
    "wof:placetype":"venue"
},
  "geometry": {"coordinates":[-84.33777600000001,46.513145],"type":"Point"}
}