{
  "type": "Feature",
  "properties": {
    "iso:country":"CA",
    "sg:city":"Concord",
    "sg:classifiers":[
        {
            "category":"Shopping",
            "subcategory":"Bicycles & Sporting Goods",
            "type":"Retail Goods"
        }
    ],
    "sg:phone":"+1 905 760 1705",
    "sg:postcode":"L4K 3V2",
    "sg:province":"ON",
    "sg:tags":[
        "equipment",
        "gymnasium",
        "supply"
    ],
    "wof:name":"W G Osborne Inc",
    "wof:placetype":"venue"
},
  "geometry": {"coordinates":[-79.53244,43.810467],"type":"Point"}
}