{
  "type": "Feature",
  "properties": {
    "iso:country":"CA",
    "sg:address":"597 Notre Dame Ave",
    "sg:city":"Winnipeg",
    "sg:classifiers":[
        {
            "category":"Professional",
            "subcategory":"Accounting & Tax Preparation",
            "type":"Services"
        }
    ],
    "sg:phone":"+1 204 779 1477",
    "sg:postcode":"R3B 1S6",
    "sg:province":"MB",
    "sg:tags":[
        "return",
        "filing"
    ],
    "wof:name":"Glenda's Tax & Consulting Svc",
    "wof:placetype":"venue"
},
  "geometry": {"coordinates":[-97.156075,49.900646],"type":"Point"}
}