{
  "type": "Feature",
  "properties": {
    "iso:country":"CA",
    "sg:address":"9929 Hillcrest Dr",
    "sg:city":"Chilliwack",
    "sg:classifiers":[
        {
            "category":"Building & Trades",
            "subcategory":"Construction",
            "type":"Services"
        }
    ],
    "sg:phone":"+1 604 792 7014",
    "sg:postcode":"V2P 7P4",
    "sg:province":"BC",
    "sg:tags":[
        "masonry",
        "contractor"
    ],
    "wof:name":"Henning Thomson Masonry",
    "wof:placetype":"venue"
},
  "geometry": {"coordinates":[-121.905677795,49.182220459],"type":"Point"}
}