{
  "type": "Feature",
  "properties": {
    "addr:full":"710 Rue Sainte-Catherine O Montreal QC H3B 1B9",
    "addr:housenumber":"710",
    "addr:postcode":"h3b 1b9",
    "addr:street":"Rue Sainte-Catherine O",
    "iso:country":"CA",
    "sg:address":"710 Rue Sainte-Catherine O",
    "sg:city":"Montreal",
    "sg:classifiers":[
        {
            "category":"Restaurant",
            "type":"Food & Drink"
        }
    ],
    "sg:phone":"+1 514 871 2899",
    "sg:postcode":"H3B 1B9",
    "sg:province":"QC",
    "wof:name":"Restaurants Nickels",
    "wof:placetype":"venue"
},
  "geometry": {"coordinates":[-73.558868,45.515217],"type":"Point"}
}