{
  "type": "Feature",
  "properties": {
    "addr:full":"Chatham ON N7M 5J5",
    "addr:postcode":"n7m 5j5",
    "iso:country":"CA",
    "sg:city":"Chatham",
    "sg:classifiers":[
        {
            "category":"Retail",
            "subcategory":"Auto Repair",
            "type":"Services"
        }
    ],
    "sg:phone":"+1 519 354 6202",
    "sg:postcode":"N7M 5J5",
    "sg:province":"ON",
    "sg:tags":[
        "body",
        "automobile",
        "painting"
    ],
    "wof:name":"Imperial Auto Body",
    "wof:placetype":"venue"
},
  "geometry": {"coordinates":[-82.219345,42.391438],"type":"Point"}
}