{
  "type": "Feature",
  "properties": {
    "addr:full":"128 50 Ave SE Calgary AB T2G 2A8",
    "addr:postcode":"t2g 2a8",
    "addr:street":"128 50 Ave Se",
    "iso:country":"CA",
    "sg:address":"128 50 Ave SE",
    "sg:city":"Calgary",
    "sg:classifiers":[
        {
            "category":"Shopping",
            "subcategory":"Hobbies, Toys, & Games",
            "type":"Retail Goods"
        }
    ],
    "sg:phone":"+1 403 253 0992",
    "sg:postcode":"T2G 2A8",
    "sg:province":"AB",
    "sg:tags":[
        "craft",
        "supply"
    ],
    "wof:name":"Pro-Graphics Ltd",
    "wof:placetype":"venue"
},
  "geometry": {"coordinates":[-114.063416,51.008846],"type":"Point"}
}