{
  "type": "Feature",
  "properties": {
    "addr:full":"Almonte ON K0A 1A0",
    "addr:postcode":"k0a 1a0",
    "iso:country":"CA",
    "sg:city":"Almonte",
    "sg:classifiers":[
        {
            "category":"Retail",
            "subcategory":"Repair Shop",
            "type":"Services"
        }
    ],
    "sg:phone":"+1 613 256 5195",
    "sg:postcode":"K0A 1A0",
    "sg:province":"ON",
    "sg:tags":[
        "caning",
        "refinishing"
    ],
    "wof:name":"Be Seated",
    "wof:placetype":"venue"
},
  "geometry": {"coordinates":[-76.1892089844,45.2304763794],"type":"Point"}
}