{
  "type": "Feature",
  "properties": {
    "iso:country":"CA",
    "sg:city":"North York",
    "sg:classifiers":[
        {
            "category":"Professional",
            "subcategory":"Credit Reporting & Collection",
            "type":"Services"
        }
    ],
    "sg:phone":"+1 416 784 3770",
    "sg:postcode":"M6A 2A4",
    "sg:province":"ON",
    "sg:tags":[
        "agency"
    ],
    "wof:name":"Canadian Corporate Legal Svc",
    "wof:placetype":"venue"
},
  "geometry": {"coordinates":[-79.4298171997,43.7203903198],"type":"Point"}
}