{
  "type": "Feature",
  "properties": {
    "addr:full":"472 High St Orillia ON L3V 4X7",
    "addr:housenumber":"472",
    "addr:postcode":"l3v 4x7",
    "addr:street":"High St",
    "iso:country":"CA",
    "sg:address":"472 High St",
    "sg:city":"Orillia",
    "sg:classifiers":[
        {
            "category":"Real Estate",
            "subcategory":"Real Estate Operator",
            "type":"Services"
        }
    ],
    "sg:phone":"+1 705 329 0132",
    "sg:postcode":"L3V 4X7",
    "sg:province":"ON",
    "sg:tags":[
        "apartment"
    ],
    "wof:name":"Fellowship Villa",
    "wof:placetype":"venue"
},
  "geometry": {"coordinates":[-79.40477,44.597157],"type":"Point"}
}