{
  "type": "Feature",
  "properties": {
    "addr:full":"Deux-Montagnes QC J7R 1N1",
    "addr:postcode":"j7r 1n1",
    "iso:country":"CA",
    "sg:city":"Deux-Montagnes",
    "sg:classifiers":[
        {
            "category":"Personal",
            "type":"Services"
        }
    ],
    "sg:phone":"+1 450 974 9292",
    "sg:postcode":"J7R 1N1",
    "sg:province":"QC",
    "sg:tags":[
        "therapist",
        "electrolysis",
        "massage"
    ],
    "wof:name":"Maison DE Beaute Esthetique",
    "wof:placetype":"venue"
},
  "geometry": {"coordinates":[-73.99458300000001,45.501686],"type":"Point"}
}