{
  "type": "Feature",
  "properties": {
    "addr:full":"64 Grand Ave S Cambridge ON N1S 2L8",
    "addr:housenumber":"64",
    "addr:postcode":"n1s 2l8",
    "addr:street":"Grand Ave S",
    "iso:country":"CA",
    "sg:address":"64 Grand Ave S",
    "sg:city":"Cambridge",
    "sg:classifiers":[
        {
            "category":"Home & Garden",
            "subcategory":"Home Furnishings",
            "type":"Retail Goods"
        }
    ],
    "sg:phone":"+1 519 624 9911",
    "sg:postcode":"N1S 2L8",
    "sg:province":"ON",
    "sg:tags":[
        "housewares"
    ],
    "wof:name":"Corning Revere Factory Stores",
    "wof:placetype":"venue"
},
  "geometry": {"coordinates":[-80.3177108765,43.3554153442],"type":"Point"}
}