{
  "type": "Feature",
  "properties": {
    "addr:full":"1720 2nd Ave W Vancouver BC V6J 1H6",
    "addr:housenumber":"1720",
    "addr:postcode":"v6j 1h6",
    "addr:street":"2Nd Ave W",
    "iso:country":"CA",
    "sg:address":"1720 2nd Ave W",
    "sg:city":"Vancouver",
    "sg:classifiers":[
        {
            "category":"Communications",
            "subcategory":"Film & Video Production",
            "type":"Services"
        }
    ],
    "sg:phone":"+1 604 736 7474",
    "sg:postcode":"V6J 1H6",
    "sg:province":"BC",
    "sg:tags":[
        "motion",
        "picture",
        "studio",
        "producer"
    ],
    "wof:name":"Post Modern Sound Inc",
    "wof:placetype":"venue"
},
  "geometry": {"coordinates":[-123.143822,49.269623],"type":"Point"}
}