{
  "type": "Feature",
  "properties": {
    "addr:full":"4817 54 St Vegreville AB T9C 1N1",
    "addr:housenumber":"4817",
    "addr:postcode":"t9c 1n1",
    "addr:street":"54 St",
    "iso:country":"CA",
    "sg:address":"4817 54 St",
    "sg:city":"Vegreville",
    "sg:classifiers":[
        {
            "category":"Professional",
            "type":"Services"
        }
    ],
    "sg:phone":"+1 780 632 4818",
    "sg:postcode":"T9C 1N1",
    "sg:province":"AB",
    "sg:tags":[
        "establishment",
        "television",
        "radio"
    ],
    "wof:name":"D S Radio & Tv",
    "wof:placetype":"venue"
},
  "geometry": {"coordinates":[-112.06452179,53.4969367981],"type":"Point"}
}