{
  "type": "Feature",
  "properties": {
    "iso:country":"CA",
    "sg:address":"420 Mtee Letang",
    "sg:city":"Temiscaming",
    "sg:classifiers":[
        {
            "category":"Retail",
            "subcategory":"Auto Repair",
            "type":"Services"
        }
    ],
    "sg:phone":"+1 819 627 9613",
    "sg:postcode":"J0Z 3R0",
    "sg:province":"QC",
    "sg:tags":[
        "body",
        "automobile",
        "painting"
    ],
    "wof:name":"Atelier DE Debosselage Raymond",
    "wof:placetype":"venue"
},
  "geometry": {"coordinates":[-79.06536865229999,46.7367095947],"type":"Point"}
}