{
  "type": "Feature",
  "properties": {
    "addr:full":"3821 Ch Brassard S Saint-Zenon QC J0K 3N0",
    "addr:housenumber":"3821",
    "addr:postcode":"j0k 3n0",
    "addr:street":"Ch Brassard S Saint-Zenon",
    "iso:country":"CA",
    "sg:address":"3821 Ch Brassard S",
    "sg:city":"Saint-Zenon",
    "sg:classifiers":[
        {
            "category":"Food & Beverages",
            "subcategory":"Groceries & Convenience Stores",
            "type":"Retail Goods"
        }
    ],
    "sg:phone":"+1 450 884 0172",
    "sg:postcode":"J0K 3N0",
    "sg:province":"QC",
    "wof:name":"Depanneur Des 7 Chutes Enr",
    "wof:placetype":"venue"
},
  "geometry": {"coordinates":[-73.720703,46.445915],"type":"Point"}
}