{
  "type": "Feature",
  "properties": {
    "addr:full":"140 Rue Saint-Jean Quebec QC G1R 1N7",
    "addr:housenumber":"140",
    "addr:postcode":"g1r 1n7",
    "addr:street":"Rue Saint-Jean",
    "iso:country":"CA",
    "sg:address":"140 Rue Saint-Jean",
    "sg:city":"Quebec",
    "sg:classifiers":[
        {
            "category":"Government",
            "subcategory":"Fire Station",
            "type":"Public Place"
        }
    ],
    "sg:phone":"+1 ",
    "sg:postcode":"G1R 1N7",
    "sg:province":"QC",
    "sg:tags":[
        "department"
    ],
    "wof:name":"Quebec Incendie",
    "wof:placetype":"venue"
},
  "geometry": {"coordinates":[-71.226196,46.807755],"type":"Point"}
}