{
  "type": "Feature",
  "properties": {
    "iso:country":"CA",
    "sg:address":"67 Main St S",
    "sg:city":"Seaforth",
    "sg:classifiers":[
        {
            "category":"Shopping",
            "subcategory":"Pharmacy",
            "type":"Retail Goods"
        }
    ],
    "sg:phone":"+1 519 527 1990",
    "sg:postcode":"N0K 1W0",
    "sg:province":"ON",
    "wof:name":"Keating's Pharmacy Ltd",
    "wof:placetype":"venue"
},
  "geometry": {"coordinates":[-81.3949890137,43.5517730713],"type":"Point"}
}