{
  "type": "Feature",
  "properties": {
    "addr:full":"420 Neptune Cres London ON N6M 1A1",
    "addr:housenumber":"420",
    "addr:postcode":"n6m 1a1",
    "addr:street":"Neptune Cres",
    "iso:country":"CA",
    "sg:address":"420 Neptune Cres",
    "sg:city":"London",
    "sg:classifiers":[
        {
            "category":"Wholesale",
            "subcategory":"Machinery & Supplies",
            "type":"Manufacturing & Wholesale Goods"
        }
    ],
    "sg:phone":"+1 519 451 5320",
    "sg:postcode":"N6M 1A1",
    "sg:province":"ON",
    "sg:tags":[
        "equipment",
        "foundry",
        "maker",
        "pattern"
    ],
    "wof:name":"Gudgeon Brothers Ltd",
    "wof:placetype":"venue"
},
  "geometry": {"coordinates":[-81.140503,42.995911],"type":"Point"}
}