{
  "type": "Feature",
  "properties": {
    "addr:full":"79 Goulding Ave North York ON M2M 1L1",
    "addr:housenumber":"79",
    "addr:postcode":"m2m 1l1",
    "addr:street":"Goulding Ave",
    "iso:country":"CA",
    "sg:address":"79 Goulding Ave",
    "sg:city":"North York",
    "sg:classifiers":[
        {
            "category":"Building & Trades",
            "subcategory":"Landscaping Services",
            "type":"Services"
        }
    ],
    "sg:phone":"+1 416 222 7567",
    "sg:postcode":"M2M 1L1",
    "sg:province":"ON",
    "sg:tags":[
        "landscape",
        "contractor"
    ],
    "wof:name":"Russell Neice Landscape Grdng",
    "wof:placetype":"venue"
},
  "geometry": {"coordinates":[-79.42529296879999,43.7904205322],"type":"Point"}
}