{
  "type": "Feature",
  "properties": {
    "addr:full":"1146 Rue Papineau Sherbrooke QC J1E 3B2",
    "addr:housenumber":"1146",
    "addr:postcode":"j1e 3b2",
    "addr:street":"Rue Papineau",
    "iso:country":"CA",
    "sg:address":"1146 Rue Papineau",
    "sg:city":"Sherbrooke",
    "sg:classifiers":[
        {
            "category":"Professional",
            "subcategory":"Computer Services",
            "type":"Services"
        }
    ],
    "sg:phone":"+1 819 829 9598",
    "sg:postcode":"J1E 3B2",
    "sg:province":"QC",
    "sg:tags":[
        "repair",
        "refrigeration",
        "contractor"
    ],
    "wof:name":"A-1 Refrigeration",
    "wof:placetype":"venue"
},
  "geometry": {"coordinates":[-71.864189,45.41431],"type":"Point"}
}