{
  "type": "Feature",
  "properties": {
    "addr:full":"PO Box 11 Little Bay East NL A0E 2J0",
    "addr:housenumber":"po box 11",
    "addr:postcode":"a0e 2j0",
    "addr:street":"Little Bay East",
    "iso:country":"CA",
    "sg:address":"PO Box 11",
    "sg:city":"Little Bay East",
    "sg:classifiers":[
        {
            "category":"Farming",
            "subcategory":"Aquatic Farm",
            "type":"Manufacturing & Wholesale Goods"
        }
    ],
    "sg:phone":"+1 709 461 2445",
    "sg:postcode":"A0E 2J0",
    "sg:province":"NL",
    "sg:tags":[
        "hatchery",
        "consultant",
        "fish",
        "fishery"
    ],
    "wof:name":"Fortune Bay Fisheries Ltd",
    "wof:placetype":"venue"
},
  "geometry": {"coordinates":[-54.8558273315,47.5528526306],"type":"Point"}
}