{
  "type": "Feature",
  "properties": {
    "addr:full":"Sainte-Brigitte-DE-Laval QC G0A 3K0",
    "addr:postcode":"g0a 3k0",
    "iso:country":"CA",
    "sg:city":"Sainte-Brigitte-DE-Laval",
    "sg:classifiers":[
        {
            "category":"Building & Trades",
            "subcategory":"Construction",
            "type":"Services"
        }
    ],
    "sg:phone":"+1 418 825 3089",
    "sg:postcode":"G0A 3K0",
    "sg:province":"QC",
    "sg:tags":[
        "maker",
        "cabinet"
    ],
    "wof:name":"Ebenisterie Serge Drouin Enr",
    "wof:placetype":"venue"
},
  "geometry": {"coordinates":[-71.20687100000001,46.954235],"type":"Point"}
}