{
  "type": "Feature",
  "properties": {
    "addr:full":"320 Rue Saint-Germain E Rimouski QC G5L 1C2",
    "addr:housenumber":"320",
    "addr:postcode":"g5l 1c2",
    "addr:street":"Rue Saint-Germain E",
    "iso:country":"CA",
    "sg:address":"320 Rue Saint-Germain E",
    "sg:city":"Rimouski",
    "sg:classifiers":[
        {
            "category":"Banks & Credit Unions",
            "subcategory":"Bank",
            "type":"Services"
        }
    ],
    "sg:phone":"+1 418 723 2329",
    "sg:postcode":"G5L 1C2",
    "sg:province":"QC",
    "wof:name":"Banque Laurentienne Du Canada",
    "wof:placetype":"venue"
},
  "geometry": {"coordinates":[-68.51783,48.460121],"type":"Point"}
}