{
  "type": "Feature",
  "properties": {
    "addr:full":"Fabre QC J0Z 1Z0",
    "addr:postcode":"j0z 1z0",
    "iso:country":"CA",
    "sg:city":"Fabre",
    "sg:classifiers":[
        {
            "category":"Local Transit",
            "type":"Transportation"
        }
    ],
    "sg:phone":"+1 819 634 3511",
    "sg:postcode":"J0Z 1Z0",
    "sg:province":"QC",
    "sg:tags":[
        "bus",
        "line"
    ],
    "wof:name":"Transport Gilles Paquette",
    "wof:placetype":"venue"
},
  "geometry": {"coordinates":[-79.36740112299999,47.2005615234],"type":"Point"}
}