{
  "type": "Feature",
  "properties": {
    "addr:full":"Keswick ON L4P 3J4",
    "addr:postcode":"l4p 3j4",
    "iso:country":"CA",
    "sg:city":"Keswick",
    "sg:classifiers":[
        {
            "category":"Shopping",
            "type":"Retail Goods"
        }
    ],
    "sg:phone":"+1 905 476 0575",
    "sg:postcode":"L4P 3J4",
    "sg:province":"ON",
    "sg:tags":[
        "pet",
        "food",
        "supply"
    ],
    "wof:name":"Global Pet Foods",
    "wof:placetype":"venue"
},
  "geometry": {"coordinates":[-79.464553833,44.2141265869],"type":"Point"}
}