{
  "type": "Feature",
  "properties": {
    "addr:full":"Richmond BC V6Y 2C3",
    "addr:postcode":"v6y 2c3",
    "iso:country":"CA",
    "sg:city":"Richmond",
    "sg:classifiers":[
        {
            "category":"Shopping",
            "subcategory":"Computers & Home Electronics",
            "type":"Retail Goods"
        }
    ],
    "sg:phone":"+1 604 207 4636",
    "sg:postcode":"V6Y 2C3",
    "sg:province":"BC",
    "sg:tags":[
        "software"
    ],
    "wof:name":"Infocus Commerce Solutions",
    "wof:placetype":"venue"
},
  "geometry": {"coordinates":[-123.136383057,49.1652336121],"type":"Point"}
}