{
  "type": "Feature",
  "properties": {
    "addr:full":"100 Rue Hotel DE Ville Durham-Sud QC J0H 2C0",
    "addr:housenumber":"100",
    "addr:postcode":"j0h 2c0",
    "addr:street":"Rue Hotel De Ville",
    "iso:country":"CA",
    "sg:address":"100 Rue Hotel DE Ville",
    "sg:city":"Durham-Sud",
    "sg:classifiers":[
        {
            "category":"Food & Beverages",
            "subcategory":"Groceries & Convenience Stores",
            "type":"Retail Goods"
        }
    ],
    "sg:phone":"+1 819 858 1110",
    "sg:postcode":"J0H 2C0",
    "sg:province":"QC",
    "sg:tags":[
        "grocer"
    ],
    "wof:name":"Epicerie DE Durham Sud-Coop",
    "wof:placetype":"venue"
},
  "geometry": {"coordinates":[-72.34296399999999,45.661213],"type":"Point"}
}