{
  "type": "Feature",
  "properties": {
    "addr:full":"1300 Rue Montplaisir Saint-Charles-DE-Drummond QC J2B 7T5",
    "addr:housenumber":"1300",
    "addr:postcode":"j2b 7t5",
    "addr:street":"Rue Montplaisir",
    "iso:country":"CA",
    "sg:address":"1300 Rue Montplaisir",
    "sg:city":"Saint-Charles-DE-Drummond",
    "sg:classifiers":[
        {
            "category":"Bars & Pubs",
            "type":"Food & Drink"
        }
    ],
    "sg:phone":"+1 819 475 2336",
    "sg:postcode":"J2B 7T5",
    "sg:province":"QC",
    "sg:tags":[
        "lounge",
        "cocktail"
    ],
    "wof:name":"Bar Chez Popaul",
    "wof:placetype":"venue"
},
  "geometry": {"coordinates":[-72.489059,45.898678],"type":"Point"}
}