{
  "type": "Feature",
  "properties": {
    "addr:full":"6 Queen St W St Stephen NB E3L 2J8",
    "addr:housenumber":"6",
    "addr:postcode":"e3l 2j8",
    "addr:street":"Queen St W",
    "iso:country":"CA",
    "sg:address":"6 Queen St W",
    "sg:city":"St Stephen",
    "sg:classifiers":[
        {
            "category":"Health Services",
            "subcategory":"Optometrist",
            "type":"Services"
        }
    ],
    "sg:phone":"+1 506 466 1388",
    "sg:postcode":"E3L 2J8",
    "sg:province":"NB",
    "wof:name":"Murphy, Michael OD",
    "wof:placetype":"venue"
},
  "geometry": {"coordinates":[-67.2749786377,45.1978263855],"type":"Point"}
}