{
  "type": "Feature",
  "properties": {
    "addr:full":"284 Wood St W Prescott ON K0E 1T0",
    "addr:housenumber":"284",
    "addr:postcode":"k0e 1t0",
    "addr:street":"Wood St W",
    "iso:country":"CA",
    "sg:address":"284 Wood St W",
    "sg:city":"Prescott",
    "sg:classifiers":[
        {
            "category":"Building & Trades",
            "subcategory":"Landscaping Services",
            "type":"Services"
        }
    ],
    "sg:phone":"+1 613 925 4764",
    "sg:postcode":"K0E 1T0",
    "sg:province":"ON",
    "sg:tags":[
        "excavating",
        "contractor",
        "topsoil"
    ],
    "wof:name":"Beck's Construction CO Ltd",
    "wof:placetype":"venue"
},
  "geometry": {"coordinates":[-75.519768,44.712379],"type":"Point"}
}