{
  "type": "Feature",
  "properties": {
    "addr:full":"54 Carden St Guelph ON N1H 3A2",
    "addr:housenumber":"54",
    "addr:postcode":"n1h 3a2",
    "addr:street":"Carden St",
    "iso:country":"CA",
    "sg:address":"54 Carden St",
    "sg:city":"Guelph",
    "sg:classifiers":[
        {
            "category":"Shopping",
            "subcategory":"Clothing, Apparel, & Fashions",
            "type":"Retail Goods"
        }
    ],
    "sg:phone":"+1 519 763 2993",
    "sg:postcode":"N1H 3A2",
    "sg:province":"ON",
    "wof:name":"Dealer 420",
    "wof:placetype":"venue"
},
  "geometry": {"coordinates":[-80.248268,43.54422],"type":"Point"}
}