{
  "type": "Feature",
  "properties": {
    "addr:full":"1320 33 St N Lethbridge AB T1H 5H3",
    "addr:housenumber":"1320",
    "addr:postcode":"t1h 5h3",
    "addr:street":"33 St N",
    "iso:country":"CA",
    "sg:address":"1320 33 St N",
    "sg:city":"Lethbridge",
    "sg:classifiers":[
        {
            "category":"Freight",
            "type":"Transportation"
        }
    ],
    "sg:phone":"+1 403 328 2774",
    "sg:postcode":"T1H 5H3",
    "sg:province":"AB",
    "sg:tags":[
        "trucking"
    ],
    "wof:name":"Big Horn Transport Ltd",
    "wof:placetype":"venue"
},
  "geometry": {"coordinates":[-112.792030334,49.7173690796],"type":"Point"}
}