{
  "type": "Feature",
  "properties": {
    "addr:full":"591 Rue Principale Eel River Crossing NB E8E 1S7",
    "addr:housenumber":"591",
    "addr:postcode":"e8e 1s7",
    "addr:street":"Rue Principale Eel River Crossing",
    "iso:country":"CA",
    "sg:address":"591 Rue Principale",
    "sg:city":"Eel River Crossing",
    "sg:classifiers":[
        {
            "category":"Personal",
            "subcategory":"Beauty Salon",
            "type":"Services"
        }
    ],
    "sg:phone":"+1 506 826 2024",
    "sg:postcode":"E8E 1S7",
    "sg:province":"NB",
    "wof:name":"Esthetique DE Soins LA Tendre",
    "wof:placetype":"venue"
},
  "geometry": {"coordinates":[-66.416451,48.001675],"type":"Point"}
}