{
  "type": "Feature",
  "properties": {
    "addr:full":"Oshawa ON L1G 6Z6",
    "addr:postcode":"l1g 6z6",
    "iso:country":"CA",
    "sg:city":"Oshawa",
    "sg:classifiers":[
        {
            "category":"Bars & Pubs",
            "type":"Food & Drink"
        }
    ],
    "sg:phone":"+1 905 433 0687",
    "sg:postcode":"L1G 6Z6",
    "sg:province":"ON",
    "wof:name":"Village Pump Restaurant & Tvrn",
    "wof:placetype":"venue"
},
  "geometry": {"coordinates":[-78.86895800000001,43.934235],"type":"Point"}
}