{
  "type": "Feature",
  "properties": {
    "addr:full":"677 Davie St Vancouver BC V6B 2G6",
    "addr:housenumber":"677",
    "addr:postcode":"bc v6b 2g6",
    "addr:street":"Davie St",
    "iso:country":"CA",
    "sg:address":"677 Davie St",
    "sg:city":"Vancouver",
    "sg:classifiers":[
        {
            "category":"Personal",
            "type":"Services"
        }
    ],
    "sg:phone":"+1 604 606 6438",
    "sg:postcode":"V6B 2G6",
    "sg:province":"BC",
    "sg:tags":[
        "therapist",
        "massage"
    ],
    "wof:name":"Dance Therapy Clinic",
    "wof:placetype":"venue"
},
  "geometry": {"coordinates":[-123.125816,49.27705],"type":"Point"}
}