{
  "type": "Feature",
  "properties": {
    "addr:full":"120 Saskatchewan Ave W Outlook SK S0L 2N0",
    "addr:housenumber":"120",
    "addr:postcode":"s0l 2n0",
    "addr:street":"Saskatchewan Ave W Outlook",
    "iso:country":"CA",
    "sg:address":"120 Saskatchewan Ave W",
    "sg:city":"Outlook",
    "sg:classifiers":[
        {
            "category":"Restaurant",
            "type":"Food & Drink"
        }
    ],
    "sg:phone":"+1 306 867 8345",
    "sg:postcode":"S0L 2N0",
    "sg:province":"SK",
    "wof:name":"New Outlook Cafe",
    "wof:placetype":"venue"
},
  "geometry": {"coordinates":[-107.05696106000001,51.4880485535],"type":"Point"}
}