{
  "type": "Feature",
  "properties": {
    "iso:country":"CA",
    "sg:city":"Saint-Eustache",
    "sg:classifiers":[
        {
            "category":"Travel",
            "subcategory":"Travel Agent",
            "type":"Entertainment"
        }
    ],
    "sg:phone":"+1 450 473 2934",
    "sg:postcode":"J7P 1K3",
    "sg:province":"QC",
    "sg:tags":[
        "agency",
        "bureau"
    ],
    "wof:name":"Uniglobe Voyages Solerama Inc",
    "wof:placetype":"venue"
},
  "geometry": {"coordinates":[-73.8517532349,45.5857391357],"type":"Point"}
}