{
  "type": "Feature",
  "properties": {
    "addr:full":"28 Victoria St Truro NS B2N 1Y6",
    "addr:housenumber":"28",
    "addr:postcode":"b2n 1y6",
    "addr:street":"Victoria St",
    "iso:country":"CA",
    "sg:address":"28 Victoria St",
    "sg:city":"Truro",
    "sg:classifiers":[
        {
            "category":"Health Services",
            "subcategory":"Doctor",
            "type":"Services"
        }
    ],
    "sg:phone":"+1 902 893 1133",
    "sg:postcode":"B2N 1Y6",
    "sg:province":"NS",
    "sg:tags":[
        "physician",
        "surgeon"
    ],
    "wof:name":"Victoria Street Medical Clinic",
    "wof:placetype":"venue"
},
  "geometry": {"coordinates":[-63.286686,45.361881],"type":"Point"}
}