{
  "type": "Feature",
  "properties": {
    "addr:full":"Manning AB T0H 2M0",
    "addr:postcode":"t0h 2m0",
    "iso:country":"CA",
    "sg:city":"Manning",
    "sg:classifiers":[
        {
            "category":"Mining & Drilling",
            "type":"Manufacturing & Wholesale Goods"
        }
    ],
    "sg:phone":"+1 780 836 3049",
    "sg:postcode":"T0H 2M0",
    "sg:province":"AB",
    "sg:tags":[
        "field",
        "excavating",
        "oil",
        "contractor"
    ],
    "wof:name":"B & B King Holdings Ltd",
    "wof:placetype":"venue"
},
  "geometry": {"coordinates":[-117.62841,56.923977],"type":"Point"}
}