{
  "type": "Feature",
  "properties": {
    "iso:country":"CA",
    "sg:address":"296 Smith St",
    "sg:city":"Hinton",
    "sg:classifiers":[
        {
            "category":"Restaurant",
            "type":"Food & Drink"
        }
    ],
    "sg:phone":"+1 780 865 1111",
    "sg:postcode":"T7V 2A1",
    "sg:province":"AB",
    "wof:name":"Royal Garden Restaurant",
    "wof:placetype":"venue"
},
  "geometry": {"coordinates":[-117.561501,53.403976],"type":"Point"}
}