{
  "type": "Feature",
  "properties": {
    "addr:full":"8201 Boul Newman Lasalle QC H8N 1Y1",
    "addr:housenumber":"8201",
    "addr:postcode":"h8n 1y1",
    "addr:street":"Boul Newman",
    "iso:country":"CA",
    "sg:address":"8201 Boul Newman",
    "sg:city":"Lasalle",
    "sg:classifiers":[
        {
            "category":"Restaurant",
            "type":"Food & Drink"
        }
    ],
    "sg:phone":"+1 514 367 0473",
    "sg:postcode":"H8N 1Y1",
    "sg:province":"QC",
    "wof:name":"Restaurant LA Belle Province",
    "wof:placetype":"venue"
},
  "geometry": {"coordinates":[-73.6280212402,45.4344139099],"type":"Point"}
}