{
  "type": "Feature",
  "properties": {
    "addr:full":"Calgary AB T2S 0C7",
    "addr:postcode":"t2s 0c7",
    "iso:country":"CA",
    "sg:city":"Calgary",
    "sg:classifiers":[
        {
            "category":"Health Services",
            "subcategory":"Health Practitioner",
            "type":"Services"
        }
    ],
    "sg:phone":"+1 403 228 5191",
    "sg:postcode":"T2S 0C7",
    "sg:province":"AB",
    "sg:tags":[
        "psychologist"
    ],
    "wof:name":"Philips, Michele PhD",
    "wof:placetype":"venue"
},
  "geometry": {"coordinates":[-114.071793,51.036808],"type":"Point"}
}