{
  "type": "Feature",
  "properties": {
    "iso:country":"CA",
    "sg:address":"59 King William St",
    "sg:city":"Huntsville",
    "sg:classifiers":[
        {
            "category":"Autos & Motor Vehicles",
            "subcategory":"Fuel & Gas Station",
            "type":"Retail Goods"
        }
    ],
    "sg:phone":"+1 705 789 7561",
    "sg:postcode":"P1H 1E5",
    "sg:province":"ON",
    "sg:tags":[
        "oil"
    ],
    "wof:name":"Sunoco",
    "wof:placetype":"venue"
},
  "geometry": {"coordinates":[-79.20724487299999,45.3325576782],"type":"Point"}
}