{
  "type": "Feature",
  "properties": {
    "iso:country":"CA",
    "sg:address":"2530 E Assiniboine Ave",
    "sg:city":"Regina",
    "sg:classifiers":[
        {
            "category":"Education",
            "subcategory":"School",
            "type":"Public Place"
        }
    ],
    "sg:phone":"+1 306 791 8445",
    "sg:postcode":"S4V 2R6",
    "sg:province":"SK",
    "wof:name":"W S Hawrylak Public Elem Schl",
    "wof:placetype":"venue"
},
  "geometry": {"coordinates":[-104.544059753,50.4215698242],"type":"Point"}
}