{
  "type": "Feature",
  "properties": {
    "addr:full":"Ottawa ON K1P 6E6",
    "addr:postcode":"k1p 6e6",
    "iso:country":"CA",
    "sg:city":"Ottawa",
    "sg:classifiers":[
        {
            "category":"Professional",
            "subcategory":"Employment Agencies",
            "type":"Services"
        }
    ],
    "sg:phone":"+1 613 232 9767",
    "sg:postcode":"K1P 6E6",
    "sg:province":"ON",
    "sg:tags":[
        "opportunity"
    ],
    "wof:name":"Artemp Personnel",
    "wof:placetype":"venue"
},
  "geometry": {"coordinates":[-75.7018737793,45.4191055298],"type":"Point"}
}