{
  "type": "Feature",
  "properties": {
    "iso:country":"CA",
    "sg:address":"2374 Sooke River Rd",
    "sg:city":"Sooke",
    "sg:classifiers":[
        {
            "category":"Wholesale",
            "subcategory":"Auto Parts",
            "type":"Manufacturing & Wholesale Goods"
        }
    ],
    "sg:phone":"+1 250 642 1524",
    "sg:postcode":"V0S 1N0",
    "sg:province":"BC",
    "sg:tags":[
        "automobile",
        "rebuilt",
        "wrecking"
    ],
    "wof:name":"Rcu Auto Parts",
    "wof:placetype":"venue"
},
  "geometry": {"coordinates":[-123.7004776,48.3949317932],"type":"Point"}
}