{
  "type": "Feature",
  "properties": {
    "addr:full":"2930 Erin Centre Blvd Mississauga ON L5M 7M4",
    "addr:housenumber":"2930",
    "addr:postcode":"l5m 7m4",
    "addr:street":"Erin Centre Blvd",
    "iso:country":"CA",
    "sg:address":"2930 Erin Centre Blvd",
    "sg:city":"Mississauga",
    "sg:classifiers":[
        {
            "category":"Health Services",
            "subcategory":"Nursing And Care Facility",
            "type":"Services"
        }
    ],
    "sg:phone":"+1 905 569 7155",
    "sg:postcode":"L5M 7M4",
    "sg:province":"ON",
    "sg:tags":[
        "home",
        "retirement",
        "convalescent",
        "community"
    ],
    "wof:name":"Village of Erin Meadows",
    "wof:placetype":"venue"
},
  "geometry": {"coordinates":[-79.7228469849,43.5530509949],"type":"Point"}
}