{
  "type": "Feature",
  "properties": {
    "addr:full":"2905 43 Ave Vernon BC V1T 3L4",
    "addr:housenumber":"2905",
    "addr:postcode":"v1t 3l4",
    "addr:street":"43 Ave",
    "iso:country":"CA",
    "sg:address":"2905 43 Ave",
    "sg:city":"Vernon",
    "sg:classifiers":[
        {
            "category":"Autos & Motor Vehicles",
            "subcategory":"Auto Supplies",
            "type":"Retail Goods"
        }
    ],
    "sg:phone":"+1 250 545 2361",
    "sg:postcode":"V1T 3L4",
    "sg:province":"BC",
    "sg:tags":[
        "automobile",
        "parts"
    ],
    "wof:name":"Uap Napa Auto Parts",
    "wof:placetype":"venue"
},
  "geometry": {"coordinates":[-119.27018700000001,50.27491],"type":"Point"}
}