{
  "type": "Feature",
  "properties": {
    "addr:full":"4520 97 St NW Edmonton AB T6E 5N9",
    "addr:housenumber":"4520",
    "addr:postcode":"t6e 5n9",
    "addr:street":"97 St Nw",
    "iso:country":"CA",
    "sg:address":"4520 97 St NW",
    "sg:city":"Edmonton",
    "sg:classifiers":[
        {
            "category":"Home & Garden",
            "subcategory":"Home Furnishings",
            "type":"Retail Goods"
        }
    ],
    "sg:phone":"+1 780 944 1728",
    "sg:postcode":"T6E 5N9",
    "sg:province":"AB",
    "sg:tags":[
        "venetian",
        "blind",
        "made",
        "drapery"
    ],
    "wof:name":"Accent Window Care",
    "wof:placetype":"venue"
},
  "geometry": {"coordinates":[-113.47949199999999,53.483433],"type":"Point"}
}