{
  "type": "Feature",
  "properties": {
    "addr:full":"Vancouver BC V6B 6H5",
    "addr:postcode":"v6b 6h5",
    "iso:country":"CA",
    "sg:city":"Vancouver",
    "sg:classifiers":[
        {
            "category":"Real Estate",
            "subcategory":"Architect",
            "type":"Services"
        }
    ],
    "sg:phone":"+1 604 605 8663",
    "sg:postcode":"V6B 6H5",
    "sg:province":"BC",
    "sg:tags":[
        "building",
        "construction"
    ],
    "wof:name":"Premise Building Corp",
    "wof:placetype":"venue"
},
  "geometry": {"coordinates":[-123.112876892,49.2835960388],"type":"Point"}
}