{
  "type": "Feature",
  "properties": {
    "addr:full":"2755 Cameron Taggart Rd Cobble Hill BC V0R 1L0",
    "addr:housenumber":"2755",
    "addr:postcode":"bc v0r 1l0",
    "addr:street":"Cameron Taggart Rd",
    "iso:country":"CA",
    "sg:address":"2755 Cameron Taggart Rd",
    "sg:city":"Cobble Hill",
    "sg:classifiers":[
        {
            "category":"Organizations",
            "subcategory":"Non-profit Organization",
            "type":"Services"
        }
    ],
    "sg:phone":"+1 250 727 0415",
    "sg:postcode":"V0R 1L0",
    "sg:province":"BC",
    "sg:tags":[
        "fund",
        "counselor",
        "raising"
    ],
    "wof:name":"Branta Can Fund Raising",
    "wof:placetype":"venue"
},
  "geometry": {"coordinates":[-123.60392761200001,48.686958313],"type":"Point"}
}