{
  "type": "Feature",
  "properties": {
    "addr:full":"1092 Valewood Trail Victoria BC V8X 5E3",
    "addr:housenumber":"1092",
    "addr:postcode":"v8x 5e3",
    "addr:street":"Valewood Trail",
    "iso:country":"CA",
    "sg:address":"1092 Valewood Trail",
    "sg:city":"Victoria",
    "sg:classifiers":[
        {
            "category":"Autos & Motor Vehicles",
            "subcategory":"Auto Supplies",
            "type":"Retail Goods"
        }
    ],
    "sg:phone":"+1 250 658 5359",
    "sg:postcode":"V8X 5E3",
    "sg:province":"BC",
    "sg:tags":[
        "automobile",
        "winch",
        "parts"
    ],
    "wof:name":"Top Gear Auto Accessories",
    "wof:placetype":"venue"
},
  "geometry": {"coordinates":[-123.36451700000001,48.428314],"type":"Point"}
}