{
  "type": "Feature",
  "properties": {
    "addr:full":"1018 5th St Estevan SK S4A 2B2",
    "addr:housenumber":"1018",
    "addr:postcode":"s4a 2b2",
    "addr:street":"5Th St",
    "iso:country":"CA",
    "sg:address":"1018 5th St",
    "sg:city":"Estevan",
    "sg:classifiers":[
        {
            "category":"Home & Garden",
            "subcategory":"Building Materials",
            "type":"Retail Goods"
        }
    ],
    "sg:phone":"+1 306 634 3689",
    "sg:postcode":"S4A 2B2",
    "sg:province":"SK",
    "sg:tags":[
        "lumber"
    ],
    "wof:name":"Home Building Ctr",
    "wof:placetype":"venue"
},
  "geometry": {"coordinates":[-102.990898132,49.1397972107],"type":"Point"}
}