{
  "type": "Feature",
  "properties": {
    "addr:full":"121 Mary St N Oshawa ON L1G 5B7",
    "addr:housenumber":"121",
    "addr:postcode":"l1g 5b7",
    "addr:street":"Mary St N",
    "iso:country":"CA",
    "sg:address":"121 Mary St N",
    "sg:city":"Oshawa",
    "sg:classifiers":[
        {
            "category":"Shopping",
            "subcategory":"Discount & Variety Stores",
            "type":"Retail Goods"
        }
    ],
    "sg:phone":"+1 905 725 7949",
    "sg:postcode":"L1G 5B7",
    "sg:province":"ON",
    "wof:name":"U Save Variety",
    "wof:placetype":"venue"
},
  "geometry": {"coordinates":[-78.86186981199999,43.9014511108],"type":"Point"}
}