{
  "type": "Feature",
  "properties": {
    "addr:full":"161 Rue Des Industries Montmagny QC G5V 4G2",
    "addr:housenumber":"161",
    "addr:postcode":"g5v 4g2",
    "addr:street":"Rue Des Industries",
    "iso:country":"CA",
    "sg:address":"161 Rue Des Industries",
    "sg:city":"Montmagny",
    "sg:classifiers":[
        {
            "category":"Wholesale",
            "subcategory":"Machinery & Supplies",
            "type":"Manufacturing & Wholesale Goods"
        }
    ],
    "sg:phone":"+1 418 248 4211",
    "sg:postcode":"G5V 4G2",
    "sg:province":"QC",
    "sg:tags":[
        "machine",
        "shop",
        "gasket"
    ],
    "wof:name":"Promax Usinage",
    "wof:placetype":"venue"
},
  "geometry": {"coordinates":[-70.570663,46.968773],"type":"Point"}
}