{
  "type": "Feature",
  "properties": {
    "addr:full":"Chapais QC G0W 1H0",
    "addr:postcode":"g0w 1h0",
    "iso:country":"CA",
    "sg:city":"Chapais",
    "sg:classifiers":[
        {
            "category":"Taxi",
            "type":"Transportation"
        }
    ],
    "sg:phone":"+1 418 745 3600",
    "sg:postcode":"G0W 1H0",
    "sg:province":"QC",
    "sg:tags":[
        "taxicab"
    ],
    "wof:name":"Taxi Chapais",
    "wof:placetype":"venue"
},
  "geometry": {"coordinates":[-74.856086731,49.7820587158],"type":"Point"}
}