{
  "type": "Feature",
  "properties": {
    "addr:full":"10008 82 Ave NW Edmonton AB T6E 1Z3",
    "addr:housenumber":"10008",
    "addr:postcode":"t6e 1z3",
    "addr:street":"82 Ave Nw",
    "iso:country":"CA",
    "sg:address":"10008 82 Ave NW",
    "sg:city":"Edmonton",
    "sg:classifiers":[
        {
            "category":"Shopping",
            "subcategory":"Bicycles & Sporting Goods",
            "type":"Retail Goods"
        }
    ],
    "sg:phone":"+1 780 439 4599",
    "sg:postcode":"T6E 1Z3",
    "sg:province":"AB",
    "wof:name":"Hardcore Mountain Bike Store",
    "wof:placetype":"venue"
},
  "geometry": {"coordinates":[-113.48915100000001,53.518337],"type":"Point"}
}