{
  "type": "Feature",
  "properties": {
    "iso:country":"CA",
    "sg:city":"Mississauga",
    "sg:classifiers":[
        {
            "category":"Manufacturing",
            "subcategory":"Signs",
            "type":"Manufacturing & Wholesale Goods"
        }
    ],
    "sg:phone":"+1 905 564 0831",
    "sg:postcode":"L5T 1E8",
    "sg:province":"ON",
    "wof:name":"Ultimate Signs",
    "wof:placetype":"venue"
},
  "geometry": {"coordinates":[-79.658951,43.648682],"type":"Point"}
}