{
  "type": "Feature",
  "properties": {
    "addr:full":"1081 Topsail Rd Mount Pearl NL A1N 5G1",
    "addr:housenumber":"1081",
    "addr:postcode":"a1n 5g1",
    "addr:street":"Topsail Rd",
    "iso:country":"CA",
    "sg:address":"1081 Topsail Rd",
    "sg:city":"Mount Pearl",
    "sg:classifiers":[
        {
            "category":"Retail",
            "subcategory":"Funeral Services",
            "type":"Services"
        }
    ],
    "sg:phone":"+1 709 364 1937",
    "sg:postcode":"A1N 5G1",
    "sg:province":"NL",
    "sg:tags":[
        "director"
    ],
    "wof:name":"Barrett's Funeral Home Ltd",
    "wof:placetype":"venue"
},
  "geometry": {"coordinates":[-52.8153800964,47.5260734558],"type":"Point"}
}