{
  "type": "Feature",
  "properties": {
    "iso:country":"CA",
    "sg:address":"8108 Beddington Blvd NW",
    "sg:city":"Calgary",
    "sg:classifiers":[
        {
            "category":"Restaurant",
            "type":"Food & Drink"
        }
    ],
    "sg:phone":"+1 403 295 0555",
    "sg:postcode":"T3K 2A8",
    "sg:province":"AB",
    "wof:name":"Boston Pizza",
    "wof:placetype":"venue"
},
  "geometry": {"coordinates":[-114.072357178,51.1253967285],"type":"Point"}
}