{
  "type": "Feature",
  "properties": {
    "addr:full":"10 Farrand St Thunder Bay ON P7A 3H5",
    "addr:housenumber":"10",
    "addr:postcode":"p7a 3h5",
    "addr:street":"Farrand St",
    "iso:country":"CA",
    "sg:address":"10 Farrand St",
    "sg:city":"Thunder Bay",
    "sg:classifiers":[
        {
            "category":"Organizations",
            "subcategory":"Religious Organization",
            "type":"Services"
        }
    ],
    "sg:phone":"+1 807 344 6756",
    "sg:postcode":"P7A 3H5",
    "sg:province":"ON",
    "sg:tags":[
        "church"
    ],
    "wof:name":"Our Saviour's Lutheran Church",
    "wof:placetype":"venue"
},
  "geometry": {"coordinates":[-89.21886444090001,48.4441947937],"type":"Point"}
}