{
  "type": "Feature",
  "properties": {
    "addr:full":"101 Queensway W # 130 Mississauga ON L5B 2P7",
    "addr:housenumber":"101",
    "addr:postcode":"l5b 2p7",
    "addr:street":"Queensway W # 130",
    "iso:country":"CA",
    "sg:address":"101 Queensway W # 130",
    "sg:city":"Mississauga",
    "sg:classifiers":[
        {
            "category":"Health Services",
            "subcategory":"Doctor",
            "type":"Services"
        }
    ],
    "sg:phone":"+1 905 279 9397",
    "sg:postcode":"L5B 2P7",
    "sg:province":"ON",
    "sg:tags":[
        "physician",
        "surgeon"
    ],
    "wof:name":"Mc Mullen, W MD",
    "wof:placetype":"venue"
},
  "geometry": {"coordinates":[-79.6106872559,43.5718040466],"type":"Point"}
}