{
  "type": "Feature",
  "properties": {
    "iso:country":"CA",
    "sg:address":"1155 Rue University",
    "sg:city":"Montreal",
    "sg:classifiers":[
        {
            "category":"Restaurant",
            "type":"Food & Drink"
        }
    ],
    "sg:phone":"+1 514 866 1410",
    "sg:postcode":"H3B 3A7",
    "sg:province":"QC",
    "sg:tags":[
        "shop",
        "tea",
        "coffee"
    ],
    "wof:name":"Mexicafe Canada Inc",
    "wof:placetype":"venue"
},
  "geometry": {"coordinates":[-73.56744384770001,45.5020866394],"type":"Point"}
}