{
  "type": "Feature",
  "properties": {
    "iso:country":"CA",
    "sg:address":"4100 Boul DE L'Auvergne",
    "sg:city":"Quebec",
    "sg:classifiers":[
        {
            "category":"Health Services",
            "subcategory":"Chiropractor",
            "type":"Services"
        }
    ],
    "sg:phone":"+1 418 845 1234",
    "sg:postcode":"G2C 1T8",
    "sg:province":"QC",
    "wof:name":"Action Chiropratique Pierre",
    "wof:placetype":"venue"
},
  "geometry": {"coordinates":[-71.348129,46.830212],"type":"Point"}
}