{
  "type": "Feature",
  "properties": {
    "iso:country":"CA",
    "sg:address":"224 Miron Dr",
    "sg:city":"Hay River",
    "sg:classifiers":[
        {
            "category":"Home & Garden",
            "subcategory":"Furniture",
            "type":"Retail Goods"
        }
    ],
    "sg:phone":"+1 867 874 6724",
    "sg:postcode":"X0E 0R2",
    "sg:province":"NT",
    "sg:tags":[
        "kitchen",
        "maker",
        "cabinet"
    ],
    "wof:name":"K P Woodwright Inc",
    "wof:placetype":"venue"
},
  "geometry": {"coordinates":[-115.815635681,60.7945518494],"type":"Point"}
}