{
  "type": "Feature",
  "properties": {
    "iso:country":"CA",
    "sg:address":"121 Boul Maple",
    "sg:city":"Chateauguay",
    "sg:classifiers":[
        {
            "category":"Personal",
            "subcategory":"Beauty Salon",
            "type":"Services"
        }
    ],
    "sg:phone":"+1 450 698 2441",
    "sg:postcode":"J6J 3P9",
    "sg:province":"QC",
    "wof:name":"Salon Girondin Inc",
    "wof:placetype":"venue"
},
  "geometry": {"coordinates":[-73.7323684692,45.3634872437],"type":"Point"}
}