{
  "type": "Feature",
  "properties": {
    "iso:country":"CA",
    "sg:address":"105 Villa St # 200",
    "sg:city":"Thunder Bay",
    "sg:classifiers":[
        {
            "category":"Professional",
            "subcategory":"Engineering",
            "type":"Services"
        }
    ],
    "sg:phone":"+1 807 345 1131",
    "sg:postcode":"P7A 7W5",
    "sg:province":"ON",
    "sg:tags":[
        "engineer"
    ],
    "wof:name":"Jml Engineering Ltd",
    "wof:placetype":"venue"
},
  "geometry": {"coordinates":[-89.215164,48.437523],"type":"Point"}
}