{
  "type": "Feature",
  "properties": {
    "addr:full":"489 Elgin St Port Elgin ON N0H 2C0",
    "addr:housenumber":"489",
    "addr:postcode":"n0h 2c0",
    "addr:street":"Elgin St",
    "iso:country":"CA",
    "sg:address":"489 Elgin St",
    "sg:city":"Port Elgin",
    "sg:classifiers":[
        {
            "category":"Shopping",
            "type":"Retail Goods"
        }
    ],
    "sg:phone":"+1 519 832 9195",
    "sg:postcode":"N0H 2C0",
    "sg:province":"ON",
    "sg:tags":[
        "picture",
        "frame"
    ],
    "wof:name":"Frames By Deb",
    "wof:placetype":"venue"
},
  "geometry": {"coordinates":[-81.390739,44.439968],"type":"Point"}
}