{
  "type": "Feature",
  "properties": {
    "addr:full":"609 1st Ave Maple Creek SK S0N 1N0",
    "addr:housenumber":"609",
    "addr:postcode":"s0n 1n0",
    "addr:street":"1St Ave",
    "iso:country":"CA",
    "sg:address":"609 1st Ave",
    "sg:city":"Maple Creek",
    "sg:classifiers":[
        {
            "category":"Retail",
            "subcategory":"Laundry & Dry Cleaning",
            "type":"Services"
        }
    ],
    "sg:phone":"+1 306 662 2740",
    "sg:postcode":"S0N 1N0",
    "sg:province":"SK",
    "sg:tags":[
        "cleaners"
    ],
    "wof:name":"Cypress Cleaners",
    "wof:placetype":"venue"
},
  "geometry": {"coordinates":[-109.480407715,49.9065856934],"type":"Point"}
}