{
  "type": "Feature",
  "properties": {
    "iso:country":"CA",
    "sg:city":"Faro",
    "sg:classifiers":[
        {
            "category":"Shopping",
            "subcategory":"Catalog Store",
            "type":"Retail Goods"
        }
    ],
    "sg:phone":"+1 867 994 2328",
    "sg:postcode":"Y0B 1K0",
    "sg:province":"YT",
    "sg:tags":[
        "mail",
        "order",
        "internet"
    ],
    "wof:name":"Sears Canada Inc",
    "wof:placetype":"venue"
},
  "geometry": {"coordinates":[-133.354812622,62.2291564941],"type":"Point"}
}