{
  "type": "Feature",
  "properties": {
    "addr:full":"PO Box 205 Hilton Beach ON P0R 1G0",
    "addr:housenumber":"po",
    "addr:postcode":"p0r 1g0",
    "addr:street":"Box 205",
    "iso:country":"CA",
    "sg:address":"PO Box 205",
    "sg:city":"Hilton Beach",
    "sg:classifiers":[
        {
            "category":"Government",
            "subcategory":"Office",
            "type":"Public Place"
        }
    ],
    "sg:phone":"+1 705 246 1781",
    "sg:postcode":"P0R 1G0",
    "sg:province":"ON",
    "sg:tags":[
        "village"
    ],
    "wof:name":"Hilton Municipal Garage",
    "wof:placetype":"venue"
},
  "geometry": {"coordinates":[-83.88988500000001,46.256531],"type":"Point"}
}