{
  "type": "Feature",
  "properties": {
    "iso:country":"CA",
    "sg:address":"552 Boul Wilfrid-Hamel",
    "sg:city":"Quebec",
    "sg:classifiers":[
        {
            "category":"Shopping",
            "subcategory":"Gifts & Souvenirs",
            "type":"Retail Goods"
        }
    ],
    "sg:phone":"+1 418 522 6247",
    "sg:postcode":"G1M 3E5",
    "sg:province":"QC",
    "sg:tags":[
        "shop"
    ],
    "wof:name":"Arteq",
    "wof:placetype":"venue"
},
  "geometry": {"coordinates":[-71.248924,46.820335],"type":"Point"}
}