{
  "type": "Feature",
  "properties": {
    "iso:country":"CA",
    "sg:address":"9806 100 St",
    "sg:city":"Morinville",
    "sg:classifiers":[
        {
            "category":"Health Services",
            "subcategory":"Medical Lab",
            "type":"Services"
        }
    ],
    "sg:phone":"+1 780 939 3190",
    "sg:postcode":"T8R 1G3",
    "sg:province":"AB",
    "wof:name":"Bachand Denture Ctr",
    "wof:placetype":"venue"
},
  "geometry": {"coordinates":[-113.645088196,53.7989425659],"type":"Point"}
}