{
  "type": "Feature",
  "properties": {
    "iso:country":"CA",
    "sg:address":"2658 Rue Notre-Dame O",
    "sg:city":"Montreal",
    "sg:classifiers":[
        {
            "category":"Shopping",
            "subcategory":"Used Merchandise",
            "type":"Retail Goods"
        }
    ],
    "sg:phone":"+1 514 933 9355",
    "sg:postcode":"H3J 1N7",
    "sg:province":"QC",
    "sg:tags":[
        "antique"
    ],
    "wof:name":"Celine Antiquaire",
    "wof:placetype":"venue"
},
  "geometry": {"coordinates":[-73.543236,45.531147],"type":"Point"}
}