{
  "type": "Feature",
  "properties": {
    "addr:full":"2658 Rue Notre-Dame O Montreal QC H3J 1N7",
    "addr:housenumber":"2658",
    "addr:postcode":"h3j 1n7",
    "addr:street":"Rue Notre-Dame O",
    "iso:country":"CA",
    "sg:address":"2658 Rue Notre-Dame O",
    "sg:city":"Montreal",
    "sg:classifiers":[
        {
            "category":"Shopping",
            "subcategory":"Used Merchandise",
            "type":"Retail Goods"
        }
    ],
    "sg:phone":"+1 514 933 9355",
    "sg:postcode":"H3J 1N7",
    "sg:province":"QC",
    "sg:tags":[
        "antique"
    ],
    "wof:name":"Celine Antiquaire",
    "wof:placetype":"venue"
},
  "geometry": {"coordinates":[-73.54323599999999,45.531147],"type":"Point"}
}