{
  "type": "Feature",
  "properties": {
    "addr:full":"Winnipeg MB R2H 1C7",
    "addr:postcode":"r2h 1c7",
    "iso:country":"CA",
    "sg:city":"Winnipeg",
    "sg:classifiers":[
        {
            "category":"Real Estate",
            "subcategory":"Real Estate Operator",
            "type":"Services"
        }
    ],
    "sg:phone":"+1 204 237 6682",
    "sg:postcode":"R2H 1C7",
    "sg:province":"MB",
    "sg:tags":[
        "apartment"
    ],
    "wof:name":"Enfield Estates",
    "wof:placetype":"venue"
},
  "geometry": {"coordinates":[-97.11312103269999,49.8838043213],"type":"Point"}
}