{
  "type": "Feature",
  "properties": {
    "addr:full":"375 Lynden Cres London ON N6K 2J1",
    "addr:housenumber":"375",
    "addr:postcode":"n6k 2j1",
    "addr:street":"Lynden Cres",
    "iso:country":"CA",
    "sg:address":"375 Lynden Cres",
    "sg:city":"London",
    "sg:classifiers":[
        {
            "category":"Education",
            "subcategory":"School",
            "type":"Public Place"
        }
    ],
    "sg:phone":"+1 519 471 5040",
    "sg:postcode":"N6K 2J1",
    "sg:province":"ON",
    "wof:name":"St George School",
    "wof:placetype":"venue"
},
  "geometry": {"coordinates":[-81.3260269165,42.956451416],"type":"Point"}
}