{
  "type": "Feature",
  "properties": {
    "addr:full":"11639 Rue Joly Pierrefonds QC H8Y 1E5",
    "addr:housenumber":"11639",
    "addr:postcode":"h8y 1e5",
    "addr:street":"Rue Joly",
    "iso:country":"CA",
    "sg:address":"11639 Rue Joly",
    "sg:city":"Pierrefonds",
    "sg:classifiers":[
        {
            "category":"Professional",
            "subcategory":"Detective & Security Services",
            "type":"Services"
        }
    ],
    "sg:phone":"+1 514 685 8886",
    "sg:postcode":"H8Y 1E5",
    "sg:province":"QC",
    "sg:tags":[
        "control",
        "burglary",
        "protective",
        "system",
        "robbery"
    ],
    "wof:name":"Alarme Imperial Alarm",
    "wof:placetype":"venue"
},
  "geometry": {"coordinates":[-73.814835,45.50433],"type":"Point"}
}