{
  "type": "Feature",
  "properties": {
    "iso:country":"CA",
    "sg:address":"2831 Regional Rd 81",
    "sg:city":"Jordan Station",
    "sg:classifiers":[
        {
            "category":"Education",
            "subcategory":"School",
            "type":"Public Place"
        }
    ],
    "sg:phone":"+1 905 562 7491",
    "sg:postcode":"L0R 1S0",
    "sg:province":"ON",
    "wof:name":"Jordan School",
    "wof:placetype":"venue"
},
  "geometry": {"coordinates":[-79.3641662598,43.1635818481],"type":"Point"}
}