{
  "type": "Feature",
  "properties": {
    "addr:full":"Regina SK S4R 0P2",
    "addr:postcode":"s4r 0p2",
    "iso:country":"CA",
    "sg:city":"Regina",
    "sg:classifiers":[
        {
            "category":"Real Estate",
            "subcategory":"Real Estate Operator",
            "type":"Services"
        }
    ],
    "sg:phone":"+1 306 949 6559",
    "sg:postcode":"S4R 0P2",
    "sg:province":"SK",
    "sg:tags":[
        "apartment"
    ],
    "wof:name":"Haworth Manor",
    "wof:placetype":"venue"
},
  "geometry": {"coordinates":[-104.619003296,50.4790382385],"type":"Point"}
}