{
  "type": "Feature",
  "properties": {
    "addr:full":"840 Boul DE Perigny Chambly QC J3L 1W3",
    "addr:housenumber":"840",
    "addr:postcode":"j3l 1w3",
    "addr:street":"Boul De Perigny",
    "iso:country":"CA",
    "sg:address":"840 Boul DE Perigny",
    "sg:city":"Chambly",
    "sg:classifiers":[
        {
            "category":"Personal",
            "subcategory":"Beauty Salon",
            "type":"Services"
        }
    ],
    "sg:phone":"+1 450 447 2920",
    "sg:postcode":"J3L 1W3",
    "sg:province":"QC",
    "wof:name":"Salon Coiffure Fanny Enr",
    "wof:placetype":"venue"
},
  "geometry": {"coordinates":[-73.302437,45.45517],"type":"Point"}
}