{
  "type": "Feature",
  "properties": {
    "iso:country":"CA",
    "sg:address":"185 Thickson Rd N",
    "sg:city":"Whitby",
    "sg:classifiers":[
        {
            "category":"Personal",
            "subcategory":"Beauty Salon",
            "type":"Services"
        }
    ],
    "sg:phone":"+1 905 436 1324",
    "sg:postcode":"L1N 6T9",
    "sg:province":"ON",
    "wof:name":"Laura's Hair Design",
    "wof:placetype":"venue"
},
  "geometry": {"coordinates":[-78.917725,43.898495],"type":"Point"}
}