{
  "type": "Feature",
  "properties": {
    "addr:full":"350 Wentworth St E Oshawa ON L1H 7R7",
    "addr:housenumber":"350",
    "addr:postcode":"l1h 7r7",
    "addr:street":"Wentworth St E",
    "iso:country":"CA",
    "sg:address":"350 Wentworth St E",
    "sg:city":"Oshawa",
    "sg:classifiers":[
        {
            "category":"Restaurant",
            "type":"Food & Drink"
        }
    ],
    "sg:phone":"+1 905 579 4081",
    "sg:postcode":"L1H 7R7",
    "sg:province":"ON",
    "wof:name":"Marwood Park Restaurant & Tvrn",
    "wof:placetype":"venue"
},
  "geometry": {"coordinates":[-78.834045,43.877548],"type":"Point"}
}