{
  "type": "Feature",
  "properties": {
    "addr:full":"1255 Prince Edward St Melville SK S0A 2P0",
    "addr:housenumber":"1255",
    "addr:postcode":"s0a 2p0",
    "addr:street":"Prince Edward St",
    "iso:country":"CA",
    "sg:address":"1255 Prince Edward St",
    "sg:city":"Melville",
    "sg:classifiers":[
        {
            "category":"Recreation",
            "type":"Entertainment"
        }
    ],
    "sg:phone":"+1 306 728 4111",
    "sg:postcode":"S0A 2P0",
    "sg:province":"SK",
    "sg:tags":[
        "provincial",
        "parks"
    ],
    "wof:name":"Melville Regional Park",
    "wof:placetype":"venue"
},
  "geometry": {"coordinates":[-102.796257,50.930874],"type":"Point"}
}