{
  "type": "Feature",
  "properties": {
    "iso:country":"CA",
    "sg:city":"Aurora",
    "sg:classifiers":[
        {
            "category":"Professional",
            "subcategory":"Advertising",
            "type":"Services"
        }
    ],
    "sg:phone":"+1 416 798 7557",
    "sg:postcode":"L4G 4C3",
    "sg:province":"ON",
    "sg:tags":[
        "mail"
    ],
    "wof:name":"Andrew's Mailing Svc",
    "wof:placetype":"venue"
},
  "geometry": {"coordinates":[-79.462799,44.013721],"type":"Point"}
}