{
  "type": "Feature",
  "properties": {
    "addr:full":"1623 Wyandotte St E Windsor ON N8Y 1C8",
    "addr:housenumber":"1623",
    "addr:postcode":"n8y 1c8",
    "addr:street":"Wyandotte St E",
    "iso:country":"CA",
    "sg:address":"1623 Wyandotte St E",
    "sg:city":"Windsor",
    "sg:classifiers":[
        {
            "category":"Home & Garden",
            "subcategory":"Furniture",
            "type":"Retail Goods"
        }
    ],
    "sg:phone":"+1 519 252 9174",
    "sg:postcode":"N8Y 1C8",
    "sg:province":"ON",
    "wof:name":"Icon For the Home",
    "wof:placetype":"venue"
},
  "geometry": {"coordinates":[-83.015388,42.32172],"type":"Point"}
}