{
  "type": "Feature",
  "properties": {
    "addr:full":"North York ON M9L 1Y3",
    "addr:postcode":"m9l 1y3",
    "iso:country":"CA",
    "sg:city":"North York",
    "sg:classifiers":[
        {
            "category":"Retail",
            "subcategory":"Auto Repair",
            "type":"Services"
        }
    ],
    "sg:phone":"+1 416 745 8888",
    "sg:postcode":"M9L 1Y3",
    "sg:province":"ON",
    "sg:tags":[
        "body",
        "automobile",
        "painting"
    ],
    "wof:name":"Great Wall",
    "wof:placetype":"venue"
},
  "geometry": {"coordinates":[-79.56043243409999,43.7586174011],"type":"Point"}
}