{
  "type": "Feature",
  "properties": {
    "addr:full":"75 Rue Principale Armagh QC G0R 1A0",
    "addr:housenumber":"75",
    "addr:postcode":"g0r 1a0",
    "addr:street":"Rue Principale",
    "iso:country":"CA",
    "sg:address":"75 Rue Principale",
    "sg:city":"Armagh",
    "sg:classifiers":[
        {
            "category":"Home & Garden",
            "subcategory":"Hardware",
            "type":"Retail Goods"
        }
    ],
    "sg:phone":"+1 418 466 1330",
    "sg:postcode":"G0R 1A0",
    "sg:province":"QC",
    "wof:name":"Quincaillerie Armagh",
    "wof:placetype":"venue"
},
  "geometry": {"coordinates":[-70.58910400000001,46.743511],"type":"Point"}
}