{
  "type": "Feature",
  "properties": {
    "addr:full":"1411 Boul Pere-Lelievre Quebec QC G1M 1N7",
    "addr:housenumber":"1411",
    "addr:postcode":"g1m 1n7",
    "addr:street":"Boul Pere-Lelievre",
    "iso:country":"CA",
    "sg:address":"1411 Boul Pere-Lelievre",
    "sg:city":"Quebec",
    "sg:classifiers":[
        {
            "category":"Social Services",
            "type":"Services"
        }
    ],
    "sg:phone":"+1 418 687 6635",
    "sg:postcode":"G1M 1N7",
    "sg:province":"QC",
    "sg:tags":[
        "organization",
        "welfare"
    ],
    "wof:name":"Noel Du Bonheur",
    "wof:placetype":"venue"
},
  "geometry": {"coordinates":[-71.27773999999999,46.811218],"type":"Point"}
}