{
  "type": "Feature",
  "properties": {
    "addr:full":"6415 Knight Dr Delta BC V4E 1S2",
    "addr:housenumber":"6415",
    "addr:postcode":"v4e 1s2",
    "addr:street":"Knight Dr",
    "iso:country":"CA",
    "sg:address":"6415 Knight Dr",
    "sg:city":"Delta",
    "sg:classifiers":[
        {
            "category":"Social Services",
            "subcategory":"Child Care",
            "type":"Services"
        }
    ],
    "sg:phone":"+1 604 502 0691",
    "sg:postcode":"V4E 1S2",
    "sg:province":"BC",
    "wof:name":"Sunshine Hills Montessori",
    "wof:placetype":"venue"
},
  "geometry": {"coordinates":[-122.90323600000001,49.119781],"type":"Point"}
}