{
  "type": "Feature",
  "properties": {
    "addr:full":"550 Rue Principale LA Sarre QC J9Z 2A1",
    "addr:housenumber":"550",
    "addr:postcode":"j9z 2a1",
    "addr:street":"Rue Principale La Sarre",
    "iso:country":"CA",
    "sg:address":"550 Rue Principale",
    "sg:city":"LA Sarre",
    "sg:classifiers":[
        {
            "category":"Government",
            "subcategory":"Office",
            "type":"Public Place"
        }
    ],
    "sg:phone":"+1 819 333 2291",
    "sg:postcode":"J9Z 2A1",
    "sg:province":"QC",
    "sg:tags":[
        "village"
    ],
    "wof:name":"LA Sarre Commission Des Loisir",
    "wof:placetype":"venue"
},
  "geometry": {"coordinates":[-79.20552062989999,48.7946014404],"type":"Point"}
}