{
  "type": "Feature",
  "properties": {
    "addr:full":"21 Robert Dollard Dr Bracebridge ON P1L 1P9",
    "addr:housenumber":"21",
    "addr:postcode":"p1l 1p9",
    "addr:street":"Robert Dollard Dr",
    "iso:country":"CA",
    "sg:address":"21 Robert Dollard Dr",
    "sg:city":"Bracebridge",
    "sg:classifiers":[
        {
            "category":"Autos & Motor Vehicles",
            "subcategory":"Automobile Sales",
            "type":"Retail Goods"
        }
    ],
    "sg:phone":"+1 705 645 6575",
    "sg:postcode":"P1L 1P9",
    "sg:province":"ON",
    "sg:tags":[
        "car",
        "dealer"
    ],
    "wof:name":"Muskoka Kia",
    "wof:placetype":"venue"
},
  "geometry": {"coordinates":[-79.3136062622,45.0248947144],"type":"Point"}
}