{
  "type": "Feature",
  "properties": {
    "addr:full":"305 North Front St Belleville ON K8P 3C3",
    "addr:housenumber":"305",
    "addr:postcode":"k8p 3c3",
    "addr:street":"North Front St",
    "iso:country":"CA",
    "sg:address":"305 North Front St",
    "sg:city":"Belleville",
    "sg:classifiers":[
        {
            "category":"Restaurant",
            "type":"Food & Drink"
        }
    ],
    "sg:phone":"+1 613 966 6617",
    "sg:postcode":"K8P 3C3",
    "sg:province":"ON",
    "wof:name":"Pita Pit",
    "wof:placetype":"venue"
},
  "geometry": {"coordinates":[-77.394203,44.184307],"type":"Point"}
}