{
  "type": "Feature",
  "properties": {
    "addr:full":"24 4th Ave E Vancouver BC V5T 1E8",
    "addr:housenumber":"24",
    "addr:postcode":"v5t 1e8",
    "addr:street":"4Th Ave E",
    "iso:country":"CA",
    "sg:address":"24 4th Ave E",
    "sg:city":"Vancouver",
    "sg:classifiers":[
        {
            "category":"Building & Trades",
            "subcategory":"Electrical",
            "type":"Services"
        }
    ],
    "sg:phone":"+1 604 873 0402",
    "sg:postcode":"V5T 1E8",
    "sg:province":"BC",
    "sg:tags":[
        "electric",
        "contractor"
    ],
    "wof:name":"Del Industries Ltd",
    "wof:placetype":"venue"
},
  "geometry": {"coordinates":[-123.10419464100001,49.2672615051],"type":"Point"}
}