{
  "type": "Feature",
  "properties": {
    "addr:full":"5354 Av Notre-Dame-DE-Grace Montreal QC H4A 1L3",
    "addr:housenumber":"5354",
    "addr:postcode":"h4a 1l3",
    "addr:street":"Av Notre-Dame-De-Grace",
    "iso:country":"CA",
    "sg:address":"5354 Av Notre-Dame-DE-Grace",
    "sg:city":"Montreal",
    "sg:classifiers":[
        {
            "category":"Professional",
            "subcategory":"Business Services",
            "type":"Services"
        }
    ],
    "sg:phone":"+1 514 482 2073",
    "sg:postcode":"H4A 1L3",
    "sg:province":"QC",
    "sg:tags":[
        "notary"
    ],
    "wof:name":"Brossard, Jean-Pierre",
    "wof:placetype":"venue"
},
  "geometry": {"coordinates":[-73.615921,45.476498],"type":"Point"}
}