{
  "type": "Feature",
  "properties": {
    "addr:full":"7150 125 Rte Chertsey QC J0K 3K0",
    "addr:housenumber":"7150",
    "addr:postcode":"j0k 3k0",
    "addr:street":"125 Rte",
    "iso:country":"CA",
    "sg:address":"7150 125 Rte",
    "sg:city":"Chertsey",
    "sg:classifiers":[
        {
            "category":"Autos & Motor Vehicles",
            "subcategory":"Motorcycle Sales",
            "type":"Retail Goods"
        }
    ],
    "sg:phone":"+1 450 882 2888",
    "sg:postcode":"J0K 3K0",
    "sg:province":"QC",
    "sg:tags":[
        "all",
        "terrain",
        "scooter"
    ],
    "wof:name":"Latendresse Sports Inc",
    "wof:placetype":"venue"
},
  "geometry": {"coordinates":[-73.89223480219999,46.0730743408],"type":"Point"}
}