{
  "type": "Feature",
  "properties": {
    "addr:full":"Little Fort BC V0E 2C0",
    "addr:postcode":"v0e 2c0",
    "iso:country":"CA",
    "sg:city":"Little Fort",
    "sg:classifiers":[
        {
            "category":"Autos & Motor Vehicles",
            "subcategory":"Fuel & Gas Station",
            "type":"Retail Goods"
        }
    ],
    "sg:phone":"+1 250 677 4224",
    "sg:postcode":"V0E 2C0",
    "sg:province":"BC",
    "sg:tags":[
        "oil",
        "merchandise",
        "general"
    ],
    "wof:name":"Little Fort General Store",
    "wof:placetype":"venue"
},
  "geometry": {"coordinates":[-120.21006800000001,51.42598],"type":"Point"}
}