{
  "type": "Feature",
  "properties": {
    "addr:full":"Regina SK S4V 2Y7",
    "addr:postcode":"s4v 2y7",
    "iso:country":"CA",
    "sg:city":"Regina",
    "sg:classifiers":[
        {
            "category":"Restaurant",
            "type":"Food & Drink"
        }
    ],
    "sg:phone":"+1 306 757 1666",
    "sg:postcode":"S4V 2Y7",
    "sg:province":"SK",
    "wof:name":"Mediterranean Bistro",
    "wof:placetype":"venue"
},
  "geometry": {"coordinates":[-104.53898599999999,50.445847],"type":"Point"}
}