{
  "type": "Feature",
  "properties": {
    "iso:country":"CA",
    "sg:city":"Montreal",
    "sg:classifiers":[
        {
            "category":"Insurance",
            "subcategory":"Insurance Agent",
            "type":"Services"
        }
    ],
    "sg:phone":"+1 514 284 6711",
    "sg:postcode":"H3G 1G2",
    "sg:province":"QC",
    "wof:name":"Compagnie D'Assurance Standard",
    "wof:placetype":"venue"
},
  "geometry": {"coordinates":[-73.5653381348,45.5241394043],"type":"Point"}
}