{
  "type": "Feature",
  "properties": {
    "iso:country":"CA",
    "sg:address":"368 Kerr St",
    "sg:city":"Oakville",
    "sg:classifiers":[
        {
            "category":"Retail",
            "subcategory":"Laundry & Dry Cleaning",
            "type":"Services"
        }
    ],
    "sg:phone":"+1 905 845 6242",
    "sg:postcode":"L6K 3B8",
    "sg:province":"ON",
    "sg:tags":[
        "cleaners"
    ],
    "wof:name":"Oakville Dry Cleaners",
    "wof:placetype":"venue"
},
  "geometry": {"coordinates":[-79.682838,43.444218],"type":"Point"}
}