{
  "type": "Feature",
  "properties": {
    "addr:full":"Brampton ON L6W 3J1",
    "addr:postcode":"l6w 3j1",
    "iso:country":"CA",
    "sg:city":"Brampton",
    "sg:classifiers":[
        {
            "category":"Shopping",
            "subcategory":"Bicycles & Sporting Goods",
            "type":"Retail Goods"
        }
    ],
    "sg:phone":"+1 905 455 5566",
    "sg:postcode":"L6W 3J1",
    "sg:province":"ON",
    "wof:name":"Sports Unlimited",
    "wof:placetype":"venue"
},
  "geometry": {"coordinates":[-79.74118804930001,43.7009544373],"type":"Point"}
}