{
  "type": "Feature",
  "properties": {
    "addr:full":"333 Rue DE LA Jacques-Cartier Victoriaville QC G6T 1Y1",
    "addr:housenumber":"333",
    "addr:postcode":"g6t 1y1",
    "addr:street":"Rue De La Jacques-Cartier",
    "iso:country":"CA",
    "sg:address":"333 Rue DE LA Jacques-Cartier",
    "sg:city":"Victoriaville",
    "sg:classifiers":[
        {
            "category":"Wholesale",
            "subcategory":"Machinery & Supplies",
            "type":"Manufacturing & Wholesale Goods"
        }
    ],
    "sg:phone":"+1 819 752 3388",
    "sg:postcode":"G6T 1Y1",
    "sg:province":"QC",
    "sg:tags":[
        "director",
        "funeral"
    ],
    "wof:name":"Cercueils Vic Royal Inc",
    "wof:placetype":"venue"
},
  "geometry": {"coordinates":[-71.943054,46.082363],"type":"Point"}
}