{
  "type": "Feature",
  "properties": {
    "addr:full":"263 John St S Hamilton ON L8N 2C9",
    "addr:housenumber":"263",
    "addr:postcode":"l8n 2c9",
    "addr:street":"John St S",
    "iso:country":"CA",
    "sg:address":"263 John St S",
    "sg:city":"Hamilton",
    "sg:classifiers":[
        {
            "category":"Professional",
            "subcategory":"Lawyer & Legal Services",
            "type":"Services"
        }
    ],
    "sg:phone":"+1 905 523 7052",
    "sg:postcode":"L8N 2C9",
    "sg:province":"ON",
    "sg:tags":[
        "attorney"
    ],
    "wof:name":"Scoccia, Thomas R QC",
    "wof:placetype":"venue"
},
  "geometry": {"coordinates":[-79.868866,43.24942],"type":"Point"}
}