{
  "type": "Feature",
  "properties": {
    "addr:full":"Longueuil QC J4H 2J3",
    "addr:postcode":"j4h 2j3",
    "iso:country":"CA",
    "sg:city":"Longueuil",
    "sg:classifiers":[
        {
            "category":"Real Estate",
            "subcategory":"Real Estate Agent",
            "type":"Services"
        }
    ],
    "sg:phone":"+1 450 442 9520",
    "sg:postcode":"J4H 2J3",
    "sg:province":"QC",
    "sg:tags":[
        "management"
    ],
    "wof:name":"Capada Limitee",
    "wof:placetype":"venue"
},
  "geometry": {"coordinates":[-73.5179977417,45.5328521729],"type":"Point"}
}