{
  "type": "Feature",
  "properties": {
    "addr:full":"1300 Av Maguire Sillery QC G1T 1Z3",
    "addr:housenumber":"1300",
    "addr:postcode":"g1t 1z3",
    "addr:street":"Av Maguire",
    "iso:country":"CA",
    "sg:address":"1300 Av Maguire",
    "sg:city":"Sillery",
    "sg:classifiers":[
        {
            "category":"Shopping",
            "subcategory":"Books",
            "type":"Retail Goods"
        }
    ],
    "sg:phone":"+1 418 681 0254",
    "sg:postcode":"G1T 1Z3",
    "sg:province":"QC",
    "sg:tags":[
        "dealer"
    ],
    "wof:name":"Librairie Vaugeois Inc",
    "wof:placetype":"venue"
},
  "geometry": {"coordinates":[-71.251938,46.781555],"type":"Point"}
}