{
  "type": "Feature",
  "properties": {
    "addr:full":"1695 Boul Laval # 205 Laval QC H7S 2M2",
    "addr:housenumber":"1695;# 205",
    "addr:postcode":"h7s 2m2",
    "addr:street":"Boul Laval",
    "iso:country":"CA",
    "sg:address":"1695 Boul Laval # 205",
    "sg:city":"Laval",
    "sg:classifiers":[
        {
            "category":"Banks & Credit Unions",
            "subcategory":"Investment Brokerage",
            "type":"Services"
        }
    ],
    "sg:phone":"+1 450 967 5525",
    "sg:postcode":"H7S 2M2",
    "sg:province":"QC",
    "sg:tags":[
        "bankruptcy",
        "consultant",
        "planning",
        "financial",
        "trustee"
    ],
    "wof:name":"Labelle Marquis Inc",
    "wof:placetype":"venue"
},
  "geometry": {"coordinates":[-73.72026099999999,45.57103],"type":"Point"}
}