{
  "type": "Feature",
  "properties": {
    "addr:full":"355 Rue Chapel Grand-Sault/Grand Falls NB E3Z 2M5",
    "addr:housenumber":"355",
    "addr:postcode":"e3z 2m5",
    "addr:street":"Rue Chapel",
    "iso:country":"CA",
    "sg:address":"355 Rue Chapel",
    "sg:city":"Grand-Sault/Grand Falls",
    "sg:classifiers":[
        {
            "category":"Organizations",
            "subcategory":"Religious Organization",
            "type":"Services"
        }
    ],
    "sg:phone":"+1 506 473 3783",
    "sg:postcode":"E3Z 2M5",
    "sg:province":"NB",
    "sg:tags":[
        "church"
    ],
    "wof:name":"Presbytere Assomption",
    "wof:placetype":"venue"
},
  "geometry": {"coordinates":[-67.741165,47.044559],"type":"Point"}
}