{
  "type": "Feature",
  "properties": {
    "addr:full":"915 Av Du Pont S Alma QC G8B 2V5",
    "addr:postcode":"g8b 2v5",
    "addr:street":"915 Av Du Pont S",
    "iso:country":"CA",
    "sg:address":"915 Av Du Pont S",
    "sg:city":"Alma",
    "sg:classifiers":[
        {
            "category":"Cinema",
            "subcategory":"Movie Rental",
            "type":"Entertainment"
        }
    ],
    "sg:phone":"+1 418 668 2245",
    "sg:postcode":"G8B 2V5",
    "sg:province":"QC",
    "sg:tags":[
        "leasing",
        "video",
        "disc",
        "tape"
    ],
    "wof:name":"Premiere Video",
    "wof:placetype":"venue"
},
  "geometry": {"coordinates":[-71.6472702026,48.5366401672],"type":"Point"}
}