{
  "type": "Feature",
  "properties": {
    "addr:full":"105 Main St E Hawkesbury ON K6A 1A1",
    "addr:housenumber":"105",
    "addr:postcode":"k6a 1a1",
    "addr:street":"Main St E",
    "iso:country":"CA",
    "sg:address":"105 Main St E",
    "sg:city":"Hawkesbury",
    "sg:classifiers":[
        {
            "category":"Banks & Credit Unions",
            "subcategory":"Bank",
            "type":"Services"
        }
    ],
    "sg:phone":"+1 613 632 2731",
    "sg:postcode":"K6A 1A1",
    "sg:province":"ON",
    "sg:tags":[
        "loan",
        "real estate"
    ],
    "wof:name":"Citifinancial",
    "wof:placetype":"venue"
},
  "geometry": {"coordinates":[-74.6109466553,45.609664917],"type":"Point"}
}