{
  "type": "Feature",
  "properties": {
    "addr:full":"9076 Yonge St Richmond Hill ON L4C 6Z9",
    "addr:housenumber":"9076",
    "addr:postcode":"l4c 6z9",
    "addr:street":"Yonge St",
    "iso:country":"CA",
    "sg:address":"9076 Yonge St",
    "sg:city":"Richmond Hill",
    "sg:classifiers":[
        {
            "category":"Autos & Motor Vehicles",
            "subcategory":"Fuel & Gas Station",
            "type":"Retail Goods"
        }
    ],
    "sg:phone":"+1 416 213 5690",
    "sg:postcode":"L4C 6Z9",
    "sg:province":"ON",
    "sg:tags":[
        "oil",
        "truck"
    ],
    "wof:name":"York Truck Ctr",
    "wof:placetype":"venue"
},
  "geometry": {"coordinates":[-79.432137,43.848701],"type":"Point"}
}