{
  "type": "Feature",
  "properties": {
    "addr:full":"Acton Vale QC J0H 1A0",
    "addr:postcode":"j0h 1a0",
    "iso:country":"CA",
    "sg:city":"Acton Vale",
    "sg:classifiers":[
        {
            "category":"Health Services",
            "subcategory":"Doctor",
            "type":"Services"
        }
    ],
    "sg:phone":"+1 450 546 7272",
    "sg:postcode":"J0H 1A0",
    "sg:province":"QC",
    "sg:tags":[
        "clinic"
    ],
    "wof:name":"Centre Dentaire Familial Acton",
    "wof:placetype":"venue"
},
  "geometry": {"coordinates":[-72.56362900000001,45.64806],"type":"Point"}
}