{
  "type": "Feature",
  "properties": {
    "iso:country":"CA",
    "sg:address":"920 Rue Jean-Talon E",
    "sg:city":"Montreal",
    "sg:classifiers":[
        {
            "category":"Shopping",
            "subcategory":"Clothing, Apparel, & Fashions",
            "type":"Retail Goods"
        }
    ],
    "sg:phone":"+1 514 271 6512",
    "sg:postcode":"H2R 1V4",
    "sg:province":"QC",
    "sg:tags":[
        "dancing",
        "supply"
    ],
    "wof:name":"Danz Etc Inc",
    "wof:placetype":"venue"
},
  "geometry": {"coordinates":[-73.612701,45.541218],"type":"Point"}
}