{
  "type": "Feature",
  "properties": {
    "addr:full":"Vancouver BC V6H 3S4",
    "addr:postcode":"v6h 3s4",
    "iso:country":"CA",
    "sg:city":"Vancouver",
    "sg:classifiers":[
        {
            "category":"Manufacturing",
            "subcategory":"Printing",
            "type":"Manufacturing & Wholesale Goods"
        }
    ],
    "sg:phone":"+1 604 688 0320",
    "sg:postcode":"V6H 3S4",
    "sg:province":"BC",
    "sg:tags":[
        "editorial"
    ],
    "wof:name":"Granville Island Publishing",
    "wof:placetype":"venue"
},
  "geometry": {"coordinates":[-123.13607,49.271881],"type":"Point"}
}