{
  "type": "Feature",
  "properties": {
    "addr:full":"North Vancouver BC V7R 2P2",
    "addr:postcode":"v7r 2p2",
    "iso:country":"CA",
    "sg:city":"North Vancouver",
    "sg:classifiers":[
        {
            "category":"Shopping",
            "subcategory":"Pharmacy",
            "type":"Retail Goods"
        }
    ],
    "sg:phone":"+1 604 984 2245",
    "sg:postcode":"V7R 2P2",
    "sg:province":"BC",
    "wof:name":"Apple Pharmacy",
    "wof:placetype":"venue"
},
  "geometry": {"coordinates":[-123.103798,49.339092],"type":"Point"}
}