{
  "type": "Feature",
  "properties": {
    "iso:country":"CA",
    "sg:city":"Sarnia",
    "sg:classifiers":[
        {
            "category":"Health Services",
            "subcategory":"Health Practitioner",
            "type":"Services"
        }
    ],
    "sg:phone":"+1 519 337 2229",
    "sg:postcode":"N7T 6Y5",
    "sg:province":"ON",
    "sg:tags":[
        "midwife"
    ],
    "wof:name":"Midwifery Service of Sarnia",
    "wof:placetype":"venue"
},
  "geometry": {"coordinates":[-82.38607,42.982487],"type":"Point"}
}