{
  "type": "Feature",
  "properties": {
    "addr:full":"4357 10th Ave W Vancouver BC V6R 2H6",
    "addr:housenumber":"4357",
    "addr:postcode":"v6r 2h6",
    "addr:street":"10Th Ave W",
    "iso:country":"CA",
    "sg:address":"4357 10th Ave W",
    "sg:city":"Vancouver",
    "sg:classifiers":[
        {
            "category":"Home & Garden",
            "subcategory":"Furniture",
            "type":"Retail Goods"
        }
    ],
    "sg:phone":"+1 604 222 1317",
    "sg:postcode":"V6R 2H6",
    "sg:province":"BC",
    "wof:name":"Form & Function",
    "wof:placetype":"venue"
},
  "geometry": {"coordinates":[-123.20472717299999,49.2638931274],"type":"Point"}
}