{
  "type": "Feature",
  "properties": {
    "iso:country":"CA",
    "sg:address":"PO Box 1050",
    "sg:city":"Bassano",
    "sg:classifiers":[
        {
            "category":"Education",
            "subcategory":"School",
            "type":"Public Place"
        }
    ],
    "sg:phone":"+1 403 641 2005",
    "sg:postcode":"T0J 0B0",
    "sg:province":"AB",
    "wof:name":"Fairville Colony School",
    "wof:placetype":"venue"
},
  "geometry": {"coordinates":[-112.46641540500001,50.7858734131],"type":"Point"}
}