{
  "type": "Feature",
  "properties": {
    "iso:country":"CA",
    "sg:address":"160 Finch Ave W",
    "sg:city":"North York",
    "sg:classifiers":[
        {
            "category":"Education",
            "subcategory":"School",
            "type":"Public Place"
        }
    ],
    "sg:phone":"+1 416 393 5339",
    "sg:postcode":"M2N 2J2",
    "sg:province":"ON",
    "wof:name":"Saint Antoine Daniel Elem Schl",
    "wof:placetype":"venue"
},
  "geometry": {"coordinates":[-79.429359436,43.7768287659],"type":"Point"}
}