{
  "type": "Feature",
  "properties": {
    "addr:full":"Winnipeg MB R3T 2A7",
    "addr:postcode":"r3t 2a7",
    "iso:country":"CA",
    "sg:city":"Winnipeg",
    "sg:classifiers":[
        {
            "category":"Banks & Credit Unions",
            "subcategory":"Bank",
            "type":"Services"
        }
    ],
    "sg:phone":"+1 204 284 2091",
    "sg:postcode":"R3T 2A7",
    "sg:province":"MB",
    "sg:tags":[
        "loan",
        "real estate"
    ],
    "wof:name":"Express Mortgage",
    "wof:placetype":"venue"
},
  "geometry": {"coordinates":[-97.15284699999999,49.844826],"type":"Point"}
}