{
  "type": "Feature",
  "properties": {
    "addr:full":"325 Curling St Corner Brook NL A2H 3J8",
    "addr:housenumber":"325",
    "addr:postcode":"a2h 3j8",
    "addr:street":"Curling St",
    "iso:country":"CA",
    "sg:address":"325 Curling St",
    "sg:city":"Corner Brook",
    "sg:classifiers":[
        {
            "category":"Shopping",
            "subcategory":"Discount & Variety Stores",
            "type":"Retail Goods"
        }
    ],
    "sg:phone":"+1 709 785 2231",
    "sg:postcode":"A2H 3J8",
    "sg:province":"NL",
    "sg:tags":[
        "merchandise",
        "general"
    ],
    "wof:name":"Taylor's Store",
    "wof:placetype":"venue"
},
  "geometry": {"coordinates":[-57.994267,48.957802],"type":"Point"}
}