{
  "type": "Feature",
  "properties": {
    "addr:full":"2822 Rue DE Lyon Longueuil QC J4L 3R2",
    "addr:housenumber":"2822",
    "addr:postcode":"j4l 3r2",
    "addr:street":"Rue De Lyon",
    "iso:country":"CA",
    "sg:address":"2822 Rue DE Lyon",
    "sg:city":"Longueuil",
    "sg:classifiers":[
        {
            "category":"Personal",
            "subcategory":"Barber",
            "type":"Services"
        }
    ],
    "sg:phone":"+1 450 677 3337",
    "sg:postcode":"J4L 3R2",
    "sg:province":"QC",
    "wof:name":"Salon DE Lyon",
    "wof:placetype":"venue"
},
  "geometry": {"coordinates":[-73.4648132324,45.5150375366],"type":"Point"}
}