{
  "type": "Feature",
  "properties": {
    "addr:full":"281 Oxford St E London ON N6A 1V3",
    "addr:housenumber":"281",
    "addr:postcode":"n6a 1v3",
    "addr:street":"Oxford St E",
    "iso:country":"CA",
    "sg:address":"281 Oxford St E",
    "sg:city":"London",
    "sg:classifiers":[
        {
            "category":"Health Services",
            "subcategory":"Doctor",
            "type":"Services"
        }
    ],
    "sg:phone":"+1 519 672 7740",
    "sg:postcode":"N6A 1V3",
    "sg:province":"ON",
    "sg:tags":[
        "dentist"
    ],
    "wof:name":"Marti Health Svc",
    "wof:placetype":"venue"
},
  "geometry": {"coordinates":[-81.25048099999999,42.996147],"type":"Point"}
}