{
  "type": "Feature",
  "properties": {
    "iso:country":"CA",
    "sg:address":"281 Oxford St E",
    "sg:city":"London",
    "sg:classifiers":[
        {
            "category":"Health Services",
            "subcategory":"Doctor",
            "type":"Services"
        }
    ],
    "sg:phone":"+1 519 672 7740",
    "sg:postcode":"N6A 1V3",
    "sg:province":"ON",
    "sg:tags":[
        "dentist"
    ],
    "wof:name":"Marti Health Svc",
    "wof:placetype":"venue"
},
  "geometry": {"coordinates":[-81.250481,42.996147],"type":"Point"}
}