{
  "type": "Feature",
  "properties": {
    "addr:full":"760 Boul Industriel E Victoriaville QC G6T 1S6",
    "addr:housenumber":"760",
    "addr:postcode":"g6t 1s6",
    "addr:street":"Boul Industriel E",
    "iso:country":"CA",
    "sg:address":"760 Boul Industriel E",
    "sg:city":"Victoriaville",
    "sg:classifiers":[
        {
            "category":"Wholesale",
            "subcategory":"Apparel",
            "type":"Manufacturing & Wholesale Goods"
        }
    ],
    "sg:phone":"+1 819 752 8857",
    "sg:postcode":"G6T 1S6",
    "sg:province":"QC",
    "sg:tags":[
        "screen",
        "printing"
    ],
    "wof:name":"257",
    "wof:placetype":"venue"
},
  "geometry": {"coordinates":[-71.95547500000001,46.080406],"type":"Point"}
}