{
  "type": "Feature",
  "properties": {
    "addr:full":"188 St. George St Bathurst NB E2A 1B5",
    "addr:housenumber":"188",
    "addr:postcode":"e2a 1b5",
    "addr:street":"St. George St",
    "iso:country":"CA",
    "sg:address":"188 St. George St",
    "sg:city":"Bathurst",
    "sg:classifiers":[
        {
            "category":"Real Estate",
            "subcategory":"Real Estate Agent",
            "type":"Services"
        }
    ],
    "sg:phone":"+1 506 546 7777",
    "sg:postcode":"E2A 1B5",
    "sg:province":"NB",
    "wof:name":"Re/Max Bathurst Realty Ltd",
    "wof:placetype":"venue"
},
  "geometry": {"coordinates":[-65.65371704099999,47.619052887],"type":"Point"}
}