{
  "type": "Feature",
  "properties": {
    "addr:full":"6420 28 Ave NW Edmonton AB T6L 6N3",
    "addr:housenumber":"6420",
    "addr:postcode":"t6l 6n3",
    "addr:street":"28 Ave Nw",
    "iso:country":"CA",
    "sg:address":"6420 28 Ave NW",
    "sg:city":"Edmonton",
    "sg:classifiers":[
        {
            "category":"Health Services",
            "subcategory":"Doctor",
            "type":"Services"
        }
    ],
    "sg:phone":"+1 780 463 0555",
    "sg:postcode":"T6L 6N3",
    "sg:province":"AB",
    "sg:tags":[
        "dentist"
    ],
    "wof:name":"Millwoods Dental Ctr",
    "wof:placetype":"venue"
},
  "geometry": {"coordinates":[-113.431763,53.4585],"type":"Point"}
}