{
  "type": "Feature",
  "properties": {
    "addr:full":"5120 Av DE Courtrai Montreal QC H3W 1A7",
    "addr:housenumber":"5120",
    "addr:postcode":"h3w 1a7",
    "addr:street":"Av De Courtrai",
    "iso:country":"CA",
    "sg:address":"5120 Av DE Courtrai",
    "sg:city":"Montreal",
    "sg:classifiers":[
        {
            "category":"Organizations",
            "subcategory":"Membership Organization",
            "type":"Services"
        }
    ],
    "sg:phone":"+1 514 344 2424",
    "sg:postcode":"H3W 1A7",
    "sg:province":"QC",
    "wof:name":"Chai Center",
    "wof:placetype":"venue"
},
  "geometry": {"coordinates":[-73.647476,45.495113],"type":"Point"}
}