{
  "type": "Feature",
  "properties": {
    "addr:full":"320 Circle Dr E Saskatoon SK S7K 0T6",
    "addr:housenumber":"320",
    "addr:postcode":"s7k 0t6",
    "addr:street":"Circle Dr E",
    "iso:country":"CA",
    "sg:address":"320 Circle Dr E",
    "sg:city":"Saskatoon",
    "sg:classifiers":[
        {
            "category":"Banks & Credit Unions",
            "subcategory":"Bank",
            "type":"Services"
        }
    ],
    "sg:phone":"+1 306 668 3466",
    "sg:postcode":"S7K 0T6",
    "sg:province":"SK",
    "wof:name":"Cibc",
    "wof:placetype":"venue"
},
  "geometry": {"coordinates":[-106.666656,52.158138],"type":"Point"}
}