{
  "type": "Feature",
  "properties": {
    "addr:full":"22 Rue Martin Chateauguay QC J6J 1A5",
    "addr:housenumber":"22",
    "addr:postcode":"j6j 1a5",
    "addr:street":"Rue Martin Chateauguay",
    "iso:country":"CA",
    "sg:address":"22 Rue Martin",
    "sg:city":"Chateauguay",
    "sg:classifiers":[
        {
            "category":"Building & Trades",
            "subcategory":"Construction",
            "type":"Services"
        }
    ],
    "sg:phone":"+1 450 699 5152",
    "sg:postcode":"J6J 1A5",
    "sg:province":"QC",
    "sg:tags":[
        "home",
        "builder",
        "general",
        "contractor"
    ],
    "wof:name":"Habitations Enault & Freres",
    "wof:placetype":"venue"
},
  "geometry": {"coordinates":[-73.7474899292,45.3905181885],"type":"Point"}
}