{
  "type": "Feature",
  "properties": {
    "iso:country":"CA",
    "sg:address":"3007 Kingston Rd",
    "sg:city":"Scarborough",
    "sg:classifiers":[
        {
            "category":"Wholesale",
            "subcategory":"Hardware",
            "type":"Manufacturing & Wholesale Goods"
        }
    ],
    "sg:phone":"+1 416 264 4123",
    "sg:postcode":"M1M 1P1",
    "sg:province":"ON",
    "sg:tags":[
        "box",
        "mail"
    ],
    "wof:name":"Asap",
    "wof:placetype":"venue"
},
  "geometry": {"coordinates":[-79.23133087159999,43.7258415222],"type":"Point"}
}