{
  "type": "Feature",
  "properties": {
    "addr:full":"6776 Pleasant Valley Rd Vernon BC V1B 3R5",
    "addr:housenumber":"6776",
    "addr:postcode":"bc v1b 3r5",
    "addr:street":"Pleasant Valley Rd",
    "iso:country":"CA",
    "sg:address":"6776 Pleasant Valley Rd",
    "sg:city":"Vernon",
    "sg:classifiers":[
        {
            "category":"Food & Beverages",
            "subcategory":"Fruits & Vegetables",
            "type":"Retail Goods"
        }
    ],
    "sg:phone":"+1 250 545 2093",
    "sg:postcode":"V1B 3R5",
    "sg:province":"BC",
    "sg:tags":[
        "produce"
    ],
    "wof:name":"Burke's Fruits & Vegetables",
    "wof:placetype":"venue"
},
  "geometry": {"coordinates":[-119.25355529799999,50.2829284668],"type":"Point"}
}