{
  "type": "Feature",
  "properties": {
    "addr:full":"North York ON M3A 1A3",
    "addr:postcode":"m3a 1a3",
    "iso:country":"CA",
    "sg:city":"North York",
    "sg:classifiers":[
        {
            "category":"Organizations",
            "subcategory":"Non-profit Organization",
            "type":"Services"
        }
    ],
    "sg:phone":"+1 416 510 3351",
    "sg:postcode":"M3A 1A3",
    "sg:province":"ON",
    "sg:tags":[
        "disability"
    ],
    "wof:name":"Harmony Place Support Svc",
    "wof:placetype":"venue"
},
  "geometry": {"coordinates":[-79.32722473139999,43.7366371155],"type":"Point"}
}