{
  "type": "Feature",
  "properties": {
    "addr:full":"Calgary AB T1Y 7K2",
    "addr:postcode":"t1y 7k2",
    "iso:country":"CA",
    "sg:city":"Calgary",
    "sg:classifiers":[
        {
            "category":"Freight",
            "type":"Transportation"
        }
    ],
    "sg:phone":"+1 403 717 0757",
    "sg:postcode":"T1Y 7K2",
    "sg:province":"AB",
    "sg:tags":[
        "mover"
    ],
    "wof:name":"Crown Relocations",
    "wof:placetype":"venue"
},
  "geometry": {"coordinates":[-113.972908,51.07777],"type":"Point"}
}