{
  "type": "Feature",
  "properties": {
    "addr:full":"695 Markham St Toronto ON M6G 2M2",
    "addr:housenumber":"695",
    "addr:postcode":"m6g 2m2",
    "addr:street":"Markham St",
    "iso:country":"CA",
    "sg:address":"695 Markham St",
    "sg:city":"Toronto",
    "sg:classifiers":[
        {
            "category":"Social Services",
            "type":"Services"
        }
    ],
    "sg:phone":"+1 416 289 1200",
    "sg:postcode":"M6G 2M2",
    "sg:province":"ON",
    "sg:tags":[
        "organization",
        "welfare"
    ],
    "wof:name":"Multiple Sclerosis Society",
    "wof:placetype":"venue"
},
  "geometry": {"coordinates":[-79.41297900000001,43.666828],"type":"Point"}
}