{
  "type": "Feature",
  "properties": {
    "addr:full":"Scarborough ON M1B 5N1",
    "addr:postcode":"m1b 5n1",
    "iso:country":"CA",
    "sg:city":"Scarborough",
    "sg:classifiers":[
        {
            "category":"Utilities",
            "subcategory":"Telephone",
            "type":"Services"
        }
    ],
    "sg:phone":"+1 416 310 2355",
    "sg:postcode":"M1B 5N1",
    "sg:province":"ON",
    "sg:tags":[
        "company"
    ],
    "wof:name":"Bell Canada",
    "wof:placetype":"venue"
},
  "geometry": {"coordinates":[-79.2335968018,43.7901573181],"type":"Point"}
}