{
  "type": "Feature",
  "properties": {
    "addr:full":"433 Bowen Island Trunk Bowen Island BC V0N 1G0",
    "addr:housenumber":"433",
    "addr:postcode":"v0n 1g0",
    "addr:street":"Bowen Island Trunk",
    "iso:country":"CA",
    "sg:address":"433 Bowen Island Trunk",
    "sg:city":"Bowen Island",
    "sg:classifiers":[
        {
            "category":"Restaurant",
            "type":"Food & Drink"
        }
    ],
    "sg:phone":"+1 604 947 2583",
    "sg:postcode":"V0N 1G0",
    "sg:province":"BC",
    "wof:name":"Blue Eyed Marys Restaurant",
    "wof:placetype":"venue"
},
  "geometry": {"coordinates":[-123.334045,49.379528],"type":"Point"}
}