{
  "type": "Feature",
  "properties": {
    "addr:full":"431 Av Gagnon Roberval QC G8H 1L8",
    "addr:postcode":"g8h 1l8",
    "addr:street":"431 Av Gagnon",
    "iso:country":"CA",
    "sg:address":"431 Av Gagnon",
    "sg:city":"Roberval",
    "sg:classifiers":[
        {
            "category":"Health Services",
            "subcategory":"Doctor",
            "type":"Services"
        }
    ],
    "sg:phone":"+1 418 275 0395",
    "sg:postcode":"G8H 1L8",
    "sg:province":"QC",
    "sg:tags":[
        "clinic"
    ],
    "wof:name":"Clinique Chiropratique Robvl",
    "wof:placetype":"venue"
},
  "geometry": {"coordinates":[-72.229591,48.518845],"type":"Point"}
}