{
  "type": "Feature",
  "properties": {
    "addr:full":"Surrey BC V3W 1A4",
    "addr:postcode":"v3w 1a4",
    "iso:country":"CA",
    "sg:city":"Surrey",
    "sg:classifiers":[
        {
            "category":"Restaurant",
            "type":"Food & Drink"
        }
    ],
    "sg:phone":"+1 604 501 6692",
    "sg:postcode":"V3W 1A4",
    "sg:province":"BC",
    "wof:name":"Interwest Restaurants Inc",
    "wof:placetype":"venue"
},
  "geometry": {"coordinates":[-122.842948914,49.1362915039],"type":"Point"}
}