{
  "type": "Feature",
  "properties": {
    "addr:full":"331 Rue Emery Montreal QC H2X 1J2",
    "addr:housenumber":"331",
    "addr:postcode":"h2x 1j2",
    "addr:street":"Rue Emery",
    "iso:country":"CA",
    "sg:address":"331 Rue Emery",
    "sg:city":"Montreal",
    "sg:classifiers":[
        {
            "category":"Shopping",
            "type":"Retail Goods"
        }
    ],
    "sg:phone":"+1 514 982 6639",
    "sg:postcode":"H2X 1J2",
    "sg:province":"QC",
    "sg:tags":[
        "miscellaneous",
        "store"
    ],
    "wof:name":"Distribution Pierres DE Lune",
    "wof:placetype":"venue"
},
  "geometry": {"coordinates":[-73.5640029907,45.5144729614],"type":"Point"}
}