{
  "type": "Feature",
  "properties": {
    "addr:full":"525 Colborne St Brantford ON N3S 3P3",
    "addr:housenumber":"525",
    "addr:postcode":"n3s 3p3",
    "addr:street":"Colborne St",
    "iso:country":"CA",
    "sg:address":"525 Colborne St",
    "sg:city":"Brantford",
    "sg:classifiers":[
        {
            "category":"Organizations",
            "subcategory":"Professional Association",
            "type":"Services"
        }
    ],
    "sg:phone":"+1 519 752 2551",
    "sg:postcode":"N3S 3P3",
    "sg:province":"ON",
    "sg:tags":[
        "club"
    ],
    "wof:name":"Shriners' Club",
    "wof:placetype":"venue"
},
  "geometry": {"coordinates":[-80.24825286870001,43.1393928528],"type":"Point"}
}