{
  "type": "Feature",
  "properties": {
    "addr:full":"3069 Ch Royal Beauport QC G1E 1T9",
    "addr:housenumber":"3069",
    "addr:postcode":"qc g1e 1t9",
    "addr:street":"Ch Royal",
    "iso:country":"CA",
    "sg:address":"3069 Ch Royal",
    "sg:city":"Beauport",
    "sg:classifiers":[
        {
            "category":"Personal",
            "subcategory":"Beauty Salon",
            "type":"Services"
        }
    ],
    "sg:phone":"+1 418 666 3110",
    "sg:postcode":"G1E 1T9",
    "sg:province":"QC",
    "wof:name":"Institut Sante Coiffe",
    "wof:placetype":"venue"
},
  "geometry": {"coordinates":[-71.21209,46.849339],"type":"Point"}
}