{
  "type": "Feature",
  "properties": {
    "iso:country":"CA",
    "sg:address":"245 Rue Frontenac",
    "sg:city":"Sherbrooke",
    "sg:classifiers":[
        {
            "category":"Personal",
            "subcategory":"Beauty Salon",
            "type":"Services"
        }
    ],
    "sg:phone":"+1 819 562 9976",
    "sg:postcode":"J1H 1K1",
    "sg:province":"QC",
    "wof:name":"Coiffure Soleil Du Musee",
    "wof:placetype":"venue"
},
  "geometry": {"coordinates":[-71.89604949949999,45.4030838013],"type":"Point"}
}