{
  "type": "Feature",
  "properties": {
    "addr:full":"Ryley AB T0B 4A0",
    "addr:postcode":"t0b 4a0",
    "iso:country":"CA",
    "sg:city":"Ryley",
    "sg:classifiers":[
        {
            "category":"Restaurant",
            "type":"Food & Drink"
        }
    ],
    "sg:phone":"+1 780 663 3527",
    "sg:postcode":"T0B 4A0",
    "sg:province":"AB",
    "wof:name":"Wong's Restaurant",
    "wof:placetype":"venue"
},
  "geometry": {"coordinates":[-112.430733,53.289162],"type":"Point"}
}