{
  "type": "Feature",
  "properties": {
    "addr:full":"3700 Boul Thimens Saint-Laurent QC H4R 1T8",
    "addr:housenumber":"3700",
    "addr:postcode":"h4r 1t8",
    "addr:street":"Boul Thimens",
    "iso:country":"CA",
    "sg:address":"3700 Boul Thimens",
    "sg:city":"Saint-Laurent",
    "sg:classifiers":[
        {
            "category":"Manufacturing",
            "subcategory":"Food",
            "type":"Manufacturing & Wholesale Goods"
        }
    ],
    "sg:phone":"+1 514 332 3770",
    "sg:postcode":"H4R 1T8",
    "sg:province":"QC",
    "sg:tags":[
        "beverage"
    ],
    "wof:name":"Breuvages Pepsi-Cola Canada",
    "wof:placetype":"venue"
},
  "geometry": {"coordinates":[-73.71356201170001,45.4963378906],"type":"Point"}
}