{
  "type": "Feature",
  "properties": {
    "addr:full":"PO Box 525 STN Main Whitecourt AB T7S 1N6",
    "addr:housenumber":"po",
    "addr:postcode":"t7s 1n6",
    "addr:street":"Box 525 Stn Main",
    "iso:country":"CA",
    "sg:address":"PO Box 525 STN Main",
    "sg:city":"Whitecourt",
    "sg:classifiers":[
        {
            "category":"Building & Trades",
            "subcategory":"Construction",
            "type":"Services"
        }
    ],
    "sg:phone":"+1 780 778 2155",
    "sg:postcode":"T7S 1N6",
    "sg:province":"AB",
    "sg:tags":[
        "sand",
        "gravel",
        "excavating",
        "contractor"
    ],
    "wof:name":"Lionel Prokipchuk Trucking",
    "wof:placetype":"venue"
},
  "geometry": {"coordinates":[-115.70787811300001,54.1394348145],"type":"Point"}
}