{
  "type": "Feature",
  "properties": {
    "addr:full":"186 Cowan Ave Toronto ON M6K 2N6",
    "addr:housenumber":"186",
    "addr:postcode":"m6k 2n6",
    "addr:street":"Cowan Ave",
    "iso:country":"CA",
    "sg:address":"186 Cowan Ave",
    "sg:city":"Toronto",
    "sg:classifiers":[
        {
            "category":"Organizations",
            "subcategory":"Religious Organization",
            "type":"Services"
        }
    ],
    "sg:phone":"+1 416 532 8249",
    "sg:postcode":"M6K 2N6",
    "sg:province":"ON",
    "sg:tags":[
        "church"
    ],
    "wof:name":"St Johns Polish National Cath",
    "wof:placetype":"venue"
},
  "geometry": {"coordinates":[-79.43268585209999,43.6398735046],"type":"Point"}
}