{
  "type": "Feature",
  "properties": {
    "addr:full":"22254 Dewdney Trunk Rd Maple Ridge BC V2X 3H9",
    "addr:housenumber":"22254",
    "addr:postcode":"v2x 3h9",
    "addr:street":"Dewdney Trunk Rd",
    "iso:country":"CA",
    "sg:address":"22254 Dewdney Trunk Rd",
    "sg:city":"Maple Ridge",
    "sg:classifiers":[
        {
            "category":"Food & Beverages",
            "subcategory":"Specialty",
            "type":"Retail Goods"
        }
    ],
    "sg:phone":"+1 604 467 1822",
    "sg:postcode":"V2X 3H9",
    "sg:province":"BC",
    "sg:tags":[
        "health",
        "vitamin",
        "diet"
    ],
    "wof:name":"Root's Natural Organic Foods",
    "wof:placetype":"venue"
},
  "geometry": {"coordinates":[-122.60556800000001,49.220371],"type":"Point"}
}