{
  "type": "Feature",
  "properties": {
    "addr:full":"999 Av Roland-Beaudin Sainte-Foy QC G1V 4M8",
    "addr:postcode":"g1v 4m8",
    "addr:street":"999 Av Roland-Beaudin",
    "iso:country":"CA",
    "sg:address":"999 Av Roland-Beaudin",
    "sg:city":"Sainte-Foy",
    "sg:classifiers":[
        {
            "category":"Education",
            "subcategory":"Library",
            "type":"Public Place"
        }
    ],
    "sg:phone":"+1 418 641 6277",
    "sg:postcode":"G1V 4M8",
    "sg:province":"QC",
    "wof:name":"Bibliotheque Monique-Corriveau",
    "wof:placetype":"venue"
},
  "geometry": {"coordinates":[-71.296921,46.772339],"type":"Point"}
}