{
  "type": "Feature",
  "properties": {
    "iso:country":"CA",
    "sg:address":"2555 Rue Cardin",
    "sg:city":"Sorel-Tracy",
    "sg:classifiers":[
        {
            "category":"Education",
            "subcategory":"School",
            "type":"Public Place"
        }
    ],
    "sg:phone":"+1 450 742 1948",
    "sg:postcode":"J3R 2S5",
    "sg:province":"QC",
    "wof:name":"Ecole Laplume",
    "wof:placetype":"venue"
},
  "geometry": {"coordinates":[-73.1469039917,46.0247535706],"type":"Point"}
}