{
  "type": "Feature",
  "properties": {
    "addr:full":"40 4th St Tofino BC V0R 2Z0",
    "addr:housenumber":"40",
    "addr:postcode":"v0r 2z0",
    "addr:street":"4Th St",
    "iso:country":"CA",
    "sg:address":"40 4th St",
    "sg:city":"Tofino",
    "sg:classifiers":[
        {
            "category":"Government",
            "subcategory":"Office",
            "type":"Public Place"
        }
    ],
    "sg:phone":"+1 250 725 4441",
    "sg:postcode":"V0R 2Z0",
    "sg:province":"BC",
    "wof:name":"Canada Fisheries & Oceans",
    "wof:placetype":"venue"
},
  "geometry": {"coordinates":[-125.90351099999999,49.152538],"type":"Point"}
}