{
  "type": "Feature",
  "properties": {
    "addr:full":"1366 Danforth Ave Toronto ON M4J 1M9",
    "addr:housenumber":"1366",
    "addr:postcode":"m4j 1m9",
    "addr:street":"Danforth Ave",
    "iso:country":"CA",
    "sg:address":"1366 Danforth Ave",
    "sg:city":"Toronto",
    "sg:classifiers":[
        {
            "category":"Shopping",
            "type":"Retail Goods"
        }
    ],
    "sg:phone":"+1 416 466 6357",
    "sg:postcode":"M4J 1M9",
    "sg:province":"ON",
    "sg:tags":[
        "preparation",
        "toilet",
        "cosmetic"
    ],
    "wof:name":"Penny Wise Fragrance",
    "wof:placetype":"venue"
},
  "geometry": {"coordinates":[-79.329224,43.682224],"type":"Point"}
}