{
  "type": "Feature",
  "properties": {
    "addr:full":"6052 52 Ave Vermilion AB T9X 1X3",
    "addr:housenumber":"6052",
    "addr:postcode":"t9x 1x3",
    "addr:street":"52 Ave",
    "iso:country":"CA",
    "sg:address":"6052 52 Ave",
    "sg:city":"Vermilion",
    "sg:classifiers":[
        {
            "category":"Organizations",
            "subcategory":"Religious Organization",
            "type":"Services"
        }
    ],
    "sg:phone":"+1 780 853 5370",
    "sg:postcode":"T9X 1X3",
    "sg:province":"AB",
    "sg:tags":[
        "church"
    ],
    "wof:name":"Ukrainian Catholic Church",
    "wof:placetype":"venue"
},
  "geometry": {"coordinates":[-110.880989075,53.3578071594],"type":"Point"}
}