{
  "type": "Feature",
  "properties": {
    "addr:full":"732 Mount Paul Way Kamloops BC V2H 1B5",
    "addr:housenumber":"732",
    "addr:postcode":"bc v2h 1b5",
    "addr:street":"Mount Paul Way",
    "iso:country":"CA",
    "sg:address":"732 Mount Paul Way",
    "sg:city":"Kamloops",
    "sg:classifiers":[
        {
            "category":"Building & Trades",
            "subcategory":"Electrical",
            "type":"Services"
        }
    ],
    "sg:phone":"+1 250 554 1622",
    "sg:postcode":"V2H 1B5",
    "sg:province":"BC",
    "sg:tags":[
        "electric",
        "contractor"
    ],
    "wof:name":"Aspen Electric Ltd",
    "wof:placetype":"venue"
},
  "geometry": {"coordinates":[-120.32228088399999,50.6913490295],"type":"Point"}
}