{
  "type": "Feature",
  "properties": {
    "iso:country":"CA",
    "sg:address":"50 Rue Michel",
    "sg:city":"Mont-Saint-Hilaire",
    "sg:classifiers":[
        {
            "category":"Education",
            "subcategory":"School",
            "type":"Public Place"
        }
    ],
    "sg:phone":"+1 450 467 0971",
    "sg:postcode":"J3H 3R3",
    "sg:province":"QC",
    "wof:name":"Ecole DE L'Aquarelle",
    "wof:placetype":"venue"
},
  "geometry": {"coordinates":[-73.191124,45.555946],"type":"Point"}
}