{
  "type": "Feature",
  "properties": {
    "addr:full":"3004 Boul DE LA Rousseliere Pointe-Aux-Trembles QC H1A 4G3",
    "addr:housenumber":"3004",
    "addr:postcode":"h1a 4g3",
    "addr:street":"Boul De La Rousseliere",
    "iso:country":"CA",
    "sg:address":"3004 Boul DE LA Rousseliere",
    "sg:city":"Pointe-Aux-Trembles",
    "sg:classifiers":[
        {
            "category":"Food & Beverages",
            "subcategory":"Groceries & Convenience Stores",
            "type":"Retail Goods"
        }
    ],
    "sg:phone":"+1 514 498 7117",
    "sg:postcode":"H1A 4G3",
    "sg:province":"QC",
    "sg:tags":[
        "grocer"
    ],
    "wof:name":"Metro DE LA Rousselliere",
    "wof:placetype":"venue"
},
  "geometry": {"coordinates":[-73.50633999999999,45.66946],"type":"Point"}
}