{
  "type": "Feature",
  "properties": {
    "iso:country":"CA",
    "sg:address":"1 Stone Mason Dr # 5",
    "sg:city":"Markham",
    "sg:classifiers":[
        {
            "category":"Restaurant",
            "type":"Food & Drink"
        }
    ],
    "sg:phone":"+1 905 294 8500",
    "sg:postcode":"L3P 6X3",
    "sg:province":"ON",
    "wof:name":"Judy's Pizzeria",
    "wof:placetype":"venue"
},
  "geometry": {"coordinates":[-79.273438,43.889042],"type":"Point"}
}