{
  "type": "Feature",
  "properties": {
    "addr:full":"360 Fitton St Midland ON L4R 2T5",
    "addr:housenumber":"360",
    "addr:postcode":"l4r 2t5",
    "addr:street":"Fitton St",
    "iso:country":"CA",
    "sg:address":"360 Fitton St",
    "sg:city":"Midland",
    "sg:classifiers":[
        {
            "category":"Building & Trades",
            "subcategory":"Plumbing",
            "type":"Services"
        }
    ],
    "sg:phone":"+1 705 526 8465",
    "sg:postcode":"L4R 2T5",
    "sg:province":"ON",
    "sg:tags":[
        "furnace",
        "cleaning"
    ],
    "wof:name":"Elton Cruise Burner Svc",
    "wof:placetype":"venue"
},
  "geometry": {"coordinates":[-79.8726577759,44.7515983582],"type":"Point"}
}