{
  "type": "Feature",
  "properties": {
    "addr:full":"409 Monashee Ave Edgewood BC V0G 1J0",
    "addr:housenumber":"409",
    "addr:postcode":"v0g 1j0",
    "addr:street":"Monashee Ave",
    "iso:country":"CA",
    "sg:address":"409 Monashee Ave",
    "sg:city":"Edgewood",
    "sg:classifiers":[
        {
            "category":"Education",
            "subcategory":"School",
            "type":"Public Place"
        }
    ],
    "sg:phone":"+1 250 269 7212",
    "sg:postcode":"V0G 1J0",
    "sg:province":"BC",
    "wof:name":"Edgewood Elementary School",
    "wof:placetype":"venue"
},
  "geometry": {"coordinates":[-118.14617200000001,49.77774],"type":"Point"}
}