{
  "type": "Feature",
  "properties": {
    "iso:country":"CA",
    "sg:address":"35 Danforth Rd",
    "sg:city":"Scarborough",
    "sg:classifiers":[
        {
            "category":"Wholesale",
            "subcategory":"Groceries",
            "type":"Manufacturing & Wholesale Goods"
        }
    ],
    "sg:phone":"+1 416 693 5832",
    "sg:postcode":"M1L 3W5",
    "sg:province":"ON",
    "sg:tags":[
        "grocer"
    ],
    "wof:name":"Zeea Imports Ltd",
    "wof:placetype":"venue"
},
  "geometry": {"coordinates":[-79.27611541749999,43.6948394775],"type":"Point"}
}