{
  "type": "Feature",
  "properties": {
    "addr:full":"720 Beatty St Vancouver BC V6B 2M1",
    "addr:housenumber":"720",
    "addr:postcode":"bc v6b 2m1",
    "addr:street":"Beatty St",
    "iso:country":"CA",
    "sg:address":"720 Beatty St",
    "sg:city":"Vancouver",
    "sg:classifiers":[
        {
            "category":"Utilities",
            "subcategory":"Natural Gas",
            "type":"Services"
        }
    ],
    "sg:phone":"+1 604 688 9584",
    "sg:postcode":"V6B 2M1",
    "sg:province":"BC",
    "sg:tags":[
        "heat",
        "company",
        "supplying"
    ],
    "wof:name":"Central Heat Distribution Ltd",
    "wof:placetype":"venue"
},
  "geometry": {"coordinates":[-123.11254119900001,49.278301239],"type":"Point"}
}