{
  "type": "Feature",
  "properties": {
    "iso:country":"CA",
    "sg:address":"407 Rue Saint-Alexis",
    "sg:city":"Saint-Louis-DE-France",
    "sg:classifiers":[
        {
            "category":"Organizations",
            "subcategory":"Religious Organization",
            "type":"Services"
        }
    ],
    "sg:phone":"+1 819 375 3655",
    "sg:postcode":"G8W 2E2",
    "sg:province":"QC",
    "sg:tags":[
        "church"
    ],
    "wof:name":"Eglise Biblique Baptiste",
    "wof:placetype":"venue"
},
  "geometry": {"coordinates":[-72.579185,46.394577],"type":"Point"}
}