{
  "type": "Feature",
  "properties": {
    "addr:full":"120 Rue Saint-Georges Drummondville QC J2C 4G8",
    "addr:housenumber":"120",
    "addr:postcode":"j2c 4g8",
    "addr:street":"Rue Saint-Georges",
    "iso:country":"CA",
    "sg:address":"120 Rue Saint-Georges",
    "sg:city":"Drummondville",
    "sg:classifiers":[
        {
            "category":"Health Services",
            "subcategory":"Doctor",
            "type":"Services"
        }
    ],
    "sg:phone":"+1 819 473 0959",
    "sg:postcode":"J2C 4G8",
    "sg:province":"QC",
    "sg:tags":[
        "clinic"
    ],
    "wof:name":"Jutras, Robert",
    "wof:placetype":"venue"
},
  "geometry": {"coordinates":[-72.493042,45.886513],"type":"Point"}
}