{
  "type": "Feature",
  "properties": {
    "iso:country":"CA",
    "sg:address":"1675 Tenth Line Rd",
    "sg:city":"Orleans",
    "sg:classifiers":[
        {
            "category":"Banks & Credit Unions",
            "subcategory":"Bank",
            "type":"Services"
        }
    ],
    "sg:phone":"+1 613 837 8464",
    "sg:postcode":"K1E 3P6",
    "sg:province":"ON",
    "wof:name":"Cibc",
    "wof:placetype":"venue"
},
  "geometry": {"coordinates":[-75.51141357420001,45.4801216125],"type":"Point"}
}