{
  "type": "Feature",
  "properties": {
    "addr:full":"Minden ON K0M 2K0",
    "addr:postcode":"k0m 2k0",
    "iso:country":"CA",
    "sg:city":"Minden",
    "sg:classifiers":[
        {
            "category":"Social Services",
            "type":"Services"
        }
    ],
    "sg:phone":"+1 705 286 6838",
    "sg:postcode":"K0M 2K0",
    "sg:province":"ON",
    "sg:tags":[
        "organization",
        "welfare"
    ],
    "wof:name":"Minden Community Food Bank",
    "wof:placetype":"venue"
},
  "geometry": {"coordinates":[-78.725899,44.926125],"type":"Point"}
}