{
  "type": "Feature",
  "properties": {
    "iso:country":"CA",
    "sg:address":"397 Springbank Dr",
    "sg:city":"London",
    "sg:classifiers":[
        {
            "category":"Organizations",
            "subcategory":"Religious Organization",
            "type":"Services"
        }
    ],
    "sg:phone":"+1 519 471 7780",
    "sg:postcode":"N6J 1G7",
    "sg:province":"ON",
    "sg:tags":[
        "church"
    ],
    "wof:name":"St Michael & All Angels",
    "wof:placetype":"venue"
},
  "geometry": {"coordinates":[-81.28286,42.968727],"type":"Point"}
}