{
  "type": "Feature",
  "properties": {
    "addr:full":"Labrador City NL A2V 2X4",
    "iso:country":"CA",
    "sg:city":"Labrador City",
    "sg:classifiers":[
        {
            "category":"Cinema",
            "subcategory":"Movie Rental",
            "type":"Entertainment"
        }
    ],
    "sg:phone":"+1 709 944 4070",
    "sg:postcode":"A2V 2X4",
    "sg:province":"NL",
    "sg:tags":[
        "leasing",
        "video",
        "disc",
        "tape"
    ],
    "wof:name":"Late Nite Video",
    "wof:placetype":"venue"
},
  "geometry": {"coordinates":[-66.92589599999999,52.935806],"type":"Point"}
}