{
  "type": "Feature",
  "properties": {
    "addr:full":"Toronto ON M5R 1K1",
    "addr:postcode":"m5r 1k1",
    "iso:country":"CA",
    "sg:city":"Toronto",
    "sg:classifiers":[
        {
            "category":"Professional",
            "subcategory":"Management & Consulting",
            "type":"Services"
        }
    ],
    "sg:phone":"+1 416 923 3930",
    "sg:postcode":"M5R 1K1",
    "sg:province":"ON",
    "sg:tags":[
        "consultant",
        "business"
    ],
    "wof:name":"Lionel D Feldman Consulting",
    "wof:placetype":"venue"
},
  "geometry": {"coordinates":[-79.39748382569999,43.6744117737],"type":"Point"}
}