{
  "type": "Feature",
  "properties": {
    "addr:full":"595 57th Ave W Vancouver BC V6P 1R8",
    "addr:housenumber":"595",
    "addr:postcode":"v6p 1r8",
    "addr:street":"57Th Ave W",
    "iso:country":"CA",
    "sg:address":"595 57th Ave W",
    "sg:city":"Vancouver",
    "sg:classifiers":[
        {
            "category":"Health Services",
            "subcategory":"Doctor",
            "type":"Services"
        }
    ],
    "sg:phone":"+1 604 327 4808",
    "sg:postcode":"V6P 1R8",
    "sg:province":"BC",
    "sg:tags":[
        "dentist"
    ],
    "wof:name":"Yu, Elisa K K DDS",
    "wof:placetype":"venue"
},
  "geometry": {"coordinates":[-123.118537903,49.219203949],"type":"Point"}
}