{
  "type": "Feature",
  "properties": {
    "addr:full":"107 Brett Dr Fort Mcmurray AB T9K 1V1",
    "addr:housenumber":"107",
    "addr:postcode":"t9k 1v1",
    "addr:street":"Brett Dr",
    "iso:country":"CA",
    "sg:address":"107 Brett Dr",
    "sg:city":"Fort Mcmurray",
    "sg:classifiers":[
        {
            "category":"Education",
            "subcategory":"School",
            "type":"Public Place"
        }
    ],
    "sg:phone":"+1 780 743 5771",
    "sg:postcode":"T9K 1V1",
    "sg:province":"AB",
    "wof:name":"Timberlea School",
    "wof:placetype":"venue"
},
  "geometry": {"coordinates":[-111.46498099999999,56.74485],"type":"Point"}
}