{
  "type": "Feature",
  "properties": {
    "addr:full":"19 Charles St Cobourg ON K9A 2T4",
    "addr:housenumber":"19",
    "addr:postcode":"k9a 2t4",
    "addr:street":"Charles St",
    "iso:country":"CA",
    "sg:address":"19 Charles St",
    "sg:city":"Cobourg",
    "sg:classifiers":[
        {
            "category":"Recreation",
            "type":"Entertainment"
        }
    ],
    "sg:phone":"+1 905 373 7321",
    "sg:postcode":"K9A 2T4",
    "sg:province":"ON",
    "sg:tags":[
        "provincial",
        "parks",
        "government"
    ],
    "wof:name":"Victoria Park Trailer Camp",
    "wof:placetype":"venue"
},
  "geometry": {"coordinates":[-78.16356658940001,43.9584541321],"type":"Point"}
}