{
  "type": "Feature",
  "properties": {
    "addr:full":"4025 Brandon Gate Dr Mississauga ON L4T 3Z9",
    "addr:housenumber":"4025",
    "addr:postcode":"l4t 3z9",
    "addr:street":"Brandon Gate Dr",
    "iso:country":"CA",
    "sg:address":"4025 Brandon Gate Dr",
    "sg:city":"Mississauga",
    "sg:classifiers":[
        {
            "category":"Health Services",
            "subcategory":"Doctor",
            "type":"Services"
        }
    ],
    "sg:phone":"+1 905 673 6565",
    "sg:postcode":"L4T 3Z9",
    "sg:province":"ON",
    "sg:tags":[
        "dentist"
    ],
    "wof:name":"Brandon Gate Dental Office",
    "wof:placetype":"venue"
},
  "geometry": {"coordinates":[-79.6345672607,43.7320556641],"type":"Point"}
}