{
  "type": "Feature",
  "properties": {
    "iso:country":"CA",
    "sg:city":"Vancouver",
    "sg:classifiers":[
        {
            "category":"Arts & Performance",
            "subcategory":"Theater",
            "type":"Entertainment"
        }
    ],
    "sg:phone":"+1 604 713 6980",
    "sg:postcode":"V5T 1G5",
    "sg:province":"BC",
    "sg:tags":[
        "talent",
        "agency",
        "casting"
    ],
    "wof:name":"King Talent Inc",
    "wof:placetype":"venue"
},
  "geometry": {"coordinates":[-123.100136,49.2672],"type":"Point"}
}