{
  "type": "Feature",
  "properties": {
    "addr:full":"6830 42 St NW Edmonton AB T6B 3C9",
    "addr:housenumber":"6830",
    "addr:postcode":"t6b 3c9",
    "addr:street":"42 St Nw",
    "iso:country":"CA",
    "sg:address":"6830 42 St NW",
    "sg:city":"Edmonton",
    "sg:classifiers":[
        {
            "category":"Manufacturing",
            "subcategory":"Tools & Machinery",
            "type":"Manufacturing & Wholesale Goods"
        }
    ],
    "sg:phone":"+1 780 469 7000",
    "sg:postcode":"T6B 3C9",
    "sg:province":"AB",
    "sg:tags":[
        "machine",
        "shop"
    ],
    "wof:name":"Gambit Products Ltd",
    "wof:placetype":"venue"
},
  "geometry": {"coordinates":[-113.405975,53.505272],"type":"Point"}
}