{
  "type": "Feature",
  "properties": {
    "addr:full":"1545 Ch Beaulne Val-Morin QC J0T 2R0",
    "addr:housenumber":"1545",
    "addr:postcode":"j0t 2r0",
    "addr:street":"Ch Beaulne",
    "iso:country":"CA",
    "sg:address":"1545 Ch Beaulne",
    "sg:city":"Val-Morin",
    "sg:classifiers":[
        {
            "category":"Education",
            "subcategory":"School",
            "type":"Public Place"
        }
    ],
    "sg:phone":"+1 819 322 7178",
    "sg:postcode":"J0T 2R0",
    "sg:province":"QC",
    "sg:tags":[
        "academic",
        "special"
    ],
    "wof:name":"Ecole Emanuel",
    "wof:placetype":"venue"
},
  "geometry": {"coordinates":[-74.226105,45.983601],"type":"Point"}
}