{
  "type": "Feature",
  "properties": {
    "addr:full":"222 Aylmer Rd Chase BC V0E 1M0",
    "addr:housenumber":"222",
    "addr:postcode":"v0e 1m0",
    "addr:street":"Aylmer Rd",
    "iso:country":"CA",
    "sg:address":"222 Aylmer Rd",
    "sg:city":"Chase",
    "sg:classifiers":[
        {
            "category":"Retail",
            "subcategory":"Auto Repair",
            "type":"Services"
        }
    ],
    "sg:phone":"+1 250 679 8443",
    "sg:postcode":"V0E 1M0",
    "sg:province":"BC",
    "sg:tags":[
        "body",
        "automobile",
        "painting"
    ],
    "wof:name":"Norm's Auto Body",
    "wof:placetype":"venue"
},
  "geometry": {"coordinates":[-119.702232,50.821575],"type":"Point"}
}