{
  "type": "Feature",
  "properties": {
    "addr:full":"195 Av Leonidas S # 3 Rimouski QC G5L 2T5",
    "addr:postcode":"g5l 2t5",
    "addr:street":"195 Av Leonidas S # 3",
    "iso:country":"CA",
    "sg:address":"195 Av Leonidas S # 3",
    "sg:city":"Rimouski",
    "sg:classifiers":[
        {
            "category":"Retail",
            "subcategory":"Auto Repair",
            "type":"Services"
        }
    ],
    "sg:phone":"+1 418 725 7424",
    "sg:postcode":"G5L 2T5",
    "sg:province":"QC",
    "sg:tags":[
        "body",
        "automobile",
        "painting"
    ],
    "wof:name":"Atelier DE Carroserie SD Inc",
    "wof:placetype":"venue"
},
  "geometry": {"coordinates":[-68.5082015991,48.4615364075],"type":"Point"}
}