{
  "type": "Feature",
  "properties": {
    "addr:full":"81 Rte Du Fleuve Beaumont QC G0R 1C0",
    "addr:housenumber":"81",
    "addr:postcode":"g0r 1c0",
    "addr:street":"Rte Du Fleuve",
    "iso:country":"CA",
    "sg:address":"81 Rte Du Fleuve",
    "sg:city":"Beaumont",
    "sg:classifiers":[
        {
            "category":"Building & Trades",
            "subcategory":"Construction",
            "type":"Services"
        }
    ],
    "sg:phone":"+1 418 833 5658",
    "sg:postcode":"G0R 1C0",
    "sg:province":"QC",
    "sg:tags":[
        "foundation"
    ],
    "wof:name":"Fondations Bg Inc",
    "wof:placetype":"venue"
},
  "geometry": {"coordinates":[-70.963829,46.843624],"type":"Point"}
}