{
  "type": "Feature",
  "properties": {
    "addr:full":"49 Rue Tetreault Mont-Saint-Gregoire QC J0J 1K0",
    "addr:housenumber":"49",
    "addr:postcode":"j0j 1k0",
    "addr:street":"Rue Tetreault Mont-Saint-Gregoire",
    "iso:country":"CA",
    "sg:address":"49 Rue Tetreault",
    "sg:city":"Mont-Saint-Gregoire",
    "sg:classifiers":[
        {
            "category":"Building & Trades",
            "subcategory":"Construction",
            "type":"Services"
        }
    ],
    "sg:phone":"+1 450 346 4518",
    "sg:postcode":"J0J 1K0",
    "sg:province":"QC",
    "sg:tags":[
        "painter"
    ],
    "wof:name":"Robert Dupuis Entrepreneur Inc",
    "wof:placetype":"venue"
},
  "geometry": {"coordinates":[-73.162971,45.335594],"type":"Point"}
}