{
  "type": "Feature",
  "properties": {
    "iso:country":"CA",
    "sg:address":"3500 Dufferin St",
    "sg:city":"North York",
    "sg:classifiers":[
        {
            "category":"Professional",
            "subcategory":"Lawyer & Legal Services",
            "type":"Services"
        }
    ],
    "sg:phone":"+1 416 636 1652",
    "sg:postcode":"M3K 1N2",
    "sg:province":"ON",
    "sg:tags":[
        "attorney"
    ],
    "wof:name":"Hagler, Sidney S",
    "wof:placetype":"venue"
},
  "geometry": {"coordinates":[-79.45825958250001,43.7291717529],"type":"Point"}
}