{
  "type": "Feature",
  "properties": {
    "addr:full":"27545 31 Ave Aldergrove BC V4W 3L4",
    "addr:housenumber":"27545",
    "addr:postcode":"v4w 3l4",
    "addr:street":"31 Ave",
    "iso:country":"CA",
    "sg:address":"27545 31 Ave",
    "sg:city":"Aldergrove",
    "sg:classifiers":[
        {
            "category":"Retail",
            "subcategory":"Auto Repair",
            "type":"Services"
        }
    ],
    "sg:phone":"+1 604 856 8816",
    "sg:postcode":"V4W 3L4",
    "sg:province":"BC",
    "sg:tags":[
        "transmission"
    ],
    "wof:name":"Bob's Driveline Svc",
    "wof:placetype":"venue"
},
  "geometry": {"coordinates":[-122.461494,49.05875],"type":"Point"}
}