{
  "type": "Feature",
  "properties": {
    "addr:full":"9153 Commercial St New Minas NS B4N 3E6",
    "addr:housenumber":"9153",
    "addr:postcode":"b4n 3e6",
    "addr:street":"Commercial St",
    "iso:country":"CA",
    "sg:address":"9153 Commercial St",
    "sg:city":"New Minas",
    "sg:classifiers":[
        {
            "category":"Insurance",
            "subcategory":"Insurance Agent",
            "type":"Services"
        }
    ],
    "sg:phone":"+1 902 681 1234",
    "sg:postcode":"B4N 3E6",
    "sg:province":"NS",
    "wof:name":"Gates Insurance Ltd",
    "wof:placetype":"venue"
},
  "geometry": {"coordinates":[-64.45092,45.067345],"type":"Point"}
}