{
  "type": "Feature",
  "properties": {
    "addr:full":"1605 Rue Girouard O Saint-Hyacinthe QC J2S 2Z9",
    "addr:housenumber":"1605",
    "addr:postcode":"j2s 2z9",
    "addr:street":"Rue Girouard O",
    "iso:country":"CA",
    "sg:address":"1605 Rue Girouard O",
    "sg:city":"Saint-Hyacinthe",
    "sg:classifiers":[
        {
            "category":"Banks & Credit Unions",
            "subcategory":"Bank",
            "type":"Services"
        }
    ],
    "sg:phone":"+1 450 261 1010",
    "sg:postcode":"J2S 2Z9",
    "sg:province":"QC",
    "wof:name":"Cibc",
    "wof:placetype":"venue"
},
  "geometry": {"coordinates":[-72.93961299999999,45.641582],"type":"Point"}
}