{
  "type": "Feature",
  "properties": {
    "iso:country":"CA",
    "sg:address":"114 3 Ave SW",
    "sg:city":"Calgary",
    "sg:classifiers":[
        {
            "category":"Restaurant",
            "type":"Food & Drink"
        }
    ],
    "sg:phone":"+1 403 269 4990",
    "sg:postcode":"T2P 0E7",
    "sg:province":"AB",
    "wof:name":"Tong KY B-B-Q House",
    "wof:placetype":"venue"
},
  "geometry": {"coordinates":[-114.063278,51.050354],"type":"Point"}
}