{
  "type": "Feature",
  "properties": {
    "iso:country":"CA",
    "sg:address":"12804 141 St NW",
    "sg:city":"Edmonton",
    "sg:classifiers":[
        {
            "category":"Manufacturing",
            "subcategory":"Furniture",
            "type":"Manufacturing & Wholesale Goods"
        }
    ],
    "sg:phone":"+1 780 451 4746",
    "sg:postcode":"T5L 4N8",
    "sg:province":"AB",
    "sg:tags":[
        "general",
        "contractor"
    ],
    "wof:name":"Alps Construction Ltd",
    "wof:placetype":"venue"
},
  "geometry": {"coordinates":[-113.563903809,53.5852279663],"type":"Point"}
}