{
  "type": "Feature",
  "properties": {
    "addr:full":"5505 Broadway Ave # 2 Blackfalds AB T0M 0J0",
    "addr:housenumber":"5505",
    "addr:postcode":"t0m 0j0",
    "addr:street":"Broadway Ave # 2",
    "iso:country":"CA",
    "sg:address":"5505 Broadway Ave # 2",
    "sg:city":"Blackfalds",
    "sg:classifiers":[
        {
            "category":"Mining & Drilling",
            "type":"Manufacturing & Wholesale Goods"
        }
    ],
    "sg:phone":"+1 403 885 7779",
    "sg:postcode":"T0M 0J0",
    "sg:province":"AB",
    "sg:tags":[
        "field",
        "oil"
    ],
    "wof:name":"Brahmatech Limited",
    "wof:placetype":"venue"
},
  "geometry": {"coordinates":[-113.795425415,52.3833312988],"type":"Point"}
}