{
  "type": "Feature",
  "properties": {
    "addr:full":"1355 Regent St Sudbury ON P3E 3Z1",
    "addr:housenumber":"1355",
    "addr:postcode":"p3e 3z1",
    "addr:street":"Regent St",
    "iso:country":"CA",
    "sg:address":"1355 Regent St",
    "sg:city":"Sudbury",
    "sg:classifiers":[
        {
            "category":"Personal",
            "subcategory":"Beauty Salon",
            "type":"Services"
        }
    ],
    "sg:phone":"+1 705 523 0005",
    "sg:postcode":"P3E 3Z1",
    "sg:province":"ON",
    "wof:name":"Hair Biz",
    "wof:placetype":"venue"
},
  "geometry": {"coordinates":[-81.00975800000001,46.462776],"type":"Point"}
}