{
  "type": "Feature",
  "properties": {
    "addr:full":"Lloydminster AB T9V 0Z6",
    "addr:postcode":"t9v 0z6",
    "iso:country":"CA",
    "sg:city":"Lloydminster",
    "sg:classifiers":[
        {
            "category":"Education",
            "subcategory":"School",
            "type":"Public Place"
        }
    ],
    "sg:phone":"+1 780 875 3112",
    "sg:postcode":"T9V 0Z6",
    "sg:province":"AB",
    "wof:name":"Martin Browne School",
    "wof:placetype":"venue"
},
  "geometry": {"coordinates":[-110.020545959,53.2818145752],"type":"Point"}
}