{
  "type": "Feature",
  "properties": {
    "addr:full":"49 Industrial Dr Elmira ON N3B 3B1",
    "addr:housenumber":"49",
    "addr:postcode":"n3b 3b1",
    "addr:street":"Industrial Dr",
    "iso:country":"CA",
    "sg:address":"49 Industrial Dr",
    "sg:city":"Elmira",
    "sg:classifiers":[
        {
            "category":"Insurance",
            "subcategory":"Insurance Agent",
            "type":"Services"
        }
    ],
    "sg:phone":"+1 519 669 1631",
    "sg:postcode":"N3B 3B1",
    "sg:province":"ON",
    "wof:name":"Programmed Insurance",
    "wof:placetype":"venue"
},
  "geometry": {"coordinates":[-80.5612411499,43.587387085],"type":"Point"}
}