{
  "type": "Feature",
  "properties": {
    "addr:full":"232 Rue DE Castelnau E Montreal QC H2R 1P5",
    "addr:housenumber":"232",
    "addr:postcode":"h2r 1p5",
    "addr:street":"Rue De Castelnau E",
    "iso:country":"CA",
    "sg:address":"232 Rue DE Castelnau E",
    "sg:city":"Montreal",
    "sg:classifiers":[
        {
            "category":"Building & Trades",
            "subcategory":"Plumbing",
            "type":"Services"
        }
    ],
    "sg:phone":"+1 514 279 0367",
    "sg:postcode":"H2R 1P5",
    "sg:province":"QC",
    "sg:tags":[
        "heating",
        "contractor"
    ],
    "wof:name":"Mecanique 47 Inc",
    "wof:placetype":"venue"
},
  "geometry": {"coordinates":[-73.6180725098,45.5374336243],"type":"Point"}
}