{
  "type": "Feature",
  "properties": {
    "addr:full":"1600 Ominica St E Moose Jaw SK S6H 7K7",
    "addr:housenumber":"1600",
    "addr:postcode":"s6h 7k7",
    "addr:street":"Ominica St E",
    "iso:country":"CA",
    "sg:address":"1600 Ominica St E",
    "sg:city":"Moose Jaw",
    "sg:classifiers":[
        {
            "category":"Farming",
            "subcategory":"Nursery",
            "type":"Manufacturing & Wholesale Goods"
        }
    ],
    "sg:phone":"+1 306 692 1663",
    "sg:postcode":"S6H 7K7",
    "sg:province":"SK",
    "sg:tags":[
        "greenhouse"
    ],
    "wof:name":"Windmill Greenhouses",
    "wof:placetype":"venue"
},
  "geometry": {"coordinates":[-105.505791,50.39349],"type":"Point"}
}