{
  "type": "Feature",
  "properties": {
    "iso:country":"CA",
    "sg:address":"1013 Kentucky Crt",
    "sg:city":"New Minas",
    "sg:classifiers":[
        {
            "category":"Restaurant",
            "type":"Food & Drink"
        }
    ],
    "sg:phone":"+1 902 681 0709",
    "sg:postcode":"B4N 4N1",
    "sg:province":"NS",
    "wof:name":"Hau's Restaurant",
    "wof:placetype":"venue"
},
  "geometry": {"coordinates":[-64.4728927612,45.0706863403],"type":"Point"}
}