{
  "type": "Feature",
  "properties": {
    "iso:country":"CA",
    "sg:city":"Ottawa",
    "sg:classifiers":[
        {
            "category":"Professional",
            "subcategory":"Lawyer & Legal Services",
            "type":"Services"
        }
    ],
    "sg:phone":"+1 613 722 5292",
    "sg:postcode":"K1Z 7M4",
    "sg:province":"ON",
    "sg:tags":[
        "attorney"
    ],
    "wof:name":"Byrne, Donald J",
    "wof:placetype":"venue"
},
  "geometry": {"coordinates":[-75.74551391599999,45.3808860779],"type":"Point"}
}