{
  "type": "Feature",
  "properties": {
    "addr:full":"94 Roslyn Rd Winnipeg MB R3L 0G6",
    "addr:housenumber":"94",
    "addr:postcode":"r3l 0g6",
    "addr:street":"Roslyn Rd",
    "iso:country":"CA",
    "sg:address":"94 Roslyn Rd",
    "sg:city":"Winnipeg",
    "sg:classifiers":[
        {
            "category":"Professional",
            "subcategory":"Research",
            "type":"Services"
        }
    ],
    "sg:phone":"+1 204 452 6000",
    "sg:postcode":"R3L 0G6",
    "sg:province":"MB",
    "sg:tags":[
        "development",
        "laboratory"
    ],
    "wof:name":"Cultural Research",
    "wof:placetype":"venue"
},
  "geometry": {"coordinates":[-97.14636993409999,49.8800964355],"type":"Point"}
}