{
  "type": "Feature",
  "properties": {
    "addr:full":"2360 Midland Ave Scarborough ON M1S 4A9",
    "addr:housenumber":"2360",
    "addr:postcode":"m1s 4a9",
    "addr:street":"Midland Ave",
    "iso:country":"CA",
    "sg:address":"2360 Midland Ave",
    "sg:city":"Scarborough",
    "sg:classifiers":[
        {
            "category":"Home & Garden",
            "subcategory":"Building Materials",
            "type":"Retail Goods"
        }
    ],
    "sg:phone":"+1 416 291 8955",
    "sg:postcode":"M1S 4A9",
    "sg:province":"ON",
    "sg:tags":[
        "glass",
        "window",
        "plate"
    ],
    "wof:name":"Auto Glass Spot",
    "wof:placetype":"venue"
},
  "geometry": {"coordinates":[-79.275841,43.779411],"type":"Point"}
}