{
  "type": "Feature",
  "properties": {
    "addr:full":"Victoria BC V8W 1G1",
    "addr:postcode":"v8w 1g1",
    "iso:country":"CA",
    "sg:city":"Victoria",
    "sg:classifiers":[
        {
            "category":"Professional",
            "subcategory":"Lawyer & Legal Services",
            "type":"Services"
        }
    ],
    "sg:phone":"+1 250 383 3466",
    "sg:postcode":"V8W 1G1",
    "sg:province":"BC",
    "sg:tags":[
        "attorney"
    ],
    "wof:name":"Hillyer Atkins",
    "wof:placetype":"venue"
},
  "geometry": {"coordinates":[-123.367149353,48.4246292114],"type":"Point"}
}