{
  "type": "Feature",
  "properties": {
    "addr:full":"3210 3 St SW Calgary AB T2S 1V3",
    "addr:housenumber":"3210 3",
    "addr:postcode":"t2s 1v3",
    "addr:street":"St Sw",
    "iso:country":"CA",
    "sg:address":"3210 3 St SW",
    "sg:city":"Calgary",
    "sg:classifiers":[
        {
            "category":"Mining & Drilling",
            "type":"Manufacturing & Wholesale Goods"
        }
    ],
    "sg:phone":"+1 403 237 0160",
    "sg:postcode":"T2S 1V3",
    "sg:province":"AB",
    "sg:tags":[
        "company",
        "oil"
    ],
    "wof:name":"Foret Management Ltd",
    "wof:placetype":"venue"
},
  "geometry": {"coordinates":[-114.069771,51.026138],"type":"Point"}
}