{
  "type": "Feature",
  "properties": {
    "addr:full":"621 Boul Saint-Laurent E # A Louiseville QC J5V 1J1",
    "addr:housenumber":"621",
    "addr:postcode":"j5v 1j1",
    "addr:street":"Boul Saint-Laurent E # A",
    "iso:country":"CA",
    "sg:address":"621 Boul Saint-Laurent E # A",
    "sg:city":"Louiseville",
    "sg:classifiers":[
        {
            "category":"Health Services",
            "subcategory":"Doctor",
            "type":"Services"
        }
    ],
    "sg:phone":"+1 819 228 4151",
    "sg:postcode":"J5V 1J1",
    "sg:province":"QC",
    "sg:tags":[
        "clinic"
    ],
    "wof:name":"Lessard, Gilles",
    "wof:placetype":"venue"
},
  "geometry": {"coordinates":[-72.919601,46.257965],"type":"Point"}
}