{
  "type": "Feature",
  "properties": {
    "addr:full":"191 Main St W # 611 Hamilton ON L8P 4S2",
    "addr:housenumber":"191;611",
    "addr:postcode":"l8p 4s2",
    "addr:street":"Main St W #",
    "iso:country":"CA",
    "sg:address":"191 Main St W # 611",
    "sg:city":"Hamilton",
    "sg:classifiers":[
        {
            "category":"Social Services",
            "type":"Services"
        }
    ],
    "sg:phone":"+1 905 540 8932",
    "sg:postcode":"L8P 4S2",
    "sg:province":"ON",
    "sg:tags":[
        "organization",
        "welfare"
    ],
    "wof:name":"Gwen Lee Supportive Housing",
    "wof:placetype":"venue"
},
  "geometry": {"coordinates":[-79.87767028810001,43.2571754456],"type":"Point"}
}