{
  "type": "Feature",
  "properties": {
    "addr:full":"1353 Marine Dr West Vancouver BC V7T 1B6",
    "addr:housenumber":"1353",
    "addr:postcode":"v7t 1b6",
    "addr:street":"Marine Dr",
    "iso:country":"CA",
    "sg:address":"1353 Marine Dr",
    "sg:city":"West Vancouver",
    "sg:classifiers":[
        {
            "category":"Organizations",
            "subcategory":"Religious Organization",
            "type":"Services"
        }
    ],
    "sg:phone":"+1 604 922 2646",
    "sg:postcode":"V7T 1B6",
    "sg:province":"BC",
    "sg:tags":[
        "church"
    ],
    "wof:name":"Christian Science Reading Room",
    "wof:placetype":"venue"
},
  "geometry": {"coordinates":[-123.153030395,49.3278961182],"type":"Point"}
}