{
  "type": "Feature",
  "properties": {
    "addr:full":"184 Veneto Dr Woodbridge ON L4L 8X6",
    "addr:housenumber":"184",
    "addr:postcode":"l4l 8x6",
    "addr:street":"Veneto Dr",
    "iso:country":"CA",
    "sg:address":"184 Veneto Dr",
    "sg:city":"Woodbridge",
    "sg:classifiers":[
        {
            "category":"Professional",
            "subcategory":"Accounting & Tax Preparation",
            "type":"Services"
        }
    ],
    "sg:phone":"+1 905 850 9956",
    "sg:postcode":"L4L 8X6",
    "sg:province":"ON",
    "sg:tags":[
        "accountant"
    ],
    "wof:name":"Kramer, AL",
    "wof:placetype":"venue"
},
  "geometry": {"coordinates":[-79.59074401860001,43.7754058838],"type":"Point"}
}