{
  "type": "Feature",
  "properties": {
    "addr:full":"Ottawa ON K1N 5M5",
    "addr:postcode":"k1n 5m5",
    "iso:country":"CA",
    "sg:city":"Ottawa",
    "sg:classifiers":[
        {
            "category":"Health Services",
            "subcategory":"Doctor",
            "type":"Services"
        }
    ],
    "sg:phone":"+1 613 562 1972",
    "sg:postcode":"K1N 5M5",
    "sg:province":"ON",
    "sg:tags":[
        "physician",
        "surgeon"
    ],
    "wof:name":"Krelina, Michael MD",
    "wof:placetype":"venue"
},
  "geometry": {"coordinates":[-75.692795,45.430199],"type":"Point"}
}