{
  "type": "Feature",
  "properties": {
    "iso:country":"CA",
    "sg:city":"Vancouver",
    "sg:classifiers":[
        {
            "category":"Professional",
            "subcategory":"Business Services",
            "type":"Services"
        }
    ],
    "sg:phone":"+1 604 689 8232",
    "sg:postcode":"V6C 3C1",
    "sg:province":"BC",
    "sg:tags":[
        "convention",
        "meeting",
        "facility"
    ],
    "wof:name":"Vancouver Convention & Exhbtn",
    "wof:placetype":"venue"
},
  "geometry": {"coordinates":[-123.114898682,49.2880020142],"type":"Point"}
}