{
  "type": "Feature",
  "properties": {
    "addr:full":"4261 Rue Sainte-Catherine E Montreal QC H1V 1X5",
    "addr:housenumber":"4261",
    "addr:postcode":"h1v 1x5",
    "addr:street":"Rue Sainte-Catherine E",
    "iso:country":"CA",
    "sg:address":"4261 Rue Sainte-Catherine E",
    "sg:city":"Montreal",
    "sg:classifiers":[
        {
            "category":"Personal",
            "subcategory":"Beauty Salon",
            "type":"Services"
        }
    ],
    "sg:phone":"+1 514 931 2189",
    "sg:postcode":"H1V 1X5",
    "sg:province":"QC",
    "wof:name":"Esthetique Gentillesse",
    "wof:placetype":"venue"
},
  "geometry": {"coordinates":[-73.5346069336,45.5502586365],"type":"Point"}
}