{
  "type": "Feature",
  "properties": {
    "addr:full":"4 Sir Lou Dr Brampton ON L6Y 4J7",
    "addr:housenumber":"4",
    "addr:postcode":"l6y 4j7",
    "addr:street":"Sir Lou Dr",
    "iso:country":"CA",
    "sg:address":"4 Sir Lou Dr",
    "sg:city":"Brampton",
    "sg:classifiers":[
        {
            "category":"Social Services",
            "type":"Services"
        }
    ],
    "sg:phone":"+1 905 451 9475",
    "sg:postcode":"L6Y 4J7",
    "sg:province":"ON",
    "sg:tags":[
        "organization",
        "welfare"
    ],
    "wof:name":"Supportive Housing in Peel",
    "wof:placetype":"venue"
},
  "geometry": {"coordinates":[-79.72805,43.661472],"type":"Point"}
}