{
  "type": "Feature",
  "properties": {
    "addr:full":"906 1st Ave W Prince Albert SK S6V 4Y2",
    "addr:housenumber":"906",
    "addr:postcode":"s6v 4y2",
    "addr:street":"1St Ave W",
    "iso:country":"CA",
    "sg:address":"906 1st Ave W",
    "sg:city":"Prince Albert",
    "sg:classifiers":[
        {
            "category":"Travel",
            "subcategory":"Hotels & Motels",
            "type":"Entertainment"
        }
    ],
    "sg:phone":"+1 306 763 2671",
    "sg:postcode":"S6V 4Y2",
    "sg:province":"SK",
    "wof:name":"National Hotel",
    "wof:placetype":"venue"
},
  "geometry": {"coordinates":[-105.75710296600001,53.2042274475],"type":"Point"}
}