{
  "type": "Feature",
  "properties": {
    "addr:full":"602 Lenore Dr Saskatoon SK S7K 6A6",
    "addr:housenumber":"602",
    "addr:postcode":"s7k 6a6",
    "addr:street":"Lenore Dr",
    "iso:country":"CA",
    "sg:address":"602 Lenore Dr",
    "sg:city":"Saskatoon",
    "sg:classifiers":[
        {
            "category":"Education",
            "subcategory":"School",
            "type":"Public Place"
        }
    ],
    "sg:phone":"+1 306 683 7750",
    "sg:postcode":"S7K 6A6",
    "sg:province":"SK",
    "wof:name":"Marion M Graham Collegiate",
    "wof:placetype":"venue"
},
  "geometry": {"coordinates":[-106.620666504,52.1758537292],"type":"Point"}
}