{
  "type": "Feature",
  "properties": {
    "addr:full":"60 Leduc Towne Ctr Leduc AB T9E 7K6",
    "addr:housenumber":"60",
    "addr:postcode":"t9e 7k6",
    "addr:street":"Leduc Towne Ctr",
    "iso:country":"CA",
    "sg:address":"60 Leduc Towne Ctr",
    "sg:city":"Leduc",
    "sg:classifiers":[
        {
            "category":"Manufacturing",
            "subcategory":"Printing",
            "type":"Manufacturing & Wholesale Goods"
        }
    ],
    "sg:phone":"+1 780 986 5656",
    "sg:postcode":"T9E 7K6",
    "sg:province":"AB",
    "sg:tags":[
        "printer",
        "duplicating",
        "copying"
    ],
    "wof:name":"Sure Print & Copy",
    "wof:placetype":"venue"
},
  "geometry": {"coordinates":[-113.552177,53.265797],"type":"Point"}
}