{
  "type": "Feature",
  "properties": {
    "addr:full":"606 38 Ave NE Calgary AB T2E 8J9",
    "addr:postcode":"t2e 8j9",
    "addr:street":"606 38 Ave Ne",
    "iso:country":"CA",
    "sg:address":"606 38 Ave NE",
    "sg:city":"Calgary",
    "sg:classifiers":[
        {
            "category":"Organizations",
            "subcategory":"Professional Association",
            "type":"Services"
        }
    ],
    "sg:phone":"+1 403 276 1775",
    "sg:postcode":"T2E 8J9",
    "sg:province":"AB",
    "wof:name":"Royal Canadian Legion",
    "wof:placetype":"venue"
},
  "geometry": {"coordinates":[-114.050797,51.087002],"type":"Point"}
}