{
  "type": "Feature",
  "properties": {
    "addr:full":"514 Montee Morel Sainte-Sophie QC J5J 2R8",
    "addr:housenumber":"514",
    "addr:postcode":"j5j 2r8",
    "addr:street":"Montee Morel",
    "iso:country":"CA",
    "sg:address":"514 Montee Morel",
    "sg:city":"Sainte-Sophie",
    "sg:classifiers":[
        {
            "category":"Building & Trades",
            "subcategory":"Construction",
            "type":"Services"
        }
    ],
    "sg:phone":"+1 450 432 7881",
    "sg:postcode":"J5J 2R8",
    "sg:province":"QC",
    "sg:tags":[
        "general",
        "contractor"
    ],
    "wof:name":"Construction J LA Pointe & Fil",
    "wof:placetype":"venue"
},
  "geometry": {"coordinates":[-73.8984680176,45.8190879822],"type":"Point"}
}