{
  "type": "Feature",
  "properties": {
    "iso:country":"CA",
    "sg:address":"38 College St",
    "sg:city":"Chesterville",
    "sg:classifiers":[
        {
            "category":"Education",
            "subcategory":"School",
            "type":"Public Place"
        }
    ],
    "sg:phone":"+1 613 448 2224",
    "sg:postcode":"K0C 1H0",
    "sg:province":"ON",
    "wof:name":"Chesterville Public School",
    "wof:placetype":"venue"
},
  "geometry": {"coordinates":[-75.2330169678,45.1005172729],"type":"Point"}
}