{
  "type": "Feature",
  "properties": {
    "addr:full":"Bathurst NB E2A 4W7",
    "addr:postcode":"e2a 4w7",
    "iso:country":"CA",
    "sg:city":"Bathurst",
    "sg:classifiers":[
        {
            "category":"Freight",
            "type":"Transportation"
        }
    ],
    "sg:phone":"+1 506 546 7400",
    "sg:postcode":"E2A 4W7",
    "sg:province":"NB",
    "sg:tags":[
        "trucking"
    ],
    "wof:name":"Day & Ross Inc",
    "wof:placetype":"venue"
},
  "geometry": {"coordinates":[-65.62506866459999,47.600730896],"type":"Point"}
}