{
  "type": "Feature",
  "properties": {
    "addr:full":"1st Ave Glaslyn SK S0M 0Y0",
    "addr:postcode":"s0m 0y0",
    "addr:street":"1St Ave",
    "iso:country":"CA",
    "sg:address":"1st Ave",
    "sg:city":"Glaslyn",
    "sg:classifiers":[
        {
            "category":"Health Services",
            "subcategory":"Doctor",
            "type":"Services"
        }
    ],
    "sg:phone":"+1 306 342 4567",
    "sg:postcode":"S0M 0Y0",
    "sg:province":"SK",
    "sg:tags":[
        "clinic"
    ],
    "wof:name":"Glaslyn Medical Clinic",
    "wof:placetype":"venue"
},
  "geometry": {"coordinates":[-108.357513,53.362999],"type":"Point"}
}