{
  "type": "Feature",
  "properties": {
    "addr:full":"275 Rue Houde Saint-Laurent QC H4N 2J3",
    "addr:housenumber":"275",
    "addr:postcode":"h4n 2j3",
    "addr:street":"Rue Houde",
    "iso:country":"CA",
    "sg:address":"275 Rue Houde",
    "sg:city":"Saint-Laurent",
    "sg:classifiers":[
        {
            "category":"Organizations",
            "subcategory":"Professional Association",
            "type":"Services"
        }
    ],
    "sg:phone":"+1 514 744 3321",
    "sg:postcode":"H4N 2J3",
    "sg:province":"QC",
    "wof:name":"Communaute Hellenique DE Mtl",
    "wof:placetype":"venue"
},
  "geometry": {"coordinates":[-73.662399292,45.51537323],"type":"Point"}
}