{
  "type": "Feature",
  "properties": {
    "addr:full":"3007 Granville St Vancouver BC V6H 3J9",
    "addr:housenumber":"3007",
    "addr:postcode":"v6h 3j9",
    "addr:street":"Granville St",
    "iso:country":"CA",
    "sg:address":"3007 Granville St",
    "sg:city":"Vancouver",
    "sg:classifiers":[
        {
            "category":"Shopping",
            "subcategory":"Used Merchandise",
            "type":"Retail Goods"
        }
    ],
    "sg:phone":"+1 604 733 1326",
    "sg:postcode":"V6H 3J9",
    "sg:province":"BC",
    "sg:tags":[
        "antique"
    ],
    "wof:name":"Hampshire Antiques Ltd",
    "wof:placetype":"venue"
},
  "geometry": {"coordinates":[-123.138916016,49.2587966919],"type":"Point"}
}