{
  "type": "Feature",
  "properties": {
    "addr:full":"1601 Boul Saint-Martin E Laval QC H7G 4R4",
    "addr:housenumber":"1601",
    "addr:postcode":"qc h7g 4r4",
    "addr:street":"Boul Saint-Martin E",
    "iso:country":"CA",
    "sg:address":"1601 Boul Saint-Martin E",
    "sg:city":"Laval",
    "sg:classifiers":[
        {
            "category":"Autos & Motor Vehicles",
            "subcategory":"Automobile Sales",
            "type":"Retail Goods"
        }
    ],
    "sg:phone":"+1 450 669 7070",
    "sg:postcode":"H7G 4R4",
    "sg:province":"QC",
    "sg:tags":[
        "car",
        "dealer"
    ],
    "wof:name":"Bourassa Pontiac Buick Gmc",
    "wof:placetype":"venue"
},
  "geometry": {"coordinates":[-73.695168,45.591679],"type":"Point"}
}