{
  "type": "Feature",
  "properties": {
    "iso:country":"CA",
    "sg:address":"4909 50th St",
    "sg:city":"Mayerthorpe",
    "sg:classifiers":[
        {
            "category":"Shopping",
            "subcategory":"Catalog Store",
            "type":"Retail Goods"
        }
    ],
    "sg:phone":"+1 780 786 2221",
    "sg:postcode":"T0E 1N0",
    "sg:province":"AB",
    "sg:tags":[
        "mail",
        "order",
        "internet"
    ],
    "wof:name":"Sears Canada Inc",
    "wof:placetype":"venue"
},
  "geometry": {"coordinates":[-115.13871765099999,53.9539413452],"type":"Point"}
}