{
  "type": "Feature",
  "properties": {
    "addr:full":"House 247 Cape Dorset NU X0A 0C0",
    "addr:housenumber":"247",
    "addr:postcode":"x0a 0c0",
    "iso:country":"CA",
    "sg:address":"House 247",
    "sg:city":"Cape Dorset",
    "sg:classifiers":[
        {
            "category":"Utilities",
            "subcategory":"Cable",
            "type":"Services"
        }
    ],
    "sg:phone":"+1 867 897 8080",
    "sg:postcode":"X0A 0C0",
    "sg:province":"NU",
    "sg:tags":[
        "television"
    ],
    "wof:name":"Kingait Cablevision",
    "wof:placetype":"venue"
},
  "geometry": {"coordinates":[-76.54080963129999,64.2313461304],"type":"Point"}
}