{
  "type": "Feature",
  "properties": {
    "addr:full":"2465 Hastings St E Vancouver BC V5K 1Y8",
    "addr:housenumber":"2465",
    "addr:postcode":"v5k 1y8",
    "addr:street":"Hastings St E",
    "iso:country":"CA",
    "sg:address":"2465 Hastings St E",
    "sg:city":"Vancouver",
    "sg:classifiers":[
        {
            "category":"Restaurant",
            "type":"Food & Drink"
        }
    ],
    "sg:phone":"+1 604 253 2522",
    "sg:postcode":"V5K 1Y8",
    "sg:province":"BC",
    "wof:name":"Roundel Cafe",
    "wof:placetype":"venue"
},
  "geometry": {"coordinates":[-123.055290222,49.2813949585],"type":"Point"}
}