{
  "type": "Feature",
  "properties": {
    "addr:full":"750 Boul Lebeau Saint-Laurent QC H4N 1S4",
    "addr:housenumber":"750",
    "addr:postcode":"h4n 1s4",
    "addr:street":"Boul Lebeau",
    "iso:country":"CA",
    "sg:address":"750 Boul Lebeau",
    "sg:city":"Saint-Laurent",
    "sg:classifiers":[
        {
            "category":"Manufacturing",
            "subcategory":"Printing",
            "type":"Manufacturing & Wholesale Goods"
        }
    ],
    "sg:phone":"+1 514 336 0710",
    "sg:postcode":"H4N 1S4",
    "sg:province":"QC",
    "sg:tags":[
        "printer"
    ],
    "wof:name":"Edicible Limitee",
    "wof:placetype":"venue"
},
  "geometry": {"coordinates":[-73.665482,45.527611],"type":"Point"}
}