{
  "type": "Feature",
  "properties": {
    "addr:full":"2135 41st Ave W Vancouver BC V6M 1Z6",
    "addr:housenumber":"2135",
    "addr:postcode":"v6m 1z6",
    "addr:street":"41St Ave W",
    "iso:country":"CA",
    "sg:address":"2135 41st Ave W",
    "sg:city":"Vancouver",
    "sg:classifiers":[
        {
            "category":"Shopping",
            "subcategory":"Clothing, Apparel, & Fashions",
            "type":"Retail Goods"
        }
    ],
    "sg:phone":"+1 604 261 5128",
    "sg:postcode":"V6M 1Z6",
    "sg:province":"BC",
    "wof:name":"Chapy's Women's Wear",
    "wof:placetype":"venue"
},
  "geometry": {"coordinates":[-123.156585693,49.2347183228],"type":"Point"}
}