{
  "type": "Feature",
  "properties": {
    "addr:full":"1723 Jane St North York ON M9N 2S3",
    "addr:housenumber":"1723",
    "addr:postcode":"m9n 2s3",
    "addr:street":"Jane St",
    "iso:country":"CA",
    "sg:address":"1723 Jane St",
    "sg:city":"North York",
    "sg:classifiers":[
        {
            "category":"Shopping",
            "subcategory":"Clothing, Apparel, & Fashions",
            "type":"Retail Goods"
        }
    ],
    "sg:phone":"+1 416 248 5441",
    "sg:postcode":"M9N 2S3",
    "sg:province":"ON",
    "wof:name":"Glady's Variedades",
    "wof:placetype":"venue"
},
  "geometry": {"coordinates":[-79.503868,43.703876],"type":"Point"}
}