{
  "type": "Feature",
  "properties": {
    "addr:full":"12285 Rue April Pointe-Aux-Trembles QC H1B 5L8",
    "addr:housenumber":"12285",
    "addr:postcode":"h1b 5l8",
    "addr:street":"Rue April",
    "iso:country":"CA",
    "sg:address":"12285 Rue April",
    "sg:city":"Pointe-Aux-Trembles",
    "sg:classifiers":[
        {
            "category":"Manufacturing",
            "subcategory":"Metals",
            "type":"Manufacturing & Wholesale Goods"
        }
    ],
    "sg:phone":"+1 514 640 3151",
    "sg:postcode":"H1B 5L8",
    "sg:province":"QC",
    "sg:tags":[
        "steel"
    ],
    "wof:name":"Can-Bec Metal Inc",
    "wof:placetype":"venue"
},
  "geometry": {"coordinates":[-73.515556,45.648365],"type":"Point"}
}