{
  "type": "Feature",
  "properties": {
    "addr:full":"Quebec QC G2K 2A2",
    "addr:postcode":"g2k 2a2",
    "iso:country":"CA",
    "sg:city":"Quebec",
    "sg:classifiers":[
        {
            "category":"Insurance",
            "subcategory":"Insurance Agent",
            "type":"Services"
        }
    ],
    "sg:phone":"+1 418 658 8771",
    "sg:postcode":"G2K 2A2",
    "sg:province":"QC",
    "wof:name":"Guy Bergeron & Assoc",
    "wof:placetype":"venue"
},
  "geometry": {"coordinates":[-71.29475402830001,46.8310585022],"type":"Point"}
}