{
  "type": "Feature",
  "properties": {
    "addr:full":"Highway 10 N Flesherton ON N0C 1E0",
    "addr:postcode":"n0c 1e0",
    "addr:street":"Highway 10 N",
    "iso:country":"CA",
    "sg:address":"Highway 10 N",
    "sg:city":"Flesherton",
    "sg:classifiers":[
        {
            "category":"Government",
            "subcategory":"Office",
            "type":"Public Place"
        }
    ],
    "sg:phone":"+1 519 924 3658",
    "sg:postcode":"N0C 1E0",
    "sg:province":"ON",
    "sg:tags":[
        "village"
    ],
    "wof:name":"Flesherton Wastewater Treatmnt",
    "wof:placetype":"venue"
},
  "geometry": {"coordinates":[-80.54986572270001,44.2612342834],"type":"Point"}
}