{
  "type": "Feature",
  "properties": {
    "addr:full":"110 Charlotte St Saint John NB E2L 2J3",
    "addr:housenumber":"110",
    "addr:postcode":"nb e2l 2j3",
    "addr:street":"Charlotte St",
    "iso:country":"CA",
    "sg:address":"110 Charlotte St",
    "sg:city":"Saint John",
    "sg:classifiers":[
        {
            "category":"Government",
            "subcategory":"Office",
            "type":"Public Place"
        }
    ],
    "sg:phone":"+1 506 658 2504",
    "sg:postcode":"E2L 2J3",
    "sg:province":"NB",
    "wof:name":"New Brunswick Public Utilities",
    "wof:placetype":"venue"
},
  "geometry": {"coordinates":[-66.0583190918,45.272480011],"type":"Point"}
}