{
  "type": "Feature",
  "properties": {
    "addr:full":"419 Sutherland Dr East York ON M4G 1K4",
    "addr:housenumber":"419",
    "addr:postcode":"m4g 1k4",
    "addr:street":"Sutherland Dr",
    "iso:country":"CA",
    "sg:address":"419 Sutherland Dr",
    "sg:city":"East York",
    "sg:classifiers":[
        {
            "category":"Personal",
            "subcategory":"Beauty Salon",
            "type":"Services"
        }
    ],
    "sg:phone":"+1 416 425 6404",
    "sg:postcode":"M4G 1K4",
    "sg:province":"ON",
    "wof:name":"Leeside Haircare",
    "wof:placetype":"venue"
},
  "geometry": {"coordinates":[-79.36687499999999,43.712746],"type":"Point"}
}