{
  "type": "Feature",
  "properties": {
    "addr:full":"440 Niagara St Welland ON L3C 1L5",
    "addr:housenumber":"440",
    "addr:postcode":"l3c 1l5",
    "addr:street":"Niagara St",
    "iso:country":"CA",
    "sg:address":"440 Niagara St",
    "sg:city":"Welland",
    "sg:classifiers":[
        {
            "category":"Banks & Credit Unions",
            "subcategory":"Bank",
            "type":"Services"
        }
    ],
    "sg:phone":"+1 905 735 8750",
    "sg:postcode":"L3C 1L5",
    "sg:province":"ON",
    "wof:name":"Scotiabank",
    "wof:placetype":"venue"
},
  "geometry": {"coordinates":[-79.2527923584,43.0025901794],"type":"Point"}
}