{
  "type": "Feature",
  "properties": {
    "addr:full":"Mississauga ON L4W 3E6",
    "addr:postcode":"l4w 3e6",
    "iso:country":"CA",
    "sg:city":"Mississauga",
    "sg:classifiers":[
        {
            "category":"Manufacturing",
            "subcategory":"Metals",
            "type":"Manufacturing & Wholesale Goods"
        }
    ],
    "sg:phone":"+1 905 624 8435",
    "sg:postcode":"L4W 3E6",
    "sg:province":"ON",
    "sg:tags":[
        "door"
    ],
    "wof:name":"Greater Toronto Area Custom",
    "wof:placetype":"venue"
},
  "geometry": {"coordinates":[-79.622803,43.634041],"type":"Point"}
}