{
  "type": "Feature",
  "properties": {
    "addr:full":"314 Rue Pinder O Rouyn-Noranda QC J9X 2Y8",
    "addr:housenumber":"314",
    "addr:postcode":"j9x 2y8",
    "addr:street":"Rue Pinder O",
    "iso:country":"CA",
    "sg:address":"314 Rue Pinder O",
    "sg:city":"Rouyn-Noranda",
    "sg:classifiers":[
        {
            "category":"Food & Beverages",
            "subcategory":"Groceries & Convenience Stores",
            "type":"Retail Goods"
        }
    ],
    "sg:phone":"+1 819 762 4031",
    "sg:postcode":"J9X 2Y8",
    "sg:province":"QC",
    "sg:tags":[
        "grocer"
    ],
    "wof:name":"Epicerie Leo Enr",
    "wof:placetype":"venue"
},
  "geometry": {"coordinates":[-79.02990699999999,48.234657],"type":"Point"}
}