{
  "type": "Feature",
  "properties": {
    "iso:country":"CA",
    "sg:city":"Chilliwack",
    "sg:classifiers":[
        {
            "category":"Health Services",
            "subcategory":"Health Practitioner",
            "type":"Services"
        }
    ],
    "sg:phone":"+1 604 858 7422",
    "sg:postcode":"V2R 3V1",
    "sg:province":"BC",
    "sg:tags":[
        "physician"
    ],
    "wof:name":"Sardis Naturoprathic Medical",
    "wof:placetype":"venue"
},
  "geometry": {"coordinates":[-121.968078613,49.1424026489],"type":"Point"}
}