{
  "type": "Feature",
  "properties": {
    "iso:country":"CA",
    "sg:address":"1 Govt Road Allowance N",
    "sg:city":"Pierson",
    "sg:classifiers":[
        {
            "category":"Education",
            "subcategory":"School",
            "type":"Public Place"
        }
    ],
    "sg:phone":"+1 204 634 2390",
    "sg:postcode":"R0M 1S0",
    "sg:province":"MB",
    "wof:name":"Pierson School",
    "wof:placetype":"venue"
},
  "geometry": {"coordinates":[-101.25668335,49.1793899536],"type":"Point"}
}