{
  "type": "Feature",
  "properties": {
    "addr:full":"4710 50 Ave Camrose AB T4V 0R8",
    "addr:housenumber":"4710",
    "addr:postcode":"t4v 0r8",
    "addr:street":"50 Ave",
    "iso:country":"CA",
    "sg:address":"4710 50 Ave",
    "sg:city":"Camrose",
    "sg:classifiers":[
        {
            "category":"Education",
            "subcategory":"Library",
            "type":"Public Place"
        }
    ],
    "sg:phone":"+1 780 672 4214",
    "sg:postcode":"T4V 0R8",
    "sg:province":"AB",
    "wof:name":"Camrose Public Library",
    "wof:placetype":"venue"
},
  "geometry": {"coordinates":[-112.820472717,53.0219612122],"type":"Point"}
}