{
  "type": "Feature",
  "properties": {
    "addr:full":"Estevan SK S4A 2A7",
    "addr:postcode":"s4a 2a7",
    "iso:country":"CA",
    "sg:city":"Estevan",
    "sg:classifiers":[
        {
            "category":"Manufacturing",
            "subcategory":"Tools & Machinery",
            "type":"Manufacturing & Wholesale Goods"
        }
    ],
    "sg:phone":"+1 306 637 4000",
    "sg:postcode":"S4A 2A7",
    "sg:province":"SK",
    "sg:tags":[
        "pump"
    ],
    "wof:name":"Harbison-Fischer Canada Ltd",
    "wof:placetype":"venue"
},
  "geometry": {"coordinates":[-102.977882385,49.1383094788],"type":"Point"}
}