{
  "type": "Feature",
  "properties": {
    "addr:full":"PO Box 7534 STN Main Edson AB T7E 1V7",
    "addr:housenumber":"po",
    "addr:postcode":"t7e 1v7",
    "addr:street":"Box 7534 Stn Main",
    "iso:country":"CA",
    "sg:address":"PO Box 7534 STN Main",
    "sg:city":"Edson",
    "sg:classifiers":[
        {
            "category":"Building & Trades",
            "subcategory":"Construction",
            "type":"Services"
        }
    ],
    "sg:phone":"+1 780 712 0692",
    "sg:postcode":"T7E 1V7",
    "sg:province":"AB",
    "sg:tags":[
        "general",
        "contractor"
    ],
    "wof:name":"A F Excavating Ltd",
    "wof:placetype":"venue"
},
  "geometry": {"coordinates":[-116.43409729,53.5821304321],"type":"Point"}
}