{
  "type": "Feature",
  "properties": {
    "iso:country":"CA",
    "sg:address":"1340 Boul Foucault",
    "sg:city":"Saint-Charles-DE-Drummond",
    "sg:classifiers":[
        {
            "category":"Building & Trades",
            "subcategory":"Construction",
            "type":"Services"
        }
    ],
    "sg:phone":"+1 819 472 4852",
    "sg:postcode":"J2C 1B1",
    "sg:province":"QC",
    "sg:tags":[
        "general",
        "contractor"
    ],
    "wof:name":"Sintra Inc",
    "wof:placetype":"venue"
},
  "geometry": {"coordinates":[-72.4790725708,45.9083747864],"type":"Point"}
}