{
  "type": "Feature",
  "properties": {
    "addr:full":"Calgary AB T2R 0A4",
    "addr:postcode":"t2r 0a4",
    "iso:country":"CA",
    "sg:city":"Calgary",
    "sg:classifiers":[
        {
            "category":"Professional",
            "subcategory":"Lawyer & Legal Services",
            "type":"Services"
        }
    ],
    "sg:phone":"+1 403 232 6200",
    "sg:postcode":"T2R 0A4",
    "sg:province":"AB",
    "sg:tags":[
        "attorney"
    ],
    "wof:name":"Nahman, Joe",
    "wof:placetype":"venue"
},
  "geometry": {"coordinates":[-114.066184998,51.0432510376],"type":"Point"}
}