{
  "type": "Feature",
  "properties": {
    "addr:full":"32040 Downes Rd Abbotsford BC V4X 1X5",
    "addr:housenumber":"32040",
    "addr:postcode":"v4x 1x5",
    "addr:street":"Downes Rd",
    "iso:country":"CA",
    "sg:address":"32040 Downes Rd",
    "sg:city":"Abbotsford",
    "sg:classifiers":[
        {
            "category":"Organizations",
            "subcategory":"Religious Organization",
            "type":"Services"
        }
    ],
    "sg:phone":"+1 604 853 2931",
    "sg:postcode":"V4X 1X5",
    "sg:province":"BC",
    "sg:tags":[
        "church"
    ],
    "wof:name":"Northview Community Church",
    "wof:placetype":"venue"
},
  "geometry": {"coordinates":[-122.336730957,49.0743179321],"type":"Point"}
}