{
  "type": "Feature",
  "properties": {
    "addr:full":"330 South Service Rd W Oakville ON L6K 3S1",
    "addr:housenumber":"330",
    "addr:postcode":"l6k 3s1",
    "addr:street":"South Service Rd W",
    "iso:country":"CA",
    "sg:address":"330 South Service Rd W",
    "sg:city":"Oakville",
    "sg:classifiers":[
        {
            "category":"Restaurant",
            "type":"Food & Drink"
        }
    ],
    "sg:phone":"+1 905 845 2963",
    "sg:postcode":"L6K 3S1",
    "sg:province":"ON",
    "sg:tags":[
        "chicken",
        "dinner"
    ],
    "wof:name":"Kfc",
    "wof:placetype":"venue"
},
  "geometry": {"coordinates":[-79.701286,43.444572],"type":"Point"}
}