{
  "type": "Feature",
  "properties": {
    "addr:full":"Oshawa ON L1G 1B2",
    "addr:postcode":"l1g 1b2",
    "iso:country":"CA",
    "sg:city":"Oshawa",
    "sg:classifiers":[
        {
            "category":"Professional",
            "subcategory":"Lawyer & Legal Services",
            "type":"Services"
        }
    ],
    "sg:phone":"+1 905 579 9400",
    "sg:postcode":"L1G 1B2",
    "sg:province":"ON",
    "sg:tags":[
        "attorney"
    ],
    "wof:name":"Scott, Brian J",
    "wof:placetype":"venue"
},
  "geometry": {"coordinates":[-78.8624343872,43.8986778259],"type":"Point"}
}