{
  "type": "Feature",
  "properties": {
    "iso:country":"CA",
    "sg:city":"Courtice",
    "sg:classifiers":[
        {
            "category":"Organizations",
            "subcategory":"Religious Organization",
            "type":"Services"
        }
    ],
    "sg:phone":"+1 905 436 3482",
    "sg:postcode":"L1E 2R6",
    "sg:province":"ON",
    "sg:tags":[
        "church"
    ],
    "wof:name":"Courtice Baptist Church",
    "wof:placetype":"venue"
},
  "geometry": {"coordinates":[-78.785484314,43.9111099243],"type":"Point"}
}