{
  "type": "Feature",
  "properties": {
    "addr:full":"1320 102 Ave Dawson Creek BC V1G 2C6",
    "addr:housenumber":"1320",
    "addr:postcode":"v1g 2c6",
    "addr:street":"102 Ave",
    "iso:country":"CA",
    "sg:address":"1320 102 Ave",
    "sg:city":"Dawson Creek",
    "sg:classifiers":[
        {
            "category":"Professional",
            "subcategory":"Lawyer & Legal Services",
            "type":"Services"
        }
    ],
    "sg:phone":"+1 250 782 7335",
    "sg:postcode":"V1G 2C6",
    "sg:province":"BC",
    "sg:tags":[
        "attorney",
        "referral"
    ],
    "wof:name":"Native Court Workers & Cnslng",
    "wof:placetype":"venue"
},
  "geometry": {"coordinates":[-120.238449,55.759781],"type":"Point"}
}