{
  "type": "Feature",
  "properties": {
    "addr:full":"1222 Robson St Vancouver BC V6E 1C1",
    "addr:housenumber":"1222",
    "addr:postcode":"v6e 1c1",
    "addr:street":"Robson St",
    "iso:country":"CA",
    "sg:address":"1222 Robson St",
    "sg:city":"Vancouver",
    "sg:classifiers":[
        {
            "category":"Restaurant",
            "type":"Food & Drink"
        }
    ],
    "sg:phone":"+1 604 694 0108",
    "sg:postcode":"V6E 1C1",
    "sg:province":"BC",
    "sg:tags":[
        "parlor",
        "ice",
        "cream"
    ],
    "wof:name":"Mondo Gelato",
    "wof:placetype":"venue"
},
  "geometry": {"coordinates":[-123.127579,49.286217],"type":"Point"}
}