{
  "type": "Feature",
  "properties": {
    "addr:full":"110 Lindgren Rd W # 1 Huntsville ON P1H 1Y2",
    "addr:housenumber":"110",
    "addr:postcode":"p1h 1y2",
    "addr:street":"Lindgren Rd W # 1",
    "iso:country":"CA",
    "sg:address":"110 Lindgren Rd W # 1",
    "sg:city":"Huntsville",
    "sg:classifiers":[
        {
            "category":"Retail",
            "subcategory":"Auto Repair",
            "type":"Services"
        }
    ],
    "sg:phone":"+1 705 789 3883",
    "sg:postcode":"P1H 1Y2",
    "sg:province":"ON",
    "sg:tags":[
        "truck"
    ],
    "wof:name":"Huntsville Truck Repairs",
    "wof:placetype":"venue"
},
  "geometry": {"coordinates":[-79.2495269775,45.3048286438],"type":"Point"}
}