{
  "type": "Feature",
  "properties": {
    "addr:full":"Saint-Antonin QC G0L 2J0",
    "addr:postcode":"g0l 2j0",
    "iso:country":"CA",
    "sg:city":"Saint-Antonin",
    "sg:classifiers":[
        {
            "category":"Government",
            "subcategory":"Office",
            "type":"Public Place"
        }
    ],
    "sg:phone":"+1 418 862 4017",
    "sg:postcode":"G0L 2J0",
    "sg:province":"QC",
    "sg:tags":[
        "village"
    ],
    "wof:name":"St-Antonin Salle Paroissiale",
    "wof:placetype":"venue"
},
  "geometry": {"coordinates":[-69.478416,47.761192],"type":"Point"}
}