{
  "type": "Feature",
  "properties": {
    "iso:country":"CA",
    "sg:address":"309 Middleton N-Wal T-L Rd",
    "sg:city":"Courtland",
    "sg:classifiers":[
        {
            "category":"Food & Beverages",
            "subcategory":"Specialty",
            "type":"Retail Goods"
        }
    ],
    "sg:phone":"+1 519 842 9912",
    "sg:postcode":"N0J 1E0",
    "sg:province":"ON",
    "sg:tags":[
        "herb"
    ],
    "wof:name":"Country Herbs",
    "wof:placetype":"venue"
},
  "geometry": {"coordinates":[-80.64297485349999,42.8417625427],"type":"Point"}
}