{
  "type": "Feature",
  "properties": {
    "addr:full":"1545 Tecumseh Rd E Windsor ON N8W 1C3",
    "addr:housenumber":"1545",
    "addr:postcode":"n8w 1c3",
    "addr:street":"Tecumseh Rd E",
    "iso:country":"CA",
    "sg:address":"1545 Tecumseh Rd E",
    "sg:city":"Windsor",
    "sg:classifiers":[
        {
            "category":"Restaurant",
            "type":"Food & Drink"
        }
    ],
    "sg:phone":"+1 519 258 3151",
    "sg:postcode":"N8W 1C3",
    "sg:province":"ON",
    "wof:name":"Franco's Restaurant",
    "wof:placetype":"venue"
},
  "geometry": {"coordinates":[-83.0030136108,42.30052948],"type":"Point"}
}