{
  "type": "Feature",
  "properties": {
    "iso:country":"CA",
    "sg:address":"26 Rue Thibault",
    "sg:city":"Levis",
    "sg:classifiers":[
        {
            "category":"Shopping",
            "subcategory":"Clothing, Apparel, & Fashions",
            "type":"Retail Goods"
        }
    ],
    "sg:phone":"+1 418 837 1175",
    "sg:postcode":"G6V 2J7",
    "sg:province":"QC",
    "sg:tags":[
        "fur",
        "business"
    ],
    "wof:name":"Fourrures Artisanales Levis",
    "wof:placetype":"venue"
},
  "geometry": {"coordinates":[-71.17131,46.814594],"type":"Point"}
}