{
  "type": "Feature",
  "properties": {
    "addr:full":"Scarborough ON M1P 4M8",
    "addr:postcode":"m1p 4m8",
    "iso:country":"CA",
    "sg:city":"Scarborough",
    "sg:classifiers":[
        {
            "category":"Wholesale",
            "subcategory":"Auto Parts",
            "type":"Manufacturing & Wholesale Goods"
        }
    ],
    "sg:phone":"+1 416 321 8966",
    "sg:postcode":"M1P 4M8",
    "sg:province":"ON",
    "sg:tags":[
        "automobile",
        "rebuilt"
    ],
    "wof:name":"Leading Place Japanese Auto",
    "wof:placetype":"venue"
},
  "geometry": {"coordinates":[-79.264061,43.771591],"type":"Point"}
}