{
  "type": "Feature",
  "properties": {
    "iso:country":"CA",
    "sg:address":"503 1st St",
    "sg:city":"Kaslo",
    "sg:classifiers":[
        {
            "category":"Social Services",
            "subcategory":"Child Care",
            "type":"Services"
        }
    ],
    "sg:phone":"+1 250 353 2222",
    "sg:postcode":"V0G 1M0",
    "sg:province":"BC",
    "wof:name":"Periwinkle Children's Ctr",
    "wof:placetype":"venue"
},
  "geometry": {"coordinates":[-116.911743164,49.9132118225],"type":"Point"}
}