{
  "type": "Feature",
  "properties": {
    "addr:full":"185 Rue Principale Granby QC J2G 2V5",
    "addr:housenumber":"185",
    "addr:postcode":"j2g 2v5",
    "addr:street":"Rue Principale",
    "iso:country":"CA",
    "sg:address":"185 Rue Principale",
    "sg:city":"Granby",
    "sg:classifiers":[
        {
            "category":"Shopping",
            "type":"Retail Goods"
        }
    ],
    "sg:phone":"+1 450 777 0804",
    "sg:postcode":"J2G 2V5",
    "sg:province":"QC",
    "sg:tags":[
        "miscellaneous",
        "store"
    ],
    "wof:name":"Plaisir Intime",
    "wof:placetype":"venue"
},
  "geometry": {"coordinates":[-72.72659299999999,45.400028],"type":"Point"}
}