{
  "type": "Feature",
  "properties": {
    "addr:full":"1850 Rue DE Malapart Trois-Rivieres QC G8Y 2N6",
    "addr:housenumber":"1850",
    "addr:postcode":"g8y 2n6",
    "addr:street":"Rue De Malapart Trois-Rivieres",
    "iso:country":"CA",
    "sg:address":"1850 Rue DE Malapart",
    "sg:city":"Trois-Rivieres",
    "sg:classifiers":[
        {
            "category":"Health Services",
            "subcategory":"Nursing And Care Facility",
            "type":"Services"
        }
    ],
    "sg:phone":"+1 819 376 1493",
    "sg:postcode":"G8Y 2N6",
    "sg:province":"QC",
    "sg:tags":[
        "home",
        "retirement",
        "community"
    ],
    "wof:name":"Residence Les Rivieres",
    "wof:placetype":"venue"
},
  "geometry": {"coordinates":[-72.587639,46.351055],"type":"Point"}
}