{
  "type": "Feature",
  "properties": {
    "iso:country":"CA",
    "sg:address":"11162 Ilderton Rd",
    "sg:city":"Ilderton",
    "sg:classifiers":[
        {
            "category":"Health Services",
            "subcategory":"Chiropractor",
            "type":"Services"
        }
    ],
    "sg:phone":"+1 519 666 2122",
    "sg:postcode":"N0M 2A0",
    "sg:province":"ON",
    "wof:name":"Mac Intosh, John A DC",
    "wof:placetype":"venue"
},
  "geometry": {"coordinates":[-81.4607849121,43.0456809998],"type":"Point"}
}