{
  "type": "Feature",
  "properties": {
    "addr:full":"555 Rue Arthur-Fecteau Dorval QC H4Y 1J7",
    "addr:housenumber":"555",
    "addr:postcode":"h4y 1j7",
    "addr:street":"Rue Arthur-Fecteau",
    "iso:country":"CA",
    "sg:address":"555 Rue Arthur-Fecteau",
    "sg:city":"Dorval",
    "sg:classifiers":[
        {
            "category":"Retail",
            "subcategory":"Auto Rental",
            "type":"Services"
        }
    ],
    "sg:phone":"+1 450 476 3385",
    "sg:postcode":"H4Y 1J7",
    "sg:province":"QC",
    "sg:tags":[
        "renting",
        "automobile"
    ],
    "wof:name":"Hertz Location D'Autos",
    "wof:placetype":"venue"
},
  "geometry": {"coordinates":[-73.7460479736,45.4506530762],"type":"Point"}
}