{
  "type": "Feature",
  "properties": {
    "addr:full":"10155 102 St NW # 170 Edmonton AB T5J 4G8",
    "addr:housenumber":"10155",
    "addr:postcode":"t5j 4g8",
    "addr:street":"102 St Nw # 170",
    "iso:country":"CA",
    "sg:address":"10155 102 St NW # 170",
    "sg:city":"Edmonton",
    "sg:classifiers":[
        {
            "category":"Professional",
            "subcategory":"Lawyer & Legal Services",
            "type":"Services"
        }
    ],
    "sg:phone":"+1 780 423 7786",
    "sg:postcode":"T5J 4G8",
    "sg:province":"AB",
    "sg:tags":[
        "attorney"
    ],
    "wof:name":"Kantor & Assoc",
    "wof:placetype":"venue"
},
  "geometry": {"coordinates":[-113.49533099999999,53.542088],"type":"Point"}
}