{
  "type": "Feature",
  "properties": {
    "iso:country":"CA",
    "sg:address":"1303 Queen St W",
    "sg:city":"Toronto",
    "sg:classifiers":[
        {
            "category":"Government",
            "subcategory":"Office",
            "type":"Public Place"
        }
    ],
    "sg:phone":"+1 416 393 7689",
    "sg:postcode":"M6K 1L6",
    "sg:province":"ON",
    "wof:name":"Parkdale Community Info Ctr",
    "wof:placetype":"venue"
},
  "geometry": {"coordinates":[-79.432723999,43.6412506104],"type":"Point"}
}