{
  "type": "Feature",
  "properties": {
    "addr:full":"80 Tycos Dr North York ON M6B 1V9",
    "addr:housenumber":"80",
    "addr:postcode":"m6b 1v9",
    "addr:street":"Tycos Dr",
    "iso:country":"CA",
    "sg:address":"80 Tycos Dr",
    "sg:city":"North York",
    "sg:classifiers":[
        {
            "category":"Organizations",
            "subcategory":"Religious Organization",
            "type":"Services"
        }
    ],
    "sg:phone":"+1 416 781 4802",
    "sg:postcode":"M6B 1V9",
    "sg:province":"ON",
    "sg:tags":[
        "church"
    ],
    "wof:name":"Ethiopian Orthodox Church",
    "wof:placetype":"venue"
},
  "geometry": {"coordinates":[-79.45742,43.704887],"type":"Point"}
}