{
  "type": "Feature",
  "properties": {
    "addr:full":"6770 King Rd Nobleton ON L0G 1N0",
    "addr:housenumber":"6770",
    "addr:postcode":"l0g 1n0",
    "addr:street":"King Rd",
    "iso:country":"CA",
    "sg:address":"6770 King Rd",
    "sg:city":"Nobleton",
    "sg:classifiers":[
        {
            "category":"Manufacturing",
            "subcategory":"Tools & Machinery",
            "type":"Manufacturing & Wholesale Goods"
        }
    ],
    "sg:phone":"+1 905 859 0581",
    "sg:postcode":"L0G 1N0",
    "sg:province":"ON",
    "sg:tags":[
        "farm",
        "contractor"
    ],
    "wof:name":"Nobleton Farm Svc Ltd",
    "wof:placetype":"venue"
},
  "geometry": {"coordinates":[-79.679397583,43.8954467773],"type":"Point"}
}