{
  "type": "Feature",
  "properties": {
    "iso:country":"CA",
    "sg:address":"PO Box 600",
    "sg:city":"Hobbema",
    "sg:classifiers":[
        {
            "category":"Education",
            "subcategory":"School",
            "type":"Public Place"
        }
    ],
    "sg:phone":"+1 780 585 3788",
    "sg:postcode":"T0C 1N0",
    "sg:province":"AB",
    "sg:tags":[
        "kindergarten"
    ],
    "wof:name":"Ermineskin Kindergarten",
    "wof:placetype":"venue"
},
  "geometry": {"coordinates":[-113.446144104,52.8340835571],"type":"Point"}
}