{
  "type": "Feature",
  "properties": {
    "iso:country":"CA",
    "sg:address":"2115 Upland Dr",
    "sg:city":"Burlington",
    "sg:classifiers":[
        {
            "category":"Insurance",
            "subcategory":"Insurance Agent",
            "type":"Services"
        }
    ],
    "sg:phone":"+1 905 336 9122",
    "sg:postcode":"L7M 2Z2",
    "sg:province":"ON",
    "sg:tags":[
        "adjuster"
    ],
    "wof:name":"Strecker Insurance Adjusters",
    "wof:placetype":"venue"
},
  "geometry": {"coordinates":[-79.825836,43.369068],"type":"Point"}
}