{
  "type": "Feature",
  "properties": {
    "iso:country":"CA",
    "sg:address":"22680 Westminster Hwy",
    "sg:city":"Richmond",
    "sg:classifiers":[
        {
            "category":"Organizations",
            "subcategory":"Religious Organization",
            "type":"Services"
        }
    ],
    "sg:phone":"+1 604 519 0123",
    "sg:postcode":"V6V 1B7",
    "sg:province":"BC",
    "sg:tags":[
        "church"
    ],
    "wof:name":"Bethany Baptist Church",
    "wof:placetype":"venue"
},
  "geometry": {"coordinates":[-122.97028350799999,49.1737632751],"type":"Point"}
}