{
  "type": "Feature",
  "properties": {
    "addr:full":"North Vancouver BC V7N 3Z4",
    "addr:postcode":"v7n 3z4",
    "iso:country":"CA",
    "sg:city":"North Vancouver",
    "sg:classifiers":[
        {
            "category":"Retail",
            "subcategory":"Laundry & Dry Cleaning",
            "type":"Services"
        }
    ],
    "sg:phone":"+1 604 987 7921",
    "sg:postcode":"V7N 3Z4",
    "sg:province":"BC",
    "sg:tags":[
        "cleaners"
    ],
    "wof:name":"Delbrook One Hour Cleaners Ltd",
    "wof:placetype":"venue"
},
  "geometry": {"coordinates":[-123.085845947,49.3430290222],"type":"Point"}
}