{
  "type": "Feature",
  "properties": {
    "addr:full":"Dixon Rd Powell River BC V8A 5C1",
    "addr:postcode":"v8a 5c1",
    "addr:street":"Dixon Rd",
    "iso:country":"CA",
    "sg:address":"Dixon Rd",
    "sg:city":"Powell River",
    "sg:classifiers":[
        {
            "category":"Farming",
            "subcategory":"Aquatic Farm",
            "type":"Manufacturing & Wholesale Goods"
        }
    ],
    "sg:phone":"+1 604 487 9202",
    "sg:postcode":"V8A 5C1",
    "sg:province":"BC",
    "sg:tags":[
        "hatchery",
        "fish"
    ],
    "wof:name":"West Coast Fishculture Ltd",
    "wof:placetype":"venue"
},
  "geometry": {"coordinates":[-124.345046997,49.7876548767],"type":"Point"}
}