{
  "type": "Feature",
  "properties": {
    "addr:full":"600 7E Rue Val-D'Or QC J9P 3P3",
    "addr:housenumber":"600",
    "addr:postcode":"j9p 3p3",
    "addr:street":"7E Rue",
    "iso:country":"CA",
    "sg:address":"600 7E Rue",
    "sg:city":"Val-D'Or",
    "sg:classifiers":[
        {
            "category":"Government",
            "subcategory":"Office",
            "type":"Public Place"
        }
    ],
    "sg:phone":"+1 819 825 3060",
    "sg:postcode":"J9P 3P3",
    "sg:province":"QC",
    "sg:tags":[
        "village"
    ],
    "wof:name":"Val D'Or Service Culturel",
    "wof:placetype":"venue"
},
  "geometry": {"coordinates":[-65.499062,48.96093],"type":"Point"}
}