{
  "type": "Feature",
  "properties": {
    "addr:full":"Saskatoon SK S7L 1E4",
    "addr:postcode":"s7l 1e4",
    "iso:country":"CA",
    "sg:city":"Saskatoon",
    "sg:classifiers":[
        {
            "category":"Real Estate",
            "subcategory":"Real Estate Operator",
            "type":"Services"
        }
    ],
    "sg:phone":"+1 306 664 1096",
    "sg:postcode":"S7L 1E4",
    "sg:province":"SK",
    "sg:tags":[
        "apartment"
    ],
    "wof:name":"Hillcrest Apartments",
    "wof:placetype":"venue"
},
  "geometry": {"coordinates":[-106.671638489,52.1341552734],"type":"Point"}
}