{
  "type": "Feature",
  "properties": {
    "iso:country":"CA",
    "sg:address":"7101 Rue Saint-Denis",
    "sg:city":"Montreal",
    "sg:classifiers":[
        {
            "category":"Food & Beverages",
            "subcategory":"Groceries & Convenience Stores",
            "type":"Retail Goods"
        }
    ],
    "sg:phone":"+1 514 271 7878",
    "sg:postcode":"H2S 2S5",
    "sg:province":"QC",
    "sg:tags":[
        "grocer"
    ],
    "wof:name":"Marche Orientale St-Denis",
    "wof:placetype":"venue"
},
  "geometry": {"coordinates":[-73.613777,45.538139],"type":"Point"}
}