{
  "type": "Feature",
  "properties": {
    "addr:full":"London ON N6K 4L2",
    "addr:postcode":"n6k 4l2",
    "iso:country":"CA",
    "sg:city":"London",
    "sg:classifiers":[
        {
            "category":"Insurance",
            "subcategory":"Insurance Agent",
            "type":"Services"
        }
    ],
    "sg:phone":"+1 519 473 2888",
    "sg:postcode":"N6K 4L2",
    "sg:province":"ON",
    "wof:name":"State Farm Insurance CO",
    "wof:placetype":"venue"
},
  "geometry": {"coordinates":[-81.330856,42.95266],"type":"Point"}
}