{
  "type": "Feature",
  "properties": {
    "addr:full":"433 Rang Bord DE L'Eau Saint-Bernard QC G0S 2G0",
    "addr:housenumber":"433",
    "addr:postcode":"g0s 2g0",
    "addr:street":"Rang Bord De L'Eau",
    "iso:country":"CA",
    "sg:address":"433 Rang Bord DE L'Eau",
    "sg:city":"Saint-Bernard",
    "sg:classifiers":[
        {
            "category":"Retail",
            "subcategory":"Auto Repair",
            "type":"Services"
        }
    ],
    "sg:phone":"+1 418 475 6630",
    "sg:postcode":"G0S 2G0",
    "sg:province":"QC",
    "sg:tags":[
        "repairing",
        "automobile"
    ],
    "wof:name":"Garage Raymac",
    "wof:placetype":"venue"
},
  "geometry": {"coordinates":[-71.114937,46.511921],"type":"Point"}
}