{
  "type": "Feature",
  "properties": {
    "addr:full":"4900 Molly Bannister Dr #1100 Red Deer AB T4R 1N9",
    "addr:housenumber":"4900",
    "addr:postcode":"t4r 1n9",
    "addr:street":"Molly Bannister Dr # 1100",
    "iso:country":"CA",
    "sg:address":"4900 Molly Bannister Dr #1100",
    "sg:city":"Red Deer",
    "sg:classifiers":[
        {
            "category":"Shopping",
            "subcategory":"Gifts & Souvenirs",
            "type":"Retail Goods"
        }
    ],
    "sg:phone":"+1 403 347 1667",
    "sg:postcode":"T4R 1N9",
    "sg:province":"AB",
    "sg:tags":[
        "cards",
        "greeting"
    ],
    "wof:name":"Carlton Cards",
    "wof:placetype":"venue"
},
  "geometry": {"coordinates":[-113.807006836,52.2450561523],"type":"Point"}
}