{
  "type": "Feature",
  "properties": {
    "addr:full":"Duart ON N0L 1H0",
    "addr:postcode":"n0l 1h0",
    "addr:street":"Duart",
    "iso:country":"CA",
    "sg:city":"Duart",
    "sg:classifiers":[
        {
            "category":"Food & Beverages",
            "subcategory":"Groceries & Convenience Stores",
            "type":"Retail Goods"
        }
    ],
    "sg:phone":"+1 519 678 3631",
    "sg:postcode":"N0L 1H0",
    "sg:province":"ON",
    "sg:tags":[
        "grocer"
    ],
    "wof:name":"Kennedy's Grocery",
    "wof:placetype":"venue"
},
  "geometry": {"coordinates":[-81.7515716553,42.5002288818],"type":"Point"}
}