{
  "type": "Feature",
  "properties": {
    "addr:full":"20 Glenbrook Way Nepean ON K2G 0V2",
    "addr:housenumber":"20",
    "addr:postcode":"k2g 0v2",
    "addr:street":"Glenbrook Way",
    "iso:country":"CA",
    "sg:address":"20 Glenbrook Way",
    "sg:city":"Nepean",
    "sg:classifiers":[
        {
            "category":"Professional",
            "subcategory":"Engineering",
            "type":"Services"
        }
    ],
    "sg:phone":"+1 613 596 1099",
    "sg:postcode":"K2G 0V2",
    "sg:province":"ON",
    "sg:tags":[
        "engineer"
    ],
    "wof:name":"Glencor Engineering Ltd",
    "wof:placetype":"venue"
},
  "geometry": {"coordinates":[-75.775246,45.339703],"type":"Point"}
}