{
  "type": "Feature",
  "properties": {
    "addr:full":"9628 102 Ave NW Edmonton AB T5H 0E6",
    "addr:housenumber":"9628",
    "addr:postcode":"t5h 0e6",
    "addr:street":"102 Ave Nw",
    "iso:country":"CA",
    "sg:address":"9628 102 Ave NW",
    "sg:city":"Edmonton",
    "sg:classifiers":[
        {
            "category":"Recreation",
            "type":"Entertainment"
        }
    ],
    "sg:phone":"+1 780 421 8968",
    "sg:postcode":"T5H 0E6",
    "sg:province":"AB",
    "sg:tags":[
        "center"
    ],
    "wof:name":"Zhi Yang Seniors Recreation",
    "wof:placetype":"venue"
},
  "geometry": {"coordinates":[-113.483818,53.544567],"type":"Point"}
}