{
  "type": "Feature",
  "properties": {
    "iso:country":"CA",
    "sg:address":"9628 102 Ave NW",
    "sg:city":"Edmonton",
    "sg:classifiers":[
        {
            "category":"Recreation",
            "type":"Entertainment"
        }
    ],
    "sg:phone":"+1 780 421 8968",
    "sg:postcode":"T5H 0E6",
    "sg:province":"AB",
    "sg:tags":[
        "center"
    ],
    "wof:name":"Zhi Yang Seniors Recreation",
    "wof:placetype":"venue"
},
  "geometry": {"coordinates":[-113.483818,53.544567],"type":"Point"}
}