{
  "type": "Feature",
  "properties": {
    "addr:full":"740 Queen St Kincardine ON N2Z 2Z5",
    "addr:housenumber":"740",
    "addr:postcode":"n2z 2z5",
    "addr:street":"Queen St",
    "iso:country":"CA",
    "sg:address":"740 Queen St",
    "sg:city":"Kincardine",
    "sg:classifiers":[
        {
            "category":"Shopping",
            "subcategory":"Clothing, Apparel, & Fashions",
            "type":"Retail Goods"
        }
    ],
    "sg:phone":"+1 519 396 5757",
    "sg:postcode":"N2Z 2Z5",
    "sg:province":"ON",
    "wof:name":"Baxter's Row Fashions",
    "wof:placetype":"venue"
},
  "geometry": {"coordinates":[-81.636169,44.176083],"type":"Point"}
}