{
  "type": "Feature",
  "properties": {
    "addr:full":"12819 Old Yale Rd Surrey BC V3T 3B1",
    "addr:housenumber":"12819",
    "addr:postcode":"v3t 3b1",
    "addr:street":"Old Yale Rd",
    "iso:country":"CA",
    "sg:address":"12819 Old Yale Rd",
    "sg:city":"Surrey",
    "sg:classifiers":[
        {
            "category":"Social Services",
            "subcategory":"Child Care",
            "type":"Services"
        }
    ],
    "sg:phone":"+1 604 930 4800",
    "sg:postcode":"V3T 3B1",
    "sg:province":"BC",
    "wof:name":"Kid's Play Daycare Ctr",
    "wof:placetype":"venue"
},
  "geometry": {"coordinates":[-122.863441467,49.1916885376],"type":"Point"}
}