{
  "type": "Feature",
  "properties": {
    "addr:full":"66 Kings Dr # 400 Winnipeg MB R3T 3E5",
    "addr:housenumber":"66",
    "addr:postcode":"r3t 3e5",
    "addr:street":"Kings Dr # 400",
    "iso:country":"CA",
    "sg:address":"66 Kings Dr # 400",
    "sg:city":"Winnipeg",
    "sg:classifiers":[
        {
            "category":"Professional",
            "subcategory":"Business Services",
            "type":"Services"
        }
    ],
    "sg:phone":"+1 204 943 9415",
    "sg:postcode":"R3T 3E5",
    "sg:province":"MB",
    "sg:tags":[
        "embroidery"
    ],
    "wof:name":"Compu-Stitch Embroidery Design",
    "wof:placetype":"venue"
},
  "geometry": {"coordinates":[-97.13217926030001,49.80286026],"type":"Point"}
}