{
  "type": "Feature",
  "properties": {
    "addr:full":"52 Walton St Port Hope ON L1A 1N1",
    "addr:housenumber":"52",
    "addr:postcode":"l1a 1n1",
    "addr:street":"Walton St",
    "iso:country":"CA",
    "sg:address":"52 Walton St",
    "sg:city":"Port Hope",
    "sg:classifiers":[
        {
            "category":"Shopping",
            "subcategory":"Gifts & Souvenirs",
            "type":"Retail Goods"
        }
    ],
    "sg:phone":"+1 905 885 2424",
    "sg:postcode":"L1A 1N1",
    "sg:province":"ON",
    "sg:tags":[
        "shop"
    ],
    "wof:name":"Randalls",
    "wof:placetype":"venue"
},
  "geometry": {"coordinates":[-78.293594,43.951527],"type":"Point"}
}