{
  "type": "Feature",
  "properties": {
    "addr:full":"275 Broadway # 500 Winnipeg MB R3C 4M6",
    "addr:housenumber":"275;# 500",
    "addr:postcode":"r3c 4m6",
    "addr:street":"Broadway",
    "iso:country":"CA",
    "sg:address":"275 Broadway # 500",
    "sg:city":"Winnipeg",
    "sg:classifiers":[
        {
            "category":"Organizations",
            "subcategory":"Labor Organization",
            "type":"Services"
        }
    ],
    "sg:phone":"+1 204 947 9494",
    "sg:postcode":"R3C 4M6",
    "sg:province":"MB",
    "wof:name":"Canadian Labour Congress",
    "wof:placetype":"venue"
},
  "geometry": {"coordinates":[-97.1385803223,49.8882408142],"type":"Point"}
}