{
  "type": "Feature",
  "properties": {
    "addr:full":"9111 Roger Rd Aylmer ON N5H 2R4",
    "addr:housenumber":"9111",
    "addr:postcode":"n5h 2r4",
    "addr:street":"Roger Rd",
    "iso:country":"CA",
    "sg:address":"9111 Roger Rd",
    "sg:city":"Aylmer",
    "sg:classifiers":[
        {
            "category":"Farming",
            "subcategory":"Farm",
            "type":"Manufacturing & Wholesale Goods"
        }
    ],
    "sg:phone":"+1 519 773 2833",
    "sg:postcode":"N5H 2R4",
    "sg:province":"ON",
    "sg:tags":[
        "mushroom"
    ],
    "wof:name":"Eatmore Mushrooms Ltd",
    "wof:placetype":"venue"
},
  "geometry": {"coordinates":[-80.983627,42.773006],"type":"Point"}
}