{
  "type": "Feature",
  "properties": {
    "iso:country":"CA",
    "sg:address":"174 King St",
    "sg:city":"Truro",
    "sg:classifiers":[
        {
            "category":"Professional",
            "subcategory":"Business Services",
            "type":"Services"
        }
    ],
    "sg:phone":"+1 902 893 4700",
    "sg:postcode":"B2N 3L4",
    "sg:province":"NS",
    "sg:tags":[
        "drafting"
    ],
    "wof:name":"Babineau's Custom Home Plans",
    "wof:placetype":"venue"
},
  "geometry": {"coordinates":[-63.2843055725,45.3591156006],"type":"Point"}
}