{
  "type": "Feature",
  "properties": {
    "addr:full":"422 Rte Du Canton Brownsburg-Chatham QC J8G 1R1",
    "addr:housenumber":"422",
    "addr:postcode":"j8g 1r1",
    "addr:street":"Rte Du Canton",
    "iso:country":"CA",
    "sg:address":"422 Rte Du Canton",
    "sg:city":"Brownsburg-Chatham",
    "sg:classifiers":[
        {
            "category":"Wholesale",
            "subcategory":"Machinery & Supplies",
            "type":"Manufacturing & Wholesale Goods"
        }
    ],
    "sg:phone":"+1 450 562 2414",
    "sg:postcode":"J8G 1R1",
    "sg:province":"QC",
    "sg:tags":[
        "equipment",
        "sawmill"
    ],
    "wof:name":"Wood-Mizer Quebec",
    "wof:placetype":"venue"
},
  "geometry": {"coordinates":[-74.487869,45.629036],"type":"Point"}
}