{
  "type": "Feature",
  "properties": {
    "addr:full":"Saint-Hyacinthe QC J2S 8L1",
    "addr:postcode":"j2s 8l1",
    "iso:country":"CA",
    "sg:city":"Saint-Hyacinthe",
    "sg:classifiers":[
        {
            "category":"Manufacturing",
            "subcategory":"Food",
            "type":"Manufacturing & Wholesale Goods"
        }
    ],
    "sg:phone":"+1 450 771 7177",
    "sg:postcode":"J2S 8L1",
    "sg:province":"QC",
    "sg:tags":[
        "cocoa",
        "chocolate"
    ],
    "wof:name":"Aliments Brookside Quebec Inc",
    "wof:placetype":"venue"
},
  "geometry": {"coordinates":[-72.994308,45.628933],"type":"Point"}
}