{
  "type": "Feature",
  "properties": {
    "addr:full":"143 Wellington St Bowmanville ON L1C 1W2",
    "addr:housenumber":"143",
    "addr:postcode":"l1c 1w2",
    "addr:street":"Wellington St",
    "iso:country":"CA",
    "sg:address":"143 Wellington St",
    "sg:city":"Bowmanville",
    "sg:classifiers":[
        {
            "category":"Manufacturing",
            "subcategory":"Metals",
            "type":"Manufacturing & Wholesale Goods"
        }
    ],
    "sg:phone":"+1 905 623 3410",
    "sg:postcode":"L1C 1W2",
    "sg:province":"ON",
    "sg:tags":[
        "windows"
    ],
    "wof:name":"Bowmanville Glass",
    "wof:placetype":"venue"
},
  "geometry": {"coordinates":[-78.691574,43.914993],"type":"Point"}
}