{
  "type": "Feature",
  "properties": {
    "addr:full":"1104 Chapel Rd Canning NS B0P 1H0",
    "addr:housenumber":"1104",
    "addr:postcode":"b0p 1h0",
    "addr:street":"Chapel Rd",
    "iso:country":"CA",
    "sg:address":"1104 Chapel Rd",
    "sg:city":"Canning",
    "sg:classifiers":[
        {
            "category":"Building & Trades",
            "subcategory":"Plumbing",
            "type":"Services"
        }
    ],
    "sg:phone":"+1 902 582 7615",
    "sg:postcode":"B0P 1H0",
    "sg:province":"NS",
    "sg:tags":[
        "heating",
        "contractor"
    ],
    "wof:name":"Calvin Rogers Electrical",
    "wof:placetype":"venue"
},
  "geometry": {"coordinates":[-64.431664,45.156918],"type":"Point"}
}