{
  "type": "Feature",
  "properties": {
    "addr:full":"2012 27 Ave NW Calgary AB T2M 2J7",
    "addr:housenumber":"2012",
    "addr:postcode":"t2m 2j7",
    "addr:street":"27 Ave Nw",
    "iso:country":"CA",
    "sg:address":"2012 27 Ave NW",
    "sg:city":"Calgary",
    "sg:classifiers":[
        {
            "category":"Arts & Performance",
            "subcategory":"Theater",
            "type":"Entertainment"
        }
    ],
    "sg:phone":"+1 403 282 4695",
    "sg:postcode":"T2M 2J7",
    "sg:province":"AB",
    "sg:tags":[
        "live",
        "music"
    ],
    "wof:name":"Monarch Music Disc Jockey",
    "wof:placetype":"venue"
},
  "geometry": {"coordinates":[-114.110961914,51.0790138245],"type":"Point"}
}