{
  "type": "Feature",
  "properties": {
    "addr:full":"26 Beckwith St S Smiths Falls ON K7A 2A8",
    "addr:housenumber":"26",
    "addr:postcode":"k7a 2a8",
    "addr:street":"Beckwith St S",
    "iso:country":"CA",
    "sg:address":"26 Beckwith St S",
    "sg:city":"Smiths Falls",
    "sg:classifiers":[
        {
            "category":"Professional",
            "subcategory":"Accounting & Tax Preparation",
            "type":"Services"
        }
    ],
    "sg:phone":"+1 613 283 7385",
    "sg:postcode":"K7A 2A8",
    "sg:province":"ON",
    "sg:tags":[
        "consultant",
        "return",
        "filing"
    ],
    "wof:name":"H & R Block Canada Inc",
    "wof:placetype":"venue"
},
  "geometry": {"coordinates":[-76.02130099999999,44.89933],"type":"Point"}
}