{
  "type": "Feature",
  "properties": {
    "addr:full":"777 Bay St Toronto ON M5G 2C8",
    "addr:housenumber":"777",
    "addr:postcode":"m5g 2c8",
    "addr:street":"Bay St",
    "iso:country":"CA",
    "sg:address":"777 Bay St",
    "sg:city":"Toronto",
    "sg:classifiers":[
        {
            "category":"Health Services",
            "subcategory":"Optometrist",
            "type":"Services"
        }
    ],
    "sg:phone":"+1 416 977 4949",
    "sg:postcode":"M5G 2C8",
    "sg:province":"ON",
    "wof:name":"Winston Koo & Assoc",
    "wof:placetype":"venue"
},
  "geometry": {"coordinates":[-79.38539900000001,43.660233],"type":"Point"}
}