{
  "type": "Feature",
  "properties": {
    "addr:full":"5516 Trent Dr Prince George BC V2N 2E9",
    "addr:housenumber":"5516",
    "addr:postcode":"v2n 2e9",
    "addr:street":"Trent Dr",
    "iso:country":"CA",
    "sg:address":"5516 Trent Dr",
    "sg:city":"Prince George",
    "sg:classifiers":[
        {
            "category":"Building & Trades",
            "subcategory":"Construction",
            "type":"Services"
        }
    ],
    "sg:phone":"+1 250 964 8816",
    "sg:postcode":"V2N 2E9",
    "sg:province":"BC",
    "sg:tags":[
        "painter"
    ],
    "wof:name":"Michael's Professional Pntng",
    "wof:placetype":"venue"
},
  "geometry": {"coordinates":[-122.762787,53.870537],"type":"Point"}
}