{
  "type": "Feature",
  "properties": {
    "addr:full":"Toronto ON M4W 3E2",
    "addr:postcode":"m4w 3e2",
    "iso:country":"CA",
    "sg:city":"Toronto",
    "sg:classifiers":[
        {
            "category":"Restaurant",
            "type":"Food & Drink"
        }
    ],
    "sg:phone":"+1 416 968 2435",
    "sg:postcode":"M4W 3E2",
    "sg:province":"ON",
    "sg:tags":[
        "chicken",
        "dinner"
    ],
    "wof:name":"Texas Chicken",
    "wof:placetype":"venue"
},
  "geometry": {"coordinates":[-79.3874130249,43.6702346802],"type":"Point"}
}