{
  "type": "Feature",
  "properties": {
    "addr:full":"Burnaby BC V5H 4N2",
    "addr:postcode":"v5h 4n2",
    "iso:country":"CA",
    "sg:city":"Burnaby",
    "sg:classifiers":[
        {
            "category":"Wholesale",
            "subcategory":"Durable Goods & Equipment",
            "type":"Manufacturing & Wholesale Goods"
        }
    ],
    "sg:phone":"+1 604 431 3600",
    "sg:postcode":"V5H 4N2",
    "sg:province":"BC",
    "sg:tags":[
        "steel",
        "importer",
        "mills"
    ],
    "wof:name":"Marubeni-Itochu Steel Canada",
    "wof:placetype":"venue"
},
  "geometry": {"coordinates":[-122.99862670900001,49.2280311584],"type":"Point"}
}