{
  "type": "Feature",
  "properties": {
    "addr:full":"57117 Range Rd 241 Bon Accord AB T0A 0K0",
    "addr:housenumber":"57117",
    "addr:postcode":"t0a 0k0",
    "addr:street":"Range Rd 241",
    "iso:country":"CA",
    "sg:address":"57117 Range Rd 241",
    "sg:city":"Bon Accord",
    "sg:classifiers":[
        {
            "category":"Building & Trades",
            "subcategory":"Construction",
            "type":"Services"
        }
    ],
    "sg:phone":"+1 780 921 2220",
    "sg:postcode":"T0A 0K0",
    "sg:province":"AB",
    "sg:tags":[
        "paving",
        "contractor"
    ],
    "wof:name":"Mc Asphalt Western Ltd",
    "wof:placetype":"venue"
},
  "geometry": {"coordinates":[-113.41079711899999,53.8372764587],"type":"Point"}
}