{
  "type": "Feature",
  "properties": {
    "iso:country":"CA",
    "sg:address":"197 Rue Thornhill",
    "sg:city":"Dollard-Des-Ormeaux",
    "sg:classifiers":[
        {
            "category":"Health Services",
            "subcategory":"Nursing And Care Facility",
            "type":"Services"
        }
    ],
    "sg:phone":"+1 514 684 0173",
    "sg:postcode":"H9B 3H8",
    "sg:province":"QC",
    "sg:tags":[
        "home",
        "rest"
    ],
    "wof:name":"Centre D'Accueil Dollard Inc",
    "wof:placetype":"venue"
},
  "geometry": {"coordinates":[-73.816513,45.479523],"type":"Point"}
}