{
  "type": "Feature",
  "properties": {
    "addr:full":"3905 Chesswood Dr North York ON M3J 2R8",
    "addr:housenumber":"3905",
    "addr:postcode":"m3j 2r8",
    "addr:street":"Chesswood Dr",
    "iso:country":"CA",
    "sg:address":"3905 Chesswood Dr",
    "sg:city":"North York",
    "sg:classifiers":[
        {
            "category":"Wholesale",
            "subcategory":"Meat",
            "type":"Manufacturing & Wholesale Goods"
        }
    ],
    "sg:phone":"+1 416 636 6143",
    "sg:postcode":"M3J 2R8",
    "sg:province":"ON",
    "sg:tags":[
        "butchering"
    ],
    "wof:name":"Arax Meat Products",
    "wof:placetype":"venue"
},
  "geometry": {"coordinates":[-79.475571,43.757893],"type":"Point"}
}