{
  "type": "Feature",
  "properties": {
    "iso:country":"CA",
    "sg:address":"38 Gotha St",
    "sg:city":"Trenton",
    "sg:classifiers":[
        {
            "category":"Shopping",
            "subcategory":"Hobbies, Toys, & Games",
            "type":"Retail Goods"
        }
    ],
    "sg:phone":"+1 613 394 2697",
    "sg:postcode":"K8V 6E1",
    "sg:province":"ON",
    "sg:tags":[
        "product",
        "ceramic"
    ],
    "wof:name":"Looney Ceramics",
    "wof:placetype":"venue"
},
  "geometry": {"coordinates":[-77.587272644,44.1062583923],"type":"Point"}
}