{
  "type": "Feature",
  "properties": {
    "addr:full":"719 33 St NW Calgary AB T2N 2W7",
    "addr:housenumber":"33",
    "addr:postcode":"t2n 2w7",
    "addr:street":"719;St Nw",
    "iso:country":"CA",
    "sg:address":"719 33 St NW",
    "sg:city":"Calgary",
    "sg:classifiers":[
        {
            "category":"Freight",
            "type":"Transportation"
        }
    ],
    "sg:phone":"+1 403 283 6471",
    "sg:postcode":"T2N 2W7",
    "sg:province":"AB",
    "sg:tags":[
        "courier"
    ],
    "wof:name":"Mile Post Messenger & Courier",
    "wof:placetype":"venue"
},
  "geometry": {"coordinates":[-114.13308000000001,51.059196],"type":"Point"}
}