{
  "type": "Feature",
  "properties": {
    "addr:full":"1934 Wildflower Dr Pickering ON L1V 7B1",
    "addr:housenumber":"1934",
    "addr:postcode":"l1v 7b1",
    "addr:street":"Wildflower Dr",
    "iso:country":"CA",
    "sg:address":"1934 Wildflower Dr",
    "sg:city":"Pickering",
    "sg:classifiers":[
        {
            "category":"Building & Trades",
            "subcategory":"Electrical",
            "type":"Services"
        }
    ],
    "sg:phone":"+1 905 837 8889",
    "sg:postcode":"L1V 7B1",
    "sg:province":"ON",
    "sg:tags":[
        "electric",
        "contractor"
    ],
    "wof:name":"Albright Electric CO",
    "wof:placetype":"venue"
},
  "geometry": {"coordinates":[-79.133987,43.833019],"type":"Point"}
}