{
  "type": "Feature",
  "properties": {
    "addr:full":"1859 Harvey Ave Kelowna BC V1Y 6G4",
    "addr:housenumber":"1859",
    "addr:postcode":"v1y 6g4",
    "addr:street":"Harvey Ave",
    "iso:country":"CA",
    "sg:address":"1859 Harvey Ave",
    "sg:city":"Kelowna",
    "sg:classifiers":[
        {
            "category":"Real Estate",
            "subcategory":"Real Estate Agent",
            "type":"Services"
        }
    ],
    "sg:phone":"+1 250 860 7330",
    "sg:postcode":"V1Y 6G4",
    "sg:province":"BC",
    "sg:tags":[
        "management"
    ],
    "wof:name":"Gold Key Management",
    "wof:placetype":"venue"
},
  "geometry": {"coordinates":[-119.45565795900001,49.8818397522],"type":"Point"}
}