{
  "type": "Feature",
  "properties": {
    "addr:full":"22 Highway 20 W Fonthill ON L0S 1E0",
    "addr:housenumber":"22",
    "addr:postcode":"l0s 1e0",
    "addr:street":"Highway 20 W Fonthill",
    "iso:country":"CA",
    "sg:address":"22 Highway 20 W",
    "sg:city":"Fonthill",
    "sg:classifiers":[
        {
            "category":"Manufacturing",
            "subcategory":"Printing",
            "type":"Manufacturing & Wholesale Goods"
        }
    ],
    "sg:phone":"+1 905 892 6544",
    "sg:postcode":"L0S 1E0",
    "sg:province":"ON",
    "sg:tags":[
        "printer"
    ],
    "wof:name":"Pelham Printing & Promotions",
    "wof:placetype":"venue"
},
  "geometry": {"coordinates":[-79.2818222046,43.0440979004],"type":"Point"}
}