{
  "type": "Feature",
  "properties": {
    "iso:country":"CA",
    "sg:address":"212 Fifth Ave W",
    "sg:city":"Qualicum Beach",
    "sg:classifiers":[
        {
            "category":"Professional",
            "subcategory":"Accounting & Tax Preparation",
            "type":"Services"
        }
    ],
    "sg:phone":"+1 250 752 2976",
    "sg:postcode":"V9K 1S2",
    "sg:province":"BC",
    "sg:tags":[
        "accountant"
    ],
    "wof:name":"Higgins, Doug CA",
    "wof:placetype":"venue"
},
  "geometry": {"coordinates":[-124.44751739500001,49.3441085815],"type":"Point"}
}