{
  "type": "Feature",
  "properties": {
    "iso:country":"CA",
    "sg:address":"2430 Dougall Ave",
    "sg:city":"Windsor",
    "sg:classifiers":[
        {
            "category":"Recreation",
            "type":"Entertainment"
        }
    ],
    "sg:phone":"+1 519 972 7824",
    "sg:postcode":"N8X 1T2",
    "sg:province":"ON",
    "sg:tags":[
        "lottery",
        "agent"
    ],
    "wof:name":"Cnib Corner Store",
    "wof:placetype":"venue"
},
  "geometry": {"coordinates":[-83.0231246948,42.2875747681],"type":"Point"}
}