{
  "type": "Feature",
  "properties": {
    "addr:full":"2933 Gunn Rd Prince George BC V2N 2H8",
    "addr:housenumber":"2933",
    "addr:postcode":"v2n 2h8",
    "addr:street":"Gunn Rd",
    "iso:country":"CA",
    "sg:address":"2933 Gunn Rd",
    "sg:city":"Prince George",
    "sg:classifiers":[
        {
            "category":"Retail",
            "subcategory":"Veterinary Services",
            "type":"Services"
        }
    ],
    "sg:phone":"+1 250 963 9898",
    "sg:postcode":"V2N 2H8",
    "sg:province":"BC",
    "sg:tags":[
        "veterinarian"
    ],
    "wof:name":"Murdoch Veterinary Svc",
    "wof:placetype":"venue"
},
  "geometry": {"coordinates":[-122.67952699999999,53.902107],"type":"Point"}
}