{
  "type": "Feature",
  "properties": {
    "addr:full":"4913 49 St Wetaskiwin AB T9A 1H5",
    "addr:housenumber":"4913",
    "addr:postcode":"t9a 1h5",
    "addr:street":"49 St",
    "iso:country":"CA",
    "sg:address":"4913 49 St",
    "sg:city":"Wetaskiwin",
    "sg:classifiers":[
        {
            "category":"Retail",
            "subcategory":"Repair Shop",
            "type":"Services"
        }
    ],
    "sg:phone":"+1 780 352 4656",
    "sg:postcode":"T9A 1H5",
    "sg:province":"AB",
    "sg:tags":[
        "upholsterer",
        "furniture"
    ],
    "wof:name":"Geurtsen Upholstery & Drapes",
    "wof:placetype":"venue"
},
  "geometry": {"coordinates":[-113.372459412,52.9687309265],"type":"Point"}
}