{
  "type": "Feature",
  "properties": {
    "iso:country":"CA",
    "sg:address":"777 Guelph Line",
    "sg:city":"Burlington",
    "sg:classifiers":[
        {
            "category":"Shopping",
            "subcategory":"Gifts & Souvenirs",
            "type":"Retail Goods"
        }
    ],
    "sg:phone":"+1 905 631 7780",
    "sg:postcode":"L7R 3N2",
    "sg:province":"ON",
    "sg:tags":[
        "shop"
    ],
    "wof:name":"Green Earth",
    "wof:placetype":"venue"
},
  "geometry": {"coordinates":[-79.796143,43.346584],"type":"Point"}
}