{
  "type": "Feature",
  "properties": {
    "addr:full":"200 Nelson St Monkton ON N0K 1P0",
    "addr:housenumber":"200",
    "addr:postcode":"n0k 1p0",
    "addr:street":"Nelson St",
    "iso:country":"CA",
    "sg:address":"200 Nelson St",
    "sg:city":"Monkton",
    "sg:classifiers":[
        {
            "category":"Recreation",
            "type":"Entertainment"
        }
    ],
    "sg:phone":"+1 519 347 2650",
    "sg:postcode":"N0K 1P0",
    "sg:province":"ON",
    "sg:tags":[
        "government",
        "hall",
        "auditorium"
    ],
    "wof:name":"Monkton Community Ctr",
    "wof:placetype":"venue"
},
  "geometry": {"coordinates":[-81.08176400000001,43.587383],"type":"Point"}
}