{
  "type": "Feature",
  "properties": {
    "iso:country":"CA",
    "sg:city":"Coldbrook",
    "sg:classifiers":[
        {
            "category":"Retail",
            "subcategory":"Auto Repair",
            "type":"Services"
        }
    ],
    "sg:phone":"+1 902 679 6637",
    "sg:postcode":"B4R 1B6",
    "sg:province":"NS",
    "sg:tags":[
        "repairing",
        "automobile"
    ],
    "wof:name":"Taylor's Family Mechanical",
    "wof:placetype":"venue"
},
  "geometry": {"coordinates":[-64.57695,45.06683],"type":"Point"}
}