{
  "type": "Feature",
  "properties": {
    "addr:full":"468 James St Delhi ON N4B 2C3",
    "addr:housenumber":"468",
    "addr:postcode":"n4b 2c3",
    "addr:street":"James St",
    "iso:country":"CA",
    "sg:address":"468 James St",
    "sg:city":"Delhi",
    "sg:classifiers":[
        {
            "category":"Shopping",
            "subcategory":"Discount & Variety Stores",
            "type":"Retail Goods"
        }
    ],
    "sg:phone":"+1 519 582 1820",
    "sg:postcode":"N4B 2C3",
    "sg:province":"ON",
    "wof:name":"Dave's Variety",
    "wof:placetype":"venue"
},
  "geometry": {"coordinates":[-80.4918518066,42.8492126465],"type":"Point"}
}