{
  "type": "Feature",
  "properties": {
    "addr:full":"Scarborough ON M1M 1T9",
    "addr:postcode":"m1m 1t9",
    "iso:country":"CA",
    "sg:city":"Scarborough",
    "sg:classifiers":[
        {
            "category":"Building & Trades",
            "subcategory":"Construction",
            "type":"Services"
        }
    ],
    "sg:phone":"+1 416 267 1854",
    "sg:postcode":"M1M 1T9",
    "sg:province":"ON",
    "sg:tags":[
        "roofing",
        "contractor"
    ],
    "wof:name":"Kingston Road Roofing",
    "wof:placetype":"venue"
},
  "geometry": {"coordinates":[-79.24250000000001,43.720772],"type":"Point"}
}