{
  "type": "Feature",
  "properties": {
    "addr:full":"53 Rue Cate Sherbrooke QC J1J 2N9",
    "addr:housenumber":"53",
    "addr:postcode":"j1j 2n9",
    "addr:street":"Rue Cate",
    "iso:country":"CA",
    "sg:address":"53 Rue Cate",
    "sg:city":"Sherbrooke",
    "sg:classifiers":[
        {
            "category":"Professional",
            "subcategory":"Business Services",
            "type":"Services"
        }
    ],
    "sg:phone":"+1 819 565 9688",
    "sg:postcode":"J1J 2N9",
    "sg:province":"QC",
    "sg:tags":[
        "water",
        "treatment"
    ],
    "wof:name":"Atlas",
    "wof:placetype":"venue"
},
  "geometry": {"coordinates":[-71.931763,45.399338],"type":"Point"}
}