{
  "type": "Feature",
  "properties": {
    "iso:country":"CA",
    "sg:address":"767 Bank St",
    "sg:city":"Ottawa",
    "sg:classifiers":[
        {
            "category":"Building & Trades",
            "subcategory":"Construction",
            "type":"Services"
        }
    ],
    "sg:phone":"+1 613 232 5341",
    "sg:postcode":"K1S 3V3",
    "sg:province":"ON",
    "sg:tags":[
        "tile",
        "dealer"
    ],
    "wof:name":"World Mosaic Ottawa Inc",
    "wof:placetype":"venue"
},
  "geometry": {"coordinates":[-75.68869,45.403893],"type":"Point"}
}