{
  "type": "Feature",
  "properties": {
    "addr:full":"115 Barnesdale Ave N Hamilton ON L8L 6S6",
    "addr:housenumber":"115",
    "addr:postcode":"l8l 6s6",
    "addr:street":"Barnesdale Ave N",
    "iso:country":"CA",
    "sg:address":"115 Barnesdale Ave N",
    "sg:city":"Hamilton",
    "sg:classifiers":[
        {
            "category":"Education",
            "subcategory":"School",
            "type":"Public Place"
        }
    ],
    "sg:phone":"+1 905 545 1832",
    "sg:postcode":"L8L 6S6",
    "sg:province":"ON",
    "wof:name":"Holy Spirit School",
    "wof:placetype":"venue"
},
  "geometry": {"coordinates":[-79.833557,43.255371],"type":"Point"}
}