{
  "type": "Feature",
  "properties": {
    "addr:full":"823 Rue Saint-Clement Mercier QC J6R 1J3",
    "addr:housenumber":"823",
    "addr:postcode":"j6r 1j3",
    "addr:street":"Rue Saint-Clement",
    "iso:country":"CA",
    "sg:address":"823 Rue Saint-Clement",
    "sg:city":"Mercier",
    "sg:classifiers":[
        {
            "category":"Recreation",
            "type":"Entertainment"
        }
    ],
    "sg:phone":"+1 450 691 9219",
    "sg:postcode":"J6R 1J3",
    "sg:province":"QC",
    "sg:tags":[
        "instruction",
        "swimming"
    ],
    "wof:name":"Centre DE Natation Mercier",
    "wof:placetype":"venue"
},
  "geometry": {"coordinates":[-73.7392578125,45.3114852905],"type":"Point"}
}