{
  "type": "Feature",
  "properties": {
    "addr:full":"2505 Victoria Ave Brandon MB R7B 0M6",
    "addr:housenumber":"2505",
    "addr:postcode":"r7b 0m6",
    "addr:street":"Victoria Ave",
    "iso:country":"CA",
    "sg:address":"2505 Victoria Ave",
    "sg:city":"Brandon",
    "sg:classifiers":[
        {
            "category":"Wholesale",
            "subcategory":"Non-durable Goods",
            "type":"Manufacturing & Wholesale Goods"
        }
    ],
    "sg:phone":"+1 204 728 3330",
    "sg:postcode":"R7B 0M6",
    "sg:province":"MB",
    "sg:tags":[
        "organization",
        "political"
    ],
    "wof:name":"Summit Stitchwear & Promotions",
    "wof:placetype":"venue"
},
  "geometry": {"coordinates":[-99.97235870359999,49.8425598145],"type":"Point"}
}