{
  "type": "Feature",
  "properties": {
    "addr:full":"11 Mill St Orangeville ON L9W 2M2",
    "addr:housenumber":"11",
    "addr:postcode":"l9w 2m2",
    "addr:street":"Mill St",
    "iso:country":"CA",
    "sg:address":"11 Mill St",
    "sg:city":"Orangeville",
    "sg:classifiers":[
        {
            "category":"Insurance",
            "subcategory":"Insurance Agent",
            "type":"Services"
        }
    ],
    "sg:phone":"+1 519 941 1500",
    "sg:postcode":"L9W 2M2",
    "sg:province":"ON",
    "wof:name":"Hogan, Susan",
    "wof:placetype":"venue"
},
  "geometry": {"coordinates":[-80.09577178959999,43.9191436768],"type":"Point"}
}