{
  "type": "Feature",
  "properties": {
    "addr:full":"Salmon Arm BC V1E 1B6",
    "addr:postcode":"v1e 1b6",
    "iso:country":"CA",
    "sg:city":"Salmon Arm",
    "sg:classifiers":[
        {
            "category":"Shopping",
            "subcategory":"Clothing, Apparel, & Fashions",
            "type":"Retail Goods"
        }
    ],
    "sg:phone":"+1 250 832 2218",
    "sg:postcode":"V1E 1B6",
    "sg:province":"BC",
    "wof:name":"Suzanne's",
    "wof:placetype":"venue"
},
  "geometry": {"coordinates":[-119.28997,50.699497],"type":"Point"}
}