{
  "type": "Feature",
  "properties": {
    "addr:full":"208 Rue Saint-Hubert Laval QC H7G 2Y4",
    "addr:housenumber":"208",
    "addr:postcode":"qc h7g 2y4",
    "addr:street":"Rue Saint-Hubert",
    "iso:country":"CA",
    "sg:address":"208 Rue Saint-Hubert",
    "sg:city":"Laval",
    "sg:classifiers":[
        {
            "category":"Building & Trades",
            "subcategory":"Construction",
            "type":"Services"
        }
    ],
    "sg:phone":"+1 450 967 7315",
    "sg:postcode":"H7G 2Y4",
    "sg:province":"QC",
    "sg:tags":[
        "repairing",
        "remodeling",
        "contractor"
    ],
    "wof:name":"Hpm Aluminium Inc",
    "wof:placetype":"venue"
},
  "geometry": {"coordinates":[-73.6841125488,45.5646476746],"type":"Point"}
}