{
  "type": "Feature",
  "properties": {
    "iso:country":"CA",
    "sg:address":"35954 Cabot Trl",
    "sg:city":"Ingonish",
    "sg:classifiers":[
        {
            "category":"Building & Trades",
            "subcategory":"Construction",
            "type":"Services"
        }
    ],
    "sg:phone":"+1 902 285 2221",
    "sg:postcode":"B0C 1K0",
    "sg:province":"NS",
    "sg:tags":[
        "general",
        "contractor"
    ],
    "wof:name":"Ingonish Contracting Ltd",
    "wof:placetype":"venue"
},
  "geometry": {"coordinates":[-60.362651825,46.6918373108],"type":"Point"}
}