{
  "type": "Feature",
  "properties": {
    "addr:full":"745 Sackville Dr Lower Sackville NS B4E 2R2",
    "addr:housenumber":"745",
    "addr:postcode":"b4e 2r2",
    "addr:street":"Sackville Dr",
    "iso:country":"CA",
    "sg:address":"745 Sackville Dr",
    "sg:city":"Lower Sackville",
    "sg:classifiers":[
        {
            "category":"Retail",
            "subcategory":"Laundry & Dry Cleaning",
            "type":"Services"
        }
    ],
    "sg:phone":"+1 902 865 2292",
    "sg:postcode":"B4E 2R2",
    "sg:province":"NS",
    "sg:tags":[
        "cleaners"
    ],
    "wof:name":"Drycleaners",
    "wof:placetype":"venue"
},
  "geometry": {"coordinates":[-63.691814,44.772835],"type":"Point"}
}