{
  "type": "Feature",
  "properties": {
    "addr:full":"188 Mcleod Ave Quesnel BC V2J 3J2",
    "addr:housenumber":"188",
    "addr:postcode":"v2j 3j2",
    "addr:street":"Mcleod Ave",
    "iso:country":"CA",
    "sg:address":"188 Mcleod Ave",
    "sg:city":"Quesnel",
    "sg:classifiers":[
        {
            "category":"Manufacturing",
            "subcategory":"Paper Products",
            "type":"Manufacturing & Wholesale Goods"
        }
    ],
    "sg:phone":"+1 250 992 5431",
    "sg:postcode":"V2J 3J2",
    "sg:province":"BC",
    "sg:tags":[
        "pulp"
    ],
    "wof:name":"Blue Chipwood Products Ltd",
    "wof:placetype":"venue"
},
  "geometry": {"coordinates":[-122.50559199999999,52.998802],"type":"Point"}
}