{
  "type": "Feature",
  "properties": {
    "addr:full":"811 Wharf St Victoria BC V8W 1T2",
    "addr:housenumber":"811",
    "addr:postcode":"v8w 1t2",
    "addr:street":"Wharf St",
    "iso:country":"CA",
    "sg:address":"811 Wharf St",
    "sg:city":"Victoria",
    "sg:classifiers":[
        {
            "category":"Recreation",
            "type":"Entertainment"
        }
    ],
    "sg:phone":"+1 250 386 2277",
    "sg:postcode":"V8W 1T2",
    "sg:province":"BC",
    "sg:tags":[
        "whale",
        "charter",
        "watching"
    ],
    "wof:name":"Great Pacific Adventures Inc",
    "wof:placetype":"venue"
},
  "geometry": {"coordinates":[-123.36869812,48.4229812622],"type":"Point"}
}