{
  "type": "Feature",
  "properties": {
    "iso:country":"CA",
    "sg:address":"7 Swan St",
    "sg:city":"Port Dover",
    "sg:classifiers":[
        {
            "category":"Government",
            "subcategory":"Office",
            "type":"Public Place"
        }
    ],
    "sg:phone":"+1 519 583 1756",
    "sg:postcode":"N0A 1N6",
    "sg:province":"ON",
    "sg:tags":[
        "organization",
        "protection",
        "animal"
    ],
    "wof:name":"Fur & Feather Wildlife Ctr",
    "wof:placetype":"venue"
},
  "geometry": {"coordinates":[-80.1965789795,42.7939186096],"type":"Point"}
}