{
  "type": "Feature",
  "properties": {
    "iso:country":"CA",
    "sg:city":"Waterloo",
    "sg:classifiers":[
        {
            "category":"Wholesale",
            "subcategory":"Electrical",
            "type":"Manufacturing & Wholesale Goods"
        }
    ],
    "sg:phone":"+1 519 576 0956",
    "sg:postcode":"N2J 2J9",
    "sg:province":"ON",
    "sg:tags":[
        "fire",
        "alarm",
        "system"
    ],
    "wof:name":"Twin City Fire Alarm Systems",
    "wof:placetype":"venue"
},
  "geometry": {"coordinates":[-80.497292,43.472832],"type":"Point"}
}