{
  "type": "Feature",
  "properties": {
    "addr:full":"North York ON M3L 1A2",
    "addr:postcode":"m3l 1a2",
    "iso:country":"CA",
    "sg:city":"North York",
    "sg:classifiers":[
        {
            "category":"Food & Beverages",
            "subcategory":"Bakery",
            "type":"Retail Goods"
        }
    ],
    "sg:phone":"+1 416 243 5242",
    "sg:postcode":"M3L 1A2",
    "sg:province":"ON",
    "sg:tags":[
        "caterer"
    ],
    "wof:name":"Beverly Hills Bakery",
    "wof:placetype":"venue"
},
  "geometry": {"coordinates":[-79.513283,43.717743],"type":"Point"}
}