{
  "type": "Feature",
  "properties": {
    "addr:full":"3203 Port LA Tour Rd Barrington NS B0W 1E0",
    "addr:housenumber":"3203",
    "addr:postcode":"b0w 1e0",
    "addr:street":"Port La Tour Rd",
    "iso:country":"CA",
    "sg:address":"3203 Port LA Tour Rd",
    "sg:city":"Barrington",
    "sg:classifiers":[
        {
            "category":"Manufacturing",
            "subcategory":"Food",
            "type":"Manufacturing & Wholesale Goods"
        }
    ],
    "sg:phone":"+1 902 768 2550",
    "sg:postcode":"B0W 1E0",
    "sg:province":"NS",
    "sg:tags":[
        "packer",
        "fish"
    ],
    "wof:name":"Cape Breeze Seafoods Ltd",
    "wof:placetype":"venue"
},
  "geometry": {"coordinates":[-65.474358,43.496208],"type":"Point"}
}