{
  "type": "Feature",
  "properties": {
    "iso:country":"CA",
    "sg:address":"3132 Eglinton Ave E",
    "sg:city":"Scarborough",
    "sg:classifiers":[
        {
            "category":"Autos & Motor Vehicles",
            "subcategory":"Automobile Sales",
            "type":"Retail Goods"
        }
    ],
    "sg:phone":"+1 416 264 2311",
    "sg:postcode":"M1J 2H1",
    "sg:province":"ON",
    "sg:tags":[
        "car",
        "dealer"
    ],
    "wof:name":"Marvin Starr Pontiac Buick Cad",
    "wof:placetype":"venue"
},
  "geometry": {"coordinates":[-79.2243270874,43.742149353],"type":"Point"}
}