{
  "type": "Feature",
  "properties": {
    "addr:full":"53 Stone Church Rd W Hamilton ON L9B 1A1",
    "addr:housenumber":"53",
    "addr:postcode":"l9b 1a1",
    "addr:street":"Stone Church Rd W",
    "iso:country":"CA",
    "sg:address":"53 Stone Church Rd W",
    "sg:city":"Hamilton",
    "sg:classifiers":[
        {
            "category":"Wholesale",
            "subcategory":"Sporting Goods",
            "type":"Manufacturing & Wholesale Goods"
        }
    ],
    "sg:phone":"+1 905 387 9921",
    "sg:postcode":"L9B 1A1",
    "sg:province":"ON",
    "sg:tags":[
        "refrigerating",
        "system",
        "air",
        "equipment",
        "conditioning",
        "contractor",
        "pool",
        "swimming"
    ],
    "wof:name":"Ancaster Mechanical Ltd",
    "wof:placetype":"venue"
},
  "geometry": {"coordinates":[-79.8919296265,43.2116622925],"type":"Point"}
}