{
  "type": "Feature",
  "properties": {
    "iso:country":"CA",
    "sg:address":"2554 Confederation Pky",
    "sg:city":"Mississauga",
    "sg:classifiers":[
        {
            "category":"Health Services",
            "subcategory":"Optometrist",
            "type":"Services"
        }
    ],
    "sg:phone":"+1 905 897 1856",
    "sg:postcode":"L5B 1S2",
    "sg:province":"ON",
    "wof:name":"Kathleen Breen & Assoc",
    "wof:placetype":"venue"
},
  "geometry": {"coordinates":[-79.61732499999999,43.576046],"type":"Point"}
}