{
  "type": "Feature",
  "properties": {
    "addr:full":"2550 Rue Saint-Pierre Drummondville QC J2C 7Y3",
    "addr:housenumber":"2550",
    "addr:postcode":"j2c 7y3",
    "addr:street":"Rue Saint-Pierre",
    "iso:country":"CA",
    "sg:address":"2550 Rue Saint-Pierre",
    "sg:city":"Drummondville",
    "sg:classifiers":[
        {
            "category":"Home & Garden",
            "subcategory":"Building Materials",
            "type":"Retail Goods"
        }
    ],
    "sg:phone":"+1 819 477 4141",
    "sg:postcode":"J2C 7Y3",
    "sg:province":"QC",
    "sg:tags":[
        "windows",
        "door"
    ],
    "wof:name":"Portes & Fenetres Lariviere",
    "wof:placetype":"venue"
},
  "geometry": {"coordinates":[-72.522278,45.867062],"type":"Point"}
}