{
  "type": "Feature",
  "properties": {
    "iso:country":"CA",
    "sg:city":"Montreal",
    "sg:classifiers":[
        {
            "category":"Building & Trades",
            "subcategory":"Construction",
            "type":"Services"
        }
    ],
    "sg:phone":"+1 514 722 3174",
    "sg:postcode":"H1T 3J9",
    "sg:province":"QC",
    "sg:tags":[
        "repairing",
        "refinishing",
        "floor",
        "laying",
        "contractor",
        "resurfacing",
        "remodeling"
    ],
    "wof:name":"P L Planchers Enr",
    "wof:placetype":"venue"
},
  "geometry": {"coordinates":[-73.579872,45.566479],"type":"Point"}
}