{
  "type": "Feature",
  "properties": {
    "addr:full":"787 Srigley St Newmarket ON L3Y 1X8",
    "addr:housenumber":"787",
    "addr:postcode":"l3y 1x8",
    "addr:street":"Srigley St",
    "iso:country":"CA",
    "sg:address":"787 Srigley St",
    "sg:city":"Newmarket",
    "sg:classifiers":[
        {
            "category":"Local Transit",
            "type":"Transportation"
        }
    ],
    "sg:phone":"+1 905 898 5466",
    "sg:postcode":"L3Y 1X8",
    "sg:province":"ON",
    "sg:tags":[
        "limousine"
    ],
    "wof:name":"Legge Limousine Svc",
    "wof:placetype":"venue"
},
  "geometry": {"coordinates":[-79.443748,44.0574],"type":"Point"}
}