{
  "type": "Feature",
  "properties": {
    "iso:country":"CA",
    "sg:city":"Arran",
    "sg:classifiers":[
        {
            "category":"Recreation",
            "type":"Entertainment"
        }
    ],
    "sg:phone":"+1 306 595 4441",
    "sg:postcode":"S0A 0B0",
    "sg:province":"SK",
    "sg:tags":[
        "club",
        "curling"
    ],
    "wof:name":"Arran Curling Club",
    "wof:placetype":"venue"
},
  "geometry": {"coordinates":[-101.71866607699999,51.885848999],"type":"Point"}
}