{
  "type": "Feature",
  "properties": {
    "addr:full":"1165 Rang Du Petit-Saint-Espri Saint-Jean-Baptiste-DE-Nicolet QC J3T 1L8",
    "addr:housenumber":"1165",
    "addr:postcode":"j3t 1l8",
    "addr:street":"Rang Du Petit-Saint-Espri Saint-Jean-Baptiste-De-Nicolet",
    "iso:country":"CA",
    "sg:address":"1165 Rang Du Petit-Saint-Espri",
    "sg:city":"Saint-Jean-Baptiste-DE-Nicolet",
    "sg:classifiers":[
        {
            "category":"Retail",
            "subcategory":"Auto Repair",
            "type":"Services"
        }
    ],
    "sg:phone":"+1 819 293 8666",
    "sg:postcode":"J3T 1L8",
    "sg:province":"QC",
    "sg:tags":[
        "body",
        "automobile",
        "painting"
    ],
    "wof:name":"Pro Color Prestige",
    "wof:placetype":"venue"
},
  "geometry": {"coordinates":[-72.616027832,46.2285499573],"type":"Point"}
}