{
  "type": "Feature",
  "properties": {
    "addr:full":"Calgary AB T2G 0V9",
    "addr:postcode":"t2g 0v9",
    "iso:country":"CA",
    "sg:city":"Calgary",
    "sg:classifiers":[
        {
            "category":"Building & Trades",
            "subcategory":"Landscaping Services",
            "type":"Services"
        }
    ],
    "sg:phone":"+1 403 264 4433",
    "sg:postcode":"T2G 0V9",
    "sg:province":"AB",
    "sg:tags":[
        "planning",
        "designer",
        "park",
        "landscape"
    ],
    "wof:name":"Lombard North Group Ltd",
    "wof:placetype":"venue"
},
  "geometry": {"coordinates":[-114.05973053,51.0430717468],"type":"Point"}
}