{
  "type": "Feature",
  "properties": {
    "addr:full":"10300 Av Du Bois-DE-Boulogne Montreal QC H4N 1L1",
    "addr:housenumber":"10300",
    "addr:postcode":"h4n 1l1",
    "addr:street":"Av Du Bois-De-Boulogne",
    "iso:country":"CA",
    "sg:address":"10300 Av Du Bois-DE-Boulogne",
    "sg:city":"Montreal",
    "sg:classifiers":[
        {
            "category":"Food & Beverages",
            "subcategory":"Groceries & Convenience Stores",
            "type":"Retail Goods"
        }
    ],
    "sg:phone":"+1 514 337 1059",
    "sg:postcode":"H4N 1L1",
    "sg:province":"QC",
    "wof:name":"Depanneur Bois DE Boulogne",
    "wof:placetype":"venue"
},
  "geometry": {"coordinates":[-73.6729507446,45.5374298096],"type":"Point"}
}