{
  "type": "Feature",
  "properties": {
    "iso:country":"CA",
    "sg:address":"626 Queen St E",
    "sg:city":"Sault Ste Marie",
    "sg:classifiers":[
        {
            "category":"Personal",
            "type":"Services"
        }
    ],
    "sg:phone":"+1 705 256 8989",
    "sg:postcode":"P6A 2A4",
    "sg:province":"ON",
    "sg:tags":[
        "control",
        "weight",
        "program",
        "fitness",
        "exercise",
        "physical"
    ],
    "wof:name":"Curves For Women",
    "wof:placetype":"venue"
},
  "geometry": {"coordinates":[-84.3291091919,46.5088195801],"type":"Point"}
}