{
  "type": "Feature",
  "properties": {
    "addr:full":"218 Lauzon Rd Windsor ON N8S 3L6",
    "addr:housenumber":"218",
    "addr:postcode":"n8s 3l6",
    "addr:street":"Lauzon Rd",
    "iso:country":"CA",
    "sg:address":"218 Lauzon Rd",
    "sg:city":"Windsor",
    "sg:classifiers":[
        {
            "category":"Retail",
            "subcategory":"Laundry & Dry Cleaning",
            "type":"Services"
        }
    ],
    "sg:phone":"+1 519 948 0435",
    "sg:postcode":"N8S 3L6",
    "sg:province":"ON",
    "sg:tags":[
        "cleaners"
    ],
    "wof:name":"Blondie Cleaners Ltd",
    "wof:placetype":"venue"
},
  "geometry": {"coordinates":[-82.947593689,42.339756012],"type":"Point"}
}