{
  "type": "Feature",
  "properties": {
    "addr:full":"23 Rue Du Parc Adstock QC G0N 1S0",
    "addr:housenumber":"23",
    "addr:postcode":"g0n 1s0",
    "addr:street":"Rue Du Parc",
    "iso:country":"CA",
    "sg:address":"23 Rue Du Parc",
    "sg:city":"Adstock",
    "sg:classifiers":[
        {
            "category":"Education",
            "subcategory":"School",
            "type":"Public Place"
        }
    ],
    "sg:phone":"+1 418 422 2431",
    "sg:postcode":"G0N 1S0",
    "sg:province":"QC",
    "wof:name":"Ecole Aux Quatre-Vents",
    "wof:placetype":"venue"
},
  "geometry": {"coordinates":[-71.078896,46.046791],"type":"Point"}
}