{
  "type": "Feature",
  "properties": {
    "addr:full":"1 Yonge St Toronto ON M5E 1E5",
    "addr:housenumber":"1",
    "addr:postcode":"m5e 1e5",
    "addr:street":"Yonge St",
    "iso:country":"CA",
    "sg:address":"1 Yonge St",
    "sg:city":"Toronto",
    "sg:classifiers":[
        {
            "category":"Professional",
            "subcategory":"Computer Services",
            "type":"Services"
        }
    ],
    "sg:phone":"+1 416 203 3676",
    "sg:postcode":"M5E 1E5",
    "sg:province":"ON",
    "sg:tags":[
        "internet"
    ],
    "wof:name":"Certainty Solutions Canada Inc",
    "wof:placetype":"venue"
},
  "geometry": {"coordinates":[-79.37457999999999,43.642052],"type":"Point"}
}