{
  "type": "Feature",
  "properties": {
    "addr:full":"9 Well Head St Devon AB T9G 1Z6",
    "addr:housenumber":"9",
    "addr:postcode":"t9g 1z6",
    "addr:street":"Well Head St",
    "iso:country":"CA",
    "sg:address":"9 Well Head St",
    "sg:city":"Devon",
    "sg:classifiers":[
        {
            "category":"Freight",
            "type":"Transportation"
        }
    ],
    "sg:phone":"+1 780 987 5151",
    "sg:postcode":"T9G 1Z6",
    "sg:province":"AB",
    "sg:tags":[
        "field",
        "oil"
    ],
    "wof:name":"Great Dane Trucking Ltd",
    "wof:placetype":"venue"
},
  "geometry": {"coordinates":[-113.730293,53.343155],"type":"Point"}
}