{
  "type": "Feature",
  "properties": {
    "addr:full":"6323 10 Ave NW Edmonton AB T6L 3A4",
    "addr:housenumber":"6323",
    "addr:postcode":"t6l 3a4",
    "addr:street":"10 Ave Nw",
    "iso:country":"CA",
    "sg:address":"6323 10 Ave NW",
    "sg:city":"Edmonton",
    "sg:classifiers":[
        {
            "category":"Manufacturing",
            "subcategory":"Apparel",
            "type":"Manufacturing & Wholesale Goods"
        }
    ],
    "sg:phone":"+1 780 466 6010",
    "sg:postcode":"T6L 3A4",
    "sg:province":"AB",
    "sg:tags":[
        "uniform"
    ],
    "wof:name":"Louis Hebert Uniform",
    "wof:placetype":"venue"
},
  "geometry": {"coordinates":[-113.43461600000001,53.438251],"type":"Point"}
}