{
  "type": "Feature",
  "properties": {
    "addr:full":"10005 Telkwa Coalmine Rd Telkwa BC V0J 2X3",
    "addr:housenumber":"10005",
    "addr:postcode":"v0j 2x3",
    "addr:street":"Telkwa Coalmine Rd",
    "iso:country":"CA",
    "sg:address":"10005 Telkwa Coalmine Rd",
    "sg:city":"Telkwa",
    "sg:classifiers":[
        {
            "category":"Building & Trades",
            "subcategory":"Construction",
            "type":"Services"
        }
    ],
    "sg:phone":"+1 250 846 5661",
    "sg:postcode":"V0J 2X3",
    "sg:province":"BC",
    "sg:tags":[
        "excavating",
        "contractor"
    ],
    "wof:name":"C G Brooks Contracting Ltd",
    "wof:placetype":"venue"
},
  "geometry": {"coordinates":[-127.050606,54.697594],"type":"Point"}
}