{
  "type": "Feature",
  "properties": {
    "iso:country":"CA",
    "sg:city":"Windsor",
    "sg:classifiers":[
        {
            "category":"Retail",
            "subcategory":"Veterinary Services",
            "type":"Services"
        }
    ],
    "sg:phone":"+1 519 969 6095",
    "sg:postcode":"N9H 1R9",
    "sg:province":"ON",
    "sg:tags":[
        "veterinarian"
    ],
    "wof:name":"Malden Road Veterinary Hosp",
    "wof:placetype":"venue"
},
  "geometry": {"coordinates":[-83.06075286870001,42.251914978],"type":"Point"}
}