{
  "type": "Feature",
  "properties": {
    "addr:full":"9305 169 St NW Edmonton AB T5R 2X4",
    "addr:housenumber":"9305",
    "addr:postcode":"t5r 2x4",
    "addr:street":"169 St Nw",
    "iso:country":"CA",
    "sg:address":"9305 169 St NW",
    "sg:city":"Edmonton",
    "sg:classifiers":[
        {
            "category":"Professional",
            "subcategory":"Research",
            "type":"Services"
        }
    ],
    "sg:phone":"+1 780 483 0498",
    "sg:postcode":"T5R 2X4",
    "sg:province":"AB",
    "sg:tags":[
        "environmental",
        "ecological"
    ],
    "wof:name":"A A Aquatic Research Ltd",
    "wof:placetype":"venue"
},
  "geometry": {"coordinates":[-113.61319,53.528858],"type":"Point"}
}