{
  "type": "Feature",
  "properties": {
    "iso:country":"CA",
    "sg:address":"5000 Rue Saint-Denis",
    "sg:city":"Montreal",
    "sg:classifiers":[
        {
            "category":"Food & Beverages",
            "subcategory":"Fruits & Vegetables",
            "type":"Retail Goods"
        }
    ],
    "sg:phone":"+1 514 284 6377",
    "sg:postcode":"H2J 2L8",
    "sg:province":"QC",
    "sg:tags":[
        "produce"
    ],
    "wof:name":"Fruterie Muscat Inc",
    "wof:placetype":"venue"
},
  "geometry": {"coordinates":[-73.58823394780001,45.5262413025],"type":"Point"}
}