{
  "type": "Feature",
  "properties": {
    "addr:full":"701 Souris Ave Estevan SK S4A 2T1",
    "addr:housenumber":"701",
    "addr:postcode":"s4a 2t1",
    "addr:street":"Souris Ave",
    "iso:country":"CA",
    "sg:address":"701 Souris Ave",
    "sg:city":"Estevan",
    "sg:classifiers":[
        {
            "category":"Museum",
            "type":"Entertainment"
        }
    ],
    "sg:phone":"+1 306 634 3942",
    "sg:postcode":"S4A 2T1",
    "sg:province":"SK",
    "sg:tags":[
        "organization",
        "arts",
        "information"
    ],
    "wof:name":"Estevan Arts Council",
    "wof:placetype":"venue"
},
  "geometry": {"coordinates":[-102.991333008,49.1427001953],"type":"Point"}
}