{
  "type": "Feature",
  "properties": {
    "addr:full":"Highgate ON N0P 1T0",
    "addr:postcode":"n0p 1t0",
    "addr:street":"Highgate",
    "iso:country":"CA",
    "sg:city":"Highgate",
    "sg:classifiers":[
        {
            "category":"Health Services",
            "subcategory":"Doctor",
            "type":"Services"
        }
    ],
    "sg:phone":"+1 519 678 3875",
    "sg:postcode":"N0P 1T0",
    "sg:province":"ON",
    "sg:tags":[
        "dentist"
    ],
    "wof:name":"Highgate Dental Office",
    "wof:placetype":"venue"
},
  "geometry": {"coordinates":[-81.814414978,42.4994773865],"type":"Point"}
}