{
  "type": "Feature",
  "properties": {
    "addr:full":"6410 Kingsway Burnaby BC V5E 1C5",
    "addr:housenumber":"6410",
    "addr:postcode":"v5e 1c5",
    "addr:street":"Kingsway",
    "iso:country":"CA",
    "sg:address":"6410 Kingsway",
    "sg:city":"Burnaby",
    "sg:classifiers":[
        {
            "category":"Autos & Motor Vehicles",
            "subcategory":"Auto Supplies",
            "type":"Retail Goods"
        }
    ],
    "sg:phone":"+1 604 430 1491",
    "sg:postcode":"V5E 1C5",
    "sg:province":"BC",
    "sg:tags":[
        "automobile",
        "parts"
    ],
    "wof:name":"Mercury Equipment",
    "wof:placetype":"venue"
},
  "geometry": {"coordinates":[-122.97017700000001,49.219402],"type":"Point"}
}