{
  "type": "Feature",
  "properties": {
    "addr:full":"Kemptville ON K0G 1J0",
    "addr:postcode":"k0g 1j0",
    "iso:country":"CA",
    "sg:city":"Kemptville",
    "sg:classifiers":[
        {
            "category":"Shopping",
            "subcategory":"Optical Goods",
            "type":"Retail Goods"
        }
    ],
    "sg:phone":"+1 613 258 2285",
    "sg:postcode":"K0G 1J0",
    "sg:province":"ON",
    "sg:tags":[
        "optician"
    ],
    "wof:name":"Kemptville's Optician",
    "wof:placetype":"venue"
},
  "geometry": {"coordinates":[-75.641609,45.01833],"type":"Point"}
}