{
  "type": "Feature",
  "properties": {
    "addr:full":"308 3rd St E Meadow Lake SK S9X 1R5",
    "addr:housenumber":"308",
    "addr:postcode":"s9x 1r5",
    "addr:street":"3Rd St E;Lake",
    "iso:country":"CA",
    "sg:address":"308 3rd St E",
    "sg:city":"Meadow Lake",
    "sg:classifiers":[
        {
            "category":"Retail",
            "subcategory":"Auto Repair",
            "type":"Services"
        }
    ],
    "sg:phone":"+1 306 236 5701",
    "sg:postcode":"S9X 1R5",
    "sg:province":"SK",
    "sg:tags":[
        "body",
        "automobile",
        "painting"
    ],
    "wof:name":"Northland Auto Body",
    "wof:placetype":"venue"
},
  "geometry": {"coordinates":[-108.427841187,54.1300773621],"type":"Point"}
}