{
  "type": "Feature",
  "properties": {
    "addr:full":"New Westminster BC V3L 3C2",
    "addr:postcode":"v3l 3c2",
    "iso:country":"CA",
    "sg:city":"New Westminster",
    "sg:classifiers":[
        {
            "category":"Utilities",
            "subcategory":"Mobile Phone",
            "type":"Services"
        }
    ],
    "sg:phone":"+1 604 526 7800",
    "sg:postcode":"V3L 3C2",
    "sg:province":"BC",
    "sg:tags":[
        "telephone",
        "cellular"
    ],
    "wof:name":"Harmen Communications & Scrty",
    "wof:placetype":"venue"
},
  "geometry": {"coordinates":[-122.920890808,49.2133674622],"type":"Point"}
}