{
  "type": "Feature",
  "properties": {
    "addr:full":"112 1/2 King St S Waterloo ON N2J 1P5",
    "addr:housenumber":"112 1 / 2",
    "addr:postcode":"n2j 1p5",
    "addr:street":"King St S",
    "iso:country":"CA",
    "sg:address":"112 1/2 King St S",
    "sg:city":"Waterloo",
    "sg:classifiers":[
        {
            "category":"Shopping",
            "type":"Retail Goods"
        }
    ],
    "sg:phone":"+1 519 886 5290",
    "sg:postcode":"N2J 1P5",
    "sg:province":"ON",
    "sg:tags":[
        "picture",
        "frame",
        "art",
        "gallery",
        "dealer"
    ],
    "wof:name":"Pdr Picture Frames",
    "wof:placetype":"venue"
},
  "geometry": {"coordinates":[-80.521446,43.462578],"type":"Point"}
}