{
  "type": "Feature",
  "properties": {
    "addr:full":"211 Saskatchewan Ave E Portage LA Prairie MB R1N 0L7",
    "addr:housenumber":"211",
    "addr:postcode":"r1n 0l7",
    "addr:street":"Saskatchewan Ave E",
    "iso:country":"CA",
    "sg:address":"211 Saskatchewan Ave E",
    "sg:city":"Portage LA Prairie",
    "sg:classifiers":[
        {
            "category":"Shopping",
            "type":"Retail Goods"
        }
    ],
    "sg:phone":"+1 204 239 1411",
    "sg:postcode":"R1N 0L7",
    "sg:province":"MB",
    "sg:tags":[
        "paint",
        "picture"
    ],
    "wof:name":"New-Era Paints",
    "wof:placetype":"venue"
},
  "geometry": {"coordinates":[-98.288933,49.972858],"type":"Point"}
}