{
  "type": "Feature",
  "properties": {
    "addr:full":"1200 Av DE Germain-Des-Pres Sainte-Foy QC G1V 3M7",
    "addr:housenumber":"1200",
    "addr:postcode":"g1v 3m7",
    "addr:street":"Av De Germain-Des-Pres",
    "iso:country":"CA",
    "sg:address":"1200 Av DE Germain-Des-Pres",
    "sg:city":"Sainte-Foy",
    "sg:classifiers":[
        {
            "category":"Travel",
            "subcategory":"Travel Agent",
            "type":"Entertainment"
        }
    ],
    "sg:phone":"+1 418 659 6650",
    "sg:postcode":"G1V 3M7",
    "sg:province":"QC",
    "sg:tags":[
        "agency",
        "bureau"
    ],
    "wof:name":"Agence DE Voyages Paradis Inc",
    "wof:placetype":"venue"
},
  "geometry": {"coordinates":[-71.28796386720001,46.7693939209],"type":"Point"}
}