{
  "type": "Feature",
  "properties": {
    "iso:country":"CA",
    "sg:address":"273 King St W",
    "sg:city":"Kitchener",
    "sg:classifiers":[
        {
            "category":"Restaurant",
            "type":"Food & Drink"
        }
    ],
    "sg:phone":"+1 519 570 1260",
    "sg:postcode":"N2G 1B1",
    "sg:province":"ON",
    "sg:tags":[
        "banquet",
        "rooms"
    ],
    "wof:name":"Bars For Rent",
    "wof:placetype":"venue"
},
  "geometry": {"coordinates":[-80.49424,43.451462],"type":"Point"}
}