{
  "type": "Feature",
  "properties": {
    "addr:full":"215 20th Ave E Vancouver BC V5V 1M2",
    "addr:housenumber":"215",
    "addr:postcode":"v5v 1m2",
    "addr:street":"20Th Ave E",
    "iso:country":"CA",
    "sg:address":"215 20th Ave E",
    "sg:city":"Vancouver",
    "sg:classifiers":[
        {
            "category":"Home & Garden",
            "subcategory":"Household Appliances",
            "type":"Retail Goods"
        }
    ],
    "sg:phone":"+1 604 875 6890",
    "sg:postcode":"V5V 1M2",
    "sg:province":"BC",
    "sg:tags":[
        "cleaners",
        "vacuum"
    ],
    "wof:name":"Felmar Industries",
    "wof:placetype":"venue"
},
  "geometry": {"coordinates":[-123.100311,49.253117],"type":"Point"}
}