{
  "type": "Feature",
  "properties": {
    "iso:country":"CA",
    "sg:address":"9800 Territorial Dr",
    "sg:city":"North Battleford",
    "sg:classifiers":[
        {
            "category":"Shopping",
            "subcategory":"Gifts & Souvenirs",
            "type":"Retail Goods"
        }
    ],
    "sg:phone":"+1 306 445 6603",
    "sg:postcode":"S9A 3W6",
    "sg:province":"SK",
    "sg:tags":[
        "party",
        "supply",
        "store",
        "variety"
    ],
    "wof:name":"Your Dollar Store With More",
    "wof:placetype":"venue"
},
  "geometry": {"coordinates":[-108.304832459,52.7916412354],"type":"Point"}
}