{
  "type": "Feature",
  "properties": {
    "iso:country":"CA",
    "sg:address":"119 11th Ave N",
    "sg:city":"Creston",
    "sg:classifiers":[
        {
            "category":"Professional",
            "subcategory":"Employment Agencies",
            "type":"Services"
        }
    ],
    "sg:phone":"+1 250 428 5655",
    "sg:postcode":"V0B 1G0",
    "sg:province":"BC",
    "sg:tags":[
        "training",
        "co",
        "fraternal"
    ],
    "wof:name":"Kootenay Employment Svc",
    "wof:placetype":"venue"
},
  "geometry": {"coordinates":[-116.512062073,49.09608078],"type":"Point"}
}