{
  "type": "Feature",
  "properties": {
    "addr:full":"651 Boul Saint-Laurent E Louiseville QC J5V 1J1",
    "addr:housenumber":"651",
    "addr:postcode":"j5v 1j1",
    "addr:street":"Boul Saint-Laurent E",
    "iso:country":"CA",
    "sg:address":"651 Boul Saint-Laurent E",
    "sg:city":"Louiseville",
    "sg:classifiers":[
        {
            "category":"Professional",
            "subcategory":"Management & Consulting",
            "type":"Services"
        }
    ],
    "sg:phone":"+1 819 228 5921",
    "sg:postcode":"J5V 1J1",
    "sg:province":"QC",
    "sg:tags":[
        "development",
        "economic",
        "agency",
        "association"
    ],
    "wof:name":"Societe D'Aide-Developpement",
    "wof:placetype":"venue"
},
  "geometry": {"coordinates":[-72.918381,46.258095],"type":"Point"}
}