{
  "type": "Feature",
  "properties": {
    "addr:full":"342 Lower Ganges Rd # 103 Salt Spring Island BC V8K 2V3",
    "addr:housenumber":"342",
    "addr:postcode":"v8k 2v3",
    "addr:street":"Lower Ganges Rd # 103",
    "iso:country":"CA",
    "sg:address":"342 Lower Ganges Rd # 103",
    "sg:city":"Salt Spring Island",
    "sg:classifiers":[
        {
            "category":"Food & Beverages",
            "subcategory":"Groceries & Convenience Stores",
            "type":"Retail Goods"
        }
    ],
    "sg:phone":"+1 250 537 1766",
    "sg:postcode":"V8K 2V3",
    "sg:province":"BC",
    "sg:tags":[
        "grocer"
    ],
    "wof:name":"Upper Centre Store",
    "wof:placetype":"venue"
},
  "geometry": {"coordinates":[-123.509148,48.859787],"type":"Point"}
}