{
  "type": "Feature",
  "properties": {
    "addr:full":"428 Knightsbridge Rd Kingston ON K7M 5S7",
    "addr:housenumber":"428",
    "addr:postcode":"k7m 5s7",
    "addr:street":"Knightsbridge Rd",
    "iso:country":"CA",
    "sg:address":"428 Knightsbridge Rd",
    "sg:city":"Kingston",
    "sg:classifiers":[
        {
            "category":"Personal",
            "subcategory":"Beauty Salon",
            "type":"Services"
        }
    ],
    "sg:phone":"+1 613 384 8496",
    "sg:postcode":"K7M 5S7",
    "sg:province":"ON",
    "wof:name":"Mila's Hair Design",
    "wof:placetype":"venue"
},
  "geometry": {"coordinates":[-76.578506,44.232208],"type":"Point"}
}