{
  "type": "Feature",
  "properties": {
    "iso:country":"CA",
    "sg:address":"5022 51 St",
    "sg:city":"Yellowknife",
    "sg:classifiers":[
        {
            "category":"Professional",
            "subcategory":"Computer Services",
            "type":"Services"
        }
    ],
    "sg:phone":"+1 867 920 0818",
    "sg:postcode":"X1A 1S6",
    "sg:province":"NT",
    "sg:tags":[
        "machine",
        "repair",
        "duplicating",
        "copying",
        "furniture"
    ],
    "wof:name":"Workplace Plus Ltd",
    "wof:placetype":"venue"
},
  "geometry": {"coordinates":[-114.372444153,62.4530181885],"type":"Point"}
}