{
  "type": "Feature",
  "properties": {
    "iso:country":"CA",
    "sg:address":"3520 31 St NW",
    "sg:city":"Calgary",
    "sg:classifiers":[
        {
            "category":"Real Estate",
            "subcategory":"Real Estate Operator",
            "type":"Services"
        }
    ],
    "sg:phone":"+1 403 215 8714",
    "sg:postcode":"T2L 2A4",
    "sg:province":"AB",
    "sg:tags":[
        "apartment"
    ],
    "wof:name":"Brentview Towers",
    "wof:placetype":"venue"
},
  "geometry": {"coordinates":[-114.129142761,51.0834770203],"type":"Point"}
}