{
  "type": "Feature",
  "properties": {
    "addr:full":"301 Aqueduct St Welland ON L3C 1C9",
    "addr:housenumber":"301",
    "addr:postcode":"l3c 1c9",
    "addr:street":"Aqueduct St",
    "iso:country":"CA",
    "sg:address":"301 Aqueduct St",
    "sg:city":"Welland",
    "sg:classifiers":[
        {
            "category":"Shopping",
            "type":"Retail Goods"
        }
    ],
    "sg:phone":"+1 905 735 9717",
    "sg:postcode":"L3C 1C9",
    "sg:province":"ON",
    "sg:tags":[
        "monument"
    ],
    "wof:name":"Niagara Cemetery Memorials",
    "wof:placetype":"venue"
},
  "geometry": {"coordinates":[-79.250046,43.0042],"type":"Point"}
}