{
  "type": "Feature",
  "properties": {
    "addr:full":"350 Rue Mccaffrey Saint-Laurent QC H4T 1N1",
    "addr:housenumber":"350",
    "addr:postcode":"h4t 1n1",
    "addr:street":"Rue Mccaffrey",
    "iso:country":"CA",
    "sg:address":"350 Rue Mccaffrey",
    "sg:city":"Saint-Laurent",
    "sg:classifiers":[
        {
            "category":"Wholesale",
            "subcategory":"Apparel",
            "type":"Manufacturing & Wholesale Goods"
        }
    ],
    "sg:phone":"+1 514 344 6767",
    "sg:postcode":"H4T 1N1",
    "sg:province":"QC",
    "sg:tags":[
        "cap",
        "hat"
    ],
    "wof:name":"Ajm Intl Sports Ltd",
    "wof:placetype":"venue"
},
  "geometry": {"coordinates":[-73.703705,45.483086],"type":"Point"}
}