{
  "type": "Feature",
  "properties": {
    "addr:full":"552 Paul St # 105 Dieppe NB E1A 5Z1",
    "addr:housenumber":"552",
    "addr:postcode":"e1a 5z1",
    "addr:street":"Paul St # 105",
    "iso:country":"CA",
    "sg:address":"552 Paul St # 105",
    "sg:city":"Dieppe",
    "sg:classifiers":[
        {
            "category":"Travel",
            "subcategory":"Travel Agent",
            "type":"Entertainment"
        }
    ],
    "sg:phone":"+1 506 383 1919",
    "sg:postcode":"E1A 5Z1",
    "sg:province":"NB",
    "sg:tags":[
        "agency",
        "bureau"
    ],
    "wof:name":"Harvey's Travel",
    "wof:placetype":"venue"
},
  "geometry": {"coordinates":[-64.756218,46.095604],"type":"Point"}
}