{
  "type": "Feature",
  "properties": {
    "addr:full":"20 Brook Point Rd Tantallon NS B3Z 2R3",
    "addr:housenumber":"20",
    "addr:postcode":"b3z 2r3",
    "addr:street":"Brook Point Rd",
    "iso:country":"CA",
    "sg:address":"20 Brook Point Rd",
    "sg:city":"Tantallon",
    "sg:classifiers":[
        {
            "category":"Retail",
            "subcategory":"Portrait Studio",
            "type":"Services"
        }
    ],
    "sg:phone":"+1 902 499 2409",
    "sg:postcode":"B3Z 2R3",
    "sg:province":"NS",
    "sg:tags":[
        "photographer"
    ],
    "wof:name":"Mark Doucette Photographic",
    "wof:placetype":"venue"
},
  "geometry": {"coordinates":[-63.921242,44.656101],"type":"Point"}
}