{
  "type": "Feature",
  "properties": {
    "addr:full":"2755 Boul Des Oiseaux Laval QC H7L 4S9",
    "addr:housenumber":"2755",
    "addr:postcode":"h7l 4s9",
    "addr:street":"Boul Des Oiseaux",
    "iso:country":"CA",
    "sg:address":"2755 Boul Des Oiseaux",
    "sg:city":"Laval",
    "sg:classifiers":[
        {
            "category":"Personal",
            "subcategory":"Beauty Salon",
            "type":"Services"
        }
    ],
    "sg:phone":"+1 450 963 1422",
    "sg:postcode":"H7L 4S9",
    "sg:province":"QC",
    "wof:name":"Coiffure Top-Chik",
    "wof:placetype":"venue"
},
  "geometry": {"coordinates":[-73.78061700000001,45.588902],"type":"Point"}
}