{
  "type": "Feature",
  "properties": {
    "iso:country":"CA",
    "sg:address":"2755 Boul Des Oiseaux",
    "sg:city":"Laval",
    "sg:classifiers":[
        {
            "category":"Personal",
            "subcategory":"Beauty Salon",
            "type":"Services"
        }
    ],
    "sg:phone":"+1 450 963 1422",
    "sg:postcode":"H7L 4S9",
    "sg:province":"QC",
    "wof:name":"Coiffure Top-Chik",
    "wof:placetype":"venue"
},
  "geometry": {"coordinates":[-73.780617,45.588902],"type":"Point"}
}