{
  "type": "Feature",
  "properties": {
    "addr:full":"Granby QC J2G 5B6",
    "addr:postcode":"j2g 5b6",
    "iso:country":"CA",
    "sg:city":"Granby",
    "sg:classifiers":[
        {
            "category":"Real Estate",
            "subcategory":"Real Estate Agent",
            "type":"Services"
        }
    ],
    "sg:phone":"+1 450 378 3882",
    "sg:postcode":"J2G 5B6",
    "sg:province":"QC",
    "sg:tags":[
        "management"
    ],
    "wof:name":"Societe DE Gestion Bernard",
    "wof:placetype":"venue"
},
  "geometry": {"coordinates":[-72.725616,45.402725],"type":"Point"}
}