{
  "type": "Feature",
  "properties": {
    "addr:full":"2525 Boul Laurier Sainte-Foy QC G1V 2L2",
    "addr:housenumber":"2525",
    "addr:postcode":"g1v 2l2",
    "addr:street":"Boul Laurier",
    "iso:country":"CA",
    "sg:address":"2525 Boul Laurier",
    "sg:city":"Sainte-Foy",
    "sg:classifiers":[
        {
            "category":"Professional",
            "subcategory":"Lawyer & Legal Services",
            "type":"Services"
        }
    ],
    "sg:phone":"+1 418 658 1080",
    "sg:postcode":"G1V 2L2",
    "sg:province":"QC",
    "sg:tags":[
        "attorney"
    ],
    "wof:name":"Pouliot L'Ecuyer",
    "wof:placetype":"venue"
},
  "geometry": {"coordinates":[-71.27658099999999,46.772827],"type":"Point"}
}