{
  "type": "Feature",
  "properties": {
    "iso:country":"CA",
    "sg:address":"8748 Boul Langelier",
    "sg:city":"Saint-Leonard",
    "sg:classifiers":[
        {
            "category":"Shopping",
            "type":"Retail Goods"
        }
    ],
    "sg:phone":"+1 514 321 2146",
    "sg:postcode":"H1P 3C6",
    "sg:province":"QC",
    "sg:tags":[
        "equipment",
        "wine",
        "supply"
    ],
    "wof:name":"Vignes St-Leonard",
    "wof:placetype":"venue"
},
  "geometry": {"coordinates":[-73.59362,45.599613],"type":"Point"}
}