{
  "type": "Feature",
  "properties": {
    "addr:full":"Calgary AB T2Z 3V8",
    "addr:postcode":"t2z 3v8",
    "iso:country":"CA",
    "sg:city":"Calgary",
    "sg:classifiers":[
        {
            "category":"Insurance",
            "subcategory":"Insurance Agent",
            "type":"Services"
        }
    ],
    "sg:phone":"+1 403 221 7185",
    "sg:postcode":"T2Z 3V8",
    "sg:province":"AB",
    "wof:name":"CO-Operators General Insurance",
    "wof:placetype":"venue"
},
  "geometry": {"coordinates":[-113.97018432599999,50.9317817688],"type":"Point"}
}