{
  "type": "Feature",
  "properties": {
    "addr:full":"Sainte-Julienne QC J0K 2T0",
    "addr:postcode":"j0k 2t0",
    "iso:country":"CA",
    "sg:city":"Sainte-Julienne",
    "sg:classifiers":[
        {
            "category":"Organizations",
            "subcategory":"Religious Organization",
            "type":"Services"
        }
    ],
    "sg:phone":"+1 450 831 4666",
    "sg:postcode":"J0K 2T0",
    "sg:province":"QC",
    "wof:name":"Wat Thepbandol",
    "wof:placetype":"venue"
},
  "geometry": {"coordinates":[-73.70594024659999,45.9615058899],"type":"Point"}
}