{
  "type": "Feature",
  "properties": {
    "addr:full":"149 3rd St W North Vancouver BC V7M 1E7",
    "addr:housenumber":"149",
    "addr:postcode":"v7m 1e7",
    "addr:street":"3Rd St W",
    "iso:country":"CA",
    "sg:address":"149 3rd St W",
    "sg:city":"North Vancouver",
    "sg:classifiers":[
        {
            "category":"Restaurant",
            "type":"Food & Drink"
        }
    ],
    "sg:phone":"+1 604 987 9782",
    "sg:postcode":"V7M 1E7",
    "sg:province":"BC",
    "wof:name":"El Nopalito Mexican Restaurant",
    "wof:placetype":"venue"
},
  "geometry": {"coordinates":[-123.07865099999999,49.314011],"type":"Point"}
}