{
  "type": "Feature",
  "properties": {
    "addr:full":"5764 Quesnel Hixon Rd Quesnel BC V2J 6Y4",
    "addr:housenumber":"5764",
    "addr:postcode":"v2j 6y4",
    "addr:street":"Hixon Rd",
    "iso:country":"CA",
    "sg:address":"5764 Quesnel Hixon Rd",
    "sg:city":"Quesnel",
    "sg:classifiers":[
        {
            "category":"Building & Trades",
            "subcategory":"Construction",
            "type":"Services"
        }
    ],
    "sg:phone":"+1 250 992 5907",
    "sg:postcode":"V2J 6Y4",
    "sg:province":"BC",
    "sg:tags":[
        "general",
        "contractor"
    ],
    "wof:name":"Berlin Construction",
    "wof:placetype":"venue"
},
  "geometry": {"coordinates":[-122.52154541,53.0266685486],"type":"Point"}
}