{
  "type": "Feature",
  "properties": {
    "addr:full":"North York ON M2N 3B3",
    "addr:postcode":"m2n 3b3",
    "iso:country":"CA",
    "sg:city":"North York",
    "sg:classifiers":[
        {
            "category":"Building & Trades",
            "subcategory":"Construction",
            "type":"Services"
        }
    ],
    "sg:phone":"+1 416 229 9966",
    "sg:postcode":"M2N 3B3",
    "sg:province":"ON",
    "sg:tags":[
        "contractor",
        "general"
    ],
    "wof:name":"Ghods Builders Inc",
    "wof:placetype":"venue"
},
  "geometry": {"coordinates":[-79.390259,43.765961],"type":"Point"}
}