{
  "type": "Feature",
  "properties": {
    "addr:full":"Ebenezer SK S0A 0T0",
    "addr:postcode":"s0a 0t0",
    "iso:country":"CA",
    "sg:city":"Ebenezer",
    "sg:classifiers":[
        {
            "category":"Building & Trades",
            "subcategory":"Construction",
            "type":"Services"
        }
    ],
    "sg:phone":"+1 306 782 7147",
    "sg:postcode":"S0A 0T0",
    "sg:province":"SK",
    "sg:tags":[
        "maker",
        "cabinet"
    ],
    "wof:name":"Terry's Cabinets",
    "wof:placetype":"venue"
},
  "geometry": {"coordinates":[-102.453041,51.369064],"type":"Point"}
}