{
  "type": "Feature",
  "properties": {
    "iso:country":"CA",
    "sg:city":"Montreal",
    "sg:classifiers":[
        {
            "category":"Freight",
            "type":"Transportation"
        }
    ],
    "sg:phone":"+1 514 384 5632",
    "sg:postcode":"H4N 2T2",
    "sg:province":"QC",
    "sg:tags":[
        "broker",
        "trucking"
    ],
    "wof:name":"Pars Cargo",
    "wof:placetype":"venue"
},
  "geometry": {"coordinates":[-73.63369,45.581413],"type":"Point"}
}