{
  "type": "Feature",
  "properties": {
    "addr:full":"14 Rang Bellevue Saint-Robert QC J0G 1S0",
    "addr:housenumber":"14",
    "addr:postcode":"j0g 1s0",
    "addr:street":"Rang Bellevue",
    "iso:country":"CA",
    "sg:address":"14 Rang Bellevue",
    "sg:city":"Saint-Robert",
    "sg:classifiers":[
        {
            "category":"Building & Trades",
            "subcategory":"Construction",
            "type":"Services"
        }
    ],
    "sg:phone":"+1 450 782 3586",
    "sg:postcode":"J0G 1S0",
    "sg:province":"QC",
    "sg:tags":[
        "concrete",
        "builder",
        "deck",
        "patio",
        "contractor"
    ],
    "wof:name":"Patios Clement Gagnon",
    "wof:placetype":"venue"
},
  "geometry": {"coordinates":[-73.034592,45.965572],"type":"Point"}
}