{
  "type": "Feature",
  "properties": {
    "addr:full":"182 Boul Harwood Vaudreuil-Dorion QC J7V 1Y2",
    "addr:housenumber":"182",
    "addr:postcode":"j7v 1y2",
    "addr:street":"Boul Harwood",
    "iso:country":"CA",
    "sg:address":"182 Boul Harwood",
    "sg:city":"Vaudreuil-Dorion",
    "sg:classifiers":[
        {
            "category":"Social Services",
            "subcategory":"Job Training",
            "type":"Services"
        }
    ],
    "sg:phone":"+1 450 424 5727",
    "sg:postcode":"J7V 1Y2",
    "sg:province":"QC",
    "sg:tags":[
        "employment",
        "agency",
        "opportunity"
    ],
    "wof:name":"Reseaux Emploi Entrepreneurshp",
    "wof:placetype":"venue"
},
  "geometry": {"coordinates":[-74.0122756958,45.3825569153],"type":"Point"}
}