{
  "type": "Feature",
  "properties": {
    "addr:full":"5863 Ladyburn Cres Mississauga ON L5M 4V2",
    "addr:housenumber":"5863",
    "addr:postcode":"l5m 4v2",
    "addr:street":"Ladyburn Cres",
    "iso:country":"CA",
    "sg:address":"5863 Ladyburn Cres",
    "sg:city":"Mississauga",
    "sg:classifiers":[
        {
            "category":"Personal",
            "subcategory":"Beauty Salon",
            "type":"Services"
        }
    ],
    "sg:phone":"+1 905 819 0662",
    "sg:postcode":"L5M 4V2",
    "sg:province":"ON",
    "wof:name":"Kate's LA Pari Skin Care",
    "wof:placetype":"venue"
},
  "geometry": {"coordinates":[-79.70903,43.594238],"type":"Point"}
}