{
  "type": "Feature",
  "properties": {
    "addr:full":"Winnipeg MB R3C 0A1",
    "addr:postcode":"r3c 0a1",
    "iso:country":"CA",
    "sg:city":"Winnipeg",
    "sg:classifiers":[
        {
            "category":"Professional",
            "subcategory":"Engineering",
            "type":"Services"
        }
    ],
    "sg:phone":"+1 204 947 2222",
    "sg:postcode":"R3C 0A1",
    "sg:province":"MB",
    "sg:tags":[
        "engineer"
    ],
    "wof:name":"Lavergne Draward & Assoc",
    "wof:placetype":"venue"
},
  "geometry": {"coordinates":[-97.1373596191,49.8951454163],"type":"Point"}
}