{
  "type": "Feature",
  "properties": {
    "addr:full":"4225 Jefton Cres Mississauga ON L5L 1Z2",
    "addr:housenumber":"4225",
    "addr:postcode":"l5l 1z2",
    "addr:street":"Jefton Cres",
    "iso:country":"CA",
    "sg:address":"4225 Jefton Cres",
    "sg:city":"Mississauga",
    "sg:classifiers":[
        {
            "category":"Home & Garden",
            "subcategory":"Building Materials",
            "type":"Retail Goods"
        }
    ],
    "sg:phone":"+1 905 607 5024",
    "sg:postcode":"L5L 1Z2",
    "sg:province":"ON",
    "sg:tags":[
        "door"
    ],
    "wof:name":"Delta Overhead Doors",
    "wof:placetype":"venue"
},
  "geometry": {"coordinates":[-79.6993713379,43.5403633118],"type":"Point"}
}