{
  "type": "Feature",
  "properties": {
    "addr:full":"13095 60 Ave Surrey BC V3X 2L6",
    "addr:housenumber":"13095",
    "addr:postcode":"v3x 2l6",
    "addr:street":"60 Ave",
    "iso:country":"CA",
    "sg:address":"13095 60 Ave",
    "sg:city":"Surrey",
    "sg:classifiers":[
        {
            "category":"Organizations",
            "subcategory":"Religious Organization",
            "type":"Services"
        }
    ],
    "sg:phone":"+1 604 594 7166",
    "sg:postcode":"V3X 2L6",
    "sg:province":"BC",
    "sg:tags":[
        "church"
    ],
    "wof:name":"Jehovah's Witnesses",
    "wof:placetype":"venue"
},
  "geometry": {"coordinates":[-122.85948944099999,49.1119422913],"type":"Point"}
}