{
  "type": "Feature",
  "properties": {
    "addr:full":"PO Box 69 Benson SK S0C 0L0",
    "addr:housenumber":"po box 69",
    "addr:postcode":"s0c 0l0",
    "iso:country":"CA",
    "sg:address":"PO Box 69",
    "sg:city":"Benson",
    "sg:classifiers":[
        {
            "category":"Government",
            "subcategory":"Office",
            "type":"Public Place"
        }
    ],
    "sg:phone":"+1 306 634 9410",
    "sg:postcode":"S0C 0L0",
    "sg:province":"SK",
    "sg:tags":[
        "municipality"
    ],
    "wof:name":"Rural Municipality-Benson 35",
    "wof:placetype":"venue"
},
  "geometry": {"coordinates":[-103.00694300000001,49.463203],"type":"Point"}
}