{
  "type": "Feature",
  "properties": {
    "iso:country":"CA",
    "sg:city":"Pemberton",
    "sg:classifiers":[
        {
            "category":"Retail",
            "subcategory":"Auto Repair",
            "type":"Services"
        }
    ],
    "sg:phone":"+1 604 894 5102",
    "sg:postcode":"V0N 2L0",
    "sg:province":"BC",
    "sg:tags":[
        "repairing",
        "automobile"
    ],
    "wof:name":"Olemotive Auto Repair",
    "wof:placetype":"venue"
},
  "geometry": {"coordinates":[-122.804916382,50.3219795227],"type":"Point"}
}