{
  "type": "Feature",
  "properties": {
    "addr:full":"3451 Pembina Hwy Winnipeg MB R3V 1A4",
    "addr:housenumber":"3451",
    "addr:postcode":"r3v 1a4",
    "addr:street":"Pembina Hwy",
    "iso:country":"CA",
    "sg:address":"3451 Pembina Hwy",
    "sg:city":"Winnipeg",
    "sg:classifiers":[
        {
            "category":"Retail",
            "subcategory":"Auto Repair",
            "type":"Services"
        }
    ],
    "sg:phone":"+1 204 269 1839",
    "sg:postcode":"R3V 1A4",
    "sg:province":"MB",
    "sg:tags":[
        "repairing",
        "automobile"
    ],
    "wof:name":"Kmc Enterprises",
    "wof:placetype":"venue"
},
  "geometry": {"coordinates":[-97.1564483643,49.7679443359],"type":"Point"}
}