{
  "type": "Feature",
  "properties": {
    "addr:full":"224 13 Ave SW Calgary AB T2R 0K2",
    "addr:postcode":"t2r 0k2",
    "addr:street":"224 13 Ave Sw",
    "iso:country":"CA",
    "sg:address":"224 13 Ave SW",
    "sg:city":"Calgary",
    "sg:classifiers":[
        {
            "category":"Communications",
            "subcategory":"Film & Video Production",
            "type":"Services"
        }
    ],
    "sg:phone":"+1 403 263 5552",
    "sg:postcode":"T2R 0K2",
    "sg:province":"AB",
    "sg:tags":[
        "taping"
    ],
    "wof:name":"Video Dex",
    "wof:placetype":"venue"
},
  "geometry": {"coordinates":[-114.066292,51.040649],"type":"Point"}
}