{
  "type": "Feature",
  "properties": {
    "addr:full":"2467 Yonge St Toronto ON M4P 2H6",
    "addr:housenumber":"2467",
    "addr:postcode":"m4p 2h6",
    "addr:street":"Yonge St",
    "iso:country":"CA",
    "sg:address":"2467 Yonge St",
    "sg:city":"Toronto",
    "sg:classifiers":[
        {
            "category":"Personal",
            "subcategory":"Beauty Salon",
            "type":"Services"
        }
    ],
    "sg:phone":"+1 416 440 4247",
    "sg:postcode":"M4P 2H6",
    "sg:province":"ON",
    "wof:name":"Jalouse Hair Michael Rutledge",
    "wof:placetype":"venue"
},
  "geometry": {"coordinates":[-79.399162,43.711388],"type":"Point"}
}