{
  "type": "Feature",
  "properties": {
    "addr:full":"201 Front St N #303 Sarnia ON N7T 7T9",
    "addr:housenumber":"201",
    "addr:postcode":"n7t 7t9",
    "addr:street":"Front St N # 303",
    "iso:country":"CA",
    "sg:address":"201 Front St N #303",
    "sg:city":"Sarnia",
    "sg:classifiers":[
        {
            "category":"Professional",
            "subcategory":"Lawyer & Legal Services",
            "type":"Services"
        }
    ],
    "sg:phone":"+1 519 336 5447",
    "sg:postcode":"N7T 7T9",
    "sg:province":"ON",
    "sg:tags":[
        "attorney"
    ],
    "wof:name":"Mathews Dinsdale & Clark",
    "wof:placetype":"venue"
},
  "geometry": {"coordinates":[-82.4080581665,42.9736671448],"type":"Point"}
}