{
  "type": "Feature",
  "properties": {
    "addr:full":"298 Kerr St # B Oakville ON L6K 3B3",
    "addr:housenumber":"298",
    "addr:postcode":"l6k 3b3",
    "addr:street":"Kerr St # B",
    "iso:country":"CA",
    "sg:address":"298 Kerr St # B",
    "sg:city":"Oakville",
    "sg:classifiers":[
        {
            "category":"Food & Beverages",
            "subcategory":"Bakery",
            "type":"Retail Goods"
        }
    ],
    "sg:phone":"+1 905 815 0185",
    "sg:postcode":"L6K 3B3",
    "sg:province":"ON",
    "sg:tags":[
        "baker"
    ],
    "wof:name":"Oakville Portuguese Pastry",
    "wof:placetype":"venue"
},
  "geometry": {"coordinates":[-79.68059539790001,43.4429779053],"type":"Point"}
}