{
  "type": "Feature",
  "properties": {
    "addr:full":"58 Montcalm Cres Winnipeg MB R2V 2N4",
    "addr:housenumber":"58",
    "addr:postcode":"r2v 2n4",
    "addr:street":"Montcalm Cres",
    "iso:country":"CA",
    "sg:address":"58 Montcalm Cres",
    "sg:city":"Winnipeg",
    "sg:classifiers":[
        {
            "category":"Retail",
            "subcategory":"Laundry & Dry Cleaning",
            "type":"Services"
        }
    ],
    "sg:phone":"+1 204 334 6222",
    "sg:postcode":"R2V 2N4",
    "sg:province":"MB",
    "sg:tags":[
        "cleaners",
        "rug",
        "carpet"
    ],
    "wof:name":"Tower Custom Cleaners",
    "wof:placetype":"venue"
},
  "geometry": {"coordinates":[-97.137878,49.940994],"type":"Point"}
}