{
  "type": "Feature",
  "properties": {
    "addr:full":"5003 47A St # 239 Whitecourt AB T7S 1N4",
    "addr:housenumber":"5003",
    "addr:postcode":"t7s 1n4",
    "addr:street":"47A St # 239 Whitecourt",
    "iso:country":"CA",
    "sg:address":"5003 47A St # 239",
    "sg:city":"Whitecourt",
    "sg:classifiers":[
        {
            "category":"Retail",
            "subcategory":"Auto Repair",
            "type":"Services"
        }
    ],
    "sg:phone":"+1 780 778 4224",
    "sg:postcode":"T7S 1N4",
    "sg:province":"AB",
    "sg:tags":[
        "muffler",
        "exhaust",
        "system"
    ],
    "wof:name":"S & S Muffler Shop",
    "wof:placetype":"venue"
},
  "geometry": {"coordinates":[-115.678078,54.144871],"type":"Point"}
}