{
  "type": "Feature",
  "properties": {
    "iso:country":"CA",
    "sg:city":"Barrie",
    "sg:classifiers":[
        {
            "category":"Retail",
            "subcategory":"Auto Repair",
            "type":"Services"
        }
    ],
    "sg:phone":"+1 705 725 8615",
    "sg:postcode":"L4N 2G5",
    "sg:province":"ON",
    "sg:tags":[
        "body",
        "automobile",
        "painting"
    ],
    "wof:name":"Barrie Collision Ctr",
    "wof:placetype":"venue"
},
  "geometry": {"coordinates":[-79.7050628662,44.379940033],"type":"Point"}
}