{
  "type": "Feature",
  "properties": {
    "addr:full":"1581 Grand Ave Buena Vista SK S2V 1A3",
    "addr:housenumber":"1581",
    "addr:postcode":"s2v 1a3",
    "addr:street":"Grand Ave",
    "iso:country":"CA",
    "sg:address":"1581 Grand Ave",
    "sg:city":"Buena Vista",
    "sg:classifiers":[
        {
            "category":"Building & Trades",
            "subcategory":"Equipment Rental",
            "type":"Services"
        }
    ],
    "sg:phone":"+1 306 729 4258",
    "sg:postcode":"S2V 1A3",
    "sg:province":"SK",
    "sg:tags":[
        "camping"
    ],
    "wof:name":"Buena Vista Tentworks",
    "wof:placetype":"venue"
},
  "geometry": {"coordinates":[-104.942154,50.77887],"type":"Point"}
}