{
  "type": "Feature",
  "properties": {
    "addr:full":"8331 Av Chenier Anjou QC H1K 2B5",
    "addr:housenumber":"8331",
    "addr:postcode":"h1k 2b5",
    "addr:street":"Av Chenier",
    "iso:country":"CA",
    "sg:address":"8331 Av Chenier",
    "sg:city":"Anjou",
    "sg:classifiers":[
        {
            "category":"Manufacturing",
            "subcategory":"Printing",
            "type":"Manufacturing & Wholesale Goods"
        }
    ],
    "sg:phone":"+1 514 351 3125",
    "sg:postcode":"H1K 2B5",
    "sg:province":"QC",
    "sg:tags":[
        "publisher",
        "guide"
    ],
    "wof:name":"Publications Excellence",
    "wof:placetype":"venue"
},
  "geometry": {"coordinates":[-73.5436553955,45.6046981812],"type":"Point"}
}