{
  "type": "Feature",
  "properties": {
    "addr:full":"127 Rue Principale East Broughton QC G0N 1G0",
    "addr:housenumber":"127",
    "addr:postcode":"g0n 1g0",
    "addr:street":"Rue Principale",
    "iso:country":"CA",
    "sg:address":"127 Rue Principale",
    "sg:city":"East Broughton",
    "sg:classifiers":[
        {
            "category":"Bars & Pubs",
            "type":"Food & Drink"
        }
    ],
    "sg:phone":"+1 418 427 5967",
    "sg:postcode":"G0N 1G0",
    "sg:province":"QC",
    "sg:tags":[
        "lounge",
        "cocktail"
    ],
    "wof:name":"Bar LA Ronde Enr",
    "wof:placetype":"venue"
},
  "geometry": {"coordinates":[-71.07100699999999,46.218956],"type":"Point"}
}