{
  "type": "Feature",
  "properties": {
    "addr:full":"35 Rue Saint-Louis # B Riviere-Du-Loup QC G5R 2V3",
    "addr:housenumber":"35;# b",
    "addr:postcode":"g5r 2v3",
    "addr:street":"Rue Saint-Louis;Riviere-Du-Loup",
    "iso:country":"CA",
    "sg:address":"35 Rue Saint-Louis # B",
    "sg:city":"Riviere-Du-Loup",
    "sg:classifiers":[
        {
            "category":"Professional",
            "subcategory":"Business Services",
            "type":"Services"
        }
    ],
    "sg:phone":"+1 418 867 3598",
    "sg:postcode":"G5R 2V3",
    "sg:province":"QC",
    "sg:tags":[
        "consultant",
        "rug",
        "design",
        "interior",
        "dealer",
        "decorator",
        "carpet"
    ],
    "wof:name":"Aubaine Du Tapis Saucier Inc",
    "wof:placetype":"venue"
},
  "geometry": {"coordinates":[-69.53488900000001,47.83268],"type":"Point"}
}