{
  "type": "Feature",
  "properties": {
    "addr:full":"3320 Pike Ave Regina SK S4T 1S4",
    "addr:housenumber":"3320",
    "addr:postcode":"s4t 1s4",
    "addr:street":"Pike Ave",
    "iso:country":"CA",
    "sg:address":"3320 Pike Ave",
    "sg:city":"Regina",
    "sg:classifiers":[
        {
            "category":"Professional",
            "subcategory":"Management & Consulting",
            "type":"Services"
        }
    ],
    "sg:phone":"+1 306 757 8200",
    "sg:postcode":"S4T 1S4",
    "sg:province":"SK",
    "sg:tags":[
        "communications",
        "consultant"
    ],
    "wof:name":"Soundings/Steele Inc",
    "wof:placetype":"venue"
},
  "geometry": {"coordinates":[-104.628632,50.444752],"type":"Point"}
}