{
  "type": "Feature",
  "properties": {
    "addr:full":"1200 Pembroke St W Pembroke ON K8A 7T1",
    "addr:housenumber":"1200",
    "addr:postcode":"k8a 7t1",
    "addr:street":"Pembroke St W",
    "iso:country":"CA",
    "sg:address":"1200 Pembroke St W",
    "sg:city":"Pembroke",
    "sg:classifiers":[
        {
            "category":"Shopping",
            "subcategory":"Gifts & Souvenirs",
            "type":"Retail Goods"
        }
    ],
    "sg:phone":"+1 613 732 1942",
    "sg:postcode":"K8A 7T1",
    "sg:province":"ON",
    "sg:tags":[
        "cards",
        "greeting"
    ],
    "wof:name":"Carlton Cards",
    "wof:placetype":"venue"
},
  "geometry": {"coordinates":[-77.1457290649,45.8320960999],"type":"Point"}
}