{
  "type": "Feature",
  "properties": {
    "addr:full":"Penticton BC V2A 5B7",
    "addr:postcode":"v2a 5b7",
    "iso:country":"CA",
    "sg:city":"Penticton",
    "sg:classifiers":[
        {
            "category":"Shopping",
            "subcategory":"Clothing, Apparel, & Fashions",
            "type":"Retail Goods"
        }
    ],
    "sg:phone":"+1 250 493 9391",
    "sg:postcode":"V2A 5B7",
    "sg:province":"BC",
    "sg:tags":[
        "lingerie"
    ],
    "wof:name":"Caroline's",
    "wof:placetype":"venue"
},
  "geometry": {"coordinates":[-119.591797,49.497238],"type":"Point"}
}