{
  "type": "Feature",
  "properties": {
    "addr:full":"1445 Duford Dr Orleans ON K1E 1E8",
    "addr:housenumber":"1445",
    "addr:postcode":"k1e 1e8",
    "addr:street":"Duford Dr",
    "iso:country":"CA",
    "sg:address":"1445 Duford Dr",
    "sg:city":"Orleans",
    "sg:classifiers":[
        {
            "category":"Education",
            "subcategory":"School",
            "type":"Public Place"
        }
    ],
    "sg:phone":"+1 613 824 4163",
    "sg:postcode":"K1E 1E8",
    "sg:province":"ON",
    "wof:name":"Queenswood Public School",
    "wof:placetype":"venue"
},
  "geometry": {"coordinates":[-75.508895874,45.4723472595],"type":"Point"}
}