{
  "type": "Feature",
  "properties": {
    "addr:full":"576 Wall St Winnipeg MB R3G 2T3",
    "addr:housenumber":"576",
    "addr:postcode":"r3g 2t3",
    "addr:street":"Wall St",
    "iso:country":"CA",
    "sg:address":"576 Wall St",
    "sg:city":"Winnipeg",
    "sg:classifiers":[
        {
            "category":"Retail",
            "subcategory":"Repair Shop",
            "type":"Services"
        }
    ],
    "sg:phone":"+1 204 786 5533",
    "sg:postcode":"R3G 2T3",
    "sg:province":"MB",
    "sg:tags":[
        "television",
        "radio"
    ],
    "wof:name":"Advance Electronics",
    "wof:placetype":"venue"
},
  "geometry": {"coordinates":[-97.1829986572,49.8852462769],"type":"Point"}
}