{
  "type": "Feature",
  "properties": {
    "iso:country":"CA",
    "sg:address":"850 Sawmill Rd",
    "sg:city":"Bloomingdale",
    "sg:classifiers":[
        {
            "category":"Organizations",
            "subcategory":"Religious Organization",
            "type":"Services"
        }
    ],
    "sg:phone":"+1 519 744 7447",
    "sg:postcode":"N0B 1K0",
    "sg:province":"ON",
    "sg:tags":[
        "church"
    ],
    "wof:name":"Koinonia Christian Fellowship",
    "wof:placetype":"venue"
},
  "geometry": {"coordinates":[-80.462402,43.509655],"type":"Point"}
}