{
  "type": "Feature",
  "properties": {
    "addr:full":"802 Maquinna Pl Zeballos BC V0P 2A0",
    "addr:housenumber":"802",
    "addr:postcode":"v0p 2a0",
    "addr:street":"Maquinna Pl",
    "iso:country":"CA",
    "sg:address":"802 Maquinna Pl",
    "sg:city":"Zeballos",
    "sg:classifiers":[
        {
            "category":"Autos & Motor Vehicles",
            "subcategory":"Fuel & Gas Station",
            "type":"Retail Goods"
        }
    ],
    "sg:phone":"+1 250 761 4201",
    "sg:postcode":"V0P 2A0",
    "sg:province":"BC",
    "sg:tags":[
        "marine"
    ],
    "wof:name":"Weston Enterprises",
    "wof:placetype":"venue"
},
  "geometry": {"coordinates":[-126.845512,49.986698],"type":"Point"}
}