{
  "type": "Feature",
  "properties": {
    "iso:country":"CA",
    "sg:address":"3355 Woodward Blvd",
    "sg:city":"Windsor",
    "sg:classifiers":[
        {
            "category":"Education",
            "subcategory":"School",
            "type":"Public Place"
        }
    ],
    "sg:phone":"+1 519 969 3820",
    "sg:postcode":"N8W 2Y7",
    "sg:province":"ON",
    "wof:name":"St Christopher Elementary Schl",
    "wof:placetype":"venue"
},
  "geometry": {"coordinates":[-82.9825286865,42.27576828],"type":"Point"}
}