{
  "type": "Feature",
  "properties": {
    "addr:full":"3023 Av Beaudry-Leman Shawinigan QC G9N 3H9",
    "addr:housenumber":"3023",
    "addr:postcode":"g9n 3h9",
    "addr:street":"Av Beaudry-Leman",
    "iso:country":"CA",
    "sg:address":"3023 Av Beaudry-Leman",
    "sg:city":"Shawinigan",
    "sg:classifiers":[
        {
            "category":"Restaurant",
            "type":"Food & Drink"
        }
    ],
    "sg:phone":"+1 819 539 4752",
    "sg:postcode":"G9N 3H9",
    "sg:province":"QC",
    "wof:name":"Restaurant Jeannot",
    "wof:placetype":"venue"
},
  "geometry": {"coordinates":[-72.7439193726,46.5659294128],"type":"Point"}
}