{
  "type": "Feature",
  "properties": {
    "addr:full":"3036 Sherman Rd Duncan BC V9L 2B8",
    "addr:housenumber":"3036",
    "addr:postcode":"v9l 2b8",
    "addr:street":"Sherman Rd",
    "iso:country":"CA",
    "sg:address":"3036 Sherman Rd",
    "sg:city":"Duncan",
    "sg:classifiers":[
        {
            "category":"Social Services",
            "subcategory":"Child Care",
            "type":"Services"
        }
    ],
    "sg:phone":"+1 250 746 1655",
    "sg:postcode":"V9L 2B8",
    "sg:province":"BC",
    "wof:name":"We'Re All Sharing Together Inc",
    "wof:placetype":"venue"
},
  "geometry": {"coordinates":[-123.707382,48.779095],"type":"Point"}
}