{
  "type": "Feature",
  "properties": {
    "iso:country":"CA",
    "sg:address":"4 Mckenzie Ave",
    "sg:city":"Hughenden",
    "sg:classifiers":[
        {
            "category":"Food & Beverages",
            "subcategory":"Liquor & Beverages",
            "type":"Retail Goods"
        }
    ],
    "sg:phone":"+1 780 856 2704",
    "sg:postcode":"T0B 2E0",
    "sg:province":"AB",
    "sg:tags":[
        "store"
    ],
    "wof:name":"J D's Liquor & Cold Beer",
    "wof:placetype":"venue"
},
  "geometry": {"coordinates":[-110.968353272,52.5104980469],"type":"Point"}
}