{
  "type": "Feature",
  "properties": {
    "addr:full":"514 5 Ave S Lethbridge AB T1J 0T8",
    "addr:housenumber":"514",
    "addr:postcode":"t1j 0t8",
    "addr:street":"5 Ave S",
    "iso:country":"CA",
    "sg:address":"514 5 Ave S",
    "sg:city":"Lethbridge",
    "sg:classifiers":[
        {
            "category":"Health Services",
            "subcategory":"Doctor",
            "type":"Services"
        }
    ],
    "sg:phone":"+1 403 329 1616",
    "sg:postcode":"T1J 0T8",
    "sg:province":"AB",
    "sg:tags":[
        "dentist"
    ],
    "wof:name":"Fifth Ave Dental Clinic",
    "wof:placetype":"venue"
},
  "geometry": {"coordinates":[-112.839637756,49.6926612854],"type":"Point"}
}