{
  "type": "Feature",
  "properties": {
    "addr:full":"301 Lanor Ave # 7 Etobicoke ON M8W 2R1",
    "addr:housenumber":"301",
    "addr:postcode":"m8w 2r1",
    "addr:street":"Lanor Ave # 7",
    "iso:country":"CA",
    "sg:address":"301 Lanor Ave # 7",
    "sg:city":"Etobicoke",
    "sg:classifiers":[
        {
            "category":"Education",
            "subcategory":"School",
            "type":"Public Place"
        }
    ],
    "sg:phone":"+1 416 259 4445",
    "sg:postcode":"M8W 2R1",
    "sg:province":"ON",
    "wof:name":"New Haven Learning Ctr",
    "wof:placetype":"venue"
},
  "geometry": {"coordinates":[-79.5353851318,43.611000061],"type":"Point"}
}