{
  "type": "Feature",
  "properties": {
    "addr:full":"2344 Bloor St W Toronto ON M6S 1P3",
    "addr:housenumber":"2344",
    "addr:postcode":"m6s 1p3",
    "addr:street":"Bloor St W",
    "iso:country":"CA",
    "sg:address":"2344 Bloor St W",
    "sg:city":"Toronto",
    "sg:classifiers":[
        {
            "category":"Shopping",
            "subcategory":"Jewelry",
            "type":"Retail Goods"
        }
    ],
    "sg:phone":"+1 416 767 9992",
    "sg:postcode":"M6S 1P3",
    "sg:province":"ON",
    "sg:tags":[
        "jeweler"
    ],
    "wof:name":"Mc Lellan Jewellers",
    "wof:placetype":"venue"
},
  "geometry": {"coordinates":[-79.481033,43.650234],"type":"Point"}
}