{
  "type": "Feature",
  "properties": {
    "addr:full":"358 King St Fredericton NB E3B 1E3",
    "addr:housenumber":"358",
    "addr:postcode":"e3b 1e3",
    "addr:street":"King St",
    "iso:country":"CA",
    "sg:address":"358 King St",
    "sg:city":"Fredericton",
    "sg:classifiers":[
        {
            "category":"Personal",
            "subcategory":"Beauty Salon",
            "type":"Services"
        }
    ],
    "sg:phone":"+1 506 459 1356",
    "sg:postcode":"E3B 1E3",
    "sg:province":"NB",
    "wof:name":"Catherine's Aesthetics",
    "wof:placetype":"venue"
},
  "geometry": {"coordinates":[-66.645302,45.962452],"type":"Point"}
}