{
  "type": "Feature",
  "properties": {
    "addr:full":"Delta BC V3M 6Y8",
    "addr:postcode":"v3m 6y8",
    "iso:country":"CA",
    "sg:city":"Delta",
    "sg:classifiers":[
        {
            "category":"Manufacturing",
            "subcategory":"Furniture",
            "type":"Manufacturing & Wholesale Goods"
        }
    ],
    "sg:phone":"+1 604 525 2220",
    "sg:postcode":"V3M 6Y8",
    "sg:province":"BC",
    "sg:tags":[
        "bedding"
    ],
    "wof:name":"Rjs Trading Intl Ltd",
    "wof:placetype":"venue"
},
  "geometry": {"coordinates":[-123.05961600000001,49.084801],"type":"Point"}
}