{
  "type": "Feature",
  "properties": {
    "addr:full":"2347 Inglewood Ave West Vancouver BC V7V 1Z9",
    "addr:housenumber":"2347",
    "addr:postcode":"v7v 1z9",
    "addr:street":"Inglewood Ave",
    "iso:country":"CA",
    "sg:address":"2347 Inglewood Ave",
    "sg:city":"West Vancouver",
    "sg:classifiers":[
        {
            "category":"Organizations",
            "subcategory":"Religious Organization",
            "type":"Services"
        }
    ],
    "sg:phone":"+1 604 926 6881",
    "sg:postcode":"V7V 1Z9",
    "sg:province":"BC",
    "sg:tags":[
        "church"
    ],
    "wof:name":"St Anthony's Parish",
    "wof:placetype":"venue"
},
  "geometry": {"coordinates":[-123.176040649,49.3348388672],"type":"Point"}
}