{
  "type": "Feature",
  "properties": {
    "addr:full":"4559 River Rd W Delta BC V4K 1R9",
    "addr:housenumber":"4559",
    "addr:postcode":"v4k 1r9",
    "addr:street":"River Rd W",
    "iso:country":"CA",
    "sg:address":"4559 River Rd W",
    "sg:city":"Delta",
    "sg:classifiers":[
        {
            "category":"Manufacturing",
            "subcategory":"Food",
            "type":"Manufacturing & Wholesale Goods"
        }
    ],
    "sg:phone":"+1 604 946 1803",
    "sg:postcode":"V4K 1R9",
    "sg:province":"BC",
    "sg:tags":[
        "preserves",
        "jam",
        "jelly"
    ],
    "wof:name":"Lone Willow Wine Jellies",
    "wof:placetype":"venue"
},
  "geometry": {"coordinates":[-123.10250854500001,49.0864906311],"type":"Point"}
}