{
  "type": "Feature",
  "properties": {
    "iso:country":"CA",
    "sg:city":"Vancouver",
    "sg:classifiers":[
        {
            "category":"Manufacturing",
            "subcategory":"Printing",
            "type":"Manufacturing & Wholesale Goods"
        }
    ],
    "sg:phone":"+1 604 688 3358",
    "sg:postcode":"V6A 1T1",
    "sg:province":"BC",
    "sg:tags":[
        "typesetting"
    ],
    "wof:name":"B C Graphic CO Ltd",
    "wof:placetype":"venue"
},
  "geometry": {"coordinates":[-123.10415649399999,49.2803649902],"type":"Point"}
}