{
  "type": "Feature",
  "properties": {
    "iso:country":"CA",
    "sg:address":"111 Colonnade Rd",
    "sg:city":"Nepean",
    "sg:classifiers":[
        {
            "category":"Restaurant",
            "type":"Food & Drink"
        }
    ],
    "sg:phone":"+1 613 226 2881",
    "sg:postcode":"K2E 7M3",
    "sg:province":"ON",
    "sg:tags":[
        "caterer"
    ],
    "wof:name":"Grillman's Fresh Eatery",
    "wof:placetype":"venue"
},
  "geometry": {"coordinates":[-75.7030792236,45.3461303711],"type":"Point"}
}