{
  "type": "Feature",
  "properties": {
    "addr:full":"59 Garden St Simcoe ON N3Y 1C3",
    "addr:housenumber":"59",
    "addr:postcode":"n3y 1c3",
    "addr:street":"Garden St",
    "iso:country":"CA",
    "sg:address":"59 Garden St",
    "sg:city":"Simcoe",
    "sg:classifiers":[
        {
            "category":"Wholesale",
            "subcategory":"Non-durable Goods",
            "type":"Manufacturing & Wholesale Goods"
        }
    ],
    "sg:phone":"+1 519 426 7277",
    "sg:postcode":"N3Y 1C3",
    "sg:province":"ON",
    "sg:tags":[
        "advertising"
    ],
    "wof:name":"B G Specialties",
    "wof:placetype":"venue"
},
  "geometry": {"coordinates":[-80.310104,42.824848],"type":"Point"}
}