{
  "type": "Feature",
  "properties": {
    "addr:full":"Woodville ON K0M 2T0",
    "addr:postcode":"k0m 2t0",
    "iso:country":"CA",
    "sg:city":"Woodville",
    "sg:classifiers":[
        {
            "category":"Professional",
            "subcategory":"Business Services",
            "type":"Services"
        }
    ],
    "sg:phone":"+1 705 439 2589",
    "sg:postcode":"K0M 2T0",
    "sg:province":"ON",
    "sg:tags":[
        "water",
        "treatment"
    ],
    "wof:name":"Jackson Water Conditioning",
    "wof:placetype":"venue"
},
  "geometry": {"coordinates":[-78.9812088013,44.4122924805],"type":"Point"}
}