{
  "type": "Feature",
  "properties": {
    "addr:full":"107 St James St Stirling ON K0K 3E0",
    "addr:housenumber":"107",
    "addr:postcode":"k0k 3e0",
    "addr:street":"St James St",
    "iso:country":"CA",
    "sg:address":"107 St James St",
    "sg:city":"Stirling",
    "sg:classifiers":[
        {
            "category":"Education",
            "subcategory":"School",
            "type":"Public Place"
        }
    ],
    "sg:phone":"+1 613 395 3389",
    "sg:postcode":"K0K 3E0",
    "sg:province":"ON",
    "wof:name":"Stirling Senior School",
    "wof:placetype":"venue"
},
  "geometry": {"coordinates":[-77.5531616211,44.2936592102],"type":"Point"}
}