{
  "type": "Feature",
  "properties": {
    "iso:country":"CA",
    "sg:address":"545 Rue Notre-Dame",
    "sg:city":"Repentigny",
    "sg:classifiers":[
        {
            "category":"Home & Garden",
            "subcategory":"Furniture",
            "type":"Retail Goods"
        }
    ],
    "sg:phone":"+1 450 585 0100",
    "sg:postcode":"J6A 2T6",
    "sg:province":"QC",
    "wof:name":"Piscines 2000 Inc",
    "wof:placetype":"venue"
},
  "geometry": {"coordinates":[-73.4394607544,45.7440719604],"type":"Point"}
}