{
  "type": "Feature",
  "properties": {
    "addr:full":"Penticton BC V2A 4B9",
    "addr:postcode":"v2a 4b9",
    "iso:country":"CA",
    "sg:city":"Penticton",
    "sg:classifiers":[
        {
            "category":"Wholesale",
            "subcategory":"Machinery & Supplies",
            "type":"Manufacturing & Wholesale Goods"
        }
    ],
    "sg:phone":"+1 250 492 4136",
    "sg:postcode":"V2A 4B9",
    "sg:province":"BC",
    "sg:tags":[
        "equipment",
        "welding"
    ],
    "wof:name":"Air Liquide Okanagan",
    "wof:placetype":"venue"
},
  "geometry": {"coordinates":[-119.569618225,49.4808959961],"type":"Point"}
}