{
  "type": "Feature",
  "properties": {
    "iso:country":"CA",
    "sg:city":"Saint-Cyprien",
    "sg:classifiers":[
        {
            "category":"Organizations",
            "subcategory":"Professional Association",
            "type":"Services"
        }
    ],
    "sg:phone":"+1 418 963 3723",
    "sg:postcode":"G0L 2P0",
    "sg:province":"QC",
    "wof:name":"Club DE L'Age D'Or",
    "wof:placetype":"venue"
},
  "geometry": {"coordinates":[-69.01564788819999,47.8925437927],"type":"Point"}
}