{
  "type": "Feature",
  "properties": {
    "addr:full":"1725 Boul DE LA Rive-Sud Saint-Romuald QC G6W 5M6",
    "addr:housenumber":"1725",
    "addr:postcode":"g6w 5m6",
    "addr:street":"Boul De La Rive-Sud",
    "iso:country":"CA",
    "sg:address":"1725 Boul DE LA Rive-Sud",
    "sg:city":"Saint-Romuald",
    "sg:classifiers":[
        {
            "category":"Home & Garden",
            "subcategory":"Carpets & Floor Coverings",
            "type":"Retail Goods"
        }
    ],
    "sg:phone":"+1 418 839 0184",
    "sg:postcode":"G6W 5M6",
    "sg:province":"QC",
    "sg:tags":[
        "dealer",
        "rug"
    ],
    "wof:name":"Tapis DE St-Romuald Inc",
    "wof:placetype":"venue"
},
  "geometry": {"coordinates":[-71.24784099999999,46.744572],"type":"Point"}
}