{
  "type": "Feature",
  "properties": {
    "addr:full":"124 Rue Elizabeth Sorel-Tracy QC J3P 4G9",
    "addr:housenumber":"124",
    "addr:postcode":"j3p 4g9",
    "addr:street":"Rue Elizabeth",
    "iso:country":"CA",
    "sg:address":"124 Rue Elizabeth",
    "sg:city":"Sorel-Tracy",
    "sg:classifiers":[
        {
            "category":"Shopping",
            "subcategory":"Clothing, Apparel, & Fashions",
            "type":"Retail Goods"
        }
    ],
    "sg:phone":"+1 450 743 7150",
    "sg:postcode":"J3P 4G9",
    "sg:province":"QC",
    "wof:name":"Boutique Allure Inc",
    "wof:placetype":"venue"
},
  "geometry": {"coordinates":[-73.1119003296,46.042339325],"type":"Point"}
}