{
  "type": "Feature",
  "properties": {
    "addr:full":"Innisfail AB T4G 1B6",
    "addr:postcode":"t4g 1b6",
    "iso:country":"CA",
    "sg:city":"Innisfail",
    "sg:classifiers":[
        {
            "category":"Shopping",
            "subcategory":"Pharmacy",
            "type":"Retail Goods"
        }
    ],
    "sg:phone":"+1 403 227 1111",
    "sg:postcode":"T4G 1B6",
    "sg:province":"AB",
    "wof:name":"Innisfail Value Drug Mart",
    "wof:placetype":"venue"
},
  "geometry": {"coordinates":[-113.936584473,52.0275840759],"type":"Point"}
}