{
  "type": "Feature",
  "properties": {
    "addr:full":"Apsley ON K0L 1A0",
    "addr:postcode":"k0l 1a0",
    "iso:country":"CA",
    "sg:city":"Apsley",
    "sg:classifiers":[
        {
            "category":"Government",
            "subcategory":"Police Station",
            "type":"Public Place"
        }
    ],
    "sg:phone":"+1 705 656 4431",
    "sg:postcode":"K0L 1A0",
    "sg:province":"ON",
    "sg:tags":[
        "department"
    ],
    "wof:name":"Ontario Provincial Police",
    "wof:placetype":"venue"
},
  "geometry": {"coordinates":[-78.0853729248,44.7530212402],"type":"Point"}
}