{
  "type": "Feature",
  "properties": {
    "addr:full":"Toronto ON M5H 3M7",
    "addr:postcode":"m5h 3m7",
    "iso:country":"CA",
    "sg:city":"Toronto",
    "sg:classifiers":[
        {
            "category":"Mining & Drilling",
            "type":"Manufacturing & Wholesale Goods"
        }
    ],
    "sg:phone":"+1 416 362 2237",
    "sg:postcode":"M5H 3M7",
    "sg:province":"ON",
    "sg:tags":[
        "contractor"
    ],
    "wof:name":"Aber Diamond Corp",
    "wof:placetype":"venue"
},
  "geometry": {"coordinates":[-79.385414,43.649048],"type":"Point"}
}