{
  "type": "Feature",
  "properties": {
    "addr:full":"99 Belmont Dr #4 London ON N6J 4K2",
    "addr:housenumber":"99",
    "addr:postcode":"n6j 4k2",
    "addr:street":"Belmont Dr # 4",
    "iso:country":"CA",
    "sg:address":"99 Belmont Dr #4",
    "sg:city":"London",
    "sg:classifiers":[
        {
            "category":"Autos & Motor Vehicles",
            "subcategory":"Auto Supplies",
            "type":"Retail Goods"
        }
    ],
    "sg:phone":"+1 519 685 7406",
    "sg:postcode":"N6J 4K2",
    "sg:province":"ON",
    "sg:tags":[
        "equipment",
        "racing",
        "car",
        "automobile"
    ],
    "wof:name":"Auto Sport Club",
    "wof:placetype":"venue"
},
  "geometry": {"coordinates":[-81.2606964111,42.9474449158],"type":"Point"}
}