{
  "type": "Feature",
  "properties": {
    "addr:full":"566 Av Du Phare E Matane QC G4W 1B1",
    "addr:housenumber":"566",
    "addr:postcode":"g4w 1b1",
    "addr:street":"Av Du Phare E",
    "iso:country":"CA",
    "sg:address":"566 Av Du Phare E",
    "sg:city":"Matane",
    "sg:classifiers":[
        {
            "category":"Retail",
            "subcategory":"Repair Shop",
            "type":"Services"
        }
    ],
    "sg:phone":"+1 418 562 6637",
    "sg:postcode":"G4W 1B1",
    "sg:province":"QC",
    "sg:tags":[
        "equipment",
        "electronic",
        "supply"
    ],
    "wof:name":"Cmc Electronics",
    "wof:placetype":"venue"
},
  "geometry": {"coordinates":[-67.5100479126,48.8525314331],"type":"Point"}
}