{
  "type": "Feature",
  "properties": {
    "addr:full":"Winnipeg MB R3T 3Y6",
    "addr:postcode":"r3t 3y6",
    "iso:country":"CA",
    "sg:city":"Winnipeg",
    "sg:classifiers":[
        {
            "category":"Shopping",
            "subcategory":"Bicycles & Sporting Goods",
            "type":"Retail Goods"
        }
    ],
    "sg:phone":"+1 204 475 4908",
    "sg:postcode":"R3T 3Y6",
    "sg:province":"MB",
    "wof:name":"Alter Ego Sports",
    "wof:placetype":"venue"
},
  "geometry": {"coordinates":[-97.15139000000001,49.831654],"type":"Point"}
}