{
  "type": "Feature",
  "properties": {
    "addr:full":"Toronto ON M6S 1R6",
    "addr:postcode":"m6s 1r6",
    "iso:country":"CA",
    "sg:city":"Toronto",
    "sg:classifiers":[
        {
            "category":"Shopping",
            "subcategory":"Pharmacy",
            "type":"Retail Goods"
        }
    ],
    "sg:phone":"+1 416 769 7362",
    "sg:postcode":"M6S 1R6",
    "sg:province":"ON",
    "wof:name":"St Mary Old Mill Pharmacy",
    "wof:placetype":"venue"
},
  "geometry": {"coordinates":[-79.48677062989999,43.647819519],"type":"Point"}
}