{
  "type": "Feature",
  "properties": {
    "addr:full":"397 Lyndhurst Rd Lyndhurst ON K0E 1N0",
    "addr:housenumber":"397",
    "addr:postcode":"k0e 1n0",
    "addr:street":"Lyndhurst Rd",
    "iso:country":"CA",
    "sg:address":"397 Lyndhurst Rd",
    "sg:city":"Lyndhurst",
    "sg:classifiers":[
        {
            "category":"Home & Garden",
            "subcategory":"Building Materials",
            "type":"Retail Goods"
        }
    ],
    "sg:phone":"+1 613 928 2828",
    "sg:postcode":"K0E 1N0",
    "sg:province":"ON",
    "sg:tags":[
        "lumber"
    ],
    "wof:name":"R A Warner Building Supplies",
    "wof:placetype":"venue"
},
  "geometry": {"coordinates":[-76.12657900000001,44.548145],"type":"Point"}
}