{
  "type": "Feature",
  "properties": {
    "addr:full":"353 Boul St Laurent Ottawa ON K1K 2Z7",
    "addr:housenumber":"353",
    "addr:postcode":"k1k 2z7",
    "addr:street":"Boul St Laurent",
    "iso:country":"CA",
    "sg:address":"353 Boul St Laurent",
    "sg:city":"Ottawa",
    "sg:classifiers":[
        {
            "category":"Restaurant",
            "type":"Food & Drink"
        }
    ],
    "sg:phone":"+1 613 741 2323",
    "sg:postcode":"K1K 2Z7",
    "sg:province":"ON",
    "sg:tags":[
        "pizza"
    ],
    "wof:name":"St Laurent Pizzeria",
    "wof:placetype":"venue"
},
  "geometry": {"coordinates":[-75.651161,45.449162],"type":"Point"}
}