{
  "type": "Feature",
  "properties": {
    "addr:full":"Surrey BC V3R 8X8",
    "addr:postcode":"v3r 8x8",
    "iso:country":"CA",
    "sg:city":"Surrey",
    "sg:classifiers":[
        {
            "category":"Professional",
            "subcategory":"Advertising",
            "type":"Services"
        }
    ],
    "sg:phone":"+1 604 589 8150",
    "sg:postcode":"V3R 8X8",
    "sg:province":"BC",
    "sg:tags":[
        "mailing",
        "shipping",
        "courier"
    ],
    "wof:name":"Mail Boxes Etc",
    "wof:placetype":"venue"
},
  "geometry": {"coordinates":[-122.800720215,49.1858711243],"type":"Point"}
}