{
  "type": "Feature",
  "properties": {
    "addr:full":"899 Boul Chomedey Laval QC H7V 2X1",
    "addr:housenumber":"899",
    "addr:postcode":"h7v 2x1",
    "addr:street":"Boul Chomedey",
    "iso:country":"CA",
    "sg:address":"899 Boul Chomedey",
    "sg:city":"Laval",
    "sg:classifiers":[
        {
            "category":"Organizations",
            "subcategory":"Religious Organization",
            "type":"Services"
        }
    ],
    "sg:phone":"+1 450 688 3887",
    "sg:postcode":"H7V 2X1",
    "sg:province":"QC",
    "sg:tags":[
        "church"
    ],
    "wof:name":"Holy Name",
    "wof:placetype":"venue"
},
  "geometry": {"coordinates":[-73.74016571040001,45.5459098816],"type":"Point"}
}