{
  "type": "Feature",
  "properties": {
    "addr:full":"3355 Skaha Lake Rd Penticton BC V2A 6G6",
    "addr:postcode":"3355;v2a 6g6",
    "addr:street":"Skaha Lake Rd",
    "iso:country":"CA",
    "sg:address":"3355 Skaha Lake Rd",
    "sg:city":"Penticton",
    "sg:classifiers":[
        {
            "category":"Travel",
            "subcategory":"Hotels & Motels",
            "type":"Entertainment"
        }
    ],
    "sg:phone":"+1 250 492 8422",
    "sg:postcode":"V2A 6G6",
    "sg:province":"BC",
    "wof:name":"Holiday House Motel",
    "wof:placetype":"venue"
},
  "geometry": {"coordinates":[-119.58790588399999,49.4577865601],"type":"Point"}
}