{
  "type": "Feature",
  "properties": {
    "addr:full":"953 St Mary's Rd Winnipeg MB R2M 3R9",
    "addr:housenumber":"953",
    "addr:postcode":"r2m 3r9",
    "addr:street":"St Mary'S Rd",
    "iso:country":"CA",
    "sg:address":"953 St Mary's Rd",
    "sg:city":"Winnipeg",
    "sg:classifiers":[
        {
            "category":"Shopping",
            "subcategory":"Crafts & Fabrics",
            "type":"Retail Goods"
        }
    ],
    "sg:phone":"+1 204 255 3534",
    "sg:postcode":"R2M 3R9",
    "sg:province":"MB",
    "sg:tags":[
        "picture",
        "frame",
        "needlework"
    ],
    "wof:name":"Sheena's Needle-Art Gallery",
    "wof:placetype":"venue"
},
  "geometry": {"coordinates":[-97.11236599999999,49.84288],"type":"Point"}
}