{
  "type": "Feature",
  "properties": {
    "addr:full":"231 Bentley St Markham ON L3R 3L1",
    "addr:housenumber":"231",
    "addr:postcode":"l3r 3l1",
    "addr:street":"Bentley St",
    "iso:country":"CA",
    "sg:address":"231 Bentley St",
    "sg:city":"Markham",
    "sg:classifiers":[
        {
            "category":"Wholesale",
            "subcategory":"Furniture",
            "type":"Manufacturing & Wholesale Goods"
        }
    ],
    "sg:phone":"+1 416 609 9095",
    "sg:postcode":"L3R 3L1",
    "sg:province":"ON",
    "wof:name":"M & L Art Furniture Makers Ltd",
    "wof:placetype":"venue"
},
  "geometry": {"coordinates":[-79.33384700000001,43.829399],"type":"Point"}
}