{
  "type": "Feature",
  "properties": {
    "addr:full":"Coquitlam BC V3E 1J7",
    "addr:postcode":"v3e 1j7",
    "iso:country":"CA",
    "sg:city":"Coquitlam",
    "sg:classifiers":[
        {
            "category":"Health Services",
            "subcategory":"Health Practitioner",
            "type":"Services"
        }
    ],
    "sg:phone":"+1 604 464 1779",
    "sg:postcode":"V3E 1J7",
    "sg:province":"BC",
    "sg:tags":[
        "physiotherapist",
        "therapist",
        "massage"
    ],
    "wof:name":"Tri-City Physiotherapy Ctr",
    "wof:placetype":"venue"
},
  "geometry": {"coordinates":[-122.809547424,49.2838172913],"type":"Point"}
}