{
  "type": "Feature",
  "properties": {
    "addr:full":"PO Box 87561 Rpo Thornhill Sq. Thornhill ON L3T 7R3",
    "addr:housenumber":"po box",
    "addr:postcode":"87561;l3t 7r3",
    "iso:country":"CA",
    "sg:address":"PO Box 87561 Rpo Thornhill Sq.",
    "sg:city":"Thornhill",
    "sg:classifiers":[
        {
            "category":"Wholesale",
            "subcategory":"Groceries",
            "type":"Manufacturing & Wholesale Goods"
        }
    ],
    "sg:phone":"+1 905 881 4256",
    "sg:postcode":"L3T 7R3",
    "sg:province":"ON",
    "sg:tags":[
        "beverage"
    ],
    "wof:name":"Rnh Enterprises",
    "wof:placetype":"venue"
},
  "geometry": {"coordinates":[-79.4235534668,43.8155250549],"type":"Point"}
}