{
  "type": "Feature",
  "properties": {
    "addr:full":"11455 41 Ave NW # 108 Edmonton AB T6J 0T9",
    "addr:housenumber":"11455",
    "addr:postcode":"t6j 0t9",
    "addr:street":"41 Ave Nw # 108",
    "iso:country":"CA",
    "sg:address":"11455 41 Ave NW # 108",
    "sg:city":"Edmonton",
    "sg:classifiers":[
        {
            "category":"Real Estate",
            "subcategory":"Real Estate Operator",
            "type":"Services"
        }
    ],
    "sg:phone":"+1 780 438 5126",
    "sg:postcode":"T6J 0T9",
    "sg:province":"AB",
    "sg:tags":[
        "apartment"
    ],
    "wof:name":"Cedarbrae Gardens",
    "wof:placetype":"venue"
},
  "geometry": {"coordinates":[-113.527938843,53.477519989],"type":"Point"}
}