{
  "type": "Feature",
  "properties": {
    "addr:full":"274 Josephine St Wingham ON N0G 2W0",
    "addr:housenumber":"274",
    "addr:postcode":"n0g 2w0",
    "addr:street":"Josephine St",
    "iso:country":"CA",
    "sg:address":"274 Josephine St",
    "sg:city":"Wingham",
    "sg:classifiers":[
        {
            "category":"Arts & Performance",
            "subcategory":"Theater",
            "type":"Entertainment"
        }
    ],
    "sg:phone":"+1 519 357 4082",
    "sg:postcode":"N0G 2W0",
    "sg:province":"ON",
    "wof:name":"Town Hall Heritage Theatre",
    "wof:placetype":"venue"
},
  "geometry": {"coordinates":[-81.31243133540001,43.8872032166],"type":"Point"}
}