{
  "type": "Feature",
  "properties": {
    "addr:full":"5107 49 St Lacombe AB T4L 1J4",
    "addr:housenumber":"5107",
    "addr:postcode":"t4l 1j4",
    "addr:street":"49 St",
    "iso:country":"CA",
    "sg:address":"5107 49 St",
    "sg:city":"Lacombe",
    "sg:classifiers":[
        {
            "category":"Building & Trades",
            "subcategory":"Electrical",
            "type":"Services"
        }
    ],
    "sg:phone":"+1 403 782 5685",
    "sg:postcode":"T4L 1J4",
    "sg:province":"AB",
    "sg:tags":[
        "electric",
        "contractor"
    ],
    "wof:name":"Aca Electric",
    "wof:placetype":"venue"
},
  "geometry": {"coordinates":[-113.729057,52.46492],"type":"Point"}
}