{
  "type": "Feature",
  "properties": {
    "iso:country":"CA",
    "sg:address":"4750 Av Henri-Julien",
    "sg:city":"Montreal",
    "sg:classifiers":[
        {
            "category":"Restaurant",
            "type":"Food & Drink"
        }
    ],
    "sg:phone":"+1 514 282 3369",
    "sg:postcode":"H2T 2C8",
    "sg:province":"QC",
    "sg:tags":[
        "shop",
        "coffee"
    ],
    "wof:name":"Cafe Vienne",
    "wof:placetype":"venue"
},
  "geometry": {"coordinates":[-73.586426,45.52383],"type":"Point"}
}