{
  "type": "Feature",
  "properties": {
    "addr:full":"1350 Rue Raoul-Charette Joliette QC J6E 8S7",
    "addr:housenumber":"1350",
    "addr:postcode":"j6e 8s7",
    "addr:street":"Rue Raoul-Charette",
    "iso:country":"CA",
    "sg:address":"1350 Rue Raoul-Charette",
    "sg:city":"Joliette",
    "sg:classifiers":[
        {
            "category":"Manufacturing",
            "subcategory":"Food",
            "type":"Manufacturing & Wholesale Goods"
        }
    ],
    "sg:phone":"+1 450 759 3287",
    "sg:postcode":"J6E 8S7",
    "sg:province":"QC",
    "sg:tags":[
        "baker",
        "product",
        "manufacturer"
    ],
    "wof:name":"Boulangerie Multi-Marques Inc",
    "wof:placetype":"venue"
},
  "geometry": {"coordinates":[-73.444984436,46.0068244934],"type":"Point"}
}