{
  "type": "Feature",
  "properties": {
    "addr:full":"232 Rue Sylvestre Repentigny QC J5Y 2A3",
    "addr:housenumber":"232",
    "addr:postcode":"j5y 2a3",
    "addr:street":"Rue Sylvestre",
    "iso:country":"CA",
    "sg:address":"232 Rue Sylvestre",
    "sg:city":"Repentigny",
    "sg:classifiers":[
        {
            "category":"Building & Trades",
            "subcategory":"Electrical",
            "type":"Services"
        }
    ],
    "sg:phone":"+1 514 664 2400",
    "sg:postcode":"J5Y 2A3",
    "sg:province":"QC",
    "sg:tags":[
        "electric",
        "contractor"
    ],
    "wof:name":"Installations Elec Energie-Pls",
    "wof:placetype":"venue"
},
  "geometry": {"coordinates":[-73.433487,45.772045],"type":"Point"}
}