{
  "type": "Feature",
  "properties": {
    "addr:full":"3264 Linwood Rd Roberts Creek BC V0N 2W1",
    "addr:housenumber":"3264",
    "addr:postcode":"v0n 2w1",
    "addr:street":"Linwood Rd",
    "iso:country":"CA",
    "sg:address":"3264 Linwood Rd",
    "sg:city":"Roberts Creek",
    "sg:classifiers":[
        {
            "category":"Retail",
            "subcategory":"Repair Shop",
            "type":"Services"
        }
    ],
    "sg:phone":"+1 604 885 1111",
    "sg:postcode":"V0N 2W1",
    "sg:province":"BC",
    "sg:tags":[
        "equipment",
        "hydraulic"
    ],
    "wof:name":"Mainland Hard Chrome & Hydrlcs",
    "wof:placetype":"venue"
},
  "geometry": {"coordinates":[-123.606461,49.413261],"type":"Point"}
}