{
  "type": "Feature",
  "properties": {
    "addr:full":"3055 Boul DE LA Concorde E Laval QC H7E 2C1",
    "addr:housenumber":"3055",
    "addr:postcode":"h7e 2c1",
    "addr:street":"Boul De La Concorde E",
    "iso:country":"CA",
    "sg:address":"3055 Boul DE LA Concorde E",
    "sg:city":"Laval",
    "sg:classifiers":[
        {
            "category":"Personal",
            "type":"Services"
        }
    ],
    "sg:phone":"+1 450 661 4647",
    "sg:postcode":"H7E 2C1",
    "sg:province":"QC",
    "sg:tags":[
        "therapist",
        "massage"
    ],
    "wof:name":"Cote, Sylvie",
    "wof:placetype":"venue"
},
  "geometry": {"coordinates":[-73.6690444946,45.5923957825],"type":"Point"}
}