{
  "type": "Feature",
  "properties": {
    "addr:full":"687 6 Hwy N Hamilton ON L8N 2Z7",
    "addr:housenumber":"687",
    "addr:postcode":"l8n 2z7",
    "addr:street":"6 Hwy N",
    "iso:country":"CA",
    "sg:address":"687 6 Hwy N",
    "sg:city":"Hamilton",
    "sg:classifiers":[
        {
            "category":"Building & Trades",
            "subcategory":"Equipment Rental",
            "type":"Services"
        }
    ],
    "sg:phone":"+1 905 689 5311",
    "sg:postcode":"L8N 2Z7",
    "sg:province":"ON",
    "sg:tags":[
        "crane"
    ],
    "wof:name":"York Crane Rental Ltd",
    "wof:placetype":"venue"
},
  "geometry": {"coordinates":[-79.9363021851,43.3255386353],"type":"Point"}
}