{
  "type": "Feature",
  "properties": {
    "addr:full":"7380 King George Hwy # 900 Surrey BC V3W 5A5",
    "addr:housenumber":"7380",
    "addr:postcode":"v3w 5a5",
    "addr:street":"King George Hwy # 900",
    "iso:country":"CA",
    "sg:address":"7380 King George Hwy # 900",
    "sg:city":"Surrey",
    "sg:classifiers":[
        {
            "category":"Banks & Credit Unions",
            "subcategory":"Bank",
            "type":"Services"
        }
    ],
    "sg:phone":"+1 604 654 2000",
    "sg:postcode":"V3W 5A5",
    "sg:province":"BC",
    "wof:name":"Community Savings Credit Union",
    "wof:placetype":"venue"
},
  "geometry": {"coordinates":[-122.84568786600001,49.1408309937],"type":"Point"}
}