{
  "type": "Feature",
  "properties": {
    "iso:country":"CA",
    "sg:city":"Barrington",
    "sg:classifiers":[
        {
            "category":"Recreation",
            "type":"Entertainment"
        }
    ],
    "sg:phone":"+1 902 637 1989",
    "sg:postcode":"B0W 1E0",
    "sg:province":"NS",
    "sg:tags":[
        "entertainer",
        "information",
        "activity"
    ],
    "wof:name":"Pinkie the Clown",
    "wof:placetype":"venue"
},
  "geometry": {"coordinates":[-65.6028671265,43.5508918762],"type":"Point"}
}