{
  "type": "Feature",
  "properties": {
    "addr:full":"20 Gore St Kingston ON K7L 2L1",
    "addr:housenumber":"20",
    "addr:postcode":"k7l 2l1",
    "addr:street":"Gore St",
    "iso:country":"CA",
    "sg:address":"20 Gore St",
    "sg:city":"Kingston",
    "sg:classifiers":[
        {
            "category":"Real Estate",
            "subcategory":"Real Estate Operator",
            "type":"Services"
        }
    ],
    "sg:phone":"+1 613 531 1853",
    "sg:postcode":"K7L 2L1",
    "sg:province":"ON",
    "sg:tags":[
        "condominium"
    ],
    "wof:name":"Admiralty Place",
    "wof:placetype":"venue"
},
  "geometry": {"coordinates":[-76.48305499999999,44.225655],"type":"Point"}
}