{
  "type": "Feature",
  "properties": {
    "addr:full":"5239 River Rd Niagara Falls ON L2E 3G9",
    "addr:housenumber":"5239",
    "addr:postcode":"l2e 3g9",
    "addr:street":"River Rd",
    "iso:country":"CA",
    "sg:address":"5239 River Rd",
    "sg:city":"Niagara Falls",
    "sg:classifiers":[
        {
            "category":"Travel",
            "subcategory":"Hotels & Motels",
            "type":"Entertainment"
        }
    ],
    "sg:phone":"+1 905 374 1681",
    "sg:postcode":"L2E 3G9",
    "sg:province":"ON",
    "sg:tags":[
        "breakfast",
        "accommodation",
        "bed"
    ],
    "wof:name":"Lion's Head Bed & Breakfast",
    "wof:placetype":"venue"
},
  "geometry": {"coordinates":[-79.06572,43.098545],"type":"Point"}
}