{
  "type": "Feature",
  "properties": {
    "addr:full":"Niagara Falls ON L2J 1A1",
    "addr:postcode":"l2j 1a1",
    "iso:country":"CA",
    "sg:city":"Niagara Falls",
    "sg:classifiers":[
        {
            "category":"Retail",
            "subcategory":"Auto Repair",
            "type":"Services"
        }
    ],
    "sg:phone":"+1 905 374 8845",
    "sg:postcode":"L2J 1A1",
    "sg:province":"ON",
    "sg:tags":[
        "repairing",
        "automobile"
    ],
    "wof:name":"Stamford Auto Repairs",
    "wof:placetype":"venue"
},
  "geometry": {"coordinates":[-79.0935974121,43.1155204773],"type":"Point"}
}