{
  "type": "Feature",
  "properties": {
    "iso:country":"CA",
    "sg:address":"106 George St",
    "sg:city":"Brantford",
    "sg:classifiers":[
        {
            "category":"Real Estate",
            "subcategory":"Real Estate Agent",
            "type":"Services"
        }
    ],
    "sg:phone":"+1 519 753 0308",
    "sg:postcode":"N3T 2Y4",
    "sg:province":"ON",
    "wof:name":"Brantford Regional Real Est",
    "wof:placetype":"venue"
},
  "geometry": {"coordinates":[-80.26299285890001,43.1426887512],"type":"Point"}
}