{
  "type": "Feature",
  "properties": {
    "addr:full":"741 King St W Kitchener ON N2G 1E3",
    "addr:housenumber":"741",
    "addr:postcode":"n2g 1e3",
    "addr:street":"King St W",
    "iso:country":"CA",
    "sg:address":"741 King St W",
    "sg:city":"Kitchener",
    "sg:classifiers":[
        {
            "category":"Professional",
            "subcategory":"Lawyer & Legal Services",
            "type":"Services"
        }
    ],
    "sg:phone":"+1 519 576 6710",
    "sg:postcode":"N2G 1E3",
    "sg:province":"ON",
    "sg:tags":[
        "attorney"
    ],
    "wof:name":"Hare, Robert J",
    "wof:placetype":"venue"
},
  "geometry": {"coordinates":[-80.506996,43.455498],"type":"Point"}
}