{
  "type": "Feature",
  "properties": {
    "addr:full":"2450 Av Dumas Quebec QC G1L 5A3",
    "addr:housenumber":"2450",
    "addr:postcode":"g1l 5a3",
    "addr:street":"Av Dumas",
    "iso:country":"CA",
    "sg:address":"2450 Av Dumas",
    "sg:city":"Quebec",
    "sg:classifiers":[
        {
            "category":"Freight",
            "type":"Transportation"
        }
    ],
    "sg:phone":"+1 418 622 0697",
    "sg:postcode":"G1L 5A3",
    "sg:province":"QC",
    "sg:tags":[
        "mover"
    ],
    "wof:name":"Transport Dion Gerard Inc",
    "wof:placetype":"venue"
},
  "geometry": {"coordinates":[-71.252274,46.83009],"type":"Point"}
}