{
  "type": "Feature",
  "properties": {
    "addr:full":"225 Rang 2 Saint-Cyprien QC G0L 2P0",
    "addr:housenumber":"225",
    "addr:postcode":"g0l 2p0",
    "addr:street":"Rang 2",
    "iso:country":"CA",
    "sg:address":"225 Rang 2",
    "sg:city":"Saint-Cyprien",
    "sg:classifiers":[
        {
            "category":"Building & Trades",
            "subcategory":"Construction",
            "type":"Services"
        }
    ],
    "sg:phone":"+1 418 383 3242",
    "sg:postcode":"G0L 2P0",
    "sg:province":"QC",
    "sg:tags":[
        "contractor",
        "general"
    ],
    "wof:name":"Construction Scierie Bernard",
    "wof:placetype":"venue"
},
  "geometry": {"coordinates":[-70.202065,46.354435],"type":"Point"}
}