{
  "type": "Feature",
  "properties": {
    "addr:full":"64 East Lake Ave NE Airdrie AB T4A 2G8",
    "addr:housenumber":"64",
    "addr:postcode":"t4a 2g8",
    "addr:street":"East Lake Ave Ne",
    "iso:country":"CA",
    "sg:address":"64 East Lake Ave NE",
    "sg:city":"Airdrie",
    "sg:classifiers":[
        {
            "category":"Travel",
            "subcategory":"Hotels & Motels",
            "type":"Entertainment"
        }
    ],
    "sg:phone":"+1 403 912 1952",
    "sg:postcode":"T4A 2G8",
    "sg:province":"AB",
    "wof:name":"Holiday Inn Express-North",
    "wof:placetype":"venue"
},
  "geometry": {"coordinates":[-113.990844727,51.2963752747],"type":"Point"}
}