{
  "type": "Feature",
  "properties": {
    "addr:full":"PO Box 231 STN Main Cold Lake AB T9M 1P1",
    "addr:housenumber":"po",
    "addr:postcode":"t9m 1p1",
    "addr:street":"Box 231 Stn Main",
    "iso:country":"CA",
    "sg:address":"PO Box 231 STN Main",
    "sg:city":"Cold Lake",
    "sg:classifiers":[
        {
            "category":"Building & Trades",
            "subcategory":"Construction",
            "type":"Services"
        }
    ],
    "sg:phone":"+1 780 594 3973",
    "sg:postcode":"T9M 1P1",
    "sg:province":"AB",
    "sg:tags":[
        "painter"
    ],
    "wof:name":"Leo's Painting Ltd",
    "wof:placetype":"venue"
},
  "geometry": {"coordinates":[-110.17379,54.465027],"type":"Point"}
}