{
  "type": "Feature",
  "properties": {
    "iso:country":"CA",
    "sg:address":"PO Box 231 STN Main",
    "sg:city":"Cold Lake",
    "sg:classifiers":[
        {
            "category":"Building & Trades",
            "subcategory":"Construction",
            "type":"Services"
        }
    ],
    "sg:phone":"+1 780 594 3973",
    "sg:postcode":"T9M 1P1",
    "sg:province":"AB",
    "sg:tags":[
        "painter"
    ],
    "wof:name":"Leo's Painting Ltd",
    "wof:placetype":"venue"
},
  "geometry": {"coordinates":[-110.17379,54.465027],"type":"Point"}
}