{
  "type": "Feature",
  "properties": {
    "addr:full":"4750 Haggart St Vancouver BC V6L 2H8",
    "addr:housenumber":"4750",
    "addr:postcode":"v6l 2h8",
    "addr:street":"Haggart St",
    "iso:country":"CA",
    "sg:address":"4750 Haggart St",
    "sg:city":"Vancouver",
    "sg:classifiers":[
        {
            "category":"Education",
            "subcategory":"School",
            "type":"Public Place"
        }
    ],
    "sg:phone":"+1 604 713 8981",
    "sg:postcode":"V6L 2H8",
    "sg:province":"BC",
    "wof:name":"Prince of Wales Mini School",
    "wof:placetype":"venue"
},
  "geometry": {"coordinates":[-123.15872192400001,49.244102478],"type":"Point"}
}