{
  "type": "Feature",
  "properties": {
    "addr:full":"6083 Mckay Ave Burnaby BC V5H 2W7",
    "addr:housenumber":"6083",
    "addr:postcode":"v5h 2w7",
    "addr:street":"Mckay Ave",
    "iso:country":"CA",
    "sg:address":"6083 Mckay Ave",
    "sg:city":"Burnaby",
    "sg:classifiers":[
        {
            "category":"Travel",
            "subcategory":"Hotels & Motels",
            "type":"Entertainment"
        }
    ],
    "sg:phone":"+1 604 438 1200",
    "sg:postcode":"V5H 2W7",
    "sg:province":"BC",
    "wof:name":"Hilton Vancouver Metrotown",
    "wof:placetype":"venue"
},
  "geometry": {"coordinates":[-123.003540039,49.228931427],"type":"Point"}
}