{
  "type": "Feature",
  "properties": {
    "addr:full":"Toronto ON M5K 1K8",
    "addr:postcode":"m5k 1k8",
    "iso:country":"CA",
    "sg:city":"Toronto",
    "sg:classifiers":[
        {
            "category":"Professional",
            "subcategory":"Lawyer & Legal Services",
            "type":"Services"
        }
    ],
    "sg:phone":"+1 416 362 1011",
    "sg:postcode":"M5K 1K8",
    "sg:province":"ON",
    "sg:tags":[
        "attorney"
    ],
    "wof:name":"Hicks Morley Hamilton Stewart",
    "wof:placetype":"venue"
},
  "geometry": {"coordinates":[-79.53117370610001,43.5981407166],"type":"Point"}
}