{
  "type": "Feature",
  "properties": {
    "addr:full":"912 138 Rte Neuville QC G0A 2R0",
    "addr:housenumber":"138",
    "addr:postcode":"g0a 2r0",
    "addr:street":"Rte Neuville",
    "iso:country":"CA",
    "sg:address":"912 138 Rte",
    "sg:city":"Neuville",
    "sg:classifiers":[
        {
            "category":"Food & Beverages",
            "subcategory":"Groceries & Convenience Stores",
            "type":"Retail Goods"
        }
    ],
    "sg:phone":"+1 418 876 2733",
    "sg:postcode":"G0A 2R0",
    "sg:province":"QC",
    "sg:tags":[
        "grocer"
    ],
    "wof:name":"Accommodation Goguen",
    "wof:placetype":"venue"
},
  "geometry": {"coordinates":[-71.58532700000001,46.696613],"type":"Point"}
}