{
  "type": "Feature",
  "properties": {
    "addr:full":"548 Mackenzie Ave S Williams Lake BC V2G 1E1",
    "addr:housenumber":"548",
    "addr:postcode":"v2g 1e1",
    "addr:street":"Mackenzie Ave S Williams",
    "iso:country":"CA",
    "sg:address":"548 Mackenzie Ave S",
    "sg:city":"Williams Lake",
    "sg:classifiers":[
        {
            "category":"Mining & Drilling",
            "type":"Manufacturing & Wholesale Goods"
        }
    ],
    "sg:phone":"+1 250 392 2979",
    "sg:postcode":"V2G 1E1",
    "sg:province":"BC",
    "sg:tags":[
        "company",
        "oil"
    ],
    "wof:name":"Esso Petroleum Canada",
    "wof:placetype":"venue"
},
  "geometry": {"coordinates":[-122.13909099999999,52.12302],"type":"Point"}
}