{
  "type": "Feature",
  "properties": {
    "iso:country":"CA",
    "sg:address":"15 Toulinquet St",
    "sg:city":"Twillingate",
    "sg:classifiers":[
        {
            "category":"Insurance",
            "subcategory":"Insurance Agent",
            "type":"Services"
        }
    ],
    "sg:phone":"+1 709 884 2118",
    "sg:postcode":"A0G 4M0",
    "sg:province":"NL",
    "wof:name":"Wedgwood Insurance Ltd",
    "wof:placetype":"venue"
},
  "geometry": {"coordinates":[-54.7759742737,49.6569213867],"type":"Point"}
}