{
  "type": "Feature",
  "properties": {
    "addr:full":"2115 Rue Lamothe Drummondville QC J2B 7B7",
    "addr:housenumber":"2115",
    "addr:postcode":"j2b 7b7",
    "addr:street":"Rue Lamothe",
    "iso:country":"CA",
    "sg:address":"2115 Rue Lamothe",
    "sg:city":"Drummondville",
    "sg:classifiers":[
        {
            "category":"Wholesale",
            "subcategory":"Electrical",
            "type":"Manufacturing & Wholesale Goods"
        }
    ],
    "sg:phone":"+1 819 478 3128",
    "sg:postcode":"J2B 7B7",
    "sg:province":"QC",
    "sg:tags":[
        "equipment",
        "electric",
        "supply"
    ],
    "wof:name":"Marnel International Inc",
    "wof:placetype":"venue"
},
  "geometry": {"coordinates":[-72.49587200000001,45.860607],"type":"Point"}
}