{
  "type": "Feature",
  "properties": {
    "addr:full":"10832 62 Ave NW Edmonton AB T6H 1N1",
    "addr:housenumber":"10832",
    "addr:postcode":"t6h 1n1",
    "addr:street":"62 Ave Nw",
    "iso:country":"CA",
    "sg:address":"10832 62 Ave NW",
    "sg:city":"Edmonton",
    "sg:classifiers":[
        {
            "category":"Social Services",
            "type":"Services"
        }
    ],
    "sg:phone":"+1 780 435 9515",
    "sg:postcode":"T6H 1N1",
    "sg:province":"AB",
    "sg:tags":[
        "organization",
        "welfare"
    ],
    "wof:name":"Southwest Senior Outreach Soc",
    "wof:placetype":"venue"
},
  "geometry": {"coordinates":[-113.510239,53.499302],"type":"Point"}
}