{
  "type": "Feature",
  "properties": {
    "iso:country":"CA",
    "sg:address":"20875 Dalton Rd",
    "sg:city":"Sutton West",
    "sg:classifiers":[
        {
            "category":"Home & Garden",
            "subcategory":"Hardware",
            "type":"Retail Goods"
        }
    ],
    "sg:phone":"+1 905 722 6575",
    "sg:postcode":"L0E 1R0",
    "sg:province":"ON",
    "wof:name":"Sutton Home Hardware",
    "wof:placetype":"venue"
},
  "geometry": {"coordinates":[-79.3653259277,44.3105659485],"type":"Point"}
}