{
  "type": "Feature",
  "properties": {
    "addr:full":"1886 Dundas St E Mississauga ON L4X 1L9",
    "addr:housenumber":"1886",
    "addr:postcode":"l4x 1l9",
    "addr:street":"Dundas St E",
    "iso:country":"CA",
    "sg:address":"1886 Dundas St E",
    "sg:city":"Mississauga",
    "sg:classifiers":[
        {
            "category":"Travel",
            "subcategory":"Hotels & Motels",
            "type":"Entertainment"
        }
    ],
    "sg:phone":"+1 905 273 9500",
    "sg:postcode":"L4X 1L9",
    "sg:province":"ON",
    "wof:name":"Monte Carlo Motel",
    "wof:placetype":"venue"
},
  "geometry": {"coordinates":[-79.5717468262,43.6203575134],"type":"Point"}
}