{
  "type": "Feature",
  "properties": {
    "addr:full":"10519 King George Hwy Surrey BC V3T 2X1",
    "addr:housenumber":"10519",
    "addr:postcode":"v3t 2x1",
    "addr:street":"King George Hwy",
    "iso:country":"CA",
    "sg:address":"10519 King George Hwy",
    "sg:city":"Surrey",
    "sg:classifiers":[
        {
            "category":"Building & Trades",
            "subcategory":"Construction",
            "type":"Services"
        }
    ],
    "sg:phone":"+1 604 584 9626",
    "sg:postcode":"V3T 2X1",
    "sg:province":"BC",
    "sg:tags":[
        "tile",
        "dealer"
    ],
    "wof:name":"Surrey Tile Ltd",
    "wof:placetype":"venue"
},
  "geometry": {"coordinates":[-122.845466614,49.1916389465],"type":"Point"}
}