{
  "type": "Feature",
  "properties": {
    "addr:full":"110 Millwick Dr North York ON M9L 1Y3",
    "addr:housenumber":"110",
    "addr:postcode":"m9l 1y3",
    "addr:street":"Millwick Dr",
    "iso:country":"CA",
    "sg:address":"110 Millwick Dr",
    "sg:city":"North York",
    "sg:classifiers":[
        {
            "category":"Autos & Motor Vehicles",
            "subcategory":"Automobile Sales",
            "type":"Retail Goods"
        }
    ],
    "sg:phone":"+1 416 746 8686",
    "sg:postcode":"M9L 1Y3",
    "sg:province":"ON",
    "sg:tags":[
        "car",
        "dealer"
    ],
    "wof:name":"World Used Cars",
    "wof:placetype":"venue"
},
  "geometry": {"coordinates":[-79.564743042,43.7602272034],"type":"Point"}
}