{
  "type": "Feature",
  "properties": {
    "addr:full":"2450 Cranbrook St N Cranbrook BC V1C 3T4",
    "addr:housenumber":"2450",
    "addr:postcode":"v1c 3t4",
    "addr:street":"Cranbrook St N",
    "iso:country":"CA",
    "sg:address":"2450 Cranbrook St N",
    "sg:city":"Cranbrook",
    "sg:classifiers":[
        {
            "category":"Building & Trades",
            "subcategory":"Construction",
            "type":"Services"
        }
    ],
    "sg:phone":"+1 250 426 5254",
    "sg:postcode":"V1C 3T4",
    "sg:province":"BC",
    "sg:tags":[
        "concrete",
        "cutting",
        "rental",
        "breaking",
        "sawing"
    ],
    "wof:name":"Sandor Rental Equipment Ltd",
    "wof:placetype":"venue"
},
  "geometry": {"coordinates":[-115.739868164,49.5356712341],"type":"Point"}
}