{
  "type": "Feature",
  "properties": {
    "iso:country":"CA",
    "sg:address":"555 Albert St",
    "sg:city":"Regina",
    "sg:classifiers":[
        {
            "category":"Retail",
            "subcategory":"Auto Repair",
            "type":"Services"
        }
    ],
    "sg:phone":"+1 306 949 3800",
    "sg:postcode":"S4R 2P2",
    "sg:province":"SK",
    "sg:tags":[
        "glass",
        "installation",
        "automobile"
    ],
    "wof:name":"Advance Glass & Mirror Ltd",
    "wof:placetype":"venue"
},
  "geometry": {"coordinates":[-104.61779,50.469639],"type":"Point"}
}