{
  "type": "Feature",
  "properties": {
    "addr:full":"Calgary AB T2N 2A1",
    "addr:postcode":"t2n 2a1",
    "iso:country":"CA",
    "sg:city":"Calgary",
    "sg:classifiers":[
        {
            "category":"Health Services",
            "subcategory":"Health Practitioner",
            "type":"Services"
        }
    ],
    "sg:phone":"+1 403 283 0770",
    "sg:postcode":"T2N 2A1",
    "sg:province":"AB",
    "sg:tags":[
        "counseling",
        "psychologist"
    ],
    "wof:name":"Lorraine Andriuk Psychological",
    "wof:placetype":"venue"
},
  "geometry": {"coordinates":[-114.09496307400001,51.0568504333],"type":"Point"}
}