{
  "type": "Feature",
  "properties": {
    "addr:full":"Richmond BC V6X 3V7",
    "addr:postcode":"v6x 3v7",
    "iso:country":"CA",
    "sg:city":"Richmond",
    "sg:classifiers":[
        {
            "category":"Restaurant",
            "type":"Food & Drink"
        }
    ],
    "sg:phone":"+1 604 276 0205",
    "sg:postcode":"V6X 3V7",
    "sg:province":"BC",
    "wof:name":"Ikku Tel Japanese Restaurant",
    "wof:placetype":"venue"
},
  "geometry": {"coordinates":[-123.136261,49.181854],"type":"Point"}
}