{
  "type": "Feature",
  "properties": {
    "addr:full":"200 Aberdeen Ave Woodbridge ON L4L 1C4",
    "addr:housenumber":"200",
    "addr:postcode":"l4l 1c4",
    "addr:street":"Aberdeen Ave",
    "iso:country":"CA",
    "sg:address":"200 Aberdeen Ave",
    "sg:city":"Woodbridge",
    "sg:classifiers":[
        {
            "category":"Education",
            "subcategory":"School",
            "type":"Public Place"
        }
    ],
    "sg:phone":"+1 905 851 2859",
    "sg:postcode":"L4L 1C4",
    "sg:province":"ON",
    "wof:name":"St Francis of Assisi School",
    "wof:placetype":"venue"
},
  "geometry": {"coordinates":[-79.5707778931,43.8004951477],"type":"Point"}
}