{
  "type": "Feature",
  "properties": {
    "addr:full":"4695 Boul Grande-Allee Brossard QC J4Z 3E9",
    "addr:housenumber":"4695",
    "addr:postcode":"j4z 3e9",
    "addr:street":"Boul Grande-Allee",
    "iso:country":"CA",
    "sg:address":"4695 Boul Grande-Allee",
    "sg:city":"Brossard",
    "sg:classifiers":[
        {
            "category":"Restaurant",
            "type":"Food & Drink"
        }
    ],
    "sg:phone":"+1 450 656 7658",
    "sg:postcode":"J4Z 3E9",
    "sg:province":"QC",
    "wof:name":"Combos Express",
    "wof:placetype":"venue"
},
  "geometry": {"coordinates":[-73.4552230835,45.4826087952],"type":"Point"}
}