{
  "type": "Feature",
  "properties": {
    "iso:country":"CA",
    "sg:address":"92 Bertram Blvd",
    "sg:city":"Belleville",
    "sg:classifiers":[
        {
            "category":"Shopping",
            "subcategory":"Clothing, Apparel, & Fashions",
            "type":"Retail Goods"
        }
    ],
    "sg:phone":"+1 613 968 3333",
    "sg:postcode":"K8N 4C3",
    "sg:province":"ON",
    "sg:tags":[
        "wig",
        "toupee",
        "hairpiece"
    ],
    "wof:name":"Henry's Hairstyling",
    "wof:placetype":"venue"
},
  "geometry": {"coordinates":[-77.364944458,44.1732978821],"type":"Point"}
}