{
  "type": "Feature",
  "properties": {
    "addr:full":"1307 Longview Dr Peterborough ON K9J 6X4",
    "addr:housenumber":"1307",
    "addr:postcode":"k9j 6x4",
    "addr:street":"Longview Dr",
    "iso:country":"CA",
    "sg:address":"1307 Longview Dr",
    "sg:city":"Peterborough",
    "sg:classifiers":[
        {
            "category":"Arts & Performance",
            "subcategory":"Theater",
            "type":"Entertainment"
        }
    ],
    "sg:phone":"+1 705 743 7354",
    "sg:postcode":"K9J 6X4",
    "sg:province":"ON",
    "sg:tags":[
        "bureau"
    ],
    "wof:name":"Rocklands Talent & Management",
    "wof:placetype":"venue"
},
  "geometry": {"coordinates":[-78.32131200000001,44.300732],"type":"Point"}
}