{
  "type": "Feature",
  "properties": {
    "addr:full":"15 Clover Leaf St Woodbridge ON L4L 5M2",
    "addr:housenumber":"15",
    "addr:postcode":"l4l 5m2",
    "addr:street":"Clover Leaf St",
    "iso:country":"CA",
    "sg:address":"15 Clover Leaf St",
    "sg:city":"Woodbridge",
    "sg:classifiers":[
        {
            "category":"Retail",
            "subcategory":"Portrait Studio",
            "type":"Services"
        }
    ],
    "sg:phone":"+1 905 851 8294",
    "sg:postcode":"L4L 5M2",
    "sg:province":"ON",
    "sg:tags":[
        "photographer"
    ],
    "wof:name":"Sid Calzavara Photography",
    "wof:placetype":"venue"
},
  "geometry": {"coordinates":[-79.57034299999999,43.791779],"type":"Point"}
}