{
  "type": "Feature",
  "properties": {
    "iso:country":"CA",
    "sg:address":"15 Clover Leaf St",
    "sg:city":"Woodbridge",
    "sg:classifiers":[
        {
            "category":"Retail",
            "subcategory":"Portrait Studio",
            "type":"Services"
        }
    ],
    "sg:phone":"+1 905 851 8294",
    "sg:postcode":"L4L 5M2",
    "sg:province":"ON",
    "sg:tags":[
        "photographer"
    ],
    "wof:name":"Sid Calzavara Photography",
    "wof:placetype":"venue"
},
  "geometry": {"coordinates":[-79.570343,43.791779],"type":"Point"}
}