{
  "type": "Feature",
  "properties": {
    "addr:full":"2111 Kingsway Vancouver BC V5N 2T4",
    "addr:housenumber":"2111",
    "addr:postcode":"v5n 2t4",
    "addr:street":"Kingsway",
    "iso:country":"CA",
    "sg:address":"2111 Kingsway",
    "sg:city":"Vancouver",
    "sg:classifiers":[
        {
            "category":"Home & Garden",
            "subcategory":"Furniture",
            "type":"Retail Goods"
        }
    ],
    "sg:phone":"+1 604 717 1198",
    "sg:postcode":"V5N 2T4",
    "sg:province":"BC",
    "wof:name":"High Sun Mattress Factory",
    "wof:placetype":"venue"
},
  "geometry": {"coordinates":[-123.063271,49.244438],"type":"Point"}
}