{
  "type": "Feature",
  "properties": {
    "addr:full":"47 Cartier Cres Scarborough ON M1P 3N7",
    "addr:housenumber":"47",
    "addr:postcode":"m1p 3n7",
    "addr:street":"Cartier Cres",
    "iso:country":"CA",
    "sg:address":"47 Cartier Cres",
    "sg:city":"Scarborough",
    "sg:classifiers":[
        {
            "category":"Education",
            "subcategory":"Special Training",
            "type":"Public Place"
        }
    ],
    "sg:phone":"+1 416 755 7320",
    "sg:postcode":"M1P 3N7",
    "sg:province":"ON",
    "sg:tags":[
        "art",
        "school",
        "graphic",
        "instruction",
        "designer"
    ],
    "wof:name":"E B Designers & Consultants",
    "wof:placetype":"venue"
},
  "geometry": {"coordinates":[-79.2665176392,43.7624015808],"type":"Point"}
}