{
  "type": "Feature",
  "properties": {
    "addr:full":"1201 Fairview St #6 Burlington ON L7S 1Y5",
    "addr:housenumber":"1201",
    "addr:postcode":"l7s 1y5",
    "addr:street":"Fairview St # 6",
    "iso:country":"CA",
    "sg:address":"1201 Fairview St #6",
    "sg:city":"Burlington",
    "sg:classifiers":[
        {
            "category":"Retail",
            "subcategory":"Auto Repair",
            "type":"Services"
        }
    ],
    "sg:phone":"+1 905 634 3456",
    "sg:postcode":"L7S 1Y5",
    "sg:province":"ON",
    "sg:tags":[
        "automobile",
        "lubrication"
    ],
    "wof:name":"Pennzoil 10 Minute Oil Change",
    "wof:placetype":"venue"
},
  "geometry": {"coordinates":[-79.8213195801,43.3291473389],"type":"Point"}
}