{
  "type": "Feature",
  "properties": {
    "addr:full":"69 Hartzell Rd St Catharines ON L2P 1M6",
    "addr:housenumber":"69",
    "addr:postcode":"l2p 1m6",
    "addr:street":"Hartzell Rd",
    "iso:country":"CA",
    "sg:address":"69 Hartzell Rd",
    "sg:city":"St Catharines",
    "sg:classifiers":[
        {
            "category":"Personal",
            "subcategory":"Beauty Salon",
            "type":"Services"
        }
    ],
    "sg:phone":"+1 905 685 0160",
    "sg:postcode":"L2P 1M6",
    "sg:province":"ON",
    "wof:name":"Brendan's Hairstyling & Barber",
    "wof:placetype":"venue"
},
  "geometry": {"coordinates":[-79.214516,43.154217],"type":"Point"}
}