{
  "type": "Feature",
  "properties": {
    "iso:country":"CA",
    "sg:address":"26 Old Colony Trail",
    "sg:city":"Guelph",
    "sg:classifiers":[
        {
            "category":"Banks & Credit Unions",
            "subcategory":"Investment Brokerage",
            "type":"Services"
        }
    ],
    "sg:phone":"+1 519 821 5444",
    "sg:postcode":"N1G 4A4",
    "sg:province":"ON",
    "sg:tags":[
        "consultant",
        "planning",
        "financial"
    ],
    "wof:name":"Fundex Investments Inc",
    "wof:placetype":"venue"
},
  "geometry": {"coordinates":[-80.240334,43.509151],"type":"Point"}
}