{
  "type": "Feature",
  "properties": {
    "iso:country":"CA",
    "sg:city":"Tavistock",
    "sg:classifiers":[
        {
            "category":"Building & Trades",
            "subcategory":"Electrical",
            "type":"Services"
        }
    ],
    "sg:phone":"+1 519 655 6802",
    "sg:postcode":"N0B 2R0",
    "sg:province":"ON",
    "sg:tags":[
        "electric",
        "contractor"
    ],
    "wof:name":"Crescent Ridge Svc",
    "wof:placetype":"venue"
},
  "geometry": {"coordinates":[-80.8363494873,43.3213920593],"type":"Point"}
}