{
  "type": "Feature",
  "properties": {
    "addr:full":"4747 30 St SE Calgary AB T2B 3K5",
    "addr:housenumber":"4747",
    "addr:postcode":"t2b 3k5",
    "addr:street":"30 St Se",
    "iso:country":"CA",
    "sg:address":"4747 30 St SE",
    "sg:city":"Calgary",
    "sg:classifiers":[
        {
            "category":"Organizations",
            "subcategory":"Religious Organization",
            "type":"Services"
        }
    ],
    "sg:phone":"+1 403 273 0866",
    "sg:postcode":"T2B 3K5",
    "sg:province":"AB",
    "sg:tags":[
        "church"
    ],
    "wof:name":"Portuguese Community Ctr",
    "wof:placetype":"venue"
},
  "geometry": {"coordinates":[-113.98912,51.011887],"type":"Point"}
}