{
  "type": "Feature",
  "properties": {
    "iso:country":"CA",
    "sg:address":"125 Centre St",
    "sg:city":"Vulcan",
    "sg:classifiers":[
        {
            "category":"Banks & Credit Unions",
            "subcategory":"Investment Brokerage",
            "type":"Services"
        }
    ],
    "sg:phone":"+1 403 485 2526",
    "sg:postcode":"T0L 2B0",
    "sg:province":"AB",
    "sg:tags":[
        "consultant",
        "planning",
        "financial"
    ],
    "wof:name":"Deitz Financial Svc",
    "wof:placetype":"venue"
},
  "geometry": {"coordinates":[-113.259544373,50.4051704407],"type":"Point"}
}