{
  "type": "Feature",
  "properties": {
    "addr:full":"310 6th Ave Rapid City MB R0K 1W0",
    "addr:housenumber":"310",
    "addr:postcode":"r0k 1w0",
    "addr:street":"6Th Ave",
    "iso:country":"CA",
    "sg:address":"310 6th Ave",
    "sg:city":"Rapid City",
    "sg:classifiers":[
        {
            "category":"Building & Trades",
            "subcategory":"Construction",
            "type":"Services"
        }
    ],
    "sg:phone":"+1 204 826 2492",
    "sg:postcode":"R0K 1W0",
    "sg:province":"MB",
    "sg:tags":[
        "home",
        "improvement"
    ],
    "wof:name":"Op/Knox Enterprises",
    "wof:placetype":"venue"
},
  "geometry": {"coordinates":[-100.037285,50.119984],"type":"Point"}
}