{
  "type": "Feature",
  "properties": {
    "addr:full":"213 W Old N Thompson Hwy Clearwater BC V0E 1N0",
    "addr:housenumber":"213",
    "addr:postcode":"v0e 1n0",
    "addr:street":"W Old N Thompson Hwy",
    "iso:country":"CA",
    "sg:address":"213 W Old N Thompson Hwy",
    "sg:city":"Clearwater",
    "sg:classifiers":[
        {
            "category":"Home & Garden",
            "subcategory":"Building Materials",
            "type":"Retail Goods"
        }
    ],
    "sg:phone":"+1 250 674 3386",
    "sg:postcode":"V0E 1N0",
    "sg:province":"BC",
    "wof:name":"Irly Building Ctr",
    "wof:placetype":"venue"
},
  "geometry": {"coordinates":[-120.034820557,51.6509246826],"type":"Point"}
}