{
  "type": "Feature",
  "properties": {
    "addr:full":"220 Bradford St Barrie ON L4N 3B6",
    "addr:housenumber":"220",
    "addr:postcode":"l4n 3b6",
    "addr:street":"Bradford St",
    "iso:country":"CA",
    "sg:address":"220 Bradford St",
    "sg:city":"Barrie",
    "sg:classifiers":[
        {
            "category":"Autos & Motor Vehicles",
            "subcategory":"Automobile Sales",
            "type":"Retail Goods"
        }
    ],
    "sg:phone":"+1 705 728 5430",
    "sg:postcode":"L4N 3B6",
    "sg:province":"ON",
    "sg:tags":[
        "car",
        "dealer"
    ],
    "wof:name":"Honest Joe's Motors Ltd",
    "wof:placetype":"venue"
},
  "geometry": {"coordinates":[-79.69282531739999,44.376209259],"type":"Point"}
}