{
  "type": "Feature",
  "properties": {
    "addr:full":"95 Creditstone Rd Concord ON L4K 1N3",
    "addr:housenumber":"95",
    "addr:postcode":"l4k 1n3",
    "addr:street":"Creditstone Rd",
    "iso:country":"CA",
    "sg:address":"95 Creditstone Rd",
    "sg:city":"Concord",
    "sg:classifiers":[
        {
            "category":"Retail",
            "subcategory":"Auto Repair",
            "type":"Services"
        }
    ],
    "sg:phone":"+1 905 669 1064",
    "sg:postcode":"L4K 1N3",
    "sg:province":"ON",
    "sg:tags":[
        "truck"
    ],
    "wof:name":"Johns Truck Repair Ctr Ltd",
    "wof:placetype":"venue"
},
  "geometry": {"coordinates":[-79.516418,43.790768],"type":"Point"}
}