{
  "type": "Feature",
  "properties": {
    "addr:full":"15077 Marine Dr White Rock BC V4B 1C5",
    "addr:housenumber":"15077",
    "addr:postcode":"v4b 1c5",
    "addr:street":"Marine Dr",
    "iso:country":"CA",
    "sg:address":"15077 Marine Dr",
    "sg:city":"White Rock",
    "sg:classifiers":[
        {
            "category":"Restaurant",
            "type":"Food & Drink"
        }
    ],
    "sg:phone":"+1 604 542 5191",
    "sg:postcode":"V4B 1C5",
    "sg:province":"BC",
    "wof:name":"Bichos Mexican Taste",
    "wof:placetype":"venue"
},
  "geometry": {"coordinates":[-122.804626,49.021175],"type":"Point"}
}