{
  "type": "Feature",
  "properties": {
    "addr:full":"4324 Boul Du Royaume Jonquiere QC G7X 7V5",
    "addr:housenumber":"4324",
    "addr:postcode":"g7x 7v5",
    "addr:street":"Boul Du Royaume",
    "iso:country":"CA",
    "sg:address":"4324 Boul Du Royaume",
    "sg:city":"Jonquiere",
    "sg:classifiers":[
        {
            "category":"Autos & Motor Vehicles",
            "subcategory":"Auto Supplies",
            "type":"Retail Goods"
        }
    ],
    "sg:phone":"+1 418 547 6619",
    "sg:postcode":"G7X 7V5",
    "sg:province":"QC",
    "sg:tags":[
        "tire"
    ],
    "wof:name":"Mega Pneu",
    "wof:placetype":"venue"
},
  "geometry": {"coordinates":[-71.2790603638,48.4213104248],"type":"Point"}
}