{
  "type": "Feature",
  "properties": {
    "addr:full":"3821 Lake Shore Blvd W Etobicoke ON M8W 1R2",
    "addr:housenumber":"3821",
    "addr:postcode":"m8w 1r2",
    "addr:street":"Lake Shore Blvd W",
    "iso:country":"CA",
    "sg:address":"3821 Lake Shore Blvd W",
    "sg:city":"Etobicoke",
    "sg:classifiers":[
        {
            "category":"Cinema",
            "subcategory":"Movie Rental",
            "type":"Entertainment"
        }
    ],
    "sg:phone":"+1 416 255 7442",
    "sg:postcode":"M8W 1R2",
    "sg:province":"ON",
    "sg:tags":[
        "leasing",
        "video",
        "disc",
        "tape"
    ],
    "wof:name":"Adults Unlimited",
    "wof:placetype":"venue"
},
  "geometry": {"coordinates":[-79.5432128906,43.591999054],"type":"Point"}
}