{
  "type": "Feature",
  "properties": {
    "iso:country":"CA",
    "sg:address":"139 Grand River St N",
    "sg:city":"Paris",
    "sg:classifiers":[
        {
            "category":"Health Services",
            "subcategory":"Clinic",
            "type":"Services"
        }
    ],
    "sg:phone":"+1 519 442 0734",
    "sg:postcode":"N3L 2M4",
    "sg:province":"ON",
    "sg:tags":[
        "equipment",
        "hospital",
        "therapy",
        "oxygen",
        "supply"
    ],
    "wof:name":"Medigas",
    "wof:placetype":"venue"
},
  "geometry": {"coordinates":[-80.3846817017,43.1950302124],"type":"Point"}
}