{
  "type": "Feature",
  "properties": {
    "addr:full":"Enderby BC V0E 1V0",
    "addr:postcode":"v0e 1v0",
    "iso:country":"CA",
    "sg:city":"Enderby",
    "sg:classifiers":[
        {
            "category":"Health Services",
            "subcategory":"Doctor",
            "type":"Services"
        }
    ],
    "sg:phone":"+1 250 838 9494",
    "sg:postcode":"V0E 1V0",
    "sg:province":"BC",
    "sg:tags":[
        "physician",
        "surgeon"
    ],
    "wof:name":"Enderby Medical Clinic",
    "wof:placetype":"venue"
},
  "geometry": {"coordinates":[-119.14025116000001,50.5495529175],"type":"Point"}
}