{
  "type": "Feature",
  "properties": {
    "iso:country":"CA",
    "sg:address":"97 Simmonds Dr",
    "sg:city":"Dartmouth",
    "sg:classifiers":[
        {
            "category":"Wholesale",
            "subcategory":"Machinery & Supplies",
            "type":"Manufacturing & Wholesale Goods"
        }
    ],
    "sg:phone":"+1 902 468 1210",
    "sg:postcode":"B3B 1N7",
    "sg:province":"NS",
    "sg:tags":[
        "equipment",
        "material",
        "truck",
        "handling"
    ],
    "wof:name":"Prime Material Handling",
    "wof:placetype":"venue"
},
  "geometry": {"coordinates":[-63.5997848511,44.7173843384],"type":"Point"}
}