{
  "type": "Feature",
  "properties": {
    "iso:country":"CA",
    "sg:address":"59 Deer Lane Close SE",
    "sg:city":"Calgary",
    "sg:classifiers":[
        {
            "category":"Retail",
            "subcategory":"Animal Services",
            "type":"Services"
        }
    ],
    "sg:phone":"+1 403 278 7541",
    "sg:postcode":"T2J 5X8",
    "sg:province":"AB",
    "sg:tags":[
        "pet",
        "grooming",
        "washing"
    ],
    "wof:name":"Pat's Puppy Parlour",
    "wof:placetype":"venue"
},
  "geometry": {"coordinates":[-114.008033752,50.9236030579],"type":"Point"}
}