{
  "type": "Feature",
  "properties": {
    "addr:full":"3580 4th Ave Port Alberni BC V9Y 4H4",
    "addr:housenumber":"3580",
    "addr:postcode":"v9y 4h4",
    "addr:street":"4Th Ave",
    "iso:country":"CA",
    "sg:address":"3580 4th Ave",
    "sg:city":"Port Alberni",
    "sg:classifiers":[
        {
            "category":"Retail",
            "subcategory":"Auto Repair",
            "type":"Services"
        }
    ],
    "sg:phone":"+1 250 723 5133",
    "sg:postcode":"V9Y 4H4",
    "sg:province":"BC",
    "sg:tags":[
        "repairing",
        "automobile"
    ],
    "wof:name":"Denis Hiway Svc",
    "wof:placetype":"venue"
},
  "geometry": {"coordinates":[-124.806335,49.241447],"type":"Point"}
}