{
  "type": "Feature",
  "properties": {
    "iso:country":"CA",
    "sg:address":"14527 Parkland Blvd SE",
    "sg:city":"Calgary",
    "sg:classifiers":[
        {
            "category":"Shopping",
            "subcategory":"Gifts & Souvenirs",
            "type":"Retail Goods"
        }
    ],
    "sg:phone":"+1 403 271 8496",
    "sg:postcode":"T2J 4M6",
    "sg:province":"AB",
    "sg:tags":[
        "glass",
        "art",
        "blown"
    ],
    "wof:name":"All That Glass",
    "wof:placetype":"venue"
},
  "geometry": {"coordinates":[-114.02597045900001,50.9207115173],"type":"Point"}
}