{
  "type": "Feature",
  "properties": {
    "addr:full":"80 Ward St Toronto ON M6H 4A6",
    "addr:housenumber":"80",
    "addr:postcode":"m6h 4a6",
    "addr:street":"Ward St",
    "iso:country":"CA",
    "sg:address":"80 Ward St",
    "sg:city":"Toronto",
    "sg:classifiers":[
        {
            "category":"Home & Garden",
            "subcategory":"Furniture",
            "type":"Retail Goods"
        }
    ],
    "sg:phone":"+1 416 531 6635",
    "sg:postcode":"M6H 4A6",
    "sg:province":"ON",
    "sg:tags":[
        "builder",
        "custom"
    ],
    "wof:name":"Built Work Design",
    "wof:placetype":"venue"
},
  "geometry": {"coordinates":[-79.4468078613,43.6639404297],"type":"Point"}
}