{
  "type": "Feature",
  "properties": {
    "iso:country":"CA",
    "sg:city":"Toronto",
    "sg:classifiers":[
        {
            "category":"Education",
            "subcategory":"Special Training",
            "type":"Public Place"
        }
    ],
    "sg:phone":"+1 416 928 6888",
    "sg:postcode":"M4W 2L2",
    "sg:province":"ON",
    "sg:tags":[
        "school",
        "language"
    ],
    "wof:name":"Language Studies Intl",
    "wof:placetype":"venue"
},
  "geometry": {"coordinates":[-79.3899230957,43.6784706116],"type":"Point"}
}