{
  "type": "Feature",
  "properties": {
    "addr:full":"280 Rue Sabrique Saint-Sebastien-DE-Frontenac QC G0Y 1M0",
    "addr:housenumber":"280",
    "addr:postcode":"g0y 1m0",
    "addr:street":"Rue Sabrique Saint-Sebastien-De-Frontenac",
    "iso:country":"CA",
    "sg:address":"280 Rue Sabrique",
    "sg:city":"Saint-Sebastien-DE-Frontenac",
    "sg:classifiers":[
        {
            "category":"Organizations",
            "subcategory":"Religious Organization",
            "type":"Services"
        }
    ],
    "sg:phone":"+1 819 652 2020",
    "sg:postcode":"G0Y 1M0",
    "sg:province":"QC",
    "sg:tags":[
        "church"
    ],
    "wof:name":"Eglise St Sebastien",
    "wof:placetype":"venue"
},
  "geometry": {"coordinates":[-70.84272,45.572762],"type":"Point"}
}