{
  "type": "Feature",
  "properties": {
    "addr:full":"6001 52 Ave Bonnyville AB T9N 2M3",
    "addr:housenumber":"6001",
    "addr:postcode":"t9n 2m3",
    "addr:street":"52 Ave",
    "iso:country":"CA",
    "sg:address":"6001 52 Ave",
    "sg:city":"Bonnyville",
    "sg:classifiers":[
        {
            "category":"Autos & Motor Vehicles",
            "subcategory":"Auto Supplies",
            "type":"Retail Goods"
        }
    ],
    "sg:phone":"+1 780 826 6859",
    "sg:postcode":"T9N 2M3",
    "sg:province":"AB",
    "sg:tags":[
        "repairing",
        "automobile"
    ],
    "wof:name":"Kal Tire",
    "wof:placetype":"venue"
},
  "geometry": {"coordinates":[-110.769272,54.270466],"type":"Point"}
}