{
  "type": "Feature",
  "properties": {
    "addr:full":"5275 Bradner Rd Abbotsford BC V4X 2P1",
    "addr:housenumber":"5275",
    "addr:postcode":"v4x 2p1",
    "addr:street":"Bradner Rd",
    "iso:country":"CA",
    "sg:address":"5275 Bradner Rd",
    "sg:city":"Abbotsford",
    "sg:classifiers":[
        {
            "category":"Organizations",
            "subcategory":"Religious Organization",
            "type":"Services"
        }
    ],
    "sg:phone":"+1 604 856 0304",
    "sg:postcode":"V4X 2P1",
    "sg:province":"BC",
    "sg:tags":[
        "church"
    ],
    "wof:name":"Bradner Presbyterian Church",
    "wof:placetype":"venue"
},
  "geometry": {"coordinates":[-122.42665863000001,49.0979766846],"type":"Point"}
}