{
  "type": "Feature",
  "properties": {
    "addr:full":"8001 Weston Rd Woodbridge ON L4L 9C8",
    "addr:housenumber":"8001",
    "addr:postcode":"l4l 9c8",
    "addr:street":"Weston Rd",
    "iso:country":"CA",
    "sg:address":"8001 Weston Rd",
    "sg:city":"Woodbridge",
    "sg:classifiers":[
        {
            "category":"Professional",
            "subcategory":"Business Services",
            "type":"Services"
        }
    ],
    "sg:phone":"+1 905 264 1774",
    "sg:postcode":"L4L 9C8",
    "sg:province":"ON",
    "wof:name":"Grape Brands Ltd",
    "wof:placetype":"venue"
},
  "geometry": {"coordinates":[-79.5488586426,43.7958602905],"type":"Point"}
}