{
  "type": "Feature",
  "properties": {
    "iso:country":"CA",
    "sg:address":"26688 56 Ave",
    "sg:city":"Langley",
    "sg:classifiers":[
        {
            "category":"Manufacturing",
            "subcategory":"Rubber & Plastics",
            "type":"Manufacturing & Wholesale Goods"
        }
    ],
    "sg:phone":"+1 604 607 6000",
    "sg:postcode":"V4W 3X5",
    "sg:province":"BC",
    "sg:tags":[
        "product"
    ],
    "wof:name":"Redwood Plastics Corp",
    "wof:placetype":"venue"
},
  "geometry": {"coordinates":[-122.485466003,49.1036300659],"type":"Point"}
}