{
  "type": "Feature",
  "properties": {
    "addr:full":"Hwy 35 Manning AB T0H 2M0",
    "addr:postcode":"t0h 2m0",
    "addr:street":"Hwy 35",
    "iso:country":"CA",
    "sg:address":"Hwy 35",
    "sg:city":"Manning",
    "sg:phone":"+1 780 836 2872",
    "sg:postcode":"T0H 2M0",
    "sg:province":"AB",
    "sg:tags":[
        "fuel",
        "aviation"
    ],
    "wof:name":"Swan Aeromotive Ltd",
    "wof:placetype":"venue"
},
  "geometry": {"coordinates":[-117.624786,56.931015],"type":"Point"}
}