{
  "type": "Feature",
  "properties": {
    "addr:full":"North York ON M2J 4T1",
    "addr:postcode":"m2j 4t1",
    "iso:country":"CA",
    "sg:city":"North York",
    "sg:classifiers":[
        {
            "category":"Manufacturing",
            "subcategory":"Printing",
            "type":"Manufacturing & Wholesale Goods"
        }
    ],
    "sg:phone":"+1 416 494 1066",
    "sg:postcode":"M2J 4T1",
    "sg:province":"ON",
    "sg:tags":[
        "publisher"
    ],
    "wof:name":"Powershift Communications Inc",
    "wof:placetype":"venue"
},
  "geometry": {"coordinates":[-79.3424,43.779739],"type":"Point"}
}