{
  "type": "Feature",
  "properties": {
    "addr:full":"20 Iron Ore Hill Rd Jacksonville NB E7M 3H5",
    "addr:housenumber":"20",
    "addr:postcode":"e7m 3h5",
    "addr:street":"Iron Ore Hill Rd",
    "iso:country":"CA",
    "sg:address":"20 Iron Ore Hill Rd",
    "sg:city":"Jacksonville",
    "sg:classifiers":[
        {
            "category":"Retail",
            "subcategory":"Auto Repair",
            "type":"Services"
        }
    ],
    "sg:phone":"+1 506 328 9509",
    "sg:postcode":"E7M 3H5",
    "sg:province":"NB",
    "sg:tags":[
        "truck"
    ],
    "wof:name":"Anderson Enterprises Ltd",
    "wof:placetype":"venue"
},
  "geometry": {"coordinates":[-67.622337,46.197159],"type":"Point"}
}