{
  "type": "Feature",
  "properties": {
    "addr:full":"385 the West Mall Etobicoke ON M9C 1E7",
    "addr:housenumber":"385",
    "addr:postcode":"m9c 1e7",
    "addr:street":"The West Mall",
    "iso:country":"CA",
    "sg:address":"385 the West Mall",
    "sg:city":"Etobicoke",
    "sg:classifiers":[
        {
            "category":"Bars & Pubs",
            "type":"Food & Drink"
        }
    ],
    "sg:phone":"+1 416 621 9010",
    "sg:postcode":"M9C 1E7",
    "sg:province":"ON",
    "sg:tags":[
        "club",
        "night"
    ],
    "wof:name":"Dior",
    "wof:placetype":"venue"
},
  "geometry": {"coordinates":[-79.56568900000001,43.642101],"type":"Point"}
}