{
  "type": "Feature",
  "properties": {
    "iso:country":"CA",
    "sg:city":"Laurier-Station",
    "sg:classifiers":[
        {
            "category":"Government",
            "subcategory":"Office",
            "type":"Public Place"
        }
    ],
    "sg:phone":"+1 418 728 5015",
    "sg:postcode":"G0S 1N0",
    "sg:province":"QC",
    "wof:name":"Canada Deputes Federaux",
    "wof:placetype":"venue"
},
  "geometry": {"coordinates":[-71.6310958862,46.5385513306],"type":"Point"}
}