{
  "type": "Feature",
  "properties": {
    "addr:full":"159 Ch Pembina Trail Ste Agathe MB R0G 1Y0",
    "addr:housenumber":"159",
    "addr:postcode":"r0g 1y0",
    "addr:street":"Ch Pembina Trail Ste Agathe",
    "iso:country":"CA",
    "sg:address":"159 Ch Pembina Trail",
    "sg:city":"Ste Agathe",
    "sg:classifiers":[
        {
            "category":"Professional",
            "subcategory":"Management & Consulting",
            "type":"Services"
        }
    ],
    "sg:phone":"+1 204 882 2153",
    "sg:postcode":"R0G 1Y0",
    "sg:province":"MB",
    "sg:tags":[
        "development",
        "economic",
        "agency"
    ],
    "wof:name":"Parc Riel Ind Park",
    "wof:placetype":"venue"
},
  "geometry": {"coordinates":[-97.146591,49.600487],"type":"Point"}
}