{
  "type": "Feature",
  "properties": {
    "addr:full":"3050 106 St NW Edmonton AB T6J 5M5",
    "addr:housenumber":"3050",
    "addr:postcode":"t6j 5m5",
    "addr:street":"106 St Nw",
    "iso:country":"CA",
    "sg:address":"3050 106 St NW",
    "sg:city":"Edmonton",
    "sg:classifiers":[
        {
            "category":"Restaurant",
            "type":"Food & Drink"
        }
    ],
    "sg:phone":"+1 780 496 9999",
    "sg:postcode":"T6J 5M5",
    "sg:province":"AB",
    "wof:name":"Domino's Pizza",
    "wof:placetype":"venue"
},
  "geometry": {"coordinates":[-113.501991,53.46249],"type":"Point"}
}