{
  "type": "Feature",
  "properties": {
    "addr:full":"3460 Rue Peel Montreal QC H3A 2M1",
    "addr:housenumber":"3460",
    "addr:postcode":"h3a 2m1",
    "addr:street":"Rue Peel",
    "iso:country":"CA",
    "sg:address":"3460 Rue Peel",
    "sg:city":"Montreal",
    "sg:classifiers":[
        {
            "category":"Organizations",
            "subcategory":"Labor Organization",
            "type":"Services"
        }
    ],
    "sg:phone":"+1 514 849 2009",
    "sg:postcode":"H3A 2M1",
    "sg:province":"QC",
    "wof:name":"Syndicat Des Travailleurs",
    "wof:placetype":"venue"
},
  "geometry": {"coordinates":[-73.57759094239999,45.5023002625],"type":"Point"}
}