{
  "type": "Feature",
  "properties": {
    "iso:country":"CA",
    "sg:address":"657176 15th Line",
    "sg:city":"Tavistock",
    "sg:classifiers":[
        {
            "category":"Shopping",
            "subcategory":"Clothing, Apparel, & Fashions",
            "type":"Retail Goods"
        }
    ],
    "sg:phone":"+1 519 655 2085",
    "sg:postcode":"N0B 2R0",
    "sg:province":"ON",
    "sg:tags":[
        "shop",
        "fabric"
    ],
    "wof:name":"Cindy's Fabric Shop",
    "wof:placetype":"venue"
},
  "geometry": {"coordinates":[-80.808846,43.32959],"type":"Point"}
}