{
  "type": "Feature",
  "properties": {
    "addr:full":"Saskatoon SK S7H 0W2",
    "addr:postcode":"s7h 0w2",
    "iso:country":"CA",
    "sg:city":"Saskatoon",
    "sg:classifiers":[
        {
            "category":"Travel",
            "subcategory":"Travel Agent",
            "type":"Entertainment"
        }
    ],
    "sg:phone":"+1 306 373 9633",
    "sg:postcode":"S7H 0W2",
    "sg:province":"SK",
    "sg:tags":[
        "agency",
        "bureau"
    ],
    "wof:name":"Jubilee Travel",
    "wof:placetype":"venue"
},
  "geometry": {"coordinates":[-106.606132507,52.1145210266],"type":"Point"}
}