{
  "type": "Feature",
  "properties": {
    "addr:full":"24 Kaliska Dr Picture Butte AB T0K 1V0",
    "addr:housenumber":"24",
    "addr:postcode":"t0k 1v0",
    "addr:street":"Kaliska Dr",
    "iso:country":"CA",
    "sg:address":"24 Kaliska Dr",
    "sg:city":"Picture Butte",
    "sg:classifiers":[
        {
            "category":"Building & Trades",
            "subcategory":"Electrical",
            "type":"Services"
        }
    ],
    "sg:phone":"+1 403 732 5506",
    "sg:postcode":"T0K 1V0",
    "sg:province":"AB",
    "sg:tags":[
        "electric",
        "contractor"
    ],
    "wof:name":"Peter Bell Electric Ltd",
    "wof:placetype":"venue"
},
  "geometry": {"coordinates":[-112.77497863799999,49.8659057617],"type":"Point"}
}