{
  "type": "Feature",
  "properties": {
    "addr:full":"White Rock BC V4B 2L1",
    "addr:postcode":"v4b 2l1",
    "iso:country":"CA",
    "sg:city":"White Rock",
    "sg:classifiers":[
        {
            "category":"Health Services",
            "subcategory":"Clinic",
            "type":"Services"
        }
    ],
    "sg:phone":"+1 604 541 0606",
    "sg:postcode":"V4B 2L1",
    "sg:province":"BC",
    "sg:tags":[
        "agency",
        "welfare"
    ],
    "wof:name":"Alzheimer Society of BC",
    "wof:placetype":"venue"
},
  "geometry": {"coordinates":[-122.79995700000001,49.02737],"type":"Point"}
}