{
  "type": "Feature",
  "properties": {
    "iso:country":"CA",
    "sg:address":"19 Fifth Ave",
    "sg:city":"Sioux Lookout",
    "sg:classifiers":[
        {
            "category":"Shopping",
            "subcategory":"Stationery & Office Supplies",
            "type":"Retail Goods"
        }
    ],
    "sg:phone":"+1 807 737 1292",
    "sg:postcode":"P8T 1B9",
    "sg:province":"ON",
    "wof:name":"Wilson's Business Solutions",
    "wof:placetype":"venue"
},
  "geometry": {"coordinates":[-91.91928863530001,50.0935173035],"type":"Point"}
}