{
  "type": "Feature",
  "properties": {
    "addr:full":"1427 Penage Rd Whitefish ON P0M 3E0",
    "addr:housenumber":"1427",
    "addr:postcode":"p0m 3e0",
    "addr:street":"Penage Rd",
    "iso:country":"CA",
    "sg:address":"1427 Penage Rd",
    "sg:city":"Whitefish",
    "sg:classifiers":[
        {
            "category":"Mining & Drilling",
            "type":"Manufacturing & Wholesale Goods"
        }
    ],
    "sg:phone":"+1 705 866 2262",
    "sg:postcode":"P0M 3E0",
    "sg:province":"ON",
    "sg:tags":[
        "saw"
    ],
    "wof:name":"Vancon Marketing",
    "wof:placetype":"venue"
},
  "geometry": {"coordinates":[-81.31559753419999,46.3781814575],"type":"Point"}
}