{
  "type": "Feature",
  "properties": {
    "addr:full":"5925 Rue Belanger Saint-Leonard QC H1T 1G8",
    "addr:housenumber":"5925",
    "addr:postcode":"h1t 1g8",
    "addr:street":"Rue Belanger",
    "iso:country":"CA",
    "sg:address":"5925 Rue Belanger",
    "sg:city":"Saint-Leonard",
    "sg:classifiers":[
        {
            "category":"Personal",
            "type":"Services"
        }
    ],
    "sg:phone":"+1 514 899 9967",
    "sg:postcode":"H1T 1G8",
    "sg:province":"QC",
    "sg:tags":[
        "electrolysis"
    ],
    "wof:name":"Clinique DE Beaute Yolande",
    "wof:placetype":"venue"
},
  "geometry": {"coordinates":[-73.57177734379999,45.5839614868],"type":"Point"}
}