{
  "type": "Feature",
  "properties": {
    "addr:full":"42 Main St Carberry MB R0K 0H0",
    "addr:housenumber":"42",
    "addr:postcode":"r0k 0h0",
    "addr:street":"Main St",
    "iso:country":"CA",
    "sg:address":"42 Main St",
    "sg:city":"Carberry",
    "sg:classifiers":[
        {
            "category":"Food & Beverages",
            "subcategory":"Bakery",
            "type":"Retail Goods"
        }
    ],
    "sg:phone":"+1 204 834 2414",
    "sg:postcode":"R0K 0H0",
    "sg:province":"MB",
    "sg:tags":[
        "baker"
    ],
    "wof:name":"Modern Bakery",
    "wof:placetype":"venue"
},
  "geometry": {"coordinates":[-99.359093,49.868328],"type":"Point"}
}