{
  "type": "Feature",
  "properties": {
    "addr:full":"10973 138 St NW Edmonton AB T5M 1P3",
    "addr:housenumber":"10973",
    "addr:postcode":"t5m 1p3",
    "addr:street":"138 St Nw",
    "iso:country":"CA",
    "sg:address":"10973 138 St NW",
    "sg:city":"Edmonton",
    "sg:classifiers":[
        {
            "category":"Professional",
            "subcategory":"Engineering",
            "type":"Services"
        }
    ],
    "sg:phone":"+1 780 454 0884",
    "sg:postcode":"T5M 1P3",
    "sg:province":"AB",
    "sg:tags":[
        "engineer"
    ],
    "wof:name":"Laviolette Engineering Ltd",
    "wof:placetype":"venue"
},
  "geometry": {"coordinates":[-113.559685,53.557049],"type":"Point"}
}