{
  "type": "Feature",
  "properties": {
    "addr:full":"Quebec QC G2J 1C2",
    "addr:postcode":"g2j 1c2",
    "iso:country":"CA",
    "sg:city":"Quebec",
    "sg:classifiers":[
        {
            "category":"Wholesale",
            "subcategory":"Farm Supplies",
            "type":"Manufacturing & Wholesale Goods"
        }
    ],
    "sg:phone":"+1 418 623 9013",
    "sg:postcode":"G2J 1C2",
    "sg:province":"QC",
    "sg:tags":[
        "pet",
        "food"
    ],
    "wof:name":"Nutrition Animale Ap Inc",
    "wof:placetype":"venue"
},
  "geometry": {"coordinates":[-71.27310900000001,46.834042],"type":"Point"}
}