{
  "type": "Feature",
  "properties": {
    "iso:country":"CA",
    "sg:address":"124 Lower Truro Rd",
    "sg:city":"Truro",
    "sg:classifiers":[
        {
            "category":"Retail",
            "subcategory":"Auto Repair",
            "type":"Services"
        }
    ],
    "sg:phone":"+1 902 895 0511",
    "sg:postcode":"B2N 5E8",
    "sg:province":"NS",
    "sg:tags":[
        "truck",
        "wrecker"
    ],
    "wof:name":"Mac Kay's Truck & Trailer Ctr",
    "wof:placetype":"venue"
},
  "geometry": {"coordinates":[-63.3081359863,45.3598442078],"type":"Point"}
}