{
  "type": "Feature",
  "properties": {
    "addr:full":"369 Mary St Wiarton ON N0H 2T0",
    "addr:housenumber":"369",
    "addr:postcode":"n0h 2t0",
    "addr:street":"Mary St",
    "iso:country":"CA",
    "sg:address":"369 Mary St",
    "sg:city":"Wiarton",
    "sg:classifiers":[
        {
            "category":"Health Services",
            "subcategory":"Doctor",
            "type":"Services"
        }
    ],
    "sg:phone":"+1 519 534 2411",
    "sg:postcode":"N0H 2T0",
    "sg:province":"ON",
    "sg:tags":[
        "physician",
        "surgeon"
    ],
    "wof:name":"Barker, E J MD",
    "wof:placetype":"venue"
},
  "geometry": {"coordinates":[-81.1386566162,44.7383003235],"type":"Point"}
}