{
  "type": "Feature",
  "properties": {
    "addr:full":"Delta BC V4E 2A9",
    "addr:postcode":"v4e 2a9",
    "iso:country":"CA",
    "sg:city":"Delta",
    "sg:classifiers":[
        {
            "category":"Shopping",
            "subcategory":"Clothing, Apparel, & Fashions",
            "type":"Retail Goods"
        }
    ],
    "sg:phone":"+1 604 597 0029",
    "sg:postcode":"V4E 2A9",
    "sg:province":"BC",
    "sg:tags":[
        "accessory"
    ],
    "wof:name":"Ardene",
    "wof:placetype":"venue"
},
  "geometry": {"coordinates":[-122.890556,49.131149],"type":"Point"}
}