{
  "type": "Feature",
  "properties": {
    "addr:full":"1548 Dundas St London ON N5W 3C1",
    "addr:housenumber":"1548",
    "addr:postcode":"n5w 3c1",
    "addr:street":"Dundas St",
    "iso:country":"CA",
    "sg:address":"1548 Dundas St",
    "sg:city":"London",
    "sg:classifiers":[
        {
            "category":"Restaurant",
            "type":"Food & Drink"
        }
    ],
    "sg:phone":"+1 519 453 6460",
    "sg:postcode":"N5W 3C1",
    "sg:province":"ON",
    "sg:tags":[
        "pizza"
    ],
    "wof:name":"Domino's Pizza",
    "wof:placetype":"venue"
},
  "geometry": {"coordinates":[-81.19399300000001,42.999767],"type":"Point"}
}