{
  "type": "Feature",
  "properties": {
    "addr:full":"Vancouver BC V5Z 1A5",
    "addr:postcode":"v5z 1a5",
    "iso:country":"CA",
    "sg:city":"Vancouver",
    "sg:classifiers":[
        {
            "category":"Communications",
            "subcategory":"Film & Video Production",
            "type":"Services"
        }
    ],
    "sg:phone":"+1 604 877 2299",
    "sg:postcode":"V5Z 1A5",
    "sg:province":"BC",
    "sg:tags":[
        "taping"
    ],
    "wof:name":"A 24 Frames Film & Video Inc",
    "wof:placetype":"venue"
},
  "geometry": {"coordinates":[-123.12086499999999,49.265816],"type":"Point"}
}