{
  "type": "Feature",
  "properties": {
    "addr:full":"Calgary AB T2P 1G3",
    "addr:postcode":"t2p 1g3",
    "iso:country":"CA",
    "sg:city":"Calgary",
    "sg:classifiers":[
        {
            "category":"Utilities",
            "subcategory":"Mobile Phone",
            "type":"Services"
        }
    ],
    "sg:phone":"+1 403 264 2244",
    "sg:postcode":"T2P 1G3",
    "sg:province":"AB",
    "sg:tags":[
        "telephone",
        "cellular"
    ],
    "wof:name":"Downtown Wireless",
    "wof:placetype":"venue"
},
  "geometry": {"coordinates":[-114.072006,51.04567],"type":"Point"}
}