{
  "type": "Feature",
  "properties": {
    "addr:full":"Calgary AB T2C 1J7",
    "addr:postcode":"t2c 1j7",
    "iso:country":"CA",
    "sg:city":"Calgary",
    "sg:classifiers":[
        {
            "category":"Building & Trades",
            "subcategory":"Construction",
            "type":"Services"
        }
    ],
    "sg:phone":"+1 403 279 4411",
    "sg:postcode":"T2C 1J7",
    "sg:province":"AB",
    "sg:tags":[
        "maker",
        "cabinet"
    ],
    "wof:name":"H & L Woodcraft Ltd",
    "wof:placetype":"venue"
},
  "geometry": {"coordinates":[-113.98584,50.982796],"type":"Point"}
}