{
  "type": "Feature",
  "properties": {
    "addr:full":"Whitehorse YT Y1A 2B9",
    "addr:postcode":"y1a 2b9",
    "iso:country":"CA",
    "sg:city":"Whitehorse",
    "sg:classifiers":[
        {
            "category":"Food & Beverages",
            "subcategory":"Specialty",
            "type":"Retail Goods"
        }
    ],
    "sg:phone":"+1 867 667 4372",
    "sg:postcode":"Y1A 2B9",
    "sg:province":"YT",
    "sg:tags":[
        "health",
        "diet"
    ],
    "wof:name":"Aroma Borealis",
    "wof:placetype":"venue"
},
  "geometry": {"coordinates":[-135.05859375,60.7186470032],"type":"Point"}
}