{
  "type": "Feature",
  "properties": {
    "addr:full":"Bell Island NL A0A 4H0",
    "addr:postcode":"a0a 4h0",
    "iso:country":"CA",
    "sg:city":"Bell Island",
    "sg:classifiers":[
        {
            "category":"Shopping",
            "subcategory":"Catalog Store",
            "type":"Retail Goods"
        }
    ],
    "sg:phone":"+1 709 488 2838",
    "sg:postcode":"A0A 4H0",
    "sg:province":"NL",
    "sg:tags":[
        "mail",
        "order",
        "internet"
    ],
    "wof:name":"Sears Canada Inc",
    "wof:placetype":"venue"
},
  "geometry": {"coordinates":[-52.9490699768,47.6229782104],"type":"Point"}
}