{
  "type": "Feature",
  "properties": {
    "iso:country":"CA",
    "sg:city":"Brampton",
    "sg:classifiers":[
        {
            "category":"Real Estate",
            "subcategory":"Real Estate Operator",
            "type":"Services"
        }
    ],
    "sg:phone":"+1 905 451 3535",
    "sg:postcode":"L6Y 1T8",
    "sg:province":"ON",
    "sg:tags":[
        "apartment"
    ],
    "wof:name":"Serrento Towers",
    "wof:placetype":"venue"
},
  "geometry": {"coordinates":[-79.7497634888,43.6746749878],"type":"Point"}
}