{
  "type": "Feature",
  "properties": {
    "addr:full":"72 Main St Picton ON K0K 2T0",
    "addr:housenumber":"72",
    "addr:postcode":"k0k 2t0",
    "addr:street":"Main St",
    "iso:country":"CA",
    "sg:address":"72 Main St",
    "sg:city":"Picton",
    "sg:classifiers":[
        {
            "category":"Restaurant",
            "type":"Food & Drink"
        }
    ],
    "sg:phone":"+1 613 476 2288",
    "sg:postcode":"K0K 2T0",
    "sg:province":"ON",
    "wof:name":"Schooners' Fish & Chips",
    "wof:placetype":"venue"
},
  "geometry": {"coordinates":[-77.148422,44.00428],"type":"Point"}
}