{
  "type": "Feature",
  "properties": {
    "addr:full":"30 Rue DE L'Eglise Nord Lacolle QC J0J 1J0",
    "addr:housenumber":"30",
    "addr:postcode":"j0j 1j0",
    "addr:street":"Rue De L'Eglise Nord",
    "iso:country":"CA",
    "sg:address":"30 Rue DE L'Eglise Nord",
    "sg:city":"Lacolle",
    "sg:classifiers":[
        {
            "category":"Real Estate",
            "subcategory":"Real Estate Agent",
            "type":"Services"
        }
    ],
    "sg:phone":"+1 450 246 2644",
    "sg:postcode":"J0J 1J0",
    "sg:province":"QC",
    "wof:name":"Re/Max",
    "wof:placetype":"venue"
},
  "geometry": {"coordinates":[-73.3726882935,45.0825958252],"type":"Point"}
}