{
  "type": "Feature",
  "properties": {
    "iso:country":"CA",
    "sg:city":"Westmount",
    "sg:classifiers":[
        {
            "category":"Wholesale",
            "subcategory":"Durable Goods & Equipment",
            "type":"Manufacturing & Wholesale Goods"
        }
    ],
    "sg:phone":"+1 514 931 7677",
    "sg:postcode":"H3Z 1J9",
    "sg:province":"QC",
    "sg:tags":[
        "exporter"
    ],
    "wof:name":"Audax Perishables Intl Inc",
    "wof:placetype":"venue"
},
  "geometry": {"coordinates":[-73.5875091553,45.4884033203],"type":"Point"}
}