{
  "type": "Feature",
  "properties": {
    "addr:full":"1469 Princess St Kingston ON K7M 3E9",
    "addr:housenumber":"1469",
    "addr:postcode":"k7m 3e9",
    "addr:street":"Princess St",
    "iso:country":"CA",
    "sg:address":"1469 Princess St",
    "sg:city":"Kingston",
    "sg:classifiers":[
        {
            "category":"Shopping",
            "subcategory":"Used Merchandise",
            "type":"Retail Goods"
        }
    ],
    "sg:phone":"+1 613 545 9780",
    "sg:postcode":"K7M 3E9",
    "sg:province":"ON",
    "sg:tags":[
        "second",
        "store",
        "hand"
    ],
    "wof:name":"Goodwill",
    "wof:placetype":"venue"
},
  "geometry": {"coordinates":[-76.53382873539999,44.2518692017],"type":"Point"}
}