{
  "type": "Feature",
  "properties": {
    "addr:full":"Fisher Branch MB R0C 0Z0",
    "addr:postcode":"r0c 0z0",
    "iso:country":"CA",
    "sg:city":"Fisher Branch",
    "sg:classifiers":[
        {
            "category":"Shopping",
            "subcategory":"Clothing, Apparel, & Fashions",
            "type":"Retail Goods"
        }
    ],
    "sg:phone":"+1 204 372 8593",
    "sg:postcode":"R0C 0Z0",
    "sg:province":"MB",
    "wof:name":"S & L Clothing",
    "wof:placetype":"venue"
},
  "geometry": {"coordinates":[-97.61844600000001,51.0826],"type":"Point"}
}