{
  "type": "Feature",
  "properties": {
    "addr:full":"RR 2 Auburn ON N0M 1E0",
    "addr:postcode":"n0m 1e0",
    "addr:street":"Rr 2",
    "iso:country":"CA",
    "sg:address":"RR 2",
    "sg:city":"Auburn",
    "sg:classifiers":[
        {
            "category":"Government",
            "subcategory":"Office",
            "type":"Public Place"
        }
    ],
    "sg:phone":"+1 519 526 7231",
    "sg:postcode":"N0M 1E0",
    "sg:province":"ON",
    "wof:name":"County of Huron Mntnc Garage",
    "wof:placetype":"venue"
},
  "geometry": {"coordinates":[-81.5352935791,43.7744216919],"type":"Point"}
}