{
  "type": "Feature",
  "properties": {
    "addr:full":"115 Rue DE Martigny O Saint-Jerome QC J7Y 2G2",
    "addr:housenumber":"115",
    "addr:postcode":"j7y 2g2",
    "addr:street":"Rue De Martigny O Saint-Jerome",
    "iso:country":"CA",
    "sg:address":"115 Rue DE Martigny O",
    "sg:city":"Saint-Jerome",
    "sg:classifiers":[
        {
            "category":"Shopping",
            "subcategory":"Used Merchandise",
            "type":"Retail Goods"
        }
    ],
    "sg:phone":"+1 450 431 1861",
    "sg:postcode":"J7Y 2G2",
    "sg:province":"QC",
    "sg:tags":[
        "clothing"
    ],
    "wof:name":"P'Tit Bazar",
    "wof:placetype":"venue"
},
  "geometry": {"coordinates":[-74.01082599999999,45.779793],"type":"Point"}
}