{
  "type": "Feature",
  "properties": {
    "addr:full":"Vancouver BC V6P 6G5",
    "addr:postcode":"v6p 6g5",
    "iso:country":"CA",
    "sg:city":"Vancouver",
    "sg:classifiers":[
        {
            "category":"Professional",
            "subcategory":"Accounting & Tax Preparation",
            "type":"Services"
        }
    ],
    "sg:phone":"+1 604 266 6828",
    "sg:postcode":"V6P 6G5",
    "sg:province":"BC",
    "sg:tags":[
        "accountant"
    ],
    "wof:name":"Fitch, Edward L CA",
    "wof:placetype":"venue"
},
  "geometry": {"coordinates":[-123.133239746,49.2042617798],"type":"Point"}
}