{
  "type": "Feature",
  "properties": {
    "iso:country":"CA",
    "sg:address":"500 Rue Fleury O",
    "sg:city":"Montreal",
    "sg:classifiers":[
        {
            "category":"Organizations",
            "subcategory":"Religious Organization",
            "type":"Services"
        }
    ],
    "sg:phone":"+1 514 387 4082",
    "sg:postcode":"H3L 1W1",
    "sg:province":"QC",
    "sg:tags":[
        "church"
    ],
    "wof:name":"St Benoit Eglise",
    "wof:placetype":"venue"
},
  "geometry": {"coordinates":[-73.662178,45.552719],"type":"Point"}
}