{
  "type": "Feature",
  "properties": {
    "iso:country":"CA",
    "sg:address":"677 Victoria St",
    "sg:city":"London",
    "sg:classifiers":[
        {
            "category":"Personal",
            "subcategory":"Beauty Salon",
            "type":"Services"
        }
    ],
    "sg:phone":"+1 519 645 0524",
    "sg:postcode":"N5Y 4C2",
    "sg:province":"ON",
    "wof:name":"New Image Hair Design",
    "wof:placetype":"venue"
},
  "geometry": {"coordinates":[-81.238327,43.008942],"type":"Point"}
}