{
  "type": "Feature",
  "properties": {
    "addr:full":"1341 Martindale Rd Sudbury ON P3E 4J7",
    "addr:housenumber":"1341",
    "addr:postcode":"p3e 4j7",
    "addr:street":"Martindale Rd",
    "iso:country":"CA",
    "sg:address":"1341 Martindale Rd",
    "sg:city":"Sudbury",
    "sg:classifiers":[
        {
            "category":"Restaurant",
            "type":"Food & Drink"
        }
    ],
    "sg:phone":"+1 705 522 3400",
    "sg:postcode":"P3E 4J7",
    "sg:province":"ON",
    "wof:name":"Kfc",
    "wof:placetype":"venue"
},
  "geometry": {"coordinates":[-81.009033,46.464909],"type":"Point"}
}