{
  "type": "Feature",
  "properties": {
    "addr:full":"Port Coquitlam BC V3C 6K5",
    "addr:postcode":"v3c 6k5",
    "iso:country":"CA",
    "sg:city":"Port Coquitlam",
    "sg:classifiers":[
        {
            "category":"Professional",
            "subcategory":"Employment Agencies",
            "type":"Services"
        }
    ],
    "sg:phone":"+1 604 552 4390",
    "sg:postcode":"V3C 6K5",
    "sg:province":"BC",
    "sg:tags":[
        "opportunity"
    ],
    "wof:name":"Permanent Solutions",
    "wof:placetype":"venue"
},
  "geometry": {"coordinates":[-122.777519,49.266109],"type":"Point"}
}