{
  "type": "Feature",
  "properties": {
    "iso:country":"CA",
    "sg:address":"1900 Rue Martineau",
    "sg:city":"Saint-Hyacinthe",
    "sg:classifiers":[
        {
            "category":"Shopping",
            "subcategory":"Musical Instruments",
            "type":"Retail Goods"
        }
    ],
    "sg:phone":"+1 450 787 2294",
    "sg:postcode":"J2S 8B1",
    "sg:province":"QC",
    "wof:name":"Atelier Du Violin Enr",
    "wof:placetype":"venue"
},
  "geometry": {"coordinates":[-72.9538803101,45.6485214233],"type":"Point"}
}