{
  "type": "Feature",
  "properties": {
    "addr:full":"688 Rue Principale Neguac NB E9G 1N4",
    "addr:housenumber":"688",
    "addr:postcode":"e9g 1n4",
    "addr:street":"Rue Principale",
    "iso:country":"CA",
    "sg:address":"688 Rue Principale",
    "sg:city":"Neguac",
    "sg:classifiers":[
        {
            "category":"Food & Beverages",
            "subcategory":"Groceries & Convenience Stores",
            "type":"Retail Goods"
        }
    ],
    "sg:phone":"+1 506 776 1994",
    "sg:postcode":"E9G 1N4",
    "sg:province":"NB",
    "wof:name":"Neguac Mainway",
    "wof:placetype":"venue"
},
  "geometry": {"coordinates":[-65.0825958252,47.2443084717],"type":"Point"}
}