{
  "type": "Feature",
  "properties": {
    "addr:full":"Gatineau QC J8V 1A4",
    "addr:postcode":"j8v 1a4",
    "iso:country":"CA",
    "sg:city":"Gatineau",
    "sg:classifiers":[
        {
            "category":"Personal",
            "subcategory":"Beauty Salon",
            "type":"Services"
        }
    ],
    "sg:phone":"+1 819 246 9011",
    "sg:postcode":"J8V 1A4",
    "sg:province":"QC",
    "wof:name":"Coiffure DE Meche Avec Vous",
    "wof:placetype":"venue"
},
  "geometry": {"coordinates":[-75.7104873657,45.4278526306],"type":"Point"}
}