{
  "type": "Feature",
  "properties": {
    "addr:full":"Garden Bay BC V0N 1S0",
    "addr:postcode":"v0n 1s0",
    "iso:country":"CA",
    "sg:city":"Garden Bay",
    "sg:classifiers":[
        {
            "category":"Utilities",
            "subcategory":"Water",
            "type":"Services"
        }
    ],
    "sg:phone":"+1 604 883 2775",
    "sg:postcode":"V0N 1S0",
    "sg:province":"BC",
    "sg:tags":[
        "company",
        "sewage"
    ],
    "wof:name":"Garden Bay Water Works Distr",
    "wof:placetype":"venue"
},
  "geometry": {"coordinates":[-123.971725464,49.6389541626],"type":"Point"}
}