{
  "type": "Feature",
  "properties": {
    "addr:full":"421 Water St Peterborough ON K9H 3L9",
    "addr:housenumber":"421",
    "addr:postcode":"k9h 3l9",
    "addr:street":"Water St",
    "iso:country":"CA",
    "sg:address":"421 Water St",
    "sg:city":"Peterborough",
    "sg:classifiers":[
        {
            "category":"Professional",
            "subcategory":"Advertising",
            "type":"Services"
        }
    ],
    "sg:phone":"+1 705 876 6664",
    "sg:postcode":"K9H 3L9",
    "sg:province":"ON",
    "sg:tags":[
        "counselor"
    ],
    "wof:name":"Water Street Media",
    "wof:placetype":"venue"
},
  "geometry": {"coordinates":[-78.319176,44.306587],"type":"Point"}
}