{
  "type": "Feature",
  "properties": {
    "addr:full":"172 Parkview Ave Orillia ON L3V 4M5",
    "addr:housenumber":"172",
    "addr:postcode":"on l3v 4m5",
    "addr:street":"Parkview Ave",
    "iso:country":"CA",
    "sg:address":"172 Parkview Ave",
    "sg:city":"Orillia",
    "sg:classifiers":[
        {
            "category":"Building & Trades",
            "subcategory":"Construction",
            "type":"Services"
        }
    ],
    "sg:phone":"+1 705 326 0925",
    "sg:postcode":"L3V 4M5",
    "sg:province":"ON",
    "sg:tags":[
        "painter"
    ],
    "wof:name":"Beitz Painting & Decorating",
    "wof:placetype":"venue"
},
  "geometry": {"coordinates":[-79.417564,44.617188],"type":"Point"}
}