{
  "type": "Feature",
  "properties": {
    "addr:full":"186 Ch Du Bas-DE-Sainte-Theres # 101 Blainville QC J7B 1A7",
    "addr:housenumber":"186",
    "addr:postcode":"j7b 1a7",
    "addr:street":"Ch Du Bas-De-Sainte-Theres # 101",
    "iso:country":"CA",
    "sg:address":"186 Ch Du Bas-DE-Sainte-Theres # 101",
    "sg:city":"Blainville",
    "sg:classifiers":[
        {
            "category":"Personal",
            "type":"Services"
        }
    ],
    "sg:phone":"+1 450 430 4660",
    "sg:postcode":"J7B 1A7",
    "sg:province":"QC",
    "sg:tags":[
        "electrolysis"
    ],
    "wof:name":"Esthetique Fontainbleau",
    "wof:placetype":"venue"
},
  "geometry": {"coordinates":[-73.812225,45.645515],"type":"Point"}
}