{
  "type": "Feature",
  "properties": {
    "addr:full":"1545 Rue Principale Saint-Come QC J0K 2B0",
    "addr:housenumber":"1545",
    "addr:postcode":"j0k 2b0",
    "addr:street":"Rue Principale",
    "iso:country":"CA",
    "sg:address":"1545 Rue Principale",
    "sg:city":"Saint-Come",
    "sg:classifiers":[
        {
            "category":"Retail",
            "subcategory":"Auto Repair",
            "type":"Services"
        }
    ],
    "sg:phone":"+1 450 883 6121",
    "sg:postcode":"J0K 2B0",
    "sg:province":"QC",
    "sg:tags":[
        "repairing",
        "automobile"
    ],
    "wof:name":"Garage Yves Morin",
    "wof:placetype":"venue"
},
  "geometry": {"coordinates":[-73.77136230470001,46.2711982727],"type":"Point"}
}