{
  "type": "Feature",
  "properties": {
    "addr:full":"399 Yonge St Toronto ON M5B 1S9",
    "addr:housenumber":"399",
    "addr:postcode":"m5b 1s9",
    "addr:street":"Yonge St",
    "iso:country":"CA",
    "sg:address":"399 Yonge St",
    "sg:city":"Toronto",
    "sg:classifiers":[
        {
            "category":"Recreation",
            "type":"Entertainment"
        }
    ],
    "sg:phone":"+1 416 585 9602",
    "sg:postcode":"M5B 1S9",
    "sg:province":"ON",
    "sg:tags":[
        "martial",
        "arts",
        "instruction"
    ],
    "wof:name":"Aikido Yoshinkai Canada",
    "wof:placetype":"venue"
},
  "geometry": {"coordinates":[-79.382034,43.659382],"type":"Point"}
}