{
  "type": "Feature",
  "properties": {
    "addr:full":"237 Av Du Mont-Royal O Montreal QC H2T 2T2",
    "addr:postcode":"h2t 2t2",
    "addr:street":"237 Av Du Mont-Royal O",
    "iso:country":"CA",
    "sg:address":"237 Av Du Mont-Royal O",
    "sg:city":"Montreal",
    "sg:classifiers":[
        {
            "category":"Professional",
            "subcategory":"Business Services",
            "type":"Services"
        }
    ],
    "sg:phone":"+1 514 844 1602",
    "sg:postcode":"H2T 2T2",
    "sg:province":"QC",
    "sg:tags":[
        "plant",
        "design",
        "maintenance"
    ],
    "wof:name":"Marche Des Plantes Venus",
    "wof:placetype":"venue"
},
  "geometry": {"coordinates":[-73.58438099999999,45.5224],"type":"Point"}
}