{
  "type": "Feature",
  "properties": {
    "addr:full":"Abbotsford BC V2S 2J5",
    "addr:postcode":"v2s 2j5",
    "iso:country":"CA",
    "sg:city":"Abbotsford",
    "sg:classifiers":[
        {
            "category":"Real Estate",
            "subcategory":"Real Estate Operator",
            "type":"Services"
        }
    ],
    "sg:phone":"+1 604 854 6204",
    "sg:postcode":"V2S 2J5",
    "sg:province":"BC",
    "sg:tags":[
        "condominium"
    ],
    "wof:name":"Sherwood Forest CO-OP",
    "wof:placetype":"venue"
},
  "geometry": {"coordinates":[-122.30344390899999,49.0512580872],"type":"Point"}
}