{
  "type": "Feature",
  "properties": {
    "iso:country":"CA",
    "sg:address":"400 Bayfield St",
    "sg:city":"Barrie",
    "sg:classifiers":[
        {
            "category":"Restaurant",
            "type":"Food & Drink"
        }
    ],
    "sg:phone":"+1 705 734 3328",
    "sg:postcode":"L4M 5A1",
    "sg:province":"ON",
    "wof:name":"Golden Wok Plus",
    "wof:placetype":"venue"
},
  "geometry": {"coordinates":[-79.704346,44.40538],"type":"Point"}
}