{
  "type": "Feature",
  "properties": {
    "iso:country":"CA",
    "sg:city":"Spruce Grove",
    "sg:classifiers":[
        {
            "category":"Retail",
            "subcategory":"Repair Shop",
            "type":"Services"
        }
    ],
    "sg:phone":"+1 780 470 3113",
    "sg:postcode":"T7Y 1B3",
    "sg:province":"AB",
    "sg:tags":[
        "repairing",
        "piano",
        "refinishing"
    ],
    "wof:name":"D W Schafer Piano Svc",
    "wof:placetype":"venue"
},
  "geometry": {"coordinates":[-113.901855469,53.5446357727],"type":"Point"}
}