{
  "type": "Feature",
  "properties": {
    "addr:full":"340 College St # 580 Toronto ON M5T 3A9",
    "addr:housenumber":"340",
    "addr:postcode":"m5t 3a9",
    "addr:street":"College St # 580",
    "iso:country":"CA",
    "sg:address":"340 College St # 580",
    "sg:city":"Toronto",
    "sg:classifiers":[
        {
            "category":"Health Services",
            "subcategory":"Health Practitioner",
            "type":"Services"
        }
    ],
    "sg:phone":"+1 416 323 2007",
    "sg:postcode":"M5T 3A9",
    "sg:province":"ON",
    "sg:tags":[
        "psychologist"
    ],
    "wof:name":"Toronto Psychiatric Research",
    "wof:placetype":"venue"
},
  "geometry": {"coordinates":[-79.40334320069999,43.6574478149],"type":"Point"}
}