{
  "type": "Feature",
  "properties": {
    "addr:full":"629 Rue Beriault Longueuil QC J4G 1Z1",
    "addr:housenumber":"629",
    "addr:postcode":"j4g 1z1",
    "addr:street":"Rue Beriault",
    "iso:country":"CA",
    "sg:address":"629 Rue Beriault",
    "sg:city":"Longueuil",
    "sg:classifiers":[
        {
            "category":"Shopping",
            "subcategory":"Computers & Home Electronics",
            "type":"Retail Goods"
        }
    ],
    "sg:phone":"+1 450 646 2893",
    "sg:postcode":"J4G 1Z1",
    "sg:province":"QC",
    "sg:tags":[
        "parts",
        "supply"
    ],
    "wof:name":"Exponent Microport Inc",
    "wof:placetype":"venue"
},
  "geometry": {"coordinates":[-73.473679,45.565083],"type":"Point"}
}