{
  "type": "Feature",
  "properties": {
    "addr:full":"180 Riverglen Dr SE Calgary AB T2C 3W9",
    "addr:housenumber":"180",
    "addr:postcode":"t2c 3w9",
    "addr:street":"Riverglen Dr Se",
    "iso:country":"CA",
    "sg:address":"180 Riverglen Dr SE",
    "sg:city":"Calgary",
    "sg:classifiers":[
        {
            "category":"Communications",
            "subcategory":"Film & Video Production",
            "type":"Services"
        }
    ],
    "sg:phone":"+1 403 720 2744",
    "sg:postcode":"T2C 3W9",
    "sg:province":"AB",
    "sg:tags":[
        "taping"
    ],
    "wof:name":"Drystone Productions",
    "wof:placetype":"venue"
},
  "geometry": {"coordinates":[-114.00485229500001,50.9754753113],"type":"Point"}
}