{
  "type": "Feature",
  "properties": {
    "addr:full":"2142 99 St NW Edmonton AB T6N 1L2",
    "addr:housenumber":"2142",
    "addr:postcode":"t6n 1l2",
    "addr:street":"99 St Nw",
    "iso:country":"CA",
    "sg:address":"2142 99 St NW",
    "sg:city":"Edmonton",
    "sg:classifiers":[
        {
            "category":"Banks & Credit Unions",
            "subcategory":"Bank",
            "type":"Services"
        }
    ],
    "sg:phone":"+1 780 988 8607",
    "sg:postcode":"T6N 1L2",
    "sg:province":"AB",
    "wof:name":"Canadian Western Bank",
    "wof:placetype":"venue"
},
  "geometry": {"coordinates":[-113.486328,53.452076],"type":"Point"}
}