{
  "type": "Feature",
  "properties": {
    "addr:full":"1631 Oxford St E London ON N5V 2Z4",
    "addr:housenumber":"1631",
    "addr:postcode":"n5v 2z4",
    "addr:street":"Oxford St E",
    "iso:country":"CA",
    "sg:address":"1631 Oxford St E",
    "sg:city":"London",
    "sg:classifiers":[
        {
            "category":"Shopping",
            "subcategory":"Discount & Variety Stores",
            "type":"Retail Goods"
        }
    ],
    "sg:phone":"+1 519 451 4760",
    "sg:postcode":"N5V 2Z4",
    "sg:province":"ON",
    "wof:name":"Fanshawe Mini Mart",
    "wof:placetype":"venue"
},
  "geometry": {"coordinates":[-81.19575500489999,43.0120735168],"type":"Point"}
}