{
  "type": "Feature",
  "properties": {
    "addr:full":"Hull QC J8X 1P1",
    "addr:postcode":"j8x 1p1",
    "iso:country":"CA",
    "sg:city":"Hull",
    "sg:classifiers":[
        {
            "category":"Organizations",
            "subcategory":"Professional Association",
            "type":"Services"
        }
    ],
    "sg:phone":"+1 819 770 3839",
    "sg:postcode":"J8X 1P1",
    "sg:province":"QC",
    "wof:name":"Assn Pour LA Defense-Droits",
    "wof:placetype":"venue"
},
  "geometry": {"coordinates":[-75.7252197266,45.4315414429],"type":"Point"}
}