{
  "type": "Feature",
  "properties": {
    "addr:full":"Tramping Lake Unity SK S0K 4L0",
    "addr:postcode":"s0k 4l0",
    "iso:country":"CA",
    "sg:address":"Tramping Lake",
    "sg:city":"Unity",
    "sg:classifiers":[
        {
            "category":"Autos & Motor Vehicles",
            "subcategory":"Automobile Sales",
            "type":"Retail Goods"
        }
    ],
    "sg:phone":"+1 306 228 8288",
    "sg:postcode":"S0K 4L0",
    "sg:province":"SK",
    "sg:tags":[
        "car",
        "dealer"
    ],
    "wof:name":"Hilltop Auto Sales",
    "wof:placetype":"venue"
},
  "geometry": {"coordinates":[-109.145545959,52.4371109009],"type":"Point"}
}