{
  "type": "Feature",
  "properties": {
    "addr:full":"Calgary AB T2N 3R7",
    "addr:postcode":"t2n 3r7",
    "iso:country":"CA",
    "sg:city":"Calgary",
    "sg:classifiers":[
        {
            "category":"Shopping",
            "subcategory":"Clothing, Apparel, & Fashions",
            "type":"Retail Goods"
        }
    ],
    "sg:phone":"+1 403 283 1654",
    "sg:postcode":"T2N 3R7",
    "sg:province":"AB",
    "sg:tags":[
        "shop",
        "infant",
        "consignment"
    ],
    "wof:name":"Growthspurtz",
    "wof:placetype":"venue"
},
  "geometry": {"coordinates":[-114.108650208,51.0526275635],"type":"Point"}
}