{
  "type": "Feature",
  "properties": {
    "iso:country":"CA",
    "sg:address":"14 Day Hollow Dr",
    "sg:city":"Lake Fletcher",
    "sg:classifiers":[
        {
            "category":"Wholesale",
            "subcategory":"Non-durable Goods",
            "type":"Manufacturing & Wholesale Goods"
        }
    ],
    "sg:phone":"+1 902 860 1066",
    "sg:postcode":"B2T 1A5",
    "sg:province":"NS",
    "sg:tags":[
        "hat"
    ],
    "wof:name":"Merrick's Trophy & Gifts",
    "wof:placetype":"venue"
},
  "geometry": {"coordinates":[-63.60887146,44.835395813],"type":"Point"}
}