{
  "type": "Feature",
  "properties": {
    "addr:full":"501 Rue DE L'Eglise Tracadie-Sheila NB E1X 1B1",
    "addr:housenumber":"501",
    "addr:postcode":"e1x 1b1",
    "addr:street":"Rue De L'Eglise",
    "iso:country":"CA",
    "sg:address":"501 Rue DE L'Eglise",
    "sg:city":"Tracadie-Sheila",
    "sg:classifiers":[
        {
            "category":"Health Services",
            "subcategory":"Doctor",
            "type":"Services"
        }
    ],
    "sg:phone":"+1 506 395 6306",
    "sg:postcode":"E1X 1B1",
    "sg:province":"NB",
    "sg:tags":[
        "dentist"
    ],
    "wof:name":"Clinique Dentaire Petrie",
    "wof:placetype":"venue"
},
  "geometry": {"coordinates":[-64.910591,47.521309],"type":"Point"}
}