{
  "type": "Feature",
  "properties": {
    "addr:full":"1498 Bay Ave Trail BC V1R 4B1",
    "addr:housenumber":"1498",
    "addr:postcode":"bc v1r 4b1",
    "addr:street":"Bay Ave Trail",
    "iso:country":"CA",
    "sg:address":"1498 Bay Ave",
    "sg:city":"Trail",
    "sg:classifiers":[
        {
            "category":"Banks & Credit Unions",
            "subcategory":"Bank",
            "type":"Services"
        }
    ],
    "sg:phone":"+1 250 368 9141",
    "sg:postcode":"V1R 4B1",
    "sg:province":"BC",
    "wof:name":"Bank of Montreal",
    "wof:placetype":"venue"
},
  "geometry": {"coordinates":[-117.706642,49.094791],"type":"Point"}
}