{
  "type": "Feature",
  "properties": {
    "addr:full":"2710 Av Loti Quebec QC G1P 3A1",
    "addr:housenumber":"2710",
    "addr:postcode":"g1p 3a1",
    "addr:street":"Av Loti",
    "iso:country":"CA",
    "sg:address":"2710 Av Loti",
    "sg:city":"Quebec",
    "sg:classifiers":[
        {
            "category":"Professional",
            "subcategory":"Art Services",
            "type":"Services"
        }
    ],
    "sg:phone":"+1 418 683 0851",
    "sg:postcode":"G1P 3A1",
    "sg:province":"QC",
    "sg:tags":[
        "photographer"
    ],
    "wof:name":"Air Photo Inc",
    "wof:placetype":"venue"
},
  "geometry": {"coordinates":[-71.3157577515,46.8125648499],"type":"Point"}
}