{
  "type": "Feature",
  "properties": {
    "iso:country":"CA",
    "sg:address":"866 Cardington St",
    "sg:city":"Mississauga",
    "sg:classifiers":[
        {
            "category":"Communications",
            "subcategory":"Film & Video Production",
            "type":"Services"
        }
    ],
    "sg:phone":"+1 905 712 8072",
    "sg:postcode":"L5V 1Z7",
    "sg:province":"ON",
    "sg:tags":[
        "taping"
    ],
    "wof:name":"C C Video Productions",
    "wof:placetype":"venue"
},
  "geometry": {"coordinates":[-79.68012237550001,43.5929298401],"type":"Point"}
}