{
  "type": "Feature",
  "properties": {
    "addr:full":"185 Beliveau Rd # D Winnipeg MB R2M 5G4",
    "addr:housenumber":"185",
    "addr:postcode":"r2m 5g4",
    "addr:street":"Beliveau Rd # D",
    "iso:country":"CA",
    "sg:address":"185 Beliveau Rd # D",
    "sg:city":"Winnipeg",
    "sg:classifiers":[
        {
            "category":"Building & Trades",
            "subcategory":"Construction",
            "type":"Services"
        }
    ],
    "sg:phone":"+1 204 255 2730",
    "sg:postcode":"R2M 5G4",
    "sg:province":"MB",
    "wof:name":"R 3 Svc",
    "wof:placetype":"venue"
},
  "geometry": {"coordinates":[-97.104034,49.83773],"type":"Point"}
}