{
  "type": "Feature",
  "properties": {
    "addr:full":"Calgary AB T2E 6S1",
    "addr:postcode":"t2e 6s1",
    "iso:country":"CA",
    "sg:city":"Calgary",
    "sg:classifiers":[
        {
            "category":"Manufacturing",
            "subcategory":"Tools & Machinery",
            "type":"Manufacturing & Wholesale Goods"
        }
    ],
    "sg:phone":"+1 403 216 0630",
    "sg:postcode":"T2E 6S1",
    "sg:province":"AB",
    "sg:tags":[
        "machine",
        "shop"
    ],
    "wof:name":"Brc Engineering",
    "wof:placetype":"venue"
},
  "geometry": {"coordinates":[-114.049217,51.090618],"type":"Point"}
}