{
  "type": "Feature",
  "properties": {
    "addr:full":"3316 Grand Marais Rd E Windsor ON N8W 1W7",
    "addr:housenumber":"3316",
    "addr:postcode":"n8w 1w7",
    "addr:street":"Grand Marais Rd E",
    "iso:country":"CA",
    "sg:address":"3316 Grand Marais Rd E",
    "sg:city":"Windsor",
    "sg:classifiers":[
        {
            "category":"Restaurant",
            "type":"Food & Drink"
        }
    ],
    "sg:phone":"+1 519 944 2950",
    "sg:postcode":"N8W 1W7",
    "sg:province":"ON",
    "wof:name":"Back Road Cafe",
    "wof:placetype":"venue"
},
  "geometry": {"coordinates":[-82.9758529663,42.2933197021],"type":"Point"}
}