{
  "type": "Feature",
  "properties": {
    "iso:country":"CA",
    "sg:address":"16708 100 St NW",
    "sg:city":"Edmonton",
    "sg:classifiers":[
        {
            "category":"Health Services",
            "subcategory":"Doctor",
            "type":"Services"
        }
    ],
    "sg:phone":"+1 780 456 6759",
    "sg:postcode":"T5X 2S9",
    "sg:province":"AB",
    "sg:tags":[
        "dentist"
    ],
    "wof:name":"Grainge, P L DDS",
    "wof:placetype":"venue"
},
  "geometry": {"coordinates":[-113.498649597,53.6290855408],"type":"Point"}
}