{
  "type": "Feature",
  "properties": {
    "addr:full":"Brentwood Bay BC V8M 1J5",
    "addr:postcode":"v8m 1j5",
    "iso:country":"CA",
    "sg:city":"Brentwood Bay",
    "sg:classifiers":[
        {
            "category":"Retail",
            "subcategory":"Car Wash",
            "type":"Services"
        }
    ],
    "sg:phone":"+1 250 652 1822",
    "sg:postcode":"V8M 1J5",
    "sg:province":"BC",
    "sg:tags":[
        "polishing",
        "washing"
    ],
    "wof:name":"Peninsula CO-OP",
    "wof:placetype":"venue"
},
  "geometry": {"coordinates":[-123.43874359100001,48.5657310486],"type":"Point"}
}