{
  "type": "Feature",
  "properties": {
    "iso:country":"CA",
    "sg:address":"4 Rue Nicoud",
    "sg:city":"Charlemagne",
    "sg:classifiers":[
        {
            "category":"Building & Trades",
            "subcategory":"Construction",
            "type":"Services"
        }
    ],
    "sg:phone":"+1 450 581 1638",
    "sg:postcode":"J5Z 3H4",
    "sg:province":"QC",
    "sg:tags":[
        "repairing",
        "remodeling",
        "contractor"
    ],
    "wof:name":"Renovation Gosselin Inc",
    "wof:placetype":"venue"
},
  "geometry": {"coordinates":[-73.483757019,45.7246627808],"type":"Point"}
}