{
  "type": "Feature",
  "properties": {
    "iso:country":"CA",
    "sg:city":"Calgary",
    "sg:classifiers":[
        {
            "category":"Organizations",
            "subcategory":"Professional Association",
            "type":"Services"
        }
    ],
    "sg:phone":"+1 403 212 1336",
    "sg:postcode":"T2H 2L2",
    "sg:province":"AB",
    "wof:name":"Terry Fox Run",
    "wof:placetype":"venue"
},
  "geometry": {"coordinates":[-114.057327,50.998505],"type":"Point"}
}