{
  "type": "Feature",
  "properties": {
    "addr:full":"864 15th St W North Vancouver BC V7P 1M6",
    "addr:housenumber":"864",
    "addr:postcode":"v7p 1m6",
    "addr:street":"15Th St W",
    "iso:country":"CA",
    "sg:address":"864 15th St W",
    "sg:city":"North Vancouver",
    "sg:classifiers":[
        {
            "category":"Retail",
            "subcategory":"Auto Repair",
            "type":"Services"
        }
    ],
    "sg:phone":"+1 604 986 6909",
    "sg:postcode":"V7P 1M6",
    "sg:province":"BC",
    "sg:tags":[
        "wheel",
        "alignment",
        "axle"
    ],
    "wof:name":"Sals Motors Ltd",
    "wof:placetype":"venue"
},
  "geometry": {"coordinates":[-123.09622192400001,49.322429657],"type":"Point"}
}