{
  "type": "Feature",
  "properties": {
    "addr:full":"395 Boul Des Bois-Francs N Victoriaville QC G6P 1H1",
    "addr:housenumber":"395",
    "addr:postcode":"g6p 1h1",
    "addr:street":"Boul Des Bois-Francs N",
    "iso:country":"CA",
    "sg:address":"395 Boul Des Bois-Francs N",
    "sg:city":"Victoriaville",
    "sg:classifiers":[
        {
            "category":"Food & Beverages",
            "subcategory":"Groceries & Convenience Stores",
            "type":"Retail Goods"
        }
    ],
    "sg:phone":"+1 819 751 0394",
    "sg:postcode":"G6P 1H1",
    "sg:province":"QC",
    "wof:name":"Depanneur Du Boulevard Enr",
    "wof:placetype":"venue"
},
  "geometry": {"coordinates":[-71.964287,46.066219],"type":"Point"}
}