{
  "type": "Feature",
  "properties": {
    "addr:full":"1329 Boul Dagenais O Laval QC H7L 5Z9",
    "addr:housenumber":"1329",
    "addr:postcode":"h7l 5z9",
    "addr:street":"Boul Dagenais O",
    "iso:country":"CA",
    "sg:address":"1329 Boul Dagenais O",
    "sg:city":"Laval",
    "sg:classifiers":[
        {
            "category":"Wholesale",
            "subcategory":"Hardware",
            "type":"Manufacturing & Wholesale Goods"
        }
    ],
    "sg:phone":"+1 450 625 2660",
    "sg:postcode":"H7L 5Z9",
    "sg:province":"QC",
    "wof:name":"Reno Direct Inc",
    "wof:placetype":"venue"
},
  "geometry": {"coordinates":[-73.7523727417,45.5975265503],"type":"Point"}
}