{
  "type": "Feature",
  "properties": {
    "iso:country":"CA",
    "sg:address":"5555 Imperial St",
    "sg:city":"Burnaby",
    "sg:classifiers":[
        {
            "category":"Building & Trades",
            "subcategory":"Construction",
            "type":"Services"
        }
    ],
    "sg:phone":"+1 604 434 0773",
    "sg:postcode":"V5J 1E8",
    "sg:province":"BC",
    "sg:tags":[
        "repairing",
        "siding",
        "remodeling",
        "contractor"
    ],
    "wof:name":"Shell Busey's House Smart Ctr",
    "wof:placetype":"venue"
},
  "geometry": {"coordinates":[-122.983848572,49.2220535278],"type":"Point"}
}