{
  "type": "Feature",
  "properties": {
    "addr:full":"1684 Barrington St Halifax NS B3J 2A2",
    "addr:housenumber":"1684",
    "addr:postcode":"ns b3j 2a2",
    "addr:street":"Barrington St",
    "iso:country":"CA",
    "sg:address":"1684 Barrington St",
    "sg:city":"Halifax",
    "sg:classifiers":[
        {
            "category":"Shopping",
            "subcategory":"Used Merchandise",
            "type":"Retail Goods"
        }
    ],
    "sg:phone":"+1 902 429 1652",
    "sg:postcode":"B3J 2A2",
    "sg:province":"NS",
    "sg:tags":[
        "book",
        "rare",
        "dealer"
    ],
    "wof:name":"John W Doull Bookseller",
    "wof:placetype":"venue"
},
  "geometry": {"coordinates":[-63.574081,44.646912],"type":"Point"}
}