{
  "type": "Feature",
  "properties": {
    "addr:full":"40 Main St S Kenora ON P9N 1S7",
    "addr:housenumber":"40",
    "addr:postcode":"p9n 1s7",
    "addr:street":"Main St S",
    "iso:country":"CA",
    "sg:address":"40 Main St S",
    "sg:city":"Kenora",
    "sg:classifiers":[
        {
            "category":"Banks & Credit Unions",
            "subcategory":"Bank",
            "type":"Services"
        }
    ],
    "sg:phone":"+1 807 468 6483",
    "sg:postcode":"P9N 1S7",
    "sg:province":"ON",
    "wof:name":"Scotiabank",
    "wof:placetype":"venue"
},
  "geometry": {"coordinates":[-94.48997497560001,49.7681846619],"type":"Point"}
}