{
  "type": "Feature",
  "properties": {
    "addr:full":"East York ON M4C 3E7",
    "addr:postcode":"m4c 3e7",
    "iso:country":"CA",
    "sg:city":"East York",
    "sg:classifiers":[
        {
            "category":"Health Services",
            "subcategory":"Doctor",
            "type":"Services"
        }
    ],
    "sg:phone":"+1 416 469 3325",
    "sg:postcode":"M4C 3E7",
    "sg:province":"ON",
    "sg:tags":[
        "physician",
        "surgeon"
    ],
    "wof:name":"Meharchand, Jacinta MD",
    "wof:placetype":"venue"
},
  "geometry": {"coordinates":[-79.326286,43.690365],"type":"Point"}
}