{
  "type": "Feature",
  "properties": {
    "addr:full":"9483 Hwy 221 Canning NS B0P 1H0",
    "addr:housenumber":"9483",
    "addr:postcode":"b0p 1h0",
    "addr:street":"Hwy 221",
    "iso:country":"CA",
    "sg:address":"9483 Hwy 221",
    "sg:city":"Canning",
    "sg:classifiers":[
        {
            "category":"Social Services",
            "type":"Services"
        }
    ],
    "sg:phone":"+1 902 582 3030",
    "sg:postcode":"B0P 1H0",
    "sg:province":"NS",
    "sg:tags":[
        "pregnancy",
        "counseling",
        "information"
    ],
    "wof:name":"Great Beginnings",
    "wof:placetype":"venue"
},
  "geometry": {"coordinates":[-64.431664,45.156918],"type":"Point"}
}