{
  "type": "Feature",
  "properties": {
    "addr:full":"6405 Boul Saint-Laurent Montreal QC H2S 3C3",
    "addr:housenumber":"6405",
    "addr:postcode":"h2s 3c3",
    "addr:street":"Boul Saint-Laurent",
    "iso:country":"CA",
    "sg:address":"6405 Boul Saint-Laurent",
    "sg:city":"Montreal",
    "sg:classifiers":[
        {
            "category":"Shopping",
            "subcategory":"Shoes",
            "type":"Retail Goods"
        }
    ],
    "sg:phone":"+1 514 276 4026",
    "sg:postcode":"H2S 3C3",
    "sg:province":"QC",
    "wof:name":"Norest",
    "wof:placetype":"venue"
},
  "geometry": {"coordinates":[-73.607933,45.530125],"type":"Point"}
}