{
  "type": "Feature",
  "properties": {
    "addr:full":"3580 Clearbrook Rd Abbotsford BC V2T 5C1",
    "addr:housenumber":"3580",
    "addr:postcode":"v2t 5c1",
    "addr:street":"Clearbrook Rd",
    "iso:country":"CA",
    "sg:address":"3580 Clearbrook Rd",
    "sg:city":"Abbotsford",
    "sg:classifiers":[
        {
            "category":"Organizations",
            "subcategory":"Religious Organization",
            "type":"Services"
        }
    ],
    "sg:phone":"+1 604 854 1505",
    "sg:postcode":"V2T 5C1",
    "sg:province":"BC",
    "sg:tags":[
        "church"
    ],
    "wof:name":"Maranatha Baptist Church",
    "wof:placetype":"venue"
},
  "geometry": {"coordinates":[-122.33795929,49.0669288635],"type":"Point"}
}