{
  "type": "Feature",
  "properties": {
    "addr:full":"5120 48 St Yellowknife NT X1A 1N6",
    "addr:housenumber":"5120",
    "addr:postcode":"x1a 1n6",
    "addr:street":"48 St",
    "iso:country":"CA",
    "sg:address":"5120 48 St",
    "sg:city":"Yellowknife",
    "sg:classifiers":[
        {
            "category":"Health Services",
            "subcategory":"Chiropractor",
            "type":"Services"
        }
    ],
    "sg:phone":"+1 867 920 2157",
    "sg:postcode":"X1A 1N6",
    "sg:province":"NT",
    "wof:name":"Barker's Chiropractic Clinic",
    "wof:placetype":"venue"
},
  "geometry": {"coordinates":[-114.36610400000001,62.453445],"type":"Point"}
}