{
  "type": "Feature",
  "properties": {
    "addr:full":"Sussex NB E4E 2A3",
    "addr:postcode":"e4e 2a3",
    "iso:country":"CA",
    "sg:city":"Sussex",
    "sg:classifiers":[
        {
            "category":"Retail",
            "subcategory":"Veterinary Services",
            "type":"Services"
        }
    ],
    "sg:phone":"+1 506 832 2056",
    "sg:postcode":"E4E 2A3",
    "sg:province":"NB",
    "sg:tags":[
        "veterinarian"
    ],
    "wof:name":"Abbate, Chuck DVM",
    "wof:placetype":"venue"
},
  "geometry": {"coordinates":[-65.51448822019999,45.7227096558],"type":"Point"}
}