{
  "type": "Feature",
  "properties": {
    "addr:full":"Haliburton ON K0M 1S0",
    "addr:postcode":"k0m 1s0",
    "iso:country":"CA",
    "sg:city":"Haliburton",
    "sg:classifiers":[
        {
            "category":"Professional",
            "subcategory":"Lawyer & Legal Services",
            "type":"Services"
        }
    ],
    "sg:phone":"+1 705 457 2435",
    "sg:postcode":"K0M 1S0",
    "sg:province":"ON",
    "sg:tags":[
        "attorney"
    ],
    "wof:name":"Selbie, Raymond G",
    "wof:placetype":"venue"
},
  "geometry": {"coordinates":[-78.51029200000001,45.049438],"type":"Point"}
}