{
  "type": "Feature",
  "properties": {
    "addr:full":"151 Boul Greber # 26 Gatineau QC J8T 6G6",
    "addr:housenumber":"151",
    "addr:postcode":"j8t 6g6",
    "addr:street":"Boul Greber # 26",
    "iso:country":"CA",
    "sg:address":"151 Boul Greber # 26",
    "sg:city":"Gatineau",
    "sg:classifiers":[
        {
            "category":"Home & Garden",
            "subcategory":"Building Materials",
            "type":"Retail Goods"
        }
    ],
    "sg:phone":"+1 819 561 0064",
    "sg:postcode":"J8T 6G6",
    "sg:province":"QC",
    "sg:tags":[
        "paint"
    ],
    "wof:name":"Betonel Limitee",
    "wof:placetype":"venue"
},
  "geometry": {"coordinates":[-75.700554,45.469307],"type":"Point"}
}