{
  "type": "Feature",
  "properties": {
    "addr:full":"78 Rue Front Hull QC J8Y 3M5",
    "addr:housenumber":"78",
    "addr:postcode":"j8y 3m5",
    "addr:street":"Rue Front",
    "iso:country":"CA",
    "sg:address":"78 Rue Front",
    "sg:city":"Hull",
    "sg:classifiers":[
        {
            "category":"Museum",
            "type":"Entertainment"
        }
    ],
    "sg:phone":"+1 819 770 8525",
    "sg:postcode":"J8Y 3M5",
    "sg:province":"QC",
    "sg:tags":[
        "organization",
        "arts",
        "information"
    ],
    "wof:name":"Daimon Centre DE Production",
    "wof:placetype":"venue"
},
  "geometry": {"coordinates":[-75.7172470093,45.4289703369],"type":"Point"}
}