{
  "type": "Feature",
  "properties": {
    "addr:full":"358 Francis St E Thunder Bay ON P7E 4B5",
    "addr:housenumber":"358",
    "addr:postcode":"p7e 4b5",
    "addr:street":"Francis St E",
    "iso:country":"CA",
    "sg:address":"358 Francis St E",
    "sg:city":"Thunder Bay",
    "sg:classifiers":[
        {
            "category":"Building & Trades",
            "subcategory":"Construction",
            "type":"Services"
        }
    ],
    "sg:phone":"+1 807 623 3234",
    "sg:postcode":"P7E 4B5",
    "sg:province":"ON",
    "sg:tags":[
        "home",
        "window",
        "cleaning",
        "improvement"
    ],
    "wof:name":"Joynson Window Cleaning Ltd",
    "wof:placetype":"venue"
},
  "geometry": {"coordinates":[-89.26383209230001,48.3671646118],"type":"Point"}
}