{
  "type": "Feature",
  "properties": {
    "addr:full":"3499 Bathurst St North York ON M6A 2C5",
    "addr:housenumber":"3499",
    "addr:postcode":"m6a 2c5",
    "addr:street":"Bathurst St",
    "iso:country":"CA",
    "sg:address":"3499 Bathurst St",
    "sg:city":"North York",
    "sg:classifiers":[
        {
            "category":"Retail",
            "subcategory":"Laundry & Dry Cleaning",
            "type":"Services"
        }
    ],
    "sg:phone":"+1 416 785 4935",
    "sg:postcode":"M6A 2C5",
    "sg:province":"ON",
    "sg:tags":[
        "cleaners"
    ],
    "wof:name":"Target Dry Cleaners",
    "wof:placetype":"venue"
},
  "geometry": {"coordinates":[-79.431816,43.728851],"type":"Point"}
}