{
  "type": "Feature",
  "properties": {
    "addr:full":"Listowel ON N4W 3G6",
    "addr:postcode":"n4w 3g6",
    "iso:country":"CA",
    "sg:city":"Listowel",
    "sg:classifiers":[
        {
            "category":"Wholesale",
            "subcategory":"Machinery & Supplies",
            "type":"Manufacturing & Wholesale Goods"
        }
    ],
    "sg:phone":"+1 519 291 5012",
    "sg:postcode":"N4W 3G6",
    "sg:province":"ON",
    "sg:tags":[
        "farm",
        "equipment"
    ],
    "wof:name":"First Choice Agriquip Ltd",
    "wof:placetype":"venue"
},
  "geometry": {"coordinates":[-80.92456799999999,43.767834],"type":"Point"}
}