{
  "type": "Feature",
  "properties": {
    "addr:full":"13256 Leslie St Richmond Hill ON L4E 1A2",
    "addr:housenumber":"13256",
    "addr:postcode":"l4e 1a2",
    "addr:street":"Leslie St",
    "iso:country":"CA",
    "sg:address":"13256 Leslie St",
    "sg:city":"Richmond Hill",
    "sg:classifiers":[
        {
            "category":"Restaurant",
            "type":"Food & Drink"
        }
    ],
    "sg:phone":"+1 905 888 0606",
    "sg:postcode":"L4E 1A2",
    "sg:province":"ON",
    "sg:tags":[
        "banquet",
        "rooms"
    ],
    "wof:name":"Oakview Terrace",
    "wof:placetype":"venue"
},
  "geometry": {"coordinates":[-79.4081573486,43.9607810974],"type":"Point"}
}