{
  "type": "Feature",
  "properties": {
    "iso:country":"CA",
    "sg:address":"100 Boul Gagne",
    "sg:city":"Sorel-Tracy",
    "sg:classifiers":[
        {
            "category":"Professional",
            "subcategory":"Printing & Photocopies",
            "type":"Services"
        }
    ],
    "sg:phone":"+1 450 746 0242",
    "sg:postcode":"J3P 7S6",
    "sg:province":"QC",
    "sg:tags":[
        "printer",
        "duplicating",
        "copying"
    ],
    "wof:name":"Page Cournoyer Interface",
    "wof:placetype":"venue"
},
  "geometry": {"coordinates":[-73.11646270750001,46.0313949585],"type":"Point"}
}