{
  "type": "Feature",
  "properties": {
    "addr:full":"70 Bobolink Rd Hamilton ON L9A 2P5",
    "addr:housenumber":"70",
    "addr:postcode":"l9a 2p5",
    "addr:street":"Bobolink Rd",
    "iso:country":"CA",
    "sg:address":"70 Bobolink Rd",
    "sg:city":"Hamilton",
    "sg:classifiers":[
        {
            "category":"Education",
            "subcategory":"School",
            "type":"Public Place"
        }
    ],
    "sg:phone":"+1 905 385 5344",
    "sg:postcode":"L9A 2P5",
    "sg:province":"ON",
    "wof:name":"Cardinal Heights School",
    "wof:placetype":"venue"
},
  "geometry": {"coordinates":[-79.86995697019999,43.2210960388],"type":"Point"}
}