{
  "type": "Feature",
  "properties": {
    "addr:full":"116 Brian Dickie Dr Musquodoboit Harbour NS B0J 2L0",
    "addr:housenumber":"116",
    "addr:postcode":"b0j 2l0",
    "addr:street":"Brian Dickie Dr",
    "iso:country":"CA",
    "sg:address":"116 Brian Dickie Dr",
    "sg:city":"Musquodoboit Harbour",
    "sg:classifiers":[
        {
            "category":"Shopping",
            "subcategory":"Florist",
            "type":"Retail Goods"
        }
    ],
    "sg:phone":"+1 902 889 3582",
    "sg:postcode":"B0J 2L0",
    "sg:province":"NS",
    "wof:name":"Wild Grape Florals",
    "wof:placetype":"venue"
},
  "geometry": {"coordinates":[-63.148285,44.787056],"type":"Point"}
}