{
  "type": "Feature",
  "properties": {
    "addr:full":"775 Boul Cure-Labelle Laval QC H7V 2V2",
    "addr:housenumber":"775",
    "addr:postcode":"h7v 2v2",
    "addr:street":"Boul Cure-Labelle",
    "iso:country":"CA",
    "sg:address":"775 Boul Cure-Labelle",
    "sg:city":"Laval",
    "sg:classifiers":[
        {
            "category":"Bars & Pubs",
            "type":"Food & Drink"
        }
    ],
    "sg:phone":"+1 450 681 4695",
    "sg:postcode":"H7V 2V2",
    "sg:province":"QC",
    "sg:tags":[
        "club",
        "night"
    ],
    "wof:name":"Deesses",
    "wof:placetype":"venue"
},
  "geometry": {"coordinates":[-73.7459945679,45.5388946533],"type":"Point"}
}