{
  "type": "Feature",
  "properties": {
    "addr:full":"122 Barlow Ave Quesnel BC V2J 2B7",
    "addr:housenumber":"122",
    "addr:postcode":"v2j 2b7",
    "addr:street":"Barlow Ave",
    "iso:country":"CA",
    "sg:address":"122 Barlow Ave",
    "sg:city":"Quesnel",
    "sg:classifiers":[
        {
            "category":"Restaurant",
            "type":"Food & Drink"
        }
    ],
    "sg:phone":"+1 250 992 6606",
    "sg:postcode":"V2J 2B7",
    "sg:province":"BC",
    "wof:name":"Ulysses Restaurant",
    "wof:placetype":"venue"
},
  "geometry": {"coordinates":[-122.49754299999999,52.977207],"type":"Point"}
}