{
  "type": "Feature",
  "properties": {
    "addr:full":"404 Fruitland Rd Stoney Creek ON L8E 5L9",
    "addr:housenumber":"404",
    "addr:postcode":"l8e 5l9",
    "addr:street":"Fruitland Rd",
    "iso:country":"CA",
    "sg:address":"404 Fruitland Rd",
    "sg:city":"Stoney Creek",
    "sg:classifiers":[
        {
            "category":"Wholesale",
            "subcategory":"Auto Parts",
            "type":"Manufacturing & Wholesale Goods"
        }
    ],
    "sg:phone":"+1 905 570 8797",
    "sg:postcode":"L8E 5L9",
    "sg:province":"ON",
    "sg:tags":[
        "glass",
        "rebuilt",
        "automobile"
    ],
    "wof:name":"Dominion Auto Recycling",
    "wof:placetype":"venue"
},
  "geometry": {"coordinates":[-79.6981430054,43.226940155],"type":"Point"}
}