{
  "type": "Feature",
  "properties": {
    "addr:full":"4919 49 Ave Holden AB T0B 2C0",
    "addr:housenumber":"4919",
    "addr:postcode":"t0b 2c0",
    "addr:street":"49 Ave",
    "iso:country":"CA",
    "sg:address":"4919 49 Ave",
    "sg:city":"Holden",
    "sg:classifiers":[
        {
            "category":"Organizations",
            "subcategory":"Professional Association",
            "type":"Services"
        }
    ],
    "sg:phone":"+1 780 688 9905",
    "sg:postcode":"T0B 2C0",
    "sg:province":"AB",
    "sg:tags":[
        "club"
    ],
    "wof:name":"Holden Community Hall",
    "wof:placetype":"venue"
},
  "geometry": {"coordinates":[-112.234031677,53.2315483093],"type":"Point"}
}