{
  "type": "Feature",
  "properties": {
    "addr:full":"1735 Bayly St Pickering ON L1W 3G7",
    "addr:housenumber":"1735",
    "addr:postcode":"l1w 3g7",
    "addr:street":"Bayly St",
    "iso:country":"CA",
    "sg:address":"1735 Bayly St",
    "sg:city":"Pickering",
    "sg:classifiers":[
        {
            "category":"Organizations",
            "subcategory":"Religious Organization",
            "type":"Services"
        }
    ],
    "sg:phone":"+1 905 420 0877",
    "sg:postcode":"L1W 3G7",
    "sg:province":"ON",
    "sg:tags":[
        "church"
    ],
    "wof:name":"All Nations Full Gospel Church",
    "wof:placetype":"venue"
},
  "geometry": {"coordinates":[-79.0657196045,43.8333435059],"type":"Point"}
}