{
  "type": "Feature",
  "properties": {
    "addr:full":"General Delivery Fort Resolution NT X0E 0M0",
    "addr:postcode":"x0e 0m0",
    "addr:street":"Fort",
    "iso:country":"CA",
    "sg:address":"General Delivery",
    "sg:city":"Fort Resolution",
    "sg:classifiers":[
        {
            "category":"Organizations",
            "subcategory":"Religious Organization",
            "type":"Services"
        }
    ],
    "sg:phone":"+1 867 394 4461",
    "sg:postcode":"X0E 0M0",
    "sg:province":"NT",
    "sg:tags":[
        "church"
    ],
    "wof:name":"Pentecostal Church",
    "wof:placetype":"venue"
},
  "geometry": {"coordinates":[-113.757583618,60.9963569641],"type":"Point"}
}