{
  "type": "Feature",
  "properties": {
    "addr:full":"25 Beckwith St S Smiths Falls ON K7A 2A9",
    "addr:housenumber":"25",
    "addr:postcode":"k7a 2a9",
    "addr:street":"Beckwith St S",
    "iso:country":"CA",
    "sg:address":"25 Beckwith St S",
    "sg:city":"Smiths Falls",
    "sg:classifiers":[
        {
            "category":"Banks & Credit Unions",
            "subcategory":"Bank",
            "type":"Services"
        }
    ],
    "sg:phone":"+1 613 283 4292",
    "sg:postcode":"K7A 2A9",
    "sg:province":"ON",
    "wof:name":"Bank of Montreal",
    "wof:placetype":"venue"
},
  "geometry": {"coordinates":[-76.0209274292,44.8993606567],"type":"Point"}
}