{
  "type": "Feature",
  "properties": {
    "addr:full":"6722 Bertram Pl Saanichton BC V8M 1Z6",
    "addr:housenumber":"6722",
    "addr:postcode":"v8m 1z6",
    "addr:street":"Bertram Pl",
    "iso:country":"CA",
    "sg:address":"6722 Bertram Pl",
    "sg:city":"Saanichton",
    "sg:classifiers":[
        {
            "category":"Utilities",
            "subcategory":"Refuse",
            "type":"Services"
        }
    ],
    "sg:phone":"+1 250 544 1764",
    "sg:postcode":"V8M 1Z6",
    "sg:province":"BC",
    "sg:tags":[
        "equipment",
        "recycling",
        "system"
    ],
    "wof:name":"Industrial Recycling Systems",
    "wof:placetype":"venue"
},
  "geometry": {"coordinates":[-123.416893,48.5952],"type":"Point"}
}