{
  "type": "Feature",
  "properties": {
    "addr:full":"270 Killam Dr Moncton NB E1C 3S4",
    "addr:housenumber":"270",
    "addr:postcode":"e1c 3s4",
    "addr:street":"Killam Dr",
    "iso:country":"CA",
    "sg:address":"270 Killam Dr",
    "sg:city":"Moncton",
    "sg:phone":"+1 506 857 3101",
    "sg:postcode":"E1C 3S4",
    "sg:province":"NB",
    "sg:tags":[
        "oil"
    ],
    "wof:name":"Esso Home Heating",
    "wof:placetype":"venue"
},
  "geometry": {"coordinates":[-64.82489,46.09531],"type":"Point"}
}