{
  "type": "Feature",
  "properties": {
    "addr:full":"2020 Rue University # 2300 Montreal QC H3A 2A5",
    "addr:housenumber":"2020;#",
    "addr:postcode":"h3a 2a5",
    "addr:street":"Rue University",
    "iso:country":"CA",
    "sg:address":"2020 Rue University # 2300",
    "sg:city":"Montreal",
    "sg:classifiers":[
        {
            "category":"Education",
            "subcategory":"Special Training",
            "type":"Public Place"
        }
    ],
    "sg:phone":"+1 514 287 7433",
    "sg:postcode":"H3A 2A5",
    "sg:province":"QC",
    "sg:tags":[
        "school",
        "language"
    ],
    "wof:name":"Ecole DE Langues Caron Ltee",
    "wof:placetype":"venue"
},
  "geometry": {"coordinates":[-73.57186900000001,45.50407],"type":"Point"}
}