{
  "type": "Feature",
  "properties": {
    "addr:full":"Waterloo QC J0E 2N0",
    "addr:postcode":"j0e 2n0",
    "iso:country":"CA",
    "sg:city":"Waterloo",
    "sg:classifiers":[
        {
            "category":"Health Services",
            "subcategory":"Doctor",
            "type":"Services"
        }
    ],
    "sg:phone":"+1 450 539 1102",
    "sg:postcode":"J0E 2N0",
    "sg:province":"QC",
    "sg:tags":[
        "clinic"
    ],
    "wof:name":"Clinique Medica Waterloo",
    "wof:placetype":"venue"
},
  "geometry": {"coordinates":[-72.516006,45.343864],"type":"Point"}
}