{
  "type": "Feature",
  "properties": {
    "iso:country":"CA",
    "sg:address":"185 Rue Sainte-Catherine O",
    "sg:city":"Montreal",
    "sg:classifiers":[
        {
            "category":"Restaurant",
            "type":"Food & Drink"
        }
    ],
    "sg:phone":"+1 514 847 6900",
    "sg:postcode":"H2X 3X5",
    "sg:province":"QC",
    "wof:name":"Restaurant LA Rotonde",
    "wof:placetype":"venue"
},
  "geometry": {"coordinates":[-73.5625305176,45.5115776062],"type":"Point"}
}