{
  "type": "Feature",
  "properties": {
    "iso:country":"CA",
    "sg:address":"92 Geary Ave",
    "sg:city":"Toronto",
    "sg:classifiers":[
        {
            "category":"Manufacturing",
            "subcategory":"Furniture",
            "type":"Manufacturing & Wholesale Goods"
        }
    ],
    "sg:phone":"+1 416 533 2693",
    "sg:postcode":"M6H 2B6",
    "sg:province":"ON",
    "wof:name":"Sharp Design Furniture",
    "wof:placetype":"venue"
},
  "geometry": {"coordinates":[-79.4336776733,43.6707496643],"type":"Point"}
}