{
  "type": "Feature",
  "properties": {
    "iso:country":"CA",
    "sg:address":"4406 58 St S",
    "sg:city":"Lethbridge",
    "sg:classifiers":[
        {
            "category":"Wholesale",
            "subcategory":"Machinery & Supplies",
            "type":"Manufacturing & Wholesale Goods"
        }
    ],
    "sg:phone":"+1 403 380 5047",
    "sg:postcode":"T1K 7E2",
    "sg:province":"AB",
    "sg:tags":[
        "machine",
        "equipment",
        "tool",
        "industrial"
    ],
    "wof:name":"Haco Canada Inc",
    "wof:placetype":"venue"
},
  "geometry": {"coordinates":[-112.756782532,49.6666069031],"type":"Point"}
}