{
  "type": "Feature",
  "properties": {
    "addr:full":"11401 89 Ave Grande Prairie AB T8V 7M9",
    "addr:housenumber":"11401",
    "addr:postcode":"t8v 7m9",
    "addr:street":"89 Ave",
    "iso:country":"CA",
    "sg:address":"11401 89 Ave",
    "sg:city":"Grande Prairie",
    "sg:classifiers":[
        {
            "category":"Building & Trades",
            "subcategory":"Plumbing",
            "type":"Services"
        }
    ],
    "sg:phone":"+1 780 513 8820",
    "sg:postcode":"T8V 7M9",
    "sg:province":"AB",
    "sg:tags":[
        "system",
        "contractor",
        "heating",
        "refrigeration",
        "conditioning",
        "air"
    ],
    "wof:name":"Albright Refrigeration Heating",
    "wof:placetype":"venue"
},
  "geometry": {"coordinates":[-118.840614319,55.158908844],"type":"Point"}
}