{
  "type": "Feature",
  "properties": {
    "addr:full":"3115 Goldstein Rd Washago ON L0K 2B0",
    "addr:housenumber":"3115",
    "addr:postcode":"l0k 2b0",
    "addr:street":"Goldstein Rd",
    "iso:country":"CA",
    "sg:address":"3115 Goldstein Rd",
    "sg:city":"Washago",
    "sg:classifiers":[
        {
            "category":"Professional",
            "subcategory":"Accounting & Tax Preparation",
            "type":"Services"
        }
    ],
    "sg:phone":"+1 705 689 8295",
    "sg:postcode":"L0K 2B0",
    "sg:province":"ON",
    "sg:tags":[
        "accountant"
    ],
    "wof:name":"Hanson, Marilyn",
    "wof:placetype":"venue"
},
  "geometry": {"coordinates":[-79.33865356450001,44.7217674255],"type":"Point"}
}