{
  "type": "Feature",
  "properties": {
    "addr:full":"1550 Cameron St Hawkesbury ON K6A 3S5",
    "addr:housenumber":"1550",
    "addr:postcode":"k6a 3s5",
    "addr:street":"Cameron St",
    "iso:country":"CA",
    "sg:address":"1550 Cameron St",
    "sg:city":"Hawkesbury",
    "sg:classifiers":[
        {
            "category":"Shopping",
            "subcategory":"Pharmacy",
            "type":"Retail Goods"
        }
    ],
    "sg:phone":"+1 613 632 6062",
    "sg:postcode":"K6A 3S5",
    "sg:province":"ON",
    "wof:name":"Zellers Pharmacy",
    "wof:placetype":"venue"
},
  "geometry": {"coordinates":[-74.600685,45.592323],"type":"Point"}
}