{
  "type": "Feature",
  "properties": {
    "iso:country":"CA",
    "sg:address":"9 Main St N",
    "sg:city":"Montague",
    "sg:classifiers":[
        {
            "category":"Manufacturing",
            "subcategory":"Printing",
            "type":"Manufacturing & Wholesale Goods"
        }
    ],
    "sg:phone":"+1 902 838 2521",
    "sg:postcode":"C0A 1R0",
    "sg:province":"PE",
    "sg:tags":[
        "newspaper"
    ],
    "wof:name":"Guardian",
    "wof:placetype":"venue"
},
  "geometry": {"coordinates":[-62.6485519409,46.1646270752],"type":"Point"}
}