{
  "type": "Feature",
  "properties": {
    "addr:full":"Vancouver BC V6G 1N2",
    "addr:postcode":"v6g 1n2",
    "iso:country":"CA",
    "sg:city":"Vancouver",
    "sg:classifiers":[
        {
            "category":"Building & Trades",
            "subcategory":"Construction",
            "type":"Services"
        }
    ],
    "sg:phone":"+1 604 688 2970",
    "sg:postcode":"V6G 1N2",
    "sg:province":"BC",
    "sg:tags":[
        "dock"
    ],
    "wof:name":"Lindmeier's Docks Unlimited",
    "wof:placetype":"venue"
},
  "geometry": {"coordinates":[-123.14061,49.290436],"type":"Point"}
}