{
  "type": "Feature",
  "properties": {
    "addr:full":"Waterloo ON N2J 1P8",
    "addr:postcode":"n2j 1p8",
    "iso:country":"CA",
    "sg:city":"Waterloo",
    "sg:classifiers":[
        {
            "category":"Banks & Credit Unions",
            "subcategory":"Investment Brokerage",
            "type":"Services"
        }
    ],
    "sg:phone":"+1 519 742 9991",
    "sg:postcode":"N2J 1P8",
    "sg:province":"ON",
    "sg:tags":[
        "consultant",
        "planning",
        "financial"
    ],
    "wof:name":"National Bank Financial Inc",
    "wof:placetype":"venue"
},
  "geometry": {"coordinates":[-80.51922607420001,43.4605140686],"type":"Point"}
}