{
  "type": "Feature",
  "properties": {
    "addr:full":"22133 Hwy 17 Iron Bridge ON P0R 1H0",
    "addr:housenumber":"22133",
    "addr:postcode":"p0r 1h0",
    "addr:street":"Hwy 17 Iron Bridge",
    "iso:country":"CA",
    "sg:address":"22133 Hwy 17",
    "sg:city":"Iron Bridge",
    "sg:classifiers":[
        {
            "category":"Travel",
            "subcategory":"Hotels & Motels",
            "type":"Entertainment"
        }
    ],
    "sg:phone":"+1 705 843 2100",
    "sg:postcode":"P0R 1H0",
    "sg:province":"ON",
    "wof:name":"Red Top Motor Inn",
    "wof:placetype":"venue"
},
  "geometry": {"coordinates":[-83.2261962891,46.278591156],"type":"Point"}
}