{
  "type": "Feature",
  "properties": {
    "addr:full":"2337 Richter St Kelowna BC V1Y 2P3",
    "addr:housenumber":"2337",
    "addr:postcode":"v1y 2p3",
    "addr:street":"Richter St",
    "iso:country":"CA",
    "sg:address":"2337 Richter St",
    "sg:city":"Kelowna",
    "sg:classifiers":[
        {
            "category":"Social Services",
            "subcategory":"Child Care",
            "type":"Services"
        }
    ],
    "sg:phone":"+1 250 762 9344",
    "sg:postcode":"V1Y 2P3",
    "sg:province":"BC",
    "wof:name":"Cameron Park Day Care",
    "wof:placetype":"venue"
},
  "geometry": {"coordinates":[-119.488052,49.871647],"type":"Point"}
}