{
  "type": "Feature",
  "properties": {
    "addr:full":"703 Clearbrook Rd Abbotsford BC V2T 5X1",
    "addr:housenumber":"703",
    "addr:postcode":"v2t 5x1",
    "addr:street":"Clearbrook Rd",
    "iso:country":"CA",
    "sg:address":"703 Clearbrook Rd",
    "sg:city":"Abbotsford",
    "sg:classifiers":[
        {
            "category":"Retail",
            "subcategory":"Auto Repair",
            "type":"Services"
        }
    ],
    "sg:phone":"+1 604 859 5586",
    "sg:postcode":"V2T 5X1",
    "sg:province":"BC",
    "sg:tags":[
        "automobile",
        "restoration",
        "classic"
    ],
    "wof:name":"Olde Iron Auto Works",
    "wof:placetype":"venue"
},
  "geometry": {"coordinates":[-122.33782959,49.0138816833],"type":"Point"}
}