{
  "type": "Feature",
  "properties": {
    "addr:full":"10919 Alaska Rd Fort St John BC V1J 6P3",
    "addr:housenumber":"10919",
    "addr:postcode":"v1j 6p3",
    "addr:street":"Alaska Rd",
    "iso:country":"CA",
    "sg:address":"10919 Alaska Rd",
    "sg:city":"Fort St John",
    "sg:classifiers":[
        {
            "category":"Wholesale",
            "subcategory":"Machinery & Supplies",
            "type":"Manufacturing & Wholesale Goods"
        }
    ],
    "sg:phone":"+1 250 785 0285",
    "sg:postcode":"V1J 6P3",
    "sg:province":"BC",
    "sg:tags":[
        "field",
        "oil",
        "equipment"
    ],
    "wof:name":"Spartan Controls",
    "wof:placetype":"venue"
},
  "geometry": {"coordinates":[-120.861954,56.241467],"type":"Point"}
}