{
  "type": "Feature",
  "properties": {
    "addr:full":"1050 Ellesmere Rd Scarborough ON M1P 2X3",
    "addr:housenumber":"1050",
    "addr:postcode":"m1p 2x3",
    "addr:street":"Ellesmere Rd",
    "iso:country":"CA",
    "sg:address":"1050 Ellesmere Rd",
    "sg:city":"Scarborough",
    "sg:classifiers":[
        {
            "category":"Government",
            "subcategory":"Office",
            "type":"Public Place"
        }
    ],
    "sg:phone":"+1 416 396 7372",
    "sg:postcode":"M1P 2X3",
    "sg:province":"ON",
    "sg:tags":[
        "village"
    ],
    "wof:name":"Toronto Recycling Depot",
    "wof:placetype":"venue"
},
  "geometry": {"coordinates":[-79.2724761963,43.7677536011],"type":"Point"}
}