{
  "type": "Feature",
  "properties": {
    "addr:full":"57 Carson St Etobicoke ON M8W 3S1",
    "addr:housenumber":"57",
    "addr:postcode":"m8w 3s1",
    "addr:street":"Carson St",
    "iso:country":"CA",
    "sg:address":"57 Carson St",
    "sg:city":"Etobicoke",
    "sg:classifiers":[
        {
            "category":"Retail",
            "subcategory":"Auto Repair",
            "type":"Services"
        }
    ],
    "sg:phone":"+1 416 255 5001",
    "sg:postcode":"M8W 3S1",
    "sg:province":"ON",
    "sg:tags":[
        "body",
        "automobile",
        "painting"
    ],
    "wof:name":"Carson Collision Ctr",
    "wof:placetype":"venue"
},
  "geometry": {"coordinates":[-79.5340957642,43.6025161743],"type":"Point"}
}