{
  "type": "Feature",
  "properties": {
    "addr:full":"3700 Rue Saint-Denis Montreal QC H2X 3L7",
    "addr:housenumber":"3700",
    "addr:postcode":"h2x 3l7",
    "addr:street":"Rue Saint-Denis",
    "iso:country":"CA",
    "sg:address":"3700 Rue Saint-Denis",
    "sg:city":"Montreal",
    "sg:classifiers":[
        {
            "category":"Home & Garden",
            "subcategory":"Furniture",
            "type":"Retail Goods"
        }
    ],
    "sg:phone":"+1 514 282 2062",
    "sg:postcode":"H2X 3L7",
    "sg:province":"QC",
    "sg:tags":[
        "futon"
    ],
    "wof:name":"Futon Svp",
    "wof:placetype":"venue"
},
  "geometry": {"coordinates":[-73.57107499999999,45.518421],"type":"Point"}
}