{
  "type": "Feature",
  "properties": {
    "addr:full":"NE 30 1 20 Boissevain MB R0K 0E0",
    "addr:housenumber":"20",
    "addr:postcode":"r0k 0e0",
    "addr:street":"Ne 30 1",
    "iso:country":"CA",
    "sg:address":"NE 30 1 20",
    "sg:city":"Boissevain",
    "sg:classifiers":[
        {
            "category":"Travel",
            "subcategory":"Campground",
            "type":"Entertainment"
        }
    ],
    "sg:phone":"+1 204 534 2504",
    "sg:postcode":"R0K 0E0",
    "sg:province":"MB",
    "sg:tags":[
        "camp"
    ],
    "wof:name":"Camp Koinonia",
    "wof:placetype":"venue"
},
  "geometry": {"coordinates":[-100.059456,49.229626],"type":"Point"}
}