{
  "type": "Feature",
  "properties": {
    "addr:full":"6465 120 St Delta BC V4E 3G3",
    "addr:housenumber":"6465",
    "addr:postcode":"v4e 3g3",
    "addr:street":"120 St",
    "iso:country":"CA",
    "sg:address":"6465 120 St",
    "sg:city":"Delta",
    "sg:classifiers":[
        {
            "category":"Health Services",
            "subcategory":"Doctor",
            "type":"Services"
        }
    ],
    "sg:phone":"+1 604 591 7700",
    "sg:postcode":"V4E 3G3",
    "sg:province":"BC",
    "sg:tags":[
        "dentist"
    ],
    "wof:name":"Persson, Brad A DDS",
    "wof:placetype":"venue"
},
  "geometry": {"coordinates":[-122.890563965,49.1204414368],"type":"Point"}
}