{
  "type": "Feature",
  "properties": {
    "addr:full":"1002 Rue Saint-Urbain Montreal QC H2Z 1K6",
    "addr:housenumber":"1002",
    "addr:postcode":"h2z 1k6",
    "addr:street":"Rue Saint-Urbain",
    "iso:country":"CA",
    "sg:address":"1002 Rue Saint-Urbain",
    "sg:city":"Montreal",
    "sg:classifiers":[
        {
            "category":"Shopping",
            "subcategory":"Florist",
            "type":"Retail Goods"
        }
    ],
    "sg:phone":"+1 514 861 5059",
    "sg:postcode":"H2Z 1K6",
    "sg:province":"QC",
    "wof:name":"Helen Florist & Gift Shop",
    "wof:placetype":"venue"
},
  "geometry": {"coordinates":[-73.5604019165,45.506565094],"type":"Point"}
}