{
  "type": "Feature",
  "properties": {
    "addr:full":"190 Boul Labelle Sainte-Therese QC J7E 2X5",
    "addr:housenumber":"190",
    "addr:postcode":"j7e 2x5",
    "addr:street":"Boul Labelle Sainte-Therese",
    "iso:country":"CA",
    "sg:address":"190 Boul Labelle",
    "sg:city":"Sainte-Therese",
    "sg:classifiers":[
        {
            "category":"Restaurant",
            "type":"Food & Drink"
        }
    ],
    "sg:phone":"+1 450 437 1261",
    "sg:postcode":"J7E 2X5",
    "sg:province":"QC",
    "wof:name":"Restaurant Le Friand Oeuf Inc",
    "wof:placetype":"venue"
},
  "geometry": {"coordinates":[-73.833054,45.642979],"type":"Point"}
}