{
  "type": "Feature",
  "properties": {
    "addr:full":"99 Rue Quevillon Varennes QC J3X 1X6",
    "addr:housenumber":"99",
    "addr:postcode":"j3x 1x6",
    "addr:street":"Rue Quevillon",
    "iso:country":"CA",
    "sg:address":"99 Rue Quevillon",
    "sg:city":"Varennes",
    "sg:classifiers":[
        {
            "category":"Shopping",
            "subcategory":"Optical Goods",
            "type":"Retail Goods"
        }
    ],
    "sg:phone":"+1 450 652 2191",
    "sg:postcode":"J3X 1X6",
    "sg:province":"QC",
    "sg:tags":[
        "optician"
    ],
    "wof:name":"Lunetterie F Farhat",
    "wof:placetype":"venue"
},
  "geometry": {"coordinates":[-73.43105300000001,45.686321],"type":"Point"}
}