{
  "type": "Feature",
  "properties": {
    "addr:full":"350 St George St S Dresden ON N0P 1M0",
    "addr:housenumber":"350",
    "addr:postcode":"n0p 1m0",
    "addr:street":"St George St S",
    "iso:country":"CA",
    "sg:address":"350 St George St S",
    "sg:city":"Dresden",
    "sg:classifiers":[
        {
            "category":"Organizations",
            "subcategory":"Religious Organization",
            "type":"Services"
        }
    ],
    "sg:phone":"+1 519 683 4050",
    "sg:postcode":"N0P 1M0",
    "sg:province":"ON",
    "sg:tags":[
        "church"
    ],
    "wof:name":"Christ Church",
    "wof:placetype":"venue"
},
  "geometry": {"coordinates":[-82.1797332764,42.5914268494],"type":"Point"}
}