{
  "type": "Feature",
  "properties": {
    "addr:full":"61 Rue Gautreau Cap-Pele NB E4N 1V2",
    "addr:housenumber":"61",
    "addr:postcode":"e4n 1v2",
    "addr:street":"Rue Gautreau",
    "iso:country":"CA",
    "sg:address":"61 Rue Gautreau",
    "sg:city":"Cap-Pele",
    "sg:classifiers":[
        {
            "category":"Manufacturing",
            "subcategory":"Food",
            "type":"Manufacturing & Wholesale Goods"
        }
    ],
    "sg:phone":"+1 506 577 2993",
    "sg:postcode":"E4N 1V2",
    "sg:province":"NB",
    "sg:tags":[
        "packer",
        "fish"
    ],
    "wof:name":"Michel/Charles Leblanc Fishery",
    "wof:placetype":"venue"
},
  "geometry": {"coordinates":[-64.2580108643,46.2324409485],"type":"Point"}
}