{
  "type": "Feature",
  "properties": {
    "addr:full":"Oakville ON L6J 7W5",
    "addr:postcode":"l6j 7w5",
    "iso:country":"CA",
    "sg:city":"Oakville",
    "sg:classifiers":[
        {
            "category":"Professional",
            "subcategory":"Accounting & Tax Preparation",
            "type":"Services"
        }
    ],
    "sg:phone":"+1 905 338 8343",
    "sg:postcode":"L6J 7W5",
    "sg:province":"ON",
    "sg:tags":[
        "accountant"
    ],
    "wof:name":"John Macdonald & Assoc",
    "wof:placetype":"venue"
},
  "geometry": {"coordinates":[-79.662727,43.474735],"type":"Point"}
}