{
  "type": "Feature",
  "properties": {
    "addr:full":"3789 Royal Oak Ave Burnaby BC V5G 3M1",
    "addr:housenumber":"3789",
    "addr:postcode":"v5g 3m1",
    "addr:street":"Royal Oak Ave",
    "iso:country":"CA",
    "sg:address":"3789 Royal Oak Ave",
    "sg:city":"Burnaby",
    "sg:classifiers":[
        {
            "category":"Retail",
            "subcategory":"Funeral Services",
            "type":"Services"
        }
    ],
    "sg:phone":"+1 604 299 7720",
    "sg:postcode":"V5G 3M1",
    "sg:province":"BC",
    "sg:tags":[
        "director"
    ],
    "wof:name":"Forest Lawn Funeral Home",
    "wof:placetype":"venue"
},
  "geometry": {"coordinates":[-122.98912,49.250038],"type":"Point"}
}