{
  "type": "Feature",
  "properties": {
    "addr:full":"215 Av Proulx Vanier QC G1M 1W6",
    "addr:housenumber":"215",
    "addr:postcode":"g1m 1w6",
    "addr:street":"Av Proulx",
    "iso:country":"CA",
    "sg:address":"215 Av Proulx",
    "sg:city":"Vanier",
    "sg:classifiers":[
        {
            "category":"Personal",
            "subcategory":"Beauty Salon",
            "type":"Services"
        }
    ],
    "sg:phone":"+1 418 683 7165",
    "sg:postcode":"G1M 1W6",
    "sg:province":"QC",
    "wof:name":"Salon Marcelle Cloutier Enr",
    "wof:placetype":"venue"
},
  "geometry": {"coordinates":[-71.258171,46.814514],"type":"Point"}
}