{
  "type": "Feature",
  "properties": {
    "iso:country":"CA",
    "sg:address":"1147 Lawrence Ave W",
    "sg:city":"North York",
    "sg:classifiers":[
        {
            "category":"Home & Garden",
            "subcategory":"Building Materials",
            "type":"Retail Goods"
        }
    ],
    "sg:phone":"+1 416 657 2436",
    "sg:postcode":"M6A 1E1",
    "sg:province":"ON",
    "sg:tags":[
        "glass",
        "window",
        "plate"
    ],
    "wof:name":"Agm Car Care & Glass",
    "wof:placetype":"venue"
},
  "geometry": {"coordinates":[-79.4650726318,43.7116737366],"type":"Point"}
}