{
  "type": "Feature",
  "properties": {
    "addr:full":"593 Rue Bureau Trois-Rivieres QC G9A 2N2",
    "addr:housenumber":"593",
    "addr:postcode":"g9a 2n2",
    "addr:street":"Rue Bureau Trois-Rivieres",
    "iso:country":"CA",
    "sg:address":"593 Rue Bureau",
    "sg:city":"Trois-Rivieres",
    "sg:classifiers":[
        {
            "category":"Social Services",
            "type":"Services"
        }
    ],
    "sg:phone":"+1 819 374 6164",
    "sg:postcode":"G9A 2N2",
    "sg:province":"QC",
    "sg:tags":[
        "info",
        "drug",
        "abuse",
        "treatment",
        "welfare",
        "organization",
        "addiction"
    ],
    "wof:name":"Maison DE Sobriete-Trois Rvrs",
    "wof:placetype":"venue"
},
  "geometry": {"coordinates":[-72.54806499999999,46.340034],"type":"Point"}
}