{
  "type": "Feature",
  "properties": {
    "addr:full":"5359 Boul Saint-Michel Montreal QC H1Y 2C8",
    "addr:housenumber":"5359",
    "addr:postcode":"h1y 2c8",
    "addr:street":"Boul Saint-Michel",
    "iso:country":"CA",
    "sg:address":"5359 Boul Saint-Michel",
    "sg:city":"Montreal",
    "sg:classifiers":[
        {
            "category":"Retail",
            "subcategory":"Funeral Services",
            "type":"Services"
        }
    ],
    "sg:phone":"+1 514 721 4925",
    "sg:postcode":"H1Y 2C8",
    "sg:province":"QC",
    "sg:tags":[
        "director"
    ],
    "wof:name":"J A Guilbault Inc",
    "wof:placetype":"venue"
},
  "geometry": {"coordinates":[-73.5722961426,45.5508842468],"type":"Point"}
}