{
  "type": "Feature",
  "properties": {
    "addr:full":"Prince Albert SK S6V 1C6",
    "addr:postcode":"s6v 1c6",
    "iso:country":"CA",
    "sg:city":"Prince Albert",
    "sg:classifiers":[
        {
            "category":"Professional",
            "subcategory":"Lawyer & Legal Services",
            "type":"Services"
        }
    ],
    "sg:phone":"+1 306 763 7441",
    "sg:postcode":"S6V 1C6",
    "sg:province":"SK",
    "sg:tags":[
        "attorney"
    ],
    "wof:name":"Eggum Abrametz & Eggum",
    "wof:placetype":"venue"
},
  "geometry": {"coordinates":[-105.751778,53.201496],"type":"Point"}
}