{
  "type": "Feature",
  "properties": {
    "addr:full":"25 Bentall St Winnipeg MB R2X 2Z7",
    "addr:housenumber":"25",
    "addr:postcode":"r2x 2z7",
    "addr:street":"Bentall St",
    "iso:country":"CA",
    "sg:address":"25 Bentall St",
    "sg:city":"Winnipeg",
    "sg:phone":"+1 204 771 4070",
    "sg:postcode":"R2X 2Z7",
    "sg:province":"MB",
    "sg:tags":[
        "equipment",
        "supply"
    ],
    "wof:name":"Williams Restaurant Equipment",
    "wof:placetype":"venue"
},
  "geometry": {"coordinates":[-97.177986,49.93327],"type":"Point"}
}