{
  "type": "Feature",
  "properties": {
    "iso:country":"CA",
    "sg:address":"2645 Main St",
    "sg:city":"Barrington",
    "sg:classifiers":[
        {
            "category":"Autos & Motor Vehicles",
            "subcategory":"Automobile Sales",
            "type":"Retail Goods"
        }
    ],
    "sg:phone":"+1 902 637 3880",
    "sg:postcode":"B0W 1E0",
    "sg:province":"NS",
    "sg:tags":[
        "car",
        "dealer"
    ],
    "wof:name":"Messenger Motor Sales Ltd",
    "wof:placetype":"venue"
},
  "geometry": {"coordinates":[-65.56322479249999,43.5638275146],"type":"Point"}
}