{
  "type": "Feature",
  "properties": {
    "addr:full":"Atholville NB E3N 4E2",
    "addr:postcode":"e3n 4e2",
    "iso:country":"CA",
    "sg:city":"Atholville",
    "sg:classifiers":[
        {
            "category":"Home & Garden",
            "subcategory":"Household Appliances",
            "type":"Retail Goods"
        }
    ],
    "sg:phone":"+1 506 753 6261",
    "sg:postcode":"E3N 4E2",
    "sg:province":"NB",
    "wof:name":"Sears Canada Inc",
    "wof:placetype":"venue"
},
  "geometry": {"coordinates":[-66.71411895750001,47.9930801392],"type":"Point"}
}