{
  "type": "Feature",
  "properties": {
    "addr:full":"Cambridge ON N1R 6J9",
    "addr:postcode":"n1r 6j9",
    "iso:country":"CA",
    "sg:city":"Cambridge",
    "sg:classifiers":[
        {
            "category":"Manufacturing",
            "subcategory":"Pet Food",
            "type":"Manufacturing & Wholesale Goods"
        }
    ],
    "sg:phone":"+1 519 620 2488",
    "sg:postcode":"N1R 6J9",
    "sg:province":"ON",
    "sg:tags":[
        "laboratory",
        "health",
        "animal"
    ],
    "wof:name":"Gallant Custom Laboratories",
    "wof:placetype":"venue"
},
  "geometry": {"coordinates":[-80.321068,43.395935],"type":"Point"}
}