{
  "type": "Feature",
  "properties": {
    "iso:country":"CA",
    "sg:address":"7889 Boul Saint-Laurent",
    "sg:city":"Montreal",
    "sg:classifiers":[
        {
            "category":"Manufacturing",
            "subcategory":"Apparel",
            "type":"Manufacturing & Wholesale Goods"
        }
    ],
    "sg:phone":"+1 514 271 9799",
    "sg:postcode":"H2R 1X1",
    "sg:province":"QC",
    "sg:tags":[
        "infant",
        "wear",
        "clothes"
    ],
    "wof:name":"Zighi Children's Wear Inc",
    "wof:placetype":"venue"
},
  "geometry": {"coordinates":[-73.6277313232,45.5380744934],"type":"Point"}
}