{
  "type": "Feature",
  "properties": {
    "addr:full":"1629 Main St Vancouver BC V6A 2W5",
    "addr:housenumber":"1629",
    "addr:postcode":"v6a 2w5",
    "addr:street":"Main St",
    "iso:country":"CA",
    "sg:address":"1629 Main St",
    "sg:city":"Vancouver",
    "sg:classifiers":[
        {
            "category":"Shopping",
            "type":"Retail Goods"
        }
    ],
    "sg:phone":"+1 604 681 7351",
    "sg:postcode":"V6A 2W5",
    "sg:province":"BC",
    "sg:tags":[
        "material",
        "artist",
        "supply"
    ],
    "wof:name":"Loomis Art Store",
    "wof:placetype":"venue"
},
  "geometry": {"coordinates":[-123.10080719,49.2708244324],"type":"Point"}
}