{
  "type": "Feature",
  "properties": {
    "addr:full":"320 Rue Demers Sherbrooke QC J1E 3W9",
    "addr:housenumber":"320",
    "addr:postcode":"j1e 3w9",
    "addr:street":"Rue Demers",
    "iso:country":"CA",
    "sg:address":"320 Rue Demers",
    "sg:city":"Sherbrooke",
    "sg:classifiers":[
        {
            "category":"Personal",
            "subcategory":"Beauty Salon",
            "type":"Services"
        }
    ],
    "sg:phone":"+1 819 565 2911",
    "sg:postcode":"J1E 3W9",
    "sg:province":"QC",
    "wof:name":"Salon DE Coiffure Decy-Bel",
    "wof:placetype":"venue"
},
  "geometry": {"coordinates":[-71.86274719239999,45.413684845],"type":"Point"}
}