{
  "type": "Feature",
  "properties": {
    "addr:full":"6004 Hwy 24 Lone Butte BC V0K 1X0",
    "addr:housenumber":"6004",
    "addr:postcode":"v0k 1x0",
    "addr:street":"Hwy 24 Lone",
    "iso:country":"CA",
    "sg:address":"6004 Hwy 24",
    "sg:city":"Lone Butte",
    "sg:classifiers":[
        {
            "category":"Manufacturing",
            "subcategory":"Tools & Machinery",
            "type":"Manufacturing & Wholesale Goods"
        }
    ],
    "sg:phone":"+1 250 395 1727",
    "sg:postcode":"V0K 1X0",
    "sg:province":"BC",
    "sg:tags":[
        "repairing",
        "automobile",
        "alternator"
    ],
    "wof:name":"Lone Butte Svc Ctr",
    "wof:placetype":"venue"
},
  "geometry": {"coordinates":[-121.19493866000001,51.5545310974],"type":"Point"}
}