{
  "type": "Feature",
  "properties": {
    "addr:full":"14963 Marine Dr White Rock BC V4B 1C3",
    "addr:housenumber":"14963",
    "addr:postcode":"v4b 1c3",
    "addr:street":"Marine Dr",
    "iso:country":"CA",
    "sg:address":"14963 Marine Dr",
    "sg:city":"White Rock",
    "sg:classifiers":[
        {
            "category":"Shopping",
            "subcategory":"Gifts & Souvenirs",
            "type":"Retail Goods"
        }
    ],
    "sg:phone":"+1 604 538 7107",
    "sg:postcode":"V4B 1C3",
    "sg:province":"BC",
    "sg:tags":[
        "shop"
    ],
    "wof:name":"Tweezle Junction",
    "wof:placetype":"venue"
},
  "geometry": {"coordinates":[-122.807029724,49.0218582153],"type":"Point"}
}