{
  "type": "Feature",
  "properties": {
    "addr:full":"1100 Mountain Rd Moncton NB E1C 2T2",
    "addr:housenumber":"1100",
    "addr:postcode":"e1c 2t2",
    "addr:street":"Mountain Rd",
    "iso:country":"CA",
    "sg:address":"1100 Mountain Rd",
    "sg:city":"Moncton",
    "sg:classifiers":[
        {
            "category":"Restaurant",
            "type":"Food & Drink"
        }
    ],
    "sg:phone":"+1 506 862 7647",
    "sg:postcode":"E1C 2T2",
    "sg:province":"NB",
    "wof:name":"Wendy's",
    "wof:placetype":"venue"
},
  "geometry": {"coordinates":[-64.8209075928,46.1051330566],"type":"Point"}
}