{
  "type": "Feature",
  "properties": {
    "addr:full":"Vancouver BC V5T 4R6",
    "addr:postcode":"v5t 4r6",
    "iso:country":"CA",
    "sg:city":"Vancouver",
    "sg:classifiers":[
        {
            "category":"Professional",
            "subcategory":"Art Services",
            "type":"Services"
        }
    ],
    "sg:phone":"+1 604 737 1958",
    "sg:postcode":"V5T 4R6",
    "sg:province":"BC",
    "sg:tags":[
        "graphic",
        "designer"
    ],
    "wof:name":"Industrial Brand Creative Inc",
    "wof:placetype":"venue"
},
  "geometry": {"coordinates":[-123.096779,49.267883],"type":"Point"}
}