{
  "type": "Feature",
  "properties": {
    "addr:full":"20361 Duncan Way Langley BC V3A 7N3",
    "addr:housenumber":"20361",
    "addr:postcode":"v3a 7n3",
    "addr:street":"Duncan Way",
    "iso:country":"CA",
    "sg:address":"20361 Duncan Way",
    "sg:city":"Langley",
    "sg:classifiers":[
        {
            "category":"Manufacturing",
            "subcategory":"Textiles",
            "type":"Manufacturing & Wholesale Goods"
        }
    ],
    "sg:phone":"+1 604 532 3883",
    "sg:postcode":"V3A 7N3",
    "sg:province":"BC",
    "sg:tags":[
        "coating",
        "waterproofing"
    ],
    "wof:name":"Fabrikem Manufacturing Ltd",
    "wof:placetype":"venue"
},
  "geometry": {"coordinates":[-122.659484863,49.1098480225],"type":"Point"}
}