{
  "type": "Feature",
  "properties": {
    "addr:full":"Prophet River BC V0C 2V0",
    "addr:postcode":"v0c 2v0",
    "iso:country":"CA",
    "sg:city":"Prophet River",
    "sg:classifiers":[
        {
            "category":"Mining & Drilling",
            "type":"Manufacturing & Wholesale Goods"
        }
    ],
    "sg:phone":"+1 250 773 6333",
    "sg:postcode":"V0C 2V0",
    "sg:province":"BC",
    "sg:tags":[
        "field",
        "oil"
    ],
    "wof:name":"Prophet River Contracting Ltd",
    "wof:placetype":"venue"
},
  "geometry": {"coordinates":[-122.718643,58.118019],"type":"Point"}
}