{
  "type": "Feature",
  "properties": {
    "addr:full":"5203 50 Ave Red Deer AB T4N 4B4",
    "addr:housenumber":"5203",
    "addr:postcode":"t4n 4b4",
    "addr:street":"50 Ave",
    "iso:country":"CA",
    "sg:address":"5203 50 Ave",
    "sg:city":"Red Deer",
    "sg:classifiers":[
        {
            "category":"Sports & Exercise",
            "subcategory":"Gym",
            "type":"Entertainment"
        }
    ],
    "sg:phone":"+1 403 346 6772",
    "sg:postcode":"T4N 4B4",
    "sg:province":"AB",
    "sg:tags":[
        "arts",
        "club",
        "instruction",
        "gymnasium",
        "martial",
        "health",
        "studio"
    ],
    "wof:name":"Taoist Tai Chi Society-Canada",
    "wof:placetype":"venue"
},
  "geometry": {"coordinates":[-113.813926697,52.2710075378],"type":"Point"}
}