{
  "type": "Feature",
  "properties": {
    "addr:full":"25 Howard St Toronto ON M4X 1J6",
    "addr:housenumber":"25",
    "addr:postcode":"m4x 1j6",
    "addr:street":"Howard St",
    "iso:country":"CA",
    "sg:address":"25 Howard St",
    "sg:city":"Toronto",
    "sg:classifiers":[
        {
            "category":"Shopping",
            "subcategory":"Pharmacy",
            "type":"Retail Goods"
        }
    ],
    "sg:phone":"+1 416 515 1515",
    "sg:postcode":"M4X 1J6",
    "sg:province":"ON",
    "wof:name":"Howard Pharmacy",
    "wof:placetype":"venue"
},
  "geometry": {"coordinates":[-79.375557,43.671204],"type":"Point"}
}