{
  "type": "Feature",
  "properties": {
    "iso:country":"CA",
    "sg:address":"123 London Rd",
    "sg:city":"Thamesville",
    "sg:classifiers":[
        {
            "category":"Autos & Motor Vehicles",
            "subcategory":"Automobile Sales",
            "type":"Retail Goods"
        }
    ],
    "sg:phone":"+1 519 692 3906",
    "sg:postcode":"N0P 2K0",
    "sg:province":"ON",
    "sg:tags":[
        "car",
        "dealer"
    ],
    "wof:name":"Dickson Motors",
    "wof:placetype":"venue"
},
  "geometry": {"coordinates":[-81.978996,42.55151],"type":"Point"}
}