{
  "type": "Feature",
  "properties": {
    "addr:full":"470 Dundas St E # 2 Belleville ON K8N 1G1",
    "addr:housenumber":"470",
    "addr:postcode":"k8n 1g1",
    "addr:street":"Dundas St E # 2",
    "iso:country":"CA",
    "sg:address":"470 Dundas St E # 2",
    "sg:city":"Belleville",
    "sg:classifiers":[
        {
            "category":"Organizations",
            "subcategory":"Professional Association",
            "type":"Services"
        }
    ],
    "sg:phone":"+1 613 962 0892",
    "sg:postcode":"K8N 1G1",
    "sg:province":"ON",
    "wof:name":"Alzheimer Society Belleville",
    "wof:placetype":"venue"
},
  "geometry": {"coordinates":[-77.35340118409999,44.1675300598],"type":"Point"}
}