{
  "type": "Feature",
  "properties": {
    "iso:country":"CA",
    "sg:address":"138 Station St",
    "sg:city":"Duncan",
    "sg:classifiers":[
        {
            "category":"Shopping",
            "subcategory":"Shoes",
            "type":"Retail Goods"
        }
    ],
    "sg:phone":"+1 250 746 7523",
    "sg:postcode":"V9L 1M7",
    "sg:province":"BC",
    "sg:tags":[
        "clothing",
        "furnishing"
    ],
    "wof:name":"Charlie Onn Mens' Fashions",
    "wof:placetype":"venue"
},
  "geometry": {"coordinates":[-123.70903778100001,48.7775192261],"type":"Point"}
}