{
  "type": "Feature",
  "properties": {
    "addr:full":"281 Campbell St Sarnia ON N7T 2H2",
    "addr:housenumber":"281",
    "addr:postcode":"n7t 2h2",
    "addr:street":"Campbell St",
    "iso:country":"CA",
    "sg:address":"281 Campbell St",
    "sg:city":"Sarnia",
    "sg:classifiers":[
        {
            "category":"Wholesale",
            "subcategory":"Machinery & Supplies",
            "type":"Manufacturing & Wholesale Goods"
        }
    ],
    "sg:phone":"+1 519 336 9797",
    "sg:postcode":"N7T 2H2",
    "sg:province":"ON",
    "sg:tags":[
        "equipment",
        "oil",
        "well"
    ],
    "wof:name":"C E Franklin Ltd",
    "wof:placetype":"venue"
},
  "geometry": {"coordinates":[-82.393593,42.958855],"type":"Point"}
}