{
  "type": "Feature",
  "properties": {
    "iso:country":"CA",
    "sg:address":"2211 19th Ave",
    "sg:city":"Nanton",
    "sg:classifiers":[
        {
            "category":"Farming",
            "subcategory":"Farm & Veterinary Services",
            "type":"Manufacturing & Wholesale Goods"
        }
    ],
    "sg:phone":"+1 403 646 2051",
    "sg:postcode":"T0L 1R0",
    "sg:province":"AB",
    "sg:tags":[
        "seed",
        "grain",
        "cleaning"
    ],
    "wof:name":"Nanton Seed Cleaning Plant Ltd",
    "wof:placetype":"venue"
},
  "geometry": {"coordinates":[-113.76739502,50.346408844],"type":"Point"}
}