{
  "type": "Feature",
  "properties": {
    "iso:country":"CA",
    "sg:address":"64 Vaughan Rd",
    "sg:city":"Toronto",
    "sg:classifiers":[
        {
            "category":"Health Services",
            "subcategory":"Chiropractor",
            "type":"Services"
        }
    ],
    "sg:phone":"+1 416 654 4542",
    "sg:postcode":"M6G 2N4",
    "sg:province":"ON",
    "sg:tags":[
        "physiotherapist"
    ],
    "wof:name":"Toronto Health Care Group",
    "wof:placetype":"venue"
},
  "geometry": {"coordinates":[-79.41998291020001,43.6824951172],"type":"Point"}
}