{
  "type": "Feature",
  "properties": {
    "iso:country":"CA",
    "sg:address":"16302 106 Ave NW",
    "sg:city":"Edmonton",
    "sg:classifiers":[
        {
            "category":"Organizations",
            "subcategory":"Religious Organization",
            "type":"Services"
        }
    ],
    "sg:phone":"+1 780 489 5803",
    "sg:postcode":"T5P 0W9",
    "sg:province":"AB",
    "sg:tags":[
        "church"
    ],
    "wof:name":"Ebenezer United Church",
    "wof:placetype":"venue"
},
  "geometry": {"coordinates":[-113.602859497,53.5499000549],"type":"Point"}
}