{
  "type": "Feature",
  "properties": {
    "addr:full":"548 Boul Perron Carleton QC G0C 1J0",
    "addr:housenumber":"548",
    "addr:postcode":"g0c 1j0",
    "addr:street":"Boul Perron",
    "iso:country":"CA",
    "sg:address":"548 Boul Perron",
    "sg:city":"Carleton",
    "sg:classifiers":[
        {
            "category":"Restaurant",
            "type":"Food & Drink"
        }
    ],
    "sg:phone":"+1 418 364 7618",
    "sg:postcode":"G0C 1J0",
    "sg:province":"QC",
    "wof:name":"St-Honore",
    "wof:placetype":"venue"
},
  "geometry": {"coordinates":[-66.127808,48.105343],"type":"Point"}
}