{
  "type": "Feature",
  "properties": {
    "addr:full":"PO Box 171 Bruce AB T0B 0R0",
    "addr:housenumber":"po",
    "addr:postcode":"t0b 0r0",
    "addr:street":"Box 171",
    "iso:country":"CA",
    "sg:address":"PO Box 171",
    "sg:city":"Bruce",
    "sg:classifiers":[
        {
            "category":"Farming",
            "subcategory":"Farm",
            "type":"Manufacturing & Wholesale Goods"
        }
    ],
    "sg:phone":"+1 780 688 2186",
    "sg:postcode":"T0B 0R0",
    "sg:province":"AB",
    "wof:name":"Oat Farm",
    "wof:placetype":"venue"
},
  "geometry": {"coordinates":[-112.039161682,53.1728210449],"type":"Point"}
}