{
  "type": "Feature",
  "properties": {
    "addr:full":"22 Anderson Rd Beachburg ON K0J 1C0",
    "addr:housenumber":"22",
    "addr:postcode":"k0j 1c0",
    "addr:street":"Anderson Rd",
    "iso:country":"CA",
    "sg:address":"22 Anderson Rd",
    "sg:city":"Beachburg",
    "sg:classifiers":[
        {
            "category":"Manufacturing",
            "subcategory":"Glass & Minerals",
            "type":"Manufacturing & Wholesale Goods"
        }
    ],
    "sg:phone":"+1 613 582 3459",
    "sg:postcode":"K0J 1C0",
    "sg:province":"ON",
    "sg:tags":[
        "concrete",
        "brick",
        "block",
        "septic"
    ],
    "wof:name":"Mac Gregor Concrete Products",
    "wof:placetype":"venue"
},
  "geometry": {"coordinates":[-76.851799,45.725029],"type":"Point"}
}