{
  "type": "Feature",
  "properties": {
    "addr:full":"13800 Boul Gouin O Pierrefonds QC H8Z 3H6",
    "addr:housenumber":"13800",
    "addr:postcode":"h8z 3h6",
    "addr:street":"Boul Gouin O",
    "iso:country":"CA",
    "sg:address":"13800 Boul Gouin O",
    "sg:city":"Pierrefonds",
    "sg:classifiers":[
        {
            "category":"Health Services",
            "subcategory":"Doctor",
            "type":"Services"
        }
    ],
    "sg:phone":"+1 514 626 2572",
    "sg:postcode":"H8Z 3H6",
    "sg:province":"QC",
    "sg:tags":[
        "clinic"
    ],
    "wof:name":"Clinique Sante-Voyage",
    "wof:placetype":"venue"
},
  "geometry": {"coordinates":[-73.8487243652,45.4977798462],"type":"Point"}
}