{
  "type": "Feature",
  "properties": {
    "addr:full":"6617 Longwoods Rd Melbourne ON N0L 1T0",
    "addr:housenumber":"6617",
    "addr:postcode":"n0l 1t0",
    "addr:street":"Longwoods Rd",
    "iso:country":"CA",
    "sg:address":"6617 Longwoods Rd",
    "sg:city":"Melbourne",
    "sg:classifiers":[
        {
            "category":"Retail",
            "subcategory":"Auto Repair",
            "type":"Services"
        }
    ],
    "sg:phone":"+1 519 289 2422",
    "sg:postcode":"N0L 1T0",
    "sg:province":"ON",
    "sg:tags":[
        "repairing",
        "automobile"
    ],
    "wof:name":"Automotive Professional Svc",
    "wof:placetype":"venue"
},
  "geometry": {"coordinates":[-81.55061340330001,42.8179397583],"type":"Point"}
}