{
  "type": "Feature",
  "properties": {
    "iso:country":"CA",
    "sg:address":"290 Mcclellan Way",
    "sg:city":"Aurora",
    "sg:classifiers":[
        {
            "category":"Social Services",
            "subcategory":"Child Care",
            "type":"Services"
        }
    ],
    "sg:phone":"+1 905 841 7742",
    "sg:postcode":"L4G 6P3",
    "sg:province":"ON",
    "wof:name":"Light of Christ Child Care Ctr",
    "wof:placetype":"venue"
},
  "geometry": {"coordinates":[-79.484673,43.970963],"type":"Point"}
}