{
  "type": "Feature",
  "properties": {
    "iso:country":"CA",
    "sg:address":"30 Nova Cres",
    "sg:city":"Welland",
    "sg:classifiers":[
        {
            "category":"Health Services",
            "subcategory":"Nursing And Care Facility",
            "type":"Services"
        }
    ],
    "sg:phone":"+1 905 788 1844",
    "sg:postcode":"L3C 6P8",
    "sg:province":"ON",
    "sg:tags":[
        "home",
        "retirement",
        "community"
    ],
    "wof:name":"St Charles Retirement Village",
    "wof:placetype":"venue"
},
  "geometry": {"coordinates":[-79.2392425537,42.9934501648],"type":"Point"}
}