{
  "type": "Feature",
  "properties": {
    "iso:country":"CA",
    "sg:address":"207 Rue Gamble O",
    "sg:city":"Rouyn-Noranda",
    "sg:classifiers":[
        {
            "category":"Personal",
            "type":"Services"
        }
    ],
    "sg:phone":"+1 819 762 0856",
    "sg:postcode":"J9X 2R8",
    "sg:province":"QC",
    "sg:tags":[
        "therapist",
        "massage"
    ],
    "wof:name":"Principautes DE Daniel",
    "wof:placetype":"venue"
},
  "geometry": {"coordinates":[-79.0260314941,48.2397651672],"type":"Point"}
}