{
  "type": "Feature",
  "properties": {
    "iso:country":"CA",
    "sg:address":"950 Dixon Rd # 160",
    "sg:city":"Etobicoke",
    "sg:classifiers":[
        {
            "category":"Personal",
            "subcategory":"Beauty Salon",
            "type":"Services"
        }
    ],
    "sg:phone":"+1 416 675 7854",
    "sg:postcode":"M9W 1J9",
    "sg:province":"ON",
    "wof:name":"Mario's Hairgrooming Place",
    "wof:placetype":"venue"
},
  "geometry": {"coordinates":[-79.597298,43.686932],"type":"Point"}
}