{
  "type": "Feature",
  "properties": {
    "addr:full":"347 Rue Comtois Chicoutimi QC G7G 4K4",
    "addr:housenumber":"347",
    "addr:postcode":"g7g 4k4",
    "addr:street":"Rue Comtois",
    "iso:country":"CA",
    "sg:address":"347 Rue Comtois",
    "sg:city":"Chicoutimi",
    "sg:classifiers":[
        {
            "category":"Building & Trades",
            "subcategory":"Construction",
            "type":"Services"
        }
    ],
    "sg:phone":"+1 418 543 4788",
    "sg:postcode":"G7G 4K4",
    "sg:province":"QC",
    "sg:tags":[
        "excavating",
        "contractor"
    ],
    "wof:name":"Terrassement Brt Enr",
    "wof:placetype":"venue"
},
  "geometry": {"coordinates":[-71.05935700000001,48.448685],"type":"Point"}
}