{
  "type": "Feature",
  "properties": {
    "addr:full":"Saskatoon SK S7K 8A9",
    "addr:postcode":"s7k 8a9",
    "iso:country":"CA",
    "sg:city":"Saskatoon",
    "sg:classifiers":[
        {
            "category":"Professional",
            "subcategory":"Engineering",
            "type":"Services"
        }
    ],
    "sg:phone":"+1 306 934 2442",
    "sg:postcode":"S7K 8A9",
    "sg:province":"SK",
    "sg:tags":[
        "engineer"
    ],
    "wof:name":"Jbs Engineering Inc",
    "wof:placetype":"venue"
},
  "geometry": {"coordinates":[-106.650963,52.175259],"type":"Point"}
}