{
  "type": "Feature",
  "properties": {
    "addr:full":"154 University Ave # 510 Toronto ON M5H 3Y9",
    "addr:housenumber":"154",
    "addr:postcode":"m5h 3y9",
    "addr:street":"University Ave # 510",
    "iso:country":"CA",
    "sg:address":"154 University Ave # 510",
    "sg:city":"Toronto",
    "sg:classifiers":[
        {
            "category":"Professional",
            "subcategory":"Lawyer & Legal Services",
            "type":"Services"
        }
    ],
    "sg:phone":"+1 416 848 6993",
    "sg:postcode":"M5H 3Y9",
    "sg:province":"ON",
    "sg:tags":[
        "consultant",
        "planning",
        "estate"
    ],
    "wof:name":"Asset Planning Group",
    "wof:placetype":"venue"
},
  "geometry": {"coordinates":[-79.3854293823,43.6483840942],"type":"Point"}
}