{
  "type": "Feature",
  "properties": {
    "addr:full":"663 Third Line Oakville ON L6L 4A9",
    "addr:housenumber":"663",
    "addr:postcode":"l6l 4a9",
    "addr:street":"Third Line",
    "iso:country":"CA",
    "sg:address":"663 Third Line",
    "sg:city":"Oakville",
    "sg:classifiers":[
        {
            "category":"Manufacturing",
            "subcategory":"Metals",
            "type":"Manufacturing & Wholesale Goods"
        }
    ],
    "sg:phone":"+1 905 825 0015",
    "sg:postcode":"L6L 4A9",
    "sg:province":"ON",
    "sg:tags":[
        "steel"
    ],
    "wof:name":"Klacko Spars Ltd",
    "wof:placetype":"venue"
},
  "geometry": {"coordinates":[-79.718559,43.419769],"type":"Point"}
}