{
  "type": "Feature",
  "properties": {
    "addr:full":"Mississauga ON L4Y 2B1",
    "addr:postcode":"l4y 2b1",
    "iso:country":"CA",
    "sg:city":"Mississauga",
    "sg:classifiers":[
        {
            "category":"Health Services",
            "subcategory":"Doctor",
            "type":"Services"
        }
    ],
    "sg:phone":"+1 905 625 1681",
    "sg:postcode":"L4Y 2B1",
    "sg:province":"ON",
    "sg:tags":[
        "physician",
        "surgeon"
    ],
    "wof:name":"Leung, Robert Sai MD",
    "wof:placetype":"venue"
},
  "geometry": {"coordinates":[-79.5953292847,43.6174850464],"type":"Point"}
}