{
  "type": "Feature",
  "properties": {
    "addr:full":"11 Av Addison Scoudouc NB E4P 3N3",
    "addr:postcode":"e4p 3n3",
    "addr:street":"11 Av Addison",
    "iso:country":"CA",
    "sg:address":"11 Av Addison",
    "sg:city":"Scoudouc",
    "sg:classifiers":[
        {
            "category":"Manufacturing",
            "subcategory":"Food",
            "type":"Manufacturing & Wholesale Goods"
        }
    ],
    "sg:phone":"+1 506 532 6111",
    "sg:postcode":"E4P 3N3",
    "sg:province":"NB",
    "sg:tags":[
        "packer",
        "fish"
    ],
    "wof:name":"Eastern Sea Products Ltd",
    "wof:placetype":"venue"
},
  "geometry": {"coordinates":[-64.587456,46.168007],"type":"Point"}
}