{
  "type": "Feature",
  "properties": {
    "addr:full":"151 Ch Des Raymond Riviere-Du-Loup QC G5R 5X9",
    "addr:housenumber":"151",
    "addr:postcode":"g5r 5x9",
    "addr:street":"Ch Des Raymond Riviere-Du-Loup",
    "iso:country":"CA",
    "sg:address":"151 Ch Des Raymond",
    "sg:city":"Riviere-Du-Loup",
    "sg:classifiers":[
        {
            "category":"Freight",
            "type":"Transportation"
        }
    ],
    "sg:phone":"+1 418 867 1541",
    "sg:postcode":"G5R 5X9",
    "sg:province":"QC",
    "sg:tags":[
        "mover"
    ],
    "wof:name":"Demenagement Grand Portage Inc",
    "wof:placetype":"venue"
},
  "geometry": {"coordinates":[-69.5008773804,47.8371124268],"type":"Point"}
}