{
  "type": "Feature",
  "properties": {
    "iso:country":"CA",
    "sg:address":"2929 15 St NE",
    "sg:city":"Calgary",
    "sg:classifiers":[
        {
            "category":"Mining & Drilling",
            "type":"Manufacturing & Wholesale Goods"
        }
    ],
    "sg:phone":"+1 403 250 7225",
    "sg:postcode":"T2E 7L8",
    "sg:province":"AB",
    "sg:tags":[
        "development",
        "gas",
        "oil",
        "exploration"
    ],
    "wof:name":"Tudor Corp Ltd",
    "wof:placetype":"venue"
},
  "geometry": {"coordinates":[-114.022766113,51.0787124634],"type":"Point"}
}