{
  "type": "Feature",
  "properties": {
    "addr:full":"Vancouver BC V6J 1Z3",
    "addr:postcode":"v6j 1z3",
    "iso:country":"CA",
    "sg:city":"Vancouver",
    "sg:classifiers":[
        {
            "category":"Retail",
            "subcategory":"Laundry & Dry Cleaning",
            "type":"Services"
        }
    ],
    "sg:phone":"+1 604 731 5351",
    "sg:postcode":"V6J 1Z3",
    "sg:province":"BC",
    "sg:tags":[
        "cleaners",
        "rug",
        "carpet"
    ],
    "wof:name":"Cleaning Connection",
    "wof:placetype":"venue"
},
  "geometry": {"coordinates":[-123.148781,49.263908],"type":"Point"}
}