{
  "type": "Feature",
  "properties": {
    "addr:full":"5425 Main St Pointe Aux Roches ON N0R 1N0",
    "addr:housenumber":"5425",
    "addr:postcode":"n0r 1n0",
    "addr:street":"Main St",
    "iso:country":"CA",
    "sg:address":"5425 Main St",
    "sg:city":"Pointe Aux Roches",
    "sg:classifiers":[
        {
            "category":"Retail",
            "subcategory":"Auto Repair",
            "type":"Services"
        }
    ],
    "sg:phone":"+1 519 798 3314",
    "sg:postcode":"N0R 1N0",
    "sg:province":"ON",
    "sg:tags":[
        "body",
        "automobile",
        "painting"
    ],
    "wof:name":"Gerry's Body Shop",
    "wof:placetype":"venue"
},
  "geometry": {"coordinates":[-82.55171199999999,42.314281],"type":"Point"}
}