{
  "type": "Feature",
  "properties": {
    "addr:full":"6700 Av Du Parc Montreal QC H2V 4H9",
    "addr:housenumber":"6700",
    "addr:postcode":"h2v 4h9",
    "addr:street":"Av Du Parc",
    "iso:country":"CA",
    "sg:address":"6700 Av Du Parc",
    "sg:city":"Montreal",
    "sg:classifiers":[
        {
            "category":"Manufacturing",
            "subcategory":"Printing",
            "type":"Manufacturing & Wholesale Goods"
        }
    ],
    "sg:phone":"+1 514 948 4227",
    "sg:postcode":"H2V 4H9",
    "sg:province":"QC",
    "sg:tags":[
        "printer"
    ],
    "wof:name":"Inst-Art Litho Inc",
    "wof:placetype":"venue"
},
  "geometry": {"coordinates":[-73.6150588989,45.5277557373],"type":"Point"}
}