{
  "type": "Feature",
  "properties": {
    "addr:full":"948 Attersley Dr Oshawa ON L1K 1V5",
    "addr:housenumber":"948",
    "addr:postcode":"l1k 1v5",
    "addr:street":"Attersley Dr",
    "iso:country":"CA",
    "sg:address":"948 Attersley Dr",
    "sg:city":"Oshawa",
    "sg:classifiers":[
        {
            "category":"Building & Trades",
            "subcategory":"Landscaping Services",
            "type":"Services"
        }
    ],
    "sg:phone":"+1 905 725 3948",
    "sg:postcode":"L1K 1V5",
    "sg:province":"ON",
    "sg:tags":[
        "lawn",
        "maintenance",
        "grounds"
    ],
    "wof:name":"Four Seasons Lawncare",
    "wof:placetype":"venue"
},
  "geometry": {"coordinates":[-78.8469238281,43.9279975891],"type":"Point"}
}