{
  "type": "Feature",
  "properties": {
    "addr:full":"360 Bloor St W # 309 Toronto ON M5S 1X1",
    "addr:housenumber":"360",
    "addr:postcode":"m5s 1x1",
    "addr:street":"Bloor St W # 309",
    "iso:country":"CA",
    "sg:address":"360 Bloor St W # 309",
    "sg:city":"Toronto",
    "sg:classifiers":[
        {
            "category":"Health Services",
            "subcategory":"Doctor",
            "type":"Services"
        }
    ],
    "sg:phone":"+1 416 925 0411",
    "sg:postcode":"M5S 1X1",
    "sg:province":"ON",
    "sg:tags":[
        "physician",
        "surgeon"
    ],
    "wof:name":"Felix, John L MD",
    "wof:placetype":"venue"
},
  "geometry": {"coordinates":[-79.4052200317,43.6664505005],"type":"Point"}
}