{
  "type": "Feature",
  "properties": {
    "addr:full":"Winnipeg MB R3L 2R4",
    "addr:postcode":"r3l 2r4",
    "iso:country":"CA",
    "sg:city":"Winnipeg",
    "sg:classifiers":[
        {
            "category":"Banks & Credit Unions",
            "subcategory":"Investment Brokerage",
            "type":"Services"
        }
    ],
    "sg:phone":"+1 204 452 4193",
    "sg:postcode":"R3L 2R4",
    "sg:province":"MB",
    "sg:tags":[
        "trade",
        "barter",
        "exchange"
    ],
    "wof:name":"Canadian Barter System",
    "wof:placetype":"venue"
},
  "geometry": {"coordinates":[-97.14637,49.878838],"type":"Point"}
}