{
  "type": "Feature",
  "properties": {
    "addr:full":"145 Windy Oaks Mississauga ON L5G 1Z4",
    "addr:housenumber":"145",
    "addr:postcode":"l5g 1z4",
    "addr:street":"Windy Oaks",
    "iso:country":"CA",
    "sg:address":"145 Windy Oaks",
    "sg:city":"Mississauga",
    "sg:classifiers":[
        {
            "category":"Education",
            "subcategory":"School",
            "type":"Public Place"
        }
    ],
    "sg:phone":"+1 905 278 3144",
    "sg:postcode":"L5G 1Z4",
    "sg:province":"ON",
    "wof:name":"Mineola School",
    "wof:placetype":"venue"
},
  "geometry": {"coordinates":[-79.5841293335,43.5637893677],"type":"Point"}
}