{
  "type": "Feature",
  "properties": {
    "addr:full":"128 David St N Noelville ON P0M 2N0",
    "addr:housenumber":"128",
    "addr:postcode":"p0m 2n0",
    "addr:street":"David St N",
    "iso:country":"CA",
    "sg:address":"128 David St N",
    "sg:city":"Noelville",
    "sg:classifiers":[
        {
            "category":"Professional",
            "subcategory":"Accounting & Tax Preparation",
            "type":"Services"
        }
    ],
    "sg:phone":"+1 705 898 2307",
    "sg:postcode":"P0M 2N0",
    "sg:province":"ON",
    "sg:tags":[
        "return",
        "filing"
    ],
    "wof:name":"Turenne's Income Tax Svc",
    "wof:placetype":"venue"
},
  "geometry": {"coordinates":[-80.4316711426,46.1341705322],"type":"Point"}
}