{
  "type": "Feature",
  "properties": {
    "iso:country":"CA",
    "sg:address":"2060 Commerce Park Dr",
    "sg:city":"Innisfil",
    "sg:classifiers":[
        {
            "category":"Home & Garden",
            "subcategory":"Furniture",
            "type":"Retail Goods"
        }
    ],
    "sg:phone":"+1 705 436 5535",
    "sg:postcode":"L9S 4A3",
    "sg:province":"ON",
    "sg:tags":[
        "interior",
        "consultant",
        "design",
        "decorator"
    ],
    "wof:name":"Munro's Furnishings",
    "wof:placetype":"venue"
},
  "geometry": {"coordinates":[-79.67589569090001,44.2840538025],"type":"Point"}
}