{
  "type": "Feature",
  "properties": {
    "iso:country":"CA",
    "sg:city":"Sainte-Sophie",
    "sg:classifiers":[
        {
            "category":"Building & Trades",
            "subcategory":"Plumbing",
            "type":"Services"
        }
    ],
    "sg:phone":"+1 450 432 5698",
    "sg:postcode":"J5J 2S8",
    "sg:province":"QC",
    "sg:tags":[
        "contractor"
    ],
    "wof:name":"Plomberie Coteau",
    "wof:placetype":"venue"
},
  "geometry": {"coordinates":[-74.02001953120001,45.8405265808],"type":"Point"}
}