{
  "type": "Feature",
  "properties": {
    "addr:full":"8276 Conc 8 RR 2 Utopia ON L0M 1T0",
    "addr:housenumber":"8276;8 rr 2",
    "addr:postcode":"l0m 1t0",
    "addr:street":"Conc",
    "iso:country":"CA",
    "sg:address":"8276 Conc 8 RR 2",
    "sg:city":"Utopia",
    "sg:classifiers":[
        {
            "category":"Building & Trades",
            "subcategory":"Construction",
            "type":"Services"
        }
    ],
    "sg:phone":"+1 705 424 7126",
    "sg:postcode":"L0M 1T0",
    "sg:province":"ON",
    "sg:tags":[
        "concrete",
        "contractor"
    ],
    "wof:name":"Ken Muir Concrete Floor",
    "wof:placetype":"venue"
},
  "geometry": {"coordinates":[-79.838615,44.33247],"type":"Point"}
}