{
  "type": "Feature",
  "properties": {
    "addr:full":"510 Boul Cure-Labelle Laval QC H7V 2T2",
    "addr:housenumber":"510",
    "addr:postcode":"h7v 2t2",
    "addr:street":"Boul Cure-Labelle",
    "iso:country":"CA",
    "sg:address":"510 Boul Cure-Labelle",
    "sg:city":"Laval",
    "sg:classifiers":[
        {
            "category":"Retail",
            "subcategory":"Auto Repair",
            "type":"Services"
        }
    ],
    "sg:phone":"+1 450 688 4941",
    "sg:postcode":"H7V 2T2",
    "sg:province":"QC",
    "sg:tags":[
        "muffler",
        "exhaust",
        "system"
    ],
    "wof:name":"Silencieux Gms",
    "wof:placetype":"venue"
},
  "geometry": {"coordinates":[-73.7388534546,45.5377235413],"type":"Point"}
}