{
  "type": "Feature",
  "properties": {
    "addr:full":"The Pas MB R9A 1K3",
    "addr:postcode":"r9a 1k3",
    "iso:country":"CA",
    "sg:city":"The Pas",
    "sg:classifiers":[
        {
            "category":"Food & Beverages",
            "subcategory":"Specialty",
            "type":"Retail Goods"
        }
    ],
    "sg:phone":"+1 204 623 5542",
    "sg:postcode":"R9A 1K3",
    "sg:province":"MB",
    "sg:tags":[
        "water",
        "bulk",
        "company"
    ],
    "wof:name":"Northern Water Svc",
    "wof:placetype":"venue"
},
  "geometry": {"coordinates":[-101.25035095200001,53.8134307861],"type":"Point"}
}