{
  "type": "Feature",
  "properties": {
    "addr:full":"8255 Burnlake Dr Burnaby BC V5A 3L1",
    "addr:housenumber":"8255",
    "addr:postcode":"v5a 3l1",
    "addr:street":"Burnlake Dr",
    "iso:country":"CA",
    "sg:address":"8255 Burnlake Dr",
    "sg:city":"Burnaby",
    "sg:classifiers":[
        {
            "category":"Arts & Performance",
            "subcategory":"Theater",
            "type":"Entertainment"
        }
    ],
    "sg:phone":"+1 604 421 1570",
    "sg:postcode":"V5A 3L1",
    "sg:province":"BC",
    "sg:tags":[
        "live",
        "music"
    ],
    "wof:name":"Packard Systems Mobile Music",
    "wof:placetype":"venue"
},
  "geometry": {"coordinates":[-122.92424,49.250084],"type":"Point"}
}