{
  "type": "Feature",
  "properties": {
    "addr:full":"3004 120 Ave NE Edmonton AB T6S 1E1",
    "addr:housenumber":"3004",
    "addr:postcode":"t6s 1e1",
    "addr:street":"120 Ave Ne",
    "iso:country":"CA",
    "sg:address":"3004 120 Ave NE",
    "sg:city":"Edmonton",
    "sg:classifiers":[
        {
            "category":"Retail",
            "subcategory":"Auto Repair",
            "type":"Services"
        }
    ],
    "sg:phone":"+1 780 457 1401",
    "sg:postcode":"T6S 1E1",
    "sg:province":"AB",
    "sg:tags":[
        "body",
        "automobile",
        "painting"
    ],
    "wof:name":"Xray Autobody",
    "wof:placetype":"venue"
},
  "geometry": {"coordinates":[-113.299858,53.573376],"type":"Point"}
}