{
  "type": "Feature",
  "properties": {
    "addr:full":"Moonbeam ON P0L 1V0",
    "addr:postcode":"p0l 1v0",
    "iso:country":"CA",
    "sg:city":"Moonbeam",
    "sg:classifiers":[
        {
            "category":"Travel",
            "subcategory":"Hotels & Motels",
            "type":"Entertainment"
        }
    ],
    "sg:phone":"+1 705 367 2450",
    "sg:postcode":"P0L 1V0",
    "sg:province":"ON",
    "sg:tags":[
        "tourist",
        "accommodation"
    ],
    "wof:name":"Kap Outfitters",
    "wof:placetype":"venue"
},
  "geometry": {"coordinates":[-82.19330600000001,49.40633],"type":"Point"}
}