{
  "type": "Feature",
  "properties": {
    "iso:country":"CA",
    "sg:address":"120 Oakdale Rd # 7",
    "sg:city":"North York",
    "sg:classifiers":[
        {
            "category":"Retail",
            "subcategory":"Auto Repair",
            "type":"Services"
        }
    ],
    "sg:phone":"+1 416 746 1400",
    "sg:postcode":"M3N 1V9",
    "sg:province":"ON",
    "sg:tags":[
        "automobile",
        "electric"
    ],
    "wof:name":"Rexdale Alternator & Starter",
    "wof:placetype":"venue"
},
  "geometry": {"coordinates":[-79.52619934080001,43.7426757812],"type":"Point"}
}