{
  "type": "Feature",
  "properties": {
    "addr:full":"1870 Albion Rd Etobicoke ON M9W 5T2",
    "addr:housenumber":"1870",
    "addr:postcode":"m9w 5t2",
    "addr:street":"Albion Rd",
    "iso:country":"CA",
    "sg:address":"1870 Albion Rd",
    "sg:city":"Etobicoke",
    "sg:classifiers":[
        {
            "category":"Manufacturing",
            "subcategory":"Chemicals & Compounds",
            "type":"Manufacturing & Wholesale Goods"
        }
    ],
    "sg:phone":"+1 416 675 7225",
    "sg:postcode":"M9W 5T2",
    "sg:province":"ON",
    "wof:name":"Premier Packaging Inc",
    "wof:placetype":"venue"
},
  "geometry": {"coordinates":[-79.6176605225,43.746257782],"type":"Point"}
}