{
  "type": "Feature",
  "properties": {
    "iso:country":"CA",
    "sg:city":"Brossard",
    "sg:classifiers":[
        {
            "category":"Professional",
            "subcategory":"Accounting & Tax Preparation",
            "type":"Services"
        }
    ],
    "sg:phone":"+1 450 465 2220",
    "sg:postcode":"J4W 3B3",
    "sg:province":"QC",
    "sg:tags":[
        "accountant"
    ],
    "wof:name":"Bergeron & Senecal",
    "wof:placetype":"venue"
},
  "geometry": {"coordinates":[-73.47454833979999,45.4737739563],"type":"Point"}
}