{
  "type": "Feature",
  "properties": {
    "addr:full":"20 Front St E Strathroy ON N7G 1Y4",
    "addr:housenumber":"20",
    "addr:postcode":"n7g 1y4",
    "addr:street":"Front St E",
    "iso:country":"CA",
    "sg:address":"20 Front St E",
    "sg:city":"Strathroy",
    "sg:classifiers":[
        {
            "category":"Autos & Motor Vehicles",
            "subcategory":"Auto Supplies",
            "type":"Retail Goods"
        }
    ],
    "sg:phone":"+1 519 245 2720",
    "sg:postcode":"N7G 1Y4",
    "sg:province":"ON",
    "sg:tags":[
        "automobile",
        "parts"
    ],
    "wof:name":"Ross Automotive",
    "wof:placetype":"venue"
},
  "geometry": {"coordinates":[-81.6232376099,42.9588661194],"type":"Point"}
}