{
  "type": "Feature",
  "properties": {
    "addr:full":"Haliburton ON K0M 1S0",
    "addr:postcode":"k0m 1s0",
    "iso:country":"CA",
    "sg:city":"Haliburton",
    "sg:classifiers":[
        {
            "category":"Autos & Motor Vehicles",
            "subcategory":"Automobile Sales",
            "type":"Retail Goods"
        }
    ],
    "sg:phone":"+1 705 457 2100",
    "sg:postcode":"K0M 1S0",
    "sg:province":"ON",
    "sg:tags":[
        "car",
        "dealer"
    ],
    "wof:name":"Curry Motors Ltd",
    "wof:placetype":"venue"
},
  "geometry": {"coordinates":[-78.508629,45.046371],"type":"Point"}
}