{
  "type": "Feature",
  "properties": {
    "addr:full":"Toronto ON M5K 1E6",
    "addr:postcode":"m5k 1e6",
    "iso:country":"CA",
    "sg:city":"Toronto",
    "sg:classifiers":[
        {
            "category":"Professional",
            "subcategory":"Lawyer & Legal Services",
            "type":"Services"
        }
    ],
    "sg:phone":"+1 416 362 1812",
    "sg:postcode":"M5K 1E6",
    "sg:province":"ON",
    "sg:tags":[
        "attorney"
    ],
    "wof:name":"Mc Carthy Tetrault Llp",
    "wof:placetype":"venue"
},
  "geometry": {"coordinates":[-79.3743362427,43.648639679],"type":"Point"}
}