{
  "type": "Feature",
  "properties": {
    "iso:country":"CA",
    "sg:address":"4714 Highway 2A",
    "sg:city":"Lacombe",
    "sg:classifiers":[
        {
            "category":"Home & Garden",
            "subcategory":"Building Materials",
            "type":"Retail Goods"
        }
    ],
    "sg:phone":"+1 403 782 6600",
    "sg:postcode":"T4L 1H4",
    "sg:province":"AB",
    "sg:tags":[
        "glass",
        "window",
        "plate"
    ],
    "wof:name":"Croft Glass Ltd",
    "wof:placetype":"venue"
},
  "geometry": {"coordinates":[-113.72217559800001,52.4684791565],"type":"Point"}
}