{
  "type": "Feature",
  "properties": {
    "addr:full":"1305 Rue Mazurette Montreal QC H4N 1G8",
    "addr:housenumber":"1305",
    "addr:postcode":"h4n 1g8",
    "addr:street":"Rue Mazurette",
    "iso:country":"CA",
    "sg:address":"1305 Rue Mazurette",
    "sg:city":"Montreal",
    "sg:classifiers":[
        {
            "category":"Manufacturing",
            "subcategory":"Textiles",
            "type":"Manufacturing & Wholesale Goods"
        }
    ],
    "sg:phone":"+1 514 383 4137",
    "sg:postcode":"H4N 1G8",
    "sg:province":"QC",
    "sg:tags":[
        "notion"
    ],
    "wof:name":"Tricot Abba",
    "wof:placetype":"venue"
},
  "geometry": {"coordinates":[-73.659721,45.532852],"type":"Point"}
}