{
  "type": "Feature",
  "properties": {
    "iso:country":"CA",
    "sg:address":"105 Rue Marie-DE-L'Incarnation",
    "sg:city":"Quebec",
    "sg:classifiers":[
        {
            "category":"Retail",
            "subcategory":"Auto Repair",
            "type":"Services"
        }
    ],
    "sg:phone":"+1 418 527 9093",
    "sg:postcode":"G1N 3E9",
    "sg:province":"QC",
    "sg:tags":[
        "muffler",
        "exhaust",
        "system"
    ],
    "wof:name":"Silencieux Lortie Inc",
    "wof:placetype":"venue"
},
  "geometry": {"coordinates":[-71.4194717407,46.858581543],"type":"Point"}
}