{
  "type": "Feature",
  "properties": {
    "addr:full":"North York ON M9M 1L7",
    "addr:postcode":"m9m 1l7",
    "iso:country":"CA",
    "sg:city":"North York",
    "sg:classifiers":[
        {
            "category":"Professional",
            "subcategory":"Advertising",
            "type":"Services"
        }
    ],
    "sg:phone":"+1 416 916 3700",
    "sg:postcode":"M9M 1L7",
    "sg:province":"ON",
    "sg:tags":[
        "newspaper"
    ],
    "wof:name":"Ghanaian News",
    "wof:placetype":"venue"
},
  "geometry": {"coordinates":[-79.53175354,43.7353172302],"type":"Point"}
}