{
  "type": "Feature",
  "properties": {
    "addr:full":"51 Main St Hantsport NS B0P 1P0",
    "addr:housenumber":"51",
    "addr:postcode":"b0p 1p0",
    "addr:street":"Main St",
    "iso:country":"CA",
    "sg:address":"51 Main St",
    "sg:city":"Hantsport",
    "sg:classifiers":[
        {
            "category":"Personal",
            "subcategory":"Beauty Salon",
            "type":"Services"
        }
    ],
    "sg:phone":"+1 902 684 0931",
    "sg:postcode":"B0P 1P0",
    "sg:province":"NS",
    "wof:name":"Hair Sense",
    "wof:placetype":"venue"
},
  "geometry": {"coordinates":[-64.18389129640001,45.0649223328],"type":"Point"}
}