{
  "type": "Feature",
  "properties": {
    "addr:full":"10159 Nordel Crt Delta BC V4G 1J8",
    "addr:housenumber":"10159",
    "addr:postcode":"v4g 1j8",
    "addr:street":"Nordel Crt",
    "iso:country":"CA",
    "sg:address":"10159 Nordel Crt",
    "sg:city":"Delta",
    "sg:classifiers":[
        {
            "category":"Professional",
            "subcategory":"Advertising",
            "type":"Services"
        }
    ],
    "sg:phone":"+1 604 951 6855",
    "sg:postcode":"V4G 1J8",
    "sg:province":"BC",
    "sg:tags":[
        "mail",
        "mailing",
        "shipping"
    ],
    "wof:name":"International Direct Response",
    "wof:placetype":"venue"
},
  "geometry": {"coordinates":[-122.941810608,49.1493530273],"type":"Point"}
}