{
  "type": "Feature",
  "properties": {
    "addr:full":"1680 Sargent Ave Winnipeg MB R3H 0C2",
    "addr:housenumber":"1680",
    "addr:postcode":"r3h 0c2",
    "addr:street":"Sargent Ave",
    "iso:country":"CA",
    "sg:address":"1680 Sargent Ave",
    "sg:city":"Winnipeg",
    "sg:classifiers":[
        {
            "category":"Professional",
            "subcategory":"Business Services",
            "type":"Services"
        }
    ],
    "sg:phone":"+1 204 783 3572",
    "sg:postcode":"R3H 0C2",
    "sg:province":"MB",
    "sg:tags":[
        "record"
    ],
    "wof:name":"Access Record Ctr Ltd",
    "wof:placetype":"venue"
},
  "geometry": {"coordinates":[-97.202324,49.897762],"type":"Point"}
}