{
  "type": "Feature",
  "properties": {
    "addr:full":"Brandon MB R7A 5B6",
    "addr:postcode":"r7a 5b6",
    "iso:country":"CA",
    "sg:city":"Brandon",
    "sg:classifiers":[
        {
            "category":"Shopping",
            "subcategory":"Florist",
            "type":"Retail Goods"
        }
    ],
    "sg:phone":"+1 204 727 7673",
    "sg:postcode":"R7A 5B6",
    "sg:province":"MB",
    "wof:name":"Grower Direct Fresh Cut Flower",
    "wof:placetype":"venue"
},
  "geometry": {"coordinates":[-99.96163900000001,49.838428],"type":"Point"}
}