{
  "type": "Feature",
  "properties": {
    "addr:full":"718 Cathcart Blvd Sarnia ON N7V 2N5",
    "addr:housenumber":"718",
    "addr:postcode":"n7v 2n5",
    "addr:street":"Cathcart Blvd",
    "iso:country":"CA",
    "sg:address":"718 Cathcart Blvd",
    "sg:city":"Sarnia",
    "sg:classifiers":[
        {
            "category":"Organizations",
            "subcategory":"Religious Organization",
            "type":"Services"
        }
    ],
    "sg:phone":"+1 519 383 6933",
    "sg:postcode":"N7V 2N5",
    "sg:province":"ON",
    "sg:tags":[
        "church"
    ],
    "wof:name":"St Bartholomew's Anglican Chr",
    "wof:placetype":"venue"
},
  "geometry": {"coordinates":[-82.385796,43.005188],"type":"Point"}
}