{
  "type": "Feature",
  "properties": {
    "addr:full":"119 Point Dr NW Calgary AB T3B 5C8",
    "addr:housenumber":"119",
    "addr:postcode":"t3b 5c8",
    "addr:street":"Point Dr Nw",
    "iso:country":"CA",
    "sg:address":"119 Point Dr NW",
    "sg:city":"Calgary",
    "sg:classifiers":[
        {
            "category":"Mining & Drilling",
            "type":"Manufacturing & Wholesale Goods"
        }
    ],
    "sg:phone":"+1 403 262 8987",
    "sg:postcode":"T3B 5C8",
    "sg:province":"AB",
    "sg:tags":[
        "company",
        "oil"
    ],
    "wof:name":"Sedbergh Resources Ltd",
    "wof:placetype":"venue"
},
  "geometry": {"coordinates":[-114.146621704,51.0610466003],"type":"Point"}
}