{
  "type": "Feature",
  "properties": {
    "addr:full":"160 Niagara St St Catharines ON L2R 4L4",
    "addr:housenumber":"160",
    "addr:postcode":"l2r 4l4",
    "addr:street":"Niagara St",
    "iso:country":"CA",
    "sg:address":"160 Niagara St",
    "sg:city":"St Catharines",
    "sg:classifiers":[
        {
            "category":"Retail",
            "subcategory":"Portrait Studio",
            "type":"Services"
        }
    ],
    "sg:phone":"+1 905 682 7112",
    "sg:postcode":"L2R 4L4",
    "sg:province":"ON",
    "sg:tags":[
        "photographer"
    ],
    "wof:name":"Nerses Photo Studio",
    "wof:placetype":"venue"
},
  "geometry": {"coordinates":[-79.23337600000001,43.171143],"type":"Point"}
}