{
  "type": "Feature",
  "properties": {
    "addr:full":"Saint John NB E2M 4K2",
    "addr:postcode":"e2m 4k2",
    "iso:country":"CA",
    "sg:city":"Saint John",
    "sg:classifiers":[
        {
            "category":"Building & Trades",
            "subcategory":"Construction",
            "type":"Services"
        }
    ],
    "sg:phone":"+1 506 672 0505",
    "sg:postcode":"E2M 4K2",
    "sg:province":"NB",
    "sg:tags":[
        "roofing",
        "contractor"
    ],
    "wof:name":"Lunn's Roofing Ltd",
    "wof:placetype":"venue"
},
  "geometry": {"coordinates":[-66.11528800000001,45.250965],"type":"Point"}
}