{
  "type": "Feature",
  "properties": {
    "addr:full":"188 King St E Prescott ON K0E 1T0",
    "addr:housenumber":"188",
    "addr:postcode":"k0e 1t0",
    "addr:street":"King St E",
    "iso:country":"CA",
    "sg:address":"188 King St E",
    "sg:city":"Prescott",
    "sg:classifiers":[
        {
            "category":"Building & Trades",
            "subcategory":"Landscaping Services",
            "type":"Services"
        }
    ],
    "sg:phone":"+1 613 925 2432",
    "sg:postcode":"K0E 1T0",
    "sg:province":"ON",
    "sg:tags":[
        "lawn",
        "maintenance",
        "grounds"
    ],
    "wof:name":"Grass Man",
    "wof:placetype":"venue"
},
  "geometry": {"coordinates":[-75.51190200000001,44.711117],"type":"Point"}
}