{
  "type": "Feature",
  "properties": {
    "addr:full":"Mont-Laurier QC J9L 3J1",
    "addr:postcode":"j9l 3j1",
    "iso:country":"CA",
    "sg:city":"Mont-Laurier",
    "sg:classifiers":[
        {
            "category":"Shopping",
            "subcategory":"Clothing, Apparel, & Fashions",
            "type":"Retail Goods"
        }
    ],
    "sg:phone":"+1 819 623 9561",
    "sg:postcode":"J9L 3J1",
    "sg:province":"QC",
    "sg:tags":[
        "item",
        "boutique"
    ],
    "wof:name":"Boutique Erotique Adam & Eve",
    "wof:placetype":"venue"
},
  "geometry": {"coordinates":[-75.4869384766,46.5511207581],"type":"Point"}
}