{
  "type": "Feature",
  "properties": {
    "addr:full":"7920 Rue Lefebvre Lasalle QC H8N 2A8",
    "addr:housenumber":"7920",
    "addr:postcode":"h8n 2a8",
    "addr:street":"Rue Lefebvre",
    "iso:country":"CA",
    "sg:address":"7920 Rue Lefebvre",
    "sg:city":"Lasalle",
    "sg:classifiers":[
        {
            "category":"Professional",
            "subcategory":"Credit Reporting & Collection",
            "type":"Services"
        }
    ],
    "sg:phone":"+1 514 364 3757",
    "sg:postcode":"H8N 2A8",
    "sg:province":"QC",
    "sg:tags":[
        "agency"
    ],
    "wof:name":"Bureau D'Informations-Credit",
    "wof:placetype":"venue"
},
  "geometry": {"coordinates":[-73.623268,45.43549],"type":"Point"}
}