{
  "type": "Feature",
  "properties": {
    "addr:full":"106 Main St Maidstone SK S0M 1M0",
    "addr:housenumber":"106",
    "addr:postcode":"s0m 1m0",
    "addr:street":"Main St",
    "iso:country":"CA",
    "sg:address":"106 Main St",
    "sg:city":"Maidstone",
    "sg:classifiers":[
        {
            "category":"Food & Beverages",
            "subcategory":"Groceries & Convenience Stores",
            "type":"Retail Goods"
        }
    ],
    "sg:phone":"+1 306 893 4550",
    "sg:postcode":"S0M 1M0",
    "sg:province":"SK",
    "wof:name":"A & S Corner Store",
    "wof:placetype":"venue"
},
  "geometry": {"coordinates":[-109.28984832800001,53.0874786377],"type":"Point"}
}