{
  "type": "Feature",
  "properties": {
    "addr:full":"Jasper AB T0E 1E0",
    "addr:postcode":"t0e 1e0",
    "iso:country":"CA",
    "sg:city":"Jasper",
    "sg:classifiers":[
        {
            "category":"Professional",
            "subcategory":"Accounting & Tax Preparation",
            "type":"Services"
        }
    ],
    "sg:phone":"+1 780 852 3896",
    "sg:postcode":"T0E 1E0",
    "sg:province":"AB",
    "sg:tags":[
        "accountant"
    ],
    "wof:name":"Anthony Jones Pro Corp",
    "wof:placetype":"venue"
},
  "geometry": {"coordinates":[-118.07963599999999,52.878761],"type":"Point"}
}