{
  "type": "Feature",
  "properties": {
    "addr:full":"Toronto ON M5V 1V1",
    "addr:postcode":"m5v 1v1",
    "iso:country":"CA",
    "sg:city":"Toronto",
    "sg:classifiers":[
        {
            "category":"Real Estate",
            "subcategory":"Real Estate Agent",
            "type":"Services"
        }
    ],
    "sg:phone":"+1 416 504 7100",
    "sg:postcode":"M5V 1V1",
    "sg:province":"ON",
    "wof:name":"Locations Realty Corp",
    "wof:placetype":"venue"
},
  "geometry": {"coordinates":[-79.3963394165,43.6474113464],"type":"Point"}
}