{
  "type": "Feature",
  "properties": {
    "addr:full":"4897 Main St Vancouver BC V5V 3R9",
    "addr:housenumber":"4897",
    "addr:postcode":"v5v 3r9",
    "addr:street":"Main St",
    "iso:country":"CA",
    "sg:address":"4897 Main St",
    "sg:city":"Vancouver",
    "sg:classifiers":[
        {
            "category":"Personal",
            "subcategory":"Beauty Salon",
            "type":"Services"
        }
    ],
    "sg:phone":"+1 604 877 1928",
    "sg:postcode":"V5V 3R9",
    "sg:province":"BC",
    "wof:name":"J & J Hair Beauty Salon",
    "wof:placetype":"venue"
},
  "geometry": {"coordinates":[-123.101593018,49.2406845093],"type":"Point"}
}