{
  "type": "Feature",
  "properties": {
    "addr:full":"51 Osborne St Winnipeg MB R3L 1Y2",
    "addr:housenumber":"51",
    "addr:postcode":"r3l 1y2",
    "addr:street":"Osborne St",
    "iso:country":"CA",
    "sg:address":"51 Osborne St",
    "sg:city":"Winnipeg",
    "sg:classifiers":[
        {
            "category":"Restaurant",
            "type":"Food & Drink"
        }
    ],
    "sg:phone":"+1 204 477 9551",
    "sg:postcode":"R3L 1Y2",
    "sg:province":"MB",
    "wof:name":"VI-Ann Restaurant",
    "wof:placetype":"venue"
},
  "geometry": {"coordinates":[-97.1472320557,49.879901886],"type":"Point"}
}