{
  "type": "Feature",
  "properties": {
    "addr:full":"Calgary AB T2V 0E5",
    "addr:postcode":"t2v 0e5",
    "iso:country":"CA",
    "sg:city":"Calgary",
    "sg:classifiers":[
        {
            "category":"Real Estate",
            "subcategory":"Real Estate Agent",
            "type":"Services"
        }
    ],
    "sg:phone":"+1 403 252 5081",
    "sg:postcode":"T2V 0E5",
    "sg:province":"AB",
    "sg:tags":[
        "desk",
        "space"
    ],
    "wof:name":"Business Ctr",
    "wof:placetype":"venue"
},
  "geometry": {"coordinates":[-114.08329000000001,50.993153],"type":"Point"}
}