{
  "type": "Feature",
  "properties": {
    "addr:full":"100 Boul Omer-Marcil Saint-Luc QC J2W 2X2",
    "addr:housenumber":"100",
    "addr:postcode":"j2w 2x2",
    "addr:street":"Boul Omer-Marcil",
    "iso:country":"CA",
    "sg:address":"100 Boul Omer-Marcil",
    "sg:city":"Saint-Luc",
    "sg:classifiers":[
        {
            "category":"Shopping",
            "subcategory":"Department Store",
            "type":"Retail Goods"
        }
    ],
    "sg:phone":"+1 450 349 0666",
    "sg:postcode":"J2W 2X2",
    "sg:province":"QC",
    "sg:tags":[
        "pharmacy"
    ],
    "wof:name":"Wal-Mart",
    "wof:placetype":"venue"
},
  "geometry": {"coordinates":[-73.29864499999999,45.331665],"type":"Point"}
}