{
  "type": "Feature",
  "properties": {
    "addr:full":"1410 Victoria Park Ave North York ON M4A 2L8",
    "addr:housenumber":"1410",
    "addr:postcode":"m4a 2l8",
    "addr:street":"Victoria Park Ave",
    "iso:country":"CA",
    "sg:address":"1410 Victoria Park Ave",
    "sg:city":"North York",
    "sg:classifiers":[
        {
            "category":"Restaurant",
            "type":"Food & Drink"
        }
    ],
    "sg:phone":"+1 416 750 1483",
    "sg:postcode":"M4A 2L8",
    "sg:province":"ON",
    "wof:name":"Sansimian",
    "wof:placetype":"venue"
},
  "geometry": {"coordinates":[-79.300461,43.71899],"type":"Point"}
}