{
  "type": "Feature",
  "properties": {
    "addr:full":"Aldergrove BC V4W 3V9",
    "addr:postcode":"v4w 3v9",
    "iso:country":"CA",
    "sg:city":"Aldergrove",
    "sg:classifiers":[
        {
            "category":"Retail",
            "subcategory":"Repair Shop",
            "type":"Services"
        }
    ],
    "sg:phone":"+1 604 857 9004",
    "sg:postcode":"V4W 3V9",
    "sg:province":"BC",
    "sg:tags":[
        "ironwork"
    ],
    "wof:name":"Creative Metal Works",
    "wof:placetype":"venue"
},
  "geometry": {"coordinates":[-122.472290039,49.0568656921],"type":"Point"}
}