{
  "type": "Feature",
  "properties": {
    "addr:full":"110 Columbus Dr Carbonear NL A1Y 1A6",
    "addr:housenumber":"110",
    "addr:postcode":"a1y 1a6",
    "addr:street":"Columbus Dr",
    "iso:country":"CA",
    "sg:address":"110 Columbus Dr",
    "sg:city":"Carbonear",
    "sg:classifiers":[
        {
            "category":"Home & Garden",
            "subcategory":"Furniture",
            "type":"Retail Goods"
        }
    ],
    "sg:phone":"+1 709 596 7106",
    "sg:postcode":"A1Y 1A6",
    "sg:province":"NL",
    "wof:name":"Cohen's Home Furnishings Ltd",
    "wof:placetype":"venue"
},
  "geometry": {"coordinates":[-53.245014,47.726326],"type":"Point"}
}