{
  "type": "Feature",
  "properties": {
    "addr:full":"58 Charles Killarney ON P0M 2A0",
    "addr:housenumber":"58",
    "addr:postcode":"p0m 2a0",
    "addr:street":"Charles",
    "iso:country":"CA",
    "sg:address":"58 Charles",
    "sg:city":"Killarney",
    "sg:classifiers":[
        {
            "category":"Arena",
            "subcategory":"Sports Club",
            "type":"Entertainment"
        }
    ],
    "sg:phone":"+1 705 287 2195",
    "sg:postcode":"P0M 2A0",
    "sg:province":"ON",
    "sg:tags":[
        "athletic",
        "fields",
        "stadium"
    ],
    "wof:name":"Killarney Rink",
    "wof:placetype":"venue"
},
  "geometry": {"coordinates":[-81.509033,45.974918],"type":"Point"}
}