{
  "type": "Feature",
  "properties": {
    "iso:country":"CA",
    "sg:city":"Calgary",
    "sg:classifiers":[
        {
            "category":"Professional",
            "subcategory":"Lawyer & Legal Services",
            "type":"Services"
        }
    ],
    "sg:phone":"+1 403 299 9283",
    "sg:postcode":"T2S 2T4",
    "sg:province":"AB",
    "sg:tags":[
        "attorney"
    ],
    "wof:name":"Munro & Wood",
    "wof:placetype":"venue"
},
  "geometry": {"coordinates":[-114.071312,51.031254],"type":"Point"}
}