{
  "type": "Feature",
  "properties": {
    "addr:full":"Vancouver BC V6E 2E2",
    "addr:postcode":"v6e 2e2",
    "iso:country":"CA",
    "sg:city":"Vancouver",
    "sg:classifiers":[
        {
            "category":"Manufacturing",
            "subcategory":"Signs",
            "type":"Manufacturing & Wholesale Goods"
        }
    ],
    "sg:phone":"+1 604 682 0100",
    "sg:postcode":"V6E 2E2",
    "sg:province":"BC",
    "wof:name":"Amber Sign & Design",
    "wof:placetype":"venue"
},
  "geometry": {"coordinates":[-123.13501739500001,49.2826004028],"type":"Point"}
}