{
  "type": "Feature",
  "properties": {
    "addr:full":"1516 Merivale Rd Nepean ON K2G 3J6",
    "addr:housenumber":"1516",
    "addr:postcode":"k2g 3j6",
    "addr:street":"Merivale Rd",
    "iso:country":"CA",
    "sg:address":"1516 Merivale Rd",
    "sg:city":"Nepean",
    "sg:classifiers":[
        {
            "category":"Shopping",
            "subcategory":"Pharmacy",
            "type":"Retail Goods"
        }
    ],
    "sg:phone":"+1 613 224 7322",
    "sg:postcode":"K2G 3J6",
    "sg:province":"ON",
    "wof:name":"Pharma Plus Drugmart",
    "wof:placetype":"venue"
},
  "geometry": {"coordinates":[-75.73709869379999,45.3565063477],"type":"Point"}
}