{
  "type": "Feature",
  "properties": {
    "addr:full":"Red Deer AB T4R 2H6",
    "addr:postcode":"t4r 2h6",
    "iso:country":"CA",
    "sg:city":"Red Deer",
    "sg:classifiers":[
        {
            "category":"Health Services",
            "subcategory":"Doctor",
            "type":"Services"
        }
    ],
    "sg:phone":"+1 403 342 5800",
    "sg:postcode":"T4R 2H6",
    "sg:province":"AB",
    "sg:tags":[
        "dentist"
    ],
    "wof:name":"Berger, Eunice DDS",
    "wof:placetype":"venue"
},
  "geometry": {"coordinates":[-113.76532,52.255501],"type":"Point"}
}