{
  "type": "Feature",
  "properties": {
    "addr:full":"22471 Lougheed Hwy Maple Ridge BC V2X 2T8",
    "addr:housenumber":"22471",
    "addr:postcode":"v2x 2t8",
    "addr:street":"Lougheed Hwy",
    "iso:country":"CA",
    "sg:address":"22471 Lougheed Hwy",
    "sg:city":"Maple Ridge",
    "sg:classifiers":[
        {
            "category":"Restaurant",
            "type":"Food & Drink"
        }
    ],
    "sg:phone":"+1 604 467 3212",
    "sg:postcode":"V2X 2T8",
    "sg:province":"BC",
    "wof:name":"Bella Vita Restaurant Ltd",
    "wof:placetype":"venue"
},
  "geometry": {"coordinates":[-122.59967,49.217171],"type":"Point"}
}