{
  "type": "Feature",
  "properties": {
    "addr:full":"Hamilton ON L8W 3X1",
    "addr:postcode":"l8w 3x1",
    "iso:country":"CA",
    "sg:city":"Hamilton",
    "sg:classifiers":[
        {
            "category":"Shopping",
            "subcategory":"Optical Goods",
            "type":"Retail Goods"
        }
    ],
    "sg:phone":"+1 905 318 5125",
    "sg:postcode":"L8W 3X1",
    "sg:province":"ON",
    "sg:tags":[
        "optician"
    ],
    "wof:name":"Ultimate Optics Inc",
    "wof:placetype":"venue"
},
  "geometry": {"coordinates":[-79.87051391599999,43.1970710754],"type":"Point"}
}