{
  "type": "Feature",
  "properties": {
    "addr:full":"130 16th St W North Vancouver BC V7M 1T4",
    "addr:housenumber":"130",
    "addr:postcode":"v7m 1t4",
    "addr:street":"16Th St W",
    "iso:country":"CA",
    "sg:address":"130 16th St W",
    "sg:city":"North Vancouver",
    "sg:classifiers":[
        {
            "category":"Personal",
            "subcategory":"Beauty Salon",
            "type":"Services"
        }
    ],
    "sg:phone":"+1 604 988 0121",
    "sg:postcode":"V7M 1T4",
    "sg:province":"BC",
    "wof:name":"Nations Hair Design",
    "wof:placetype":"venue"
},
  "geometry": {"coordinates":[-123.073364,49.323231],"type":"Point"}
}