{
  "type": "Feature",
  "properties": {
    "addr:full":"Etobicoke ON M9V 3T2",
    "addr:postcode":"m9v 3t2",
    "iso:country":"CA",
    "sg:city":"Etobicoke",
    "sg:classifiers":[
        {
            "category":"Real Estate",
            "subcategory":"Real Estate Operator",
            "type":"Services"
        }
    ],
    "sg:phone":"+1 416 743 3761",
    "sg:postcode":"M9V 3T2",
    "sg:province":"ON",
    "sg:tags":[
        "apartment"
    ],
    "wof:name":"Martella Place",
    "wof:placetype":"venue"
},
  "geometry": {"coordinates":[-79.5957870483,43.7455482483],"type":"Point"}
}