{
  "type": "Feature",
  "properties": {
    "addr:full":"Mississauga ON L5R 3V6",
    "addr:postcode":"l5r 3v6",
    "iso:country":"CA",
    "sg:city":"Mississauga",
    "sg:classifiers":[
        {
            "category":"Shopping",
            "subcategory":"Clothing, Apparel, & Fashions",
            "type":"Retail Goods"
        }
    ],
    "sg:phone":"+1 905 501 1200",
    "sg:postcode":"L5R 3V6",
    "sg:province":"ON",
    "sg:tags":[
        "leather"
    ],
    "wof:name":"Roots Canada Ltd",
    "wof:placetype":"venue"
},
  "geometry": {"coordinates":[-79.68969,43.613277],"type":"Point"}
}