{
  "type": "Feature",
  "properties": {
    "addr:full":"85 Rue D'Ottawa Granby QC J2G 2R9",
    "addr:housenumber":"85",
    "addr:postcode":"j2g 2r9",
    "addr:street":"Rue D'Ottawa",
    "iso:country":"CA",
    "sg:address":"85 Rue D'Ottawa",
    "sg:city":"Granby",
    "sg:classifiers":[
        {
            "category":"Professional",
            "subcategory":"Business Services",
            "type":"Services"
        }
    ],
    "sg:phone":"+1 450 375 6486",
    "sg:postcode":"J2G 2R9",
    "sg:province":"QC",
    "sg:tags":[
        "translator",
        "employment",
        "agency",
        "opportunity",
        "interpreter"
    ],
    "wof:name":"Interim Plus Inc",
    "wof:placetype":"venue"
},
  "geometry": {"coordinates":[-72.7208328247,45.3996734619],"type":"Point"}
}