{
  "type": "Feature",
  "properties": {
    "addr:full":"10 Deer Valley Rd Deer Valley SK S2V 1B6",
    "addr:housenumber":"10",
    "addr:postcode":"s2v 1b6",
    "addr:street":"Deer Valley Rd",
    "iso:country":"CA",
    "sg:address":"10 Deer Valley Rd",
    "sg:city":"Deer Valley",
    "sg:classifiers":[
        {
            "category":"Sports & Exercise",
            "subcategory":"Golf",
            "type":"Entertainment"
        }
    ],
    "sg:phone":"+1 306 731 1445",
    "sg:postcode":"S2V 1B6",
    "sg:province":"SK",
    "sg:tags":[
        "course"
    ],
    "wof:name":"Deer Valley Golf & Estates",
    "wof:placetype":"venue"
},
  "geometry": {"coordinates":[-104.87752533,50.6009521484],"type":"Point"}
}