{
  "type": "Feature",
  "properties": {
    "addr:full":"7095 Thunderbird Rd Port Hardy BC V0N 2P0",
    "addr:housenumber":"7095",
    "addr:postcode":"v0n 2p0",
    "addr:street":"Thunderbird Rd",
    "iso:country":"CA",
    "sg:address":"7095 Thunderbird Rd",
    "sg:city":"Port Hardy",
    "sg:classifiers":[
        {
            "category":"Social Services",
            "type":"Services"
        }
    ],
    "sg:phone":"+1 250 949 6033",
    "sg:postcode":"V0N 2P0",
    "sg:province":"BC",
    "sg:tags":[
        "crisis",
        "center"
    ],
    "wof:name":"North Island Crisis & Cnslng",
    "wof:placetype":"venue"
},
  "geometry": {"coordinates":[-127.50357099999999,50.720917],"type":"Point"}
}