{
  "type": "Feature",
  "properties": {
    "addr:full":"819 Rue Chalifoux Sherbrooke QC J1G 1R7",
    "addr:housenumber":"819",
    "addr:postcode":"j1g 1r7",
    "addr:street":"Rue Chalifoux",
    "iso:country":"CA",
    "sg:address":"819 Rue Chalifoux",
    "sg:city":"Sherbrooke",
    "sg:classifiers":[
        {
            "category":"Home & Garden",
            "subcategory":"Building Materials",
            "type":"Retail Goods"
        }
    ],
    "sg:phone":"+1 819 569 4368",
    "sg:postcode":"J1G 1R7",
    "sg:province":"QC",
    "sg:tags":[
        "paint"
    ],
    "wof:name":"Peinture & Ciment DE L'Estrie",
    "wof:placetype":"venue"
},
  "geometry": {"coordinates":[-71.871117,45.40123],"type":"Point"}
}