{
  "type": "Feature",
  "properties": {
    "addr:full":"163 Rue Cowie Granby QC J2G 3V5",
    "addr:housenumber":"163",
    "addr:postcode":"j2g 3v5",
    "addr:street":"Rue Cowie",
    "iso:country":"CA",
    "sg:address":"163 Rue Cowie",
    "sg:city":"Granby",
    "sg:classifiers":[
        {
            "category":"Manufacturing",
            "subcategory":"Furniture",
            "type":"Manufacturing & Wholesale Goods"
        }
    ],
    "sg:phone":"+1 450 777 3337",
    "sg:postcode":"J2G 3V5",
    "sg:province":"QC",
    "wof:name":"Papeterie Haute-Ville Inc",
    "wof:placetype":"venue"
},
  "geometry": {"coordinates":[-72.7282867432,45.3970298767],"type":"Point"}
}