{
  "type": "Feature",
  "properties": {
    "iso:country":"CA",
    "sg:address":"3122 Blenheim St",
    "sg:city":"Vancouver",
    "sg:classifiers":[
        {
            "category":"Retail",
            "subcategory":"Veterinary Services",
            "type":"Services"
        }
    ],
    "sg:phone":"+1 604 732 1011",
    "sg:postcode":"V6K 4J7",
    "sg:province":"BC",
    "sg:tags":[
        "veterinarian"
    ],
    "wof:name":"Blenheim Animal Clinic",
    "wof:placetype":"venue"
},
  "geometry": {"coordinates":[-123.177764893,49.2585868835],"type":"Point"}
}