{
  "type": "Feature",
  "properties": {
    "addr:full":"1359 Rue Notre-Dame O Victoriaville QC G6P 7L5",
    "addr:housenumber":"1359",
    "addr:postcode":"g6p 7l5",
    "addr:street":"Rue Notre-Dame O",
    "iso:country":"CA",
    "sg:address":"1359 Rue Notre-Dame O",
    "sg:city":"Victoriaville",
    "sg:classifiers":[
        {
            "category":"Retail",
            "subcategory":"Auto Repair",
            "type":"Services"
        }
    ],
    "sg:phone":"+1 819 752 4149",
    "sg:postcode":"G6P 7L5",
    "sg:province":"QC",
    "sg:tags":[
        "repairing",
        "automobile"
    ],
    "wof:name":"Garage A Drouin & Fils Inc",
    "wof:placetype":"venue"
},
  "geometry": {"coordinates":[-71.93371582029999,46.0720787048],"type":"Point"}
}