{
  "type": "Feature",
  "properties": {
    "iso:country":"CA",
    "sg:address":"1097 Bank St",
    "sg:city":"Ottawa",
    "sg:classifiers":[
        {
            "category":"Shopping",
            "subcategory":"Used Merchandise",
            "type":"Retail Goods"
        }
    ],
    "sg:phone":"+1 613 730 8943",
    "sg:postcode":"K1S 3X4",
    "sg:province":"ON",
    "sg:tags":[
        "antique"
    ],
    "wof:name":"Logan Antiques",
    "wof:placetype":"venue"
},
  "geometry": {"coordinates":[-75.68309021,45.3940887451],"type":"Point"}
}