{
  "type": "Feature",
  "properties": {
    "addr:full":"761 Boul Saint-Laurent E Louiseville QC J5V 1J1",
    "addr:housenumber":"761",
    "addr:postcode":"j5v 1j1",
    "addr:street":"Boul Saint-Laurent E",
    "iso:country":"CA",
    "sg:address":"761 Boul Saint-Laurent E",
    "sg:city":"Louiseville",
    "sg:classifiers":[
        {
            "category":"Manufacturing",
            "subcategory":"Motor Vehicles & Parts",
            "type":"Manufacturing & Wholesale Goods"
        }
    ],
    "sg:phone":"+1 819 228 3124",
    "sg:postcode":"J5V 1J1",
    "sg:province":"QC",
    "sg:tags":[
        "motorcycle"
    ],
    "wof:name":"Creations Jpl Inc",
    "wof:placetype":"venue"
},
  "geometry": {"coordinates":[-72.91392500000001,46.258572],"type":"Point"}
}