{
  "type": "Feature",
  "properties": {
    "addr:full":"177 138 Rte Saint-Augustin-DE-Desmaures QC G3A 1W7",
    "addr:housenumber":"138",
    "addr:postcode":"g3a 1w7",
    "addr:street":"Rte Saint-Augustin-De-Desmaures",
    "iso:country":"CA",
    "sg:address":"177 138 Rte",
    "sg:city":"Saint-Augustin-DE-Desmaures",
    "sg:classifiers":[
        {
            "category":"Local Transit",
            "type":"Transportation"
        }
    ],
    "sg:phone":"+1 418 878 2093",
    "sg:postcode":"G3A 1W7",
    "sg:province":"QC",
    "sg:tags":[
        "bus",
        "line"
    ],
    "wof:name":"Transport St-Augustin Inc",
    "wof:placetype":"venue"
},
  "geometry": {"coordinates":[-71.384727478,46.7491760254],"type":"Point"}
}