{
  "type": "Feature",
  "properties": {
    "iso:country":"CA",
    "sg:address":"3930 Rue Jean-Talon E",
    "sg:city":"Montreal",
    "sg:classifiers":[
        {
            "category":"Wholesale",
            "subcategory":"Meat",
            "type":"Manufacturing & Wholesale Goods"
        }
    ],
    "sg:phone":"+1 514 727 0936",
    "sg:postcode":"H2A 1Y8",
    "sg:province":"QC",
    "sg:tags":[
        "butchering"
    ],
    "wof:name":"Boucherie Epicerie A Sabrah",
    "wof:placetype":"venue"
},
  "geometry": {"coordinates":[-73.592041,45.565575],"type":"Point"}
}