{
  "type": "Feature",
  "properties": {
    "addr:full":"770 Wright St Strathroy ON N7G 3H8",
    "addr:housenumber":"770",
    "addr:postcode":"n7g 3h8",
    "addr:street":"Wright St",
    "iso:country":"CA",
    "sg:address":"770 Wright St",
    "sg:city":"Strathroy",
    "sg:classifiers":[
        {
            "category":"Manufacturing",
            "subcategory":"Tools & Machinery",
            "type":"Manufacturing & Wholesale Goods"
        }
    ],
    "sg:phone":"+1 519 245 0404",
    "sg:postcode":"N7G 3H8",
    "sg:province":"ON",
    "sg:tags":[
        "equipment",
        "conveyor",
        "conveying"
    ],
    "wof:name":"Metamag Inc",
    "wof:placetype":"venue"
},
  "geometry": {"coordinates":[-81.625175,42.987186],"type":"Point"}
}