{
  "type": "Feature",
  "properties": {
    "addr:full":"5408 Highway 34 Vankleek Hill ON K0B 1R0",
    "addr:housenumber":"5408",
    "addr:postcode":"k0b 1r0",
    "addr:street":"Highway 34",
    "iso:country":"CA",
    "sg:address":"5408 Highway 34",
    "sg:city":"Vankleek Hill",
    "sg:classifiers":[
        {
            "category":"Bus Charters",
            "type":"Transportation"
        }
    ],
    "sg:phone":"+1 613 678 2585",
    "sg:postcode":"K0B 1R0",
    "sg:province":"ON",
    "sg:tags":[
        "rental"
    ],
    "wof:name":"G & L Bus Lines Inc",
    "wof:placetype":"venue"
},
  "geometry": {"coordinates":[-74.6567001343,45.5126495361],"type":"Point"}
}