{
  "type": "Feature",
  "properties": {
    "addr:full":"2 Queen St Dryden ON P8N 1A2",
    "addr:housenumber":"2",
    "addr:postcode":"p8n 1a2",
    "addr:street":"Queen St",
    "iso:country":"CA",
    "sg:address":"2 Queen St",
    "sg:city":"Dryden",
    "sg:classifiers":[
        {
            "category":"Home & Garden",
            "subcategory":"Building Materials",
            "type":"Retail Goods"
        }
    ],
    "sg:phone":"+1 807 223 2570",
    "sg:postcode":"P8N 1A2",
    "sg:province":"ON",
    "sg:tags":[
        "body",
        "plate",
        "window",
        "automobile"
    ],
    "wof:name":"Walter's Auto Body Pro",
    "wof:placetype":"venue"
},
  "geometry": {"coordinates":[-92.8421783447,49.784866333],"type":"Point"}
}