{
  "type": "Feature",
  "properties": {
    "addr:full":"8810 112 St Grande Prairie AB T8V 5X4",
    "addr:housenumber":"8810",
    "addr:postcode":"t8v 5x4",
    "addr:street":"112 St",
    "iso:country":"CA",
    "sg:address":"8810 112 St",
    "sg:city":"Grande Prairie",
    "sg:classifiers":[
        {
            "category":"Building & Trades",
            "subcategory":"Construction",
            "type":"Services"
        }
    ],
    "sg:phone":"+1 780 538 2827",
    "sg:postcode":"T8V 5X4",
    "sg:province":"AB",
    "sg:tags":[
        "contractor"
    ],
    "wof:name":"Ken-Dor Concrete Pumping Ltd",
    "wof:placetype":"venue"
},
  "geometry": {"coordinates":[-118.83461800000001,55.159748],"type":"Point"}
}