{
  "type": "Feature",
  "properties": {
    "addr:full":"50 Weybright Crt # 6 Scarborough ON M1S 5A8",
    "addr:housenumber":"50",
    "addr:postcode":"m1s 5a8",
    "addr:street":"Weybright Crt # 6",
    "iso:country":"CA",
    "sg:address":"50 Weybright Crt # 6",
    "sg:city":"Scarborough",
    "sg:classifiers":[
        {
            "category":"Wholesale",
            "subcategory":"Office Equipment",
            "type":"Manufacturing & Wholesale Goods"
        }
    ],
    "sg:phone":"+1 416 332 9432",
    "sg:postcode":"M1S 5A8",
    "sg:province":"ON",
    "sg:tags":[
        "machine",
        "duplicating",
        "copying"
    ],
    "wof:name":"Copyserve",
    "wof:placetype":"venue"
},
  "geometry": {"coordinates":[-79.278427124,43.781791687],"type":"Point"}
}