{
  "type": "Feature",
  "properties": {
    "iso:country":"CA",
    "sg:address":"95 Montebello Dr",
    "sg:city":"Dartmouth",
    "sg:classifiers":[
        {
            "category":"Food & Beverages",
            "subcategory":"Groceries & Convenience Stores",
            "type":"Retail Goods"
        }
    ],
    "sg:phone":"+1 902 435 5152",
    "sg:postcode":"B2X 3J7",
    "sg:province":"NS",
    "wof:name":"Cascade Video & Variety Store",
    "wof:placetype":"venue"
},
  "geometry": {"coordinates":[-63.5383834839,44.700088501],"type":"Point"}
}