{
  "type": "Feature",
  "properties": {
    "addr:full":"375 Rg Des Chutes Ham-Nord QC G0P 1A0",
    "addr:housenumber":"375",
    "addr:postcode":"g0p 1a0",
    "addr:street":"Rg Des Chutes",
    "iso:country":"CA",
    "sg:address":"375 Rg Des Chutes",
    "sg:city":"Ham-Nord",
    "sg:classifiers":[
        {
            "category":"Food & Beverages",
            "subcategory":"Specialty",
            "type":"Retail Goods"
        }
    ],
    "sg:phone":"+1 819 344 2080",
    "sg:postcode":"G0P 1A0",
    "sg:province":"QC",
    "sg:tags":[
        "herb"
    ],
    "wof:name":"Armoire Aux Herbes Inc",
    "wof:placetype":"venue"
},
  "geometry": {"coordinates":[-71.6540756226,45.8955307007],"type":"Point"}
}