{
  "type": "Feature",
  "properties": {
    "addr:full":"141 Savage Dr Cambridge ON N1T 1S5",
    "addr:housenumber":"141",
    "addr:postcode":"n1t 1s5",
    "addr:street":"Savage Dr",
    "iso:country":"CA",
    "sg:address":"141 Savage Dr",
    "sg:city":"Cambridge",
    "sg:classifiers":[
        {
            "category":"Manufacturing",
            "subcategory":"Furniture",
            "type":"Manufacturing & Wholesale Goods"
        }
    ],
    "sg:phone":"+1 519 623 0430",
    "sg:postcode":"N1T 1S5",
    "sg:province":"ON",
    "sg:tags":[
        "material",
        "fixture",
        "display"
    ],
    "wof:name":"Galt Display Rack CO Ltd",
    "wof:placetype":"venue"
},
  "geometry": {"coordinates":[-80.282616,43.367165],"type":"Point"}
}