{
  "type": "Feature",
  "properties": {
    "addr:full":"PO Box 685 STN Main Terrace BC V8G 4B8",
    "addr:housenumber":"po",
    "addr:postcode":"v8g 4b8",
    "addr:street":"Box 685 Stn Main Terrace",
    "iso:country":"CA",
    "sg:address":"PO Box 685 STN Main",
    "sg:city":"Terrace",
    "sg:classifiers":[
        {
            "category":"Organizations",
            "subcategory":"Professional Association",
            "type":"Services"
        }
    ],
    "sg:phone":"+1 250 635 8799",
    "sg:postcode":"V8G 4B8",
    "sg:province":"BC",
    "wof:name":"Nechako-Kitamaat Development",
    "wof:placetype":"venue"
},
  "geometry": {"coordinates":[-128.60217299999999,54.515858],"type":"Point"}
}