{
  "type": "Feature",
  "properties": {
    "addr:full":"69 1 Ave Fox Creek AB T0H 1P0",
    "addr:postcode":"t0h 1p0",
    "addr:street":"69 1 Ave",
    "iso:country":"CA",
    "sg:address":"69 1 Ave",
    "sg:city":"Fox Creek",
    "sg:classifiers":[
        {
            "category":"Real Estate",
            "subcategory":"Real Estate Agent",
            "type":"Services"
        }
    ],
    "sg:phone":"+1 780 622 2211",
    "sg:postcode":"T0H 1P0",
    "sg:province":"AB",
    "wof:name":"Royal Le Page Real Estate",
    "wof:placetype":"venue"
},
  "geometry": {"coordinates":[-116.80117799999999,54.393478],"type":"Point"}
}