{
  "type": "Feature",
  "properties": {
    "addr:full":"Cambridge ON N1R 8K9",
    "addr:postcode":"n1r 8k9",
    "iso:country":"CA",
    "sg:city":"Cambridge",
    "sg:classifiers":[
        {
            "category":"Manufacturing",
            "subcategory":"Tools & Machinery",
            "type":"Manufacturing & Wholesale Goods"
        }
    ],
    "sg:phone":"+1 519 740 2851",
    "sg:postcode":"N1R 8K9",
    "sg:province":"ON",
    "sg:tags":[
        "machine",
        "shop"
    ],
    "wof:name":"Deltex Machine Shop Inc",
    "wof:placetype":"venue"
},
  "geometry": {"coordinates":[-80.2938995361,43.3599586487],"type":"Point"}
}