{
  "type": "Feature",
  "properties": {
    "addr:full":"Scarborough ON M1E 2N7",
    "addr:postcode":"m1e 2n7",
    "iso:country":"CA",
    "sg:city":"Scarborough",
    "sg:classifiers":[
        {
            "category":"Retail",
            "subcategory":"Auto Repair",
            "type":"Services"
        }
    ],
    "sg:phone":"+1 416 282 1192",
    "sg:postcode":"M1E 2N7",
    "sg:province":"ON",
    "sg:tags":[
        "repairing",
        "automobile"
    ],
    "wof:name":"Goodyear Canada Inc",
    "wof:placetype":"venue"
},
  "geometry": {"coordinates":[-79.187363,43.769775],"type":"Point"}
}