{
  "type": "Feature",
  "properties": {
    "addr:full":"109 Finlay Ave E Deloraine MB R0M 0M0",
    "addr:housenumber":"109",
    "addr:postcode":"r0m 0m0",
    "addr:street":"Finlay Ave E Deloraine",
    "iso:country":"CA",
    "sg:address":"109 Finlay Ave E",
    "sg:city":"Deloraine",
    "sg:classifiers":[
        {
            "category":"Retail",
            "subcategory":"Auto Repair",
            "type":"Services"
        }
    ],
    "sg:phone":"+1 204 747 2182",
    "sg:postcode":"R0M 0M0",
    "sg:province":"MB",
    "sg:tags":[
        "body",
        "automobile",
        "painting"
    ],
    "wof:name":"D & M Motors Ltd Body Shop",
    "wof:placetype":"venue"
},
  "geometry": {"coordinates":[-100.496070862,49.1933364868],"type":"Point"}
}