{
  "type": "Feature",
  "properties": {
    "addr:full":"6265 Quinpool Rd Halifax NS B3L 1A4",
    "addr:housenumber":"6265",
    "addr:postcode":"b3l 1a4",
    "addr:street":"Quinpool Rd",
    "iso:country":"CA",
    "sg:address":"6265 Quinpool Rd",
    "sg:city":"Halifax",
    "sg:classifiers":[
        {
            "category":"Shopping",
            "subcategory":"Computers & Home Electronics",
            "type":"Retail Goods"
        }
    ],
    "sg:phone":"+1 902 429 1345",
    "sg:postcode":"B3L 1A4",
    "sg:province":"NS",
    "sg:tags":[
        "game",
        "video"
    ],
    "wof:name":"Game World",
    "wof:placetype":"venue"
},
  "geometry": {"coordinates":[-63.597706,44.64542],"type":"Point"}
}