{
  "type": "Feature",
  "properties": {
    "addr:full":"18 Hollister Rd Etobicoke ON M9C 4M7",
    "addr:housenumber":"18",
    "addr:postcode":"m9c 4m7",
    "addr:street":"Hollister Rd",
    "iso:country":"CA",
    "sg:address":"18 Hollister Rd",
    "sg:city":"Etobicoke",
    "sg:classifiers":[
        {
            "category":"Professional",
            "subcategory":"Accounting & Tax Preparation",
            "type":"Services"
        }
    ],
    "sg:phone":"+1 416 626 5160",
    "sg:postcode":"M9C 4M7",
    "sg:province":"ON",
    "sg:tags":[
        "bookkeeping",
        "general"
    ],
    "wof:name":"Fullscale Enterprises Ltd",
    "wof:placetype":"venue"
},
  "geometry": {"coordinates":[-79.5768585205,43.6645774841],"type":"Point"}
}