{
  "type": "Feature",
  "properties": {
    "addr:full":"11069 Huntington Rd Kleinburg ON L0J 1C0",
    "addr:housenumber":"11069",
    "addr:postcode":"l0j 1c0",
    "addr:street":"Huntington Rd",
    "iso:country":"CA",
    "sg:address":"11069 Huntington Rd",
    "sg:city":"Kleinburg",
    "sg:classifiers":[
        {
            "category":"Building & Trades",
            "subcategory":"Landscaping Services",
            "type":"Services"
        }
    ],
    "sg:phone":"+1 905 893 7600",
    "sg:postcode":"L0J 1C0",
    "sg:province":"ON",
    "sg:tags":[
        "contractor",
        "sodding",
        "landscape",
        "sod"
    ],
    "wof:name":"Nashville Sod Supply",
    "wof:placetype":"venue"
},
  "geometry": {"coordinates":[-79.666161,43.850834],"type":"Point"}
}