{
  "type": "Feature",
  "properties": {
    "iso:country":"CA",
    "sg:address":"1 Collver Rd",
    "sg:city":"Thessalon",
    "sg:classifiers":[
        {
            "category":"Government",
            "subcategory":"Office",
            "type":"Public Place"
        }
    ],
    "sg:phone":"+1 705 842 3370",
    "sg:postcode":"P0R 1L0",
    "sg:province":"ON",
    "sg:tags":[
        "village"
    ],
    "wof:name":"Algoma District Svc Admn Brd",
    "wof:placetype":"venue"
},
  "geometry": {"coordinates":[-83.5464553833,46.265411377],"type":"Point"}
}