{
  "type": "Feature",
  "properties": {
    "addr:full":"Montreal QC H2K 2X4",
    "addr:postcode":"h2k 2x4",
    "iso:country":"CA",
    "sg:city":"Montreal",
    "sg:classifiers":[
        {
            "category":"Real Estate",
            "subcategory":"Real Estate Operator",
            "type":"Services"
        }
    ],
    "sg:phone":"+1 514 524 2020",
    "sg:postcode":"H2K 2X4",
    "sg:province":"QC",
    "sg:tags":[
        "apartment"
    ],
    "wof:name":"Degimi Immobilier Inc",
    "wof:placetype":"venue"
},
  "geometry": {"coordinates":[-73.550209,45.532917],"type":"Point"}
}