{
  "type": "Feature",
  "properties": {
    "addr:full":"2700 Rue DE Lorimier Longueuil QC J4K 3P9",
    "addr:housenumber":"2700",
    "addr:postcode":"j4k 3p9",
    "addr:street":"Rue De Lorimier",
    "iso:country":"CA",
    "sg:address":"2700 Rue DE Lorimier",
    "sg:city":"Longueuil",
    "sg:classifiers":[
        {
            "category":"Retail",
            "subcategory":"Auto Repair",
            "type":"Services"
        }
    ],
    "sg:phone":"+1 450 674 3838",
    "sg:postcode":"J4K 3P9",
    "sg:province":"QC",
    "sg:tags":[
        "body",
        "automobile",
        "painting"
    ],
    "wof:name":"Roger Arnold Ltee",
    "wof:placetype":"venue"
},
  "geometry": {"coordinates":[-73.474899292,45.5091171265],"type":"Point"}
}