{
  "type": "Feature",
  "properties": {
    "addr:full":"25 Eastbourne Ave Toronto ON M5P 2E8",
    "addr:housenumber":"25",
    "addr:postcode":"m5p 2e8",
    "addr:street":"Eastbourne Ave",
    "iso:country":"CA",
    "sg:address":"25 Eastbourne Ave",
    "sg:city":"Toronto",
    "sg:classifiers":[
        {
            "category":"Professional",
            "subcategory":"Research",
            "type":"Services"
        }
    ],
    "sg:phone":"+1 416 253 6382",
    "sg:postcode":"M5P 2E8",
    "sg:province":"ON",
    "sg:tags":[
        "market",
        "analysis"
    ],
    "wof:name":"Intellipulse Inc",
    "wof:placetype":"venue"
},
  "geometry": {"coordinates":[-79.4025268555,43.6997909546],"type":"Point"}
}