{
  "type": "Feature",
  "properties": {
    "addr:full":"1166 14th St W North Vancouver BC V7P 1J8",
    "addr:housenumber":"1166",
    "addr:postcode":"v7p 1j8",
    "addr:street":"14Th St W",
    "iso:country":"CA",
    "sg:address":"1166 14th St W",
    "sg:city":"North Vancouver",
    "sg:classifiers":[
        {
            "category":"Building & Trades",
            "subcategory":"Construction",
            "type":"Services"
        }
    ],
    "sg:phone":"+1 604 986 7591",
    "sg:postcode":"V7P 1J8",
    "sg:province":"BC",
    "sg:tags":[
        "repairing",
        "remodeling",
        "contractor"
    ],
    "wof:name":"Character Builders Inc",
    "wof:placetype":"venue"
},
  "geometry": {"coordinates":[-123.09362793,49.3212585449],"type":"Point"}
}