{
  "type": "Feature",
  "properties": {
    "addr:full":"C21260 Side Road 18A Cannington ON L0E 1E0",
    "addr:postcode":"l0e 1e0",
    "addr:street":"C21260 Side Road 18A",
    "iso:country":"CA",
    "sg:address":"C21260 Side Road 18A",
    "sg:city":"Cannington",
    "sg:classifiers":[
        {
            "category":"Retail",
            "subcategory":"Veterinary Services",
            "type":"Services"
        }
    ],
    "sg:phone":"+1 705 432 3392",
    "sg:postcode":"L0E 1E0",
    "sg:province":"ON",
    "sg:tags":[
        "veterinarian"
    ],
    "wof:name":"Cannington Veterinary Svc",
    "wof:placetype":"venue"
},
  "geometry": {"coordinates":[-79.019485,44.307125],"type":"Point"}
}