{
  "type": "Feature",
  "properties": {
    "addr:full":"553 Gregg Ave Hinton AB T7V 1N1",
    "addr:housenumber":"553",
    "addr:postcode":"t7v 1n1",
    "addr:street":"Gregg Ave",
    "iso:country":"CA",
    "sg:address":"553 Gregg Ave",
    "sg:city":"Hinton",
    "sg:classifiers":[
        {
            "category":"Autos & Motor Vehicles",
            "subcategory":"Automobile Sales",
            "type":"Retail Goods"
        }
    ],
    "sg:phone":"+1 780 865 3354",
    "sg:postcode":"T7V 1N1",
    "sg:province":"AB",
    "sg:tags":[
        "car",
        "dealer"
    ],
    "wof:name":"Griffiths Ford",
    "wof:placetype":"venue"
},
  "geometry": {"coordinates":[-117.60498800000001,53.39357],"type":"Point"}
}