{
  "type": "Feature",
  "properties": {
    "addr:full":"39 Oswald St Quill Lake SK S0A 3E0",
    "addr:housenumber":"39",
    "addr:postcode":"s0a 3e0",
    "addr:street":"Oswald St",
    "iso:country":"CA",
    "sg:address":"39 Oswald St",
    "sg:city":"Quill Lake",
    "sg:classifiers":[
        {
            "category":"Organizations",
            "subcategory":"Religious Organization",
            "type":"Services"
        }
    ],
    "sg:phone":"+1 306 383 4132",
    "sg:postcode":"S0A 3E0",
    "sg:province":"SK",
    "sg:tags":[
        "church"
    ],
    "wof:name":"Quill Lake Evangelical Church",
    "wof:placetype":"venue"
},
  "geometry": {"coordinates":[-104.256980896,52.069934845],"type":"Point"}
}