{
  "type": "Feature",
  "properties": {
    "iso:country":"CA",
    "sg:address":"4257 Hastings St",
    "sg:city":"Burnaby",
    "sg:classifiers":[
        {
            "category":"Shopping",
            "subcategory":"Computers & Home Electronics",
            "type":"Retail Goods"
        }
    ],
    "sg:phone":"+1 604 298 5444",
    "sg:postcode":"V5C 2J5",
    "sg:province":"BC",
    "sg:tags":[
        "radio",
        "dealer"
    ],
    "wof:name":"Burnaby Radio Communications",
    "wof:placetype":"venue"
},
  "geometry": {"coordinates":[-123.009841919,49.2811775208],"type":"Point"}
}