{
  "type": "Feature",
  "properties": {
    "addr:full":"Toronto ON M6K 3J7",
    "addr:postcode":"m6k 3j7",
    "iso:country":"CA",
    "sg:city":"Toronto",
    "sg:classifiers":[
        {
            "category":"Shopping",
            "subcategory":"Computers & Home Electronics",
            "type":"Retail Goods"
        }
    ],
    "sg:phone":"+1 416 536 6777",
    "sg:postcode":"M6K 3J7",
    "sg:province":"ON",
    "sg:tags":[
        "parts",
        "supply"
    ],
    "wof:name":"Laser Corp",
    "wof:placetype":"venue"
},
  "geometry": {"coordinates":[-79.42443799999999,43.637878],"type":"Point"}
}