{
  "type": "Feature",
  "properties": {
    "addr:full":"Burlington ON L7R 2E3",
    "addr:postcode":"l7r 2e3",
    "iso:country":"CA",
    "sg:city":"Burlington",
    "sg:classifiers":[
        {
            "category":"Education",
            "subcategory":"Special Training",
            "type":"Public Place"
        }
    ],
    "sg:phone":"+1 905 631 1206",
    "sg:postcode":"L7R 2E3",
    "sg:province":"ON",
    "sg:tags":[
        "school",
        "tutoring"
    ],
    "wof:name":"Burlington Educational Ctr",
    "wof:placetype":"venue"
},
  "geometry": {"coordinates":[-79.80303192140001,43.3431434631],"type":"Point"}
}