{
  "type": "Feature",
  "properties": {
    "iso:country":"CA",
    "sg:address":"259 Broadway",
    "sg:city":"Orangeville",
    "sg:classifiers":[
        {
            "category":"Building & Trades",
            "subcategory":"Cleaning & Sanitation",
            "type":"Services"
        }
    ],
    "sg:phone":"+1 519 942 4534",
    "sg:postcode":"L9W 1K6",
    "sg:province":"ON",
    "sg:tags":[
        "house"
    ],
    "wof:name":"Mrs Moppit",
    "wof:placetype":"venue"
},
  "geometry": {"coordinates":[-80.10126495359999,43.9185409546],"type":"Point"}
}