{
  "type": "Feature",
  "properties": {
    "addr:full":"11 St. Laurent Blvd Penetanguishene ON L9M 1R3",
    "addr:housenumber":"11",
    "addr:postcode":"l9m 1r3",
    "addr:street":"St. Laurent Blvd",
    "iso:country":"CA",
    "sg:address":"11 St. Laurent Blvd",
    "sg:city":"Penetanguishene",
    "sg:classifiers":[
        {
            "category":"Building & Trades",
            "subcategory":"Construction",
            "type":"Services"
        }
    ],
    "sg:phone":"+1 705 533 4688",
    "sg:postcode":"L9M 1R3",
    "sg:province":"ON",
    "sg:tags":[
        "downspouts",
        "gutter",
        "aluminum"
    ],
    "wof:name":"Andee Aluminum",
    "wof:placetype":"venue"
},
  "geometry": {"coordinates":[-79.9353561401,44.768119812],"type":"Point"}
}