{
  "type": "Feature",
  "properties": {
    "iso:country":"CA",
    "sg:address":"5727 23 Ave SE",
    "sg:city":"Calgary",
    "sg:classifiers":[
        {
            "category":"Government",
            "subcategory":"Fire Station",
            "type":"Public Place"
        }
    ],
    "sg:phone":"+1 ",
    "sg:postcode":"T2B 3E2",
    "sg:province":"AB",
    "sg:tags":[
        "department"
    ],
    "wof:name":"Calgary Fire Dept-Training Div",
    "wof:placetype":"venue"
},
  "geometry": {"coordinates":[-113.953873,51.033188],"type":"Point"}
}