{
  "type": "Feature",
  "properties": {
    "addr:full":"146 Main St S Morris MB R0G 1K0",
    "addr:housenumber":"146",
    "addr:postcode":"r0g 1k0",
    "addr:street":"Main St S Morris",
    "iso:country":"CA",
    "sg:address":"146 Main St S",
    "sg:city":"Morris",
    "sg:classifiers":[
        {
            "category":"Autos & Motor Vehicles",
            "subcategory":"Automobile Sales",
            "type":"Retail Goods"
        }
    ],
    "sg:phone":"+1 204 746 2727",
    "sg:postcode":"R0G 1K0",
    "sg:province":"MB",
    "sg:tags":[
        "car",
        "dealer"
    ],
    "wof:name":"Car Manitoba Inc",
    "wof:placetype":"venue"
},
  "geometry": {"coordinates":[-97.3642959595,49.353477478],"type":"Point"}
}