{
  "type": "Feature",
  "properties": {
    "addr:full":"171 Oliver St Williams Lake BC V2G 1L9",
    "addr:housenumber":"171",
    "addr:postcode":"v2g 1l9",
    "addr:street":"Oliver St",
    "iso:country":"CA",
    "sg:address":"171 Oliver St",
    "sg:city":"Williams Lake",
    "sg:classifiers":[
        {
            "category":"Real Estate",
            "subcategory":"Real Estate Agent",
            "type":"Services"
        }
    ],
    "sg:phone":"+1 250 392 4422",
    "sg:postcode":"V2G 1L9",
    "sg:province":"BC",
    "wof:name":"Crosina Realty Ltd",
    "wof:placetype":"venue"
},
  "geometry": {"coordinates":[-122.14443199999999,52.12875],"type":"Point"}
}