{
  "type": "Feature",
  "properties": {
    "iso:country":"CA",
    "sg:address":"59 Forest Rd",
    "sg:city":"Dartmouth",
    "sg:classifiers":[
        {
            "category":"Professional",
            "subcategory":"Business Services",
            "type":"Services"
        }
    ],
    "sg:phone":"+1 902 461 1434",
    "sg:postcode":"B3A 2M4",
    "sg:province":"NS",
    "sg:tags":[
        "interior",
        "consultant",
        "design",
        "decorator"
    ],
    "wof:name":"Contract Design Inc",
    "wof:placetype":"venue"
},
  "geometry": {"coordinates":[-63.5693244934,44.6797637939],"type":"Point"}
}