{
  "type": "Feature",
  "properties": {
    "addr:full":"707 Yonge St Toronto ON M4Y 2B2",
    "addr:housenumber":"707",
    "addr:postcode":"m4y 2b2",
    "addr:street":"Yonge St",
    "iso:country":"CA",
    "sg:address":"707 Yonge St",
    "sg:city":"Toronto",
    "sg:classifiers":[
        {
            "category":"Restaurant",
            "type":"Food & Drink"
        }
    ],
    "sg:phone":"+1 416 920 5448",
    "sg:postcode":"M4Y 2B2",
    "sg:province":"ON",
    "wof:name":"Green Mango Soup Stories",
    "wof:placetype":"venue"
},
  "geometry": {"coordinates":[-79.386276,43.669304],"type":"Point"}
}