{
  "type": "Feature",
  "properties": {
    "addr:full":"100 Mile House BC V0K 2E0",
    "addr:postcode":"v0k 2e0",
    "iso:country":"CA",
    "sg:city":"100 Mile House",
    "sg:classifiers":[
        {
            "category":"Professional",
            "subcategory":"Business Services",
            "type":"Services"
        }
    ],
    "sg:phone":"+1 250 395 3353",
    "sg:postcode":"V0K 2E0",
    "sg:province":"BC",
    "sg:tags":[
        "notary"
    ],
    "wof:name":"Ralph Fossum Corp",
    "wof:placetype":"venue"
},
  "geometry": {"coordinates":[-121.29737900000001,51.642132],"type":"Point"}
}