{
  "type": "Feature",
  "properties": {
    "addr:full":"Grimsby ON L3M 4S5",
    "addr:postcode":"l3m 4s5",
    "iso:country":"CA",
    "sg:city":"Grimsby",
    "sg:classifiers":[
        {
            "category":"Building & Trades",
            "subcategory":"Plumbing",
            "type":"Services"
        }
    ],
    "sg:phone":"+1 905 945 2641",
    "sg:postcode":"L3M 4S5",
    "sg:province":"ON",
    "sg:tags":[
        "contractor"
    ],
    "wof:name":"Brian's Plumbing & Heating Ltd",
    "wof:placetype":"venue"
},
  "geometry": {"coordinates":[-79.57854500000001,43.197723],"type":"Point"}
}