{
  "type": "Feature",
  "properties": {
    "addr:full":"10 Ivy Lane Windsor NS B0N 2T0",
    "addr:housenumber":"10",
    "addr:postcode":"b0n 2t0",
    "addr:street":"Ivy Lane",
    "iso:country":"CA",
    "sg:address":"10 Ivy Lane",
    "sg:city":"Windsor",
    "sg:classifiers":[
        {
            "category":"Wholesale",
            "subcategory":"Machinery & Supplies",
            "type":"Manufacturing & Wholesale Goods"
        }
    ],
    "sg:phone":"+1 902 798 2929",
    "sg:postcode":"B0N 2T0",
    "sg:province":"NS",
    "sg:tags":[
        "ventilating",
        "cleaning",
        "system"
    ],
    "wof:name":"Super Clean Svc Ltd",
    "wof:placetype":"venue"
},
  "geometry": {"coordinates":[-64.1306762695,44.98985672],"type":"Point"}
}