{
  "type": "Feature",
  "properties": {
    "addr:full":"177 Rue Galipeau Thurso QC J0X 3B0",
    "addr:housenumber":"177",
    "addr:postcode":"j0x 3b0",
    "addr:street":"Rue Galipeau",
    "iso:country":"CA",
    "sg:address":"177 Rue Galipeau",
    "sg:city":"Thurso",
    "sg:classifiers":[
        {
            "category":"Arena",
            "subcategory":"Sports Club",
            "type":"Entertainment"
        }
    ],
    "sg:phone":"+1 819 985 2696",
    "sg:postcode":"J0X 3B0",
    "sg:province":"QC",
    "sg:tags":[
        "athletic",
        "fields",
        "stadium",
        "government"
    ],
    "wof:name":"Thurso Arena Guy Lafleur",
    "wof:placetype":"venue"
},
  "geometry": {"coordinates":[-75.2438201904,45.59973526],"type":"Point"}
}