{
  "type": "Feature",
  "properties": {
    "addr:full":"626 Main St Humboldt SK S0K 2A0",
    "addr:housenumber":"626",
    "addr:postcode":"s0k 2a0",
    "addr:street":"Main St",
    "iso:country":"CA",
    "sg:address":"626 Main St",
    "sg:city":"Humboldt",
    "sg:classifiers":[
        {
            "category":"Shopping",
            "subcategory":"Crafts & Fabrics",
            "type":"Retail Goods"
        }
    ],
    "sg:phone":"+1 306 682 0772",
    "sg:postcode":"S0K 2A0",
    "sg:province":"SK",
    "sg:tags":[
        "shop"
    ],
    "wof:name":"Haus of Stitches",
    "wof:placetype":"venue"
},
  "geometry": {"coordinates":[-105.122711,52.199306],"type":"Point"}
}