{
  "type": "Feature",
  "properties": {
    "iso:country":"CA",
    "sg:address":"28 Harvard Ave",
    "sg:city":"Toronto",
    "sg:classifiers":[
        {
            "category":"Home & Garden",
            "subcategory":"Household Appliances",
            "type":"Retail Goods"
        }
    ],
    "sg:phone":"+1 905 677 1360",
    "sg:postcode":"M6R 1C6",
    "sg:province":"ON",
    "wof:name":"Murray's Appliance Svc",
    "wof:placetype":"venue"
},
  "geometry": {"coordinates":[-79.443993,43.640873],"type":"Point"}
}