{
  "type": "Feature",
  "properties": {
    "addr:full":"Delburne AB T0M 0V0",
    "addr:postcode":"t0m 0v0",
    "iso:country":"CA",
    "sg:city":"Delburne",
    "sg:classifiers":[
        {
            "category":"Food & Beverages",
            "subcategory":"Groceries & Convenience Stores",
            "type":"Retail Goods"
        }
    ],
    "sg:phone":"+1 403 749 3610",
    "sg:postcode":"T0M 0V0",
    "sg:province":"AB",
    "sg:tags":[
        "grocer"
    ],
    "wof:name":"Delburne Foods",
    "wof:placetype":"venue"
},
  "geometry": {"coordinates":[-113.239456,52.197369],"type":"Point"}
}