{
  "type": "Feature",
  "properties": {
    "iso:country":"CA",
    "sg:city":"Calgary",
    "sg:phone":"+1 403 250 7881",
    "sg:postcode":"T2E 7B2",
    "sg:province":"AB",
    "sg:tags":[
        "shelving"
    ],
    "wof:name":"Waymarc Industries Ltd",
    "wof:placetype":"venue"
},
  "geometry": {"coordinates":[-114.01388549799999,51.0798110962],"type":"Point"}
}