{
  "type": "Feature",
  "properties": {
    "addr:full":"1010 Rivers Edge Dr West Montrose ON N0B 2V0",
    "addr:housenumber":"1010",
    "addr:postcode":"n0b 2v0",
    "addr:street":"Rivers Edge Dr West",
    "iso:country":"CA",
    "sg:address":"1010 Rivers Edge Dr",
    "sg:city":"West Montrose",
    "sg:classifiers":[
        {
            "category":"Home & Garden",
            "subcategory":"Furniture",
            "type":"Retail Goods"
        }
    ],
    "sg:phone":"+1 519 669 4296",
    "sg:postcode":"N0B 2V0",
    "sg:province":"ON",
    "sg:tags":[
        "builder",
        "custom"
    ],
    "wof:name":"Westwood Furniture CO",
    "wof:placetype":"venue"
},
  "geometry": {"coordinates":[-80.468605,43.586758],"type":"Point"}
}