{
  "type": "Feature",
  "properties": {
    "addr:full":"925 10th St E Owen Sound ON N4K 1T5",
    "addr:housenumber":"925",
    "addr:postcode":"n4k 1t5",
    "addr:street":"10Th St E",
    "iso:country":"CA",
    "sg:address":"925 10th St E",
    "sg:city":"Owen Sound",
    "sg:classifiers":[
        {
            "category":"Food & Beverages",
            "subcategory":"Bakery",
            "type":"Retail Goods"
        }
    ],
    "sg:phone":"+1 519 376 6070",
    "sg:postcode":"N4K 1T5",
    "sg:province":"ON",
    "sg:tags":[
        "doughnut"
    ],
    "wof:name":"Tim Hortons",
    "wof:placetype":"venue"
},
  "geometry": {"coordinates":[-80.92771148680001,44.5693740845],"type":"Point"}
}