{
  "type": "Feature",
  "properties": {
    "addr:full":"521 Gladwish Dr Sarnia ON N7T 7H3",
    "addr:housenumber":"521",
    "addr:postcode":"n7t 7h3",
    "addr:street":"Gladwish Dr",
    "iso:country":"CA",
    "sg:address":"521 Gladwish Dr",
    "sg:city":"Sarnia",
    "sg:classifiers":[
        {
            "category":"Retail",
            "subcategory":"Animal Services",
            "type":"Services"
        }
    ],
    "sg:phone":"+1 519 336 8618",
    "sg:postcode":"N7T 7H3",
    "sg:province":"ON",
    "sg:tags":[
        "pet",
        "boarding",
        "sitting"
    ],
    "wof:name":"Barkers Lodge",
    "wof:placetype":"venue"
},
  "geometry": {"coordinates":[-82.3497009277,42.9423294067],"type":"Point"}
}