{
  "type": "Feature",
  "properties": {
    "addr:full":"858 16 Ave SW Calgary AB T2R 0S9",
    "addr:postcode":"t2r 0s9",
    "addr:street":"858 16 Ave Sw",
    "iso:country":"CA",
    "sg:address":"858 16 Ave SW",
    "sg:city":"Calgary",
    "sg:classifiers":[
        {
            "category":"Shopping",
            "subcategory":"Stationery & Office Supplies",
            "type":"Retail Goods"
        }
    ],
    "sg:phone":"+1 403 245 8868",
    "sg:postcode":"T2R 0S9",
    "sg:province":"AB",
    "sg:tags":[
        "stationer"
    ],
    "wof:name":"Social Page",
    "wof:placetype":"venue"
},
  "geometry": {"coordinates":[-114.080719,51.038219],"type":"Point"}
}