{
  "type": "Feature",
  "properties": {
    "addr:full":"PO Box 121 Howick QC J0S 1G0",
    "addr:housenumber":"po;121",
    "addr:postcode":"j0s 1g0",
    "addr:street":"Box",
    "iso:country":"CA",
    "sg:address":"PO Box 121",
    "sg:city":"Howick",
    "sg:classifiers":[
        {
            "category":"Organizations",
            "subcategory":"Religious Organization",
            "type":"Services"
        }
    ],
    "sg:phone":"+1 514 825 2736",
    "sg:postcode":"J0S 1G0",
    "sg:province":"QC",
    "sg:tags":[
        "church"
    ],
    "wof:name":"Howick United Church",
    "wof:placetype":"venue"
},
  "geometry": {"coordinates":[-73.856667,45.19368],"type":"Point"}
}