{
  "type": "Feature",
  "properties": {
    "iso:country":"CA",
    "sg:address":"513 Westney Rd S",
    "sg:city":"Ajax",
    "sg:classifiers":[
        {
            "category":"Real Estate",
            "subcategory":"Real Estate Agent",
            "type":"Services"
        }
    ],
    "sg:phone":"+1 905 683 7800",
    "sg:postcode":"L1S 6W8",
    "sg:province":"ON",
    "wof:name":"Kondo, Brian",
    "wof:placetype":"venue"
},
  "geometry": {"coordinates":[-79.0324935913,43.8314857483],"type":"Point"}
}