{
  "type": "Feature",
  "properties": {
    "addr:full":"Pike Lake Rd Thunder Bay ON P7B 6B3",
    "addr:postcode":"p7b 6b3",
    "addr:street":"Pike Lake Rd",
    "iso:country":"CA",
    "sg:address":"Pike Lake Rd",
    "sg:city":"Thunder Bay",
    "sg:classifiers":[
        {
            "category":"Retail",
            "subcategory":"Auto Repair",
            "type":"Services"
        }
    ],
    "sg:phone":"+1 807 683 7445",
    "sg:postcode":"P7B 6B3",
    "sg:province":"ON",
    "sg:tags":[
        "repairing",
        "automobile"
    ],
    "wof:name":"Marty's Automotive Repair Svc",
    "wof:placetype":"venue"
},
  "geometry": {"coordinates":[-89.26714324949999,48.5941925049],"type":"Point"}
}