{
  "type": "Feature",
  "properties": {
    "iso:country":"CA",
    "sg:address":"545 Erskine Ave",
    "sg:city":"Peterborough",
    "sg:classifiers":[
        {
            "category":"Building & Trades",
            "subcategory":"Plumbing",
            "type":"Services"
        }
    ],
    "sg:phone":"+1 705 741 1606",
    "sg:postcode":"K9J 7Z1",
    "sg:province":"ON",
    "sg:tags":[
        "heating",
        "contractor"
    ],
    "wof:name":"David's Gas Svc",
    "wof:placetype":"venue"
},
  "geometry": {"coordinates":[-78.332214,44.273823],"type":"Point"}
}