{
  "type": "Feature",
  "properties": {
    "addr:full":"Copper Cliff ON P0M 1N0",
    "addr:postcode":"p0m 1n0",
    "iso:country":"CA",
    "sg:city":"Copper Cliff",
    "sg:classifiers":[
        {
            "category":"Health Services",
            "subcategory":"Doctor",
            "type":"Services"
        }
    ],
    "sg:phone":"+1 705 682 0622",
    "sg:postcode":"P0M 1N0",
    "sg:province":"ON",
    "sg:tags":[
        "dentist"
    ],
    "wof:name":"Ulrichsen, R F DDS",
    "wof:placetype":"venue"
},
  "geometry": {"coordinates":[-81.06640625,46.4778518677],"type":"Point"}
}