{
  "type": "Feature",
  "properties": {
    "addr:full":"Milton ON L9T 5C1",
    "addr:postcode":"l9t 5c1",
    "iso:country":"CA",
    "sg:city":"Milton",
    "sg:classifiers":[
        {
            "category":"Building & Trades",
            "subcategory":"Construction",
            "type":"Services"
        }
    ],
    "sg:phone":"+1 905 875 0090",
    "sg:postcode":"L9T 5C1",
    "sg:province":"ON",
    "sg:tags":[
        "millwright"
    ],
    "wof:name":"Meehan's Industrial Mntnc Ltd",
    "wof:placetype":"venue"
},
  "geometry": {"coordinates":[-79.9026184082,43.5170936584],"type":"Point"}
}