{
  "type": "Feature",
  "properties": {
    "iso:country":"CA",
    "sg:address":"6041 West Blvd",
    "sg:city":"Vancouver",
    "sg:classifiers":[
        {
            "category":"Personal",
            "subcategory":"Shoe Repair & Shine",
            "type":"Services"
        }
    ],
    "sg:phone":"+1 604 263 0699",
    "sg:postcode":"V6M 3X2",
    "sg:province":"BC",
    "sg:tags":[
        "repairing",
        "boot"
    ],
    "wof:name":"Tony's Shoe Repair",
    "wof:placetype":"venue"
},
  "geometry": {"coordinates":[-123.15592956499999,49.2313957214],"type":"Point"}
}