{
  "type": "Feature",
  "properties": {
    "addr:full":"69 Hickman St Amherst NS B4H 2M6",
    "addr:housenumber":"69",
    "addr:postcode":"b4h 2m6",
    "addr:street":"Hickman St",
    "iso:country":"CA",
    "sg:address":"69 Hickman St",
    "sg:city":"Amherst",
    "sg:classifiers":[
        {
            "category":"Food & Beverages",
            "subcategory":"Groceries & Convenience Stores",
            "type":"Retail Goods"
        }
    ],
    "sg:phone":"+1 902 667 4821",
    "sg:postcode":"B4H 2M6",
    "sg:province":"NS",
    "sg:tags":[
        "grocer"
    ],
    "wof:name":"Highland Market",
    "wof:placetype":"venue"
},
  "geometry": {"coordinates":[-64.212982,45.821129],"type":"Point"}
}