{
  "type": "Feature",
  "properties": {
    "addr:full":"604 Duchess St Saskatoon SK S7K 0R1",
    "addr:housenumber":"604",
    "addr:postcode":"s7k 0r1",
    "addr:street":"Duchess St",
    "iso:country":"CA",
    "sg:address":"604 Duchess St",
    "sg:city":"Saskatoon",
    "sg:classifiers":[
        {
            "category":"Health Services",
            "subcategory":"Clinic",
            "type":"Services"
        }
    ],
    "sg:phone":"+1 306 956 3334",
    "sg:postcode":"S7K 0R1",
    "sg:province":"SK",
    "sg:tags":[
        "home"
    ],
    "wof:name":"Saskatoon Home Support Svc",
    "wof:placetype":"venue"
},
  "geometry": {"coordinates":[-106.653442383,52.142616272],"type":"Point"}
}