{
  "type": "Feature",
  "properties": {
    "addr:full":"3660 20 Ave NE # 3 Calgary AB T1Y 6E8",
    "addr:housenumber":"3660",
    "addr:postcode":"t1y 6e8",
    "addr:street":"20 Ave Ne # 3",
    "iso:country":"CA",
    "sg:address":"3660 20 Ave NE # 3",
    "sg:city":"Calgary",
    "sg:classifiers":[
        {
            "category":"Retail",
            "subcategory":"Veterinary Services",
            "type":"Services"
        }
    ],
    "sg:phone":"+1 403 285 8777",
    "sg:postcode":"T1Y 6E8",
    "sg:province":"AB",
    "sg:tags":[
        "veterinarian"
    ],
    "wof:name":"Sunridge Veterinary Clinic",
    "wof:placetype":"venue"
},
  "geometry": {"coordinates":[-113.982834,51.071735],"type":"Point"}
}