{
  "type": "Feature",
  "properties": {
    "addr:full":"205 Bear St Banff AB T1L 1H1",
    "addr:housenumber":"205",
    "addr:postcode":"t1l 1h1",
    "addr:street":"Bear St",
    "iso:country":"CA",
    "sg:address":"205 Bear St",
    "sg:city":"Banff",
    "sg:classifiers":[
        {
            "category":"Professional",
            "subcategory":"Lawyer & Legal Services",
            "type":"Services"
        }
    ],
    "sg:phone":"+1 403 762 2770",
    "sg:postcode":"T1L 1H1",
    "sg:province":"AB",
    "sg:tags":[
        "attorney"
    ],
    "wof:name":"Rathbone, Gordon",
    "wof:placetype":"venue"
},
  "geometry": {"coordinates":[-115.57261657700001,51.1768836975],"type":"Point"}
}