{
  "type": "Feature",
  "properties": {
    "addr:full":"202 Main St Elnora AB T0M 0Y0",
    "addr:housenumber":"202",
    "addr:postcode":"t0m 0y0",
    "addr:street":"Main St",
    "iso:country":"CA",
    "sg:address":"202 Main St",
    "sg:city":"Elnora",
    "sg:classifiers":[
        {
            "category":"Travel",
            "subcategory":"Hotels & Motels",
            "type":"Entertainment"
        }
    ],
    "sg:phone":"+1 403 773 3567",
    "sg:postcode":"T0M 0Y0",
    "sg:province":"AB",
    "wof:name":"Elnora Hotel",
    "wof:placetype":"venue"
},
  "geometry": {"coordinates":[-113.199692,51.991722],"type":"Point"}
}