{
  "type": "Feature",
  "properties": {
    "addr:full":"30 Harmony Rd S Oshawa ON L1H 6T3",
    "addr:housenumber":"30",
    "addr:postcode":"l1h 6t3",
    "addr:street":"Harmony Rd",
    "iso:country":"CA",
    "sg:address":"30 Harmony Rd S",
    "sg:city":"Oshawa",
    "sg:classifiers":[
        {
            "category":"Shopping",
            "subcategory":"Discount & Variety Stores",
            "type":"Retail Goods"
        }
    ],
    "sg:phone":"+1 905 576 1678",
    "sg:postcode":"L1H 6T3",
    "sg:province":"ON",
    "wof:name":"L & G Grocery & Variety",
    "wof:placetype":"venue"
},
  "geometry": {"coordinates":[-78.83373260499999,43.9032592773],"type":"Point"}
}