{
  "type": "Feature",
  "properties": {
    "addr:full":"1779 Rue DE LA Cimaise L'Ancienne-Lorette QC G2E 6A4",
    "addr:housenumber":"1779",
    "addr:postcode":"g2e 6a4",
    "addr:street":"Rue De La Cimaise",
    "iso:country":"CA",
    "sg:address":"1779 Rue DE LA Cimaise",
    "sg:city":"L'Ancienne-Lorette",
    "sg:classifiers":[
        {
            "category":"Building & Trades",
            "subcategory":"Electrical",
            "type":"Services"
        }
    ],
    "sg:phone":"+1 418 877 3817",
    "sg:postcode":"G2E 6A4",
    "sg:province":"QC",
    "sg:tags":[
        "electric",
        "contractor"
    ],
    "wof:name":"Caron Gregoire Inc",
    "wof:placetype":"venue"
},
  "geometry": {"coordinates":[-71.354591,46.814682],"type":"Point"}
}