{
  "type": "Feature",
  "properties": {
    "addr:full":"19790 Telegraph Trail Langley BC V1M 3E5",
    "addr:housenumber":"19790",
    "addr:postcode":"v1m 3e5",
    "addr:street":"Telegraph Trail",
    "iso:country":"CA",
    "sg:address":"19790 Telegraph Trail",
    "sg:city":"Langley",
    "sg:classifiers":[
        {
            "category":"Wholesale",
            "subcategory":"Drugs",
            "type":"Manufacturing & Wholesale Goods"
        }
    ],
    "sg:phone":"+1 604 888 2631",
    "sg:postcode":"V1M 3E5",
    "sg:province":"BC",
    "sg:tags":[
        "pharmaceutical",
        "product"
    ],
    "wof:name":"Pacifico Cotton Rayon Cnvrtrs",
    "wof:placetype":"venue"
},
  "geometry": {"coordinates":[-122.674255371,49.17811203],"type":"Point"}
}