{
  "type": "Feature",
  "properties": {
    "addr:full":"Regina SK S4P 3N6",
    "addr:postcode":"s4p 3n6",
    "iso:country":"CA",
    "sg:city":"Regina",
    "sg:classifiers":[
        {
            "category":"Professional",
            "subcategory":"Management & Consulting",
            "type":"Services"
        }
    ],
    "sg:phone":"+1 306 584 1000",
    "sg:postcode":"S4P 3N6",
    "sg:province":"SK",
    "sg:tags":[
        "publisher",
        "counselor",
        "public",
        "relations"
    ],
    "wof:name":"Charlton Communications Inc",
    "wof:placetype":"venue"
},
  "geometry": {"coordinates":[-104.609603882,50.4484977722],"type":"Point"}
}