{
  "type": "Feature",
  "properties": {
    "addr:full":"4744 Dundas St E Thorndale ON N0M 2P0",
    "addr:housenumber":"4744",
    "addr:postcode":"n0m 2p0",
    "addr:street":"Dundas St",
    "iso:country":"CA",
    "sg:address":"4744 Dundas St E",
    "sg:city":"Thorndale",
    "sg:classifiers":[
        {
            "category":"Recreation",
            "type":"Entertainment"
        }
    ],
    "sg:phone":"+1 519 268 8651",
    "sg:postcode":"N0M 2P0",
    "sg:province":"ON",
    "sg:tags":[
        "range",
        "practice",
        "golf"
    ],
    "wof:name":"Maple View Driving Range",
    "wof:placetype":"venue"
},
  "geometry": {"coordinates":[-81.1411819458,43.1051330566],"type":"Point"}
}