{
  "type": "Feature",
  "properties": {
    "addr:full":"1238 Homer St # 3 Vancouver BC V6B 2Y5",
    "addr:housenumber":"1238",
    "addr:postcode":"bc v6b 2y5",
    "addr:street":"Homer St # 3",
    "iso:country":"CA",
    "sg:address":"1238 Homer St # 3",
    "sg:city":"Vancouver",
    "sg:classifiers":[
        {
            "category":"Health Services",
            "subcategory":"Chiropractor",
            "type":"Services"
        }
    ],
    "sg:phone":"+1 604 688 1500",
    "sg:postcode":"V6B 2Y5",
    "sg:province":"BC",
    "wof:name":"Yaletown Chiropractic",
    "wof:placetype":"venue"
},
  "geometry": {"coordinates":[-123.12381000000001,49.274742],"type":"Point"}
}