{
  "type": "Feature",
  "properties": {
    "addr:full":"34 Village Centre Pl Mississauga ON L4Z 1V9",
    "addr:housenumber":"34",
    "addr:postcode":"l4z 1v9",
    "addr:street":"Village Centre Pl",
    "iso:country":"CA",
    "sg:address":"34 Village Centre Pl",
    "sg:city":"Mississauga",
    "sg:classifiers":[
        {
            "category":"Shopping",
            "subcategory":"Computers & Home Electronics",
            "type":"Retail Goods"
        }
    ],
    "sg:phone":"+1 905 272 5929",
    "sg:postcode":"L4Z 1V9",
    "sg:province":"ON",
    "sg:tags":[
        "software"
    ],
    "wof:name":"Hansen Information Tech Canada",
    "wof:placetype":"venue"
},
  "geometry": {"coordinates":[-79.641006,43.600563],"type":"Point"}
}