{
  "type": "Feature",
  "properties": {
    "addr:full":"6647 177 St NW Edmonton AB T5T 4K3",
    "addr:housenumber":"6647",
    "addr:postcode":"t5t 4k3",
    "addr:street":"177 St Nw",
    "iso:country":"CA",
    "sg:address":"6647 177 St NW",
    "sg:city":"Edmonton",
    "sg:classifiers":[
        {
            "category":"Health Services",
            "subcategory":"Doctor",
            "type":"Services"
        }
    ],
    "sg:phone":"+1 780 481 8668",
    "sg:postcode":"T5T 4K3",
    "sg:province":"AB",
    "sg:tags":[
        "dentist"
    ],
    "wof:name":"Callingwood Orthodontics",
    "wof:placetype":"venue"
},
  "geometry": {"coordinates":[-113.627029419,53.5016021729],"type":"Point"}
}