{
  "type": "Feature",
  "properties": {
    "addr:full":"257 Wentworth St W Oshawa ON L1J 1M9",
    "addr:housenumber":"257",
    "addr:postcode":"l1j 1m9",
    "addr:street":"Wentworth St W",
    "iso:country":"CA",
    "sg:address":"257 Wentworth St W",
    "sg:city":"Oshawa",
    "sg:classifiers":[
        {
            "category":"Food & Beverages",
            "subcategory":"Liquor & Beverages",
            "type":"Retail Goods"
        }
    ],
    "sg:phone":"+1 905 576 9595",
    "sg:postcode":"L1J 1M9",
    "sg:province":"ON",
    "sg:tags":[
        "beer",
        "ale"
    ],
    "wof:name":"Beer Store",
    "wof:placetype":"venue"
},
  "geometry": {"coordinates":[-78.8528289795,43.8695411682],"type":"Point"}
}