{
  "type": "Feature",
  "properties": {
    "addr:full":"1244 Cornwall St Regina SK S4R 2H3",
    "addr:housenumber":"1244",
    "addr:postcode":"s4r 2h3",
    "addr:street":"Cornwall St",
    "iso:country":"CA",
    "sg:address":"1244 Cornwall St",
    "sg:city":"Regina",
    "sg:classifiers":[
        {
            "category":"Building & Trades",
            "subcategory":"Landscaping Services",
            "type":"Services"
        }
    ],
    "sg:phone":"+1 306 525 0009",
    "sg:postcode":"S4R 2H3",
    "sg:province":"SK",
    "sg:tags":[
        "lawn",
        "maintenance",
        "grounds"
    ],
    "wof:name":"Brook's Yard Maintenance",
    "wof:placetype":"venue"
},
  "geometry": {"coordinates":[-104.61240386999999,50.4591255188],"type":"Point"}
}