{
  "type": "Feature",
  "properties": {
    "addr:full":"15709 111 St NW Edmonton AB T5X 4S3",
    "addr:housenumber":"15709",
    "addr:postcode":"t5x 4s3",
    "addr:street":"111 St Nw",
    "iso:country":"CA",
    "sg:address":"15709 111 St NW",
    "sg:city":"Edmonton",
    "sg:classifiers":[
        {
            "category":"Professional",
            "subcategory":"Art Services",
            "type":"Services"
        }
    ],
    "sg:phone":"+1 780 476 8661",
    "sg:postcode":"T5X 4S3",
    "sg:province":"AB",
    "sg:tags":[
        "graphic",
        "designer"
    ],
    "wof:name":"Planet Rebus",
    "wof:placetype":"venue"
},
  "geometry": {"coordinates":[-113.513992,53.618378],"type":"Point"}
}