{
  "type": "Feature",
  "properties": {
    "addr:full":"Hampton NB E5N 6C1",
    "addr:postcode":"e5n 6c1",
    "iso:country":"CA",
    "sg:city":"Hampton",
    "sg:classifiers":[
        {
            "category":"Restaurant",
            "type":"Food & Drink"
        }
    ],
    "sg:phone":"+1 506 832 5520",
    "sg:postcode":"E5N 6C1",
    "sg:province":"NB",
    "wof:name":"Holly's Restaurant",
    "wof:placetype":"venue"
},
  "geometry": {"coordinates":[-65.83335099999999,45.519939],"type":"Point"}
}