{
  "type": "Feature",
  "properties": {
    "iso:country":"CA",
    "sg:address":"20 Cherrytree Dr",
    "sg:city":"Brampton",
    "sg:classifiers":[
        {
            "category":"Real Estate",
            "subcategory":"Real Estate Operator",
            "type":"Services"
        }
    ],
    "sg:phone":"+1 905 454 1273",
    "sg:postcode":"L6Y 3V1",
    "sg:province":"ON",
    "sg:tags":[
        "condominium"
    ],
    "wof:name":"Peel Condominium Corp 304",
    "wof:placetype":"venue"
},
  "geometry": {"coordinates":[-79.7235870361,43.6560096741],"type":"Point"}
}