{
  "type": "Feature",
  "properties": {
    "addr:full":"477 Paul St Dieppe NB E1A 4X5",
    "addr:housenumber":"477",
    "addr:postcode":"e1a 4x5",
    "addr:street":"Paul St",
    "iso:country":"CA",
    "sg:address":"477 Paul St",
    "sg:city":"Dieppe",
    "sg:classifiers":[
        {
            "category":"Shopping",
            "subcategory":"Bicycles & Sporting Goods",
            "type":"Retail Goods"
        }
    ],
    "sg:phone":"+1 506 858 0160",
    "sg:postcode":"E1A 4X5",
    "sg:province":"NB",
    "wof:name":"Sport Chek",
    "wof:placetype":"venue"
},
  "geometry": {"coordinates":[-64.76100158689999,46.0988845825],"type":"Point"}
}