{
  "type": "Feature",
  "properties": {
    "addr:full":"196 Robert St Toronto ON M5S 2K7",
    "addr:housenumber":"196",
    "addr:postcode":"m5s 2k7",
    "addr:street":"Robert St",
    "iso:country":"CA",
    "sg:address":"196 Robert St",
    "sg:city":"Toronto",
    "sg:classifiers":[
        {
            "category":"Restaurant",
            "type":"Food & Drink"
        }
    ],
    "sg:phone":"+1 416 966 6671",
    "sg:postcode":"M5S 2K7",
    "sg:province":"ON",
    "wof:name":"Momo's",
    "wof:placetype":"venue"
},
  "geometry": {"coordinates":[-79.4041213989,43.6629333496],"type":"Point"}
}