{
  "type": "Feature",
  "properties": {
    "iso:country":"CA",
    "sg:address":"800 Petrolia Rd #1",
    "sg:city":"North York",
    "sg:classifiers":[
        {
            "category":"Retail",
            "subcategory":"Car Wash",
            "type":"Services"
        }
    ],
    "sg:phone":"+1 416 667 0875",
    "sg:postcode":"M3J 3K4",
    "sg:province":"ON",
    "sg:tags":[
        "polishing",
        "washing"
    ],
    "wof:name":"Custom Car Care Gold Plated",
    "wof:placetype":"venue"
},
  "geometry": {"coordinates":[-79.48862457280001,43.7784194946],"type":"Point"}
}