{
  "type": "Feature",
  "properties": {
    "addr:full":"8083 Boul Du Centre-Hospitalie Charny QC G6X 1L3",
    "addr:housenumber":"8083",
    "addr:postcode":"g6x 1l3",
    "addr:street":"Boul Du Centre-Hospitalie",
    "iso:country":"CA",
    "sg:address":"8083 Boul Du Centre-Hospitalie",
    "sg:city":"Charny",
    "sg:classifiers":[
        {
            "category":"Organizations",
            "subcategory":"Professional Association",
            "type":"Services"
        }
    ],
    "sg:phone":"+1 418 832 7884",
    "sg:postcode":"G6X 1L3",
    "sg:province":"QC",
    "wof:name":"Federation Intl DE Sport Kin",
    "wof:placetype":"venue"
},
  "geometry": {"coordinates":[-71.2683181763,46.7218780518],"type":"Point"}
}