{
  "type": "Feature",
  "properties": {
    "addr:full":"509 Boul Du Cure-Boivin Boisbriand QC J7G 2A8",
    "addr:housenumber":"509",
    "addr:postcode":"j7g 2a8",
    "addr:street":"Boul Du Cure-Boivin",
    "iso:country":"CA",
    "sg:address":"509 Boul Du Cure-Boivin",
    "sg:city":"Boisbriand",
    "sg:classifiers":[
        {
            "category":"Retail",
            "subcategory":"Repair Shop",
            "type":"Services"
        }
    ],
    "sg:phone":"+1 450 435 5131",
    "sg:postcode":"J7G 2A8",
    "sg:province":"QC",
    "sg:tags":[
        "ironwork"
    ],
    "wof:name":"Decoration Metallique Gr Inc",
    "wof:placetype":"venue"
},
  "geometry": {"coordinates":[-73.82569100000001,45.620632],"type":"Point"}
}