{
  "type": "Feature",
  "properties": {
    "iso:country":"CA",
    "sg:address":"44 Commercial Ave",
    "sg:city":"Ajax",
    "sg:classifiers":[
        {
            "category":"Restaurant",
            "type":"Food & Drink"
        }
    ],
    "sg:phone":"+1 905 619 9296",
    "sg:postcode":"L1S 2H5",
    "sg:province":"ON",
    "wof:name":"Michael's Eatery",
    "wof:placetype":"venue"
},
  "geometry": {"coordinates":[-79.023514,43.849857],"type":"Point"}
}