{
  "type": "Feature",
  "properties": {
    "addr:full":"5421 Hamilton Rd Dorchester ON N0L 1G6",
    "addr:housenumber":"5421",
    "addr:postcode":"n0l 1g6",
    "addr:street":"Hamilton Rd",
    "iso:country":"CA",
    "sg:address":"5421 Hamilton Rd",
    "sg:city":"Dorchester",
    "sg:classifiers":[
        {
            "category":"Recreation",
            "type":"Entertainment"
        }
    ],
    "sg:phone":"+1 519 268 3352",
    "sg:postcode":"N0L 1G6",
    "sg:province":"ON",
    "sg:tags":[
        "course",
        "golf"
    ],
    "wof:name":"Pine Knot Golf & Country Club",
    "wof:placetype":"venue"
},
  "geometry": {"coordinates":[-81.012947,42.979073],"type":"Point"}
}