{
  "type": "Feature",
  "properties": {
    "addr:full":"PO Box 323 Beachville ON N0J 1A0",
    "addr:housenumber":"po",
    "addr:postcode":"n0j 1a0",
    "addr:street":"Box 323",
    "iso:country":"CA",
    "sg:address":"PO Box 323",
    "sg:city":"Beachville",
    "sg:classifiers":[
        {
            "category":"Building & Trades",
            "subcategory":"Construction",
            "type":"Services"
        }
    ],
    "sg:phone":"+1 519 423 6938",
    "sg:postcode":"N0J 1A0",
    "sg:province":"ON",
    "sg:tags":[
        "excavating",
        "contractor"
    ],
    "wof:name":"Paul J Seys Ltd",
    "wof:placetype":"venue"
},
  "geometry": {"coordinates":[-80.829948,43.090088],"type":"Point"}
}