{
  "type": "Feature",
  "properties": {
    "addr:full":"1050 Baxter Rd # 7C Ottawa ON K2C 3P1",
    "addr:housenumber":"1050",
    "addr:postcode":"k2c 3p1",
    "addr:street":"Baxter Rd # 7C",
    "iso:country":"CA",
    "sg:address":"1050 Baxter Rd # 7C",
    "sg:city":"Ottawa",
    "sg:classifiers":[
        {
            "category":"Home & Garden",
            "subcategory":"Furniture",
            "type":"Retail Goods"
        }
    ],
    "sg:phone":"+1 613 596 5155",
    "sg:postcode":"K2C 3P1",
    "sg:province":"ON",
    "sg:tags":[
        "equipment",
        "kitchen",
        "cabinet"
    ],
    "wof:name":"Deslaurier Custom Cabinets Inc",
    "wof:placetype":"venue"
},
  "geometry": {"coordinates":[-75.7827377319,45.3531112671],"type":"Point"}
}