{
  "type": "Feature",
  "properties": {
    "addr:full":"1432 Rue DE Bleury Montreal QC H3A 2J1",
    "addr:housenumber":"1432",
    "addr:postcode":"h3a 2j1",
    "addr:street":"Rue De Bleury",
    "iso:country":"CA",
    "sg:address":"1432 Rue DE Bleury",
    "sg:city":"Montreal",
    "sg:classifiers":[
        {
            "category":"Cinema",
            "subcategory":"Movie Theater",
            "type":"Entertainment"
        }
    ],
    "sg:phone":"+1 514 848 0300",
    "sg:postcode":"H3A 2J1",
    "sg:province":"QC",
    "wof:name":"Cinema Imperial",
    "wof:placetype":"venue"
},
  "geometry": {"coordinates":[-73.567421,45.506386],"type":"Point"}
}