{
  "type": "Feature",
  "properties": {
    "addr:full":"175 Kent Ave North W Vancouver BC V5X 2X4",
    "addr:housenumber":"175",
    "addr:postcode":"v5x 2x4",
    "addr:street":"Kent Ave North W",
    "iso:country":"CA",
    "sg:address":"175 Kent Ave North W",
    "sg:city":"Vancouver",
    "sg:classifiers":[
        {
            "category":"Retail",
            "subcategory":"Auto Repair",
            "type":"Services"
        }
    ],
    "sg:phone":"+1 604 322 9494",
    "sg:postcode":"V5X 2X4",
    "sg:province":"BC",
    "sg:tags":[
        "body",
        "automobile",
        "painting"
    ],
    "wof:name":"Spotlite Custom Collision Ltd",
    "wof:placetype":"venue"
},
  "geometry": {"coordinates":[-123.103325,49.207333],"type":"Point"}
}