{
  "type": "Feature",
  "properties": {
    "addr:full":"142 North St Hinton AB T7V 1S8",
    "addr:housenumber":"142",
    "addr:postcode":"t7v 1s8",
    "addr:street":"North St",
    "iso:country":"CA",
    "sg:address":"142 North St",
    "sg:city":"Hinton",
    "sg:classifiers":[
        {
            "category":"Building & Trades",
            "subcategory":"Electrical",
            "type":"Services"
        }
    ],
    "sg:phone":"+1 780 865 5901",
    "sg:postcode":"T7V 1S8",
    "sg:province":"AB",
    "sg:tags":[
        "field",
        "oil",
        "electric",
        "contractor"
    ],
    "wof:name":"Enerflex Syntech",
    "wof:placetype":"venue"
},
  "geometry": {"coordinates":[-117.607147,53.394531],"type":"Point"}
}