{
  "type": "Feature",
  "properties": {
    "addr:full":"207 Tiffin St Barrie ON L4N 2N3",
    "addr:housenumber":"207",
    "addr:postcode":"l4n 2n3",
    "addr:street":"Tiffin St",
    "iso:country":"CA",
    "sg:address":"207 Tiffin St",
    "sg:city":"Barrie",
    "sg:classifiers":[
        {
            "category":"Manufacturing",
            "subcategory":"Glass & Minerals",
            "type":"Manufacturing & Wholesale Goods"
        }
    ],
    "sg:phone":"+1 705 726 6543",
    "sg:postcode":"L4N 2N3",
    "sg:province":"ON",
    "sg:tags":[
        "concrete",
        "shape",
        "block",
        "structural"
    ],
    "wof:name":"Simcoe Block",
    "wof:placetype":"venue"
},
  "geometry": {"coordinates":[-79.702309,44.371773],"type":"Point"}
}