{
  "type": "Feature",
  "properties": {
    "addr:full":"20 Minuk Acres Scarborough ON M1E 4Y6",
    "addr:housenumber":"20",
    "addr:postcode":"m1e 4y6",
    "addr:street":"Minuk Acres",
    "iso:country":"CA",
    "sg:address":"20 Minuk Acres",
    "sg:city":"Scarborough",
    "sg:classifiers":[
        {
            "category":"Wholesale",
            "subcategory":"Meat",
            "type":"Manufacturing & Wholesale Goods"
        }
    ],
    "sg:phone":"+1 416 283 8777",
    "sg:postcode":"M1E 4Y6",
    "sg:province":"ON",
    "sg:tags":[
        "product"
    ],
    "wof:name":"Beechgrove Country Foods",
    "wof:placetype":"venue"
},
  "geometry": {"coordinates":[-79.15804300000001,43.765762],"type":"Point"}
}