{
  "type": "Feature",
  "properties": {
    "iso:country":"CA",
    "sg:address":"20 Minuk Acres",
    "sg:city":"Scarborough",
    "sg:classifiers":[
        {
            "category":"Wholesale",
            "subcategory":"Meat",
            "type":"Manufacturing & Wholesale Goods"
        }
    ],
    "sg:phone":"+1 416 283 8777",
    "sg:postcode":"M1E 4Y6",
    "sg:province":"ON",
    "sg:tags":[
        "product"
    ],
    "wof:name":"Beechgrove Country Foods",
    "wof:placetype":"venue"
},
  "geometry": {"coordinates":[-79.158043,43.765762],"type":"Point"}
}