{
  "type": "Feature",
  "properties": {
    "addr:full":"113 Rue Saint-Germain E Rimouski QC G5L 1A5",
    "addr:housenumber":"113",
    "addr:postcode":"g5l 1a5",
    "addr:street":"Rue Saint-Germain E",
    "iso:country":"CA",
    "sg:address":"113 Rue Saint-Germain E",
    "sg:city":"Rimouski",
    "sg:classifiers":[
        {
            "category":"Shopping",
            "subcategory":"Bicycles & Sporting Goods",
            "type":"Retail Goods"
        }
    ],
    "sg:phone":"+1 418 721 0052",
    "sg:postcode":"G5L 1A5",
    "sg:province":"QC",
    "sg:tags":[
        "equipment",
        "skateboard"
    ],
    "wof:name":"Alternative Sports Inc",
    "wof:placetype":"venue"
},
  "geometry": {"coordinates":[-68.522476,48.453255],"type":"Point"}
}