{
  "type": "Feature",
  "properties": {
    "addr:full":"Montreal QC H4P 2N5",
    "addr:postcode":"h4p 2n5",
    "iso:country":"CA",
    "sg:city":"Montreal",
    "sg:classifiers":[
        {
            "category":"Manufacturing",
            "subcategory":"Printing",
            "type":"Manufacturing & Wholesale Goods"
        }
    ],
    "sg:phone":"+1 514 343 5436",
    "sg:postcode":"H4P 2N5",
    "sg:province":"QC",
    "sg:tags":[
        "printer"
    ],
    "wof:name":"Imprimerie Phil Lieberman Ltee",
    "wof:placetype":"venue"
},
  "geometry": {"coordinates":[-73.648544,45.498058],"type":"Point"}
}