{
  "type": "Feature",
  "properties": {
    "addr:full":"Nanaimo BC V9R 5W6",
    "addr:postcode":"v9r 5w6",
    "iso:country":"CA",
    "sg:city":"Nanaimo",
    "sg:classifiers":[
        {
            "category":"Building & Trades",
            "subcategory":"Construction",
            "type":"Services"
        }
    ],
    "sg:phone":"+1 250 754 6388",
    "sg:postcode":"V9R 5W6",
    "sg:province":"BC",
    "sg:tags":[
        "general",
        "contractor"
    ],
    "wof:name":"Jdg Construction Management",
    "wof:placetype":"venue"
},
  "geometry": {"coordinates":[-123.95287322999999,49.1512184143],"type":"Point"}
}