{
  "type": "Feature",
  "properties": {
    "addr:full":"143 Harold Princeton BC V0X 1W0",
    "addr:housenumber":"143",
    "addr:postcode":"v0x 1w0",
    "addr:street":"Harold",
    "iso:country":"CA",
    "sg:address":"143 Harold",
    "sg:city":"Princeton",
    "sg:classifiers":[
        {
            "category":"Building & Trades",
            "subcategory":"Construction",
            "type":"Services"
        }
    ],
    "sg:phone":"+1 250 295 7106",
    "sg:postcode":"V0X 1W0",
    "sg:province":"BC",
    "sg:tags":[
        "tile",
        "resurfacing",
        "laying",
        "refinishing",
        "floor"
    ],
    "wof:name":"Cam's Tile",
    "wof:placetype":"venue"
},
  "geometry": {"coordinates":[-120.51121500000001,49.460777],"type":"Point"}
}