{
  "type": "Feature",
  "properties": {
    "iso:country":"CA",
    "sg:address":"8730 River Rd",
    "sg:city":"Delta",
    "sg:classifiers":[
        {
            "category":"Local Transit",
            "type":"Transportation"
        }
    ],
    "sg:phone":"+1 604 946 8866",
    "sg:postcode":"V4G 1B5",
    "sg:province":"BC",
    "sg:tags":[
        "bus",
        "line",
        "airport"
    ],
    "wof:name":"Vancouver Airporter",
    "wof:placetype":"venue"
},
  "geometry": {"coordinates":[-122.979057,49.153328],"type":"Point"}
}