{
  "type": "Feature",
  "properties": {
    "addr:full":"469 Guelph Line Burlington ON L7R 3L8",
    "addr:housenumber":"469",
    "addr:postcode":"l7r 3l8",
    "addr:street":"Guelph Line",
    "iso:country":"CA",
    "sg:address":"469 Guelph Line",
    "sg:city":"Burlington",
    "sg:classifiers":[
        {
            "category":"Health Services",
            "subcategory":"Optometrist",
            "type":"Services"
        }
    ],
    "sg:phone":"+1 905 333 3086",
    "sg:postcode":"L7R 3L8",
    "sg:province":"ON",
    "wof:name":"Jongepier, Julie OD",
    "wof:placetype":"venue"
},
  "geometry": {"coordinates":[-79.78573608400001,43.3387985229],"type":"Point"}
}