{
  "type": "Feature",
  "properties": {
    "addr:full":"Main Hwy Hermitage NL A0H 1S0",
    "addr:postcode":"a0h 1s0",
    "addr:street":"Main Hwy",
    "iso:country":"CA",
    "sg:address":"Main Hwy",
    "sg:city":"Hermitage",
    "sg:classifiers":[
        {
            "category":"Autos & Motor Vehicles",
            "subcategory":"Fuel & Gas Station",
            "type":"Retail Goods"
        }
    ],
    "sg:phone":"+1 709 883 2210",
    "sg:postcode":"A0H 1S0",
    "sg:province":"NL",
    "sg:tags":[
        "oil"
    ],
    "wof:name":"Bill's Convenience & Gas Bar",
    "wof:placetype":"venue"
},
  "geometry": {"coordinates":[-55.927914,47.557442],"type":"Point"}
}