{
  "type": "Feature",
  "properties": {
    "iso:country":"CA",
    "sg:address":"231 Rue Main",
    "sg:city":"Gatineau",
    "sg:classifiers":[
        {
            "category":"Wholesale",
            "subcategory":"Office Equipment",
            "type":"Manufacturing & Wholesale Goods"
        }
    ],
    "sg:phone":"+1 819 643 4721",
    "sg:postcode":"J8P 5J7",
    "sg:province":"QC",
    "sg:tags":[
        "accounting",
        "bookkeeping",
        "system"
    ],
    "wof:name":"Consultants Leclair",
    "wof:placetype":"venue"
},
  "geometry": {"coordinates":[-75.6514129639,45.4850311279],"type":"Point"}
}