{
  "type": "Feature",
  "properties": {
    "addr:full":"37 Mill St Almonte ON K0A 1A0",
    "addr:housenumber":"37",
    "addr:postcode":"k0a 1a0",
    "addr:street":"Mill St",
    "iso:country":"CA",
    "sg:address":"37 Mill St",
    "sg:city":"Almonte",
    "sg:classifiers":[
        {
            "category":"Autos & Motor Vehicles",
            "subcategory":"Fuel & Gas Station",
            "type":"Retail Goods"
        }
    ],
    "sg:phone":"+1 613 256 3264",
    "sg:postcode":"K0A 1A0",
    "sg:province":"ON",
    "sg:tags":[
        "oil"
    ],
    "wof:name":"Maynard's Ultrmar",
    "wof:placetype":"venue"
},
  "geometry": {"coordinates":[-76.19686900000001,45.225422],"type":"Point"}
}