{
  "type": "Feature",
  "properties": {
    "addr:full":"Port Lambton ON N0P 2B0",
    "addr:postcode":"n0p 2b0",
    "addr:street":"Port",
    "iso:country":"CA",
    "sg:city":"Port Lambton",
    "sg:classifiers":[
        {
            "category":"Home & Garden",
            "subcategory":"Garden Supply",
            "type":"Retail Goods"
        }
    ],
    "sg:phone":"+1 519 892 3070",
    "sg:postcode":"N0P 2B0",
    "sg:province":"ON",
    "sg:tags":[
        "engine",
        "lawn",
        "mower"
    ],
    "wof:name":"Parsons Small Engine Repair",
    "wof:placetype":"venue"
},
  "geometry": {"coordinates":[-82.48803700000001,42.696236],"type":"Point"}
}