{
  "type": "Feature",
  "properties": {
    "addr:full":"Etobicoke ON M9R 1H5",
    "addr:postcode":"m9r 1h5",
    "iso:country":"CA",
    "sg:city":"Etobicoke",
    "sg:classifiers":[
        {
            "category":"Shopping",
            "subcategory":"Florist",
            "type":"Retail Goods"
        }
    ],
    "sg:phone":"+1 416 241 9348",
    "sg:postcode":"M9R 1H5",
    "sg:province":"ON",
    "wof:name":"Flower & Gift Boutique",
    "wof:placetype":"venue"
},
  "geometry": {"coordinates":[-79.564919,43.683681],"type":"Point"}
}