{
  "type": "Feature",
  "properties": {
    "addr:full":"728 Bloor St W Toronto ON M6G 1L4",
    "addr:housenumber":"728",
    "addr:postcode":"m6g 1l4",
    "addr:street":"Bloor St W",
    "iso:country":"CA",
    "sg:address":"728 Bloor St W",
    "sg:city":"Toronto",
    "sg:classifiers":[
        {
            "category":"Shopping",
            "subcategory":"Pharmacy",
            "type":"Retail Goods"
        }
    ],
    "sg:phone":"+1 416 531 2426",
    "sg:postcode":"M6G 1L4",
    "sg:province":"ON",
    "wof:name":"Bloor Park Pharmacy",
    "wof:placetype":"venue"
},
  "geometry": {"coordinates":[-79.41808319090001,43.6637763977],"type":"Point"}
}