{
  "type": "Feature",
  "properties": {
    "addr:full":"Charlesbourg QC G1G 4A2",
    "addr:postcode":"g1g 4a2",
    "iso:country":"CA",
    "sg:city":"Charlesbourg",
    "sg:classifiers":[
        {
            "category":"Health Services",
            "subcategory":"Doctor",
            "type":"Services"
        }
    ],
    "sg:phone":"+1 418 628 9074",
    "sg:postcode":"G1G 4A2",
    "sg:province":"QC",
    "sg:tags":[
        "clinic"
    ],
    "wof:name":"Clinique Medicale Du Jardin",
    "wof:placetype":"venue"
},
  "geometry": {"coordinates":[-71.29143500000001,46.885315],"type":"Point"}
}