{
  "type": "Feature",
  "properties": {
    "addr:full":"153 Preston St Ottawa ON K1R 7P6",
    "addr:housenumber":"153",
    "addr:postcode":"k1r 7p6",
    "addr:street":"Preston St",
    "iso:country":"CA",
    "sg:address":"153 Preston St",
    "sg:city":"Ottawa",
    "sg:classifiers":[
        {
            "category":"Home & Garden",
            "subcategory":"Building Materials",
            "type":"Retail Goods"
        }
    ],
    "sg:phone":"+1 613 725 1151",
    "sg:postcode":"K1R 7P6",
    "sg:province":"ON",
    "sg:tags":[
        "glass",
        "window",
        "plate"
    ],
    "wof:name":"Preston & Lieff Glass & Door",
    "wof:placetype":"venue"
},
  "geometry": {"coordinates":[-75.713409,45.407261],"type":"Point"}
}