{
  "type": "Feature",
  "properties": {
    "iso:country":"CA",
    "sg:address":"6313 35 St SE",
    "sg:city":"Calgary",
    "sg:classifiers":[
        {
            "category":"Manufacturing",
            "subcategory":"Metals",
            "type":"Manufacturing & Wholesale Goods"
        }
    ],
    "sg:phone":"+1 403 279 2633",
    "sg:postcode":"T2C 1N1",
    "sg:province":"AB",
    "sg:tags":[
        "steel"
    ],
    "wof:name":"Three Star Steel Ltd",
    "wof:placetype":"venue"
},
  "geometry": {"coordinates":[-113.984596252,50.9998512268],"type":"Point"}
}