{
  "type": "Feature",
  "properties": {
    "addr:full":"8 Rue Sherbrooke E Montreal QC H2X 1C2",
    "addr:housenumber":"8",
    "addr:postcode":"h2x 1c2",
    "addr:street":"Rue Sherbrooke E",
    "iso:country":"CA",
    "sg:address":"8 Rue Sherbrooke E",
    "sg:city":"Montreal",
    "sg:classifiers":[
        {
            "category":"Shopping",
            "type":"Retail Goods"
        }
    ],
    "sg:phone":"+1 514 849 8609",
    "sg:postcode":"H2X 1C2",
    "sg:province":"QC",
    "sg:tags":[
        "coin",
        "dealer",
        "supply"
    ],
    "wof:name":"Roi DE LA Monnaie",
    "wof:placetype":"venue"
},
  "geometry": {"coordinates":[-73.569267,45.512615],"type":"Point"}
}