{
  "type": "Feature",
  "properties": {
    "addr:full":"North Bay ON P1B 8J1",
    "addr:postcode":"p1b 8j1",
    "iso:country":"CA",
    "sg:city":"North Bay",
    "sg:classifiers":[
        {
            "category":"Utilities",
            "subcategory":"Fuel Oil & Lpg",
            "type":"Services"
        }
    ],
    "sg:phone":"+1 705 476 2334",
    "sg:postcode":"P1B 8J1",
    "sg:province":"ON",
    "sg:tags":[
        "propane",
        "gas"
    ],
    "wof:name":"Moore Propane Ltd",
    "wof:placetype":"venue"
},
  "geometry": {"coordinates":[-79.405006,46.268669],"type":"Point"}
}