{
  "type": "Feature",
  "properties": {
    "addr:full":"Bowen Island BC V0N 1G0",
    "addr:postcode":"v0n 1g0",
    "iso:country":"CA",
    "sg:city":"Bowen Island",
    "sg:classifiers":[
        {
            "category":"Retail",
            "subcategory":"Auto Repair",
            "type":"Services"
        }
    ],
    "sg:phone":"+1 604 947 2838",
    "sg:postcode":"V0N 1G0",
    "sg:province":"BC",
    "sg:tags":[
        "repairing",
        "automobile"
    ],
    "wof:name":"Brs Water Svc",
    "wof:placetype":"venue"
},
  "geometry": {"coordinates":[-123.334785,49.385891],"type":"Point"}
}