{
  "type": "Feature",
  "properties": {
    "addr:full":"Hinton AB T7V 1S8",
    "addr:postcode":"t7v 1s8",
    "iso:country":"CA",
    "sg:city":"Hinton",
    "sg:classifiers":[
        {
            "category":"Wholesale",
            "subcategory":"Machinery & Supplies",
            "type":"Manufacturing & Wholesale Goods"
        }
    ],
    "sg:phone":"+1 780 865 7976",
    "sg:postcode":"T7V 1S8",
    "sg:province":"AB",
    "sg:tags":[
        "bearing"
    ],
    "wof:name":"B C Bearing Engineers Ltd",
    "wof:placetype":"venue"
},
  "geometry": {"coordinates":[-117.60674299999999,53.394718],"type":"Point"}
}