{
  "type": "Feature",
  "properties": {
    "addr:full":"270 Rte 109 S Saint-Felix-DE-Dalquier QC J0Y 1G0",
    "addr:housenumber":"270",
    "addr:postcode":"j0y 1g0",
    "addr:street":"Rte 109 S Saint-Felix-De-Dalquier",
    "iso:country":"CA",
    "sg:address":"270 Rte 109 S",
    "sg:city":"Saint-Felix-DE-Dalquier",
    "sg:classifiers":[
        {
            "category":"Retail",
            "subcategory":"Auto Repair",
            "type":"Services"
        }
    ],
    "sg:phone":"+1 819 732 4858",
    "sg:postcode":"J0Y 1G0",
    "sg:province":"QC",
    "sg:tags":[
        "repairing",
        "automobile"
    ],
    "wof:name":"Garage Ti-L'Or Enr",
    "wof:placetype":"venue"
},
  "geometry": {"coordinates":[-78.1143112183,48.650177002],"type":"Point"}
}