{
  "type": "Feature",
  "properties": {
    "addr:full":"Courtenay BC V9N 1J6",
    "addr:postcode":"v9n 1j6",
    "iso:country":"CA",
    "sg:city":"Courtenay",
    "sg:classifiers":[
        {
            "category":"Shopping",
            "subcategory":"Books",
            "type":"Retail Goods"
        }
    ],
    "sg:phone":"+1 250 334 2556",
    "sg:postcode":"V9N 1J6",
    "sg:province":"BC",
    "sg:tags":[
        "dealer"
    ],
    "wof:name":"Jacob's Well",
    "wof:placetype":"venue"
},
  "geometry": {"coordinates":[-124.998131,49.69099],"type":"Point"}
}