{
  "type": "Feature",
  "properties": {
    "addr:full":"75 Carl Hall Rd North York ON M3K 2B9",
    "addr:housenumber":"75",
    "addr:postcode":"m3k 2b9",
    "addr:street":"Carl Hall Rd",
    "iso:country":"CA",
    "sg:address":"75 Carl Hall Rd",
    "sg:city":"North York",
    "sg:classifiers":[
        {
            "category":"Arena",
            "subcategory":"Sports Club",
            "type":"Entertainment"
        }
    ],
    "sg:phone":"+1 416 638 8478",
    "sg:postcode":"M3K 2B9",
    "sg:province":"ON",
    "sg:tags":[
        "soccer"
    ],
    "wof:name":"Hangar",
    "wof:placetype":"venue"
},
  "geometry": {"coordinates":[-79.41255200000001,43.767914],"type":"Point"}
}