{
  "type": "Feature",
  "properties": {
    "addr:full":"357 Ongman Rd Prince George BC V2K 4K9",
    "addr:housenumber":"357",
    "addr:postcode":"v2k 4k9",
    "addr:street":"Ongman Rd",
    "iso:country":"CA",
    "sg:address":"357 Ongman Rd",
    "sg:city":"Prince George",
    "sg:classifiers":[
        {
            "category":"Wholesale",
            "subcategory":"Medical Equipment & Supplies",
            "type":"Manufacturing & Wholesale Goods"
        }
    ],
    "sg:phone":"+1 250 563 4058",
    "sg:postcode":"V2K 4K9",
    "sg:province":"BC",
    "sg:tags":[
        "x",
        "apparatus"
    ],
    "wof:name":"F/R Imaging Ltd",
    "wof:placetype":"venue"
},
  "geometry": {"coordinates":[-122.77113300000001,53.928699],"type":"Point"}
}