{
  "type": "Feature",
  "properties": {
    "addr:full":"24 Macnaughton Rd East York ON M4G 3H4",
    "addr:housenumber":"24",
    "addr:postcode":"m4g 3h4",
    "addr:street":"Macnaughton Rd",
    "iso:country":"CA",
    "sg:address":"24 Macnaughton Rd",
    "sg:city":"East York",
    "sg:classifiers":[
        {
            "category":"Communications",
            "subcategory":"Film & Video Production",
            "type":"Services"
        }
    ],
    "sg:phone":"+1 416 487 5036",
    "sg:postcode":"M4G 3H4",
    "sg:province":"ON",
    "sg:tags":[
        "taping"
    ],
    "wof:name":"Newsreach Canada Inc",
    "wof:placetype":"venue"
},
  "geometry": {"coordinates":[-79.372749,43.705616],"type":"Point"}
}