{
  "type": "Feature",
  "properties": {
    "addr:full":"15125 100 Ave Surrey BC V3R 9P4",
    "addr:housenumber":"15125",
    "addr:postcode":"v3r 9p4",
    "addr:street":"100 Ave",
    "iso:country":"CA",
    "sg:address":"15125 100 Ave",
    "sg:city":"Surrey",
    "sg:classifiers":[
        {
            "category":"Restaurant",
            "type":"Food & Drink"
        }
    ],
    "sg:phone":"+1 604 581 3600",
    "sg:postcode":"V3R 9P4",
    "sg:province":"BC",
    "wof:name":"Boston Pizza",
    "wof:placetype":"venue"
},
  "geometry": {"coordinates":[-122.803055,49.184418],"type":"Point"}
}