{
  "type": "Feature",
  "properties": {
    "addr:full":"100 Rte 202 Huntingdon QC J0S 1H0",
    "addr:housenumber":"100",
    "addr:postcode":"j0s 1h0",
    "addr:street":"Rte 202",
    "iso:country":"CA",
    "sg:address":"100 Rte 202",
    "sg:city":"Huntingdon",
    "sg:classifiers":[
        {
            "category":"Wholesale",
            "subcategory":"Machinery & Supplies",
            "type":"Manufacturing & Wholesale Goods"
        }
    ],
    "sg:phone":"+1 450 264 5198",
    "sg:postcode":"J0S 1H0",
    "sg:province":"QC",
    "sg:tags":[
        "farm",
        "equipment"
    ],
    "wof:name":"Lazure & Riendeau Equipements",
    "wof:placetype":"venue"
},
  "geometry": {"coordinates":[-74.1672134399,45.0834693909],"type":"Point"}
}