{
  "type": "Feature",
  "properties": {
    "addr:full":"3791 Paden Rd RR 2 North Gower ON K0A 2T0",
    "addr:housenumber":"3791",
    "addr:postcode":"k0a 2t0",
    "addr:street":"Paden Rd;2",
    "iso:country":"CA",
    "sg:address":"3791 Paden Rd RR 2",
    "sg:city":"North Gower",
    "sg:classifiers":[
        {
            "category":"Arts & Performance",
            "subcategory":"Theater",
            "type":"Entertainment"
        }
    ],
    "sg:phone":"+1 613 258 7870",
    "sg:postcode":"K0A 2T0",
    "sg:province":"ON",
    "sg:tags":[
        "live",
        "music"
    ],
    "wof:name":"Super Sound Productions",
    "wof:placetype":"venue"
},
  "geometry": {"coordinates":[-75.7071151733,45.1352081299],"type":"Point"}
}