{
  "type": "Feature",
  "properties": {
    "addr:full":"1 Rue Sylvan Drummondville QC J2C 2S8",
    "addr:housenumber":"1",
    "addr:postcode":"j2c 2s8",
    "addr:street":"Rue Sylvan",
    "iso:country":"CA",
    "sg:address":"1 Rue Sylvan",
    "sg:city":"Drummondville",
    "sg:classifiers":[
        {
            "category":"Organizations",
            "subcategory":"Labor Organization",
            "type":"Services"
        }
    ],
    "sg:phone":"+1 819 477 8541",
    "sg:postcode":"J2C 2S8",
    "sg:province":"QC",
    "wof:name":"Syndicat Des Employes-Sylvania",
    "wof:placetype":"venue"
},
  "geometry": {"coordinates":[-72.4980392456,45.87525177],"type":"Point"}
}