{
  "type": "Feature",
  "properties": {
    "addr:full":"80 Cowan Ave St. John's NL A1E 3P2",
    "addr:housenumber":"80",
    "addr:postcode":"a1e 3p2",
    "addr:street":"Cowan Ave",
    "iso:country":"CA",
    "sg:address":"80 Cowan Ave",
    "sg:city":"St. John's",
    "sg:classifiers":[
        {
            "category":"Professional",
            "subcategory":"Business Services",
            "type":"Services"
        }
    ],
    "sg:phone":"+1 709 364 3931",
    "sg:postcode":"A1E 3P2",
    "sg:province":"NL",
    "sg:tags":[
        "screen",
        "printing",
        "embroidery"
    ],
    "wof:name":"Crown Five Advertising Ltd",
    "wof:placetype":"venue"
},
  "geometry": {"coordinates":[-52.760231,47.53194],"type":"Point"}
}