{
  "type": "Feature",
  "properties": {
    "iso:country":"CA",
    "sg:address":"3333 Boul DE LA Cote-Vertu # 210",
    "sg:city":"Saint-Laurent",
    "sg:classifiers":[
        {
            "category":"Wholesale",
            "subcategory":"Electrical",
            "type":"Manufacturing & Wholesale Goods"
        }
    ],
    "sg:phone":"+1 514 334 2446",
    "sg:postcode":"H4R 2N1",
    "sg:province":"QC",
    "sg:tags":[
        "equipment",
        "electronic",
        "supply"
    ],
    "wof:name":"Zilex Electronics Inc",
    "wof:placetype":"venue"
},
  "geometry": {"coordinates":[-73.70565,45.49633],"type":"Point"}
}