{
  "type": "Feature",
  "properties": {
    "addr:full":"153 Amber Trail Winnipeg MB R2P 2S4",
    "addr:housenumber":"153",
    "addr:postcode":"r2p 2s4",
    "addr:street":"Amber Trail",
    "iso:country":"CA",
    "sg:address":"153 Amber Trail",
    "sg:city":"Winnipeg",
    "sg:classifiers":[
        {
            "category":"Building & Trades",
            "subcategory":"Construction",
            "type":"Services"
        }
    ],
    "sg:phone":"+1 204 697 2001",
    "sg:postcode":"R2P 2S4",
    "sg:province":"MB",
    "sg:tags":[
        "concrete",
        "contractor"
    ],
    "wof:name":"D'Ottavio Construction",
    "wof:placetype":"venue"
},
  "geometry": {"coordinates":[-97.1656951904,49.9617652893],"type":"Point"}
}