{
  "type": "Feature",
  "properties": {
    "addr:full":"12245 Boul Laurentien Montreal QC H4K 1N4",
    "addr:housenumber":"12245",
    "addr:postcode":"h4k 1n4",
    "addr:street":"Boul Laurentien",
    "iso:country":"CA",
    "sg:address":"12245 Boul Laurentien",
    "sg:city":"Montreal",
    "sg:classifiers":[
        {
            "category":"Food & Beverages",
            "subcategory":"Groceries & Convenience Stores",
            "type":"Retail Goods"
        }
    ],
    "sg:phone":"+1 514 337 8141",
    "sg:postcode":"H4K 1N4",
    "sg:province":"QC",
    "sg:tags":[
        "grocer"
    ],
    "wof:name":"Couche-Tard",
    "wof:placetype":"venue"
},
  "geometry": {"coordinates":[-73.721504,45.528751],"type":"Point"}
}