{
  "type": "Feature",
  "properties": {
    "iso:country":"CA",
    "sg:address":"582 Laural Dr",
    "sg:city":"Burlington",
    "sg:classifiers":[
        {
            "category":"Health Services",
            "subcategory":"Clinic",
            "type":"Services"
        }
    ],
    "sg:phone":"+1 905 631 1440",
    "sg:postcode":"L7L 5C8",
    "sg:province":"ON",
    "sg:tags":[
        "equipment",
        "therapy",
        "oxygen"
    ],
    "wof:name":"Canadian Respiratory Hlthcr",
    "wof:placetype":"venue"
},
  "geometry": {"coordinates":[-79.76593017579999,43.3652305603],"type":"Point"}
}