{
  "type": "Feature",
  "properties": {
    "addr:full":"Victoria BC V8V 1B1",
    "addr:postcode":"v8v 1b1",
    "iso:country":"CA",
    "sg:city":"Victoria",
    "sg:classifiers":[
        {
            "category":"Real Estate",
            "subcategory":"Real Estate Operator",
            "type":"Services"
        }
    ],
    "sg:phone":"+1 250 386 9292",
    "sg:postcode":"V8V 1B1",
    "sg:province":"BC",
    "sg:tags":[
        "apartment"
    ],
    "wof:name":"Seaview Towers Apartments",
    "wof:placetype":"venue"
},
  "geometry": {"coordinates":[-123.378044,48.412319],"type":"Point"}
}