{
  "type": "Feature",
  "properties": {
    "addr:full":"11 Ch Maxime Lac-Cayamant QC J0X 1Y0",
    "addr:housenumber":"11",
    "addr:postcode":"j0x 1y0",
    "addr:street":"Ch Maxime Lac-Cayamant",
    "iso:country":"CA",
    "sg:address":"11 Ch Maxime",
    "sg:city":"Lac-Cayamant",
    "sg:classifiers":[
        {
            "category":"Professional",
            "subcategory":"Secretarial Services",
            "type":"Services"
        }
    ],
    "sg:phone":"+1 819 463 1717",
    "sg:postcode":"J0X 1Y0",
    "sg:province":"QC",
    "sg:tags":[
        "processing",
        "word"
    ],
    "wof:name":"Enterprises Rllh",
    "wof:placetype":"venue"
},
  "geometry": {"coordinates":[-76.2099533081,46.1760482788],"type":"Point"}
}