{
  "type": "Feature",
  "properties": {
    "addr:full":"6 Lyons Ave Brantford ON N3R 4P7",
    "addr:housenumber":"6",
    "addr:postcode":"n3r 4p7",
    "addr:street":"Lyons Ave",
    "iso:country":"CA",
    "sg:address":"6 Lyons Ave",
    "sg:city":"Brantford",
    "sg:classifiers":[
        {
            "category":"Building & Trades",
            "subcategory":"Construction",
            "type":"Services"
        }
    ],
    "sg:phone":"+1 519 759 5431",
    "sg:postcode":"N3R 4P7",
    "sg:province":"ON",
    "sg:tags":[
        "general",
        "contractor"
    ],
    "wof:name":"Belko Contracting Inc",
    "wof:placetype":"venue"
},
  "geometry": {"coordinates":[-80.2794418335,43.1512985229],"type":"Point"}
}