{
  "type": "Feature",
  "properties": {
    "addr:full":"31 Riverview Dr Bridgewater NS B4V 3A1",
    "addr:housenumber":"31",
    "addr:postcode":"b4v 3a1",
    "addr:street":"Riverview Dr",
    "iso:country":"CA",
    "sg:address":"31 Riverview Dr",
    "sg:city":"Bridgewater",
    "sg:classifiers":[
        {
            "category":"Retail",
            "subcategory":"Auto Repair",
            "type":"Services"
        }
    ],
    "sg:phone":"+1 902 543 5369",
    "sg:postcode":"B4V 3A1",
    "sg:province":"NS",
    "sg:tags":[
        "repairing",
        "automobile"
    ],
    "wof:name":"Riverview Automotive",
    "wof:placetype":"venue"
},
  "geometry": {"coordinates":[-64.550949,44.402363],"type":"Point"}
}