{
  "type": "Feature",
  "properties": {
    "addr:full":"2100 Rue Bagot LA Baie QC G7B 3Z3",
    "addr:housenumber":"2100",
    "addr:postcode":"g7b 3z3",
    "addr:street":"Rue Bagot",
    "iso:country":"CA",
    "sg:address":"2100 Rue Bagot",
    "sg:city":"LA Baie",
    "sg:classifiers":[
        {
            "category":"Manufacturing",
            "subcategory":"Tools & Machinery",
            "type":"Manufacturing & Wholesale Goods"
        }
    ],
    "sg:phone":"+1 418 544 7789",
    "sg:postcode":"G7B 3Z3",
    "sg:province":"QC",
    "sg:tags":[
        "optometrist",
        "optical"
    ],
    "wof:name":"Optimum Clinique Visuelle",
    "wof:placetype":"venue"
},
  "geometry": {"coordinates":[-70.894867,48.335781],"type":"Point"}
}