{
  "type": "Feature",
  "properties": {
    "addr:full":"Courtenay BC V9N 2N7",
    "addr:postcode":"v9n 2n7",
    "iso:country":"CA",
    "sg:city":"Courtenay",
    "sg:classifiers":[
        {
            "category":"Government",
            "subcategory":"Office",
            "type":"Public Place"
        }
    ],
    "sg:phone":"+1 250 898 2211",
    "sg:postcode":"V9N 2N7",
    "sg:province":"BC",
    "wof:name":"B C Alcohol & Drug Svc",
    "wof:placetype":"venue"
},
  "geometry": {"coordinates":[-124.998283386,49.6881065369],"type":"Point"}
}