{
  "type": "Feature",
  "properties": {
    "iso:country":"CA",
    "sg:address":"3906 Boul Wilfrid-Hamel",
    "sg:city":"Quebec",
    "sg:classifiers":[
        {
            "category":"Shopping",
            "subcategory":"Used Merchandise",
            "type":"Retail Goods"
        }
    ],
    "sg:phone":"+1 418 877 3663",
    "sg:postcode":"G1P 2J2",
    "sg:province":"QC",
    "sg:tags":[
        "pawnbroker"
    ],
    "wof:name":"Instant Comptant",
    "wof:placetype":"venue"
},
  "geometry": {"coordinates":[-71.3148651123,46.8063735962],"type":"Point"}
}