{
  "type": "Feature",
  "properties": {
    "addr:full":"4838 49 St Camrose AB T4V 1N2",
    "addr:housenumber":"4838",
    "addr:postcode":"t4v 1n2",
    "addr:street":"49 St",
    "iso:country":"CA",
    "sg:address":"4838 49 St",
    "sg:city":"Camrose",
    "sg:classifiers":[
        {
            "category":"Banks & Credit Unions",
            "subcategory":"Investment Brokerage",
            "type":"Services"
        }
    ],
    "sg:phone":"+1 780 672 6399",
    "sg:postcode":"T4V 1N2",
    "sg:province":"AB",
    "sg:tags":[
        "consultant",
        "planning",
        "financial"
    ],
    "wof:name":"Kroeger Financial Svc",
    "wof:placetype":"venue"
},
  "geometry": {"coordinates":[-112.824203,53.019539],"type":"Point"}
}