{
  "type": "Feature",
  "properties": {
    "iso:country":"CA",
    "sg:address":"7350 Boul Taschereau",
    "sg:city":"Brossard",
    "sg:classifiers":[
        {
            "category":"Shopping",
            "subcategory":"Clothing, Apparel, & Fashions",
            "type":"Retail Goods"
        }
    ],
    "sg:phone":"+1 450 672 0795",
    "sg:postcode":"J4W 1M9",
    "sg:province":"QC",
    "sg:tags":[
        "dancing",
        "supply"
    ],
    "wof:name":"Soulier DE Satin",
    "wof:placetype":"venue"
},
  "geometry": {"coordinates":[-73.465492,45.459793],"type":"Point"}
}