{
  "type": "Feature",
  "properties": {
    "addr:full":"150 North Queen St Etobicoke ON M9C 1A8",
    "addr:housenumber":"150",
    "addr:postcode":"m9c 1a8",
    "addr:street":"North Queen St",
    "iso:country":"CA",
    "sg:address":"150 North Queen St",
    "sg:city":"Etobicoke",
    "sg:classifiers":[
        {
            "category":"Wholesale",
            "subcategory":"Machinery & Supplies",
            "type":"Manufacturing & Wholesale Goods"
        }
    ],
    "sg:phone":"+1 416 621 9921",
    "sg:postcode":"M9C 1A8",
    "sg:province":"ON",
    "sg:tags":[
        "engine"
    ],
    "wof:name":"Cummins Ontario Inc",
    "wof:placetype":"venue"
},
  "geometry": {"coordinates":[-79.55429100000001,43.619465],"type":"Point"}
}