{
  "type": "Feature",
  "properties": {
    "addr:full":"1379 Hammond St North Bay ON P1B 2J2",
    "addr:housenumber":"1379",
    "addr:postcode":"p1b 2j2",
    "addr:street":"Hammond St",
    "iso:country":"CA",
    "sg:address":"1379 Hammond St",
    "sg:city":"North Bay",
    "sg:classifiers":[
        {
            "category":"Building & Trades",
            "subcategory":"Construction",
            "type":"Services"
        }
    ],
    "sg:phone":"+1 705 495 1622",
    "sg:postcode":"P1B 2J2",
    "sg:province":"ON",
    "sg:tags":[
        "material",
        "dealer",
        "floor"
    ],
    "wof:name":"North Tech Stone & Ceramic",
    "wof:placetype":"venue"
},
  "geometry": {"coordinates":[-79.445663,46.311474],"type":"Point"}
}