{
  "type": "Feature",
  "properties": {
    "addr:full":"64 Prince Andrew Pl North York ON M3C 2H4",
    "addr:housenumber":"64",
    "addr:postcode":"m3c 2h4",
    "addr:street":"Prince Andrew Pl",
    "iso:country":"CA",
    "sg:address":"64 Prince Andrew Pl",
    "sg:city":"North York",
    "sg:classifiers":[
        {
            "category":"Professional",
            "subcategory":"Engineering",
            "type":"Services"
        }
    ],
    "sg:phone":"+1 416 443 8049",
    "sg:postcode":"M3C 2H4",
    "sg:province":"ON",
    "sg:tags":[
        "engineer"
    ],
    "wof:name":"Invodane Engineering Ltd",
    "wof:placetype":"venue"
},
  "geometry": {"coordinates":[-79.346062,43.726627],"type":"Point"}
}