{
  "type": "Feature",
  "properties": {
    "addr:full":"7510 Place Tremblay Brossard QC J4W 2Y5",
    "addr:housenumber":"7510",
    "addr:postcode":"j4w 2y5",
    "addr:street":"Place Tremblay",
    "iso:country":"CA",
    "sg:address":"7510 Place Tremblay",
    "sg:city":"Brossard",
    "sg:classifiers":[
        {
            "category":"Professional",
            "subcategory":"Computer Services",
            "type":"Services"
        }
    ],
    "sg:phone":"+1 450 672 1678",
    "sg:postcode":"J4W 2Y5",
    "sg:province":"QC",
    "sg:tags":[
        "repair"
    ],
    "wof:name":"Actiontech Groupe-Bureautique",
    "wof:placetype":"venue"
},
  "geometry": {"coordinates":[-73.480598,45.461086],"type":"Point"}
}