{
  "type": "Feature",
  "properties": {
    "addr:full":"Nanaimo BC V9T 6J4",
    "addr:postcode":"v9t 6j4",
    "iso:country":"CA",
    "sg:city":"Nanaimo",
    "sg:classifiers":[
        {
            "category":"Shopping",
            "subcategory":"Jewelry",
            "type":"Retail Goods"
        }
    ],
    "sg:phone":"+1 250 758 9383",
    "sg:postcode":"V9T 6J4",
    "sg:province":"BC",
    "sg:tags":[
        "jeweler"
    ],
    "wof:name":"Imhoff Jewellers Ltd",
    "wof:placetype":"venue"
},
  "geometry": {"coordinates":[-124.035522461,49.2257919312],"type":"Point"}
}