{
  "type": "Feature",
  "properties": {
    "addr:full":"3249 City Road 42 Creemore ON L0M 1G0",
    "addr:housenumber":"3249",
    "addr:postcode":"l0m 1g0",
    "addr:street":"City Road 42",
    "iso:country":"CA",
    "sg:address":"3249 City Road 42",
    "sg:city":"Creemore",
    "sg:classifiers":[
        {
            "category":"Shopping",
            "subcategory":"Used Merchandise",
            "type":"Retail Goods"
        }
    ],
    "sg:phone":"+1 705 466 2207",
    "sg:postcode":"L0M 1G0",
    "sg:province":"ON",
    "sg:tags":[
        "auctioneer"
    ],
    "wof:name":"John Simpson Auctioneer",
    "wof:placetype":"venue"
},
  "geometry": {"coordinates":[-80.108566,44.330444],"type":"Point"}
}