{
  "type": "Feature",
  "properties": {
    "addr:full":"Cambridge ON N1R 6V1",
    "addr:postcode":"n1r 6v1",
    "iso:country":"CA",
    "sg:city":"Cambridge",
    "sg:classifiers":[
        {
            "category":"Retail",
            "subcategory":"Auto Repair",
            "type":"Services"
        }
    ],
    "sg:phone":"+1 519 623 6600",
    "sg:postcode":"N1R 6V1",
    "sg:province":"ON",
    "sg:tags":[
        "body",
        "automobile",
        "painting"
    ],
    "wof:name":"Wayne Shouldice Collision Ltd",
    "wof:placetype":"venue"
},
  "geometry": {"coordinates":[-80.310478,43.404644],"type":"Point"}
}