{
  "type": "Feature",
  "properties": {
    "addr:full":"178 Sophia St Peterborough ON K9H 1E5",
    "addr:housenumber":"178",
    "addr:postcode":"k9h 1e5",
    "addr:street":"Sophia St",
    "iso:country":"CA",
    "sg:address":"178 Sophia St",
    "sg:city":"Peterborough",
    "sg:classifiers":[
        {
            "category":"Organizations",
            "subcategory":"Labor Organization",
            "type":"Services"
        }
    ],
    "sg:phone":"+1 705 745 6428",
    "sg:postcode":"K9H 1E5",
    "sg:province":"ON",
    "wof:name":"Independent Union of Precision",
    "wof:placetype":"venue"
},
  "geometry": {"coordinates":[-78.305283,44.304043],"type":"Point"}
}