{
  "type": "Feature",
  "properties": {
    "addr:full":"406 Main St Manning AB T0H 2M0",
    "addr:housenumber":"406",
    "addr:postcode":"t0h 2m0",
    "addr:street":"Main St",
    "iso:country":"CA",
    "sg:address":"406 Main St",
    "sg:city":"Manning",
    "sg:classifiers":[
        {
            "category":"Building & Trades",
            "subcategory":"Plumbing",
            "type":"Services"
        }
    ],
    "sg:phone":"+1 780 836 3462",
    "sg:postcode":"T0H 2M0",
    "sg:province":"AB",
    "sg:tags":[
        "contractor"
    ],
    "wof:name":"Vandeck Plumbing & Heating",
    "wof:placetype":"venue"
},
  "geometry": {"coordinates":[-117.630341,56.922119],"type":"Point"}
}