{
  "type": "Feature",
  "properties": {
    "addr:full":"186 Gore St E Perth ON K7H 1K3",
    "addr:housenumber":"186",
    "addr:postcode":"k7h 1k3",
    "addr:street":"Gore St E",
    "iso:country":"CA",
    "sg:address":"186 Gore St E",
    "sg:city":"Perth",
    "sg:classifiers":[
        {
            "category":"Recreation",
            "type":"Entertainment"
        }
    ],
    "sg:phone":"+1 613 267 7895",
    "sg:postcode":"K7H 1K3",
    "sg:province":"ON",
    "sg:tags":[
        "hall",
        "auditorium"
    ],
    "wof:name":"Farrell Hall",
    "wof:placetype":"venue"
},
  "geometry": {"coordinates":[-76.243568,44.894779],"type":"Point"}
}