{
  "type": "Feature",
  "properties": {
    "addr:full":"1147 Boul Vachon N Sainte-Marie QC G6E 1M9",
    "addr:housenumber":"1147",
    "addr:postcode":"g6e 1m9",
    "addr:street":"Boul Vachon N",
    "iso:country":"CA",
    "sg:address":"1147 Boul Vachon N",
    "sg:city":"Sainte-Marie",
    "sg:classifiers":[
        {
            "category":"Manufacturing",
            "subcategory":"Printing",
            "type":"Manufacturing & Wholesale Goods"
        }
    ],
    "sg:phone":"+1 418 387 8000",
    "sg:postcode":"G6E 1M9",
    "sg:province":"QC",
    "sg:tags":[
        "newspaper"
    ],
    "wof:name":"Beauce Media Inc",
    "wof:placetype":"venue"
},
  "geometry": {"coordinates":[-71.0386886597,46.4569091797],"type":"Point"}
}