{
  "type": "Feature",
  "properties": {
    "addr:full":"5395 Boul Henri-Bourassa E Montreal-Nord QC H1G 2T1",
    "addr:housenumber":"5395",
    "addr:postcode":"h1g 2t1",
    "addr:street":"Boul Henri-Bourassa E",
    "iso:country":"CA",
    "sg:address":"5395 Boul Henri-Bourassa E",
    "sg:city":"Montreal-Nord",
    "sg:classifiers":[
        {
            "category":"Food & Beverages",
            "subcategory":"Groceries & Convenience Stores",
            "type":"Retail Goods"
        }
    ],
    "sg:phone":"+1 514 852 0585",
    "sg:postcode":"H1G 2T1",
    "sg:province":"QC",
    "wof:name":"Couche-Tard",
    "wof:placetype":"venue"
},
  "geometry": {"coordinates":[-73.624664,45.605324],"type":"Point"}
}