{
  "type": "Feature",
  "properties": {
    "addr:full":"22366 Dewdney Trunk Rd Maple Ridge BC V2X 3J2",
    "addr:housenumber":"22366",
    "addr:postcode":"v2x 3j2",
    "addr:street":"Dewdney Trunk Rd",
    "iso:country":"CA",
    "sg:address":"22366 Dewdney Trunk Rd",
    "sg:city":"Maple Ridge",
    "sg:classifiers":[
        {
            "category":"Personal",
            "subcategory":"Beauty Salon",
            "type":"Services"
        }
    ],
    "sg:phone":"+1 604 463 1155",
    "sg:postcode":"V2X 3J2",
    "sg:province":"BC",
    "wof:name":"Time in Eden Spa & Hair Studio",
    "wof:placetype":"venue"
},
  "geometry": {"coordinates":[-122.602546692,49.2203674316],"type":"Point"}
}