{
  "type": "Feature",
  "properties": {
    "addr:full":"4513 Maple St Bruce AB T0B 0R0",
    "addr:housenumber":"4513",
    "addr:postcode":"t0b 0r0",
    "addr:street":"Maple St",
    "iso:country":"CA",
    "sg:address":"4513 Maple St",
    "sg:city":"Bruce",
    "sg:classifiers":[
        {
            "category":"Organizations",
            "subcategory":"Religious Organization",
            "type":"Services"
        }
    ],
    "sg:phone":"+1 403 632 3207",
    "sg:postcode":"T0B 0R0",
    "sg:province":"AB",
    "sg:tags":[
        "church"
    ],
    "wof:name":"Immanuel Lutheran Church",
    "wof:placetype":"venue"
},
  "geometry": {"coordinates":[-112.039162,53.172821],"type":"Point"}
}