{
  "type": "Feature",
  "properties": {
    "addr:full":"Saint-Clet QC J0P 1S0",
    "addr:postcode":"j0p 1s0",
    "iso:country":"CA",
    "sg:city":"Saint-Clet",
    "sg:classifiers":[
        {
            "category":"Autos & Motor Vehicles",
            "subcategory":"Auto Supplies",
            "type":"Retail Goods"
        }
    ],
    "sg:phone":"+1 450 456 3226",
    "sg:postcode":"J0P 1S0",
    "sg:province":"QC",
    "sg:tags":[
        "automobile",
        "parts"
    ],
    "wof:name":"Pieces D'Auto Yvan Inc",
    "wof:placetype":"venue"
},
  "geometry": {"coordinates":[-74.21942138670001,45.3549346924],"type":"Point"}
}