{
  "type": "Feature",
  "properties": {
    "addr:full":"6679 Woodworth Rd Port Burwell ON N0J 1T0",
    "addr:housenumber":"6679",
    "addr:postcode":"n0j 1t0",
    "addr:street":"Woodworth Rd",
    "iso:country":"CA",
    "sg:address":"6679 Woodworth Rd",
    "sg:city":"Port Burwell",
    "sg:classifiers":[
        {
            "category":"Travel",
            "subcategory":"Campground",
            "type":"Entertainment"
        }
    ],
    "sg:phone":"+1 519 874 4150",
    "sg:postcode":"N0J 1T0",
    "sg:province":"ON",
    "wof:name":"Country Camping",
    "wof:placetype":"venue"
},
  "geometry": {"coordinates":[-80.8059463501,42.6457061768],"type":"Point"}
}