{
  "type": "Feature",
  "properties": {
    "addr:full":"54 Main St Flin Flon MB R8A 1J6",
    "addr:housenumber":"54",
    "addr:postcode":"r8a 1j6",
    "addr:street":"Main St",
    "iso:country":"CA",
    "sg:address":"54 Main St",
    "sg:city":"Flin Flon",
    "sg:classifiers":[
        {
            "category":"Shopping",
            "type":"Retail Goods"
        }
    ],
    "sg:phone":"+1 204 687 5191",
    "sg:postcode":"R8A 1J6",
    "sg:province":"MB",
    "sg:tags":[
        "stamp",
        "collector",
        "for"
    ],
    "wof:name":"Canada Post Corp",
    "wof:placetype":"venue"
},
  "geometry": {"coordinates":[-101.876487732,54.7659378052],"type":"Point"}
}