{
  "type": "Feature",
  "properties": {
    "addr:full":"353 Cook St Victoria BC V8V 3X8",
    "addr:housenumber":"353",
    "addr:postcode":"v8v 3x8",
    "addr:street":"Cook St",
    "iso:country":"CA",
    "sg:address":"353 Cook St",
    "sg:city":"Victoria",
    "sg:classifiers":[
        {
            "category":"Personal",
            "subcategory":"Shoe Repair & Shine",
            "type":"Services"
        }
    ],
    "sg:phone":"+1 250 383 9635",
    "sg:postcode":"V8V 3X8",
    "sg:province":"BC",
    "sg:tags":[
        "repairing",
        "boot"
    ],
    "wof:name":"Arcadia Shoe Svc",
    "wof:placetype":"venue"
},
  "geometry": {"coordinates":[-123.35582700000001,48.415501],"type":"Point"}
}