{
  "type": "Feature",
  "properties": {
    "addr:full":"38 Newcastle Rd Winnipeg MB R3T 3Y7",
    "addr:housenumber":"38",
    "addr:postcode":"r3t 3y7",
    "addr:street":"Newcastle Rd",
    "iso:country":"CA",
    "sg:address":"38 Newcastle Rd",
    "sg:city":"Winnipeg",
    "sg:classifiers":[
        {
            "category":"Professional",
            "subcategory":"Management & Consulting",
            "type":"Services"
        }
    ],
    "sg:phone":"+1 204 269 5483",
    "sg:postcode":"R3T 3Y7",
    "sg:province":"MB",
    "sg:tags":[
        "consultant",
        "training"
    ],
    "wof:name":"Think Unlimited",
    "wof:placetype":"venue"
},
  "geometry": {"coordinates":[-97.1508178711,49.7848472595],"type":"Point"}
}