{
  "type": "Feature",
  "properties": {
    "iso:country":"CA",
    "sg:city":"Edmonton",
    "sg:classifiers":[
        {
            "category":"Banks & Credit Unions",
            "subcategory":"Investment Brokerage",
            "type":"Services"
        }
    ],
    "sg:phone":"+1 780 408 3665",
    "sg:postcode":"T5K 0J8",
    "sg:province":"AB",
    "sg:tags":[
        "consultant",
        "planning",
        "financial"
    ],
    "wof:name":"Assante Financial Management",
    "wof:placetype":"venue"
},
  "geometry": {"coordinates":[-113.519981384,53.5387077332],"type":"Point"}
}