{
  "type": "Feature",
  "properties": {
    "iso:country":"CA",
    "sg:city":"Saint-Lambert",
    "sg:classifiers":[
        {
            "category":"Health Services",
            "subcategory":"Doctor",
            "type":"Services"
        }
    ],
    "sg:phone":"+1 450 672 2052",
    "sg:postcode":"J4P 1S6",
    "sg:province":"QC",
    "sg:tags":[
        "dentist"
    ],
    "wof:name":"Abergel, Denis DDS",
    "wof:placetype":"venue"
},
  "geometry": {"coordinates":[-73.5099563599,45.5030021667],"type":"Point"}
}