{
  "type": "Feature",
  "properties": {
    "addr:full":"680 Josephine St Wingham ON N0G 2W0",
    "addr:housenumber":"680",
    "addr:postcode":"n0g 2w0",
    "addr:street":"Josephine St",
    "iso:country":"CA",
    "sg:address":"680 Josephine St",
    "sg:city":"Wingham",
    "sg:classifiers":[
        {
            "category":"Professional",
            "subcategory":"Business Services",
            "type":"Services"
        }
    ],
    "sg:phone":"+1 519 357 2987",
    "sg:postcode":"N0G 2W0",
    "sg:province":"ON",
    "sg:tags":[
        "auctioneer",
        "furniture"
    ],
    "wof:name":"Wingham Sales Arena",
    "wof:placetype":"venue"
},
  "geometry": {"coordinates":[-81.304787,43.896519],"type":"Point"}
}