{
  "type": "Feature",
  "properties": {
    "iso:country":"CA",
    "sg:address":"79 Rue Richard",
    "sg:city":"L'Epiphanie",
    "sg:classifiers":[
        {
            "category":"Banks & Credit Unions",
            "subcategory":"Bank",
            "type":"Services"
        }
    ],
    "sg:phone":"+1 450 588 5506",
    "sg:postcode":"J5X 3Y8",
    "sg:province":"QC",
    "sg:tags":[
        "financing"
    ],
    "wof:name":"Services Financiers Agri-Com",
    "wof:placetype":"venue"
},
  "geometry": {"coordinates":[-73.4838256836,45.8454475403],"type":"Point"}
}