{
  "type": "Feature",
  "properties": {
    "addr:full":"134 Charlotte St Sydney NS B1P 1C3",
    "addr:housenumber":"134",
    "addr:postcode":"b1p 1c3",
    "addr:street":"Charlotte St",
    "iso:country":"CA",
    "sg:address":"134 Charlotte St",
    "sg:city":"Sydney",
    "sg:classifiers":[
        {
            "category":"Professional",
            "subcategory":"Detective & Security Services",
            "type":"Services"
        }
    ],
    "sg:phone":"+1 902 564 9517",
    "sg:postcode":"B1P 1C3",
    "sg:province":"NS",
    "sg:tags":[
        "control",
        "guard",
        "patrol",
        "system"
    ],
    "wof:name":"Maritect Investigations & Scrt",
    "wof:placetype":"venue"
},
  "geometry": {"coordinates":[-60.19648,46.141735],"type":"Point"}
}