{
  "type": "Feature",
  "properties": {
    "addr:full":"Salmon Arm BC V1E 1R6",
    "addr:postcode":"v1e 1r6",
    "iso:country":"CA",
    "sg:city":"Salmon Arm",
    "sg:classifiers":[
        {
            "category":"Professional",
            "subcategory":"Accounting & Tax Preparation",
            "type":"Services"
        }
    ],
    "sg:phone":"+1 250 832 7171",
    "sg:postcode":"V1E 1R6",
    "sg:province":"BC",
    "sg:tags":[
        "accountant"
    ],
    "wof:name":"Aitken, Kathie",
    "wof:placetype":"venue"
},
  "geometry": {"coordinates":[-119.27847300000001,50.703583],"type":"Point"}
}