{
  "type": "Feature",
  "properties": {
    "iso:country":"CA",
    "sg:address":"1133 Hwy 97A #4",
    "sg:city":"Sicamous",
    "sg:classifiers":[
        {
            "category":"Insurance",
            "subcategory":"Insurance Agent",
            "type":"Services"
        }
    ],
    "sg:phone":"+1 250 836 3600",
    "sg:postcode":"V0E 2V0",
    "sg:province":"BC",
    "wof:name":"Barton Insurance Brokers Ltd",
    "wof:placetype":"venue"
},
  "geometry": {"coordinates":[-118.974975586,50.8015098572],"type":"Point"}
}