{
  "type": "Feature",
  "properties": {
    "iso:country":"CA",
    "sg:address":"382 Guelph Line",
    "sg:city":"Burlington",
    "sg:classifiers":[
        {
            "category":"Health Services",
            "subcategory":"Podiatrist",
            "type":"Services"
        }
    ],
    "sg:phone":"+1 905 632 9631",
    "sg:postcode":"L7R 3L4",
    "sg:province":"ON",
    "wof:name":"Cassel, Steven W E DPM",
    "wof:placetype":"venue"
},
  "geometry": {"coordinates":[-79.783653,43.336937],"type":"Point"}
}