{
  "type": "Feature",
  "properties": {
    "iso:country":"CA",
    "sg:address":"Hwy 43",
    "sg:city":"Kemptville",
    "sg:classifiers":[
        {
            "category":"Shopping",
            "subcategory":"Pharmacy",
            "type":"Retail Goods"
        }
    ],
    "sg:phone":"+1 613 258 4522",
    "sg:postcode":"K0G 1J0",
    "sg:province":"ON",
    "wof:name":"Proxim Care Pharma Drug Mart",
    "wof:placetype":"venue"
},
  "geometry": {"coordinates":[-75.6747512817,45.010055542],"type":"Point"}
}