{
  "type": "Feature",
  "properties": {
    "addr:full":"16 Rue DE L'Aqueduc Victoriaville QC G6P 1L6",
    "addr:housenumber":"16",
    "addr:postcode":"g6p 1l6",
    "addr:street":"Rue De L'Aqueduc",
    "iso:country":"CA",
    "sg:address":"16 Rue DE L'Aqueduc",
    "sg:city":"Victoriaville",
    "sg:classifiers":[
        {
            "category":"Manufacturing",
            "subcategory":"Metals",
            "type":"Manufacturing & Wholesale Goods"
        }
    ],
    "sg:phone":"+1 819 752 4929",
    "sg:postcode":"G6P 1L6",
    "sg:province":"QC",
    "sg:tags":[
        "solder",
        "welding"
    ],
    "wof:name":"Soudures Thibodeau Inc",
    "wof:placetype":"venue"
},
  "geometry": {"coordinates":[-71.97309112550001,46.0619316101],"type":"Point"}
}