{
  "type": "Feature",
  "properties": {
    "addr:full":"1319 Boul Des Peupliers Sainte-Marie QC G6E 3L2",
    "addr:housenumber":"1319",
    "addr:postcode":"g6e 3l2",
    "addr:street":"Boul Des Peupliers",
    "iso:country":"CA",
    "sg:address":"1319 Boul Des Peupliers",
    "sg:city":"Sainte-Marie",
    "sg:classifiers":[
        {
            "category":"Personal",
            "subcategory":"Beauty Salon",
            "type":"Services"
        }
    ],
    "sg:phone":"+1 418 387 7315",
    "sg:postcode":"G6E 3L2",
    "sg:province":"QC",
    "wof:name":"Salon Harmonies",
    "wof:placetype":"venue"
},
  "geometry": {"coordinates":[-71.041748,46.457287],"type":"Point"}
}