{
  "type": "Feature",
  "properties": {
    "addr:full":"1097 Trans Canada Way SE Medicine Hat AB T1B 1H9",
    "addr:housenumber":"1097",
    "addr:postcode":"t1b 1h9",
    "addr:street":"Trans Canada Way Se",
    "iso:country":"CA",
    "sg:address":"1097 Trans Canada Way SE",
    "sg:city":"Medicine Hat",
    "sg:classifiers":[
        {
            "category":"Shopping",
            "subcategory":"Department Store",
            "type":"Retail Goods"
        }
    ],
    "sg:phone":"+1 403 528 4200",
    "sg:postcode":"T1B 1H9",
    "sg:province":"AB",
    "sg:tags":[
        "shop"
    ],
    "wof:name":"Liquidation World Inc",
    "wof:placetype":"venue"
},
  "geometry": {"coordinates":[-110.65475499999999,50.003284],"type":"Point"}
}