{
  "type": "Feature",
  "properties": {
    "addr:full":"Mississauga ON L5A 4G1",
    "addr:postcode":"l5a 4g1",
    "iso:country":"CA",
    "sg:city":"Mississauga",
    "sg:classifiers":[
        {
            "category":"Professional",
            "subcategory":"Lawyer & Legal Services",
            "type":"Services"
        }
    ],
    "sg:phone":"+1 905 827 5415",
    "sg:postcode":"L5A 4G1",
    "sg:province":"ON",
    "sg:tags":[
        "attorney"
    ],
    "wof:name":"Baytor, Robert",
    "wof:placetype":"venue"
},
  "geometry": {"coordinates":[-79.602684,43.570786],"type":"Point"}
}