{
  "type": "Feature",
  "properties": {
    "addr:full":"475 Rue LA Fontaine Chicoutimi QC G7H 4V2",
    "addr:housenumber":"475",
    "addr:postcode":"g7h 4v2",
    "addr:street":"Rue La Fontaine",
    "iso:country":"CA",
    "sg:address":"475 Rue LA Fontaine",
    "sg:city":"Chicoutimi",
    "sg:classifiers":[
        {
            "category":"Education",
            "subcategory":"School",
            "type":"Public Place"
        }
    ],
    "sg:phone":"+1 418 698 5200",
    "sg:postcode":"G7H 4V2",
    "sg:province":"QC",
    "wof:name":"Lafontaine Ecole",
    "wof:placetype":"venue"
},
  "geometry": {"coordinates":[-71.060226,48.423592],"type":"Point"}
}