{
  "type": "Feature",
  "properties": {
    "addr:full":"Rimouski QC G5M 1A6",
    "addr:postcode":"g5m 1a6",
    "iso:country":"CA",
    "sg:city":"Rimouski",
    "sg:classifiers":[
        {
            "category":"Building & Trades",
            "subcategory":"Plumbing",
            "type":"Services"
        }
    ],
    "sg:phone":"+1 418 724 4816",
    "sg:postcode":"G5M 1A6",
    "sg:province":"QC",
    "sg:tags":[
        "contractor"
    ],
    "wof:name":"Plomberie St-Pie X Inc",
    "wof:placetype":"venue"
},
  "geometry": {"coordinates":[-68.50588226319999,48.4652671814],"type":"Point"}
}