{
  "type": "Feature",
  "properties": {
    "addr:full":"361 Jackson St W Hamilton ON L8P 1N2",
    "addr:housenumber":"361",
    "addr:postcode":"l8p 1n2",
    "addr:street":"Jackson St W",
    "iso:country":"CA",
    "sg:address":"361 Jackson St W",
    "sg:city":"Hamilton",
    "sg:classifiers":[
        {
            "category":"Professional",
            "subcategory":"Management & Consulting",
            "type":"Services"
        }
    ],
    "sg:phone":"+1 905 525 2786",
    "sg:postcode":"L8P 1N2",
    "sg:province":"ON",
    "sg:tags":[
        "consultant",
        "educational"
    ],
    "wof:name":"Personal Moves",
    "wof:placetype":"venue"
},
  "geometry": {"coordinates":[-79.8851852417,43.2580299377],"type":"Point"}
}