{
  "type": "Feature",
  "properties": {
    "iso:country":"CA",
    "sg:address":"9737 Yonge St # 218",
    "sg:city":"Richmond Hill",
    "sg:classifiers":[
        {
            "category":"Food & Beverages",
            "subcategory":"Bakery",
            "type":"Retail Goods"
        }
    ],
    "sg:phone":"+1 905 770 3660",
    "sg:postcode":"L4C 8S7",
    "sg:province":"ON",
    "sg:tags":[
        "baker"
    ],
    "wof:name":"What A Bagel",
    "wof:placetype":"venue"
},
  "geometry": {"coordinates":[-79.435631,43.865044],"type":"Point"}
}