{
  "type": "Feature",
  "properties": {
    "iso:country":"CA",
    "sg:address":"330 Boul Dr Albiny-Paquette",
    "sg:city":"Mont-Laurier",
    "sg:classifiers":[
        {
            "category":"Autos & Motor Vehicles",
            "subcategory":"Automobile Sales",
            "type":"Retail Goods"
        }
    ],
    "sg:phone":"+1 819 623 3511",
    "sg:postcode":"J9L 1J9",
    "sg:province":"QC",
    "sg:tags":[
        "car",
        "dealer"
    ],
    "wof:name":"Claude Auto Inc",
    "wof:placetype":"venue"
},
  "geometry": {"coordinates":[-75.50189208979999,46.5485534668],"type":"Point"}
}