{
  "type": "Feature",
  "properties": {
    "iso:country":"CA",
    "sg:address":"1357 Boul Saint-Paul",
    "sg:city":"Chicoutimi",
    "sg:classifiers":[
        {
            "category":"Wholesale",
            "subcategory":"Office Equipment",
            "type":"Manufacturing & Wholesale Goods"
        }
    ],
    "sg:phone":"+1 418 549 5447",
    "sg:postcode":"G7J 3Y3",
    "sg:province":"QC",
    "sg:tags":[
        "accounting",
        "bookkeeping",
        "system",
        "general"
    ],
    "wof:name":"Immeubles Pacami Inc",
    "wof:placetype":"venue"
},
  "geometry": {"coordinates":[-71.0934143066,48.4070549011],"type":"Point"}
}