{
  "type": "Feature",
  "properties": {
    "addr:full":"1082 Rte Sainte-Genevieve Val-Belair QC G3K 1A7",
    "addr:housenumber":"1082",
    "addr:postcode":"g3k 1a7",
    "addr:street":"Rte Sainte-Genevieve Val-Belair",
    "iso:country":"CA",
    "sg:address":"1082 Rte Sainte-Genevieve",
    "sg:city":"Val-Belair",
    "sg:classifiers":[
        {
            "category":"Manufacturing",
            "subcategory":"Metals",
            "type":"Manufacturing & Wholesale Goods"
        }
    ],
    "sg:phone":"+1 418 845 5723",
    "sg:postcode":"G3K 1A7",
    "sg:province":"QC",
    "sg:tags":[
        "shelter",
        "garage",
        "temporary"
    ],
    "wof:name":"L & M Toiles Enr",
    "wof:placetype":"venue"
},
  "geometry": {"coordinates":[-71.4083023071,46.8305931091],"type":"Point"}
}