{
  "type": "Feature",
  "properties": {
    "addr:full":"Ottawa ON K1R 6R4",
    "addr:postcode":"k1r 6r4",
    "iso:country":"CA",
    "sg:city":"Ottawa",
    "sg:classifiers":[
        {
            "category":"Shopping",
            "subcategory":"Pharmacy",
            "type":"Retail Goods"
        }
    ],
    "sg:phone":"+1 613 230 1368",
    "sg:postcode":"K1R 6R4",
    "sg:province":"ON",
    "wof:name":"Clinic Pharmacy an",
    "wof:placetype":"venue"
},
  "geometry": {"coordinates":[-75.71127300000001,45.409401],"type":"Point"}
}