{
  "type": "Feature",
  "properties": {
    "addr:full":"5330 3 Ave Delta BC V4M 1E7",
    "addr:housenumber":"5330",
    "addr:postcode":"v4m 1e7",
    "addr:street":"3 Ave",
    "iso:country":"CA",
    "sg:address":"5330 3 Ave",
    "sg:city":"Delta",
    "sg:classifiers":[
        {
            "category":"Communications",
            "subcategory":"Film & Video Production",
            "type":"Services"
        }
    ],
    "sg:phone":"+1 604 943 7100",
    "sg:postcode":"V4M 1E7",
    "sg:province":"BC",
    "sg:tags":[
        "motion",
        "picture"
    ],
    "wof:name":"Breakdown Services",
    "wof:placetype":"venue"
},
  "geometry": {"coordinates":[-123.076553,49.008221],"type":"Point"}
}