{
  "type": "Feature",
  "properties": {
    "addr:full":"244 Dundas St London ON N6A 1H3",
    "addr:housenumber":"244",
    "addr:postcode":"n6a 1h3",
    "addr:street":"Dundas St",
    "iso:country":"CA",
    "sg:address":"244 Dundas St",
    "sg:city":"London",
    "sg:classifiers":[
        {
            "category":"Restaurant",
            "type":"Food & Drink"
        }
    ],
    "sg:phone":"+1 519 645 6524",
    "sg:postcode":"N6A 1H3",
    "sg:province":"ON",
    "wof:name":"Braywick Bistro",
    "wof:placetype":"venue"
},
  "geometry": {"coordinates":[-81.246498,42.984741],"type":"Point"}
}