{
  "type": "Feature",
  "properties": {
    "addr:full":"10760 Boul Henri-Bourassa E Montreal QC H1C 1S9",
    "addr:housenumber":"10760",
    "addr:postcode":"h1c 1s9",
    "addr:street":"Boul Henri-Bourassa E",
    "iso:country":"CA",
    "sg:address":"10760 Boul Henri-Bourassa E",
    "sg:city":"Montreal",
    "sg:classifiers":[
        {
            "category":"Retail",
            "subcategory":"Auto Rental",
            "type":"Services"
        }
    ],
    "sg:phone":"+1 514 643 1422",
    "sg:postcode":"H1C 1S9",
    "sg:province":"QC",
    "sg:tags":[
        "renting",
        "truck",
        "leasing"
    ],
    "wof:name":"Penske Truck Leasing",
    "wof:placetype":"venue"
},
  "geometry": {"coordinates":[-73.535538,45.652447],"type":"Point"}
}