{
  "type": "Feature",
  "properties": {
    "addr:full":"125 Cathcart St Sault Ste Marie ON P6A 1E2",
    "addr:housenumber":"125",
    "addr:postcode":"p6a 1e2",
    "addr:street":"Cathcart St",
    "iso:country":"CA",
    "sg:address":"125 Cathcart St",
    "sg:city":"Sault Ste Marie",
    "sg:classifiers":[
        {
            "category":"Building & Trades",
            "subcategory":"Landscaping Services",
            "type":"Services"
        }
    ],
    "sg:phone":"+1 705 253 8733",
    "sg:postcode":"P6A 1E2",
    "sg:province":"ON",
    "sg:tags":[
        "tree"
    ],
    "wof:name":"Tree Men & A Chainsaw",
    "wof:placetype":"venue"
},
  "geometry": {"coordinates":[-84.342102,46.520237],"type":"Point"}
}