{
  "type": "Feature",
  "properties": {
    "addr:full":"Edmonton AB T5G 0X4",
    "addr:postcode":"t5g 0x4",
    "iso:country":"CA",
    "sg:city":"Edmonton",
    "sg:classifiers":[
        {
            "category":"Health Services",
            "subcategory":"Health Practitioner",
            "type":"Services"
        }
    ],
    "sg:phone":"+1 780 447 2614",
    "sg:postcode":"T5G 0X4",
    "sg:province":"AB",
    "sg:tags":[
        "psychologist"
    ],
    "wof:name":"H J Mc Leod & Assoc Ltd",
    "wof:placetype":"venue"
},
  "geometry": {"coordinates":[-113.51818799999999,53.565483],"type":"Point"}
}