{
  "type": "Feature",
  "properties": {
    "addr:full":"546 Maude Petrolia ON N0N 1R0",
    "addr:housenumber":"546",
    "addr:postcode":"n0n 1r0",
    "addr:street":"Maude",
    "iso:country":"CA",
    "sg:address":"546 Maude",
    "sg:city":"Petrolia",
    "sg:classifiers":[
        {
            "category":"Utilities",
            "subcategory":"Water",
            "type":"Services"
        }
    ],
    "sg:phone":"+1 519 882 3137",
    "sg:postcode":"N0N 1R0",
    "sg:province":"ON",
    "sg:tags":[
        "plant",
        "management",
        "treatment"
    ],
    "wof:name":"Omi Canada",
    "wof:placetype":"venue"
},
  "geometry": {"coordinates":[-82.15882873539999,42.8707733154],"type":"Point"}
}