{
  "type": "Feature",
  "properties": {
    "addr:full":"4320 52 Ave Red Deer AB T4N 4J9",
    "addr:housenumber":"4320",
    "addr:postcode":"t4n 4j9",
    "addr:street":"52 Ave",
    "iso:country":"CA",
    "sg:address":"4320 52 Ave",
    "sg:city":"Red Deer",
    "sg:classifiers":[
        {
            "category":"Professional",
            "type":"Services"
        }
    ],
    "sg:phone":"+1 403 346 4114",
    "sg:postcode":"T4N 4J9",
    "sg:province":"AB",
    "sg:tags":[
        "establishment",
        "trucking"
    ],
    "wof:name":"Bettenson's Cartage CO Ltd",
    "wof:placetype":"venue"
},
  "geometry": {"coordinates":[-113.81980133099999,52.2623291016],"type":"Point"}
}