{
  "type": "Feature",
  "properties": {
    "addr:full":"124 Durham St E Walkerton ON N0G 2V0",
    "addr:housenumber":"124",
    "addr:postcode":"n0g 2v0",
    "addr:street":"Durham St E Walkerton",
    "iso:country":"CA",
    "sg:address":"124 Durham St E",
    "sg:city":"Walkerton",
    "sg:classifiers":[
        {
            "category":"Bars & Pubs",
            "type":"Food & Drink"
        }
    ],
    "sg:phone":"+1 519 881 4402",
    "sg:postcode":"N0G 2V0",
    "sg:province":"ON",
    "wof:name":"Harvey's Place",
    "wof:placetype":"venue"
},
  "geometry": {"coordinates":[-81.1510391235,44.1336784363],"type":"Point"}
}