{
  "type": "Feature",
  "properties": {
    "addr:full":"Aylmer QC J9H 3L2",
    "addr:postcode":"j9h 3l2",
    "iso:country":"CA",
    "sg:city":"Aylmer",
    "sg:classifiers":[
        {
            "category":"Professional",
            "subcategory":"Business Services",
            "type":"Services"
        }
    ],
    "sg:phone":"+1 819 329 1410",
    "sg:postcode":"J9H 3L2",
    "sg:province":"QC",
    "sg:tags":[
        "appraiser"
    ],
    "wof:name":"Evaluations B Hogan",
    "wof:placetype":"venue"
},
  "geometry": {"coordinates":[-75.85127300000001,45.394638],"type":"Point"}
}