{
  "type": "Feature",
  "properties": {
    "addr:full":"2694 Kings Rd Sydney Forks NS B1L 1A1",
    "addr:housenumber":"2694",
    "addr:postcode":"b1l 1a1",
    "addr:street":"Kings Rd",
    "iso:country":"CA",
    "sg:address":"2694 Kings Rd",
    "sg:city":"Sydney Forks",
    "sg:classifiers":[
        {
            "category":"Professional",
            "type":"Services"
        }
    ],
    "sg:phone":"+1 902 567 9816",
    "sg:postcode":"B1L 1A1",
    "sg:province":"NS",
    "sg:tags":[
        "pump",
        "establishment"
    ],
    "wof:name":"Tom Angell's Pump Sales & Svc",
    "wof:placetype":"venue"
},
  "geometry": {"coordinates":[-60.305229187,46.0596618652],"type":"Point"}
}