{
  "type": "Feature",
  "properties": {
    "addr:full":"Fox Creek AB T0H 1P0",
    "addr:postcode":"t0h 1p0",
    "iso:country":"CA",
    "sg:city":"Fox Creek",
    "sg:classifiers":[
        {
            "category":"Government",
            "subcategory":"Office",
            "type":"Public Place"
        }
    ],
    "sg:phone":"+1 780 622 3113",
    "sg:postcode":"T0H 1P0",
    "sg:province":"AB",
    "wof:name":"Alberta Provincial Court",
    "wof:placetype":"venue"
},
  "geometry": {"coordinates":[-116.809898377,54.4136428833],"type":"Point"}
}