{
  "type": "Feature",
  "properties": {
    "addr:full":"1284 Rue Beaubien E Montreal QC H2S 1T9",
    "addr:housenumber":"1284",
    "addr:postcode":"h2s 1t9",
    "addr:street":"Rue Beaubien E",
    "iso:country":"CA",
    "sg:address":"1284 Rue Beaubien E",
    "sg:city":"Montreal",
    "sg:classifiers":[
        {
            "category":"Food & Beverages",
            "subcategory":"Groceries & Convenience Stores",
            "type":"Retail Goods"
        }
    ],
    "sg:phone":"+1 514 271 7720",
    "sg:postcode":"H2S 1T9",
    "sg:province":"QC",
    "sg:tags":[
        "grocer"
    ],
    "wof:name":"Marche A Asselin",
    "wof:placetype":"venue"
},
  "geometry": {"coordinates":[-73.599586,45.539669],"type":"Point"}
}