{
  "type": "Feature",
  "properties": {
    "addr:full":"366 Barrie St Kingston ON K7K 3T3",
    "addr:housenumber":"366",
    "addr:postcode":"k7k 3t3",
    "addr:street":"Barrie St",
    "iso:country":"CA",
    "sg:address":"366 Barrie St",
    "sg:city":"Kingston",
    "sg:classifiers":[
        {
            "category":"Professional",
            "subcategory":"Management & Consulting",
            "type":"Services"
        }
    ],
    "sg:phone":"+1 613 542 6268",
    "sg:postcode":"K7K 3T3",
    "sg:province":"ON",
    "sg:tags":[
        "consultant",
        "telecommunication"
    ],
    "wof:name":"Digital & Analogue Telephone",
    "wof:placetype":"venue"
},
  "geometry": {"coordinates":[-76.49060799999999,44.234234],"type":"Point"}
}