{
  "type": "Feature",
  "properties": {
    "addr:full":"95 Victoria St Edmundston NB E3V 3K8",
    "addr:housenumber":"95",
    "addr:postcode":"e3v 3k8",
    "addr:street":"Victoria St",
    "iso:country":"CA",
    "sg:address":"95 Victoria St",
    "sg:city":"Edmundston",
    "sg:classifiers":[
        {
            "category":"Recreation",
            "type":"Entertainment"
        }
    ],
    "sg:phone":"+1 506 739 6608",
    "sg:postcode":"E3V 3K8",
    "sg:province":"NB",
    "sg:tags":[
        "attraction",
        "tourist",
        "carnival"
    ],
    "wof:name":"Foire Brayonne",
    "wof:placetype":"venue"
},
  "geometry": {"coordinates":[-68.322029,47.366325],"type":"Point"}
}