{
  "type": "Feature",
  "properties": {
    "addr:full":"2294 Camilla Rd Mississauga ON L5A 2K3",
    "addr:housenumber":"2294",
    "addr:postcode":"l5a 2k3",
    "addr:street":"Camilla Rd",
    "iso:country":"CA",
    "sg:address":"2294 Camilla Rd",
    "sg:city":"Mississauga",
    "sg:classifiers":[
        {
            "category":"Professional",
            "subcategory":"Lawyer & Legal Services",
            "type":"Services"
        }
    ],
    "sg:phone":"+1 905 279 9831",
    "sg:postcode":"L5A 2K3",
    "sg:province":"ON",
    "sg:tags":[
        "attorney"
    ],
    "wof:name":"Shaw, Donald N QC",
    "wof:placetype":"venue"
},
  "geometry": {"coordinates":[-79.60347,43.577518],"type":"Point"}
}