{
  "type": "Feature",
  "properties": {
    "addr:full":"1791 Boul DE Sainte-Adele Sainte-Adele QC J8B 2N6",
    "addr:housenumber":"1791",
    "addr:postcode":"j8b 2n6",
    "addr:street":"Boul De Sainte-Adele Sainte-Adele",
    "iso:country":"CA",
    "sg:address":"1791 Boul DE Sainte-Adele",
    "sg:city":"Sainte-Adele",
    "sg:classifiers":[
        {
            "category":"Recreation",
            "type":"Entertainment"
        }
    ],
    "sg:phone":"+1 450 430 7930",
    "sg:postcode":"J8B 2N6",
    "sg:province":"QC",
    "sg:tags":[
        "amusement"
    ],
    "wof:name":"Glissade D'Eau Super Splash",
    "wof:placetype":"venue"
},
  "geometry": {"coordinates":[-74.134193,45.950706],"type":"Point"}
}