{
  "type": "Feature",
  "properties": {
    "addr:full":"Langley BC V1M 3E8",
    "addr:postcode":"v1m 3e8",
    "iso:country":"CA",
    "sg:city":"Langley",
    "sg:classifiers":[
        {
            "category":"Professional",
            "subcategory":"Computer Services",
            "type":"Services"
        }
    ],
    "sg:phone":"+1 604 882 3100",
    "sg:postcode":"V1M 3E8",
    "sg:province":"BC",
    "sg:tags":[
        "repair",
        "television",
        "radio"
    ],
    "wof:name":"B-Tronics",
    "wof:placetype":"venue"
},
  "geometry": {"coordinates":[-122.664154053,49.1779823303],"type":"Point"}
}