{
  "type": "Feature",
  "properties": {
    "iso:country":"CA",
    "sg:city":"Chesley",
    "sg:classifiers":[
        {
            "category":"Government",
            "subcategory":"Fire Station",
            "type":"Public Place"
        }
    ],
    "sg:phone":"+1 519 363 3730",
    "sg:postcode":"N0G 1L0",
    "sg:province":"ON",
    "sg:tags":[
        "department"
    ],
    "wof:name":"Chesley Fire Hall",
    "wof:placetype":"venue"
},
  "geometry": {"coordinates":[-81.096496582,44.3022766113],"type":"Point"}
}