{
  "type": "Feature",
  "properties": {
    "addr:full":"2300 13 St N Lethbridge AB T1H 4E8",
    "addr:housenumber":"2300",
    "addr:postcode":"t1h 4e8",
    "addr:street":"13 St N",
    "iso:country":"CA",
    "sg:address":"2300 13 St N",
    "sg:city":"Lethbridge",
    "sg:classifiers":[
        {
            "category":"Real Estate",
            "subcategory":"Developer",
            "type":"Services"
        }
    ],
    "sg:phone":"+1 403 320 6333",
    "sg:postcode":"T1H 4E8",
    "sg:province":"AB",
    "sg:tags":[
        "mobile",
        "home"
    ],
    "wof:name":"Bridge Villa Estates",
    "wof:placetype":"venue"
},
  "geometry": {"coordinates":[-112.824265,49.72504],"type":"Point"}
}