{
  "type": "Feature",
  "properties": {
    "iso:country":"CA",
    "sg:address":"309 Blake St",
    "sg:city":"Barrie",
    "sg:classifiers":[
        {
            "category":"Shopping",
            "subcategory":"Tobacco",
            "type":"Retail Goods"
        }
    ],
    "sg:phone":"+1 705 739 9762",
    "sg:postcode":"L4M 1K7",
    "sg:province":"ON",
    "sg:tags":[
        "cigarette",
        "cigar",
        "dealer"
    ],
    "wof:name":"Lucky's Smoke & Cigar",
    "wof:placetype":"venue"
},
  "geometry": {"coordinates":[-79.658028,44.396584],"type":"Point"}
}