{
  "type": "Feature",
  "properties": {
    "iso:country":"CA",
    "sg:address":"3981 Rue Wellington",
    "sg:city":"Verdun",
    "sg:classifiers":[
        {
            "category":"Shopping",
            "subcategory":"Gifts & Souvenirs",
            "type":"Retail Goods"
        }
    ],
    "sg:phone":"+1 514 767 5383",
    "sg:postcode":"H4G 1V6",
    "sg:province":"QC",
    "sg:tags":[
        "shop"
    ],
    "wof:name":"Sauve",
    "wof:placetype":"venue"
},
  "geometry": {"coordinates":[-73.567108,45.464024],"type":"Point"}
}