{
  "type": "Feature",
  "properties": {
    "addr:full":"256 the Queensway S Keswick ON L4P 2B1",
    "addr:housenumber":"256",
    "addr:postcode":"l4p 2b1",
    "addr:street":"The Queensway S",
    "iso:country":"CA",
    "sg:address":"256 the Queensway S",
    "sg:city":"Keswick",
    "sg:classifiers":[
        {
            "category":"Restaurant",
            "type":"Food & Drink"
        }
    ],
    "sg:phone":"+1 905 476 1335",
    "sg:postcode":"L4P 2B1",
    "sg:province":"ON",
    "wof:name":"Gino's Pizza",
    "wof:placetype":"venue"
},
  "geometry": {"coordinates":[-79.46450042719999,44.2268333435],"type":"Point"}
}