{
  "type": "Feature",
  "properties": {
    "addr:full":"1950 Rue DE Gaspe Terrebonne QC J6X 2R9",
    "addr:housenumber":"1950",
    "addr:postcode":"j6x 2r9",
    "addr:street":"Rue De Gaspe",
    "iso:country":"CA",
    "sg:address":"1950 Rue DE Gaspe",
    "sg:city":"Terrebonne",
    "sg:phone":"+1 450 964 1805",
    "sg:postcode":"J6X 2R9",
    "sg:province":"QC",
    "sg:tags":[
        "shelving"
    ],
    "wof:name":"Prescott Installation Inc",
    "wof:placetype":"venue"
},
  "geometry": {"coordinates":[-73.670029,45.721748],"type":"Point"}
}