{
  "type": "Feature",
  "properties": {
    "addr:full":"914 Esquimalt Rd Victoria BC V9A 3M6",
    "addr:housenumber":"914",
    "addr:postcode":"v9a 3m6",
    "addr:street":"Esquimalt Rd",
    "iso:country":"CA",
    "sg:address":"914 Esquimalt Rd",
    "sg:city":"Victoria",
    "sg:classifiers":[
        {
            "category":"Restaurant",
            "type":"Food & Drink"
        }
    ],
    "sg:phone":"+1 250 385 2322",
    "sg:postcode":"V9A 3M6",
    "sg:province":"BC",
    "wof:name":"Lum's Polynesian Restaurant",
    "wof:placetype":"venue"
},
  "geometry": {"coordinates":[-123.394188,48.431808],"type":"Point"}
}