{
  "type": "Feature",
  "properties": {
    "addr:full":"2060 Peninsula St Ucluelet BC V0R 3A0",
    "addr:housenumber":"2060",
    "addr:postcode":"bc v0r 3a0",
    "addr:street":"Peninsula St",
    "iso:country":"CA",
    "sg:address":"2060 Peninsula St",
    "sg:city":"Ucluelet",
    "sg:classifiers":[
        {
            "category":"Building & Trades",
            "subcategory":"Landscaping Services",
            "type":"Services"
        }
    ],
    "sg:phone":"+1 250 726 7113",
    "sg:postcode":"V0R 3A0",
    "sg:province":"BC",
    "sg:tags":[
        "lawn",
        "sales",
        "maintenance",
        "dealer",
        "boat",
        "grounds"
    ],
    "wof:name":"Westwood Power & Marine Ltd",
    "wof:placetype":"venue"
},
  "geometry": {"coordinates":[-125.542610169,48.9380264282],"type":"Point"}
}