{
  "type": "Feature",
  "properties": {
    "addr:full":"4857 Chisholm St Delta BC V4K 2K6",
    "addr:housenumber":"4857",
    "addr:postcode":"v4k 2k6",
    "addr:street":"Chisholm St",
    "iso:country":"CA",
    "sg:address":"4857 Chisholm St",
    "sg:city":"Delta",
    "sg:classifiers":[
        {
            "category":"Manufacturing",
            "subcategory":"Food",
            "type":"Manufacturing & Wholesale Goods"
        }
    ],
    "sg:phone":"+1 604 946 1266",
    "sg:postcode":"V4K 2K6",
    "sg:province":"BC",
    "sg:tags":[
        "product",
        "seafood",
        "fish",
        "prepared"
    ],
    "wof:name":"Seven Seas Fish CO Ltd",
    "wof:placetype":"venue"
},
  "geometry": {"coordinates":[-123.088157654,49.0923423767],"type":"Point"}
}