{
  "type": "Feature",
  "properties": {
    "addr:full":"5812 Boul Talbot Laterriere QC G7N 1W1",
    "addr:housenumber":"5812",
    "addr:postcode":"g7n 1w1",
    "addr:street":"Boul Talbot Laterriere",
    "iso:country":"CA",
    "sg:address":"5812 Boul Talbot",
    "sg:city":"Laterriere",
    "sg:classifiers":[
        {
            "category":"Banks & Credit Unions",
            "subcategory":"Bank",
            "type":"Services"
        }
    ],
    "sg:phone":"+1 418 678 2710",
    "sg:postcode":"G7N 1W1",
    "sg:province":"QC",
    "sg:tags":[
        "insurance"
    ],
    "wof:name":"Caisses Populaires Desjardins",
    "wof:placetype":"venue"
},
  "geometry": {"coordinates":[-71.133888,48.317001],"type":"Point"}
}