{
  "type": "Feature",
  "properties": {
    "addr:full":"Surrey BC V3R 4E7",
    "addr:postcode":"v3r 4e7",
    "iso:country":"CA",
    "sg:city":"Surrey",
    "sg:classifiers":[
        {
            "category":"Cinema",
            "subcategory":"Movie Rental",
            "type":"Entertainment"
        }
    ],
    "sg:phone":"+1 604 582 6522",
    "sg:postcode":"V3R 4E7",
    "sg:province":"BC",
    "sg:tags":[
        "leasing",
        "video",
        "disc",
        "tape"
    ],
    "wof:name":"Blockbuster Video",
    "wof:placetype":"venue"
},
  "geometry": {"coordinates":[-122.80120100000001,49.166592],"type":"Point"}
}