{
  "type": "Feature",
  "properties": {
    "addr:full":"65 Maccullach Rd Bridgewater NS B4V 2W1",
    "addr:housenumber":"65",
    "addr:postcode":"b4v 2w1",
    "addr:street":"Maccullach Rd",
    "iso:country":"CA",
    "sg:address":"65 Maccullach Rd",
    "sg:city":"Bridgewater",
    "sg:classifiers":[
        {
            "category":"Home & Garden",
            "subcategory":"Home Furnishings",
            "type":"Retail Goods"
        }
    ],
    "sg:phone":"+1 902 543 8885",
    "sg:postcode":"B4V 2W1",
    "sg:province":"NS",
    "sg:tags":[
        "fireplace"
    ],
    "wof:name":"Traditional Hearth & Fireplace",
    "wof:placetype":"venue"
},
  "geometry": {"coordinates":[-64.5230331421,44.3804969788],"type":"Point"}
}