{
  "type": "Feature",
  "properties": {
    "addr:full":"Toronto ON M4S 3C3",
    "addr:postcode":"m4s 3c3",
    "iso:country":"CA",
    "sg:city":"Toronto",
    "sg:classifiers":[
        {
            "category":"Professional",
            "subcategory":"Employment Agencies",
            "type":"Services"
        }
    ],
    "sg:phone":"+1 416 482 2420",
    "sg:postcode":"M4S 3C3",
    "sg:province":"ON",
    "sg:tags":[
        "opportunity"
    ],
    "wof:name":"Employment Solution",
    "wof:placetype":"venue"
},
  "geometry": {"coordinates":[-79.3964920044,43.7056884766],"type":"Point"}
}