{
  "type": "Feature",
  "properties": {
    "iso:country":"CA",
    "sg:address":"81 Ontario St",
    "sg:city":"Stratford",
    "sg:classifiers":[
        {
            "category":"Restaurant",
            "type":"Food & Drink"
        }
    ],
    "sg:phone":"+1 519 271 9678",
    "sg:postcode":"N5A 3H1",
    "sg:province":"ON",
    "wof:name":"Gene's Restaurant",
    "wof:placetype":"venue"
},
  "geometry": {"coordinates":[-80.9818649292,43.3712921143],"type":"Point"}
}