{
  "type": "Feature",
  "properties": {
    "addr:full":"Antigonish NS B2G 2C1",
    "addr:postcode":"b2g 2c1",
    "iso:country":"CA",
    "sg:city":"Antigonish",
    "sg:classifiers":[
        {
            "category":"Insurance",
            "subcategory":"Insurance Agent",
            "type":"Services"
        }
    ],
    "sg:phone":"+1 902 863 3999",
    "sg:postcode":"B2G 2C1",
    "sg:province":"NS",
    "wof:name":"A A Munro Insurance",
    "wof:placetype":"venue"
},
  "geometry": {"coordinates":[-61.989414,45.622547],"type":"Point"}
}