{
  "type": "Feature",
  "properties": {
    "addr:full":"2051 Rue Wellington Montreal QC H3K 1W7",
    "addr:housenumber":"2051",
    "addr:postcode":"h3k 1w7",
    "addr:street":"Rue Wellington",
    "iso:country":"CA",
    "sg:address":"2051 Rue Wellington",
    "sg:city":"Montreal",
    "sg:classifiers":[
        {
            "category":"Health Services",
            "subcategory":"Doctor",
            "type":"Services"
        }
    ],
    "sg:phone":"+1 514 932 5147",
    "sg:postcode":"H3K 1W7",
    "sg:province":"QC",
    "sg:tags":[
        "clinic"
    ],
    "wof:name":"Centre Medical Wellington",
    "wof:placetype":"venue"
},
  "geometry": {"coordinates":[-73.5591201782,45.4784622192],"type":"Point"}
}