{
  "type": "Feature",
  "properties": {
    "addr:full":"Waterloo ON N2J 4K8",
    "addr:postcode":"n2j 4k8",
    "iso:country":"CA",
    "sg:city":"Waterloo",
    "sg:classifiers":[
        {
            "category":"Health Services",
            "subcategory":"Doctor",
            "type":"Services"
        }
    ],
    "sg:phone":"+1 519 885 5880",
    "sg:postcode":"N2J 4K8",
    "sg:province":"ON",
    "sg:tags":[
        "dentist"
    ],
    "wof:name":"Donald Edwards Dental Office",
    "wof:placetype":"venue"
},
  "geometry": {"coordinates":[-80.518737793,43.4656028748],"type":"Point"}
}