{
  "type": "Feature",
  "properties": {
    "addr:full":"1844 Boul Pie-Ix Montreal QC H1V 2C6",
    "addr:housenumber":"1844",
    "addr:postcode":"h1v 2c6",
    "addr:street":"Boul Pie-Ix",
    "iso:country":"CA",
    "sg:address":"1844 Boul Pie-Ix",
    "sg:city":"Montreal",
    "sg:classifiers":[
        {
            "category":"Social Services",
            "type":"Services"
        }
    ],
    "sg:phone":"+1 514 526 9128",
    "sg:postcode":"H1V 2C6",
    "sg:province":"QC",
    "sg:tags":[
        "organization",
        "welfare"
    ],
    "wof:name":"Maison Des Enfants/L'Ile DE MT",
    "wof:placetype":"venue"
},
  "geometry": {"coordinates":[-73.53987100000001,45.549664],"type":"Point"}
}