{
  "type": "Feature",
  "properties": {
    "addr:full":"1800 Ch Galvin Fleurimont QC J1G 3E9",
    "addr:housenumber":"1800",
    "addr:postcode":"j1g 3e9",
    "addr:street":"Ch Galvin",
    "iso:country":"CA",
    "sg:address":"1800 Ch Galvin",
    "sg:city":"Fleurimont",
    "sg:classifiers":[
        {
            "category":"Wholesale",
            "subcategory":"Photographic Equipment",
            "type":"Manufacturing & Wholesale Goods"
        }
    ],
    "sg:phone":"+1 819 563 6113",
    "sg:postcode":"J1G 3E9",
    "sg:province":"QC",
    "sg:tags":[
        "supply"
    ],
    "wof:name":"Distributions Johnson Inc",
    "wof:placetype":"venue"
},
  "geometry": {"coordinates":[-71.848381,45.405983],"type":"Point"}
}