{
  "type": "Feature",
  "properties": {
    "addr:full":"Alberton PE C0B 1B0",
    "addr:postcode":"c0b 1b0",
    "iso:country":"CA",
    "sg:city":"Alberton",
    "sg:classifiers":[
        {
            "category":"Health Services",
            "subcategory":"Optometrist",
            "type":"Services"
        }
    ],
    "sg:phone":"+1 902 853 3361",
    "sg:postcode":"C0B 1B0",
    "sg:province":"PE",
    "wof:name":"Williams, Craig OD",
    "wof:placetype":"venue"
},
  "geometry": {"coordinates":[-64.0641403198,46.8130226135],"type":"Point"}
}