{
  "type": "Feature",
  "properties": {
    "addr:full":"303 North Railway St Morden MB R6M 2B2",
    "addr:housenumber":"303",
    "addr:postcode":"r6m 2b2",
    "addr:street":"North Railway St",
    "iso:country":"CA",
    "sg:address":"303 North Railway St",
    "sg:city":"Morden",
    "sg:classifiers":[
        {
            "category":"Travel",
            "subcategory":"Hotels & Motels",
            "type":"Entertainment"
        }
    ],
    "sg:phone":"+1 204 822 4515",
    "sg:postcode":"R6M 2B2",
    "sg:province":"MB",
    "wof:name":"Travellers Inn",
    "wof:placetype":"venue"
},
  "geometry": {"coordinates":[-98.0970153809,49.1889801025],"type":"Point"}
}