{
  "type": "Feature",
  "properties": {
    "addr:full":"1895 Venables St Vancouver BC V5L 2H6",
    "addr:housenumber":"1895",
    "addr:postcode":"v5l 2h6",
    "addr:street":"Venables St",
    "iso:country":"CA",
    "sg:address":"1895 Venables St",
    "sg:city":"Vancouver",
    "sg:classifiers":[
        {
            "category":"Arts & Performance",
            "subcategory":"Theater",
            "type":"Entertainment"
        }
    ],
    "sg:phone":"+1 604 254 9578",
    "sg:postcode":"V5L 2H6",
    "sg:province":"BC",
    "wof:name":"Vancouver East Cultural Ctr",
    "wof:placetype":"venue"
},
  "geometry": {"coordinates":[-123.06592559800001,49.2768745422],"type":"Point"}
}