{
  "type": "Feature",
  "properties": {
    "addr:full":"36 Bruce St S Thornbury ON N0H 2P0",
    "addr:housenumber":"36",
    "addr:postcode":"n0h 2p0",
    "addr:street":"Bruce St S",
    "iso:country":"CA",
    "sg:address":"36 Bruce St S",
    "sg:city":"Thornbury",
    "sg:classifiers":[
        {
            "category":"Health Services",
            "subcategory":"Doctor",
            "type":"Services"
        }
    ],
    "sg:phone":"+1 519 599 3038",
    "sg:postcode":"N0H 2P0",
    "sg:province":"ON",
    "sg:tags":[
        "dentist"
    ],
    "wof:name":"Rose, David DDS",
    "wof:placetype":"venue"
},
  "geometry": {"coordinates":[-80.4537734985,44.5613136292],"type":"Point"}
}