{
  "type": "Feature",
  "properties": {
    "addr:full":"1037 Craigdarroch Rd Victoria BC V8S 2A5",
    "addr:housenumber":"1037",
    "addr:postcode":"v8s 2a5",
    "addr:street":"Craigdarroch Rd",
    "iso:country":"CA",
    "sg:address":"1037 Craigdarroch Rd",
    "sg:city":"Victoria",
    "sg:classifiers":[
        {
            "category":"Travel",
            "subcategory":"Hotels & Motels",
            "type":"Entertainment"
        }
    ],
    "sg:phone":"+1 250 595 5411",
    "sg:postcode":"V8S 2A5",
    "sg:province":"BC",
    "sg:tags":[
        "breakfast",
        "accommodation",
        "bed"
    ],
    "wof:name":"Craigmyle Guest House",
    "wof:placetype":"venue"
},
  "geometry": {"coordinates":[-123.345046997,48.4227752686],"type":"Point"}
}