{
  "type": "Feature",
  "properties": {
    "iso:country":"CA",
    "sg:city":"Woodbridge",
    "sg:classifiers":[
        {
            "category":"Building & Trades",
            "subcategory":"Cleaning & Sanitation",
            "type":"Services"
        }
    ],
    "sg:phone":"+1 905 851 1275",
    "sg:postcode":"L4L 3T4",
    "sg:province":"ON",
    "sg:tags":[
        "janitor"
    ],
    "wof:name":"Direct Maintenance",
    "wof:placetype":"venue"
},
  "geometry": {"coordinates":[-79.557091,43.770679],"type":"Point"}
}