{
  "type": "Feature",
  "properties": {
    "addr:full":"19 Ann St Forest ON N0N 1J0",
    "addr:housenumber":"19",
    "addr:postcode":"n0n 1j0",
    "addr:street":"Ann St",
    "iso:country":"CA",
    "sg:address":"19 Ann St",
    "sg:city":"Forest",
    "sg:classifiers":[
        {
            "category":"Government",
            "subcategory":"Office",
            "type":"Public Place"
        }
    ],
    "sg:phone":"+1 519 786 2335",
    "sg:postcode":"N0N 1J0",
    "sg:province":"ON",
    "sg:tags":[
        "village"
    ],
    "wof:name":"Forest Administration Office",
    "wof:placetype":"venue"
},
  "geometry": {"coordinates":[-82.0035400391,43.0974197388],"type":"Point"}
}