{
  "type": "Feature",
  "properties": {
    "addr:full":"160 Rue Des Nomades Repentigny QC J5Y 2Z2",
    "addr:housenumber":"160",
    "addr:postcode":"j5y 2z2",
    "addr:street":"Rue Des Nomades",
    "iso:country":"CA",
    "sg:address":"160 Rue Des Nomades",
    "sg:city":"Repentigny",
    "sg:classifiers":[
        {
            "category":"Professional",
            "subcategory":"Business Services",
            "type":"Services"
        }
    ],
    "sg:phone":"+1 450 654 1624",
    "sg:postcode":"J5Y 2Z2",
    "sg:province":"QC",
    "sg:tags":[
        "specification",
        "architectural",
        "drafting"
    ],
    "wof:name":"Dessin Db",
    "wof:placetype":"venue"
},
  "geometry": {"coordinates":[-73.42145499999999,45.777496],"type":"Point"}
}