{
  "type": "Feature",
  "properties": {
    "iso:country":"CA",
    "sg:address":"160 Rue Des Nomades",
    "sg:city":"Repentigny",
    "sg:classifiers":[
        {
            "category":"Professional",
            "subcategory":"Business Services",
            "type":"Services"
        }
    ],
    "sg:phone":"+1 450 654 1624",
    "sg:postcode":"J5Y 2Z2",
    "sg:province":"QC",
    "sg:tags":[
        "specification",
        "architectural",
        "drafting"
    ],
    "wof:name":"Dessin Db",
    "wof:placetype":"venue"
},
  "geometry": {"coordinates":[-73.421455,45.777496],"type":"Point"}
}