{
  "type": "Feature",
  "properties": {
    "addr:full":"1537 Commercial Dr Vancouver BC V5L 3Y1",
    "addr:housenumber":"1537",
    "addr:postcode":"v5l 3y1",
    "addr:street":"Commercial Dr",
    "iso:country":"CA",
    "sg:address":"1537 Commercial Dr",
    "sg:city":"Vancouver",
    "sg:classifiers":[
        {
            "category":"Restaurant",
            "type":"Food & Drink"
        }
    ],
    "sg:phone":"+1 604 251 1177",
    "sg:postcode":"V5L 3Y1",
    "sg:province":"BC",
    "wof:name":"Arriva Ristorante Ltd",
    "wof:placetype":"venue"
},
  "geometry": {"coordinates":[-123.069878,49.270969],"type":"Point"}
}