{
  "type": "Feature",
  "properties": {
    "addr:full":"756 Summer St New Glasgow NS B2H 3Y8",
    "addr:housenumber":"756",
    "addr:postcode":"b2h 3y8",
    "addr:street":"Summer St",
    "iso:country":"CA",
    "sg:address":"756 Summer St",
    "sg:city":"New Glasgow",
    "sg:classifiers":[
        {
            "category":"Health Services",
            "subcategory":"Health Practitioner",
            "type":"Services"
        }
    ],
    "sg:phone":"+1 902 928 0063",
    "sg:postcode":"B2H 3Y8",
    "sg:province":"NS",
    "sg:tags":[
        "acupuncture",
        "therapist",
        "massage"
    ],
    "wof:name":"Pressure Points Massage",
    "wof:placetype":"venue"
},
  "geometry": {"coordinates":[-62.641094,45.574238],"type":"Point"}
}