{
  "type": "Feature",
  "properties": {
    "addr:full":"Quebec QC G1N 3L8",
    "addr:postcode":"g1n 3l8",
    "iso:country":"CA",
    "sg:city":"Quebec",
    "sg:classifiers":[
        {
            "category":"Professional",
            "subcategory":"Business Services",
            "type":"Services"
        }
    ],
    "sg:phone":"+1 418 681 3397",
    "sg:postcode":"G1N 3L8",
    "sg:province":"QC",
    "sg:tags":[
        "interior",
        "consultant",
        "design",
        "decorator"
    ],
    "wof:name":"Marc Desgagnes Designer",
    "wof:placetype":"venue"
},
  "geometry": {"coordinates":[-71.2430267334,46.8033981323],"type":"Point"}
}