{
  "type": "Feature",
  "properties": {
    "addr:full":"Vermilion Bay ON P0V 2V0",
    "addr:postcode":"p0v 2v0",
    "addr:street":"Vermilion Bay",
    "iso:country":"CA",
    "sg:city":"Vermilion Bay",
    "sg:classifiers":[
        {
            "category":"Shopping",
            "subcategory":"Bicycles & Sporting Goods",
            "type":"Retail Goods"
        }
    ],
    "sg:phone":"+1 807 227 2695",
    "sg:postcode":"P0V 2V0",
    "sg:province":"ON",
    "wof:name":"Bobby's Sport Shop",
    "wof:placetype":"venue"
},
  "geometry": {"coordinates":[-93.3945159912,49.8607177734],"type":"Point"}
}