{
  "type": "Feature",
  "properties": {
    "iso:country":"CA",
    "sg:address":"272 Breithaupt St",
    "sg:city":"Kitchener",
    "sg:classifiers":[
        {
            "category":"Retail",
            "subcategory":"Auto Repair",
            "type":"Services"
        }
    ],
    "sg:phone":"+1 519 743 3311",
    "sg:postcode":"N2H 5H5",
    "sg:province":"ON",
    "sg:tags":[
        "body",
        "automobile",
        "painting"
    ],
    "wof:name":"Discount Automotive",
    "wof:placetype":"venue"
},
  "geometry": {"coordinates":[-80.48811340330001,43.4583206177],"type":"Point"}
}