{
  "type": "Feature",
  "properties": {
    "addr:full":"1736 Weston Rd York ON M9N 1V6",
    "addr:housenumber":"1736",
    "addr:postcode":"m9n 1v6",
    "addr:street":"Weston Rd",
    "iso:country":"CA",
    "sg:address":"1736 Weston Rd",
    "sg:city":"York",
    "sg:classifiers":[
        {
            "category":"Organizations",
            "subcategory":"Religious Organization",
            "type":"Services"
        }
    ],
    "sg:phone":"+1 416 781 2940",
    "sg:postcode":"M9N 1V6",
    "sg:province":"ON",
    "sg:tags":[
        "church"
    ],
    "wof:name":"Grace Restoration Ministries",
    "wof:placetype":"venue"
},
  "geometry": {"coordinates":[-79.51066589360001,43.6979446411],"type":"Point"}
}