{
  "type": "Feature",
  "properties": {
    "addr:full":"831 Rue St-Joseph St-Barnabe-Nord QC G0X 2K0",
    "addr:housenumber":"831",
    "addr:postcode":"g0x 2k0",
    "addr:street":"Rue St-Joseph St-Barnabe-Nord",
    "iso:country":"CA",
    "sg:address":"831 Rue St-Joseph",
    "sg:city":"St-Barnabe-Nord",
    "sg:classifiers":[
        {
            "category":"Personal",
            "subcategory":"Beauty Salon",
            "type":"Services"
        }
    ],
    "sg:phone":"+1 819 264 5464",
    "sg:postcode":"G0X 2K0",
    "sg:province":"QC",
    "wof:name":"Salon Vivaldi Coiffure",
    "wof:placetype":"venue"
},
  "geometry": {"coordinates":[-72.880669,46.39481],"type":"Point"}
}