{
  "type": "Feature",
  "properties": {
    "addr:full":"190 Toryork Dr North York ON M9L 1X6",
    "addr:housenumber":"190",
    "addr:postcode":"m9l 1x6",
    "addr:street":"Toryork Dr",
    "iso:country":"CA",
    "sg:address":"190 Toryork Dr",
    "sg:city":"North York",
    "sg:classifiers":[
        {
            "category":"Restaurant",
            "type":"Food & Drink"
        }
    ],
    "sg:phone":"+1 416 749 2176",
    "sg:postcode":"M9L 1X6",
    "sg:province":"ON",
    "wof:name":"Papadeli",
    "wof:placetype":"venue"
},
  "geometry": {"coordinates":[-79.5587692261,43.760433197],"type":"Point"}
}