{
  "type": "Feature",
  "properties": {
    "iso:country":"CA",
    "sg:address":"293 Oxford St E",
    "sg:city":"London",
    "sg:classifiers":[
        {
            "category":"Banks & Credit Unions",
            "subcategory":"Investment Brokerage",
            "type":"Services"
        }
    ],
    "sg:phone":"+1 519 672 7878",
    "sg:postcode":"N6A 1V3",
    "sg:province":"ON",
    "sg:tags":[
        "consultant",
        "planning",
        "financial"
    ],
    "wof:name":"Creighton & Assoc",
    "wof:placetype":"venue"
},
  "geometry": {"coordinates":[-81.250069,42.996273],"type":"Point"}
}