{
  "type": "Feature",
  "properties": {
    "addr:full":"825 Rte Marie-Victorin Sorel-Tracy QC J3R 1L1",
    "addr:housenumber":"825",
    "addr:postcode":"j3r 1l1",
    "addr:street":"Rte Marie-Victorin",
    "iso:country":"CA",
    "sg:address":"825 Rte Marie-Victorin",
    "sg:city":"Sorel-Tracy",
    "sg:classifiers":[
        {
            "category":"Home & Garden",
            "subcategory":"Building Materials",
            "type":"Retail Goods"
        }
    ],
    "sg:phone":"+1 450 743 5551",
    "sg:postcode":"J3R 1L1",
    "sg:province":"QC",
    "sg:tags":[
        "glass",
        "window",
        "plate"
    ],
    "wof:name":"Vitrerie Ent Mg Duchesne Inc",
    "wof:placetype":"venue"
},
  "geometry": {"coordinates":[-73.12670900000001,46.0401],"type":"Point"}
}