{
  "type": "Feature",
  "properties": {
    "addr:full":"2840 Boul Saint-Martin E Laval QC H7E 5A1",
    "addr:housenumber":"2840",
    "addr:postcode":"h7e 5a1",
    "addr:street":"Boul Saint-Martin E",
    "iso:country":"CA",
    "sg:address":"2840 Boul Saint-Martin E",
    "sg:city":"Laval",
    "sg:classifiers":[
        {
            "category":"Personal",
            "subcategory":"Beauty Salon",
            "type":"Services"
        }
    ],
    "sg:phone":"+1 450 664 4074",
    "sg:postcode":"H7E 5A1",
    "sg:province":"QC",
    "wof:name":"Vag Coiffure",
    "wof:placetype":"venue"
},
  "geometry": {"coordinates":[-73.6818695068,45.5999336243],"type":"Point"}
}