{
  "type": "Feature",
  "properties": {
    "addr:full":"2309 Cape Horn Ave Coquitlam BC V3K 1J6",
    "addr:housenumber":"2309",
    "addr:postcode":"v3k 1j6",
    "addr:street":"Cape Horn Ave",
    "iso:country":"CA",
    "sg:address":"2309 Cape Horn Ave",
    "sg:city":"Coquitlam",
    "sg:classifiers":[
        {
            "category":"Building & Trades",
            "subcategory":"Cleaning & Sanitation",
            "type":"Services"
        }
    ],
    "sg:phone":"+1 604 540 2275",
    "sg:postcode":"V3K 1J6",
    "sg:province":"BC",
    "sg:tags":[
        "janitor"
    ],
    "wof:name":"Fidelity Building Mntnce",
    "wof:placetype":"venue"
},
  "geometry": {"coordinates":[-122.830704,49.233562],"type":"Point"}
}