{
  "type": "Feature",
  "properties": {
    "addr:full":"22714 Dewdney Trunk Rd Maple Ridge BC V2X 3K2",
    "addr:housenumber":"22714",
    "addr:postcode":"v2x 3k2",
    "addr:street":"Dewdney Trunk Rd",
    "iso:country":"CA",
    "sg:address":"22714 Dewdney Trunk Rd",
    "sg:city":"Maple Ridge",
    "sg:classifiers":[
        {
            "category":"Retail",
            "subcategory":"Repair Shop",
            "type":"Services"
        }
    ],
    "sg:phone":"+1 604 467 4322",
    "sg:postcode":"V2X 3K2",
    "sg:province":"BC",
    "sg:tags":[
        "television",
        "radio"
    ],
    "wof:name":"Hart's Tv & Stereo",
    "wof:placetype":"venue"
},
  "geometry": {"coordinates":[-122.592849731,49.2202835083],"type":"Point"}
}