{
  "type": "Feature",
  "properties": {
    "addr:full":"Vancouver BC V6Z 2S5",
    "addr:postcode":"v6z 2s5",
    "iso:country":"CA",
    "sg:city":"Vancouver",
    "sg:classifiers":[
        {
            "category":"Retail",
            "subcategory":"Car Wash",
            "type":"Services"
        }
    ],
    "sg:phone":"+1 604 689 9264",
    "sg:postcode":"V6Z 2S5",
    "sg:province":"BC",
    "sg:tags":[
        "polishing",
        "washing"
    ],
    "wof:name":"Classic Car Wash Ltd",
    "wof:placetype":"venue"
},
  "geometry": {"coordinates":[-123.126319885,49.2798309326],"type":"Point"}
}