{
  "type": "Feature",
  "properties": {
    "addr:full":"157 Rue Notre-Dame O Victoriaville QC G6P 1R8",
    "addr:housenumber":"157",
    "addr:postcode":"g6p 1r8",
    "addr:street":"Rue Notre-Dame O",
    "iso:country":"CA",
    "sg:address":"157 Rue Notre-Dame O",
    "sg:city":"Victoriaville",
    "sg:classifiers":[
        {
            "category":"Restaurant",
            "type":"Food & Drink"
        }
    ],
    "sg:phone":"+1 819 752 5550",
    "sg:postcode":"G6P 1R8",
    "sg:province":"QC",
    "wof:name":"Restaurant Victo Victoria",
    "wof:placetype":"venue"
},
  "geometry": {"coordinates":[-71.955551,46.05669],"type":"Point"}
}