{
  "type": "Feature",
  "properties": {
    "addr:full":"11908 Hawthorne St Maple Ridge BC V2X 6V4",
    "addr:housenumber":"11908",
    "addr:postcode":"v2x 6v4",
    "addr:street":"Hawthorne St",
    "iso:country":"CA",
    "sg:address":"11908 Hawthorne St",
    "sg:city":"Maple Ridge",
    "sg:classifiers":[
        {
            "category":"Building & Trades",
            "subcategory":"Electrical",
            "type":"Services"
        }
    ],
    "sg:phone":"+1 604 466 5775",
    "sg:postcode":"V2X 6V4",
    "sg:province":"BC",
    "sg:tags":[
        "electric",
        "contractor"
    ],
    "wof:name":"Meyer Electric",
    "wof:placetype":"venue"
},
  "geometry": {"coordinates":[-122.576981,49.218674],"type":"Point"}
}