{
  "type": "Feature",
  "properties": {
    "addr:full":"2805 Kingsway Vancouver BC V5R 5H9",
    "addr:housenumber":"2805",
    "addr:postcode":"v5r 5h9",
    "addr:street":"Kingsway",
    "iso:country":"CA",
    "sg:address":"2805 Kingsway",
    "sg:city":"Vancouver",
    "sg:classifiers":[
        {
            "category":"Health Services",
            "subcategory":"Clinic",
            "type":"Services"
        }
    ],
    "sg:phone":"+1 604 451 5511",
    "sg:postcode":"V5R 5H9",
    "sg:province":"BC",
    "sg:tags":[
        "agency",
        "welfare"
    ],
    "wof:name":"Childrens Rehabilitation Assn",
    "wof:placetype":"venue"
},
  "geometry": {"coordinates":[-123.047370911,49.2370948792],"type":"Point"}
}