{
  "type": "Feature",
  "properties": {
    "addr:full":"5205 Boul Decarie Montreal QC H3W 3C2",
    "addr:housenumber":"5205",
    "addr:postcode":"h3w 3c2",
    "addr:street":"Boul Decarie",
    "iso:country":"CA",
    "sg:address":"5205 Boul Decarie",
    "sg:city":"Montreal",
    "sg:classifiers":[
        {
            "category":"Shopping",
            "subcategory":"Florist",
            "type":"Retail Goods"
        }
    ],
    "sg:phone":"+1 514 484 8221",
    "sg:postcode":"H3W 3C2",
    "sg:province":"QC",
    "wof:name":"Fleuriste Main",
    "wof:placetype":"venue"
},
  "geometry": {"coordinates":[-73.63063,45.484692],"type":"Point"}
}