{
  "type": "Feature",
  "properties": {
    "addr:full":"555 1st St S Ste Rose Du Lac MB R0L 1S0",
    "addr:housenumber":"555",
    "addr:postcode":"r0l 1s0",
    "addr:street":"1St St S Ste Rose Du Lac",
    "iso:country":"CA",
    "sg:address":"555 1st St S",
    "sg:city":"Ste Rose Du Lac",
    "sg:classifiers":[
        {
            "category":"Recreation",
            "type":"Entertainment"
        }
    ],
    "sg:phone":"+1 204 447 3201",
    "sg:postcode":"R0L 1S0",
    "sg:province":"MB",
    "sg:tags":[
        "club",
        "curling"
    ],
    "wof:name":"Ste Rose Curling Rink",
    "wof:placetype":"venue"
},
  "geometry": {"coordinates":[-99.5232009888,51.0591850281],"type":"Point"}
}