{
  "type": "Feature",
  "properties": {
    "addr:full":"2749 Danforth Ave Toronto ON M4C 1L8",
    "addr:housenumber":"2749",
    "addr:postcode":"m4c 1l8",
    "addr:street":"Danforth Ave",
    "iso:country":"CA",
    "sg:address":"2749 Danforth Ave",
    "sg:city":"Toronto",
    "sg:classifiers":[
        {
            "category":"Banks & Credit Unions",
            "subcategory":"Bank",
            "type":"Services"
        }
    ],
    "sg:phone":"+1 416 691 9523",
    "sg:postcode":"M4C 1L8",
    "sg:province":"ON",
    "sg:tags":[
        "financing",
        "loan"
    ],
    "wof:name":"Stop N Cash",
    "wof:placetype":"venue"
},
  "geometry": {"coordinates":[-79.2975769043,43.6889724731],"type":"Point"}
}