{
  "type": "Feature",
  "properties": {
    "addr:full":"1080 Finch Ave E North York ON M2J 2X2",
    "addr:housenumber":"1080",
    "addr:postcode":"m2j 2x2",
    "addr:street":"Finch Ave E",
    "iso:country":"CA",
    "sg:address":"1080 Finch Ave E",
    "sg:city":"North York",
    "sg:classifiers":[
        {
            "category":"Organizations",
            "subcategory":"Religious Organization",
            "type":"Services"
        }
    ],
    "sg:phone":"+1 416 494 2442",
    "sg:postcode":"M2J 2X2",
    "sg:province":"ON",
    "sg:tags":[
        "church"
    ],
    "wof:name":"St Cyprian's Anglican Church",
    "wof:placetype":"venue"
},
  "geometry": {"coordinates":[-79.3634185791,43.7908821106],"type":"Point"}
}