{
  "type": "Feature",
  "properties": {
    "addr:full":"14 Main St Maxville ON K0C 1T0",
    "addr:housenumber":"14",
    "addr:postcode":"k0c 1t0",
    "addr:street":"Main St",
    "iso:country":"CA",
    "sg:address":"14 Main St",
    "sg:city":"Maxville",
    "sg:classifiers":[
        {
            "category":"Shopping",
            "subcategory":"Gifts & Souvenirs",
            "type":"Retail Goods"
        }
    ],
    "sg:phone":"+1 613 527 2800",
    "sg:postcode":"K0C 1T0",
    "sg:province":"ON",
    "sg:tags":[
        "shop"
    ],
    "wof:name":"Debbie's Country Corner",
    "wof:placetype":"venue"
},
  "geometry": {"coordinates":[-74.8562164307,45.2890396118],"type":"Point"}
}