{
  "type": "Feature",
  "properties": {
    "addr:full":"17 Young St Capreol ON P0M 1H0",
    "addr:housenumber":"17",
    "addr:postcode":"p0m 1h0",
    "addr:street":"Young St",
    "iso:country":"CA",
    "sg:address":"17 Young St",
    "sg:city":"Capreol",
    "sg:classifiers":[
        {
            "category":"Shopping",
            "subcategory":"Clothing, Apparel, & Fashions",
            "type":"Retail Goods"
        }
    ],
    "sg:phone":"+1 705 858 1866",
    "sg:postcode":"P0M 1H0",
    "sg:province":"ON",
    "wof:name":"Lynn's Place",
    "wof:placetype":"venue"
},
  "geometry": {"coordinates":[-80.9269332886,46.7096443176],"type":"Point"}
}