{
  "type": "Feature",
  "properties": {
    "addr:full":"2642 Rue Notre-Dame O Montreal QC H3J 1N7",
    "addr:housenumber":"2642",
    "addr:postcode":"h3j 1n7",
    "addr:street":"Rue Notre-Dame O",
    "iso:country":"CA",
    "sg:address":"2642 Rue Notre-Dame O",
    "sg:city":"Montreal",
    "sg:classifiers":[
        {
            "category":"Home & Garden",
            "subcategory":"Building Materials",
            "type":"Retail Goods"
        }
    ],
    "sg:phone":"+1 514 933 8439",
    "sg:postcode":"H3J 1N7",
    "sg:province":"QC",
    "sg:tags":[
        "glass",
        "window",
        "plate"
    ],
    "wof:name":"Vitrerie Raymond Inc",
    "wof:placetype":"venue"
},
  "geometry": {"coordinates":[-73.543296814,45.5309753418],"type":"Point"}
}