{
  "type": "Feature",
  "properties": {
    "addr:full":"18 Rue Sainte-Ursule Quebec QC G1R 4C9",
    "addr:housenumber":"18",
    "addr:postcode":"g1r 4c9",
    "addr:street":"Rue Sainte-Ursule",
    "iso:country":"CA",
    "sg:address":"18 Rue Sainte-Ursule",
    "sg:city":"Quebec",
    "sg:classifiers":[
        {
            "category":"Travel",
            "subcategory":"Hotels & Motels",
            "type":"Entertainment"
        }
    ],
    "sg:phone":"+1 418 692 9953",
    "sg:postcode":"G1R 4C9",
    "sg:province":"QC",
    "wof:name":"Manoir LA Salle",
    "wof:placetype":"venue"
},
  "geometry": {"coordinates":[-71.21147155760001,46.8121604919],"type":"Point"}
}