{
  "type": "Feature",
  "properties": {
    "addr:full":"79 James St S Hamilton ON L8P 2Z1",
    "addr:housenumber":"79",
    "addr:postcode":"l8p 2z1",
    "addr:street":"James St S",
    "iso:country":"CA",
    "sg:address":"79 James St S",
    "sg:city":"Hamilton",
    "sg:classifiers":[
        {
            "category":"Social Services",
            "subcategory":"Job Training",
            "type":"Services"
        }
    ],
    "sg:phone":"+1 905 317 4934",
    "sg:postcode":"L8P 2Z1",
    "sg:province":"ON",
    "sg:tags":[
        "career",
        "counseling",
        "vocational"
    ],
    "wof:name":"Ymca Career Dev & Learning",
    "wof:placetype":"venue"
},
  "geometry": {"coordinates":[-79.8700256348,43.2543067932],"type":"Point"}
}