{
  "type": "Feature",
  "properties": {
    "addr:full":"1788 Jane St York ON M9N 2T2",
    "addr:housenumber":"1788",
    "addr:postcode":"m9n 2t2",
    "addr:street":"Jane St",
    "iso:country":"CA",
    "sg:address":"1788 Jane St",
    "sg:city":"York",
    "sg:classifiers":[
        {
            "category":"Restaurant",
            "type":"Food & Drink"
        }
    ],
    "sg:phone":"+1 416 240 0707",
    "sg:postcode":"M9N 2T2",
    "sg:province":"ON",
    "sg:tags":[
        "pizza"
    ],
    "wof:name":"Papino's Pizza",
    "wof:placetype":"venue"
},
  "geometry": {"coordinates":[-79.5048751831,43.706199646],"type":"Point"}
}