{
  "type": "Feature",
  "properties": {
    "addr:full":"76 Prospect St Newmarket ON L3Y 3T2",
    "addr:housenumber":"76",
    "addr:postcode":"l3y 3t2",
    "addr:street":"Prospect St",
    "iso:country":"CA",
    "sg:address":"76 Prospect St",
    "sg:city":"Newmarket",
    "sg:classifiers":[
        {
            "category":"Real Estate",
            "subcategory":"Real Estate Agent",
            "type":"Services"
        }
    ],
    "sg:phone":"+1 905 898 2384",
    "sg:postcode":"L3Y 3T2",
    "sg:province":"ON",
    "sg:tags":[
        "management"
    ],
    "wof:name":"Devotti Property Management",
    "wof:placetype":"venue"
},
  "geometry": {"coordinates":[-79.4537734985,44.0579910278],"type":"Point"}
}