{
  "type": "Feature",
  "properties": {
    "addr:full":"Outremont QC H2V 1V7",
    "addr:postcode":"h2v 1v7",
    "iso:country":"CA",
    "sg:city":"Outremont",
    "sg:classifiers":[
        {
            "category":"Manufacturing",
            "subcategory":"Printing",
            "type":"Manufacturing & Wholesale Goods"
        }
    ],
    "sg:phone":"+1 514 276 2949",
    "sg:postcode":"H2V 1V7",
    "sg:province":"QC",
    "sg:tags":[
        "publisher"
    ],
    "wof:name":"Ariane Editions Inc",
    "wof:placetype":"venue"
},
  "geometry": {"coordinates":[-73.6086425781,45.5204696655],"type":"Point"}
}