{
  "type": "Feature",
  "properties": {
    "addr:full":"4080 Vanguard Rd Richmond BC V6X 2P4",
    "addr:housenumber":"4080",
    "addr:postcode":"v6x 2p4",
    "addr:street":"Vanguard Rd",
    "iso:country":"CA",
    "sg:address":"4080 Vanguard Rd",
    "sg:city":"Richmond",
    "sg:classifiers":[
        {
            "category":"Professional",
            "subcategory":"Business Services",
            "type":"Services"
        }
    ],
    "sg:phone":"+1 604 273 6715",
    "sg:postcode":"V6X 2P4",
    "sg:province":"BC",
    "sg:tags":[
        "auctioneer"
    ],
    "wof:name":"Marvel Auctions Ltd",
    "wof:placetype":"venue"
},
  "geometry": {"coordinates":[-123.100639,49.182976],"type":"Point"}
}