{
  "type": "Feature",
  "properties": {
    "iso:country":"CA",
    "sg:address":"11316 134 Ave NW",
    "sg:city":"Edmonton",
    "sg:classifiers":[
        {
            "category":"Food & Beverages",
            "subcategory":"Groceries & Convenience Stores",
            "type":"Retail Goods"
        }
    ],
    "sg:phone":"+1 780 475 4909",
    "sg:postcode":"T5E 1K5",
    "sg:province":"AB",
    "sg:tags":[
        "grocer"
    ],
    "wof:name":"Elsafadi Brothers Super Market",
    "wof:placetype":"venue"
},
  "geometry": {"coordinates":[-113.516159058,53.5950584412],"type":"Point"}
}