{
  "type": "Feature",
  "properties": {
    "addr:full":"Gordon Island Magnetawan ON P0A 1P0",
    "addr:postcode":"p0a 1p0",
    "addr:street":"Gordon Island",
    "iso:country":"CA",
    "sg:address":"Gordon Island",
    "sg:city":"Magnetawan",
    "sg:classifiers":[
        {
            "category":"Travel",
            "subcategory":"Hotels & Motels",
            "type":"Entertainment"
        }
    ],
    "sg:phone":"+1 705 387 0181",
    "sg:postcode":"P0A 1P0",
    "sg:province":"ON",
    "sg:tags":[
        "resort"
    ],
    "wof:name":"Rockwynn Lodge",
    "wof:placetype":"venue"
},
  "geometry": {"coordinates":[-79.629921,45.671268],"type":"Point"}
}