{
  "type": "Feature",
  "properties": {
    "addr:full":"18 Ontario St Port Hope ON L1A 2T6",
    "addr:housenumber":"18",
    "addr:postcode":"l1a 2t6",
    "addr:street":"Ontario St",
    "iso:country":"CA",
    "sg:address":"18 Ontario St",
    "sg:city":"Port Hope",
    "sg:classifiers":[
        {
            "category":"Food & Beverages",
            "subcategory":"Groceries & Convenience Stores",
            "type":"Retail Goods"
        }
    ],
    "sg:phone":"+1 905 885 9900",
    "sg:postcode":"L1A 2T6",
    "sg:province":"ON",
    "sg:tags":[
        "product"
    ],
    "wof:name":"Sun Tree Foods",
    "wof:placetype":"venue"
},
  "geometry": {"coordinates":[-78.294121,43.951962],"type":"Point"}
}