{
  "type": "Feature",
  "properties": {
    "addr:full":"3655 Rue Isabelle Brossard QC J4Y 2R2",
    "addr:housenumber":"3655",
    "addr:postcode":"j4y 2r2",
    "addr:street":"Rue Isabelle",
    "iso:country":"CA",
    "sg:address":"3655 Rue Isabelle",
    "sg:city":"Brossard",
    "sg:classifiers":[
        {
            "category":"Manufacturing",
            "subcategory":"Tools & Machinery",
            "type":"Manufacturing & Wholesale Goods"
        }
    ],
    "sg:phone":"+1 450 444 8669",
    "sg:postcode":"J4Y 2R2",
    "sg:province":"QC",
    "sg:tags":[
        "machine",
        "shop"
    ],
    "wof:name":"Jermac Precision Inc",
    "wof:placetype":"venue"
},
  "geometry": {"coordinates":[-73.464798,45.427731],"type":"Point"}
}