{
  "type": "Feature",
  "properties": {
    "addr:full":"2697 Hughes Rd Kingston ON K7L 4V3",
    "addr:housenumber":"2697",
    "addr:postcode":"k7l 4v3",
    "addr:street":"Hughes Rd",
    "iso:country":"CA",
    "sg:address":"2697 Hughes Rd",
    "sg:city":"Kingston",
    "sg:classifiers":[
        {
            "category":"Building & Trades",
            "subcategory":"Plumbing",
            "type":"Services"
        }
    ],
    "sg:phone":"+1 613 542 0774",
    "sg:postcode":"K7L 4V3",
    "sg:province":"ON",
    "sg:tags":[
        "contractor"
    ],
    "wof:name":"Ubdegrove Plumbing & Heating",
    "wof:placetype":"venue"
},
  "geometry": {"coordinates":[-76.3907775879,44.3314094543],"type":"Point"}
}