{
  "type": "Feature",
  "properties": {
    "addr:full":"14628 Southview Dr Surrey BC V3S 1A4",
    "addr:housenumber":"14628",
    "addr:postcode":"v3s 1a4",
    "addr:street":"Southview Dr",
    "iso:country":"CA",
    "sg:address":"14628 Southview Dr",
    "sg:city":"Surrey",
    "sg:classifiers":[
        {
            "category":"Manufacturing",
            "subcategory":"Signs",
            "type":"Manufacturing & Wholesale Goods"
        }
    ],
    "sg:phone":"+1 604 532 1877",
    "sg:postcode":"V3S 1A4",
    "sg:province":"BC",
    "wof:name":"Moran Signs",
    "wof:placetype":"venue"
},
  "geometry": {"coordinates":[-122.81703899999999,49.101566],"type":"Point"}
}