{
  "type": "Feature",
  "properties": {
    "addr:full":"745 Rifle Rd Kelowna BC V1V 2H7",
    "addr:housenumber":"745",
    "addr:postcode":"v1v 2h7",
    "addr:street":"Rifle Rd",
    "iso:country":"CA",
    "sg:address":"745 Rifle Rd",
    "sg:city":"Kelowna",
    "sg:classifiers":[
        {
            "category":"Farming",
            "subcategory":"Farm",
            "type":"Manufacturing & Wholesale Goods"
        }
    ],
    "sg:phone":"+1 250 861 4774",
    "sg:postcode":"V1V 2H7",
    "sg:province":"BC",
    "sg:tags":[
        "mushroom"
    ],
    "wof:name":"Francis Mushrooms Ltd",
    "wof:placetype":"venue"
},
  "geometry": {"coordinates":[-119.422729,49.903271],"type":"Point"}
}