{
  "type": "Feature",
  "properties": {
    "iso:country":"CA",
    "sg:address":"2210 Bank St",
    "sg:city":"Ottawa",
    "sg:classifiers":[
        {
            "category":"Cinema",
            "subcategory":"Movie Rental",
            "type":"Entertainment"
        }
    ],
    "sg:phone":"+1 613 731 7672",
    "sg:postcode":"K1V 1J5",
    "sg:province":"ON",
    "sg:tags":[
        "leasing",
        "video",
        "disc",
        "tape"
    ],
    "wof:name":"Blockbuster Video",
    "wof:placetype":"venue"
},
  "geometry": {"coordinates":[-75.6543502808,45.3574905396],"type":"Point"}
}