{
  "type": "Feature",
  "properties": {
    "addr:full":"185 Rue Turgeon Sainte-Therese QC J7E 3J4",
    "addr:housenumber":"185",
    "addr:postcode":"j7e 3j4",
    "addr:street":"Rue Turgeon Sainte-Therese",
    "iso:country":"CA",
    "sg:address":"185 Rue Turgeon",
    "sg:city":"Sainte-Therese",
    "sg:classifiers":[
        {
            "category":"Health Services",
            "subcategory":"Doctor",
            "type":"Services"
        }
    ],
    "sg:phone":"+1 450 430 6985",
    "sg:postcode":"J7E 3J4",
    "sg:province":"QC",
    "sg:tags":[
        "dentist"
    ],
    "wof:name":"Tremblay, Louise DDS",
    "wof:placetype":"venue"
},
  "geometry": {"coordinates":[-73.83215300000001,45.632881],"type":"Point"}
}