{
  "type": "Feature",
  "properties": {
    "addr:full":"501 Ch Cochrane Compton QC J0B 1L0",
    "addr:housenumber":"501",
    "addr:postcode":"j0b 1l0",
    "addr:street":"Ch Cochrane",
    "iso:country":"CA",
    "sg:address":"501 Ch Cochrane",
    "sg:city":"Compton",
    "sg:classifiers":[
        {
            "category":"Farming",
            "subcategory":"Farm",
            "type":"Manufacturing & Wholesale Goods"
        }
    ],
    "sg:phone":"+1 819 849 4372",
    "sg:postcode":"J0B 1L0",
    "sg:province":"QC",
    "wof:name":"Girard, Christian",
    "wof:placetype":"venue"
},
  "geometry": {"coordinates":[-71.789688,45.179131],"type":"Point"}
}