{
  "type": "Feature",
  "properties": {
    "addr:full":"5012 48 St Yellowknife NT X1A 1N3",
    "addr:housenumber":"5012",
    "addr:postcode":"x1a 1n3",
    "addr:street":"48 St",
    "iso:country":"CA",
    "sg:address":"5012 48 St",
    "sg:city":"Yellowknife",
    "sg:classifiers":[
        {
            "category":"Shopping",
            "subcategory":"Stationery & Office Supplies",
            "type":"Retail Goods"
        }
    ],
    "sg:phone":"+1 867 920 2486",
    "sg:postcode":"X1A 1N3",
    "sg:province":"NT",
    "wof:name":"Creative Basics",
    "wof:placetype":"venue"
},
  "geometry": {"coordinates":[-114.369118,62.454826],"type":"Point"}
}