{
  "type": "Feature",
  "properties": {
    "iso:country":"CA",
    "sg:city":"Souris",
    "sg:classifiers":[
        {
            "category":"Personal",
            "subcategory":"Beauty Salon",
            "type":"Services"
        }
    ],
    "sg:phone":"+1 902 687 3500",
    "sg:postcode":"C0A 2B0",
    "sg:province":"PE",
    "wof:name":"Classique Hair & Tanning Salon",
    "wof:placetype":"venue"
},
  "geometry": {"coordinates":[-62.252910614,46.3543205261],"type":"Point"}
}