{
  "type": "Feature",
  "properties": {
    "addr:full":"Calgary AB T2G 4X4",
    "addr:postcode":"t2g 4x4",
    "iso:country":"CA",
    "sg:city":"Calgary",
    "sg:phone":"+1 403 243 5111",
    "sg:postcode":"T2G 4X4",
    "sg:province":"AB",
    "sg:tags":[
        "scoreboard"
    ],
    "wof:name":"Centaur Products Inc",
    "wof:placetype":"venue"
},
  "geometry": {"coordinates":[-114.039169312,51.013835907],"type":"Point"}
}