{
  "type": "Feature",
  "properties": {
    "iso:country":"CA",
    "sg:city":"Hampstead",
    "sg:classifiers":[
        {
            "category":"Real Estate",
            "subcategory":"Real Estate Agent",
            "type":"Services"
        }
    ],
    "sg:phone":"+1 514 484 8420",
    "sg:postcode":"H3X 3E3",
    "sg:province":"QC",
    "wof:name":"Services Immobiliers Lupu Ltee",
    "wof:placetype":"venue"
},
  "geometry": {"coordinates":[-73.645652771,45.4838142395],"type":"Point"}
}