{
  "type": "Feature",
  "properties": {
    "addr:full":"726 Rue Du Conseil Sherbrooke QC J1G 1K9",
    "addr:housenumber":"726",
    "addr:postcode":"j1g 1k9",
    "addr:street":"Rue Du Conseil",
    "iso:country":"CA",
    "sg:address":"726 Rue Du Conseil",
    "sg:city":"Sherbrooke",
    "sg:classifiers":[
        {
            "category":"Retail",
            "subcategory":"Auto Repair",
            "type":"Services"
        }
    ],
    "sg:phone":"+1 819 564 2844",
    "sg:postcode":"J1G 1K9",
    "sg:province":"QC",
    "sg:tags":[
        "repairing",
        "automobile"
    ],
    "wof:name":"Mecanique Conseil",
    "wof:placetype":"venue"
},
  "geometry": {"coordinates":[-71.873085,45.403507],"type":"Point"}
}