{
  "type": "Feature",
  "properties": {
    "addr:full":"234 Knobel St Foam Lake SK S0A 1A0",
    "addr:housenumber":"234",
    "addr:postcode":"s0a 1a0",
    "addr:street":"Knobel St",
    "iso:country":"CA",
    "sg:address":"234 Knobel St",
    "sg:city":"Foam Lake",
    "sg:classifiers":[
        {
            "category":"Local Transit",
            "type":"Transportation"
        }
    ],
    "sg:phone":"+1 306 272 3622",
    "sg:postcode":"S0A 1A0",
    "sg:province":"SK",
    "sg:tags":[
        "ambulance"
    ],
    "wof:name":"Shamrock Ambulance Care Inc",
    "wof:placetype":"venue"
},
  "geometry": {"coordinates":[-103.53939099999999,51.639305],"type":"Point"}
}