{
  "type": "Feature",
  "properties": {
    "addr:full":"13191 Princess St Richmond BC V7E 3S1",
    "addr:housenumber":"13191",
    "addr:postcode":"v7e 3s1",
    "addr:street":"Princess St",
    "iso:country":"CA",
    "sg:address":"13191 Princess St",
    "sg:city":"Richmond",
    "sg:classifiers":[
        {
            "category":"Manufacturing",
            "subcategory":"Food",
            "type":"Manufacturing & Wholesale Goods"
        }
    ],
    "sg:phone":"+1 604 272 5758",
    "sg:postcode":"V7E 3S1",
    "sg:province":"BC",
    "sg:tags":[
        "product",
        "manufacturer"
    ],
    "wof:name":"Soo Singapore Jerky Ltd",
    "wof:placetype":"venue"
},
  "geometry": {"coordinates":[-123.156143188,49.1175117493],"type":"Point"}
}