{
  "type": "Feature",
  "properties": {
    "iso:country":"CA",
    "sg:city":"Gatineau",
    "sg:classifiers":[
        {
            "category":"Wholesale",
            "subcategory":"Non-durable Goods",
            "type":"Manufacturing & Wholesale Goods"
        }
    ],
    "sg:phone":"+1 819 243 8583",
    "sg:postcode":"J8T 5L7",
    "sg:province":"QC",
    "sg:tags":[
        "water"
    ],
    "wof:name":"Cascade D'Eau Pure",
    "wof:placetype":"venue"
},
  "geometry": {"coordinates":[-75.710487,45.427853],"type":"Point"}
}