{
  "type": "Feature",
  "properties": {
    "addr:full":"4624 2 Ave Edson AB T7E 1C1",
    "addr:housenumber":"4624",
    "addr:postcode":"t7e 1c1",
    "addr:street":"2 Ave",
    "iso:country":"CA",
    "sg:address":"4624 2 Ave",
    "sg:city":"Edson",
    "sg:classifiers":[
        {
            "category":"Autos & Motor Vehicles",
            "subcategory":"Recreational Vehicle Sales",
            "type":"Retail Goods"
        }
    ],
    "sg:phone":"+1 780 723 2355",
    "sg:postcode":"T7E 1C1",
    "sg:province":"AB",
    "wof:name":"Happy Camper Rv",
    "wof:placetype":"venue"
},
  "geometry": {"coordinates":[-116.422050476,53.5840797424],"type":"Point"}
}