{
  "type": "Feature",
  "properties": {
    "addr:full":"Surrey BC V4N 4A9",
    "addr:postcode":"v4n 4a9",
    "iso:country":"CA",
    "sg:city":"Surrey",
    "sg:classifiers":[
        {
            "category":"Organizations",
            "subcategory":"Religious Organization",
            "type":"Services"
        }
    ],
    "sg:phone":"+1 604 581 8242",
    "sg:postcode":"V4N 4A9",
    "sg:province":"BC",
    "sg:tags":[
        "church"
    ],
    "wof:name":"Child Evangelism Fellowship",
    "wof:placetype":"venue"
},
  "geometry": {"coordinates":[-122.733261,49.177113],"type":"Point"}
}