{
  "type": "Feature",
  "properties": {
    "addr:full":"Dorset ON P0A 1E0",
    "addr:postcode":"p0a 1e0",
    "iso:country":"CA",
    "sg:city":"Dorset",
    "sg:classifiers":[
        {
            "category":"Building & Trades",
            "subcategory":"Plumbing",
            "type":"Services"
        }
    ],
    "sg:phone":"+1 705 766 9659",
    "sg:postcode":"P0A 1E0",
    "sg:province":"ON",
    "sg:tags":[
        "excavating",
        "tank",
        "septic",
        "contractor"
    ],
    "wof:name":"R Keown Haulage",
    "wof:placetype":"venue"
},
  "geometry": {"coordinates":[-78.896034,45.239559],"type":"Point"}
}