{
  "type": "Feature",
  "properties": {
    "addr:full":"67 Water St Windsor NS B0N 2T0",
    "addr:housenumber":"67",
    "addr:postcode":"b0n 2t0",
    "addr:street":"Water St",
    "iso:country":"CA",
    "sg:address":"67 Water St",
    "sg:city":"Windsor",
    "sg:classifiers":[
        {
            "category":"Personal",
            "subcategory":"Beauty Salon",
            "type":"Services"
        }
    ],
    "sg:phone":"+1 902 798 5253",
    "sg:postcode":"B0N 2T0",
    "sg:province":"NS",
    "wof:name":"One on One Hairstyling",
    "wof:placetype":"venue"
},
  "geometry": {"coordinates":[-64.13896200000001,44.994965],"type":"Point"}
}