{
  "type": "Feature",
  "properties": {
    "addr:full":"3989 Main St Niagara Falls ON L2G 6B9",
    "addr:housenumber":"3989",
    "addr:postcode":"l2g 6b9",
    "addr:street":"Main St",
    "iso:country":"CA",
    "sg:address":"3989 Main St",
    "sg:city":"Niagara Falls",
    "sg:classifiers":[
        {
            "category":"Health Services",
            "subcategory":"Doctor",
            "type":"Services"
        }
    ],
    "sg:phone":"+1 905 295 3011",
    "sg:postcode":"L2G 6B9",
    "sg:province":"ON",
    "sg:tags":[
        "dentist"
    ],
    "wof:name":"Spencer, William J DDS",
    "wof:placetype":"venue"
},
  "geometry": {"coordinates":[-79.055679,43.055286],"type":"Point"}
}