{
  "type": "Feature",
  "properties": {
    "addr:full":"931 Oxford St E London ON N5Y 3K1",
    "addr:housenumber":"931",
    "addr:postcode":"n5y 3k1",
    "addr:street":"Oxford St E",
    "iso:country":"CA",
    "sg:address":"931 Oxford St E",
    "sg:city":"London",
    "sg:classifiers":[
        {
            "category":"Restaurant",
            "type":"Food & Drink"
        }
    ],
    "sg:phone":"+1 519 453 8888",
    "sg:postcode":"N5Y 3K1",
    "sg:province":"ON",
    "wof:name":"Dragon Court Restaurant",
    "wof:placetype":"venue"
},
  "geometry": {"coordinates":[-81.225838,43.003399],"type":"Point"}
}