{
  "type": "Feature",
  "properties": {
    "addr:full":"42 Wakopa Pl Winnipeg MB R2M 5H2",
    "addr:housenumber":"42",
    "addr:postcode":"r2m 5h2",
    "addr:street":"Wakopa Pl",
    "iso:country":"CA",
    "sg:address":"42 Wakopa Pl",
    "sg:city":"Winnipeg",
    "sg:classifiers":[
        {
            "category":"Professional",
            "subcategory":"Business Services",
            "type":"Services"
        }
    ],
    "sg:phone":"+1 204 253 2194",
    "sg:postcode":"R2M 5H2",
    "sg:province":"MB",
    "sg:tags":[
        "fund",
        "promotion",
        "raising"
    ],
    "wof:name":"Check Promotions",
    "wof:placetype":"venue"
},
  "geometry": {"coordinates":[-97.1044921875,49.8315925598],"type":"Point"}
}