{
  "type": "Feature",
  "properties": {
    "addr:full":"840 Av Du Moulin Saint-Joseph-DE-Beauce QC G0S 2V0",
    "addr:housenumber":"840",
    "addr:postcode":"g0s 2v0",
    "addr:street":"Av Du Moulin",
    "iso:country":"CA",
    "sg:address":"840 Av Du Moulin",
    "sg:city":"Saint-Joseph-DE-Beauce",
    "sg:classifiers":[
        {
            "category":"Health Services",
            "subcategory":"Nursing And Care Facility",
            "type":"Services"
        }
    ],
    "sg:phone":"+1 418 397 5400",
    "sg:postcode":"G0S 2V0",
    "sg:province":"QC",
    "sg:tags":[
        "home",
        "retirement",
        "community"
    ],
    "wof:name":"Villa Du Moulin",
    "wof:placetype":"venue"
},
  "geometry": {"coordinates":[-70.880753,46.307182],"type":"Point"}
}