{
  "type": "Feature",
  "properties": {
    "addr:full":"1000 Rue Moreau O Alma QC G8B 4V7",
    "addr:housenumber":"1000",
    "addr:postcode":"g8b 4v7",
    "addr:street":"Rue Moreau O",
    "iso:country":"CA",
    "sg:address":"1000 Rue Moreau O",
    "sg:city":"Alma",
    "sg:classifiers":[
        {
            "category":"Professional",
            "subcategory":"Research",
            "type":"Services"
        }
    ],
    "sg:phone":"+1 418 668 3576",
    "sg:postcode":"G8B 4V7",
    "sg:province":"QC",
    "sg:tags":[
        "environmental",
        "ecological"
    ],
    "wof:name":"Enviro-Action",
    "wof:placetype":"venue"
},
  "geometry": {"coordinates":[-71.653938,48.555515],"type":"Point"}
}