{
  "type": "Feature",
  "properties": {
    "addr:full":"Peguis MB R0C 3J0",
    "addr:postcode":"r0c 3j0",
    "iso:country":"CA",
    "sg:city":"Peguis",
    "sg:classifiers":[
        {
            "category":"Freight",
            "type":"Transportation"
        }
    ],
    "sg:phone":"+1 204 645 2375",
    "sg:postcode":"R0C 3J0",
    "sg:province":"MB",
    "sg:tags":[
        "trucking"
    ],
    "wof:name":"Bear Transport",
    "wof:placetype":"venue"
},
  "geometry": {"coordinates":[-97.5586395264,51.3196105957],"type":"Point"}
}