{
  "type": "Feature",
  "properties": {
    "addr:full":"4522 13th Ave New Hazelton BC V0J 2J0",
    "addr:housenumber":"4522",
    "addr:postcode":"v0j 2j0",
    "addr:street":"13Th Ave",
    "iso:country":"CA",
    "sg:address":"4522 13th Ave",
    "sg:city":"New Hazelton",
    "sg:classifiers":[
        {
            "category":"Retail",
            "subcategory":"Auto Repair",
            "type":"Services"
        }
    ],
    "sg:phone":"+1 250 842 5733",
    "sg:postcode":"V0J 2J0",
    "sg:province":"BC",
    "sg:tags":[
        "wrecker"
    ],
    "wof:name":"Seeley Lake Svc Ltd",
    "wof:placetype":"venue"
},
  "geometry": {"coordinates":[-127.58074999999999,55.244061],"type":"Point"}
}