{
  "type": "Feature",
  "properties": {
    "addr:full":"675 Rue Thomas Magog QC J1X 3E9",
    "addr:housenumber":"675",
    "addr:postcode":"j1x 3e9",
    "addr:street":"Rue Thomas",
    "iso:country":"CA",
    "sg:address":"675 Rue Thomas",
    "sg:city":"Magog",
    "sg:classifiers":[
        {
            "category":"Recreation",
            "subcategory":"Marina",
            "type":"Entertainment"
        }
    ],
    "sg:phone":"+1 819 843 3788",
    "sg:postcode":"J1X 3E9",
    "sg:province":"QC",
    "wof:name":"Magog Marine",
    "wof:placetype":"venue"
},
  "geometry": {"coordinates":[-72.1544494629,45.2650756836],"type":"Point"}
}