{
  "type": "Feature",
  "properties": {
    "addr:full":"9922 113 Ave Grande Prairie AB T8V 1W7",
    "addr:housenumber":"9922",
    "addr:postcode":"t8v 1w7",
    "addr:street":"113 Ave",
    "iso:country":"CA",
    "sg:address":"9922 113 Ave",
    "sg:city":"Grande Prairie",
    "sg:classifiers":[
        {
            "category":"Manufacturing",
            "subcategory":"Printing",
            "type":"Manufacturing & Wholesale Goods"
        }
    ],
    "sg:phone":"+1 780 532 0243",
    "sg:postcode":"T8V 1W7",
    "sg:province":"AB",
    "sg:tags":[
        "printer"
    ],
    "wof:name":"Dca Printing",
    "wof:placetype":"venue"
},
  "geometry": {"coordinates":[-118.79238100000001,55.182747],"type":"Point"}
}