{
  "type": "Feature",
  "properties": {
    "addr:full":"8338 St. George St Vancouver BC V5X 3S7",
    "addr:housenumber":"8338",
    "addr:postcode":"v5x 3s7",
    "addr:street":"St. George St",
    "iso:country":"CA",
    "sg:address":"8338 St. George St",
    "sg:city":"Vancouver",
    "sg:classifiers":[
        {
            "category":"Manufacturing",
            "subcategory":"Printing",
            "type":"Manufacturing & Wholesale Goods"
        }
    ],
    "sg:phone":"+1 604 322 1815",
    "sg:postcode":"V5X 3S7",
    "sg:province":"BC",
    "sg:tags":[
        "bookbinder",
        "printer"
    ],
    "wof:name":"Advance Bindery CO",
    "wof:placetype":"venue"
},
  "geometry": {"coordinates":[-123.09379577599999,49.2088928223],"type":"Point"}
}