{
  "type": "Feature",
  "properties": {
    "iso:country":"CA",
    "sg:address":"2063 Parker St",
    "sg:city":"Halifax",
    "sg:classifiers":[
        {
            "category":"Organizations",
            "subcategory":"Religious Organization",
            "type":"Services"
        }
    ],
    "sg:phone":"+1 902 423 3021",
    "sg:postcode":"B3K 4T6",
    "sg:province":"NS",
    "sg:tags":[
        "church"
    ],
    "wof:name":"Halifax Seventh Day Adventis",
    "wof:placetype":"venue"
},
  "geometry": {"coordinates":[-63.5919113159,44.6481781006],"type":"Point"}
}