{
  "type": "Feature",
  "properties": {
    "addr:full":"592 Rue DE LA Riviere Cowansville QC J2K 3G6",
    "addr:housenumber":"592",
    "addr:postcode":"j2k 3g6",
    "addr:street":"Rue De La Riviere",
    "iso:country":"CA",
    "sg:address":"592 Rue DE LA Riviere",
    "sg:city":"Cowansville",
    "sg:classifiers":[
        {
            "category":"Building & Trades",
            "subcategory":"Construction",
            "type":"Services"
        }
    ],
    "sg:phone":"+1 450 266 6000",
    "sg:postcode":"J2K 3G6",
    "sg:province":"QC",
    "sg:tags":[
        "concrete",
        "pumping"
    ],
    "wof:name":"Beton Cowansville 1989 Inc",
    "wof:placetype":"venue"
},
  "geometry": {"coordinates":[-72.79858400000001,45.210613],"type":"Point"}
}