{
  "type": "Feature",
  "properties": {
    "addr:full":"Saint-Alphonse-DE-Granby QC J0E 2A0",
    "addr:postcode":"j0e 2a0",
    "iso:country":"CA",
    "sg:city":"Saint-Alphonse-DE-Granby",
    "sg:classifiers":[
        {
            "category":"Manufacturing",
            "subcategory":"Apparel",
            "type":"Manufacturing & Wholesale Goods"
        }
    ],
    "sg:phone":"+1 450 375 4686",
    "sg:postcode":"J0E 2A0",
    "sg:province":"QC",
    "sg:tags":[
        "outboard",
        "motor"
    ],
    "wof:name":"Picard Marine Enr",
    "wof:placetype":"venue"
},
  "geometry": {"coordinates":[-72.721771,45.397995],"type":"Point"}
}