{
  "type": "Feature",
  "properties": {
    "addr:full":"2521 Tyee Dr Gabriola BC V0R 1X7",
    "addr:housenumber":"2521",
    "addr:postcode":"v0r 1x7",
    "addr:street":"Tyee Dr",
    "iso:country":"CA",
    "sg:address":"2521 Tyee Dr",
    "sg:city":"Gabriola",
    "sg:classifiers":[
        {
            "category":"Building & Trades",
            "subcategory":"Construction",
            "type":"Services"
        }
    ],
    "sg:phone":"+1 250 247 8817",
    "sg:postcode":"V0R 1X7",
    "sg:province":"BC",
    "sg:tags":[
        "excavating",
        "contractor"
    ],
    "wof:name":"Degnen Excavators",
    "wof:placetype":"venue"
},
  "geometry": {"coordinates":[-123.7379,49.130474],"type":"Point"}
}