{
  "type": "Feature",
  "properties": {
    "addr:full":"4385 Tsse Des Chenes Saint-Antoine-DE-Tilly QC G0S 2C0",
    "addr:housenumber":"4385",
    "addr:postcode":"g0s 2c0",
    "addr:street":"Tsse Des Chenes",
    "iso:country":"CA",
    "sg:address":"4385 Tsse Des Chenes",
    "sg:city":"Saint-Antoine-DE-Tilly",
    "sg:classifiers":[
        {
            "category":"Wholesale",
            "subcategory":"Fruits & Vegetables",
            "type":"Manufacturing & Wholesale Goods"
        }
    ],
    "sg:phone":"+1 418 886 2539",
    "sg:postcode":"G0S 2C0",
    "sg:province":"QC",
    "sg:tags":[
        "shipper"
    ],
    "wof:name":"Vergers DE Tilly Inc",
    "wof:placetype":"venue"
},
  "geometry": {"coordinates":[-71.60290500000001,46.655209],"type":"Point"}
}