{
  "type": "Feature",
  "properties": {
    "addr:full":"235 Bowman St Hamilton ON L8S 2T9",
    "addr:housenumber":"235",
    "addr:postcode":"l8s 2t9",
    "addr:street":"Bowman St",
    "iso:country":"CA",
    "sg:address":"235 Bowman St",
    "sg:city":"Hamilton",
    "sg:classifiers":[
        {
            "category":"Education",
            "subcategory":"School",
            "type":"Public Place"
        }
    ],
    "sg:phone":"+1 905 528 5451",
    "sg:postcode":"L8S 2T9",
    "sg:province":"ON",
    "wof:name":"Yeshiva of Hamilton",
    "wof:placetype":"venue"
},
  "geometry": {"coordinates":[-79.91986799999999,43.250881],"type":"Point"}
}