{
  "type": "Feature",
  "properties": {
    "addr:full":"Lindsay ON K9V 6G8",
    "addr:postcode":"k9v 6g8",
    "iso:country":"CA",
    "sg:city":"Lindsay",
    "sg:classifiers":[
        {
            "category":"Food & Beverages",
            "subcategory":"Bakery",
            "type":"Retail Goods"
        }
    ],
    "sg:phone":"+1 705 878 4157",
    "sg:postcode":"K9V 6G8",
    "sg:province":"ON",
    "sg:tags":[
        "baker"
    ],
    "wof:name":"Euro Delight",
    "wof:placetype":"venue"
},
  "geometry": {"coordinates":[-78.757668,44.3507],"type":"Point"}
}