{
  "type": "Feature",
  "properties": {
    "addr:full":"1520 Courtneypark Dr E Mississauga ON L5T 2C7",
    "addr:housenumber":"1520",
    "addr:postcode":"l5t 2c7",
    "addr:street":"Courtneypark Dr E",
    "iso:country":"CA",
    "sg:address":"1520 Courtneypark Dr E",
    "sg:city":"Mississauga",
    "sg:classifiers":[
        {
            "category":"Retail",
            "subcategory":"Car Wash",
            "type":"Services"
        }
    ],
    "sg:phone":"+1 905 670 7619",
    "sg:postcode":"L5T 2C7",
    "sg:province":"ON",
    "sg:tags":[
        "polishing",
        "washing"
    ],
    "wof:name":"Shell Canada Products Ltd",
    "wof:placetype":"venue"
},
  "geometry": {"coordinates":[-79.657318,43.663948],"type":"Point"}
}