{
  "type": "Feature",
  "properties": {
    "addr:full":"294 Picton Ave Ottawa ON K1Z 8P8",
    "addr:housenumber":"294",
    "addr:postcode":"k1z 8p8",
    "addr:street":"Picton Ave",
    "iso:country":"CA",
    "sg:address":"294 Picton Ave",
    "sg:city":"Ottawa",
    "sg:classifiers":[
        {
            "category":"Organizations",
            "subcategory":"Professional Association",
            "type":"Services"
        }
    ],
    "sg:phone":"+1 613 798 7711",
    "sg:postcode":"K1Z 8P8",
    "sg:province":"ON",
    "sg:tags":[
        "club"
    ],
    "wof:name":"Medallion Club of Ottawa Inc",
    "wof:placetype":"venue"
},
  "geometry": {"coordinates":[-75.752876,45.393257],"type":"Point"}
}