{
  "type": "Feature",
  "properties": {
    "addr:full":"605 Rue Principale Saint-Prime QC G8J 1T3",
    "addr:housenumber":"605",
    "addr:postcode":"g8j 1t3",
    "addr:street":"Rue Principale",
    "iso:country":"CA",
    "sg:address":"605 Rue Principale",
    "sg:city":"Saint-Prime",
    "sg:classifiers":[
        {
            "category":"Organizations",
            "subcategory":"Religious Organization",
            "type":"Services"
        }
    ],
    "sg:phone":"+1 418 251 3011",
    "sg:postcode":"G8J 1T3",
    "sg:province":"QC",
    "sg:tags":[
        "church"
    ],
    "wof:name":"Presbytere DE St-Prime",
    "wof:placetype":"venue"
},
  "geometry": {"coordinates":[-72.33651,48.593494],"type":"Point"}
}