{
  "type": "Feature",
  "properties": {
    "iso:country":"CA",
    "sg:city":"Swan River",
    "sg:classifiers":[
        {
            "category":"Personal",
            "subcategory":"Beauty Salon",
            "type":"Services"
        }
    ],
    "sg:phone":"+1 204 734 4576",
    "sg:postcode":"R0L 1Z0",
    "sg:province":"MB",
    "wof:name":"Elizabeth's Beauty Bar",
    "wof:placetype":"venue"
},
  "geometry": {"coordinates":[-101.263046265,52.1064376831],"type":"Point"}
}