{
  "type": "Feature",
  "properties": {
    "addr:full":"Rexton NB E4W 2B3",
    "addr:postcode":"e4w 2b3",
    "iso:country":"CA",
    "sg:city":"Rexton",
    "sg:classifiers":[
        {
            "category":"Shopping",
            "subcategory":"Discount & Variety Stores",
            "type":"Retail Goods"
        }
    ],
    "sg:phone":"+1 506 523 6829",
    "sg:postcode":"E4W 2B3",
    "sg:province":"NB",
    "sg:tags":[
        "shop",
        "gift"
    ],
    "wof:name":"Great Canadian Dollar Store",
    "wof:placetype":"venue"
},
  "geometry": {"coordinates":[-64.877174,46.649818],"type":"Point"}
}