{
  "type": "Feature",
  "properties": {
    "iso:country":"CA",
    "sg:address":"6304 6A St SE",
    "sg:city":"Calgary",
    "sg:classifiers":[
        {
            "category":"Manufacturing",
            "subcategory":"Signs",
            "type":"Manufacturing & Wholesale Goods"
        }
    ],
    "sg:phone":"+1 403 258 0556",
    "sg:postcode":"T2H 2B7",
    "sg:province":"AB",
    "wof:name":"Pattison Sign Group",
    "wof:placetype":"venue"
},
  "geometry": {"coordinates":[-114.049278259,50.9971694946],"type":"Point"}
}