{
  "type": "Feature",
  "properties": {
    "addr:full":"6304 6A St SE Calgary AB T2H 2B7",
    "addr:housenumber":"6304",
    "addr:postcode":"t2h 2b7",
    "addr:street":"6A St Se",
    "iso:country":"CA",
    "sg:address":"6304 6A St SE",
    "sg:city":"Calgary",
    "sg:classifiers":[
        {
            "category":"Manufacturing",
            "subcategory":"Signs",
            "type":"Manufacturing & Wholesale Goods"
        }
    ],
    "sg:phone":"+1 403 258 0556",
    "sg:postcode":"T2H 2B7",
    "sg:province":"AB",
    "wof:name":"Pattison Sign Group",
    "wof:placetype":"venue"
},
  "geometry": {"coordinates":[-114.049278259,50.9971694946],"type":"Point"}
}