{
  "type": "Feature",
  "properties": {
    "addr:full":"2532 Rue Sainte-Catherine E Montreal QC H2K 2K2",
    "addr:housenumber":"2532",
    "addr:postcode":"h2k 2k2",
    "addr:street":"Rue Sainte-Catherine E",
    "iso:country":"CA",
    "sg:address":"2532 Rue Sainte-Catherine E",
    "sg:city":"Montreal",
    "sg:classifiers":[
        {
            "category":"Bars & Pubs",
            "type":"Food & Drink"
        }
    ],
    "sg:phone":"+1 514 526 5446",
    "sg:postcode":"H2K 2K2",
    "sg:province":"QC",
    "wof:name":"Bistro Frontenac",
    "wof:placetype":"venue"
},
  "geometry": {"coordinates":[-73.545586,45.529728],"type":"Point"}
}