{
  "type": "Feature",
  "properties": {
    "addr:full":"1385 Odlum Dr Vancouver BC V5L 3M1",
    "addr:housenumber":"1385",
    "addr:postcode":"v5l 3m1",
    "addr:street":"Odlum Dr",
    "iso:country":"CA",
    "sg:address":"1385 Odlum Dr",
    "sg:city":"Vancouver",
    "sg:classifiers":[
        {
            "category":"Wholesale",
            "subcategory":"Hardware",
            "type":"Manufacturing & Wholesale Goods"
        }
    ],
    "sg:phone":"+1 604 251 3151",
    "sg:postcode":"V5L 3M1",
    "sg:province":"BC",
    "sg:tags":[
        "caster",
        "glide"
    ],
    "wof:name":"Coast Materials Handling Ltd",
    "wof:placetype":"venue"
},
  "geometry": {"coordinates":[-123.07608,49.272354],"type":"Point"}
}