{
  "type": "Feature",
  "properties": {
    "addr:full":"16079 Boul Du Cure-Labelle Mirabel QC J7J 2G6",
    "addr:housenumber":"16079",
    "addr:postcode":"j7j 2g6",
    "addr:street":"Boul Du Cure-Labelle",
    "iso:country":"CA",
    "sg:address":"16079 Boul Du Cure-Labelle",
    "sg:city":"Mirabel",
    "sg:classifiers":[
        {
            "category":"Autos & Motor Vehicles",
            "subcategory":"Auto Supplies",
            "type":"Retail Goods"
        }
    ],
    "sg:phone":"+1 450 438 6400",
    "sg:postcode":"J7J 2G6",
    "sg:province":"QC",
    "sg:tags":[
        "trailer",
        "hitch"
    ],
    "wof:name":"Attache Pierquip Inc",
    "wof:placetype":"venue"
},
  "geometry": {"coordinates":[-73.966965,45.73513],"type":"Point"}
}