{
  "type": "Feature",
  "properties": {
    "addr:full":"489 Grange Rd Guelph ON N1E 7C4",
    "addr:housenumber":"489",
    "addr:postcode":"n1e 7c4",
    "addr:street":"Grange Rd",
    "iso:country":"CA",
    "sg:address":"489 Grange Rd",
    "sg:city":"Guelph",
    "sg:classifiers":[
        {
            "category":"Building & Trades",
            "subcategory":"Construction",
            "type":"Services"
        }
    ],
    "sg:phone":"+1 519 824 7382",
    "sg:postcode":"N1E 7C4",
    "sg:province":"ON",
    "sg:tags":[
        "home",
        "improvement"
    ],
    "wof:name":"Carson Roofing",
    "wof:placetype":"venue"
},
  "geometry": {"coordinates":[-80.221802,43.570255],"type":"Point"}
}