{
  "type": "Feature",
  "properties": {
    "addr:full":"Charlesbourg QC G1H 1H1",
    "addr:postcode":"g1h 1h1",
    "iso:country":"CA",
    "sg:city":"Charlesbourg",
    "sg:classifiers":[
        {
            "category":"Sports & Exercise",
            "subcategory":"Gym",
            "type":"Entertainment"
        }
    ],
    "sg:phone":"+1 418 622 5005",
    "sg:postcode":"G1H 1H1",
    "sg:province":"QC",
    "sg:tags":[
        "club",
        "health",
        "studio",
        "gymnasium"
    ],
    "wof:name":"Nautilus Plus Inc",
    "wof:placetype":"venue"
},
  "geometry": {"coordinates":[-71.25490570069999,46.8640213013],"type":"Point"}
}