{
  "type": "Feature",
  "properties": {
    "addr:full":"5596 Canim-Hendrix Lake Rd 100 Mile House BC V0K 2E0",
    "addr:housenumber":"5596",
    "addr:postcode":"v0k 2e0",
    "addr:street":"Canim-Hendrix Lake Rd",
    "iso:country":"CA",
    "sg:address":"5596 Canim-Hendrix Lake Rd",
    "sg:city":"100 Mile House",
    "sg:classifiers":[
        {
            "category":"Building & Trades",
            "subcategory":"Construction",
            "type":"Services"
        }
    ],
    "sg:phone":"+1 250 395 3846",
    "sg:postcode":"V0K 2E0",
    "sg:province":"BC",
    "sg:tags":[
        "general",
        "contractor"
    ],
    "wof:name":"P & R Roofing & Construction",
    "wof:placetype":"venue"
},
  "geometry": {"coordinates":[-121.391159058,51.3140258789],"type":"Point"}
}