{
  "type": "Feature",
  "properties": {
    "addr:full":"85 York St Sackville NB E4L 4R6",
    "addr:housenumber":"85",
    "addr:postcode":"e4l 4r6",
    "addr:street":"York St",
    "iso:country":"CA",
    "sg:address":"85 York St",
    "sg:city":"Sackville",
    "sg:classifiers":[
        {
            "category":"Real Estate",
            "subcategory":"Architect",
            "type":"Services"
        }
    ],
    "sg:phone":"+1 506 536 1606",
    "sg:postcode":"E4L 4R6",
    "sg:province":"NB",
    "wof:name":"Arseneau, Arthur J",
    "wof:placetype":"venue"
},
  "geometry": {"coordinates":[-64.37670900000001,45.899891],"type":"Point"}
}