{
  "type": "Feature",
  "properties": {
    "iso:country":"CA",
    "sg:city":"Toronto",
    "sg:classifiers":[
        {
            "category":"Health Services",
            "subcategory":"Health Practitioner",
            "type":"Services"
        }
    ],
    "sg:phone":"+1 416 925 4417",
    "sg:postcode":"M4Y 2P2",
    "sg:province":"ON",
    "sg:tags":[
        "nurse",
        "registry"
    ],
    "wof:name":"Mps Best Care Ltd",
    "wof:placetype":"venue"
},
  "geometry": {"coordinates":[-79.3856964111,43.669380188],"type":"Point"}
}