{
  "type": "Feature",
  "properties": {
    "addr:full":"London ON N5Z 5A9",
    "addr:postcode":"n5z 5a9",
    "iso:country":"CA",
    "sg:city":"London",
    "sg:classifiers":[
        {
            "category":"Health Services",
            "subcategory":"Doctor",
            "type":"Services"
        }
    ],
    "sg:phone":"+1 519 668 1466",
    "sg:postcode":"N5Z 5A9",
    "sg:province":"ON",
    "sg:tags":[
        "dentist"
    ],
    "wof:name":"Kashyap, Suman K DDS",
    "wof:placetype":"venue"
},
  "geometry": {"coordinates":[-81.2007522583,42.9631080627],"type":"Point"}
}