{
  "type": "Feature",
  "properties": {
    "addr:full":"2511 8th St E Saskatoon SK S7H 0V4",
    "addr:housenumber":"2511",
    "addr:postcode":"s7h 0v4",
    "addr:street":"8Th St E",
    "iso:country":"CA",
    "sg:address":"2511 8th St E",
    "sg:city":"Saskatoon",
    "sg:classifiers":[
        {
            "category":"Personal",
            "subcategory":"Beauty Salon",
            "type":"Services"
        }
    ],
    "sg:phone":"+1 306 955 1001",
    "sg:postcode":"S7H 0V4",
    "sg:province":"SK",
    "wof:name":"Hair Affair 1",
    "wof:placetype":"venue"
},
  "geometry": {"coordinates":[-106.61813354500001,52.1150779724],"type":"Point"}
}