{
  "type": "Feature",
  "properties": {
    "addr:full":"Saint-Philippe QC J0L 2K0",
    "addr:postcode":"j0l 2k0",
    "iso:country":"CA",
    "sg:city":"Saint-Philippe",
    "sg:classifiers":[
        {
            "category":"Travel",
            "subcategory":"Campground",
            "type":"Entertainment"
        }
    ],
    "sg:phone":"+1 450 659 3451",
    "sg:postcode":"J0L 2K0",
    "sg:province":"QC",
    "wof:name":"Camping St-Andre",
    "wof:placetype":"venue"
},
  "geometry": {"coordinates":[-73.492287,45.332359],"type":"Point"}
}