{
  "type": "Feature",
  "properties": {
    "addr:full":"113 Westmoreland Ave Toronto ON M6H 2Z8",
    "addr:housenumber":"113",
    "addr:postcode":"m6h 2z8",
    "addr:street":"Westmoreland Ave",
    "iso:country":"CA",
    "sg:address":"113 Westmoreland Ave",
    "sg:city":"Toronto",
    "sg:classifiers":[
        {
            "category":"Education",
            "subcategory":"School",
            "type":"Public Place"
        }
    ],
    "sg:phone":"+1 416 532 5082",
    "sg:postcode":"M6H 2Z8",
    "sg:province":"ON",
    "wof:name":"Gnostic Institute of Canada",
    "wof:placetype":"venue"
},
  "geometry": {"coordinates":[-79.4313735962,43.6637382507],"type":"Point"}
}