{
  "type": "Feature",
  "properties": {
    "addr:full":"850 Bank St Ottawa ON K1S 3W1",
    "addr:housenumber":"850",
    "addr:postcode":"k1s 3w1",
    "addr:street":"Bank St",
    "iso:country":"CA",
    "sg:address":"850 Bank St",
    "sg:city":"Ottawa",
    "sg:classifiers":[
        {
            "category":"Shopping",
            "subcategory":"Stationery & Office Supplies",
            "type":"Retail Goods"
        }
    ],
    "sg:phone":"+1 613 230 1313",
    "sg:postcode":"K1S 3W1",
    "sg:province":"ON",
    "sg:tags":[
        "stationer"
    ],
    "wof:name":"Papery",
    "wof:placetype":"venue"
},
  "geometry": {"coordinates":[-75.68775177000001,45.4017486572],"type":"Point"}
}