{
  "type": "Feature",
  "properties": {
    "addr:full":"3473 Rue University Montreal QC H3A 2A8",
    "addr:housenumber":"3473",
    "addr:postcode":"h3a 2a8",
    "addr:street":"Rue University",
    "iso:country":"CA",
    "sg:address":"3473 Rue University",
    "sg:city":"Montreal",
    "sg:classifiers":[
        {
            "category":"Education",
            "subcategory":"College",
            "type":"Public Place"
        }
    ],
    "sg:phone":"+1 514 849 3004",
    "sg:postcode":"H3A 2A8",
    "sg:province":"QC",
    "sg:tags":[
        "academic",
        "school"
    ],
    "wof:name":"Montreal Diocesan Theological",
    "wof:placetype":"venue"
},
  "geometry": {"coordinates":[-73.575531,45.50613],"type":"Point"}
}