{
  "type": "Feature",
  "properties": {
    "addr:full":"Montreal QC H3B 4G5",
    "addr:postcode":"h3b 4g5",
    "iso:country":"CA",
    "sg:city":"Montreal",
    "sg:classifiers":[
        {
            "category":"Shopping",
            "type":"Retail Goods"
        }
    ],
    "sg:phone":"+1 514 286 1996",
    "sg:postcode":"H3B 4G5",
    "sg:province":"QC",
    "sg:tags":[
        "cosmetic",
        "perfume"
    ],
    "wof:name":"Cosmic Perfumes",
    "wof:placetype":"venue"
},
  "geometry": {"coordinates":[-73.55435900000001,45.51231],"type":"Point"}
}