{
  "type": "Feature",
  "properties": {
    "addr:full":"630 1 Ave NE Calgary AB T2E 0B6",
    "addr:housenumber":"630",
    "addr:postcode":"t2e 0b6",
    "addr:street":"1 Ave Ne",
    "iso:country":"CA",
    "sg:address":"630 1 Ave NE",
    "sg:city":"Calgary",
    "sg:classifiers":[
        {
            "category":"Food & Beverages",
            "subcategory":"Groceries & Convenience Stores",
            "type":"Retail Goods"
        }
    ],
    "sg:phone":"+1 403 263 7917",
    "sg:postcode":"T2E 0B6",
    "sg:province":"AB",
    "wof:name":"Mac's Convenience Stores",
    "wof:placetype":"venue"
},
  "geometry": {"coordinates":[-114.05001799999999,51.053314],"type":"Point"}
}