{
  "type": "Feature",
  "properties": {
    "iso:country":"CA",
    "sg:address":"861 York Mills Rd",
    "sg:city":"North York",
    "sg:classifiers":[
        {
            "category":"Restaurant",
            "type":"Food & Drink"
        }
    ],
    "sg:phone":"+1 416 385 7744",
    "sg:postcode":"M3B 1Y2",
    "sg:province":"ON",
    "wof:name":"Mr Greek Junior",
    "wof:placetype":"venue"
},
  "geometry": {"coordinates":[-79.351616,43.754635],"type":"Point"}
}