{
  "type": "Feature",
  "properties": {
    "iso:country":"CA",
    "sg:city":"Cambridge",
    "sg:classifiers":[
        {
            "category":"Building & Trades",
            "subcategory":"Landscaping Services",
            "type":"Services"
        }
    ],
    "sg:phone":"+1 519 740 2032",
    "sg:postcode":"N1R 7S7",
    "sg:province":"ON",
    "sg:tags":[
        "lawn",
        "janitor",
        "maintenance",
        "grounds"
    ],
    "wof:name":"Wayco Cleaning & Landscaping",
    "wof:placetype":"venue"
},
  "geometry": {"coordinates":[-80.31884002690001,43.403087616],"type":"Point"}
}