{
  "type": "Feature",
  "properties": {
    "addr:full":"3292 Dunmore Rd SE # 132 Medicine Hat AB T1B 2R4",
    "addr:housenumber":"3292",
    "addr:postcode":"t1b 2r4",
    "addr:street":"Dunmore Rd Se # 132",
    "iso:country":"CA",
    "sg:address":"3292 Dunmore Rd SE # 132",
    "sg:city":"Medicine Hat",
    "sg:classifiers":[
        {
            "category":"Travel",
            "subcategory":"Travel Agent",
            "type":"Entertainment"
        }
    ],
    "sg:phone":"+1 403 526 6605",
    "sg:postcode":"T1B 2R4",
    "sg:province":"AB",
    "sg:tags":[
        "agency",
        "bureau"
    ],
    "wof:name":"Marlin Travel",
    "wof:placetype":"venue"
},
  "geometry": {"coordinates":[-110.647041321,50.007183075],"type":"Point"}
}