{
  "type": "Feature",
  "properties": {
    "addr:full":"2890 Rue Du Meunier Vaudreuil-Dorion QC J7V 8P2",
    "addr:housenumber":"2890",
    "addr:postcode":"j7v 8p2",
    "addr:street":"Rue Du Meunier",
    "iso:country":"CA",
    "sg:address":"2890 Rue Du Meunier",
    "sg:city":"Vaudreuil-Dorion",
    "sg:classifiers":[
        {
            "category":"Freight",
            "type":"Transportation"
        }
    ],
    "sg:phone":"+1 450 455 5959",
    "sg:postcode":"J7V 8P2",
    "sg:province":"QC",
    "sg:tags":[
        "trucking"
    ],
    "wof:name":"North-am",
    "wof:placetype":"venue"
},
  "geometry": {"coordinates":[-74.03434753419999,45.3709640503],"type":"Point"}
}