{
  "type": "Feature",
  "properties": {
    "iso:country":"CA",
    "sg:city":"Kelowna",
    "sg:classifiers":[
        {
            "category":"Health Services",
            "subcategory":"Chiropractor",
            "type":"Services"
        }
    ],
    "sg:phone":"+1 250 869 0991",
    "sg:postcode":"V1Y 4A9",
    "sg:province":"BC",
    "wof:name":"Brummund, Mel A DC",
    "wof:placetype":"venue"
},
  "geometry": {"coordinates":[-119.464897,49.88287],"type":"Point"}
}