{
  "type": "Feature",
  "properties": {
    "addr:full":"109 Plains Rd E Burlington ON L7T 2C2",
    "addr:housenumber":"109",
    "addr:postcode":"l7t 2c2",
    "addr:street":"Plains Rd E",
    "iso:country":"CA",
    "sg:address":"109 Plains Rd E",
    "sg:city":"Burlington",
    "sg:classifiers":[
        {
            "category":"Wholesale",
            "subcategory":"Meat",
            "type":"Manufacturing & Wholesale Goods"
        }
    ],
    "sg:phone":"+1 905 634 0196",
    "sg:postcode":"L7T 2C2",
    "sg:province":"ON",
    "sg:tags":[
        "product"
    ],
    "wof:name":"J & G Quality Meats Ltd",
    "wof:placetype":"venue"
},
  "geometry": {"coordinates":[-79.849121,43.309574],"type":"Point"}
}