{
  "type": "Feature",
  "properties": {
    "addr:full":"Ruthven ON N0P 2G0",
    "addr:postcode":"n0p 2g0",
    "iso:country":"CA",
    "sg:city":"Ruthven",
    "sg:classifiers":[
        {
            "category":"Sports & Exercise",
            "subcategory":"Golf",
            "type":"Entertainment"
        }
    ],
    "sg:phone":"+1 519 326 6993",
    "sg:postcode":"N0P 2G0",
    "sg:province":"ON",
    "sg:tags":[
        "course"
    ],
    "wof:name":"Orchard View Golf Course",
    "wof:placetype":"venue"
},
  "geometry": {"coordinates":[-82.67137099999999,42.062248],"type":"Point"}
}