{
  "type": "Feature",
  "properties": {
    "addr:full":"380 Harvey Ave Kelowna BC V1Y 6C4",
    "addr:housenumber":"380",
    "addr:postcode":"v1y 6c4",
    "addr:street":"Harvey Ave",
    "iso:country":"CA",
    "sg:address":"380 Harvey Ave",
    "sg:city":"Kelowna",
    "sg:classifiers":[
        {
            "category":"Autos & Motor Vehicles",
            "subcategory":"Fuel & Gas Station",
            "type":"Retail Goods"
        }
    ],
    "sg:phone":"+1 250 763 5076",
    "sg:postcode":"V1Y 6C4",
    "sg:province":"BC",
    "sg:tags":[
        "oil"
    ],
    "wof:name":"Kelowna Husky Svc",
    "wof:placetype":"venue"
},
  "geometry": {"coordinates":[-119.49543799999999,49.883755],"type":"Point"}
}