{
  "type": "Feature",
  "properties": {
    "addr:full":"Vancouver BC V6C 3S8",
    "addr:postcode":"v6c 3s8",
    "iso:country":"CA",
    "sg:city":"Vancouver",
    "sg:classifiers":[
        {
            "category":"Insurance",
            "subcategory":"Hazard Insurance",
            "type":"Services"
        }
    ],
    "sg:phone":"+1 604 683 6761",
    "sg:postcode":"V6C 3S8",
    "sg:province":"BC",
    "sg:tags":[
        "employee",
        "benefit",
        "compensation",
        "plan"
    ],
    "wof:name":"Mercer Human Resource Consult",
    "wof:placetype":"venue"
},
  "geometry": {"coordinates":[-123.11846199999999,49.285934],"type":"Point"}
}