{
  "type": "Feature",
  "properties": {
    "addr:full":"1501 32 Ave Vernon BC V1T 2H9",
    "addr:housenumber":"1501",
    "addr:postcode":"v1t 2h9",
    "addr:street":"32 Ave",
    "iso:country":"CA",
    "sg:address":"1501 32 Ave",
    "sg:city":"Vernon",
    "sg:classifiers":[
        {
            "category":"Food & Beverages",
            "subcategory":"Groceries & Convenience Stores",
            "type":"Retail Goods"
        }
    ],
    "sg:phone":"+1 250 542 3046",
    "sg:postcode":"V1T 2H9",
    "sg:province":"BC",
    "sg:tags":[
        "grocer"
    ],
    "wof:name":"Lakeview Market",
    "wof:placetype":"venue"
},
  "geometry": {"coordinates":[-119.25127410899999,50.2654953003],"type":"Point"}
}