{
  "type": "Feature",
  "properties": {
    "iso:country":"CA",
    "sg:city":"Saskatoon",
    "sg:classifiers":[
        {
            "category":"Real Estate",
            "subcategory":"Real Estate Agent",
            "type":"Services"
        }
    ],
    "sg:phone":"+1 306 955 5522",
    "sg:postcode":"S7H 0Z7",
    "sg:province":"SK",
    "wof:name":"Service Realty",
    "wof:placetype":"venue"
},
  "geometry": {"coordinates":[-106.625671,52.113388],"type":"Point"}
}