{
  "type": "Feature",
  "properties": {
    "addr:full":"West Vancouver BC V7V 1J3",
    "addr:postcode":"v7v 1j3",
    "iso:country":"CA",
    "sg:city":"West Vancouver",
    "sg:classifiers":[
        {
            "category":"Health Services",
            "subcategory":"Clinic",
            "type":"Services"
        }
    ],
    "sg:phone":"+1 604 926 7589",
    "sg:postcode":"V7V 1J3",
    "sg:province":"BC",
    "wof:name":"Secret Garden Holistic Spa",
    "wof:placetype":"venue"
},
  "geometry": {"coordinates":[-123.160705566,49.3284034729],"type":"Point"}
}