{
  "type": "Feature",
  "properties": {
    "addr:full":"177 Sutton Pl Sault Ste Marie ON P6A 6A8",
    "addr:housenumber":"177",
    "addr:postcode":"p6a 6a8",
    "addr:street":"Sutton Pl",
    "iso:country":"CA",
    "sg:address":"177 Sutton Pl",
    "sg:city":"Sault Ste Marie",
    "sg:classifiers":[
        {
            "category":"Building & Trades",
            "subcategory":"Landscaping Services",
            "type":"Services"
        }
    ],
    "sg:phone":"+1 705 942 9676",
    "sg:postcode":"P6A 6A8",
    "sg:province":"ON",
    "sg:tags":[
        "lawn",
        "maintenance",
        "grounds"
    ],
    "wof:name":"Mr Earth Worm Lawn & Yard",
    "wof:placetype":"venue"
},
  "geometry": {"coordinates":[-84.273865,46.515705],"type":"Point"}
}