{
  "type": "Feature",
  "properties": {
    "addr:full":"931 Rte Lagueux Saint-Etienne-DE-Lauzon QC G6J 1C7",
    "addr:housenumber":"931",
    "addr:postcode":"g6j 1c7",
    "addr:street":"Rte Lagueux Saint-Etienne-De-Lauzon",
    "iso:country":"CA",
    "sg:address":"931 Rte Lagueux",
    "sg:city":"Saint-Etienne-DE-Lauzon",
    "sg:classifiers":[
        {
            "category":"Professional",
            "subcategory":"Business Services",
            "type":"Services"
        }
    ],
    "sg:phone":"+1 418 836 1149",
    "sg:postcode":"G6J 1C7",
    "sg:province":"QC",
    "sg:tags":[
        "painter",
        "sign"
    ],
    "wof:name":"Graphique Cgc",
    "wof:placetype":"venue"
},
  "geometry": {"coordinates":[-71.32010699999999,46.657173],"type":"Point"}
}