{
  "type": "Feature",
  "properties": {
    "addr:full":"Timmins ON P4N 2K1",
    "addr:postcode":"p4n 2k1",
    "iso:country":"CA",
    "sg:city":"Timmins",
    "sg:classifiers":[
        {
            "category":"Personal",
            "type":"Services"
        }
    ],
    "sg:phone":"+1 705 267 5817",
    "sg:postcode":"P4N 2K1",
    "sg:province":"ON",
    "sg:tags":[
        "organization",
        "social",
        "credit",
        "welfare",
        "counseling",
        "debt"
    ],
    "wof:name":"Credit Counselling Svc",
    "wof:placetype":"venue"
},
  "geometry": {"coordinates":[-81.3285293579,48.4744377136],"type":"Point"}
}