{
  "type": "Feature",
  "properties": {
    "iso:country":"CA",
    "sg:address":"3221 Boul Des Sources",
    "sg:city":"Dollard-Des-Ormeaux",
    "sg:classifiers":[
        {
            "category":"Health Services",
            "subcategory":"Doctor",
            "type":"Services"
        }
    ],
    "sg:phone":"+1 514 685 0880",
    "sg:postcode":"H9B 1Z6",
    "sg:province":"QC",
    "sg:tags":[
        "clinic"
    ],
    "wof:name":"Clinique Enfant-Matic",
    "wof:placetype":"venue"
},
  "geometry": {"coordinates":[-73.795349,45.482899],"type":"Point"}
}