{
  "type": "Feature",
  "properties": {
    "addr:full":"4750 Av Henri-Julien Montreal QC H2T 2C8",
    "addr:housenumber":"4750",
    "addr:postcode":"h2t 2c8",
    "addr:street":"Av Henri-Julien",
    "iso:country":"CA",
    "sg:address":"4750 Av Henri-Julien",
    "sg:city":"Montreal",
    "sg:classifiers":[
        {
            "category":"Real Estate",
            "subcategory":"Real Estate Agent",
            "type":"Services"
        }
    ],
    "sg:phone":"+1 514 982 6774",
    "sg:postcode":"H2T 2C8",
    "sg:province":"QC",
    "sg:tags":[
        "management"
    ],
    "wof:name":"Opsis",
    "wof:placetype":"venue"
},
  "geometry": {"coordinates":[-73.58642578120001,45.5238304138],"type":"Point"}
}