{
  "type": "Feature",
  "properties": {
    "addr:full":"207 Guigues Ave Ottawa ON K1N 5J3",
    "addr:housenumber":"207",
    "addr:postcode":"k1n 5j3",
    "addr:street":"Guigues Ave",
    "iso:country":"CA",
    "sg:address":"207 Guigues Ave",
    "sg:city":"Ottawa",
    "sg:classifiers":[
        {
            "category":"Wholesale",
            "subcategory":"Meat",
            "type":"Manufacturing & Wholesale Goods"
        }
    ],
    "sg:phone":"+1 613 789 3210",
    "sg:postcode":"K1N 5J3",
    "sg:province":"ON",
    "sg:tags":[
        "butchering"
    ],
    "wof:name":"Lauzon Meats & Groceries",
    "wof:placetype":"venue"
},
  "geometry": {"coordinates":[-75.69104,45.432755],"type":"Point"}
}