{
  "type": "Feature",
  "properties": {
    "addr:full":"42 Centre St Harrow ON N0R 1G0",
    "addr:housenumber":"42",
    "addr:postcode":"n0r 1g0",
    "addr:street":"Centre St",
    "iso:country":"CA",
    "sg:address":"42 Centre St",
    "sg:city":"Harrow",
    "sg:classifiers":[
        {
            "category":"Shopping",
            "subcategory":"Used Merchandise",
            "type":"Retail Goods"
        }
    ],
    "sg:phone":"+1 519 738 2958",
    "sg:postcode":"N0R 1G0",
    "sg:province":"ON",
    "sg:tags":[
        "second",
        "store",
        "hand"
    ],
    "wof:name":"St Vincent DE Paul",
    "wof:placetype":"venue"
},
  "geometry": {"coordinates":[-82.91688499999999,42.036755],"type":"Point"}
}