{
  "type": "Feature",
  "properties": {
    "addr:full":"30 Rue Thibault Salaberry-DE-Valleyfield QC J6S 4H8",
    "addr:housenumber":"30",
    "addr:postcode":"j6s 4h8",
    "addr:street":"Rue Thibault",
    "iso:country":"CA",
    "sg:address":"30 Rue Thibault",
    "sg:city":"Salaberry-DE-Valleyfield",
    "sg:classifiers":[
        {
            "category":"Personal",
            "subcategory":"Beauty Salon",
            "type":"Services"
        }
    ],
    "sg:phone":"+1 450 371 0311",
    "sg:postcode":"J6S 4H8",
    "sg:province":"QC",
    "wof:name":"Salon Leslie",
    "wof:placetype":"venue"
},
  "geometry": {"coordinates":[-74.11479949949999,45.2641677856],"type":"Point"}
}