{
  "type": "Feature",
  "properties": {
    "iso:country":"CA",
    "sg:address":"61 Ormond St N",
    "sg:city":"Thorold",
    "sg:classifiers":[
        {
            "category":"Retail",
            "subcategory":"Auto Repair",
            "type":"Services"
        }
    ],
    "sg:phone":"+1 905 227 2097",
    "sg:postcode":"L2V 1Z3",
    "sg:province":"ON",
    "sg:tags":[
        "repairing",
        "automobile"
    ],
    "wof:name":"Cosgrove Auto Repair & Machine",
    "wof:placetype":"venue"
},
  "geometry": {"coordinates":[-79.19943237299999,43.129989624],"type":"Point"}
}