{
  "type": "Feature",
  "properties": {
    "iso:country":"CA",
    "sg:address":"114 Tache St",
    "sg:city":"Fisher Branch",
    "sg:classifiers":[
        {
            "category":"Autos & Motor Vehicles",
            "subcategory":"Fuel & Gas Station",
            "type":"Retail Goods"
        }
    ],
    "sg:phone":"+1 204 372 6248",
    "sg:postcode":"R0C 0Z0",
    "sg:province":"MB",
    "sg:tags":[
        "oil"
    ],
    "wof:name":"Mike Stocki & Sons",
    "wof:placetype":"venue"
},
  "geometry": {"coordinates":[-97.6184539795,51.0826034546],"type":"Point"}
}