{
  "type": "Feature",
  "properties": {
    "addr:full":"124 Bunting Rd St Catharines ON L2P 3G5",
    "addr:housenumber":"124",
    "addr:postcode":"l2p 3g5",
    "addr:street":"Bunting Rd",
    "iso:country":"CA",
    "sg:address":"124 Bunting Rd",
    "sg:city":"St Catharines",
    "sg:classifiers":[
        {
            "category":"Recreation",
            "type":"Entertainment"
        }
    ],
    "sg:phone":"+1 905 682 7616",
    "sg:postcode":"L2P 3G5",
    "sg:province":"ON",
    "sg:tags":[
        "organization",
        "labor",
        "hall",
        "auditorium"
    ],
    "wof:name":"Caw Ctr",
    "wof:placetype":"venue"
},
  "geometry": {"coordinates":[-79.209435,43.16333],"type":"Point"}
}