{
  "type": "Feature",
  "properties": {
    "addr:full":"46 Uplands Ave Thornhill ON L4J 1K2",
    "addr:housenumber":"46",
    "addr:postcode":"l4j 1k2",
    "addr:street":"Uplands Ave",
    "iso:country":"CA",
    "sg:address":"46 Uplands Ave",
    "sg:city":"Thornhill",
    "sg:classifiers":[
        {
            "category":"Recreation",
            "type":"Entertainment"
        }
    ],
    "sg:phone":"+1 905 889 3291",
    "sg:postcode":"L4J 1K2",
    "sg:province":"ON",
    "sg:tags":[
        "course",
        "golf"
    ],
    "wof:name":"Uplands Golf Club & Ski Ctr",
    "wof:placetype":"venue"
},
  "geometry": {"coordinates":[-79.43644714360001,43.8263473511],"type":"Point"}
}