{
  "type": "Feature",
  "properties": {
    "addr:full":"Aurora ON L4G 2N9",
    "addr:postcode":"l4g 2n9",
    "iso:country":"CA",
    "sg:city":"Aurora",
    "sg:classifiers":[
        {
            "category":"Retail",
            "subcategory":"Laundry & Dry Cleaning",
            "type":"Services"
        }
    ],
    "sg:phone":"+1 905 841 0115",
    "sg:postcode":"L4G 2N9",
    "sg:province":"ON",
    "sg:tags":[
        "cleaners"
    ],
    "wof:name":"NU Mode Cleaners",
    "wof:placetype":"venue"
},
  "geometry": {"coordinates":[-79.4775543213,43.9976272583],"type":"Point"}
}