{
  "type": "Feature",
  "properties": {
    "iso:country":"CA",
    "sg:city":"Saint-Andre-Avellin",
    "sg:classifiers":[
        {
            "category":"Shopping",
            "subcategory":"Florist",
            "type":"Retail Goods"
        }
    ],
    "sg:phone":"+1 819 983 2715",
    "sg:postcode":"J0V 1W0",
    "sg:province":"QC",
    "wof:name":"Fleuriste Louis Xvi",
    "wof:placetype":"venue"
},
  "geometry": {"coordinates":[-75.0546722412,45.7236022949],"type":"Point"}
}