{
  "type": "Feature",
  "properties": {
    "addr:full":"Mississauga ON L5A 4B4",
    "addr:postcode":"l5a 4b4",
    "iso:country":"CA",
    "sg:city":"Mississauga",
    "sg:classifiers":[
        {
            "category":"Building & Trades",
            "subcategory":"Equipment Rental",
            "type":"Services"
        }
    ],
    "sg:phone":"+1 905 848 4800",
    "sg:postcode":"L5A 4B4",
    "sg:province":"ON",
    "sg:tags":[
        "yard",
        "contractor"
    ],
    "wof:name":"Rental Max",
    "wof:placetype":"venue"
},
  "geometry": {"coordinates":[-79.595741272,43.5848045349],"type":"Point"}
}