{
  "type": "Feature",
  "properties": {
    "iso:country":"CA",
    "sg:address":"2221 Boul Angrignon",
    "sg:city":"Lasalle",
    "sg:classifiers":[
        {
            "category":"Autos & Motor Vehicles",
            "subcategory":"Auto Supplies",
            "type":"Retail Goods"
        }
    ],
    "sg:phone":"+1 514 365 8880",
    "sg:postcode":"H8N 3E3",
    "sg:province":"QC",
    "sg:tags":[
        "repairing",
        "automobile",
        "parts"
    ],
    "wof:name":"Canadian Tire",
    "wof:placetype":"venue"
},
  "geometry": {"coordinates":[-73.612823,45.449413],"type":"Point"}
}