{
  "type": "Feature",
  "properties": {
    "addr:full":"13911 Maycrest Way # 140 Richmond BC V6V 2J4",
    "addr:housenumber":"13911;140",
    "addr:postcode":"v6v 2j4",
    "addr:street":"Maycrest Way #",
    "iso:country":"CA",
    "sg:address":"13911 Maycrest Way # 140",
    "sg:city":"Richmond",
    "sg:classifiers":[
        {
            "category":"Manufacturing",
            "subcategory":"Food",
            "type":"Manufacturing & Wholesale Goods"
        }
    ],
    "sg:phone":"+1 604 273 7628",
    "sg:postcode":"V6V 2J4",
    "sg:province":"BC",
    "sg:tags":[
        "grocer",
        "product",
        "manufacturer"
    ],
    "wof:name":"Harvest Noodles & Dim Sum Mfg",
    "wof:placetype":"venue"
},
  "geometry": {"coordinates":[-123.07038900000001,49.179756],"type":"Point"}
}