{
  "type": "Feature",
  "properties": {
    "addr:full":"8200 Rue Grenache Anjou QC H1J 1C5",
    "addr:housenumber":"8200",
    "addr:postcode":"h1j 1c5",
    "addr:street":"Rue Grenache",
    "iso:country":"CA",
    "sg:address":"8200 Rue Grenache",
    "sg:city":"Anjou",
    "sg:classifiers":[
        {
            "category":"Organizations",
            "subcategory":"Labor Organization",
            "type":"Services"
        }
    ],
    "sg:phone":"+1 514 493 4586",
    "sg:postcode":"H1J 1C5",
    "sg:province":"QC",
    "wof:name":"Teamsters Conseil Conjoint",
    "wof:placetype":"venue"
},
  "geometry": {"coordinates":[-73.5701370239,45.6146965027],"type":"Point"}
}