{
  "type": "Feature",
  "properties": {
    "addr:full":"7711 152 St NW Edmonton AB T5R 1K9",
    "addr:housenumber":"7711",
    "addr:postcode":"t5r 1k9",
    "addr:street":"152 St Nw",
    "iso:country":"CA",
    "sg:address":"7711 152 St NW",
    "sg:city":"Edmonton",
    "sg:classifiers":[
        {
            "category":"Banks & Credit Unions",
            "subcategory":"Investment Brokerage",
            "type":"Services"
        }
    ],
    "sg:phone":"+1 780 443 4282",
    "sg:postcode":"T5R 1K9",
    "sg:province":"AB",
    "sg:tags":[
        "consultant",
        "planning",
        "financial"
    ],
    "wof:name":"Lamphier Financial Corp Inc",
    "wof:placetype":"venue"
},
  "geometry": {"coordinates":[-113.582603455,53.5108718872],"type":"Point"}
}