{
  "type": "Feature",
  "properties": {
    "addr:full":"602 Hwy 17 Alfred ON K0B 1A0",
    "addr:housenumber":"602",
    "addr:postcode":"k0b 1a0",
    "addr:street":"Hwy 17 Alfred",
    "iso:country":"CA",
    "sg:address":"602 Hwy 17",
    "sg:city":"Alfred",
    "sg:classifiers":[
        {
            "category":"Food & Beverages",
            "subcategory":"Liquor & Beverages",
            "type":"Retail Goods"
        }
    ],
    "sg:phone":"+1 613 679 2973",
    "sg:postcode":"K0B 1A0",
    "sg:province":"ON",
    "sg:tags":[
        "store"
    ],
    "wof:name":"Liquor Control Board of Ont",
    "wof:placetype":"venue"
},
  "geometry": {"coordinates":[-74.88402600000001,45.557522],"type":"Point"}
}