{
  "type": "Feature",
  "properties": {
    "addr:full":"1 Broadway St E Yorkton SK S3N 0K2",
    "addr:housenumber":"1",
    "addr:postcode":"s3n 0k2",
    "addr:street":"Broadway St E",
    "iso:country":"CA",
    "sg:address":"1 Broadway St E",
    "sg:city":"Yorkton",
    "sg:classifiers":[
        {
            "category":"Insurance",
            "subcategory":"Insurance Agent",
            "type":"Services"
        }
    ],
    "sg:phone":"+1 306 782 2514",
    "sg:postcode":"S3N 0K2",
    "sg:province":"SK",
    "sg:tags":[
        "investment"
    ],
    "wof:name":"Clarica Life Insurance CO",
    "wof:placetype":"venue"
},
  "geometry": {"coordinates":[-102.46251700000001,51.210381],"type":"Point"}
}