{
  "type": "Feature",
  "properties": {
    "addr:full":"108 Main St Watson SK S0K 4V0",
    "addr:housenumber":"108",
    "addr:postcode":"s0k 4v0",
    "addr:street":"Main St",
    "iso:country":"CA",
    "sg:address":"108 Main St",
    "sg:city":"Watson",
    "sg:classifiers":[
        {
            "category":"Shopping",
            "subcategory":"Catalog Store",
            "type":"Retail Goods"
        }
    ],
    "sg:phone":"+1 306 287 3717",
    "sg:postcode":"S0K 4V0",
    "sg:province":"SK",
    "sg:tags":[
        "mail",
        "order",
        "internet"
    ],
    "wof:name":"Sears Canada Inc",
    "wof:placetype":"venue"
},
  "geometry": {"coordinates":[-104.524330139,52.1280860901],"type":"Point"}
}