{
  "type": "Feature",
  "properties": {
    "iso:country":"CA",
    "sg:address":"RR 4",
    "sg:city":"Powassan",
    "sg:classifiers":[
        {
            "category":"Wholesale",
            "subcategory":"Meat",
            "type":"Manufacturing & Wholesale Goods"
        }
    ],
    "sg:phone":"+1 705 724 5999",
    "sg:postcode":"P0H 1Z0",
    "sg:province":"ON",
    "sg:tags":[
        "packer"
    ],
    "wof:name":"D & K Poultry",
    "wof:placetype":"venue"
},
  "geometry": {"coordinates":[-79.3640594482,46.0820159912],"type":"Point"}
}