{
  "type": "Feature",
  "properties": {
    "addr:full":"1437 Otter Lake Cross Rd Armstrong BC V0E 1B6",
    "addr:housenumber":"1437",
    "addr:postcode":"v0e 1b6",
    "addr:street":"Otter Lake Cross Rd",
    "iso:country":"CA",
    "sg:address":"1437 Otter Lake Cross Rd",
    "sg:city":"Armstrong",
    "sg:classifiers":[
        {
            "category":"Wholesale",
            "subcategory":"Durable Goods & Equipment",
            "type":"Manufacturing & Wholesale Goods"
        }
    ],
    "sg:phone":"+1 250 546 8954",
    "sg:postcode":"V0E 1B6",
    "sg:province":"BC",
    "sg:tags":[
        "representative",
        "manufacturer"
    ],
    "wof:name":"D D Agency Inc",
    "wof:placetype":"venue"
},
  "geometry": {"coordinates":[-119.183700562,50.4418182373],"type":"Point"}
}