{
  "type": "Feature",
  "properties": {
    "addr:full":"864 Queen St E Sault Ste Marie ON P6A 2B4",
    "addr:housenumber":"864",
    "addr:postcode":"p6a 2b4",
    "addr:street":"Queen St E",
    "iso:country":"CA",
    "sg:address":"864 Queen St E",
    "sg:city":"Sault Ste Marie",
    "sg:classifiers":[
        {
            "category":"Travel",
            "subcategory":"Hotels & Motels",
            "type":"Entertainment"
        }
    ],
    "sg:phone":"+1 705 253 2311",
    "sg:postcode":"P6A 2B4",
    "sg:province":"ON",
    "wof:name":"Algonquin Hotel",
    "wof:placetype":"venue"
},
  "geometry": {"coordinates":[-84.32312,46.506248],"type":"Point"}
}