{
  "type": "Feature",
  "properties": {
    "addr:full":"139 Rockland Rd Hartland NB E7P 1E9",
    "addr:housenumber":"139",
    "addr:postcode":"e7p 1e9",
    "addr:street":"Rockland Rd",
    "iso:country":"CA",
    "sg:address":"139 Rockland Rd",
    "sg:city":"Hartland",
    "sg:classifiers":[
        {
            "category":"Health Services",
            "subcategory":"Nursing And Care Facility",
            "type":"Services"
        }
    ],
    "sg:phone":"+1 506 375 3033",
    "sg:postcode":"E7P 1E9",
    "sg:province":"NB",
    "sg:tags":[
        "home",
        "convalescent"
    ],
    "wof:name":"Central Carleton Nursing Home",
    "wof:placetype":"venue"
},
  "geometry": {"coordinates":[-67.5152664185,46.3043861389],"type":"Point"}
}