{
  "type": "Feature",
  "properties": {
    "iso:country":"CA",
    "sg:address":"6290 Jenson Cove Rd",
    "sg:city":"Port Hardy",
    "sg:classifiers":[
        {
            "category":"Marine",
            "type":"Transportation"
        }
    ],
    "sg:phone":"+1 250 949 7076",
    "sg:postcode":"V0N 2P0",
    "sg:province":"BC",
    "sg:tags":[
        "towing"
    ],
    "wof:name":"More Marine Ltd",
    "wof:placetype":"venue"
},
  "geometry": {"coordinates":[-127.476814,50.717312],"type":"Point"}
}