{
  "type": "Feature",
  "properties": {
    "addr:full":"89 King St E Bowmanville ON L1C 1N4",
    "addr:housenumber":"89",
    "addr:postcode":"l1c 1n4",
    "addr:street":"King St",
    "iso:country":"CA",
    "sg:address":"89 King St E",
    "sg:city":"Bowmanville",
    "sg:classifiers":[
        {
            "category":"Restaurant",
            "type":"Food & Drink"
        }
    ],
    "sg:phone":"+1 905 623 4262",
    "sg:postcode":"L1C 1N4",
    "sg:province":"ON",
    "wof:name":"Hanc's Chicken 'N Ribs",
    "wof:placetype":"venue"
},
  "geometry": {"coordinates":[-78.6865158081,43.9113807678],"type":"Point"}
}