{
  "type": "Feature",
  "properties": {
    "addr:full":"Hannon ON L0R 1P0",
    "addr:postcode":"l0r 1p0",
    "iso:country":"CA",
    "sg:city":"Hannon",
    "sg:classifiers":[
        {
            "category":"Manufacturing",
            "subcategory":"Building Materials",
            "type":"Manufacturing & Wholesale Goods"
        }
    ],
    "sg:phone":"+1 905 692 5616",
    "sg:postcode":"L0R 1P0",
    "sg:province":"ON",
    "wof:name":"B K & S Wood Products",
    "wof:placetype":"venue"
},
  "geometry": {"coordinates":[-79.8376998901,43.1985282898],"type":"Point"}
}