{
  "type": "Feature",
  "properties": {
    "addr:full":"401 4th Ave W Kindersley SK S0L 1S0",
    "addr:housenumber":"401",
    "addr:postcode":"s0l 1s0",
    "addr:street":"4Th Ave W Kindersley",
    "iso:country":"CA",
    "sg:address":"401 4th Ave W",
    "sg:city":"Kindersley",
    "sg:classifiers":[
        {
            "category":"Organizations",
            "subcategory":"Religious Organization",
            "type":"Services"
        }
    ],
    "sg:phone":"+1 306 463 6600",
    "sg:postcode":"S0L 1S0",
    "sg:province":"SK",
    "sg:tags":[
        "church"
    ],
    "wof:name":"Anglican Church",
    "wof:placetype":"venue"
},
  "geometry": {"coordinates":[-109.159279,51.46722],"type":"Point"}
}