{
  "type": "Feature",
  "properties": {
    "addr:full":"37 Mapleview Dr E Barrie ON L4N 9H5",
    "addr:housenumber":"37",
    "addr:postcode":"l4n 9h5",
    "addr:street":"Mapleview Dr E",
    "iso:country":"CA",
    "sg:address":"37 Mapleview Dr E",
    "sg:city":"Barrie",
    "sg:classifiers":[
        {
            "category":"Shopping",
            "subcategory":"Department Store",
            "type":"Retail Goods"
        }
    ],
    "sg:phone":"+1 705 735 3268",
    "sg:postcode":"L4N 9H5",
    "sg:province":"ON",
    "sg:tags":[
        "shop"
    ],
    "wof:name":"A Buck or Two",
    "wof:placetype":"venue"
},
  "geometry": {"coordinates":[-79.6822433472,44.335811615],"type":"Point"}
}