{
  "type": "Feature",
  "properties": {
    "addr:full":"Toronto ON M5R 2C8",
    "addr:postcode":"m5r 2c8",
    "iso:country":"CA",
    "sg:city":"Toronto",
    "sg:classifiers":[
        {
            "category":"Personal",
            "type":"Services"
        }
    ],
    "sg:phone":"+1 416 966 0216",
    "sg:postcode":"M5R 2C8",
    "sg:province":"ON",
    "sg:tags":[
        "electrolysis"
    ],
    "wof:name":"Bellair Electrolysis",
    "wof:placetype":"venue"
},
  "geometry": {"coordinates":[-79.39083862299999,43.6705093384],"type":"Point"}
}