{
  "type": "Feature",
  "properties": {
    "addr:full":"761 Ch Des Pionniers LA Minerve QC J0T 1S0",
    "addr:housenumber":"761",
    "addr:postcode":"j0t 1s0",
    "addr:street":"Ch Des Pionniers",
    "iso:country":"CA",
    "sg:address":"761 Ch Des Pionniers",
    "sg:city":"LA Minerve",
    "sg:classifiers":[
        {
            "category":"Manufacturing",
            "subcategory":"Lumber",
            "type":"Manufacturing & Wholesale Goods"
        }
    ],
    "sg:phone":"+1 819 274 2442",
    "sg:postcode":"J0T 1S0",
    "sg:province":"QC",
    "sg:tags":[
        "forester"
    ],
    "wof:name":"Cooperative Forestiere Nation",
    "wof:placetype":"venue"
},
  "geometry": {"coordinates":[-75.05513000489999,46.180683136],"type":"Point"}
}