{
  "type": "Feature",
  "properties": {
    "addr:full":"Stoney Creek ON L8J 2T7",
    "addr:postcode":"l8j 2t7",
    "iso:country":"CA",
    "sg:city":"Stoney Creek",
    "sg:classifiers":[
        {
            "category":"Wholesale",
            "subcategory":"Machinery & Supplies",
            "type":"Manufacturing & Wholesale Goods"
        }
    ],
    "sg:phone":"+1 905 662 2828",
    "sg:postcode":"L8J 2T7",
    "sg:province":"ON",
    "sg:tags":[
        "contractor"
    ],
    "wof:name":"Dan Greer Enterprises Ltd",
    "wof:placetype":"venue"
},
  "geometry": {"coordinates":[-79.6898803711,43.2120666504],"type":"Point"}
}