{
  "type": "Feature",
  "properties": {
    "addr:full":"10738 Av Millen Montreal QC H2C 2E6",
    "addr:postcode":"h2c 2e6",
    "addr:street":"Av Millen",
    "iso:country":"CA",
    "sg:address":"10738 Av Millen",
    "sg:city":"Montreal",
    "sg:classifiers":[
        {
            "category":"Shopping",
            "subcategory":"Music",
            "type":"Retail Goods"
        }
    ],
    "sg:phone":"+1 514 383 9999",
    "sg:postcode":"H2C 2E6",
    "sg:province":"QC",
    "sg:tags":[
        "compact",
        "record",
        "disc",
        "tape"
    ],
    "wof:name":"Underworld Skateboard",
    "wof:placetype":"venue"
},
  "geometry": {"coordinates":[-73.668182,45.556717],"type":"Point"}
}