{
  "type": "Feature",
  "properties": {
    "addr:full":"970 Memorial Ave Thunder Bay ON P7B 4A2",
    "addr:housenumber":"970",
    "addr:postcode":"p7b 4a2",
    "addr:street":"Memorial Ave",
    "iso:country":"CA",
    "sg:address":"970 Memorial Ave",
    "sg:city":"Thunder Bay",
    "sg:classifiers":[
        {
            "category":"Autos & Motor Vehicles",
            "subcategory":"Fuel & Gas Station",
            "type":"Retail Goods"
        }
    ],
    "sg:phone":"+1 807 345 1737",
    "sg:postcode":"P7B 4A2",
    "sg:province":"ON",
    "sg:tags":[
        "oil"
    ],
    "wof:name":"Memorial Avenue Gas Bar",
    "wof:placetype":"venue"
},
  "geometry": {"coordinates":[-89.2457351685,48.4086112976],"type":"Point"}
}