{
  "type": "Feature",
  "properties": {
    "addr:full":"Rostock ON N0K 1T0",
    "addr:postcode":"n0k 1t0",
    "iso:country":"CA",
    "sg:city":"Rostock",
    "sg:classifiers":[
        {
            "category":"Wholesale",
            "subcategory":"Auto Parts",
            "type":"Manufacturing & Wholesale Goods"
        }
    ],
    "sg:phone":"+1 519 393 6169",
    "sg:postcode":"N0K 1T0",
    "sg:province":"ON",
    "sg:tags":[
        "automobile",
        "wrecking"
    ],
    "wof:name":"Schneider's Auto Wrecking Ltd",
    "wof:placetype":"venue"
},
  "geometry": {"coordinates":[-81.010643,43.482391],"type":"Point"}
}