{
  "type": "Feature",
  "properties": {
    "addr:full":"333 King Edward Ave Ottawa ON K1N 7M5",
    "addr:housenumber":"333",
    "addr:postcode":"k1n 7m5",
    "addr:street":"King Edward Ave",
    "iso:country":"CA",
    "sg:address":"333 King Edward Ave",
    "sg:city":"Ottawa",
    "sg:classifiers":[
        {
            "category":"Cinema",
            "subcategory":"Movie Theater",
            "type":"Entertainment"
        }
    ],
    "sg:phone":"+1 613 241 2727",
    "sg:postcode":"K1N 7M5",
    "sg:province":"ON",
    "wof:name":"Nouvelle Scene",
    "wof:placetype":"venue"
},
  "geometry": {"coordinates":[-75.686607,45.430202],"type":"Point"}
}