{
  "type": "Feature",
  "properties": {
    "addr:full":"2707 Commercial Dr Vancouver BC V5N 4C5",
    "addr:housenumber":"2707",
    "addr:postcode":"v5n 4c5",
    "addr:street":"Commercial Dr",
    "iso:country":"CA",
    "sg:address":"2707 Commercial Dr",
    "sg:city":"Vancouver",
    "sg:classifiers":[
        {
            "category":"Restaurant",
            "type":"Food & Drink"
        }
    ],
    "sg:phone":"+1 604 876 3343",
    "sg:postcode":"V5N 4C5",
    "sg:province":"BC",
    "sg:tags":[
        "pizza"
    ],
    "wof:name":"Jamaican Pizza Jerk",
    "wof:placetype":"venue"
},
  "geometry": {"coordinates":[-123.069962,49.260338],"type":"Point"}
}