{
  "type": "Feature",
  "properties": {
    "addr:full":"1950 Gorse St Prince George BC V2L 1G6",
    "addr:housenumber":"1950",
    "addr:postcode":"v2l 1g6",
    "addr:street":"Gorse St",
    "iso:country":"CA",
    "sg:address":"1950 Gorse St",
    "sg:city":"Prince George",
    "sg:classifiers":[
        {
            "category":"Professional",
            "subcategory":"Research",
            "type":"Services"
        }
    ],
    "sg:phone":"+1 250 561 7327",
    "sg:postcode":"V2L 1G6",
    "sg:province":"BC",
    "sg:tags":[
        "info",
        "training",
        "recycling",
        "education"
    ],
    "wof:name":"Recycling & Environmental Actn",
    "wof:placetype":"venue"
},
  "geometry": {"coordinates":[-122.737762,53.906147],"type":"Point"}
}