{
  "type": "Feature",
  "properties": {
    "addr:full":"106 Stevenson Rd S Oshawa ON L1J 5M1",
    "addr:housenumber":"106",
    "addr:postcode":"l1j 5m1",
    "addr:street":"Stevenson Rd",
    "iso:country":"CA",
    "sg:address":"106 Stevenson Rd S",
    "sg:city":"Oshawa",
    "sg:classifiers":[
        {
            "category":"Professional",
            "subcategory":"Lawyer & Legal Services",
            "type":"Services"
        }
    ],
    "sg:phone":"+1 905 571 1774",
    "sg:postcode":"L1J 5M1",
    "sg:province":"ON",
    "sg:tags":[
        "attorney"
    ],
    "wof:name":"Woodley, Richard J",
    "wof:placetype":"venue"
},
  "geometry": {"coordinates":[-78.882294,43.890331],"type":"Point"}
}