{
  "type": "Feature",
  "properties": {
    "addr:full":"Lachenaie QC J6W 5H9",
    "addr:postcode":"j6w 5h9",
    "iso:country":"CA",
    "sg:city":"Lachenaie",
    "sg:classifiers":[
        {
            "category":"Professional",
            "subcategory":"Accounting & Tax Preparation",
            "type":"Services"
        }
    ],
    "sg:phone":"+1 450 492 9121",
    "sg:postcode":"J6W 5H9",
    "sg:province":"QC",
    "sg:tags":[
        "accountant"
    ],
    "wof:name":"Consultants Dfg Inc",
    "wof:placetype":"venue"
},
  "geometry": {"coordinates":[-73.62715911870001,45.7108955383],"type":"Point"}
}