{
  "type": "Feature",
  "properties": {
    "addr:full":"29 Eagle St Newmarket ON L3Y 1J2",
    "addr:housenumber":"29",
    "addr:postcode":"l3y 1j2",
    "addr:street":"Eagle St",
    "iso:country":"CA",
    "sg:address":"29 Eagle St",
    "sg:city":"Newmarket",
    "sg:classifiers":[
        {
            "category":"Health Services",
            "subcategory":"Doctor",
            "type":"Services"
        }
    ],
    "sg:phone":"+1 905 836 7989",
    "sg:postcode":"L3Y 1J2",
    "sg:province":"ON",
    "sg:tags":[
        "dentist"
    ],
    "wof:name":"Brown, David A DDS",
    "wof:placetype":"venue"
},
  "geometry": {"coordinates":[-79.4770736694,44.0458106995],"type":"Point"}
}