{
  "type": "Feature",
  "properties": {
    "addr:full":"2283 Tottenham Rd Tottenham ON L0G 1W0",
    "addr:housenumber":"2283",
    "addr:postcode":"l0g 1w0",
    "addr:street":"Tottenham Rd",
    "iso:country":"CA",
    "sg:address":"2283 Tottenham Rd",
    "sg:city":"Tottenham",
    "sg:classifiers":[
        {
            "category":"Building & Trades",
            "subcategory":"Construction",
            "type":"Services"
        }
    ],
    "sg:phone":"+1 905 936 2452",
    "sg:postcode":"L0G 1W0",
    "sg:province":"ON",
    "sg:tags":[
        "general",
        "contractor"
    ],
    "wof:name":"L & D Masonry",
    "wof:placetype":"venue"
},
  "geometry": {"coordinates":[-79.81086000000001,44.041855],"type":"Point"}
}