{
  "type": "Feature",
  "properties": {
    "addr:full":"17005 Hwy 7 #S Sunderland ON L0C 1H0",
    "addr:housenumber":"17005",
    "addr:postcode":"l0c 1h0",
    "addr:street":"Hwy 7 # S Sunderland",
    "iso:country":"CA",
    "sg:address":"17005 Hwy 7 #S",
    "sg:city":"Sunderland",
    "sg:classifiers":[
        {
            "category":"Wholesale",
            "subcategory":"Auto Parts",
            "type":"Manufacturing & Wholesale Goods"
        }
    ],
    "sg:phone":"+1 705 357 3600",
    "sg:postcode":"L0C 1H0",
    "sg:province":"ON",
    "sg:tags":[
        "equipment",
        "truck"
    ],
    "wof:name":"Greenbank Cartage",
    "wof:placetype":"venue"
},
  "geometry": {"coordinates":[-78.9994049072,44.115272522],"type":"Point"}
}