{
  "type": "Feature",
  "properties": {
    "iso:country":"CA",
    "sg:city":"Trenton",
    "sg:classifiers":[
        {
            "category":"Food & Beverages",
            "subcategory":"Groceries & Convenience Stores",
            "type":"Retail Goods"
        }
    ],
    "sg:phone":"+1 613 392 8471",
    "sg:postcode":"K8V 5P5",
    "sg:province":"ON",
    "sg:tags":[
        "variety"
    ],
    "wof:name":"White's Road Variety",
    "wof:placetype":"venue"
},
  "geometry": {"coordinates":[-77.5763092041,44.1011390686],"type":"Point"}
}