{
  "type": "Feature",
  "properties": {
    "addr:full":"Calgary AB T2E 2P8",
    "addr:postcode":"t2e 2p8",
    "iso:country":"CA",
    "sg:city":"Calgary",
    "sg:classifiers":[
        {
            "category":"Shopping",
            "type":"Retail Goods"
        }
    ],
    "sg:phone":"+1 403 230 2218",
    "sg:postcode":"T2E 2P8",
    "sg:province":"AB",
    "sg:tags":[
        "cosmetic",
        "perfume"
    ],
    "wof:name":"Natural Beauty Professional",
    "wof:placetype":"venue"
},
  "geometry": {"coordinates":[-114.062752,51.060883],"type":"Point"}
}