{
  "type": "Feature",
  "properties": {
    "addr:full":"Calgary AB T2P 0Z3",
    "addr:postcode":"t2p 0z3",
    "iso:country":"CA",
    "sg:city":"Calgary",
    "sg:classifiers":[
        {
            "category":"Professional",
            "subcategory":"Lawyer & Legal Services",
            "type":"Services"
        }
    ],
    "sg:phone":"+1 403 266 4440",
    "sg:postcode":"T2P 0Z3",
    "sg:province":"AB",
    "sg:tags":[
        "attorney"
    ],
    "wof:name":"Silver, H Markham",
    "wof:placetype":"venue"
},
  "geometry": {"coordinates":[-114.076843,51.046734],"type":"Point"}
}