{
  "type": "Feature",
  "properties": {
    "addr:full":"262 Beatrice St Toronto ON M6G 3G1",
    "addr:housenumber":"262",
    "addr:postcode":"m6g 3g1",
    "addr:street":"Beatrice St",
    "iso:country":"CA",
    "sg:address":"262 Beatrice St",
    "sg:city":"Toronto",
    "sg:classifiers":[
        {
            "category":"Manufacturing",
            "subcategory":"Jewelry",
            "type":"Manufacturing & Wholesale Goods"
        }
    ],
    "sg:phone":"+1 416 538 5995",
    "sg:postcode":"M6G 3G1",
    "sg:province":"ON",
    "wof:name":"Soto, Carlos",
    "wof:placetype":"venue"
},
  "geometry": {"coordinates":[-79.417976,43.657066],"type":"Point"}
}