{
  "type": "Feature",
  "properties": {
    "addr:full":"869 Ch DE LA Paix St-Sauveur QC J0R 1R2",
    "addr:housenumber":"869",
    "addr:postcode":"j0r 1r2",
    "addr:street":"Ch De La Paix St-Sauveur",
    "iso:country":"CA",
    "sg:address":"869 Ch DE LA Paix",
    "sg:city":"St-Sauveur",
    "sg:classifiers":[
        {
            "category":"Professional",
            "subcategory":"Management & Consulting",
            "type":"Services"
        }
    ],
    "sg:phone":"+1 450 227 0284",
    "sg:postcode":"J0R 1R2",
    "sg:province":"QC",
    "sg:tags":[
        "communications",
        "consultant"
    ],
    "wof:name":"Communications Oncorp Inc",
    "wof:placetype":"venue"
},
  "geometry": {"coordinates":[-74.20668000000001,45.867756],"type":"Point"}
}