{
  "type": "Feature",
  "properties": {
    "addr:full":"3 Carpenter's Lane Bonavista NL A0C 1B0",
    "addr:housenumber":"3",
    "addr:postcode":"a0c 1b0",
    "addr:street":"Carpenter'S Lane",
    "iso:country":"CA",
    "sg:address":"3 Carpenter's Lane",
    "sg:city":"Bonavista",
    "sg:classifiers":[
        {
            "category":"Personal",
            "subcategory":"Beauty Salon",
            "type":"Services"
        }
    ],
    "sg:phone":"+1 709 468 2775",
    "sg:postcode":"A0C 1B0",
    "sg:province":"NL",
    "wof:name":"Beauty Shop",
    "wof:placetype":"venue"
},
  "geometry": {"coordinates":[-53.099121,48.65612],"type":"Point"}
}