{
  "type": "Feature",
  "properties": {
    "addr:full":"8 Lee Valley Dr Port Carling ON P0B 1J0",
    "addr:housenumber":"8",
    "addr:postcode":"p0b 1j0",
    "addr:street":"Lee Valley Dr",
    "iso:country":"CA",
    "sg:address":"8 Lee Valley Dr",
    "sg:city":"Port Carling",
    "sg:classifiers":[
        {
            "category":"Building & Trades",
            "subcategory":"Construction",
            "type":"Services"
        }
    ],
    "sg:phone":"+1 705 765 1343",
    "sg:postcode":"P0B 1J0",
    "sg:province":"ON",
    "sg:tags":[
        "contractor"
    ],
    "wof:name":"Sylvain Roy Builder",
    "wof:placetype":"venue"
},
  "geometry": {"coordinates":[-79.587928772,45.1155700684],"type":"Point"}
}