{
  "type": "Feature",
  "properties": {
    "addr:full":"411 Mill Rd Etobicoke ON M9C 1Y9",
    "addr:housenumber":"411",
    "addr:postcode":"m9c 1y9",
    "addr:street":"Mill Rd",
    "iso:country":"CA",
    "sg:address":"411 Mill Rd",
    "sg:city":"Etobicoke",
    "sg:classifiers":[
        {
            "category":"Education",
            "subcategory":"School",
            "type":"Public Place"
        }
    ],
    "sg:phone":"+1 416 394 7061",
    "sg:postcode":"M9C 1Y9",
    "sg:province":"ON",
    "wof:name":"Mill Valley Junior School",
    "wof:placetype":"venue"
},
  "geometry": {"coordinates":[-79.587677,43.644287],"type":"Point"}
}