{
  "type": "Feature",
  "properties": {
    "addr:full":"5845 Trans Canada Hwy Duncan BC V9L 3R9",
    "addr:housenumber":"5845",
    "addr:postcode":"v9l 3r9",
    "addr:street":"Trans Canada Hwy",
    "iso:country":"CA",
    "sg:address":"5845 Trans Canada Hwy",
    "sg:city":"Duncan",
    "sg:classifiers":[
        {
            "category":"Restaurant",
            "type":"Food & Drink"
        }
    ],
    "sg:phone":"+1 250 748 3424",
    "sg:postcode":"V9L 3R9",
    "sg:province":"BC",
    "wof:name":"Wendy's",
    "wof:placetype":"venue"
},
  "geometry": {"coordinates":[-123.69882200000001,48.780491],"type":"Point"}
}