{
  "type": "Feature",
  "properties": {
    "addr:full":"909 Rue DE L'Acadie Victoriaville QC G6T 1W4",
    "addr:housenumber":"909",
    "addr:postcode":"g6t 1w4",
    "addr:street":"Rue De L'Acadie",
    "iso:country":"CA",
    "sg:address":"909 Rue DE L'Acadie",
    "sg:city":"Victoriaville",
    "sg:classifiers":[
        {
            "category":"Wholesale",
            "subcategory":"Construction Materials",
            "type":"Manufacturing & Wholesale Goods"
        }
    ],
    "sg:phone":"+1 819 751 2282",
    "sg:postcode":"G6T 1W4",
    "sg:province":"QC",
    "sg:tags":[
        "building"
    ],
    "wof:name":"Placages Lignum Inc",
    "wof:placetype":"venue"
},
  "geometry": {"coordinates":[-71.94678497309999,46.0736694336],"type":"Point"}
}