{
  "type": "Feature",
  "properties": {
    "iso:country":"CA",
    "sg:address":"112 Crosby Ave",
    "sg:city":"Richmond Hill",
    "sg:classifiers":[
        {
            "category":"Recreation",
            "type":"Entertainment"
        }
    ],
    "sg:phone":"+1 905 508 0244",
    "sg:postcode":"L4C 9N5",
    "sg:province":"ON",
    "sg:tags":[
        "hall",
        "auditorium"
    ],
    "wof:name":"Masonic Lodge",
    "wof:placetype":"venue"
},
  "geometry": {"coordinates":[-79.4343261719,43.8810005188],"type":"Point"}
}