{
  "type": "Feature",
  "properties": {
    "addr:full":"30 Anne St S Barrie ON L4N 2C6",
    "addr:housenumber":"30",
    "addr:postcode":"l4n 2c6",
    "addr:street":"Anne St S",
    "iso:country":"CA",
    "sg:address":"30 Anne St S",
    "sg:city":"Barrie",
    "sg:classifiers":[
        {
            "category":"Food & Beverages",
            "subcategory":"Liquor & Beverages",
            "type":"Retail Goods"
        }
    ],
    "sg:phone":"+1 705 728 4043",
    "sg:postcode":"L4N 2C6",
    "sg:province":"ON",
    "sg:tags":[
        "beer",
        "ale"
    ],
    "wof:name":"Beer Store",
    "wof:placetype":"venue"
},
  "geometry": {"coordinates":[-79.70407899999999,44.380871],"type":"Point"}
}