{
  "type": "Feature",
  "properties": {
    "iso:country":"CA",
    "sg:address":"61 Rue Paquin",
    "sg:city":"Saint-Charles-DE-Mandeville",
    "sg:classifiers":[
        {
            "category":"Organizations",
            "subcategory":"Professional Association",
            "type":"Services"
        }
    ],
    "sg:phone":"+1 450 835 4951",
    "sg:postcode":"J0K 1L0",
    "sg:province":"QC",
    "wof:name":"Centre D'Entraide Mandeville",
    "wof:placetype":"venue"
},
  "geometry": {"coordinates":[-73.35172271730001,46.3595046997],"type":"Point"}
}