{
  "type": "Feature",
  "properties": {
    "iso:country":"CA",
    "sg:city":"Saint-Felix-DE-Dalquier",
    "sg:classifiers":[
        {
            "category":"Government",
            "subcategory":"Office",
            "type":"Public Place"
        }
    ],
    "sg:phone":"+1 819 727 1732",
    "sg:postcode":"J0Y 1G0",
    "sg:province":"QC",
    "sg:tags":[
        "village"
    ],
    "wof:name":"St Felix DE Dalquier Corp Muni",
    "wof:placetype":"venue"
},
  "geometry": {"coordinates":[-78.1143493652,48.6752967834],"type":"Point"}
}