{
  "type": "Feature",
  "properties": {
    "iso:country":"CA",
    "sg:address":"492 Martindale Rd",
    "sg:city":"Parksville",
    "sg:classifiers":[
        {
            "category":"Building & Trades",
            "subcategory":"Construction",
            "type":"Services"
        }
    ],
    "sg:phone":"+1 250 248 9644",
    "sg:postcode":"V9P 1P9",
    "sg:province":"BC",
    "sg:tags":[
        "stucco",
        "contractor"
    ],
    "wof:name":"Pro Line Stucco",
    "wof:placetype":"venue"
},
  "geometry": {"coordinates":[-124.28755200000001,49.309483],"type":"Point"}
}