{
  "type": "Feature",
  "properties": {
    "addr:full":"245 Bowes Rd Concord ON L4K 1H8",
    "addr:housenumber":"245",
    "addr:postcode":"l4k 1h8",
    "addr:street":"Bowes Rd",
    "iso:country":"CA",
    "sg:address":"245 Bowes Rd",
    "sg:city":"Concord",
    "sg:classifiers":[
        {
            "category":"Manufacturing",
            "subcategory":"Furniture",
            "type":"Manufacturing & Wholesale Goods"
        }
    ],
    "sg:phone":"+1 905 738 8362",
    "sg:postcode":"L4K 1H8",
    "sg:province":"ON",
    "sg:tags":[
        "equipment",
        "supply"
    ],
    "wof:name":"Montana Equipment Ltd",
    "wof:placetype":"venue"
},
  "geometry": {"coordinates":[-79.4925689697,43.8087539673],"type":"Point"}
}