{
  "type": "Feature",
  "properties": {
    "addr:full":"7444 Edmonds St Burnaby BC V3N 1A8",
    "addr:housenumber":"7444",
    "addr:postcode":"v3n 1a8",
    "addr:street":"Edmonds St",
    "iso:country":"CA",
    "sg:address":"7444 Edmonds St",
    "sg:city":"Burnaby",
    "sg:classifiers":[
        {
            "category":"Autos & Motor Vehicles",
            "subcategory":"Auto Supplies",
            "type":"Retail Goods"
        }
    ],
    "sg:phone":"+1 604 526 2912",
    "sg:postcode":"V3N 1A8",
    "sg:province":"BC",
    "sg:tags":[
        "tire"
    ],
    "wof:name":"Big O Tire Dealers Ltd",
    "wof:placetype":"venue"
},
  "geometry": {"coordinates":[-122.947097778,49.2206344604],"type":"Point"}
}