{
  "type": "Feature",
  "properties": {
    "addr:full":"Pointe-Claire QC H9R 4S2",
    "addr:postcode":"h9r 4s2",
    "iso:country":"CA",
    "sg:city":"Pointe-Claire",
    "sg:classifiers":[
        {
            "category":"Wholesale",
            "subcategory":"Chemicals & Plastics",
            "type":"Manufacturing & Wholesale Goods"
        }
    ],
    "sg:phone":"+1 514 694 8644",
    "sg:postcode":"H9R 4S2",
    "sg:province":"QC",
    "wof:name":"Clorox CO Canada Inc",
    "wof:placetype":"venue"
},
  "geometry": {"coordinates":[-73.838218689,45.4578323364],"type":"Point"}
}