{
  "type": "Feature",
  "properties": {
    "iso:country":"CA",
    "sg:address":"625 Boul Lafleche",
    "sg:city":"Baie-Comeau",
    "sg:classifiers":[
        {
            "category":"Restaurant",
            "type":"Food & Drink"
        }
    ],
    "sg:phone":"+1 418 589 9983",
    "sg:postcode":"G5C 1C5",
    "sg:province":"QC",
    "wof:name":"Petit Gouter Enr",
    "wof:placetype":"venue"
},
  "geometry": {"coordinates":[-68.2566452026,49.2004737854],"type":"Point"}
}