{
  "type": "Feature",
  "properties": {
    "addr:full":"4122 Av DE Lorimier Montreal QC H2K 3X7",
    "addr:housenumber":"4122",
    "addr:postcode":"h2k 3x7",
    "addr:street":"Av De Lorimier",
    "iso:country":"CA",
    "sg:address":"4122 Av DE Lorimier",
    "sg:city":"Montreal",
    "sg:classifiers":[
        {
            "category":"Health Services",
            "subcategory":"Nursing And Care Facility",
            "type":"Services"
        }
    ],
    "sg:phone":"+1 514 524 3975",
    "sg:postcode":"H2K 3X7",
    "sg:province":"QC",
    "sg:tags":[
        "home",
        "retirement",
        "community"
    ],
    "wof:name":"Olymbos Residence",
    "wof:placetype":"venue"
},
  "geometry": {"coordinates":[-73.56662,45.532269],"type":"Point"}
}