{
  "type": "Feature",
  "properties": {
    "addr:full":"18 Manor Rd St George NB E5C 3N7",
    "addr:housenumber":"18",
    "addr:postcode":"e5c 3n7",
    "addr:street":"Manor Rd",
    "iso:country":"CA",
    "sg:address":"18 Manor Rd",
    "sg:city":"St George",
    "sg:classifiers":[
        {
            "category":"Organizations",
            "subcategory":"Community Association",
            "type":"Services"
        }
    ],
    "sg:phone":"+1 506 755 2307",
    "sg:postcode":"E5C 3N7",
    "sg:province":"NB",
    "sg:tags":[
        "club"
    ],
    "wof:name":"St George Curling Club",
    "wof:placetype":"venue"
},
  "geometry": {"coordinates":[-66.841446,45.14399],"type":"Point"}
}