{
  "type": "Feature",
  "properties": {
    "addr:full":"15 Mill St S Waterdown ON L0R 2H0",
    "addr:housenumber":"15",
    "addr:postcode":"l0r 2h0",
    "addr:street":"Mill St S",
    "iso:country":"CA",
    "sg:address":"15 Mill St S",
    "sg:city":"Waterdown",
    "sg:classifiers":[
        {
            "category":"Personal",
            "subcategory":"Beauty Salon",
            "type":"Services"
        }
    ],
    "sg:phone":"+1 905 689 5992",
    "sg:postcode":"L0R 2H0",
    "sg:province":"ON",
    "wof:name":"House of Hair Images",
    "wof:placetype":"venue"
},
  "geometry": {"coordinates":[-79.891075,43.334076],"type":"Point"}
}