{
  "type": "Feature",
  "properties": {
    "iso:country":"CA",
    "sg:address":"29 Chapados",
    "sg:city":"Gascons",
    "sg:classifiers":[
        {
            "category":"Organizations",
            "subcategory":"Professional Association",
            "type":"Services"
        }
    ],
    "sg:phone":"+1 418 396 2264",
    "sg:postcode":"G0C 1P0",
    "sg:province":"QC",
    "wof:name":"Maison Des Jeunes DE Gascons",
    "wof:placetype":"venue"
},
  "geometry": {"coordinates":[-64.861000061,48.1939048767],"type":"Point"}
}