{
  "type": "Feature",
  "properties": {
    "addr:full":"Vars ON K0A 3H0",
    "addr:postcode":"k0a 3h0",
    "iso:country":"CA",
    "sg:city":"Vars",
    "sg:classifiers":[
        {
            "category":"Manufacturing",
            "subcategory":"Building Materials",
            "type":"Manufacturing & Wholesale Goods"
        }
    ],
    "sg:phone":"+1 613 443 3399",
    "sg:postcode":"K0A 3H0",
    "sg:province":"ON",
    "wof:name":"M & R Kitchens & Renovations",
    "wof:placetype":"venue"
},
  "geometry": {"coordinates":[-75.35219573969999,45.3546218872],"type":"Point"}
}