{
  "type": "Feature",
  "properties": {
    "addr:full":"6760 Graybar Rd Richmond BC V6W 1J1",
    "addr:housenumber":"6760",
    "addr:postcode":"v6w 1j1",
    "addr:street":"Graybar Rd",
    "iso:country":"CA",
    "sg:address":"6760 Graybar Rd",
    "sg:city":"Richmond",
    "sg:classifiers":[
        {
            "category":"Building & Trades",
            "subcategory":"Construction",
            "type":"Services"
        }
    ],
    "sg:phone":"+1 604 270 8080",
    "sg:postcode":"V6W 1J1",
    "sg:province":"BC",
    "sg:tags":[
        "equipment",
        "kitchen",
        "maker",
        "cabinet"
    ],
    "wof:name":"Nickels Custom Cabinets Ltd",
    "wof:placetype":"venue"
},
  "geometry": {"coordinates":[-122.9895401,49.1651077271],"type":"Point"}
}