{
  "type": "Feature",
  "properties": {
    "addr:full":"Blenheim Rd Cambridge ON N1R 5S3",
    "addr:postcode":"n1r 5s3",
    "addr:street":"Blenheim Rd",
    "iso:country":"CA",
    "sg:address":"Blenheim Rd",
    "sg:city":"Cambridge",
    "sg:classifiers":[
        {
            "category":"Government",
            "subcategory":"Office",
            "type":"Public Place"
        }
    ],
    "sg:phone":"+1 519 740 4569",
    "sg:postcode":"N1R 5S3",
    "sg:province":"ON",
    "sg:tags":[
        "village"
    ],
    "wof:name":"Cambridge Mountview Cemetery",
    "wof:placetype":"venue"
},
  "geometry": {"coordinates":[-80.32089233400001,43.3615989685],"type":"Point"}
}