{
  "type": "Feature",
  "properties": {
    "addr:full":"9441 Jasper Ave NW Edmonton AB T5H 3T8",
    "addr:housenumber":"9441",
    "addr:postcode":"t5h 3t8",
    "addr:street":"Jasper Ave Nw",
    "iso:country":"CA",
    "sg:address":"9441 Jasper Ave NW",
    "sg:city":"Edmonton",
    "sg:classifiers":[
        {
            "category":"Restaurant",
            "type":"Food & Drink"
        }
    ],
    "sg:phone":"+1 780 413 8898",
    "sg:postcode":"T5H 3T8",
    "sg:province":"AB",
    "wof:name":"P & L Chinese Restaurant",
    "wof:placetype":"venue"
},
  "geometry": {"coordinates":[-113.478241,53.545597],"type":"Point"}
}