{
  "type": "Feature",
  "properties": {
    "addr:full":"1800 Bowen Rd Nanaimo BC V9S 5W4",
    "addr:housenumber":"1800",
    "addr:postcode":"v9s 5w4",
    "addr:street":"Bowen Rd",
    "iso:country":"CA",
    "sg:address":"1800 Bowen Rd",
    "sg:city":"Nanaimo",
    "sg:classifiers":[
        {
            "category":"Retail",
            "subcategory":"Veterinary Services",
            "type":"Services"
        }
    ],
    "sg:phone":"+1 250 753 1288",
    "sg:postcode":"V9S 5W4",
    "sg:province":"BC",
    "sg:tags":[
        "veterinarian"
    ],
    "wof:name":"Island Veterinary Hospital",
    "wof:placetype":"venue"
},
  "geometry": {"coordinates":[-123.98054500000001,49.182423],"type":"Point"}
}