{
  "type": "Feature",
  "properties": {
    "addr:full":"Vancouver BC V6B 1R6",
    "addr:postcode":"v6b 1r6",
    "iso:country":"CA",
    "sg:city":"Vancouver",
    "sg:classifiers":[
        {
            "category":"Social Services",
            "type":"Services"
        }
    ],
    "sg:phone":"+1 604 688 0898",
    "sg:postcode":"V6B 1R6",
    "sg:province":"BC",
    "sg:tags":[
        "organization",
        "welfare"
    ],
    "wof:name":"Cba Housing Society",
    "wof:placetype":"venue"
},
  "geometry": {"coordinates":[-123.105774,49.280674],"type":"Point"}
}