{
  "type": "Feature",
  "properties": {
    "addr:full":"73 Cunnington Ave Winnipeg MB R2M 0W6",
    "addr:housenumber":"73",
    "addr:postcode":"r2m 0w6",
    "addr:street":"Cunnington Ave",
    "iso:country":"CA",
    "sg:address":"73 Cunnington Ave",
    "sg:city":"Winnipeg",
    "sg:classifiers":[
        {
            "category":"Personal",
            "subcategory":"Beauty Salon",
            "type":"Services"
        }
    ],
    "sg:phone":"+1 204 233 7963",
    "sg:postcode":"R2M 0W6",
    "sg:province":"MB",
    "wof:name":"Goulet, C",
    "wof:placetype":"venue"
},
  "geometry": {"coordinates":[-97.119011,49.85498],"type":"Point"}
}