{
  "type": "Feature",
  "properties": {
    "addr:full":"100 Rue Napoleon Sept-Iles QC G4R 3L5",
    "addr:housenumber":"100",
    "addr:postcode":"g4r 3l5",
    "addr:street":"Rue Napoleon Sept-Iles",
    "iso:country":"CA",
    "sg:address":"100 Rue Napoleon",
    "sg:city":"Sept-Iles",
    "sg:classifiers":[
        {
            "category":"Retail",
            "subcategory":"Auto Repair",
            "type":"Services"
        }
    ],
    "sg:phone":"+1 418 962 1828",
    "sg:postcode":"G4R 3L5",
    "sg:province":"QC",
    "sg:tags":[
        "repairing",
        "automobile",
        "dealer"
    ],
    "wof:name":"Porlier Automobiles Inc",
    "wof:placetype":"venue"
},
  "geometry": {"coordinates":[-66.375381,50.209534],"type":"Point"}
}