{
  "type": "Feature",
  "properties": {
    "addr:full":"Dalhousie NB E8C 2E2",
    "addr:postcode":"e8c 2e2",
    "iso:country":"CA",
    "sg:city":"Dalhousie",
    "sg:classifiers":[
        {
            "category":"Shopping",
            "subcategory":"Pharmacy",
            "type":"Retail Goods"
        }
    ],
    "sg:phone":"+1 506 684 3381",
    "sg:postcode":"E8C 2E2",
    "sg:province":"NB",
    "wof:name":"Pharmasave",
    "wof:placetype":"venue"
},
  "geometry": {"coordinates":[-66.40052,48.039967],"type":"Point"}
}