{
  "type": "Feature",
  "properties": {
    "addr:full":"12405 107 Ave NW Edmonton AB T5M 1Z2",
    "addr:housenumber":"12405",
    "addr:postcode":"t5m 1z2",
    "addr:street":"107 Ave Nw",
    "iso:country":"CA",
    "sg:address":"12405 107 Ave NW",
    "sg:city":"Edmonton",
    "sg:classifiers":[
        {
            "category":"Shopping",
            "subcategory":"Computers & Home Electronics",
            "type":"Retail Goods"
        }
    ],
    "sg:phone":"+1 780 482 2213",
    "sg:postcode":"T5M 1Z2",
    "sg:province":"AB",
    "sg:tags":[
        "high",
        "fidelity",
        "stereophonic"
    ],
    "wof:name":"Classic hi Fi",
    "wof:placetype":"venue"
},
  "geometry": {"coordinates":[-113.536118,53.550716],"type":"Point"}
}