{
  "type": "Feature",
  "properties": {
    "addr:full":"1350 Adelaide St Crofton BC V0R 1R0",
    "addr:housenumber":"1350",
    "addr:postcode":"v0r 1r0",
    "addr:street":"Adelaide St",
    "iso:country":"CA",
    "sg:address":"1350 Adelaide St",
    "sg:city":"Crofton",
    "sg:classifiers":[
        {
            "category":"Health Services",
            "subcategory":"Health Practitioner",
            "type":"Services"
        }
    ],
    "sg:phone":"+1 250 246 4249",
    "sg:postcode":"V0R 1R0",
    "sg:province":"BC",
    "sg:tags":[
        "physiotherapist"
    ],
    "wof:name":"Crofton Physiotherapist Corp",
    "wof:placetype":"venue"
},
  "geometry": {"coordinates":[-123.63249999999999,48.859024],"type":"Point"}
}