{
  "type": "Feature",
  "properties": {
    "iso:country":"CA",
    "sg:address":"170 Dorion Loop Rd",
    "sg:city":"Dorion",
    "sg:classifiers":[
        {
            "category":"Government",
            "subcategory":"Office",
            "type":"Public Place"
        }
    ],
    "sg:phone":"+1 807 857 2289",
    "sg:postcode":"P0T 1K0",
    "sg:province":"ON",
    "sg:tags":[
        "municipality"
    ],
    "wof:name":"Dorion Municipal Office",
    "wof:placetype":"venue"
},
  "geometry": {"coordinates":[-88.54020690919999,48.7883911133],"type":"Point"}
}