{
  "type": "Feature",
  "properties": {
    "addr:full":"9602 113 St Grande Prairie AB T8V 4Z7",
    "addr:housenumber":"9602",
    "addr:postcode":"t8v 4z7",
    "addr:street":"113 St",
    "iso:country":"CA",
    "sg:address":"9602 113 St",
    "sg:city":"Grande Prairie",
    "sg:classifiers":[
        {
            "category":"Wholesale",
            "subcategory":"Machinery & Supplies",
            "type":"Manufacturing & Wholesale Goods"
        }
    ],
    "sg:phone":"+1 780 538 1792",
    "sg:postcode":"T8V 4Z7",
    "sg:province":"AB",
    "sg:tags":[
        "joint",
        "expansion"
    ],
    "wof:name":"A R Thomson Ltd",
    "wof:placetype":"venue"
},
  "geometry": {"coordinates":[-118.835975647,55.1659011841],"type":"Point"}
}