{
  "type": "Feature",
  "properties": {
    "addr:full":"Luskville QC J0X 2G0",
    "addr:postcode":"j0x 2g0",
    "iso:country":"CA",
    "sg:city":"Luskville",
    "sg:classifiers":[
        {
            "category":"Organizations",
            "subcategory":"Religious Organization",
            "type":"Services"
        }
    ],
    "sg:phone":"+1 819 455 2482",
    "sg:postcode":"J0X 2G0",
    "sg:province":"QC",
    "sg:tags":[
        "church"
    ],
    "wof:name":"Paroisse St-Dominique",
    "wof:placetype":"venue"
},
  "geometry": {"coordinates":[-76.0051727295,45.5290756226],"type":"Point"}
}