{
  "type": "Feature",
  "properties": {
    "addr:full":"694 Rue Saint-Roch Montreal QC H3N 1L1",
    "addr:housenumber":"694",
    "addr:postcode":"h3n 1l1",
    "addr:street":"Rue Saint-Roch",
    "iso:country":"CA",
    "sg:address":"694 Rue Saint-Roch",
    "sg:city":"Montreal",
    "sg:classifiers":[
        {
            "category":"Personal",
            "subcategory":"Beauty Salon",
            "type":"Services"
        }
    ],
    "sg:phone":"+1 514 273 8947",
    "sg:postcode":"H3N 1L1",
    "sg:province":"QC",
    "wof:name":"Gold Scissors",
    "wof:placetype":"venue"
},
  "geometry": {"coordinates":[-73.629631,45.528793],"type":"Point"}
}