{
  "type": "Feature",
  "properties": {
    "addr:full":"465 St. Peter Ave Bathurst NB E2A 2Y5",
    "addr:housenumber":"465",
    "addr:postcode":"e2a 2y5",
    "addr:street":"St. Peter Ave",
    "iso:country":"CA",
    "sg:address":"465 St. Peter Ave",
    "sg:city":"Bathurst",
    "sg:classifiers":[
        {
            "category":"Retail",
            "subcategory":"Car Wash",
            "type":"Services"
        }
    ],
    "sg:phone":"+1 506 548 4334",
    "sg:postcode":"E2A 2Y5",
    "sg:province":"NB",
    "sg:tags":[
        "polishing",
        "washing"
    ],
    "wof:name":"Top Gun Car Wash",
    "wof:placetype":"venue"
},
  "geometry": {"coordinates":[-65.665245,47.628773],"type":"Point"}
}