{
  "type": "Feature",
  "properties": {
    "addr:full":"262 Ottawa St N Hamilton ON L8H 3Z9",
    "addr:housenumber":"262",
    "addr:postcode":"l8h 3z9",
    "addr:street":"Ottawa St N",
    "iso:country":"CA",
    "sg:address":"262 Ottawa St N",
    "sg:city":"Hamilton",
    "sg:classifiers":[
        {
            "category":"Shopping",
            "subcategory":"Crafts & Fabrics",
            "type":"Retail Goods"
        }
    ],
    "sg:phone":"+1 905 544 0002",
    "sg:postcode":"L8H 3Z9",
    "sg:province":"ON",
    "sg:tags":[
        "shop",
        "textile",
        "designer"
    ],
    "wof:name":"Fabric By Designers",
    "wof:placetype":"venue"
},
  "geometry": {"coordinates":[-79.816727,43.249634],"type":"Point"}
}