{
  "type": "Feature",
  "properties": {
    "addr:full":"PO Box 386 Duchess AB T0J 0Z0",
    "addr:housenumber":"po;386",
    "addr:postcode":"t0j 0z0",
    "addr:street":"Box",
    "iso:country":"CA",
    "sg:address":"PO Box 386",
    "sg:city":"Duchess",
    "sg:classifiers":[
        {
            "category":"Manufacturing",
            "subcategory":"Food",
            "type":"Manufacturing & Wholesale Goods"
        }
    ],
    "sg:phone":"+1 403 728 3444",
    "sg:postcode":"T0J 0Z0",
    "sg:province":"AB",
    "sg:tags":[
        "grocer",
        "product",
        "manufacturer"
    ],
    "wof:name":"Dutch Pantry",
    "wof:placetype":"venue"
},
  "geometry": {"coordinates":[-111.90441131599999,50.7324981689],"type":"Point"}
}