{
  "type": "Feature",
  "properties": {
    "addr:full":"18 Germain St Saint John NB E2L 2E5",
    "addr:housenumber":"18",
    "addr:postcode":"nb e2l 2e5",
    "addr:street":"Germain St",
    "iso:country":"CA",
    "sg:address":"18 Germain St",
    "sg:city":"Saint John",
    "sg:classifiers":[
        {
            "category":"Manufacturing",
            "subcategory":"Printing",
            "type":"Manufacturing & Wholesale Goods"
        }
    ],
    "sg:phone":"+1 506 637 9160",
    "sg:postcode":"E2L 2E5",
    "sg:province":"NB",
    "sg:tags":[
        "printer"
    ],
    "wof:name":"Print Digital Inc",
    "wof:placetype":"venue"
},
  "geometry": {"coordinates":[-66.0605926514,45.2737541199],"type":"Point"}
}