{
  "type": "Feature",
  "properties": {
    "addr:full":"Dorval QC H9S 2E3",
    "addr:postcode":"h9s 2e3",
    "iso:country":"CA",
    "sg:city":"Dorval",
    "sg:classifiers":[
        {
            "category":"Recreation",
            "subcategory":"Marina",
            "type":"Entertainment"
        }
    ],
    "sg:phone":"+1 514 631 2720",
    "sg:postcode":"H9S 2E3",
    "sg:province":"QC",
    "wof:name":"Royal St Lawrence Yacht Club",
    "wof:placetype":"venue"
},
  "geometry": {"coordinates":[-73.778862,45.445587],"type":"Point"}
}