{
  "type": "Feature",
  "properties": {
    "addr:full":"Sept-Iles QC G4R 3X2",
    "addr:postcode":"g4r 3x2",
    "iso:country":"CA",
    "sg:city":"Sept-Iles",
    "sg:classifiers":[
        {
            "category":"Organizations",
            "subcategory":"Professional Association",
            "type":"Services"
        }
    ],
    "sg:phone":"+1 418 968 3022",
    "sg:postcode":"G4R 3X2",
    "sg:province":"QC",
    "wof:name":"Module D'Epanouissement Vie",
    "wof:placetype":"venue"
},
  "geometry": {"coordinates":[-66.381767,50.219769],"type":"Point"}
}