{
  "type": "Feature",
  "properties": {
    "addr:full":"5007 50th Ave Caroline AB T0M 0M0",
    "addr:housenumber":"5007",
    "addr:postcode":"t0m 0m0",
    "addr:street":"50Th Ave",
    "iso:country":"CA",
    "sg:address":"5007 50th Ave",
    "sg:city":"Caroline",
    "sg:classifiers":[
        {
            "category":"Home & Garden",
            "subcategory":"Hardware",
            "type":"Retail Goods"
        }
    ],
    "sg:phone":"+1 403 722 3755",
    "sg:postcode":"T0M 0M0",
    "sg:province":"AB",
    "wof:name":"Pioneer General Store",
    "wof:placetype":"venue"
},
  "geometry": {"coordinates":[-114.73981499999999,52.093464],"type":"Point"}
}