{
  "type": "Feature",
  "properties": {
    "iso:country":"CA",
    "sg:address":"142 Albion St S",
    "sg:city":"Amherst",
    "sg:classifiers":[
        {
            "category":"Shopping",
            "subcategory":"Gifts & Souvenirs",
            "type":"Retail Goods"
        }
    ],
    "sg:phone":"+1 902 667 7652",
    "sg:postcode":"B4H 4H4",
    "sg:province":"NS",
    "sg:tags":[
        "cards",
        "greeting"
    ],
    "wof:name":"Carlton Cards",
    "wof:placetype":"venue"
},
  "geometry": {"coordinates":[-64.202438,45.812096],"type":"Point"}
}