{
  "type": "Feature",
  "properties": {
    "addr:full":"1375 Marine Dr North Vancouver BC V7P 3E5",
    "addr:housenumber":"1375",
    "addr:postcode":"v7p 3e5",
    "addr:street":"Marine Dr",
    "iso:country":"CA",
    "sg:address":"1375 Marine Dr",
    "sg:city":"North Vancouver",
    "sg:classifiers":[
        {
            "category":"Autos & Motor Vehicles",
            "subcategory":"Automobile Sales",
            "type":"Retail Goods"
        }
    ],
    "sg:phone":"+1 604 984 9351",
    "sg:postcode":"V7P 3E5",
    "sg:province":"BC",
    "sg:tags":[
        "car",
        "dealer"
    ],
    "wof:name":"Mercedes-Benz Canada Inc",
    "wof:placetype":"venue"
},
  "geometry": {"coordinates":[-123.112709,49.323803],"type":"Point"}
}