{
  "type": "Feature",
  "properties": {
    "iso:country":"CA",
    "sg:city":"Saint-Jerome",
    "sg:classifiers":[
        {
            "category":"Health Services",
            "subcategory":"Optometrist",
            "type":"Services"
        }
    ],
    "sg:phone":"+1 450 438 4647",
    "sg:postcode":"J7Z 5L3",
    "sg:province":"QC",
    "wof:name":"Clinique D'Optometrie Iris",
    "wof:placetype":"venue"
},
  "geometry": {"coordinates":[-74.0036849976,45.7799911499],"type":"Point"}
}