{
  "type": "Feature",
  "properties": {
    "addr:full":"261 Centrepointe Dr Nepean ON K2G 6E8",
    "addr:housenumber":"261",
    "addr:postcode":"k2g 6e8",
    "addr:street":"Centrepointe Dr",
    "iso:country":"CA",
    "sg:address":"261 Centrepointe Dr",
    "sg:city":"Nepean",
    "sg:classifiers":[
        {
            "category":"Food & Beverages",
            "subcategory":"Groceries & Convenience Stores",
            "type":"Retail Goods"
        }
    ],
    "sg:phone":"+1 613 224 8747",
    "sg:postcode":"K2G 6E8",
    "sg:province":"ON",
    "wof:name":"Mike's At Centrepointe",
    "wof:placetype":"venue"
},
  "geometry": {"coordinates":[-75.770561,45.338764],"type":"Point"}
}