{
  "type": "Feature",
  "properties": {
    "addr:full":"157 Augusta Ave Toronto ON M5T 2L4",
    "addr:housenumber":"157",
    "addr:postcode":"m5t 2l4",
    "addr:street":"Augusta Ave",
    "iso:country":"CA",
    "sg:address":"157 Augusta Ave",
    "sg:city":"Toronto",
    "sg:classifiers":[
        {
            "category":"Food & Beverages",
            "subcategory":"Bakery",
            "type":"Retail Goods"
        }
    ],
    "sg:phone":"+1 416 593 6111",
    "sg:postcode":"M5T 2L4",
    "sg:province":"ON",
    "sg:tags":[
        "baker"
    ],
    "wof:name":"Gold Bridge Food CO",
    "wof:placetype":"venue"
},
  "geometry": {"coordinates":[-79.40120697019999,43.6529808044],"type":"Point"}
}