{
  "type": "Feature",
  "properties": {
    "iso:country":"CA",
    "sg:address":"1710 Gershaw Ave Dr SW",
    "sg:city":"Medicine Hat",
    "sg:classifiers":[
        {
            "category":"Organizations",
            "subcategory":"Community Association",
            "type":"Services"
        }
    ],
    "sg:phone":"+1 403 527 2065",
    "sg:postcode":"T1A 7E8",
    "sg:province":"AB",
    "sg:tags":[
        "club"
    ],
    "wof:name":"A A Alcoholics Anonymous",
    "wof:placetype":"venue"
},
  "geometry": {"coordinates":[-110.725868225,50.0234489441],"type":"Point"}
}