{
  "type": "Feature",
  "properties": {
    "addr:full":"5631 No 3 Rd # 201 Richmond BC V6X 2C7",
    "addr:housenumber":"201",
    "addr:postcode":"5631;v6x 2c7",
    "addr:street":"No 3 Rd #",
    "iso:country":"CA",
    "sg:address":"5631 No 3 Rd # 201",
    "sg:city":"Richmond",
    "sg:classifiers":[
        {
            "category":"Building & Trades",
            "subcategory":"Construction",
            "type":"Services"
        }
    ],
    "sg:phone":"+1 604 244 9594",
    "sg:postcode":"V6X 2C7",
    "sg:province":"BC",
    "sg:tags":[
        "general",
        "contractor"
    ],
    "wof:name":"Penta Homes Ltd",
    "wof:placetype":"venue"
},
  "geometry": {"coordinates":[-123.137039,49.174408],"type":"Point"}
}