{
  "type": "Feature",
  "properties": {
    "addr:full":"99 Rue Saint-Vincent Sainte-Agathe-Des-Monts QC J8C 2A8",
    "addr:housenumber":"99",
    "addr:postcode":"j8c 2a8",
    "addr:street":"Rue Saint-Vincent",
    "iso:country":"CA",
    "sg:address":"99 Rue Saint-Vincent",
    "sg:city":"Sainte-Agathe-Des-Monts",
    "sg:classifiers":[
        {
            "category":"Personal",
            "subcategory":"Beauty Salon",
            "type":"Services"
        }
    ],
    "sg:phone":"+1 819 326 6366",
    "sg:postcode":"J8C 2A8",
    "sg:province":"QC",
    "wof:name":"Salon DE Coiffure Zazzy Plus",
    "wof:placetype":"venue"
},
  "geometry": {"coordinates":[-74.288094,46.049351],"type":"Point"}
}