{
  "type": "Feature",
  "properties": {
    "addr:full":"3247 Dufferin St North York ON M6A 2T2",
    "addr:housenumber":"3247",
    "addr:postcode":"m6a 2t2",
    "addr:street":"Dufferin St",
    "iso:country":"CA",
    "sg:address":"3247 Dufferin St",
    "sg:city":"North York",
    "sg:classifiers":[
        {
            "category":"Wholesale",
            "subcategory":"Apparel",
            "type":"Manufacturing & Wholesale Goods"
        }
    ],
    "sg:phone":"+1 905 265 7979",
    "sg:postcode":"M6A 2T2",
    "sg:province":"ON",
    "sg:tags":[
        "clothing"
    ],
    "wof:name":"Firsthand Distributors Ltd",
    "wof:placetype":"venue"
},
  "geometry": {"coordinates":[-79.45581799999999,43.71999],"type":"Point"}
}