{
  "type": "Feature",
  "properties": {
    "addr:full":"3515 2 Ave N Lethbridge AB T1H 0C7",
    "addr:housenumber":"3515",
    "addr:postcode":"t1h 0c7",
    "addr:street":"2 Ave N",
    "iso:country":"CA",
    "sg:address":"3515 2 Ave N",
    "sg:city":"Lethbridge",
    "sg:classifiers":[
        {
            "category":"Wholesale",
            "subcategory":"Farm Supplies",
            "type":"Manufacturing & Wholesale Goods"
        }
    ],
    "sg:phone":"+1 403 320 0006",
    "sg:postcode":"T1H 0C7",
    "sg:province":"AB",
    "sg:tags":[
        "grain"
    ],
    "wof:name":"C B Constantini Ltd",
    "wof:placetype":"venue"
},
  "geometry": {"coordinates":[-112.78914642300001,49.7010154724],"type":"Point"}
}