{
  "type": "Feature",
  "properties": {
    "addr:full":"Kingston ON K7K 2B7",
    "addr:postcode":"k7k 2b7",
    "iso:country":"CA",
    "sg:city":"Kingston",
    "sg:classifiers":[
        {
            "category":"Food & Beverages",
            "subcategory":"Groceries & Convenience Stores",
            "type":"Retail Goods"
        }
    ],
    "sg:phone":"+1 613 546 6929",
    "sg:postcode":"K7K 2B7",
    "sg:province":"ON",
    "sg:tags":[
        "delicatessen"
    ],
    "wof:name":"Merry Market",
    "wof:placetype":"venue"
},
  "geometry": {"coordinates":[-76.50844600000001,44.241344],"type":"Point"}
}