{
  "type": "Feature",
  "properties": {
    "addr:full":"62 Rue Champlain Quebec QC G1K 4H7",
    "addr:housenumber":"62",
    "addr:postcode":"g1k 4h7",
    "addr:street":"Rue Champlain",
    "iso:country":"CA",
    "sg:address":"62 Rue Champlain",
    "sg:city":"Quebec",
    "sg:classifiers":[
        {
            "category":"Shopping",
            "subcategory":"Clothing, Apparel, & Fashions",
            "type":"Retail Goods"
        }
    ],
    "sg:phone":"+1 418 694 9043",
    "sg:postcode":"G1K 4H7",
    "sg:province":"QC",
    "wof:name":"Boutique LA Gitane Enr",
    "wof:placetype":"venue"
},
  "geometry": {"coordinates":[-71.2062988281,46.8049049377],"type":"Point"}
}