{
  "type": "Feature",
  "properties": {
    "addr:full":"75 Bridgeport Rd E Waterloo ON N2J 2K1",
    "addr:housenumber":"75",
    "addr:postcode":"n2j 2k1",
    "addr:street":"Bridgeport Rd E",
    "iso:country":"CA",
    "sg:address":"75 Bridgeport Rd E",
    "sg:city":"Waterloo",
    "sg:classifiers":[
        {
            "category":"Wholesale",
            "subcategory":"Hardware",
            "type":"Manufacturing & Wholesale Goods"
        }
    ],
    "sg:phone":"+1 519 888 0865",
    "sg:postcode":"N2J 2K1",
    "sg:province":"ON",
    "sg:tags":[
        "water",
        "cooler",
        "company",
        "fountain",
        "filter"
    ],
    "wof:name":"Water Store",
    "wof:placetype":"venue"
},
  "geometry": {"coordinates":[-80.51574707029999,43.4688224792],"type":"Point"}
}