{
  "type": "Feature",
  "properties": {
    "iso:country":"CA",
    "sg:city":"Waterloo",
    "sg:classifiers":[
        {
            "category":"Insurance",
            "subcategory":"Insurance Agent",
            "type":"Services"
        }
    ],
    "sg:phone":"+1 519 883 8792",
    "sg:postcode":"N2J 4R8",
    "sg:province":"ON",
    "wof:name":"Ziegler & Assoc",
    "wof:placetype":"venue"
},
  "geometry": {"coordinates":[-80.518166,43.485786],"type":"Point"}
}