{
  "type": "Feature",
  "properties": {
    "addr:full":"177 Division St S Kingsville ON N9Y 1R1",
    "addr:housenumber":"177",
    "addr:postcode":"n9y 1r1",
    "addr:street":"Division St S",
    "iso:country":"CA",
    "sg:address":"177 Division St S",
    "sg:city":"Kingsville",
    "sg:classifiers":[
        {
            "category":"Shopping",
            "type":"Retail Goods"
        }
    ],
    "sg:phone":"+1 519 733 3331",
    "sg:postcode":"N9Y 1R1",
    "sg:province":"ON",
    "sg:tags":[
        "hearing",
        "equipment",
        "supply",
        "impaired"
    ],
    "wof:name":"Cleartone Hearing",
    "wof:placetype":"venue"
},
  "geometry": {"coordinates":[-82.739983,42.031822],"type":"Point"}
}