{
  "type": "Feature",
  "properties": {
    "addr:full":"590 Brant St Burlington ON L7R 2G9",
    "addr:housenumber":"590",
    "addr:postcode":"l7r 2g9",
    "addr:street":"Brant St",
    "iso:country":"CA",
    "sg:address":"590 Brant St",
    "sg:city":"Burlington",
    "sg:classifiers":[
        {
            "category":"Professional",
            "subcategory":"Accounting & Tax Preparation",
            "type":"Services"
        }
    ],
    "sg:phone":"+1 905 632 2141",
    "sg:postcode":"L7R 2G9",
    "sg:province":"ON",
    "sg:tags":[
        "accountant",
        "return",
        "filing"
    ],
    "wof:name":"Tax House",
    "wof:placetype":"venue"
},
  "geometry": {"coordinates":[-79.80334499999999,43.329308],"type":"Point"}
}