{
  "type": "Feature",
  "properties": {
    "addr:full":"11 Rue Tourigny Victoriaville QC G6P 4C5",
    "addr:housenumber":"11",
    "addr:postcode":"g6p 4c5",
    "addr:street":"Rue Tourigny",
    "iso:country":"CA",
    "sg:address":"11 Rue Tourigny",
    "sg:city":"Victoriaville",
    "sg:classifiers":[
        {
            "category":"Bars & Pubs",
            "type":"Food & Drink"
        }
    ],
    "sg:phone":"+1 819 752 3030",
    "sg:postcode":"G6P 4C5",
    "sg:province":"QC",
    "sg:tags":[
        "lounge",
        "cocktail"
    ],
    "wof:name":"Bar Chez Bidou",
    "wof:placetype":"venue"
},
  "geometry": {"coordinates":[-71.95912199999999,46.054867],"type":"Point"}
}