{
  "type": "Feature",
  "properties": {
    "addr:full":"Killaloe ON K0J 2A0",
    "addr:postcode":"k0j 2a0",
    "iso:country":"CA",
    "sg:city":"Killaloe",
    "sg:classifiers":[
        {
            "category":"Building & Trades",
            "subcategory":"Electrical",
            "type":"Services"
        }
    ],
    "sg:phone":"+1 613 757 2955",
    "sg:postcode":"K0J 2A0",
    "sg:province":"ON",
    "sg:tags":[
        "equipment",
        "supply",
        "electronic",
        "electric",
        "contractor"
    ],
    "wof:name":"Welk Electrical Ltd",
    "wof:placetype":"venue"
},
  "geometry": {"coordinates":[-77.425774,45.55368],"type":"Point"}
}