{
  "type": "Feature",
  "properties": {
    "addr:full":"204 9th St W Meadow Lake SK S9X 1S5",
    "addr:housenumber":"204",
    "addr:postcode":"s9x 1s5",
    "addr:street":"9Th St W Meadow",
    "iso:country":"CA",
    "sg:address":"204 9th St W",
    "sg:city":"Meadow Lake",
    "sg:classifiers":[
        {
            "category":"Retail",
            "subcategory":"Car Wash",
            "type":"Services"
        }
    ],
    "sg:phone":"+1 306 236 3339",
    "sg:postcode":"S9X 1S5",
    "sg:province":"SK",
    "sg:tags":[
        "polishing",
        "washing"
    ],
    "wof:name":"Meadow Wash & Water Clinic",
    "wof:placetype":"venue"
},
  "geometry": {"coordinates":[-108.45298,54.124512],"type":"Point"}
}