{
  "type": "Feature",
  "properties": {
    "addr:full":"93 Main Springhill NS B0M 1X0",
    "addr:housenumber":"93",
    "addr:postcode":"b0m 1x0",
    "addr:street":"Main",
    "iso:country":"CA",
    "sg:address":"93 Main",
    "sg:city":"Springhill",
    "sg:classifiers":[
        {
            "category":"Organizations",
            "subcategory":"Religious Organization",
            "type":"Services"
        }
    ],
    "sg:phone":"+1 902 597 3954",
    "sg:postcode":"B0M 1X0",
    "sg:province":"NS",
    "sg:tags":[
        "church"
    ],
    "wof:name":"Salvation Army",
    "wof:placetype":"venue"
},
  "geometry": {"coordinates":[-64.055862,45.650784],"type":"Point"}
}