{
  "type": "Feature",
  "properties": {
    "addr:full":"1415 Bridgestone Lane Mississauga ON L5J 4E1",
    "addr:housenumber":"1415",
    "addr:postcode":"l5j 4e1",
    "addr:street":"Bridgestone Lane",
    "iso:country":"CA",
    "sg:address":"1415 Bridgestone Lane",
    "sg:city":"Mississauga",
    "sg:classifiers":[
        {
            "category":"Professional",
            "subcategory":"Computer Services",
            "type":"Services"
        }
    ],
    "sg:phone":"+1 905 855 1304",
    "sg:postcode":"L5J 4E1",
    "sg:province":"ON",
    "sg:tags":[
        "consultant"
    ],
    "wof:name":"Aixia Computer Technics",
    "wof:placetype":"venue"
},
  "geometry": {"coordinates":[-79.610741,43.521309],"type":"Point"}
}