{
  "type": "Feature",
  "properties": {
    "iso:country":"CA",
    "sg:address":"109 Main St",
    "sg:city":"Spiritwood",
    "sg:classifiers":[
        {
            "category":"Shopping",
            "subcategory":"Used Merchandise",
            "type":"Retail Goods"
        }
    ],
    "sg:phone":"+1 306 883 2266",
    "sg:postcode":"S0J 2M0",
    "sg:province":"SK",
    "sg:tags":[
        "second",
        "pawnbroker",
        "store",
        "hand"
    ],
    "wof:name":"Spiritwood New & Used Furn",
    "wof:placetype":"venue"
},
  "geometry": {"coordinates":[-107.51890564,53.3658561707],"type":"Point"}
}