{
  "type": "Feature",
  "properties": {
    "addr:full":"Edmonton AB T5S 1G4",
    "addr:postcode":"t5s 1g4",
    "iso:country":"CA",
    "sg:city":"Edmonton",
    "sg:classifiers":[
        {
            "category":"Organizations",
            "subcategory":"Professional Association",
            "type":"Services"
        }
    ],
    "sg:phone":"+1 780 483 9404",
    "sg:postcode":"T5S 1G4",
    "sg:province":"AB",
    "wof:name":"Yellow Head Tribal Comm Crrctn",
    "wof:placetype":"venue"
},
  "geometry": {"coordinates":[-113.619178772,53.5487480164],"type":"Point"}
}