{
  "type": "Feature",
  "properties": {
    "addr:full":"Nanaimo BC V9T 6L8",
    "addr:postcode":"v9t 6l8",
    "iso:country":"CA",
    "sg:city":"Nanaimo",
    "sg:classifiers":[
        {
            "category":"Banks & Credit Unions",
            "subcategory":"Bank",
            "type":"Services"
        }
    ],
    "sg:phone":"+1 250 390 1248",
    "sg:postcode":"V9T 6L8",
    "sg:province":"BC",
    "wof:name":"Td Canada Trust",
    "wof:placetype":"venue"
},
  "geometry": {"coordinates":[-124.035461426,49.2253608704],"type":"Point"}
}