{
  "type": "Feature",
  "properties": {
    "addr:full":"199 Water St Windsor NS B0N 2T0",
    "addr:housenumber":"199",
    "addr:postcode":"b0n 2t0",
    "addr:street":"Water St",
    "iso:country":"CA",
    "sg:address":"199 Water St",
    "sg:city":"Windsor",
    "sg:classifiers":[
        {
            "category":"Autos & Motor Vehicles",
            "subcategory":"Automobile Sales",
            "type":"Retail Goods"
        }
    ],
    "sg:phone":"+1 902 798 2720",
    "sg:postcode":"B0N 2T0",
    "sg:province":"NS",
    "sg:tags":[
        "car",
        "dealer"
    ],
    "wof:name":"Stephens & Yeaton Ltd",
    "wof:placetype":"venue"
},
  "geometry": {"coordinates":[-64.140366,44.993279],"type":"Point"}
}