{
  "type": "Feature",
  "properties": {
    "addr:full":"1945 Main St Fruitvale BC V0G 1L0",
    "addr:housenumber":"1945",
    "addr:postcode":"v0g 1l0",
    "addr:street":"Main St",
    "iso:country":"CA",
    "sg:address":"1945 Main St",
    "sg:city":"Fruitvale",
    "sg:classifiers":[
        {
            "category":"Banks & Credit Unions",
            "subcategory":"Bank",
            "type":"Services"
        }
    ],
    "sg:phone":"+1 250 367 9223",
    "sg:postcode":"V0G 1L0",
    "sg:province":"BC",
    "wof:name":"Kootenay Savings Credit Union",
    "wof:placetype":"venue"
},
  "geometry": {"coordinates":[-117.54684399999999,49.113754],"type":"Point"}
}