{
  "type": "Feature",
  "properties": {
    "iso:country":"CA",
    "sg:city":"Waterloo",
    "sg:classifiers":[
        {
            "category":"Manufacturing",
            "subcategory":"Printing",
            "type":"Manufacturing & Wholesale Goods"
        }
    ],
    "sg:phone":"+1 519 747 5722",
    "sg:postcode":"N2L 6H7",
    "sg:province":"ON",
    "sg:tags":[
        "publisher"
    ],
    "wof:name":"Mennonite Publishing House",
    "wof:placetype":"venue"
},
  "geometry": {"coordinates":[-80.5385971069,43.4939689636],"type":"Point"}
}