{
  "type": "Feature",
  "properties": {
    "addr:full":"248 Rue Principale Lambton QC G0M 1H0",
    "addr:housenumber":"248",
    "addr:postcode":"g0m 1h0",
    "addr:street":"Rue Principale",
    "iso:country":"CA",
    "sg:address":"248 Rue Principale",
    "sg:city":"Lambton",
    "sg:classifiers":[
        {
            "category":"Food & Beverages",
            "subcategory":"Bakery",
            "type":"Retail Goods"
        }
    ],
    "sg:phone":"+1 418 486 2839",
    "sg:postcode":"G0M 1H0",
    "sg:province":"QC",
    "sg:tags":[
        "baker"
    ],
    "wof:name":"Boulangerie Lambton Inc",
    "wof:placetype":"venue"
},
  "geometry": {"coordinates":[-71.0925827026,45.8351097107],"type":"Point"}
}