{
  "type": "Feature",
  "properties": {
    "addr:full":"93 Rte Marie-Victorin Saint-Francois-Du-Lac QC J0G 1M0",
    "addr:housenumber":"93",
    "addr:postcode":"j0g 1m0",
    "addr:street":"Rte Marie-Victorin",
    "iso:country":"CA",
    "sg:address":"93 Rte Marie-Victorin",
    "sg:city":"Saint-Francois-Du-Lac",
    "sg:classifiers":[
        {
            "category":"Education",
            "subcategory":"School",
            "type":"Public Place"
        }
    ],
    "sg:phone":"+1 450 568 2277",
    "sg:postcode":"J0G 1M0",
    "sg:province":"QC",
    "wof:name":"Centre DE Formation Gen-Adults",
    "wof:placetype":"venue"
},
  "geometry": {"coordinates":[-72.8237609863,46.0577468872],"type":"Point"}
}