{
  "type": "Feature",
  "properties": {
    "addr:full":"148 Queen St Dunnville ON N1A 1H7",
    "addr:housenumber":"148",
    "addr:postcode":"n1a 1h7",
    "addr:street":"Queen St",
    "iso:country":"CA",
    "sg:address":"148 Queen St",
    "sg:city":"Dunnville",
    "sg:classifiers":[
        {
            "category":"Shopping",
            "subcategory":"Crafts & Fabrics",
            "type":"Retail Goods"
        }
    ],
    "sg:phone":"+1 905 701 0115",
    "sg:postcode":"N1A 1H7",
    "sg:province":"ON",
    "sg:tags":[
        "shop"
    ],
    "wof:name":"Town & Country Craft Supplies",
    "wof:placetype":"venue"
},
  "geometry": {"coordinates":[-79.61790499999999,42.902363],"type":"Point"}
}