{
  "type": "Feature",
  "properties": {
    "iso:country":"CA",
    "sg:city":"Courtenay",
    "sg:classifiers":[
        {
            "category":"Government",
            "subcategory":"Office",
            "type":"Public Place"
        }
    ],
    "sg:phone":"+1 250 334 1125",
    "sg:postcode":"V9N 2C4",
    "sg:province":"BC",
    "wof:name":"B C Corrections Branch",
    "wof:placetype":"venue"
},
  "geometry": {"coordinates":[-124.99948120099999,49.689289093],"type":"Point"}
}