{
  "type": "Feature",
  "properties": {
    "addr:full":"252 Main St # 2 Picton ON K0K 2T0",
    "addr:housenumber":"252",
    "addr:postcode":"k0k 2t0",
    "addr:street":"Main St # 2",
    "iso:country":"CA",
    "sg:address":"252 Main St # 2",
    "sg:city":"Picton",
    "sg:classifiers":[
        {
            "category":"Restaurant",
            "type":"Food & Drink"
        }
    ],
    "sg:phone":"+1 613 476 6374",
    "sg:postcode":"K0K 2T0",
    "sg:province":"ON",
    "wof:name":"Currah's Cafe & Restaurant",
    "wof:placetype":"venue"
},
  "geometry": {"coordinates":[-77.14032,44.007938],"type":"Point"}
}