{
  "type": "Feature",
  "properties": {
    "addr:full":"3913 44 Ave Camrose AB T4V 3T2",
    "addr:housenumber":"3913",
    "addr:postcode":"t4v 3t2",
    "addr:street":"44 Ave",
    "iso:country":"CA",
    "sg:address":"3913 44 Ave",
    "sg:city":"Camrose",
    "sg:classifiers":[
        {
            "category":"Building & Trades",
            "subcategory":"Construction",
            "type":"Services"
        }
    ],
    "sg:phone":"+1 780 672 1444",
    "sg:postcode":"T4V 3T2",
    "sg:province":"AB",
    "sg:tags":[
        "steam",
        "cleaning"
    ],
    "wof:name":"Double T Mobile Sandblasting",
    "wof:placetype":"venue"
},
  "geometry": {"coordinates":[-112.807159,53.010551],"type":"Point"}
}