{
  "type": "Feature",
  "properties": {
    "addr:full":"2088 Dundas St Cardinal ON K0E 1E0",
    "addr:housenumber":"2088",
    "addr:postcode":"k0e 1e0",
    "addr:street":"Dundas St",
    "iso:country":"CA",
    "sg:address":"2088 Dundas St",
    "sg:city":"Cardinal",
    "sg:classifiers":[
        {
            "category":"Professional",
            "subcategory":"Lawyer & Legal Services",
            "type":"Services"
        }
    ],
    "sg:phone":"+1 613 657 3184",
    "sg:postcode":"K0E 1E0",
    "sg:province":"ON",
    "sg:tags":[
        "attorney"
    ],
    "wof:name":"Remillard, Peter J",
    "wof:placetype":"venue"
},
  "geometry": {"coordinates":[-75.380066,44.787636],"type":"Point"}
}