{
  "type": "Feature",
  "properties": {
    "addr:full":"9154 279 Rte Saint-Charles-DE-Bellechasse QC G0R 2T0",
    "addr:housenumber":"9154",
    "addr:postcode":"g0r 2t0",
    "addr:street":"279 Rte",
    "iso:country":"CA",
    "sg:address":"9154 279 Rte",
    "sg:city":"Saint-Charles-DE-Bellechasse",
    "sg:classifiers":[
        {
            "category":"Home & Garden",
            "subcategory":"Garden Supply",
            "type":"Retail Goods"
        }
    ],
    "sg:phone":"+1 418 887 3653",
    "sg:postcode":"G0R 2T0",
    "sg:province":"QC",
    "sg:tags":[
        "engine",
        "lawn",
        "mower"
    ],
    "wof:name":"Roy Mini-Moteurs Enr",
    "wof:placetype":"venue"
},
  "geometry": {"coordinates":[-70.9421844482,46.7705383301],"type":"Point"}
}