{
  "type": "Feature",
  "properties": {
    "addr:full":"Montreal QC H3X 2J7",
    "addr:postcode":"h3x 2j7",
    "iso:country":"CA",
    "sg:city":"Montreal",
    "sg:classifiers":[
        {
            "category":"Personal",
            "subcategory":"Beauty Salon",
            "type":"Services"
        }
    ],
    "sg:phone":"+1 514 739 4746",
    "sg:postcode":"H3X 2J7",
    "sg:province":"QC",
    "wof:name":"Inter Coupe Monsieur",
    "wof:placetype":"venue"
},
  "geometry": {"coordinates":[-73.6406707764,45.4884529114],"type":"Point"}
}