{
  "type": "Feature",
  "properties": {
    "addr:full":"5325 Ch Queen-Mary Montreal QC H3X 1T9",
    "addr:housenumber":"5325",
    "addr:postcode":"h3x 1t9",
    "addr:street":"Ch Queen-Mary",
    "iso:country":"CA",
    "sg:address":"5325 Ch Queen-Mary",
    "sg:city":"Montreal",
    "sg:classifiers":[
        {
            "category":"Manufacturing",
            "subcategory":"Printing",
            "type":"Manufacturing & Wholesale Goods"
        }
    ],
    "sg:phone":"+1 514 481 0609",
    "sg:postcode":"H3X 1T9",
    "sg:province":"QC",
    "sg:tags":[
        "publisher"
    ],
    "wof:name":"Snowdon Investments Inc",
    "wof:placetype":"venue"
},
  "geometry": {"coordinates":[-73.629807,45.483181],"type":"Point"}
}