{
  "type": "Feature",
  "properties": {
    "iso:country":"CA",
    "sg:city":"Saint-Lazare",
    "sg:classifiers":[
        {
            "category":"Sports & Exercise",
            "subcategory":"Gym",
            "type":"Entertainment"
        }
    ],
    "sg:phone":"+1 450 458 4766",
    "sg:postcode":"J7T 2H8",
    "sg:province":"QC",
    "sg:tags":[
        "club",
        "health",
        "studio",
        "gymnasium"
    ],
    "wof:name":"Hudson Racquet Club",
    "wof:placetype":"venue"
},
  "geometry": {"coordinates":[-74.1732559204,45.4360809326],"type":"Point"}
}