{
  "type": "Feature",
  "properties": {
    "addr:full":"Edmonton AB T5E 6C1",
    "addr:postcode":"t5e 6c1",
    "iso:country":"CA",
    "sg:city":"Edmonton",
    "sg:classifiers":[
        {
            "category":"Shopping",
            "subcategory":"Department Store",
            "type":"Retail Goods"
        }
    ],
    "sg:phone":"+1 780 473 1296",
    "sg:postcode":"T5E 6C1",
    "sg:province":"AB",
    "sg:tags":[
        "shop",
        "gift"
    ],
    "wof:name":"Dollar Store",
    "wof:placetype":"venue"
},
  "geometry": {"coordinates":[-113.49037199999999,53.546219],"type":"Point"}
}