{
  "type": "Feature",
  "properties": {
    "addr:full":"4418 Eleniak Rd NW Edmonton AB T6B 2S1",
    "addr:housenumber":"4418",
    "addr:postcode":"t6b 2s1",
    "addr:street":"Eleniak Rd Nw",
    "iso:country":"CA",
    "sg:address":"4418 Eleniak Rd NW",
    "sg:city":"Edmonton",
    "sg:classifiers":[
        {
            "category":"Retail",
            "subcategory":"Auto Repair",
            "type":"Services"
        }
    ],
    "sg:phone":"+1 780 463 9228",
    "sg:postcode":"T6B 2S1",
    "sg:province":"AB",
    "sg:tags":[
        "truck"
    ],
    "wof:name":"Heavy Hauler Svc & Repair Ltd",
    "wof:placetype":"venue"
},
  "geometry": {"coordinates":[-113.410545,53.503387],"type":"Point"}
}