{
  "type": "Feature",
  "properties": {
    "addr:full":"6285 Rue Marivaux Saint-Leonard QC H1P 3H6",
    "addr:housenumber":"6285",
    "addr:postcode":"h1p 3h6",
    "addr:street":"Rue Marivaux",
    "iso:country":"CA",
    "sg:address":"6285 Rue Marivaux",
    "sg:city":"Saint-Leonard",
    "sg:classifiers":[
        {
            "category":"Manufacturing",
            "subcategory":"Metals",
            "type":"Manufacturing & Wholesale Goods"
        }
    ],
    "sg:phone":"+1 514 323 4691",
    "sg:postcode":"H1P 3H6",
    "sg:province":"QC",
    "sg:tags":[
        "ironwork"
    ],
    "wof:name":"Waverley Metal",
    "wof:placetype":"venue"
},
  "geometry": {"coordinates":[-73.6058883667,45.6027832031],"type":"Point"}
}