{
  "type": "Feature",
  "properties": {
    "addr:full":"Toronto ON M4K 1N2",
    "addr:postcode":"m4k 1n2",
    "iso:country":"CA",
    "sg:city":"Toronto",
    "sg:classifiers":[
        {
            "category":"Food & Beverages",
            "subcategory":"Candy",
            "type":"Retail Goods"
        }
    ],
    "sg:phone":"+1 416 778 7978",
    "sg:postcode":"M4K 1N2",
    "sg:province":"ON",
    "sg:tags":[
        "confectionery"
    ],
    "wof:name":"Simryn Chocolate",
    "wof:placetype":"venue"
},
  "geometry": {"coordinates":[-79.35701,43.676388],"type":"Point"}
}