{
  "type": "Feature",
  "properties": {
    "addr:full":"35 Jillson Ave York ON M6S 2P3",
    "addr:housenumber":"35",
    "addr:postcode":"m6s 2p3",
    "addr:street":"Jillson Ave",
    "iso:country":"CA",
    "sg:address":"35 Jillson Ave",
    "sg:city":"York",
    "sg:classifiers":[
        {
            "category":"Building & Trades",
            "subcategory":"Construction",
            "type":"Services"
        }
    ],
    "sg:phone":"+1 416 767 8376",
    "sg:postcode":"M6S 2P3",
    "sg:province":"ON",
    "sg:tags":[
        "masonry",
        "contractor"
    ],
    "wof:name":"Masonryworks",
    "wof:placetype":"venue"
},
  "geometry": {"coordinates":[-79.4866409302,43.6649284363],"type":"Point"}
}