{
  "type": "Feature",
  "properties": {
    "addr:full":"Brockville ON K6V 5T3",
    "addr:postcode":"k6v 5t3",
    "iso:country":"CA",
    "sg:city":"Brockville",
    "sg:classifiers":[
        {
            "category":"Building & Trades",
            "subcategory":"Plumbing",
            "type":"Services"
        }
    ],
    "sg:phone":"+1 613 342 3083",
    "sg:postcode":"K6V 5T3",
    "sg:province":"ON",
    "sg:tags":[
        "contractor"
    ],
    "wof:name":"Pryer, E W",
    "wof:placetype":"venue"
},
  "geometry": {"coordinates":[-75.683014,44.590389],"type":"Point"}
}