{
  "type": "Feature",
  "properties": {
    "addr:full":"50 Parkinson Rd Markham ON L3P 4G5",
    "addr:housenumber":"50",
    "addr:postcode":"l3p 4g5",
    "addr:street":"Parkinson Rd",
    "iso:country":"CA",
    "sg:address":"50 Parkinson Rd",
    "sg:city":"Markham",
    "sg:classifiers":[
        {
            "category":"Wholesale",
            "subcategory":"Auto Parts",
            "type":"Manufacturing & Wholesale Goods"
        }
    ],
    "sg:phone":"+1 905 201 9711",
    "sg:postcode":"L3P 4G5",
    "sg:province":"ON",
    "sg:tags":[
        "body",
        "automobile",
        "shop"
    ],
    "wof:name":"Flatline Spray Booth",
    "wof:placetype":"venue"
},
  "geometry": {"coordinates":[-79.24256099999999,43.890739],"type":"Point"}
}