{
  "type": "Feature",
  "properties": {
    "addr:full":"900 20th St W Saskatoon SK S7M 0Y4",
    "addr:housenumber":"900",
    "addr:postcode":"s7m 0y4",
    "addr:street":"20Th St W",
    "iso:country":"CA",
    "sg:address":"900 20th St W",
    "sg:city":"Saskatoon",
    "sg:classifiers":[
        {
            "category":"Shopping",
            "subcategory":"Used Merchandise",
            "type":"Retail Goods"
        }
    ],
    "sg:phone":"+1 306 664 1939",
    "sg:postcode":"S7M 0Y4",
    "sg:province":"SK",
    "sg:tags":[
        "pawnbroker"
    ],
    "wof:name":"City Used Furniture & Pawn",
    "wof:placetype":"venue"
},
  "geometry": {"coordinates":[-106.683098,52.126316],"type":"Point"}
}