{
  "type": "Feature",
  "properties": {
    "addr:full":"Lochend Rd Cochrane AB T4C 1A2",
    "addr:postcode":"t4c 1a2",
    "addr:street":"Lochend Rd",
    "iso:country":"CA",
    "sg:address":"Lochend Rd",
    "sg:city":"Cochrane",
    "sg:classifiers":[
        {
            "category":"Professional",
            "subcategory":"Engineering",
            "type":"Services"
        }
    ],
    "sg:phone":"+1 403 932 4848",
    "sg:postcode":"T4C 1A2",
    "sg:province":"AB",
    "sg:tags":[
        "engineer"
    ],
    "wof:name":"Metal Engineers Intl Inc",
    "wof:placetype":"venue"
},
  "geometry": {"coordinates":[-114.468002,51.190826],"type":"Point"}
}