{
  "type": "Feature",
  "properties": {
    "addr:full":"107 Main St N Sauble Beach ON N0H 2G0",
    "addr:housenumber":"107",
    "addr:postcode":"n0h 2g0",
    "addr:street":"Main St N",
    "iso:country":"CA",
    "sg:address":"107 Main St N",
    "sg:city":"Sauble Beach",
    "sg:classifiers":[
        {
            "category":"Shopping",
            "subcategory":"Clothing, Apparel, & Fashions",
            "type":"Retail Goods"
        }
    ],
    "sg:phone":"+1 519 422 0390",
    "sg:postcode":"N0H 2G0",
    "sg:province":"ON",
    "wof:name":"Iptionelle Outlet",
    "wof:placetype":"venue"
},
  "geometry": {"coordinates":[-81.270279,44.629524],"type":"Point"}
}