{
  "type": "Feature",
  "properties": {
    "addr:full":"205 Hiram St Lower Level Bracebridge ON P1L 2C1",
    "addr:housenumber":"205",
    "addr:postcode":"p1l 2c1",
    "addr:street":"Hiram St",
    "iso:country":"CA",
    "sg:address":"205 Hiram St Lower Level",
    "sg:city":"Bracebridge",
    "sg:classifiers":[
        {
            "category":"Shopping",
            "type":"Retail Goods"
        }
    ],
    "sg:phone":"+1 705 646 2227",
    "sg:postcode":"P1L 2C1",
    "sg:province":"ON",
    "sg:tags":[
        "supply",
        "equipment",
        "audiologists",
        "hearing",
        "impaired"
    ],
    "wof:name":"Muskoka Audiology Clinic",
    "wof:placetype":"venue"
},
  "geometry": {"coordinates":[-79.2886352539,45.0555801392],"type":"Point"}
}