{
  "type": "Feature",
  "properties": {
    "addr:full":"91 James St Parry Sound ON P2A 1T7",
    "addr:housenumber":"91",
    "addr:postcode":"p2a 1t7",
    "addr:street":"James St",
    "iso:country":"CA",
    "sg:address":"91 James St",
    "sg:city":"Parry Sound",
    "sg:classifiers":[
        {
            "category":"Government",
            "subcategory":"Jail",
            "type":"Public Place"
        }
    ],
    "sg:phone":"+1 705 746 6218",
    "sg:postcode":"P2A 1T7",
    "sg:province":"ON",
    "sg:tags":[
        "provincial",
        "institution"
    ],
    "wof:name":"Ontario Correctional Svc Dept",
    "wof:placetype":"venue"
},
  "geometry": {"coordinates":[-80.033508,45.346916],"type":"Point"}
}