{
  "type": "Feature",
  "properties": {
    "addr:full":"Laval QC H7V 2S3",
    "addr:postcode":"h7v 2s3",
    "iso:country":"CA",
    "sg:city":"Laval",
    "sg:classifiers":[
        {
            "category":"Retail",
            "subcategory":"Auto Repair",
            "type":"Services"
        }
    ],
    "sg:phone":"+1 450 681 4143",
    "sg:postcode":"H7V 2S3",
    "sg:province":"QC",
    "sg:tags":[
        "repairing",
        "automobile"
    ],
    "wof:name":"Garage DE L'Esterel",
    "wof:placetype":"venue"
},
  "geometry": {"coordinates":[-73.7345962524,45.5383071899],"type":"Point"}
}