{
  "type": "Feature",
  "properties": {
    "addr:full":"81 Gertrude St E North Bay ON P1A 1K1",
    "addr:housenumber":"81",
    "addr:postcode":"p1a 1k1",
    "addr:street":"Gertrude St E",
    "iso:country":"CA",
    "sg:address":"81 Gertrude St E",
    "sg:city":"North Bay",
    "sg:classifiers":[
        {
            "category":"Wholesale",
            "subcategory":"Machinery & Supplies",
            "type":"Manufacturing & Wholesale Goods"
        }
    ],
    "sg:phone":"+1 705 474 3109",
    "sg:postcode":"P1A 1K1",
    "sg:province":"ON",
    "sg:tags":[
        "equipment",
        "industrial",
        "janitor"
    ],
    "wof:name":"Ace Industrial Supply",
    "wof:placetype":"venue"
},
  "geometry": {"coordinates":[-79.446144104,46.2893676758],"type":"Point"}
}