{
  "type": "Feature",
  "properties": {
    "addr:full":"546 Government Rd W Chaput Hughes ON P0K 1A0",
    "addr:housenumber":"546",
    "addr:postcode":"p0k 1a0",
    "addr:street":"Government Rd W Chaput",
    "iso:country":"CA",
    "sg:address":"546 Government Rd W",
    "sg:city":"Chaput Hughes",
    "sg:classifiers":[
        {
            "category":"Retail",
            "subcategory":"Repair Shop",
            "type":"Services"
        }
    ],
    "sg:phone":"+1 705 567 1128",
    "sg:postcode":"P0K 1A0",
    "sg:province":"ON",
    "sg:tags":[
        "appliance"
    ],
    "wof:name":"Blake's Appliance Svc",
    "wof:placetype":"venue"
},
  "geometry": {"coordinates":[-80.08268,48.122501],"type":"Point"}
}