{
  "type": "Feature",
  "properties": {
    "addr:full":"501 1st Ave St Brieux SK S0K 3V0",
    "addr:housenumber":"501",
    "addr:postcode":"s0k 3v0",
    "addr:street":"1St Ave St",
    "iso:country":"CA",
    "sg:address":"501 1st Ave",
    "sg:city":"St Brieux",
    "sg:classifiers":[
        {
            "category":"Health Services",
            "subcategory":"Nursing And Care Facility",
            "type":"Services"
        }
    ],
    "sg:phone":"+1 306 275 2227",
    "sg:postcode":"S0K 3V0",
    "sg:province":"SK",
    "sg:tags":[
        "home",
        "convalescent"
    ],
    "wof:name":"Chateau Providence Home",
    "wof:placetype":"venue"
},
  "geometry": {"coordinates":[-104.892776,52.634571],"type":"Point"}
}