{
  "type": "Feature",
  "properties": {
    "addr:full":"Pine Rd Mattawa ON P0H 1V0",
    "addr:postcode":"p0h 1v0",
    "addr:street":"Pine Rd",
    "iso:country":"CA",
    "sg:address":"Pine Rd",
    "sg:city":"Mattawa",
    "sg:classifiers":[
        {
            "category":"Wholesale",
            "subcategory":"Machinery & Supplies",
            "type":"Manufacturing & Wholesale Goods"
        }
    ],
    "sg:phone":"+1 705 744 3246",
    "sg:postcode":"P0H 1V0",
    "sg:province":"ON",
    "sg:tags":[
        "instrument",
        "laser",
        "surveying"
    ],
    "wof:name":"Northern Survey Supply",
    "wof:placetype":"venue"
},
  "geometry": {"coordinates":[-78.701981,46.316418],"type":"Point"}
}