{
  "type": "Feature",
  "properties": {
    "addr:full":"87 Rue Principale Saint-Valerien-DE-Rimouski QC G0L 4E0",
    "addr:housenumber":"87",
    "addr:postcode":"g0l 4e0",
    "addr:street":"Rue Principale",
    "iso:country":"CA",
    "sg:address":"87 Rue Principale",
    "sg:city":"Saint-Valerien-DE-Rimouski",
    "sg:classifiers":[
        {
            "category":"Food & Beverages",
            "subcategory":"Groceries & Convenience Stores",
            "type":"Retail Goods"
        }
    ],
    "sg:phone":"+1 418 736 4863",
    "sg:postcode":"G0L 4E0",
    "sg:province":"QC",
    "sg:tags":[
        "grocer"
    ],
    "wof:name":"Epicerie Jc Cote Inc",
    "wof:placetype":"venue"
},
  "geometry": {"coordinates":[-68.52467300000001,48.449295],"type":"Point"}
}