{
  "type": "Feature",
  "properties": {
    "addr:full":"Mississauga ON L5T 2J6",
    "addr:postcode":"l5t 2j6",
    "iso:country":"CA",
    "sg:city":"Mississauga",
    "sg:classifiers":[
        {
            "category":"Professional",
            "subcategory":"Business Services",
            "type":"Services"
        }
    ],
    "sg:phone":"+1 905 564 1632",
    "sg:postcode":"L5T 2J6",
    "sg:province":"ON",
    "sg:tags":[
        "interior",
        "consultant",
        "design",
        "decorator"
    ],
    "wof:name":"Eurocrafts International",
    "wof:placetype":"venue"
},
  "geometry": {"coordinates":[-79.677612,43.660271],"type":"Point"}
}