{
  "type": "Feature",
  "properties": {
    "addr:full":"75 University Ave W Windsor ON N9A 5N8",
    "addr:housenumber":"75",
    "addr:postcode":"n9a 5n8",
    "addr:street":"University Ave W",
    "iso:country":"CA",
    "sg:address":"75 University Ave W",
    "sg:city":"Windsor",
    "sg:classifiers":[
        {
            "category":"Personal",
            "subcategory":"Beauty Salon",
            "type":"Services"
        }
    ],
    "sg:phone":"+1 519 973 8888",
    "sg:postcode":"N9A 5N8",
    "sg:province":"ON",
    "wof:name":"Rose City Nail",
    "wof:placetype":"venue"
},
  "geometry": {"coordinates":[-83.03969573969999,42.317276001],"type":"Point"}
}