{
  "type": "Feature",
  "properties": {
    "addr:full":"North York ON M3B 1X8",
    "addr:postcode":"m3b 1x8",
    "iso:country":"CA",
    "sg:city":"North York",
    "sg:classifiers":[
        {
            "category":"Personal",
            "subcategory":"Beauty Salon",
            "type":"Services"
        }
    ],
    "sg:phone":"+1 416 383 1616",
    "sg:postcode":"M3B 1X8",
    "sg:province":"ON",
    "wof:name":"Salon Venere",
    "wof:placetype":"venue"
},
  "geometry": {"coordinates":[-79.358299,43.753468],"type":"Point"}
}