{
  "type": "Feature",
  "properties": {
    "addr:full":"760 Ch Saint-Louis Quebec QC G1S 1C3",
    "addr:housenumber":"760",
    "addr:postcode":"g1s 1c3",
    "addr:street":"Ch Saint-Louis",
    "iso:country":"CA",
    "sg:address":"760 Ch Saint-Louis",
    "sg:city":"Quebec",
    "sg:classifiers":[
        {
            "category":"Travel",
            "subcategory":"Hotels & Motels",
            "type":"Entertainment"
        }
    ],
    "sg:phone":"+1 418 682 9959",
    "sg:postcode":"G1S 1C3",
    "sg:province":"QC",
    "sg:tags":[
        "breakfast",
        "accommodation",
        "bed"
    ],
    "wof:name":"Bed & Breakfast Maison Lesage",
    "wof:placetype":"venue"
},
  "geometry": {"coordinates":[-71.339996,46.749989],"type":"Point"}
}