{
  "type": "Feature",
  "properties": {
    "addr:full":"Penticton BC V2A 5B7",
    "addr:postcode":"v2a 5b7",
    "iso:country":"CA",
    "sg:city":"Penticton",
    "sg:classifiers":[
        {
            "category":"Professional",
            "subcategory":"Lawyer & Legal Services",
            "type":"Services"
        }
    ],
    "sg:phone":"+1 250 493 9100",
    "sg:postcode":"V2A 5B7",
    "sg:province":"BC",
    "sg:tags":[
        "attorney"
    ],
    "wof:name":"Davie & Assoc",
    "wof:placetype":"venue"
},
  "geometry": {"coordinates":[-119.59264400000001,49.498722],"type":"Point"}
}