{
  "type": "Feature",
  "properties": {
    "addr:full":"Saskatoon SK S7K 0W3",
    "addr:postcode":"s7k 0w3",
    "iso:country":"CA",
    "sg:city":"Saskatoon",
    "sg:classifiers":[
        {
            "category":"Retail",
            "subcategory":"Auto Repair",
            "type":"Services"
        }
    ],
    "sg:phone":"+1 306 244 0800",
    "sg:postcode":"S7K 0W3",
    "sg:province":"SK",
    "sg:tags":[
        "transmission"
    ],
    "wof:name":"Trans-Torq Mfg Ltd",
    "wof:placetype":"venue"
},
  "geometry": {"coordinates":[-106.664688,52.162338],"type":"Point"}
}