{
  "type": "Feature",
  "properties": {
    "addr:full":"2860 Ahearn Ave Ottawa ON K2B 6Z9",
    "addr:housenumber":"2860",
    "addr:postcode":"k2b 6z9",
    "addr:street":"Ahearn Ave",
    "iso:country":"CA",
    "sg:address":"2860 Ahearn Ave",
    "sg:city":"Ottawa",
    "sg:classifiers":[
        {
            "category":"Social Services",
            "subcategory":"Child Care",
            "type":"Services"
        }
    ],
    "sg:phone":"+1 613 829 1125",
    "sg:postcode":"K2B 6Z9",
    "sg:province":"ON",
    "wof:name":"Pine Crest Queensway Nursery",
    "wof:placetype":"venue"
},
  "geometry": {"coordinates":[-75.80117799999999,45.360413],"type":"Point"}
}