{
  "type": "Feature",
  "properties": {
    "addr:full":"267 Matheson Blvd E Mississauga ON L4Z 1X8",
    "addr:housenumber":"267",
    "addr:postcode":"l4z 1x8",
    "addr:street":"Matheson Blvd E",
    "iso:country":"CA",
    "sg:address":"267 Matheson Blvd E",
    "sg:city":"Mississauga",
    "sg:classifiers":[
        {
            "category":"Shopping",
            "subcategory":"Computers & Home Electronics",
            "type":"Retail Goods"
        }
    ],
    "sg:phone":"+1 905 890 0011",
    "sg:postcode":"L4Z 1X8",
    "sg:province":"ON",
    "sg:tags":[
        "equipment",
        "dealer"
    ],
    "wof:name":"Data Micro Inc",
    "wof:placetype":"venue"
},
  "geometry": {"coordinates":[-79.66399383540001,43.6223373413],"type":"Point"}
}