{
  "type": "Feature",
  "properties": {
    "addr:full":"5133 Boundary Rd Abbotsford BC V3G 2N4",
    "addr:housenumber":"5133",
    "addr:postcode":"v3g 2n4",
    "addr:street":"Boundary Rd",
    "iso:country":"CA",
    "sg:address":"5133 Boundary Rd",
    "sg:city":"Abbotsford",
    "sg:classifiers":[
        {
            "category":"Social Services",
            "subcategory":"Adult Care",
            "type":"Services"
        }
    ],
    "sg:phone":"+1 604 823 6712",
    "sg:postcode":"V3G 2N4",
    "sg:province":"BC",
    "sg:tags":[
        "community",
        "facility"
    ],
    "wof:name":"Mountain View Home",
    "wof:placetype":"venue"
},
  "geometry": {"coordinates":[-122.080612183,49.0957221985],"type":"Point"}
}