{
  "type": "Feature",
  "properties": {
    "iso:country":"CA",
    "sg:address":"5204 84 St NW",
    "sg:city":"Edmonton",
    "sg:classifiers":[
        {
            "category":"Communications",
            "subcategory":"Radio Station",
            "type":"Services"
        }
    ],
    "sg:phone":"+1 780 428 1104",
    "sg:postcode":"T6E 5N8",
    "sg:province":"AB",
    "sg:tags":[
        "company",
        "broadcasting"
    ],
    "wof:name":"Cisn",
    "wof:placetype":"venue"
},
  "geometry": {"coordinates":[-113.4478302,53.4907493591],"type":"Point"}
}