{
  "type": "Feature",
  "properties": {
    "addr:full":"343 Talbot St St Thomas ON N5P 1B7",
    "addr:housenumber":"343",
    "addr:postcode":"n5p 1b7",
    "addr:street":"Talbot St",
    "iso:country":"CA",
    "sg:address":"343 Talbot St",
    "sg:city":"St Thomas",
    "sg:classifiers":[
        {
            "category":"Food & Beverages",
            "subcategory":"Fruits & Vegetables",
            "type":"Retail Goods"
        }
    ],
    "sg:phone":"+1 519 631 6150",
    "sg:postcode":"N5P 1B7",
    "sg:province":"ON",
    "sg:tags":[
        "produce"
    ],
    "wof:name":"Smitty's Country Market",
    "wof:placetype":"venue"
},
  "geometry": {"coordinates":[-81.19858551030001,42.7791557312],"type":"Point"}
}