{
  "type": "Feature",
  "properties": {
    "addr:full":"91 Wright Ave Dartmouth NS B3B 1K6",
    "addr:housenumber":"91",
    "addr:postcode":"b3b 1k6",
    "addr:street":"Wright Ave",
    "iso:country":"CA",
    "sg:address":"91 Wright Ave",
    "sg:city":"Dartmouth",
    "sg:classifiers":[
        {
            "category":"Home & Garden",
            "subcategory":"Building Materials",
            "type":"Retail Goods"
        }
    ],
    "sg:phone":"+1 902 468 2646",
    "sg:postcode":"B3B 1K6",
    "sg:province":"NS",
    "sg:tags":[
        "siding"
    ],
    "wof:name":"Kaycan Limited",
    "wof:placetype":"venue"
},
  "geometry": {"coordinates":[-63.595356,44.705132],"type":"Point"}
}