{
  "type": "Feature",
  "properties": {
    "addr:full":"192 Rue Notre-Dame L'Assomption QC J5W 3E1",
    "addr:housenumber":"192",
    "addr:postcode":"j5w 3e1",
    "addr:street":"Rue Notre-Dame",
    "iso:country":"CA",
    "sg:address":"192 Rue Notre-Dame",
    "sg:city":"L'Assomption",
    "sg:classifiers":[
        {
            "category":"Shopping",
            "subcategory":"Clothing, Apparel, & Fashions",
            "type":"Retail Goods"
        }
    ],
    "sg:phone":"+1 450 589 4301",
    "sg:postcode":"J5W 3E1",
    "sg:province":"QC",
    "wof:name":"Culotton Inc",
    "wof:placetype":"venue"
},
  "geometry": {"coordinates":[-73.4238357544,45.8263893127],"type":"Point"}
}