{
  "type": "Feature",
  "properties": {
    "addr:full":"6670 Rue Fontaine Rock Forest QC J1N 2T2",
    "addr:housenumber":"6670",
    "addr:postcode":"j1n 2t2",
    "addr:street":"Rue Fontaine",
    "iso:country":"CA",
    "sg:address":"6670 Rue Fontaine",
    "sg:city":"Rock Forest",
    "sg:classifiers":[
        {
            "category":"Recreation",
            "type":"Entertainment"
        }
    ],
    "sg:phone":"+1 819 864 4043",
    "sg:postcode":"J1N 2T2",
    "sg:province":"QC",
    "sg:tags":[
        "government",
        "hall",
        "auditorium"
    ],
    "wof:name":"Rock Forest Centre Communautre",
    "wof:placetype":"venue"
},
  "geometry": {"coordinates":[-71.9906082153,45.3490867615],"type":"Point"}
}