{
  "type": "Feature",
  "properties": {
    "addr:full":"25 Rue Des Oblats N Ville-Marie QC J9V 1H9",
    "addr:housenumber":"25",
    "addr:postcode":"j9v 1h9",
    "addr:street":"Rue Des Oblats N",
    "iso:country":"CA",
    "sg:address":"25 Rue Des Oblats N",
    "sg:city":"Ville-Marie",
    "sg:classifiers":[
        {
            "category":"Travel",
            "subcategory":"Hotels & Motels",
            "type":"Entertainment"
        }
    ],
    "sg:phone":"+1 819 629 2770",
    "sg:postcode":"J9V 1H9",
    "sg:province":"QC",
    "wof:name":"Motel Louise Enrg",
    "wof:placetype":"venue"
},
  "geometry": {"coordinates":[-79.4372558594,47.334815979],"type":"Point"}
}