{
  "type": "Feature",
  "properties": {
    "addr:full":"4050 Rue Ferland Boisbriand QC J7E 4H5",
    "addr:housenumber":"4050",
    "addr:postcode":"j7e 4h5",
    "addr:street":"Rue Ferland",
    "iso:country":"CA",
    "sg:address":"4050 Rue Ferland",
    "sg:city":"Boisbriand",
    "sg:classifiers":[
        {
            "category":"Retail",
            "subcategory":"Repair Shop",
            "type":"Services"
        }
    ],
    "sg:phone":"+1 450 430 4373",
    "sg:postcode":"J7E 4H5",
    "sg:province":"QC",
    "sg:tags":[
        "plumbing",
        "gas",
        "contractor"
    ],
    "wof:name":"Plomberie Riopel & Grignon Inc",
    "wof:placetype":"venue"
},
  "geometry": {"coordinates":[-73.8939819336,45.6335868835],"type":"Point"}
}