{
  "type": "Feature",
  "properties": {
    "iso:country":"CA",
    "sg:address":"45 Bronte Rd",
    "sg:city":"Oakville",
    "sg:classifiers":[
        {
            "category":"Shopping",
            "type":"Retail Goods"
        }
    ],
    "sg:phone":"+1 905 825 3248",
    "sg:postcode":"L6L 3B6",
    "sg:province":"ON",
    "sg:tags":[
        "art",
        "gallery",
        "dealer"
    ],
    "wof:name":"Bronte Harbour Fine Arts",
    "wof:placetype":"venue"
},
  "geometry": {"coordinates":[-79.7098693848,43.3940544128],"type":"Point"}
}