{
  "type": "Feature",
  "properties": {
    "iso:country":"CA",
    "sg:address":"135 6th Ave S",
    "sg:city":"Cranbrook",
    "sg:classifiers":[
        {
            "category":"Professional",
            "subcategory":"Computer Services",
            "type":"Services"
        }
    ],
    "sg:phone":"+1 250 489 4289",
    "sg:postcode":"V1C 2H5",
    "sg:province":"BC",
    "sg:tags":[
        "internet"
    ],
    "wof:name":"Cintek",
    "wof:placetype":"venue"
},
  "geometry": {"coordinates":[-115.773338318,49.5096244812],"type":"Point"}
}