{
  "type": "Feature",
  "properties": {
    "iso:country":"CA",
    "sg:address":"280 West Beaver Creek Rd",
    "sg:city":"Richmond Hill",
    "sg:classifiers":[
        {
            "category":"Restaurant",
            "type":"Food & Drink"
        }
    ],
    "sg:phone":"+1 905 709 3003",
    "sg:postcode":"L4B 3Z1",
    "sg:province":"ON",
    "sg:tags":[
        "parlor",
        "ice",
        "cream"
    ],
    "wof:name":"Sweet Dynasty",
    "wof:placetype":"venue"
},
  "geometry": {"coordinates":[-79.3870544434,43.8446884155],"type":"Point"}
}