{
  "type": "Feature",
  "properties": {
    "addr:full":"659 Colborne St Brantford ON N3S 3M8",
    "addr:housenumber":"659",
    "addr:postcode":"n3s 3m8",
    "addr:street":"Colborne St",
    "iso:country":"CA",
    "sg:address":"659 Colborne St",
    "sg:city":"Brantford",
    "sg:classifiers":[
        {
            "category":"Restaurant",
            "type":"Food & Drink"
        }
    ],
    "sg:phone":"+1 519 751 1010",
    "sg:postcode":"N3S 3M8",
    "sg:province":"ON",
    "sg:tags":[
        "out",
        "pizza"
    ],
    "wof:name":"Mario's Two For One Pizza",
    "wof:placetype":"venue"
},
  "geometry": {"coordinates":[-80.23782300000001,43.140995],"type":"Point"}
}