{
  "type": "Feature",
  "properties": {
    "addr:full":"6 North Hastings St Marmora ON K0K 2M0",
    "addr:housenumber":"6",
    "addr:postcode":"k0k 2m0",
    "addr:street":"North Hastings St",
    "iso:country":"CA",
    "sg:address":"6 North Hastings St",
    "sg:city":"Marmora",
    "sg:classifiers":[
        {
            "category":"Organizations",
            "subcategory":"Professional Association",
            "type":"Services"
        }
    ],
    "sg:phone":"+1 613 472 2218",
    "sg:postcode":"K0K 2M0",
    "sg:province":"ON",
    "wof:name":"Royal Canadian Legion",
    "wof:placetype":"venue"
},
  "geometry": {"coordinates":[-77.680984,44.485889],"type":"Point"}
}