{
  "type": "Feature",
  "properties": {
    "iso:country":"CA",
    "sg:address":"843 Guelph St",
    "sg:city":"Kitchener",
    "sg:classifiers":[
        {
            "category":"Building & Trades",
            "subcategory":"Plumbing",
            "type":"Services"
        }
    ],
    "sg:phone":"+1 519 749 2790",
    "sg:postcode":"N2H 5Z2",
    "sg:province":"ON",
    "sg:tags":[
        "sheet",
        "work",
        "metal",
        "contractor"
    ],
    "wof:name":"William Radtke Sheet Metal Ltd",
    "wof:placetype":"venue"
},
  "geometry": {"coordinates":[-80.480835,43.466244],"type":"Point"}
}