{
  "type": "Feature",
  "properties": {
    "addr:full":"4310 Rue Shakespeare Rawdon QC J0K 1S0",
    "addr:housenumber":"4310",
    "addr:postcode":"j0k 1s0",
    "addr:street":"Rue Shakespeare",
    "iso:country":"CA",
    "sg:address":"4310 Rue Shakespeare",
    "sg:city":"Rawdon",
    "sg:classifiers":[
        {
            "category":"Personal",
            "subcategory":"Beauty Salon",
            "type":"Services"
        }
    ],
    "sg:phone":"+1 450 834 1529",
    "sg:postcode":"J0K 1S0",
    "sg:province":"QC",
    "wof:name":"Coiffure Rose Poitras",
    "wof:placetype":"venue"
},
  "geometry": {"coordinates":[-73.72360992430001,46.0570983887],"type":"Point"}
}