{
  "type": "Feature",
  "properties": {
    "addr:full":"Bawlf AB T0B 0J0",
    "addr:postcode":"t0b 0j0",
    "iso:country":"CA",
    "sg:city":"Bawlf",
    "sg:classifiers":[
        {
            "category":"Building & Trades",
            "subcategory":"Construction",
            "type":"Services"
        }
    ],
    "sg:phone":"+1 780 373 3940",
    "sg:postcode":"T0B 0J0",
    "sg:province":"AB",
    "sg:tags":[
        "contractor"
    ],
    "wof:name":"Ronsko's Building Construction",
    "wof:placetype":"venue"
},
  "geometry": {"coordinates":[-112.46668243400001,52.9201011658],"type":"Point"}
}