{
  "type": "Feature",
  "properties": {
    "addr:full":"626 Jacks Lake Rd Apsley ON K0L 1A0",
    "addr:housenumber":"626",
    "addr:postcode":"k0l 1a0",
    "addr:street":"Jacks Lake Rd",
    "iso:country":"CA",
    "sg:address":"626 Jacks Lake Rd",
    "sg:city":"Apsley",
    "sg:classifiers":[
        {
            "category":"Building & Trades",
            "subcategory":"Electrical",
            "type":"Services"
        }
    ],
    "sg:phone":"+1 705 656 4948",
    "sg:postcode":"K0L 1A0",
    "sg:province":"ON",
    "sg:tags":[
        "electric",
        "contractor"
    ],
    "wof:name":"Tucker Cottage Svc",
    "wof:placetype":"venue"
},
  "geometry": {"coordinates":[-78.0853729248,44.7530212402],"type":"Point"}
}