{
  "type": "Feature",
  "properties": {
    "addr:full":"Carman MB R0G 0J0",
    "addr:postcode":"r0g 0j0",
    "iso:country":"CA",
    "sg:city":"Carman",
    "sg:classifiers":[
        {
            "category":"Personal",
            "subcategory":"Beauty Salon",
            "type":"Services"
        }
    ],
    "sg:phone":"+1 204 745 3458",
    "sg:postcode":"R0G 0J0",
    "sg:province":"MB",
    "wof:name":"Cut of Class",
    "wof:placetype":"venue"
},
  "geometry": {"coordinates":[-98.0017623901,49.5031509399],"type":"Point"}
}