{
  "type": "Feature",
  "properties": {
    "addr:full":"22311 119 Ave Maple Ridge BC V2X 2Z2",
    "addr:housenumber":"22311",
    "addr:postcode":"v2x 2z2",
    "addr:street":"119 Ave",
    "iso:country":"CA",
    "sg:address":"22311 119 Ave",
    "sg:city":"Maple Ridge",
    "sg:classifiers":[
        {
            "category":"Professional",
            "subcategory":"Lawyer & Legal Services",
            "type":"Services"
        }
    ],
    "sg:phone":"+1 604 463 6281",
    "sg:postcode":"V2X 2Z2",
    "sg:province":"BC",
    "sg:tags":[
        "attorney"
    ],
    "wof:name":"Dinsley, Thomas E",
    "wof:placetype":"venue"
},
  "geometry": {"coordinates":[-122.604012,49.218681],"type":"Point"}
}