{
  "type": "Feature",
  "properties": {
    "addr:full":"8866 Boul Saint-Laurent Montreal QC H2N 1M4",
    "addr:housenumber":"8866",
    "addr:postcode":"h2n 1m4",
    "addr:street":"Boul Saint-Laurent",
    "iso:country":"CA",
    "sg:address":"8866 Boul Saint-Laurent",
    "sg:city":"Montreal",
    "sg:classifiers":[
        {
            "category":"Professional",
            "type":"Services"
        }
    ],
    "sg:phone":"+1 514 381 8866",
    "sg:postcode":"H2N 1M4",
    "sg:province":"QC",
    "sg:tags":[
        "repairing",
        "automobile",
        "establishment"
    ],
    "wof:name":"Autoelectro Touchette",
    "wof:placetype":"venue"
},
  "geometry": {"coordinates":[-73.644302,45.54232],"type":"Point"}
}