{
  "type": "Feature",
  "properties": {
    "addr:full":"6695 Boul Henri-Bourassa O Saint-Laurent QC H4R 1E1",
    "addr:housenumber":"6695",
    "addr:postcode":"h4r 1e1",
    "addr:street":"Boul Henri-Bourassa O",
    "iso:country":"CA",
    "sg:address":"6695 Boul Henri-Bourassa O",
    "sg:city":"Saint-Laurent",
    "sg:classifiers":[
        {
            "category":"Autos & Motor Vehicles",
            "subcategory":"Auto Supplies",
            "type":"Retail Goods"
        }
    ],
    "sg:phone":"+1 514 337 6082",
    "sg:postcode":"H4R 1E1",
    "sg:province":"QC",
    "sg:tags":[
        "automobile",
        "parts"
    ],
    "wof:name":"K & A Auto Distribution Inc",
    "wof:placetype":"venue"
},
  "geometry": {"coordinates":[-73.7324676514,45.5115509033],"type":"Point"}
}