{
  "type": "Feature",
  "properties": {
    "iso:country":"CA",
    "sg:address":"29 Babbit St",
    "sg:city":"Gagetown",
    "sg:classifiers":[
        {
            "category":"Organizations",
            "subcategory":"Religious Organization",
            "type":"Services"
        }
    ],
    "sg:phone":"+1 506 488 2069",
    "sg:postcode":"E5M 1C5",
    "sg:province":"NB",
    "sg:tags":[
        "church"
    ],
    "wof:name":"Anglican Church Rectory",
    "wof:placetype":"venue"
},
  "geometry": {"coordinates":[-66.1523895264,45.778137207],"type":"Point"}
}