{
  "type": "Feature",
  "properties": {
    "addr:full":"Bancroft ON K0L 1C0",
    "addr:postcode":"k0l 1c0",
    "iso:country":"CA",
    "sg:city":"Bancroft",
    "sg:classifiers":[
        {
            "category":"Shopping",
            "subcategory":"Gifts & Souvenirs",
            "type":"Retail Goods"
        }
    ],
    "sg:phone":"+1 613 332 2303",
    "sg:postcode":"K0L 1C0",
    "sg:province":"ON",
    "sg:tags":[
        "shop"
    ],
    "wof:name":"Victorian Lady",
    "wof:placetype":"venue"
},
  "geometry": {"coordinates":[-77.853874,45.057838],"type":"Point"}
}