{
  "type": "Feature",
  "properties": {
    "addr:full":"4331 10th Ave W Vancouver BC V6R 2H6",
    "addr:housenumber":"4331",
    "addr:postcode":"v6r 2h6",
    "addr:street":"10Th Ave W",
    "iso:country":"CA",
    "sg:address":"4331 10th Ave W",
    "sg:city":"Vancouver",
    "sg:classifiers":[
        {
            "category":"Retail",
            "subcategory":"Repair Shop",
            "type":"Services"
        }
    ],
    "sg:phone":"+1 604 222 8722",
    "sg:postcode":"V6R 2H6",
    "sg:province":"BC",
    "sg:tags":[
        "clocks",
        "parts"
    ],
    "wof:name":"West Point Grey Time CO",
    "wof:placetype":"venue"
},
  "geometry": {"coordinates":[-123.204086,49.263882],"type":"Point"}
}