{
  "type": "Feature",
  "properties": {
    "addr:full":"3020 Underhill Dr NW Calgary AB T2N 4E5",
    "addr:housenumber":"3020",
    "addr:postcode":"t2n 4e5",
    "addr:street":"Underhill Dr Nw",
    "iso:country":"CA",
    "sg:address":"3020 Underhill Dr NW",
    "sg:city":"Calgary",
    "sg:classifiers":[
        {
            "category":"Professional",
            "subcategory":"Engineering",
            "type":"Services"
        }
    ],
    "sg:phone":"+1 403 210 0746",
    "sg:postcode":"T2N 4E5",
    "sg:province":"AB",
    "sg:tags":[
        "engineer"
    ],
    "wof:name":"Lateral Solutions Inc",
    "wof:placetype":"venue"
},
  "geometry": {"coordinates":[-114.129578,51.072201],"type":"Point"}
}