{
  "type": "Feature",
  "properties": {
    "addr:full":"43 Silver Aspen Dr Thornhill ON L3T 3T1",
    "addr:housenumber":"43",
    "addr:postcode":"l3t 3t1",
    "addr:street":"Silver Aspen Dr",
    "iso:country":"CA",
    "sg:address":"43 Silver Aspen Dr",
    "sg:city":"Thornhill",
    "sg:classifiers":[
        {
            "category":"Home & Garden",
            "subcategory":"Household Appliances",
            "type":"Retail Goods"
        }
    ],
    "sg:phone":"+1 905 881 6382",
    "sg:postcode":"L3T 3T1",
    "sg:province":"ON",
    "sg:tags":[
        "refrigerator",
        "freezer"
    ],
    "wof:name":"North Region Appliance Svc",
    "wof:placetype":"venue"
},
  "geometry": {"coordinates":[-79.42041,43.823997],"type":"Point"}
}