{
  "type": "Feature",
  "properties": {
    "iso:country":"CA",
    "sg:city":"Kamloops",
    "sg:classifiers":[
        {
            "category":"Social Services",
            "subcategory":"Child Care",
            "type":"Services"
        }
    ],
    "sg:phone":"+1 250 828 9767",
    "sg:postcode":"V2H 1H1",
    "sg:province":"BC",
    "wof:name":"Little Fawn Daycare",
    "wof:placetype":"venue"
},
  "geometry": {"coordinates":[-120.298706055,50.6800727844],"type":"Point"}
}