{
  "type": "Feature",
  "properties": {
    "addr:full":"Red Deer County AB T4S 2A3",
    "addr:postcode":"t4s 2a3",
    "iso:country":"CA",
    "sg:city":"Red Deer County",
    "sg:classifiers":[
        {
            "category":"Freight",
            "type":"Transportation"
        }
    ],
    "sg:phone":"+1 403 342 1440",
    "sg:postcode":"T4S 2A3",
    "sg:province":"AB",
    "sg:tags":[
        "self",
        "storage"
    ],
    "wof:name":"Stor-Mor Mini Warehousing Ltd",
    "wof:placetype":"venue"
},
  "geometry": {"coordinates":[-113.93289900000001,52.028362],"type":"Point"}
}