{
  "type": "Feature",
  "properties": {
    "addr:full":"904 Barrydowne Rd Sudbury ON P3A 3V2",
    "addr:housenumber":"904",
    "addr:postcode":"p3a 3v2",
    "addr:street":"Barrydowne Rd",
    "iso:country":"CA",
    "sg:address":"904 Barrydowne Rd",
    "sg:city":"Sudbury",
    "sg:classifiers":[
        {
            "category":"Shopping",
            "subcategory":"Crafts & Fabrics",
            "type":"Retail Goods"
        }
    ],
    "sg:phone":"+1 705 560 6410",
    "sg:postcode":"P3A 3V2",
    "sg:province":"ON",
    "sg:tags":[
        "shop"
    ],
    "wof:name":"Fabricland Distributors",
    "wof:placetype":"venue"
},
  "geometry": {"coordinates":[-80.943977356,46.5162200928],"type":"Point"}
}