{
  "type": "Feature",
  "properties": {
    "addr:full":"106 Mayfield Ave # 2 Williams Lake BC V2G 2Y1",
    "addr:housenumber":"106",
    "addr:postcode":"bc v2g 2y1",
    "addr:street":"Mayfield Ave # 2",
    "iso:country":"CA",
    "sg:address":"106 Mayfield Ave # 2",
    "sg:city":"Williams Lake",
    "sg:classifiers":[
        {
            "category":"Real Estate",
            "subcategory":"Real Estate Operator",
            "type":"Services"
        }
    ],
    "sg:phone":"+1 250 392 7131",
    "sg:postcode":"V2G 2Y1",
    "sg:province":"BC",
    "sg:tags":[
        "mobile",
        "home",
        "community"
    ],
    "wof:name":"C & H Development Ltd",
    "wof:placetype":"venue"
},
  "geometry": {"coordinates":[-122.13073,52.132832],"type":"Point"}
}