{
  "type": "Feature",
  "properties": {
    "addr:full":"504 32nd St W Saskatoon SK S7L 0S9",
    "addr:housenumber":"504",
    "addr:postcode":"s7l 0s9",
    "addr:street":"32Nd St W",
    "iso:country":"CA",
    "sg:address":"504 32nd St W",
    "sg:city":"Saskatoon",
    "sg:classifiers":[
        {
            "category":"Education",
            "subcategory":"Special Training",
            "type":"Public Place"
        }
    ],
    "sg:phone":"+1 306 652 2036",
    "sg:postcode":"S7L 0S9",
    "sg:province":"SK",
    "sg:tags":[
        "instruction",
        "driving"
    ],
    "wof:name":"Travelon Truck Professional",
    "wof:placetype":"venue"
},
  "geometry": {"coordinates":[-106.677063,52.142078],"type":"Point"}
}