{
  "type": "Feature",
  "properties": {
    "iso:country":"CA",
    "sg:address":"2849 Howard Ave",
    "sg:city":"Windsor",
    "sg:classifiers":[
        {
            "category":"Shopping",
            "subcategory":"Musical Instruments",
            "type":"Retail Goods"
        }
    ],
    "sg:phone":"+1 519 739 2766",
    "sg:postcode":"N8X 3Y4",
    "sg:province":"ON",
    "sg:tags":[
        "music",
        "dealer"
    ],
    "wof:name":"Labonte School of Music",
    "wof:placetype":"venue"
},
  "geometry": {"coordinates":[-83.009475708,42.2806053162],"type":"Point"}
}