{
  "type": "Feature",
  "properties": {
    "addr:full":"Drumheller AB T0J 0Y4",
    "addr:postcode":"t0j 0y4",
    "iso:country":"CA",
    "sg:city":"Drumheller",
    "sg:classifiers":[
        {
            "category":"Banks & Credit Unions",
            "subcategory":"Bank",
            "type":"Services"
        }
    ],
    "sg:phone":"+1 403 823 3336",
    "sg:postcode":"T0J 0Y4",
    "sg:province":"AB",
    "wof:name":"Bank of Montreal",
    "wof:placetype":"venue"
},
  "geometry": {"coordinates":[-112.70899199999999,51.463734],"type":"Point"}
}