{
  "type": "Feature",
  "properties": {
    "addr:full":"15297 Rue DE Saint-Augustin Mirabel QC J7N 1X4",
    "addr:housenumber":"15297",
    "addr:postcode":"j7n 1x4",
    "addr:street":"Rue De Saint-Augustin",
    "iso:country":"CA",
    "sg:address":"15297 Rue DE Saint-Augustin",
    "sg:city":"Mirabel",
    "sg:classifiers":[
        {
            "category":"Real Estate",
            "subcategory":"Real Estate Agent",
            "type":"Services"
        }
    ],
    "sg:phone":"+1 450 475 8676",
    "sg:postcode":"J7N 1X4",
    "sg:province":"QC",
    "sg:tags":[
        "tool",
        "agency",
        "rental"
    ],
    "wof:name":"Location D'Outils Mirabel",
    "wof:placetype":"venue"
},
  "geometry": {"coordinates":[-73.978149,45.625534],"type":"Point"}
}