{
  "type": "Feature",
  "properties": {
    "addr:full":"34419 97th St Oliver BC V0H 1T0",
    "addr:housenumber":"34419",
    "addr:postcode":"bc v0h 1t0",
    "addr:street":"97Th St",
    "iso:country":"CA",
    "sg:address":"34419 97th St",
    "sg:city":"Oliver",
    "sg:classifiers":[
        {
            "category":"Building & Trades",
            "subcategory":"Equipment Rental",
            "type":"Services"
        }
    ],
    "sg:phone":"+1 250 498 6109",
    "sg:postcode":"V0H 1T0",
    "sg:province":"BC",
    "sg:tags":[
        "contractor"
    ],
    "wof:name":"Oliver Rental Ctr",
    "wof:placetype":"venue"
},
  "geometry": {"coordinates":[-119.552933,49.176365],"type":"Point"}
}