{
  "type": "Feature",
  "properties": {
    "iso:country":"CA",
    "sg:address":"461 Columbia",
    "sg:city":"Mcbride",
    "sg:classifiers":[
        {
            "category":"Organizations",
            "subcategory":"Professional Association",
            "type":"Services"
        }
    ],
    "sg:phone":"+1 250 569 2222",
    "sg:postcode":"V0J 2E0",
    "sg:province":"BC",
    "wof:name":"Mc Bride Curling Club",
    "wof:placetype":"venue"
},
  "geometry": {"coordinates":[-120.170692,53.304169],"type":"Point"}
}