{
  "type": "Feature",
  "properties": {
    "addr:full":"4497 Boul DE LA Rive-Sud Levis QC G6W 6M9",
    "addr:housenumber":"4497",
    "addr:postcode":"g6w 6m9",
    "addr:street":"Boul De La Rive-Sud",
    "iso:country":"CA",
    "sg:address":"4497 Boul DE LA Rive-Sud",
    "sg:city":"Levis",
    "sg:classifiers":[
        {
            "category":"Health Services",
            "subcategory":"Doctor",
            "type":"Services"
        }
    ],
    "sg:phone":"+1 418 833 4791",
    "sg:postcode":"G6W 6M9",
    "sg:province":"QC",
    "sg:tags":[
        "clinic"
    ],
    "wof:name":"Clinique Medicale St-David",
    "wof:placetype":"venue"
},
  "geometry": {"coordinates":[-71.192855835,46.780872345],"type":"Point"}
}