{
  "type": "Feature",
  "properties": {
    "iso:country":"CA",
    "sg:address":"1157 3rd Ave",
    "sg:city":"Prince George",
    "sg:classifiers":[
        {
            "category":"Personal",
            "subcategory":"Barber",
            "type":"Services"
        }
    ],
    "sg:phone":"+1 250 562 2912",
    "sg:postcode":"V2L 3E4",
    "sg:province":"BC",
    "wof:name":"Cariboo Barber Shop",
    "wof:placetype":"venue"
},
  "geometry": {"coordinates":[-122.743812561,53.916217804],"type":"Point"}
}