{
  "type": "Feature",
  "properties": {
    "addr:full":"2998 54th Ave E Vancouver BC V5S 1Y5",
    "addr:housenumber":"2998",
    "addr:postcode":"v5s 1y5",
    "addr:street":"54Th Ave E",
    "iso:country":"CA",
    "sg:address":"2998 54th Ave E",
    "sg:city":"Vancouver",
    "sg:classifiers":[
        {
            "category":"Real Estate",
            "subcategory":"Real Estate Agent",
            "type":"Services"
        }
    ],
    "sg:phone":"+1 604 436 2886",
    "sg:postcode":"V5S 1Y5",
    "sg:province":"BC",
    "sg:tags":[
        "cooperative"
    ],
    "wof:name":"Killarney Gardens Housing Coop",
    "wof:placetype":"venue"
},
  "geometry": {"coordinates":[-123.04450199999999,49.22015],"type":"Point"}
}