{
  "type": "Feature",
  "properties": {
    "addr:full":"789 Warden Ave Scarborough ON M1L 4C2",
    "addr:housenumber":"789",
    "addr:postcode":"m1l 4c2",
    "addr:street":"Warden Ave",
    "iso:country":"CA",
    "sg:address":"789 Warden Ave",
    "sg:city":"Scarborough",
    "sg:classifiers":[
        {
            "category":"Organizations",
            "subcategory":"Religious Organization",
            "type":"Services"
        }
    ],
    "sg:phone":"+1 416 285 9506",
    "sg:postcode":"M1L 4C2",
    "sg:province":"ON",
    "wof:name":"Word For the World Christian",
    "wof:placetype":"venue"
},
  "geometry": {"coordinates":[-79.28685760499999,43.7264328003],"type":"Point"}
}