{
  "type": "Feature",
  "properties": {
    "iso:country":"CA",
    "sg:address":"606 Welland Ave",
    "sg:city":"St Catharines",
    "sg:classifiers":[
        {
            "category":"Wholesale",
            "subcategory":"Machinery & Supplies",
            "type":"Manufacturing & Wholesale Goods"
        }
    ],
    "sg:phone":"+1 905 684 6311",
    "sg:postcode":"L2M 5V6",
    "sg:province":"ON",
    "sg:tags":[
        "equipment",
        "industrial",
        "hydraulic"
    ],
    "wof:name":"Niagara Industrial Supls Ltd",
    "wof:placetype":"venue"
},
  "geometry": {"coordinates":[-79.2068939209,43.1775474548],"type":"Point"}
}