{
  "type": "Feature",
  "properties": {
    "addr:full":"Mississauga ON L4T 3Y7",
    "addr:postcode":"l4t 3y7",
    "iso:country":"CA",
    "sg:city":"Mississauga",
    "sg:classifiers":[
        {
            "category":"Wholesale",
            "subcategory":"Durable Goods & Equipment",
            "type":"Manufacturing & Wholesale Goods"
        }
    ],
    "sg:phone":"+1 905 672 5211",
    "sg:postcode":"L4T 3Y7",
    "sg:province":"ON",
    "sg:tags":[
        "representative",
        "manufacturer"
    ],
    "wof:name":"Ascencion Equipment Sales Ltd",
    "wof:placetype":"venue"
},
  "geometry": {"coordinates":[-79.66082763670001,43.6999855042],"type":"Point"}
}