{
  "type": "Feature",
  "properties": {
    "addr:full":"5871 Haughan Rd Nanaimo BC V9T 5P1",
    "addr:housenumber":"5871",
    "addr:postcode":"v9t 5p1",
    "addr:street":"Haughan Rd",
    "iso:country":"CA",
    "sg:address":"5871 Haughan Rd",
    "sg:city":"Nanaimo",
    "sg:classifiers":[
        {
            "category":"Building & Trades",
            "subcategory":"Construction",
            "type":"Services"
        }
    ],
    "sg:phone":"+1 250 758 0257",
    "sg:postcode":"V9T 5P1",
    "sg:province":"BC",
    "sg:tags":[
        "insulation",
        "heat",
        "contractor"
    ],
    "wof:name":"Tlc Insulation Ltd",
    "wof:placetype":"venue"
},
  "geometry": {"coordinates":[-124.024567,49.218166],"type":"Point"}
}