{
  "type": "Feature",
  "properties": {
    "addr:full":"272 Carlisle Rd Douglas NB E3A 7N9",
    "addr:housenumber":"272",
    "addr:postcode":"e3a 7n9",
    "addr:street":"Carlisle Rd",
    "iso:country":"CA",
    "sg:address":"272 Carlisle Rd",
    "sg:city":"Douglas",
    "sg:classifiers":[
        {
            "category":"Building & Trades",
            "subcategory":"Construction",
            "type":"Services"
        }
    ],
    "sg:phone":"+1 506 450 3776",
    "sg:postcode":"E3A 7N9",
    "sg:province":"NB",
    "sg:tags":[
        "general",
        "contractor"
    ],
    "wof:name":"Distinctive Homes By Brian Ltd",
    "wof:placetype":"venue"
},
  "geometry": {"coordinates":[-66.789772,45.994465],"type":"Point"}
}