{
  "type": "Feature",
  "properties": {
    "addr:full":"13 Wootten Way N Markham ON L3P 2Y2",
    "addr:housenumber":"13",
    "addr:postcode":"l3p 2y2",
    "addr:street":"Wootten Way N",
    "iso:country":"CA",
    "sg:address":"13 Wootten Way N",
    "sg:city":"Markham",
    "sg:classifiers":[
        {
            "category":"Personal",
            "subcategory":"Beauty Salon",
            "type":"Services"
        }
    ],
    "sg:phone":"+1 905 294 5716",
    "sg:postcode":"L3P 2Y2",
    "sg:province":"ON",
    "wof:name":"Mike & Gino Coiffure",
    "wof:placetype":"venue"
},
  "geometry": {"coordinates":[-79.243256,43.878223],"type":"Point"}
}