{
  "type": "Feature",
  "properties": {
    "addr:full":"9632 Queen St Harwood ON K0K 2H0",
    "addr:housenumber":"9632",
    "addr:postcode":"k0k 2h0",
    "addr:street":"Queen St",
    "iso:country":"CA",
    "sg:address":"9632 Queen St",
    "sg:city":"Harwood",
    "sg:classifiers":[
        {
            "category":"Shopping",
            "subcategory":"Discount & Variety Stores",
            "type":"Retail Goods"
        }
    ],
    "sg:phone":"+1 905 342 3292",
    "sg:postcode":"K0K 2H0",
    "sg:province":"ON",
    "wof:name":"Bonnie's Country Store",
    "wof:placetype":"venue"
},
  "geometry": {"coordinates":[-78.180443,44.137516],"type":"Point"}
}