{
  "type": "Feature",
  "properties": {
    "addr:full":"Godfrey ON K0H 1T0",
    "addr:postcode":"k0h 1t0",
    "iso:country":"CA",
    "sg:city":"Godfrey",
    "sg:classifiers":[
        {
            "category":"Travel",
            "subcategory":"Hotels & Motels",
            "type":"Entertainment"
        }
    ],
    "sg:phone":"+1 613 273 5358",
    "sg:postcode":"K0H 1T0",
    "sg:province":"ON",
    "sg:tags":[
        "cottage",
        "cabin"
    ],
    "wof:name":"Twin Oaks Camp",
    "wof:placetype":"venue"
},
  "geometry": {"coordinates":[-76.679062,44.543114],"type":"Point"}
}