{
  "type": "Feature",
  "properties": {
    "addr:full":"2440 Rue Cantin Jonquiere QC G7X 8S6",
    "addr:housenumber":"2440",
    "addr:postcode":"g7x 8s6",
    "addr:street":"Rue Cantin",
    "iso:country":"CA",
    "sg:address":"2440 Rue Cantin",
    "sg:city":"Jonquiere",
    "sg:classifiers":[
        {
            "category":"Freight",
            "type":"Transportation"
        }
    ],
    "sg:phone":"+1 418 547 7510",
    "sg:postcode":"G7X 8S6",
    "sg:province":"QC",
    "sg:tags":[
        "trucking"
    ],
    "wof:name":"Transporteurs En Vrac",
    "wof:placetype":"venue"
},
  "geometry": {"coordinates":[-71.23397799999999,48.403881],"type":"Point"}
}