{
  "type": "Feature",
  "properties": {
    "addr:full":"Hwy 72 Sioux Lookout ON P8T 1B7",
    "addr:postcode":"p8t 1b7",
    "addr:street":"Hwy 72",
    "iso:country":"CA",
    "sg:address":"Hwy 72",
    "sg:city":"Sioux Lookout",
    "sg:classifiers":[
        {
            "category":"Travel",
            "subcategory":"Campground",
            "type":"Entertainment"
        }
    ],
    "sg:phone":"+1 807 737 5642",
    "sg:postcode":"P8T 1B7",
    "sg:province":"ON",
    "sg:tags":[
        "camp",
        "fishing"
    ],
    "wof:name":"Northwood Outposts",
    "wof:placetype":"venue"
},
  "geometry": {"coordinates":[-91.9727935791,50.0577087402],"type":"Point"}
}