{
  "type": "Feature",
  "properties": {
    "addr:full":"2970 Rue King O Sherbrooke QC J1L 1Y7",
    "addr:housenumber":"2970",
    "addr:postcode":"j1l 1y7",
    "addr:street":"Rue King O",
    "iso:country":"CA",
    "sg:address":"2970 Rue King O",
    "sg:city":"Sherbrooke",
    "sg:classifiers":[
        {
            "category":"Health Services",
            "subcategory":"Doctor",
            "type":"Services"
        }
    ],
    "sg:phone":"+1 819 348 0116",
    "sg:postcode":"J1L 1Y7",
    "sg:province":"QC",
    "sg:tags":[
        "dentist"
    ],
    "wof:name":"Remillard, Yves DDS",
    "wof:placetype":"venue"
},
  "geometry": {"coordinates":[-71.9438171387,45.3968353271],"type":"Point"}
}