{
  "type": "Feature",
  "properties": {
    "addr:full":"7880 Fraser Park Dr Burnaby BC V5J 5L8",
    "addr:housenumber":"7880",
    "addr:postcode":"v5j 5l8",
    "addr:street":"Fraser Park Dr",
    "iso:country":"CA",
    "sg:address":"7880 Fraser Park Dr",
    "sg:city":"Burnaby",
    "sg:classifiers":[
        {
            "category":"Wholesale",
            "subcategory":"Machinery & Supplies",
            "type":"Manufacturing & Wholesale Goods"
        }
    ],
    "sg:phone":"+1 604 294 3461",
    "sg:postcode":"V5J 5L8",
    "sg:province":"BC",
    "sg:tags":[
        "bearing"
    ],
    "wof:name":"Ringball Corp",
    "wof:placetype":"venue"
},
  "geometry": {"coordinates":[-122.98925781200001,49.1856651306],"type":"Point"}
}