{
  "type": "Feature",
  "properties": {
    "addr:full":"51 the Chimneystack Rd North York ON M3J 3L9",
    "addr:housenumber":"51",
    "addr:postcode":"m3j 3l9",
    "addr:street":"The Chimneystack Rd",
    "iso:country":"CA",
    "sg:address":"51 the Chimneystack Rd",
    "sg:city":"North York",
    "sg:classifiers":[
        {
            "category":"Real Estate",
            "subcategory":"Real Estate Agent",
            "type":"Services"
        }
    ],
    "sg:phone":"+1 416 736 8889",
    "sg:postcode":"M3J 3L9",
    "sg:province":"ON",
    "sg:tags":[
        "cooperative"
    ],
    "wof:name":"Harry Sherman Crowe Housing",
    "wof:placetype":"venue"
},
  "geometry": {"coordinates":[-79.499008,43.776558],"type":"Point"}
}