{
  "type": "Feature",
  "properties": {
    "addr:full":"Dartmouth NS B3B 1S8",
    "addr:postcode":"b3b 1s8",
    "iso:country":"CA",
    "sg:city":"Dartmouth",
    "sg:classifiers":[
        {
            "category":"Shopping",
            "subcategory":"Bicycles & Sporting Goods",
            "type":"Retail Goods"
        }
    ],
    "sg:phone":"+1 902 468 9445",
    "sg:postcode":"B3B 1S8",
    "sg:province":"NS",
    "wof:name":"Express Fitness Equipment",
    "wof:placetype":"venue"
},
  "geometry": {"coordinates":[-63.586002,44.699612],"type":"Point"}
}