{
  "type": "Feature",
  "properties": {
    "addr:full":"108 Industrial Rd Whitehorse YT Y1A 2T9",
    "addr:housenumber":"108",
    "addr:postcode":"y1a 2t9",
    "addr:street":"Industrial Rd",
    "iso:country":"CA",
    "sg:address":"108 Industrial Rd",
    "sg:city":"Whitehorse",
    "sg:classifiers":[
        {
            "category":"Retail",
            "subcategory":"Auto Repair",
            "type":"Services"
        }
    ],
    "sg:phone":"+1 867 668 4902",
    "sg:postcode":"Y1A 2T9",
    "sg:province":"YT",
    "sg:tags":[
        "repairing",
        "automobile",
        "radiator"
    ],
    "wof:name":"Yukon Radiator",
    "wof:placetype":"venue"
},
  "geometry": {"coordinates":[-135.07723999000001,60.7344245911],"type":"Point"}
}