{
  "type": "Feature",
  "properties": {
    "addr:full":"549 Rue DE Newport Lasalle QC H8R 3B3",
    "addr:housenumber":"549",
    "addr:postcode":"h8r 3b3",
    "addr:street":"Rue De Newport",
    "iso:country":"CA",
    "sg:address":"549 Rue DE Newport",
    "sg:city":"Lasalle",
    "sg:classifiers":[
        {
            "category":"Real Estate",
            "subcategory":"Surveying",
            "type":"Services"
        }
    ],
    "sg:phone":"+1 514 366 4040",
    "sg:postcode":"H8R 3B3",
    "sg:province":"QC",
    "sg:tags":[
        "surveyor"
    ],
    "wof:name":"Poupard Arpenteur Geometre Enr",
    "wof:placetype":"venue"
},
  "geometry": {"coordinates":[-73.6427764893,45.4221954346],"type":"Point"}
}