{
  "type": "Feature",
  "properties": {
    "iso:country":"CA",
    "sg:address":"7180 Tranmere Dr",
    "sg:city":"Mississauga",
    "sg:classifiers":[
        {
            "category":"Building & Trades",
            "subcategory":"Landscaping Services",
            "type":"Services"
        }
    ],
    "sg:phone":"+1 905 672 1132",
    "sg:postcode":"L5S 1L9",
    "sg:province":"ON",
    "sg:tags":[
        "landscape",
        "contractor"
    ],
    "wof:name":"Custom Landscaping",
    "wof:placetype":"venue"
},
  "geometry": {"coordinates":[-79.668716,43.686195],"type":"Point"}
}