{
  "type": "Feature",
  "properties": {
    "addr:full":"355 Rue Saint-Georges Trois-Rivieres QC G9A 2K5",
    "addr:housenumber":"355",
    "addr:postcode":"g9a 2k5",
    "addr:street":"Rue Saint-Georges Trois-Rivieres",
    "iso:country":"CA",
    "sg:address":"355 Rue Saint-Georges",
    "sg:city":"Trois-Rivieres",
    "sg:classifiers":[
        {
            "category":"Restaurant",
            "type":"Food & Drink"
        }
    ],
    "sg:phone":"+1 819 370 1010",
    "sg:postcode":"G9A 2K5",
    "sg:province":"QC",
    "wof:name":"Casa Domani",
    "wof:placetype":"venue"
},
  "geometry": {"coordinates":[-72.544403,46.341015],"type":"Point"}
}