{
  "type": "Feature",
  "properties": {
    "iso:country":"CA",
    "sg:address":"141 Wortley Rd",
    "sg:city":"London",
    "sg:classifiers":[
        {
            "category":"Professional",
            "subcategory":"Lawyer & Legal Services",
            "type":"Services"
        }
    ],
    "sg:phone":"+1 519 673 1300",
    "sg:postcode":"N6C 3P4",
    "sg:province":"ON",
    "sg:tags":[
        "attorney"
    ],
    "wof:name":"Mueller, Frederick A",
    "wof:placetype":"venue"
},
  "geometry": {"coordinates":[-81.253944,42.973095],"type":"Point"}
}