{
  "type": "Feature",
  "properties": {
    "iso:country":"CA",
    "sg:city":"South River",
    "sg:classifiers":[
        {
            "category":"Personal",
            "type":"Services"
        }
    ],
    "sg:phone":"+1 705 386 2772",
    "sg:postcode":"P0A 1X0",
    "sg:province":"ON",
    "sg:tags":[
        "salon",
        "beauty",
        "program",
        "fitness",
        "exercise",
        "physical"
    ],
    "wof:name":"Ma Maison Barber & Hairstyling",
    "wof:placetype":"venue"
},
  "geometry": {"coordinates":[-79.3810043335,45.8418159485],"type":"Point"}
}