{
  "type": "Feature",
  "properties": {
    "iso:country":"CA",
    "sg:address":"950 Victoria St",
    "sg:city":"Prince George",
    "sg:classifiers":[
        {
            "category":"Autos & Motor Vehicles",
            "subcategory":"Fuel & Gas Station",
            "type":"Retail Goods"
        }
    ],
    "sg:phone":"+1 250 563 1034",
    "sg:postcode":"V2L 2K8",
    "sg:province":"BC",
    "sg:tags":[
        "oil"
    ],
    "wof:name":"Super Save Gas",
    "wof:placetype":"venue"
},
  "geometry": {"coordinates":[-122.753051758,53.9127998352],"type":"Point"}
}