{
  "type": "Feature",
  "properties": {
    "addr:full":"5729 Wales St Vancouver BC V5R 3N3",
    "addr:housenumber":"5729",
    "addr:postcode":"v5r 3n3",
    "addr:street":"Wales St",
    "iso:country":"CA",
    "sg:address":"5729 Wales St",
    "sg:city":"Vancouver",
    "sg:classifiers":[
        {
            "category":"Social Services",
            "subcategory":"Child Care",
            "type":"Services"
        }
    ],
    "sg:phone":"+1 604 434 9496",
    "sg:postcode":"V5R 3N3",
    "sg:province":"BC",
    "wof:name":"Sarah House Child Care Ctr",
    "wof:placetype":"venue"
},
  "geometry": {"coordinates":[-123.051864624,49.2322006226],"type":"Point"}
}