{
  "type": "Feature",
  "properties": {
    "addr:full":"475 Woodview Rd # 7 Burlington ON L7N 2Z9",
    "addr:housenumber":"475",
    "addr:postcode":"l7n 2z9",
    "addr:street":"Woodview Rd # 7",
    "iso:country":"CA",
    "sg:address":"475 Woodview Rd # 7",
    "sg:city":"Burlington",
    "sg:classifiers":[
        {
            "category":"Real Estate",
            "subcategory":"Real Estate Agent",
            "type":"Services"
        }
    ],
    "sg:phone":"+1 905 630 2600",
    "sg:postcode":"L7N 2Z9",
    "sg:province":"ON",
    "sg:tags":[
        "appraiser"
    ],
    "wof:name":"Woodview Real Estate Appraisal",
    "wof:placetype":"venue"
},
  "geometry": {"coordinates":[-79.77565800000001,43.349857],"type":"Point"}
}