{
  "type": "Feature",
  "properties": {
    "addr:full":"565 Rue Des Ormeaux Montreal QC H1L 4W7",
    "addr:housenumber":"565",
    "addr:postcode":"h1l 4w7",
    "addr:street":"Rue Des Ormeaux",
    "iso:country":"CA",
    "sg:address":"565 Rue Des Ormeaux",
    "sg:city":"Montreal",
    "sg:classifiers":[
        {
            "category":"Manufacturing",
            "subcategory":"Tools & Machinery",
            "type":"Manufacturing & Wholesale Goods"
        }
    ],
    "sg:phone":"+1 514 351 9750",
    "sg:postcode":"H1L 4W7",
    "sg:province":"QC",
    "sg:tags":[
        "machine",
        "shop"
    ],
    "wof:name":"Atelier D'Usinage Dubuc",
    "wof:placetype":"venue"
},
  "geometry": {"coordinates":[-73.513184,45.599693],"type":"Point"}
}