{
  "type": "Feature",
  "properties": {
    "addr:full":"Collingwood ON L9Y 4M7",
    "addr:postcode":"l9y 4m7",
    "iso:country":"CA",
    "sg:city":"Collingwood",
    "sg:classifiers":[
        {
            "category":"Building & Trades",
            "subcategory":"Landscaping Services",
            "type":"Services"
        }
    ],
    "sg:phone":"+1 705 444 8383",
    "sg:postcode":"L9Y 4M7",
    "sg:province":"ON",
    "sg:tags":[
        "topsoil"
    ],
    "wof:name":"Michelle's Top Soil",
    "wof:placetype":"venue"
},
  "geometry": {"coordinates":[-80.23519899999999,44.494507],"type":"Point"}
}