{
  "type": "Feature",
  "properties": {
    "addr:full":"Quebec QC G1N 2W1",
    "addr:postcode":"g1n 2w1",
    "iso:country":"CA",
    "sg:city":"Quebec",
    "sg:classifiers":[
        {
            "category":"Organizations",
            "subcategory":"Professional Association",
            "type":"Services"
        }
    ],
    "sg:phone":"+1 418 524 8752",
    "sg:postcode":"G1N 2W1",
    "sg:province":"QC",
    "wof:name":"Epilepsie Section DE Quebec",
    "wof:placetype":"venue"
},
  "geometry": {"coordinates":[-71.2451629639,46.8122520447],"type":"Point"}
}