{
  "type": "Feature",
  "properties": {
    "addr:full":"59 Stronach Mtn Rd Kingston NS B0P 1R0",
    "addr:housenumber":"59",
    "addr:postcode":"b0p 1r0",
    "addr:street":"Stronach Mtn Rd",
    "iso:country":"CA",
    "sg:address":"59 Stronach Mtn Rd",
    "sg:city":"Kingston",
    "sg:classifiers":[
        {
            "category":"Retail",
            "subcategory":"Repair Shop",
            "type":"Services"
        }
    ],
    "sg:phone":"+1 902 848 6750",
    "sg:postcode":"B0P 1R0",
    "sg:province":"NS",
    "sg:tags":[
        "lock",
        "locksmith"
    ],
    "wof:name":"Tibb's Tumblers Locksmithing",
    "wof:placetype":"venue"
},
  "geometry": {"coordinates":[-64.9493560791,44.9874382019],"type":"Point"}
}