{
  "type": "Feature",
  "properties": {
    "addr:full":"229 Kenmount Rd St. John's NL A1B 3P9",
    "addr:housenumber":"229",
    "addr:postcode":"a1b 3p9",
    "addr:street":"Kenmount Rd",
    "iso:country":"CA",
    "sg:address":"229 Kenmount Rd",
    "sg:city":"St. John's",
    "sg:classifiers":[
        {
            "category":"Autos & Motor Vehicles",
            "subcategory":"Automobile Sales",
            "type":"Retail Goods"
        }
    ],
    "sg:phone":"+1 709 726 6277",
    "sg:postcode":"A1B 3P9",
    "sg:province":"NL",
    "sg:tags":[
        "car",
        "dealer"
    ],
    "wof:name":"Auto Source Inc",
    "wof:placetype":"venue"
},
  "geometry": {"coordinates":[-52.770775,47.553661],"type":"Point"}
}