{
  "type": "Feature",
  "properties": {
    "addr:full":"Estevan SK S4A 0W9",
    "addr:postcode":"s4a 0w9",
    "iso:country":"CA",
    "sg:city":"Estevan",
    "sg:classifiers":[
        {
            "category":"Health Services",
            "subcategory":"Doctor",
            "type":"Services"
        }
    ],
    "sg:phone":"+1 306 634 7261",
    "sg:postcode":"S4A 0W9",
    "sg:province":"SK",
    "sg:tags":[
        "dentist"
    ],
    "wof:name":"Blischak, Gale J DDS",
    "wof:placetype":"venue"
},
  "geometry": {"coordinates":[-102.99558258099999,49.1405258179],"type":"Point"}
}