{
  "type": "Feature",
  "properties": {
    "addr:full":"5102 50 St Eckville AB T0M 0X0",
    "addr:housenumber":"5102",
    "addr:postcode":"t0m 0x0",
    "addr:street":"50 St",
    "iso:country":"CA",
    "sg:address":"5102 50 St",
    "sg:city":"Eckville",
    "sg:classifiers":[
        {
            "category":"Professional",
            "subcategory":"Business Services",
            "type":"Services"
        }
    ],
    "sg:phone":"+1 403 746 2339",
    "sg:postcode":"T0M 0X0",
    "sg:province":"AB",
    "sg:tags":[
        "water",
        "hauling"
    ],
    "wof:name":"Hughes Transport Svc Ltd",
    "wof:placetype":"venue"
},
  "geometry": {"coordinates":[-114.368126,52.360172],"type":"Point"}
}