{
  "type": "Feature",
  "properties": {
    "iso:country":"CA",
    "sg:address":"52 Monterey Ave",
    "sg:city":"Brampton",
    "sg:classifiers":[
        {
            "category":"Retail",
            "subcategory":"Repair Shop",
            "type":"Services"
        }
    ],
    "sg:phone":"+1 905 840 8143",
    "sg:postcode":"L6Z 1B5",
    "sg:province":"ON",
    "sg:tags":[
        "lock",
        "locksmith"
    ],
    "wof:name":"K D Lock Svc",
    "wof:placetype":"venue"
},
  "geometry": {"coordinates":[-79.803375,43.732048],"type":"Point"}
}