{
  "type": "Feature",
  "properties": {
    "addr:full":"269 Newport Dr Port Moody BC V3H 5C9",
    "addr:housenumber":"269",
    "addr:postcode":"v3h 5c9",
    "addr:street":"Newport Dr",
    "iso:country":"CA",
    "sg:address":"269 Newport Dr",
    "sg:city":"Port Moody",
    "sg:classifiers":[
        {
            "category":"Personal",
            "subcategory":"Barber",
            "type":"Services"
        }
    ],
    "sg:phone":"+1 604 461 6678",
    "sg:postcode":"V3H 5C9",
    "sg:province":"BC",
    "wof:name":"Newport Village Barbers",
    "wof:placetype":"venue"
},
  "geometry": {"coordinates":[-122.825974,49.28336],"type":"Point"}
}