{
  "type": "Feature",
  "properties": {
    "addr:full":"410 Clare Ave Burnaby BC V5B 4L4",
    "addr:housenumber":"410",
    "addr:postcode":"v5b 4l4",
    "addr:street":"Clare Ave",
    "iso:country":"CA",
    "sg:address":"410 Clare Ave",
    "sg:city":"Burnaby",
    "sg:classifiers":[
        {
            "category":"Social Services",
            "type":"Services"
        }
    ],
    "sg:phone":"+1 604 299 5112",
    "sg:postcode":"V5B 4L4",
    "sg:province":"BC",
    "sg:tags":[
        "community"
    ],
    "wof:name":"Burnaby Family Place",
    "wof:placetype":"venue"
},
  "geometry": {"coordinates":[-122.963211,49.280148],"type":"Point"}
}