{
  "type": "Feature",
  "properties": {
    "iso:country":"CA",
    "sg:address":"180 Woodbridge St",
    "sg:city":"Fredericton",
    "sg:classifiers":[
        {
            "category":"Health Services",
            "subcategory":"Doctor",
            "type":"Services"
        }
    ],
    "sg:phone":"+1 506 452 5681",
    "sg:postcode":"E3B 4R3",
    "sg:province":"NB",
    "sg:tags":[
        "physician",
        "surgeon"
    ],
    "wof:name":"Lecky, J R MD",
    "wof:placetype":"venue"
},
  "geometry": {"coordinates":[-66.6358718872,45.933052063],"type":"Point"}
}