{
  "type": "Feature",
  "properties": {
    "iso:country":"CA",
    "sg:address":"1 Protection St",
    "sg:city":"Saint John",
    "sg:classifiers":[
        {
            "category":"Professional",
            "subcategory":"Employment Agencies",
            "type":"Services"
        }
    ],
    "sg:phone":"+1 506 635 1910",
    "sg:postcode":"E2M 4Y1",
    "sg:province":"NB",
    "sg:tags":[
        "contractor"
    ],
    "wof:name":"Forest Products Terminal Corp",
    "wof:placetype":"venue"
},
  "geometry": {"coordinates":[-66.064125061,45.2734298706],"type":"Point"}
}