{
  "type": "Feature",
  "properties": {
    "addr:full":"1198 Sherwin Rd Winnipeg MB R3H 0V2",
    "addr:housenumber":"1198",
    "addr:postcode":"r3h 0v2",
    "addr:street":"Sherwin Rd",
    "iso:country":"CA",
    "sg:address":"1198 Sherwin Rd",
    "sg:city":"Winnipeg",
    "sg:classifiers":[
        {
            "category":"Wholesale",
            "subcategory":"Painting Supplies",
            "type":"Manufacturing & Wholesale Goods"
        }
    ],
    "sg:phone":"+1 204 633 3117",
    "sg:postcode":"R3H 0V2",
    "sg:province":"MB",
    "sg:tags":[
        "equipment",
        "painter"
    ],
    "wof:name":"Lemmer Spray Systems Ltd",
    "wof:placetype":"venue"
},
  "geometry": {"coordinates":[-97.21147918699999,49.913848877],"type":"Point"}
}