{
  "type": "Feature",
  "properties": {
    "addr:full":"164 Bagshaw St Parksville BC V9P 2H2",
    "addr:housenumber":"164",
    "addr:postcode":"v9p 2h2",
    "addr:street":"Bagshaw St",
    "iso:country":"CA",
    "sg:address":"164 Bagshaw St",
    "sg:city":"Parksville",
    "sg:classifiers":[
        {
            "category":"Restaurant",
            "type":"Food & Drink"
        }
    ],
    "sg:phone":"+1 250 248 8829",
    "sg:postcode":"V9P 2H2",
    "sg:province":"BC",
    "wof:name":"Pizza Hut",
    "wof:placetype":"venue"
},
  "geometry": {"coordinates":[-124.304084778,49.3182296753],"type":"Point"}
}