{
  "type": "Feature",
  "properties": {
    "addr:full":"1748 Ch DE Chambly Longueuil QC J4J 3X5",
    "addr:housenumber":"1748",
    "addr:postcode":"j4j 3x5",
    "addr:street":"Ch De Chambly",
    "iso:country":"CA",
    "sg:address":"1748 Ch DE Chambly",
    "sg:city":"Longueuil",
    "sg:classifiers":[
        {
            "category":"Shopping",
            "subcategory":"Pharmacy",
            "type":"Retail Goods"
        }
    ],
    "sg:phone":"+1 450 651 2000",
    "sg:postcode":"J4J 3X5",
    "sg:province":"QC",
    "wof:name":"Jean Coutu",
    "wof:placetype":"venue"
},
  "geometry": {"coordinates":[-73.4830780029,45.5299377441],"type":"Point"}
}