{
  "type": "Feature",
  "properties": {
    "addr:full":"797 Milford Dr Peterborough ON K9J 8J5",
    "addr:housenumber":"797",
    "addr:postcode":"k9j 8j5",
    "addr:street":"Milford Dr",
    "iso:country":"CA",
    "sg:address":"797 Milford Dr",
    "sg:city":"Peterborough",
    "sg:classifiers":[
        {
            "category":"Building & Trades",
            "subcategory":"Plumbing",
            "type":"Services"
        }
    ],
    "sg:phone":"+1 705 742 8769",
    "sg:postcode":"K9J 8J5",
    "sg:province":"ON",
    "sg:tags":[
        "furnace",
        "heating",
        "contractor"
    ],
    "wof:name":"Neil Johnston Heating",
    "wof:placetype":"venue"
},
  "geometry": {"coordinates":[-78.3018951416,44.2826652527],"type":"Point"}
}