{
  "type": "Feature",
  "properties": {
    "addr:full":"256Ab River Rd Corbyville ON K0K 1V0",
    "addr:housenumber":"256ab",
    "addr:postcode":"k0k 1v0",
    "addr:street":"River Rd",
    "iso:country":"CA",
    "sg:address":"256Ab River Rd",
    "sg:city":"Corbyville",
    "sg:classifiers":[
        {
            "category":"Home & Garden",
            "subcategory":"Household Appliances",
            "type":"Retail Goods"
        }
    ],
    "sg:phone":"+1 613 969 0287",
    "sg:postcode":"K0K 1V0",
    "sg:province":"ON",
    "wof:name":"Smitty's New & Used Appls Ltd",
    "wof:placetype":"venue"
},
  "geometry": {"coordinates":[-77.3887557983,44.2203102112],"type":"Point"}
}