{
  "type": "Feature",
  "properties": {
    "addr:full":"50 Riverside Dr Plaster Rock NB E7G 2P8",
    "addr:housenumber":"50",
    "addr:postcode":"e7g 2p8",
    "addr:street":"Riverside Dr",
    "iso:country":"CA",
    "sg:address":"50 Riverside Dr",
    "sg:city":"Plaster Rock",
    "sg:classifiers":[
        {
            "category":"Organizations",
            "subcategory":"Religious Organization",
            "type":"Services"
        }
    ],
    "sg:phone":"+1 506 356 2952",
    "sg:postcode":"E7G 2P8",
    "sg:province":"NB",
    "sg:tags":[
        "church"
    ],
    "wof:name":"Plaster Rock United Church",
    "wof:placetype":"venue"
},
  "geometry": {"coordinates":[-67.389732,46.898781],"type":"Point"}
}