{
  "type": "Feature",
  "properties": {
    "addr:full":"477 Rue Principale Saint-Patrice-DE-Beaurivage QC G0S 1B0",
    "addr:housenumber":"477",
    "addr:postcode":"g0s 1b0",
    "addr:street":"Rue Principale",
    "iso:country":"CA",
    "sg:address":"477 Rue Principale",
    "sg:city":"Saint-Patrice-DE-Beaurivage",
    "sg:classifiers":[
        {
            "category":"Organizations",
            "subcategory":"Religious Organization",
            "type":"Services"
        }
    ],
    "sg:phone":"+1 418 596 2154",
    "sg:postcode":"G0S 1B0",
    "sg:province":"QC",
    "sg:tags":[
        "church"
    ],
    "wof:name":"Presbytere St Patrice-Beaurvg",
    "wof:placetype":"venue"
},
  "geometry": {"coordinates":[-71.23947099999999,46.41151],"type":"Point"}
}