{
  "type": "Feature",
  "properties": {
    "addr:full":"Farm Naicam SK S0K 2Z0",
    "addr:postcode":"s0k 2z0",
    "iso:country":"CA",
    "sg:address":"Farm",
    "sg:city":"Naicam",
    "sg:classifiers":[
        {
            "category":"Government",
            "subcategory":"Office",
            "type":"Public Place"
        }
    ],
    "sg:phone":"+1 306 874 5209",
    "sg:postcode":"S0K 2Z0",
    "sg:province":"SK",
    "wof:name":"Saskatchewan Pleasandale Farm",
    "wof:placetype":"venue"
},
  "geometry": {"coordinates":[-104.49769592299999,52.4200744629],"type":"Point"}
}