{
  "type": "Feature",
  "properties": {
    "iso:country":"CA",
    "sg:address":"9292 Rue Meilleur",
    "sg:city":"Montreal",
    "sg:classifiers":[
        {
            "category":"Wholesale",
            "subcategory":"Drugs",
            "type":"Manufacturing & Wholesale Goods"
        }
    ],
    "sg:phone":"+1 514 389 8667",
    "sg:postcode":"H2N 2A5",
    "sg:province":"QC",
    "sg:tags":[
        "perfume"
    ],
    "wof:name":"J & M Grossiste En Parfums",
    "wof:placetype":"venue"
},
  "geometry": {"coordinates":[-73.654861,45.537323],"type":"Point"}
}