{
  "type": "Feature",
  "properties": {
    "addr:full":"21 Toro Rd North York ON M3J 2A4",
    "addr:housenumber":"21",
    "addr:postcode":"m3j 2a4",
    "addr:street":"Toro Rd",
    "iso:country":"CA",
    "sg:address":"21 Toro Rd",
    "sg:city":"North York",
    "sg:classifiers":[
        {
            "category":"Autos & Motor Vehicles",
            "subcategory":"Automobile Sales",
            "type":"Retail Goods"
        }
    ],
    "sg:phone":"+1 416 398 1383",
    "sg:postcode":"M3J 2A4",
    "sg:province":"ON",
    "sg:tags":[
        "car",
        "dealer"
    ],
    "wof:name":"Sun Auto",
    "wof:placetype":"venue"
},
  "geometry": {"coordinates":[-79.48857879640001,43.7599754333],"type":"Point"}
}