{
  "type": "Feature",
  "properties": {
    "addr:full":"Mine Rd Balmertown ON P0V 1C0",
    "addr:postcode":"p0v 1c0",
    "addr:street":"Mine Rd",
    "iso:country":"CA",
    "sg:address":"Mine Rd",
    "sg:city":"Balmertown",
    "sg:classifiers":[
        {
            "category":"Education",
            "subcategory":"School",
            "type":"Public Place"
        }
    ],
    "sg:phone":"+1 807 735 2088",
    "sg:postcode":"P0V 1C0",
    "sg:province":"ON",
    "wof:name":"Golden Learning Ctr",
    "wof:placetype":"venue"
},
  "geometry": {"coordinates":[-93.748856,51.059875],"type":"Point"}
}