{
  "type": "Feature",
  "properties": {
    "addr:full":"10115 93 St Grande Prairie AB T8V 1Y1",
    "addr:housenumber":"10115",
    "addr:postcode":"t8v 1y1",
    "addr:street":"93 St",
    "iso:country":"CA",
    "sg:address":"10115 93 St",
    "sg:city":"Grande Prairie",
    "sg:classifiers":[
        {
            "category":"Organizations",
            "subcategory":"Professional Association",
            "type":"Services"
        }
    ],
    "sg:phone":"+1 780 538 2608",
    "sg:postcode":"T8V 1Y1",
    "sg:province":"AB",
    "sg:tags":[
        "club"
    ],
    "wof:name":"Centaurs Rugby Football Club",
    "wof:placetype":"venue"
},
  "geometry": {"coordinates":[-118.77372,55.17178],"type":"Point"}
}