{
  "type": "Feature",
  "properties": {
    "addr:full":"2837 Rue Des Berges Levis QC G6V 8Y5",
    "addr:housenumber":"2837",
    "addr:postcode":"g6v 8y5",
    "addr:street":"Rue Des Berges",
    "iso:country":"CA",
    "sg:address":"2837 Rue Des Berges",
    "sg:city":"Levis",
    "sg:classifiers":[
        {
            "category":"Banks & Credit Unions",
            "subcategory":"Investment Brokerage",
            "type":"Services"
        }
    ],
    "sg:phone":"+1 418 834 8250",
    "sg:postcode":"G6V 8Y5",
    "sg:province":"QC",
    "sg:tags":[
        "advisory",
        "financial"
    ],
    "wof:name":"Services Financiers Rsl Inc",
    "wof:placetype":"venue"
},
  "geometry": {"coordinates":[-71.2251281738,46.7653121948],"type":"Point"}
}