{
  "type": "Feature",
  "properties": {
    "addr:full":"Highway 3 Hubbards NS B0J 1T0",
    "addr:postcode":"b0j 1t0",
    "addr:street":"Highway 3",
    "iso:country":"CA",
    "sg:address":"Highway 3",
    "sg:city":"Hubbards",
    "sg:classifiers":[
        {
            "category":"Government",
            "subcategory":"Office",
            "type":"Public Place"
        }
    ],
    "sg:phone":"+1 902 857 5646",
    "sg:postcode":"B0J 1T0",
    "sg:province":"NS",
    "sg:tags":[
        "member",
        "legislative",
        "assembly"
    ],
    "wof:name":"Chataway, John",
    "wof:placetype":"venue"
},
  "geometry": {"coordinates":[-64.052055,44.643314],"type":"Point"}
}