{
  "type": "Feature",
  "properties": {
    "iso:country":"CA",
    "sg:city":"Burlington",
    "sg:classifiers":[
        {
            "category":"Manufacturing",
            "subcategory":"Tools & Machinery",
            "type":"Manufacturing & Wholesale Goods"
        }
    ],
    "sg:phone":"+1 905 335 5038",
    "sg:postcode":"L7M 1K5",
    "sg:province":"ON",
    "sg:tags":[
        "machine",
        "shop"
    ],
    "wof:name":"Burlington Centreless Grinding",
    "wof:placetype":"venue"
},
  "geometry": {"coordinates":[-79.8014297485,43.3631401062],"type":"Point"}
}