{
  "type": "Feature",
  "properties": {
    "addr:full":"380 Vansickle Rd St Catharines ON L2R 6P7",
    "addr:housenumber":"380",
    "addr:postcode":"l2r 6p7",
    "addr:street":"Vansickle Rd",
    "iso:country":"CA",
    "sg:address":"380 Vansickle Rd",
    "sg:city":"St Catharines",
    "sg:classifiers":[
        {
            "category":"Restaurant",
            "type":"Food & Drink"
        }
    ],
    "sg:phone":"+1 905 682 2433",
    "sg:postcode":"L2R 6P7",
    "sg:province":"ON",
    "sg:tags":[
        "caterer"
    ],
    "wof:name":"Chef Paul's Catering Svc Inc",
    "wof:placetype":"venue"
},
  "geometry": {"coordinates":[-79.270195,43.148914],"type":"Point"}
}