{
  "type": "Feature",
  "properties": {
    "addr:full":"15325 Bannister Rd SE Calgary AB T2X 1Z3",
    "addr:housenumber":"15325",
    "addr:postcode":"t2x 1z3",
    "addr:street":"Bannister Rd Se",
    "iso:country":"CA",
    "sg:address":"15325 Bannister Rd SE",
    "sg:city":"Calgary",
    "sg:classifiers":[
        {
            "category":"Restaurant",
            "type":"Food & Drink"
        }
    ],
    "sg:phone":"+1 403 254 6988",
    "sg:postcode":"T2X 1Z3",
    "sg:province":"AB",
    "wof:name":"Kfc",
    "wof:placetype":"venue"
},
  "geometry": {"coordinates":[-114.067154,50.915863],"type":"Point"}
}