{
  "type": "Feature",
  "properties": {
    "addr:full":"24 Rue Elgin Aylmer QC J9H 1E2",
    "addr:housenumber":"24",
    "addr:postcode":"j9h 1e2",
    "addr:street":"Rue Elgin",
    "iso:country":"CA",
    "sg:address":"24 Rue Elgin",
    "sg:city":"Aylmer",
    "sg:classifiers":[
        {
            "category":"Professional",
            "subcategory":"Art Services",
            "type":"Services"
        }
    ],
    "sg:phone":"+1 819 682 4677",
    "sg:postcode":"J9H 1E2",
    "sg:province":"QC",
    "sg:tags":[
        "writer",
        "graphic",
        "designer"
    ],
    "wof:name":"R K Asterisk Inc",
    "wof:placetype":"venue"
},
  "geometry": {"coordinates":[-75.827545,45.393341],"type":"Point"}
}