{
  "type": "Feature",
  "properties": {
    "iso:country":"CA",
    "sg:city":"Port Coquitlam",
    "sg:classifiers":[
        {
            "category":"Food & Beverages",
            "subcategory":"Bakery",
            "type":"Retail Goods"
        }
    ],
    "sg:phone":"+1 604 942 5000",
    "sg:postcode":"V3C 2A9",
    "sg:province":"BC",
    "sg:tags":[
        "baker"
    ],
    "wof:name":"Gisela's Bakery & Deli",
    "wof:placetype":"venue"
},
  "geometry": {"coordinates":[-122.77916,49.26215],"type":"Point"}
}