{
  "type": "Feature",
  "properties": {
    "addr:full":"9230 Islington Ave Woodbridge ON L4L 1A6",
    "addr:housenumber":"9230",
    "addr:postcode":"l4l 1a6",
    "addr:street":"Islington Ave",
    "iso:country":"CA",
    "sg:address":"9230 Islington Ave",
    "sg:city":"Woodbridge",
    "sg:classifiers":[
        {
            "category":"Wholesale",
            "subcategory":"Construction Materials",
            "type":"Manufacturing & Wholesale Goods"
        }
    ],
    "sg:phone":"+1 905 856 3332",
    "sg:postcode":"L4L 1A6",
    "sg:province":"ON",
    "sg:tags":[
        "pallet",
        "skid"
    ],
    "wof:name":"Woodbridge Pallet Ltd",
    "wof:placetype":"venue"
},
  "geometry": {"coordinates":[-79.5993652344,43.8163032532],"type":"Point"}
}