{
  "type": "Feature",
  "properties": {
    "iso:country":"CA",
    "sg:address":"52 St Gerard St",
    "sg:city":"Ste Anne",
    "sg:classifiers":[
        {
            "category":"Health Services",
            "subcategory":"Hospital",
            "type":"Services"
        }
    ],
    "sg:phone":"+1 204 422 8837",
    "sg:postcode":"R5H 1C4",
    "sg:province":"MB",
    "wof:name":"Ste Anne Hospital",
    "wof:placetype":"venue"
},
  "geometry": {"coordinates":[-96.648109436,49.6679878235],"type":"Point"}
}