{
  "type": "Feature",
  "properties": {
    "iso:country":"CA",
    "sg:address":"2775 Kew Dr",
    "sg:city":"Windsor",
    "sg:classifiers":[
        {
            "category":"Wholesale",
            "subcategory":"Machinery & Supplies",
            "type":"Manufacturing & Wholesale Goods"
        }
    ],
    "sg:phone":"+1 519 944 3877",
    "sg:postcode":"N8T 3B7",
    "sg:province":"ON",
    "sg:tags":[
        "equipment",
        "hydraulic"
    ],
    "wof:name":"Morrell Controls Canada",
    "wof:placetype":"venue"
},
  "geometry": {"coordinates":[-82.9394989014,42.3050117493],"type":"Point"}
}