{
  "type": "Feature",
  "properties": {
    "addr:full":"82 Lorne St Sudbury ON P3C 4N8",
    "addr:housenumber":"82",
    "addr:postcode":"p3c 4n8",
    "addr:street":"Lorne St",
    "iso:country":"CA",
    "sg:address":"82 Lorne St",
    "sg:city":"Sudbury",
    "sg:classifiers":[
        {
            "category":"Food & Beverages",
            "subcategory":"Groceries & Convenience Stores",
            "type":"Retail Goods"
        }
    ],
    "sg:phone":"+1 705 671 3051",
    "sg:postcode":"P3C 4N8",
    "sg:province":"ON",
    "sg:tags":[
        "grocer"
    ],
    "wof:name":"Your Independent Grocer",
    "wof:placetype":"venue"
},
  "geometry": {"coordinates":[-81.001656,46.491032],"type":"Point"}
}