{
  "type": "Feature",
  "properties": {
    "iso:country":"CA",
    "sg:address":"3297 Douglas St",
    "sg:city":"Victoria",
    "sg:classifiers":[
        {
            "category":"Banks & Credit Unions",
            "subcategory":"Bank",
            "type":"Services"
        }
    ],
    "sg:phone":"+1 250 475 3958",
    "sg:postcode":"V8Z 3K9",
    "sg:province":"BC",
    "sg:tags":[
        "cashing",
        "check"
    ],
    "wof:name":"Money Mart",
    "wof:placetype":"venue"
},
  "geometry": {"coordinates":[-123.37233,48.44767],"type":"Point"}
}