{
  "type": "Feature",
  "properties": {
    "addr:full":"5165 Enfield Rd Hampton ON L0B 1J0",
    "addr:housenumber":"5165",
    "addr:postcode":"l0b 1j0",
    "addr:street":"Enfield Rd",
    "iso:country":"CA",
    "sg:address":"5165 Enfield Rd",
    "sg:city":"Hampton",
    "sg:classifiers":[
        {
            "category":"Organizations",
            "subcategory":"Religious Organization",
            "type":"Services"
        }
    ],
    "sg:phone":"+1 905 725 6145",
    "sg:postcode":"L0B 1J0",
    "sg:province":"ON",
    "sg:tags":[
        "church"
    ],
    "wof:name":"Zion United Church",
    "wof:placetype":"venue"
},
  "geometry": {"coordinates":[-78.748352,43.972511],"type":"Point"}
}