{
  "type": "Feature",
  "properties": {
    "addr:full":"7930 Kipling Ave Woodbridge ON L4L 1Z5",
    "addr:housenumber":"7930",
    "addr:postcode":"l4l 1z5",
    "addr:street":"Kipling Ave",
    "iso:country":"CA",
    "sg:address":"7930 Kipling Ave",
    "sg:city":"Woodbridge",
    "sg:classifiers":[
        {
            "category":"Retail",
            "subcategory":"Portrait Studio",
            "type":"Services"
        }
    ],
    "sg:phone":"+1 905 850 9596",
    "sg:postcode":"L4L 1Z5",
    "sg:province":"ON",
    "sg:tags":[
        "photographer"
    ],
    "wof:name":"Quarum Studios",
    "wof:placetype":"venue"
},
  "geometry": {"coordinates":[-79.5984802246,43.7830924988],"type":"Point"}
}