{
  "type": "Feature",
  "properties": {
    "addr:full":"1231 Rue Sainte-Catherine O # 508 Montreal QC H3G 1P5",
    "addr:housenumber":"1231",
    "addr:postcode":"h3g 1p5",
    "addr:street":"Rue Sainte-Catherine O # 508",
    "iso:country":"CA",
    "sg:address":"1231 Rue Sainte-Catherine O # 508",
    "sg:city":"Montreal",
    "sg:classifiers":[
        {
            "category":"Professional",
            "subcategory":"Lawyer & Legal Services",
            "type":"Services"
        }
    ],
    "sg:phone":"+1 514 667 5700",
    "sg:postcode":"H3G 1P5",
    "sg:province":"QC",
    "sg:tags":[
        "attorney"
    ],
    "wof:name":"Centruion, Manuel",
    "wof:placetype":"venue"
},
  "geometry": {"coordinates":[-73.5561294556,45.5187110901],"type":"Point"}
}