{
  "type": "Feature",
  "properties": {
    "addr:full":"2999 Voght St Merritt BC V1K 1G9",
    "addr:housenumber":"2999",
    "addr:postcode":"v1k 1g9",
    "addr:street":"Voght St",
    "iso:country":"CA",
    "sg:address":"2999 Voght St",
    "sg:city":"Merritt",
    "sg:classifiers":[
        {
            "category":"Social Services",
            "type":"Services"
        }
    ],
    "sg:phone":"+1 250 378 5699",
    "sg:postcode":"V1K 1G9",
    "sg:province":"BC",
    "sg:tags":[
        "crisis",
        "center"
    ],
    "wof:name":"Merritt Victim Svc",
    "wof:placetype":"venue"
},
  "geometry": {"coordinates":[-120.781448364,50.1183624268],"type":"Point"}
}