{
  "type": "Feature",
  "properties": {
    "addr:full":"602 Baker St Nelson BC V1L 4J4",
    "addr:housenumber":"602",
    "addr:postcode":"bc v1l 4j4",
    "addr:street":"Baker St",
    "iso:country":"CA",
    "sg:address":"602 Baker St",
    "sg:city":"Nelson",
    "sg:classifiers":[
        {
            "category":"Banks & Credit Unions",
            "subcategory":"Investment Brokerage",
            "type":"Services"
        }
    ],
    "sg:phone":"+1 250 354 4834",
    "sg:postcode":"V1L 4J4",
    "sg:province":"BC",
    "wof:name":"Cibc Wood Gundy Inc",
    "wof:placetype":"venue"
},
  "geometry": {"coordinates":[-117.29235799999999,49.492477],"type":"Point"}
}