{
  "type": "Feature",
  "properties": {
    "addr:full":"4700 Rue DE LA Savane Montreal QC H4P 1T7",
    "addr:housenumber":"4700",
    "addr:postcode":"h4p 1t7",
    "addr:street":"Rue De La Savane",
    "iso:country":"CA",
    "sg:address":"4700 Rue DE LA Savane",
    "sg:city":"Montreal",
    "sg:classifiers":[
        {
            "category":"Professional",
            "subcategory":"Management & Consulting",
            "type":"Services"
        }
    ],
    "sg:phone":"+1 514 737 9393",
    "sg:postcode":"H4P 1T7",
    "sg:province":"QC",
    "sg:tags":[
        "consultant",
        "educational"
    ],
    "wof:name":"Intra Med",
    "wof:placetype":"venue"
},
  "geometry": {"coordinates":[-73.65063499999999,45.500538],"type":"Point"}
}