{
  "type": "Feature",
  "properties": {
    "addr:full":"242 Echo Bay Rd Huntsville ON P1H 1R4",
    "addr:housenumber":"242",
    "addr:postcode":"p1h 1r4",
    "addr:street":"Echo Bay Rd",
    "iso:country":"CA",
    "sg:address":"242 Echo Bay Rd",
    "sg:city":"Huntsville",
    "sg:classifiers":[
        {
            "category":"Building & Trades",
            "subcategory":"Plumbing",
            "type":"Services"
        }
    ],
    "sg:phone":"+1 705 789 5411",
    "sg:postcode":"P1H 1R4",
    "sg:province":"ON",
    "sg:tags":[
        "conditioning",
        "air",
        "system",
        "contractor"
    ],
    "wof:name":"Obee Refrigeration & Electric",
    "wof:placetype":"venue"
},
  "geometry": {"coordinates":[-79.19626599999999,45.314568],"type":"Point"}
}