{
  "type": "Feature",
  "properties": {
    "addr:full":"Kitchener ON N2E 3G4",
    "addr:postcode":"n2e 3g4",
    "iso:country":"CA",
    "sg:city":"Kitchener",
    "sg:classifiers":[
        {
            "category":"Manufacturing",
            "subcategory":"Printing",
            "type":"Manufacturing & Wholesale Goods"
        }
    ],
    "sg:phone":"+1 519 894 6514",
    "sg:postcode":"N2E 3G4",
    "sg:province":"ON",
    "sg:tags":[
        "printer",
        "advertising"
    ],
    "wof:name":"Direction Inc",
    "wof:placetype":"venue"
},
  "geometry": {"coordinates":[-80.471603,43.40667],"type":"Point"}
}