{
  "type": "Feature",
  "properties": {
    "iso:country":"CA",
    "sg:city":"Marmora",
    "sg:classifiers":[
        {
            "category":"Travel",
            "subcategory":"Hotels & Motels",
            "type":"Entertainment"
        }
    ],
    "sg:phone":"+1 613 472 2415",
    "sg:postcode":"K0K 2M0",
    "sg:province":"ON",
    "sg:tags":[
        "resort"
    ],
    "wof:name":"Glen Allan Trailer Park",
    "wof:placetype":"venue"
},
  "geometry": {"coordinates":[-77.6815567017,44.483089447],"type":"Point"}
}