{
  "type": "Feature",
  "properties": {
    "addr:full":"252 Queen St S Mississauga ON L5M 1L8",
    "addr:housenumber":"252",
    "addr:postcode":"l5m 1l8",
    "addr:street":"Queen St S",
    "iso:country":"CA",
    "sg:address":"252 Queen St S",
    "sg:city":"Mississauga",
    "sg:classifiers":[
        {
            "category":"Health Services",
            "subcategory":"Medical Lab",
            "type":"Services"
        }
    ],
    "sg:phone":"+1 905 821 0334",
    "sg:postcode":"L5M 1L8",
    "sg:province":"ON",
    "wof:name":"Kulik Denture Clinic",
    "wof:placetype":"venue"
},
  "geometry": {"coordinates":[-79.6005554199,43.5429115295],"type":"Point"}
}