{
  "type": "Feature",
  "properties": {
    "iso:country":"CA",
    "sg:city":"Burnaby",
    "sg:classifiers":[
        {
            "category":"Autos & Motor Vehicles",
            "subcategory":"Auto Supplies",
            "type":"Retail Goods"
        }
    ],
    "sg:phone":"+1 604 435 2749",
    "sg:postcode":"V5J 3H6",
    "sg:province":"BC",
    "sg:tags":[
        "tire"
    ],
    "wof:name":"Rudy's Tire Svc Ltd",
    "wof:placetype":"venue"
},
  "geometry": {"coordinates":[-122.993721,49.195637],"type":"Point"}
}