{
  "type": "Feature",
  "properties": {
    "iso:country":"CA",
    "sg:address":"Salt Springs Rd",
    "sg:city":"Antigonish",
    "sg:classifiers":[
        {
            "category":"Autos & Motor Vehicles",
            "subcategory":"Fuel & Gas Station",
            "type":"Retail Goods"
        }
    ],
    "sg:phone":"+1 902 863 5677",
    "sg:postcode":"B2G 2L3",
    "sg:province":"NS",
    "sg:tags":[
        "oil"
    ],
    "wof:name":"Mac Eachern's Ultramar",
    "wof:placetype":"venue"
},
  "geometry": {"coordinates":[-61.996181488,45.5783157349],"type":"Point"}
}