{
  "type": "Feature",
  "properties": {
    "iso:country":"CA",
    "sg:address":"326 Boul Saint-Joseph E",
    "sg:city":"Montreal",
    "sg:classifiers":[
        {
            "category":"Professional",
            "subcategory":"Management & Consulting",
            "type":"Services"
        }
    ],
    "sg:phone":"+1 514 849 7900",
    "sg:postcode":"H2T 1J2",
    "sg:province":"QC",
    "sg:tags":[
        "technical",
        "expertise",
        "analysis"
    ],
    "wof:name":"Centre Helios",
    "wof:placetype":"venue"
},
  "geometry": {"coordinates":[-73.588417,45.525288],"type":"Point"}
}