{
  "type": "Feature",
  "properties": {
    "addr:full":"326 Boul Saint-Joseph E Montreal QC H2T 1J2",
    "addr:housenumber":"326",
    "addr:postcode":"h2t 1j2",
    "addr:street":"Boul Saint-Joseph E",
    "iso:country":"CA",
    "sg:address":"326 Boul Saint-Joseph E",
    "sg:city":"Montreal",
    "sg:classifiers":[
        {
            "category":"Professional",
            "subcategory":"Management & Consulting",
            "type":"Services"
        }
    ],
    "sg:phone":"+1 514 849 7900",
    "sg:postcode":"H2T 1J2",
    "sg:province":"QC",
    "sg:tags":[
        "technical",
        "expertise",
        "analysis"
    ],
    "wof:name":"Centre Helios",
    "wof:placetype":"venue"
},
  "geometry": {"coordinates":[-73.58841700000001,45.525288],"type":"Point"}
}