{
  "type": "Feature",
  "properties": {
    "addr:full":"1528 Michigan Line Sarnia ON N7T 7H4",
    "addr:housenumber":"1528",
    "addr:postcode":"n7t 7h4",
    "addr:street":"Michigan Line",
    "iso:country":"CA",
    "sg:address":"1528 Michigan Line",
    "sg:city":"Sarnia",
    "sg:classifiers":[
        {
            "category":"Organizations",
            "subcategory":"Religious Organization",
            "type":"Services"
        }
    ],
    "sg:phone":"+1 519 542 4995",
    "sg:postcode":"N7T 7H4",
    "sg:province":"ON",
    "sg:tags":[
        "church"
    ],
    "wof:name":"Foundation of Faith Fellowship",
    "wof:placetype":"venue"
},
  "geometry": {"coordinates":[-82.338539,43.003696],"type":"Point"}
}