{
  "type": "Feature",
  "properties": {
    "addr:full":"283 Port Union Rd Scarborough ON M1C 2L3",
    "addr:housenumber":"283",
    "addr:postcode":"m1c 2l3",
    "addr:street":"Port Union Rd",
    "iso:country":"CA",
    "sg:address":"283 Port Union Rd",
    "sg:city":"Scarborough",
    "sg:classifiers":[
        {
            "category":"Shopping",
            "subcategory":"Gifts & Souvenirs",
            "type":"Retail Goods"
        }
    ],
    "sg:phone":"+1 416 724 7223",
    "sg:postcode":"M1C 2L3",
    "sg:province":"ON",
    "sg:tags":[
        "collectible"
    ],
    "wof:name":"Toronto Motorsport Collectible",
    "wof:placetype":"venue"
},
  "geometry": {"coordinates":[-79.14046478269999,43.7891044617],"type":"Point"}
}