{
  "type": "Feature",
  "properties": {
    "iso:country":"CA",
    "sg:city":"Winnipeg",
    "sg:classifiers":[
        {
            "category":"Manufacturing",
            "subcategory":"Lumber",
            "type":"Manufacturing & Wholesale Goods"
        }
    ],
    "sg:phone":"+1 204 474 5047",
    "sg:postcode":"R3T 3L6",
    "sg:province":"MB",
    "wof:name":"Great Northern Remanufacturing",
    "wof:placetype":"venue"
},
  "geometry": {"coordinates":[-97.1581039429,49.8272781372],"type":"Point"}
}