{
  "type": "Feature",
  "properties": {
    "iso:country":"CA",
    "sg:address":"1575 Rue Turmel",
    "sg:city":"L'Ancienne-Lorette",
    "sg:classifiers":[
        {
            "category":"Social Services",
            "type":"Services"
        }
    ],
    "sg:phone":"+1 418 871 7055",
    "sg:postcode":"G2E 3J5",
    "sg:province":"QC",
    "sg:tags":[
        "organization",
        "government",
        "welfare"
    ],
    "wof:name":"Service D'Entraide Comm Rayon",
    "wof:placetype":"venue"
},
  "geometry": {"coordinates":[-71.362259,46.798412],"type":"Point"}
}