{
  "type": "Feature",
  "properties": {
    "addr:full":"11 Armstrong Ave Georgetown ON L7G 4S1",
    "addr:housenumber":"11",
    "addr:postcode":"l7g 4s1",
    "addr:street":"Armstrong Ave",
    "iso:country":"CA",
    "sg:address":"11 Armstrong Ave",
    "sg:city":"Georgetown",
    "sg:classifiers":[
        {
            "category":"Wholesale",
            "subcategory":"Metals & Minerals",
            "type":"Manufacturing & Wholesale Goods"
        }
    ],
    "sg:phone":"+1 905 877 2293",
    "sg:postcode":"L7G 4S1",
    "sg:province":"ON",
    "sg:tags":[
        "valve"
    ],
    "wof:name":"Howell Pipe & Supply",
    "wof:placetype":"venue"
},
  "geometry": {"coordinates":[-79.9060592651,43.6553153992],"type":"Point"}
}