{
  "type": "Feature",
  "properties": {
    "iso:country":"CA",
    "sg:address":"4715 10 Ave NW",
    "sg:city":"Edmonton",
    "sg:classifiers":[
        {
            "category":"Building & Trades",
            "subcategory":"Plumbing",
            "type":"Services"
        }
    ],
    "sg:phone":"+1 780 469 3054",
    "sg:postcode":"T6L 4S2",
    "sg:province":"AB",
    "sg:tags":[
        "conditioning",
        "air",
        "refrigeration",
        "system",
        "contractor"
    ],
    "wof:name":"Capital Region Hvac Svc Ltd",
    "wof:placetype":"venue"
},
  "geometry": {"coordinates":[-113.41268158,53.4379844666],"type":"Point"}
}