{
  "type": "Feature",
  "properties": {
    "addr:full":"Toronto ON M4T 1M9",
    "addr:postcode":"m4t 1m9",
    "iso:country":"CA",
    "sg:city":"Toronto",
    "sg:classifiers":[
        {
            "category":"Education",
            "subcategory":"Vocational School",
            "type":"Public Place"
        }
    ],
    "sg:phone":"+1 416 515 1151",
    "sg:postcode":"M4T 1M9",
    "sg:province":"ON",
    "sg:tags":[
        "nurse"
    ],
    "wof:name":"Parmed Academy",
    "wof:placetype":"venue"
},
  "geometry": {"coordinates":[-79.392105,43.688629],"type":"Point"}
}