{
  "type": "Feature",
  "properties": {
    "addr:full":"Westville NS B0K 2A0",
    "addr:postcode":"b0k 2a0",
    "iso:country":"CA",
    "sg:city":"Westville",
    "sg:classifiers":[
        {
            "category":"Airport",
            "type":"Transportation"
        }
    ],
    "sg:phone":"+1 902 396 1533",
    "sg:postcode":"B0K 2A0",
    "sg:province":"NS",
    "sg:tags":[
        "aircraft",
        "maintenance"
    ],
    "wof:name":"Mac Kay, J L",
    "wof:placetype":"venue"
},
  "geometry": {"coordinates":[-62.717590332,45.5608863831],"type":"Point"}
}