{
  "type": "Feature",
  "properties": {
    "addr:full":"8730 51 Ave NW Edmonton AB T6E 5E8",
    "addr:housenumber":"8730",
    "addr:postcode":"t6e 5e8",
    "addr:street":"51 Ave Nw",
    "iso:country":"CA",
    "sg:address":"8730 51 Ave NW",
    "sg:city":"Edmonton",
    "sg:classifiers":[
        {
            "category":"Shopping",
            "type":"Retail Goods"
        }
    ],
    "sg:phone":"+1 780 468 3347",
    "sg:postcode":"T6E 5E8",
    "sg:province":"AB",
    "sg:tags":[
        "art",
        "gallery",
        "dealer"
    ],
    "wof:name":"Art CO Ltd",
    "wof:placetype":"venue"
},
  "geometry": {"coordinates":[-113.458641052,53.4882774353],"type":"Point"}
}