{
  "type": "Feature",
  "properties": {
    "iso:country":"CA",
    "sg:address":"666 Burnhamthorpe Rd",
    "sg:city":"Etobicoke",
    "sg:classifiers":[
        {
            "category":"Health Services",
            "subcategory":"Optometrist",
            "type":"Services"
        }
    ],
    "sg:phone":"+1 416 626 3292",
    "sg:postcode":"M9C 2Z4",
    "sg:province":"ON",
    "wof:name":"Weinryb, Calvin OD",
    "wof:placetype":"venue"
},
  "geometry": {"coordinates":[-79.5771942139,43.6421508789],"type":"Point"}
}