{
  "type": "Feature",
  "properties": {
    "addr:full":"Rockwood ON N0B 2K0",
    "addr:postcode":"n0b 2k0",
    "iso:country":"CA",
    "sg:city":"Rockwood",
    "sg:classifiers":[
        {
            "category":"Social Services",
            "type":"Services"
        }
    ],
    "sg:phone":"+1 519 856 4671",
    "sg:postcode":"N0B 2K0",
    "sg:province":"ON",
    "sg:tags":[
        "youth",
        "organization",
        "center"
    ],
    "wof:name":"Camp Brebeuf",
    "wof:placetype":"venue"
},
  "geometry": {"coordinates":[-80.128868,43.590118],"type":"Point"}
}