{
  "type": "Feature",
  "properties": {
    "addr:full":"Lanoraie QC J0K 1E0",
    "addr:postcode":"j0k 1e0",
    "iso:country":"CA",
    "sg:city":"Lanoraie",
    "sg:classifiers":[
        {
            "category":"Government",
            "subcategory":"Office",
            "type":"Public Place"
        }
    ],
    "sg:phone":"+1 450 887 7878",
    "sg:postcode":"J0K 1E0",
    "sg:province":"QC",
    "sg:tags":[
        "village"
    ],
    "wof:name":"Pavillon Clement Loranger",
    "wof:placetype":"venue"
},
  "geometry": {"coordinates":[-73.22023799999999,45.958256],"type":"Point"}
}