{
  "type": "Feature",
  "properties": {
    "iso:country":"CA",
    "sg:address":"870 Car DE Tracy E",
    "sg:city":"Charlesbourg",
    "sg:classifiers":[
        {
            "category":"Manufacturing",
            "subcategory":"Printing",
            "type":"Manufacturing & Wholesale Goods"
        }
    ],
    "sg:phone":"+1 418 628 3445",
    "sg:postcode":"G2L 1L2",
    "sg:province":"QC",
    "sg:tags":[
        "publisher"
    ],
    "wof:name":"Editions Le Renouveau Chrlsbrg",
    "wof:placetype":"venue"
},
  "geometry": {"coordinates":[-71.2468414307,46.8826980591],"type":"Point"}
}