{
  "type": "Feature",
  "properties": {
    "addr:full":"1 Whitewood Ave New Liskeard ON P0J 1P0",
    "addr:housenumber":"1",
    "addr:postcode":"p0j 1p0",
    "addr:street":"Whitewood Ave",
    "iso:country":"CA",
    "sg:address":"1 Whitewood Ave",
    "sg:city":"New Liskeard",
    "sg:classifiers":[
        {
            "category":"Recreation",
            "subcategory":"Marina",
            "type":"Entertainment"
        }
    ],
    "sg:phone":"+1 705 647 0010",
    "sg:postcode":"P0J 1P0",
    "sg:province":"ON",
    "wof:name":"Waterfront Marina",
    "wof:placetype":"venue"
},
  "geometry": {"coordinates":[-79.67137099999999,47.50872],"type":"Point"}
}