{
  "type": "Feature",
  "properties": {
    "addr:full":"8248 Yonge St Thornhill ON L4J 1W6",
    "addr:housenumber":"8248",
    "addr:postcode":"l4j 1w6",
    "addr:street":"Yonge St",
    "iso:country":"CA",
    "sg:address":"8248 Yonge St",
    "sg:city":"Thornhill",
    "sg:classifiers":[
        {
            "category":"Autos & Motor Vehicles",
            "subcategory":"Automobile Sales",
            "type":"Retail Goods"
        }
    ],
    "sg:phone":"+1 905 762 8886",
    "sg:postcode":"L4J 1W6",
    "sg:province":"ON",
    "sg:tags":[
        "car",
        "dealer"
    ],
    "wof:name":"Daewoo of Thornhill",
    "wof:placetype":"venue"
},
  "geometry": {"coordinates":[-79.427505,43.828571],"type":"Point"}
}