{
  "type": "Feature",
  "properties": {
    "addr:full":"81 Elizabeth St Brighton ON K0K 1H0",
    "addr:housenumber":"81",
    "addr:postcode":"k0k 1h0",
    "addr:street":"Elizabeth St",
    "iso:country":"CA",
    "sg:address":"81 Elizabeth St",
    "sg:city":"Brighton",
    "sg:classifiers":[
        {
            "category":"Restaurant",
            "type":"Food & Drink"
        }
    ],
    "sg:phone":"+1 613 475 4250",
    "sg:postcode":"K0K 1H0",
    "sg:province":"ON",
    "sg:tags":[
        "banquet",
        "rooms"
    ],
    "wof:name":"Lions Community Hall",
    "wof:placetype":"venue"
},
  "geometry": {"coordinates":[-77.7334060669,44.042350769],"type":"Point"}
}