{
  "type": "Feature",
  "properties": {
    "iso:country":"CA",
    "sg:city":"Richmond Hill",
    "sg:classifiers":[
        {
            "category":"Wholesale",
            "subcategory":"Electrical",
            "type":"Manufacturing & Wholesale Goods"
        }
    ],
    "sg:phone":"+1 905 881 8669",
    "sg:postcode":"L4B 3A8",
    "sg:province":"ON",
    "sg:tags":[
        "equipment",
        "electronic",
        "supply"
    ],
    "wof:name":"Excellon Automation",
    "wof:placetype":"venue"
},
  "geometry": {"coordinates":[-79.38646697999999,43.8453369141],"type":"Point"}
}