{
  "type": "Feature",
  "properties": {
    "addr:full":"NW 34 20 28W Russell MB R0J 1W0",
    "addr:housenumber":"20 28w",
    "addr:postcode":"r0j 1w0",
    "addr:street":"Nw 34",
    "iso:country":"CA",
    "sg:address":"NW 34 20 28W",
    "sg:city":"Russell",
    "sg:classifiers":[
        {
            "category":"Education",
            "subcategory":"Special Training",
            "type":"Public Place"
        }
    ],
    "sg:phone":"+1 204 773 2707",
    "sg:postcode":"R0J 1W0",
    "sg:province":"MB",
    "sg:tags":[
        "aircraft",
        "instruction",
        "flight"
    ],
    "wof:name":"Russell Flying Club",
    "wof:placetype":"venue"
},
  "geometry": {"coordinates":[-101.288269,50.773129],"type":"Point"}
}