{
  "type": "Feature",
  "properties": {
    "addr:full":"3509 Carrington Rd Westbank BC V4T 2E6",
    "addr:housenumber":"3509",
    "addr:postcode":"v4t 2e6",
    "addr:street":"Carrington Rd",
    "iso:country":"CA",
    "sg:address":"3509 Carrington Rd",
    "sg:city":"Westbank",
    "sg:classifiers":[
        {
            "category":"Sports & Exercise",
            "subcategory":"Golf",
            "type":"Entertainment"
        }
    ],
    "sg:phone":"+1 250 768 0080",
    "sg:postcode":"V4T 2E6",
    "sg:province":"BC",
    "sg:tags":[
        "course"
    ],
    "wof:name":"Vintage Hills Golf Course",
    "wof:placetype":"venue"
},
  "geometry": {"coordinates":[-119.609542847,49.83776474],"type":"Point"}
}