{
  "type": "Feature",
  "properties": {
    "addr:full":"1708 Jane St York ON M9N 2S4",
    "addr:housenumber":"1708",
    "addr:postcode":"m9n 2s4",
    "addr:street":"Jane St",
    "iso:country":"CA",
    "sg:address":"1708 Jane St",
    "sg:city":"York",
    "sg:classifiers":[
        {
            "category":"Food & Beverages",
            "subcategory":"Groceries & Convenience Stores",
            "type":"Retail Goods"
        }
    ],
    "sg:phone":"+1 416 240 0039",
    "sg:postcode":"M9N 2S4",
    "sg:province":"ON",
    "sg:tags":[
        "grocer"
    ],
    "wof:name":"Kajanth Grocery",
    "wof:placetype":"venue"
},
  "geometry": {"coordinates":[-79.5041503906,43.7035331726],"type":"Point"}
}