{
  "type": "Feature",
  "properties": {
    "iso:country":"CA",
    "sg:address":"28 Av Sauriol",
    "sg:city":"Laval",
    "sg:classifiers":[
        {
            "category":"Social Services",
            "subcategory":"Child Care",
            "type":"Services"
        }
    ],
    "sg:phone":"+1 450 681 3540",
    "sg:postcode":"H7N 3A4",
    "sg:province":"QC",
    "sg:tags":[
        "kindergarten",
        "academic",
        "school"
    ],
    "wof:name":"Pre-Maternelle Colette Lefort",
    "wof:placetype":"venue"
},
  "geometry": {"coordinates":[-73.71361541749999,45.5445404053],"type":"Point"}
}