{
  "type": "Feature",
  "properties": {
    "addr:full":"RR 2 STN Main Morinville AB T8R 1P5",
    "addr:postcode":"t8r 1p5",
    "addr:street":"Rr 2 Stn Main",
    "iso:country":"CA",
    "sg:address":"RR 2 STN Main",
    "sg:city":"Morinville",
    "sg:classifiers":[
        {
            "category":"Building & Trades",
            "subcategory":"Construction",
            "type":"Services"
        }
    ],
    "sg:phone":"+1 780 939 7176",
    "sg:postcode":"T8R 1P5",
    "sg:province":"AB",
    "sg:tags":[
        "boring",
        "drilling",
        "contractor"
    ],
    "wof:name":"Sun-Alta Drilling Ltd",
    "wof:placetype":"venue"
},
  "geometry": {"coordinates":[-113.648208618,53.8000183105],"type":"Point"}
}