{
  "type": "Feature",
  "properties": {
    "addr:full":"3030 223 St Bellevue AB T0K 0C0",
    "addr:housenumber":"3030",
    "addr:postcode":"t0k 0c0",
    "addr:street":"223 St",
    "iso:country":"CA",
    "sg:address":"3030 223 St",
    "sg:city":"Bellevue",
    "sg:classifiers":[
        {
            "category":"Retail",
            "subcategory":"Repair Shop",
            "type":"Services"
        }
    ],
    "sg:phone":"+1 403 564 4348",
    "sg:postcode":"T0K 0C0",
    "sg:province":"AB",
    "sg:tags":[
        "upholstery",
        "fabric",
        "upholsterer"
    ],
    "wof:name":"D & L Upholstery & Fabrics",
    "wof:placetype":"venue"
},
  "geometry": {"coordinates":[-114.356674,49.574436],"type":"Point"}
}