{
  "type": "Feature",
  "properties": {
    "iso:country":"CA",
    "sg:address":"2895 Saint Paul Ave",
    "sg:city":"Niagara Falls",
    "sg:classifiers":[
        {
            "category":"Shopping",
            "subcategory":"Clothing, Apparel, & Fashions",
            "type":"Retail Goods"
        }
    ],
    "sg:phone":"+1 905 374 7455",
    "sg:postcode":"L2J 2L3",
    "sg:province":"ON",
    "sg:tags":[
        "theatrical",
        "costume"
    ],
    "wof:name":"Act 1 Theatrical Supplies",
    "wof:placetype":"venue"
},
  "geometry": {"coordinates":[-79.100112915,43.1304779053],"type":"Point"}
}