{
  "type": "Feature",
  "properties": {
    "addr:full":"Kitchener ON N2R 1L6",
    "addr:postcode":"n2r 1l6",
    "iso:country":"CA",
    "sg:city":"Kitchener",
    "sg:classifiers":[
        {
            "category":"Shopping",
            "subcategory":"Computers & Home Electronics",
            "type":"Retail Goods"
        }
    ],
    "sg:phone":"+1 519 893 7777",
    "sg:postcode":"N2R 1L6",
    "sg:province":"ON",
    "sg:tags":[
        "software"
    ],
    "wof:name":"Bold Point Software",
    "wof:placetype":"venue"
},
  "geometry": {"coordinates":[-80.453728,43.397732],"type":"Point"}
}