{
  "type": "Feature",
  "properties": {
    "addr:full":"110 Rue Notre-Dame Repentigny QC J6A 2P3",
    "addr:housenumber":"110",
    "addr:postcode":"j6a 2p3",
    "addr:street":"Rue Notre-Dame",
    "iso:country":"CA",
    "sg:address":"110 Rue Notre-Dame",
    "sg:city":"Repentigny",
    "sg:classifiers":[
        {
            "category":"Autos & Motor Vehicles",
            "subcategory":"Automobile Sales",
            "type":"Retail Goods"
        }
    ],
    "sg:phone":"+1 514 875 1975",
    "sg:postcode":"J6A 2P3",
    "sg:province":"QC",
    "sg:tags":[
        "car",
        "dealer"
    ],
    "wof:name":"Honda Lallier Automobile Inc",
    "wof:placetype":"venue"
},
  "geometry": {"coordinates":[-73.472672,45.715588],"type":"Point"}
}