{
  "type": "Feature",
  "properties": {
    "addr:full":"99 Mann Ave Ottawa ON K1N 5A4",
    "addr:housenumber":"99",
    "addr:postcode":"k1n 5a4",
    "addr:street":"Mann Ave",
    "iso:country":"CA",
    "sg:address":"99 Mann Ave",
    "sg:city":"Ottawa",
    "sg:classifiers":[
        {
            "category":"Retail",
            "subcategory":"Laundry & Dry Cleaning",
            "type":"Services"
        }
    ],
    "sg:phone":"+1 613 565 2255",
    "sg:postcode":"K1N 5A4",
    "sg:province":"ON",
    "sg:tags":[
        "cleaners"
    ],
    "wof:name":"Sandy Hill Speed Queen",
    "wof:placetype":"venue"
},
  "geometry": {"coordinates":[-75.6725845337,45.421005249],"type":"Point"}
}