{
  "type": "Feature",
  "properties": {
    "iso:country":"CA",
    "sg:address":"965 Syscon Rd",
    "sg:city":"Burlington",
    "sg:classifiers":[
        {
            "category":"Manufacturing",
            "subcategory":"Furniture",
            "type":"Manufacturing & Wholesale Goods"
        }
    ],
    "sg:phone":"+1 905 333 0300",
    "sg:postcode":"L7L 5S3",
    "sg:province":"ON",
    "sg:tags":[
        "partition"
    ],
    "wof:name":"Hadrian Manufacturing Inc",
    "wof:placetype":"venue"
},
  "geometry": {"coordinates":[-79.7570571899,43.3924560547],"type":"Point"}
}