{
  "type": "Feature",
  "properties": {
    "addr:full":"9395 Rue Main Richibucto NB E4W 4B6",
    "addr:housenumber":"9395",
    "addr:postcode":"e4w 4b6",
    "addr:street":"Rue Main",
    "iso:country":"CA",
    "sg:address":"9395 Rue Main",
    "sg:city":"Richibucto",
    "sg:classifiers":[
        {
            "category":"Food & Beverages",
            "subcategory":"Groceries & Convenience Stores",
            "type":"Retail Goods"
        }
    ],
    "sg:phone":"+1 506 523 9064",
    "sg:postcode":"E4W 4B6",
    "sg:province":"NB",
    "wof:name":"Richibucto Convenience Str Ltd",
    "wof:placetype":"venue"
},
  "geometry": {"coordinates":[-64.861786,46.682938],"type":"Point"}
}