{
  "type": "Feature",
  "properties": {
    "addr:full":"1004 Prospect Rd Goodwood NS B3T 1P4",
    "addr:housenumber":"1004",
    "addr:postcode":"b3t 1p4",
    "addr:street":"Prospect Rd",
    "iso:country":"CA",
    "sg:address":"1004 Prospect Rd",
    "sg:city":"Goodwood",
    "sg:classifiers":[
        {
            "category":"Retail",
            "subcategory":"Auto Repair",
            "type":"Services"
        }
    ],
    "sg:phone":"+1 902 876 8306",
    "sg:postcode":"B3T 1P4",
    "sg:province":"NS",
    "sg:tags":[
        "body",
        "automobile",
        "painting"
    ],
    "wof:name":"Leonard's Auto Salvage",
    "wof:placetype":"venue"
},
  "geometry": {"coordinates":[-63.687458,44.598438],"type":"Point"}
}