{
  "type": "Feature",
  "properties": {
    "addr:full":"871 Boul Saint-Joseph Roberval QC G8H 2L8",
    "addr:housenumber":"871",
    "addr:postcode":"g8h 2l8",
    "addr:street":"Boul Saint-Joseph",
    "iso:country":"CA",
    "sg:address":"871 Boul Saint-Joseph",
    "sg:city":"Roberval",
    "sg:classifiers":[
        {
            "category":"Health Services",
            "subcategory":"Optometrist",
            "type":"Services"
        }
    ],
    "sg:phone":"+1 418 275 5090",
    "sg:postcode":"G8H 2L8",
    "sg:province":"QC",
    "wof:name":"Azur Optometristes",
    "wof:placetype":"venue"
},
  "geometry": {"coordinates":[-72.22198486329999,48.5189323425],"type":"Point"}
}