{
  "type": "Feature",
  "properties": {
    "addr:full":"Cartwright MB R0K 0L0",
    "addr:postcode":"r0k 0l0",
    "iso:country":"CA",
    "sg:city":"Cartwright",
    "sg:classifiers":[
        {
            "category":"Education",
            "subcategory":"Library",
            "type":"Public Place"
        }
    ],
    "sg:phone":"+1 204 529 2261",
    "sg:postcode":"R0K 0L0",
    "sg:province":"MB",
    "wof:name":"Lakeland Regional Library",
    "wof:placetype":"venue"
},
  "geometry": {"coordinates":[-99.3453674316,49.0949668884],"type":"Point"}
}