{
  "type": "Feature",
  "properties": {
    "addr:full":"1060 Alberni St Vancouver BC V6E 4K2",
    "addr:housenumber":"1060",
    "addr:postcode":"v6e 4k2",
    "addr:street":"Alberni St",
    "iso:country":"CA",
    "sg:address":"1060 Alberni St",
    "sg:city":"Vancouver",
    "sg:classifiers":[
        {
            "category":"Real Estate",
            "subcategory":"Real Estate Operator",
            "type":"Services"
        }
    ],
    "sg:phone":"+1 604 682 5224",
    "sg:postcode":"V6E 4K2",
    "sg:province":"BC",
    "sg:tags":[
        "apartment"
    ],
    "wof:name":"Carlyle Apartments",
    "wof:placetype":"venue"
},
  "geometry": {"coordinates":[-123.123169,49.284679],"type":"Point"}
}