{
  "type": "Feature",
  "properties": {
    "iso:country":"CA",
    "sg:city":"Ottawa",
    "sg:classifiers":[
        {
            "category":"Professional",
            "subcategory":"Management & Consulting",
            "type":"Services"
        }
    ],
    "sg:phone":"+1 613 565 5888",
    "sg:postcode":"K2P 2H7",
    "sg:province":"ON",
    "sg:tags":[
        "marketing",
        "consultant"
    ],
    "wof:name":"Generation Promotions & Design",
    "wof:placetype":"venue"
},
  "geometry": {"coordinates":[-75.6966552734,45.4160346985],"type":"Point"}
}