{
  "type": "Feature",
  "properties": {
    "addr:full":"582 Front St Watford ON N0M 2S0",
    "addr:housenumber":"582",
    "addr:postcode":"n0m 2s0",
    "addr:street":"Front St",
    "iso:country":"CA",
    "sg:address":"582 Front St",
    "sg:city":"Watford",
    "sg:classifiers":[
        {
            "category":"Home & Garden",
            "subcategory":"Garden Supply",
            "type":"Retail Goods"
        }
    ],
    "sg:phone":"+1 519 876 2915",
    "sg:postcode":"N0M 2S0",
    "sg:province":"ON",
    "sg:tags":[
        "lawn",
        "rental",
        "mower"
    ],
    "wof:name":"Kernohan Rental",
    "wof:placetype":"venue"
},
  "geometry": {"coordinates":[-81.8770599365,42.9461402893],"type":"Point"}
}