{
  "type": "Feature",
  "properties": {
    "addr:full":"22 Head St Dundas ON L9H 3H3",
    "addr:housenumber":"22",
    "addr:postcode":"l9h 3h3",
    "addr:street":"Head St",
    "iso:country":"CA",
    "sg:address":"22 Head St",
    "sg:city":"Dundas",
    "sg:classifiers":[
        {
            "category":"Home & Garden",
            "subcategory":"Carpets & Floor Coverings",
            "type":"Retail Goods"
        }
    ],
    "sg:phone":"+1 905 627 2212",
    "sg:postcode":"L9H 3H3",
    "sg:province":"ON",
    "sg:tags":[
        "material"
    ],
    "wof:name":"I & S Custom Flooring Inc",
    "wof:placetype":"venue"
},
  "geometry": {"coordinates":[-79.974174,43.269985],"type":"Point"}
}