{
  "type": "Feature",
  "properties": {
    "addr:full":"4009 Rue Hochelaga Montreal QC H1W 1K4",
    "addr:housenumber":"4009",
    "addr:postcode":"h1w 1k4",
    "addr:street":"Rue Hochelaga",
    "iso:country":"CA",
    "sg:address":"4009 Rue Hochelaga",
    "sg:city":"Montreal",
    "sg:classifiers":[
        {
            "category":"Health Services",
            "subcategory":"Medical Lab",
            "type":"Services"
        }
    ],
    "sg:phone":"+1 514 894 7847",
    "sg:postcode":"H1W 1K4",
    "sg:province":"QC",
    "wof:name":"A Maurice Dufresne Dntrlgst",
    "wof:placetype":"venue"
},
  "geometry": {"coordinates":[-73.54875946040001,45.5518913269],"type":"Point"}
}