{
  "type": "Feature",
  "properties": {
    "iso:country":"CA",
    "sg:city":"Scarborough",
    "sg:classifiers":[
        {
            "category":"Wholesale",
            "subcategory":"Electrical",
            "type":"Manufacturing & Wholesale Goods"
        }
    ],
    "sg:phone":"+1 416 284 7613",
    "sg:postcode":"M1E 5C7",
    "sg:province":"ON",
    "sg:tags":[
        "alarm",
        "burglar",
        "system"
    ],
    "wof:name":"AAA Installations",
    "wof:placetype":"venue"
},
  "geometry": {"coordinates":[-79.166275,43.764896],"type":"Point"}
}