{
  "type": "Feature",
  "properties": {
    "addr:full":"1455 Queen St W Toronto ON M6R 1A1",
    "addr:housenumber":"1455",
    "addr:postcode":"m6r 1a1",
    "addr:street":"Queen St W",
    "iso:country":"CA",
    "sg:address":"1455 Queen St W",
    "sg:city":"Toronto",
    "sg:classifiers":[
        {
            "category":"Food & Beverages",
            "subcategory":"Groceries & Convenience Stores",
            "type":"Retail Goods"
        }
    ],
    "sg:phone":"+1 416 534 7770",
    "sg:postcode":"M6R 1A1",
    "sg:province":"ON",
    "sg:tags":[
        "grocer"
    ],
    "wof:name":"Kana Super Marker",
    "wof:placetype":"venue"
},
  "geometry": {"coordinates":[-79.4383926392,43.6401176453],"type":"Point"}
}