{
  "type": "Feature",
  "properties": {
    "addr:full":"155 Richmond Blvd Napanee ON K7R 3Z9",
    "addr:housenumber":"155",
    "addr:postcode":"k7r 3z9",
    "addr:street":"Richmond Blvd",
    "iso:country":"CA",
    "sg:address":"155 Richmond Blvd",
    "sg:city":"Napanee",
    "sg:classifiers":[
        {
            "category":"Autos & Motor Vehicles",
            "subcategory":"Auto Supplies",
            "type":"Retail Goods"
        }
    ],
    "sg:phone":"+1 613 354 9782",
    "sg:postcode":"K7R 3Z9",
    "sg:province":"ON",
    "sg:tags":[
        "automobile",
        "parts"
    ],
    "wof:name":"Napa Auto Parts",
    "wof:placetype":"venue"
},
  "geometry": {"coordinates":[-76.95375799999999,44.264122],"type":"Point"}
}