{
  "type": "Feature",
  "properties": {
    "addr:full":"1904 Powell St Vancouver BC V5L 1J3",
    "addr:housenumber":"1904",
    "addr:postcode":"v5l 1j3",
    "addr:street":"Powell St",
    "iso:country":"CA",
    "sg:address":"1904 Powell St",
    "sg:city":"Vancouver",
    "sg:classifiers":[
        {
            "category":"Manufacturing",
            "subcategory":"Food",
            "type":"Manufacturing & Wholesale Goods"
        }
    ],
    "sg:phone":"+1 604 254 0161",
    "sg:postcode":"V5L 1J3",
    "sg:province":"BC",
    "sg:tags":[
        "tea",
        "coffee",
        "product"
    ],
    "wof:name":"J J Bean the Coffee Roaster",
    "wof:placetype":"venue"
},
  "geometry": {"coordinates":[-123.06513200000001,49.284756],"type":"Point"}
}