{
  "type": "Feature",
  "properties": {
    "addr:full":"17 Noble St Toronto ON M6K 2C7",
    "addr:housenumber":"17",
    "addr:postcode":"m6k 2c7",
    "addr:street":"Noble St",
    "iso:country":"CA",
    "sg:address":"17 Noble St",
    "sg:city":"Toronto",
    "sg:classifiers":[
        {
            "category":"Wholesale",
            "subcategory":"Apparel",
            "type":"Manufacturing & Wholesale Goods"
        }
    ],
    "sg:phone":"+1 416 504 4299",
    "sg:postcode":"M6K 2C7",
    "sg:province":"ON",
    "wof:name":"Duet Designs",
    "wof:placetype":"venue"
},
  "geometry": {"coordinates":[-79.43023700000001,43.642754],"type":"Point"}
}