{
  "type": "Feature",
  "properties": {
    "addr:full":"Saint-Leonard QC H1S 1V7",
    "addr:postcode":"h1s 1v7",
    "iso:country":"CA",
    "sg:city":"Saint-Leonard",
    "sg:classifiers":[
        {
            "category":"Restaurant",
            "type":"Food & Drink"
        }
    ],
    "sg:phone":"+1 514 259 2228",
    "sg:postcode":"H1S 1V7",
    "sg:province":"QC",
    "wof:name":"Les Taouk Express",
    "wof:placetype":"venue"
},
  "geometry": {"coordinates":[-73.57231899999999,45.591599],"type":"Point"}
}