{
  "type": "Feature",
  "properties": {
    "addr:full":"Halifax NS B3L 4N9",
    "addr:postcode":"b3l 4n9",
    "iso:country":"CA",
    "sg:city":"Halifax",
    "sg:classifiers":[
        {
            "category":"Shopping",
            "subcategory":"Clothing, Apparel, & Fashions",
            "type":"Retail Goods"
        }
    ],
    "sg:phone":"+1 902 454 4489",
    "sg:postcode":"B3L 4N9",
    "sg:province":"NS",
    "wof:name":"Northern Reflections",
    "wof:placetype":"venue"
},
  "geometry": {"coordinates":[-63.619663,44.647785],"type":"Point"}
}