{
  "type": "Feature",
  "properties": {
    "iso:country":"CA",
    "sg:address":"10 2nd St",
    "sg:city":"Tompkins",
    "sg:classifiers":[
        {
            "category":"Restaurant",
            "type":"Food & Drink"
        }
    ],
    "sg:phone":"+1 306 622 2250",
    "sg:postcode":"S0N 2S0",
    "sg:province":"SK",
    "sg:tags":[
        "tea",
        "rooms"
    ],
    "wof:name":"Buffalo Bean Tea House",
    "wof:placetype":"venue"
},
  "geometry": {"coordinates":[-108.801384,50.063721],"type":"Point"}
}