{
  "type": "Feature",
  "properties": {
    "addr:full":"7263 18 St NW Edmonton AB T6P 1N1",
    "addr:housenumber":"7263",
    "addr:postcode":"t6p 1n1",
    "addr:street":"18 St Nw",
    "iso:country":"CA",
    "sg:address":"7263 18 St NW",
    "sg:city":"Edmonton",
    "sg:classifiers":[
        {
            "category":"Wholesale",
            "subcategory":"Hardware",
            "type":"Manufacturing & Wholesale Goods"
        }
    ],
    "sg:phone":"+1 780 440 1997",
    "sg:postcode":"T6P 1N1",
    "sg:province":"AB",
    "sg:tags":[
        "fastener"
    ],
    "wof:name":"Strathcona Manufacturing Inc",
    "wof:placetype":"venue"
},
  "geometry": {"coordinates":[-113.371529,53.508213],"type":"Point"}
}