{
  "type": "Feature",
  "properties": {
    "iso:country":"CA",
    "sg:city":"Ottawa",
    "sg:classifiers":[
        {
            "category":"Personal",
            "subcategory":"Beauty Salon",
            "type":"Services"
        }
    ],
    "sg:phone":"+1 613 234 0600",
    "sg:postcode":"K1P 6C9",
    "sg:province":"ON",
    "wof:name":"Studio 240 Hairstylists",
    "wof:placetype":"venue"
},
  "geometry": {"coordinates":[-75.701981,45.42075],"type":"Point"}
}