{
  "type": "Feature",
  "properties": {
    "addr:full":"139 Av Dresden Mont-Royal QC H3P 3K1",
    "addr:postcode":"h3p 3k1",
    "addr:street":"139 Av Dresden",
    "iso:country":"CA",
    "sg:address":"139 Av Dresden",
    "sg:city":"Mont-Royal",
    "sg:classifiers":[
        {
            "category":"Professional",
            "subcategory":"Computer Services",
            "type":"Services"
        }
    ],
    "sg:phone":"+1 514 340 1414",
    "sg:postcode":"H3P 3K1",
    "sg:province":"QC",
    "sg:tags":[
        "information",
        "system",
        "consultant"
    ],
    "wof:name":"Softtarget Inc",
    "wof:placetype":"venue"
},
  "geometry": {"coordinates":[-73.630409,45.516987],"type":"Point"}
}