{
  "type": "Feature",
  "properties": {
    "iso:country":"CA",
    "sg:address":"45816 Yale Rd",
    "sg:city":"Chilliwack",
    "sg:classifiers":[
        {
            "category":"Restaurant",
            "type":"Food & Drink"
        }
    ],
    "sg:phone":"+1 604 795 5911",
    "sg:postcode":"V2P 2N7",
    "sg:province":"BC",
    "wof:name":"Mc Donald's",
    "wof:placetype":"venue"
},
  "geometry": {"coordinates":[-121.958839416,49.1637039185],"type":"Point"}
}