{
  "type": "Feature",
  "properties": {
    "addr:full":"1425 Dundas St E # 17 Mississauga ON L4X 2W4",
    "addr:housenumber":"1425",
    "addr:postcode":"l4x 2w4",
    "addr:street":"Dundas St E # 17",
    "iso:country":"CA",
    "sg:address":"1425 Dundas St E # 17",
    "sg:city":"Mississauga",
    "sg:classifiers":[
        {
            "category":"Government",
            "subcategory":"Office",
            "type":"Public Place"
        }
    ],
    "sg:phone":"+1 905 238 1751",
    "sg:postcode":"L4X 2W4",
    "sg:province":"ON",
    "wof:name":"Defaria, Carl",
    "wof:placetype":"venue"
},
  "geometry": {"coordinates":[-79.583122,43.610168],"type":"Point"}
}