{
  "type": "Feature",
  "properties": {
    "addr:full":"531 57th Ave W Vancouver BC V6P 1R8",
    "addr:housenumber":"531",
    "addr:postcode":"v6p 1r8",
    "addr:street":"57Th Ave W",
    "iso:country":"CA",
    "sg:address":"531 57th Ave W",
    "sg:city":"Vancouver",
    "sg:classifiers":[
        {
            "category":"Banks & Credit Unions",
            "subcategory":"Bank",
            "type":"Services"
        }
    ],
    "sg:phone":"+1 604 665 0555",
    "sg:postcode":"V6P 1R8",
    "sg:province":"BC",
    "wof:name":"Royal Bank Financial Group",
    "wof:placetype":"venue"
},
  "geometry": {"coordinates":[-123.117660523,49.2191925049],"type":"Point"}
}