{
  "type": "Feature",
  "properties": {
    "addr:full":"1859 Scarth St Regina SK S4P 2G9",
    "addr:housenumber":"1859",
    "addr:postcode":"s4p 2g9",
    "addr:street":"Scarth St",
    "iso:country":"CA",
    "sg:address":"1859 Scarth St",
    "sg:city":"Regina",
    "sg:classifiers":[
        {
            "category":"Shopping",
            "subcategory":"News",
            "type":"Retail Goods"
        }
    ],
    "sg:phone":"+1 306 757 7902",
    "sg:postcode":"S4P 2G9",
    "sg:province":"SK",
    "sg:tags":[
        "magazine"
    ],
    "wof:name":"Book End Smoke & Novelty Shop",
    "wof:placetype":"venue"
},
  "geometry": {"coordinates":[-104.610671997,50.4495239258],"type":"Point"}
}