{
  "type": "Feature",
  "properties": {
    "iso:country":"CA",
    "sg:address":"7180 12 St SE",
    "sg:city":"Calgary",
    "sg:classifiers":[
        {
            "category":"Home & Garden",
            "subcategory":"Furniture",
            "type":"Retail Goods"
        }
    ],
    "sg:phone":"+1 403 259 5000",
    "sg:postcode":"T2H 2Y4",
    "sg:province":"AB",
    "wof:name":"United Furniture Warehouse",
    "wof:placetype":"venue"
},
  "geometry": {"coordinates":[-114.036819,50.990253],"type":"Point"}
}