{
  "type": "Feature",
  "properties": {
    "addr:full":"65 Rue DE Castelnau O Montreal QC H2R 2W3",
    "addr:housenumber":"65",
    "addr:postcode":"h2r 2w3",
    "addr:street":"Rue De Castelnau O",
    "iso:country":"CA",
    "sg:address":"65 Rue DE Castelnau O",
    "sg:city":"Montreal",
    "sg:classifiers":[
        {
            "category":"Freight",
            "type":"Transportation"
        }
    ],
    "sg:phone":"+1 514 276 6938",
    "sg:postcode":"H2R 2W3",
    "sg:province":"QC",
    "sg:tags":[
        "trucking"
    ],
    "wof:name":"Messageries Jpc Enr",
    "wof:placetype":"venue"
},
  "geometry": {"coordinates":[-73.6193389893,45.5362052917],"type":"Point"}
}