{
  "type": "Feature",
  "properties": {
    "iso:country":"CA",
    "sg:address":"8372 Rue Bougainville",
    "sg:city":"Montreal",
    "sg:classifiers":[
        {
            "category":"Professional",
            "subcategory":"Accounting & Tax Preparation",
            "type":"Services"
        }
    ],
    "sg:phone":"+1 514 735 3775",
    "sg:postcode":"H4P 2G1",
    "sg:province":"QC",
    "sg:tags":[
        "accountant"
    ],
    "wof:name":"Rabinovitch Shemie Luciano",
    "wof:placetype":"venue"
},
  "geometry": {"coordinates":[-73.66175842289999,45.5013999939],"type":"Point"}
}