{
  "type": "Feature",
  "properties": {
    "addr:full":"605 33E Rue Saint-Georges QC G5Y 7M8",
    "addr:housenumber":"605",
    "addr:postcode":"g5y 7m8",
    "addr:street":"33E Rue",
    "iso:country":"CA",
    "sg:address":"605 33E Rue",
    "sg:city":"Saint-Georges",
    "sg:classifiers":[
        {
            "category":"Personal",
            "subcategory":"Beauty Salon",
            "type":"Services"
        }
    ],
    "sg:phone":"+1 418 228 9495",
    "sg:postcode":"G5Y 7M8",
    "sg:province":"QC",
    "wof:name":"Coiffure Bruno",
    "wof:placetype":"venue"
},
  "geometry": {"coordinates":[-70.6682891846,46.1086349487],"type":"Point"}
}