{
  "type": "Feature",
  "properties": {
    "addr:full":"652 Baker St Nelson BC V1L 4J4",
    "addr:housenumber":"652",
    "addr:postcode":"bc v1l 4j4",
    "addr:street":"Baker St",
    "iso:country":"CA",
    "sg:address":"652 Baker St",
    "sg:city":"Nelson",
    "sg:classifiers":[
        {
            "category":"Restaurant",
            "type":"Food & Drink"
        }
    ],
    "sg:phone":"+1 250 352 2912",
    "sg:postcode":"V1L 4J4",
    "sg:province":"BC",
    "wof:name":"King's Family Restaurant",
    "wof:placetype":"venue"
},
  "geometry": {"coordinates":[-117.29179382300001,49.4926528931],"type":"Point"}
}