{
  "type": "Feature",
  "properties": {
    "addr:full":"381 Sackville Dr Lower Sackville NS B4C 2R9",
    "addr:housenumber":"381",
    "addr:postcode":"b4c 2r9",
    "addr:street":"Sackville Dr",
    "iso:country":"CA",
    "sg:address":"381 Sackville Dr",
    "sg:city":"Lower Sackville",
    "sg:classifiers":[
        {
            "category":"Retail",
            "subcategory":"Auto Rental",
            "type":"Services"
        }
    ],
    "sg:phone":"+1 902 865 9483",
    "sg:postcode":"B4C 2R9",
    "sg:province":"NS",
    "sg:tags":[
        "renting",
        "truck",
        "leasing"
    ],
    "wof:name":"U-Haul CO",
    "wof:placetype":"venue"
},
  "geometry": {"coordinates":[-63.6753768921,44.7637748718],"type":"Point"}
}