{
  "type": "Feature",
  "properties": {
    "addr:full":"3275 Rue Ontario E Montreal QC H1W 1P5",
    "addr:housenumber":"3275",
    "addr:postcode":"h1w 1p5",
    "addr:street":"Rue Ontario E",
    "iso:country":"CA",
    "sg:address":"3275 Rue Ontario E",
    "sg:city":"Montreal",
    "sg:classifiers":[
        {
            "category":"Personal",
            "subcategory":"Beauty Salon",
            "type":"Services"
        }
    ],
    "sg:phone":"+1 514 523 0002",
    "sg:postcode":"H1W 1P5",
    "sg:province":"QC",
    "wof:name":"Coiffure Economique",
    "wof:placetype":"venue"
},
  "geometry": {"coordinates":[-73.546829,45.541992],"type":"Point"}
}