{
  "type": "Feature",
  "properties": {
    "addr:full":"206 Mackenzie Ave Revelstoke BC V0E 2S0",
    "addr:housenumber":"206",
    "addr:postcode":"v0e 2s0",
    "addr:street":"Mackenzie Ave",
    "iso:country":"CA",
    "sg:address":"206 Mackenzie Ave",
    "sg:city":"Revelstoke",
    "sg:classifiers":[
        {
            "category":"Restaurant",
            "type":"Food & Drink"
        }
    ],
    "sg:phone":"+1 250 837 6743",
    "sg:postcode":"V0E 2S0",
    "sg:province":"BC",
    "wof:name":"Claudio's Pizza & Pasta",
    "wof:placetype":"venue"
},
  "geometry": {"coordinates":[-118.195274353,50.9985847473],"type":"Point"}
}