{
  "type": "Feature",
  "properties": {
    "addr:full":"Oakville ON L6J 5Z7",
    "addr:postcode":"l6j 5z7",
    "iso:country":"CA",
    "sg:city":"Oakville",
    "sg:classifiers":[
        {
            "category":"Health Services",
            "subcategory":"Doctor",
            "type":"Services"
        }
    ],
    "sg:phone":"+1 905 842 2355",
    "sg:postcode":"L6J 5Z7",
    "sg:province":"ON",
    "sg:tags":[
        "dentist"
    ],
    "wof:name":"Bell, Ron DDS",
    "wof:placetype":"venue"
},
  "geometry": {"coordinates":[-79.689751,43.453926],"type":"Point"}
}