{
  "type": "Feature",
  "properties": {
    "addr:full":"Milton ON L9T 5B7",
    "addr:postcode":"l9t 5b7",
    "iso:country":"CA",
    "sg:city":"Milton",
    "sg:classifiers":[
        {
            "category":"Wholesale",
            "subcategory":"Electrical",
            "type":"Manufacturing & Wholesale Goods"
        }
    ],
    "sg:phone":"+1 905 875 2985",
    "sg:postcode":"L9T 5B7",
    "sg:province":"ON",
    "sg:tags":[
        "electronic",
        "representative"
    ],
    "wof:name":"Seltech Electronics",
    "wof:placetype":"venue"
},
  "geometry": {"coordinates":[-79.8786773682,43.5013046265],"type":"Point"}
}