{
  "type": "Feature",
  "properties": {
    "iso:country":"CA",
    "sg:address":"1000 Silvertip Trail",
    "sg:city":"Canmore",
    "sg:classifiers":[
        {
            "category":"Sports & Exercise",
            "subcategory":"Golf",
            "type":"Entertainment"
        }
    ],
    "sg:phone":"+1 403 678 1600",
    "sg:postcode":"T1W 3J4",
    "sg:province":"AB",
    "sg:tags":[
        "course"
    ],
    "wof:name":"Silvertip",
    "wof:placetype":"venue"
},
  "geometry": {"coordinates":[-115.338882446,51.101776123],"type":"Point"}
}