{
  "type": "Feature",
  "properties": {
    "addr:full":"8100 Rue DE Marseille Montreal QC H1L 1P3",
    "addr:housenumber":"8100",
    "addr:postcode":"h1l 1p3",
    "addr:street":"Rue De Marseille",
    "iso:country":"CA",
    "sg:address":"8100 Rue DE Marseille",
    "sg:city":"Montreal",
    "sg:classifiers":[
        {
            "category":"Education",
            "subcategory":"School",
            "type":"Public Place"
        }
    ],
    "sg:phone":"+1 514 596 5044",
    "sg:postcode":"H1L 1P3",
    "sg:province":"QC",
    "wof:name":"Ecole Ste-Louise-DE-Marillac",
    "wof:placetype":"venue"
},
  "geometry": {"coordinates":[-73.529586792,45.5969581604],"type":"Point"}
}