{
  "type": "Feature",
  "properties": {
    "addr:full":"1901 Lasalle Blvd Sudbury ON P3A 2A3",
    "addr:housenumber":"1901",
    "addr:postcode":"p3a 2a3",
    "addr:street":"Lasalle Blvd",
    "iso:country":"CA",
    "sg:address":"1901 Lasalle Blvd",
    "sg:city":"Sudbury",
    "sg:classifiers":[
        {
            "category":"Real Estate",
            "subcategory":"Real Estate Agent",
            "type":"Services"
        }
    ],
    "sg:phone":"+1 705 525 4211",
    "sg:postcode":"P3A 2A3",
    "sg:province":"ON",
    "sg:tags":[
        "desk",
        "space"
    ],
    "wof:name":"Symsyl Business Ctr",
    "wof:placetype":"venue"
},
  "geometry": {"coordinates":[-80.928185,46.521927],"type":"Point"}
}