{
  "type": "Feature",
  "properties": {
    "iso:country":"CA",
    "sg:city":"Whitby",
    "sg:classifiers":[
        {
            "category":"Health Services",
            "subcategory":"Doctor",
            "type":"Services"
        }
    ],
    "sg:phone":"+1 905 725 9530",
    "sg:postcode":"L1N 8Y8",
    "sg:province":"ON",
    "sg:tags":[
        "dentist"
    ],
    "wof:name":"Sperber, Ronald L DDS",
    "wof:placetype":"venue"
},
  "geometry": {"coordinates":[-78.912209,43.886776],"type":"Point"}
}