{
  "type": "Feature",
  "properties": {
    "addr:full":"283 Chaplin Cres Toronto ON M5P 1B1",
    "addr:housenumber":"283",
    "addr:postcode":"m5p 1b1",
    "addr:street":"Chaplin Cres",
    "iso:country":"CA",
    "sg:address":"283 Chaplin Cres",
    "sg:city":"Toronto",
    "sg:classifiers":[
        {
            "category":"Wholesale",
            "subcategory":"Farm Supplies",
            "type":"Manufacturing & Wholesale Goods"
        }
    ],
    "sg:phone":"+1 416 781 6100",
    "sg:postcode":"M5P 1B1",
    "sg:province":"ON",
    "sg:tags":[
        "product",
        "health",
        "animal"
    ],
    "wof:name":"Apperon Inc Glutasyn",
    "wof:placetype":"venue"
},
  "geometry": {"coordinates":[-79.415451,43.701805],"type":"Point"}
}