{
  "type": "Feature",
  "properties": {
    "addr:full":"5567 Boul Saint-Michel Montreal QC H1Y 2C9",
    "addr:housenumber":"5567",
    "addr:postcode":"h1y 2c9",
    "addr:street":"Boul Saint-Michel",
    "iso:country":"CA",
    "sg:address":"5567 Boul Saint-Michel",
    "sg:city":"Montreal",
    "sg:classifiers":[
        {
            "category":"Personal",
            "subcategory":"Beauty Salon",
            "type":"Services"
        }
    ],
    "sg:phone":"+1 514 728 2641",
    "sg:postcode":"H1Y 2C9",
    "sg:province":"QC",
    "sg:tags":[
        "barber"
    ],
    "wof:name":"Salon A Perry Como",
    "wof:placetype":"venue"
},
  "geometry": {"coordinates":[-73.575439,45.5518],"type":"Point"}
}