{
  "type": "Feature",
  "properties": {
    "addr:full":"570 Kortright Rd W Guelph ON N1G 3W8",
    "addr:housenumber":"570",
    "addr:postcode":"n1g 3w8",
    "addr:street":"Kortright Rd W",
    "iso:country":"CA",
    "sg:address":"570 Kortright Rd W",
    "sg:city":"Guelph",
    "sg:classifiers":[
        {
            "category":"Health Services",
            "subcategory":"Doctor",
            "type":"Services"
        }
    ],
    "sg:phone":"+1 519 763 1488",
    "sg:postcode":"N1G 3W8",
    "sg:province":"ON",
    "sg:tags":[
        "dentist"
    ],
    "wof:name":"Hussein, Mohamed DDS",
    "wof:placetype":"venue"
},
  "geometry": {"coordinates":[-80.2313537598,43.5083656311],"type":"Point"}
}