{
  "type": "Feature",
  "properties": {
    "iso:country":"CA",
    "sg:city":"Jonquiere",
    "sg:classifiers":[
        {
            "category":"Social Services",
            "subcategory":"Child Care",
            "type":"Services"
        }
    ],
    "sg:phone":"+1 418 548 5413",
    "sg:postcode":"G7S 3B3",
    "sg:province":"QC",
    "sg:tags":[
        "school"
    ],
    "wof:name":"Jardin D'Enfants D'Arvida",
    "wof:placetype":"venue"
},
  "geometry": {"coordinates":[-71.18347167970001,48.4338989258],"type":"Point"}
}