{
  "type": "Feature",
  "properties": {
    "addr:full":"Surrey BC V3W 3B2",
    "addr:postcode":"v3w 3b2",
    "iso:country":"CA",
    "sg:city":"Surrey",
    "sg:classifiers":[
        {
            "category":"Food & Beverages",
            "subcategory":"Bakery",
            "type":"Retail Goods"
        }
    ],
    "sg:phone":"+1 604 502 0104",
    "sg:postcode":"V3W 3B2",
    "sg:province":"BC",
    "sg:tags":[
        "baker"
    ],
    "wof:name":"Vegetarian Delite Bakery",
    "wof:placetype":"venue"
},
  "geometry": {"coordinates":[-122.858604431,49.1480178833],"type":"Point"}
}