{
  "type": "Feature",
  "properties": {
    "iso:country":"CA",
    "sg:address":"3500 Ch Des Quatre-Bourgeois",
    "sg:city":"Sainte-Foy",
    "sg:classifiers":[
        {
            "category":"Wholesale",
            "subcategory":"Meat",
            "type":"Manufacturing & Wholesale Goods"
        }
    ],
    "sg:phone":"+1 418 653 7687",
    "sg:postcode":"G1W 2L2",
    "sg:province":"QC",
    "sg:tags":[
        "butchering"
    ],
    "wof:name":"Boucherie 4-Bourgeois Enr",
    "wof:placetype":"venue"
},
  "geometry": {"coordinates":[-71.319344,46.761673],"type":"Point"}
}