{
  "type": "Feature",
  "properties": {
    "iso:country":"CA",
    "sg:address":"542 St Clair Ave W",
    "sg:city":"Toronto",
    "sg:classifiers":[
        {
            "category":"Restaurant",
            "type":"Food & Drink"
        }
    ],
    "sg:phone":"+1 416 658 9445",
    "sg:postcode":"M6C 1A5",
    "sg:province":"ON",
    "wof:name":"Albert's Real Jamaican Foods",
    "wof:placetype":"venue"
},
  "geometry": {"coordinates":[-79.420486,43.682858],"type":"Point"}
}