{
  "type": "Feature",
  "properties": {
    "addr:full":"907 Iroquois Rd Ottawa ON K2A 3N4",
    "addr:housenumber":"907",
    "addr:postcode":"k2a 3n4",
    "addr:street":"Iroquois Rd",
    "iso:country":"CA",
    "sg:address":"907 Iroquois Rd",
    "sg:city":"Ottawa",
    "sg:classifiers":[
        {
            "category":"Education",
            "subcategory":"Vocational School",
            "type":"Public Place"
        }
    ],
    "sg:phone":"+1 613 724 3773",
    "sg:postcode":"K2A 3N4",
    "sg:province":"ON",
    "sg:tags":[
        "training",
        "computer"
    ],
    "wof:name":"Anzai Inc",
    "wof:placetype":"venue"
},
  "geometry": {"coordinates":[-75.765434,45.368702],"type":"Point"}
}