{
  "type": "Feature",
  "properties": {
    "iso:country":"CA",
    "sg:address":"1115 Fort St",
    "sg:city":"Victoria",
    "sg:classifiers":[
        {
            "category":"Shopping",
            "type":"Retail Goods"
        }
    ],
    "sg:phone":"+1 250 384 6441",
    "sg:postcode":"V8V 3K9",
    "sg:province":"BC",
    "sg:tags":[
        "dealer",
        "art",
        "gallery",
        "auctioneer"
    ],
    "wof:name":"Kilshaw's Auctioneers Ltd",
    "wof:placetype":"venue"
},
  "geometry": {"coordinates":[-123.353225708,48.423160553],"type":"Point"}
}