{
  "type": "Feature",
  "properties": {
    "addr:full":"80 Rte DE Saint-Pierre Montmagny QC G5V 3R8",
    "addr:housenumber":"80",
    "addr:postcode":"g5v 3r8",
    "addr:street":"Rte De Saint-Pierre",
    "iso:country":"CA",
    "sg:address":"80 Rte DE Saint-Pierre",
    "sg:city":"Montmagny",
    "sg:classifiers":[
        {
            "category":"Manufacturing",
            "subcategory":"Wood Products",
            "type":"Manufacturing & Wholesale Goods"
        }
    ],
    "sg:phone":"+1 418 248 8283",
    "sg:postcode":"G5V 3R8",
    "sg:province":"QC",
    "sg:tags":[
        "lumber"
    ],
    "wof:name":"Bois Traite Mg",
    "wof:placetype":"venue"
},
  "geometry": {"coordinates":[-70.658226,46.946922],"type":"Point"}
}