{
  "type": "Feature",
  "properties": {
    "addr:full":"5610 Rue Sherbrooke O Montreal QC H4A 1W5",
    "addr:housenumber":"5610",
    "addr:postcode":"h4a 1w5",
    "addr:street":"Rue Sherbrooke O",
    "iso:country":"CA",
    "sg:address":"5610 Rue Sherbrooke O",
    "sg:city":"Montreal",
    "sg:classifiers":[
        {
            "category":"Retail",
            "subcategory":"Funeral Services",
            "type":"Services"
        }
    ],
    "sg:phone":"+1 514 483 1870",
    "sg:postcode":"H4A 1W5",
    "sg:province":"QC",
    "sg:tags":[
        "director"
    ],
    "wof:name":"Collins Clarke Mac Gillivary",
    "wof:placetype":"venue"
},
  "geometry": {"coordinates":[-73.5495223999,45.5722160339],"type":"Point"}
}