{
  "type": "Feature",
  "properties": {
    "addr:full":"3019 Pandosy St Kelowna BC V1Y 1W3",
    "addr:housenumber":"3019",
    "addr:postcode":"v1y 1w3",
    "addr:street":"Pandosy St",
    "iso:country":"CA",
    "sg:address":"3019 Pandosy St",
    "sg:city":"Kelowna",
    "sg:classifiers":[
        {
            "category":"Health Services",
            "subcategory":"Chiropractor",
            "type":"Services"
        }
    ],
    "sg:phone":"+1 250 861 1332",
    "sg:postcode":"V1Y 1W3",
    "sg:province":"BC",
    "wof:name":"Lakeview Chiropractic",
    "wof:placetype":"venue"
},
  "geometry": {"coordinates":[-119.491028,49.862984],"type":"Point"}
}