{
  "type": "Feature",
  "properties": {
    "iso:country":"CA",
    "sg:address":"4400 Aut Chomedey",
    "sg:city":"Laval",
    "sg:classifiers":[
        {
            "category":"Shopping",
            "subcategory":"Shoes",
            "type":"Retail Goods"
        }
    ],
    "sg:phone":"+1 450 625 8511",
    "sg:postcode":"H7R 6E9",
    "sg:province":"QC",
    "sg:tags":[
        "instrument",
        "scientific",
        "apparatus"
    ],
    "wof:name":"Serum International Inc",
    "wof:placetype":"venue"
},
  "geometry": {"coordinates":[-73.8207244873,45.5644836426],"type":"Point"}
}