{
  "type": "Feature",
  "properties": {
    "addr:full":"396 Notre Dame Ave Winnipeg MB R3B 1R1",
    "addr:housenumber":"396",
    "addr:postcode":"r3b 1r1",
    "addr:street":"Notre Dame Ave",
    "iso:country":"CA",
    "sg:address":"396 Notre Dame Ave",
    "sg:city":"Winnipeg",
    "sg:classifiers":[
        {
            "category":"Food & Beverages",
            "subcategory":"Groceries & Convenience Stores",
            "type":"Retail Goods"
        }
    ],
    "sg:phone":"+1 204 956 2434",
    "sg:postcode":"R3B 1R1",
    "sg:province":"MB",
    "sg:tags":[
        "grocer"
    ],
    "wof:name":"Abyssinian Commercial Trade",
    "wof:placetype":"venue"
},
  "geometry": {"coordinates":[-97.14808654789999,49.8977661133],"type":"Point"}
}