{
  "type": "Feature",
  "properties": {
    "addr:full":"Newmarket ON L3Y 4Z1",
    "addr:postcode":"l3y 4z1",
    "iso:country":"CA",
    "sg:city":"Newmarket",
    "sg:classifiers":[
        {
            "category":"Shopping",
            "subcategory":"Gifts & Souvenirs",
            "type":"Retail Goods"
        }
    ],
    "sg:phone":"+1 905 967 0704",
    "sg:postcode":"L3Y 4Z1",
    "sg:province":"ON",
    "sg:tags":[
        "shop"
    ],
    "wof:name":"Crabtree & Evelyn",
    "wof:placetype":"venue"
},
  "geometry": {"coordinates":[-79.4811096191,44.057056427],"type":"Point"}
}