{
  "type": "Feature",
  "properties": {
    "addr:full":"4705 49 Ave Athabasca AB T9S 1B7",
    "addr:housenumber":"4705",
    "addr:postcode":"t9s 1b7",
    "addr:street":"49 Ave",
    "iso:country":"CA",
    "sg:address":"4705 49 Ave",
    "sg:city":"Athabasca",
    "sg:classifiers":[
        {
            "category":"Education",
            "subcategory":"School",
            "type":"Public Place"
        }
    ],
    "sg:phone":"+1 780 675 5650",
    "sg:postcode":"T9S 1B7",
    "sg:province":"AB",
    "wof:name":"Words Work Learning Ctr",
    "wof:placetype":"venue"
},
  "geometry": {"coordinates":[-113.28295900000001,54.719532],"type":"Point"}
}