{
  "type": "Feature",
  "properties": {
    "iso:country":"CA",
    "sg:address":"3683 197A St",
    "sg:city":"Langley",
    "sg:classifiers":[
        {
            "category":"Retail",
            "subcategory":"Repair Shop",
            "type":"Services"
        }
    ],
    "sg:phone":"+1 604 534 1674",
    "sg:postcode":"V3A 1B8",
    "sg:province":"BC",
    "sg:tags":[
        "refinishing",
        "furniture"
    ],
    "wof:name":"W C Beningfield & CO",
    "wof:placetype":"venue"
},
  "geometry": {"coordinates":[-122.65657043500001,49.1041221619],"type":"Point"}
}