{
  "type": "Feature",
  "properties": {
    "addr:full":"35 Mckelvey Dr Thornhill ON L3T 5X6",
    "addr:housenumber":"35",
    "addr:postcode":"l3t 5x6",
    "addr:street":"Mckelvey Dr",
    "iso:country":"CA",
    "sg:address":"35 Mckelvey Dr",
    "sg:city":"Thornhill",
    "sg:classifiers":[
        {
            "category":"Organizations",
            "subcategory":"Non-profit Organization",
            "type":"Services"
        }
    ],
    "sg:phone":"+1 905 886 9122",
    "sg:postcode":"L3T 5X6",
    "sg:province":"ON",
    "sg:tags":[
        "breastfeeding",
        "information",
        "supply"
    ],
    "wof:name":"Lactation Centre of Thornhill",
    "wof:placetype":"venue"
},
  "geometry": {"coordinates":[-79.390236,43.821308],"type":"Point"}
}