{
  "type": "Feature",
  "properties": {
    "addr:full":"Saint-Leonard QC H1S 3G4",
    "addr:postcode":"h1s 3g4",
    "iso:country":"CA",
    "sg:city":"Saint-Leonard",
    "sg:classifiers":[
        {
            "category":"Health Services",
            "subcategory":"Doctor",
            "type":"Services"
        }
    ],
    "sg:phone":"+1 514 593 5000",
    "sg:postcode":"H1S 3G4",
    "sg:province":"QC",
    "sg:tags":[
        "dentist"
    ],
    "wof:name":"Reich, Eric DDS",
    "wof:placetype":"venue"
},
  "geometry": {"coordinates":[-73.583641,45.576778],"type":"Point"}
}