{
  "type": "Feature",
  "properties": {
    "iso:country":"CA",
    "sg:address":"1630 Rte Del'Eglise",
    "sg:city":"L'Ascension-DE-Notre-Seigneur",
    "sg:classifiers":[
        {
            "category":"Food & Beverages",
            "subcategory":"Fruits & Vegetables",
            "type":"Retail Goods"
        }
    ],
    "sg:phone":"+1 418 347 2555",
    "sg:postcode":"G0W 1Y0",
    "sg:province":"QC",
    "sg:tags":[
        "equipment",
        "greenhouse",
        "supply"
    ],
    "wof:name":"Serres Arc-En-Ciel",
    "wof:placetype":"venue"
},
  "geometry": {"coordinates":[-71.6733016968,48.6879310608],"type":"Point"}
}