{
  "type": "Feature",
  "properties": {
    "addr:full":"1706 Simcoe St N Oshawa ON L1G 4X9",
    "addr:housenumber":"1706",
    "addr:postcode":"l1g 4x9",
    "addr:street":"Simcoe St N",
    "iso:country":"CA",
    "sg:address":"1706 Simcoe St N",
    "sg:city":"Oshawa",
    "sg:classifiers":[
        {
            "category":"Autos & Motor Vehicles",
            "subcategory":"Automobile Sales",
            "type":"Retail Goods"
        }
    ],
    "sg:phone":"+1 905 579 8897",
    "sg:postcode":"L1G 4X9",
    "sg:province":"ON",
    "sg:tags":[
        "car",
        "dealer"
    ],
    "wof:name":"Countryside Motors",
    "wof:placetype":"venue"
},
  "geometry": {"coordinates":[-78.8867111206,43.9412345886],"type":"Point"}
}