{
  "type": "Feature",
  "properties": {
    "addr:full":"Calgary AB T2H 1Y6",
    "addr:postcode":"t2h 1y6",
    "iso:country":"CA",
    "sg:city":"Calgary",
    "sg:classifiers":[
        {
            "category":"Food & Beverages",
            "subcategory":"Specialty",
            "type":"Retail Goods"
        }
    ],
    "sg:phone":"+1 403 243 4566",
    "sg:postcode":"T2H 1Y6",
    "sg:province":"AB",
    "sg:tags":[
        "health",
        "diet"
    ],
    "wof:name":"Sunrider Independent Dist",
    "wof:placetype":"venue"
},
  "geometry": {"coordinates":[-114.068375,51.003376],"type":"Point"}
}