{
  "type": "Feature",
  "properties": {
    "addr:full":"Peterborough ON K9J 7J6",
    "addr:postcode":"k9j 7j6",
    "iso:country":"CA",
    "sg:city":"Peterborough",
    "sg:classifiers":[
        {
            "category":"Home & Garden",
            "subcategory":"Carpets & Floor Coverings",
            "type":"Retail Goods"
        }
    ],
    "sg:phone":"+1 705 745 4592",
    "sg:postcode":"K9J 7J6",
    "sg:province":"ON",
    "sg:tags":[
        "material",
        "rug"
    ],
    "wof:name":"Westby Flooring Ltd",
    "wof:placetype":"venue"
},
  "geometry": {"coordinates":[-78.33638000489999,44.2778816223],"type":"Point"}
}