{
  "type": "Feature",
  "properties": {
    "iso:country":"CA",
    "sg:address":"114 Grande Allee",
    "sg:city":"Saint-Nicephore",
    "sg:classifiers":[
        {
            "category":"Wholesale",
            "subcategory":"Machinery & Supplies",
            "type":"Manufacturing & Wholesale Goods"
        }
    ],
    "sg:phone":"+1 819 475 3556",
    "sg:postcode":"J2A 1M8",
    "sg:province":"QC",
    "sg:tags":[
        "window",
        "janitor",
        "cleaning"
    ],
    "wof:name":"Service D'Entretien Rb Enr",
    "wof:placetype":"venue"
},
  "geometry": {"coordinates":[-72.4190368652,45.8311386108],"type":"Point"}
}