{
  "type": "Feature",
  "properties": {
    "addr:full":"179 Kent St W Lindsay ON K9V 2Y7",
    "addr:housenumber":"179",
    "addr:postcode":"k9v 2y7",
    "addr:street":"Kent St W",
    "iso:country":"CA",
    "sg:address":"179 Kent St W",
    "sg:city":"Lindsay",
    "sg:classifiers":[
        {
            "category":"Professional",
            "subcategory":"Accounting & Tax Preparation",
            "type":"Services"
        }
    ],
    "sg:phone":"+1 705 324 2572",
    "sg:postcode":"K9V 2Y7",
    "sg:province":"ON",
    "sg:tags":[
        "return",
        "filing"
    ],
    "wof:name":"H & R Block Canada Inc",
    "wof:placetype":"venue"
},
  "geometry": {"coordinates":[-78.739952,44.354172],"type":"Point"}
}