{
  "type": "Feature",
  "properties": {
    "addr:full":"13 27 42 8 W 5 Rocky Mountain House AB T4T 1A5",
    "addr:housenumber":"27 42 8;5",
    "addr:postcode":"t4t 1a5",
    "addr:street":"W",
    "iso:country":"CA",
    "sg:address":"13 27 42 8 W 5",
    "sg:city":"Rocky Mountain House",
    "sg:classifiers":[
        {
            "category":"Mining & Drilling",
            "type":"Manufacturing & Wholesale Goods"
        }
    ],
    "sg:phone":"+1 403 845 3309",
    "sg:postcode":"T4T 1A5",
    "sg:province":"AB",
    "sg:tags":[
        "company",
        "oil"
    ],
    "wof:name":"Penn West Petroleum Ltd",
    "wof:placetype":"venue"
},
  "geometry": {"coordinates":[-114.931236267,52.3775901794],"type":"Point"}
}