{
  "type": "Feature",
  "properties": {
    "addr:full":"905 Rue DE Nemours # 201 Charlesbourg QC G1H 6Z5",
    "addr:housenumber":"905",
    "addr:postcode":"g1h 6z5",
    "addr:street":"Rue De Nemours # 201",
    "iso:country":"CA",
    "sg:address":"905 Rue DE Nemours # 201",
    "sg:city":"Charlesbourg",
    "sg:classifiers":[
        {
            "category":"Professional",
            "subcategory":"Art Services",
            "type":"Services"
        }
    ],
    "sg:phone":"+1 418 681 5559",
    "sg:postcode":"G1H 6Z5",
    "sg:province":"QC",
    "sg:tags":[
        "communications",
        "graphic",
        "designer",
        "consultant"
    ],
    "wof:name":"Mercure Inc",
    "wof:placetype":"venue"
},
  "geometry": {"coordinates":[-71.240227,46.850819],"type":"Point"}
}