{
  "type": "Feature",
  "properties": {
    "addr:full":"Montreal QC H2G 2J1",
    "addr:postcode":"h2g 2j1",
    "iso:country":"CA",
    "sg:city":"Montreal",
    "sg:classifiers":[
        {
            "category":"Retail",
            "subcategory":"Repair Shop",
            "type":"Services"
        }
    ],
    "sg:phone":"+1 514 277 9020",
    "sg:postcode":"H2G 2J1",
    "sg:province":"QC",
    "sg:tags":[
        "related"
    ],
    "wof:name":"Gingras Taximetres Enrg",
    "wof:placetype":"venue"
},
  "geometry": {"coordinates":[-73.5867233276,45.5446815491],"type":"Point"}
}