{
  "type": "Feature",
  "properties": {
    "addr:full":"Surrey BC V3S 3K8",
    "addr:postcode":"v3s 3k8",
    "iso:country":"CA",
    "sg:city":"Surrey",
    "sg:classifiers":[
        {
            "category":"Food & Beverages",
            "subcategory":"Groceries & Convenience Stores",
            "type":"Retail Goods"
        }
    ],
    "sg:phone":"+1 604 597 6498",
    "sg:postcode":"V3S 3K8",
    "sg:province":"BC",
    "sg:tags":[
        "grocer"
    ],
    "wof:name":"M K Fong Enterprise CO",
    "wof:placetype":"venue"
},
  "geometry": {"coordinates":[-122.80119323700001,49.1177940369],"type":"Point"}
}