{
  "type": "Feature",
  "properties": {
    "addr:full":"2485 King George Hwy Miramichi NB E1V 6W3",
    "addr:housenumber":"2485",
    "addr:postcode":"e1v 6w3",
    "addr:street":"King George Hwy",
    "iso:country":"CA",
    "sg:address":"2485 King George Hwy",
    "sg:city":"Miramichi",
    "sg:classifiers":[
        {
            "category":"Personal",
            "subcategory":"Beauty Salon",
            "type":"Services"
        }
    ],
    "sg:phone":"+1 506 778 9880",
    "sg:postcode":"E1V 6W3",
    "sg:province":"NB",
    "wof:name":"First Choice Haircutters Ltd",
    "wof:placetype":"venue"
},
  "geometry": {"coordinates":[-65.489876,47.030827],"type":"Point"}
}