{
  "type": "Feature",
  "properties": {
    "addr:full":"48 Rue DE LA Baie Canton-DE-Granby QC J2G 8C8",
    "addr:housenumber":"48",
    "addr:postcode":"j2g 8c8",
    "addr:street":"Rue De La Baie Canton-De-Granby",
    "iso:country":"CA",
    "sg:address":"48 Rue DE LA Baie",
    "sg:city":"Canton-DE-Granby",
    "sg:classifiers":[
        {
            "category":"Wholesale",
            "subcategory":"Construction Materials",
            "type":"Manufacturing & Wholesale Goods"
        }
    ],
    "sg:phone":"+1 450 375 4748",
    "sg:postcode":"J2G 8C8",
    "sg:province":"QC",
    "sg:tags":[
        "concrete",
        "form"
    ],
    "wof:name":"Coffrages Form-I Inc",
    "wof:placetype":"venue"
},
  "geometry": {"coordinates":[-72.7055435181,45.433429718],"type":"Point"}
}