{
  "type": "Feature",
  "properties": {
    "iso:country":"CA",
    "sg:address":"117 Rue Principale",
    "sg:city":"Lac-Des-Aigles",
    "sg:classifiers":[
        {
            "category":"Home & Garden",
            "subcategory":"Hardware",
            "type":"Retail Goods"
        }
    ],
    "sg:phone":"+1 418 779 2343",
    "sg:postcode":"G0K 1V0",
    "sg:province":"QC",
    "wof:name":"Materiaux Jc Morin Inc",
    "wof:placetype":"venue"
},
  "geometry": {"coordinates":[-68.67557525629999,47.9931945801],"type":"Point"}
}