{
  "type": "Feature",
  "properties": {
    "addr:full":"8426 Hwy 103 Port Mouton NS B0T 1T0",
    "addr:housenumber":"8426",
    "addr:postcode":"b0t 1t0",
    "addr:street":"Hwy 103",
    "iso:country":"CA",
    "sg:address":"8426 Hwy 103",
    "sg:city":"Port Mouton",
    "sg:classifiers":[
        {
            "category":"Restaurant",
            "type":"Food & Drink"
        }
    ],
    "sg:phone":"+1 902 683 2626",
    "sg:postcode":"B0T 1T0",
    "sg:province":"NS",
    "wof:name":"Seascape Restaurant",
    "wof:placetype":"venue"
},
  "geometry": {"coordinates":[-64.84832,43.927761],"type":"Point"}
}