{
  "type": "Feature",
  "properties": {
    "addr:full":"Red Deer AB T4P 3R2",
    "addr:postcode":"t4p 3r2",
    "iso:country":"CA",
    "sg:city":"Red Deer",
    "sg:classifiers":[
        {
            "category":"Building & Trades",
            "subcategory":"Construction",
            "type":"Services"
        }
    ],
    "sg:phone":"+1 403 342 7223",
    "sg:postcode":"T4P 3R2",
    "sg:province":"AB",
    "sg:tags":[
        "dry wall",
        "contractor"
    ],
    "wof:name":"Ste-Mac Contracting Inc",
    "wof:placetype":"venue"
},
  "geometry": {"coordinates":[-113.856666565,52.2998733521],"type":"Point"}
}