{
  "type": "Feature",
  "properties": {
    "iso:country":"CA",
    "sg:address":"820 Park W",
    "sg:city":"Chatham",
    "sg:classifiers":[
        {
            "category":"Organizations",
            "subcategory":"Religious Organization",
            "type":"Services"
        }
    ],
    "sg:phone":"+1 519 351 2078",
    "sg:postcode":"N7M 5J6",
    "sg:province":"ON",
    "sg:tags":[
        "church"
    ],
    "wof:name":"Zion Christian Church",
    "wof:placetype":"venue"
},
  "geometry": {"coordinates":[-82.2022399902,42.3794212341],"type":"Point"}
}