{
  "type": "Feature",
  "properties": {
    "iso:country":"CA",
    "sg:address":"2492 Ch Sainte-Marie",
    "sg:city":"Mascouche",
    "sg:classifiers":[
        {
            "category":"Personal",
            "subcategory":"Beauty Salon",
            "type":"Services"
        }
    ],
    "sg:phone":"+1 450 474 3737",
    "sg:postcode":"J7K 1M5",
    "sg:province":"QC",
    "wof:name":"Selection Coiffure",
    "wof:placetype":"venue"
},
  "geometry": {"coordinates":[-73.616936,45.752796],"type":"Point"}
}