{
  "type": "Feature",
  "properties": {
    "addr:full":"1180 St Clair Ave W Toronto ON M6E 1B4",
    "addr:housenumber":"1180",
    "addr:postcode":"m6e 1b4",
    "addr:street":"St Clair Ave W",
    "iso:country":"CA",
    "sg:address":"1180 St Clair Ave W",
    "sg:city":"Toronto",
    "sg:classifiers":[
        {
            "category":"Shopping",
            "subcategory":"Department Store",
            "type":"Retail Goods"
        }
    ],
    "sg:phone":"+1 416 658 2841",
    "sg:postcode":"M6E 1B4",
    "sg:province":"ON",
    "sg:tags":[
        "shop"
    ],
    "wof:name":"Cozy Gifts & Discount",
    "wof:placetype":"venue"
},
  "geometry": {"coordinates":[-79.44371,43.677944],"type":"Point"}
}