{
  "type": "Feature",
  "properties": {
    "addr:full":"Hwy 54 Innisfail AB T4G 1S7",
    "addr:postcode":"t4g 1s7",
    "addr:street":"Hwy 54",
    "iso:country":"CA",
    "sg:address":"Hwy 54",
    "sg:city":"Innisfail",
    "sg:classifiers":[
        {
            "category":"Recreation",
            "type":"Entertainment"
        }
    ],
    "sg:phone":"+1 403 227 3444",
    "sg:postcode":"T4G 1S7",
    "sg:province":"AB",
    "sg:tags":[
        "course",
        "golf"
    ],
    "wof:name":"Innisfail Golf Club",
    "wof:placetype":"venue"
},
  "geometry": {"coordinates":[-113.93328099999999,52.027481],"type":"Point"}
}