{
  "type": "Feature",
  "properties": {
    "addr:full":"2207 Glenmore Rd Campbell River BC V9H 1E1",
    "addr:housenumber":"2207",
    "addr:postcode":"v9h 1e1",
    "addr:street":"Glenmore Rd",
    "iso:country":"CA",
    "sg:address":"2207 Glenmore Rd",
    "sg:city":"Campbell River",
    "sg:classifiers":[
        {
            "category":"Food & Beverages",
            "subcategory":"Groceries & Convenience Stores",
            "type":"Retail Goods"
        }
    ],
    "sg:phone":"+1 250 923 7733",
    "sg:postcode":"V9H 1E1",
    "sg:province":"BC",
    "sg:tags":[
        "grocer"
    ],
    "wof:name":"Discovery Foods",
    "wof:placetype":"venue"
},
  "geometry": {"coordinates":[-125.248168945,50.0246086121],"type":"Point"}
}