{
  "type": "Feature",
  "properties": {
    "addr:full":"308 Rue Fafard Maniwaki QC J9E 1Z1",
    "addr:housenumber":"308",
    "addr:postcode":"j9e 1z1",
    "addr:street":"Rue Fafard",
    "iso:country":"CA",
    "sg:address":"308 Rue Fafard",
    "sg:city":"Maniwaki",
    "sg:classifiers":[
        {
            "category":"Organizations",
            "subcategory":"Religious Organization",
            "type":"Services"
        }
    ],
    "sg:phone":"+1 819 449 2900",
    "sg:postcode":"J9E 1Z1",
    "sg:province":"QC",
    "sg:tags":[
        "church"
    ],
    "wof:name":"Presbytere Reserve Indienne",
    "wof:placetype":"venue"
},
  "geometry": {"coordinates":[-75.983513,46.369965],"type":"Point"}
}