{
  "type": "Feature",
  "properties": {
    "addr:full":"678 Derwent Way Delta BC V3M 5P8",
    "addr:housenumber":"678",
    "addr:postcode":"v3m 5p8",
    "addr:street":"Derwent Way",
    "iso:country":"CA",
    "sg:address":"678 Derwent Way",
    "sg:city":"Delta",
    "sg:classifiers":[
        {
            "category":"Manufacturing",
            "subcategory":"Metals",
            "type":"Manufacturing & Wholesale Goods"
        }
    ],
    "sg:phone":"+1 604 525 2224",
    "sg:postcode":"V3M 5P8",
    "sg:province":"BC",
    "sg:tags":[
        "steel"
    ],
    "wof:name":"Independent Specialty Steels",
    "wof:placetype":"venue"
},
  "geometry": {"coordinates":[-122.930351257,49.1787376404],"type":"Point"}
}