{
  "type": "Feature",
  "properties": {
    "addr:full":"598 Union St Vancouver BC V6A 2B8",
    "addr:housenumber":"598",
    "addr:postcode":"v6a 2b8",
    "addr:street":"Union St",
    "iso:country":"CA",
    "sg:address":"598 Union St",
    "sg:city":"Vancouver",
    "sg:classifiers":[
        {
            "category":"Food & Beverages",
            "subcategory":"Groceries & Convenience Stores",
            "type":"Retail Goods"
        }
    ],
    "sg:phone":"+1 604 254 2746",
    "sg:postcode":"V6A 2B8",
    "sg:province":"BC",
    "sg:tags":[
        "grocer"
    ],
    "wof:name":"Benny Foods Ltd",
    "wof:placetype":"venue"
},
  "geometry": {"coordinates":[-123.09178199999999,49.277393],"type":"Point"}
}