{
  "type": "Feature",
  "properties": {
    "addr:full":"284 Hwy 11 S South River ON P0A 1X0",
    "addr:housenumber":"284",
    "addr:postcode":"p0a 1x0",
    "addr:street":"Hwy 11 S",
    "iso:country":"CA",
    "sg:address":"284 Hwy 11 S",
    "sg:city":"South River",
    "sg:classifiers":[
        {
            "category":"Retail",
            "subcategory":"Auto Repair",
            "type":"Services"
        }
    ],
    "sg:phone":"+1 705 386 2272",
    "sg:postcode":"P0A 1X0",
    "sg:province":"ON",
    "sg:tags":[
        "repairing",
        "automobile"
    ],
    "wof:name":"Griffith Brothers Svc Ctr Ltd",
    "wof:placetype":"venue"
},
  "geometry": {"coordinates":[-79.377861,45.837502],"type":"Point"}
}