{
  "type": "Feature",
  "properties": {
    "addr:full":"Arviat NU X0C 0E0",
    "addr:postcode":"x0c 0e0",
    "iso:country":"CA",
    "sg:city":"Arviat",
    "sg:classifiers":[
        {
            "category":"Government",
            "subcategory":"Office",
            "type":"Public Place"
        }
    ],
    "sg:phone":"+1 867 857 2962",
    "sg:postcode":"X0C 0E0",
    "sg:province":"NU",
    "wof:name":"N T Social Svc",
    "wof:placetype":"venue"
},
  "geometry": {"coordinates":[-94.058998,61.109707],"type":"Point"}
}