{
  "type": "Feature",
  "properties": {
    "addr:full":"4709 Bender St Niagara Falls ON L2G 3K3",
    "addr:housenumber":"4709",
    "addr:postcode":"l2g 3k3",
    "addr:street":"Bender St",
    "iso:country":"CA",
    "sg:address":"4709 Bender St",
    "sg:city":"Niagara Falls",
    "sg:classifiers":[
        {
            "category":"Restaurant",
            "type":"Food & Drink"
        }
    ],
    "sg:phone":"+1 905 358 8822",
    "sg:postcode":"L2G 3K3",
    "sg:province":"ON",
    "sg:tags":[
        "caterer"
    ],
    "wof:name":"Falls Sushi Korean Japanese",
    "wof:placetype":"venue"
},
  "geometry": {"coordinates":[-79.071106,43.093899],"type":"Point"}
}