{
  "type": "Feature",
  "properties": {
    "addr:full":"Winnipeg MB R3E 3R3",
    "addr:postcode":"r3e 3r3",
    "iso:country":"CA",
    "sg:city":"Winnipeg",
    "sg:classifiers":[
        {
            "category":"Manufacturing",
            "subcategory":"Tools & Machinery",
            "type":"Manufacturing & Wholesale Goods"
        }
    ],
    "sg:phone":"+1 204 783 7378",
    "sg:postcode":"R3E 3R3",
    "sg:province":"MB",
    "sg:tags":[
        "equipment",
        "electric"
    ],
    "wof:name":"Siemens in Canada",
    "wof:placetype":"venue"
},
  "geometry": {"coordinates":[-97.1899185181,49.9095687866],"type":"Point"}
}