{
  "type": "Feature",
  "properties": {
    "addr:full":"124 Wilson St W Ancaster ON L9G 1N3",
    "addr:housenumber":"124",
    "addr:postcode":"l9g 1n3",
    "addr:street":"Wilson St W",
    "iso:country":"CA",
    "sg:address":"124 Wilson St W",
    "sg:city":"Ancaster",
    "sg:classifiers":[
        {
            "category":"Personal",
            "type":"Services"
        }
    ],
    "sg:phone":"+1 905 304 6158",
    "sg:postcode":"L9G 1N3",
    "sg:province":"ON",
    "sg:tags":[
        "therapist",
        "massage"
    ],
    "wof:name":"Ancaster Massage Therapy Ctr",
    "wof:placetype":"venue"
},
  "geometry": {"coordinates":[-79.99224853520001,43.2143821716],"type":"Point"}
}