{
  "type": "Feature",
  "properties": {
    "iso:country":"CA",
    "sg:address":"201 Brock St E",
    "sg:city":"Thunder Bay",
    "sg:classifiers":[
        {
            "category":"Organizations",
            "subcategory":"Religious Organization",
            "type":"Services"
        }
    ],
    "sg:phone":"+1 807 623 8274",
    "sg:postcode":"P7E 4H3",
    "sg:province":"ON",
    "sg:tags":[
        "church"
    ],
    "wof:name":"First Church United",
    "wof:placetype":"venue"
},
  "geometry": {"coordinates":[-89.272232,48.368542],"type":"Point"}
}