{
  "type": "Feature",
  "properties": {
    "addr:full":"972 Dundas St Woodstock ON N4S 1H3",
    "addr:housenumber":"972",
    "addr:postcode":"n4s 1h3",
    "addr:street":"Dundas St",
    "iso:country":"CA",
    "sg:address":"972 Dundas St",
    "sg:city":"Woodstock",
    "sg:classifiers":[
        {
            "category":"Recreation",
            "type":"Entertainment"
        }
    ],
    "sg:phone":"+1 519 421 3261",
    "sg:postcode":"N4S 1H3",
    "sg:province":"ON",
    "sg:tags":[
        "parlor",
        "billiard"
    ],
    "wof:name":"Hustler Billiards",
    "wof:placetype":"venue"
},
  "geometry": {"coordinates":[-80.731003,43.133675],"type":"Point"}
}