{
  "type": "Feature",
  "properties": {
    "addr:full":"3900 Rue Claude Verdun QC H4G 1H3",
    "addr:housenumber":"3900",
    "addr:postcode":"h4g 1h3",
    "addr:street":"Rue Claude",
    "iso:country":"CA",
    "sg:address":"3900 Rue Claude",
    "sg:city":"Verdun",
    "sg:classifiers":[
        {
            "category":"Food & Beverages",
            "subcategory":"Groceries & Convenience Stores",
            "type":"Retail Goods"
        }
    ],
    "sg:phone":"+1 514 766 3751",
    "sg:postcode":"H4G 1H3",
    "sg:province":"QC",
    "wof:name":"Depanneur Claude",
    "wof:placetype":"venue"
},
  "geometry": {"coordinates":[-73.5731964111,45.464969635],"type":"Point"}
}