{
  "type": "Feature",
  "properties": {
    "addr:full":"Yarmouth NS B5A 4P8",
    "addr:postcode":"b5a 4p8",
    "iso:country":"CA",
    "sg:city":"Yarmouth",
    "sg:classifiers":[
        {
            "category":"Recreation",
            "type":"Entertainment"
        }
    ],
    "sg:phone":"+1 902 742 0965",
    "sg:postcode":"B5A 4P8",
    "sg:province":"NS",
    "sg:tags":[
        "bingo",
        "game"
    ],
    "wof:name":"Cotton Mill Community Ctr",
    "wof:placetype":"venue"
},
  "geometry": {"coordinates":[-66.1221542358,43.8336486816],"type":"Point"}
}