{
  "type": "Feature",
  "properties": {
    "addr:full":"11216 76 Ave NW Edmonton AB T6G 0K1",
    "addr:housenumber":"11216",
    "addr:postcode":"t6g 0k1",
    "addr:street":"76 Ave Nw",
    "iso:country":"CA",
    "sg:address":"11216 76 Ave NW",
    "sg:city":"Edmonton",
    "sg:classifiers":[
        {
            "category":"Shopping",
            "subcategory":"Books",
            "type":"Retail Goods"
        }
    ],
    "sg:phone":"+1 780 433 1781",
    "sg:postcode":"T6G 0K1",
    "sg:province":"AB",
    "sg:tags":[
        "dealer"
    ],
    "wof:name":"Edmonton Book Store Ltd",
    "wof:placetype":"venue"
},
  "geometry": {"coordinates":[-113.52066000000001,53.51239],"type":"Point"}
}