{
  "type": "Feature",
  "properties": {
    "addr:full":"136 9 St NW Drumheller AB T0J 0Y1",
    "addr:housenumber":"136 9",
    "addr:postcode":"t0j 0y1",
    "addr:street":"St Nw",
    "iso:country":"CA",
    "sg:address":"136 9 St NW",
    "sg:city":"Drumheller",
    "sg:classifiers":[
        {
            "category":"Building & Trades",
            "subcategory":"Construction",
            "type":"Services"
        }
    ],
    "sg:phone":"+1 403 823 5666",
    "sg:postcode":"T0J 0Y1",
    "sg:province":"AB",
    "sg:tags":[
        "excavating",
        "contractor"
    ],
    "wof:name":"Gary Trentham Excavating Ltd",
    "wof:placetype":"venue"
},
  "geometry": {"coordinates":[-112.72376300000001,51.466877],"type":"Point"}
}