{
  "type": "Feature",
  "properties": {
    "addr:full":"205 Boul DE Quen N Alma QC G8B 5N6",
    "addr:housenumber":"205",
    "addr:postcode":"g8b 5n6",
    "addr:street":"Boul De Quen N",
    "iso:country":"CA",
    "sg:address":"205 Boul DE Quen N",
    "sg:city":"Alma",
    "sg:classifiers":[
        {
            "category":"Personal",
            "subcategory":"Beauty Salon",
            "type":"Services"
        }
    ],
    "sg:phone":"+1 418 668 4693",
    "sg:postcode":"G8B 5N6",
    "sg:province":"QC",
    "wof:name":"Salon DE Coiffure Mixa Enr",
    "wof:placetype":"venue"
},
  "geometry": {"coordinates":[-71.6488265991,48.5558624268],"type":"Point"}
}