{
  "type": "Feature",
  "properties": {
    "iso:country":"CA",
    "sg:address":"Port Severn Rd",
    "sg:city":"Port Severn",
    "sg:classifiers":[
        {
            "category":"Recreation",
            "subcategory":"Marina",
            "type":"Entertainment"
        }
    ],
    "sg:phone":"+1 705 538 2571",
    "sg:postcode":"L0K 1S0",
    "sg:province":"ON",
    "wof:name":"Severn Marina Ltd",
    "wof:placetype":"venue"
},
  "geometry": {"coordinates":[-79.717606,44.804485],"type":"Point"}
}