{
  "type": "Feature",
  "properties": {
    "addr:full":"632 Rue Principale Clair NB E7A 2H2",
    "addr:housenumber":"632",
    "addr:postcode":"e7a 2h2",
    "addr:street":"Rue Principale",
    "iso:country":"CA",
    "sg:address":"632 Rue Principale",
    "sg:city":"Clair",
    "sg:classifiers":[
        {
            "category":"Manufacturing",
            "subcategory":"Lumber",
            "type":"Manufacturing & Wholesale Goods"
        }
    ],
    "sg:phone":"+1 506 992 9020",
    "sg:postcode":"E7A 2H2",
    "sg:province":"NB",
    "wof:name":"J D Irving Ltd Hardwood Div",
    "wof:placetype":"venue"
},
  "geometry": {"coordinates":[-68.6009063721,47.256477356],"type":"Point"}
}