{
  "type": "Feature",
  "properties": {
    "addr:full":"3305 Monarch Dr Orillia ON L3V 7Z4",
    "addr:housenumber":"3305",
    "addr:postcode":"l3v 7z4",
    "addr:street":"Monarch Dr",
    "iso:country":"CA",
    "sg:address":"3305 Monarch Dr",
    "sg:city":"Orillia",
    "sg:classifiers":[
        {
            "category":"Banks & Credit Unions",
            "subcategory":"Bank",
            "type":"Services"
        }
    ],
    "sg:phone":"+1 705 325 2267",
    "sg:postcode":"L3V 7Z4",
    "sg:province":"ON",
    "wof:name":"Scotiabank",
    "wof:placetype":"venue"
},
  "geometry": {"coordinates":[-79.4520950317,44.609172821],"type":"Point"}
}