{
  "type": "Feature",
  "properties": {
    "addr:full":"Red Deer AB T4N 6C2",
    "addr:postcode":"t4n 6c2",
    "iso:country":"CA",
    "sg:city":"Red Deer",
    "sg:classifiers":[
        {
            "category":"Organizations",
            "subcategory":"Non-profit Organization",
            "type":"Services"
        }
    ],
    "sg:phone":"+1 403 342 4550",
    "sg:postcode":"T4N 6C2",
    "sg:province":"AB",
    "sg:tags":[
        "disability"
    ],
    "wof:name":"Cars",
    "wof:placetype":"venue"
},
  "geometry": {"coordinates":[-113.814163208,52.2691307068],"type":"Point"}
}