{
  "type": "Feature",
  "properties": {
    "addr:full":"273 Cove Rd Irishtown NB E1H 1R3",
    "addr:housenumber":"273",
    "addr:postcode":"e1h 1r3",
    "addr:street":"Cove Rd",
    "iso:country":"CA",
    "sg:address":"273 Cove Rd",
    "sg:city":"Irishtown",
    "sg:classifiers":[
        {
            "category":"Building & Trades",
            "subcategory":"Construction",
            "type":"Services"
        }
    ],
    "sg:phone":"+1 506 383 9927",
    "sg:postcode":"E1H 1R3",
    "sg:province":"NB",
    "sg:tags":[
        "home",
        "general",
        "improvement",
        "contractor"
    ],
    "wof:name":"Spicer Brothers Construction",
    "wof:placetype":"venue"
},
  "geometry": {"coordinates":[-64.793274,46.190609],"type":"Point"}
}