{
  "type": "Feature",
  "properties": {
    "iso:country":"CA",
    "sg:address":"1 Lyon Ave",
    "sg:city":"Guelph",
    "sg:classifiers":[
        {
            "category":"Professional",
            "subcategory":"Accounting & Tax Preparation",
            "type":"Services"
        }
    ],
    "sg:phone":"+1 519 766 1430",
    "sg:postcode":"N1H 5C5",
    "sg:province":"ON",
    "sg:tags":[
        "return",
        "investment",
        "filing"
    ],
    "wof:name":"Lyon Financial Svc Inc",
    "wof:placetype":"venue"
},
  "geometry": {"coordinates":[-80.2619171143,43.5466995239],"type":"Point"}
}