{
  "type": "Feature",
  "properties": {
    "addr:full":"1950 Rue Sherbrooke O # 400 Montreal QC H3H 1E7",
    "addr:housenumber":"1950",
    "addr:postcode":"h3h 1e7",
    "addr:street":"Rue Sherbrooke O # 400",
    "iso:country":"CA",
    "sg:address":"1950 Rue Sherbrooke O # 400",
    "sg:city":"Montreal",
    "sg:classifiers":[
        {
            "category":"Professional",
            "subcategory":"Engineering",
            "type":"Services"
        }
    ],
    "sg:phone":"+1 514 846 4000",
    "sg:postcode":"H3H 1E7",
    "sg:province":"QC",
    "sg:tags":[
        "engineer"
    ],
    "wof:name":"Axor Experts Conseils Inc",
    "wof:placetype":"venue"
},
  "geometry": {"coordinates":[-73.563369751,45.5294418335],"type":"Point"}
}