{
  "type": "Feature",
  "properties": {
    "iso:country":"CA",
    "sg:address":"151 York St",
    "sg:city":"London",
    "sg:classifiers":[
        {
            "category":"Banks & Credit Unions",
            "subcategory":"Bank",
            "type":"Services"
        }
    ],
    "sg:phone":"+1 519 858 2966",
    "sg:postcode":"N6A 1A8",
    "sg:province":"ON",
    "sg:tags":[
        "financing",
        "loan",
        "real estate"
    ],
    "wof:name":"Charleton Building Credit",
    "wof:placetype":"venue"
},
  "geometry": {"coordinates":[-81.249504,42.980885],"type":"Point"}
}