{
  "type": "Feature",
  "properties": {
    "addr:full":"161 Athabasca Ave Hinton AB T7V 2A4",
    "addr:housenumber":"161",
    "addr:postcode":"t7v 2a4",
    "addr:street":"Athabasca Ave",
    "iso:country":"CA",
    "sg:address":"161 Athabasca Ave",
    "sg:city":"Hinton",
    "sg:classifiers":[
        {
            "category":"Shopping",
            "subcategory":"Used Merchandise",
            "type":"Retail Goods"
        }
    ],
    "sg:phone":"+1 780 865 5095",
    "sg:postcode":"T7V 2A4",
    "sg:province":"AB",
    "sg:tags":[
        "shop",
        "consignment"
    ],
    "wof:name":"Christine's Clothes Closet",
    "wof:placetype":"venue"
},
  "geometry": {"coordinates":[-117.545082092,53.4238853455],"type":"Point"}
}