{
  "type": "Feature",
  "properties": {
    "addr:full":"115 King St Ll Sioux Lookout ON P8T 1B9",
    "addr:housenumber":"115",
    "addr:postcode":"p8t 1b9",
    "addr:street":"King St",
    "iso:country":"CA",
    "sg:address":"115 King St Ll",
    "sg:city":"Sioux Lookout",
    "sg:classifiers":[
        {
            "category":"Organizations",
            "subcategory":"Professional Association",
            "type":"Services"
        }
    ],
    "sg:phone":"+1 807 737 1135",
    "sg:postcode":"P8T 1B9",
    "sg:province":"ON",
    "sg:tags":[
        "native"
    ],
    "wof:name":"Northern Chiefs Council",
    "wof:placetype":"venue"
},
  "geometry": {"coordinates":[-91.92584991459999,50.0987358093],"type":"Point"}
}