{
  "type": "Feature",
  "properties": {
    "addr:full":"129 Ch Du College Dunham QC J0E 1M0",
    "addr:housenumber":"129",
    "addr:postcode":"j0e 1m0",
    "addr:street":"Ch Du College",
    "iso:country":"CA",
    "sg:address":"129 Ch Du College",
    "sg:city":"Dunham",
    "sg:classifiers":[
        {
            "category":"Organizations",
            "subcategory":"Religious Organization",
            "type":"Services"
        }
    ],
    "sg:phone":"+1 450 295 2201",
    "sg:postcode":"J0E 1M0",
    "sg:province":"QC",
    "sg:tags":[
        "church"
    ],
    "wof:name":"All Saints' Anglican Church",
    "wof:placetype":"venue"
},
  "geometry": {"coordinates":[-72.79843099999999,45.129517],"type":"Point"}
}