{
  "type": "Feature",
  "properties": {
    "iso:country":"CA",
    "sg:address":"8056 Yonge St",
    "sg:city":"Innisfil",
    "sg:classifiers":[
        {
            "category":"Personal",
            "type":"Services"
        }
    ],
    "sg:phone":"+1 705 431 1222",
    "sg:postcode":"L9S 1L6",
    "sg:province":"ON",
    "sg:tags":[
        "control",
        "weight"
    ],
    "wof:name":"Herbal Magic Systems",
    "wof:placetype":"venue"
},
  "geometry": {"coordinates":[-79.622719,44.336941],"type":"Point"}
}