{
  "type": "Feature",
  "properties": {
    "addr:full":"177 Rebecca St Hamilton ON L8R 1B9",
    "addr:housenumber":"177",
    "addr:postcode":"l8r 1b9",
    "addr:street":"Rebecca St",
    "iso:country":"CA",
    "sg:address":"177 Rebecca St",
    "sg:city":"Hamilton",
    "sg:classifiers":[
        {
            "category":"Social Services",
            "type":"Services"
        }
    ],
    "sg:phone":"+1 905 527 4543",
    "sg:postcode":"L8R 1B9",
    "sg:province":"ON",
    "sg:tags":[
        "organization",
        "welfare"
    ],
    "wof:name":"United Way",
    "wof:placetype":"venue"
},
  "geometry": {"coordinates":[-79.8614120483,43.2564697266],"type":"Point"}
}