{
  "type": "Feature",
  "properties": {
    "addr:full":"1021 Meyerside Dr Mississauga ON L5T 1J6",
    "addr:housenumber":"1021",
    "addr:postcode":"l5t 1j6",
    "addr:street":"Meyerside Dr",
    "iso:country":"CA",
    "sg:address":"1021 Meyerside Dr",
    "sg:city":"Mississauga",
    "sg:classifiers":[
        {
            "category":"Manufacturing",
            "subcategory":"Tools & Machinery",
            "type":"Manufacturing & Wholesale Goods"
        }
    ],
    "sg:phone":"+1 905 564 7337",
    "sg:postcode":"L5T 1J6",
    "sg:province":"ON",
    "sg:tags":[
        "machine",
        "shop"
    ],
    "wof:name":"New Dimension Machine & Tools",
    "wof:placetype":"venue"
},
  "geometry": {"coordinates":[-79.664207,43.651581],"type":"Point"}
}