{
  "type": "Feature",
  "properties": {
    "iso:country":"CA",
    "sg:city":"Langley",
    "sg:classifiers":[
        {
            "category":"Freight",
            "type":"Transportation"
        }
    ],
    "sg:phone":"+1 604 882 7661",
    "sg:postcode":"V1M 3C2",
    "sg:province":"BC",
    "sg:tags":[
        "trucking"
    ],
    "wof:name":"Clark Trucking Lines Ltd",
    "wof:placetype":"venue"
},
  "geometry": {"coordinates":[-122.67034149200001,49.1767845154],"type":"Point"}
}