{
  "type": "Feature",
  "properties": {
    "addr:full":"3192 Sunridge Blvd NE Calgary AB T1Y 7G6",
    "addr:housenumber":"3192",
    "addr:postcode":"t1y 7g6",
    "addr:street":"Sunridge Blvd Ne",
    "iso:country":"CA",
    "sg:address":"3192 Sunridge Blvd NE",
    "sg:city":"Calgary",
    "sg:classifiers":[
        {
            "category":"Restaurant",
            "type":"Food & Drink"
        }
    ],
    "sg:phone":"+1 403 250 3557",
    "sg:postcode":"T1Y 7G6",
    "sg:province":"AB",
    "sg:tags":[
        "shop",
        "coffee"
    ],
    "wof:name":"Second Cup",
    "wof:placetype":"venue"
},
  "geometry": {"coordinates":[-113.987289429,51.075668335],"type":"Point"}
}