{
  "type": "Feature",
  "properties": {
    "iso:country":"CA",
    "sg:address":"42 Cook Crt SE",
    "sg:city":"Medicine Hat",
    "sg:classifiers":[
        {
            "category":"Professional",
            "subcategory":"Business Services",
            "type":"Services"
        }
    ],
    "sg:phone":"+1 403 529 2812",
    "sg:postcode":"T1B 3Y3",
    "sg:province":"AB",
    "sg:tags":[
        "interior",
        "consultant",
        "design",
        "decorator"
    ],
    "wof:name":"Well Dressed House",
    "wof:placetype":"venue"
},
  "geometry": {"coordinates":[-110.639404297,50.0240516663],"type":"Point"}
}