{
  "type": "Feature",
  "properties": {
    "addr:full":"Noel NS B0N 2C0",
    "addr:postcode":"b0n 2c0",
    "iso:country":"CA",
    "sg:city":"Noel",
    "sg:classifiers":[
        {
            "category":"Organizations",
            "subcategory":"Religious Organization",
            "type":"Services"
        }
    ],
    "sg:phone":"+1 902 369 2989",
    "sg:postcode":"B0N 2C0",
    "sg:province":"NS",
    "sg:tags":[
        "church"
    ],
    "wof:name":"United Church of Canada",
    "wof:placetype":"venue"
},
  "geometry": {"coordinates":[-63.744888,45.295807],"type":"Point"}
}