{
  "type": "Feature",
  "properties": {
    "addr:full":"4593 Lincoln Ave Beamsville ON L0R 1B3",
    "addr:housenumber":"4593",
    "addr:postcode":"l0r 1b3",
    "addr:street":"Lincoln Ave",
    "iso:country":"CA",
    "sg:address":"4593 Lincoln Ave",
    "sg:city":"Beamsville",
    "sg:classifiers":[
        {
            "category":"Building & Trades",
            "subcategory":"Construction",
            "type":"Services"
        }
    ],
    "sg:phone":"+1 905 563 0999",
    "sg:postcode":"L0R 1B3",
    "sg:province":"ON",
    "sg:tags":[
        "contractor",
        "general"
    ],
    "wof:name":"Pride Homes By Fred Hendriks",
    "wof:placetype":"venue"
},
  "geometry": {"coordinates":[-79.48683200000001,43.178772],"type":"Point"}
}