{
  "type": "Feature",
  "properties": {
    "addr:full":"372 Highway 7 E Richmond Hill ON L4B 1A7",
    "addr:housenumber":"372;e",
    "addr:postcode":"l4b 1a7",
    "addr:street":"Highway 7",
    "iso:country":"CA",
    "sg:address":"372 Highway 7 E",
    "sg:city":"Richmond Hill",
    "sg:classifiers":[
        {
            "category":"Retail",
            "subcategory":"Auto Repair",
            "type":"Services"
        }
    ],
    "sg:phone":"+1 905 764 0891",
    "sg:postcode":"L4B 1A7",
    "sg:province":"ON",
    "sg:tags":[
        "wrecker"
    ],
    "wof:name":"Reid's Towing Svc",
    "wof:placetype":"venue"
},
  "geometry": {"coordinates":[-79.37847137449999,43.8465538025],"type":"Point"}
}