{
  "type": "Feature",
  "properties": {
    "addr:full":"408 Enterprise Ave Kitimat BC V8C 2E2",
    "addr:housenumber":"408",
    "addr:postcode":"bc v8c 2e2",
    "addr:street":"Enterprise Ave",
    "iso:country":"CA",
    "sg:address":"408 Enterprise Ave",
    "sg:city":"Kitimat",
    "sg:classifiers":[
        {
            "category":"Manufacturing",
            "subcategory":"Pottery",
            "type":"Manufacturing & Wholesale Goods"
        }
    ],
    "sg:phone":"+1 250 632 2587",
    "sg:postcode":"V8C 2E2",
    "sg:province":"BC",
    "sg:tags":[
        "souvenir"
    ],
    "wof:name":"Commercial Lettering & Signs",
    "wof:placetype":"venue"
},
  "geometry": {"coordinates":[-128.687866211,54.0588684082],"type":"Point"}
}