{
  "type": "Feature",
  "properties": {
    "addr:full":"39 Orfus Rd North York ON M6A 1L7",
    "addr:housenumber":"39",
    "addr:postcode":"m6a 1l7",
    "addr:street":"Orfus Rd",
    "iso:country":"CA",
    "sg:address":"39 Orfus Rd",
    "sg:city":"North York",
    "sg:classifiers":[
        {
            "category":"Wholesale",
            "subcategory":"Machinery & Supplies",
            "type":"Manufacturing & Wholesale Goods"
        }
    ],
    "sg:phone":"+1 416 256 2036",
    "sg:postcode":"M6A 1L7",
    "sg:province":"ON",
    "sg:tags":[
        "salon",
        "beauty"
    ],
    "wof:name":"Shades of Beauty",
    "wof:placetype":"venue"
},
  "geometry": {"coordinates":[-79.459518,43.719547],"type":"Point"}
}