{
  "type": "Feature",
  "properties": {
    "iso:country":"CA",
    "sg:address":"9910 Boul Saint-Laurent",
    "sg:city":"Montreal",
    "sg:classifiers":[
        {
            "category":"Food & Beverages",
            "subcategory":"Groceries & Convenience Stores",
            "type":"Retail Goods"
        }
    ],
    "sg:phone":"+1 514 389 5236",
    "sg:postcode":"H3L 2N7",
    "sg:province":"QC",
    "sg:tags":[
        "grocer"
    ],
    "wof:name":"Marche Mayls Inc",
    "wof:placetype":"venue"
},
  "geometry": {"coordinates":[-73.656326,45.545952],"type":"Point"}
}