{
  "type": "Feature",
  "properties": {
    "addr:full":"Pointe-Claire QC H9S 4R9",
    "addr:postcode":"h9s 4r9",
    "iso:country":"CA",
    "sg:city":"Pointe-Claire",
    "sg:classifiers":[
        {
            "category":"Shopping",
            "subcategory":"Bicycles & Sporting Goods",
            "type":"Retail Goods"
        }
    ],
    "sg:phone":"+1 514 630 6717",
    "sg:postcode":"H9S 4R9",
    "sg:province":"QC",
    "wof:name":"Camp DE Base",
    "wof:placetype":"venue"
},
  "geometry": {"coordinates":[-73.8271560669,45.4407043457],"type":"Point"}
}