{
  "type": "Feature",
  "properties": {
    "addr:full":"516 Rue Du Parc Saint-Eustache QC J7R 5B2",
    "addr:housenumber":"516",
    "addr:postcode":"j7r 5b2",
    "addr:street":"Rue Du Parc",
    "iso:country":"CA",
    "sg:address":"516 Rue Du Parc",
    "sg:city":"Saint-Eustache",
    "sg:classifiers":[
        {
            "category":"Wholesale",
            "subcategory":"Machinery & Supplies",
            "type":"Manufacturing & Wholesale Goods"
        }
    ],
    "sg:phone":"+1 450 472 9120",
    "sg:postcode":"J7R 5B2",
    "sg:province":"QC",
    "sg:tags":[
        "printer",
        "printing",
        "cartridge"
    ],
    "wof:name":"Groupe Christie Limitee",
    "wof:placetype":"venue"
},
  "geometry": {"coordinates":[-73.91203299999999,45.568092],"type":"Point"}
}