{
  "type": "Feature",
  "properties": {
    "iso:country":"CA",
    "sg:address":"94 Dunkirk Rd",
    "sg:city":"St Catharines",
    "sg:classifiers":[
        {
            "category":"Wholesale",
            "subcategory":"Electrical",
            "type":"Manufacturing & Wholesale Goods"
        }
    ],
    "sg:phone":"+1 905 682 7250",
    "sg:postcode":"L2P 3H4",
    "sg:province":"ON",
    "sg:tags":[
        "control",
        "security",
        "system"
    ],
    "wof:name":"Protel Alarm & Signal",
    "wof:placetype":"venue"
},
  "geometry": {"coordinates":[-79.21929168699999,43.1699104309],"type":"Point"}
}