{
  "type": "Feature",
  "properties": {
    "addr:full":"19 Av Thibaudeau Edmundston NB E3V 4Z2",
    "addr:postcode":"e3v 4z2",
    "addr:street":"19 Av Thibaudeau",
    "iso:country":"CA",
    "sg:address":"19 Av Thibaudeau",
    "sg:city":"Edmundston",
    "sg:classifiers":[
        {
            "category":"Real Estate",
            "subcategory":"Surveying",
            "type":"Services"
        }
    ],
    "sg:phone":"+1 506 739 8781",
    "sg:postcode":"E3V 4Z2",
    "sg:province":"NB",
    "sg:tags":[
        "surveyor"
    ],
    "wof:name":"Arpenteurs DE LA Republique",
    "wof:placetype":"venue"
},
  "geometry": {"coordinates":[-68.315521,47.38063],"type":"Point"}
}