{
  "type": "Feature",
  "properties": {
    "addr:full":"40 Boul Du Saguenay O Chicoutimi QC G7J 1C8",
    "addr:housenumber":"40",
    "addr:postcode":"g7j 1c8",
    "addr:street":"Boul Du Saguenay O",
    "iso:country":"CA",
    "sg:address":"40 Boul Du Saguenay O",
    "sg:city":"Chicoutimi",
    "sg:classifiers":[
        {
            "category":"Manufacturing",
            "subcategory":"Signs",
            "type":"Manufacturing & Wholesale Goods"
        }
    ],
    "sg:phone":"+1 418 549 8624",
    "sg:postcode":"G7J 1C8",
    "sg:province":"QC",
    "wof:name":"Atelier Pierre Le Lettreur",
    "wof:placetype":"venue"
},
  "geometry": {"coordinates":[-71.0672073364,48.4292793274],"type":"Point"}
}