{
  "type": "Feature",
  "properties": {
    "addr:full":"65 Newell Rd Mill Village NS B0J 2H0",
    "addr:housenumber":"65",
    "addr:postcode":"b0j 2h0",
    "addr:street":"Newell Rd",
    "iso:country":"CA",
    "sg:address":"65 Newell Rd",
    "sg:city":"Mill Village",
    "sg:classifiers":[
        {
            "category":"Wholesale",
            "subcategory":"Seafood",
            "type":"Manufacturing & Wholesale Goods"
        }
    ],
    "sg:phone":"+1 902 677 2491",
    "sg:postcode":"B0J 2H0",
    "sg:province":"NS",
    "wof:name":"Rbn Fisheries",
    "wof:placetype":"venue"
},
  "geometry": {"coordinates":[-64.647018,44.144821],"type":"Point"}
}