{
  "type": "Feature",
  "properties": {
    "addr:full":"Strasbourg SK S0G 4V0",
    "addr:postcode":"s0g 4v0",
    "iso:country":"CA",
    "sg:city":"Strasbourg",
    "sg:classifiers":[
        {
            "category":"Wholesale",
            "subcategory":"Machinery & Supplies",
            "type":"Manufacturing & Wholesale Goods"
        }
    ],
    "sg:phone":"+1 306 725 3031",
    "sg:postcode":"S0G 4V0",
    "sg:province":"SK",
    "sg:tags":[
        "farm",
        "agricultural",
        "implement",
        "equipment"
    ],
    "wof:name":"Strasbourg Agro Sales & Svc",
    "wof:placetype":"venue"
},
  "geometry": {"coordinates":[-104.961158752,51.0701332092],"type":"Point"}
}