{
  "type": "Feature",
  "properties": {
    "addr:full":"662 1/2 Progress Ave Kingston ON K7M 4W9",
    "addr:housenumber":"662 1 / 2",
    "addr:postcode":"k7m 4w9",
    "addr:street":"Progress Ave",
    "iso:country":"CA",
    "sg:address":"662 1/2 Progress Ave",
    "sg:city":"Kingston",
    "sg:classifiers":[
        {
            "category":"Building & Trades",
            "subcategory":"Plumbing",
            "type":"Services"
        }
    ],
    "sg:phone":"+1 613 634 8499",
    "sg:postcode":"K7M 4W9",
    "sg:province":"ON",
    "sg:tags":[
        "air",
        "conditioning",
        "contractor",
        "system",
        "heating"
    ],
    "wof:name":"G T Air Systems Inc",
    "wof:placetype":"venue"
},
  "geometry": {"coordinates":[-76.57019,44.246758],"type":"Point"}
}