{
  "type": "Feature",
  "properties": {
    "addr:full":"7024 Farrell Rd SE Calgary AB T2H 0T2",
    "addr:housenumber":"7024",
    "addr:postcode":"t2h 0t2",
    "addr:street":"Farrell Rd Se",
    "iso:country":"CA",
    "sg:address":"7024 Farrell Rd SE",
    "sg:city":"Calgary",
    "sg:classifiers":[
        {
            "category":"Mining & Drilling",
            "type":"Manufacturing & Wholesale Goods"
        }
    ],
    "sg:phone":"+1 403 252 4421",
    "sg:postcode":"T2H 0T2",
    "sg:province":"AB",
    "sg:tags":[
        "field",
        "oil"
    ],
    "wof:name":"Tuboscope Vetco Canada Inc",
    "wof:placetype":"venue"
},
  "geometry": {"coordinates":[-114.05883,50.99218],"type":"Point"}
}