{
  "type": "Feature",
  "properties": {
    "addr:full":"1159 Notre Dame St Embrun ON K0A 1W0",
    "addr:housenumber":"1159",
    "addr:postcode":"k0a 1w0",
    "addr:street":"Notre Dame St",
    "iso:country":"CA",
    "sg:address":"1159 Notre Dame St",
    "sg:city":"Embrun",
    "sg:classifiers":[
        {
            "category":"Personal",
            "subcategory":"Beauty Salon",
            "type":"Services"
        }
    ],
    "sg:phone":"+1 613 443 1393",
    "sg:postcode":"K0A 1W0",
    "sg:province":"ON",
    "wof:name":"Esthetique Lynne Charbonneau",
    "wof:placetype":"venue"
},
  "geometry": {"coordinates":[-75.263451,45.27597],"type":"Point"}
}