{
  "type": "Feature",
  "properties": {
    "iso:country":"CA",
    "sg:address":"132 3rd St W",
    "sg:city":"North Vancouver",
    "sg:classifiers":[
        {
            "category":"Restaurant",
            "type":"Food & Drink"
        }
    ],
    "sg:phone":"+1 604 980 0331",
    "sg:postcode":"V7M 1E8",
    "sg:province":"BC",
    "wof:name":"Pasparos Taverna",
    "wof:placetype":"venue"
},
  "geometry": {"coordinates":[-123.078025818,49.3140602112],"type":"Point"}
}