{
  "type": "Feature",
  "properties": {
    "iso:country":"CA",
    "sg:city":"Regina",
    "sg:classifiers":[
        {
            "category":"Real Estate",
            "subcategory":"Real Estate Operator",
            "type":"Services"
        }
    ],
    "sg:phone":"+1 306 525 3751",
    "sg:postcode":"S4P 3X9",
    "sg:province":"SK",
    "sg:tags":[
        "apartment"
    ],
    "wof:name":"Cornwall Apartments",
    "wof:placetype":"venue"
},
  "geometry": {"coordinates":[-104.612030029,50.446937561],"type":"Point"}
}