{
  "type": "Feature",
  "properties": {
    "addr:full":"3 E Main St Welland ON L3B 3W4",
    "addr:housenumber":"3",
    "addr:postcode":"l3b 3w4",
    "addr:street":"E Main St",
    "iso:country":"CA",
    "sg:address":"3 E Main St",
    "sg:city":"Welland",
    "sg:classifiers":[
        {
            "category":"Professional",
            "subcategory":"Computer Services",
            "type":"Services"
        }
    ],
    "sg:phone":"+1 905 714 1400",
    "sg:postcode":"L3B 3W4",
    "sg:province":"ON",
    "sg:tags":[
        "internet"
    ],
    "wof:name":"Internet Access Worldwide",
    "wof:placetype":"venue"
},
  "geometry": {"coordinates":[-79.250221,42.991611],"type":"Point"}
}