{
  "type": "Feature",
  "properties": {
    "iso:country":"CA",
    "sg:address":"1095 Av Laframboise",
    "sg:city":"Saint-Hyacinthe",
    "sg:classifiers":[
        {
            "category":"Retail",
            "subcategory":"Self-service Laundry",
            "type":"Services"
        }
    ],
    "sg:phone":"+1 450 771 1510",
    "sg:postcode":"J2S 4W7",
    "sg:province":"QC",
    "sg:tags":[
        "cleaners"
    ],
    "wof:name":"Buandier DE LA Gare",
    "wof:placetype":"venue"
},
  "geometry": {"coordinates":[-72.94738769529999,45.6270103455],"type":"Point"}
}