{
  "type": "Feature",
  "properties": {
    "addr:full":"960 Ouellette Ave Windsor ON N9A 1C6",
    "addr:housenumber":"960",
    "addr:postcode":"n9a 1c6",
    "addr:street":"Ouellette Ave",
    "iso:country":"CA",
    "sg:address":"960 Ouellette Ave",
    "sg:city":"Windsor",
    "sg:classifiers":[
        {
            "category":"Organizations",
            "subcategory":"Professional Association",
            "type":"Services"
        }
    ],
    "sg:phone":"+1 519 256 5906",
    "sg:postcode":"N9A 1C6",
    "sg:province":"ON",
    "wof:name":"Army Cadets Royal Canadian",
    "wof:placetype":"venue"
},
  "geometry": {"coordinates":[-83.033829,42.309769],"type":"Point"}
}