{
  "type": "Feature",
  "properties": {
    "addr:full":"10612 63 St NW Edmonton AB T6A 2M6",
    "addr:housenumber":"10612",
    "addr:postcode":"t6a 2m6",
    "addr:street":"63 St Nw",
    "iso:country":"CA",
    "sg:address":"10612 63 St NW",
    "sg:city":"Edmonton",
    "sg:classifiers":[
        {
            "category":"Professional",
            "subcategory":"Accounting & Tax Preparation",
            "type":"Services"
        }
    ],
    "sg:phone":"+1 780 465 7626",
    "sg:postcode":"T6A 2M6",
    "sg:province":"AB",
    "sg:tags":[
        "return",
        "filing"
    ],
    "wof:name":"Annor Services",
    "wof:placetype":"venue"
},
  "geometry": {"coordinates":[-113.429886,53.550083],"type":"Point"}
}