{
  "type": "Feature",
  "properties": {
    "addr:full":"3-32-45-21 W 4 New Norway AB T0B 3L0",
    "addr:housenumber":"4",
    "addr:postcode":"t0b 3l0",
    "addr:street":"W",
    "iso:country":"CA",
    "sg:address":"3-32-45-21 W 4",
    "sg:city":"New Norway",
    "sg:classifiers":[
        {
            "category":"Mining & Drilling",
            "type":"Manufacturing & Wholesale Goods"
        }
    ],
    "sg:phone":"+1 780 855 3948",
    "sg:postcode":"T0B 3L0",
    "sg:province":"AB",
    "sg:tags":[
        "company",
        "oil"
    ],
    "wof:name":"Canadian Natural Resources Ltd",
    "wof:placetype":"venue"
},
  "geometry": {"coordinates":[-112.95079,52.869144],"type":"Point"}
}