{
  "type": "Feature",
  "properties": {
    "iso:country":"CA",
    "sg:address":"4655 Montee Gagnon",
    "sg:city":"Terrebonne",
    "sg:classifiers":[
        {
            "category":"Building & Trades",
            "subcategory":"Construction",
            "type":"Services"
        }
    ],
    "sg:phone":"+1 450 430 3229",
    "sg:postcode":"J6Y 1J4",
    "sg:province":"QC",
    "sg:tags":[
        "repairing",
        "remodeling",
        "contractor"
    ],
    "wof:name":"Sablage Au Jet Inc",
    "wof:placetype":"venue"
},
  "geometry": {"coordinates":[-73.81903076170001,45.7124290466],"type":"Point"}
}