{
  "type": "Feature",
  "properties": {
    "addr:full":"410 1st St E Assiniboia SK S0H 0B0",
    "addr:housenumber":"410",
    "addr:postcode":"s0h 0b0",
    "addr:street":"1St St E Assiniboia",
    "iso:country":"CA",
    "sg:address":"410 1st St E",
    "sg:city":"Assiniboia",
    "sg:classifiers":[
        {
            "category":"Manufacturing",
            "subcategory":"Printing",
            "type":"Manufacturing & Wholesale Goods"
        }
    ],
    "sg:phone":"+1 306 642 5901",
    "sg:postcode":"S0H 0B0",
    "sg:province":"SK",
    "sg:tags":[
        "newspaper"
    ],
    "wof:name":"Assiniboia Times",
    "wof:placetype":"venue"
},
  "geometry": {"coordinates":[-105.985366821,49.6329612732],"type":"Point"}
}