{
  "type": "Feature",
  "properties": {
    "iso:country":"CA",
    "sg:address":"410 1st St E",
    "sg:city":"Assiniboia",
    "sg:classifiers":[
        {
            "category":"Manufacturing",
            "subcategory":"Printing",
            "type":"Manufacturing & Wholesale Goods"
        }
    ],
    "sg:phone":"+1 306 642 5901",
    "sg:postcode":"S0H 0B0",
    "sg:province":"SK",
    "sg:tags":[
        "newspaper"
    ],
    "wof:name":"Assiniboia Times",
    "wof:placetype":"venue"
},
  "geometry": {"coordinates":[-105.985366821,49.6329612732],"type":"Point"}
}