{
  "type": "Feature",
  "properties": {
    "addr:full":"Malartic QC J0Y 1Z0",
    "addr:postcode":"j0y 1z0",
    "iso:country":"CA",
    "sg:city":"Malartic",
    "sg:classifiers":[
        {
            "category":"Health Services",
            "subcategory":"Medical Lab",
            "type":"Services"
        }
    ],
    "sg:phone":"+1 819 757 3232",
    "sg:postcode":"J0Y 1Z0",
    "sg:province":"QC",
    "wof:name":"Clinique DE Protheses Dentaire",
    "wof:placetype":"venue"
},
  "geometry": {"coordinates":[-78.120293,48.134289],"type":"Point"}
}