{
  "type": "Feature",
  "properties": {
    "addr:full":"53448 Range Road 222 Ardrossan AB T8E 2M5",
    "addr:housenumber":"53448",
    "addr:postcode":"t8e 2m5",
    "addr:street":"Range Road 222",
    "iso:country":"CA",
    "sg:address":"53448 Range Road 222",
    "sg:city":"Ardrossan",
    "sg:classifiers":[
        {
            "category":"Retail",
            "subcategory":"Animal Services",
            "type":"Services"
        }
    ],
    "sg:phone":"+1 780 922 5723",
    "sg:postcode":"T8E 2M5",
    "sg:province":"AB",
    "sg:tags":[
        "pet",
        "boarding",
        "sitting"
    ],
    "wof:name":"Aminta Kennels",
    "wof:placetype":"venue"
},
  "geometry": {"coordinates":[-113.14791870099999,53.5675582886],"type":"Point"}
}