{
  "type": "Feature",
  "properties": {
    "addr:full":"1314 Rue Saint-Antoine O Montreal QC H3C 1C2",
    "addr:housenumber":"1314",
    "addr:postcode":"h3c 1c2",
    "addr:street":"Rue Saint-Antoine O",
    "iso:country":"CA",
    "sg:address":"1314 Rue Saint-Antoine O",
    "sg:city":"Montreal",
    "sg:classifiers":[
        {
            "category":"Personal",
            "subcategory":"Barber",
            "type":"Services"
        }
    ],
    "sg:phone":"+1 514 933 0300",
    "sg:postcode":"H3C 1C2",
    "sg:province":"QC",
    "wof:name":"P Sudayan Barber Shop",
    "wof:placetype":"venue"
},
  "geometry": {"coordinates":[-73.56921386720001,45.4948196411],"type":"Point"}
}