{
  "type": "Feature",
  "properties": {
    "addr:full":"Mississauga ON L5N 7K2",
    "addr:postcode":"l5n 7k2",
    "iso:country":"CA",
    "sg:city":"Mississauga",
    "sg:classifiers":[
        {
            "category":"Shopping",
            "type":"Retail Goods"
        }
    ],
    "sg:phone":"+1 905 821 3242",
    "sg:postcode":"L5N 7K2",
    "sg:province":"ON",
    "sg:tags":[
        "equipment",
        "care",
        "health",
        "home"
    ],
    "wof:name":"Victorian Order of Nurses",
    "wof:placetype":"venue"
},
  "geometry": {"coordinates":[-79.744011,43.600777],"type":"Point"}
}