{
  "type": "Feature",
  "properties": {
    "addr:full":"1 MI NE Side Hwy 368 St Brieux SK S0K 3V0",
    "addr:postcode":"s0k 3v0",
    "addr:street":"1 Mi Ne Side Hwy 368 St",
    "iso:country":"CA",
    "sg:address":"1 MI NE Side Hwy 368",
    "sg:city":"St Brieux",
    "sg:classifiers":[
        {
            "category":"Wholesale",
            "subcategory":"Machinery & Supplies",
            "type":"Manufacturing & Wholesale Goods"
        }
    ],
    "sg:phone":"+1 306 275 2300",
    "sg:postcode":"S0K 3V0",
    "sg:province":"SK",
    "sg:tags":[
        "agricultural",
        "implement"
    ],
    "wof:name":"Bourgault Industries",
    "wof:placetype":"venue"
},
  "geometry": {"coordinates":[-104.89115099999999,52.638451],"type":"Point"}
}