{
  "type": "Feature",
  "properties": {
    "iso:country":"CA",
    "sg:city":"Saint-Georges",
    "sg:classifiers":[
        {
            "category":"Shopping",
            "subcategory":"Clothing, Apparel, & Fashions",
            "type":"Retail Goods"
        }
    ],
    "sg:phone":"+1 418 228 8877",
    "sg:postcode":"G5Y 5L6",
    "sg:province":"QC",
    "wof:name":"Boutique Ainsi-Soit-Elle",
    "wof:placetype":"venue"
},
  "geometry": {"coordinates":[-70.69873046879999,46.1320381165],"type":"Point"}
}