{
  "type": "Feature",
  "properties": {
    "addr:full":"111 Main St Carlyle SK S0C 0R0",
    "addr:housenumber":"111",
    "addr:postcode":"s0c 0r0",
    "addr:street":"Main St",
    "iso:country":"CA",
    "sg:address":"111 Main St",
    "sg:city":"Carlyle",
    "sg:classifiers":[
        {
            "category":"Recreation",
            "type":"Entertainment"
        }
    ],
    "sg:phone":"+1 306 453 2331",
    "sg:postcode":"S0C 0R0",
    "sg:province":"SK",
    "sg:tags":[
        "hall",
        "auditorium"
    ],
    "wof:name":"Carlyle Memorial Hall",
    "wof:placetype":"venue"
},
  "geometry": {"coordinates":[-102.266235352,49.6348190308],"type":"Point"}
}