{
  "type": "Feature",
  "properties": {
    "addr:full":"2544 Sharon Cres Mississauga ON L5C 1Y8",
    "addr:housenumber":"2544",
    "addr:postcode":"l5c 1y8",
    "addr:street":"Sharon Cres",
    "iso:country":"CA",
    "sg:address":"2544 Sharon Cres",
    "sg:city":"Mississauga",
    "sg:classifiers":[
        {
            "category":"Freight",
            "type":"Transportation"
        }
    ],
    "sg:phone":"+1 905 273 4103",
    "sg:postcode":"L5C 1Y8",
    "sg:province":"ON",
    "sg:tags":[
        "cartage",
        "trucking"
    ],
    "wof:name":"Bear Trail Xpress",
    "wof:placetype":"venue"
},
  "geometry": {"coordinates":[-79.64093800000001,43.554298],"type":"Point"}
}