{
  "type": "Feature",
  "properties": {
    "addr:full":"Mississauga ON L4T 4J2",
    "addr:postcode":"l4t 4j2",
    "iso:country":"CA",
    "sg:city":"Mississauga",
    "sg:classifiers":[
        {
            "category":"Organizations",
            "subcategory":"Membership Organization",
            "type":"Services"
        }
    ],
    "sg:phone":"+1 905 678 9691",
    "sg:postcode":"L4T 4J2",
    "sg:province":"ON",
    "wof:name":"B'Nai Brith Halton Peel",
    "wof:placetype":"venue"
},
  "geometry": {"coordinates":[-79.64028167719999,43.7197036743],"type":"Point"}
}