{
  "type": "Feature",
  "properties": {
    "addr:full":"91 English Dr Moncton NB E1E 3X3",
    "addr:housenumber":"91",
    "addr:postcode":"e1e 3x3",
    "addr:street":"English Dr",
    "iso:country":"CA",
    "sg:address":"91 English Dr",
    "sg:city":"Moncton",
    "sg:classifiers":[
        {
            "category":"Freight",
            "type":"Transportation"
        }
    ],
    "sg:phone":"+1 506 857 8170",
    "sg:postcode":"E1E 3X3",
    "sg:province":"NB",
    "sg:tags":[
        "trucking"
    ],
    "wof:name":"Consolidated Fastfrate",
    "wof:placetype":"venue"
},
  "geometry": {"coordinates":[-64.8402252197,46.0810661316],"type":"Point"}
}