{
  "type": "Feature",
  "properties": {
    "addr:full":"Cote Saint-Luc QC H4W 2V2",
    "addr:postcode":"h4w 2v2",
    "addr:street":"Cote Saint-Luc",
    "iso:country":"CA",
    "sg:city":"Cote Saint-Luc",
    "sg:classifiers":[
        {
            "category":"Health Services",
            "subcategory":"Health Practitioner",
            "type":"Services"
        }
    ],
    "sg:phone":"+1 514 481 6799",
    "sg:postcode":"H4W 2V2",
    "sg:province":"QC",
    "sg:tags":[
        "psychotherapist"
    ],
    "wof:name":"Silver, Randa",
    "wof:placetype":"venue"
},
  "geometry": {"coordinates":[-73.66065999999999,45.476589],"type":"Point"}
}