{
  "type": "Feature",
  "properties": {
    "addr:full":"General Delivery Macdiarmid ON P0T 2B0",
    "addr:postcode":"p0t 2b0",
    "iso:country":"CA",
    "sg:address":"General Delivery",
    "sg:city":"Macdiarmid",
    "sg:classifiers":[
        {
            "category":"Government",
            "subcategory":"Office",
            "type":"Public Place"
        }
    ],
    "sg:phone":"+1 807 885 3401",
    "sg:postcode":"P0T 2B0",
    "sg:province":"ON",
    "wof:name":"Rocky Bay Economic & Emplymnt",
    "wof:placetype":"venue"
},
  "geometry": {"coordinates":[-88.129738,49.43639],"type":"Point"}
}