{
  "type": "Feature",
  "properties": {
    "addr:full":"Charlesbourg QC G1H 6Z5",
    "addr:postcode":"g1h 6z5",
    "iso:country":"CA",
    "sg:city":"Charlesbourg",
    "sg:classifiers":[
        {
            "category":"Education",
            "subcategory":"Special Training",
            "type":"Public Place"
        }
    ],
    "sg:phone":"+1 418 626 2811",
    "sg:postcode":"G1H 6Z5",
    "sg:province":"QC",
    "sg:tags":[
        "school",
        "massage"
    ],
    "wof:name":"Ecole DE Massotherapie",
    "wof:placetype":"venue"
},
  "geometry": {"coordinates":[-71.240227,46.850819],"type":"Point"}
}