{
  "type": "Feature",
  "properties": {
    "addr:full":"550 Av Orly Dorval QC H9P 1E9",
    "addr:housenumber":"550",
    "addr:postcode":"h9p 1e9",
    "addr:street":"Av Orly",
    "iso:country":"CA",
    "sg:address":"550 Av Orly",
    "sg:city":"Dorval",
    "sg:classifiers":[
        {
            "category":"Manufacturing",
            "subcategory":"Metals",
            "type":"Manufacturing & Wholesale Goods"
        }
    ],
    "sg:phone":"+1 514 420 1040",
    "sg:postcode":"H9P 1E9",
    "sg:province":"QC",
    "sg:tags":[
        "steel"
    ],
    "wof:name":"Acier Aeroport Ltee",
    "wof:placetype":"venue"
},
  "geometry": {"coordinates":[-73.7314987183,45.452671051],"type":"Point"}
}