{
  "type": "Feature",
  "properties": {
    "addr:full":"2145 Gordon St Innisfil ON L9S 1C5",
    "addr:housenumber":"2145",
    "addr:postcode":"l9s 1c5",
    "addr:street":"Gordon St",
    "iso:country":"CA",
    "sg:address":"2145 Gordon St",
    "sg:city":"Innisfil",
    "sg:classifiers":[
        {
            "category":"Building & Trades",
            "subcategory":"Construction",
            "type":"Services"
        }
    ],
    "sg:phone":"+1 705 436 7755",
    "sg:postcode":"L9S 1C5",
    "sg:province":"ON",
    "sg:tags":[
        "resurfacing",
        "laying",
        "refinishing",
        "floor"
    ],
    "wof:name":"R & D Hardwood Floors",
    "wof:placetype":"venue"
},
  "geometry": {"coordinates":[-79.616119,44.321079],"type":"Point"}
}