{
  "type": "Feature",
  "properties": {
    "addr:full":"4865 Leslie St North York ON M2J 2K8",
    "addr:housenumber":"4865",
    "addr:postcode":"m2j 2k8",
    "addr:street":"Leslie St",
    "iso:country":"CA",
    "sg:address":"4865 Leslie St",
    "sg:city":"North York",
    "sg:classifiers":[
        {
            "category":"Shopping",
            "subcategory":"Pharmacy",
            "type":"Retail Goods"
        }
    ],
    "sg:phone":"+1 416 493 2111",
    "sg:postcode":"M2J 2K8",
    "sg:province":"ON",
    "sg:tags":[
        "post"
    ],
    "wof:name":"Shoppers Drug Mart",
    "wof:placetype":"venue"
},
  "geometry": {"coordinates":[-79.3652877808,43.7790184021],"type":"Point"}
}