{
  "type": "Feature",
  "properties": {
    "addr:full":"2916 29 St Vernon BC V1T 5A6",
    "addr:housenumber":"2916",
    "addr:postcode":"v1t 5a6",
    "addr:street":"29 St",
    "iso:country":"CA",
    "sg:address":"2916 29 St",
    "sg:city":"Vernon",
    "sg:classifiers":[
        {
            "category":"Professional",
            "type":"Services"
        }
    ],
    "sg:phone":"+1 250 542 9897",
    "sg:postcode":"V1T 5A6",
    "sg:province":"BC",
    "sg:tags":[
        "geophysicist"
    ],
    "wof:name":"Mwh Geo-Surveys Ltd",
    "wof:placetype":"venue"
},
  "geometry": {"coordinates":[-119.269295,50.263145],"type":"Point"}
}