{
  "type": "Feature",
  "properties": {
    "iso:country":"CA",
    "sg:address":"228 Londonderry Mall NW",
    "sg:city":"Edmonton",
    "sg:classifiers":[
        {
            "category":"Utilities",
            "subcategory":"Mobile Phone",
            "type":"Services"
        }
    ],
    "sg:phone":"+1 780 473 9283",
    "sg:postcode":"T5C 3C8",
    "sg:province":"AB",
    "sg:tags":[
        "telephone",
        "cellular"
    ],
    "wof:name":"Glentel Wireless Wave",
    "wof:placetype":"venue"
},
  "geometry": {"coordinates":[-113.490371704,53.5462188721],"type":"Point"}
}