{
  "type": "Feature",
  "properties": {
    "addr:full":"341 Rue Victoria Thurso QC J0X 3B0",
    "addr:housenumber":"341",
    "addr:postcode":"j0x 3b0",
    "addr:street":"Rue Victoria",
    "iso:country":"CA",
    "sg:address":"341 Rue Victoria",
    "sg:city":"Thurso",
    "sg:classifiers":[
        {
            "category":"Health Services",
            "subcategory":"Doctor",
            "type":"Services"
        }
    ],
    "sg:phone":"+1 819 985 2583",
    "sg:postcode":"J0X 3B0",
    "sg:province":"QC",
    "sg:tags":[
        "dentist"
    ],
    "wof:name":"Clinique Dentaire Thurso",
    "wof:placetype":"venue"
},
  "geometry": {"coordinates":[-75.244766,45.596714],"type":"Point"}
}