{
  "type": "Feature",
  "properties": {
    "addr:full":"465 Morden Rd Oakville ON L6K 3W6",
    "addr:housenumber":"465",
    "addr:postcode":"l6k 3w6",
    "addr:street":"Morden Rd",
    "iso:country":"CA",
    "sg:address":"465 Morden Rd",
    "sg:city":"Oakville",
    "sg:classifiers":[
        {
            "category":"Professional",
            "subcategory":"Employment Agencies",
            "type":"Services"
        }
    ],
    "sg:phone":"+1 905 815 1600",
    "sg:postcode":"L6K 3W6",
    "sg:province":"ON",
    "sg:tags":[
        "opportunity"
    ],
    "wof:name":"Ian Martin Ltd",
    "wof:placetype":"venue"
},
  "geometry": {"coordinates":[-79.69463348390001,43.4411659241],"type":"Point"}
}