{
  "type": "Feature",
  "properties": {
    "addr:full":"Cambridge ON N3H 4W5",
    "addr:postcode":"n3h 4w5",
    "iso:country":"CA",
    "sg:city":"Cambridge",
    "sg:classifiers":[
        {
            "category":"Manufacturing",
            "subcategory":"Tools & Machinery",
            "type":"Manufacturing & Wholesale Goods"
        }
    ],
    "sg:phone":"+1 519 653 3300",
    "sg:postcode":"N3H 4W5",
    "sg:province":"ON",
    "sg:tags":[
        "machine",
        "shop"
    ],
    "wof:name":"Accurate Custom Machining",
    "wof:placetype":"venue"
},
  "geometry": {"coordinates":[-80.3296203613,43.3923988342],"type":"Point"}
}