{
  "type": "Feature",
  "properties": {
    "addr:full":"Ivry-Sur-Le-Lac QC J8C 2Z8",
    "addr:postcode":"j8c 2z8",
    "iso:country":"CA",
    "sg:city":"Ivry-Sur-Le-Lac",
    "sg:classifiers":[
        {
            "category":"Social Services",
            "type":"Services"
        }
    ],
    "sg:phone":"+1 819 326 3520",
    "sg:postcode":"J8C 2Z8",
    "sg:province":"QC",
    "sg:tags":[
        "organization",
        "rehabilitation",
        "welfare"
    ],
    "wof:name":"Pavillon Pierre-Peladeau",
    "wof:placetype":"venue"
},
  "geometry": {"coordinates":[-74.3372955322,46.0751991272],"type":"Point"}
}