{
  "type": "Feature",
  "properties": {
    "addr:full":"4140 Pheasant Run Mississauga ON L5L 2C1",
    "addr:housenumber":"4140",
    "addr:postcode":"l5l 2c1",
    "addr:street":"Pheasant Run",
    "iso:country":"CA",
    "sg:address":"4140 Pheasant Run",
    "sg:city":"Mississauga",
    "sg:classifiers":[
        {
            "category":"Education",
            "subcategory":"School",
            "type":"Public Place"
        }
    ],
    "sg:phone":"+1 905 820 2206",
    "sg:postcode":"L5L 2C1",
    "sg:province":"ON",
    "wof:name":"Pheasant Run School",
    "wof:placetype":"venue"
},
  "geometry": {"coordinates":[-79.698921,43.543396],"type":"Point"}
}