{
  "type": "Feature",
  "properties": {
    "addr:full":"7 Place DE L'Eglise Cap-Sante QC G0A 1L0",
    "addr:housenumber":"7",
    "addr:postcode":"g0a 1l0",
    "addr:street":"Place De L'Eglise Cap-Sante",
    "iso:country":"CA",
    "sg:address":"7 Place DE L'Eglise",
    "sg:city":"Cap-Sante",
    "sg:classifiers":[
        {
            "category":"Retail",
            "subcategory":"Funeral Services",
            "type":"Services"
        }
    ],
    "sg:phone":"+1 418 285 2868",
    "sg:postcode":"G0A 1L0",
    "sg:province":"QC",
    "sg:tags":[
        "director"
    ],
    "wof:name":"Roger Benoit & Fils Ltee",
    "wof:placetype":"venue"
},
  "geometry": {"coordinates":[-71.779800415,46.6758804321],"type":"Point"}
}