{
  "type": "Feature",
  "properties": {
    "addr:full":"179 Rue Principale St-Sauveur-Des-Monts QC J0R 1R0",
    "addr:housenumber":"179",
    "addr:postcode":"j0r 1r0",
    "addr:street":"Rue Principale",
    "iso:country":"CA",
    "sg:address":"179 Rue Principale",
    "sg:city":"St-Sauveur-Des-Monts",
    "sg:classifiers":[
        {
            "category":"Restaurant",
            "type":"Food & Drink"
        }
    ],
    "sg:phone":"+1 450 227 0245",
    "sg:postcode":"J0R 1R0",
    "sg:province":"QC",
    "wof:name":"Restaurant Casablanca Francais",
    "wof:placetype":"venue"
},
  "geometry": {"coordinates":[-74.155029,45.896282],"type":"Point"}
}