{
  "type": "Feature",
  "properties": {
    "addr:full":"25 Main St W # 200 Hamilton ON L8P 1H1",
    "addr:housenumber":"25;200",
    "addr:postcode":"l8p 1h1",
    "addr:street":"Main St W #",
    "iso:country":"CA",
    "sg:address":"25 Main St W # 200",
    "sg:city":"Hamilton",
    "sg:classifiers":[
        {
            "category":"Professional",
            "subcategory":"Lawyer & Legal Services",
            "type":"Services"
        }
    ],
    "sg:phone":"+1 905 777 0300",
    "sg:postcode":"L8P 1H1",
    "sg:province":"ON",
    "sg:tags":[
        "attorney"
    ],
    "wof:name":"Wynperle, Allen",
    "wof:placetype":"venue"
},
  "geometry": {"coordinates":[-79.87059021,43.2554588318],"type":"Point"}
}