{
  "type": "Feature",
  "properties": {
    "iso:country":"CA",
    "sg:address":"295 the West Mall #507",
    "sg:city":"Etobicoke",
    "sg:classifiers":[
        {
            "category":"Insurance",
            "subcategory":"Insurance Agent",
            "type":"Services"
        }
    ],
    "sg:phone":"+1 416 621 0639",
    "sg:postcode":"M9C 4Z4",
    "sg:province":"ON",
    "sg:tags":[
        "consultant"
    ],
    "wof:name":"Pitcher & Doyle Svc",
    "wof:placetype":"venue"
},
  "geometry": {"coordinates":[-79.5614395142,43.634853363],"type":"Point"}
}