{
  "type": "Feature",
  "properties": {
    "addr:full":"3615 Victoria Dr Vancouver BC V5N 5K9",
    "addr:housenumber":"3615",
    "addr:postcode":"v5n 5k9",
    "addr:street":"Victoria Dr",
    "iso:country":"CA",
    "sg:address":"3615 Victoria Dr",
    "sg:city":"Vancouver",
    "sg:classifiers":[
        {
            "category":"Retail",
            "subcategory":"Auto Repair",
            "type":"Services"
        }
    ],
    "sg:phone":"+1 604 876 8822",
    "sg:postcode":"V5N 5K9",
    "sg:province":"BC",
    "sg:tags":[
        "body",
        "automobile",
        "painting"
    ],
    "wof:name":"Uniglobe Auto Ctr",
    "wof:placetype":"venue"
},
  "geometry": {"coordinates":[-123.06616200000001,49.252647],"type":"Point"}
}