{
  "type": "Feature",
  "properties": {
    "addr:full":"1598 6th Ave Prince George BC V2L 5G7",
    "addr:housenumber":"1598",
    "addr:postcode":"v2l 5g7",
    "addr:street":"6Th Ave",
    "iso:country":"CA",
    "sg:address":"1598 6th Ave",
    "sg:city":"Prince George",
    "sg:classifiers":[
        {
            "category":"Professional",
            "subcategory":"Lawyer & Legal Services",
            "type":"Services"
        }
    ],
    "sg:phone":"+1 250 563 0681",
    "sg:postcode":"V2L 5G7",
    "sg:province":"BC",
    "sg:tags":[
        "attorney"
    ],
    "wof:name":"Matte, Terrence P",
    "wof:placetype":"venue"
},
  "geometry": {"coordinates":[-122.75252500000001,53.916107],"type":"Point"}
}