{
  "type": "Feature",
  "properties": {
    "addr:full":"901 Avenue C N Saskatoon SK S7L 1J9",
    "addr:housenumber":"901",
    "addr:postcode":"s7l 1j9",
    "addr:street":"Avenue;N",
    "iso:country":"CA",
    "sg:address":"901 Avenue C N",
    "sg:city":"Saskatoon",
    "sg:classifiers":[
        {
            "category":"Professional",
            "subcategory":"Research",
            "type":"Services"
        }
    ],
    "sg:phone":"+1 306 665 3289",
    "sg:postcode":"S7L 1J9",
    "sg:province":"SK",
    "sg:tags":[
        "environmental",
        "ecological"
    ],
    "wof:name":"Jrl Ind Hygiene Svc",
    "wof:placetype":"venue"
},
  "geometry": {"coordinates":[-106.67369100000001,52.138725],"type":"Point"}
}