{
  "type": "Feature",
  "properties": {
    "iso:country":"CA",
    "sg:address":"485 Mcallister Dr",
    "sg:city":"Saint John",
    "sg:classifiers":[
        {
            "category":"Freight",
            "type":"Transportation"
        }
    ],
    "sg:phone":"+1 506 634 8800",
    "sg:postcode":"E2J 2S8",
    "sg:province":"NB",
    "sg:tags":[
        "trucking"
    ],
    "wof:name":"Rst Industries",
    "wof:placetype":"venue"
},
  "geometry": {"coordinates":[-66.008995,45.303539],"type":"Point"}
}