{
  "type": "Feature",
  "properties": {
    "addr:full":"130 Crescent St Unity SK S0K 4L0",
    "addr:housenumber":"130",
    "addr:postcode":"s0k 4l0",
    "addr:street":"Crescent St",
    "iso:country":"CA",
    "sg:address":"130 Crescent St",
    "sg:city":"Unity",
    "sg:classifiers":[
        {
            "category":"Wholesale",
            "subcategory":"Construction Materials",
            "type":"Manufacturing & Wholesale Goods"
        }
    ],
    "sg:phone":"+1 306 228 3766",
    "sg:postcode":"S0K 4L0",
    "sg:province":"SK",
    "sg:tags":[
        "concrete",
        "sand",
        "gravel"
    ],
    "wof:name":"Greenwald Ready-Mix Ltd",
    "wof:placetype":"venue"
},
  "geometry": {"coordinates":[-109.157372,52.436474],"type":"Point"}
}