{
  "type": "Feature",
  "properties": {
    "iso:country":"CA",
    "sg:address":"19 Hutton Dr",
    "sg:city":"Belleville",
    "sg:classifiers":[
        {
            "category":"Professional",
            "type":"Services"
        }
    ],
    "sg:phone":"+1 613 962 8860",
    "sg:postcode":"K8P 1E9",
    "sg:province":"ON",
    "sg:tags":[
        "arts",
        "artist"
    ],
    "wof:name":"Gabriel Krekk Ltd Editions",
    "wof:placetype":"venue"
},
  "geometry": {"coordinates":[-77.399521,44.153038],"type":"Point"}
}