{
  "type": "Feature",
  "properties": {
    "addr:full":"1701 Rue Joliette Longueuil QC J4K 4W6",
    "addr:housenumber":"1701",
    "addr:postcode":"j4k 4w6",
    "addr:street":"Rue Joliette",
    "iso:country":"CA",
    "sg:address":"1701 Rue Joliette",
    "sg:city":"Longueuil",
    "sg:classifiers":[
        {
            "category":"Retail",
            "subcategory":"Auto Repair",
            "type":"Services"
        }
    ],
    "sg:phone":"+1 450 677 2428",
    "sg:postcode":"J4K 4W6",
    "sg:province":"QC",
    "sg:tags":[
        "body",
        "automobile",
        "painting"
    ],
    "wof:name":"Garage Sylvain Inc",
    "wof:placetype":"venue"
},
  "geometry": {"coordinates":[-73.4921875,45.522102356],"type":"Point"}
}