{
  "type": "Feature",
  "properties": {
    "addr:full":"10 Liberty St N Bowmanville ON L1C 2L4",
    "addr:housenumber":"10",
    "addr:postcode":"l1c 2l4",
    "addr:street":"Liberty St N",
    "iso:country":"CA",
    "sg:address":"10 Liberty St N",
    "sg:city":"Bowmanville",
    "sg:classifiers":[
        {
            "category":"Health Services",
            "subcategory":"Medical Lab",
            "type":"Services"
        }
    ],
    "sg:phone":"+1 905 623 4473",
    "sg:postcode":"L1C 2L4",
    "sg:province":"ON",
    "wof:name":"Bowmanville Denture Clinic",
    "wof:placetype":"venue"
},
  "geometry": {"coordinates":[-78.68068700000001,43.911106],"type":"Point"}
}