{
  "type": "Feature",
  "properties": {
    "addr:full":"460 Boul Cartier O Laval QC H7N 5J6",
    "addr:housenumber":"460",
    "addr:postcode":"h7n 5j6",
    "addr:street":"Boul Cartier O",
    "iso:country":"CA",
    "sg:address":"460 Boul Cartier O",
    "sg:city":"Laval",
    "sg:classifiers":[
        {
            "category":"Health Services",
            "subcategory":"Podiatrist",
            "type":"Services"
        }
    ],
    "sg:phone":"+1 450 681 4009",
    "sg:postcode":"H7N 5J6",
    "sg:province":"QC",
    "wof:name":"Savard, J J DPM",
    "wof:placetype":"venue"
},
  "geometry": {"coordinates":[-73.716515,45.547302],"type":"Point"}
}