{
  "type": "Feature",
  "properties": {
    "addr:full":"300 Lake St St Catharines ON L2N 4H2",
    "addr:housenumber":"300",
    "addr:postcode":"l2n 4h2",
    "addr:street":"Lake St",
    "iso:country":"CA",
    "sg:address":"300 Lake St",
    "sg:city":"St Catharines",
    "sg:classifiers":[
        {
            "category":"Shopping",
            "type":"Retail Goods"
        }
    ],
    "sg:phone":"+1 905 935 2413",
    "sg:postcode":"L2N 4H2",
    "sg:province":"ON",
    "sg:tags":[
        "picture",
        "frame",
        "art",
        "gallery",
        "dealer"
    ],
    "wof:name":"Framing & Art Ctr",
    "wof:placetype":"venue"
},
  "geometry": {"coordinates":[-79.251457,43.183395],"type":"Point"}
}