{
  "type": "Feature",
  "properties": {
    "addr:full":"20451 50 St NW Edmonton AB T5E 5S7",
    "addr:housenumber":"20451",
    "addr:postcode":"t5e 5s7",
    "addr:street":"50 St Nw",
    "iso:country":"CA",
    "sg:address":"20451 50 St NW",
    "sg:city":"Edmonton",
    "sg:classifiers":[
        {
            "category":"Retail",
            "subcategory":"Veterinary Services",
            "type":"Services"
        }
    ],
    "sg:phone":"+1 780 472 6243",
    "sg:postcode":"T5E 5S7",
    "sg:province":"AB",
    "sg:tags":[
        "veterinarian"
    ],
    "wof:name":"Bar Xo Veterinary Svc Ltd",
    "wof:placetype":"venue"
},
  "geometry": {"coordinates":[-113.417938232,53.6676635742],"type":"Point"}
}