{
  "type": "Feature",
  "properties": {
    "addr:full":"2128 Highway 311 Truro NS B2N 5B4",
    "addr:housenumber":"2128",
    "addr:postcode":"b2n 5b4",
    "addr:street":"Highway 311",
    "iso:country":"CA",
    "sg:address":"2128 Highway 311",
    "sg:city":"Truro",
    "sg:classifiers":[
        {
            "category":"Manufacturing",
            "subcategory":"Pottery",
            "type":"Manufacturing & Wholesale Goods"
        }
    ],
    "sg:phone":"+1 902 895 3131",
    "sg:postcode":"B2N 5B4",
    "sg:province":"NS",
    "sg:tags":[
        "shop",
        "gift"
    ],
    "wof:name":"Foxy Souvenirs",
    "wof:placetype":"venue"
},
  "geometry": {"coordinates":[-63.28904,45.36602],"type":"Point"}
}