{
  "type": "Feature",
  "properties": {
    "addr:full":"27 Montcalm Cres Winnipeg MB R2V 2N5",
    "addr:housenumber":"27",
    "addr:postcode":"r2v 2n5",
    "addr:street":"Montcalm Cres",
    "iso:country":"CA",
    "sg:address":"27 Montcalm Cres",
    "sg:city":"Winnipeg",
    "sg:classifiers":[
        {
            "category":"Professional",
            "subcategory":"Advertising",
            "type":"Services"
        }
    ],
    "sg:phone":"+1 204 339 6737",
    "sg:postcode":"R2V 2N5",
    "sg:province":"MB",
    "sg:tags":[
        "counselor"
    ],
    "wof:name":"Laurie A Mainster Adv Ltd",
    "wof:placetype":"venue"
},
  "geometry": {"coordinates":[-97.1392440796,49.9413909912],"type":"Point"}
}