{
  "type": "Feature",
  "properties": {
    "addr:full":"9692 Danforth E Cobourg ON K9A 4J8",
    "addr:housenumber":"9692",
    "addr:postcode":"k9a 4j8",
    "addr:street":"Danforth E",
    "iso:country":"CA",
    "sg:address":"9692 Danforth E",
    "sg:city":"Cobourg",
    "sg:classifiers":[
        {
            "category":"Insurance",
            "subcategory":"Insurance Agent",
            "type":"Services"
        }
    ],
    "sg:phone":"+1 905 373 0530",
    "sg:postcode":"K9A 4J8",
    "sg:province":"ON",
    "wof:name":"Prize Indemnity Underwriters",
    "wof:placetype":"venue"
},
  "geometry": {"coordinates":[-78.13606299999999,43.990688],"type":"Point"}
}