{
  "type": "Feature",
  "properties": {
    "addr:full":"2822 Ch Sainte-Marie Mascouche QC J7K 1N4",
    "addr:postcode":"2822;j7k 1n4",
    "addr:street":"Ch Sainte-Marie",
    "iso:country":"CA",
    "sg:address":"2822 Ch Sainte-Marie",
    "sg:city":"Mascouche",
    "sg:classifiers":[
        {
            "category":"Education",
            "subcategory":"Special Training",
            "type":"Public Place"
        }
    ],
    "sg:phone":"+1 450 471 2245",
    "sg:postcode":"J7K 1N4",
    "sg:province":"QC",
    "sg:tags":[
        "instruction",
        "driving"
    ],
    "wof:name":"Ecole DE Conduite Tecnic",
    "wof:placetype":"venue"
},
  "geometry": {"coordinates":[-73.6072921753,45.7502403259],"type":"Point"}
}