{
  "type": "Feature",
  "properties": {
    "addr:full":"101 Dover St Campbellton NB E3N 3K6",
    "addr:housenumber":"101",
    "addr:postcode":"e3n 3k6",
    "addr:street":"Dover St",
    "iso:country":"CA",
    "sg:address":"101 Dover St",
    "sg:city":"Campbellton",
    "sg:classifiers":[
        {
            "category":"Personal",
            "subcategory":"Beauty Salon",
            "type":"Services"
        }
    ],
    "sg:phone":"+1 506 753 7916",
    "sg:postcode":"E3N 3K6",
    "sg:province":"NB",
    "wof:name":"Salon Fascination Beauty Salon",
    "wof:placetype":"venue"
},
  "geometry": {"coordinates":[-66.66744199999999,47.999809],"type":"Point"}
}