{
  "type": "Feature",
  "properties": {
    "addr:full":"655 Iroquois Ave Ancaster ON L9G 3B6",
    "addr:housenumber":"655",
    "addr:postcode":"l9g 3b6",
    "addr:street":"Iroquois Ave",
    "iso:country":"CA",
    "sg:address":"655 Iroquois Ave",
    "sg:city":"Ancaster",
    "sg:classifiers":[
        {
            "category":"Building & Trades",
            "subcategory":"Cleaning & Sanitation",
            "type":"Services"
        }
    ],
    "sg:phone":"+1 905 648 0607",
    "sg:postcode":"L9G 3B6",
    "sg:province":"ON",
    "sg:tags":[
        "janitor"
    ],
    "wof:name":"Naples Janitorial Svc",
    "wof:placetype":"venue"
},
  "geometry": {"coordinates":[-79.959801,43.22905],"type":"Point"}
}