{
  "type": "Feature",
  "properties": {
    "addr:full":"375 Rue Saint-Joseph Laurier-Station QC G0S 1N0",
    "addr:housenumber":"375",
    "addr:postcode":"g0s 1n0",
    "addr:street":"Rue Saint-Joseph",
    "iso:country":"CA",
    "sg:address":"375 Rue Saint-Joseph",
    "sg:city":"Laurier-Station",
    "sg:classifiers":[
        {
            "category":"Education",
            "subcategory":"Special Training",
            "type":"Public Place"
        }
    ],
    "sg:phone":"+1 418 728 4484",
    "sg:postcode":"G0S 1N0",
    "sg:province":"QC",
    "sg:tags":[
        "school",
        "massage"
    ],
    "wof:name":"Academie Internationale DE LA",
    "wof:placetype":"venue"
},
  "geometry": {"coordinates":[-71.6312866211,46.5388832092],"type":"Point"}
}