{
  "type": "Feature",
  "properties": {
    "addr:full":"328 Rue Principale O Magog QC J1X 2A9",
    "addr:housenumber":"328",
    "addr:postcode":"j1x 2a9",
    "addr:street":"Rue Principale O",
    "iso:country":"CA",
    "sg:address":"328 Rue Principale O",
    "sg:city":"Magog",
    "sg:classifiers":[
        {
            "category":"Shopping",
            "subcategory":"Tobacco",
            "type":"Retail Goods"
        }
    ],
    "sg:phone":"+1 819 843 7222",
    "sg:postcode":"J1X 2A9",
    "sg:province":"QC",
    "sg:tags":[
        "news",
        "cigar",
        "dealer",
        "cigarette"
    ],
    "wof:name":"Tabagie & Librairie Centrale",
    "wof:placetype":"venue"
},
  "geometry": {"coordinates":[-72.13827514650001,45.2622947693],"type":"Point"}
}