{
  "type": "Feature",
  "properties": {
    "addr:full":"5498 Fraser St Vancouver BC V5W 2Z2",
    "addr:housenumber":"5498",
    "addr:postcode":"v5w 2z2",
    "addr:street":"Fraser St",
    "iso:country":"CA",
    "sg:address":"5498 Fraser St",
    "sg:city":"Vancouver",
    "sg:classifiers":[
        {
            "category":"Wholesale",
            "subcategory":"Machinery & Supplies",
            "type":"Manufacturing & Wholesale Goods"
        }
    ],
    "sg:phone":"+1 604 327 1230",
    "sg:postcode":"V5W 2Z2",
    "sg:province":"BC",
    "sg:tags":[
        "funeral",
        "monument"
    ],
    "wof:name":"W R Chandler Memorials Ltd",
    "wof:placetype":"venue"
},
  "geometry": {"coordinates":[-123.090377808,49.234916687],"type":"Point"}
}