{
  "type": "Feature",
  "properties": {
    "addr:full":"4 Bottrel St Cochrane AB T4C 1A1",
    "addr:housenumber":"4",
    "addr:postcode":"t4c 1a1",
    "addr:street":"Bottrel St",
    "iso:country":"CA",
    "sg:address":"4 Bottrel St",
    "sg:city":"Cochrane",
    "sg:classifiers":[
        {
            "category":"Shopping",
            "subcategory":"Discount & Variety Stores",
            "type":"Retail Goods"
        }
    ],
    "sg:phone":"+1 403 932 5423",
    "sg:postcode":"T4C 1A1",
    "sg:province":"AB",
    "sg:tags":[
        "merchandise",
        "general"
    ],
    "wof:name":"Bottrel General Store",
    "wof:placetype":"venue"
},
  "geometry": {"coordinates":[-114.46800231900001,51.190826416],"type":"Point"}
}