{
  "type": "Feature",
  "properties": {
    "addr:full":"12214 242 Rd Fort St John BC V1J 4H8",
    "addr:housenumber":"12214",
    "addr:postcode":"v1j 4h8",
    "addr:street":"242 Rd",
    "iso:country":"CA",
    "sg:address":"12214 242 Rd",
    "sg:city":"Fort St John",
    "sg:classifiers":[
        {
            "category":"Freight",
            "type":"Transportation"
        }
    ],
    "sg:phone":"+1 250 787 9225",
    "sg:postcode":"V1J 4H8",
    "sg:province":"BC",
    "sg:tags":[
        "commercial",
        "storage"
    ],
    "wof:name":"Country Odds 'N Ends",
    "wof:placetype":"venue"
},
  "geometry": {"coordinates":[-120.847458,56.252464],"type":"Point"}
}