{
  "type": "Feature",
  "properties": {
    "addr:full":"391 Charles Ave Renfrew ON K7V 3J2",
    "addr:housenumber":"391",
    "addr:postcode":"k7v 3j2",
    "addr:street":"Charles Ave",
    "iso:country":"CA",
    "sg:address":"391 Charles Ave",
    "sg:city":"Renfrew",
    "sg:classifiers":[
        {
            "category":"Wholesale",
            "subcategory":"Hardware",
            "type":"Manufacturing & Wholesale Goods"
        }
    ],
    "sg:phone":"+1 613 432 9286",
    "sg:postcode":"K7V 3J2",
    "sg:province":"ON",
    "sg:tags":[
        "furnace"
    ],
    "wof:name":"Tim's Burner Svc",
    "wof:placetype":"venue"
},
  "geometry": {"coordinates":[-76.679169,45.479057],"type":"Point"}
}