{
  "type": "Feature",
  "properties": {
    "addr:full":"Brampton ON L6T 5H1",
    "addr:postcode":"l6t 5h1",
    "iso:country":"CA",
    "sg:city":"Brampton",
    "sg:classifiers":[
        {
            "category":"Wholesale",
            "subcategory":"Machinery & Supplies",
            "type":"Manufacturing & Wholesale Goods"
        }
    ],
    "sg:phone":"+1 905 790 1500",
    "sg:postcode":"L6T 5H1",
    "sg:province":"ON",
    "sg:tags":[
        "janitor"
    ],
    "wof:name":"Peel Industries Inc",
    "wof:placetype":"venue"
},
  "geometry": {"coordinates":[-79.687286,43.720051],"type":"Point"}
}