{
  "type": "Feature",
  "properties": {
    "addr:full":"1470 5th Ave Valemount BC V0E 2Z0",
    "addr:housenumber":"1470",
    "addr:postcode":"v0e 2z0",
    "addr:street":"5Th Ave",
    "iso:country":"CA",
    "sg:address":"1470 5th Ave",
    "sg:city":"Valemount",
    "sg:classifiers":[
        {
            "category":"Restaurant",
            "type":"Food & Drink"
        }
    ],
    "sg:phone":"+1 250 566 4471",
    "sg:postcode":"V0E 2Z0",
    "sg:province":"BC",
    "sg:tags":[
        "motel",
        "hotel"
    ],
    "wof:name":"Alpine Inn",
    "wof:placetype":"venue"
},
  "geometry": {"coordinates":[-119.25743866000001,52.8321075439],"type":"Point"}
}