{
  "type": "Feature",
  "properties": {
    "addr:full":"883 Mulock Dr Newmarket ON L3Y 8S3",
    "addr:housenumber":"883",
    "addr:postcode":"l3y 8s3",
    "addr:street":"Mulock Dr",
    "iso:country":"CA",
    "sg:address":"883 Mulock Dr",
    "sg:city":"Newmarket",
    "sg:classifiers":[
        {
            "category":"Shopping",
            "subcategory":"Pharmacy",
            "type":"Retail Goods"
        }
    ],
    "sg:phone":"+1 905 830 5677",
    "sg:postcode":"L3Y 8S3",
    "sg:province":"ON",
    "wof:name":"College Manor Pharmacy & Well",
    "wof:placetype":"venue"
},
  "geometry": {"coordinates":[-79.436295,44.045616],"type":"Point"}
}