{
  "type": "Feature",
  "properties": {
    "addr:full":"North York ON M2N 5X3",
    "addr:postcode":"m2n 5x3",
    "iso:country":"CA",
    "sg:city":"North York",
    "sg:classifiers":[
        {
            "category":"Retail",
            "subcategory":"Photofinishing",
            "type":"Services"
        }
    ],
    "sg:phone":"+1 416 733 7699",
    "sg:postcode":"M2N 5X3",
    "sg:province":"ON",
    "sg:tags":[
        "photo",
        "finishing"
    ],
    "wof:name":"1 Hour Foto Max",
    "wof:placetype":"venue"
},
  "geometry": {"coordinates":[-79.41101837159999,43.7622680664],"type":"Point"}
}