{
  "type": "Feature",
  "properties": {
    "addr:full":"2762 Boul Saint-Charles Kirkland QC H9H 3B6",
    "addr:housenumber":"2762",
    "addr:postcode":"h9h 3b6",
    "addr:street":"Boul Saint-Charles",
    "iso:country":"CA",
    "sg:address":"2762 Boul Saint-Charles",
    "sg:city":"Kirkland",
    "sg:classifiers":[
        {
            "category":"Restaurant",
            "type":"Food & Drink"
        }
    ],
    "sg:phone":"+1 514 697 8598",
    "sg:postcode":"H9H 3B6",
    "sg:province":"QC",
    "wof:name":"Pizza Hut",
    "wof:placetype":"venue"
},
  "geometry": {"coordinates":[-73.852684021,45.4459609985],"type":"Point"}
}