{
  "type": "Feature",
  "properties": {
    "iso:country":"CA",
    "sg:city":"Fleurimont",
    "sg:classifiers":[
        {
            "category":"Shopping",
            "subcategory":"Clothing, Apparel, & Fashions",
            "type":"Retail Goods"
        }
    ],
    "sg:phone":"+1 819 821 2450",
    "sg:postcode":"J1G 4T2",
    "sg:province":"QC",
    "sg:tags":[
        "wig",
        "toupee",
        "hairpiece"
    ],
    "wof:name":"Ajustements Naturels Gosselin",
    "wof:placetype":"venue"
},
  "geometry": {"coordinates":[-71.8319854736,45.4067993164],"type":"Point"}
}