{
  "type": "Feature",
  "properties": {
    "iso:country":"CA",
    "sg:address":"29 Madison Ave",
    "sg:city":"Toronto",
    "sg:classifiers":[
        {
            "category":"Education",
            "subcategory":"School",
            "type":"Public Place"
        }
    ],
    "sg:phone":"+1 416 960 4833",
    "sg:postcode":"M5R 2S2",
    "sg:province":"ON",
    "wof:name":"School of Philosophy",
    "wof:placetype":"venue"
},
  "geometry": {"coordinates":[-79.4030456543,43.6683235168],"type":"Point"}
}