{
  "type": "Feature",
  "properties": {
    "addr:full":"Calgary AB T2M 0J7",
    "addr:postcode":"t2m 0j7",
    "iso:country":"CA",
    "sg:city":"Calgary",
    "sg:classifiers":[
        {
            "category":"Health Services",
            "subcategory":"Clinic",
            "type":"Services"
        }
    ],
    "sg:phone":"+1 403 284 5334",
    "sg:postcode":"T2M 0J7",
    "sg:province":"AB",
    "sg:tags":[
        "information",
        "dentist",
        "bureau"
    ],
    "wof:name":"A-1 Denture Clinic",
    "wof:placetype":"venue"
},
  "geometry": {"coordinates":[-114.074226,51.067101],"type":"Point"}
}