{
  "type": "Feature",
  "properties": {
    "addr:full":"34 Ch DE LA Cote Trois-Ruisseaux NB E4N 2V7",
    "addr:housenumber":"34",
    "addr:postcode":"e4n 2v7",
    "addr:street":"Ch De La Cote Trois-Ruisseaux",
    "iso:country":"CA",
    "sg:address":"34 Ch DE LA Cote",
    "sg:city":"Trois-Ruisseaux",
    "sg:classifiers":[
        {
            "category":"Building & Trades",
            "subcategory":"Construction",
            "type":"Services"
        }
    ],
    "sg:phone":"+1 506 577 4108",
    "sg:postcode":"E4N 2V7",
    "sg:province":"NB",
    "sg:tags":[
        "excavating",
        "contractor",
        "general"
    ],
    "wof:name":"Landco Construction Ltd",
    "wof:placetype":"venue"
},
  "geometry": {"coordinates":[-64.212906,46.211948],"type":"Point"}
}