{
  "type": "Feature",
  "properties": {
    "addr:full":"8600 Rue Berri Montreal QC H2P 2G4",
    "addr:housenumber":"8600",
    "addr:postcode":"h2p 2g4",
    "addr:street":"Rue Berri",
    "iso:country":"CA",
    "sg:address":"8600 Rue Berri",
    "sg:city":"Montreal",
    "sg:classifiers":[
        {
            "category":"Shopping",
            "subcategory":"Computers & Home Electronics",
            "type":"Retail Goods"
        }
    ],
    "sg:phone":"+1 514 382 0999",
    "sg:postcode":"H2P 2G4",
    "sg:province":"QC",
    "sg:tags":[
        "equipment",
        "dealer"
    ],
    "wof:name":"Cimex International Enr",
    "wof:placetype":"venue"
},
  "geometry": {"coordinates":[-73.6366271973,45.5453300476],"type":"Point"}
}