{
  "type": "Feature",
  "properties": {
    "addr:full":"293 Rue Saint-Joseph E Quebec QC G1K 3B1",
    "addr:housenumber":"293",
    "addr:postcode":"g1k 3b1",
    "addr:street":"Rue Saint-Joseph E",
    "iso:country":"CA",
    "sg:address":"293 Rue Saint-Joseph E",
    "sg:city":"Quebec",
    "sg:classifiers":[
        {
            "category":"Food & Beverages",
            "subcategory":"Groceries & Convenience Stores",
            "type":"Retail Goods"
        }
    ],
    "sg:phone":"+1 418 529 2226",
    "sg:postcode":"G1K 3B1",
    "sg:province":"QC",
    "sg:tags":[
        "grocer"
    ],
    "wof:name":"Epicerie Economique",
    "wof:placetype":"venue"
},
  "geometry": {"coordinates":[-71.22662353520001,46.8133659363],"type":"Point"}
}