{
  "type": "Feature",
  "properties": {
    "addr:full":"4940 No 3 Rd # 133 Richmond BC V6X 3A5",
    "addr:housenumber":"133",
    "addr:postcode":"4940;v6x 3a5",
    "addr:street":"No 3 Rd #",
    "iso:country":"CA",
    "sg:address":"4940 No 3 Rd # 133",
    "sg:city":"Richmond",
    "sg:classifiers":[
        {
            "category":"Travel",
            "subcategory":"Travel Agent",
            "type":"Entertainment"
        }
    ],
    "sg:phone":"+1 604 303 8161",
    "sg:postcode":"V6X 3A5",
    "sg:province":"BC",
    "sg:tags":[
        "agency",
        "bureau"
    ],
    "wof:name":"Canadian Paradise Holiday Ltd",
    "wof:placetype":"venue"
},
  "geometry": {"coordinates":[-123.13617706300001,49.1779327393],"type":"Point"}
}