{
  "type": "Feature",
  "properties": {
    "addr:full":"10659 149 St NW Edmonton AB T5P 1L9",
    "addr:housenumber":"10659",
    "addr:postcode":"t5p 1l9",
    "addr:street":"149 St Nw",
    "iso:country":"CA",
    "sg:address":"10659 149 St NW",
    "sg:city":"Edmonton",
    "sg:classifiers":[
        {
            "category":"Building & Trades",
            "subcategory":"Plumbing",
            "type":"Services"
        }
    ],
    "sg:phone":"+1 780 453 2074",
    "sg:postcode":"T5P 1L9",
    "sg:province":"AB",
    "sg:tags":[
        "heating",
        "contractor"
    ],
    "wof:name":"Ansa Heating & Contracting Ltd",
    "wof:placetype":"venue"
},
  "geometry": {"coordinates":[-113.577568054,53.5501899719],"type":"Point"}
}