{
  "type": "Feature",
  "properties": {
    "iso:country":"CA",
    "sg:address":"3000 Av Boulle",
    "sg:city":"Saint-Hyacinthe",
    "sg:classifiers":[
        {
            "category":"Education",
            "subcategory":"College",
            "type":"Public Place"
        }
    ],
    "sg:phone":"+1 450 774 2255",
    "sg:postcode":"J2S 1H9",
    "sg:province":"QC",
    "sg:tags":[
        "academic",
        "school"
    ],
    "wof:name":"Universite Du Quebec",
    "wof:placetype":"venue"
},
  "geometry": {"coordinates":[-72.974205,45.616673],"type":"Point"}
}