{
  "type": "Feature",
  "properties": {
    "addr:full":"118 10 St NW #B Calgary AB T2N 1V3",
    "addr:housenumber":"10",
    "addr:postcode":"t2n 1v3",
    "addr:street":"118;St Nw # B",
    "iso:country":"CA",
    "sg:address":"118 10 St NW #B",
    "sg:city":"Calgary",
    "sg:classifiers":[
        {
            "category":"Shopping",
            "subcategory":"Clothing, Apparel, & Fashions",
            "type":"Retail Goods"
        }
    ],
    "sg:phone":"+1 403 283 1141",
    "sg:postcode":"T2N 1V3",
    "sg:province":"AB",
    "wof:name":"Kismet Clothing",
    "wof:placetype":"venue"
},
  "geometry": {"coordinates":[-114.085739136,51.0526580811],"type":"Point"}
}