{
  "type": "Feature",
  "properties": {
    "addr:full":"Calgary AB T2R 1N7",
    "addr:postcode":"t2r 1n7",
    "iso:country":"CA",
    "sg:city":"Calgary",
    "sg:classifiers":[
        {
            "category":"Manufacturing",
            "subcategory":"Printing",
            "type":"Manufacturing & Wholesale Goods"
        }
    ],
    "sg:phone":"+1 403 209 3500",
    "sg:postcode":"T2R 1N7",
    "sg:province":"AB",
    "sg:tags":[
        "newspaper"
    ],
    "wof:name":"Nickle's Petroleum Explorer",
    "wof:placetype":"venue"
},
  "geometry": {"coordinates":[-114.081588745,51.0440330505],"type":"Point"}
}