{
  "type": "Feature",
  "properties": {
    "addr:full":"Gypsumville MB R0C 1J0",
    "addr:postcode":"r0c 1j0",
    "iso:country":"CA",
    "sg:city":"Gypsumville",
    "sg:classifiers":[
        {
            "category":"Organizations",
            "subcategory":"Professional Association",
            "type":"Services"
        }
    ],
    "sg:phone":"+1 204 659 2699",
    "sg:postcode":"R0C 1J0",
    "sg:province":"MB",
    "sg:tags":[
        "native"
    ],
    "wof:name":"Narrows Education Authority",
    "wof:placetype":"venue"
},
  "geometry": {"coordinates":[-98.6343917847,51.7704162598],"type":"Point"}
}