{
  "type": "Feature",
  "properties": {
    "addr:full":"2147 Av Du Mont-Royal E Montreal QC H2H 1J9",
    "addr:housenumber":"2147",
    "addr:postcode":"h2h 1j9",
    "addr:street":"Av Du Mont-Royal E",
    "iso:country":"CA",
    "sg:address":"2147 Av Du Mont-Royal E",
    "sg:city":"Montreal",
    "sg:classifiers":[
        {
            "category":"Food & Beverages",
            "subcategory":"Fruits & Vegetables",
            "type":"Retail Goods"
        }
    ],
    "sg:phone":"+1 514 523 8212",
    "sg:postcode":"H2H 1J9",
    "sg:province":"QC",
    "sg:tags":[
        "produce"
    ],
    "wof:name":"Fruiterie Val-Mont",
    "wof:placetype":"venue"
},
  "geometry": {"coordinates":[-73.57204400000001,45.535736],"type":"Point"}
}