{
  "type": "Feature",
  "properties": {
    "addr:full":"600 Boul Sir-Wilfrid-Laurier Beloeil QC J3G 4J2",
    "addr:housenumber":"600",
    "addr:postcode":"j3g 4j2",
    "addr:street":"Boul Sir-Wilfrid-Laurier",
    "iso:country":"CA",
    "sg:address":"600 Boul Sir-Wilfrid-Laurier",
    "sg:city":"Beloeil",
    "sg:classifiers":[
        {
            "category":"Health Services",
            "subcategory":"Optometrist",
            "type":"Services"
        }
    ],
    "sg:phone":"+1 450 464 0733",
    "sg:postcode":"J3G 4J2",
    "sg:province":"QC",
    "wof:name":"Greiche & Scaff Optometristes",
    "wof:placetype":"venue"
},
  "geometry": {"coordinates":[-73.207481,45.561615],"type":"Point"}
}