{
  "type": "Feature",
  "properties": {
    "addr:full":"829 Rue Notre Dame Embrun ON K0A 1W1",
    "addr:housenumber":"829",
    "addr:postcode":"k0a 1w1",
    "addr:street":"Rue Notre Dame",
    "iso:country":"CA",
    "sg:address":"829 Rue Notre Dame",
    "sg:city":"Embrun",
    "sg:classifiers":[
        {
            "category":"Shopping",
            "subcategory":"Clothing, Apparel, & Fashions",
            "type":"Retail Goods"
        }
    ],
    "sg:phone":"+1 613 443 1218",
    "sg:postcode":"K0A 1W1",
    "sg:province":"ON",
    "wof:name":"Vagabond",
    "wof:placetype":"venue"
},
  "geometry": {"coordinates":[-75.295242,45.269135],"type":"Point"}
}