{
  "type": "Feature",
  "properties": {
    "addr:full":"52 Rue Hervieux Le Gardeur QC J5Z 2Y5",
    "addr:housenumber":"52",
    "addr:postcode":"j5z 2y5",
    "addr:street":"Rue Hervieux;Gardeur",
    "iso:country":"CA",
    "sg:address":"52 Rue Hervieux",
    "sg:city":"Le Gardeur",
    "sg:classifiers":[
        {
            "category":"Building & Trades",
            "subcategory":"Plumbing",
            "type":"Services"
        }
    ],
    "sg:phone":"+1 450 585 2065",
    "sg:postcode":"J5Z 2Y5",
    "sg:province":"QC",
    "sg:tags":[
        "contractor"
    ],
    "wof:name":"Plomberies Jacques April Inc",
    "wof:placetype":"venue"
},
  "geometry": {"coordinates":[-73.46245574949999,45.7598342896],"type":"Point"}
}