{
  "type": "Feature",
  "properties": {
    "addr:full":"Quebec QC G2B 3K9",
    "addr:postcode":"g2b 3k9",
    "iso:country":"CA",
    "sg:city":"Quebec",
    "sg:classifiers":[
        {
            "category":"Manufacturing",
            "subcategory":"Food",
            "type":"Manufacturing & Wholesale Goods"
        }
    ],
    "sg:phone":"+1 418 840 2508",
    "sg:postcode":"G2B 3K9",
    "sg:province":"QC",
    "sg:tags":[
        "water",
        "cooler",
        "fountain",
        "filter",
        "winery"
    ],
    "wof:name":"Boutique Le Vignoble",
    "wof:placetype":"venue"
},
  "geometry": {"coordinates":[-71.3399353027,46.8249206543],"type":"Point"}
}