{
  "type": "Feature",
  "properties": {
    "iso:country":"CA",
    "sg:address":"12294 104 Ave",
    "sg:city":"Surrey",
    "sg:classifiers":[
        {
            "category":"Manufacturing",
            "subcategory":"Buildings",
            "type":"Manufacturing & Wholesale Goods"
        }
    ],
    "sg:phone":"+1 604 582 1158",
    "sg:postcode":"V3V 3H3",
    "sg:province":"BC",
    "sg:tags":[
        "home",
        "log",
        "cabin"
    ],
    "wof:name":"Arcadia Log Homes Inc",
    "wof:placetype":"venue"
},
  "geometry": {"coordinates":[-122.88111114500001,49.1917800903],"type":"Point"}
}