{
  "type": "Feature",
  "properties": {
    "iso:country":"CA",
    "sg:address":"5705 50th Ave",
    "sg:city":"Bonnyville",
    "sg:classifiers":[
        {
            "category":"Autos & Motor Vehicles",
            "subcategory":"Motorcycle Sales",
            "type":"Retail Goods"
        }
    ],
    "sg:phone":"+1 780 826 6121",
    "sg:postcode":"T9N 2L1",
    "sg:province":"AB",
    "sg:tags":[
        "all",
        "terrain"
    ],
    "wof:name":"T & T Power Sports Ltd",
    "wof:placetype":"venue"
},
  "geometry": {"coordinates":[-110.76309967,54.2685089111],"type":"Point"}
}