{
  "type": "Feature",
  "properties": {
    "addr:full":"9116 82 Ave NW Edmonton AB T6C 0Z5",
    "addr:housenumber":"9116",
    "addr:postcode":"t6c 0z5",
    "addr:street":"82 Ave Nw",
    "iso:country":"CA",
    "sg:address":"9116 82 Ave NW",
    "sg:city":"Edmonton",
    "sg:classifiers":[
        {
            "category":"Health Services",
            "subcategory":"Doctor",
            "type":"Services"
        }
    ],
    "sg:phone":"+1 780 465 0521",
    "sg:postcode":"T6C 0Z5",
    "sg:province":"AB",
    "sg:tags":[
        "physician",
        "surgeon"
    ],
    "wof:name":"Mediclinic",
    "wof:placetype":"venue"
},
  "geometry": {"coordinates":[-113.467880249,53.5182571411],"type":"Point"}
}