{
  "type": "Feature",
  "properties": {
    "addr:full":"470 Longman Cres Regina SK S4N 6J4",
    "addr:housenumber":"470",
    "addr:postcode":"s4n 6j4",
    "addr:street":"Longman Cres",
    "iso:country":"CA",
    "sg:address":"470 Longman Cres",
    "sg:city":"Regina",
    "sg:classifiers":[
        {
            "category":"Building & Trades",
            "subcategory":"Equipment Rental",
            "type":"Services"
        }
    ],
    "sg:phone":"+1 306 721 6141",
    "sg:postcode":"S4N 6J4",
    "sg:province":"SK",
    "sg:tags":[
        "crane"
    ],
    "wof:name":"J Giesbrecht & Son Cranes Ltd",
    "wof:placetype":"venue"
},
  "geometry": {"coordinates":[-104.562294006,50.4828910828],"type":"Point"}
}