{
  "type": "Feature",
  "properties": {
    "iso:country":"CA",
    "sg:address":"605 Oakwood Ave",
    "sg:city":"York",
    "sg:classifiers":[
        {
            "category":"Food & Beverages",
            "subcategory":"Groceries & Convenience Stores",
            "type":"Retail Goods"
        }
    ],
    "sg:phone":"+1 416 781 3095",
    "sg:postcode":"M6E 2X9",
    "sg:province":"ON",
    "sg:tags":[
        "grocer"
    ],
    "wof:name":"Tropical Food King",
    "wof:placetype":"venue"
},
  "geometry": {"coordinates":[-79.4424209595,43.6967201233],"type":"Point"}
}