{
  "type": "Feature",
  "properties": {
    "addr:full":"244 Rte 232 Saint-Eusebe QC G0L 2Y0",
    "addr:housenumber":"244",
    "addr:postcode":"g0l 2y0",
    "addr:street":"Rte 232 Saint-Eusebe",
    "iso:country":"CA",
    "sg:address":"244 Rte 232",
    "sg:city":"Saint-Eusebe",
    "sg:classifiers":[
        {
            "category":"Farming",
            "subcategory":"Nursery",
            "type":"Manufacturing & Wholesale Goods"
        }
    ],
    "sg:phone":"+1 418 899 2957",
    "sg:postcode":"G0L 2Y0",
    "sg:province":"QC",
    "sg:tags":[
        "greenhouse"
    ],
    "wof:name":"Serres DE LA Riviere Enr",
    "wof:placetype":"venue"
},
  "geometry": {"coordinates":[-68.95313299999999,47.552429],"type":"Point"}
}