{
  "type": "Feature",
  "properties": {
    "addr:full":"1144 the Queensway Etobicoke ON M8Z 1P7",
    "addr:housenumber":"1144",
    "addr:postcode":"m8z 1p7",
    "addr:street":"The Queensway",
    "iso:country":"CA",
    "sg:address":"1144 the Queensway",
    "sg:city":"Etobicoke",
    "sg:classifiers":[
        {
            "category":"Autos & Motor Vehicles",
            "subcategory":"Auto Supplies",
            "type":"Retail Goods"
        }
    ],
    "sg:phone":"+1 416 252 9126",
    "sg:postcode":"M8Z 1P7",
    "sg:province":"ON",
    "sg:tags":[
        "wheel",
        "cover"
    ],
    "wof:name":"Wheel Covers Unlimited",
    "wof:placetype":"venue"
},
  "geometry": {"coordinates":[-79.519867,43.622547],"type":"Point"}
}