{
  "type": "Feature",
  "properties": {
    "addr:full":"Saskatoon SK S7K 1J9",
    "addr:postcode":"s7k 1j9",
    "iso:country":"CA",
    "sg:city":"Saskatoon",
    "sg:classifiers":[
        {
            "category":"Shopping",
            "subcategory":"Jewelry",
            "type":"Retail Goods"
        }
    ],
    "sg:phone":"+1 306 652 9108",
    "sg:postcode":"S7K 1J9",
    "sg:province":"SK",
    "sg:tags":[
        "jeweler"
    ],
    "wof:name":"Peoples Jewellers",
    "wof:placetype":"venue"
},
  "geometry": {"coordinates":[-106.65933200000001,52.130508],"type":"Point"}
}