{
  "type": "Feature",
  "properties": {
    "addr:full":"8544 126 Ave NW Edmonton AB T5B 1G9",
    "addr:housenumber":"8544",
    "addr:postcode":"t5b 1g9",
    "addr:street":"126 Ave Nw",
    "iso:country":"CA",
    "sg:address":"8544 126 Ave NW",
    "sg:city":"Edmonton",
    "sg:classifiers":[
        {
            "category":"Freight",
            "type":"Transportation"
        }
    ],
    "sg:phone":"+1 780 477 8777",
    "sg:postcode":"T5B 1G9",
    "sg:province":"AB",
    "wof:name":"Hercules Forwarding Inc",
    "wof:placetype":"venue"
},
  "geometry": {"coordinates":[-113.47374000000001,53.582787],"type":"Point"}
}