{
  "type": "Feature",
  "properties": {
    "iso:country":"CA",
    "sg:address":"1300 Rue Marchand",
    "sg:city":"Drummondville",
    "sg:classifiers":[
        {
            "category":"Banks & Credit Unions",
            "subcategory":"Bank",
            "type":"Services"
        }
    ],
    "sg:phone":"+1 819 471 4667",
    "sg:postcode":"J2C 7S5",
    "sg:province":"QC",
    "sg:tags":[
        "loan",
        "real estate"
    ],
    "wof:name":"Multi-Prets Hypotheques",
    "wof:placetype":"venue"
},
  "geometry": {"coordinates":[-72.5021820068,45.8692970276],"type":"Point"}
}