{
  "type": "Feature",
  "properties": {
    "iso:country":"CA",
    "sg:city":"Vancouver",
    "sg:classifiers":[
        {
            "category":"Banks & Credit Unions",
            "subcategory":"Investment Brokerage",
            "type":"Services"
        }
    ],
    "sg:phone":"+1 604 688 1779",
    "sg:postcode":"V6E 4M3",
    "sg:province":"BC",
    "wof:name":"Wesbild Holdings Ltd",
    "wof:placetype":"venue"
},
  "geometry": {"coordinates":[-123.123336792,49.2860832214],"type":"Point"}
}