{
  "type": "Feature",
  "properties": {
    "addr:full":"221 Weber St N Waterloo ON N2J 3H5",
    "addr:housenumber":"221",
    "addr:postcode":"n2j 3h5",
    "addr:street":"Weber St N",
    "iso:country":"CA",
    "sg:address":"221 Weber St N",
    "sg:city":"Waterloo",
    "sg:classifiers":[
        {
            "category":"Restaurant",
            "type":"Food & Drink"
        }
    ],
    "sg:phone":"+1 519 746 2728",
    "sg:postcode":"N2J 3H5",
    "sg:province":"ON",
    "wof:name":"Wendy's",
    "wof:placetype":"venue"
},
  "geometry": {"coordinates":[-80.51903533940001,43.4769058228],"type":"Point"}
}