{
  "type": "Feature",
  "properties": {
    "addr:full":"Laval QC H7T 1C8",
    "addr:postcode":"h7t 1c8",
    "iso:country":"CA",
    "sg:city":"Laval",
    "sg:classifiers":[
        {
            "category":"Shopping",
            "subcategory":"Clothing, Apparel, & Fashions",
            "type":"Retail Goods"
        }
    ],
    "sg:phone":"+1 450 687 6399",
    "sg:postcode":"H7T 1C8",
    "sg:province":"QC",
    "sg:tags":[
        "item",
        "boutique"
    ],
    "wof:name":"Mexx Canada Inc",
    "wof:placetype":"venue"
},
  "geometry": {"coordinates":[-73.75048828120001,45.5681304932],"type":"Point"}
}