{
  "type": "Feature",
  "properties": {
    "addr:full":"380 Scott St St Catharines ON L2M 3W4",
    "addr:housenumber":"380",
    "addr:postcode":"l2m 3w4",
    "addr:street":"Scott St",
    "iso:country":"CA",
    "sg:address":"380 Scott St",
    "sg:city":"St Catharines",
    "sg:classifiers":[
        {
            "category":"Banks & Credit Unions",
            "subcategory":"Bank",
            "type":"Services"
        }
    ],
    "sg:phone":"+1 905 934 4303",
    "sg:postcode":"L2M 3W4",
    "sg:province":"ON",
    "wof:name":"Royal Bank Financial Group",
    "wof:placetype":"venue"
},
  "geometry": {"coordinates":[-79.228409,43.189007],"type":"Point"}
}