{
  "type": "Feature",
  "properties": {
    "addr:full":"3 Simpson Rd Bolton ON L7E 1E4",
    "addr:housenumber":"3",
    "addr:postcode":"l7e 1e4",
    "addr:street":"Simpson Rd",
    "iso:country":"CA",
    "sg:address":"3 Simpson Rd",
    "sg:city":"Bolton",
    "sg:classifiers":[
        {
            "category":"Building & Trades",
            "subcategory":"Construction",
            "type":"Services"
        }
    ],
    "sg:phone":"+1 905 857 8579",
    "sg:postcode":"L7E 1E4",
    "sg:province":"ON",
    "sg:tags":[
        "concrete"
    ],
    "wof:name":"Italform Structures",
    "wof:placetype":"venue"
},
  "geometry": {"coordinates":[-79.727554,43.862099],"type":"Point"}
}