{
  "type": "Feature",
  "properties": {
    "addr:full":"555 Yonge St Toronto ON M4Y 3A6",
    "addr:housenumber":"555",
    "addr:postcode":"m4y 3a6",
    "addr:street":"Yonge St",
    "iso:country":"CA",
    "sg:address":"555 Yonge St",
    "sg:city":"Toronto",
    "sg:classifiers":[
        {
            "category":"Banks & Credit Unions",
            "subcategory":"Bank",
            "type":"Services"
        }
    ],
    "sg:phone":"+1 416 515 2800",
    "sg:postcode":"M4Y 3A6",
    "sg:province":"ON",
    "wof:name":"Scotiabank",
    "wof:placetype":"venue"
},
  "geometry": {"coordinates":[-79.38436900000001,43.664822],"type":"Point"}
}