{
  "type": "Feature",
  "properties": {
    "addr:full":"515 Talbot St E Aylmer ON N5H 2W1",
    "addr:housenumber":"515",
    "addr:postcode":"n5h 2w1",
    "addr:street":"Talbot St E",
    "iso:country":"CA",
    "sg:address":"515 Talbot St E",
    "sg:city":"Aylmer",
    "sg:classifiers":[
        {
            "category":"Autos & Motor Vehicles",
            "subcategory":"Fuel & Gas Station",
            "type":"Retail Goods"
        }
    ],
    "sg:phone":"+1 519 773 2994",
    "sg:postcode":"N5H 2W1",
    "sg:province":"ON",
    "sg:tags":[
        "oil"
    ],
    "wof:name":"Sunoco",
    "wof:placetype":"venue"
},
  "geometry": {"coordinates":[-80.997032,42.773335],"type":"Point"}
}