{
  "type": "Feature",
  "properties": {
    "addr:full":"Clearwater BC V0E 1N0",
    "addr:postcode":"v0e 1n0",
    "iso:country":"CA",
    "sg:city":"Clearwater",
    "sg:classifiers":[
        {
            "category":"Manufacturing",
            "subcategory":"Signs",
            "type":"Manufacturing & Wholesale Goods"
        }
    ],
    "sg:phone":"+1 250 674 2735",
    "sg:postcode":"V0E 1N0",
    "sg:province":"BC",
    "wof:name":"Colonica Signs & Off Road Spec",
    "wof:placetype":"venue"
},
  "geometry": {"coordinates":[-120.034820557,51.6509246826],"type":"Point"}
}