{
  "type": "Feature",
  "properties": {
    "iso:country":"CA",
    "sg:address":"707 East Main St",
    "sg:city":"Welland",
    "sg:classifiers":[
        {
            "category":"Insurance",
            "subcategory":"Insurance Agent",
            "type":"Services"
        }
    ],
    "sg:phone":"+1 905 788 9966",
    "sg:postcode":"L3B 3Y5",
    "sg:province":"ON",
    "sg:tags":[
        "consultant",
        "planning",
        "financial"
    ],
    "wof:name":"King Prior Financial Svc Inc",
    "wof:placetype":"venue"
},
  "geometry": {"coordinates":[-79.2330627441,42.9933547974],"type":"Point"}
}