{
  "type": "Feature",
  "properties": {
    "addr:full":"105 Charing Cross St Brantford ON N3R 2H8",
    "addr:housenumber":"105",
    "addr:postcode":"n3r 2h8",
    "addr:street":"Charing Cross St",
    "iso:country":"CA",
    "sg:address":"105 Charing Cross St",
    "sg:city":"Brantford",
    "sg:classifiers":[
        {
            "category":"Education",
            "subcategory":"Special Training",
            "type":"Public Place"
        }
    ],
    "sg:phone":"+1 519 753 8805",
    "sg:postcode":"N3R 2H8",
    "sg:province":"ON",
    "sg:tags":[
        "instruction",
        "driving"
    ],
    "wof:name":"Abc Driving Academy",
    "wof:placetype":"venue"
},
  "geometry": {"coordinates":[-80.26535800000001,43.15963],"type":"Point"}
}