{
  "type": "Feature",
  "properties": {
    "iso:country":"CA",
    "sg:address":"1212 Av Greene",
    "sg:city":"Westmount",
    "sg:classifiers":[
        {
            "category":"Shopping",
            "subcategory":"Gifts & Souvenirs",
            "type":"Retail Goods"
        }
    ],
    "sg:phone":"+1 514 932 9977",
    "sg:postcode":"H3Z 2A3",
    "sg:province":"QC",
    "sg:tags":[
        "shop"
    ],
    "wof:name":"Boutique Marie Dumas",
    "wof:placetype":"venue"
},
  "geometry": {"coordinates":[-73.588264,45.486176],"type":"Point"}
}