{
  "type": "Feature",
  "properties": {
    "addr:full":"498 25E Av Saint-Eustache QC J7R 4K3",
    "addr:housenumber":"498",
    "addr:postcode":"j7r 4k3",
    "addr:street":"25E Av Saint-Eustache",
    "iso:country":"CA",
    "sg:address":"498 25E Av",
    "sg:city":"Saint-Eustache",
    "sg:classifiers":[
        {
            "category":"Building & Trades",
            "subcategory":"Construction",
            "type":"Services"
        }
    ],
    "sg:phone":"+1 450 472 1653",
    "sg:postcode":"J7R 4K3",
    "sg:province":"QC",
    "sg:tags":[
        "excavating",
        "contractor"
    ],
    "wof:name":"Excavation Nordel Inc",
    "wof:placetype":"venue"
},
  "geometry": {"coordinates":[-73.888901,45.558048],"type":"Point"}
}