{
  "type": "Feature",
  "properties": {
    "addr:full":"RR 1 STN Main Spruce View AB T0M 1V0",
    "addr:postcode":"t0m 1v0",
    "addr:street":"Rr 1 Stn Main",
    "iso:country":"CA",
    "sg:address":"RR 1 STN Main",
    "sg:city":"Spruce View",
    "sg:classifiers":[
        {
            "category":"Utilities",
            "subcategory":"Electric",
            "type":"Services"
        }
    ],
    "sg:phone":"+1 403 728 3111",
    "sg:postcode":"T0M 1V0",
    "sg:province":"AB",
    "sg:tags":[
        "company"
    ],
    "wof:name":"Dickson Dam Powerhouse",
    "wof:placetype":"venue"
},
  "geometry": {"coordinates":[-114.334075928,52.0862350464],"type":"Point"}
}