{
  "type": "Feature",
  "properties": {
    "addr:full":"7700 Boul Langelier Saint-Leonard QC H1S 2Z6",
    "addr:housenumber":"7700",
    "addr:postcode":"h1s 2z6",
    "addr:street":"Boul Langelier",
    "iso:country":"CA",
    "sg:address":"7700 Boul Langelier",
    "sg:city":"Saint-Leonard",
    "sg:classifiers":[
        {
            "category":"Government",
            "subcategory":"Police Station",
            "type":"Public Place"
        }
    ],
    "sg:phone":"+1 514 280 0900",
    "sg:postcode":"H1S 2Z6",
    "sg:province":"QC",
    "sg:tags":[
        "department"
    ],
    "wof:name":"St-Leonard Centre Operationnel",
    "wof:placetype":"venue"
},
  "geometry": {"coordinates":[-73.575912,45.592262],"type":"Point"}
}