{
  "type": "Feature",
  "properties": {
    "addr:full":"23 Rue Des Bocages Laval QC H7W 4Z1",
    "addr:housenumber":"23",
    "addr:postcode":"h7w 4z1",
    "addr:street":"Rue Des Bocages",
    "iso:country":"CA",
    "sg:address":"23 Rue Des Bocages",
    "sg:city":"Laval",
    "sg:classifiers":[
        {
            "category":"Professional",
            "subcategory":"Accounting & Tax Preparation",
            "type":"Services"
        }
    ],
    "sg:phone":"+1 450 688 9607",
    "sg:postcode":"H7W 4Z1",
    "sg:province":"QC",
    "sg:tags":[
        "bookkeeping",
        "general"
    ],
    "wof:name":"Professional Bookkeeping Svc",
    "wof:placetype":"venue"
},
  "geometry": {"coordinates":[-73.7583618164,45.5201377869],"type":"Point"}
}