{
  "type": "Feature",
  "properties": {
    "addr:full":"50 Falstaff Ave North York ON M6L 2C7",
    "addr:housenumber":"50",
    "addr:postcode":"m6l 2c7",
    "addr:street":"Falstaff Ave",
    "iso:country":"CA",
    "sg:address":"50 Falstaff Ave",
    "sg:city":"North York",
    "sg:classifiers":[
        {
            "category":"Recreation",
            "type":"Entertainment"
        }
    ],
    "sg:phone":"+1 416 395 7924",
    "sg:postcode":"M6L 2C7",
    "sg:province":"ON",
    "sg:tags":[
        "government",
        "hall",
        "auditorium"
    ],
    "wof:name":"Falstaff Community Ctr",
    "wof:placetype":"venue"
},
  "geometry": {"coordinates":[-79.50505800000001,43.715813],"type":"Point"}
}