{
  "type": "Feature",
  "properties": {
    "iso:country":"CA",
    "sg:city":"Montreal",
    "sg:classifiers":[
        {
            "category":"Manufacturing",
            "subcategory":"Furniture",
            "type":"Manufacturing & Wholesale Goods"
        }
    ],
    "sg:phone":"+1 514 868 6666",
    "sg:postcode":"H2Z 1G2",
    "sg:province":"QC",
    "sg:tags":[
        "exposition",
        "stand"
    ],
    "wof:name":"Freeman Decorateur",
    "wof:placetype":"venue"
},
  "geometry": {"coordinates":[-73.55735,45.509602],"type":"Point"}
}