{
  "type": "Feature",
  "properties": {
    "iso:country":"CA",
    "sg:address":"120 Rang Bayonne Rivi N",
    "sg:city":"Berthierville",
    "sg:classifiers":[
        {
            "category":"Travel",
            "subcategory":"Hotels & Motels",
            "type":"Entertainment"
        }
    ],
    "sg:phone":"+1 450 836 1129",
    "sg:postcode":"J0K 1A0",
    "sg:province":"QC",
    "wof:name":"Manoir DE LA Tourelle",
    "wof:placetype":"venue"
},
  "geometry": {"coordinates":[-73.1784667969,46.0809059143],"type":"Point"}
}