{
  "type": "Feature",
  "properties": {
    "iso:country":"CA",
    "sg:address":"609 James St N",
    "sg:city":"Thunder Bay",
    "sg:classifiers":[
        {
            "category":"Professional",
            "type":"Services"
        }
    ],
    "sg:phone":"+1 807 628 9775",
    "sg:postcode":"P7C 5Z7",
    "sg:province":"ON",
    "sg:tags":[
        "martial",
        "arts",
        "instruction",
        "establishment"
    ],
    "wof:name":"Northwest Combative Arts Acdmy",
    "wof:placetype":"venue"
},
  "geometry": {"coordinates":[-89.2897644043,48.397315979],"type":"Point"}
}