{
  "type": "Feature",
  "properties": {
    "iso:country":"CA",
    "sg:address":"1150 Dundas St W",
    "sg:city":"Oakville",
    "sg:classifiers":[
        {
            "category":"Organizations",
            "subcategory":"Religious Organization",
            "type":"Services"
        }
    ],
    "sg:phone":"+1 905 257 2770",
    "sg:postcode":"L6H 7E4",
    "sg:province":"ON",
    "sg:tags":[
        "church"
    ],
    "wof:name":"Knox Presbyterian Church 16",
    "wof:placetype":"venue"
},
  "geometry": {"coordinates":[-79.7092208862,43.4971046448],"type":"Point"}
}