{
  "type": "Feature",
  "properties": {
    "addr:full":"4607 Lazelle Ave Terrace BC V8G 1S3",
    "addr:housenumber":"4607",
    "addr:postcode":"v8g 1s3",
    "addr:street":"Lazelle Ave",
    "iso:country":"CA",
    "sg:address":"4607 Lazelle Ave",
    "sg:city":"Terrace",
    "sg:classifiers":[
        {
            "category":"Shopping",
            "subcategory":"Books",
            "type":"Retail Goods"
        }
    ],
    "sg:phone":"+1 250 635 3803",
    "sg:postcode":"V8G 1S3",
    "sg:province":"BC",
    "sg:tags":[
        "dealer"
    ],
    "wof:name":"Treasure House Books",
    "wof:placetype":"venue"
},
  "geometry": {"coordinates":[-128.58749399999999,54.517258],"type":"Point"}
}