{
  "type": "Feature",
  "properties": {
    "addr:full":"2350 Ch Herron Dorval QC H9S 1C5",
    "addr:postcode":"2350;h9s 1c5",
    "addr:street":"Ch Herron",
    "iso:country":"CA",
    "sg:address":"2350 Ch Herron",
    "sg:city":"Dorval",
    "sg:classifiers":[
        {
            "category":"Building & Trades",
            "subcategory":"Electrical",
            "type":"Services"
        }
    ],
    "sg:phone":"+1 514 420 0111",
    "sg:postcode":"H9S 1C5",
    "sg:province":"QC",
    "sg:tags":[
        "electric",
        "contractor"
    ],
    "wof:name":"Tri-Tech Electrique Inc",
    "wof:placetype":"venue"
},
  "geometry": {"coordinates":[-73.77797698969999,45.4489097595],"type":"Point"}
}