{
  "type": "Feature",
  "properties": {
    "addr:full":"163 Gowland Mountain Rd Elgin NB E4Z 1T3",
    "addr:housenumber":"163",
    "addr:postcode":"e4z 1t3",
    "addr:street":"Gowland Mountain Rd",
    "iso:country":"CA",
    "sg:address":"163 Gowland Mountain Rd",
    "sg:city":"Elgin",
    "sg:classifiers":[
        {
            "category":"Manufacturing",
            "subcategory":"Lumber",
            "type":"Manufacturing & Wholesale Goods"
        }
    ],
    "sg:phone":"+1 506 756 2373",
    "sg:postcode":"E4Z 1T3",
    "sg:province":"NB",
    "sg:tags":[
        "syrup",
        "maple",
        "sugar"
    ],
    "wof:name":"Canadian Syrup Inc",
    "wof:placetype":"venue"
},
  "geometry": {"coordinates":[-65.0775299072,45.7981147766],"type":"Point"}
}