{
  "type": "Feature",
  "properties": {
    "iso:country":"CA",
    "sg:address":"162 Dumoulin St",
    "sg:city":"Winnipeg",
    "sg:classifiers":[
        {
            "category":"Retail",
            "subcategory":"Auto Repair",
            "type":"Services"
        }
    ],
    "sg:phone":"+1 204 231 5444",
    "sg:postcode":"R2H 0E1",
    "sg:province":"MB",
    "sg:tags":[
        "body",
        "automobile",
        "painting"
    ],
    "wof:name":"Lester Automotive",
    "wof:placetype":"venue"
},
  "geometry": {"coordinates":[-97.1235656738,49.8926582336],"type":"Point"}
}