{
  "type": "Feature",
  "properties": {
    "addr:full":"Penticton BC V2A 8X1",
    "addr:postcode":"v2a 8x1",
    "iso:country":"CA",
    "sg:city":"Penticton",
    "sg:classifiers":[
        {
            "category":"Restaurant",
            "type":"Food & Drink"
        }
    ],
    "sg:phone":"+1 250 493 3536",
    "sg:postcode":"V2A 8X1",
    "sg:province":"BC",
    "wof:name":"Flight Deck Cafe",
    "wof:placetype":"venue"
},
  "geometry": {"coordinates":[-119.605361938,49.4612846375],"type":"Point"}
}