{
  "type": "Feature",
  "properties": {
    "addr:full":"247 Centennial Pky N Hamilton ON L8E 2X3",
    "addr:housenumber":"247",
    "addr:postcode":"l8e 2x3",
    "addr:street":"Centennial Pky N",
    "iso:country":"CA",
    "sg:address":"247 Centennial Pky N",
    "sg:city":"Hamilton",
    "sg:classifiers":[
        {
            "category":"Home & Garden",
            "subcategory":"Home Furnishings",
            "type":"Retail Goods"
        }
    ],
    "sg:phone":"+1 905 560 1244",
    "sg:postcode":"L8E 2X3",
    "sg:province":"ON",
    "sg:tags":[
        "venetian",
        "curtain",
        "drapery"
    ],
    "wof:name":"Centennial Decorating Ctr",
    "wof:placetype":"venue"
},
  "geometry": {"coordinates":[-79.760262,43.237801],"type":"Point"}
}