{
  "type": "Feature",
  "properties": {
    "addr:full":"38 Industrial Park Rd Minto NB E4B 3A5",
    "addr:housenumber":"38",
    "addr:postcode":"e4b 3a5",
    "addr:street":"Industrial Park Rd",
    "iso:country":"CA",
    "sg:address":"38 Industrial Park Rd",
    "sg:city":"Minto",
    "sg:classifiers":[
        {
            "category":"Wholesale",
            "subcategory":"Machinery & Supplies",
            "type":"Manufacturing & Wholesale Goods"
        }
    ],
    "sg:phone":"+1 506 327 4550",
    "sg:postcode":"E4B 3A5",
    "sg:province":"NB",
    "sg:tags":[
        "contractor"
    ],
    "wof:name":"Wobo Industries Ltd",
    "wof:placetype":"venue"
},
  "geometry": {"coordinates":[-66.050201,46.077209],"type":"Point"}
}