{
  "type": "Feature",
  "properties": {
    "addr:full":"Ottawa ON K1N 7B7",
    "addr:postcode":"k1n 7b7",
    "iso:country":"CA",
    "sg:city":"Ottawa",
    "sg:classifiers":[
        {
            "category":"Organizations",
            "subcategory":"Professional Association",
            "type":"Services"
        }
    ],
    "sg:phone":"+1 613 241 3080",
    "sg:postcode":"K1N 7B7",
    "sg:province":"ON",
    "wof:name":"Frequency Coordination System",
    "wof:placetype":"venue"
},
  "geometry": {"coordinates":[-75.690529,45.426689],"type":"Point"}
}