{
  "type": "Feature",
  "properties": {
    "iso:country":"CA",
    "sg:address":"27165 Fraser Hwy",
    "sg:city":"Aldergrove",
    "sg:classifiers":[
        {
            "category":"Autos & Motor Vehicles",
            "subcategory":"Auto Supplies",
            "type":"Retail Goods"
        }
    ],
    "sg:phone":"+1 604 856 3483",
    "sg:postcode":"V4W 3R1",
    "sg:province":"BC",
    "sg:tags":[
        "automobile",
        "parts"
    ],
    "wof:name":"Lordco Parts Ltd",
    "wof:placetype":"venue"
},
  "geometry": {"coordinates":[-122.471565247,49.0582618713],"type":"Point"}
}