{
  "type": "Feature",
  "properties": {
    "iso:country":"CA",
    "sg:address":"1211 King St E",
    "sg:city":"Kitchener",
    "sg:classifiers":[
        {
            "category":"Restaurant",
            "type":"Food & Drink"
        }
    ],
    "sg:phone":"+1 519 744 4682",
    "sg:postcode":"N2G 2N5",
    "sg:province":"ON",
    "wof:name":"Crock & Block Rstrnt & Tavern",
    "wof:placetype":"venue"
},
  "geometry": {"coordinates":[-80.4697341919,43.4409675598],"type":"Point"}
}