{
  "type": "Feature",
  "properties": {
    "iso:country":"CA",
    "sg:city":"Hartington",
    "sg:classifiers":[
        {
            "category":"Education",
            "subcategory":"Library",
            "type":"Public Place"
        }
    ],
    "sg:phone":"+1 613 372 2524",
    "sg:postcode":"K0H 1W0",
    "sg:province":"ON",
    "wof:name":"Hartington Branch Library",
    "wof:placetype":"venue"
},
  "geometry": {"coordinates":[-76.6686630249,44.4409065247],"type":"Point"}
}