{
  "type": "Feature",
  "properties": {
    "addr:full":"4925 Keith Ave Terrace BC V8G 1K7",
    "addr:housenumber":"4925",
    "addr:postcode":"v8g 1k7",
    "addr:street":"Keith Ave",
    "iso:country":"CA",
    "sg:address":"4925 Keith Ave",
    "sg:city":"Terrace",
    "sg:classifiers":[
        {
            "category":"Retail",
            "subcategory":"Auto Repair",
            "type":"Services"
        }
    ],
    "sg:phone":"+1 250 635 9474",
    "sg:postcode":"V8G 1K7",
    "sg:province":"BC",
    "sg:tags":[
        "repairing",
        "automobile"
    ],
    "wof:name":"Off Road Specialties Ltd",
    "wof:placetype":"venue"
},
  "geometry": {"coordinates":[-128.607223511,54.5132827759],"type":"Point"}
}