{
  "type": "Feature",
  "properties": {
    "addr:full":"622 King St Bridgewater NS B4V 1B4",
    "addr:housenumber":"622",
    "addr:postcode":"b4v 1b4",
    "addr:street":"King St",
    "iso:country":"CA",
    "sg:address":"622 King St",
    "sg:city":"Bridgewater",
    "sg:classifiers":[
        {
            "category":"Manufacturing",
            "subcategory":"Signs",
            "type":"Manufacturing & Wholesale Goods"
        }
    ],
    "sg:phone":"+1 902 527 2082",
    "sg:postcode":"B4V 1B4",
    "sg:province":"NS",
    "sg:tags":[
        "engraver"
    ],
    "wof:name":"Choice Awards & Gifts",
    "wof:placetype":"venue"
},
  "geometry": {"coordinates":[-64.519592,44.378387],"type":"Point"}
}