{
  "type": "Feature",
  "properties": {
    "addr:full":"104 Meadwell Dr Sioux Lookout ON P8T 1H4",
    "addr:housenumber":"104",
    "addr:postcode":"p8t 1h4",
    "addr:street":"Meadwell Dr",
    "iso:country":"CA",
    "sg:address":"104 Meadwell Dr",
    "sg:city":"Sioux Lookout",
    "sg:classifiers":[
        {
            "category":"Shopping",
            "subcategory":"Books",
            "type":"Retail Goods"
        }
    ],
    "sg:phone":"+1 807 737 4202",
    "sg:postcode":"P8T 1H4",
    "sg:province":"ON",
    "sg:tags":[
        "dealer"
    ],
    "wof:name":"Good News Books 'N Things",
    "wof:placetype":"venue"
},
  "geometry": {"coordinates":[-91.91476400000001,50.103016],"type":"Point"}
}