{
  "type": "Feature",
  "properties": {
    "addr:full":"1645 Gladwin Rd Abbotsford BC V2T 5Y5",
    "addr:housenumber":"1645",
    "addr:postcode":"v2t 5y5",
    "addr:street":"Gladwin Rd",
    "iso:country":"CA",
    "sg:address":"1645 Gladwin Rd",
    "sg:city":"Abbotsford",
    "sg:classifiers":[
        {
            "category":"Building & Trades",
            "subcategory":"Construction",
            "type":"Services"
        }
    ],
    "sg:phone":"+1 604 853 6964",
    "sg:postcode":"V2T 5Y5",
    "sg:province":"BC",
    "sg:tags":[
        "builder",
        "patio",
        "deck"
    ],
    "wof:name":"Frank's Total Deck",
    "wof:placetype":"venue"
},
  "geometry": {"coordinates":[-122.315659,49.031803],"type":"Point"}
}