{
  "type": "Feature",
  "properties": {
    "iso:country":"CA",
    "sg:city":"Calgary",
    "sg:classifiers":[
        {
            "category":"Personal",
            "subcategory":"Beauty Salon",
            "type":"Services"
        }
    ],
    "sg:phone":"+1 403 271 6220",
    "sg:postcode":"T2J 6W5",
    "sg:province":"AB",
    "wof:name":"Ultimate Nail Studio",
    "wof:placetype":"venue"
},
  "geometry": {"coordinates":[-114.02845764200001,50.9270553589],"type":"Point"}
}