{
  "type": "Feature",
  "properties": {
    "iso:country":"CA",
    "sg:address":"139 Main St",
    "sg:city":"Selkirk",
    "sg:classifiers":[
        {
            "category":"Retail",
            "subcategory":"Auto Repair",
            "type":"Services"
        }
    ],
    "sg:phone":"+1 204 482 9888",
    "sg:postcode":"R1A 1R2",
    "sg:province":"MB",
    "sg:tags":[
        "body",
        "automobile",
        "painting"
    ],
    "wof:name":"Boyd Autobody & Glass Ltd",
    "wof:placetype":"venue"
},
  "geometry": {"coordinates":[-96.8871002197,50.1328926086],"type":"Point"}
}