{
  "type": "Feature",
  "properties": {
    "addr:full":"200 Hebert Blvd # 10 Edmundston NB E3V 2S6",
    "addr:housenumber":"200",
    "addr:postcode":"e3v 2s6",
    "addr:street":"Hebert Blvd # 10",
    "iso:country":"CA",
    "sg:address":"200 Hebert Blvd # 10",
    "sg:city":"Edmundston",
    "sg:classifiers":[
        {
            "category":"Real Estate",
            "subcategory":"Real Estate Operator",
            "type":"Services"
        }
    ],
    "sg:phone":"+1 506 739 9373",
    "sg:postcode":"E3V 2S6",
    "sg:province":"NB",
    "sg:tags":[
        "apartment",
        "rental",
        "agency"
    ],
    "wof:name":"Campbellton Enterprise",
    "wof:placetype":"venue"
},
  "geometry": {"coordinates":[-68.31443,47.375504],"type":"Point"}
}