{
  "type": "Feature",
  "properties": {
    "iso:country":"CA",
    "sg:address":"3876 Harrowsmith Rd",
    "sg:city":"Harrowsmith",
    "sg:classifiers":[
        {
            "category":"Organizations",
            "subcategory":"Religious Organization",
            "type":"Services"
        }
    ],
    "sg:phone":"+1 613 372 1238",
    "sg:postcode":"K0H 1V0",
    "sg:province":"ON",
    "sg:tags":[
        "church"
    ],
    "wof:name":"Harrowsmith Free Methodist Chr",
    "wof:placetype":"venue"
},
  "geometry": {"coordinates":[-76.6641693115,44.4048995972],"type":"Point"}
}