{
  "type": "Feature",
  "properties": {
    "addr:full":"45 Rideau St Ottawa ON K1N 5W8",
    "addr:housenumber":"45",
    "addr:postcode":"k1n 5w8",
    "addr:street":"Rideau St",
    "iso:country":"CA",
    "sg:address":"45 Rideau St",
    "sg:city":"Ottawa",
    "sg:classifiers":[
        {
            "category":"Professional",
            "subcategory":"Management & Consulting",
            "type":"Services"
        }
    ],
    "sg:phone":"+1 613 562 4077",
    "sg:postcode":"K1N 5W8",
    "sg:province":"ON",
    "sg:tags":[
        "consultant",
        "business"
    ],
    "wof:name":"Delsys Research Group Inc",
    "wof:placetype":"venue"
},
  "geometry": {"coordinates":[-75.6919937134,45.4442138672],"type":"Point"}
}