{
  "type": "Feature",
  "properties": {
    "iso:country":"CA",
    "sg:address":"37 Tannery Rd",
    "sg:city":"Lunenburg",
    "sg:classifiers":[
        {
            "category":"Museum",
            "type":"Entertainment"
        }
    ],
    "sg:phone":"+1 902 634 2010",
    "sg:postcode":"B0J 2C0",
    "sg:province":"NS",
    "sg:tags":[
        "government"
    ],
    "wof:name":"Captain Angus J Walters House",
    "wof:placetype":"venue"
},
  "geometry": {"coordinates":[-64.318443,44.377213],"type":"Point"}
}