{
  "type": "Feature",
  "properties": {
    "addr:full":"Hwy 10 N The Pas MB R9A 1R8",
    "addr:postcode":"r9a 1r8",
    "addr:street":"Hwy 10 N",
    "iso:country":"CA",
    "sg:address":"Hwy 10 N",
    "sg:city":"The Pas",
    "sg:classifiers":[
        {
            "category":"Food & Beverages",
            "subcategory":"Groceries & Convenience Stores",
            "type":"Retail Goods"
        }
    ],
    "sg:phone":"+1 204 623 6187",
    "sg:postcode":"R9A 1R8",
    "sg:province":"MB",
    "sg:tags":[
        "grocer"
    ],
    "wof:name":"Pas Iga Food Products",
    "wof:placetype":"venue"
},
  "geometry": {"coordinates":[-101.250816,53.801739],"type":"Point"}
}