{
  "type": "Feature",
  "properties": {
    "iso:country":"CA",
    "sg:address":"34 Queen St",
    "sg:city":"Dryden",
    "sg:classifiers":[
        {
            "category":"Recreation",
            "type":"Entertainment"
        }
    ],
    "sg:phone":"+1 807 223 4033",
    "sg:postcode":"P8N 1A3",
    "sg:province":"ON",
    "sg:tags":[
        "hall",
        "auditorium"
    ],
    "wof:name":"Royal Canadian Legion",
    "wof:placetype":"venue"
},
  "geometry": {"coordinates":[-92.840012,49.785004],"type":"Point"}
}