{
  "type": "Feature",
  "properties": {
    "addr:full":"8403 187 St NW Edmonton AB T5T 1H9",
    "addr:housenumber":"8403",
    "addr:postcode":"t5t 1h9",
    "addr:street":"187 St Nw",
    "iso:country":"CA",
    "sg:address":"8403 187 St NW",
    "sg:city":"Edmonton",
    "sg:classifiers":[
        {
            "category":"Professional",
            "subcategory":"Engineering",
            "type":"Services"
        }
    ],
    "sg:phone":"+1 780 443 2290",
    "sg:postcode":"T5T 1H9",
    "sg:province":"AB",
    "sg:tags":[
        "engineer"
    ],
    "wof:name":"James Progithin Intl Ltd",
    "wof:placetype":"venue"
},
  "geometry": {"coordinates":[-113.644805908,53.5178642273],"type":"Point"}
}