{
  "type": "Feature",
  "properties": {
    "addr:full":"275 Rue Principale Saint-Basile-Le-Grand QC J3N 1J7",
    "addr:housenumber":"275",
    "addr:postcode":"j3n 1j7",
    "addr:street":"Rue Principale",
    "iso:country":"CA",
    "sg:address":"275 Rue Principale",
    "sg:city":"Saint-Basile-Le-Grand",
    "sg:classifiers":[
        {
            "category":"Professional",
            "subcategory":"Business Services",
            "type":"Services"
        }
    ],
    "sg:phone":"+1 450 653 2518",
    "sg:postcode":"J3N 1J7",
    "sg:province":"QC",
    "sg:tags":[
        "notary"
    ],
    "wof:name":"Lapointe, G Marc",
    "wof:placetype":"venue"
},
  "geometry": {"coordinates":[-73.292564,45.519814],"type":"Point"}
}