{
  "type": "Feature",
  "properties": {
    "addr:full":"1687 Nanaimo St Vancouver BC V5L 4T9",
    "addr:housenumber":"1687",
    "addr:postcode":"v5l 4t9",
    "addr:street":"Nanaimo St",
    "iso:country":"CA",
    "sg:address":"1687 Nanaimo St",
    "sg:city":"Vancouver",
    "sg:classifiers":[
        {
            "category":"Food & Beverages",
            "subcategory":"Groceries & Convenience Stores",
            "type":"Retail Goods"
        }
    ],
    "sg:phone":"+1 604 253 4402",
    "sg:postcode":"V5L 4T9",
    "sg:province":"BC",
    "sg:tags":[
        "grocer"
    ],
    "wof:name":"B & B Store",
    "wof:placetype":"venue"
},
  "geometry": {"coordinates":[-123.056725,49.269749],"type":"Point"}
}