{
  "type": "Feature",
  "properties": {
    "addr:full":"St Albert ON K0A 3C0",
    "addr:postcode":"k0a 3c0",
    "iso:country":"CA",
    "sg:city":"St Albert",
    "sg:classifiers":[
        {
            "category":"Professional",
            "subcategory":"Management & Consulting",
            "type":"Services"
        }
    ],
    "sg:phone":"+1 613 987 2860",
    "sg:postcode":"K0A 3C0",
    "sg:province":"ON",
    "sg:tags":[
        "consultant",
        "business"
    ],
    "wof:name":"Business Projections & Control",
    "wof:placetype":"venue"
},
  "geometry": {"coordinates":[-75.12264999999999,45.254864],"type":"Point"}
}