{
  "type": "Feature",
  "properties": {
    "addr:full":"Owen Sound ON N4K 2M8",
    "addr:postcode":"n4k 2m8",
    "iso:country":"CA",
    "sg:city":"Owen Sound",
    "sg:classifiers":[
        {
            "category":"Shopping",
            "type":"Retail Goods"
        }
    ],
    "sg:phone":"+1 519 371 4281",
    "sg:postcode":"N4K 2M8",
    "sg:province":"ON",
    "sg:tags":[
        "cosmetic",
        "perfume"
    ],
    "wof:name":"Mary Kay Cosmetics",
    "wof:placetype":"venue"
},
  "geometry": {"coordinates":[-80.93740099999999,44.557476],"type":"Point"}
}