{
  "type": "Feature",
  "properties": {
    "iso:country":"CA",
    "sg:address":"18167 59 Ave",
    "sg:city":"Surrey",
    "sg:classifiers":[
        {
            "category":"Retail",
            "subcategory":"Laundry & Dry Cleaning",
            "type":"Services"
        }
    ],
    "sg:phone":"+1 604 431 8960",
    "sg:postcode":"V3S 5R8",
    "sg:province":"BC",
    "sg:tags":[
        "cleaners",
        "rug",
        "carpet"
    ],
    "wof:name":"Langenwalter Carpet Dyeing",
    "wof:placetype":"venue"
},
  "geometry": {"coordinates":[-122.718719482,49.1097145081],"type":"Point"}
}