{
  "type": "Feature",
  "properties": {
    "addr:full":"57 Ch Du Bord-DE-L'Eau Laval QC H7X 1S5",
    "addr:housenumber":"57",
    "addr:postcode":"h7x 1s5",
    "addr:street":"Ch Du Bord-De-L'Eau",
    "iso:country":"CA",
    "sg:address":"57 Ch Du Bord-DE-L'Eau",
    "sg:city":"Laval",
    "sg:classifiers":[
        {
            "category":"Building & Trades",
            "subcategory":"Landscaping Services",
            "type":"Services"
        }
    ],
    "sg:phone":"+1 450 689 8722",
    "sg:postcode":"H7X 1S5",
    "sg:province":"QC",
    "sg:tags":[
        "topsoil"
    ],
    "wof:name":"Charbonneau Le Specialiste",
    "wof:placetype":"venue"
},
  "geometry": {"coordinates":[-73.77748099999999,45.52153],"type":"Point"}
}