{
  "type": "Feature",
  "properties": {
    "addr:full":"85 Rue Sauve O Montreal QC H3L 1Y2",
    "addr:housenumber":"85",
    "addr:postcode":"h3l 1y2",
    "addr:street":"Rue Sauve O",
    "iso:country":"CA",
    "sg:address":"85 Rue Sauve O",
    "sg:city":"Montreal",
    "sg:classifiers":[
        {
            "category":"Social Services",
            "subcategory":"Child Care",
            "type":"Services"
        }
    ],
    "sg:phone":"+1 514 388 2883",
    "sg:postcode":"H3L 1Y2",
    "sg:province":"QC",
    "wof:name":"Cpe Les Marmousets",
    "wof:placetype":"venue"
},
  "geometry": {"coordinates":[-73.659668,45.547684],"type":"Point"}
}