{
  "type": "Feature",
  "properties": {
    "addr:full":"10121 124 St NW Edmonton AB T5N 1P5",
    "addr:housenumber":"10121",
    "addr:postcode":"t5n 1p5",
    "addr:street":"124 St Nw",
    "iso:country":"CA",
    "sg:address":"10121 124 St NW",
    "sg:city":"Edmonton",
    "sg:classifiers":[
        {
            "category":"Shopping",
            "subcategory":"Computers & Home Electronics",
            "type":"Retail Goods"
        }
    ],
    "sg:phone":"+1 780 452 7743",
    "sg:postcode":"T5N 1P5",
    "sg:province":"AB",
    "sg:tags":[
        "game",
        "video"
    ],
    "wof:name":"Pride Video",
    "wof:placetype":"venue"
},
  "geometry": {"coordinates":[-113.53565999999999,53.542007],"type":"Point"}
}