{
  "type": "Feature",
  "properties": {
    "addr:full":"4118 118 Ave NW Edmonton AB T5W 1A3",
    "addr:housenumber":"4118",
    "addr:postcode":"t5w 1a3",
    "addr:street":"118 Ave Nw",
    "iso:country":"CA",
    "sg:address":"4118 118 Ave NW",
    "sg:city":"Edmonton",
    "sg:classifiers":[
        {
            "category":"Wholesale",
            "subcategory":"Groceries",
            "type":"Manufacturing & Wholesale Goods"
        }
    ],
    "sg:phone":"+1 780 474 2229",
    "sg:postcode":"T5W 1A3",
    "sg:province":"AB",
    "sg:tags":[
        "baker"
    ],
    "wof:name":"Italian Bakery CO Ltd",
    "wof:placetype":"venue"
},
  "geometry": {"coordinates":[-113.404938,53.570625],"type":"Point"}
}