{
  "type": "Feature",
  "properties": {
    "addr:full":"Gibbons AB T0A 1N0",
    "addr:postcode":"t0a 1n0",
    "iso:country":"CA",
    "sg:city":"Gibbons",
    "sg:classifiers":[
        {
            "category":"Manufacturing",
            "subcategory":"Buildings",
            "type":"Manufacturing & Wholesale Goods"
        }
    ],
    "sg:phone":"+1 780 923 2119",
    "sg:postcode":"T0A 1N0",
    "sg:province":"AB",
    "sg:tags":[
        "prefab",
        "mobile",
        "home"
    ],
    "wof:name":"Alcove Trailer Park",
    "wof:placetype":"venue"
},
  "geometry": {"coordinates":[-113.3279953,53.8276100159],"type":"Point"}
}