{
  "type": "Feature",
  "properties": {
    "addr:full":"Bobcaygeon ON K0M 1A0",
    "addr:postcode":"k0m 1a0",
    "iso:country":"CA",
    "sg:city":"Bobcaygeon",
    "sg:classifiers":[
        {
            "category":"Building & Trades",
            "subcategory":"Electrical",
            "type":"Services"
        }
    ],
    "sg:phone":"+1 705 738 5586",
    "sg:postcode":"K0M 1A0",
    "sg:province":"ON",
    "sg:tags":[
        "electric",
        "contractor"
    ],
    "wof:name":"Craig Electric Plumbing & Htg",
    "wof:placetype":"venue"
},
  "geometry": {"coordinates":[-78.53755200000001,44.536301],"type":"Point"}
}