{
  "type": "Feature",
  "properties": {
    "addr:full":"4523 68 Ave NW Edmonton AB T6B 2N2",
    "addr:housenumber":"4523",
    "addr:postcode":"t6b 2n2",
    "addr:street":"68 Ave Nw",
    "iso:country":"CA",
    "sg:address":"4523 68 Ave NW",
    "sg:city":"Edmonton",
    "sg:classifiers":[
        {
            "category":"Retail",
            "subcategory":"Auto Repair",
            "type":"Services"
        }
    ],
    "sg:phone":"+1 780 461 1886",
    "sg:postcode":"T6B 2N2",
    "sg:province":"AB",
    "sg:tags":[
        "repairing",
        "automobile"
    ],
    "wof:name":"Sovereign Automotive Inc",
    "wof:placetype":"venue"
},
  "geometry": {"coordinates":[-113.412811,53.504768],"type":"Point"}
}