{
  "type": "Feature",
  "properties": {
    "addr:full":"Agassiz BC V0M 1A1",
    "addr:postcode":"v0m 1a1",
    "iso:country":"CA",
    "sg:city":"Agassiz",
    "sg:classifiers":[
        {
            "category":"Food & Beverages",
            "subcategory":"Groceries & Convenience Stores",
            "type":"Retail Goods"
        }
    ],
    "sg:phone":"+1 604 796 9252",
    "sg:postcode":"V0M 1A1",
    "sg:province":"BC",
    "sg:tags":[
        "grocer"
    ],
    "wof:name":"Chehalis Band Store",
    "wof:placetype":"venue"
},
  "geometry": {"coordinates":[-121.76375579800001,49.2383041382],"type":"Point"}
}