{
  "type": "Feature",
  "properties": {
    "addr:full":"8764 Rue Marcel-Cadieux Montreal QC H2M 2L1",
    "addr:housenumber":"8764",
    "addr:postcode":"h2m 2l1",
    "addr:street":"Rue Marcel-Cadieux",
    "iso:country":"CA",
    "sg:address":"8764 Rue Marcel-Cadieux",
    "sg:city":"Montreal",
    "sg:classifiers":[
        {
            "category":"Professional",
            "subcategory":"Management & Consulting",
            "type":"Services"
        }
    ],
    "sg:phone":"+1 514 383 0205",
    "sg:postcode":"H2M 2L1",
    "sg:province":"QC",
    "sg:tags":[
        "consultant",
        "business"
    ],
    "wof:name":"Gestions Artistiques Badeaux",
    "wof:placetype":"venue"
},
  "geometry": {"coordinates":[-73.637428,45.550678],"type":"Point"}
}