{
  "type": "Feature",
  "properties": {
    "addr:full":"240 Rue Tardif E Rouyn-Noranda QC J9X 3R3",
    "addr:housenumber":"240",
    "addr:postcode":"j9x 3r3",
    "addr:street":"Rue Tardif E",
    "iso:country":"CA",
    "sg:address":"240 Rue Tardif E",
    "sg:city":"Rouyn-Noranda",
    "sg:classifiers":[
        {
            "category":"Wholesale",
            "subcategory":"Hardware",
            "type":"Manufacturing & Wholesale Goods"
        }
    ],
    "sg:phone":"+1 819 762 2575",
    "sg:postcode":"J9X 3R3",
    "sg:province":"QC",
    "sg:tags":[
        "tool"
    ],
    "wof:name":"Richard Denomme Enr",
    "wof:placetype":"venue"
},
  "geometry": {"coordinates":[-79.01290130620001,48.2272071838],"type":"Point"}
}