{
  "type": "Feature",
  "properties": {
    "addr:full":"90 Av Charbonneau # D Vaudreuil-Dorion QC J7V 7G1",
    "addr:housenumber":"# d",
    "addr:postcode":"j7v 7g1",
    "addr:street":"90 Av Charbonneau;Vaudreuil-Dorion",
    "iso:country":"CA",
    "sg:address":"90 Av Charbonneau # D",
    "sg:city":"Vaudreuil-Dorion",
    "sg:classifiers":[
        {
            "category":"Manufacturing",
            "subcategory":"Furniture",
            "type":"Manufacturing & Wholesale Goods"
        }
    ],
    "sg:phone":"+1 450 455 1566",
    "sg:postcode":"J7V 7G1",
    "sg:province":"QC",
    "sg:tags":[
        "exposition",
        "stand"
    ],
    "wof:name":"Presentex Canada Inc",
    "wof:placetype":"venue"
},
  "geometry": {"coordinates":[-74.01366400000001,45.384972],"type":"Point"}
}