{
  "type": "Feature",
  "properties": {
    "iso:country":"CA",
    "sg:address":"24 Rue Gamble O",
    "sg:city":"Rouyn-Noranda",
    "sg:classifiers":[
        {
            "category":"Personal",
            "subcategory":"Beauty Salon",
            "type":"Services"
        }
    ],
    "sg:phone":"+1 819 764 4232",
    "sg:postcode":"J9X 2R2",
    "sg:province":"QC",
    "wof:name":"Coiffure Beaute Plus",
    "wof:placetype":"venue"
},
  "geometry": {"coordinates":[-79.0194854736,48.2397994995],"type":"Point"}
}