{
  "type": "Feature",
  "properties": {
    "addr:full":"533 Queen St E Toronto ON M5A 1V1",
    "addr:housenumber":"533",
    "addr:postcode":"m5a 1v1",
    "addr:street":"Queen St E",
    "iso:country":"CA",
    "sg:address":"533 Queen St E",
    "sg:city":"Toronto",
    "sg:classifiers":[
        {
            "category":"Professional",
            "subcategory":"Lawyer & Legal Services",
            "type":"Services"
        }
    ],
    "sg:phone":"+1 416 364 6755",
    "sg:postcode":"M5A 1V1",
    "sg:province":"ON",
    "sg:tags":[
        "attorney"
    ],
    "wof:name":"Dempsey, Andre M QC",
    "wof:placetype":"venue"
},
  "geometry": {"coordinates":[-79.356956,43.657131],"type":"Point"}
}