{
  "type": "Feature",
  "properties": {
    "iso:country":"CA",
    "sg:city":"Saint-Laurent",
    "sg:classifiers":[
        {
            "category":"Wholesale",
            "subcategory":"Groceries",
            "type":"Manufacturing & Wholesale Goods"
        }
    ],
    "sg:phone":"+1 514 747 5957",
    "sg:postcode":"H4M 2P5",
    "sg:province":"QC",
    "sg:tags":[
        "grocer"
    ],
    "wof:name":"National Importers Ltee",
    "wof:placetype":"venue"
},
  "geometry": {"coordinates":[-73.676857,45.496281],"type":"Point"}
}