{
  "type": "Feature",
  "properties": {
    "addr:full":"1810 Kosmina Rd Vernon BC V1T 8T2",
    "addr:housenumber":"1810",
    "addr:postcode":"v1t 8t2",
    "addr:street":"Kosmina Rd",
    "iso:country":"CA",
    "sg:address":"1810 Kosmina Rd",
    "sg:city":"Vernon",
    "sg:classifiers":[
        {
            "category":"Manufacturing",
            "subcategory":"Pottery",
            "type":"Manufacturing & Wholesale Goods"
        }
    ],
    "sg:phone":"+1 250 549 1323",
    "sg:postcode":"V1T 8T2",
    "sg:province":"BC",
    "sg:tags":[
        "chinaware",
        "decorator"
    ],
    "wof:name":"Universal Specialties Inc",
    "wof:placetype":"venue"
},
  "geometry": {"coordinates":[-119.25507399999999,50.249966],"type":"Point"}
}