{
  "type": "Feature",
  "properties": {
    "addr:full":"111 St Anne's Rd Winnipeg MB R2M 2Z1",
    "addr:housenumber":"111",
    "addr:postcode":"r2m 2z1",
    "addr:street":"St Anne'S Rd",
    "iso:country":"CA",
    "sg:address":"111 St Anne's Rd",
    "sg:city":"Winnipeg",
    "sg:classifiers":[
        {
            "category":"Personal",
            "subcategory":"Barber",
            "type":"Services"
        }
    ],
    "sg:phone":"+1 204 256 5429",
    "sg:postcode":"R2M 2Z1",
    "sg:province":"MB",
    "wof:name":"Carl's Barber Shop",
    "wof:placetype":"venue"
},
  "geometry": {"coordinates":[-97.107788,49.860565],"type":"Point"}
}