{
  "type": "Feature",
  "properties": {
    "addr:full":"5077 Hwy 35 Fenelon Falls ON K0M 1N0",
    "addr:housenumber":"5077",
    "addr:postcode":"k0m 1n0",
    "addr:street":"Hwy 35",
    "iso:country":"CA",
    "sg:address":"5077 Hwy 35",
    "sg:city":"Fenelon Falls",
    "sg:classifiers":[
        {
            "category":"Building & Trades",
            "subcategory":"Plumbing",
            "type":"Services"
        }
    ],
    "sg:phone":"+1 705 887 1670",
    "sg:postcode":"K0M 1N0",
    "sg:province":"ON",
    "sg:tags":[
        "propane",
        "gas",
        "system",
        "air",
        "conditioning",
        "contractor"
    ],
    "wof:name":"Highlands Propane",
    "wof:placetype":"venue"
},
  "geometry": {"coordinates":[-78.7819366455,44.5227241516],"type":"Point"}
}