{
  "type": "Feature",
  "properties": {
    "iso:country":"CA",
    "sg:city":"Burnaby",
    "sg:classifiers":[
        {
            "category":"Home & Garden",
            "subcategory":"Building Materials",
            "type":"Retail Goods"
        }
    ],
    "sg:phone":"+1 604 438 1000",
    "sg:postcode":"V5H 4M2",
    "sg:province":"BC",
    "sg:tags":[
        "glass",
        "window",
        "plate"
    ],
    "wof:name":"Tcg Intl Inc",
    "wof:placetype":"venue"
},
  "geometry": {"coordinates":[-122.998886,49.228115],"type":"Point"}
}