{
  "type": "Feature",
  "properties": {
    "addr:full":"260 Adam St Belleville ON K8N 5S4",
    "addr:housenumber":"260",
    "addr:postcode":"k8n 5s4",
    "addr:street":"Adam St",
    "iso:country":"CA",
    "sg:address":"260 Adam St",
    "sg:city":"Belleville",
    "sg:classifiers":[
        {
            "category":"Shopping",
            "type":"Retail Goods"
        }
    ],
    "sg:phone":"+1 613 969 1616",
    "sg:postcode":"K8N 5S4",
    "sg:province":"ON",
    "sg:tags":[
        "telephone",
        "cellular"
    ],
    "wof:name":"Tas Communications",
    "wof:placetype":"venue"
},
  "geometry": {"coordinates":[-77.377663,44.192398],"type":"Point"}
}