{
  "type": "Feature",
  "properties": {
    "addr:full":"653 Colborne St W Brantford ON N3T 5L5",
    "addr:housenumber":"653",
    "addr:postcode":"n3t 5l5",
    "addr:street":"Colborne St W",
    "iso:country":"CA",
    "sg:address":"653 Colborne St W",
    "sg:city":"Brantford",
    "sg:classifiers":[
        {
            "category":"Shopping",
            "subcategory":"Clothing, Apparel, & Fashions",
            "type":"Retail Goods"
        }
    ],
    "sg:phone":"+1 519 756 5840",
    "sg:postcode":"N3T 5L5",
    "sg:province":"ON",
    "sg:tags":[
        "riding",
        "equipment"
    ],
    "wof:name":"Pleasant Ridge Saddlery",
    "wof:placetype":"venue"
},
  "geometry": {"coordinates":[-80.2382736206,43.1408653259],"type":"Point"}
}