{
  "type": "Feature",
  "properties": {
    "addr:full":"6775 Hazeldean Rd Stittsville ON K2S 1B9",
    "addr:housenumber":"6775",
    "addr:postcode":"k2s 1b9",
    "addr:street":"Hazeldean Rd",
    "iso:country":"CA",
    "sg:address":"6775 Hazeldean Rd",
    "sg:city":"Stittsville",
    "sg:classifiers":[
        {
            "category":"Building & Trades",
            "subcategory":"Landscaping Services",
            "type":"Services"
        }
    ],
    "sg:phone":"+1 613 836 6238",
    "sg:postcode":"K2S 1B9",
    "sg:province":"ON",
    "sg:tags":[
        "concrete",
        "landscape",
        "contractor"
    ],
    "wof:name":"Permacon Ottawa",
    "wof:placetype":"venue"
},
  "geometry": {"coordinates":[-75.9634017944,45.2501182556],"type":"Point"}
}