{
  "type": "Feature",
  "properties": {
    "iso:country":"CA",
    "sg:address":"6202 44 Ave",
    "sg:city":"Stettler",
    "sg:classifiers":[
        {
            "category":"Organizations",
            "subcategory":"Professional Association",
            "type":"Services"
        }
    ],
    "sg:phone":"+1 403 742 4214",
    "sg:postcode":"T0C 2L1",
    "sg:province":"AB",
    "wof:name":"Stettler & District Minor",
    "wof:placetype":"venue"
},
  "geometry": {"coordinates":[-112.721069336,52.3176612854],"type":"Point"}
}