{
  "type": "Feature",
  "properties": {
    "iso:country":"CA",
    "sg:address":"103 3rd Ave E",
    "sg:city":"Watrous",
    "sg:classifiers":[
        {
            "category":"Retail",
            "subcategory":"Laundry & Dry Cleaning",
            "type":"Services"
        }
    ],
    "sg:phone":"+1 306 946 3830",
    "sg:postcode":"S0K 4T0",
    "sg:province":"SK",
    "sg:tags":[
        "cleaners"
    ],
    "wof:name":"Watrous Cleaners Ltd",
    "wof:placetype":"venue"
},
  "geometry": {"coordinates":[-105.454788208,51.6693191528],"type":"Point"}
}