{
  "type": "Feature",
  "properties": {
    "iso:country":"CA",
    "sg:address":"353 Rue Saint-Etienne",
    "sg:city":"LA Malbaie",
    "sg:classifiers":[
        {
            "category":"Organizations",
            "subcategory":"Religious Organization",
            "type":"Services"
        }
    ],
    "sg:phone":"+1 418 665 3935",
    "sg:postcode":"G5A 1T1",
    "sg:province":"QC",
    "sg:tags":[
        "church"
    ],
    "wof:name":"Presbytere LA Malbaie-Cap-A-L",
    "wof:placetype":"venue"
},
  "geometry": {"coordinates":[-70.1509094238,47.6551780701],"type":"Point"}
}