{
  "type": "Feature",
  "properties": {
    "addr:full":"RR 1 Bloomfield Station PE C0B 1E0",
    "addr:postcode":"c0b 1e0",
    "addr:street":"Rr 1 Bloomfield",
    "iso:country":"CA",
    "sg:address":"RR 1",
    "sg:city":"Bloomfield Station",
    "sg:classifiers":[
        {
            "category":"Organizations",
            "subcategory":"Religious Organization",
            "type":"Services"
        }
    ],
    "sg:phone":"+1 902 859 2013",
    "sg:postcode":"C0B 1E0",
    "sg:province":"PE",
    "sg:tags":[
        "church"
    ],
    "wof:name":"St Mark Catholic Church",
    "wof:placetype":"venue"
},
  "geometry": {"coordinates":[-64.2351531982,46.7763366699],"type":"Point"}
}