{
  "type": "Feature",
  "properties": {
    "iso:country":"CA",
    "sg:city":"Mississauga",
    "sg:classifiers":[
        {
            "category":"Wholesale",
            "subcategory":"Machinery & Supplies",
            "type":"Manufacturing & Wholesale Goods"
        }
    ],
    "sg:phone":"+1 905 813 1966",
    "sg:postcode":"L5N 7X9",
    "sg:province":"ON",
    "sg:tags":[
        "parking"
    ],
    "wof:name":"Zeag North America Inc",
    "wof:placetype":"venue"
},
  "geometry": {"coordinates":[-79.7769775391,43.5993804932],"type":"Point"}
}