{
  "type": "Feature",
  "properties": {
    "addr:full":"3290 Boul DE Portland Sherbrooke QC J1L 2A6",
    "addr:housenumber":"3290",
    "addr:postcode":"j1l 2a6",
    "addr:street":"Boul De Portland",
    "iso:country":"CA",
    "sg:address":"3290 Boul DE Portland",
    "sg:city":"Sherbrooke",
    "sg:classifiers":[
        {
            "category":"Shopping",
            "subcategory":"Optical Goods",
            "type":"Retail Goods"
        }
    ],
    "sg:phone":"+1 819 829 0089",
    "sg:postcode":"J1L 2A6",
    "sg:province":"QC",
    "sg:tags":[
        "optician"
    ],
    "wof:name":"Lunetterie F Farhat",
    "wof:placetype":"venue"
},
  "geometry": {"coordinates":[-71.95658899999999,45.403015],"type":"Point"}
}