{
  "type": "Feature",
  "properties": {
    "iso:country":"CA",
    "sg:address":"120 Rte Du Mont-Adstock",
    "sg:city":"Adstock",
    "sg:classifiers":[
        {
            "category":"Sports & Exercise",
            "subcategory":"Golf",
            "type":"Entertainment"
        }
    ],
    "sg:phone":"+1 418 422 2242",
    "sg:postcode":"G0N 1S0",
    "sg:province":"QC",
    "sg:tags":[
        "resort",
        "center",
        "skiing"
    ],
    "wof:name":"Club DE Golf Du Mont Adstock",
    "wof:placetype":"venue"
},
  "geometry": {"coordinates":[-71.1917800903,46.0263824463],"type":"Point"}
}