{
  "type": "Feature",
  "properties": {
    "iso:country":"CA",
    "sg:address":"6482 Victoria Dr",
    "sg:city":"Vancouver",
    "sg:classifiers":[
        {
            "category":"Restaurant",
            "type":"Food & Drink"
        }
    ],
    "sg:phone":"+1 604 325 2412",
    "sg:postcode":"V5P 3X7",
    "sg:province":"BC",
    "wof:name":"Victoria Restaurant",
    "wof:placetype":"venue"
},
  "geometry": {"coordinates":[-123.065513611,49.2254905701],"type":"Point"}
}