{
  "type": "Feature",
  "properties": {
    "addr:full":"Richmond BC V6X 3Z9",
    "addr:postcode":"v6x 3z9",
    "iso:country":"CA",
    "sg:city":"Richmond",
    "sg:classifiers":[
        {
            "category":"Restaurant",
            "type":"Food & Drink"
        }
    ],
    "sg:phone":"+1 604 241 8828",
    "sg:postcode":"V6X 3Z9",
    "sg:province":"BC",
    "wof:name":"Wah Wing Seafood Restaurant",
    "wof:placetype":"venue"
},
  "geometry": {"coordinates":[-123.128304,49.185127],"type":"Point"}
}