{
  "type": "Feature",
  "properties": {
    "addr:full":"5870 48 St SE Calgary AB T2C 4L4",
    "addr:housenumber":"5870",
    "addr:postcode":"t2c 4l4",
    "addr:street":"48 St Se",
    "iso:country":"CA",
    "sg:address":"5870 48 St SE",
    "sg:city":"Calgary",
    "sg:classifiers":[
        {
            "category":"Wholesale",
            "subcategory":"Construction Materials",
            "type":"Manufacturing & Wholesale Goods"
        }
    ],
    "sg:phone":"+1 403 236 9100",
    "sg:postcode":"T2C 4L4",
    "sg:province":"AB",
    "sg:tags":[
        "lumber"
    ],
    "wof:name":"Hardwoods",
    "wof:placetype":"venue"
},
  "geometry": {"coordinates":[-113.96405,51.000957],"type":"Point"}
}