{
  "type": "Feature",
  "properties": {
    "addr:full":"349 1st Ave Arborg MB R0C 0A0",
    "addr:housenumber":"349",
    "addr:postcode":"r0c 0a0",
    "addr:street":"1St Ave",
    "iso:country":"CA",
    "sg:address":"349 1st Ave",
    "sg:city":"Arborg",
    "sg:classifiers":[
        {
            "category":"Restaurant",
            "type":"Food & Drink"
        }
    ],
    "sg:phone":"+1 204 376 2960",
    "sg:postcode":"R0C 0A0",
    "sg:province":"MB",
    "wof:name":"Golden Lake",
    "wof:placetype":"venue"
},
  "geometry": {"coordinates":[-97.2208099365,50.9080467224],"type":"Point"}
}