{
  "type": "Feature",
  "properties": {
    "addr:full":"5156 Manson Ave Powell River BC V8A 3P1",
    "addr:housenumber":"5156",
    "addr:postcode":"v8a 3p1",
    "addr:street":"Manson Ave Powell",
    "iso:country":"CA",
    "sg:address":"5156 Manson Ave",
    "sg:city":"Powell River",
    "sg:classifiers":[
        {
            "category":"Building & Trades",
            "subcategory":"Construction",
            "type":"Services"
        }
    ],
    "sg:phone":"+1 604 483 9834",
    "sg:postcode":"V8A 3P1",
    "sg:province":"BC",
    "sg:tags":[
        "excavating",
        "contractor"
    ],
    "wof:name":"L & R Excavating Ltd",
    "wof:placetype":"venue"
},
  "geometry": {"coordinates":[-124.51132200000001,49.855289],"type":"Point"}
}