{
  "type": "Feature",
  "properties": {
    "addr:full":"96 Doncaster Ave Thornhill ON L3T 1L3",
    "addr:housenumber":"96",
    "addr:postcode":"l3t 1l3",
    "addr:street":"Doncaster Ave",
    "iso:country":"CA",
    "sg:address":"96 Doncaster Ave",
    "sg:city":"Thornhill",
    "sg:classifiers":[
        {
            "category":"Wholesale",
            "subcategory":"Home Furnishings",
            "type":"Manufacturing & Wholesale Goods"
        }
    ],
    "sg:phone":"+1 905 764 7265",
    "sg:postcode":"L3T 1L3",
    "sg:province":"ON",
    "sg:tags":[
        "closet",
        "accessory"
    ],
    "wof:name":"Shelving Outlet",
    "wof:placetype":"venue"
},
  "geometry": {"coordinates":[-79.4141540527,43.8047370911],"type":"Point"}
}