{
  "type": "Feature",
  "properties": {
    "addr:full":"360 Sugar Maple Crt Richmond Hill ON L4C 4C5",
    "addr:housenumber":"360",
    "addr:postcode":"l4c 4c5",
    "addr:street":"Sugar Maple Crt",
    "iso:country":"CA",
    "sg:address":"360 Sugar Maple Crt",
    "sg:city":"Richmond Hill",
    "sg:classifiers":[
        {
            "category":"Building & Trades",
            "subcategory":"Landscaping Services",
            "type":"Services"
        }
    ],
    "sg:phone":"+1 905 884 0511",
    "sg:postcode":"L4C 4C5",
    "sg:province":"ON",
    "sg:tags":[
        "landscape",
        "contractor"
    ],
    "wof:name":"Dave Lund Tree Svc & Forestry",
    "wof:placetype":"venue"
},
  "geometry": {"coordinates":[-79.45578,43.875954],"type":"Point"}
}