{
  "type": "Feature",
  "properties": {
    "addr:full":"4564 11th Ave W Vancouver BC V6R 2M4",
    "addr:housenumber":"4564",
    "addr:postcode":"v6r 2m4",
    "addr:street":"11Th Ave W",
    "iso:country":"CA",
    "sg:address":"4564 11th Ave W",
    "sg:city":"Vancouver",
    "sg:classifiers":[
        {
            "category":"Professional",
            "subcategory":"Business Services",
            "type":"Services"
        }
    ],
    "sg:phone":"+1 604 222 3002",
    "sg:postcode":"V6R 2M4",
    "sg:province":"BC",
    "sg:tags":[
        "building",
        "inspection"
    ],
    "wof:name":"Discovery Engineering",
    "wof:placetype":"venue"
},
  "geometry": {"coordinates":[-123.210999,49.262848],"type":"Point"}
}