{
  "type": "Feature",
  "properties": {
    "addr:full":"475 Mountain Rd Moncton NB E1C 2N2",
    "addr:housenumber":"475",
    "addr:postcode":"e1c 2n2",
    "addr:street":"Mountain Rd",
    "iso:country":"CA",
    "sg:address":"475 Mountain Rd",
    "sg:city":"Moncton",
    "sg:classifiers":[
        {
            "category":"Autos & Motor Vehicles",
            "subcategory":"Automobile Sales",
            "type":"Retail Goods"
        }
    ],
    "sg:phone":"+1 506 857 4226",
    "sg:postcode":"E1C 2N2",
    "sg:province":"NB",
    "sg:tags":[
        "car",
        "dealer"
    ],
    "wof:name":"Belliveau's Auto Sales Ltd",
    "wof:placetype":"venue"
},
  "geometry": {"coordinates":[-64.7941436768,46.0970306396],"type":"Point"}
}