{
  "type": "Feature",
  "properties": {
    "addr:full":"3742 Nafziger Wellesley ON N0B 2T0",
    "addr:housenumber":"3742",
    "addr:postcode":"n0b 2t0",
    "addr:street":"Nafziger",
    "iso:country":"CA",
    "sg:address":"3742 Nafziger",
    "sg:city":"Wellesley",
    "sg:classifiers":[
        {
            "category":"Health Services",
            "subcategory":"Doctor",
            "type":"Services"
        }
    ],
    "sg:phone":"+1 519 656 2220",
    "sg:postcode":"N0B 2T0",
    "sg:province":"ON",
    "sg:tags":[
        "physician",
        "surgeon"
    ],
    "wof:name":"Finn & Finn",
    "wof:placetype":"venue"
},
  "geometry": {"coordinates":[-80.76467132569999,43.4776954651],"type":"Point"}
}