{
  "type": "Feature",
  "properties": {
    "addr:full":"245 West Beaver Creek Rd # 7 Richmond Hill ON L4B 1L1",
    "addr:housenumber":"245",
    "addr:postcode":"l4b 1l1",
    "addr:street":"West Beaver Creek Rd # 7",
    "iso:country":"CA",
    "sg:address":"245 West Beaver Creek Rd # 7",
    "sg:city":"Richmond Hill",
    "sg:classifiers":[
        {
            "category":"Education",
            "subcategory":"Dance Studio",
            "type":"Public Place"
        }
    ],
    "sg:phone":"+1 905 881 1762",
    "sg:postcode":"L4B 1L1",
    "sg:province":"ON",
    "sg:tags":[
        "instruction",
        "dancing"
    ],
    "wof:name":"Alice Kwong School of Dance",
    "wof:placetype":"venue"
},
  "geometry": {"coordinates":[-79.3869476318,43.8456840515],"type":"Point"}
}