{
  "type": "Feature",
  "properties": {
    "addr:full":"PO Box 340 Rankin Inlet NU X0C 0G0",
    "addr:housenumber":"po;340",
    "addr:postcode":"x0c 0g0",
    "addr:street":"Box;Inlet",
    "iso:country":"CA",
    "sg:address":"PO Box 340",
    "sg:city":"Rankin Inlet",
    "sg:classifiers":[
        {
            "category":"Organizations",
            "subcategory":"Professional Association",
            "type":"Services"
        }
    ],
    "sg:phone":"+1 867 645 2800",
    "sg:postcode":"X0C 0G0",
    "sg:province":"NU",
    "wof:name":"Kivalliq Inuit Assn",
    "wof:placetype":"venue"
},
  "geometry": {"coordinates":[-92.08335099999999,62.807144],"type":"Point"}
}