{
  "type": "Feature",
  "properties": {
    "iso:country":"CA",
    "sg:address":"138 Boul Harwood",
    "sg:city":"Vaudreuil-Dorion",
    "sg:classifiers":[
        {
            "category":"Insurance",
            "subcategory":"Insurance Agent",
            "type":"Services"
        }
    ],
    "sg:phone":"+1 450 455 6133",
    "sg:postcode":"J7V 1Y2",
    "sg:province":"QC",
    "wof:name":"A-1 Assurance Rochefort Perron",
    "wof:placetype":"venue"
},
  "geometry": {"coordinates":[-74.0108718872,45.3832817078],"type":"Point"}
}