{
  "type": "Feature",
  "properties": {
    "addr:full":"12280 41E Av Montreal QC H1E 2E7",
    "addr:housenumber":"12280",
    "addr:postcode":"h1e 2e7",
    "addr:street":"41E Av",
    "iso:country":"CA",
    "sg:address":"12280 41E Av",
    "sg:city":"Montreal",
    "sg:classifiers":[
        {
            "category":"Building & Trades",
            "subcategory":"Electrical",
            "type":"Services"
        }
    ],
    "sg:phone":"+1 514 324 5835",
    "sg:postcode":"H1E 2E7",
    "sg:province":"QC",
    "sg:tags":[
        "electric",
        "contractor"
    ],
    "wof:name":"Entreprises D'Electricite Inc",
    "wof:placetype":"venue"
},
  "geometry": {"coordinates":[-73.5786819458,45.6460151672],"type":"Point"}
}