{
  "type": "Feature",
  "properties": {
    "addr:full":"10212 Yonge St Richmond Hill ON L4C 3B6",
    "addr:housenumber":"10212",
    "addr:postcode":"l4c 3b6",
    "addr:street":"Yonge St",
    "iso:country":"CA",
    "sg:address":"10212 Yonge St",
    "sg:city":"Richmond Hill",
    "sg:classifiers":[
        {
            "category":"Wholesale",
            "subcategory":"Groceries",
            "type":"Manufacturing & Wholesale Goods"
        }
    ],
    "sg:phone":"+1 905 737 1304",
    "sg:postcode":"L4C 3B6",
    "sg:province":"ON",
    "sg:tags":[
        "food",
        "broker"
    ],
    "wof:name":"Sbm Foods Sales & Marketing",
    "wof:placetype":"venue"
},
  "geometry": {"coordinates":[-79.4386062622,43.8764648438],"type":"Point"}
}