{
  "type": "Feature",
  "properties": {
    "addr:full":"3575 Felton St Rock Forest QC J1N 2Y7",
    "addr:housenumber":"3575",
    "addr:postcode":"j1n 2y7",
    "addr:street":"Felton St",
    "iso:country":"CA",
    "sg:address":"3575 Felton St",
    "sg:city":"Rock Forest",
    "sg:classifiers":[
        {
            "category":"Professional",
            "subcategory":"Management & Consulting",
            "type":"Services"
        }
    ],
    "sg:phone":"+1 819 823 6666",
    "sg:postcode":"J1N 2Y7",
    "sg:province":"QC",
    "sg:tags":[
        "consultant",
        "energy",
        "conservation",
        "telecommunication"
    ],
    "wof:name":"Controle Concept Estrie Inc",
    "wof:placetype":"venue"
},
  "geometry": {"coordinates":[-71.9535369873,45.3491439819],"type":"Point"}
}