{
  "type": "Feature",
  "properties": {
    "addr:full":"525 Rue Hodge Saint-Laurent QC H4N 2A3",
    "addr:housenumber":"525",
    "addr:postcode":"h4n 2a3",
    "addr:street":"Rue Hodge",
    "iso:country":"CA",
    "sg:address":"525 Rue Hodge",
    "sg:city":"Saint-Laurent",
    "sg:classifiers":[
        {
            "category":"Manufacturing",
            "subcategory":"Metals",
            "type":"Manufacturing & Wholesale Goods"
        }
    ],
    "sg:phone":"+1 514 747 4747",
    "sg:postcode":"H4N 2A3",
    "sg:province":"QC",
    "sg:tags":[
        "caster",
        "glide"
    ],
    "wof:name":"Monsieur Roulette Inc",
    "wof:placetype":"venue"
},
  "geometry": {"coordinates":[-73.661209,45.520161],"type":"Point"}
}