{
  "type": "Feature",
  "properties": {
    "iso:country":"CA",
    "sg:address":"84 Frank St",
    "sg:city":"Strathroy",
    "sg:classifiers":[
        {
            "category":"Restaurant",
            "type":"Food & Drink"
        }
    ],
    "sg:phone":"+1 519 245 0520",
    "sg:postcode":"N7G 2R6",
    "sg:province":"ON",
    "wof:name":"Salt's & Pepper's",
    "wof:placetype":"venue"
},
  "geometry": {"coordinates":[-81.62530517579999,42.9573173523],"type":"Point"}
}