{
  "type": "Feature",
  "properties": {
    "iso:country":"CA",
    "sg:city":"Montreal",
    "sg:classifiers":[
        {
            "category":"Health Services",
            "subcategory":"Doctor",
            "type":"Services"
        }
    ],
    "sg:phone":"+1 514 739 6693",
    "sg:postcode":"H3S 1Z4",
    "sg:province":"QC",
    "sg:tags":[
        "physician",
        "surgeon"
    ],
    "wof:name":"Wilmar",
    "wof:placetype":"venue"
},
  "geometry": {"coordinates":[-73.6300582886,45.4999961853],"type":"Point"}
}