{
  "type": "Feature",
  "properties": {
    "addr:full":"3333 Ch Queen-Mary Montreal QC H3V 1A2",
    "addr:housenumber":"3333",
    "addr:postcode":"h3v 1a2",
    "addr:street":"Ch Queen-Mary",
    "iso:country":"CA",
    "sg:address":"3333 Ch Queen-Mary",
    "sg:city":"Montreal",
    "sg:classifiers":[
        {
            "category":"Professional",
            "subcategory":"Computer Services",
            "type":"Services"
        }
    ],
    "sg:phone":"+1 514 340 1123",
    "sg:postcode":"H3V 1A2",
    "sg:province":"QC",
    "sg:tags":[
        "internet"
    ],
    "wof:name":"123 Netsolution",
    "wof:placetype":"venue"
},
  "geometry": {"coordinates":[-73.6179885864,45.4964408875],"type":"Point"}
}