{
  "type": "Feature",
  "properties": {
    "addr:full":"105 Mclean St Quesnel BC V2J 2N6",
    "addr:housenumber":"105",
    "addr:postcode":"v2j 2n6",
    "addr:street":"Mclean St",
    "iso:country":"CA",
    "sg:address":"105 Mclean St",
    "sg:city":"Quesnel",
    "sg:classifiers":[
        {
            "category":"Shopping",
            "subcategory":"Clothing, Apparel, & Fashions",
            "type":"Retail Goods"
        }
    ],
    "sg:phone":"+1 250 992 2888",
    "sg:postcode":"V2J 2N6",
    "sg:province":"BC",
    "sg:tags":[
        "lingerie"
    ],
    "wof:name":"Cupids Touch Novelties",
    "wof:placetype":"venue"
},
  "geometry": {"coordinates":[-122.494857788,52.9743156433],"type":"Point"}
}