{
  "type": "Feature",
  "properties": {
    "addr:full":"Kirkland QC H9H 3B5",
    "addr:postcode":"h9h 3b5",
    "iso:country":"CA",
    "sg:city":"Kirkland",
    "sg:classifiers":[
        {
            "category":"Communications",
            "subcategory":"Film & Video Production",
            "type":"Services"
        }
    ],
    "sg:phone":"+1 514 697 5541",
    "sg:postcode":"H9H 3B5",
    "sg:province":"QC",
    "sg:tags":[
        "audio"
    ],
    "wof:name":"Covington-Hill Communications",
    "wof:placetype":"venue"
},
  "geometry": {"coordinates":[-73.85353851319999,45.4475593567],"type":"Point"}
}