{
  "type": "Feature",
  "properties": {
    "addr:full":"457 Hazeldean Rd Kanata ON K2L 1V1",
    "addr:housenumber":"457",
    "addr:postcode":"k2l 1v1",
    "addr:street":"Hazeldean Rd",
    "iso:country":"CA",
    "sg:address":"457 Hazeldean Rd",
    "sg:city":"Kanata",
    "sg:classifiers":[
        {
            "category":"Food & Beverages",
            "subcategory":"Groceries & Convenience Stores",
            "type":"Retail Goods"
        }
    ],
    "sg:phone":"+1 613 831 4646",
    "sg:postcode":"K2L 1V1",
    "sg:province":"ON",
    "sg:tags":[
        "product"
    ],
    "wof:name":"Bulk Barn",
    "wof:placetype":"venue"
},
  "geometry": {"coordinates":[-75.886101,45.299763],"type":"Point"}
}