{
  "type": "Feature",
  "properties": {
    "iso:country":"CA",
    "sg:address":"3217 Rue Prieur E",
    "sg:city":"Montreal-Nord",
    "sg:classifiers":[
        {
            "category":"Food & Beverages",
            "subcategory":"Groceries & Convenience Stores",
            "type":"Retail Goods"
        }
    ],
    "sg:phone":"+1 514 381 8775",
    "sg:postcode":"H1H 2K2",
    "sg:province":"QC",
    "wof:name":"Depanneur Matinal Inc",
    "wof:placetype":"venue"
},
  "geometry": {"coordinates":[-73.646736,45.581211],"type":"Point"}
}