{
  "type": "Feature",
  "properties": {
    "iso:country":"CA",
    "sg:address":"4975 Boul DE LA Rive-Sud",
    "sg:city":"Levis",
    "sg:classifiers":[
        {
            "category":"Restaurant",
            "type":"Food & Drink"
        }
    ],
    "sg:phone":"+1 418 835 2799",
    "sg:postcode":"G6V 4Z5",
    "sg:province":"QC",
    "wof:name":"Restaurant LA Cafe Bouffe",
    "wof:placetype":"venue"
},
  "geometry": {"coordinates":[-71.184952,46.789753],"type":"Point"}
}