{
  "type": "Feature",
  "properties": {
    "iso:country":"CA",
    "sg:address":"4246 Sheppard Ave E",
    "sg:city":"Scarborough",
    "sg:classifiers":[
        {
            "category":"Health Services",
            "subcategory":"Doctor",
            "type":"Services"
        }
    ],
    "sg:phone":"+1 416 299 6801",
    "sg:postcode":"M1S 1T5",
    "sg:province":"ON",
    "sg:tags":[
        "dentist"
    ],
    "wof:name":"Hui, John DDS",
    "wof:placetype":"venue"
},
  "geometry": {"coordinates":[-79.276962,43.785839],"type":"Point"}
}