{
  "type": "Feature",
  "properties": {
    "addr:full":"223 42 Ave SW Calgary AB T2S 1A7",
    "addr:postcode":"t2s 1a7",
    "addr:street":"223 42 Ave Sw",
    "iso:country":"CA",
    "sg:address":"223 42 Ave SW",
    "sg:city":"Calgary",
    "sg:classifiers":[
        {
            "category":"Professional",
            "subcategory":"Business Services",
            "type":"Services"
        }
    ],
    "sg:phone":"+1 403 243 5988",
    "sg:postcode":"T2S 1A7",
    "sg:province":"AB",
    "sg:tags":[
        "interior",
        "consultant",
        "design",
        "decorator"
    ],
    "wof:name":"Kamac Design",
    "wof:placetype":"venue"
},
  "geometry": {"coordinates":[-114.06616200000001,51.015972],"type":"Point"}
}