{
  "type": "Feature",
  "properties": {
    "addr:full":"2375 Mayor Magrath Dr S Lethbridge AB T1K 7M1",
    "addr:housenumber":"2375",
    "addr:postcode":"t1k 7m1",
    "addr:street":"Mayor Magrath Dr S",
    "iso:country":"CA",
    "sg:address":"2375 Mayor Magrath Dr S",
    "sg:city":"Lethbridge",
    "sg:classifiers":[
        {
            "category":"Travel",
            "subcategory":"Hotels & Motels",
            "type":"Entertainment"
        }
    ],
    "sg:phone":"+1 403 380 5050",
    "sg:postcode":"T1K 7M1",
    "sg:province":"AB",
    "wof:name":"Ramada Hotel & Suites & Water",
    "wof:placetype":"venue"
},
  "geometry": {"coordinates":[-112.798141,49.669704],"type":"Point"}
}