{
  "type": "Feature",
  "properties": {
    "iso:country":"CA",
    "sg:address":"67 Cote Du Passage",
    "sg:city":"Levis",
    "sg:classifiers":[
        {
            "category":"Professional",
            "subcategory":"Business Services",
            "type":"Services"
        }
    ],
    "sg:phone":"+1 418 833 0311",
    "sg:postcode":"G6V 5S8",
    "sg:province":"QC",
    "sg:tags":[
        "notary"
    ],
    "wof:name":"Gosselin Lagueux Roy",
    "wof:placetype":"venue"
},
  "geometry": {"coordinates":[-71.183075,46.80632],"type":"Point"}
}