{
  "type": "Feature",
  "properties": {
    "addr:full":"52261 Range Road 231 Sherwood Park AB T8B 1A7",
    "addr:housenumber":"52261",
    "addr:postcode":"t8b 1a7",
    "addr:street":"Range Road 231;Park",
    "iso:country":"CA",
    "sg:address":"52261 Range Road 231",
    "sg:city":"Sherwood Park",
    "sg:classifiers":[
        {
            "category":"Organizations",
            "subcategory":"Religious Organization",
            "type":"Services"
        }
    ],
    "sg:phone":"+1 780 467 2636",
    "sg:postcode":"T8B 1A7",
    "sg:province":"AB",
    "sg:tags":[
        "church"
    ],
    "wof:name":"Victory Baptist Church",
    "wof:placetype":"venue"
},
  "geometry": {"coordinates":[-113.295738,53.526402],"type":"Point"}
}