{
  "type": "Feature",
  "properties": {
    "addr:full":"17 Rue Notre-Dame E Victoriaville QC G6P 3Z4",
    "addr:housenumber":"17",
    "addr:postcode":"g6p 3z4",
    "addr:street":"Rue Notre-Dame E",
    "iso:country":"CA",
    "sg:address":"17 Rue Notre-Dame E",
    "sg:city":"Victoriaville",
    "sg:classifiers":[
        {
            "category":"Social Services",
            "type":"Services"
        }
    ],
    "sg:phone":"+1 819 751 6291",
    "sg:postcode":"G6P 3Z4",
    "sg:province":"QC",
    "sg:tags":[
        "employee",
        "assistance",
        "program"
    ],
    "wof:name":"Centre DE Recherche D'Expertis",
    "wof:placetype":"venue"
},
  "geometry": {"coordinates":[-71.958313,46.055721],"type":"Point"}
}