{
  "type": "Feature",
  "properties": {
    "addr:full":"555 Boul DE L'Universite E Chicoutimi QC G7H 2B1",
    "addr:housenumber":"555",
    "addr:postcode":"g7h 2b1",
    "addr:street":"Boul De L'Universite E",
    "iso:country":"CA",
    "sg:address":"555 Boul DE L'Universite E",
    "sg:city":"Chicoutimi",
    "sg:classifiers":[
        {
            "category":"Health Services",
            "subcategory":"Doctor",
            "type":"Services"
        }
    ],
    "sg:phone":"+1 418 545 4443",
    "sg:postcode":"G7H 2B1",
    "sg:province":"QC",
    "sg:tags":[
        "clinic"
    ],
    "wof:name":"Centre Physio Plus Sport",
    "wof:placetype":"venue"
},
  "geometry": {"coordinates":[-71.068275,48.4216],"type":"Point"}
}