{
  "type": "Feature",
  "properties": {
    "addr:full":"135 Felaber Rd Hinton AB T7V 1Z8",
    "addr:housenumber":"135",
    "addr:postcode":"t7v 1z8",
    "addr:street":"Felaber Rd",
    "iso:country":"CA",
    "sg:address":"135 Felaber Rd",
    "sg:city":"Hinton",
    "sg:classifiers":[
        {
            "category":"Manufacturing",
            "subcategory":"Tools & Machinery",
            "type":"Manufacturing & Wholesale Goods"
        }
    ],
    "sg:phone":"+1 780 865 7770",
    "sg:postcode":"T7V 1Z8",
    "sg:province":"AB",
    "sg:tags":[
        "machine",
        "shop",
        "welding"
    ],
    "wof:name":"Summit Machining & Welding Ltd",
    "wof:placetype":"venue"
},
  "geometry": {"coordinates":[-117.55291748,53.4098472595],"type":"Point"}
}