{
  "type": "Feature",
  "properties": {
    "iso:country":"CA",
    "sg:address":"22324 Dewdney Trunk Rd",
    "sg:city":"Maple Ridge",
    "sg:classifiers":[
        {
            "category":"Home & Garden",
            "subcategory":"Carpets & Floor Coverings",
            "type":"Retail Goods"
        }
    ],
    "sg:phone":"+1 604 467 9222",
    "sg:postcode":"V2X 3J2",
    "sg:province":"BC",
    "sg:tags":[
        "rug"
    ],
    "wof:name":"Mc Donald's Flooring Ltd",
    "wof:placetype":"venue"
},
  "geometry": {"coordinates":[-122.604003906,49.2204437256],"type":"Point"}
}