{
  "type": "Feature",
  "properties": {
    "iso:country":"CA",
    "sg:address":"4190 Steeles Ave W",
    "sg:city":"Woodbridge",
    "sg:classifiers":[
        {
            "category":"Personal",
            "type":"Services"
        }
    ],
    "sg:phone":"+1 905 851 8542",
    "sg:postcode":"L4L 3S8",
    "sg:province":"ON",
    "sg:tags":[
        "program",
        "physical",
        "exercise",
        "fitness"
    ],
    "wof:name":"Fabulous Fitness Inc",
    "wof:placetype":"venue"
},
  "geometry": {"coordinates":[-79.558601,43.767944],"type":"Point"}
}