{
  "type": "Feature",
  "properties": {
    "iso:country":"CA",
    "sg:address":"955 Grandview St W",
    "sg:city":"Moose Jaw",
    "sg:classifiers":[
        {
            "category":"Building & Trades",
            "subcategory":"Construction",
            "type":"Services"
        }
    ],
    "sg:phone":"+1 306 693 3656",
    "sg:postcode":"S6H 5M1",
    "sg:province":"SK",
    "sg:tags":[
        "general",
        "contractor"
    ],
    "wof:name":"Sun Wood Builders",
    "wof:placetype":"venue"
},
  "geometry": {"coordinates":[-105.559631348,50.3799514771],"type":"Point"}
}