{
  "type": "Feature",
  "properties": {
    "addr:full":"3352 Compton Rd Victoria BC V9E 1C8",
    "addr:housenumber":"3352",
    "addr:postcode":"v9e 1c8",
    "addr:street":"Compton Rd",
    "iso:country":"CA",
    "sg:address":"3352 Compton Rd",
    "sg:city":"Victoria",
    "sg:classifiers":[
        {
            "category":"Autos & Motor Vehicles",
            "subcategory":"Auto Supplies",
            "type":"Retail Goods"
        }
    ],
    "sg:phone":"+1 250 727 2890",
    "sg:postcode":"V9E 1C8",
    "sg:province":"BC",
    "sg:tags":[
        "equipment",
        "welding",
        "racing",
        "car",
        "automobile"
    ],
    "wof:name":"A & A Performance Chasis",
    "wof:placetype":"venue"
},
  "geometry": {"coordinates":[-123.364517212,48.428314209],"type":"Point"}
}