{
  "type": "Feature",
  "properties": {
    "addr:full":"13 Tennessee Dr Stephenville NL A2N 2Y3",
    "addr:housenumber":"13",
    "addr:postcode":"a2n 2y3",
    "addr:street":"Tennessee Dr",
    "iso:country":"CA",
    "sg:address":"13 Tennessee Dr",
    "sg:city":"Stephenville",
    "sg:classifiers":[
        {
            "category":"Airline",
            "type":"Transportation"
        }
    ],
    "sg:phone":"+1 709 643 3400",
    "sg:postcode":"A2N 2Y3",
    "sg:province":"NL",
    "sg:tags":[
        "company"
    ],
    "wof:name":"Provincial Airlines Ltd",
    "wof:placetype":"venue"
},
  "geometry": {"coordinates":[-58.564228,48.548248],"type":"Point"}
}