{
  "type": "Feature",
  "properties": {
    "addr:full":"Surrey BC V3S 7X1",
    "addr:postcode":"v3s 7x1",
    "iso:country":"CA",
    "sg:city":"Surrey",
    "sg:classifiers":[
        {
            "category":"Shopping",
            "subcategory":"Computers & Home Electronics",
            "type":"Retail Goods"
        }
    ],
    "sg:phone":"+1 604 702 5655",
    "sg:postcode":"V3S 7X1",
    "sg:province":"BC",
    "sg:tags":[
        "equipment",
        "dealer"
    ],
    "wof:name":"Basic Business Systems Ltd",
    "wof:placetype":"venue"
},
  "geometry": {"coordinates":[-122.73171234100001,49.1223068237],"type":"Point"}
}