{
  "type": "Feature",
  "properties": {
    "addr:full":"Rigaud QC J0P 1P0",
    "addr:postcode":"j0p 1p0",
    "iso:country":"CA",
    "sg:city":"Rigaud",
    "sg:classifiers":[
        {
            "category":"Social Services",
            "subcategory":"Child Care",
            "type":"Services"
        }
    ],
    "sg:phone":"+1 450 451 0025",
    "sg:postcode":"J0P 1P0",
    "sg:province":"QC",
    "wof:name":"Garderie Les Tourterelles Inc",
    "wof:placetype":"venue"
},
  "geometry": {"coordinates":[-74.291618,45.479366],"type":"Point"}
}