{
  "type": "Feature",
  "properties": {
    "addr:full":"1150 Montreal Rd Cornwall ON K6H 1E2",
    "addr:housenumber":"1150",
    "addr:postcode":"k6h 1e2",
    "addr:street":"Montreal Rd",
    "iso:country":"CA",
    "sg:address":"1150 Montreal Rd",
    "sg:city":"Cornwall",
    "sg:classifiers":[
        {
            "category":"Shopping",
            "subcategory":"Computers & Home Electronics",
            "type":"Retail Goods"
        }
    ],
    "sg:phone":"+1 613 938 8087",
    "sg:postcode":"K6H 1E2",
    "sg:province":"ON",
    "sg:tags":[
        "equipment",
        "dealer"
    ],
    "wof:name":"Micro Age Computers",
    "wof:placetype":"venue"
},
  "geometry": {"coordinates":[-74.6982727051,45.0198745728],"type":"Point"}
}