{
  "type": "Feature",
  "properties": {
    "addr:full":"1060 Georgia St W #160 Vancouver BC V6E 2Y2",
    "addr:housenumber":"1060",
    "addr:postcode":"v6e 2y2",
    "addr:street":"Georgia St W # 160",
    "iso:country":"CA",
    "sg:address":"1060 Georgia St W #160",
    "sg:city":"Vancouver",
    "sg:classifiers":[
        {
            "category":"Retail",
            "subcategory":"Laundry & Dry Cleaning",
            "type":"Services"
        }
    ],
    "sg:phone":"+1 604 669 1944",
    "sg:postcode":"V6E 2Y2",
    "sg:province":"BC",
    "sg:tags":[
        "cleaners"
    ],
    "wof:name":"Fast Iron Cleaners",
    "wof:placetype":"venue"
},
  "geometry": {"coordinates":[-123.122551,49.285202],"type":"Point"}
}