{
  "type": "Feature",
  "properties": {
    "addr:full":"4655 Lakelse Ave Terrace BC V8G 1R3",
    "addr:housenumber":"4655",
    "addr:postcode":"v8g 1r3",
    "addr:street":"Lakelse Ave",
    "iso:country":"CA",
    "sg:address":"4655 Lakelse Ave",
    "sg:city":"Terrace",
    "sg:classifiers":[
        {
            "category":"Food & Beverages",
            "subcategory":"Groceries & Convenience Stores",
            "type":"Retail Goods"
        }
    ],
    "sg:phone":"+1 250 635 1372",
    "sg:postcode":"V8G 1R3",
    "sg:province":"BC",
    "sg:tags":[
        "florist",
        "delicatessen"
    ],
    "wof:name":"Canada Safeway Ltd",
    "wof:placetype":"venue"
},
  "geometry": {"coordinates":[-128.59149199999999,54.516685],"type":"Point"}
}