{
  "type": "Feature",
  "properties": {
    "iso:country":"CA",
    "sg:city":"Pictou",
    "sg:phone":"+1 902 485 4376",
    "sg:postcode":"B0K 1H0",
    "sg:province":"NS",
    "sg:tags":[
        "automobile",
        "dealer"
    ],
    "wof:name":"Underwood Brothers Sales & Svc",
    "wof:placetype":"venue"
},
  "geometry": {"coordinates":[-62.7084236145,45.6759338379],"type":"Point"}
}