{
  "type": "Feature",
  "properties": {
    "addr:full":"Topley BC V0J 2Y0",
    "addr:postcode":"v0j 2y0",
    "iso:country":"CA",
    "sg:city":"Topley",
    "sg:classifiers":[
        {
            "category":"Food & Beverages",
            "subcategory":"Groceries & Convenience Stores",
            "type":"Retail Goods"
        }
    ],
    "sg:phone":"+1 250 696 3478",
    "sg:postcode":"V0J 2Y0",
    "sg:province":"BC",
    "sg:tags":[
        "grocer"
    ],
    "wof:name":"Topley Grocery",
    "wof:placetype":"venue"
},
  "geometry": {"coordinates":[-126.29652404799999,54.5053825378],"type":"Point"}
}