{
  "type": "Feature",
  "properties": {
    "addr:full":"Richmond BC V6X 2X9",
    "addr:postcode":"v6x 2x9",
    "iso:country":"CA",
    "sg:city":"Richmond",
    "sg:classifiers":[
        {
            "category":"Health Services",
            "subcategory":"Doctor",
            "type":"Services"
        }
    ],
    "sg:phone":"+1 604 278 1818",
    "sg:postcode":"V6X 2X9",
    "sg:province":"BC",
    "sg:tags":[
        "dentist"
    ],
    "wof:name":"Ng, Stanley DDS",
    "wof:placetype":"venue"
},
  "geometry": {"coordinates":[-123.136291504,49.1751708984],"type":"Point"}
}