{
  "type": "Feature",
  "properties": {
    "addr:full":"142 Provost St New Glasgow NS B2H 2P7",
    "addr:housenumber":"142",
    "addr:postcode":"b2h 2p7",
    "addr:street":"Provost St",
    "iso:country":"CA",
    "sg:address":"142 Provost St",
    "sg:city":"New Glasgow",
    "sg:classifiers":[
        {
            "category":"Real Estate",
            "subcategory":"Real Estate Agent",
            "type":"Services"
        }
    ],
    "sg:phone":"+1 902 755 4250",
    "sg:postcode":"B2H 2P7",
    "sg:province":"NS",
    "wof:name":"J F Mac Ivor Properties",
    "wof:placetype":"venue"
},
  "geometry": {"coordinates":[-62.644825,45.587578],"type":"Point"}
}