{
  "type": "Feature",
  "properties": {
    "addr:full":"6724 Eustace Sooke BC V0S 1N0",
    "addr:housenumber":"6724",
    "addr:postcode":"v0s 1n0",
    "addr:street":"Eustace",
    "iso:country":"CA",
    "sg:address":"6724 Eustace",
    "sg:city":"Sooke",
    "sg:classifiers":[
        {
            "category":"Health Services",
            "subcategory":"Nursing And Care Facility",
            "type":"Services"
        }
    ],
    "sg:phone":"+1 250 642 3033",
    "sg:postcode":"V0S 1N0",
    "sg:province":"BC",
    "sg:tags":[
        "home",
        "retirement",
        "community"
    ],
    "wof:name":"Sooke Branch 54 Royal Canadian",
    "wof:placetype":"venue"
},
  "geometry": {"coordinates":[-123.72541809099999,48.3775520325],"type":"Point"}
}