{
  "type": "Feature",
  "properties": {
    "iso:country":"CA",
    "sg:address":"62 Dundas St E",
    "sg:city":"Napanee",
    "sg:classifiers":[
        {
            "category":"Restaurant",
            "type":"Food & Drink"
        }
    ],
    "sg:phone":"+1 613 354 7504",
    "sg:postcode":"K7R 1H8",
    "sg:province":"ON",
    "wof:name":"Louie's Pizzeria & Restaurant",
    "wof:placetype":"venue"
},
  "geometry": {"coordinates":[-76.9482421875,44.2483711243],"type":"Point"}
}