{
  "type": "Feature",
  "properties": {
    "addr:full":"245 Rue Du Pont Quebec QC G1K 6L6",
    "addr:housenumber":"245",
    "addr:postcode":"g1k 6l6",
    "addr:street":"Rue Du Pont",
    "iso:country":"CA",
    "sg:address":"245 Rue Du Pont",
    "sg:city":"Quebec",
    "sg:classifiers":[
        {
            "category":"Government",
            "subcategory":"Office",
            "type":"Public Place"
        }
    ],
    "sg:phone":"+1 418 641 6208",
    "sg:postcode":"G1K 6L6",
    "sg:province":"QC",
    "sg:tags":[
        "village"
    ],
    "wof:name":"Quebec Gestion Des Immeubles",
    "wof:placetype":"venue"
},
  "geometry": {"coordinates":[-71.222404,46.817963],"type":"Point"}
}