{
  "type": "Feature",
  "properties": {
    "addr:full":"Hamilton ON L9A 4X5",
    "addr:postcode":"l9a 4x5",
    "iso:country":"CA",
    "sg:city":"Hamilton",
    "sg:classifiers":[
        {
            "category":"Shopping",
            "subcategory":"Optical Goods",
            "type":"Retail Goods"
        }
    ],
    "sg:phone":"+1 905 387 8830",
    "sg:postcode":"L9A 4X5",
    "sg:province":"ON",
    "sg:tags":[
        "optician"
    ],
    "wof:name":"Illuminata Eyewear",
    "wof:placetype":"venue"
},
  "geometry": {"coordinates":[-79.864464,43.216755],"type":"Point"}
}