{
  "type": "Feature",
  "properties": {
    "addr:full":"1009 Rue Cusson Saint-Jerome QC J5L 1K2",
    "addr:housenumber":"1009",
    "addr:postcode":"j5l 1k2",
    "addr:street":"Rue Cusson Saint-Jerome",
    "iso:country":"CA",
    "sg:address":"1009 Rue Cusson",
    "sg:city":"Saint-Jerome",
    "sg:classifiers":[
        {
            "category":"Freight",
            "type":"Transportation"
        }
    ],
    "sg:phone":"+1 450 431 4550",
    "sg:postcode":"J5L 1K2",
    "sg:province":"QC",
    "sg:tags":[
        "trucking"
    ],
    "wof:name":"Aaml Transport Demenagement",
    "wof:placetype":"venue"
},
  "geometry": {"coordinates":[-74.04708100000001,45.785534],"type":"Point"}
}