{
  "type": "Feature",
  "properties": {
    "addr:full":"121 Hume St Collingwood ON L9Y 1V6",
    "addr:housenumber":"121",
    "addr:postcode":"l9y 1v6",
    "addr:street":"Hume St",
    "iso:country":"CA",
    "sg:address":"121 Hume St",
    "sg:city":"Collingwood",
    "sg:classifiers":[
        {
            "category":"Retail",
            "subcategory":"Car Wash",
            "type":"Services"
        }
    ],
    "sg:phone":"+1 705 444 1704",
    "sg:postcode":"L9Y 1V6",
    "sg:province":"ON",
    "sg:tags":[
        "polishing",
        "automobile",
        "washing",
        "detail"
    ],
    "wof:name":"John's Car Wash",
    "wof:placetype":"venue"
},
  "geometry": {"coordinates":[-80.21277600000001,44.496189],"type":"Point"}
}