{
  "type": "Feature",
  "properties": {
    "addr:full":"81175 Londesboro Rd Goderich ON N7A 3Y1",
    "addr:postcode":"81175;n7a 3y1",
    "addr:street":"Londesboro Rd",
    "iso:country":"CA",
    "sg:address":"81175 Londesboro Rd",
    "sg:city":"Goderich",
    "sg:classifiers":[
        {
            "category":"Travel",
            "subcategory":"Hotels & Motels",
            "type":"Entertainment"
        }
    ],
    "sg:phone":"+1 519 524 2191",
    "sg:postcode":"N7A 3Y1",
    "sg:province":"ON",
    "wof:name":"Benmiller Inn & Spa",
    "wof:placetype":"venue"
},
  "geometry": {"coordinates":[-81.7077636719,43.742641449],"type":"Point"}
}