{
  "type": "Feature",
  "properties": {
    "addr:full":"24 Pelham Rd St Catharines ON L2S 1R2",
    "addr:housenumber":"24",
    "addr:postcode":"l2s 1r2",
    "addr:street":"Pelham Rd",
    "iso:country":"CA",
    "sg:address":"24 Pelham Rd",
    "sg:city":"St Catharines",
    "sg:classifiers":[
        {
            "category":"Retail",
            "subcategory":"Self-service Laundry",
            "type":"Services"
        }
    ],
    "sg:phone":"+1 905 685 9821",
    "sg:postcode":"L2S 1R2",
    "sg:province":"ON",
    "wof:name":"King Koin Laundromat",
    "wof:placetype":"venue"
},
  "geometry": {"coordinates":[-79.2507553101,43.1457595825],"type":"Point"}
}