{
  "type": "Feature",
  "properties": {
    "addr:full":"2115 Rue DE LA Montagne Montreal QC H3G 1Z8",
    "addr:housenumber":"2115",
    "addr:postcode":"h3g 1z8",
    "addr:street":"Rue De La Montagne",
    "iso:country":"CA",
    "sg:address":"2115 Rue DE LA Montagne",
    "sg:city":"Montreal",
    "sg:classifiers":[
        {
            "category":"Banks & Credit Unions",
            "subcategory":"Investment Brokerage",
            "type":"Services"
        }
    ],
    "sg:phone":"+1 514 985 5757",
    "sg:postcode":"H3G 1Z8",
    "sg:province":"QC",
    "sg:tags":[
        "advisory",
        "financial"
    ],
    "wof:name":"Cfg Heward Investment Mgmt",
    "wof:placetype":"venue"
},
  "geometry": {"coordinates":[-73.57749200000001,45.499268],"type":"Point"}
}