{
  "type": "Feature",
  "properties": {
    "addr:full":"Verdun QC H3E 1J4",
    "addr:postcode":"h3e 1j4",
    "iso:country":"CA",
    "sg:city":"Verdun",
    "sg:classifiers":[
        {
            "category":"Health Services",
            "subcategory":"Optometrist",
            "type":"Services"
        }
    ],
    "sg:phone":"+1 514 762 2020",
    "sg:postcode":"H3E 1J4",
    "sg:province":"QC",
    "sg:tags":[
        "optical",
        "good"
    ],
    "wof:name":"Services Optometriques Inc",
    "wof:placetype":"venue"
},
  "geometry": {"coordinates":[-73.571762085,45.4590187073],"type":"Point"}
}