{
  "type": "Feature",
  "properties": {
    "addr:full":"29 Dunlop St W Barrie ON L4N 1A1",
    "addr:housenumber":"29",
    "addr:postcode":"l4n 1a1",
    "addr:street":"Dunlop St W",
    "iso:country":"CA",
    "sg:address":"29 Dunlop St W",
    "sg:city":"Barrie",
    "sg:classifiers":[
        {
            "category":"Restaurant",
            "type":"Food & Drink"
        }
    ],
    "sg:phone":"+1 705 728 4484",
    "sg:postcode":"L4N 1A1",
    "sg:province":"ON",
    "wof:name":"Pita Pit",
    "wof:placetype":"venue"
},
  "geometry": {"coordinates":[-79.69082641599999,44.3887863159],"type":"Point"}
}