{
  "type": "Feature",
  "properties": {
    "addr:full":"Lloydminster AB T9V 2E6",
    "addr:postcode":"t9v 2e6",
    "iso:country":"CA",
    "sg:city":"Lloydminster",
    "sg:classifiers":[
        {
            "category":"Manufacturing",
            "subcategory":"Tools & Machinery",
            "type":"Manufacturing & Wholesale Goods"
        }
    ],
    "sg:phone":"+1 780 875 1500",
    "sg:postcode":"T9V 2E6",
    "sg:province":"AB",
    "sg:tags":[
        "machine",
        "shop"
    ],
    "wof:name":"Eng Machining Ltd",
    "wof:placetype":"venue"
},
  "geometry": {"coordinates":[-110.01260376,53.3018035889],"type":"Point"}
}