{
  "type": "Feature",
  "properties": {
    "addr:full":"143 Prom Du Portage Hull QC J8X 2K4",
    "addr:housenumber":"143",
    "addr:postcode":"j8x 2k4",
    "addr:street":"Prom Du Portage",
    "iso:country":"CA",
    "sg:address":"143 Prom Du Portage",
    "sg:city":"Hull",
    "sg:classifiers":[
        {
            "category":"Shopping",
            "subcategory":"Jewelry",
            "type":"Retail Goods"
        }
    ],
    "sg:phone":"+1 819 777 4916",
    "sg:postcode":"J8X 2K4",
    "sg:province":"QC",
    "sg:tags":[
        "jeweler"
    ],
    "wof:name":"Bijouterie Richer & Snow Jewel",
    "wof:placetype":"venue"
},
  "geometry": {"coordinates":[-75.716179,45.426006],"type":"Point"}
}