{
  "type": "Feature",
  "properties": {
    "iso:country":"CA",
    "sg:address":"465 Norfinch Dr",
    "sg:city":"North York",
    "sg:classifiers":[
        {
            "category":"Wholesale",
            "subcategory":"Groceries",
            "type":"Manufacturing & Wholesale Goods"
        }
    ],
    "sg:phone":"+1 416 667 1919",
    "sg:postcode":"M3N 1Y7",
    "sg:province":"ON",
    "sg:tags":[
        "grocer"
    ],
    "wof:name":"Nutri Fresh Juice Dispenser",
    "wof:placetype":"venue"
},
  "geometry": {"coordinates":[-79.53109,43.767941],"type":"Point"}
}