{
  "type": "Feature",
  "properties": {
    "addr:full":"29 Huron St New Hamburg ON N3A 1K1",
    "addr:housenumber":"29",
    "addr:postcode":"n3a 1k1",
    "addr:street":"Huron St",
    "iso:country":"CA",
    "sg:address":"29 Huron St",
    "sg:city":"New Hamburg",
    "sg:classifiers":[
        {
            "category":"Banks & Credit Unions",
            "subcategory":"Bank",
            "type":"Services"
        }
    ],
    "sg:phone":"+1 519 662 1263",
    "sg:postcode":"N3A 1K1",
    "sg:province":"ON",
    "wof:name":"Royal Bank Financial Group",
    "wof:placetype":"venue"
},
  "geometry": {"coordinates":[-80.710037,43.378193],"type":"Point"}
}