{
  "type": "Feature",
  "properties": {
    "addr:full":"Winnipeg MB R3T 2A7",
    "addr:postcode":"r3t 2a7",
    "iso:country":"CA",
    "sg:city":"Winnipeg",
    "sg:classifiers":[
        {
            "category":"Building & Trades",
            "subcategory":"Construction",
            "type":"Services"
        }
    ],
    "sg:phone":"+1 204 945 9020",
    "sg:postcode":"R3T 2A7",
    "sg:province":"MB",
    "sg:tags":[
        "home",
        "builder",
        "general",
        "contractor"
    ],
    "wof:name":"Wise Choice Homes",
    "wof:placetype":"venue"
},
  "geometry": {"coordinates":[-97.15284729,49.8448257446],"type":"Point"}
}