{
  "type": "Feature",
  "properties": {
    "iso:country":"CA",
    "sg:address":"120 Columbus Dr",
    "sg:city":"Carbonear",
    "sg:classifiers":[
        {
            "category":"Real Estate",
            "subcategory":"Real Estate Operator",
            "type":"Services"
        }
    ],
    "sg:phone":"+1 709 596 5124",
    "sg:postcode":"A1Y 1B3",
    "sg:province":"NL",
    "sg:tags":[
        "mall",
        "shopping",
        "center"
    ],
    "wof:name":"Trinity Conception Square",
    "wof:placetype":"venue"
},
  "geometry": {"coordinates":[-53.2453117371,47.7265205383],"type":"Point"}
}