{
  "type": "Feature",
  "properties": {
    "addr:full":"North York ON M2N 5R2",
    "addr:postcode":"m2n 5r2",
    "iso:country":"CA",
    "sg:city":"North York",
    "sg:classifiers":[
        {
            "category":"Banks & Credit Unions",
            "subcategory":"Investment Brokerage",
            "type":"Services"
        }
    ],
    "sg:phone":"+1 416 222 1612",
    "sg:postcode":"M2N 5R2",
    "sg:province":"ON",
    "sg:tags":[
        "loan",
        "real estate"
    ],
    "wof:name":"Sas Financial Svc Inc",
    "wof:placetype":"venue"
},
  "geometry": {"coordinates":[-79.41389465330001,43.7725410461],"type":"Point"}
}