{
  "type": "Feature",
  "properties": {
    "addr:full":"326 Main St Shawville QC J0X 2Y0",
    "addr:housenumber":"326",
    "addr:postcode":"j0x 2y0",
    "addr:street":"Main St",
    "iso:country":"CA",
    "sg:address":"326 Main St",
    "sg:city":"Shawville",
    "sg:classifiers":[
        {
            "category":"Autos & Motor Vehicles",
            "subcategory":"Auto Supplies",
            "type":"Retail Goods"
        }
    ],
    "sg:phone":"+1 819 647 2261",
    "sg:postcode":"J0X 2Y0",
    "sg:province":"QC",
    "sg:tags":[
        "automobile",
        "parts"
    ],
    "wof:name":"Auto Parts Extra",
    "wof:placetype":"venue"
},
  "geometry": {"coordinates":[-76.49076843260001,45.603313446],"type":"Point"}
}