{
  "type": "Feature",
  "properties": {
    "addr:full":"3540 6th Ave Regina SK S4T 0N5",
    "addr:housenumber":"3540",
    "addr:postcode":"s4t 0n5",
    "addr:street":"6Th Ave",
    "iso:country":"CA",
    "sg:address":"3540 6th Ave",
    "sg:city":"Regina",
    "sg:classifiers":[
        {
            "category":"Organizations",
            "subcategory":"Religious Organization",
            "type":"Services"
        }
    ],
    "sg:phone":"+1 306 757 8421",
    "sg:postcode":"S4T 0N5",
    "sg:province":"SK",
    "sg:tags":[
        "church"
    ],
    "wof:name":"Morning Star Ministries",
    "wof:placetype":"venue"
},
  "geometry": {"coordinates":[-104.631790161,50.4599685669],"type":"Point"}
}