{
  "type": "Feature",
  "properties": {
    "addr:full":"1657 Barrington St # 310 Halifax NS B3J 2A1",
    "addr:housenumber":"1657",
    "addr:postcode":"ns b3j 2a1",
    "addr:street":"Barrington St # 310",
    "iso:country":"CA",
    "sg:address":"1657 Barrington St # 310",
    "sg:city":"Halifax",
    "sg:classifiers":[
        {
            "category":"Professional",
            "subcategory":"Lawyer & Legal Services",
            "type":"Services"
        }
    ],
    "sg:phone":"+1 902 422 5854",
    "sg:postcode":"B3J 2A1",
    "sg:province":"NS",
    "sg:tags":[
        "attorney"
    ],
    "wof:name":"Meisner, Mary E QC",
    "wof:placetype":"venue"
},
  "geometry": {"coordinates":[-63.573654,44.646854],"type":"Point"}
}