{
  "type": "Feature",
  "properties": {
    "addr:full":"Tottenham ON L0G 1W0",
    "addr:postcode":"l0g 1w0",
    "iso:country":"CA",
    "sg:city":"Tottenham",
    "sg:classifiers":[
        {
            "category":"Retail",
            "subcategory":"Animal Services",
            "type":"Services"
        }
    ],
    "sg:phone":"+1 416 675 4405",
    "sg:postcode":"L0G 1W0",
    "sg:province":"ON",
    "sg:tags":[
        "horse",
        "training"
    ],
    "wof:name":"Green Meadows Farm",
    "wof:placetype":"venue"
},
  "geometry": {"coordinates":[-79.80578613279999,44.0228767395],"type":"Point"}
}