{
  "type": "Feature",
  "properties": {
    "addr:full":"109 14 St NW Calgary AB T2N 1Z6",
    "addr:housenumber":"109 14",
    "addr:postcode":"t2n 1z6",
    "addr:street":"St Nw",
    "iso:country":"CA",
    "sg:address":"109 14 St NW",
    "sg:city":"Calgary",
    "sg:classifiers":[
        {
            "category":"Shopping",
            "subcategory":"Shoes",
            "type":"Retail Goods"
        }
    ],
    "sg:phone":"+1 403 270 8299",
    "sg:postcode":"T2N 1Z6",
    "sg:province":"AB",
    "wof:name":"Birkenstock",
    "wof:placetype":"venue"
},
  "geometry": {"coordinates":[-114.094902,51.05275],"type":"Point"}
}