{
  "type": "Feature",
  "properties": {
    "iso:country":"CA",
    "sg:city":"Montreal",
    "sg:classifiers":[
        {
            "category":"Health Services",
            "subcategory":"Doctor",
            "type":"Services"
        }
    ],
    "sg:phone":"+1 514 849 8391",
    "sg:postcode":"H2W 1V1",
    "sg:province":"QC",
    "sg:tags":[
        "clinic"
    ],
    "wof:name":"Clinique Orthopedique St-Urbai",
    "wof:placetype":"venue"
},
  "geometry": {"coordinates":[-73.578537,45.51503],"type":"Point"}
}