{
  "type": "Feature",
  "properties": {
    "addr:full":"Labrador City NL A2V 2W7",
    "addr:postcode":"a2v 2w7",
    "iso:country":"CA",
    "sg:city":"Labrador City",
    "sg:classifiers":[
        {
            "category":"Shopping",
            "subcategory":"Department Store",
            "type":"Retail Goods"
        }
    ],
    "sg:phone":"+1 709 944 3211",
    "sg:postcode":"A2V 2W7",
    "sg:province":"NL",
    "wof:name":"Hart's Department Store",
    "wof:placetype":"venue"
},
  "geometry": {"coordinates":[-66.9224014282,52.9484024048],"type":"Point"}
}