{
  "type": "Feature",
  "properties": {
    "addr:full":"522 Big Marsh Rd River Denys NS B0E 2Y0",
    "addr:housenumber":"522",
    "addr:postcode":"b0e 2y0",
    "addr:street":"Big Marsh Rd",
    "iso:country":"CA",
    "sg:address":"522 Big Marsh Rd",
    "sg:city":"River Denys",
    "sg:classifiers":[
        {
            "category":"Building & Trades",
            "subcategory":"Landscaping Services",
            "type":"Services"
        }
    ],
    "sg:phone":"+1 902 631 0325",
    "sg:postcode":"B0E 2Y0",
    "sg:province":"NS",
    "sg:tags":[
        "tree"
    ],
    "wof:name":"Germatt Woodchipping Svc",
    "wof:placetype":"venue"
},
  "geometry": {"coordinates":[-61.176071,45.831905],"type":"Point"}
}