{
  "type": "Feature",
  "properties": {
    "addr:full":"Three Hills AB T0M 2A0",
    "addr:postcode":"t0m 2a0",
    "iso:country":"CA",
    "sg:city":"Three Hills",
    "sg:classifiers":[
        {
            "category":"Real Estate",
            "subcategory":"Real Estate Agent",
            "type":"Services"
        }
    ],
    "sg:phone":"+1 403 443 5558",
    "sg:postcode":"T0M 2A0",
    "sg:province":"AB",
    "sg:tags":[
        "inspection"
    ],
    "wof:name":"Home Place Inspections Plus",
    "wof:placetype":"venue"
},
  "geometry": {"coordinates":[-113.27395629900001,51.6951904297],"type":"Point"}
}