{
  "type": "Feature",
  "properties": {
    "addr:full":"186 Main St # 4 Sturgeon Falls ON P2B 1N9",
    "addr:housenumber":"186",
    "addr:postcode":"p2b 1n9",
    "addr:street":"Main St # 4",
    "iso:country":"CA",
    "sg:address":"186 Main St # 4",
    "sg:city":"Sturgeon Falls",
    "sg:classifiers":[
        {
            "category":"Organizations",
            "subcategory":"Community Association",
            "type":"Services"
        }
    ],
    "sg:phone":"+1 705 753 1682",
    "sg:postcode":"P2B 1N9",
    "sg:province":"ON",
    "sg:tags":[
        "club"
    ],
    "wof:name":"Chevalier DE Colomb",
    "wof:placetype":"venue"
},
  "geometry": {"coordinates":[-79.9280700684,46.3684501648],"type":"Point"}
}