{
  "type": "Feature",
  "properties": {
    "addr:full":"Pickering ON L1W 1Z9",
    "addr:postcode":"l1w 1z9",
    "iso:country":"CA",
    "sg:city":"Pickering",
    "sg:classifiers":[
        {
            "category":"Shopping",
            "type":"Retail Goods"
        }
    ],
    "sg:phone":"+1 905 839 2425",
    "sg:postcode":"L1W 1Z9",
    "sg:province":"ON",
    "sg:tags":[
        "equipment",
        "telephone",
        "supply"
    ],
    "wof:name":"Mikala Inc",
    "wof:placetype":"venue"
},
  "geometry": {"coordinates":[-79.06471999999999,43.82613],"type":"Point"}
}