{
  "type": "Feature",
  "properties": {
    "addr:full":"4710 Railway Ave Vermilion AB T9X 1L7",
    "addr:housenumber":"4710",
    "addr:postcode":"t9x 1l7",
    "addr:street":"Railway Ave",
    "iso:country":"CA",
    "sg:address":"4710 Railway Ave",
    "sg:city":"Vermilion",
    "sg:classifiers":[
        {
            "category":"Home & Garden",
            "subcategory":"Building Materials",
            "type":"Retail Goods"
        }
    ],
    "sg:phone":"+1 780 853 4757",
    "sg:postcode":"T9X 1L7",
    "sg:province":"AB",
    "wof:name":"Home Building Ctr",
    "wof:placetype":"venue"
},
  "geometry": {"coordinates":[-110.843856812,53.3511505127],"type":"Point"}
}