{
  "type": "Feature",
  "properties": {
    "addr:full":"372 Pine St S Timmins ON P4N 2L3",
    "addr:housenumber":"372",
    "addr:postcode":"p4n 2l3",
    "addr:street":"Pine St S",
    "iso:country":"CA",
    "sg:address":"372 Pine St S",
    "sg:city":"Timmins",
    "sg:classifiers":[
        {
            "category":"Wholesale",
            "subcategory":"Meat",
            "type":"Manufacturing & Wholesale Goods"
        }
    ],
    "sg:phone":"+1 705 268 0226",
    "sg:postcode":"P4N 2L3",
    "sg:province":"ON",
    "sg:tags":[
        "product"
    ],
    "wof:name":"Butcher Shop",
    "wof:placetype":"venue"
},
  "geometry": {"coordinates":[-81.32828521730001,48.4684638977],"type":"Point"}
}