{
  "type": "Feature",
  "properties": {
    "addr:full":"Langley BC V2Y 1N8",
    "addr:postcode":"v2y 1n8",
    "iso:country":"CA",
    "sg:city":"Langley",
    "sg:classifiers":[
        {
            "category":"Wholesale",
            "subcategory":"Motor Vehicles",
            "type":"Manufacturing & Wholesale Goods"
        }
    ],
    "sg:phone":"+1 604 533 8881",
    "sg:postcode":"V2Y 1N8",
    "sg:province":"BC",
    "sg:tags":[
        "trailer"
    ],
    "wof:name":"Wheel in Truck & Trailer Rpr",
    "wof:placetype":"venue"
},
  "geometry": {"coordinates":[-122.650733948,49.1167411804],"type":"Point"}
}