{
  "type": "Feature",
  "properties": {
    "addr:full":"112 Main St Belleoram NL A0H 1B0",
    "addr:housenumber":"112",
    "addr:postcode":"a0h 1b0",
    "addr:street":"Main St",
    "iso:country":"CA",
    "sg:address":"112 Main St",
    "sg:city":"Belleoram",
    "sg:classifiers":[
        {
            "category":"Shopping",
            "subcategory":"Computers & Home Electronics",
            "type":"Retail Goods"
        }
    ],
    "sg:phone":"+1 709 881 4100",
    "sg:postcode":"A0H 1B0",
    "sg:province":"NL",
    "sg:tags":[
        "equipment",
        "satellite",
        "system"
    ],
    "wof:name":"Electronic Shop Inc",
    "wof:placetype":"venue"
},
  "geometry": {"coordinates":[-55.4121627808,47.5237464905],"type":"Point"}
}