{
  "type": "Feature",
  "properties": {
    "addr:full":"428 Dixon Ave Kamsack SK S0A 1S0",
    "addr:housenumber":"428",
    "addr:postcode":"s0a 1s0",
    "addr:street":"Dixon Ave",
    "iso:country":"CA",
    "sg:address":"428 Dixon Ave",
    "sg:city":"Kamsack",
    "sg:classifiers":[
        {
            "category":"Education",
            "subcategory":"School",
            "type":"Public Place"
        }
    ],
    "sg:phone":"+1 306 542 2521",
    "sg:postcode":"S0A 1S0",
    "sg:province":"SK",
    "wof:name":"Kamsack Comprehensive Inst",
    "wof:placetype":"venue"
},
  "geometry": {"coordinates":[-101.886161804,51.5625648499],"type":"Point"}
}