{
  "type": "Feature",
  "properties": {
    "addr:full":"235 Railroad Ave Treherne MB R0G 2V0",
    "addr:housenumber":"235",
    "addr:postcode":"r0g 2v0",
    "addr:street":"Railroad Ave",
    "iso:country":"CA",
    "sg:address":"235 Railroad Ave",
    "sg:city":"Treherne",
    "sg:classifiers":[
        {
            "category":"Home & Garden",
            "subcategory":"Building Materials",
            "type":"Retail Goods"
        }
    ],
    "sg:phone":"+1 204 723 2428",
    "sg:postcode":"R0G 2V0",
    "sg:province":"MB",
    "sg:tags":[
        "windows"
    ],
    "wof:name":"D & G Enterprises",
    "wof:placetype":"venue"
},
  "geometry": {"coordinates":[-98.6973571777,49.6357040405],"type":"Point"}
}