{
  "type": "Feature",
  "properties": {
    "addr:full":"2800 Dufferin St North York ON M6B 3R7",
    "addr:housenumber":"2800",
    "addr:postcode":"m6b 3r7",
    "addr:street":"Dufferin St",
    "iso:country":"CA",
    "sg:address":"2800 Dufferin St",
    "sg:city":"North York",
    "sg:classifiers":[
        {
            "category":"Retail",
            "subcategory":"Auto Repair",
            "type":"Services"
        }
    ],
    "sg:phone":"+1 416 781 6149",
    "sg:postcode":"M6B 3R7",
    "sg:province":"ON",
    "sg:tags":[
        "repairing",
        "automobile",
        "brake"
    ],
    "wof:name":"Midas Auto Svc Experts",
    "wof:placetype":"venue"
},
  "geometry": {"coordinates":[-79.452988,43.70528],"type":"Point"}
}