{
  "type": "Feature",
  "properties": {
    "iso:country":"CA",
    "sg:address":"19275 54 Ave",
    "sg:city":"Surrey",
    "sg:classifiers":[
        {
            "category":"Manufacturing",
            "subcategory":"Glass & Minerals",
            "type":"Manufacturing & Wholesale Goods"
        }
    ],
    "sg:phone":"+1 604 574 5748",
    "sg:postcode":"V3S 8E5",
    "sg:province":"BC",
    "sg:tags":[
        "concrete",
        "brick",
        "product",
        "block"
    ],
    "wof:name":"Kee Bee Svc",
    "wof:placetype":"venue"
},
  "geometry": {"coordinates":[-122.689109802,49.1013908386],"type":"Point"}
}