{
  "type": "Feature",
  "properties": {
    "addr:full":"Springford ON N0J 1X0",
    "addr:postcode":"n0j 1x0",
    "iso:country":"CA",
    "sg:city":"Springford",
    "sg:classifiers":[
        {
            "category":"Recreation",
            "type":"Entertainment"
        }
    ],
    "sg:phone":"+1 519 842 2675",
    "sg:postcode":"N0J 1X0",
    "sg:province":"ON",
    "sg:tags":[
        "hall",
        "auditorium"
    ],
    "wof:name":"Springford Community Hall",
    "wof:placetype":"venue"
},
  "geometry": {"coordinates":[-80.67144,42.916512],"type":"Point"}
}