{
  "type": "Feature",
  "properties": {
    "addr:full":"1195 Boul Des Laurentides Saint-Jerome QC J7Z 7L3",
    "addr:housenumber":"1195",
    "addr:postcode":"j7z 7l3",
    "addr:street":"Boul Des Laurentides",
    "iso:country":"CA",
    "sg:address":"1195 Boul Des Laurentides",
    "sg:city":"Saint-Jerome",
    "sg:classifiers":[
        {
            "category":"Restaurant",
            "type":"Food & Drink"
        }
    ],
    "sg:phone":"+1 450 565 9020",
    "sg:postcode":"J7Z 7L3",
    "sg:province":"QC",
    "wof:name":"Buffet Chinois Ming Wah",
    "wof:placetype":"venue"
},
  "geometry": {"coordinates":[-73.9805526733,45.754901886],"type":"Point"}
}