{
  "type": "Feature",
  "properties": {
    "addr:full":"5240 1A St SE Calgary AB T2H 1J1",
    "addr:housenumber":"5240",
    "addr:postcode":"t2h 1j1",
    "addr:street":"1A St Se",
    "iso:country":"CA",
    "sg:address":"5240 1A St SE",
    "sg:city":"Calgary",
    "sg:classifiers":[
        {
            "category":"Retail",
            "subcategory":"Repair Shop",
            "type":"Services"
        }
    ],
    "sg:phone":"+1 403 212 1005",
    "sg:postcode":"T2H 1J1",
    "sg:province":"AB",
    "sg:tags":[
        "upholsterer"
    ],
    "wof:name":"Spencer's Upholstery",
    "wof:placetype":"venue"
},
  "geometry": {"coordinates":[-114.061211,51.008087],"type":"Point"}
}