{
  "type": "Feature",
  "properties": {
    "addr:full":"107 Dunelm St Scarborough ON M1J 3G3",
    "addr:housenumber":"107",
    "addr:postcode":"m1j 3g3",
    "addr:street":"Dunelm St",
    "iso:country":"CA",
    "sg:address":"107 Dunelm St",
    "sg:city":"Scarborough",
    "sg:classifiers":[
        {
            "category":"Professional",
            "subcategory":"Management & Consulting",
            "type":"Services"
        }
    ],
    "sg:phone":"+1 416 266 3871",
    "sg:postcode":"M1J 3G3",
    "sg:province":"ON",
    "sg:tags":[
        "consultant",
        "business"
    ],
    "wof:name":"Cynthia Calluori & Assn Inc",
    "wof:placetype":"venue"
},
  "geometry": {"coordinates":[-79.214515686,43.7484016418],"type":"Point"}
}