{
  "type": "Feature",
  "properties": {
    "addr:full":"837 Memorial Ave RR 1 Orillia ON L3V 6H1",
    "addr:housenumber":"837",
    "addr:postcode":"l3v 6h1",
    "addr:street":"Memorial Ave Rr 1",
    "iso:country":"CA",
    "sg:address":"837 Memorial Ave RR 1",
    "sg:city":"Orillia",
    "sg:classifiers":[
        {
            "category":"Autos & Motor Vehicles",
            "subcategory":"Fuel & Gas Station",
            "type":"Retail Goods"
        }
    ],
    "sg:phone":"+1 705 325 8300",
    "sg:postcode":"L3V 6H1",
    "sg:province":"ON",
    "sg:tags":[
        "repairing",
        "automobile",
        "oil"
    ],
    "wof:name":"Bob's Discount Svc",
    "wof:placetype":"venue"
},
  "geometry": {"coordinates":[-79.43620300000001,44.578487],"type":"Point"}
}