{
  "type": "Feature",
  "properties": {
    "iso:country":"CA",
    "sg:address":"1154 Morningside Ave",
    "sg:city":"Scarborough",
    "sg:classifiers":[
        {
            "category":"Restaurant",
            "type":"Food & Drink"
        }
    ],
    "sg:phone":"+1 416 281 8222",
    "sg:postcode":"M1B 3A4",
    "sg:province":"ON",
    "wof:name":"Darlyn's Restaurant",
    "wof:placetype":"venue"
},
  "geometry": {"coordinates":[-79.1996383667,43.8011665344],"type":"Point"}
}