{
  "type": "Feature",
  "properties": {
    "addr:full":"100 University Ave E Cobourg ON K9A 1C8",
    "addr:housenumber":"100",
    "addr:postcode":"k9a 1c8",
    "addr:street":"University Ave E",
    "iso:country":"CA",
    "sg:address":"100 University Ave E",
    "sg:city":"Cobourg",
    "sg:classifiers":[
        {
            "category":"Health Services",
            "subcategory":"Nursing And Care Facility",
            "type":"Services"
        }
    ],
    "sg:phone":"+1 905 377 1555",
    "sg:postcode":"K9A 1C8",
    "sg:province":"ON",
    "sg:tags":[
        "home",
        "retirement",
        "community"
    ],
    "wof:name":"Victoria Retirement Living",
    "wof:placetype":"venue"
},
  "geometry": {"coordinates":[-78.16424600000001,43.965172],"type":"Point"}
}