{
  "type": "Feature",
  "properties": {
    "addr:full":"910 102 Ave Dawson Creek BC V1G 2B7",
    "addr:housenumber":"910",
    "addr:postcode":"v1g 2b7",
    "addr:street":"102 Ave",
    "iso:country":"CA",
    "sg:address":"910 102 Ave",
    "sg:city":"Dawson Creek",
    "sg:classifiers":[
        {
            "category":"Restaurant",
            "type":"Food & Drink"
        }
    ],
    "sg:phone":"+1 250 782 8297",
    "sg:postcode":"V1G 2B7",
    "sg:province":"BC",
    "wof:name":"Orion Restaurant",
    "wof:placetype":"venue"
},
  "geometry": {"coordinates":[-120.226631165,55.7580718994],"type":"Point"}
}