{
  "type": "Feature",
  "properties": {
    "addr:full":"8780 Rue D'Arras Saint-Leonard QC H1P 2Y6",
    "addr:housenumber":"8780",
    "addr:postcode":"h1p 2y6",
    "addr:street":"Rue D'Arras",
    "iso:country":"CA",
    "sg:address":"8780 Rue D'Arras",
    "sg:city":"Saint-Leonard",
    "sg:classifiers":[
        {
            "category":"Retail",
            "subcategory":"Portrait Studio",
            "type":"Services"
        }
    ],
    "sg:phone":"+1 514 322 4214",
    "sg:postcode":"H1P 2Y6",
    "sg:province":"QC",
    "sg:tags":[
        "photographer"
    ],
    "wof:name":"Aldo DE Lisio",
    "wof:placetype":"venue"
},
  "geometry": {"coordinates":[-73.5953216553,45.5988426208],"type":"Point"}
}