{
  "type": "Feature",
  "properties": {
    "addr:full":"2320 Stevenage Dr Ottawa ON K1G 3W3",
    "addr:housenumber":"2320",
    "addr:postcode":"k1g 3w3",
    "addr:street":"Stevenage Dr",
    "iso:country":"CA",
    "sg:address":"2320 Stevenage Dr",
    "sg:city":"Ottawa",
    "sg:classifiers":[
        {
            "category":"Professional",
            "subcategory":"Business Services",
            "type":"Services"
        }
    ],
    "sg:phone":"+1 613 744 4389",
    "sg:postcode":"K1G 3W3",
    "sg:province":"ON",
    "sg:tags":[
        "fire",
        "protection"
    ],
    "wof:name":"C & C Welding",
    "wof:placetype":"venue"
},
  "geometry": {"coordinates":[-75.6096496582,45.3798141479],"type":"Point"}
}