{
  "type": "Feature",
  "properties": {
    "addr:full":"6104 Davies Rd NW Edmonton AB T6E 4M9",
    "addr:housenumber":"6104",
    "addr:postcode":"t6e 4m9",
    "addr:street":"Davies Rd Nw",
    "iso:country":"CA",
    "sg:address":"6104 Davies Rd NW",
    "sg:city":"Edmonton",
    "sg:classifiers":[
        {
            "category":"Building & Trades",
            "subcategory":"Plumbing",
            "type":"Services"
        }
    ],
    "sg:phone":"+1 780 413 0075",
    "sg:postcode":"T6E 4M9",
    "sg:province":"AB",
    "sg:tags":[
        "cleaning",
        "boiler"
    ],
    "wof:name":"Mechanical World Inc",
    "wof:placetype":"venue"
},
  "geometry": {"coordinates":[-113.446609497,53.4980545044],"type":"Point"}
}