{
  "type": "Feature",
  "properties": {
    "addr:full":"Winnipeg MB R2G 2T7",
    "addr:postcode":"r2g 2t7",
    "iso:country":"CA",
    "sg:city":"Winnipeg",
    "sg:classifiers":[
        {
            "category":"Health Services",
            "subcategory":"Chiropractor",
            "type":"Services"
        }
    ],
    "sg:phone":"+1 204 663 1551",
    "sg:postcode":"R2G 2T7",
    "sg:province":"MB",
    "wof:name":"Mc Leod Chiropractic Clinic",
    "wof:placetype":"venue"
},
  "geometry": {"coordinates":[-97.06768,49.928242],"type":"Point"}
}