{
  "type": "Feature",
  "properties": {
    "addr:full":"75 Sparks St Ottawa ON K1P 5A5",
    "addr:housenumber":"75",
    "addr:postcode":"k1p 5a5",
    "addr:street":"Sparks St",
    "iso:country":"CA",
    "sg:address":"75 Sparks St",
    "sg:city":"Ottawa",
    "sg:classifiers":[
        {
            "category":"Organizations",
            "subcategory":"Membership Organization",
            "type":"Services"
        }
    ],
    "sg:phone":"+1 613 232 2387",
    "sg:postcode":"K1P 5A5",
    "sg:province":"ON",
    "sg:tags":[
        "meditation",
        "instruction"
    ],
    "wof:name":"Sri Chinmoy Ctr",
    "wof:placetype":"venue"
},
  "geometry": {"coordinates":[-75.6971130371,45.4231567383],"type":"Point"}
}