{
  "type": "Feature",
  "properties": {
    "addr:full":"Grande Prairie AB T8V 5M7",
    "addr:postcode":"t8v 5m7",
    "iso:country":"CA",
    "sg:city":"Grande Prairie",
    "sg:classifiers":[
        {
            "category":"Personal",
            "subcategory":"Beauty Salon",
            "type":"Services"
        }
    ],
    "sg:phone":"+1 780 532 4531",
    "sg:postcode":"T8V 5M7",
    "sg:province":"AB",
    "wof:name":"South Side Hair & Nail Studio",
    "wof:placetype":"venue"
},
  "geometry": {"coordinates":[-118.779526,55.148232],"type":"Point"}
}