{
  "type": "Feature",
  "properties": {
    "iso:country":"CA",
    "sg:city":"Barrie",
    "sg:classifiers":[
        {
            "category":"Restaurant",
            "type":"Food & Drink"
        }
    ],
    "sg:phone":"+1 705 739 8888",
    "sg:postcode":"L4N 7L2",
    "sg:province":"ON",
    "wof:name":"Wok Inn",
    "wof:placetype":"venue"
},
  "geometry": {"coordinates":[-79.706932,44.381973],"type":"Point"}
}