{
  "type": "Feature",
  "properties": {
    "iso:country":"CA",
    "sg:address":"4403 52 St",
    "sg:city":"Vermilion",
    "sg:classifiers":[
        {
            "category":"Wholesale",
            "subcategory":"Petroleum",
            "type":"Manufacturing & Wholesale Goods"
        }
    ],
    "sg:phone":"+1 780 853 5039",
    "sg:postcode":"T9X 1J8",
    "sg:province":"AB",
    "sg:tags":[
        "bulk",
        "oil",
        "gasoline"
    ],
    "wof:name":"Vermilion Husky Bulk Plant",
    "wof:placetype":"venue"
},
  "geometry": {"coordinates":[-110.858818054,53.3482322693],"type":"Point"}
}