{
  "type": "Feature",
  "properties": {
    "addr:full":"170 Rue Gerard-Morisset Quebec QC G1S 4X3",
    "addr:housenumber":"170",
    "addr:postcode":"g1s 4x3",
    "addr:street":"Rue Gerard-Morisset",
    "iso:country":"CA",
    "sg:address":"170 Rue Gerard-Morisset",
    "sg:city":"Quebec",
    "sg:classifiers":[
        {
            "category":"Real Estate",
            "subcategory":"Real Estate Agent",
            "type":"Services"
        }
    ],
    "sg:phone":"+1 418 687 0617",
    "sg:postcode":"G1S 4X3",
    "sg:province":"QC",
    "sg:tags":[
        "management"
    ],
    "wof:name":"Condominiums Le 170 Enr",
    "wof:placetype":"venue"
},
  "geometry": {"coordinates":[-71.2558670044,46.7895393372],"type":"Point"}
}