{
  "type": "Feature",
  "properties": {
    "addr:full":"62 Main St Blackville NB E9B 1N4",
    "addr:housenumber":"62",
    "addr:postcode":"e9b 1n4",
    "addr:street":"Main St",
    "iso:country":"CA",
    "sg:address":"62 Main St",
    "sg:city":"Blackville",
    "sg:classifiers":[
        {
            "category":"Manufacturing",
            "subcategory":"Lumber",
            "type":"Manufacturing & Wholesale Goods"
        }
    ],
    "sg:phone":"+1 506 843 6401",
    "sg:postcode":"E9B 1N4",
    "sg:province":"NB",
    "wof:name":"Blackville Lumber Inc",
    "wof:placetype":"venue"
},
  "geometry": {"coordinates":[-65.8314590454,46.7268180847],"type":"Point"}
}