{
  "type": "Feature",
  "properties": {
    "addr:full":"604 Main St S Slave Lake AB T0G 2A3",
    "addr:housenumber":"604",
    "addr:postcode":"t0g 2a3",
    "addr:street":"Main St S Slave",
    "iso:country":"CA",
    "sg:address":"604 Main St S",
    "sg:city":"Slave Lake",
    "sg:classifiers":[
        {
            "category":"Restaurant",
            "type":"Food & Drink"
        }
    ],
    "sg:phone":"+1 780 849 9699",
    "sg:postcode":"T0G 2A3",
    "sg:province":"AB",
    "wof:name":"Boston Pizza",
    "wof:placetype":"venue"
},
  "geometry": {"coordinates":[-114.773971558,55.277469635],"type":"Point"}
}