{
  "type": "Feature",
  "properties": {
    "addr:full":"545 Boul Du College Rouyn-Noranda QC J9X 5C6",
    "addr:housenumber":"545",
    "addr:postcode":"j9x 5c6",
    "addr:street":"Boul Du College",
    "iso:country":"CA",
    "sg:address":"545 Boul Du College",
    "sg:city":"Rouyn-Noranda",
    "sg:classifiers":[
        {
            "category":"Social Services",
            "subcategory":"Child Care",
            "type":"Services"
        }
    ],
    "sg:phone":"+1 819 762 7121",
    "sg:postcode":"J9X 5C6",
    "sg:province":"QC",
    "wof:name":"Cpe Fleur & Miel Inc",
    "wof:placetype":"venue"
},
  "geometry": {"coordinates":[-79.0077590942,48.2278747559],"type":"Point"}
}