{
  "type": "Feature",
  "properties": {
    "iso:country":"CA",
    "sg:address":"85 Dalton Ave",
    "sg:city":"Kingston",
    "sg:classifiers":[
        {
            "category":"Restaurant",
            "type":"Food & Drink"
        }
    ],
    "sg:phone":"+1 613 547 0100",
    "sg:postcode":"K7K 6C2",
    "sg:province":"ON",
    "wof:name":"Swiss Chalet Rotisserie/Grill",
    "wof:placetype":"venue"
},
  "geometry": {"coordinates":[-76.501175,44.265903],"type":"Point"}
}