{
  "type": "Feature",
  "properties": {
    "addr:full":"163 11E Av Dolbeau-Mistassini QC G8L 2H1",
    "addr:housenumber":"163",
    "addr:postcode":"g8l 2h1",
    "addr:street":"11E Av Dolbeau-Mistassini",
    "iso:country":"CA",
    "sg:address":"163 11E Av",
    "sg:city":"Dolbeau-Mistassini",
    "sg:classifiers":[
        {
            "category":"Education",
            "subcategory":"School",
            "type":"Public Place"
        }
    ],
    "sg:phone":"+1 418 276 1305",
    "sg:postcode":"G8L 2H1",
    "sg:province":"QC",
    "wof:name":"Ecole Sacre-Coeur",
    "wof:placetype":"venue"
},
  "geometry": {"coordinates":[-72.23946380620001,48.8842926025],"type":"Point"}
}