{
  "type": "Feature",
  "properties": {
    "addr:full":"540 Lower Ganges Rd Salt Spring Island BC V8K 2P6",
    "addr:housenumber":"540",
    "addr:postcode":"v8k 2p6",
    "addr:street":"Lower Ganges Rd",
    "iso:country":"CA",
    "sg:address":"540 Lower Ganges Rd",
    "sg:city":"Salt Spring Island",
    "sg:classifiers":[
        {
            "category":"Retail",
            "subcategory":"Veterinary Services",
            "type":"Services"
        }
    ],
    "sg:phone":"+1 250 537 5334",
    "sg:postcode":"V8K 2P6",
    "sg:province":"BC",
    "sg:tags":[
        "veterinarian"
    ],
    "wof:name":"Gulf Islands Veterinary Clinic",
    "wof:placetype":"venue"
},
  "geometry": {"coordinates":[-123.521294,48.863777],"type":"Point"}
}