{
  "type": "Feature",
  "properties": {
    "addr:full":"206 St Lawrence St Merrickville ON K0G 1N0",
    "addr:housenumber":"206",
    "addr:postcode":"k0g 1n0",
    "addr:street":"St Lawrence St",
    "iso:country":"CA",
    "sg:address":"206 St Lawrence St",
    "sg:city":"Merrickville",
    "sg:classifiers":[
        {
            "category":"Shopping",
            "subcategory":"Gifts & Souvenirs",
            "type":"Retail Goods"
        }
    ],
    "sg:phone":"+1 613 269 2761",
    "sg:postcode":"K0G 1N0",
    "sg:province":"ON",
    "sg:tags":[
        "shop"
    ],
    "wof:name":"Country Bumpkins",
    "wof:placetype":"venue"
},
  "geometry": {"coordinates":[-75.836861,44.915272],"type":"Point"}
}