{
  "type": "Feature",
  "properties": {
    "addr:full":"Barrie ON L4N 4C8",
    "addr:postcode":"l4n 4c8",
    "iso:country":"CA",
    "sg:city":"Barrie",
    "sg:classifiers":[
        {
            "category":"Retail",
            "subcategory":"Auto Repair",
            "type":"Services"
        }
    ],
    "sg:phone":"+1 705 735 9992",
    "sg:postcode":"L4N 4C8",
    "sg:province":"ON",
    "sg:tags":[
        "repairing",
        "automobile"
    ],
    "wof:name":"Master Mechanic Barrie",
    "wof:placetype":"venue"
},
  "geometry": {"coordinates":[-79.669067,44.36993],"type":"Point"}
}