{
  "type": "Feature",
  "properties": {
    "iso:country":"CA",
    "sg:address":"501 Canada Ave",
    "sg:city":"Duncan",
    "sg:classifiers":[
        {
            "category":"Restaurant",
            "type":"Food & Drink"
        }
    ],
    "sg:phone":"+1 250 715 1540",
    "sg:postcode":"V9L 1T8",
    "sg:province":"BC",
    "sg:tags":[
        "shop",
        "coffee"
    ],
    "wof:name":"Coffee on the Moon",
    "wof:placetype":"venue"
},
  "geometry": {"coordinates":[-123.70810699499999,48.7809181213],"type":"Point"}
}