{
  "type": "Feature",
  "properties": {
    "addr:full":"Dorchester ON N0L 1G5",
    "addr:postcode":"n0l 1g5",
    "iso:country":"CA",
    "sg:city":"Dorchester",
    "sg:classifiers":[
        {
            "category":"Health Services",
            "subcategory":"Health Practitioner",
            "type":"Services"
        }
    ],
    "sg:phone":"+1 519 268 6000",
    "sg:postcode":"N0L 1G5",
    "sg:province":"ON",
    "sg:tags":[
        "occupational",
        "safety"
    ],
    "wof:name":"Millennium Compliance Svc",
    "wof:placetype":"venue"
},
  "geometry": {"coordinates":[-81.0611495972,42.959690094],"type":"Point"}
}