{
  "type": "Feature",
  "properties": {
    "addr:full":"900 Mountain Ave Crossfield AB T0M 0S0",
    "addr:housenumber":"900",
    "addr:postcode":"t0m 0s0",
    "addr:street":"Mountain Ave",
    "iso:country":"CA",
    "sg:address":"900 Mountain Ave",
    "sg:city":"Crossfield",
    "sg:classifiers":[
        {
            "category":"Recreation",
            "type":"Entertainment"
        }
    ],
    "sg:phone":"+1 403 946 5554",
    "sg:postcode":"T0M 0S0",
    "sg:province":"AB",
    "sg:tags":[
        "hall",
        "auditorium"
    ],
    "wof:name":"Crossfield & District Comm Ctr",
    "wof:placetype":"venue"
},
  "geometry": {"coordinates":[-114.025558472,51.4327507019],"type":"Point"}
}