{
  "type": "Feature",
  "properties": {
    "addr:full":"1029 Aggregate Trl Harcourt ON K0L 1X0",
    "addr:housenumber":"1029",
    "addr:postcode":"k0l 1x0",
    "addr:street":"Aggregate Trl",
    "iso:country":"CA",
    "sg:address":"1029 Aggregate Trl",
    "sg:city":"Harcourt",
    "sg:classifiers":[
        {
            "category":"Wholesale",
            "subcategory":"Construction Materials",
            "type":"Manufacturing & Wholesale Goods"
        }
    ],
    "sg:phone":"+1 705 448 9094",
    "sg:postcode":"K0L 1X0",
    "sg:province":"ON",
    "sg:tags":[
        "sand",
        "gravel"
    ],
    "wof:name":"Trotter Lumber & Aggregate Inc",
    "wof:placetype":"venue"
},
  "geometry": {"coordinates":[-78.1474761963,45.0849304199],"type":"Point"}
}