{
  "type": "Feature",
  "properties": {
    "addr:full":"608 Rue Du Portage Repentigny QC J6A 7M1",
    "addr:housenumber":"608",
    "addr:postcode":"j6a 7m1",
    "addr:street":"Rue Du Portage",
    "iso:country":"CA",
    "sg:address":"608 Rue Du Portage",
    "sg:city":"Repentigny",
    "sg:classifiers":[
        {
            "category":"Retail",
            "subcategory":"Laundry & Dry Cleaning",
            "type":"Services"
        }
    ],
    "sg:phone":"+1 450 585 3390",
    "sg:postcode":"J6A 7M1",
    "sg:province":"QC",
    "sg:tags":[
        "cleaners",
        "rug",
        "carpet"
    ],
    "wof:name":"Nettoyage DE Tapis J Cardinal",
    "wof:placetype":"venue"
},
  "geometry": {"coordinates":[-73.4588851929,45.7502479553],"type":"Point"}
}