{
  "type": "Feature",
  "properties": {
    "addr:full":"385 Jane St Toronto ON M6S 3Z3",
    "addr:housenumber":"385",
    "addr:postcode":"m6s 3z3",
    "addr:street":"Jane St",
    "iso:country":"CA",
    "sg:address":"385 Jane St",
    "sg:city":"Toronto",
    "sg:classifiers":[
        {
            "category":"Food & Beverages",
            "subcategory":"Bakery",
            "type":"Retail Goods"
        }
    ],
    "sg:phone":"+1 416 767 5871",
    "sg:postcode":"M6S 3Z3",
    "sg:province":"ON",
    "sg:tags":[
        "baker"
    ],
    "wof:name":"Pastry Chef",
    "wof:placetype":"venue"
},
  "geometry": {"coordinates":[-79.48782300000001,43.657974],"type":"Point"}
}