{
  "type": "Feature",
  "properties": {
    "addr:full":"126 Sydney St Cornwall ON K6H 3H2",
    "addr:housenumber":"126",
    "addr:postcode":"k6h 3h2",
    "addr:street":"Sydney St",
    "iso:country":"CA",
    "sg:address":"126 Sydney St",
    "sg:city":"Cornwall",
    "sg:classifiers":[
        {
            "category":"Professional",
            "subcategory":"Lawyer & Legal Services",
            "type":"Services"
        }
    ],
    "sg:phone":"+1 613 933 9455",
    "sg:postcode":"K6H 3H2",
    "sg:province":"ON",
    "sg:tags":[
        "attorney"
    ],
    "wof:name":"Paul, Ian",
    "wof:placetype":"venue"
},
  "geometry": {"coordinates":[-74.72622699999999,45.017811],"type":"Point"}
}