{
  "type": "Feature",
  "properties": {
    "addr:full":"9129 111 Ave NW Edmonton AB T5B 0C3",
    "addr:housenumber":"9129",
    "addr:postcode":"t5b 0c3",
    "addr:street":"111 Ave Nw",
    "iso:country":"CA",
    "sg:address":"9129 111 Ave NW",
    "sg:city":"Edmonton",
    "sg:classifiers":[
        {
            "category":"Autos & Motor Vehicles",
            "subcategory":"Fuel & Gas Station",
            "type":"Retail Goods"
        }
    ],
    "sg:phone":"+1 780 471 2100",
    "sg:postcode":"T5B 0C3",
    "sg:province":"AB",
    "sg:tags":[
        "oil"
    ],
    "wof:name":"Fillmore Gas",
    "wof:placetype":"venue"
},
  "geometry": {"coordinates":[-113.48194100000001,53.560589],"type":"Point"}
}