{
  "type": "Feature",
  "properties": {
    "iso:country":"CA",
    "sg:address":"18 Griffith Rd",
    "sg:city":"Stratford",
    "sg:classifiers":[
        {
            "category":"Retail",
            "subcategory":"Repair Shop",
            "type":"Services"
        }
    ],
    "sg:phone":"+1 519 273 2162",
    "sg:postcode":"N5A 6S4",
    "sg:province":"ON",
    "sg:tags":[
        "lock",
        "locksmith"
    ],
    "wof:name":"D & J Mc Culloch Lock Svc",
    "wof:placetype":"venue"
},
  "geometry": {"coordinates":[-80.9858016968,43.3517875671],"type":"Point"}
}