{
  "type": "Feature",
  "properties": {
    "addr:full":"Kitchener ON N2E 3J2",
    "addr:postcode":"n2e 3j2",
    "iso:country":"CA",
    "sg:city":"Kitchener",
    "sg:classifiers":[
        {
            "category":"Manufacturing",
            "subcategory":"Furniture",
            "type":"Manufacturing & Wholesale Goods"
        }
    ],
    "sg:phone":"+1 519 895 0250",
    "sg:postcode":"N2E 3J2",
    "sg:province":"ON",
    "sg:tags":[
        "baby",
        "accessory"
    ],
    "wof:name":"Sweet Kyla",
    "wof:placetype":"venue"
},
  "geometry": {"coordinates":[-80.46455400000001,43.402107],"type":"Point"}
}