{
  "type": "Feature",
  "properties": {
    "addr:full":"975 Cameron St Hawkesbury ON K6A 2B8",
    "addr:housenumber":"975",
    "addr:postcode":"k6a 2b8",
    "addr:street":"Cameron St",
    "iso:country":"CA",
    "sg:address":"975 Cameron St",
    "sg:city":"Hawkesbury",
    "sg:classifiers":[
        {
            "category":"Home & Garden",
            "subcategory":"Building Materials",
            "type":"Retail Goods"
        }
    ],
    "sg:phone":"+1 613 632 7722",
    "sg:postcode":"K6A 2B8",
    "sg:province":"ON",
    "sg:tags":[
        "glass",
        "window",
        "plate"
    ],
    "wof:name":"Gauthier Glass Ltd",
    "wof:placetype":"venue"
},
  "geometry": {"coordinates":[-74.59674800000001,45.599979],"type":"Point"}
}