{
  "type": "Feature",
  "properties": {
    "addr:full":"869 Boul Cure-Poirier O Longueuil QC J4K 2C3",
    "addr:housenumber":"869",
    "addr:postcode":"j4k 2c3",
    "addr:street":"Boul Cure-Poirier O",
    "iso:country":"CA",
    "sg:address":"869 Boul Cure-Poirier O",
    "sg:city":"Longueuil",
    "sg:classifiers":[
        {
            "category":"Home & Garden",
            "subcategory":"Home Furnishings",
            "type":"Retail Goods"
        }
    ],
    "sg:phone":"+1 450 674 1521",
    "sg:postcode":"J4K 2C3",
    "sg:province":"QC",
    "sg:tags":[
        "lighting",
        "fixture"
    ],
    "wof:name":"Mde Accessoires Elec Enr",
    "wof:placetype":"venue"
},
  "geometry": {"coordinates":[-73.476372,45.538731],"type":"Point"}
}