{
  "type": "Feature",
  "properties": {
    "addr:full":"5964 Av Notre-Dame-DE-Grace Montreal QC H4A 1N1",
    "addr:housenumber":"5964",
    "addr:postcode":"h4a 1n1",
    "addr:street":"Av Notre-Dame-De-Grace",
    "iso:country":"CA",
    "sg:address":"5964 Av Notre-Dame-DE-Grace",
    "sg:city":"Montreal",
    "sg:classifiers":[
        {
            "category":"Organizations",
            "subcategory":"Religious Organization",
            "type":"Services"
        }
    ],
    "sg:phone":"+1 514 484 7221",
    "sg:postcode":"H4A 1N1",
    "sg:province":"QC",
    "sg:tags":[
        "church"
    ],
    "wof:name":"Wesley United Church",
    "wof:placetype":"venue"
},
  "geometry": {"coordinates":[-73.6222229004,45.4693450928],"type":"Point"}
}