{
  "type": "Feature",
  "properties": {
    "iso:country":"CA",
    "sg:address":"20 Rue Francois-Richard",
    "sg:city":"Montmagny",
    "sg:classifiers":[
        {
            "category":"Personal",
            "subcategory":"Beauty Salon",
            "type":"Services"
        }
    ],
    "sg:phone":"+1 418 248 2467",
    "sg:postcode":"G5V 4A2",
    "sg:province":"QC",
    "wof:name":"Salon Elle",
    "wof:placetype":"venue"
},
  "geometry": {"coordinates":[-70.5661239624,46.9821510315],"type":"Point"}
}