{
  "type": "Feature",
  "properties": {
    "addr:full":"Odessa SK S0G 3S0",
    "addr:postcode":"s0g 3s0",
    "iso:country":"CA",
    "sg:city":"Odessa",
    "sg:classifiers":[
        {
            "category":"Retail",
            "subcategory":"Repair Shop",
            "type":"Services"
        }
    ],
    "sg:phone":"+1 306 957 4279",
    "sg:postcode":"S0G 3S0",
    "sg:province":"SK",
    "sg:tags":[
        "welding"
    ],
    "wof:name":"Adam's Welding & Machine Shop",
    "wof:placetype":"venue"
},
  "geometry": {"coordinates":[-103.781097,50.281212],"type":"Point"}
}