{
  "type": "Feature",
  "properties": {
    "addr:full":"31696 South Fraser Way Abbotsford BC V2T 1T9",
    "addr:housenumber":"31696",
    "addr:postcode":"v2t 1t9",
    "addr:street":"South Fraser Way",
    "iso:country":"CA",
    "sg:address":"31696 South Fraser Way",
    "sg:city":"Abbotsford",
    "sg:classifiers":[
        {
            "category":"Autos & Motor Vehicles",
            "subcategory":"Recreational Vehicle Sales",
            "type":"Retail Goods"
        }
    ],
    "sg:phone":"+1 604 850 2455",
    "sg:postcode":"V2T 1T9",
    "sg:province":"BC",
    "sg:tags":[
        "canopy",
        "shell",
        "truck",
        "cap"
    ],
    "wof:name":"Canopy West Truck Canopies",
    "wof:placetype":"venue"
},
  "geometry": {"coordinates":[-122.345467,49.046532],"type":"Point"}
}