{
  "type": "Feature",
  "properties": {
    "addr:full":"6939 Palm Ave Burnaby BC V5J 4M1",
    "addr:housenumber":"6939",
    "addr:postcode":"v5j 4m1",
    "addr:street":"Palm Ave",
    "iso:country":"CA",
    "sg:address":"6939 Palm Ave",
    "sg:city":"Burnaby",
    "sg:classifiers":[
        {
            "category":"Professional",
            "subcategory":"Accounting & Tax Preparation",
            "type":"Services"
        }
    ],
    "sg:phone":"+1 604 431 8444",
    "sg:postcode":"V5J 4M1",
    "sg:province":"BC",
    "sg:tags":[
        "accountant"
    ],
    "wof:name":"Fitzgerald, Kenneth H CA",
    "wof:placetype":"venue"
},
  "geometry": {"coordinates":[-122.987061,49.220757],"type":"Point"}
}