{
  "type": "Feature",
  "properties": {
    "addr:full":"63 Church St #306 St Catharines ON L2R 3C4",
    "addr:housenumber":"63",
    "addr:postcode":"l2r 3c4",
    "addr:street":"Church St # 306",
    "iso:country":"CA",
    "sg:address":"63 Church St #306",
    "sg:city":"St Catharines",
    "sg:classifiers":[
        {
            "category":"Banks & Credit Unions",
            "subcategory":"Investment Brokerage",
            "type":"Services"
        }
    ],
    "sg:phone":"+1 905 988 5888",
    "sg:postcode":"L2R 3C4",
    "sg:province":"ON",
    "wof:name":"Rbc Dominion Securities Inc",
    "wof:placetype":"venue"
},
  "geometry": {"coordinates":[-79.2468261719,43.1603507996],"type":"Point"}
}