{
  "type": "Feature",
  "properties": {
    "iso:country":"CA",
    "sg:address":"933 Park St",
    "sg:city":"Kentville",
    "sg:classifiers":[
        {
            "category":"Autos & Motor Vehicles",
            "subcategory":"Automobile Sales",
            "type":"Retail Goods"
        }
    ],
    "sg:phone":"+1 902 679 0029",
    "sg:postcode":"B4N 3X9",
    "sg:province":"NS",
    "sg:tags":[
        "car",
        "dealer"
    ],
    "wof:name":"Kings County Honda",
    "wof:placetype":"venue"
},
  "geometry": {"coordinates":[-64.55461120610001,45.0697021484],"type":"Point"}
}