{
  "type": "Feature",
  "properties": {
    "addr:full":"21783 Mountainview Cres Maple Ridge BC V2X 3V2",
    "addr:housenumber":"21783",
    "addr:postcode":"v2x 3v2",
    "addr:street":"Mountainview Cres",
    "iso:country":"CA",
    "sg:address":"21783 Mountainview Cres",
    "sg:city":"Maple Ridge",
    "sg:classifiers":[
        {
            "category":"Building & Trades",
            "subcategory":"Construction",
            "type":"Services"
        }
    ],
    "sg:phone":"+1 604 467 4457",
    "sg:postcode":"V2X 3V2",
    "sg:province":"BC",
    "sg:tags":[
        "deck",
        "cleaners",
        "rug",
        "restoration",
        "cleaning",
        "patio",
        "carpet"
    ],
    "wof:name":"Able Blind Cleaning",
    "wof:placetype":"venue"
},
  "geometry": {"coordinates":[-122.617874,49.223606],"type":"Point"}
}