{
  "type": "Feature",
  "properties": {
    "addr:full":"Prince Albert SK S6V 5T1",
    "addr:postcode":"s6v 5t1",
    "iso:country":"CA",
    "sg:city":"Prince Albert",
    "sg:classifiers":[
        {
            "category":"Airport",
            "type":"Transportation"
        }
    ],
    "sg:phone":"+1 306 922 2877",
    "sg:postcode":"S6V 5T1",
    "sg:province":"SK",
    "sg:tags":[
        "aircraft",
        "maintenance"
    ],
    "wof:name":"Elite Aero Ltd",
    "wof:placetype":"venue"
},
  "geometry": {"coordinates":[-105.67489624,53.2124900818],"type":"Point"}
}