{
  "type": "Feature",
  "properties": {
    "addr:full":"112 Queen St # 4 Lakefield ON K0L 2H0",
    "addr:housenumber":"112",
    "addr:postcode":"k0l 2h0",
    "addr:street":"Queen St # 4 Lakefield",
    "iso:country":"CA",
    "sg:address":"112 Queen St # 4",
    "sg:city":"Lakefield",
    "sg:classifiers":[
        {
            "category":"Manufacturing",
            "subcategory":"Jewelry",
            "type":"Manufacturing & Wholesale Goods"
        }
    ],
    "sg:phone":"+1 705 652 0906",
    "sg:postcode":"K0L 2H0",
    "sg:province":"ON",
    "sg:tags":[
        "craftsman"
    ],
    "wof:name":"Tompkins Jewellers",
    "wof:placetype":"venue"
},
  "geometry": {"coordinates":[-78.269897,44.427071],"type":"Point"}
}