{
  "type": "Feature",
  "properties": {
    "iso:country":"CA",
    "sg:address":"12 Rue Belcourt",
    "sg:city":"Dollard-Des-Ormeaux",
    "sg:classifiers":[
        {
            "category":"Health Services",
            "subcategory":"Doctor",
            "type":"Services"
        }
    ],
    "sg:phone":"+1 514 684 1248",
    "sg:postcode":"H9A 1X7",
    "sg:province":"QC",
    "sg:tags":[
        "physician",
        "surgeon"
    ],
    "wof:name":"Neumann, P Z MD",
    "wof:placetype":"venue"
},
  "geometry": {"coordinates":[-73.814697,45.498852],"type":"Point"}
}