{
  "type": "Feature",
  "properties": {
    "addr:full":"Pickering ON L1W 3S1",
    "addr:postcode":"l1w 3s1",
    "iso:country":"CA",
    "sg:city":"Pickering",
    "sg:classifiers":[
        {
            "category":"Professional",
            "subcategory":"Engineering",
            "type":"Services"
        }
    ],
    "sg:phone":"+1 905 420 1268",
    "sg:postcode":"L1W 3S1",
    "sg:province":"ON",
    "sg:tags":[
        "engineer"
    ],
    "wof:name":"Ara Paints",
    "wof:placetype":"venue"
},
  "geometry": {"coordinates":[-79.06989299999999,43.834465],"type":"Point"}
}