{
  "type": "Feature",
  "properties": {
    "iso:country":"CA",
    "sg:address":"755 Davis Dr",
    "sg:city":"Newmarket",
    "sg:classifiers":[
        {
            "category":"Personal",
            "subcategory":"Beauty Salon",
            "type":"Services"
        }
    ],
    "sg:phone":"+1 905 895 7391",
    "sg:postcode":"L3Y 2R2",
    "sg:province":"ON",
    "wof:name":"Huron Heights Beauty Salon",
    "wof:placetype":"venue"
},
  "geometry": {"coordinates":[-79.446167,44.062683],"type":"Point"}
}