{
  "type": "Feature",
  "properties": {
    "addr:full":"212 Lambert St Whitehorse YT Y1A 1Z4",
    "addr:housenumber":"212",
    "addr:postcode":"y1a 1z4",
    "addr:street":"Lambert St",
    "iso:country":"CA",
    "sg:address":"212 Lambert St",
    "sg:city":"Whitehorse",
    "sg:classifiers":[
        {
            "category":"Travel",
            "subcategory":"Travel Agent",
            "type":"Entertainment"
        }
    ],
    "sg:phone":"+1 867 668 5599",
    "sg:postcode":"Y1A 1Z4",
    "sg:province":"YT",
    "sg:tags":[
        "agency",
        "bureau"
    ],
    "wof:name":"Whitehorse Travel",
    "wof:placetype":"venue"
},
  "geometry": {"coordinates":[-135.051605225,60.7181434631],"type":"Point"}
}