{
  "type": "Feature",
  "properties": {
    "addr:full":"1405 Boul Marie-Victorin LA Prairie QC J5R 1C9",
    "addr:housenumber":"1405",
    "addr:postcode":"j5r 1c9",
    "addr:street":"Boul Marie-Victorin",
    "iso:country":"CA",
    "sg:address":"1405 Boul Marie-Victorin",
    "sg:city":"LA Prairie",
    "sg:classifiers":[
        {
            "category":"Personal",
            "type":"Services"
        }
    ],
    "sg:phone":"+1 450 659 7161",
    "sg:postcode":"J5R 1C9",
    "sg:province":"QC",
    "sg:tags":[
        "therapist",
        "massage"
    ],
    "wof:name":"Institut DE Beaute Avanti",
    "wof:placetype":"venue"
},
  "geometry": {"coordinates":[-73.5132141113,45.40574646],"type":"Point"}
}