{
  "type": "Feature",
  "properties": {
    "iso:country":"CA",
    "sg:address":"2569 Kenworth Rd",
    "sg:city":"Nanaimo",
    "sg:classifiers":[
        {
            "category":"Professional",
            "subcategory":"Engineering",
            "type":"Services"
        }
    ],
    "sg:phone":"+1 250 729 8080",
    "sg:postcode":"V9T 3M4",
    "sg:province":"BC",
    "sg:tags":[
        "engineer"
    ],
    "wof:name":"Inuktun Services Ltd",
    "wof:placetype":"venue"
},
  "geometry": {"coordinates":[-124.007209778,49.2026481628],"type":"Point"}
}