{
  "type": "Feature",
  "properties": {
    "addr:full":"RR 3 STN Main Olds AB T4H 1P4",
    "addr:postcode":"t4h 1p4",
    "addr:street":"Rr 3 Stn Main",
    "iso:country":"CA",
    "sg:address":"RR 3 STN Main",
    "sg:city":"Olds",
    "sg:classifiers":[
        {
            "category":"Professional",
            "subcategory":"Business Services",
            "type":"Services"
        }
    ],
    "sg:phone":"+1 403 556 6535",
    "sg:postcode":"T4H 1P4",
    "sg:province":"AB",
    "sg:tags":[
        "water",
        "hauling"
    ],
    "wof:name":"Morgan Tank Truck Svc Ltd",
    "wof:placetype":"venue"
},
  "geometry": {"coordinates":[-114.11061100000001,51.791626],"type":"Point"}
}