{
  "type": "Feature",
  "properties": {
    "iso:country":"CA",
    "sg:address":"5401 Ravenshoe Rd",
    "sg:city":"Sutton West",
    "sg:classifiers":[
        {
            "category":"Retail",
            "subcategory":"Auto Repair",
            "type":"Services"
        }
    ],
    "sg:phone":"+1 905 473 2978",
    "sg:postcode":"L0E 1R0",
    "sg:province":"ON",
    "sg:tags":[
        "repairing",
        "automobile"
    ],
    "wof:name":"Brown Hill Auto Svc",
    "wof:placetype":"venue"
},
  "geometry": {"coordinates":[-79.3612365723,44.3048667908],"type":"Point"}
}