{
  "type": "Feature",
  "properties": {
    "addr:full":"640 Queen St E Toronto ON M4M 1G3",
    "addr:housenumber":"640",
    "addr:postcode":"m4m 1g3",
    "addr:street":"Queen St E",
    "iso:country":"CA",
    "sg:address":"640 Queen St E",
    "sg:city":"Toronto",
    "sg:classifiers":[
        {
            "category":"Restaurant",
            "type":"Food & Drink"
        }
    ],
    "sg:phone":"+1 416 461 5455",
    "sg:postcode":"M4M 1G3",
    "sg:province":"ON",
    "wof:name":"Speedy Burger",
    "wof:placetype":"venue"
},
  "geometry": {"coordinates":[-79.352547,43.658401],"type":"Point"}
}