{
  "type": "Feature",
  "properties": {
    "addr:full":"161 Rue Principale Grenville QC J0V 1J0",
    "addr:housenumber":"161",
    "addr:postcode":"j0v 1j0",
    "addr:street":"Rue Principale",
    "iso:country":"CA",
    "sg:address":"161 Rue Principale",
    "sg:city":"Grenville",
    "sg:classifiers":[
        {
            "category":"Manufacturing",
            "subcategory":"Lumber",
            "type":"Manufacturing & Wholesale Goods"
        }
    ],
    "sg:phone":"+1 819 242 4976",
    "sg:postcode":"J0V 1J0",
    "sg:province":"QC",
    "sg:tags":[
        "company",
        "logging"
    ],
    "wof:name":"Investissements Forestiers",
    "wof:placetype":"venue"
},
  "geometry": {"coordinates":[-74.598946,45.633671],"type":"Point"}
}