{
  "type": "Feature",
  "properties": {
    "addr:full":"Red Deer AB T4P 1K1",
    "addr:postcode":"t4p 1k1",
    "iso:country":"CA",
    "sg:city":"Red Deer",
    "sg:classifiers":[
        {
            "category":"Real Estate",
            "subcategory":"Developer",
            "type":"Services"
        }
    ],
    "sg:phone":"+1 403 347 3434",
    "sg:postcode":"T4P 1K1",
    "sg:province":"AB",
    "sg:tags":[
        "mobile",
        "home"
    ],
    "wof:name":"Parkside Mobile Estates",
    "wof:placetype":"venue"
},
  "geometry": {"coordinates":[-113.817436218,52.2623023987],"type":"Point"}
}