{
  "type": "Feature",
  "properties": {
    "addr:full":"Surrey BC V3W 0A6",
    "addr:postcode":"v3w 0a6",
    "iso:country":"CA",
    "sg:city":"Surrey",
    "sg:classifiers":[
        {
            "category":"Building & Trades",
            "subcategory":"Electrical",
            "type":"Services"
        }
    ],
    "sg:phone":"+1 604 591 1809",
    "sg:postcode":"V3W 0A6",
    "sg:province":"BC",
    "sg:tags":[
        "electric",
        "contractor"
    ],
    "wof:name":"Neidig Electric Ltd",
    "wof:placetype":"venue"
},
  "geometry": {"coordinates":[-122.865562,49.154095],"type":"Point"}
}