{
  "type": "Feature",
  "properties": {
    "addr:full":"Saint-Emile QC G3E 1Z3",
    "addr:postcode":"g3e 1z3",
    "iso:country":"CA",
    "sg:city":"Saint-Emile",
    "sg:classifiers":[
        {
            "category":"Manufacturing",
            "subcategory":"Lumber",
            "type":"Manufacturing & Wholesale Goods"
        }
    ],
    "sg:phone":"+1 418 842 8405",
    "sg:postcode":"G3E 1Z3",
    "sg:province":"QC",
    "sg:tags":[
        "sawmill"
    ],
    "wof:name":"Scierie Leduc",
    "wof:placetype":"venue"
},
  "geometry": {"coordinates":[-71.3313369751,46.8638763428],"type":"Point"}
}