{
  "type": "Feature",
  "properties": {
    "addr:full":"910 Boul Lionel-Boulet Varennes QC J3X 1P7",
    "addr:housenumber":"910",
    "addr:postcode":"j3x 1p7",
    "addr:street":"Boul Lionel-Boulet",
    "iso:country":"CA",
    "sg:address":"910 Boul Lionel-Boulet",
    "sg:city":"Varennes",
    "sg:classifiers":[
        {
            "category":"Utilities",
            "subcategory":"Refuse",
            "type":"Services"
        }
    ],
    "sg:phone":"+1 450 652 4282",
    "sg:postcode":"J3X 1P7",
    "sg:province":"QC",
    "sg:tags":[
        "hazardous",
        "material",
        "storage",
        "removal",
        "equipment",
        "toxic",
        "waste"
    ],
    "wof:name":"Transport Rollex Ltee",
    "wof:placetype":"venue"
},
  "geometry": {"coordinates":[-73.412155,45.648575],"type":"Point"}
}