{
  "type": "Feature",
  "properties": {
    "addr:full":"23 Rowland Cres St Albert AB T8N 5B3",
    "addr:housenumber":"23",
    "addr:postcode":"t8n 5b3",
    "addr:street":"Rowland Cres",
    "iso:country":"CA",
    "sg:address":"23 Rowland Cres",
    "sg:city":"St Albert",
    "sg:classifiers":[
        {
            "category":"Recreation",
            "type":"Entertainment"
        }
    ],
    "sg:phone":"+1 780 459 6739",
    "sg:postcode":"T8N 5B3",
    "sg:province":"AB",
    "sg:tags":[
        "hall",
        "auditorium"
    ],
    "wof:name":"Fraternal Order of Eagles",
    "wof:placetype":"venue"
},
  "geometry": {"coordinates":[-113.643913,53.61784],"type":"Point"}
}