{
  "type": "Feature",
  "properties": {
    "addr:full":"285 Taunton Rd E Oshawa ON L1G 3V2",
    "addr:housenumber":"285",
    "addr:postcode":"l1g 3v2",
    "addr:street":"Taunton Rd E",
    "iso:country":"CA",
    "sg:address":"285 Taunton Rd E",
    "sg:city":"Oshawa",
    "sg:classifiers":[
        {
            "category":"Shopping",
            "subcategory":"Clothing, Apparel, & Fashions",
            "type":"Retail Goods"
        }
    ],
    "sg:phone":"+1 905 721 1903",
    "sg:postcode":"L1G 3V2",
    "sg:province":"ON",
    "sg:tags":[
        "dancing",
        "supply"
    ],
    "wof:name":"Stardust Dancewear & Giftware",
    "wof:placetype":"venue"
},
  "geometry": {"coordinates":[-78.868225,43.935211],"type":"Point"}
}