{
  "type": "Feature",
  "properties": {
    "iso:country":"CA",
    "sg:city":"Thompson",
    "sg:classifiers":[
        {
            "category":"Retail",
            "subcategory":"Repair Shop",
            "type":"Services"
        }
    ],
    "sg:phone":"+1 204 778 7948",
    "sg:postcode":"R8N 1X2",
    "sg:province":"MB",
    "sg:tags":[
        "welding"
    ],
    "wof:name":"Thompson Custom Welding Repair",
    "wof:placetype":"venue"
},
  "geometry": {"coordinates":[-97.862449646,55.7313499451],"type":"Point"}
}