{
  "type": "Feature",
  "properties": {
    "addr:full":"462 381 Rte S Ferland-Et-Boilleau QC G0V 1H0",
    "addr:housenumber":"381",
    "addr:postcode":"g0v 1h0",
    "addr:street":"Rte S",
    "iso:country":"CA",
    "sg:address":"462 381 Rte S",
    "sg:city":"Ferland-Et-Boilleau",
    "sg:classifiers":[
        {
            "category":"Government",
            "subcategory":"Office",
            "type":"Public Place"
        }
    ],
    "sg:phone":"+1 418 676 2282",
    "sg:postcode":"G0V 1H0",
    "sg:province":"QC",
    "sg:tags":[
        "village"
    ],
    "wof:name":"Ferland Et Boilleau",
    "wof:placetype":"venue"
},
  "geometry": {"coordinates":[-70.87565600000001,48.129974],"type":"Point"}
}