{
  "type": "Feature",
  "properties": {
    "addr:full":"1527 Ellis St Kelowna BC V1Y 2A7",
    "addr:housenumber":"1527",
    "addr:postcode":"v1y 2a7",
    "addr:street":"Ellis St",
    "iso:country":"CA",
    "sg:address":"1527 Ellis St",
    "sg:city":"Kelowna",
    "sg:classifiers":[
        {
            "category":"Organizations",
            "subcategory":"Professional Association",
            "type":"Services"
        }
    ],
    "sg:phone":"+1 250 861 6654",
    "sg:postcode":"V1Y 2A7",
    "sg:province":"BC",
    "wof:name":"Okanagan Wine Festivals",
    "wof:placetype":"venue"
},
  "geometry": {"coordinates":[-119.49333190900001,49.8860054016],"type":"Point"}
}