{
  "type": "Feature",
  "properties": {
    "addr:full":"3030 Birchmount Rd Scarborough ON M1W 3W3",
    "addr:housenumber":"3030",
    "addr:postcode":"m1w 3w3",
    "addr:street":"Birchmount Rd",
    "iso:country":"CA",
    "sg:address":"3030 Birchmount Rd",
    "sg:city":"Scarborough",
    "sg:classifiers":[
        {
            "category":"Social Services",
            "type":"Services"
        }
    ],
    "sg:phone":"+1 416 495 2555",
    "sg:postcode":"M1W 3W3",
    "sg:province":"ON",
    "sg:tags":[
        "assault",
        "abuse",
        "sexual",
        "crisis"
    ],
    "wof:name":"Sexual Assault Care Ctr",
    "wof:placetype":"venue"
},
  "geometry": {"coordinates":[-79.308052,43.80151],"type":"Point"}
}