{
  "type": "Feature",
  "properties": {
    "addr:full":"Boucherville QC J4B 5M4",
    "addr:postcode":"j4b 5m4",
    "iso:country":"CA",
    "sg:city":"Boucherville",
    "sg:classifiers":[
        {
            "category":"Health Services",
            "subcategory":"Chiropractor",
            "type":"Services"
        }
    ],
    "sg:phone":"+1 450 641 4808",
    "sg:postcode":"J4B 5M4",
    "sg:province":"QC",
    "wof:name":"Menard, Raymond DC",
    "wof:placetype":"venue"
},
  "geometry": {"coordinates":[-73.45313299999999,45.603718],"type":"Point"}
}