{
  "type": "Feature",
  "properties": {
    "addr:full":"1990 Alberni Hwy Coombs BC V0R 1M0",
    "addr:housenumber":"1990",
    "addr:postcode":"v0r 1m0",
    "addr:street":"Alberni Hwy",
    "iso:country":"CA",
    "sg:address":"1990 Alberni Hwy",
    "sg:city":"Coombs",
    "sg:classifiers":[
        {
            "category":"Food & Beverages",
            "subcategory":"Groceries & Convenience Stores",
            "type":"Retail Goods"
        }
    ],
    "sg:phone":"+1 250 248 9240",
    "sg:postcode":"V0R 1M0",
    "sg:province":"BC",
    "sg:tags":[
        "lawn",
        "market",
        "maintenance",
        "grounds"
    ],
    "wof:name":"Regatta Gardens",
    "wof:placetype":"venue"
},
  "geometry": {"coordinates":[-124.407883,49.305851],"type":"Point"}
}