{
  "type": "Feature",
  "properties": {
    "addr:full":"9851 63 Ave NW Edmonton AB T6E 0G7",
    "addr:housenumber":"9851",
    "addr:postcode":"t6e 0g7",
    "addr:street":"63 Ave Nw",
    "iso:country":"CA",
    "sg:address":"9851 63 Ave NW",
    "sg:city":"Edmonton",
    "sg:classifiers":[
        {
            "category":"Retail",
            "subcategory":"Repair Shop",
            "type":"Services"
        }
    ],
    "sg:phone":"+1 780 435 5352",
    "sg:postcode":"T6E 0G7",
    "sg:province":"AB",
    "sg:tags":[
        "lock",
        "locksmith"
    ],
    "wof:name":"Royal Lock & Key Ltd",
    "wof:placetype":"venue"
},
  "geometry": {"coordinates":[-113.484901428,53.4997177124],"type":"Point"}
}