{
  "type": "Feature",
  "properties": {
    "addr:full":"1695 Tecumseh Rd W Windsor ON N9B 1V1",
    "addr:housenumber":"1695",
    "addr:postcode":"n9b 1v1",
    "addr:street":"Tecumseh Rd W",
    "iso:country":"CA",
    "sg:address":"1695 Tecumseh Rd W",
    "sg:city":"Windsor",
    "sg:classifiers":[
        {
            "category":"Recreation",
            "type":"Entertainment"
        }
    ],
    "sg:phone":"+1 519 253 1585",
    "sg:postcode":"N9B 1V1",
    "sg:province":"ON",
    "sg:tags":[
        "lottery",
        "agent"
    ],
    "wof:name":"Ma's Lottery Shop",
    "wof:placetype":"venue"
},
  "geometry": {"coordinates":[-83.048119,42.295242],"type":"Point"}
}