{
  "type": "Feature",
  "properties": {
    "addr:full":"3610 Boul Poirier Saint-Laurent QC H4R 2J5",
    "addr:housenumber":"3610",
    "addr:postcode":"h4r 2j5",
    "addr:street":"Boul Poirier",
    "iso:country":"CA",
    "sg:address":"3610 Boul Poirier",
    "sg:city":"Saint-Laurent",
    "sg:classifiers":[
        {
            "category":"Wholesale",
            "subcategory":"Apparel",
            "type":"Manufacturing & Wholesale Goods"
        }
    ],
    "sg:phone":"+1 514 745 6446",
    "sg:postcode":"H4R 2J5",
    "sg:province":"QC",
    "sg:tags":[
        "shoes"
    ],
    "wof:name":"Chaussures Orlando Inc",
    "wof:placetype":"venue"
},
  "geometry": {"coordinates":[-73.71867370610001,45.4990959167],"type":"Point"}
}