{
  "type": "Feature",
  "properties": {
    "addr:full":"2001 Finch Ave W North York ON M3N 2V3",
    "addr:housenumber":"2001",
    "addr:postcode":"m3n 2v3",
    "addr:street":"Finch Ave W",
    "iso:country":"CA",
    "sg:address":"2001 Finch Ave W",
    "sg:city":"North York",
    "sg:classifiers":[
        {
            "category":"Shopping",
            "subcategory":"Department Store",
            "type":"Retail Goods"
        }
    ],
    "sg:phone":"+1 416 744 6575",
    "sg:postcode":"M3N 2V3",
    "sg:province":"ON",
    "sg:tags":[
        "shop"
    ],
    "wof:name":"Perfect Deals & Discounts",
    "wof:placetype":"venue"
},
  "geometry": {"coordinates":[-79.519958,43.756779],"type":"Point"}
}