{
  "type": "Feature",
  "properties": {
    "addr:full":"910 Regional Rd 9 Hagersville ON N0A 1H0",
    "addr:housenumber":"910",
    "addr:postcode":"n0a 1h0",
    "addr:street":"Regional Rd 9",
    "iso:country":"CA",
    "sg:address":"910 Regional Rd 9",
    "sg:city":"Hagersville",
    "sg:classifiers":[
        {
            "category":"Organizations",
            "subcategory":"Religious Organization",
            "type":"Services"
        }
    ],
    "sg:phone":"+1 905 768 3239",
    "sg:postcode":"N0A 1H0",
    "sg:province":"ON",
    "sg:tags":[
        "church"
    ],
    "wof:name":"Oneida United Church",
    "wof:placetype":"venue"
},
  "geometry": {"coordinates":[-80.05113220210001,42.9626541138],"type":"Point"}
}