{
  "type": "Feature",
  "properties": {
    "addr:full":"Chestermere AB T1X 1M1",
    "addr:postcode":"t1x 1m1",
    "iso:country":"CA",
    "sg:city":"Chestermere",
    "sg:classifiers":[
        {
            "category":"Personal",
            "subcategory":"Beauty Salon",
            "type":"Services"
        }
    ],
    "sg:phone":"+1 403 204 0003",
    "sg:postcode":"T1X 1M1",
    "sg:province":"AB",
    "wof:name":"Palacios Salon & Spa Ltd",
    "wof:placetype":"venue"
},
  "geometry": {"coordinates":[-113.815437,51.051655],"type":"Point"}
}