{
  "type": "Feature",
  "properties": {
    "iso:country":"CA",
    "sg:address":"11 Second Ave N",
    "sg:city":"Yorkton",
    "sg:classifiers":[
        {
            "category":"Personal",
            "subcategory":"Beauty Salon",
            "type":"Services"
        }
    ],
    "sg:phone":"+1 306 783 4633",
    "sg:postcode":"S3N 1G1",
    "sg:province":"SK",
    "wof:name":"Partners Hair Design",
    "wof:placetype":"venue"
},
  "geometry": {"coordinates":[-102.461235046,51.2106666565],"type":"Point"}
}