{
  "type": "Feature",
  "properties": {
    "addr:full":"Joliette QC J6E 3A4",
    "addr:postcode":"j6e 3a4",
    "iso:country":"CA",
    "sg:city":"Joliette",
    "sg:classifiers":[
        {
            "category":"Organizations",
            "subcategory":"Professional Association",
            "type":"Services"
        }
    ],
    "sg:phone":"+1 450 759 5221",
    "sg:postcode":"J6E 3A4",
    "sg:province":"QC",
    "wof:name":"Bureau Des Soumissions",
    "wof:placetype":"venue"
},
  "geometry": {"coordinates":[-73.4501037598,46.0206031799],"type":"Point"}
}