{
  "type": "Feature",
  "properties": {
    "addr:full":"5410 2E Av Montreal QC H1Y 2Y3",
    "addr:housenumber":"5410",
    "addr:postcode":"h1y 2y3",
    "addr:street":"2E Av",
    "iso:country":"CA",
    "sg:address":"5410 2E Av",
    "sg:city":"Montreal",
    "sg:classifiers":[
        {
            "category":"Social Services",
            "type":"Services"
        }
    ],
    "sg:phone":"+1 514 855 8991",
    "sg:postcode":"H1Y 2Y3",
    "sg:province":"QC",
    "sg:tags":[
        "organization",
        "welfare"
    ],
    "wof:name":"Centre DE Ressources Sante",
    "wof:placetype":"venue"
},
  "geometry": {"coordinates":[-73.57669799999999,45.545914],"type":"Point"}
}