{
  "type": "Feature",
  "properties": {
    "addr:full":"RR 1 Fournier ON K0B 1G0",
    "addr:postcode":"k0b 1g0",
    "addr:street":"Rr 1 Fournier",
    "iso:country":"CA",
    "sg:address":"RR 1",
    "sg:city":"Fournier",
    "sg:classifiers":[
        {
            "category":"Wholesale",
            "subcategory":"Machinery & Supplies",
            "type":"Manufacturing & Wholesale Goods"
        }
    ],
    "sg:phone":"+1 613 673 1373",
    "sg:postcode":"K0B 1G0",
    "sg:province":"ON",
    "sg:tags":[
        "farm",
        "equipment"
    ],
    "wof:name":"Fernando Enr",
    "wof:placetype":"venue"
},
  "geometry": {"coordinates":[-74.89949799999999,45.441303],"type":"Point"}
}