{
  "type": "Feature",
  "properties": {
    "iso:country":"CA",
    "sg:address":"290 White Hills Run",
    "sg:city":"Hammonds Plains",
    "sg:classifiers":[
        {
            "category":"Education",
            "subcategory":"School",
            "type":"Public Place"
        }
    ],
    "sg:phone":"+1 902 832 2300",
    "sg:postcode":"B4B 1W6",
    "sg:province":"NS",
    "wof:name":"Madeline Symonds Middle School",
    "wof:placetype":"venue"
},
  "geometry": {"coordinates":[-63.8040885925,44.7487335205],"type":"Point"}
}