{
  "type": "Feature",
  "properties": {
    "addr:full":"80 Rue DE Vimy Sherbrooke QC J1J 3M4",
    "addr:housenumber":"80",
    "addr:postcode":"j1j 3m4",
    "addr:street":"Rue De Vimy",
    "iso:country":"CA",
    "sg:address":"80 Rue DE Vimy",
    "sg:city":"Sherbrooke",
    "sg:classifiers":[
        {
            "category":"Health Services",
            "subcategory":"Doctor",
            "type":"Services"
        }
    ],
    "sg:phone":"+1 819 822 2555",
    "sg:postcode":"J1J 3M4",
    "sg:province":"QC",
    "sg:tags":[
        "clinic",
        "cosmetic",
        "surgery"
    ],
    "wof:name":"Clinique Medico Esthetique",
    "wof:placetype":"venue"
},
  "geometry": {"coordinates":[-71.9104385376,45.3998832703],"type":"Point"}
}