{
  "type": "Feature",
  "properties": {
    "iso:country":"CA",
    "sg:address":"155 Breckenridge Dr",
    "sg:city":"Kitchener",
    "sg:classifiers":[
        {
            "category":"Personal",
            "subcategory":"Beauty Salon",
            "type":"Services"
        }
    ],
    "sg:phone":"+1 519 896 1881",
    "sg:postcode":"N2B 3R8",
    "sg:province":"ON",
    "wof:name":"Mythos Spa & Beauty Salon",
    "wof:placetype":"venue"
},
  "geometry": {"coordinates":[-80.442955,43.452545],"type":"Point"}
}