{
  "type": "Feature",
  "properties": {
    "addr:full":"House 407A Oxford House MB R0B 1C0",
    "addr:housenumber":"407a",
    "addr:postcode":"r0b 1c0",
    "addr:street":"Oxford",
    "iso:country":"CA",
    "sg:address":"House 407A",
    "sg:city":"Oxford House",
    "sg:classifiers":[
        {
            "category":"Travel",
            "subcategory":"Hotels & Motels",
            "type":"Entertainment"
        }
    ],
    "sg:phone":"+1 204 538 2419",
    "sg:postcode":"R0B 1C0",
    "sg:province":"MB",
    "wof:name":"Triple B Motel",
    "wof:placetype":"venue"
},
  "geometry": {"coordinates":[-95.284103,54.93586],"type":"Point"}
}