{
  "type": "Feature",
  "properties": {
    "addr:full":"Wooler ON K0K 3M0",
    "addr:postcode":"k0k 3m0",
    "iso:country":"CA",
    "sg:city":"Wooler",
    "sg:classifiers":[
        {
            "category":"Building & Trades",
            "subcategory":"Construction",
            "type":"Services"
        }
    ],
    "sg:phone":"+1 613 397 3019",
    "sg:postcode":"K0K 3M0",
    "sg:province":"ON",
    "sg:tags":[
        "excavating",
        "contractor"
    ],
    "wof:name":"Donaldson Excavating",
    "wof:placetype":"venue"
},
  "geometry": {"coordinates":[-77.7002105713,44.1564292908],"type":"Point"}
}