{
  "type": "Feature",
  "properties": {
    "addr:full":"725 Montrose St Winnipeg MB R3M 3M5",
    "addr:housenumber":"725",
    "addr:postcode":"r3m 3m5",
    "addr:street":"Montrose St",
    "iso:country":"CA",
    "sg:address":"725 Montrose St",
    "sg:city":"Winnipeg",
    "sg:classifiers":[
        {
            "category":"Building & Trades",
            "subcategory":"Construction",
            "type":"Services"
        }
    ],
    "sg:phone":"+1 204 489 5815",
    "sg:postcode":"R3M 3M5",
    "sg:province":"MB",
    "sg:tags":[
        "tile",
        "dealer"
    ],
    "wof:name":"Euro Tile",
    "wof:placetype":"venue"
},
  "geometry": {"coordinates":[-97.180008,49.855476],"type":"Point"}
}