{
  "type": "Feature",
  "properties": {
    "addr:full":"350 Cheadle St W Swift Current SK S9H 4G3",
    "addr:housenumber":"350",
    "addr:postcode":"s9h 4g3",
    "addr:street":"Cheadle St W",
    "iso:country":"CA",
    "sg:address":"350 Cheadle St W",
    "sg:city":"Swift Current",
    "sg:classifiers":[
        {
            "category":"Government",
            "subcategory":"Fire Station",
            "type":"Public Place"
        }
    ],
    "sg:phone":"+1 ",
    "sg:postcode":"S9H 4G3",
    "sg:province":"SK",
    "sg:tags":[
        "department"
    ],
    "wof:name":"Saskatchewan Fire Commissioner",
    "wof:placetype":"venue"
},
  "geometry": {"coordinates":[-107.8046875,50.2832450867],"type":"Point"}
}