{
  "type": "Feature",
  "properties": {
    "iso:country":"CA",
    "sg:city":"Winnipeg",
    "sg:classifiers":[
        {
            "category":"Health Services",
            "subcategory":"Podiatrist",
            "type":"Services"
        }
    ],
    "sg:phone":"+1 204 487 1314",
    "sg:postcode":"R3P 0N5",
    "sg:province":"MB",
    "wof:name":"Fernando Foot Clinic",
    "wof:placetype":"venue"
},
  "geometry": {"coordinates":[-97.211639,49.866642],"type":"Point"}
}