{
  "type": "Feature",
  "properties": {
    "iso:country":"CA",
    "sg:address":"178 Rue Merizzi",
    "sg:city":"Saint-Laurent",
    "sg:classifiers":[
        {
            "category":"Communications",
            "subcategory":"Film & Video Production",
            "type":"Services"
        }
    ],
    "sg:phone":"+1 514 738 4747",
    "sg:postcode":"H4T 1S4",
    "sg:province":"QC",
    "sg:tags":[
        "duplication",
        "tape",
        "taping"
    ],
    "wof:name":"Dana Video Media Inc",
    "wof:placetype":"venue"
},
  "geometry": {"coordinates":[-73.695465,45.479412],"type":"Point"}
}