{
  "type": "Feature",
  "properties": {
    "addr:full":"259 Hillcroft St Oshawa ON L1G 8E4",
    "addr:housenumber":"259",
    "addr:postcode":"l1g 8e4",
    "addr:street":"Hillcroft St",
    "iso:country":"CA",
    "sg:address":"259 Hillcroft St",
    "sg:city":"Oshawa",
    "sg:classifiers":[
        {
            "category":"Health Services",
            "subcategory":"Nursing And Care Facility",
            "type":"Services"
        }
    ],
    "sg:phone":"+1 905 436 1901",
    "sg:postcode":"L1G 8E4",
    "sg:province":"ON",
    "sg:tags":[
        "home",
        "retirement",
        "community"
    ],
    "wof:name":"Centennial Retirement Rsdnc",
    "wof:placetype":"venue"
},
  "geometry": {"coordinates":[-78.860405,43.912682],"type":"Point"}
}