{
  "type": "Feature",
  "properties": {
    "addr:full":"3631 Dundas St W York ON M6S 2T2",
    "addr:housenumber":"3631",
    "addr:postcode":"m6s 2t2",
    "addr:street":"Dundas St W",
    "iso:country":"CA",
    "sg:address":"3631 Dundas St W",
    "sg:city":"York",
    "sg:classifiers":[
        {
            "category":"Home & Garden",
            "subcategory":"Building Materials",
            "type":"Retail Goods"
        }
    ],
    "sg:phone":"+1 416 766 6955",
    "sg:postcode":"M6S 2T2",
    "sg:province":"ON",
    "sg:tags":[
        "glass",
        "leaded"
    ],
    "wof:name":"Han Stained Glass",
    "wof:placetype":"venue"
},
  "geometry": {"coordinates":[-79.5056610107,43.6627502441],"type":"Point"}
}