{
  "type": "Feature",
  "properties": {
    "addr:full":"94 Holly Berry Lane Thetis Island BC V0R 2Y0",
    "addr:housenumber":"94",
    "addr:postcode":"v0r 2y0",
    "addr:street":"Holly Berry Lane",
    "iso:country":"CA",
    "sg:address":"94 Holly Berry Lane",
    "sg:city":"Thetis Island",
    "sg:classifiers":[
        {
            "category":"Professional",
            "subcategory":"Accounting & Tax Preparation",
            "type":"Services"
        }
    ],
    "sg:phone":"+1 250 246 3328",
    "sg:postcode":"V0R 2Y0",
    "sg:province":"BC",
    "sg:tags":[
        "accountant"
    ],
    "wof:name":"Culver & CO",
    "wof:placetype":"venue"
},
  "geometry": {"coordinates":[-123.662003,48.989223],"type":"Point"}
}