{
  "type": "Feature",
  "properties": {
    "addr:full":"Natashquan QC G0G 2E0",
    "addr:postcode":"g0g 2e0",
    "iso:country":"CA",
    "sg:city":"Natashquan",
    "sg:classifiers":[
        {
            "category":"Government",
            "subcategory":"Police Station",
            "type":"Public Place"
        }
    ],
    "sg:phone":"+1 418 726 3532",
    "sg:postcode":"G0G 2E0",
    "sg:province":"QC",
    "sg:tags":[
        "department"
    ],
    "wof:name":"Police Amerindienne Natashquan",
    "wof:placetype":"venue"
},
  "geometry": {"coordinates":[-61.7999534607,50.1335906982],"type":"Point"}
}