{
  "type": "Feature",
  "properties": {
    "addr:full":"1028 LA Rue Tchizo Lac-Simon QC J0Y 3M0",
    "addr:housenumber":"1028",
    "addr:postcode":"j0y 3m0",
    "addr:street":"La Rue Tchizo",
    "iso:country":"CA",
    "sg:address":"1028 LA Rue Tchizo",
    "sg:city":"Lac-Simon",
    "sg:classifiers":[
        {
            "category":"Health Services",
            "subcategory":"Hospital",
            "type":"Services"
        }
    ],
    "sg:phone":"+1 819 736 2199",
    "sg:postcode":"J0Y 3M0",
    "sg:province":"QC",
    "sg:tags":[
        "mental",
        "facility"
    ],
    "wof:name":"Service DE Consultation En",
    "wof:placetype":"venue"
},
  "geometry": {"coordinates":[-75.09307098390001,45.9053764343],"type":"Point"}
}