{
  "type": "Feature",
  "properties": {
    "iso:country":"CA",
    "sg:address":"160 Davenport Rd",
    "sg:city":"Toronto",
    "sg:classifiers":[
        {
            "category":"Personal",
            "subcategory":"Beauty Salon",
            "type":"Services"
        }
    ],
    "sg:phone":"+1 416 962 2599",
    "sg:postcode":"M5R 1J2",
    "sg:province":"ON",
    "wof:name":"Signature Nails & Esthetics",
    "wof:placetype":"venue"
},
  "geometry": {"coordinates":[-79.394493103,43.6752891541],"type":"Point"}
}