{
  "type": "Feature",
  "properties": {
    "addr:full":"159 Rue Principale Saint-Damase QC J0H 1J0",
    "addr:housenumber":"159",
    "addr:postcode":"j0h 1j0",
    "addr:street":"Rue Principale",
    "iso:country":"CA",
    "sg:address":"159 Rue Principale",
    "sg:city":"Saint-Damase",
    "sg:classifiers":[
        {
            "category":"Wholesale",
            "subcategory":"Meat",
            "type":"Manufacturing & Wholesale Goods"
        }
    ],
    "sg:phone":"+1 450 797 3381",
    "sg:postcode":"J0H 1J0",
    "sg:province":"QC",
    "sg:tags":[
        "butchering"
    ],
    "wof:name":"Boucherie Mario Darsigny",
    "wof:placetype":"venue"
},
  "geometry": {"coordinates":[-73.008652,45.526314],"type":"Point"}
}