{
  "type": "Feature",
  "properties": {
    "addr:full":"Causapscal QC G0J 1J0",
    "addr:postcode":"g0j 1j0",
    "iso:country":"CA",
    "sg:city":"Causapscal",
    "sg:classifiers":[
        {
            "category":"Arena",
            "subcategory":"Sports Club",
            "type":"Entertainment"
        }
    ],
    "sg:phone":"+1 418 756 5543",
    "sg:postcode":"G0J 1J0",
    "sg:province":"QC",
    "sg:tags":[
        "athletic",
        "fields",
        "stadium",
        "government"
    ],
    "wof:name":"Causapscal Arena",
    "wof:placetype":"venue"
},
  "geometry": {"coordinates":[-67.2218322754,48.3542671204],"type":"Point"}
}