{
  "type": "Feature",
  "properties": {
    "iso:country":"CA",
    "sg:address":"177 Rue Principale",
    "sg:city":"Granby",
    "sg:classifiers":[
        {
            "category":"Bars & Pubs",
            "type":"Food & Drink"
        }
    ],
    "sg:phone":"+1 450 375 5780",
    "sg:postcode":"J2G 2V5",
    "sg:province":"QC",
    "wof:name":"Taverne Nationale Inc",
    "wof:placetype":"venue"
},
  "geometry": {"coordinates":[-72.72640199999999,45.399952],"type":"Point"}
}