{
  "type": "Feature",
  "properties": {
    "addr:full":"1 Dennis Rd Channel-Port-Aux-Basques NL A0M 1C0",
    "addr:housenumber":"1",
    "addr:postcode":"a0m 1c0",
    "addr:street":"Dennis Rd",
    "iso:country":"CA",
    "sg:address":"1 Dennis Rd",
    "sg:city":"Channel-Port-Aux-Basques",
    "sg:classifiers":[
        {
            "category":"Freight",
            "type":"Transportation"
        }
    ],
    "sg:phone":"+1 709 695 2738",
    "sg:postcode":"A0M 1C0",
    "sg:province":"NL",
    "sg:tags":[
        "trucking"
    ],
    "wof:name":"Doyle's Transport Ltd",
    "wof:placetype":"venue"
},
  "geometry": {"coordinates":[-59.142372,47.573521],"type":"Point"}
}