{
  "type": "Feature",
  "properties": {
    "iso:country":"CA",
    "sg:address":"312 Broadway",
    "sg:city":"Orangeville",
    "sg:classifiers":[
        {
            "category":"Personal",
            "subcategory":"Beauty Salon",
            "type":"Services"
        }
    ],
    "sg:phone":"+1 519 942 1644",
    "sg:postcode":"L9W 1L3",
    "sg:province":"ON",
    "wof:name":"Broadway Hairstyling",
    "wof:placetype":"venue"
},
  "geometry": {"coordinates":[-80.11172485349999,43.9159545898],"type":"Point"}
}