{
  "type": "Feature",
  "properties": {
    "iso:country":"CA",
    "sg:address":"290 Ukraine Rd",
    "sg:city":"Mississauga",
    "sg:classifiers":[
        {
            "category":"Freight",
            "type":"Transportation"
        }
    ],
    "sg:phone":"+1 905 279 2689",
    "sg:postcode":"L5B 3W6",
    "sg:province":"ON",
    "sg:tags":[
        "broker",
        "trucking"
    ],
    "wof:name":"Jmd Corp",
    "wof:placetype":"venue"
},
  "geometry": {"coordinates":[-79.63042449949999,43.5786132812],"type":"Point"}
}