{
  "type": "Feature",
  "properties": {
    "addr:full":"Bow Island AB T0K 0G0",
    "addr:postcode":"t0k 0g0",
    "addr:street":"Bow",
    "iso:country":"CA",
    "sg:city":"Bow Island",
    "sg:classifiers":[
        {
            "category":"Restaurant",
            "type":"Food & Drink"
        }
    ],
    "sg:phone":"+1 403 545 6262",
    "sg:postcode":"T0K 0G0",
    "sg:province":"AB",
    "wof:name":"Bobby's Bar & Restaurant",
    "wof:placetype":"venue"
},
  "geometry": {"coordinates":[-111.378998,49.869457],"type":"Point"}
}