{
  "type": "Feature",
  "properties": {
    "iso:country":"CA",
    "sg:address":"289 4E Rue",
    "sg:city":"Quebec",
    "sg:classifiers":[
        {
            "category":"Personal",
            "subcategory":"Beauty Salon",
            "type":"Services"
        }
    ],
    "sg:phone":"+1 418 525 1033",
    "sg:postcode":"G1L 2S4",
    "sg:province":"QC",
    "wof:name":"Coiffure Mirage",
    "wof:placetype":"venue"
},
  "geometry": {"coordinates":[-71.226578,46.822544],"type":"Point"}
}