{
  "type": "Feature",
  "properties": {
    "addr:full":"280 West Beaver Creek Rd # 33 Richmond Hill ON L4B 3Z1",
    "addr:housenumber":"280;33",
    "addr:postcode":"l4b 3z1",
    "addr:street":"West Beaver Creek Rd #",
    "iso:country":"CA",
    "sg:address":"280 West Beaver Creek Rd # 33",
    "sg:city":"Richmond Hill",
    "sg:classifiers":[
        {
            "category":"Health Services",
            "subcategory":"Doctor",
            "type":"Services"
        }
    ],
    "sg:phone":"+1 905 762 1111",
    "sg:postcode":"L4B 3Z1",
    "sg:province":"ON",
    "sg:tags":[
        "physician",
        "surgeon"
    ],
    "wof:name":"Tsang, Michael MD",
    "wof:placetype":"venue"
},
  "geometry": {"coordinates":[-79.3870544434,43.8446884155],"type":"Point"}
}