{
  "type": "Feature",
  "properties": {
    "iso:country":"CA",
    "sg:address":"17 Denver Rd",
    "sg:city":"Whitehorse",
    "sg:classifiers":[
        {
            "category":"Building & Trades",
            "subcategory":"Construction",
            "type":"Services"
        }
    ],
    "sg:phone":"+1 867 667 6156",
    "sg:postcode":"Y1A 5S7",
    "sg:province":"YT",
    "sg:tags":[
        "general",
        "contractor"
    ],
    "wof:name":"Tsl Contractors Ltd",
    "wof:placetype":"venue"
},
  "geometry": {"coordinates":[-134.996490478,60.6363945007],"type":"Point"}
}