{
  "type": "Feature",
  "properties": {
    "addr:full":"17 Denver Rd Whitehorse YT Y1A 5S7",
    "addr:housenumber":"17",
    "addr:postcode":"y1a 5s7",
    "addr:street":"Denver Rd",
    "iso:country":"CA",
    "sg:address":"17 Denver Rd",
    "sg:city":"Whitehorse",
    "sg:classifiers":[
        {
            "category":"Building & Trades",
            "subcategory":"Construction",
            "type":"Services"
        }
    ],
    "sg:phone":"+1 867 667 6156",
    "sg:postcode":"Y1A 5S7",
    "sg:province":"YT",
    "sg:tags":[
        "general",
        "contractor"
    ],
    "wof:name":"Tsl Contractors Ltd",
    "wof:placetype":"venue"
},
  "geometry": {"coordinates":[-134.996490478,60.6363945007],"type":"Point"}
}