{
  "type": "Feature",
  "properties": {
    "addr:full":"Burlington ON L7N 3H8",
    "addr:postcode":"l7n 3h8",
    "iso:country":"CA",
    "sg:city":"Burlington",
    "sg:classifiers":[
        {
            "category":"Professional",
            "subcategory":"Engineering",
            "type":"Services"
        }
    ],
    "sg:phone":"+1 905 631 9294",
    "sg:postcode":"L7N 3H8",
    "sg:province":"ON",
    "sg:tags":[
        "engineer"
    ],
    "wof:name":"Millenium Engineering Ltd",
    "wof:placetype":"venue"
},
  "geometry": {"coordinates":[-79.797409,43.357185],"type":"Point"}
}