{
  "type": "Feature",
  "properties": {
    "iso:country":"CA",
    "sg:address":"86 London Rd",
    "sg:city":"Thamesville",
    "sg:classifiers":[
        {
            "category":"Restaurant",
            "type":"Food & Drink"
        }
    ],
    "sg:phone":"+1 519 692 9064",
    "sg:postcode":"N0P 2K0",
    "sg:province":"ON",
    "wof:name":"Picassos's",
    "wof:placetype":"venue"
},
  "geometry": {"coordinates":[-81.9762496948,42.5520782471],"type":"Point"}
}