{
  "type": "Feature",
  "properties": {
    "iso:country":"CA",
    "sg:city":"Waterloo",
    "sg:classifiers":[
        {
            "category":"Shopping",
            "subcategory":"Stationery & Office Supplies",
            "type":"Retail Goods"
        }
    ],
    "sg:phone":"+1 519 885 0826",
    "sg:postcode":"N2V 1C5",
    "sg:province":"ON",
    "sg:tags":[
        "educational",
        "material"
    ],
    "wof:name":"Resource Centre",
    "wof:placetype":"venue"
},
  "geometry": {"coordinates":[-80.5497512817,43.5020484924],"type":"Point"}
}