{
  "type": "Feature",
  "properties": {
    "addr:full":"500 Rexdale Blvd # F7A Etobicoke ON M9W 6K5",
    "addr:housenumber":"500",
    "addr:postcode":"m9w 6k5",
    "addr:street":"Rexdale Blvd # F7A",
    "iso:country":"CA",
    "sg:address":"500 Rexdale Blvd # F7A",
    "sg:city":"Etobicoke",
    "sg:classifiers":[
        {
            "category":"Personal",
            "subcategory":"Beauty Salon",
            "type":"Services"
        }
    ],
    "sg:phone":"+1 416 679 9029",
    "sg:postcode":"M9W 6K5",
    "sg:province":"ON",
    "sg:tags":[
        "manicuring"
    ],
    "wof:name":"Surprise Nails",
    "wof:placetype":"venue"
},
  "geometry": {"coordinates":[-79.5970840454,43.7178230286],"type":"Point"}
}