{
  "type": "Feature",
  "properties": {
    "addr:full":"32 Rue Saint-Jean-Baptiste E Rigaud QC J0P 1P0",
    "addr:housenumber":"32",
    "addr:postcode":"j0p 1p0",
    "addr:street":"Rue Saint-Jean-Baptiste E",
    "iso:country":"CA",
    "sg:address":"32 Rue Saint-Jean-Baptiste E",
    "sg:city":"Rigaud",
    "sg:classifiers":[
        {
            "category":"Professional",
            "subcategory":"Lawyer & Legal Services",
            "type":"Services"
        }
    ],
    "sg:phone":"+1 450 451 6555",
    "sg:postcode":"J0P 1P0",
    "sg:province":"QC",
    "sg:tags":[
        "attorney"
    ],
    "wof:name":"Morin, Claudette",
    "wof:placetype":"venue"
},
  "geometry": {"coordinates":[-74.29911,45.479145],"type":"Point"}
}