{
  "type": "Feature",
  "properties": {
    "addr:full":"Gore Bay ON P0P 1H0",
    "addr:postcode":"p0p 1h0",
    "iso:country":"CA",
    "sg:city":"Gore Bay",
    "sg:classifiers":[
        {
            "category":"Government",
            "subcategory":"Office",
            "type":"Public Place"
        }
    ],
    "sg:phone":"+1 705 282 2531",
    "sg:postcode":"P0P 1H0",
    "sg:province":"ON",
    "wof:name":"Ontario Criminal Courts",
    "wof:placetype":"venue"
},
  "geometry": {"coordinates":[-82.46607971189999,45.9165649414],"type":"Point"}
}