{
  "type": "Feature",
  "properties": {
    "iso:country":"CA",
    "sg:address":"820 14 St SW",
    "sg:city":"Medicine Hat",
    "sg:classifiers":[
        {
            "category":"Wholesale",
            "subcategory":"Electrical",
            "type":"Manufacturing & Wholesale Goods"
        }
    ],
    "sg:phone":"+1 403 528 8802",
    "sg:postcode":"T1A 4W1",
    "sg:province":"AB",
    "sg:tags":[
        "electric",
        "motor"
    ],
    "wof:name":"Southern Rewind Ltd",
    "wof:placetype":"venue"
},
  "geometry": {"coordinates":[-110.70561981199999,50.0262908936],"type":"Point"}
}