{
  "type": "Feature",
  "properties": {
    "addr:full":"111 Court St Oshawa ON L1H 4W5",
    "addr:housenumber":"111",
    "addr:postcode":"l1h 4w5",
    "addr:street":"Court St",
    "iso:country":"CA",
    "sg:address":"111 Court St",
    "sg:city":"Oshawa",
    "sg:classifiers":[
        {
            "category":"Wholesale",
            "subcategory":"Fruits & Vegetables",
            "type":"Manufacturing & Wholesale Goods"
        }
    ],
    "sg:phone":"+1 905 723 3497",
    "sg:postcode":"L1H 4W5",
    "sg:province":"ON",
    "wof:name":"Oke Produce 2004 Ltd",
    "wof:placetype":"venue"
},
  "geometry": {"coordinates":[-78.858192,43.895264],"type":"Point"}
}