{
  "type": "Feature",
  "properties": {
    "iso:country":"CA",
    "sg:address":"7 George St",
    "sg:city":"Barrie",
    "sg:classifiers":[
        {
            "category":"Organizations",
            "subcategory":"Community Association",
            "type":"Services"
        }
    ],
    "sg:phone":"+1 705 726 4343",
    "sg:postcode":"L4N 2G5",
    "sg:province":"ON",
    "sg:tags":[
        "club"
    ],
    "wof:name":"Army Navy & Air Force Club",
    "wof:placetype":"venue"
},
  "geometry": {"coordinates":[-79.704369,44.380257],"type":"Point"}
}