{
  "type": "Feature",
  "properties": {
    "iso:country":"CA",
    "sg:city":"Gabriola",
    "sg:classifiers":[
        {
            "category":"Personal",
            "subcategory":"Beauty Salon",
            "type":"Services"
        }
    ],
    "sg:phone":"+1 250 247 8100",
    "sg:postcode":"V0R 1X3",
    "sg:province":"BC",
    "wof:name":"Gail's Hair Studio",
    "wof:placetype":"venue"
},
  "geometry": {"coordinates":[-123.840209961,49.1742897034],"type":"Point"}
}