{
  "type": "Feature",
  "properties": {
    "addr:full":"3115 222 Rte Saint-Denis-DE-Brompton QC J0B 2P0",
    "addr:housenumber":"3115",
    "addr:postcode":"j0b 2p0",
    "addr:street":"222 Rte Saint-Denis-De-Brompton",
    "iso:country":"CA",
    "sg:address":"3115 222 Rte",
    "sg:city":"Saint-Denis-DE-Brompton",
    "sg:classifiers":[
        {
            "category":"Freight",
            "type":"Transportation"
        }
    ],
    "sg:phone":"+1 819 846 2667",
    "sg:postcode":"J0B 2P0",
    "sg:province":"QC",
    "sg:tags":[
        "excavating",
        "contractor",
        "trucking"
    ],
    "wof:name":"Excavations Yoland Anctil Inc",
    "wof:placetype":"venue"
},
  "geometry": {"coordinates":[-72.08098602290001,45.4581336975],"type":"Point"}
}