{
  "type": "Feature",
  "properties": {
    "addr:full":"518 Woodbridge Knoll Sherwood Park AB T8A 4G9",
    "addr:housenumber":"518",
    "addr:postcode":"t8a 4g9",
    "addr:street":"Woodbridge Knoll Sherwood Park",
    "iso:country":"CA",
    "sg:address":"518 Woodbridge Knoll",
    "sg:city":"Sherwood Park",
    "sg:classifiers":[
        {
            "category":"Retail",
            "subcategory":"Laundry & Dry Cleaning",
            "type":"Services"
        }
    ],
    "sg:phone":"+1 780 467 0102",
    "sg:postcode":"T8A 4G9",
    "sg:province":"AB",
    "sg:tags":[
        "cleaners",
        "rug",
        "carpet"
    ],
    "wof:name":"E & L Carpet Care Ltd",
    "wof:placetype":"venue"
},
  "geometry": {"coordinates":[-113.32360799999999,53.532063],"type":"Point"}
}