{
  "type": "Feature",
  "properties": {
    "addr:full":"471 Boul DE Sainte-Adele Sainte-Adele QC J8B 2N1",
    "addr:housenumber":"471",
    "addr:postcode":"j8b 2n1",
    "addr:street":"Boul De Sainte-Adele Sainte-Adele",
    "iso:country":"CA",
    "sg:address":"471 Boul DE Sainte-Adele",
    "sg:city":"Sainte-Adele",
    "sg:classifiers":[
        {
            "category":"Bars & Pubs",
            "type":"Food & Drink"
        }
    ],
    "sg:phone":"+1 450 229 4400",
    "sg:postcode":"J8B 2N1",
    "sg:province":"QC",
    "sg:tags":[
        "lounge",
        "cocktail"
    ],
    "wof:name":"Bar Chantadele Inc",
    "wof:placetype":"venue"
},
  "geometry": {"coordinates":[-74.1341934204,45.9507064819],"type":"Point"}
}