{
  "type": "Feature",
  "properties": {
    "addr:full":"Pickering ON L1W 3V4",
    "addr:postcode":"l1w 3v4",
    "iso:country":"CA",
    "sg:city":"Pickering",
    "sg:classifiers":[
        {
            "category":"Building & Trades",
            "subcategory":"Plumbing",
            "type":"Services"
        }
    ],
    "sg:phone":"+1 905 619 0114",
    "sg:postcode":"L1W 3V4",
    "sg:province":"ON",
    "sg:tags":[
        "refrigeration",
        "contractor"
    ],
    "wof:name":"Oakwood Mechanical Systems Ltd",
    "wof:placetype":"venue"
},
  "geometry": {"coordinates":[-79.0562667847,43.8264656067],"type":"Point"}
}