{
  "type": "Feature",
  "properties": {
    "addr:full":"301 Edinborough St Windsor ON N8X 3C3",
    "addr:housenumber":"301",
    "addr:postcode":"n8x 3c3",
    "addr:street":"Edinborough St",
    "iso:country":"CA",
    "sg:address":"301 Edinborough St",
    "sg:city":"Windsor",
    "sg:classifiers":[
        {
            "category":"Home & Garden",
            "subcategory":"Furniture",
            "type":"Retail Goods"
        }
    ],
    "sg:phone":"+1 519 966 1280",
    "sg:postcode":"N8X 3C3",
    "sg:province":"ON",
    "wof:name":"Bertoni Chairs & Things",
    "wof:placetype":"venue"
},
  "geometry": {"coordinates":[-83.0127334595,42.2825927734],"type":"Point"}
}