{
  "type": "Feature",
  "properties": {
    "addr:full":"171 6th Ave Cochrane ON P0L 1C0",
    "addr:housenumber":"171",
    "addr:postcode":"p0l 1c0",
    "addr:street":"6Th Ave",
    "iso:country":"CA",
    "sg:address":"171 6th Ave",
    "sg:city":"Cochrane",
    "sg:classifiers":[
        {
            "category":"Manufacturing",
            "subcategory":"Printing",
            "type":"Manufacturing & Wholesale Goods"
        }
    ],
    "sg:phone":"+1 705 272 3344",
    "sg:postcode":"P0L 1C0",
    "sg:province":"ON",
    "sg:tags":[
        "newspaper"
    ],
    "wof:name":"Cochrane Times",
    "wof:placetype":"venue"
},
  "geometry": {"coordinates":[-81.0251464844,49.0629615784],"type":"Point"}
}