{
  "type": "Feature",
  "properties": {
    "addr:full":"705 Red River Rd Thunder Bay ON P7B 1J3",
    "addr:housenumber":"705",
    "addr:postcode":"p7b 1j3",
    "addr:street":"Red River Rd",
    "iso:country":"CA",
    "sg:address":"705 Red River Rd",
    "sg:city":"Thunder Bay",
    "sg:classifiers":[
        {
            "category":"Health Services",
            "subcategory":"Chiropractor",
            "type":"Services"
        }
    ],
    "sg:phone":"+1 807 768 2225",
    "sg:postcode":"P7B 1J3",
    "sg:province":"ON",
    "wof:name":"Outback Chiropractic Clinic",
    "wof:placetype":"venue"
},
  "geometry": {"coordinates":[-89.24561300000001,48.440834],"type":"Point"}
}