{
  "type": "Feature",
  "properties": {
    "addr:full":"Hwy 8 & Hwy 13 Redvers SK S0C 2H0",
    "addr:postcode":"s0c 2h0",
    "addr:street":"Hwy 8 & Hwy 13 Redvers",
    "iso:country":"CA",
    "sg:address":"Hwy 8 & Hwy 13",
    "sg:city":"Redvers",
    "sg:classifiers":[
        {
            "category":"Autos & Motor Vehicles",
            "subcategory":"Fuel & Gas Station",
            "type":"Retail Goods"
        }
    ],
    "sg:phone":"+1 306 452 3216",
    "sg:postcode":"S0C 2H0",
    "sg:province":"SK",
    "sg:tags":[
        "oil"
    ],
    "wof:name":"Girard Bulk Svc Ltd",
    "wof:placetype":"venue"
},
  "geometry": {"coordinates":[-101.69072,49.577179],"type":"Point"}
}