{
  "type": "Feature",
  "properties": {
    "addr:full":"12872 16 Ave Surrey BC V4A 1N6",
    "addr:housenumber":"12872",
    "addr:postcode":"v4a 1n6",
    "addr:street":"16 Ave",
    "iso:country":"CA",
    "sg:address":"12872 16 Ave",
    "sg:city":"Surrey",
    "sg:classifiers":[
        {
            "category":"Food & Beverages",
            "subcategory":"Fruits & Vegetables",
            "type":"Retail Goods"
        }
    ],
    "sg:phone":"+1 604 538 2332",
    "sg:postcode":"V4A 1N6",
    "sg:province":"BC",
    "sg:tags":[
        "produce"
    ],
    "wof:name":"Chan's Farm Market",
    "wof:placetype":"venue"
},
  "geometry": {"coordinates":[-122.864929,49.031143],"type":"Point"}
}