{
  "type": "Feature",
  "properties": {
    "addr:full":"948 South Island Hwy Campbell River BC V9W 1B1",
    "addr:housenumber":"948",
    "addr:postcode":"v9w 1b1",
    "addr:street":"South Island Hwy",
    "iso:country":"CA",
    "sg:address":"948 South Island Hwy",
    "sg:city":"Campbell River",
    "sg:classifiers":[
        {
            "category":"Travel",
            "subcategory":"Travel Agent",
            "type":"Entertainment"
        }
    ],
    "sg:phone":"+1 250 286 0681",
    "sg:postcode":"V9W 1B1",
    "sg:province":"BC",
    "sg:tags":[
        "agency",
        "bureau"
    ],
    "wof:name":"Advantage Travel Place",
    "wof:placetype":"venue"
},
  "geometry": {"coordinates":[-125.22760772700001,49.9908332825],"type":"Point"}
}