{
  "type": "Feature",
  "properties": {
    "addr:full":"99 King St St Stephen NB E3L 2C6",
    "addr:housenumber":"99",
    "addr:postcode":"nb e3l 2c6",
    "addr:street":"King St",
    "iso:country":"CA",
    "sg:address":"99 King St",
    "sg:city":"St Stephen",
    "sg:classifiers":[
        {
            "category":"Travel",
            "subcategory":"Hotels & Motels",
            "type":"Entertainment"
        }
    ],
    "sg:phone":"+1 506 466 1814",
    "sg:postcode":"E3L 2C6",
    "sg:province":"NB",
    "wof:name":"St Stephen Family Inn",
    "wof:placetype":"venue"
},
  "geometry": {"coordinates":[-67.2748031616,45.1955451965],"type":"Point"}
}