{
  "type": "Feature",
  "properties": {
    "addr:full":"250 Kingsway Vancouver BC V5T 3J4",
    "addr:housenumber":"250",
    "addr:postcode":"v5t 3j4",
    "addr:street":"Kingsway",
    "iso:country":"CA",
    "sg:address":"250 Kingsway",
    "sg:city":"Vancouver",
    "sg:classifiers":[
        {
            "category":"Social Services",
            "type":"Services"
        }
    ],
    "sg:phone":"+1 604 877 0033",
    "sg:postcode":"V5T 3J4",
    "sg:province":"BC",
    "sg:tags":[
        "organization",
        "welfare"
    ],
    "wof:name":"Pact Employment Svc",
    "wof:placetype":"venue"
},
  "geometry": {"coordinates":[-123.098518372,49.2616577148],"type":"Point"}
}