{
  "type": "Feature",
  "properties": {
    "addr:full":"582 Erie St Stratford ON N5A 2N8",
    "addr:housenumber":"582",
    "addr:postcode":"n5a 2n8",
    "addr:street":"Erie St",
    "iso:country":"CA",
    "sg:address":"582 Erie St",
    "sg:city":"Stratford",
    "sg:classifiers":[
        {
            "category":"Home & Garden",
            "subcategory":"Household Appliances",
            "type":"Retail Goods"
        }
    ],
    "sg:phone":"+1 519 271 9911",
    "sg:postcode":"N5A 2N8",
    "sg:province":"ON",
    "sg:tags":[
        "cleaners",
        "vacuum"
    ],
    "wof:name":"Vacuum Shack",
    "wof:placetype":"venue"
},
  "geometry": {"coordinates":[-80.994499,43.357868],"type":"Point"}
}