{
  "type": "Feature",
  "properties": {
    "addr:full":"720 King St Regina SK S4T 4C9",
    "addr:housenumber":"720",
    "addr:postcode":"s4t 4c9",
    "addr:street":"King St",
    "iso:country":"CA",
    "sg:address":"720 King St",
    "sg:city":"Regina",
    "sg:classifiers":[
        {
            "category":"Government",
            "subcategory":"Office",
            "type":"Public Place"
        }
    ],
    "sg:phone":"+1 306 522 3331",
    "sg:postcode":"S4T 4C9",
    "sg:province":"SK",
    "sg:tags":[
        "village"
    ],
    "wof:name":"Regina Clipsham",
    "wof:placetype":"venue"
},
  "geometry": {"coordinates":[-104.63861799999999,50.467266],"type":"Point"}
}