{
  "type": "Feature",
  "properties": {
    "addr:full":"Toronto ON M5A 2E7",
    "addr:postcode":"m5a 2e7",
    "iso:country":"CA",
    "sg:city":"Toronto",
    "sg:classifiers":[
        {
            "category":"Retail",
            "subcategory":"Auto Repair",
            "type":"Services"
        }
    ],
    "sg:phone":"+1 416 922 1752",
    "sg:postcode":"M5A 2E7",
    "sg:province":"ON",
    "sg:tags":[
        "repairing",
        "automobile"
    ],
    "wof:name":"Lorin Fraser Svc Ctr",
    "wof:placetype":"venue"
},
  "geometry": {"coordinates":[-79.37078099999999,43.661453],"type":"Point"}
}