{
  "type": "Feature",
  "properties": {
    "addr:full":"North York ON M2R 3T5",
    "addr:postcode":"m2r 3t5",
    "iso:country":"CA",
    "sg:city":"North York",
    "sg:classifiers":[
        {
            "category":"Health Services",
            "subcategory":"Doctor",
            "type":"Services"
        }
    ],
    "sg:phone":"+1 416 229 6460",
    "sg:postcode":"M2R 3T5",
    "sg:province":"ON",
    "sg:tags":[
        "dentist"
    ],
    "wof:name":"Moushovich, Alex DDS",
    "wof:placetype":"venue"
},
  "geometry": {"coordinates":[-79.444839,43.781876],"type":"Point"}
}