{
  "type": "Feature",
  "properties": {
    "addr:full":"4945 Rue Beaubien E Montreal QC H1T 1V1",
    "addr:housenumber":"4945",
    "addr:postcode":"h1t 1v1",
    "addr:street":"Rue Beaubien E",
    "iso:country":"CA",
    "sg:address":"4945 Rue Beaubien E",
    "sg:city":"Montreal",
    "sg:classifiers":[
        {
            "category":"Banks & Credit Unions",
            "subcategory":"Bank",
            "type":"Services"
        }
    ],
    "sg:phone":"+1 514 522 1846",
    "sg:postcode":"H1T 1V1",
    "sg:province":"QC",
    "wof:name":"Banque Laurentienne Du Canada",
    "wof:placetype":"venue"
},
  "geometry": {"coordinates":[-73.572395,45.571079],"type":"Point"}
}