{
  "type": "Feature",
  "properties": {
    "addr:full":"574 Rue Calixa-Lavallee Beloeil QC J3G 4B7",
    "addr:housenumber":"574",
    "addr:postcode":"j3g 4b7",
    "addr:street":"Rue Calixa-Lavallee",
    "iso:country":"CA",
    "sg:address":"574 Rue Calixa-Lavallee",
    "sg:city":"Beloeil",
    "sg:classifiers":[
        {
            "category":"Building & Trades",
            "subcategory":"Landscaping Services",
            "type":"Services"
        }
    ],
    "sg:phone":"+1 450 467 5719",
    "sg:postcode":"J3G 4B7",
    "sg:province":"QC",
    "sg:tags":[
        "tree",
        "landscape",
        "contractor"
    ],
    "wof:name":"Arbo-Taille",
    "wof:placetype":"venue"
},
  "geometry": {"coordinates":[-73.2122497559,45.5640525818],"type":"Point"}
}