{
  "type": "Feature",
  "properties": {
    "addr:full":"North Bay ON P1B 2H3",
    "addr:postcode":"p1b 2h3",
    "iso:country":"CA",
    "sg:city":"North Bay",
    "sg:classifiers":[
        {
            "category":"Food & Beverages",
            "subcategory":"Bakery",
            "type":"Retail Goods"
        }
    ],
    "sg:phone":"+1 705 495 6739",
    "sg:postcode":"P1B 2H3",
    "sg:province":"ON",
    "sg:tags":[
        "doughnut"
    ],
    "wof:name":"Tim Hortons",
    "wof:placetype":"venue"
},
  "geometry": {"coordinates":[-79.4432067871,46.3128318787],"type":"Point"}
}