{
  "type": "Feature",
  "properties": {
    "addr:full":"North York ON M6M 2L7",
    "addr:postcode":"m6m 2l7",
    "iso:country":"CA",
    "sg:city":"North York",
    "sg:classifiers":[
        {
            "category":"Retail",
            "subcategory":"Auto Repair",
            "type":"Services"
        }
    ],
    "sg:phone":"+1 416 243 2929",
    "sg:postcode":"M6M 2L7",
    "sg:province":"ON",
    "sg:tags":[
        "body",
        "automobile",
        "painting"
    ],
    "wof:name":"Elite Auto Collision Ltd",
    "wof:placetype":"venue"
},
  "geometry": {"coordinates":[-79.4727935791,43.6999702454],"type":"Point"}
}