{
  "type": "Feature",
  "properties": {
    "addr:full":"435 Kensington St Winnipeg MB R3J 1J8",
    "addr:housenumber":"435",
    "addr:postcode":"r3j 1j8",
    "addr:street":"Kensington St",
    "iso:country":"CA",
    "sg:address":"435 Kensington St",
    "sg:city":"Winnipeg",
    "sg:classifiers":[
        {
            "category":"Wholesale",
            "subcategory":"Auto Parts",
            "type":"Manufacturing & Wholesale Goods"
        }
    ],
    "sg:phone":"+1 204 779 1619",
    "sg:postcode":"R3J 1J8",
    "sg:province":"MB",
    "sg:tags":[
        "glass",
        "rebuilt",
        "automobile"
    ],
    "wof:name":"Best Auto Glass Ltd",
    "wof:placetype":"venue"
},
  "geometry": {"coordinates":[-97.20475,49.888229],"type":"Point"}
}