{
  "type": "Feature",
  "properties": {
    "addr:full":"1231 Rue Gay-Lussac Boucherville QC J4B 7K1",
    "addr:housenumber":"1231",
    "addr:postcode":"j4b 7k1",
    "addr:street":"Rue Gay-Lussac",
    "iso:country":"CA",
    "sg:address":"1231 Rue Gay-Lussac",
    "sg:city":"Boucherville",
    "sg:classifiers":[
        {
            "category":"Building & Trades",
            "subcategory":"Construction",
            "type":"Services"
        }
    ],
    "sg:phone":"+1 450 655 0689",
    "sg:postcode":"J4B 7K1",
    "sg:province":"QC",
    "sg:tags":[
        "designer",
        "dealer",
        "pool",
        "swimming"
    ],
    "wof:name":"Piscines Fontaine Inc",
    "wof:placetype":"venue"
},
  "geometry": {"coordinates":[-73.433762,45.572411],"type":"Point"}
}