{
  "type": "Feature",
  "properties": {
    "addr:full":"101 Norman Dr Kenora ON P9N 3T6",
    "addr:housenumber":"101",
    "addr:postcode":"p9n 3t6",
    "addr:street":"Norman Dr",
    "iso:country":"CA",
    "sg:address":"101 Norman Dr",
    "sg:city":"Kenora",
    "sg:classifiers":[
        {
            "category":"Organizations",
            "subcategory":"Religious Organization",
            "type":"Services"
        }
    ],
    "sg:phone":"+1 807 468 7523",
    "sg:postcode":"P9N 3T6",
    "sg:province":"ON",
    "sg:tags":[
        "church"
    ],
    "wof:name":"Church of Christ",
    "wof:placetype":"venue"
},
  "geometry": {"coordinates":[-94.5347671509,49.7661094666],"type":"Point"}
}