{
  "type": "Feature",
  "properties": {
    "addr:full":"Gods Lake Narrows MB R0B 0M0",
    "addr:postcode":"r0b 0m0",
    "addr:street":"Gods Lake",
    "iso:country":"CA",
    "sg:city":"Gods Lake Narrows",
    "sg:classifiers":[
        {
            "category":"Organizations",
            "subcategory":"Professional Association",
            "type":"Services"
        }
    ],
    "sg:phone":"+1 204 335 2596",
    "sg:postcode":"R0B 0M0",
    "sg:province":"MB",
    "sg:tags":[
        "native"
    ],
    "wof:name":"Gods Narrows Community Council",
    "wof:placetype":"venue"
},
  "geometry": {"coordinates":[-94.52273599999999,54.546169],"type":"Point"}
}