{
  "type": "Feature",
  "properties": {
    "addr:full":"380 Ouellette Ave Windsor ON N9A 6X5",
    "addr:housenumber":"380",
    "addr:postcode":"n9a 6x5",
    "addr:street":"Ouellette Ave",
    "iso:country":"CA",
    "sg:address":"380 Ouellette Ave",
    "sg:city":"Windsor",
    "sg:classifiers":[
        {
            "category":"Shopping",
            "subcategory":"Gifts & Souvenirs",
            "type":"Retail Goods"
        }
    ],
    "sg:phone":"+1 519 258 1990",
    "sg:postcode":"N9A 6X5",
    "sg:province":"ON",
    "sg:tags":[
        "shop"
    ],
    "wof:name":"Cose Belle Gifts & Unique Shop",
    "wof:placetype":"venue"
},
  "geometry": {"coordinates":[-83.03833770750001,42.3167419434],"type":"Point"}
}