{
  "type": "Feature",
  "properties": {
    "addr:full":"Burlington ON L7S 2J8",
    "addr:postcode":"l7s 2j8",
    "iso:country":"CA",
    "sg:city":"Burlington",
    "sg:classifiers":[
        {
            "category":"Restaurant",
            "type":"Food & Drink"
        }
    ],
    "sg:phone":"+1 905 681 9881",
    "sg:postcode":"L7S 2J8",
    "sg:province":"ON",
    "sg:tags":[
        "shop",
        "tea",
        "coffee"
    ],
    "wof:name":"Second Cup",
    "wof:placetype":"venue"
},
  "geometry": {"coordinates":[-79.81972500000001,43.327824],"type":"Point"}
}