{
  "type": "Feature",
  "properties": {
    "addr:full":"121 Dundas St E Belleville ON K8N 1C3",
    "addr:housenumber":"121",
    "addr:postcode":"k8n 1c3",
    "addr:street":"Dundas St E",
    "iso:country":"CA",
    "sg:address":"121 Dundas St E",
    "sg:city":"Belleville",
    "sg:classifiers":[
        {
            "category":"Shopping",
            "subcategory":"Bicycles & Sporting Goods",
            "type":"Retail Goods"
        }
    ],
    "sg:phone":"+1 613 967 2292",
    "sg:postcode":"K8N 1C3",
    "sg:province":"ON",
    "sg:tags":[
        "advertising"
    ],
    "wof:name":"Team Work",
    "wof:placetype":"venue"
},
  "geometry": {"coordinates":[-77.375389,44.161987],"type":"Point"}
}