{
  "type": "Feature",
  "properties": {
    "addr:full":"33 Mapleview Dr E Barrie ON L4N 9H5",
    "addr:housenumber":"33",
    "addr:postcode":"l4n 9h5",
    "addr:street":"Mapleview Dr E",
    "iso:country":"CA",
    "sg:address":"33 Mapleview Dr E",
    "sg:city":"Barrie",
    "sg:classifiers":[
        {
            "category":"Shopping",
            "subcategory":"Shoes",
            "type":"Retail Goods"
        }
    ],
    "sg:phone":"+1 705 727 0935",
    "sg:postcode":"L4N 9H5",
    "sg:province":"ON",
    "wof:name":"Shoe CO",
    "wof:placetype":"venue"
},
  "geometry": {"coordinates":[-79.68236541749999,44.3357810974],"type":"Point"}
}