{
  "type": "Feature",
  "properties": {
    "addr:full":"218 Victoria St Digby NS B0V 1A0",
    "addr:housenumber":"218",
    "addr:postcode":"b0v 1a0",
    "addr:street":"Victoria St",
    "iso:country":"CA",
    "sg:address":"218 Victoria St",
    "sg:city":"Digby",
    "sg:phone":"+1 902 245 6686",
    "sg:postcode":"B0V 1A0",
    "sg:province":"NS",
    "sg:tags":[
        "oil"
    ],
    "wof:name":"West Nova Fuels Ltd",
    "wof:placetype":"venue"
},
  "geometry": {"coordinates":[-65.7681732178,44.6278343201],"type":"Point"}
}