{
  "type": "Feature",
  "properties": {
    "addr:full":"Prince George BC V2M 7B1",
    "addr:postcode":"v2m 7b1",
    "iso:country":"CA",
    "sg:city":"Prince George",
    "sg:classifiers":[
        {
            "category":"Health Services",
            "subcategory":"Doctor",
            "type":"Services"
        }
    ],
    "sg:phone":"+1 250 563 8151",
    "sg:postcode":"V2M 7B1",
    "sg:province":"BC",
    "sg:tags":[
        "physician",
        "surgeon"
    ],
    "wof:name":"Susan Knoll Inc",
    "wof:placetype":"venue"
},
  "geometry": {"coordinates":[-122.766349792,53.9132995605],"type":"Point"}
}