{
  "type": "Feature",
  "properties": {
    "iso:country":"CA",
    "sg:address":"111 Centre St",
    "sg:city":"Kyle",
    "sg:classifiers":[
        {
            "category":"Personal",
            "subcategory":"Beauty Salon",
            "type":"Services"
        }
    ],
    "sg:phone":"+1 306 375 2253",
    "sg:postcode":"S0L 1T0",
    "sg:province":"SK",
    "wof:name":"Dolly's Hair Hut",
    "wof:placetype":"venue"
},
  "geometry": {"coordinates":[-108.03958129900001,50.8342781067],"type":"Point"}
}