{
  "type": "Feature",
  "properties": {
    "iso:country":"CA",
    "sg:address":"52356 Range Road 232",
    "sg:city":"Sherwood Park",
    "sg:classifiers":[
        {
            "category":"Retail",
            "subcategory":"Funeral Services",
            "type":"Services"
        }
    ],
    "sg:phone":"+1 780 467 3337",
    "sg:postcode":"T8B 1B8",
    "sg:province":"AB",
    "sg:tags":[
        "director"
    ],
    "wof:name":"Glenwood Funeral Home",
    "wof:placetype":"venue"
},
  "geometry": {"coordinates":[-113.295570373,53.5061302185],"type":"Point"}
}