{
  "type": "Feature",
  "properties": {
    "iso:country":"CA",
    "sg:address":"250 Harding Blvd W # 404",
    "sg:city":"Richmond Hill",
    "sg:classifiers":[
        {
            "category":"Health Services",
            "subcategory":"Doctor",
            "type":"Services"
        }
    ],
    "sg:phone":"+1 905 737 9898",
    "sg:postcode":"L4C 9M7",
    "sg:province":"ON",
    "sg:tags":[
        "physician",
        "surgeon"
    ],
    "wof:name":"Smith, Eileen MD",
    "wof:placetype":"venue"
},
  "geometry": {"coordinates":[-79.448425,43.868217],"type":"Point"}
}