{
  "type": "Feature",
  "properties": {
    "iso:country":"CA",
    "sg:address":"108 Clonakilty Line",
    "sg:city":"Ennismore",
    "sg:classifiers":[
        {
            "category":"Professional",
            "subcategory":"Business Services",
            "type":"Services"
        }
    ],
    "sg:phone":"+1 705 292 0560",
    "sg:postcode":"K0L 1T0",
    "sg:province":"ON",
    "sg:tags":[
        "wedding",
        "caterer",
        "supply"
    ],
    "wof:name":"Old Smoke House",
    "wof:placetype":"venue"
},
  "geometry": {"coordinates":[-78.42817687989999,44.4106636047],"type":"Point"}
}