{
  "type": "Feature",
  "properties": {
    "addr:full":"48 Richardson Side Rd Kanata ON K2K 1X2",
    "addr:housenumber":"48",
    "addr:postcode":"k2k 1x2",
    "addr:street":"Richardson Side Rd",
    "iso:country":"CA",
    "sg:address":"48 Richardson Side Rd",
    "sg:city":"Kanata",
    "sg:classifiers":[
        {
            "category":"Wholesale",
            "subcategory":"Machinery & Supplies",
            "type":"Manufacturing & Wholesale Goods"
        }
    ],
    "sg:phone":"+1 613 592 5851",
    "sg:postcode":"K2K 1X2",
    "sg:province":"ON",
    "sg:tags":[
        "mill",
        "paper"
    ],
    "wof:name":"Asten Johnson",
    "wof:placetype":"venue"
},
  "geometry": {"coordinates":[-75.903755,45.336094],"type":"Point"}
}