{
  "type": "Feature",
  "properties": {
    "addr:full":"1500 Stone Church Rd E Hamilton ON L8W 3V3",
    "addr:housenumber":"1500",
    "addr:postcode":"l8w 3v3",
    "addr:street":"Stone Church Rd E",
    "iso:country":"CA",
    "sg:address":"1500 Stone Church Rd E",
    "sg:city":"Hamilton",
    "sg:classifiers":[
        {
            "category":"Shopping",
            "subcategory":"Bicycles & Sporting Goods",
            "type":"Retail Goods"
        }
    ],
    "sg:phone":"+1 905 385 5416",
    "sg:postcode":"L8W 3V3",
    "sg:province":"ON",
    "sg:tags":[
        "gun",
        "gunsmith"
    ],
    "wof:name":"Wentworth Shooting Sports Club",
    "wof:placetype":"venue"
},
  "geometry": {"coordinates":[-79.8238601685,43.1951065063],"type":"Point"}
}