{
  "type": "Feature",
  "properties": {
    "addr:full":"220 Boul Brien Repentigny QC J6A 7E9",
    "addr:housenumber":"220",
    "addr:postcode":"j6a 7e9",
    "addr:street":"Boul Brien",
    "iso:country":"CA",
    "sg:address":"220 Boul Brien",
    "sg:city":"Repentigny",
    "sg:classifiers":[
        {
            "category":"Shopping",
            "subcategory":"Department Store",
            "type":"Retail Goods"
        }
    ],
    "sg:phone":"+1 450 581 7373",
    "sg:postcode":"J6A 7E9",
    "sg:province":"QC",
    "wof:name":"Croteau L'Aubainerie Inc",
    "wof:placetype":"venue"
},
  "geometry": {"coordinates":[-73.4638214111,45.7482948303],"type":"Point"}
}