{
  "type": "Feature",
  "properties": {
    "iso:country":"CA",
    "sg:address":"1 Patricia St",
    "sg:city":"Jasper",
    "sg:classifiers":[
        {
            "category":"Restaurant",
            "type":"Food & Drink"
        }
    ],
    "sg:phone":"+1 780 852 4114",
    "sg:postcode":"T0E 1E0",
    "sg:province":"AB",
    "wof:name":"L & W Restaurant",
    "wof:placetype":"venue"
},
  "geometry": {"coordinates":[-118.07880401600001,52.8843383789],"type":"Point"}
}