{
  "type": "Feature",
  "properties": {
    "addr:full":"1125 Gerrard St E Toronto ON M4L 1Y1",
    "addr:housenumber":"1125",
    "addr:postcode":"m4l 1y1",
    "addr:street":"Gerrard St E",
    "iso:country":"CA",
    "sg:address":"1125 Gerrard St E",
    "sg:city":"Toronto",
    "sg:classifiers":[
        {
            "category":"Wholesale",
            "subcategory":"Electrical",
            "type":"Manufacturing & Wholesale Goods"
        }
    ],
    "sg:phone":"+1 416 463 3032",
    "sg:postcode":"M4L 1Y1",
    "sg:province":"ON",
    "sg:tags":[
        "electric",
        "motor"
    ],
    "wof:name":"Delta Electrical Motor Repair",
    "wof:placetype":"venue"
},
  "geometry": {"coordinates":[-79.332741,43.669727],"type":"Point"}
}