{
  "type": "Feature",
  "properties": {
    "addr:full":"584 Headmaster Row Winnipeg MB R2G 3K9",
    "addr:housenumber":"584",
    "addr:postcode":"r2g 3k9",
    "addr:street":"Headmaster Row",
    "iso:country":"CA",
    "sg:address":"584 Headmaster Row",
    "sg:city":"Winnipeg",
    "sg:classifiers":[
        {
            "category":"Real Estate",
            "subcategory":"Real Estate Agent",
            "type":"Services"
        }
    ],
    "sg:phone":"+1 204 338 6234",
    "sg:postcode":"R2G 3K9",
    "sg:province":"MB",
    "wof:name":"Gelhorn, Valerie",
    "wof:placetype":"venue"
},
  "geometry": {"coordinates":[-97.04954499999999,49.949368],"type":"Point"}
}