{
  "type": "Feature",
  "properties": {
    "addr:full":"921 Main St Falher AB T0H 1M0",
    "addr:housenumber":"921",
    "addr:postcode":"t0h 1m0",
    "addr:street":"Main St",
    "iso:country":"CA",
    "sg:address":"921 Main St",
    "sg:city":"Falher",
    "sg:classifiers":[
        {
            "category":"Wholesale",
            "subcategory":"Petroleum",
            "type":"Manufacturing & Wholesale Goods"
        }
    ],
    "sg:phone":"+1 780 837 2284",
    "sg:postcode":"T0H 1M0",
    "sg:province":"AB",
    "sg:tags":[
        "bulk",
        "oil",
        "gasoline"
    ],
    "wof:name":"United Farmers of Alberta",
    "wof:placetype":"venue"
},
  "geometry": {"coordinates":[-117.20212600000001,55.725891],"type":"Point"}
}