{
  "type": "Feature",
  "properties": {
    "addr:full":"Fredericton NB E3A 9N6",
    "addr:postcode":"e3a 9n6",
    "iso:country":"CA",
    "sg:city":"Fredericton",
    "sg:classifiers":[
        {
            "category":"Health Services",
            "subcategory":"Chiropractor",
            "type":"Services"
        }
    ],
    "sg:phone":"+1 506 472 7000",
    "sg:postcode":"E3A 9N6",
    "sg:province":"NB",
    "wof:name":"Lilly, Trisha DC",
    "wof:placetype":"venue"
},
  "geometry": {"coordinates":[-66.65724899999999,45.979725],"type":"Point"}
}