{
  "type": "Feature",
  "properties": {
    "addr:full":"1485 Av Caldwell Ottawa ON K1Z 8M1",
    "addr:housenumber":"1485",
    "addr:postcode":"k1z 8m1",
    "addr:street":"Av Caldwell",
    "iso:country":"CA",
    "sg:address":"1485 Av Caldwell",
    "sg:city":"Ottawa",
    "sg:classifiers":[
        {
            "category":"Government",
            "subcategory":"Office",
            "type":"Public Place"
        }
    ],
    "sg:phone":"+1 613 729 3136",
    "sg:postcode":"K1Z 8M1",
    "sg:province":"ON",
    "sg:tags":[
        "village"
    ],
    "wof:name":"Bureau Du District Du Ctr",
    "wof:placetype":"venue"
},
  "geometry": {"coordinates":[-75.736786,45.372448],"type":"Point"}
}