{
  "type": "Feature",
  "properties": {
    "iso:country":"CA",
    "sg:address":"1054 Western Ave",
    "sg:city":"Peterborough",
    "sg:classifiers":[
        {
            "category":"Food & Beverages",
            "subcategory":"Specialty",
            "type":"Retail Goods"
        }
    ],
    "sg:phone":"+1 705 876 9306",
    "sg:postcode":"K9J 5W4",
    "sg:province":"ON",
    "sg:tags":[
        "supplement"
    ],
    "wof:name":"Spartan Natural Health Produts",
    "wof:placetype":"venue"
},
  "geometry": {"coordinates":[-78.34061431879999,44.2903289795],"type":"Point"}
}