{
  "type": "Feature",
  "properties": {
    "addr:full":"12371 Bridgeport Rd # 1 Richmond BC V6V 1J4",
    "addr:housenumber":"12371",
    "addr:postcode":"v6v 1j4",
    "addr:street":"Bridgeport Rd # 1",
    "iso:country":"CA",
    "sg:address":"12371 Bridgeport Rd # 1",
    "sg:city":"Richmond",
    "sg:classifiers":[
        {
            "category":"Building & Trades",
            "subcategory":"Construction",
            "type":"Services"
        }
    ],
    "sg:phone":"+1 604 276 9233",
    "sg:postcode":"V6V 1J4",
    "sg:province":"BC",
    "sg:tags":[
        "refinishing",
        "floor",
        "laying",
        "rug",
        "resurfacing",
        "dealer",
        "carpet"
    ],
    "wof:name":"Elegant Flooring",
    "wof:placetype":"venue"
},
  "geometry": {"coordinates":[-123.086097717,49.1921958923],"type":"Point"}
}