{
  "type": "Feature",
  "properties": {
    "addr:full":"15380 Av Bourdages S Saint-Hyacinthe QC J2T 3P7",
    "addr:postcode":"j2t 3p7",
    "addr:street":"Av Bourdages S",
    "iso:country":"CA",
    "sg:address":"15380 Av Bourdages S",
    "sg:city":"Saint-Hyacinthe",
    "sg:classifiers":[
        {
            "category":"Health Services",
            "subcategory":"Doctor",
            "type":"Services"
        }
    ],
    "sg:phone":"+1 450 773 7770",
    "sg:postcode":"J2T 3P7",
    "sg:province":"QC",
    "sg:tags":[
        "physician",
        "surgeon"
    ],
    "wof:name":"Bouvier, Gilles MD",
    "wof:placetype":"venue"
},
  "geometry": {"coordinates":[-72.94872283940001,45.6221389771],"type":"Point"}
}