{
  "type": "Feature",
  "properties": {
    "addr:full":"130 Glengrove Ave W Toronto ON M4R 1P2",
    "addr:housenumber":"130",
    "addr:postcode":"m4r 1p2",
    "addr:street":"Glengrove Ave W",
    "iso:country":"CA",
    "sg:address":"130 Glengrove Ave W",
    "sg:city":"Toronto",
    "sg:classifiers":[
        {
            "category":"Education",
            "subcategory":"School",
            "type":"Public Place"
        }
    ],
    "sg:phone":"+1 416 393 9399",
    "sg:postcode":"M4R 1P2",
    "sg:province":"ON",
    "wof:name":"John Ross Robertson Junior",
    "wof:placetype":"venue"
},
  "geometry": {"coordinates":[-79.408737,43.71806],"type":"Point"}
}