{
  "type": "Feature",
  "properties": {
    "iso:country":"CA",
    "sg:address":"309 Maple Leaf Ave N",
    "sg:city":"Ridgeway",
    "sg:classifiers":[
        {
            "category":"Building & Trades",
            "subcategory":"Construction",
            "type":"Services"
        }
    ],
    "sg:phone":"+1 905 894 0373",
    "sg:postcode":"L0S 1N0",
    "sg:province":"ON",
    "sg:tags":[
        "concrete",
        "restoration",
        "repair",
        "cleaning",
        "contractor"
    ],
    "wof:name":"Ochej Restoration",
    "wof:placetype":"venue"
},
  "geometry": {"coordinates":[-79.0415802002,42.8835029602],"type":"Point"}
}