{
  "type": "Feature",
  "properties": {
    "iso:country":"CA",
    "sg:address":"50 Gesner St",
    "sg:city":"Halifax",
    "sg:classifiers":[
        {
            "category":"Organizations",
            "subcategory":"Religious Organization",
            "type":"Services"
        }
    ],
    "sg:phone":"+1 902 443 3844",
    "sg:postcode":"B3M 4H4",
    "sg:province":"NS",
    "sg:tags":[
        "church"
    ],
    "wof:name":"Salvation Army",
    "wof:placetype":"venue"
},
  "geometry": {"coordinates":[-63.64743,44.649857],"type":"Point"}
}