{
  "type": "Feature",
  "properties": {
    "addr:full":"315 Dewdney Ave Regina SK S4N 0E7",
    "addr:housenumber":"315",
    "addr:postcode":"s4n 0e7",
    "addr:street":"Dewdney Ave",
    "iso:country":"CA",
    "sg:address":"315 Dewdney Ave",
    "sg:city":"Regina",
    "sg:classifiers":[
        {
            "category":"Professional",
            "subcategory":"Research",
            "type":"Services"
        }
    ],
    "sg:phone":"+1 306 585 1762",
    "sg:postcode":"S4N 0E7",
    "sg:province":"SK",
    "sg:tags":[
        "environmental",
        "ecological"
    ],
    "wof:name":"Droycon Bioconcepts Inc",
    "wof:placetype":"venue"
},
  "geometry": {"coordinates":[-104.585403,50.455017],"type":"Point"}
}