{
  "type": "Feature",
  "properties": {
    "addr:full":"105 Nugget Ave Scarborough ON M1S 3B1",
    "addr:housenumber":"105",
    "addr:postcode":"m1s 3b1",
    "addr:street":"Nugget Ave",
    "iso:country":"CA",
    "sg:address":"105 Nugget Ave",
    "sg:city":"Scarborough",
    "sg:classifiers":[
        {
            "category":"Autos & Motor Vehicles",
            "subcategory":"Automobile Sales",
            "type":"Retail Goods"
        }
    ],
    "sg:phone":"+1 416 321 2137",
    "sg:postcode":"M1S 3B1",
    "sg:province":"ON",
    "sg:tags":[
        "truck"
    ],
    "wof:name":"Hino Truck Ctr",
    "wof:placetype":"venue"
},
  "geometry": {"coordinates":[-79.25597399999999,43.793144],"type":"Point"}
}