{
  "type": "Feature",
  "properties": {
    "addr:full":"3412 15 Ave Vernon BC V1T 6N9",
    "addr:housenumber":"3412",
    "addr:postcode":"v1t 6n9",
    "addr:street":"15 Ave",
    "iso:country":"CA",
    "sg:address":"3412 15 Ave",
    "sg:city":"Vernon",
    "sg:classifiers":[
        {
            "category":"Organizations",
            "subcategory":"Religious Organization",
            "type":"Services"
        }
    ],
    "sg:phone":"+1 250 545 5941",
    "sg:postcode":"V1T 6N9",
    "sg:province":"BC",
    "sg:tags":[
        "church"
    ],
    "wof:name":"Emmanuel Fellowship Baptist",
    "wof:placetype":"venue"
},
  "geometry": {"coordinates":[-119.279502869,50.2526512146],"type":"Point"}
}