{
  "type": "Feature",
  "properties": {
    "addr:full":"4766 Hyndman Dr Appin ON N0L 1A0",
    "addr:housenumber":"4766",
    "addr:postcode":"n0l 1a0",
    "addr:street":"Hyndman Dr",
    "iso:country":"CA",
    "sg:address":"4766 Hyndman Dr",
    "sg:city":"Appin",
    "sg:classifiers":[
        {
            "category":"Wholesale",
            "subcategory":"Non-durable Goods",
            "type":"Manufacturing & Wholesale Goods"
        }
    ],
    "sg:phone":"+1 519 289 2272",
    "sg:postcode":"N0L 1A0",
    "sg:province":"ON",
    "sg:tags":[
        "advertising"
    ],
    "wof:name":"Shooters Promotional Wear",
    "wof:placetype":"venue"
},
  "geometry": {"coordinates":[-81.65004730219999,42.7957115173],"type":"Point"}
}