{
  "type": "Feature",
  "properties": {
    "addr:full":"843 Wellington St London ON N6A 3S6",
    "addr:housenumber":"843",
    "addr:postcode":"n6a 3s6",
    "addr:street":"Wellington St",
    "iso:country":"CA",
    "sg:address":"843 Wellington St",
    "sg:city":"London",
    "sg:classifiers":[
        {
            "category":"Wholesale",
            "subcategory":"Medical Equipment & Supplies",
            "type":"Manufacturing & Wholesale Goods"
        }
    ],
    "sg:phone":"+1 519 642 0424",
    "sg:postcode":"N6A 3S6",
    "sg:province":"ON",
    "sg:tags":[
        "hospital"
    ],
    "wof:name":"Dyna Medical",
    "wof:placetype":"venue"
},
  "geometry": {"coordinates":[-81.252922,42.999458],"type":"Point"}
}