{
  "type": "Feature",
  "properties": {
    "addr:full":"241 Scott Point Dr Salt Spring Island BC V8K 2R1",
    "addr:housenumber":"241",
    "addr:postcode":"v8k 2r1",
    "addr:street":"Scott Point Dr",
    "iso:country":"CA",
    "sg:address":"241 Scott Point Dr",
    "sg:city":"Salt Spring Island",
    "sg:classifiers":[
        {
            "category":"Organizations",
            "subcategory":"Community Association",
            "type":"Services"
        }
    ],
    "sg:phone":"+1 250 537 5033",
    "sg:postcode":"V8K 2R1",
    "sg:province":"BC",
    "sg:tags":[
        "club"
    ],
    "wof:name":"Royal Vancouver Yacht Club",
    "wof:placetype":"venue"
},
  "geometry": {"coordinates":[-123.439796,48.847717],"type":"Point"}
}