{
  "type": "Feature",
  "properties": {
    "iso:country":"CA",
    "sg:address":"1777 Rue Mitis",
    "sg:city":"Chicoutimi",
    "sg:classifiers":[
        {
            "category":"Manufacturing",
            "subcategory":"Tools & Machinery",
            "type":"Manufacturing & Wholesale Goods"
        }
    ],
    "sg:phone":"+1 418 698 2900",
    "sg:postcode":"G7K 1H3",
    "sg:province":"QC",
    "sg:tags":[
        "contractor"
    ],
    "wof:name":"Trans-Quebec Diesel",
    "wof:placetype":"venue"
},
  "geometry": {"coordinates":[-71.12619018549999,48.403591156],"type":"Point"}
}