{
  "type": "Feature",
  "properties": {
    "addr:full":"1525 Walters Way NW Medicine Hat AB T1C 1V9",
    "addr:housenumber":"1525",
    "addr:postcode":"t1c 1v9",
    "addr:street":"Walters Way Nw",
    "iso:country":"CA",
    "sg:address":"1525 Walters Way NW",
    "sg:city":"Medicine Hat",
    "sg:classifiers":[
        {
            "category":"Freight",
            "type":"Transportation"
        }
    ],
    "sg:phone":"+1 403 527 8666",
    "sg:postcode":"T1C 1V9",
    "sg:province":"AB",
    "sg:tags":[
        "trucking"
    ],
    "wof:name":"Lambert Trucking Ltd",
    "wof:placetype":"venue"
},
  "geometry": {"coordinates":[-110.72350299999999,50.054043],"type":"Point"}
}