{
  "type": "Feature",
  "properties": {
    "addr:full":"2334 Trent St # 190 Victoria BC V8R 4Z3",
    "addr:housenumber":"2334;190",
    "addr:postcode":"v8r 4z3",
    "addr:street":"Trent St #",
    "iso:country":"CA",
    "sg:address":"2334 Trent St # 190",
    "sg:city":"Victoria",
    "sg:classifiers":[
        {
            "category":"Health Services",
            "subcategory":"Doctor",
            "type":"Services"
        }
    ],
    "sg:phone":"+1 250 598 6021",
    "sg:postcode":"V8R 4Z3",
    "sg:province":"BC",
    "sg:tags":[
        "physician",
        "surgeon"
    ],
    "wof:name":"Victoria Medical Society",
    "wof:placetype":"venue"
},
  "geometry": {"coordinates":[-123.324043,48.43259],"type":"Point"}
}