{
  "type": "Feature",
  "properties": {
    "addr:full":"111 Pearson Rd Welland ON L3B 5N4",
    "addr:housenumber":"111",
    "addr:postcode":"l3b 5n4",
    "addr:street":"Pearson Rd",
    "iso:country":"CA",
    "sg:address":"111 Pearson Rd",
    "sg:city":"Welland",
    "sg:classifiers":[
        {
            "category":"Real Estate",
            "subcategory":"Surveying",
            "type":"Services"
        }
    ],
    "sg:phone":"+1 905 788 1448",
    "sg:postcode":"L3B 5N4",
    "sg:province":"ON",
    "sg:tags":[
        "engineer"
    ],
    "wof:name":"Russell Technical Svc Inc",
    "wof:placetype":"venue"
},
  "geometry": {"coordinates":[-79.1798171997,42.990398407],"type":"Point"}
}