{
  "type": "Feature",
  "properties": {
    "addr:full":"7321 3rd St Grand Forks BC V0H 1H0",
    "addr:housenumber":"7321",
    "addr:postcode":"v0h 1h0",
    "addr:street":"3Rd St",
    "iso:country":"CA",
    "sg:address":"7321 3rd St",
    "sg:city":"Grand Forks",
    "sg:classifiers":[
        {
            "category":"Personal",
            "subcategory":"Beauty Salon",
            "type":"Services"
        }
    ],
    "sg:phone":"+1 250 442 0114",
    "sg:postcode":"V0H 1H0",
    "sg:province":"BC",
    "wof:name":"Mane Event Hair CO",
    "wof:placetype":"venue"
},
  "geometry": {"coordinates":[-118.438728,49.032906],"type":"Point"}
}