{
  "type": "Feature",
  "properties": {
    "addr:full":"250 Queen St W Toronto ON M5V 1Z7",
    "addr:housenumber":"250",
    "addr:postcode":"m5v 1z7",
    "addr:street":"Queen St W",
    "iso:country":"CA",
    "sg:address":"250 Queen St W",
    "sg:city":"Toronto",
    "sg:classifiers":[
        {
            "category":"Shopping",
            "subcategory":"Music",
            "type":"Retail Goods"
        }
    ],
    "sg:phone":"+1 416 599 5424",
    "sg:postcode":"M5V 1Z7",
    "sg:province":"ON",
    "sg:tags":[
        "compact",
        "record",
        "disc",
        "tape"
    ],
    "wof:name":"Numb Clothing",
    "wof:placetype":"venue"
},
  "geometry": {"coordinates":[-79.391075,43.649948],"type":"Point"}
}