{
  "type": "Feature",
  "properties": {
    "addr:full":"Saint-Charles-DE-Bellechasse QC G0R 2T0",
    "addr:postcode":"g0r 2t0",
    "iso:country":"CA",
    "sg:city":"Saint-Charles-DE-Bellechasse",
    "sg:classifiers":[
        {
            "category":"Professional",
            "subcategory":"Business Services",
            "type":"Services"
        }
    ],
    "sg:phone":"+1 418 887 6720",
    "sg:postcode":"G0R 2T0",
    "sg:province":"QC",
    "sg:tags":[
        "notary"
    ],
    "wof:name":"Leblond, Nathalie",
    "wof:placetype":"venue"
},
  "geometry": {"coordinates":[-70.942527771,46.7703742981],"type":"Point"}
}