{
  "type": "Feature",
  "properties": {
    "iso:country":"CA",
    "sg:address":"466 Mill Rd",
    "sg:city":"Qualicum Beach",
    "sg:classifiers":[
        {
            "category":"Building & Trades",
            "subcategory":"Construction",
            "type":"Services"
        }
    ],
    "sg:phone":"+1 250 752 1120",
    "sg:postcode":"V9K 1J6",
    "sg:province":"BC",
    "sg:tags":[
        "repairing",
        "remodeling",
        "contractor"
    ],
    "wof:name":"Sea-Island Homes-Qualicum",
    "wof:placetype":"venue"
},
  "geometry": {"coordinates":[-124.460441589,49.3495254517],"type":"Point"}
}