{
  "type": "Feature",
  "properties": {
    "addr:full":"Sundridge ON P0A 1Z0",
    "addr:postcode":"p0a 1z0",
    "iso:country":"CA",
    "sg:city":"Sundridge",
    "sg:classifiers":[
        {
            "category":"Food & Beverages",
            "subcategory":"Groceries & Convenience Stores",
            "type":"Retail Goods"
        }
    ],
    "sg:phone":"+1 705 384 5378",
    "sg:postcode":"P0A 1Z0",
    "sg:province":"ON",
    "sg:tags":[
        "vegetable",
        "fruit",
        "produce"
    ],
    "wof:name":"Sundridge Iga",
    "wof:placetype":"venue"
},
  "geometry": {"coordinates":[-79.39643100000001,45.769032],"type":"Point"}
}