{
  "type": "Feature",
  "properties": {
    "addr:full":"215 Rue Jean-Talon O Montreal QC H2R 2X6",
    "addr:housenumber":"215",
    "addr:postcode":"h2r 2x6",
    "addr:street":"Rue Jean-Talon O",
    "iso:country":"CA",
    "sg:address":"215 Rue Jean-Talon O",
    "sg:city":"Montreal",
    "sg:classifiers":[
        {
            "category":"Organizations",
            "subcategory":"Membership Organization",
            "type":"Services"
        }
    ],
    "sg:phone":"+1 514 278 7773",
    "sg:postcode":"H2R 2X6",
    "sg:province":"QC",
    "sg:tags":[
        "dance",
        "club"
    ],
    "wof:name":"Exotika",
    "wof:placetype":"venue"
},
  "geometry": {"coordinates":[-73.616074,45.536766],"type":"Point"}
}