{
  "type": "Feature",
  "properties": {
    "addr:full":"Edmonton AB T6N 1A8",
    "addr:postcode":"t6n 1a8",
    "iso:country":"CA",
    "sg:city":"Edmonton",
    "sg:classifiers":[
        {
            "category":"Building & Trades",
            "subcategory":"Construction",
            "type":"Services"
        }
    ],
    "sg:phone":"+1 780 461 4799",
    "sg:postcode":"T6N 1A8",
    "sg:province":"AB",
    "sg:tags":[
        "control",
        "corrosion"
    ],
    "wof:name":"Asm Corrosion Control Ltd",
    "wof:placetype":"venue"
},
  "geometry": {"coordinates":[-113.48764,53.460022],"type":"Point"}
}