{
  "type": "Feature",
  "properties": {
    "addr:full":"90 Thorncliffe Park Dr East York ON M4H 1N5",
    "addr:housenumber":"90",
    "addr:postcode":"m4h 1n5",
    "addr:street":"Thorncliffe Park Dr",
    "iso:country":"CA",
    "sg:address":"90 Thorncliffe Park Dr",
    "sg:city":"East York",
    "sg:phone":"+1 416 422 1261",
    "sg:postcode":"M4H 1N5",
    "sg:province":"ON",
    "sg:tags":[
        "equipment",
        "supply"
    ],
    "wof:name":"Sunshine Bar & Restaurant Sply",
    "wof:placetype":"venue"
},
  "geometry": {"coordinates":[-79.343964,43.707806],"type":"Point"}
}