{
  "type": "Feature",
  "properties": {
    "addr:full":"Sainte-Marthe-Du-Cap QC G8T 9M1",
    "addr:postcode":"g8t 9m1",
    "iso:country":"CA",
    "sg:city":"Sainte-Marthe-Du-Cap",
    "sg:classifiers":[
        {
            "category":"Manufacturing",
            "subcategory":"Tools & Machinery",
            "type":"Manufacturing & Wholesale Goods"
        }
    ],
    "sg:phone":"+1 819 693 4162",
    "sg:postcode":"G8T 9M1",
    "sg:province":"QC",
    "sg:tags":[
        "machine",
        "shop"
    ],
    "wof:name":"Atelier Usinatex",
    "wof:placetype":"venue"
},
  "geometry": {"coordinates":[-72.4964523315,46.3772125244],"type":"Point"}
}