{
  "type": "Feature",
  "properties": {
    "addr:full":"320 Princess St Winnipeg MB R3B 3C7",
    "addr:housenumber":"320",
    "addr:postcode":"r3b 3c7",
    "addr:street":"Princess St",
    "iso:country":"CA",
    "sg:address":"320 Princess St",
    "sg:city":"Winnipeg",
    "sg:classifiers":[
        {
            "category":"Organizations",
            "subcategory":"Religious Organization",
            "type":"Services"
        }
    ],
    "sg:phone":"+1 204 943 9904",
    "sg:postcode":"R3B 3C7",
    "sg:province":"MB",
    "sg:tags":[
        "social",
        "welfare",
        "church"
    ],
    "wof:name":"Union Gospel Mission",
    "wof:placetype":"venue"
},
  "geometry": {"coordinates":[-97.137726,49.904598],"type":"Point"}
}