{
  "type": "Feature",
  "properties": {
    "addr:full":"Kelowna BC V1Y 5V7",
    "addr:postcode":"v1y 5v7",
    "iso:country":"CA",
    "sg:city":"Kelowna",
    "sg:classifiers":[
        {
            "category":"Recreation",
            "type":"Entertainment"
        }
    ],
    "sg:phone":"+1 250 717 8260",
    "sg:postcode":"V1Y 5V7",
    "sg:province":"BC",
    "sg:tags":[
        "amusement"
    ],
    "wof:name":"Planet Lazer",
    "wof:placetype":"venue"
},
  "geometry": {"coordinates":[-119.452141,49.877449],"type":"Point"}
}