{
  "type": "Feature",
  "properties": {
    "addr:full":"5039 45th St Rocky Mountain House AB T4T 1A8",
    "addr:housenumber":"5039",
    "addr:postcode":"t4t 1a8",
    "addr:street":"45Th St",
    "iso:country":"CA",
    "sg:address":"5039 45th St",
    "sg:city":"Rocky Mountain House",
    "sg:classifiers":[
        {
            "category":"Professional",
            "subcategory":"Business Services",
            "type":"Services"
        }
    ],
    "sg:phone":"+1 403 845 5602",
    "sg:postcode":"T4T 1A8",
    "sg:province":"AB",
    "sg:tags":[
        "embroidery"
    ],
    "wof:name":"Elite Embroidery & Design",
    "wof:placetype":"venue"
},
  "geometry": {"coordinates":[-114.91197200000001,52.37455],"type":"Point"}
}