{
  "type": "Feature",
  "properties": {
    "addr:full":"Calgary AB T2A 1X2",
    "addr:postcode":"t2a 1x2",
    "iso:country":"CA",
    "sg:city":"Calgary",
    "sg:classifiers":[
        {
            "category":"Building & Trades",
            "subcategory":"Plumbing",
            "type":"Services"
        }
    ],
    "sg:phone":"+1 403 248 2105",
    "sg:postcode":"T2A 1X2",
    "sg:province":"AB",
    "sg:tags":[
        "contractor"
    ],
    "wof:name":"Sani-Tech Mechanical Ltd",
    "wof:placetype":"venue"
},
  "geometry": {"coordinates":[-114.000892639,51.0508499146],"type":"Point"}
}