{
  "type": "Feature",
  "properties": {
    "addr:full":"400 Rue Des Sagueneens Chicoutimi QC G7H 5S5",
    "addr:housenumber":"400",
    "addr:postcode":"g7h 5s5",
    "addr:street":"Rue Des Sagueneens",
    "iso:country":"CA",
    "sg:address":"400 Rue Des Sagueneens",
    "sg:city":"Chicoutimi",
    "sg:classifiers":[
        {
            "category":"Shopping",
            "subcategory":"Pharmacy",
            "type":"Retail Goods"
        }
    ],
    "sg:phone":"+1 418 543 5566",
    "sg:postcode":"G7H 5S5",
    "sg:province":"QC",
    "wof:name":"Pharmacie Jean Coutu",
    "wof:placetype":"venue"
},
  "geometry": {"coordinates":[-71.059341,48.402576],"type":"Point"}
}