{
  "type": "Feature",
  "properties": {
    "addr:full":"7150 Rue Marie-Victorin Montreal QC H1G 2J5",
    "addr:housenumber":"7150",
    "addr:postcode":"h1g 2j5",
    "addr:street":"Rue Marie-Victorin",
    "iso:country":"CA",
    "sg:address":"7150 Rue Marie-Victorin",
    "sg:city":"Montreal",
    "sg:classifiers":[
        {
            "category":"Organizations",
            "subcategory":"Labor Organization",
            "type":"Services"
        }
    ],
    "sg:phone":"+1 514 325 6837",
    "sg:postcode":"H1G 2J5",
    "sg:province":"QC",
    "wof:name":"Sqees",
    "wof:placetype":"venue"
},
  "geometry": {"coordinates":[-73.606346,45.617401],"type":"Point"}
}