{
  "type": "Feature",
  "properties": {
    "iso:country":"CA",
    "sg:address":"478 Industrial Ave",
    "sg:city":"Woodstock",
    "sg:classifiers":[
        {
            "category":"Food & Beverages",
            "subcategory":"Dairy",
            "type":"Retail Goods"
        }
    ],
    "sg:phone":"+1 519 537 2361",
    "sg:postcode":"N4S 7L1",
    "sg:province":"ON",
    "sg:tags":[
        "product"
    ],
    "wof:name":"Bright Cheese House",
    "wof:placetype":"venue"
},
  "geometry": {"coordinates":[-80.7444076538,43.1489868164],"type":"Point"}
}