{
  "type": "Feature",
  "properties": {
    "iso:country":"CA",
    "sg:city":"Kelowna",
    "sg:classifiers":[
        {
            "category":"Health Services",
            "subcategory":"Clinic",
            "type":"Services"
        }
    ],
    "sg:phone":"+1 250 860 1887",
    "sg:postcode":"V1V 1Y5",
    "sg:province":"BC",
    "wof:name":"Viewpoint Kelowna",
    "wof:placetype":"venue"
},
  "geometry": {"coordinates":[-119.447135925,49.9137611389],"type":"Point"}
}