{
  "type": "Feature",
  "properties": {
    "addr:full":"Burlington ON L7L 6B5",
    "addr:postcode":"l7l 6b5",
    "iso:country":"CA",
    "sg:city":"Burlington",
    "sg:classifiers":[
        {
            "category":"Manufacturing",
            "subcategory":"Paper Products",
            "type":"Manufacturing & Wholesale Goods"
        }
    ],
    "sg:phone":"+1 905 632 2314",
    "sg:postcode":"L7L 6B5",
    "sg:province":"ON",
    "sg:tags":[
        "label"
    ],
    "wof:name":"Artcraft Label",
    "wof:placetype":"venue"
},
  "geometry": {"coordinates":[-79.762306,43.382641],"type":"Point"}
}