{
  "type": "Feature",
  "properties": {
    "addr:full":"6 Industrial Park Rd Lewisporte NL A0G 3A0",
    "addr:housenumber":"6",
    "addr:postcode":"a0g 3a0",
    "addr:street":"Industrial Park Rd",
    "iso:country":"CA",
    "sg:address":"6 Industrial Park Rd",
    "sg:city":"Lewisporte",
    "sg:classifiers":[
        {
            "category":"Autos & Motor Vehicles",
            "subcategory":"Auto Supplies",
            "type":"Retail Goods"
        }
    ],
    "sg:phone":"+1 709 535 8191",
    "sg:postcode":"A0G 3A0",
    "sg:province":"NL",
    "sg:tags":[
        "automobile",
        "parts",
        "rental"
    ],
    "wof:name":"Rentals Unlimited",
    "wof:placetype":"venue"
},
  "geometry": {"coordinates":[-55.0599365234,49.2417984009],"type":"Point"}
}