{
  "type": "Feature",
  "properties": {
    "addr:full":"Sainte-Foy QC G1V 4T3",
    "addr:postcode":"g1v 4t3",
    "iso:country":"CA",
    "sg:city":"Sainte-Foy",
    "sg:classifiers":[
        {
            "category":"Shopping",
            "subcategory":"Clothing, Apparel, & Fashions",
            "type":"Retail Goods"
        }
    ],
    "sg:phone":"+1 418 654 2944",
    "sg:postcode":"G1V 4T3",
    "sg:province":"QC",
    "wof:name":"Globus",
    "wof:placetype":"venue"
},
  "geometry": {"coordinates":[-71.281059,46.771248],"type":"Point"}
}