{
  "type": "Feature",
  "properties": {
    "addr:full":"245 Lewisville Rd Moncton NB E1A 6T1",
    "addr:housenumber":"245",
    "addr:postcode":"e1a 6t1",
    "addr:street":"Lewisville Rd",
    "iso:country":"CA",
    "sg:address":"245 Lewisville Rd",
    "sg:city":"Moncton",
    "sg:classifiers":[
        {
            "category":"Wholesale",
            "subcategory":"Machinery & Supplies",
            "type":"Manufacturing & Wholesale Goods"
        }
    ],
    "sg:phone":"+1 506 382 2550",
    "sg:postcode":"E1A 6T1",
    "sg:province":"NB",
    "sg:tags":[
        "janitor"
    ],
    "wof:name":"Maritime Sanitation Products",
    "wof:placetype":"venue"
},
  "geometry": {"coordinates":[-64.766518,46.10244],"type":"Point"}
}