{
  "type": "Feature",
  "properties": {
    "addr:full":"14130 Old Scugog Blackstock ON L0B 1B0",
    "addr:housenumber":"14130",
    "addr:postcode":"l0b 1b0",
    "addr:street":"Old Scugog Blackstock",
    "iso:country":"CA",
    "sg:address":"14130 Old Scugog",
    "sg:city":"Blackstock",
    "sg:classifiers":[
        {
            "category":"Building & Trades",
            "subcategory":"Construction",
            "type":"Services"
        }
    ],
    "sg:phone":"+1 905 986 0012",
    "sg:postcode":"L0B 1B0",
    "sg:province":"ON",
    "sg:tags":[
        "waterproofing",
        "contractor"
    ],
    "wof:name":"Schneider Waterproofing",
    "wof:placetype":"venue"
},
  "geometry": {"coordinates":[-78.821152,44.108521],"type":"Point"}
}