{
  "type": "Feature",
  "properties": {
    "addr:full":"Montreal QC H4B 2L9",
    "addr:postcode":"h4b 2l9",
    "iso:country":"CA",
    "sg:city":"Montreal",
    "sg:classifiers":[
        {
            "category":"Organizations",
            "subcategory":"Professional Association",
            "type":"Services"
        }
    ],
    "sg:phone":"+1 514 481 5619",
    "sg:postcode":"H4B 2L9",
    "sg:province":"QC",
    "wof:name":"Quebec Federation Home & Schl",
    "wof:placetype":"venue"
},
  "geometry": {"coordinates":[-73.62818900000001,45.463547],"type":"Point"}
}