{
  "type": "Feature",
  "properties": {
    "addr:full":"436 Huron Rd Goderich ON N7A 3A5",
    "addr:housenumber":"436",
    "addr:postcode":"n7a 3a5",
    "addr:street":"Huron Rd",
    "iso:country":"CA",
    "sg:address":"436 Huron Rd",
    "sg:city":"Goderich",
    "sg:classifiers":[
        {
            "category":"Wholesale",
            "subcategory":"Groceries",
            "type":"Manufacturing & Wholesale Goods"
        }
    ],
    "sg:phone":"+1 519 524 9262",
    "sg:postcode":"N7A 3A5",
    "sg:province":"ON",
    "sg:tags":[
        "salt"
    ],
    "wof:name":"Canadian Salt CO Ltd",
    "wof:placetype":"venue"
},
  "geometry": {"coordinates":[-81.6919174194,43.7317733765],"type":"Point"}
}