{
  "type": "Feature",
  "properties": {
    "addr:full":"4718 97 St NW Edmonton AB T6E 5S1",
    "addr:housenumber":"4718",
    "addr:postcode":"t6e 5s1",
    "addr:street":"97 St Nw",
    "iso:country":"CA",
    "sg:address":"4718 97 St NW",
    "sg:city":"Edmonton",
    "sg:classifiers":[
        {
            "category":"Wholesale",
            "subcategory":"Machinery & Supplies",
            "type":"Manufacturing & Wholesale Goods"
        }
    ],
    "sg:phone":"+1 780 437 7406",
    "sg:postcode":"T6E 5S1",
    "sg:province":"AB",
    "sg:tags":[
        "instrument",
        "surveying"
    ],
    "wof:name":"Cancel Survey Equipment",
    "wof:placetype":"venue"
},
  "geometry": {"coordinates":[-113.479584,53.485043],"type":"Point"}
}