{
  "type": "Feature",
  "properties": {
    "addr:full":"Campbellton NB E3N 3L4",
    "addr:postcode":"e3n 3l4",
    "iso:country":"CA",
    "sg:city":"Campbellton",
    "sg:classifiers":[
        {
            "category":"Professional",
            "subcategory":"Lawyer & Legal Services",
            "type":"Services"
        }
    ],
    "sg:phone":"+1 506 753 3306",
    "sg:postcode":"E3N 3L4",
    "sg:province":"NB",
    "sg:tags":[
        "attorney"
    ],
    "wof:name":"Humphrey Matchim Raymond",
    "wof:placetype":"venue"
},
  "geometry": {"coordinates":[-66.67580413819999,48.0066604614],"type":"Point"}
}