{
  "type": "Feature",
  "properties": {
    "addr:full":"2102 Wikwemikong Way Wikwemikong ON P0P 2J0",
    "addr:housenumber":"2102",
    "addr:postcode":"p0p 2j0",
    "addr:street":"Wikwemikong Way",
    "iso:country":"CA",
    "sg:address":"2102 Wikwemikong Way",
    "sg:city":"Wikwemikong",
    "sg:classifiers":[
        {
            "category":"Professional",
            "subcategory":"Management & Consulting",
            "type":"Services"
        }
    ],
    "sg:phone":"+1 705 859 3001",
    "sg:postcode":"P0P 2J0",
    "sg:province":"ON",
    "sg:tags":[
        "development",
        "economic",
        "agency"
    ],
    "wof:name":"Wikwemikong Dev Commission",
    "wof:placetype":"venue"
},
  "geometry": {"coordinates":[-81.736992,45.789349],"type":"Point"}
}