{
  "type": "Feature",
  "properties": {
    "addr:full":"4311 Hazelbridge Way # 1840 Richmond BC V6X 3L7",
    "addr:housenumber":"4311",
    "addr:postcode":"v6x 3l7",
    "addr:street":"Hazelbridge Way # 1840",
    "iso:country":"CA",
    "sg:address":"4311 Hazelbridge Way # 1840",
    "sg:city":"Richmond",
    "sg:classifiers":[
        {
            "category":"Autos & Motor Vehicles",
            "subcategory":"Auto Supplies",
            "type":"Retail Goods"
        }
    ],
    "sg:phone":"+1 604 244 8032",
    "sg:postcode":"V6X 3L7",
    "sg:province":"BC",
    "sg:tags":[
        "automobile",
        "parts"
    ],
    "wof:name":"Haydon Enterprises Ltd",
    "wof:placetype":"venue"
},
  "geometry": {"coordinates":[-123.13362121599999,49.1821479797],"type":"Point"}
}