{
  "type": "Feature",
  "properties": {
    "addr:full":"29 Westville Rd New Glasgow NS B2H 2J2",
    "addr:housenumber":"29",
    "addr:postcode":"b2h 2j2",
    "addr:street":"Westville Rd",
    "iso:country":"CA",
    "sg:address":"29 Westville Rd",
    "sg:city":"New Glasgow",
    "sg:classifiers":[
        {
            "category":"Restaurant",
            "type":"Food & Drink"
        }
    ],
    "sg:phone":"+1 902 752 4686",
    "sg:postcode":"B2H 2J2",
    "sg:province":"NS",
    "wof:name":"Joe Chow Drive-In Restaurant",
    "wof:placetype":"venue"
},
  "geometry": {"coordinates":[-62.6530418396,45.5860595703],"type":"Point"}
}