{
  "type": "Feature",
  "properties": {
    "addr:full":"Dartmouth NS B3B 1V6",
    "addr:postcode":"b3b 1v6",
    "iso:country":"CA",
    "sg:city":"Dartmouth",
    "sg:classifiers":[
        {
            "category":"Utilities",
            "subcategory":"Mobile Phone",
            "type":"Services"
        }
    ],
    "sg:phone":"+1 902 468 5062",
    "sg:postcode":"B3B 1V6",
    "sg:province":"NS",
    "sg:tags":[
        "telephone",
        "cellular"
    ],
    "wof:name":"Nova Communications",
    "wof:placetype":"venue"
},
  "geometry": {"coordinates":[-63.590099,44.707146],"type":"Point"}
}