{
  "type": "Feature",
  "properties": {
    "addr:full":"Mississauga ON L4Y 2B8",
    "addr:postcode":"l4y 2b8",
    "iso:country":"CA",
    "sg:city":"Mississauga",
    "sg:classifiers":[
        {
            "category":"Building & Trades",
            "subcategory":"Construction",
            "type":"Services"
        }
    ],
    "sg:phone":"+1 905 276 9980",
    "sg:postcode":"L4Y 2B8",
    "sg:province":"ON",
    "sg:tags":[
        "contractor"
    ],
    "wof:name":"Ashley Oak Homes Inc",
    "wof:placetype":"venue"
},
  "geometry": {"coordinates":[-79.59429168699999,43.5995979309],"type":"Point"}
}