{
  "type": "Feature",
  "properties": {
    "addr:full":"2255 Barton St E Hamilton ON L8H 7T4",
    "addr:housenumber":"2255",
    "addr:postcode":"l8h 7t4",
    "addr:street":"Barton St E",
    "iso:country":"CA",
    "sg:address":"2255 Barton St E",
    "sg:city":"Hamilton",
    "sg:classifiers":[
        {
            "category":"Shopping",
            "subcategory":"Clothing, Apparel, & Fashions",
            "type":"Retail Goods"
        }
    ],
    "sg:phone":"+1 905 561 6667",
    "sg:postcode":"L8H 7T4",
    "sg:province":"ON",
    "sg:tags":[
        "equipment",
        "work",
        "safety"
    ],
    "wof:name":"Iseco Safety Shoes",
    "wof:placetype":"venue"
},
  "geometry": {"coordinates":[-79.7705459595,43.2393455505],"type":"Point"}
}