{
  "type": "Feature",
  "properties": {
    "addr:full":"7 King St W Stoney Creek ON L8G 1G7",
    "addr:housenumber":"7",
    "addr:postcode":"l8g 1g7",
    "addr:street":"King St W",
    "iso:country":"CA",
    "sg:address":"7 King St W",
    "sg:city":"Stoney Creek",
    "sg:classifiers":[
        {
            "category":"Organizations",
            "subcategory":"Religious Organization",
            "type":"Services"
        }
    ],
    "sg:phone":"+1 905 664 6043",
    "sg:postcode":"L8G 1G7",
    "sg:province":"ON",
    "sg:tags":[
        "church"
    ],
    "wof:name":"Cheyne Presbyterian Church",
    "wof:placetype":"venue"
},
  "geometry": {"coordinates":[-79.758957,43.217052],"type":"Point"}
}