{
  "type": "Feature",
  "properties": {
    "addr:full":"Perkinsfield ON L0L 2J0",
    "addr:postcode":"l0l 2j0",
    "iso:country":"CA",
    "sg:city":"Perkinsfield",
    "sg:classifiers":[
        {
            "category":"Retail",
            "subcategory":"Auto Repair",
            "type":"Services"
        }
    ],
    "sg:phone":"+1 705 549 8997",
    "sg:postcode":"L0L 2J0",
    "sg:province":"ON",
    "sg:tags":[
        "body",
        "automobile",
        "painting"
    ],
    "wof:name":"G & R Moreau Auto Body",
    "wof:placetype":"venue"
},
  "geometry": {"coordinates":[-79.96974899999999,44.707382],"type":"Point"}
}