{
  "type": "Feature",
  "properties": {
    "iso:country":"CA",
    "sg:address":"138 Rue Principale",
    "sg:city":"Aylmer",
    "sg:classifiers":[
        {
            "category":"Shopping",
            "subcategory":"Florist",
            "type":"Retail Goods"
        }
    ],
    "sg:phone":"+1 819 684 8302",
    "sg:postcode":"J9H 3M4",
    "sg:province":"QC",
    "wof:name":"Au Fleuriste Aylmer",
    "wof:placetype":"venue"
},
  "geometry": {"coordinates":[-75.8422012329,45.3949584961],"type":"Point"}
}