{
  "type": "Feature",
  "properties": {
    "addr:full":"RR 1 Birch Hills SK S0J 0G0",
    "addr:postcode":"s0j 0g0",
    "addr:street":"Rr 1 Birch",
    "iso:country":"CA",
    "sg:address":"RR 1",
    "sg:city":"Birch Hills",
    "sg:classifiers":[
        {
            "category":"Government",
            "subcategory":"Office",
            "type":"Public Place"
        }
    ],
    "sg:phone":"+1 306 749 2818",
    "sg:postcode":"S0J 0G0",
    "sg:province":"SK",
    "wof:name":"SK Fenton Ferry",
    "wof:placetype":"venue"
},
  "geometry": {"coordinates":[-105.438393,52.983292],"type":"Point"}
}