{
  "type": "Feature",
  "properties": {
    "iso:country":"CA",
    "sg:address":"70 Rue Principale S",
    "sg:city":"Saint-Felix-DE-Dalquier",
    "sg:classifiers":[
        {
            "category":"Local Transit",
            "type":"Transportation"
        }
    ],
    "sg:phone":"+1 819 732 3883",
    "sg:postcode":"J0Y 1G0",
    "sg:province":"QC",
    "sg:tags":[
        "bus",
        "line"
    ],
    "wof:name":"Transport Abl Inc",
    "wof:placetype":"venue"
},
  "geometry": {"coordinates":[-78.11432647709999,48.6743812561],"type":"Point"}
}