{
  "type": "Feature",
  "properties": {
    "addr:full":"817 Rue Honore-Mercier Iberville QC J2X 3S4",
    "addr:housenumber":"817",
    "addr:postcode":"j2x 3s4",
    "addr:street":"Rue Honore-Mercier",
    "iso:country":"CA",
    "sg:address":"817 Rue Honore-Mercier",
    "sg:city":"Iberville",
    "sg:classifiers":[
        {
            "category":"Personal",
            "subcategory":"Beauty Salon",
            "type":"Services"
        }
    ],
    "sg:phone":"+1 450 347 4399",
    "sg:postcode":"J2X 3S4",
    "sg:province":"QC",
    "wof:name":"Salon DE Coiffure Autre Image",
    "wof:placetype":"venue"
},
  "geometry": {"coordinates":[-73.236549,45.304314],"type":"Point"}
}