{
  "type": "Feature",
  "properties": {
    "iso:country":"CA",
    "sg:address":"3231 No. 6 Rd",
    "sg:city":"Richmond",
    "sg:classifiers":[
        {
            "category":"Freight",
            "type":"Transportation"
        }
    ],
    "sg:phone":"+1 604 273 3967",
    "sg:postcode":"V6V 1P6",
    "sg:province":"BC",
    "sg:tags":[
        "warehouse",
        "storage"
    ],
    "wof:name":"Versacold Storage & Distr",
    "wof:placetype":"venue"
},
  "geometry": {"coordinates":[-123.06945,49.189934],"type":"Point"}
}