{
  "type": "Feature",
  "properties": {
    "addr:full":"513 Rue Principale Lachute QC J8H 1Y5",
    "addr:housenumber":"513",
    "addr:postcode":"j8h 1y5",
    "addr:street":"Rue Principale",
    "iso:country":"CA",
    "sg:address":"513 Rue Principale",
    "sg:city":"Lachute",
    "sg:classifiers":[
        {
            "category":"Social Services",
            "type":"Services"
        }
    ],
    "sg:phone":"+1 450 562 3719",
    "sg:postcode":"J8H 1Y5",
    "sg:province":"QC",
    "sg:tags":[
        "organization",
        "welfare"
    ],
    "wof:name":"Laurentian Literacy Council",
    "wof:placetype":"venue"
},
  "geometry": {"coordinates":[-74.33470916749999,45.6570739746],"type":"Point"}
}