{
  "type": "Feature",
  "properties": {
    "addr:full":"Stand Off AB T0L 1Y0",
    "addr:postcode":"t0l 1y0",
    "iso:country":"CA",
    "sg:city":"Stand Off",
    "sg:classifiers":[
        {
            "category":"Government",
            "subcategory":"Office",
            "type":"Public Place"
        }
    ],
    "sg:phone":"+1 403 737 8090",
    "sg:postcode":"T0L 1Y0",
    "sg:province":"AB",
    "wof:name":"Alberta Child Protection",
    "wof:placetype":"venue"
},
  "geometry": {"coordinates":[-113.30506099999999,49.468464],"type":"Point"}
}