{
  "type": "Feature",
  "properties": {
    "addr:full":"Fort Mackay AB T0P 1C0",
    "addr:postcode":"t0p 1c0",
    "addr:street":"Fort",
    "iso:country":"CA",
    "sg:city":"Fort Mackay",
    "sg:classifiers":[
        {
            "category":"Education",
            "subcategory":"School",
            "type":"Public Place"
        }
    ],
    "sg:phone":"+1 780 828 4434",
    "sg:postcode":"T0P 1C0",
    "sg:province":"AB",
    "sg:tags":[
        "educational",
        "program"
    ],
    "wof:name":"Fort Mackay Learning Ctr",
    "wof:placetype":"venue"
},
  "geometry": {"coordinates":[-111.47998,56.996014],"type":"Point"}
}