{
  "type": "Feature",
  "properties": {
    "addr:full":"4180 Villeneuve St Lac-Megantic QC G6B 2C3",
    "addr:housenumber":"4180",
    "addr:postcode":"g6b 2c3",
    "addr:street":"Villeneuve St",
    "iso:country":"CA",
    "sg:address":"4180 Villeneuve St",
    "sg:city":"Lac-Megantic",
    "sg:classifiers":[
        {
            "category":"Home & Garden",
            "subcategory":"Building Materials",
            "type":"Retail Goods"
        }
    ],
    "sg:phone":"+1 819 583 5885",
    "sg:postcode":"G6B 2C3",
    "sg:province":"QC",
    "sg:tags":[
        "door"
    ],
    "wof:name":"Masonite International",
    "wof:placetype":"venue"
},
  "geometry": {"coordinates":[-70.87911224370001,45.5836906433],"type":"Point"}
}