{
  "type": "Feature",
  "properties": {
    "addr:full":"2924 Main St Vancouver BC V5T 3G3",
    "addr:housenumber":"2924",
    "addr:postcode":"v5t 3g3",
    "addr:street":"Main St",
    "iso:country":"CA",
    "sg:address":"2924 Main St",
    "sg:city":"Vancouver",
    "sg:classifiers":[
        {
            "category":"Retail",
            "subcategory":"Repair Shop",
            "type":"Services"
        }
    ],
    "sg:phone":"+1 604 879 4000",
    "sg:postcode":"V5T 3G3",
    "sg:province":"BC",
    "sg:tags":[
        "repairing",
        "piano",
        "refinishing"
    ],
    "wof:name":"Janisch-Williams Piano House",
    "wof:placetype":"venue"
},
  "geometry": {"coordinates":[-123.10083,49.25909],"type":"Point"}
}