{
  "type": "Feature",
  "properties": {
    "addr:full":"5001 50 Ave Wetaskiwin AB T9A 0S3",
    "addr:housenumber":"5001",
    "addr:postcode":"t9a 0s3",
    "addr:street":"50 Ave",
    "iso:country":"CA",
    "sg:address":"5001 50 Ave",
    "sg:city":"Wetaskiwin",
    "sg:classifiers":[
        {
            "category":"Restaurant",
            "type":"Food & Drink"
        }
    ],
    "sg:phone":"+1 780 352 2646",
    "sg:postcode":"T9A 0S3",
    "sg:province":"AB",
    "wof:name":"Centaur Dining Lounge",
    "wof:placetype":"venue"
},
  "geometry": {"coordinates":[-113.37435913100001,52.9695167542],"type":"Point"}
}