{
  "type": "Feature",
  "properties": {
    "addr:full":"233 Fern Cres Waterloo ON N2V 2P9",
    "addr:housenumber":"233",
    "addr:postcode":"n2v 2p9",
    "addr:street":"Fern Cres",
    "iso:country":"CA",
    "sg:address":"233 Fern Cres",
    "sg:city":"Waterloo",
    "sg:classifiers":[
        {
            "category":"Building & Trades",
            "subcategory":"Construction",
            "type":"Services"
        }
    ],
    "sg:phone":"+1 519 747 5883",
    "sg:postcode":"N2V 2P9",
    "sg:province":"ON",
    "sg:tags":[
        "excavating",
        "contractor"
    ],
    "wof:name":"Roncare Construction Landscape",
    "wof:placetype":"venue"
},
  "geometry": {"coordinates":[-80.556274,43.498035],"type":"Point"}
}