{
  "type": "Feature",
  "properties": {
    "addr:full":"306 Saskatchewan Ave W Melfort SK S0E 1A0",
    "addr:housenumber":"306",
    "addr:postcode":"s0e 1a0",
    "addr:street":"Saskatchewan Ave W Melfort",
    "iso:country":"CA",
    "sg:address":"306 Saskatchewan Ave W",
    "sg:city":"Melfort",
    "sg:classifiers":[
        {
            "category":"Retail",
            "subcategory":"Funeral Services",
            "type":"Services"
        }
    ],
    "sg:phone":"+1 306 752 3838",
    "sg:postcode":"S0E 1A0",
    "sg:province":"SK",
    "sg:tags":[
        "director"
    ],
    "wof:name":"Fedusiak Funeral Chapel",
    "wof:placetype":"venue"
},
  "geometry": {"coordinates":[-104.616851807,52.8612251282],"type":"Point"}
}