{
  "type": "Feature",
  "properties": {
    "addr:full":"Toronto ON M4S 1Y2",
    "addr:postcode":"m4s 1y2",
    "iso:country":"CA",
    "sg:city":"Toronto",
    "sg:classifiers":[
        {
            "category":"Health Services",
            "subcategory":"Podiatrist",
            "type":"Services"
        }
    ],
    "sg:phone":"+1 416 482 2336",
    "sg:postcode":"M4S 1Y2",
    "sg:province":"ON",
    "wof:name":"Davisville Foot Clinic",
    "wof:placetype":"venue"
},
  "geometry": {"coordinates":[-79.396141,43.696793],"type":"Point"}
}