{
  "type": "Feature",
  "properties": {
    "addr:full":"4056 Dorchester Rd Niagara Falls ON L2E 6M9",
    "addr:housenumber":"4056",
    "addr:postcode":"l2e 6m9",
    "addr:street":"Dorchester Rd",
    "iso:country":"CA",
    "sg:address":"4056 Dorchester Rd",
    "sg:city":"Niagara Falls",
    "sg:classifiers":[
        {
            "category":"Professional",
            "subcategory":"Engineering",
            "type":"Services"
        }
    ],
    "sg:phone":"+1 905 356 7003",
    "sg:postcode":"L2E 6M9",
    "sg:province":"ON",
    "sg:tags":[
        "engineer"
    ],
    "wof:name":"Delcan Corp",
    "wof:placetype":"venue"
},
  "geometry": {"coordinates":[-79.111557,43.113834],"type":"Point"}
}