{
  "type": "Feature",
  "properties": {
    "addr:full":"115 3rd Ave E Kindersley SK S0L 1S0",
    "addr:housenumber":"115",
    "addr:postcode":"s0l 1s0",
    "addr:street":"3Rd Ave E Kindersley",
    "iso:country":"CA",
    "sg:address":"115 3rd Ave E",
    "sg:city":"Kindersley",
    "sg:classifiers":[
        {
            "category":"Recreation",
            "type":"Entertainment"
        }
    ],
    "sg:phone":"+1 306 463 2743",
    "sg:postcode":"S0L 1S0",
    "sg:province":"SK",
    "sg:tags":[
        "center"
    ],
    "wof:name":"Kindersley Senior Centre",
    "wof:placetype":"venue"
},
  "geometry": {"coordinates":[-109.154602,51.468616],"type":"Point"}
}