{
  "type": "Feature",
  "properties": {
    "addr:full":"1 Karon Dr Torbay NL A1K 1L2",
    "addr:housenumber":"1",
    "addr:postcode":"a1k 1l2",
    "addr:street":"Karon Dr",
    "iso:country":"CA",
    "sg:address":"1 Karon Dr",
    "sg:city":"Torbay",
    "sg:classifiers":[
        {
            "category":"Manufacturing",
            "subcategory":"Signs",
            "type":"Manufacturing & Wholesale Goods"
        }
    ],
    "sg:phone":"+1 709 753 1182",
    "sg:postcode":"A1K 1L2",
    "sg:province":"NL",
    "wof:name":"Advantage Signs & Graphic Dsgn",
    "wof:placetype":"venue"
},
  "geometry": {"coordinates":[-52.7252197266,47.6358909607],"type":"Point"}
}