{
  "type": "Feature",
  "properties": {
    "addr:full":"North York ON M3B 3N7",
    "addr:postcode":"m3b 3n7",
    "iso:country":"CA",
    "sg:city":"North York",
    "sg:classifiers":[
        {
            "category":"Real Estate",
            "subcategory":"Real Estate Agent",
            "type":"Services"
        }
    ],
    "sg:phone":"+1 416 443 9250",
    "sg:postcode":"M3B 3N7",
    "sg:province":"ON",
    "wof:name":"B & B Assoc Realty Ltd",
    "wof:placetype":"venue"
},
  "geometry": {"coordinates":[-79.346245,43.74712],"type":"Point"}
}