{
  "type": "Feature",
  "properties": {
    "addr:full":"Saskatoon SK S7N 1B4",
    "addr:postcode":"s7n 1b4",
    "iso:country":"CA",
    "sg:city":"Saskatoon",
    "sg:classifiers":[
        {
            "category":"Food & Beverages",
            "subcategory":"Specialty",
            "type":"Retail Goods"
        }
    ],
    "sg:phone":"+1 306 664 4455",
    "sg:postcode":"S7N 1B4",
    "sg:province":"SK",
    "sg:tags":[
        "health",
        "diet"
    ],
    "wof:name":"Steep Hill Food CO-OP Ltd",
    "wof:placetype":"venue"
},
  "geometry": {"coordinates":[-106.657089,52.118458],"type":"Point"}
}