{
  "type": "Feature",
  "properties": {
    "addr:full":"Richmond BC V6X 2T1",
    "addr:postcode":"v6x 2t1",
    "iso:country":"CA",
    "sg:city":"Richmond",
    "sg:classifiers":[
        {
            "category":"Manufacturing",
            "subcategory":"Signs",
            "type":"Manufacturing & Wholesale Goods"
        }
    ],
    "sg:phone":"+1 604 278 0392",
    "sg:postcode":"V6X 2T1",
    "sg:province":"BC",
    "wof:name":"Quality Awning & Signs",
    "wof:placetype":"venue"
},
  "geometry": {"coordinates":[-123.091286,49.195438],"type":"Point"}
}