{
  "type": "Feature",
  "properties": {
    "iso:country":"CA",
    "sg:address":"5102 50 St",
    "sg:city":"Olds",
    "sg:classifiers":[
        {
            "category":"Food & Beverages",
            "subcategory":"Liquor & Beverages",
            "type":"Retail Goods"
        }
    ],
    "sg:phone":"+1 403 556 8130",
    "sg:postcode":"T4H 1P6",
    "sg:province":"AB",
    "wof:name":"Bob's Cold Beer & Spirits",
    "wof:placetype":"venue"
},
  "geometry": {"coordinates":[-114.10780334499999,51.7925949097],"type":"Point"}
}