{
  "type": "Feature",
  "properties": {
    "iso:country":"CA",
    "sg:address":"1027 James St",
    "sg:city":"Wallaceburg",
    "sg:classifiers":[
        {
            "category":"Building & Trades",
            "subcategory":"Construction",
            "type":"Services"
        }
    ],
    "sg:phone":"+1 519 627 8743",
    "sg:postcode":"N8A 2P9",
    "sg:province":"ON",
    "sg:tags":[
        "home",
        "improvement"
    ],
    "wof:name":"Workman, Charles",
    "wof:placetype":"venue"
},
  "geometry": {"coordinates":[-82.3901062012,42.5910720825],"type":"Point"}
}