{
  "type": "Feature",
  "properties": {
    "addr:full":"3025 Boul DE Tracy Sorel-Tracy QC J3R 1C2",
    "addr:housenumber":"3025",
    "addr:postcode":"j3r 1c2",
    "addr:street":"Boul De Tracy",
    "iso:country":"CA",
    "sg:address":"3025 Boul DE Tracy",
    "sg:city":"Sorel-Tracy",
    "sg:classifiers":[
        {
            "category":"Professional",
            "subcategory":"Advertising",
            "type":"Services"
        }
    ],
    "sg:phone":"+1 450 742 4711",
    "sg:postcode":"J3R 1C2",
    "sg:province":"QC",
    "sg:tags":[
        "publicity"
    ],
    "wof:name":"Centre DE Ressources & Promo",
    "wof:placetype":"venue"
},
  "geometry": {"coordinates":[-73.1531219482,46.0156745911],"type":"Point"}
}