{
  "type": "Feature",
  "properties": {
    "iso:country":"CA",
    "sg:address":"1100 Boul Maloney O",
    "sg:city":"Gatineau",
    "sg:classifiers":[
        {
            "category":"Shopping",
            "subcategory":"Bicycles & Sporting Goods",
            "type":"Retail Goods"
        }
    ],
    "sg:phone":"+1 819 243 3711",
    "sg:postcode":"J8T 6G3",
    "sg:province":"QC",
    "wof:name":"Sports Experts",
    "wof:placetype":"venue"
},
  "geometry": {"coordinates":[-75.5879745483,45.492099762],"type":"Point"}
}