{
  "type": "Feature",
  "properties": {
    "addr:full":"PO Box 2610 STN Main Winnipeg MB R3C 4B3",
    "addr:housenumber":"po",
    "addr:postcode":"2610;r3c 4b3",
    "addr:street":"Box;Stn",
    "iso:country":"CA",
    "sg:address":"PO Box 2610 STN Main",
    "sg:city":"Winnipeg",
    "sg:classifiers":[
        {
            "category":"Organizations",
            "subcategory":"Professional Association",
            "type":"Services"
        }
    ],
    "sg:phone":"+1 204 947 2067",
    "sg:postcode":"R3C 4B3",
    "sg:province":"MB",
    "wof:name":"Canadian Info Processing Scty",
    "wof:placetype":"venue"
},
  "geometry": {"coordinates":[-97.14073944090001,49.8994255066],"type":"Point"}
}