{
  "type": "Feature",
  "properties": {
    "addr:full":"Calgary AB T2T 0A6",
    "addr:postcode":"t2t 0a6",
    "iso:country":"CA",
    "sg:city":"Calgary",
    "sg:classifiers":[
        {
            "category":"Building & Trades",
            "subcategory":"Construction",
            "type":"Services"
        }
    ],
    "sg:phone":"+1 403 541 1910",
    "sg:postcode":"T2T 0A6",
    "sg:province":"AB",
    "sg:tags":[
        "designer",
        "fashion"
    ],
    "wof:name":"Arcega Design",
    "wof:placetype":"venue"
},
  "geometry": {"coordinates":[-114.084862,51.038006],"type":"Point"}
}