{
  "type": "Feature",
  "properties": {
    "addr:full":"419 Main St E Shelburne ON L0N 1S4",
    "addr:housenumber":"419",
    "addr:postcode":"l0n 1s4",
    "addr:street":"Main St E",
    "iso:country":"CA",
    "sg:address":"419 Main St E",
    "sg:city":"Shelburne",
    "sg:classifiers":[
        {
            "category":"Organizations",
            "subcategory":"Religious Organization",
            "type":"Services"
        }
    ],
    "sg:phone":"+1 519 925 3910",
    "sg:postcode":"L0N 1S4",
    "sg:province":"ON",
    "sg:tags":[
        "church"
    ],
    "wof:name":"Bethel Bible Chapel",
    "wof:placetype":"venue"
},
  "geometry": {"coordinates":[-80.198128,44.079445],"type":"Point"}
}