{
  "type": "Feature",
  "properties": {
    "addr:full":"17 Sullivan Dr St Catharines ON L2N 1K3",
    "addr:housenumber":"17",
    "addr:postcode":"l2n 1k3",
    "addr:street":"Sullivan Dr",
    "iso:country":"CA",
    "sg:address":"17 Sullivan Dr",
    "sg:city":"St Catharines",
    "sg:classifiers":[
        {
            "category":"Building & Trades",
            "subcategory":"Plumbing",
            "type":"Services"
        }
    ],
    "sg:phone":"+1 905 646 2665",
    "sg:postcode":"L2N 1K3",
    "sg:province":"ON",
    "sg:tags":[
        "conditioning",
        "air",
        "system",
        "contractor"
    ],
    "wof:name":"Brian Easton Heating & Ac",
    "wof:placetype":"venue"
},
  "geometry": {"coordinates":[-79.243347,43.184696],"type":"Point"}
}