{
  "type": "Feature",
  "properties": {
    "iso:country":"CA",
    "sg:address":"3845 9 Ave N",
    "sg:city":"Lethbridge",
    "sg:classifiers":[
        {
            "category":"Professional",
            "subcategory":"Management & Consulting",
            "type":"Services"
        }
    ],
    "sg:phone":"+1 403 320 2777",
    "sg:postcode":"T1H 6G8",
    "sg:province":"AB",
    "sg:tags":[
        "agricultural",
        "consultant"
    ],
    "wof:name":"Newwest Feeds & Nutrition Svc",
    "wof:placetype":"venue"
},
  "geometry": {"coordinates":[-112.786407471,49.7128486633],"type":"Point"}
}