{
  "type": "Feature",
  "properties": {
    "addr:full":"9 Main St N St George Brant ON N0E 1N0",
    "addr:housenumber":"9",
    "addr:postcode":"n0e 1n0",
    "addr:street":"Main St N",
    "iso:country":"CA",
    "sg:address":"9 Main St N",
    "sg:city":"St George Brant",
    "sg:classifiers":[
        {
            "category":"Organizations",
            "subcategory":"Professional Association",
            "type":"Services"
        }
    ],
    "sg:phone":"+1 519 448 1462",
    "sg:postcode":"N0E 1N0",
    "sg:province":"ON",
    "sg:tags":[
        "club"
    ],
    "wof:name":"Royal Canadian Legion",
    "wof:placetype":"venue"
},
  "geometry": {"coordinates":[-80.253738,43.245937],"type":"Point"}
}