{
  "type": "Feature",
  "properties": {
    "addr:full":"Surrey BC V4N 4E9",
    "addr:postcode":"v4n 4e9",
    "iso:country":"CA",
    "sg:city":"Surrey",
    "sg:classifiers":[
        {
            "category":"Wholesale",
            "subcategory":"Machinery & Supplies",
            "type":"Manufacturing & Wholesale Goods"
        }
    ],
    "sg:phone":"+1 604 513 2260",
    "sg:postcode":"V4N 4E9",
    "sg:province":"BC",
    "sg:tags":[
        "equipment",
        "material",
        "handling"
    ],
    "wof:name":"Scott Forklift Ltd",
    "wof:placetype":"venue"
},
  "geometry": {"coordinates":[-122.684731,49.172375],"type":"Point"}
}