{
  "type": "Feature",
  "properties": {
    "addr:full":"1375 Leighland Rd Burlington ON L7R 3S6",
    "addr:housenumber":"1375",
    "addr:postcode":"l7r 3s6",
    "addr:street":"Leighland Rd",
    "iso:country":"CA",
    "sg:address":"1375 Leighland Rd",
    "sg:city":"Burlington",
    "sg:classifiers":[
        {
            "category":"Building & Trades",
            "subcategory":"Construction",
            "type":"Services"
        }
    ],
    "sg:phone":"+1 905 632 5700",
    "sg:postcode":"L7R 3S6",
    "sg:province":"ON",
    "sg:tags":[
        "general",
        "contractor"
    ],
    "wof:name":"A R Construction",
    "wof:placetype":"venue"
},
  "geometry": {"coordinates":[-79.82126599999999,43.337341],"type":"Point"}
}