{
  "type": "Feature",
  "properties": {
    "addr:full":"1890 Boul Auclair Sainte-Foy QC G2G 1R7",
    "addr:housenumber":"1890",
    "addr:postcode":"g2g 1r7",
    "addr:street":"Boul Auclair",
    "iso:country":"CA",
    "sg:address":"1890 Boul Auclair",
    "sg:city":"Sainte-Foy",
    "sg:classifiers":[
        {
            "category":"Social Services",
            "subcategory":"Child Care",
            "type":"Services"
        }
    ],
    "sg:phone":"+1 418 871 0066",
    "sg:postcode":"G2G 1R7",
    "sg:province":"QC",
    "wof:name":"Garderie Les Primeveres",
    "wof:placetype":"venue"
},
  "geometry": {"coordinates":[-71.368019104,46.7730102539],"type":"Point"}
}