{
  "type": "Feature",
  "properties": {
    "addr:full":"13753 108 Ave Surrey BC V3T 2K6",
    "addr:housenumber":"13753",
    "addr:postcode":"v3t 2k6",
    "addr:street":"108 Ave",
    "iso:country":"CA",
    "sg:address":"13753 108 Ave",
    "sg:city":"Surrey",
    "sg:classifiers":[
        {
            "category":"Organizations",
            "subcategory":"Religious Organization",
            "type":"Services"
        }
    ],
    "sg:phone":"+1 604 584 4421",
    "sg:postcode":"V3T 2K6",
    "sg:province":"BC",
    "sg:tags":[
        "church"
    ],
    "wof:name":"Ukranian Holy Cross Catholic",
    "wof:placetype":"venue"
},
  "geometry": {"coordinates":[-122.83412199999999,49.198841],"type":"Point"}
}