{
  "type": "Feature",
  "properties": {
    "addr:full":"St-Telesphore QC J0P 1Y0",
    "addr:postcode":"j0p 1y0",
    "iso:country":"CA",
    "sg:city":"St-Telesphore",
    "sg:classifiers":[
        {
            "category":"Shopping",
            "subcategory":"Used Merchandise",
            "type":"Retail Goods"
        }
    ],
    "sg:phone":"+1 450 265 3177",
    "sg:postcode":"J0P 1Y0",
    "sg:province":"QC",
    "sg:tags":[
        "antique"
    ],
    "wof:name":"Encans St-Telesphore",
    "wof:placetype":"venue"
},
  "geometry": {"coordinates":[-74.3707733154,45.3042373657],"type":"Point"}
}