{
  "type": "Feature",
  "properties": {
    "addr:full":"50 Queen St W #300 Brampton ON L6X 4H3",
    "addr:housenumber":"50",
    "addr:postcode":"l6x 4h3",
    "addr:street":"Queen St W # 300",
    "iso:country":"CA",
    "sg:address":"50 Queen St W #300",
    "sg:city":"Brampton",
    "sg:classifiers":[
        {
            "category":"Banks & Credit Unions",
            "subcategory":"Investment Brokerage",
            "type":"Services"
        }
    ],
    "sg:phone":"+1 905 450 1006",
    "sg:postcode":"L6X 4H3",
    "sg:province":"ON",
    "sg:tags":[
        "consultant",
        "planning",
        "financial"
    ],
    "wof:name":"Rbc Dominion Securities Inc",
    "wof:placetype":"venue"
},
  "geometry": {"coordinates":[-79.7610702515,43.6849746704],"type":"Point"}
}