{
  "type": "Feature",
  "properties": {
    "addr:full":"3440 Rue Beausejour Saint-Laurent QC H4K 1W6",
    "addr:housenumber":"3440",
    "addr:postcode":"h4k 1w6",
    "addr:street":"Rue Beausejour",
    "iso:country":"CA",
    "sg:address":"3440 Rue Beausejour",
    "sg:city":"Saint-Laurent",
    "sg:classifiers":[
        {
            "category":"Professional",
            "subcategory":"Business Services",
            "type":"Services"
        }
    ],
    "sg:phone":"+1 514 336 1045",
    "sg:postcode":"H4K 1W6",
    "sg:province":"QC",
    "sg:tags":[
        "translator",
        "interpreter"
    ],
    "wof:name":"Bill Bantey & Assoc",
    "wof:placetype":"venue"
},
  "geometry": {"coordinates":[-73.7291107178,45.5214729309],"type":"Point"}
}