{
  "type": "Feature",
  "properties": {
    "addr:full":"31 Rang Saint-Thomas N L'Anse-Saint-Jean QC G0V 1J0",
    "addr:housenumber":"31",
    "addr:postcode":"g0v 1j0",
    "addr:street":"Rang Saint-Thomas N",
    "iso:country":"CA",
    "sg:address":"31 Rang Saint-Thomas N",
    "sg:city":"L'Anse-Saint-Jean",
    "sg:classifiers":[
        {
            "category":"Government",
            "subcategory":"Office",
            "type":"Public Place"
        }
    ],
    "sg:phone":"+1 418 272 2032",
    "sg:postcode":"G0V 1J0",
    "sg:province":"QC",
    "sg:tags":[
        "village"
    ],
    "wof:name":"Anse St-Jean Garage Municipal",
    "wof:placetype":"venue"
},
  "geometry": {"coordinates":[-70.2487335205,48.1967811584],"type":"Point"}
}