{
  "type": "Feature",
  "properties": {
    "addr:full":"Quesnel BC V2J 2C9",
    "addr:postcode":"v2j 2c9",
    "iso:country":"CA",
    "sg:city":"Quesnel",
    "sg:classifiers":[
        {
            "category":"Shopping",
            "subcategory":"Gifts & Souvenirs",
            "type":"Retail Goods"
        }
    ],
    "sg:phone":"+1 250 992 2959",
    "sg:postcode":"V2J 2C9",
    "sg:province":"BC",
    "sg:tags":[
        "shop"
    ],
    "wof:name":"Mary's Gift Shop",
    "wof:placetype":"venue"
},
  "geometry": {"coordinates":[-122.495559692,52.9789962769],"type":"Point"}
}