{
  "type": "Feature",
  "properties": {
    "iso:country":"CA",
    "sg:city":"Uxbridge",
    "sg:classifiers":[
        {
            "category":"Personal",
            "subcategory":"Barber",
            "type":"Services"
        }
    ],
    "sg:phone":"+1 905 852 9209",
    "sg:postcode":"L9P 1E6",
    "sg:province":"ON",
    "wof:name":"Dixon's Barber Shop",
    "wof:placetype":"venue"
},
  "geometry": {"coordinates":[-79.122681,44.110111],"type":"Point"}
}