{
  "type": "Feature",
  "properties": {
    "addr:full":"26 Ch Hazelwood Gracefield QC J0X 1W0",
    "addr:housenumber":"26",
    "addr:postcode":"j0x 1w0",
    "addr:street":"Ch Hazelwood",
    "iso:country":"CA",
    "sg:address":"26 Ch Hazelwood",
    "sg:city":"Gracefield",
    "sg:classifiers":[
        {
            "category":"Travel",
            "subcategory":"Campground",
            "type":"Entertainment"
        }
    ],
    "sg:phone":"+1 819 463 2091",
    "sg:postcode":"J0X 1W0",
    "sg:province":"QC",
    "sg:tags":[
        "camp",
        "fishing"
    ],
    "wof:name":"Hazelwood Lodge",
    "wof:placetype":"venue"
},
  "geometry": {"coordinates":[-75.883751,46.103039],"type":"Point"}
}