{
  "type": "Feature",
  "properties": {
    "addr:full":"Edmonton AB T5J 2V5",
    "addr:postcode":"t5j 2v5",
    "iso:country":"CA",
    "sg:city":"Edmonton",
    "sg:classifiers":[
        {
            "category":"Arts & Performance",
            "subcategory":"Theater",
            "type":"Entertainment"
        }
    ],
    "sg:phone":"+1 780 425 9212",
    "sg:postcode":"T5J 2V5",
    "sg:province":"AB",
    "wof:name":"Metro Cinema Society",
    "wof:placetype":"venue"
},
  "geometry": {"coordinates":[-113.49064636200001,53.544593811],"type":"Point"}
}