{
  "type": "Feature",
  "properties": {
    "addr:full":"Toronto ON M5H 3B7",
    "addr:postcode":"m5h 3b7",
    "iso:country":"CA",
    "sg:city":"Toronto",
    "sg:classifiers":[
        {
            "category":"Professional",
            "subcategory":"Lawyer & Legal Services",
            "type":"Services"
        }
    ],
    "sg:phone":"+1 416 603 0700",
    "sg:postcode":"M5H 3B7",
    "sg:province":"ON",
    "sg:tags":[
        "attorney"
    ],
    "wof:name":"Sherrard Kuzz Llp",
    "wof:placetype":"venue"
},
  "geometry": {"coordinates":[-79.385086,43.648453],"type":"Point"}
}