{
  "type": "Feature",
  "properties": {
    "addr:full":"980 Rue Yvon Sainte-Beatrix QC J0K 1Y0",
    "addr:housenumber":"980",
    "addr:postcode":"j0k 1y0",
    "addr:street":"Rue Yvon Sainte-Beatrix",
    "iso:country":"CA",
    "sg:address":"980 Rue Yvon",
    "sg:city":"Sainte-Beatrix",
    "sg:classifiers":[
        {
            "category":"Health Services",
            "subcategory":"Nursing And Care Facility",
            "type":"Services"
        }
    ],
    "sg:phone":"+1 450 883 0091",
    "sg:postcode":"J0K 1Y0",
    "sg:province":"QC",
    "sg:tags":[
        "home",
        "retirement",
        "convalescent",
        "community"
    ],
    "wof:name":"Residence Ste-Beatrix",
    "wof:placetype":"venue"
},
  "geometry": {"coordinates":[-73.622162,46.195526],"type":"Point"}
}