{
  "type": "Feature",
  "properties": {
    "iso:country":"CA",
    "sg:address":"199 Boul Cure-Labelle",
    "sg:city":"Sainte-Rose",
    "sg:classifiers":[
        {
            "category":"Autos & Motor Vehicles",
            "subcategory":"Auto Supplies",
            "type":"Retail Goods"
        }
    ],
    "sg:phone":"+1 450 628 3841",
    "sg:postcode":"H7L 2Z9",
    "sg:province":"QC",
    "sg:tags":[
        "wheel",
        "trailer",
        "alignment",
        "hitch"
    ],
    "wof:name":"Alignement & Attaches",
    "wof:placetype":"venue"
},
  "geometry": {"coordinates":[-73.7904891968,45.6040687561],"type":"Point"}
}