{
  "type": "Feature",
  "properties": {
    "addr:full":"507 Hespeler Rd Cambridge ON N1R 6J2",
    "addr:housenumber":"507",
    "addr:postcode":"n1r 6j2",
    "addr:street":"Hespeler Rd",
    "iso:country":"CA",
    "sg:address":"507 Hespeler Rd",
    "sg:city":"Cambridge",
    "sg:classifiers":[
        {
            "category":"Autos & Motor Vehicles",
            "subcategory":"Automobile Sales",
            "type":"Retail Goods"
        }
    ],
    "sg:phone":"+1 519 622 8074",
    "sg:postcode":"N1R 6J2",
    "sg:province":"ON",
    "sg:tags":[
        "car",
        "dealer"
    ],
    "wof:name":"R & R Auto Sales",
    "wof:placetype":"venue"
},
  "geometry": {"coordinates":[-80.3250656128,43.3994750977],"type":"Point"}
}