{
  "type": "Feature",
  "properties": {
    "addr:full":"56 Louis St Brockville ON K6V 4H7",
    "addr:housenumber":"56",
    "addr:postcode":"k6v 4h7",
    "addr:street":"Louis St",
    "iso:country":"CA",
    "sg:address":"56 Louis St",
    "sg:city":"Brockville",
    "sg:classifiers":[
        {
            "category":"Shopping",
            "subcategory":"Crafts & Fabrics",
            "type":"Retail Goods"
        }
    ],
    "sg:phone":"+1 613 342 5343",
    "sg:postcode":"K6V 4H7",
    "sg:province":"ON",
    "sg:tags":[
        "yarn"
    ],
    "wof:name":"Woolly Lamb",
    "wof:placetype":"venue"
},
  "geometry": {"coordinates":[-75.689812,44.594761],"type":"Point"}
}