{
  "type": "Feature",
  "properties": {
    "addr:full":"14 Ellesmere Dr Yellowknife NT X1A 2P6",
    "addr:housenumber":"14",
    "addr:postcode":"x1a 2p6",
    "addr:street":"Ellesmere Dr",
    "iso:country":"CA",
    "sg:address":"14 Ellesmere Dr",
    "sg:city":"Yellowknife",
    "sg:classifiers":[
        {
            "category":"Building & Trades",
            "subcategory":"Construction",
            "type":"Services"
        }
    ],
    "sg:phone":"+1 867 669 0738",
    "sg:postcode":"X1A 2P6",
    "sg:province":"NT",
    "sg:tags":[
        "general",
        "contractor"
    ],
    "wof:name":"Coneco Equipment Inc",
    "wof:placetype":"venue"
},
  "geometry": {"coordinates":[-114.423615,62.431],"type":"Point"}
}