{
  "type": "Feature",
  "properties": {
    "addr:full":"300 Sheppard Ave W North York ON M2N 1N5",
    "addr:housenumber":"300",
    "addr:postcode":"m2n 1n5",
    "addr:street":"Sheppard Ave W",
    "iso:country":"CA",
    "sg:address":"300 Sheppard Ave W",
    "sg:city":"North York",
    "sg:classifiers":[
        {
            "category":"Professional",
            "subcategory":"Accounting & Tax Preparation",
            "type":"Services"
        }
    ],
    "sg:phone":"+1 416 221 6126",
    "sg:postcode":"M2N 1N5",
    "sg:province":"ON",
    "sg:tags":[
        "accountant"
    ],
    "wof:name":"Trubkin, Shep",
    "wof:placetype":"venue"
},
  "geometry": {"coordinates":[-79.4257888794,43.7582321167],"type":"Point"}
}