{
  "type": "Feature",
  "properties": {
    "addr:full":"21097 Campers Cove Wheatley ON N0P 2P0",
    "addr:housenumber":"21097",
    "addr:postcode":"n0p 2p0",
    "addr:street":"Campers Cove",
    "iso:country":"CA",
    "sg:address":"21097 Campers Cove",
    "sg:city":"Wheatley",
    "sg:classifiers":[
        {
            "category":"Travel",
            "subcategory":"Campground",
            "type":"Entertainment"
        }
    ],
    "sg:phone":"+1 519 825 4732",
    "sg:postcode":"N0P 2P0",
    "sg:province":"ON",
    "wof:name":"Campers Cove Family Campground",
    "wof:placetype":"venue"
},
  "geometry": {"coordinates":[-82.4316558838,42.1074981689],"type":"Point"}
}