{
  "type": "Feature",
  "properties": {
    "addr:full":"Calgary AB T2H 0K2",
    "addr:postcode":"t2h 0k2",
    "iso:country":"CA",
    "sg:city":"Calgary",
    "sg:classifiers":[
        {
            "category":"Professional",
            "subcategory":"Lawyer & Legal Services",
            "type":"Services"
        }
    ],
    "sg:phone":"+1 403 258 0800",
    "sg:postcode":"T2H 0K2",
    "sg:province":"AB",
    "sg:tags":[
        "attorney"
    ],
    "wof:name":"Hoornaert, Martin L",
    "wof:placetype":"venue"
},
  "geometry": {"coordinates":[-114.071236,51.000916],"type":"Point"}
}