{
  "type": "Feature",
  "properties": {
    "addr:full":"1014 Oak Ave Sarnia ON N7S 3T7",
    "addr:housenumber":"1014",
    "addr:postcode":"n7s 3t7",
    "addr:street":"Oak Ave",
    "iso:country":"CA",
    "sg:address":"1014 Oak Ave",
    "sg:city":"Sarnia",
    "sg:classifiers":[
        {
            "category":"Social Services",
            "subcategory":"Child Care",
            "type":"Services"
        }
    ],
    "sg:phone":"+1 519 344 9601",
    "sg:postcode":"N7S 3T7",
    "sg:province":"ON",
    "wof:name":"Coronation Park Day Care Ctr",
    "wof:placetype":"venue"
},
  "geometry": {"coordinates":[-82.37326049799999,42.9709739685],"type":"Point"}
}