{
  "type": "Feature",
  "properties": {
    "addr:full":"Winnipeg MB R3T 1N4",
    "addr:postcode":"r3t 1n4",
    "iso:country":"CA",
    "sg:city":"Winnipeg",
    "sg:classifiers":[
        {
            "category":"Professional",
            "subcategory":"Management & Consulting",
            "type":"Services"
        }
    ],
    "sg:phone":"+1 204 474 2880",
    "sg:postcode":"R3T 1N4",
    "sg:province":"MB",
    "sg:tags":[
        "consultant",
        "business"
    ],
    "wof:name":"H N Westdal & Assoc",
    "wof:placetype":"venue"
},
  "geometry": {"coordinates":[-97.15585327150001,49.8400764465],"type":"Point"}
}