{
  "type": "Feature",
  "properties": {
    "iso:country":"CA",
    "sg:address":"6430 Norvan Rd",
    "sg:city":"Sechelt",
    "sg:classifiers":[
        {
            "category":"Health Services",
            "subcategory":"Clinic",
            "type":"Services"
        }
    ],
    "sg:phone":"+1 604 740 0014",
    "sg:postcode":"V0N 3A7",
    "sg:province":"BC",
    "wof:name":"Sunshine Coast Herbal Clinic",
    "wof:placetype":"venue"
},
  "geometry": {"coordinates":[-123.7985,49.474075],"type":"Point"}
}