{
  "type": "Feature",
  "properties": {
    "addr:full":"400 Stephen St # 101 Morden MB R6M 1W3",
    "addr:housenumber":"400",
    "addr:postcode":"r6m 1w3",
    "addr:street":"Stephen St # 101",
    "iso:country":"CA",
    "sg:address":"400 Stephen St # 101",
    "sg:city":"Morden",
    "sg:classifiers":[
        {
            "category":"Social Services",
            "type":"Services"
        }
    ],
    "sg:phone":"+1 204 822 6992",
    "sg:postcode":"R6M 1W3",
    "sg:province":"MB",
    "sg:tags":[
        "organization",
        "welfare"
    ],
    "wof:name":"Morden & District United Way",
    "wof:placetype":"venue"
},
  "geometry": {"coordinates":[-98.10325622560001,49.1897392273],"type":"Point"}
}