{
  "type": "Feature",
  "properties": {
    "addr:full":"156 Av Springgrove Outremont QC H2V 3J2",
    "addr:postcode":"h2v 3j2",
    "addr:street":"156 Av Springgrove",
    "iso:country":"CA",
    "sg:address":"156 Av Springgrove",
    "sg:city":"Outremont",
    "sg:classifiers":[
        {
            "category":"Health Services",
            "subcategory":"Doctor",
            "type":"Services"
        }
    ],
    "sg:phone":"+1 514 277 1831",
    "sg:postcode":"H2V 3J2",
    "sg:province":"QC",
    "sg:tags":[
        "physician",
        "surgeon"
    ],
    "wof:name":"Tache, Charles R MD",
    "wof:placetype":"venue"
},
  "geometry": {"coordinates":[-73.6053771973,45.5139846802],"type":"Point"}
}