{
  "type": "Feature",
  "properties": {
    "addr:full":"Oakville ON L6L 6N3",
    "addr:postcode":"l6l 6n3",
    "iso:country":"CA",
    "sg:city":"Oakville",
    "sg:classifiers":[
        {
            "category":"Wholesale",
            "subcategory":"Machinery & Supplies",
            "type":"Manufacturing & Wholesale Goods"
        }
    ],
    "sg:phone":"+1 905 469 1586",
    "sg:postcode":"L6L 6N3",
    "sg:province":"ON",
    "wof:name":"Fabtec Machine Tool Solutions",
    "wof:placetype":"venue"
},
  "geometry": {"coordinates":[-79.707031,43.433971],"type":"Point"}
}