{
  "type": "Feature",
  "properties": {
    "addr:full":"Etobicoke ON M9R 1H5",
    "addr:postcode":"m9r 1h5",
    "iso:country":"CA",
    "sg:city":"Etobicoke",
    "sg:classifiers":[
        {
            "category":"Food & Beverages",
            "subcategory":"Groceries & Convenience Stores",
            "type":"Retail Goods"
        }
    ],
    "sg:phone":"+1 416 244 9713",
    "sg:postcode":"M9R 1H5",
    "sg:province":"ON",
    "sg:tags":[
        "grocer"
    ],
    "wof:name":"Jas East West Indian & African",
    "wof:placetype":"venue"
},
  "geometry": {"coordinates":[-79.5650405884,43.6836357117],"type":"Point"}
}