{
  "type": "Feature",
  "properties": {
    "addr:full":"152 Cabinet Cres Woodbridge ON L4L 6E5",
    "addr:housenumber":"152",
    "addr:postcode":"l4l 6e5",
    "addr:street":"Cabinet Cres",
    "iso:country":"CA",
    "sg:address":"152 Cabinet Cres",
    "sg:city":"Woodbridge",
    "sg:classifiers":[
        {
            "category":"Building & Trades",
            "subcategory":"Construction",
            "type":"Services"
        }
    ],
    "sg:phone":"+1 905 851 3253",
    "sg:postcode":"L4L 6E5",
    "sg:province":"ON",
    "sg:tags":[
        "painter"
    ],
    "wof:name":"Di Sevo Painting & Decorating",
    "wof:placetype":"venue"
},
  "geometry": {"coordinates":[-79.62359600000001,43.791405],"type":"Point"}
}