{
  "type": "Feature",
  "properties": {
    "addr:full":"RR 3 Tiverton ON N0G 2T0",
    "addr:postcode":"n0g 2t0",
    "addr:street":"Rr 3",
    "iso:country":"CA",
    "sg:address":"RR 3",
    "sg:city":"Tiverton",
    "sg:classifiers":[
        {
            "category":"Wholesale",
            "subcategory":"Chemicals & Plastics",
            "type":"Manufacturing & Wholesale Goods"
        }
    ],
    "sg:phone":"+1 519 368 7723",
    "sg:postcode":"N0G 2T0",
    "sg:province":"ON",
    "sg:tags":[
        "alcohol"
    ],
    "wof:name":"Commercial Alcohols Inc",
    "wof:placetype":"venue"
},
  "geometry": {"coordinates":[-81.5441207886,44.2678909302],"type":"Point"}
}