{
  "type": "Feature",
  "properties": {
    "addr:full":"9790 Rue Meunier Montreal QC H3L 2Y8",
    "addr:housenumber":"9790",
    "addr:postcode":"h3l 2y8",
    "addr:street":"Rue Meunier",
    "iso:country":"CA",
    "sg:address":"9790 Rue Meunier",
    "sg:city":"Montreal",
    "sg:classifiers":[
        {
            "category":"Wholesale",
            "subcategory":"Hardware",
            "type":"Manufacturing & Wholesale Goods"
        }
    ],
    "sg:phone":"+1 514 384 0959",
    "sg:postcode":"H3L 2Y8",
    "sg:province":"QC",
    "sg:tags":[
        "steam",
        "specialty"
    ],
    "wof:name":"Procede A Vapeur Imperial",
    "wof:placetype":"venue"
},
  "geometry": {"coordinates":[-73.6617355347,45.5429878235],"type":"Point"}
}