{
  "type": "Feature",
  "properties": {
    "addr:full":"Cartwright NL A0K 1V0",
    "addr:postcode":"a0k 1v0",
    "iso:country":"CA",
    "sg:city":"Cartwright",
    "sg:classifiers":[
        {
            "category":"Professional",
            "subcategory":"Management & Consulting",
            "type":"Services"
        }
    ],
    "sg:phone":"+1 709 938 7373",
    "sg:postcode":"A0K 1V0",
    "sg:province":"NL",
    "sg:tags":[
        "development",
        "economic",
        "agency"
    ],
    "wof:name":"Eagle River Development Assoc",
    "wof:placetype":"venue"
},
  "geometry": {"coordinates":[-57.017414093,53.7074775696],"type":"Point"}
}