{
  "type": "Feature",
  "properties": {
    "addr:full":"Toronto ON M5H 1B6",
    "addr:postcode":"m5h 1b6",
    "iso:country":"CA",
    "sg:city":"Toronto",
    "sg:classifiers":[
        {
            "category":"Banks & Credit Unions",
            "subcategory":"Investment Brokerage",
            "type":"Services"
        }
    ],
    "sg:phone":"+1 416 214 1413",
    "sg:postcode":"M5H 1B6",
    "sg:province":"ON",
    "sg:tags":[
        "consultant",
        "financing"
    ],
    "wof:name":"Rosmir Group",
    "wof:placetype":"venue"
},
  "geometry": {"coordinates":[-79.3780822754,43.6491851807],"type":"Point"}
}