{
  "type": "Feature",
  "properties": {
    "iso:country":"CA",
    "sg:city":"Kelowna",
    "sg:classifiers":[
        {
            "category":"Professional",
            "subcategory":"Management & Consulting",
            "type":"Services"
        }
    ],
    "sg:phone":"+1 250 717 1821",
    "sg:postcode":"V1Y 3J2",
    "sg:province":"BC",
    "sg:tags":[
        "personnel",
        "consultant"
    ],
    "wof:name":"Cbd Network Inc",
    "wof:placetype":"venue"
},
  "geometry": {"coordinates":[-119.476860046,49.8773574829],"type":"Point"}
}