{
  "type": "Feature",
  "properties": {
    "addr:full":"11 Waverley Pl Spruce Grove AB T7X 1P1",
    "addr:housenumber":"11",
    "addr:postcode":"t7x 1p1",
    "addr:street":"Waverley Pl",
    "iso:country":"CA",
    "sg:address":"11 Waverley Pl",
    "sg:city":"Spruce Grove",
    "sg:classifiers":[
        {
            "category":"Shopping",
            "type":"Retail Goods"
        }
    ],
    "sg:phone":"+1 780 962 8802",
    "sg:postcode":"T7X 1P1",
    "sg:province":"AB",
    "sg:tags":[
        "equipment",
        "telephone",
        "supply"
    ],
    "wof:name":"Grove Telecom",
    "wof:placetype":"venue"
},
  "geometry": {"coordinates":[-113.90593,53.551407],"type":"Point"}
}