{
  "type": "Feature",
  "properties": {
    "addr:full":"Sainte-Foy QC G1N 4N6",
    "addr:postcode":"g1n 4n6",
    "iso:country":"CA",
    "sg:city":"Sainte-Foy",
    "sg:classifiers":[
        {
            "category":"Shopping",
            "subcategory":"Computers & Home Electronics",
            "type":"Retail Goods"
        }
    ],
    "sg:phone":"+1 418 688 2061",
    "sg:postcode":"G1N 4N6",
    "sg:province":"QC",
    "sg:tags":[
        "software"
    ],
    "wof:name":"Innovmetric Logiciels Inc",
    "wof:placetype":"venue"
},
  "geometry": {"coordinates":[-71.2708740234,46.7961273193],"type":"Point"}
}