{
  "type": "Feature",
  "properties": {
    "iso:country":"CA",
    "sg:city":"Edmonton",
    "sg:classifiers":[
        {
            "category":"Manufacturing",
            "subcategory":"Metals",
            "type":"Manufacturing & Wholesale Goods"
        }
    ],
    "sg:phone":"+1 780 469 2800",
    "sg:postcode":"T6E 5L1",
    "sg:province":"AB",
    "sg:tags":[
        "cloth",
        "wire"
    ],
    "wof:name":"Western Group/Canada",
    "wof:placetype":"venue"
},
  "geometry": {"coordinates":[-113.458298,53.485085],"type":"Point"}
}