{
  "type": "Feature",
  "properties": {
    "addr:full":"46 Pinebush Rd Cambridge ON N1R 8K5",
    "addr:housenumber":"46",
    "addr:postcode":"n1r 8k5",
    "addr:street":"Pinebush Rd",
    "iso:country":"CA",
    "sg:address":"46 Pinebush Rd",
    "sg:city":"Cambridge",
    "sg:classifiers":[
        {
            "category":"Shopping",
            "subcategory":"Clothing, Apparel, & Fashions",
            "type":"Retail Goods"
        }
    ],
    "sg:phone":"+1 519 620 0824",
    "sg:postcode":"N1R 8K5",
    "sg:province":"ON",
    "sg:tags":[
        "infant",
        "furniture"
    ],
    "wof:name":"Bonnie Togs",
    "wof:placetype":"venue"
},
  "geometry": {"coordinates":[-80.325294,43.40863],"type":"Point"}
}