{
  "type": "Feature",
  "properties": {
    "addr:full":"Vancouver BC V5V 3C3",
    "addr:postcode":"v5v 3c3",
    "iso:country":"CA",
    "sg:city":"Vancouver",
    "sg:classifiers":[
        {
            "category":"Health Services",
            "subcategory":"Doctor",
            "type":"Services"
        }
    ],
    "sg:phone":"+1 604 875 9555",
    "sg:postcode":"V5V 3C3",
    "sg:province":"BC",
    "sg:tags":[
        "physician",
        "surgeon"
    ],
    "wof:name":"Chow, Raymond MD",
    "wof:placetype":"venue"
},
  "geometry": {"coordinates":[-123.085945129,49.254737854],"type":"Point"}
}