{
  "type": "Feature",
  "properties": {
    "addr:full":"300 2nd Ave NE Watson SK S0K 4V0",
    "addr:housenumber":"300",
    "addr:postcode":"s0k 4v0",
    "addr:street":"2Nd Ave Ne",
    "iso:country":"CA",
    "sg:address":"300 2nd Ave NE",
    "sg:city":"Watson",
    "sg:classifiers":[
        {
            "category":"Education",
            "subcategory":"School",
            "type":"Public Place"
        }
    ],
    "sg:phone":"+1 306 287 3535",
    "sg:postcode":"S0K 4V0",
    "sg:province":"SK",
    "wof:name":"Watson High School",
    "wof:placetype":"venue"
},
  "geometry": {"coordinates":[-104.52634399999999,52.129391],"type":"Point"}
}