{
  "type": "Feature",
  "properties": {
    "addr:full":"713 Garyray Dr North York ON M9L 1R2",
    "addr:housenumber":"713",
    "addr:postcode":"m9l 1r2",
    "addr:street":"Garyray Dr",
    "iso:country":"CA",
    "sg:address":"713 Garyray Dr",
    "sg:city":"North York",
    "sg:classifiers":[
        {
            "category":"Wholesale",
            "subcategory":"Machinery & Supplies",
            "type":"Manufacturing & Wholesale Goods"
        }
    ],
    "sg:phone":"+1 416 746 6332",
    "sg:postcode":"M9L 1R2",
    "sg:province":"ON",
    "sg:tags":[
        "repairing"
    ],
    "wof:name":"Anter Systems",
    "wof:placetype":"venue"
},
  "geometry": {"coordinates":[-79.555015564,43.7656402588],"type":"Point"}
}