{
  "type": "Feature",
  "properties": {
    "iso:country":"CA",
    "sg:address":"14 Saint Matthews Rd",
    "sg:city":"Toronto",
    "sg:classifiers":[
        {
            "category":"Organizations",
            "subcategory":"Professional Association",
            "type":"Services"
        }
    ],
    "sg:phone":"+1 416 466 7121",
    "sg:postcode":"M4M 2B5",
    "sg:province":"ON",
    "sg:tags":[
        "club"
    ],
    "wof:name":"St Matthew's Lawn Bowling",
    "wof:placetype":"venue"
},
  "geometry": {"coordinates":[-79.3550643921,43.6650886536],"type":"Point"}
}