{
  "type": "Feature",
  "properties": {
    "addr:full":"Limoges ON K0A 2M0",
    "addr:postcode":"k0a 2m0",
    "iso:country":"CA",
    "sg:city":"Limoges",
    "sg:classifiers":[
        {
            "category":"Recreation",
            "subcategory":"Amusement Park",
            "type":"Entertainment"
        }
    ],
    "sg:phone":"+1 613 443 0726",
    "sg:postcode":"K0A 2M0",
    "sg:province":"ON",
    "wof:name":"Kiddy Kars",
    "wof:placetype":"venue"
},
  "geometry": {"coordinates":[-75.23114776609999,45.295501709],"type":"Point"}
}