{
  "type": "Feature",
  "properties": {
    "addr:full":"277 1Ere Av Asbestos QC J1T 1Y6",
    "addr:housenumber":"277",
    "addr:postcode":"j1t 1y6",
    "addr:street":"1Ere Av",
    "iso:country":"CA",
    "sg:address":"277 1Ere Av",
    "sg:city":"Asbestos",
    "sg:classifiers":[
        {
            "category":"Banks & Credit Unions",
            "subcategory":"Bank",
            "type":"Services"
        }
    ],
    "sg:phone":"+1 819 879 5471",
    "sg:postcode":"J1T 1Y6",
    "sg:province":"QC",
    "wof:name":"Banque Nationale Du Canada",
    "wof:placetype":"venue"
},
  "geometry": {"coordinates":[-71.93551600000001,45.773716],"type":"Point"}
}