{
  "type": "Feature",
  "properties": {
    "addr:full":"10915 102nd Ave Fairview AB T0H 1L0",
    "addr:housenumber":"10915",
    "addr:postcode":"t0h 1l0",
    "addr:street":"102Nd Ave",
    "iso:country":"CA",
    "sg:address":"10915 102nd Ave",
    "sg:city":"Fairview",
    "sg:classifiers":[
        {
            "category":"Shopping",
            "subcategory":"Catalog Store",
            "type":"Retail Goods"
        }
    ],
    "sg:phone":"+1 780 835 2274",
    "sg:postcode":"T0H 1L0",
    "sg:province":"AB",
    "sg:tags":[
        "mail",
        "order",
        "internet"
    ],
    "wof:name":"Sears Canada Inc",
    "wof:placetype":"venue"
},
  "geometry": {"coordinates":[-118.38218689,56.0664596558],"type":"Point"}
}