{
  "type": "Feature",
  "properties": {
    "iso:country":"CA",
    "sg:address":"765 Rue Gilford",
    "sg:city":"Montreal",
    "sg:classifiers":[
        {
            "category":"Real Estate",
            "subcategory":"Architect",
            "type":"Services"
        }
    ],
    "sg:phone":"+1 514 528 9921",
    "sg:postcode":"H2J 1N8",
    "sg:province":"QC",
    "wof:name":"Deschamps, Marc",
    "wof:placetype":"venue"
},
  "geometry": {"coordinates":[-73.585648,45.527653],"type":"Point"}
}