{
  "type": "Feature",
  "properties": {
    "addr:full":"911 Wellington St Sarnia ON N7T 1J6",
    "addr:housenumber":"911",
    "addr:postcode":"n7t 1j6",
    "addr:street":"Wellington St",
    "iso:country":"CA",
    "sg:address":"911 Wellington St",
    "sg:city":"Sarnia",
    "sg:classifiers":[
        {
            "category":"Social Services",
            "type":"Services"
        }
    ],
    "sg:phone":"+1 519 332 4703",
    "sg:postcode":"N7T 1J6",
    "sg:province":"ON",
    "sg:tags":[
        "organization",
        "welfare"
    ],
    "wof:name":"Ontario March of Dimes",
    "wof:placetype":"venue"
},
  "geometry": {"coordinates":[-82.3764801025,42.9682769775],"type":"Point"}
}