{
  "type": "Feature",
  "properties": {
    "addr:full":"570 Gainsborough Rd London ON N6G 4X2",
    "addr:housenumber":"570",
    "addr:postcode":"n6g 4x2",
    "addr:street":"Gainsborough Rd",
    "iso:country":"CA",
    "sg:address":"570 Gainsborough Rd",
    "sg:city":"London",
    "sg:classifiers":[
        {
            "category":"Social Services",
            "type":"Services"
        }
    ],
    "sg:phone":"+1 519 457 4583",
    "sg:postcode":"N6G 4X2",
    "sg:province":"ON",
    "sg:tags":[
        "senior",
        "citizen"
    ],
    "wof:name":"Trinity Place",
    "wof:placetype":"venue"
},
  "geometry": {"coordinates":[-81.307510376,43.0057182312],"type":"Point"}
}