{
  "type": "Feature",
  "properties": {
    "iso:country":"CA",
    "sg:address":"48 Boul Perron E",
    "sg:city":"Sainte-Anne-Des-Monts",
    "sg:classifiers":[
        {
            "category":"Autos & Motor Vehicles",
            "subcategory":"Automobile Sales",
            "type":"Retail Goods"
        }
    ],
    "sg:phone":"+1 418 763 9119",
    "sg:postcode":"G4V 2Z8",
    "sg:province":"QC",
    "sg:tags":[
        "car",
        "dealer"
    ],
    "wof:name":"Vehicules D'Occasion Cle-Dore",
    "wof:placetype":"venue"
},
  "geometry": {"coordinates":[-66.39957427980001,49.1625480652],"type":"Point"}
}