{
  "type": "Feature",
  "properties": {
    "addr:full":"450 Av Claude Dorval QC H9S 3B3",
    "addr:housenumber":"450",
    "addr:postcode":"h9s 3b3",
    "addr:street":"Av Claude",
    "iso:country":"CA",
    "sg:address":"450 Av Claude",
    "sg:city":"Dorval",
    "sg:classifiers":[
        {
            "category":"Retail",
            "subcategory":"Auto Repair",
            "type":"Services"
        }
    ],
    "sg:phone":"+1 514 636 3360",
    "sg:postcode":"H9S 3B3",
    "sg:province":"QC",
    "sg:tags":[
        "repairing",
        "automobile",
        "wrecker"
    ],
    "wof:name":"Services Routier M & M Towing",
    "wof:placetype":"venue"
},
  "geometry": {"coordinates":[-73.7539138794,45.4470367432],"type":"Point"}
}