{
  "type": "Feature",
  "properties": {
    "addr:full":"2540 Rivers Bend Lane Oakville ON L6L 1V3",
    "addr:housenumber":"2540",
    "addr:postcode":"l6l 1v3",
    "addr:street":"Rivers Bend Lane",
    "iso:country":"CA",
    "sg:address":"2540 Rivers Bend Lane",
    "sg:city":"Oakville",
    "sg:classifiers":[
        {
            "category":"Professional",
            "subcategory":"Management & Consulting",
            "type":"Services"
        }
    ],
    "sg:phone":"+1 905 827 5701",
    "sg:postcode":"L6L 1V3",
    "sg:province":"ON",
    "sg:tags":[
        "consultant",
        "mining"
    ],
    "wof:name":"Mc Kim Comminution Related Ltd",
    "wof:placetype":"venue"
},
  "geometry": {"coordinates":[-79.718964,43.395367],"type":"Point"}
}