{
  "type": "Feature",
  "properties": {
    "addr:full":"Saint-Felicien QC G8K 1P9",
    "addr:postcode":"g8k 1p9",
    "iso:country":"CA",
    "sg:city":"Saint-Felicien",
    "sg:classifiers":[
        {
            "category":"Personal",
            "subcategory":"Barber",
            "type":"Services"
        }
    ],
    "sg:phone":"+1 418 679 9660",
    "sg:postcode":"G8K 1P9",
    "sg:province":"QC",
    "wof:name":"Salon Mychele",
    "wof:placetype":"venue"
},
  "geometry": {"coordinates":[-72.44445037840001,48.6511573792],"type":"Point"}
}