{
  "type": "Feature",
  "properties": {
    "addr:full":"16 Rue Du Belvedere Victoriaville QC G6P 6A4",
    "addr:housenumber":"16",
    "addr:postcode":"g6p 6a4",
    "addr:street":"Rue Du Belvedere",
    "iso:country":"CA",
    "sg:address":"16 Rue Du Belvedere",
    "sg:city":"Victoriaville",
    "sg:classifiers":[
        {
            "category":"Shopping",
            "subcategory":"Jewelry",
            "type":"Retail Goods"
        }
    ],
    "sg:phone":"+1 819 357 2544",
    "sg:postcode":"G6P 6A4",
    "sg:province":"QC",
    "sg:tags":[
        "clocks"
    ],
    "wof:name":"Industries Moments Inc",
    "wof:placetype":"venue"
},
  "geometry": {"coordinates":[-71.939438,46.055065],"type":"Point"}
}