{
  "type": "Feature",
  "properties": {
    "addr:full":"Montreal QC H4P 2N5",
    "addr:postcode":"h4p 2n5",
    "iso:country":"CA",
    "sg:city":"Montreal",
    "sg:classifiers":[
        {
            "category":"Real Estate",
            "subcategory":"Real Estate Agent",
            "type":"Services"
        }
    ],
    "sg:phone":"+1 514 731 4797",
    "sg:postcode":"H4P 2N5",
    "sg:province":"QC",
    "sg:tags":[
        "management"
    ],
    "wof:name":"L G Plaza Inc",
    "wof:placetype":"venue"
},
  "geometry": {"coordinates":[-73.648544,45.498058],"type":"Point"}
}