{
  "type": "Feature",
  "properties": {
    "addr:full":"5530 Calgary Trail NW Edmonton AB T6H 4K1",
    "addr:housenumber":"5530",
    "addr:postcode":"t6h 4k1",
    "addr:street":"Calgary Trail Nw",
    "iso:country":"CA",
    "sg:address":"5530 Calgary Trail NW",
    "sg:city":"Edmonton",
    "sg:classifiers":[
        {
            "category":"Retail",
            "subcategory":"Laundry & Dry Cleaning",
            "type":"Services"
        }
    ],
    "sg:phone":"+1 780 437 2508",
    "sg:postcode":"T6H 4K1",
    "sg:province":"AB",
    "sg:tags":[
        "cleaners",
        "tailor"
    ],
    "wof:name":"Carol's Tailoring & Altrtns",
    "wof:placetype":"venue"
},
  "geometry": {"coordinates":[-113.497047424,53.4925537109],"type":"Point"}
}