{
  "type": "Feature",
  "properties": {
    "addr:full":"10714 Alaska Rd Fort St John BC V1J 1B3",
    "addr:housenumber":"10714",
    "addr:postcode":"v1j 1b3",
    "addr:street":"Alaska Rd",
    "iso:country":"CA",
    "sg:address":"10714 Alaska Rd",
    "sg:city":"Fort St John",
    "sg:classifiers":[
        {
            "category":"Building & Trades",
            "subcategory":"Equipment Rental",
            "type":"Services"
        }
    ],
    "sg:phone":"+1 250 785 8700",
    "sg:postcode":"V1J 1B3",
    "sg:province":"BC",
    "sg:tags":[
        "yard",
        "contractor"
    ],
    "wof:name":"Rental Store",
    "wof:placetype":"venue"
},
  "geometry": {"coordinates":[-120.858002,56.241337],"type":"Point"}
}