{
  "type": "Feature",
  "properties": {
    "addr:full":"1035 Eglinton Ave E Mississauga ON L4W 1K4",
    "addr:housenumber":"1035",
    "addr:postcode":"l4w 1k4",
    "addr:street":"Eglinton Ave E",
    "iso:country":"CA",
    "sg:address":"1035 Eglinton Ave E",
    "sg:city":"Mississauga",
    "sg:classifiers":[
        {
            "category":"Restaurant",
            "type":"Food & Drink"
        }
    ],
    "sg:phone":"+1 905 624 1995",
    "sg:postcode":"L4W 1K4",
    "sg:province":"ON",
    "wof:name":"Peter's on Eglinton Rstrnt",
    "wof:placetype":"venue"
},
  "geometry": {"coordinates":[-79.6292190552,43.6282615662],"type":"Point"}
}