{
  "type": "Feature",
  "properties": {
    "addr:full":"53 Woodstream Blvd # 4 Woodbridge ON L4L 7Y8",
    "addr:housenumber":"53",
    "addr:postcode":"l4l 7y8",
    "addr:street":"Woodstream Blvd # 4",
    "iso:country":"CA",
    "sg:address":"53 Woodstream Blvd # 4",
    "sg:city":"Woodbridge",
    "sg:classifiers":[
        {
            "category":"Retail",
            "subcategory":"Repair Shop",
            "type":"Services"
        }
    ],
    "sg:phone":"+1 905 856 5545",
    "sg:postcode":"L4L 7Y8",
    "sg:province":"ON",
    "sg:tags":[
        "upholsterer"
    ],
    "wof:name":"A & G Furniture & Upholstering",
    "wof:placetype":"venue"
},
  "geometry": {"coordinates":[-79.604477,43.775436],"type":"Point"}
}