{
  "type": "Feature",
  "properties": {
    "addr:full":"7135 W Saanich Rd #101 Brentwood Bay BC V8M 1P7",
    "addr:housenumber":"7135",
    "addr:postcode":"v8m 1p7",
    "addr:street":"W Saanich Rd # 101",
    "iso:country":"CA",
    "sg:address":"7135 W Saanich Rd #101",
    "sg:city":"Brentwood Bay",
    "sg:classifiers":[
        {
            "category":"Personal",
            "subcategory":"Beauty Salon",
            "type":"Services"
        }
    ],
    "sg:phone":"+1 250 544 1197",
    "sg:postcode":"V8M 1P7",
    "sg:province":"BC",
    "wof:name":"Hair Flair",
    "wof:placetype":"venue"
},
  "geometry": {"coordinates":[-123.446601868,48.5762863159],"type":"Point"}
}