{
  "type": "Feature",
  "properties": {
    "addr:full":"85 Rue Bellehumeur # 302 Gatineau QC J8T 8B7",
    "addr:housenumber":"85",
    "addr:postcode":"j8t 8b7",
    "addr:street":"Rue Bellehumeur # 302",
    "iso:country":"CA",
    "sg:address":"85 Rue Bellehumeur # 302",
    "sg:city":"Gatineau",
    "sg:classifiers":[
        {
            "category":"Health Services",
            "subcategory":"Doctor",
            "type":"Services"
        }
    ],
    "sg:phone":"+1 819 243 7767",
    "sg:postcode":"J8T 8B7",
    "sg:province":"QC",
    "sg:tags":[
        "dentist"
    ],
    "wof:name":"St Pierre, Maurice DDS",
    "wof:placetype":"venue"
},
  "geometry": {"coordinates":[-75.69227600000001,45.475552],"type":"Point"}
}