{
  "type": "Feature",
  "properties": {
    "addr:full":"1025 67th Ave W Vancouver BC V6P 2S8",
    "addr:housenumber":"1025",
    "addr:postcode":"v6p 2s8",
    "addr:street":"67Th Ave W",
    "iso:country":"CA",
    "sg:address":"1025 67th Ave W",
    "sg:city":"Vancouver",
    "sg:classifiers":[
        {
            "category":"Restaurant",
            "type":"Food & Drink"
        }
    ],
    "sg:phone":"+1 604 261 8105",
    "sg:postcode":"V6P 2S8",
    "sg:province":"BC",
    "sg:tags":[
        "delicatessen"
    ],
    "wof:name":"International Deli Style",
    "wof:placetype":"venue"
},
  "geometry": {"coordinates":[-123.130554199,49.2109069824],"type":"Point"}
}