{
  "type": "Feature",
  "properties": {
    "addr:full":"43 Hilltop Dr Cambridge ON N1R 1T2",
    "addr:housenumber":"43",
    "addr:postcode":"n1r 1t2",
    "addr:street":"Hilltop Dr",
    "iso:country":"CA",
    "sg:address":"43 Hilltop Dr",
    "sg:city":"Cambridge",
    "sg:classifiers":[
        {
            "category":"Professional",
            "subcategory":"Business Services",
            "type":"Services"
        }
    ],
    "sg:phone":"+1 519 621 2524",
    "sg:postcode":"N1R 1T2",
    "sg:province":"ON",
    "sg:tags":[
        "translator",
        "interpreter"
    ],
    "wof:name":"Thies Technical Translations",
    "wof:placetype":"venue"
},
  "geometry": {"coordinates":[-80.295219,43.363628],"type":"Point"}
}