{
  "type": "Feature",
  "properties": {
    "addr:full":"860 8th Concession Rd Claremont ON L1Y 1A2",
    "addr:housenumber":"860",
    "addr:postcode":"l1y 1a2",
    "addr:street":"8Th Concession Rd",
    "iso:country":"CA",
    "sg:address":"860 8th Concession Rd",
    "sg:city":"Claremont",
    "sg:classifiers":[
        {
            "category":"Organizations",
            "subcategory":"Religious Organization",
            "type":"Services"
        }
    ],
    "sg:phone":"+1 905 649 2812",
    "sg:postcode":"L1Y 1A2",
    "sg:province":"ON",
    "sg:tags":[
        "church"
    ],
    "wof:name":"Stouffville Christian Flwshp",
    "wof:placetype":"venue"
},
  "geometry": {"coordinates":[-79.132919,43.953251],"type":"Point"}
}