{
  "type": "Feature",
  "properties": {
    "iso:country":"CA",
    "sg:city":"Fort Mcmurray",
    "sg:classifiers":[
        {
            "category":"Travel",
            "subcategory":"Campground",
            "type":"Entertainment"
        }
    ],
    "sg:phone":"+1 780 743 3176",
    "sg:postcode":"T9H 3G5",
    "sg:province":"AB",
    "sg:tags":[
        "camp",
        "fishing"
    ],
    "wof:name":"Gypsy Lake Lodge Ltd",
    "wof:placetype":"venue"
},
  "geometry": {"coordinates":[-111.380302,56.727188],"type":"Point"}
}