{
  "type": "Feature",
  "properties": {
    "iso:country":"CA",
    "sg:address":"2205 Rue Parthenais",
    "sg:city":"Montreal",
    "sg:classifiers":[
        {
            "category":"Manufacturing",
            "subcategory":"Printing",
            "type":"Manufacturing & Wholesale Goods"
        }
    ],
    "sg:phone":"+1 514 525 4442",
    "sg:postcode":"H2K 3T3",
    "sg:province":"QC",
    "sg:tags":[
        "publisher"
    ],
    "wof:name":"Agence Du Livre",
    "wof:placetype":"venue"
},
  "geometry": {"coordinates":[-73.55885314939999,45.5309143066],"type":"Point"}
}