{
  "type": "Feature",
  "properties": {
    "addr:full":"5589 Av Du Parc Montreal QC H2V 4H2",
    "addr:housenumber":"5589",
    "addr:postcode":"h2v 4h2",
    "addr:street":"Av Du Parc",
    "iso:country":"CA",
    "sg:address":"5589 Av Du Parc",
    "sg:city":"Montreal",
    "sg:classifiers":[
        {
            "category":"Manufacturing",
            "subcategory":"Jewelry",
            "type":"Manufacturing & Wholesale Goods"
        }
    ],
    "sg:phone":"+1 514 948 2276",
    "sg:postcode":"H2V 4H2",
    "sg:province":"QC",
    "wof:name":"Heto",
    "wof:placetype":"venue"
},
  "geometry": {"coordinates":[-73.60321807859999,45.5228157043],"type":"Point"}
}