{
  "type": "Feature",
  "properties": {
    "addr:full":"104 Government Rd N Stoughton SK S0G 4T0",
    "addr:housenumber":"104",
    "addr:postcode":"s0g 4t0",
    "addr:street":"Government Rd N",
    "iso:country":"CA",
    "sg:address":"104 Government Rd N",
    "sg:city":"Stoughton",
    "sg:classifiers":[
        {
            "category":"Retail",
            "subcategory":"Veterinary Services",
            "type":"Services"
        }
    ],
    "sg:phone":"+1 306 457 3133",
    "sg:postcode":"S0G 4T0",
    "sg:province":"SK",
    "sg:tags":[
        "veterinarian"
    ],
    "wof:name":"Stoughton Veterinary Clinic",
    "wof:placetype":"venue"
},
  "geometry": {"coordinates":[-103.02253,49.67664],"type":"Point"}
}