{
  "type": "Feature",
  "properties": {
    "addr:full":"527 Rue Du Sud Cowansville QC J2K 2X9",
    "addr:housenumber":"527",
    "addr:postcode":"j2k 2x9",
    "addr:street":"Rue Du Sud",
    "iso:country":"CA",
    "sg:address":"527 Rue Du Sud",
    "sg:city":"Cowansville",
    "sg:classifiers":[
        {
            "category":"Home & Garden",
            "subcategory":"Household Appliances",
            "type":"Retail Goods"
        }
    ],
    "sg:phone":"+1 450 263 5607",
    "sg:postcode":"J2K 2X9",
    "sg:province":"QC",
    "sg:tags":[
        "machine",
        "sewing"
    ],
    "wof:name":"Singer Concessionnaires",
    "wof:placetype":"venue"
},
  "geometry": {"coordinates":[-72.7468032837,45.2034721375],"type":"Point"}
}