{
  "type": "Feature",
  "properties": {
    "addr:full":"Regina SK S4P 4K8",
    "addr:postcode":"s4p 4k8",
    "iso:country":"CA",
    "sg:city":"Regina",
    "sg:classifiers":[
        {
            "category":"Wholesale",
            "subcategory":"Meat",
            "type":"Manufacturing & Wholesale Goods"
        }
    ],
    "sg:phone":"+1 306 569 4506",
    "sg:postcode":"S4P 4K8",
    "sg:province":"SK",
    "sg:tags":[
        "pork",
        "product"
    ],
    "wof:name":"Heartland Pork Mgmt Svc Inc",
    "wof:placetype":"venue"
},
  "geometry": {"coordinates":[-104.61832428,50.4486656189],"type":"Point"}
}