{
  "type": "Feature",
  "properties": {
    "iso:country":"CA",
    "sg:address":"28 Lee Crt",
    "sg:city":"Cambridge",
    "sg:classifiers":[
        {
            "category":"Shopping",
            "subcategory":"Clothing, Apparel, & Fashions",
            "type":"Retail Goods"
        }
    ],
    "sg:phone":"+1 519 624 9518",
    "sg:postcode":"N1T 1K1",
    "sg:province":"ON",
    "sg:tags":[
        "dancing",
        "sportswear",
        "supply"
    ],
    "wof:name":"Kreations Actionwear",
    "wof:placetype":"venue"
},
  "geometry": {"coordinates":[-80.29494476319999,43.3785858154],"type":"Point"}
}