{
  "type": "Feature",
  "properties": {
    "iso:country":"CA",
    "sg:address":"3530 Derry Rd E #212",
    "sg:city":"Mississauga",
    "sg:classifiers":[
        {
            "category":"Health Services",
            "subcategory":"Doctor",
            "type":"Services"
        }
    ],
    "sg:phone":"+1 905 673 6037",
    "sg:postcode":"L4T 4E3",
    "sg:province":"ON",
    "sg:tags":[
        "physician",
        "surgeon"
    ],
    "wof:name":"Ahluwalia, M S MD",
    "wof:placetype":"venue"
},
  "geometry": {"coordinates":[-79.6305389404,43.7142829895],"type":"Point"}
}