{
  "type": "Feature",
  "properties": {
    "iso:country":"CA",
    "sg:address":"250 Rue Principale",
    "sg:city":"Saint-Damase",
    "sg:classifiers":[
        {
            "category":"Autos & Motor Vehicles",
            "subcategory":"Motorcycle Sales",
            "type":"Retail Goods"
        }
    ],
    "sg:phone":"+1 450 797 2281",
    "sg:postcode":"J0H 1J0",
    "sg:province":"QC",
    "sg:tags":[
        "snowmobile"
    ],
    "wof:name":"Y Leroux Sports Inc",
    "wof:placetype":"venue"
},
  "geometry": {"coordinates":[-73.0129394531,45.5238800049],"type":"Point"}
}