{
  "type": "Feature",
  "properties": {
    "addr:full":"2 Orchard Heights Blvd # 13 Aurora ON L4G 3W3",
    "addr:housenumber":"2",
    "addr:postcode":"l4g 3w3",
    "addr:street":"Orchard Heights Blvd # 13",
    "iso:country":"CA",
    "sg:address":"2 Orchard Heights Blvd # 13",
    "sg:city":"Aurora",
    "sg:classifiers":[
        {
            "category":"Restaurant",
            "type":"Food & Drink"
        }
    ],
    "sg:phone":"+1 905 727 0155",
    "sg:postcode":"L4G 3W3",
    "sg:province":"ON",
    "wof:name":"Shoeless Joe's",
    "wof:placetype":"venue"
},
  "geometry": {"coordinates":[-79.4702835083,44.0090026855],"type":"Point"}
}