{
  "type": "Feature",
  "properties": {
    "addr:full":"2956 Granville St Vancouver BC V6H 3J7",
    "addr:housenumber":"2956",
    "addr:postcode":"v6h 3j7",
    "addr:street":"Granville St",
    "iso:country":"CA",
    "sg:address":"2956 Granville St",
    "sg:city":"Vancouver",
    "sg:classifiers":[
        {
            "category":"Shopping",
            "subcategory":"Clothing, Apparel, & Fashions",
            "type":"Retail Goods"
        }
    ],
    "sg:phone":"+1 604 731 8343",
    "sg:postcode":"V6H 3J7",
    "sg:province":"BC",
    "wof:name":"Cache",
    "wof:placetype":"venue"
},
  "geometry": {"coordinates":[-123.13851928699999,49.259349823],"type":"Point"}
}