{
  "type": "Feature",
  "properties": {
    "addr:full":"Hagersville ON N0A 1H0",
    "addr:postcode":"n0a 1h0",
    "iso:country":"CA",
    "sg:city":"Hagersville",
    "sg:classifiers":[
        {
            "category":"Health Services",
            "subcategory":"Chiropractor",
            "type":"Services"
        }
    ],
    "sg:phone":"+1 905 768 5199",
    "sg:postcode":"N0A 1H0",
    "sg:province":"ON",
    "sg:tags":[
        "therapist",
        "massage"
    ],
    "wof:name":"West Haldimand Chiropractic",
    "wof:placetype":"venue"
},
  "geometry": {"coordinates":[-80.04537999999999,42.957745],"type":"Point"}
}