{
  "type": "Feature",
  "properties": {
    "addr:full":"356 Sumach St Toronto ON M4X 1V4",
    "addr:housenumber":"356",
    "addr:postcode":"m4x 1v4",
    "addr:street":"Sumach St",
    "iso:country":"CA",
    "sg:address":"356 Sumach St",
    "sg:city":"Toronto",
    "sg:classifiers":[
        {
            "category":"Manufacturing",
            "subcategory":"Printing",
            "type":"Manufacturing & Wholesale Goods"
        }
    ],
    "sg:phone":"+1 416 963 5599",
    "sg:postcode":"M4X 1V4",
    "sg:province":"ON",
    "sg:tags":[
        "publisher"
    ],
    "wof:name":"Swimnews Magazine",
    "wof:placetype":"venue"
},
  "geometry": {"coordinates":[-79.36274719239999,43.6658058167],"type":"Point"}
}