{
  "type": "Feature",
  "properties": {
    "iso:country":"CA",
    "sg:address":"154 Cumberland St",
    "sg:city":"Toronto",
    "sg:classifiers":[
        {
            "category":"Restaurant",
            "type":"Food & Drink"
        }
    ],
    "sg:phone":"+1 416 964 8665",
    "sg:postcode":"M5R 1A8",
    "sg:province":"ON",
    "wof:name":"Shogun Japanese Restaurant",
    "wof:placetype":"venue"
},
  "geometry": {"coordinates":[-79.39292144780001,43.6700553894],"type":"Point"}
}