{
  "type": "Feature",
  "properties": {
    "iso:country":"CA",
    "sg:address":"249 Main New Denmark Rd",
    "sg:city":"New Denmark",
    "sg:classifiers":[
        {
            "category":"Organizations",
            "subcategory":"Religious Organization",
            "type":"Services"
        }
    ],
    "sg:phone":"+1 506 553 6712",
    "sg:postcode":"E7G 2B8",
    "sg:province":"NB",
    "sg:tags":[
        "church"
    ],
    "wof:name":"Bethany Ev Lutheran Church",
    "wof:placetype":"venue"
},
  "geometry": {"coordinates":[-67.56772613530001,46.9820556641],"type":"Point"}
}