{
  "type": "Feature",
  "properties": {
    "addr:full":"Halifax NS B3J 2G7",
    "addr:postcode":"ns b3j 2g7",
    "iso:country":"CA",
    "sg:city":"Halifax",
    "sg:classifiers":[
        {
            "category":"Social Services",
            "type":"Services"
        }
    ],
    "sg:phone":"+1 902 422 8143",
    "sg:postcode":"B3J 2G7",
    "sg:province":"NS",
    "sg:tags":[
        "psychologist",
        "counselor",
        "marriage",
        "family"
    ],
    "wof:name":"Stress Management Wellness Ctr",
    "wof:placetype":"venue"
},
  "geometry": {"coordinates":[-63.578449,44.649605],"type":"Point"}
}