{
  "type": "Feature",
  "properties": {
    "addr:full":"1263 Boul Des Laurentides Vimont QC H7M 2Y2",
    "addr:housenumber":"1263",
    "addr:postcode":"h7m 2y2",
    "addr:street":"Boul Des Laurentides",
    "iso:country":"CA",
    "sg:address":"1263 Boul Des Laurentides",
    "sg:city":"Vimont",
    "sg:classifiers":[
        {
            "category":"Manufacturing",
            "subcategory":"Printing",
            "type":"Manufacturing & Wholesale Goods"
        }
    ],
    "sg:phone":"+1 450 662 0153",
    "sg:postcode":"H7M 2Y2",
    "sg:province":"QC",
    "sg:tags":[
        "printer"
    ],
    "wof:name":"Imprimerie Pierre Alix Inc",
    "wof:placetype":"venue"
},
  "geometry": {"coordinates":[-73.708664,45.585075],"type":"Point"}
}