{
  "type": "Feature",
  "properties": {
    "addr:full":"13708 74 St NW Edmonton AB T5C 3R1",
    "addr:housenumber":"13708",
    "addr:postcode":"t5c 3r1",
    "addr:street":"74 St Nw",
    "iso:country":"CA",
    "sg:address":"13708 74 St NW",
    "sg:city":"Edmonton",
    "sg:classifiers":[
        {
            "category":"Organizations",
            "subcategory":"Religious Organization",
            "type":"Services"
        }
    ],
    "sg:phone":"+1 780 475 8496",
    "sg:postcode":"T5C 3R1",
    "sg:province":"AB",
    "sg:tags":[
        "church"
    ],
    "wof:name":"Mc Clure United Church-Canada",
    "wof:placetype":"venue"
},
  "geometry": {"coordinates":[-113.455612183,53.6000518799],"type":"Point"}
}