{
  "type": "Feature",
  "properties": {
    "addr:full":"5845 Yonge St North York ON M2M 3T9",
    "addr:housenumber":"5845",
    "addr:postcode":"m2m 3t9",
    "addr:street":"Yonge St",
    "iso:country":"CA",
    "sg:address":"5845 Yonge St",
    "sg:city":"North York",
    "sg:classifiers":[
        {
            "category":"Shopping",
            "subcategory":"Pharmacy",
            "type":"Retail Goods"
        }
    ],
    "sg:phone":"+1 416 221 5505",
    "sg:postcode":"M2M 3T9",
    "sg:province":"ON",
    "wof:name":"Shoppers Drug Mart",
    "wof:placetype":"venue"
},
  "geometry": {"coordinates":[-79.416687,43.785206],"type":"Point"}
}