{
  "type": "Feature",
  "properties": {
    "addr:full":"103 Rue Boyer Saint-Isidore-DE-Laprairie QC J0L 2A0",
    "addr:housenumber":"103",
    "addr:postcode":"j0l 2a0",
    "addr:street":"Rue Boyer Saint-Isidore-De-Laprairie",
    "iso:country":"CA",
    "sg:address":"103 Rue Boyer",
    "sg:city":"Saint-Isidore-DE-Laprairie",
    "sg:classifiers":[
        {
            "category":"Shopping",
            "type":"Retail Goods"
        }
    ],
    "sg:phone":"+1 450 454 3285",
    "sg:postcode":"J0L 2A0",
    "sg:province":"QC",
    "sg:tags":[
        "miscellaneous",
        "store"
    ],
    "wof:name":"Cabano Boyer Inc",
    "wof:placetype":"venue"
},
  "geometry": {"coordinates":[-73.48807499999999,45.417454],"type":"Point"}
}