{
  "type": "Feature",
  "properties": {
    "iso:country":"CA",
    "sg:address":"103 Rue Boyer",
    "sg:city":"Saint-Isidore-DE-Laprairie",
    "sg:classifiers":[
        {
            "category":"Shopping",
            "type":"Retail Goods"
        }
    ],
    "sg:phone":"+1 450 454 3285",
    "sg:postcode":"J0L 2A0",
    "sg:province":"QC",
    "sg:tags":[
        "miscellaneous",
        "store"
    ],
    "wof:name":"Cabano Boyer Inc",
    "wof:placetype":"venue"
},
  "geometry": {"coordinates":[-73.488075,45.417454],"type":"Point"}
}