{
  "type": "Feature",
  "properties": {
    "addr:full":"189 Elm St St Thomas ON N5R 5C4",
    "addr:housenumber":"189",
    "addr:postcode":"n5r 5c4",
    "addr:street":"Elm St",
    "iso:country":"CA",
    "sg:address":"189 Elm St",
    "sg:city":"St Thomas",
    "sg:classifiers":[
        {
            "category":"Health Services",
            "subcategory":"Doctor",
            "type":"Services"
        }
    ],
    "sg:phone":"+1 519 631 6337",
    "sg:postcode":"N5R 5C4",
    "sg:province":"ON",
    "sg:tags":[
        "clinic"
    ],
    "wof:name":"Ontario Breast Screening Prgrm",
    "wof:placetype":"venue"
},
  "geometry": {"coordinates":[-81.18147999999999,42.76413],"type":"Point"}
}