{
  "type": "Feature",
  "properties": {
    "addr:full":"834 Granville St Vancouver BC V6Z 1K3",
    "addr:housenumber":"834",
    "addr:postcode":"v6z 1k3",
    "addr:street":"Granville St",
    "iso:country":"CA",
    "sg:address":"834 Granville St",
    "sg:city":"Vancouver",
    "sg:classifiers":[
        {
            "category":"Personal",
            "subcategory":"Piercing",
            "type":"Services"
        }
    ],
    "sg:phone":"+1 604 681 7700",
    "sg:postcode":"V6Z 1K3",
    "sg:province":"BC",
    "sg:tags":[
        "body"
    ],
    "wof:name":"Anatomic Adornments",
    "wof:placetype":"venue"
},
  "geometry": {"coordinates":[-123.120475769,49.28074646],"type":"Point"}
}