{
  "type": "Feature",
  "properties": {
    "addr:full":"1st St N Lomond AB T0L 1G0",
    "addr:postcode":"t0l 1g0",
    "addr:street":"1St St N Lomond",
    "iso:country":"CA",
    "sg:address":"1st St N",
    "sg:city":"Lomond",
    "sg:classifiers":[
        {
            "category":"Travel",
            "subcategory":"Hotels & Motels",
            "type":"Entertainment"
        }
    ],
    "sg:phone":"+1 403 792 3606",
    "sg:postcode":"T0L 1G0",
    "sg:province":"AB",
    "wof:name":"Commercial Hotel",
    "wof:placetype":"venue"
},
  "geometry": {"coordinates":[-112.643920898,50.3511238098],"type":"Point"}
}