{
  "type": "Feature",
  "properties": {
    "iso:country":"CA",
    "sg:address":"801 Bank St",
    "sg:city":"Ottawa",
    "sg:classifiers":[
        {
            "category":"Wholesale",
            "subcategory":"Durable Goods & Equipment",
            "type":"Manufacturing & Wholesale Goods"
        }
    ],
    "sg:phone":"+1 613 565 6414",
    "sg:postcode":"K1S 3V7",
    "sg:province":"ON",
    "sg:tags":[
        "importer"
    ],
    "wof:name":"Agora in the Glebe Inc",
    "wof:placetype":"venue"
},
  "geometry": {"coordinates":[-75.688034,45.402836],"type":"Point"}
}