{
  "type": "Feature",
  "properties": {
    "addr:full":"Barrhead AB T7N 1A5",
    "addr:postcode":"t7n 1a5",
    "iso:country":"CA",
    "sg:city":"Barrhead",
    "sg:classifiers":[
        {
            "category":"Retail",
            "subcategory":"Auto Repair",
            "type":"Services"
        }
    ],
    "sg:phone":"+1 780 674 6151",
    "sg:postcode":"T7N 1A5",
    "sg:province":"AB",
    "sg:tags":[
        "repairing",
        "automobile",
        "tire"
    ],
    "wof:name":"Fountain Tire",
    "wof:placetype":"venue"
},
  "geometry": {"coordinates":[-114.40150451700001,54.1277732849],"type":"Point"}
}