{
  "type": "Feature",
  "properties": {
    "addr:full":"27 Lindsay St S Lindsay ON K9V 2L9",
    "addr:housenumber":"27",
    "addr:postcode":"k9v 2l9",
    "addr:street":"Lindsay St S",
    "iso:country":"CA",
    "sg:address":"27 Lindsay St S",
    "sg:city":"Lindsay",
    "sg:classifiers":[
        {
            "category":"Retail",
            "subcategory":"Auto Repair",
            "type":"Services"
        }
    ],
    "sg:phone":"+1 705 324 8472",
    "sg:postcode":"K9V 2L9",
    "sg:province":"ON",
    "sg:tags":[
        "automobile",
        "rustproofing",
        "undercoating"
    ],
    "wof:name":"Krown Rust Control Ctr",
    "wof:placetype":"venue"
},
  "geometry": {"coordinates":[-78.73426055909999,44.3540267944],"type":"Point"}
}