{
  "type": "Feature",
  "properties": {
    "iso:country":"CA",
    "sg:address":"255 Rue Racine E # 440",
    "sg:city":"Chicoutimi",
    "sg:classifiers":[
        {
            "category":"Insurance",
            "subcategory":"Insurance Agent",
            "type":"Services"
        }
    ],
    "sg:phone":"+1 418 545 3130",
    "sg:postcode":"G7H 7L2",
    "sg:province":"QC",
    "wof:name":"Bmo Nesbitt Burns",
    "wof:placetype":"venue"
},
  "geometry": {"coordinates":[-71.061111,48.427769],"type":"Point"}
}