{
  "type": "Feature",
  "properties": {
    "iso:country":"CA",
    "sg:city":"Milton",
    "sg:classifiers":[
        {
            "category":"Health Services",
            "subcategory":"Doctor",
            "type":"Services"
        }
    ],
    "sg:phone":"+1 905 878 0539",
    "sg:postcode":"L9T 2Y6",
    "sg:province":"ON",
    "sg:tags":[
        "physician",
        "surgeon"
    ],
    "wof:name":"Maley, Garnet J M MD",
    "wof:placetype":"venue"
},
  "geometry": {"coordinates":[-79.88650512700001,43.5102272034],"type":"Point"}
}