{
  "type": "Feature",
  "properties": {
    "addr:full":"Winnipeg MB R3J 0P4",
    "addr:postcode":"r3j 0p4",
    "iso:country":"CA",
    "sg:city":"Winnipeg",
    "sg:classifiers":[
        {
            "category":"Personal",
            "subcategory":"Beauty Salon",
            "type":"Services"
        }
    ],
    "sg:phone":"+1 204 889 5134",
    "sg:postcode":"R3J 0P4",
    "sg:province":"MB",
    "wof:name":"Singleton's Pro Hair Care",
    "wof:placetype":"venue"
},
  "geometry": {"coordinates":[-97.263214,49.875675],"type":"Point"}
}