{
  "type": "Feature",
  "properties": {
    "addr:full":"353 Rue DE L'Eglise Saint-Basile-DE-Portneuf QC G0A 3G0",
    "addr:housenumber":"353",
    "addr:postcode":"g0a 3g0",
    "addr:street":"Rue De L'Eglise Saint-Basile-De-Portneuf",
    "iso:country":"CA",
    "sg:address":"353 Rue DE L'Eglise",
    "sg:city":"Saint-Basile-DE-Portneuf",
    "sg:classifiers":[
        {
            "category":"Shopping",
            "subcategory":"Stationery & Office Supplies",
            "type":"Retail Goods"
        }
    ],
    "sg:phone":"+1 418 329 2772",
    "sg:postcode":"G0A 3G0",
    "sg:province":"QC",
    "sg:tags":[
        "furniture"
    ],
    "wof:name":"Equipement DE Bureau Champlain",
    "wof:placetype":"venue"
},
  "geometry": {"coordinates":[-71.823662,46.75565],"type":"Point"}
}