{
  "type": "Feature",
  "properties": {
    "addr:full":"3665 Rue Chicoyne Lac-Megantic QC G6B 2Z4",
    "addr:housenumber":"3665",
    "addr:postcode":"g6b 2z4",
    "addr:street":"Rue Chicoyne Lac-Megantic",
    "iso:country":"CA",
    "sg:address":"3665 Rue Chicoyne",
    "sg:city":"Lac-Megantic",
    "sg:classifiers":[
        {
            "category":"Manufacturing",
            "subcategory":"Tools & Machinery",
            "type":"Manufacturing & Wholesale Goods"
        }
    ],
    "sg:phone":"+1 819 583 5274",
    "sg:postcode":"G6B 2Z4",
    "sg:province":"QC",
    "sg:tags":[
        "machine",
        "shop"
    ],
    "wof:name":"Atelier D'Usinage Gregoire Enr",
    "wof:placetype":"venue"
},
  "geometry": {"coordinates":[-70.90988900000001,45.592884],"type":"Point"}
}