{
  "type": "Feature",
  "properties": {
    "iso:country":"CA",
    "sg:address":"392 Government Rd E",
    "sg:city":"Kapuskasing",
    "sg:classifiers":[
        {
            "category":"Autos & Motor Vehicles",
            "subcategory":"Automobile Sales",
            "type":"Retail Goods"
        }
    ],
    "sg:phone":"+1 705 335 5000",
    "sg:postcode":"P5N 2X7",
    "sg:province":"ON",
    "sg:tags":[
        "car",
        "dealer"
    ],
    "wof:name":"Val Albert Motors Ltd",
    "wof:placetype":"venue"
},
  "geometry": {"coordinates":[-82.3718414307,49.3977546692],"type":"Point"}
}