{
  "type": "Feature",
  "properties": {
    "addr:full":"6375 King Rd Nobleton ON L0G 1N0",
    "addr:housenumber":"6375",
    "addr:postcode":"l0g 1n0",
    "addr:street":"King Rd",
    "iso:country":"CA",
    "sg:address":"6375 King Rd",
    "sg:city":"Nobleton",
    "sg:classifiers":[
        {
            "category":"Building & Trades",
            "subcategory":"Construction",
            "type":"Services"
        }
    ],
    "sg:phone":"+1 905 859 0231",
    "sg:postcode":"L0G 1N0",
    "sg:province":"ON",
    "sg:tags":[
        "general",
        "contractor"
    ],
    "wof:name":"Ron Wilson Construction Ltd",
    "wof:placetype":"venue"
},
  "geometry": {"coordinates":[-79.664108,43.899578],"type":"Point"}
}