{
  "type": "Feature",
  "properties": {
    "addr:full":"871 Edgeley Blvd Concord ON L4K 4V9",
    "addr:housenumber":"871",
    "addr:postcode":"l4k 4v9",
    "addr:street":"Edgeley Blvd",
    "iso:country":"CA",
    "sg:address":"871 Edgeley Blvd",
    "sg:city":"Concord",
    "sg:classifiers":[
        {
            "category":"Wholesale",
            "subcategory":"Auto Parts",
            "type":"Manufacturing & Wholesale Goods"
        }
    ],
    "sg:phone":"+1 905 660 6200",
    "sg:postcode":"L4K 4V9",
    "sg:province":"ON",
    "sg:tags":[
        "body",
        "automobile",
        "shop"
    ],
    "wof:name":"Nourse Automotive Ltd",
    "wof:placetype":"venue"
},
  "geometry": {"coordinates":[-79.539162,43.815639],"type":"Point"}
}