{
  "type": "Feature",
  "properties": {
    "addr:full":"416 Water St Paisley ON N0G 2N0",
    "addr:housenumber":"416",
    "addr:postcode":"n0g 2n0",
    "addr:street":"Water St",
    "iso:country":"CA",
    "sg:address":"416 Water St",
    "sg:city":"Paisley",
    "sg:classifiers":[
        {
            "category":"Travel",
            "subcategory":"Campground",
            "type":"Entertainment"
        }
    ],
    "sg:phone":"+1 519 353 5575",
    "sg:postcode":"N0G 2N0",
    "sg:province":"ON",
    "wof:name":"Paisley Rotary Camp Ground",
    "wof:placetype":"venue"
},
  "geometry": {"coordinates":[-81.268227,44.306129],"type":"Point"}
}