{
  "type": "Feature",
  "properties": {
    "addr:full":"1500 Georgia St W # 1800 Vancouver BC V6G 2Z6",
    "addr:housenumber":"1500",
    "addr:postcode":"v6g 2z6",
    "addr:street":"Georgia St W # 1800",
    "iso:country":"CA",
    "sg:address":"1500 Georgia St W # 1800",
    "sg:city":"Vancouver",
    "sg:classifiers":[
        {
            "category":"Shopping",
            "subcategory":"Computers & Home Electronics",
            "type":"Retail Goods"
        }
    ],
    "sg:phone":"+1 604 257 2700",
    "sg:postcode":"V6G 2Z6",
    "sg:province":"BC",
    "sg:tags":[
        "software"
    ],
    "wof:name":"Semotus Systems Corp",
    "wof:placetype":"venue"
},
  "geometry": {"coordinates":[-123.130257,49.290321],"type":"Point"}
}