{
  "type": "Feature",
  "properties": {
    "addr:full":"333 Brighton Ave North York ON M3H 4G4",
    "addr:housenumber":"333",
    "addr:postcode":"m3h 4g4",
    "addr:street":"Brighton Ave",
    "iso:country":"CA",
    "sg:address":"333 Brighton Ave",
    "sg:city":"North York",
    "sg:classifiers":[
        {
            "category":"Professional",
            "subcategory":"Business Services",
            "type":"Services"
        }
    ],
    "sg:phone":"+1 416 633 4962",
    "sg:postcode":"M3H 4G4",
    "sg:province":"ON",
    "sg:tags":[
        "paralegal"
    ],
    "wof:name":"Alpha Paralegal Assoc",
    "wof:placetype":"venue"
},
  "geometry": {"coordinates":[-79.4619674683,43.7564315796],"type":"Point"}
}