{
  "type": "Feature",
  "properties": {
    "addr:full":"12834 163 St NW Edmonton AB T5V 1K6",
    "addr:housenumber":"12834",
    "addr:postcode":"t5v 1k6",
    "addr:street":"163 St Nw",
    "iso:country":"CA",
    "sg:address":"12834 163 St NW",
    "sg:city":"Edmonton",
    "sg:classifiers":[
        {
            "category":"Organizations",
            "subcategory":"Professional Association",
            "type":"Services"
        }
    ],
    "sg:phone":"+1 780 447 2643",
    "sg:postcode":"T5V 1K6",
    "sg:province":"AB",
    "wof:name":"Alberta Diabetes Foundation",
    "wof:placetype":"venue"
},
  "geometry": {"coordinates":[-113.60309599999999,53.586586],"type":"Point"}
}