{
  "type": "Feature",
  "properties": {
    "addr:full":"5 Chukuni St Red Lake ON P0V 2M0",
    "addr:housenumber":"5",
    "addr:postcode":"p0v 2m0",
    "addr:street":"Chukuni St",
    "iso:country":"CA",
    "sg:address":"5 Chukuni St",
    "sg:city":"Red Lake",
    "sg:classifiers":[
        {
            "category":"Building & Trades",
            "subcategory":"Plumbing",
            "type":"Services"
        }
    ],
    "sg:phone":"+1 807 727 2827",
    "sg:postcode":"P0V 2M0",
    "sg:province":"ON",
    "sg:tags":[
        "sheet",
        "work",
        "metal",
        "heating",
        "contractor"
    ],
    "wof:name":"Blondie's Heating Sales & Svc",
    "wof:placetype":"venue"
},
  "geometry": {"coordinates":[-93.83448,51.016785],"type":"Point"}
}