{
  "type": "Feature",
  "properties": {
    "addr:full":"89 Hillside Dr Brampton ON L6S 1A7",
    "addr:housenumber":"89",
    "addr:postcode":"l6s 1a7",
    "addr:street":"Hillside Dr",
    "iso:country":"CA",
    "sg:address":"89 Hillside Dr",
    "sg:city":"Brampton",
    "sg:classifiers":[
        {
            "category":"Building & Trades",
            "subcategory":"Construction",
            "type":"Services"
        }
    ],
    "sg:phone":"+1 905 450 1222",
    "sg:postcode":"L6S 1A7",
    "sg:province":"ON",
    "sg:tags":[
        "general",
        "contractor"
    ],
    "wof:name":"Bolton Paving & General Contrs",
    "wof:placetype":"venue"
},
  "geometry": {"coordinates":[-79.7351303101,43.7136001587],"type":"Point"}
}