{
  "type": "Feature",
  "properties": {
    "addr:full":"17075 Leslie St #1 Newmarket ON L3Y 8E1",
    "addr:housenumber":"17075",
    "addr:postcode":"l3y 8e1",
    "addr:street":"Leslie St # 1",
    "iso:country":"CA",
    "sg:address":"17075 Leslie St #1",
    "sg:city":"Newmarket",
    "sg:classifiers":[
        {
            "category":"Education",
            "subcategory":"School",
            "type":"Public Place"
        }
    ],
    "sg:phone":"+1 905 853 0829",
    "sg:postcode":"L3Y 8E1",
    "sg:province":"ON",
    "wof:name":"Spotlight Theatre School Inc",
    "wof:placetype":"venue"
},
  "geometry": {"coordinates":[-79.4296569824,44.0577201843],"type":"Point"}
}