{
  "type": "Feature",
  "properties": {
    "addr:full":"St. John's NL A1A 5B5",
    "addr:postcode":"a1a 5b5",
    "iso:country":"CA",
    "sg:city":"St. John's",
    "sg:classifiers":[
        {
            "category":"Airline",
            "type":"Transportation"
        }
    ],
    "sg:phone":"+1 709 739 5622",
    "sg:postcode":"A1A 5B5",
    "sg:province":"NL",
    "sg:tags":[
        "aircraft",
        "rental",
        "charter",
        "leasing",
        "company"
    ],
    "wof:name":"Prince Edward Air",
    "wof:placetype":"venue"
},
  "geometry": {"coordinates":[-52.733631134,47.6906509399],"type":"Point"}
}