{
  "type": "Feature",
  "properties": {
    "addr:full":"499 Pembroke St W Pembroke ON K8A 5P1",
    "addr:housenumber":"499",
    "addr:postcode":"k8a 5p1",
    "addr:street":"Pembroke St W",
    "iso:country":"CA",
    "sg:address":"499 Pembroke St W",
    "sg:city":"Pembroke",
    "sg:classifiers":[
        {
            "category":"Education",
            "subcategory":"School",
            "type":"Public Place"
        }
    ],
    "sg:phone":"+1 613 735 1031",
    "sg:postcode":"K8A 5P1",
    "sg:province":"ON",
    "wof:name":"Renfrew County Roman Catholic",
    "wof:placetype":"venue"
},
  "geometry": {"coordinates":[-77.125877,45.824287],"type":"Point"}
}