{
  "type": "Feature",
  "properties": {
    "iso:country":"CA",
    "sg:address":"3333 Rue Du Carrefour",
    "sg:city":"Beauport",
    "sg:classifiers":[
        {
            "category":"Restaurant",
            "type":"Food & Drink"
        }
    ],
    "sg:phone":"+1 418 661 6427",
    "sg:postcode":"G1C 5R9",
    "sg:province":"QC",
    "wof:name":"Coq Roti",
    "wof:placetype":"venue"
},
  "geometry": {"coordinates":[-71.217178,46.858871],"type":"Point"}
}