{
  "type": "Feature",
  "properties": {
    "iso:country":"CA",
    "sg:address":"117 Glebe Ave",
    "sg:city":"Ottawa",
    "sg:classifiers":[
        {
            "category":"Retail",
            "subcategory":"Car Wash",
            "type":"Services"
        }
    ],
    "sg:phone":"+1 613 230 9274",
    "sg:postcode":"K1S 2C2",
    "sg:province":"ON",
    "sg:tags":[
        "polishing",
        "washing"
    ],
    "wof:name":"Glebe Car Wash",
    "wof:placetype":"venue"
},
  "geometry": {"coordinates":[-75.6893157959,45.4054412842],"type":"Point"}
}