{
  "type": "Feature",
  "properties": {
    "addr:full":"2604 3rd Ave Fort Macleod AB T0L 0Z0",
    "addr:housenumber":"2604",
    "addr:postcode":"t0l 0z0",
    "addr:street":"3Rd Ave Fort",
    "iso:country":"CA",
    "sg:address":"2604 3rd Ave",
    "sg:city":"Fort Macleod",
    "sg:classifiers":[
        {
            "category":"Organizations",
            "subcategory":"Religious Organization",
            "type":"Services"
        }
    ],
    "sg:phone":"+1 403 553 3040",
    "sg:postcode":"T0L 0Z0",
    "sg:province":"AB",
    "sg:tags":[
        "church"
    ],
    "wof:name":"Holy Cross Catholic Church",
    "wof:placetype":"venue"
},
  "geometry": {"coordinates":[-113.405960083,49.7262916565],"type":"Point"}
}