{
  "type": "Feature",
  "properties": {
    "addr:full":"Peterborough ON K9H 3P9",
    "addr:postcode":"k9h 3p9",
    "iso:country":"CA",
    "sg:city":"Peterborough",
    "sg:classifiers":[
        {
            "category":"Professional",
            "subcategory":"Detective & Security Services",
            "type":"Services"
        }
    ],
    "sg:phone":"+1 705 743 8026",
    "sg:postcode":"K9H 3P9",
    "sg:province":"ON",
    "sg:tags":[
        "guard",
        "patrol"
    ],
    "wof:name":"Securitas Canada",
    "wof:placetype":"venue"
},
  "geometry": {"coordinates":[-78.320122,44.304272],"type":"Point"}
}