{
  "type": "Feature",
  "properties": {
    "addr:full":"319 11 St SE Medicine Hat AB T1A 1S8",
    "addr:housenumber":"11",
    "addr:postcode":"t1a 1s8",
    "addr:street":"319;St Se",
    "iso:country":"CA",
    "sg:address":"319 11 St SE",
    "sg:city":"Medicine Hat",
    "sg:classifiers":[
        {
            "category":"Building & Trades",
            "subcategory":"Cleaning & Sanitation",
            "type":"Services"
        }
    ],
    "sg:phone":"+1 403 527 4368",
    "sg:postcode":"T1A 1S8",
    "sg:province":"AB",
    "sg:tags":[
        "janitor"
    ],
    "wof:name":"Dependable Cleaning Svc",
    "wof:placetype":"venue"
},
  "geometry": {"coordinates":[-110.679146,50.0285],"type":"Point"}
}