{
  "type": "Feature",
  "properties": {
    "addr:full":"Niagara on the Lake ON L0S 1J0",
    "addr:postcode":"l0s 1j0",
    "iso:country":"CA",
    "sg:city":"Niagara on the Lake",
    "sg:classifiers":[
        {
            "category":"Manufacturing",
            "subcategory":"Food",
            "type":"Manufacturing & Wholesale Goods"
        }
    ],
    "sg:phone":"+1 905 468 2187",
    "sg:postcode":"L0S 1J0",
    "sg:province":"ON",
    "sg:tags":[
        "winery"
    ],
    "wof:name":"Inniskillin Wines Inc",
    "wof:placetype":"venue"
},
  "geometry": {"coordinates":[-79.071854,43.230717],"type":"Point"}
}