{
  "type": "Feature",
  "properties": {
    "addr:full":"L'Orignal ON K0B 1K0",
    "addr:postcode":"k0b 1k0",
    "iso:country":"CA",
    "sg:city":"L'Orignal",
    "sg:classifiers":[
        {
            "category":"Shopping",
            "subcategory":"Bicycles & Sporting Goods",
            "type":"Retail Goods"
        }
    ],
    "sg:phone":"+1 613 679 4850",
    "sg:postcode":"K0B 1K0",
    "sg:province":"ON",
    "wof:name":"Meo Bicycle Svc",
    "wof:placetype":"venue"
},
  "geometry": {"coordinates":[-74.69111599999999,45.620441],"type":"Point"}
}