{
  "type": "Feature",
  "properties": {
    "iso:country":"CA",
    "sg:city":"Windsor",
    "sg:classifiers":[
        {
            "category":"Organizations",
            "subcategory":"Religious Organization",
            "type":"Services"
        }
    ],
    "sg:phone":"+1 519 253 4641",
    "sg:postcode":"N9A 1C1",
    "sg:province":"ON",
    "sg:tags":[
        "church"
    ],
    "wof:name":"Central United Church",
    "wof:placetype":"venue"
},
  "geometry": {"coordinates":[-83.03619384770001,42.3134117126],"type":"Point"}
}