{
  "type": "Feature",
  "properties": {
    "addr:full":"160 Rue Principale Albanel QC G8M 3J5",
    "addr:housenumber":"160",
    "addr:postcode":"g8m 3j5",
    "addr:street":"Rue Principale",
    "iso:country":"CA",
    "sg:address":"160 Rue Principale",
    "sg:city":"Albanel",
    "sg:classifiers":[
        {
            "category":"Government",
            "subcategory":"Office",
            "type":"Public Place"
        }
    ],
    "sg:phone":"+1 418 279 5250",
    "sg:postcode":"G8M 3J5",
    "sg:province":"QC",
    "sg:tags":[
        "village"
    ],
    "wof:name":"Albanel Hotel DE Ville",
    "wof:placetype":"venue"
},
  "geometry": {"coordinates":[-72.44175,48.883354],"type":"Point"}
}