{
  "type": "Feature",
  "properties": {
    "addr:full":"5805 Ch Saint-Francois Saint-Laurent QC H4S 1B6",
    "addr:housenumber":"5805",
    "addr:postcode":"h4s 1b6",
    "addr:street":"Ch Saint-Francois",
    "iso:country":"CA",
    "sg:address":"5805 Ch Saint-Francois",
    "sg:city":"Saint-Laurent",
    "sg:classifiers":[
        {
            "category":"Wholesale",
            "subcategory":"Medical Equipment & Supplies",
            "type":"Manufacturing & Wholesale Goods"
        }
    ],
    "sg:phone":"+1 514 956 9843",
    "sg:postcode":"H4S 1B6",
    "sg:province":"QC",
    "sg:tags":[
        "dental"
    ],
    "wof:name":"3I Implant Innovations Canada",
    "wof:placetype":"venue"
},
  "geometry": {"coordinates":[-73.73928070069999,45.4865722656],"type":"Point"}
}