{
  "type": "Feature",
  "properties": {
    "iso:country":"CA",
    "sg:address":"5050 Dufferin St",
    "sg:city":"North York",
    "sg:classifiers":[
        {
            "category":"Manufacturing",
            "subcategory":"Signs",
            "type":"Manufacturing & Wholesale Goods"
        }
    ],
    "sg:phone":"+1 416 661 5155",
    "sg:postcode":"M3H 5T5",
    "sg:province":"ON",
    "wof:name":"S & S Signs & Engraving Ctr",
    "wof:placetype":"venue"
},
  "geometry": {"coordinates":[-79.47016143800001,43.7814826965],"type":"Point"}
}