{
  "type": "Feature",
  "properties": {
    "iso:country":"CA",
    "sg:city":"Brantford",
    "sg:classifiers":[
        {
            "category":"Cinema",
            "subcategory":"Movie Rental",
            "type":"Entertainment"
        }
    ],
    "sg:phone":"+1 519 751 1073",
    "sg:postcode":"N3S 7S8",
    "sg:province":"ON",
    "sg:tags":[
        "leasing",
        "video",
        "disc",
        "tape"
    ],
    "wof:name":"Jumbo Video",
    "wof:placetype":"venue"
},
  "geometry": {"coordinates":[-80.24193572999999,43.1400527954],"type":"Point"}
}