{
  "type": "Feature",
  "properties": {
    "addr:full":"115 Main St Salmo BC V0G 1Z0",
    "addr:housenumber":"115",
    "addr:postcode":"v0g 1z0",
    "addr:street":"Main St",
    "iso:country":"CA",
    "sg:address":"115 Main St",
    "sg:city":"Salmo",
    "sg:classifiers":[
        {
            "category":"Food & Beverages",
            "subcategory":"Liquor & Beverages",
            "type":"Retail Goods"
        }
    ],
    "sg:phone":"+1 250 357 9351",
    "sg:postcode":"V0G 1Z0",
    "sg:province":"BC",
    "sg:tags":[
        "store"
    ],
    "wof:name":"Salmo Liquor Store",
    "wof:placetype":"venue"
},
  "geometry": {"coordinates":[-117.275154,49.191364],"type":"Point"}
}