{
  "type": "Feature",
  "properties": {
    "addr:full":"Toronto ON M4W 3P4",
    "addr:postcode":"m4w 3p4",
    "iso:country":"CA",
    "sg:city":"Toronto",
    "sg:classifiers":[
        {
            "category":"Personal",
            "type":"Services"
        }
    ],
    "sg:phone":"+1 416 925 8555",
    "sg:postcode":"M4W 3P4",
    "sg:province":"ON",
    "sg:tags":[
        "hair",
        "replacement"
    ],
    "wof:name":"Fontaine Hair Replacement",
    "wof:placetype":"venue"
},
  "geometry": {"coordinates":[-79.3882980347,43.6736068726],"type":"Point"}
}