{
  "type": "Feature",
  "properties": {
    "addr:full":"808 46th St E Saskatoon SK S7K 3V7",
    "addr:housenumber":"808",
    "addr:postcode":"s7k 3v7",
    "addr:street":"46Th St E",
    "iso:country":"CA",
    "sg:address":"808 46th St E",
    "sg:city":"Saskatoon",
    "sg:classifiers":[
        {
            "category":"Freight",
            "type":"Transportation"
        }
    ],
    "sg:phone":"+1 306 934 2700",
    "sg:postcode":"S7K 3V7",
    "sg:province":"SK",
    "sg:tags":[
        "trucking"
    ],
    "wof:name":"Directwest Carriers Inc",
    "wof:placetype":"venue"
},
  "geometry": {"coordinates":[-106.65467834499999,52.1647605896],"type":"Point"}
}