{
  "type": "Feature",
  "properties": {
    "iso:country":"CA",
    "sg:address":"125 Saskatchewan St",
    "sg:city":"Elbow",
    "sg:classifiers":[
        {
            "category":"Shopping",
            "subcategory":"Gifts & Souvenirs",
            "type":"Retail Goods"
        }
    ],
    "sg:phone":"+1 306 854 2200",
    "sg:postcode":"S0H 1J0",
    "sg:province":"SK",
    "sg:tags":[
        "shop"
    ],
    "wof:name":"Driftwood Studio & Gift Shop",
    "wof:placetype":"venue"
},
  "geometry": {"coordinates":[-106.594406128,51.1214065552],"type":"Point"}
}