{
  "type": "Feature",
  "properties": {
    "addr:full":"470 Cargill Rd Winkler MB R6W 4A7",
    "addr:housenumber":"470",
    "addr:postcode":"r6w 4a7",
    "addr:street":"Cargill Rd",
    "iso:country":"CA",
    "sg:address":"470 Cargill Rd",
    "sg:city":"Winkler",
    "sg:classifiers":[
        {
            "category":"Retail",
            "subcategory":"Auto Repair",
            "type":"Services"
        }
    ],
    "sg:phone":"+1 204 325 0843",
    "sg:postcode":"R6W 4A7",
    "sg:province":"MB",
    "sg:tags":[
        "automobile",
        "electric"
    ],
    "wof:name":"Start-N-Charge Auto Electric",
    "wof:placetype":"venue"
},
  "geometry": {"coordinates":[-97.91841100000001,49.185043],"type":"Point"}
}