{
  "type": "Feature",
  "properties": {
    "addr:full":"314 Pleasant Valley Rd Berwick NS B0P 1E0",
    "addr:housenumber":"314",
    "addr:postcode":"b0p 1e0",
    "addr:street":"Pleasant Valley Rd",
    "iso:country":"CA",
    "sg:address":"314 Pleasant Valley Rd",
    "sg:city":"Berwick",
    "sg:classifiers":[
        {
            "category":"Wholesale",
            "subcategory":"Meat",
            "type":"Manufacturing & Wholesale Goods"
        }
    ],
    "sg:phone":"+1 902 538 1106",
    "sg:postcode":"B0P 1E0",
    "sg:province":"NS",
    "sg:tags":[
        "butchering"
    ],
    "wof:name":"Meadowbrook Farm Meat Market",
    "wof:placetype":"venue"
},
  "geometry": {"coordinates":[-64.737724,45.049816],"type":"Point"}
}