{
  "type": "Feature",
  "properties": {
    "addr:full":"Kabenung Lk Wawa ON P0S 1K0",
    "addr:postcode":"p0s 1k0",
    "addr:street":"Kabenung Lk",
    "iso:country":"CA",
    "sg:address":"Kabenung Lk",
    "sg:city":"Wawa",
    "sg:classifiers":[
        {
            "category":"Travel",
            "subcategory":"Hotels & Motels",
            "type":"Entertainment"
        }
    ],
    "sg:phone":"+1 705 856 2795",
    "sg:postcode":"P0S 1K0",
    "sg:province":"ON",
    "sg:tags":[
        "resort"
    ],
    "wof:name":"Agree Outpost Camp",
    "wof:placetype":"venue"
},
  "geometry": {"coordinates":[-84.772667,47.990986],"type":"Point"}
}