{
  "type": "Feature",
  "properties": {
    "iso:country":"CA",
    "sg:address":"18195 Yonge St",
    "sg:city":"Newmarket",
    "sg:classifiers":[
        {
            "category":"Restaurant",
            "type":"Food & Drink"
        }
    ],
    "sg:phone":"+1 905 953 0229",
    "sg:postcode":"L3Y 4V8",
    "sg:province":"ON",
    "wof:name":"Boston Pizza",
    "wof:placetype":"venue"
},
  "geometry": {"coordinates":[-79.483932,44.069431],"type":"Point"}
}