{
  "type": "Feature",
  "properties": {
    "iso:country":"CA",
    "sg:address":"35 Tanager Dr",
    "sg:city":"Guelph",
    "sg:classifiers":[
        {
            "category":"Professional",
            "subcategory":"Research",
            "type":"Services"
        }
    ],
    "sg:phone":"+1 519 824 7456",
    "sg:postcode":"N1C 1B7",
    "sg:province":"ON",
    "sg:tags":[
        "market",
        "analysis"
    ],
    "wof:name":"Adventus Research",
    "wof:placetype":"venue"
},
  "geometry": {"coordinates":[-80.244247,43.50185],"type":"Point"}
}