{
  "type": "Feature",
  "properties": {
    "iso:country":"CA",
    "sg:address":"4753 Boul Des Grandes-Prairies",
    "sg:city":"Saint-Leonard",
    "sg:classifiers":[
        {
            "category":"Wholesale",
            "subcategory":"Furniture",
            "type":"Manufacturing & Wholesale Goods"
        }
    ],
    "sg:phone":"+1 514 326 5300",
    "sg:postcode":"H1R 1A5",
    "sg:province":"QC",
    "sg:tags":[
        "mattress",
        "maker",
        "supply"
    ],
    "wof:name":"Serta Montreal Inc",
    "wof:placetype":"venue"
},
  "geometry": {"coordinates":[-73.623474,45.584198],"type":"Point"}
}