{
  "type": "Feature",
  "properties": {
    "addr:full":"St-Germain QC G0L 3G0",
    "addr:postcode":"g0l 3g0",
    "addr:street":"St-Germain",
    "iso:country":"CA",
    "sg:city":"St-Germain",
    "sg:classifiers":[
        {
            "category":"Freight",
            "type":"Transportation"
        }
    ],
    "sg:phone":"+1 418 492 5092",
    "sg:postcode":"G0L 3G0",
    "sg:province":"QC",
    "sg:tags":[
        "trucking"
    ],
    "wof:name":"Bosse Jp Inc",
    "wof:placetype":"venue"
},
  "geometry": {"coordinates":[-69.80810546879999,47.5806884766],"type":"Point"}
}