{
  "type": "Feature",
  "properties": {
    "addr:full":"7257 King George Hwy Surrey BC V3W 5A7",
    "addr:housenumber":"7257",
    "addr:postcode":"v3w 5a7",
    "addr:street":"King George Hwy",
    "iso:country":"CA",
    "sg:address":"7257 King George Hwy",
    "sg:city":"Surrey",
    "sg:classifiers":[
        {
            "category":"Retail",
            "subcategory":"Auto Repair",
            "type":"Services"
        }
    ],
    "sg:phone":"+1 604 594 7333",
    "sg:postcode":"V3W 5A7",
    "sg:province":"BC",
    "sg:tags":[
        "repairing",
        "automobile"
    ],
    "wof:name":"Minit-Tune & Brake Auto Ctr",
    "wof:placetype":"venue"
},
  "geometry": {"coordinates":[-122.84577179,49.1344604492],"type":"Point"}
}