{
  "type": "Feature",
  "properties": {
    "addr:full":"Houston BC V0J 1Z0",
    "addr:postcode":"v0j 1z0",
    "iso:country":"CA",
    "sg:city":"Houston",
    "sg:classifiers":[
        {
            "category":"Freight",
            "type":"Transportation"
        }
    ],
    "sg:phone":"+1 250 845 7411",
    "sg:postcode":"V0J 1Z0",
    "sg:province":"BC",
    "sg:tags":[
        "trucking"
    ],
    "wof:name":"D & A Crane Svc Ltd",
    "wof:placetype":"venue"
},
  "geometry": {"coordinates":[-126.61586,54.432289],"type":"Point"}
}