{
  "type": "Feature",
  "properties": {
    "addr:full":"12880 Clarke Pl Richmond BC V6V 2H1",
    "addr:housenumber":"12880",
    "addr:postcode":"v6v 2h1",
    "addr:street":"Clarke Pl",
    "iso:country":"CA",
    "sg:address":"12880 Clarke Pl",
    "sg:city":"Richmond",
    "sg:classifiers":[
        {
            "category":"Wholesale",
            "subcategory":"Non-durable Goods",
            "type":"Manufacturing & Wholesale Goods"
        }
    ],
    "sg:phone":"+1 604 821 1166",
    "sg:postcode":"V6V 2H1",
    "sg:province":"BC",
    "sg:tags":[
        "t"
    ],
    "wof:name":"Wilson International Products",
    "wof:placetype":"venue"
},
  "geometry": {"coordinates":[-123.081047,49.185444],"type":"Point"}
}