{
  "type": "Feature",
  "properties": {
    "addr:full":"25 Laurelcrest St Brampton ON L6S 4C4",
    "addr:housenumber":"25",
    "addr:postcode":"l6s 4c4",
    "addr:street":"Laurelcrest St",
    "iso:country":"CA",
    "sg:address":"25 Laurelcrest St",
    "sg:city":"Brampton",
    "sg:classifiers":[
        {
            "category":"Organizations",
            "subcategory":"Professional Association",
            "type":"Services"
        }
    ],
    "sg:phone":"+1 905 456 0606",
    "sg:postcode":"L6S 4C4",
    "sg:province":"ON",
    "wof:name":"Le Cercle DE L'Amitie",
    "wof:placetype":"venue"
},
  "geometry": {"coordinates":[-79.73732757569999,43.7104034424],"type":"Point"}
}