{
  "type": "Feature",
  "properties": {
    "addr:full":"3600 4th Ave Regina SK S4T 0H4",
    "addr:housenumber":"3600",
    "addr:postcode":"s4t 0h4",
    "addr:street":"4Th Ave",
    "iso:country":"CA",
    "sg:address":"3600 4th Ave",
    "sg:city":"Regina",
    "sg:classifiers":[
        {
            "category":"Organizations",
            "subcategory":"Religious Organization",
            "type":"Services"
        }
    ],
    "sg:phone":"+1 306 522 9418",
    "sg:postcode":"S4T 0H4",
    "sg:province":"SK",
    "sg:tags":[
        "church"
    ],
    "wof:name":"St John's United Church",
    "wof:placetype":"venue"
},
  "geometry": {"coordinates":[-104.63279,50.463013],"type":"Point"}
}