{
  "type": "Feature",
  "properties": {
    "addr:full":"15 West Pearce St Richmond Hill ON L4B 1H6",
    "addr:housenumber":"15",
    "addr:postcode":"l4b 1h6",
    "addr:street":"West Pearce St",
    "iso:country":"CA",
    "sg:address":"15 West Pearce St",
    "sg:city":"Richmond Hill",
    "sg:classifiers":[
        {
            "category":"Personal",
            "type":"Services"
        }
    ],
    "sg:phone":"+1 905 764 3311",
    "sg:postcode":"L4B 1H6",
    "sg:province":"ON",
    "sg:tags":[
        "arts",
        "instruction",
        "martial",
        "program",
        "fitness",
        "exercise",
        "physical"
    ],
    "wof:name":"Seibukan Traditional Martial",
    "wof:placetype":"venue"
},
  "geometry": {"coordinates":[-79.38423899999999,43.848221],"type":"Point"}
}