{
  "type": "Feature",
  "properties": {
    "addr:full":"1700 Rue Sherbrooke Magog QC J1X 5B4",
    "addr:housenumber":"1700",
    "addr:postcode":"j1x 5b4",
    "addr:street":"Rue Sherbrooke",
    "iso:country":"CA",
    "sg:address":"1700 Rue Sherbrooke",
    "sg:city":"Magog",
    "sg:classifiers":[
        {
            "category":"Restaurant",
            "type":"Food & Drink"
        }
    ],
    "sg:phone":"+1 819 847 0822",
    "sg:postcode":"J1X 5B4",
    "sg:province":"QC",
    "wof:name":"Brasserie Le Pichet",
    "wof:placetype":"venue"
},
  "geometry": {"coordinates":[-72.1320800781,45.2760734558],"type":"Point"}
}