{
  "type": "Feature",
  "properties": {
    "iso:country":"CA",
    "sg:address":"812 Browns Line",
    "sg:city":"Etobicoke",
    "sg:classifiers":[
        {
            "category":"Real Estate",
            "subcategory":"Real Estate Agent",
            "type":"Services"
        }
    ],
    "sg:phone":"+1 416 252 7878",
    "sg:postcode":"M8W 3W2",
    "sg:province":"ON",
    "sg:tags":[
        "appraiser"
    ],
    "wof:name":"Cornwall Property Consultants",
    "wof:placetype":"venue"
},
  "geometry": {"coordinates":[-79.5486373901,43.6088752747],"type":"Point"}
}