{
  "type": "Feature",
  "properties": {
    "addr:full":"35 Skyline Cres NE Calgary AB T2K 5X2",
    "addr:housenumber":"35",
    "addr:postcode":"t2k 5x2",
    "addr:street":"Skyline Cres Ne",
    "iso:country":"CA",
    "sg:address":"35 Skyline Cres NE",
    "sg:city":"Calgary",
    "sg:classifiers":[
        {
            "category":"Professional",
            "subcategory":"Engineering",
            "type":"Services"
        }
    ],
    "sg:phone":"+1 403 241 0885",
    "sg:postcode":"T2K 5X2",
    "sg:province":"AB",
    "sg:tags":[
        "engineer"
    ],
    "wof:name":"Colleaux Engineering Ltd",
    "wof:placetype":"venue"
},
  "geometry": {"coordinates":[-114.045891,51.097408],"type":"Point"}
}