{
  "type": "Feature",
  "properties": {
    "addr:full":"44 Crockford Blvd Scarborough ON M1R 3C3",
    "addr:housenumber":"44",
    "addr:postcode":"m1r 3c3",
    "addr:street":"Crockford Blvd",
    "iso:country":"CA",
    "sg:address":"44 Crockford Blvd",
    "sg:city":"Scarborough",
    "sg:classifiers":[
        {
            "category":"Professional",
            "subcategory":"Business Services",
            "type":"Services"
        }
    ],
    "sg:phone":"+1 416 701 0559",
    "sg:postcode":"M1R 3C3",
    "sg:province":"ON",
    "sg:tags":[
        "auctioneer"
    ],
    "wof:name":"White Queen Ltd",
    "wof:placetype":"venue"
},
  "geometry": {"coordinates":[-79.288223,43.738861],"type":"Point"}
}