{
  "type": "Feature",
  "properties": {
    "addr:full":"Castlegar BC V1N 2W1",
    "addr:postcode":"v1n 2w1",
    "iso:country":"CA",
    "sg:city":"Castlegar",
    "sg:classifiers":[
        {
            "category":"Freight",
            "type":"Transportation"
        }
    ],
    "sg:phone":"+1 250 365 8289",
    "sg:postcode":"V1N 2W1",
    "sg:province":"BC",
    "sg:tags":[
        "commercial",
        "storage"
    ],
    "wof:name":"Kats Mini Storage",
    "wof:placetype":"venue"
},
  "geometry": {"coordinates":[-117.64884948700001,49.2876701355],"type":"Point"}
}