{
  "type": "Feature",
  "properties": {
    "addr:full":"PO Box 119 Lourdes NL A0N 1R0",
    "addr:housenumber":"po;119",
    "addr:postcode":"a0n 1r0",
    "addr:street":"Box",
    "iso:country":"CA",
    "sg:address":"PO Box 119",
    "sg:city":"Lourdes",
    "sg:classifiers":[
        {
            "category":"Health Services",
            "subcategory":"Doctor",
            "type":"Services"
        }
    ],
    "sg:phone":"+1 709 642 5371",
    "sg:postcode":"A0N 1R0",
    "sg:province":"NL",
    "sg:tags":[
        "physician",
        "surgeon"
    ],
    "wof:name":"Lourdes Medical Clinic",
    "wof:placetype":"venue"
},
  "geometry": {"coordinates":[-59.0033531189,48.6470603943],"type":"Point"}
}