{
  "type": "Feature",
  "properties": {
    "addr:full":"500 Vanier Ave Labrador City NL A2V 2W7",
    "addr:housenumber":"500",
    "addr:postcode":"a2v 2w7",
    "addr:street":"Vanier Ave",
    "iso:country":"CA",
    "sg:address":"500 Vanier Ave",
    "sg:city":"Labrador City",
    "sg:classifiers":[
        {
            "category":"Banks & Credit Unions",
            "subcategory":"Bank",
            "type":"Services"
        }
    ],
    "sg:phone":"+1 709 944 3626",
    "sg:postcode":"A2V 2W7",
    "sg:province":"NL",
    "wof:name":"Scotiabank",
    "wof:placetype":"venue"
},
  "geometry": {"coordinates":[-66.92240099999999,52.948402],"type":"Point"}
}