{
  "type": "Feature",
  "properties": {
    "iso:country":"CA",
    "sg:address":"600 Rue Haggerty",
    "sg:city":"Drummondville",
    "sg:classifiers":[
        {
            "category":"Manufacturing",
            "subcategory":"Tools & Machinery",
            "type":"Manufacturing & Wholesale Goods"
        }
    ],
    "sg:phone":"+1 819 477 4555",
    "sg:postcode":"J2C 3G6",
    "sg:province":"QC",
    "sg:tags":[
        "machine",
        "shop"
    ],
    "wof:name":"Usinage Drummond Inc",
    "wof:placetype":"venue"
},
  "geometry": {"coordinates":[-72.5142364502,45.8848648071],"type":"Point"}
}