{
  "type": "Feature",
  "properties": {
    "addr:full":"483 Victoria St Kingston ON K7L 3Z8",
    "addr:housenumber":"483",
    "addr:postcode":"k7l 3z8",
    "addr:street":"Victoria St",
    "iso:country":"CA",
    "sg:address":"483 Victoria St",
    "sg:city":"Kingston",
    "sg:classifiers":[
        {
            "category":"Social Services",
            "subcategory":"Job Training",
            "type":"Services"
        }
    ],
    "sg:phone":"+1 613 549 1360",
    "sg:postcode":"K7L 3Z8",
    "sg:province":"ON",
    "sg:tags":[
        "career",
        "counseling",
        "vocational"
    ],
    "wof:name":"Directions",
    "wof:placetype":"venue"
},
  "geometry": {"coordinates":[-76.502822876,44.2352752686],"type":"Point"}
}