{
  "type": "Feature",
  "properties": {
    "addr:full":"475 36 St NE Calgary AB T2A 6K3",
    "addr:postcode":"475 36;t2a 6k3",
    "addr:street":"St Ne",
    "iso:country":"CA",
    "sg:address":"475 36 St NE",
    "sg:city":"Calgary",
    "sg:classifiers":[
        {
            "category":"Restaurant",
            "type":"Food & Drink"
        }
    ],
    "sg:phone":"+1 403 273 4740",
    "sg:postcode":"T2A 6K3",
    "sg:province":"AB",
    "wof:name":"Wendy's",
    "wof:placetype":"venue"
},
  "geometry": {"coordinates":[-113.98220825200001,51.055644989],"type":"Point"}
}