{
  "type": "Feature",
  "properties": {
    "addr:full":"5009 50 Ave Vegreville AB T9C 1R9",
    "addr:housenumber":"5009",
    "addr:postcode":"t9c 1r9",
    "addr:street":"50 Ave",
    "iso:country":"CA",
    "sg:address":"5009 50 Ave",
    "sg:city":"Vegreville",
    "sg:classifiers":[
        {
            "category":"Government",
            "subcategory":"Office",
            "type":"Public Place"
        }
    ],
    "sg:phone":"+1 780 632 2771",
    "sg:postcode":"T9C 1R9",
    "sg:province":"AB",
    "sg:tags":[
        "village"
    ],
    "wof:name":"Vegreville Chamber of Commerce",
    "wof:placetype":"venue"
},
  "geometry": {"coordinates":[-112.053291321,53.4947738647],"type":"Point"}
}