{
  "type": "Feature",
  "properties": {
    "addr:full":"99 New Cove Rd St. John's NL A1A 2C2",
    "addr:housenumber":"99",
    "addr:postcode":"a1a 2c2",
    "addr:street":"New Cove Rd",
    "iso:country":"CA",
    "sg:address":"99 New Cove Rd",
    "sg:city":"St. John's",
    "sg:classifiers":[
        {
            "category":"Food & Beverages",
            "subcategory":"Groceries & Convenience Stores",
            "type":"Retail Goods"
        }
    ],
    "sg:phone":"+1 709 754 4350",
    "sg:postcode":"A1A 2C2",
    "sg:province":"NL",
    "wof:name":"Sunrise Convenience & Deli",
    "wof:placetype":"venue"
},
  "geometry": {"coordinates":[-52.7090148926,47.5816116333],"type":"Point"}
}