{
  "type": "Feature",
  "properties": {
    "addr:full":"31818 Conrad Ave Abbotsford BC V2T 2K3",
    "addr:housenumber":"31818",
    "addr:postcode":"v2t 2k3",
    "addr:street":"Conrad Ave",
    "iso:country":"CA",
    "sg:address":"31818 Conrad Ave",
    "sg:city":"Abbotsford",
    "sg:classifiers":[
        {
            "category":"Building & Trades",
            "subcategory":"Electrical",
            "type":"Services"
        }
    ],
    "sg:phone":"+1 604 853 6868",
    "sg:postcode":"V2T 2K3",
    "sg:province":"BC",
    "sg:tags":[
        "electric",
        "contractor"
    ],
    "wof:name":"Gifford Electric Ltd",
    "wof:placetype":"venue"
},
  "geometry": {"coordinates":[-122.342545,49.057262],"type":"Point"}
}