{
  "type": "Feature",
  "properties": {
    "addr:full":"728 Rye St Peterborough ON K9J 6W9",
    "addr:housenumber":"728",
    "addr:postcode":"k9j 6w9",
    "addr:street":"Rye St",
    "iso:country":"CA",
    "sg:address":"728 Rye St",
    "sg:city":"Peterborough",
    "sg:classifiers":[
        {
            "category":"Retail",
            "subcategory":"Auto Repair",
            "type":"Services"
        }
    ],
    "sg:phone":"+1 705 743 0581",
    "sg:postcode":"K9J 6W9",
    "sg:province":"ON",
    "sg:tags":[
        "repairing",
        "automobile"
    ],
    "wof:name":"Liftlock Truck Repair",
    "wof:placetype":"venue"
},
  "geometry": {"coordinates":[-78.3462524414,44.2775650024],"type":"Point"}
}