{
  "type": "Feature",
  "properties": {
    "addr:full":"33 Rue Chabanel O Montreal QC H2N 1C2",
    "addr:housenumber":"33",
    "addr:postcode":"h2n 1c2",
    "addr:street":"Rue Chabanel O",
    "iso:country":"CA",
    "sg:address":"33 Rue Chabanel O",
    "sg:city":"Montreal",
    "sg:classifiers":[
        {
            "category":"Wholesale",
            "subcategory":"Apparel",
            "type":"Manufacturing & Wholesale Goods"
        }
    ],
    "sg:phone":"+1 514 388 2524",
    "sg:postcode":"H2N 1C2",
    "sg:province":"QC",
    "wof:name":"Boutique Panic",
    "wof:placetype":"venue"
},
  "geometry": {"coordinates":[-73.6510848999,45.5448150635],"type":"Point"}
}