{
  "type": "Feature",
  "properties": {
    "addr:full":"RR 1 Holland Centre ON N0H 1R0",
    "addr:postcode":"n0h 1r0",
    "addr:street":"Rr 1 Holland",
    "iso:country":"CA",
    "sg:address":"RR 1",
    "sg:city":"Holland Centre",
    "sg:classifiers":[
        {
            "category":"Building & Trades",
            "subcategory":"Construction",
            "type":"Services"
        }
    ],
    "sg:phone":"+1 519 794 2920",
    "sg:postcode":"N0H 1R0",
    "sg:province":"ON",
    "sg:tags":[
        "dry wall",
        "contractor"
    ],
    "wof:name":"Dan Harrison Drywall",
    "wof:placetype":"venue"
},
  "geometry": {"coordinates":[-80.7940750122,44.3931846619],"type":"Point"}
}