{
  "type": "Feature",
  "properties": {
    "addr:full":"North York ON M6M 3Z5",
    "addr:postcode":"m6m 3z5",
    "iso:country":"CA",
    "sg:city":"North York",
    "sg:classifiers":[
        {
            "category":"Health Services",
            "subcategory":"Doctor",
            "type":"Services"
        }
    ],
    "sg:phone":"+1 416 247 5459",
    "sg:postcode":"M6M 3Z5",
    "sg:province":"ON",
    "sg:tags":[
        "physician",
        "surgeon"
    ],
    "wof:name":"Dobbs, K MD",
    "wof:placetype":"venue"
},
  "geometry": {"coordinates":[-79.4755020142,43.6983184814],"type":"Point"}
}