{
  "type": "Feature",
  "properties": {
    "addr:full":"612 Hespeler Rd Cambridge ON N1R 6J8",
    "addr:housenumber":"612",
    "addr:postcode":"n1r 6j8",
    "addr:street":"Hespeler Rd",
    "iso:country":"CA",
    "sg:address":"612 Hespeler Rd",
    "sg:city":"Cambridge",
    "sg:classifiers":[
        {
            "category":"Autos & Motor Vehicles",
            "subcategory":"Fuel & Gas Station",
            "type":"Retail Goods"
        }
    ],
    "sg:phone":"+1 519 623 1419",
    "sg:postcode":"N1R 6J8",
    "sg:province":"ON",
    "sg:tags":[
        "oil"
    ],
    "wof:name":"Sunoco",
    "wof:placetype":"venue"
},
  "geometry": {"coordinates":[-80.32730865480001,43.404712677],"type":"Point"}
}