{
  "type": "Feature",
  "properties": {
    "addr:full":"1340 1E Rue Sainte-Marie QC G6E 3H3",
    "addr:housenumber":"1340",
    "addr:postcode":"qc g6e 3h3",
    "addr:street":"1E Rue Sainte-Marie",
    "iso:country":"CA",
    "sg:address":"1340 1E Rue",
    "sg:city":"Sainte-Marie",
    "sg:classifiers":[
        {
            "category":"Wholesale",
            "subcategory":"Machinery & Supplies",
            "type":"Manufacturing & Wholesale Goods"
        }
    ],
    "sg:phone":"+1 418 387 2778",
    "sg:postcode":"G6E 3H3",
    "sg:province":"QC",
    "sg:tags":[
        "tool"
    ],
    "wof:name":"Ste-Marie Location Enr",
    "wof:placetype":"venue"
},
  "geometry": {"coordinates":[-65.98382599999999,48.172626],"type":"Point"}
}