{
  "type": "Feature",
  "properties": {
    "addr:full":"1870 Rue Allard Brossard QC J4W 1Z4",
    "addr:housenumber":"1870",
    "addr:postcode":"j4w 1z4",
    "addr:street":"Rue Allard",
    "iso:country":"CA",
    "sg:address":"1870 Rue Allard",
    "sg:city":"Brossard",
    "sg:classifiers":[
        {
            "category":"Organizations",
            "subcategory":"Labor Organization",
            "type":"Services"
        }
    ],
    "sg:phone":"+1 450 443 0184",
    "sg:postcode":"J4W 1Z4",
    "sg:province":"QC",
    "wof:name":"Syndicat National Des Employes",
    "wof:placetype":"venue"
},
  "geometry": {"coordinates":[-73.467415,45.478737],"type":"Point"}
}