{
  "type": "Feature",
  "properties": {
    "addr:full":"450 Rue Heriot Drummondville QC J2B 1B5",
    "addr:housenumber":"450",
    "addr:postcode":"j2b 1b5",
    "addr:street":"Rue Heriot",
    "iso:country":"CA",
    "sg:address":"450 Rue Heriot",
    "sg:city":"Drummondville",
    "sg:classifiers":[
        {
            "category":"Health Services",
            "subcategory":"Health Practitioner",
            "type":"Services"
        }
    ],
    "sg:phone":"+1 819 472 7070",
    "sg:postcode":"J2B 1B5",
    "sg:province":"QC",
    "sg:tags":[
        "physiotherapist"
    ],
    "wof:name":"Centre DE Therapie Sport-Medic",
    "wof:placetype":"venue"
},
  "geometry": {"coordinates":[-72.4830245972,45.8821563721],"type":"Point"}
}