{
  "type": "Feature",
  "properties": {
    "addr:full":"650 Danforth Ave Toronto ON M4K 1R3",
    "addr:housenumber":"650",
    "addr:postcode":"m4k 1r3",
    "addr:street":"Danforth Ave",
    "iso:country":"CA",
    "sg:address":"650 Danforth Ave",
    "sg:city":"Toronto",
    "sg:classifiers":[
        {
            "category":"Banks & Credit Unions",
            "subcategory":"Bank",
            "type":"Services"
        }
    ],
    "sg:phone":"+1 416 465 5404",
    "sg:postcode":"M4K 1R3",
    "sg:province":"ON",
    "wof:name":"Royal Bank Financial Group",
    "wof:placetype":"venue"
},
  "geometry": {"coordinates":[-79.34498600000001,43.678932],"type":"Point"}
}