{
  "type": "Feature",
  "properties": {
    "addr:full":"32 Pardue Close Red Deer AB T4P 1L7",
    "addr:housenumber":"32",
    "addr:postcode":"t4p 1l7",
    "addr:street":"Pardue Close",
    "iso:country":"CA",
    "sg:address":"32 Pardue Close",
    "sg:city":"Red Deer",
    "sg:classifiers":[
        {
            "category":"Wholesale",
            "subcategory":"Machinery & Supplies",
            "type":"Manufacturing & Wholesale Goods"
        }
    ],
    "sg:phone":"+1 403 342 6400",
    "sg:postcode":"T4P 1L7",
    "sg:province":"AB",
    "sg:tags":[
        "crane",
        "derrick",
        "rental"
    ],
    "wof:name":"Burbank Crane Ltd",
    "wof:placetype":"venue"
},
  "geometry": {"coordinates":[-113.804802,52.297333],"type":"Point"}
}