{
  "type": "Feature",
  "properties": {
    "addr:full":"1501 Rue Saint-Patrick Montreal QC H3K 2B7",
    "addr:housenumber":"1501",
    "addr:postcode":"h3k 2b7",
    "addr:street":"Rue Saint-Patrick",
    "iso:country":"CA",
    "sg:address":"1501 Rue Saint-Patrick",
    "sg:city":"Montreal",
    "sg:classifiers":[
        {
            "category":"Manufacturing",
            "subcategory":"Textiles",
            "type":"Manufacturing & Wholesale Goods"
        }
    ],
    "sg:phone":"+1 514 939 4000",
    "sg:postcode":"H3K 2B7",
    "sg:province":"QC",
    "sg:tags":[
        "knitted",
        "fabric"
    ],
    "wof:name":"Agmont Inc",
    "wof:placetype":"venue"
},
  "geometry": {"coordinates":[-73.559715,45.487553],"type":"Point"}
}