{
  "type": "Feature",
  "properties": {
    "addr:full":"268 Rue Des Laurentides Chicoutimi QC G7H 7X9",
    "addr:housenumber":"268",
    "addr:postcode":"g7h 7x9",
    "addr:street":"Rue Des Laurentides",
    "iso:country":"CA",
    "sg:address":"268 Rue Des Laurentides",
    "sg:city":"Chicoutimi",
    "sg:classifiers":[
        {
            "category":"Retail",
            "subcategory":"Repair Shop",
            "type":"Services"
        }
    ],
    "sg:phone":"+1 418 696 4141",
    "sg:postcode":"G7H 7X9",
    "sg:province":"QC",
    "sg:tags":[
        "parts",
        "jeweler"
    ],
    "wof:name":"Atelier Du Bijoutier Enr",
    "wof:placetype":"venue"
},
  "geometry": {"coordinates":[-71.06356,48.398598],"type":"Point"}
}