{
  "type": "Feature",
  "properties": {
    "addr:full":"2410 26 Ave Nanton AB T0L 1R0",
    "addr:housenumber":"2410",
    "addr:postcode":"t0l 1r0",
    "addr:street":"26 Ave",
    "iso:country":"CA",
    "sg:address":"2410 26 Ave",
    "sg:city":"Nanton",
    "sg:classifiers":[
        {
            "category":"Organizations",
            "subcategory":"Religious Organization",
            "type":"Services"
        }
    ],
    "sg:phone":"+1 403 646 2567",
    "sg:postcode":"T0L 1R0",
    "sg:province":"AB",
    "sg:tags":[
        "church"
    ],
    "wof:name":"Nanton Baptist Church",
    "wof:placetype":"venue"
},
  "geometry": {"coordinates":[-113.781685,50.340904],"type":"Point"}
}