{
  "type": "Feature",
  "properties": {
    "addr:full":"Edmonton AB T5K 1C4",
    "addr:postcode":"t5k 1c4",
    "iso:country":"CA",
    "sg:city":"Edmonton",
    "sg:classifiers":[
        {
            "category":"Professional",
            "subcategory":"Lawyer & Legal Services",
            "type":"Services"
        }
    ],
    "sg:phone":"+1 780 424 9058",
    "sg:postcode":"T5K 1C4",
    "sg:province":"AB",
    "sg:tags":[
        "attorney"
    ],
    "wof:name":"Knisely, Dale M",
    "wof:placetype":"venue"
},
  "geometry": {"coordinates":[-113.50316619900001,53.5377197266],"type":"Point"}
}