{
  "type": "Feature",
  "properties": {
    "addr:full":"1 Croatia Rd London ON N5V 4X6",
    "addr:housenumber":"1",
    "addr:postcode":"n5v 4x6",
    "addr:street":"Croatia Rd",
    "iso:country":"CA",
    "sg:address":"1 Croatia Rd",
    "sg:city":"London",
    "sg:classifiers":[
        {
            "category":"Building & Trades",
            "subcategory":"Plumbing",
            "type":"Services"
        }
    ],
    "sg:phone":"+1 519 457 0671",
    "sg:postcode":"N5V 4X6",
    "sg:province":"ON",
    "sg:tags":[
        "conditioning",
        "air",
        "system",
        "contractor"
    ],
    "wof:name":"Aok Heating & Cooling Inc",
    "wof:placetype":"venue"
},
  "geometry": {"coordinates":[-81.21244799999999,43.026806],"type":"Point"}
}