{
  "type": "Feature",
  "properties": {
    "iso:country":"CA",
    "sg:address":"1 Croatia Rd",
    "sg:city":"London",
    "sg:classifiers":[
        {
            "category":"Building & Trades",
            "subcategory":"Plumbing",
            "type":"Services"
        }
    ],
    "sg:phone":"+1 519 457 0671",
    "sg:postcode":"N5V 4X6",
    "sg:province":"ON",
    "sg:tags":[
        "conditioning",
        "air",
        "system",
        "contractor"
    ],
    "wof:name":"Aok Heating & Cooling Inc",
    "wof:placetype":"venue"
},
  "geometry": {"coordinates":[-81.212448,43.026806],"type":"Point"}
}