{
  "type": "Feature",
  "properties": {
    "addr:full":"1380 Notre Dame Ave Winnipeg MB R3E 0P7",
    "addr:housenumber":"1380",
    "addr:postcode":"r3e 0p7",
    "addr:street":"Notre Dame Ave",
    "iso:country":"CA",
    "sg:address":"1380 Notre Dame Ave",
    "sg:city":"Winnipeg",
    "sg:phone":"+1 204 786 6566",
    "sg:postcode":"R3E 0P7",
    "sg:province":"MB",
    "sg:tags":[
        "tanner",
        "taxidermist"
    ],
    "wof:name":"Hawkins Taxidermists Ltd",
    "wof:placetype":"venue"
},
  "geometry": {"coordinates":[-97.18604278559999,49.9098968506],"type":"Point"}
}