{
  "type": "Feature",
  "properties": {
    "addr:full":"820 Mcphillips St Winnipeg MB R2X 2J7",
    "addr:housenumber":"820",
    "addr:postcode":"r2x 2j7",
    "addr:street":"Mcphillips St",
    "iso:country":"CA",
    "sg:address":"820 Mcphillips St",
    "sg:city":"Winnipeg",
    "sg:classifiers":[
        {
            "category":"Education",
            "subcategory":"School",
            "type":"Public Place"
        }
    ],
    "sg:phone":"+1 204 586 9625",
    "sg:postcode":"R2X 2J7",
    "sg:province":"MB",
    "wof:name":"Lord Nelson School",
    "wof:placetype":"venue"
},
  "geometry": {"coordinates":[-97.169281,49.928761],"type":"Point"}
}