{
  "type": "Feature",
  "properties": {
    "addr:full":"Edmonton AB T5N 3Y4",
    "addr:postcode":"t5n 3y4",
    "iso:country":"CA",
    "sg:city":"Edmonton",
    "sg:classifiers":[
        {
            "category":"Professional",
            "subcategory":"Lawyer & Legal Services",
            "type":"Services"
        }
    ],
    "sg:phone":"+1 780 482 9200",
    "sg:postcode":"T5N 3Y4",
    "sg:province":"AB",
    "sg:tags":[
        "attorney"
    ],
    "wof:name":"Russell, Charles P",
    "wof:placetype":"venue"
},
  "geometry": {"coordinates":[-113.532806397,53.5466384888],"type":"Point"}
}