{
  "type": "Feature",
  "properties": {
    "iso:country":"CA",
    "sg:address":"305 Cemetary Rd",
    "sg:city":"Neustadt",
    "sg:classifiers":[
        {
            "category":"Building & Trades",
            "subcategory":"Construction",
            "type":"Services"
        }
    ],
    "sg:phone":"+1 519 799 5776",
    "sg:postcode":"N0G 2M0",
    "sg:province":"ON",
    "sg:tags":[
        "contractor"
    ],
    "wof:name":"David Construction",
    "wof:placetype":"venue"
},
  "geometry": {"coordinates":[-81.0004272461,44.0855407715],"type":"Point"}
}