{
  "type": "Feature",
  "properties": {
    "addr:full":"Kananaskis AB T0L 2H0",
    "addr:postcode":"t0l 2h0",
    "iso:country":"CA",
    "sg:city":"Kananaskis",
    "sg:classifiers":[
        {
            "category":"Shopping",
            "subcategory":"Gifts & Souvenirs",
            "type":"Retail Goods"
        }
    ],
    "sg:phone":"+1 403 591 7595",
    "sg:postcode":"T0L 2H0",
    "sg:province":"AB",
    "sg:tags":[
        "shop"
    ],
    "wof:name":"Picadilly Place",
    "wof:placetype":"venue"
},
  "geometry": {"coordinates":[-115.117080688,50.6466751099],"type":"Point"}
}