{
  "type": "Feature",
  "properties": {
    "addr:full":"19 Rue Michaud Saint-Jacques NB E7B 1M1",
    "addr:housenumber":"19",
    "addr:postcode":"e7b 1m1",
    "addr:street":"Rue Michaud",
    "iso:country":"CA",
    "sg:address":"19 Rue Michaud",
    "sg:city":"Saint-Jacques",
    "sg:classifiers":[
        {
            "category":"Professional",
            "subcategory":"Engineering",
            "type":"Services"
        }
    ],
    "sg:phone":"+1 506 739 6471",
    "sg:postcode":"E7B 1M1",
    "sg:province":"NB",
    "sg:tags":[
        "engineer"
    ],
    "wof:name":"Bourque J Denys Rpf",
    "wof:placetype":"venue"
},
  "geometry": {"coordinates":[-68.4672241211,47.4772491455],"type":"Point"}
}