{
  "type": "Feature",
  "properties": {
    "addr:full":"1030 Lakeshore Dr North Bay ON P1A 2H3",
    "addr:housenumber":"1030",
    "addr:postcode":"p1a 2h3",
    "addr:street":"Lakeshore Dr",
    "iso:country":"CA",
    "sg:address":"1030 Lakeshore Dr",
    "sg:city":"North Bay",
    "sg:classifiers":[
        {
            "category":"Shopping",
            "type":"Retail Goods"
        }
    ],
    "sg:phone":"+1 705 497 8884",
    "sg:postcode":"P1A 2H3",
    "sg:province":"ON",
    "sg:tags":[
        "awning",
        "canopy"
    ],
    "wof:name":"North Country Shade & Shutter",
    "wof:placetype":"venue"
},
  "geometry": {"coordinates":[-79.417526,46.258278],"type":"Point"}
}