{
  "type": "Feature",
  "properties": {
    "addr:full":"3 Arthur Ave Renfrew ON K7V 3S1",
    "addr:housenumber":"3",
    "addr:postcode":"k7v 3s1",
    "addr:street":"Arthur Ave",
    "iso:country":"CA",
    "sg:address":"3 Arthur Ave",
    "sg:city":"Renfrew",
    "sg:classifiers":[
        {
            "category":"Home & Garden",
            "subcategory":"Building Materials",
            "type":"Retail Goods"
        }
    ],
    "sg:phone":"+1 613 432 9009",
    "sg:postcode":"K7V 3S1",
    "sg:province":"ON",
    "sg:tags":[
        "windows"
    ],
    "wof:name":"Renfrew County Window & Door",
    "wof:placetype":"venue"
},
  "geometry": {"coordinates":[-76.6947860718,45.4769973755],"type":"Point"}
}