{
  "type": "Feature",
  "properties": {
    "addr:full":"5800 Boul Industriel Montreal-Nord QC H1G 3J2",
    "addr:housenumber":"5800",
    "addr:postcode":"h1g 3j2",
    "addr:street":"Boul Industriel",
    "iso:country":"CA",
    "sg:address":"5800 Boul Industriel",
    "sg:city":"Montreal-Nord",
    "sg:classifiers":[
        {
            "category":"Manufacturing",
            "subcategory":"Motor Vehicles & Parts",
            "type":"Manufacturing & Wholesale Goods"
        }
    ],
    "sg:phone":"+1 514 327 8746",
    "sg:postcode":"H1G 3J2",
    "sg:province":"QC",
    "sg:tags":[
        "automobile",
        "supply"
    ],
    "wof:name":"Gemico Inc Produits",
    "wof:placetype":"venue"
},
  "geometry": {"coordinates":[-73.6146316528,45.6025085449],"type":"Point"}
}