{
  "type": "Feature",
  "properties": {
    "iso:country":"CA",
    "sg:address":"121 Hampton Rd",
    "sg:city":"Rothesay",
    "sg:classifiers":[
        {
            "category":"Real Estate",
            "subcategory":"Real Estate Agent",
            "type":"Services"
        }
    ],
    "sg:phone":"+1 506 847 2020",
    "sg:postcode":"E2E 2P8",
    "sg:province":"NB",
    "wof:name":"Royal Le Page Atlantic",
    "wof:placetype":"venue"
},
  "geometry": {"coordinates":[-65.9806442261,45.3981666565],"type":"Point"}
}