{
  "type": "Feature",
  "properties": {
    "addr:full":"Kaslo BC V0G 1M0",
    "addr:postcode":"v0g 1m0",
    "iso:country":"CA",
    "sg:city":"Kaslo",
    "sg:classifiers":[
        {
            "category":"Home & Garden",
            "subcategory":"Building Materials",
            "type":"Retail Goods"
        }
    ],
    "sg:phone":"+1 250 366 4358",
    "sg:postcode":"V0G 1M0",
    "sg:province":"BC",
    "sg:tags":[
        "shingles",
        "shake"
    ],
    "wof:name":"Remco Shake & Shingle Products",
    "wof:placetype":"venue"
},
  "geometry": {"coordinates":[-116.911743,49.913212],"type":"Point"}
}