{
  "type": "Feature",
  "properties": {
    "addr:full":"534 Cubert St Oshawa ON L1J 4B5",
    "addr:housenumber":"534",
    "addr:postcode":"l1j 4b5",
    "addr:street":"Cubert St",
    "iso:country":"CA",
    "sg:address":"534 Cubert St",
    "sg:city":"Oshawa",
    "sg:classifiers":[
        {
            "category":"Food & Beverages",
            "subcategory":"Groceries & Convenience Stores",
            "type":"Retail Goods"
        }
    ],
    "sg:phone":"+1 905 579 2500",
    "sg:postcode":"L1J 4B5",
    "sg:province":"ON",
    "sg:tags":[
        "grocer"
    ],
    "wof:name":"Cubert Milk & Variety",
    "wof:placetype":"venue"
},
  "geometry": {"coordinates":[-78.864548,43.881954],"type":"Point"}
}