{
  "type": "Feature",
  "properties": {
    "addr:full":"2162 Airport Dr Saskatoon SK S7L 6M6",
    "addr:housenumber":"2162",
    "addr:postcode":"s7l 6m6",
    "addr:street":"Airport Dr",
    "iso:country":"CA",
    "sg:address":"2162 Airport Dr",
    "sg:city":"Saskatoon",
    "sg:classifiers":[
        {
            "category":"Government",
            "subcategory":"Office",
            "type":"Public Place"
        }
    ],
    "sg:phone":"+1 306 975 4185",
    "sg:postcode":"S7L 6M6",
    "sg:province":"SK",
    "wof:name":"Canada Animal Health",
    "wof:placetype":"venue"
},
  "geometry": {"coordinates":[-106.68698120099999,52.1579627991],"type":"Point"}
}