{
  "type": "Feature",
  "properties": {
    "addr:full":"Surrey BC V4A 4H1",
    "addr:postcode":"v4a 4h1",
    "iso:country":"CA",
    "sg:city":"Surrey",
    "sg:classifiers":[
        {
            "category":"Health Services",
            "subcategory":"Doctor",
            "type":"Services"
        }
    ],
    "sg:phone":"+1 604 535 4499",
    "sg:postcode":"V4A 4H1",
    "sg:province":"BC",
    "sg:tags":[
        "dentist"
    ],
    "wof:name":"David Wilkie Inc",
    "wof:placetype":"venue"
},
  "geometry": {"coordinates":[-122.83457900000001,49.032219],"type":"Point"}
}