{
  "type": "Feature",
  "properties": {
    "addr:full":"1015 Danforth Ave Toronto ON M4J 1M1",
    "addr:housenumber":"1015",
    "addr:postcode":"m4j 1m1",
    "addr:street":"Danforth Ave",
    "iso:country":"CA",
    "sg:address":"1015 Danforth Ave",
    "sg:city":"Toronto",
    "sg:classifiers":[
        {
            "category":"Organizations",
            "subcategory":"Religious Organization",
            "type":"Services"
        }
    ],
    "sg:phone":"+1 416 465 7833",
    "sg:postcode":"M4J 1M1",
    "sg:province":"ON",
    "sg:tags":[
        "mosque",
        "church"
    ],
    "wof:name":"Madinah Masjid",
    "wof:placetype":"venue"
},
  "geometry": {"coordinates":[-79.337341,43.680355],"type":"Point"}
}