{
  "type": "Feature",
  "properties": {
    "addr:full":"345 Carleton Ave Ottawa ON K1Y 0K3",
    "addr:housenumber":"345",
    "addr:postcode":"k1y 0k3",
    "addr:street":"Carleton Ave",
    "iso:country":"CA",
    "sg:address":"345 Carleton Ave",
    "sg:city":"Ottawa",
    "sg:classifiers":[
        {
            "category":"Food & Beverages",
            "subcategory":"Groceries & Convenience Stores",
            "type":"Retail Goods"
        }
    ],
    "sg:phone":"+1 613 725 3065",
    "sg:postcode":"K1Y 0K3",
    "sg:province":"ON",
    "sg:tags":[
        "grocer"
    ],
    "wof:name":"Loeb Canada Inc",
    "wof:placetype":"venue"
},
  "geometry": {"coordinates":[-75.741066,45.398308],"type":"Point"}
}