{
  "type": "Feature",
  "properties": {
    "addr:full":"185 Lombard Ave Winnipeg MB R3B 0W4",
    "addr:housenumber":"185",
    "addr:postcode":"r3b 0w4",
    "addr:street":"Lombard Ave",
    "iso:country":"CA",
    "sg:address":"185 Lombard Ave",
    "sg:city":"Winnipeg",
    "sg:classifiers":[
        {
            "category":"Restaurant",
            "type":"Food & Drink"
        }
    ],
    "sg:phone":"+1 204 944 1180",
    "sg:postcode":"R3B 0W4",
    "sg:province":"MB",
    "wof:name":"Bailey's Restaurant & Bar",
    "wof:placetype":"venue"
},
  "geometry": {"coordinates":[-97.13771800000001,49.896385],"type":"Point"}
}