{
  "type": "Feature",
  "properties": {
    "addr:full":"2995 Boul Industriel Sherbrooke QC J1L 2T9",
    "addr:housenumber":"2995",
    "addr:postcode":"j1l 2t9",
    "addr:street":"Boul Industriel",
    "iso:country":"CA",
    "sg:address":"2995 Boul Industriel",
    "sg:city":"Sherbrooke",
    "sg:classifiers":[
        {
            "category":"Manufacturing",
            "subcategory":"Rubber & Plastics",
            "type":"Manufacturing & Wholesale Goods"
        }
    ],
    "sg:phone":"+1 819 565 3737",
    "sg:postcode":"J1L 2T9",
    "sg:province":"QC",
    "sg:tags":[
        "product"
    ],
    "wof:name":"Camoplast Inc",
    "wof:placetype":"venue"
},
  "geometry": {"coordinates":[-71.969742,45.414837],"type":"Point"}
}