{
  "type": "Feature",
  "properties": {
    "addr:full":"10815 Bathurst St # 16 Richmond Hill ON L4C 9Y2",
    "addr:housenumber":"10815;16",
    "addr:postcode":"l4c 9y2",
    "addr:street":"Bathurst St #",
    "iso:country":"CA",
    "sg:address":"10815 Bathurst St # 16",
    "sg:city":"Richmond Hill",
    "sg:classifiers":[
        {
            "category":"Banks & Credit Unions",
            "subcategory":"Investment Brokerage",
            "type":"Services"
        }
    ],
    "sg:phone":"+1 905 884 8898",
    "sg:postcode":"L4C 9Y2",
    "sg:province":"ON",
    "sg:tags":[
        "consultant",
        "planning",
        "financial"
    ],
    "wof:name":"Wealthworks Financial Inc",
    "wof:placetype":"venue"
},
  "geometry": {"coordinates":[-79.4675369263,43.8855857849],"type":"Point"}
}