{
  "type": "Feature",
  "properties": {
    "addr:full":"7865 Boul Saint-Laurent Montreal QC H2R 1X1",
    "addr:housenumber":"7865",
    "addr:postcode":"h2r 1x1",
    "addr:street":"Boul Saint-Laurent",
    "iso:country":"CA",
    "sg:address":"7865 Boul Saint-Laurent",
    "sg:city":"Montreal",
    "sg:classifiers":[
        {
            "category":"Manufacturing",
            "subcategory":"Tools & Machinery",
            "type":"Manufacturing & Wholesale Goods"
        }
    ],
    "sg:phone":"+1 514 948 5540",
    "sg:postcode":"H2R 1X1",
    "sg:province":"QC",
    "sg:tags":[
        "woodworking"
    ],
    "wof:name":"Brobec Systemes D'Agrafage",
    "wof:placetype":"venue"
},
  "geometry": {"coordinates":[-73.6274261475,45.5379867554],"type":"Point"}
}