{
  "type": "Feature",
  "properties": {
    "addr:full":"1565 Rue Saint Amour Acton Vale QC J0H 1A0",
    "addr:housenumber":"1565",
    "addr:postcode":"j0h 1a0",
    "addr:street":"Rue Saint Amour",
    "iso:country":"CA",
    "sg:address":"1565 Rue Saint Amour",
    "sg:city":"Acton Vale",
    "sg:classifiers":[
        {
            "category":"Health Services",
            "subcategory":"Nursing And Care Facility",
            "type":"Services"
        }
    ],
    "sg:phone":"+1 450 546 7031",
    "sg:postcode":"J0H 1A0",
    "sg:province":"QC",
    "sg:tags":[
        "home",
        "retirement",
        "community"
    ],
    "wof:name":"Maison Saint Amour",
    "wof:placetype":"venue"
},
  "geometry": {"coordinates":[-72.5630722046,45.6565284729],"type":"Point"}
}