{
  "type": "Feature",
  "properties": {
    "addr:full":"2804 Boul Ducharme LA Tuque QC G9X 4S8",
    "addr:housenumber":"2804",
    "addr:postcode":"g9x 4s8",
    "addr:street":"Boul Ducharme",
    "iso:country":"CA",
    "sg:address":"2804 Boul Ducharme",
    "sg:city":"LA Tuque",
    "sg:classifiers":[
        {
            "category":"Retail",
            "subcategory":"Car Wash",
            "type":"Services"
        }
    ],
    "sg:phone":"+1 819 523 3644",
    "sg:postcode":"G9X 4S8",
    "sg:province":"QC",
    "sg:tags":[
        "polishing",
        "glass",
        "washing"
    ],
    "wof:name":"Duro Vitres & Acces D'Autos",
    "wof:placetype":"venue"
},
  "geometry": {"coordinates":[-72.78527069090001,47.3971595764],"type":"Point"}
}