{
  "type": "Feature",
  "properties": {
    "addr:full":"Owen Sound ON N4K 5N7",
    "addr:postcode":"n4k 5n7",
    "iso:country":"CA",
    "sg:city":"Owen Sound",
    "sg:classifiers":[
        {
            "category":"Travel",
            "subcategory":"Hotels & Motels",
            "type":"Entertainment"
        }
    ],
    "sg:phone":"+1 519 376 5841",
    "sg:postcode":"N4K 5N7",
    "sg:province":"ON",
    "wof:name":"Springmount Motel",
    "wof:placetype":"venue"
},
  "geometry": {"coordinates":[-80.942604,44.564877],"type":"Point"}
}