{
  "type": "Feature",
  "properties": {
    "iso:country":"CA",
    "sg:address":"5086 Rue Frontenac",
    "sg:city":"Lac-Megantic",
    "sg:classifiers":[
        {
            "category":"Education",
            "subcategory":"Library",
            "type":"Public Place"
        }
    ],
    "sg:phone":"+1 819 583 0876",
    "sg:postcode":"G6B 1H3",
    "sg:province":"QC",
    "wof:name":"Bibliotheque Municipale DE Lac",
    "wof:placetype":"venue"
},
  "geometry": {"coordinates":[-70.884209,45.577255],"type":"Point"}
}