{
  "type": "Feature",
  "properties": {
    "addr:full":"35 Front St N Mississauga ON L5H 2E1",
    "addr:housenumber":"35",
    "addr:postcode":"l5h 2e1",
    "addr:street":"Front St N",
    "iso:country":"CA",
    "sg:address":"35 Front St N",
    "sg:city":"Mississauga",
    "sg:classifiers":[
        {
            "category":"Organizations",
            "subcategory":"Professional Association",
            "type":"Services"
        }
    ],
    "sg:phone":"+1 905 278 9001",
    "sg:postcode":"L5H 2E1",
    "sg:province":"ON",
    "sg:tags":[
        "club"
    ],
    "wof:name":"Royal Canadian Legion Mgr Ofc",
    "wof:placetype":"venue"
},
  "geometry": {"coordinates":[-79.590683,43.550884],"type":"Point"}
}