{
  "type": "Feature",
  "properties": {
    "addr:full":"Saint-Quentin NB E8A 1J9",
    "addr:postcode":"e8a 1j9",
    "iso:country":"CA",
    "sg:city":"Saint-Quentin",
    "sg:classifiers":[
        {
            "category":"Shopping",
            "subcategory":"Gifts & Souvenirs",
            "type":"Retail Goods"
        }
    ],
    "sg:phone":"+1 506 235 2762",
    "sg:postcode":"E8A 1J9",
    "sg:province":"NB",
    "sg:tags":[
        "shop"
    ],
    "wof:name":"Boutique Des Reves",
    "wof:placetype":"venue"
},
  "geometry": {"coordinates":[-67.39233400000001,47.510395],"type":"Point"}
}