{
  "type": "Feature",
  "properties": {
    "addr:full":"7229 Kingsway Burnaby BC V5E 1G5",
    "addr:housenumber":"7229",
    "addr:postcode":"v5e 1g5",
    "addr:street":"Kingsway",
    "iso:country":"CA",
    "sg:address":"7229 Kingsway",
    "sg:city":"Burnaby",
    "sg:classifiers":[
        {
            "category":"Restaurant",
            "type":"Food & Drink"
        }
    ],
    "sg:phone":"+1 604 718 1035",
    "sg:postcode":"V5E 1G5",
    "sg:province":"BC",
    "wof:name":"Mc Donald's",
    "wof:placetype":"venue"
},
  "geometry": {"coordinates":[-122.95417,49.218548],"type":"Point"}
}