{
  "type": "Feature",
  "properties": {
    "addr:full":"505 Av Bethany Lachute QC J8H 4A6",
    "addr:postcode":"j8h 4a6",
    "addr:street":"505 Av Bethany",
    "iso:country":"CA",
    "sg:address":"505 Av Bethany",
    "sg:city":"Lachute",
    "sg:classifiers":[
        {
            "category":"Government",
            "subcategory":"Office",
            "type":"Public Place"
        }
    ],
    "sg:phone":"+1 450 562 8574",
    "sg:postcode":"J8H 4A6",
    "sg:province":"QC",
    "wof:name":"Quebec Bureaux-Renseignements",
    "wof:placetype":"venue"
},
  "geometry": {"coordinates":[-74.326981,45.637634],"type":"Point"}
}