{
  "type": "Feature",
  "properties": {
    "iso:country":"CA",
    "sg:address":"149 Kellys Rd",
    "sg:city":"Lombardy",
    "sg:classifiers":[
        {
            "category":"Wholesale",
            "subcategory":"Meat",
            "type":"Manufacturing & Wholesale Goods"
        }
    ],
    "sg:phone":"+1 613 283 4121",
    "sg:postcode":"K0G 1L0",
    "sg:province":"ON",
    "sg:tags":[
        "butchering"
    ],
    "wof:name":"Alsta Farms",
    "wof:placetype":"venue"
},
  "geometry": {"coordinates":[-76.0511016846,44.8219871521],"type":"Point"}
}