{
  "type": "Feature",
  "properties": {
    "addr:full":"5430 Timberlea Blvd Mississauga ON L4W 2T7",
    "addr:housenumber":"5430",
    "addr:postcode":"l4w 2t7",
    "addr:street":"Timberlea Blvd",
    "iso:country":"CA",
    "sg:address":"5430 Timberlea Blvd",
    "sg:city":"Mississauga",
    "sg:classifiers":[
        {
            "category":"Manufacturing",
            "subcategory":"Tools & Machinery",
            "type":"Manufacturing & Wholesale Goods"
        }
    ],
    "sg:phone":"+1 905 819 8000",
    "sg:postcode":"L4W 2T7",
    "sg:province":"ON",
    "sg:tags":[
        "equipment",
        "electric"
    ],
    "wof:name":"Siemens in Canada",
    "wof:placetype":"venue"
},
  "geometry": {"coordinates":[-79.6461105347,43.6324272156],"type":"Point"}
}