{
  "type": "Feature",
  "properties": {
    "addr:full":"69 Superior St Brantford ON N3S 2K5",
    "addr:housenumber":"69",
    "addr:postcode":"n3s 2k5",
    "addr:street":"Superior St",
    "iso:country":"CA",
    "sg:address":"69 Superior St",
    "sg:city":"Brantford",
    "sg:classifiers":[
        {
            "category":"Organizations",
            "subcategory":"Religious Organization",
            "type":"Services"
        }
    ],
    "sg:phone":"+1 519 752 7979",
    "sg:postcode":"N3S 2K5",
    "sg:province":"ON",
    "sg:tags":[
        "church"
    ],
    "wof:name":"Wesley United Church",
    "wof:placetype":"venue"
},
  "geometry": {"coordinates":[-80.25514221189999,43.1305503845],"type":"Point"}
}