{
  "type": "Feature",
  "properties": {
    "addr:full":"8735 50 St NW Edmonton AB T6B 1E7",
    "addr:housenumber":"8735",
    "addr:postcode":"t6b 1e7",
    "addr:street":"50 St Nw",
    "iso:country":"CA",
    "sg:address":"8735 50 St NW",
    "sg:city":"Edmonton",
    "sg:classifiers":[
        {
            "category":"Retail",
            "subcategory":"Animal Services",
            "type":"Services"
        }
    ],
    "sg:phone":"+1 780 469 4706",
    "sg:postcode":"T6B 1E7",
    "sg:province":"AB",
    "sg:tags":[
        "pet",
        "grooming",
        "washing"
    ],
    "wof:name":"Canine Quarters",
    "wof:placetype":"venue"
},
  "geometry": {"coordinates":[-113.41791499999999,53.519913],"type":"Point"}
}