{
  "type": "Feature",
  "properties": {
    "addr:full":"755 33rd Ave E Vancouver BC V5V 3A1",
    "addr:housenumber":"755",
    "addr:postcode":"v5v 3a1",
    "addr:street":"33Rd Ave E",
    "iso:country":"CA",
    "sg:address":"755 33rd Ave E",
    "sg:city":"Vancouver",
    "sg:classifiers":[
        {
            "category":"Education",
            "subcategory":"Special Training",
            "type":"Public Place"
        }
    ],
    "sg:phone":"+1 604 879 8901",
    "sg:postcode":"V5V 3A1",
    "sg:province":"BC",
    "sg:tags":[
        "instruction",
        "driving"
    ],
    "wof:name":"Budget Driving School Ltd",
    "wof:placetype":"venue"
},
  "geometry": {"coordinates":[-123.089264,49.240402],"type":"Point"}
}