{
  "type": "Feature",
  "properties": {
    "addr:full":"15 Ch Ruisseau-Serpent Notre-Dame-Du-Laus QC J0X 2M0",
    "addr:housenumber":"15",
    "addr:postcode":"j0x 2m0",
    "addr:street":"Ch Ruisseau-Serpent",
    "iso:country":"CA",
    "sg:address":"15 Ch Ruisseau-Serpent",
    "sg:city":"Notre-Dame-Du-Laus",
    "sg:classifiers":[
        {
            "category":"Organizations",
            "subcategory":"Professional Association",
            "type":"Services"
        }
    ],
    "sg:phone":"+1 819 767 2759",
    "sg:postcode":"J0X 2M0",
    "sg:province":"QC",
    "wof:name":"Comite Des Loisirs Notre-Dame",
    "wof:placetype":"venue"
},
  "geometry": {"coordinates":[-75.622833,46.092018],"type":"Point"}
}