{
  "type": "Feature",
  "properties": {
    "addr:full":"PO Box 151 Lac LA Biche AB T0A 2C0",
    "addr:housenumber":"po",
    "addr:postcode":"t0a 2c0",
    "addr:street":"Box 151 Lac La Biche",
    "iso:country":"CA",
    "sg:address":"PO Box 151",
    "sg:city":"Lac LA Biche",
    "sg:classifiers":[
        {
            "category":"Retail",
            "subcategory":"Auto Repair",
            "type":"Services"
        }
    ],
    "sg:phone":"+1 780 623 4801",
    "sg:postcode":"T0A 2C0",
    "sg:province":"AB",
    "sg:tags":[
        "body",
        "automobile",
        "painting"
    ],
    "wof:name":"Larry's Autobody & Refinishing",
    "wof:placetype":"venue"
},
  "geometry": {"coordinates":[-111.97445678699999,54.77110672],"type":"Point"}
}