{
  "type": "Feature",
  "properties": {
    "addr:full":"1250 Rue Fleury E Montreal QC H2C 1R1",
    "addr:housenumber":"1250",
    "addr:postcode":"h2c 1r1",
    "addr:street":"Rue Fleury E",
    "iso:country":"CA",
    "sg:address":"1250 Rue Fleury E",
    "sg:city":"Montreal",
    "sg:classifiers":[
        {
            "category":"Social Services",
            "subcategory":"Child Care",
            "type":"Services"
        }
    ],
    "sg:phone":"+1 514 389 3480",
    "sg:postcode":"H2C 1R1",
    "sg:province":"QC",
    "wof:name":"Garderie L'Abri",
    "wof:placetype":"venue"
},
  "geometry": {"coordinates":[-73.658157,45.559364],"type":"Point"}
}