{
  "type": "Feature",
  "properties": {
    "addr:full":"116 Rue Saint-Gabriel Saint-Gabriel-DE-Brandon QC J0K 2N0",
    "addr:housenumber":"116",
    "addr:postcode":"j0k 2n0",
    "addr:street":"Rue Saint-Gabriel",
    "iso:country":"CA",
    "sg:address":"116 Rue Saint-Gabriel",
    "sg:city":"Saint-Gabriel-DE-Brandon",
    "sg:classifiers":[
        {
            "category":"Real Estate",
            "subcategory":"Surveying",
            "type":"Services"
        }
    ],
    "sg:phone":"+1 450 835 4725",
    "sg:postcode":"J0K 2N0",
    "sg:province":"QC",
    "sg:tags":[
        "surveyor"
    ],
    "wof:name":"Gilles Beaulieu & Assoc",
    "wof:placetype":"venue"
},
  "geometry": {"coordinates":[-73.3822402954,46.2915344238],"type":"Point"}
}