{
  "type": "Feature",
  "properties": {
    "iso:country":"CA",
    "sg:address":"7335 Rue Chambord",
    "sg:city":"Montreal",
    "sg:classifiers":[
        {
            "category":"Social Services",
            "subcategory":"Child Care",
            "type":"Services"
        }
    ],
    "sg:phone":"+1 514 271 7843",
    "sg:postcode":"H2E 1W8",
    "sg:province":"QC",
    "sg:tags":[
        "kindergarten",
        "academic",
        "school"
    ],
    "wof:name":"Centre Gemma Galgani",
    "wof:placetype":"venue"
},
  "geometry": {"coordinates":[-73.612449646,45.5457572937],"type":"Point"}
}