{
  "type": "Feature",
  "properties": {
    "addr:full":"5505 Rue DE Marseille Montreal QC H1N 1J4",
    "addr:housenumber":"5505",
    "addr:postcode":"h1n 1j4",
    "addr:street":"Rue De Marseille",
    "iso:country":"CA",
    "sg:address":"5505 Rue DE Marseille",
    "sg:city":"Montreal",
    "sg:classifiers":[
        {
            "category":"Manufacturing",
            "subcategory":"Metals",
            "type":"Manufacturing & Wholesale Goods"
        }
    ],
    "sg:phone":"+1 514 251 2528",
    "sg:postcode":"H1N 1J4",
    "sg:province":"QC",
    "sg:tags":[
        "coating"
    ],
    "wof:name":"Release Coatings",
    "wof:placetype":"venue"
},
  "geometry": {"coordinates":[-73.54557,45.569225],"type":"Point"}
}