{
  "type": "Feature",
  "properties": {
    "addr:full":"800 106 Ave Dawson Creek BC V1G 2N4",
    "addr:housenumber":"106",
    "addr:postcode":"v1g 2n4",
    "addr:street":"Ave",
    "iso:country":"CA",
    "sg:address":"800 106 Ave",
    "sg:city":"Dawson Creek",
    "sg:classifiers":[
        {
            "category":"Retail",
            "subcategory":"Self-service Laundry",
            "type":"Services"
        }
    ],
    "sg:phone":"+1 250 782 9389",
    "sg:postcode":"V1G 2N4",
    "sg:province":"BC",
    "wof:name":"Dawson Creek Coin Laundry Ltd",
    "wof:placetype":"venue"
},
  "geometry": {"coordinates":[-120.224785,55.753418],"type":"Point"}
}