{
  "type": "Feature",
  "properties": {
    "addr:full":"685 Muskoka Rd N # 2 Gravenhurst ON P1P 1N5",
    "addr:housenumber":"685",
    "addr:postcode":"p1p 1n5",
    "addr:street":"Muskoka Rd N # 2",
    "iso:country":"CA",
    "sg:address":"685 Muskoka Rd N # 2",
    "sg:city":"Gravenhurst",
    "sg:classifiers":[
        {
            "category":"Government",
            "subcategory":"Office",
            "type":"Public Place"
        }
    ],
    "sg:phone":"+1 705 687 6365",
    "sg:postcode":"P1P 1N5",
    "sg:province":"ON",
    "wof:name":"Ontario Drivers & Vehicle Lcns",
    "wof:placetype":"venue"
},
  "geometry": {"coordinates":[-79.37645000000001,44.924843],"type":"Point"}
}