{
  "type": "Feature",
  "properties": {
    "addr:full":"Huntsville ON P1H 1H4",
    "addr:postcode":"p1h 1h4",
    "iso:country":"CA",
    "sg:city":"Huntsville",
    "sg:classifiers":[
        {
            "category":"Professional",
            "subcategory":"Management & Consulting",
            "type":"Services"
        }
    ],
    "sg:phone":"+1 705 788 3188",
    "sg:postcode":"P1H 1H4",
    "sg:province":"ON",
    "sg:tags":[
        "consultant",
        "business"
    ],
    "wof:name":"Kitchen & CO Appraisal Svc",
    "wof:placetype":"venue"
},
  "geometry": {"coordinates":[-79.215858,45.327435],"type":"Point"}
}