{
  "type": "Feature",
  "properties": {
    "iso:country":"CA",
    "sg:address":"1 Royce Ave #19",
    "sg:city":"Orillia",
    "sg:classifiers":[
        {
            "category":"Building & Trades",
            "subcategory":"Construction",
            "type":"Services"
        }
    ],
    "sg:phone":"+1 705 329 1728",
    "sg:postcode":"L3V 5H8",
    "sg:province":"ON",
    "sg:tags":[
        "sewer",
        "contractor"
    ],
    "wof:name":"Orillia Sewer & Water Ltd",
    "wof:placetype":"venue"
},
  "geometry": {"coordinates":[-79.417534,44.603363],"type":"Point"}
}