{
  "type": "Feature",
  "properties": {
    "addr:full":"Montague PE C0A 1R0",
    "addr:postcode":"c0a 1r0",
    "iso:country":"CA",
    "sg:city":"Montague",
    "sg:classifiers":[
        {
            "category":"Retail",
            "subcategory":"Auto Repair",
            "type":"Services"
        }
    ],
    "sg:phone":"+1 902 838 3243",
    "sg:postcode":"C0A 1R0",
    "sg:province":"PE",
    "sg:tags":[
        "body",
        "automobile",
        "painting"
    ],
    "wof:name":"Beck's Auto Body Ltd",
    "wof:placetype":"venue"
},
  "geometry": {"coordinates":[-62.649719,46.167164],"type":"Point"}
}