{
  "type": "Feature",
  "properties": {
    "iso:country":"CA",
    "sg:address":"Dore Lake",
    "sg:city":"Big River",
    "sg:classifiers":[
        {
            "category":"Travel",
            "subcategory":"Hotels & Motels",
            "type":"Entertainment"
        }
    ],
    "sg:phone":"+1 306 832 4511",
    "sg:postcode":"S0J 0E0",
    "sg:province":"SK",
    "sg:tags":[
        "resort"
    ],
    "wof:name":"Dore Lake Lodge",
    "wof:placetype":"venue"
},
  "geometry": {"coordinates":[-107.031936645,53.8341331482],"type":"Point"}
}