{
  "type": "Feature",
  "properties": {
    "addr:full":"112 Broadway W Vancouver BC V5Y 1P3",
    "addr:housenumber":"112",
    "addr:postcode":"v5y 1p3",
    "addr:street":"Broadway W",
    "iso:country":"CA",
    "sg:address":"112 Broadway W",
    "sg:city":"Vancouver",
    "sg:classifiers":[
        {
            "category":"Restaurant",
            "type":"Food & Drink"
        }
    ],
    "sg:phone":"+1 604 875 0055",
    "sg:postcode":"V5Y 1P3",
    "sg:province":"BC",
    "sg:tags":[
        "shop",
        "coffee"
    ],
    "wof:name":"Rino's Cappuccino Bar",
    "wof:placetype":"venue"
},
  "geometry": {"coordinates":[-123.107383728,49.2629394531],"type":"Point"}
}