{
  "type": "Feature",
  "properties": {
    "iso:country":"CA",
    "sg:address":"204 Duncan Dr",
    "sg:city":"Whitehorse",
    "sg:classifiers":[
        {
            "category":"Education",
            "subcategory":"School",
            "type":"Public Place"
        }
    ],
    "sg:phone":"+1 867 667 8130",
    "sg:postcode":"Y1A 7A1",
    "sg:province":"YT",
    "wof:name":"Golden Horn Elementary School",
    "wof:placetype":"venue"
},
  "geometry": {"coordinates":[-135.05316162099999,60.7208709717],"type":"Point"}
}