{
  "type": "Feature",
  "properties": {
    "iso:country":"CA",
    "sg:address":"592 Sheppard Ave W # 521",
    "sg:city":"North York",
    "sg:classifiers":[
        {
            "category":"Banks & Credit Unions",
            "subcategory":"Investment Brokerage",
            "type":"Services"
        }
    ],
    "sg:phone":"+1 416 736 4800",
    "sg:postcode":"M3H 2S1",
    "sg:province":"ON",
    "wof:name":"Americapital",
    "wof:placetype":"venue"
},
  "geometry": {"coordinates":[-79.43915557859999,43.7555198669],"type":"Point"}
}