{
  "type": "Feature",
  "properties": {
    "addr:full":"5124 Morrison St Niagara Falls ON L2E 2E1",
    "addr:housenumber":"5124",
    "addr:postcode":"l2e 2e1",
    "addr:street":"Morrison St",
    "iso:country":"CA",
    "sg:address":"5124 Morrison St",
    "sg:city":"Niagara Falls",
    "sg:classifiers":[
        {
            "category":"Shopping",
            "subcategory":"Discount & Variety Stores",
            "type":"Retail Goods"
        }
    ],
    "sg:phone":"+1 905 357 0069",
    "sg:postcode":"L2E 2E1",
    "sg:province":"ON",
    "wof:name":"Morrison Variety & Grocery",
    "wof:placetype":"venue"
},
  "geometry": {"coordinates":[-79.0783996582,43.104385376],"type":"Point"}
}