{
  "type": "Feature",
  "properties": {
    "addr:full":"RR 4 Kirkfield ON K0M 2B0",
    "addr:postcode":"k0m 2b0",
    "addr:street":"Rr 4 Kirkfield",
    "iso:country":"CA",
    "sg:address":"RR 4",
    "sg:city":"Kirkfield",
    "sg:classifiers":[
        {
            "category":"Building & Trades",
            "subcategory":"Landscaping Services",
            "type":"Services"
        }
    ],
    "sg:phone":"+1 705 438 1119",
    "sg:postcode":"K0M 2B0",
    "sg:province":"ON",
    "sg:tags":[
        "tree"
    ],
    "wof:name":"R G Hill Tree Svc",
    "wof:placetype":"venue"
},
  "geometry": {"coordinates":[-78.979782,44.56274],"type":"Point"}
}