{
  "type": "Feature",
  "properties": {
    "addr:full":"380 Rue Saint-Antoine O Montreal QC H2Y 3X7",
    "addr:housenumber":"380",
    "addr:postcode":"h2y 3x7",
    "addr:street":"Rue Saint-Antoine O",
    "iso:country":"CA",
    "sg:address":"380 Rue Saint-Antoine O",
    "sg:city":"Montreal",
    "sg:classifiers":[
        {
            "category":"Shopping",
            "subcategory":"Pharmacy",
            "type":"Retail Goods"
        }
    ],
    "sg:phone":"+1 514 987 1581",
    "sg:postcode":"H2Y 3X7",
    "sg:province":"QC",
    "wof:name":"Pharmacie Kourdi",
    "wof:placetype":"venue"
},
  "geometry": {"coordinates":[-73.5544128418,45.5108032227],"type":"Point"}
}