{
  "type": "Feature",
  "properties": {
    "addr:full":"RR 5 STN Main Truro NS B2N 5B3",
    "addr:postcode":"b2n 5b3",
    "addr:street":"Rr 5 Stn Main",
    "iso:country":"CA",
    "sg:address":"RR 5 STN Main",
    "sg:city":"Truro",
    "sg:classifiers":[
        {
            "category":"Building & Trades",
            "subcategory":"Construction",
            "type":"Services"
        }
    ],
    "sg:phone":"+1 902 893 2055",
    "sg:postcode":"B2N 5B3",
    "sg:province":"NS",
    "sg:tags":[
        "well",
        "drilling"
    ],
    "wof:name":"Baird's Well Drilling",
    "wof:placetype":"venue"
},
  "geometry": {"coordinates":[-63.28904,45.36602],"type":"Point"}
}