{
  "type": "Feature",
  "properties": {
    "addr:full":"845 Rue Sainte-Pauline Drummondville QC J2B 4X5",
    "addr:housenumber":"845",
    "addr:postcode":"j2b 4x5",
    "addr:street":"Rue Sainte-Pauline",
    "iso:country":"CA",
    "sg:address":"845 Rue Sainte-Pauline",
    "sg:city":"Drummondville",
    "sg:classifiers":[
        {
            "category":"Retail",
            "subcategory":"Laundry & Dry Cleaning",
            "type":"Services"
        }
    ],
    "sg:phone":"+1 819 472 5242",
    "sg:postcode":"J2B 4X5",
    "sg:province":"QC",
    "sg:tags":[
        "cleaners",
        "janitor",
        "rug",
        "carpet"
    ],
    "wof:name":"Pro-Net Drummond",
    "wof:placetype":"venue"
},
  "geometry": {"coordinates":[-72.472145,45.866467],"type":"Point"}
}