{
  "type": "Feature",
  "properties": {
    "addr:full":"43 Portage Ave Fort Smith NT X0E 0P0",
    "addr:housenumber":"43",
    "addr:postcode":"x0e 0p0",
    "addr:street":"Portage Ave",
    "iso:country":"CA",
    "sg:address":"43 Portage Ave",
    "sg:city":"Fort Smith",
    "sg:classifiers":[
        {
            "category":"Travel",
            "subcategory":"Hotels & Motels",
            "type":"Entertainment"
        }
    ],
    "sg:phone":"+1 867 872 2628",
    "sg:postcode":"X0E 0P0",
    "sg:province":"NT",
    "wof:name":"Whispering Pines Cottage",
    "wof:placetype":"venue"
},
  "geometry": {"coordinates":[-111.902633667,60.0000953674],"type":"Point"}
}