{
  "type": "Feature",
  "properties": {
    "iso:country":"CA",
    "sg:address":"1554 Hwy 2",
    "sg:city":"Brookfield",
    "sg:classifiers":[
        {
            "category":"Personal",
            "subcategory":"Beauty Salon",
            "type":"Services"
        }
    ],
    "sg:phone":"+1 902 893 1014",
    "sg:postcode":"B0N 1C0",
    "sg:province":"NS",
    "wof:name":"Hilden Hairways",
    "wof:placetype":"venue"
},
  "geometry": {"coordinates":[-63.279518,45.253689],"type":"Point"}
}