{
  "type": "Feature",
  "properties": {
    "addr:full":"276 Cumberland St N Thunder Bay ON P7A 4N6",
    "addr:housenumber":"276",
    "addr:postcode":"p7a 4n6",
    "addr:street":"Cumberland St N",
    "iso:country":"CA",
    "sg:address":"276 Cumberland St N",
    "sg:city":"Thunder Bay",
    "sg:classifiers":[
        {
            "category":"Restaurant",
            "type":"Food & Drink"
        }
    ],
    "sg:phone":"+1 807 622 2478",
    "sg:postcode":"P7A 4N6",
    "sg:province":"ON",
    "wof:name":"Ling Lee's Gourmet Cuisine",
    "wof:placetype":"venue"
},
  "geometry": {"coordinates":[-89.208611,48.443359],"type":"Point"}
}