{
  "type": "Feature",
  "properties": {
    "addr:full":"Stirling ON K0K 3E0",
    "addr:postcode":"k0k 3e0",
    "iso:country":"CA",
    "sg:city":"Stirling",
    "sg:classifiers":[
        {
            "category":"Home & Garden",
            "subcategory":"Building Materials",
            "type":"Retail Goods"
        }
    ],
    "sg:phone":"+1 613 395 4074",
    "sg:postcode":"K0K 3E0",
    "sg:province":"ON",
    "sg:tags":[
        "door"
    ],
    "wof:name":"Door CO",
    "wof:placetype":"venue"
},
  "geometry": {"coordinates":[-77.55938,44.29319],"type":"Point"}
}