{
  "type": "Feature",
  "properties": {
    "addr:full":"98 Aberdeen St Kentville NS B4N 2N3",
    "addr:housenumber":"98",
    "addr:postcode":"b4n 2n3",
    "addr:street":"Aberdeen St",
    "iso:country":"CA",
    "sg:address":"98 Aberdeen St",
    "sg:city":"Kentville",
    "sg:classifiers":[
        {
            "category":"Autos & Motor Vehicles",
            "subcategory":"Auto Supplies",
            "type":"Retail Goods"
        }
    ],
    "sg:phone":"+1 902 678 3291",
    "sg:postcode":"B4N 2N3",
    "sg:province":"NS",
    "sg:tags":[
        "automobile",
        "parts"
    ],
    "wof:name":"Napa Auto Parts",
    "wof:placetype":"venue"
},
  "geometry": {"coordinates":[-64.496391,45.07856],"type":"Point"}
}