{
  "type": "Feature",
  "properties": {
    "iso:country":"CA",
    "sg:address":"11828 104 Ave NW",
    "sg:city":"Edmonton",
    "sg:classifiers":[
        {
            "category":"Retail",
            "subcategory":"Car Wash",
            "type":"Services"
        }
    ],
    "sg:phone":"+1 780 448 9274",
    "sg:postcode":"T5K 2T8",
    "sg:province":"AB",
    "sg:tags":[
        "polishing",
        "washing"
    ],
    "wof:name":"Bubbles Car Wash & Detail Ctr",
    "wof:placetype":"venue"
},
  "geometry": {"coordinates":[-113.52550506599999,53.5464363098],"type":"Point"}
}