{
  "type": "Feature",
  "properties": {
    "addr:full":"183 Main St E Port Colborne ON L3K 1S5",
    "addr:housenumber":"183",
    "addr:postcode":"l3k 1s5",
    "addr:street":"Main St E",
    "iso:country":"CA",
    "sg:address":"183 Main St E",
    "sg:city":"Port Colborne",
    "sg:classifiers":[
        {
            "category":"Arts & Performance",
            "subcategory":"Theater",
            "type":"Entertainment"
        }
    ],
    "sg:phone":"+1 905 835 1689",
    "sg:postcode":"L3K 1S5",
    "sg:province":"ON",
    "sg:tags":[
        "equipment",
        "lighting",
        "system",
        "theatrical",
        "supply"
    ],
    "wof:name":"Central Lighting",
    "wof:placetype":"venue"
},
  "geometry": {"coordinates":[-79.237061,42.901051],"type":"Point"}
}