{
  "type": "Feature",
  "properties": {
    "iso:country":"CA",
    "sg:city":"Laval",
    "sg:classifiers":[
        {
            "category":"Health Services",
            "subcategory":"Health Practitioner",
            "type":"Services"
        }
    ],
    "sg:phone":"+1 450 973 6019",
    "sg:postcode":"H7T 1A2",
    "sg:province":"QC",
    "sg:tags":[
        "acupuncture"
    ],
    "wof:name":"Acupuncture Du Boulevard",
    "wof:placetype":"venue"
},
  "geometry": {"coordinates":[-73.752586,45.555145],"type":"Point"}
}