{
  "type": "Feature",
  "properties": {
    "iso:country":"CA",
    "sg:address":"48 6th Ave",
    "sg:city":"Hornepayne",
    "sg:classifiers":[
        {
            "category":"Organizations",
            "subcategory":"Professional Association",
            "type":"Services"
        }
    ],
    "sg:phone":"+1 807 868 2083",
    "sg:postcode":"P0M 1Z0",
    "sg:province":"ON",
    "wof:name":"Royal Canadian Legion",
    "wof:placetype":"venue"
},
  "geometry": {"coordinates":[-84.7774505615,49.215045929],"type":"Point"}
}