{
  "type": "Feature",
  "properties": {
    "addr:full":"4630 Lazelle Ave Terrace BC V8G 1S6",
    "addr:housenumber":"4630",
    "addr:postcode":"v8g 1s6",
    "addr:street":"Lazelle Ave",
    "iso:country":"CA",
    "sg:address":"4630 Lazelle Ave",
    "sg:city":"Terrace",
    "sg:classifiers":[
        {
            "category":"Government",
            "subcategory":"Office",
            "type":"Public Place"
        }
    ],
    "sg:phone":"+1 250 635 7134",
    "sg:postcode":"V8G 1S6",
    "sg:province":"BC",
    "wof:name":"Canada Human Resource Ctr",
    "wof:placetype":"venue"
},
  "geometry": {"coordinates":[-128.58941650400001,54.5176429749],"type":"Point"}
}