{
  "type": "Feature",
  "properties": {
    "addr:full":"4780 Boul Henri-Bourassa Charlesbourg QC G1H 3A7",
    "addr:housenumber":"4780",
    "addr:postcode":"g1h 3a7",
    "addr:street":"Boul Henri-Bourassa",
    "iso:country":"CA",
    "sg:address":"4780 Boul Henri-Bourassa",
    "sg:city":"Charlesbourg",
    "sg:classifiers":[
        {
            "category":"Professional",
            "subcategory":"Management & Consulting",
            "type":"Services"
        }
    ],
    "sg:phone":"+1 418 622 6777",
    "sg:postcode":"G1H 3A7",
    "sg:province":"QC",
    "sg:tags":[
        "consultant",
        "automation"
    ],
    "wof:name":"Becterm Inc",
    "wof:placetype":"venue"
},
  "geometry": {"coordinates":[-71.2434997559,46.8500022888],"type":"Point"}
}