{
  "type": "Feature",
  "properties": {
    "iso:country":"CA",
    "sg:city":"Quebec",
    "sg:classifiers":[
        {
            "category":"Education",
            "subcategory":"Dance Studio",
            "type":"Public Place"
        }
    ],
    "sg:phone":"+1 418 649 4715",
    "sg:postcode":"G1K 5N3",
    "sg:province":"QC",
    "sg:tags":[
        "academic",
        "school",
        "instruction",
        "special",
        "dancing"
    ],
    "wof:name":"Ecole DE Danse DE Quebec",
    "wof:placetype":"venue"
},
  "geometry": {"coordinates":[-71.2318115234,46.8129501343],"type":"Point"}
}