{
  "type": "Feature",
  "properties": {
    "addr:full":"143 Bernfield Bay Winnipeg MB R3T 5T9",
    "addr:housenumber":"143",
    "addr:postcode":"r3t 5t9",
    "addr:street":"Bernfield Bay",
    "iso:country":"CA",
    "sg:address":"143 Bernfield Bay",
    "sg:city":"Winnipeg",
    "sg:classifiers":[
        {
            "category":"Professional",
            "subcategory":"Management & Consulting",
            "type":"Services"
        }
    ],
    "sg:phone":"+1 204 269 8176",
    "sg:postcode":"R3T 5T9",
    "sg:province":"MB",
    "sg:tags":[
        "communications",
        "consultant"
    ],
    "wof:name":"Work Communications Ltd",
    "wof:placetype":"venue"
},
  "geometry": {"coordinates":[-97.170547,49.781197],"type":"Point"}
}