{
  "type": "Feature",
  "properties": {
    "addr:full":"120 Progress Crt #2 North Bay ON P1B 8G4",
    "addr:housenumber":"120",
    "addr:postcode":"p1b 8g4",
    "addr:street":"Progress Crt # 2",
    "iso:country":"CA",
    "sg:address":"120 Progress Crt #2",
    "sg:city":"North Bay",
    "sg:classifiers":[
        {
            "category":"Professional",
            "subcategory":"Engineering",
            "type":"Services"
        }
    ],
    "sg:phone":"+1 705 476 2550",
    "sg:postcode":"P1B 8G4",
    "sg:province":"ON",
    "sg:tags":[
        "environmental",
        "ecological",
        "engineer"
    ],
    "wof:name":"Merlex Engineering Ltd",
    "wof:placetype":"venue"
},
  "geometry": {"coordinates":[-79.4272689819,46.3085327148],"type":"Point"}
}