{
  "type": "Feature",
  "properties": {
    "addr:full":"Kitchener ON N2A 1A5",
    "addr:postcode":"n2a 1a5",
    "iso:country":"CA",
    "sg:city":"Kitchener",
    "sg:classifiers":[
        {
            "category":"Travel",
            "subcategory":"Hotels & Motels",
            "type":"Entertainment"
        }
    ],
    "sg:phone":"+1 519 893 6641",
    "sg:postcode":"N2A 1A5",
    "sg:province":"ON",
    "wof:name":"Knights Inn",
    "wof:placetype":"venue"
},
  "geometry": {"coordinates":[-80.4389419556,43.4307861328],"type":"Point"}
}