{
  "type": "Feature",
  "properties": {
    "iso:country":"CA",
    "sg:address":"2 May St",
    "sg:city":"Parry Sound",
    "sg:classifiers":[
        {
            "category":"Health Services",
            "subcategory":"Health Practitioner",
            "type":"Services"
        }
    ],
    "sg:phone":"+1 705 746 5050",
    "sg:postcode":"P2A 1S2",
    "sg:province":"ON",
    "sg:tags":[
        "nurse",
        "registry"
    ],
    "wof:name":"Victorian Order of Nurses",
    "wof:placetype":"venue"
},
  "geometry": {"coordinates":[-80.038422,45.356503],"type":"Point"}
}