{
  "type": "Feature",
  "properties": {
    "addr:full":"Toronto ON M6K 3E3",
    "addr:postcode":"m6k 3e3",
    "iso:country":"CA",
    "sg:city":"Toronto",
    "sg:classifiers":[
        {
            "category":"Manufacturing",
            "subcategory":"Metals",
            "type":"Manufacturing & Wholesale Goods"
        }
    ],
    "sg:phone":"+1 416 531 2775",
    "sg:postcode":"M6K 3E3",
    "sg:province":"ON",
    "sg:tags":[
        "art",
        "casting"
    ],
    "wof:name":"Artcast Inc",
    "wof:placetype":"venue"
},
  "geometry": {"coordinates":[-79.4254074097,43.6380767822],"type":"Point"}
}