{
  "type": "Feature",
  "properties": {
    "iso:country":"CA",
    "sg:city":"Brampton",
    "sg:classifiers":[
        {
            "category":"Professional",
            "subcategory":"Engineering",
            "type":"Services"
        }
    ],
    "sg:phone":"+1 905 458 3452",
    "sg:postcode":"L6S 5N5",
    "sg:province":"ON",
    "sg:tags":[
        "engineer"
    ],
    "wof:name":"Mcpd Consultants Inc",
    "wof:placetype":"venue"
},
  "geometry": {"coordinates":[-79.709961,43.756207],"type":"Point"}
}