{
  "type": "Feature",
  "properties": {
    "addr:full":"15619 112 Ave NW # 200 Edmonton AB T5M 2V8",
    "addr:housenumber":"15619",
    "addr:postcode":"t5m 2v8",
    "addr:street":"112 Ave Nw # 200",
    "iso:country":"CA",
    "sg:address":"15619 112 Ave NW # 200",
    "sg:city":"Edmonton",
    "sg:classifiers":[
        {
            "category":"Real Estate",
            "subcategory":"Real Estate Agent",
            "type":"Services"
        }
    ],
    "sg:phone":"+1 780 451 2760",
    "sg:postcode":"T5M 2V8",
    "sg:province":"AB",
    "sg:tags":[
        "management"
    ],
    "wof:name":"Wunsch Development Ltd",
    "wof:placetype":"venue"
},
  "geometry": {"coordinates":[-113.591064,53.560646],"type":"Point"}
}