{
  "type": "Feature",
  "properties": {
    "addr:full":"962 Rue Saint-Andre Acton Vale QC J0H 1A0",
    "addr:housenumber":"962",
    "addr:postcode":"j0h 1a0",
    "addr:street":"Rue Saint-Andre",
    "iso:country":"CA",
    "sg:address":"962 Rue Saint-Andre",
    "sg:city":"Acton Vale",
    "sg:classifiers":[
        {
            "category":"Manufacturing",
            "subcategory":"Printing",
            "type":"Manufacturing & Wholesale Goods"
        }
    ],
    "sg:phone":"+1 450 546 3271",
    "sg:postcode":"J0H 1A0",
    "sg:province":"QC",
    "sg:tags":[
        "newspaper"
    ],
    "wof:name":"Pensee DE Bagot",
    "wof:placetype":"venue"
},
  "geometry": {"coordinates":[-72.564278,45.648167],"type":"Point"}
}