{
  "type": "Feature",
  "properties": {
    "addr:full":"232 Drouillard Rd Windsor ON N8Y 2P3",
    "addr:housenumber":"232",
    "addr:postcode":"n8y 2p3",
    "addr:street":"Drouillard Rd",
    "iso:country":"CA",
    "sg:address":"232 Drouillard Rd",
    "sg:city":"Windsor",
    "sg:classifiers":[
        {
            "category":"Professional",
            "subcategory":"Engineering",
            "type":"Services"
        }
    ],
    "sg:phone":"+1 519 255 9322",
    "sg:postcode":"N8Y 2P3",
    "sg:province":"ON",
    "sg:tags":[
        "engineer"
    ],
    "wof:name":"Pouti Engineering Inc",
    "wof:placetype":"venue"
},
  "geometry": {"coordinates":[-83.002724,42.32597],"type":"Point"}
}