{
  "type": "Feature",
  "properties": {
    "addr:full":"Calgary AB T2A 1X2",
    "addr:postcode":"t2a 1x2",
    "iso:country":"CA",
    "sg:city":"Calgary",
    "sg:classifiers":[
        {
            "category":"Wholesale",
            "subcategory":"Machinery & Supplies",
            "type":"Manufacturing & Wholesale Goods"
        }
    ],
    "sg:phone":"+1 403 299 0333",
    "sg:postcode":"T2A 1X2",
    "sg:province":"AB",
    "sg:tags":[
        "beauty",
        "fence"
    ],
    "wof:name":"Myric Electronics Ltd",
    "wof:placetype":"venue"
},
  "geometry": {"coordinates":[-114.000893,51.05085],"type":"Point"}
}