{
  "type": "Feature",
  "properties": {
    "addr:full":"100 Mile House BC V0K 2E2",
    "addr:postcode":"v0k 2e2",
    "iso:country":"CA",
    "sg:city":"100 Mile House",
    "sg:classifiers":[
        {
            "category":"Manufacturing",
            "subcategory":"Buildings",
            "type":"Manufacturing & Wholesale Goods"
        }
    ],
    "sg:phone":"+1 250 395 8881",
    "sg:postcode":"V0K 2E2",
    "sg:province":"BC",
    "sg:tags":[
        "home",
        "log",
        "cabin"
    ],
    "wof:name":"Calija Log & Timber Homes Ltd",
    "wof:placetype":"venue"
},
  "geometry": {"coordinates":[-121.334839,51.577568],"type":"Point"}
}