{
  "type": "Feature",
  "properties": {
    "iso:country":"CA",
    "sg:address":"12 Gleneyre St # 305",
    "sg:city":"St. John's",
    "sg:classifiers":[
        {
            "category":"Health Services",
            "subcategory":"Doctor",
            "type":"Services"
        }
    ],
    "sg:phone":"+1 709 726 5025",
    "sg:postcode":"A1A 2M7",
    "sg:province":"NL",
    "sg:tags":[
        "dentist"
    ],
    "wof:name":"Furlong, Robert M DDS",
    "wof:placetype":"venue"
},
  "geometry": {"coordinates":[-52.7125511169,47.6019592285],"type":"Point"}
}