{
  "type": "Feature",
  "properties": {
    "addr:full":"1445 Lewisham Dr Mississauga ON L5J 3R2",
    "addr:housenumber":"1445",
    "addr:postcode":"l5j 3r2",
    "addr:street":"Lewisham Dr",
    "iso:country":"CA",
    "sg:address":"1445 Lewisham Dr",
    "sg:city":"Mississauga",
    "sg:classifiers":[
        {
            "category":"Education",
            "subcategory":"School",
            "type":"Public Place"
        }
    ],
    "sg:phone":"+1 905 450 1106",
    "sg:postcode":"L5J 3R2",
    "sg:province":"ON",
    "wof:name":"Ecole Elementaire DE Langue",
    "wof:placetype":"venue"
},
  "geometry": {"coordinates":[-79.645073,43.516281],"type":"Point"}
}