{
  "type": "Feature",
  "properties": {
    "addr:full":"180 Rue DE Florimont Mont-Saint-Hilaire QC J3H 4C5",
    "addr:housenumber":"180",
    "addr:postcode":"j3h 4c5",
    "addr:street":"Rue De Florimont",
    "iso:country":"CA",
    "sg:address":"180 Rue DE Florimont",
    "sg:city":"Mont-Saint-Hilaire",
    "sg:classifiers":[
        {
            "category":"Professional",
            "subcategory":"Engineering",
            "type":"Services"
        }
    ],
    "sg:phone":"+1 450 446 5229",
    "sg:postcode":"J3H 4C5",
    "sg:province":"QC",
    "sg:tags":[
        "engineer"
    ],
    "wof:name":"Integra Process Inc",
    "wof:placetype":"venue"
},
  "geometry": {"coordinates":[-73.18338775629999,45.5862579346],"type":"Point"}
}