{
  "type": "Feature",
  "properties": {
    "addr:full":"Falcon Beach MB R0E 0N0",
    "addr:postcode":"r0e 0n0",
    "addr:street":"Falcon",
    "iso:country":"CA",
    "sg:city":"Falcon Beach",
    "sg:classifiers":[
        {
            "category":"Cinema",
            "subcategory":"Movie Rental",
            "type":"Entertainment"
        }
    ],
    "sg:phone":"+1 204 349 8030",
    "sg:postcode":"R0E 0N0",
    "sg:province":"MB",
    "sg:tags":[
        "video",
        "game",
        "leasing"
    ],
    "wof:name":"Falcon Video & Treats",
    "wof:placetype":"venue"
},
  "geometry": {"coordinates":[-95.33103199999999,49.683666],"type":"Point"}
}