{
  "type": "Feature",
  "properties": {
    "iso:country":"CA",
    "sg:address":"3651 Rue Monselet",
    "sg:city":"Montreal-Nord",
    "sg:classifiers":[
        {
            "category":"Shopping",
            "subcategory":"Pharmacy",
            "type":"Retail Goods"
        }
    ],
    "sg:phone":"+1 514 321 5880",
    "sg:postcode":"H1H 2B1",
    "sg:province":"QC",
    "wof:name":"Pharmacie Michel Cote",
    "wof:placetype":"venue"
},
  "geometry": {"coordinates":[-73.64282989500001,45.5869827271],"type":"Point"}
}