{
  "type": "Feature",
  "properties": {
    "iso:country":"CA",
    "sg:address":"2366 Ch Royal",
    "sg:city":"Saint-Jean-D'Orleans",
    "sg:classifiers":[
        {
            "category":"Manufacturing",
            "subcategory":"Food",
            "type":"Manufacturing & Wholesale Goods"
        }
    ],
    "sg:phone":"+1 418 829 0450",
    "sg:postcode":"G0A 3W0",
    "sg:province":"QC",
    "sg:tags":[
        "preserves",
        "jam",
        "jelly"
    ],
    "wof:name":"Saveurs DE L'Isle D'Orleans",
    "wof:placetype":"venue"
},
  "geometry": {"coordinates":[-70.8869857788,46.9260597229],"type":"Point"}
}