{
  "type": "Feature",
  "properties": {
    "addr:full":"150 Commercial Pl Penticton BC V2A 3H7",
    "addr:housenumber":"150",
    "addr:postcode":"v2a 3h7",
    "addr:street":"Commercial Pl",
    "iso:country":"CA",
    "sg:address":"150 Commercial Pl",
    "sg:city":"Penticton",
    "sg:classifiers":[
        {
            "category":"Building & Trades",
            "subcategory":"Construction",
            "type":"Services"
        }
    ],
    "sg:phone":"+1 250 493 1369",
    "sg:postcode":"V2A 3H7",
    "sg:province":"BC",
    "sg:tags":[
        "contractor",
        "general"
    ],
    "wof:name":"J Forsyth Contracting Ltd",
    "wof:placetype":"venue"
},
  "geometry": {"coordinates":[-119.56186676,49.480091095],"type":"Point"}
}