{
  "type": "Feature",
  "properties": {
    "iso:country":"CA",
    "sg:address":"Highway 914",
    "sg:city":"Pinehouse Lake",
    "sg:classifiers":[
        {
            "category":"Government",
            "subcategory":"Office",
            "type":"Public Place"
        }
    ],
    "sg:phone":"+1 306 884 2410",
    "sg:postcode":"S0J 2B0",
    "sg:province":"SK",
    "wof:name":"Sask Highway & Transportation",
    "wof:placetype":"venue"
},
  "geometry": {"coordinates":[-106.618476868,55.5082702637],"type":"Point"}
}