{
  "type": "Feature",
  "properties": {
    "addr:full":"250 Ch DE LA Riviere Saint-Mathieu-Du-Parc QC G0X 1N0",
    "addr:housenumber":"250",
    "addr:postcode":"g0x 1n0",
    "addr:street":"Ch De La Riviere",
    "iso:country":"CA",
    "sg:address":"250 Ch DE LA Riviere",
    "sg:city":"Saint-Mathieu-Du-Parc",
    "sg:classifiers":[
        {
            "category":"Building & Trades",
            "subcategory":"Landscaping Services",
            "type":"Services"
        }
    ],
    "sg:phone":"+1 819 532 3022",
    "sg:postcode":"G0X 1N0",
    "sg:province":"QC",
    "sg:tags":[
        "tree",
        "landscape",
        "contractor"
    ],
    "wof:name":"Service D'Arboriculture Serge",
    "wof:placetype":"venue"
},
  "geometry": {"coordinates":[-72.924637,46.611919],"type":"Point"}
}