{
  "type": "Feature",
  "properties": {
    "addr:full":"172 Angeline St N Lindsay ON K9V 4X2",
    "addr:housenumber":"172",
    "addr:postcode":"k9v 4x2",
    "addr:street":"Angeline St N",
    "iso:country":"CA",
    "sg:address":"172 Angeline St N",
    "sg:city":"Lindsay",
    "sg:classifiers":[
        {
            "category":"Food & Beverages",
            "subcategory":"Groceries & Convenience Stores",
            "type":"Retail Goods"
        }
    ],
    "sg:phone":"+1 705 324 3271",
    "sg:postcode":"K9V 4X2",
    "sg:province":"ON",
    "wof:name":"Mac's Convenience Stores Ltd",
    "wof:placetype":"venue"
},
  "geometry": {"coordinates":[-78.756516,44.36348],"type":"Point"}
}