{
  "type": "Feature",
  "properties": {
    "addr:full":"Otherside Bay Fond Du Lac SK S0J 0W0",
    "addr:postcode":"s0j 0w0",
    "iso:country":"CA",
    "sg:address":"Otherside Bay",
    "sg:city":"Fond Du Lac",
    "sg:classifiers":[
        {
            "category":"Recreation",
            "type":"Entertainment"
        }
    ],
    "sg:phone":"+1 306 686 2020",
    "sg:postcode":"S0J 0W0",
    "sg:province":"SK",
    "sg:tags":[
        "party",
        "fishing"
    ],
    "wof:name":"Athabasca Fishing Lodges",
    "wof:placetype":"venue"
},
  "geometry": {"coordinates":[-107.187569,59.327782],"type":"Point"}
}