{
  "type": "Feature",
  "properties": {
    "iso:country":"CA",
    "sg:city":"Houston",
    "sg:classifiers":[
        {
            "category":"Personal",
            "subcategory":"Barber",
            "type":"Services"
        }
    ],
    "sg:phone":"+1 250 845 2329",
    "sg:postcode":"V0J 1Z0",
    "sg:province":"BC",
    "wof:name":"Houston Barber Shop",
    "wof:placetype":"venue"
},
  "geometry": {"coordinates":[-126.647148132,54.400352478],"type":"Point"}
}