{
  "type": "Feature",
  "properties": {
    "addr:full":"3773 Boul DE LA Cote-Vertu # 350 Saint-Laurent QC H4R 2M3",
    "addr:housenumber":"3773",
    "addr:postcode":"h4r 2m3",
    "addr:street":"Boul De La Cote-Vertu # 350",
    "iso:country":"CA",
    "sg:address":"3773 Boul DE LA Cote-Vertu # 350",
    "sg:city":"Saint-Laurent",
    "sg:classifiers":[
        {
            "category":"Professional",
            "subcategory":"Accounting & Tax Preparation",
            "type":"Services"
        }
    ],
    "sg:phone":"+1 514 334 7171",
    "sg:postcode":"H4R 2M3",
    "sg:province":"QC",
    "sg:tags":[
        "accountant"
    ],
    "wof:name":"Levine, Howard CA",
    "wof:placetype":"venue"
},
  "geometry": {"coordinates":[-73.710067749,45.4928321838],"type":"Point"}
}