{
  "type": "Feature",
  "properties": {
    "addr:full":"L'Annonciation QC J0T 1T0",
    "addr:postcode":"j0t 1t0",
    "iso:country":"CA",
    "sg:city":"L'Annonciation",
    "sg:classifiers":[
        {
            "category":"Recreation",
            "type":"Entertainment"
        }
    ],
    "sg:phone":"+1 819 275 2987",
    "sg:postcode":"J0T 1T0",
    "sg:province":"QC",
    "sg:tags":[
        "government",
        "swimming"
    ],
    "wof:name":"L'Annonciation Piscine Mncpl",
    "wof:placetype":"venue"
},
  "geometry": {"coordinates":[-74.830581665,46.5512962341],"type":"Point"}
}