{
  "type": "Feature",
  "properties": {
    "addr:full":"Chateauguay QC J6K 3M3",
    "addr:postcode":"j6k 3m3",
    "iso:country":"CA",
    "sg:city":"Chateauguay",
    "sg:classifiers":[
        {
            "category":"Restaurant",
            "type":"Food & Drink"
        }
    ],
    "sg:phone":"+1 450 691 2227",
    "sg:postcode":"J6K 3M3",
    "sg:province":"QC",
    "wof:name":"Resto Jr",
    "wof:placetype":"venue"
},
  "geometry": {"coordinates":[-73.740196,45.361156],"type":"Point"}
}