{
  "type": "Feature",
  "properties": {
    "addr:full":"101 Hwy 55 Main St Debden SK S0J 0S0",
    "addr:housenumber":"101",
    "addr:postcode":"s0j 0s0",
    "addr:street":"Hwy 55 Main St",
    "iso:country":"CA",
    "sg:address":"101 Hwy 55 Main St",
    "sg:city":"Debden",
    "sg:classifiers":[
        {
            "category":"Restaurant",
            "type":"Food & Drink"
        }
    ],
    "sg:phone":"+1 306 724 2035",
    "sg:postcode":"S0J 0S0",
    "sg:province":"SK",
    "wof:name":"Imperial Oil",
    "wof:placetype":"venue"
},
  "geometry": {"coordinates":[-106.878227,53.527225],"type":"Point"}
}