{
  "type": "Feature",
  "properties": {
    "iso:country":"CA",
    "sg:city":"Ottawa",
    "sg:classifiers":[
        {
            "category":"Health Services",
            "subcategory":"Doctor",
            "type":"Services"
        }
    ],
    "sg:phone":"+1 613 733 5866",
    "sg:postcode":"K1H 1A2",
    "sg:province":"ON",
    "sg:tags":[
        "physician",
        "surgeon"
    ],
    "wof:name":"Smith, Gerald D MD",
    "wof:placetype":"venue"
},
  "geometry": {"coordinates":[-75.6698379517,45.3970565796],"type":"Point"}
}