{
  "type": "Feature",
  "properties": {
    "addr:full":"148 Green St Lunenburg NS B0J 2C0",
    "addr:housenumber":"148",
    "addr:postcode":"b0j 2c0",
    "addr:street":"Green St",
    "iso:country":"CA",
    "sg:address":"148 Green St",
    "sg:city":"Lunenburg",
    "sg:classifiers":[
        {
            "category":"Shopping",
            "subcategory":"Computers & Home Electronics",
            "type":"Retail Goods"
        }
    ],
    "sg:phone":"+1 902 634 3832",
    "sg:postcode":"B0J 2C0",
    "sg:province":"NS",
    "sg:tags":[
        "software"
    ],
    "wof:name":"High Performance Software Eng",
    "wof:placetype":"venue"
},
  "geometry": {"coordinates":[-64.32524100000001,44.379944],"type":"Point"}
}