{
  "type": "Feature",
  "properties": {
    "addr:full":"12880 96 Ave Surrey BC V3V 6A8",
    "addr:housenumber":"12880",
    "addr:postcode":"v3v 6a8",
    "addr:street":"96 Ave",
    "iso:country":"CA",
    "sg:address":"12880 96 Ave",
    "sg:city":"Surrey",
    "sg:classifiers":[
        {
            "category":"Home & Garden",
            "subcategory":"Home Furnishings",
            "type":"Retail Goods"
        }
    ],
    "sg:phone":"+1 604 584 0616",
    "sg:postcode":"V3V 6A8",
    "sg:province":"BC",
    "sg:tags":[
        "housewares"
    ],
    "wof:name":"Dollar Plus Hardware",
    "wof:placetype":"venue"
},
  "geometry": {"coordinates":[-122.86597399999999,49.177044],"type":"Point"}
}