{
  "type": "Feature",
  "properties": {
    "addr:full":"3530 Derry Rd E # 108 Mississauga ON L4T 4E3",
    "addr:housenumber":"3530",
    "addr:postcode":"l4t 4e3",
    "addr:street":"Derry Rd E # 108",
    "iso:country":"CA",
    "sg:address":"3530 Derry Rd E # 108",
    "sg:city":"Mississauga",
    "sg:classifiers":[
        {
            "category":"Health Services",
            "subcategory":"Doctor",
            "type":"Services"
        }
    ],
    "sg:phone":"+1 905 678 7324",
    "sg:postcode":"L4T 4E3",
    "sg:province":"ON",
    "sg:tags":[
        "physician",
        "surgeon"
    ],
    "wof:name":"Pandhi, H M MD",
    "wof:placetype":"venue"
},
  "geometry": {"coordinates":[-79.630539,43.714283],"type":"Point"}
}