{
  "type": "Feature",
  "properties": {
    "iso:country":"CA",
    "sg:address":"682 Rue Kirouac",
    "sg:city":"Quebec",
    "sg:classifiers":[
        {
            "category":"Professional",
            "subcategory":"Business Services",
            "type":"Services"
        }
    ],
    "sg:phone":"+1 418 683 0401",
    "sg:postcode":"G1N 2J2",
    "sg:province":"QC",
    "sg:tags":[
        "embroidery"
    ],
    "wof:name":"Broderies Spectra",
    "wof:placetype":"venue"
},
  "geometry": {"coordinates":[-71.24090576170001,46.8050079346],"type":"Point"}
}