{
  "type": "Feature",
  "properties": {
    "iso:country":"CA",
    "sg:city":"Saint-Colomban",
    "sg:classifiers":[
        {
            "category":"Retail",
            "subcategory":"Repair Shop",
            "type":"Services"
        }
    ],
    "sg:phone":"+1 450 569 8258",
    "sg:postcode":"J5K 2N4",
    "sg:province":"QC",
    "sg:tags":[
        "welding"
    ],
    "wof:name":"Fabri-Plus",
    "wof:placetype":"venue"
},
  "geometry": {"coordinates":[-74.1488494873,45.7244033813],"type":"Point"}
}