{
  "type": "Feature",
  "properties": {
    "addr:full":"2700 Boul Laurier Sainte-Foy QC G1V 2L8",
    "addr:housenumber":"2700",
    "addr:postcode":"g1v 2l8",
    "addr:street":"Boul Laurier",
    "iso:country":"CA",
    "sg:address":"2700 Boul Laurier",
    "sg:city":"Sainte-Foy",
    "sg:classifiers":[
        {
            "category":"Home & Garden",
            "subcategory":"Home Furnishings",
            "type":"Retail Goods"
        }
    ],
    "sg:phone":"+1 418 653 5878",
    "sg:postcode":"G1V 2L8",
    "sg:province":"QC",
    "sg:tags":[
        "kitchen",
        "accessory"
    ],
    "wof:name":"Pom-Pom Inc",
    "wof:placetype":"venue"
},
  "geometry": {"coordinates":[-71.28407300000001,46.769676],"type":"Point"}
}