{
  "type": "Feature",
  "properties": {
    "addr:full":"44140 Luckakuck Way Chilliwack BC V2R 4A7",
    "addr:postcode":"44140;v2r 4a7",
    "addr:street":"Luckakuck Way",
    "iso:country":"CA",
    "sg:address":"44140 Luckakuck Way",
    "sg:city":"Chilliwack",
    "sg:classifiers":[
        {
            "category":"Recreation",
            "type":"Entertainment"
        }
    ],
    "sg:phone":"+1 604 824 9927",
    "sg:postcode":"V2R 4A7",
    "sg:province":"BC",
    "sg:tags":[
        "convention",
        "meeting",
        "amusement",
        "facility"
    ],
    "wof:name":"Chilliwack Heritage Park",
    "wof:placetype":"venue"
},
  "geometry": {"coordinates":[-122.003883,49.143734],"type":"Point"}
}