{
  "type": "Feature",
  "properties": {
    "iso:country":"CA",
    "sg:address":"66 Wellington St",
    "sg:city":"Toronto",
    "sg:classifiers":[
        {
            "category":"Building & Trades",
            "subcategory":"Electrical",
            "type":"Services"
        }
    ],
    "sg:phone":"+1 416 362 3051",
    "sg:postcode":"M5K 1G8",
    "sg:province":"ON",
    "sg:tags":[
        "electric",
        "contractor"
    ],
    "wof:name":"Tenant Electric Svc",
    "wof:placetype":"venue"
},
  "geometry": {"coordinates":[-79.3743362427,43.648639679],"type":"Point"}
}