{
  "type": "Feature",
  "properties": {
    "addr:full":"229 Churchill Blvd Saint John NB E2K 3E2",
    "addr:housenumber":"229",
    "addr:postcode":"e2k 3e2",
    "addr:street":"Churchill Blvd",
    "iso:country":"CA",
    "sg:address":"229 Churchill Blvd",
    "sg:city":"Saint John",
    "sg:classifiers":[
        {
            "category":"Insurance",
            "subcategory":"Insurance Agent",
            "type":"Services"
        }
    ],
    "sg:phone":"+1 506 642 7375",
    "sg:postcode":"E2K 3E2",
    "sg:province":"NB",
    "wof:name":"Primerica Financial Svc",
    "wof:placetype":"venue"
},
  "geometry": {"coordinates":[-66.078873,45.285774],"type":"Point"}
}