{
  "type": "Feature",
  "properties": {
    "addr:full":"115 George St Enderby BC V0E 1V0",
    "addr:housenumber":"115",
    "addr:postcode":"v0e 1v0",
    "addr:street":"George St",
    "iso:country":"CA",
    "sg:address":"115 George St",
    "sg:city":"Enderby",
    "sg:classifiers":[
        {
            "category":"Organizations",
            "subcategory":"Religious Organization",
            "type":"Services"
        }
    ],
    "sg:phone":"+1 250 838 2400",
    "sg:postcode":"V0E 1V0",
    "sg:province":"BC",
    "sg:tags":[
        "church"
    ],
    "wof:name":"Jehovah's Witnesses",
    "wof:placetype":"venue"
},
  "geometry": {"coordinates":[-119.140091,50.543537],"type":"Point"}
}