{
  "type": "Feature",
  "properties": {
    "addr:full":"538 Gordon Baker Rd North York ON M2H 3B4",
    "addr:housenumber":"538",
    "addr:postcode":"m2h 3b4",
    "addr:street":"Gordon Baker Rd",
    "iso:country":"CA",
    "sg:address":"538 Gordon Baker Rd",
    "sg:city":"North York",
    "sg:classifiers":[
        {
            "category":"Building & Trades",
            "subcategory":"Construction",
            "type":"Services"
        }
    ],
    "sg:phone":"+1 416 498 4447",
    "sg:postcode":"M2H 3B4",
    "sg:province":"ON",
    "sg:tags":[
        "general",
        "contractor"
    ],
    "wof:name":"Images Restoration Inc",
    "wof:placetype":"venue"
},
  "geometry": {"coordinates":[-79.34591674799999,43.808052063],"type":"Point"}
}