{
  "type": "Feature",
  "properties": {
    "addr:full":"170 Bloor St W Toronto ON M5S 1T9",
    "addr:housenumber":"170",
    "addr:postcode":"m5s 1t9",
    "addr:street":"Bloor St W",
    "iso:country":"CA",
    "sg:address":"170 Bloor St W",
    "sg:city":"Toronto",
    "sg:classifiers":[
        {
            "category":"Health Services",
            "subcategory":"Doctor",
            "type":"Services"
        }
    ],
    "sg:phone":"+1 416 925 0804",
    "sg:postcode":"M5S 1T9",
    "sg:province":"ON",
    "sg:tags":[
        "physician",
        "surgeon"
    ],
    "wof:name":"Gilbert, Barry L MD",
    "wof:placetype":"venue"
},
  "geometry": {"coordinates":[-79.394699,43.668728],"type":"Point"}
}