{
  "type": "Feature",
  "properties": {
    "addr:full":"Mission BC V2V 1G3",
    "addr:postcode":"v2v 1g3",
    "iso:country":"CA",
    "sg:city":"Mission",
    "sg:classifiers":[
        {
            "category":"Real Estate",
            "subcategory":"Real Estate Agent",
            "type":"Services"
        }
    ],
    "sg:phone":"+1 604 826 3674",
    "sg:postcode":"V2V 1G3",
    "sg:province":"BC",
    "wof:name":"Royal Le Page Fraser Valley",
    "wof:placetype":"venue"
},
  "geometry": {"coordinates":[-122.282822,49.159988],"type":"Point"}
}