{
  "type": "Feature",
  "properties": {
    "addr:full":"Moncton NB E1C 6L9",
    "addr:postcode":"e1c 6l9",
    "iso:country":"CA",
    "sg:city":"Moncton",
    "sg:classifiers":[
        {
            "category":"Organizations",
            "subcategory":"Labor Organization",
            "type":"Services"
        }
    ],
    "sg:phone":"+1 506 858 5891",
    "sg:postcode":"E1C 6L9",
    "sg:province":"NB",
    "wof:name":"Canadian Union-Postal Workers",
    "wof:placetype":"venue"
},
  "geometry": {"coordinates":[-64.79568500000001,46.095299],"type":"Point"}
}