{
  "type": "Feature",
  "properties": {
    "addr:full":"7625 104 St NW Edmonton AB T6E 4C3",
    "addr:housenumber":"7625",
    "addr:postcode":"t6e 4c3",
    "addr:street":"104 St Nw",
    "iso:country":"CA",
    "sg:address":"7625 104 St NW",
    "sg:city":"Edmonton",
    "sg:classifiers":[
        {
            "category":"Retail",
            "subcategory":"Laundry & Dry Cleaning",
            "type":"Services"
        }
    ],
    "sg:phone":"+1 780 433 5411",
    "sg:postcode":"T6E 4C3",
    "sg:province":"AB",
    "sg:tags":[
        "cleaners"
    ],
    "wof:name":"Leader Dry Cleaners",
    "wof:placetype":"venue"
},
  "geometry": {"coordinates":[-113.497238,53.512634],"type":"Point"}
}