{
  "type": "Feature",
  "properties": {
    "iso:country":"CA",
    "sg:city":"Brossard",
    "sg:classifiers":[
        {
            "category":"Food & Beverages",
            "subcategory":"Specialty",
            "type":"Retail Goods"
        }
    ],
    "sg:phone":"+1 450 659 9737",
    "sg:postcode":"J4Y 2R2",
    "sg:province":"QC",
    "wof:name":"Produits Naturels Leblanc",
    "wof:placetype":"venue"
},
  "geometry": {"coordinates":[-73.464684,45.428581],"type":"Point"}
}