{
  "type": "Feature",
  "properties": {
    "addr:full":"204 Rte Principale Saint-Jean-DE-Matha QC J0K 2S0",
    "addr:housenumber":"204",
    "addr:postcode":"j0k 2s0",
    "addr:street":"Rte Principale",
    "iso:country":"CA",
    "sg:address":"204 Rte Principale",
    "sg:city":"Saint-Jean-DE-Matha",
    "sg:classifiers":[
        {
            "category":"Health Services",
            "subcategory":"Optometrist",
            "type":"Services"
        }
    ],
    "sg:phone":"+1 450 886 5337",
    "sg:postcode":"J0K 2S0",
    "sg:province":"QC",
    "wof:name":"Lunnetterie Joliette",
    "wof:placetype":"venue"
},
  "geometry": {"coordinates":[-73.52838897709999,46.2255744934],"type":"Point"}
}