{
  "type": "Feature",
  "properties": {
    "addr:full":"2210 Av Charland Montreal QC H1Z 1B4",
    "addr:housenumber":"2210",
    "addr:postcode":"h1z 1b4",
    "addr:street":"Av Charland",
    "iso:country":"CA",
    "sg:address":"2210 Av Charland",
    "sg:city":"Montreal",
    "sg:classifiers":[
        {
            "category":"Retail",
            "subcategory":"Auto Repair",
            "type":"Services"
        }
    ],
    "sg:phone":"+1 514 381 0613",
    "sg:postcode":"H1Z 1B4",
    "sg:province":"QC",
    "sg:tags":[
        "repairing",
        "automobile"
    ],
    "wof:name":"Gestions Luc Bougie Inc",
    "wof:placetype":"venue"
},
  "geometry": {"coordinates":[-73.6409835815,45.5689086914],"type":"Point"}
}