{
  "type": "Feature",
  "properties": {
    "addr:full":"40 Rue Saint-Joseph Sainte-Therese QC J7E 3L6",
    "addr:housenumber":"40",
    "addr:postcode":"j7e 3l6",
    "addr:street":"Rue Saint-Joseph Sainte-Therese",
    "iso:country":"CA",
    "sg:address":"40 Rue Saint-Joseph",
    "sg:city":"Sainte-Therese",
    "sg:classifiers":[
        {
            "category":"Shopping",
            "subcategory":"Books",
            "type":"Retail Goods"
        }
    ],
    "sg:phone":"+1 450 435 0581",
    "sg:postcode":"J7E 3L6",
    "sg:province":"QC",
    "sg:tags":[
        "dealer"
    ],
    "wof:name":"Mercier Librairie",
    "wof:placetype":"venue"
},
  "geometry": {"coordinates":[-73.84307861329999,45.6384735107],"type":"Point"}
}