{
  "type": "Feature",
  "properties": {
    "addr:full":"2105 8th St E Saskatoon SK S7H 0T8",
    "addr:housenumber":"2105",
    "addr:postcode":"s7h 0t8",
    "addr:street":"8Th St E",
    "iso:country":"CA",
    "sg:address":"2105 8th St E",
    "sg:city":"Saskatoon",
    "sg:classifiers":[
        {
            "category":"Shopping",
            "subcategory":"Pharmacy",
            "type":"Retail Goods"
        }
    ],
    "sg:phone":"+1 306 374 4888",
    "sg:postcode":"S7H 0T8",
    "sg:province":"SK",
    "wof:name":"Shoppers Drug Mart",
    "wof:placetype":"venue"
},
  "geometry": {"coordinates":[-106.62412261999999,52.115032196],"type":"Point"}
}