{
  "type": "Feature",
  "properties": {
    "addr:full":"340 Rue Principale Batiscan QC G0X 1A0",
    "addr:housenumber":"340",
    "addr:postcode":"g0x 1a0",
    "addr:street":"Rue Principale",
    "iso:country":"CA",
    "sg:address":"340 Rue Principale",
    "sg:city":"Batiscan",
    "sg:classifiers":[
        {
            "category":"Museum",
            "type":"Entertainment"
        }
    ],
    "sg:phone":"+1 418 362 2051",
    "sg:postcode":"G0X 1A0",
    "sg:province":"QC",
    "wof:name":"Vieux Presbytere DE Batiscan",
    "wof:placetype":"venue"
},
  "geometry": {"coordinates":[-72.2597732544,46.4825401306],"type":"Point"}
}