{
  "type": "Feature",
  "properties": {
    "addr:full":"19551 Lougheed Hwy Pitt Meadows BC V3Y 2J5",
    "addr:housenumber":"19551",
    "addr:postcode":"v3y 2j5",
    "addr:street":"Lougheed Hwy",
    "iso:country":"CA",
    "sg:address":"19551 Lougheed Hwy",
    "sg:city":"Pitt Meadows",
    "sg:classifiers":[
        {
            "category":"Manufacturing",
            "subcategory":"Metals",
            "type":"Manufacturing & Wholesale Goods"
        }
    ],
    "sg:phone":"+1 604 644 6207",
    "sg:postcode":"V3Y 2J5",
    "sg:province":"BC",
    "sg:tags":[
        "concrete",
        "reinforcement"
    ],
    "wof:name":"D & J Reinforcing Steel Ltd",
    "wof:placetype":"venue"
},
  "geometry": {"coordinates":[-122.681297302,49.2280464172],"type":"Point"}
}