{
  "type": "Feature",
  "properties": {
    "addr:full":"Norris Point NL A0K 3V0",
    "addr:postcode":"a0k 3v0",
    "addr:street":"Norris",
    "iso:country":"CA",
    "sg:city":"Norris Point",
    "sg:classifiers":[
        {
            "category":"Travel",
            "subcategory":"Hotels & Motels",
            "type":"Entertainment"
        }
    ],
    "sg:phone":"+1 709 458 2773",
    "sg:postcode":"A0K 3V0",
    "sg:province":"NL",
    "sg:tags":[
        "breakfast",
        "accommodation",
        "bed"
    ],
    "wof:name":"Neil's Bed & Breakfast",
    "wof:placetype":"venue"
},
  "geometry": {"coordinates":[-57.875305,49.5317],"type":"Point"}
}