{
  "type": "Feature",
  "properties": {
    "addr:full":"30 Prince William St E St Stephen NB E3L 1S1",
    "addr:housenumber":"30",
    "addr:postcode":"e3l 1s1",
    "addr:street":"Prince William St E",
    "iso:country":"CA",
    "sg:address":"30 Prince William St E",
    "sg:city":"St Stephen",
    "sg:classifiers":[
        {
            "category":"Organizations",
            "subcategory":"Religious Organization",
            "type":"Services"
        }
    ],
    "sg:phone":"+1 506 465 8486",
    "sg:postcode":"E3L 1S1",
    "sg:province":"NB",
    "sg:tags":[
        "church"
    ],
    "wof:name":"Anglican Church",
    "wof:placetype":"venue"
},
  "geometry": {"coordinates":[-67.2716751099,45.1937141418],"type":"Point"}
}