{
  "type": "Feature",
  "properties": {
    "addr:full":"15 Talbot St E Wheatley ON N0P 2P0",
    "addr:housenumber":"15",
    "addr:postcode":"n0p 2p0",
    "addr:street":"Talbot St E",
    "iso:country":"CA",
    "sg:address":"15 Talbot St E",
    "sg:city":"Wheatley",
    "sg:classifiers":[
        {
            "category":"Restaurant",
            "type":"Food & Drink"
        }
    ],
    "sg:phone":"+1 519 825 9225",
    "sg:postcode":"N0P 2P0",
    "sg:province":"ON",
    "wof:name":"Maria's Pizza",
    "wof:placetype":"venue"
},
  "geometry": {"coordinates":[-82.46230300000001,42.09531],"type":"Point"}
}