{
  "type": "Feature",
  "properties": {
    "iso:country":"CA",
    "sg:address":"1635 Sismet Rd",
    "sg:city":"Mississauga",
    "sg:classifiers":[
        {
            "category":"Retail",
            "subcategory":"Auto Repair",
            "type":"Services"
        }
    ],
    "sg:phone":"+1 905 212 7551",
    "sg:postcode":"L4W 1W5",
    "sg:province":"ON",
    "sg:tags":[
        "repairing",
        "automobile"
    ],
    "wof:name":"Water Doctors Intl",
    "wof:placetype":"venue"
},
  "geometry": {"coordinates":[-79.623085,43.644352],"type":"Point"}
}