{
  "type": "Feature",
  "properties": {
    "iso:country":"CA",
    "sg:address":"1680 Richmond St # L034",
    "sg:city":"London",
    "sg:classifiers":[
        {
            "category":"Shopping",
            "subcategory":"Jewelry",
            "type":"Retail Goods"
        }
    ],
    "sg:phone":"+1 519 850 0218",
    "sg:postcode":"N6G 3Y9",
    "sg:province":"ON",
    "sg:tags":[
        "jeweler"
    ],
    "wof:name":"Dan's Jewellers Inc",
    "wof:placetype":"venue"
},
  "geometry": {"coordinates":[-81.281708,43.025272],"type":"Point"}
}