{
  "type": "Feature",
  "properties": {
    "addr:full":"Repulse Bay NU X0C 0H0",
    "addr:postcode":"x0c 0h0",
    "iso:country":"CA",
    "sg:city":"Repulse Bay",
    "sg:classifiers":[
        {
            "category":"Communications",
            "subcategory":"Radio Station",
            "type":"Services"
        }
    ],
    "sg:phone":"+1 867 462 4061",
    "sg:postcode":"X0C 0H0",
    "sg:province":"NU",
    "sg:tags":[
        "company",
        "broadcasting"
    ],
    "wof:name":"Repulse Bay Radio Station",
    "wof:placetype":"venue"
},
  "geometry": {"coordinates":[-86.23571800000001,66.52507],"type":"Point"}
}