{
  "type": "Feature",
  "properties": {
    "addr:full":"126 Quarry Dr Salt Spring Island BC V8K 1J1",
    "addr:housenumber":"126",
    "addr:postcode":"v8k 1j1",
    "addr:street":"Quarry Dr",
    "iso:country":"CA",
    "sg:address":"126 Quarry Dr",
    "sg:city":"Salt Spring Island",
    "sg:classifiers":[
        {
            "category":"Home & Garden",
            "subcategory":"Building Materials",
            "type":"Retail Goods"
        }
    ],
    "sg:phone":"+1 250 537 9298",
    "sg:postcode":"V8K 1J1",
    "sg:province":"BC",
    "sg:tags":[
        "glass",
        "window",
        "plate"
    ],
    "wof:name":"Salt Spring Island Glass",
    "wof:placetype":"venue"
},
  "geometry": {"coordinates":[-123.561080933,48.8748397827],"type":"Point"}
}