{
  "type": "Feature",
  "properties": {
    "addr:full":"130 Durham St E Walkerton ON N0G 2V0",
    "addr:housenumber":"130",
    "addr:postcode":"n0g 2v0",
    "addr:street":"Durham St E Walkerton",
    "iso:country":"CA",
    "sg:address":"130 Durham St E",
    "sg:city":"Walkerton",
    "sg:classifiers":[
        {
            "category":"Sports & Exercise",
            "subcategory":"Bowling",
            "type":"Entertainment"
        }
    ],
    "sg:phone":"+1 519 881 4262",
    "sg:postcode":"N0G 2V0",
    "sg:province":"ON",
    "sg:tags":[
        "center"
    ],
    "wof:name":"Midtown Bowling Ctr",
    "wof:placetype":"venue"
},
  "geometry": {"coordinates":[-81.15097045900001,44.1336708069],"type":"Point"}
}