{
  "type": "Feature",
  "properties": {
    "addr:full":"7327 101 Ave NW Edmonton AB T6A 0H9",
    "addr:housenumber":"7327",
    "addr:postcode":"t6a 0h9",
    "addr:street":"101 Ave Nw",
    "iso:country":"CA",
    "sg:address":"7327 101 Ave NW",
    "sg:city":"Edmonton",
    "sg:classifiers":[
        {
            "category":"Shopping",
            "subcategory":"Jewelry",
            "type":"Retail Goods"
        }
    ],
    "sg:phone":"+1 780 468 2722",
    "sg:postcode":"T6A 0H9",
    "sg:province":"AB",
    "sg:tags":[
        "jeweler"
    ],
    "wof:name":"Alpine Jewellery CO Ltd",
    "wof:placetype":"venue"
},
  "geometry": {"coordinates":[-113.440422,53.541119],"type":"Point"}
}