{
  "type": "Feature",
  "properties": {
    "addr:full":"219 Manitoba Ave Selkirk MB R1A 0Y4",
    "addr:housenumber":"219",
    "addr:postcode":"r1a 0y4",
    "addr:street":"Manitoba Ave",
    "iso:country":"CA",
    "sg:address":"219 Manitoba Ave",
    "sg:city":"Selkirk",
    "sg:classifiers":[
        {
            "category":"Travel",
            "subcategory":"Hotels & Motels",
            "type":"Entertainment"
        }
    ],
    "sg:phone":"+1 204 482 1900",
    "sg:postcode":"R1A 0Y4",
    "sg:province":"MB",
    "wof:name":"Selkirk Motor Hotel",
    "wof:placetype":"venue"
},
  "geometry": {"coordinates":[-96.86995697019999,50.1441612244],"type":"Point"}
}