{
  "type": "Feature",
  "properties": {
    "iso:country":"CA",
    "sg:address":"1281 Av Du Mont-Royal E",
    "sg:city":"Montreal",
    "sg:classifiers":[
        {
            "category":"Food & Beverages",
            "subcategory":"Bakery",
            "type":"Retail Goods"
        }
    ],
    "sg:phone":"+1 514 525 8388",
    "sg:postcode":"H2J 1Y4",
    "sg:province":"QC",
    "sg:tags":[
        "baker"
    ],
    "wof:name":"Boulangerie LA Fournee Ynewa",
    "wof:placetype":"venue"
},
  "geometry": {"coordinates":[-73.5778503418,45.52967453],"type":"Point"}
}