{
  "type": "Feature",
  "properties": {
    "addr:full":"1638 Rue Daniel Roxton Pond QC J0E 1Z0",
    "addr:housenumber":"1638",
    "addr:postcode":"j0e 1z0",
    "addr:street":"Rue Daniel;Pond",
    "iso:country":"CA",
    "sg:address":"1638 Rue Daniel",
    "sg:city":"Roxton Pond",
    "sg:classifiers":[
        {
            "category":"Building & Trades",
            "subcategory":"Construction",
            "type":"Services"
        }
    ],
    "sg:phone":"+1 450 776 1146",
    "sg:postcode":"J0E 1Z0",
    "sg:province":"QC",
    "sg:tags":[
        "general",
        "contractor"
    ],
    "wof:name":"Mini Excavation Daigle",
    "wof:placetype":"venue"
},
  "geometry": {"coordinates":[-72.64402771,45.4666519165],"type":"Point"}
}