{
  "type": "Feature",
  "properties": {
    "addr:full":"9412 Commercial St New Minas NS B4N 3E9",
    "addr:housenumber":"9412",
    "addr:postcode":"b4n 3e9",
    "addr:street":"Commercial St",
    "iso:country":"CA",
    "sg:address":"9412 Commercial St",
    "sg:city":"New Minas",
    "sg:classifiers":[
        {
            "category":"Social Services",
            "type":"Services"
        }
    ],
    "sg:phone":"+1 902 681 0120",
    "sg:postcode":"B4N 3E9",
    "sg:province":"NS",
    "sg:tags":[
        "organization",
        "welfare"
    ],
    "wof:name":"Flower Cart",
    "wof:placetype":"venue"
},
  "geometry": {"coordinates":[-64.4350967407,45.0722923279],"type":"Point"}
}