{
  "type": "Feature",
  "properties": {
    "iso:country":"CA",
    "sg:city":"Calgary",
    "sg:classifiers":[
        {
            "category":"Restaurant",
            "type":"Food & Drink"
        }
    ],
    "sg:phone":"+1 403 251 3663",
    "sg:postcode":"T2W 4N4",
    "sg:province":"AB",
    "sg:tags":[
        "shop",
        "coffee"
    ],
    "wof:name":"Jungle Java Cappuccino Cafe",
    "wof:placetype":"venue"
},
  "geometry": {"coordinates":[-114.119499,50.940975],"type":"Point"}
}