{
  "type": "Feature",
  "properties": {
    "addr:full":"2630 Kipling Ave # 4A Etobicoke ON M9V 4B9",
    "addr:housenumber":"2630",
    "addr:postcode":"m9v 4b9",
    "addr:street":"Kipling Ave # 4A",
    "iso:country":"CA",
    "sg:address":"2630 Kipling Ave # 4A",
    "sg:city":"Etobicoke",
    "sg:classifiers":[
        {
            "category":"Health Services",
            "subcategory":"Doctor",
            "type":"Services"
        }
    ],
    "sg:phone":"+1 416 741 8877",
    "sg:postcode":"M9V 4B9",
    "sg:province":"ON",
    "sg:tags":[
        "physician",
        "surgeon"
    ],
    "wof:name":"Treasurer, Sushila MD",
    "wof:placetype":"venue"
},
  "geometry": {"coordinates":[-79.58568572999999,43.7504081726],"type":"Point"}
}