{
  "type": "Feature",
  "properties": {
    "addr:full":"3619 Ch D'Oka Saint-Joseph-Du-Lac QC J0N 1M0",
    "addr:postcode":"3619;j0n 1m0",
    "addr:street":"Ch D'Oka",
    "iso:country":"CA",
    "sg:address":"3619 Ch D'Oka",
    "sg:city":"Saint-Joseph-Du-Lac",
    "sg:classifiers":[
        {
            "category":"Building & Trades",
            "subcategory":"Construction",
            "type":"Services"
        }
    ],
    "sg:phone":"+1 450 473 2157",
    "sg:postcode":"J0N 1M0",
    "sg:province":"QC",
    "sg:tags":[
        "excavating",
        "contractor"
    ],
    "wof:name":"Brunet & Brunet Inc",
    "wof:placetype":"venue"
},
  "geometry": {"coordinates":[-73.99696400000001,45.501682],"type":"Point"}
}