{
  "type": "Feature",
  "properties": {
    "addr:full":"Brooks AB T1R 1B8",
    "addr:postcode":"t1r 1b8",
    "iso:country":"CA",
    "sg:city":"Brooks",
    "sg:classifiers":[
        {
            "category":"Retail",
            "subcategory":"Repair Shop",
            "type":"Services"
        }
    ],
    "sg:phone":"+1 403 793 8394",
    "sg:postcode":"T1R 1B8",
    "sg:province":"AB",
    "sg:tags":[
        "field",
        "oil",
        "welding"
    ],
    "wof:name":"Boomers Services Ltd",
    "wof:placetype":"venue"
},
  "geometry": {"coordinates":[-111.89849100000001,50.565853],"type":"Point"}
}