{
  "type": "Feature",
  "properties": {
    "addr:full":"155 Ch Sainte-Anne Sorel-Tracy QC J3P 1J6",
    "addr:housenumber":"155",
    "addr:postcode":"j3p 1j6",
    "addr:street":"Ch Sainte-Anne",
    "iso:country":"CA",
    "sg:address":"155 Ch Sainte-Anne",
    "sg:city":"Sorel-Tracy",
    "sg:classifiers":[
        {
            "category":"Government",
            "subcategory":"Office",
            "type":"Public Place"
        }
    ],
    "sg:phone":"+1 450 742 9056",
    "sg:postcode":"J3P 1J6",
    "sg:province":"QC",
    "sg:tags":[
        "marina",
        "village"
    ],
    "wof:name":"Marina Saurel Inc",
    "wof:placetype":"venue"
},
  "geometry": {"coordinates":[-73.1126327515,46.042388916],"type":"Point"}
}