{
  "type": "Feature",
  "properties": {
    "addr:full":"100 Prince Edward St Saint John NB E2L 4M5",
    "addr:housenumber":"100",
    "addr:postcode":"nb e2l 4m5",
    "addr:street":"Prince Edward St",
    "iso:country":"CA",
    "sg:address":"100 Prince Edward St",
    "sg:city":"Saint John",
    "sg:classifiers":[
        {
            "category":"Real Estate",
            "subcategory":"Real Estate Operator",
            "type":"Services"
        }
    ],
    "sg:phone":"+1 506 649 4445",
    "sg:postcode":"E2L 4M5",
    "sg:province":"NB",
    "sg:tags":[
        "mall",
        "shopping",
        "center"
    ],
    "wof:name":"Prince Edward Square",
    "wof:placetype":"venue"
},
  "geometry": {"coordinates":[-66.05461883540001,45.2771682739],"type":"Point"}
}