{
  "type": "Feature",
  "properties": {
    "addr:full":"Richmond BC V6X 1X6",
    "addr:postcode":"v6x 1x6",
    "iso:country":"CA",
    "sg:city":"Richmond",
    "sg:classifiers":[
        {
            "category":"Wholesale",
            "subcategory":"Groceries",
            "type":"Manufacturing & Wholesale Goods"
        }
    ],
    "sg:phone":"+1 604 214 9722",
    "sg:postcode":"V6X 1X6",
    "sg:province":"BC",
    "sg:tags":[
        "water",
        "company",
        "beverage"
    ],
    "wof:name":"Leading Brands of Canada Inc",
    "wof:placetype":"venue"
},
  "geometry": {"coordinates":[-123.141441345,49.1804084778],"type":"Point"}
}