{
  "type": "Feature",
  "properties": {
    "addr:full":"Montreal QC H4N 1M3",
    "addr:postcode":"h4n 1m3",
    "iso:country":"CA",
    "sg:city":"Montreal",
    "sg:classifiers":[
        {
            "category":"Professional",
            "subcategory":"Advertising",
            "type":"Services"
        }
    ],
    "sg:phone":"+1 514 383 8678",
    "sg:postcode":"H4N 1M3",
    "sg:province":"QC",
    "sg:tags":[
        "publicity"
    ],
    "wof:name":"Begin & Assoc Inc",
    "wof:placetype":"venue"
},
  "geometry": {"coordinates":[-73.6558,45.530197],"type":"Point"}
}