{
  "type": "Feature",
  "properties": {
    "addr:full":"RR 1 Keene ON K0L 2G0",
    "addr:postcode":"k0l 2g0",
    "addr:street":"Rr 1",
    "iso:country":"CA",
    "sg:address":"RR 1",
    "sg:city":"Keene",
    "sg:classifiers":[
        {
            "category":"Wholesale",
            "subcategory":"Hardware",
            "type":"Manufacturing & Wholesale Goods"
        }
    ],
    "sg:phone":"+1 705 639 2327",
    "sg:postcode":"K0L 2G0",
    "sg:province":"ON",
    "sg:tags":[
        "furnace"
    ],
    "wof:name":"Reliable Heating & Air Cond",
    "wof:placetype":"venue"
},
  "geometry": {"coordinates":[-78.1632156372,44.240146637],"type":"Point"}
}