{
  "type": "Feature",
  "properties": {
    "addr:full":"105 King St E Hamilton ON L8N 1A9",
    "addr:housenumber":"105",
    "addr:postcode":"l8n 1a9",
    "addr:street":"King St E",
    "iso:country":"CA",
    "sg:address":"105 King St E",
    "sg:city":"Hamilton",
    "sg:classifiers":[
        {
            "category":"Shopping",
            "subcategory":"Clothing, Apparel, & Fashions",
            "type":"Retail Goods"
        }
    ],
    "sg:phone":"+1 905 529 1164",
    "sg:postcode":"L8N 1A9",
    "sg:province":"ON",
    "sg:tags":[
        "shop",
        "bridal"
    ],
    "wof:name":"Rainbow Shops Ltd",
    "wof:placetype":"venue"
},
  "geometry": {"coordinates":[-79.8657989502,43.2557411194],"type":"Point"}
}