{
  "type": "Feature",
  "properties": {
    "iso:country":"CA",
    "sg:address":"3 Rue Des Saules",
    "sg:city":"Caplan",
    "sg:classifiers":[
        {
            "category":"Home & Garden",
            "subcategory":"Hardware",
            "type":"Retail Goods"
        }
    ],
    "sg:phone":"+1 418 388 2082",
    "sg:postcode":"G0C 1H0",
    "sg:province":"QC",
    "wof:name":"Quincaillerie Robichaud Inc",
    "wof:placetype":"venue"
},
  "geometry": {"coordinates":[-65.6857833862,48.1034088135],"type":"Point"}
}