{
  "type": "Feature",
  "properties": {
    "addr:full":"1385 Gainsborough Dr Oakville ON L6H 2H7",
    "addr:housenumber":"1385",
    "addr:postcode":"l6h 2h7",
    "addr:street":"Gainsborough Dr",
    "iso:country":"CA",
    "sg:address":"1385 Gainsborough Dr",
    "sg:city":"Oakville",
    "sg:classifiers":[
        {
            "category":"Education",
            "subcategory":"School",
            "type":"Public Place"
        }
    ],
    "sg:phone":"+1 905 845 7478",
    "sg:postcode":"L6H 2H7",
    "sg:province":"ON",
    "wof:name":"Falgarwood Elementary School",
    "wof:placetype":"venue"
},
  "geometry": {"coordinates":[-79.68454742430001,43.4789657593],"type":"Point"}
}