{
  "type": "Feature",
  "properties": {
    "addr:full":"Notre-Dame-Du-Laus QC J0X 2M0",
    "addr:postcode":"j0x 2m0",
    "iso:country":"CA",
    "sg:city":"Notre-Dame-Du-Laus",
    "sg:classifiers":[
        {
            "category":"Food & Beverages",
            "subcategory":"Bakery",
            "type":"Retail Goods"
        }
    ],
    "sg:phone":"+1 819 767 2202",
    "sg:postcode":"J0X 2M0",
    "sg:province":"QC",
    "sg:tags":[
        "baker"
    ],
    "wof:name":"Boulangerie Daoust",
    "wof:placetype":"venue"
},
  "geometry": {"coordinates":[-75.62281,46.089615],"type":"Point"}
}