{
  "type": "Feature",
  "properties": {
    "addr:full":"6387 Boul Monk Montreal QC H4E 3H8",
    "addr:housenumber":"6387",
    "addr:postcode":"h4e 3h8",
    "addr:street":"Boul Monk",
    "iso:country":"CA",
    "sg:address":"6387 Boul Monk",
    "sg:city":"Montreal",
    "sg:classifiers":[
        {
            "category":"Health Services",
            "subcategory":"Hospital",
            "type":"Services"
        }
    ],
    "sg:phone":"+1 514 761 1509",
    "sg:postcode":"H4E 3H8",
    "sg:province":"QC",
    "sg:tags":[
        "mental"
    ],
    "wof:name":"Centrami",
    "wof:placetype":"venue"
},
  "geometry": {"coordinates":[-73.59483299999999,45.454796],"type":"Point"}
}