{
  "type": "Feature",
  "properties": {
    "addr:full":"Napanee ON K7R 3L2",
    "addr:postcode":"k7r 3l2",
    "iso:country":"CA",
    "sg:city":"Napanee",
    "sg:classifiers":[
        {
            "category":"Building & Trades",
            "subcategory":"Plumbing",
            "type":"Services"
        }
    ],
    "sg:phone":"+1 613 354 9900",
    "sg:postcode":"K7R 3L2",
    "sg:province":"ON",
    "sg:tags":[
        "mechanical",
        "contractor"
    ],
    "wof:name":"Your Mechanical",
    "wof:placetype":"venue"
},
  "geometry": {"coordinates":[-76.9515762329,44.2483215332],"type":"Point"}
}