{
  "type": "Feature",
  "properties": {
    "addr:full":"Winnipeg MB R3T 3Y6",
    "addr:postcode":"r3t 3y6",
    "iso:country":"CA",
    "sg:city":"Winnipeg",
    "sg:classifiers":[
        {
            "category":"Recreation",
            "subcategory":"Amusement Park",
            "type":"Entertainment"
        }
    ],
    "sg:phone":"+1 204 475 4908",
    "sg:postcode":"R3T 3Y6",
    "sg:province":"MB",
    "wof:name":"Paintball Adventures Inc",
    "wof:placetype":"venue"
},
  "geometry": {"coordinates":[-97.15139007569999,49.831653595],"type":"Point"}
}