{
  "type": "Feature",
  "properties": {
    "addr:full":"Kentville NS B4N 2E3",
    "addr:postcode":"b4n 2e3",
    "iso:country":"CA",
    "sg:city":"Kentville",
    "sg:classifiers":[
        {
            "category":"Banks & Credit Unions",
            "subcategory":"Bank",
            "type":"Services"
        }
    ],
    "sg:phone":"+1 902 679 5722",
    "sg:postcode":"B4N 2E3",
    "sg:province":"NS",
    "sg:tags":[
        "financing"
    ],
    "wof:name":"Farm Credit Corp Canada",
    "wof:placetype":"venue"
},
  "geometry": {"coordinates":[-64.495148,45.085003],"type":"Point"}
}