{
  "type": "Feature",
  "properties": {
    "addr:full":"Nanaimo BC V9T 6J4",
    "addr:postcode":"v9t 6j4",
    "iso:country":"CA",
    "sg:city":"Nanaimo",
    "sg:classifiers":[
        {
            "category":"Home & Garden",
            "subcategory":"Household Appliances",
            "type":"Retail Goods"
        }
    ],
    "sg:phone":"+1 250 756 9963",
    "sg:postcode":"V9T 6J4",
    "sg:province":"BC",
    "sg:tags":[
        "cleaners",
        "vacuum"
    ],
    "wof:name":"A A Vacuum Doctor",
    "wof:placetype":"venue"
},
  "geometry": {"coordinates":[-124.035522,49.225792],"type":"Point"}
}