{
  "type": "Feature",
  "properties": {
    "addr:full":"Courtenay BC V9N 2L4",
    "addr:postcode":"v9n 2l4",
    "iso:country":"CA",
    "sg:city":"Courtenay",
    "sg:classifiers":[
        {
            "category":"Manufacturing",
            "subcategory":"Jewelry",
            "type":"Manufacturing & Wholesale Goods"
        }
    ],
    "sg:phone":"+1 250 897 0502",
    "sg:postcode":"V9N 2L4",
    "sg:province":"BC",
    "sg:tags":[
        "lapidary"
    ],
    "wof:name":"Eagle Gem & Gifts Ltd",
    "wof:placetype":"venue"
},
  "geometry": {"coordinates":[-124.983788,49.678627],"type":"Point"}
}