{
  "type": "Feature",
  "properties": {
    "addr:full":"Vancouver BC V6E 3S7",
    "addr:postcode":"v6e 3s7",
    "iso:country":"CA",
    "sg:city":"Vancouver",
    "sg:classifiers":[
        {
            "category":"Shopping",
            "subcategory":"Clothing, Apparel, & Fashions",
            "type":"Retail Goods"
        }
    ],
    "sg:phone":"+1 604 682 4121",
    "sg:postcode":"V6E 3S7",
    "sg:province":"BC",
    "sg:tags":[
        "shop",
        "bridal"
    ],
    "wof:name":"Saison Des Brides",
    "wof:placetype":"venue"
},
  "geometry": {"coordinates":[-123.119476318,49.2872161865],"type":"Point"}
}