{
  "type": "Feature",
  "properties": {
    "addr:full":"234 Main St Saint John NB E2K 1H6",
    "addr:housenumber":"234",
    "addr:postcode":"e2k 1h6",
    "addr:street":"Main St",
    "iso:country":"CA",
    "sg:address":"234 Main St",
    "sg:city":"Saint John",
    "sg:classifiers":[
        {
            "category":"Retail",
            "subcategory":"Veterinary Services",
            "type":"Services"
        }
    ],
    "sg:phone":"+1 506 634 8332",
    "sg:postcode":"E2K 1H6",
    "sg:province":"NB",
    "sg:tags":[
        "veterinarian"
    ],
    "wof:name":"Alexander, R A Lyn DVM",
    "wof:placetype":"venue"
},
  "geometry": {"coordinates":[-66.08117675779999,45.275226593],"type":"Point"}
}