{
  "type": "Feature",
  "properties": {
    "addr:full":"PO Box 21 Roseisle MB R0G 1V0",
    "addr:housenumber":"po box 21",
    "addr:postcode":"r0g 1v0",
    "addr:street":"Roseisle",
    "iso:country":"CA",
    "sg:address":"PO Box 21",
    "sg:city":"Roseisle",
    "sg:classifiers":[
        {
            "category":"Personal",
            "type":"Services"
        }
    ],
    "sg:phone":"+1 204 828 3214",
    "sg:postcode":"R0G 1V0",
    "sg:province":"MB",
    "sg:tags":[
        "therapist",
        "massage"
    ],
    "wof:name":"Jeanette LA Plante Massage",
    "wof:placetype":"venue"
},
  "geometry": {"coordinates":[-98.34349060060001,49.4997444153],"type":"Point"}
}