{
  "type": "Feature",
  "properties": {
    "addr:full":"925 Av Newton #123 Quebec QC G1P 4M2",
    "addr:housenumber":"925",
    "addr:postcode":"g1p 4m2",
    "addr:street":"Av Newton # 123",
    "iso:country":"CA",
    "sg:address":"925 Av Newton #123",
    "sg:city":"Quebec",
    "sg:classifiers":[
        {
            "category":"Professional",
            "subcategory":"Business Services",
            "type":"Services"
        }
    ],
    "sg:phone":"+1 418 871 0101",
    "sg:postcode":"G1P 4M2",
    "sg:province":"QC",
    "sg:tags":[
        "paper",
        "lamination"
    ],
    "wof:name":"Plasti-Choix Inc",
    "wof:placetype":"venue"
},
  "geometry": {"coordinates":[-71.3032,46.803944],"type":"Point"}
}