{
  "type": "Feature",
  "properties": {
    "addr:full":"210 Broadbent Ave Saskatoon SK S7K 6H8",
    "addr:housenumber":"210",
    "addr:postcode":"s7k 6h8",
    "addr:street":"Broadbent Ave",
    "iso:country":"CA",
    "sg:address":"210 Broadbent Ave",
    "sg:city":"Saskatoon",
    "sg:classifiers":[
        {
            "category":"Building & Trades",
            "subcategory":"Construction",
            "type":"Services"
        }
    ],
    "sg:phone":"+1 306 934 6082",
    "sg:postcode":"S7K 6H8",
    "sg:province":"SK",
    "sg:tags":[
        "repairing",
        "remodeling",
        "carpenter",
        "contractor"
    ],
    "wof:name":"Geno's Finishing",
    "wof:placetype":"venue"
},
  "geometry": {"coordinates":[-106.622489929,52.1861343384],"type":"Point"}
}