{
  "type": "Feature",
  "properties": {
    "iso:country":"CA",
    "sg:address":"552 Berford St",
    "sg:city":"Wiarton",
    "sg:classifiers":[
        {
            "category":"Professional",
            "subcategory":"Accounting & Tax Preparation",
            "type":"Services"
        }
    ],
    "sg:phone":"+1 519 534 4490",
    "sg:postcode":"N0H 2T0",
    "sg:province":"ON",
    "sg:tags":[
        "return",
        "filing"
    ],
    "wof:name":"H & R Block Canada Inc",
    "wof:placetype":"venue"
},
  "geometry": {"coordinates":[-81.141006,44.742176],"type":"Point"}
}