{
  "type": "Feature",
  "properties": {
    "addr:full":"501 Rue Principale Saint-Patrice-DE-Beaurivage QC G0S 1B0",
    "addr:housenumber":"501",
    "addr:postcode":"g0s 1b0",
    "addr:street":"Rue Principale",
    "iso:country":"CA",
    "sg:address":"501 Rue Principale",
    "sg:city":"Saint-Patrice-DE-Beaurivage",
    "sg:classifiers":[
        {
            "category":"Building & Trades",
            "subcategory":"Plumbing",
            "type":"Services"
        }
    ],
    "sg:phone":"+1 418 596 2100",
    "sg:postcode":"G0S 1B0",
    "sg:province":"QC",
    "sg:tags":[
        "contractor"
    ],
    "wof:name":"C C Chabot Inc",
    "wof:placetype":"venue"
},
  "geometry": {"coordinates":[-71.23687700000001,46.411564],"type":"Point"}
}