{
  "type": "Feature",
  "properties": {
    "addr:full":"6215 Ch DE LA Cote-Saint-Luc Hampstead QC H3X 2H3",
    "addr:postcode":"6215;h3x 2h3",
    "addr:street":"Ch De La Cote-Saint-Luc",
    "iso:country":"CA",
    "sg:address":"6215 Ch DE LA Cote-Saint-Luc",
    "sg:city":"Hampstead",
    "sg:classifiers":[
        {
            "category":"Organizations",
            "subcategory":"Religious Organization",
            "type":"Services"
        }
    ],
    "sg:phone":"+1 514 487 1378",
    "sg:postcode":"H3X 2H3",
    "sg:province":"QC",
    "sg:tags":[
        "church"
    ],
    "wof:name":"Christian Restoration Ctr",
    "wof:placetype":"venue"
},
  "geometry": {"coordinates":[-73.6432647705,45.4745101929],"type":"Point"}
}