{
  "type": "Feature",
  "properties": {
    "addr:full":"1 Rowat St Sudbury ON P3C 3J8",
    "addr:housenumber":"1",
    "addr:postcode":"p3c 3j8",
    "addr:street":"Rowat St",
    "iso:country":"CA",
    "sg:address":"1 Rowat St",
    "sg:city":"Sudbury",
    "sg:classifiers":[
        {
            "category":"Retail",
            "subcategory":"Repair Shop",
            "type":"Services"
        }
    ],
    "sg:phone":"+1 705 671 9975",
    "sg:postcode":"P3C 3J8",
    "sg:province":"ON",
    "sg:tags":[
        "welding"
    ],
    "wof:name":"Mwm Instrumentation",
    "wof:placetype":"venue"
},
  "geometry": {"coordinates":[-81.017769,46.477703],"type":"Point"}
}