{
  "type": "Feature",
  "properties": {
    "addr:full":"1413 23 Ave Coaldale AB T1M 1L6",
    "addr:housenumber":"1413",
    "addr:postcode":"t1m 1l6",
    "addr:street":"23 Ave",
    "iso:country":"CA",
    "sg:address":"1413 23 Ave",
    "sg:city":"Coaldale",
    "sg:classifiers":[
        {
            "category":"Education",
            "subcategory":"School",
            "type":"Public Place"
        }
    ],
    "sg:phone":"+1 403 345 3373",
    "sg:postcode":"T1M 1L6",
    "sg:province":"AB",
    "wof:name":"St Joseph's School",
    "wof:placetype":"venue"
},
  "geometry": {"coordinates":[-112.613624573,49.7219314575],"type":"Point"}
}