{
  "type": "Feature",
  "properties": {
    "addr:full":"12 Aquila Crt Etobicoke ON M9W 5J2",
    "addr:housenumber":"12",
    "addr:postcode":"m9w 5j2",
    "addr:street":"Aquila Crt",
    "iso:country":"CA",
    "sg:address":"12 Aquila Crt",
    "sg:city":"Etobicoke",
    "sg:classifiers":[
        {
            "category":"Wholesale",
            "subcategory":"Durable Goods & Equipment",
            "type":"Manufacturing & Wholesale Goods"
        }
    ],
    "sg:phone":"+1 416 748 8045",
    "sg:postcode":"M9W 5J2",
    "sg:province":"ON",
    "sg:tags":[
        "representative",
        "manufacturer"
    ],
    "wof:name":"Eastcan Marketing Ltd",
    "wof:placetype":"venue"
},
  "geometry": {"coordinates":[-79.5852890015,43.7191123962],"type":"Point"}
}