{
  "type": "Feature",
  "properties": {
    "addr:full":"193 Portland St Dartmouth NS B2Y 1J5",
    "addr:housenumber":"193",
    "addr:postcode":"b2y 1j5",
    "addr:street":"Portland St",
    "iso:country":"CA",
    "sg:address":"193 Portland St",
    "sg:city":"Dartmouth",
    "sg:classifiers":[
        {
            "category":"Health Services",
            "subcategory":"Medical Lab",
            "type":"Services"
        }
    ],
    "sg:phone":"+1 902 464 0808",
    "sg:postcode":"B2Y 1J5",
    "sg:province":"NS",
    "wof:name":"Atlantic Denture Clinic",
    "wof:placetype":"venue"
},
  "geometry": {"coordinates":[-63.5626602173,44.6679611206],"type":"Point"}
}