{
  "type": "Feature",
  "properties": {
    "addr:full":"Delta BC V4L 2A4",
    "addr:postcode":"v4l 2a4",
    "iso:country":"CA",
    "sg:city":"Delta",
    "sg:classifiers":[
        {
            "category":"Shopping",
            "subcategory":"Bicycles & Sporting Goods",
            "type":"Retail Goods"
        }
    ],
    "sg:phone":"+1 604 943 2701",
    "sg:postcode":"V4L 2A4",
    "sg:province":"BC",
    "sg:tags":[
        "hardware"
    ],
    "wof:name":"Tsawwassen Home Hardware",
    "wof:placetype":"venue"
},
  "geometry": {"coordinates":[-123.06844329800001,49.0249710083],"type":"Point"}
}