{
  "type": "Feature",
  "properties": {
    "addr:full":"712 Dundas St W Belleville ON K8N 4Z2",
    "addr:housenumber":"712",
    "addr:postcode":"k8n 4z2",
    "addr:street":"Dundas St W",
    "iso:country":"CA",
    "sg:address":"712 Dundas St W",
    "sg:city":"Belleville",
    "sg:classifiers":[
        {
            "category":"Shopping",
            "type":"Retail Goods"
        }
    ],
    "sg:phone":"+1 613 966 5154",
    "sg:postcode":"K8N 4Z2",
    "sg:province":"ON",
    "sg:tags":[
        "monument"
    ],
    "wof:name":"Campbell Monument CO Ltd",
    "wof:placetype":"venue"
},
  "geometry": {"coordinates":[-77.4246520996,44.1408615112],"type":"Point"}
}