{
  "type": "Feature",
  "properties": {
    "addr:full":"421 Lahave St Bridgewater NS B4V 3A2",
    "addr:housenumber":"421",
    "addr:postcode":"b4v 3a2",
    "addr:street":"Lahave St",
    "iso:country":"CA",
    "sg:address":"421 Lahave St",
    "sg:city":"Bridgewater",
    "sg:classifiers":[
        {
            "category":"Restaurant",
            "type":"Food & Drink"
        }
    ],
    "sg:phone":"+1 902 543 0920",
    "sg:postcode":"B4V 3A2",
    "sg:province":"NS",
    "wof:name":"Magic Wok",
    "wof:placetype":"venue"
},
  "geometry": {"coordinates":[-64.514374,44.378021],"type":"Point"}
}