{
  "type": "Feature",
  "properties": {
    "addr:full":"710 1E Av Sainte-Marie QC G6E 1B5",
    "addr:housenumber":"710",
    "addr:postcode":"qc g6e 1b5",
    "addr:street":"1E Av Sainte-Marie",
    "iso:country":"CA",
    "sg:address":"710 1E Av",
    "sg:city":"Sainte-Marie",
    "sg:classifiers":[
        {
            "category":"Building & Trades",
            "subcategory":"Construction",
            "type":"Services"
        }
    ],
    "sg:phone":"+1 418 386 2726",
    "sg:postcode":"G6E 1B5",
    "sg:province":"QC",
    "sg:tags":[
        "general",
        "contractor"
    ],
    "wof:name":"Division Ascon Inc",
    "wof:placetype":"venue"
},
  "geometry": {"coordinates":[-65.9838256836,48.1726264954],"type":"Point"}
}