{
  "type": "Feature",
  "properties": {
    "addr:full":"29 Main St Penetanguishene ON L9M 1S7",
    "addr:housenumber":"29",
    "addr:postcode":"l9m 1s7",
    "addr:street":"Main St",
    "iso:country":"CA",
    "sg:address":"29 Main St",
    "sg:city":"Penetanguishene",
    "sg:classifiers":[
        {
            "category":"Shopping",
            "subcategory":"Computers & Home Electronics",
            "type":"Retail Goods"
        }
    ],
    "sg:phone":"+1 705 549 1303",
    "sg:postcode":"L9M 1S7",
    "sg:province":"ON",
    "sg:tags":[
        "equipment",
        "dealer"
    ],
    "wof:name":"A Main Street Computer Store",
    "wof:placetype":"venue"
},
  "geometry": {"coordinates":[-79.93589799999999,44.771362],"type":"Point"}
}