{
  "type": "Feature",
  "properties": {
    "addr:full":"3550 Johnston Rd # 51 Port Alberni BC V9Y 7W8",
    "addr:housenumber":"3550",
    "addr:postcode":"v9y 7w8",
    "addr:street":"Johnston Rd # 51",
    "iso:country":"CA",
    "sg:address":"3550 Johnston Rd # 51",
    "sg:city":"Port Alberni",
    "sg:classifiers":[
        {
            "category":"Autos & Motor Vehicles",
            "subcategory":"Auto Supplies",
            "type":"Retail Goods"
        }
    ],
    "sg:phone":"+1 250 720 0085",
    "sg:postcode":"V9Y 7W8",
    "sg:province":"BC",
    "sg:tags":[
        "repairing",
        "automobile",
        "parts"
    ],
    "wof:name":"Canadian Tire",
    "wof:placetype":"venue"
},
  "geometry": {"coordinates":[-124.78608699999999,49.265972],"type":"Point"}
}