{
  "type": "Feature",
  "properties": {
    "iso:country":"CA",
    "sg:address":"2785 Av Francis-Hughes",
    "sg:city":"Laval",
    "sg:classifiers":[
        {
            "category":"Wholesale",
            "subcategory":"Hardware",
            "type":"Manufacturing & Wholesale Goods"
        }
    ],
    "sg:phone":"+1 450 629 3030",
    "sg:postcode":"H7L 3J6",
    "sg:province":"QC",
    "sg:tags":[
        "dust",
        "collecting",
        "filter",
        "system"
    ],
    "wof:name":"Camfil Farr",
    "wof:placetype":"venue"
},
  "geometry": {"coordinates":[-73.7332000732,45.5892791748],"type":"Point"}
}