{
  "type": "Feature",
  "properties": {
    "iso:country":"CA",
    "sg:address":"2700 Dufferin St",
    "sg:city":"York",
    "sg:classifiers":[
        {
            "category":"Manufacturing",
            "subcategory":"Apparel",
            "type":"Manufacturing & Wholesale Goods"
        }
    ],
    "sg:phone":"+1 416 504 8663",
    "sg:postcode":"M6B 4J3",
    "sg:province":"ON",
    "sg:tags":[
        "sewing",
        "contractor"
    ],
    "wof:name":"Dmack",
    "wof:placetype":"venue"
},
  "geometry": {"coordinates":[-79.452187,43.701878],"type":"Point"}
}