{
  "type": "Feature",
  "properties": {
    "addr:full":"Calgary AB T2N 3P9",
    "addr:postcode":"t2n 3p9",
    "iso:country":"CA",
    "sg:city":"Calgary",
    "sg:classifiers":[
        {
            "category":"Professional",
            "subcategory":"Accounting & Tax Preparation",
            "type":"Services"
        }
    ],
    "sg:phone":"+1 403 283 8034",
    "sg:postcode":"T2N 3P9",
    "sg:province":"AB",
    "sg:tags":[
        "accountant"
    ],
    "wof:name":"Smith, Kenneth R CA",
    "wof:placetype":"venue"
},
  "geometry": {"coordinates":[-114.091789246,51.0525588989],"type":"Point"}
}