{
  "type": "Feature",
  "properties": {
    "iso:country":"CA",
    "sg:address":"317 Elmwood Dr",
    "sg:city":"Belleville",
    "sg:classifiers":[
        {
            "category":"Shopping",
            "type":"Retail Goods"
        }
    ],
    "sg:phone":"+1 613 968 6191",
    "sg:postcode":"K8N 4Z4",
    "sg:province":"ON",
    "sg:tags":[
        "picture",
        "frame"
    ],
    "wof:name":"M W Matworks",
    "wof:placetype":"venue"
},
  "geometry": {"coordinates":[-77.32409667970001,44.1847114563],"type":"Point"}
}