{
  "type": "Feature",
  "properties": {
    "addr:full":"155 Gibb St Oshawa ON L1J 1Y4",
    "addr:housenumber":"155",
    "addr:postcode":"l1j 1y4",
    "addr:street":"Gibb St",
    "iso:country":"CA",
    "sg:address":"155 Gibb St",
    "sg:city":"Oshawa",
    "sg:classifiers":[
        {
            "category":"Education",
            "subcategory":"School",
            "type":"Public Place"
        }
    ],
    "sg:phone":"+1 905 723 4678",
    "sg:postcode":"L1J 1Y4",
    "sg:province":"ON",
    "wof:name":"Central Collegiate Institute",
    "wof:placetype":"venue"
},
  "geometry": {"coordinates":[-78.86608099999999,43.889107],"type":"Point"}
}