{
  "type": "Feature",
  "properties": {
    "addr:full":"Ayr ON N0B 1E0",
    "addr:postcode":"n0b 1e0",
    "iso:country":"CA",
    "sg:city":"Ayr",
    "sg:classifiers":[
        {
            "category":"Professional",
            "subcategory":"Management & Consulting",
            "type":"Services"
        }
    ],
    "sg:phone":"+1 519 620 9654",
    "sg:postcode":"N0B 1E0",
    "sg:province":"ON",
    "sg:tags":[
        "association"
    ],
    "wof:name":"Meeting Logistics & More",
    "wof:placetype":"venue"
},
  "geometry": {"coordinates":[-80.4499969482,43.2856559753],"type":"Point"}
}