{
  "type": "Feature",
  "properties": {
    "addr:full":"8308 Main St Osoyoos BC V0H 1V0",
    "addr:housenumber":"8308",
    "addr:postcode":"v0h 1v0",
    "addr:street":"Main St",
    "iso:country":"CA",
    "sg:address":"8308 Main St",
    "sg:city":"Osoyoos",
    "sg:classifiers":[
        {
            "category":"Insurance",
            "subcategory":"Insurance Agent",
            "type":"Services"
        }
    ],
    "sg:phone":"+1 250 495 6111",
    "sg:postcode":"V0H 1V0",
    "sg:province":"BC",
    "wof:name":"Eisenhut Insurance Ltd",
    "wof:placetype":"venue"
},
  "geometry": {"coordinates":[-119.463684082,49.0330619812],"type":"Point"}
}