{
  "type": "Feature",
  "properties": {
    "addr:full":"3201 30 St Vernon BC V1T 9G3",
    "addr:housenumber":"3201",
    "addr:postcode":"v1t 9g3",
    "addr:street":"30 St",
    "iso:country":"CA",
    "sg:address":"3201 30 St",
    "sg:city":"Vernon",
    "sg:classifiers":[
        {
            "category":"Government",
            "subcategory":"Office",
            "type":"Public Place"
        }
    ],
    "sg:phone":"+1 250 549 5511",
    "sg:postcode":"V1T 9G3",
    "sg:province":"BC",
    "wof:name":"British Columbia Govt Agent",
    "wof:placetype":"venue"
},
  "geometry": {"coordinates":[-119.27063,50.265396],"type":"Point"}
}