{
  "type": "Feature",
  "properties": {
    "iso:country":"CA",
    "sg:city":"North York",
    "sg:classifiers":[
        {
            "category":"Professional",
            "subcategory":"Lawyer & Legal Services",
            "type":"Services"
        }
    ],
    "sg:phone":"+1 416 502 9232",
    "sg:postcode":"M2H 3N5",
    "sg:province":"ON",
    "sg:tags":[
        "attorney"
    ],
    "wof:name":"Ngan, Metz L",
    "wof:placetype":"venue"
},
  "geometry": {"coordinates":[-79.3447341919,43.8032646179],"type":"Point"}
}