{
  "type": "Feature",
  "properties": {
    "addr:full":"264 Rue Labelle Saint-Jerome QC J7Z 5L1",
    "addr:housenumber":"264",
    "addr:postcode":"j7z 5l1",
    "addr:street":"Rue Labelle Saint-Jerome",
    "iso:country":"CA",
    "sg:address":"264 Rue Labelle",
    "sg:city":"Saint-Jerome",
    "sg:classifiers":[
        {
            "category":"Social Services",
            "type":"Services"
        }
    ],
    "sg:phone":"+1 450 569 6635",
    "sg:postcode":"J7Z 5L1",
    "sg:province":"QC",
    "sg:tags":[
        "psychotherapist",
        "counselor",
        "marriage",
        "family"
    ],
    "wof:name":"Centre Vivre En Relation",
    "wof:placetype":"venue"
},
  "geometry": {"coordinates":[-74.0043563843,45.7750816345],"type":"Point"}
}