{
  "type": "Feature",
  "properties": {
    "addr:full":"306 Model Farm Rd Quispamsis NB E2E 4Z8",
    "addr:housenumber":"306",
    "addr:postcode":"e2e 4z8",
    "addr:street":"Model Farm Rd",
    "iso:country":"CA",
    "sg:address":"306 Model Farm Rd",
    "sg:city":"Quispamsis",
    "sg:classifiers":[
        {
            "category":"Building & Trades",
            "subcategory":"Landscaping Services",
            "type":"Services"
        }
    ],
    "sg:phone":"+1 506 847 8244",
    "sg:postcode":"E2E 4Z8",
    "sg:province":"NB",
    "sg:tags":[
        "center",
        "garden",
        "landscape",
        "contractor"
    ],
    "wof:name":"Brunswick Nurseries Ltd",
    "wof:placetype":"venue"
},
  "geometry": {"coordinates":[-65.936775,45.46909],"type":"Point"}
}