{
  "type": "Feature",
  "properties": {
    "addr:full":"200 Rue Durand Saint-Jerome QC J7Z 7E2",
    "addr:housenumber":"200",
    "addr:postcode":"j7z 7e2",
    "addr:street":"Rue Durand Saint-Jerome",
    "iso:country":"CA",
    "sg:address":"200 Rue Durand",
    "sg:city":"Saint-Jerome",
    "sg:classifiers":[
        {
            "category":"Health Services",
            "subcategory":"Health Practitioner",
            "type":"Services"
        }
    ],
    "sg:phone":"+1 450 560 8305",
    "sg:postcode":"J7Z 7E2",
    "sg:province":"QC",
    "sg:tags":[
        "psychologist"
    ],
    "wof:name":"Forest, Luc",
    "wof:placetype":"venue"
},
  "geometry": {"coordinates":[-74.000496,45.767776],"type":"Point"}
}