{
  "type": "Feature",
  "properties": {
    "addr:full":"227 Vodden St E Brampton ON L6V 1N2",
    "addr:housenumber":"227",
    "addr:postcode":"l6v 1n2",
    "addr:street":"Vodden St E",
    "iso:country":"CA",
    "sg:address":"227 Vodden St E",
    "sg:city":"Brampton",
    "sg:classifiers":[
        {
            "category":"Health Services",
            "subcategory":"Doctor",
            "type":"Services"
        }
    ],
    "sg:phone":"+1 905 457 3606",
    "sg:postcode":"L6V 1N2",
    "sg:province":"ON",
    "sg:tags":[
        "dentist"
    ],
    "wof:name":"Centennial Dental Office",
    "wof:placetype":"venue"
},
  "geometry": {"coordinates":[-79.7572250366,43.7038955688],"type":"Point"}
}