{
  "type": "Feature",
  "properties": {
    "addr:full":"226 Forman Ave Stratford ON N5A 6R4",
    "addr:housenumber":"226",
    "addr:postcode":"n5a 6r4",
    "addr:street":"Forman Ave",
    "iso:country":"CA",
    "sg:address":"226 Forman Ave",
    "sg:city":"Stratford",
    "sg:classifiers":[
        {
            "category":"Organizations",
            "subcategory":"Religious Organization",
            "type":"Services"
        }
    ],
    "sg:phone":"+1 519 271 4539",
    "sg:postcode":"N5A 6R4",
    "sg:province":"ON",
    "sg:tags":[
        "church"
    ],
    "wof:name":"Community of Christ",
    "wof:placetype":"venue"
},
  "geometry": {"coordinates":[-80.996994,43.379913],"type":"Point"}
}