{
  "type": "Feature",
  "properties": {
    "addr:full":"9740 Rte Transcanadienne Saint-Laurent QC H4S 1V9",
    "addr:housenumber":"9740",
    "addr:postcode":"h4s 1v9",
    "addr:street":"Rte Transcanadienne",
    "iso:country":"CA",
    "sg:address":"9740 Rte Transcanadienne",
    "sg:city":"Saint-Laurent",
    "sg:classifiers":[
        {
            "category":"Shopping",
            "subcategory":"Computers & Home Electronics",
            "type":"Retail Goods"
        }
    ],
    "sg:phone":"+1 514 920 0512",
    "sg:postcode":"H4S 1V9",
    "sg:province":"QC",
    "sg:tags":[
        "equipment",
        "establishment",
        "dealer"
    ],
    "wof:name":"Vernon Solutions Technologies",
    "wof:placetype":"venue"
},
  "geometry": {"coordinates":[-73.7554397583,45.4899215698],"type":"Point"}
}