{
  "type": "Feature",
  "properties": {
    "addr:full":"13025 Hwy 27 Nobleton ON L0G 1N0",
    "addr:housenumber":"13025",
    "addr:postcode":"l0g 1n0",
    "addr:street":"Hwy 27",
    "iso:country":"CA",
    "sg:address":"13025 Hwy 27",
    "sg:city":"Nobleton",
    "sg:classifiers":[
        {
            "category":"Autos & Motor Vehicles",
            "subcategory":"Fuel & Gas Station",
            "type":"Retail Goods"
        }
    ],
    "sg:phone":"+1 905 859 0642",
    "sg:postcode":"L0G 1N0",
    "sg:province":"ON",
    "sg:tags":[
        "oil"
    ],
    "wof:name":"Goodfellow & Witherspoon Auto",
    "wof:placetype":"venue"
},
  "geometry": {"coordinates":[-79.652671814,43.9028091431],"type":"Point"}
}