{
  "type": "Feature",
  "properties": {
    "addr:full":"19 Kenneth Dr Quispamsis NB E2G 1H9",
    "addr:housenumber":"19",
    "addr:postcode":"e2g 1h9",
    "addr:street":"Kenneth Dr",
    "iso:country":"CA",
    "sg:address":"19 Kenneth Dr",
    "sg:city":"Quispamsis",
    "sg:classifiers":[
        {
            "category":"Freight",
            "type":"Transportation"
        }
    ],
    "sg:phone":"+1 506 847 2481",
    "sg:postcode":"E2G 1H9",
    "sg:province":"NB",
    "wof:name":"Esl Forwarding Ltd",
    "wof:placetype":"venue"
},
  "geometry": {"coordinates":[-65.921585083,45.4763565063],"type":"Point"}
}