{
  "type": "Feature",
  "properties": {
    "addr:full":"147 Woodbine Ave Toronto ON M4L 3P1",
    "addr:housenumber":"147",
    "addr:postcode":"m4l 3p1",
    "addr:street":"Woodbine Ave",
    "iso:country":"CA",
    "sg:address":"147 Woodbine Ave",
    "sg:city":"Toronto",
    "sg:classifiers":[
        {
            "category":"Building & Trades",
            "subcategory":"Landscaping Services",
            "type":"Services"
        }
    ],
    "sg:phone":"+1 416 690 1742",
    "sg:postcode":"M4L 3P1",
    "sg:province":"ON",
    "sg:tags":[
        "designer",
        "architect",
        "landscape"
    ],
    "wof:name":"A D Regehr Landscape Architect",
    "wof:placetype":"venue"
},
  "geometry": {"coordinates":[-79.305145,43.667713],"type":"Point"}
}