{
  "type": "Feature",
  "properties": {
    "addr:full":"10 Charles St E Ingersoll ON N5C 1J4",
    "addr:housenumber":"10",
    "addr:postcode":"n5c 1j4",
    "addr:street":"Charles St E",
    "iso:country":"CA",
    "sg:address":"10 Charles St E",
    "sg:city":"Ingersoll",
    "sg:classifiers":[
        {
            "category":"Professional",
            "subcategory":"Accounting & Tax Preparation",
            "type":"Services"
        }
    ],
    "sg:phone":"+1 519 425 1094",
    "sg:postcode":"N5C 1J4",
    "sg:province":"ON",
    "sg:tags":[
        "return",
        "filing"
    ],
    "wof:name":"H & R Block Canada Inc",
    "wof:placetype":"venue"
},
  "geometry": {"coordinates":[-80.8832702637,43.0392456055],"type":"Point"}
}