{
  "type": "Feature",
  "properties": {
    "iso:country":"CA",
    "sg:address":"3506 Errington Ave",
    "sg:city":"Chelmsford",
    "sg:classifiers":[
        {
            "category":"Social Services",
            "type":"Services"
        }
    ],
    "sg:phone":"+1 705 855 4637",
    "sg:postcode":"P0M 1L0",
    "sg:province":"ON",
    "sg:tags":[
        "senior",
        "citizen"
    ],
    "wof:name":"Rayside Balfour Senior Craft",
    "wof:placetype":"venue"
},
  "geometry": {"coordinates":[-81.19784545900001,46.58020401],"type":"Point"}
}