{
  "type": "Feature",
  "properties": {
    "addr:full":"Highway 503 Madawaska ON K0J 2C0",
    "addr:postcode":"k0j 2c0",
    "addr:street":"Highway 503 Madawaska",
    "iso:country":"CA",
    "sg:address":"Highway 503",
    "sg:city":"Madawaska",
    "sg:classifiers":[
        {
            "category":"Travel",
            "subcategory":"Hotels & Motels",
            "type":"Entertainment"
        }
    ],
    "sg:phone":"+1 613 637 5215",
    "sg:postcode":"K0J 2C0",
    "sg:province":"ON",
    "sg:tags":[
        "pond",
        "lake",
        "fishing",
        "resort"
    ],
    "wof:name":"Red Deer Lodge",
    "wof:placetype":"venue"
},
  "geometry": {"coordinates":[-77.99046300000001,45.501709],"type":"Point"}
}