{
  "type": "Feature",
  "properties": {
    "addr:full":"1576 7th Ave Prince George BC V2L 3P4",
    "addr:housenumber":"1576",
    "addr:postcode":"v2l 3p4",
    "addr:street":"7Th Ave",
    "iso:country":"CA",
    "sg:address":"1576 7th Ave",
    "sg:city":"Prince George",
    "sg:classifiers":[
        {
            "category":"Health Services",
            "subcategory":"Doctor",
            "type":"Services"
        }
    ],
    "sg:phone":"+1 250 563 7223",
    "sg:postcode":"V2L 3P4",
    "sg:province":"BC",
    "sg:tags":[
        "dentist"
    ],
    "wof:name":"Cochrane, John DDS",
    "wof:placetype":"venue"
},
  "geometry": {"coordinates":[-122.752815,53.915283],"type":"Point"}
}