{
  "type": "Feature",
  "properties": {
    "addr:full":"117 Ch Des Fondateurs LA Minerve QC J0T 1S0",
    "addr:housenumber":"117",
    "addr:postcode":"j0t 1s0",
    "addr:street":"Ch Des Fondateurs",
    "iso:country":"CA",
    "sg:address":"117 Ch Des Fondateurs",
    "sg:city":"LA Minerve",
    "sg:classifiers":[
        {
            "category":"Food & Beverages",
            "subcategory":"Groceries & Convenience Stores",
            "type":"Retail Goods"
        }
    ],
    "sg:phone":"+1 819 274 2721",
    "sg:postcode":"J0T 1S0",
    "sg:province":"QC",
    "sg:tags":[
        "grocer"
    ],
    "wof:name":"Marche D'Alimentation LA Miner",
    "wof:placetype":"venue"
},
  "geometry": {"coordinates":[-74.9359741211,46.2554664612],"type":"Point"}
}