{
  "type": "Feature",
  "properties": {
    "addr:full":"638 Boul Albert-DE Niverville Dorval QC H4Y 1G6",
    "addr:housenumber":"638",
    "addr:postcode":"h4y 1g6",
    "addr:street":"Boul Albert-De Niverville",
    "iso:country":"CA",
    "sg:address":"638 Boul Albert-DE Niverville",
    "sg:city":"Dorval",
    "sg:classifiers":[
        {
            "category":"Airport",
            "type":"Transportation"
        }
    ],
    "sg:phone":"+1 514 631 6937",
    "sg:postcode":"H4Y 1G6",
    "sg:province":"QC",
    "sg:tags":[
        "aircraft",
        "maintenance"
    ],
    "wof:name":"Handlex",
    "wof:placetype":"venue"
},
  "geometry": {"coordinates":[-73.75309,45.453892],"type":"Point"}
}