{
  "type": "Feature",
  "properties": {
    "addr:full":"9000 Weston Rd Woodbridge ON L4L 1A6",
    "addr:housenumber":"9000",
    "addr:postcode":"l4l 1a6",
    "addr:street":"Weston Rd",
    "iso:country":"CA",
    "sg:address":"9000 Weston Rd",
    "sg:city":"Woodbridge",
    "sg:classifiers":[
        {
            "category":"Restaurant",
            "type":"Food & Drink"
        }
    ],
    "sg:phone":"+1 905 851 6707",
    "sg:postcode":"L4L 1A6",
    "sg:province":"ON",
    "wof:name":"Pizza Prima",
    "wof:placetype":"venue"
},
  "geometry": {"coordinates":[-79.555328,43.821495],"type":"Point"}
}