{
  "type": "Feature",
  "properties": {
    "addr:full":"1639 St Mary's Rd Winnipeg MB R2N 3W1",
    "addr:housenumber":"1639",
    "addr:postcode":"r2n 3w1",
    "addr:street":"St Mary'S Rd",
    "iso:country":"CA",
    "sg:address":"1639 St Mary's Rd",
    "sg:city":"Winnipeg",
    "sg:classifiers":[
        {
            "category":"Food & Beverages",
            "subcategory":"Bakery",
            "type":"Retail Goods"
        }
    ],
    "sg:phone":"+1 204 255 6713",
    "sg:postcode":"R2N 3W1",
    "sg:province":"MB",
    "sg:tags":[
        "doughnut"
    ],
    "wof:name":"Robin's Donuts",
    "wof:placetype":"venue"
},
  "geometry": {"coordinates":[-97.1129150391,49.8198890686],"type":"Point"}
}