{
  "type": "Feature",
  "properties": {
    "addr:full":"Scarborough ON M1L 4J9",
    "addr:postcode":"m1l 4j9",
    "iso:country":"CA",
    "sg:city":"Scarborough",
    "sg:classifiers":[
        {
            "category":"Retail",
            "subcategory":"Auto Repair",
            "type":"Services"
        }
    ],
    "sg:phone":"+1 416 288 9711",
    "sg:postcode":"M1L 4J9",
    "sg:province":"ON",
    "sg:tags":[
        "repairing",
        "automobile"
    ],
    "wof:name":"Hide Auto Ctr",
    "wof:placetype":"venue"
},
  "geometry": {"coordinates":[-79.2864532471,43.7354888916],"type":"Point"}
}