{
  "type": "Feature",
  "properties": {
    "addr:full":"1681 Rte Marie-Victorin # 103 Sorel-Tracy QC J3R 4R4",
    "addr:housenumber":"1681;# 103",
    "addr:postcode":"j3r 4r4",
    "addr:street":"Rte Marie-Victorin",
    "iso:country":"CA",
    "sg:address":"1681 Rte Marie-Victorin # 103",
    "sg:city":"Sorel-Tracy",
    "sg:classifiers":[
        {
            "category":"Building & Trades",
            "subcategory":"Construction",
            "type":"Services"
        }
    ],
    "sg:phone":"+1 450 746 0569",
    "sg:postcode":"J3R 4R4",
    "sg:province":"QC",
    "sg:tags":[
        "general",
        "contractor"
    ],
    "wof:name":"Arel Mecoba Inc",
    "wof:placetype":"venue"
},
  "geometry": {"coordinates":[-73.149933,46.038532],"type":"Point"}
}