{
  "type": "Feature",
  "properties": {
    "addr:full":"Millet AB T0C 1Z0",
    "addr:postcode":"t0c 1z0",
    "iso:country":"CA",
    "sg:city":"Millet",
    "sg:classifiers":[
        {
            "category":"Freight",
            "type":"Transportation"
        }
    ],
    "sg:phone":"+1 780 387 5445",
    "sg:postcode":"T0C 1Z0",
    "sg:province":"AB",
    "sg:tags":[
        "courier"
    ],
    "wof:name":"Greyhound Canada",
    "wof:placetype":"venue"
},
  "geometry": {"coordinates":[-113.469650269,53.090549469],"type":"Point"}
}