{
  "type": "Feature",
  "properties": {
    "addr:full":"702 Main St #2 Canmore AB T1W 2B6",
    "addr:housenumber":"702",
    "addr:postcode":"t1w 2b6",
    "addr:street":"Main St # 2",
    "iso:country":"CA",
    "sg:address":"702 Main St #2",
    "sg:city":"Canmore",
    "sg:classifiers":[
        {
            "category":"Shopping",
            "subcategory":"Jewelry",
            "type":"Retail Goods"
        }
    ],
    "sg:phone":"+1 403 609 2424",
    "sg:postcode":"T1W 2B6",
    "sg:province":"AB",
    "sg:tags":[
        "jeweler"
    ],
    "wof:name":"Canmore Jewellers",
    "wof:placetype":"venue"
},
  "geometry": {"coordinates":[-115.358673,51.089333],"type":"Point"}
}