{
  "type": "Feature",
  "properties": {
    "addr:full":"1802 Centennial St Whitehorse YT Y1A 3Z4",
    "addr:housenumber":"1802",
    "addr:postcode":"y1a 3z4",
    "addr:street":"Centennial St",
    "iso:country":"CA",
    "sg:address":"1802 Centennial St",
    "sg:city":"Whitehorse",
    "sg:classifiers":[
        {
            "category":"Travel",
            "subcategory":"Hotels & Motels",
            "type":"Entertainment"
        }
    ],
    "sg:phone":"+1 867 633 2266",
    "sg:postcode":"Y1A 3Z4",
    "sg:province":"YT",
    "wof:name":"Casa Loma Motel",
    "wof:placetype":"venue"
},
  "geometry": {"coordinates":[-135.14807099999999,60.77158],"type":"Point"}
}