{
  "type": "Feature",
  "properties": {
    "addr:full":"5925 Airport Rd #200 Mississauga ON L4V 1W1",
    "addr:housenumber":"5925",
    "addr:postcode":"l4v 1w1",
    "addr:street":"Airport Rd # 200",
    "iso:country":"CA",
    "sg:address":"5925 Airport Rd #200",
    "sg:city":"Mississauga",
    "sg:classifiers":[
        {
            "category":"Real Estate",
            "subcategory":"Real Estate Agent",
            "type":"Services"
        }
    ],
    "sg:phone":"+1 905 672 1200",
    "sg:postcode":"L4V 1W1",
    "sg:province":"ON",
    "sg:tags":[
        "desk",
        "space"
    ],
    "wof:name":"Global Prime Office Network",
    "wof:placetype":"venue"
},
  "geometry": {"coordinates":[-79.6081085205,43.6860427856],"type":"Point"}
}