{
  "type": "Feature",
  "properties": {
    "addr:full":"52 Grand Ave London ON N6C 1L5",
    "addr:housenumber":"52",
    "addr:postcode":"n6c 1l5",
    "addr:street":"Grand Ave",
    "iso:country":"CA",
    "sg:address":"52 Grand Ave",
    "sg:city":"London",
    "sg:classifiers":[
        {
            "category":"Shopping",
            "subcategory":"Pharmacy",
            "type":"Retail Goods"
        }
    ],
    "sg:phone":"+1 519 672 3340",
    "sg:postcode":"N6C 1L5",
    "sg:province":"ON",
    "wof:name":"Turner Drug Store Ltd",
    "wof:placetype":"venue"
},
  "geometry": {"coordinates":[-81.2442474365,42.9717788696],"type":"Point"}
}