{
  "type": "Feature",
  "properties": {
    "addr:full":"Avon Rd Deep River ON K0J 1P0",
    "addr:postcode":"k0j 1p0",
    "addr:street":"Avon Rd",
    "iso:country":"CA",
    "sg:address":"Avon Rd",
    "sg:city":"Deep River",
    "sg:classifiers":[
        {
            "category":"Organizations",
            "subcategory":"Religious Organization",
            "type":"Services"
        }
    ],
    "sg:phone":"+1 613 584 4090",
    "sg:postcode":"K0J 1P0",
    "sg:province":"ON",
    "sg:tags":[
        "church"
    ],
    "wof:name":"Faith Lutheran Church",
    "wof:placetype":"venue"
},
  "geometry": {"coordinates":[-77.50479900000001,46.107723],"type":"Point"}
}