{
  "type": "Feature",
  "properties": {
    "addr:full":"Arden ON K0H 1B0",
    "addr:postcode":"k0h 1b0",
    "iso:country":"CA",
    "sg:city":"Arden",
    "sg:classifiers":[
        {
            "category":"Travel",
            "subcategory":"Campground",
            "type":"Entertainment"
        }
    ],
    "sg:phone":"+1 613 335 2114",
    "sg:postcode":"K0H 1B0",
    "sg:province":"ON",
    "sg:tags":[
        "camp"
    ],
    "wof:name":"Camp Kennebec South",
    "wof:placetype":"venue"
},
  "geometry": {"coordinates":[-76.924057,44.720909],"type":"Point"}
}