{
  "type": "Feature",
  "properties": {
    "addr:full":"Calgary AB T2M 0H5",
    "addr:postcode":"t2m 0h5",
    "iso:country":"CA",
    "sg:city":"Calgary",
    "sg:classifiers":[
        {
            "category":"Personal",
            "type":"Services"
        }
    ],
    "sg:phone":"+1 403 277 1283",
    "sg:postcode":"T2M 0H5",
    "sg:province":"AB",
    "sg:tags":[
        "therapist",
        "massage"
    ],
    "wof:name":"Mva Massage",
    "wof:placetype":"venue"
},
  "geometry": {"coordinates":[-114.066193,51.066757],"type":"Point"}
}