{
  "type": "Feature",
  "properties": {
    "addr:full":"777 Norquay Dr Winkler MB R6W 2S2",
    "addr:housenumber":"777",
    "addr:postcode":"r6w 2s2",
    "addr:street":"Norquay Dr",
    "iso:country":"CA",
    "sg:address":"777 Norquay Dr",
    "sg:city":"Winkler",
    "sg:classifiers":[
        {
            "category":"Shopping",
            "subcategory":"Pharmacy",
            "type":"Retail Goods"
        }
    ],
    "sg:phone":"+1 204 325 4744",
    "sg:postcode":"R6W 2S2",
    "sg:province":"MB",
    "wof:name":"Pharmasave",
    "wof:placetype":"venue"
},
  "geometry": {"coordinates":[-97.932510376,49.1905288696],"type":"Point"}
}