{
  "type": "Feature",
  "properties": {
    "addr:full":"6981 Mumford Rd Halifax NS B3L 2H7",
    "addr:housenumber":"6981",
    "addr:postcode":"b3l 2h7",
    "addr:street":"Mumford Rd",
    "iso:country":"CA",
    "sg:address":"6981 Mumford Rd",
    "sg:city":"Halifax",
    "sg:classifiers":[
        {
            "category":"Education",
            "subcategory":"School",
            "type":"Public Place"
        }
    ],
    "sg:phone":"+1 902 493 5132",
    "sg:postcode":"B3L 2H7",
    "sg:province":"NS",
    "wof:name":"St Agnes School",
    "wof:placetype":"venue"
},
  "geometry": {"coordinates":[-63.6186485291,44.6472206116],"type":"Point"}
}