{
  "type": "Feature",
  "properties": {
    "addr:full":"Concord ON L4K 1K8",
    "addr:postcode":"l4k 1k8",
    "iso:country":"CA",
    "sg:city":"Concord",
    "sg:classifiers":[
        {
            "category":"Manufacturing",
            "subcategory":"Signs",
            "type":"Manufacturing & Wholesale Goods"
        }
    ],
    "sg:phone":"+1 905 660 3371",
    "sg:postcode":"L4K 1K8",
    "sg:province":"ON",
    "wof:name":"Imperial Sign Ltd",
    "wof:placetype":"venue"
},
  "geometry": {"coordinates":[-79.4884796143,43.8171386719],"type":"Point"}
}