{
  "type": "Feature",
  "properties": {
    "addr:full":"40 Water St Digby NS B0V 1A0",
    "addr:housenumber":"40",
    "addr:postcode":"b0v 1a0",
    "addr:street":"Water St",
    "iso:country":"CA",
    "sg:address":"40 Water St",
    "sg:city":"Digby",
    "sg:classifiers":[
        {
            "category":"Restaurant",
            "type":"Food & Drink"
        }
    ],
    "sg:phone":"+1 902 245 5497",
    "sg:postcode":"B0V 1A0",
    "sg:province":"NS",
    "wof:name":"Boardwalk Cafe & Suites Ltd",
    "wof:placetype":"venue"
},
  "geometry": {"coordinates":[-65.7563323975,44.623790741],"type":"Point"}
}