{
  "type": "Feature",
  "properties": {
    "addr:full":"780 8 St SW Medicine Hat AB T1A 4M6",
    "addr:housenumber":"780 8",
    "addr:postcode":"t1a 4m6",
    "addr:street":"St Sw",
    "iso:country":"CA",
    "sg:address":"780 8 St SW",
    "sg:city":"Medicine Hat",
    "sg:classifiers":[
        {
            "category":"Travel",
            "subcategory":"Hotels & Motels",
            "type":"Entertainment"
        }
    ],
    "sg:phone":"+1 403 526 5981",
    "sg:postcode":"T1A 4M6",
    "sg:province":"AB",
    "wof:name":"Trans Canada Motel",
    "wof:placetype":"venue"
},
  "geometry": {"coordinates":[-110.70487199999999,50.03175],"type":"Point"}
}