{
  "type": "Feature",
  "properties": {
    "addr:full":"15 Victoria Ave Belleville ON K8N 1Z5",
    "addr:housenumber":"15",
    "addr:postcode":"k8n 1z5",
    "addr:street":"Victoria Ave",
    "iso:country":"CA",
    "sg:address":"15 Victoria Ave",
    "sg:city":"Belleville",
    "sg:classifiers":[
        {
            "category":"Professional",
            "subcategory":"Lawyer & Legal Services",
            "type":"Services"
        }
    ],
    "sg:phone":"+1 613 966 8156",
    "sg:postcode":"K8N 1Z5",
    "sg:province":"ON",
    "sg:tags":[
        "attorney"
    ],
    "wof:name":"Merrill Title Searching",
    "wof:placetype":"venue"
},
  "geometry": {"coordinates":[-77.38475,44.16629],"type":"Point"}
}