{
  "type": "Feature",
  "properties": {
    "addr:full":"2391 Boul St-Jean Saint-Maurice QC G0X 2X0",
    "addr:housenumber":"2391",
    "addr:postcode":"g0x 2x0",
    "addr:street":"Boul St-Jean",
    "iso:country":"CA",
    "sg:address":"2391 Boul St-Jean",
    "sg:city":"Saint-Maurice",
    "sg:classifiers":[
        {
            "category":"Organizations",
            "subcategory":"Religious Organization",
            "type":"Services"
        }
    ],
    "sg:phone":"+1 819 374 3371",
    "sg:postcode":"G0X 2X0",
    "sg:province":"QC",
    "sg:tags":[
        "church"
    ],
    "wof:name":"Eglise St Maurice",
    "wof:placetype":"venue"
},
  "geometry": {"coordinates":[-72.53257000000001,46.467968],"type":"Point"}
}