{
  "type": "Feature",
  "properties": {
    "addr:full":"Lloydminster AB T9V 2E8",
    "addr:postcode":"t9v 2e8",
    "iso:country":"CA",
    "sg:city":"Lloydminster",
    "sg:classifiers":[
        {
            "category":"Mining & Drilling",
            "type":"Manufacturing & Wholesale Goods"
        }
    ],
    "sg:phone":"+1 780 875 6035",
    "sg:postcode":"T9V 2E8",
    "sg:province":"AB",
    "sg:tags":[
        "field",
        "oil"
    ],
    "wof:name":"Wizard Well Svc Ltd",
    "wof:placetype":"venue"
},
  "geometry": {"coordinates":[-110.015151977,53.3034057617],"type":"Point"}
}