{
  "type": "Feature",
  "properties": {
    "addr:full":"340 Edinburgh Rd N Guelph ON N1H 7Y4",
    "addr:housenumber":"340",
    "addr:postcode":"n1h 7y4",
    "addr:street":"Edinburgh Rd N",
    "iso:country":"CA",
    "sg:address":"340 Edinburgh Rd N",
    "sg:city":"Guelph",
    "sg:classifiers":[
        {
            "category":"Manufacturing",
            "subcategory":"Metals",
            "type":"Manufacturing & Wholesale Goods"
        }
    ],
    "sg:phone":"+1 519 763 6633",
    "sg:postcode":"N1H 7Y4",
    "sg:province":"ON",
    "sg:tags":[
        "steel"
    ],
    "wof:name":"Welmar Group Mechanical Contr",
    "wof:placetype":"venue"
},
  "geometry": {"coordinates":[-80.275826,43.549973],"type":"Point"}
}