{
  "type": "Feature",
  "properties": {
    "addr:full":"1 Hutcherson Sq Scarborough ON M1B 1C5",
    "addr:housenumber":"1",
    "addr:postcode":"m1b 1c5",
    "addr:street":"Hutcherson Sq",
    "iso:country":"CA",
    "sg:address":"1 Hutcherson Sq",
    "sg:city":"Scarborough",
    "sg:classifiers":[
        {
            "category":"Home & Garden",
            "subcategory":"Carpets & Floor Coverings",
            "type":"Retail Goods"
        }
    ],
    "sg:phone":"+1 416 412 0111",
    "sg:postcode":"M1B 1C5",
    "sg:province":"ON",
    "sg:tags":[
        "dealer",
        "rug"
    ],
    "wof:name":"Pearl Carpets",
    "wof:placetype":"venue"
},
  "geometry": {"coordinates":[-79.22024500000001,43.799736],"type":"Point"}
}