{
  "type": "Feature",
  "properties": {
    "iso:country":"CA",
    "sg:address":"574 Stewart Blvd",
    "sg:city":"Brockville",
    "sg:classifiers":[
        {
            "category":"Health Services",
            "subcategory":"Health Practitioner",
            "type":"Services"
        }
    ],
    "sg:phone":"+1 613 498 3906",
    "sg:postcode":"K6V 7H2",
    "sg:province":"ON",
    "sg:tags":[
        "acupuncture"
    ],
    "wof:name":"Acupuncture & Traditional",
    "wof:placetype":"venue"
},
  "geometry": {"coordinates":[-75.7145233154,44.6038475037],"type":"Point"}
}