{
  "type": "Feature",
  "properties": {
    "iso:country":"CA",
    "sg:city":"Grande Prairie",
    "sg:classifiers":[
        {
            "category":"Insurance",
            "subcategory":"Insurance Agent",
            "type":"Services"
        }
    ],
    "sg:phone":"+1 780 538 4464",
    "sg:postcode":"T8V 0T8",
    "sg:province":"AB",
    "wof:name":"Mary Jo Mather Registered",
    "wof:placetype":"venue"
},
  "geometry": {"coordinates":[-118.788986206,55.1708374023],"type":"Point"}
}