{
  "type": "Feature",
  "properties": {
    "addr:full":"955 Main St Winnipeg MB R2W 3P2",
    "addr:housenumber":"955",
    "addr:postcode":"r2w 3p2",
    "addr:street":"Main St",
    "iso:country":"CA",
    "sg:address":"955 Main St",
    "sg:city":"Winnipeg",
    "sg:classifiers":[
        {
            "category":"Shopping",
            "subcategory":"Jewelry",
            "type":"Retail Goods"
        }
    ],
    "sg:phone":"+1 204 943 7851",
    "sg:postcode":"R2W 3P2",
    "sg:province":"MB",
    "sg:tags":[
        "jeweler"
    ],
    "wof:name":"Golden Hand Jewellery",
    "wof:placetype":"venue"
},
  "geometry": {"coordinates":[-97.132423,49.911377],"type":"Point"}
}