{
  "type": "Feature",
  "properties": {
    "addr:full":"Winnipeg MB R3B 1K2",
    "addr:postcode":"r3b 1k2",
    "iso:country":"CA",
    "sg:city":"Winnipeg",
    "sg:classifiers":[
        {
            "category":"Professional",
            "subcategory":"Business Services",
            "type":"Services"
        }
    ],
    "sg:phone":"+1 204 944 0008",
    "sg:postcode":"R3B 1K2",
    "sg:province":"MB",
    "sg:tags":[
        "interior",
        "consultant",
        "design",
        "decorator"
    ],
    "wof:name":"Xyz Design Intl Inc",
    "wof:placetype":"venue"
},
  "geometry": {"coordinates":[-97.1432723999,49.897277832],"type":"Point"}
}