{
  "type": "Feature",
  "properties": {
    "addr:full":"Kemptville ON K0G 1J0",
    "addr:postcode":"k0g 1j0",
    "iso:country":"CA",
    "sg:city":"Kemptville",
    "sg:classifiers":[
        {
            "category":"Health Services",
            "subcategory":"Hospital",
            "type":"Services"
        }
    ],
    "sg:phone":"+1 613 258 1959",
    "sg:postcode":"K0G 1J0",
    "sg:province":"ON",
    "sg:tags":[
        "mental"
    ],
    "wof:name":"Child & Youth Wellness Ctr",
    "wof:placetype":"venue"
},
  "geometry": {"coordinates":[-75.637604,45.015831],"type":"Point"}
}