{
  "type": "Feature",
  "properties": {
    "addr:full":"Ottawa ON K1A 0K2",
    "addr:postcode":"k1a 0k2",
    "iso:country":"CA",
    "sg:city":"Ottawa",
    "sg:classifiers":[
        {
            "category":"Travel",
            "subcategory":"Hotels & Motels",
            "type":"Entertainment"
        }
    ],
    "sg:phone":"+1 613 746 1449",
    "sg:postcode":"K1A 0K2",
    "sg:province":"ON",
    "sg:tags":[
        "resort",
        "center",
        "skiing"
    ],
    "wof:name":"Forces Ottawa Ski Club",
    "wof:placetype":"venue"
},
  "geometry": {"coordinates":[-75.67795599999999,45.446079],"type":"Point"}
}