{
  "type": "Feature",
  "properties": {
    "addr:full":"PO Box 693 Valleyview AB T0H 3N0",
    "addr:housenumber":"po",
    "addr:postcode":"ab t0h 3n0",
    "addr:street":"Box 693",
    "iso:country":"CA",
    "sg:address":"PO Box 693",
    "sg:city":"Valleyview",
    "sg:classifiers":[
        {
            "category":"Professional",
            "subcategory":"Business Services",
            "type":"Services"
        }
    ],
    "sg:phone":"+1 780 524 2001",
    "sg:postcode":"T0H 3N0",
    "sg:province":"AB",
    "wof:name":"Vetsch Steaming & Vacuum Svc",
    "wof:placetype":"venue"
},
  "geometry": {"coordinates":[-117.271774292,55.0686416626],"type":"Point"}
}