{
  "type": "Feature",
  "properties": {
    "addr:full":"3679 Ch Du Lac-Sept-Iles Saint-Raymond QC G3L 2S3",
    "addr:postcode":"3679;g3l 2s3",
    "addr:street":"Ch Du Lac-Sept-Iles",
    "iso:country":"CA",
    "sg:address":"3679 Ch Du Lac-Sept-Iles",
    "sg:city":"Saint-Raymond",
    "sg:classifiers":[
        {
            "category":"Travel",
            "subcategory":"Hotels & Motels",
            "type":"Entertainment"
        }
    ],
    "sg:phone":"+1 418 337 8893",
    "sg:postcode":"G3L 2S3",
    "sg:province":"QC",
    "wof:name":"Manoir Du Lac Sept-Lies",
    "wof:placetype":"venue"
},
  "geometry": {"coordinates":[-71.73865499999999,46.92075],"type":"Point"}
}