{
  "type": "Feature",
  "properties": {
    "addr:full":"2091 Boul Des Laurentides Laval QC H7M 4M2",
    "addr:housenumber":"2091",
    "addr:postcode":"h7m 4m2",
    "addr:street":"Boul Des Laurentides",
    "iso:country":"CA",
    "sg:address":"2091 Boul Des Laurentides",
    "sg:city":"Laval",
    "sg:classifiers":[
        {
            "category":"Wholesale",
            "subcategory":"Furniture",
            "type":"Manufacturing & Wholesale Goods"
        }
    ],
    "sg:phone":"+1 450 975 0898",
    "sg:postcode":"H7M 4M2",
    "sg:province":"QC",
    "wof:name":"R C Samson Equipement-Bureau",
    "wof:placetype":"venue"
},
  "geometry": {"coordinates":[-73.73347473139999,45.6079330444],"type":"Point"}
}