{
  "type": "Feature",
  "properties": {
    "addr:full":"Port Mcneill BC V0N 2R0",
    "addr:postcode":"v0n 2r0",
    "iso:country":"CA",
    "sg:city":"Port Mcneill",
    "sg:classifiers":[
        {
            "category":"Organizations",
            "subcategory":"Professional Association",
            "type":"Services"
        }
    ],
    "sg:phone":"+1 250 956 4722",
    "sg:postcode":"V0N 2R0",
    "sg:province":"BC",
    "wof:name":"Vancouver Island Teachers Assn",
    "wof:placetype":"venue"
},
  "geometry": {"coordinates":[-127.085960388,50.5909309387],"type":"Point"}
}