{
  "type": "Feature",
  "properties": {
    "addr:full":"4901 50 Ave Bentley AB T0C 0J0",
    "addr:housenumber":"4901",
    "addr:postcode":"t0c 0j0",
    "addr:street":"50 Ave",
    "iso:country":"CA",
    "sg:address":"4901 50 Ave",
    "sg:city":"Bentley",
    "sg:classifiers":[
        {
            "category":"Organizations",
            "subcategory":"Religious Organization",
            "type":"Services"
        }
    ],
    "sg:phone":"+1 403 748 3780",
    "sg:postcode":"T0C 0J0",
    "sg:province":"AB",
    "sg:tags":[
        "church"
    ],
    "wof:name":"United Church",
    "wof:placetype":"venue"
},
  "geometry": {"coordinates":[-114.047332764,52.4648284912],"type":"Point"}
}