{
  "type": "Feature",
  "properties": {
    "addr:full":"2693 Braeside St Abbotsford BC V2T 2R5",
    "addr:postcode":"2693;v2t 2r5",
    "addr:street":"Braeside St",
    "iso:country":"CA",
    "sg:address":"2693 Braeside St",
    "sg:city":"Abbotsford",
    "sg:classifiers":[
        {
            "category":"Organizations",
            "subcategory":"Non-profit Organization",
            "type":"Services"
        }
    ],
    "sg:phone":"+1 604 855 4440",
    "sg:postcode":"V2T 2R5",
    "sg:province":"BC",
    "sg:tags":[
        "information",
        "alcoholism",
        "treatment"
    ],
    "wof:name":"Life Recovery Assn",
    "wof:placetype":"venue"
},
  "geometry": {"coordinates":[-122.346283,49.05167],"type":"Point"}
}