{
  "type": "Feature",
  "properties": {
    "addr:full":"3525 Ch DE LA Valliere Sorel-Tracy QC J3P 5N3",
    "addr:postcode":"3525;j3p 5n3",
    "addr:street":"Ch De La Valliere",
    "iso:country":"CA",
    "sg:address":"3525 Ch DE LA Valliere",
    "sg:city":"Sorel-Tracy",
    "sg:classifiers":[
        {
            "category":"Professional",
            "subcategory":"Business Services",
            "type":"Services"
        }
    ],
    "sg:phone":"+1 450 743 0758",
    "sg:postcode":"J3P 5N3",
    "sg:province":"QC",
    "sg:tags":[
        "recycling",
        "center"
    ],
    "wof:name":"Richer & Frere Inc",
    "wof:placetype":"venue"
},
  "geometry": {"coordinates":[-73.0383987427,46.0316314697],"type":"Point"}
}