{
  "type": "Feature",
  "properties": {
    "addr:full":"Sudbury ON P3E 1A4",
    "addr:postcode":"p3e 1a4",
    "iso:country":"CA",
    "sg:city":"Sudbury",
    "sg:classifiers":[
        {
            "category":"Banks & Credit Unions",
            "subcategory":"Bank",
            "type":"Services"
        }
    ],
    "sg:phone":"+1 705 673 3621",
    "sg:postcode":"P3E 1A4",
    "sg:province":"ON",
    "sg:tags":[
        "financing"
    ],
    "wof:name":"Roy Nat Inc",
    "wof:placetype":"venue"
},
  "geometry": {"coordinates":[-80.996284,46.492344],"type":"Point"}
}