{
  "type": "Feature",
  "properties": {
    "addr:full":"Richmond BC V6V 2N8",
    "addr:postcode":"v6v 2n8",
    "iso:country":"CA",
    "sg:city":"Richmond",
    "sg:classifiers":[
        {
            "category":"Manufacturing",
            "subcategory":"Pottery",
            "type":"Manufacturing & Wholesale Goods"
        }
    ],
    "sg:phone":"+1 604 270 8975",
    "sg:postcode":"V6V 2N8",
    "sg:province":"BC",
    "wof:name":"Future Fashions",
    "wof:placetype":"venue"
},
  "geometry": {"coordinates":[-123.071716,49.180859],"type":"Point"}
}