{
  "type": "Feature",
  "properties": {
    "addr:full":"Stoney Creek ON L8J 1P8",
    "addr:postcode":"l8j 1p8",
    "iso:country":"CA",
    "sg:city":"Stoney Creek",
    "sg:classifiers":[
        {
            "category":"Retail",
            "subcategory":"Laundry & Dry Cleaning",
            "type":"Services"
        }
    ],
    "sg:phone":"+1 905 560 2894",
    "sg:postcode":"L8J 1P8",
    "sg:province":"ON",
    "sg:tags":[
        "cleaners"
    ],
    "wof:name":"Crown Cleaners",
    "wof:placetype":"venue"
},
  "geometry": {"coordinates":[-79.7942352295,43.1995658875],"type":"Point"}
}