{
  "type": "Feature",
  "properties": {
    "addr:full":"Mississauga ON L5A 4E7",
    "addr:postcode":"l5a 4e7",
    "iso:country":"CA",
    "sg:city":"Mississauga",
    "sg:classifiers":[
        {
            "category":"Shopping",
            "subcategory":"Florist",
            "type":"Retail Goods"
        }
    ],
    "sg:phone":"+1 905 306 0223",
    "sg:postcode":"L5A 4E7",
    "sg:province":"ON",
    "wof:name":"Fairview Florist",
    "wof:placetype":"venue"
},
  "geometry": {"coordinates":[-79.6257400513,43.5871047974],"type":"Point"}
}