{
  "type": "Feature",
  "properties": {
    "addr:full":"63 Queensway E Simcoe ON N3Y 4M5",
    "addr:housenumber":"63",
    "addr:postcode":"n3y 4m5",
    "addr:street":"Queensway E",
    "iso:country":"CA",
    "sg:address":"63 Queensway E",
    "sg:city":"Simcoe",
    "sg:classifiers":[
        {
            "category":"Real Estate",
            "subcategory":"Real Estate Agent",
            "type":"Services"
        }
    ],
    "sg:phone":"+1 519 426 7187",
    "sg:postcode":"N3Y 4M5",
    "sg:province":"ON",
    "wof:name":"Royal Le Page Brown Realty",
    "wof:placetype":"venue"
},
  "geometry": {"coordinates":[-80.301292,42.847214],"type":"Point"}
}