{
  "type": "Feature",
  "properties": {
    "addr:full":"4102 Boul Dorchester O Westmount QC H3Z 1V1",
    "addr:housenumber":"4102",
    "addr:postcode":"h3z 1v1",
    "addr:street":"Boul Dorchester O",
    "iso:country":"CA",
    "sg:address":"4102 Boul Dorchester O",
    "sg:city":"Westmount",
    "sg:classifiers":[
        {
            "category":"Social Services",
            "type":"Services"
        }
    ],
    "sg:phone":"+1 514 932 5306",
    "sg:postcode":"H3Z 1V1",
    "sg:province":"QC",
    "sg:tags":[
        "organization",
        "welfare"
    ],
    "wof:name":"Armee Du Salut",
    "wof:placetype":"venue"
},
  "geometry": {"coordinates":[-73.585052,45.486866],"type":"Point"}
}