{
  "type": "Feature",
  "properties": {
    "addr:full":"394 Tranquille Rd Kamloops BC V2B 3G7",
    "addr:housenumber":"394",
    "addr:postcode":"bc v2b 3g7",
    "addr:street":"Tranquille Rd",
    "iso:country":"CA",
    "sg:address":"394 Tranquille Rd",
    "sg:city":"Kamloops",
    "sg:classifiers":[
        {
            "category":"Personal",
            "subcategory":"Beauty Salon",
            "type":"Services"
        }
    ],
    "sg:phone":"+1 250 376 4021",
    "sg:postcode":"V2B 3G7",
    "sg:province":"BC",
    "wof:name":"Mary's Beauty Salon",
    "wof:placetype":"venue"
},
  "geometry": {"coordinates":[-120.35807800000001,50.689789],"type":"Point"}
}