{
  "type": "Feature",
  "properties": {
    "iso:country":"CA",
    "sg:address":"10002 94 Ave",
    "sg:city":"Grande Prairie",
    "sg:classifiers":[
        {
            "category":"Food & Beverages",
            "subcategory":"Specialty",
            "type":"Retail Goods"
        }
    ],
    "sg:phone":"+1 780 538 9710",
    "sg:postcode":"T8V 0K5",
    "sg:province":"AB",
    "sg:tags":[
        "water",
        "bulk",
        "company"
    ],
    "wof:name":"Water Express",
    "wof:placetype":"venue"
},
  "geometry": {"coordinates":[-118.79517364500001,55.1654167175],"type":"Point"}
}