{
  "type": "Feature",
  "properties": {
    "addr:full":"65 Sixth Ave E New Westminster BC V3L 4G6",
    "addr:housenumber":"65",
    "addr:postcode":"v3l 4g6",
    "addr:street":"Sixth Ave E",
    "iso:country":"CA",
    "sg:address":"65 Sixth Ave E",
    "sg:city":"New Westminster",
    "sg:classifiers":[
        {
            "category":"Museum",
            "type":"Entertainment"
        }
    ],
    "sg:phone":"+1 604 527 4639",
    "sg:postcode":"V3L 4G6",
    "sg:province":"BC",
    "sg:tags":[
        "government"
    ],
    "wof:name":"Canadian Lacrosse Hall of Fame",
    "wof:placetype":"venue"
},
  "geometry": {"coordinates":[-122.906319,49.220818],"type":"Point"}
}