{
  "type": "Feature",
  "properties": {
    "addr:full":"8999 Young Rd Chilliwack BC V2P 4R9",
    "addr:housenumber":"8999",
    "addr:postcode":"v2p 4r9",
    "addr:street":"Young Rd",
    "iso:country":"CA",
    "sg:address":"8999 Young Rd",
    "sg:city":"Chilliwack",
    "sg:classifiers":[
        {
            "category":"Professional",
            "subcategory":"Accounting & Tax Preparation",
            "type":"Services"
        }
    ],
    "sg:phone":"+1 604 792 3366",
    "sg:postcode":"V2P 4R9",
    "sg:province":"BC",
    "sg:tags":[
        "accountant"
    ],
    "wof:name":"Nicklom Conlin & CO",
    "wof:placetype":"venue"
},
  "geometry": {"coordinates":[-121.952667236,49.1655006409],"type":"Point"}
}