{
  "type": "Feature",
  "properties": {
    "addr:full":"2651 John St Markham ON L3R 2W5",
    "addr:housenumber":"2651",
    "addr:postcode":"l3r 2w5",
    "addr:street":"John St",
    "iso:country":"CA",
    "sg:address":"2651 John St",
    "sg:city":"Markham",
    "sg:classifiers":[
        {
            "category":"Real Estate",
            "subcategory":"Architect",
            "type":"Services"
        }
    ],
    "sg:phone":"+1 905 477 1065",
    "sg:postcode":"L3R 2W5",
    "sg:province":"ON",
    "wof:name":"Venchiarutti Gagliardi Archt",
    "wof:placetype":"venue"
},
  "geometry": {"coordinates":[-79.358505249,43.8247489929],"type":"Point"}
}