{
  "type": "Feature",
  "properties": {
    "addr:full":"89 Division St Colborne ON K0K 1S0",
    "addr:housenumber":"89",
    "addr:postcode":"k0k 1s0",
    "addr:street":"Division St",
    "iso:country":"CA",
    "sg:address":"89 Division St",
    "sg:city":"Colborne",
    "sg:classifiers":[
        {
            "category":"Organizations",
            "subcategory":"Religious Organization",
            "type":"Services"
        }
    ],
    "sg:phone":"+1 905 355 2179",
    "sg:postcode":"K0K 1S0",
    "sg:province":"ON",
    "sg:tags":[
        "church"
    ],
    "wof:name":"Colborne Pentecostal Church",
    "wof:placetype":"venue"
},
  "geometry": {"coordinates":[-77.884964,43.99873],"type":"Point"}
}