{
  "type": "Feature",
  "properties": {
    "addr:full":"11857 Peggys Cove Rd French Village NS B3Z 2X7",
    "addr:housenumber":"11857",
    "addr:postcode":"b3z 2x7",
    "addr:street":"Peggys Cove Rd",
    "iso:country":"CA",
    "sg:address":"11857 Peggys Cove Rd",
    "sg:city":"French Village",
    "sg:classifiers":[
        {
            "category":"Building & Trades",
            "subcategory":"Construction",
            "type":"Services"
        }
    ],
    "sg:phone":"+1 902 823 2360",
    "sg:postcode":"B3Z 2X7",
    "sg:province":"NS",
    "sg:tags":[
        "designer",
        "marine",
        "contractor"
    ],
    "wof:name":"Polaris Marine Svc Ltd",
    "wof:placetype":"venue"
},
  "geometry": {"coordinates":[-63.913338,44.63311],"type":"Point"}
}