{
  "type": "Feature",
  "properties": {
    "addr:full":"Fermont QC G0G 1J0",
    "addr:postcode":"g0g 1j0",
    "iso:country":"CA",
    "sg:city":"Fermont",
    "sg:classifiers":[
        {
            "category":"Health Services",
            "subcategory":"Optometrist",
            "type":"Services"
        }
    ],
    "sg:phone":"+1 418 287 5959",
    "sg:postcode":"G0G 1J0",
    "sg:province":"QC",
    "wof:name":"Iris Clinique D'Optometrie",
    "wof:placetype":"venue"
},
  "geometry": {"coordinates":[-67.080528,52.796814],"type":"Point"}
}