{
  "type": "Feature",
  "properties": {
    "addr:full":"510 6 Ave S Lethbridge AB T1J 0Y8",
    "addr:housenumber":"510",
    "addr:postcode":"t1j 0y8",
    "addr:street":"6 Ave S",
    "iso:country":"CA",
    "sg:address":"510 6 Ave S",
    "sg:city":"Lethbridge",
    "sg:classifiers":[
        {
            "category":"Food & Beverages",
            "subcategory":"Meat & Fish",
            "type":"Retail Goods"
        }
    ],
    "sg:phone":"+1 403 327 3492",
    "sg:postcode":"T1J 0Y8",
    "sg:province":"AB",
    "wof:name":"Alberta Meat Market Ltd",
    "wof:placetype":"venue"
},
  "geometry": {"coordinates":[-112.837914,49.690918],"type":"Point"}
}