{
  "type": "Feature",
  "properties": {
    "addr:full":"575 Rue Pierre-Caisse Saint-Jean-Sur-Richelieu QC J3A 1P1",
    "addr:housenumber":"575",
    "addr:postcode":"j3a 1p1",
    "addr:street":"Rue Pierre-Caisse",
    "iso:country":"CA",
    "sg:address":"575 Rue Pierre-Caisse",
    "sg:city":"Saint-Jean-Sur-Richelieu",
    "sg:classifiers":[
        {
            "category":"Shopping",
            "subcategory":"Clothing, Apparel, & Fashions",
            "type":"Retail Goods"
        }
    ],
    "sg:phone":"+1 450 359 7676",
    "sg:postcode":"J3A 1P1",
    "sg:province":"QC",
    "sg:tags":[
        "furnishing"
    ],
    "wof:name":"Moores Vetements Pour Hommes",
    "wof:placetype":"venue"
},
  "geometry": {"coordinates":[-73.2804031372,45.3319664001],"type":"Point"}
}