{
  "type": "Feature",
  "properties": {
    "addr:full":"1450 Rue Eugene-Labelle Terrebonne QC J6W 3M4",
    "addr:housenumber":"1450",
    "addr:postcode":"j6w 3m4",
    "addr:street":"Rue Eugene-Labelle",
    "iso:country":"CA",
    "sg:address":"1450 Rue Eugene-Labelle",
    "sg:city":"Terrebonne",
    "sg:classifiers":[
        {
            "category":"Professional",
            "subcategory":"Accounting & Tax Preparation",
            "type":"Services"
        }
    ],
    "sg:phone":"+1 450 964 1929",
    "sg:postcode":"J6W 3M4",
    "sg:province":"QC",
    "sg:tags":[
        "return",
        "filing"
    ],
    "wof:name":"Jbs Impot Svc Enr",
    "wof:placetype":"venue"
},
  "geometry": {"coordinates":[-73.6485748291,45.6946983337],"type":"Point"}
}