{
  "type": "Feature",
  "properties": {
    "addr:full":"1550 Rue Metcalfe # 903 Montreal QC H3A 1X6",
    "addr:housenumber":"1550",
    "addr:postcode":"h3a 1x6",
    "addr:street":"Rue Metcalfe # 903",
    "iso:country":"CA",
    "sg:address":"1550 Rue Metcalfe # 903",
    "sg:city":"Montreal",
    "sg:classifiers":[
        {
            "category":"Professional",
            "subcategory":"Lawyer & Legal Services",
            "type":"Services"
        }
    ],
    "sg:phone":"+1 514 849 7311",
    "sg:postcode":"H3A 1X6",
    "sg:province":"QC",
    "sg:tags":[
        "attorney"
    ],
    "wof:name":"Ferdoussi, Waice",
    "wof:placetype":"venue"
},
  "geometry": {"coordinates":[-73.573677,45.501305],"type":"Point"}
}