{
  "type": "Feature",
  "properties": {
    "addr:full":"575 Route 100 Russell ON K4R 1E5",
    "addr:housenumber":"575",
    "addr:postcode":"k4r 1e5",
    "addr:street":"Route 100",
    "iso:country":"CA",
    "sg:address":"575 Route 100",
    "sg:city":"Russell",
    "sg:classifiers":[
        {
            "category":"Real Estate",
            "subcategory":"Real Estate Agent",
            "type":"Services"
        }
    ],
    "sg:phone":"+1 613 445 8662",
    "sg:postcode":"K4R 1E5",
    "sg:province":"ON",
    "sg:tags":[
        "inspection"
    ],
    "wof:name":"Azar Home & Building Inspctn",
    "wof:placetype":"venue"
},
  "geometry": {"coordinates":[-75.379456,45.308727],"type":"Point"}
}