{
  "type": "Feature",
  "properties": {
    "addr:full":"1495 Gerald St Cornwall ON K6H 7G8",
    "addr:housenumber":"1495",
    "addr:postcode":"k6h 7g8",
    "addr:street":"Gerald St",
    "iso:country":"CA",
    "sg:address":"1495 Gerald St",
    "sg:city":"Cornwall",
    "sg:classifiers":[
        {
            "category":"Autos & Motor Vehicles",
            "subcategory":"Auto Supplies",
            "type":"Retail Goods"
        }
    ],
    "sg:phone":"+1 613 930 2615",
    "sg:postcode":"K6H 7G8",
    "sg:province":"ON",
    "sg:tags":[
        "filter",
        "gas"
    ],
    "wof:name":"Rcg Products Inc",
    "wof:placetype":"venue"
},
  "geometry": {"coordinates":[-74.730217,45.044991],"type":"Point"}
}