{
  "type": "Feature",
  "properties": {
    "addr:full":"394 Leishman Rd Campbell River BC V9W 3V6",
    "addr:housenumber":"394",
    "addr:postcode":"v9w 3v6",
    "addr:street":"Leishman Rd",
    "iso:country":"CA",
    "sg:address":"394 Leishman Rd",
    "sg:city":"Campbell River",
    "sg:classifiers":[
        {
            "category":"Social Services",
            "subcategory":"Child Care",
            "type":"Services"
        }
    ],
    "sg:phone":"+1 250 286 6443",
    "sg:postcode":"V9W 3V6",
    "sg:province":"BC",
    "wof:name":"Leishman Child Care Ctr",
    "wof:placetype":"venue"
},
  "geometry": {"coordinates":[-125.24339294400001,50.0128364563],"type":"Point"}
}