{
  "type": "Feature",
  "properties": {
    "addr:full":"244 12E Av Ferme-Neuve QC J0W 1C0",
    "addr:housenumber":"244",
    "addr:postcode":"j0w 1c0",
    "addr:street":"12E Av Ferme-Neuve",
    "iso:country":"CA",
    "sg:address":"244 12E Av",
    "sg:city":"Ferme-Neuve",
    "sg:classifiers":[
        {
            "category":"Organizations",
            "subcategory":"Religious Organization",
            "type":"Services"
        }
    ],
    "sg:phone":"+1 819 587 3261",
    "sg:postcode":"J0W 1C0",
    "sg:province":"QC",
    "wof:name":"Presbytere DE Ferme-Neuve",
    "wof:placetype":"venue"
},
  "geometry": {"coordinates":[-75.449539,46.701275],"type":"Point"}
}