{
  "type": "Feature",
  "properties": {
    "addr:full":"8984 Oakes Rd Black Creek BC V9J 1J2",
    "addr:housenumber":"8984",
    "addr:postcode":"v9j 1j2",
    "addr:street":"Oakes Rd",
    "iso:country":"CA",
    "sg:address":"8984 Oakes Rd",
    "sg:city":"Black Creek",
    "sg:classifiers":[
        {
            "category":"Professional",
            "subcategory":"Accounting & Tax Preparation",
            "type":"Services"
        }
    ],
    "sg:phone":"+1 250 337 8925",
    "sg:postcode":"V9J 1J2",
    "sg:province":"BC",
    "sg:tags":[
        "bookkeeping",
        "general"
    ],
    "wof:name":"David A Broome Bookkeeping",
    "wof:placetype":"venue"
},
  "geometry": {"coordinates":[-125.135002136,49.843006134],"type":"Point"}
}