{
  "type": "Feature",
  "properties": {
    "addr:full":"9 Rue Normandeau Saint-Mathias-Sur-Richelieu QC J3L 6G1",
    "addr:housenumber":"9",
    "addr:postcode":"j3l 6g1",
    "addr:street":"Rue Normandeau",
    "iso:country":"CA",
    "sg:address":"9 Rue Normandeau",
    "sg:city":"Saint-Mathias-Sur-Richelieu",
    "sg:classifiers":[
        {
            "category":"Retail",
            "subcategory":"Animal Services",
            "type":"Services"
        }
    ],
    "sg:phone":"+1 450 447 0775",
    "sg:postcode":"J3L 6G1",
    "sg:province":"QC",
    "sg:tags":[
        "pet",
        "grooming",
        "washing"
    ],
    "wof:name":"Degentilly",
    "wof:placetype":"venue"
},
  "geometry": {"coordinates":[-73.266456604,45.4553031921],"type":"Point"}
}