{
  "type": "Feature",
  "properties": {
    "addr:full":"810 George St Hearst ON P0L 1N0",
    "addr:housenumber":"810",
    "addr:postcode":"p0l 1n0",
    "addr:street":"George St",
    "iso:country":"CA",
    "sg:address":"810 George St",
    "sg:city":"Hearst",
    "sg:classifiers":[
        {
            "category":"Communications",
            "subcategory":"Television Station",
            "type":"Services"
        }
    ],
    "sg:phone":"+1 705 362 4255",
    "sg:postcode":"P0L 1N0",
    "sg:province":"ON",
    "sg:tags":[
        "broadcasting",
        "co"
    ],
    "wof:name":"Radio Canada",
    "wof:placetype":"venue"
},
  "geometry": {"coordinates":[-83.66295599999999,49.688931],"type":"Point"}
}