{
  "type": "Feature",
  "properties": {
    "iso:country":"CA",
    "sg:address":"125 Talbot St W",
    "sg:city":"Leamington",
    "sg:classifiers":[
        {
            "category":"Education",
            "subcategory":"School",
            "type":"Public Place"
        }
    ],
    "sg:phone":"+1 519 326 6191",
    "sg:postcode":"N8H 1N2",
    "sg:province":"ON",
    "wof:name":"Leamington District Secondary",
    "wof:placetype":"venue"
},
  "geometry": {"coordinates":[-82.607033,42.05143],"type":"Point"}
}