{
  "type": "Feature",
  "properties": {
    "addr:full":"1 Harris St S Perth ON K7H 2X8",
    "addr:housenumber":"1",
    "addr:postcode":"k7h 2x8",
    "addr:street":"Harris St S",
    "iso:country":"CA",
    "sg:address":"1 Harris St S",
    "sg:city":"Perth",
    "sg:classifiers":[
        {
            "category":"Shopping",
            "type":"Retail Goods"
        }
    ],
    "sg:phone":"+1 613 264 2969",
    "sg:postcode":"K7H 2X8",
    "sg:province":"ON",
    "sg:tags":[
        "wheel",
        "chair",
        "scooter",
        "elevator"
    ],
    "wof:name":"Mobility Care CO",
    "wof:placetype":"venue"
},
  "geometry": {"coordinates":[-76.25843,44.905483],"type":"Point"}
}