{
  "type": "Feature",
  "properties": {
    "addr:full":"63421 Yale Rd Hope BC V0X 1L2",
    "addr:housenumber":"63421",
    "addr:postcode":"v0x 1l2",
    "addr:street":"Yale Rd",
    "iso:country":"CA",
    "sg:address":"63421 Yale Rd",
    "sg:city":"Hope",
    "sg:classifiers":[
        {
            "category":"Travel",
            "subcategory":"Travel Agent",
            "type":"Entertainment"
        }
    ],
    "sg:phone":"+1 604 869 7306",
    "sg:postcode":"V0X 1L2",
    "sg:province":"BC",
    "sg:tags":[
        "agency",
        "bureau"
    ],
    "wof:name":"All Points Bus Charters",
    "wof:placetype":"venue"
},
  "geometry": {"coordinates":[-121.475433,49.367352],"type":"Point"}
}