{
  "type": "Feature",
  "properties": {
    "addr:full":"Medicine Hat AB T1A 0H2",
    "addr:postcode":"t1a 0h2",
    "iso:country":"CA",
    "sg:city":"Medicine Hat",
    "sg:classifiers":[
        {
            "category":"Professional",
            "subcategory":"Management & Consulting",
            "type":"Services"
        }
    ],
    "sg:phone":"+1 403 529 1226",
    "sg:postcode":"T1A 0H2",
    "sg:province":"AB",
    "sg:tags":[
        "consultant",
        "business"
    ],
    "wof:name":"Howard Interpersonal Dynamics",
    "wof:placetype":"venue"
},
  "geometry": {"coordinates":[-110.67614,50.03949],"type":"Point"}
}