{
  "type": "Feature",
  "properties": {
    "iso:country":"CA",
    "sg:city":"Toronto",
    "sg:classifiers":[
        {
            "category":"Professional",
            "subcategory":"Research",
            "type":"Services"
        }
    ],
    "sg:phone":"+1 416 867 3141",
    "sg:postcode":"M5H 3R3",
    "sg:province":"ON",
    "sg:tags":[
        "market",
        "analysis"
    ],
    "wof:name":"Kircher Research Assoc",
    "wof:placetype":"venue"
},
  "geometry": {"coordinates":[-79.38004302980001,43.6523780823],"type":"Point"}
}