{
  "type": "Feature",
  "properties": {
    "addr:full":"25 Rue Saint-Joseph E Quebec QC G1K 3A6",
    "addr:housenumber":"25",
    "addr:postcode":"g1k 3a6",
    "addr:street":"Rue Saint-Joseph E",
    "iso:country":"CA",
    "sg:address":"25 Rue Saint-Joseph E",
    "sg:city":"Quebec",
    "sg:classifiers":[
        {
            "category":"Wholesale",
            "subcategory":"Furniture",
            "type":"Manufacturing & Wholesale Goods"
        }
    ],
    "sg:phone":"+1 418 647 1332",
    "sg:postcode":"G1K 3A6",
    "sg:province":"QC",
    "wof:name":"Mobilier DE Bureau Mbh",
    "wof:placetype":"venue"
},
  "geometry": {"coordinates":[-71.23053,46.812164],"type":"Point"}
}