{
  "type": "Feature",
  "properties": {
    "iso:country":"CA",
    "sg:city":"Saint-Laurent",
    "sg:classifiers":[
        {
            "category":"Professional",
            "subcategory":"Employment Agencies",
            "type":"Services"
        }
    ],
    "sg:phone":"+1 514 335 3774",
    "sg:postcode":"H4R 1W4",
    "sg:province":"QC",
    "sg:tags":[
        "opportunity"
    ],
    "wof:name":"Advantage Personnel Ltd",
    "wof:placetype":"venue"
},
  "geometry": {"coordinates":[-73.714554,45.496174],"type":"Point"}
}