{
  "type": "Feature",
  "properties": {
    "addr:full":"3272 Broadway W Vancouver BC V6K 2H4",
    "addr:housenumber":"3272",
    "addr:postcode":"v6k 2h4",
    "addr:street":"Broadway W",
    "iso:country":"CA",
    "sg:address":"3272 Broadway W",
    "sg:city":"Vancouver",
    "sg:classifiers":[
        {
            "category":"Personal",
            "subcategory":"Beauty Salon",
            "type":"Services"
        }
    ],
    "sg:phone":"+1 604 738 2826",
    "sg:postcode":"V6K 2H4",
    "sg:province":"BC",
    "wof:name":"Amethyst Skin Care Ctr",
    "wof:placetype":"venue"
},
  "geometry": {"coordinates":[-123.177094,49.264065],"type":"Point"}
}