{
  "type": "Feature",
  "properties": {
    "addr:full":"4726 Canada Way Burnaby BC V5G 1L2",
    "addr:housenumber":"4726",
    "addr:postcode":"v5g 1l2",
    "addr:street":"Canada Way",
    "iso:country":"CA",
    "sg:address":"4726 Canada Way",
    "sg:city":"Burnaby",
    "sg:classifiers":[
        {
            "category":"Shopping",
            "subcategory":"Florist",
            "type":"Retail Goods"
        }
    ],
    "sg:phone":"+1 604 298 0522",
    "sg:postcode":"V5G 1L2",
    "sg:province":"BC",
    "wof:name":"Canada Florist",
    "wof:placetype":"venue"
},
  "geometry": {"coordinates":[-122.98921199999999,49.25177],"type":"Point"}
}