{
  "type": "Feature",
  "properties": {
    "addr:full":"721 Rte Du Golf Beauceville QC G5X 2T8",
    "addr:housenumber":"721",
    "addr:postcode":"g5x 2t8",
    "addr:street":"Rte Du Golf",
    "iso:country":"CA",
    "sg:address":"721 Rte Du Golf",
    "sg:city":"Beauceville",
    "sg:classifiers":[
        {
            "category":"Recreation",
            "type":"Entertainment"
        }
    ],
    "sg:phone":"+1 418 774 4653",
    "sg:postcode":"G5X 2T8",
    "sg:province":"QC",
    "sg:tags":[
        "course",
        "golf"
    ],
    "wof:name":"Club DE Golf Beauceville Inc",
    "wof:placetype":"venue"
},
  "geometry": {"coordinates":[-70.76404599999999,46.265045],"type":"Point"}
}