{
  "type": "Feature",
  "properties": {
    "addr:full":"324 Rue Saint-Jacques Lachine QC H8R 1E2",
    "addr:housenumber":"324",
    "addr:postcode":"h8r 1e2",
    "addr:street":"Rue Saint-Jacques",
    "iso:country":"CA",
    "sg:address":"324 Rue Saint-Jacques",
    "sg:city":"Lachine",
    "sg:classifiers":[
        {
            "category":"Home & Garden",
            "subcategory":"Household Appliances",
            "type":"Retail Goods"
        }
    ],
    "sg:phone":"+1 514 364 4723",
    "sg:postcode":"H8R 1E2",
    "sg:province":"QC",
    "sg:tags":[
        "cleaners",
        "vacuum"
    ],
    "wof:name":"Compact Aspirateurs",
    "wof:placetype":"venue"
},
  "geometry": {"coordinates":[-73.64743,45.444004],"type":"Point"}
}