{
  "type": "Feature",
  "properties": {
    "addr:full":"10211 101st St Lac LA Biche AB T0A 2C0",
    "addr:housenumber":"10211",
    "addr:postcode":"t0a 2c0",
    "addr:street":"101St St;La Biche",
    "iso:country":"CA",
    "sg:address":"10211 101st St",
    "sg:city":"Lac LA Biche",
    "sg:classifiers":[
        {
            "category":"Manufacturing",
            "subcategory":"Printing",
            "type":"Manufacturing & Wholesale Goods"
        }
    ],
    "sg:phone":"+1 780 623 4221",
    "sg:postcode":"T0A 2C0",
    "sg:province":"AB",
    "sg:tags":[
        "newspaper"
    ],
    "wof:name":"Lac LA Biche Post",
    "wof:placetype":"venue"
},
  "geometry": {"coordinates":[-111.976448,54.771366],"type":"Point"}
}