{
  "type": "Feature",
  "properties": {
    "iso:country":"CA",
    "sg:city":"Maple Ridge",
    "sg:classifiers":[
        {
            "category":"Retail",
            "subcategory":"Auto Repair",
            "type":"Services"
        }
    ],
    "sg:phone":"+1 604 463 8876",
    "sg:postcode":"V2X 2R1",
    "sg:province":"BC",
    "sg:tags":[
        "repairing",
        "automobile"
    ],
    "wof:name":"Westside Automotive",
    "wof:placetype":"venue"
},
  "geometry": {"coordinates":[-122.646927,49.218044],"type":"Point"}
}