{
  "type": "Feature",
  "properties": {
    "addr:full":"8440 109 St NW Edmonton AB T6G 1E2",
    "addr:housenumber":"8440",
    "addr:postcode":"t6g 1e2",
    "addr:street":"109 St Nw",
    "iso:country":"CA",
    "sg:address":"8440 109 St NW",
    "sg:city":"Edmonton",
    "sg:classifiers":[
        {
            "category":"Shopping",
            "type":"Retail Goods"
        }
    ],
    "sg:phone":"+1 780 439 7729",
    "sg:postcode":"T6G 1E2",
    "sg:province":"AB",
    "sg:tags":[
        "book",
        "religious",
        "dealer"
    ],
    "wof:name":"Canadian Bible Society",
    "wof:placetype":"venue"
},
  "geometry": {"coordinates":[-113.51217699999999,53.520443],"type":"Point"}
}