{
  "type": "Feature",
  "properties": {
    "iso:country":"CA",
    "sg:address":"281 Pleasant Ridge Rd",
    "sg:city":"Mount Pleasant",
    "sg:classifiers":[
        {
            "category":"Government",
            "subcategory":"Office",
            "type":"Public Place"
        }
    ],
    "sg:phone":"+1 519 484 2910",
    "sg:postcode":"N0E 1K0",
    "sg:province":"ON",
    "wof:name":"Brantford Public Works Bldg",
    "wof:placetype":"venue"
},
  "geometry": {"coordinates":[-80.3135070801,43.0764198303],"type":"Point"}
}