{
  "type": "Feature",
  "properties": {
    "iso:country":"CA",
    "sg:address":"651 Douglas Fir Rd",
    "sg:city":"Sparwood",
    "sg:classifiers":[
        {
            "category":"Wholesale",
            "subcategory":"Machinery & Supplies",
            "type":"Manufacturing & Wholesale Goods"
        }
    ],
    "sg:phone":"+1 250 425 7018",
    "sg:postcode":"V0B 2G0",
    "sg:province":"BC",
    "sg:tags":[
        "contractor"
    ],
    "wof:name":"Equipment Sales & Svc Ltd",
    "wof:placetype":"venue"
},
  "geometry": {"coordinates":[-114.894119,49.71661],"type":"Point"}
}