{
  "type": "Feature",
  "properties": {
    "iso:country":"CA",
    "sg:address":"903 Simpson St",
    "sg:city":"Thunder Bay",
    "sg:classifiers":[
        {
            "category":"Shopping",
            "subcategory":"Gifts & Souvenirs",
            "type":"Retail Goods"
        }
    ],
    "sg:phone":"+1 807 623 5555",
    "sg:postcode":"P7C 3K5",
    "sg:province":"ON",
    "sg:tags":[
        "party",
        "balloon",
        "artist",
        "supply"
    ],
    "wof:name":"Helium Highs",
    "wof:placetype":"venue"
},
  "geometry": {"coordinates":[-89.238091,48.396313],"type":"Point"}
}