{
  "type": "Feature",
  "properties": {
    "iso:country":"CA",
    "sg:address":"4220 Montee Gagnon #A",
    "sg:city":"Terrebonne",
    "sg:classifiers":[
        {
            "category":"Manufacturing",
            "subcategory":"Tools & Machinery",
            "type":"Manufacturing & Wholesale Goods"
        }
    ],
    "sg:phone":"+1 450 434 6314",
    "sg:postcode":"J6Y 1K9",
    "sg:province":"QC",
    "sg:tags":[
        "machine",
        "shop"
    ],
    "wof:name":"Usiconcept Inc",
    "wof:placetype":"venue"
},
  "geometry": {"coordinates":[-73.8173828125,45.7065086365],"type":"Point"}
}