{
  "type": "Feature",
  "properties": {
    "addr:full":"2637 Islington Ave Etobicoke ON M9V 2X4",
    "addr:housenumber":"2637",
    "addr:postcode":"m9v 2x4",
    "addr:street":"Islington Ave",
    "iso:country":"CA",
    "sg:address":"2637 Islington Ave",
    "sg:city":"Etobicoke",
    "sg:classifiers":[
        {
            "category":"Home & Garden",
            "subcategory":"Carpets & Floor Coverings",
            "type":"Retail Goods"
        }
    ],
    "sg:phone":"+1 416 748 6248",
    "sg:postcode":"M9V 2X4",
    "sg:province":"ON",
    "sg:tags":[
        "dealer",
        "rug"
    ],
    "wof:name":"Bestway Carpet & Rugs Inc",
    "wof:placetype":"venue"
},
  "geometry": {"coordinates":[-79.56546,43.737988],"type":"Point"}
}