{
  "type": "Feature",
  "properties": {
    "addr:full":"Saint-Isidore QC G0S 2S0",
    "addr:postcode":"g0s 2s0",
    "iso:country":"CA",
    "sg:city":"Saint-Isidore",
    "sg:classifiers":[
        {
            "category":"Retail",
            "subcategory":"Auto Repair",
            "type":"Services"
        }
    ],
    "sg:phone":"+1 418 882 5578",
    "sg:postcode":"G0S 2S0",
    "sg:province":"QC",
    "sg:tags":[
        "repairing",
        "automobile"
    ],
    "wof:name":"Garage Alain Fournier",
    "wof:placetype":"venue"
},
  "geometry": {"coordinates":[-71.0904922485,46.5829582214],"type":"Point"}
}