{
  "type": "Feature",
  "properties": {
    "addr:full":"1369 Main St E Hamilton ON L8K 1B8",
    "addr:housenumber":"1369",
    "addr:postcode":"l8k 1b8",
    "addr:street":"Main St E",
    "iso:country":"CA",
    "sg:address":"1369 Main St E",
    "sg:city":"Hamilton",
    "sg:classifiers":[
        {
            "category":"Shopping",
            "subcategory":"Books",
            "type":"Retail Goods"
        }
    ],
    "sg:phone":"+1 905 312 6642",
    "sg:postcode":"L8K 1B8",
    "sg:province":"ON",
    "sg:tags":[
        "comic"
    ],
    "wof:name":"Burdin's Comics",
    "wof:placetype":"venue"
},
  "geometry": {"coordinates":[-79.811165,43.240826],"type":"Point"}
}