{
  "type": "Feature",
  "properties": {
    "addr:full":"1176 Rue Saint-Laurent O Longueuil QC J4K 1E3",
    "addr:housenumber":"1176",
    "addr:postcode":"j4k 1e3",
    "addr:street":"Rue Saint-Laurent O",
    "iso:country":"CA",
    "sg:address":"1176 Rue Saint-Laurent O",
    "sg:city":"Longueuil",
    "sg:classifiers":[
        {
            "category":"Shopping",
            "subcategory":"Computers & Home Electronics",
            "type":"Retail Goods"
        }
    ],
    "sg:phone":"+1 450 442 2020",
    "sg:postcode":"J4K 1E3",
    "sg:province":"QC",
    "sg:tags":[
        "equipment",
        "dealer"
    ],
    "wof:name":"Clinique Du Pc",
    "wof:placetype":"venue"
},
  "geometry": {"coordinates":[-73.5131530762,45.5217781067],"type":"Point"}
}