{
  "type": "Feature",
  "properties": {
    "iso:country":"CA",
    "sg:address":"19670 8 Ave",
    "sg:city":"Langley",
    "sg:classifiers":[
        {
            "category":"Government",
            "subcategory":"Police Station",
            "type":"Public Place"
        }
    ],
    "sg:phone":"+1 604 534 2082",
    "sg:postcode":"V2Z 1W1",
    "sg:province":"BC",
    "sg:tags":[
        "bailiff"
    ],
    "wof:name":"Commonwealth Bailiffs",
    "wof:placetype":"venue"
},
  "geometry": {"coordinates":[-122.67702484100001,49.016494751],"type":"Point"}
}