{
  "type": "Feature",
  "properties": {
    "iso:country":"CA",
    "sg:address":"2370 Rue Bauman # A",
    "sg:city":"Jonquiere",
    "sg:classifiers":[
        {
            "category":"Manufacturing",
            "subcategory":"Tools & Machinery",
            "type":"Manufacturing & Wholesale Goods"
        }
    ],
    "sg:phone":"+1 418 548 1882",
    "sg:postcode":"G7S 4S4",
    "sg:province":"QC",
    "sg:tags":[
        "pulley",
        "covering"
    ],
    "wof:name":"Epsilon Levage & Manutention",
    "wof:placetype":"venue"
},
  "geometry": {"coordinates":[-71.16204833979999,48.4054679871],"type":"Point"}
}