{
  "type": "Feature",
  "properties": {
    "iso:country":"CA",
    "sg:address":"424 1st Ave NE",
    "sg:city":"Dauphin",
    "sg:classifiers":[
        {
            "category":"Organizations",
            "subcategory":"Professional Association",
            "type":"Services"
        }
    ],
    "sg:phone":"+1 204 638 5301",
    "sg:postcode":"R7N 1A9",
    "sg:province":"MB",
    "wof:name":"Arc Industries",
    "wof:placetype":"venue"
},
  "geometry": {"coordinates":[-100.04143500000001,51.14584],"type":"Point"}
}