{
  "type": "Feature",
  "properties": {
    "addr:full":"Perce QC G0C 2L0",
    "addr:postcode":"qc g0c 2l0",
    "addr:street":"Perce",
    "iso:country":"CA",
    "sg:city":"Perce",
    "sg:classifiers":[
        {
            "category":"Restaurant",
            "type":"Food & Drink"
        }
    ],
    "sg:phone":"+1 418 782 5616",
    "sg:postcode":"G0C 2L0",
    "sg:province":"QC",
    "wof:name":"Au Mille Delices Enr",
    "wof:placetype":"venue"
},
  "geometry": {"coordinates":[-64.21484375,48.5211486816],"type":"Point"}
}