{
  "type": "Feature",
  "properties": {
    "addr:full":"1783 Rue Michaud Plessisville QC G6L 1C5",
    "addr:housenumber":"1783",
    "addr:postcode":"g6l 1c5",
    "addr:street":"Rue Michaud",
    "iso:country":"CA",
    "sg:address":"1783 Rue Michaud",
    "sg:city":"Plessisville",
    "sg:classifiers":[
        {
            "category":"Retail",
            "subcategory":"Animal Services",
            "type":"Services"
        }
    ],
    "sg:phone":"+1 819 362 2064",
    "sg:postcode":"G6L 1C5",
    "sg:province":"QC",
    "sg:tags":[
        "pet",
        "grooming",
        "washing"
    ],
    "wof:name":"Salon DE Beaute Canine Enr",
    "wof:placetype":"venue"
},
  "geometry": {"coordinates":[-71.77853399999999,46.225796],"type":"Point"}
}