{
  "type": "Feature",
  "properties": {
    "addr:full":"60 Rte DE Maple Grove Maple Grove QC J6N 1K3",
    "addr:housenumber":"60",
    "addr:postcode":"j6n 1k3",
    "addr:street":"Rte De Maple Grove",
    "iso:country":"CA",
    "sg:address":"60 Rte DE Maple Grove",
    "sg:city":"Maple Grove",
    "sg:classifiers":[
        {
            "category":"Retail",
            "subcategory":"Auto Repair",
            "type":"Services"
        }
    ],
    "sg:phone":"+1 450 225 1174",
    "sg:postcode":"J6N 1K3",
    "sg:province":"QC",
    "sg:tags":[
        "repairing",
        "automobile"
    ],
    "wof:name":"Garage Ip",
    "wof:placetype":"venue"
},
  "geometry": {"coordinates":[-73.83298499999999,45.322392],"type":"Point"}
}