{
  "type": "Feature",
  "properties": {
    "iso:country":"CA",
    "sg:address":"19 Ch Rene",
    "sg:city":"Canton-DE-Granby",
    "sg:classifiers":[
        {
            "category":"Retail",
            "subcategory":"Auto Repair",
            "type":"Services"
        }
    ],
    "sg:phone":"+1 450 375 4757",
    "sg:postcode":"J2G 9H9",
    "sg:province":"QC",
    "sg:tags":[
        "repairing",
        "automobile"
    ],
    "wof:name":"Garage Gingras & Fils Inc",
    "wof:placetype":"venue"
},
  "geometry": {"coordinates":[-72.7217712402,45.3979949951],"type":"Point"}
}