{
  "type": "Feature",
  "properties": {
    "addr:full":"12321 135 St NW Edmonton AB T5L 1X6",
    "addr:housenumber":"12321",
    "addr:postcode":"t5l 1x6",
    "addr:street":"135 St Nw",
    "iso:country":"CA",
    "sg:address":"12321 135 St NW",
    "sg:city":"Edmonton",
    "sg:classifiers":[
        {
            "category":"Organizations",
            "subcategory":"Religious Organization",
            "type":"Services"
        }
    ],
    "sg:phone":"+1 780 455 0246",
    "sg:postcode":"T5L 1X6",
    "sg:province":"AB",
    "sg:tags":[
        "church"
    ],
    "wof:name":"Dovercourt Baptist Church",
    "wof:placetype":"venue"
},
  "geometry": {"coordinates":[-113.557472229,53.5761680603],"type":"Point"}
}