{
  "type": "Feature",
  "properties": {
    "addr:full":"Calgary AB T2A 6R1",
    "addr:postcode":"t2a 6r1",
    "iso:country":"CA",
    "sg:city":"Calgary",
    "sg:classifiers":[
        {
            "category":"Travel",
            "subcategory":"Travel Agent",
            "type":"Entertainment"
        }
    ],
    "sg:phone":"+1 403 272 1000",
    "sg:postcode":"T2A 6R1",
    "sg:province":"AB",
    "sg:tags":[
        "agency",
        "bureau"
    ],
    "wof:name":"Uniglobe Custom Travel",
    "wof:placetype":"venue"
},
  "geometry": {"coordinates":[-113.989998,51.05011],"type":"Point"}
}