{
  "type": "Feature",
  "properties": {
    "addr:full":"181 Carlaw Ave Toronto ON M4M 2S1",
    "addr:housenumber":"181",
    "addr:postcode":"m4m 2s1",
    "addr:street":"Carlaw Ave",
    "iso:country":"CA",
    "sg:address":"181 Carlaw Ave",
    "sg:city":"Toronto",
    "sg:classifiers":[
        {
            "category":"Professional",
            "type":"Services"
        }
    ],
    "sg:phone":"+1 416 406 1631",
    "sg:postcode":"M4M 2S1",
    "sg:province":"ON",
    "sg:tags":[
        "arranger",
        "music",
        "composer"
    ],
    "wof:name":"Mancino Digital",
    "wof:placetype":"venue"
},
  "geometry": {"coordinates":[-79.339973,43.661236],"type":"Point"}
}