{
  "type": "Feature",
  "properties": {
    "addr:full":"524 Mcnicoll Ave North York ON M2H 2E1",
    "addr:housenumber":"524",
    "addr:postcode":"m2h 2e1",
    "addr:street":"Mcnicoll Ave",
    "iso:country":"CA",
    "sg:address":"524 Mcnicoll Ave",
    "sg:city":"North York",
    "sg:classifiers":[
        {
            "category":"Wholesale",
            "subcategory":"Books, Periodicals, & Newspapers",
            "type":"Manufacturing & Wholesale Goods"
        }
    ],
    "sg:phone":"+1 416 497 2292",
    "sg:postcode":"M2H 2E1",
    "sg:province":"ON",
    "sg:tags":[
        "dealer"
    ],
    "wof:name":"Books R Our Business",
    "wof:placetype":"venue"
},
  "geometry": {"coordinates":[-79.339912,43.803936],"type":"Point"}
}