{
  "type": "Feature",
  "properties": {
    "addr:full":"351 Tilley Rd Kelowna BC V4V 2K5",
    "addr:housenumber":"351",
    "addr:postcode":"v4v 2k5",
    "addr:street":"Tilley Rd",
    "iso:country":"CA",
    "sg:address":"351 Tilley Rd",
    "sg:city":"Kelowna",
    "sg:classifiers":[
        {
            "category":"Manufacturing",
            "subcategory":"Metals",
            "type":"Manufacturing & Wholesale Goods"
        }
    ],
    "sg:phone":"+1 250 766 0649",
    "sg:postcode":"V4V 2K5",
    "sg:province":"BC",
    "sg:tags":[
        "steel"
    ],
    "wof:name":"Spartan Metal Processing Ltd",
    "wof:placetype":"venue"
},
  "geometry": {"coordinates":[-119.390282,50.01775],"type":"Point"}
}