{
  "type": "Feature",
  "properties": {
    "iso:country":"CA",
    "sg:address":"1730 Bonhill Rd",
    "sg:city":"Mississauga",
    "sg:classifiers":[
        {
            "category":"Manufacturing",
            "subcategory":"Tools & Machinery",
            "type":"Manufacturing & Wholesale Goods"
        }
    ],
    "sg:phone":"+1 905 670 2890",
    "sg:postcode":"L5T 1C8",
    "sg:province":"ON",
    "sg:tags":[
        "pattern",
        "foundry",
        "maker"
    ],
    "wof:name":"Meteor Foundry CO Ltd",
    "wof:placetype":"venue"
},
  "geometry": {"coordinates":[-79.65087127690001,43.6671791077],"type":"Point"}
}