{
  "type": "Feature",
  "properties": {
    "addr:full":"1215 Athabasca St E Moose Jaw SK S6H 0N4",
    "addr:housenumber":"1215",
    "addr:postcode":"s6h 0n4",
    "addr:street":"Athabasca St E",
    "iso:country":"CA",
    "sg:address":"1215 Athabasca St E",
    "sg:city":"Moose Jaw",
    "sg:classifiers":[
        {
            "category":"Manufacturing",
            "subcategory":"Signs",
            "type":"Manufacturing & Wholesale Goods"
        }
    ],
    "sg:phone":"+1 306 692 9910",
    "sg:postcode":"S6H 0N4",
    "sg:province":"SK",
    "wof:name":"Design Signs",
    "wof:placetype":"venue"
},
  "geometry": {"coordinates":[-105.50159499999999,50.395519],"type":"Point"}
}