{
  "type": "Feature",
  "properties": {
    "addr:full":"9364 Boul Lacordaire Saint-Leonard QC H1R 2B7",
    "addr:housenumber":"9364",
    "addr:postcode":"h1r 2b7",
    "addr:street":"Boul Lacordaire",
    "iso:country":"CA",
    "sg:address":"9364 Boul Lacordaire",
    "sg:city":"Saint-Leonard",
    "sg:classifiers":[
        {
            "category":"Retail",
            "subcategory":"Veterinary Services",
            "type":"Services"
        }
    ],
    "sg:phone":"+1 514 322 9386",
    "sg:postcode":"H1R 2B7",
    "sg:province":"QC",
    "sg:tags":[
        "veterinarian"
    ],
    "wof:name":"Hopital Veterinaire Lacordaire",
    "wof:placetype":"venue"
},
  "geometry": {"coordinates":[-73.611397,45.598076],"type":"Point"}
}