{
  "type": "Feature",
  "properties": {
    "iso:country":"CA",
    "sg:address":"1430 Prince of Wales Dr",
    "sg:city":"Ottawa",
    "sg:classifiers":[
        {
            "category":"Retail",
            "subcategory":"Laundry & Dry Cleaning",
            "type":"Services"
        }
    ],
    "sg:phone":"+1 613 225 5868",
    "sg:postcode":"K2C 1N6",
    "sg:province":"ON",
    "sg:tags":[
        "cleaners"
    ],
    "wof:name":"Browns Cleaners",
    "wof:placetype":"venue"
},
  "geometry": {"coordinates":[-75.701614,45.36895],"type":"Point"}
}