{
  "type": "Feature",
  "properties": {
    "addr:full":"Winnipeg MB R3K 0Y1",
    "addr:postcode":"r3k 0y1",
    "iso:country":"CA",
    "sg:city":"Winnipeg",
    "sg:classifiers":[
        {
            "category":"Retail",
            "subcategory":"Auto Repair",
            "type":"Services"
        }
    ],
    "sg:phone":"+1 204 832 0234",
    "sg:postcode":"R3K 0Y1",
    "sg:province":"MB",
    "sg:tags":[
        "repairing",
        "automobile"
    ],
    "wof:name":"Portage West Auto Svc Ltd",
    "wof:placetype":"venue"
},
  "geometry": {"coordinates":[-97.28121899999999,49.879734],"type":"Point"}
}