{
  "type": "Feature",
  "properties": {
    "addr:full":"200 Route 100 Morden MB R6M 1Y4",
    "addr:housenumber":"200",
    "addr:postcode":"r6m 1y4",
    "addr:street":"Route 100",
    "iso:country":"CA",
    "sg:address":"200 Route 100",
    "sg:city":"Morden",
    "sg:classifiers":[
        {
            "category":"Building & Trades",
            "subcategory":"Construction",
            "type":"Services"
        }
    ],
    "sg:phone":"+1 204 822 6151",
    "sg:postcode":"R6M 1Y4",
    "sg:province":"MB",
    "sg:tags":[
        "equipment",
        "kitchen",
        "maker",
        "cabinet"
    ],
    "wof:name":"Decor Cabinets Ltd",
    "wof:placetype":"venue"
},
  "geometry": {"coordinates":[-98.113022,49.192284],"type":"Point"}
}