{
  "type": "Feature",
  "properties": {
    "addr:full":"Lacombe AB T4L 2A1",
    "addr:postcode":"t4l 2a1",
    "iso:country":"CA",
    "sg:city":"Lacombe",
    "sg:classifiers":[
        {
            "category":"Personal",
            "subcategory":"Beauty Salon",
            "type":"Services"
        }
    ],
    "sg:phone":"+1 403 782 2222",
    "sg:postcode":"T4L 2A1",
    "sg:province":"AB",
    "wof:name":"You N' I Hair Design",
    "wof:placetype":"venue"
},
  "geometry": {"coordinates":[-113.72333500000001,52.46637],"type":"Point"}
}