{
  "type": "Feature",
  "properties": {
    "addr:full":"Boucherville QC J4B 6G6",
    "addr:postcode":"j4b 6g6",
    "iso:country":"CA",
    "sg:city":"Boucherville",
    "sg:classifiers":[
        {
            "category":"Building & Trades",
            "subcategory":"Plumbing",
            "type":"Services"
        }
    ],
    "sg:phone":"+1 450 655 7756",
    "sg:postcode":"J4B 6G6",
    "sg:province":"QC",
    "sg:tags":[
        "ventilating",
        "conditioning",
        "contractor",
        "system",
        "air"
    ],
    "wof:name":"Ventilation Econair Inc",
    "wof:placetype":"venue"
},
  "geometry": {"coordinates":[-73.4418258667,45.5636482239],"type":"Point"}
}