{
  "type": "Feature",
  "properties": {
    "addr:full":"Brantford ON N3T 6A8",
    "addr:postcode":"n3t 6a8",
    "iso:country":"CA",
    "sg:city":"Brantford",
    "sg:classifiers":[
        {
            "category":"Restaurant",
            "type":"Food & Drink"
        }
    ],
    "sg:phone":"+1 519 759 0322",
    "sg:postcode":"N3T 6A8",
    "sg:province":"ON",
    "sg:tags":[
        "tea",
        "rooms"
    ],
    "wof:name":"Little Pantry",
    "wof:placetype":"venue"
},
  "geometry": {"coordinates":[-80.2664489746,43.1402740479],"type":"Point"}
}