{
  "type": "Feature",
  "properties": {
    "addr:full":"Maclellans Brook New Glasgow NS B2H 5G2",
    "addr:postcode":"b2h 5g2",
    "addr:street":"Maclellans Brook",
    "iso:country":"CA",
    "sg:address":"Maclellans Brook",
    "sg:city":"New Glasgow",
    "sg:classifiers":[
        {
            "category":"Building & Trades",
            "subcategory":"Electrical",
            "type":"Services"
        }
    ],
    "sg:phone":"+1 902 752 1729",
    "sg:postcode":"B2H 5G2",
    "sg:province":"NS",
    "sg:tags":[
        "electric",
        "contractor"
    ],
    "wof:name":"Alan S Rumley Electrical",
    "wof:placetype":"venue"
},
  "geometry": {"coordinates":[-62.643414,45.591839],"type":"Point"}
}