{
  "type": "Feature",
  "properties": {
    "addr:full":"226 Center Line Rd Marmora ON K0K 2M0",
    "addr:housenumber":"226",
    "addr:postcode":"k0k 2m0",
    "addr:street":"Center Line Rd",
    "iso:country":"CA",
    "sg:address":"226 Center Line Rd",
    "sg:city":"Marmora",
    "sg:classifiers":[
        {
            "category":"Home & Garden",
            "subcategory":"Furniture",
            "type":"Retail Goods"
        }
    ],
    "sg:phone":"+1 613 472 2851",
    "sg:postcode":"K0K 2M0",
    "sg:province":"ON",
    "sg:tags":[
        "builder",
        "custom"
    ],
    "wof:name":"Classic Touch Furniture Rfnsh",
    "wof:placetype":"venue"
},
  "geometry": {"coordinates":[-77.681557,44.483089],"type":"Point"}
}