{
  "type": "Feature",
  "properties": {
    "iso:country":"CA",
    "sg:address":"Highway 3",
    "sg:city":"Tisdale",
    "sg:classifiers":[
        {
            "category":"Museum",
            "type":"Entertainment"
        }
    ],
    "sg:phone":"+1 306 873 4999",
    "sg:postcode":"S0E 1T0",
    "sg:province":"SK",
    "wof:name":"Tisdale & District Museum",
    "wof:placetype":"venue"
},
  "geometry": {"coordinates":[-104.05291748,52.8418045044],"type":"Point"}
}