{
  "type": "Feature",
  "properties": {
    "addr:full":"Highway 3 Tisdale SK S0E 1T0",
    "addr:postcode":"s0e 1t0",
    "addr:street":"Highway 3 Tisdale",
    "iso:country":"CA",
    "sg:address":"Highway 3",
    "sg:city":"Tisdale",
    "sg:classifiers":[
        {
            "category":"Museum",
            "type":"Entertainment"
        }
    ],
    "sg:phone":"+1 306 873 4999",
    "sg:postcode":"S0E 1T0",
    "sg:province":"SK",
    "wof:name":"Tisdale & District Museum",
    "wof:placetype":"venue"
},
  "geometry": {"coordinates":[-104.05291748,52.8418045044],"type":"Point"}
}