{
  "type": "Feature",
  "properties": {
    "addr:full":"4704 49 St Two Hills AB T0B 4K0",
    "addr:housenumber":"4704",
    "addr:postcode":"t0b 4k0",
    "addr:street":"49 St",
    "iso:country":"CA",
    "sg:address":"4704 49 St",
    "sg:city":"Two Hills",
    "sg:classifiers":[
        {
            "category":"Professional",
            "subcategory":"Accounting & Tax Preparation",
            "type":"Services"
        }
    ],
    "sg:phone":"+1 780 657 2492",
    "sg:postcode":"T0B 4K0",
    "sg:province":"AB",
    "sg:tags":[
        "accountant"
    ],
    "wof:name":"Beale Accounting Ltd",
    "wof:placetype":"venue"
},
  "geometry": {"coordinates":[-111.74227142300001,53.7090911865],"type":"Point"}
}