{
  "type": "Feature",
  "properties": {
    "addr:full":"204 Av Saint-Charles Vaudreuil-Dorion QC J7V 2L3",
    "addr:postcode":"j7v 2l3",
    "addr:street":"204 Av Saint-Charles",
    "iso:country":"CA",
    "sg:address":"204 Av Saint-Charles",
    "sg:city":"Vaudreuil-Dorion",
    "sg:classifiers":[
        {
            "category":"Building & Trades",
            "subcategory":"Construction",
            "type":"Services"
        }
    ],
    "sg:phone":"+1 450 455 3545",
    "sg:postcode":"J7V 2L3",
    "sg:province":"QC",
    "sg:tags":[
        "general",
        "contractor"
    ],
    "wof:name":"Cascades Construction",
    "wof:placetype":"venue"
},
  "geometry": {"coordinates":[-74.014541626,45.3884849548],"type":"Point"}
}