{
  "type": "Feature",
  "properties": {
    "addr:full":"2463 206 St Langley BC V2Z 2B5",
    "addr:housenumber":"2463",
    "addr:postcode":"v2z 2b5",
    "addr:street":"206 St",
    "iso:country":"CA",
    "sg:address":"2463 206 St",
    "sg:city":"Langley",
    "sg:classifiers":[
        {
            "category":"Building & Trades",
            "subcategory":"Construction",
            "type":"Services"
        }
    ],
    "sg:phone":"+1 604 514 9183",
    "sg:postcode":"V2Z 2B5",
    "sg:province":"BC",
    "sg:tags":[
        "paving",
        "contractor"
    ],
    "wof:name":"R & D Crack Sealing Svc Ltd",
    "wof:placetype":"venue"
},
  "geometry": {"coordinates":[-122.653069,49.047318],"type":"Point"}
}