{
  "type": "Feature",
  "properties": {
    "iso:country":"CA",
    "sg:address":"11 Rue Principale",
    "sg:city":"Plaisance",
    "sg:classifiers":[
        {
            "category":"Building & Trades",
            "subcategory":"Construction",
            "type":"Services"
        }
    ],
    "sg:phone":"+1 819 985 3619",
    "sg:postcode":"J0V 1S0",
    "sg:province":"QC",
    "sg:tags":[
        "contractor"
    ],
    "wof:name":"Construction Vic Prud'Homme",
    "wof:placetype":"venue"
},
  "geometry": {"coordinates":[-75.1435089111,45.6026268005],"type":"Point"}
}