{
  "type": "Feature",
  "properties": {
    "addr:full":"500 Rue Sacre-Coeur O Alma QC G8B 1M1",
    "addr:housenumber":"500",
    "addr:postcode":"g8b 1m1",
    "addr:street":"Rue Sacre-Coeur O",
    "iso:country":"CA",
    "sg:address":"500 Rue Sacre-Coeur O",
    "sg:city":"Alma",
    "sg:classifiers":[
        {
            "category":"Shopping",
            "subcategory":"Clothing, Apparel, & Fashions",
            "type":"Retail Goods"
        }
    ],
    "sg:phone":"+1 418 480 2142",
    "sg:postcode":"G8B 1M1",
    "sg:province":"QC",
    "sg:tags":[
        "item",
        "boutique"
    ],
    "wof:name":"Boutique Studio Mode",
    "wof:placetype":"venue"
},
  "geometry": {"coordinates":[-71.6332626343,48.5435333252],"type":"Point"}
}