{
  "type": "Feature",
  "properties": {
    "iso:country":"CA",
    "sg:city":"Scarborough",
    "sg:classifiers":[
        {
            "category":"Wholesale",
            "subcategory":"Meat",
            "type":"Manufacturing & Wholesale Goods"
        }
    ],
    "sg:phone":"+1 416 757 8074",
    "sg:postcode":"M1P 4V5",
    "sg:province":"ON",
    "sg:tags":[
        "product"
    ],
    "wof:name":"King Kabob",
    "wof:placetype":"venue"
},
  "geometry": {"coordinates":[-79.27630615229999,43.761680603],"type":"Point"}
}