{
  "type": "Feature",
  "properties": {
    "addr:full":"1307 Rue Maurice Lasalle QC H8N 1P7",
    "addr:housenumber":"1307",
    "addr:postcode":"h8n 1p7",
    "addr:street":"Rue Maurice",
    "iso:country":"CA",
    "sg:address":"1307 Rue Maurice",
    "sg:city":"Lasalle",
    "sg:classifiers":[
        {
            "category":"Building & Trades",
            "subcategory":"Landscaping Services",
            "type":"Services"
        }
    ],
    "sg:phone":"+1 514 363 9434",
    "sg:postcode":"H8N 1P7",
    "sg:province":"QC",
    "sg:tags":[
        "landscape",
        "contractor"
    ],
    "wof:name":"P S Landscaping",
    "wof:placetype":"venue"
},
  "geometry": {"coordinates":[-73.6204833984,45.4305114746],"type":"Point"}
}