{
  "type": "Feature",
  "properties": {
    "addr:full":"377 Churchill Ave N Ottawa ON K1Z 5C4",
    "addr:housenumber":"377",
    "addr:postcode":"k1z 5c4",
    "addr:street":"Churchill Ave N",
    "iso:country":"CA",
    "sg:address":"377 Churchill Ave N",
    "sg:city":"Ottawa",
    "sg:classifiers":[
        {
            "category":"Shopping",
            "subcategory":"Jewelry",
            "type":"Retail Goods"
        }
    ],
    "sg:phone":"+1 613 728 8494",
    "sg:postcode":"K1Z 5C4",
    "sg:province":"ON",
    "wof:name":"Gold Cast",
    "wof:placetype":"venue"
},
  "geometry": {"coordinates":[-75.75412799999999,45.392735],"type":"Point"}
}