{
  "type": "Feature",
  "properties": {
    "iso:country":"CA",
    "sg:address":"377 Churchill Ave N",
    "sg:city":"Ottawa",
    "sg:classifiers":[
        {
            "category":"Shopping",
            "subcategory":"Jewelry",
            "type":"Retail Goods"
        }
    ],
    "sg:phone":"+1 613 728 8494",
    "sg:postcode":"K1Z 5C4",
    "sg:province":"ON",
    "wof:name":"Gold Cast",
    "wof:placetype":"venue"
},
  "geometry": {"coordinates":[-75.754128,45.392735],"type":"Point"}
}