{
  "type": "Feature",
  "properties": {
    "addr:full":"96 Clyde Ave Mount Pearl NL A1N 4S2",
    "addr:housenumber":"96",
    "addr:postcode":"a1n 4s2",
    "addr:street":"Clyde Ave",
    "iso:country":"CA",
    "sg:address":"96 Clyde Ave",
    "sg:city":"Mount Pearl",
    "sg:classifiers":[
        {
            "category":"Professional",
            "subcategory":"Engineering",
            "type":"Services"
        }
    ],
    "sg:phone":"+1 709 682 5026",
    "sg:postcode":"A1N 4S2",
    "sg:province":"NL",
    "sg:tags":[
        "engineer"
    ],
    "wof:name":"Weir-Jones Ngi",
    "wof:placetype":"venue"
},
  "geometry": {"coordinates":[-52.833553,47.523041],"type":"Point"}
}