{
  "type": "Feature",
  "properties": {
    "addr:full":"194 Grosvenor Ave N Hamilton ON L8L 7S9",
    "addr:housenumber":"194",
    "addr:postcode":"l8l 7s9",
    "addr:street":"Grosvenor Ave N",
    "iso:country":"CA",
    "sg:address":"194 Grosvenor Ave N",
    "sg:city":"Hamilton",
    "sg:classifiers":[
        {
            "category":"Building & Trades",
            "subcategory":"Landscaping Services",
            "type":"Services"
        }
    ],
    "sg:phone":"+1 905 547 9735",
    "sg:postcode":"L8L 7S9",
    "sg:province":"ON",
    "sg:tags":[
        "tree"
    ],
    "wof:name":"D R Tree Svc",
    "wof:placetype":"venue"
},
  "geometry": {"coordinates":[-79.81849699999999,43.248154],"type":"Point"}
}