{
  "type": "Feature",
  "properties": {
    "addr:full":"85 Sunnyside Rd Wolfville NS B4P 2R2",
    "addr:housenumber":"85",
    "addr:postcode":"b4p 2r2",
    "addr:street":"Sunnyside Rd",
    "iso:country":"CA",
    "sg:address":"85 Sunnyside Rd",
    "sg:city":"Wolfville",
    "sg:classifiers":[
        {
            "category":"Real Estate",
            "subcategory":"Real Estate Agent",
            "type":"Services"
        }
    ],
    "sg:phone":"+1 902 542 7001",
    "sg:postcode":"B4P 2R2",
    "sg:province":"NS",
    "sg:tags":[
        "appraiser"
    ],
    "wof:name":"Davidson Appraisals",
    "wof:placetype":"venue"
},
  "geometry": {"coordinates":[-64.36320499999999,45.091354],"type":"Point"}
}