{
  "type": "Feature",
  "properties": {
    "iso:country":"CA",
    "sg:address":"48 Dundas St E",
    "sg:city":"Napanee",
    "sg:classifiers":[
        {
            "category":"Shopping",
            "subcategory":"Jewelry",
            "type":"Retail Goods"
        }
    ],
    "sg:phone":"+1 613 354 3295",
    "sg:postcode":"K7R 1H8",
    "sg:province":"ON",
    "sg:tags":[
        "jeweler"
    ],
    "wof:name":"Watch Chalet",
    "wof:placetype":"venue"
},
  "geometry": {"coordinates":[-76.948677,44.248138],"type":"Point"}
}