{
  "type": "Feature",
  "properties": {
    "addr:full":"8250 Rue Marconi Anjou QC H1J 1B2",
    "addr:housenumber":"8250",
    "addr:postcode":"h1j 1b2",
    "addr:street":"Rue Marconi",
    "iso:country":"CA",
    "sg:address":"8250 Rue Marconi",
    "sg:city":"Anjou",
    "sg:classifiers":[
        {
            "category":"Manufacturing",
            "subcategory":"Metals",
            "type":"Manufacturing & Wholesale Goods"
        }
    ],
    "sg:phone":"+1 514 351 3000",
    "sg:postcode":"H1J 1B2",
    "sg:province":"QC",
    "sg:tags":[
        "cap",
        "can",
        "bottle",
        "seal"
    ],
    "wof:name":"Dominion & Grimm Inc",
    "wof:placetype":"venue"
},
  "geometry": {"coordinates":[-73.5727310181,45.6158714294],"type":"Point"}
}