{
  "type": "Feature",
  "properties": {
    "addr:full":"270 Rue Saint-Jean Longueuil QC J4H 2X5",
    "addr:housenumber":"270",
    "addr:postcode":"j4h 2x5",
    "addr:street":"Rue Saint-Jean",
    "iso:country":"CA",
    "sg:address":"270 Rue Saint-Jean",
    "sg:city":"Longueuil",
    "sg:classifiers":[
        {
            "category":"Personal",
            "type":"Services"
        }
    ],
    "sg:phone":"+1 450 674 5516",
    "sg:postcode":"J4H 2X5",
    "sg:province":"QC",
    "sg:tags":[
        "electrolysis"
    ],
    "wof:name":"Cosmeta Enr",
    "wof:placetype":"venue"
},
  "geometry": {"coordinates":[-73.50927,45.536011],"type":"Point"}
}