{
  "type": "Feature",
  "properties": {
    "iso:country":"CA",
    "sg:city":"Saint-Felicien",
    "sg:classifiers":[
        {
            "category":"Wholesale",
            "subcategory":"Fruits & Vegetables",
            "type":"Manufacturing & Wholesale Goods"
        }
    ],
    "sg:phone":"+1 418 679 1472",
    "sg:postcode":"G8K 1B3",
    "sg:province":"QC",
    "sg:tags":[
        "shipper"
    ],
    "wof:name":"Bleuetieres Senco Inc",
    "wof:placetype":"venue"
},
  "geometry": {"coordinates":[-72.45328521730001,48.6613960266],"type":"Point"}
}