{
  "type": "Feature",
  "properties": {
    "addr:full":"124 Crockford Blvd Scarborough ON M1R 3C3",
    "addr:housenumber":"124",
    "addr:postcode":"m1r 3c3",
    "addr:street":"Crockford Blvd",
    "iso:country":"CA",
    "sg:address":"124 Crockford Blvd",
    "sg:city":"Scarborough",
    "sg:classifiers":[
        {
            "category":"Professional",
            "subcategory":"Business Services",
            "type":"Services"
        }
    ],
    "sg:phone":"+1 416 751 3675",
    "sg:postcode":"M1R 3C3",
    "sg:province":"ON",
    "sg:tags":[
        "recording",
        "studio"
    ],
    "wof:name":"Voodoo Records",
    "wof:placetype":"venue"
},
  "geometry": {"coordinates":[-79.28955841059999,43.7421836853],"type":"Point"}
}