{
  "type": "Feature",
  "properties": {
    "iso:country":"CA",
    "sg:address":"380 Boul Labelle",
    "sg:city":"Rosemere",
    "sg:classifiers":[
        {
            "category":"Restaurant",
            "type":"Food & Drink"
        }
    ],
    "sg:phone":"+1 450 437 9484",
    "sg:postcode":"J7A 3R8",
    "sg:province":"QC",
    "wof:name":"Restaurant LA Stanza",
    "wof:placetype":"venue"
},
  "geometry": {"coordinates":[-73.814743,45.632217],"type":"Point"}
}