{
  "type": "Feature",
  "properties": {
    "addr:full":"791 Lawrence Ave W North York ON M6A 1C2",
    "addr:housenumber":"791",
    "addr:postcode":"m6a 1c2",
    "addr:street":"Lawrence Ave W",
    "iso:country":"CA",
    "sg:address":"791 Lawrence Ave W",
    "sg:city":"North York",
    "sg:classifiers":[
        {
            "category":"Retail",
            "subcategory":"Laundry & Dry Cleaning",
            "type":"Services"
        }
    ],
    "sg:phone":"+1 416 256 0471",
    "sg:postcode":"M6A 1C2",
    "sg:province":"ON",
    "sg:tags":[
        "cleaners"
    ],
    "wof:name":"Summit Cleaners",
    "wof:placetype":"venue"
},
  "geometry": {"coordinates":[-79.45389556879999,43.7140312195],"type":"Point"}
}