{
  "type": "Feature",
  "properties": {
    "addr:full":"Kelowna BC V1Y 8E7",
    "addr:postcode":"v1y 8e7",
    "iso:country":"CA",
    "sg:city":"Kelowna",
    "sg:classifiers":[
        {
            "category":"Health Services",
            "subcategory":"Medical Lab",
            "type":"Services"
        }
    ],
    "sg:phone":"+1 250 762 3393",
    "sg:postcode":"V1Y 8E7",
    "sg:province":"BC",
    "wof:name":"Mission Park Denture Clinic",
    "wof:placetype":"venue"
},
  "geometry": {"coordinates":[-119.49659699999999,49.886814],"type":"Point"}
}