{
  "type": "Feature",
  "properties": {
    "iso:country":"CA",
    "sg:address":"247 Cook St",
    "sg:city":"Victoria",
    "sg:classifiers":[
        {
            "category":"Shopping",
            "subcategory":"Used Merchandise",
            "type":"Retail Goods"
        }
    ],
    "sg:phone":"+1 250 386 9095",
    "sg:postcode":"V8V 3X4",
    "sg:province":"BC",
    "sg:tags":[
        "book",
        "rare",
        "dealer"
    ],
    "wof:name":"Fairfield Bookshop",
    "wof:placetype":"venue"
},
  "geometry": {"coordinates":[-123.356887817,48.4133872986],"type":"Point"}
}