{
  "type": "Feature",
  "properties": {
    "addr:full":"350 Hilda Ave Thornhill ON L4J 5K2",
    "addr:housenumber":"350",
    "addr:postcode":"l4j 5k2",
    "addr:street":"Hilda Ave",
    "iso:country":"CA",
    "sg:address":"350 Hilda Ave",
    "sg:city":"Thornhill",
    "sg:classifiers":[
        {
            "category":"Education",
            "subcategory":"School",
            "type":"Public Place"
        }
    ],
    "sg:phone":"+1 905 764 5292",
    "sg:postcode":"L4J 5K2",
    "sg:province":"ON",
    "wof:name":"Yorkhill Public School",
    "wof:placetype":"venue"
},
  "geometry": {"coordinates":[-79.4361495972,43.8039741516],"type":"Point"}
}