{
  "type": "Feature",
  "properties": {
    "iso:country":"CA",
    "sg:address":"20065 Langley Bypass",
    "sg:city":"Langley",
    "sg:classifiers":[
        {
            "category":"Restaurant",
            "type":"Food & Drink"
        }
    ],
    "sg:phone":"+1 604 530 6007",
    "sg:postcode":"V3A 8R6",
    "sg:province":"BC",
    "wof:name":"Swiss Chalet Rotisserie",
    "wof:placetype":"venue"
},
  "geometry": {"coordinates":[-122.666809082,49.1135139465],"type":"Point"}
}