{
  "type": "Feature",
  "properties": {
    "addr:full":"Saint-Remi QC J0L 2L0",
    "addr:postcode":"j0l 2l0",
    "iso:country":"CA",
    "sg:city":"Saint-Remi",
    "sg:classifiers":[
        {
            "category":"Restaurant",
            "type":"Food & Drink"
        }
    ],
    "sg:phone":"+1 450 454 3414",
    "sg:postcode":"J0L 2L0",
    "sg:province":"QC",
    "wof:name":"Pizzeria 231",
    "wof:placetype":"venue"
},
  "geometry": {"coordinates":[-73.6132736206,45.2599639893],"type":"Point"}
}