{
  "type": "Feature",
  "properties": {
    "addr:full":"333 Vaughan St Winnipeg MB R3B 3J9",
    "addr:housenumber":"333",
    "addr:postcode":"r3b 3j9",
    "addr:street":"Vaughan St",
    "iso:country":"CA",
    "sg:address":"333 Vaughan St",
    "sg:city":"Winnipeg",
    "sg:classifiers":[
        {
            "category":"Personal",
            "subcategory":"Beauty Salon",
            "type":"Services"
        }
    ],
    "sg:phone":"+1 204 957 7763",
    "sg:postcode":"R3B 3J9",
    "sg:province":"MB",
    "wof:name":"Klip & Kurl",
    "wof:placetype":"venue"
},
  "geometry": {"coordinates":[-97.150429,49.893173],"type":"Point"}
}