{
  "type": "Feature",
  "properties": {
    "iso:country":"CA",
    "sg:address":"911 Main St N",
    "sg:city":"Moose Jaw",
    "sg:classifiers":[
        {
            "category":"Personal",
            "subcategory":"Beauty Salon",
            "type":"Services"
        }
    ],
    "sg:phone":"+1 306 693 2992",
    "sg:postcode":"S6H 0W9",
    "sg:province":"SK",
    "wof:name":"Total Exposure Tanning & Nail",
    "wof:placetype":"venue"
},
  "geometry": {"coordinates":[-105.534454346,50.3980445862],"type":"Point"}
}