{
  "type": "Feature",
  "properties": {
    "addr:full":"1179 Finch Ave W # 204 North York ON M3J 2G1",
    "addr:housenumber":"1179",
    "addr:postcode":"m3j 2g1",
    "addr:street":"Finch Ave W # 204",
    "iso:country":"CA",
    "sg:address":"1179 Finch Ave W # 204",
    "sg:city":"North York",
    "sg:classifiers":[
        {
            "category":"Home & Garden",
            "subcategory":"Building Materials",
            "type":"Retail Goods"
        }
    ],
    "sg:phone":"+1 416 665 9297",
    "sg:postcode":"M3J 2G1",
    "sg:province":"ON",
    "sg:tags":[
        "windows"
    ],
    "wof:name":"First Choice Windows & Doors",
    "wof:placetype":"venue"
},
  "geometry": {"coordinates":[-79.481567,43.76543],"type":"Point"}
}