{
  "type": "Feature",
  "properties": {
    "iso:country":"CA",
    "sg:city":"Winnipeg",
    "sg:classifiers":[
        {
            "category":"Shopping",
            "type":"Retail Goods"
        }
    ],
    "sg:phone":"+1 204 775 3895",
    "sg:postcode":"R3G 3J7",
    "sg:province":"MB",
    "sg:tags":[
        "picture",
        "frame"
    ],
    "wof:name":"Insta Frame Galleries",
    "wof:placetype":"venue"
},
  "geometry": {"coordinates":[-97.201133728,49.8900566101],"type":"Point"}
}