{
  "type": "Feature",
  "properties": {
    "addr:full":"39 Pleasant Blvd Toronto ON M4T 1K2",
    "addr:housenumber":"39",
    "addr:postcode":"m4t 1k2",
    "addr:street":"Pleasant Blvd",
    "iso:country":"CA",
    "sg:address":"39 Pleasant Blvd",
    "sg:city":"Toronto",
    "sg:classifiers":[
        {
            "category":"Health Services",
            "subcategory":"Doctor",
            "type":"Services"
        }
    ],
    "sg:phone":"+1 416 967 4446",
    "sg:postcode":"M4T 1K2",
    "sg:province":"ON",
    "sg:tags":[
        "physician",
        "surgeon"
    ],
    "wof:name":"Weinstock, M MD",
    "wof:placetype":"venue"
},
  "geometry": {"coordinates":[-79.3916549683,43.6874427795],"type":"Point"}
}