{
  "type": "Feature",
  "properties": {
    "iso:country":"CA",
    "sg:address":"118 Victoria St N",
    "sg:city":"Sarnia",
    "sg:classifiers":[
        {
            "category":"Arts & Performance",
            "subcategory":"Theater",
            "type":"Entertainment"
        }
    ],
    "sg:phone":"+1 519 337 7775",
    "sg:postcode":"N7T 5W9",
    "sg:province":"ON",
    "sg:tags":[
        "band",
        "orchestra"
    ],
    "wof:name":"International Symphony Orchstr",
    "wof:placetype":"venue"
},
  "geometry": {"coordinates":[-82.405762,42.970905],"type":"Point"}
}