{
  "type": "Feature",
  "properties": {
    "addr:full":"Hwy 430 Plum Point NL A0K 4A0",
    "addr:postcode":"a0k 4a0",
    "addr:street":"Hwy 430",
    "iso:country":"CA",
    "sg:address":"Hwy 430",
    "sg:city":"Plum Point",
    "sg:classifiers":[
        {
            "category":"Autos & Motor Vehicles",
            "subcategory":"Fuel & Gas Station",
            "type":"Retail Goods"
        }
    ],
    "sg:phone":"+1 709 247 2316",
    "sg:postcode":"A0K 4A0",
    "sg:province":"NL",
    "sg:tags":[
        "grocer",
        "oil"
    ],
    "wof:name":"Plum Point Irving",
    "wof:placetype":"venue"
},
  "geometry": {"coordinates":[-56.877193,51.07777],"type":"Point"}
}