{
  "type": "Feature",
  "properties": {
    "addr:full":"145 Rue Saint-Jean Quebec QC G1R 1N4",
    "addr:housenumber":"145",
    "addr:postcode":"g1r 1n4",
    "addr:street":"Rue Saint-Jean",
    "iso:country":"CA",
    "sg:address":"145 Rue Saint-Jean",
    "sg:city":"Quebec",
    "sg:classifiers":[
        {
            "category":"Restaurant",
            "type":"Food & Drink"
        }
    ],
    "sg:phone":"+1 418 529 7702",
    "sg:postcode":"G1R 1N4",
    "sg:province":"QC",
    "wof:name":"Chez Victor Enr",
    "wof:placetype":"venue"
},
  "geometry": {"coordinates":[-71.225792,46.807659],"type":"Point"}
}