{
  "type": "Feature",
  "properties": {
    "addr:full":"5390 Rue Orchard Saint-Hubert QC J3Y 2H1",
    "addr:housenumber":"5390",
    "addr:postcode":"j3y 2h1",
    "addr:street":"Rue Orchard",
    "iso:country":"CA",
    "sg:address":"5390 Rue Orchard",
    "sg:city":"Saint-Hubert",
    "sg:classifiers":[
        {
            "category":"Home & Garden",
            "subcategory":"Building Materials",
            "type":"Retail Goods"
        }
    ],
    "sg:phone":"+1 450 676 9772",
    "sg:postcode":"J3Y 2H1",
    "sg:province":"QC",
    "sg:tags":[
        "firewood"
    ],
    "wof:name":"Cartier, Serge",
    "wof:placetype":"venue"
},
  "geometry": {"coordinates":[-73.4419250488,45.4763221741],"type":"Point"}
}