{
  "type": "Feature",
  "properties": {
    "addr:full":"55 High St W Moose Jaw SK S6H 1S4",
    "addr:housenumber":"55",
    "addr:postcode":"s6h 1s4",
    "addr:street":"High St W",
    "iso:country":"CA",
    "sg:address":"55 High St W",
    "sg:city":"Moose Jaw",
    "sg:classifiers":[
        {
            "category":"Real Estate",
            "subcategory":"Real Estate Agent",
            "type":"Services"
        }
    ],
    "sg:phone":"+1 306 693 3012",
    "sg:postcode":"S6H 1S4",
    "sg:province":"SK",
    "wof:name":"Key West Real Estate Ltd",
    "wof:placetype":"venue"
},
  "geometry": {"coordinates":[-105.536109924,50.3914299011],"type":"Point"}
}