{
  "type": "Feature",
  "properties": {
    "addr:full":"633195 Hwy 10 Orangeville ON L9W 2Z1",
    "addr:housenumber":"633195",
    "addr:postcode":"l9w 2z1",
    "addr:street":"Hwy 10",
    "iso:country":"CA",
    "sg:address":"633195 Hwy 10",
    "sg:city":"Orangeville",
    "sg:classifiers":[
        {
            "category":"Travel",
            "subcategory":"Hotels & Motels",
            "type":"Entertainment"
        }
    ],
    "sg:phone":"+1 519 941 6831",
    "sg:postcode":"L9W 2Z1",
    "sg:province":"ON",
    "wof:name":"Orangeville Motel Inc",
    "wof:placetype":"venue"
},
  "geometry": {"coordinates":[-80.0727844238,43.9168701172],"type":"Point"}
}