{
  "type": "Feature",
  "properties": {
    "iso:country":"CA",
    "sg:address":"45 Rue Cormier",
    "sg:city":"Cap-Pele",
    "sg:classifiers":[
        {
            "category":"Manufacturing",
            "subcategory":"Food",
            "type":"Manufacturing & Wholesale Goods"
        }
    ],
    "sg:phone":"+1 506 577 6733",
    "sg:postcode":"E4N 1N8",
    "sg:province":"NB",
    "sg:tags":[
        "packer",
        "fish"
    ],
    "wof:name":"Sea Tide Ground Fish Plant",
    "wof:placetype":"venue"
},
  "geometry": {"coordinates":[-64.2779006958,46.2328224182],"type":"Point"}
}