{
  "type": "Feature",
  "properties": {
    "addr:full":"Portage LA Prairie MB R1N 3A2",
    "addr:postcode":"r1n 3a2",
    "iso:country":"CA",
    "sg:city":"Portage LA Prairie",
    "sg:classifiers":[
        {
            "category":"Manufacturing",
            "subcategory":"Tools & Machinery",
            "type":"Manufacturing & Wholesale Goods"
        }
    ],
    "sg:phone":"+1 204 239 5237",
    "sg:postcode":"R1N 3A2",
    "sg:province":"MB",
    "sg:tags":[
        "machine",
        "shop"
    ],
    "wof:name":"Parker's Machine Shop",
    "wof:placetype":"venue"
},
  "geometry": {"coordinates":[-98.290565,49.973083],"type":"Point"}
}