{
  "type": "Feature",
  "properties": {
    "addr:full":"1073 Roosevelt Cres North Vancouver BC V7P 1M4",
    "addr:housenumber":"1073",
    "addr:postcode":"v7p 1m4",
    "addr:street":"Roosevelt Cres",
    "iso:country":"CA",
    "sg:address":"1073 Roosevelt Cres",
    "sg:city":"North Vancouver",
    "sg:classifiers":[
        {
            "category":"Retail",
            "subcategory":"Portrait Studio",
            "type":"Services"
        }
    ],
    "sg:phone":"+1 604 980 8551",
    "sg:postcode":"V7P 1M4",
    "sg:province":"BC",
    "sg:tags":[
        "photographer"
    ],
    "wof:name":"Mountain West Studios Ltd",
    "wof:placetype":"venue"
},
  "geometry": {"coordinates":[-123.103706,49.321899],"type":"Point"}
}