{
  "type": "Feature",
  "properties": {
    "addr:full":"Cornwall PE C0A 1H0",
    "addr:postcode":"c0a 1h0",
    "iso:country":"CA",
    "sg:city":"Cornwall",
    "sg:classifiers":[
        {
            "category":"Restaurant",
            "type":"Food & Drink"
        }
    ],
    "sg:phone":"+1 902 892 4257",
    "sg:postcode":"C0A 1H0",
    "sg:province":"PE",
    "sg:tags":[
        "home",
        "health",
        "caterer"
    ],
    "wof:name":"Real Meals",
    "wof:placetype":"venue"
},
  "geometry": {"coordinates":[-63.218075,46.22768],"type":"Point"}
}