{
  "type": "Feature",
  "properties": {
    "addr:full":"Golden BC V0A 1H0",
    "addr:postcode":"v0a 1h0",
    "iso:country":"CA",
    "sg:city":"Golden",
    "sg:classifiers":[
        {
            "category":"Real Estate",
            "subcategory":"Real Estate Agent",
            "type":"Services"
        }
    ],
    "sg:phone":"+1 250 344 7663",
    "sg:postcode":"V0A 1H0",
    "sg:province":"BC",
    "wof:name":"Re/Max of Golden",
    "wof:placetype":"venue"
},
  "geometry": {"coordinates":[-116.97699,51.308811],"type":"Point"}
}