{
  "type": "Feature",
  "properties": {
    "addr:full":"4900 51 Ave Stony Plain AB T7Z 1C4",
    "addr:housenumber":"4900",
    "addr:postcode":"t7z 1c4",
    "addr:street":"51 Ave",
    "iso:country":"CA",
    "sg:address":"4900 51 Ave",
    "sg:city":"Stony Plain",
    "sg:classifiers":[
        {
            "category":"Home & Garden",
            "subcategory":"Home Furnishings",
            "type":"Retail Goods"
        }
    ],
    "sg:phone":"+1 780 963 5563",
    "sg:postcode":"T7Z 1C4",
    "sg:province":"AB",
    "sg:tags":[
        "curtain",
        "made",
        "drapery"
    ],
    "wof:name":"Ashly-Lane Interiors Ltd",
    "wof:placetype":"venue"
},
  "geometry": {"coordinates":[-114.004295,53.528728],"type":"Point"}
}