{
  "type": "Feature",
  "properties": {
    "addr:full":"4895 Main St Vancouver BC V5V 3R9",
    "addr:housenumber":"4895",
    "addr:postcode":"v5v 3r9",
    "addr:street":"Main St",
    "iso:country":"CA",
    "sg:address":"4895 Main St",
    "sg:city":"Vancouver",
    "sg:classifiers":[
        {
            "category":"Shopping",
            "subcategory":"Bicycles & Sporting Goods",
            "type":"Retail Goods"
        }
    ],
    "sg:phone":"+1 604 874 6910",
    "sg:postcode":"V5V 3R9",
    "sg:province":"BC",
    "wof:name":"Abbie's Sporting Goods",
    "wof:placetype":"venue"
},
  "geometry": {"coordinates":[-123.101593018,49.2407112122],"type":"Point"}
}