{
  "type": "Feature",
  "properties": {
    "iso:country":"CA",
    "sg:address":"1467 8th Line",
    "sg:city":"Lakefield",
    "sg:classifiers":[
        {
            "category":"Building & Trades",
            "subcategory":"Construction",
            "type":"Services"
        }
    ],
    "sg:phone":"+1 705 652 7183",
    "sg:postcode":"K0L 2H0",
    "sg:province":"ON",
    "sg:tags":[
        "excavating",
        "contractor"
    ],
    "wof:name":"Ivan Dunford Excavating",
    "wof:placetype":"venue"
},
  "geometry": {"coordinates":[-78.2727813721,44.4225082397],"type":"Point"}
}