{
  "type": "Feature",
  "properties": {
    "addr:full":"Cranbrook BC V1C 5M6",
    "addr:postcode":"v1c 5m6",
    "iso:country":"CA",
    "sg:city":"Cranbrook",
    "sg:classifiers":[
        {
            "category":"Wholesale",
            "subcategory":"Auto Parts",
            "type":"Manufacturing & Wholesale Goods"
        }
    ],
    "sg:phone":"+1 250 417 0888",
    "sg:postcode":"V1C 5M6",
    "sg:province":"BC",
    "sg:tags":[
        "automobile",
        "supply"
    ],
    "wof:name":"Lordco Parts Ltd",
    "wof:placetype":"venue"
},
  "geometry": {"coordinates":[-115.744171143,49.5324668884],"type":"Point"}
}