{
  "type": "Feature",
  "properties": {
    "iso:country":"CA",
    "sg:address":"4645 Macleod Trail SW",
    "sg:city":"Calgary",
    "sg:classifiers":[
        {
            "category":"Shopping",
            "subcategory":"Jewelry",
            "type":"Retail Goods"
        }
    ],
    "sg:phone":"+1 403 243 7476",
    "sg:postcode":"T2G 0A6",
    "sg:province":"AB",
    "sg:tags":[
        "jeweler"
    ],
    "wof:name":"Golden Touch Jewellers Ltd",
    "wof:placetype":"venue"
},
  "geometry": {"coordinates":[-114.066475,51.012192],"type":"Point"}
}