{
  "type": "Feature",
  "properties": {
    "addr:full":"77 Bloor St W #2000 Toronto ON M5S 1M2",
    "addr:housenumber":"77",
    "addr:postcode":"m5s 1m2",
    "addr:street":"Bloor St W # 2000",
    "iso:country":"CA",
    "sg:address":"77 Bloor St W #2000",
    "sg:city":"Toronto",
    "sg:classifiers":[
        {
            "category":"Real Estate",
            "subcategory":"Real Estate Agent",
            "type":"Services"
        }
    ],
    "sg:phone":"+1 416 923 2950",
    "sg:postcode":"M5S 1M2",
    "sg:province":"ON",
    "sg:tags":[
        "motel",
        "management",
        "hotel"
    ],
    "wof:name":"Realstar Management",
    "wof:placetype":"venue"
},
  "geometry": {"coordinates":[-79.389847,43.669441],"type":"Point"}
}