{
  "type": "Feature",
  "properties": {
    "addr:full":"Calgary AB T2P 2V1",
    "addr:postcode":"t2p 2v1",
    "iso:country":"CA",
    "sg:city":"Calgary",
    "sg:classifiers":[
        {
            "category":"Wholesale",
            "subcategory":"Metals & Minerals",
            "type":"Manufacturing & Wholesale Goods"
        }
    ],
    "sg:phone":"+1 403 262 3777",
    "sg:postcode":"T2P 2V1",
    "sg:province":"AB",
    "sg:tags":[
        "pipe"
    ],
    "wof:name":"Triumph Tubular & Supply Ltd",
    "wof:placetype":"venue"
},
  "geometry": {"coordinates":[-114.070717,51.048443],"type":"Point"}
}