{
  "type": "Feature",
  "properties": {
    "iso:country":"CA",
    "sg:address":"10 Douglas Dr",
    "sg:city":"Trenton",
    "sg:classifiers":[
        {
            "category":"Manufacturing",
            "subcategory":"Tools & Machinery",
            "type":"Manufacturing & Wholesale Goods"
        }
    ],
    "sg:phone":"+1 613 394 9993",
    "sg:postcode":"K8V 5W6",
    "sg:province":"ON",
    "sg:tags":[
        "steel",
        "machine",
        "shop"
    ],
    "wof:name":"Trent Fab Inc",
    "wof:placetype":"venue"
},
  "geometry": {"coordinates":[-77.5869216919,44.1280250549],"type":"Point"}
}