{
  "type": "Feature",
  "properties": {
    "addr:full":"514 Boul Marcotte Roberval QC G8H 1Z6",
    "addr:housenumber":"514",
    "addr:postcode":"g8h 1z6",
    "addr:street":"Boul Marcotte",
    "iso:country":"CA",
    "sg:address":"514 Boul Marcotte",
    "sg:city":"Roberval",
    "sg:classifiers":[
        {
            "category":"Autos & Motor Vehicles",
            "subcategory":"Auto Supplies",
            "type":"Retail Goods"
        }
    ],
    "sg:phone":"+1 418 275 1992",
    "sg:postcode":"G8H 1Z6",
    "sg:province":"QC",
    "sg:tags":[
        "automobile",
        "parts"
    ],
    "wof:name":"Accessoires D'Autos Roberval",
    "wof:placetype":"venue"
},
  "geometry": {"coordinates":[-72.224419,48.508854],"type":"Point"}
}