{
  "type": "Feature",
  "properties": {
    "addr:full":"2030 Douglas St Victoria BC V8T 4L1",
    "addr:housenumber":"2030",
    "addr:postcode":"v8t 4l1",
    "addr:street":"Douglas St",
    "iso:country":"CA",
    "sg:address":"2030 Douglas St",
    "sg:city":"Victoria",
    "sg:classifiers":[
        {
            "category":"Shopping",
            "subcategory":"Computers & Home Electronics",
            "type":"Retail Goods"
        }
    ],
    "sg:phone":"+1 250 386 6665",
    "sg:postcode":"V8T 4L1",
    "sg:province":"BC",
    "sg:tags":[
        "equipment",
        "dealer"
    ],
    "wof:name":"West World Computers Ltd",
    "wof:placetype":"venue"
},
  "geometry": {"coordinates":[-123.364738464,48.4321975708],"type":"Point"}
}