{
  "type": "Feature",
  "properties": {
    "addr:full":"601 Boul Perron E Maria QC G0C 1Y0",
    "addr:housenumber":"601",
    "addr:postcode":"g0c 1y0",
    "addr:street":"Boul Perron E Maria",
    "iso:country":"CA",
    "sg:address":"601 Boul Perron E",
    "sg:city":"Maria",
    "sg:classifiers":[
        {
            "category":"Shopping",
            "subcategory":"Bicycles & Sporting Goods",
            "type":"Retail Goods"
        }
    ],
    "sg:phone":"+1 418 759 5469",
    "sg:postcode":"G0C 1Y0",
    "sg:province":"QC",
    "sg:tags":[
        "equipment",
        "archery",
        "supply"
    ],
    "wof:name":"Archerie Baie Des Chaleurs Enr",
    "wof:placetype":"venue"
},
  "geometry": {"coordinates":[-65.9774093628,48.1828079224],"type":"Point"}
}