{
  "type": "Feature",
  "properties": {
    "addr:full":"33 Mill St Carleton Place ON K7C 1T6",
    "addr:housenumber":"33",
    "addr:postcode":"k7c 1t6",
    "addr:street":"Mill St",
    "iso:country":"CA",
    "sg:address":"33 Mill St",
    "sg:city":"Carleton Place",
    "sg:classifiers":[
        {
            "category":"Manufacturing",
            "subcategory":"Rubber & Plastics",
            "type":"Manufacturing & Wholesale Goods"
        }
    ],
    "sg:phone":"+1 613 253 2932",
    "sg:postcode":"K7C 1T6",
    "sg:province":"ON",
    "sg:tags":[
        "mold",
        "maker"
    ],
    "wof:name":"Starline Products",
    "wof:placetype":"venue"
},
  "geometry": {"coordinates":[-76.14525604249999,45.1413383484],"type":"Point"}
}