{
  "type": "Feature",
  "properties": {
    "addr:full":"North Vancouver BC V7P 3S1",
    "addr:postcode":"v7p 3s1",
    "iso:country":"CA",
    "sg:city":"North Vancouver",
    "sg:classifiers":[
        {
            "category":"Mining & Drilling",
            "type":"Manufacturing & Wholesale Goods"
        }
    ],
    "sg:phone":"+1 604 985 2572",
    "sg:postcode":"V7P 3S1",
    "sg:province":"BC",
    "sg:tags":[
        "contractor"
    ],
    "wof:name":"Miramar Mining Corp",
    "wof:placetype":"venue"
},
  "geometry": {"coordinates":[-123.097877502,49.3143348694],"type":"Point"}
}