{
  "type": "Feature",
  "properties": {
    "iso:country":"CA",
    "sg:address":"46 Ch Eardley",
    "sg:city":"Aylmer",
    "sg:classifiers":[
        {
            "category":"Organizations",
            "subcategory":"Professional Association",
            "type":"Services"
        }
    ],
    "sg:phone":"+1 819 684 8460",
    "sg:postcode":"J9H 4K2",
    "sg:province":"QC",
    "sg:tags":[
        "government"
    ],
    "wof:name":"Imperatif Francais",
    "wof:placetype":"venue"
},
  "geometry": {"coordinates":[-75.8497009277,45.3986434937],"type":"Point"}
}