{
  "type": "Feature",
  "properties": {
    "addr:full":"100 Rue Fontaine Saint-Denis-DE-Brompton QC J0B 2P0",
    "addr:housenumber":"100",
    "addr:postcode":"j0b 2p0",
    "addr:street":"Rue Fontaine",
    "iso:country":"CA",
    "sg:address":"100 Rue Fontaine",
    "sg:city":"Saint-Denis-DE-Brompton",
    "sg:classifiers":[
        {
            "category":"Building & Trades",
            "subcategory":"Electrical",
            "type":"Services"
        }
    ],
    "sg:phone":"+1 819 846 3105",
    "sg:postcode":"J0B 2P0",
    "sg:province":"QC",
    "sg:tags":[
        "electric",
        "contractor"
    ],
    "wof:name":"Mgg Entrepreneur Electricien",
    "wof:placetype":"venue"
},
  "geometry": {"coordinates":[-72.1129455566,45.4503440857],"type":"Point"}
}