{
  "type": "Feature",
  "properties": {
    "addr:full":"1785 Wonderland Rd N London ON N6G 5C2",
    "addr:housenumber":"1785",
    "addr:postcode":"n6g 5c2",
    "addr:street":"Wonderland Rd N",
    "iso:country":"CA",
    "sg:address":"1785 Wonderland Rd N",
    "sg:city":"London",
    "sg:classifiers":[
        {
            "category":"Manufacturing",
            "subcategory":"Tools & Machinery",
            "type":"Manufacturing & Wholesale Goods"
        }
    ],
    "sg:phone":"+1 519 657 7633",
    "sg:postcode":"N6G 5C2",
    "sg:province":"ON",
    "sg:tags":[
        "machine"
    ],
    "wof:name":"Tricut Tool Inc",
    "wof:placetype":"venue"
},
  "geometry": {"coordinates":[-81.31162999999999,43.020393],"type":"Point"}
}