{
  "type": "Feature",
  "properties": {
    "iso:country":"CA",
    "sg:address":"801 Belgrave Way",
    "sg:city":"Delta",
    "sg:classifiers":[
        {
            "category":"Professional",
            "subcategory":"Business Services",
            "type":"Services"
        }
    ],
    "sg:phone":"+1 604 522 7655",
    "sg:postcode":"V3M 5R8",
    "sg:province":"BC",
    "sg:tags":[
        "excavating",
        "contractor"
    ],
    "wof:name":"Dial Contracting Ltd",
    "wof:placetype":"venue"
},
  "geometry": {"coordinates":[-122.93699646,49.178981781],"type":"Point"}
}