{
  "type": "Feature",
  "properties": {
    "addr:full":"Creston BC V0B 1G6",
    "addr:postcode":"bc v0b 1g6",
    "iso:country":"CA",
    "sg:city":"Creston",
    "sg:classifiers":[
        {
            "category":"Insurance",
            "subcategory":"Insurance Agent",
            "type":"Services"
        }
    ],
    "sg:phone":"+1 250 428 2294",
    "sg:postcode":"V0B 1G6",
    "sg:province":"BC",
    "wof:name":"Creston Valley Insurance Svc",
    "wof:placetype":"venue"
},
  "geometry": {"coordinates":[-116.519294739,49.1045150757],"type":"Point"}
}