{
  "type": "Feature",
  "properties": {
    "iso:country":"CA",
    "sg:address":"2376 Boulder St",
    "sg:city":"Revelstoke",
    "sg:classifiers":[
        {
            "category":"Manufacturing",
            "subcategory":"Lumber",
            "type":"Manufacturing & Wholesale Goods"
        }
    ],
    "sg:phone":"+1 250 837 3969",
    "sg:postcode":"V0E 2S0",
    "sg:province":"BC",
    "sg:tags":[
        "company",
        "logging"
    ],
    "wof:name":"Schiller Contracting Ltd",
    "wof:placetype":"venue"
},
  "geometry": {"coordinates":[-118.23749542199999,50.9972496033],"type":"Point"}
}