{
  "type": "Feature",
  "properties": {
    "addr:full":"34 Robinson Dr Grafton NB E7N 1G6",
    "addr:housenumber":"34",
    "addr:postcode":"e7n 1g6",
    "addr:street":"Robinson Dr",
    "iso:country":"CA",
    "sg:address":"34 Robinson Dr",
    "sg:city":"Grafton",
    "sg:classifiers":[
        {
            "category":"Retail",
            "subcategory":"Animal Services",
            "type":"Services"
        }
    ],
    "sg:phone":"+1 506 328 6954",
    "sg:postcode":"E7N 1G6",
    "sg:province":"NB",
    "sg:tags":[
        "pet",
        "boarding",
        "sitting"
    ],
    "wof:name":"Kelmgrove Boarding & Grooming",
    "wof:placetype":"venue"
},
  "geometry": {"coordinates":[-67.565781,46.139099],"type":"Point"}
}