{
  "type": "Feature",
  "properties": {
    "addr:full":"36A Rue DE LA Fabrique E Saint-Gervais QC G0R 3C0",
    "addr:housenumber":"36a",
    "addr:postcode":"g0r 3c0",
    "addr:street":"Rue De La Fabrique E Saint-Gervais",
    "iso:country":"CA",
    "sg:address":"36A Rue DE LA Fabrique E",
    "sg:city":"Saint-Gervais",
    "sg:classifiers":[
        {
            "category":"Education",
            "subcategory":"Library",
            "type":"Public Place"
        }
    ],
    "sg:phone":"+1 418 887 3628",
    "sg:postcode":"G0R 3C0",
    "sg:province":"QC",
    "wof:name":"Bibliotheque Municipale",
    "wof:placetype":"venue"
},
  "geometry": {"coordinates":[-70.886169,46.714821],"type":"Point"}
}