{
  "type": "Feature",
  "properties": {
    "addr:full":"310 Garrison Rd Fort Erie ON L2A 1M7",
    "addr:housenumber":"310",
    "addr:postcode":"l2a 1m7",
    "addr:street":"Garrison Rd",
    "iso:country":"CA",
    "sg:address":"310 Garrison Rd",
    "sg:city":"Fort Erie",
    "sg:classifiers":[
        {
            "category":"Personal",
            "subcategory":"Beauty Salon",
            "type":"Services"
        }
    ],
    "sg:phone":"+1 905 994 1563",
    "sg:postcode":"L2A 1M7",
    "sg:province":"ON",
    "wof:name":"First Choice Haircutters",
    "wof:placetype":"venue"
},
  "geometry": {"coordinates":[-78.92615499999999,42.905418],"type":"Point"}
}