{
  "type": "Feature",
  "properties": {
    "addr:full":"332 6 Ave SE Calgary AB T2G 4S6",
    "addr:housenumber":"332",
    "addr:postcode":"t2g 4s6",
    "addr:street":"6 Ave Se",
    "iso:country":"CA",
    "sg:address":"332 6 Ave SE",
    "sg:city":"Calgary",
    "sg:classifiers":[
        {
            "category":"Education",
            "subcategory":"College",
            "type":"Public Place"
        }
    ],
    "sg:phone":"+1 403 410 1400",
    "sg:postcode":"T2G 4S6",
    "sg:province":"AB",
    "sg:tags":[
        "academic",
        "school"
    ],
    "wof:name":"Bow Valley College",
    "wof:placetype":"venue"
},
  "geometry": {"coordinates":[-114.05699157700001,51.0474052429],"type":"Point"}
}