{
  "type": "Feature",
  "properties": {
    "addr:full":"5482 Hill Rd Sechelt BC V0N 3A8",
    "addr:housenumber":"5482",
    "addr:postcode":"v0n 3a8",
    "addr:street":"Hill Rd",
    "iso:country":"CA",
    "sg:address":"5482 Hill Rd",
    "sg:city":"Sechelt",
    "sg:classifiers":[
        {
            "category":"Personal",
            "type":"Services"
        }
    ],
    "sg:phone":"+1 604 885 3144",
    "sg:postcode":"V0N 3A8",
    "sg:province":"BC",
    "sg:tags":[
        "therapist",
        "massage"
    ],
    "wof:name":"Wilkinson, Brenda A",
    "wof:placetype":"venue"
},
  "geometry": {"coordinates":[-123.83268,49.471504],"type":"Point"}
}