{
  "type": "Feature",
  "properties": {
    "addr:full":"65 Austin Dr Waterloo ON N2L 3Y5",
    "addr:housenumber":"65",
    "addr:postcode":"n2l 3y5",
    "addr:street":"Austin Dr",
    "iso:country":"CA",
    "sg:address":"65 Austin Dr",
    "sg:city":"Waterloo",
    "sg:classifiers":[
        {
            "category":"Building & Trades",
            "subcategory":"Landscaping Services",
            "type":"Services"
        }
    ],
    "sg:phone":"+1 519 576 1072",
    "sg:postcode":"N2L 3Y5",
    "sg:province":"ON",
    "sg:tags":[
        "lawn",
        "maintenance",
        "grounds"
    ],
    "wof:name":"Gerry's Home Maintenance",
    "wof:placetype":"venue"
},
  "geometry": {"coordinates":[-80.5330200195,43.4812431335],"type":"Point"}
}