{
  "type": "Feature",
  "properties": {
    "addr:full":"Seaforth ON N0K 1W0",
    "addr:postcode":"n0k 1w0",
    "iso:country":"CA",
    "sg:city":"Seaforth",
    "sg:classifiers":[
        {
            "category":"Professional",
            "subcategory":"Accounting & Tax Preparation",
            "type":"Services"
        }
    ],
    "sg:phone":"+1 519 527 0557",
    "sg:postcode":"N0K 1W0",
    "sg:province":"ON",
    "sg:tags":[
        "return",
        "filing"
    ],
    "wof:name":"Huron Tax Consultants",
    "wof:placetype":"venue"
},
  "geometry": {"coordinates":[-81.39529418950001,43.5508956909],"type":"Point"}
}