{
  "type": "Feature",
  "properties": {
    "addr:full":"42 Oakwood Ave N Mississauga ON L5G 3L8",
    "addr:housenumber":"42",
    "addr:postcode":"l5g 3l8",
    "addr:street":"Oakwood Ave N",
    "iso:country":"CA",
    "sg:address":"42 Oakwood Ave N",
    "sg:city":"Mississauga",
    "sg:classifiers":[
        {
            "category":"Professional",
            "subcategory":"Computer Services",
            "type":"Services"
        }
    ],
    "sg:phone":"+1 905 274 6785",
    "sg:postcode":"L5G 3L8",
    "sg:province":"ON",
    "sg:tags":[
        "internet"
    ],
    "wof:name":"Agorex",
    "wof:placetype":"venue"
},
  "geometry": {"coordinates":[-79.58062,43.559692],"type":"Point"}
}