{
  "type": "Feature",
  "properties": {
    "addr:full":"142 Rue Ste-Cecile Saint-Pie QC J0H 1W0",
    "addr:housenumber":"142",
    "addr:postcode":"j0h 1w0",
    "addr:street":"Rue Ste-Cecile",
    "iso:country":"CA",
    "sg:address":"142 Rue Ste-Cecile",
    "sg:city":"Saint-Pie",
    "sg:classifiers":[
        {
            "category":"Retail",
            "subcategory":"Auto Repair",
            "type":"Services"
        }
    ],
    "sg:phone":"+1 450 772 2959",
    "sg:postcode":"J0H 1W0",
    "sg:province":"QC",
    "sg:tags":[
        "repairing",
        "automobile",
        "brake"
    ],
    "wof:name":"Garage Claude Bernard Inc",
    "wof:placetype":"venue"
},
  "geometry": {"coordinates":[-72.901505,45.508099],"type":"Point"}
}