{
  "type": "Feature",
  "properties": {
    "iso:country":"CA",
    "sg:address":"5345 Boul DE L'Assomption # 220",
    "sg:city":"Montreal",
    "sg:classifiers":[
        {
            "category":"Health Services",
            "subcategory":"Doctor",
            "type":"Services"
        }
    ],
    "sg:phone":"+1 514 255 9006",
    "sg:postcode":"H1T 4B3",
    "sg:province":"QC",
    "sg:tags":[
        "clinic"
    ],
    "wof:name":"Centre D'Urologie Maisonneuve",
    "wof:placetype":"venue"
},
  "geometry": {"coordinates":[-73.54810333250001,45.5695075989],"type":"Point"}
}