{
  "type": "Feature",
  "properties": {
    "addr:full":"2447 Kaladar Ave Ottawa ON K1V 8B9",
    "addr:housenumber":"2447",
    "addr:postcode":"k1v 8b9",
    "addr:street":"Kaladar Ave",
    "iso:country":"CA",
    "sg:address":"2447 Kaladar Ave",
    "sg:city":"Ottawa",
    "sg:classifiers":[
        {
            "category":"Home & Garden",
            "subcategory":"Building Materials",
            "type":"Retail Goods"
        }
    ],
    "sg:phone":"+1 613 523 4544",
    "sg:postcode":"K1V 8B9",
    "sg:province":"ON",
    "sg:tags":[
        "glass",
        "window",
        "plate"
    ],
    "wof:name":"At Brown & Mac Farlane Glass",
    "wof:placetype":"venue"
},
  "geometry": {"coordinates":[-75.671204,45.376827],"type":"Point"}
}