{
  "type": "Feature",
  "properties": {
    "iso:country":"CA",
    "sg:address":"120 Yale Ave",
    "sg:city":"Winnipeg",
    "sg:classifiers":[
        {
            "category":"Real Estate",
            "subcategory":"Architect",
            "type":"Services"
        }
    ],
    "sg:phone":"+1 204 475 8978",
    "sg:postcode":"R3M 0L7",
    "sg:province":"MB",
    "wof:name":"Penner, David",
    "wof:placetype":"venue"
},
  "geometry": {"coordinates":[-97.1642532349,49.8711051941],"type":"Point"}
}