{
  "type": "Feature",
  "properties": {
    "addr:full":"4625 Mccall Way NE Calgary AB T2E 8A5",
    "addr:housenumber":"4625",
    "addr:postcode":"t2e 8a5",
    "addr:street":"Mccall Way Ne",
    "iso:country":"CA",
    "sg:address":"4625 Mccall Way NE",
    "sg:city":"Calgary",
    "sg:classifiers":[
        {
            "category":"Autos & Motor Vehicles",
            "subcategory":"Fuel & Gas Station",
            "type":"Retail Goods"
        }
    ],
    "sg:phone":"+1 403 250 5040",
    "sg:postcode":"T2E 8A5",
    "sg:province":"AB",
    "sg:tags":[
        "oil"
    ],
    "wof:name":"Fastop Esso",
    "wof:placetype":"venue"
},
  "geometry": {"coordinates":[-114.011894226,51.0940170288],"type":"Point"}
}