{
  "type": "Feature",
  "properties": {
    "iso:country":"CA",
    "sg:address":"295 Av Claude",
    "sg:city":"Dorval",
    "sg:classifiers":[
        {
            "category":"Wholesale",
            "subcategory":"Electrical",
            "type":"Manufacturing & Wholesale Goods"
        }
    ],
    "sg:phone":"+1 514 634 0690",
    "sg:postcode":"H9S 3B1",
    "sg:province":"QC",
    "sg:tags":[
        "intercommunication"
    ],
    "wof:name":"Intercom Montreal Enr",
    "wof:placetype":"venue"
},
  "geometry": {"coordinates":[-73.752777,45.444248],"type":"Point"}
}