{
  "type": "Feature",
  "properties": {
    "addr:full":"480 Railway St Southampton ON N0H 2L0",
    "addr:housenumber":"480",
    "addr:postcode":"n0h 2l0",
    "addr:street":"Railway St",
    "iso:country":"CA",
    "sg:address":"480 Railway St",
    "sg:city":"Southampton",
    "sg:classifiers":[
        {
            "category":"Building & Trades",
            "subcategory":"Construction",
            "type":"Services"
        }
    ],
    "sg:phone":"+1 519 797 5192",
    "sg:postcode":"N0H 2L0",
    "sg:province":"ON",
    "sg:tags":[
        "excavating",
        "contractor"
    ],
    "wof:name":"Willy's Contracting CO",
    "wof:placetype":"venue"
},
  "geometry": {"coordinates":[-81.372559,44.478909],"type":"Point"}
}