{
  "type": "Feature",
  "properties": {
    "addr:full":"211 Main St Geraldton ON P0T 1M0",
    "addr:housenumber":"211",
    "addr:postcode":"p0t 1m0",
    "addr:street":"Main St",
    "iso:country":"CA",
    "sg:address":"211 Main St",
    "sg:city":"Geraldton",
    "sg:classifiers":[
        {
            "category":"Food & Beverages",
            "subcategory":"Groceries & Convenience Stores",
            "type":"Retail Goods"
        }
    ],
    "sg:phone":"+1 807 854 0289",
    "sg:postcode":"P0T 1M0",
    "sg:province":"ON",
    "sg:tags":[
        "grocer"
    ],
    "wof:name":"Val's Variety",
    "wof:placetype":"venue"
},
  "geometry": {"coordinates":[-86.948448,49.725105],"type":"Point"}
}