{
  "type": "Feature",
  "properties": {
    "addr:full":"161 Madison Ave Toronto ON M5R 2S6",
    "addr:housenumber":"161",
    "addr:postcode":"m5r 2s6",
    "addr:street":"Madison Ave",
    "iso:country":"CA",
    "sg:address":"161 Madison Ave",
    "sg:city":"Toronto",
    "sg:classifiers":[
        {
            "category":"Social Services",
            "subcategory":"Child Care",
            "type":"Services"
        }
    ],
    "sg:phone":"+1 416 924 0545",
    "sg:postcode":"M5R 2S6",
    "sg:province":"ON",
    "wof:name":"Annex Creche Child Care Ctr",
    "wof:placetype":"venue"
},
  "geometry": {"coordinates":[-79.404922,43.673008],"type":"Point"}
}