{
  "type": "Feature",
  "properties": {
    "iso:country":"CA",
    "sg:address":"3595 Av Appleton",
    "sg:city":"Montreal",
    "sg:classifiers":[
        {
            "category":"Restaurant",
            "type":"Food & Drink"
        }
    ],
    "sg:phone":"+1 514 739 9359",
    "sg:postcode":"H3S 1L7",
    "sg:province":"QC",
    "sg:tags":[
        "parlor",
        "ice",
        "cream"
    ],
    "wof:name":"Jungle Creme Glacee",
    "wof:placetype":"venue"
},
  "geometry": {"coordinates":[-73.634819,45.50235],"type":"Point"}
}