{
  "type": "Feature",
  "properties": {
    "addr:full":"3595 Av Appleton Montreal QC H3S 1L7",
    "addr:housenumber":"3595",
    "addr:postcode":"h3s 1l7",
    "addr:street":"Av Appleton",
    "iso:country":"CA",
    "sg:address":"3595 Av Appleton",
    "sg:city":"Montreal",
    "sg:classifiers":[
        {
            "category":"Restaurant",
            "type":"Food & Drink"
        }
    ],
    "sg:phone":"+1 514 739 9359",
    "sg:postcode":"H3S 1L7",
    "sg:province":"QC",
    "sg:tags":[
        "parlor",
        "ice",
        "cream"
    ],
    "wof:name":"Jungle Creme Glacee",
    "wof:placetype":"venue"
},
  "geometry": {"coordinates":[-73.63481899999999,45.50235],"type":"Point"}
}