{
  "type": "Feature",
  "properties": {
    "addr:full":"513 North River Rd Charlottetown PE C1E 1J6",
    "addr:housenumber":"513",
    "addr:postcode":"c1e 1j6",
    "addr:street":"North River Rd",
    "iso:country":"CA",
    "sg:address":"513 North River Rd",
    "sg:city":"Charlottetown",
    "sg:classifiers":[
        {
            "category":"Real Estate",
            "subcategory":"Real Estate Operator",
            "type":"Services"
        }
    ],
    "sg:phone":"+1 902 629 8405",
    "sg:postcode":"C1E 1J6",
    "sg:province":"PE",
    "sg:tags":[
        "apartment"
    ],
    "wof:name":"Norray Properties",
    "wof:placetype":"venue"
},
  "geometry": {"coordinates":[-63.1540756226,46.2574920654],"type":"Point"}
}