{
  "type": "Feature",
  "properties": {
    "addr:full":"Rodney ON N0L 2C0",
    "addr:postcode":"n0l 2c0",
    "iso:country":"CA",
    "sg:city":"Rodney",
    "sg:classifiers":[
        {
            "category":"Real Estate",
            "subcategory":"Real Estate Agent",
            "type":"Services"
        }
    ],
    "sg:phone":"+1 519 785 1500",
    "sg:postcode":"N0L 2C0",
    "sg:province":"ON",
    "wof:name":"Compass Realty",
    "wof:placetype":"venue"
},
  "geometry": {"coordinates":[-81.681679,42.566704],"type":"Point"}
}