{
  "type": "Feature",
  "properties": {
    "addr:full":"245 Riviera Dr # 6 Markham ON L3R 5J9",
    "addr:housenumber":"245",
    "addr:postcode":"l3r 5j9",
    "addr:street":"Riviera Dr # 6",
    "iso:country":"CA",
    "sg:address":"245 Riviera Dr # 6",
    "sg:city":"Markham",
    "sg:classifiers":[
        {
            "category":"Professional",
            "subcategory":"Art Services",
            "type":"Services"
        }
    ],
    "sg:phone":"+1 905 944 1790",
    "sg:postcode":"L3R 5J9",
    "sg:province":"ON",
    "sg:tags":[
        "graphic",
        "designer"
    ],
    "wof:name":"J & D Creative Inc",
    "wof:placetype":"venue"
},
  "geometry": {"coordinates":[-79.337952,43.833412],"type":"Point"}
}