{
  "type": "Feature",
  "properties": {
    "addr:full":"Blainville QC J7C 3M9",
    "addr:postcode":"j7c 3m9",
    "iso:country":"CA",
    "sg:city":"Blainville",
    "sg:classifiers":[
        {
            "category":"Shopping",
            "subcategory":"Pharmacy",
            "type":"Retail Goods"
        }
    ],
    "sg:phone":"+1 450 435 1981",
    "sg:postcode":"J7C 3M9",
    "sg:province":"QC",
    "wof:name":"Jean Coutu",
    "wof:placetype":"venue"
},
  "geometry": {"coordinates":[-73.8862915039,45.6773948669],"type":"Point"}
}