{
  "type": "Feature",
  "properties": {
    "addr:full":"230 Main St W Port Colborne ON L3K 3V5",
    "addr:housenumber":"230",
    "addr:postcode":"l3k 3v5",
    "addr:street":"Main St W",
    "iso:country":"CA",
    "sg:address":"230 Main St W",
    "sg:city":"Port Colborne",
    "sg:classifiers":[
        {
            "category":"Travel",
            "subcategory":"Travel Agent",
            "type":"Entertainment"
        }
    ],
    "sg:phone":"+1 905 834 0088",
    "sg:postcode":"L3K 3V5",
    "sg:province":"ON",
    "sg:tags":[
        "agency",
        "bureau"
    ],
    "wof:name":"M Y Travel & Cruises",
    "wof:placetype":"venue"
},
  "geometry": {"coordinates":[-79.25308990480001,42.8993721008],"type":"Point"}
}