{
  "type": "Feature",
  "properties": {
    "addr:full":"55 Whitewood Ave New Liskeard ON P0J 1P0",
    "addr:housenumber":"55",
    "addr:postcode":"p0j 1p0",
    "addr:street":"Whitewood Ave",
    "iso:country":"CA",
    "sg:address":"55 Whitewood Ave",
    "sg:city":"New Liskeard",
    "sg:classifiers":[
        {
            "category":"Communications",
            "subcategory":"Radio Station",
            "type":"Services"
        }
    ],
    "sg:phone":"+1 705 647 6565",
    "sg:postcode":"P0J 1P0",
    "sg:province":"ON",
    "sg:tags":[
        "company",
        "broadcasting"
    ],
    "wof:name":"Cjtt Radio",
    "wof:placetype":"venue"
},
  "geometry": {"coordinates":[-79.669899,47.508678],"type":"Point"}
}