{
  "type": "Feature",
  "properties": {
    "iso:country":"CA",
    "sg:city":"Prince Rupert",
    "sg:classifiers":[
        {
            "category":"Shopping",
            "subcategory":"Shoes",
            "type":"Retail Goods"
        }
    ],
    "sg:phone":"+1 250 627 5588",
    "sg:postcode":"V8J 3T6",
    "sg:province":"BC",
    "wof:name":"Bata-Athletes World",
    "wof:placetype":"venue"
},
  "geometry": {"coordinates":[-130.32691955600001,54.3127250671],"type":"Point"}
}