{
  "type": "Feature",
  "properties": {
    "iso:country":"CA",
    "sg:address":"1193 Fisher St",
    "sg:city":"North Bay",
    "sg:classifiers":[
        {
            "category":"Farming",
            "subcategory":"Dairy Farm",
            "type":"Manufacturing & Wholesale Goods"
        }
    ],
    "sg:phone":"+1 705 476 1661",
    "sg:postcode":"P1B 2G8",
    "sg:province":"ON",
    "wof:name":"Mrs Jersey's Dairy",
    "wof:placetype":"venue"
},
  "geometry": {"coordinates":[-79.44871500000001,46.311295],"type":"Point"}
}