{
  "type": "Feature",
  "properties": {
    "iso:country":"CA",
    "sg:city":"Toronto",
    "sg:classifiers":[
        {
            "category":"Shopping",
            "subcategory":"Bicycles & Sporting Goods",
            "type":"Retail Goods"
        }
    ],
    "sg:phone":"+1 416 703 9990",
    "sg:postcode":"M6J 1E4",
    "sg:province":"ON",
    "wof:name":"Cycle Shoppe",
    "wof:placetype":"venue"
},
  "geometry": {"coordinates":[-79.4058380127,43.6469535828],"type":"Point"}
}