{
  "type": "Feature",
  "properties": {
    "addr:full":"43 Mcmurchy Ave S Brampton ON L6Y 1Y5",
    "addr:housenumber":"43",
    "addr:postcode":"l6y 1y5",
    "addr:street":"Mcmurchy Ave S",
    "iso:country":"CA",
    "sg:address":"43 Mcmurchy Ave S",
    "sg:city":"Brampton",
    "sg:classifiers":[
        {
            "category":"Personal",
            "subcategory":"Beauty Salon",
            "type":"Services"
        }
    ],
    "sg:phone":"+1 905 459 8745",
    "sg:postcode":"L6Y 1Y5",
    "sg:province":"ON",
    "wof:name":"Studio N'Style",
    "wof:placetype":"venue"
},
  "geometry": {"coordinates":[-79.762665,43.678776],"type":"Point"}
}