{
  "type": "Feature",
  "properties": {
    "addr:full":"563 Main St Bury QC J0B 1J0",
    "addr:housenumber":"563",
    "addr:postcode":"j0b 1j0",
    "addr:street":"Main St",
    "iso:country":"CA",
    "sg:address":"563 Main St",
    "sg:city":"Bury",
    "sg:classifiers":[
        {
            "category":"Government",
            "subcategory":"Office",
            "type":"Public Place"
        }
    ],
    "sg:phone":"+1 819 872 3692",
    "sg:postcode":"J0B 1J0",
    "sg:province":"QC",
    "sg:tags":[
        "municipality"
    ],
    "wof:name":"Bury Municipalite",
    "wof:placetype":"venue"
},
  "geometry": {"coordinates":[-71.51323699949999,45.4867744446],"type":"Point"}
}