{
  "type": "Feature",
  "properties": {
    "addr:full":"469 Rue DE Normandie Sherbrooke QC J1G 2Z2",
    "addr:housenumber":"469",
    "addr:postcode":"j1g 2z2",
    "addr:street":"Rue De Normandie",
    "iso:country":"CA",
    "sg:address":"469 Rue DE Normandie",
    "sg:city":"Sherbrooke",
    "sg:classifiers":[
        {
            "category":"Building & Trades",
            "subcategory":"Construction",
            "type":"Services"
        }
    ],
    "sg:phone":"+1 819 346 5172",
    "sg:postcode":"J1G 2Z2",
    "sg:province":"QC",
    "sg:tags":[
        "masonry",
        "contractor"
    ],
    "wof:name":"Maconnerie Daniel Bureau",
    "wof:placetype":"venue"
},
  "geometry": {"coordinates":[-71.865303,45.400414],"type":"Point"}
}