{
  "type": "Feature",
  "properties": {
    "addr:full":"56 Riverside Dr Big Cove NB E4W 2Y8",
    "addr:housenumber":"56",
    "addr:postcode":"e4w 2y8",
    "addr:street":"Riverside Dr Big Cove",
    "iso:country":"CA",
    "sg:address":"56 Riverside Dr",
    "sg:city":"Big Cove",
    "sg:classifiers":[
        {
            "category":"Building & Trades",
            "subcategory":"Construction",
            "type":"Services"
        }
    ],
    "sg:phone":"+1 506 532 2243",
    "sg:postcode":"E4W 2Y8",
    "sg:province":"NB",
    "sg:tags":[
        "contractor"
    ],
    "wof:name":"B & C Contractors Ltd",
    "wof:placetype":"venue"
},
  "geometry": {"coordinates":[-64.98640399999999,46.586174],"type":"Point"}
}