{
  "type": "Feature",
  "properties": {
    "addr:full":"780 Balm Beach Rd Midland ON L4R 4K4",
    "addr:housenumber":"780",
    "addr:postcode":"l4r 4k4",
    "addr:street":"Balm Beach Rd",
    "iso:country":"CA",
    "sg:address":"780 Balm Beach Rd",
    "sg:city":"Midland",
    "sg:classifiers":[
        {
            "category":"Professional",
            "subcategory":"Business Services",
            "type":"Services"
        }
    ],
    "sg:phone":"+1 705 526 6665",
    "sg:postcode":"L4R 4K4",
    "sg:province":"ON",
    "sg:tags":[
        "water",
        "treatment"
    ],
    "wof:name":"Water Stop",
    "wof:placetype":"venue"
},
  "geometry": {"coordinates":[-79.90863800050001,44.7344093323],"type":"Point"}
}