{
  "type": "Feature",
  "properties": {
    "addr:full":"245 Ontario St Port Hope ON L1A 2V9",
    "addr:housenumber":"245",
    "addr:postcode":"l1a 2v9",
    "addr:street":"Ontario St",
    "iso:country":"CA",
    "sg:address":"245 Ontario St",
    "sg:city":"Port Hope",
    "sg:classifiers":[
        {
            "category":"Government",
            "subcategory":"Fire Station",
            "type":"Public Place"
        }
    ],
    "sg:phone":"+1 905 885 5323",
    "sg:postcode":"L1A 2V9",
    "sg:province":"ON",
    "sg:tags":[
        "department"
    ],
    "wof:name":"Port Hope Fire Adm Office",
    "wof:placetype":"venue"
},
  "geometry": {"coordinates":[-78.29079400000001,43.962635],"type":"Point"}
}