{
  "type": "Feature",
  "properties": {
    "addr:full":"PO Box 6152 STN Main Wetaskiwin AB T9A 2E9",
    "addr:housenumber":"po",
    "addr:postcode":"6152;t9a 2e9",
    "addr:street":"Box;Stn Main",
    "iso:country":"CA",
    "sg:address":"PO Box 6152 STN Main",
    "sg:city":"Wetaskiwin",
    "sg:classifiers":[
        {
            "category":"Freight",
            "type":"Transportation"
        }
    ],
    "sg:phone":"+1 780 352 2526",
    "sg:postcode":"T9A 2E9",
    "sg:province":"AB",
    "sg:tags":[
        "trucking"
    ],
    "wof:name":"Wallis Transport Ltd",
    "wof:placetype":"venue"
},
  "geometry": {"coordinates":[-113.377243042,52.969909668],"type":"Point"}
}