{
  "type": "Feature",
  "properties": {
    "addr:full":"8409 Granville St Vancouver BC V6P 4Z9",
    "addr:housenumber":"8409",
    "addr:postcode":"v6p 4z9",
    "addr:street":"Granville St",
    "iso:country":"CA",
    "sg:address":"8409 Granville St",
    "sg:city":"Vancouver",
    "sg:classifiers":[
        {
            "category":"Personal",
            "subcategory":"Beauty Salon",
            "type":"Services"
        }
    ],
    "sg:phone":"+1 604 266 8872",
    "sg:postcode":"V6P 4Z9",
    "sg:province":"BC",
    "wof:name":"Red Hill Hair Salon",
    "wof:placetype":"venue"
},
  "geometry": {"coordinates":[-123.14067077599999,49.2102775574],"type":"Point"}
}