{
  "type": "Feature",
  "properties": {
    "iso:country":"CA",
    "sg:address":"161 Park Ave",
    "sg:city":"Lac Du Bonnet",
    "sg:classifiers":[
        {
            "category":"Building & Trades",
            "subcategory":"Electrical",
            "type":"Services"
        }
    ],
    "sg:phone":"+1 204 345 2320",
    "sg:postcode":"R0E 1A0",
    "sg:province":"MB",
    "sg:tags":[
        "electric",
        "contractor"
    ],
    "wof:name":"Urban Sales & Svc",
    "wof:placetype":"venue"
},
  "geometry": {"coordinates":[-96.0590667725,50.2523231506],"type":"Point"}
}