{
  "type": "Feature",
  "properties": {
    "addr:full":"PO Box 3675 STN Main Spruce Grove AB T7X 3A9",
    "addr:housenumber":"po",
    "addr:postcode":"t7x 3a9",
    "addr:street":"Box 3675 Stn Main",
    "iso:country":"CA",
    "sg:address":"PO Box 3675 STN Main",
    "sg:city":"Spruce Grove",
    "sg:classifiers":[
        {
            "category":"Building & Trades",
            "subcategory":"Construction",
            "type":"Services"
        }
    ],
    "sg:phone":"+1 780 962 8570",
    "sg:postcode":"T7X 3A9",
    "sg:province":"AB",
    "sg:tags":[
        "excavating",
        "contractor"
    ],
    "wof:name":"Kev's Backhoe & Excavating Ltd",
    "wof:placetype":"venue"
},
  "geometry": {"coordinates":[-113.901855,53.544636],"type":"Point"}
}