{
  "type": "Feature",
  "properties": {
    "addr:full":"98 Centre St St Thomas ON N5R 2Z7",
    "addr:housenumber":"98",
    "addr:postcode":"n5r 2z7",
    "addr:street":"Centre St",
    "iso:country":"CA",
    "sg:address":"98 Centre St",
    "sg:city":"St Thomas",
    "sg:classifiers":[
        {
            "category":"Professional",
            "subcategory":"Business Services",
            "type":"Services"
        }
    ],
    "sg:phone":"+1 519 633 2638",
    "sg:postcode":"N5R 2Z7",
    "sg:province":"ON",
    "sg:tags":[
        "arbitration"
    ],
    "wof:name":"Elgin Oxford Legal Clinic",
    "wof:placetype":"venue"
},
  "geometry": {"coordinates":[-81.20154599999999,42.777821],"type":"Point"}
}