{
  "type": "Feature",
  "properties": {
    "addr:full":"267 Granville St Bridgetown NS B0S 1C0",
    "addr:housenumber":"267",
    "addr:postcode":"b0s 1c0",
    "addr:street":"Granville St",
    "iso:country":"CA",
    "sg:address":"267 Granville St",
    "sg:city":"Bridgetown",
    "sg:classifiers":[
        {
            "category":"Home & Garden",
            "subcategory":"Furniture",
            "type":"Retail Goods"
        }
    ],
    "sg:phone":"+1 902 665 4612",
    "sg:postcode":"B0S 1C0",
    "sg:province":"NS",
    "sg:tags":[
        "television",
        "radio"
    ],
    "wof:name":"am Jazey's Furniture & Appls",
    "wof:placetype":"venue"
},
  "geometry": {"coordinates":[-65.29151899999999,44.841789],"type":"Point"}
}