{
  "type": "Feature",
  "properties": {
    "addr:full":"12 Hagey Ave Fort Erie ON L2A 1W3",
    "addr:housenumber":"12",
    "addr:postcode":"l2a 1w3",
    "addr:street":"Hagey Ave",
    "iso:country":"CA",
    "sg:address":"12 Hagey Ave",
    "sg:city":"Fort Erie",
    "sg:classifiers":[
        {
            "category":"Manufacturing",
            "subcategory":"Food",
            "type":"Manufacturing & Wholesale Goods"
        }
    ],
    "sg:phone":"+1 905 871 2605",
    "sg:postcode":"L2A 1W3",
    "sg:province":"ON",
    "sg:tags":[
        "frozen",
        "processor"
    ],
    "wof:name":"Rich Products of Canada Ltd",
    "wof:placetype":"venue"
},
  "geometry": {"coordinates":[-78.923225,42.911079],"type":"Point"}
}