{
  "type": "Feature",
  "properties": {
    "addr:full":"29 Boulder Blvd Stony Plain AB T7Z 1V6",
    "addr:housenumber":"29",
    "addr:postcode":"t7z 1v6",
    "addr:street":"Boulder Blvd",
    "iso:country":"CA",
    "sg:address":"29 Boulder Blvd",
    "sg:city":"Stony Plain",
    "sg:classifiers":[
        {
            "category":"Building & Trades",
            "subcategory":"Plumbing",
            "type":"Services"
        }
    ],
    "sg:phone":"+1 780 963 8282",
    "sg:postcode":"T7Z 1V6",
    "sg:province":"AB",
    "sg:tags":[
        "contractor"
    ],
    "wof:name":"Plumbing Hut",
    "wof:placetype":"venue"
},
  "geometry": {"coordinates":[-113.99277499999999,53.542606],"type":"Point"}
}