{
  "type": "Feature",
  "properties": {
    "addr:full":"1614 75th Ave W Vancouver BC V6P 6G2",
    "addr:housenumber":"1614",
    "addr:postcode":"v6p 6g2",
    "addr:street":"75Th Ave W",
    "iso:country":"CA",
    "sg:address":"1614 75th Ave W",
    "sg:city":"Vancouver",
    "sg:classifiers":[
        {
            "category":"Manufacturing",
            "subcategory":"Metals",
            "type":"Manufacturing & Wholesale Goods"
        }
    ],
    "sg:phone":"+1 604 261 8884",
    "sg:postcode":"V6P 6G2",
    "sg:province":"BC",
    "sg:tags":[
        "glass",
        "product",
        "lead"
    ],
    "wof:name":"Cascade Lead Products Ltd",
    "wof:placetype":"venue"
},
  "geometry": {"coordinates":[-123.14447800000001,49.205013],"type":"Point"}
}