{
  "type": "Feature",
  "properties": {
    "addr:full":"Hamilton ON L8H 3Z3",
    "addr:postcode":"l8h 3z3",
    "iso:country":"CA",
    "sg:city":"Hamilton",
    "sg:classifiers":[
        {
            "category":"Shopping",
            "subcategory":"Discount & Variety Stores",
            "type":"Retail Goods"
        }
    ],
    "sg:phone":"+1 905 547 7771",
    "sg:postcode":"L8H 3Z3",
    "sg:province":"ON",
    "wof:name":"Crown Grocery & Variety",
    "wof:placetype":"venue"
},
  "geometry": {"coordinates":[-79.818016,43.246349],"type":"Point"}
}