{
  "type": "Feature",
  "properties": {
    "addr:full":"9525 Boul Taschereau Brossard QC J4Y 2J3",
    "addr:housenumber":"9525",
    "addr:postcode":"j4y 2j3",
    "addr:street":"Boul Taschereau",
    "iso:country":"CA",
    "sg:address":"9525 Boul Taschereau",
    "sg:city":"Brossard",
    "sg:classifiers":[
        {
            "category":"Recreation",
            "type":"Entertainment"
        }
    ],
    "sg:phone":"+1 450 659 2966",
    "sg:postcode":"J4Y 2J3",
    "sg:province":"QC",
    "sg:tags":[
        "skating",
        "rink"
    ],
    "wof:name":"Paladium",
    "wof:placetype":"venue"
},
  "geometry": {"coordinates":[-73.4775009155,45.432762146],"type":"Point"}
}