{
  "type": "Feature",
  "properties": {
    "iso:country":"CA",
    "sg:address":"639 Yonge St",
    "sg:city":"Toronto",
    "sg:classifiers":[
        {
            "category":"Personal",
            "subcategory":"Beauty Salon",
            "type":"Services"
        }
    ],
    "sg:phone":"+1 416 962 1111",
    "sg:postcode":"M4Y 1Z9",
    "sg:province":"ON",
    "wof:name":"House of Lords Hair Design",
    "wof:placetype":"venue"
},
  "geometry": {"coordinates":[-79.385597229,43.6676445007],"type":"Point"}
}