{
  "type": "Feature",
  "properties": {
    "addr:full":"88 Hilltop Dr Hampton NB E5N 5P2",
    "addr:housenumber":"88",
    "addr:postcode":"e5n 5p2",
    "addr:street":"Hilltop Dr",
    "iso:country":"CA",
    "sg:address":"88 Hilltop Dr",
    "sg:city":"Hampton",
    "sg:classifiers":[
        {
            "category":"Professional",
            "subcategory":"Accounting & Tax Preparation",
            "type":"Services"
        }
    ],
    "sg:phone":"+1 506 832 7964",
    "sg:postcode":"E5N 5P2",
    "sg:province":"NB",
    "sg:tags":[
        "accountant"
    ],
    "wof:name":"Reid & Assoc",
    "wof:placetype":"venue"
},
  "geometry": {"coordinates":[-65.837891,45.525879],"type":"Point"}
}