{
  "type": "Feature",
  "properties": {
    "iso:country":"CA",
    "sg:address":"North Cape",
    "sg:city":"Tignish",
    "sg:classifiers":[
        {
            "category":"Restaurant",
            "type":"Food & Drink"
        }
    ],
    "sg:phone":"+1 902 882 3535",
    "sg:postcode":"C0B 2B0",
    "sg:province":"PE",
    "wof:name":"Wind & Reef Seafood Restaurant",
    "wof:placetype":"venue"
},
  "geometry": {"coordinates":[-64.03338599999999,46.951317],"type":"Point"}
}