{
  "type": "Feature",
  "properties": {
    "addr:full":"2700 Central Ave Windsor ON N8W 4J5",
    "addr:housenumber":"2700",
    "addr:postcode":"n8w 4j5",
    "addr:street":"Central Ave",
    "iso:country":"CA",
    "sg:address":"2700 Central Ave",
    "sg:city":"Windsor",
    "sg:classifiers":[
        {
            "category":"Retail",
            "subcategory":"Auto Repair",
            "type":"Services"
        }
    ],
    "sg:phone":"+1 519 974 4965",
    "sg:postcode":"N8W 4J5",
    "sg:province":"ON",
    "sg:tags":[
        "truck"
    ],
    "wof:name":"Dng Truck & Trailer Repair",
    "wof:placetype":"venue"
},
  "geometry": {"coordinates":[-82.9745941162,42.2964019775],"type":"Point"}
}