{
  "type": "Feature",
  "properties": {
    "iso:country":"CA",
    "sg:address":"314 Marten St",
    "sg:city":"Banff",
    "sg:classifiers":[
        {
            "category":"Professional",
            "subcategory":"Employment Agencies",
            "type":"Services"
        }
    ],
    "sg:phone":"+1 403 760 3311",
    "sg:postcode":"T1L 1B8",
    "sg:province":"AB",
    "sg:tags":[
        "opportunity"
    ],
    "wof:name":"Job Resource Ctr",
    "wof:placetype":"venue"
},
  "geometry": {"coordinates":[-115.572120666,51.1791687012],"type":"Point"}
}