{
  "type": "Feature",
  "properties": {
    "addr:full":"25991 Highway 41 Denbigh ON K0H 1L0",
    "addr:housenumber":"25991",
    "addr:postcode":"k0h 1l0",
    "addr:street":"Highway 41",
    "iso:country":"CA",
    "sg:address":"25991 Highway 41",
    "sg:city":"Denbigh",
    "sg:classifiers":[
        {
            "category":"Recreation",
            "type":"Entertainment"
        }
    ],
    "sg:phone":"+1 613 333 1423",
    "sg:postcode":"K0H 1L0",
    "sg:province":"ON",
    "sg:tags":[
        "center"
    ],
    "wof:name":"Griffith & Matawatchan Lions",
    "wof:placetype":"venue"
},
  "geometry": {"coordinates":[-77.2655410767,45.1427879333],"type":"Point"}
}