{
  "type": "Feature",
  "properties": {
    "addr:full":"9 Rue Arnault Notre-Dame-Des-Prairies QC J6E 6W1",
    "addr:housenumber":"9",
    "addr:postcode":"j6e 6w1",
    "addr:street":"Rue Arnault",
    "iso:country":"CA",
    "sg:address":"9 Rue Arnault",
    "sg:city":"Notre-Dame-Des-Prairies",
    "sg:classifiers":[
        {
            "category":"Health Services",
            "subcategory":"Medical Lab",
            "type":"Services"
        }
    ],
    "sg:phone":"+1 450 755 3355",
    "sg:postcode":"J6E 6W1",
    "sg:province":"QC",
    "wof:name":"Charbonneau, Jean-Pierre",
    "wof:placetype":"venue"
},
  "geometry": {"coordinates":[-73.42525500000001,46.041134],"type":"Point"}
}