{
  "type": "Feature",
  "properties": {
    "addr:full":"8155 149 St Surrey BC V3S 7H4",
    "addr:housenumber":"8155",
    "addr:postcode":"v3s 7h4",
    "addr:street":"149 St",
    "iso:country":"CA",
    "sg:address":"8155 149 St",
    "sg:city":"Surrey",
    "sg:classifiers":[
        {
            "category":"Building & Trades",
            "subcategory":"Equipment Rental",
            "type":"Services"
        }
    ],
    "sg:phone":"+1 604 594 5516",
    "sg:postcode":"V3S 7H4",
    "sg:province":"BC",
    "sg:tags":[
        "crane"
    ],
    "wof:name":"Progress Way Crane Rentals Ltd",
    "wof:placetype":"venue"
},
  "geometry": {"coordinates":[-122.80923461899999,49.150806427],"type":"Point"}
}