{
  "type": "Feature",
  "properties": {
    "addr:full":"91 George St N Peterborough ON K9J 3G3",
    "addr:housenumber":"91",
    "addr:postcode":"k9j 3g3",
    "addr:street":"George St N",
    "iso:country":"CA",
    "sg:address":"91 George St N",
    "sg:city":"Peterborough",
    "sg:classifiers":[
        {
            "category":"Shopping",
            "subcategory":"Optical Goods",
            "type":"Retail Goods"
        }
    ],
    "sg:phone":"+1 705 876 9900",
    "sg:postcode":"K9J 3G3",
    "sg:province":"ON",
    "sg:tags":[
        "optician"
    ],
    "wof:name":"Hakim Optical",
    "wof:placetype":"venue"
},
  "geometry": {"coordinates":[-78.3195343018,44.2962036133],"type":"Point"}
}