{
  "type": "Feature",
  "properties": {
    "addr:full":"Bradford ON L3Z 2A4",
    "addr:postcode":"l3z 2a4",
    "iso:country":"CA",
    "sg:city":"Bradford",
    "sg:classifiers":[
        {
            "category":"Travel",
            "subcategory":"Travel Agent",
            "type":"Entertainment"
        }
    ],
    "sg:phone":"+1 905 775 9006",
    "sg:postcode":"L3Z 2A4",
    "sg:province":"ON",
    "sg:tags":[
        "agency",
        "bureau"
    ],
    "wof:name":"Hamilton Tours Ltd",
    "wof:placetype":"venue"
},
  "geometry": {"coordinates":[-79.56366,44.114552],"type":"Point"}
}