{
  "type": "Feature",
  "properties": {
    "iso:country":"CA",
    "sg:city":"Kamloops",
    "sg:classifiers":[
        {
            "category":"Restaurant",
            "type":"Food & Drink"
        }
    ],
    "sg:phone":"+1 250 376 1005",
    "sg:postcode":"V2B 3H7",
    "sg:province":"BC",
    "wof:name":"Subway Sandwiches & Salads",
    "wof:placetype":"venue"
},
  "geometry": {"coordinates":[-120.361069,50.69648],"type":"Point"}
}