{
  "type": "Feature",
  "properties": {
    "iso:country":"CA",
    "sg:address":"1181 Thornton Rd S",
    "sg:city":"Oshawa",
    "sg:classifiers":[
        {
            "category":"Wholesale",
            "subcategory":"Construction Materials",
            "type":"Manufacturing & Wholesale Goods"
        }
    ],
    "sg:phone":"+1 905 571 2477",
    "sg:postcode":"L1J 8P4",
    "sg:province":"ON",
    "sg:tags":[
        "lumber"
    ],
    "wof:name":"Velcan Forest Products Inc",
    "wof:placetype":"venue"
},
  "geometry": {"coordinates":[-78.87940979,43.8602027893],"type":"Point"}
}