{
  "type": "Feature",
  "properties": {
    "addr:full":"152 4E Av E Amos QC J9T 1C6",
    "addr:housenumber":"152",
    "addr:postcode":"j9t 1c6",
    "addr:street":"4E Av E Amos",
    "iso:country":"CA",
    "sg:address":"152 4E Av E",
    "sg:city":"Amos",
    "sg:classifiers":[
        {
            "category":"Personal",
            "subcategory":"Beauty Salon",
            "type":"Services"
        }
    ],
    "sg:phone":"+1 819 727 1686",
    "sg:postcode":"J9T 1C6",
    "sg:province":"QC",
    "wof:name":"Salon DE Coiffure Marjolaine",
    "wof:placetype":"venue"
},
  "geometry": {"coordinates":[-78.112122,48.574997],"type":"Point"}
}