{
  "type": "Feature",
  "properties": {
    "addr:full":"280 Elson St # 7 Markham ON L3S 3L1",
    "addr:housenumber":"280",
    "addr:postcode":"l3s 3l1",
    "addr:street":"Elson St # 7",
    "iso:country":"CA",
    "sg:address":"280 Elson St # 7",
    "sg:city":"Markham",
    "sg:classifiers":[
        {
            "category":"Travel",
            "subcategory":"Travel Agent",
            "type":"Entertainment"
        }
    ],
    "sg:phone":"+1 905 294 2940",
    "sg:postcode":"L3S 3L1",
    "sg:province":"ON",
    "sg:tags":[
        "agency",
        "bureau"
    ],
    "wof:name":"Travel in Air",
    "wof:placetype":"venue"
},
  "geometry": {"coordinates":[-79.25350952150001,43.8402786255],"type":"Point"}
}