{
  "type": "Feature",
  "properties": {
    "iso:country":"CA",
    "sg:address":"305 Frederick St",
    "sg:city":"Kitchener",
    "sg:classifiers":[
        {
            "category":"Shopping",
            "type":"Retail Goods"
        }
    ],
    "sg:phone":"+1 519 742 9494",
    "sg:postcode":"N2H 2N6",
    "sg:province":"ON",
    "sg:tags":[
        "hearing",
        "equipment",
        "supply",
        "impaired"
    ],
    "wof:name":"Harold K Arnold Hearing Aids",
    "wof:placetype":"venue"
},
  "geometry": {"coordinates":[-80.47728,43.45599],"type":"Point"}
}