{
  "type": "Feature",
  "properties": {
    "addr:full":"219 Hansen Memorial Hwy Stephenville NL A2N 1W7",
    "addr:housenumber":"219",
    "addr:postcode":"a2n 1w7",
    "addr:street":"Hansen Memorial Hwy",
    "iso:country":"CA",
    "sg:address":"219 Hansen Memorial Hwy",
    "sg:city":"Stephenville",
    "sg:classifiers":[
        {
            "category":"Autos & Motor Vehicles",
            "subcategory":"Motorcycle Sales",
            "type":"Retail Goods"
        }
    ],
    "sg:phone":"+1 709 643 3503",
    "sg:postcode":"A2N 1W7",
    "sg:province":"NL",
    "sg:tags":[
        "recreational"
    ],
    "wof:name":"M & F Motors Ltd",
    "wof:placetype":"venue"
},
  "geometry": {"coordinates":[-58.575363,48.54599],"type":"Point"}
}