{
  "type": "Feature",
  "properties": {
    "addr:full":"3945 Matchette Rd Windsor ON N9C 4C2",
    "addr:housenumber":"3945",
    "addr:postcode":"n9c 4c2",
    "addr:street":"Matchette Rd",
    "iso:country":"CA",
    "sg:address":"3945 Matchette Rd",
    "sg:city":"Windsor",
    "sg:classifiers":[
        {
            "category":"Education",
            "subcategory":"School",
            "type":"Public Place"
        }
    ],
    "sg:phone":"+1 519 252 7281",
    "sg:postcode":"N9C 4C2",
    "sg:province":"ON",
    "sg:tags":[
        "rehabilitation"
    ],
    "wof:name":"Children's Rehabilitation Ctr",
    "wof:placetype":"venue"
},
  "geometry": {"coordinates":[-83.068321,42.28352],"type":"Point"}
}