{
  "type": "Feature",
  "properties": {
    "addr:full":"Campbell River BC V9W 2X9",
    "addr:postcode":"v9w 2x9",
    "iso:country":"CA",
    "sg:city":"Campbell River",
    "sg:classifiers":[
        {
            "category":"Shopping",
            "subcategory":"Florist",
            "type":"Retail Goods"
        }
    ],
    "sg:phone":"+1 250 287 8828",
    "sg:postcode":"V9W 2X9",
    "sg:province":"BC",
    "wof:name":"Bird of Paradise Floral Btq",
    "wof:placetype":"venue"
},
  "geometry": {"coordinates":[-125.247657776,50.0116004944],"type":"Point"}
}