{
  "type": "Feature",
  "properties": {
    "addr:full":"5128 50 St Mundare AB T0B 3H0",
    "addr:housenumber":"5128",
    "addr:postcode":"t0b 3h0",
    "addr:street":"50 St",
    "iso:country":"CA",
    "sg:address":"5128 50 St",
    "sg:city":"Mundare",
    "sg:classifiers":[
        {
            "category":"Personal",
            "type":"Services"
        }
    ],
    "sg:phone":"+1 780 764 2262",
    "sg:postcode":"T0B 3H0",
    "sg:province":"AB",
    "sg:tags":[
        "therapist",
        "massage"
    ],
    "wof:name":"Back To Basics Massage Therapy",
    "wof:placetype":"venue"
},
  "geometry": {"coordinates":[-112.339622498,53.5937347412],"type":"Point"}
}