{
  "type": "Feature",
  "properties": {
    "addr:full":"101 Bonnie Cres Elmira ON N3B 3G2",
    "addr:housenumber":"101",
    "addr:postcode":"n3b 3g2",
    "addr:street":"Bonnie Cres",
    "iso:country":"CA",
    "sg:address":"101 Bonnie Cres",
    "sg:city":"Elmira",
    "sg:classifiers":[
        {
            "category":"Retail",
            "subcategory":"Auto Repair",
            "type":"Services"
        }
    ],
    "sg:phone":"+1 519 669 8330",
    "sg:postcode":"N3B 3G2",
    "sg:province":"ON",
    "sg:tags":[
        "body",
        "automobile",
        "painting"
    ],
    "wof:name":"Savage Auto Body",
    "wof:placetype":"venue"
},
  "geometry": {"coordinates":[-80.554092,43.588146],"type":"Point"}
}