{
  "type": "Feature",
  "properties": {
    "addr:full":"5005 S Service Rd Beamsville ON L0R 1B5",
    "addr:housenumber":"5005",
    "addr:postcode":"l0r 1b5",
    "addr:street":"S Service Rd",
    "iso:country":"CA",
    "sg:address":"5005 S Service Rd",
    "sg:city":"Beamsville",
    "sg:classifiers":[
        {
            "category":"Autos & Motor Vehicles",
            "subcategory":"Fuel & Gas Station",
            "type":"Retail Goods"
        }
    ],
    "sg:phone":"+1 905 563 1981",
    "sg:postcode":"L0R 1B5",
    "sg:province":"ON",
    "sg:tags":[
        "oil"
    ],
    "wof:name":"Pioneer Petroleums",
    "wof:placetype":"venue"
},
  "geometry": {"coordinates":[-79.478363,43.186619],"type":"Point"}
}