{
  "type": "Feature",
  "properties": {
    "iso:country":"CA",
    "sg:address":"2260 Gladwin Rd",
    "sg:city":"Abbotsford",
    "sg:classifiers":[
        {
            "category":"Professional",
            "subcategory":"Lawyer & Legal Services",
            "type":"Services"
        }
    ],
    "sg:phone":"+1 604 859 7184",
    "sg:postcode":"V2S 2Y6",
    "sg:province":"BC",
    "sg:tags":[
        "attorney"
    ],
    "wof:name":"Bergen & CO Lawyers",
    "wof:placetype":"venue"
},
  "geometry": {"coordinates":[-122.315353394,49.0424156189],"type":"Point"}
}