{
  "type": "Feature",
  "properties": {
    "addr:full":"164 Queen St Hensall ON N0M 1X0",
    "addr:housenumber":"164",
    "addr:postcode":"n0m 1x0",
    "addr:street":"Queen St",
    "iso:country":"CA",
    "sg:address":"164 Queen St",
    "sg:city":"Hensall",
    "sg:classifiers":[
        {
            "category":"Restaurant",
            "type":"Food & Drink"
        }
    ],
    "sg:phone":"+1 519 262 3409",
    "sg:postcode":"N0M 1X0",
    "sg:province":"ON",
    "sg:tags":[
        "caterer"
    ],
    "wof:name":"Pineridge Barbecue CO",
    "wof:placetype":"venue"
},
  "geometry": {"coordinates":[-81.509308,43.434513],"type":"Point"}
}