{
  "type": "Feature",
  "properties": {
    "addr:full":"460 Rue Principale Saint-Anselme QC G0R 2N0",
    "addr:housenumber":"460",
    "addr:postcode":"g0r 2n0",
    "addr:street":"Rue Principale",
    "iso:country":"CA",
    "sg:address":"460 Rue Principale",
    "sg:city":"Saint-Anselme",
    "sg:classifiers":[
        {
            "category":"Organizations",
            "subcategory":"Professional Association",
            "type":"Services"
        }
    ],
    "sg:phone":"+1 418 885 9509",
    "sg:postcode":"G0R 2N0",
    "sg:province":"QC",
    "wof:name":"Syndicat Democratique Salaries",
    "wof:placetype":"venue"
},
  "geometry": {"coordinates":[-70.9579772949,46.6228561401],"type":"Point"}
}