{
  "type": "Feature",
  "properties": {
    "addr:full":"960 39th Ave E Vancouver BC V5W 1K8",
    "addr:housenumber":"960",
    "addr:postcode":"v5w 1k8",
    "addr:street":"39Th Ave E",
    "iso:country":"CA",
    "sg:address":"960 39th Ave E",
    "sg:city":"Vancouver",
    "sg:classifiers":[
        {
            "category":"Social Services",
            "subcategory":"Child Care",
            "type":"Services"
        }
    ],
    "sg:phone":"+1 604 321 4802",
    "sg:postcode":"V5W 1K8",
    "sg:province":"BC",
    "wof:name":"Mac Kenzie Ymca Out-School",
    "wof:placetype":"venue"
},
  "geometry": {"coordinates":[-123.085533142,49.2346191406],"type":"Point"}
}