{
  "type": "Feature",
  "properties": {
    "addr:full":"1291 Pinecrest Rd Ottawa ON K2C 3E7",
    "addr:housenumber":"1291",
    "addr:postcode":"k2c 3e7",
    "addr:street":"Pinecrest Rd",
    "iso:country":"CA",
    "sg:address":"1291 Pinecrest Rd",
    "sg:city":"Ottawa",
    "sg:classifiers":[
        {
            "category":"Professional",
            "subcategory":"Business Services",
            "type":"Services"
        }
    ],
    "sg:phone":"+1 613 726 1408",
    "sg:postcode":"K2C 3E7",
    "sg:province":"ON",
    "sg:tags":[
        "decorating",
        "contractor"
    ],
    "wof:name":"Envision This Creative Display",
    "wof:placetype":"venue"
},
  "geometry": {"coordinates":[-75.7864608765,45.3436355591],"type":"Point"}
}