{
  "type": "Feature",
  "properties": {
    "addr:full":"534 Dawson Rd Lorette MB R0A 0Y0",
    "addr:housenumber":"534",
    "addr:postcode":"r0a 0y0",
    "addr:street":"Dawson Rd",
    "iso:country":"CA",
    "sg:address":"534 Dawson Rd",
    "sg:city":"Lorette",
    "sg:classifiers":[
        {
            "category":"Autos & Motor Vehicles",
            "subcategory":"Fuel & Gas Station",
            "type":"Retail Goods"
        }
    ],
    "sg:phone":"+1 204 878 2201",
    "sg:postcode":"R0A 0Y0",
    "sg:province":"MB",
    "sg:tags":[
        "oil"
    ],
    "wof:name":"Shell Canada Products Ltd",
    "wof:placetype":"venue"
},
  "geometry": {"coordinates":[-96.87470245359999,49.7397232056],"type":"Point"}
}