{
  "type": "Feature",
  "properties": {
    "addr:full":"309 Mackenzie Ave Revelstoke BC V0E 2S0",
    "addr:housenumber":"309",
    "addr:postcode":"v0e 2s0",
    "addr:street":"Mackenzie Ave",
    "iso:country":"CA",
    "sg:address":"309 Mackenzie Ave",
    "sg:city":"Revelstoke",
    "sg:classifiers":[
        {
            "category":"Food & Beverages",
            "subcategory":"Specialty",
            "type":"Retail Goods"
        }
    ],
    "sg:phone":"+1 250 837 4458",
    "sg:postcode":"V0E 2S0",
    "sg:province":"BC",
    "sg:tags":[
        "health",
        "diet"
    ],
    "wof:name":"Revelstoke Health Food Store",
    "wof:placetype":"venue"
},
  "geometry": {"coordinates":[-118.196365,50.998158],"type":"Point"}
}