{
  "type": "Feature",
  "properties": {
    "addr:full":"1245 Dundas St W Toronto ON M6J 1X6",
    "addr:housenumber":"1245",
    "addr:postcode":"m6j 1x6",
    "addr:street":"Dundas St W",
    "iso:country":"CA",
    "sg:address":"1245 Dundas St W",
    "sg:city":"Toronto",
    "sg:classifiers":[
        {
            "category":"Retail",
            "subcategory":"Auto Repair",
            "type":"Services"
        }
    ],
    "sg:phone":"+1 416 531 3422",
    "sg:postcode":"M6J 1X6",
    "sg:province":"ON",
    "sg:tags":[
        "repairing",
        "automobile"
    ],
    "wof:name":"Honorato Auto Svc Inc",
    "wof:placetype":"venue"
},
  "geometry": {"coordinates":[-79.42408,43.649357],"type":"Point"}
}