{
  "type": "Feature",
  "properties": {
    "addr:full":"Quebec QC G1S 4T2",
    "addr:postcode":"g1s 4t2",
    "iso:country":"CA",
    "sg:city":"Quebec",
    "sg:classifiers":[
        {
            "category":"Real Estate",
            "subcategory":"Real Estate Operator",
            "type":"Services"
        }
    ],
    "sg:phone":"+1 418 687 5417",
    "sg:postcode":"G1S 4T2",
    "sg:province":"QC",
    "sg:tags":[
        "condominium"
    ],
    "wof:name":"CO-Propriete Jardins Manrese 1",
    "wof:placetype":"venue"
},
  "geometry": {"coordinates":[-71.239029,46.80164],"type":"Point"}
}