{
  "type": "Feature",
  "properties": {
    "iso:country":"CA",
    "sg:address":"Grand Bay Rd",
    "sg:city":"Grand Bay East",
    "sg:classifiers":[
        {
            "category":"Organizations",
            "subcategory":"Professional Association",
            "type":"Services"
        }
    ],
    "sg:phone":"+1 709 695 3421",
    "sg:postcode":"A0N 1K0",
    "sg:province":"NL",
    "sg:tags":[
        "club"
    ],
    "wof:name":"Lions Club",
    "wof:placetype":"venue"
},
  "geometry": {"coordinates":[-59.1755104065,47.5833702087],"type":"Point"}
}