{
  "type": "Feature",
  "properties": {
    "addr:full":"93 Murray St Ottawa ON K1N 5M5",
    "addr:housenumber":"93",
    "addr:postcode":"k1n 5m5",
    "addr:street":"Murray St",
    "iso:country":"CA",
    "sg:address":"93 Murray St",
    "sg:city":"Ottawa",
    "sg:classifiers":[
        {
            "category":"Restaurant",
            "type":"Food & Drink"
        }
    ],
    "sg:phone":"+1 613 241 2999",
    "sg:postcode":"K1N 5M5",
    "sg:province":"ON",
    "sg:tags":[
        "shop",
        "coffee"
    ],
    "wof:name":"Black Cat Cafe",
    "wof:placetype":"venue"
},
  "geometry": {"coordinates":[-75.693291,45.429989],"type":"Point"}
}