{
  "type": "Feature",
  "properties": {
    "addr:full":"66 Charlton Ave W Hamilton ON L8P 2C1",
    "addr:housenumber":"66",
    "addr:postcode":"l8p 2c1",
    "addr:street":"Charlton Ave W",
    "iso:country":"CA",
    "sg:address":"66 Charlton Ave W",
    "sg:city":"Hamilton",
    "sg:classifiers":[
        {
            "category":"Health Services",
            "subcategory":"Doctor",
            "type":"Services"
        }
    ],
    "sg:phone":"+1 905 521 0061",
    "sg:postcode":"L8P 2C1",
    "sg:province":"ON",
    "sg:tags":[
        "physician",
        "surgeon"
    ],
    "wof:name":"Reddy, K MD",
    "wof:placetype":"venue"
},
  "geometry": {"coordinates":[-79.8749923706,43.2505683899],"type":"Point"}
}