{
  "type": "Feature",
  "properties": {
    "addr:full":"1645 Rue Des Cascades O Saint-Hyacinthe QC J2S 3H9",
    "addr:housenumber":"1645",
    "addr:postcode":"j2s 3h9",
    "addr:street":"Rue Des Cascades O",
    "iso:country":"CA",
    "sg:address":"1645 Rue Des Cascades O",
    "sg:city":"Saint-Hyacinthe",
    "sg:classifiers":[
        {
            "category":"Shopping",
            "subcategory":"Clothing, Apparel, & Fashions",
            "type":"Retail Goods"
        }
    ],
    "sg:phone":"+1 450 773 7002",
    "sg:postcode":"J2S 3H9",
    "sg:province":"QC",
    "sg:tags":[
        "item",
        "boutique"
    ],
    "wof:name":"Strauss Enr",
    "wof:placetype":"venue"
},
  "geometry": {"coordinates":[-72.94615899999999,45.624142],"type":"Point"}
}