{
  "type": "Feature",
  "properties": {
    "addr:full":"2605 15th Ave E Prince Albert SK S6V 6H4",
    "addr:housenumber":"2605",
    "addr:postcode":"s6v 6h4",
    "addr:street":"15Th Ave E",
    "iso:country":"CA",
    "sg:address":"2605 15th Ave E",
    "sg:city":"Prince Albert",
    "sg:classifiers":[
        {
            "category":"Freight",
            "type":"Transportation"
        }
    ],
    "sg:phone":"+1 306 764 3857",
    "sg:postcode":"S6V 6H4",
    "sg:province":"SK",
    "sg:tags":[
        "delivery",
        "mover"
    ],
    "wof:name":"Delorme's Delivery & Moving",
    "wof:placetype":"venue"
},
  "geometry": {"coordinates":[-105.711403,53.189877],"type":"Point"}
}