{
  "type": "Feature",
  "properties": {
    "addr:full":"552 Rue Principale O Saint-Anaclet QC G0K 1H0",
    "addr:housenumber":"552",
    "addr:postcode":"g0k 1h0",
    "addr:street":"Rue Principale O Saint-Anaclet",
    "iso:country":"CA",
    "sg:address":"552 Rue Principale O",
    "sg:city":"Saint-Anaclet",
    "sg:classifiers":[
        {
            "category":"Manufacturing",
            "subcategory":"Metals",
            "type":"Manufacturing & Wholesale Goods"
        }
    ],
    "sg:phone":"+1 418 723 8885",
    "sg:postcode":"G0K 1H0",
    "sg:province":"QC",
    "sg:tags":[
        "scrap",
        "product"
    ],
    "wof:name":"Metal Du Golfe St-Anaclet Inc",
    "wof:placetype":"venue"
},
  "geometry": {"coordinates":[-68.4098815918,48.4665107727],"type":"Point"}
}