{
  "type": "Feature",
  "properties": {
    "addr:full":"586 Main Ave W # 3 Sundre AB T0M 1X0",
    "addr:housenumber":"586",
    "addr:postcode":"t0m 1x0",
    "addr:street":"Main Ave W # 3",
    "iso:country":"CA",
    "sg:address":"586 Main Ave W # 3",
    "sg:city":"Sundre",
    "sg:classifiers":[
        {
            "category":"Mining & Drilling",
            "type":"Manufacturing & Wholesale Goods"
        }
    ],
    "sg:phone":"+1 403 638 1004",
    "sg:postcode":"T0M 1X0",
    "sg:province":"AB",
    "sg:tags":[
        "company",
        "oil"
    ],
    "wof:name":"Hunt Oil CO Canada",
    "wof:placetype":"venue"
},
  "geometry": {"coordinates":[-114.64810199999999,51.795673],"type":"Point"}
}