{
  "type": "Feature",
  "properties": {
    "iso:country":"CA",
    "sg:city":"Brighton",
    "sg:classifiers":[
        {
            "category":"Wholesale",
            "subcategory":"Durable Goods & Equipment",
            "type":"Manufacturing & Wholesale Goods"
        }
    ],
    "sg:phone":"+1 613 475 3200",
    "sg:postcode":"K0K 1H0",
    "sg:province":"ON",
    "sg:tags":[
        "representative",
        "manufacturer"
    ],
    "wof:name":"Duo Plast Mfg",
    "wof:placetype":"venue"
},
  "geometry": {"coordinates":[-77.7295303345,44.0344696045],"type":"Point"}
}