{
  "type": "Feature",
  "properties": {
    "iso:country":"CA",
    "sg:city":"Westport",
    "sg:classifiers":[
        {
            "category":"Professional",
            "subcategory":"Advertising",
            "type":"Services"
        }
    ],
    "sg:phone":"+1 613 273 8000",
    "sg:postcode":"K0G 1X0",
    "sg:province":"ON",
    "sg:tags":[
        "newspaper"
    ],
    "wof:name":"Review Mirror",
    "wof:placetype":"venue"
},
  "geometry": {"coordinates":[-76.39641571040001,44.6786499023],"type":"Point"}
}