{
  "type": "Feature",
  "properties": {
    "addr:full":"Edmonton AB T5S 1R5",
    "addr:postcode":"t5s 1r5",
    "iso:country":"CA",
    "sg:city":"Edmonton",
    "sg:classifiers":[
        {
            "category":"Professional",
            "subcategory":"Engineering",
            "type":"Services"
        }
    ],
    "sg:phone":"+1 780 484 1095",
    "sg:postcode":"T5S 1R5",
    "sg:province":"AB",
    "sg:tags":[
        "engineer"
    ],
    "wof:name":"Jacobsen Hage Engineering",
    "wof:placetype":"venue"
},
  "geometry": {"coordinates":[-113.627174,53.547733],"type":"Point"}
}