{
  "type": "Feature",
  "properties": {
    "addr:full":"Saint-Come-Liniere QC G0M 1J0",
    "addr:postcode":"g0m 1j0",
    "iso:country":"CA",
    "sg:city":"Saint-Come-Liniere",
    "sg:classifiers":[
        {
            "category":"Government",
            "subcategory":"Office",
            "type":"Public Place"
        }
    ],
    "sg:phone":"+1 418 685 2126",
    "sg:postcode":"G0M 1J0",
    "sg:province":"QC",
    "sg:tags":[
        "village"
    ],
    "wof:name":"Ste-Come-Liniere Garage",
    "wof:placetype":"venue"
},
  "geometry": {"coordinates":[-70.52057647709999,46.0611000061],"type":"Point"}
}