{
  "type": "Feature",
  "properties": {
    "iso:country":"CA",
    "sg:address":"92 King St S",
    "sg:city":"Waterloo",
    "sg:classifiers":[
        {
            "category":"Restaurant",
            "type":"Food & Drink"
        }
    ],
    "sg:phone":"+1 519 725 3440",
    "sg:postcode":"N2J 1P5",
    "sg:province":"ON",
    "wof:name":"Janet Lynns Bistro",
    "wof:placetype":"venue"
},
  "geometry": {"coordinates":[-80.521591,43.463081],"type":"Point"}
}