{
  "type": "Feature",
  "properties": {
    "addr:full":"Toronto ON M4W 3B8",
    "addr:postcode":"m4w 3b8",
    "iso:country":"CA",
    "sg:city":"Toronto",
    "sg:classifiers":[
        {
            "category":"Manufacturing",
            "subcategory":"Metals",
            "type":"Manufacturing & Wholesale Goods"
        }
    ],
    "sg:phone":"+1 416 975 8251",
    "sg:postcode":"M4W 3B8",
    "sg:province":"ON",
    "sg:tags":[
        "foundry"
    ],
    "wof:name":"Norcast Corp",
    "wof:placetype":"venue"
},
  "geometry": {"coordinates":[-79.389343,43.669792],"type":"Point"}
}