{
  "type": "Feature",
  "properties": {
    "addr:full":"PO Box 110 Keg River AB T0H 2G0",
    "addr:housenumber":"po;110",
    "addr:postcode":"t0h 2g0",
    "addr:street":"Box",
    "iso:country":"CA",
    "sg:address":"PO Box 110",
    "sg:city":"Keg River",
    "sg:classifiers":[
        {
            "category":"Wholesale",
            "subcategory":"Construction Materials",
            "type":"Manufacturing & Wholesale Goods"
        }
    ],
    "sg:phone":"+1 780 981 2474",
    "sg:postcode":"T0H 2G0",
    "sg:province":"AB",
    "sg:tags":[
        "sand",
        "gravel"
    ],
    "wof:name":"Befus Gravel Supply",
    "wof:placetype":"venue"
},
  "geometry": {"coordinates":[-117.89949799999999,57.788273],"type":"Point"}
}