{
  "type": "Feature",
  "properties": {
    "iso:country":"CA",
    "sg:city":"Surrey",
    "sg:classifiers":[
        {
            "category":"Wholesale",
            "subcategory":"Electrical",
            "type":"Manufacturing & Wholesale Goods"
        }
    ],
    "sg:phone":"+1 604 594 1122",
    "sg:postcode":"V3W 2V3",
    "sg:province":"BC",
    "sg:tags":[
        "lighting",
        "fixture"
    ],
    "wof:name":"G Bull & Assoc",
    "wof:placetype":"venue"
},
  "geometry": {"coordinates":[-122.86792755099999,49.1410598755],"type":"Point"}
}