{
  "type": "Feature",
  "properties": {
    "addr:full":"62 Steacie Dr Kanata ON K2K 2A9",
    "addr:housenumber":"62",
    "addr:postcode":"k2k 2a9",
    "addr:street":"Steacie Dr",
    "iso:country":"CA",
    "sg:address":"62 Steacie Dr",
    "sg:city":"Kanata",
    "sg:classifiers":[
        {
            "category":"Professional",
            "subcategory":"Research",
            "type":"Services"
        }
    ],
    "sg:phone":"+1 613 591 0336",
    "sg:postcode":"K2K 2A9",
    "sg:province":"ON",
    "sg:tags":[
        "development",
        "electronic"
    ],
    "wof:name":"Optotek Limited",
    "wof:placetype":"venue"
},
  "geometry": {"coordinates":[-75.91274300000001,45.3358],"type":"Point"}
}