{
  "type": "Feature",
  "properties": {
    "addr:full":"2610 Airport Rd Regina SK S4W 1A3",
    "addr:housenumber":"2610",
    "addr:postcode":"s4w 1a3",
    "addr:street":"Airport Rd",
    "iso:country":"CA",
    "sg:address":"2610 Airport Rd",
    "sg:city":"Regina",
    "sg:classifiers":[
        {
            "category":"Airport",
            "type":"Transportation"
        }
    ],
    "sg:phone":"+1 306 352 8200",
    "sg:postcode":"S4W 1A3",
    "sg:province":"SK",
    "sg:tags":[
        "aircraft",
        "maintenance"
    ],
    "wof:name":"Sos Avionics",
    "wof:placetype":"venue"
},
  "geometry": {"coordinates":[-104.59517700000001,50.448013],"type":"Point"}
}