{
  "type": "Feature",
  "properties": {
    "addr:full":"Saint-Germain-DE-Grantham QC J0C 1K0",
    "addr:postcode":"j0c 1k0",
    "iso:country":"CA",
    "sg:city":"Saint-Germain-DE-Grantham",
    "sg:classifiers":[
        {
            "category":"Building & Trades",
            "subcategory":"Construction",
            "type":"Services"
        }
    ],
    "sg:phone":"+1 819 395 4379",
    "sg:postcode":"J0C 1K0",
    "sg:province":"QC",
    "sg:tags":[
        "home",
        "builder",
        "general",
        "contractor"
    ],
    "wof:name":"Habitations Mon Toit Inc",
    "wof:placetype":"venue"
},
  "geometry": {"coordinates":[-72.56852000000001,45.847286],"type":"Point"}
}