{
  "type": "Feature",
  "properties": {
    "addr:full":"641 Yonge St Toronto ON M4Y 1Z9",
    "addr:housenumber":"641",
    "addr:postcode":"m4y 1z9",
    "addr:street":"Yonge St",
    "iso:country":"CA",
    "sg:address":"641 Yonge St",
    "sg:city":"Toronto",
    "sg:classifiers":[
        {
            "category":"Shopping",
            "type":"Retail Goods"
        }
    ],
    "sg:phone":"+1 416 924 8731",
    "sg:postcode":"M4Y 1Z9",
    "sg:province":"ON",
    "sg:tags":[
        "art",
        "gallery",
        "dealer"
    ],
    "wof:name":"Roberts Gallery",
    "wof:placetype":"venue"
},
  "geometry": {"coordinates":[-79.385559,43.667717],"type":"Point"}
}