{
  "type": "Feature",
  "properties": {
    "addr:full":"1480 Lands End Rd North Saanich BC V8L 5K1",
    "addr:housenumber":"1480",
    "addr:postcode":"v8l 5k1",
    "addr:street":"Lands End Rd",
    "iso:country":"CA",
    "sg:address":"1480 Lands End Rd",
    "sg:city":"North Saanich",
    "sg:classifiers":[
        {
            "category":"Health Services",
            "subcategory":"Health Practitioner",
            "type":"Services"
        }
    ],
    "sg:phone":"+1 250 656 5611",
    "sg:postcode":"V8L 5K1",
    "sg:province":"BC",
    "sg:tags":[
        "psychologist",
        "counselor",
        "marriage",
        "family"
    ],
    "wof:name":"Walter & Humphrey Counselling",
    "wof:placetype":"venue"
},
  "geometry": {"coordinates":[-123.43814086899999,48.6977233887],"type":"Point"}
}