{
  "type": "Feature",
  "properties": {
    "addr:full":"127 Rue Sainte-Anne Sainte-Anne-DE-Bellevue QC H9X 1M3",
    "addr:housenumber":"127",
    "addr:postcode":"h9x 1m3",
    "addr:street":"Rue Sainte-Anne",
    "iso:country":"CA",
    "sg:address":"127 Rue Sainte-Anne",
    "sg:city":"Sainte-Anne-DE-Bellevue",
    "sg:classifiers":[
        {
            "category":"Autos & Motor Vehicles",
            "subcategory":"Boat Sales",
            "type":"Retail Goods"
        }
    ],
    "sg:phone":"+1 514 457 9131",
    "sg:postcode":"H9X 1M3",
    "sg:province":"QC",
    "sg:tags":[
        "sporting",
        "dealer"
    ],
    "wof:name":"Norway Nordic Inc",
    "wof:placetype":"venue"
},
  "geometry": {"coordinates":[-73.95246899999999,45.403725],"type":"Point"}
}