{
  "type": "Feature",
  "properties": {
    "addr:full":"Sabaskong Bay Rd Nestor Falls ON P0X 1K0",
    "addr:postcode":"p0x 1k0",
    "addr:street":"Bay Rd",
    "iso:country":"CA",
    "sg:address":"Sabaskong Bay Rd",
    "sg:city":"Nestor Falls",
    "sg:classifiers":[
        {
            "category":"Building & Trades",
            "subcategory":"Electrical",
            "type":"Services"
        }
    ],
    "sg:phone":"+1 807 484 2194",
    "sg:postcode":"P0X 1K0",
    "sg:province":"ON",
    "sg:tags":[
        "electric",
        "contractor"
    ],
    "wof:name":"Kropelin Electric Ltd",
    "wof:placetype":"venue"
},
  "geometry": {"coordinates":[-93.946129,49.196758],"type":"Point"}
}