{
  "type": "Feature",
  "properties": {
    "addr:full":"9 Tangiers Rd North York ON M3J 2B1",
    "addr:housenumber":"9",
    "addr:postcode":"m3j 2b1",
    "addr:street":"Tangiers Rd",
    "iso:country":"CA",
    "sg:address":"9 Tangiers Rd",
    "sg:city":"North York",
    "sg:classifiers":[
        {
            "category":"Autos & Motor Vehicles",
            "subcategory":"Auto Supplies",
            "type":"Retail Goods"
        }
    ],
    "sg:phone":"+1 416 635 9113",
    "sg:postcode":"M3J 2B1",
    "sg:province":"ON",
    "sg:tags":[
        "tire"
    ],
    "wof:name":"Phil's Tire Svc",
    "wof:placetype":"venue"
},
  "geometry": {"coordinates":[-79.487396,43.761463],"type":"Point"}
}