{
  "type": "Feature",
  "properties": {
    "addr:full":"Abbotsford BC V2T 2Y1",
    "addr:postcode":"v2t 2y1",
    "iso:country":"CA",
    "sg:city":"Abbotsford",
    "sg:classifiers":[
        {
            "category":"Food & Beverages",
            "subcategory":"Meat & Fish",
            "type":"Retail Goods"
        }
    ],
    "sg:phone":"+1 604 556 7708",
    "sg:postcode":"V2T 2Y1",
    "sg:province":"BC",
    "wof:name":"Desi Meat & Masala Chckn Soup",
    "wof:placetype":"venue"
},
  "geometry": {"coordinates":[-122.33725699999999,49.04668],"type":"Point"}
}