{
  "type": "Feature",
  "properties": {
    "addr:full":"5495 Spring Garden Rd Halifax NS B3J 1G2",
    "addr:housenumber":"5495",
    "addr:postcode":"ns b3j 1g2",
    "addr:street":"Spring Garden Rd",
    "iso:country":"CA",
    "sg:address":"5495 Spring Garden Rd",
    "sg:city":"Halifax",
    "sg:classifiers":[
        {
            "category":"Shopping",
            "subcategory":"Clothing, Apparel, & Fashions",
            "type":"Retail Goods"
        }
    ],
    "sg:phone":"+1 902 429 7625",
    "sg:postcode":"B3J 1G2",
    "sg:province":"NS",
    "sg:tags":[
        "accessory"
    ],
    "wof:name":"Sock It To Ya",
    "wof:placetype":"venue"
},
  "geometry": {"coordinates":[-63.576714,44.643238],"type":"Point"}
}