{
  "type": "Feature",
  "properties": {
    "addr:full":"Gormley ON L0H 1G0",
    "addr:postcode":"l0h 1g0",
    "iso:country":"CA",
    "sg:city":"Gormley",
    "sg:classifiers":[
        {
            "category":"Manufacturing",
            "subcategory":"Rubber & Plastics",
            "type":"Manufacturing & Wholesale Goods"
        }
    ],
    "sg:phone":"+1 905 888 0715",
    "sg:postcode":"L0H 1G0",
    "sg:province":"ON",
    "sg:tags":[
        "die",
        "tool",
        "maker"
    ],
    "wof:name":"Whyte Machine & Tool",
    "wof:placetype":"venue"
},
  "geometry": {"coordinates":[-79.37776947019999,43.9446868896],"type":"Point"}
}