{
  "type": "Feature",
  "properties": {
    "addr:full":"737 Arlington Park Pl Kingston ON K7M 8M8",
    "addr:housenumber":"737",
    "addr:postcode":"k7m 8m8",
    "addr:street":"Arlington Park Pl",
    "iso:country":"CA",
    "sg:address":"737 Arlington Park Pl",
    "sg:city":"Kingston",
    "sg:classifiers":[
        {
            "category":"Health Services",
            "subcategory":"Clinic",
            "type":"Services"
        }
    ],
    "sg:phone":"+1 613 634 0130",
    "sg:postcode":"K7M 8M8",
    "sg:province":"ON",
    "sg:tags":[
        "home"
    ],
    "wof:name":"Von Clinic",
    "wof:placetype":"venue"
},
  "geometry": {"coordinates":[-76.571541,44.249001],"type":"Point"}
}