{
  "type": "Feature",
  "properties": {
    "iso:country":"CA",
    "sg:address":"243 Main St",
    "sg:city":"Unionville",
    "sg:classifiers":[
        {
            "category":"Organizations",
            "subcategory":"Religious Organization",
            "type":"Services"
        }
    ],
    "sg:phone":"+1 905 479 0942",
    "sg:postcode":"L3R 2H3",
    "sg:province":"ON",
    "sg:tags":[
        "church"
    ],
    "wof:name":"Unionville Baptist Church",
    "wof:placetype":"venue"
},
  "geometry": {"coordinates":[-79.31196594239999,43.8712158203],"type":"Point"}
}