{
  "type": "Feature",
  "properties": {
    "iso:country":"CA",
    "sg:address":"2494 Boul Henri-Bourassa E",
    "sg:city":"Montreal",
    "sg:classifiers":[
        {
            "category":"Real Estate",
            "subcategory":"Real Estate Agent",
            "type":"Services"
        }
    ],
    "sg:phone":"+1 514 384 3400",
    "sg:postcode":"H2B 1T9",
    "sg:province":"QC",
    "wof:name":"Enna Courtiers Ltee",
    "wof:placetype":"venue"
},
  "geometry": {"coordinates":[-73.6533508301,45.5777931213],"type":"Point"}
}