{
  "type": "Feature",
  "properties": {
    "addr:full":"375 University Ave Charlottetown PE C1A 4N4",
    "addr:housenumber":"375",
    "addr:postcode":"c1a 4n4",
    "addr:street":"University Ave",
    "iso:country":"CA",
    "sg:address":"375 University Ave",
    "sg:city":"Charlottetown",
    "sg:classifiers":[
        {
            "category":"Professional",
            "subcategory":"Business Services",
            "type":"Services"
        }
    ],
    "sg:phone":"+1 902 566 3337",
    "sg:postcode":"C1A 4N4",
    "sg:province":"PE",
    "sg:tags":[
        "screen",
        "printing",
        "embroidery"
    ],
    "wof:name":"East Coast Cresting",
    "wof:placetype":"venue"
},
  "geometry": {"coordinates":[-63.134021759,46.2440948486],"type":"Point"}
}