{
  "type": "Feature",
  "properties": {
    "iso:country":"CA",
    "sg:address":"5301 Airport Rd S",
    "sg:city":"Richmond",
    "sg:classifiers":[
        {
            "category":"Airport",
            "type":"Transportation"
        }
    ],
    "sg:phone":"+1 604 279 9579",
    "sg:postcode":"V7B 1B5",
    "sg:province":"BC",
    "sg:tags":[
        "aircraft",
        "maintenance"
    ],
    "wof:name":"Pacific Aircraft Maintenance",
    "wof:placetype":"venue"
},
  "geometry": {"coordinates":[-123.166160584,49.1802520752],"type":"Point"}
}