{
  "type": "Feature",
  "properties": {
    "addr:full":"3520 Rue Saint-Patrick Montreal QC H4E 1A2",
    "addr:housenumber":"3520",
    "addr:postcode":"h4e 1a2",
    "addr:street":"Rue Saint-Patrick",
    "iso:country":"CA",
    "sg:address":"3520 Rue Saint-Patrick",
    "sg:city":"Montreal",
    "sg:classifiers":[
        {
            "category":"Building & Trades",
            "subcategory":"Landscaping Services",
            "type":"Services"
        }
    ],
    "sg:phone":"+1 514 723 6659",
    "sg:postcode":"H4E 1A2",
    "sg:province":"QC",
    "sg:tags":[
        "landscape",
        "contractor"
    ],
    "wof:name":"Terrapro Construction Inc",
    "wof:placetype":"venue"
},
  "geometry": {"coordinates":[-73.5790176392,45.4724349976],"type":"Point"}
}