{
  "type": "Feature",
  "properties": {
    "iso:country":"CA",
    "sg:address":"1619 Rue King O",
    "sg:city":"Sherbrooke",
    "sg:classifiers":[
        {
            "category":"Restaurant",
            "type":"Food & Drink"
        }
    ],
    "sg:phone":"+1 819 569 2881",
    "sg:postcode":"J1J 2C7",
    "sg:province":"QC",
    "wof:name":"Cafe King",
    "wof:placetype":"venue"
},
  "geometry": {"coordinates":[-71.9151916504,45.3987846375],"type":"Point"}
}