{
  "type": "Feature",
  "properties": {
    "iso:country":"CA",
    "sg:address":"204 Boul Labelle # 225",
    "sg:city":"Sainte-Therese",
    "sg:classifiers":[
        {
            "category":"Professional",
            "subcategory":"Accounting & Tax Preparation",
            "type":"Services"
        }
    ],
    "sg:phone":"+1 450 430 8002",
    "sg:postcode":"J7E 2X7",
    "sg:province":"QC",
    "sg:tags":[
        "accountant",
        "management"
    ],
    "wof:name":"Comptable Guindon Chabot Inc",
    "wof:placetype":"venue"
},
  "geometry": {"coordinates":[-73.8342666626,45.6438026428],"type":"Point"}
}