{
  "type": "Feature",
  "properties": {
    "addr:full":"PO Box 256 Gods Lake Narrows MB R0B 0M0",
    "addr:housenumber":"po",
    "addr:postcode":"r0b 0m0",
    "addr:street":"Box 256 Gods Lake",
    "iso:country":"CA",
    "sg:address":"PO Box 256",
    "sg:city":"Gods Lake Narrows",
    "sg:classifiers":[
        {
            "category":"Government",
            "subcategory":"Office",
            "type":"Public Place"
        }
    ],
    "sg:phone":"+1 204 335 2024",
    "sg:postcode":"R0B 0M0",
    "sg:province":"MB",
    "wof:name":"Manitoba Northern Airports",
    "wof:placetype":"venue"
},
  "geometry": {"coordinates":[-94.52273599999999,54.546169],"type":"Point"}
}