{
  "type": "Feature",
  "properties": {
    "addr:full":"10572 Clairmont Subdiv Fort St John BC V1J 4M7",
    "addr:housenumber":"10572",
    "addr:postcode":"v1j 4m7",
    "addr:street":"Clairmont Subdiv",
    "iso:country":"CA",
    "sg:address":"10572 Clairmont Subdiv",
    "sg:city":"Fort St John",
    "sg:classifiers":[
        {
            "category":"Building & Trades",
            "subcategory":"Equipment Rental",
            "type":"Services"
        }
    ],
    "sg:phone":"+1 250 787 8474",
    "sg:postcode":"V1J 4M7",
    "sg:province":"BC",
    "sg:tags":[
        "oil",
        "well",
        "supply"
    ],
    "wof:name":"Raven Oilfield Rentals",
    "wof:placetype":"venue"
},
  "geometry": {"coordinates":[-120.847458,56.252464],"type":"Point"}
}