{
  "type": "Feature",
  "properties": {
    "addr:full":"North Bay ON P1B 7K8",
    "addr:postcode":"p1b 7k8",
    "iso:country":"CA",
    "sg:city":"North Bay",
    "sg:classifiers":[
        {
            "category":"Professional",
            "subcategory":"Employment Agencies",
            "type":"Services"
        }
    ],
    "sg:phone":"+1 705 474 5767",
    "sg:postcode":"P1B 7K8",
    "sg:province":"ON",
    "sg:tags":[
        "opportunity"
    ],
    "wof:name":"Cts Employment Resource Ctr",
    "wof:placetype":"venue"
},
  "geometry": {"coordinates":[-79.46574401860001,46.3315734863],"type":"Point"}
}