{
  "type": "Feature",
  "properties": {
    "addr:full":"4 Rue Querry Saint-Quentin NB E8A 1Z1",
    "addr:housenumber":"4",
    "addr:postcode":"e8a 1z1",
    "addr:street":"Rue Querry",
    "iso:country":"CA",
    "sg:address":"4 Rue Querry",
    "sg:city":"Saint-Quentin",
    "sg:classifiers":[
        {
            "category":"Personal",
            "subcategory":"Beauty Salon",
            "type":"Services"
        }
    ],
    "sg:phone":"+1 506 235 2669",
    "sg:postcode":"E8A 1Z1",
    "sg:province":"NB",
    "wof:name":"Salon DE Coiffure Martine",
    "wof:placetype":"venue"
},
  "geometry": {"coordinates":[-67.3914031982,47.5202713013],"type":"Point"}
}