{
  "type": "Feature",
  "properties": {
    "iso:country":"CA",
    "sg:address":"1275 Rue Blanchette",
    "sg:city":"Saint-Hyacinthe",
    "sg:classifiers":[
        {
            "category":"Real Estate",
            "subcategory":"Real Estate Agent",
            "type":"Services"
        }
    ],
    "sg:phone":"+1 450 774 8185",
    "sg:postcode":"J2S 1J9",
    "sg:province":"QC",
    "wof:name":"Yvan Larivee Inc",
    "wof:placetype":"venue"
},
  "geometry": {"coordinates":[-72.958229,45.633659],"type":"Point"}
}