{
  "type": "Feature",
  "properties": {
    "addr:full":"84 Dover St #1 Chatham ON N7L 1T1",
    "addr:housenumber":"84",
    "addr:postcode":"n7l 1t1",
    "addr:street":"Dover St # 1",
    "iso:country":"CA",
    "sg:address":"84 Dover St #1",
    "sg:city":"Chatham",
    "sg:classifiers":[
        {
            "category":"Professional",
            "subcategory":"Lawyer & Legal Services",
            "type":"Services"
        }
    ],
    "sg:phone":"+1 519 352 1360",
    "sg:postcode":"N7L 1T1",
    "sg:province":"ON",
    "sg:tags":[
        "notary",
        "attorney"
    ],
    "wof:name":"Cormiskey, J Bernard",
    "wof:placetype":"venue"
},
  "geometry": {"coordinates":[-82.186859,42.407749],"type":"Point"}
}