{
  "type": "Feature",
  "properties": {
    "addr:full":"2072 Bradner Rd Abbotsford BC V4X 1C3",
    "addr:housenumber":"2072",
    "addr:postcode":"v4x 1c3",
    "addr:street":"Bradner Rd",
    "iso:country":"CA",
    "sg:address":"2072 Bradner Rd",
    "sg:city":"Abbotsford",
    "sg:classifiers":[
        {
            "category":"Home & Garden",
            "subcategory":"Building Materials",
            "type":"Retail Goods"
        }
    ],
    "sg:phone":"+1 604 856 9646",
    "sg:postcode":"V4X 1C3",
    "sg:province":"BC",
    "wof:name":"Southwest Forest Products Ltd",
    "wof:placetype":"venue"
},
  "geometry": {"coordinates":[-122.426399231,49.0392570496],"type":"Point"}
}