{
  "type": "Feature",
  "properties": {
    "addr:full":"4721 Rue DE Verdun Verdun QC H4G 1M9",
    "addr:housenumber":"4721",
    "addr:postcode":"h4g 1m9",
    "addr:street":"Rue De Verdun",
    "iso:country":"CA",
    "sg:address":"4721 Rue DE Verdun",
    "sg:city":"Verdun",
    "sg:classifiers":[
        {
            "category":"Personal",
            "subcategory":"Beauty Salon",
            "type":"Services"
        }
    ],
    "sg:phone":"+1 514 769 5241",
    "sg:postcode":"H4G 1M9",
    "sg:province":"QC",
    "wof:name":"Salon DE Beaute Opera Lyne",
    "wof:placetype":"venue"
},
  "geometry": {"coordinates":[-73.572029,45.457886],"type":"Point"}
}