{
  "type": "Feature",
  "properties": {
    "addr:full":"420 Ecclestone Dr Bracebridge ON P1L 1R1",
    "addr:housenumber":"420",
    "addr:postcode":"p1l 1r1",
    "addr:street":"Ecclestone Dr",
    "iso:country":"CA",
    "sg:address":"420 Ecclestone Dr",
    "sg:city":"Bracebridge",
    "sg:classifiers":[
        {
            "category":"Autos & Motor Vehicles",
            "subcategory":"Automobile Sales",
            "type":"Retail Goods"
        }
    ],
    "sg:phone":"+1 705 645 8731",
    "sg:postcode":"P1L 1R1",
    "sg:province":"ON",
    "sg:tags":[
        "car",
        "dealer"
    ],
    "wof:name":"Cavalcade Ford Lincoln Sales",
    "wof:placetype":"venue"
},
  "geometry": {"coordinates":[-79.314682,45.016869],"type":"Point"}
}