{
  "type": "Feature",
  "properties": {
    "addr:full":"309 Exeter Rd # 15 London ON N6L 1C1",
    "addr:housenumber":"309",
    "addr:postcode":"n6l 1c1",
    "addr:street":"Exeter Rd # 15",
    "iso:country":"CA",
    "sg:address":"309 Exeter Rd # 15",
    "sg:city":"London",
    "sg:classifiers":[
        {
            "category":"Autos & Motor Vehicles",
            "subcategory":"Auto Supplies",
            "type":"Retail Goods"
        }
    ],
    "sg:phone":"+1 519 652 4041",
    "sg:postcode":"N6L 1C1",
    "sg:province":"ON",
    "sg:tags":[
        "automobile",
        "parts",
        "racing",
        "car",
        "equipment"
    ],
    "wof:name":"Transcan Auto Parts Ltd",
    "wof:placetype":"venue"
},
  "geometry": {"coordinates":[-81.250648,42.922844],"type":"Point"}
}