{
  "type": "Feature",
  "properties": {
    "iso:country":"CA",
    "sg:address":"2477 Lake Shore Blvd W",
    "sg:city":"Etobicoke",
    "sg:classifiers":[
        {
            "category":"Shopping",
            "subcategory":"Music",
            "type":"Retail Goods"
        }
    ],
    "sg:phone":"+1 416 251 2728",
    "sg:postcode":"M8V 1C5",
    "sg:province":"ON",
    "sg:tags":[
        "compact",
        "record",
        "disc",
        "tape"
    ],
    "wof:name":"Mimico Books",
    "wof:placetype":"venue"
},
  "geometry": {"coordinates":[-79.48950958250001,43.61302948],"type":"Point"}
}