{
  "type": "Feature",
  "properties": {
    "addr:full":"85 Rue Principale N Windsor QC J1S 2C5",
    "addr:housenumber":"85",
    "addr:postcode":"j1s 2c5",
    "addr:street":"Rue Principale N",
    "iso:country":"CA",
    "sg:address":"85 Rue Principale N",
    "sg:city":"Windsor",
    "sg:classifiers":[
        {
            "category":"Banks & Credit Unions",
            "subcategory":"Bank",
            "type":"Services"
        }
    ],
    "sg:phone":"+1 819 845 2726",
    "sg:postcode":"J1S 2C5",
    "sg:province":"QC",
    "wof:name":"Cibc",
    "wof:placetype":"venue"
},
  "geometry": {"coordinates":[-72.00715599999999,45.569866],"type":"Point"}
}