{
  "type": "Feature",
  "properties": {
    "addr:full":"Saint-Cyprien QC G0L 2P0",
    "addr:postcode":"g0l 2p0",
    "iso:country":"CA",
    "sg:city":"Saint-Cyprien",
    "sg:classifiers":[
        {
            "category":"Travel",
            "subcategory":"Hotels & Motels",
            "type":"Entertainment"
        }
    ],
    "sg:phone":"+1 418 963 2272",
    "sg:postcode":"G0L 2P0",
    "sg:province":"QC",
    "wof:name":"Auberge LA Clef Des Champs",
    "wof:placetype":"venue"
},
  "geometry": {"coordinates":[-69.0217971802,47.8974952698],"type":"Point"}
}