{
  "type": "Feature",
  "properties": {
    "addr:full":"316 Souris St Yellow Grass SK S0G 5J0",
    "addr:housenumber":"316",
    "addr:postcode":"s0g 5j0",
    "addr:street":"Souris St",
    "iso:country":"CA",
    "sg:address":"316 Souris St",
    "sg:city":"Yellow Grass",
    "sg:classifiers":[
        {
            "category":"Freight",
            "type":"Transportation"
        }
    ],
    "sg:phone":"+1 306 465 2421",
    "sg:postcode":"S0G 5J0",
    "sg:province":"SK",
    "sg:tags":[
        "trucking"
    ],
    "wof:name":"Caprice Carriers Inc",
    "wof:placetype":"venue"
},
  "geometry": {"coordinates":[-104.16069,49.805389],"type":"Point"}
}