{
  "type": "Feature",
  "properties": {
    "addr:full":"5250 Orbitor Dr Mississauga ON L4W 5G7",
    "addr:housenumber":"5250",
    "addr:postcode":"l4w 5g7",
    "addr:street":"Orbitor Dr",
    "iso:country":"CA",
    "sg:address":"5250 Orbitor Dr",
    "sg:city":"Mississauga",
    "sg:classifiers":[
        {
            "category":"Wholesale",
            "subcategory":"Electrical",
            "type":"Manufacturing & Wholesale Goods"
        }
    ],
    "sg:phone":"+1 905 629 9340",
    "sg:postcode":"L4W 5G7",
    "sg:province":"ON",
    "sg:tags":[
        "control"
    ],
    "wof:name":"Lakeside Process Controls Ltd",
    "wof:placetype":"venue"
},
  "geometry": {"coordinates":[-79.60652160639999,43.6600112915],"type":"Point"}
}