{
  "type": "Feature",
  "properties": {
    "iso:country":"CA",
    "sg:address":"88 Shoemaker St",
    "sg:city":"Kitchener",
    "sg:classifiers":[
        {
            "category":"Professional",
            "subcategory":"Employment Agencies",
            "type":"Services"
        }
    ],
    "sg:phone":"+1 519 576 3322",
    "sg:postcode":"N2E 3G4",
    "sg:province":"ON",
    "sg:tags":[
        "opportunity"
    ],
    "wof:name":"Ics",
    "wof:placetype":"venue"
},
  "geometry": {"coordinates":[-80.4709396362,43.4068527222],"type":"Point"}
}