{
  "type": "Feature",
  "properties": {
    "addr:full":"326 Mill St Regina SK S4P 3E1",
    "addr:housenumber":"326",
    "addr:postcode":"s4p 3e1",
    "addr:street":"Mill St",
    "iso:country":"CA",
    "sg:address":"326 Mill St",
    "sg:city":"Regina",
    "sg:classifiers":[
        {
            "category":"Freight",
            "type":"Transportation"
        }
    ],
    "sg:phone":"+1 306 721 3332",
    "sg:postcode":"S4P 3E1",
    "sg:province":"SK",
    "sg:tags":[
        "trucking"
    ],
    "wof:name":"Big Horn Transport Ltd",
    "wof:placetype":"venue"
},
  "geometry": {"coordinates":[-104.55130800000001,50.451881],"type":"Point"}
}