{
  "type": "Feature",
  "properties": {
    "addr:full":"1802 Pharmacy Ave Scarborough ON M1T 1H6",
    "addr:housenumber":"1802",
    "addr:postcode":"m1t 1h6",
    "addr:street":"Pharmacy Ave",
    "iso:country":"CA",
    "sg:address":"1802 Pharmacy Ave",
    "sg:city":"Scarborough",
    "sg:classifiers":[
        {
            "category":"Restaurant",
            "type":"Food & Drink"
        }
    ],
    "sg:phone":"+1 416 490 9688",
    "sg:postcode":"M1T 1H6",
    "sg:province":"ON",
    "wof:name":"Cafe Michi",
    "wof:placetype":"venue"
},
  "geometry": {"coordinates":[-79.31719200000001,43.775204],"type":"Point"}
}