{
  "type": "Feature",
  "properties": {
    "addr:full":"80 Lakewood Country Lane Lions Head ON N0H 1W0",
    "addr:housenumber":"80",
    "addr:postcode":"n0h 1w0",
    "addr:street":"Lakewood Country Lane",
    "iso:country":"CA",
    "sg:address":"80 Lakewood Country Lane",
    "sg:city":"Lions Head",
    "sg:classifiers":[
        {
            "category":"Building & Trades",
            "subcategory":"Construction",
            "type":"Services"
        }
    ],
    "sg:phone":"+1 519 793 3572",
    "sg:postcode":"N0H 1W0",
    "sg:province":"ON",
    "sg:tags":[
        "contractor"
    ],
    "wof:name":"Northernwood Builders Ltd",
    "wof:placetype":"venue"
},
  "geometry": {"coordinates":[-81.254204,44.98658],"type":"Point"}
}