{
  "type": "Feature",
  "properties": {
    "addr:full":"78 Rt 116 O Danville QC J0A 1A0",
    "addr:housenumber":"78",
    "addr:postcode":"j0a 1a0",
    "addr:street":"Rt 116 O",
    "iso:country":"CA",
    "sg:address":"78 Rt 116 O",
    "sg:city":"Danville",
    "sg:classifiers":[
        {
            "category":"Retail",
            "subcategory":"Auto Repair",
            "type":"Services"
        }
    ],
    "sg:phone":"+1 819 839 2065",
    "sg:postcode":"J0A 1A0",
    "sg:province":"QC",
    "sg:tags":[
        "repairing",
        "automobile",
        "radiator"
    ],
    "wof:name":"Radiateurs A Leroux & Fils Inc",
    "wof:placetype":"venue"
},
  "geometry": {"coordinates":[-72.023438,45.782902],"type":"Point"}
}