{
  "type": "Feature",
  "properties": {
    "addr:full":"Dolbeau-Mistassini QC G8L 4W4",
    "addr:postcode":"g8l 4w4",
    "iso:country":"CA",
    "sg:city":"Dolbeau-Mistassini",
    "sg:classifiers":[
        {
            "category":"Travel",
            "subcategory":"Hotels & Motels",
            "type":"Entertainment"
        }
    ],
    "sg:phone":"+1 418 276 8104",
    "sg:postcode":"G8L 4W4",
    "sg:province":"QC",
    "sg:tags":[
        "authorities",
        "housing",
        "accommodation"
    ],
    "wof:name":"Habitat Metis Du Nord",
    "wof:placetype":"venue"
},
  "geometry": {"coordinates":[-72.23155975340001,48.8819503784],"type":"Point"}
}