{
  "type": "Feature",
  "properties": {
    "addr:full":"13 Knollsbrook Dr Nepean ON K2J 1K7",
    "addr:housenumber":"13",
    "addr:postcode":"k2j 1k7",
    "addr:street":"Knollsbrook Dr",
    "iso:country":"CA",
    "sg:address":"13 Knollsbrook Dr",
    "sg:city":"Nepean",
    "sg:classifiers":[
        {
            "category":"Shopping",
            "type":"Retail Goods"
        }
    ],
    "sg:phone":"+1 613 825 9700",
    "sg:postcode":"K2J 1K7",
    "sg:province":"ON",
    "sg:tags":[
        "wedding",
        "advertising",
        "supply"
    ],
    "wof:name":"Ron Cogan Advertising & Mktng",
    "wof:placetype":"venue"
},
  "geometry": {"coordinates":[-75.751518,45.285442],"type":"Point"}
}