{
  "type": "Feature",
  "properties": {
    "addr:full":"50 Newkirk Rd Richmond Hill ON L4C 3G3",
    "addr:housenumber":"50",
    "addr:postcode":"l4c 3g3",
    "addr:street":"Newkirk Rd",
    "iso:country":"CA",
    "sg:address":"50 Newkirk Rd",
    "sg:city":"Richmond Hill",
    "sg:classifiers":[
        {
            "category":"Home & Garden",
            "subcategory":"Building Materials",
            "type":"Retail Goods"
        }
    ],
    "sg:phone":"+1 416 798 1112",
    "sg:postcode":"L4C 3G3",
    "sg:province":"ON",
    "sg:tags":[
        "mixed",
        "concrete"
    ],
    "wof:name":"Innocon Inc",
    "wof:placetype":"venue"
},
  "geometry": {"coordinates":[-79.42663574220001,43.8792076111],"type":"Point"}
}