{
  "type": "Feature",
  "properties": {
    "addr:full":"1303 Fellows Rd Ottawa ON K2C 2V8",
    "addr:housenumber":"1303",
    "addr:postcode":"k2c 2v8",
    "addr:street":"Fellows Rd",
    "iso:country":"CA",
    "sg:address":"1303 Fellows Rd",
    "sg:city":"Ottawa",
    "sg:classifiers":[
        {
            "category":"Education",
            "subcategory":"School",
            "type":"Public Place"
        }
    ],
    "sg:phone":"+1 613 820 0992",
    "sg:postcode":"K2C 2V8",
    "sg:province":"ON",
    "wof:name":"Ecole Secondaire Publique Chmp",
    "wof:placetype":"venue"
},
  "geometry": {"coordinates":[-75.76850899999999,45.352467],"type":"Point"}
}