{
  "type": "Feature",
  "properties": {
    "addr:full":"135 Wellington St Bowmanville ON L1C 1W2",
    "addr:housenumber":"135",
    "addr:postcode":"l1c 1w2",
    "addr:street":"Wellington St",
    "iso:country":"CA",
    "sg:address":"135 Wellington St",
    "sg:city":"Bowmanville",
    "sg:classifiers":[
        {
            "category":"Building & Trades",
            "subcategory":"Electrical",
            "type":"Services"
        }
    ],
    "sg:phone":"+1 905 623 8806",
    "sg:postcode":"L1C 1W2",
    "sg:province":"ON",
    "sg:tags":[
        "electric",
        "contractor"
    ],
    "wof:name":"Bankwell Electric Ltd",
    "wof:placetype":"venue"
},
  "geometry": {"coordinates":[-78.691101,43.914883],"type":"Point"}
}