{
  "type": "Feature",
  "properties": {
    "addr:full":"PO Box 190 Shell Lake SK S0J 2G0",
    "addr:housenumber":"po;190",
    "addr:postcode":"s0j 2g0",
    "addr:street":"Box",
    "iso:country":"CA",
    "sg:address":"PO Box 190",
    "sg:city":"Shell Lake",
    "sg:classifiers":[
        {
            "category":"Education",
            "subcategory":"School",
            "type":"Public Place"
        }
    ],
    "sg:phone":"+1 306 468 2100",
    "sg:postcode":"S0J 2G0",
    "sg:province":"SK",
    "wof:name":"Ahtahkakaoop Adult Education",
    "wof:placetype":"venue"
},
  "geometry": {"coordinates":[-107.065262,53.305565],"type":"Point"}
}