{
  "type": "Feature",
  "properties": {
    "addr:full":"5289 Tanner Ave Powell River BC V8A 5B4",
    "addr:housenumber":"5289",
    "addr:postcode":"v8a 5b4",
    "addr:street":"Tanner Ave Powell",
    "iso:country":"CA",
    "sg:address":"5289 Tanner Ave",
    "sg:city":"Powell River",
    "sg:classifiers":[
        {
            "category":"Building & Trades",
            "subcategory":"Construction",
            "type":"Services"
        }
    ],
    "sg:phone":"+1 604 483 9380",
    "sg:postcode":"V8A 5B4",
    "sg:province":"BC",
    "sg:tags":[
        "excavating",
        "contractor"
    ],
    "wof:name":"Gloslee Trucking Ltd",
    "wof:placetype":"venue"
},
  "geometry": {"coordinates":[-124.504081726,49.858341217],"type":"Point"}
}