{
  "type": "Feature",
  "properties": {
    "addr:full":"7310 Woodbine Ave Markham ON L3R 1A4",
    "addr:housenumber":"7310",
    "addr:postcode":"l3r 1a4",
    "addr:street":"Woodbine Ave",
    "iso:country":"CA",
    "sg:address":"7310 Woodbine Ave",
    "sg:city":"Markham",
    "sg:classifiers":[
        {
            "category":"Shopping",
            "type":"Retail Goods"
        }
    ],
    "sg:phone":"+1 905 474 2496",
    "sg:postcode":"L3R 1A4",
    "sg:province":"ON",
    "sg:tags":[
        "equipment",
        "telephone",
        "supply"
    ],
    "wof:name":"Telephone Depot",
    "wof:placetype":"venue"
},
  "geometry": {"coordinates":[-79.3508071899,43.8214263916],"type":"Point"}
}