{
  "type": "Feature",
  "properties": {
    "addr:full":"16 Mackey Pl St. John's NL A1G 1A1",
    "addr:housenumber":"16",
    "addr:postcode":"a1g 1a1",
    "addr:street":"Mackey Pl",
    "iso:country":"CA",
    "sg:address":"16 Mackey Pl",
    "sg:city":"St. John's",
    "sg:classifiers":[
        {
            "category":"Building & Trades",
            "subcategory":"Plumbing",
            "type":"Services"
        }
    ],
    "sg:phone":"+1 709 368 4182",
    "sg:postcode":"A1G 1A1",
    "sg:province":"NL",
    "sg:tags":[
        "mechanical",
        "contractor"
    ],
    "wof:name":"Canadian Process Svc",
    "wof:placetype":"venue"
},
  "geometry": {"coordinates":[-52.7410736084,47.5295295715],"type":"Point"}
}