{
  "type": "Feature",
  "properties": {
    "addr:full":"20 Rue Du Pont Amqui QC G5J 2P5",
    "addr:housenumber":"20",
    "addr:postcode":"g5j 2p5",
    "addr:street":"Rue Du Pont",
    "iso:country":"CA",
    "sg:address":"20 Rue Du Pont",
    "sg:city":"Amqui",
    "sg:classifiers":[
        {
            "category":"Shopping",
            "subcategory":"Pharmacy",
            "type":"Retail Goods"
        }
    ],
    "sg:phone":"+1 418 629 1414",
    "sg:postcode":"G5J 2P5",
    "sg:province":"QC",
    "wof:name":"Levesque, Aubert",
    "wof:placetype":"venue"
},
  "geometry": {"coordinates":[-67.431023,48.46513],"type":"Point"}
}