{
  "type": "Feature",
  "properties": {
    "addr:full":"15 Vansittart Ave Woodstock ON N4S 6E1",
    "addr:housenumber":"15",
    "addr:postcode":"n4s 6e1",
    "addr:street":"Vansittart Ave",
    "iso:country":"CA",
    "sg:address":"15 Vansittart Ave",
    "sg:city":"Woodstock",
    "sg:classifiers":[
        {
            "category":"Social Services",
            "subcategory":"Child Care",
            "type":"Services"
        }
    ],
    "sg:phone":"+1 519 539 4287",
    "sg:postcode":"N4S 6E1",
    "sg:province":"ON",
    "wof:name":"Friendship CO Op Play School",
    "wof:placetype":"venue"
},
  "geometry": {"coordinates":[-80.762283,43.129955],"type":"Point"}
}