{
  "type": "Feature",
  "properties": {
    "addr:full":"2661 Ch Acadie Cap-Pele NB E4N 1C2",
    "addr:postcode":"2661;e4n 1c2",
    "addr:street":"Ch Acadie",
    "iso:country":"CA",
    "sg:address":"2661 Ch Acadie",
    "sg:city":"Cap-Pele",
    "sg:classifiers":[
        {
            "category":"Personal",
            "subcategory":"Beauty Salon",
            "type":"Services"
        }
    ],
    "sg:phone":"+1 506 577 0111",
    "sg:postcode":"E4N 1C2",
    "sg:province":"NB",
    "wof:name":"Look",
    "wof:placetype":"venue"
},
  "geometry": {"coordinates":[-64.269859314,46.2149276733],"type":"Point"}
}