{
  "type": "Feature",
  "properties": {
    "addr:full":"134 Falcon St London ON N5W 4Z1",
    "addr:housenumber":"134",
    "addr:postcode":"n5w 4z1",
    "addr:street":"Falcon St",
    "iso:country":"CA",
    "sg:address":"134 Falcon St",
    "sg:city":"London",
    "sg:classifiers":[
        {
            "category":"Arts & Performance",
            "subcategory":"Theater",
            "type":"Entertainment"
        }
    ],
    "sg:phone":"+1 519 451 5185",
    "sg:postcode":"N5W 4Z1",
    "sg:province":"ON",
    "sg:tags":[
        "music"
    ],
    "wof:name":"Holy Spirit Marching Band",
    "wof:placetype":"venue"
},
  "geometry": {"coordinates":[-81.1754455566,42.9892425537],"type":"Point"}
}