{
  "type": "Feature",
  "properties": {
    "addr:full":"730 Rue Du Hibou-Blanc Sainte-Adele QC J8B 3J1",
    "addr:housenumber":"730",
    "addr:postcode":"j8b 3j1",
    "addr:street":"Rue Du Hibou-Blanc Sainte-Adele",
    "iso:country":"CA",
    "sg:address":"730 Rue Du Hibou-Blanc",
    "sg:city":"Sainte-Adele",
    "sg:classifiers":[
        {
            "category":"Building & Trades",
            "subcategory":"Construction",
            "type":"Services"
        }
    ],
    "sg:phone":"+1 450 229 4645",
    "sg:postcode":"J8B 3J1",
    "sg:province":"QC",
    "sg:tags":[
        "roofing",
        "contractor"
    ],
    "wof:name":"Ferblanterie P Dufort & Fils",
    "wof:placetype":"venue"
},
  "geometry": {"coordinates":[-74.2004394531,45.9712638855],"type":"Point"}
}