{
  "type": "Feature",
  "properties": {
    "addr:full":"209 Main St Whitehorse YT Y1A 2B2",
    "addr:housenumber":"209",
    "addr:postcode":"y1a 2b2",
    "addr:street":"Main St",
    "iso:country":"CA",
    "sg:address":"209 Main St",
    "sg:city":"Whitehorse",
    "sg:classifiers":[
        {
            "category":"Restaurant",
            "type":"Food & Drink"
        }
    ],
    "sg:phone":"+1 867 667 6888",
    "sg:postcode":"Y1A 2B2",
    "sg:province":"YT",
    "wof:name":"Pasta Palace",
    "wof:placetype":"venue"
},
  "geometry": {"coordinates":[-135.052536011,60.7195014954],"type":"Point"}
}