{
  "type": "Feature",
  "properties": {
    "addr:full":"68 Algoma St N Thunder Bay ON P7A 4Z3",
    "addr:housenumber":"68",
    "addr:postcode":"p7a 4z3",
    "addr:street":"Algoma St N",
    "iso:country":"CA",
    "sg:address":"68 Algoma St N",
    "sg:city":"Thunder Bay",
    "sg:classifiers":[
        {
            "category":"Health Services",
            "subcategory":"Doctor",
            "type":"Services"
        }
    ],
    "sg:phone":"+1 807 346 6468",
    "sg:postcode":"P7A 4Z3",
    "sg:province":"ON",
    "sg:tags":[
        "clinic"
    ],
    "wof:name":"Fresh Breath Clinic",
    "wof:placetype":"venue"
},
  "geometry": {"coordinates":[-89.2221832275,48.4390182495],"type":"Point"}
}