{
  "type": "Feature",
  "properties": {
    "addr:full":"425 King St W Toronto ON M5V 1K4",
    "addr:housenumber":"425",
    "addr:postcode":"m5v 1k4",
    "addr:street":"King St W",
    "iso:country":"CA",
    "sg:address":"425 King St W",
    "sg:city":"Toronto",
    "sg:classifiers":[
        {
            "category":"Professional",
            "type":"Services"
        }
    ],
    "sg:phone":"+1 416 599 2695",
    "sg:postcode":"M5V 1K4",
    "sg:province":"ON",
    "sg:tags":[
        "establishment",
        "sign"
    ],
    "wof:name":"Imaging Excellence Inc",
    "wof:placetype":"venue"
},
  "geometry": {"coordinates":[-79.3955993652,43.6452102661],"type":"Point"}
}