{
  "type": "Feature",
  "properties": {
    "addr:full":"202 8E Av Deux-Montagnes QC J7R 3K3",
    "addr:housenumber":"202",
    "addr:postcode":"j7r 3k3",
    "addr:street":"8E Av Deux-Montagnes",
    "iso:country":"CA",
    "sg:address":"202 8E Av",
    "sg:city":"Deux-Montagnes",
    "sg:classifiers":[
        {
            "category":"Government",
            "subcategory":"Office",
            "type":"Public Place"
        }
    ],
    "sg:phone":"+1 450 473 4833",
    "sg:postcode":"J7R 3K3",
    "sg:province":"QC",
    "sg:tags":[
        "village"
    ],
    "wof:name":"Deux-Montagnes Svc Des Comms",
    "wof:placetype":"venue"
},
  "geometry": {"coordinates":[-73.893288,45.542057],"type":"Point"}
}