{
  "type": "Feature",
  "properties": {
    "addr:full":"483 Speedvale Ave E Guelph ON N1E 6J2",
    "addr:housenumber":"483",
    "addr:postcode":"n1e 6j2",
    "addr:street":"Speedvale Ave E",
    "iso:country":"CA",
    "sg:address":"483 Speedvale Ave E",
    "sg:city":"Guelph",
    "sg:classifiers":[
        {
            "category":"Shopping",
            "subcategory":"Discount & Variety Stores",
            "type":"Retail Goods"
        }
    ],
    "sg:phone":"+1 519 822 4019",
    "sg:postcode":"N1E 6J2",
    "sg:province":"ON",
    "wof:name":"Victoria Variety",
    "wof:placetype":"venue"
},
  "geometry": {"coordinates":[-80.25169372560001,43.5702667236],"type":"Point"}
}