{
  "type": "Feature",
  "properties": {
    "addr:full":"12856 60 Ave Surrey BC V3X 2L5",
    "addr:housenumber":"12856",
    "addr:postcode":"v3x 2l5",
    "addr:street":"60 Ave",
    "iso:country":"CA",
    "sg:address":"12856 60 Ave",
    "sg:city":"Surrey",
    "sg:classifiers":[
        {
            "category":"Local Transit",
            "type":"Transportation"
        }
    ],
    "sg:phone":"+1 604 591 6049",
    "sg:postcode":"V3X 2L5",
    "sg:province":"BC",
    "sg:tags":[
        "limousine"
    ],
    "wof:name":"Lalonnie's Limousine",
    "wof:placetype":"venue"
},
  "geometry": {"coordinates":[-122.86586800000001,49.111637],"type":"Point"}
}