{
  "type": "Feature",
  "properties": {
    "addr:full":"104 Boul Industriel Repentigny QC J6A 4X6",
    "addr:housenumber":"104",
    "addr:postcode":"j6a 4x6",
    "addr:street":"Boul Industriel",
    "iso:country":"CA",
    "sg:address":"104 Boul Industriel",
    "sg:city":"Repentigny",
    "sg:classifiers":[
        {
            "category":"Food & Beverages",
            "subcategory":"Fruits & Vegetables",
            "type":"Retail Goods"
        }
    ],
    "sg:phone":"+1 450 582 1777",
    "sg:postcode":"J6A 4X6",
    "sg:province":"QC",
    "sg:tags":[
        "produce"
    ],
    "wof:name":"Fruits Legumes Notre-Dame",
    "wof:placetype":"venue"
},
  "geometry": {"coordinates":[-73.44329071040001,45.7545433044],"type":"Point"}
}