{
  "type": "Feature",
  "properties": {
    "addr:full":"Lambton QC G0M 1H0",
    "addr:postcode":"g0m 1h0",
    "iso:country":"CA",
    "sg:city":"Lambton",
    "sg:classifiers":[
        {
            "category":"Manufacturing",
            "subcategory":"Tools & Machinery",
            "type":"Manufacturing & Wholesale Goods"
        }
    ],
    "sg:phone":"+1 418 486 7533",
    "sg:postcode":"G0M 1H0",
    "sg:province":"QC",
    "sg:tags":[
        "electric",
        "motor"
    ],
    "wof:name":"Ber-For Electrique Ltee",
    "wof:placetype":"venue"
},
  "geometry": {"coordinates":[-71.085892,45.840351],"type":"Point"}
}