{
  "type": "Feature",
  "properties": {
    "addr:full":"768 Erie St Stratford ON N4Z 1A2",
    "addr:housenumber":"768",
    "addr:postcode":"n4z 1a2",
    "addr:street":"Erie St",
    "iso:country":"CA",
    "sg:address":"768 Erie St",
    "sg:city":"Stratford",
    "sg:classifiers":[
        {
            "category":"Wholesale",
            "subcategory":"Hardware",
            "type":"Manufacturing & Wholesale Goods"
        }
    ],
    "sg:phone":"+1 519 271 5800",
    "sg:postcode":"N4Z 1A2",
    "sg:province":"ON",
    "sg:tags":[
        "water",
        "heater"
    ],
    "wof:name":"A O Smith Enterprises Ltd",
    "wof:placetype":"venue"
},
  "geometry": {"coordinates":[-80.9977264404,43.3540687561],"type":"Point"}
}