{
  "type": "Feature",
  "properties": {
    "addr:full":"5052 Boul Samson Laval QC H7W 2J1",
    "addr:housenumber":"5052",
    "addr:postcode":"h7w 2j1",
    "addr:street":"Boul Samson",
    "iso:country":"CA",
    "sg:address":"5052 Boul Samson",
    "sg:city":"Laval",
    "sg:classifiers":[
        {
            "category":"Local Transit",
            "type":"Transportation"
        }
    ],
    "sg:phone":"+1 450 682 2123",
    "sg:postcode":"H7W 2J1",
    "sg:province":"QC",
    "sg:tags":[
        "limousine"
    ],
    "wof:name":"Air Executive Limousine",
    "wof:placetype":"venue"
},
  "geometry": {"coordinates":[-73.767326,45.526375],"type":"Point"}
}