{
  "type": "Feature",
  "properties": {
    "addr:full":"Richmond BC V6X 3J4",
    "addr:postcode":"v6x 3j4",
    "iso:country":"CA",
    "sg:city":"Richmond",
    "sg:classifiers":[
        {
            "category":"Shopping",
            "subcategory":"Clothing, Apparel, & Fashions",
            "type":"Retail Goods"
        }
    ],
    "sg:phone":"+1 604 273 3929",
    "sg:postcode":"V6X 3J4",
    "sg:province":"BC",
    "sg:tags":[
        "knit"
    ],
    "wof:name":"Kanata Hand-Knit Inc",
    "wof:placetype":"venue"
},
  "geometry": {"coordinates":[-123.094078064,49.1915168762],"type":"Point"}
}