{
  "type": "Feature",
  "properties": {
    "addr:full":"90 Centrepointe Dr Nepean ON K2G 6B1",
    "addr:housenumber":"90",
    "addr:postcode":"k2g 6b1",
    "addr:street":"Centrepointe Dr",
    "iso:country":"CA",
    "sg:address":"90 Centrepointe Dr",
    "sg:city":"Nepean",
    "sg:classifiers":[
        {
            "category":"Professional",
            "subcategory":"Lawyer & Legal Services",
            "type":"Services"
        }
    ],
    "sg:phone":"+1 613 226 6802",
    "sg:postcode":"K2G 6B1",
    "sg:province":"ON",
    "sg:tags":[
        "attorney"
    ],
    "wof:name":"Warren & Smith",
    "wof:placetype":"venue"
},
  "geometry": {"coordinates":[-75.7658,45.34597],"type":"Point"}
}