{
  "type": "Feature",
  "properties": {
    "addr:full":"6314 Drummond Rd Niagara Falls ON L2G 4M9",
    "addr:housenumber":"6314",
    "addr:postcode":"l2g 4m9",
    "addr:street":"Drummond Rd",
    "iso:country":"CA",
    "sg:address":"6314 Drummond Rd",
    "sg:city":"Niagara Falls",
    "sg:classifiers":[
        {
            "category":"Retail",
            "subcategory":"Repair Shop",
            "type":"Services"
        }
    ],
    "sg:phone":"+1 905 354 1074",
    "sg:postcode":"L2G 4M9",
    "sg:province":"ON",
    "sg:tags":[
        "upholsterer"
    ],
    "wof:name":"Alice's Upholstery",
    "wof:placetype":"venue"
},
  "geometry": {"coordinates":[-79.0972442627,43.0835113525],"type":"Point"}
}