{
  "type": "Feature",
  "properties": {
    "addr:full":"5621 Av Mcmurray Cote Saint-Luc QC H4W 2G1",
    "addr:housenumber":"5621",
    "addr:postcode":"h4w 2g1",
    "addr:street":"Av Mcmurray Cote",
    "iso:country":"CA",
    "sg:address":"5621 Av Mcmurray",
    "sg:city":"Cote Saint-Luc",
    "sg:classifiers":[
        {
            "category":"Education",
            "subcategory":"School",
            "type":"Public Place"
        }
    ],
    "sg:phone":"+1 514 484 5324",
    "sg:postcode":"H4W 2G1",
    "sg:province":"QC",
    "wof:name":"DE LA Mosaique Ecole",
    "wof:placetype":"venue"
},
  "geometry": {"coordinates":[-73.664948,45.462749],"type":"Point"}
}