{
  "type": "Feature",
  "properties": {
    "addr:full":"Kirkland Lake ON P2N 3P4",
    "addr:postcode":"p2n 3p4",
    "iso:country":"CA",
    "sg:city":"Kirkland Lake",
    "sg:classifiers":[
        {
            "category":"Recreation",
            "type":"Entertainment"
        }
    ],
    "sg:phone":"+1 705 567 5215",
    "sg:postcode":"P2N 3P4",
    "sg:province":"ON",
    "sg:tags":[
        "government",
        "swimming"
    ],
    "wof:name":"Kirkland Lake Community Cmplx",
    "wof:placetype":"venue"
},
  "geometry": {"coordinates":[-80.026382,48.154179],"type":"Point"}
}