{
  "type": "Feature",
  "properties": {
    "addr:full":"228 Valley Rd Kelowna BC V1V 2G2",
    "addr:housenumber":"228",
    "addr:postcode":"v1v 2g2",
    "addr:street":"Valley Rd",
    "iso:country":"CA",
    "sg:address":"228 Valley Rd",
    "sg:city":"Kelowna",
    "sg:classifiers":[
        {
            "category":"Organizations",
            "subcategory":"Religious Organization",
            "type":"Services"
        }
    ],
    "sg:phone":"+1 250 763 4822",
    "sg:postcode":"V1V 2G2",
    "sg:province":"BC",
    "sg:tags":[
        "church"
    ],
    "wof:name":"Garden Valley Community Church",
    "wof:placetype":"venue"
},
  "geometry": {"coordinates":[-119.435349,49.918892],"type":"Point"}
}