{
  "type": "Feature",
  "properties": {
    "addr:full":"5109 50 Ave Whitecourt AB T7S 1S8",
    "addr:housenumber":"5109",
    "addr:postcode":"t7s 1s8",
    "addr:street":"50 Ave",
    "iso:country":"CA",
    "sg:address":"5109 50 Ave",
    "sg:city":"Whitecourt",
    "sg:classifiers":[
        {
            "category":"Insurance",
            "subcategory":"Insurance Agent",
            "type":"Services"
        }
    ],
    "sg:phone":"+1 780 778 3001",
    "sg:postcode":"T7S 1S8",
    "sg:province":"AB",
    "wof:name":"Nelsen, Charlene",
    "wof:placetype":"venue"
},
  "geometry": {"coordinates":[-115.687507629,54.1404190063],"type":"Point"}
}