{
  "type": "Feature",
  "properties": {
    "addr:full":"3900 Boul Sir-Wilfrid-Laurier Saint-Hubert QC J3Y 6T1",
    "addr:housenumber":"3900",
    "addr:postcode":"j3y 6t1",
    "addr:street":"Boul Sir-Wilfrid-Laurier",
    "iso:country":"CA",
    "sg:address":"3900 Boul Sir-Wilfrid-Laurier",
    "sg:city":"Saint-Hubert",
    "sg:classifiers":[
        {
            "category":"Freight",
            "type":"Transportation"
        }
    ],
    "sg:phone":"+1 450 676 6236",
    "sg:postcode":"J3Y 6T1",
    "sg:province":"QC",
    "sg:tags":[
        "commercial",
        "storage"
    ],
    "wof:name":"Entreposage Domestik",
    "wof:placetype":"venue"
},
  "geometry": {"coordinates":[-73.445885,45.506634],"type":"Point"}
}