{
  "type": "Feature",
  "properties": {
    "addr:full":"540 Pelissier St Windsor ON N9A 4L1",
    "addr:housenumber":"540",
    "addr:postcode":"n9a 4l1",
    "addr:street":"Pelissier St",
    "iso:country":"CA",
    "sg:address":"540 Pelissier St",
    "sg:city":"Windsor",
    "sg:classifiers":[
        {
            "category":"Health Services",
            "subcategory":"Doctor",
            "type":"Services"
        }
    ],
    "sg:phone":"+1 519 252 2631",
    "sg:postcode":"N9A 4L1",
    "sg:province":"ON",
    "sg:tags":[
        "dentist"
    ],
    "wof:name":"Nicola, Stelica DDS",
    "wof:placetype":"venue"
},
  "geometry": {"coordinates":[-83.0379867554,42.3144454956],"type":"Point"}
}