{
  "type": "Feature",
  "properties": {
    "addr:full":"146 Boul DE Mortagne Boucherville QC J4B 5M7",
    "addr:housenumber":"146",
    "addr:postcode":"j4b 5m7",
    "addr:street":"Boul De Mortagne",
    "iso:country":"CA",
    "sg:address":"146 Boul DE Mortagne",
    "sg:city":"Boucherville",
    "sg:classifiers":[
        {
            "category":"Professional",
            "subcategory":"Art Services",
            "type":"Services"
        }
    ],
    "sg:phone":"+1 450 449 7131",
    "sg:postcode":"J4B 5M7",
    "sg:province":"QC",
    "sg:tags":[
        "graphic",
        "designer"
    ],
    "wof:name":"Indigo Communications Visuelle",
    "wof:placetype":"venue"
},
  "geometry": {"coordinates":[-73.44652600000001,45.577999],"type":"Point"}
}