{
  "type": "Feature",
  "properties": {
    "addr:full":"Richmond BC V7B 1B4",
    "addr:postcode":"v7b 1b4",
    "iso:country":"CA",
    "sg:city":"Richmond",
    "sg:classifiers":[
        {
            "category":"Building & Trades",
            "subcategory":"Equipment Rental",
            "type":"Services"
        }
    ],
    "sg:phone":"+1 604 272 8123",
    "sg:postcode":"V7B 1B4",
    "sg:province":"BC",
    "sg:tags":[
        "aircraft",
        "leasing",
        "charter"
    ],
    "wof:name":"London Air Svc",
    "wof:placetype":"venue"
},
  "geometry": {"coordinates":[-123.165604,49.1805],"type":"Point"}
}