{
  "type": "Feature",
  "properties": {
    "addr:full":"2030 Weston Rd York ON M9N 1X4",
    "addr:housenumber":"2030",
    "addr:postcode":"m9n 1x4",
    "addr:street":"Weston Rd",
    "iso:country":"CA",
    "sg:address":"2030 Weston Rd",
    "sg:city":"York",
    "sg:classifiers":[
        {
            "category":"Professional",
            "subcategory":"Accounting & Tax Preparation",
            "type":"Services"
        }
    ],
    "sg:phone":"+1 416 241 9070",
    "sg:postcode":"M9N 1X4",
    "sg:province":"ON",
    "sg:tags":[
        "accountant",
        "return",
        "filing"
    ],
    "wof:name":"Canadian Tax Svc Inc",
    "wof:placetype":"venue"
},
  "geometry": {"coordinates":[-79.5211639404,43.7013664246],"type":"Point"}
}