{
  "type": "Feature",
  "properties": {
    "addr:full":"Canmore AB T1W 1P5",
    "addr:postcode":"t1w 1p5",
    "iso:country":"CA",
    "sg:city":"Canmore",
    "sg:classifiers":[
        {
            "category":"Health Services",
            "subcategory":"Health Practitioner",
            "type":"Services"
        }
    ],
    "sg:phone":"+1 403 678 8891",
    "sg:postcode":"T1W 1P5",
    "sg:province":"AB",
    "sg:tags":[
        "psychologist"
    ],
    "wof:name":"DE Wet, Charl PhD",
    "wof:placetype":"venue"
},
  "geometry": {"coordinates":[-115.35058593799999,51.0909805298],"type":"Point"}
}