{
  "type": "Feature",
  "properties": {
    "addr:full":"760 Yates St Victoria BC V8W 1L4",
    "addr:housenumber":"760",
    "addr:postcode":"v8w 1l4",
    "addr:street":"Yates St",
    "iso:country":"CA",
    "sg:address":"760 Yates St",
    "sg:city":"Victoria",
    "sg:classifiers":[
        {
            "category":"Personal",
            "subcategory":"Shoe Repair & Shine",
            "type":"Services"
        }
    ],
    "sg:phone":"+1 250 385 1813",
    "sg:postcode":"V8W 1L4",
    "sg:province":"BC",
    "sg:tags":[
        "repairing",
        "boot"
    ],
    "wof:name":"Manton Shoe Repair",
    "wof:placetype":"venue"
},
  "geometry": {"coordinates":[-123.36323547400001,48.4262313843],"type":"Point"}
}