{
  "type": "Feature",
  "properties": {
    "addr:full":"130 Grand Rd Campbellford ON K0L 1L0",
    "addr:housenumber":"130",
    "addr:postcode":"k0l 1l0",
    "addr:street":"Grand Rd",
    "iso:country":"CA",
    "sg:address":"130 Grand Rd",
    "sg:city":"Campbellford",
    "sg:classifiers":[
        {
            "category":"Autos & Motor Vehicles",
            "subcategory":"Auto Supplies",
            "type":"Retail Goods"
        }
    ],
    "sg:phone":"+1 705 653 3250",
    "sg:postcode":"K0L 1L0",
    "sg:province":"ON",
    "sg:tags":[
        "automobile",
        "parts"
    ],
    "wof:name":"Canadian Tire",
    "wof:placetype":"venue"
},
  "geometry": {"coordinates":[-77.803307,44.304466],"type":"Point"}
}