{
  "type": "Feature",
  "properties": {
    "addr:full":"Langley BC V3A 1G5",
    "addr:postcode":"v3a 1g5",
    "iso:country":"CA",
    "sg:city":"Langley",
    "sg:classifiers":[
        {
            "category":"Wholesale",
            "subcategory":"Auto Parts",
            "type":"Manufacturing & Wholesale Goods"
        }
    ],
    "sg:phone":"+1 604 532 7939",
    "sg:postcode":"V3A 1G5",
    "sg:province":"BC",
    "sg:tags":[
        "automobile",
        "wrecking"
    ],
    "wof:name":"Autobahn Dismantlers",
    "wof:placetype":"venue"
},
  "geometry": {"coordinates":[-122.673965,49.107166],"type":"Point"}
}