{
  "type": "Feature",
  "properties": {
    "addr:full":"Vancouver BC V7X 1L4",
    "addr:postcode":"v7x 1l4",
    "iso:country":"CA",
    "sg:city":"Vancouver",
    "sg:classifiers":[
        {
            "category":"Banks & Credit Unions",
            "subcategory":"Investment Brokerage",
            "type":"Services"
        }
    ],
    "sg:phone":"+1 604 662 1800",
    "sg:postcode":"V7X 1L4",
    "sg:province":"BC",
    "sg:tags":[
        "stock",
        "broker",
        "bond"
    ],
    "wof:name":"Research Capital Corp",
    "wof:placetype":"venue"
},
  "geometry": {"coordinates":[-123.12000999999999,49.285961],"type":"Point"}
}