{
  "type": "Feature",
  "properties": {
    "iso:country":"CA",
    "sg:address":"7964 Rue DE Marseille",
    "sg:city":"Montreal",
    "sg:classifiers":[
        {
            "category":"Personal",
            "subcategory":"Beauty Salon",
            "type":"Services"
        }
    ],
    "sg:phone":"+1 514 356 1369",
    "sg:postcode":"H1L 1N7",
    "sg:province":"QC",
    "wof:name":"Salon DE Coiffure Mercier",
    "wof:placetype":"venue"
},
  "geometry": {"coordinates":[-73.5304260254,45.5955924988],"type":"Point"}
}