{
  "type": "Feature",
  "properties": {
    "addr:full":"551 Windermere Rd London ON N5X 2T1",
    "addr:housenumber":"551",
    "addr:postcode":"n5x 2t1",
    "addr:street":"Windermere Rd",
    "iso:country":"CA",
    "sg:address":"551 Windermere Rd",
    "sg:city":"London",
    "sg:classifiers":[
        {
            "category":"Travel",
            "subcategory":"Hotels & Motels",
            "type":"Entertainment"
        }
    ],
    "sg:phone":"+1 519 679 4546",
    "sg:postcode":"N5X 2T1",
    "sg:province":"ON",
    "sg:tags":[
        "convention",
        "meeting",
        "facility"
    ],
    "wof:name":"Spencer Hall Conference Ctr",
    "wof:placetype":"venue"
},
  "geometry": {"coordinates":[-81.261002,43.019485],"type":"Point"}
}