{
  "type": "Feature",
  "properties": {
    "addr:full":"174 Mc Donalds St Peterborough ON K9J 6W7",
    "addr:housenumber":"174",
    "addr:postcode":"k9j 6w7",
    "addr:street":"Mc Donalds St",
    "iso:country":"CA",
    "sg:address":"174 Mc Donalds St",
    "sg:city":"Peterborough",
    "sg:classifiers":[
        {
            "category":"Wholesale",
            "subcategory":"Metals & Minerals",
            "type":"Manufacturing & Wholesale Goods"
        }
    ],
    "sg:phone":"+1 705 748 3364",
    "sg:postcode":"K9J 6W7",
    "sg:province":"ON",
    "sg:tags":[
        "die",
        "casting"
    ],
    "wof:name":"Kenneth C Edwards & Assoc",
    "wof:placetype":"venue"
},
  "geometry": {"coordinates":[-78.3212585449,44.3097381592],"type":"Point"}
}