{
  "type": "Feature",
  "properties": {
    "addr:full":"701 Rossland Rd E # 1 Whitby ON L1N 9K3",
    "addr:housenumber":"701",
    "addr:postcode":"l1n 9k3",
    "addr:street":"Rossland Rd E # 1",
    "iso:country":"CA",
    "sg:address":"701 Rossland Rd E # 1",
    "sg:city":"Whitby",
    "sg:classifiers":[
        {
            "category":"Food & Beverages",
            "subcategory":"Bakery",
            "type":"Retail Goods"
        }
    ],
    "sg:phone":"+1 905 666 5015",
    "sg:postcode":"L1N 9K3",
    "sg:province":"ON",
    "sg:tags":[
        "doughnut"
    ],
    "wof:name":"Coffee Time Donuts",
    "wof:placetype":"venue"
},
  "geometry": {"coordinates":[-78.939598,43.899757],"type":"Point"}
}