{
  "type": "Feature",
  "properties": {
    "addr:full":"825 Rue Saint-Laurent O # 1 Longueuil QC J4K 2V1",
    "addr:housenumber":"825",
    "addr:postcode":"j4k 2v1",
    "addr:street":"Rue Saint-Laurent O # 1",
    "iso:country":"CA",
    "sg:address":"825 Rue Saint-Laurent O # 1",
    "sg:city":"Longueuil",
    "sg:classifiers":[
        {
            "category":"Shopping",
            "subcategory":"Jewelry",
            "type":"Retail Goods"
        }
    ],
    "sg:phone":"+1 450 674 3290",
    "sg:postcode":"J4K 2V1",
    "sg:province":"QC",
    "sg:tags":[
        "jeweler"
    ],
    "wof:name":"Bijoutieries Lavigueur Ltee",
    "wof:placetype":"venue"
},
  "geometry": {"coordinates":[-73.5135726929,45.5283432007],"type":"Point"}
}