{
  "type": "Feature",
  "properties": {
    "addr:full":"405 Tecumseh Rd W Windsor ON N8X 1G6",
    "addr:housenumber":"405",
    "addr:postcode":"n8x 1g6",
    "addr:street":"Tecumseh Rd W",
    "iso:country":"CA",
    "sg:address":"405 Tecumseh Rd W",
    "sg:city":"Windsor",
    "sg:classifiers":[
        {
            "category":"Recreation",
            "type":"Entertainment"
        }
    ],
    "sg:phone":"+1 519 256 7871",
    "sg:postcode":"N8X 1G6",
    "sg:province":"ON",
    "sg:tags":[
        "lottery",
        "agent"
    ],
    "wof:name":"Corner Store",
    "wof:placetype":"venue"
},
  "geometry": {"coordinates":[-83.0297470093,42.2954940796],"type":"Point"}
}