{
  "type": "Feature",
  "properties": {
    "iso:country":"CA",
    "sg:address":"900 Ste Therese Ave",
    "sg:city":"Winnipeg",
    "sg:classifiers":[
        {
            "category":"Education",
            "subcategory":"School",
            "type":"Public Place"
        }
    ],
    "sg:phone":"+1 204 261 4430",
    "sg:postcode":"R3V 1H8",
    "sg:province":"MB",
    "wof:name":"St Norbert Immersion School",
    "wof:placetype":"venue"
},
  "geometry": {"coordinates":[-97.147858,49.763577],"type":"Point"}
}