{
  "type": "Feature",
  "properties": {
    "addr:full":"Ottawa ON K2B 6V4",
    "addr:postcode":"k2b 6v4",
    "iso:country":"CA",
    "sg:city":"Ottawa",
    "sg:classifiers":[
        {
            "category":"Real Estate",
            "subcategory":"Real Estate Operator",
            "type":"Services"
        }
    ],
    "sg:phone":"+1 613 721 0090",
    "sg:postcode":"K2B 6V4",
    "sg:province":"ON",
    "sg:tags":[
        "apartment"
    ],
    "wof:name":"Parkway Towers Apartments",
    "wof:placetype":"venue"
},
  "geometry": {"coordinates":[-75.78046399999999,45.373146],"type":"Point"}
}