{
  "type": "Feature",
  "properties": {
    "addr:full":"1337 London Rd Sarnia ON N7S 1P6",
    "addr:housenumber":"1337",
    "addr:postcode":"n7s 1p6",
    "addr:street":"London Rd",
    "iso:country":"CA",
    "sg:address":"1337 London Rd",
    "sg:city":"Sarnia",
    "sg:classifiers":[
        {
            "category":"Restaurant",
            "type":"Food & Drink"
        }
    ],
    "sg:phone":"+1 519 542 7789",
    "sg:postcode":"N7S 1P6",
    "sg:province":"ON",
    "wof:name":"East Side Mario's",
    "wof:placetype":"venue"
},
  "geometry": {"coordinates":[-82.35565200000001,42.979939],"type":"Point"}
}