{
  "type": "Feature",
  "properties": {
    "addr:full":"Alliston ON L9R 1R1",
    "addr:postcode":"l9r 1r1",
    "addr:street":"Alliston",
    "iso:country":"CA",
    "sg:city":"Alliston",
    "sg:classifiers":[
        {
            "category":"Wholesale",
            "subcategory":"Machinery & Supplies",
            "type":"Manufacturing & Wholesale Goods"
        }
    ],
    "sg:phone":"+1 705 434 4888",
    "sg:postcode":"L9R 1R1",
    "sg:province":"ON",
    "sg:tags":[
        "equipment",
        "bottler",
        "wine"
    ],
    "wof:name":"Cork & Vine",
    "wof:placetype":"venue"
},
  "geometry": {"coordinates":[-79.87255859379999,44.1531562805],"type":"Point"}
}