{
  "type": "Feature",
  "properties": {
    "addr:full":"42 Champlain Blvd Lindsay ON K9V 4R1",
    "addr:housenumber":"42",
    "addr:postcode":"k9v 4r1",
    "addr:street":"Champlain Blvd",
    "iso:country":"CA",
    "sg:address":"42 Champlain Blvd",
    "sg:city":"Lindsay",
    "sg:classifiers":[
        {
            "category":"Insurance",
            "subcategory":"Insurance Agent",
            "type":"Services"
        }
    ],
    "sg:phone":"+1 705 878 8708",
    "sg:postcode":"K9V 4R1",
    "sg:province":"ON",
    "sg:tags":[
        "consultant"
    ],
    "wof:name":"Douglas Robertson & Assoc",
    "wof:placetype":"venue"
},
  "geometry": {"coordinates":[-78.7521057129,44.37550354],"type":"Point"}
}