{
  "type": "Feature",
  "properties": {
    "addr:full":"219 E 4th Ave Regina SK S4N 4Z7",
    "addr:housenumber":"219",
    "addr:postcode":"s4n 4z7",
    "addr:street":"E 4Th Ave",
    "iso:country":"CA",
    "sg:address":"219 E 4th Ave",
    "sg:city":"Regina",
    "sg:classifiers":[
        {
            "category":"Wholesale",
            "subcategory":"Machinery & Supplies",
            "type":"Manufacturing & Wholesale Goods"
        }
    ],
    "sg:phone":"+1 306 565 2074",
    "sg:postcode":"S4N 4Z7",
    "sg:province":"SK",
    "sg:tags":[
        "fastener",
        "actuated"
    ],
    "wof:name":"Prime Fasteners",
    "wof:placetype":"venue"
},
  "geometry": {"coordinates":[-104.580055237,50.4628295898],"type":"Point"}
}