{
  "type": "Feature",
  "properties": {
    "addr:full":"3957 Chesswood Dr North York ON M3J 2R8",
    "addr:housenumber":"3957",
    "addr:postcode":"m3j 2r8",
    "addr:street":"Chesswood Dr",
    "iso:country":"CA",
    "sg:address":"3957 Chesswood Dr",
    "sg:city":"North York",
    "sg:classifiers":[
        {
            "category":"Manufacturing",
            "subcategory":"Printing",
            "type":"Manufacturing & Wholesale Goods"
        }
    ],
    "sg:phone":"+1 416 635 8761",
    "sg:postcode":"M3J 2R8",
    "sg:province":"ON",
    "sg:tags":[
        "printer"
    ],
    "wof:name":"New Typro Printing",
    "wof:placetype":"venue"
},
  "geometry": {"coordinates":[-79.476128,43.758083],"type":"Point"}
}