{
  "type": "Feature",
  "properties": {
    "addr:full":"Fort Mcmurray AB T9H 1R3",
    "addr:postcode":"t9h 1r3",
    "iso:country":"CA",
    "sg:city":"Fort Mcmurray",
    "sg:classifiers":[
        {
            "category":"Real Estate",
            "subcategory":"Real Estate Operator",
            "type":"Services"
        }
    ],
    "sg:phone":"+1 780 743 4478",
    "sg:postcode":"T9H 1R3",
    "sg:province":"AB",
    "sg:tags":[
        "apartment"
    ],
    "wof:name":"River Valley Manor",
    "wof:placetype":"venue"
},
  "geometry": {"coordinates":[-111.376785,56.721882],"type":"Point"}
}