{
  "type": "Feature",
  "properties": {
    "addr:full":"507 Av DE LA Tuilerie Westbury QC J0B 1R0",
    "addr:postcode":"j0b 1r0",
    "addr:street":"507 Av De La Tuilerie",
    "iso:country":"CA",
    "sg:address":"507 Av DE LA Tuilerie",
    "sg:city":"Westbury",
    "sg:classifiers":[
        {
            "category":"Retail",
            "subcategory":"Auto Repair",
            "type":"Services"
        }
    ],
    "sg:phone":"+1 819 832 2595",
    "sg:postcode":"J0B 1R0",
    "sg:province":"QC",
    "sg:tags":[
        "repairing",
        "automobile"
    ],
    "wof:name":"Garage Jean-Luc Bissonette",
    "wof:placetype":"venue"
},
  "geometry": {"coordinates":[-71.6399,45.488831],"type":"Point"}
}