{
  "type": "Feature",
  "properties": {
    "addr:full":"373 Bridge St W #8 Waterloo ON N2K 3K3",
    "addr:housenumber":"373",
    "addr:postcode":"n2k 3k3",
    "addr:street":"Bridge St W # 8",
    "iso:country":"CA",
    "sg:address":"373 Bridge St W #8",
    "sg:city":"Waterloo",
    "sg:classifiers":[
        {
            "category":"Retail",
            "subcategory":"Laundry & Dry Cleaning",
            "type":"Services"
        }
    ],
    "sg:phone":"+1 519 885 0780",
    "sg:postcode":"N2K 3K3",
    "sg:province":"ON",
    "sg:tags":[
        "cleaners"
    ],
    "wof:name":"Reese Dry Cleaning",
    "wof:placetype":"venue"
},
  "geometry": {"coordinates":[-80.5009460449,43.4955940247],"type":"Point"}
}