{
  "type": "Feature",
  "properties": {
    "addr:full":"4910 Yonge St North York ON M2N 5N5",
    "addr:housenumber":"4910",
    "addr:postcode":"m2n 5n5",
    "addr:street":"Yonge St",
    "iso:country":"CA",
    "sg:address":"4910 Yonge St",
    "sg:city":"North York",
    "sg:classifiers":[
        {
            "category":"Personal",
            "subcategory":"Beauty Salon",
            "type":"Services"
        }
    ],
    "sg:phone":"+1 416 226 3399",
    "sg:postcode":"M2N 5N5",
    "sg:province":"ON",
    "wof:name":"Vienna Beauty Spa",
    "wof:placetype":"venue"
},
  "geometry": {"coordinates":[-79.41175800000001,43.764114],"type":"Point"}
}