{
  "type": "Feature",
  "properties": {
    "addr:full":"6419 Main St Vancouver BC V5W 2V5",
    "addr:housenumber":"6419",
    "addr:postcode":"v5w 2v5",
    "addr:street":"Main St",
    "iso:country":"CA",
    "sg:address":"6419 Main St",
    "sg:city":"Vancouver",
    "sg:classifiers":[
        {
            "category":"Health Services",
            "subcategory":"Doctor",
            "type":"Services"
        }
    ],
    "sg:phone":"+1 604 325 5211",
    "sg:postcode":"V5W 2V5",
    "sg:province":"BC",
    "sg:tags":[
        "physician",
        "surgeon"
    ],
    "wof:name":"Nasir Jetha Inc",
    "wof:placetype":"venue"
},
  "geometry": {"coordinates":[-123.101707459,49.2264862061],"type":"Point"}
}