{
  "type": "Feature",
  "properties": {
    "addr:full":"Calgary AB T2Z 3J3",
    "addr:postcode":"t2z 3j3",
    "iso:country":"CA",
    "sg:city":"Calgary",
    "sg:classifiers":[
        {
            "category":"Restaurant",
            "type":"Food & Drink"
        }
    ],
    "sg:phone":"+1 403 203 3473",
    "sg:postcode":"T2Z 3J3",
    "sg:province":"AB",
    "wof:name":"Subway Sandwiches & Salads",
    "wof:placetype":"venue"
},
  "geometry": {"coordinates":[-114.001960754,50.9519691467],"type":"Point"}
}