{
  "type": "Feature",
  "properties": {
    "addr:full":"1103 Michigan Ave Sarnia ON N7S 2B5",
    "addr:housenumber":"1103",
    "addr:postcode":"n7s 2b5",
    "addr:street":"Michigan Ave",
    "iso:country":"CA",
    "sg:address":"1103 Michigan Ave",
    "sg:city":"Sarnia",
    "sg:classifiers":[
        {
            "category":"Social Services",
            "subcategory":"Child Care",
            "type":"Services"
        }
    ],
    "sg:phone":"+1 519 542 2129",
    "sg:postcode":"N7S 2B5",
    "sg:province":"ON",
    "wof:name":"Chateau Magique French",
    "wof:placetype":"venue"
},
  "geometry": {"coordinates":[-82.366027832,42.9992485046],"type":"Point"}
}