{
  "type": "Feature",
  "properties": {
    "addr:full":"185 Boul Provencher Winnipeg MB R2H 0G4",
    "addr:housenumber":"185",
    "addr:postcode":"r2h 0g4",
    "addr:street":"Boul Provencher",
    "iso:country":"CA",
    "sg:address":"185 Boul Provencher",
    "sg:city":"Winnipeg",
    "sg:classifiers":[
        {
            "category":"Banks & Credit Unions",
            "subcategory":"Bank",
            "type":"Services"
        }
    ],
    "sg:phone":"+1 204 237 8874",
    "sg:postcode":"R2H 0G4",
    "sg:province":"MB",
    "wof:name":"Caisse Populaire St Boniface",
    "wof:placetype":"venue"
},
  "geometry": {"coordinates":[-97.12200900000001,49.892395],"type":"Point"}
}