{
  "type": "Feature",
  "properties": {
    "addr:full":"6 West St Belleville ON K8N 4X4",
    "addr:housenumber":"6",
    "addr:postcode":"k8n 4x4",
    "addr:street":"West St",
    "iso:country":"CA",
    "sg:address":"6 West St",
    "sg:city":"Belleville",
    "sg:classifiers":[
        {
            "category":"Building & Trades",
            "subcategory":"Cleaning & Sanitation",
            "type":"Services"
        }
    ],
    "sg:phone":"+1 613 962 0336",
    "sg:postcode":"K8N 4X4",
    "sg:province":"ON",
    "sg:tags":[
        "janitor"
    ],
    "wof:name":"C & M Cleaning",
    "wof:placetype":"venue"
},
  "geometry": {"coordinates":[-77.37232208250001,44.1815757751],"type":"Point"}
}