{
  "type": "Feature",
  "properties": {
    "addr:full":"114 Industrial Rd 2 Invermere BC V0A 1K5",
    "addr:housenumber":"114",
    "addr:postcode":"v0a 1k5",
    "addr:street":"Industrial Rd 2",
    "iso:country":"CA",
    "sg:address":"114 Industrial Rd 2",
    "sg:city":"Invermere",
    "sg:classifiers":[
        {
            "category":"Freight",
            "type":"Transportation"
        }
    ],
    "sg:phone":"+1 250 342 3939",
    "sg:postcode":"V0A 1K5",
    "sg:province":"BC",
    "sg:tags":[
        "trucking"
    ],
    "wof:name":"W Letcher Trucking",
    "wof:placetype":"venue"
},
  "geometry": {"coordinates":[-116.04216003400001,50.509223938],"type":"Point"}
}