{
  "type": "Feature",
  "properties": {
    "addr:full":"620 Mary St Craik SK S0G 0V0",
    "addr:housenumber":"620",
    "addr:postcode":"s0g 0v0",
    "addr:street":"Mary St",
    "iso:country":"CA",
    "sg:address":"620 Mary St",
    "sg:city":"Craik",
    "sg:classifiers":[
        {
            "category":"Health Services",
            "subcategory":"Hospital",
            "type":"Services"
        }
    ],
    "sg:phone":"+1 306 734 2288",
    "sg:postcode":"S0G 0V0",
    "sg:province":"SK",
    "wof:name":"Craik & District Health Ctr",
    "wof:placetype":"venue"
},
  "geometry": {"coordinates":[-105.81104999999999,51.045319],"type":"Point"}
}