{
  "type": "Feature",
  "properties": {
    "addr:full":"590 Rue Saint-Roch Trois-Rivieres QC G9A 2M2",
    "addr:housenumber":"590",
    "addr:postcode":"g9a 2m2",
    "addr:street":"Rue Saint-Roch Trois-Rivieres",
    "iso:country":"CA",
    "sg:address":"590 Rue Saint-Roch",
    "sg:city":"Trois-Rivieres",
    "sg:classifiers":[
        {
            "category":"Health Services",
            "subcategory":"Doctor",
            "type":"Services"
        }
    ],
    "sg:phone":"+1 819 374 8000",
    "sg:postcode":"G9A 2M2",
    "sg:province":"QC",
    "sg:tags":[
        "physician",
        "surgeon"
    ],
    "wof:name":"Cote, Andree MD",
    "wof:placetype":"venue"
},
  "geometry": {"coordinates":[-72.547325,46.341],"type":"Point"}
}