{
  "type": "Feature",
  "properties": {
    "addr:full":"Saint-Jean-Sur-Richelieu QC J3B 8H7",
    "addr:postcode":"j3b 8h7",
    "iso:country":"CA",
    "sg:city":"Saint-Jean-Sur-Richelieu",
    "sg:classifiers":[
        {
            "category":"Wholesale",
            "subcategory":"Machinery & Supplies",
            "type":"Manufacturing & Wholesale Goods"
        }
    ],
    "sg:phone":"+1 450 359 1400",
    "sg:postcode":"J3B 8H7",
    "sg:province":"QC",
    "sg:tags":[
        "bearing"
    ],
    "wof:name":"Motion Canada",
    "wof:placetype":"venue"
},
  "geometry": {"coordinates":[-73.29650100000001,45.324642],"type":"Point"}
}