{
  "type": "Feature",
  "properties": {
    "addr:full":"1258 Henderson Hwy Winnipeg MB R2G 1M2",
    "addr:housenumber":"1258",
    "addr:postcode":"r2g 1m2",
    "addr:street":"Henderson Hwy",
    "iso:country":"CA",
    "sg:address":"1258 Henderson Hwy",
    "sg:city":"Winnipeg",
    "sg:classifiers":[
        {
            "category":"Social Services",
            "type":"Services"
        }
    ],
    "sg:phone":"+1 204 338 3339",
    "sg:postcode":"R2G 1M2",
    "sg:province":"MB",
    "sg:tags":[
        "counselor",
        "marriage",
        "family"
    ],
    "wof:name":"Keystone Counselling Assoc",
    "wof:placetype":"venue"
},
  "geometry": {"coordinates":[-97.090172,49.941326],"type":"Point"}
}