{
  "type": "Feature",
  "properties": {
    "addr:full":"14035 Victoria Trail NW Edmonton AB T5Y 2B6",
    "addr:housenumber":"14035",
    "addr:postcode":"t5y 2b6",
    "addr:street":"Victoria Trail Nw",
    "iso:country":"CA",
    "sg:address":"14035 Victoria Trail NW",
    "sg:city":"Edmonton",
    "sg:classifiers":[
        {
            "category":"Autos & Motor Vehicles",
            "subcategory":"Fuel & Gas Station",
            "type":"Retail Goods"
        }
    ],
    "sg:phone":"+1 780 478 2677",
    "sg:postcode":"T5Y 2B6",
    "sg:province":"AB",
    "sg:tags":[
        "oil"
    ],
    "wof:name":"Clareview Village Self Serve",
    "wof:placetype":"venue"
},
  "geometry": {"coordinates":[-113.384964,53.604321],"type":"Point"}
}