{
  "type": "Feature",
  "properties": {
    "addr:full":"300 Place Des Oliviers L'Acadie QC J2Y 1E1",
    "addr:housenumber":"300",
    "addr:postcode":"j2y 1e1",
    "addr:street":"Place Des Oliviers",
    "iso:country":"CA",
    "sg:address":"300 Place Des Oliviers",
    "sg:city":"L'Acadie",
    "sg:classifiers":[
        {
            "category":"Personal",
            "type":"Services"
        }
    ],
    "sg:phone":"+1 450 346 2664",
    "sg:postcode":"J2Y 1E1",
    "sg:province":"QC",
    "sg:tags":[
        "electrolysis"
    ],
    "wof:name":"Huitieme Jour",
    "wof:placetype":"venue"
},
  "geometry": {"coordinates":[-73.3451766968,45.3149414062],"type":"Point"}
}