{
  "type": "Feature",
  "properties": {
    "addr:full":"640 Boul Langelier Quebec QC G1K 5R3",
    "addr:housenumber":"640",
    "addr:postcode":"g1k 5r3",
    "addr:street":"Boul Langelier",
    "iso:country":"CA",
    "sg:address":"640 Boul Langelier",
    "sg:city":"Quebec",
    "sg:classifiers":[
        {
            "category":"Wholesale",
            "subcategory":"Tobacco Products",
            "type":"Manufacturing & Wholesale Goods"
        }
    ],
    "sg:phone":"+1 418 522 0211",
    "sg:postcode":"G1K 5R3",
    "sg:province":"QC",
    "sg:tags":[
        "cigarette",
        "cigar",
        "dealer"
    ],
    "wof:name":"Tabacs Tremblay",
    "wof:placetype":"venue"
},
  "geometry": {"coordinates":[-71.229393,46.808212],"type":"Point"}
}