{
  "type": "Feature",
  "properties": {
    "addr:full":"686 Boul Perron Maria QC G0C 1Y0",
    "addr:housenumber":"686",
    "addr:postcode":"g0c 1y0",
    "addr:street":"Boul Perron",
    "iso:country":"CA",
    "sg:address":"686 Boul Perron",
    "sg:city":"Maria",
    "sg:classifiers":[
        {
            "category":"Personal",
            "subcategory":"Beauty Salon",
            "type":"Services"
        }
    ],
    "sg:phone":"+1 418 759 5908",
    "sg:postcode":"G0C 1Y0",
    "sg:province":"QC",
    "wof:name":"Boudrau, Gaetane",
    "wof:placetype":"venue"
},
  "geometry": {"coordinates":[-65.9709472656,48.1886634827],"type":"Point"}
}