{
  "type": "Feature",
  "properties": {
    "iso:country":"CA",
    "sg:city":"Berthierville",
    "sg:classifiers":[
        {
            "category":"Social Services",
            "type":"Services"
        }
    ],
    "sg:phone":"+1 450 836 6777",
    "sg:postcode":"J0K 1A0",
    "sg:province":"QC",
    "sg:tags":[
        "organization",
        "welfare"
    ],
    "wof:name":"Clsc-Chsld D'Autray",
    "wof:placetype":"venue"
},
  "geometry": {"coordinates":[-73.1784667969,46.0809059143],"type":"Point"}
}