{
  "type": "Feature",
  "properties": {
    "addr:full":"Vancouver BC V6A 1T6",
    "addr:postcode":"v6a 1t6",
    "iso:country":"CA",
    "sg:city":"Vancouver",
    "sg:classifiers":[
        {
            "category":"Restaurant",
            "type":"Food & Drink"
        }
    ],
    "sg:phone":"+1 604 688 3877",
    "sg:postcode":"V6A 1T6",
    "sg:province":"BC",
    "wof:name":"Garden Villa Seafood Rstrnt",
    "wof:placetype":"venue"
},
  "geometry": {"coordinates":[-123.10144805900001,49.2805480957],"type":"Point"}
}