{
  "type": "Feature",
  "properties": {
    "addr:full":"Mississauga ON L4W 1E4",
    "addr:postcode":"l4w 1e4",
    "iso:country":"CA",
    "sg:city":"Mississauga",
    "sg:classifiers":[
        {
            "category":"Health Services",
            "subcategory":"Clinic",
            "type":"Services"
        }
    ],
    "sg:phone":"+1 905 238 2766",
    "sg:postcode":"L4W 1E4",
    "sg:province":"ON",
    "sg:tags":[
        "home"
    ],
    "wof:name":"Manutex Products",
    "wof:placetype":"venue"
},
  "geometry": {"coordinates":[-79.62627410890001,43.6394729614],"type":"Point"}
}