{
  "type": "Feature",
  "properties": {
    "addr:full":"194 Ossington Ave Toronto ON M6J 2Z7",
    "addr:housenumber":"194",
    "addr:postcode":"m6j 2z7",
    "addr:street":"Ossington Ave",
    "iso:country":"CA",
    "sg:address":"194 Ossington Ave",
    "sg:city":"Toronto",
    "sg:classifiers":[
        {
            "category":"Manufacturing",
            "subcategory":"Wood Products",
            "type":"Manufacturing & Wholesale Goods"
        }
    ],
    "sg:phone":"+1 416 538 0890",
    "sg:postcode":"M6J 2Z7",
    "sg:province":"ON",
    "sg:tags":[
        "picture",
        "frame"
    ],
    "wof:name":"Royal Picture Framing Factory",
    "wof:placetype":"venue"
},
  "geometry": {"coordinates":[-79.4206237793,43.6485404968],"type":"Point"}
}