{
  "type": "Feature",
  "properties": {
    "addr:full":"Pelican Narrows SK S0P 0E0",
    "addr:postcode":"s0p 0e0",
    "addr:street":"Pelican Narrows",
    "iso:country":"CA",
    "sg:city":"Pelican Narrows",
    "sg:classifiers":[
        {
            "category":"Local Transit",
            "type":"Transportation"
        }
    ],
    "sg:phone":"+1 306 632 2020",
    "sg:postcode":"S0P 0E0",
    "sg:province":"SK",
    "sg:tags":[
        "rental",
        "airport",
        "charter",
        "leasing",
        "aircraft"
    ],
    "wof:name":"Pelican Narrows Air Svc Ltd",
    "wof:placetype":"venue"
},
  "geometry": {"coordinates":[-102.933891,55.171551],"type":"Point"}
}