{
  "type": "Feature",
  "properties": {
    "addr:full":"355 Rue Lahaie Saint-Eustache QC J7P 3X1",
    "addr:housenumber":"355",
    "addr:postcode":"j7p 3x1",
    "addr:street":"Rue Lahaie",
    "iso:country":"CA",
    "sg:address":"355 Rue Lahaie",
    "sg:city":"Saint-Eustache",
    "sg:classifiers":[
        {
            "category":"Building & Trades",
            "subcategory":"Construction",
            "type":"Services"
        }
    ],
    "sg:phone":"+1 450 473 7525",
    "sg:postcode":"J7P 3X1",
    "sg:province":"QC",
    "sg:tags":[
        "contractor",
        "general"
    ],
    "wof:name":"Construction Andre Drouin Inc",
    "wof:placetype":"venue"
},
  "geometry": {"coordinates":[-73.8941726685,45.5704421997],"type":"Point"}
}