{
  "type": "Feature",
  "properties": {
    "iso:country":"CA",
    "sg:address":"111 Esna Park Dr # 9",
    "sg:city":"Markham",
    "sg:classifiers":[
        {
            "category":"Manufacturing",
            "subcategory":"Tools & Machinery",
            "type":"Manufacturing & Wholesale Goods"
        }
    ],
    "sg:phone":"+1 905 477 8326",
    "sg:postcode":"L3R 1H2",
    "sg:province":"ON",
    "sg:tags":[
        "equipment",
        "hospital",
        "supply"
    ],
    "wof:name":"Home Aid Products",
    "wof:placetype":"venue"
},
  "geometry": {"coordinates":[-79.339935,43.827301],"type":"Point"}
}