{
  "type": "Feature",
  "properties": {
    "addr:full":"114 Av Lafontaine Chibougamau QC G8P 2H5",
    "addr:postcode":"g8p 2h5",
    "addr:street":"114 Av Lafontaine",
    "iso:country":"CA",
    "sg:address":"114 Av Lafontaine",
    "sg:city":"Chibougamau",
    "sg:classifiers":[
        {
            "category":"Personal",
            "subcategory":"Beauty Salon",
            "type":"Services"
        }
    ],
    "sg:phone":"+1 418 748 6314",
    "sg:postcode":"G8P 2H5",
    "sg:province":"QC",
    "wof:name":"Salon DE Coiffure Dalys Enr",
    "wof:placetype":"venue"
},
  "geometry": {"coordinates":[-74.37133799999999,49.912235],"type":"Point"}
}