{
  "type": "Feature",
  "properties": {
    "addr:full":"113 Wiser Rd Corbyville ON K0K 1V0",
    "addr:housenumber":"113",
    "addr:postcode":"k0k 1v0",
    "addr:street":"Wiser Rd",
    "iso:country":"CA",
    "sg:address":"113 Wiser Rd",
    "sg:city":"Corbyville",
    "sg:classifiers":[
        {
            "category":"Social Services",
            "type":"Services"
        }
    ],
    "sg:phone":"+1 613 968 8958",
    "sg:postcode":"K0K 1V0",
    "sg:province":"ON",
    "sg:tags":[
        "organization",
        "welfare"
    ],
    "wof:name":"Corbyville Children's Home Inc",
    "wof:placetype":"venue"
},
  "geometry": {"coordinates":[-77.38832855219999,44.2199783325],"type":"Point"}
}