{
  "type": "Feature",
  "properties": {
    "addr:full":"PO Box 130 L'Ile-Du-Grand-Calumet QC J0X 1J0",
    "addr:housenumber":"po",
    "addr:postcode":"j0x 1j0",
    "addr:street":"Box 130 L'Ile-Du-Grand-Calumet",
    "iso:country":"CA",
    "sg:address":"PO Box 130",
    "sg:city":"L'Ile-Du-Grand-Calumet",
    "sg:classifiers":[
        {
            "category":"Government",
            "subcategory":"Office",
            "type":"Public Place"
        }
    ],
    "sg:phone":"+1 819 648 5965",
    "sg:postcode":"J0X 1J0",
    "sg:province":"QC",
    "sg:tags":[
        "village"
    ],
    "wof:name":"Grand Calumet Secretary",
    "wof:placetype":"venue"
},
  "geometry": {"coordinates":[-76.60980987550001,45.7190589905],"type":"Point"}
}