{
  "type": "Feature",
  "properties": {
    "iso:country":"CA",
    "sg:city":"Toronto",
    "sg:classifiers":[
        {
            "category":"Banks & Credit Unions",
            "subcategory":"Bank",
            "type":"Services"
        }
    ],
    "sg:phone":"+1 416 515 7000",
    "sg:postcode":"M4V 3A1",
    "sg:province":"ON",
    "sg:tags":[
        "company",
        "trust"
    ],
    "wof:name":"Equitable Trust CO",
    "wof:placetype":"venue"
},
  "geometry": {"coordinates":[-79.3956985474,43.6879005432],"type":"Point"}
}