{
  "type": "Feature",
  "properties": {
    "addr:full":"755 West Dr Bathurst NB E2A 6L7",
    "addr:housenumber":"755",
    "addr:postcode":"e2a 6l7",
    "addr:street":"West Dr",
    "iso:country":"CA",
    "sg:address":"755 West Dr",
    "sg:city":"Bathurst",
    "sg:classifiers":[
        {
            "category":"Building & Trades",
            "subcategory":"Construction",
            "type":"Services"
        }
    ],
    "sg:phone":"+1 506 546 5649",
    "sg:postcode":"E2A 6L7",
    "sg:province":"NB",
    "sg:tags":[
        "excavating",
        "contractor"
    ],
    "wof:name":"W M Doucet & Sons Ltd",
    "wof:placetype":"venue"
},
  "geometry": {"coordinates":[-65.675797,47.599068],"type":"Point"}
}