{
  "type": "Feature",
  "properties": {
    "addr:full":"10640 95 St NW Edmonton AB T5H 2C6",
    "addr:housenumber":"10640",
    "addr:postcode":"t5h 2c6",
    "addr:street":"95 St Nw",
    "iso:country":"CA",
    "sg:address":"10640 95 St NW",
    "sg:city":"Edmonton",
    "sg:classifiers":[
        {
            "category":"Building & Trades",
            "subcategory":"Plumbing",
            "type":"Services"
        }
    ],
    "sg:phone":"+1 780 429 0295",
    "sg:postcode":"T5H 2C6",
    "sg:province":"AB",
    "sg:tags":[
        "contractor"
    ],
    "wof:name":"Neumann Plumbing Ltd",
    "wof:placetype":"venue"
},
  "geometry": {"coordinates":[-113.48277282700001,53.552230835],"type":"Point"}
}