{
  "type": "Feature",
  "properties": {
    "iso:country":"CA",
    "sg:address":"350 Park Ave E",
    "sg:city":"Brandon",
    "sg:classifiers":[
        {
            "category":"Retail",
            "subcategory":"Auto Repair",
            "type":"Services"
        }
    ],
    "sg:phone":"+1 204 725 0510",
    "sg:postcode":"R7A 7A7",
    "sg:province":"MB",
    "sg:tags":[
        "fuel",
        "equipment",
        "injection"
    ],
    "wof:name":"Dave Mc Millan Diesel Injctn",
    "wof:placetype":"venue"
},
  "geometry": {"coordinates":[-99.92905426030001,49.8325614929],"type":"Point"}
}