{
  "type": "Feature",
  "properties": {
    "iso:country":"CA",
    "sg:address":"1064 51st Ave E",
    "sg:city":"Vancouver",
    "sg:classifiers":[
        {
            "category":"Retail",
            "subcategory":"Portrait Studio",
            "type":"Services"
        }
    ],
    "sg:phone":"+1 604 322 4822",
    "sg:postcode":"V5X 1E7",
    "sg:province":"BC",
    "sg:tags":[
        "photographer"
    ],
    "wof:name":"Top Hat Photography",
    "wof:placetype":"venue"
},
  "geometry": {"coordinates":[-123.08379364,49.2233963013],"type":"Point"}
}