{
  "type": "Feature",
  "properties": {
    "addr:full":"254 Commercial St North Sydney NS B2A 1B8",
    "addr:housenumber":"254",
    "addr:postcode":"b2a 1b8",
    "addr:street":"Commercial St",
    "iso:country":"CA",
    "sg:address":"254 Commercial St",
    "sg:city":"North Sydney",
    "sg:classifiers":[
        {
            "category":"Professional",
            "subcategory":"Lawyer & Legal Services",
            "type":"Services"
        }
    ],
    "sg:phone":"+1 902 794 8803",
    "sg:postcode":"B2A 1B8",
    "sg:province":"NS",
    "sg:tags":[
        "attorney"
    ],
    "wof:name":"Tobin, Michael A",
    "wof:placetype":"venue"
},
  "geometry": {"coordinates":[-60.24934,46.208649],"type":"Point"}
}