{
  "type": "Feature",
  "properties": {
    "addr:full":"Montreal QC H3M 3A9",
    "addr:postcode":"h3m 3a9",
    "iso:country":"CA",
    "sg:city":"Montreal",
    "sg:classifiers":[
        {
            "category":"Health Services",
            "subcategory":"Doctor",
            "type":"Services"
        }
    ],
    "sg:phone":"+1 514 337 1139",
    "sg:postcode":"H3M 3A9",
    "sg:province":"QC",
    "sg:tags":[
        "ophthalmologist",
        "clinic"
    ],
    "wof:name":"Salem, Jacques",
    "wof:placetype":"venue"
},
  "geometry": {"coordinates":[-73.66134599999999,45.565144],"type":"Point"}
}