{
  "type": "Feature",
  "properties": {
    "addr:full":"1467 Rue Cunard Laval QC H7S 2H8",
    "addr:housenumber":"1467",
    "addr:postcode":"h7s 2h8",
    "addr:street":"Rue Cunard",
    "iso:country":"CA",
    "sg:address":"1467 Rue Cunard",
    "sg:city":"Laval",
    "sg:classifiers":[
        {
            "category":"Recreation",
            "subcategory":"Marina",
            "type":"Entertainment"
        }
    ],
    "sg:phone":"+1 450 668 5400",
    "sg:postcode":"H7S 2H8",
    "sg:province":"QC",
    "sg:tags":[
        "repairing",
        "steam",
        "boat",
        "cleaning"
    ],
    "wof:name":"Auvents Net Quebec",
    "wof:placetype":"venue"
},
  "geometry": {"coordinates":[-73.734573,45.581024],"type":"Point"}
}