{
  "type": "Feature",
  "properties": {
    "addr:full":"Saskatoon SK S7H 5H9",
    "addr:postcode":"s7h 5h9",
    "iso:country":"CA",
    "sg:city":"Saskatoon",
    "sg:classifiers":[
        {
            "category":"Mining & Drilling",
            "type":"Manufacturing & Wholesale Goods"
        }
    ],
    "sg:phone":"+1 306 244 4878",
    "sg:postcode":"S7H 5H9",
    "sg:province":"SK",
    "sg:tags":[
        "development",
        "gas",
        "oil",
        "exploration"
    ],
    "wof:name":"North Rim Exploration Ltd",
    "wof:placetype":"venue"
},
  "geometry": {"coordinates":[-106.59858699999999,52.104458],"type":"Point"}
}