{
  "type": "Feature",
  "properties": {
    "addr:full":"Mississauga ON L5T 1C5",
    "addr:postcode":"l5t 1c5",
    "iso:country":"CA",
    "sg:city":"Mississauga",
    "sg:classifiers":[
        {
            "category":"Manufacturing",
            "subcategory":"Electronics",
            "type":"Manufacturing & Wholesale Goods"
        }
    ],
    "sg:phone":"+1 905 564 2710",
    "sg:postcode":"L5T 1C5",
    "sg:province":"ON",
    "sg:tags":[
        "control",
        "equipment",
        "electronic"
    ],
    "wof:name":"Berlet Electronics Ltd",
    "wof:placetype":"venue"
},
  "geometry": {"coordinates":[-79.649124,43.664822],"type":"Point"}
}