{
  "type": "Feature",
  "properties": {
    "iso:country":"CA",
    "sg:city":"Montreal",
    "sg:classifiers":[
        {
            "category":"Shopping",
            "subcategory":"Jewelry",
            "type":"Retail Goods"
        }
    ],
    "sg:phone":"+1 514 271 2325",
    "sg:postcode":"H2S 2M3",
    "sg:province":"QC",
    "sg:tags":[
        "jeweler"
    ],
    "wof:name":"Boutique Arto",
    "wof:placetype":"venue"
},
  "geometry": {"coordinates":[-73.604858,45.536945],"type":"Point"}
}