{
  "type": "Feature",
  "properties": {
    "iso:country":"CA",
    "sg:address":"70 Mary St",
    "sg:city":"Aurora",
    "sg:classifiers":[
        {
            "category":"Retail",
            "subcategory":"Auto Repair",
            "type":"Services"
        }
    ],
    "sg:phone":"+1 905 727 2192",
    "sg:postcode":"L4G 6C8",
    "sg:province":"ON",
    "sg:tags":[
        "repairing",
        "automobile"
    ],
    "wof:name":"Bondi's Auto Svc Ltd",
    "wof:placetype":"venue"
},
  "geometry": {"coordinates":[-79.453201,43.999893],"type":"Point"}
}