{
  "type": "Feature",
  "properties": {
    "addr:full":"70 Mary St Aurora ON L4G 6C8",
    "addr:housenumber":"70",
    "addr:postcode":"l4g 6c8",
    "addr:street":"Mary St",
    "iso:country":"CA",
    "sg:address":"70 Mary St",
    "sg:city":"Aurora",
    "sg:classifiers":[
        {
            "category":"Retail",
            "subcategory":"Auto Repair",
            "type":"Services"
        }
    ],
    "sg:phone":"+1 905 727 2192",
    "sg:postcode":"L4G 6C8",
    "sg:province":"ON",
    "sg:tags":[
        "repairing",
        "automobile"
    ],
    "wof:name":"Bondi's Auto Svc Ltd",
    "wof:placetype":"venue"
},
  "geometry": {"coordinates":[-79.45320100000001,43.999893],"type":"Point"}
}