{
  "type": "Feature",
  "properties": {
    "addr:full":"117 Conc 18 Apsley ON K0L 1A0",
    "addr:housenumber":"117;18",
    "addr:postcode":"k0l 1a0",
    "addr:street":"Conc",
    "iso:country":"CA",
    "sg:address":"117 Conc 18",
    "sg:city":"Apsley",
    "sg:classifiers":[
        {
            "category":"Autos & Motor Vehicles",
            "subcategory":"Boat Sales",
            "type":"Retail Goods"
        }
    ],
    "sg:phone":"+1 705 656 4707",
    "sg:postcode":"K0L 1A0",
    "sg:province":"ON",
    "sg:tags":[
        "top",
        "upholstery",
        "cover"
    ],
    "wof:name":"Busy Bee Custom Sewing",
    "wof:placetype":"venue"
},
  "geometry": {"coordinates":[-78.0853729248,44.7530212402],"type":"Point"}
}