{
  "type": "Feature",
  "properties": {
    "iso:country":"CA",
    "sg:address":"27 Rue Cross",
    "sg:city":"Ormstown",
    "sg:classifiers":[
        {
            "category":"Home & Garden",
            "subcategory":"Furniture",
            "type":"Retail Goods"
        }
    ],
    "sg:phone":"+1 450 829 2362",
    "sg:postcode":"J0S 1K0",
    "sg:province":"QC",
    "wof:name":"Garage Dandurand Inc",
    "wof:placetype":"venue"
},
  "geometry": {"coordinates":[-73.9951019287,45.1296081543],"type":"Point"}
}