{
  "type": "Feature",
  "properties": {
    "iso:country":"CA",
    "sg:address":"3631 76 Ave NW",
    "sg:city":"Edmonton",
    "sg:classifiers":[
        {
            "category":"Professional",
            "subcategory":"Management & Consulting",
            "type":"Services"
        }
    ],
    "sg:phone":"+1 780 465 5516",
    "sg:postcode":"T6B 2S8",
    "sg:province":"AB",
    "sg:tags":[
        "consultant",
        "industrial",
        "engineer"
    ],
    "wof:name":"Cord Projects Ltd",
    "wof:placetype":"venue"
},
  "geometry": {"coordinates":[-113.397483826,53.5122413635],"type":"Point"}
}