{
  "type": "Feature",
  "properties": {
    "addr:full":"120 Welland Ave St Catharines ON L2R 2N3",
    "addr:housenumber":"120",
    "addr:postcode":"l2r 2n3",
    "addr:street":"Welland Ave",
    "iso:country":"CA",
    "sg:address":"120 Welland Ave",
    "sg:city":"St Catharines",
    "sg:classifiers":[
        {
            "category":"Shopping",
            "subcategory":"Department Store",
            "type":"Retail Goods"
        }
    ],
    "sg:phone":"+1 905 988 5733",
    "sg:postcode":"L2R 2N3",
    "sg:province":"ON",
    "sg:tags":[
        "shop"
    ],
    "wof:name":"Dollar Mart",
    "wof:placetype":"venue"
},
  "geometry": {"coordinates":[-79.245628,43.16367],"type":"Point"}
}