{
  "type": "Feature",
  "properties": {
    "addr:full":"53323 Range Road 232 Sherwood Park AB T8A 4V2",
    "addr:housenumber":"53323",
    "addr:postcode":"t8a 4v2",
    "addr:street":"Range Road 232;Park",
    "iso:country":"CA",
    "sg:address":"53323 Range Road 232",
    "sg:city":"Sherwood Park",
    "sg:classifiers":[
        {
            "category":"Building & Trades",
            "subcategory":"Construction",
            "type":"Services"
        }
    ],
    "sg:phone":"+1 780 472 6969",
    "sg:postcode":"T8A 4V2",
    "sg:province":"AB",
    "sg:tags":[
        "sandblasting",
        "painter"
    ],
    "wof:name":"Dragon Sandblasting & Painting",
    "wof:placetype":"venue"
},
  "geometry": {"coordinates":[-113.295570373,53.5101509094],"type":"Point"}
}