{
  "type": "Feature",
  "properties": {
    "iso:country":"CA",
    "sg:city":"Mississauga",
    "sg:classifiers":[
        {
            "category":"Wholesale",
            "subcategory":"Machinery & Supplies",
            "type":"Manufacturing & Wholesale Goods"
        }
    ],
    "sg:phone":"+1 905 270 3939",
    "sg:postcode":"L5C 1W4",
    "sg:province":"ON",
    "sg:tags":[
        "contractor"
    ],
    "wof:name":"Mississauga Equipment Garage",
    "wof:placetype":"venue"
},
  "geometry": {"coordinates":[-79.647331,43.570652],"type":"Point"}
}