{
  "type": "Feature",
  "properties": {
    "addr:full":"214 Mansel Hill Rd Cobden ON K0J 1K0",
    "addr:housenumber":"214",
    "addr:postcode":"k0j 1k0",
    "addr:street":"Mansel Hill Rd",
    "iso:country":"CA",
    "sg:address":"214 Mansel Hill Rd",
    "sg:city":"Cobden",
    "sg:classifiers":[
        {
            "category":"Wholesale",
            "subcategory":"Machinery & Supplies",
            "type":"Manufacturing & Wholesale Goods"
        }
    ],
    "sg:phone":"+1 613 646 7184",
    "sg:postcode":"K0J 1K0",
    "sg:province":"ON",
    "sg:tags":[
        "research"
    ],
    "wof:name":"Engine Research",
    "wof:placetype":"venue"
},
  "geometry": {"coordinates":[-76.879982,45.627075],"type":"Point"}
}