{
  "type": "Feature",
  "properties": {
    "addr:full":"3475 Sussex St Abbotsford BC V2S 5A7",
    "addr:housenumber":"3475",
    "addr:postcode":"v2s 5a7",
    "addr:street":"Sussex St",
    "iso:country":"CA",
    "sg:address":"3475 Sussex St",
    "sg:city":"Abbotsford",
    "sg:classifiers":[
        {
            "category":"Wholesale",
            "subcategory":"Non-durable Goods",
            "type":"Manufacturing & Wholesale Goods"
        }
    ],
    "sg:phone":"+1 604 853 7060",
    "sg:postcode":"V2S 5A7",
    "sg:province":"BC",
    "wof:name":"Chris-Cad Designs Ltd",
    "wof:placetype":"venue"
},
  "geometry": {"coordinates":[-122.263267517,49.065032959],"type":"Point"}
}