{
  "type": "Feature",
  "properties": {
    "addr:full":"Red Rock ON P0T 2P0",
    "addr:postcode":"p0t 2p0",
    "iso:country":"CA",
    "sg:city":"Red Rock",
    "sg:classifiers":[
        {
            "category":"Professional",
            "subcategory":"Lawyer & Legal Services",
            "type":"Services"
        }
    ],
    "sg:phone":"+1 807 886 2167",
    "sg:postcode":"P0T 2P0",
    "sg:province":"ON",
    "sg:tags":[
        "attorney"
    ],
    "wof:name":"Brothers, Kevin W",
    "wof:placetype":"venue"
},
  "geometry": {"coordinates":[-88.25862100000001,48.939835],"type":"Point"}
}