{
  "type": "Feature",
  "properties": {
    "iso:country":"CA",
    "sg:address":"360 Algonquin Blvd E",
    "sg:city":"Timmins",
    "sg:classifiers":[
        {
            "category":"Autos & Motor Vehicles",
            "subcategory":"Motorcycle Sales",
            "type":"Retail Goods"
        }
    ],
    "sg:phone":"+1 705 268 9191",
    "sg:postcode":"P4N 1B6",
    "sg:province":"ON",
    "sg:tags":[
        "all",
        "terrain",
        "dealer",
        "boat"
    ],
    "wof:name":"J & B Cycle & Marine",
    "wof:placetype":"venue"
},
  "geometry": {"coordinates":[-81.3258361816,48.4762496948],"type":"Point"}
}