{
  "type": "Feature",
  "properties": {
    "iso:country":"CA",
    "sg:address":"4084 Rue Sainte-Catherine O",
    "sg:city":"Westmount",
    "sg:classifiers":[
        {
            "category":"Banks & Credit Unions",
            "subcategory":"Bank",
            "type":"Services"
        }
    ],
    "sg:phone":"+1 514 394 5555",
    "sg:postcode":"H3Z 1P2",
    "sg:province":"QC",
    "wof:name":"Banque National Du Canada",
    "wof:placetype":"venue"
},
  "geometry": {"coordinates":[-73.586052,45.487801],"type":"Point"}
}