{
  "type": "Feature",
  "properties": {
    "iso:country":"CA",
    "sg:city":"Victoria",
    "sg:classifiers":[
        {
            "category":"Banks & Credit Unions",
            "subcategory":"Investment Brokerage",
            "type":"Services"
        }
    ],
    "sg:phone":"+1 250 418 8770",
    "sg:postcode":"V8W 1R8",
    "sg:province":"BC",
    "sg:tags":[
        "consultant",
        "planning",
        "financial"
    ],
    "wof:name":"J R Brennan Financial Svc",
    "wof:placetype":"venue"
},
  "geometry": {"coordinates":[-123.363624573,48.4292602539],"type":"Point"}
}