{
  "type": "Feature",
  "properties": {
    "addr:full":"593 Rue Du Palais Saint-Jerome QC J7Z 1Y8",
    "addr:housenumber":"593",
    "addr:postcode":"j7z 1y8",
    "addr:street":"Rue Du Palais Saint-Jerome",
    "iso:country":"CA",
    "sg:address":"593 Rue Du Palais",
    "sg:city":"Saint-Jerome",
    "sg:classifiers":[
        {
            "category":"Organizations",
            "subcategory":"Religious Organization",
            "type":"Services"
        }
    ],
    "sg:phone":"+1 450 438 1094",
    "sg:postcode":"J7Z 1Y8",
    "sg:province":"QC",
    "sg:tags":[
        "home",
        "retirement",
        "community",
        "retreat",
        "house"
    ],
    "wof:name":"Residence Marie-Lou",
    "wof:placetype":"venue"
},
  "geometry": {"coordinates":[-73.990562439,45.777141571],"type":"Point"}
}