{
  "type": "Feature",
  "properties": {
    "addr:full":"171 Buchanan Dr Charlottetown PE C1E 2E4",
    "addr:housenumber":"171",
    "addr:postcode":"c1e 2e4",
    "addr:street":"Buchanan Dr",
    "iso:country":"CA",
    "sg:address":"171 Buchanan Dr",
    "sg:city":"Charlottetown",
    "sg:classifiers":[
        {
            "category":"Shopping",
            "subcategory":"Gifts & Souvenirs",
            "type":"Retail Goods"
        }
    ],
    "sg:phone":"+1 902 892 4770",
    "sg:postcode":"C1E 2E4",
    "sg:province":"PE",
    "sg:tags":[
        "shop"
    ],
    "wof:name":"English Butler",
    "wof:placetype":"venue"
},
  "geometry": {"coordinates":[-63.150192,46.263756],"type":"Point"}
}