{
  "type": "Feature",
  "properties": {
    "addr:full":"362 Flagstone Terr Scarborough ON M1C 2X6",
    "addr:housenumber":"362",
    "addr:postcode":"m1c 2x6",
    "addr:street":"Flagstone Terr",
    "iso:country":"CA",
    "sg:address":"362 Flagstone Terr",
    "sg:city":"Scarborough",
    "sg:classifiers":[
        {
            "category":"Building & Trades",
            "subcategory":"Plumbing",
            "type":"Services"
        }
    ],
    "sg:phone":"+1 416 281 8767",
    "sg:postcode":"M1C 2X6",
    "sg:province":"ON",
    "sg:tags":[
        "heating",
        "contractor"
    ],
    "wof:name":"J P Heating & Mechanical Ltd",
    "wof:placetype":"venue"
},
  "geometry": {"coordinates":[-79.1345672607,43.7934150696],"type":"Point"}
}