{
  "type": "Feature",
  "properties": {
    "addr:full":"292 Leamon St Waterford ON N0E 1Y0",
    "addr:housenumber":"292",
    "addr:postcode":"n0e 1y0",
    "addr:street":"Leamon St",
    "iso:country":"CA",
    "sg:address":"292 Leamon St",
    "sg:city":"Waterford",
    "sg:classifiers":[
        {
            "category":"Home & Garden",
            "subcategory":"Building Materials",
            "type":"Retail Goods"
        }
    ],
    "sg:phone":"+1 519 443 8613",
    "sg:postcode":"N0E 1Y0",
    "sg:province":"ON",
    "sg:tags":[
        "lumber"
    ],
    "wof:name":"Riddoch Lumber Ltd",
    "wof:placetype":"venue"
},
  "geometry": {"coordinates":[-80.2892150879,42.9255104065],"type":"Point"}
}