{
  "type": "Feature",
  "properties": {
    "addr:full":"6291 Camgreen Cir Mississauga ON L5N 4N5",
    "addr:housenumber":"6291",
    "addr:postcode":"l5n 4n5",
    "addr:street":"Camgreen Cir",
    "iso:country":"CA",
    "sg:address":"6291 Camgreen Cir",
    "sg:city":"Mississauga",
    "sg:classifiers":[
        {
            "category":"Professional",
            "subcategory":"Employment Agencies",
            "type":"Services"
        }
    ],
    "sg:phone":"+1 416 626 2444",
    "sg:postcode":"L5N 4N5",
    "sg:province":"ON",
    "sg:tags":[
        "consultant",
        "search",
        "executive"
    ],
    "wof:name":"Searchsmiths Inc",
    "wof:placetype":"venue"
},
  "geometry": {"coordinates":[-79.713776,43.596062],"type":"Point"}
}