{
  "type": "Feature",
  "properties": {
    "addr:full":"14435 116 Ave NW Edmonton AB T5M 3E8",
    "addr:housenumber":"14435",
    "addr:postcode":"t5m 3e8",
    "addr:street":"116 Ave Nw",
    "iso:country":"CA",
    "sg:address":"14435 116 Ave NW",
    "sg:city":"Edmonton",
    "sg:classifiers":[
        {
            "category":"Mining & Drilling",
            "type":"Manufacturing & Wholesale Goods"
        }
    ],
    "sg:phone":"+1 780 455 2176",
    "sg:postcode":"T5M 3E8",
    "sg:province":"AB",
    "sg:tags":[
        "field",
        "oil",
        "supply"
    ],
    "wof:name":"Weatherford Products",
    "wof:placetype":"venue"
},
  "geometry": {"coordinates":[-113.56930542000001,53.5676612854],"type":"Point"}
}