{
  "type": "Feature",
  "properties": {
    "addr:full":"132 LA Ronge Ave LA Ronge SK S0J 1L0",
    "addr:housenumber":"132",
    "addr:postcode":"s0j 1l0",
    "addr:street":"La Ronge Ave",
    "iso:country":"CA",
    "sg:address":"132 LA Ronge Ave",
    "sg:city":"LA Ronge",
    "sg:classifiers":[
        {
            "category":"Professional",
            "subcategory":"Art Services",
            "type":"Services"
        }
    ],
    "sg:phone":"+1 306 425 1313",
    "sg:postcode":"S0J 1L0",
    "sg:province":"SK",
    "sg:tags":[
        "graphic",
        "designer"
    ],
    "wof:name":"Cre8Iv Communications",
    "wof:placetype":"venue"
},
  "geometry": {"coordinates":[-105.295326,55.112495],"type":"Point"}
}