{
  "type": "Feature",
  "properties": {
    "addr:full":"15 Mallard Pl Chatham ON N7L 4A5",
    "addr:housenumber":"15",
    "addr:postcode":"n7l 4a5",
    "addr:street":"Mallard Pl",
    "iso:country":"CA",
    "sg:address":"15 Mallard Pl",
    "sg:city":"Chatham",
    "sg:classifiers":[
        {
            "category":"Building & Trades",
            "subcategory":"Electrical",
            "type":"Services"
        }
    ],
    "sg:phone":"+1 519 352 6617",
    "sg:postcode":"N7L 4A5",
    "sg:province":"ON",
    "sg:tags":[
        "electric",
        "contractor"
    ],
    "wof:name":"Emery Electrical & Electronic",
    "wof:placetype":"venue"
},
  "geometry": {"coordinates":[-82.2177276611,42.4002456665],"type":"Point"}
}