{
  "type": "Feature",
  "properties": {
    "addr:full":"576 Broadway St Belle River ON N0R 1A0",
    "addr:housenumber":"576",
    "addr:postcode":"n0r 1a0",
    "addr:street":"Broadway St",
    "iso:country":"CA",
    "sg:address":"576 Broadway St",
    "sg:city":"Belle River",
    "sg:classifiers":[
        {
            "category":"Retail",
            "subcategory":"Veterinary Services",
            "type":"Services"
        }
    ],
    "sg:phone":"+1 519 728 3221",
    "sg:postcode":"N0R 1A0",
    "sg:province":"ON",
    "sg:tags":[
        "veterinarian"
    ],
    "wof:name":"Belle River Animal Clinic",
    "wof:placetype":"venue"
},
  "geometry": {"coordinates":[-82.709717,42.293888],"type":"Point"}
}