{
  "type": "Feature",
  "properties": {
    "addr:full":"1117 Salmon River Rd Truro NS B2N 5B2",
    "addr:housenumber":"1117",
    "addr:postcode":"b2n 5b2",
    "addr:street":"Salmon River Rd",
    "iso:country":"CA",
    "sg:address":"1117 Salmon River Rd",
    "sg:city":"Truro",
    "sg:classifiers":[
        {
            "category":"Retail",
            "subcategory":"Auto Repair",
            "type":"Services"
        }
    ],
    "sg:phone":"+1 902 895 2539",
    "sg:postcode":"B2N 5B2",
    "sg:province":"NS",
    "sg:tags":[
        "body",
        "automobile",
        "painting"
    ],
    "wof:name":"Salmon River Collision Repair",
    "wof:placetype":"venue"
},
  "geometry": {"coordinates":[-63.28904,45.36602],"type":"Point"}
}