{
  "type": "Feature",
  "properties": {
    "iso:country":"CA",
    "sg:address":"209 Lowe St",
    "sg:city":"Whitehorse",
    "sg:classifiers":[
        {
            "category":"Professional",
            "subcategory":"Management & Consulting",
            "type":"Services"
        }
    ],
    "sg:phone":"+1 867 633 3978",
    "sg:postcode":"Y1A 1W5",
    "sg:province":"YT",
    "sg:tags":[
        "consultant",
        "business"
    ],
    "wof:name":"Clarity Job Analysis Inc",
    "wof:placetype":"venue"
},
  "geometry": {"coordinates":[-135.04901123100001,60.7148895264],"type":"Point"}
}