{
  "type": "Feature",
  "properties": {
    "iso:country":"CA",
    "sg:address":"1751 Rue Nobel",
    "sg:city":"Sainte-Julie",
    "sg:classifiers":[
        {
            "category":"Retail",
            "subcategory":"Repair Shop",
            "type":"Services"
        }
    ],
    "sg:phone":"+1 450 922 2022",
    "sg:postcode":"J3E 1Z6",
    "sg:province":"QC",
    "sg:tags":[
        "welding"
    ],
    "wof:name":"Gepay Inc",
    "wof:placetype":"venue"
},
  "geometry": {"coordinates":[-73.319519043,45.5808677673],"type":"Point"}
}