{
  "type": "Feature",
  "properties": {
    "addr:full":"291 Lipton St Winnipeg MB R3G 2H2",
    "addr:housenumber":"291",
    "addr:postcode":"r3g 2h2",
    "addr:street":"Lipton St",
    "iso:country":"CA",
    "sg:address":"291 Lipton St",
    "sg:city":"Winnipeg",
    "sg:classifiers":[
        {
            "category":"Building & Trades",
            "subcategory":"Construction",
            "type":"Services"
        }
    ],
    "sg:phone":"+1 204 772 3700",
    "sg:postcode":"R3G 2H2",
    "sg:province":"MB",
    "sg:tags":[
        "painter"
    ],
    "wof:name":"Creative Horizons",
    "wof:placetype":"venue"
},
  "geometry": {"coordinates":[-97.17334747309999,49.8862457275],"type":"Point"}
}