{
  "type": "Feature",
  "properties": {
    "addr:full":"200 Beaver St Ignace ON P0T 1T0",
    "addr:housenumber":"200",
    "addr:postcode":"p0t 1t0",
    "addr:street":"Beaver St",
    "iso:country":"CA",
    "sg:address":"200 Beaver St",
    "sg:city":"Ignace",
    "sg:classifiers":[
        {
            "category":"Arena",
            "subcategory":"Sports Club",
            "type":"Entertainment"
        }
    ],
    "sg:phone":"+1 807 934 2990",
    "sg:postcode":"P0T 1T0",
    "sg:province":"ON",
    "sg:tags":[
        "athletic",
        "fields",
        "stadium",
        "government"
    ],
    "wof:name":"Ignace Arena",
    "wof:placetype":"venue"
},
  "geometry": {"coordinates":[-91.6723480225,49.417678833],"type":"Point"}
}