{
  "type": "Feature",
  "properties": {
    "addr:full":"206 Woodworth Ave E Kenton MB R0M 0Z0",
    "addr:housenumber":"206",
    "addr:postcode":"r0m 0z0",
    "addr:street":"Woodworth Ave E",
    "iso:country":"CA",
    "sg:address":"206 Woodworth Ave E",
    "sg:city":"Kenton",
    "sg:classifiers":[
        {
            "category":"Autos & Motor Vehicles",
            "subcategory":"Automobile Sales",
            "type":"Retail Goods"
        }
    ],
    "sg:phone":"+1 204 838 2373",
    "sg:postcode":"R0M 0Z0",
    "sg:province":"MB",
    "sg:tags":[
        "car",
        "dealer"
    ],
    "wof:name":"Woodworth Dodge Chrysler Ltd",
    "wof:placetype":"venue"
},
  "geometry": {"coordinates":[-100.61486053500001,49.9876899719],"type":"Point"}
}