{
  "type": "Feature",
  "properties": {
    "addr:full":"6801 Aut Transcanadienne Pointe-Claire QC H9R 5J2",
    "addr:postcode":"6801;h9r 5j2",
    "addr:street":"Transcanadienne",
    "iso:country":"CA",
    "sg:address":"6801 Aut Transcanadienne",
    "sg:city":"Pointe-Claire",
    "sg:classifiers":[
        {
            "category":"Shopping",
            "subcategory":"Hobbies, Toys, & Games",
            "type":"Retail Goods"
        }
    ],
    "sg:phone":"+1 514 630 4886",
    "sg:postcode":"H9R 5J2",
    "sg:province":"QC",
    "wof:name":"Tour DE Jeux",
    "wof:placetype":"venue"
},
  "geometry": {"coordinates":[-73.838218689,45.4578323364],"type":"Point"}
}