{
  "type": "Feature",
  "properties": {
    "addr:full":"70 Picasso Dr Ottawa ON K1G 5S7",
    "addr:housenumber":"70",
    "addr:postcode":"k1g 5s7",
    "addr:street":"Picasso Dr",
    "iso:country":"CA",
    "sg:address":"70 Picasso Dr",
    "sg:city":"Ottawa",
    "sg:classifiers":[
        {
            "category":"Professional",
            "subcategory":"Management & Consulting",
            "type":"Services"
        }
    ],
    "sg:phone":"+1 613 738 1117",
    "sg:postcode":"K1G 5S7",
    "sg:province":"ON",
    "sg:tags":[
        "consultant",
        "business"
    ],
    "wof:name":"Cathro Kantor & Assoc",
    "wof:placetype":"venue"
},
  "geometry": {"coordinates":[-75.606934,45.371964],"type":"Point"}
}