{
  "type": "Feature",
  "properties": {
    "addr:full":"554 Maclellands Brook Rd New Glasgow NS B2H 5C5",
    "addr:housenumber":"554",
    "addr:postcode":"b2h 5c5",
    "addr:street":"Maclellands Brook Rd",
    "iso:country":"CA",
    "sg:address":"554 Maclellands Brook Rd",
    "sg:city":"New Glasgow",
    "sg:classifiers":[
        {
            "category":"Retail",
            "subcategory":"Auto Repair",
            "type":"Services"
        }
    ],
    "sg:phone":"+1 902 396 1616",
    "sg:postcode":"B2H 5C5",
    "sg:province":"NS",
    "sg:tags":[
        "wrecker"
    ],
    "wof:name":"Tri-County Towing",
    "wof:placetype":"venue"
},
  "geometry": {"coordinates":[-62.643414,45.591839],"type":"Point"}
}