{
  "type": "Feature",
  "properties": {
    "iso:country":"CA",
    "sg:address":"109 3rd Ave W",
    "sg:city":"Melville",
    "sg:classifiers":[
        {
            "category":"Restaurant",
            "type":"Food & Drink"
        }
    ],
    "sg:phone":"+1 306 728 3966",
    "sg:postcode":"S0A 2P0",
    "sg:province":"SK",
    "sg:tags":[
        "parlor",
        "ice",
        "cream"
    ],
    "wof:name":"Dairy Queen",
    "wof:placetype":"venue"
},
  "geometry": {"coordinates":[-102.81609344500001,50.9311256409],"type":"Point"}
}