{
  "type": "Feature",
  "properties": {
    "iso:country":"CA",
    "sg:address":"12782 80 Ave",
    "sg:city":"Surrey",
    "sg:classifiers":[
        {
            "category":"Wholesale",
            "subcategory":"Machinery & Supplies",
            "type":"Manufacturing & Wholesale Goods"
        }
    ],
    "sg:phone":"+1 604 590 3101",
    "sg:postcode":"V3W 3A7",
    "sg:province":"BC",
    "sg:tags":[
        "equipment",
        "strapping"
    ],
    "wof:name":"Gerrard-Ovalstrapping",
    "wof:placetype":"venue"
},
  "geometry": {"coordinates":[-122.868652344,49.148059845],"type":"Point"}
}