{
  "type": "Feature",
  "properties": {
    "addr:full":"38 Queen St S Tottenham ON L0G 1W0",
    "addr:housenumber":"38",
    "addr:postcode":"l0g 1w0",
    "addr:street":"Queen St S Tottenham",
    "iso:country":"CA",
    "sg:address":"38 Queen St S",
    "sg:city":"Tottenham",
    "sg:classifiers":[
        {
            "category":"Professional",
            "subcategory":"Business Services",
            "type":"Services"
        }
    ],
    "sg:phone":"+1 905 936 9090",
    "sg:postcode":"L0G 1W0",
    "sg:province":"ON",
    "sg:tags":[
        "interior",
        "consultant",
        "design",
        "decorator"
    ],
    "wof:name":"Adm Design",
    "wof:placetype":"venue"
},
  "geometry": {"coordinates":[-79.8054428101,44.0207901001],"type":"Point"}
}