{
  "type": "Feature",
  "properties": {
    "iso:country":"CA",
    "sg:city":"London",
    "sg:classifiers":[
        {
            "category":"Restaurant",
            "type":"Food & Drink"
        }
    ],
    "sg:phone":"+1 519 649 7688",
    "sg:postcode":"N6J 4K2",
    "sg:province":"ON",
    "wof:name":"Mustang Sally's",
    "wof:placetype":"venue"
},
  "geometry": {"coordinates":[-81.260696,42.947445],"type":"Point"}
}