{
  "type": "Feature",
  "properties": {
    "addr:full":"257 Dundas St E Trenton ON K8V 1M1",
    "addr:housenumber":"257",
    "addr:postcode":"k8v 1m1",
    "addr:street":"Dundas St E",
    "iso:country":"CA",
    "sg:address":"257 Dundas St E",
    "sg:city":"Trenton",
    "sg:classifiers":[
        {
            "category":"Shopping",
            "subcategory":"Used Merchandise",
            "type":"Retail Goods"
        }
    ],
    "sg:phone":"+1 613 392 2292",
    "sg:postcode":"K8V 1M1",
    "sg:province":"ON",
    "sg:tags":[
        "second",
        "pawnbroker",
        "store",
        "hand"
    ],
    "wof:name":"Buy & Sell Shop",
    "wof:placetype":"venue"
},
  "geometry": {"coordinates":[-77.55862399999999,44.104542],"type":"Point"}
}