{
  "type": "Feature",
  "properties": {
    "addr:full":"43 Kimberley Ave Toronto ON M4E 2Z4",
    "addr:housenumber":"43",
    "addr:postcode":"m4e 2z4",
    "addr:street":"Kimberley Ave",
    "iso:country":"CA",
    "sg:address":"43 Kimberley Ave",
    "sg:city":"Toronto",
    "sg:classifiers":[
        {
            "category":"Organizations",
            "subcategory":"Religious Organization",
            "type":"Services"
        }
    ],
    "sg:phone":"+1 416 699 6512",
    "sg:postcode":"M4E 2Z4",
    "sg:province":"ON",
    "sg:tags":[
        "church"
    ],
    "wof:name":"St Saviour's Church",
    "wof:placetype":"venue"
},
  "geometry": {"coordinates":[-79.297905,43.68272],"type":"Point"}
}