{
  "type": "Feature",
  "properties": {
    "iso:country":"CA",
    "sg:city":"London",
    "sg:classifiers":[
        {
            "category":"Personal",
            "subcategory":"Beauty Salon",
            "type":"Services"
        }
    ],
    "sg:phone":"+1 519 850 6262",
    "sg:postcode":"N5Y 4J8",
    "sg:province":"ON",
    "wof:name":"Glamour Cuts",
    "wof:placetype":"venue"
},
  "geometry": {"coordinates":[-81.24192810060001,43.0123023987],"type":"Point"}
}