{
  "type": "Feature",
  "properties": {
    "addr:full":"12510 75 Ave Surrey BC V3W 0R5",
    "addr:housenumber":"12510",
    "addr:postcode":"v3w 0r5",
    "addr:street":"75 Ave",
    "iso:country":"CA",
    "sg:address":"12510 75 Ave",
    "sg:city":"Surrey",
    "sg:classifiers":[
        {
            "category":"Personal",
            "subcategory":"Barber",
            "type":"Services"
        }
    ],
    "sg:phone":"+1 604 572 9942",
    "sg:postcode":"V3W 0R5",
    "sg:province":"BC",
    "wof:name":"Haji Haircut",
    "wof:placetype":"venue"
},
  "geometry": {"coordinates":[-122.875160217,49.1393203735],"type":"Point"}
}