{
  "type": "Feature",
  "properties": {
    "addr:full":"4000 Imperial St Burnaby BC V5J 1A4",
    "addr:housenumber":"4000",
    "addr:postcode":"v5j 1a4",
    "addr:street":"Imperial St",
    "iso:country":"CA",
    "sg:address":"4000 Imperial St",
    "sg:city":"Burnaby",
    "sg:classifiers":[
        {
            "category":"Real Estate",
            "subcategory":"Developer",
            "type":"Services"
        }
    ],
    "sg:phone":"+1 604 435 6688",
    "sg:postcode":"V5J 1A4",
    "sg:province":"BC",
    "sg:tags":[
        "planning",
        "cemetery"
    ],
    "wof:name":"Ocean View Burial Park & Mslm",
    "wof:placetype":"venue"
},
  "geometry": {"coordinates":[-123.01259613000001,49.2219696045],"type":"Point"}
}