{
  "type": "Feature",
  "properties": {
    "addr:full":"777 York Blvd Hamilton ON L8R 2A4",
    "addr:housenumber":"777",
    "addr:postcode":"l8r 2a4",
    "addr:street":"York Blvd",
    "iso:country":"CA",
    "sg:address":"777 York Blvd",
    "sg:city":"Hamilton",
    "sg:classifiers":[
        {
            "category":"Real Estate",
            "subcategory":"Developer",
            "type":"Services"
        }
    ],
    "sg:phone":"+1 905 546 4704",
    "sg:postcode":"L8R 2A4",
    "sg:province":"ON",
    "sg:tags":[
        "cemetery"
    ],
    "wof:name":"Hamilton Municipal Cemeteries",
    "wof:placetype":"venue"
},
  "geometry": {"coordinates":[-79.8868484497,43.2715301514],"type":"Point"}
}