{
  "type": "Feature",
  "properties": {
    "iso:country":"CA",
    "sg:address":"2628 Ch Bellerive",
    "sg:city":"Carignan",
    "sg:classifiers":[
        {
            "category":"Recreation",
            "type":"Entertainment"
        }
    ],
    "sg:phone":"+1 450 447 1322",
    "sg:postcode":"J3L 4J9",
    "sg:province":"QC",
    "sg:tags":[
        "stable"
    ],
    "wof:name":"Centre Hippique Monteregie Inc",
    "wof:placetype":"venue"
},
  "geometry": {"coordinates":[-73.306022644,45.4619979858],"type":"Point"}
}