{
  "type": "Feature",
  "properties": {
    "iso:country":"CA",
    "sg:city":"Vaudreuil-Dorion",
    "sg:classifiers":[
        {
            "category":"Government",
            "subcategory":"Office",
            "type":"Public Place"
        }
    ],
    "sg:phone":"+1 450 455 5753",
    "sg:postcode":"J7V 2N1",
    "sg:province":"QC",
    "sg:tags":[
        "village"
    ],
    "wof:name":"Mrc DE Vaudreuil-Soulanges",
    "wof:placetype":"venue"
},
  "geometry": {"coordinates":[-74.0354003906,45.4049301147],"type":"Point"}
}