{
  "type": "Feature",
  "properties": {
    "addr:full":"Medicine Hat AB T1A 2S8",
    "addr:postcode":"t1a 2s8",
    "iso:country":"CA",
    "sg:city":"Medicine Hat",
    "sg:classifiers":[
        {
            "category":"Professional",
            "subcategory":"Lawyer & Legal Services",
            "type":"Services"
        }
    ],
    "sg:phone":"+1 403 527 4411",
    "sg:postcode":"T1A 2S8",
    "sg:province":"AB",
    "sg:tags":[
        "attorney"
    ],
    "wof:name":"Dolan, Michael J",
    "wof:placetype":"venue"
},
  "geometry": {"coordinates":[-110.674538,50.038166],"type":"Point"}
}