{
  "type": "Feature",
  "properties": {
    "addr:full":"1916 Mersea Rd 3 Leamington ON N8H 3V7",
    "addr:housenumber":"1916",
    "addr:postcode":"n8h 3v7",
    "addr:street":"Mersea Rd 3",
    "iso:country":"CA",
    "sg:address":"1916 Mersea Rd 3",
    "sg:city":"Leamington",
    "sg:classifiers":[
        {
            "category":"Manufacturing",
            "subcategory":"Tools & Machinery",
            "type":"Manufacturing & Wholesale Goods"
        }
    ],
    "sg:phone":"+1 519 255 8484",
    "sg:postcode":"N8H 3V7",
    "sg:province":"ON",
    "sg:tags":[
        "mold"
    ],
    "wof:name":"B & S Custom Metal Polishing",
    "wof:placetype":"venue"
},
  "geometry": {"coordinates":[-82.506927,42.055653],"type":"Point"}
}