{
  "type": "Feature",
  "properties": {
    "addr:full":"700 Rte DE L'Eglise Saint-Jean-Port-Joli QC G0R 3G0",
    "addr:housenumber":"700",
    "addr:postcode":"g0r 3g0",
    "addr:street":"Rte De L'Eglise",
    "iso:country":"CA",
    "sg:address":"700 Rte DE L'Eglise",
    "sg:city":"Saint-Jean-Port-Joli",
    "sg:classifiers":[
        {
            "category":"Restaurant",
            "type":"Food & Drink"
        }
    ],
    "sg:phone":"+1 418 598 6240",
    "sg:postcode":"G0R 3G0",
    "sg:province":"QC",
    "wof:name":"Restaurant Normandin",
    "wof:placetype":"venue"
},
  "geometry": {"coordinates":[-70.26676940919999,47.2121009827],"type":"Point"}
}