{
  "type": "Feature",
  "properties": {
    "addr:full":"Scarborough ON M1H 3C2",
    "addr:postcode":"m1h 3c2",
    "iso:country":"CA",
    "sg:city":"Scarborough",
    "sg:classifiers":[
        {
            "category":"Health Services",
            "subcategory":"Podiatrist",
            "type":"Services"
        }
    ],
    "sg:phone":"+1 416 289 9886",
    "sg:postcode":"M1H 3C2",
    "sg:province":"ON",
    "wof:name":"Scarborough Podiatry Clinic",
    "wof:placetype":"venue"
},
  "geometry": {"coordinates":[-79.2403640747,43.7564735413],"type":"Point"}
}