{
  "type": "Feature",
  "properties": {
    "addr:full":"1017 Railway Ave Lipton SK S0G 3B0",
    "addr:housenumber":"1017",
    "addr:postcode":"s0g 3b0",
    "addr:street":"Railway Ave",
    "iso:country":"CA",
    "sg:address":"1017 Railway Ave",
    "sg:city":"Lipton",
    "sg:classifiers":[
        {
            "category":"Real Estate",
            "subcategory":"Real Estate Agent",
            "type":"Services"
        }
    ],
    "sg:phone":"+1 306 336 2333",
    "sg:postcode":"S0G 3B0",
    "sg:province":"SK",
    "sg:tags":[
        "cooperative"
    ],
    "wof:name":"Lipton CO-Operative Assoc Ltd",
    "wof:placetype":"venue"
},
  "geometry": {"coordinates":[-103.849358,50.902802],"type":"Point"}
}