{
  "type": "Feature",
  "properties": {
    "addr:full":"1 Rue Saint-Alexandre Gatineau QC J8V 1A8",
    "addr:housenumber":"1",
    "addr:postcode":"j8v 1a8",
    "addr:street":"Rue Saint-Alexandre",
    "iso:country":"CA",
    "sg:address":"1 Rue Saint-Alexandre",
    "sg:city":"Gatineau",
    "sg:classifiers":[
        {
            "category":"Education",
            "subcategory":"School",
            "type":"Public Place"
        }
    ],
    "sg:phone":"+1 819 561 3313",
    "sg:postcode":"J8V 1A8",
    "sg:province":"QC",
    "wof:name":"Masse Ecole",
    "wof:placetype":"venue"
},
  "geometry": {"coordinates":[-75.7537078857,45.4939613342],"type":"Point"}
}