{
  "type": "Feature",
  "properties": {
    "addr:full":"Plaster Rock NB E7G 2C6",
    "addr:postcode":"e7g 2c6",
    "iso:country":"CA",
    "sg:city":"Plaster Rock",
    "sg:classifiers":[
        {
            "category":"Education",
            "subcategory":"Library",
            "type":"Public Place"
        }
    ],
    "sg:phone":"+1 506 356 6018",
    "sg:postcode":"E7G 2C6",
    "sg:province":"NB",
    "wof:name":"Plaster Rock Public Schl Lbry",
    "wof:placetype":"venue"
},
  "geometry": {"coordinates":[-67.39534,46.896988],"type":"Point"}
}