{
  "type": "Feature",
  "properties": {
    "iso:country":"CA",
    "sg:city":"Salaberry-DE-Valleyfield",
    "sg:classifiers":[
        {
            "category":"Professional",
            "subcategory":"Detective & Security Services",
            "type":"Services"
        }
    ],
    "sg:phone":"+1 450 377 3008",
    "sg:postcode":"J6T 3C6",
    "sg:province":"QC",
    "sg:tags":[
        "guard",
        "patrol"
    ],
    "wof:name":"Ipas Inc",
    "wof:placetype":"venue"
},
  "geometry": {"coordinates":[-74.1177978516,45.2424278259],"type":"Point"}
}