{
  "type": "Feature",
  "properties": {
    "addr:full":"Waterloo QC J0E 2N0",
    "addr:postcode":"j0e 2n0",
    "iso:country":"CA",
    "sg:city":"Waterloo",
    "sg:classifiers":[
        {
            "category":"Building & Trades",
            "subcategory":"Construction",
            "type":"Services"
        }
    ],
    "sg:phone":"+1 450 539 4215",
    "sg:postcode":"J0E 2N0",
    "sg:province":"QC",
    "sg:tags":[
        "consultant",
        "land",
        "general",
        "contractor"
    ],
    "wof:name":"Chambourg-Sur-Le-Lac Domaine",
    "wof:placetype":"venue"
},
  "geometry": {"coordinates":[-72.52428399999999,45.328606],"type":"Point"}
}