{
  "type": "Feature",
  "properties": {
    "addr:full":"156 Clarence St Brantford ON N3T 2V8",
    "addr:housenumber":"156",
    "addr:postcode":"n3t 2v8",
    "addr:street":"Clarence St",
    "iso:country":"CA",
    "sg:address":"156 Clarence St",
    "sg:city":"Brantford",
    "sg:classifiers":[
        {
            "category":"Autos & Motor Vehicles",
            "subcategory":"Auto Supplies",
            "type":"Retail Goods"
        }
    ],
    "sg:phone":"+1 519 752 3747",
    "sg:postcode":"N3T 2V8",
    "sg:province":"ON",
    "sg:tags":[
        "automobile",
        "parts"
    ],
    "wof:name":"Sherman's Canadian Auto Value",
    "wof:placetype":"venue"
},
  "geometry": {"coordinates":[-80.2601699829,43.1475524902],"type":"Point"}
}