{
  "type": "Feature",
  "properties": {
    "addr:full":"1240 Commissioners Rd W London ON N6K 1C7",
    "addr:housenumber":"1240",
    "addr:postcode":"n6k 1c7",
    "addr:street":"Commissioners Rd W",
    "iso:country":"CA",
    "sg:address":"1240 Commissioners Rd W",
    "sg:city":"London",
    "sg:classifiers":[
        {
            "category":"Shopping",
            "subcategory":"Pharmacy",
            "type":"Retail Goods"
        }
    ],
    "sg:phone":"+1 519 474 7425",
    "sg:postcode":"N6K 1C7",
    "sg:province":"ON",
    "wof:name":"Pharma Plus Drugmart",
    "wof:placetype":"venue"
},
  "geometry": {"coordinates":[-81.33120700000001,42.959114],"type":"Point"}
}