{
  "type": "Feature",
  "properties": {
    "addr:full":"6025 86 St NW # 200 Edmonton AB T6E 2X4",
    "addr:housenumber":"6025",
    "addr:postcode":"t6e 2x4",
    "addr:street":"86 St Nw # 200",
    "iso:country":"CA",
    "sg:address":"6025 86 St NW # 200",
    "sg:city":"Edmonton",
    "sg:classifiers":[
        {
            "category":"Organizations",
            "subcategory":"Professional Association",
            "type":"Services"
        }
    ],
    "sg:phone":"+1 780 462 5738",
    "sg:postcode":"T6E 2X4",
    "sg:province":"AB",
    "wof:name":"Chargers Football Club",
    "wof:placetype":"venue"
},
  "geometry": {"coordinates":[-113.454887,53.496105],"type":"Point"}
}