{
  "type": "Feature",
  "properties": {
    "addr:full":"56 Moir Cres Barrie ON L4N 8B2",
    "addr:housenumber":"56",
    "addr:postcode":"l4n 8b2",
    "addr:street":"Moir Cres",
    "iso:country":"CA",
    "sg:address":"56 Moir Cres",
    "sg:city":"Barrie",
    "sg:classifiers":[
        {
            "category":"Recreation",
            "subcategory":"Arcade",
            "type":"Entertainment"
        }
    ],
    "sg:phone":"+1 705 720 2721",
    "sg:postcode":"L4N 8B2",
    "sg:province":"ON",
    "sg:tags":[
        "break",
        "coffee",
        "amusement",
        "devices",
        "supply"
    ],
    "wof:name":"Northern Repairs",
    "wof:placetype":"venue"
},
  "geometry": {"coordinates":[-79.659988,44.358456],"type":"Point"}
}