{
  "type": "Feature",
  "properties": {
    "addr:full":"150 Ste Catherine O Montreal QC H2X 1Z8",
    "addr:housenumber":"150",
    "addr:postcode":"h2x 1z8",
    "addr:street":"Ste Catherine O",
    "iso:country":"CA",
    "sg:address":"150 Ste Catherine O",
    "sg:city":"Montreal",
    "sg:classifiers":[
        {
            "category":"Restaurant",
            "type":"Food & Drink"
        }
    ],
    "sg:phone":"+1 514 288 5995",
    "sg:postcode":"H2X 1Z8",
    "sg:province":"QC",
    "sg:tags":[
        "parlor",
        "ice",
        "cream"
    ],
    "wof:name":"Cremerie Zazou",
    "wof:placetype":"venue"
},
  "geometry": {"coordinates":[-73.56255299999999,45.511166],"type":"Point"}
}