{
  "type": "Feature",
  "properties": {
    "addr:full":"3 Christensen Rd New Denmark NB E7G 1J4",
    "addr:housenumber":"3",
    "addr:postcode":"e7g 1j4",
    "addr:street":"Christensen Rd",
    "iso:country":"CA",
    "sg:address":"3 Christensen Rd",
    "sg:city":"New Denmark",
    "sg:classifiers":[
        {
            "category":"Wholesale",
            "subcategory":"Farm Supplies",
            "type":"Manufacturing & Wholesale Goods"
        }
    ],
    "sg:phone":"+1 506 553 6515",
    "sg:postcode":"E7G 1J4",
    "sg:province":"NB",
    "sg:tags":[
        "feed"
    ],
    "wof:name":"Nyborg Farms",
    "wof:placetype":"venue"
},
  "geometry": {"coordinates":[-67.56772599999999,46.982056],"type":"Point"}
}