{
  "type": "Feature",
  "properties": {
    "iso:country":"CA",
    "sg:address":"554 Av Duluth E",
    "sg:city":"Montreal",
    "sg:classifiers":[
        {
            "category":"Restaurant",
            "type":"Food & Drink"
        }
    ],
    "sg:phone":"+1 514 849 8844",
    "sg:postcode":"H2L 1A9",
    "sg:province":"QC",
    "wof:name":"Restaurant LA Colombe",
    "wof:placetype":"venue"
},
  "geometry": {"coordinates":[-73.574318,45.522205],"type":"Point"}
}