{
  "type": "Feature",
  "properties": {
    "addr:full":"1718 Lakeshore Rd W Mississauga ON L5J 1J5",
    "addr:housenumber":"1718",
    "addr:postcode":"l5j 1j5",
    "addr:street":"Lakeshore Rd W",
    "iso:country":"CA",
    "sg:address":"1718 Lakeshore Rd W",
    "sg:city":"Mississauga",
    "sg:classifiers":[
        {
            "category":"Personal",
            "subcategory":"Beauty Salon",
            "type":"Services"
        }
    ],
    "sg:phone":"+1 905 822 2777",
    "sg:postcode":"L5J 1J5",
    "sg:province":"ON",
    "wof:name":"Dominic's Beauty Salon",
    "wof:placetype":"venue"
},
  "geometry": {"coordinates":[-79.62237548829999,43.5177650452],"type":"Point"}
}