{
  "type": "Feature",
  "properties": {
    "addr:full":"95 Mullen Dr Thornhill ON L4J 2T6",
    "addr:housenumber":"95",
    "addr:postcode":"l4j 2t6",
    "addr:street":"Mullen Dr",
    "iso:country":"CA",
    "sg:address":"95 Mullen Dr",
    "sg:city":"Thornhill",
    "sg:classifiers":[
        {
            "category":"Building & Trades",
            "subcategory":"Construction",
            "type":"Services"
        }
    ],
    "sg:phone":"+1 905 882 4440",
    "sg:postcode":"L4J 2T6",
    "sg:province":"ON",
    "sg:tags":[
        "resurfacing",
        "laying",
        "refinishing",
        "floor"
    ],
    "wof:name":"Jules Flooring",
    "wof:placetype":"venue"
},
  "geometry": {"coordinates":[-79.455879,43.796555],"type":"Point"}
}