{
  "type": "Feature",
  "properties": {
    "addr:full":"526 Michigan St Victoria BC V8V 1S2",
    "addr:housenumber":"526",
    "addr:postcode":"v8v 1s2",
    "addr:street":"Michigan St",
    "iso:country":"CA",
    "sg:address":"526 Michigan St",
    "sg:city":"Victoria",
    "sg:classifiers":[
        {
            "category":"Social Services",
            "type":"Services"
        }
    ],
    "sg:phone":"+1 250 384 0408",
    "sg:postcode":"V8V 1S2",
    "sg:province":"BC",
    "sg:tags":[
        "organization",
        "welfare"
    ],
    "wof:name":"Family Caregivers' Network Soc",
    "wof:placetype":"venue"
},
  "geometry": {"coordinates":[-123.37190246599999,48.4170837402],"type":"Point"}
}