{
  "type": "Feature",
  "properties": {
    "addr:full":"Church Point NS B0W 1M0",
    "addr:postcode":"b0w 1m0",
    "iso:country":"CA",
    "sg:city":"Church Point",
    "sg:classifiers":[
        {
            "category":"Home & Garden",
            "subcategory":"Building Materials",
            "type":"Retail Goods"
        }
    ],
    "sg:phone":"+1 902 769 2237",
    "sg:postcode":"B0W 1M0",
    "sg:province":"NS",
    "wof:name":"R A Belliveau Ltd",
    "wof:placetype":"venue"
},
  "geometry": {"coordinates":[-66.1161117554,44.3366355896],"type":"Point"}
}