{
  "type": "Feature",
  "properties": {
    "iso:country":"CA",
    "sg:address":"923 Commissioners Rd E",
    "sg:city":"London",
    "sg:classifiers":[
        {
            "category":"Organizations",
            "subcategory":"Professional Association",
            "type":"Services"
        }
    ],
    "sg:phone":"+1 519 668 1944",
    "sg:postcode":"N5Z 3H9",
    "sg:province":"ON",
    "sg:tags":[
        "club"
    ],
    "wof:name":"Sicilia Club of London",
    "wof:placetype":"venue"
},
  "geometry": {"coordinates":[-81.21408081049999,42.9593200684],"type":"Point"}
}