{
  "type": "Feature",
  "properties": {
    "addr:full":"36 Oak St Lancaster ON K0C 1N0",
    "addr:housenumber":"36",
    "addr:postcode":"k0c 1n0",
    "addr:street":"Oak St",
    "iso:country":"CA",
    "sg:address":"36 Oak St",
    "sg:city":"Lancaster",
    "sg:classifiers":[
        {
            "category":"Organizations",
            "subcategory":"Religious Organization",
            "type":"Services"
        }
    ],
    "sg:phone":"+1 613 347 2027",
    "sg:postcode":"K0C 1N0",
    "sg:province":"ON",
    "sg:tags":[
        "church"
    ],
    "wof:name":"St Joseph Catholic Church",
    "wof:placetype":"venue"
},
  "geometry": {"coordinates":[-74.503151,45.138988],"type":"Point"}
}