{
  "type": "Feature",
  "properties": {
    "addr:full":"200 Clearmeadow Blvd Newmarket ON L3X 2E4",
    "addr:housenumber":"200",
    "addr:postcode":"l3x 2e4",
    "addr:street":"Clearmeadow Blvd",
    "iso:country":"CA",
    "sg:address":"200 Clearmeadow Blvd",
    "sg:city":"Newmarket",
    "sg:classifiers":[
        {
            "category":"Social Services",
            "subcategory":"Child Care",
            "type":"Services"
        }
    ],
    "sg:phone":"+1 905 953 7812",
    "sg:postcode":"L3X 2E4",
    "sg:province":"ON",
    "wof:name":"Clearmeadow Child Care",
    "wof:placetype":"venue"
},
  "geometry": {"coordinates":[-79.487228,44.037651],"type":"Point"}
}