{
  "type": "Feature",
  "properties": {
    "iso:country":"CA",
    "sg:city":"Micmac",
    "sg:classifiers":[
        {
            "category":"Social Services",
            "subcategory":"Child Care",
            "type":"Services"
        }
    ],
    "sg:phone":"+1 902 758 3788",
    "sg:postcode":"B0N 1W0",
    "sg:province":"NS",
    "sg:tags":[
        "kindergarten",
        "academic",
        "school"
    ],
    "wof:name":"Sister Elizabeth Cody Pre-K",
    "wof:placetype":"venue"
},
  "geometry": {"coordinates":[-63.4855651855,45.0924415588],"type":"Point"}
}