{
  "type": "Feature",
  "properties": {
    "addr:full":"102 1st Ave W Blaine Lake SK S0J 0J0",
    "addr:housenumber":"102",
    "addr:postcode":"s0j 0j0",
    "addr:street":"1St Ave W Blaine Lake",
    "iso:country":"CA",
    "sg:address":"102 1st Ave W",
    "sg:city":"Blaine Lake",
    "sg:classifiers":[
        {
            "category":"Autos & Motor Vehicles",
            "subcategory":"Auto Supplies",
            "type":"Retail Goods"
        }
    ],
    "sg:phone":"+1 306 497 2290",
    "sg:postcode":"S0J 0J0",
    "sg:province":"SK",
    "sg:tags":[
        "tire"
    ],
    "wof:name":"Blaine Lake Tire & Repair",
    "wof:placetype":"venue"
},
  "geometry": {"coordinates":[-106.87867,52.827629],"type":"Point"}
}