{
  "type": "Feature",
  "properties": {
    "iso:country":"CA",
    "sg:address":"156 St Vincent St",
    "sg:city":"Barrie",
    "sg:classifiers":[
        {
            "category":"Organizations",
            "subcategory":"Religious Organization",
            "type":"Services"
        }
    ],
    "sg:phone":"+1 705 739 9556",
    "sg:postcode":"L4M 3Z1",
    "sg:province":"ON",
    "sg:tags":[
        "church"
    ],
    "wof:name":"Full Gospel Lighthouse",
    "wof:placetype":"venue"
},
  "geometry": {"coordinates":[-79.678719,44.399292],"type":"Point"}
}