{
  "type": "Feature",
  "properties": {
    "iso:country":"CA",
    "sg:address":"2227 Quebec St",
    "sg:city":"Vancouver",
    "sg:classifiers":[
        {
            "category":"Wholesale",
            "subcategory":"Hardware",
            "type":"Manufacturing & Wholesale Goods"
        }
    ],
    "sg:phone":"+1 604 874 2110",
    "sg:postcode":"V5T 3A1",
    "sg:province":"BC",
    "wof:name":"Cmc Architectural Hardware",
    "wof:placetype":"venue"
},
  "geometry": {"coordinates":[-123.10307312,49.2652664185],"type":"Point"}
}