{
  "type": "Feature",
  "properties": {
    "iso:country":"CA",
    "sg:address":"1595 Boul Talbot",
    "sg:city":"Chicoutimi",
    "sg:classifiers":[
        {
            "category":"Travel",
            "subcategory":"Hotels & Motels",
            "type":"Entertainment"
        }
    ],
    "sg:phone":"+1 418 693 8686",
    "sg:postcode":"G7H 4C3",
    "sg:province":"QC",
    "wof:name":"Comfort Inn",
    "wof:placetype":"venue"
},
  "geometry": {"coordinates":[-71.061378479,48.4010391235],"type":"Point"}
}