{
  "type": "Feature",
  "properties": {
    "iso:country":"CA",
    "sg:address":"259 King St W",
    "sg:city":"Prescott",
    "sg:classifiers":[
        {
            "category":"Shopping",
            "subcategory":"Shoes",
            "type":"Retail Goods"
        }
    ],
    "sg:phone":"+1 613 925 1120",
    "sg:postcode":"K0E 1T0",
    "sg:province":"ON",
    "wof:name":"Wiseman's Shoe Prescott Ltd",
    "wof:placetype":"venue"
},
  "geometry": {"coordinates":[-75.515296936,44.7087211609],"type":"Point"}
}