{
  "type": "Feature",
  "properties": {
    "addr:full":"730 16 Ave NW Calgary AB T2M 0J8",
    "addr:postcode":"730;t2m 0j8",
    "addr:street":"16 Ave Nw",
    "iso:country":"CA",
    "sg:address":"730 16 Ave NW",
    "sg:city":"Calgary",
    "sg:classifiers":[
        {
            "category":"Autos & Motor Vehicles",
            "subcategory":"Auto Supplies",
            "type":"Retail Goods"
        }
    ],
    "sg:phone":"+1 403 289 7500",
    "sg:postcode":"T2M 0J8",
    "sg:province":"AB",
    "sg:tags":[
        "automobile",
        "parts"
    ],
    "wof:name":"Uap Napa Auto Parts",
    "wof:placetype":"venue"
},
  "geometry": {"coordinates":[-114.0783,51.067097],"type":"Point"}
}