{
  "type": "Feature",
  "properties": {
    "addr:full":"141 Jessop Ave Saskatoon SK S7N 1Y3",
    "addr:housenumber":"141",
    "addr:postcode":"s7n 1y3",
    "addr:street":"Jessop Ave",
    "iso:country":"CA",
    "sg:address":"141 Jessop Ave",
    "sg:city":"Saskatoon",
    "sg:classifiers":[
        {
            "category":"Recreation",
            "type":"Entertainment"
        }
    ],
    "sg:phone":"+1 306 374 8400",
    "sg:postcode":"S7N 1Y3",
    "sg:province":"SK",
    "sg:tags":[
        "club",
        "curling"
    ],
    "wof:name":"Sutherland Curling Club",
    "wof:placetype":"venue"
},
  "geometry": {"coordinates":[-106.59701538100001,52.1288337708],"type":"Point"}
}