{
  "type": "Feature",
  "properties": {
    "addr:full":"305 Evans Ave Etobicoke ON M8Z 1K2",
    "addr:housenumber":"305",
    "addr:postcode":"m8z 1k2",
    "addr:street":"Evans Ave",
    "iso:country":"CA",
    "sg:address":"305 Evans Ave",
    "sg:city":"Etobicoke",
    "sg:classifiers":[
        {
            "category":"Wholesale",
            "subcategory":"Machinery & Supplies",
            "type":"Manufacturing & Wholesale Goods"
        }
    ],
    "sg:phone":"+1 416 255 0111",
    "sg:postcode":"M8Z 1K2",
    "sg:province":"ON",
    "sg:tags":[
        "machine",
        "tool"
    ],
    "wof:name":"Sizetech Inc",
    "wof:placetype":"venue"
},
  "geometry": {"coordinates":[-79.5206451416,43.6164360046],"type":"Point"}
}