{
  "type": "Feature",
  "properties": {
    "addr:full":"206 Rue Vallilee Chute-Aux-Outardes QC G0H 1C0",
    "addr:housenumber":"206",
    "addr:postcode":"g0h 1c0",
    "addr:street":"Rue Vallilee",
    "iso:country":"CA",
    "sg:address":"206 Rue Vallilee",
    "sg:city":"Chute-Aux-Outardes",
    "sg:classifiers":[
        {
            "category":"Retail",
            "subcategory":"Auto Repair",
            "type":"Services"
        }
    ],
    "sg:phone":"+1 418 567 4211",
    "sg:postcode":"G0H 1C0",
    "sg:province":"QC",
    "sg:tags":[
        "repairing",
        "automobile"
    ],
    "wof:name":"Migneault Service Jmy Inc",
    "wof:placetype":"venue"
},
  "geometry": {"coordinates":[-68.39376831049999,49.1224021912],"type":"Point"}
}