{
  "type": "Feature",
  "properties": {
    "addr:full":"Calgary AB T2X 1N4",
    "addr:postcode":"t2x 1n4",
    "iso:country":"CA",
    "sg:city":"Calgary",
    "sg:classifiers":[
        {
            "category":"Health Services",
            "subcategory":"Doctor",
            "type":"Services"
        }
    ],
    "sg:phone":"+1 403 256 2355",
    "sg:postcode":"T2X 1N4",
    "sg:province":"AB",
    "sg:tags":[
        "physician",
        "surgeon"
    ],
    "wof:name":"Hardin, Barry MD",
    "wof:placetype":"venue"
},
  "geometry": {"coordinates":[-114.06430053699999,50.9121627808],"type":"Point"}
}