{
  "type": "Feature",
  "properties": {
    "addr:full":"Port Hardy BC V0N 2P0",
    "addr:postcode":"v0n 2p0",
    "iso:country":"CA",
    "sg:city":"Port Hardy",
    "sg:classifiers":[
        {
            "category":"Personal",
            "subcategory":"Beauty Salon",
            "type":"Services"
        }
    ],
    "sg:phone":"+1 250 949 9798",
    "sg:postcode":"V0N 2P0",
    "sg:province":"BC",
    "wof:name":"Pacific Waves Hair Studio",
    "wof:placetype":"venue"
},
  "geometry": {"coordinates":[-127.49211099999999,50.722546],"type":"Point"}
}