{
  "type": "Feature",
  "properties": {
    "iso:country":"CA",
    "sg:address":"1656 Ch West River",
    "sg:city":"Dsl DE Grand-Sault/Falls",
    "sg:classifiers":[
        {
            "category":"Real Estate",
            "subcategory":"Surveying",
            "type":"Services"
        }
    ],
    "sg:phone":"+1 506 473 7010",
    "sg:postcode":"E3Z 1T7",
    "sg:province":"NB",
    "sg:tags":[
        "surveyor"
    ],
    "wof:name":"G H Surveys",
    "wof:placetype":"venue"
},
  "geometry": {"coordinates":[-64.60907745359999,45.8118896484],"type":"Point"}
}