{
  "type": "Feature",
  "properties": {
    "addr:full":"44 Boul Montclair Hull QC J8Y 2E6",
    "addr:housenumber":"44",
    "addr:postcode":"j8y 2e6",
    "addr:street":"Boul Montclair",
    "iso:country":"CA",
    "sg:address":"44 Boul Montclair",
    "sg:city":"Hull",
    "sg:classifiers":[
        {
            "category":"Professional",
            "subcategory":"Business Services",
            "type":"Services"
        }
    ],
    "sg:phone":"+1 819 777 2828",
    "sg:postcode":"J8Y 2E6",
    "sg:province":"QC",
    "sg:tags":[
        "notary"
    ],
    "wof:name":"Nadeau, Marc",
    "wof:placetype":"venue"
},
  "geometry": {"coordinates":[-75.7348937988,45.4403762817],"type":"Point"}
}