{
  "type": "Feature",
  "properties": {
    "iso:country":"CA",
    "sg:address":"3669 Highland Ave",
    "sg:city":"Halifax",
    "sg:classifiers":[
        {
            "category":"Education",
            "subcategory":"School",
            "type":"Public Place"
        }
    ],
    "sg:phone":"+1 902 493 5155",
    "sg:postcode":"B3K 4J9",
    "sg:province":"NS",
    "wof:name":"St Stephen's School",
    "wof:placetype":"venue"
},
  "geometry": {"coordinates":[-63.6112976074,44.6679153442],"type":"Point"}
}