{
  "type": "Feature",
  "properties": {
    "addr:full":"8 Lismer Cres Kanata ON K2K 1A2",
    "addr:housenumber":"8",
    "addr:postcode":"k2k 1a2",
    "addr:street":"Lismer Cres",
    "iso:country":"CA",
    "sg:address":"8 Lismer Cres",
    "sg:city":"Kanata",
    "sg:classifiers":[
        {
            "category":"Professional",
            "subcategory":"Business Services",
            "type":"Services"
        }
    ],
    "sg:phone":"+1 613 599 6295",
    "sg:postcode":"K2K 1A2",
    "sg:province":"ON",
    "sg:tags":[
        "inspection"
    ],
    "wof:name":"Energy Building Group Ltd",
    "wof:placetype":"venue"
},
  "geometry": {"coordinates":[-75.909721,45.334064],"type":"Point"}
}