{
  "type": "Feature",
  "properties": {
    "addr:full":"637 Av Brochu Sept-Iles QC G4R 2X7",
    "addr:postcode":"g4r 2x7",
    "addr:street":"637 Av Brochu Sept-Iles",
    "iso:country":"CA",
    "sg:address":"637 Av Brochu",
    "sg:city":"Sept-Iles",
    "sg:classifiers":[
        {
            "category":"Shopping",
            "subcategory":"Bicycles & Sporting Goods",
            "type":"Retail Goods"
        }
    ],
    "sg:phone":"+1 418 962 7223",
    "sg:postcode":"G4R 2X7",
    "sg:province":"QC",
    "wof:name":"Vetements Des Iles Enr",
    "wof:placetype":"venue"
},
  "geometry": {"coordinates":[-66.391479,50.210827],"type":"Point"}
}