{
  "type": "Feature",
  "properties": {
    "addr:full":"21 Lamport Vittoria ON N0E 1W0",
    "addr:housenumber":"21",
    "addr:postcode":"n0e 1w0",
    "addr:street":"Lamport",
    "iso:country":"CA",
    "sg:address":"21 Lamport",
    "sg:city":"Vittoria",
    "sg:classifiers":[
        {
            "category":"Building & Trades",
            "subcategory":"Construction",
            "type":"Services"
        }
    ],
    "sg:phone":"+1 519 426 2163",
    "sg:postcode":"N0E 1W0",
    "sg:province":"ON",
    "sg:tags":[
        "water",
        "well",
        "drilling"
    ],
    "wof:name":"M & M Pump Svc",
    "wof:placetype":"venue"
},
  "geometry": {"coordinates":[-80.322174,42.761543],"type":"Point"}
}