{
  "type": "Feature",
  "properties": {
    "addr:full":"1440 Hurontario St Mississauga ON L5G 3H4",
    "addr:housenumber":"1440",
    "addr:postcode":"l5g 3h4",
    "addr:street":"Hurontario St",
    "iso:country":"CA",
    "sg:address":"1440 Hurontario St",
    "sg:city":"Mississauga",
    "sg:classifiers":[
        {
            "category":"Real Estate",
            "subcategory":"Real Estate Agent",
            "type":"Services"
        }
    ],
    "sg:phone":"+1 905 278 1900",
    "sg:postcode":"L5G 3H4",
    "sg:province":"ON",
    "wof:name":"Realty Executives Plus Ltd",
    "wof:placetype":"venue"
},
  "geometry": {"coordinates":[-79.593468,43.563538],"type":"Point"}
}