{
  "type": "Feature",
  "properties": {
    "iso:country":"CA",
    "sg:address":"295 Rue Marino",
    "sg:city":"Beauport",
    "sg:classifiers":[
        {
            "category":"Shopping",
            "subcategory":"Computers & Home Electronics",
            "type":"Retail Goods"
        }
    ],
    "sg:phone":"+1 418 650 1129",
    "sg:postcode":"G1C 7P2",
    "sg:province":"QC",
    "sg:tags":[
        "software"
    ],
    "wof:name":"Institut Sas Inc",
    "wof:placetype":"venue"
},
  "geometry": {"coordinates":[-71.198929,46.895752],"type":"Point"}
}