{
  "type": "Feature",
  "properties": {
    "iso:country":"CA",
    "sg:address":"1258 Rebecca St",
    "sg:city":"Oakville",
    "sg:classifiers":[
        {
            "category":"Organizations",
            "subcategory":"Religious Organization",
            "type":"Services"
        }
    ],
    "sg:phone":"+1 905 827 3711",
    "sg:postcode":"L6L 1Z2",
    "sg:province":"ON",
    "sg:tags":[
        "church"
    ],
    "wof:name":"St Hilda's Anglican Church",
    "wof:placetype":"venue"
},
  "geometry": {"coordinates":[-79.698097229,43.4178237915],"type":"Point"}
}