{
  "type": "Feature",
  "properties": {
    "addr:full":"135 Roland Michener Dr Kanata ON K2T 1G7",
    "addr:housenumber":"135",
    "addr:postcode":"k2t 1g7",
    "addr:street":"Roland Michener Dr",
    "iso:country":"CA",
    "sg:address":"135 Roland Michener Dr",
    "sg:city":"Kanata",
    "sg:classifiers":[
        {
            "category":"Restaurant",
            "type":"Food & Drink"
        }
    ],
    "sg:phone":"+1 613 592 7031",
    "sg:postcode":"K2T 1G7",
    "sg:province":"ON",
    "wof:name":"Boston Pizza",
    "wof:placetype":"venue"
},
  "geometry": {"coordinates":[-75.913048,45.30854],"type":"Point"}
}