{
  "type": "Feature",
  "properties": {
    "iso:country":"CA",
    "sg:address":"11505 6E Av",
    "sg:city":"Montreal",
    "sg:classifiers":[
        {
            "category":"Manufacturing",
            "subcategory":"Signs",
            "type":"Manufacturing & Wholesale Goods"
        }
    ],
    "sg:phone":"+1 514 648 6342",
    "sg:postcode":"H1E 1R8",
    "sg:province":"QC",
    "wof:name":"Lettrage Poirier Inc",
    "wof:placetype":"venue"
},
  "geometry": {"coordinates":[-73.59707641599999,45.6200714111],"type":"Point"}
}