{
  "type": "Feature",
  "properties": {
    "addr:full":"280 Brickyard Rd Albert Bridge NS B1K 2R4",
    "addr:housenumber":"280",
    "addr:postcode":"b1k 2r4",
    "addr:street":"Brickyard Rd",
    "iso:country":"CA",
    "sg:address":"280 Brickyard Rd",
    "sg:city":"Albert Bridge",
    "sg:classifiers":[
        {
            "category":"Building & Trades",
            "subcategory":"Construction",
            "type":"Services"
        }
    ],
    "sg:phone":"+1 902 564 9001",
    "sg:postcode":"B1K 2R4",
    "sg:province":"NS",
    "sg:tags":[
        "general",
        "contractor"
    ],
    "wof:name":"Roclan Industries Ltd",
    "wof:placetype":"venue"
},
  "geometry": {"coordinates":[-60.058437,46.020313],"type":"Point"}
}