{
  "type": "Feature",
  "properties": {
    "addr:full":"7210 51 Ave NW Edmonton AB T6B 2P4",
    "addr:housenumber":"7210",
    "addr:postcode":"t6b 2p4",
    "addr:street":"51 Ave Nw",
    "iso:country":"CA",
    "sg:address":"7210 51 Ave NW",
    "sg:city":"Edmonton",
    "sg:classifiers":[
        {
            "category":"Manufacturing",
            "subcategory":"Toys & Sporting Goods",
            "type":"Manufacturing & Wholesale Goods"
        }
    ],
    "sg:phone":"+1 780 466 6789",
    "sg:postcode":"T6B 2P4",
    "sg:province":"AB",
    "sg:tags":[
        "athletic"
    ],
    "wof:name":"Talon Tapes Industries Ltd",
    "wof:placetype":"venue"
},
  "geometry": {"coordinates":[-113.43807983400001,53.4881286621],"type":"Point"}
}