{
  "type": "Feature",
  "properties": {
    "addr:full":"2655 Douglas St Victoria BC V8T 4M2",
    "addr:housenumber":"2655",
    "addr:postcode":"v8t 4m2",
    "addr:street":"Douglas St",
    "iso:country":"CA",
    "sg:address":"2655 Douglas St",
    "sg:city":"Victoria",
    "sg:classifiers":[
        {
            "category":"Home & Garden",
            "subcategory":"Furniture",
            "type":"Retail Goods"
        }
    ],
    "sg:phone":"+1 250 386 7632",
    "sg:postcode":"V8T 4M2",
    "sg:province":"BC",
    "wof:name":"Norwalk the Furniture Idea",
    "wof:placetype":"venue"
},
  "geometry": {"coordinates":[-123.36618,48.437458],"type":"Point"}
}