{
  "type": "Feature",
  "properties": {
    "iso:country":"CA",
    "sg:address":"186 Hunter St E",
    "sg:city":"Hamilton",
    "sg:classifiers":[
        {
            "category":"Shopping",
            "subcategory":"Hobbies, Toys, & Games",
            "type":"Retail Goods"
        }
    ],
    "sg:phone":"+1 905 527 1117",
    "sg:postcode":"L8N 3X9",
    "sg:province":"ON",
    "sg:tags":[
        "ceramic",
        "sewing",
        "contractor"
    ],
    "wof:name":"Rainbow Ceramics & Crafts",
    "wof:placetype":"venue"
},
  "geometry": {"coordinates":[-79.86293029789999,43.2515144348],"type":"Point"}
}