{
  "type": "Feature",
  "properties": {
    "addr:full":"3020 Heather St Vancouver BC V5Z 3K3",
    "addr:housenumber":"3020",
    "addr:postcode":"v5z 3k3",
    "addr:street":"Heather St",
    "iso:country":"CA",
    "sg:address":"3020 Heather St",
    "sg:city":"Vancouver",
    "sg:classifiers":[
        {
            "category":"Education",
            "subcategory":"School",
            "type":"Public Place"
        }
    ],
    "sg:phone":"+1 604 876 7211",
    "sg:postcode":"V5Z 3K3",
    "sg:province":"BC",
    "wof:name":"Blessed Sacrament French Schl",
    "wof:placetype":"venue"
},
  "geometry": {"coordinates":[-123.11972045900001,49.2583999634],"type":"Point"}
}