{
  "type": "Feature",
  "properties": {
    "iso:country":"CA",
    "sg:address":"6702 Rajpur Pl",
    "sg:city":"Saanichton",
    "sg:classifiers":[
        {
            "category":"Wholesale",
            "subcategory":"Machinery & Supplies",
            "type":"Manufacturing & Wholesale Goods"
        }
    ],
    "sg:phone":"+1 250 652 9211",
    "sg:postcode":"V8M 1Z5",
    "sg:province":"BC",
    "sg:tags":[
        "pulverizing",
        "crushing"
    ],
    "wof:name":"Island Crushing CO",
    "wof:placetype":"venue"
},
  "geometry": {"coordinates":[-123.41689300500001,48.595199585],"type":"Point"}
}