{
  "type": "Feature",
  "properties": {
    "iso:country":"CA",
    "sg:city":"Redwater",
    "sg:classifiers":[
        {
            "category":"Local Transit",
            "type":"Transportation"
        }
    ],
    "sg:phone":"+1 780 942 4703",
    "sg:postcode":"T0A 2W0",
    "sg:province":"AB",
    "sg:tags":[
        "ambulance"
    ],
    "wof:name":"Medicare Ambulance Svc",
    "wof:placetype":"venue"
},
  "geometry": {"coordinates":[-113.108215332,53.9521446228],"type":"Point"}
}