{
  "type": "Feature",
  "properties": {
    "iso:country":"CA",
    "sg:address":"383 Humberline Dr",
    "sg:city":"Etobicoke",
    "sg:classifiers":[
        {
            "category":"Wholesale",
            "subcategory":"Meat",
            "type":"Manufacturing & Wholesale Goods"
        }
    ],
    "sg:phone":"+1 416 675 1785",
    "sg:postcode":"M9W 5X3",
    "sg:province":"ON",
    "sg:tags":[
        "product"
    ],
    "wof:name":"Santa Maria Foods Corp",
    "wof:placetype":"venue"
},
  "geometry": {"coordinates":[-79.6206665039,43.7436943054],"type":"Point"}
}