{
  "type": "Feature",
  "properties": {
    "iso:country":"CA",
    "sg:city":"Saint-Laurent",
    "sg:classifiers":[
        {
            "category":"Insurance",
            "subcategory":"Insurance Agent",
            "type":"Services"
        }
    ],
    "sg:phone":"+1 514 332 0816",
    "sg:postcode":"H4R 2N1",
    "sg:province":"QC",
    "wof:name":"P D Admin Group",
    "wof:placetype":"venue"
},
  "geometry": {"coordinates":[-73.70565,45.49633],"type":"Point"}
}