{
  "type": "Feature",
  "properties": {
    "addr:full":"Montague PE C0A 1R0",
    "addr:postcode":"c0a 1r0",
    "iso:country":"CA",
    "sg:city":"Montague",
    "sg:classifiers":[
        {
            "category":"Manufacturing",
            "subcategory":"Lumber",
            "type":"Manufacturing & Wholesale Goods"
        }
    ],
    "sg:phone":"+1 902 838 2688",
    "sg:postcode":"C0A 1R0",
    "sg:province":"PE",
    "sg:tags":[
        "company",
        "logging"
    ],
    "wof:name":"Ryan Wood Producers",
    "wof:placetype":"venue"
},
  "geometry": {"coordinates":[-62.6497192383,46.1671638489],"type":"Point"}
}