{
  "type": "Feature",
  "properties": {
    "addr:full":"Highway 20 N Humboldt SK S0K 2A0",
    "addr:postcode":"s0k 2a0",
    "addr:street":"Highway 20 N",
    "iso:country":"CA",
    "sg:address":"Highway 20 N",
    "sg:city":"Humboldt",
    "sg:classifiers":[
        {
            "category":"Organizations",
            "subcategory":"Religious Organization",
            "type":"Services"
        }
    ],
    "sg:phone":"+1 306 682 4426",
    "sg:postcode":"S0K 2A0",
    "sg:province":"SK",
    "sg:tags":[
        "church"
    ],
    "wof:name":"Humboldt Bible Church",
    "wof:placetype":"venue"
},
  "geometry": {"coordinates":[-105.12146799999999,52.2019],"type":"Point"}
}