{
  "type": "Feature",
  "properties": {
    "addr:full":"1 Regent Sq Corner Brook NL A2H 7K6",
    "addr:housenumber":"1",
    "addr:postcode":"a2h 7k6",
    "addr:street":"Regent Sq",
    "iso:country":"CA",
    "sg:address":"1 Regent Sq",
    "sg:city":"Corner Brook",
    "sg:classifiers":[
        {
            "category":"Government",
            "subcategory":"Office",
            "type":"Public Place"
        }
    ],
    "sg:phone":"+1 709 637 4388",
    "sg:postcode":"A2H 7K6",
    "sg:province":"NL",
    "wof:name":"Canada Food Inspection Branch",
    "wof:placetype":"venue"
},
  "geometry": {"coordinates":[-57.94947052,48.9501991272],"type":"Point"}
}