{
  "type": "Feature",
  "properties": {
    "iso:country":"CA",
    "sg:address":"961 Pembroke St W",
    "sg:city":"Pembroke",
    "sg:classifiers":[
        {
            "category":"Organizations",
            "subcategory":"Community Association",
            "type":"Services"
        }
    ],
    "sg:phone":"+1 613 735 5230",
    "sg:postcode":"K8A 8R4",
    "sg:province":"ON",
    "sg:tags":[
        "club"
    ],
    "wof:name":"Kiwanis Club of Pembroke",
    "wof:placetype":"venue"
},
  "geometry": {"coordinates":[-77.13702392579999,45.8287391663],"type":"Point"}
}