{
  "type": "Feature",
  "properties": {
    "addr:full":"Saint-Philippe QC J0L 2K0",
    "addr:postcode":"j0l 2k0",
    "iso:country":"CA",
    "sg:city":"Saint-Philippe",
    "sg:classifiers":[
        {
            "category":"Building & Trades",
            "subcategory":"Construction",
            "type":"Services"
        }
    ],
    "sg:phone":"+1 450 444 3755",
    "sg:postcode":"J0L 2K0",
    "sg:province":"QC",
    "sg:tags":[
        "general",
        "contractor"
    ],
    "wof:name":"Construction Gc 2001 Inc",
    "wof:placetype":"venue"
},
  "geometry": {"coordinates":[-73.48098,45.362663],"type":"Point"}
}