{
  "type": "Feature",
  "properties": {
    "addr:full":"Hwy 23 Mitchell ON N0K 1N0",
    "addr:postcode":"n0k 1n0",
    "addr:street":"Hwy 23",
    "iso:country":"CA",
    "sg:address":"Hwy 23",
    "sg:city":"Mitchell",
    "sg:classifiers":[
        {
            "category":"Government",
            "subcategory":"Office",
            "type":"Public Place"
        }
    ],
    "sg:phone":"+1 519 348 8462",
    "sg:postcode":"N0K 1N0",
    "sg:province":"ON",
    "wof:name":"Ontario Patrol Yards",
    "wof:placetype":"venue"
},
  "geometry": {"coordinates":[-81.20422363279999,43.4638137817],"type":"Point"}
}