{
  "type": "Feature",
  "properties": {
    "addr:full":"10 Eby St St Jacobs ON N0B 2N0",
    "addr:housenumber":"10",
    "addr:postcode":"n0b 2n0",
    "addr:street":"Eby St St",
    "iso:country":"CA",
    "sg:address":"10 Eby St",
    "sg:city":"St Jacobs",
    "sg:classifiers":[
        {
            "category":"Professional",
            "subcategory":"Management & Consulting",
            "type":"Services"
        }
    ],
    "sg:phone":"+1 519 664 3171",
    "sg:postcode":"N0B 2N0",
    "sg:province":"ON",
    "sg:tags":[
        "roofing",
        "consultant"
    ],
    "wof:name":"Brubacher Industrial Mntnc",
    "wof:placetype":"venue"
},
  "geometry": {"coordinates":[-80.552216,43.541821],"type":"Point"}
}