{
  "type": "Feature",
  "properties": {
    "addr:full":"13639 72 Ave Surrey BC V3W 2P2",
    "addr:housenumber":"13639",
    "addr:postcode":"v3w 2p2",
    "addr:street":"72 Ave",
    "iso:country":"CA",
    "sg:address":"13639 72 Ave",
    "sg:city":"Surrey",
    "sg:classifiers":[
        {
            "category":"Personal",
            "subcategory":"Beauty Salon",
            "type":"Services"
        }
    ],
    "sg:phone":"+1 604 596 5616",
    "sg:postcode":"V3W 2P2",
    "sg:province":"BC",
    "wof:name":"Newton Beauty Bar",
    "wof:placetype":"venue"
},
  "geometry": {"coordinates":[-122.844521,49.133766],"type":"Point"}
}