{
  "type": "Feature",
  "properties": {
    "iso:country":"CA",
    "sg:address":"9350 Malden Rd",
    "sg:city":"Windsor",
    "sg:classifiers":[
        {
            "category":"Shopping",
            "subcategory":"Discount & Variety Stores",
            "type":"Retail Goods"
        }
    ],
    "sg:phone":"+1 519 734 1772",
    "sg:postcode":"N9J 2V8",
    "sg:province":"ON",
    "wof:name":"D B's Discount Variety",
    "wof:placetype":"venue"
},
  "geometry": {"coordinates":[-83.059319,42.273022],"type":"Point"}
}