{
  "type": "Feature",
  "properties": {
    "addr:full":"212 Rue Notre-Dame O Montreal QC H2Y 1T3",
    "addr:housenumber":"212",
    "addr:postcode":"h2y 1t3",
    "addr:street":"Rue Notre-Dame O",
    "iso:country":"CA",
    "sg:address":"212 Rue Notre-Dame O",
    "sg:city":"Montreal",
    "sg:classifiers":[
        {
            "category":"Restaurant",
            "type":"Food & Drink"
        }
    ],
    "sg:phone":"+1 514 845 5436",
    "sg:postcode":"H2Y 1T3",
    "sg:province":"QC",
    "wof:name":"Au Cepage",
    "wof:placetype":"venue"
},
  "geometry": {"coordinates":[-73.5537490845,45.5083999634],"type":"Point"}
}