{
  "type": "Feature",
  "properties": {
    "iso:country":"CA",
    "sg:city":"Scarborough",
    "sg:classifiers":[
        {
            "category":"Wholesale",
            "subcategory":"Machinery & Supplies",
            "type":"Manufacturing & Wholesale Goods"
        }
    ],
    "sg:phone":"+1 416 292 2877",
    "sg:postcode":"M1B 5R1",
    "sg:province":"ON",
    "sg:tags":[
        "seal"
    ],
    "wof:name":"Flowserve Inc",
    "wof:placetype":"venue"
},
  "geometry": {"coordinates":[-79.2339935303,43.815071106],"type":"Point"}
}