{
  "type": "Feature",
  "properties": {
    "iso:country":"CA",
    "sg:address":"4155 Fairview St",
    "sg:city":"Burlington",
    "sg:classifiers":[
        {
            "category":"Shopping",
            "subcategory":"Stationery & Office Supplies",
            "type":"Retail Goods"
        }
    ],
    "sg:phone":"+1 905 637 7737",
    "sg:postcode":"L7L 2A4",
    "sg:province":"ON",
    "sg:tags":[
        "album",
        "scrapbook",
        "craft"
    ],
    "wof:name":"Scraps & Scribbles",
    "wof:placetype":"venue"
},
  "geometry": {"coordinates":[-79.7751922607,43.363986969],"type":"Point"}
}