{
  "type": "Feature",
  "properties": {
    "addr:full":"44 Queen St Dryden ON P8N 1A4",
    "addr:housenumber":"44",
    "addr:postcode":"p8n 1a4",
    "addr:street":"Queen St",
    "iso:country":"CA",
    "sg:address":"44 Queen St",
    "sg:city":"Dryden",
    "sg:classifiers":[
        {
            "category":"Personal",
            "subcategory":"Beauty Salon",
            "type":"Services"
        }
    ],
    "sg:phone":"+1 807 223 5005",
    "sg:postcode":"P8N 1A4",
    "sg:province":"ON",
    "wof:name":"Curl Up & Dye",
    "wof:placetype":"venue"
},
  "geometry": {"coordinates":[-92.8385009766,49.7851295471],"type":"Point"}
}