{
  "type": "Feature",
  "properties": {
    "addr:full":"8100 Kipling Ave Woodbridge ON L4L 2A1",
    "addr:housenumber":"8100",
    "addr:postcode":"l4l 2a1",
    "addr:street":"Kipling Ave",
    "iso:country":"CA",
    "sg:address":"8100 Kipling Ave",
    "sg:city":"Woodbridge",
    "sg:classifiers":[
        {
            "category":"Home & Garden",
            "subcategory":"Building Materials",
            "type":"Retail Goods"
        }
    ],
    "sg:phone":"+1 905 851 2804",
    "sg:postcode":"L4L 2A1",
    "sg:province":"ON",
    "sg:tags":[
        "lumber"
    ],
    "wof:name":"Woodbridge Lumber",
    "wof:placetype":"venue"
},
  "geometry": {"coordinates":[-79.59944152830001,43.7871704102],"type":"Point"}
}