{
  "type": "Feature",
  "properties": {
    "addr:full":"Lachine QC H8S 1Z4",
    "addr:postcode":"h8s 1z4",
    "iso:country":"CA",
    "sg:city":"Lachine",
    "sg:classifiers":[
        {
            "category":"Professional",
            "subcategory":"Business Services",
            "type":"Services"
        }
    ],
    "sg:phone":"+1 514 634 0060",
    "sg:postcode":"H8S 1Z4",
    "sg:province":"QC",
    "sg:tags":[
        "packaging",
        "machinery"
    ],
    "wof:name":"Sealed Air of Canada Ltd",
    "wof:placetype":"venue"
},
  "geometry": {"coordinates":[-73.68946099999999,45.43623],"type":"Point"}
}