{
  "type": "Feature",
  "properties": {
    "addr:full":"148 York St London ON N6A 1A9",
    "addr:housenumber":"148",
    "addr:postcode":"n6a 1a9",
    "addr:street":"York St",
    "iso:country":"CA",
    "sg:address":"148 York St",
    "sg:city":"London",
    "sg:classifiers":[
        {
            "category":"Professional",
            "subcategory":"Computer Services",
            "type":"Services"
        }
    ],
    "sg:phone":"+1 519 434 3722",
    "sg:postcode":"N6A 1A9",
    "sg:province":"ON",
    "sg:tags":[
        "consultant"
    ],
    "wof:name":"Larkson Communications",
    "wof:placetype":"venue"
},
  "geometry": {"coordinates":[-81.2494430542,42.9811859131],"type":"Point"}
}