{
  "type": "Feature",
  "properties": {
    "addr:full":"Lindsay ON K9V 6A5",
    "addr:postcode":"k9v 6a5",
    "iso:country":"CA",
    "sg:city":"Lindsay",
    "sg:classifiers":[
        {
            "category":"Health Services",
            "subcategory":"Medical Lab",
            "type":"Services"
        }
    ],
    "sg:phone":"+1 705 324 0767",
    "sg:postcode":"K9V 6A5",
    "sg:province":"ON",
    "wof:name":"Kawartha Denture Clinic",
    "wof:placetype":"venue"
},
  "geometry": {"coordinates":[-78.7413406372,44.3527297974],"type":"Point"}
}