{
  "type": "Feature",
  "properties": {
    "iso:country":"CA",
    "sg:address":"150 Rue Ann",
    "sg:city":"Montreal",
    "sg:classifiers":[
        {
            "category":"Freight",
            "type":"Transportation"
        }
    ],
    "sg:phone":"+1 514 866 9700",
    "sg:postcode":"H3C 2J8",
    "sg:province":"QC",
    "sg:tags":[
        "mover",
        "trucking"
    ],
    "wof:name":"Demenagement Gaetan Boucher",
    "wof:placetype":"venue"
},
  "geometry": {"coordinates":[-73.557632,45.494717],"type":"Point"}
}