{
  "type": "Feature",
  "properties": {
    "addr:full":"38 Park Place Mall # D25 Lethbridge AB T1J 4L9",
    "addr:housenumber":"38",
    "addr:postcode":"t1j 4l9",
    "addr:street":"Park Place Mall # D25",
    "iso:country":"CA",
    "sg:address":"38 Park Place Mall # D25",
    "sg:city":"Lethbridge",
    "sg:classifiers":[
        {
            "category":"Shopping",
            "subcategory":"Gifts & Souvenirs",
            "type":"Retail Goods"
        }
    ],
    "sg:phone":"+1 403 320 2130",
    "sg:postcode":"T1J 4L9",
    "sg:province":"AB",
    "sg:tags":[
        "shop"
    ],
    "wof:name":"San Francisco Gifts",
    "wof:placetype":"venue"
},
  "geometry": {"coordinates":[-112.833740234,49.6938362122],"type":"Point"}
}