{
  "type": "Feature",
  "properties": {
    "addr:full":"3090 Westwood St Port Coquitlam BC V3C 3L7",
    "addr:housenumber":"3090",
    "addr:postcode":"v3c 3l7",
    "addr:street":"Westwood St",
    "iso:country":"CA",
    "sg:address":"3090 Westwood St",
    "sg:city":"Port Coquitlam",
    "sg:classifiers":[
        {
            "category":"Building & Trades",
            "subcategory":"Construction",
            "type":"Services"
        }
    ],
    "sg:phone":"+1 604 461 0333",
    "sg:postcode":"V3C 3L7",
    "sg:province":"BC",
    "sg:tags":[
        "retaining",
        "wall",
        "feeder",
        "bird",
        "house"
    ],
    "wof:name":"Landscape Construction Ctr",
    "wof:placetype":"venue"
},
  "geometry": {"coordinates":[-122.790482,49.267494],"type":"Point"}
}