{
  "type": "Feature",
  "properties": {
    "addr:full":"5074 Ch Saint-Anicet LA Baie QC G7B 3N8",
    "addr:postcode":"5074;g7b 3n8",
    "addr:street":"Ch Saint-Anicet",
    "iso:country":"CA",
    "sg:address":"5074 Ch Saint-Anicet",
    "sg:city":"LA Baie",
    "sg:classifiers":[
        {
            "category":"Building & Trades",
            "subcategory":"Landscaping Services",
            "type":"Services"
        }
    ],
    "sg:phone":"+1 418 677 2657",
    "sg:postcode":"G7B 3N8",
    "sg:province":"QC",
    "sg:tags":[
        "contractor",
        "sodding",
        "landscape",
        "sod"
    ],
    "wof:name":"Gazon Larouche",
    "wof:placetype":"venue"
},
  "geometry": {"coordinates":[-70.94483200000001,48.327515],"type":"Point"}
}