{
  "type": "Feature",
  "properties": {
    "addr:full":"Pointe-Claire QC H9S 4L3",
    "addr:postcode":"h9s 4l3",
    "iso:country":"CA",
    "sg:city":"Pointe-Claire",
    "sg:classifiers":[
        {
            "category":"Shopping",
            "subcategory":"Clothing, Apparel, & Fashions",
            "type":"Retail Goods"
        }
    ],
    "sg:phone":"+1 514 695 0480",
    "sg:postcode":"H9S 4L3",
    "sg:province":"QC",
    "sg:tags":[
        "infant",
        "wear"
    ],
    "wof:name":"Village D'Enfants",
    "wof:placetype":"venue"
},
  "geometry": {"coordinates":[-73.82575199999999,45.428932],"type":"Point"}
}