{
  "type": "Feature",
  "properties": {
    "addr:full":"321 Seymour Blvd North Vancouver BC V7J 2J4",
    "addr:housenumber":"321",
    "addr:postcode":"v7j 2j4",
    "addr:street":"Seymour Blvd",
    "iso:country":"CA",
    "sg:address":"321 Seymour Blvd",
    "sg:city":"North Vancouver",
    "sg:classifiers":[
        {
            "category":"Organizations",
            "subcategory":"Community Association",
            "type":"Services"
        }
    ],
    "sg:phone":"+1 604 988 8807",
    "sg:postcode":"V7J 2J4",
    "sg:province":"BC",
    "sg:tags":[
        "native"
    ],
    "wof:name":"Squamish Nation Income Assist",
    "wof:placetype":"venue"
},
  "geometry": {"coordinates":[-123.02391799999999,49.30809],"type":"Point"}
}