{
  "type": "Feature",
  "properties": {
    "addr:full":"1 Chvo Dr Carbonear NL A1Y 1A2",
    "addr:housenumber":"1",
    "addr:postcode":"a1y 1a2",
    "addr:street":"Chvo Dr",
    "iso:country":"CA",
    "sg:address":"1 Chvo Dr",
    "sg:city":"Carbonear",
    "sg:classifiers":[
        {
            "category":"Communications",
            "subcategory":"Radio Station",
            "type":"Services"
        }
    ],
    "sg:phone":"+1 709 596 1560",
    "sg:postcode":"A1Y 1A2",
    "sg:province":"NL",
    "sg:tags":[
        "company",
        "broadcasting"
    ],
    "wof:name":"Chvo",
    "wof:placetype":"venue"
},
  "geometry": {"coordinates":[-53.2294998169,47.7363815308],"type":"Point"}
}