{
  "type": "Feature",
  "properties": {
    "addr:full":"180 Yorkland Blvd North York ON M2J 1R5",
    "addr:housenumber":"180",
    "addr:postcode":"m2j 1r5",
    "addr:street":"Yorkland Blvd",
    "iso:country":"CA",
    "sg:address":"180 Yorkland Blvd",
    "sg:city":"North York",
    "sg:classifiers":[
        {
            "category":"Organizations",
            "subcategory":"Membership Organization",
            "type":"Services"
        }
    ],
    "sg:phone":"+1 416 502 8711",
    "sg:postcode":"M2J 1R5",
    "sg:province":"ON",
    "sg:tags":[
        "athletic"
    ],
    "wof:name":"Toronto Police Amateur Athltc",
    "wof:placetype":"venue"
},
  "geometry": {"coordinates":[-79.334778,43.770828],"type":"Point"}
}