{
  "type": "Feature",
  "properties": {
    "addr:full":"Thunder Bay ON P7A 4T6",
    "addr:postcode":"p7a 4t6",
    "iso:country":"CA",
    "sg:city":"Thunder Bay",
    "sg:classifiers":[
        {
            "category":"Health Services",
            "subcategory":"Doctor",
            "type":"Services"
        }
    ],
    "sg:phone":"+1 807 345 1751",
    "sg:postcode":"P7A 4T6",
    "sg:province":"ON",
    "sg:tags":[
        "dentist"
    ],
    "wof:name":"Ballantyne, Doug DDS",
    "wof:placetype":"venue"
},
  "geometry": {"coordinates":[-89.22013099999999,48.437302],"type":"Point"}
}