{
  "type": "Feature",
  "properties": {
    "addr:full":"Scarborough ON M1H 2V8",
    "addr:postcode":"m1h 2v8",
    "iso:country":"CA",
    "sg:city":"Scarborough",
    "sg:classifiers":[
        {
            "category":"Home & Garden",
            "subcategory":"Home Furnishings",
            "type":"Retail Goods"
        }
    ],
    "sg:phone":"+1 416 431 4428",
    "sg:postcode":"M1H 2V8",
    "sg:province":"ON",
    "sg:tags":[
        "bathroom",
        "fixture",
        "accessory"
    ],
    "wof:name":"Chateau Marble Mfrs",
    "wof:placetype":"venue"
},
  "geometry": {"coordinates":[-79.238716,43.775078],"type":"Point"}
}