{
  "type": "Feature",
  "properties": {
    "addr:full":"9504 37 Ave NW Edmonton AB T6E 5K3",
    "addr:housenumber":"9504",
    "addr:postcode":"t6e 5k3",
    "addr:street":"37 Ave Nw",
    "iso:country":"CA",
    "sg:address":"9504 37 Ave NW",
    "sg:city":"Edmonton",
    "sg:classifiers":[
        {
            "category":"Organizations",
            "subcategory":"Professional Association",
            "type":"Services"
        }
    ],
    "sg:phone":"+1 780 430 1716",
    "sg:postcode":"T6E 5K3",
    "sg:province":"AB",
    "sg:tags":[
        "club"
    ],
    "wof:name":"Asian Youth Club of Edmonton",
    "wof:placetype":"venue"
},
  "geometry": {"coordinates":[-113.47644043,53.4722480774],"type":"Point"}
}