{
  "type": "Feature",
  "properties": {
    "addr:full":"117 Main St Dartmouth NS B2X 1R6",
    "addr:housenumber":"117",
    "addr:postcode":"b2x 1r6",
    "addr:street":"Main St",
    "iso:country":"CA",
    "sg:address":"117 Main St",
    "sg:city":"Dartmouth",
    "sg:classifiers":[
        {
            "category":"Personal",
            "subcategory":"Beauty Salon",
            "type":"Services"
        }
    ],
    "sg:phone":"+1 902 462 5911",
    "sg:postcode":"B2X 1R6",
    "sg:province":"NS",
    "wof:name":"Salon 117 Hair Design",
    "wof:placetype":"venue"
},
  "geometry": {"coordinates":[-63.520981,44.686321],"type":"Point"}
}