{
  "type": "Feature",
  "properties": {
    "addr:full":"159 Rue Principale Saint-Valerien-DE-Rimouski QC G0L 4E0",
    "addr:housenumber":"159",
    "addr:postcode":"g0l 4e0",
    "addr:street":"Rue Principale",
    "iso:country":"CA",
    "sg:address":"159 Rue Principale",
    "sg:city":"Saint-Valerien-DE-Rimouski",
    "sg:classifiers":[
        {
            "category":"Education",
            "subcategory":"School",
            "type":"Public Place"
        }
    ],
    "sg:phone":"+1 418 736 4725",
    "sg:postcode":"G0L 4E0",
    "sg:province":"QC",
    "wof:name":"Ecole St-Rosaire",
    "wof:placetype":"venue"
},
  "geometry": {"coordinates":[-68.52467346189999,48.4492950439],"type":"Point"}
}