{
  "type": "Feature",
  "properties": {
    "addr:full":"1658 Bedford Hwy Bedford NS B4A 2X9",
    "addr:housenumber":"1658",
    "addr:postcode":"b4a 2x9",
    "addr:street":"Bedford Hwy",
    "iso:country":"CA",
    "sg:address":"1658 Bedford Hwy",
    "sg:city":"Bedford",
    "sg:classifiers":[
        {
            "category":"Restaurant",
            "type":"Food & Drink"
        }
    ],
    "sg:phone":"+1 902 835 8726",
    "sg:postcode":"B4A 2X9",
    "sg:province":"NS",
    "wof:name":"Ponderosa Steak House",
    "wof:placetype":"venue"
},
  "geometry": {"coordinates":[-63.6548042297,44.7364006042],"type":"Point"}
}