{
  "type": "Feature",
  "properties": {
    "addr:full":"9800 Highway 95A Cranbrook BC V1C 7C6",
    "addr:housenumber":"9800",
    "addr:postcode":"v1c 7c6",
    "addr:street":"Highway 95A",
    "iso:country":"CA",
    "sg:address":"9800 Highway 95A",
    "sg:city":"Cranbrook",
    "sg:classifiers":[
        {
            "category":"Sports & Exercise",
            "subcategory":"Golf",
            "type":"Entertainment"
        }
    ],
    "sg:phone":"+1 250 427 2825",
    "sg:postcode":"V1C 7C6",
    "sg:province":"BC",
    "sg:tags":[
        "course"
    ],
    "wof:name":"Way-Lyn Ranch Golf Course",
    "wof:placetype":"venue"
},
  "geometry": {"coordinates":[-115.768699646,49.5135002136],"type":"Point"}
}