{
  "type": "Feature",
  "properties": {
    "iso:country":"CA",
    "sg:address":"547 Michigan St",
    "sg:city":"Victoria",
    "sg:classifiers":[
        {
            "category":"Social Services",
            "type":"Services"
        }
    ],
    "sg:phone":"+1 250 360 2020",
    "sg:postcode":"V8V 1S5",
    "sg:province":"BC",
    "sg:tags":[
        "community"
    ],
    "wof:name":"Glendale Foundation-Research",
    "wof:placetype":"venue"
},
  "geometry": {"coordinates":[-123.37104034399999,48.4168815613],"type":"Point"}
}