{
  "type": "Feature",
  "properties": {
    "addr:full":"1527 Cliveden Ave Delta BC V3M 6P7",
    "addr:housenumber":"1527",
    "addr:postcode":"v3m 6p7",
    "addr:street":"Cliveden Ave",
    "iso:country":"CA",
    "sg:address":"1527 Cliveden Ave",
    "sg:city":"Delta",
    "sg:classifiers":[
        {
            "category":"Wholesale",
            "subcategory":"Drugs",
            "type":"Manufacturing & Wholesale Goods"
        }
    ],
    "sg:phone":"+1 604 525 5052",
    "sg:postcode":"V3M 6P7",
    "sg:province":"BC",
    "sg:tags":[
        "pharmaceutical",
        "product"
    ],
    "wof:name":"Phytogen Life Sciences Inc",
    "wof:placetype":"venue"
},
  "geometry": {"coordinates":[-122.96601104699999,49.1654472351],"type":"Point"}
}