{
  "type": "Feature",
  "properties": {
    "addr:full":"11902 100 St Grande Prairie AB T8V 4H5",
    "addr:housenumber":"11902",
    "addr:postcode":"t8v 4h5",
    "addr:street":"100 St",
    "iso:country":"CA",
    "sg:address":"11902 100 St",
    "sg:city":"Grande Prairie",
    "sg:classifiers":[
        {
            "category":"Travel",
            "subcategory":"Hotels & Motels",
            "type":"Entertainment"
        }
    ],
    "sg:phone":"+1 780 532 1040",
    "sg:postcode":"T8V 4H5",
    "sg:province":"AB",
    "wof:name":"Silver Crest Lodge",
    "wof:placetype":"venue"
},
  "geometry": {"coordinates":[-118.79520416299999,55.1883583069],"type":"Point"}
}