{
  "type": "Feature",
  "properties": {
    "iso:country":"CA",
    "sg:city":"Victoria",
    "sg:classifiers":[
        {
            "category":"Health Services",
            "subcategory":"Doctor",
            "type":"Services"
        }
    ],
    "sg:phone":"+1 250 598 3200",
    "sg:postcode":"V8P 5G8",
    "sg:province":"BC",
    "sg:tags":[
        "clinic"
    ],
    "wof:name":"Shelbourne Medical Treatment",
    "wof:placetype":"venue"
},
  "geometry": {"coordinates":[-123.33323669400001,48.4481506348],"type":"Point"}
}