{
  "type": "Feature",
  "properties": {
    "addr:full":"611 Rue Jean-Bourdon Lanoraie QC J0K 1E0",
    "addr:housenumber":"611",
    "addr:postcode":"j0k 1e0",
    "addr:street":"Rue Jean-Bourdon",
    "iso:country":"CA",
    "sg:address":"611 Rue Jean-Bourdon",
    "sg:city":"Lanoraie",
    "sg:classifiers":[
        {
            "category":"Home & Garden",
            "subcategory":"Household Appliances",
            "type":"Retail Goods"
        }
    ],
    "sg:phone":"+1 450 836 1221",
    "sg:postcode":"J0K 1E0",
    "sg:province":"QC",
    "wof:name":"Electromenager Sans Frontieres",
    "wof:placetype":"venue"
},
  "geometry": {"coordinates":[-73.19955400000001,46.015495],"type":"Point"}
}