{
  "type": "Feature",
  "properties": {
    "iso:country":"CA",
    "sg:address":"95 Rue Morin",
    "sg:city":"Sainte-Adele",
    "sg:classifiers":[
        {
            "category":"Retail",
            "subcategory":"Repair Shop",
            "type":"Services"
        }
    ],
    "sg:phone":"+1 450 229 4788",
    "sg:postcode":"J8B 2P6",
    "sg:province":"QC",
    "sg:tags":[
        "upholsterer"
    ],
    "wof:name":"Belair Decoration",
    "wof:placetype":"venue"
},
  "geometry": {"coordinates":[-74.1378250122,45.9506111145],"type":"Point"}
}