{
  "type": "Feature",
  "properties": {
    "addr:full":"10708 113 Ave Fort St John BC V1J 6H1",
    "addr:housenumber":"10708",
    "addr:postcode":"v1j 6h1",
    "addr:street":"113 Ave",
    "iso:country":"CA",
    "sg:address":"10708 113 Ave",
    "sg:city":"Fort St John",
    "sg:classifiers":[
        {
            "category":"Professional",
            "subcategory":"Computer Services",
            "type":"Services"
        }
    ],
    "sg:phone":"+1 250 262 0013",
    "sg:postcode":"V1J 6H1",
    "sg:province":"BC",
    "sg:tags":[
        "consultant",
        "designer"
    ],
    "wof:name":"Systems Solutions",
    "wof:placetype":"venue"
},
  "geometry": {"coordinates":[-120.85991668699999,56.2579994202],"type":"Point"}
}