{
  "type": "Feature",
  "properties": {
    "addr:full":"11232 Dartford St Maple Ridge BC V2X 1V1",
    "addr:housenumber":"11232",
    "addr:postcode":"v2x 1v1",
    "addr:street":"Dartford St",
    "iso:country":"CA",
    "sg:address":"11232 Dartford St",
    "sg:city":"Maple Ridge",
    "sg:classifiers":[
        {
            "category":"Food & Beverages",
            "subcategory":"Liquor & Beverages",
            "type":"Retail Goods"
        }
    ],
    "sg:phone":"+1 604 465 9411",
    "sg:postcode":"V2X 1V1",
    "sg:province":"BC",
    "sg:tags":[
        "pub"
    ],
    "wof:name":"By Baileys Pub",
    "wof:placetype":"venue"
},
  "geometry": {"coordinates":[-122.649475098,49.2066688538],"type":"Point"}
}