{
  "type": "Feature",
  "properties": {
    "iso:country":"CA",
    "sg:address":"7461 Middle Line",
    "sg:city":"Charing Cross",
    "sg:classifiers":[
        {
            "category":"Building & Trades",
            "subcategory":"Construction",
            "type":"Services"
        }
    ],
    "sg:phone":"+1 519 354 6280",
    "sg:postcode":"N0P 1G0",
    "sg:province":"ON",
    "sg:tags":[
        "concrete",
        "contractor"
    ],
    "wof:name":"W V Concrete Floors",
    "wof:placetype":"venue"
},
  "geometry": {"coordinates":[-82.13283538819999,42.3081092834],"type":"Point"}
}