{
  "type": "Feature",
  "properties": {
    "iso:country":"CA",
    "sg:address":"159 Birch St",
    "sg:city":"Collingwood",
    "sg:classifiers":[
        {
            "category":"Health Services",
            "subcategory":"Doctor",
            "type":"Services"
        }
    ],
    "sg:phone":"+1 705 445 2827",
    "sg:postcode":"L9Y 2V4",
    "sg:province":"ON",
    "sg:tags":[
        "physician",
        "surgeon"
    ],
    "wof:name":"Wells, Peter B MD",
    "wof:placetype":"venue"
},
  "geometry": {"coordinates":[-80.2226715088,44.4988975525],"type":"Point"}
}