{
  "type": "Feature",
  "properties": {
    "addr:full":"Blindfold Lake # Eb172 Kenora ON P9N 3X5",
    "addr:postcode":"p9n 3x5",
    "iso:country":"CA",
    "sg:address":"Blindfold Lake # Eb172",
    "sg:city":"Kenora",
    "sg:classifiers":[
        {
            "category":"Travel",
            "subcategory":"Hotels & Motels",
            "type":"Entertainment"
        }
    ],
    "sg:phone":"+1 807 548 4766",
    "sg:postcode":"P9N 3X5",
    "sg:province":"ON",
    "sg:tags":[
        "resort"
    ],
    "wof:name":"Camp Waterfall",
    "wof:placetype":"venue"
},
  "geometry": {"coordinates":[-94.4893112183,49.7706260681],"type":"Point"}
}