{
  "type": "Feature",
  "properties": {
    "addr:full":"Etobicoke ON M9W 6V6",
    "addr:postcode":"m9w 6v6",
    "iso:country":"CA",
    "sg:city":"Etobicoke",
    "sg:classifiers":[
        {
            "category":"Retail",
            "subcategory":"Repair Shop",
            "type":"Services"
        }
    ],
    "sg:phone":"+1 416 798 9954",
    "sg:postcode":"M9W 6V6",
    "sg:province":"ON",
    "sg:tags":[
        "equipment",
        "dental",
        "refinishing"
    ],
    "wof:name":"Servinet Dental Repair Inc",
    "wof:placetype":"venue"
},
  "geometry": {"coordinates":[-79.627892,43.747742],"type":"Point"}
}