{
  "type": "Feature",
  "properties": {
    "iso:country":"CA",
    "sg:address":"2632 Millar Ave",
    "sg:city":"Saskatoon",
    "sg:classifiers":[
        {
            "category":"Freight",
            "type":"Transportation"
        }
    ],
    "sg:phone":"+1 306 683 1430",
    "sg:postcode":"S7K 4C8",
    "sg:province":"SK",
    "sg:tags":[
        "trucking"
    ],
    "wof:name":"Day & Ross Inc",
    "wof:placetype":"venue"
},
  "geometry": {"coordinates":[-106.646629334,52.1691131592],"type":"Point"}
}