{
  "type": "Feature",
  "properties": {
    "addr:full":"1923 5 Ave S Lethbridge AB T1J 0W7",
    "addr:housenumber":"1923",
    "addr:postcode":"t1j 0w7",
    "addr:street":"5 Ave S",
    "iso:country":"CA",
    "sg:address":"1923 5 Ave S",
    "sg:city":"Lethbridge",
    "sg:classifiers":[
        {
            "category":"Education",
            "subcategory":"School",
            "type":"Public Place"
        }
    ],
    "sg:phone":"+1 403 327 3098",
    "sg:postcode":"T1J 0W7",
    "sg:province":"AB",
    "wof:name":"St Mary's School",
    "wof:placetype":"venue"
},
  "geometry": {"coordinates":[-112.81443786600001,49.6935806274],"type":"Point"}
}