{
  "type": "Feature",
  "properties": {
    "addr:full":"10624 148 St NW Edmonton AB T5N 3H1",
    "addr:housenumber":"10624",
    "addr:postcode":"t5n 3h1",
    "addr:street":"148 St Nw",
    "iso:country":"CA",
    "sg:address":"10624 148 St NW",
    "sg:city":"Edmonton",
    "sg:classifiers":[
        {
            "category":"Building & Trades",
            "subcategory":"Construction",
            "type":"Services"
        }
    ],
    "sg:phone":"+1 780 454 6931",
    "sg:postcode":"T5N 3H1",
    "sg:province":"AB",
    "sg:tags":[
        "waterproofing",
        "contractor"
    ],
    "wof:name":"Du-Rite Restoration CO Ltd",
    "wof:placetype":"venue"
},
  "geometry": {"coordinates":[-113.57625579800001,53.5491294861],"type":"Point"}
}