{
  "type": "Feature",
  "properties": {
    "iso:country":"CA",
    "sg:address":"481 Rue Bertrand",
    "sg:city":"Cap-DE-LA-Madeleine",
    "sg:classifiers":[
        {
            "category":"Retail",
            "subcategory":"Auto Repair",
            "type":"Services"
        }
    ],
    "sg:phone":"+1 819 378 2031",
    "sg:postcode":"G8T 5Y4",
    "sg:province":"QC",
    "sg:tags":[
        "transmission",
        "automobile",
        "repairing"
    ],
    "wof:name":"Garage Paul Vallee",
    "wof:placetype":"venue"
},
  "geometry": {"coordinates":[-72.529259,46.376583],"type":"Point"}
}