{
  "type": "Feature",
  "properties": {
    "iso:country":"CA",
    "sg:address":"99 Horton St W",
    "sg:city":"London",
    "sg:classifiers":[
        {
            "category":"Health Services",
            "subcategory":"Doctor",
            "type":"Services"
        }
    ],
    "sg:phone":"+1 519 675 0330",
    "sg:postcode":"N6J 4Y6",
    "sg:province":"ON",
    "sg:tags":[
        "dentist"
    ],
    "wof:name":"Baby, Paula DDS",
    "wof:placetype":"venue"
},
  "geometry": {"coordinates":[-81.2648239136,42.9764976501],"type":"Point"}
}