{
  "type": "Feature",
  "properties": {
    "addr:full":"187 Rue Commerciale Saint-Damien-DE-Buckland QC G0R 2Y0",
    "addr:housenumber":"187",
    "addr:postcode":"g0r 2y0",
    "addr:street":"Rue Commerciale",
    "iso:country":"CA",
    "sg:address":"187 Rue Commerciale",
    "sg:city":"Saint-Damien-DE-Buckland",
    "sg:classifiers":[
        {
            "category":"Food & Beverages",
            "subcategory":"Groceries & Convenience Stores",
            "type":"Retail Goods"
        }
    ],
    "sg:phone":"+1 418 789 2961",
    "sg:postcode":"G0R 2Y0",
    "sg:province":"QC",
    "sg:tags":[
        "grocer"
    ],
    "wof:name":"Guillemette Alimentation Inc",
    "wof:placetype":"venue"
},
  "geometry": {"coordinates":[-70.65688323969999,46.6256828308],"type":"Point"}
}