{
  "type": "Feature",
  "properties": {
    "addr:full":"8864 Boul Saint-Michel Montreal QC H1Z 3G4",
    "addr:housenumber":"8864",
    "addr:postcode":"h1z 3g4",
    "addr:street":"Boul Saint-Michel",
    "iso:country":"CA",
    "sg:address":"8864 Boul Saint-Michel",
    "sg:city":"Montreal",
    "sg:classifiers":[
        {
            "category":"Shopping",
            "subcategory":"Used Merchandise",
            "type":"Retail Goods"
        }
    ],
    "sg:phone":"+1 514 383 6006",
    "sg:postcode":"H1Z 3G4",
    "sg:province":"QC",
    "sg:tags":[
        "flea",
        "market"
    ],
    "wof:name":"Bazar St-Michel",
    "wof:placetype":"venue"
},
  "geometry": {"coordinates":[-73.625,45.5703849792],"type":"Point"}
}