{
  "type": "Feature",
  "properties": {
    "addr:full":"Moose Jaw SK S6H 3K1",
    "addr:postcode":"s6h 3k1",
    "iso:country":"CA",
    "sg:city":"Moose Jaw",
    "sg:classifiers":[
        {
            "category":"Real Estate",
            "subcategory":"Surveying",
            "type":"Services"
        }
    ],
    "sg:phone":"+1 306 692 3775",
    "sg:postcode":"S6H 3K1",
    "sg:province":"SK",
    "sg:tags":[
        "surveyor"
    ],
    "wof:name":"General Surveys Ltd",
    "wof:placetype":"venue"
},
  "geometry": {"coordinates":[-105.53497299999999,50.392738],"type":"Point"}
}