{
  "type": "Feature",
  "properties": {
    "addr:full":"General Delivery Torrington AB T0M 2B0",
    "addr:postcode":"t0m 2b0",
    "iso:country":"CA",
    "sg:address":"General Delivery",
    "sg:city":"Torrington",
    "sg:classifiers":[
        {
            "category":"Recreation",
            "type":"Entertainment"
        }
    ],
    "sg:phone":"+1 403 631 2163",
    "sg:postcode":"T0M 2B0",
    "sg:province":"AB",
    "sg:tags":[
        "club",
        "curling"
    ],
    "wof:name":"Torrington Curling Club",
    "wof:placetype":"venue"
},
  "geometry": {"coordinates":[-113.606987,51.794552],"type":"Point"}
}