{
  "type": "Feature",
  "properties": {
    "addr:full":"7476 Simcoe Rd 169 Washago ON L0K 2B0",
    "addr:housenumber":"7476",
    "addr:postcode":"l0k 2b0",
    "addr:street":"Simcoe Rd 169 Washago",
    "iso:country":"CA",
    "sg:address":"7476 Simcoe Rd 169",
    "sg:city":"Washago",
    "sg:classifiers":[
        {
            "category":"Travel",
            "subcategory":"Campground",
            "type":"Entertainment"
        }
    ],
    "sg:phone":"+1 705 689 1543",
    "sg:postcode":"L0K 2B0",
    "sg:province":"ON",
    "wof:name":"Black River Wilderness Park",
    "wof:placetype":"venue"
},
  "geometry": {"coordinates":[-79.2863693237,44.7249984741],"type":"Point"}
}