{
  "type": "Feature",
  "properties": {
    "addr:full":"9920 Fairmount Dr SE Calgary AB T2J 0S4",
    "addr:housenumber":"9920",
    "addr:postcode":"t2j 0s4",
    "addr:street":"Fairmount Dr Se",
    "iso:country":"CA",
    "sg:address":"9920 Fairmount Dr SE",
    "sg:city":"Calgary",
    "sg:classifiers":[
        {
            "category":"Organizations",
            "subcategory":"Religious Organization",
            "type":"Services"
        }
    ],
    "sg:phone":"+1 403 271 0346",
    "sg:postcode":"T2J 0S4",
    "sg:province":"AB",
    "sg:tags":[
        "church"
    ],
    "wof:name":"Trinity Baptist Church",
    "wof:placetype":"venue"
},
  "geometry": {"coordinates":[-114.058418,50.963299],"type":"Point"}
}