{
  "type": "Feature",
  "properties": {
    "addr:full":"56 Cordova St E Vancouver BC V6A 1K2",
    "addr:housenumber":"56",
    "addr:postcode":"v6a 1k2",
    "addr:street":"Cordova St E",
    "iso:country":"CA",
    "sg:address":"56 Cordova St E",
    "sg:city":"Vancouver",
    "sg:classifiers":[
        {
            "category":"Real Estate",
            "subcategory":"Real Estate Agent",
            "type":"Services"
        }
    ],
    "sg:phone":"+1 604 488 1517",
    "sg:postcode":"V6A 1K2",
    "sg:province":"BC",
    "sg:tags":[
        "management"
    ],
    "wof:name":"M Mannette Property Management",
    "wof:placetype":"venue"
},
  "geometry": {"coordinates":[-123.103218,49.282204],"type":"Point"}
}