{
  "type": "Feature",
  "properties": {
    "addr:full":"105 Commerce Valley Dr W Thornhill ON L3T 7W3",
    "addr:housenumber":"105",
    "addr:postcode":"l3t 7w3",
    "addr:street":"Commerce Valley Dr W",
    "iso:country":"CA",
    "sg:address":"105 Commerce Valley Dr W",
    "sg:city":"Thornhill",
    "sg:classifiers":[
        {
            "category":"Professional",
            "subcategory":"Engineering",
            "type":"Services"
        }
    ],
    "sg:phone":"+1 905 886 7022",
    "sg:postcode":"L3T 7W3",
    "sg:province":"ON",
    "sg:tags":[
        "engineer"
    ],
    "wof:name":"Earth Tech Canada Inc",
    "wof:placetype":"venue"
},
  "geometry": {"coordinates":[-79.383308,43.839466],"type":"Point"}
}