{
  "type": "Feature",
  "properties": {
    "iso:country":"CA",
    "sg:address":"7755 Boul Saint-Laurent # 200",
    "sg:city":"Montreal",
    "sg:classifiers":[
        {
            "category":"Wholesale",
            "subcategory":"Apparel",
            "type":"Manufacturing & Wholesale Goods"
        }
    ],
    "sg:phone":"+1 514 273 1573",
    "sg:postcode":"H2R 1X1",
    "sg:province":"QC",
    "sg:tags":[
        "textile"
    ],
    "wof:name":"Allsha Fabric Imports",
    "wof:placetype":"venue"
},
  "geometry": {"coordinates":[-73.626007,45.537586],"type":"Point"}
}