{
  "type": "Feature",
  "properties": {
    "addr:full":"Edmonton AB T6G 1E6",
    "addr:postcode":"t6g 1e6",
    "iso:country":"CA",
    "sg:city":"Edmonton",
    "sg:classifiers":[
        {
            "category":"Professional",
            "subcategory":"Accounting & Tax Preparation",
            "type":"Services"
        }
    ],
    "sg:phone":"+1 780 430 6206",
    "sg:postcode":"T6G 1E6",
    "sg:province":"AB",
    "sg:tags":[
        "accountant"
    ],
    "wof:name":"Davidow & Nelson",
    "wof:placetype":"venue"
},
  "geometry": {"coordinates":[-113.512176514,53.5213928223],"type":"Point"}
}