{
  "type": "Feature",
  "properties": {
    "addr:full":"30 Rue Saint-Andre Saint-Remi QC J0L 2L0",
    "addr:housenumber":"30",
    "addr:postcode":"j0l 2l0",
    "addr:street":"Rue Saint-Andre Saint-Remi",
    "iso:country":"CA",
    "sg:address":"30 Rue Saint-Andre",
    "sg:city":"Saint-Remi",
    "sg:classifiers":[
        {
            "category":"Shopping",
            "subcategory":"Clothing, Apparel, & Fashions",
            "type":"Retail Goods"
        }
    ],
    "sg:phone":"+1 450 454 7967",
    "sg:postcode":"J0L 2L0",
    "sg:province":"QC",
    "sg:tags":[
        "work"
    ],
    "wof:name":"Ventes Universelles Cb Enr",
    "wof:placetype":"venue"
},
  "geometry": {"coordinates":[-73.618736,45.258587],"type":"Point"}
}