{
  "type": "Feature",
  "properties": {
    "addr:full":"69 Lindel Cres Welland ON L3C 3S2",
    "addr:housenumber":"69",
    "addr:postcode":"l3c 3s2",
    "addr:street":"Lindel Cres",
    "iso:country":"CA",
    "sg:address":"69 Lindel Cres",
    "sg:city":"Welland",
    "sg:classifiers":[
        {
            "category":"Building & Trades",
            "subcategory":"Construction",
            "type":"Services"
        }
    ],
    "sg:phone":"+1 905 735 8919",
    "sg:postcode":"L3C 3S2",
    "sg:province":"ON",
    "sg:tags":[
        "painter"
    ],
    "wof:name":"Kertai Painting",
    "wof:placetype":"venue"
},
  "geometry": {"coordinates":[-79.2635345459,43.0060272217],"type":"Point"}
}