{
  "type": "Feature",
  "properties": {
    "addr:full":"65 Rue Saint-Luc Quebec QC G1N 2R3",
    "addr:housenumber":"65",
    "addr:postcode":"g1n 2r3",
    "addr:street":"Rue Saint-Luc",
    "iso:country":"CA",
    "sg:address":"65 Rue Saint-Luc",
    "sg:city":"Quebec",
    "sg:classifiers":[
        {
            "category":"Organizations",
            "subcategory":"Religious Organization",
            "type":"Services"
        }
    ],
    "sg:phone":"+1 418 648 2878",
    "sg:postcode":"G1N 2R3",
    "sg:province":"QC",
    "wof:name":"Marie Jeunesse",
    "wof:placetype":"venue"
},
  "geometry": {"coordinates":[-71.2447280884,46.813041687],"type":"Point"}
}