{
  "type": "Feature",
  "properties": {
    "iso:country":"CA",
    "sg:address":"9064 Commercial St",
    "sg:city":"New Minas",
    "sg:classifiers":[
        {
            "category":"Shopping",
            "subcategory":"Pharmacy",
            "type":"Retail Goods"
        }
    ],
    "sg:phone":"+1 902 681 0728",
    "sg:postcode":"B4N 3E4",
    "sg:province":"NS",
    "wof:name":"Drugstore Pharmacy",
    "wof:placetype":"venue"
},
  "geometry": {"coordinates":[-64.4558334351,45.0674438477],"type":"Point"}
}