{
  "type": "Feature",
  "properties": {
    "addr:full":"1800 Carling Ave Ottawa ON K2A 1E2",
    "addr:housenumber":"1800",
    "addr:postcode":"k2a 1e2",
    "addr:street":"Carling Ave",
    "iso:country":"CA",
    "sg:address":"1800 Carling Ave",
    "sg:city":"Ottawa",
    "sg:classifiers":[
        {
            "category":"Banks & Credit Unions",
            "subcategory":"Bank",
            "type":"Services"
        }
    ],
    "sg:phone":"+1 613 728 1802",
    "sg:postcode":"K2A 1E2",
    "sg:province":"ON",
    "wof:name":"Banque Td",
    "wof:placetype":"venue"
},
  "geometry": {"coordinates":[-75.75471496580001,45.3768882751],"type":"Point"}
}