{
  "type": "Feature",
  "properties": {
    "addr:full":"175 Rte Maritime Forestville QC G0T 1E0",
    "addr:housenumber":"175",
    "addr:postcode":"g0t 1e0",
    "addr:street":"Rte Maritime",
    "iso:country":"CA",
    "sg:address":"175 Rte Maritime",
    "sg:city":"Forestville",
    "sg:classifiers":[
        {
            "category":"Home & Garden",
            "subcategory":"Building Materials",
            "type":"Retail Goods"
        }
    ],
    "sg:phone":"+1 418 587 2218",
    "sg:postcode":"G0T 1E0",
    "sg:province":"QC",
    "sg:tags":[
        "mixed",
        "concrete"
    ],
    "wof:name":"Beton Provincial Ltee",
    "wof:placetype":"venue"
},
  "geometry": {"coordinates":[-69.07977294920001,48.7477035522],"type":"Point"}
}