{
  "type": "Feature",
  "properties": {
    "addr:full":"18 Harlech Crt Thornhill ON L3T 6L5",
    "addr:housenumber":"18",
    "addr:postcode":"l3t 6l5",
    "addr:street":"Harlech Crt",
    "iso:country":"CA",
    "sg:address":"18 Harlech Crt",
    "sg:city":"Thornhill",
    "sg:classifiers":[
        {
            "category":"Retail",
            "subcategory":"Auto Repair",
            "type":"Services"
        }
    ],
    "sg:phone":"+1 905 731 6800",
    "sg:postcode":"L3T 6L5",
    "sg:province":"ON",
    "sg:tags":[
        "repairing",
        "automobile"
    ],
    "wof:name":"Car Care Auto Ctr",
    "wof:placetype":"venue"
},
  "geometry": {"coordinates":[-79.396843,43.825157],"type":"Point"}
}