{
  "type": "Feature",
  "properties": {
    "addr:full":"5180 Smith Dr Richmond BC V6V 2W5",
    "addr:housenumber":"5180",
    "addr:postcode":"v6v 2w5",
    "addr:street":"Smith Dr",
    "iso:country":"CA",
    "sg:address":"5180 Smith Dr",
    "sg:city":"Richmond",
    "sg:classifiers":[
        {
            "category":"Education",
            "subcategory":"School",
            "type":"Public Place"
        }
    ],
    "sg:phone":"+1 604 668 6514",
    "sg:postcode":"V6V 2W5",
    "sg:province":"BC",
    "wof:name":"Hamilton Elementary School",
    "wof:placetype":"venue"
},
  "geometry": {"coordinates":[-122.966103,49.176006],"type":"Point"}
}