{
  "type": "Feature",
  "properties": {
    "addr:full":"Mcdougall Rd Parry Sound ON P2A 2W7",
    "addr:postcode":"p2a 2w7",
    "addr:street":"Mcdougall Rd",
    "iso:country":"CA",
    "sg:address":"Mcdougall Rd",
    "sg:city":"Parry Sound",
    "sg:classifiers":[
        {
            "category":"Restaurant",
            "type":"Food & Drink"
        }
    ],
    "sg:phone":"+1 705 746 4653",
    "sg:postcode":"P2A 2W7",
    "sg:province":"ON",
    "sg:tags":[
        "course",
        "golf"
    ],
    "wof:name":"Deer Run Golf Course",
    "wof:placetype":"venue"
},
  "geometry": {"coordinates":[-80.00811,45.355766],"type":"Point"}
}