{
  "type": "Feature",
  "properties": {
    "iso:country":"CA",
    "sg:city":"Camrose",
    "sg:classifiers":[
        {
            "category":"Sports & Exercise",
            "subcategory":"Golf",
            "type":"Entertainment"
        }
    ],
    "sg:phone":"+1 780 672 6490",
    "sg:postcode":"T4V 2N1",
    "sg:province":"AB",
    "sg:tags":[
        "course"
    ],
    "wof:name":"Whistle Stop Golf Course",
    "wof:placetype":"venue"
},
  "geometry": {"coordinates":[-112.829780579,53.0242347717],"type":"Point"}
}