{
  "type": "Feature",
  "properties": {
    "addr:full":"Montreal QC H3A 2R7",
    "addr:postcode":"h3a 2r7",
    "iso:country":"CA",
    "sg:city":"Montreal",
    "sg:classifiers":[
        {
            "category":"Airline",
            "type":"Transportation"
        }
    ],
    "sg:phone":"+1 514 487 0685",
    "sg:postcode":"H3A 2R7",
    "sg:province":"QC",
    "sg:tags":[
        "company"
    ],
    "wof:name":"Mexicana",
    "wof:placetype":"venue"
},
  "geometry": {"coordinates":[-73.56554412840001,45.5208816528],"type":"Point"}
}