{
  "type": "Feature",
  "properties": {
    "iso:country":"CA",
    "sg:address":"320 Queen St",
    "sg:city":"Ottawa",
    "sg:classifiers":[
        {
            "category":"Shopping",
            "subcategory":"Tobacco",
            "type":"Retail Goods"
        }
    ],
    "sg:phone":"+1 613 232 6635",
    "sg:postcode":"K1A 1G1",
    "sg:province":"ON",
    "sg:tags":[
        "cigarette",
        "cigar",
        "dealer"
    ],
    "wof:name":"United Cigar Stores Ltd",
    "wof:placetype":"venue"
},
  "geometry": {"coordinates":[-75.70397949220001,45.4190406799],"type":"Point"}
}