{
  "type": "Feature",
  "properties": {
    "addr:full":"New Westminster BC V3M 6Z1",
    "addr:postcode":"v3m 6z1",
    "iso:country":"CA",
    "sg:city":"New Westminster",
    "sg:classifiers":[
        {
            "category":"Wholesale",
            "subcategory":"Durable Goods & Equipment",
            "type":"Manufacturing & Wholesale Goods"
        }
    ],
    "sg:phone":"+1 604 526 8545",
    "sg:postcode":"V3M 6Z1",
    "sg:province":"BC",
    "sg:tags":[
        "log",
        "broker"
    ],
    "wof:name":"E R Probyn Ltd",
    "wof:placetype":"venue"
},
  "geometry": {"coordinates":[-122.920692,49.212807],"type":"Point"}
}