{
  "type": "Feature",
  "properties": {
    "addr:full":"32 Gibson St Parry Sound ON P2A 1W9",
    "addr:housenumber":"32",
    "addr:postcode":"p2a 1w9",
    "addr:street":"Gibson St",
    "iso:country":"CA",
    "sg:address":"32 Gibson St",
    "sg:city":"Parry Sound",
    "sg:classifiers":[
        {
            "category":"Home & Garden",
            "subcategory":"Carpets & Floor Coverings",
            "type":"Retail Goods"
        }
    ],
    "sg:phone":"+1 705 746 5421",
    "sg:postcode":"P2A 1W9",
    "sg:province":"ON",
    "sg:tags":[
        "material",
        "wallpaper"
    ],
    "wof:name":"Grey's Paint & Wallpaper",
    "wof:placetype":"venue"
},
  "geometry": {"coordinates":[-80.03531599999999,45.343971],"type":"Point"}
}