{
  "type": "Feature",
  "properties": {
    "addr:full":"168 Hespeler Rd Cambridge ON N1R 6V7",
    "addr:housenumber":"168",
    "addr:postcode":"n1r 6v7",
    "addr:street":"Hespeler Rd",
    "iso:country":"CA",
    "sg:address":"168 Hespeler Rd",
    "sg:city":"Cambridge",
    "sg:classifiers":[
        {
            "category":"Social Services",
            "type":"Services"
        }
    ],
    "sg:phone":"+1 519 623 6970",
    "sg:postcode":"N1R 6V7",
    "sg:province":"ON",
    "sg:tags":[
        "organization",
        "welfare"
    ],
    "wof:name":"Family & Children's Svc",
    "wof:placetype":"venue"
},
  "geometry": {"coordinates":[-80.320038,43.381493],"type":"Point"}
}