{
  "type": "Feature",
  "properties": {
    "addr:full":"2370 Boul Saint-Martin E Laval QC H7E 5A4",
    "addr:housenumber":"2370",
    "addr:postcode":"h7e 5a4",
    "addr:street":"Boul Saint-Martin E",
    "iso:country":"CA",
    "sg:address":"2370 Boul Saint-Martin E",
    "sg:city":"Laval",
    "sg:classifiers":[
        {
            "category":"Health Services",
            "subcategory":"Chiropractor",
            "type":"Services"
        }
    ],
    "sg:phone":"+1 450 669 7090",
    "sg:postcode":"H7E 5A4",
    "sg:province":"QC",
    "wof:name":"Clinique Chiropratique Val-Des",
    "wof:placetype":"venue"
},
  "geometry": {"coordinates":[-73.68506622309999,45.5981025696],"type":"Point"}
}