{
  "type": "Feature",
  "properties": {
    "addr:full":"Oakville ON L6L 6M6",
    "addr:postcode":"l6l 6m6",
    "iso:country":"CA",
    "sg:city":"Oakville",
    "sg:classifiers":[
        {
            "category":"Wholesale",
            "subcategory":"Machinery & Supplies",
            "type":"Manufacturing & Wholesale Goods"
        }
    ],
    "sg:phone":"+1 905 469 8500",
    "sg:postcode":"L6L 6M6",
    "sg:province":"ON",
    "sg:tags":[
        "salon",
        "beauty"
    ],
    "wof:name":"Truso Limited",
    "wof:placetype":"venue"
},
  "geometry": {"coordinates":[-79.7329940796,43.4107246399],"type":"Point"}
}