{
  "type": "Feature",
  "properties": {
    "addr:full":"1438 Broadway St Port Coquitlam BC V3C 5W2",
    "addr:housenumber":"1438",
    "addr:postcode":"v3c 5w2",
    "addr:street":"Broadway St",
    "iso:country":"CA",
    "sg:address":"1438 Broadway St",
    "sg:city":"Port Coquitlam",
    "sg:classifiers":[
        {
            "category":"Manufacturing",
            "subcategory":"Chemicals & Compounds",
            "type":"Manufacturing & Wholesale Goods"
        }
    ],
    "sg:phone":"+1 604 464 5018",
    "sg:postcode":"V3C 5W2",
    "sg:province":"BC",
    "sg:tags":[
        "food",
        "equipment",
        "product",
        "health"
    ],
    "wof:name":"Sunrider International Canada",
    "wof:placetype":"venue"
},
  "geometry": {"coordinates":[-122.76153600000001,49.240646],"type":"Point"}
}