{
  "type": "Feature",
  "properties": {
    "addr:full":"857 Wyandotte St E Windsor ON N9A 3J7",
    "addr:housenumber":"857",
    "addr:postcode":"n9a 3j7",
    "addr:street":"Wyandotte St E",
    "iso:country":"CA",
    "sg:address":"857 Wyandotte St E",
    "sg:city":"Windsor",
    "sg:classifiers":[
        {
            "category":"Shopping",
            "subcategory":"Used Merchandise",
            "type":"Retail Goods"
        }
    ],
    "sg:phone":"+1 519 252 5892",
    "sg:postcode":"N9A 3J7",
    "sg:province":"ON",
    "sg:tags":[
        "pawnbroker"
    ],
    "wof:name":"Economy Exchange Second Hand",
    "wof:placetype":"venue"
},
  "geometry": {"coordinates":[-83.024559,42.318329],"type":"Point"}
}