{
  "type": "Feature",
  "properties": {
    "addr:full":"12900 87 Ave Surrey BC V3W 3H9",
    "addr:housenumber":"12900",
    "addr:postcode":"v3w 3h9",
    "addr:street":"87 Ave",
    "iso:country":"CA",
    "sg:address":"12900 87 Ave",
    "sg:city":"Surrey",
    "sg:classifiers":[
        {
            "category":"Wholesale",
            "subcategory":"Machinery & Supplies",
            "type":"Manufacturing & Wholesale Goods"
        }
    ],
    "sg:phone":"+1 604 594 8431",
    "sg:postcode":"V3W 3H9",
    "sg:province":"BC",
    "sg:tags":[
        "valve"
    ],
    "wof:name":"M A Stewart & Sons Ltd",
    "wof:placetype":"venue"
},
  "geometry": {"coordinates":[-122.86637899999999,49.16069],"type":"Point"}
}