{
  "type": "Feature",
  "properties": {
    "addr:full":"240 Beach Rd Hamilton ON L8L 4B2",
    "addr:housenumber":"240",
    "addr:postcode":"l8l 4b2",
    "addr:street":"Beach Rd",
    "iso:country":"CA",
    "sg:address":"240 Beach Rd",
    "sg:city":"Hamilton",
    "sg:classifiers":[
        {
            "category":"Manufacturing",
            "subcategory":"Metals",
            "type":"Manufacturing & Wholesale Goods"
        }
    ],
    "sg:phone":"+1 905 545 5818",
    "sg:postcode":"L8L 4B2",
    "sg:province":"ON",
    "sg:tags":[
        "production",
        "knife"
    ],
    "wof:name":"Central Welding CO Ltd",
    "wof:placetype":"venue"
},
  "geometry": {"coordinates":[-79.819,43.256207],"type":"Point"}
}