{
  "type": "Feature",
  "properties": {
    "addr:full":"93 Rue DE LA Chapelle Saint-Simeon QC G0T 1X0",
    "addr:housenumber":"93",
    "addr:postcode":"g0t 1x0",
    "addr:street":"Rue De La Chapelle",
    "iso:country":"CA",
    "sg:address":"93 Rue DE LA Chapelle",
    "sg:city":"Saint-Simeon",
    "sg:classifiers":[
        {
            "category":"Building & Trades",
            "subcategory":"Construction",
            "type":"Services"
        }
    ],
    "sg:phone":"+1 418 638 5206",
    "sg:postcode":"G0T 1X0",
    "sg:province":"QC",
    "sg:tags":[
        "general",
        "contractor"
    ],
    "wof:name":"Construction Morneau & Freres",
    "wof:placetype":"venue"
},
  "geometry": {"coordinates":[-69.850227,47.957401],"type":"Point"}
}