{
  "type": "Feature",
  "properties": {
    "addr:full":"St Catharines ON L2R 7N1",
    "addr:postcode":"l2r 7n1",
    "iso:country":"CA",
    "sg:city":"St Catharines",
    "sg:classifiers":[
        {
            "category":"Retail",
            "subcategory":"Auto Repair",
            "type":"Services"
        }
    ],
    "sg:phone":"+1 905 688 2288",
    "sg:postcode":"L2R 7N1",
    "sg:province":"ON",
    "sg:tags":[
        "transmission"
    ],
    "wof:name":"Quality Transmission",
    "wof:placetype":"venue"
},
  "geometry": {"coordinates":[-79.229919,43.169041],"type":"Point"}
}