{
  "type": "Feature",
  "properties": {
    "addr:full":"Kemptville ON K0G 1J0",
    "addr:postcode":"k0g 1j0",
    "iso:country":"CA",
    "sg:city":"Kemptville",
    "sg:classifiers":[
        {
            "category":"Wholesale",
            "subcategory":"Chemicals & Plastics",
            "type":"Manufacturing & Wholesale Goods"
        }
    ],
    "sg:phone":"+1 613 258 3974",
    "sg:postcode":"K0G 1J0",
    "sg:province":"ON",
    "sg:tags":[
        "deodorant"
    ],
    "wof:name":"Flower Pot Productions",
    "wof:placetype":"venue"
},
  "geometry": {"coordinates":[-75.654800415,45.0022201538],"type":"Point"}
}