{
  "type": "Feature",
  "properties": {
    "iso:country":"CA",
    "sg:address":"521 107 Rte",
    "sg:city":"Deleage",
    "sg:classifiers":[
        {
            "category":"Building & Trades",
            "subcategory":"Construction",
            "type":"Services"
        }
    ],
    "sg:phone":"+1 819 441 3026",
    "sg:postcode":"J9E 3A8",
    "sg:province":"QC",
    "sg:tags":[
        "bridge",
        "builder"
    ],
    "wof:name":"Construction Mg",
    "wof:placetype":"venue"
},
  "geometry": {"coordinates":[-75.95938110349999,46.3846244812],"type":"Point"}
}