{
  "type": "Feature",
  "properties": {
    "iso:country":"CA",
    "sg:address":"3251 Boul Henri-Bourassa E",
    "sg:city":"Montreal-Nord",
    "sg:classifiers":[
        {
            "category":"Restaurant",
            "type":"Food & Drink"
        }
    ],
    "sg:phone":"+1 514 852 7777",
    "sg:postcode":"H1H 1H3",
    "sg:province":"QC",
    "wof:name":"Restaurant Paragon II",
    "wof:placetype":"venue"
},
  "geometry": {"coordinates":[-73.65051269529999,45.5842704773],"type":"Point"}
}