{
  "type": "Feature",
  "properties": {
    "iso:country":"CA",
    "sg:address":"15 Bloor St E",
    "sg:city":"Toronto",
    "sg:classifiers":[
        {
            "category":"Food & Beverages",
            "subcategory":"Bakery",
            "type":"Retail Goods"
        }
    ],
    "sg:phone":"+1 416 966 2607",
    "sg:postcode":"M4W 1A9",
    "sg:province":"ON",
    "sg:tags":[
        "shop",
        "cookie"
    ],
    "wof:name":"Monsieur Felix & Mr Norton",
    "wof:placetype":"venue"
},
  "geometry": {"coordinates":[-79.38618469239999,43.6702003479],"type":"Point"}
}