{
  "type": "Feature",
  "properties": {
    "addr:full":"Bromont QC J2L 2Y6",
    "addr:postcode":"j2l 2y6",
    "iso:country":"CA",
    "sg:city":"Bromont",
    "sg:classifiers":[
        {
            "category":"Retail",
            "subcategory":"Auto Repair",
            "type":"Services"
        }
    ],
    "sg:phone":"+1 450 263 0558",
    "sg:postcode":"J2L 2Y6",
    "sg:province":"QC",
    "sg:tags":[
        "repairing",
        "automobile"
    ],
    "wof:name":"Garage Lacroix Roger",
    "wof:placetype":"venue"
},
  "geometry": {"coordinates":[-72.785179,45.277966],"type":"Point"}
}