{
  "type": "Feature",
  "properties": {
    "iso:country":"CA",
    "sg:address":"1239 Queen St",
    "sg:city":"Smithers",
    "sg:classifiers":[
        {
            "category":"Retail",
            "subcategory":"Funeral Services",
            "type":"Services"
        }
    ],
    "sg:phone":"+1 250 847 2441",
    "sg:postcode":"V0J 2N0",
    "sg:province":"BC",
    "sg:tags":[
        "director"
    ],
    "wof:name":"R A Schrader Funeral Home",
    "wof:placetype":"venue"
},
  "geometry": {"coordinates":[-127.1720047,54.7820739746],"type":"Point"}
}