{
  "type": "Feature",
  "properties": {
    "addr:full":"2082 Yonge St Toronto ON M4S 2A3",
    "addr:housenumber":"2082",
    "addr:postcode":"m4s 2a3",
    "addr:street":"Yonge St",
    "iso:country":"CA",
    "sg:address":"2082 Yonge St",
    "sg:city":"Toronto",
    "sg:classifiers":[
        {
            "category":"Shopping",
            "subcategory":"Bicycles & Sporting Goods",
            "type":"Retail Goods"
        }
    ],
    "sg:phone":"+1 416 488 1000",
    "sg:postcode":"M4S 2A3",
    "sg:province":"ON",
    "sg:tags":[
        "diving",
        "instruction"
    ],
    "wof:name":"Water Sports",
    "wof:placetype":"venue"
},
  "geometry": {"coordinates":[-79.3975906372,43.7021369934],"type":"Point"}
}