{
  "type": "Feature",
  "properties": {
    "addr:full":"Belle River ON N0R 1A0",
    "addr:postcode":"n0r 1a0",
    "iso:country":"CA",
    "sg:city":"Belle River",
    "sg:classifiers":[
        {
            "category":"Shopping",
            "subcategory":"Pharmacy",
            "type":"Retail Goods"
        }
    ],
    "sg:phone":"+1 519 728 1119",
    "sg:postcode":"N0R 1A0",
    "sg:province":"ON",
    "wof:name":"Lakeshore Medical Pharmacy",
    "wof:placetype":"venue"
},
  "geometry": {"coordinates":[-82.708832,42.293312],"type":"Point"}
}