{
  "type": "Feature",
  "properties": {
    "addr:full":"14 Rue Fontaine Granby QC J2G 8C6",
    "addr:housenumber":"14",
    "addr:postcode":"j2g 8c6",
    "addr:street":"Rue Fontaine",
    "iso:country":"CA",
    "sg:address":"14 Rue Fontaine",
    "sg:city":"Granby",
    "sg:classifiers":[
        {
            "category":"Building & Trades",
            "subcategory":"Construction",
            "type":"Services"
        }
    ],
    "sg:phone":"+1 450 375 4789",
    "sg:postcode":"J2G 8C6",
    "sg:province":"QC",
    "sg:tags":[
        "concrete",
        "contractor"
    ],
    "wof:name":"Finition DE Beton Robin",
    "wof:placetype":"venue"
},
  "geometry": {"coordinates":[-72.708,45.36219],"type":"Point"}
}