{
  "type": "Feature",
  "properties": {
    "addr:full":"930 Lakefront Prom Mississauga ON L5E 2C4",
    "addr:housenumber":"930",
    "addr:postcode":"l5e 2c4",
    "addr:street":"Lakefront Prom",
    "iso:country":"CA",
    "sg:address":"930 Lakefront Prom",
    "sg:city":"Mississauga",
    "sg:classifiers":[
        {
            "category":"Manufacturing",
            "subcategory":"Tools & Machinery",
            "type":"Manufacturing & Wholesale Goods"
        }
    ],
    "sg:phone":"+1 905 278 9186",
    "sg:postcode":"L5E 2C4",
    "sg:province":"ON",
    "sg:tags":[
        "popcorn",
        "machine"
    ],
    "wof:name":"Wonderland Food & Equipment",
    "wof:placetype":"venue"
},
  "geometry": {"coordinates":[-79.5591049194,43.5738372803],"type":"Point"}
}