{
  "type": "Feature",
  "properties": {
    "addr:full":"Levis QC G6V 6C9",
    "addr:postcode":"g6v 6c9",
    "iso:country":"CA",
    "sg:city":"Levis",
    "sg:classifiers":[
        {
            "category":"Health Services",
            "subcategory":"Chiropractor",
            "type":"Services"
        }
    ],
    "sg:phone":"+1 418 833 4248",
    "sg:postcode":"G6V 6C9",
    "sg:province":"QC",
    "wof:name":"Clinique Chiropratique Couture",
    "wof:placetype":"venue"
},
  "geometry": {"coordinates":[-71.1682357788,46.7894172668],"type":"Point"}
}