{
  "type": "Feature",
  "properties": {
    "iso:country":"CA",
    "sg:address":"165 Queenston Rd",
    "sg:city":"Hamilton",
    "sg:classifiers":[
        {
            "category":"Autos & Motor Vehicles",
            "subcategory":"Automobile Sales",
            "type":"Retail Goods"
        }
    ],
    "sg:phone":"+1 905 544 3100",
    "sg:postcode":"L8K 1G7",
    "sg:province":"ON",
    "sg:tags":[
        "renting",
        "car"
    ],
    "wof:name":"Automotion",
    "wof:placetype":"venue"
},
  "geometry": {"coordinates":[-79.796463,43.235386],"type":"Point"}
}