{
  "type": "Feature",
  "properties": {
    "addr:full":"127 Rue Principale Lambton QC G0M 1H0",
    "addr:housenumber":"127",
    "addr:postcode":"g0m 1h0",
    "addr:street":"Rue Principale",
    "iso:country":"CA",
    "sg:address":"127 Rue Principale",
    "sg:city":"Lambton",
    "sg:classifiers":[
        {
            "category":"Home & Garden",
            "subcategory":"Garden Supply",
            "type":"Retail Goods"
        }
    ],
    "sg:phone":"+1 418 486 7071",
    "sg:postcode":"G0M 1H0",
    "sg:province":"QC",
    "sg:tags":[
        "lawn",
        "mower"
    ],
    "wof:name":"Equipro Andre Bolduc",
    "wof:placetype":"venue"
},
  "geometry": {"coordinates":[-71.08749389650001,45.843547821],"type":"Point"}
}