{
  "type": "Feature",
  "properties": {
    "addr:full":"Victoria BC V9A 4C7",
    "addr:postcode":"v9a 4c7",
    "iso:country":"CA",
    "sg:city":"Victoria",
    "sg:classifiers":[
        {
            "category":"Manufacturing",
            "subcategory":"Lumber",
            "type":"Manufacturing & Wholesale Goods"
        }
    ],
    "sg:phone":"+1 250 383 4428",
    "sg:postcode":"V9A 4C7",
    "sg:province":"BC",
    "sg:tags":[
        "wood"
    ],
    "wof:name":"Dan Rippon Woodworking",
    "wof:placetype":"venue"
},
  "geometry": {"coordinates":[-123.39289100000001,48.431564],"type":"Point"}
}