{
  "type": "Feature",
  "properties": {
    "addr:full":"Scarborough ON M1X 1G4",
    "addr:postcode":"m1x 1g4",
    "iso:country":"CA",
    "sg:city":"Scarborough",
    "sg:classifiers":[
        {
            "category":"Wholesale",
            "subcategory":"Machinery & Supplies",
            "type":"Manufacturing & Wholesale Goods"
        }
    ],
    "sg:phone":"+1 416 321 0990",
    "sg:postcode":"M1X 1G4",
    "sg:province":"ON",
    "sg:tags":[
        "equipment",
        "fitting",
        "hose",
        "coupling",
        "hydraulic"
    ],
    "wof:name":"Dtc Industry Sales Ltd",
    "wof:placetype":"venue"
},
  "geometry": {"coordinates":[-79.2471008301,43.8262443542],"type":"Point"}
}