{
  "type": "Feature",
  "properties": {
    "addr:full":"1809 Mountain Rd Moncton NB E1G 1A7",
    "addr:housenumber":"1809",
    "addr:postcode":"e1g 1a7",
    "addr:street":"Mountain Rd",
    "iso:country":"CA",
    "sg:address":"1809 Mountain Rd",
    "sg:city":"Moncton",
    "sg:classifiers":[
        {
            "category":"Real Estate",
            "subcategory":"Real Estate Agent",
            "type":"Services"
        }
    ],
    "sg:phone":"+1 506 858 0111",
    "sg:postcode":"E1G 1A7",
    "sg:province":"NB",
    "wof:name":"Royal Lepage Town & Kountry",
    "wof:placetype":"venue"
},
  "geometry": {"coordinates":[-64.8477630615,46.121799469],"type":"Point"}
}