{
  "type": "Feature",
  "properties": {
    "addr:full":"5555 S Island Hwy Union Bay BC V0R 3B0",
    "addr:housenumber":"5555",
    "addr:postcode":"v0r 3b0",
    "addr:street":"S Island Hwy Union",
    "iso:country":"CA",
    "sg:address":"5555 S Island Hwy",
    "sg:city":"Union Bay",
    "sg:classifiers":[
        {
            "category":"Food & Beverages",
            "subcategory":"Groceries & Convenience Stores",
            "type":"Retail Goods"
        }
    ],
    "sg:phone":"+1 250 335 2622",
    "sg:postcode":"V0R 3B0",
    "sg:province":"BC",
    "sg:tags":[
        "grocer"
    ],
    "wof:name":"Union Bay Market",
    "wof:placetype":"venue"
},
  "geometry": {"coordinates":[-124.885178,49.581749],"type":"Point"}
}