{
  "type": "Feature",
  "properties": {
    "addr:full":"9 Shady Lane Grand Bend ON N0M 1T0",
    "addr:housenumber":"9",
    "addr:postcode":"n0m 1t0",
    "addr:street":"Shady Lane",
    "iso:country":"CA",
    "sg:address":"9 Shady Lane",
    "sg:city":"Grand Bend",
    "sg:classifiers":[
        {
            "category":"Travel",
            "subcategory":"Hotels & Motels",
            "type":"Entertainment"
        }
    ],
    "sg:phone":"+1 519 238 2008",
    "sg:postcode":"N0M 1T0",
    "sg:province":"ON",
    "sg:tags":[
        "cottage",
        "cabin"
    ],
    "wof:name":"Shady Lane Cottages",
    "wof:placetype":"venue"
},
  "geometry": {"coordinates":[-81.762062,43.313835],"type":"Point"}
}