{
  "type": "Feature",
  "properties": {
    "addr:full":"Richmond BC V6X 1A7",
    "addr:postcode":"v6x 1a7",
    "iso:country":"CA",
    "sg:city":"Richmond",
    "sg:classifiers":[
        {
            "category":"Food & Beverages",
            "subcategory":"Bakery",
            "type":"Retail Goods"
        }
    ],
    "sg:phone":"+1 604 273 7683",
    "sg:postcode":"V6X 1A7",
    "sg:province":"BC",
    "sg:tags":[
        "baker"
    ],
    "wof:name":"Golden Apple Bakery Ltd",
    "wof:placetype":"venue"
},
  "geometry": {"coordinates":[-123.134773,49.170406],"type":"Point"}
}