{
  "type": "Feature",
  "properties": {
    "addr:full":"1350 Peninsula Rd Ucluelet BC V0R 3A0",
    "addr:housenumber":"1350",
    "addr:postcode":"bc v0r 3a0",
    "addr:street":"Peninsula Rd",
    "iso:country":"CA",
    "sg:address":"1350 Peninsula Rd",
    "sg:city":"Ucluelet",
    "sg:classifiers":[
        {
            "category":"Education",
            "subcategory":"School",
            "type":"Public Place"
        }
    ],
    "sg:phone":"+1 250 726 7793",
    "sg:postcode":"V0R 3A0",
    "sg:province":"BC",
    "wof:name":"Ucluelet Elementary School",
    "wof:placetype":"venue"
},
  "geometry": {"coordinates":[-125.54261,48.938026],"type":"Point"}
}