{
  "type": "Feature",
  "properties": {
    "addr:full":"110 Ash St Whitby ON L1N 4A9",
    "addr:housenumber":"110",
    "addr:postcode":"l1n 4a9",
    "addr:street":"Ash St",
    "iso:country":"CA",
    "sg:address":"110 Ash St",
    "sg:city":"Whitby",
    "sg:classifiers":[
        {
            "category":"Organizations",
            "subcategory":"Community Association",
            "type":"Services"
        }
    ],
    "sg:phone":"+1 905 668 6242",
    "sg:postcode":"L1N 4A9",
    "sg:province":"ON",
    "sg:tags":[
        "club"
    ],
    "wof:name":"Durham Celtic Sports",
    "wof:placetype":"venue"
},
  "geometry": {"coordinates":[-78.939545,43.880814],"type":"Point"}
}