{
  "type": "Feature",
  "properties": {
    "addr:full":"234 Primrose Dr # 15 Saskatoon SK S7K 6Y6",
    "addr:housenumber":"234",
    "addr:postcode":"s7k 6y6",
    "addr:street":"Primrose Dr # 15",
    "iso:country":"CA",
    "sg:address":"234 Primrose Dr # 15",
    "sg:city":"Saskatoon",
    "sg:classifiers":[
        {
            "category":"Restaurant",
            "type":"Food & Drink"
        }
    ],
    "sg:phone":"+1 306 242 1100",
    "sg:postcode":"S7K 6Y6",
    "sg:province":"SK",
    "wof:name":"Brothers Two Restaurants",
    "wof:placetype":"venue"
},
  "geometry": {"coordinates":[-106.633354,52.1717],"type":"Point"}
}