{
  "type": "Feature",
  "properties": {
    "iso:country":"CA",
    "sg:address":"930 Prospect St",
    "sg:city":"Fredericton",
    "sg:classifiers":[
        {
            "category":"Professional",
            "subcategory":"Lawyer & Legal Services",
            "type":"Services"
        }
    ],
    "sg:phone":"+1 506 453 9898",
    "sg:postcode":"E3B 2T8",
    "sg:province":"NB",
    "sg:tags":[
        "attorney"
    ],
    "wof:name":"Shepard, A Gordon",
    "wof:placetype":"venue"
},
  "geometry": {"coordinates":[-66.672424,45.943516],"type":"Point"}
}