{
  "type": "Feature",
  "properties": {
    "addr:full":"5643 111 Rte W Amos QC J9T 3A3",
    "addr:housenumber":"5643",
    "addr:postcode":"j9t 3a3",
    "addr:street":"111 Rte W Amos",
    "iso:country":"CA",
    "sg:address":"5643 111 Rte W",
    "sg:city":"Amos",
    "sg:classifiers":[
        {
            "category":"Building & Trades",
            "subcategory":"Construction",
            "type":"Services"
        }
    ],
    "sg:phone":"+1 819 732 4144",
    "sg:postcode":"J9T 3A3",
    "sg:province":"QC",
    "sg:tags":[
        "insulation",
        "heat",
        "contractor"
    ],
    "wof:name":"Isolation Polypro",
    "wof:placetype":"venue"
},
  "geometry": {"coordinates":[-78.04599,48.537704],"type":"Point"}
}