{
  "type": "Feature",
  "properties": {
    "iso:country":"CA",
    "sg:address":"158 Rue Champlain",
    "sg:city":"Hull",
    "sg:classifiers":[
        {
            "category":"Organizations",
            "subcategory":"Professional Association",
            "type":"Services"
        }
    ],
    "sg:phone":"+1 819 777 6311",
    "sg:postcode":"J8X 3R2",
    "sg:province":"QC",
    "wof:name":"Aptafo",
    "wof:placetype":"venue"
},
  "geometry": {"coordinates":[-75.711845,45.430374],"type":"Point"}
}