{
  "type": "Feature",
  "properties": {
    "addr:full":"2385 Rue Des Cypres Jonquiere QC G8A 2E6",
    "addr:housenumber":"2385",
    "addr:postcode":"g8a 2e6",
    "addr:street":"Rue Des Cypres",
    "iso:country":"CA",
    "sg:address":"2385 Rue Des Cypres",
    "sg:city":"Jonquiere",
    "sg:classifiers":[
        {
            "category":"Education",
            "subcategory":"School",
            "type":"Public Place"
        }
    ],
    "sg:phone":"+1 418 547 6663",
    "sg:postcode":"G8A 2E6",
    "sg:province":"QC",
    "wof:name":"Treffle-Gauthier Ecole",
    "wof:placetype":"venue"
},
  "geometry": {"coordinates":[-71.27171300000001,48.405518],"type":"Point"}
}