{
  "type": "Feature",
  "properties": {
    "addr:full":"266 Dalhurst Way NW Calgary AB T3A 1P5",
    "addr:housenumber":"266",
    "addr:postcode":"t3a 1p5",
    "addr:street":"Dalhurst Way Nw",
    "iso:country":"CA",
    "sg:address":"266 Dalhurst Way NW",
    "sg:city":"Calgary",
    "sg:classifiers":[
        {
            "category":"Professional",
            "subcategory":"Business Services",
            "type":"Services"
        }
    ],
    "sg:phone":"+1 403 286 8557",
    "sg:postcode":"T3A 1P5",
    "sg:province":"AB",
    "wof:name":"Parade Display Productions Ltd",
    "wof:placetype":"venue"
},
  "geometry": {"coordinates":[-114.154633,51.110821],"type":"Point"}
}