{
  "type": "Feature",
  "properties": {
    "addr:full":"437 Mount Paul Way Kamloops BC V2H 1A7",
    "addr:housenumber":"437",
    "addr:postcode":"bc v2h 1a7",
    "addr:street":"Mount Paul Way",
    "iso:country":"CA",
    "sg:address":"437 Mount Paul Way",
    "sg:city":"Kamloops",
    "sg:classifiers":[
        {
            "category":"Home & Garden",
            "subcategory":"Building Materials",
            "type":"Retail Goods"
        }
    ],
    "sg:phone":"+1 250 372 5177",
    "sg:postcode":"V2H 1A7",
    "sg:province":"BC",
    "sg:tags":[
        "glass",
        "window",
        "plate"
    ],
    "wof:name":"Aall Glass Ltd",
    "wof:placetype":"venue"
},
  "geometry": {"coordinates":[-120.322502136,50.6858634949],"type":"Point"}
}