{
  "type": "Feature",
  "properties": {
    "addr:full":"North York ON M9L 2Y7",
    "addr:postcode":"m9l 2y7",
    "iso:country":"CA",
    "sg:city":"North York",
    "sg:classifiers":[
        {
            "category":"Manufacturing",
            "subcategory":"Motor Vehicles & Parts",
            "type":"Manufacturing & Wholesale Goods"
        }
    ],
    "sg:phone":"+1 416 748 7706",
    "sg:postcode":"M9L 2Y7",
    "sg:province":"ON",
    "sg:tags":[
        "trophy",
        "medal",
        "award"
    ],
    "wof:name":"Award Ribbons & Rosettes",
    "wof:placetype":"venue"
},
  "geometry": {"coordinates":[-79.556084,43.758678],"type":"Point"}
}