{
  "type": "Feature",
  "properties": {
    "addr:full":"170 Burton Ave Barrie ON L4N 2S1",
    "addr:housenumber":"170",
    "addr:postcode":"l4n 2s1",
    "addr:street":"Burton Ave",
    "iso:country":"CA",
    "sg:address":"170 Burton Ave",
    "sg:city":"Barrie",
    "sg:classifiers":[
        {
            "category":"Retail",
            "subcategory":"Auto Repair",
            "type":"Services"
        }
    ],
    "sg:phone":"+1 705 733 8333",
    "sg:postcode":"L4N 2S1",
    "sg:province":"ON",
    "sg:tags":[
        "repairing",
        "automobile",
        "radiator"
    ],
    "wof:name":"Chau's Radiator & Gastank Ltd",
    "wof:placetype":"venue"
},
  "geometry": {"coordinates":[-79.67989349370001,44.3714103699],"type":"Point"}
}