{
  "type": "Feature",
  "properties": {
    "iso:country":"CA",
    "sg:address":"234 Boul Saint-Luc # 2",
    "sg:city":"Saint-Luc",
    "sg:classifiers":[
        {
            "category":"Restaurant",
            "type":"Food & Drink"
        }
    ],
    "sg:phone":"+1 450 359 8661",
    "sg:postcode":"J2W 1C2",
    "sg:province":"QC",
    "wof:name":"Tim Hortons",
    "wof:placetype":"venue"
},
  "geometry": {"coordinates":[-73.2939605713,45.3521499634],"type":"Point"}
}