{
  "type": "Feature",
  "properties": {
    "addr:full":"North York ON M2H 2E1",
    "addr:postcode":"m2h 2e1",
    "iso:country":"CA",
    "sg:city":"North York",
    "sg:classifiers":[
        {
            "category":"Shopping",
            "subcategory":"Florist",
            "type":"Retail Goods"
        }
    ],
    "sg:phone":"+1 416 491 1566",
    "sg:postcode":"M2H 2E1",
    "sg:province":"ON",
    "wof:name":"Floral Classics",
    "wof:placetype":"venue"
},
  "geometry": {"coordinates":[-79.340363,43.803852],"type":"Point"}
}