{
  "type": "Feature",
  "properties": {
    "addr:full":"424 Av Victoria Saint-Lambert QC J4P 2H9",
    "addr:postcode":"j4p 2h9",
    "addr:street":"424 Av Victoria",
    "iso:country":"CA",
    "sg:address":"424 Av Victoria",
    "sg:city":"Saint-Lambert",
    "sg:classifiers":[
        {
            "category":"Shopping",
            "subcategory":"Clothing, Apparel, & Fashions",
            "type":"Retail Goods"
        }
    ],
    "sg:phone":"+1 450 923 5110",
    "sg:postcode":"J4P 2H9",
    "sg:province":"QC",
    "wof:name":"Boutique 424",
    "wof:placetype":"venue"
},
  "geometry": {"coordinates":[-73.51258900000001,45.501972],"type":"Point"}
}