{
  "type": "Feature",
  "properties": {
    "addr:full":"11 Rang Saint-Joseph Pierreville QC J0G 1J0",
    "addr:housenumber":"11",
    "addr:postcode":"j0g 1j0",
    "addr:street":"Rang Saint-Joseph",
    "iso:country":"CA",
    "sg:address":"11 Rang Saint-Joseph",
    "sg:city":"Pierreville",
    "sg:classifiers":[
        {
            "category":"Building & Trades",
            "subcategory":"Construction",
            "type":"Services"
        }
    ],
    "sg:phone":"+1 450 568 0484",
    "sg:postcode":"J0G 1J0",
    "sg:province":"QC",
    "sg:tags":[
        "contractor"
    ],
    "wof:name":"J C Gill Construction Inc",
    "wof:placetype":"venue"
},
  "geometry": {"coordinates":[-72.8099594116,46.0856781006],"type":"Point"}
}