{
  "type": "Feature",
  "properties": {
    "addr:full":"2 Bloor St W # L16 Toronto ON M4W 3E2",
    "addr:housenumber":"2",
    "addr:postcode":"m4w 3e2",
    "addr:street":"Bloor St W # L16",
    "iso:country":"CA",
    "sg:address":"2 Bloor St W # L16",
    "sg:city":"Toronto",
    "sg:classifiers":[
        {
            "category":"Retail",
            "subcategory":"Laundry & Dry Cleaning",
            "type":"Services"
        }
    ],
    "sg:phone":"+1 416 964 3354",
    "sg:postcode":"M4W 3E2",
    "sg:province":"ON",
    "sg:tags":[
        "cleaners"
    ],
    "wof:name":"Prime Cleaners",
    "wof:placetype":"venue"
},
  "geometry": {"coordinates":[-79.387428,43.670231],"type":"Point"}
}