{
  "type": "Feature",
  "properties": {
    "addr:full":"11469 100 Ave Grande Prairie AB T8V 5M6",
    "addr:housenumber":"11469",
    "addr:postcode":"t8v 5m6",
    "addr:street":"100 Ave",
    "iso:country":"CA",
    "sg:address":"11469 100 Ave",
    "sg:city":"Grande Prairie",
    "sg:classifiers":[
        {
            "category":"Restaurant",
            "type":"Food & Drink"
        }
    ],
    "sg:phone":"+1 780 513 2330",
    "sg:postcode":"T8V 5M6",
    "sg:province":"AB",
    "wof:name":"Mc Donald's",
    "wof:placetype":"venue"
},
  "geometry": {"coordinates":[-118.84388,55.170376],"type":"Point"}
}