{
  "type": "Feature",
  "properties": {
    "iso:country":"CA",
    "sg:address":"329 March Rd",
    "sg:city":"Kanata",
    "sg:classifiers":[
        {
            "category":"Shopping",
            "subcategory":"Florist",
            "type":"Retail Goods"
        }
    ],
    "sg:phone":"+1 613 599 6849",
    "sg:postcode":"K2K 2E1",
    "sg:province":"ON",
    "wof:name":"Trillium Floral Designs",
    "wof:placetype":"venue"
},
  "geometry": {"coordinates":[-75.9080734253,45.3355331421],"type":"Point"}
}