{
  "type": "Feature",
  "properties": {
    "addr:full":"11852 Highway 97 # 8 Winfield BC V4V 1E3",
    "addr:housenumber":"11852",
    "addr:postcode":"v4v 1e3",
    "addr:street":"Highway 97 # 8",
    "iso:country":"CA",
    "sg:address":"11852 Highway 97 # 8",
    "sg:city":"Winfield",
    "sg:classifiers":[
        {
            "category":"Restaurant",
            "type":"Food & Drink"
        }
    ],
    "sg:phone":"+1 250 766 4171",
    "sg:postcode":"V4V 1E3",
    "sg:province":"BC",
    "wof:name":"Winfield Chinese Restaurant",
    "wof:placetype":"venue"
},
  "geometry": {"coordinates":[-119.405601502,50.0245361328],"type":"Point"}
}