{
  "type": "Feature",
  "properties": {
    "addr:full":"17 Linton Park Rd Belleville ON K8N 4K7",
    "addr:housenumber":"17",
    "addr:postcode":"k8n 4k7",
    "addr:street":"Linton Park Rd",
    "iso:country":"CA",
    "sg:address":"17 Linton Park Rd",
    "sg:city":"Belleville",
    "sg:classifiers":[
        {
            "category":"Social Services",
            "type":"Services"
        }
    ],
    "sg:phone":"+1 613 968 5350",
    "sg:postcode":"K8N 4K7",
    "sg:province":"ON",
    "sg:tags":[
        "organization",
        "agency",
        "adoption",
        "welfare"
    ],
    "wof:name":"Campbell Josefina Licensee",
    "wof:placetype":"venue"
},
  "geometry": {"coordinates":[-77.35393500000001,44.176109],"type":"Point"}
}