{
  "type": "Feature",
  "properties": {
    "iso:country":"CA",
    "sg:address":"PO Box 247",
    "sg:city":"Onoway",
    "sg:classifiers":[
        {
            "category":"Farming",
            "subcategory":"Nursery",
            "type":"Manufacturing & Wholesale Goods"
        }
    ],
    "sg:phone":"+1 780 967 2016",
    "sg:postcode":"T0E 1V0",
    "sg:province":"AB",
    "sg:tags":[
        "greenhouse"
    ],
    "wof:name":"Hillside Greenhouses",
    "wof:placetype":"venue"
},
  "geometry": {"coordinates":[-114.19152832,53.7030181885],"type":"Point"}
}