{
  "type": "Feature",
  "properties": {
    "addr:full":"88 Mountain Ave Hamilton ON L8P 4G2",
    "addr:housenumber":"88",
    "addr:postcode":"l8p 4g2",
    "addr:street":"Mountain Ave",
    "iso:country":"CA",
    "sg:address":"88 Mountain Ave",
    "sg:city":"Hamilton",
    "sg:classifiers":[
        {
            "category":"Professional",
            "subcategory":"Engineering",
            "type":"Services"
        }
    ],
    "sg:phone":"+1 905 664 9441",
    "sg:postcode":"L8P 4G2",
    "sg:province":"ON",
    "sg:tags":[
        "vibration",
        "measurement"
    ],
    "wof:name":"Itr Inc",
    "wof:placetype":"venue"
},
  "geometry": {"coordinates":[-79.8906707764,43.2465629578],"type":"Point"}
}