{
  "type": "Feature",
  "properties": {
    "addr:full":"174 Rue Adelaide Sorel-Tracy QC J3P 1X2",
    "addr:housenumber":"174",
    "addr:postcode":"j3p 1x2",
    "addr:street":"Rue Adelaide",
    "iso:country":"CA",
    "sg:address":"174 Rue Adelaide",
    "sg:city":"Sorel-Tracy",
    "sg:classifiers":[
        {
            "category":"Manufacturing",
            "subcategory":"Signs",
            "type":"Manufacturing & Wholesale Goods"
        }
    ],
    "sg:phone":"+1 450 780 0928",
    "sg:postcode":"J3P 1X2",
    "sg:province":"QC",
    "wof:name":"Mike Enseignes",
    "wof:placetype":"venue"
},
  "geometry": {"coordinates":[-73.105721,46.040707],"type":"Point"}
}