{
  "type": "Feature",
  "properties": {
    "iso:country":"CA",
    "sg:address":"801 Arrow Rd",
    "sg:city":"North York",
    "sg:classifiers":[
        {
            "category":"Shopping",
            "subcategory":"Computers & Home Electronics",
            "type":"Retail Goods"
        }
    ],
    "sg:phone":"+1 416 741 5476",
    "sg:postcode":"M9M 2L4",
    "sg:province":"ON",
    "sg:tags":[
        "equipment",
        "electronic",
        "supply"
    ],
    "wof:name":"Internet Electronics",
    "wof:placetype":"venue"
},
  "geometry": {"coordinates":[-79.5310134888,43.7483062744],"type":"Point"}
}