{
  "type": "Feature",
  "properties": {
    "addr:full":"67 Joseph St North Bay ON P1A 1L9",
    "addr:housenumber":"67",
    "addr:postcode":"p1a 1l9",
    "addr:street":"Joseph St",
    "iso:country":"CA",
    "sg:address":"67 Joseph St",
    "sg:city":"North Bay",
    "sg:classifiers":[
        {
            "category":"Professional",
            "subcategory":"Computer Services",
            "type":"Services"
        }
    ],
    "sg:phone":"+1 705 495 1232",
    "sg:postcode":"P1A 1L9",
    "sg:province":"ON",
    "sg:tags":[
        "consultant"
    ],
    "wof:name":"Keech Computer Software",
    "wof:placetype":"venue"
},
  "geometry": {"coordinates":[-79.44328308110001,46.2868728638],"type":"Point"}
}