{
  "type": "Feature",
  "properties": {
    "iso:country":"CA",
    "sg:address":"1444 Rue Principale",
    "sg:city":"Saint-Amable",
    "sg:classifiers":[
        {
            "category":"Government",
            "subcategory":"Office",
            "type":"Public Place"
        }
    ],
    "sg:phone":"+1 450 649 3030",
    "sg:postcode":"J0L 1N0",
    "sg:province":"QC",
    "sg:tags":[
        "village"
    ],
    "wof:name":"St Amable Salle Municipale",
    "wof:placetype":"venue"
},
  "geometry": {"coordinates":[-73.284477,45.666073],"type":"Point"}
}