{
  "type": "Feature",
  "properties": {
    "addr:full":"36728 Dashwood Rd Dashwood ON N0M 1N0",
    "addr:postcode":"36728;n0m 1n0",
    "addr:street":"Dashwood Rd",
    "iso:country":"CA",
    "sg:address":"36728 Dashwood Rd",
    "sg:city":"Dashwood",
    "sg:classifiers":[
        {
            "category":"Building & Trades",
            "subcategory":"Plumbing",
            "type":"Services"
        }
    ],
    "sg:phone":"+1 519 237 3271",
    "sg:postcode":"N0M 1N0",
    "sg:province":"ON",
    "sg:tags":[
        "contractor"
    ],
    "wof:name":"Norman Fischer Plumbing & Elec",
    "wof:placetype":"venue"
},
  "geometry": {"coordinates":[-81.63452100000001,43.34605],"type":"Point"}
}