{
  "type": "Feature",
  "properties": {
    "iso:country":"CA",
    "sg:address":"4716 Wyandotte St E",
    "sg:city":"Windsor",
    "sg:classifiers":[
        {
            "category":"Shopping",
            "subcategory":"Gifts & Souvenirs",
            "type":"Retail Goods"
        }
    ],
    "sg:phone":"+1 519 251 9852",
    "sg:postcode":"N8Y 1H7",
    "sg:province":"ON",
    "sg:tags":[
        "shop"
    ],
    "wof:name":"At the Tea Room",
    "wof:placetype":"venue"
},
  "geometry": {"coordinates":[-82.9800186157,42.3265037537],"type":"Point"}
}