{
  "type": "Feature",
  "properties": {
    "addr:full":"964 Westport Cres #6 Mississauga ON L5T 1S3",
    "addr:housenumber":"964",
    "addr:postcode":"l5t 1s3",
    "addr:street":"Westport Cres # 6",
    "iso:country":"CA",
    "sg:address":"964 Westport Cres #6",
    "sg:city":"Mississauga",
    "sg:classifiers":[
        {
            "category":"Professional",
            "type":"Services"
        }
    ],
    "sg:phone":"+1 905 670 8121",
    "sg:postcode":"L5T 1S3",
    "sg:province":"ON",
    "sg:tags":[
        "lubricant",
        "establishment"
    ],
    "wof:name":"Magnus Chemicals Ltd",
    "wof:placetype":"venue"
},
  "geometry": {"coordinates":[-79.65801999999999,43.648304],"type":"Point"}
}