{
  "type": "Feature",
  "properties": {
    "iso:country":"CA",
    "sg:address":"35 Duck Bay Rd",
    "sg:city":"Waubaushene",
    "sg:classifiers":[
        {
            "category":"Recreation",
            "subcategory":"Marina",
            "type":"Entertainment"
        }
    ],
    "sg:phone":"+1 705 538 2295",
    "sg:postcode":"L0K 2C0",
    "sg:province":"ON",
    "wof:name":"Twin Bridge Marina",
    "wof:placetype":"venue"
},
  "geometry": {"coordinates":[-79.69915008540001,44.7600593567],"type":"Point"}
}