{
  "type": "Feature",
  "properties": {
    "addr:full":"Casselman ON K0A 1M0",
    "addr:postcode":"k0a 1m0",
    "iso:country":"CA",
    "sg:city":"Casselman",
    "sg:classifiers":[
        {
            "category":"Restaurant",
            "type":"Food & Drink"
        }
    ],
    "sg:phone":"+1 613 764 0454",
    "sg:postcode":"K0A 1M0",
    "sg:province":"ON",
    "sg:tags":[
        "out"
    ],
    "wof:name":"Subway Sandwiches & Salads",
    "wof:placetype":"venue"
},
  "geometry": {"coordinates":[-75.082458,45.306595],"type":"Point"}
}