{
  "type": "Feature",
  "properties": {
    "addr:full":"Toronto ON M5P 2B9",
    "addr:postcode":"m5p 2b9",
    "iso:country":"CA",
    "sg:city":"Toronto",
    "sg:classifiers":[
        {
            "category":"Communications",
            "subcategory":"Film & Video Production",
            "type":"Services"
        }
    ],
    "sg:phone":"+1 416 483 3862",
    "sg:postcode":"M5P 2B9",
    "sg:province":"ON",
    "sg:tags":[
        "taping"
    ],
    "wof:name":"Intercom Films Ltd",
    "wof:placetype":"venue"
},
  "geometry": {"coordinates":[-79.400192,43.699493],"type":"Point"}
}