{
  "type": "Feature",
  "properties": {
    "addr:full":"3605 24 Ave Vernon BC V1T 1L7",
    "addr:housenumber":"3605",
    "addr:postcode":"v1t 1l7",
    "addr:street":"24 Ave",
    "iso:country":"CA",
    "sg:address":"3605 24 Ave",
    "sg:city":"Vernon",
    "sg:classifiers":[
        {
            "category":"Social Services",
            "subcategory":"Adult Care",
            "type":"Services"
        }
    ],
    "sg:phone":"+1 250 542 4645",
    "sg:postcode":"V1T 1L7",
    "sg:province":"BC",
    "sg:tags":[
        "community",
        "facility"
    ],
    "wof:name":"24th Avenue",
    "wof:placetype":"venue"
},
  "geometry": {"coordinates":[-119.28182200000001,50.259399],"type":"Point"}
}