{
  "type": "Feature",
  "properties": {
    "iso:country":"CA",
    "sg:address":"18 Jacobson Dr",
    "sg:city":"Lively",
    "sg:classifiers":[
        {
            "category":"Health Services",
            "subcategory":"Nursing And Care Facility",
            "type":"Services"
        }
    ],
    "sg:phone":"+1 705 692 1832",
    "sg:postcode":"P3Y 1P7",
    "sg:province":"ON",
    "sg:tags":[
        "home",
        "retirement",
        "community"
    ],
    "wof:name":"Meadowbrook Village",
    "wof:placetype":"venue"
},
  "geometry": {"coordinates":[-81.1412811279,46.4236907959],"type":"Point"}
}