{
  "type": "Feature",
  "properties": {
    "addr:full":"31 Weller Ave Kingston ON K7K 2T1",
    "addr:housenumber":"31",
    "addr:postcode":"k7k 2t1",
    "addr:street":"Weller Ave",
    "iso:country":"CA",
    "sg:address":"31 Weller Ave",
    "sg:city":"Kingston",
    "sg:classifiers":[
        {
            "category":"Organizations",
            "subcategory":"Religious Organization",
            "type":"Services"
        }
    ],
    "sg:phone":"+1 613 542 2768",
    "sg:postcode":"K7K 2T1",
    "sg:province":"ON",
    "sg:tags":[
        "church"
    ],
    "wof:name":"St Matthew's United Church",
    "wof:placetype":"venue"
},
  "geometry": {"coordinates":[-76.48126999999999,44.262753],"type":"Point"}
}