{
  "type": "Feature",
  "properties": {
    "addr:full":"Topley Landing Granisle BC V0J 1W0",
    "addr:postcode":"v0j 1w0",
    "iso:country":"CA",
    "sg:address":"Topley Landing",
    "sg:city":"Granisle",
    "sg:classifiers":[
        {
            "category":"Travel",
            "subcategory":"Hotels & Motels",
            "type":"Entertainment"
        }
    ],
    "sg:phone":"+1 250 697 2992",
    "sg:postcode":"V0J 1W0",
    "sg:province":"BC",
    "sg:tags":[
        "resort"
    ],
    "wof:name":"Coyote Lodge",
    "wof:placetype":"venue"
},
  "geometry": {"coordinates":[-126.20499420199999,54.8854255676],"type":"Point"}
}