{
  "type": "Feature",
  "properties": {
    "iso:country":"CA",
    "sg:address":"245 Creditstone Rd # 2",
    "sg:city":"Concord",
    "sg:classifiers":[
        {
            "category":"Retail",
            "subcategory":"Auto Repair",
            "type":"Services"
        }
    ],
    "sg:phone":"+1 905 738 6191",
    "sg:postcode":"L4K 1N6",
    "sg:province":"ON",
    "sg:tags":[
        "automobile",
        "rustproofing",
        "undercoating"
    ],
    "wof:name":"Krown Rust Control System",
    "wof:placetype":"venue"
},
  "geometry": {"coordinates":[-79.517342,43.794521],"type":"Point"}
}