{
  "type": "Feature",
  "properties": {
    "iso:country":"CA",
    "sg:address":"9 Cote DE L'Eglise",
    "sg:city":"Boischatel",
    "sg:classifiers":[
        {
            "category":"Government",
            "subcategory":"Office",
            "type":"Public Place"
        }
    ],
    "sg:phone":"+1 418 822 4500",
    "sg:postcode":"G0A 1H0",
    "sg:province":"QC",
    "sg:tags":[
        "village"
    ],
    "wof:name":"Boischatel Administration",
    "wof:placetype":"venue"
},
  "geometry": {"coordinates":[-71.0068054199,46.9804115295],"type":"Point"}
}