{
  "type": "Feature",
  "properties": {
    "addr:full":"110 Av Saint-Jacques Saint-Raymond QC G3L 3Y2",
    "addr:housenumber":"110",
    "addr:postcode":"g3l 3y2",
    "addr:street":"Av Saint-Jacques",
    "iso:country":"CA",
    "sg:address":"110 Av Saint-Jacques",
    "sg:city":"Saint-Raymond",
    "sg:classifiers":[
        {
            "category":"Manufacturing",
            "subcategory":"Metals",
            "type":"Manufacturing & Wholesale Goods"
        }
    ],
    "sg:phone":"+1 418 337 8078",
    "sg:postcode":"G3L 3Y2",
    "sg:province":"QC",
    "sg:tags":[
        "solder"
    ],
    "wof:name":"Fer-Di-MO",
    "wof:placetype":"venue"
},
  "geometry": {"coordinates":[-71.8404388428,46.8928947449],"type":"Point"}
}