{
  "type": "Feature",
  "properties": {
    "iso:country":"CA",
    "sg:address":"395 Cochrane Dr",
    "sg:city":"Markham",
    "sg:classifiers":[
        {
            "category":"Wholesale",
            "subcategory":"Durable Goods & Equipment",
            "type":"Manufacturing & Wholesale Goods"
        }
    ],
    "sg:phone":"+1 905 944 1696",
    "sg:postcode":"L3R 9R5",
    "sg:province":"ON",
    "sg:tags":[
        "instrument",
        "meteorological"
    ],
    "wof:name":"Airflow Dev Ltd",
    "wof:placetype":"venue"
},
  "geometry": {"coordinates":[-79.36246490480001,43.8430328369],"type":"Point"}
}