{
  "type": "Feature",
  "properties": {
    "iso:country":"CA",
    "sg:address":"11005 100 St",
    "sg:city":"Grande Prairie",
    "sg:classifiers":[
        {
            "category":"Sports & Exercise",
            "subcategory":"Bowling",
            "type":"Entertainment"
        }
    ],
    "sg:phone":"+1 780 532 4616",
    "sg:postcode":"T8V 2M9",
    "sg:province":"AB",
    "sg:tags":[
        "center"
    ],
    "wof:name":"Family Affair Bowling Lanes",
    "wof:placetype":"venue"
},
  "geometry": {"coordinates":[-118.79460907000001,55.1799888611],"type":"Point"}
}