{
  "type": "Feature",
  "properties": {
    "addr:full":"23 Polymer Rd Truro NS B2N 6T8",
    "addr:housenumber":"23",
    "addr:postcode":"b2n 6t8",
    "addr:street":"Polymer Rd",
    "iso:country":"CA",
    "sg:address":"23 Polymer Rd",
    "sg:city":"Truro",
    "sg:classifiers":[
        {
            "category":"Manufacturing",
            "subcategory":"Building Materials",
            "type":"Manufacturing & Wholesale Goods"
        }
    ],
    "sg:phone":"+1 902 893 8660",
    "sg:postcode":"B2N 6T8",
    "sg:province":"NS",
    "sg:tags":[
        "truss"
    ],
    "wof:name":"Maritime Truss Ltd",
    "wof:placetype":"venue"
},
  "geometry": {"coordinates":[-63.290886,45.350384],"type":"Point"}
}