{
  "type": "Feature",
  "properties": {
    "addr:full":"New Westminster BC V3L 3W4",
    "addr:postcode":"v3l 3w4",
    "iso:country":"CA",
    "sg:city":"New Westminster",
    "sg:classifiers":[
        {
            "category":"Government",
            "subcategory":"Office",
            "type":"Public Place"
        }
    ],
    "sg:phone":"+1 604 660 8160",
    "sg:postcode":"V3L 3W4",
    "sg:province":"BC",
    "wof:name":"B C Human Resources",
    "wof:placetype":"venue"
},
  "geometry": {"coordinates":[-122.893081665,49.2247428894],"type":"Point"}
}