{
  "type": "Feature",
  "properties": {
    "addr:full":"1160 Cassells St North Bay ON P1B 4B5",
    "addr:housenumber":"1160",
    "addr:postcode":"p1b 4b5",
    "addr:street":"Cassells St",
    "iso:country":"CA",
    "sg:address":"1160 Cassells St",
    "sg:city":"North Bay",
    "sg:classifiers":[
        {
            "category":"Shopping",
            "subcategory":"Computers & Home Electronics",
            "type":"Retail Goods"
        }
    ],
    "sg:phone":"+1 705 385 2672",
    "sg:postcode":"P1B 4B5",
    "sg:province":"ON",
    "sg:tags":[
        "radio",
        "dealer"
    ],
    "wof:name":"M & M Communications",
    "wof:placetype":"venue"
},
  "geometry": {"coordinates":[-79.4558563232,46.318031311],"type":"Point"}
}