{
  "type": "Feature",
  "properties": {
    "addr:full":"990 Rue Salaberry Laval QC H7S 2J1",
    "addr:housenumber":"990",
    "addr:postcode":"h7s 2j1",
    "addr:street":"Rue Salaberry",
    "iso:country":"CA",
    "sg:address":"990 Rue Salaberry",
    "sg:city":"Laval",
    "sg:classifiers":[
        {
            "category":"Manufacturing",
            "subcategory":"Furniture",
            "type":"Manufacturing & Wholesale Goods"
        }
    ],
    "sg:phone":"+1 450 668 8670",
    "sg:postcode":"H7S 2J1",
    "sg:province":"QC",
    "sg:tags":[
        "mattress",
        "maker",
        "supply"
    ],
    "wof:name":"Matelas Mirabel Inc",
    "wof:placetype":"venue"
},
  "geometry": {"coordinates":[-73.72351837159999,45.5749359131],"type":"Point"}
}