{
  "type": "Feature",
  "properties": {
    "addr:full":"1515 41 Ave SE Calgary AB T2G 1X7",
    "addr:housenumber":"1515",
    "addr:postcode":"t2g 1x7",
    "addr:street":"41 Ave Se",
    "iso:country":"CA",
    "sg:address":"1515 41 Ave SE",
    "sg:city":"Calgary",
    "sg:classifiers":[
        {
            "category":"Retail",
            "subcategory":"Auto Repair",
            "type":"Services"
        }
    ],
    "sg:phone":"+1 403 269 3766",
    "sg:postcode":"T2G 1X7",
    "sg:province":"AB",
    "sg:tags":[
        "truck"
    ],
    "wof:name":"Bow Valley Diesel Ltd",
    "wof:placetype":"venue"
},
  "geometry": {"coordinates":[-113.974487305,51.0406951904],"type":"Point"}
}