{
  "type": "Feature",
  "properties": {
    "addr:full":"748 Development Dr Kingston ON K7M 4W8",
    "addr:housenumber":"748",
    "addr:postcode":"k7m 4w8",
    "addr:street":"Development Dr",
    "iso:country":"CA",
    "sg:address":"748 Development Dr",
    "sg:city":"Kingston",
    "sg:classifiers":[
        {
            "category":"Professional",
            "subcategory":"Business Services",
            "type":"Services"
        }
    ],
    "sg:phone":"+1 613 389 5555",
    "sg:postcode":"K7M 4W8",
    "sg:province":"ON",
    "sg:tags":[
        "automobile",
        "appraiser"
    ],
    "wof:name":"R D Cooper Appraisals Svc Ltd",
    "wof:placetype":"venue"
},
  "geometry": {"coordinates":[-76.573387146,44.2417373657],"type":"Point"}
}