{
  "type": "Feature",
  "properties": {
    "iso:country":"CA",
    "sg:address":"35 Rue DE Port-Royal E",
    "sg:city":"Montreal",
    "sg:classifiers":[
        {
            "category":"Government",
            "subcategory":"Office",
            "type":"Public Place"
        }
    ],
    "sg:phone":"+1 514 873 2723",
    "sg:postcode":"H3L 3T1",
    "sg:province":"QC",
    "wof:name":"Quebec Commissaire General",
    "wof:placetype":"venue"
},
  "geometry": {"coordinates":[-73.657143,45.546677],"type":"Point"}
}