{
  "type": "Feature",
  "properties": {
    "iso:country":"CA",
    "sg:address":"7380 Wyandotte St E",
    "sg:city":"Windsor",
    "sg:classifiers":[
        {
            "category":"Organizations",
            "subcategory":"Religious Organization",
            "type":"Services"
        }
    ],
    "sg:phone":"+1 519 944 1317",
    "sg:postcode":"N8S 1R7",
    "sg:province":"ON",
    "sg:tags":[
        "church"
    ],
    "wof:name":"United Pentecostal Church",
    "wof:placetype":"venue"
},
  "geometry": {"coordinates":[-82.9501113892,42.33253479],"type":"Point"}
}