{
  "type": "Feature",
  "properties": {
    "addr:full":"Edmonton AB T6J 6R5",
    "addr:postcode":"t6j 6r5",
    "iso:country":"CA",
    "sg:city":"Edmonton",
    "sg:classifiers":[
        {
            "category":"Sports & Exercise",
            "subcategory":"Bowling",
            "type":"Entertainment"
        }
    ],
    "sg:phone":"+1 780 435 1922",
    "sg:postcode":"T6J 6R5",
    "sg:province":"AB",
    "sg:tags":[
        "center"
    ],
    "wof:name":"Gateway Lanes & Recreation Ctr",
    "wof:placetype":"venue"
},
  "geometry": {"coordinates":[-113.49037199999999,53.546219],"type":"Point"}
}