{
  "type": "Feature",
  "properties": {
    "addr:full":"501 Victoria Ave Regina SK S4N 0P8",
    "addr:housenumber":"501",
    "addr:postcode":"s4n 0p8",
    "addr:street":"Victoria Ave",
    "iso:country":"CA",
    "sg:address":"501 Victoria Ave",
    "sg:city":"Regina",
    "sg:classifiers":[
        {
            "category":"Food & Beverages",
            "subcategory":"Specialty",
            "type":"Retail Goods"
        }
    ],
    "sg:phone":"+1 306 352 8623",
    "sg:postcode":"S4N 0P8",
    "sg:province":"SK",
    "sg:tags":[
        "health",
        "diet"
    ],
    "wof:name":"Old Fashion Foods Ltd",
    "wof:placetype":"venue"
},
  "geometry": {"coordinates":[-104.58813499999999,50.446995],"type":"Point"}
}