{
  "type": "Feature",
  "properties": {
    "addr:full":"835 Ontario Rd Welland ON L3B 5V6",
    "addr:housenumber":"835",
    "addr:postcode":"l3b 5v6",
    "addr:street":"Ontario Rd",
    "iso:country":"CA",
    "sg:address":"835 Ontario Rd",
    "sg:city":"Welland",
    "sg:classifiers":[
        {
            "category":"Food & Beverages",
            "subcategory":"Liquor & Beverages",
            "type":"Retail Goods"
        }
    ],
    "sg:phone":"+1 905 734 3132",
    "sg:postcode":"L3B 5V6",
    "sg:province":"ON",
    "sg:tags":[
        "store"
    ],
    "wof:name":"Liquor Control Board of Ont",
    "wof:placetype":"venue"
},
  "geometry": {"coordinates":[-79.23932600000001,42.974792],"type":"Point"}
}