{
  "type": "Feature",
  "properties": {
    "iso:country":"CA",
    "sg:address":"6900 Boul Gouin E",
    "sg:city":"Montreal-Nord",
    "sg:classifiers":[
        {
            "category":"Real Estate",
            "subcategory":"Real Estate Operator",
            "type":"Services"
        }
    ],
    "sg:phone":"+1 514 323 2552",
    "sg:postcode":"H1G 6L9",
    "sg:province":"QC",
    "sg:tags":[
        "condominium"
    ],
    "wof:name":"Condominium Cascades Des Prair",
    "wof:placetype":"venue"
},
  "geometry": {"coordinates":[-73.620636,45.628056],"type":"Point"}
}