{
  "type": "Feature",
  "properties": {
    "iso:country":"CA",
    "sg:address":"851 Monterey Ave",
    "sg:city":"Victoria",
    "sg:classifiers":[
        {
            "category":"Education",
            "subcategory":"School",
            "type":"Public Place"
        }
    ],
    "sg:phone":"+1 250 598 4589",
    "sg:postcode":"V8S 4V1",
    "sg:province":"BC",
    "wof:name":"Monterey Elementary Schools",
    "wof:placetype":"venue"
},
  "geometry": {"coordinates":[-123.364517,48.428314],"type":"Point"}
}