{
  "type": "Feature",
  "properties": {
    "addr:full":"851 Monterey Ave Victoria BC V8S 4V1",
    "addr:housenumber":"851",
    "addr:postcode":"v8s 4v1",
    "addr:street":"Monterey Ave",
    "iso:country":"CA",
    "sg:address":"851 Monterey Ave",
    "sg:city":"Victoria",
    "sg:classifiers":[
        {
            "category":"Education",
            "subcategory":"School",
            "type":"Public Place"
        }
    ],
    "sg:phone":"+1 250 598 4589",
    "sg:postcode":"V8S 4V1",
    "sg:province":"BC",
    "wof:name":"Monterey Elementary Schools",
    "wof:placetype":"venue"
},
  "geometry": {"coordinates":[-123.36451700000001,48.428314],"type":"Point"}
}