{
  "type": "Feature",
  "properties": {
    "addr:full":"General Delivery Campbellton NB E3N 3E9",
    "addr:postcode":"e3n 3e9",
    "iso:country":"CA",
    "sg:address":"General Delivery",
    "sg:city":"Campbellton",
    "sg:classifiers":[
        {
            "category":"Recreation",
            "type":"Entertainment"
        }
    ],
    "sg:phone":"+1 506 753 5948",
    "sg:postcode":"E3N 3E9",
    "sg:province":"NB",
    "sg:tags":[
        "skating",
        "rink"
    ],
    "wof:name":"Arena DE St Arthur",
    "wof:placetype":"venue"
},
  "geometry": {"coordinates":[-66.6672210693,47.9954986572],"type":"Point"}
}