{
  "type": "Feature",
  "properties": {
    "addr:full":"2999 Rosebery Ave West Vancouver BC V7V 3A8",
    "addr:housenumber":"2999",
    "addr:postcode":"v7v 3a8",
    "addr:street":"Rosebery Ave",
    "iso:country":"CA",
    "sg:address":"2999 Rosebery Ave",
    "sg:city":"West Vancouver",
    "sg:classifiers":[
        {
            "category":"Building & Trades",
            "subcategory":"Landscaping Services",
            "type":"Services"
        }
    ],
    "sg:phone":"+1 604 922 5101",
    "sg:postcode":"V7V 3A8",
    "sg:province":"BC",
    "sg:tags":[
        "tree"
    ],
    "wof:name":"Bell Disposal Svc Ltd",
    "wof:placetype":"venue"
},
  "geometry": {"coordinates":[-123.19850921600001,49.3434791565],"type":"Point"}
}