{
  "type": "Feature",
  "properties": {
    "addr:full":"1580 Princeton Cres Oakville ON L6H 4H7",
    "addr:housenumber":"1580",
    "addr:postcode":"l6h 4h7",
    "addr:street":"Princeton Cres",
    "iso:country":"CA",
    "sg:address":"1580 Princeton Cres",
    "sg:city":"Oakville",
    "sg:classifiers":[
        {
            "category":"Manufacturing",
            "subcategory":"Metals",
            "type":"Manufacturing & Wholesale Goods"
        }
    ],
    "sg:phone":"+1 905 844 5483",
    "sg:postcode":"L6H 4H7",
    "sg:province":"ON",
    "sg:tags":[
        "windows"
    ],
    "wof:name":"A B Aluminum Siding",
    "wof:placetype":"venue"
},
  "geometry": {"coordinates":[-79.7035522461,43.4702606201],"type":"Point"}
}