{
  "type": "Feature",
  "properties": {
    "addr:full":"Kelowna BC V1Z 1G5",
    "addr:postcode":"v1z 1g5",
    "iso:country":"CA",
    "sg:city":"Kelowna",
    "sg:classifiers":[
        {
            "category":"Manufacturing",
            "subcategory":"Paper Products",
            "type":"Manufacturing & Wholesale Goods"
        }
    ],
    "sg:phone":"+1 250 769 3289",
    "sg:postcode":"V1Z 1G5",
    "sg:province":"BC",
    "sg:tags":[
        "label"
    ],
    "wof:name":"Challenge Labels Ltd",
    "wof:placetype":"venue"
},
  "geometry": {"coordinates":[-119.56877900000001,49.86438],"type":"Point"}
}