{
  "type": "Feature",
  "properties": {
    "addr:full":"1200 Boul Chomedey Laval QC H7V 3Z3",
    "addr:housenumber":"1200",
    "addr:postcode":"h7v 3z3",
    "addr:street":"Boul Chomedey",
    "iso:country":"CA",
    "sg:address":"1200 Boul Chomedey",
    "sg:city":"Laval",
    "sg:classifiers":[
        {
            "category":"Professional",
            "subcategory":"Advertising",
            "type":"Services"
        }
    ],
    "sg:phone":"+1 450 688 7866",
    "sg:postcode":"H7V 3Z3",
    "sg:province":"QC",
    "wof:name":"Reseau Vmm",
    "wof:placetype":"venue"
},
  "geometry": {"coordinates":[-73.74383544920001,45.5492401123],"type":"Point"}
}