{
  "type": "Feature",
  "properties": {
    "addr:full":"23 Cleopatra Dr Nepean ON K2G 0B6",
    "addr:housenumber":"23",
    "addr:postcode":"k2g 0b6",
    "addr:street":"Cleopatra Dr",
    "iso:country":"CA",
    "sg:address":"23 Cleopatra Dr",
    "sg:city":"Nepean",
    "sg:classifiers":[
        {
            "category":"Manufacturing",
            "subcategory":"Tools & Machinery",
            "type":"Manufacturing & Wholesale Goods"
        }
    ],
    "sg:phone":"+1 613 225 7200",
    "sg:postcode":"K2G 0B6",
    "sg:province":"ON",
    "sg:tags":[
        "machine",
        "shop"
    ],
    "wof:name":"Dynamic Precision Inc",
    "wof:placetype":"venue"
},
  "geometry": {"coordinates":[-75.723045,45.326336],"type":"Point"}
}