{
  "type": "Feature",
  "properties": {
    "addr:full":"1010 Riverwood Ave Winnipeg MB R3T 1L3",
    "addr:housenumber":"1010",
    "addr:postcode":"r3t 1l3",
    "addr:street":"Riverwood Ave",
    "iso:country":"CA",
    "sg:address":"1010 Riverwood Ave",
    "sg:city":"Winnipeg",
    "sg:classifiers":[
        {
            "category":"Organizations",
            "subcategory":"Religious Organization",
            "type":"Services"
        }
    ],
    "sg:phone":"+1 204 284 7903",
    "sg:postcode":"R3T 1L3",
    "sg:province":"MB",
    "sg:tags":[
        "church"
    ],
    "wof:name":"Winnipeg Chinese Mennonite Chr",
    "wof:placetype":"venue"
},
  "geometry": {"coordinates":[-97.1546783447,49.8420906067],"type":"Point"}
}