{
  "type": "Feature",
  "properties": {
    "addr:full":"1047 Davie St Vancouver BC V6E 1M5",
    "addr:housenumber":"1047",
    "addr:postcode":"v6e 1m5",
    "addr:street":"Davie St",
    "iso:country":"CA",
    "sg:address":"1047 Davie St",
    "sg:city":"Vancouver",
    "sg:classifiers":[
        {
            "category":"Restaurant",
            "type":"Food & Drink"
        }
    ],
    "sg:phone":"+1 604 687 2577",
    "sg:postcode":"V6E 1M5",
    "sg:province":"BC",
    "wof:name":"Gigi's Pizza & Spaghetti House",
    "wof:placetype":"venue"
},
  "geometry": {"coordinates":[-123.13001300000001,49.279797],"type":"Point"}
}