{
  "type": "Feature",
  "properties": {
    "addr:full":"5629 Av DE Monkland Montreal QC H4A 1E2",
    "addr:housenumber":"5629",
    "addr:postcode":"h4a 1e2",
    "addr:street":"Av De Monkland",
    "iso:country":"CA",
    "sg:address":"5629 Av DE Monkland",
    "sg:city":"Montreal",
    "sg:classifiers":[
        {
            "category":"Food & Beverages",
            "subcategory":"Bakery",
            "type":"Retail Goods"
        }
    ],
    "sg:phone":"+1 514 487 8051",
    "sg:postcode":"H4A 1E2",
    "sg:province":"QC",
    "sg:tags":[
        "cafe"
    ],
    "wof:name":"St-Viateur Bagel & Cafe",
    "wof:placetype":"venue"
},
  "geometry": {"coordinates":[-73.6231994629,45.4753990173],"type":"Point"}
}