{
  "type": "Feature",
  "properties": {
    "addr:full":"360 Edgeworth Ave London ON N5W 5C4",
    "addr:housenumber":"360",
    "addr:postcode":"n5w 5c4",
    "addr:street":"Edgeworth Ave",
    "iso:country":"CA",
    "sg:address":"360 Edgeworth Ave",
    "sg:city":"London",
    "sg:classifiers":[
        {
            "category":"Organizations",
            "subcategory":"Religious Organization",
            "type":"Services"
        }
    ],
    "sg:phone":"+1 519 455 3470",
    "sg:postcode":"N5W 5C4",
    "sg:province":"ON",
    "sg:tags":[
        "church"
    ],
    "wof:name":"Richards Memorial United Chr",
    "wof:placetype":"venue"
},
  "geometry": {"coordinates":[-81.1763305664,43.0024261475],"type":"Point"}
}