{
  "type": "Feature",
  "properties": {
    "addr:full":"3600 Dufferin St North York ON M3K 1N7",
    "addr:housenumber":"3600",
    "addr:postcode":"m3k 1n7",
    "addr:street":"Dufferin St",
    "iso:country":"CA",
    "sg:address":"3600 Dufferin St",
    "sg:city":"North York",
    "sg:classifiers":[
        {
            "category":"Wholesale",
            "subcategory":"Machinery & Supplies",
            "type":"Manufacturing & Wholesale Goods"
        }
    ],
    "sg:phone":"+1 416 633 1512",
    "sg:postcode":"M3K 1N7",
    "sg:province":"ON",
    "sg:tags":[
        "salon",
        "beauty"
    ],
    "wof:name":"Rainbow Electric",
    "wof:placetype":"venue"
},
  "geometry": {"coordinates":[-79.4588088989,43.7310409546],"type":"Point"}
}