{
  "type": "Feature",
  "properties": {
    "addr:full":"71 Rue Saint-Alphonse O Thetford Mines QC G6G 3W5",
    "addr:housenumber":"71",
    "addr:postcode":"g6g 3w5",
    "addr:street":"Rue Saint-Alphonse O",
    "iso:country":"CA",
    "sg:address":"71 Rue Saint-Alphonse O",
    "sg:city":"Thetford Mines",
    "sg:classifiers":[
        {
            "category":"Banks & Credit Unions",
            "subcategory":"Investment Brokerage",
            "type":"Services"
        }
    ],
    "sg:phone":"+1 418 338 8383",
    "sg:postcode":"G6G 3W5",
    "sg:province":"QC",
    "wof:name":"Options Investissements Inc",
    "wof:placetype":"venue"
},
  "geometry": {"coordinates":[-71.29861450200001,46.0902481079],"type":"Point"}
}