{
  "type": "Feature",
  "properties": {
    "addr:full":"400 Rue Principale O Cacouna QC G0L 1G0",
    "addr:housenumber":"400",
    "addr:postcode":"g0l 1g0",
    "addr:street":"Rue Principale O",
    "iso:country":"CA",
    "sg:address":"400 Rue Principale O",
    "sg:city":"Cacouna",
    "sg:classifiers":[
        {
            "category":"Health Services",
            "subcategory":"Doctor",
            "type":"Services"
        }
    ],
    "sg:phone":"+1 418 862 2170",
    "sg:postcode":"G0L 1G0",
    "sg:province":"QC",
    "sg:tags":[
        "clinic"
    ],
    "wof:name":"Clinique Medicale Cacouna",
    "wof:placetype":"venue"
},
  "geometry": {"coordinates":[-69.507233,47.910126],"type":"Point"}
}