{
  "type": "Feature",
  "properties": {
    "addr:full":"3663 Rang Saint-Elzear E Laval QC H7E 4P2",
    "addr:housenumber":"3663",
    "addr:postcode":"h7e 4p2",
    "addr:street":"Rang Saint-Elzear E",
    "iso:country":"CA",
    "sg:address":"3663 Rang Saint-Elzear E",
    "sg:city":"Laval",
    "sg:classifiers":[
        {
            "category":"Farming",
            "subcategory":"Farm",
            "type":"Manufacturing & Wholesale Goods"
        }
    ],
    "sg:phone":"+1 450 661 4139",
    "sg:postcode":"H7E 4P2",
    "sg:province":"QC",
    "wof:name":"Fermes Flg Inc",
    "wof:placetype":"venue"
},
  "geometry": {"coordinates":[-73.6849899292,45.6303024292],"type":"Point"}
}