{
  "type": "Feature",
  "properties": {
    "addr:full":"2827 Murray St Port Moody BC V3H 1X3",
    "addr:housenumber":"2827",
    "addr:postcode":"v3h 1x3",
    "addr:street":"Murray St",
    "iso:country":"CA",
    "sg:address":"2827 Murray St",
    "sg:city":"Port Moody",
    "sg:classifiers":[
        {
            "category":"Wholesale",
            "subcategory":"Machinery & Supplies",
            "type":"Manufacturing & Wholesale Goods"
        }
    ],
    "sg:phone":"+1 604 469 7191",
    "sg:postcode":"V3H 1X3",
    "sg:province":"BC",
    "sg:tags":[
        "equipment",
        "baker"
    ],
    "wof:name":"Ken Hall Contractors Ltd",
    "wof:placetype":"venue"
},
  "geometry": {"coordinates":[-122.84733581499999,49.2787246704],"type":"Point"}
}