{
  "type": "Feature",
  "properties": {
    "addr:full":"305 107E Rue # 202 Saint-Georges QC G5Y 3J8",
    "addr:housenumber":"305",
    "addr:postcode":"g5y 3j8",
    "addr:street":"107E Rue # 202",
    "iso:country":"CA",
    "sg:address":"305 107E Rue # 202",
    "sg:city":"Saint-Georges",
    "sg:classifiers":[
        {
            "category":"Professional",
            "subcategory":"Business Services",
            "type":"Services"
        }
    ],
    "sg:phone":"+1 418 228 8026",
    "sg:postcode":"G5Y 3J8",
    "sg:province":"QC",
    "sg:tags":[
        "notary"
    ],
    "wof:name":"Poirier Mathieu & Veilleux",
    "wof:placetype":"venue"
},
  "geometry": {"coordinates":[-70.67115,46.123348],"type":"Point"}
}