{
  "type": "Feature",
  "properties": {
    "addr:full":"184 Rue Grenier Laurierville QC G0S 1P0",
    "addr:housenumber":"184",
    "addr:postcode":"g0s 1p0",
    "addr:street":"Rue Grenier",
    "iso:country":"CA",
    "sg:address":"184 Rue Grenier",
    "sg:city":"Laurierville",
    "sg:classifiers":[
        {
            "category":"Shopping",
            "subcategory":"Pharmacy",
            "type":"Retail Goods"
        }
    ],
    "sg:phone":"+1 819 365 9995",
    "sg:postcode":"G0S 1P0",
    "sg:province":"QC",
    "wof:name":"Pharmacie Claude Labrie",
    "wof:placetype":"venue"
},
  "geometry": {"coordinates":[-71.6552581787,46.2990837097],"type":"Point"}
}