{
  "type": "Feature",
  "properties": {
    "addr:full":"Port Coquitlam BC V3C 3W4",
    "addr:postcode":"v3c 3w4",
    "iso:country":"CA",
    "sg:city":"Port Coquitlam",
    "sg:classifiers":[
        {
            "category":"Restaurant",
            "type":"Food & Drink"
        }
    ],
    "sg:phone":"+1 604 942 2001",
    "sg:postcode":"V3C 3W4",
    "sg:province":"BC",
    "sg:tags":[
        "sandwich"
    ],
    "wof:name":"Subway Sandwiches & Salads",
    "wof:placetype":"venue"
},
  "geometry": {"coordinates":[-122.782005,49.261684],"type":"Point"}
}