{
  "type": "Feature",
  "properties": {
    "addr:full":"115 Tremblay Ave Saint-Edmond-Les-Plaines QC G0W 2M0",
    "addr:housenumber":"115",
    "addr:postcode":"g0w 2m0",
    "addr:street":"Tremblay Ave",
    "iso:country":"CA",
    "sg:address":"115 Tremblay Ave",
    "sg:city":"Saint-Edmond-Les-Plaines",
    "sg:classifiers":[
        {
            "category":"Recreation",
            "type":"Entertainment"
        }
    ],
    "sg:phone":"+1 418 274 3482",
    "sg:postcode":"G0W 2M0",
    "sg:province":"QC",
    "sg:tags":[
        "center"
    ],
    "wof:name":"Rendez-Vous Sportif",
    "wof:placetype":"venue"
},
  "geometry": {"coordinates":[-72.5525054932,48.9040222168],"type":"Point"}
}