{
  "type": "Feature",
  "properties": {
    "addr:full":"1559 Rue Dudemaine Montreal QC H3M 1R2",
    "addr:housenumber":"1559",
    "addr:postcode":"h3m 1r2",
    "addr:street":"Rue Dudemaine",
    "iso:country":"CA",
    "sg:address":"1559 Rue Dudemaine",
    "sg:city":"Montreal",
    "sg:classifiers":[
        {
            "category":"Food & Beverages",
            "subcategory":"Groceries & Convenience Stores",
            "type":"Retail Goods"
        }
    ],
    "sg:phone":"+1 514 332 3070",
    "sg:postcode":"H3M 1R2",
    "sg:province":"QC",
    "sg:tags":[
        "grocer"
    ],
    "wof:name":"Epicerie Normandie Enr",
    "wof:placetype":"venue"
},
  "geometry": {"coordinates":[-73.687461853,45.5402297974],"type":"Point"}
}