{
  "type": "Feature",
  "properties": {
    "addr:full":"24 Stavanger Dr St. John's NL A1A 5E8",
    "addr:housenumber":"24",
    "addr:postcode":"a1a 5e8",
    "addr:street":"Stavanger Dr",
    "iso:country":"CA",
    "sg:address":"24 Stavanger Dr",
    "sg:city":"St. John's",
    "sg:classifiers":[
        {
            "category":"Shopping",
            "subcategory":"Department Store",
            "type":"Retail Goods"
        }
    ],
    "sg:phone":"+1 709 722 7850",
    "sg:postcode":"A1A 5E8",
    "sg:province":"NL",
    "wof:name":"Zellers",
    "wof:placetype":"venue"
},
  "geometry": {"coordinates":[-52.7184715271,47.6156272888],"type":"Point"}
}