{
  "type": "Feature",
  "properties": {
    "addr:full":"1 Rue Martin Saint-Pie QC J0H 1W0",
    "addr:housenumber":"1",
    "addr:postcode":"j0h 1w0",
    "addr:street":"Rue Martin",
    "iso:country":"CA",
    "sg:address":"1 Rue Martin",
    "sg:city":"Saint-Pie",
    "sg:classifiers":[
        {
            "category":"Manufacturing",
            "subcategory":"Pet Food",
            "type":"Manufacturing & Wholesale Goods"
        }
    ],
    "sg:phone":"+1 450 772 2445",
    "sg:postcode":"J0H 1W0",
    "sg:province":"QC",
    "sg:tags":[
        "feed"
    ],
    "wof:name":"Olier Grise & Cie Ltee",
    "wof:placetype":"venue"
},
  "geometry": {"coordinates":[-72.91194900000001,45.506618],"type":"Point"}
}