{
  "type": "Feature",
  "properties": {
    "iso:country":"CA",
    "sg:city":"Labelle",
    "sg:classifiers":[
        {
            "category":"Building & Trades",
            "subcategory":"Construction",
            "type":"Services"
        }
    ],
    "sg:phone":"+1 819 686 2031",
    "sg:postcode":"J0T 1H0",
    "sg:province":"QC",
    "sg:tags":[
        "home",
        "builder",
        "general",
        "contractor"
    ],
    "wof:name":"Construction Telmosse & Fils",
    "wof:placetype":"venue"
},
  "geometry": {"coordinates":[-74.75537872309999,46.2838516235],"type":"Point"}
}