{
  "type": "Feature",
  "properties": {
    "addr:full":"27 Ashdale Cres North Bay ON P1A 4L8",
    "addr:housenumber":"27",
    "addr:postcode":"p1a 4l8",
    "addr:street":"Ashdale Cres",
    "iso:country":"CA",
    "sg:address":"27 Ashdale Cres",
    "sg:city":"North Bay",
    "sg:classifiers":[
        {
            "category":"Social Services",
            "type":"Services"
        }
    ],
    "sg:phone":"+1 705 495 4293",
    "sg:postcode":"P1A 4L8",
    "sg:province":"ON",
    "sg:tags":[
        "organization",
        "welfare"
    ],
    "wof:name":"Ashdale Residence",
    "wof:placetype":"venue"
},
  "geometry": {"coordinates":[-79.4284667969,46.2738380432],"type":"Point"}
}