{
  "type": "Feature",
  "properties": {
    "addr:full":"RR 2 Ilderton ON N0M 2A0",
    "addr:postcode":"n0m 2a0",
    "addr:street":"Rr 2",
    "iso:country":"CA",
    "sg:address":"RR 2",
    "sg:city":"Ilderton",
    "sg:classifiers":[
        {
            "category":"Government",
            "subcategory":"Fire Station",
            "type":"Public Place"
        }
    ],
    "sg:phone":"+1 ",
    "sg:postcode":"N0M 2A0",
    "sg:province":"ON",
    "sg:tags":[
        "department"
    ],
    "wof:name":"Lobo Fire Hall",
    "wof:placetype":"venue"
},
  "geometry": {"coordinates":[-81.38208,43.079128],"type":"Point"}
}