{
  "type": "Feature",
  "properties": {
    "addr:full":"685 Notre Dame Dr Kamloops BC V2C 5N7",
    "addr:housenumber":"685",
    "addr:postcode":"bc v2c 5n7",
    "addr:street":"Notre Dame Dr",
    "iso:country":"CA",
    "sg:address":"685 Notre Dame Dr",
    "sg:city":"Kamloops",
    "sg:classifiers":[
        {
            "category":"Manufacturing",
            "subcategory":"Motor Vehicles & Parts",
            "type":"Manufacturing & Wholesale Goods"
        }
    ],
    "sg:phone":"+1 250 374 1135",
    "sg:postcode":"V2C 5N7",
    "sg:province":"BC",
    "sg:tags":[
        "automobile",
        "dealer"
    ],
    "wof:name":"Zimmer Wheaton Pontiac Buick",
    "wof:placetype":"venue"
},
  "geometry": {"coordinates":[-120.355758667,50.6635742188],"type":"Point"}
}