{
  "type": "Feature",
  "properties": {
    "addr:full":"123 Rue Des Vieux-Ponts Bonaventure QC G0C 1E0",
    "addr:housenumber":"123",
    "addr:postcode":"g0c 1e0",
    "addr:street":"Rue Des Vieux-Ponts",
    "iso:country":"CA",
    "sg:address":"123 Rue Des Vieux-Ponts",
    "sg:city":"Bonaventure",
    "sg:classifiers":[
        {
            "category":"Recreation",
            "type":"Entertainment"
        }
    ],
    "sg:phone":"+1 418 534 1997",
    "sg:postcode":"G0C 1E0",
    "sg:province":"QC",
    "sg:tags":[
        "attraction",
        "tourist"
    ],
    "wof:name":"Bioparc DE LA Gaspesie",
    "wof:placetype":"venue"
},
  "geometry": {"coordinates":[-65.472099,48.04797],"type":"Point"}
}