{
  "type": "Feature",
  "properties": {
    "iso:country":"CA",
    "sg:address":"332 5 St S",
    "sg:city":"Lethbridge",
    "sg:classifiers":[
        {
            "category":"Travel",
            "subcategory":"Hotels & Motels",
            "type":"Entertainment"
        }
    ],
    "sg:phone":"+1 403 327 2337",
    "sg:postcode":"T1J 2B5",
    "sg:province":"AB",
    "wof:name":"Smart Alecs Delivery",
    "wof:placetype":"venue"
},
  "geometry": {"coordinates":[-112.840461731,49.6952323914],"type":"Point"}
}