{
  "type": "Feature",
  "properties": {
    "addr:full":"Shawinigan QC G9N 1P6",
    "addr:postcode":"g9n 1p6",
    "iso:country":"CA",
    "sg:city":"Shawinigan",
    "sg:classifiers":[
        {
            "category":"Health Services",
            "subcategory":"Doctor",
            "type":"Services"
        }
    ],
    "sg:phone":"+1 819 536 2644",
    "sg:postcode":"G9N 1P6",
    "sg:province":"QC",
    "sg:tags":[
        "clinic",
        "dentist"
    ],
    "wof:name":"Clinique Dentaire Lupien",
    "wof:placetype":"venue"
},
  "geometry": {"coordinates":[-72.74612399999999,46.544151],"type":"Point"}
}