{
  "type": "Feature",
  "properties": {
    "addr:full":"4610 Dufferin St # 108 North York ON M3H 5S4",
    "addr:housenumber":"4610",
    "addr:postcode":"m3h 5s4",
    "addr:street":"Dufferin St # 108",
    "iso:country":"CA",
    "sg:address":"4610 Dufferin St # 108",
    "sg:city":"North York",
    "sg:classifiers":[
        {
            "category":"Organizations",
            "subcategory":"Professional Association",
            "type":"Services"
        }
    ],
    "sg:phone":"+1 905 738 5542",
    "sg:postcode":"M3H 5S4",
    "sg:province":"ON",
    "wof:name":"Zareniu Fundraising Office",
    "wof:placetype":"venue"
},
  "geometry": {"coordinates":[-79.46771200000001,43.771309],"type":"Point"}
}