{
  "type": "Feature",
  "properties": {
    "addr:full":"7205 8th Ave Regina SK S4T 0X1",
    "addr:housenumber":"7205",
    "addr:postcode":"s4t 0x1",
    "addr:street":"8Th Ave",
    "iso:country":"CA",
    "sg:address":"7205 8th Ave",
    "sg:city":"Regina",
    "sg:classifiers":[
        {
            "category":"Health Services",
            "subcategory":"Nursing And Care Facility",
            "type":"Services"
        }
    ],
    "sg:phone":"+1 306 545 8931",
    "sg:postcode":"S4T 0X1",
    "sg:province":"SK",
    "sg:tags":[
        "personal",
        "home"
    ],
    "wof:name":"Kelsey Manor",
    "wof:placetype":"venue"
},
  "geometry": {"coordinates":[-104.681793,50.456963],"type":"Point"}
}