{
  "type": "Feature",
  "properties": {
    "addr:full":"Havre-Saint-Pierre QC G0G 1P0",
    "addr:postcode":"g0g 1p0",
    "iso:country":"CA",
    "sg:city":"Havre-Saint-Pierre",
    "sg:classifiers":[
        {
            "category":"Professional",
            "subcategory":"Business Services",
            "type":"Services"
        }
    ],
    "sg:phone":"+1 418 538 2900",
    "sg:postcode":"G0G 1P0",
    "sg:province":"QC",
    "sg:tags":[
        "embroidery",
        "sportswear"
    ],
    "wof:name":"Confections Minganie Inc",
    "wof:placetype":"venue"
},
  "geometry": {"coordinates":[-63.594704,50.241852],"type":"Point"}
}