{
  "type": "Feature",
  "properties": {
    "addr:full":"1359 Wilson Ave North York ON M3M 1H7",
    "addr:housenumber":"1359",
    "addr:postcode":"m3m 1h7",
    "addr:street":"Wilson Ave",
    "iso:country":"CA",
    "sg:address":"1359 Wilson Ave",
    "sg:city":"North York",
    "sg:classifiers":[
        {
            "category":"Communications",
            "subcategory":"Film & Video Production",
            "type":"Services"
        }
    ],
    "sg:phone":"+1 416 244 1822",
    "sg:postcode":"M3M 1H7",
    "sg:province":"ON",
    "sg:tags":[
        "taping"
    ],
    "wof:name":"Overseas Video Lab",
    "wof:placetype":"venue"
},
  "geometry": {"coordinates":[-79.4978027344,43.7230186462],"type":"Point"}
}