{
  "type": "Feature",
  "properties": {
    "addr:full":"4270 Alice St Windsor ON N8Y 2B8",
    "addr:housenumber":"4270",
    "addr:postcode":"n8y 2b8",
    "addr:street":"Alice St",
    "iso:country":"CA",
    "sg:address":"4270 Alice St",
    "sg:city":"Windsor",
    "sg:classifiers":[
        {
            "category":"Recreation",
            "type":"Entertainment"
        }
    ],
    "sg:phone":"+1 519 945 2452",
    "sg:postcode":"N8Y 2B8",
    "sg:province":"ON",
    "sg:tags":[
        "government",
        "hall",
        "auditorium"
    ],
    "wof:name":"Ako Neighbourhood Ctr",
    "wof:placetype":"venue"
},
  "geometry": {"coordinates":[-82.97714233400001,42.3131752014],"type":"Point"}
}