{
  "type": "Feature",
  "properties": {
    "addr:full":"1467 Boul Saint-Martin O Laval QC H7S 1N1",
    "addr:housenumber":"1467",
    "addr:postcode":"h7s 1n1",
    "addr:street":"Boul Saint-Martin O",
    "iso:country":"CA",
    "sg:address":"1467 Boul Saint-Martin O",
    "sg:city":"Laval",
    "sg:classifiers":[
        {
            "category":"Shopping",
            "subcategory":"Books",
            "type":"Retail Goods"
        }
    ],
    "sg:phone":"+1 450 972 1922",
    "sg:postcode":"H7S 1N1",
    "sg:province":"QC",
    "sg:tags":[
        "collectible",
        "comic"
    ],
    "wof:name":"B D Cosmos",
    "wof:placetype":"venue"
},
  "geometry": {"coordinates":[-73.7244796753,45.5699996948],"type":"Point"}
}