{
  "type": "Feature",
  "properties": {
    "addr:full":"6395 Boul Robert Saint-Leonard QC H1P 1N2",
    "addr:housenumber":"6395",
    "addr:postcode":"h1p 1n2",
    "addr:street":"Boul Robert",
    "iso:country":"CA",
    "sg:address":"6395 Boul Robert",
    "sg:city":"Saint-Leonard",
    "sg:classifiers":[
        {
            "category":"Wholesale",
            "subcategory":"Meat",
            "type":"Manufacturing & Wholesale Goods"
        }
    ],
    "sg:phone":"+1 514 322 0883",
    "sg:postcode":"H1P 1N2",
    "sg:province":"QC",
    "sg:tags":[
        "butchering"
    ],
    "wof:name":"Boucherie Massimo",
    "wof:placetype":"venue"
},
  "geometry": {"coordinates":[-73.58843231199999,45.5964012146],"type":"Point"}
}