{
  "type": "Feature",
  "properties": {
    "iso:country":"CA",
    "sg:address":"6395 Boul Robert",
    "sg:city":"Saint-Leonard",
    "sg:classifiers":[
        {
            "category":"Wholesale",
            "subcategory":"Meat",
            "type":"Manufacturing & Wholesale Goods"
        }
    ],
    "sg:phone":"+1 514 322 0883",
    "sg:postcode":"H1P 1N2",
    "sg:province":"QC",
    "sg:tags":[
        "butchering"
    ],
    "wof:name":"Boucherie Massimo",
    "wof:placetype":"venue"
},
  "geometry": {"coordinates":[-73.58843231199999,45.5964012146],"type":"Point"}
}