{
  "type": "Feature",
  "properties": {
    "addr:full":"Main Hwy South River NL A0A 3W0",
    "addr:postcode":"a0a 3w0",
    "addr:street":"Main Hwy",
    "iso:country":"CA",
    "sg:address":"Main Hwy",
    "sg:city":"South River",
    "sg:classifiers":[
        {
            "category":"Food & Beverages",
            "subcategory":"Meat & Fish",
            "type":"Retail Goods"
        }
    ],
    "sg:phone":"+1 709 528 3469",
    "sg:postcode":"A0A 3W0",
    "sg:province":"NL",
    "sg:tags":[
        "seafood"
    ],
    "wof:name":"King's Fish Market Ltd",
    "wof:placetype":"venue"
},
  "geometry": {"coordinates":[-53.269871,47.536968],"type":"Point"}
}