{
  "type": "Feature",
  "properties": {
    "addr:full":"M'Chigeeng ON P0P 1G0",
    "addr:postcode":"p0p 1g0",
    "iso:country":"CA",
    "sg:city":"M'Chigeeng",
    "sg:classifiers":[
        {
            "category":"Health Services",
            "subcategory":"Nursing And Care Facility",
            "type":"Services"
        }
    ],
    "sg:phone":"+1 705 377 4240",
    "sg:postcode":"P0P 1G0",
    "sg:province":"ON",
    "sg:tags":[
        "home",
        "association",
        "rest"
    ],
    "wof:name":"West Bay First Nation",
    "wof:placetype":"venue"
},
  "geometry": {"coordinates":[-82.1614685059,45.8249015808],"type":"Point"}
}