{
  "type": "Feature",
  "properties": {
    "iso:country":"CA",
    "sg:address":"64 Rue Marchand",
    "sg:city":"Saint-Constant",
    "sg:classifiers":[
        {
            "category":"Manufacturing",
            "subcategory":"Printing",
            "type":"Manufacturing & Wholesale Goods"
        }
    ],
    "sg:phone":"+1 450 635 9359",
    "sg:postcode":"J5A 1B2",
    "sg:province":"QC",
    "sg:tags":[
        "business"
    ],
    "wof:name":"Comunik Media",
    "wof:placetype":"venue"
},
  "geometry": {"coordinates":[-73.553055,45.37989],"type":"Point"}
}