{
  "type": "Feature",
  "properties": {
    "iso:country":"CA",
    "sg:city":"Vancouver",
    "sg:classifiers":[
        {
            "category":"Professional",
            "subcategory":"Management & Consulting",
            "type":"Services"
        }
    ],
    "sg:phone":"+1 604 687 8759",
    "sg:postcode":"V6C 3B6",
    "sg:province":"BC",
    "sg:tags":[
        "consultant",
        "mining"
    ],
    "wof:name":"Merlion Consulting Ltd",
    "wof:placetype":"venue"
},
  "geometry": {"coordinates":[-123.117699,49.285042],"type":"Point"}
}