{
  "type": "Feature",
  "properties": {
    "addr:full":"453 Estate Dr Sherwood Park AB T8B 1L9",
    "addr:housenumber":"453",
    "addr:postcode":"t8b 1l9",
    "addr:street":"Estate Dr",
    "iso:country":"CA",
    "sg:address":"453 Estate Dr",
    "sg:city":"Sherwood Park",
    "sg:classifiers":[
        {
            "category":"Building & Trades",
            "subcategory":"Construction",
            "type":"Services"
        }
    ],
    "sg:phone":"+1 780 464 0616",
    "sg:postcode":"T8B 1L9",
    "sg:province":"AB",
    "sg:tags":[
        "home",
        "builder"
    ],
    "wof:name":"Brickwood Homes Ltd",
    "wof:placetype":"venue"
},
  "geometry": {"coordinates":[-113.284690857,53.5079078674],"type":"Point"}
}