{
  "type": "Feature",
  "properties": {
    "iso:country":"CA",
    "sg:city":"Longueuil",
    "sg:classifiers":[
        {
            "category":"Building & Trades",
            "subcategory":"Construction",
            "type":"Services"
        }
    ],
    "sg:phone":"+1 450 651 0230",
    "sg:postcode":"J4J 1G4",
    "sg:province":"QC",
    "sg:tags":[
        "repairing",
        "remodeling",
        "contractor"
    ],
    "wof:name":"Caron, Bruno",
    "wof:placetype":"venue"
},
  "geometry": {"coordinates":[-73.489532,45.536572],"type":"Point"}
}