{
  "type": "Feature",
  "properties": {
    "addr:full":"15 Olive Ave Toronto ON M6G 1T7",
    "addr:housenumber":"15",
    "addr:postcode":"m6g 1t7",
    "addr:street":"Olive Ave",
    "iso:country":"CA",
    "sg:address":"15 Olive Ave",
    "sg:city":"Toronto",
    "sg:classifiers":[
        {
            "category":"Organizations",
            "subcategory":"Religious Organization",
            "type":"Services"
        }
    ],
    "sg:phone":"+1 416 225 9989",
    "sg:postcode":"M6G 1T7",
    "sg:province":"ON",
    "sg:tags":[
        "church"
    ],
    "wof:name":"Jesus Bitnaeri Korean Presby",
    "wof:placetype":"venue"
},
  "geometry": {"coordinates":[-79.4140167236,43.6700172424],"type":"Point"}
}