{
  "type": "Feature",
  "properties": {
    "addr:full":"158 Boul Saint-Michel Dolbeau-Mistassini QC G8L 5J9",
    "addr:housenumber":"158",
    "addr:postcode":"g8l 5j9",
    "addr:street":"Boul Saint-Michel",
    "iso:country":"CA",
    "sg:address":"158 Boul Saint-Michel",
    "sg:city":"Dolbeau-Mistassini",
    "sg:classifiers":[
        {
            "category":"Real Estate",
            "subcategory":"Real Estate Agent",
            "type":"Services"
        }
    ],
    "sg:phone":"+1 418 276 0303",
    "sg:postcode":"G8L 5J9",
    "sg:province":"QC",
    "sg:tags":[
        "consultant"
    ],
    "wof:name":"Royal Lecompte Inc",
    "wof:placetype":"venue"
},
  "geometry": {"coordinates":[-72.2038116455,48.8938522339],"type":"Point"}
}