{
  "type": "Feature",
  "properties": {
    "addr:full":"501 2nd Ave E Alexander MB R0K 0A0",
    "addr:housenumber":"501",
    "addr:postcode":"r0k 0a0",
    "addr:street":"2Nd Ave E Alexander",
    "iso:country":"CA",
    "sg:address":"501 2nd Ave E",
    "sg:city":"Alexander",
    "sg:classifiers":[
        {
            "category":"Food & Beverages",
            "subcategory":"Groceries & Convenience Stores",
            "type":"Retail Goods"
        }
    ],
    "sg:phone":"+1 204 752 2027",
    "sg:postcode":"R0K 0A0",
    "sg:province":"MB",
    "sg:tags":[
        "grocer"
    ],
    "wof:name":"Stahl's Food Mart",
    "wof:placetype":"venue"
},
  "geometry": {"coordinates":[-100.30331420900001,49.8305854797],"type":"Point"}
}