{
  "type": "Feature",
  "properties": {
    "addr:full":"107 Rebecca St Stratford ON N5A 3P4",
    "addr:housenumber":"107",
    "addr:postcode":"n5a 3p4",
    "addr:street":"Rebecca St",
    "iso:country":"CA",
    "sg:address":"107 Rebecca St",
    "sg:city":"Stratford",
    "sg:classifiers":[
        {
            "category":"Building & Trades",
            "subcategory":"Construction",
            "type":"Services"
        }
    ],
    "sg:phone":"+1 519 271 8380",
    "sg:postcode":"N5A 3P4",
    "sg:province":"ON",
    "sg:tags":[
        "roofing",
        "contractor"
    ],
    "wof:name":"A Mabey Roofing Siding & Home",
    "wof:placetype":"venue"
},
  "geometry": {"coordinates":[-80.976006,43.368809],"type":"Point"}
}