{
  "type": "Feature",
  "properties": {
    "addr:full":"1651 St John St Regina SK S4P 1R6",
    "addr:housenumber":"1651",
    "addr:postcode":"s4p 1r6",
    "addr:street":"St John St",
    "iso:country":"CA",
    "sg:address":"1651 St John St",
    "sg:city":"Regina",
    "sg:classifiers":[
        {
            "category":"Building & Trades",
            "subcategory":"Electrical",
            "type":"Services"
        }
    ],
    "sg:phone":"+1 306 949 4774",
    "sg:postcode":"S4P 1R6",
    "sg:province":"SK",
    "sg:tags":[
        "electric",
        "contractor"
    ],
    "wof:name":"K West Electric Ltd",
    "wof:placetype":"venue"
},
  "geometry": {"coordinates":[-104.601814,50.45285],"type":"Point"}
}