{
  "type": "Feature",
  "properties": {
    "addr:full":"372 Rue Laurier Saint-Apollinaire QC G0S 2E0",
    "addr:housenumber":"372",
    "addr:postcode":"g0s 2e0",
    "addr:street":"Rue Laurier",
    "iso:country":"CA",
    "sg:address":"372 Rue Laurier",
    "sg:city":"Saint-Apollinaire",
    "sg:classifiers":[
        {
            "category":"Travel",
            "subcategory":"Hotels & Motels",
            "type":"Entertainment"
        }
    ],
    "sg:phone":"+1 418 881 3335",
    "sg:postcode":"G0S 2E0",
    "sg:province":"QC",
    "wof:name":"Motel Demers Inc",
    "wof:placetype":"venue"
},
  "geometry": {"coordinates":[-71.51222199999999,46.617695],"type":"Point"}
}