{
  "type": "Feature",
  "properties": {
    "addr:full":"37 Cross St York ON M9N 2B8",
    "addr:housenumber":"37",
    "addr:postcode":"m9n 2b8",
    "addr:street":"Cross St",
    "iso:country":"CA",
    "sg:address":"37 Cross St",
    "sg:city":"York",
    "sg:classifiers":[
        {
            "category":"Professional",
            "subcategory":"Computer Services",
            "type":"Services"
        }
    ],
    "sg:phone":"+1 416 245 7896",
    "sg:postcode":"M9N 2B8",
    "sg:province":"ON",
    "sg:tags":[
        "consultant"
    ],
    "wof:name":"Net Set Technologies Inc",
    "wof:placetype":"venue"
},
  "geometry": {"coordinates":[-79.524681,43.704388],"type":"Point"}
}