{
  "type": "Feature",
  "properties": {
    "addr:full":"Cranbrook BC V1C 2M9",
    "addr:postcode":"v1c 2m9",
    "iso:country":"CA",
    "sg:city":"Cranbrook",
    "sg:classifiers":[
        {
            "category":"Professional",
            "subcategory":"Accounting & Tax Preparation",
            "type":"Services"
        }
    ],
    "sg:phone":"+1 250 426 4285",
    "sg:postcode":"V1C 2M9",
    "sg:province":"BC",
    "sg:tags":[
        "accountant"
    ],
    "wof:name":"Bdo Dunwoody Ltd",
    "wof:placetype":"venue"
},
  "geometry": {"coordinates":[-115.767769,49.511593],"type":"Point"}
}