{
  "type": "Feature",
  "properties": {
    "iso:country":"CA",
    "sg:address":"145 Centenial Dr",
    "sg:city":"Longlac",
    "sg:classifiers":[
        {
            "category":"Building & Trades",
            "subcategory":"Plumbing",
            "type":"Services"
        }
    ],
    "sg:phone":"+1 807 876 4787",
    "sg:postcode":"P0T 2A0",
    "sg:province":"ON",
    "sg:tags":[
        "air",
        "conditioning",
        "contractor",
        "system",
        "heating"
    ],
    "wof:name":"Bedard, Marcel",
    "wof:placetype":"venue"
},
  "geometry": {"coordinates":[-86.5326461792,49.7747993469],"type":"Point"}
}