{
  "type": "Feature",
  "properties": {
    "iso:country":"CA",
    "sg:address":"5184 Av Du Parc",
    "sg:city":"Montreal",
    "sg:classifiers":[
        {
            "category":"Shopping",
            "subcategory":"Pharmacy",
            "type":"Retail Goods"
        }
    ],
    "sg:phone":"+1 514 271 2345",
    "sg:postcode":"H2V 4G6",
    "sg:province":"QC",
    "wof:name":"Pharmacie Nicolas Liounis",
    "wof:placetype":"venue"
},
  "geometry": {"coordinates":[-73.5973205566,45.5201644897],"type":"Point"}
}