{
  "type": "Feature",
  "properties": {
    "addr:full":"16 Mechanic St Springhill NS B0M 1X0",
    "addr:housenumber":"16",
    "addr:postcode":"b0m 1x0",
    "addr:street":"Mechanic St",
    "iso:country":"CA",
    "sg:address":"16 Mechanic St",
    "sg:city":"Springhill",
    "sg:classifiers":[
        {
            "category":"Health Services",
            "subcategory":"Medical Lab",
            "type":"Services"
        }
    ],
    "sg:phone":"+1 902 597 3076",
    "sg:postcode":"B0M 1X0",
    "sg:province":"NS",
    "wof:name":"Laurie Springhill Denture Clnc",
    "wof:placetype":"venue"
},
  "geometry": {"coordinates":[-64.05541229249999,45.6498718262],"type":"Point"}
}