{
  "type": "Feature",
  "properties": {
    "iso:country":"CA",
    "sg:address":"806 Fort William Rd",
    "sg:city":"Thunder Bay",
    "sg:classifiers":[
        {
            "category":"Home & Garden",
            "subcategory":"Carpets & Floor Coverings",
            "type":"Retail Goods"
        }
    ],
    "sg:phone":"+1 807 344 3848",
    "sg:postcode":"P7B 3A3",
    "sg:province":"ON",
    "sg:tags":[
        "material"
    ],
    "wof:name":"Q C Quality Carpet Inc",
    "wof:placetype":"venue"
},
  "geometry": {"coordinates":[-89.23998260499999,48.4091911316],"type":"Point"}
}