{
  "type": "Feature",
  "properties": {
    "addr:full":"2300 Hart Hwy Dawson Creek BC V1G 4L1",
    "addr:housenumber":"2300",
    "addr:postcode":"v1g 4l1",
    "addr:street":"Hart Hwy",
    "iso:country":"CA",
    "sg:address":"2300 Hart Hwy",
    "sg:city":"Dawson Creek",
    "sg:classifiers":[
        {
            "category":"Wholesale",
            "subcategory":"Machinery & Supplies",
            "type":"Manufacturing & Wholesale Goods"
        }
    ],
    "sg:phone":"+1 250 782 2287",
    "sg:postcode":"V1G 4L1",
    "sg:province":"BC",
    "sg:tags":[
        "contractor"
    ],
    "wof:name":"Pollard Equipment Ltd",
    "wof:placetype":"venue"
},
  "geometry": {"coordinates":[-120.237061,55.761726],"type":"Point"}
}