{
  "type": "Feature",
  "properties": {
    "iso:country":"CA",
    "sg:address":"143 Keown St",
    "sg:city":"Essex",
    "sg:classifiers":[
        {
            "category":"Shopping",
            "type":"Retail Goods"
        }
    ],
    "sg:phone":"+1 519 776 5767",
    "sg:postcode":"N8M 1J2",
    "sg:province":"ON",
    "sg:tags":[
        "art",
        "gallery",
        "dealer"
    ],
    "wof:name":"Suchiu Art & Framing",
    "wof:placetype":"venue"
},
  "geometry": {"coordinates":[-82.82688903810001,42.1738243103],"type":"Point"}
}