{
  "type": "Feature",
  "properties": {
    "iso:country":"CA",
    "sg:address":"979 Mountain Rd",
    "sg:city":"Moncton",
    "sg:classifiers":[
        {
            "category":"Restaurant",
            "type":"Food & Drink"
        }
    ],
    "sg:phone":"+1 506 858 1188",
    "sg:postcode":"E1C 2S5",
    "sg:province":"NB",
    "wof:name":"Sun Sun Take Out Restaurant",
    "wof:placetype":"venue"
},
  "geometry": {"coordinates":[-64.8167190552,46.1031341553],"type":"Point"}
}