{
  "type": "Feature",
  "properties": {
    "addr:full":"225 Main St S Newmarket ON L3Y 3Y9",
    "addr:housenumber":"225",
    "addr:postcode":"l3y 3y9",
    "addr:street":"Main St S",
    "iso:country":"CA",
    "sg:address":"225 Main St S",
    "sg:city":"Newmarket",
    "sg:classifiers":[
        {
            "category":"Professional",
            "subcategory":"Business Services",
            "type":"Services"
        }
    ],
    "sg:phone":"+1 905 853 5544",
    "sg:postcode":"L3Y 3Y9",
    "sg:province":"ON",
    "sg:tags":[
        "shop",
        "gift",
        "consultant",
        "design",
        "interior",
        "decorator"
    ],
    "wof:name":"What's in Store",
    "wof:placetype":"venue"
},
  "geometry": {"coordinates":[-79.45684799999999,44.052658],"type":"Point"}
}