{
  "type": "Feature",
  "properties": {
    "addr:full":"15371 Castle Downs Rd NW Edmonton AB T5X 6C3",
    "addr:housenumber":"15371",
    "addr:postcode":"t5x 6c3",
    "addr:street":"Castle Downs Rd Nw",
    "iso:country":"CA",
    "sg:address":"15371 Castle Downs Rd NW",
    "sg:city":"Edmonton",
    "sg:classifiers":[
        {
            "category":"Shopping",
            "subcategory":"Gifts & Souvenirs",
            "type":"Retail Goods"
        }
    ],
    "sg:phone":"+1 780 472 1796",
    "sg:postcode":"T5X 6C3",
    "sg:province":"AB",
    "sg:tags":[
        "shop"
    ],
    "wof:name":"Whimsy's",
    "wof:placetype":"venue"
},
  "geometry": {"coordinates":[-113.516464,53.615524],"type":"Point"}
}