{
  "type": "Feature",
  "properties": {
    "addr:full":"Etobicoke ON M8X 1Y3",
    "addr:postcode":"m8x 1y3",
    "iso:country":"CA",
    "sg:city":"Etobicoke",
    "sg:classifiers":[
        {
            "category":"Retail",
            "subcategory":"Veterinary Services",
            "type":"Services"
        }
    ],
    "sg:phone":"+1 416 236 2316",
    "sg:postcode":"M8X 1Y3",
    "sg:province":"ON",
    "sg:tags":[
        "veterinarian"
    ],
    "wof:name":"Cloverdale Veterinary Hospital",
    "wof:placetype":"venue"
},
  "geometry": {"coordinates":[-79.511246,43.66021],"type":"Point"}
}