{
  "type": "Feature",
  "properties": {
    "addr:full":"Calgary AB T3G 4B7",
    "addr:postcode":"t3g 4b7",
    "iso:country":"CA",
    "sg:city":"Calgary",
    "sg:classifiers":[
        {
            "category":"Retail",
            "subcategory":"Auto Repair",
            "type":"Services"
        }
    ],
    "sg:phone":"+1 403 547 6116",
    "sg:postcode":"T3G 4B7",
    "sg:province":"AB",
    "sg:tags":[
        "automobile",
        "lubrication"
    ],
    "wof:name":"Minit Lube",
    "wof:placetype":"venue"
},
  "geometry": {"coordinates":[-114.207756,51.12574],"type":"Point"}
}