{
  "type": "Feature",
  "properties": {
    "addr:full":"43 Epworth Ave Nepean ON K2G 2L8",
    "addr:housenumber":"43",
    "addr:postcode":"k2g 2l8",
    "addr:street":"Epworth Ave",
    "iso:country":"CA",
    "sg:address":"43 Epworth Ave",
    "sg:city":"Nepean",
    "sg:classifiers":[
        {
            "category":"Building & Trades",
            "subcategory":"Construction",
            "type":"Services"
        }
    ],
    "sg:phone":"+1 613 225 4835",
    "sg:postcode":"K2G 2L8",
    "sg:province":"ON",
    "sg:tags":[
        "concrete",
        "contractor"
    ],
    "wof:name":"M Fantinic Forming Ltd",
    "wof:placetype":"venue"
},
  "geometry": {"coordinates":[-75.74530799999999,45.350079],"type":"Point"}
}