{
  "type": "Feature",
  "properties": {
    "addr:full":"Altona MB R0G 0B0",
    "addr:postcode":"r0g 0b0",
    "iso:country":"CA",
    "sg:city":"Altona",
    "sg:classifiers":[
        {
            "category":"Autos & Motor Vehicles",
            "subcategory":"Motorcycle Sales",
            "type":"Retail Goods"
        }
    ],
    "sg:phone":"+1 204 324 5074",
    "sg:postcode":"R0G 0B0",
    "sg:province":"MB",
    "sg:tags":[
        "all",
        "terrain",
        "snowmobile"
    ],
    "wof:name":"Keystone Cat Shop",
    "wof:placetype":"venue"
},
  "geometry": {"coordinates":[-97.551216,49.103539],"type":"Point"}
}