{
  "type": "Feature",
  "properties": {
    "addr:full":"5430 County Rd 1 Consecon ON K0K 1T0",
    "addr:housenumber":"5430",
    "addr:postcode":"k0k 1t0",
    "addr:street":"County Rd 1",
    "iso:country":"CA",
    "sg:address":"5430 County Rd 1",
    "sg:city":"Consecon",
    "sg:classifiers":[
        {
            "category":"Travel",
            "subcategory":"Hotels & Motels",
            "type":"Entertainment"
        }
    ],
    "sg:phone":"+1 613 399 5518",
    "sg:postcode":"K0K 1T0",
    "sg:province":"ON",
    "sg:tags":[
        "cottage",
        "cabin"
    ],
    "wof:name":"Lake Consecon Resort",
    "wof:placetype":"venue"
},
  "geometry": {"coordinates":[-77.5215,43.991421],"type":"Point"}
}