{
  "type": "Feature",
  "properties": {
    "addr:full":"1020 Huntercove Pl NW Calgary AB T2K 4S4",
    "addr:housenumber":"1020",
    "addr:postcode":"t2k 4s4",
    "addr:street":"Huntercove Pl Nw",
    "iso:country":"CA",
    "sg:address":"1020 Huntercove Pl NW",
    "sg:city":"Calgary",
    "sg:classifiers":[
        {
            "category":"Professional",
            "subcategory":"Accounting & Tax Preparation",
            "type":"Services"
        }
    ],
    "sg:phone":"+1 403 275 5980",
    "sg:postcode":"T2K 4S4",
    "sg:province":"AB",
    "sg:tags":[
        "consultant",
        "accountant",
        "management",
        "business"
    ],
    "wof:name":"Monette Management Inc",
    "wof:placetype":"venue"
},
  "geometry": {"coordinates":[-114.08240499999999,51.115517],"type":"Point"}
}