{
  "type": "Feature",
  "properties": {
    "addr:full":"5572 Extrom Rd Chilliwack BC V2R 4S7",
    "addr:housenumber":"5572",
    "addr:postcode":"v2r 4s7",
    "addr:street":"Extrom Rd",
    "iso:country":"CA",
    "sg:address":"5572 Extrom Rd",
    "sg:city":"Chilliwack",
    "sg:classifiers":[
        {
            "category":"Retail",
            "subcategory":"Repair Shop",
            "type":"Services"
        }
    ],
    "sg:phone":"+1 604 795 3210",
    "sg:postcode":"V2R 4S7",
    "sg:province":"BC",
    "sg:tags":[
        "appliance"
    ],
    "wof:name":"Chilliwack Appliance & Refrig",
    "wof:placetype":"venue"
},
  "geometry": {"coordinates":[-121.89613300000001,49.103981],"type":"Point"}
}