{
  "type": "Feature",
  "properties": {
    "addr:full":"64 Holland St E Bradford ON L3Z 2B4",
    "addr:housenumber":"64",
    "addr:postcode":"l3z 2b4",
    "addr:street":"Holland St E",
    "iso:country":"CA",
    "sg:address":"64 Holland St E",
    "sg:city":"Bradford",
    "sg:classifiers":[
        {
            "category":"Personal",
            "subcategory":"Beauty Salon",
            "type":"Services"
        }
    ],
    "sg:phone":"+1 905 775 4000",
    "sg:postcode":"L3Z 2B4",
    "sg:province":"ON",
    "wof:name":"Head Shoppe",
    "wof:placetype":"venue"
},
  "geometry": {"coordinates":[-79.56237792970001,44.1147499084],"type":"Point"}
}