{
  "type": "Feature",
  "properties": {
    "addr:full":"230 78 Ave SE Calgary AB T2H 1C4",
    "addr:postcode":"230;t2h 1c4",
    "addr:street":"78 Ave Se",
    "iso:country":"CA",
    "sg:address":"230 78 Ave SE",
    "sg:city":"Calgary",
    "sg:classifiers":[
        {
            "category":"Organizations",
            "subcategory":"Religious Organization",
            "type":"Services"
        }
    ],
    "sg:phone":"+1 403 252 1704",
    "sg:postcode":"T2H 1C4",
    "sg:province":"AB",
    "sg:tags":[
        "church"
    ],
    "wof:name":"Fairview Baptist Church",
    "wof:placetype":"venue"
},
  "geometry": {"coordinates":[-114.061699,50.983818],"type":"Point"}
}