{
  "type": "Feature",
  "properties": {
    "addr:full":"8176 Rue Jean-Brillon Lasalle QC H8N 2J5",
    "addr:housenumber":"8176",
    "addr:postcode":"h8n 2j5",
    "addr:street":"Rue Jean-Brillon",
    "iso:country":"CA",
    "sg:address":"8176 Rue Jean-Brillon",
    "sg:city":"Lasalle",
    "sg:classifiers":[
        {
            "category":"Health Services",
            "subcategory":"Hospital",
            "type":"Services"
        }
    ],
    "sg:phone":"+1 514 366 3266",
    "sg:postcode":"H8N 2J5",
    "sg:province":"QC",
    "wof:name":"Pyramide",
    "wof:placetype":"venue"
},
  "geometry": {"coordinates":[-73.6170043945,45.4329872131],"type":"Point"}
}