{
  "type": "Feature",
  "properties": {
    "addr:full":"2875 Av Douglas Montreal QC H3R 2C7",
    "addr:housenumber":"2875",
    "addr:postcode":"h3r 2c7",
    "addr:street":"Av Douglas",
    "iso:country":"CA",
    "sg:address":"2875 Av Douglas",
    "sg:city":"Montreal",
    "sg:classifiers":[
        {
            "category":"Professional",
            "subcategory":"Advertising",
            "type":"Services"
        }
    ],
    "sg:phone":"+1 514 738 5517",
    "sg:postcode":"H3R 2C7",
    "sg:province":"QC",
    "sg:tags":[
        "publisher"
    ],
    "wof:name":"Alexandre-Alexander Enr",
    "wof:placetype":"venue"
},
  "geometry": {"coordinates":[-73.63655853269999,45.5124778748],"type":"Point"}
}