{
  "type": "Feature",
  "properties": {
    "addr:full":"Mississauga ON L5K 1R8",
    "addr:postcode":"l5k 1r8",
    "iso:country":"CA",
    "sg:city":"Mississauga",
    "sg:classifiers":[
        {
            "category":"Retail",
            "subcategory":"Laundry & Dry Cleaning",
            "type":"Services"
        }
    ],
    "sg:phone":"+1 905 823 7895",
    "sg:postcode":"L5K 1R8",
    "sg:province":"ON",
    "sg:tags":[
        "cleaners"
    ],
    "wof:name":"Stitch & Clean",
    "wof:placetype":"venue"
},
  "geometry": {"coordinates":[-79.6756973267,43.5280380249],"type":"Point"}
}