{
  "type": "Feature",
  "properties": {
    "addr:full":"Cochenour Airport Cochenour ON P0V 1L0",
    "addr:postcode":"p0v 1l0",
    "iso:country":"CA",
    "sg:address":"Cochenour Airport",
    "sg:city":"Cochenour",
    "sg:classifiers":[
        {
            "category":"Government",
            "subcategory":"Fire Station",
            "type":"Public Place"
        }
    ],
    "sg:phone":"+1 807 662 7501",
    "sg:postcode":"P0V 1L0",
    "sg:province":"ON",
    "sg:tags":[
        "department"
    ],
    "wof:name":"Ontario Red Lake Tanker Base",
    "wof:placetype":"venue"
},
  "geometry": {"coordinates":[-93.807716,51.07362],"type":"Point"}
}