{
  "type": "Feature",
  "properties": {
    "addr:full":"8168 46 St NW Edmonton AB T6B 2M8",
    "addr:housenumber":"8168",
    "addr:postcode":"t6b 2m8",
    "addr:street":"46 St Nw",
    "iso:country":"CA",
    "sg:address":"8168 46 St NW",
    "sg:city":"Edmonton",
    "sg:classifiers":[
        {
            "category":"Manufacturing",
            "subcategory":"Tools & Machinery",
            "type":"Manufacturing & Wholesale Goods"
        }
    ],
    "sg:phone":"+1 780 468 4744",
    "sg:postcode":"T6B 2M8",
    "sg:province":"AB",
    "sg:tags":[
        "corrugated",
        "solid",
        "fiber",
        "box"
    ],
    "wof:name":"Specialty Packaging",
    "wof:placetype":"venue"
},
  "geometry": {"coordinates":[-113.41206359900001,53.517162323],"type":"Point"}
}