{
  "type": "Feature",
  "properties": {
    "iso:country":"CA",
    "sg:address":"1450 Ch DE Chambly",
    "sg:city":"Longueuil",
    "sg:classifiers":[
        {
            "category":"Health Services",
            "subcategory":"Doctor",
            "type":"Services"
        }
    ],
    "sg:phone":"+1 450 651 0580",
    "sg:postcode":"J4J 3X3",
    "sg:province":"QC",
    "sg:tags":[
        "dentist"
    ],
    "wof:name":"David, Guy DDS",
    "wof:placetype":"venue"
},
  "geometry": {"coordinates":[-73.486198,45.531136],"type":"Point"}
}