{
  "type": "Feature",
  "properties": {
    "addr:full":"9341 Burns Dr Delta BC V4K 3N3",
    "addr:housenumber":"9341",
    "addr:postcode":"v4k 3n3",
    "addr:street":"Burns Dr",
    "iso:country":"CA",
    "sg:address":"9341 Burns Dr",
    "sg:city":"Delta",
    "sg:classifiers":[
        {
            "category":"Health Services",
            "subcategory":"Hospital",
            "type":"Services"
        }
    ],
    "sg:phone":"+1 604 596 8842",
    "sg:postcode":"V4K 3N3",
    "sg:province":"BC",
    "wof:name":"Delta View Habilitation Ctr",
    "wof:placetype":"venue"
},
  "geometry": {"coordinates":[-122.96672100000001,49.090992],"type":"Point"}
}