{
  "type": "Feature",
  "properties": {
    "iso:country":"CA",
    "sg:address":"633 Lions Park Dr",
    "sg:city":"Mount Brydges",
    "sg:classifiers":[
        {
            "category":"Organizations",
            "subcategory":"Professional Association",
            "type":"Services"
        }
    ],
    "sg:phone":"+1 519 264 1444",
    "sg:postcode":"N0L 1W0",
    "sg:province":"ON",
    "wof:name":"Ontario Federation",
    "wof:placetype":"venue"
},
  "geometry": {"coordinates":[-81.4964065552,42.9099998474],"type":"Point"}
}