{
  "type": "Feature",
  "properties": {
    "addr:full":"203 Front St Sturgeon Falls ON P2B 2J4",
    "addr:housenumber":"203",
    "addr:postcode":"p2b 2j4",
    "addr:street":"Front St",
    "iso:country":"CA",
    "sg:address":"203 Front St",
    "sg:city":"Sturgeon Falls",
    "sg:classifiers":[
        {
            "category":"Food & Beverages",
            "subcategory":"Groceries & Convenience Stores",
            "type":"Retail Goods"
        }
    ],
    "sg:phone":"+1 705 753 4033",
    "sg:postcode":"P2B 2J4",
    "sg:province":"ON",
    "sg:tags":[
        "grocer"
    ],
    "wof:name":"A & P Food Stores Ltd",
    "wof:placetype":"venue"
},
  "geometry": {"coordinates":[-79.91664886469999,46.3660888672],"type":"Point"}
}