{
  "type": "Feature",
  "properties": {
    "addr:full":"309 Main St N Russell MB R0J 1W0",
    "addr:housenumber":"309",
    "addr:postcode":"r0j 1w0",
    "addr:street":"Main St N",
    "iso:country":"CA",
    "sg:address":"309 Main St N",
    "sg:city":"Russell",
    "sg:classifiers":[
        {
            "category":"Travel",
            "subcategory":"Hotels & Motels",
            "type":"Entertainment"
        }
    ],
    "sg:phone":"+1 204 773 2002",
    "sg:postcode":"R0J 1W0",
    "sg:province":"MB",
    "wof:name":"Asessippi Inn",
    "wof:placetype":"venue"
},
  "geometry": {"coordinates":[-101.288024902,50.7818717957],"type":"Point"}
}