{
  "type": "Feature",
  "properties": {
    "addr:full":"8109 104 St NW Edmonton AB T6E 4E4",
    "addr:housenumber":"8109",
    "addr:postcode":"t6e 4e4",
    "addr:street":"104 St Nw",
    "iso:country":"CA",
    "sg:address":"8109 104 St NW",
    "sg:city":"Edmonton",
    "sg:classifiers":[
        {
            "category":"Restaurant",
            "type":"Food & Drink"
        }
    ],
    "sg:phone":"+1 780 435 3200",
    "sg:postcode":"T6E 4E4",
    "sg:province":"AB",
    "wof:name":"Pita Pit",
    "wof:placetype":"venue"
},
  "geometry": {"coordinates":[-113.497215,53.517231],"type":"Point"}
}