{
  "type": "Feature",
  "properties": {
    "addr:full":"107 Hwy 592 Novar ON P0A 1R0",
    "addr:housenumber":"107",
    "addr:postcode":"p0a 1r0",
    "addr:street":"Hwy 592",
    "iso:country":"CA",
    "sg:address":"107 Hwy 592",
    "sg:city":"Novar",
    "sg:classifiers":[
        {
            "category":"Manufacturing",
            "subcategory":"Lumber",
            "type":"Manufacturing & Wholesale Goods"
        }
    ],
    "sg:phone":"+1 519 665 2492",
    "sg:postcode":"P0A 1R0",
    "sg:province":"ON",
    "sg:tags":[
        "company",
        "logging"
    ],
    "wof:name":"D J Logging",
    "wof:placetype":"venue"
},
  "geometry": {"coordinates":[-79.249207,45.449757],"type":"Point"}
}