{
  "type": "Feature",
  "properties": {
    "iso:country":"CA",
    "sg:address":"21030 Glen Robertson Rd",
    "sg:city":"Alexandria",
    "sg:classifiers":[
        {
            "category":"Manufacturing",
            "subcategory":"Tools & Machinery",
            "type":"Manufacturing & Wholesale Goods"
        }
    ],
    "sg:phone":"+1 613 525 3691",
    "sg:postcode":"K0C 1A0",
    "sg:province":"ON",
    "sg:tags":[
        "farm",
        "equipment"
    ],
    "wof:name":"R B Farm & Dairy Equipment Ltd",
    "wof:placetype":"venue"
},
  "geometry": {"coordinates":[-74.577293396,45.3278923035],"type":"Point"}
}