{
  "type": "Feature",
  "properties": {
    "iso:country":"CA",
    "sg:city":"Montreal",
    "sg:classifiers":[
        {
            "category":"Professional",
            "subcategory":"Employment Agencies",
            "type":"Services"
        }
    ],
    "sg:phone":"+1 514 987 0202",
    "sg:postcode":"H3A 1T8",
    "sg:province":"QC",
    "sg:tags":[
        "consultant",
        "search",
        "executive"
    ],
    "wof:name":"Societe Jean Pierre Brisebois",
    "wof:placetype":"venue"
},
  "geometry": {"coordinates":[-73.5749969482,45.5012283325],"type":"Point"}
}