{
  "type": "Feature",
  "properties": {
    "addr:full":"1384 Av Greene Westmount QC H3Z 2B1",
    "addr:housenumber":"1384",
    "addr:postcode":"h3z 2b1",
    "addr:street":"Av Greene",
    "iso:country":"CA",
    "sg:address":"1384 Av Greene",
    "sg:city":"Westmount",
    "sg:classifiers":[
        {
            "category":"Real Estate",
            "subcategory":"Real Estate Agent",
            "type":"Services"
        }
    ],
    "sg:phone":"+1 514 846 4045",
    "sg:postcode":"H3Z 2B1",
    "sg:province":"QC",
    "sg:tags":[
        "attorney"
    ],
    "wof:name":"Morris Feinsten Inc",
    "wof:placetype":"venue"
},
  "geometry": {"coordinates":[-73.59142300000001,45.48756],"type":"Point"}
}