{
  "type": "Feature",
  "properties": {
    "iso:country":"CA",
    "sg:city":"Burlington",
    "sg:classifiers":[
        {
            "category":"Wholesale",
            "subcategory":"Machinery & Supplies",
            "type":"Manufacturing & Wholesale Goods"
        }
    ],
    "sg:phone":"+1 905 632 2592",
    "sg:postcode":"L7R 2G3",
    "sg:province":"ON",
    "sg:tags":[
        "janitor"
    ],
    "wof:name":"Acsi",
    "wof:placetype":"venue"
},
  "geometry": {"coordinates":[-79.799126,43.326771],"type":"Point"}
}