{
  "type": "Feature",
  "properties": {
    "addr:full":"2027 50th Ave E Vancouver BC V5P 1V4",
    "addr:housenumber":"2027",
    "addr:postcode":"v5p 1v4",
    "addr:street":"50Th Ave E",
    "iso:country":"CA",
    "sg:address":"2027 50th Ave E",
    "sg:city":"Vancouver",
    "sg:classifiers":[
        {
            "category":"Real Estate",
            "subcategory":"Surveying",
            "type":"Services"
        }
    ],
    "sg:phone":"+1 604 325 2696",
    "sg:postcode":"V5P 1V4",
    "sg:province":"BC",
    "sg:tags":[
        "surveyor"
    ],
    "wof:name":"Caffo Land Surveying Ltd",
    "wof:placetype":"venue"
},
  "geometry": {"coordinates":[-123.065048218,49.2242355347],"type":"Point"}
}