{
  "type": "Feature",
  "properties": {
    "iso:country":"CA",
    "sg:city":"Sainte-Emelie-DE-L'Energie",
    "sg:classifiers":[
        {
            "category":"Home & Garden",
            "subcategory":"Hardware",
            "type":"Retail Goods"
        }
    ],
    "sg:phone":"+1 450 886 3854",
    "sg:postcode":"J0K 2K0",
    "sg:province":"QC",
    "wof:name":"Georges H Durand Ltee",
    "wof:placetype":"venue"
},
  "geometry": {"coordinates":[-67.52100372309999,48.8455467224],"type":"Point"}
}