{
  "type": "Feature",
  "properties": {
    "iso:country":"CA",
    "sg:address":"4654 Lazelle Ave",
    "sg:city":"Terrace",
    "sg:classifiers":[
        {
            "category":"Government",
            "subcategory":"Office",
            "type":"Public Place"
        }
    ],
    "sg:phone":"+1 250 635 1601",
    "sg:postcode":"V8G 1S6",
    "sg:province":"BC",
    "wof:name":"Canada Member of Parliament",
    "wof:placetype":"venue"
},
  "geometry": {"coordinates":[-128.59095764200001,54.5177345276],"type":"Point"}
}