{
  "type": "Feature",
  "properties": {
    "addr:full":"778 50th Ave E Vancouver BC V5X 1B3",
    "addr:housenumber":"778",
    "addr:postcode":"v5x 1b3",
    "addr:street":"50Th Ave E",
    "iso:country":"CA",
    "sg:address":"778 50th Ave E",
    "sg:city":"Vancouver",
    "sg:classifiers":[
        {
            "category":"Banks & Credit Unions",
            "subcategory":"Financial Services",
            "type":"Services"
        }
    ],
    "sg:phone":"+1 604 325 8820",
    "sg:postcode":"V5X 1B3",
    "sg:province":"BC",
    "sg:tags":[
        "company",
        "holding"
    ],
    "wof:name":"Lai's Enterprises Ltd",
    "wof:placetype":"venue"
},
  "geometry": {"coordinates":[-123.08875999999999,49.224396],"type":"Point"}
}