{
  "type": "Feature",
  "properties": {
    "addr:full":"5728 111 St NW Edmonton AB T6H 3G1",
    "addr:housenumber":"5728",
    "addr:postcode":"t6h 3g1",
    "addr:street":"111 St Nw",
    "iso:country":"CA",
    "sg:address":"5728 111 St NW",
    "sg:city":"Edmonton",
    "sg:classifiers":[
        {
            "category":"Food & Beverages",
            "subcategory":"Groceries & Convenience Stores",
            "type":"Retail Goods"
        }
    ],
    "sg:phone":"+1 780 434 2610",
    "sg:postcode":"T6H 3G1",
    "sg:province":"AB",
    "sg:tags":[
        "grocer"
    ],
    "wof:name":"Sunterra Marketplace",
    "wof:placetype":"venue"
},
  "geometry": {"coordinates":[-113.517174,53.494606],"type":"Point"}
}