{
  "type": "Feature",
  "properties": {
    "addr:full":"Scarborough ON M1V 4V7",
    "addr:postcode":"m1v 4v7",
    "iso:country":"CA",
    "sg:city":"Scarborough",
    "sg:classifiers":[
        {
            "category":"Retail",
            "subcategory":"Auto Repair",
            "type":"Services"
        }
    ],
    "sg:phone":"+1 416 291 7323",
    "sg:postcode":"M1V 4V7",
    "sg:province":"ON",
    "sg:tags":[
        "repairing",
        "automobile",
        "painting"
    ],
    "wof:name":"Mac Gyver Collision Autobody",
    "wof:placetype":"venue"
},
  "geometry": {"coordinates":[-79.28954315190001,43.8086280823],"type":"Point"}
}