{
  "type": "Feature",
  "properties": {
    "addr:full":"Kelowna BC V1Y 9M9",
    "addr:postcode":"v1y 9m9",
    "iso:country":"CA",
    "sg:city":"Kelowna",
    "sg:classifiers":[
        {
            "category":"Home & Garden",
            "subcategory":"Building Materials",
            "type":"Retail Goods"
        }
    ],
    "sg:phone":"+1 250 979 4383",
    "sg:postcode":"V1Y 9M9",
    "sg:province":"BC",
    "sg:tags":[
        "glass",
        "leaded"
    ],
    "wof:name":"High Country Stained Glass",
    "wof:placetype":"venue"
},
  "geometry": {"coordinates":[-119.464569,49.880688],"type":"Point"}
}