{
  "type": "Feature",
  "properties": {
    "addr:full":"153 Simcoe St N Oshawa ON L1G 4S6",
    "addr:housenumber":"153",
    "addr:postcode":"l1g 4s6",
    "addr:street":"Simcoe St N",
    "iso:country":"CA",
    "sg:address":"153 Simcoe St N",
    "sg:city":"Oshawa",
    "sg:classifiers":[
        {
            "category":"Professional",
            "subcategory":"Lawyer & Legal Services",
            "type":"Services"
        }
    ],
    "sg:phone":"+1 905 723 2288",
    "sg:postcode":"L1G 4S6",
    "sg:province":"ON",
    "sg:tags":[
        "attorney"
    ],
    "wof:name":"Worboy, Ronald F",
    "wof:placetype":"venue"
},
  "geometry": {"coordinates":[-78.865234,43.901569],"type":"Point"}
}