{
  "type": "Feature",
  "properties": {
    "iso:country":"CA",
    "sg:address":"4285 Rue Beaubien E",
    "sg:city":"Montreal",
    "sg:classifiers":[
        {
            "category":"Personal",
            "subcategory":"Beauty Salon",
            "type":"Services"
        }
    ],
    "sg:phone":"+1 514 727 2599",
    "sg:postcode":"H1T 1S7",
    "sg:province":"QC",
    "wof:name":"Nathalie Brosseau Coiffure",
    "wof:placetype":"venue"
},
  "geometry": {"coordinates":[-73.57847595210001,45.5642585754],"type":"Point"}
}