{
  "type": "Feature",
  "properties": {
    "iso:country":"CA",
    "sg:address":"317 Gore Rd",
    "sg:city":"Kingston",
    "sg:classifiers":[
        {
            "category":"Organizations",
            "subcategory":"Community Association",
            "type":"Services"
        }
    ],
    "sg:phone":"+1 613 549 7597",
    "sg:postcode":"K7L 5H6",
    "sg:province":"ON",
    "sg:tags":[
        "club"
    ],
    "wof:name":"Army Navy Air Force Unit 377",
    "wof:placetype":"venue"
},
  "geometry": {"coordinates":[-76.4488830566,44.2600593567],"type":"Point"}
}