{
  "type": "Feature",
  "properties": {
    "iso:country":"CA",
    "sg:address":"122 George St",
    "sg:city":"Lanark",
    "sg:classifiers":[
        {
            "category":"Home & Garden",
            "subcategory":"Garden Supply",
            "type":"Retail Goods"
        }
    ],
    "sg:phone":"+1 613 259 2949",
    "sg:postcode":"K0G 1K0",
    "sg:province":"ON",
    "sg:tags":[
        "lawn"
    ],
    "wof:name":"Lanark Farm Supplies",
    "wof:placetype":"venue"
},
  "geometry": {"coordinates":[-76.3688964844,45.0209617615],"type":"Point"}
}