{
  "type": "Feature",
  "properties": {
    "addr:full":"1456 Dundas St E Mississauga ON L4X 1L4",
    "addr:housenumber":"1456",
    "addr:postcode":"l4x 1l4",
    "addr:street":"Dundas St E",
    "iso:country":"CA",
    "sg:address":"1456 Dundas St E",
    "sg:city":"Mississauga",
    "sg:classifiers":[
        {
            "category":"Restaurant",
            "type":"Food & Drink"
        }
    ],
    "sg:phone":"+1 905 270 8866",
    "sg:postcode":"L4X 1L4",
    "sg:province":"ON",
    "wof:name":"China Buffet",
    "wof:placetype":"venue"
},
  "geometry": {"coordinates":[-79.58203125,43.6106948853],"type":"Point"}
}