{
  "type": "Feature",
  "properties": {
    "addr:full":"4556 Main St Spirit River AB T0H 3G0",
    "addr:housenumber":"4556",
    "addr:postcode":"t0h 3g0",
    "addr:street":"Main St",
    "iso:country":"CA",
    "sg:address":"4556 Main St",
    "sg:city":"Spirit River",
    "sg:classifiers":[
        {
            "category":"Personal",
            "subcategory":"Barber",
            "type":"Services"
        }
    ],
    "sg:phone":"+1 780 864 3600",
    "sg:postcode":"T0H 3G0",
    "sg:province":"AB",
    "wof:name":"Shenda's Barber Shop",
    "wof:placetype":"venue"
},
  "geometry": {"coordinates":[-118.848541,55.7813],"type":"Point"}
}