{
  "type": "Feature",
  "properties": {
    "addr:full":"370 Lower Bench Rd Penticton BC V2A 8V4",
    "addr:housenumber":"370",
    "addr:postcode":"v2a 8v4",
    "addr:street":"Lower Bench Rd",
    "iso:country":"CA",
    "sg:address":"370 Lower Bench Rd",
    "sg:city":"Penticton",
    "sg:classifiers":[
        {
            "category":"Real Estate",
            "subcategory":"Architect",
            "type":"Services"
        }
    ],
    "sg:phone":"+1 250 493 3996",
    "sg:postcode":"V2A 8V4",
    "sg:province":"BC",
    "wof:name":"Coady, Matthew J",
    "wof:placetype":"venue"
},
  "geometry": {"coordinates":[-119.574699,49.510666],"type":"Point"}
}