{
  "type": "Feature",
  "properties": {
    "addr:full":"10864 Imperial Rd Aylmer ON N5H 2R3",
    "addr:housenumber":"10864",
    "addr:postcode":"n5h 2r3",
    "addr:street":"Imperial Rd",
    "iso:country":"CA",
    "sg:address":"10864 Imperial Rd",
    "sg:city":"Aylmer",
    "sg:classifiers":[
        {
            "category":"Building & Trades",
            "subcategory":"Construction",
            "type":"Services"
        }
    ],
    "sg:phone":"+1 519 773 5294",
    "sg:postcode":"N5H 2R3",
    "sg:province":"ON",
    "sg:tags":[
        "excavating",
        "contractor"
    ],
    "wof:name":"Mark Wilson Backhoe & Truck",
    "wof:placetype":"venue"
},
  "geometry": {"coordinates":[-80.982468,42.79171],"type":"Point"}
}