{
  "type": "Feature",
  "properties": {
    "addr:full":"6670 Sooke Rd Sooke BC V0S 1N0",
    "addr:housenumber":"6670",
    "addr:postcode":"v0s 1n0",
    "addr:street":"Sooke Rd",
    "iso:country":"CA",
    "sg:address":"6670 Sooke Rd",
    "sg:city":"Sooke",
    "sg:classifiers":[
        {
            "category":"Autos & Motor Vehicles",
            "subcategory":"Fuel & Gas Station",
            "type":"Retail Goods"
        }
    ],
    "sg:phone":"+1 250 642 4541",
    "sg:postcode":"V0S 1N0",
    "sg:province":"BC",
    "sg:tags":[
        "oil"
    ],
    "wof:name":"Payless Gas",
    "wof:placetype":"venue"
},
  "geometry": {"coordinates":[-123.722267151,48.3785514832],"type":"Point"}
}