{
  "type": "Feature",
  "properties": {
    "addr:full":"Edmonton AB T5J 1M4",
    "addr:postcode":"t5j 1m4",
    "iso:country":"CA",
    "sg:city":"Edmonton",
    "sg:classifiers":[
        {
            "category":"Education",
            "subcategory":"Special Training",
            "type":"Public Place"
        }
    ],
    "sg:phone":"+1 780 424 9543",
    "sg:postcode":"T5J 1M4",
    "sg:province":"AB",
    "sg:tags":[
        "instruction",
        "driving"
    ],
    "wof:name":"Canadian Driving School",
    "wof:placetype":"venue"
},
  "geometry": {"coordinates":[-113.50865899999999,53.539268],"type":"Point"}
}