{
  "type": "Feature",
  "properties": {
    "addr:full":"Melocheville QC J0S 1J0",
    "addr:postcode":"j0s 1j0",
    "iso:country":"CA",
    "sg:city":"Melocheville",
    "sg:classifiers":[
        {
            "category":"Autos & Motor Vehicles",
            "subcategory":"Motorcycle Sales",
            "type":"Retail Goods"
        }
    ],
    "sg:phone":"+1 450 225 3500",
    "sg:postcode":"J0S 1J0",
    "sg:province":"QC",
    "sg:tags":[
        "scooter"
    ],
    "wof:name":"Motoplus",
    "wof:placetype":"venue"
},
  "geometry": {"coordinates":[-73.964127,45.313763],"type":"Point"}
}