{
  "type": "Feature",
  "properties": {
    "iso:country":"CA",
    "sg:address":"416 Monarch Crt",
    "sg:city":"Kamloops",
    "sg:classifiers":[
        {
            "category":"Building & Trades",
            "subcategory":"Construction",
            "type":"Services"
        }
    ],
    "sg:phone":"+1 250 372 5644",
    "sg:postcode":"V2E 2A1",
    "sg:province":"BC",
    "sg:tags":[
        "general",
        "contractor"
    ],
    "wof:name":"S W Cousins Construction Ltd",
    "wof:placetype":"venue"
},
  "geometry": {"coordinates":[-120.348885,50.65321],"type":"Point"}
}