{
  "type": "Feature",
  "properties": {
    "addr:full":"Barwick ON P0W 1A0",
    "addr:postcode":"p0w 1a0",
    "iso:country":"CA",
    "sg:city":"Barwick",
    "sg:classifiers":[
        {
            "category":"Recreation",
            "type":"Entertainment"
        }
    ],
    "sg:phone":"+1 807 487 2505",
    "sg:postcode":"P0W 1A0",
    "sg:province":"ON",
    "sg:tags":[
        "hall",
        "auditorium"
    ],
    "wof:name":"Barwick Curling Club",
    "wof:placetype":"venue"
},
  "geometry": {"coordinates":[-93.98854064939999,48.6488494873],"type":"Point"}
}