{
  "type": "Feature",
  "properties": {
    "addr:full":"2921 Tammy Dr Port Colborne ON L3K 5V3",
    "addr:housenumber":"2921",
    "addr:postcode":"l3k 5v3",
    "addr:street":"Tammy Dr",
    "iso:country":"CA",
    "sg:address":"2921 Tammy Dr",
    "sg:city":"Port Colborne",
    "sg:classifiers":[
        {
            "category":"Retail",
            "subcategory":"Portrait Studio",
            "type":"Services"
        }
    ],
    "sg:phone":"+1 905 835 2206",
    "sg:postcode":"L3K 5V3",
    "sg:province":"ON",
    "sg:tags":[
        "photographer"
    ],
    "wof:name":"Photography By Sue Petri",
    "wof:placetype":"venue"
},
  "geometry": {"coordinates":[-79.174606,42.886089],"type":"Point"}
}