{
  "type": "Feature",
  "properties": {
    "addr:full":"Saint-Etienne-Des-Gres QC G0X 2P0",
    "addr:postcode":"g0x 2p0",
    "iso:country":"CA",
    "sg:city":"Saint-Etienne-Des-Gres",
    "sg:classifiers":[
        {
            "category":"Retail",
            "subcategory":"Animal Services",
            "type":"Services"
        }
    ],
    "sg:phone":"+1 819 535 5100",
    "sg:postcode":"G0X 2P0",
    "sg:province":"QC",
    "sg:tags":[
        "pet",
        "training"
    ],
    "wof:name":"Auberge Des Quat Pat",
    "wof:placetype":"venue"
},
  "geometry": {"coordinates":[-72.7750015259,46.4415397644],"type":"Point"}
}