{
  "type": "Feature",
  "properties": {
    "addr:full":"63 Moore St South Porcupine ON P0N 1H0",
    "addr:housenumber":"63",
    "addr:postcode":"p0n 1h0",
    "addr:street":"Moore St",
    "iso:country":"CA",
    "sg:address":"63 Moore St",
    "sg:city":"South Porcupine",
    "sg:classifiers":[
        {
            "category":"Professional",
            "subcategory":"Accounting & Tax Preparation",
            "type":"Services"
        }
    ],
    "sg:phone":"+1 705 235 5166",
    "sg:postcode":"P0N 1H0",
    "sg:province":"ON",
    "sg:tags":[
        "return",
        "filing"
    ],
    "wof:name":"Rta Accounting Svc",
    "wof:placetype":"venue"
},
  "geometry": {"coordinates":[-81.2130661011,48.4786109924],"type":"Point"}
}