{
  "type": "Feature",
  "properties": {
    "addr:full":"507 17 Ave SW Calgary AB T2S 0A9",
    "addr:postcode":"t2s 0a9",
    "addr:street":"507 17 Ave Sw",
    "iso:country":"CA",
    "sg:address":"507 17 Ave SW",
    "sg:city":"Calgary",
    "sg:classifiers":[
        {
            "category":"Restaurant",
            "type":"Food & Drink"
        }
    ],
    "sg:phone":"+1 403 244 2294",
    "sg:postcode":"T2S 0A9",
    "sg:province":"AB",
    "wof:name":"Kashmir",
    "wof:placetype":"venue"
},
  "geometry": {"coordinates":[-114.071915,51.037685],"type":"Point"}
}