{
  "type": "Feature",
  "properties": {
    "addr:full":"10422 Boul Gouin O Roxboro QC H8Y 1W4",
    "addr:housenumber":"10422",
    "addr:postcode":"h8y 1w4",
    "addr:street":"Boul Gouin O",
    "iso:country":"CA",
    "sg:address":"10422 Boul Gouin O",
    "sg:city":"Roxboro",
    "sg:classifiers":[
        {
            "category":"Retail",
            "subcategory":"Auto Repair",
            "type":"Services"
        }
    ],
    "sg:phone":"+1 514 683 6912",
    "sg:postcode":"H8Y 1W4",
    "sg:province":"QC",
    "sg:tags":[
        "repairing",
        "automobile"
    ],
    "wof:name":"Luidgi Service Station",
    "wof:placetype":"venue"
},
  "geometry": {"coordinates":[-73.8064956665,45.5107498169],"type":"Point"}
}