{
  "type": "Feature",
  "properties": {
    "addr:full":"888 Av Bourdages N Saint-Hyacinthe QC J2S 5N9",
    "addr:postcode":"j2s 5n9",
    "addr:street":"888 Av Bourdages N",
    "iso:country":"CA",
    "sg:address":"888 Av Bourdages N",
    "sg:city":"Saint-Hyacinthe",
    "sg:classifiers":[
        {
            "category":"Professional",
            "subcategory":"Management & Consulting",
            "type":"Services"
        }
    ],
    "sg:phone":"+1 450 774 3343",
    "sg:postcode":"J2S 5N9",
    "sg:province":"QC",
    "sg:tags":[
        "agricultural",
        "consultant"
    ],
    "wof:name":"Daniel Labbe Agronome",
    "wof:placetype":"venue"
},
  "geometry": {"coordinates":[-72.950935,45.624256],"type":"Point"}
}