{
  "type": "Feature",
  "properties": {
    "iso:country":"CA",
    "sg:address":"4712 Eastwood Cres",
    "sg:city":"Niagara Falls",
    "sg:classifiers":[
        {
            "category":"Shopping",
            "subcategory":"Luggage & Leather Goods",
            "type":"Retail Goods"
        }
    ],
    "sg:phone":"+1 905 371 3756",
    "sg:postcode":"L2E 1B5",
    "sg:province":"ON",
    "wof:name":"Show Flex Intl Inc",
    "wof:placetype":"venue"
},
  "geometry": {"coordinates":[-79.07176971440001,43.0970573425],"type":"Point"}
}