{
  "type": "Feature",
  "properties": {
    "addr:full":"225 Charlotte St Sydney NS B1P 1C4",
    "addr:housenumber":"225",
    "addr:postcode":"b1p 1c4",
    "addr:street":"Charlotte St",
    "iso:country":"CA",
    "sg:address":"225 Charlotte St",
    "sg:city":"Sydney",
    "sg:classifiers":[
        {
            "category":"Professional",
            "subcategory":"Computer Services",
            "type":"Services"
        }
    ],
    "sg:phone":"+1 902 562 3202",
    "sg:postcode":"B1P 1C4",
    "sg:province":"NS",
    "wof:name":"A G Research",
    "wof:placetype":"venue"
},
  "geometry": {"coordinates":[-60.195034,46.139828],"type":"Point"}
}