{
  "type": "Feature",
  "properties": {
    "addr:full":"5492 Rue DE San-Remo Saint-Leonard QC H1P 2W9",
    "addr:housenumber":"5492",
    "addr:postcode":"h1p 2w9",
    "addr:street":"Rue De San-Remo",
    "iso:country":"CA",
    "sg:address":"5492 Rue DE San-Remo",
    "sg:city":"Saint-Leonard",
    "sg:classifiers":[
        {
            "category":"Professional",
            "subcategory":"Accounting & Tax Preparation",
            "type":"Services"
        }
    ],
    "sg:phone":"+1 514 930 5818",
    "sg:postcode":"H1P 2W9",
    "sg:province":"QC",
    "sg:tags":[
        "return",
        "filing"
    ],
    "wof:name":"Bureau Mobile",
    "wof:placetype":"venue"
},
  "geometry": {"coordinates":[-73.588821,45.584396],"type":"Point"}
}