{
  "type": "Feature",
  "properties": {
    "addr:full":"195 Rang DE LA Barbotte Lacolle QC J0J 1J0",
    "addr:housenumber":"195",
    "addr:postcode":"j0j 1j0",
    "addr:street":"Rang De La Barbotte",
    "iso:country":"CA",
    "sg:address":"195 Rang DE LA Barbotte",
    "sg:city":"Lacolle",
    "sg:classifiers":[
        {
            "category":"Recreation",
            "subcategory":"Marina",
            "type":"Entertainment"
        }
    ],
    "sg:phone":"+1 450 246 2144",
    "sg:postcode":"J0J 1J0",
    "sg:province":"QC",
    "sg:tags":[
        "repairing",
        "boat"
    ],
    "wof:name":"Marina Le Sieur DE Champlain",
    "wof:placetype":"venue"
},
  "geometry": {"coordinates":[-73.352272,45.028381],"type":"Point"}
}