{
  "type": "Feature",
  "properties": {
    "addr:full":"666 Rue Principale Casselman ON K0A 1M0",
    "addr:housenumber":"666",
    "addr:postcode":"k0a 1m0",
    "addr:street":"Rue Principale",
    "iso:country":"CA",
    "sg:address":"666 Rue Principale",
    "sg:city":"Casselman",
    "sg:classifiers":[
        {
            "category":"Building & Trades",
            "subcategory":"Construction",
            "type":"Services"
        }
    ],
    "sg:phone":"+1 613 764 2803",
    "sg:postcode":"K0A 1M0",
    "sg:province":"ON",
    "sg:tags":[
        "excavating",
        "contractor"
    ],
    "wof:name":"Claude Gagne Construction Ltee",
    "wof:placetype":"venue"
},
  "geometry": {"coordinates":[-75.0833206177,45.308681488],"type":"Point"}
}