{
  "type": "Feature",
  "properties": {
    "addr:full":"552 Darlington Dr Dalhousie NB E8C 1N1",
    "addr:housenumber":"552",
    "addr:postcode":"e8c 1n1",
    "addr:street":"Darlington Dr",
    "iso:country":"CA",
    "sg:address":"552 Darlington Dr",
    "sg:city":"Dalhousie",
    "sg:classifiers":[
        {
            "category":"Personal",
            "type":"Services"
        }
    ],
    "sg:phone":"+1 506 684 4331",
    "sg:postcode":"E8C 1N1",
    "sg:province":"NB",
    "sg:tags":[
        "therapist",
        "massage"
    ],
    "wof:name":"Alice Fournier Massotherapeute",
    "wof:placetype":"venue"
},
  "geometry": {"coordinates":[-66.402458,48.039993],"type":"Point"}
}