{
  "type": "Feature",
  "properties": {
    "addr:full":"25772 116 Ave Maple Ridge BC V4R 1Z6",
    "addr:housenumber":"25772",
    "addr:postcode":"bc v4r 1z6",
    "addr:street":"116 Ave",
    "iso:country":"CA",
    "sg:address":"25772 116 Ave",
    "sg:city":"Maple Ridge",
    "sg:classifiers":[
        {
            "category":"Wholesale",
            "subcategory":"Office Equipment",
            "type":"Manufacturing & Wholesale Goods"
        }
    ],
    "sg:phone":"+1 604 466 5507",
    "sg:postcode":"V4R 1Z6",
    "sg:province":"BC",
    "sg:tags":[
        "accounting",
        "bookkeeping",
        "system",
        "general"
    ],
    "wof:name":"Infotech Consulting Inc",
    "wof:placetype":"venue"
},
  "geometry": {"coordinates":[-122.507545471,49.2129516602],"type":"Point"}
}