{
  "type": "Feature",
  "properties": {
    "iso:country":"CA",
    "sg:address":"176 Vidal St S #202",
    "sg:city":"Sarnia",
    "sg:classifiers":[
        {
            "category":"Real Estate",
            "subcategory":"Real Estate Operator",
            "type":"Services"
        }
    ],
    "sg:phone":"+1 519 339 1011",
    "sg:postcode":"N7T 2T6",
    "sg:province":"ON",
    "sg:tags":[
        "apartment"
    ],
    "wof:name":"Riverview Towers",
    "wof:placetype":"venue"
},
  "geometry": {"coordinates":[-82.4058,42.967754],"type":"Point"}
}