{
  "type": "Feature",
  "properties": {
    "iso:country":"CA",
    "sg:address":"40 Rue Maurice",
    "sg:city":"Saint-Remi",
    "sg:classifiers":[
        {
            "category":"Professional",
            "subcategory":"Business Services",
            "type":"Services"
        }
    ],
    "sg:phone":"+1 450 454 4841",
    "sg:postcode":"J0L 2L0",
    "sg:province":"QC",
    "sg:tags":[
        "notary"
    ],
    "wof:name":"Legare, Robert",
    "wof:placetype":"venue"
},
  "geometry": {"coordinates":[-73.61251831049999,45.2636375427],"type":"Point"}
}