{
  "type": "Feature",
  "properties": {
    "addr:full":"235 Somerset St Saint John NB E2K 2Y1",
    "addr:housenumber":"235",
    "addr:postcode":"e2k 2y1",
    "addr:street":"Somerset St",
    "iso:country":"CA",
    "sg:address":"235 Somerset St",
    "sg:city":"Saint John",
    "sg:classifiers":[
        {
            "category":"Health Services",
            "subcategory":"Doctor",
            "type":"Services"
        }
    ],
    "sg:phone":"+1 506 634 1848",
    "sg:postcode":"E2K 2Y1",
    "sg:province":"NB",
    "sg:tags":[
        "physician",
        "surgeon"
    ],
    "wof:name":"Reardon, Edward P MD",
    "wof:placetype":"venue"
},
  "geometry": {"coordinates":[-66.073547,45.28392],"type":"Point"}
}