{
  "type": "Feature",
  "properties": {
    "addr:full":"4619 Rue Saint-Denis Montreal QC H2J 2L4",
    "addr:housenumber":"4619",
    "addr:postcode":"h2j 2l4",
    "addr:street":"Rue Saint-Denis",
    "iso:country":"CA",
    "sg:address":"4619 Rue Saint-Denis",
    "sg:city":"Montreal",
    "sg:classifiers":[
        {
            "category":"Health Services",
            "subcategory":"Doctor",
            "type":"Services"
        }
    ],
    "sg:phone":"+1 514 847 7777",
    "sg:postcode":"H2J 2L4",
    "sg:province":"QC",
    "sg:tags":[
        "clinic",
        "chiropractor"
    ],
    "wof:name":"Clinique Chiropratique Action",
    "wof:placetype":"venue"
},
  "geometry": {"coordinates":[-73.5841217041,45.5246772766],"type":"Point"}
}