{
  "type": "Feature",
  "properties": {
    "addr:full":"905 Victoria Ave E Thunder Bay ON P7C 1B3",
    "addr:housenumber":"905",
    "addr:postcode":"p7c 1b3",
    "addr:street":"Victoria Ave E",
    "iso:country":"CA",
    "sg:address":"905 Victoria Ave E",
    "sg:city":"Thunder Bay",
    "sg:classifiers":[
        {
            "category":"Health Services",
            "subcategory":"Hospital",
            "type":"Services"
        }
    ],
    "sg:phone":"+1 807 626 1801",
    "sg:postcode":"P7C 1B3",
    "sg:province":"ON",
    "sg:tags":[
        "mental"
    ],
    "wof:name":"Assertive Community Treatment",
    "wof:placetype":"venue"
},
  "geometry": {"coordinates":[-89.250092,48.38427],"type":"Point"}
}