{
  "type": "Feature",
  "properties": {
    "iso:country":"CA",
    "sg:address":"449 Main St",
    "sg:city":"Winchester",
    "sg:classifiers":[
        {
            "category":"Professional",
            "subcategory":"Accounting & Tax Preparation",
            "type":"Services"
        }
    ],
    "sg:phone":"+1 613 821 3436",
    "sg:postcode":"K0C 2K0",
    "sg:province":"ON",
    "sg:tags":[
        "return",
        "filing"
    ],
    "wof:name":"Jmp Business Svc Ltd",
    "wof:placetype":"venue"
},
  "geometry": {"coordinates":[-75.3497085571,45.0942306519],"type":"Point"}
}