{
  "type": "Feature",
  "properties": {
    "iso:country":"CA",
    "sg:address":"4785 Rue Baillargeon",
    "sg:city":"Saint-Hubert",
    "sg:classifiers":[
        {
            "category":"Retail",
            "subcategory":"Portrait Studio",
            "type":"Services"
        }
    ],
    "sg:phone":"+1 514 485 8512",
    "sg:postcode":"J3Y 2A5",
    "sg:province":"QC",
    "sg:tags":[
        "photographer"
    ],
    "wof:name":"Photographie Harold H Perlman",
    "wof:placetype":"venue"
},
  "geometry": {"coordinates":[-73.43635559080001,45.4833946228],"type":"Point"}
}