{
  "type": "Feature",
  "properties": {
    "iso:country":"CA",
    "sg:city":"Ottawa",
    "sg:classifiers":[
        {
            "category":"Manufacturing",
            "subcategory":"Wood Products",
            "type":"Manufacturing & Wholesale Goods"
        }
    ],
    "sg:phone":"+1 613 563 4080",
    "sg:postcode":"K1R 6K7",
    "sg:province":"ON",
    "sg:tags":[
        "picture",
        "lamination"
    ],
    "wof:name":"Display Laminating",
    "wof:placetype":"venue"
},
  "geometry": {"coordinates":[-75.717537,45.410683],"type":"Point"}
}