{
  "type": "Feature",
  "properties": {
    "addr:full":"212 Millway Ave Concord ON L4K 3W4",
    "addr:housenumber":"212",
    "addr:postcode":"l4k 3w4",
    "addr:street":"Millway Ave",
    "iso:country":"CA",
    "sg:address":"212 Millway Ave",
    "sg:city":"Concord",
    "sg:classifiers":[
        {
            "category":"Manufacturing",
            "subcategory":"Lumber",
            "type":"Manufacturing & Wholesale Goods"
        }
    ],
    "sg:phone":"+1 905 738 7900",
    "sg:postcode":"L4K 3W4",
    "sg:province":"ON",
    "sg:tags":[
        "frame",
        "furniture"
    ],
    "wof:name":"Superior Frames",
    "wof:placetype":"venue"
},
  "geometry": {"coordinates":[-79.528183,43.799309],"type":"Point"}
}