{
  "type": "Feature",
  "properties": {
    "addr:full":"3400 Institute Rd North Vancouver BC V7K 2K9",
    "addr:postcode":"3400;v7k 2k9",
    "addr:street":"Institute Rd",
    "iso:country":"CA",
    "sg:address":"3400 Institute Rd",
    "sg:city":"North Vancouver",
    "sg:classifiers":[
        {
            "category":"Organizations",
            "subcategory":"Religious Organization",
            "type":"Services"
        }
    ],
    "sg:phone":"+1 604 988 4418",
    "sg:postcode":"V7K 2K9",
    "sg:province":"BC",
    "sg:tags":[
        "church"
    ],
    "wof:name":"St Clement's Anglican Church",
    "wof:placetype":"venue"
},
  "geometry": {"coordinates":[-123.036636,49.339718],"type":"Point"}
}