{
  "type": "Feature",
  "properties": {
    "addr:full":"202 Boul Pabos Pabos QC G0C 2H0",
    "addr:housenumber":"202",
    "addr:postcode":"g0c 2h0",
    "addr:street":"Boul Pabos Pabos",
    "iso:country":"CA",
    "sg:address":"202 Boul Pabos",
    "sg:city":"Pabos",
    "sg:classifiers":[
        {
            "category":"Food & Beverages",
            "subcategory":"Meat & Fish",
            "type":"Retail Goods"
        }
    ],
    "sg:phone":"+1 418 689 3564",
    "sg:postcode":"G0C 2H0",
    "sg:province":"QC",
    "sg:tags":[
        "seafood"
    ],
    "wof:name":"Marche Blais",
    "wof:placetype":"venue"
},
  "geometry": {"coordinates":[-64.63736,48.356384],"type":"Point"}
}