{
  "type": "Feature",
  "properties": {
    "addr:full":"224 Westmorland Rd Saint John NB E2J 2E7",
    "addr:housenumber":"224",
    "addr:postcode":"e2j 2e7",
    "addr:street":"Westmorland Rd",
    "iso:country":"CA",
    "sg:address":"224 Westmorland Rd",
    "sg:city":"Saint John",
    "sg:classifiers":[
        {
            "category":"Shopping",
            "type":"Retail Goods"
        }
    ],
    "sg:phone":"+1 506 652 4350",
    "sg:postcode":"E2J 2E7",
    "sg:province":"NB",
    "sg:tags":[
        "monument"
    ],
    "wof:name":"Nelson Monuments Ltd",
    "wof:placetype":"venue"
},
  "geometry": {"coordinates":[-66.032585,45.295612],"type":"Point"}
}