{
  "type": "Feature",
  "properties": {
    "iso:country":"CA",
    "sg:address":"725 Rue Du Pomp",
    "sg:city":"Saint-Lambert-DE-Lauzon",
    "sg:classifiers":[
        {
            "category":"Manufacturing",
            "subcategory":"Tools & Machinery",
            "type":"Manufacturing & Wholesale Goods"
        }
    ],
    "sg:phone":"+1 418 889 8840",
    "sg:postcode":"G0S 2W0",
    "sg:province":"QC",
    "sg:tags":[
        "equipment",
        "system",
        "automation"
    ],
    "wof:name":"Fhb Electronique Inc",
    "wof:placetype":"venue"
},
  "geometry": {"coordinates":[-71.2111587524,46.5876846313],"type":"Point"}
}