{
  "type": "Feature",
  "properties": {
    "iso:country":"CA",
    "sg:address":"4250 Lakeshore Rd",
    "sg:city":"Burlington",
    "sg:classifiers":[
        {
            "category":"Recreation",
            "type":"Entertainment"
        }
    ],
    "sg:phone":"+1 905 632 7809",
    "sg:postcode":"L7L 1A6",
    "sg:province":"ON",
    "sg:tags":[
        "provincial",
        "hall",
        "parks",
        "auditorium"
    ],
    "wof:name":"Paletta Lakefront Park",
    "wof:placetype":"venue"
},
  "geometry": {"coordinates":[-79.75434112550001,43.3534889221],"type":"Point"}
}