{
  "type": "Feature",
  "properties": {
    "iso:country":"CA",
    "sg:address":"2016 Boul Rene-Gaultier",
    "sg:city":"Varennes",
    "sg:classifiers":[
        {
            "category":"Government",
            "subcategory":"Office",
            "type":"Public Place"
        }
    ],
    "sg:phone":"+1 450 652 2624",
    "sg:postcode":"J3X 1E9",
    "sg:province":"QC",
    "sg:tags":[
        "village"
    ],
    "wof:name":"Varennes Service Des Loisirs",
    "wof:placetype":"venue"
},
  "geometry": {"coordinates":[-73.433868,45.677258],"type":"Point"}
}