{
  "type": "Feature",
  "properties": {
    "addr:full":"1802 Av John-Kane LA Baie QC G7B 1K2",
    "addr:housenumber":"1802",
    "addr:postcode":"g7b 1k2",
    "addr:street":"Av John-Kane",
    "iso:country":"CA",
    "sg:address":"1802 Av John-Kane",
    "sg:city":"LA Baie",
    "sg:classifiers":[
        {
            "category":"Education",
            "subcategory":"School",
            "type":"Public Place"
        }
    ],
    "sg:phone":"+1 418 544 2843",
    "sg:postcode":"G7B 1K2",
    "sg:province":"QC",
    "wof:name":"Ecole Secondaire Polyvalente",
    "wof:placetype":"venue"
},
  "geometry": {"coordinates":[-70.88344600000001,48.323025],"type":"Point"}
}