{
  "type": "Feature",
  "properties": {
    "iso:country":"CA",
    "sg:address":"6262 S Ford St",
    "sg:city":"Stellarton",
    "sg:classifiers":[
        {
            "category":"Retail",
            "subcategory":"Auto Rental",
            "type":"Services"
        }
    ],
    "sg:phone":"+1 902 752 9400",
    "sg:postcode":"B0K 1S0",
    "sg:province":"NS",
    "sg:tags":[
        "renting",
        "truck",
        "leasing"
    ],
    "wof:name":"U-Haul CO Ltd",
    "wof:placetype":"venue"
},
  "geometry": {"coordinates":[-62.660465,45.556454],"type":"Point"}
}