{
  "type": "Feature",
  "properties": {
    "iso:country":"CA",
    "sg:address":"60 Main St",
    "sg:city":"Petitcodiac",
    "sg:classifiers":[
        {
            "category":"Wholesale",
            "subcategory":"Scrap",
            "type":"Manufacturing & Wholesale Goods"
        }
    ],
    "sg:phone":"+1 506 756 8525",
    "sg:postcode":"E4Z 4M3",
    "sg:province":"NB",
    "sg:tags":[
        "recycling",
        "center"
    ],
    "wof:name":"Petty Redemption Ctr",
    "wof:placetype":"venue"
},
  "geometry": {"coordinates":[-65.1773757935,45.9298744202],"type":"Point"}
}