{
  "type": "Feature",
  "properties": {
    "addr:full":"23 Bellerose Dr St Albert AB T8N 5E1",
    "addr:housenumber":"23",
    "addr:postcode":"t8n 5e1",
    "addr:street":"Bellerose Dr",
    "iso:country":"CA",
    "sg:address":"23 Bellerose Dr",
    "sg:city":"St Albert",
    "sg:classifiers":[
        {
            "category":"Building & Trades",
            "subcategory":"Construction",
            "type":"Services"
        }
    ],
    "sg:phone":"+1 780 459 6611",
    "sg:postcode":"T8N 5E1",
    "sg:province":"AB",
    "sg:tags":[
        "paving",
        "contractor"
    ],
    "wof:name":"Standard General Inc",
    "wof:placetype":"venue"
},
  "geometry": {"coordinates":[-113.621994,53.64632],"type":"Point"}
}