{
  "type": "Feature",
  "properties": {
    "addr:full":"511 Danforth Ave Toronto ON M4K 1P5",
    "addr:housenumber":"511",
    "addr:postcode":"m4k 1p5",
    "addr:street":"Danforth Ave",
    "iso:country":"CA",
    "sg:address":"511 Danforth Ave",
    "sg:city":"Toronto",
    "sg:classifiers":[
        {
            "category":"Home & Garden",
            "subcategory":"Home Furnishings",
            "type":"Retail Goods"
        }
    ],
    "sg:phone":"+1 416 461 4663",
    "sg:postcode":"M4K 1P5",
    "sg:province":"ON",
    "sg:tags":[
        "housewares"
    ],
    "wof:name":"Romancing the Home",
    "wof:placetype":"venue"
},
  "geometry": {"coordinates":[-79.348739624,43.6780166626],"type":"Point"}
}