{
  "type": "Feature",
  "properties": {
    "addr:full":"Toronto ON M6K 3K9",
    "addr:postcode":"m6k 3k9",
    "iso:country":"CA",
    "sg:city":"Toronto",
    "sg:classifiers":[
        {
            "category":"Professional",
            "subcategory":"Computer Services",
            "type":"Services"
        }
    ],
    "sg:phone":"+1 416 535 2414",
    "sg:postcode":"M6K 3K9",
    "sg:province":"ON",
    "sg:tags":[
        "internet"
    ],
    "wof:name":"Snap Media Corp",
    "wof:placetype":"venue"
},
  "geometry": {"coordinates":[-79.42589599999999,43.638367],"type":"Point"}
}