{
  "type": "Feature",
  "properties": {
    "addr:full":"2875 Rue Hochelaga Montreal QC H2K 1K7",
    "addr:housenumber":"2875",
    "addr:postcode":"h2k 1k7",
    "addr:street":"Rue Hochelaga",
    "iso:country":"CA",
    "sg:address":"2875 Rue Hochelaga",
    "sg:city":"Montreal",
    "sg:classifiers":[
        {
            "category":"Wholesale",
            "subcategory":"Auto Parts",
            "type":"Manufacturing & Wholesale Goods"
        }
    ],
    "sg:phone":"+1 514 524 7603",
    "sg:postcode":"H2K 1K7",
    "sg:province":"QC",
    "sg:tags":[
        "automobile",
        "rebuilt"
    ],
    "wof:name":"Coco Gmcl Pieces D'Auto Enr",
    "wof:placetype":"venue"
},
  "geometry": {"coordinates":[-73.556488,45.538895],"type":"Point"}
}