{
  "type": "Feature",
  "properties": {
    "iso:country":"CA",
    "sg:address":"195 Rue Scaron",
    "sg:city":"Laval",
    "sg:classifiers":[
        {
            "category":"Building & Trades",
            "subcategory":"Construction",
            "type":"Services"
        }
    ],
    "sg:phone":"+1 450 628 0146",
    "sg:postcode":"H7H 1J6",
    "sg:province":"QC",
    "sg:tags":[
        "roofing",
        "contractor"
    ],
    "wof:name":"Couvreur Denis Courville Inc",
    "wof:placetype":"venue"
},
  "geometry": {"coordinates":[-73.7572937012,45.6343688965],"type":"Point"}
}