{
  "type": "Feature",
  "properties": {
    "addr:full":"1557 Kingston Rd Scarborough ON M1N 1R9",
    "addr:housenumber":"1557",
    "addr:postcode":"m1n 1r9",
    "addr:street":"Kingston Rd",
    "iso:country":"CA",
    "sg:address":"1557 Kingston Rd",
    "sg:city":"Scarborough",
    "sg:classifiers":[
        {
            "category":"Professional",
            "subcategory":"Research",
            "type":"Services"
        }
    ],
    "sg:phone":"+1 416 690 7729",
    "sg:postcode":"M1N 1R9",
    "sg:province":"ON",
    "sg:tags":[
        "market",
        "analysis"
    ],
    "wof:name":"Sunray Media Inc",
    "wof:placetype":"venue"
},
  "geometry": {"coordinates":[-79.267563,43.689793],"type":"Point"}
}