{
  "type": "Feature",
  "properties": {
    "addr:full":"120 Hawthorne Rd London ON N6G 2W8",
    "addr:housenumber":"120",
    "addr:postcode":"n6g 2w8",
    "addr:street":"Hawthorne Rd",
    "iso:country":"CA",
    "sg:address":"120 Hawthorne Rd",
    "sg:city":"London",
    "sg:classifiers":[
        {
            "category":"Communications",
            "subcategory":"Film & Video Production",
            "type":"Services"
        }
    ],
    "sg:phone":"+1 519 438 9053",
    "sg:postcode":"N6G 2W8",
    "sg:province":"ON",
    "sg:tags":[
        "taping"
    ],
    "wof:name":"Raemer Video Productions",
    "wof:placetype":"venue"
},
  "geometry": {"coordinates":[-81.3181152344,43.0074272156],"type":"Point"}
}