{
  "type": "Feature",
  "properties": {
    "addr:full":"Laval QC H7T 2J7",
    "addr:postcode":"h7t 2j7",
    "iso:country":"CA",
    "sg:city":"Laval",
    "sg:classifiers":[
        {
            "category":"Professional",
            "subcategory":"Accounting & Tax Preparation",
            "type":"Services"
        }
    ],
    "sg:phone":"+1 514 745 2900",
    "sg:postcode":"H7T 2J7",
    "sg:province":"QC",
    "sg:tags":[
        "accountant"
    ],
    "wof:name":"Henaire Danis Brunet",
    "wof:placetype":"venue"
},
  "geometry": {"coordinates":[-73.7520904541,45.5663795471],"type":"Point"}
}