{
  "type": "Feature",
  "properties": {
    "addr:full":"Vancouver BC V6C 3K4",
    "addr:postcode":"v6c 3k4",
    "iso:country":"CA",
    "sg:city":"Vancouver",
    "sg:classifiers":[
        {
            "category":"Banks & Credit Unions",
            "subcategory":"Investment Brokerage",
            "type":"Services"
        }
    ],
    "sg:phone":"+1 604 654 3783",
    "sg:postcode":"V6C 3K4",
    "sg:province":"BC",
    "sg:tags":[
        "stock",
        "broker",
        "bond"
    ],
    "wof:name":"Td Waterhouse",
    "wof:placetype":"venue"
},
  "geometry": {"coordinates":[-123.118202,49.28466],"type":"Point"}
}