{
  "type": "Feature",
  "properties": {
    "iso:country":"CA",
    "sg:address":"Main St",
    "sg:city":"New Denver",
    "sg:classifiers":[
        {
            "category":"Shopping",
            "subcategory":"Gifts & Souvenirs",
            "type":"Retail Goods"
        }
    ],
    "sg:phone":"+1 250 358 2142",
    "sg:postcode":"V0G 1S0",
    "sg:province":"BC",
    "sg:tags":[
        "shop"
    ],
    "wof:name":"Prospector's Pick",
    "wof:placetype":"venue"
},
  "geometry": {"coordinates":[-117.37213897700001,49.991973877],"type":"Point"}
}