{
  "type": "Feature",
  "properties": {
    "addr:full":"201 Rue Elizabeth Sorel-Tracy QC J3P 4H7",
    "addr:housenumber":"201",
    "addr:postcode":"j3p 4h7",
    "addr:street":"Rue Elizabeth",
    "iso:country":"CA",
    "sg:address":"201 Rue Elizabeth",
    "sg:city":"Sorel-Tracy",
    "sg:classifiers":[
        {
            "category":"Recreation",
            "type":"Entertainment"
        }
    ],
    "sg:phone":"+1 450 743 5431",
    "sg:postcode":"J3P 4H7",
    "sg:province":"QC",
    "sg:tags":[
        "center",
        "government"
    ],
    "wof:name":"St Joseph DE Sorel Local Du 3",
    "wof:placetype":"venue"
},
  "geometry": {"coordinates":[-73.11042,46.039646],"type":"Point"}
}