{
  "type": "Feature",
  "properties": {
    "addr:full":"460 Rue Saint-Charles O Longueuil QC J4H 1G4",
    "addr:housenumber":"460",
    "addr:postcode":"j4h 1g4",
    "addr:street":"Rue Saint-Charles O",
    "iso:country":"CA",
    "sg:address":"460 Rue Saint-Charles O",
    "sg:city":"Longueuil",
    "sg:classifiers":[
        {
            "category":"Professional",
            "subcategory":"Business Services",
            "type":"Services"
        }
    ],
    "sg:phone":"+1 450 670 5111",
    "sg:postcode":"J4H 1G4",
    "sg:province":"QC",
    "sg:tags":[
        "notary"
    ],
    "wof:name":"Gervais, Lomer",
    "wof:placetype":"venue"
},
  "geometry": {"coordinates":[-73.50353200000001,45.545719],"type":"Point"}
}