{
  "type": "Feature",
  "properties": {
    "addr:full":"80 Spadina Ave # 309 Toronto ON M5V 2J4",
    "addr:housenumber":"80",
    "addr:postcode":"m5v 2j4",
    "addr:street":"Spadina Ave # 309",
    "iso:country":"CA",
    "sg:address":"80 Spadina Ave # 309",
    "sg:city":"Toronto",
    "sg:classifiers":[
        {
            "category":"Shopping",
            "type":"Retail Goods"
        }
    ],
    "sg:phone":"+1 416 961 0511",
    "sg:postcode":"M5V 2J4",
    "sg:province":"ON",
    "sg:tags":[
        "art",
        "gallery",
        "dealer"
    ],
    "wof:name":"Dorset Fine Arts",
    "wof:placetype":"venue"
},
  "geometry": {"coordinates":[-79.395447,43.645809],"type":"Point"}
}