{
  "type": "Feature",
  "properties": {
    "addr:full":"Stellarton NS B0K 1S0",
    "addr:postcode":"b0k 1s0",
    "iso:country":"CA",
    "sg:city":"Stellarton",
    "sg:classifiers":[
        {
            "category":"Food & Beverages",
            "subcategory":"Groceries & Convenience Stores",
            "type":"Retail Goods"
        }
    ],
    "sg:phone":"+1 902 755 1830",
    "sg:postcode":"B0K 1S0",
    "sg:province":"NS",
    "sg:tags":[
        "grocer"
    ],
    "wof:name":"Sobeys Inc",
    "wof:placetype":"venue"
},
  "geometry": {"coordinates":[-62.6604652405,45.5564537048],"type":"Point"}
}