{
  "type": "Feature",
  "properties": {
    "addr:full":"178 Rue DE LA Montagne Lac-Des-Ecorces QC J0W 1H0",
    "addr:housenumber":"178",
    "addr:postcode":"j0w 1h0",
    "addr:street":"Rue De La Montagne Lac-Des-Ecorces",
    "iso:country":"CA",
    "sg:address":"178 Rue DE LA Montagne",
    "sg:city":"Lac-Des-Ecorces",
    "sg:classifiers":[
        {
            "category":"Shopping",
            "subcategory":"Bicycles & Sporting Goods",
            "type":"Retail Goods"
        }
    ],
    "sg:phone":"+1 819 585 3472",
    "sg:postcode":"J0W 1H0",
    "sg:province":"QC",
    "sg:tags":[
        "equipment",
        "diver",
        "supply"
    ],
    "wof:name":"Centre DE Plongee Sous-Marine",
    "wof:placetype":"venue"
},
  "geometry": {"coordinates":[-75.36277800000001,46.555313],"type":"Point"}
}