{
  "type": "Feature",
  "properties": {
    "addr:full":"182 Av DE LA Fabrique Montmagny QC G5V 2J8",
    "addr:postcode":"g5v 2j8",
    "addr:street":"182 Av De La Fabrique",
    "iso:country":"CA",
    "sg:address":"182 Av DE LA Fabrique",
    "sg:city":"Montmagny",
    "sg:classifiers":[
        {
            "category":"Banks & Credit Unions",
            "subcategory":"Bank",
            "type":"Services"
        }
    ],
    "sg:phone":"+1 418 248 7084",
    "sg:postcode":"G5V 2J8",
    "sg:province":"QC",
    "wof:name":"Caisses Desjardins",
    "wof:placetype":"venue"
},
  "geometry": {"coordinates":[-70.55413799999999,46.979324],"type":"Point"}
}