{
  "type": "Feature",
  "properties": {
    "addr:full":"222 Rue Principale Frampton QC G0R 1M0",
    "addr:housenumber":"222",
    "addr:postcode":"g0r 1m0",
    "addr:street":"Rue Principale",
    "iso:country":"CA",
    "sg:address":"222 Rue Principale",
    "sg:city":"Frampton",
    "sg:classifiers":[
        {
            "category":"Autos & Motor Vehicles",
            "subcategory":"Fuel & Gas Station",
            "type":"Retail Goods"
        }
    ],
    "sg:phone":"+1 418 479 5524",
    "sg:postcode":"G0R 1M0",
    "sg:province":"QC",
    "sg:tags":[
        "oil"
    ],
    "wof:name":"Ghislain Lessard Station Svc",
    "wof:placetype":"venue"
},
  "geometry": {"coordinates":[-70.801483,46.455898],"type":"Point"}
}