{
  "type": "Feature",
  "properties": {
    "addr:full":"Winnipeg MB R3G 1C3",
    "addr:postcode":"r3g 1c3",
    "iso:country":"CA",
    "sg:city":"Winnipeg",
    "sg:classifiers":[
        {
            "category":"Social Services",
            "subcategory":"Adult Care",
            "type":"Services"
        }
    ],
    "sg:phone":"+1 204 772 3533",
    "sg:postcode":"R3G 1C3",
    "sg:province":"MB",
    "sg:tags":[
        "organization",
        "senior",
        "citizen"
    ],
    "wof:name":"Broadway Seniors Resource Ctr",
    "wof:placetype":"venue"
},
  "geometry": {"coordinates":[-97.16007999999999,49.880421],"type":"Point"}
}