{
  "type": "Feature",
  "properties": {
    "addr:full":"Quebec QC G2K 1S7",
    "addr:postcode":"g2k 1s7",
    "iso:country":"CA",
    "sg:city":"Quebec",
    "sg:classifiers":[
        {
            "category":"Wholesale",
            "subcategory":"Fruits & Vegetables",
            "type":"Manufacturing & Wholesale Goods"
        }
    ],
    "sg:phone":"+1 418 626 8636",
    "sg:postcode":"G2K 1S7",
    "sg:province":"QC",
    "wof:name":"Chambertin Gl Inc",
    "wof:placetype":"venue"
},
  "geometry": {"coordinates":[-71.219353,46.81274],"type":"Point"}
}