{
  "type": "Feature",
  "properties": {
    "addr:full":"Lindsay ON K9V 5G6",
    "addr:postcode":"k9v 5g6",
    "iso:country":"CA",
    "sg:city":"Lindsay",
    "sg:classifiers":[
        {
            "category":"Real Estate",
            "subcategory":"Real Estate Agent",
            "type":"Services"
        }
    ],
    "sg:phone":"+1 705 324 2185",
    "sg:postcode":"K9V 5G6",
    "sg:province":"ON",
    "sg:tags":[
        "management"
    ],
    "wof:name":"Found Realty Ltd",
    "wof:placetype":"venue"
},
  "geometry": {"coordinates":[-78.7405471802,44.3540382385],"type":"Point"}
}