{
  "type": "Feature",
  "properties": {
    "addr:full":"St-Sauveur-Des-Monts QC J0R 1R6",
    "addr:postcode":"j0r 1r6",
    "iso:country":"CA",
    "sg:city":"St-Sauveur-Des-Monts",
    "sg:classifiers":[
        {
            "category":"Shopping",
            "subcategory":"Clothing, Apparel, & Fashions",
            "type":"Retail Goods"
        }
    ],
    "sg:phone":"+1 450 227 0641",
    "sg:postcode":"J0R 1R6",
    "sg:province":"QC",
    "wof:name":"Boutique Claudel",
    "wof:placetype":"venue"
},
  "geometry": {"coordinates":[-74.1544494629,45.8920631409],"type":"Point"}
}