{
  "type": "Feature",
  "properties": {
    "addr:full":"PO Box 585 Moosomin SK S0G 3N0",
    "addr:housenumber":"po",
    "addr:postcode":"s0g 3n0",
    "addr:street":"Box 585",
    "iso:country":"CA",
    "sg:address":"PO Box 585",
    "sg:city":"Moosomin",
    "sg:classifiers":[
        {
            "category":"Organizations",
            "subcategory":"Religious Organization",
            "type":"Services"
        }
    ],
    "sg:phone":"+1 306 435 2155",
    "sg:postcode":"S0G 3N0",
    "sg:province":"SK",
    "sg:tags":[
        "church"
    ],
    "wof:name":"St Andrew's Presbyterian Ch",
    "wof:placetype":"venue"
},
  "geometry": {"coordinates":[-101.663292,50.147034],"type":"Point"}
}