{
  "type": "Feature",
  "properties": {
    "iso:country":"CA",
    "sg:address":"8815 145 St NW",
    "sg:city":"Edmonton",
    "sg:classifiers":[
        {
            "category":"Education",
            "subcategory":"School",
            "type":"Public Place"
        }
    ],
    "sg:phone":"+1 780 483 2695",
    "sg:postcode":"T5R 0T7",
    "sg:province":"AB",
    "wof:name":"St Rose Catholic Jr High Schl",
    "wof:placetype":"venue"
},
  "geometry": {"coordinates":[-113.57003,53.520702],"type":"Point"}
}