{
  "type": "Feature",
  "properties": {
    "iso:country":"CA",
    "sg:address":"887 Boul Pie-Xii",
    "sg:city":"Sainte-Foy",
    "sg:classifiers":[
        {
            "category":"Wholesale",
            "subcategory":"Office Equipment",
            "type":"Manufacturing & Wholesale Goods"
        }
    ],
    "sg:phone":"+1 418 659 6398",
    "sg:postcode":"G1X 3T3",
    "sg:province":"QC",
    "sg:tags":[
        "accounting",
        "bookkeeping",
        "system"
    ],
    "wof:name":"Gestion Mp Enr",
    "wof:placetype":"venue"
},
  "geometry": {"coordinates":[-71.3230438232,46.7624015808],"type":"Point"}
}