{
  "type": "Feature",
  "properties": {
    "iso:country":"CA",
    "sg:address":"1400 3E Av",
    "sg:city":"Quebec",
    "sg:classifiers":[
        {
            "category":"Wholesale",
            "subcategory":"Plants",
            "type":"Manufacturing & Wholesale Goods"
        }
    ],
    "sg:phone":"+1 418 688 3131",
    "sg:postcode":"G1L 2Y2",
    "sg:province":"QC",
    "sg:tags":[
        "florist"
    ],
    "wof:name":"Audrey Rose",
    "wof:placetype":"venue"
},
  "geometry": {"coordinates":[-71.2321853638,46.8291778564],"type":"Point"}
}