{
  "type": "Feature",
  "properties": {
    "addr:full":"700 Coxwell Ave Toronto ON M4C 3B9",
    "addr:housenumber":"700",
    "addr:postcode":"m4c 3b9",
    "addr:street":"Coxwell Ave",
    "iso:country":"CA",
    "sg:address":"700 Coxwell Ave",
    "sg:city":"Toronto",
    "sg:classifiers":[
        {
            "category":"Health Services",
            "subcategory":"Doctor",
            "type":"Services"
        }
    ],
    "sg:phone":"+1 416 461 2273",
    "sg:postcode":"M4C 3B9",
    "sg:province":"ON",
    "sg:tags":[
        "dentist"
    ],
    "wof:name":"C M Binert & Assoc",
    "wof:placetype":"venue"
},
  "geometry": {"coordinates":[-79.323928833,43.6836700439],"type":"Point"}
}