{
  "type": "Feature",
  "properties": {
    "iso:country":"CA",
    "sg:city":"Castleton",
    "sg:classifiers":[
        {
            "category":"Shopping",
            "type":"Retail Goods"
        }
    ],
    "sg:phone":"+1 905 344 7258",
    "sg:postcode":"K0K 1M0",
    "sg:province":"ON",
    "sg:tags":[
        "candle"
    ],
    "wof:name":"Kokimo Candles",
    "wof:placetype":"venue"
},
  "geometry": {"coordinates":[-77.9381103516,44.0927085876],"type":"Point"}
}