{
  "type": "Feature",
  "properties": {
    "addr:full":"Brampton ON L6W 4K6",
    "addr:postcode":"l6w 4k6",
    "iso:country":"CA",
    "sg:city":"Brampton",
    "sg:classifiers":[
        {
            "category":"Health Services",
            "subcategory":"Health Practitioner",
            "type":"Services"
        }
    ],
    "sg:phone":"+1 905 451 8131",
    "sg:postcode":"L6W 4K6",
    "sg:province":"ON",
    "sg:tags":[
        "physiotherapist"
    ],
    "wof:name":"Pro Action Physiotherapy",
    "wof:placetype":"venue"
},
  "geometry": {"coordinates":[-79.74292800000001,43.701229],"type":"Point"}
}