{
  "type": "Feature",
  "properties": {
    "addr:full":"383 Boul Cartier O Laval QC H7N 2K5",
    "addr:housenumber":"383",
    "addr:postcode":"h7n 2k5",
    "addr:street":"Boul Cartier O",
    "iso:country":"CA",
    "sg:address":"383 Boul Cartier O",
    "sg:city":"Laval",
    "sg:classifiers":[
        {
            "category":"Professional",
            "subcategory":"Business Services",
            "type":"Services"
        }
    ],
    "sg:phone":"+1 450 975 4488",
    "sg:postcode":"H7N 2K5",
    "sg:province":"QC",
    "sg:tags":[
        "notary"
    ],
    "wof:name":"Chartrand Cyr Hebert",
    "wof:placetype":"venue"
},
  "geometry": {"coordinates":[-73.711128,45.550484],"type":"Point"}
}