{
  "type": "Feature",
  "properties": {
    "addr:full":"743 3E Av E L'Ascension-DE-Notre-Seigneur QC G0W 1Y0",
    "addr:housenumber":"743",
    "addr:postcode":"g0w 1y0",
    "addr:street":"3E Av E",
    "iso:country":"CA",
    "sg:address":"743 3E Av E",
    "sg:city":"L'Ascension-DE-Notre-Seigneur",
    "sg:classifiers":[
        {
            "category":"Retail",
            "subcategory":"Auto Repair",
            "type":"Services"
        }
    ],
    "sg:phone":"+1 418 347 3594",
    "sg:postcode":"G0W 1Y0",
    "sg:province":"QC",
    "sg:tags":[
        "repairing",
        "automobile"
    ],
    "wof:name":"Garage Bertrand Potvin Enr",
    "wof:placetype":"venue"
},
  "geometry": {"coordinates":[-71.67330200000001,48.687935],"type":"Point"}
}