{
  "type": "Feature",
  "properties": {
    "addr:full":"714 20th St West Vancouver BC V7V 3Y7",
    "addr:housenumber":"714",
    "addr:postcode":"v7v 3y7",
    "addr:street":"20Th St",
    "iso:country":"CA",
    "sg:address":"714 20th St",
    "sg:city":"West Vancouver",
    "sg:classifiers":[
        {
            "category":"Organizations",
            "subcategory":"Religious Organization",
            "type":"Services"
        }
    ],
    "sg:phone":"+1 604 922 2023",
    "sg:postcode":"V7V 3Y7",
    "sg:province":"BC",
    "sg:tags":[
        "church"
    ],
    "wof:name":"First Church of Christ Scntst",
    "wof:placetype":"venue"
},
  "geometry": {"coordinates":[-123.16626739500001,49.3308792114],"type":"Point"}
}