{
  "type": "Feature",
  "properties": {
    "addr:full":"6557 Thorold Stone Rd Niagara Falls ON L2J 1B2",
    "addr:housenumber":"6557",
    "addr:postcode":"l2j 1b2",
    "addr:street":"Thorold Stone Rd",
    "iso:country":"CA",
    "sg:address":"6557 Thorold Stone Rd",
    "sg:city":"Niagara Falls",
    "sg:classifiers":[
        {
            "category":"Organizations",
            "subcategory":"Religious Organization",
            "type":"Services"
        }
    ],
    "sg:phone":"+1 905 358 7611",
    "sg:postcode":"L2J 1B2",
    "sg:province":"ON",
    "sg:tags":[
        "church"
    ],
    "wof:name":"Our Lady of the Scapular Chr",
    "wof:placetype":"venue"
},
  "geometry": {"coordinates":[-79.10554500000001,43.115273],"type":"Point"}
}