{
  "type": "Feature",
  "properties": {
    "addr:full":"Winnipeg MB R2J 1M3",
    "addr:postcode":"r2j 1m3",
    "iso:country":"CA",
    "sg:city":"Winnipeg",
    "sg:classifiers":[
        {
            "category":"Shopping",
            "subcategory":"Bicycles & Sporting Goods",
            "type":"Retail Goods"
        }
    ],
    "sg:phone":"+1 204 231 8226",
    "sg:postcode":"R2J 1M3",
    "sg:province":"MB",
    "sg:tags":[
        "canoe"
    ],
    "wof:name":"Wave Track",
    "wof:placetype":"venue"
},
  "geometry": {"coordinates":[-97.073509,49.873508],"type":"Point"}
}