{
  "type": "Feature",
  "properties": {
    "addr:full":"80 White Oak Dr E Sault Ste Marie ON P6B 4J8",
    "addr:housenumber":"80",
    "addr:postcode":"p6b 4j8",
    "addr:street":"White Oak Dr E",
    "iso:country":"CA",
    "sg:address":"80 White Oak Dr E",
    "sg:city":"Sault Ste Marie",
    "sg:classifiers":[
        {
            "category":"Manufacturing",
            "subcategory":"Printing",
            "type":"Manufacturing & Wholesale Goods"
        }
    ],
    "sg:phone":"+1 705 759 1718",
    "sg:postcode":"P6B 4J8",
    "sg:province":"ON",
    "sg:tags":[
        "printer"
    ],
    "wof:name":"Quality Printing",
    "wof:placetype":"venue"
},
  "geometry": {"coordinates":[-84.332848,46.537472],"type":"Point"}
}