{
  "type": "Feature",
  "properties": {
    "addr:full":"270 Chancellor Dr Woodbridge ON L4L 7M1",
    "addr:housenumber":"270",
    "addr:postcode":"l4l 7m1",
    "addr:street":"Chancellor Dr",
    "iso:country":"CA",
    "sg:address":"270 Chancellor Dr",
    "sg:city":"Woodbridge",
    "sg:classifiers":[
        {
            "category":"Restaurant",
            "type":"Food & Drink"
        }
    ],
    "sg:phone":"+1 905 856 4140",
    "sg:postcode":"L4L 7M1",
    "sg:province":"ON",
    "sg:tags":[
        "pizza"
    ],
    "wof:name":"Ital Vera Pizza",
    "wof:placetype":"venue"
},
  "geometry": {"coordinates":[-79.559792,43.796658],"type":"Point"}
}