{
  "type": "Feature",
  "properties": {
    "addr:full":"4310 Briardale Rd Courtenay BC V9N 9R7",
    "addr:housenumber":"4310",
    "addr:postcode":"v9n 9r7",
    "addr:street":"Briardale Rd",
    "iso:country":"CA",
    "sg:address":"4310 Briardale Rd",
    "sg:city":"Courtenay",
    "sg:classifiers":[
        {
            "category":"Freight",
            "type":"Transportation"
        }
    ],
    "sg:phone":"+1 250 338 6855",
    "sg:postcode":"V9N 9R7",
    "sg:province":"BC",
    "sg:tags":[
        "trucking"
    ],
    "wof:name":"Tri-Mountain Transport Inc",
    "wof:placetype":"venue"
},
  "geometry": {"coordinates":[-124.99314099999999,49.686722],"type":"Point"}
}