{
  "type": "Feature",
  "properties": {
    "iso:country":"CA",
    "sg:address":"6336 Rue Jean-Talon E",
    "sg:city":"Saint-Leonard",
    "sg:classifiers":[
        {
            "category":"Shopping",
            "subcategory":"Jewelry",
            "type":"Retail Goods"
        }
    ],
    "sg:phone":"+1 514 252 9881",
    "sg:postcode":"H1S 1M8",
    "sg:province":"QC",
    "sg:tags":[
        "jeweler"
    ],
    "wof:name":"Boccaccio Bijouterie",
    "wof:placetype":"venue"
},
  "geometry": {"coordinates":[-73.575843811,45.590965271],"type":"Point"}
}