{
  "type": "Feature",
  "properties": {
    "addr:full":"1839 Franklin St # A Vancouver BC V5L 1P9",
    "addr:housenumber":"1839",
    "addr:postcode":"v5l 1p9",
    "addr:street":"Franklin St # A",
    "iso:country":"CA",
    "sg:address":"1839 Franklin St # A",
    "sg:city":"Vancouver",
    "sg:classifiers":[
        {
            "category":"Shopping",
            "subcategory":"Clothing, Apparel, & Fashions",
            "type":"Retail Goods"
        }
    ],
    "sg:phone":"+1 604 215 1200",
    "sg:postcode":"V5L 1P9",
    "sg:province":"BC",
    "sg:tags":[
        "made"
    ],
    "wof:name":"Winning Manufacturing Ltd",
    "wof:placetype":"venue"
},
  "geometry": {"coordinates":[-123.067123413,49.2823104858],"type":"Point"}
}