{
  "type": "Feature",
  "properties": {
    "addr:full":"615 Main St Yarmouth NS B5A 1K1",
    "addr:housenumber":"615",
    "addr:postcode":"b5a 1k1",
    "addr:street":"Main St",
    "iso:country":"CA",
    "sg:address":"615 Main St",
    "sg:city":"Yarmouth",
    "sg:classifiers":[
        {
            "category":"Health Services",
            "subcategory":"Doctor",
            "type":"Services"
        }
    ],
    "sg:phone":"+1 902 749 1945",
    "sg:postcode":"B5A 1K1",
    "sg:province":"NS",
    "sg:tags":[
        "dentist"
    ],
    "wof:name":"El Geneidy, A K DDS",
    "wof:placetype":"venue"
},
  "geometry": {"coordinates":[-66.1139297485,43.8518676758],"type":"Point"}
}