{
  "type": "Feature",
  "properties": {
    "addr:full":"924 Main St Lorne NB E8G 1M2",
    "addr:housenumber":"924",
    "addr:postcode":"e8g 1m2",
    "addr:street":"Main St",
    "iso:country":"CA",
    "sg:address":"924 Main St",
    "sg:city":"Lorne",
    "sg:classifiers":[
        {
            "category":"Manufacturing",
            "subcategory":"Furniture",
            "type":"Manufacturing & Wholesale Goods"
        }
    ],
    "sg:phone":"+1 506 548 4566",
    "sg:postcode":"E8G 1M2",
    "sg:province":"NB",
    "sg:tags":[
        "venetian",
        "blind"
    ],
    "wof:name":"Caroflex Inc",
    "wof:placetype":"venue"
},
  "geometry": {"coordinates":[-67.18156399999999,47.210796],"type":"Point"}
}