{
  "type": "Feature",
  "properties": {
    "addr:full":"607 Legion Ave Kitimat BC V8C 2B3",
    "addr:housenumber":"607",
    "addr:postcode":"bc v8c 2b3",
    "addr:street":"Legion Ave",
    "iso:country":"CA",
    "sg:address":"607 Legion Ave",
    "sg:city":"Kitimat",
    "sg:classifiers":[
        {
            "category":"Restaurant",
            "type":"Food & Drink"
        }
    ],
    "sg:phone":"+1 250 632 4980",
    "sg:postcode":"V8C 2B3",
    "sg:province":"BC",
    "wof:name":"Rosario's Restaurant",
    "wof:placetype":"venue"
},
  "geometry": {"coordinates":[-128.66554300000001,54.055832],"type":"Point"}
}