{
  "type": "Feature",
  "properties": {
    "addr:full":"16389 130 Ave NW Edmonton AB T5V 1K5",
    "addr:housenumber":"16389",
    "addr:postcode":"t5v 1k5",
    "addr:street":"130 Ave Nw",
    "iso:country":"CA",
    "sg:address":"16389 130 Ave NW",
    "sg:city":"Edmonton",
    "sg:classifiers":[
        {
            "category":"Freight",
            "type":"Transportation"
        }
    ],
    "sg:phone":"+1 780 447 1639",
    "sg:postcode":"T5V 1K5",
    "sg:province":"AB",
    "sg:tags":[
        "courier"
    ],
    "wof:name":"Antler Express Ltd",
    "wof:placetype":"venue"
},
  "geometry": {"coordinates":[-113.60578918500001,53.5893592834],"type":"Point"}
}