{
  "type": "Feature",
  "properties": {
    "iso:country":"CA",
    "sg:city":"Coquitlam",
    "sg:classifiers":[
        {
            "category":"Professional",
            "subcategory":"Accounting & Tax Preparation",
            "type":"Services"
        }
    ],
    "sg:phone":"+1 604 466 9333",
    "sg:postcode":"V3B 2P7",
    "sg:province":"BC",
    "sg:tags":[
        "accountant"
    ],
    "wof:name":"Mont & Assoc",
    "wof:placetype":"venue"
},
  "geometry": {"coordinates":[-122.796905518,49.2828063965],"type":"Point"}
}