{
  "type": "Feature",
  "properties": {
    "addr:full":"66 Govt Rd Allowance N Camperville MB R0L 0J0",
    "addr:housenumber":"66",
    "addr:postcode":"r0l 0j0",
    "addr:street":"Govt Rd Allowance N",
    "iso:country":"CA",
    "sg:address":"66 Govt Rd Allowance N",
    "sg:city":"Camperville",
    "sg:classifiers":[
        {
            "category":"Organizations",
            "subcategory":"Religious Organization",
            "type":"Services"
        }
    ],
    "sg:phone":"+1 204 524 2459",
    "sg:postcode":"R0L 0J0",
    "sg:province":"MB",
    "sg:tags":[
        "church"
    ],
    "wof:name":"Roman Catholic Church",
    "wof:placetype":"venue"
},
  "geometry": {"coordinates":[-100.145203,51.98592],"type":"Point"}
}