{
  "type": "Feature",
  "properties": {
    "addr:full":"358 Danforth Ave Toronto ON M4K 1N8",
    "addr:housenumber":"358",
    "addr:postcode":"m4k 1n8",
    "addr:street":"Danforth Ave",
    "iso:country":"CA",
    "sg:address":"358 Danforth Ave",
    "sg:city":"Toronto",
    "sg:classifiers":[
        {
            "category":"Manufacturing",
            "subcategory":"Printing",
            "type":"Manufacturing & Wholesale Goods"
        }
    ],
    "sg:phone":"+1 416 778 4115",
    "sg:postcode":"M4K 1N8",
    "sg:province":"ON",
    "sg:tags":[
        "newspaper"
    ],
    "wof:name":"Tribe Magazine",
    "wof:placetype":"venue"
},
  "geometry": {"coordinates":[-79.352554,43.677551],"type":"Point"}
}