{
  "type": "Feature",
  "properties": {
    "addr:full":"100 Central Park Dr Markham ON L3P 7G2",
    "addr:housenumber":"100",
    "addr:postcode":"l3p 7g2",
    "addr:street":"Central Park Dr",
    "iso:country":"CA",
    "sg:address":"100 Central Park Dr",
    "sg:city":"Markham",
    "sg:classifiers":[
        {
            "category":"Social Services",
            "subcategory":"Child Care",
            "type":"Services"
        }
    ],
    "sg:phone":"+1 905 940 3274",
    "sg:postcode":"L3P 7G2",
    "sg:province":"ON",
    "sg:tags":[
        "kindergarten",
        "academic",
        "school"
    ],
    "wof:name":"Central Park Junior Y",
    "wof:placetype":"venue"
},
  "geometry": {"coordinates":[-79.29145812989999,43.8801498413],"type":"Point"}
}