{
  "type": "Feature",
  "properties": {
    "addr:full":"Easterville MB R0C 0V0",
    "addr:postcode":"r0c 0v0",
    "iso:country":"CA",
    "sg:city":"Easterville",
    "sg:classifiers":[
        {
            "category":"Taxi",
            "type":"Transportation"
        }
    ],
    "sg:phone":"+1 204 329 2264",
    "sg:postcode":"R0C 0V0",
    "sg:province":"MB",
    "sg:tags":[
        "taxicab"
    ],
    "wof:name":"Ledoux Taxi",
    "wof:placetype":"venue"
},
  "geometry": {"coordinates":[-99.8197097778,53.1060409546],"type":"Point"}
}