{
  "type": "Feature",
  "properties": {
    "addr:full":"London ON N6A 5A9",
    "addr:postcode":"n6a 5a9",
    "iso:country":"CA",
    "sg:city":"London",
    "sg:classifiers":[
        {
            "category":"Shopping",
            "type":"Retail Goods"
        }
    ],
    "sg:phone":"+1 519 432 7396",
    "sg:postcode":"N6A 5A9",
    "sg:province":"ON",
    "sg:tags":[
        "orthopedic",
        "appliance",
        "shoes"
    ],
    "wof:name":"Scientific Foot & Leg Care Ctr",
    "wof:placetype":"venue"
},
  "geometry": {"coordinates":[-81.250831604,42.9863777161],"type":"Point"}
}