{
  "type": "Feature",
  "properties": {
    "addr:full":"92 Arthur St Winnipeg MB R3B 1H3",
    "addr:housenumber":"92",
    "addr:postcode":"r3b 1h3",
    "addr:street":"Arthur St",
    "iso:country":"CA",
    "sg:address":"92 Arthur St",
    "sg:city":"Winnipeg",
    "sg:classifiers":[
        {
            "category":"Shopping",
            "subcategory":"Used Merchandise",
            "type":"Retail Goods"
        }
    ],
    "sg:phone":"+1 204 943 9788",
    "sg:postcode":"R3B 1H3",
    "sg:province":"MB",
    "sg:tags":[
        "book",
        "rare",
        "dealer"
    ],
    "wof:name":"Red River Book Shop",
    "wof:placetype":"venue"
},
  "geometry": {"coordinates":[-97.1409,49.897392],"type":"Point"}
}