{
  "type": "Feature",
  "properties": {
    "iso:country":"CA",
    "sg:city":"Quebec",
    "sg:classifiers":[
        {
            "category":"Organizations",
            "subcategory":"Labor Organization",
            "type":"Services"
        }
    ],
    "sg:phone":"+1 418 622 3535",
    "sg:postcode":"G2J 1N3",
    "sg:province":"QC",
    "wof:name":"Fipoe",
    "wof:placetype":"venue"
},
  "geometry": {"coordinates":[-71.271523,46.836735],"type":"Point"}
}