{
  "type": "Feature",
  "properties": {
    "addr:full":"1030 Baseline Rd Ottawa ON K2C 0A6",
    "addr:housenumber":"1030",
    "addr:postcode":"k2c 0a6",
    "addr:street":"Baseline Rd",
    "iso:country":"CA",
    "sg:address":"1030 Baseline Rd",
    "sg:city":"Ottawa",
    "sg:classifiers":[
        {
            "category":"Organizations",
            "subcategory":"Religious Organization",
            "type":"Services"
        }
    ],
    "sg:phone":"+1 613 727 1255",
    "sg:postcode":"K2C 0A6",
    "sg:province":"ON",
    "wof:name":"Ukrainian Seminary",
    "wof:placetype":"venue"
},
  "geometry": {"coordinates":[-75.72756195069999,45.3664855957],"type":"Point"}
}