{
  "type": "Feature",
  "properties": {
    "addr:full":"3271 Schmon Pky Thorold ON L2V 4Y6",
    "addr:housenumber":"3271",
    "addr:postcode":"l2v 4y6",
    "addr:street":"Schmon Pky",
    "iso:country":"CA",
    "sg:address":"3271 Schmon Pky",
    "sg:city":"Thorold",
    "sg:classifiers":[
        {
            "category":"Travel",
            "subcategory":"Travel Agent",
            "type":"Entertainment"
        }
    ],
    "sg:phone":"+1 905 984 8585",
    "sg:postcode":"L2V 4Y6",
    "sg:province":"ON",
    "sg:tags":[
        "agency",
        "bureau"
    ],
    "wof:name":"Caa Niagara",
    "wof:placetype":"venue"
},
  "geometry": {"coordinates":[-79.2400588989,43.1117858887],"type":"Point"}
}