{
  "type": "Feature",
  "properties": {
    "addr:full":"2 Paxman Rd Etobicoke ON M9C 1B6",
    "addr:housenumber":"2",
    "addr:postcode":"m9c 1b6",
    "addr:street":"Paxman Rd",
    "iso:country":"CA",
    "sg:address":"2 Paxman Rd",
    "sg:city":"Etobicoke",
    "sg:classifiers":[
        {
            "category":"Building & Trades",
            "subcategory":"Cleaning & Sanitation",
            "type":"Services"
        }
    ],
    "sg:phone":"+1 416 620 1888",
    "sg:postcode":"M9C 1B6",
    "sg:province":"ON",
    "sg:tags":[
        "cleaners",
        "rug",
        "carpet"
    ],
    "wof:name":"United Cleaning Svc Ltd",
    "wof:placetype":"venue"
},
  "geometry": {"coordinates":[-79.559113,43.624149],"type":"Point"}
}