{
  "type": "Feature",
  "properties": {
    "addr:full":"374 1st St W Stonewall MB R0C 2Z0",
    "addr:housenumber":"374",
    "addr:postcode":"r0c 2z0",
    "addr:street":"1St St W",
    "iso:country":"CA",
    "sg:address":"374 1st St W",
    "sg:city":"Stonewall",
    "sg:classifiers":[
        {
            "category":"Recreation",
            "type":"Entertainment"
        }
    ],
    "sg:phone":"+1 204 467 5556",
    "sg:postcode":"R0C 2Z0",
    "sg:province":"MB",
    "sg:tags":[
        "hall",
        "auditorium"
    ],
    "wof:name":"Odd Fellows Hall",
    "wof:placetype":"venue"
},
  "geometry": {"coordinates":[-97.327507019,50.124458313],"type":"Point"}
}