{
  "type": "Feature",
  "properties": {
    "addr:full":"500 Waterloo Crt Oshawa ON L1H 3X1",
    "addr:housenumber":"500",
    "addr:postcode":"l1h 3x1",
    "addr:street":"Waterloo Crt",
    "iso:country":"CA",
    "sg:address":"500 Waterloo Crt",
    "sg:city":"Oshawa",
    "sg:classifiers":[
        {
            "category":"Wholesale",
            "subcategory":"Scrap",
            "type":"Manufacturing & Wholesale Goods"
        }
    ],
    "sg:phone":"+1 905 576 7868",
    "sg:postcode":"L1H 3X1",
    "sg:province":"ON",
    "sg:tags":[
        "recycling",
        "center"
    ],
    "wof:name":"Gerdau Ameristeel Corp",
    "wof:placetype":"venue"
},
  "geometry": {"coordinates":[-78.833473,43.874966],"type":"Point"}
}