{
  "type": "Feature",
  "properties": {
    "addr:full":"3200 Island Hwy N # 6 Nanaimo BC V9T 1W1",
    "addr:housenumber":"3200",
    "addr:postcode":"v9t 1w1",
    "addr:street":"Island Hwy N # 6",
    "iso:country":"CA",
    "sg:address":"3200 Island Hwy N # 6",
    "sg:city":"Nanaimo",
    "sg:classifiers":[
        {
            "category":"Shopping",
            "subcategory":"Books",
            "type":"Retail Goods"
        }
    ],
    "sg:phone":"+1 250 756 2157",
    "sg:postcode":"V9T 1W1",
    "sg:province":"BC",
    "sg:tags":[
        "comic"
    ],
    "wof:name":"Curious Comics",
    "wof:placetype":"venue"
},
  "geometry": {"coordinates":[-124.002250671,49.2047576904],"type":"Point"}
}