{
  "type": "Feature",
  "properties": {
    "addr:full":"13221 115 Ave NW Edmonton AB T5M 4B7",
    "addr:housenumber":"13221",
    "addr:postcode":"t5m 4b7",
    "addr:street":"115 Ave Nw",
    "iso:country":"CA",
    "sg:address":"13221 115 Ave NW",
    "sg:city":"Edmonton",
    "sg:classifiers":[
        {
            "category":"Health Services",
            "subcategory":"Doctor",
            "type":"Services"
        }
    ],
    "sg:phone":"+1 780 413 5720",
    "sg:postcode":"T5M 4B7",
    "sg:province":"AB",
    "sg:tags":[
        "clinic"
    ],
    "wof:name":"Woodcroft Public Health Ctr",
    "wof:placetype":"venue"
},
  "geometry": {"coordinates":[-113.55100299999999,53.565067],"type":"Point"}
}