{
  "type": "Feature",
  "properties": {
    "addr:full":"1665 Ellis St Kelowna BC V1Y 2B3",
    "addr:housenumber":"1665",
    "addr:postcode":"v1y 2b3",
    "addr:street":"Ellis St",
    "iso:country":"CA",
    "sg:address":"1665 Ellis St",
    "sg:city":"Kelowna",
    "sg:classifiers":[
        {
            "category":"Professional",
            "subcategory":"Lawyer & Legal Services",
            "type":"Services"
        }
    ],
    "sg:phone":"+1 250 869 1225",
    "sg:postcode":"V1Y 2B3",
    "sg:province":"BC",
    "sg:tags":[
        "attorney"
    ],
    "wof:name":"Forrest, E Blair",
    "wof:placetype":"venue"
},
  "geometry": {"coordinates":[-119.49330139200001,49.8842964172],"type":"Point"}
}