{
  "type": "Feature",
  "properties": {
    "addr:full":"1013 Rue Beaugrand Acton Vale QC J0H 1A0",
    "addr:housenumber":"1013",
    "addr:postcode":"j0h 1a0",
    "addr:street":"Rue Beaugrand",
    "iso:country":"CA",
    "sg:address":"1013 Rue Beaugrand",
    "sg:city":"Acton Vale",
    "sg:classifiers":[
        {
            "category":"Personal",
            "subcategory":"Beauty Salon",
            "type":"Services"
        }
    ],
    "sg:phone":"+1 450 546 2933",
    "sg:postcode":"J0H 1A0",
    "sg:province":"QC",
    "wof:name":"Salon LA Marquise Enr",
    "wof:placetype":"venue"
},
  "geometry": {"coordinates":[-72.565056,45.649185],"type":"Point"}
}