{
  "type": "Feature",
  "properties": {
    "iso:country":"CA",
    "sg:address":"289 Ch Tache",
    "sg:city":"Cantley",
    "sg:classifiers":[
        {
            "category":"Building & Trades",
            "subcategory":"Cleaning & Sanitation",
            "type":"Services"
        }
    ],
    "sg:phone":"+1 819 827 0412",
    "sg:postcode":"J8V 3H3",
    "sg:province":"QC",
    "sg:tags":[
        "fireplace",
        "chimney"
    ],
    "wof:name":"Yaro's Chimney Sweeping",
    "wof:placetype":"venue"
},
  "geometry": {"coordinates":[-75.7348251343,45.5230140686],"type":"Point"}
}