{
  "type": "Feature",
  "properties": {
    "addr:full":"Kelowna BC V1Y 2H4",
    "addr:postcode":"v1y 2h4",
    "iso:country":"CA",
    "sg:city":"Kelowna",
    "sg:classifiers":[
        {
            "category":"Personal",
            "subcategory":"Beauty Salon",
            "type":"Services"
        }
    ],
    "sg:phone":"+1 250 861 6868",
    "sg:postcode":"V1Y 2H4",
    "sg:province":"BC",
    "wof:name":"Via Veneto Hair Design",
    "wof:placetype":"venue"
},
  "geometry": {"coordinates":[-119.489555,49.863155],"type":"Point"}
}