{
  "type": "Feature",
  "properties": {
    "addr:full":"23 Norcross Rd North York ON M3H 2R3",
    "addr:housenumber":"23",
    "addr:postcode":"m3h 2r3",
    "addr:street":"Norcross Rd",
    "iso:country":"CA",
    "sg:address":"23 Norcross Rd",
    "sg:city":"North York",
    "sg:classifiers":[
        {
            "category":"Building & Trades",
            "subcategory":"Electrical",
            "type":"Services"
        }
    ],
    "sg:phone":"+1 416 635 9494",
    "sg:postcode":"M3H 2R3",
    "sg:province":"ON",
    "sg:tags":[
        "electric",
        "contractor"
    ],
    "wof:name":"Mueller Electrical Contracting",
    "wof:placetype":"venue"
},
  "geometry": {"coordinates":[-79.452141,43.75135],"type":"Point"}
}