{
  "type": "Feature",
  "properties": {
    "addr:full":"1609 Wharncliffe Rd S London ON N6L 1J9",
    "addr:housenumber":"1609",
    "addr:postcode":"n6l 1j9",
    "addr:street":"Wharncliffe Rd",
    "iso:country":"CA",
    "sg:address":"1609 Wharncliffe Rd S",
    "sg:city":"London",
    "sg:classifiers":[
        {
            "category":"Retail",
            "subcategory":"Auto Repair",
            "type":"Services"
        }
    ],
    "sg:phone":"+1 519 652 8844",
    "sg:postcode":"N6L 1J9",
    "sg:province":"ON",
    "sg:tags":[
        "repairing",
        "automobile"
    ],
    "wof:name":"Ultra Auto Care",
    "wof:placetype":"venue"
},
  "geometry": {"coordinates":[-81.2737960815,42.926700592],"type":"Point"}
}