{
  "type": "Feature",
  "properties": {
    "addr:full":"225 Rue Saint-Andre Saint-Remi QC J0L 2L0",
    "addr:housenumber":"225",
    "addr:postcode":"j0l 2l0",
    "addr:street":"Rue Saint-Andre Saint-Remi",
    "iso:country":"CA",
    "sg:address":"225 Rue Saint-Andre",
    "sg:city":"Saint-Remi",
    "sg:classifiers":[
        {
            "category":"Wholesale",
            "subcategory":"Groceries",
            "type":"Manufacturing & Wholesale Goods"
        }
    ],
    "sg:phone":"+1 450 454 7541",
    "sg:postcode":"J0L 2L0",
    "sg:province":"QC",
    "sg:tags":[
        "food",
        "grocer",
        "product"
    ],
    "wof:name":"Saladexpress Inc",
    "wof:placetype":"venue"
},
  "geometry": {"coordinates":[-73.608673,45.255577],"type":"Point"}
}