{
  "type": "Feature",
  "properties": {
    "addr:full":"270 Boul DE Palerme LA Prairie QC J5R 5V9",
    "addr:housenumber":"270",
    "addr:postcode":"j5r 5v9",
    "addr:street":"Boul De Palerme",
    "iso:country":"CA",
    "sg:address":"270 Boul DE Palerme",
    "sg:city":"LA Prairie",
    "sg:classifiers":[
        {
            "category":"Real Estate",
            "subcategory":"Real Estate Agent",
            "type":"Services"
        }
    ],
    "sg:phone":"+1 450 444 5555",
    "sg:postcode":"J5R 5V9",
    "sg:province":"QC",
    "wof:name":"Turgeon & Assoc",
    "wof:placetype":"venue"
},
  "geometry": {"coordinates":[-73.474121,45.405109],"type":"Point"}
}