{
  "type": "Feature",
  "properties": {
    "iso:country":"CA",
    "sg:address":"341 Av Lafleur",
    "sg:city":"Lasalle",
    "sg:classifiers":[
        {
            "category":"Utilities",
            "subcategory":"Fuel Oil & Lpg",
            "type":"Services"
        }
    ],
    "sg:phone":"+1 514 595 4747",
    "sg:postcode":"H8R 3H3",
    "sg:province":"QC",
    "sg:tags":[
        "propane",
        "gas"
    ],
    "wof:name":"Wiseman Propane Inc",
    "wof:placetype":"venue"
},
  "geometry": {"coordinates":[-73.6474151611,45.4297943115],"type":"Point"}
}