{
  "type": "Feature",
  "properties": {
    "addr:full":"Mississauga ON L5C 3G1",
    "addr:postcode":"l5c 3g1",
    "iso:country":"CA",
    "sg:city":"Mississauga",
    "sg:classifiers":[
        {
            "category":"Organizations",
            "subcategory":"Community Association",
            "type":"Services"
        }
    ],
    "sg:phone":"+1 905 272 8343",
    "sg:postcode":"L5C 3G1",
    "sg:province":"ON",
    "sg:tags":[
        "club"
    ],
    "wof:name":"Cosenza Social Club",
    "wof:placetype":"venue"
},
  "geometry": {"coordinates":[-79.6533508301,43.5776672363],"type":"Point"}
}