{
  "type": "Feature",
  "properties": {
    "addr:full":"115 Rue Principale Notre-Dame-Du-Laus QC J0X 2M0",
    "addr:housenumber":"115",
    "addr:postcode":"j0x 2m0",
    "addr:street":"Rue Principale",
    "iso:country":"CA",
    "sg:address":"115 Rue Principale",
    "sg:city":"Notre-Dame-Du-Laus",
    "sg:classifiers":[
        {
            "category":"Freight",
            "type":"Transportation"
        }
    ],
    "sg:phone":"+1 819 767 2737",
    "sg:postcode":"J0X 2M0",
    "sg:province":"QC",
    "sg:tags":[
        "hardware",
        "commercial"
    ],
    "wof:name":"Quincaillerie Vincent & Frere",
    "wof:placetype":"venue"
},
  "geometry": {"coordinates":[-75.6248092651,46.0893363953],"type":"Point"}
}