{
  "type": "Feature",
  "properties": {
    "addr:full":"160 Confederation Pky Concord ON L4K 4T8",
    "addr:housenumber":"160",
    "addr:postcode":"l4k 4t8",
    "addr:street":"Confederation Pky",
    "iso:country":"CA",
    "sg:address":"160 Confederation Pky",
    "sg:city":"Concord",
    "sg:classifiers":[
        {
            "category":"Building & Trades",
            "subcategory":"Plumbing",
            "type":"Services"
        }
    ],
    "sg:phone":"+1 905 660 3569",
    "sg:postcode":"L4K 4T8",
    "sg:province":"ON",
    "sg:tags":[
        "furnace",
        "heating",
        "contractor"
    ],
    "wof:name":"Montwest Air Ltd",
    "wof:placetype":"venue"
},
  "geometry": {"coordinates":[-79.486771,43.829197],"type":"Point"}
}