{
  "type": "Feature",
  "properties": {
    "iso:country":"CA",
    "sg:address":"95 Haverhill Rd SW",
    "sg:city":"Calgary",
    "sg:classifiers":[
        {
            "category":"Professional",
            "subcategory":"Business Services",
            "type":"Services"
        }
    ],
    "sg:phone":"+1 403 252 8865",
    "sg:postcode":"T2V 3E4",
    "sg:province":"AB",
    "sg:tags":[
        "interior",
        "consultant",
        "design",
        "decorator"
    ],
    "wof:name":"Suzanne Hayden Design",
    "wof:placetype":"venue"
},
  "geometry": {"coordinates":[-114.088340759,50.9771614075],"type":"Point"}
}