{
  "type": "Feature",
  "properties": {
    "addr:full":"3933 Boul Leman Laval QC H7E 4V7",
    "addr:housenumber":"3933",
    "addr:postcode":"h7e 4v7",
    "addr:street":"Boul Leman",
    "iso:country":"CA",
    "sg:address":"3933 Boul Leman",
    "sg:city":"Laval",
    "sg:classifiers":[
        {
            "category":"Building & Trades",
            "subcategory":"Plumbing",
            "type":"Services"
        }
    ],
    "sg:phone":"+1 450 661 9243",
    "sg:postcode":"H7E 4V7",
    "sg:province":"QC",
    "sg:tags":[
        "contractor"
    ],
    "wof:name":"Domier Plomberie & Chauffage",
    "wof:placetype":"venue"
},
  "geometry": {"coordinates":[-73.67166900629999,45.6129837036],"type":"Point"}
}