{
  "type": "Feature",
  "properties": {
    "addr:full":"770 Notre Dame Ave Winnipeg MB R3E 0L9",
    "addr:housenumber":"770",
    "addr:postcode":"r3e 0l9",
    "addr:street":"Notre Dame Ave",
    "iso:country":"CA",
    "sg:address":"770 Notre Dame Ave",
    "sg:city":"Winnipeg",
    "sg:classifiers":[
        {
            "category":"Food & Beverages",
            "subcategory":"Specialty",
            "type":"Retail Goods"
        }
    ],
    "sg:phone":"+1 204 775 9044",
    "sg:postcode":"R3E 0L9",
    "sg:province":"MB",
    "sg:tags":[
        "health",
        "diet"
    ],
    "wof:name":"House of Nutrition Ltd",
    "wof:placetype":"venue"
},
  "geometry": {"coordinates":[-97.1628646851,49.9022750854],"type":"Point"}
}