{
  "type": "Feature",
  "properties": {
    "addr:full":"Vancouver BC V6P 6G5",
    "addr:postcode":"v6p 6g5",
    "iso:country":"CA",
    "sg:city":"Vancouver",
    "sg:classifiers":[
        {
            "category":"Real Estate",
            "subcategory":"Real Estate Agent",
            "type":"Services"
        }
    ],
    "sg:phone":"+1 604 266 8287",
    "sg:postcode":"V6P 6G5",
    "sg:province":"BC",
    "sg:tags":[
        "appraiser"
    ],
    "wof:name":"Appraisal Institute of Canada",
    "wof:placetype":"venue"
},
  "geometry": {"coordinates":[-123.133239746,49.2042617798],"type":"Point"}
}