{
  "type": "Feature",
  "properties": {
    "addr:full":"3215 Forest Glade Dr Windsor ON N8R 1W7",
    "addr:housenumber":"3215",
    "addr:postcode":"n8r 1w7",
    "addr:street":"Forest Glade Dr",
    "iso:country":"CA",
    "sg:address":"3215 Forest Glade Dr",
    "sg:city":"Windsor",
    "sg:classifiers":[
        {
            "category":"Recreation",
            "type":"Entertainment"
        }
    ],
    "sg:phone":"+1 519 735 3536",
    "sg:postcode":"N8R 1W7",
    "sg:province":"ON",
    "sg:tags":[
        "government",
        "hall",
        "auditorium"
    ],
    "wof:name":"Forest Glade Community Ctr",
    "wof:placetype":"venue"
},
  "geometry": {"coordinates":[-82.9143295288,42.3024291992],"type":"Point"}
}