{
  "type": "Feature",
  "properties": {
    "addr:full":"5112 50th St Evansburg AB T0E 0T0",
    "addr:housenumber":"5112",
    "addr:postcode":"t0e 0t0",
    "addr:street":"50Th St",
    "iso:country":"CA",
    "sg:address":"5112 50th St",
    "sg:city":"Evansburg",
    "sg:classifiers":[
        {
            "category":"Travel",
            "subcategory":"Hotels & Motels",
            "type":"Entertainment"
        }
    ],
    "sg:phone":"+1 780 727 3621",
    "sg:postcode":"T0E 0T0",
    "sg:province":"AB",
    "wof:name":"Evansburg Inn",
    "wof:placetype":"venue"
},
  "geometry": {"coordinates":[-115.018966675,53.6030349731],"type":"Point"}
}