{
  "type": "Feature",
  "properties": {
    "addr:full":"7829 Marchwood Pl Vancouver BC V5S 4A6",
    "addr:housenumber":"7829",
    "addr:postcode":"v5s 4a6",
    "addr:street":"Marchwood Pl",
    "iso:country":"CA",
    "sg:address":"7829 Marchwood Pl",
    "sg:city":"Vancouver",
    "sg:classifiers":[
        {
            "category":"Manufacturing",
            "subcategory":"Lumber",
            "type":"Manufacturing & Wholesale Goods"
        }
    ],
    "sg:phone":"+1 604 431 0990",
    "sg:postcode":"V5S 4A6",
    "sg:province":"BC",
    "sg:tags":[
        "forester"
    ],
    "wof:name":"H & W Saunders Assoc",
    "wof:placetype":"venue"
},
  "geometry": {"coordinates":[-123.114037,49.260441],"type":"Point"}
}