{
  "type": "Feature",
  "properties": {
    "iso:country":"CA",
    "sg:address":"598 Rue Principale",
    "sg:city":"L'Avenir",
    "sg:classifiers":[
        {
            "category":"Bars & Pubs",
            "type":"Food & Drink"
        }
    ],
    "sg:phone":"+1 819 394 3058",
    "sg:postcode":"J0C 1B0",
    "sg:province":"QC",
    "sg:tags":[
        "club",
        "lounge",
        "cocktail",
        "night"
    ],
    "wof:name":"Bar L'Escale L'Avenir",
    "wof:placetype":"venue"
},
  "geometry": {"coordinates":[-72.3072357178,45.7642440796],"type":"Point"}
}