{
  "type": "Feature",
  "properties": {
    "addr:full":"Ottawa ON K1S 2E1",
    "addr:postcode":"k1s 2e1",
    "iso:country":"CA",
    "sg:city":"Ottawa",
    "sg:classifiers":[
        {
            "category":"Professional",
            "subcategory":"Computer Services",
            "type":"Services"
        }
    ],
    "sg:phone":"+1 613 236 4567",
    "sg:postcode":"K1S 2E1",
    "sg:province":"ON",
    "wof:name":"Cinnabar Network Inc",
    "wof:placetype":"venue"
},
  "geometry": {"coordinates":[-75.7009506226,45.4007949829],"type":"Point"}
}