{
  "type": "Feature",
  "properties": {
    "addr:full":"30 Duhamel Rd Lively ON P3Y 1L4",
    "addr:housenumber":"30",
    "addr:postcode":"p3y 1l4",
    "addr:street":"Duhamel Rd",
    "iso:country":"CA",
    "sg:address":"30 Duhamel Rd",
    "sg:city":"Lively",
    "sg:classifiers":[
        {
            "category":"Freight",
            "type":"Transportation"
        }
    ],
    "sg:phone":"+1 705 692 1201",
    "sg:postcode":"P3Y 1L4",
    "sg:province":"ON",
    "sg:tags":[
        "trucking"
    ],
    "wof:name":"Gardewine North",
    "wof:placetype":"venue"
},
  "geometry": {"coordinates":[-81.10804748539999,46.4348602295],"type":"Point"}
}