{
  "type": "Feature",
  "properties": {
    "addr:full":"3870 Rue Jean-Talon E Montreal QC H2A 1Y7",
    "addr:housenumber":"3870",
    "addr:postcode":"h2a 1y7",
    "addr:street":"Rue Jean-Talon E",
    "iso:country":"CA",
    "sg:address":"3870 Rue Jean-Talon E",
    "sg:city":"Montreal",
    "sg:classifiers":[
        {
            "category":"Education",
            "subcategory":"School",
            "type":"Public Place"
        }
    ],
    "sg:phone":"+1 514 722 9305",
    "sg:postcode":"H2A 1Y7",
    "sg:province":"QC",
    "wof:name":"Studio Ballet Jazz C Martin",
    "wof:placetype":"venue"
},
  "geometry": {"coordinates":[-73.5927886963,45.5647544861],"type":"Point"}
}