{
  "type": "Feature",
  "properties": {
    "addr:full":"15 Colborne St S Simcoe ON N3Y 4H2",
    "addr:housenumber":"15",
    "addr:postcode":"n3y 4h2",
    "addr:street":"Colborne St S",
    "iso:country":"CA",
    "sg:address":"15 Colborne St S",
    "sg:city":"Simcoe",
    "sg:classifiers":[
        {
            "category":"Personal",
            "subcategory":"Beauty Salon",
            "type":"Services"
        }
    ],
    "sg:phone":"+1 519 426 2491",
    "sg:postcode":"N3Y 4H2",
    "sg:province":"ON",
    "wof:name":"Clips Hair Design",
    "wof:placetype":"venue"
},
  "geometry": {"coordinates":[-80.30591583250001,42.8365592957],"type":"Point"}
}