{
  "type": "Feature",
  "properties": {
    "addr:full":"94 Golden Ave South Porcupine ON P0N 1H0",
    "addr:housenumber":"94",
    "addr:postcode":"p0n 1h0",
    "addr:street":"Golden Ave South",
    "iso:country":"CA",
    "sg:address":"94 Golden Ave",
    "sg:city":"South Porcupine",
    "sg:classifiers":[
        {
            "category":"Restaurant",
            "type":"Food & Drink"
        }
    ],
    "sg:phone":"+1 705 235 3600",
    "sg:postcode":"P0N 1H0",
    "sg:province":"ON",
    "wof:name":"Country Haven",
    "wof:placetype":"venue"
},
  "geometry": {"coordinates":[-81.209969,48.477386],"type":"Point"}
}