{
  "type": "Feature",
  "properties": {
    "addr:full":"739 Vinden St Midland ON L4R 4L9",
    "addr:housenumber":"739",
    "addr:postcode":"l4r 4l9",
    "addr:street":"Vinden St",
    "iso:country":"CA",
    "sg:address":"739 Vinden St",
    "sg:city":"Midland",
    "sg:classifiers":[
        {
            "category":"Home & Garden",
            "subcategory":"Furniture",
            "type":"Retail Goods"
        }
    ],
    "sg:phone":"+1 705 527 9090",
    "sg:postcode":"L4R 4L9",
    "sg:province":"ON",
    "sg:tags":[
        "equipment",
        "kitchen",
        "cabinet"
    ],
    "wof:name":"Georgian Kitchen Ctr",
    "wof:placetype":"venue"
},
  "geometry": {"coordinates":[-79.902023,44.753487],"type":"Point"}
}