{
  "type": "Feature",
  "properties": {
    "addr:full":"1661 Bayview Ave East York ON M4G 3C1",
    "addr:housenumber":"1661",
    "addr:postcode":"m4g 3c1",
    "addr:street":"Bayview Ave",
    "iso:country":"CA",
    "sg:address":"1661 Bayview Ave",
    "sg:city":"East York",
    "sg:classifiers":[
        {
            "category":"Home & Garden",
            "subcategory":"Furniture",
            "type":"Retail Goods"
        }
    ],
    "sg:phone":"+1 416 480 2221",
    "sg:postcode":"M4G 3C1",
    "sg:province":"ON",
    "sg:tags":[
        "builder",
        "custom"
    ],
    "wof:name":"Neoset Canada",
    "wof:placetype":"venue"
},
  "geometry": {"coordinates":[-79.37557200000001,43.70734],"type":"Point"}
}