{
  "type": "Feature",
  "properties": {
    "iso:country":"CA",
    "sg:address":"2 King St W",
    "sg:city":"Hamilton",
    "sg:classifiers":[
        {
            "category":"Personal",
            "subcategory":"Tanning Parlor",
            "type":"Services"
        }
    ],
    "sg:phone":"+1 905 777 8267",
    "sg:postcode":"L8P 1A1",
    "sg:province":"ON",
    "sg:tags":[
        "salon"
    ],
    "wof:name":"Summer Sun Safe Tan",
    "wof:placetype":"venue"
},
  "geometry": {"coordinates":[-79.86921691889999,43.2568092346],"type":"Point"}
}