{
  "type": "Feature",
  "properties": {
    "addr:full":"1173 Rue Principale Saint-Prosper QC G0X 3A0",
    "addr:housenumber":"1173",
    "addr:postcode":"g0x 3a0",
    "addr:street":"Rue Principale",
    "iso:country":"CA",
    "sg:address":"1173 Rue Principale",
    "sg:city":"Saint-Prosper",
    "sg:classifiers":[
        {
            "category":"Retail",
            "subcategory":"Funeral Services",
            "type":"Services"
        }
    ],
    "sg:phone":"+1 418 325 2462",
    "sg:postcode":"G0X 3A0",
    "sg:province":"QC",
    "sg:tags":[
        "director"
    ],
    "wof:name":"Salon Funeraire Roland Hivon",
    "wof:placetype":"venue"
},
  "geometry": {"coordinates":[-72.293419,46.615799],"type":"Point"}
}