{
  "type": "Feature",
  "properties": {
    "addr:full":"13 Mary Walk Elliot Lake ON P5A 1Z9",
    "addr:housenumber":"13",
    "addr:postcode":"p5a 1z9",
    "addr:street":"Mary Walk",
    "iso:country":"CA",
    "sg:address":"13 Mary Walk",
    "sg:city":"Elliot Lake",
    "sg:classifiers":[
        {
            "category":"Sports & Exercise",
            "subcategory":"Bowling",
            "type":"Entertainment"
        }
    ],
    "sg:phone":"+1 705 848 3314",
    "sg:postcode":"P5A 1Z9",
    "sg:province":"ON",
    "sg:tags":[
        "center"
    ],
    "wof:name":"Northern Light Bowling Ctr",
    "wof:placetype":"venue"
},
  "geometry": {"coordinates":[-82.64906311039999,46.3869285583],"type":"Point"}
}