{
  "type": "Feature",
  "properties": {
    "addr:full":"15 Rue Du Boise-Des-Muriers Cantley QC J8V 2V7",
    "addr:housenumber":"15",
    "addr:postcode":"j8v 2v7",
    "addr:street":"Rue Du Boise-Des-Muriers",
    "iso:country":"CA",
    "sg:address":"15 Rue Du Boise-Des-Muriers",
    "sg:city":"Cantley",
    "sg:classifiers":[
        {
            "category":"Health Services",
            "subcategory":"Health Practitioner",
            "type":"Services"
        }
    ],
    "sg:phone":"+1 819 827 0511",
    "sg:postcode":"J8V 2V7",
    "sg:province":"QC",
    "sg:tags":[
        "psychotherapist"
    ],
    "wof:name":"Fleury, Donald",
    "wof:placetype":"venue"
},
  "geometry": {"coordinates":[-75.75122833250001,45.5244789124],"type":"Point"}
}