{
  "type": "Feature",
  "properties": {
    "iso:country":"CA",
    "sg:address":"3224 Boul Rosemont",
    "sg:city":"Montreal",
    "sg:classifiers":[
        {
            "category":"Restaurant",
            "type":"Food & Drink"
        }
    ],
    "sg:phone":"+1 514 722 3030",
    "sg:postcode":"H1Y 1M7",
    "sg:province":"QC",
    "wof:name":"Pizza En Route",
    "wof:placetype":"venue"
},
  "geometry": {"coordinates":[-73.5805435181,45.5527954102],"type":"Point"}
}