{
  "type": "Feature",
  "properties": {
    "iso:country":"CA",
    "sg:city":"London",
    "sg:classifiers":[
        {
            "category":"Professional",
            "subcategory":"Accounting & Tax Preparation",
            "type":"Services"
        }
    ],
    "sg:phone":"+1 519 672 4880",
    "sg:postcode":"N6A 5P2",
    "sg:province":"ON",
    "sg:tags":[
        "accountant"
    ],
    "wof:name":"Kpmg",
    "wof:placetype":"venue"
},
  "geometry": {"coordinates":[-81.25206756590001,42.9852104187],"type":"Point"}
}