{
  "type": "Feature",
  "properties": {
    "addr:full":"3887 Jane St North York ON M3N 2K1",
    "addr:housenumber":"3887",
    "addr:postcode":"m3n 2k1",
    "addr:street":"Jane St",
    "iso:country":"CA",
    "sg:address":"3887 Jane St",
    "sg:city":"North York",
    "sg:classifiers":[
        {
            "category":"Shopping",
            "subcategory":"Clothing, Apparel, & Fashions",
            "type":"Retail Goods"
        }
    ],
    "sg:phone":"+1 416 638 1728",
    "sg:postcode":"M3N 2K1",
    "sg:province":"ON",
    "wof:name":"Society",
    "wof:placetype":"venue"
},
  "geometry": {"coordinates":[-79.517448,43.756824],"type":"Point"}
}