{
  "type": "Feature",
  "properties": {
    "iso:country":"CA",
    "sg:address":"6760 164 Ave NW",
    "sg:city":"Edmonton",
    "sg:classifiers":[
        {
            "category":"Manufacturing",
            "subcategory":"Metals",
            "type":"Manufacturing & Wholesale Goods"
        }
    ],
    "sg:phone":"+1 780 481 1005",
    "sg:postcode":"T5Z 3M6",
    "sg:province":"AB",
    "sg:tags":[
        "steel",
        "reinforcing",
        "supply"
    ],
    "wof:name":"Alberta Rebar Placers Ltd",
    "wof:placetype":"venue"
},
  "geometry": {"coordinates":[-113.445617676,53.6261978149],"type":"Point"}
}