{
  "type": "Feature",
  "properties": {
    "addr:full":"1371 Pembroke St W Pembroke ON K8A 7A5",
    "addr:housenumber":"1371",
    "addr:postcode":"k8a 7a5",
    "addr:street":"Pembroke St W",
    "iso:country":"CA",
    "sg:address":"1371 Pembroke St W",
    "sg:city":"Pembroke",
    "sg:classifiers":[
        {
            "category":"Recreation",
            "type":"Entertainment"
        }
    ],
    "sg:phone":"+1 613 732 8565",
    "sg:postcode":"K8A 7A5",
    "sg:province":"ON",
    "sg:tags":[
        "bingo",
        "game"
    ],
    "wof:name":"Bingo Country",
    "wof:placetype":"venue"
},
  "geometry": {"coordinates":[-77.153717,45.834881],"type":"Point"}
}