{
  "type": "Feature",
  "properties": {
    "iso:country":"CA",
    "sg:address":"10535 170 St NW",
    "sg:city":"Edmonton",
    "sg:classifiers":[
        {
            "category":"Building & Trades",
            "subcategory":"Construction",
            "type":"Services"
        }
    ],
    "sg:phone":"+1 780 496 7658",
    "sg:postcode":"T5P 4W2",
    "sg:province":"AB",
    "sg:tags":[
        "communications",
        "fiber",
        "optics",
        "contractor"
    ],
    "wof:name":"Alberta Communication Cbl Svc",
    "wof:placetype":"venue"
},
  "geometry": {"coordinates":[-113.61495208700001,53.550868988],"type":"Point"}
}