{
  "type": "Feature",
  "properties": {
    "addr:full":"3552 Victoria Park Ave North York ON M2H 2N5",
    "addr:housenumber":"3552",
    "addr:postcode":"m2h 2n5",
    "addr:street":"Victoria Park Ave",
    "iso:country":"CA",
    "sg:address":"3552 Victoria Park Ave",
    "sg:city":"North York",
    "sg:classifiers":[
        {
            "category":"Shopping",
            "subcategory":"Bicycles & Sporting Goods",
            "type":"Retail Goods"
        }
    ],
    "sg:phone":"+1 416 298 2649",
    "sg:postcode":"M2H 2N5",
    "sg:province":"ON",
    "wof:name":"Absolutely Hockey",
    "wof:placetype":"venue"
},
  "geometry": {"coordinates":[-79.33721199999999,43.805668],"type":"Point"}
}