{
  "type": "Feature",
  "properties": {
    "iso:country":"CA",
    "sg:address":"19 Blais St",
    "sg:city":"Embrun",
    "sg:classifiers":[
        {
            "category":"Health Services",
            "subcategory":"Optometrist",
            "type":"Services"
        }
    ],
    "sg:phone":"+1 613 443 5550",
    "sg:postcode":"K0A 1W0",
    "sg:province":"ON",
    "wof:name":"Levasseur & Assoc",
    "wof:placetype":"venue"
},
  "geometry": {"coordinates":[-75.2829666138,45.2739677429],"type":"Point"}
}