{
  "type": "Feature",
  "properties": {
    "addr:full":"6203 Rte 217 Sandy Cove NS B0V 1E0",
    "addr:housenumber":"6203",
    "addr:postcode":"b0v 1e0",
    "addr:street":"Rte 217",
    "iso:country":"CA",
    "sg:address":"6203 Rte 217",
    "sg:city":"Sandy Cove",
    "sg:classifiers":[
        {
            "category":"Education",
            "subcategory":"School",
            "type":"Public Place"
        }
    ],
    "sg:phone":"+1 902 834 6600",
    "sg:postcode":"B0V 1E0",
    "sg:province":"NS",
    "wof:name":"Digby Neck Consolidated School",
    "wof:placetype":"venue"
},
  "geometry": {"coordinates":[-66.087807,44.490582],"type":"Point"}
}