{
  "type": "Feature",
  "properties": {
    "addr:full":"12719 97 St NW Edmonton AB T5E 4C1",
    "addr:housenumber":"12719",
    "addr:postcode":"t5e 4c1",
    "addr:street":"97 St Nw",
    "iso:country":"CA",
    "sg:address":"12719 97 St NW",
    "sg:city":"Edmonton",
    "sg:classifiers":[
        {
            "category":"Shopping",
            "subcategory":"Bicycles & Sporting Goods",
            "type":"Retail Goods"
        }
    ],
    "sg:phone":"+1 780 475 0555",
    "sg:postcode":"T5E 4C1",
    "sg:province":"AB",
    "sg:tags":[
        "tackle",
        "fishing"
    ],
    "wof:name":"Fishin' Hole Ltd",
    "wof:placetype":"venue"
},
  "geometry": {"coordinates":[-113.491859436,53.5854072571],"type":"Point"}
}