{
  "type": "Feature",
  "properties": {
    "addr:full":"170 Aulac Rd Aulac NB E4L 2X2",
    "addr:housenumber":"170",
    "addr:postcode":"e4l 2x2",
    "addr:street":"Aulac Rd",
    "iso:country":"CA",
    "sg:address":"170 Aulac Rd",
    "sg:city":"Aulac",
    "sg:classifiers":[
        {
            "category":"Autos & Motor Vehicles",
            "subcategory":"Auto Supplies",
            "type":"Retail Goods"
        }
    ],
    "sg:phone":"+1 506 536 0650",
    "sg:postcode":"E4L 2X2",
    "sg:province":"NB",
    "sg:tags":[
        "tire"
    ],
    "wof:name":"Benick Svc Inc",
    "wof:placetype":"venue"
},
  "geometry": {"coordinates":[-64.28042600000001,45.869953],"type":"Point"}
}