{
  "type": "Feature",
  "properties": {
    "addr:full":"Grimsby ON L3M 4H1",
    "addr:postcode":"l3m 4h1",
    "iso:country":"CA",
    "sg:city":"Grimsby",
    "sg:classifiers":[
        {
            "category":"Personal",
            "subcategory":"Beauty Salon",
            "type":"Services"
        }
    ],
    "sg:phone":"+1 905 309 4386",
    "sg:postcode":"L3M 4H1",
    "sg:province":"ON",
    "sg:tags":[
        "manicuring"
    ],
    "wof:name":"Pretty Nails",
    "wof:placetype":"venue"
},
  "geometry": {"coordinates":[-79.563118,43.194405],"type":"Point"}
}