{
  "type": "Feature",
  "properties": {
    "addr:full":"388 Centre St Drumheller AB T0J 0Y0",
    "addr:housenumber":"388",
    "addr:postcode":"t0j 0y0",
    "addr:street":"Centre St",
    "iso:country":"CA",
    "sg:address":"388 Centre St",
    "sg:city":"Drumheller",
    "sg:classifiers":[
        {
            "category":"Restaurant",
            "type":"Food & Drink"
        }
    ],
    "sg:phone":"+1 403 823 3030",
    "sg:postcode":"T0J 0Y0",
    "sg:province":"AB",
    "wof:name":"Diana Restaurant",
    "wof:placetype":"venue"
},
  "geometry": {"coordinates":[-112.592499,51.395912],"type":"Point"}
}