{
  "type": "Feature",
  "properties": {
    "iso:country":"CA",
    "sg:address":"33094 South Fraser Way",
    "sg:city":"Abbotsford",
    "sg:classifiers":[
        {
            "category":"Education",
            "subcategory":"School",
            "type":"Public Place"
        }
    ],
    "sg:phone":"+1 604 852 8986",
    "sg:postcode":"V2S 2A8",
    "sg:province":"BC",
    "wof:name":"Dasmesh Punjabi School",
    "wof:placetype":"venue"
},
  "geometry": {"coordinates":[-122.306602,49.050518],"type":"Point"}
}