{
  "type": "Feature",
  "properties": {
    "addr:full":"174 Pentland St Winnipeg MB R2G 2S3",
    "addr:housenumber":"174",
    "addr:postcode":"r2g 2s3",
    "addr:street":"Pentland St",
    "iso:country":"CA",
    "sg:address":"174 Pentland St",
    "sg:city":"Winnipeg",
    "sg:classifiers":[
        {
            "category":"Organizations",
            "subcategory":"Religious Organization",
            "type":"Services"
        }
    ],
    "sg:phone":"+1 204 667 7408",
    "sg:postcode":"R2G 2S3",
    "sg:province":"MB",
    "sg:tags":[
        "church"
    ],
    "wof:name":"North Kildonan United Church",
    "wof:placetype":"venue"
},
  "geometry": {"coordinates":[-97.0740661621,49.9507522583],"type":"Point"}
}