{
  "type": "Feature",
  "properties": {
    "iso:country":"CA",
    "sg:city":"Iqaluit",
    "sg:classifiers":[
        {
            "category":"Airport",
            "type":"Transportation"
        }
    ],
    "sg:phone":"+1 867 979 4018",
    "sg:postcode":"X0A 0H0",
    "sg:province":"NU",
    "sg:tags":[
        "rental",
        "aircraft",
        "leasing",
        "charter",
        "maintenance"
    ],
    "wof:name":"Air Nunavut",
    "wof:placetype":"venue"
},
  "geometry": {"coordinates":[-68.5190200806,63.7514762878],"type":"Point"}
}