{
  "type": "Feature",
  "properties": {
    "addr:full":"1000 Rue DE L'Acadie Victoriaville QC G6T 1R3",
    "addr:housenumber":"1000",
    "addr:postcode":"g6t 1r3",
    "addr:street":"Rue De L'Acadie",
    "iso:country":"CA",
    "sg:address":"1000 Rue DE L'Acadie",
    "sg:city":"Victoriaville",
    "sg:classifiers":[
        {
            "category":"Manufacturing",
            "subcategory":"Apparel",
            "type":"Manufacturing & Wholesale Goods"
        }
    ],
    "sg:phone":"+1 819 758 4610",
    "sg:postcode":"G6T 1R3",
    "sg:province":"QC",
    "sg:tags":[
        "clothes",
        "accessory"
    ],
    "wof:name":"Confection Dms Inc",
    "wof:placetype":"venue"
},
  "geometry": {"coordinates":[-71.94678500000001,46.073669],"type":"Point"}
}