{
  "type": "Feature",
  "properties": {
    "iso:country":"CA",
    "sg:address":"Esher Rd Conc 6 #1",
    "sg:city":"Chapleau",
    "sg:classifiers":[
        {
            "category":"Travel",
            "subcategory":"Campground",
            "type":"Entertainment"
        }
    ],
    "sg:phone":"+1 705 864 0773",
    "sg:postcode":"P0M 1K0",
    "sg:province":"ON",
    "sg:tags":[
        "camp"
    ],
    "wof:name":"Paquette's Camp",
    "wof:placetype":"venue"
},
  "geometry": {"coordinates":[-83.52527618409999,47.8303375244],"type":"Point"}
}