{
  "type": "Feature",
  "properties": {
    "addr:full":"8571 Willoughby Dr Niagara Falls ON L2G 6X6",
    "addr:housenumber":"8571",
    "addr:postcode":"l2g 6x6",
    "addr:street":"Willoughby Dr",
    "iso:country":"CA",
    "sg:address":"8571 Willoughby Dr",
    "sg:city":"Niagara Falls",
    "sg:classifiers":[
        {
            "category":"Retail",
            "subcategory":"Auto Repair",
            "type":"Services"
        }
    ],
    "sg:phone":"+1 905 295 4147",
    "sg:postcode":"L2G 6X6",
    "sg:province":"ON",
    "sg:tags":[
        "body",
        "automobile",
        "painting"
    ],
    "wof:name":"Chippawa Auto Body Ltd",
    "wof:placetype":"venue"
},
  "geometry": {"coordinates":[-79.0464553833,43.0529785156],"type":"Point"}
}