{
  "type": "Feature",
  "properties": {
    "addr:full":"615 Pacific Ave Acme AB T0M 0A0",
    "addr:housenumber":"615",
    "addr:postcode":"t0m 0a0",
    "addr:street":"Pacific Ave",
    "iso:country":"CA",
    "sg:address":"615 Pacific Ave",
    "sg:city":"Acme",
    "sg:classifiers":[
        {
            "category":"Home & Garden",
            "subcategory":"Building Materials",
            "type":"Retail Goods"
        }
    ],
    "sg:phone":"+1 403 546 2157",
    "sg:postcode":"T0M 0A0",
    "sg:province":"AB",
    "sg:tags":[
        "lumber"
    ],
    "wof:name":"Acme Farm & Building Ctr",
    "wof:placetype":"venue"
},
  "geometry": {"coordinates":[-113.507149,51.496807],"type":"Point"}
}