{
  "type": "Feature",
  "properties": {
    "addr:full":"4645 Sarcee Rd SW Calgary AB T3E 7C8",
    "addr:housenumber":"4645",
    "addr:postcode":"t3e 7c8",
    "addr:street":"Sarcee Rd Sw",
    "iso:country":"CA",
    "sg:address":"4645 Sarcee Rd SW",
    "sg:city":"Calgary",
    "sg:classifiers":[
        {
            "category":"Retail",
            "subcategory":"Car Wash",
            "type":"Services"
        }
    ],
    "sg:phone":"+1 403 686 6749",
    "sg:postcode":"T3E 7C8",
    "sg:province":"AB",
    "sg:tags":[
        "polishing",
        "washing"
    ],
    "wof:name":"College Car Wash",
    "wof:placetype":"venue"
},
  "geometry": {"coordinates":[-114.13898467999999,51.0132331848],"type":"Point"}
}