{
  "type": "Feature",
  "properties": {
    "addr:full":"6701 Av Fielding Montreal QC H4V 1N7",
    "addr:housenumber":"6701",
    "addr:postcode":"h4v 1n7",
    "addr:street":"Av Fielding",
    "iso:country":"CA",
    "sg:address":"6701 Av Fielding",
    "sg:city":"Montreal",
    "sg:classifiers":[
        {
            "category":"Restaurant",
            "type":"Food & Drink"
        }
    ],
    "sg:phone":"+1 514 489 8740",
    "sg:postcode":"H4V 1N7",
    "sg:province":"QC",
    "sg:tags":[
        "delicatessen"
    ],
    "wof:name":"Laila Delicatessen & Grocery",
    "wof:placetype":"venue"
},
  "geometry": {"coordinates":[-73.6439208984,45.4667625427],"type":"Point"}
}