{
  "type": "Feature",
  "properties": {
    "addr:full":"235 Ridge Rd Red Bank Queens CO NB E4A 2L5",
    "addr:housenumber":"235",
    "addr:postcode":"e4a 2l5",
    "addr:street":"Ridge Rd",
    "iso:country":"CA",
    "sg:address":"235 Ridge Rd",
    "sg:city":"Red Bank Queens CO",
    "sg:classifiers":[
        {
            "category":"Autos & Motor Vehicles",
            "subcategory":"Recreational Vehicle Sales",
            "type":"Retail Goods"
        }
    ],
    "sg:phone":"+1 506 339 1818",
    "sg:postcode":"E4A 2L5",
    "sg:province":"NB",
    "wof:name":"Ward's Recreation Ltd",
    "wof:placetype":"venue"
},
  "geometry": {"coordinates":[-65.953018,45.824661],"type":"Point"}
}