{
  "type": "Feature",
  "properties": {
    "addr:full":"Highway 24 Guelph ON N1H 6H7",
    "addr:postcode":"n1h 6h7",
    "addr:street":"Highway 24",
    "iso:country":"CA",
    "sg:address":"Highway 24",
    "sg:city":"Guelph",
    "sg:classifiers":[
        {
            "category":"Freight",
            "type":"Transportation"
        }
    ],
    "sg:phone":"+1 519 822 1011",
    "sg:postcode":"N1H 6H7",
    "sg:province":"ON",
    "sg:tags":[
        "trucking"
    ],
    "wof:name":"Crawford Transport",
    "wof:placetype":"venue"
},
  "geometry": {"coordinates":[-80.247871,43.544563],"type":"Point"}
}