{
  "type": "Feature",
  "properties": {
    "addr:full":"70 Massey Rd Regina SK S4S 4M9",
    "addr:housenumber":"70",
    "addr:postcode":"s4s 4m9",
    "addr:street":"Massey Rd",
    "iso:country":"CA",
    "sg:address":"70 Massey Rd",
    "sg:city":"Regina",
    "sg:classifiers":[
        {
            "category":"Recreation",
            "type":"Entertainment"
        }
    ],
    "sg:phone":"+1 306 777 7386",
    "sg:postcode":"S4S 4M9",
    "sg:province":"SK",
    "sg:tags":[
        "skating",
        "rink"
    ],
    "wof:name":"Regina Murray Balfour Arena",
    "wof:placetype":"venue"
},
  "geometry": {"coordinates":[-104.609261,50.41354],"type":"Point"}
}