{
  "type": "Feature",
  "properties": {
    "addr:full":"1080 Moha Rd # A Lillooet BC V0K 1V0",
    "addr:housenumber":"1080",
    "addr:postcode":"v0k 1v0",
    "addr:street":"Moha Rd # A Lillooet",
    "iso:country":"CA",
    "sg:address":"1080 Moha Rd # A",
    "sg:city":"Lillooet",
    "sg:classifiers":[
        {
            "category":"Food & Beverages",
            "subcategory":"Groceries & Convenience Stores",
            "type":"Retail Goods"
        }
    ],
    "sg:phone":"+1 250 256 4502",
    "sg:postcode":"V0K 1V0",
    "sg:province":"BC",
    "sg:tags":[
        "grocer"
    ],
    "wof:name":"Country Store",
    "wof:placetype":"venue"
},
  "geometry": {"coordinates":[-121.926163,50.704781],"type":"Point"}
}