{
  "type": "Feature",
  "properties": {
    "addr:full":"Calgary AB T2E 6N6",
    "addr:postcode":"t2e 6n6",
    "iso:country":"CA",
    "sg:city":"Calgary",
    "sg:classifiers":[
        {
            "category":"Manufacturing",
            "subcategory":"Metals",
            "type":"Manufacturing & Wholesale Goods"
        }
    ],
    "sg:phone":"+1 403 291 2757",
    "sg:postcode":"T2E 6N6",
    "sg:province":"AB",
    "sg:tags":[
        "steel"
    ],
    "wof:name":"A & A Mfg",
    "wof:placetype":"venue"
},
  "geometry": {"coordinates":[-114.03335571300001,51.0850753784],"type":"Point"}
}