{
  "type": "Feature",
  "properties": {
    "addr:full":"Hamilton ON L8L 2X2",
    "addr:postcode":"l8l 2x2",
    "iso:country":"CA",
    "sg:city":"Hamilton",
    "sg:classifiers":[
        {
            "category":"Health Services",
            "subcategory":"Doctor",
            "type":"Services"
        }
    ],
    "sg:phone":"+1 905 523 1241",
    "sg:postcode":"L8L 2X2",
    "sg:province":"ON",
    "sg:tags":[
        "physician",
        "surgeon"
    ],
    "wof:name":"Holder, Douglas A MD",
    "wof:placetype":"venue"
},
  "geometry": {"coordinates":[-79.85437011720001,43.2613868713],"type":"Point"}
}