{
  "type": "Feature",
  "properties": {
    "addr:full":"Toronto ON M5C 1B5",
    "addr:postcode":"m5c 1b5",
    "iso:country":"CA",
    "sg:city":"Toronto",
    "sg:classifiers":[
        {
            "category":"Professional",
            "subcategory":"Management & Consulting",
            "type":"Services"
        }
    ],
    "sg:phone":"+1 416 368 6636",
    "sg:postcode":"M5C 1B5",
    "sg:province":"ON",
    "sg:tags":[
        "communications",
        "consultant"
    ],
    "wof:name":"P R Toolbox Inc",
    "wof:placetype":"venue"
},
  "geometry": {"coordinates":[-79.3775939941,43.6493225098],"type":"Point"}
}