{
  "type": "Feature",
  "properties": {
    "addr:full":"Saskatoon SK S7K 6M1",
    "addr:postcode":"s7k 6m1",
    "iso:country":"CA",
    "sg:city":"Saskatoon",
    "sg:classifiers":[
        {
            "category":"Shopping",
            "subcategory":"Florist",
            "type":"Retail Goods"
        }
    ],
    "sg:phone":"+1 306 956 0600",
    "sg:postcode":"S7K 6M1",
    "sg:province":"SK",
    "wof:name":"Grower Direct Fresh Cut Flwrs",
    "wof:placetype":"venue"
},
  "geometry": {"coordinates":[-106.65026899999999,52.157551],"type":"Point"}
}