{
  "type": "Feature",
  "properties": {
    "addr:full":"20 Canterbury Lane Sherwood Park AB T8H 1E7",
    "addr:housenumber":"20",
    "addr:postcode":"t8h 1e7",
    "addr:street":"Canterbury Lane",
    "iso:country":"CA",
    "sg:address":"20 Canterbury Lane",
    "sg:city":"Sherwood Park",
    "sg:classifiers":[
        {
            "category":"Recreation",
            "type":"Entertainment"
        }
    ],
    "sg:phone":"+1 780 467 1788",
    "sg:postcode":"T8H 1E7",
    "sg:province":"AB",
    "sg:tags":[
        "guide"
    ],
    "wof:name":"Buck Mountain Outfitters",
    "wof:placetype":"venue"
},
  "geometry": {"coordinates":[-113.267578,53.547295],"type":"Point"}
}