{
  "type": "Feature",
  "properties": {
    "addr:full":"32 John St Port Hope ON L1A 2Z2",
    "addr:housenumber":"32",
    "addr:postcode":"l1a 2z2",
    "addr:street":"John St",
    "iso:country":"CA",
    "sg:address":"32 John St",
    "sg:city":"Port Hope",
    "sg:classifiers":[
        {
            "category":"Real Estate",
            "subcategory":"Real Estate Agent",
            "type":"Services"
        }
    ],
    "sg:phone":"+1 905 885 1085",
    "sg:postcode":"L1A 2Z2",
    "sg:province":"ON",
    "wof:name":"Tiptop Realty Inc",
    "wof:placetype":"venue"
},
  "geometry": {"coordinates":[-78.29499800000001,43.950844],"type":"Point"}
}