{
  "type": "Feature",
  "properties": {
    "addr:full":"103 Boul St Joseph # 326 Gracefield QC J0X 1W0",
    "addr:housenumber":"103",
    "addr:postcode":"j0x 1w0",
    "addr:street":"Boul St Joseph # 326",
    "iso:country":"CA",
    "sg:address":"103 Boul St Joseph # 326",
    "sg:city":"Gracefield",
    "sg:classifiers":[
        {
            "category":"Retail",
            "subcategory":"Auto Repair",
            "type":"Services"
        }
    ],
    "sg:phone":"+1 819 463 2412",
    "sg:postcode":"J0X 1W0",
    "sg:province":"QC",
    "sg:tags":[
        "body",
        "automobile",
        "painting"
    ],
    "wof:name":"P Alie Debosselage & Peinture",
    "wof:placetype":"venue"
},
  "geometry": {"coordinates":[-76.052605,46.094261],"type":"Point"}
}