{
  "type": "Feature",
  "properties": {
    "addr:full":"4207 Loch Lomond Rd Saint John NB E2N 1C6",
    "addr:housenumber":"4207",
    "addr:postcode":"e2n 1c6",
    "addr:street":"Loch Lomond Rd",
    "iso:country":"CA",
    "sg:address":"4207 Loch Lomond Rd",
    "sg:city":"Saint John",
    "sg:classifiers":[
        {
            "category":"Food & Beverages",
            "subcategory":"Groceries & Convenience Stores",
            "type":"Retail Goods"
        }
    ],
    "sg:phone":"+1 506 696 5364",
    "sg:postcode":"E2N 1C6",
    "sg:province":"NB",
    "wof:name":"Airport Irving",
    "wof:placetype":"venue"
},
  "geometry": {"coordinates":[-65.89344,45.330231],"type":"Point"}
}