{
  "type": "Feature",
  "properties": {
    "addr:full":"26 Boul Saint-Raymond Hull QC J8Y 1R4",
    "addr:housenumber":"26",
    "addr:postcode":"j8y 1r4",
    "addr:street":"Boul Saint-Raymond",
    "iso:country":"CA",
    "sg:address":"26 Boul Saint-Raymond",
    "sg:city":"Hull",
    "sg:classifiers":[
        {
            "category":"Health Services",
            "subcategory":"Doctor",
            "type":"Services"
        }
    ],
    "sg:phone":"+1 819 777 6735",
    "sg:postcode":"J8Y 1R4",
    "sg:province":"QC",
    "sg:tags":[
        "physician",
        "surgeon",
        "chiropractor"
    ],
    "wof:name":"Centre Chiro Specifique Ayers",
    "wof:placetype":"venue"
},
  "geometry": {"coordinates":[-75.73561100000001,45.447464],"type":"Point"}
}