{
  "type": "Feature",
  "properties": {
    "addr:full":"21 East St Sutton West ON L0E 1R0",
    "addr:housenumber":"21",
    "addr:postcode":"l0e 1r0",
    "addr:street":"East St",
    "iso:country":"CA",
    "sg:address":"21 East St",
    "sg:city":"Sutton West",
    "sg:classifiers":[
        {
            "category":"Organizations",
            "subcategory":"Professional Association",
            "type":"Services"
        }
    ],
    "sg:phone":"+1 905 722 8171",
    "sg:postcode":"L0E 1R0",
    "sg:province":"ON",
    "sg:tags":[
        "club"
    ],
    "wof:name":"Royal Canadian Legion",
    "wof:placetype":"venue"
},
  "geometry": {"coordinates":[-79.352234,44.300991],"type":"Point"}
}