{
  "type": "Feature",
  "properties": {
    "addr:full":"Surrey BC V3R 9V8",
    "addr:postcode":"v3r 9v8",
    "iso:country":"CA",
    "sg:city":"Surrey",
    "sg:classifiers":[
        {
            "category":"Retail",
            "subcategory":"Laundry & Dry Cleaning",
            "type":"Services"
        }
    ],
    "sg:phone":"+1 604 585 3853",
    "sg:postcode":"V3R 9V8",
    "sg:province":"BC",
    "sg:tags":[
        "cleaners"
    ],
    "wof:name":"Quality Dry Cleaners",
    "wof:placetype":"venue"
},
  "geometry": {"coordinates":[-122.798309,49.187332],"type":"Point"}
}