{
  "type": "Feature",
  "properties": {
    "addr:full":"Montreal QC H2X 2H5",
    "addr:postcode":"h2x 2h5",
    "iso:country":"CA",
    "sg:city":"Montreal",
    "sg:classifiers":[
        {
            "category":"Banks & Credit Unions",
            "subcategory":"Investment Brokerage",
            "type":"Services"
        }
    ],
    "sg:phone":"+1 514 844 0747",
    "sg:postcode":"H2X 2H5",
    "sg:province":"QC",
    "sg:tags":[
        "advisory",
        "financial"
    ],
    "wof:name":"Theodorakis Investment Reg'd",
    "wof:placetype":"venue"
},
  "geometry": {"coordinates":[-73.5716934204,45.5083961487],"type":"Point"}
}