{
  "type": "Feature",
  "properties": {
    "addr:full":"7017 Nesters Rd Whistler BC V0N 1B7",
    "addr:housenumber":"7017",
    "addr:postcode":"v0n 1b7",
    "addr:street":"Nesters Rd",
    "iso:country":"CA",
    "sg:address":"7017 Nesters Rd",
    "sg:city":"Whistler",
    "sg:classifiers":[
        {
            "category":"Shopping",
            "subcategory":"Bicycles & Sporting Goods",
            "type":"Retail Goods"
        }
    ],
    "sg:phone":"+1 604 938 8036",
    "sg:postcode":"V0N 1B7",
    "sg:province":"BC",
    "wof:name":"Wild Willie's Ski Shop",
    "wof:placetype":"venue"
},
  "geometry": {"coordinates":[-122.954376,50.130146],"type":"Point"}
}