{
  "type": "Feature",
  "properties": {
    "addr:full":"8348 County Rd 50 Campbellford ON K0L 1L0",
    "addr:housenumber":"8348;50",
    "addr:postcode":"k0l 1l0",
    "addr:street":"County Rd",
    "iso:country":"CA",
    "sg:address":"8348 County Rd 50",
    "sg:city":"Campbellford",
    "sg:classifiers":[
        {
            "category":"Retail",
            "subcategory":"Repair Shop",
            "type":"Services"
        }
    ],
    "sg:phone":"+1 705 653 2267",
    "sg:postcode":"K0L 1L0",
    "sg:province":"ON",
    "sg:tags":[
        "water",
        "equipment",
        "treatment",
        "softening"
    ],
    "wof:name":"Campbellford Water Ctr",
    "wof:placetype":"venue"
},
  "geometry": {"coordinates":[-77.797493,44.309212],"type":"Point"}
}