{
  "type": "Feature",
  "properties": {
    "addr:full":"Vancouver BC V6Z 1M5",
    "addr:postcode":"v6z 1m5",
    "iso:country":"CA",
    "sg:city":"Vancouver",
    "sg:classifiers":[
        {
            "category":"Shopping",
            "subcategory":"Musical Instruments",
            "type":"Retail Goods"
        }
    ],
    "sg:phone":"+1 604 682 4422",
    "sg:postcode":"V6Z 1M5",
    "sg:province":"BC",
    "wof:name":"Westcoast Music",
    "wof:placetype":"venue"
},
  "geometry": {"coordinates":[-123.12736511200001,49.2766075134],"type":"Point"}
}