{
  "type": "Feature",
  "properties": {
    "addr:full":"Zurich ON N0M 2T0",
    "addr:postcode":"n0m 2t0",
    "iso:country":"CA",
    "sg:city":"Zurich",
    "sg:classifiers":[
        {
            "category":"Retail",
            "subcategory":"Veterinary Services",
            "type":"Services"
        }
    ],
    "sg:phone":"+1 519 236 4301",
    "sg:postcode":"N0M 2T0",
    "sg:province":"ON",
    "sg:tags":[
        "veterinarian"
    ],
    "wof:name":"South Huron Veterinary Clinic",
    "wof:placetype":"venue"
},
  "geometry": {"coordinates":[-81.625336,43.421253],"type":"Point"}
}