{
  "type": "Feature",
  "properties": {
    "addr:full":"76 Kitchener Rd Scarborough ON M1E 2X5",
    "addr:housenumber":"76",
    "addr:postcode":"m1e 2x5",
    "addr:street":"Kitchener Rd",
    "iso:country":"CA",
    "sg:address":"76 Kitchener Rd",
    "sg:city":"Scarborough",
    "sg:classifiers":[
        {
            "category":"Retail",
            "subcategory":"Veterinary Services",
            "type":"Services"
        }
    ],
    "sg:phone":"+1 416 284 4610",
    "sg:postcode":"M1E 2X5",
    "sg:province":"ON",
    "sg:tags":[
        "veterinarian"
    ],
    "wof:name":"Gerrard Mobile Veterinary Svc",
    "wof:placetype":"venue"
},
  "geometry": {"coordinates":[-79.187004,43.759827],"type":"Point"}
}