{
  "type": "Feature",
  "properties": {
    "addr:full":"323 Symington Ave Toronto ON M6P 3X1",
    "addr:housenumber":"323",
    "addr:postcode":"m6p 3x1",
    "addr:street":"Symington Ave",
    "iso:country":"CA",
    "sg:address":"323 Symington Ave",
    "sg:city":"Toronto",
    "sg:classifiers":[
        {
            "category":"Food & Beverages",
            "subcategory":"Liquor & Beverages",
            "type":"Retail Goods"
        }
    ],
    "sg:phone":"+1 416 536 4852",
    "sg:postcode":"M6P 3X1",
    "sg:province":"ON",
    "sg:tags":[
        "beer",
        "ale"
    ],
    "wof:name":"Beer Store",
    "wof:placetype":"venue"
},
  "geometry": {"coordinates":[-79.4512023926,43.6660575867],"type":"Point"}
}