{
  "type": "Feature",
  "properties": {
    "addr:full":"23 Church St Truro NS B2N 3Z5",
    "addr:housenumber":"23",
    "addr:postcode":"b2n 3z5",
    "addr:street":"Church St",
    "iso:country":"CA",
    "sg:address":"23 Church St",
    "sg:city":"Truro",
    "sg:classifiers":[
        {
            "category":"Organizations",
            "subcategory":"Religious Organization",
            "type":"Services"
        }
    ],
    "sg:phone":"+1 902 897 0566",
    "sg:postcode":"B2N 3Z5",
    "sg:province":"NS",
    "sg:tags":[
        "church"
    ],
    "wof:name":"St John's Anglican Church",
    "wof:placetype":"venue"
},
  "geometry": {"coordinates":[-63.275894,45.365452],"type":"Point"}
}