{
  "type": "Feature",
  "properties": {
    "addr:full":"632 Bloor St Mississauga ON L5A 3V9",
    "addr:housenumber":"632",
    "addr:postcode":"l5a 3v9",
    "addr:street":"Bloor St",
    "iso:country":"CA",
    "sg:address":"632 Bloor St",
    "sg:city":"Mississauga",
    "sg:classifiers":[
        {
            "category":"Health Services",
            "subcategory":"Doctor",
            "type":"Services"
        }
    ],
    "sg:phone":"+1 905 273 5600",
    "sg:postcode":"L5A 3V9",
    "sg:province":"ON",
    "sg:tags":[
        "dentist"
    ],
    "wof:name":"Manacki, Alex DDS",
    "wof:placetype":"venue"
},
  "geometry": {"coordinates":[-79.6110076904,43.5998649597],"type":"Point"}
}