{
  "type": "Feature",
  "properties": {
    "addr:full":"Vancouver BC V6J 1Y9",
    "addr:postcode":"v6j 1y9",
    "iso:country":"CA",
    "sg:city":"Vancouver",
    "sg:classifiers":[
        {
            "category":"Banks & Credit Unions",
            "subcategory":"Bank",
            "type":"Services"
        }
    ],
    "sg:phone":"+1 604 606 9511",
    "sg:postcode":"V6J 1Y9",
    "sg:province":"BC",
    "sg:tags":[
        "cashing",
        "loan",
        "check"
    ],
    "wof:name":"Money Mart",
    "wof:placetype":"venue"
},
  "geometry": {"coordinates":[-123.147750855,49.2636222839],"type":"Point"}
}