{
  "type": "Feature",
  "properties": {
    "addr:full":"1133 Portage Ave Winnipeg MB R3G 0S9",
    "addr:housenumber":"1133",
    "addr:postcode":"r3g 0s9",
    "addr:street":"Portage Ave",
    "iso:country":"CA",
    "sg:address":"1133 Portage Ave",
    "sg:city":"Winnipeg",
    "sg:classifiers":[
        {
            "category":"Bars & Pubs",
            "type":"Food & Drink"
        }
    ],
    "sg:phone":"+1 204 772 0454",
    "sg:postcode":"R3G 0S9",
    "sg:province":"MB",
    "sg:tags":[
        "club",
        "night"
    ],
    "wof:name":"Palomino Club",
    "wof:placetype":"venue"
},
  "geometry": {"coordinates":[-97.180611,49.884056],"type":"Point"}
}