{
  "type": "Feature",
  "properties": {
    "addr:full":"380 College St Toronto ON M5T 1S6",
    "addr:housenumber":"380",
    "addr:postcode":"m5t 1s6",
    "addr:street":"College St",
    "iso:country":"CA",
    "sg:address":"380 College St",
    "sg:city":"Toronto",
    "sg:classifiers":[
        {
            "category":"Restaurant",
            "type":"Food & Drink"
        }
    ],
    "sg:phone":"+1 416 972 6286",
    "sg:postcode":"M5T 1S6",
    "sg:province":"ON",
    "wof:name":"Amato Pizza",
    "wof:placetype":"venue"
},
  "geometry": {"coordinates":[-79.405083,43.657085],"type":"Point"}
}