{
  "type": "Feature",
  "properties": {
    "addr:full":"Ottawa ON K1S 5P3",
    "addr:postcode":"k1s 5p3",
    "iso:country":"CA",
    "sg:city":"Ottawa",
    "sg:classifiers":[
        {
            "category":"Real Estate",
            "subcategory":"Real Estate Operator",
            "type":"Services"
        }
    ],
    "sg:phone":"+1 613 565 8520",
    "sg:postcode":"K1S 5P3",
    "sg:province":"ON",
    "sg:tags":[
        "apartment"
    ],
    "wof:name":"Bona Vista Apartments",
    "wof:placetype":"venue"
},
  "geometry": {"coordinates":[-75.67186700000001,45.415443],"type":"Point"}
}