{
  "type": "Feature",
  "properties": {
    "iso:country":"CA",
    "sg:city":"Ashcroft",
    "sg:classifiers":[
        {
            "category":"Government",
            "subcategory":"Office",
            "type":"Public Place"
        }
    ],
    "sg:phone":"+1 250 453 1940",
    "sg:postcode":"V0K 1A0",
    "sg:province":"BC",
    "wof:name":"B C Public Health",
    "wof:placetype":"venue"
},
  "geometry": {"coordinates":[-121.282913208,50.7282142639],"type":"Point"}
}