{
  "type": "Feature",
  "properties": {
    "addr:full":"19708 16 Ave Langley BC V2Z 1K1",
    "addr:housenumber":"19708",
    "addr:postcode":"v2z 1k1",
    "addr:street":"16 Ave",
    "iso:country":"CA",
    "sg:address":"19708 16 Ave",
    "sg:city":"Langley",
    "sg:classifiers":[
        {
            "category":"Retail",
            "subcategory":"Portrait Studio",
            "type":"Services"
        }
    ],
    "sg:phone":"+1 604 530 8022",
    "sg:postcode":"V2Z 1K1",
    "sg:province":"BC",
    "sg:tags":[
        "photographer"
    ],
    "wof:name":"Michael's Fine Photography Ltd",
    "wof:placetype":"venue"
},
  "geometry": {"coordinates":[-122.677467346,49.0308952332],"type":"Point"}
}