{
  "type": "Feature",
  "properties": {
    "addr:full":"25 Penn Dr North York ON M9L 2A7",
    "addr:housenumber":"25",
    "addr:postcode":"m9l 2a7",
    "addr:street":"Penn Dr",
    "iso:country":"CA",
    "sg:address":"25 Penn Dr",
    "sg:city":"North York",
    "sg:classifiers":[
        {
            "category":"Manufacturing",
            "subcategory":"Metals",
            "type":"Manufacturing & Wholesale Goods"
        }
    ],
    "sg:phone":"+1 416 749 0221",
    "sg:postcode":"M9L 2A7",
    "sg:province":"ON",
    "sg:tags":[
        "machine",
        "screw",
        "product"
    ],
    "wof:name":"Emjac Screw Products Ltd",
    "wof:placetype":"venue"
},
  "geometry": {"coordinates":[-79.555519104,43.7512283325],"type":"Point"}
}