{
  "type": "Feature",
  "properties": {
    "addr:full":"Highway 1 Field BC V0A 1G0",
    "addr:postcode":"v0a 1g0",
    "addr:street":"Highway 1",
    "iso:country":"CA",
    "sg:address":"Highway 1",
    "sg:city":"Field",
    "sg:classifiers":[
        {
            "category":"Government",
            "subcategory":"Office",
            "type":"Public Place"
        }
    ],
    "sg:phone":"+1 250 343 6783",
    "sg:postcode":"V0A 1G0",
    "sg:province":"BC",
    "wof:name":"Canada Field Visitor Reception",
    "wof:placetype":"venue"
},
  "geometry": {"coordinates":[-116.48165899999999,51.404022],"type":"Point"}
}