{
  "type": "Feature",
  "properties": {
    "addr:full":"114 Rue Ryan Dollard-Des-Ormeaux QC H9A 3C4",
    "addr:housenumber":"114",
    "addr:postcode":"h9a 3c4",
    "addr:street":"Rue Ryan",
    "iso:country":"CA",
    "sg:address":"114 Rue Ryan",
    "sg:city":"Dollard-Des-Ormeaux",
    "sg:classifiers":[
        {
            "category":"Wholesale",
            "subcategory":"Chemicals & Plastics",
            "type":"Manufacturing & Wholesale Goods"
        }
    ],
    "sg:phone":"+1 514 620 1564",
    "sg:postcode":"H9A 3C4",
    "sg:province":"QC",
    "wof:name":"Alibar Sales Inc",
    "wof:placetype":"venue"
},
  "geometry": {"coordinates":[-73.83372497560001,45.4885215759],"type":"Point"}
}