{
  "type": "Feature",
  "properties": {
    "addr:full":"Kelowna BC V1Y 6M4",
    "addr:postcode":"v1y 6m4",
    "iso:country":"CA",
    "sg:city":"Kelowna",
    "sg:classifiers":[
        {
            "category":"Health Services",
            "subcategory":"Clinic",
            "type":"Services"
        }
    ],
    "sg:phone":"+1 250 763 9805",
    "sg:postcode":"V1Y 6M4",
    "sg:province":"BC",
    "sg:tags":[
        "acupuncture"
    ],
    "wof:name":"Lakelands Acupuncture",
    "wof:placetype":"venue"
},
  "geometry": {"coordinates":[-119.47668457,49.8854484558],"type":"Point"}
}