{
  "type": "Feature",
  "properties": {
    "addr:full":"355 Gorge Rd W Victoria BC V9A 1M9",
    "addr:housenumber":"355",
    "addr:postcode":"v9a 1m9",
    "addr:street":"Gorge Rd W",
    "iso:country":"CA",
    "sg:address":"355 Gorge Rd W",
    "sg:city":"Victoria",
    "sg:classifiers":[
        {
            "category":"Autos & Motor Vehicles",
            "subcategory":"Boat Sales",
            "type":"Retail Goods"
        }
    ],
    "sg:phone":"+1 250 361 4238",
    "sg:postcode":"V9A 1M9",
    "sg:province":"BC",
    "sg:tags":[
        "dealer",
        "canoe"
    ],
    "wof:name":"Victoria Canoe & Kayak Club",
    "wof:placetype":"venue"
},
  "geometry": {"coordinates":[-123.378075,48.442268],"type":"Point"}
}