{
  "type": "Feature",
  "properties": {
    "addr:full":"Peterborough ON K9J 6X3",
    "addr:postcode":"k9j 6x3",
    "iso:country":"CA",
    "sg:city":"Peterborough",
    "sg:classifiers":[
        {
            "category":"Banks & Credit Unions",
            "subcategory":"Investment Brokerage",
            "type":"Services"
        }
    ],
    "sg:phone":"+1 705 799 6622",
    "sg:postcode":"K9J 6X3",
    "sg:province":"ON",
    "sg:tags":[
        "consultant",
        "planning",
        "financial"
    ],
    "wof:name":"Lennox Financial Svc",
    "wof:placetype":"venue"
},
  "geometry": {"coordinates":[-78.32131195069999,44.3007316589],"type":"Point"}
}