{
  "type": "Feature",
  "properties": {
    "addr:full":"Barrie ON L4N 9P5",
    "addr:postcode":"l4n 9p5",
    "iso:country":"CA",
    "sg:city":"Barrie",
    "sg:classifiers":[
        {
            "category":"Restaurant",
            "type":"Food & Drink"
        }
    ],
    "sg:phone":"+1 705 733 2334",
    "sg:postcode":"L4N 9P5",
    "sg:province":"ON",
    "wof:name":"Brunchies Restaurant",
    "wof:placetype":"venue"
},
  "geometry": {"coordinates":[-79.6780014038,44.3330688477],"type":"Point"}
}