{
  "type": "Feature",
  "properties": {
    "addr:full":"4900 Gladstone Dr Mossley ON N0L 1V0",
    "addr:housenumber":"4900",
    "addr:postcode":"n0l 1v0",
    "addr:street":"Gladstone Dr",
    "iso:country":"CA",
    "sg:address":"4900 Gladstone Dr",
    "sg:city":"Mossley",
    "sg:classifiers":[
        {
            "category":"Farming",
            "subcategory":"Farm",
            "type":"Manufacturing & Wholesale Goods"
        }
    ],
    "sg:phone":"+1 519 269 9777",
    "sg:postcode":"N0L 1V0",
    "sg:province":"ON",
    "sg:tags":[
        "mushroom"
    ],
    "wof:name":"Middlesex Mushrooms Ltd",
    "wof:placetype":"venue"
},
  "geometry": {"coordinates":[-81.011391,42.944607],"type":"Point"}
}