{
  "type": "Feature",
  "properties": {
    "iso:country":"CA",
    "sg:address":"550 Bay St",
    "sg:city":"Victoria",
    "sg:classifiers":[
        {
            "category":"Autos & Motor Vehicles",
            "subcategory":"Fuel & Gas Station",
            "type":"Retail Goods"
        }
    ],
    "sg:phone":"+1 250 381 3552",
    "sg:postcode":"V8T 1P9",
    "sg:province":"BC",
    "sg:tags":[
        "oil"
    ],
    "wof:name":"Payless Gas",
    "wof:placetype":"venue"
},
  "geometry": {"coordinates":[-123.37107849100001,48.4360923767],"type":"Point"}
}