{
  "type": "Feature",
  "properties": {
    "addr:full":"Richmond BC V7C 4V5",
    "addr:postcode":"v7c 4v5",
    "iso:country":"CA",
    "sg:city":"Richmond",
    "sg:classifiers":[
        {
            "category":"Shopping",
            "subcategory":"Clothing, Apparel, & Fashions",
            "type":"Retail Goods"
        }
    ],
    "sg:phone":"+1 604 277 4778",
    "sg:postcode":"V7C 4V5",
    "sg:province":"BC",
    "wof:name":"Von Trading",
    "wof:placetype":"venue"
},
  "geometry": {"coordinates":[-123.147491,49.173019],"type":"Point"}
}