{
  "type": "Feature",
  "properties": {
    "iso:country":"CA",
    "sg:city":"Noelville",
    "sg:classifiers":[
        {
            "category":"Farming",
            "subcategory":"Dairy Farm",
            "type":"Manufacturing & Wholesale Goods"
        }
    ],
    "sg:phone":"+1 705 898 2806",
    "sg:postcode":"P0M 2N0",
    "sg:province":"ON",
    "wof:name":"Noelville Dairy",
    "wof:placetype":"venue"
},
  "geometry": {"coordinates":[-80.4316711426,46.1341705322],"type":"Point"}
}