{
  "type": "Feature",
  "properties": {
    "iso:country":"CA",
    "sg:address":"1230 Main St",
    "sg:city":"Winnipeg",
    "sg:classifiers":[
        {
            "category":"Recreation",
            "type":"Entertainment"
        }
    ],
    "sg:phone":"+1 204 589 4294",
    "sg:postcode":"R2W 3S8",
    "sg:province":"MB",
    "sg:tags":[
        "hall",
        "auditorium"
    ],
    "wof:name":"Holy Ghost Fraternal Aid Soc",
    "wof:placetype":"venue"
},
  "geometry": {"coordinates":[-97.129051,49.920231],"type":"Point"}
}