{
  "type": "Feature",
  "properties": {
    "iso:country":"CA",
    "sg:address":"3788 Selkirk Ave",
    "sg:city":"Powell River",
    "sg:classifiers":[
        {
            "category":"Building & Trades",
            "subcategory":"Construction",
            "type":"Services"
        }
    ],
    "sg:phone":"+1 604 485 2348",
    "sg:postcode":"V8A 3C1",
    "sg:province":"BC",
    "sg:tags":[
        "contractor",
        "general"
    ],
    "wof:name":"D Derton Construction",
    "wof:placetype":"venue"
},
  "geometry": {"coordinates":[-124.51877594,49.8183479309],"type":"Point"}
}