{
  "type": "Feature",
  "properties": {
    "addr:full":"2100 Oak St Sherwood Park AB T8A 0V9",
    "addr:housenumber":"2100",
    "addr:postcode":"t8a 0v9",
    "addr:street":"Oak St",
    "iso:country":"CA",
    "sg:address":"2100 Oak St",
    "sg:city":"Sherwood Park",
    "sg:classifiers":[
        {
            "category":"Sports & Exercise",
            "subcategory":"Golf",
            "type":"Entertainment"
        }
    ],
    "sg:phone":"+1 780 467 7373",
    "sg:postcode":"T8A 0V9",
    "sg:province":"AB",
    "sg:tags":[
        "course"
    ],
    "wof:name":"Broadmoor Public Golf Course",
    "wof:placetype":"venue"
},
  "geometry": {"coordinates":[-113.30738830599999,53.5288772583],"type":"Point"}
}