{
  "type": "Feature",
  "properties": {
    "addr:full":"27 Rue Levis Riviere-Du-Loup QC G5R 2R2",
    "addr:housenumber":"27",
    "addr:postcode":"g5r 2r2",
    "addr:street":"Rue Levis Riviere-Du-Loup",
    "iso:country":"CA",
    "sg:address":"27 Rue Levis",
    "sg:city":"Riviere-Du-Loup",
    "sg:classifiers":[
        {
            "category":"Shopping",
            "type":"Retail Goods"
        }
    ],
    "sg:phone":"+1 418 867 8425",
    "sg:postcode":"G5R 2R2",
    "sg:province":"QC",
    "sg:tags":[
        "orthopedic",
        "appliance"
    ],
    "wof:name":"Laboratories Orthopediques",
    "wof:placetype":"venue"
},
  "geometry": {"coordinates":[-69.537781,47.840202],"type":"Point"}
}