{
  "type": "Feature",
  "properties": {
    "addr:full":"360 Elgin St Brantford ON N3S 7P6",
    "addr:housenumber":"360",
    "addr:postcode":"n3s 7p6",
    "addr:street":"Elgin St",
    "iso:country":"CA",
    "sg:address":"360 Elgin St",
    "sg:city":"Brantford",
    "sg:classifiers":[
        {
            "category":"Wholesale",
            "subcategory":"Hardware",
            "type":"Manufacturing & Wholesale Goods"
        }
    ],
    "sg:phone":"+1 519 753 3186",
    "sg:postcode":"N3S 7P6",
    "sg:province":"ON",
    "sg:tags":[
        "plumbing",
        "fixture",
        "supply"
    ],
    "wof:name":"Mc Keough Supply Inc",
    "wof:placetype":"venue"
},
  "geometry": {"coordinates":[-80.232093811,43.1514205933],"type":"Point"}
}