{
  "type": "Feature",
  "properties": {
    "addr:full":"808 Laval Cres Kamloops BC V2C 5P3",
    "addr:housenumber":"808",
    "addr:postcode":"bc v2c 5p3",
    "addr:street":"Laval Cres",
    "iso:country":"CA",
    "sg:address":"808 Laval Cres",
    "sg:city":"Kamloops",
    "sg:classifiers":[
        {
            "category":"Retail",
            "subcategory":"Repair Shop",
            "type":"Services"
        }
    ],
    "sg:phone":"+1 250 372 8898",
    "sg:postcode":"V2C 5P3",
    "sg:province":"BC",
    "sg:tags":[
        "equipment",
        "conditioning",
        "air"
    ],
    "wof:name":"Air-Ease Distributors",
    "wof:placetype":"venue"
},
  "geometry": {"coordinates":[-120.359664917,50.6618537903],"type":"Point"}
}