{
  "type": "Feature",
  "properties": {
    "iso:country":"CA",
    "sg:address":"605 Rue Fleury E",
    "sg:city":"Montreal",
    "sg:classifiers":[
        {
            "category":"Manufacturing",
            "subcategory":"Musical Instruments",
            "type":"Manufacturing & Wholesale Goods"
        }
    ],
    "sg:phone":"+1 514 387 8275",
    "sg:postcode":"H2C 1N7",
    "sg:province":"QC",
    "sg:tags":[
        "violin",
        "maker"
    ],
    "wof:name":"Clairmont DE LA Croizetiere",
    "wof:placetype":"venue"
},
  "geometry": {"coordinates":[-73.66157531739999,45.5542564392],"type":"Point"}
}