{
  "type": "Feature",
  "properties": {
    "addr:full":"75 Shields Crt # 3 Markham ON L3R 9T4",
    "addr:housenumber":"75",
    "addr:postcode":"l3r 9t4",
    "addr:street":"Shields Crt # 3",
    "iso:country":"CA",
    "sg:address":"75 Shields Crt # 3",
    "sg:city":"Markham",
    "sg:classifiers":[
        {
            "category":"Shopping",
            "subcategory":"Computers & Home Electronics",
            "type":"Retail Goods"
        }
    ],
    "sg:phone":"+1 905 479 0130",
    "sg:postcode":"L3R 9T4",
    "sg:province":"ON",
    "sg:tags":[
        "parts",
        "supply"
    ],
    "wof:name":"Multilink Computers",
    "wof:placetype":"venue"
},
  "geometry": {"coordinates":[-79.3591995239,43.8343429565],"type":"Point"}
}