{
  "type": "Feature",
  "properties": {
    "addr:full":"16 Kilbarron Rd Nepean ON K2J 5B2",
    "addr:housenumber":"16",
    "addr:postcode":"k2j 5b2",
    "addr:street":"Kilbarron Rd",
    "iso:country":"CA",
    "sg:address":"16 Kilbarron Rd",
    "sg:city":"Nepean",
    "sg:classifiers":[
        {
            "category":"Social Services",
            "type":"Services"
        }
    ],
    "sg:phone":"+1 613 823 8452",
    "sg:postcode":"K2J 5B2",
    "sg:province":"ON",
    "sg:tags":[
        "housing",
        "assistance"
    ],
    "wof:name":"Nepean Housing Corp",
    "wof:placetype":"venue"
},
  "geometry": {"coordinates":[-75.734871,45.286587],"type":"Point"}
}