{
  "type": "Feature",
  "properties": {
    "addr:full":"86 Second Ave W Simcoe ON N3Y 2P3",
    "addr:housenumber":"86",
    "addr:postcode":"n3y 2p3",
    "addr:street":"Second Ave W",
    "iso:country":"CA",
    "sg:address":"86 Second Ave W",
    "sg:city":"Simcoe",
    "sg:classifiers":[
        {
            "category":"Professional",
            "subcategory":"Business Services",
            "type":"Services"
        }
    ],
    "sg:phone":"+1 519 426 7271",
    "sg:postcode":"N3Y 2P3",
    "sg:province":"ON",
    "sg:tags":[
        "printer",
        "embroidery"
    ],
    "wof:name":"Second Avenue Printing Ltd",
    "wof:placetype":"venue"
},
  "geometry": {"coordinates":[-80.311554,42.849197],"type":"Point"}
}