{
  "type": "Feature",
  "properties": {
    "addr:full":"30 Rue Du Rocher Riviere-Du-Loup QC G5R 1J6",
    "addr:housenumber":"30",
    "addr:postcode":"g5r 1j6",
    "addr:street":"Rue Du Rocher Riviere-Du-Loup",
    "iso:country":"CA",
    "sg:address":"30 Rue Du Rocher",
    "sg:city":"Riviere-Du-Loup",
    "sg:classifiers":[
        {
            "category":"Personal",
            "subcategory":"Beauty Salon",
            "type":"Services"
        }
    ],
    "sg:phone":"+1 418 867 2992",
    "sg:postcode":"G5R 1J6",
    "sg:province":"QC",
    "wof:name":"Salon Lise",
    "wof:placetype":"venue"
},
  "geometry": {"coordinates":[-69.5339508057,47.8394737244],"type":"Point"}
}