{
  "type": "Feature",
  "properties": {
    "addr:full":"Timmins ON P4N 1M7",
    "addr:postcode":"p4n 1m7",
    "iso:country":"CA",
    "sg:city":"Timmins",
    "sg:classifiers":[
        {
            "category":"Food & Beverages",
            "subcategory":"Groceries & Convenience Stores",
            "type":"Retail Goods"
        }
    ],
    "sg:phone":"+1 705 267 5945",
    "sg:postcode":"P4N 1M7",
    "sg:province":"ON",
    "wof:name":"T & S Variety Store",
    "wof:placetype":"venue"
},
  "geometry": {"coordinates":[-81.20453643800001,48.4696273804],"type":"Point"}
}