{
  "type": "Feature",
  "properties": {
    "addr:full":"324 Steeles Ave E Milton ON L9T 1Y4",
    "addr:housenumber":"324",
    "addr:postcode":"l9t 1y4",
    "addr:street":"Steeles Ave E",
    "iso:country":"CA",
    "sg:address":"324 Steeles Ave E",
    "sg:city":"Milton",
    "sg:classifiers":[
        {
            "category":"Restaurant",
            "type":"Food & Drink"
        }
    ],
    "sg:phone":"+1 905 878 7934",
    "sg:postcode":"L9T 1Y4",
    "sg:province":"ON",
    "wof:name":"Grand Chalet",
    "wof:placetype":"venue"
},
  "geometry": {"coordinates":[-79.891052,43.523949],"type":"Point"}
}