{
  "type": "Feature",
  "properties": {
    "addr:full":"4305 76 Ave NW Edmonton AB T6B 2H7",
    "addr:housenumber":"4305",
    "addr:postcode":"t6b 2h7",
    "addr:street":"76 Ave Nw",
    "iso:country":"CA",
    "sg:address":"4305 76 Ave NW",
    "sg:city":"Edmonton",
    "sg:classifiers":[
        {
            "category":"Manufacturing",
            "subcategory":"Tools & Machinery",
            "type":"Manufacturing & Wholesale Goods"
        }
    ],
    "sg:phone":"+1 780 469 6918",
    "sg:postcode":"T6B 2H7",
    "sg:province":"AB",
    "sg:tags":[
        "machine",
        "shop"
    ],
    "wof:name":"Hallmach Machining Ltd",
    "wof:placetype":"venue"
},
  "geometry": {"coordinates":[-113.407753,53.512257],"type":"Point"}
}