{
  "type": "Feature",
  "properties": {
    "addr:full":"7 Centennial Dr # 5 Martensville SK S0K 2T0",
    "addr:housenumber":"7",
    "addr:postcode":"s0k 2t0",
    "addr:street":"Centennial Dr # 5",
    "iso:country":"CA",
    "sg:address":"7 Centennial Dr # 5",
    "sg:city":"Martensville",
    "sg:classifiers":[
        {
            "category":"Restaurant",
            "type":"Food & Drink"
        }
    ],
    "sg:phone":"+1 306 668 3566",
    "sg:postcode":"S0K 2T0",
    "sg:province":"SK",
    "wof:name":"Vern's Pizza",
    "wof:placetype":"venue"
},
  "geometry": {"coordinates":[-106.67024231000001,52.2814712524],"type":"Point"}
}