{
  "type": "Feature",
  "properties": {
    "addr:full":"Calgary AB T3C 3T6",
    "addr:postcode":"t3c 3t6",
    "iso:country":"CA",
    "sg:city":"Calgary",
    "sg:classifiers":[
        {
            "category":"Real Estate",
            "subcategory":"Real Estate Agent",
            "type":"Services"
        }
    ],
    "sg:phone":"+1 403 242 8080",
    "sg:postcode":"T3C 3T6",
    "sg:province":"AB",
    "sg:tags":[
        "housing",
        "cooperative"
    ],
    "wof:name":"West Heritage Manor House",
    "wof:placetype":"venue"
},
  "geometry": {"coordinates":[-114.154854,51.039959],"type":"Point"}
}