{
  "type": "Feature",
  "properties": {
    "addr:full":"Mcdonald St Piapot SK S0N 1Y0",
    "addr:postcode":"s0n 1y0",
    "addr:street":"Mcdonald St",
    "iso:country":"CA",
    "sg:address":"Mcdonald St",
    "sg:city":"Piapot",
    "sg:classifiers":[
        {
            "category":"Education",
            "subcategory":"School",
            "type":"Public Place"
        }
    ],
    "sg:phone":"+1 306 558 2000",
    "sg:postcode":"S0N 1Y0",
    "sg:province":"SK",
    "wof:name":"Piapot School",
    "wof:placetype":"venue"
},
  "geometry": {"coordinates":[-109.12716674799999,49.9896316528],"type":"Point"}
}