{
  "type": "Feature",
  "properties": {
    "iso:country":"CA",
    "sg:address":"3931 Highland Dr",
    "sg:city":"Prince George",
    "sg:classifiers":[
        {
            "category":"Building & Trades",
            "subcategory":"Construction",
            "type":"Services"
        }
    ],
    "sg:phone":"+1 250 962 8040",
    "sg:postcode":"V2K 3R1",
    "sg:province":"BC",
    "sg:tags":[
        "painter"
    ],
    "wof:name":"Bernie's Painting & Decorating",
    "wof:placetype":"venue"
},
  "geometry": {"coordinates":[-122.795326233,53.9801177979],"type":"Point"}
}