{
  "type": "Feature",
  "properties": {
    "iso:country":"CA",
    "sg:address":"110 Boulder Cres",
    "sg:city":"Canmore",
    "sg:classifiers":[
        {
            "category":"Manufacturing",
            "subcategory":"Tools & Machinery",
            "type":"Manufacturing & Wholesale Goods"
        }
    ],
    "sg:phone":"+1 403 678 2361",
    "sg:postcode":"T1W 1L2",
    "sg:province":"AB",
    "sg:tags":[
        "steel",
        "machine",
        "shop"
    ],
    "wof:name":"Bow-Cor Custom Welding Ltd",
    "wof:placetype":"venue"
},
  "geometry": {"coordinates":[-115.324211121,51.077041626],"type":"Point"}
}