{
  "type": "Feature",
  "properties": {
    "addr:full":"Drayton Valley AB T7A 1R5",
    "addr:postcode":"t7a 1r5",
    "addr:street":"Drayton",
    "iso:country":"CA",
    "sg:city":"Drayton Valley",
    "sg:classifiers":[
        {
            "category":"Home & Garden",
            "subcategory":"Household Appliances",
            "type":"Retail Goods"
        }
    ],
    "sg:phone":"+1 780 542 5386",
    "sg:postcode":"T7A 1R5",
    "sg:province":"AB",
    "wof:name":"Sears Canada Inc",
    "wof:placetype":"venue"
},
  "geometry": {"coordinates":[-114.977928162,53.2229385376],"type":"Point"}
}