{
  "type": "Feature",
  "properties": {
    "addr:full":"64 31E Av Edmundston NB E3V 2R5",
    "addr:housenumber":"64",
    "addr:postcode":"e3v 2r5",
    "addr:street":"31E Av",
    "iso:country":"CA",
    "sg:address":"64 31E Av",
    "sg:city":"Edmundston",
    "sg:classifiers":[
        {
            "category":"Personal",
            "subcategory":"Beauty Salon",
            "type":"Services"
        }
    ],
    "sg:phone":"+1 506 735 1995",
    "sg:postcode":"E3V 2R5",
    "sg:province":"NB",
    "wof:name":"Coiffure Marie-Paule",
    "wof:placetype":"venue"
},
  "geometry": {"coordinates":[-68.319237,47.369747],"type":"Point"}
}