{
  "type": "Feature",
  "properties": {
    "iso:country":"CA",
    "sg:address":"6349 Boul Leger",
    "sg:city":"Montreal-Nord",
    "sg:classifiers":[
        {
            "category":"Restaurant",
            "type":"Food & Drink"
        }
    ],
    "sg:phone":"+1 514 955 8409",
    "sg:postcode":"H1G 1L4",
    "sg:province":"QC",
    "wof:name":"Belle Province",
    "wof:placetype":"venue"
},
  "geometry": {"coordinates":[-73.62362670900001,45.6227226257],"type":"Point"}
}