{
  "type": "Feature",
  "properties": {
    "addr:full":"717 Rue Des Cedres Saint-Alexandre-DE-Kamouraska QC G0L 2G0",
    "addr:housenumber":"717",
    "addr:postcode":"g0l 2g0",
    "addr:street":"Rue Des Cedres",
    "iso:country":"CA",
    "sg:address":"717 Rue Des Cedres",
    "sg:city":"Saint-Alexandre-DE-Kamouraska",
    "sg:classifiers":[
        {
            "category":"Freight",
            "type":"Transportation"
        }
    ],
    "sg:phone":"+1 418 495 2273",
    "sg:postcode":"G0L 2G0",
    "sg:province":"QC",
    "sg:tags":[
        "excavating",
        "contractor",
        "trucking"
    ],
    "wof:name":"Entreprises Dionne Lionel Inc",
    "wof:placetype":"venue"
},
  "geometry": {"coordinates":[-69.62164300000001,47.684372],"type":"Point"}
}