{
  "type": "Feature",
  "properties": {
    "addr:full":"25 Ashmore Close Red Deer AB T4R 2R7",
    "addr:housenumber":"25",
    "addr:postcode":"t4r 2r7",
    "addr:street":"Ashmore Close",
    "iso:country":"CA",
    "sg:address":"25 Ashmore Close",
    "sg:city":"Red Deer",
    "sg:classifiers":[
        {
            "category":"Banks & Credit Unions",
            "subcategory":"Bank",
            "type":"Services"
        }
    ],
    "sg:phone":"+1 403 342 0006",
    "sg:postcode":"T4R 2R7",
    "sg:province":"AB",
    "sg:tags":[
        "financing"
    ],
    "wof:name":"Liquid Capital Alberta Corp",
    "wof:placetype":"venue"
},
  "geometry": {"coordinates":[-113.77190399200001,52.2512741089],"type":"Point"}
}