{
  "type": "Feature",
  "properties": {
    "addr:full":"Mississauga ON L4T 4G3",
    "addr:postcode":"l4t 4g3",
    "iso:country":"CA",
    "sg:city":"Mississauga",
    "sg:classifiers":[
        {
            "category":"Manufacturing",
            "subcategory":"Metals",
            "type":"Manufacturing & Wholesale Goods"
        }
    ],
    "sg:phone":"+1 905 678 1992",
    "sg:postcode":"L4T 4G3",
    "sg:province":"ON",
    "sg:tags":[
        "brass",
        "bronze",
        "aluminum"
    ],
    "wof:name":"Mirco Sales Ltd",
    "wof:placetype":"venue"
},
  "geometry": {"coordinates":[-79.658508,43.698654],"type":"Point"}
}