{
  "type": "Feature",
  "properties": {
    "iso:country":"CA",
    "sg:address":"1765 Boul Cure-Labelle",
    "sg:city":"Laval",
    "sg:classifiers":[
        {
            "category":"Professional",
            "subcategory":"Business Services",
            "type":"Services"
        }
    ],
    "sg:phone":"+1 450 688 7916",
    "sg:postcode":"H7T 1L1",
    "sg:province":"QC",
    "sg:tags":[
        "fire",
        "protection"
    ],
    "wof:name":"Securite Domiciliaire Rg Inc",
    "wof:placetype":"venue"
},
  "geometry": {"coordinates":[-73.760956,45.553154],"type":"Point"}
}