{
  "type": "Feature",
  "properties": {
    "addr:full":"14 Rue Du Pont Labelle QC J0T 1H0",
    "addr:housenumber":"14",
    "addr:postcode":"j0t 1h0",
    "addr:street":"Rue Du Pont",
    "iso:country":"CA",
    "sg:address":"14 Rue Du Pont",
    "sg:city":"Labelle",
    "sg:classifiers":[
        {
            "category":"Cinema",
            "subcategory":"Movie Rental",
            "type":"Entertainment"
        }
    ],
    "sg:phone":"+1 819 686 9517",
    "sg:postcode":"J0T 1H0",
    "sg:province":"QC",
    "sg:tags":[
        "leasing",
        "video",
        "disc",
        "tape"
    ],
    "wof:name":"Videotheque Ll Enr",
    "wof:placetype":"venue"
},
  "geometry": {"coordinates":[-74.734863,46.280018],"type":"Point"}
}