{
  "type": "Feature",
  "properties": {
    "addr:full":"975 Rue Bernard-Pilon Beloeil QC J3G 1V7",
    "addr:housenumber":"975",
    "addr:postcode":"j3g 1v7",
    "addr:street":"Rue Bernard-Pilon",
    "iso:country":"CA",
    "sg:address":"975 Rue Bernard-Pilon",
    "sg:city":"Beloeil",
    "sg:classifiers":[
        {
            "category":"Bars & Pubs",
            "type":"Food & Drink"
        }
    ],
    "sg:phone":"+1 450 467 0968",
    "sg:postcode":"J3G 1V7",
    "sg:province":"QC",
    "wof:name":"Brasserie LA Poudriere Inc",
    "wof:placetype":"venue"
},
  "geometry": {"coordinates":[-73.23036999999999,45.557056],"type":"Point"}
}