{
  "type": "Feature",
  "properties": {
    "iso:country":"CA",
    "sg:address":"602 Dufferin Ave",
    "sg:city":"London",
    "sg:classifiers":[
        {
            "category":"Banks & Credit Unions",
            "subcategory":"Investment Brokerage",
            "type":"Services"
        }
    ],
    "sg:phone":"+1 519 432 2361",
    "sg:postcode":"N6B 2A4",
    "sg:province":"ON",
    "sg:tags":[
        "consultant",
        "planning",
        "financial"
    ],
    "wof:name":"Lewkowitz Financial Consulting",
    "wof:placetype":"venue"
},
  "geometry": {"coordinates":[-81.23317,42.991394],"type":"Point"}
}