{
  "type": "Feature",
  "properties": {
    "iso:country":"CA",
    "sg:address":"4791 Hwy 28",
    "sg:city":"Burleigh Falls",
    "sg:classifiers":[
        {
            "category":"Travel",
            "subcategory":"Hotels & Motels",
            "type":"Entertainment"
        }
    ],
    "sg:phone":"+1 705 654 3441",
    "sg:postcode":"K0L 1K0",
    "sg:province":"ON",
    "sg:tags":[
        "resort"
    ],
    "wof:name":"Burliegh Island Lodge & Spa",
    "wof:placetype":"venue"
},
  "geometry": {"coordinates":[-78.20970916749999,44.5614013672],"type":"Point"}
}