{
  "type": "Feature",
  "properties": {
    "iso:country":"CA",
    "sg:address":"18 Wilson W",
    "sg:city":"Little Current",
    "sg:classifiers":[
        {
            "category":"Building & Trades",
            "subcategory":"Plumbing",
            "type":"Services"
        }
    ],
    "sg:phone":"+1 705 368 2460",
    "sg:postcode":"P0P 1K0",
    "sg:province":"ON",
    "sg:tags":[
        "refrigeration",
        "contractor"
    ],
    "wof:name":"Perry Refrigeration & Ac",
    "wof:placetype":"venue"
},
  "geometry": {"coordinates":[-81.92395019529999,45.9752426147],"type":"Point"}
}