{
  "type": "Feature",
  "properties": {
    "addr:full":"5760 Cedarbridge Way Richmond BC V6X 2A7",
    "addr:housenumber":"5760",
    "addr:postcode":"v6x 2a7",
    "addr:street":"Cedarbridge Way",
    "iso:country":"CA",
    "sg:address":"5760 Cedarbridge Way",
    "sg:city":"Richmond",
    "sg:classifiers":[
        {
            "category":"Retail",
            "subcategory":"Laundry & Dry Cleaning",
            "type":"Services"
        }
    ],
    "sg:phone":"+1 604 270 2866",
    "sg:postcode":"V6X 2A7",
    "sg:province":"BC",
    "wof:name":"Prosperity Laundry Svc",
    "wof:placetype":"venue"
},
  "geometry": {"coordinates":[-123.14196,49.173576],"type":"Point"}
}