{
  "type": "Feature",
  "properties": {
    "addr:full":"Boisbriand QC J7G 1A9",
    "addr:postcode":"j7g 1a9",
    "iso:country":"CA",
    "sg:city":"Boisbriand",
    "sg:classifiers":[
        {
            "category":"Personal",
            "subcategory":"Shoe Repair & Shine",
            "type":"Services"
        }
    ],
    "sg:phone":"+1 450 430 4848",
    "sg:postcode":"J7G 1A9",
    "sg:province":"QC",
    "sg:tags":[
        "repairing",
        "boot"
    ],
    "wof:name":"Cordonnerie Eric",
    "wof:placetype":"venue"
},
  "geometry": {"coordinates":[-73.834976,45.605858],"type":"Point"}
}