{
  "type": "Feature",
  "properties": {
    "addr:full":"100 Macgregor Ave Stellarton NS B0K 1S0",
    "addr:housenumber":"100",
    "addr:postcode":"b0k 1s0",
    "addr:street":"Macgregor Ave",
    "iso:country":"CA",
    "sg:address":"100 Macgregor Ave",
    "sg:city":"Stellarton",
    "sg:classifiers":[
        {
            "category":"Freight",
            "type":"Transportation"
        }
    ],
    "sg:phone":"+1 902 755 5656",
    "sg:postcode":"B0K 1S0",
    "sg:province":"NS",
    "sg:tags":[
        "mover",
        "commercial"
    ],
    "wof:name":"Metro Self Storage",
    "wof:placetype":"venue"
},
  "geometry": {"coordinates":[-62.677795,45.567364],"type":"Point"}
}