{
  "type": "Feature",
  "properties": {
    "addr:full":"Ottawa ON K1V 7P2",
    "addr:postcode":"k1v 7p2",
    "iso:country":"CA",
    "sg:city":"Ottawa",
    "sg:classifiers":[
        {
            "category":"Insurance",
            "subcategory":"Insurance Agent",
            "type":"Services"
        }
    ],
    "sg:phone":"+1 613 232 5704",
    "sg:postcode":"K1V 7P2",
    "sg:province":"ON",
    "wof:name":"Tanner Insurance Svc Ltd",
    "wof:placetype":"venue"
},
  "geometry": {"coordinates":[-75.6389465332,45.3793678284],"type":"Point"}
}