{
  "type": "Feature",
  "properties": {
    "iso:country":"CA",
    "sg:city":"Medicine Hat",
    "sg:classifiers":[
        {
            "category":"Autos & Motor Vehicles",
            "subcategory":"Auto Supplies",
            "type":"Retail Goods"
        }
    ],
    "sg:phone":"+1 403 526 3088",
    "sg:postcode":"T1A 2W2",
    "sg:province":"AB",
    "sg:tags":[
        "automobile",
        "parts"
    ],
    "wof:name":"City Auto Parts",
    "wof:placetype":"venue"
},
  "geometry": {"coordinates":[-110.663971,50.031998],"type":"Point"}
}