{
  "type": "Feature",
  "properties": {
    "addr:full":"607 Rue Tessier Rimouski QC G5L 4M2",
    "addr:housenumber":"607",
    "addr:postcode":"g5l 4m2",
    "addr:street":"Rue Tessier",
    "iso:country":"CA",
    "sg:address":"607 Rue Tessier",
    "sg:city":"Rimouski",
    "sg:classifiers":[
        {
            "category":"Government",
            "subcategory":"Office",
            "type":"Public Place"
        }
    ],
    "sg:phone":"+1 418 727 3704",
    "sg:postcode":"G5L 4M2",
    "sg:province":"QC",
    "wof:name":"Quebec Transports",
    "wof:placetype":"venue"
},
  "geometry": {"coordinates":[-68.54810333250001,48.4228401184],"type":"Point"}
}