{
  "type": "Feature",
  "properties": {
    "addr:full":"8 Isaac Athens ON K0E 1B0",
    "addr:housenumber":"8",
    "addr:postcode":"k0e 1b0",
    "addr:street":"Isaac Athens",
    "iso:country":"CA",
    "sg:address":"8 Isaac",
    "sg:city":"Athens",
    "sg:classifiers":[
        {
            "category":"Building & Trades",
            "subcategory":"Electrical",
            "type":"Services"
        }
    ],
    "sg:phone":"+1 613 924 2601",
    "sg:postcode":"K0E 1B0",
    "sg:province":"ON",
    "sg:tags":[
        "electric",
        "contractor"
    ],
    "wof:name":"Doug Greenham Electric",
    "wof:placetype":"venue"
},
  "geometry": {"coordinates":[-75.94942500000001,44.624229],"type":"Point"}
}