{
  "type": "Feature",
  "properties": {
    "addr:full":"1379 Boul Sainte-Marguerite Mercier QC J6R 2L1",
    "addr:housenumber":"1379",
    "addr:postcode":"j6r 2l1",
    "addr:street":"Boul Sainte-Marguerite",
    "iso:country":"CA",
    "sg:address":"1379 Boul Sainte-Marguerite",
    "sg:city":"Mercier",
    "sg:classifiers":[
        {
            "category":"Wholesale",
            "subcategory":"Machinery & Supplies",
            "type":"Manufacturing & Wholesale Goods"
        }
    ],
    "sg:phone":"+1 450 691 2207",
    "sg:postcode":"J6R 2L1",
    "sg:province":"QC",
    "sg:tags":[
        "engine"
    ],
    "wof:name":"Direct Diesel Inc",
    "wof:placetype":"venue"
},
  "geometry": {"coordinates":[-73.73838000000001,45.288322],"type":"Point"}
}