{
  "type": "Feature",
  "properties": {
    "addr:full":"1160 Rue Chartrand LA Plaine QC J7M 2B1",
    "addr:housenumber":"1160",
    "addr:postcode":"j7m 2b1",
    "addr:street":"Rue Chartrand",
    "iso:country":"CA",
    "sg:address":"1160 Rue Chartrand",
    "sg:city":"LA Plaine",
    "sg:classifiers":[
        {
            "category":"Food & Beverages",
            "subcategory":"Groceries & Convenience Stores",
            "type":"Retail Goods"
        }
    ],
    "sg:phone":"+1 450 477 8805",
    "sg:postcode":"J7M 2B1",
    "sg:province":"QC",
    "sg:tags":[
        "grocer"
    ],
    "wof:name":"Depanneur Place Chartrand",
    "wof:placetype":"venue"
},
  "geometry": {"coordinates":[-73.706085,45.751713],"type":"Point"}
}