{
  "type": "Feature",
  "properties": {
    "addr:full":"175 Industry Rd Kingsville ON N9Y 1K9",
    "addr:housenumber":"175",
    "addr:postcode":"n9y 1k9",
    "addr:street":"Industry Rd",
    "iso:country":"CA",
    "sg:address":"175 Industry Rd",
    "sg:city":"Kingsville",
    "sg:classifiers":[
        {
            "category":"Manufacturing",
            "subcategory":"Tools & Machinery",
            "type":"Manufacturing & Wholesale Goods"
        }
    ],
    "sg:phone":"+1 519 733 2389",
    "sg:postcode":"N9Y 1K9",
    "sg:province":"ON",
    "sg:tags":[
        "equipment",
        "material",
        "handling"
    ],
    "wof:name":"Delta 70 Mfg Ltd",
    "wof:placetype":"venue"
},
  "geometry": {"coordinates":[-82.7309341431,42.0307312012],"type":"Point"}
}