{
  "type": "Feature",
  "properties": {
    "addr:full":"1050 Grande Ligne Roxton Pond QC J0E 1Z0",
    "addr:housenumber":"1050",
    "addr:postcode":"j0e 1z0",
    "addr:street":"Grande Ligne",
    "iso:country":"CA",
    "sg:address":"1050 Grande Ligne",
    "sg:city":"Roxton Pond",
    "sg:classifiers":[
        {
            "category":"Manufacturing",
            "subcategory":"Wood Products",
            "type":"Manufacturing & Wholesale Goods"
        }
    ],
    "sg:phone":"+1 450 372 1280",
    "sg:postcode":"J0E 1Z0",
    "sg:province":"QC",
    "sg:tags":[
        "pallet",
        "equipment",
        "material",
        "handling"
    ],
    "wof:name":"Entreprises Jap Enr",
    "wof:placetype":"venue"
},
  "geometry": {"coordinates":[-72.6580657959,45.5359764099],"type":"Point"}
}