{
  "type": "Feature",
  "properties": {
    "addr:full":"646 Alpha St Victoria BC V8Z 1B2",
    "addr:housenumber":"646",
    "addr:postcode":"v8z 1b2",
    "addr:street":"Alpha St",
    "iso:country":"CA",
    "sg:address":"646 Alpha St",
    "sg:city":"Victoria",
    "sg:classifiers":[
        {
            "category":"Home & Garden",
            "subcategory":"Furniture",
            "type":"Retail Goods"
        }
    ],
    "sg:phone":"+1 250 383 1926",
    "sg:postcode":"V8Z 1B2",
    "sg:province":"BC",
    "sg:tags":[
        "top",
        "counter"
    ],
    "wof:name":"Colonial Countertops",
    "wof:placetype":"venue"
},
  "geometry": {"coordinates":[-123.373329,48.447292],"type":"Point"}
}