{
  "type": "Feature",
  "properties": {
    "addr:full":"2925 Rte Marie-Victorin Sorel-Tracy QC J3R 1N6",
    "addr:housenumber":"2925",
    "addr:postcode":"j3r 1n6",
    "addr:street":"Rte Marie-Victorin",
    "iso:country":"CA",
    "sg:address":"2925 Rte Marie-Victorin",
    "sg:city":"Sorel-Tracy",
    "sg:classifiers":[
        {
            "category":"Recreation",
            "type":"Entertainment"
        }
    ],
    "sg:phone":"+1 450 743 2826",
    "sg:postcode":"J3R 1N6",
    "sg:province":"QC",
    "sg:tags":[
        "hall",
        "pub",
        "auditorium"
    ],
    "wof:name":"Brasserie St-Louis",
    "wof:placetype":"venue"
},
  "geometry": {"coordinates":[-73.1536102295,46.0314559937],"type":"Point"}
}