{
  "type": "Feature",
  "properties": {
    "addr:full":"174 Rte 237 S Frelighsburg QC J0J 1C0",
    "addr:housenumber":"174",
    "addr:postcode":"j0j 1c0",
    "addr:street":"Rte 237 S",
    "iso:country":"CA",
    "sg:address":"174 Rte 237 S",
    "sg:city":"Frelighsburg",
    "sg:classifiers":[
        {
            "category":"Travel",
            "subcategory":"Campground",
            "type":"Entertainment"
        }
    ],
    "sg:phone":"+1 450 298 5259",
    "sg:postcode":"J0J 1C0",
    "sg:province":"QC",
    "wof:name":"Camping Ecologique Enr",
    "wof:placetype":"venue"
},
  "geometry": {"coordinates":[-72.82315800000001,45.024666],"type":"Point"}
}