{
  "type": "Feature",
  "properties": {
    "iso:country":"CA",
    "sg:city":"Innisfail",
    "sg:classifiers":[
        {
            "category":"Freight",
            "type":"Transportation"
        }
    ],
    "sg:phone":"+1 403 227 7210",
    "sg:postcode":"T4G 1T4",
    "sg:province":"AB",
    "sg:tags":[
        "bus",
        "line",
        "courier"
    ],
    "wof:name":"Greyhound Canada",
    "wof:placetype":"venue"
},
  "geometry": {"coordinates":[-113.944969177,52.0202407837],"type":"Point"}
}