{
  "type": "Feature",
  "properties": {
    "addr:full":"Nepean ON K2E 7Y5",
    "addr:postcode":"k2e 7y5",
    "iso:country":"CA",
    "sg:city":"Nepean",
    "sg:classifiers":[
        {
            "category":"Home & Garden",
            "subcategory":"Furniture",
            "type":"Retail Goods"
        }
    ],
    "sg:phone":"+1 613 228 3109",
    "sg:postcode":"K2E 7Y5",
    "sg:province":"ON",
    "sg:tags":[
        "kitchen",
        "maker",
        "cabinet"
    ],
    "wof:name":"D Marinelli Custom Woodwork",
    "wof:placetype":"venue"
},
  "geometry": {"coordinates":[-75.711929,45.328506],"type":"Point"}
}