{
  "type": "Feature",
  "properties": {
    "addr:full":"110 8E Av Drummondville QC J2B 2R6",
    "addr:housenumber":"110",
    "addr:postcode":"j2b 2r6",
    "addr:street":"8E Av",
    "iso:country":"CA",
    "sg:address":"110 8E Av",
    "sg:city":"Drummondville",
    "sg:classifiers":[
        {
            "category":"Wholesale",
            "subcategory":"Hardware",
            "type":"Manufacturing & Wholesale Goods"
        }
    ],
    "sg:phone":"+1 819 477 4360",
    "sg:postcode":"J2B 2R6",
    "sg:province":"QC",
    "sg:tags":[
        "refrigerating"
    ],
    "wof:name":"Refrigeration Den-Mar Inc",
    "wof:placetype":"venue"
},
  "geometry": {"coordinates":[-72.49090576170001,45.8725318909],"type":"Point"}
}