{
  "type": "Feature",
  "properties": {
    "addr:full":"1154 Morningside Ave Scarborough ON M1B 3A4",
    "addr:housenumber":"1154",
    "addr:postcode":"m1b 3a4",
    "addr:street":"Morningside Ave",
    "iso:country":"CA",
    "sg:address":"1154 Morningside Ave",
    "sg:city":"Scarborough",
    "sg:classifiers":[
        {
            "category":"Personal",
            "subcategory":"Beauty Salon",
            "type":"Services"
        }
    ],
    "sg:phone":"+1 416 287 9998",
    "sg:postcode":"M1B 3A4",
    "sg:province":"ON",
    "wof:name":"Koscuts Hair Salon",
    "wof:placetype":"venue"
},
  "geometry": {"coordinates":[-79.19963799999999,43.801167],"type":"Point"}
}