{
  "type": "Feature",
  "properties": {
    "addr:full":"5959 Anderson St # L3 Whitby ON L1M 2E9",
    "addr:housenumber":"5959;# l3",
    "addr:postcode":"l1m 2e9",
    "addr:street":"Anderson St",
    "iso:country":"CA",
    "sg:address":"5959 Anderson St # L3",
    "sg:city":"Whitby",
    "sg:classifiers":[
        {
            "category":"Health Services",
            "subcategory":"Health Practitioner",
            "type":"Services"
        }
    ],
    "sg:phone":"+1 905 655 7776",
    "sg:postcode":"L1M 2E9",
    "sg:province":"ON",
    "sg:tags":[
        "physiotherapist",
        "therapist",
        "massage"
    ],
    "wof:name":"Brooklin Village Physiotherapy",
    "wof:placetype":"venue"
},
  "geometry": {"coordinates":[-78.94663199999999,43.955826],"type":"Point"}
}