{
  "type": "Feature",
  "properties": {
    "iso:country":"CA",
    "sg:address":"4747 Boul Levesque E",
    "sg:city":"Laval",
    "sg:classifiers":[
        {
            "category":"Retail",
            "subcategory":"Auto Repair",
            "type":"Services"
        }
    ],
    "sg:phone":"+1 450 661 7066",
    "sg:postcode":"H7C 1M9",
    "sg:province":"QC",
    "sg:tags":[
        "repairing",
        "automobile"
    ],
    "wof:name":"Frechette Station Svc Inc",
    "wof:placetype":"venue"
},
  "geometry": {"coordinates":[-73.645142,45.607071],"type":"Point"}
}