{
  "type": "Feature",
  "properties": {
    "addr:full":"Nanaimo BC V9S 4M4",
    "addr:postcode":"v9s 4m4",
    "iso:country":"CA",
    "sg:city":"Nanaimo",
    "sg:classifiers":[
        {
            "category":"Building & Trades",
            "subcategory":"Electrical",
            "type":"Services"
        }
    ],
    "sg:phone":"+1 250 758 3011",
    "sg:postcode":"V9S 4M4",
    "sg:province":"BC",
    "sg:tags":[
        "electric",
        "contractor"
    ],
    "wof:name":"Houle Electric Ltd",
    "wof:placetype":"venue"
},
  "geometry": {"coordinates":[-123.982727,49.193222],"type":"Point"}
}