{
  "type": "Feature",
  "properties": {
    "addr:full":"432 Rectory St London ON N5W 3W4",
    "addr:housenumber":"432",
    "addr:postcode":"n5w 3w4",
    "addr:street":"Rectory St",
    "iso:country":"CA",
    "sg:address":"432 Rectory St",
    "sg:city":"London",
    "sg:classifiers":[
        {
            "category":"Professional",
            "subcategory":"Business Services",
            "type":"Services"
        }
    ],
    "sg:phone":"+1 519 433 0777",
    "sg:postcode":"N5W 3W4",
    "sg:province":"ON",
    "sg:tags":[
        "recording",
        "studio"
    ],
    "wof:name":"Location Audio Recorders",
    "wof:placetype":"venue"
},
  "geometry": {"coordinates":[-81.224129,42.990002],"type":"Point"}
}