{
  "type": "Feature",
  "properties": {
    "addr:full":"Montreal QC H3B 2S2",
    "addr:postcode":"h3b 2s2",
    "iso:country":"CA",
    "sg:city":"Montreal",
    "sg:classifiers":[
        {
            "category":"Retail",
            "subcategory":"Repair Shop",
            "type":"Services"
        }
    ],
    "sg:phone":"+1 514 861 2985",
    "sg:postcode":"H3B 2S2",
    "sg:province":"QC",
    "sg:tags":[
        "watch"
    ],
    "wof:name":"Helvetia Service Des Montres",
    "wof:placetype":"venue"
},
  "geometry": {"coordinates":[-73.55331420900001,45.5158615112],"type":"Point"}
}