{
  "type": "Feature",
  "properties": {
    "addr:full":"5 Tallforest Cres Etobicoke ON M9C 2X1",
    "addr:housenumber":"5",
    "addr:postcode":"m9c 2x1",
    "addr:street":"Tallforest Cres",
    "iso:country":"CA",
    "sg:address":"5 Tallforest Cres",
    "sg:city":"Etobicoke",
    "sg:classifiers":[
        {
            "category":"Professional",
            "subcategory":"Management & Consulting",
            "type":"Services"
        }
    ],
    "sg:phone":"+1 416 621 7000",
    "sg:postcode":"M9C 2X1",
    "sg:province":"ON",
    "sg:tags":[
        "promotion",
        "sales"
    ],
    "wof:name":"Promolink Marketing Ltd",
    "wof:placetype":"venue"
},
  "geometry": {"coordinates":[-79.5804367065,43.6354904175],"type":"Point"}
}