{
  "type": "Feature",
  "properties": {
    "addr:full":"3355 Rue Dandurand Montreal QC H1X 1M7",
    "addr:housenumber":"3355",
    "addr:postcode":"h1x 1m7",
    "addr:street":"Rue Dandurand",
    "iso:country":"CA",
    "sg:address":"3355 Rue Dandurand",
    "sg:city":"Montreal",
    "sg:classifiers":[
        {
            "category":"Organizations",
            "subcategory":"Professional Association",
            "type":"Services"
        }
    ],
    "sg:phone":"+1 514 722 3252",
    "sg:postcode":"H1X 1M7",
    "sg:province":"QC",
    "wof:name":"Plast Ukrainian Youth Assn",
    "wof:placetype":"venue"
},
  "geometry": {"coordinates":[-73.5759277344,45.5528793335],"type":"Point"}
}