{
  "type": "Feature",
  "properties": {
    "iso:country":"CA",
    "sg:address":"2605 Rue Hertel",
    "sg:city":"Sherbrooke",
    "sg:classifiers":[
        {
            "category":"Manufacturing",
            "subcategory":"Printing",
            "type":"Manufacturing & Wholesale Goods"
        }
    ],
    "sg:phone":"+1 819 566 7611",
    "sg:postcode":"J1J 2J4",
    "sg:province":"QC",
    "sg:tags":[
        "printer"
    ],
    "wof:name":"Imprimerie Hln Inc",
    "wof:placetype":"venue"
},
  "geometry": {"coordinates":[-71.936241,45.39613],"type":"Point"}
}