{
  "type": "Feature",
  "properties": {
    "iso:country":"CA",
    "sg:city":"Saint-Leonard",
    "sg:classifiers":[
        {
            "category":"Health Services",
            "subcategory":"Doctor",
            "type":"Services"
        }
    ],
    "sg:phone":"+1 514 253 1306",
    "sg:postcode":"H1S 1M8",
    "sg:province":"QC",
    "sg:tags":[
        "dentist"
    ],
    "wof:name":"Ciccocioppo, Sebastien DDS",
    "wof:placetype":"venue"
},
  "geometry": {"coordinates":[-73.575287,45.591522],"type":"Point"}
}