{
  "type": "Feature",
  "properties": {
    "iso:country":"CA",
    "sg:address":"26 Facer St",
    "sg:city":"St Catharines",
    "sg:classifiers":[
        {
            "category":"Travel",
            "subcategory":"Travel Agent",
            "type":"Entertainment"
        }
    ],
    "sg:phone":"+1 905 937 4991",
    "sg:postcode":"L2M 5H3",
    "sg:province":"ON",
    "sg:tags":[
        "agency",
        "bureau"
    ],
    "wof:name":"Aris Travel Ltd",
    "wof:placetype":"venue"
},
  "geometry": {"coordinates":[-79.227165,43.174992],"type":"Point"}
}