{
  "type": "Feature",
  "properties": {
    "addr:full":"500 Church St Toronto ON M4Y 2C8",
    "addr:housenumber":"500",
    "addr:postcode":"m4y 2c8",
    "addr:street":"Church St",
    "iso:country":"CA",
    "sg:address":"500 Church St",
    "sg:city":"Toronto",
    "sg:classifiers":[
        {
            "category":"Restaurant",
            "type":"Food & Drink"
        }
    ],
    "sg:phone":"+1 416 925 8550",
    "sg:postcode":"M4Y 2C8",
    "sg:province":"ON",
    "wof:name":"Timothy's World Coffee",
    "wof:placetype":"venue"
},
  "geometry": {"coordinates":[-79.38028,43.66378],"type":"Point"}
}