{
  "type": "Feature",
  "properties": {
    "addr:full":"Lloydminster AB T9V 2R9",
    "addr:postcode":"t9v 2r9",
    "iso:country":"CA",
    "sg:city":"Lloydminster",
    "sg:classifiers":[
        {
            "category":"Mining & Drilling",
            "type":"Manufacturing & Wholesale Goods"
        }
    ],
    "sg:phone":"+1 780 875 7744",
    "sg:postcode":"T9V 2R9",
    "sg:province":"AB",
    "sg:tags":[
        "field",
        "oil",
        "general",
        "contractor"
    ],
    "wof:name":"Prodahl Enterprise Ltd",
    "wof:placetype":"venue"
},
  "geometry": {"coordinates":[-110.029930115,53.2754707336],"type":"Point"}
}