{
  "type": "Feature",
  "properties": {
    "addr:full":"555 Southgate Dr Guelph ON N1G 3W6",
    "addr:housenumber":"555",
    "addr:postcode":"n1g 3w6",
    "addr:street":"Southgate Dr",
    "iso:country":"CA",
    "sg:address":"555 Southgate Dr",
    "sg:city":"Guelph",
    "sg:classifiers":[
        {
            "category":"Wholesale",
            "subcategory":"Chemicals & Plastics",
            "type":"Manufacturing & Wholesale Goods"
        }
    ],
    "sg:phone":"+1 519 826 7666",
    "sg:postcode":"N1G 3W6",
    "sg:province":"ON",
    "wof:name":"Chemcentral Canada",
    "wof:placetype":"venue"
},
  "geometry": {"coordinates":[-80.215912,43.495934],"type":"Point"}
}