{
  "type": "Feature",
  "properties": {
    "addr:full":"18 Plaza Dr Dundas ON L9H 4H4",
    "addr:housenumber":"18",
    "addr:postcode":"l9h 4h4",
    "addr:street":"Plaza Dr",
    "iso:country":"CA",
    "sg:address":"18 Plaza Dr",
    "sg:city":"Dundas",
    "sg:classifiers":[
        {
            "category":"Shopping",
            "subcategory":"Gifts & Souvenirs",
            "type":"Retail Goods"
        }
    ],
    "sg:phone":"+1 905 627 0402",
    "sg:postcode":"L9H 4H4",
    "sg:province":"ON",
    "sg:tags":[
        "cards",
        "shop",
        "greeting"
    ],
    "wof:name":"Hallmark",
    "wof:placetype":"venue"
},
  "geometry": {"coordinates":[-79.9432678223,43.2593383789],"type":"Point"}
}