{
  "type": "Feature",
  "properties": {
    "addr:full":"11 Airport Rd NW Edmonton AB T5G 0W6",
    "addr:housenumber":"11",
    "addr:postcode":"t5g 0w6",
    "addr:street":"Airport Rd Nw",
    "iso:country":"CA",
    "sg:address":"11 Airport Rd NW",
    "sg:city":"Edmonton",
    "sg:classifiers":[
        {
            "category":"Airport",
            "type":"Transportation"
        }
    ],
    "sg:phone":"+1 780 454 2129",
    "sg:postcode":"T5G 0W6",
    "sg:province":"AB",
    "sg:tags":[
        "aircraft",
        "maintenance"
    ],
    "wof:name":"Alberta Aero Engine Ltd",
    "wof:placetype":"venue"
},
  "geometry": {"coordinates":[-113.51866099999999,53.566181],"type":"Point"}
}