{
  "type": "Feature",
  "properties": {
    "iso:country":"CA",
    "sg:address":"9720 60 Ave NW",
    "sg:city":"Edmonton",
    "sg:classifiers":[
        {
            "category":"Manufacturing",
            "subcategory":"Metals",
            "type":"Manufacturing & Wholesale Goods"
        }
    ],
    "sg:phone":"+1 780 435 3400",
    "sg:postcode":"T6E 0C5",
    "sg:province":"AB",
    "sg:tags":[
        "steel"
    ],
    "wof:name":"Premier Steel Inc",
    "wof:placetype":"venue"
},
  "geometry": {"coordinates":[-113.480407715,53.496006012],"type":"Point"}
}