{
  "type": "Feature",
  "properties": {
    "addr:full":"Picture Butte AB T0K 1V0",
    "addr:postcode":"t0k 1v0",
    "iso:country":"CA",
    "sg:city":"Picture Butte",
    "sg:classifiers":[
        {
            "category":"Professional",
            "subcategory":"Accounting & Tax Preparation",
            "type":"Services"
        }
    ],
    "sg:phone":"+1 403 732 4469",
    "sg:postcode":"T0K 1V0",
    "sg:province":"AB",
    "sg:tags":[
        "accountant"
    ],
    "wof:name":"Bdo Dunwoody",
    "wof:placetype":"venue"
},
  "geometry": {"coordinates":[-112.77944946300001,49.8777732849],"type":"Point"}
}