{
  "type": "Feature",
  "properties": {
    "addr:full":"144 Yorkville Ave Toronto ON M5R 1C2",
    "addr:housenumber":"144",
    "addr:postcode":"m5r 1c2",
    "addr:street":"Yorkville Ave",
    "iso:country":"CA",
    "sg:address":"144 Yorkville Ave",
    "sg:city":"Toronto",
    "sg:classifiers":[
        {
            "category":"Shopping",
            "subcategory":"Clothing, Apparel, & Fashions",
            "type":"Retail Goods"
        }
    ],
    "sg:phone":"+1 416 960 3096",
    "sg:postcode":"M5R 1C2",
    "sg:province":"ON",
    "sg:tags":[
        "leather"
    ],
    "wof:name":"Bart Leather Fashions",
    "wof:placetype":"venue"
},
  "geometry": {"coordinates":[-79.39376799999999,43.670719],"type":"Point"}
}