{
  "type": "Feature",
  "properties": {
    "iso:country":"CA",
    "sg:address":"7512 144 Ave NW",
    "sg:city":"Edmonton",
    "sg:classifiers":[
        {
            "category":"Education",
            "subcategory":"School",
            "type":"Public Place"
        }
    ],
    "sg:phone":"+1 780 476 0606",
    "sg:postcode":"T5C 2R7",
    "sg:province":"AB",
    "wof:name":"Father Leo Green Elementary",
    "wof:placetype":"venue"
},
  "geometry": {"coordinates":[-113.456665039,53.607208252],"type":"Point"}
}