{
  "type": "Feature",
  "properties": {
    "addr:full":"135 Gardiner Dr Hamilton ON L9C 5W7",
    "addr:housenumber":"135",
    "addr:postcode":"l9c 5w7",
    "addr:street":"Gardiner Dr",
    "iso:country":"CA",
    "sg:address":"135 Gardiner Dr",
    "sg:city":"Hamilton",
    "sg:classifiers":[
        {
            "category":"Building & Trades",
            "subcategory":"Landscaping Services",
            "type":"Services"
        }
    ],
    "sg:phone":"+1 905 388 8799",
    "sg:postcode":"L9C 5W7",
    "sg:province":"ON",
    "sg:tags":[
        "landscape",
        "contractor"
    ],
    "wof:name":"Vince's Landscaping Svc",
    "wof:placetype":"venue"
},
  "geometry": {"coordinates":[-79.9150466919,43.2192192078],"type":"Point"}
}