{
  "type": "Feature",
  "properties": {
    "addr:full":"810 Commissioners Rd E London ON N6C 2V5",
    "addr:housenumber":"810",
    "addr:postcode":"n6c 2v5",
    "addr:street":"Commissioners Rd E",
    "iso:country":"CA",
    "sg:address":"810 Commissioners Rd E",
    "sg:city":"London",
    "sg:classifiers":[
        {
            "category":"Health Services",
            "subcategory":"Clinic",
            "type":"Services"
        }
    ],
    "sg:phone":"+1 519 681 7330",
    "sg:postcode":"N6C 2V5",
    "sg:province":"ON",
    "sg:tags":[
        "home",
        "first",
        "aid"
    ],
    "wof:name":"Canadian Red Cross Society",
    "wof:placetype":"venue"
},
  "geometry": {"coordinates":[-81.225418,42.958527],"type":"Point"}
}