{
  "type": "Feature",
  "properties": {
    "addr:full":"Mont-Laurier QC J9L 1K5",
    "addr:postcode":"j9l 1k5",
    "iso:country":"CA",
    "sg:city":"Mont-Laurier",
    "sg:classifiers":[
        {
            "category":"Insurance",
            "subcategory":"Insurance Agent",
            "type":"Services"
        }
    ],
    "sg:phone":"+1 819 623 2855",
    "sg:postcode":"J9L 1K5",
    "sg:province":"QC",
    "wof:name":"Assurances L L'Allier Ltee",
    "wof:placetype":"venue"
},
  "geometry": {"coordinates":[-75.5006484985,46.5490989685],"type":"Point"}
}