{
  "type": "Feature",
  "properties": {
    "addr:full":"115 Boul Canam N Saint-Gedeon-DE-Beauce QC G0M 1T0",
    "addr:housenumber":"115",
    "addr:postcode":"g0m 1t0",
    "addr:street":"Boul Canam N",
    "iso:country":"CA",
    "sg:address":"115 Boul Canam N",
    "sg:city":"Saint-Gedeon-DE-Beauce",
    "sg:classifiers":[
        {
            "category":"Manufacturing",
            "subcategory":"Metals",
            "type":"Manufacturing & Wholesale Goods"
        }
    ],
    "sg:phone":"+1 418 582 3331",
    "sg:postcode":"G0M 1T0",
    "sg:province":"QC",
    "sg:tags":[
        "steel"
    ],
    "wof:name":"Canam Steel Works",
    "wof:placetype":"venue"
},
  "geometry": {"coordinates":[-70.635055542,45.8579978943],"type":"Point"}
}