{
  "type": "Feature",
  "properties": {
    "addr:full":"795 Rue Alain Sainte-Foy QC G1X 4C8",
    "addr:housenumber":"795",
    "addr:postcode":"g1x 4c8",
    "addr:street":"Rue Alain",
    "iso:country":"CA",
    "sg:address":"795 Rue Alain",
    "sg:city":"Sainte-Foy",
    "sg:classifiers":[
        {
            "category":"Health Services",
            "subcategory":"Nursing And Care Facility",
            "type":"Services"
        }
    ],
    "sg:phone":"+1 418 658 6550",
    "sg:postcode":"G1X 4C8",
    "sg:province":"QC",
    "sg:tags":[
        "house",
        "retirement",
        "retreat",
        "community",
        "home"
    ],
    "wof:name":"Logidor Inc",
    "wof:placetype":"venue"
},
  "geometry": {"coordinates":[-71.335556,46.764217],"type":"Point"}
}