{
  "type": "Feature",
  "properties": {
    "addr:full":"1105 5th Ave Humboldt SK S0K 2A0",
    "addr:housenumber":"1105",
    "addr:postcode":"s0k 2a0",
    "addr:street":"5Th Ave",
    "iso:country":"CA",
    "sg:address":"1105 5th Ave",
    "sg:city":"Humboldt",
    "sg:classifiers":[
        {
            "category":"Wholesale",
            "subcategory":"Petroleum",
            "type":"Manufacturing & Wholesale Goods"
        }
    ],
    "sg:phone":"+1 306 682 2675",
    "sg:postcode":"S0K 2A0",
    "sg:province":"SK",
    "sg:tags":[
        "oil"
    ],
    "wof:name":"Imperial Oil Ltd",
    "wof:placetype":"venue"
},
  "geometry": {"coordinates":[-105.12838000000001,52.198025],"type":"Point"}
}