{
  "type": "Feature",
  "properties": {
    "addr:full":"10427 Yonge St Richmond Hill ON L4C 3C2",
    "addr:housenumber":"10427",
    "addr:postcode":"l4c 3c2",
    "addr:street":"Yonge St",
    "iso:country":"CA",
    "sg:address":"10427 Yonge St",
    "sg:city":"Richmond Hill",
    "sg:classifiers":[
        {
            "category":"Retail",
            "subcategory":"Auto Repair",
            "type":"Services"
        }
    ],
    "sg:phone":"+1 905 884 1141",
    "sg:postcode":"L4C 3C2",
    "sg:province":"ON",
    "sg:tags":[
        "body",
        "automobile",
        "painting"
    ],
    "wof:name":"Town Auto Body",
    "wof:placetype":"venue"
},
  "geometry": {"coordinates":[-79.43944500000001,43.881561],"type":"Point"}
}