{
  "type": "Feature",
  "properties": {
    "addr:full":"London ON N6L 1E7",
    "addr:postcode":"n6l 1e7",
    "iso:country":"CA",
    "sg:city":"London",
    "sg:classifiers":[
        {
            "category":"Building & Trades",
            "subcategory":"Construction",
            "type":"Services"
        }
    ],
    "sg:phone":"+1 519 652 0588",
    "sg:postcode":"N6L 1E7",
    "sg:province":"ON",
    "sg:tags":[
        "elevator"
    ],
    "wof:name":"Silver Cross London",
    "wof:placetype":"venue"
},
  "geometry": {"coordinates":[-81.26683800000001,42.92012],"type":"Point"}
}