{
  "type": "Feature",
  "properties": {
    "addr:full":"23 Wellington St N # 265 St Marys ON N4X 1B7",
    "addr:housenumber":"23",
    "addr:postcode":"n4x 1b7",
    "addr:street":"Wellington St N # 265",
    "iso:country":"CA",
    "sg:address":"23 Wellington St N # 265",
    "sg:city":"St Marys",
    "sg:classifiers":[
        {
            "category":"Organizations",
            "subcategory":"Community Association",
            "type":"Services"
        }
    ],
    "sg:phone":"+1 519 284 4390",
    "sg:postcode":"N4X 1B7",
    "sg:province":"ON",
    "sg:tags":[
        "club"
    ],
    "wof:name":"Army & Navy Air Force Veterans",
    "wof:placetype":"venue"
},
  "geometry": {"coordinates":[-81.14208984379999,43.26014328],"type":"Point"}
}