{
  "type": "Feature",
  "properties": {
    "addr:full":"1688 Boul Des Laurentides Vimont QC H7M 2P4",
    "addr:housenumber":"1688",
    "addr:postcode":"h7m 2p4",
    "addr:street":"Boul Des Laurentides",
    "iso:country":"CA",
    "sg:address":"1688 Boul Des Laurentides",
    "sg:city":"Vimont",
    "sg:classifiers":[
        {
            "category":"Health Services",
            "subcategory":"Health Practitioner",
            "type":"Services"
        }
    ],
    "sg:phone":"+1 450 621 3028",
    "sg:postcode":"H7M 2P4",
    "sg:province":"QC",
    "sg:tags":[
        "psychologist"
    ],
    "wof:name":"Cartier, Yves",
    "wof:placetype":"venue"
},
  "geometry": {"coordinates":[-73.7213973999,45.5961532593],"type":"Point"}
}