{
  "type": "Feature",
  "properties": {
    "addr:full":"103 Rue Du Parc Saint-Patrice-DE-Beaurivage QC G0S 1B0",
    "addr:housenumber":"103",
    "addr:postcode":"g0s 1b0",
    "addr:street":"Rue Du Parc",
    "iso:country":"CA",
    "sg:address":"103 Rue Du Parc",
    "sg:city":"Saint-Patrice-DE-Beaurivage",
    "sg:classifiers":[
        {
            "category":"Wholesale",
            "subcategory":"Metals & Minerals",
            "type":"Manufacturing & Wholesale Goods"
        }
    ],
    "sg:phone":"+1 418 596 2606",
    "sg:postcode":"G0S 1B0",
    "sg:province":"QC",
    "sg:tags":[
        "aluminum"
    ],
    "wof:name":"Moulures 2000 Inc",
    "wof:placetype":"venue"
},
  "geometry": {"coordinates":[-71.24232499999999,46.407066],"type":"Point"}
}