{
  "type": "Feature",
  "properties": {
    "addr:full":"4862 Athalmer Rd Invermere BC V0A 1K3",
    "addr:housenumber":"4862",
    "addr:postcode":"v0a 1k3",
    "addr:street":"Athalmer Rd",
    "iso:country":"CA",
    "sg:address":"4862 Athalmer Rd",
    "sg:city":"Invermere",
    "sg:classifiers":[
        {
            "category":"Home & Garden",
            "subcategory":"Carpets & Floor Coverings",
            "type":"Retail Goods"
        }
    ],
    "sg:phone":"+1 250 342 3221",
    "sg:postcode":"V0A 1K3",
    "sg:province":"BC",
    "sg:tags":[
        "dealer",
        "rug"
    ],
    "wof:name":"Abbey Carpets-Invermere",
    "wof:placetype":"venue"
},
  "geometry": {"coordinates":[-116.03037261999999,50.5091705322],"type":"Point"}
}