{
  "type": "Feature",
  "properties": {
    "addr:full":"200 Welland Ave St Catharines ON L2R 2P3",
    "addr:housenumber":"200",
    "addr:postcode":"l2r 2p3",
    "addr:street":"Welland Ave",
    "iso:country":"CA",
    "sg:address":"200 Welland Ave",
    "sg:city":"St Catharines",
    "sg:classifiers":[
        {
            "category":"Insurance",
            "subcategory":"Insurance Agent",
            "type":"Services"
        }
    ],
    "sg:phone":"+1 905 688 4080",
    "sg:postcode":"L2R 2P3",
    "sg:province":"ON",
    "wof:name":"Market Place Ins & Financial",
    "wof:placetype":"venue"
},
  "geometry": {"coordinates":[-79.2391586304,43.1660041809],"type":"Point"}
}