{
  "type": "Feature",
  "properties": {
    "addr:full":"North York ON M3K 2B5",
    "addr:postcode":"m3k 2b5",
    "iso:country":"CA",
    "sg:city":"North York",
    "sg:classifiers":[
        {
            "category":"Food & Beverages",
            "subcategory":"Bakery",
            "type":"Retail Goods"
        }
    ],
    "sg:phone":"+1 416 222 1111",
    "sg:postcode":"M3K 2B5",
    "sg:province":"ON",
    "sg:tags":[
        "frozen"
    ],
    "wof:name":"Almost Perfect",
    "wof:placetype":"venue"
},
  "geometry": {"coordinates":[-79.4688873291,43.7537345886],"type":"Point"}
}