{
  "type": "Feature",
  "properties": {
    "iso:country":"CA",
    "sg:address":"2 East Beaver Creek Rd",
    "sg:city":"Richmond Hill",
    "sg:classifiers":[
        {
            "category":"Wholesale",
            "subcategory":"Electrical",
            "type":"Manufacturing & Wholesale Goods"
        }
    ],
    "sg:phone":"+1 905 886 6960",
    "sg:postcode":"L4B 2N3",
    "sg:province":"ON",
    "sg:tags":[
        "equipment",
        "television",
        "station"
    ],
    "wof:name":"Acura Technology Group Inc",
    "wof:placetype":"venue"
},
  "geometry": {"coordinates":[-79.385208,43.857132],"type":"Point"}
}