{
  "type": "Feature",
  "properties": {
    "addr:full":"401 20th St W Saskatoon SK S7M 0X3",
    "addr:housenumber":"401",
    "addr:postcode":"s7m 0x3",
    "addr:street":"20Th St W",
    "iso:country":"CA",
    "sg:address":"401 20th St W",
    "sg:city":"Saskatoon",
    "sg:classifiers":[
        {
            "category":"Food & Beverages",
            "subcategory":"Liquor & Beverages",
            "type":"Retail Goods"
        }
    ],
    "sg:phone":"+1 306 933 5312",
    "sg:postcode":"S7M 0X3",
    "sg:province":"SK",
    "sg:tags":[
        "store"
    ],
    "wof:name":"Liquor Store",
    "wof:placetype":"venue"
},
  "geometry": {"coordinates":[-106.675331,52.126064],"type":"Point"}
}