{
  "type": "Feature",
  "properties": {
    "addr:full":"North York ON M9M 2E7",
    "addr:postcode":"m9m 2e7",
    "iso:country":"CA",
    "sg:city":"North York",
    "sg:classifiers":[
        {
            "category":"Shopping",
            "subcategory":"Computers & Home Electronics",
            "type":"Retail Goods"
        }
    ],
    "sg:phone":"+1 416 745 1900",
    "sg:postcode":"M9M 2E7",
    "sg:province":"ON",
    "sg:tags":[
        "television",
        "radio"
    ],
    "wof:name":"Ben Thanh Electronics",
    "wof:placetype":"venue"
},
  "geometry": {"coordinates":[-79.55027,43.750252],"type":"Point"}
}