{
  "type": "Feature",
  "properties": {
    "addr:full":"20 Eveningside Rd Thornhill ON L3T 4K2",
    "addr:housenumber":"20",
    "addr:postcode":"l3t 4k2",
    "addr:street":"Eveningside Rd",
    "iso:country":"CA",
    "sg:address":"20 Eveningside Rd",
    "sg:city":"Thornhill",
    "sg:classifiers":[
        {
            "category":"Manufacturing",
            "subcategory":"Apparel",
            "type":"Manufacturing & Wholesale Goods"
        }
    ],
    "sg:phone":"+1 905 882 0106",
    "sg:postcode":"L3T 4K2",
    "sg:province":"ON",
    "sg:tags":[
        "clothing"
    ],
    "wof:name":"Eugene Corporate Neckwear",
    "wof:placetype":"venue"
},
  "geometry": {"coordinates":[-79.36696600000001,43.821018],"type":"Point"}
}