{
  "type": "Feature",
  "properties": {
    "addr:full":"700 Main St W Hamilton ON L8S 1A5",
    "addr:housenumber":"700",
    "addr:postcode":"l8s 1a5",
    "addr:street":"Main St W",
    "iso:country":"CA",
    "sg:address":"700 Main St W",
    "sg:city":"Hamilton",
    "sg:classifiers":[
        {
            "category":"Education",
            "subcategory":"School",
            "type":"Public Place"
        }
    ],
    "sg:phone":"+1 905 522 1387",
    "sg:postcode":"L8S 1A5",
    "sg:province":"ON",
    "wof:name":"Westdale School",
    "wof:placetype":"venue"
},
  "geometry": {"coordinates":[-79.89788799999999,43.260147],"type":"Point"}
}