{
  "type": "Feature",
  "properties": {
    "addr:full":"633 Main St Woodstock NB E7M 2C6",
    "addr:housenumber":"633",
    "addr:postcode":"e7m 2c6",
    "addr:street":"Main St",
    "iso:country":"CA",
    "sg:address":"633 Main St",
    "sg:city":"Woodstock",
    "sg:classifiers":[
        {
            "category":"Real Estate",
            "subcategory":"Developer",
            "type":"Services"
        }
    ],
    "sg:phone":"+1 506 328 3540",
    "sg:postcode":"E7M 2C6",
    "sg:province":"NB",
    "wof:name":"Central Holdings",
    "wof:placetype":"venue"
},
  "geometry": {"coordinates":[-67.573463,46.150032],"type":"Point"}
}