{
  "type": "Feature",
  "properties": {
    "addr:full":"12519 125 St NW Edmonton AB T5L 0T4",
    "addr:housenumber":"12519",
    "addr:postcode":"t5l 0t4",
    "addr:street":"125 St Nw",
    "iso:country":"CA",
    "sg:address":"12519 125 St NW",
    "sg:city":"Edmonton",
    "sg:classifiers":[
        {
            "category":"Retail",
            "subcategory":"Auto Repair",
            "type":"Services"
        }
    ],
    "sg:phone":"+1 780 482 1944",
    "sg:postcode":"T5L 0T4",
    "sg:province":"AB",
    "sg:tags":[
        "repairing",
        "automobile"
    ],
    "wof:name":"Bent Willow Automotive Svc",
    "wof:placetype":"venue"
},
  "geometry": {"coordinates":[-113.537514,53.581249],"type":"Point"}
}