{
  "type": "Feature",
  "properties": {
    "iso:country":"CA",
    "sg:city":"Anjou",
    "sg:classifiers":[
        {
            "category":"Banks & Credit Unions",
            "subcategory":"Investment Brokerage",
            "type":"Services"
        }
    ],
    "sg:phone":"+1 514 493 4151",
    "sg:postcode":"H1M 3N8",
    "sg:province":"QC",
    "sg:tags":[
        "consultant",
        "planning",
        "financial"
    ],
    "wof:name":"London Life Insurance CO",
    "wof:placetype":"venue"
},
  "geometry": {"coordinates":[-73.56968688960001,45.5984230042],"type":"Point"}
}