{
  "type": "Feature",
  "properties": {
    "addr:full":"79 Laurentian Dr Kitchener ON N2E 1C3",
    "addr:housenumber":"79",
    "addr:postcode":"n2e 1c3",
    "addr:street":"Laurentian Dr",
    "iso:country":"CA",
    "sg:address":"79 Laurentian Dr",
    "sg:city":"Kitchener",
    "sg:classifiers":[
        {
            "category":"Education",
            "subcategory":"School",
            "type":"Public Place"
        }
    ],
    "sg:phone":"+1 519 743 6368",
    "sg:postcode":"N2E 1C3",
    "sg:province":"ON",
    "wof:name":"Trillium Public School",
    "wof:placetype":"venue"
},
  "geometry": {"coordinates":[-80.496674,43.418159],"type":"Point"}
}