{
  "type": "Feature",
  "properties": {
    "addr:full":"6 Havelock St Truro NS B2N 4B7",
    "addr:housenumber":"6",
    "addr:postcode":"b2n 4b7",
    "addr:street":"Havelock St",
    "iso:country":"CA",
    "sg:address":"6 Havelock St",
    "sg:city":"Truro",
    "sg:classifiers":[
        {
            "category":"Shopping",
            "subcategory":"Jewelry",
            "type":"Retail Goods"
        }
    ],
    "sg:phone":"+1 902 895 0478",
    "sg:postcode":"B2N 4B7",
    "sg:province":"NS",
    "sg:tags":[
        "watch"
    ],
    "wof:name":"Gold 'N Watch",
    "wof:placetype":"venue"
},
  "geometry": {"coordinates":[-63.2757720947,45.3642883301],"type":"Point"}
}