{
  "type": "Feature",
  "properties": {
    "iso:country":"CA",
    "sg:address":"6939 Farrell Rd SE",
    "sg:city":"Calgary",
    "sg:classifiers":[
        {
            "category":"Professional",
            "type":"Services"
        }
    ],
    "sg:phone":"+1 403 252 1307",
    "sg:postcode":"T2H 0T3",
    "sg:province":"AB",
    "sg:tags":[
        "geophysical"
    ],
    "wof:name":"Datum Exploration Ltd",
    "wof:placetype":"venue"
},
  "geometry": {"coordinates":[-114.062515,50.991917],"type":"Point"}
}