{
  "type": "Feature",
  "properties": {
    "addr:full":"Lac Du Bonnet MB R0E 1A0",
    "addr:postcode":"r0e 1a0",
    "iso:country":"CA",
    "sg:city":"Lac Du Bonnet",
    "sg:classifiers":[
        {
            "category":"Home & Garden",
            "subcategory":"Building Materials",
            "type":"Retail Goods"
        }
    ],
    "sg:phone":"+1 204 345 2810",
    "sg:postcode":"R0E 1A0",
    "sg:province":"MB",
    "sg:tags":[
        "windows"
    ],
    "wof:name":"Lee-Way Glass",
    "wof:placetype":"venue"
},
  "geometry": {"coordinates":[-96.06197400000001,50.251629],"type":"Point"}
}