{
  "type": "Feature",
  "properties": {
    "addr:full":"Simcoe ON N3Y 4K2",
    "addr:postcode":"n3y 4k2",
    "iso:country":"CA",
    "sg:city":"Simcoe",
    "sg:classifiers":[
        {
            "category":"Retail",
            "subcategory":"Animal Services",
            "type":"Services"
        }
    ],
    "sg:phone":"+1 519 428 3647",
    "sg:postcode":"N3Y 4K2",
    "sg:province":"ON",
    "sg:tags":[
        "pet",
        "breeder",
        "dog"
    ],
    "wof:name":"Gagent Holdings",
    "wof:placetype":"venue"
},
  "geometry": {"coordinates":[-80.299644,42.797928],"type":"Point"}
}