{
  "type": "Feature",
  "properties": {
    "iso:country":"CA",
    "sg:address":"364 Hamilton Rd",
    "sg:city":"London",
    "sg:classifiers":[
        {
            "category":"Home & Garden",
            "subcategory":"Building Materials",
            "type":"Retail Goods"
        }
    ],
    "sg:phone":"+1 519 438 5246",
    "sg:postcode":"N5Z 1R5",
    "sg:province":"ON",
    "sg:tags":[
        "windows"
    ],
    "wof:name":"W D Smith Aluminum Prods Ltd",
    "wof:placetype":"venue"
},
  "geometry": {"coordinates":[-81.221642,42.980988],"type":"Point"}
}