{
  "type": "Feature",
  "properties": {
    "addr:full":"Port Moody BC V3H 1Z4",
    "addr:postcode":"v3h 1z4",
    "iso:country":"CA",
    "sg:city":"Port Moody",
    "sg:classifiers":[
        {
            "category":"Education",
            "subcategory":"Dance Studio",
            "type":"Public Place"
        }
    ],
    "sg:phone":"+1 604 936 0966",
    "sg:postcode":"V3H 1Z4",
    "sg:province":"BC",
    "sg:tags":[
        "instruction",
        "dancing"
    ],
    "wof:name":"Port Moody School of Dance",
    "wof:placetype":"venue"
},
  "geometry": {"coordinates":[-122.854057,49.27771],"type":"Point"}
}