{
  "type": "Feature",
  "properties": {
    "addr:full":"3041 Sherman Dr Prince Albert SK S6V 7B7",
    "addr:housenumber":"3041",
    "addr:postcode":"s6v 7b7",
    "addr:street":"Sherman Dr",
    "iso:country":"CA",
    "sg:address":"3041 Sherman Dr",
    "sg:city":"Prince Albert",
    "sg:classifiers":[
        {
            "category":"Social Services",
            "type":"Services"
        }
    ],
    "sg:phone":"+1 306 922 3247",
    "sg:postcode":"S6V 7B7",
    "sg:province":"SK",
    "sg:tags":[
        "organization",
        "welfare"
    ],
    "wof:name":"Early Childhood Intervention",
    "wof:placetype":"venue"
},
  "geometry": {"coordinates":[-105.717522,53.183685],"type":"Point"}
}