{
  "type": "Feature",
  "properties": {
    "iso:country":"CA",
    "sg:city":"Delta",
    "sg:classifiers":[
        {
            "category":"Manufacturing",
            "subcategory":"Metals",
            "type":"Manufacturing & Wholesale Goods"
        }
    ],
    "sg:phone":"+1 604 940 0070",
    "sg:postcode":"V4G 1M5",
    "sg:province":"BC",
    "sg:tags":[
        "plate",
        "name"
    ],
    "wof:name":"Western Nameplates",
    "wof:placetype":"venue"
},
  "geometry": {"coordinates":[-123.023971558,49.1335906982],"type":"Point"}
}