{
  "type": "Feature",
  "properties": {
    "iso:country":"CA",
    "sg:address":"200 Rg 10",
    "sg:city":"Lefebvre",
    "sg:classifiers":[
        {
            "category":"Organizations",
            "subcategory":"Religious Organization",
            "type":"Services"
        }
    ],
    "sg:phone":"+1 819 394 2587",
    "sg:postcode":"J0H 2C0",
    "sg:province":"QC",
    "sg:tags":[
        "church"
    ],
    "wof:name":"Presbytere Ste-Jeanne D'Arc",
    "wof:placetype":"venue"
},
  "geometry": {"coordinates":[-72.412399,45.712132],"type":"Point"}
}