{
  "type": "Feature",
  "properties": {
    "iso:country":"CA",
    "sg:address":"9480 Finn Rd",
    "sg:city":"Richmond",
    "sg:classifiers":[
        {
            "category":"Building & Trades",
            "subcategory":"Landscaping Services",
            "type":"Services"
        }
    ],
    "sg:phone":"+1 604 271 6520",
    "sg:postcode":"V7A 2L4",
    "sg:province":"BC",
    "sg:tags":[
        "lawn",
        "maintenance",
        "grounds"
    ],
    "wof:name":"West Coast Horticultural Svc",
    "wof:placetype":"venue"
},
  "geometry": {"coordinates":[-123.119178772,49.1187973022],"type":"Point"}
}