{
  "type": "Feature",
  "properties": {
    "addr:full":"1025 Davie St Vancouver BC V6E 1M5",
    "addr:housenumber":"1025",
    "addr:postcode":"v6e 1m5",
    "addr:street":"Davie St",
    "iso:country":"CA",
    "sg:address":"1025 Davie St",
    "sg:city":"Vancouver",
    "sg:classifiers":[
        {
            "category":"Bars & Pubs",
            "type":"Food & Drink"
        }
    ],
    "sg:phone":"+1 604 687 2222",
    "sg:postcode":"V6E 1M5",
    "sg:province":"BC",
    "wof:name":"Fountainhead Pub",
    "wof:placetype":"venue"
},
  "geometry": {"coordinates":[-123.129654,49.279564],"type":"Point"}
}