{
  "type": "Feature",
  "properties": {
    "iso:country":"CA",
    "sg:city":"Peterborough",
    "sg:classifiers":[
        {
            "category":"Autos & Motor Vehicles",
            "subcategory":"Boat Sales",
            "type":"Retail Goods"
        }
    ],
    "sg:phone":"+1 705 876 7979",
    "sg:postcode":"K9J 6X5",
    "sg:province":"ON",
    "sg:tags":[
        "dealer"
    ],
    "wof:name":"Cus Consignment Specialists",
    "wof:placetype":"venue"
},
  "geometry": {"coordinates":[-78.321312,44.300732],"type":"Point"}
}