{
  "type": "Feature",
  "properties": {
    "iso:country":"CA",
    "sg:city":"Atikokan",
    "sg:classifiers":[
        {
            "category":"Professional",
            "subcategory":"Employment Agencies",
            "type":"Services"
        }
    ],
    "sg:phone":"+1 807 597 2485",
    "sg:postcode":"P0T 1C0",
    "sg:province":"ON",
    "sg:tags":[
        "opportunity"
    ],
    "wof:name":"Atikokan Employment Ctr",
    "wof:placetype":"venue"
},
  "geometry": {"coordinates":[-91.6235656738,48.7576179504],"type":"Point"}
}