{
  "type": "Feature",
  "properties": {
    "iso:country":"CA",
    "sg:city":"Thunder Bay",
    "sg:classifiers":[
        {
            "category":"Social Services",
            "type":"Services"
        }
    ],
    "sg:phone":"+1 807 344 1717",
    "sg:postcode":"P7A 4T6",
    "sg:province":"ON",
    "sg:tags":[
        "counselor",
        "marriage",
        "family"
    ],
    "wof:name":"Cummins, E Ruth PhD",
    "wof:placetype":"venue"
},
  "geometry": {"coordinates":[-89.220131,48.437302],"type":"Point"}
}