{
  "type": "Feature",
  "properties": {
    "iso:country":"CA",
    "sg:address":"4000 Chesswood Dr",
    "sg:city":"North York",
    "sg:classifiers":[
        {
            "category":"Recreation",
            "type":"Entertainment"
        }
    ],
    "sg:phone":"+1 416 635 5100",
    "sg:postcode":"M3J 2B9",
    "sg:province":"ON",
    "sg:tags":[
        "amusement"
    ],
    "wof:name":"Hockey Tech Intl",
    "wof:placetype":"venue"
},
  "geometry": {"coordinates":[-79.4755020142,43.7574310303],"type":"Point"}
}