{
  "type": "Feature",
  "properties": {
    "addr:full":"342 Tollendal Mill Rd Barrie ON L4N 7S6",
    "addr:housenumber":"342",
    "addr:postcode":"l4n 7s6",
    "addr:street":"Tollendal Mill Rd",
    "iso:country":"CA",
    "sg:address":"342 Tollendal Mill Rd",
    "sg:city":"Barrie",
    "sg:classifiers":[
        {
            "category":"Recreation",
            "subcategory":"Marina",
            "type":"Entertainment"
        }
    ],
    "sg:phone":"+1 705 722 8344",
    "sg:postcode":"L4N 7S6",
    "sg:province":"ON",
    "wof:name":"Brentwood Marine",
    "wof:placetype":"venue"
},
  "geometry": {"coordinates":[-79.65152,44.372292],"type":"Point"}
}