{
  "type": "Feature",
  "properties": {
    "iso:country":"CA",
    "sg:address":"975 Elgin St",
    "sg:city":"Cobourg",
    "sg:classifiers":[
        {
            "category":"Restaurant",
            "type":"Food & Drink"
        }
    ],
    "sg:phone":"+1 905 372 7212",
    "sg:postcode":"K9A 5J3",
    "sg:province":"ON",
    "wof:name":"Home Plate Pancake House",
    "wof:placetype":"venue"
},
  "geometry": {"coordinates":[-78.1406555176,43.9846801758],"type":"Point"}
}