{
  "type": "Feature",
  "properties": {
    "addr:full":"34 Queen St S Bolton ON L7E 1B3",
    "addr:housenumber":"34",
    "addr:postcode":"l7e 1b3",
    "addr:street":"Queen St S",
    "iso:country":"CA",
    "sg:address":"34 Queen St S",
    "sg:city":"Bolton",
    "sg:classifiers":[
        {
            "category":"Real Estate",
            "subcategory":"Real Estate Agent",
            "type":"Services"
        }
    ],
    "sg:phone":"+1 905 857 2791",
    "sg:postcode":"L7E 1B3",
    "sg:province":"ON",
    "sg:tags":[
        "appraiser"
    ],
    "wof:name":"Appraisal Services",
    "wof:placetype":"venue"
},
  "geometry": {"coordinates":[-79.737206,43.878754],"type":"Point"}
}