{
  "type": "Feature",
  "properties": {
    "addr:full":"12 Regent St Thorold ON L2V 1T1",
    "addr:housenumber":"12",
    "addr:postcode":"l2v 1t1",
    "addr:street":"Regent St",
    "iso:country":"CA",
    "sg:address":"12 Regent St",
    "sg:city":"Thorold",
    "sg:classifiers":[
        {
            "category":"Health Services",
            "subcategory":"Optometrist",
            "type":"Services"
        }
    ],
    "sg:phone":"+1 905 227 3937",
    "sg:postcode":"L2V 1T1",
    "sg:province":"ON",
    "wof:name":"Petra Cantrup & Assoc",
    "wof:placetype":"venue"
},
  "geometry": {"coordinates":[-79.1993942261,43.1270828247],"type":"Point"}
}