{
  "type": "Feature",
  "properties": {
    "addr:full":"818 43rd St E Saskatoon SK S7K 3V1",
    "addr:housenumber":"818",
    "addr:postcode":"s7k 3v1",
    "addr:street":"43Rd St E",
    "iso:country":"CA",
    "sg:address":"818 43rd St E",
    "sg:city":"Saskatoon",
    "sg:classifiers":[
        {
            "category":"Manufacturing",
            "subcategory":"Tools & Machinery",
            "type":"Manufacturing & Wholesale Goods"
        }
    ],
    "sg:phone":"+1 306 244 0423",
    "sg:postcode":"S7K 3V1",
    "sg:province":"SK",
    "sg:tags":[
        "contractor"
    ],
    "wof:name":"Wrt Equipment Ltd",
    "wof:placetype":"venue"
},
  "geometry": {"coordinates":[-106.652855,52.160442],"type":"Point"}
}