{
  "type": "Feature",
  "properties": {
    "iso:country":"CA",
    "sg:address":"818 43rd St E",
    "sg:city":"Saskatoon",
    "sg:classifiers":[
        {
            "category":"Manufacturing",
            "subcategory":"Tools & Machinery",
            "type":"Manufacturing & Wholesale Goods"
        }
    ],
    "sg:phone":"+1 306 244 0423",
    "sg:postcode":"S7K 3V1",
    "sg:province":"SK",
    "sg:tags":[
        "contractor"
    ],
    "wof:name":"Wrt Equipment Ltd",
    "wof:placetype":"venue"
},
  "geometry": {"coordinates":[-106.652855,52.160442],"type":"Point"}
}