{
  "type": "Feature",
  "properties": {
    "addr:full":"1111 42 Ave SE Calgary AB T2G 1Z3",
    "addr:housenumber":"1111",
    "addr:postcode":"t2g 1z3",
    "addr:street":"42 Ave Se",
    "iso:country":"CA",
    "sg:address":"1111 42 Ave SE",
    "sg:city":"Calgary",
    "sg:classifiers":[
        {
            "category":"Freight",
            "type":"Transportation"
        }
    ],
    "sg:phone":"+1 403 236 7869",
    "sg:postcode":"T2G 1Z3",
    "sg:province":"AB",
    "sg:tags":[
        "trucking"
    ],
    "wof:name":"Winfield Motor Freight Inc",
    "wof:placetype":"venue"
},
  "geometry": {"coordinates":[-114.03840599999999,51.015903],"type":"Point"}
}