{
  "type": "Feature",
  "properties": {
    "addr:full":"2915 Fulford-Ganges Rd Salt Spring Island BC V8K 1X6",
    "addr:housenumber":"2915",
    "addr:postcode":"v8k 1x6",
    "addr:street":"Fulford-Ganges Rd",
    "iso:country":"CA",
    "sg:address":"2915 Fulford-Ganges Rd",
    "sg:city":"Salt Spring Island",
    "sg:classifiers":[
        {
            "category":"Food & Beverages",
            "subcategory":"Groceries & Convenience Stores",
            "type":"Retail Goods"
        }
    ],
    "sg:phone":"+1 250 653 4321",
    "sg:postcode":"V8K 1X6",
    "sg:province":"BC",
    "sg:tags":[
        "grocer"
    ],
    "wof:name":"Patterson's Store",
    "wof:placetype":"venue"
},
  "geometry": {"coordinates":[-123.448554993,48.7704391479],"type":"Point"}
}