{
  "type": "Feature",
  "properties": {
    "iso:country":"CA",
    "sg:address":"332 Route 445",
    "sg:city":"Lagaceville",
    "sg:classifiers":[
        {
            "category":"Building & Trades",
            "subcategory":"Construction",
            "type":"Services"
        }
    ],
    "sg:phone":"+1 506 776 8582",
    "sg:postcode":"E9G 2P4",
    "sg:province":"NB",
    "sg:tags":[
        "roofing",
        "contractor"
    ],
    "wof:name":"Rejean Richard Roofing Ltd",
    "wof:placetype":"venue"
},
  "geometry": {"coordinates":[-65.174599,47.23093],"type":"Point"}
}