{
  "type": "Feature",
  "properties": {
    "addr:full":"3856 132 Rte Saint-Anicet QC J0S 1M0",
    "addr:housenumber":"3856",
    "addr:postcode":"j0s 1m0",
    "addr:street":"132 Rte",
    "iso:country":"CA",
    "sg:address":"3856 132 Rte",
    "sg:city":"Saint-Anicet",
    "sg:classifiers":[
        {
            "category":"Retail",
            "subcategory":"Auto Repair",
            "type":"Services"
        }
    ],
    "sg:phone":"+1 450 264 5579",
    "sg:postcode":"J0S 1M0",
    "sg:province":"QC",
    "sg:tags":[
        "repairing",
        "automobile"
    ],
    "wof:name":"Garage Lapierre Gerald Inc",
    "wof:placetype":"venue"
},
  "geometry": {"coordinates":[-74.395996,45.095112],"type":"Point"}
}