{
  "type": "Feature",
  "properties": {
    "iso:country":"CA",
    "sg:address":"632 Rue Jean-Delisle",
    "sg:city":"Aylmer",
    "sg:classifiers":[
        {
            "category":"Social Services",
            "subcategory":"Child Care",
            "type":"Services"
        }
    ],
    "sg:phone":"+1 819 684 9989",
    "sg:postcode":"J9H 6N3",
    "sg:province":"QC",
    "wof:name":"Garderie Chez Becassine",
    "wof:placetype":"venue"
},
  "geometry": {"coordinates":[-75.8397979736,45.4099082947],"type":"Point"}
}