{
  "type": "Feature",
  "properties": {
    "addr:full":"741 Rue Du Moulin Saint-Jean-Chrysostome QC G6Z 1X8",
    "addr:housenumber":"741",
    "addr:postcode":"g6z 1x8",
    "addr:street":"Rue Du Moulin Saint-Jean-Chrysostome",
    "iso:country":"CA",
    "sg:address":"741 Rue Du Moulin",
    "sg:city":"Saint-Jean-Chrysostome",
    "sg:classifiers":[
        {
            "category":"Arts & Performance",
            "subcategory":"Theater",
            "type":"Entertainment"
        }
    ],
    "sg:phone":"+1 418 839 7257",
    "sg:postcode":"G6Z 1X8",
    "sg:province":"QC",
    "sg:tags":[
        "music"
    ],
    "wof:name":"Centre Des Orchestres-Quebec",
    "wof:placetype":"venue"
},
  "geometry": {"coordinates":[-71.20079800000001,46.738052],"type":"Point"}
}