{
  "type": "Feature",
  "properties": {
    "addr:full":"1375 Weber St E Kitchener ON N2A 3Y7",
    "addr:housenumber":"1375",
    "addr:postcode":"n2a 3y7",
    "addr:street":"Weber St E",
    "iso:country":"CA",
    "sg:address":"1375 Weber St E",
    "sg:city":"Kitchener",
    "sg:classifiers":[
        {
            "category":"Banks & Credit Unions",
            "subcategory":"Bank",
            "type":"Services"
        }
    ],
    "sg:phone":"+1 519 885 9293",
    "sg:postcode":"N2A 3Y7",
    "sg:province":"ON",
    "wof:name":"Bank of Montreal",
    "wof:placetype":"venue"
},
  "geometry": {"coordinates":[-80.440483,43.432976],"type":"Point"}
}