{
  "type": "Feature",
  "properties": {
    "addr:full":"82 Brownstone Cir Thornhill ON L4J 7P6",
    "addr:housenumber":"82",
    "addr:postcode":"l4j 7p6",
    "addr:street":"Brownstone Cir",
    "iso:country":"CA",
    "sg:address":"82 Brownstone Cir",
    "sg:city":"Thornhill",
    "sg:classifiers":[
        {
            "category":"Organizations",
            "subcategory":"Religious Organization",
            "type":"Services"
        }
    ],
    "sg:phone":"+1 905 889 4588",
    "sg:postcode":"L4J 7P6",
    "sg:province":"ON",
    "sg:tags":[
        "church"
    ],
    "wof:name":"Brown Corners United Church",
    "wof:placetype":"venue"
},
  "geometry": {"coordinates":[-79.4250488281,43.8074798584],"type":"Point"}
}