{
  "type": "Feature",
  "properties": {
    "addr:full":"538 12 Ave SE Calgary AB T2G 1A6",
    "addr:postcode":"t2g 1a6",
    "addr:street":"538 12 Ave Se",
    "iso:country":"CA",
    "sg:address":"538 12 Ave SE",
    "sg:city":"Calgary",
    "sg:classifiers":[
        {
            "category":"Food & Beverages",
            "subcategory":"Groceries & Convenience Stores",
            "type":"Retail Goods"
        }
    ],
    "sg:phone":"+1 403 269 7271",
    "sg:postcode":"T2G 1A6",
    "sg:province":"AB",
    "sg:tags":[
        "grocer"
    ],
    "wof:name":"Stampede Grocery",
    "wof:placetype":"venue"
},
  "geometry": {"coordinates":[-114.05249000000001,51.041225],"type":"Point"}
}