{
  "type": "Feature",
  "properties": {
    "addr:full":"Main St Paradise Hill SK S0M 2G0",
    "addr:postcode":"s0m 2g0",
    "addr:street":"Main St",
    "iso:country":"CA",
    "sg:address":"Main St",
    "sg:city":"Paradise Hill",
    "sg:classifiers":[
        {
            "category":"Wholesale",
            "subcategory":"Petroleum",
            "type":"Manufacturing & Wholesale Goods"
        }
    ],
    "sg:phone":"+1 306 344 2175",
    "sg:postcode":"S0M 2G0",
    "sg:province":"SK",
    "sg:tags":[
        "fuel"
    ],
    "wof:name":"Petro-Canada",
    "wof:placetype":"venue"
},
  "geometry": {"coordinates":[-109.459159851,53.5389175415],"type":"Point"}
}