{
  "type": "Feature",
  "properties": {
    "addr:full":"92 Browning Blvd Winnipeg MB R3K 0L7",
    "addr:housenumber":"92",
    "addr:postcode":"r3k 0l7",
    "addr:street":"Browning Blvd",
    "iso:country":"CA",
    "sg:address":"92 Browning Blvd",
    "sg:city":"Winnipeg",
    "sg:classifiers":[
        {
            "category":"Personal",
            "subcategory":"Beauty Salon",
            "type":"Services"
        }
    ],
    "sg:phone":"+1 204 832 0009",
    "sg:postcode":"R3K 0L7",
    "sg:province":"MB",
    "wof:name":"Ultimate Design",
    "wof:placetype":"venue"
},
  "geometry": {"coordinates":[-97.29982757569999,49.8722572327],"type":"Point"}
}