{
  "type": "Feature",
  "properties": {
    "addr:full":"1790 Av Champfleury Quebec QC G1J 4M2",
    "addr:housenumber":"1790",
    "addr:postcode":"g1j 4m2",
    "addr:street":"Av Champfleury",
    "iso:country":"CA",
    "sg:address":"1790 Av Champfleury",
    "sg:city":"Quebec",
    "sg:classifiers":[
        {
            "category":"Restaurant",
            "type":"Food & Drink"
        }
    ],
    "sg:phone":"+1 418 660 5331",
    "sg:postcode":"G1J 4M2",
    "sg:province":"QC",
    "wof:name":"Restaurant Mai Lan",
    "wof:placetype":"venue"
},
  "geometry": {"coordinates":[-71.22187,46.838432],"type":"Point"}
}