{
  "type": "Feature",
  "properties": {
    "iso:country":"CA",
    "sg:city":"West Vancouver",
    "sg:classifiers":[
        {
            "category":"Health Services",
            "subcategory":"Doctor",
            "type":"Services"
        }
    ],
    "sg:phone":"+1 604 913 7717",
    "sg:postcode":"V7V 1J7",
    "sg:province":"BC",
    "sg:tags":[
        "physician",
        "surgeon"
    ],
    "wof:name":"Mc Bride, Judith A MD",
    "wof:placetype":"venue"
},
  "geometry": {"coordinates":[-123.163513,49.328785],"type":"Point"}
}