{
  "type": "Feature",
  "properties": {
    "addr:full":"2343 Main St Vancouver BC V5T 3C9",
    "addr:housenumber":"2343",
    "addr:postcode":"v5t 3c9",
    "addr:street":"Main St",
    "iso:country":"CA",
    "sg:address":"2343 Main St",
    "sg:city":"Vancouver",
    "sg:classifiers":[
        {
            "category":"Wholesale",
            "subcategory":"Vending Machines",
            "type":"Manufacturing & Wholesale Goods"
        }
    ],
    "sg:phone":"+1 604 872 5757",
    "sg:postcode":"V5T 3C9",
    "sg:province":"BC",
    "sg:tags":[
        "equipment",
        "ride",
        "park",
        "amusement"
    ],
    "wof:name":"John's Jukes Ltd",
    "wof:placetype":"venue"
},
  "geometry": {"coordinates":[-123.101128,49.264126],"type":"Point"}
}