{
  "type": "Feature",
  "properties": {
    "addr:full":"3177 Napperton Dr Strathroy ON N7G 3H8",
    "addr:housenumber":"3177",
    "addr:postcode":"n7g 3h8",
    "addr:street":"Napperton Dr",
    "iso:country":"CA",
    "sg:address":"3177 Napperton Dr",
    "sg:city":"Strathroy",
    "sg:classifiers":[
        {
            "category":"Manufacturing",
            "subcategory":"Signs",
            "type":"Manufacturing & Wholesale Goods"
        }
    ],
    "sg:phone":"+1 519 245 4189",
    "sg:postcode":"N7G 3H8",
    "sg:province":"ON",
    "wof:name":"Signs & Designs",
    "wof:placetype":"venue"
},
  "geometry": {"coordinates":[-81.622299,42.955772],"type":"Point"}
}