{
  "type": "Feature",
  "properties": {
    "addr:full":"24 the Square Goderich ON N7A 1M4",
    "addr:housenumber":"24",
    "addr:postcode":"n7a 1m4",
    "addr:street":"The Square",
    "iso:country":"CA",
    "sg:address":"24 the Square",
    "sg:city":"Goderich",
    "sg:classifiers":[
        {
            "category":"Banks & Credit Unions",
            "subcategory":"Bank",
            "type":"Services"
        }
    ],
    "sg:phone":"+1 519 524 8371",
    "sg:postcode":"N7A 1M4",
    "sg:province":"ON",
    "wof:name":"Cibc",
    "wof:placetype":"venue"
},
  "geometry": {"coordinates":[-81.707764,43.742641],"type":"Point"}
}