{
  "type": "Feature",
  "properties": {
    "iso:country":"CA",
    "sg:address":"263 Dunn Ave",
    "sg:city":"Toronto",
    "sg:classifiers":[
        {
            "category":"Food & Beverages",
            "subcategory":"Groceries & Convenience Stores",
            "type":"Retail Goods"
        }
    ],
    "sg:phone":"+1 416 537 3974",
    "sg:postcode":"M6K 2S1",
    "sg:province":"ON",
    "sg:tags":[
        "grocer"
    ],
    "wof:name":"A 1 Convenience",
    "wof:placetype":"venue"
},
  "geometry": {"coordinates":[-79.433883667,43.6399230957],"type":"Point"}
}