{
  "type": "Feature",
  "properties": {
    "addr:full":"902 Prom Du Saint-Maurice Shawinigan QC G9N 1L8",
    "addr:housenumber":"902",
    "addr:postcode":"g9n 1l8",
    "addr:street":"Prom Du Saint-Maurice",
    "iso:country":"CA",
    "sg:address":"902 Prom Du Saint-Maurice",
    "sg:city":"Shawinigan",
    "sg:classifiers":[
        {
            "category":"Restaurant",
            "type":"Food & Drink"
        }
    ],
    "sg:phone":"+1 819 537 7806",
    "sg:postcode":"G9N 1L8",
    "sg:province":"QC",
    "wof:name":"Restaurant LA Pinata Inc",
    "wof:placetype":"venue"
},
  "geometry": {"coordinates":[-72.75309799999999,46.539673],"type":"Point"}
}