{
  "type": "Feature",
  "properties": {
    "addr:full":"873 Bedford Hwy Bedford NS B4A 1A7",
    "addr:housenumber":"873",
    "addr:postcode":"b4a 1a7",
    "addr:street":"Bedford Hwy",
    "iso:country":"CA",
    "sg:address":"873 Bedford Hwy",
    "sg:city":"Bedford",
    "sg:classifiers":[
        {
            "category":"Food & Beverages",
            "subcategory":"Groceries & Convenience Stores",
            "type":"Retail Goods"
        }
    ],
    "sg:phone":"+1 902 835 3000",
    "sg:postcode":"B4A 1A7",
    "sg:province":"NS",
    "wof:name":"Ultramar Pipeline & Corner",
    "wof:placetype":"venue"
},
  "geometry": {"coordinates":[-63.6742515564,44.7127075195],"type":"Point"}
}