{
  "type": "Feature",
  "properties": {
    "iso:country":"CA",
    "sg:city":"Montreal",
    "sg:classifiers":[
        {
            "category":"Wholesale",
            "subcategory":"Medical Equipment & Supplies",
            "type":"Manufacturing & Wholesale Goods"
        }
    ],
    "sg:phone":"+1 514 722 2426",
    "sg:postcode":"H2E 2M3",
    "sg:province":"QC",
    "sg:tags":[
        "hospital"
    ],
    "wof:name":"Yelco Distributions Inc",
    "wof:placetype":"venue"
},
  "geometry": {"coordinates":[-73.60508,45.5494],"type":"Point"}
}