{
  "type": "Feature",
  "properties": {
    "iso:country":"CA",
    "sg:address":"265 Coxwell Ave",
    "sg:city":"Toronto",
    "sg:classifiers":[
        {
            "category":"Wholesale",
            "subcategory":"Durable Goods & Equipment",
            "type":"Manufacturing & Wholesale Goods"
        }
    ],
    "sg:phone":"+1 416 406 3770",
    "sg:postcode":"M4L 3B5",
    "sg:province":"ON",
    "sg:tags":[
        "importer"
    ],
    "wof:name":"Merchants Trading CO Ltd",
    "wof:placetype":"venue"
},
  "geometry": {"coordinates":[-79.3192901611,43.6733665466],"type":"Point"}
}