{
  "type": "Feature",
  "properties": {
    "addr:full":"Westville NS B0K 2A0",
    "addr:postcode":"b0k 2a0",
    "iso:country":"CA",
    "sg:city":"Westville",
    "sg:classifiers":[
        {
            "category":"Building & Trades",
            "subcategory":"Electrical",
            "type":"Services"
        }
    ],
    "sg:phone":"+1 902 396 1787",
    "sg:postcode":"B0K 2A0",
    "sg:province":"NS",
    "sg:tags":[
        "electric",
        "contractor"
    ],
    "wof:name":"Northumberland Electric",
    "wof:placetype":"venue"
},
  "geometry": {"coordinates":[-62.709908,45.56176],"type":"Point"}
}