{
  "type": "Feature",
  "properties": {
    "addr:full":"62 Shaft Rd Etobicoke ON M9W 4M2",
    "addr:housenumber":"62",
    "addr:postcode":"m9w 4m2",
    "addr:street":"Shaft Rd",
    "iso:country":"CA",
    "sg:address":"62 Shaft Rd",
    "sg:city":"Etobicoke",
    "sg:classifiers":[
        {
            "category":"Autos & Motor Vehicles",
            "subcategory":"Automobile Sales",
            "type":"Retail Goods"
        }
    ],
    "sg:phone":"+1 416 614 8210",
    "sg:postcode":"M9W 4M2",
    "sg:province":"ON",
    "sg:tags":[
        "car",
        "parts",
        "supply"
    ],
    "wof:name":"Prestige Collision Inc",
    "wof:placetype":"venue"
},
  "geometry": {"coordinates":[-79.5652770996,43.7022132874],"type":"Point"}
}