{
  "type": "Feature",
  "properties": {
    "addr:full":"Hull QC J8Z 2M4",
    "addr:postcode":"j8z 2m4",
    "iso:country":"CA",
    "sg:city":"Hull",
    "sg:classifiers":[
        {
            "category":"Retail",
            "subcategory":"Auto Repair",
            "type":"Services"
        }
    ],
    "sg:phone":"+1 819 778 2553",
    "sg:postcode":"J8Z 2M4",
    "sg:province":"QC",
    "sg:tags":[
        "repairing",
        "automobile"
    ],
    "wof:name":"Garage Du Parc Enr",
    "wof:placetype":"venue"
},
  "geometry": {"coordinates":[-75.7344589233,45.4686088562],"type":"Point"}
}