{
  "type": "Feature",
  "properties": {
    "addr:full":"1645 Minto Ave Windsor ON N9J 3H2",
    "addr:housenumber":"1645",
    "addr:postcode":"n9j 3h2",
    "addr:street":"Minto Ave",
    "iso:country":"CA",
    "sg:address":"1645 Minto Ave",
    "sg:city":"Windsor",
    "sg:classifiers":[
        {
            "category":"Shopping",
            "subcategory":"Computers & Home Electronics",
            "type":"Retail Goods"
        }
    ],
    "sg:phone":"+1 519 978 7888",
    "sg:postcode":"N9J 3H2",
    "sg:province":"ON",
    "sg:tags":[
        "equipment",
        "dealer"
    ],
    "wof:name":"AAA Computer Pro Svc",
    "wof:placetype":"venue"
},
  "geometry": {"coordinates":[-83.033913,42.317822],"type":"Point"}
}