{
  "type": "Feature",
  "properties": {
    "iso:country":"CA",
    "sg:address":"411 Victoria Ave",
    "sg:city":"Regina",
    "sg:classifiers":[
        {
            "category":"Home & Garden",
            "subcategory":"Building Materials",
            "type":"Retail Goods"
        }
    ],
    "sg:phone":"+1 306 757 1737",
    "sg:postcode":"S4N 0P7",
    "sg:province":"SK",
    "sg:tags":[
        "glass",
        "window",
        "plate"
    ],
    "wof:name":"Glass Suppliers & Installation",
    "wof:placetype":"venue"
},
  "geometry": {"coordinates":[-104.58678436300001,50.4469108582],"type":"Point"}
}