{
  "type": "Feature",
  "properties": {
    "iso:country":"CA",
    "sg:city":"Vancouver",
    "sg:classifiers":[
        {
            "category":"Food & Beverages",
            "subcategory":"Groceries & Convenience Stores",
            "type":"Retail Goods"
        }
    ],
    "sg:phone":"+1 604 224 5131",
    "sg:postcode":"V6T 1K6",
    "sg:province":"BC",
    "sg:tags":[
        "grocer"
    ],
    "wof:name":"Students Lucky Supermarket",
    "wof:placetype":"venue"
},
  "geometry": {"coordinates":[-123.242912292,49.2666053772],"type":"Point"}
}