{
  "type": "Feature",
  "properties": {
    "iso:country":"CA",
    "sg:address":"6520 Viscount Rd",
    "sg:city":"Mississauga",
    "sg:classifiers":[
        {
            "category":"Manufacturing",
            "subcategory":"Motor Vehicles & Parts",
            "type":"Manufacturing & Wholesale Goods"
        }
    ],
    "sg:phone":"+1 905 677 5763",
    "sg:postcode":"L4V 1H3",
    "sg:province":"ON",
    "sg:tags":[
        "automobile",
        "wrecking"
    ],
    "wof:name":"Factory Engine Exchange",
    "wof:placetype":"venue"
},
  "geometry": {"coordinates":[-79.6267166138,43.6954078674],"type":"Point"}
}