{
  "type": "Feature",
  "properties": {
    "iso:country":"CA",
    "sg:city":"Vancouver",
    "sg:classifiers":[
        {
            "category":"Shopping",
            "subcategory":"Clothing, Apparel, & Fashions",
            "type":"Retail Goods"
        }
    ],
    "sg:phone":"+1 604 688 0828",
    "sg:postcode":"V6B 2R9",
    "sg:province":"BC",
    "wof:name":"Zero Gravity Clothing Store",
    "wof:placetype":"venue"
},
  "geometry": {"coordinates":[-123.11998,49.276482],"type":"Point"}
}