{
  "type": "Feature",
  "properties": {
    "addr:full":"5012 Rig St Swan Hills AB T0G 2C0",
    "addr:postcode":"5012;t0g 2c0",
    "addr:street":"Rig St",
    "iso:country":"CA",
    "sg:address":"5012 Rig St",
    "sg:city":"Swan Hills",
    "sg:classifiers":[
        {
            "category":"Professional",
            "type":"Services"
        }
    ],
    "sg:phone":"+1 780 333 2747",
    "sg:postcode":"T0G 2C0",
    "sg:province":"AB",
    "sg:tags":[
        "pipe",
        "equipment",
        "line"
    ],
    "wof:name":"Gill's Vacuum Svc",
    "wof:placetype":"venue"
},
  "geometry": {"coordinates":[-115.40010833700001,54.7113685608],"type":"Point"}
}