{
  "type": "Feature",
  "properties": {
    "addr:full":"150 Rue Lemay Louiseville QC J5V 1A8",
    "addr:housenumber":"150",
    "addr:postcode":"j5v 1a8",
    "addr:street":"Rue Lemay",
    "iso:country":"CA",
    "sg:address":"150 Rue Lemay",
    "sg:city":"Louiseville",
    "sg:classifiers":[
        {
            "category":"Freight",
            "type":"Transportation"
        }
    ],
    "sg:phone":"+1 819 228 0736",
    "sg:postcode":"J5V 1A8",
    "sg:province":"QC",
    "sg:tags":[
        "trucking"
    ],
    "wof:name":"Transport Drassel Inc",
    "wof:placetype":"venue"
},
  "geometry": {"coordinates":[-72.934921,46.261658],"type":"Point"}
}