{
  "type": "Feature",
  "properties": {
    "addr:full":"Nepean ON K2E 7J5",
    "addr:postcode":"k2e 7j5",
    "iso:country":"CA",
    "sg:city":"Nepean",
    "sg:classifiers":[
        {
            "category":"Travel",
            "subcategory":"Travel Agent",
            "type":"Entertainment"
        }
    ],
    "sg:phone":"+1 613 224 4447",
    "sg:postcode":"K2E 7J5",
    "sg:province":"ON",
    "sg:tags":[
        "agency",
        "bureau"
    ],
    "wof:name":"Sharma Travel Agency",
    "wof:placetype":"venue"
},
  "geometry": {"coordinates":[-75.7099761963,45.342376709],"type":"Point"}
}