{
  "type": "Feature",
  "properties": {
    "addr:full":"332 Frankcom St Ajax ON L1S 1R5",
    "addr:housenumber":"332",
    "addr:postcode":"l1s 1r5",
    "addr:street":"Frankcom St",
    "iso:country":"CA",
    "sg:address":"332 Frankcom St",
    "sg:city":"Ajax",
    "sg:classifiers":[
        {
            "category":"Manufacturing",
            "subcategory":"Chemicals & Compounds",
            "type":"Manufacturing & Wholesale Goods"
        }
    ],
    "sg:phone":"+1 905 683 5400",
    "sg:postcode":"L1S 1R5",
    "sg:province":"ON",
    "sg:tags":[
        "plastic"
    ],
    "wof:name":"Dunlop Plastics Canada",
    "wof:placetype":"venue"
},
  "geometry": {"coordinates":[-79.03210449220001,43.8467102051],"type":"Point"}
}