{
  "type": "Feature",
  "properties": {
    "iso:country":"CA",
    "sg:address":"1129 Rue Saint-Jean",
    "sg:city":"Quebec",
    "sg:classifiers":[
        {
            "category":"Restaurant",
            "type":"Food & Drink"
        }
    ],
    "sg:phone":"+1 418 694 9218",
    "sg:postcode":"G1R 1S3",
    "sg:province":"QC",
    "wof:name":"Restaurant Le Retro",
    "wof:placetype":"venue"
},
  "geometry": {"coordinates":[-71.21028099999999,46.813889],"type":"Point"}
}