{
  "type": "Feature",
  "properties": {
    "iso:country":"CA",
    "sg:address":"920 20th St W",
    "sg:city":"Saskatoon",
    "sg:classifiers":[
        {
            "category":"Building & Trades",
            "subcategory":"Construction",
            "type":"Services"
        }
    ],
    "sg:phone":"+1 306 382 4884",
    "sg:postcode":"S7M 0Y4",
    "sg:province":"SK",
    "sg:tags":[
        "downspouts",
        "roofing",
        "gutter",
        "contractor"
    ],
    "wof:name":"Little Rainbow Roofing",
    "wof:placetype":"venue"
},
  "geometry": {"coordinates":[-106.683327,52.126408],"type":"Point"}
}