{
  "type": "Feature",
  "properties": {
    "addr:full":"150 132 Rte W New Richmond QC G0C 2B0",
    "addr:housenumber":"132",
    "addr:postcode":"g0c 2b0",
    "addr:street":"Rte W",
    "iso:country":"CA",
    "sg:address":"150 132 Rte W",
    "sg:city":"New Richmond",
    "sg:classifiers":[
        {
            "category":"Freight",
            "type":"Transportation"
        }
    ],
    "sg:phone":"+1 418 392 6000",
    "sg:postcode":"G0C 2B0",
    "sg:province":"QC",
    "sg:tags":[
        "commercial",
        "storage"
    ],
    "wof:name":"Mini Entrepot Moreau",
    "wof:placetype":"venue"
},
  "geometry": {"coordinates":[-65.85642199999999,48.160873],"type":"Point"}
}