{
  "type": "Feature",
  "properties": {
    "addr:full":"2970 Rue Girouard O Saint-Hyacinthe QC J2S 3B9",
    "addr:housenumber":"2970",
    "addr:postcode":"j2s 3b9",
    "addr:street":"Rue Girouard O",
    "iso:country":"CA",
    "sg:address":"2970 Rue Girouard O",
    "sg:city":"Saint-Hyacinthe",
    "sg:classifiers":[
        {
            "category":"Wholesale",
            "subcategory":"Durable Goods & Equipment",
            "type":"Manufacturing & Wholesale Goods"
        }
    ],
    "sg:phone":"+1 450 799 4876",
    "sg:postcode":"J2S 3B9",
    "sg:province":"QC",
    "sg:tags":[
        "representative",
        "manufacturer"
    ],
    "wof:name":"Lmh Canada Inc",
    "wof:placetype":"venue"
},
  "geometry": {"coordinates":[-72.95796199999999,45.618256],"type":"Point"}
}