{
  "type": "Feature",
  "properties": {
    "addr:full":"101 Upper Halfway Wonowon BC V0C 2N0",
    "addr:housenumber":"101",
    "addr:postcode":"bc v0c 2n0",
    "addr:street":"Upper Halfway",
    "iso:country":"CA",
    "sg:address":"101 Upper Halfway",
    "sg:city":"Wonowon",
    "sg:classifiers":[
        {
            "category":"Mining & Drilling",
            "type":"Manufacturing & Wholesale Goods"
        }
    ],
    "sg:phone":"+1 250 772 4900",
    "sg:postcode":"V0C 2N0",
    "sg:province":"BC",
    "sg:tags":[
        "development",
        "gas",
        "oil",
        "exploration"
    ],
    "wof:name":"Suncor Inc",
    "wof:placetype":"venue"
},
  "geometry": {"coordinates":[-121.81315600000001,56.731262],"type":"Point"}
}