{
  "type": "Feature",
  "properties": {
    "addr:full":"425 University Ave E Waterloo ON N2K 4C9",
    "addr:housenumber":"425",
    "addr:postcode":"n2k 4c9",
    "addr:street":"University Ave E",
    "iso:country":"CA",
    "sg:address":"425 University Ave E",
    "sg:city":"Waterloo",
    "sg:classifiers":[
        {
            "category":"Food & Beverages",
            "subcategory":"Bakery",
            "type":"Retail Goods"
        }
    ],
    "sg:phone":"+1 519 585 2146",
    "sg:postcode":"N2K 4C9",
    "sg:province":"ON",
    "sg:tags":[
        "doughnut"
    ],
    "wof:name":"Tim Hortons",
    "wof:placetype":"venue"
},
  "geometry": {"coordinates":[-80.4917602539,43.4908294678],"type":"Point"}
}