{
  "type": "Feature",
  "properties": {
    "addr:full":"135 North View Pl Salt Spring Island BC V8K 1A9",
    "addr:housenumber":"135",
    "addr:postcode":"v8k 1a9",
    "addr:street":"North View Pl",
    "iso:country":"CA",
    "sg:address":"135 North View Pl",
    "sg:city":"Salt Spring Island",
    "sg:classifiers":[
        {
            "category":"Local Transit",
            "type":"Transportation"
        }
    ],
    "sg:phone":"+1 250 537 4196",
    "sg:postcode":"V8K 1A9",
    "sg:province":"BC",
    "sg:tags":[
        "limousine"
    ],
    "wof:name":"Gulf Island Limousine Svc",
    "wof:placetype":"venue"
},
  "geometry": {"coordinates":[-123.57504299999999,48.930637],"type":"Point"}
}