{
  "type": "Feature",
  "properties": {
    "addr:full":"314 George St Wiarton ON N0H 2T0",
    "addr:housenumber":"314",
    "addr:postcode":"n0h 2t0",
    "addr:street":"George St",
    "iso:country":"CA",
    "sg:address":"314 George St",
    "sg:city":"Wiarton",
    "sg:classifiers":[
        {
            "category":"Social Services",
            "type":"Services"
        }
    ],
    "sg:phone":"+1 519 534 0553",
    "sg:postcode":"N0H 2T0",
    "sg:province":"ON",
    "sg:tags":[
        "organization",
        "welfare"
    ],
    "wof:name":"Bruce Peninsula Assn",
    "wof:placetype":"venue"
},
  "geometry": {"coordinates":[-81.141251,44.742054],"type":"Point"}
}