{
  "type": "Feature",
  "properties": {
    "addr:full":"927 King St E Cambridge ON N3H 3P4",
    "addr:housenumber":"927",
    "addr:postcode":"n3h 3p4",
    "addr:street":"King St E",
    "iso:country":"CA",
    "sg:address":"927 King St E",
    "sg:city":"Cambridge",
    "sg:classifiers":[
        {
            "category":"Professional",
            "type":"Services"
        }
    ],
    "sg:phone":"+1 519 653 8800",
    "sg:postcode":"N3H 3P4",
    "sg:province":"ON",
    "sg:tags":[
        "metal",
        "cleaning"
    ],
    "wof:name":"Hetworth Corp",
    "wof:placetype":"venue"
},
  "geometry": {"coordinates":[-80.35496500000001,43.394249],"type":"Point"}
}