{
  "type": "Feature",
  "properties": {
    "addr:full":"3525 24th Ave W Vancouver BC V6S 1L5",
    "addr:housenumber":"3525",
    "addr:postcode":"v6s 1l5",
    "addr:street":"24Th Ave W",
    "iso:country":"CA",
    "sg:address":"3525 24th Ave W",
    "sg:city":"Vancouver",
    "sg:classifiers":[
        {
            "category":"Social Services",
            "subcategory":"Child Care",
            "type":"Services"
        }
    ],
    "sg:phone":"+1 604 734 4013",
    "sg:postcode":"V6S 1L5",
    "sg:province":"BC",
    "wof:name":"Dragons & Butterflies Nursery",
    "wof:placetype":"venue"
},
  "geometry": {"coordinates":[-123.18277,49.251255],"type":"Point"}
}