{
  "type": "Feature",
  "properties": {
    "addr:full":"2397 Lasalle Blvd Sudbury ON P3A 2A9",
    "addr:housenumber":"2397",
    "addr:postcode":"p3a 2a9",
    "addr:street":"Lasalle Blvd",
    "iso:country":"CA",
    "sg:address":"2397 Lasalle Blvd",
    "sg:city":"Sudbury",
    "sg:classifiers":[
        {
            "category":"Home & Garden",
            "subcategory":"Garden Supply",
            "type":"Retail Goods"
        }
    ],
    "sg:phone":"+1 705 566 8845",
    "sg:postcode":"P3A 2A9",
    "sg:province":"ON",
    "sg:tags":[
        "equipment",
        "snow",
        "removal"
    ],
    "wof:name":"Superior After Market",
    "wof:placetype":"venue"
},
  "geometry": {"coordinates":[-80.91175800000001,46.521854],"type":"Point"}
}