{
  "type": "Feature",
  "properties": {
    "iso:country":"CA",
    "sg:address":"147 King St W",
    "sg:city":"Kitchener",
    "sg:classifiers":[
        {
            "category":"Shopping",
            "subcategory":"Shoes",
            "type":"Retail Goods"
        }
    ],
    "sg:phone":"+1 519 745 7442",
    "sg:postcode":"N2G 1A7",
    "sg:province":"ON",
    "wof:name":"Petsche's Shoes Ltd",
    "wof:placetype":"venue"
},
  "geometry": {"coordinates":[-80.49192810060001,43.4506988525],"type":"Point"}
}