{
  "type": "Feature",
  "properties": {
    "addr:full":"7627 Rue Centrale Lasalle QC H8P 1L1",
    "addr:housenumber":"7627",
    "addr:postcode":"h8p 1l1",
    "addr:street":"Rue Centrale",
    "iso:country":"CA",
    "sg:address":"7627 Rue Centrale",
    "sg:city":"Lasalle",
    "sg:classifiers":[
        {
            "category":"Health Services",
            "subcategory":"Health Practitioner",
            "type":"Services"
        }
    ],
    "sg:phone":"+1 514 367 1848",
    "sg:postcode":"H8P 1L1",
    "sg:province":"QC",
    "sg:tags":[
        "acupuncture"
    ],
    "wof:name":"Clinique D'Acupuncture-Lasalle",
    "wof:placetype":"venue"
},
  "geometry": {"coordinates":[-73.5978393555,45.4317779541],"type":"Point"}
}