{
  "type": "Feature",
  "properties": {
    "iso:country":"CA",
    "sg:address":"101 Worthington St E # 437",
    "sg:city":"North Bay",
    "sg:classifiers":[
        {
            "category":"Organizations",
            "subcategory":"Professional Association",
            "type":"Services"
        }
    ],
    "sg:phone":"+1 705 476 6992",
    "sg:postcode":"P1B 1G5",
    "sg:province":"ON",
    "wof:name":"Canadian Drilling Assoc",
    "wof:placetype":"venue"
},
  "geometry": {"coordinates":[-79.4619293213,46.3111953735],"type":"Point"}
}