{
  "type": "Feature",
  "properties": {
    "addr:full":"Delta BC V4E 2A6",
    "addr:postcode":"v4e 2a6",
    "iso:country":"CA",
    "sg:city":"Delta",
    "sg:classifiers":[
        {
            "category":"Shopping",
            "subcategory":"Shoes",
            "type":"Retail Goods"
        }
    ],
    "sg:phone":"+1 604 501 1333",
    "sg:postcode":"V4E 2A6",
    "sg:province":"BC",
    "wof:name":"New Balance Athletic Footwear",
    "wof:placetype":"venue"
},
  "geometry": {"coordinates":[-122.890587,49.118145],"type":"Point"}
}