{
  "type": "Feature",
  "properties": {
    "addr:full":"Saint-Jean-Sur-Richelieu QC J3A 1M1",
    "addr:postcode":"j3a 1m1",
    "iso:country":"CA",
    "sg:city":"Saint-Jean-Sur-Richelieu",
    "sg:classifiers":[
        {
            "category":"Restaurant",
            "type":"Food & Drink"
        }
    ],
    "sg:phone":"+1 450 349 8008",
    "sg:postcode":"J3A 1M1",
    "sg:province":"QC",
    "sg:tags":[
        "parlor",
        "ice",
        "cream"
    ],
    "wof:name":"Cremiere",
    "wof:placetype":"venue"
},
  "geometry": {"coordinates":[-73.281479,45.331577],"type":"Point"}
}