{
  "type": "Feature",
  "properties": {
    "addr:full":"587 Notre Dame Ave Winnipeg MB R3B 1S6",
    "addr:housenumber":"587",
    "addr:postcode":"r3b 1s6",
    "addr:street":"Notre Dame Ave",
    "iso:country":"CA",
    "sg:address":"587 Notre Dame Ave",
    "sg:city":"Winnipeg",
    "sg:classifiers":[
        {
            "category":"Food & Beverages",
            "subcategory":"Groceries & Convenience Stores",
            "type":"Retail Goods"
        }
    ],
    "sg:phone":"+1 204 774 1766",
    "sg:postcode":"R3B 1S6",
    "sg:province":"MB",
    "sg:tags":[
        "grocer"
    ],
    "wof:name":"Pampanga Food Market & Deli",
    "wof:placetype":"venue"
},
  "geometry": {"coordinates":[-97.155563,49.900455],"type":"Point"}
}