{
  "type": "Feature",
  "properties": {
    "addr:full":"160 Erie St Stratford ON N5A 2M7",
    "addr:housenumber":"160",
    "addr:postcode":"n5a 2m7",
    "addr:street":"Erie St",
    "iso:country":"CA",
    "sg:address":"160 Erie St",
    "sg:city":"Stratford",
    "sg:classifiers":[
        {
            "category":"Wholesale",
            "subcategory":"Office Equipment",
            "type":"Manufacturing & Wholesale Goods"
        }
    ],
    "sg:phone":"+1 519 271 7961",
    "sg:postcode":"N5A 2M7",
    "sg:province":"ON",
    "sg:tags":[
        "blueprinting",
        "supply"
    ],
    "wof:name":"D & W Blueprinting",
    "wof:placetype":"venue"
},
  "geometry": {"coordinates":[-80.98556499999999,43.368435],"type":"Point"}
}