{
  "type": "Feature",
  "properties": {
    "addr:full":"165 2nd Ave W Fox Valley SK S0N 0V0",
    "addr:housenumber":"165",
    "addr:postcode":"s0n 0v0",
    "addr:street":"2Nd Ave W Fox",
    "iso:country":"CA",
    "sg:address":"165 2nd Ave W",
    "sg:city":"Fox Valley",
    "sg:classifiers":[
        {
            "category":"Recreation",
            "type":"Entertainment"
        }
    ],
    "sg:phone":"+1 306 666 2100",
    "sg:postcode":"S0N 0V0",
    "sg:province":"SK",
    "sg:tags":[
        "club",
        "curling"
    ],
    "wof:name":"Fox Valley Curling Club",
    "wof:placetype":"venue"
},
  "geometry": {"coordinates":[-109.482849121,50.4662666321],"type":"Point"}
}