{
  "type": "Feature",
  "properties": {
    "addr:full":"590 Rue Des Erables # A Saint-Lambert-DE-Lauzon QC G0S 2W0",
    "addr:housenumber":"590",
    "addr:postcode":"g0s 2w0",
    "addr:street":"Rue Des Erables # A Saint-Lambert-De-Lauzon",
    "iso:country":"CA",
    "sg:address":"590 Rue Des Erables # A",
    "sg:city":"Saint-Lambert-DE-Lauzon",
    "sg:classifiers":[
        {
            "category":"Retail",
            "subcategory":"Auto Repair",
            "type":"Services"
        }
    ],
    "sg:phone":"+1 418 889 0708",
    "sg:postcode":"G0S 2W0",
    "sg:province":"QC",
    "sg:tags":[
        "body",
        "automobile",
        "painting"
    ],
    "wof:name":"Garage Richard Langlais Inc",
    "wof:placetype":"venue"
},
  "geometry": {"coordinates":[-71.22942399999999,46.620552],"type":"Point"}
}