{
  "type": "Feature",
  "properties": {
    "iso:country":"CA",
    "sg:address":"6900 Rue Saint-Jacques",
    "sg:city":"Montreal",
    "sg:classifiers":[
        {
            "category":"Food & Beverages",
            "subcategory":"Groceries & Convenience Stores",
            "type":"Retail Goods"
        }
    ],
    "sg:phone":"+1 514 484 3136",
    "sg:postcode":"H4B 1V8",
    "sg:province":"QC",
    "sg:tags":[
        "grocer"
    ],
    "wof:name":"Super C",
    "wof:placetype":"venue"
},
  "geometry": {"coordinates":[-73.6288146973,45.4573822021],"type":"Point"}
}