{
  "type": "Feature",
  "properties": {
    "addr:full":"68 Thames St S Ingersoll ON N5C 2T1",
    "addr:housenumber":"68",
    "addr:postcode":"n5c 2t1",
    "addr:street":"Thames St S",
    "iso:country":"CA",
    "sg:address":"68 Thames St S",
    "sg:city":"Ingersoll",
    "sg:classifiers":[
        {
            "category":"Home & Garden",
            "subcategory":"Building Materials",
            "type":"Retail Goods"
        }
    ],
    "sg:phone":"+1 519 485 5471",
    "sg:postcode":"N5C 2T1",
    "sg:province":"ON",
    "sg:tags":[
        "windows",
        "plate",
        "window"
    ],
    "wof:name":"Ingersoll Glass & Mirror",
    "wof:placetype":"venue"
},
  "geometry": {"coordinates":[-80.88427,43.039642],"type":"Point"}
}