{
  "type": "Feature",
  "properties": {
    "addr:full":"1159 Passchendaele Rd # A Sorrento BC V0E 2W0",
    "addr:housenumber":"1159",
    "addr:postcode":"v0e 2w0",
    "addr:street":"Passchendaele Rd # A",
    "iso:country":"CA",
    "sg:address":"1159 Passchendaele Rd # A",
    "sg:city":"Sorrento",
    "sg:classifiers":[
        {
            "category":"Professional",
            "subcategory":"Business Services",
            "type":"Services"
        }
    ],
    "sg:phone":"+1 250 675 2421",
    "sg:postcode":"V0E 2W0",
    "sg:province":"BC",
    "sg:tags":[
        "conference",
        "center"
    ],
    "wof:name":"Sorrento Centre Anglican Ctr",
    "wof:placetype":"venue"
},
  "geometry": {"coordinates":[-119.47544860799999,50.8786506653],"type":"Point"}
}