{
  "type": "Feature",
  "properties": {
    "addr:full":"326 Main St Foam Lake SK S0A 1A0",
    "addr:housenumber":"326",
    "addr:postcode":"s0a 1a0",
    "addr:street":"Main St",
    "iso:country":"CA",
    "sg:address":"326 Main St",
    "sg:city":"Foam Lake",
    "sg:classifiers":[
        {
            "category":"Banks & Credit Unions",
            "subcategory":"Bank",
            "type":"Services"
        }
    ],
    "sg:phone":"+1 306 272 3385",
    "sg:postcode":"S0A 1A0",
    "sg:province":"SK",
    "wof:name":"Foam Lake Credit Union",
    "wof:placetype":"venue"
},
  "geometry": {"coordinates":[-103.533844,51.641541],"type":"Point"}
}