{
  "type": "Feature",
  "properties": {
    "addr:full":"906 Rue Fernand-Dufour Vanier QC G1M 3B1",
    "addr:housenumber":"906",
    "addr:postcode":"g1m 3b1",
    "addr:street":"Rue Fernand-Dufour",
    "iso:country":"CA",
    "sg:address":"906 Rue Fernand-Dufour",
    "sg:city":"Vanier",
    "sg:classifiers":[
        {
            "category":"Wholesale",
            "subcategory":"Construction Materials",
            "type":"Manufacturing & Wholesale Goods"
        }
    ],
    "sg:phone":"+1 418 527 5587",
    "sg:postcode":"G1M 3B1",
    "sg:province":"QC",
    "sg:tags":[
        "marble"
    ],
    "wof:name":"Poly-Pierres",
    "wof:placetype":"venue"
},
  "geometry": {"coordinates":[-71.28119700000001,46.822559],"type":"Point"}
}