{
  "type": "Feature",
  "properties": {
    "addr:full":"7720 17 St NW Edmonton AB T6P 1S7",
    "addr:housenumber":"7720",
    "addr:postcode":"t6p 1s7",
    "addr:street":"17 St Nw",
    "iso:country":"CA",
    "sg:address":"7720 17 St NW",
    "sg:city":"Edmonton",
    "sg:classifiers":[
        {
            "category":"Manufacturing",
            "subcategory":"Tools & Machinery",
            "type":"Manufacturing & Wholesale Goods"
        }
    ],
    "sg:phone":"+1 780 440 4440",
    "sg:postcode":"T6P 1S7",
    "sg:province":"AB",
    "sg:tags":[
        "field",
        "oil",
        "equipment"
    ],
    "wof:name":"Top-CO Ind Ltd",
    "wof:placetype":"venue"
},
  "geometry": {"coordinates":[-113.369514,53.514244],"type":"Point"}
}