{
  "type": "Feature",
  "properties": {
    "iso:country":"CA",
    "sg:address":"1220 Hammond Ave",
    "sg:city":"Crossfield",
    "sg:classifiers":[
        {
            "category":"Social Services",
            "subcategory":"Adult Care",
            "type":"Services"
        }
    ],
    "sg:phone":"+1 403 946 4354",
    "sg:postcode":"T0M 0S0",
    "sg:province":"AB",
    "sg:tags":[
        "senior",
        "housing",
        "citizen"
    ],
    "wof:name":"Rocky View Foundation",
    "wof:placetype":"venue"
},
  "geometry": {"coordinates":[-114.03262329099999,51.4294776917],"type":"Point"}
}