{
  "type": "Feature",
  "properties": {
    "addr:full":"Brunner ON N0K 1C0",
    "addr:postcode":"n0k 1c0",
    "iso:country":"CA",
    "sg:city":"Brunner",
    "sg:classifiers":[
        {
            "category":"Government",
            "subcategory":"Post Office",
            "type":"Public Place"
        }
    ],
    "sg:phone":"+1 519 595 8232",
    "sg:postcode":"N0K 1C0",
    "sg:province":"ON",
    "wof:name":"Brunner Post Office",
    "wof:placetype":"venue"
},
  "geometry": {"coordinates":[-80.926697,43.521927],"type":"Point"}
}