{
  "type": "Feature",
  "properties": {
    "iso:country":"CA",
    "sg:address":"11201 Boul Ray-Lawson",
    "sg:city":"Anjou",
    "sg:classifiers":[
        {
            "category":"Wholesale",
            "subcategory":"Machinery & Supplies",
            "type":"Manufacturing & Wholesale Goods"
        }
    ],
    "sg:phone":"+1 514 356 7600",
    "sg:postcode":"H1J 1M6",
    "sg:province":"QC",
    "sg:tags":[
        "equipment",
        "welding"
    ],
    "wof:name":"Air Liquide Canada Inc",
    "wof:placetype":"venue"
},
  "geometry": {"coordinates":[-73.58020019529999,45.6247520447],"type":"Point"}
}