{
  "type": "Feature",
  "properties": {
    "iso:country":"CA",
    "sg:address":"3155 Highway 7",
    "sg:city":"Markham",
    "sg:classifiers":[
        {
            "category":"Retail",
            "subcategory":"Veterinary Services",
            "type":"Services"
        }
    ],
    "sg:phone":"+1 905 946 0336",
    "sg:postcode":"L3R 0T9",
    "sg:province":"ON",
    "sg:tags":[
        "veterinarian"
    ],
    "wof:name":"Alkesh, Dave DVM",
    "wof:placetype":"venue"
},
  "geometry": {"coordinates":[-79.339943,43.856033],"type":"Point"}
}