{
  "type": "Feature",
  "properties": {
    "iso:country":"CA",
    "sg:address":"1041 Gainsborough Rd",
    "sg:city":"London",
    "sg:classifiers":[
        {
            "category":"Travel",
            "subcategory":"Travel Agent",
            "type":"Entertainment"
        }
    ],
    "sg:phone":"+1 519 473 8480",
    "sg:postcode":"N6H 5L4",
    "sg:province":"ON",
    "sg:tags":[
        "agency",
        "bureau"
    ],
    "wof:name":"G D Hyde Park Travel",
    "wof:placetype":"venue"
},
  "geometry": {"coordinates":[-81.331573,42.999062],"type":"Point"}
}