{
  "type": "Feature",
  "properties": {
    "iso:country":"CA",
    "sg:address":"1875 Rue Du Plateau-Ouimet",
    "sg:city":"Laval",
    "sg:classifiers":[
        {
            "category":"Health Services",
            "subcategory":"Nursing And Care Facility",
            "type":"Services"
        }
    ],
    "sg:phone":"+1 450 628 2176",
    "sg:postcode":"H7L 2X4",
    "sg:province":"QC",
    "sg:tags":[
        "home",
        "retirement",
        "community"
    ],
    "wof:name":"Residence Johanne Methot",
    "wof:placetype":"venue"
},
  "geometry": {"coordinates":[-73.7883224487,45.6088752747],"type":"Point"}
}