{
  "type": "Feature",
  "properties": {
    "addr:full":"Savant Lake ON P0V 2S0",
    "addr:postcode":"p0v 2s0",
    "addr:street":"Lake",
    "iso:country":"CA",
    "sg:city":"Savant Lake",
    "sg:classifiers":[
        {
            "category":"Travel",
            "subcategory":"Campground",
            "type":"Entertainment"
        }
    ],
    "sg:phone":"+1 807 584 2202",
    "sg:postcode":"P0V 2S0",
    "sg:province":"ON",
    "sg:tags":[
        "camp"
    ],
    "wof:name":"Barrington Lake Wilderness",
    "wof:placetype":"venue"
},
  "geometry": {"coordinates":[-90.70961,50.246468],"type":"Point"}
}