{
  "type": "Feature",
  "properties": {
    "addr:full":"410 Wharncliffe Rd S London ON N6J 2M4",
    "addr:housenumber":"410",
    "addr:postcode":"n6j 2m4",
    "addr:street":"Wharncliffe Rd",
    "iso:country":"CA",
    "sg:address":"410 Wharncliffe Rd S",
    "sg:city":"London",
    "sg:classifiers":[
        {
            "category":"Shopping",
            "subcategory":"Books",
            "type":"Retail Goods"
        }
    ],
    "sg:phone":"+1 519 679 8720",
    "sg:postcode":"N6J 2M4",
    "sg:province":"ON",
    "sg:tags":[
        "dealer"
    ],
    "wof:name":"Upper Room Book Store",
    "wof:placetype":"venue"
},
  "geometry": {"coordinates":[-81.26109313960001,42.9627799988],"type":"Point"}
}