{
  "type": "Feature",
  "properties": {
    "iso:country":"CA",
    "sg:address":"7715 Yonge St",
    "sg:city":"Thornhill",
    "sg:classifiers":[
        {
            "category":"Shopping",
            "subcategory":"Clothing, Apparel, & Fashions",
            "type":"Retail Goods"
        }
    ],
    "sg:phone":"+1 905 889 1772",
    "sg:postcode":"L3T 2C4",
    "sg:province":"ON",
    "sg:tags":[
        "tailor"
    ],
    "wof:name":"Thornhill Tailors",
    "wof:placetype":"venue"
},
  "geometry": {"coordinates":[-79.424141,43.815659],"type":"Point"}
}