{
  "type": "Feature",
  "properties": {
    "addr:full":"1234 Boul Saint-Paul Chicoutimi QC G7J 3C5",
    "addr:housenumber":"1234",
    "addr:postcode":"g7j 3c5",
    "addr:street":"Boul Saint-Paul",
    "iso:country":"CA",
    "sg:address":"1234 Boul Saint-Paul",
    "sg:city":"Chicoutimi",
    "sg:classifiers":[
        {
            "category":"Building & Trades",
            "subcategory":"Pest Control",
            "type":"Services"
        }
    ],
    "sg:phone":"+1 418 543 6863",
    "sg:postcode":"G7J 3C5",
    "sg:province":"QC",
    "wof:name":"Tremblay & Lemieux",
    "wof:placetype":"venue"
},
  "geometry": {"coordinates":[-71.0907897949,48.4093894958],"type":"Point"}
}