{
  "type": "Feature",
  "properties": {
    "iso:country":"CA",
    "sg:city":"Guelph",
    "sg:classifiers":[
        {
            "category":"Professional",
            "subcategory":"Business Services",
            "type":"Services"
        }
    ],
    "sg:phone":"+1 519 822 5551",
    "sg:postcode":"N1H 7K5",
    "sg:province":"ON",
    "sg:tags":[
        "license"
    ],
    "wof:name":"Motor Vehicle Licence Svc",
    "wof:placetype":"venue"
},
  "geometry": {"coordinates":[-80.295464,43.55101],"type":"Point"}
}