{
  "type": "Feature",
  "properties": {
    "addr:full":"1450 Gordon Ave The Pas MB R9A 1K6",
    "addr:housenumber":"1450",
    "addr:postcode":"r9a 1k6",
    "addr:street":"Gordon Ave",
    "iso:country":"CA",
    "sg:address":"1450 Gordon Ave",
    "sg:city":"The Pas",
    "sg:classifiers":[
        {
            "category":"Autos & Motor Vehicles",
            "subcategory":"Auto Supplies",
            "type":"Retail Goods"
        }
    ],
    "sg:phone":"+1 204 623 4411",
    "sg:postcode":"R9A 1K6",
    "sg:province":"MB",
    "sg:tags":[
        "tire"
    ],
    "wof:name":"Wright Tirecraft Auto Ctr",
    "wof:placetype":"venue"
},
  "geometry": {"coordinates":[-101.251846,53.807018],"type":"Point"}
}