{
  "type": "Feature",
  "properties": {
    "addr:full":"Winnipeg MB R3B 1K2",
    "addr:postcode":"r3b 1k2",
    "iso:country":"CA",
    "sg:city":"Winnipeg",
    "sg:classifiers":[
        {
            "category":"Real Estate",
            "subcategory":"Real Estate Agent",
            "type":"Services"
        }
    ],
    "sg:phone":"+1 204 956 1885",
    "sg:postcode":"R3B 1K2",
    "sg:province":"MB",
    "sg:tags":[
        "appraiser"
    ],
    "wof:name":"Warren R Baldwin & Assoc Ltd",
    "wof:placetype":"venue"
},
  "geometry": {"coordinates":[-97.143196106,49.8973274231],"type":"Point"}
}