{
  "type": "Feature",
  "properties": {
    "addr:full":"5321 Sherkston Rd Sherkston ON L0S 1R0",
    "addr:housenumber":"5321",
    "addr:postcode":"l0s 1r0",
    "addr:street":"Sherkston Rd",
    "iso:country":"CA",
    "sg:address":"5321 Sherkston Rd",
    "sg:city":"Sherkston",
    "sg:classifiers":[
        {
            "category":"Building & Trades",
            "subcategory":"Construction",
            "type":"Services"
        }
    ],
    "sg:phone":"+1 905 894 0077",
    "sg:postcode":"L0S 1R0",
    "sg:province":"ON",
    "sg:tags":[
        "siding",
        "contractor"
    ],
    "wof:name":"Precision Siding & Renovating",
    "wof:placetype":"venue"
},
  "geometry": {"coordinates":[-79.127037,42.885689],"type":"Point"}
}