{
  "type": "Feature",
  "properties": {
    "addr:full":"White Rock BC V4B 3Z2",
    "addr:postcode":"v4b 3z2",
    "iso:country":"CA",
    "sg:city":"White Rock",
    "sg:classifiers":[
        {
            "category":"Organizations",
            "subcategory":"Religious Organization",
            "type":"Services"
        }
    ],
    "sg:phone":"+1 604 536 0313",
    "sg:postcode":"V4B 3Z2",
    "sg:province":"BC",
    "sg:tags":[
        "church"
    ],
    "wof:name":"Eckankar Canada",
    "wof:placetype":"venue"
},
  "geometry": {"coordinates":[-122.800972,49.026245],"type":"Point"}
}