{
  "type": "Feature",
  "properties": {
    "addr:full":"14410 118 Ave NW Edmonton AB T5L 2M5",
    "addr:housenumber":"14410",
    "addr:postcode":"t5l 2m5",
    "addr:street":"118 Ave Nw",
    "iso:country":"CA",
    "sg:address":"14410 118 Ave NW",
    "sg:city":"Edmonton",
    "sg:classifiers":[
        {
            "category":"Manufacturing",
            "subcategory":"Printing",
            "type":"Manufacturing & Wholesale Goods"
        }
    ],
    "sg:phone":"+1 780 488 9559",
    "sg:postcode":"T5L 2M5",
    "sg:province":"AB",
    "sg:tags":[
        "screen",
        "sportswear"
    ],
    "wof:name":"Spark Printwear",
    "wof:placetype":"venue"
},
  "geometry": {"coordinates":[-113.569366,53.570637],"type":"Point"}
}