{
  "type": "Feature",
  "properties": {
    "addr:full":"50 Lombard St Toronto ON M5C 2X4",
    "addr:housenumber":"50",
    "addr:postcode":"m5c 2x4",
    "addr:street":"Lombard St",
    "iso:country":"CA",
    "sg:address":"50 Lombard St",
    "sg:city":"Toronto",
    "sg:classifiers":[
        {
            "category":"Real Estate",
            "subcategory":"Real Estate Operator",
            "type":"Services"
        }
    ],
    "sg:phone":"+1 416 777 0122",
    "sg:postcode":"M5C 2X4",
    "sg:province":"ON",
    "sg:tags":[
        "condominium"
    ],
    "wof:name":"Indigo the Condominium Res",
    "wof:placetype":"venue"
},
  "geometry": {"coordinates":[-79.37552599999999,43.651882],"type":"Point"}
}