{
  "type": "Feature",
  "properties": {
    "iso:country":"CA",
    "sg:address":"50 Lombard St",
    "sg:city":"Toronto",
    "sg:classifiers":[
        {
            "category":"Real Estate",
            "subcategory":"Real Estate Operator",
            "type":"Services"
        }
    ],
    "sg:phone":"+1 416 777 0122",
    "sg:postcode":"M5C 2X4",
    "sg:province":"ON",
    "sg:tags":[
        "condominium"
    ],
    "wof:name":"Indigo the Condominium Res",
    "wof:placetype":"venue"
},
  "geometry": {"coordinates":[-79.375526,43.651882],"type":"Point"}
}