{
  "type": "Feature",
  "properties": {
    "addr:full":"921 Boul Saint-Laurent O Louiseville QC J5V 1L3",
    "addr:housenumber":"921",
    "addr:postcode":"j5v 1l3",
    "addr:street":"Boul Saint-Laurent O",
    "iso:country":"CA",
    "sg:address":"921 Boul Saint-Laurent O",
    "sg:city":"Louiseville",
    "sg:classifiers":[
        {
            "category":"Manufacturing",
            "subcategory":"Furniture",
            "type":"Manufacturing & Wholesale Goods"
        }
    ],
    "sg:phone":"+1 819 228 8577",
    "sg:postcode":"J5V 1L3",
    "sg:province":"QC",
    "wof:name":"Finition Chez Soie Inc",
    "wof:placetype":"venue"
},
  "geometry": {"coordinates":[-72.9074935913,46.2593841553],"type":"Point"}
}