{
  "type": "Feature",
  "properties": {
    "addr:full":"300 Av Lafleur Lasalle QC H8R 3H5",
    "addr:postcode":"h8r 3h5",
    "addr:street":"300 Av Lafleur",
    "iso:country":"CA",
    "sg:address":"300 Av Lafleur",
    "sg:city":"Lasalle",
    "sg:classifiers":[
        {
            "category":"Organizations",
            "subcategory":"Religious Organization",
            "type":"Services"
        }
    ],
    "sg:phone":"+1 514 363 1555",
    "sg:postcode":"H8R 3H5",
    "sg:province":"QC",
    "sg:tags":[
        "church"
    ],
    "wof:name":"Assemblee Du Plein Evangile",
    "wof:placetype":"venue"
},
  "geometry": {"coordinates":[-73.6482543945,45.4288368225],"type":"Point"}
}