{
  "type": "Feature",
  "properties": {
    "addr:full":"398 3E Rang E St-Octave QC G0J 3B0",
    "addr:housenumber":"398",
    "addr:postcode":"g0j 3b0",
    "addr:street":"3E Rang E St-Octave",
    "iso:country":"CA",
    "sg:address":"398 3E Rang E",
    "sg:city":"St-Octave",
    "sg:classifiers":[
        {
            "category":"Building & Trades",
            "subcategory":"Construction",
            "type":"Services"
        }
    ],
    "sg:phone":"+1 418 775 4967",
    "sg:postcode":"G0J 3B0",
    "sg:province":"QC",
    "sg:tags":[
        "general",
        "contractor"
    ],
    "wof:name":"Entreprises R Dube Inc",
    "wof:placetype":"venue"
},
  "geometry": {"coordinates":[-68.08010899999999,48.600639],"type":"Point"}
}