{
  "type": "Feature",
  "properties": {
    "iso:country":"CA",
    "sg:city":"Atikokan",
    "sg:classifiers":[
        {
            "category":"Social Services",
            "type":"Services"
        }
    ],
    "sg:phone":"+1 807 597 2695",
    "sg:postcode":"P0T 1C0",
    "sg:province":"ON",
    "sg:tags":[
        "organization",
        "welfare"
    ],
    "wof:name":"Atikokan & District Assn",
    "wof:placetype":"venue"
},
  "geometry": {"coordinates":[-91.6273651123,48.7548408508],"type":"Point"}
}