{
  "type": "Feature",
  "properties": {
    "addr:full":"1451 Royal York Rd Etobicoke ON M9P 3B2",
    "addr:housenumber":"1451",
    "addr:postcode":"m9p 3b2",
    "addr:street":"Royal York Rd",
    "iso:country":"CA",
    "sg:address":"1451 Royal York Rd",
    "sg:city":"Etobicoke",
    "sg:classifiers":[
        {
            "category":"Professional",
            "subcategory":"Lawyer & Legal Services",
            "type":"Services"
        }
    ],
    "sg:phone":"+1 416 243 0532",
    "sg:postcode":"M9P 3B2",
    "sg:province":"ON",
    "sg:tags":[
        "attorney"
    ],
    "wof:name":"Schell, Susan",
    "wof:placetype":"venue"
},
  "geometry": {"coordinates":[-79.5284042358,43.6869087219],"type":"Point"}
}