{
  "type": "Feature",
  "properties": {
    "addr:full":"Laforce QC J0Z 2J0",
    "addr:postcode":"j0z 2j0",
    "iso:country":"CA",
    "sg:city":"Laforce",
    "sg:classifiers":[
        {
            "category":"Autos & Motor Vehicles",
            "subcategory":"Fuel & Gas Station",
            "type":"Retail Goods"
        }
    ],
    "sg:phone":"+1 819 722 2522",
    "sg:postcode":"J0Z 2J0",
    "sg:province":"QC",
    "sg:tags":[
        "oil"
    ],
    "wof:name":"Shell Canada Ltd",
    "wof:placetype":"venue"
},
  "geometry": {"coordinates":[-78.72146600000001,47.536304],"type":"Point"}
}