{
  "type": "Feature",
  "properties": {
    "iso:country":"CA",
    "sg:address":"3281 Boul Cavendish",
    "sg:city":"Montreal",
    "sg:classifiers":[
        {
            "category":"Restaurant",
            "type":"Food & Drink"
        }
    ],
    "sg:phone":"+1 514 481 2729",
    "sg:postcode":"H4B 2L7",
    "sg:province":"QC",
    "wof:name":"Hum's Restaurant",
    "wof:placetype":"venue"
},
  "geometry": {"coordinates":[-73.628181,45.463543],"type":"Point"}
}