{
  "type": "Feature",
  "properties": {
    "addr:full":"Calgary AB T2G 4R7",
    "addr:postcode":"t2g 4r7",
    "iso:country":"CA",
    "sg:city":"Calgary",
    "sg:classifiers":[
        {
            "category":"Food & Beverages",
            "subcategory":"Bakery",
            "type":"Retail Goods"
        }
    ],
    "sg:phone":"+1 403 263 8225",
    "sg:postcode":"T2G 4R7",
    "sg:province":"AB",
    "sg:tags":[
        "doughnut"
    ],
    "wof:name":"Patty's Donuts",
    "wof:placetype":"venue"
},
  "geometry": {"coordinates":[-114.030739,51.028816],"type":"Point"}
}