{
  "type": "Feature",
  "properties": {
    "iso:country":"CA",
    "sg:address":"521 Erie St",
    "sg:city":"Stratford",
    "sg:classifiers":[
        {
            "category":"Manufacturing",
            "subcategory":"Tools & Machinery",
            "type":"Manufacturing & Wholesale Goods"
        }
    ],
    "sg:phone":"+1 519 271 0822",
    "sg:postcode":"N5A 2N7",
    "sg:province":"ON",
    "sg:tags":[
        "machine",
        "shop"
    ],
    "wof:name":"Strawbridge Machine & Tool",
    "wof:placetype":"venue"
},
  "geometry": {"coordinates":[-80.9929656982,43.3591575623],"type":"Point"}
}