{
  "type": "Feature",
  "properties": {
    "addr:full":"715 Edward St Hearst ON P0L 1N0",
    "addr:housenumber":"715",
    "addr:postcode":"p0l 1n0",
    "addr:street":"Edward St",
    "iso:country":"CA",
    "sg:address":"715 Edward St",
    "sg:city":"Hearst",
    "sg:classifiers":[
        {
            "category":"Retail",
            "subcategory":"Funeral Services",
            "type":"Services"
        }
    ],
    "sg:phone":"+1 705 362 4644",
    "sg:postcode":"P0L 1N0",
    "sg:province":"ON",
    "sg:tags":[
        "director"
    ],
    "wof:name":"Salon Funeraire Lafrance",
    "wof:placetype":"venue"
},
  "geometry": {"coordinates":[-83.66177399999999,49.685192],"type":"Point"}
}