{
  "type": "Feature",
  "properties": {
    "iso:country":"CA",
    "sg:city":"Lasalle",
    "sg:classifiers":[
        {
            "category":"Real Estate",
            "subcategory":"Architect",
            "type":"Services"
        }
    ],
    "sg:phone":"+1 514 364 9162",
    "sg:postcode":"H8P 2P9",
    "sg:province":"QC",
    "wof:name":"Peled, Moshe",
    "wof:placetype":"venue"
},
  "geometry": {"coordinates":[-73.5988311768,45.4271507263],"type":"Point"}
}