{
  "type": "Feature",
  "properties": {
    "addr:full":"512 West Ave Kamsack SK S0A 1S0",
    "addr:housenumber":"512",
    "addr:postcode":"s0a 1s0",
    "addr:street":"West Ave",
    "iso:country":"CA",
    "sg:address":"512 West Ave",
    "sg:city":"Kamsack",
    "sg:classifiers":[
        {
            "category":"Education",
            "subcategory":"School",
            "type":"Public Place"
        }
    ],
    "sg:phone":"+1 306 542 2546",
    "sg:postcode":"S0A 1S0",
    "sg:province":"SK",
    "wof:name":"Victoria School",
    "wof:placetype":"venue"
},
  "geometry": {"coordinates":[-101.894790649,51.5571899414],"type":"Point"}
}