{
  "type": "Feature",
  "properties": {
    "addr:full":"171 Blair Lane Ancaster ON L9G 1B8",
    "addr:housenumber":"171",
    "addr:postcode":"l9g 1b8",
    "addr:street":"Blair Lane",
    "iso:country":"CA",
    "sg:address":"171 Blair Lane",
    "sg:city":"Ancaster",
    "sg:classifiers":[
        {
            "category":"Building & Trades",
            "subcategory":"Construction",
            "type":"Services"
        }
    ],
    "sg:phone":"+1 905 304 8407",
    "sg:postcode":"L9G 1B8",
    "sg:province":"ON",
    "sg:tags":[
        "stucco",
        "contractor"
    ],
    "wof:name":"Kingsway Stucco Inc",
    "wof:placetype":"venue"
},
  "geometry": {"coordinates":[-79.99522399999999,43.220654],"type":"Point"}
}