{
  "type": "Feature",
  "properties": {
    "addr:full":"Toronto ON M4W 3R8",
    "addr:postcode":"m4w 3r8",
    "iso:country":"CA",
    "sg:city":"Toronto",
    "sg:classifiers":[
        {
            "category":"Retail",
            "subcategory":"Photofinishing",
            "type":"Services"
        }
    ],
    "sg:phone":"+1 416 929 3000",
    "sg:postcode":"M4W 3R8",
    "sg:province":"ON",
    "sg:tags":[
        "photograph"
    ],
    "wof:name":"Masterfile",
    "wof:placetype":"venue"
},
  "geometry": {"coordinates":[-79.3829956055,43.6709671021],"type":"Point"}
}