{
  "type": "Feature",
  "properties": {
    "addr:full":"10 Toronto St Toronto ON M5C 2B7",
    "addr:housenumber":"10",
    "addr:postcode":"m5c 2b7",
    "addr:street":"Toronto St",
    "iso:country":"CA",
    "sg:address":"10 Toronto St",
    "sg:city":"Toronto",
    "sg:classifiers":[
        {
            "category":"Manufacturing",
            "subcategory":"Printing",
            "type":"Manufacturing & Wholesale Goods"
        }
    ],
    "sg:phone":"+1 416 363 8721",
    "sg:postcode":"M5C 2B7",
    "sg:province":"ON",
    "sg:tags":[
        "newspaper"
    ],
    "wof:name":"Hollinger Canadian Newspapers",
    "wof:placetype":"venue"
},
  "geometry": {"coordinates":[-79.37623600000001,43.649822],"type":"Point"}
}