{
  "type": "Feature",
  "properties": {
    "iso:country":"CA",
    "sg:city":"Etobicoke",
    "sg:classifiers":[
        {
            "category":"Building & Trades",
            "subcategory":"Construction",
            "type":"Services"
        }
    ],
    "sg:phone":"+1 416 742 5090",
    "sg:postcode":"M9V 4A8",
    "sg:province":"ON",
    "sg:tags":[
        "concrete",
        "contractor"
    ],
    "wof:name":"Triplecrete Limited",
    "wof:placetype":"venue"
},
  "geometry": {"coordinates":[-79.605911,43.745876],"type":"Point"}
}