{
  "type": "Feature",
  "properties": {
    "iso:country":"CA",
    "sg:city":"Saint-Laurent",
    "sg:classifiers":[
        {
            "category":"Professional",
            "subcategory":"Research",
            "type":"Services"
        }
    ],
    "sg:phone":"+1 514 855 0888",
    "sg:postcode":"H4M 2P4",
    "sg:province":"QC",
    "sg:tags":[
        "development",
        "laboratory"
    ],
    "wof:name":"Quintiles",
    "wof:placetype":"venue"
},
  "geometry": {"coordinates":[-73.6768569946,45.4962806702],"type":"Point"}
}