{
  "type": "Feature",
  "properties": {
    "addr:full":"Surrey BC V3S 6J9",
    "addr:postcode":"v3s 6j9",
    "iso:country":"CA",
    "sg:city":"Surrey",
    "sg:classifiers":[
        {
            "category":"Building & Trades",
            "subcategory":"Construction",
            "type":"Services"
        }
    ],
    "sg:phone":"+1 604 575 7623",
    "sg:postcode":"V3S 6J9",
    "sg:province":"BC",
    "sg:tags":[
        "road",
        "contractor"
    ],
    "wof:name":"Road-Line Construction Ltd",
    "wof:placetype":"venue"
},
  "geometry": {"coordinates":[-122.689301,49.107655],"type":"Point"}
}