{
  "type": "Feature",
  "properties": {
    "iso:country":"CA",
    "sg:address":"259 Boul Saint-Michel",
    "sg:city":"Dolbeau-Mistassini",
    "sg:classifiers":[
        {
            "category":"Home & Garden",
            "subcategory":"Furniture",
            "type":"Retail Goods"
        }
    ],
    "sg:phone":"+1 418 276 7752",
    "sg:postcode":"G8L 4P7",
    "sg:province":"QC",
    "wof:name":"Meubles Le Roi Du Meuble",
    "wof:placetype":"venue"
},
  "geometry": {"coordinates":[-72.1993026733,48.8900794983],"type":"Point"}
}