{
  "type": "Feature",
  "properties": {
    "addr:full":"6160 Av DE Monkland Montreal QC H4B 1G4",
    "addr:housenumber":"6160",
    "addr:postcode":"h4b 1g4",
    "addr:street":"Av De Monkland",
    "iso:country":"CA",
    "sg:address":"6160 Av DE Monkland",
    "sg:city":"Montreal",
    "sg:classifiers":[
        {
            "category":"Personal",
            "subcategory":"Beauty Salon",
            "type":"Services"
        }
    ],
    "sg:phone":"+1 514 486 3446",
    "sg:postcode":"H4B 1G4",
    "sg:province":"QC",
    "wof:name":"Coiffure Jean-Denis",
    "wof:placetype":"venue"
},
  "geometry": {"coordinates":[-73.6280670166,45.4695625305],"type":"Point"}
}