{
  "type": "Feature",
  "properties": {
    "iso:country":"CA",
    "sg:address":"99 Fifth Ave CT # 14",
    "sg:city":"Ottawa",
    "sg:classifiers":[
        {
            "category":"Professional",
            "subcategory":"Business Services",
            "type":"Services"
        }
    ],
    "sg:phone":"+1 613 232 9770",
    "sg:postcode":"K1S 5K4",
    "sg:province":"ON",
    "sg:tags":[
        "translator",
        "interpreter"
    ],
    "wof:name":"Languages of Life Inc",
    "wof:placetype":"venue"
},
  "geometry": {"coordinates":[-75.691895,45.421501],"type":"Point"}
}