{
  "type": "Feature",
  "properties": {
    "addr:full":"880 Av Du Pont N Alma QC G8B 5E9",
    "addr:housenumber":"880",
    "addr:postcode":"g8b 5e9",
    "addr:street":"Av Du Pont N",
    "iso:country":"CA",
    "sg:address":"880 Av Du Pont N",
    "sg:city":"Alma",
    "sg:classifiers":[
        {
            "category":"Autos & Motor Vehicles",
            "subcategory":"Auto Supplies",
            "type":"Retail Goods"
        }
    ],
    "sg:phone":"+1 418 662 2817",
    "sg:postcode":"G8B 5E9",
    "sg:province":"QC",
    "sg:tags":[
        "repairing",
        "automobile",
        "parts"
    ],
    "wof:name":"Couture Auto Electrique Enr",
    "wof:placetype":"venue"
},
  "geometry": {"coordinates":[-71.640778,48.565594],"type":"Point"}
}