{
  "type": "Feature",
  "properties": {
    "addr:full":"21869 61 Ave Langley BC V2Y 2P2",
    "addr:housenumber":"21869",
    "addr:postcode":"v2y 2p2",
    "addr:street":"61 Ave",
    "iso:country":"CA",
    "sg:address":"21869 61 Ave",
    "sg:city":"Langley",
    "sg:classifiers":[
        {
            "category":"Building & Trades",
            "subcategory":"Construction",
            "type":"Services"
        }
    ],
    "sg:phone":"+1 604 533 5025",
    "sg:postcode":"V2Y 2P2",
    "sg:province":"BC",
    "sg:tags":[
        "insulation",
        "heat",
        "contractor"
    ],
    "wof:name":"Four Seasons Insulation Ltd",
    "wof:placetype":"venue"
},
  "geometry": {"coordinates":[-122.616859436,49.1141586304],"type":"Point"}
}