{
  "type": "Feature",
  "properties": {
    "iso:country":"CA",
    "sg:address":"399 Dundas St W",
    "sg:city":"Toronto",
    "sg:classifiers":[
        {
            "category":"Shopping",
            "subcategory":"Pharmacy",
            "type":"Retail Goods"
        }
    ],
    "sg:phone":"+1 416 977 8338",
    "sg:postcode":"M5T 1G6",
    "sg:province":"ON",
    "wof:name":"99 Pharmacy",
    "wof:placetype":"venue"
},
  "geometry": {"coordinates":[-79.39476,43.653481],"type":"Point"}
}