{
  "type": "Feature",
  "properties": {
    "addr:full":"437 Rue Principale S Sainte-Perpetue-DE-L'Islet QC G0R 3Z0",
    "addr:housenumber":"437",
    "addr:postcode":"g0r 3z0",
    "addr:street":"Rue Principale S Sainte-Perpetue-De-L'Islet",
    "iso:country":"CA",
    "sg:address":"437 Rue Principale S",
    "sg:city":"Sainte-Perpetue-DE-L'Islet",
    "sg:phone":"+1 418 359 2787",
    "sg:postcode":"G0R 3Z0",
    "sg:province":"QC",
    "sg:tags":[
        "food",
        "equipment",
        "processing"
    ],
    "wof:name":"Dominion & Grimm Inc",
    "wof:placetype":"venue"
},
  "geometry": {"coordinates":[-70.331535,47.089802],"type":"Point"}
}