{
  "type": "Feature",
  "properties": {
    "iso:country":"CA",
    "sg:address":"309 Government Rd",
    "sg:city":"Black Diamond",
    "sg:classifiers":[
        {
            "category":"Retail",
            "subcategory":"Auto Rental",
            "type":"Services"
        }
    ],
    "sg:phone":"+1 403 933 4884",
    "sg:postcode":"T0L 0H0",
    "sg:province":"AB",
    "sg:tags":[
        "renting",
        "truck",
        "leasing"
    ],
    "wof:name":"U-Haul CO Ltd",
    "wof:placetype":"venue"
},
  "geometry": {"coordinates":[-114.232849121,50.6858024597],"type":"Point"}
}