{
  "type": "Feature",
  "properties": {
    "iso:country":"CA",
    "sg:address":"4701 50th Ave",
    "sg:city":"Legal",
    "sg:classifiers":[
        {
            "category":"Retail",
            "subcategory":"Auto Repair",
            "type":"Services"
        }
    ],
    "sg:phone":"+1 780 961 3800",
    "sg:postcode":"T0G 1L0",
    "sg:province":"AB",
    "sg:tags":[
        "repairing",
        "automobile"
    ],
    "wof:name":"G & J Mechanic Svc",
    "wof:placetype":"venue"
},
  "geometry": {"coordinates":[-113.590797424,53.9489097595],"type":"Point"}
}