{
  "type": "Feature",
  "properties": {
    "addr:full":"51 Rue Des Forges Amqui QC G5J 3A5",
    "addr:housenumber":"51",
    "addr:postcode":"g5j 3a5",
    "addr:street":"Rue Des Forges",
    "iso:country":"CA",
    "sg:address":"51 Rue Des Forges",
    "sg:city":"Amqui",
    "sg:classifiers":[
        {
            "category":"Bars & Pubs",
            "type":"Food & Drink"
        }
    ],
    "sg:phone":"+1 418 629 1962",
    "sg:postcode":"G5J 3A5",
    "sg:province":"QC",
    "sg:tags":[
        "lounge",
        "cocktail"
    ],
    "wof:name":"Bar LA Cave Aux Sports",
    "wof:placetype":"venue"
},
  "geometry": {"coordinates":[-67.4324645996,48.4643592834],"type":"Point"}
}