{
  "type": "Feature",
  "properties": {
    "addr:full":"135 LA Rose Ave Etobicoke ON M9P 1A6",
    "addr:housenumber":"135",
    "addr:postcode":"m9p 1a6",
    "addr:street":"La Rose Ave",
    "iso:country":"CA",
    "sg:address":"135 LA Rose Ave",
    "sg:city":"Etobicoke",
    "sg:classifiers":[
        {
            "category":"Organizations",
            "subcategory":"Religious Organization",
            "type":"Services"
        }
    ],
    "sg:phone":"+1 416 244 5333",
    "sg:postcode":"M9P 1A6",
    "sg:province":"ON",
    "sg:tags":[
        "church"
    ],
    "wof:name":"St Demetrius Ukrainian Church",
    "wof:placetype":"venue"
},
  "geometry": {"coordinates":[-79.522285,43.685139],"type":"Point"}
}