{
  "type": "Feature",
  "properties": {
    "addr:full":"1033 Fort St Victoria BC V8V 3K5",
    "addr:housenumber":"1033",
    "addr:postcode":"v8v 3k5",
    "addr:street":"Fort St",
    "iso:country":"CA",
    "sg:address":"1033 Fort St",
    "sg:city":"Victoria",
    "sg:classifiers":[
        {
            "category":"Wholesale",
            "subcategory":"Jewelry",
            "type":"Manufacturing & Wholesale Goods"
        }
    ],
    "sg:phone":"+1 250 475 2632",
    "sg:postcode":"V8V 3K5",
    "sg:province":"BC",
    "sg:tags":[
        "antique",
        "beads"
    ],
    "wof:name":"Skanda Holdings Inc",
    "wof:placetype":"venue"
},
  "geometry": {"coordinates":[-123.355919,48.42345],"type":"Point"}
}