{
  "type": "Feature",
  "properties": {
    "iso:country":"CA",
    "sg:city":"Sherbrooke",
    "sg:classifiers":[
        {
            "category":"Home & Garden",
            "subcategory":"Garden Supply",
            "type":"Retail Goods"
        }
    ],
    "sg:phone":"+1 819 569 5523",
    "sg:postcode":"J1L 2B5",
    "sg:province":"QC",
    "sg:tags":[
        "nurseryman",
        "center"
    ],
    "wof:name":"Centre Floral Enr",
    "wof:placetype":"venue"
},
  "geometry": {"coordinates":[-71.946236,45.396351],"type":"Point"}
}