{
  "type": "Feature",
  "properties": {
    "addr:full":"26 Lennox Dr # 3 Barrie ON L4N 9V8",
    "addr:housenumber":"26",
    "addr:postcode":"l4n 9v8",
    "addr:street":"Lennox Dr # 3",
    "iso:country":"CA",
    "sg:address":"26 Lennox Dr # 3",
    "sg:city":"Barrie",
    "sg:classifiers":[
        {
            "category":"Retail",
            "subcategory":"Auto Repair",
            "type":"Services"
        }
    ],
    "sg:phone":"+1 705 737 9240",
    "sg:postcode":"L4N 9V8",
    "sg:province":"ON",
    "sg:tags":[
        "repairing",
        "automobile",
        "body"
    ],
    "wof:name":"J's Autobody",
    "wof:placetype":"venue"
},
  "geometry": {"coordinates":[-79.72032900000001,44.377991],"type":"Point"}
}