{
  "type": "Feature",
  "properties": {
    "addr:full":"171 Rue Saint-Joseph Baie-Saint-Paul QC G3Z 1J3",
    "addr:housenumber":"171",
    "addr:postcode":"g3z 1j3",
    "addr:street":"Rue Saint-Joseph",
    "iso:country":"CA",
    "sg:address":"171 Rue Saint-Joseph",
    "sg:city":"Baie-Saint-Paul",
    "sg:classifiers":[
        {
            "category":"Travel",
            "subcategory":"Travel Agent",
            "type":"Entertainment"
        }
    ],
    "sg:phone":"+1 418 435 3545",
    "sg:postcode":"G3Z 1J3",
    "sg:province":"QC",
    "sg:tags":[
        "agency",
        "bureau"
    ],
    "wof:name":"Agence DE Voyages Paradis Inc",
    "wof:placetype":"venue"
},
  "geometry": {"coordinates":[-70.492355,47.440678],"type":"Point"}
}