{
  "type": "Feature",
  "properties": {
    "addr:full":"314 Booth St Ottawa ON K1R 7K2",
    "addr:housenumber":"314",
    "addr:postcode":"k1r 7k2",
    "addr:street":"Booth St",
    "iso:country":"CA",
    "sg:address":"314 Booth St",
    "sg:city":"Ottawa",
    "sg:classifiers":[
        {
            "category":"Food & Beverages",
            "subcategory":"Groceries & Convenience Stores",
            "type":"Retail Goods"
        }
    ],
    "sg:phone":"+1 613 232 1775",
    "sg:postcode":"K1R 7K2",
    "sg:province":"ON",
    "sg:tags":[
        "grocer"
    ],
    "wof:name":"Loeb Canada Inc",
    "wof:placetype":"venue"
},
  "geometry": {"coordinates":[-75.71017500000001,45.408669],"type":"Point"}
}