{
  "type": "Feature",
  "properties": {
    "iso:country":"CA",
    "sg:city":"West Vancouver",
    "sg:classifiers":[
        {
            "category":"Utilities",
            "subcategory":"Mobile Phone",
            "type":"Services"
        }
    ],
    "sg:phone":"+1 604 921 4720",
    "sg:postcode":"V7T 2W4",
    "sg:province":"BC",
    "sg:tags":[
        "telephone",
        "cellular"
    ],
    "wof:name":"Bell World",
    "wof:placetype":"venue"
},
  "geometry": {"coordinates":[-123.140136719,49.3245506287],"type":"Point"}
}