{
  "type": "Feature",
  "properties": {
    "addr:full":"158 Prince William St Saint John NB E2L 2B6",
    "addr:housenumber":"158",
    "addr:postcode":"nb e2l 2b6",
    "addr:street":"Prince William St",
    "iso:country":"CA",
    "sg:address":"158 Prince William St",
    "sg:city":"Saint John",
    "sg:classifiers":[
        {
            "category":"Insurance",
            "subcategory":"Insurance Agent",
            "type":"Services"
        }
    ],
    "sg:phone":"+1 506 634 2092",
    "sg:postcode":"E2L 2B6",
    "sg:province":"NB",
    "wof:name":"Fitzgerald, Annette",
    "wof:placetype":"venue"
},
  "geometry": {"coordinates":[-66.0613250732,45.2702522278],"type":"Point"}
}