{
  "type": "Feature",
  "properties": {
    "addr:full":"1440 Redwood St Campbell River BC V9W 5L2",
    "addr:housenumber":"1440",
    "addr:postcode":"v9w 5l2",
    "addr:street":"Redwood St",
    "iso:country":"CA",
    "sg:address":"1440 Redwood St",
    "sg:city":"Campbell River",
    "sg:classifiers":[
        {
            "category":"Autos & Motor Vehicles",
            "subcategory":"Automobile Sales",
            "type":"Retail Goods"
        }
    ],
    "sg:phone":"+1 250 286 1151",
    "sg:postcode":"V9W 5L2",
    "sg:province":"BC",
    "sg:tags":[
        "truck"
    ],
    "wof:name":"Bailey Western Star Trucks Inc",
    "wof:placetype":"venue"
},
  "geometry": {"coordinates":[-125.268646,50.029755],"type":"Point"}
}