{
  "type": "Feature",
  "properties": {
    "addr:full":"Edmonton AB T5G 2T8",
    "addr:postcode":"t5g 2t8",
    "iso:country":"CA",
    "sg:city":"Edmonton",
    "sg:classifiers":[
        {
            "category":"Education",
            "subcategory":"Special Training",
            "type":"Public Place"
        }
    ],
    "sg:phone":"+1 780 944 9210",
    "sg:postcode":"T5G 2T8",
    "sg:province":"AB",
    "sg:tags":[
        "aircraft",
        "school"
    ],
    "wof:name":"Air Start Corp",
    "wof:placetype":"venue"
},
  "geometry": {"coordinates":[-113.507789612,53.5692977905],"type":"Point"}
}