{
  "type": "Feature",
  "properties": {
    "addr:full":"3125 Rue Bernard-Pilon Saint-Mathieu-DE-Beloeil QC J3G 4S5",
    "addr:housenumber":"3125",
    "addr:postcode":"j3g 4s5",
    "addr:street":"Rue Bernard-Pilon",
    "iso:country":"CA",
    "sg:address":"3125 Rue Bernard-Pilon",
    "sg:city":"Saint-Mathieu-DE-Beloeil",
    "sg:classifiers":[
        {
            "category":"Manufacturing",
            "subcategory":"Tools & Machinery",
            "type":"Manufacturing & Wholesale Goods"
        }
    ],
    "sg:phone":"+1 450 446 9837",
    "sg:postcode":"J3G 4S5",
    "sg:province":"QC",
    "sg:tags":[
        "lighting",
        "fixture"
    ],
    "wof:name":"Interballast",
    "wof:placetype":"venue"
},
  "geometry": {"coordinates":[-73.26248931879999,45.5802650452],"type":"Point"}
}