{
  "type": "Feature",
  "properties": {
    "addr:full":"400 Main St Kindersley SK S0L 1S0",
    "addr:housenumber":"400",
    "addr:postcode":"s0l 1s0",
    "addr:street":"Main St",
    "iso:country":"CA",
    "sg:address":"400 Main St",
    "sg:city":"Kindersley",
    "sg:classifiers":[
        {
            "category":"Home & Garden",
            "subcategory":"Hardware",
            "type":"Retail Goods"
        }
    ],
    "sg:phone":"+1 306 463 2321",
    "sg:postcode":"S0L 1S0",
    "sg:province":"SK",
    "wof:name":"Home Hardware Stores",
    "wof:placetype":"venue"
},
  "geometry": {"coordinates":[-109.161057,51.47216],"type":"Point"}
}