{
  "type": "Feature",
  "properties": {
    "addr:full":"227 10E Av Lachine QC H8S 3E4",
    "addr:housenumber":"227",
    "addr:postcode":"h8s 3e4",
    "addr:street":"10E Av",
    "iso:country":"CA",
    "sg:address":"227 10E Av",
    "sg:city":"Lachine",
    "sg:classifiers":[
        {
            "category":"Shopping",
            "subcategory":"Clothing, Apparel, & Fashions",
            "type":"Retail Goods"
        }
    ],
    "sg:phone":"+1 514 637 6831",
    "sg:postcode":"H8S 3E4",
    "sg:province":"QC",
    "sg:tags":[
        "fur",
        "business"
    ],
    "wof:name":"Pageau Fourrures",
    "wof:placetype":"venue"
},
  "geometry": {"coordinates":[-73.6727676392,45.4353485107],"type":"Point"}
}