{
  "type": "Feature",
  "properties": {
    "addr:full":"Surrey BC V3W 3A4",
    "addr:postcode":"v3w 3a4",
    "iso:country":"CA",
    "sg:city":"Surrey",
    "sg:classifiers":[
        {
            "category":"Retail",
            "subcategory":"Auto Repair",
            "type":"Services"
        }
    ],
    "sg:phone":"+1 604 597 7788",
    "sg:postcode":"V3W 3A4",
    "sg:province":"BC",
    "sg:tags":[
        "repairing",
        "automobile",
        "body"
    ],
    "wof:name":"Ramy's Auto & Diesel Rep Ltd",
    "wof:placetype":"venue"
},
  "geometry": {"coordinates":[-122.874473572,49.1484260559],"type":"Point"}
}