{
  "type": "Feature",
  "properties": {
    "addr:full":"2050 Sheppard Ave E North York ON M2J 5B3",
    "addr:housenumber":"2050",
    "addr:postcode":"m2j 5b3",
    "addr:street":"Sheppard Ave E",
    "iso:country":"CA",
    "sg:address":"2050 Sheppard Ave E",
    "sg:city":"North York",
    "sg:classifiers":[
        {
            "category":"Professional",
            "subcategory":"Lawyer & Legal Services",
            "type":"Services"
        }
    ],
    "sg:phone":"+1 416 498 9122",
    "sg:postcode":"M2J 5B3",
    "sg:province":"ON",
    "sg:tags":[
        "naturalization",
        "immigration"
    ],
    "wof:name":"Canada Immigration Consulting",
    "wof:placetype":"venue"
},
  "geometry": {"coordinates":[-79.330276,43.775124],"type":"Point"}
}