{
  "type": "Feature",
  "properties": {
    "addr:full":"6127 Barlow Trail SE Calgary AB T2C 4W8",
    "addr:housenumber":"6127",
    "addr:postcode":"t2c 4w8",
    "addr:street":"Barlow Trail Se",
    "iso:country":"CA",
    "sg:address":"6127 Barlow Trail SE",
    "sg:city":"Calgary",
    "sg:classifiers":[
        {
            "category":"Banks & Credit Unions",
            "subcategory":"Bank",
            "type":"Services"
        }
    ],
    "sg:phone":"+1 403 269 9882",
    "sg:postcode":"T2C 4W8",
    "sg:province":"AB",
    "wof:name":"Canadian Western Bank",
    "wof:placetype":"venue"
},
  "geometry": {"coordinates":[-113.984306335,50.9983978271],"type":"Point"}
}