{
  "type": "Feature",
  "properties": {
    "addr:full":"10461 Av Henault Montreal-Nord QC H1G 5R5",
    "addr:postcode":"h1g 5r5",
    "addr:street":"Av Henault",
    "iso:country":"CA",
    "sg:address":"10461 Av Henault",
    "sg:city":"Montreal-Nord",
    "sg:classifiers":[
        {
            "category":"Retail",
            "subcategory":"Repair Shop",
            "type":"Services"
        }
    ],
    "sg:phone":"+1 514 322 6015",
    "sg:postcode":"H1G 5R5",
    "sg:province":"QC",
    "sg:tags":[
        "refinishing",
        "furniture"
    ],
    "wof:name":"Finitions Optima",
    "wof:placetype":"venue"
},
  "geometry": {"coordinates":[-73.62302398680001,45.5928115845],"type":"Point"}
}