{
  "type": "Feature",
  "properties": {
    "addr:full":"67 South Shore Rd Lake Cowichan BC V0R 2G0",
    "addr:housenumber":"67",
    "addr:postcode":"v0r 2g0",
    "addr:street":"South Shore Rd",
    "iso:country":"CA",
    "sg:address":"67 South Shore Rd",
    "sg:city":"Lake Cowichan",
    "sg:classifiers":[
        {
            "category":"Building & Trades",
            "subcategory":"Construction",
            "type":"Services"
        }
    ],
    "sg:phone":"+1 250 749 3542",
    "sg:postcode":"V0R 2G0",
    "sg:province":"BC",
    "sg:tags":[
        "tackle",
        "roofing",
        "fishing",
        "contractor"
    ],
    "wof:name":"Ed's Fix-It Shop Ltd",
    "wof:placetype":"venue"
},
  "geometry": {"coordinates":[-124.05738100000001,48.825218],"type":"Point"}
}