{
  "type": "Feature",
  "properties": {
    "addr:full":"Pointe-Claire QC H9R 5J2",
    "addr:postcode":"h9r 5j2",
    "iso:country":"CA",
    "sg:city":"Pointe-Claire",
    "sg:classifiers":[
        {
            "category":"Shopping",
            "subcategory":"Florist",
            "type":"Retail Goods"
        }
    ],
    "sg:phone":"+1 514 695 6160",
    "sg:postcode":"H9R 5J2",
    "sg:province":"QC",
    "wof:name":"Alain Simon Fleurs",
    "wof:placetype":"venue"
},
  "geometry": {"coordinates":[-73.81675720210001,45.4683609009],"type":"Point"}
}