{
  "type": "Feature",
  "properties": {
    "addr:full":"98 Brigantine Dr Coquitlam BC V3K 6Z6",
    "addr:housenumber":"98",
    "addr:postcode":"v3k 6z6",
    "addr:street":"Brigantine Dr",
    "iso:country":"CA",
    "sg:address":"98 Brigantine Dr",
    "sg:city":"Coquitlam",
    "sg:classifiers":[
        {
            "category":"Education",
            "subcategory":"Dance Studio",
            "type":"Public Place"
        }
    ],
    "sg:phone":"+1 604 523 6868",
    "sg:postcode":"V3K 6Z6",
    "sg:province":"BC",
    "sg:tags":[
        "instruction",
        "dancing"
    ],
    "wof:name":"Tri-City Dance Ctr",
    "wof:placetype":"venue"
},
  "geometry": {"coordinates":[-122.848885,49.228561],"type":"Point"}
}