{
  "type": "Feature",
  "properties": {
    "addr:full":"1374 Rue Eugene-Belisle Mont-Joli QC G5H 3Y8",
    "addr:housenumber":"1374",
    "addr:postcode":"g5h 3y8",
    "addr:street":"Rue Eugene-Belisle",
    "iso:country":"CA",
    "sg:address":"1374 Rue Eugene-Belisle",
    "sg:city":"Mont-Joli",
    "sg:classifiers":[
        {
            "category":"Building & Trades",
            "subcategory":"Electrical",
            "type":"Services"
        }
    ],
    "sg:phone":"+1 418 775 8160",
    "sg:postcode":"G5H 3Y8",
    "sg:province":"QC",
    "sg:tags":[
        "electric",
        "contractor"
    ],
    "wof:name":"Electriciens Jacques Berube",
    "wof:placetype":"venue"
},
  "geometry": {"coordinates":[-68.1879730225,48.5953407288],"type":"Point"}
}