{
  "type": "Feature",
  "properties": {
    "addr:full":"13058 50 St NW Edmonton AB T5A 4V9",
    "addr:housenumber":"13058",
    "addr:postcode":"t5a 4v9",
    "addr:street":"50 St Nw",
    "iso:country":"CA",
    "sg:address":"13058 50 St NW",
    "sg:city":"Edmonton",
    "sg:classifiers":[
        {
            "category":"Professional",
            "subcategory":"Business Services",
            "type":"Services"
        }
    ],
    "sg:phone":"+1 780 473 8899",
    "sg:postcode":"T5A 4V9",
    "sg:province":"AB",
    "sg:tags":[
        "license"
    ],
    "wof:name":"North East Registry Ltd",
    "wof:placetype":"venue"
},
  "geometry": {"coordinates":[-113.417435,53.59116],"type":"Point"}
}