{
  "type": "Feature",
  "properties": {
    "addr:full":"293 Rue Principale O Magog QC J1X 2A8",
    "addr:housenumber":"293",
    "addr:postcode":"j1x 2a8",
    "addr:street":"Rue Principale O",
    "iso:country":"CA",
    "sg:address":"293 Rue Principale O",
    "sg:city":"Magog",
    "sg:classifiers":[
        {
            "category":"Personal",
            "subcategory":"Beauty Salon",
            "type":"Services"
        }
    ],
    "sg:phone":"+1 819 843 3591",
    "sg:postcode":"J1X 2A8",
    "sg:province":"QC",
    "wof:name":"Salon Inter Coiffure",
    "wof:placetype":"venue"
},
  "geometry": {"coordinates":[-72.13910675050001,45.2628173828],"type":"Point"}
}