{
  "type": "Feature",
  "properties": {
    "addr:full":"315 Front St Stratford ON N5A 4J4",
    "addr:housenumber":"315",
    "addr:postcode":"n5a 4j4",
    "addr:street":"Front St",
    "iso:country":"CA",
    "sg:address":"315 Front St",
    "sg:city":"Stratford",
    "sg:classifiers":[
        {
            "category":"Education",
            "subcategory":"Special Training",
            "type":"Public Place"
        }
    ],
    "sg:phone":"+1 519 273 1105",
    "sg:postcode":"N5A 4J4",
    "sg:province":"ON",
    "sg:tags":[
        "instruction",
        "music"
    ],
    "wof:name":"Page Two Music Studios",
    "wof:placetype":"venue"
},
  "geometry": {"coordinates":[-80.9734573364,43.3654212952],"type":"Point"}
}