{
  "type": "Feature",
  "properties": {
    "addr:full":"Saint-Athanase QC J2X 1G9",
    "addr:postcode":"j2x 1g9",
    "iso:country":"CA",
    "sg:city":"Saint-Athanase",
    "sg:classifiers":[
        {
            "category":"Personal",
            "type":"Services"
        }
    ],
    "sg:phone":"+1 450 346 2205",
    "sg:postcode":"J2X 1G9",
    "sg:province":"QC",
    "sg:tags":[
        "electrolysis"
    ],
    "wof:name":"Clinique DE Beaute Maryse Enr",
    "wof:placetype":"venue"
},
  "geometry": {"coordinates":[-73.22789001460001,45.3131713867],"type":"Point"}
}