{
  "type": "Feature",
  "properties": {
    "addr:full":"200 Streambank Ave Sherwood Park AB T8H 1N1",
    "addr:housenumber":"200",
    "addr:postcode":"t8h 1n1",
    "addr:street":"Streambank Ave",
    "iso:country":"CA",
    "sg:address":"200 Streambank Ave",
    "sg:city":"Sherwood Park",
    "sg:classifiers":[
        {
            "category":"Local Transit",
            "type":"Transportation"
        }
    ],
    "sg:phone":"+1 780 417 7187",
    "sg:postcode":"T8H 1N1",
    "sg:province":"AB",
    "sg:tags":[
        "bus",
        "line"
    ],
    "wof:name":"Strathcona County Transit",
    "wof:placetype":"venue"
},
  "geometry": {"coordinates":[-113.321548462,53.559967041],"type":"Point"}
}