{
  "type": "Feature",
  "properties": {
    "addr:full":"1140 Rue Notre-Dame Lachine QC H8S 2C4",
    "addr:housenumber":"1140",
    "addr:postcode":"h8s 2c4",
    "addr:street":"Rue Notre-Dame",
    "iso:country":"CA",
    "sg:address":"1140 Rue Notre-Dame",
    "sg:city":"Lachine",
    "sg:classifiers":[
        {
            "category":"Health Services",
            "subcategory":"Optometrist",
            "type":"Services"
        }
    ],
    "sg:phone":"+1 514 634 7111",
    "sg:postcode":"H8S 2C4",
    "sg:province":"QC",
    "wof:name":"Cote, Elaine OD",
    "wof:placetype":"venue"
},
  "geometry": {"coordinates":[-73.673996,45.435059],"type":"Point"}
}