{
  "type": "Feature",
  "properties": {
    "addr:full":"Railway Ave Tees AB T0C 2N0",
    "addr:postcode":"t0c 2n0",
    "addr:street":"Railway Ave",
    "iso:country":"CA",
    "sg:address":"Railway Ave",
    "sg:city":"Tees",
    "sg:classifiers":[
        {
            "category":"Utilities",
            "subcategory":"Natural Gas",
            "type":"Services"
        }
    ],
    "sg:phone":"+1 403 784 3343",
    "sg:postcode":"T0C 2N0",
    "sg:province":"AB",
    "sg:tags":[
        "company"
    ],
    "wof:name":"Chain Lakes Gas CO-OP",
    "wof:placetype":"venue"
},
  "geometry": {"coordinates":[-113.32402,52.470009],"type":"Point"}
}