{
  "type": "Feature",
  "properties": {
    "addr:full":"550 Rue Deslauriers Saint-Laurent QC H4N 1V8",
    "addr:housenumber":"550",
    "addr:postcode":"h4n 1v8",
    "addr:street":"Rue Deslauriers",
    "iso:country":"CA",
    "sg:address":"550 Rue Deslauriers",
    "sg:city":"Saint-Laurent",
    "sg:classifiers":[
        {
            "category":"Wholesale",
            "subcategory":"Drugs",
            "type":"Manufacturing & Wholesale Goods"
        }
    ],
    "sg:phone":"+1 514 856 3031",
    "sg:postcode":"H4N 1V8",
    "sg:province":"QC",
    "sg:tags":[
        "food",
        "pharmaceutical",
        "natural"
    ],
    "wof:name":"Laboratoires Colba Inc",
    "wof:placetype":"venue"
},
  "geometry": {"coordinates":[-73.66551971440001,45.5243453979],"type":"Point"}
}