{
  "type": "Feature",
  "properties": {
    "addr:full":"377 Boul Cure-Poirier O Longueuil QC J4J 2H1",
    "addr:housenumber":"377",
    "addr:postcode":"j4j 2h1",
    "addr:street":"Boul Cure-Poirier O",
    "iso:country":"CA",
    "sg:address":"377 Boul Cure-Poirier O",
    "sg:city":"Longueuil",
    "sg:classifiers":[
        {
            "category":"Retail",
            "subcategory":"Auto Repair",
            "type":"Services"
        }
    ],
    "sg:phone":"+1 450 679 1960",
    "sg:postcode":"J4J 2H1",
    "sg:province":"QC",
    "sg:tags":[
        "repairing",
        "automobile",
        "muffler",
        "system",
        "exhaust"
    ],
    "wof:name":"Monsieur Muffler",
    "wof:placetype":"venue"
},
  "geometry": {"coordinates":[-73.47956848139999,45.5336112976],"type":"Point"}
}