{
  "type": "Feature",
  "properties": {
    "addr:full":"1089 Rue Saint-Cyrille Normandin QC G8M 4J5",
    "addr:housenumber":"1089",
    "addr:postcode":"g8m 4j5",
    "addr:street":"Rue Saint-Cyrille",
    "iso:country":"CA",
    "sg:address":"1089 Rue Saint-Cyrille",
    "sg:city":"Normandin",
    "sg:classifiers":[
        {
            "category":"Health Services",
            "subcategory":"Doctor",
            "type":"Services"
        }
    ],
    "sg:phone":"+1 418 274 3413",
    "sg:postcode":"G8M 4J5",
    "sg:province":"QC",
    "sg:tags":[
        "clinic",
        "dentist"
    ],
    "wof:name":"Clinique Dentaire H Leclerc",
    "wof:placetype":"venue"
},
  "geometry": {"coordinates":[-72.52908325200001,48.8369674683],"type":"Point"}
}