{
  "type": "Feature",
  "properties": {
    "iso:country":"CA",
    "sg:city":"Alliston",
    "sg:classifiers":[
        {
            "category":"Home & Garden",
            "subcategory":"Building Materials",
            "type":"Retail Goods"
        }
    ],
    "sg:phone":"+1 705 435 9869",
    "sg:postcode":"L9R 1K4",
    "sg:province":"ON",
    "sg:tags":[
        "paint"
    ],
    "wof:name":"Color Your World",
    "wof:placetype":"venue"
},
  "geometry": {"coordinates":[-79.855568,44.157059],"type":"Point"}
}