{
  "type": "Feature",
  "properties": {
    "addr:full":"2283 Rue Guenette Saint-Laurent QC H4R 2E9",
    "addr:housenumber":"2283",
    "addr:postcode":"h4r 2e9",
    "addr:street":"Rue Guenette",
    "iso:country":"CA",
    "sg:address":"2283 Rue Guenette",
    "sg:city":"Saint-Laurent",
    "sg:classifiers":[
        {
            "category":"Manufacturing",
            "subcategory":"Tools & Machinery",
            "type":"Manufacturing & Wholesale Goods"
        }
    ],
    "sg:phone":"+1 514 335 4575",
    "sg:postcode":"H4R 2E9",
    "sg:province":"QC",
    "sg:tags":[
        "industrial",
        "truck"
    ],
    "wof:name":"Germarc Equipements Inds Ltee",
    "wof:placetype":"venue"
},
  "geometry": {"coordinates":[-73.7259597778,45.4987258911],"type":"Point"}
}