{
  "type": "Feature",
  "properties": {
    "addr:full":"Waterdown ON L0R 2H6",
    "addr:postcode":"l0r 2h6",
    "iso:country":"CA",
    "sg:city":"Waterdown",
    "sg:classifiers":[
        {
            "category":"Shopping",
            "type":"Retail Goods"
        }
    ],
    "sg:phone":"+1 905 689 3377",
    "sg:postcode":"L0R 2H6",
    "sg:province":"ON",
    "sg:tags":[
        "pet",
        "food",
        "supply"
    ],
    "wof:name":"Ryan's Pet Food Inc",
    "wof:placetype":"venue"
},
  "geometry": {"coordinates":[-79.89720199999999,43.329884],"type":"Point"}
}