{
  "type": "Feature",
  "properties": {
    "iso:country":"CA",
    "sg:address":"613 113E Rue",
    "sg:city":"Shawinigan-Sud",
    "sg:classifiers":[
        {
            "category":"Food & Beverages",
            "subcategory":"Groceries & Convenience Stores",
            "type":"Retail Goods"
        }
    ],
    "sg:phone":"+1 819 536 5224",
    "sg:postcode":"G9P 2W8",
    "sg:province":"QC",
    "wof:name":"Depanneur Chez Tom Enr",
    "wof:placetype":"venue"
},
  "geometry": {"coordinates":[-72.7516708374,46.5229454041],"type":"Point"}
}