{
  "type": "Feature",
  "properties": {
    "addr:full":"48 Aspen Ave Souris MB R0K 2C0",
    "addr:housenumber":"48",
    "addr:postcode":"r0k 2c0",
    "addr:street":"Aspen Ave",
    "iso:country":"CA",
    "sg:address":"48 Aspen Ave",
    "sg:city":"Souris",
    "sg:classifiers":[
        {
            "category":"Building & Trades",
            "subcategory":"Equipment Rental",
            "type":"Services"
        }
    ],
    "sg:phone":"+1 204 483 3334",
    "sg:postcode":"R0K 2C0",
    "sg:province":"MB",
    "sg:tags":[
        "yard",
        "camping"
    ],
    "wof:name":"I am A Wild Party Spec Event",
    "wof:placetype":"venue"
},
  "geometry": {"coordinates":[-100.258865,49.620834],"type":"Point"}
}