{
  "type": "Feature",
  "properties": {
    "addr:full":"238 Lakeshore Rd E Oakville ON L6J 1H8",
    "addr:housenumber":"238",
    "addr:postcode":"l6j 1h8",
    "addr:street":"Lakeshore Rd E",
    "iso:country":"CA",
    "sg:address":"238 Lakeshore Rd E",
    "sg:city":"Oakville",
    "sg:classifiers":[
        {
            "category":"Health Services",
            "subcategory":"Health Practitioner",
            "type":"Services"
        }
    ],
    "sg:phone":"+1 905 842 8869",
    "sg:postcode":"L6J 1H8",
    "sg:province":"ON",
    "sg:tags":[
        "psychotherapist"
    ],
    "wof:name":"James Whetstone & Assoc",
    "wof:placetype":"venue"
},
  "geometry": {"coordinates":[-79.66738891599999,43.4463691711],"type":"Point"}
}