{
  "type": "Feature",
  "properties": {
    "iso:country":"CA",
    "sg:address":"293 Rue Saint-Joseph",
    "sg:city":"LA Tuque",
    "sg:classifiers":[
        {
            "category":"Shopping",
            "type":"Retail Goods"
        }
    ],
    "sg:phone":"+1 819 523 3802",
    "sg:postcode":"G9X 1K6",
    "sg:province":"QC",
    "sg:tags":[
        "pet",
        "shop"
    ],
    "wof:name":"Animalerie Aquatheque Inc",
    "wof:placetype":"venue"
},
  "geometry": {"coordinates":[-72.7853927612,47.4408454895],"type":"Point"}
}