{
  "type": "Feature",
  "properties": {
    "addr:full":"Vancouver BC V5Z 4B3",
    "addr:postcode":"v5z 4b3",
    "iso:country":"CA",
    "sg:city":"Vancouver",
    "sg:classifiers":[
        {
            "category":"Travel",
            "subcategory":"Travel Agent",
            "type":"Entertainment"
        }
    ],
    "sg:phone":"+1 604 879 6466",
    "sg:postcode":"V5Z 4B3",
    "sg:province":"BC",
    "sg:tags":[
        "bureau",
        "agency",
        "tours"
    ],
    "wof:name":"Globespan Travel",
    "wof:placetype":"venue"
},
  "geometry": {"coordinates":[-123.119011,49.267509],"type":"Point"}
}