{
  "type": "Feature",
  "properties": {
    "iso:country":"CA",
    "sg:address":"164 Greenlaw Ave",
    "sg:city":"Toronto",
    "sg:classifiers":[
        {
            "category":"Retail",
            "subcategory":"Laundry & Dry Cleaning",
            "type":"Services"
        }
    ],
    "sg:phone":"+1 416 654 8646",
    "sg:postcode":"M6H 3V5",
    "sg:province":"ON",
    "sg:tags":[
        "cleaners"
    ],
    "wof:name":"St Clair Cleaners",
    "wof:placetype":"venue"
},
  "geometry": {"coordinates":[-79.4480895996,43.6762886047],"type":"Point"}
}