{
  "type": "Feature",
  "properties": {
    "iso:country":"CA",
    "sg:city":"St Catharines",
    "sg:classifiers":[
        {
            "category":"Social Services",
            "type":"Services"
        }
    ],
    "sg:phone":"+1 905 685 5485",
    "sg:postcode":"L2W 1A4",
    "sg:province":"ON",
    "sg:tags":[
        "physiotherapist",
        "welfare",
        "organization"
    ],
    "wof:name":"Community Rehab",
    "wof:placetype":"venue"
},
  "geometry": {"coordinates":[-79.2773513794,43.1742172241],"type":"Point"}
}