{
  "type": "Feature",
  "properties": {
    "iso:country":"CA",
    "sg:address":"52 Av Leonidas S",
    "sg:city":"Rimouski",
    "sg:classifiers":[
        {
            "category":"Shopping",
            "type":"Retail Goods"
        }
    ],
    "sg:phone":"+1 418 725 3966",
    "sg:postcode":"G5L 2T2",
    "sg:province":"QC",
    "sg:tags":[
        "pet",
        "shop"
    ],
    "wof:name":"Animalerie Dyno Rimouski Enr",
    "wof:placetype":"venue"
},
  "geometry": {"coordinates":[-68.51501500000001,48.466213],"type":"Point"}
}