{
  "type": "Feature",
  "properties": {
    "addr:full":"Hinton AB T7V 1B4",
    "addr:postcode":"t7v 1b4",
    "iso:country":"CA",
    "sg:city":"Hinton",
    "sg:classifiers":[
        {
            "category":"Health Services",
            "subcategory":"Chiropractor",
            "type":"Services"
        }
    ],
    "sg:phone":"+1 780 865 8881",
    "sg:postcode":"T7V 1B4",
    "sg:province":"AB",
    "wof:name":"Hinton Chiropractic Clinic",
    "wof:placetype":"venue"
},
  "geometry": {"coordinates":[-117.54199218799999,53.4244308472],"type":"Point"}
}