{
  "type": "Feature",
  "properties": {
    "addr:full":"1894 Lasalle Blvd Sudbury ON P3A 2A4",
    "addr:housenumber":"1894",
    "addr:postcode":"p3a 2a4",
    "addr:street":"Lasalle Blvd",
    "iso:country":"CA",
    "sg:address":"1894 Lasalle Blvd",
    "sg:city":"Sudbury",
    "sg:classifiers":[
        {
            "category":"Restaurant",
            "type":"Food & Drink"
        }
    ],
    "sg:phone":"+1 705 521 1287",
    "sg:postcode":"P3A 2A4",
    "sg:province":"ON",
    "sg:tags":[
        "delicatessen"
    ],
    "wof:name":"Rossi's Lasalle Cheese & Deli",
    "wof:placetype":"venue"
},
  "geometry": {"coordinates":[-80.928787,46.522202],"type":"Point"}
}