{
  "type": "Feature",
  "properties": {
    "addr:full":"444 Montrose St Winnipeg MB R3M 3M9",
    "addr:housenumber":"444",
    "addr:postcode":"r3m 3m9",
    "addr:street":"Montrose St",
    "iso:country":"CA",
    "sg:address":"444 Montrose St",
    "sg:city":"Winnipeg",
    "sg:classifiers":[
        {
            "category":"Manufacturing",
            "subcategory":"Toys & Sporting Goods",
            "type":"Manufacturing & Wholesale Goods"
        }
    ],
    "sg:phone":"+1 204 487 0956",
    "sg:postcode":"R3M 3M9",
    "sg:province":"MB",
    "sg:tags":[
        "athletic"
    ],
    "wof:name":"Michael Ashton Agency",
    "wof:placetype":"venue"
},
  "geometry": {"coordinates":[-97.17879499999999,49.865139],"type":"Point"}
}