{
  "type": "Feature",
  "properties": {
    "addr:full":"376 Dunluce Rd NW Edmonton AB T5X 4K9",
    "addr:housenumber":"376",
    "addr:postcode":"t5x 4k9",
    "addr:street":"Dunluce Rd Nw",
    "iso:country":"CA",
    "sg:address":"376 Dunluce Rd NW",
    "sg:city":"Edmonton",
    "sg:classifiers":[
        {
            "category":"Building & Trades",
            "subcategory":"Cleaning & Sanitation",
            "type":"Services"
        }
    ],
    "sg:phone":"+1 780 456 4507",
    "sg:postcode":"T5X 4K9",
    "sg:province":"AB",
    "sg:tags":[
        "janitor"
    ],
    "wof:name":"Joe's Janitorial Svc Ltd",
    "wof:placetype":"venue"
},
  "geometry": {"coordinates":[-113.53465300000001,53.625816],"type":"Point"}
}