{
  "type": "Feature",
  "properties": {
    "addr:full":"2165 Boul Lemire Drummondville QC J2B 6X6",
    "addr:housenumber":"2165",
    "addr:postcode":"j2b 6x6",
    "addr:street":"Boul Lemire",
    "iso:country":"CA",
    "sg:address":"2165 Boul Lemire",
    "sg:city":"Drummondville",
    "sg:classifiers":[
        {
            "category":"Autos & Motor Vehicles",
            "subcategory":"Automobile Sales",
            "type":"Retail Goods"
        }
    ],
    "sg:phone":"+1 819 478 8511",
    "sg:postcode":"J2B 6X6",
    "sg:province":"QC",
    "sg:tags":[
        "car",
        "dealer"
    ],
    "wof:name":"Garage Mathieu & Cote Inc",
    "wof:placetype":"venue"
},
  "geometry": {"coordinates":[-72.5009384155,45.8651161194],"type":"Point"}
}