{
  "type": "Feature",
  "properties": {
    "addr:full":"236 King St E Toronto ON M5A 1K1",
    "addr:housenumber":"236",
    "addr:postcode":"m5a 1k1",
    "addr:street":"King St E",
    "iso:country":"CA",
    "sg:address":"236 King St E",
    "sg:city":"Toronto",
    "sg:classifiers":[
        {
            "category":"Professional",
            "type":"Services"
        }
    ],
    "sg:phone":"+1 416 971 6003",
    "sg:postcode":"M5A 1K1",
    "sg:province":"ON",
    "sg:tags":[
        "arranger",
        "music",
        "composer"
    ],
    "wof:name":"Egg Plant",
    "wof:placetype":"venue"
},
  "geometry": {"coordinates":[-79.3676605225,43.6515350342],"type":"Point"}
}