{
  "type": "Feature",
  "properties": {
    "addr:full":"2 Wintergreen Dr Moose Jaw SK S6J 1M9",
    "addr:housenumber":"2",
    "addr:postcode":"s6j 1m9",
    "addr:street":"Wintergreen Dr",
    "iso:country":"CA",
    "sg:address":"2 Wintergreen Dr",
    "sg:city":"Moose Jaw",
    "sg:classifiers":[
        {
            "category":"Organizations",
            "subcategory":"Religious Organization",
            "type":"Services"
        }
    ],
    "sg:phone":"+1 306 694 0045",
    "sg:postcode":"S6J 1M9",
    "sg:province":"SK",
    "sg:tags":[
        "church"
    ],
    "wof:name":"Salvation Army",
    "wof:placetype":"venue"
},
  "geometry": {"coordinates":[-105.55463399999999,50.412186],"type":"Point"}
}