{
  "type": "Feature",
  "properties": {
    "addr:full":"3 Concession St Nanticoke ON N0A 1L0",
    "addr:housenumber":"3",
    "addr:postcode":"n0a 1l0",
    "addr:street":"Concession St",
    "iso:country":"CA",
    "sg:address":"3 Concession St",
    "sg:city":"Nanticoke",
    "sg:classifiers":[
        {
            "category":"Wholesale",
            "subcategory":"Petroleum",
            "type":"Manufacturing & Wholesale Goods"
        }
    ],
    "sg:phone":"+1 519 587 4733",
    "sg:postcode":"N0A 1L0",
    "sg:province":"ON",
    "sg:tags":[
        "pipe",
        "line",
        "company"
    ],
    "wof:name":"Enbridge Pipelines Inc",
    "wof:placetype":"venue"
},
  "geometry": {"coordinates":[-80.07197600000001,42.810741],"type":"Point"}
}