{
  "type": "Feature",
  "properties": {
    "addr:full":"326 Rte Bellevue Sainte-Anne-Des-Monts QC G4V 2S6",
    "addr:housenumber":"326",
    "addr:postcode":"g4v 2s6",
    "addr:street":"Rte Bellevue",
    "iso:country":"CA",
    "sg:address":"326 Rte Bellevue",
    "sg:city":"Sainte-Anne-Des-Monts",
    "sg:classifiers":[
        {
            "category":"Building & Trades",
            "subcategory":"Construction",
            "type":"Services"
        }
    ],
    "sg:phone":"+1 418 763 3037",
    "sg:postcode":"G4V 2S6",
    "sg:province":"QC",
    "sg:tags":[
        "contractor"
    ],
    "wof:name":"Entreprise Fernand Gagnon Inc",
    "wof:placetype":"venue"
},
  "geometry": {"coordinates":[-66.5116729736,49.1141967773],"type":"Point"}
}