{
  "type": "Feature",
  "properties": {
    "iso:country":"CA",
    "sg:city":"Milton",
    "sg:classifiers":[
        {
            "category":"Manufacturing",
            "subcategory":"Tools & Machinery",
            "type":"Manufacturing & Wholesale Goods"
        }
    ],
    "sg:phone":"+1 905 878 4821",
    "sg:postcode":"L9T 4K6",
    "sg:province":"ON",
    "sg:tags":[
        "conditioning",
        "air",
        "system",
        "contractor"
    ],
    "wof:name":"Bailey Heating & Cooling",
    "wof:placetype":"venue"
},
  "geometry": {"coordinates":[-79.896965,43.519127],"type":"Point"}
}