{
  "type": "Feature",
  "properties": {
    "addr:full":"99 15E Rue Shippagan NB E8S 1E2",
    "addr:housenumber":"99",
    "addr:postcode":"e8s 1e2",
    "addr:street":"15E Rue Shippagan",
    "iso:country":"CA",
    "sg:address":"99 15E Rue",
    "sg:city":"Shippagan",
    "sg:classifiers":[
        {
            "category":"Manufacturing",
            "subcategory":"Food",
            "type":"Manufacturing & Wholesale Goods"
        }
    ],
    "sg:phone":"+1 506 336 2360",
    "sg:postcode":"E8S 1E2",
    "sg:province":"NB",
    "sg:tags":[
        "packer",
        "fish"
    ],
    "wof:name":"Pecheries Fn Fisheries Ltd",
    "wof:placetype":"venue"
},
  "geometry": {"coordinates":[-64.708763,47.743847],"type":"Point"}
}