{
  "type": "Feature",
  "properties": {
    "addr:full":"1865 Sheppard Ave W North York ON M3L 1Y5",
    "addr:housenumber":"1865",
    "addr:postcode":"m3l 1y5",
    "addr:street":"Sheppard Ave W",
    "iso:country":"CA",
    "sg:address":"1865 Sheppard Ave W",
    "sg:city":"North York",
    "sg:classifiers":[
        {
            "category":"Education",
            "subcategory":"School",
            "type":"Public Place"
        }
    ],
    "sg:phone":"+1 416 393 5344",
    "sg:postcode":"M3L 1Y5",
    "sg:province":"ON",
    "wof:name":"Saint Martha Elementary",
    "wof:placetype":"venue"
},
  "geometry": {"coordinates":[-79.50305899999999,43.741032],"type":"Point"}
}