{
  "type": "Feature",
  "properties": {
    "iso:country":"CA",
    "sg:address":"33 Windebanks Dr",
    "sg:city":"Ajax",
    "sg:classifiers":[
        {
            "category":"Building & Trades",
            "subcategory":"Construction",
            "type":"Services"
        }
    ],
    "sg:phone":"+1 905 426 5887",
    "sg:postcode":"L1S 4C5",
    "sg:province":"ON",
    "sg:tags":[
        "general",
        "contractor"
    ],
    "wof:name":"Noblett Carpentry Ltd",
    "wof:placetype":"venue"
},
  "geometry": {"coordinates":[-79.016663,43.829487],"type":"Point"}
}