{
  "type": "Feature",
  "properties": {
    "addr:full":"10290 Boul Louis-H.-Lafontaine Anjou QC H1J 2T3",
    "addr:housenumber":"10290",
    "addr:postcode":"h1j 2t3",
    "addr:street":"Boul Louis-H.-Lafontaine",
    "iso:country":"CA",
    "sg:address":"10290 Boul Louis-H.-Lafontaine",
    "sg:city":"Anjou",
    "sg:classifiers":[
        {
            "category":"Wholesale",
            "subcategory":"Chemicals & Plastics",
            "type":"Manufacturing & Wholesale Goods"
        }
    ],
    "sg:phone":"+1 514 354 4140",
    "sg:postcode":"H1J 2T3",
    "sg:province":"QC",
    "sg:tags":[
        "sanitary",
        "product",
        "compound",
        "cleaning",
        "supply"
    ],
    "wof:name":"Laboratoir Choisy Ltee",
    "wof:placetype":"venue"
},
  "geometry": {"coordinates":[-73.58487700000001,45.611706],"type":"Point"}
}