{
  "type": "Feature",
  "properties": {
    "addr:full":"Winnipeg MB R3M 3H5",
    "addr:postcode":"r3m 3h5",
    "iso:country":"CA",
    "sg:city":"Winnipeg",
    "sg:classifiers":[
        {
            "category":"Real Estate",
            "subcategory":"Real Estate Operator",
            "type":"Services"
        }
    ],
    "sg:phone":"+1 204 452 5903",
    "sg:postcode":"R3M 3H5",
    "sg:province":"MB",
    "sg:tags":[
        "apartment"
    ],
    "wof:name":"Cambridge South Condominiums",
    "wof:placetype":"venue"
},
  "geometry": {"coordinates":[-97.175766,49.852077],"type":"Point"}
}