{
  "type": "Feature",
  "properties": {
    "addr:full":"12109 100 St Grande Prairie AB T8V 4H1",
    "addr:housenumber":"12109",
    "addr:postcode":"t8v 4h1",
    "addr:street":"100 St",
    "iso:country":"CA",
    "sg:address":"12109 100 St",
    "sg:city":"Grande Prairie",
    "sg:classifiers":[
        {
            "category":"Autos & Motor Vehicles",
            "subcategory":"Fuel & Gas Station",
            "type":"Retail Goods"
        }
    ],
    "sg:phone":"+1 780 539 0430",
    "sg:postcode":"T8V 4H1",
    "sg:province":"AB",
    "sg:tags":[
        "oil"
    ],
    "wof:name":"Norwood Esso Ltd",
    "wof:placetype":"venue"
},
  "geometry": {"coordinates":[-118.793960571,55.1898918152],"type":"Point"}
}