{
  "type": "Feature",
  "properties": {
    "addr:full":"238 Bertie St Fort Erie ON L2A 1Z3",
    "addr:housenumber":"238",
    "addr:postcode":"l2a 1z3",
    "addr:street":"Bertie St",
    "iso:country":"CA",
    "sg:address":"238 Bertie St",
    "sg:city":"Fort Erie",
    "sg:classifiers":[
        {
            "category":"Health Services",
            "subcategory":"Health Practitioner",
            "type":"Services"
        }
    ],
    "sg:phone":"+1 905 871 3180",
    "sg:postcode":"L2A 1Z3",
    "sg:province":"ON",
    "sg:tags":[
        "physiotherapist"
    ],
    "wof:name":"Fort Erie Physiotherapy",
    "wof:placetype":"venue"
},
  "geometry": {"coordinates":[-78.9253692627,42.9127731323],"type":"Point"}
}