{
  "type": "Feature",
  "properties": {
    "addr:full":"555 Oak St E North Bay ON P1B 8E3",
    "addr:housenumber":"555",
    "addr:postcode":"p1b 8e3",
    "addr:street":"Oak St E",
    "iso:country":"CA",
    "sg:address":"555 Oak St E",
    "sg:city":"North Bay",
    "sg:classifiers":[
        {
            "category":"Bus Charters",
            "type":"Transportation"
        }
    ],
    "sg:phone":"+1 705 472 4500",
    "sg:postcode":"P1B 8E3",
    "sg:province":"ON",
    "sg:tags":[
        "rental"
    ],
    "wof:name":"Ontario Northland",
    "wof:placetype":"venue"
},
  "geometry": {"coordinates":[-79.45966300000001,46.304153],"type":"Point"}
}