{
  "type": "Feature",
  "properties": {
    "iso:country":"CA",
    "sg:address":"301 Railway Ave",
    "sg:city":"Dalmeny",
    "sg:classifiers":[
        {
            "category":"Government",
            "subcategory":"Office",
            "type":"Public Place"
        }
    ],
    "sg:phone":"+1 306 254 2133",
    "sg:postcode":"S0K 1E0",
    "sg:province":"SK",
    "sg:tags":[
        "village",
        "hall",
        "auditorium"
    ],
    "wof:name":"Dalmeny Town Office",
    "wof:placetype":"venue"
},
  "geometry": {"coordinates":[-106.780418396,52.340839386],"type":"Point"}
}