{
  "type": "Feature",
  "properties": {
    "addr:full":"705 Av Albert-Rousseau Saint-Etienne-DE-Lauzon QC G6J 1Z6",
    "addr:postcode":"g6j 1z6",
    "addr:street":"705 Av Albert-Rousseau Saint-Etienne-De-Lauzon",
    "iso:country":"CA",
    "sg:address":"705 Av Albert-Rousseau",
    "sg:city":"Saint-Etienne-DE-Lauzon",
    "sg:classifiers":[
        {
            "category":"Social Services",
            "subcategory":"Child Care",
            "type":"Services"
        }
    ],
    "sg:phone":"+1 418 831 7217",
    "sg:postcode":"G6J 1Z6",
    "sg:province":"QC",
    "wof:name":"Cpe LA Salopette Inc",
    "wof:placetype":"venue"
},
  "geometry": {"coordinates":[-71.3138961792,46.653553009],"type":"Point"}
}