{
  "type": "Feature",
  "properties": {
    "addr:full":"Victoria BC V8W 2C5",
    "addr:postcode":"v8w 2c5",
    "iso:country":"CA",
    "sg:city":"Victoria",
    "sg:classifiers":[
        {
            "category":"Education",
            "subcategory":"Special Training",
            "type":"Public Place"
        }
    ],
    "sg:phone":"+1 250 384 2432",
    "sg:postcode":"V8W 2C5",
    "sg:province":"BC",
    "sg:tags":[
        "consultant",
        "management",
        "business"
    ],
    "wof:name":"Business Victoria",
    "wof:placetype":"venue"
},
  "geometry": {"coordinates":[-123.365341187,48.4239006042],"type":"Point"}
}