{
  "type": "Feature",
  "properties": {
    "addr:full":"125 Rue Jacques-Cartier N Saint-Jean-Sur-Richelieu QC J3B 8C9",
    "addr:housenumber":"125",
    "addr:postcode":"j3b 8c9",
    "addr:street":"Rue Jacques-Cartier N",
    "iso:country":"CA",
    "sg:address":"125 Rue Jacques-Cartier N",
    "sg:city":"Saint-Jean-Sur-Richelieu",
    "sg:classifiers":[
        {
            "category":"Organizations",
            "subcategory":"Professional Association",
            "type":"Services"
        }
    ],
    "sg:phone":"+1 450 347 8091",
    "sg:postcode":"J3B 8C9",
    "sg:province":"QC",
    "wof:name":"Parrainage Civique Du Haut",
    "wof:placetype":"venue"
},
  "geometry": {"coordinates":[-73.2532424927,45.3021774292],"type":"Point"}
}