{
  "type": "Feature",
  "properties": {
    "addr:full":"4833 Lazelle Ave Terrace BC V8G 1T5",
    "addr:housenumber":"4833",
    "addr:postcode":"v8g 1t5",
    "addr:street":"Lazelle Ave",
    "iso:country":"CA",
    "sg:address":"4833 Lazelle Ave",
    "sg:city":"Terrace",
    "sg:classifiers":[
        {
            "category":"Wholesale",
            "subcategory":"Scrap",
            "type":"Manufacturing & Wholesale Goods"
        }
    ],
    "sg:phone":"+1 250 635 2157",
    "sg:postcode":"V8G 1T5",
    "sg:province":"BC",
    "sg:tags":[
        "recycling",
        "center"
    ],
    "wof:name":"Northwest Cartridge Exchange",
    "wof:placetype":"venue"
},
  "geometry": {"coordinates":[-128.601257,54.517696],"type":"Point"}
}