{
  "type": "Feature",
  "properties": {
    "addr:full":"150 Rue Frontenac Sherbrooke QC J1H 1J9",
    "addr:housenumber":"150",
    "addr:postcode":"j1h 1j9",
    "addr:street":"Rue Frontenac",
    "iso:country":"CA",
    "sg:address":"150 Rue Frontenac",
    "sg:city":"Sherbrooke",
    "sg:classifiers":[
        {
            "category":"Real Estate",
            "subcategory":"Real Estate Agent",
            "type":"Services"
        }
    ],
    "sg:phone":"+1 819 820 2286",
    "sg:postcode":"J1H 1J9",
    "sg:province":"QC",
    "wof:name":"Distributions Matinales",
    "wof:placetype":"venue"
},
  "geometry": {"coordinates":[-71.893699646,45.4041290283],"type":"Point"}
}