{
  "type": "Feature",
  "properties": {
    "addr:full":"PO Box 7137 STN Main Drayton Valley AB T7A 1S4",
    "addr:housenumber":"po",
    "addr:postcode":"t7a 1s4",
    "addr:street":"Box 7137 Stn Main",
    "iso:country":"CA",
    "sg:address":"PO Box 7137 STN Main",
    "sg:city":"Drayton Valley",
    "sg:classifiers":[
        {
            "category":"Manufacturing",
            "subcategory":"Lumber",
            "type":"Manufacturing & Wholesale Goods"
        }
    ],
    "sg:phone":"+1 780 542 3918",
    "sg:postcode":"T7A 1S4",
    "sg:province":"AB",
    "sg:tags":[
        "company",
        "logging"
    ],
    "wof:name":"Elk River Transport",
    "wof:placetype":"venue"
},
  "geometry": {"coordinates":[-114.9868927,53.2279968262],"type":"Point"}
}