{
  "type": "Feature",
  "properties": {
    "addr:full":"39 Hogarth Ave Toronto ON M4K 1J8",
    "addr:housenumber":"39",
    "addr:postcode":"m4k 1j8",
    "addr:street":"Hogarth Ave",
    "iso:country":"CA",
    "sg:address":"39 Hogarth Ave",
    "sg:city":"Toronto",
    "sg:classifiers":[
        {
            "category":"Building & Trades",
            "subcategory":"Construction",
            "type":"Services"
        }
    ],
    "sg:phone":"+1 416 465 3790",
    "sg:postcode":"M4K 1J8",
    "sg:province":"ON",
    "sg:tags":[
        "roofing",
        "contractor"
    ],
    "wof:name":"Conitec Group Inc",
    "wof:placetype":"venue"
},
  "geometry": {"coordinates":[-79.354133606,43.6736183167],"type":"Point"}
}