{
  "type": "Feature",
  "properties": {
    "iso:country":"CA",
    "sg:address":"3640 Rle Mercier",
    "sg:city":"Lac-Megantic",
    "sg:classifiers":[
        {
            "category":"Manufacturing",
            "subcategory":"Tools & Machinery",
            "type":"Manufacturing & Wholesale Goods"
        }
    ],
    "sg:phone":"+1 819 583 0777",
    "sg:postcode":"G6B 2T7",
    "sg:province":"QC",
    "sg:tags":[
        "machine"
    ],
    "wof:name":"Atelier D'Usinage M Mercier",
    "wof:placetype":"venue"
},
  "geometry": {"coordinates":[-70.8801727295,45.5725708008],"type":"Point"}
}