{
  "type": "Feature",
  "properties": {
    "addr:full":"164 Beverly St Cambridge ON N1R 3Z7",
    "addr:housenumber":"164",
    "addr:postcode":"n1r 3z7",
    "addr:street":"Beverly St",
    "iso:country":"CA",
    "sg:address":"164 Beverly St",
    "sg:city":"Cambridge",
    "sg:classifiers":[
        {
            "category":"Restaurant",
            "type":"Food & Drink"
        }
    ],
    "sg:phone":"+1 519 740 9860",
    "sg:postcode":"N1R 3Z7",
    "sg:province":"ON",
    "wof:name":"Oliver's Bar & Grill",
    "wof:placetype":"venue"
},
  "geometry": {"coordinates":[-80.306343,43.365749],"type":"Point"}
}