{
  "type": "Feature",
  "properties": {
    "addr:full":"Surrey BC V3S 1G3",
    "addr:postcode":"v3s 1g3",
    "iso:country":"CA",
    "sg:city":"Surrey",
    "sg:classifiers":[
        {
            "category":"Health Services",
            "subcategory":"Chiropractor",
            "type":"Services"
        }
    ],
    "sg:phone":"+1 604 574 4222",
    "sg:postcode":"V3S 1G3",
    "sg:province":"BC",
    "wof:name":"Gasparin, Morris D DC",
    "wof:placetype":"venue"
},
  "geometry": {"coordinates":[-122.830215454,49.105178833],"type":"Point"}
}