{
  "type": "Feature",
  "properties": {
    "addr:full":"300 Av DE LA Concorde N Saint-Hyacinthe QC J2S 4N7",
    "addr:postcode":"j2s 4n7",
    "addr:street":"300 Av De La Concorde N",
    "iso:country":"CA",
    "sg:address":"300 Av DE LA Concorde N",
    "sg:city":"Saint-Hyacinthe",
    "sg:classifiers":[
        {
            "category":"Organizations",
            "subcategory":"Religious Organization",
            "type":"Services"
        }
    ],
    "sg:phone":"+1 450 774 4684",
    "sg:postcode":"J2S 4N7",
    "sg:province":"QC",
    "sg:tags":[
        "church"
    ],
    "wof:name":"Christ-Roi",
    "wof:placetype":"venue"
},
  "geometry": {"coordinates":[-72.94175720210001,45.6251907349],"type":"Point"}
}