{
  "type": "Feature",
  "properties": {
    "addr:full":"Burlington ON L7S 2J8",
    "addr:postcode":"l7s 2j8",
    "iso:country":"CA",
    "sg:city":"Burlington",
    "sg:classifiers":[
        {
            "category":"Shopping",
            "subcategory":"Jewelry",
            "type":"Retail Goods"
        }
    ],
    "sg:phone":"+1 905 639 6678",
    "sg:postcode":"L7S 2J8",
    "sg:province":"ON",
    "sg:tags":[
        "jeweler"
    ],
    "wof:name":"Barry's Jewellers",
    "wof:placetype":"venue"
},
  "geometry": {"coordinates":[-79.8197021484,43.3278427124],"type":"Point"}
}