{
  "type": "Feature",
  "properties": {
    "addr:full":"258 Main St S Newmarket ON L3Y 3Z5",
    "addr:housenumber":"258",
    "addr:postcode":"l3y 3z5",
    "addr:street":"Main St S",
    "iso:country":"CA",
    "sg:address":"258 Main St S",
    "sg:city":"Newmarket",
    "sg:classifiers":[
        {
            "category":"Banks & Credit Unions",
            "subcategory":"Bank",
            "type":"Services"
        }
    ],
    "sg:phone":"+1 905 853 4985",
    "sg:postcode":"L3Y 3Z5",
    "sg:province":"ON",
    "wof:name":"Scotiabank",
    "wof:placetype":"venue"
},
  "geometry": {"coordinates":[-79.45677947999999,44.0519943237],"type":"Point"}
}