{
  "type": "Feature",
  "properties": {
    "addr:full":"3230 Lauren Mary Pl Nanaimo BC V9T 5R5",
    "addr:housenumber":"3230",
    "addr:postcode":"v9t 5r5",
    "addr:street":"Lauren Mary Pl",
    "iso:country":"CA",
    "sg:address":"3230 Lauren Mary Pl",
    "sg:city":"Nanaimo",
    "sg:classifiers":[
        {
            "category":"Building & Trades",
            "subcategory":"Construction",
            "type":"Services"
        }
    ],
    "sg:phone":"+1 250 756 3137",
    "sg:postcode":"V9T 5R5",
    "sg:province":"BC",
    "sg:tags":[
        "contractor"
    ],
    "wof:name":"Trelin Enterprises Ltd",
    "wof:placetype":"venue"
},
  "geometry": {"coordinates":[-123.981651306,49.2147445679],"type":"Point"}
}