{
  "type": "Feature",
  "properties": {
    "addr:full":"10164 Yonge St Richmond Hill ON L4C 1T6",
    "addr:housenumber":"10164",
    "addr:postcode":"l4c 1t6",
    "addr:street":"Yonge St",
    "iso:country":"CA",
    "sg:address":"10164 Yonge St",
    "sg:city":"Richmond Hill",
    "sg:classifiers":[
        {
            "category":"Personal",
            "subcategory":"Beauty Salon",
            "type":"Services"
        }
    ],
    "sg:phone":"+1 905 884 5484",
    "sg:postcode":"L4C 1T6",
    "sg:province":"ON",
    "wof:name":"Farah Salon & Spa",
    "wof:placetype":"venue"
},
  "geometry": {"coordinates":[-79.43828600000001,43.875198],"type":"Point"}
}