{
  "type": "Feature",
  "properties": {
    "addr:full":"141 Rue Du Gouverneur Vaudreuil-Dorion QC J7V 9L1",
    "addr:housenumber":"141",
    "addr:postcode":"j7v 9l1",
    "addr:street":"Rue Du Gouverneur",
    "iso:country":"CA",
    "sg:address":"141 Rue Du Gouverneur",
    "sg:city":"Vaudreuil-Dorion",
    "sg:classifiers":[
        {
            "category":"Building & Trades",
            "subcategory":"Electrical",
            "type":"Services"
        }
    ],
    "sg:phone":"+1 450 424 2222",
    "sg:postcode":"J7V 9L1",
    "sg:province":"QC",
    "sg:tags":[
        "electric",
        "contractor"
    ],
    "wof:name":"Lafleche Electrique",
    "wof:placetype":"venue"
},
  "geometry": {"coordinates":[-74.0282897949,45.4035072327],"type":"Point"}
}