{
  "type": "Feature",
  "properties": {
    "addr:full":"366 Eglinton Ave W Toronto ON M5N 1A2",
    "addr:housenumber":"366",
    "addr:postcode":"m5n 1a2",
    "addr:street":"Eglinton Ave W",
    "iso:country":"CA",
    "sg:address":"366 Eglinton Ave W",
    "sg:city":"Toronto",
    "sg:classifiers":[
        {
            "category":"Home & Garden",
            "subcategory":"Carpets & Floor Coverings",
            "type":"Retail Goods"
        }
    ],
    "sg:phone":"+1 416 932 9734",
    "sg:postcode":"M5N 1A2",
    "sg:province":"ON",
    "sg:tags":[
        "dealer",
        "rug"
    ],
    "wof:name":"Hakim Rugs",
    "wof:placetype":"venue"
},
  "geometry": {"coordinates":[-79.40933990480001,43.7045707703],"type":"Point"}
}