{
  "type": "Feature",
  "properties": {
    "addr:full":"Antigonish NS B2G 1N5",
    "addr:postcode":"b2g 1n5",
    "iso:country":"CA",
    "sg:city":"Antigonish",
    "sg:classifiers":[
        {
            "category":"Building & Trades",
            "subcategory":"Construction",
            "type":"Services"
        }
    ],
    "sg:phone":"+1 902 863 3735",
    "sg:postcode":"B2G 1N5",
    "sg:province":"NS",
    "sg:tags":[
        "general",
        "contractor"
    ],
    "wof:name":"A & R Venedam Construction Ltd",
    "wof:placetype":"venue"
},
  "geometry": {"coordinates":[-62.015881,45.779221],"type":"Point"}
}