{
  "type": "Feature",
  "properties": {
    "addr:full":"187 Boucherville Rd Stratton ON P0W 1N0",
    "addr:housenumber":"187",
    "addr:postcode":"p0w 1n0",
    "addr:street":"Boucherville Rd",
    "iso:country":"CA",
    "sg:address":"187 Boucherville Rd",
    "sg:city":"Stratton",
    "sg:classifiers":[
        {
            "category":"Wholesale",
            "subcategory":"Farm Supplies",
            "type":"Manufacturing & Wholesale Goods"
        }
    ],
    "sg:phone":"+1 807 483 5865",
    "sg:postcode":"P0W 1N0",
    "sg:province":"ON",
    "sg:tags":[
        "fertilizer"
    ],
    "wof:name":"Northland Fertilizer",
    "wof:placetype":"venue"
},
  "geometry": {"coordinates":[-94.16321600000001,48.683563],"type":"Point"}
}