{
  "type": "Feature",
  "properties": {
    "addr:full":"6 Rutherford Rd S Brampton ON L6W 3J1",
    "addr:housenumber":"6",
    "addr:postcode":"l6w 3j1",
    "addr:street":"Rutherford Rd S",
    "iso:country":"CA",
    "sg:address":"6 Rutherford Rd S",
    "sg:city":"Brampton",
    "sg:classifiers":[
        {
            "category":"Retail",
            "subcategory":"Auto Repair",
            "type":"Services"
        }
    ],
    "sg:phone":"+1 905 457 8249",
    "sg:postcode":"L6W 3J1",
    "sg:province":"ON",
    "sg:tags":[
        "repairing",
        "automobile"
    ],
    "wof:name":"Brampton Auto Ctr",
    "wof:placetype":"venue"
},
  "geometry": {"coordinates":[-79.741692,43.701317],"type":"Point"}
}