{
  "type": "Feature",
  "properties": {
    "addr:full":"2592 Finch Ave W North York ON M9M 2G3",
    "addr:housenumber":"2592",
    "addr:postcode":"m9m 2g3",
    "addr:street":"Finch Ave W",
    "iso:country":"CA",
    "sg:address":"2592 Finch Ave W",
    "sg:city":"North York",
    "sg:classifiers":[
        {
            "category":"Food & Beverages",
            "subcategory":"Groceries & Convenience Stores",
            "type":"Retail Goods"
        }
    ],
    "sg:phone":"+1 416 747 0982",
    "sg:postcode":"M9M 2G3",
    "sg:province":"ON",
    "sg:tags":[
        "grocer"
    ],
    "wof:name":"Galati Bros Supermarkets",
    "wof:placetype":"venue"
},
  "geometry": {"coordinates":[-79.56204200000001,43.747982],"type":"Point"}
}