{
  "type": "Feature",
  "properties": {
    "iso:country":"CA",
    "sg:address":"259 Brunswick St #204",
    "sg:city":"Fredericton",
    "sg:classifiers":[
        {
            "category":"Professional",
            "subcategory":"Lawyer & Legal Services",
            "type":"Services"
        }
    ],
    "sg:phone":"+1 506 451 4726",
    "sg:postcode":"E3B 1G8",
    "sg:province":"NB",
    "sg:tags":[
        "attorney"
    ],
    "wof:name":"Gale L Mac Donald Law Office",
    "wof:placetype":"venue"
},
  "geometry": {"coordinates":[-66.64785766599999,45.9625892639],"type":"Point"}
}