{
  "type": "Feature",
  "properties": {
    "iso:country":"CA",
    "sg:address":"2084 Speers Rd # 1",
    "sg:city":"Oakville",
    "sg:classifiers":[
        {
            "category":"Retail",
            "subcategory":"Laundry & Dry Cleaning",
            "type":"Services"
        }
    ],
    "sg:phone":"+1 905 465 2337",
    "sg:postcode":"L6L 2X8",
    "sg:province":"ON",
    "sg:tags":[
        "cleaners",
        "rug",
        "carpet"
    ],
    "wof:name":"Lakeshore Carpet Cleaners",
    "wof:placetype":"venue"
},
  "geometry": {"coordinates":[-79.719788,43.416267],"type":"Point"}
}