{
  "type": "Feature",
  "properties": {
    "addr:full":"37 St Lawrence St W Madoc ON K0K 2K0",
    "addr:housenumber":"37",
    "addr:postcode":"k0k 2k0",
    "addr:street":"St Lawrence St W",
    "iso:country":"CA",
    "sg:address":"37 St Lawrence St W",
    "sg:city":"Madoc",
    "sg:classifiers":[
        {
            "category":"Wholesale",
            "subcategory":"Meat",
            "type":"Manufacturing & Wholesale Goods"
        }
    ],
    "sg:phone":"+1 613 473 0508",
    "sg:postcode":"K0K 2K0",
    "sg:province":"ON",
    "sg:tags":[
        "butchering"
    ],
    "wof:name":"One Stop Butcher Shop",
    "wof:placetype":"venue"
},
  "geometry": {"coordinates":[-77.473213,44.504959],"type":"Point"}
}