{
  "type": "Feature",
  "properties": {
    "addr:full":"5152 Rue Jean-Talon E Saint-Leonard QC H1S 1K7",
    "addr:housenumber":"5152",
    "addr:postcode":"h1s 1k7",
    "addr:street":"Rue Jean-Talon E",
    "iso:country":"CA",
    "sg:address":"5152 Rue Jean-Talon E",
    "sg:city":"Saint-Leonard",
    "sg:classifiers":[
        {
            "category":"Professional",
            "subcategory":"Business Services",
            "type":"Services"
        }
    ],
    "sg:phone":"+1 514 593 1002",
    "sg:postcode":"H1S 1K7",
    "sg:province":"QC",
    "sg:tags":[
        "notary"
    ],
    "wof:name":"Scaglione, Giovanni",
    "wof:placetype":"venue"
},
  "geometry": {"coordinates":[-73.58309199999999,45.577007],"type":"Point"}
}