{
  "type": "Feature",
  "properties": {
    "addr:full":"125 Dolomite Dr North York ON M3J 2N1",
    "addr:housenumber":"125",
    "addr:postcode":"m3j 2n1",
    "addr:street":"Dolomite Dr",
    "iso:country":"CA",
    "sg:address":"125 Dolomite Dr",
    "sg:city":"North York",
    "sg:classifiers":[
        {
            "category":"Manufacturing",
            "subcategory":"Jewelry",
            "type":"Manufacturing & Wholesale Goods"
        }
    ],
    "sg:phone":"+1 416 588 0107",
    "sg:postcode":"M3J 2N1",
    "sg:province":"ON",
    "sg:tags":[
        "polishing"
    ],
    "wof:name":"Carman's Star Jewellers Ltd",
    "wof:placetype":"venue"
},
  "geometry": {"coordinates":[-79.472267,43.780159],"type":"Point"}
}