{
  "type": "Feature",
  "properties": {
    "iso:country":"CA",
    "sg:city":"Waterdown",
    "sg:classifiers":[
        {
            "category":"Personal",
            "subcategory":"Barber",
            "type":"Services"
        }
    ],
    "sg:phone":"+1 905 689 7151",
    "sg:postcode":"L0R 2H0",
    "sg:province":"ON",
    "wof:name":"Retreat Hairstyling For Men",
    "wof:placetype":"venue"
},
  "geometry": {"coordinates":[-79.892166,43.333107],"type":"Point"}
}