{
  "type": "Feature",
  "properties": {
    "addr:full":"59 Rue Monfette # 213 Victoriaville QC G6P 1J8",
    "addr:housenumber":"59",
    "addr:postcode":"g6p 1j8",
    "addr:street":"Rue Monfette # 213",
    "iso:country":"CA",
    "sg:address":"59 Rue Monfette # 213",
    "sg:city":"Victoriaville",
    "sg:classifiers":[
        {
            "category":"Professional",
            "subcategory":"Research",
            "type":"Services"
        }
    ],
    "sg:phone":"+1 819 758 0606",
    "sg:postcode":"G6P 1J8",
    "sg:province":"QC",
    "sg:tags":[
        "environmental",
        "ecological"
    ],
    "wof:name":"Centre DE Recherche & Edctn",
    "wof:placetype":"venue"
},
  "geometry": {"coordinates":[-71.96629299999999,46.061481],"type":"Point"}
}