{
  "type": "Feature",
  "properties": {
    "addr:full":"280 Rue Robinson S Granby QC J2G 7M8",
    "addr:housenumber":"280",
    "addr:postcode":"j2g 7m8",
    "addr:street":"Rue Robinson S Granby",
    "iso:country":"CA",
    "sg:address":"280 Rue Robinson S",
    "sg:city":"Granby",
    "sg:classifiers":[
        {
            "category":"Wholesale",
            "subcategory":"Electrical",
            "type":"Manufacturing & Wholesale Goods"
        }
    ],
    "sg:phone":"+1 450 375 2101",
    "sg:postcode":"J2G 7M8",
    "sg:province":"QC",
    "sg:tags":[
        "equipment",
        "electric",
        "supply"
    ],
    "wof:name":"Fournitures Electrique Andre",
    "wof:placetype":"venue"
},
  "geometry": {"coordinates":[-72.741348,45.398319],"type":"Point"}
}