{
  "type": "Feature",
  "properties": {
    "addr:full":"Brampton ON L6T 5G7",
    "addr:postcode":"l6t 5g7",
    "iso:country":"CA",
    "sg:city":"Brampton",
    "sg:classifiers":[
        {
            "category":"Manufacturing",
            "subcategory":"Tools & Machinery",
            "type":"Manufacturing & Wholesale Goods"
        }
    ],
    "sg:phone":"+1 905 793 5185",
    "sg:postcode":"L6T 5G7",
    "sg:province":"ON",
    "wof:name":"Ragogna Custom Machinery Ltd",
    "wof:placetype":"venue"
},
  "geometry": {"coordinates":[-79.64893341059999,43.7379646301],"type":"Point"}
}