{
  "type": "Feature",
  "properties": {
    "addr:full":"Winnipeg MB R3J 0H2",
    "addr:postcode":"r3j 0h2",
    "iso:country":"CA",
    "sg:city":"Winnipeg",
    "sg:classifiers":[
        {
            "category":"Professional",
            "subcategory":"Accounting & Tax Preparation",
            "type":"Services"
        }
    ],
    "sg:phone":"+1 204 889 0992",
    "sg:postcode":"R3J 0H2",
    "sg:province":"MB",
    "sg:tags":[
        "accountant"
    ],
    "wof:name":"Hodgins, Ken CA",
    "wof:placetype":"venue"
},
  "geometry": {"coordinates":[-97.21849822999999,49.8784408569],"type":"Point"}
}