{
  "type": "Feature",
  "properties": {
    "addr:full":"3016 Lonsdale Ave North Vancouver BC V7N 3J5",
    "addr:housenumber":"3016",
    "addr:postcode":"v7n 3j5",
    "addr:street":"Lonsdale Ave",
    "iso:country":"CA",
    "sg:address":"3016 Lonsdale Ave",
    "sg:city":"North Vancouver",
    "sg:classifiers":[
        {
            "category":"Retail",
            "subcategory":"Laundry & Dry Cleaning",
            "type":"Services"
        }
    ],
    "sg:phone":"+1 604 988 6541",
    "sg:postcode":"V7N 3J5",
    "sg:province":"BC",
    "sg:tags":[
        "cleaners"
    ],
    "wof:name":"Queensdale One-Hour Cleaners",
    "wof:placetype":"venue"
},
  "geometry": {"coordinates":[-123.071960449,49.3356513977],"type":"Point"}
}