{
  "type": "Feature",
  "properties": {
    "iso:country":"CA",
    "sg:address":"10223 164 Ave NW",
    "sg:city":"Edmonton",
    "sg:classifiers":[
        {
            "category":"Retail",
            "subcategory":"Veterinary Services",
            "type":"Services"
        }
    ],
    "sg:phone":"+1 780 456 3616",
    "sg:postcode":"T5X 3C9",
    "sg:province":"AB",
    "sg:tags":[
        "veterinarian"
    ],
    "wof:name":"Castledowns Animal Clinic",
    "wof:placetype":"venue"
},
  "geometry": {"coordinates":[-113.500427,53.625481],"type":"Point"}
}