{
  "type": "Feature",
  "properties": {
    "iso:country":"CA",
    "sg:address":"140 Esplanade Ave",
    "sg:city":"Harrison Hot Springs",
    "sg:classifiers":[
        {
            "category":"Travel",
            "subcategory":"Hotels & Motels",
            "type":"Entertainment"
        }
    ],
    "sg:phone":"+1 604 796 2828",
    "sg:postcode":"V0M 1K0",
    "sg:province":"BC",
    "wof:name":"Harrison Spa Motel",
    "wof:placetype":"venue"
},
  "geometry": {"coordinates":[-116.071266174,50.6213645935],"type":"Point"}
}