{
  "type": "Feature",
  "properties": {
    "addr:full":"596 Davis Dr Newmarket ON L3Y 2P9",
    "addr:housenumber":"596",
    "addr:postcode":"l3y 2p9",
    "addr:street":"Davis Dr",
    "iso:country":"CA",
    "sg:address":"596 Davis Dr",
    "sg:city":"Newmarket",
    "sg:classifiers":[
        {
            "category":"Shopping",
            "subcategory":"Pharmacy",
            "type":"Retail Goods"
        }
    ],
    "sg:phone":"+1 905 830 5988",
    "sg:postcode":"L3Y 2P9",
    "sg:province":"ON",
    "wof:name":"Bridle Trail Pharmacy",
    "wof:placetype":"venue"
},
  "geometry": {"coordinates":[-79.4530944824,44.0608253479],"type":"Point"}
}