{
  "type": "Feature",
  "properties": {
    "addr:full":"Vancouver BC V6Z 2S9",
    "addr:postcode":"v6z 2s9",
    "iso:country":"CA",
    "sg:city":"Vancouver",
    "sg:classifiers":[
        {
            "category":"Government",
            "subcategory":"Office",
            "type":"Public Place"
        }
    ],
    "sg:phone":"+1 604 666 2061",
    "sg:postcode":"V6Z 2S9",
    "sg:province":"BC",
    "wof:name":"Canada Justice Department",
    "wof:placetype":"venue"
},
  "geometry": {"coordinates":[-123.12153600000001,49.281254],"type":"Point"}
}