{
  "type": "Feature",
  "properties": {
    "addr:full":"Innisfail AB T4G 1S7",
    "addr:postcode":"t4g 1s7",
    "iso:country":"CA",
    "sg:city":"Innisfail",
    "sg:classifiers":[
        {
            "category":"Retail",
            "subcategory":"Auto Repair",
            "type":"Services"
        }
    ],
    "sg:phone":"+1 403 227 2424",
    "sg:postcode":"T4G 1S7",
    "sg:province":"AB",
    "sg:tags":[
        "repairing",
        "automobile"
    ],
    "wof:name":"Specialty Automotive Repairs",
    "wof:placetype":"venue"
},
  "geometry": {"coordinates":[-113.969032,52.018635],"type":"Point"}
}