{
  "type": "Feature",
  "properties": {
    "iso:country":"CA",
    "sg:address":"1670 Rue Notre-Dame E",
    "sg:city":"Montreal",
    "sg:classifiers":[
        {
            "category":"Banks & Credit Unions",
            "subcategory":"Bank",
            "type":"Services"
        }
    ],
    "sg:phone":"+1 514 598 6988",
    "sg:postcode":"H2L 2R4",
    "sg:province":"QC",
    "wof:name":"Caisse D'Economie Desjardins",
    "wof:placetype":"venue"
},
  "geometry": {"coordinates":[-73.547806,45.518517],"type":"Point"}
}