{
  "type": "Feature",
  "properties": {
    "iso:country":"CA",
    "sg:address":"7473 Boul Lacordaire",
    "sg:city":"Saint-Leonard",
    "sg:classifiers":[
        {
            "category":"Restaurant",
            "type":"Food & Drink"
        }
    ],
    "sg:phone":"+1 514 254 5349",
    "sg:postcode":"H1S 3B2",
    "sg:province":"QC",
    "wof:name":"Restaurant Pacini",
    "wof:placetype":"venue"
},
  "geometry": {"coordinates":[-73.581596,45.583145],"type":"Point"}
}