{
  "type": "Feature",
  "properties": {
    "iso:country":"CA",
    "sg:city":"Whitby",
    "sg:classifiers":[
        {
            "category":"Real Estate",
            "subcategory":"Real Estate Agent",
            "type":"Services"
        }
    ],
    "sg:phone":"+1 905 666 6858",
    "sg:postcode":"L1N 8P9",
    "sg:province":"ON",
    "sg:tags":[
        "management"
    ],
    "wof:name":"Hornung Investments Ltd",
    "wof:placetype":"venue"
},
  "geometry": {"coordinates":[-78.92482,43.873657],"type":"Point"}
}