{
  "type": "Feature",
  "properties": {
    "addr:full":"1090 9E Rue Saint-Jerome QC J7Z 5Z7",
    "addr:housenumber":"1090",
    "addr:postcode":"j7z 5z7",
    "addr:street":"9E Rue Saint-Jerome",
    "iso:country":"CA",
    "sg:address":"1090 9E Rue",
    "sg:city":"Saint-Jerome",
    "sg:classifiers":[
        {
            "category":"Health Services",
            "subcategory":"Health Practitioner",
            "type":"Services"
        }
    ],
    "sg:phone":"+1 450 432 6435",
    "sg:postcode":"J7Z 5Z7",
    "sg:province":"QC",
    "sg:tags":[
        "nurse",
        "registry"
    ],
    "wof:name":"Mar Cha",
    "wof:placetype":"venue"
},
  "geometry": {"coordinates":[-73.98472599999999,45.771175],"type":"Point"}
}