{
  "type": "Feature",
  "properties": {
    "addr:full":"30 Hanna Crt Belleville ON K8P 5J2",
    "addr:housenumber":"30",
    "addr:postcode":"k8p 5j2",
    "addr:street":"Hanna Crt",
    "iso:country":"CA",
    "sg:address":"30 Hanna Crt",
    "sg:city":"Belleville",
    "sg:classifiers":[
        {
            "category":"Wholesale",
            "subcategory":"Machinery & Supplies",
            "type":"Manufacturing & Wholesale Goods"
        }
    ],
    "sg:phone":"+1 613 966 4735",
    "sg:postcode":"K8P 5J2",
    "sg:province":"ON",
    "sg:tags":[
        "industrial",
        "truck"
    ],
    "wof:name":"J H Ryder Machinery Ltd",
    "wof:placetype":"venue"
},
  "geometry": {"coordinates":[-77.41690800000001,44.184158],"type":"Point"}
}