{
  "type": "Feature",
  "properties": {
    "iso:country":"CA",
    "sg:address":"375 Rue DE Courcelette",
    "sg:city":"Sherbrooke",
    "sg:classifiers":[
        {
            "category":"Professional",
            "subcategory":"Business Services",
            "type":"Services"
        }
    ],
    "sg:phone":"+1 819 829 2251",
    "sg:postcode":"J1H 3X4",
    "sg:province":"QC",
    "sg:tags":[
        "recycling",
        "center"
    ],
    "wof:name":"Turcal",
    "wof:placetype":"venue"
},
  "geometry": {"coordinates":[-71.8987731934,45.3953552246],"type":"Point"}
}