{
  "type": "Feature",
  "properties": {
    "iso:country":"CA",
    "sg:address":"49 North St E",
    "sg:city":"Tillsonburg",
    "sg:classifiers":[
        {
            "category":"Building & Trades",
            "subcategory":"Construction",
            "type":"Services"
        }
    ],
    "sg:phone":"+1 519 842 4392",
    "sg:postcode":"N4G 1B4",
    "sg:province":"ON",
    "sg:tags":[
        "general",
        "contractor"
    ],
    "wof:name":"Grassmere Construction Ltd",
    "wof:placetype":"venue"
},
  "geometry": {"coordinates":[-80.7388687134,42.8792877197],"type":"Point"}
}