{
  "type": "Feature",
  "properties": {
    "addr:full":"37 Argonne Cres North York ON M2K 2K2",
    "addr:housenumber":"37",
    "addr:postcode":"m2k 2k2",
    "addr:street":"Argonne Cres",
    "iso:country":"CA",
    "sg:address":"37 Argonne Cres",
    "sg:city":"North York",
    "sg:classifiers":[
        {
            "category":"Banks & Credit Unions",
            "subcategory":"Bank",
            "type":"Services"
        }
    ],
    "sg:phone":"+1 416 759 1681",
    "sg:postcode":"M2K 2K2",
    "sg:province":"ON",
    "sg:tags":[
        "company",
        "trust"
    ],
    "wof:name":"Trans Canada Transfer Inc",
    "wof:placetype":"venue"
},
  "geometry": {"coordinates":[-79.39102172849999,43.7946128845],"type":"Point"}
}