{
  "type": "Feature",
  "properties": {
    "addr:full":"194 Tache Ave Winnipeg MB R2H 1Z6",
    "addr:housenumber":"194",
    "addr:postcode":"r2h 1z6",
    "addr:street":"Tache Ave",
    "iso:country":"CA",
    "sg:address":"194 Tache Ave",
    "sg:city":"Winnipeg",
    "sg:classifiers":[
        {
            "category":"Shopping",
            "type":"Retail Goods"
        }
    ],
    "sg:phone":"+1 204 237 4073",
    "sg:postcode":"R2H 1Z6",
    "sg:province":"MB",
    "sg:tags":[
        "picture",
        "frame"
    ],
    "wof:name":"Block Mounts",
    "wof:placetype":"venue"
},
  "geometry": {"coordinates":[-97.1228713989,49.8776321411],"type":"Point"}
}