{
  "type": "Feature",
  "properties": {
    "iso:country":"CA",
    "sg:address":"17 Rue Principale",
    "sg:city":"Listuguj",
    "sg:classifiers":[
        {
            "category":"Food & Beverages",
            "subcategory":"Groceries & Convenience Stores",
            "type":"Retail Goods"
        }
    ],
    "sg:phone":"+1 418 788 3203",
    "sg:postcode":"G0C 2R0",
    "sg:province":"QC",
    "sg:tags":[
        "grocer"
    ],
    "wof:name":"Depanneur Restigouche",
    "wof:placetype":"venue"
},
  "geometry": {"coordinates":[-66.7017211914,48.0119132996],"type":"Point"}
}