{
  "type": "Feature",
  "properties": {
    "addr:full":"Scarborough ON M1S 3R3",
    "addr:postcode":"m1s 3r3",
    "iso:country":"CA",
    "sg:city":"Scarborough",
    "sg:classifiers":[
        {
            "category":"Wholesale",
            "subcategory":"Machinery & Supplies",
            "type":"Manufacturing & Wholesale Goods"
        }
    ],
    "sg:phone":"+1 416 293 2460",
    "sg:postcode":"M1S 3R3",
    "sg:province":"ON",
    "sg:tags":[
        "paint",
        "equipment"
    ],
    "wof:name":"Fluid Management Canada",
    "wof:placetype":"venue"
},
  "geometry": {"coordinates":[-79.246315,43.785439],"type":"Point"}
}