{
  "type": "Feature",
  "properties": {
    "addr:full":"Toronto ON M4V 1N6",
    "addr:postcode":"m4v 1n6",
    "iso:country":"CA",
    "sg:city":"Toronto",
    "sg:classifiers":[
        {
            "category":"Real Estate",
            "subcategory":"Architect",
            "type":"Services"
        }
    ],
    "sg:phone":"+1 416 924 9966",
    "sg:postcode":"M4V 1N6",
    "sg:province":"ON",
    "wof:name":"Page & Steele Architects",
    "wof:placetype":"venue"
},
  "geometry": {"coordinates":[-79.40005499999999,43.686741],"type":"Point"}
}