{
  "type": "Feature",
  "properties": {
    "addr:full":"589 Cannon St E Hamilton ON L8L 2G6",
    "addr:housenumber":"589",
    "addr:postcode":"l8l 2g6",
    "addr:street":"Cannon St E",
    "iso:country":"CA",
    "sg:address":"589 Cannon St E",
    "sg:city":"Hamilton",
    "sg:classifiers":[
        {
            "category":"Manufacturing",
            "subcategory":"Tools & Machinery",
            "type":"Manufacturing & Wholesale Goods"
        }
    ],
    "sg:phone":"+1 905 547 5757",
    "sg:postcode":"L8L 2G6",
    "sg:province":"ON",
    "sg:tags":[
        "furnace"
    ],
    "wof:name":"Blackhawk Combustioneering Ltd",
    "wof:placetype":"venue"
},
  "geometry": {"coordinates":[-79.839172,43.253746],"type":"Point"}
}