{
  "type": "Feature",
  "properties": {
    "iso:country":"CA",
    "sg:city":"Peterborough",
    "sg:classifiers":[
        {
            "category":"Real Estate",
            "subcategory":"Real Estate Operator",
            "type":"Services"
        }
    ],
    "sg:phone":"+1 705 742 6047",
    "sg:postcode":"K9J 7T1",
    "sg:province":"ON",
    "sg:tags":[
        "apartment"
    ],
    "wof:name":"Valley High 300",
    "wof:placetype":"venue"
},
  "geometry": {"coordinates":[-78.3432235718,44.3099861145],"type":"Point"}
}