{
  "type": "Feature",
  "properties": {
    "addr:full":"48 Rue Temiscouata Riviere-Du-Loup QC G5R 2X9",
    "addr:housenumber":"48",
    "addr:postcode":"g5r 2x9",
    "addr:street":"Rue Temiscouata Riviere-Du-Loup",
    "iso:country":"CA",
    "sg:address":"48 Rue Temiscouata",
    "sg:city":"Riviere-Du-Loup",
    "sg:classifiers":[
        {
            "category":"Health Services",
            "subcategory":"Doctor",
            "type":"Services"
        }
    ],
    "sg:phone":"+1 418 860 3469",
    "sg:postcode":"G5R 2X9",
    "sg:province":"QC",
    "sg:tags":[
        "clinic"
    ],
    "wof:name":"Clinique Medical St-Ludger",
    "wof:placetype":"venue"
},
  "geometry": {"coordinates":[-69.527252,47.826405],"type":"Point"}
}