{
  "type": "Feature",
  "properties": {
    "addr:full":"Etobicoke ON M9P 2M5",
    "addr:postcode":"m9p 2m5",
    "iso:country":"CA",
    "sg:city":"Etobicoke",
    "sg:classifiers":[
        {
            "category":"Personal",
            "subcategory":"Beauty Salon",
            "type":"Services"
        }
    ],
    "sg:phone":"+1 416 243 5199",
    "sg:postcode":"M9P 2M5",
    "sg:province":"ON",
    "sg:tags":[
        "manicuring"
    ],
    "wof:name":"Nail Gallery",
    "wof:placetype":"venue"
},
  "geometry": {"coordinates":[-79.5440292358,43.6976165771],"type":"Point"}
}