{
  "type": "Feature",
  "properties": {
    "addr:full":"330 Selkirk St Wallaceburg ON N8A 3X7",
    "addr:housenumber":"330",
    "addr:postcode":"n8a 3x7",
    "addr:street":"Selkirk St",
    "iso:country":"CA",
    "sg:address":"330 Selkirk St",
    "sg:city":"Wallaceburg",
    "sg:classifiers":[
        {
            "category":"Retail",
            "subcategory":"Auto Repair",
            "type":"Services"
        }
    ],
    "sg:phone":"+1 519 627 6292",
    "sg:postcode":"N8A 3X7",
    "sg:province":"ON",
    "sg:tags":[
        "repairing",
        "automobile"
    ],
    "wof:name":"Belanger's Auto & Rad",
    "wof:placetype":"venue"
},
  "geometry": {"coordinates":[-82.392616,42.593323],"type":"Point"}
}