{
  "type": "Feature",
  "properties": {
    "addr:full":"2025 Rue Jean-Marie-Langlois LA Prairie QC J5R 5Z8",
    "addr:housenumber":"2025",
    "addr:postcode":"j5r 5z8",
    "addr:street":"Rue Jean-Marie-Langlois",
    "iso:country":"CA",
    "sg:address":"2025 Rue Jean-Marie-Langlois",
    "sg:city":"LA Prairie",
    "sg:classifiers":[
        {
            "category":"Freight",
            "type":"Transportation"
        }
    ],
    "sg:phone":"+1 450 659 9333",
    "sg:postcode":"J5R 5Z8",
    "sg:province":"QC",
    "sg:tags":[
        "trucking"
    ],
    "wof:name":"J M Langlois Inc",
    "wof:placetype":"venue"
},
  "geometry": {"coordinates":[-73.50299800000001,45.398132],"type":"Point"}
}