{
  "type": "Feature",
  "properties": {
    "addr:full":"Coaldale AB T1M 1M7",
    "addr:postcode":"t1m 1m7",
    "iso:country":"CA",
    "sg:city":"Coaldale",
    "sg:classifiers":[
        {
            "category":"Real Estate",
            "subcategory":"Real Estate Agent",
            "type":"Services"
        }
    ],
    "sg:phone":"+1 403 345 5100",
    "sg:postcode":"T1M 1M7",
    "sg:province":"AB",
    "wof:name":"Info Market Group Gmac",
    "wof:placetype":"venue"
},
  "geometry": {"coordinates":[-112.619972,49.727341],"type":"Point"}
}