{
  "type": "Feature",
  "properties": {
    "addr:full":"1110 E Victoria Ave Regina SK S4N 7A9",
    "addr:housenumber":"1110",
    "addr:postcode":"s4n 7a9",
    "addr:street":"E Victoria Ave",
    "iso:country":"CA",
    "sg:address":"1110 E Victoria Ave",
    "sg:city":"Regina",
    "sg:classifiers":[
        {
            "category":"Travel",
            "subcategory":"Hotels & Motels",
            "type":"Entertainment"
        }
    ],
    "sg:phone":"+1 306 565 0455",
    "sg:postcode":"S4N 7A9",
    "sg:province":"SK",
    "wof:name":"Travelodge Regina East",
    "wof:placetype":"venue"
},
  "geometry": {"coordinates":[-104.596535,50.447411],"type":"Point"}
}