{
  "type": "Feature",
  "properties": {
    "addr:full":"3370 Pharmacy Ave Scarborough ON M1W 3K4",
    "addr:housenumber":"3370",
    "addr:postcode":"m1w 3k4",
    "addr:street":"Pharmacy Ave",
    "iso:country":"CA",
    "sg:address":"3370 Pharmacy Ave",
    "sg:city":"Scarborough",
    "sg:classifiers":[
        {
            "category":"Wholesale",
            "subcategory":"Machinery & Supplies",
            "type":"Manufacturing & Wholesale Goods"
        }
    ],
    "sg:phone":"+1 416 492 5576",
    "sg:postcode":"M1W 3K4",
    "sg:province":"ON",
    "sg:tags":[
        "tool"
    ],
    "wof:name":"Compucut Computerized Tooling",
    "wof:placetype":"venue"
},
  "geometry": {"coordinates":[-79.33155059809999,43.8055038452],"type":"Point"}
}