{
  "type": "Feature",
  "properties": {
    "addr:full":"942 Goldie St Bell Ewart ON L0L 1C0",
    "addr:housenumber":"942",
    "addr:postcode":"l0l 1c0",
    "addr:street":"Goldie St",
    "iso:country":"CA",
    "sg:address":"942 Goldie St",
    "sg:city":"Bell Ewart",
    "sg:classifiers":[
        {
            "category":"Building & Trades",
            "subcategory":"Construction",
            "type":"Services"
        }
    ],
    "sg:phone":"+1 705 456 2462",
    "sg:postcode":"L0L 1C0",
    "sg:province":"ON",
    "sg:tags":[
        "contractor"
    ],
    "wof:name":"Van Berkel Construction Ltd",
    "wof:placetype":"venue"
},
  "geometry": {"coordinates":[-79.5403747559,44.2734451294],"type":"Point"}
}