{
  "type": "Feature",
  "properties": {
    "addr:full":"10055 106 St NW # 550 Edmonton AB T5J 2Y2",
    "addr:housenumber":"10055",
    "addr:postcode":"t5j 2y2",
    "addr:street":"106 St Nw # 550",
    "iso:country":"CA",
    "sg:address":"10055 106 St NW # 550",
    "sg:city":"Edmonton",
    "sg:classifiers":[
        {
            "category":"Professional",
            "subcategory":"Lawyer & Legal Services",
            "type":"Services"
        }
    ],
    "sg:phone":"+1 780 429 1133",
    "sg:postcode":"T5J 2Y2",
    "sg:province":"AB",
    "sg:tags":[
        "attorney"
    ],
    "wof:name":"Alberta Civil Trial Lawyers",
    "wof:placetype":"venue"
},
  "geometry": {"coordinates":[-113.502686,53.539963],"type":"Point"}
}