{
  "type": "Feature",
  "properties": {
    "addr:full":"5719 Morrison St Niagara Falls ON L2E 2E8",
    "addr:housenumber":"5719",
    "addr:postcode":"l2e 2e8",
    "addr:street":"Morrison St",
    "iso:country":"CA",
    "sg:address":"5719 Morrison St",
    "sg:city":"Niagara Falls",
    "sg:classifiers":[
        {
            "category":"Education",
            "subcategory":"School",
            "type":"Public Place"
        }
    ],
    "sg:phone":"+1 905 354 7744",
    "sg:postcode":"L2E 2E8",
    "sg:province":"ON",
    "wof:name":"St Mary's Catholic School",
    "wof:placetype":"venue"
},
  "geometry": {"coordinates":[-79.089821,43.104477],"type":"Point"}
}