{
  "type": "Feature",
  "properties": {
    "addr:full":"572 King St W Toronto ON M5V 1M3",
    "addr:housenumber":"572",
    "addr:postcode":"m5v 1m3",
    "addr:street":"King St W",
    "iso:country":"CA",
    "sg:address":"572 King St W",
    "sg:city":"Toronto",
    "sg:classifiers":[
        {
            "category":"Manufacturing",
            "subcategory":"Signs",
            "type":"Manufacturing & Wholesale Goods"
        }
    ],
    "sg:phone":"+1 416 504 1825",
    "sg:postcode":"M5V 1M3",
    "sg:province":"ON",
    "sg:tags":[
        "truck"
    ],
    "wof:name":"Booth Signs CO",
    "wof:placetype":"venue"
},
  "geometry": {"coordinates":[-79.39896400000001,43.644821],"type":"Point"}
}