{
  "type": "Feature",
  "properties": {
    "addr:full":"50 Rue Saint-Laurent O Longueuil QC J4H 1L6",
    "addr:housenumber":"50",
    "addr:postcode":"j4h 1l6",
    "addr:street":"Rue Saint-Laurent O",
    "iso:country":"CA",
    "sg:address":"50 Rue Saint-Laurent O",
    "sg:city":"Longueuil",
    "sg:classifiers":[
        {
            "category":"Personal",
            "subcategory":"Barber",
            "type":"Services"
        }
    ],
    "sg:phone":"+1 450 679 2080",
    "sg:postcode":"J4H 1L6",
    "sg:province":"QC",
    "wof:name":"Creations 2080",
    "wof:placetype":"venue"
},
  "geometry": {"coordinates":[-73.5054016113,45.5388069153],"type":"Point"}
}