{
  "type": "Feature",
  "properties": {
    "addr:full":"2608 Paul Cres Saskatoon SK S7J 2T6",
    "addr:housenumber":"2608",
    "addr:postcode":"s7j 2t6",
    "addr:street":"Paul Cres",
    "iso:country":"CA",
    "sg:address":"2608 Paul Cres",
    "sg:city":"Saskatoon",
    "sg:classifiers":[
        {
            "category":"Manufacturing",
            "subcategory":"Apparel",
            "type":"Manufacturing & Wholesale Goods"
        }
    ],
    "sg:phone":"+1 306 374 6621",
    "sg:postcode":"S7J 2T6",
    "sg:province":"SK",
    "sg:tags":[
        "flag",
        "banner"
    ],
    "wof:name":"Sportcomp Data Systems",
    "wof:placetype":"venue"
},
  "geometry": {"coordinates":[-106.631385803,52.0979347229],"type":"Point"}
}