{
  "type": "Feature",
  "properties": {
    "addr:full":"Edmonton AB T5K 0J8",
    "addr:postcode":"t5k 0j8",
    "iso:country":"CA",
    "sg:city":"Edmonton",
    "sg:classifiers":[
        {
            "category":"Health Services",
            "subcategory":"Health Practitioner",
            "type":"Services"
        }
    ],
    "sg:phone":"+1 780 488 8203",
    "sg:postcode":"T5K 0J8",
    "sg:province":"AB",
    "sg:tags":[
        "psychologist"
    ],
    "wof:name":"Eliuk, Jim PhD",
    "wof:placetype":"venue"
},
  "geometry": {"coordinates":[-113.519981384,53.5387077332],"type":"Point"}
}