{
  "type": "Feature",
  "properties": {
    "addr:full":"1055 Rang Des Trente Saint-Jean-Baptiste QC J0L 2B0",
    "addr:housenumber":"1055",
    "addr:postcode":"j0l 2b0",
    "addr:street":"Rang Des Trente",
    "iso:country":"CA",
    "sg:address":"1055 Rang Des Trente",
    "sg:city":"Saint-Jean-Baptiste",
    "sg:classifiers":[
        {
            "category":"Retail",
            "subcategory":"Veterinary Services",
            "type":"Services"
        }
    ],
    "sg:phone":"+1 450 446 4838",
    "sg:postcode":"J0L 2B0",
    "sg:province":"QC",
    "sg:tags":[
        "veterinarian"
    ],
    "wof:name":"Services Veterinaires",
    "wof:placetype":"venue"
},
  "geometry": {"coordinates":[-73.0865478516,45.5316352844],"type":"Point"}
}