{
  "type": "Feature",
  "properties": {
    "addr:full":"3085 Universal Dr Mississauga ON L4X 2E2",
    "addr:housenumber":"3085",
    "addr:postcode":"l4x 2e2",
    "addr:street":"Universal Dr",
    "iso:country":"CA",
    "sg:address":"3085 Universal Dr",
    "sg:city":"Mississauga",
    "sg:classifiers":[
        {
            "category":"Wholesale",
            "subcategory":"Books, Periodicals, & Newspapers",
            "type":"Manufacturing & Wholesale Goods"
        }
    ],
    "sg:phone":"+1 905 629 5055",
    "sg:postcode":"L4X 2E2",
    "sg:province":"ON",
    "sg:tags":[
        "dealer"
    ],
    "wof:name":"S & B Books Ltd",
    "wof:placetype":"venue"
},
  "geometry": {"coordinates":[-79.5721282959,43.6241111755],"type":"Point"}
}