{
  "type": "Feature",
  "properties": {
    "iso:country":"CA",
    "sg:address":"134 Rue Jean-Talon O",
    "sg:city":"Montreal",
    "sg:classifiers":[
        {
            "category":"Restaurant",
            "type":"Food & Drink"
        }
    ],
    "sg:phone":"+1 514 948 8884",
    "sg:postcode":"H2R 2X1",
    "sg:province":"QC",
    "wof:name":"Restaurant Nhu Y",
    "wof:placetype":"venue"
},
  "geometry": {"coordinates":[-73.616806,45.535561],"type":"Point"}
}