{
  "type": "Feature",
  "properties": {
    "addr:full":"Eastman QC J0E 1P0",
    "addr:postcode":"j0e 1p0",
    "iso:country":"CA",
    "sg:city":"Eastman",
    "sg:classifiers":[
        {
            "category":"Building & Trades",
            "subcategory":"Construction",
            "type":"Services"
        }
    ],
    "sg:phone":"+1 450 297 2434",
    "sg:postcode":"J0E 1P0",
    "sg:province":"QC",
    "sg:tags":[
        "real estate",
        "contractor"
    ],
    "wof:name":"Domaine MT Orford Terrains",
    "wof:placetype":"venue"
},
  "geometry": {"coordinates":[-72.3162765503,45.301525116],"type":"Point"}
}