{
  "type": "Feature",
  "properties": {
    "addr:full":"2391 4th Ave W Vancouver BC V6K 1P2",
    "addr:housenumber":"2391",
    "addr:postcode":"v6k 1p2",
    "addr:street":"4Th Ave W",
    "iso:country":"CA",
    "sg:address":"2391 4th Ave W",
    "sg:city":"Vancouver",
    "sg:classifiers":[
        {
            "category":"Restaurant",
            "type":"Food & Drink"
        }
    ],
    "sg:phone":"+1 604 718 1185",
    "sg:postcode":"V6K 1P2",
    "sg:province":"BC",
    "wof:name":"Mc Donald's",
    "wof:placetype":"venue"
},
  "geometry": {"coordinates":[-123.159378,49.268436],"type":"Point"}
}