{
  "type": "Feature",
  "properties": {
    "addr:full":"2288 Clark Dr Vancouver BC V5N 3G8",
    "addr:housenumber":"2288",
    "addr:postcode":"v5n 3g8",
    "addr:street":"Clark Dr",
    "iso:country":"CA",
    "sg:address":"2288 Clark Dr",
    "sg:city":"Vancouver",
    "sg:classifiers":[
        {
            "category":"Manufacturing",
            "subcategory":"Printing",
            "type":"Manufacturing & Wholesale Goods"
        }
    ],
    "sg:phone":"+1 604 876 1338",
    "sg:postcode":"V5N 3G8",
    "sg:province":"BC",
    "sg:tags":[
        "newspaper"
    ],
    "wof:name":"World Journal",
    "wof:placetype":"venue"
},
  "geometry": {"coordinates":[-123.077232,49.264416],"type":"Point"}
}