{
  "type": "Feature",
  "properties": {
    "addr:full":"11421 Alaska Rd Fort St John BC V1J 6N2",
    "addr:housenumber":"11421",
    "addr:postcode":"v1j 6n2",
    "addr:street":"Alaska Rd",
    "iso:country":"CA",
    "sg:address":"11421 Alaska Rd",
    "sg:city":"Fort St John",
    "sg:classifiers":[
        {
            "category":"Professional",
            "subcategory":"Business Services",
            "type":"Services"
        }
    ],
    "sg:phone":"+1 250 787 1030",
    "sg:postcode":"V1J 6N2",
    "sg:province":"BC",
    "sg:tags":[
        "reservation",
        "motel",
        "hotel"
    ],
    "wof:name":"Vlad Motor Inn CO",
    "wof:placetype":"venue"
},
  "geometry": {"coordinates":[-120.870223999,56.244342804],"type":"Point"}
}