{
  "type": "Feature",
  "properties": {
    "iso:country":"CA",
    "sg:address":"34 Rue Charles-Edouard",
    "sg:city":"Levis",
    "sg:classifiers":[
        {
            "category":"Health Services",
            "subcategory":"Nursing And Care Facility",
            "type":"Services"
        }
    ],
    "sg:phone":"+1 418 833 0323",
    "sg:postcode":"G6V 8E8",
    "sg:province":"QC",
    "sg:tags":[
        "house",
        "retirement",
        "retreat",
        "community",
        "home"
    ],
    "wof:name":"Villa Mon Repos Enr",
    "wof:placetype":"venue"
},
  "geometry": {"coordinates":[-71.181038,46.815407],"type":"Point"}
}