{
  "type": "Feature",
  "properties": {
    "addr:full":"20 Ainslie St N Cambridge ON N1R 3J4",
    "addr:housenumber":"20",
    "addr:postcode":"n1r 3j4",
    "addr:street":"Ainslie St N",
    "iso:country":"CA",
    "sg:address":"20 Ainslie St N",
    "sg:city":"Cambridge",
    "sg:classifiers":[
        {
            "category":"Home & Garden",
            "subcategory":"Furniture",
            "type":"Retail Goods"
        }
    ],
    "sg:phone":"+1 519 621 2180",
    "sg:postcode":"N1R 3J4",
    "sg:province":"ON",
    "wof:name":"Mannion's Quality Furn Ltd",
    "wof:placetype":"venue"
},
  "geometry": {"coordinates":[-80.313766,43.35939],"type":"Point"}
}