{
  "type": "Feature",
  "properties": {
    "addr:full":"2 Hunts Lane St. John's NL A1B 2L3",
    "addr:housenumber":"2",
    "addr:postcode":"a1b 2l3",
    "addr:street":"Hunts Lane",
    "iso:country":"CA",
    "sg:address":"2 Hunts Lane",
    "sg:city":"St. John's",
    "sg:classifiers":[
        {
            "category":"Professional",
            "subcategory":"Engineering",
            "type":"Services"
        }
    ],
    "sg:phone":"+1 709 753 2100",
    "sg:postcode":"A1B 2L3",
    "sg:province":"NL",
    "sg:tags":[
        "engineer"
    ],
    "wof:name":"Fga Consulting Engineers Ltd",
    "wof:placetype":"venue"
},
  "geometry": {"coordinates":[-52.7304153442,47.5968093872],"type":"Point"}
}