{
  "type": "Feature",
  "properties": {
    "addr:full":"2600 Airport Rd Windsor ON N8V 1A1",
    "addr:housenumber":"2600",
    "addr:postcode":"n8v 1a1",
    "addr:street":"Airport Rd",
    "iso:country":"CA",
    "sg:address":"2600 Airport Rd",
    "sg:city":"Windsor",
    "sg:classifiers":[
        {
            "category":"Museum",
            "type":"Entertainment"
        }
    ],
    "sg:phone":"+1 519 966 9742",
    "sg:postcode":"N8V 1A1",
    "sg:province":"ON",
    "wof:name":"Canadian Historical Aircraft",
    "wof:placetype":"venue"
},
  "geometry": {"coordinates":[-82.9687652588,42.2680892944],"type":"Point"}
}