{
  "type": "Feature",
  "properties": {
    "addr:full":"9145 Rue Boivin Lasalle QC H8R 2E5",
    "addr:housenumber":"9145",
    "addr:postcode":"h8r 2e5",
    "addr:street":"Rue Boivin",
    "iso:country":"CA",
    "sg:address":"9145 Rue Boivin",
    "sg:city":"Lasalle",
    "sg:classifiers":[
        {
            "category":"Manufacturing",
            "subcategory":"Tools & Machinery",
            "type":"Manufacturing & Wholesale Goods"
        }
    ],
    "sg:phone":"+1 514 595 1671",
    "sg:postcode":"H8R 2E5",
    "sg:province":"QC",
    "sg:tags":[
        "lighting",
        "fixture"
    ],
    "wof:name":"Peerless Luminaires Ltee",
    "wof:placetype":"venue"
},
  "geometry": {"coordinates":[-73.634293,45.422649],"type":"Point"}
}