{
  "type": "Feature",
  "properties": {
    "iso:country":"CA",
    "sg:city":"Ottawa",
    "sg:classifiers":[
        {
            "category":"Home & Garden",
            "subcategory":"Household Appliances",
            "type":"Retail Goods"
        }
    ],
    "sg:phone":"+1 613 725 0536",
    "sg:postcode":"K1S 5K4",
    "sg:province":"ON",
    "wof:name":"Arsenault Appliance Svc",
    "wof:placetype":"venue"
},
  "geometry": {"coordinates":[-75.68747711180001,45.4018783569],"type":"Point"}
}