{
  "type": "Feature",
  "properties": {
    "addr:full":"8550 Boul Pie-Ix Montreal QC H1Z 4G2",
    "addr:housenumber":"8550",
    "addr:postcode":"h1z 4g2",
    "addr:street":"Boul Pie-Ix",
    "iso:country":"CA",
    "sg:address":"8550 Boul Pie-Ix",
    "sg:city":"Montreal",
    "sg:classifiers":[
        {
            "category":"Professional",
            "subcategory":"Computer Services",
            "type":"Services"
        }
    ],
    "sg:phone":"+1 514 721 0865",
    "sg:postcode":"H1Z 4G2",
    "sg:province":"QC",
    "sg:tags":[
        "information",
        "system",
        "consultant"
    ],
    "wof:name":"Altimum Ims",
    "wof:placetype":"venue"
},
  "geometry": {"coordinates":[-73.611214,45.575096],"type":"Point"}
}