{
  "type": "Feature",
  "properties": {
    "addr:full":"12 Stafford Dr Brampton ON L6W 1L4",
    "addr:housenumber":"12",
    "addr:postcode":"l6w 1l4",
    "addr:street":"Stafford Dr",
    "iso:country":"CA",
    "sg:address":"12 Stafford Dr",
    "sg:city":"Brampton",
    "sg:classifiers":[
        {
            "category":"Home & Garden",
            "subcategory":"Building Materials",
            "type":"Retail Goods"
        }
    ],
    "sg:phone":"+1 905 457 2362",
    "sg:postcode":"L6W 1L4",
    "sg:province":"ON",
    "sg:tags":[
        "plate",
        "window",
        "upholstery",
        "top",
        "automobile"
    ],
    "wof:name":"Standard Auto Glass",
    "wof:placetype":"venue"
},
  "geometry": {"coordinates":[-79.7355728149,43.6864776611],"type":"Point"}
}