{
  "type": "Feature",
  "properties": {
    "addr:full":"3129 Dufferin St North York ON M6A 2S9",
    "addr:housenumber":"3129",
    "addr:postcode":"m6a 2s9",
    "addr:street":"Dufferin St",
    "iso:country":"CA",
    "sg:address":"3129 Dufferin St",
    "sg:city":"North York",
    "sg:classifiers":[
        {
            "category":"Personal",
            "subcategory":"Tanning Parlor",
            "type":"Services"
        }
    ],
    "sg:phone":"+1 416 782 8267",
    "sg:postcode":"M6A 2S9",
    "sg:province":"ON",
    "sg:tags":[
        "salon"
    ],
    "wof:name":"Tantasia Tanning",
    "wof:placetype":"venue"
},
  "geometry": {"coordinates":[-79.45501708979999,43.7164077759],"type":"Point"}
}