{
  "type": "Feature",
  "properties": {
    "addr:full":"1570 Liverpool Crt Ottawa ON K1B 4L2",
    "addr:housenumber":"1570",
    "addr:postcode":"k1b 4l2",
    "addr:street":"Liverpool Crt",
    "iso:country":"CA",
    "sg:address":"1570 Liverpool Crt",
    "sg:city":"Ottawa",
    "sg:classifiers":[
        {
            "category":"Retail",
            "subcategory":"Auto Repair",
            "type":"Services"
        }
    ],
    "sg:phone":"+1 613 744 1821",
    "sg:postcode":"K1B 4L2",
    "sg:province":"ON",
    "sg:tags":[
        "repairing",
        "automobile"
    ],
    "wof:name":"Ken's Automotive",
    "wof:placetype":"venue"
},
  "geometry": {"coordinates":[-75.623336792,45.411277771],"type":"Point"}
}