{
  "type": "Feature",
  "properties": {
    "addr:full":"2480 Rue Provost Lachine QC H8S 1P9",
    "addr:housenumber":"2480",
    "addr:postcode":"h8s 1p9",
    "addr:street":"Rue Provost",
    "iso:country":"CA",
    "sg:address":"2480 Rue Provost",
    "sg:city":"Lachine",
    "sg:classifiers":[
        {
            "category":"Banks & Credit Unions",
            "subcategory":"Bank",
            "type":"Services"
        }
    ],
    "sg:phone":"+1 514 637 3581",
    "sg:postcode":"H8S 1P9",
    "sg:province":"QC",
    "wof:name":"Banquescotia",
    "wof:placetype":"venue"
},
  "geometry": {"coordinates":[-73.6862411499,45.4419898987],"type":"Point"}
}