{
  "type": "Feature",
  "properties": {
    "addr:full":"1584 Broughton Bld # 3 Port Mcneill BC V0N 2R0",
    "addr:housenumber":"1584",
    "addr:postcode":"v0n 2r0",
    "addr:street":"Broughton Bld # 3",
    "iso:country":"CA",
    "sg:address":"1584 Broughton Bld # 3",
    "sg:city":"Port Mcneill",
    "sg:classifiers":[
        {
            "category":"Personal",
            "subcategory":"Beauty Salon",
            "type":"Services"
        }
    ],
    "sg:phone":"+1 250 956 2800",
    "sg:postcode":"V0N 2R0",
    "sg:province":"BC",
    "wof:name":"Hair Teezers Salon",
    "wof:placetype":"venue"
},
  "geometry": {"coordinates":[-127.08678436300001,50.5895767212],"type":"Point"}
}