{
  "type": "Feature",
  "properties": {
    "addr:full":"364 Richmond St London ON N6A 3C3",
    "addr:housenumber":"364",
    "addr:postcode":"n6a 3c3",
    "addr:street":"Richmond St",
    "iso:country":"CA",
    "sg:address":"364 Richmond St",
    "sg:city":"London",
    "sg:classifiers":[
        {
            "category":"Shopping",
            "subcategory":"Musical Instruments",
            "type":"Retail Goods"
        }
    ],
    "sg:phone":"+1 519 439 2000",
    "sg:postcode":"N6A 3C3",
    "sg:province":"ON",
    "wof:name":"London Guitar Shoppe",
    "wof:placetype":"venue"
},
  "geometry": {"coordinates":[-81.24881000000001,42.982384],"type":"Point"}
}