{
  "type": "Feature",
  "properties": {
    "addr:full":"296 Lake St St Catharines ON L2N 4H2",
    "addr:housenumber":"296",
    "addr:postcode":"l2n 4h2",
    "addr:street":"Lake St",
    "iso:country":"CA",
    "sg:address":"296 Lake St",
    "sg:city":"St Catharines",
    "sg:classifiers":[
        {
            "category":"Home & Garden",
            "subcategory":"Home Furnishings",
            "type":"Retail Goods"
        }
    ],
    "sg:phone":"+1 905 935 3621",
    "sg:postcode":"L2N 4H2",
    "sg:province":"ON",
    "sg:tags":[
        "lighting",
        "fixture"
    ],
    "wof:name":"Don's Light House Ltd",
    "wof:placetype":"venue"
},
  "geometry": {"coordinates":[-79.2514419556,43.1829833984],"type":"Point"}
}