{
  "type": "Feature",
  "properties": {
    "addr:full":"Surrey BC V3S 9A5",
    "addr:postcode":"v3s 9a5",
    "iso:country":"CA",
    "sg:city":"Surrey",
    "sg:classifiers":[
        {
            "category":"Government",
            "subcategory":"Office",
            "type":"Public Place"
        }
    ],
    "sg:phone":"+1 604 575 5141",
    "sg:postcode":"V3S 9A5",
    "sg:province":"BC",
    "wof:name":"Recruitment & Education",
    "wof:placetype":"venue"
},
  "geometry": {"coordinates":[-122.80284881599999,49.1045608521],"type":"Point"}
}