{
  "type": "Feature",
  "properties": {
    "addr:full":"3400 Richmond Rd Victoria BC V8P 4P5",
    "addr:housenumber":"3400",
    "addr:postcode":"v8p 4p5",
    "addr:street":"Richmond Rd",
    "iso:country":"CA",
    "sg:address":"3400 Richmond Rd",
    "sg:city":"Victoria",
    "sg:classifiers":[
        {
            "category":"Education",
            "subcategory":"School",
            "type":"Public Place"
        }
    ],
    "sg:phone":"+1 250 592 3549",
    "sg:postcode":"V8P 4P5",
    "sg:province":"BC",
    "wof:name":"St Michaels Middle School",
    "wof:placetype":"venue"
},
  "geometry": {"coordinates":[-123.32807200000001,48.43869],"type":"Point"}
}