{
  "type": "Feature",
  "properties": {
    "addr:full":"9462 Boul Lacordaire Saint-Leonard QC H1R 3N3",
    "addr:housenumber":"9462",
    "addr:postcode":"h1r 3n3",
    "addr:street":"Boul Lacordaire",
    "iso:country":"CA",
    "sg:address":"9462 Boul Lacordaire",
    "sg:city":"Saint-Leonard",
    "sg:classifiers":[
        {
            "category":"Education",
            "subcategory":"Dance Studio",
            "type":"Public Place"
        }
    ],
    "sg:phone":"+1 514 322 2587",
    "sg:postcode":"H1R 3N3",
    "sg:province":"QC",
    "sg:tags":[
        "club",
        "instruction",
        "dancing"
    ],
    "wof:name":"Le Rendez-Vous Inc",
    "wof:placetype":"venue"
},
  "geometry": {"coordinates":[-73.61256408689999,45.5995521545],"type":"Point"}
}