{
  "type": "Feature",
  "properties": {
    "iso:country":"CA",
    "sg:address":"7241 Bathurst St",
    "sg:city":"Thornhill",
    "sg:classifiers":[
        {
            "category":"Food & Beverages",
            "subcategory":"Fruits & Vegetables",
            "type":"Retail Goods"
        }
    ],
    "sg:phone":"+1 905 731 2132",
    "sg:postcode":"L4J 3W1",
    "sg:province":"ON",
    "sg:tags":[
        "produce"
    ],
    "wof:name":"Sue's Thornhill Fruit Market",
    "wof:placetype":"venue"
},
  "geometry": {"coordinates":[-79.4468917847,43.7979354858],"type":"Point"}
}