{
  "type": "Feature",
  "properties": {
    "addr:full":"26 Swayne St Cobourg ON K9A 1K5",
    "addr:housenumber":"26",
    "addr:postcode":"k9a 1k5",
    "addr:street":"Swayne St",
    "iso:country":"CA",
    "sg:address":"26 Swayne St",
    "sg:city":"Cobourg",
    "sg:classifiers":[
        {
            "category":"Personal",
            "subcategory":"Beauty Salon",
            "type":"Services"
        }
    ],
    "sg:phone":"+1 905 372 7382",
    "sg:postcode":"K9A 1K5",
    "sg:province":"ON",
    "wof:name":"Beginning's Family Hair Stylst",
    "wof:placetype":"venue"
},
  "geometry": {"coordinates":[-78.16487121580001,43.9607887268],"type":"Point"}
}