{
  "type": "Feature",
  "properties": {
    "iso:country":"CA",
    "sg:address":"364 Wilson Rd S",
    "sg:city":"Oshawa",
    "sg:classifiers":[
        {
            "category":"Personal",
            "subcategory":"Barber",
            "type":"Services"
        }
    ],
    "sg:phone":"+1 905 728 6007",
    "sg:postcode":"L1H 6C7",
    "sg:province":"ON",
    "wof:name":"Emil's Barber Shop For Men",
    "wof:placetype":"venue"
},
  "geometry": {"coordinates":[-78.8397445679,43.8924827576],"type":"Point"}
}