{
  "type": "Feature",
  "properties": {
    "addr:full":"40 Rue Josee Saint-Louis-DE-France QC G8W 1K5",
    "addr:housenumber":"40",
    "addr:postcode":"g8w 1k5",
    "addr:street":"Rue Josee",
    "iso:country":"CA",
    "sg:address":"40 Rue Josee",
    "sg:city":"Saint-Louis-DE-France",
    "sg:classifiers":[
        {
            "category":"Building & Trades",
            "subcategory":"Electrical",
            "type":"Services"
        }
    ],
    "sg:phone":"+1 819 371 8482",
    "sg:postcode":"G8W 1K5",
    "sg:province":"QC",
    "sg:tags":[
        "electric",
        "contractor"
    ],
    "wof:name":"Electricite Pelmont",
    "wof:placetype":"venue"
},
  "geometry": {"coordinates":[-72.57225800000001,46.385223],"type":"Point"}
}