{
  "type": "Feature",
  "properties": {
    "addr:full":"111 Tacoma Dr Dartmouth NS B2W 3E8",
    "addr:housenumber":"111",
    "addr:postcode":"b2w 3e8",
    "addr:street":"Tacoma Dr",
    "iso:country":"CA",
    "sg:address":"111 Tacoma Dr",
    "sg:city":"Dartmouth",
    "sg:classifiers":[
        {
            "category":"Real Estate",
            "subcategory":"Surveying",
            "type":"Services"
        }
    ],
    "sg:phone":"+1 902 466 7768",
    "sg:postcode":"B2W 3E8",
    "sg:province":"NS",
    "sg:tags":[
        "surveyor"
    ],
    "wof:name":"Longstaff/Parker Surveys",
    "wof:placetype":"venue"
},
  "geometry": {"coordinates":[-63.5357055664,44.6809959412],"type":"Point"}
}