{
  "type": "Feature",
  "properties": {
    "addr:full":"114 Rue Reid Hudson QC J0P 1H0",
    "addr:housenumber":"114",
    "addr:postcode":"j0p 1h0",
    "addr:street":"Rue Reid",
    "iso:country":"CA",
    "sg:address":"114 Rue Reid",
    "sg:city":"Hudson",
    "sg:classifiers":[
        {
            "category":"Wholesale",
            "subcategory":"Construction Materials",
            "type":"Manufacturing & Wholesale Goods"
        }
    ],
    "sg:phone":"+1 450 458 3311",
    "sg:postcode":"J0P 1H0",
    "sg:province":"QC",
    "sg:tags":[
        "building"
    ],
    "wof:name":"Produits Architecturaux",
    "wof:placetype":"venue"
},
  "geometry": {"coordinates":[-74.144417,45.460732],"type":"Point"}
}