{
  "type": "Feature",
  "properties": {
    "addr:full":"6169 Rue Principale Sainte-Croix QC G0S 2H0",
    "addr:housenumber":"6169",
    "addr:postcode":"g0s 2h0",
    "addr:street":"Rue Principale",
    "iso:country":"CA",
    "sg:address":"6169 Rue Principale",
    "sg:city":"Sainte-Croix",
    "sg:classifiers":[
        {
            "category":"Banks & Credit Unions",
            "subcategory":"Bank",
            "type":"Services"
        }
    ],
    "sg:phone":"+1 418 926 3270",
    "sg:postcode":"G0S 2H0",
    "sg:province":"QC",
    "wof:name":"Banque Nationale Du Canada",
    "wof:placetype":"venue"
},
  "geometry": {"coordinates":[-71.73371899999999,46.623375],"type":"Point"}
}