{
  "type": "Feature",
  "properties": {
    "addr:full":"69 Water St Pictou NS B0K 1H0",
    "addr:housenumber":"69",
    "addr:postcode":"b0k 1h0",
    "addr:street":"Water St",
    "iso:country":"CA",
    "sg:address":"69 Water St",
    "sg:city":"Pictou",
    "sg:classifiers":[
        {
            "category":"Government",
            "subcategory":"Office",
            "type":"Public Place"
        }
    ],
    "sg:phone":"+1 902 485 4223",
    "sg:postcode":"B0K 1H0",
    "sg:province":"NS",
    "sg:tags":[
        "map"
    ],
    "wof:name":"Land Information Ctr",
    "wof:placetype":"venue"
},
  "geometry": {"coordinates":[-62.711399,45.676189],"type":"Point"}
}