{
  "type": "Feature",
  "properties": {
    "addr:full":"Gronlid SK S0E 0W0",
    "addr:postcode":"s0e 0w0",
    "addr:street":"Gronlid",
    "iso:country":"CA",
    "sg:city":"Gronlid",
    "sg:classifiers":[
        {
            "category":"Travel",
            "subcategory":"Hotels & Motels",
            "type":"Entertainment"
        }
    ],
    "sg:phone":"+1 306 862 5621",
    "sg:postcode":"S0E 0W0",
    "sg:province":"SK",
    "sg:tags":[
        "resort",
        "center",
        "skiing"
    ],
    "wof:name":"Wapiti Valley Regional Park",
    "wof:placetype":"venue"
},
  "geometry": {"coordinates":[-104.464408874,53.0992584229],"type":"Point"}
}