{
  "type": "Feature",
  "properties": {
    "iso:country":"CA",
    "sg:city":"Pefferlaw",
    "sg:classifiers":[
        {
            "category":"Retail",
            "subcategory":"Repair Shop",
            "type":"Services"
        }
    ],
    "sg:phone":"+1 705 437 2937",
    "sg:postcode":"L0E 1N0",
    "sg:province":"ON",
    "sg:tags":[
        "welding"
    ],
    "wof:name":"Erwin Steel",
    "wof:placetype":"venue"
},
  "geometry": {"coordinates":[-79.22347259519999,44.3292922974],"type":"Point"}
}