{
  "type": "Feature",
  "properties": {
    "iso:country":"CA",
    "sg:address":"98 Dunsmore Dr",
    "sg:city":"Regina",
    "sg:classifiers":[
        {
            "category":"Building & Trades",
            "subcategory":"Construction",
            "type":"Services"
        }
    ],
    "sg:phone":"+1 306 545 1728",
    "sg:postcode":"S4R 7G2",
    "sg:province":"SK",
    "sg:tags":[
        "general",
        "contractor"
    ],
    "wof:name":"Fischer Construction Inc",
    "wof:placetype":"venue"
},
  "geometry": {"coordinates":[-104.660835,50.489059],"type":"Point"}
}