{
  "type": "Feature",
  "properties": {
    "iso:country":"CA",
    "sg:city":"Windsor",
    "sg:classifiers":[
        {
            "category":"Health Services",
            "subcategory":"Doctor",
            "type":"Services"
        }
    ],
    "sg:phone":"+1 519 258 7671",
    "sg:postcode":"N8W 1C9",
    "sg:province":"ON",
    "sg:tags":[
        "physician",
        "surgeon"
    ],
    "wof:name":"Zaher, Amjad MD",
    "wof:placetype":"venue"
},
  "geometry": {"coordinates":[-82.9991149902,42.3013076782],"type":"Point"}
}