{
  "type": "Feature",
  "properties": {
    "addr:full":"458 Main St Kentville NS B4N 1K8",
    "addr:housenumber":"458",
    "addr:postcode":"b4n 1k8",
    "addr:street":"Main St",
    "iso:country":"CA",
    "sg:address":"458 Main St",
    "sg:city":"Kentville",
    "sg:classifiers":[
        {
            "category":"Health Services",
            "subcategory":"Health Practitioner",
            "type":"Services"
        }
    ],
    "sg:phone":"+1 902 678 4142",
    "sg:postcode":"B4N 1K8",
    "sg:province":"NS",
    "sg:tags":[
        "acupuncture",
        "physician"
    ],
    "wof:name":"Hawthorn Naturopathic Clinic",
    "wof:placetype":"venue"
},
  "geometry": {"coordinates":[-64.490517,45.075756],"type":"Point"}
}