{
  "type": "Feature",
  "properties": {
    "iso:country":"CA",
    "sg:address":"6028 30 St NW",
    "sg:city":"Edmonton",
    "sg:classifiers":[
        {
            "category":"Building & Trades",
            "subcategory":"Construction",
            "type":"Services"
        }
    ],
    "sg:phone":"+1 780 466 2187",
    "sg:postcode":"T6P 1J7",
    "sg:province":"AB",
    "sg:tags":[
        "coating",
        "sandblasting"
    ],
    "wof:name":"Sahara Sandblasting & Painting",
    "wof:placetype":"venue"
},
  "geometry": {"coordinates":[-113.38789367699999,53.4982185364],"type":"Point"}
}