{
  "type": "Feature",
  "properties": {
    "iso:country":"CA",
    "sg:city":"Burnaby",
    "sg:classifiers":[
        {
            "category":"Restaurant",
            "type":"Food & Drink"
        }
    ],
    "sg:phone":"+1 604 298 9900",
    "sg:postcode":"V5C 2H6",
    "sg:province":"BC",
    "wof:name":"Moldovanos Restaurant",
    "wof:placetype":"venue"
},
  "geometry": {"coordinates":[-123.023125,49.28125],"type":"Point"}
}