{
  "type": "Feature",
  "properties": {
    "addr:full":"Sudbury ON P3E 6J9",
    "addr:postcode":"p3e 6j9",
    "iso:country":"CA",
    "sg:city":"Sudbury",
    "sg:classifiers":[
        {
            "category":"Government",
            "subcategory":"Office",
            "type":"Public Place"
        }
    ],
    "sg:phone":"+1 705 523 2900",
    "sg:postcode":"P3E 6J9",
    "sg:province":"ON",
    "wof:name":"Societe Candienne D'Hypotheque",
    "wof:placetype":"venue"
},
  "geometry": {"coordinates":[-81.003578,46.450897],"type":"Point"}
}