{
  "type": "Feature",
  "properties": {
    "iso:country":"CA",
    "sg:address":"10 Saint Mary St #505",
    "sg:city":"Toronto",
    "sg:classifiers":[
        {
            "category":"Health Services",
            "subcategory":"Health Practitioner",
            "type":"Services"
        }
    ],
    "sg:phone":"+1 416 975 8766",
    "sg:postcode":"M4Y 1P9",
    "sg:province":"ON",
    "sg:tags":[
        "psychologist"
    ],
    "wof:name":"Salsberg, Ezrin S",
    "wof:placetype":"venue"
},
  "geometry": {"coordinates":[-79.3863372803,43.6680145264],"type":"Point"}
}