{
  "type": "Feature",
  "properties": {
    "addr:full":"111 Ridelle Ave Toronto ON M6B 1J7",
    "addr:housenumber":"111",
    "addr:postcode":"m6b 1j7",
    "addr:street":"Ridelle Ave",
    "iso:country":"CA",
    "sg:address":"111 Ridelle Ave",
    "sg:city":"Toronto",
    "sg:classifiers":[
        {
            "category":"Retail",
            "subcategory":"Animal Services",
            "type":"Services"
        }
    ],
    "sg:phone":"+1 416 817 7387",
    "sg:postcode":"M6B 1J7",
    "sg:province":"ON",
    "sg:tags":[
        "pet",
        "boarding",
        "sitting"
    ],
    "wof:name":"Alma Dog Walking Svc",
    "wof:placetype":"venue"
},
  "geometry": {"coordinates":[-79.437988,43.704731],"type":"Point"}
}