{
  "type": "Feature",
  "properties": {
    "addr:full":"19 Clarence St Ottawa ON K1N 5P4",
    "addr:housenumber":"19",
    "addr:postcode":"k1n 5p4",
    "addr:street":"Clarence St",
    "iso:country":"CA",
    "sg:address":"19 Clarence St",
    "sg:city":"Ottawa",
    "sg:classifiers":[
        {
            "category":"Shopping",
            "type":"Retail Goods"
        }
    ],
    "sg:phone":"+1 613 562 0284",
    "sg:postcode":"K1N 5P4",
    "sg:province":"ON",
    "sg:tags":[
        "art",
        "gallery",
        "dealer"
    ],
    "wof:name":"Giraffe the African Store",
    "wof:placetype":"venue"
},
  "geometry": {"coordinates":[-75.69493900000001,45.428413],"type":"Point"}
}