{
  "type": "Feature",
  "properties": {
    "addr:full":"14323 57 Ave Surrey BC V3X 1B1",
    "addr:housenumber":"14323",
    "addr:postcode":"v3x 1b1",
    "addr:street":"57 Ave",
    "iso:country":"CA",
    "sg:address":"14323 57 Ave",
    "sg:city":"Surrey",
    "sg:classifiers":[
        {
            "category":"Government",
            "subcategory":"Office",
            "type":"Public Place"
        }
    ],
    "sg:phone":"+1 604 599 4110",
    "sg:postcode":"V3X 1B1",
    "sg:province":"BC",
    "wof:name":"BC Surrey Pretrial Svc Ctr",
    "wof:placetype":"venue"
},
  "geometry": {"coordinates":[-122.82564499999999,49.106457],"type":"Point"}
}