{
  "type": "Feature",
  "properties": {
    "iso:country":"CA",
    "sg:address":"168 Kennedy Rd S",
    "sg:city":"Brampton",
    "sg:classifiers":[
        {
            "category":"Shopping",
            "subcategory":"Discount & Variety Stores",
            "type":"Retail Goods"
        }
    ],
    "sg:phone":"+1 905 457 8845",
    "sg:postcode":"L6W 3G6",
    "sg:province":"ON",
    "wof:name":"Kennedy Variety Store",
    "wof:placetype":"venue"
},
  "geometry": {"coordinates":[-79.7306213379,43.6817893982],"type":"Point"}
}