{
  "type": "Feature",
  "properties": {
    "iso:country":"CA",
    "sg:address":"302 8th St",
    "sg:city":"Brandon",
    "sg:classifiers":[
        {
            "category":"Recreation",
            "type":"Entertainment"
        }
    ],
    "sg:phone":"+1 204 727 4893",
    "sg:postcode":"R7A 3X4",
    "sg:province":"MB",
    "sg:tags":[
        "hall",
        "auditorium"
    ],
    "wof:name":"Masonic Temple",
    "wof:placetype":"venue"
},
  "geometry": {"coordinates":[-99.948868,49.845146],"type":"Point"}
}