{
  "type": "Feature",
  "properties": {
    "addr:full":"Southwold ON N0L 2G0",
    "addr:postcode":"n0l 2g0",
    "iso:country":"CA",
    "sg:city":"Southwold",
    "sg:classifiers":[
        {
            "category":"Restaurant",
            "type":"Food & Drink"
        }
    ],
    "sg:phone":"+1 519 764 2385",
    "sg:postcode":"N0L 2G0",
    "sg:province":"ON",
    "sg:tags":[
        "banquet",
        "rooms"
    ],
    "wof:name":"Lawrence Station Community",
    "wof:placetype":"venue"
},
  "geometry": {"coordinates":[-81.35702499999999,42.810307],"type":"Point"}
}