{
  "type": "Feature",
  "properties": {
    "addr:full":"777 Warden Ave #208 Scarborough ON M1L 4C3",
    "addr:housenumber":"777",
    "addr:postcode":"m1l 4c3",
    "addr:street":"Warden Ave # 208",
    "iso:country":"CA",
    "sg:address":"777 Warden Ave #208",
    "sg:city":"Scarborough",
    "sg:classifiers":[
        {
            "category":"Bus Charters",
            "type":"Transportation"
        }
    ],
    "sg:phone":"+1 416 285 8861",
    "sg:postcode":"M1L 4C3",
    "sg:province":"ON",
    "sg:tags":[
        "rental"
    ],
    "wof:name":"Travel Goodtime Tours",
    "wof:placetype":"venue"
},
  "geometry": {"coordinates":[-79.286034,43.724491],"type":"Point"}
}