{
  "type": "Feature",
  "properties": {
    "addr:full":"163 1E Av Saint-Simeon-DE-Bonaventure QC G0C 3A0",
    "addr:housenumber":"163",
    "addr:postcode":"g0c 3a0",
    "addr:street":"1E Av Saint-Simeon-De-Bonaventure",
    "iso:country":"CA",
    "sg:address":"163 1E Av",
    "sg:city":"Saint-Simeon-DE-Bonaventure",
    "sg:classifiers":[
        {
            "category":"Building & Trades",
            "subcategory":"Construction",
            "type":"Services"
        }
    ],
    "sg:phone":"+1 418 534 4079",
    "sg:postcode":"G0C 3A0",
    "sg:province":"QC",
    "sg:tags":[
        "painter"
    ],
    "wof:name":"Peintures Serge Bujold Enr",
    "wof:placetype":"venue"
},
  "geometry": {"coordinates":[-65.494446,48.045422],"type":"Point"}
}