{
  "type": "Feature",
  "properties": {
    "addr:full":"2601 Ch DE LA Canardiere Quebec QC G1J 2G3",
    "addr:housenumber":"2601",
    "addr:postcode":"g1j 2g3",
    "addr:street":"Ch De La Canardiere",
    "iso:country":"CA",
    "sg:address":"2601 Ch DE LA Canardiere",
    "sg:city":"Quebec",
    "sg:classifiers":[
        {
            "category":"Health Services",
            "subcategory":"Hospital",
            "type":"Services"
        }
    ],
    "sg:phone":"+1 418 663 5321",
    "sg:postcode":"G1J 2G3",
    "sg:province":"QC",
    "wof:name":"Centre Hospitalier R Giffard",
    "wof:placetype":"venue"
},
  "geometry": {"coordinates":[-71.21714,46.845947],"type":"Point"}
}