{
  "type": "Feature",
  "properties": {
    "addr:full":"861 Hilliers Rd Qualicum Beach BC V9K 1X5",
    "addr:housenumber":"861",
    "addr:postcode":"v9k 1x5",
    "addr:street":"Hilliers Rd",
    "iso:country":"CA",
    "sg:address":"861 Hilliers Rd",
    "sg:city":"Qualicum Beach",
    "sg:classifiers":[
        {
            "category":"Education",
            "subcategory":"School",
            "type":"Public Place"
        }
    ],
    "sg:phone":"+1 250 752 2722",
    "sg:postcode":"V9K 1X5",
    "sg:province":"BC",
    "wof:name":"Morning Glory School",
    "wof:placetype":"venue"
},
  "geometry": {"coordinates":[-124.441704,49.346706],"type":"Point"}
}