{
  "type": "Feature",
  "properties": {
    "addr:full":"166 15th St E North Vancouver BC V7L 2R1",
    "addr:housenumber":"166",
    "addr:postcode":"v7l 2r1",
    "addr:street":"15Th St E",
    "iso:country":"CA",
    "sg:address":"166 15th St E",
    "sg:city":"North Vancouver",
    "sg:classifiers":[
        {
            "category":"Personal",
            "subcategory":"Beauty Salon",
            "type":"Services"
        }
    ],
    "sg:phone":"+1 604 988 0789",
    "sg:postcode":"V7L 2R1",
    "sg:province":"BC",
    "sg:tags":[
        "consultant",
        "health"
    ],
    "wof:name":"Advanced Beauty Studio",
    "wof:placetype":"venue"
},
  "geometry": {"coordinates":[-123.069953919,49.3221931458],"type":"Point"}
}