{
  "type": "Feature",
  "properties": {
    "addr:full":"Railway Ave Oyen AB T0J 2J0",
    "addr:postcode":"t0j 2j0",
    "addr:street":"Railway Ave",
    "iso:country":"CA",
    "sg:address":"Railway Ave",
    "sg:city":"Oyen",
    "sg:classifiers":[
        {
            "category":"Farming",
            "subcategory":"Nursery",
            "type":"Manufacturing & Wholesale Goods"
        }
    ],
    "sg:phone":"+1 403 664 3086",
    "sg:postcode":"T0J 2J0",
    "sg:province":"AB",
    "sg:tags":[
        "greenhouse"
    ],
    "wof:name":"Oyen Agro Ctr",
    "wof:placetype":"venue"
},
  "geometry": {"coordinates":[-110.48191070599999,51.3555259705],"type":"Point"}
}