{
  "type": "Feature",
  "properties": {
    "iso:country":"CA",
    "sg:address":"138 Av Atwater",
    "sg:city":"Montreal",
    "sg:classifiers":[
        {
            "category":"Restaurant",
            "type":"Food & Drink"
        }
    ],
    "sg:phone":"+1 514 937 5090",
    "sg:postcode":"H4C 2G3",
    "sg:province":"QC",
    "wof:name":"Sushi Shop",
    "wof:placetype":"venue"
},
  "geometry": {"coordinates":[-73.576263,45.479614],"type":"Point"}
}