{
  "type": "Feature",
  "properties": {
    "iso:country":"CA",
    "sg:address":"100 Sandiford Dr",
    "sg:city":"Stouffville",
    "sg:classifiers":[
        {
            "category":"Wholesale",
            "subcategory":"Hardware",
            "type":"Manufacturing & Wholesale Goods"
        }
    ],
    "sg:phone":"+1 905 642 2200",
    "sg:postcode":"L4A 7X5",
    "sg:province":"ON",
    "sg:tags":[
        "conditioning",
        "air",
        "system",
        "refrigerating",
        "contractor"
    ],
    "wof:name":"Atlantic Cooling Ltd",
    "wof:placetype":"venue"
},
  "geometry": {"coordinates":[-79.26983642579999,43.9644966125],"type":"Point"}
}