{
  "type": "Feature",
  "properties": {
    "addr:full":"220 Edworthy Way New Westminster BC V3L 5G5",
    "addr:housenumber":"220",
    "addr:postcode":"v3l 5g5",
    "addr:street":"Edworthy Way",
    "iso:country":"CA",
    "sg:address":"220 Edworthy Way",
    "sg:city":"New Westminster",
    "sg:classifiers":[
        {
            "category":"Building & Trades",
            "subcategory":"Construction",
            "type":"Services"
        }
    ],
    "sg:phone":"+1 604 522 3921",
    "sg:postcode":"V3L 5G5",
    "sg:province":"BC",
    "sg:tags":[
        "product",
        "paving",
        "asphalt",
        "contractor"
    ],
    "wof:name":"Winvan Paving Ltd",
    "wof:placetype":"venue"
},
  "geometry": {"coordinates":[-122.88700900000001,49.223476],"type":"Point"}
}