{
  "type": "Feature",
  "properties": {
    "addr:full":"134 the Market Crt #111 Scarborough ON M1L 2K1",
    "addr:housenumber":"134",
    "addr:postcode":"m1l 2k1",
    "addr:street":"The Market Crt # 111",
    "iso:country":"CA",
    "sg:address":"134 the Market Crt #111",
    "sg:city":"Scarborough",
    "sg:classifiers":[
        {
            "category":"Health Services",
            "subcategory":"Doctor",
            "type":"Services"
        }
    ],
    "sg:phone":"+1 416 752 8222",
    "sg:postcode":"M1L 2K1",
    "sg:province":"ON",
    "sg:tags":[
        "dentist"
    ],
    "wof:name":"Boetto, John DDS",
    "wof:placetype":"venue"
},
  "geometry": {"coordinates":[-79.25666,43.772228],"type":"Point"}
}