{
  "type": "Feature",
  "properties": {
    "addr:full":"451 6E Ave A Grand-Mere QC G9T 2E7",
    "addr:housenumber":"451",
    "addr:postcode":"g9t 2e7",
    "addr:street":"6E Ave A Grand-Mere",
    "iso:country":"CA",
    "sg:address":"451 6E Ave A",
    "sg:city":"Grand-Mere",
    "sg:classifiers":[
        {
            "category":"Health Services",
            "subcategory":"Nursing And Care Facility",
            "type":"Services"
        }
    ],
    "sg:phone":"+1 819 533 4352",
    "sg:postcode":"G9T 2E7",
    "sg:province":"QC",
    "sg:tags":[
        "home",
        "retirement",
        "community"
    ],
    "wof:name":"Domaine Centre Ville Enr",
    "wof:placetype":"venue"
},
  "geometry": {"coordinates":[-72.68596599999999,46.615631],"type":"Point"}
}