{
  "type": "Feature",
  "properties": {
    "addr:full":"North York ON M6A 2W5",
    "addr:postcode":"m6a 2w5",
    "iso:country":"CA",
    "sg:city":"North York",
    "sg:classifiers":[
        {
            "category":"Building & Trades",
            "subcategory":"Construction",
            "type":"Services"
        }
    ],
    "sg:phone":"+1 416 784 0064",
    "sg:postcode":"M6A 2W5",
    "sg:province":"ON",
    "sg:tags":[
        "resurfacing",
        "laying",
        "refinishing",
        "floor"
    ],
    "wof:name":"Amcan Hardwood Ltd",
    "wof:placetype":"venue"
},
  "geometry": {"coordinates":[-79.4672241211,43.7133483887],"type":"Point"}
}