{
  "type": "Feature",
  "properties": {
    "addr:full":"15420 Bayview Ave Aurora ON L4G 7J1",
    "addr:housenumber":"15420",
    "addr:postcode":"l4g 7j1",
    "addr:street":"Bayview Ave",
    "iso:country":"CA",
    "sg:address":"15420 Bayview Ave",
    "sg:city":"Aurora",
    "sg:classifiers":[
        {
            "category":"Banks & Credit Unions",
            "subcategory":"Bank",
            "type":"Services"
        }
    ],
    "sg:phone":"+1 905 727 1025",
    "sg:postcode":"L4G 7J1",
    "sg:province":"ON",
    "wof:name":"Scotiabank",
    "wof:placetype":"venue"
},
  "geometry": {"coordinates":[-79.4451828003,44.0103721619],"type":"Point"}
}