{
  "type": "Feature",
  "properties": {
    "addr:full":"2866 Portland Dr Oakville ON L6H 5W8",
    "addr:housenumber":"2866",
    "addr:postcode":"l6h 5w8",
    "addr:street":"Portland Dr",
    "iso:country":"CA",
    "sg:address":"2866 Portland Dr",
    "sg:city":"Oakville",
    "sg:classifiers":[
        {
            "category":"Banks & Credit Unions",
            "subcategory":"Financial Services",
            "type":"Services"
        }
    ],
    "sg:phone":"+1 905 829 5514",
    "sg:postcode":"L6H 5W8",
    "sg:province":"ON",
    "sg:tags":[
        "annuity",
        "insurance"
    ],
    "wof:name":"Canada Loyal Insurance Corp",
    "wof:placetype":"venue"
},
  "geometry": {"coordinates":[-79.680931,43.516739],"type":"Point"}
}