{
  "type": "Feature",
  "properties": {
    "addr:full":"1177 Brookfield Rd Ottawa ON K1V 0C3",
    "addr:housenumber":"1177",
    "addr:postcode":"k1v 0c3",
    "addr:street":"Brookfield Rd",
    "iso:country":"CA",
    "sg:address":"1177 Brookfield Rd",
    "sg:city":"Ottawa",
    "sg:classifiers":[
        {
            "category":"Manufacturing",
            "subcategory":"Textiles",
            "type":"Manufacturing & Wholesale Goods"
        }
    ],
    "sg:phone":"+1 613 733 4444",
    "sg:postcode":"K1V 0C3",
    "sg:province":"ON",
    "sg:tags":[
        "curtain",
        "drapery"
    ],
    "wof:name":"Drapery Factory of Ottawa Ltd",
    "wof:placetype":"venue"
},
  "geometry": {"coordinates":[-75.669006,45.374699],"type":"Point"}
}