{
  "type": "Feature",
  "properties": {
    "addr:full":"205 Mackenzie Ave Revelstoke BC V0E 2S0",
    "addr:housenumber":"205",
    "addr:postcode":"v0e 2s0",
    "addr:street":"Mackenzie Ave",
    "iso:country":"CA",
    "sg:address":"205 Mackenzie Ave",
    "sg:city":"Revelstoke",
    "sg:classifiers":[
        {
            "category":"Restaurant",
            "type":"Food & Drink"
        }
    ],
    "sg:phone":"+1 250 837 4772",
    "sg:postcode":"V0E 2S0",
    "sg:province":"BC",
    "sg:tags":[
        "shop",
        "coffee"
    ],
    "wof:name":"Conversations",
    "wof:placetype":"venue"
},
  "geometry": {"coordinates":[-118.195472717,50.9987220764],"type":"Point"}
}