{
  "type": "Feature",
  "properties": {
    "addr:full":"460 Ch Pierre-Peladeau Sainte-Adele QC J8B 1Z4",
    "addr:housenumber":"460",
    "addr:postcode":"j8b 1z4",
    "addr:street":"Ch Pierre-Peladeau Sainte-Adele",
    "iso:country":"CA",
    "sg:address":"460 Ch Pierre-Peladeau",
    "sg:city":"Sainte-Adele",
    "sg:classifiers":[
        {
            "category":"Personal",
            "subcategory":"Beauty Salon",
            "type":"Services"
        }
    ],
    "sg:phone":"+1 450 229 5801",
    "sg:postcode":"J8B 1Z4",
    "sg:province":"QC",
    "wof:name":"Coiffure Les Cupidons",
    "wof:placetype":"venue"
},
  "geometry": {"coordinates":[-74.13401,45.953075],"type":"Point"}
}