{
  "type": "Feature",
  "properties": {
    "addr:full":"2020 St Patrick Ave Saskatoon SK S7M 0L9",
    "addr:housenumber":"2020",
    "addr:postcode":"s7m 0l9",
    "addr:street":"St Patrick Ave",
    "iso:country":"CA",
    "sg:address":"2020 St Patrick Ave",
    "sg:city":"Saskatoon",
    "sg:classifiers":[
        {
            "category":"Wholesale",
            "subcategory":"Meat",
            "type":"Manufacturing & Wholesale Goods"
        }
    ],
    "sg:phone":"+1 306 665 2999",
    "sg:postcode":"S7M 0L9",
    "sg:province":"SK",
    "sg:tags":[
        "food",
        "product",
        "manufacturer"
    ],
    "wof:name":"Centennial Foodservice",
    "wof:placetype":"venue"
},
  "geometry": {"coordinates":[-106.67463684099999,52.1032867432],"type":"Point"}
}