{
  "type": "Feature",
  "properties": {
    "iso:country":"CA",
    "sg:address":"213 King St W",
    "sg:city":"Kitchener",
    "sg:classifiers":[
        {
            "category":"Real Estate",
            "subcategory":"Developer",
            "type":"Services"
        }
    ],
    "sg:phone":"+1 519 744 3113",
    "sg:postcode":"N2G 1B1",
    "sg:province":"ON",
    "wof:name":"Amalfi Investments",
    "wof:placetype":"venue"
},
  "geometry": {"coordinates":[-80.49322509770001,43.4511375427],"type":"Point"}
}