{
  "type": "Feature",
  "properties": {
    "addr:full":"Golden Lake ON K0J 1X0",
    "addr:postcode":"k0j 1x0",
    "iso:country":"CA",
    "sg:city":"Golden Lake",
    "sg:classifiers":[
        {
            "category":"Restaurant",
            "type":"Food & Drink"
        }
    ],
    "sg:phone":"+1 613 625 2898",
    "sg:postcode":"K0J 1X0",
    "sg:province":"ON",
    "wof:name":"Crossroads Restaurant & Pizza",
    "wof:placetype":"venue"
},
  "geometry": {"coordinates":[-77.189178,45.57143],"type":"Point"}
}