{
  "type": "Feature",
  "properties": {
    "addr:full":"70 Paris Rd Brantford ON N3R 1H9",
    "addr:housenumber":"70",
    "addr:postcode":"n3r 1h9",
    "addr:street":"Paris Rd",
    "iso:country":"CA",
    "sg:address":"70 Paris Rd",
    "sg:city":"Brantford",
    "sg:classifiers":[
        {
            "category":"Retail",
            "subcategory":"Animal Services",
            "type":"Services"
        }
    ],
    "sg:phone":"+1 519 756 1779",
    "sg:postcode":"N3R 1H9",
    "sg:province":"ON",
    "sg:tags":[
        "pet",
        "grooming",
        "washing"
    ],
    "wof:name":"Pet Grooming Svc",
    "wof:placetype":"venue"
},
  "geometry": {"coordinates":[-80.28881800000001,43.16003],"type":"Point"}
}