{
  "type": "Feature",
  "properties": {
    "addr:full":"1187 King Rd Burlington ON L7R 3X5",
    "addr:housenumber":"1187",
    "addr:postcode":"l7r 3x5",
    "addr:street":"King Rd",
    "iso:country":"CA",
    "sg:address":"1187 King Rd",
    "sg:city":"Burlington",
    "sg:classifiers":[
        {
            "category":"Wholesale",
            "subcategory":"Sporting Goods",
            "type":"Manufacturing & Wholesale Goods"
        }
    ],
    "sg:phone":"+1 905 637 3431",
    "sg:postcode":"L7R 3X5",
    "sg:province":"ON",
    "wof:name":"Sports Distributors of Canada",
    "wof:placetype":"venue"
},
  "geometry": {"coordinates":[-79.8389663696,43.3265342712],"type":"Point"}
}