{
  "type": "Feature",
  "properties": {
    "addr:full":"Saint-Hubert QC J3Y 8Y5",
    "addr:postcode":"j3y 8y5",
    "iso:country":"CA",
    "sg:city":"Saint-Hubert",
    "sg:classifiers":[
        {
            "category":"Shopping",
            "subcategory":"Crafts & Fabrics",
            "type":"Retail Goods"
        }
    ],
    "sg:phone":"+1 450 676 5152",
    "sg:postcode":"J3Y 8Y5",
    "sg:province":"QC",
    "sg:tags":[
        "shop"
    ],
    "wof:name":"Club Tissus",
    "wof:placetype":"venue"
},
  "geometry": {"coordinates":[-73.3927612305,45.4742965698],"type":"Point"}
}