{
  "type": "Feature",
  "properties": {
    "addr:full":"3115 13 Ave SE Medicine Hat AB T1B 3Z7",
    "addr:housenumber":"3115",
    "addr:postcode":"t1b 3z7",
    "addr:street":"13 Ave Se",
    "iso:country":"CA",
    "sg:address":"3115 13 Ave SE",
    "sg:city":"Medicine Hat",
    "sg:classifiers":[
        {
            "category":"Retail",
            "subcategory":"Car Wash",
            "type":"Services"
        }
    ],
    "sg:phone":"+1 403 527 3127",
    "sg:postcode":"T1B 3Z7",
    "sg:province":"AB",
    "sg:tags":[
        "polishing",
        "washing"
    ],
    "wof:name":"Southview Auto Spa",
    "wof:placetype":"venue"
},
  "geometry": {"coordinates":[-110.664161682,50.0107040405],"type":"Point"}
}