{
  "type": "Feature",
  "properties": {
    "addr:full":"140 Pitt St Sydney NS B1P 5X9",
    "addr:housenumber":"140",
    "addr:postcode":"b1p 5x9",
    "addr:street":"Pitt St",
    "iso:country":"CA",
    "sg:address":"140 Pitt St",
    "sg:city":"Sydney",
    "sg:classifiers":[
        {
            "category":"Insurance",
            "subcategory":"Insurance Agent",
            "type":"Services"
        }
    ],
    "sg:phone":"+1 902 539 7001",
    "sg:postcode":"B1P 5X9",
    "sg:province":"NS",
    "wof:name":"Mac Coy Insurance Brokers Ltd",
    "wof:placetype":"venue"
},
  "geometry": {"coordinates":[-60.191189,46.139751],"type":"Point"}
}