{
  "type": "Feature",
  "properties": {
    "addr:full":"640 Boul Casavant O Saint-Hyacinthe QC J2S 7S3",
    "addr:housenumber":"640",
    "addr:postcode":"j2s 7s3",
    "addr:street":"Boul Casavant O",
    "iso:country":"CA",
    "sg:address":"640 Boul Casavant O",
    "sg:city":"Saint-Hyacinthe",
    "sg:classifiers":[
        {
            "category":"Shopping",
            "subcategory":"Clothing, Apparel, & Fashions",
            "type":"Retail Goods"
        }
    ],
    "sg:phone":"+1 450 774 6633",
    "sg:postcode":"J2S 7S3",
    "sg:province":"QC",
    "sg:tags":[
        "furnishing"
    ],
    "wof:name":"Henri Christof",
    "wof:placetype":"venue"
},
  "geometry": {"coordinates":[-72.95835876460001,45.6418037415],"type":"Point"}
}