{
  "type": "Feature",
  "properties": {
    "addr:full":"155 East 26th St Hamilton ON L8V 3C5",
    "addr:housenumber":"155",
    "addr:postcode":"l8v 3c5",
    "addr:street":"East 26Th St",
    "iso:country":"CA",
    "sg:address":"155 East 26th St",
    "sg:city":"Hamilton",
    "sg:classifiers":[
        {
            "category":"Education",
            "subcategory":"School",
            "type":"Public Place"
        }
    ],
    "sg:phone":"+1 905 387 0172",
    "sg:postcode":"L8V 3C5",
    "sg:province":"ON",
    "wof:name":"Eastmount Park School",
    "wof:placetype":"venue"
},
  "geometry": {"coordinates":[-79.8490447998,43.2358093262],"type":"Point"}
}