{
  "type": "Feature",
  "properties": {
    "addr:full":"120 Crawford St Chatsworth ON N0H 1G0",
    "addr:housenumber":"120",
    "addr:postcode":"n0h 1g0",
    "addr:street":"Crawford St",
    "iso:country":"CA",
    "sg:address":"120 Crawford St",
    "sg:city":"Chatsworth",
    "sg:classifiers":[
        {
            "category":"Home & Garden",
            "subcategory":"Furniture",
            "type":"Retail Goods"
        }
    ],
    "sg:phone":"+1 519 794 2366",
    "sg:postcode":"N0H 1G0",
    "sg:province":"ON",
    "sg:tags":[
        "equipment",
        "kitchen",
        "cabinet"
    ],
    "wof:name":"Gordon Wright Custom Woodwork",
    "wof:placetype":"venue"
},
  "geometry": {"coordinates":[-80.893593,44.454674],"type":"Point"}
}