{
  "type": "Feature",
  "properties": {
    "iso:country":"CA",
    "sg:address":"601 Melchers St",
    "sg:city":"Berthierville",
    "sg:classifiers":[
        {
            "category":"Manufacturing",
            "subcategory":"Paper Products",
            "type":"Manufacturing & Wholesale Goods"
        }
    ],
    "sg:phone":"+1 450 836 7026",
    "sg:postcode":"J0K 1A0",
    "sg:province":"QC",
    "sg:tags":[
        "converter"
    ],
    "wof:name":"Converdis Inc",
    "wof:placetype":"venue"
},
  "geometry": {"coordinates":[-73.1806106567,46.0885810852],"type":"Point"}
}