{
  "type": "Feature",
  "properties": {
    "iso:country":"CA",
    "sg:city":"Stonewall",
    "sg:classifiers":[
        {
            "category":"Insurance",
            "subcategory":"Insurance Agent",
            "type":"Services"
        }
    ],
    "sg:phone":"+1 204 467 8927",
    "sg:postcode":"R0C 2Z0",
    "sg:province":"MB",
    "wof:name":"Slater-Roy Agencies Ltd",
    "wof:placetype":"venue"
},
  "geometry": {"coordinates":[-97.3266296387,50.1346893311],"type":"Point"}
}