{
  "type": "Feature",
  "properties": {
    "addr:full":"3776 Rue Georges-Corbeil Terrebonne QC J6X 4J4",
    "addr:housenumber":"3776",
    "addr:postcode":"j6x 4j4",
    "addr:street":"Rue Georges-Corbeil",
    "iso:country":"CA",
    "sg:address":"3776 Rue Georges-Corbeil",
    "sg:city":"Terrebonne",
    "sg:classifiers":[
        {
            "category":"Manufacturing",
            "subcategory":"Metals",
            "type":"Manufacturing & Wholesale Goods"
        }
    ],
    "sg:phone":"+1 450 477 3447",
    "sg:postcode":"J6X 4J4",
    "sg:province":"QC",
    "sg:tags":[
        "plating"
    ],
    "wof:name":"Placages Des Moulins Inc",
    "wof:placetype":"venue"
},
  "geometry": {"coordinates":[-73.674171,45.728188],"type":"Point"}
}