{
  "type": "Feature",
  "properties": {
    "addr:full":"2139 Rte 235 Sainte-Sabine QC J0J 2B0",
    "addr:housenumber":"2139",
    "addr:postcode":"j0j 2b0",
    "addr:street":"Rte 235",
    "iso:country":"CA",
    "sg:address":"2139 Rte 235",
    "sg:city":"Sainte-Sabine",
    "sg:classifiers":[
        {
            "category":"Building & Trades",
            "subcategory":"Construction",
            "type":"Services"
        }
    ],
    "sg:phone":"+1 450 293 5062",
    "sg:postcode":"J0J 2B0",
    "sg:province":"QC",
    "sg:tags":[
        "excavating",
        "contractor"
    ],
    "wof:name":"Excavation F Lanoue Inc",
    "wof:placetype":"venue"
},
  "geometry": {"coordinates":[-72.992638,45.219578],"type":"Point"}
}