{
  "type": "Feature",
  "properties": {
    "iso:country":"CA",
    "sg:address":"536 Queen St W",
    "sg:city":"Toronto",
    "sg:classifiers":[
        {
            "category":"Shopping",
            "subcategory":"Used Merchandise",
            "type":"Retail Goods"
        }
    ],
    "sg:phone":"+1 416 504 7706",
    "sg:postcode":"M5V 2B5",
    "sg:province":"ON",
    "sg:tags":[
        "antique"
    ],
    "wof:name":"Red Indian Art Deco",
    "wof:placetype":"venue"
},
  "geometry": {"coordinates":[-79.4025650024,43.6476211548],"type":"Point"}
}