{
  "type": "Feature",
  "properties": {
    "addr:full":"9200 Rue Des Voyaux Mirabel QC J7N 2H4",
    "addr:housenumber":"9200",
    "addr:postcode":"j7n 2h4",
    "addr:street":"Rue Des Voyaux",
    "iso:country":"CA",
    "sg:address":"9200 Rue Des Voyaux",
    "sg:city":"Mirabel",
    "sg:classifiers":[
        {
            "category":"Wholesale",
            "subcategory":"Fruits & Vegetables",
            "type":"Manufacturing & Wholesale Goods"
        }
    ],
    "sg:phone":"+1 450 475 7924",
    "sg:postcode":"J7N 2H4",
    "sg:province":"QC",
    "sg:tags":[
        "shipper"
    ],
    "wof:name":"Hydroserre Mirabel Inc",
    "wof:placetype":"venue"
},
  "geometry": {"coordinates":[-74.02522999999999,45.639809],"type":"Point"}
}