{
  "type": "Feature",
  "properties": {
    "addr:full":"2315 Parkcrest Ave Kamloops BC V2B 4Y2",
    "addr:housenumber":"2315",
    "addr:postcode":"bc v2b 4y2",
    "addr:street":"Parkcrest Ave",
    "iso:country":"CA",
    "sg:address":"2315 Parkcrest Ave",
    "sg:city":"Kamloops",
    "sg:classifiers":[
        {
            "category":"Building & Trades",
            "subcategory":"Construction",
            "type":"Services"
        }
    ],
    "sg:phone":"+1 250 554 5087",
    "sg:postcode":"V2B 4Y2",
    "sg:province":"BC",
    "sg:tags":[
        "masonry",
        "contractor"
    ],
    "wof:name":"Kamloops Brick & Block Ltd",
    "wof:placetype":"venue"
},
  "geometry": {"coordinates":[-120.411674499,50.7077407837],"type":"Point"}
}