{
  "type": "Feature",
  "properties": {
    "addr:full":"10887 Ilderton Rd Ilderton ON N0M 2A0",
    "addr:housenumber":"10887",
    "addr:postcode":"n0m 2a0",
    "addr:street":"Ilderton Rd",
    "iso:country":"CA",
    "sg:address":"10887 Ilderton Rd",
    "sg:city":"Ilderton",
    "sg:classifiers":[
        {
            "category":"Retail",
            "subcategory":"Auto Repair",
            "type":"Services"
        }
    ],
    "sg:phone":"+1 519 666 1942",
    "sg:postcode":"N0M 2A0",
    "sg:province":"ON",
    "sg:tags":[
        "repairing",
        "automobile"
    ],
    "wof:name":"Moraal's Garage",
    "wof:placetype":"venue"
},
  "geometry": {"coordinates":[-81.4744720459,43.0351867676],"type":"Point"}
}