{
  "type": "Feature",
  "properties": {
    "addr:full":"4955 No. 3 Rd Richmond BC V6X 2C3",
    "addr:postcode":"4955;v6x 2c3",
    "addr:street":"3 Rd",
    "iso:country":"CA",
    "sg:address":"4955 No. 3 Rd",
    "sg:city":"Richmond",
    "sg:classifiers":[
        {
            "category":"Shopping",
            "subcategory":"Department Store",
            "type":"Retail Goods"
        }
    ],
    "sg:phone":"+1 604 232 9957",
    "sg:postcode":"V6X 2C3",
    "sg:province":"BC",
    "sg:tags":[
        "shop"
    ],
    "wof:name":"Big Crazy Discount Variety",
    "wof:placetype":"venue"
},
  "geometry": {"coordinates":[-123.13684845,49.1778373718],"type":"Point"}
}