{
  "type": "Feature",
  "properties": {
    "iso:country":"CA",
    "sg:address":"29 Seapark Dr #2",
    "sg:city":"St Catharines",
    "sg:classifiers":[
        {
            "category":"Manufacturing",
            "subcategory":"Metals",
            "type":"Manufacturing & Wholesale Goods"
        }
    ],
    "sg:phone":"+1 905 984 5400",
    "sg:postcode":"L2M 6S5",
    "sg:province":"ON",
    "sg:tags":[
        "tool",
        "production"
    ],
    "wof:name":"Regal Carbide Tools Ltd",
    "wof:placetype":"venue"
},
  "geometry": {"coordinates":[-79.2033462524,43.1746063232],"type":"Point"}
}