{
  "type": "Feature",
  "properties": {
    "addr:full":"Langley BC V1M 3G1",
    "addr:postcode":"v1m 3g1",
    "iso:country":"CA",
    "sg:city":"Langley",
    "sg:classifiers":[
        {
            "category":"Freight",
            "type":"Transportation"
        }
    ],
    "sg:phone":"+1 604 888 6300",
    "sg:postcode":"V1M 3G1",
    "sg:province":"BC",
    "sg:tags":[
        "trucking"
    ],
    "wof:name":"West Arm Truck Lines Ltd",
    "wof:placetype":"venue"
},
  "geometry": {"coordinates":[-122.673500061,49.1806335449],"type":"Point"}
}