{
  "type": "Feature",
  "properties": {
    "addr:full":"Windsor ON N8X 5E8",
    "addr:postcode":"n8x 5e8",
    "iso:country":"CA",
    "sg:city":"Windsor",
    "sg:classifiers":[
        {
            "category":"Food & Beverages",
            "subcategory":"Groceries & Convenience Stores",
            "type":"Retail Goods"
        }
    ],
    "sg:phone":"+1 519 253 5495",
    "sg:postcode":"N8X 5E8",
    "sg:province":"ON",
    "sg:tags":[
        "grocer"
    ],
    "wof:name":"Price Chopper",
    "wof:placetype":"venue"
},
  "geometry": {"coordinates":[-83.020706,42.297413],"type":"Point"}
}