{
  "type": "Feature",
  "properties": {
    "iso:country":"CA",
    "sg:address":"143 Cardinal Cres",
    "sg:city":"Saskatoon",
    "sg:classifiers":[
        {
            "category":"Real Estate",
            "subcategory":"Real Estate Agent",
            "type":"Services"
        }
    ],
    "sg:phone":"+1 306 934 2799",
    "sg:postcode":"S7L 6H5",
    "sg:province":"SK",
    "sg:tags":[
        "management"
    ],
    "wof:name":"P R Developments Ltd",
    "wof:placetype":"venue"
},
  "geometry": {"coordinates":[-106.68536377,52.1539573669],"type":"Point"}
}