{
  "type": "Feature",
  "properties": {
    "addr:full":"380 Riverside Rd # 3 Abbotsford BC V2S 7M4",
    "addr:housenumber":"380",
    "addr:postcode":"v2s 7m4",
    "addr:street":"Riverside Rd # 3",
    "iso:country":"CA",
    "sg:address":"380 Riverside Rd # 3",
    "sg:city":"Abbotsford",
    "sg:classifiers":[
        {
            "category":"Retail",
            "subcategory":"Auto Repair",
            "type":"Services"
        }
    ],
    "sg:phone":"+1 604 504 5750",
    "sg:postcode":"V2S 7M4",
    "sg:province":"BC",
    "sg:tags":[
        "truck"
    ],
    "wof:name":"Western Star & Sterling Trucks",
    "wof:placetype":"venue"
},
  "geometry": {"coordinates":[-122.27166699999999,49.009094],"type":"Point"}
}