{
  "type": "Feature",
  "properties": {
    "addr:full":"Richmond BC V6V 2L9",
    "addr:postcode":"v6v 2l9",
    "iso:country":"CA",
    "sg:city":"Richmond",
    "sg:classifiers":[
        {
            "category":"Wholesale",
            "subcategory":"Drugs",
            "type":"Manufacturing & Wholesale Goods"
        }
    ],
    "sg:phone":"+1 604 279 0363",
    "sg:postcode":"V6V 2L9",
    "sg:province":"BC",
    "sg:tags":[
        "pharmaceutical",
        "product"
    ],
    "wof:name":"Kinesys Pharmaceutical Inc",
    "wof:placetype":"venue"
},
  "geometry": {"coordinates":[-123.080521,49.187248],"type":"Point"}
}