{
  "type": "Feature",
  "properties": {
    "iso:country":"CA",
    "sg:address":"1175 Granville St",
    "sg:city":"Vancouver",
    "sg:classifiers":[
        {
            "category":"Restaurant",
            "type":"Food & Drink"
        }
    ],
    "sg:phone":"+1 604 669 7495",
    "sg:postcode":"V6Z 1M1",
    "sg:province":"BC",
    "wof:name":"Grade A Steak & Seafood Rstrnt",
    "wof:placetype":"venue"
},
  "geometry": {"coordinates":[-123.125900269,49.277557373],"type":"Point"}
}