{
  "type": "Feature",
  "properties": {
    "addr:full":"Lacombe AB T4L 2A1",
    "addr:postcode":"t4l 2a1",
    "iso:country":"CA",
    "sg:city":"Lacombe",
    "sg:classifiers":[
        {
            "category":"Shopping",
            "subcategory":"Florist",
            "type":"Retail Goods"
        }
    ],
    "sg:phone":"+1 403 782 5016",
    "sg:postcode":"T4L 2A1",
    "sg:province":"AB",
    "wof:name":"Lacombe Florist Ltd",
    "wof:placetype":"venue"
},
  "geometry": {"coordinates":[-113.72333526600001,52.4663696289],"type":"Point"}
}