{
  "type": "Feature",
  "properties": {
    "addr:full":"Calgary AB T2Y 1X7",
    "addr:postcode":"t2y 1x7",
    "iso:country":"CA",
    "sg:city":"Calgary",
    "sg:classifiers":[
        {
            "category":"Autos & Motor Vehicles",
            "subcategory":"Fuel & Gas Station",
            "type":"Retail Goods"
        }
    ],
    "sg:phone":"+1 403 254 0900",
    "sg:postcode":"T2Y 1X7",
    "sg:province":"AB",
    "sg:tags":[
        "oil"
    ],
    "wof:name":"Millrise Turbo",
    "wof:placetype":"venue"
},
  "geometry": {"coordinates":[-114.075272,50.920586],"type":"Point"}
}