{
  "type": "Feature",
  "properties": {
    "addr:full":"Victoria BC V9A 5V1",
    "addr:postcode":"v9a 5v1",
    "iso:country":"CA",
    "sg:city":"Victoria",
    "sg:classifiers":[
        {
            "category":"Manufacturing",
            "subcategory":"Metals",
            "type":"Manufacturing & Wholesale Goods"
        }
    ],
    "sg:phone":"+1 250 388 3536",
    "sg:postcode":"V9A 5V1",
    "sg:province":"BC",
    "sg:tags":[
        "work",
        "sheet",
        "heating",
        "contractor"
    ],
    "wof:name":"Blue Valley Ind Ltd",
    "wof:placetype":"venue"
},
  "geometry": {"coordinates":[-123.363106,48.421227],"type":"Point"}
}