{
  "type": "Feature",
  "properties": {
    "addr:full":"2875 Boul DE Portland Sherbrooke QC J1L 2S1",
    "addr:housenumber":"2875",
    "addr:postcode":"j1l 2s1",
    "addr:street":"Boul De Portland",
    "iso:country":"CA",
    "sg:address":"2875 Boul DE Portland",
    "sg:city":"Sherbrooke",
    "sg:classifiers":[
        {
            "category":"Government",
            "subcategory":"Office",
            "type":"Public Place"
        }
    ],
    "sg:phone":"+1 819 820 3057",
    "sg:postcode":"J1L 2S1",
    "sg:province":"QC",
    "wof:name":"Quebec Readaptation",
    "wof:placetype":"venue"
},
  "geometry": {"coordinates":[-71.94663199999999,45.403824],"type":"Point"}
}