{
  "type": "Feature",
  "properties": {
    "iso:country":"CA",
    "sg:city":"Brockville",
    "sg:classifiers":[
        {
            "category":"Real Estate",
            "subcategory":"Real Estate Operator",
            "type":"Services"
        }
    ],
    "sg:phone":"+1 613 498 0898",
    "sg:postcode":"K6V 6N8",
    "sg:province":"ON",
    "sg:tags":[
        "apartment"
    ],
    "wof:name":"Kensington 2 Partnership",
    "wof:placetype":"venue"
},
  "geometry": {"coordinates":[-75.7144622803,44.6081047058],"type":"Point"}
}