{
  "type": "Feature",
  "properties": {
    "addr:full":"1964 Rue Saint-Zotique E Montreal QC H2G 1J1",
    "addr:housenumber":"1964",
    "addr:postcode":"h2g 1j1",
    "addr:street":"Rue Saint-Zotique E",
    "iso:country":"CA",
    "sg:address":"1964 Rue Saint-Zotique E",
    "sg:city":"Montreal",
    "sg:classifiers":[
        {
            "category":"Building & Trades",
            "subcategory":"Construction",
            "type":"Services"
        }
    ],
    "sg:phone":"+1 514 728 3615",
    "sg:postcode":"H2G 1J1",
    "sg:province":"QC",
    "sg:tags":[
        "repairing",
        "contractor",
        "remodeling",
        "general"
    ],
    "wof:name":"Champoux Gaston Inc",
    "wof:placetype":"venue"
},
  "geometry": {"coordinates":[-73.59865600000001,45.546047],"type":"Point"}
}