{
  "type": "Feature",
  "properties": {
    "addr:full":"7 1st Ave SW Carman MB R0G 0J0",
    "addr:housenumber":"7",
    "addr:postcode":"r0g 0j0",
    "addr:street":"1St Ave Sw",
    "iso:country":"CA",
    "sg:address":"7 1st Ave SW",
    "sg:city":"Carman",
    "sg:classifiers":[
        {
            "category":"Banks & Credit Unions",
            "subcategory":"Bank",
            "type":"Services"
        }
    ],
    "sg:phone":"+1 204 745 2043",
    "sg:postcode":"R0G 0J0",
    "sg:province":"MB",
    "wof:name":"Dufferin Credit Union",
    "wof:placetype":"venue"
},
  "geometry": {"coordinates":[-98.00329600000001,49.507076],"type":"Point"}
}