{
  "type": "Feature",
  "properties": {
    "iso:country":"CA",
    "sg:address":"360 Gibson St",
    "sg:city":"Fredericton",
    "sg:classifiers":[
        {
            "category":"Building & Trades",
            "subcategory":"Construction",
            "type":"Services"
        }
    ],
    "sg:phone":"+1 506 450 2772",
    "sg:postcode":"E3A 4E6",
    "sg:province":"NB",
    "sg:tags":[
        "repairing",
        "home",
        "contractor",
        "remodeling",
        "improvement"
    ],
    "wof:name":"Restoration-Renovations",
    "wof:placetype":"venue"
},
  "geometry": {"coordinates":[-66.6134262085,45.9644737244],"type":"Point"}
}