{
  "type": "Feature",
  "properties": {
    "addr:full":"592 Sherbourne St Toronto ON M4X 1L4",
    "addr:housenumber":"592",
    "addr:postcode":"m4x 1l4",
    "addr:street":"Sherbourne St",
    "iso:country":"CA",
    "sg:address":"592 Sherbourne St",
    "sg:city":"Toronto",
    "sg:classifiers":[
        {
            "category":"Bars & Pubs",
            "type":"Food & Drink"
        }
    ],
    "sg:phone":"+1 416 921 0665",
    "sg:postcode":"M4X 1L4",
    "sg:province":"ON",
    "wof:name":"Boots Bar",
    "wof:placetype":"venue"
},
  "geometry": {"coordinates":[-79.3764877319,43.6712875366],"type":"Point"}
}