{
  "type": "Feature",
  "properties": {
    "iso:country":"CA",
    "sg:city":"Aurora",
    "sg:classifiers":[
        {
            "category":"Manufacturing",
            "subcategory":"Tools & Machinery",
            "type":"Manufacturing & Wholesale Goods"
        }
    ],
    "sg:phone":"+1 905 751 1500",
    "sg:postcode":"L4G 1H7",
    "sg:province":"ON",
    "sg:tags":[
        "turbine"
    ],
    "wof:name":"Pacific Industries Intl Inc",
    "wof:placetype":"venue"
},
  "geometry": {"coordinates":[-79.463394,44.000431],"type":"Point"}
}