{
  "type": "Feature",
  "properties": {
    "addr:full":"87 Copernicus Blvd #B Brantford ON N3P 1N4",
    "addr:housenumber":"87",
    "addr:postcode":"n3p 1n4",
    "addr:street":"Copernicus Blvd # B",
    "iso:country":"CA",
    "sg:address":"87 Copernicus Blvd #B",
    "sg:city":"Brantford",
    "sg:classifiers":[
        {
            "category":"Manufacturing",
            "subcategory":"Tools & Machinery",
            "type":"Manufacturing & Wholesale Goods"
        }
    ],
    "sg:phone":"+1 519 756 5504",
    "sg:postcode":"N3P 1N4",
    "sg:province":"ON",
    "sg:tags":[
        "machine",
        "shop"
    ],
    "wof:name":"Apex Metal Works",
    "wof:placetype":"venue"
},
  "geometry": {"coordinates":[-80.23891399999999,43.179585],"type":"Point"}
}