{
  "type": "Feature",
  "properties": {
    "iso:country":"CA",
    "sg:address":"359 Shannon Rd",
    "sg:city":"Sault Ste Marie",
    "sg:classifiers":[
        {
            "category":"Organizations",
            "subcategory":"Professional Association",
            "type":"Services"
        }
    ],
    "sg:phone":"+1 705 254 1378",
    "sg:postcode":"P6A 4K6",
    "sg:province":"ON",
    "wof:name":"Community Living Algoma",
    "wof:placetype":"venue"
},
  "geometry": {"coordinates":[-84.283661,46.508396],"type":"Point"}
}