{
  "type": "Feature",
  "properties": {
    "addr:full":"Toronto ON M5G 1Z6",
    "addr:postcode":"m5g 1z6",
    "iso:country":"CA",
    "sg:city":"Toronto",
    "sg:classifiers":[
        {
            "category":"Professional",
            "subcategory":"Research",
            "type":"Services"
        }
    ],
    "sg:phone":"+1 416 586 5421",
    "sg:postcode":"M5G 1Z6",
    "sg:province":"ON",
    "sg:tags":[
        "development",
        "laboratory"
    ],
    "wof:name":"Ellipsis Bio Therapeutics",
    "wof:placetype":"venue"
},
  "geometry": {"coordinates":[-79.384964,43.658237],"type":"Point"}
}