{
  "type": "Feature",
  "properties": {
    "addr:full":"3640 Victoria Park Ave North York ON M2H 3B2",
    "addr:housenumber":"3640",
    "addr:postcode":"m2h 3b2",
    "addr:street":"Victoria Park Ave",
    "iso:country":"CA",
    "sg:address":"3640 Victoria Park Ave",
    "sg:city":"North York",
    "sg:classifiers":[
        {
            "category":"Real Estate",
            "subcategory":"Real Estate Agent",
            "type":"Services"
        }
    ],
    "sg:phone":"+1 416 756 0663",
    "sg:postcode":"M2H 3B2",
    "sg:province":"ON",
    "sg:tags":[
        "management"
    ],
    "wof:name":"Farne Properties Ltd",
    "wof:placetype":"venue"
},
  "geometry": {"coordinates":[-79.33805084230001,43.8075523376],"type":"Point"}
}