{
  "type": "Feature",
  "properties": {
    "addr:full":"2965 Airport Rd Kamloops BC V2B 7W8",
    "addr:housenumber":"2965",
    "addr:postcode":"bc v2b 7w8",
    "addr:street":"Airport Rd",
    "iso:country":"CA",
    "sg:address":"2965 Airport Rd",
    "sg:city":"Kamloops",
    "sg:classifiers":[
        {
            "category":"Wholesale",
            "subcategory":"Machinery & Supplies",
            "type":"Manufacturing & Wholesale Goods"
        }
    ],
    "sg:phone":"+1 250 376 1223",
    "sg:postcode":"V2B 7W8",
    "sg:province":"BC",
    "sg:tags":[
        "engine",
        "aircraft",
        "parts"
    ],
    "wof:name":"Pro-Aero Engines Inc",
    "wof:placetype":"venue"
},
  "geometry": {"coordinates":[-120.439438,50.706833],"type":"Point"}
}