{
  "type": "Feature",
  "properties": {
    "addr:full":"Vancouver BC V6B 5L7",
    "addr:postcode":"v6b 5l7",
    "iso:country":"CA",
    "sg:city":"Vancouver",
    "sg:classifiers":[
        {
            "category":"Professional",
            "subcategory":"Management & Consulting",
            "type":"Services"
        }
    ],
    "sg:phone":"+1 604 623 3007",
    "sg:postcode":"V6B 5L7",
    "sg:province":"BC",
    "sg:tags":[
        "counselor",
        "public",
        "relations"
    ],
    "wof:name":"Karyo Communications Inc",
    "wof:placetype":"venue"
},
  "geometry": {"coordinates":[-123.118858,49.275646],"type":"Point"}
}