{
  "type": "Feature",
  "properties": {
    "addr:full":"5133 53 St Daysland AB T0B 1A0",
    "addr:housenumber":"5133",
    "addr:postcode":"t0b 1a0",
    "addr:street":"53 St",
    "iso:country":"CA",
    "sg:address":"5133 53 St",
    "sg:city":"Daysland",
    "sg:classifiers":[
        {
            "category":"Professional",
            "subcategory":"Business Services",
            "type":"Services"
        }
    ],
    "sg:phone":"+1 780 374 3802",
    "sg:postcode":"T0B 1A0",
    "sg:province":"AB",
    "wof:name":"Delta Vac Trucking Ltd",
    "wof:placetype":"venue"
},
  "geometry": {"coordinates":[-112.261589,52.8633],"type":"Point"}
}