{
  "type": "Feature",
  "properties": {
    "addr:full":"21 John St Petawawa ON K8H 1S5",
    "addr:housenumber":"21",
    "addr:postcode":"k8h 1s5",
    "addr:street":"John St",
    "iso:country":"CA",
    "sg:address":"21 John St",
    "sg:city":"Petawawa",
    "sg:classifiers":[
        {
            "category":"Personal",
            "type":"Services"
        }
    ],
    "sg:phone":"+1 613 687 7017",
    "sg:postcode":"K8H 1S5",
    "sg:province":"ON",
    "sg:tags":[
        "school",
        "electrolysis",
        "beauty"
    ],
    "wof:name":"Laurie Anne's Electrolysis",
    "wof:placetype":"venue"
},
  "geometry": {"coordinates":[-77.27752700000001,45.893246],"type":"Point"}
}