{
  "type": "Feature",
  "properties": {
    "addr:full":"2154 Rue King O Sherbrooke QC J1J 2E8",
    "addr:housenumber":"2154",
    "addr:postcode":"j1j 2e8",
    "addr:street":"Rue King O",
    "iso:country":"CA",
    "sg:address":"2154 Rue King O",
    "sg:city":"Sherbrooke",
    "sg:classifiers":[
        {
            "category":"Personal",
            "subcategory":"Tanning Parlor",
            "type":"Services"
        }
    ],
    "sg:phone":"+1 819 822 2224",
    "sg:postcode":"J1J 2E8",
    "sg:province":"QC",
    "sg:tags":[
        "club",
        "studio",
        "salon",
        "health",
        "gymnasium"
    ],
    "wof:name":"Femme Estrie",
    "wof:placetype":"venue"
},
  "geometry": {"coordinates":[-71.9253768921,45.3979492188],"type":"Point"}
}