{
  "type": "Feature",
  "properties": {
    "iso:country":"CA",
    "sg:address":"5050 Dufferin St #122",
    "sg:city":"North York",
    "sg:classifiers":[
        {
            "category":"Building & Trades",
            "subcategory":"Plumbing",
            "type":"Services"
        }
    ],
    "sg:phone":"+1 416 665 4357",
    "sg:postcode":"M3H 5T5",
    "sg:province":"ON",
    "sg:tags":[
        "contractor"
    ],
    "wof:name":"Pipeline Mechanical Svc Ltd",
    "wof:placetype":"venue"
},
  "geometry": {"coordinates":[-79.47016143800001,43.7814826965],"type":"Point"}
}