{
  "type": "Feature",
  "properties": {
    "addr:full":"5585 Timberlea Blvd Mississauga ON L4W 2S4",
    "addr:housenumber":"5585",
    "addr:postcode":"l4w 2s4",
    "addr:street":"Timberlea Blvd",
    "iso:country":"CA",
    "sg:address":"5585 Timberlea Blvd",
    "sg:city":"Mississauga",
    "sg:classifiers":[
        {
            "category":"Manufacturing",
            "subcategory":"Printing",
            "type":"Manufacturing & Wholesale Goods"
        }
    ],
    "sg:phone":"+1 905 629 1688",
    "sg:postcode":"L4W 2S4",
    "sg:province":"ON",
    "sg:tags":[
        "printer"
    ],
    "wof:name":"Value Printing Ltd",
    "wof:placetype":"venue"
},
  "geometry": {"coordinates":[-79.6498031616,43.6361732483],"type":"Point"}
}