{
  "type": "Feature",
  "properties": {
    "addr:full":"10541 60A Ave NW Edmonton AB T6H 1K4",
    "addr:housenumber":"10541",
    "addr:postcode":"t6h 1k4",
    "addr:street":"60A Ave Nw",
    "iso:country":"CA",
    "sg:address":"10541 60A Ave NW",
    "sg:city":"Edmonton",
    "sg:classifiers":[
        {
            "category":"Education",
            "subcategory":"School",
            "type":"Public Place"
        }
    ],
    "sg:phone":"+1 780 434 6766",
    "sg:postcode":"T6H 1K4",
    "sg:province":"AB",
    "wof:name":"Mount Pleasant Elementary Schl",
    "wof:placetype":"venue"
},
  "geometry": {"coordinates":[-113.50206756599999,53.4960823059],"type":"Point"}
}