{
  "type": "Feature",
  "properties": {
    "addr:full":"North York ON M6A 1Z6",
    "addr:postcode":"m6a 1z6",
    "iso:country":"CA",
    "sg:city":"North York",
    "sg:phone":"+1 416 787 1813",
    "sg:postcode":"M6A 1Z6",
    "sg:province":"ON",
    "sg:tags":[
        "light",
        "material",
        "fixture",
        "display",
        "decoration",
        "christmas"
    ],
    "wof:name":"Studio Specialties Ltd",
    "wof:placetype":"venue"
},
  "geometry": {"coordinates":[-79.470268,43.723869],"type":"Point"}
}