{
  "type": "Feature",
  "properties": {
    "addr:full":"880 Nairn Ave Winnipeg MB R2L 0X8",
    "addr:housenumber":"880",
    "addr:postcode":"r2l 0x8",
    "addr:street":"Nairn Ave",
    "iso:country":"CA",
    "sg:address":"880 Nairn Ave",
    "sg:city":"Winnipeg",
    "sg:classifiers":[
        {
            "category":"Home & Garden",
            "subcategory":"Furniture",
            "type":"Retail Goods"
        }
    ],
    "sg:phone":"+1 204 667 1578",
    "sg:postcode":"R2L 0X8",
    "sg:province":"MB",
    "wof:name":"Dufresne Furniture & Appliance",
    "wof:placetype":"venue"
},
  "geometry": {"coordinates":[-97.08618927000001,49.9012680054],"type":"Point"}
}