{
  "type": "Feature",
  "properties": {
    "addr:full":"Saskatoon SK S7L 5X4",
    "addr:postcode":"s7l 5x4",
    "iso:country":"CA",
    "sg:city":"Saskatoon",
    "sg:phone":"+1 306 242 0088",
    "sg:postcode":"S7L 5X4",
    "sg:province":"SK",
    "sg:tags":[
        "fuel",
        "aviation"
    ],
    "wof:name":"Airport Esso",
    "wof:placetype":"venue"
},
  "geometry": {"coordinates":[-106.689323425,52.1703109741],"type":"Point"}
}