{
  "type": "Feature",
  "properties": {
    "addr:full":"77 Ross St W Moose Jaw SK S6H 2M2",
    "addr:housenumber":"77",
    "addr:postcode":"s6h 2m2",
    "addr:street":"Ross St W",
    "iso:country":"CA",
    "sg:address":"77 Ross St W",
    "sg:city":"Moose Jaw",
    "sg:classifiers":[
        {
            "category":"Health Services",
            "subcategory":"Doctor",
            "type":"Services"
        }
    ],
    "sg:phone":"+1 306 692 0200",
    "sg:postcode":"S6H 2M2",
    "sg:province":"SK",
    "sg:tags":[
        "physician",
        "surgeon"
    ],
    "wof:name":"Dautremont, K MD",
    "wof:placetype":"venue"
},
  "geometry": {"coordinates":[-105.537132263,50.3977584839],"type":"Point"}
}