{
  "type": "Feature",
  "properties": {
    "addr:full":"Kamloops BC V2C 6H6",
    "addr:postcode":"bc v2c 6h6",
    "iso:country":"CA",
    "sg:city":"Kamloops",
    "sg:classifiers":[
        {
            "category":"Professional",
            "subcategory":"Lawyer & Legal Services",
            "type":"Services"
        }
    ],
    "sg:phone":"+1 250 374 3161",
    "sg:postcode":"V2C 6H6",
    "sg:province":"BC",
    "sg:tags":[
        "attorney"
    ],
    "wof:name":"Harrison, Marlene S",
    "wof:placetype":"venue"
},
  "geometry": {"coordinates":[-120.335083008,50.6765594482],"type":"Point"}
}