{
  "type": "Feature",
  "properties": {
    "addr:full":"800 Centre St # 105 Espanola ON P5E 1J3",
    "addr:housenumber":"800",
    "addr:postcode":"p5e 1j3",
    "addr:street":"Centre St # 105",
    "iso:country":"CA",
    "sg:address":"800 Centre St # 105",
    "sg:city":"Espanola",
    "sg:classifiers":[
        {
            "category":"Shopping",
            "subcategory":"Clothing, Apparel, & Fashions",
            "type":"Retail Goods"
        }
    ],
    "sg:phone":"+1 705 869 6780",
    "sg:postcode":"P5E 1J3",
    "sg:province":"ON",
    "sg:tags":[
        "furnishing"
    ],
    "wof:name":"Mark's Work Wearhouse",
    "wof:placetype":"venue"
},
  "geometry": {"coordinates":[-81.758064,46.247795],"type":"Point"}
}