{
  "type": "Feature",
  "properties": {
    "addr:full":"3055 Massey Dr Prince George BC V2N 2S9",
    "addr:housenumber":"3055",
    "addr:postcode":"v2n 2s9",
    "addr:street":"Massey Dr",
    "iso:country":"CA",
    "sg:address":"3055 Massey Dr",
    "sg:city":"Prince George",
    "sg:classifiers":[
        {
            "category":"Shopping",
            "subcategory":"Clothing, Apparel, & Fashions",
            "type":"Retail Goods"
        }
    ],
    "sg:phone":"+1 250 563 8535",
    "sg:postcode":"V2N 2S9",
    "sg:province":"BC",
    "wof:name":"Bryan's Fashions",
    "wof:placetype":"venue"
},
  "geometry": {"coordinates":[-122.779839,53.899452],"type":"Point"}
}