{
  "type": "Feature",
  "properties": {
    "iso:country":"CA",
    "sg:address":"215 Thames St S",
    "sg:city":"Ingersoll",
    "sg:classifiers":[
        {
            "category":"Restaurant",
            "type":"Food & Drink"
        }
    ],
    "sg:phone":"+1 519 425 0075",
    "sg:postcode":"N5C 2T6",
    "sg:province":"ON",
    "wof:name":"Crabby Joe's Pub & Grill",
    "wof:placetype":"venue"
},
  "geometry": {"coordinates":[-80.88065338129999,43.036693573],"type":"Point"}
}