{
  "type": "Feature",
  "properties": {
    "addr:full":"Charlesbourg QC G1G 4E1",
    "addr:postcode":"g1g 4e1",
    "iso:country":"CA",
    "sg:city":"Charlesbourg",
    "sg:classifiers":[
        {
            "category":"Shopping",
            "subcategory":"Gifts & Souvenirs",
            "type":"Retail Goods"
        }
    ],
    "sg:phone":"+1 418 622 3115",
    "sg:postcode":"G1G 4E1",
    "sg:province":"QC",
    "sg:tags":[
        "shop"
    ],
    "wof:name":"Aux Sept Tiroirs",
    "wof:placetype":"venue"
},
  "geometry": {"coordinates":[-71.2705917358,46.8646011353],"type":"Point"}
}