{
  "type": "Feature",
  "properties": {
    "addr:full":"Richmond BC V7A 1N6",
    "addr:postcode":"v7a 1n6",
    "iso:country":"CA",
    "sg:city":"Richmond",
    "sg:classifiers":[
        {
            "category":"Restaurant",
            "type":"Food & Drink"
        }
    ],
    "sg:phone":"+1 604 274 2462",
    "sg:postcode":"V7A 1N6",
    "sg:province":"BC",
    "wof:name":"Death By Chocolate",
    "wof:placetype":"venue"
},
  "geometry": {"coordinates":[-123.09522247300001,49.1331443787],"type":"Point"}
}