{
  "type": "Feature",
  "properties": {
    "addr:full":"PO Box 76 Boat Harbour West NL A0E 1C0",
    "addr:housenumber":"po box 76",
    "addr:postcode":"harbour;a0e 1c0",
    "addr:street":"West",
    "iso:country":"CA",
    "sg:address":"PO Box 76",
    "sg:city":"Boat Harbour West",
    "sg:classifiers":[
        {
            "category":"Organizations",
            "subcategory":"Professional Association",
            "type":"Services"
        }
    ],
    "sg:phone":"+1 709 443 2550",
    "sg:postcode":"A0E 1C0",
    "sg:province":"NL",
    "wof:name":"Placentia West Development",
    "wof:placetype":"venue"
},
  "geometry": {"coordinates":[-54.860706,47.440262],"type":"Point"}
}