{
  "type": "Feature",
  "properties": {
    "addr:full":"Carleton QC G0C 1J0",
    "addr:postcode":"g0c 1j0",
    "iso:country":"CA",
    "sg:city":"Carleton",
    "sg:classifiers":[
        {
            "category":"Retail",
            "subcategory":"Auto Repair",
            "type":"Services"
        }
    ],
    "sg:phone":"+1 418 364 7231",
    "sg:postcode":"G0C 1J0",
    "sg:province":"QC",
    "sg:tags":[
        "repairing",
        "automobile"
    ],
    "wof:name":"Garage Jean-Yves Otis Enr",
    "wof:placetype":"venue"
},
  "geometry": {"coordinates":[-66.11834,48.101406],"type":"Point"}
}