{
  "type": "Feature",
  "properties": {
    "addr:full":"509 N 8th Ave Golden BC V0A 1H0",
    "addr:housenumber":"509",
    "addr:postcode":"v0a 1h0",
    "addr:street":"N 8Th Ave",
    "iso:country":"CA",
    "sg:address":"509 N 8th Ave",
    "sg:city":"Golden",
    "sg:classifiers":[
        {
            "category":"Professional",
            "subcategory":"Employment Agencies",
            "type":"Services"
        }
    ],
    "sg:phone":"+1 250 344 5413",
    "sg:postcode":"V0A 1H0",
    "sg:province":"BC",
    "sg:tags":[
        "opportunity"
    ],
    "wof:name":"Golden Employment Svc",
    "wof:placetype":"venue"
},
  "geometry": {"coordinates":[-116.968582,51.298744],"type":"Point"}
}