{
  "type": "Feature",
  "properties": {
    "iso:country":"CA",
    "sg:address":"290 College St",
    "sg:city":"Toronto",
    "sg:classifiers":[
        {
            "category":"Shopping",
            "subcategory":"Computers & Home Electronics",
            "type":"Retail Goods"
        }
    ],
    "sg:phone":"+1 416 962 7788",
    "sg:postcode":"M5T 1R9",
    "sg:province":"ON",
    "sg:tags":[
        "equipment",
        "dealer"
    ],
    "wof:name":"Factory Direct Computer",
    "wof:placetype":"venue"
},
  "geometry": {"coordinates":[-79.40130615229999,43.6578674316],"type":"Point"}
}