{
  "type": "Feature",
  "properties": {
    "addr:full":"2279 Cranbrook St N Cranbrook BC V1C 3T3",
    "addr:housenumber":"2279",
    "addr:postcode":"v1c 3t3",
    "addr:street":"Cranbrook St N",
    "iso:country":"CA",
    "sg:address":"2279 Cranbrook St N",
    "sg:city":"Cranbrook",
    "sg:classifiers":[
        {
            "category":"Organizations",
            "subcategory":"Professional Association",
            "type":"Services"
        }
    ],
    "sg:phone":"+1 250 426 5914",
    "sg:postcode":"V1C 3T3",
    "sg:province":"BC",
    "sg:tags":[
        "chambers",
        "commerce"
    ],
    "wof:name":"Chamber of Commerce",
    "wof:placetype":"venue"
},
  "geometry": {"coordinates":[-115.74314099999999,49.53323],"type":"Point"}
}