{
  "type": "Feature",
  "properties": {
    "addr:full":"460 Nadeau St Quesnel BC V2J 2Z7",
    "addr:housenumber":"460",
    "addr:postcode":"v2j 2z7",
    "addr:street":"Nadeau St",
    "iso:country":"CA",
    "sg:address":"460 Nadeau St",
    "sg:city":"Quesnel",
    "sg:classifiers":[
        {
            "category":"Social Services",
            "subcategory":"Child Care",
            "type":"Services"
        }
    ],
    "sg:phone":"+1 250 992 1188",
    "sg:postcode":"V2J 2Z7",
    "sg:province":"BC",
    "wof:name":"Abc 123 Family Daycare",
    "wof:placetype":"venue"
},
  "geometry": {"coordinates":[-122.47601299999999,52.981647],"type":"Point"}
}