{
  "type": "Feature",
  "properties": {
    "addr:full":"4526 Viewmont Ave Victoria BC V8Z 5L2",
    "addr:housenumber":"4526",
    "addr:postcode":"v8z 5l2",
    "addr:street":"Viewmont Ave",
    "iso:country":"CA",
    "sg:address":"4526 Viewmont Ave",
    "sg:city":"Victoria",
    "sg:classifiers":[
        {
            "category":"Wholesale",
            "subcategory":"Auto Parts",
            "type":"Manufacturing & Wholesale Goods"
        }
    ],
    "sg:phone":"+1 250 727 2678",
    "sg:postcode":"V8Z 5L2",
    "sg:province":"BC",
    "sg:tags":[
        "automobile",
        "supply"
    ],
    "wof:name":"Peninsula Restoration Parts",
    "wof:placetype":"venue"
},
  "geometry": {"coordinates":[-123.364517212,48.428314209],"type":"Point"}
}