{
  "type": "Feature",
  "properties": {
    "addr:full":"3000 Boul Matte Brossard QC J4Y 2H5",
    "addr:housenumber":"3000",
    "addr:postcode":"j4y 2h5",
    "addr:street":"Boul Matte",
    "iso:country":"CA",
    "sg:address":"3000 Boul Matte",
    "sg:city":"Brossard",
    "sg:classifiers":[
        {
            "category":"Manufacturing",
            "subcategory":"Glass & Minerals",
            "type":"Manufacturing & Wholesale Goods"
        }
    ],
    "sg:phone":"+1 450 659 9101",
    "sg:postcode":"J4Y 2H5",
    "sg:province":"QC",
    "sg:tags":[
        "fabricator",
        "fiber"
    ],
    "wof:name":"Isolation Manson Inc",
    "wof:placetype":"venue"
},
  "geometry": {"coordinates":[-73.47101600000001,45.432743],"type":"Point"}
}