{
  "type": "Feature",
  "properties": {
    "addr:full":"672 Lorne Ave E Stratford ON N5A 6S5",
    "addr:housenumber":"672",
    "addr:postcode":"n5a 6s5",
    "addr:street":"Lorne Ave E",
    "iso:country":"CA",
    "sg:address":"672 Lorne Ave E",
    "sg:city":"Stratford",
    "sg:classifiers":[
        {
            "category":"Manufacturing",
            "subcategory":"Retail Goods",
            "type":"Manufacturing & Wholesale Goods"
        }
    ],
    "sg:phone":"+1 519 271 3743",
    "sg:postcode":"N5A 6S5",
    "sg:province":"ON",
    "sg:tags":[
        "button",
        "maker",
        "engraver"
    ],
    "wof:name":"Korner Shoppe",
    "wof:placetype":"venue"
},
  "geometry": {"coordinates":[-80.967415,43.352962],"type":"Point"}
}