{
  "type": "Feature",
  "properties": {
    "addr:full":"1 Sulkara Crt North York ON M4A 2G8",
    "addr:housenumber":"1",
    "addr:postcode":"m4a 2g8",
    "addr:street":"Sulkara Crt",
    "iso:country":"CA",
    "sg:address":"1 Sulkara Crt",
    "sg:city":"North York",
    "sg:classifiers":[
        {
            "category":"Professional",
            "subcategory":"Management & Consulting",
            "type":"Services"
        }
    ],
    "sg:phone":"+1 416 755 8280",
    "sg:postcode":"M4A 2G8",
    "sg:province":"ON",
    "sg:tags":[
        "marketing",
        "consultant"
    ],
    "wof:name":"Ascot Marketing Ltd",
    "wof:placetype":"venue"
},
  "geometry": {"coordinates":[-79.3231964111,43.7323455811],"type":"Point"}
}