{
  "type": "Feature",
  "properties": {
    "addr:full":"127 3rd Ave W Hussar AB T0J 1S0",
    "addr:housenumber":"127",
    "addr:postcode":"t0j 1s0",
    "addr:street":"3Rd Ave W Hussar",
    "iso:country":"CA",
    "sg:address":"127 3rd Ave W",
    "sg:city":"Hussar",
    "sg:classifiers":[
        {
            "category":"Insurance",
            "subcategory":"Insurance Agent",
            "type":"Services"
        }
    ],
    "sg:phone":"+1 403 787 3969",
    "sg:postcode":"T0J 1S0",
    "sg:province":"AB",
    "wof:name":"CO-Operators General Insurance",
    "wof:placetype":"venue"
},
  "geometry": {"coordinates":[-112.680908,51.041958],"type":"Point"}
}