{
  "type": "Feature",
  "properties": {
    "iso:country":"CA",
    "sg:address":"3358 Yellowhead Hwy 16",
    "sg:city":"Houston",
    "sg:classifiers":[
        {
            "category":"Autos & Motor Vehicles",
            "subcategory":"Fuel & Gas Station",
            "type":"Retail Goods"
        }
    ],
    "sg:phone":"+1 250 845 2966",
    "sg:postcode":"V0J 1Z0",
    "sg:province":"BC",
    "sg:tags":[
        "oil"
    ],
    "wof:name":"Houston Husky Food Store",
    "wof:placetype":"venue"
},
  "geometry": {"coordinates":[-126.6665802,54.3942489624],"type":"Point"}
}