{
  "type": "Feature",
  "properties": {
    "addr:full":"419 14 Th St E Simcoe ON N3Y 4K3",
    "addr:housenumber":"14",
    "addr:postcode":"n3y 4k3",
    "addr:street":"419;Th St E",
    "iso:country":"CA",
    "sg:address":"419 14 Th St E",
    "sg:city":"Simcoe",
    "sg:classifiers":[
        {
            "category":"Wholesale",
            "subcategory":"Meat",
            "type":"Manufacturing & Wholesale Goods"
        }
    ],
    "sg:phone":"+1 519 426 6750",
    "sg:postcode":"N3Y 4K3",
    "sg:province":"ON",
    "sg:tags":[
        "butchering"
    ],
    "wof:name":"Townsend Butchers",
    "wof:placetype":"venue"
},
  "geometry": {"coordinates":[-80.28940582280001,42.8613815308],"type":"Point"}
}