{
  "type": "Feature",
  "properties": {
    "addr:full":"9344 Plank Rd Straffordville ON N0J 1Y0",
    "addr:housenumber":"9344",
    "addr:postcode":"n0j 1y0",
    "addr:street":"Plank Rd",
    "iso:country":"CA",
    "sg:address":"9344 Plank Rd",
    "sg:city":"Straffordville",
    "sg:classifiers":[
        {
            "category":"Government",
            "subcategory":"Office",
            "type":"Public Place"
        }
    ],
    "sg:phone":"+1 519 866 5521",
    "sg:postcode":"N0J 1Y0",
    "sg:province":"ON",
    "sg:tags":[
        "village"
    ],
    "wof:name":"Bayham Municipal Office",
    "wof:placetype":"venue"
},
  "geometry": {"coordinates":[-80.776489,42.75008],"type":"Point"}
}