{
  "type": "Feature",
  "properties": {
    "addr:full":"150 King St E Toronto ON M5A 1J3",
    "addr:housenumber":"150",
    "addr:postcode":"m5a 1j3",
    "addr:street":"King St E",
    "iso:country":"CA",
    "sg:address":"150 King St E",
    "sg:city":"Toronto",
    "sg:classifiers":[
        {
            "category":"Shopping",
            "subcategory":"Gifts & Souvenirs",
            "type":"Retail Goods"
        }
    ],
    "sg:phone":"+1 416 363 5454",
    "sg:postcode":"M5A 1J3",
    "sg:province":"ON",
    "sg:tags":[
        "shop"
    ],
    "wof:name":"Elle Maison",
    "wof:placetype":"venue"
},
  "geometry": {"coordinates":[-79.37177276609999,43.6505775452],"type":"Point"}
}