{
  "type": "Feature",
  "properties": {
    "addr:full":"995 Onondaga St Oromocto NB E2V 1B8",
    "addr:housenumber":"995",
    "addr:postcode":"e2v 1b8",
    "addr:street":"Onondaga St",
    "iso:country":"CA",
    "sg:address":"995 Onondaga St",
    "sg:city":"Oromocto",
    "sg:classifiers":[
        {
            "category":"Retail",
            "subcategory":"Auto Repair",
            "type":"Services"
        }
    ],
    "sg:phone":"+1 506 357 0828",
    "sg:postcode":"E2V 1B8",
    "sg:province":"NB",
    "sg:tags":[
        "repairing",
        "automobile"
    ],
    "wof:name":"Warren Developments",
    "wof:placetype":"venue"
},
  "geometry": {"coordinates":[-66.47756200000001,45.851406],"type":"Point"}
}