{
  "type": "Feature",
  "properties": {
    "addr:full":"21 Reddin Hts Stratford PE C1B 1Z3",
    "addr:housenumber":"21",
    "addr:postcode":"c1b 1z3",
    "addr:street":"Reddin Hts",
    "iso:country":"CA",
    "sg:address":"21 Reddin Hts",
    "sg:city":"Stratford",
    "sg:classifiers":[
        {
            "category":"Retail",
            "subcategory":"Laundry & Dry Cleaning",
            "type":"Services"
        }
    ],
    "sg:phone":"+1 902 569 3515",
    "sg:postcode":"C1B 1Z3",
    "sg:province":"PE",
    "sg:tags":[
        "ventilating",
        "cleaners",
        "carpet",
        "rug",
        "system"
    ],
    "wof:name":"Drake Clean Up Systems",
    "wof:placetype":"venue"
},
  "geometry": {"coordinates":[-63.098431,46.220852],"type":"Point"}
}