{
  "type": "Feature",
  "properties": {
    "addr:full":"3946 Bishopstoke Lane Mississauga ON L4Z 1J2",
    "addr:housenumber":"3946",
    "addr:postcode":"l4z 1j2",
    "addr:street":"Bishopstoke Lane",
    "iso:country":"CA",
    "sg:address":"3946 Bishopstoke Lane",
    "sg:city":"Mississauga",
    "sg:classifiers":[
        {
            "category":"Professional",
            "subcategory":"Engineering",
            "type":"Services"
        }
    ],
    "sg:phone":"+1 905 896 4274",
    "sg:postcode":"L4Z 1J2",
    "sg:province":"ON",
    "sg:tags":[
        "engineer"
    ],
    "wof:name":"Pharaohs Engineering Ltd",
    "wof:placetype":"venue"
},
  "geometry": {"coordinates":[-79.629822,43.599072],"type":"Point"}
}