{
  "type": "Feature",
  "properties": {
    "addr:full":"Meadow Creek Rd Meadow Creek BC V0G 1N0",
    "addr:postcode":"v0g 1n0",
    "addr:street":"Meadow Creek Rd Meadow",
    "iso:country":"CA",
    "sg:address":"Meadow Creek Rd",
    "sg:city":"Meadow Creek",
    "sg:classifiers":[
        {
            "category":"Home & Garden",
            "subcategory":"Building Materials",
            "type":"Retail Goods"
        }
    ],
    "sg:phone":"+1 250 366 4605",
    "sg:postcode":"V0G 1N0",
    "sg:province":"BC",
    "sg:tags":[
        "lumber"
    ],
    "wof:name":"Meadow Creek Cedar Ltd",
    "wof:placetype":"venue"
},
  "geometry": {"coordinates":[-116.960182,50.196888],"type":"Point"}
}