{
  "type": "Feature",
  "properties": {
    "addr:full":"64 Steadman St Moncton NB E1C 4P4",
    "addr:housenumber":"64",
    "addr:postcode":"e1c 4p4",
    "addr:street":"Steadman St",
    "iso:country":"CA",
    "sg:address":"64 Steadman St",
    "sg:city":"Moncton",
    "sg:classifiers":[
        {
            "category":"Health Services",
            "subcategory":"Nursing And Care Facility",
            "type":"Services"
        }
    ],
    "sg:phone":"+1 506 388 2666",
    "sg:postcode":"E1C 4P4",
    "sg:province":"NB",
    "sg:tags":[
        "home",
        "rest"
    ],
    "wof:name":"Residence Collette Residence",
    "wof:placetype":"venue"
},
  "geometry": {"coordinates":[-64.773117,46.092045],"type":"Point"}
}