{
  "type": "Feature",
  "properties": {
    "addr:full":"710 High St W Moose Jaw SK S6H 1T8",
    "addr:housenumber":"710",
    "addr:postcode":"s6h 1t8",
    "addr:street":"High St W",
    "iso:country":"CA",
    "sg:address":"710 High St W",
    "sg:city":"Moose Jaw",
    "sg:classifiers":[
        {
            "category":"Manufacturing",
            "subcategory":"Printing",
            "type":"Manufacturing & Wholesale Goods"
        }
    ],
    "sg:phone":"+1 306 692 2921",
    "sg:postcode":"S6H 1T8",
    "sg:province":"SK",
    "sg:tags":[
        "printer"
    ],
    "wof:name":"Quick Printing",
    "wof:placetype":"venue"
},
  "geometry": {"coordinates":[-105.55220799999999,50.391781],"type":"Point"}
}