{
  "type": "Feature",
  "properties": {
    "addr:full":"55 Arena Rd Ste Anne MB R5H 1G6",
    "addr:housenumber":"55",
    "addr:postcode":"r5h 1g6",
    "addr:street":"Arena Rd",
    "iso:country":"CA",
    "sg:address":"55 Arena Rd",
    "sg:city":"Ste Anne",
    "sg:classifiers":[
        {
            "category":"Recreation",
            "type":"Entertainment"
        }
    ],
    "sg:phone":"+1 204 422 5990",
    "sg:postcode":"R5H 1G6",
    "sg:province":"MB",
    "sg:tags":[
        "club",
        "curling"
    ],
    "wof:name":"Ste Anne Curling Club",
    "wof:placetype":"venue"
},
  "geometry": {"coordinates":[-96.6524276733,49.6711997986],"type":"Point"}
}