{
  "type": "Feature",
  "properties": {
    "addr:full":"105 Rue Principale Saint-Michel-DE-Bellechasse QC G0R 3S0",
    "addr:housenumber":"105",
    "addr:postcode":"g0r 3s0",
    "addr:street":"Rue Principale",
    "iso:country":"CA",
    "sg:address":"105 Rue Principale",
    "sg:city":"Saint-Michel-DE-Bellechasse",
    "sg:classifiers":[
        {
            "category":"Organizations",
            "subcategory":"Religious Organization",
            "type":"Services"
        }
    ],
    "sg:phone":"+1 418 884 2333",
    "sg:postcode":"G0R 3S0",
    "sg:province":"QC",
    "sg:tags":[
        "church"
    ],
    "wof:name":"Presbytere DE St-Michel",
    "wof:placetype":"venue"
},
  "geometry": {"coordinates":[-70.90803527830001,46.8759269714],"type":"Point"}
}