{
  "type": "Feature",
  "properties": {
    "addr:full":"11499 79 Ave Delta BC V4C 1S9",
    "addr:housenumber":"11499",
    "addr:postcode":"v4c 1s9",
    "addr:street":"79 Ave",
    "iso:country":"CA",
    "sg:address":"11499 79 Ave",
    "sg:city":"Delta",
    "sg:classifiers":[
        {
            "category":"Building & Trades",
            "subcategory":"Plumbing",
            "type":"Services"
        }
    ],
    "sg:phone":"+1 604 594 7828",
    "sg:postcode":"V4C 1S9",
    "sg:province":"BC",
    "sg:tags":[
        "heating",
        "contractor"
    ],
    "wof:name":"Arai Mechanical Svc Ltd",
    "wof:placetype":"venue"
},
  "geometry": {"coordinates":[-122.904312,49.147194],"type":"Point"}
}