{
  "type": "Feature",
  "properties": {
    "iso:country":"CA",
    "sg:address":"1611 Bank St # 3",
    "sg:city":"Ottawa",
    "sg:classifiers":[
        {
            "category":"Restaurant",
            "type":"Food & Drink"
        }
    ],
    "sg:phone":"+1 613 523 7482",
    "sg:postcode":"K1V 7Y8",
    "sg:province":"ON",
    "wof:name":"Extreme Pita",
    "wof:placetype":"venue"
},
  "geometry": {"coordinates":[-75.667061,45.378094],"type":"Point"}
}