{
  "type": "Feature",
  "properties": {
    "addr:full":"533 Rue Dufferin Granby QC J2G 9G3",
    "addr:housenumber":"533",
    "addr:postcode":"j2g 9g3",
    "addr:street":"Rue Dufferin",
    "iso:country":"CA",
    "sg:address":"533 Rue Dufferin",
    "sg:city":"Granby",
    "sg:classifiers":[
        {
            "category":"Wholesale",
            "subcategory":"Machinery & Supplies",
            "type":"Manufacturing & Wholesale Goods"
        }
    ],
    "sg:phone":"+1 450 375 9183",
    "sg:postcode":"J2G 9G3",
    "sg:province":"QC",
    "sg:tags":[
        "food",
        "equipment",
        "processing",
        "maple"
    ],
    "wof:name":"Equipements D'Erabiliere",
    "wof:placetype":"venue"
},
  "geometry": {"coordinates":[-72.71669,45.42038],"type":"Point"}
}