{
  "type": "Feature",
  "properties": {
    "iso:country":"CA",
    "sg:city":"Burnaby",
    "sg:classifiers":[
        {
            "category":"Insurance",
            "subcategory":"Insurance Agent",
            "type":"Services"
        }
    ],
    "sg:phone":"+1 604 421 2422",
    "sg:postcode":"V3J 1N4",
    "sg:province":"BC",
    "wof:name":"Johnston Meier Insurance",
    "wof:placetype":"venue"
},
  "geometry": {"coordinates":[-122.895767,49.249142],"type":"Point"}
}