{
  "type": "Feature",
  "properties": {
    "addr:full":"120 N Mayor Magrath Dr Lethbridge AB T1H 3P4",
    "addr:housenumber":"120",
    "addr:postcode":"t1h 3p4",
    "addr:street":"N Mayor Magrath Dr",
    "iso:country":"CA",
    "sg:address":"120 N Mayor Magrath Dr",
    "sg:city":"Lethbridge",
    "sg:classifiers":[
        {
            "category":"Retail",
            "subcategory":"Repair Shop",
            "type":"Services"
        }
    ],
    "sg:phone":"+1 403 320 7375",
    "sg:postcode":"T1H 3P4",
    "sg:province":"AB",
    "sg:tags":[
        "upholsterer"
    ],
    "wof:name":"Kennedy's Upholstery",
    "wof:placetype":"venue"
},
  "geometry": {"coordinates":[-112.81171417199999,49.6998214722],"type":"Point"}
}