{
  "type": "Feature",
  "properties": {
    "addr:full":"49 John St Chesterville ON K0C 1H0",
    "addr:housenumber":"49",
    "addr:postcode":"k0c 1h0",
    "addr:street":"John St",
    "iso:country":"CA",
    "sg:address":"49 John St",
    "sg:city":"Chesterville",
    "sg:classifiers":[
        {
            "category":"Recreation",
            "type":"Entertainment"
        }
    ],
    "sg:phone":"+1 613 448 1233",
    "sg:postcode":"K0C 1H0",
    "sg:province":"ON",
    "sg:tags":[
        "martial",
        "arts",
        "instruction"
    ],
    "wof:name":"Therien Jiu Jitsu",
    "wof:placetype":"venue"
},
  "geometry": {"coordinates":[-75.23406199999999,45.105324],"type":"Point"}
}