{
  "type": "Feature",
  "properties": {
    "iso:country":"CA",
    "sg:address":"8957 Boul Henri-Bourassa O",
    "sg:city":"Saint-Laurent",
    "sg:classifiers":[
        {
            "category":"Home & Garden",
            "subcategory":"Furniture",
            "type":"Retail Goods"
        }
    ],
    "sg:phone":"+1 514 332 2365",
    "sg:postcode":"H4S 1P7",
    "sg:province":"QC",
    "sg:tags":[
        "builder",
        "custom"
    ],
    "wof:name":"Meubles Traditionnels",
    "wof:placetype":"venue"
},
  "geometry": {"coordinates":[-73.7463684082,45.5014610291],"type":"Point"}
}