{
  "type": "Feature",
  "properties": {
    "addr:full":"26 Cook Rd SE Medicine Hat AB T1B 1K1",
    "addr:housenumber":"26",
    "addr:postcode":"t1b 1k1",
    "addr:street":"Cook Rd Se",
    "iso:country":"CA",
    "sg:address":"26 Cook Rd SE",
    "sg:city":"Medicine Hat",
    "sg:classifiers":[
        {
            "category":"Mining & Drilling",
            "type":"Manufacturing & Wholesale Goods"
        }
    ],
    "sg:phone":"+1 403 526 2430",
    "sg:postcode":"T1B 1K1",
    "sg:province":"AB",
    "sg:tags":[
        "field",
        "oil"
    ],
    "wof:name":"Ingram Power Tongs",
    "wof:placetype":"venue"
},
  "geometry": {"coordinates":[-110.647514,50.011768],"type":"Point"}
}