{
  "type": "Feature",
  "properties": {
    "iso:country":"CA",
    "sg:address":"43 Industrial Lane",
    "sg:city":"Weyburn",
    "sg:classifiers":[
        {
            "category":"Home & Garden",
            "subcategory":"Garden Supply",
            "type":"Retail Goods"
        }
    ],
    "sg:phone":"+1 306 842 1777",
    "sg:postcode":"S4H 0M5",
    "sg:province":"SK",
    "sg:tags":[
        "nurseryman"
    ],
    "wof:name":"Rose Gardens Nursery",
    "wof:placetype":"venue"
},
  "geometry": {"coordinates":[-103.840675354,49.6393280029],"type":"Point"}
}