{
  "type": "Feature",
  "properties": {
    "addr:full":"5010 50 Ave Leduc AB T9E 6T3",
    "addr:housenumber":"5010",
    "addr:postcode":"t9e 6t3",
    "addr:street":"50 Ave",
    "iso:country":"CA",
    "sg:address":"5010 50 Ave",
    "sg:city":"Leduc",
    "sg:classifiers":[
        {
            "category":"Manufacturing",
            "subcategory":"Printing",
            "type":"Manufacturing & Wholesale Goods"
        }
    ],
    "sg:phone":"+1 780 986 0235",
    "sg:postcode":"T9E 6T3",
    "sg:province":"AB",
    "sg:tags":[
        "printer"
    ],
    "wof:name":"Suburban Printing & Stationery",
    "wof:placetype":"venue"
},
  "geometry": {"coordinates":[-113.553032,53.264927],"type":"Point"}
}