{
  "type": "Feature",
  "properties": {
    "addr:full":"1063 Rang Saint-Pierre Herouxville QC G0X 1J0",
    "addr:housenumber":"1063",
    "addr:postcode":"g0x 1j0",
    "addr:street":"Rang Saint-Pierre Herouxville",
    "iso:country":"CA",
    "sg:address":"1063 Rang Saint-Pierre",
    "sg:city":"Herouxville",
    "sg:classifiers":[
        {
            "category":"Personal",
            "subcategory":"Beauty Salon",
            "type":"Services"
        }
    ],
    "sg:phone":"+1 418 365 7035",
    "sg:postcode":"G0X 1J0",
    "sg:province":"QC",
    "wof:name":"Salon DE Coiffure Johanne Cyr",
    "wof:placetype":"venue"
},
  "geometry": {"coordinates":[-72.6120834351,46.6731643677],"type":"Point"}
}