{
  "type": "Feature",
  "properties": {
    "addr:full":"11120 234A St Maple Ridge BC V2W 1C8",
    "addr:housenumber":"11120",
    "addr:postcode":"v2w 1c8",
    "addr:street":"234A St",
    "iso:country":"CA",
    "sg:address":"11120 234A St",
    "sg:city":"Maple Ridge",
    "sg:classifiers":[
        {
            "category":"Education",
            "subcategory":"School",
            "type":"Public Place"
        }
    ],
    "sg:phone":"+1 604 467 9050",
    "sg:postcode":"V2W 1C8",
    "sg:province":"BC",
    "wof:name":"Kanaka Creek Elementary School",
    "wof:placetype":"venue"
},
  "geometry": {"coordinates":[-122.60582700000001,49.216846],"type":"Point"}
}