{
  "type": "Feature",
  "properties": {
    "iso:country":"CA",
    "sg:address":"371 Main St",
    "sg:city":"Selkirk",
    "sg:classifiers":[
        {
            "category":"Restaurant",
            "type":"Food & Drink"
        }
    ],
    "sg:phone":"+1 204 482 1231",
    "sg:postcode":"R1A 1T7",
    "sg:province":"MB",
    "wof:name":"Paul's Chinese Restaurant",
    "wof:placetype":"venue"
},
  "geometry": {"coordinates":[-96.87456512449999,50.1439247131],"type":"Point"}
}