{
  "type": "Feature",
  "properties": {
    "iso:country":"CA",
    "sg:address":"939 Main St",
    "sg:city":"Moncton",
    "sg:classifiers":[
        {
            "category":"Manufacturing",
            "subcategory":"Printing",
            "type":"Manufacturing & Wholesale Goods"
        }
    ],
    "sg:phone":"+1 506 859 4900",
    "sg:postcode":"E1C 1G8",
    "sg:province":"NB",
    "sg:tags":[
        "newspaper"
    ],
    "wof:name":"Times-Transcript",
    "wof:placetype":"venue"
},
  "geometry": {"coordinates":[-64.7819442749,46.0875053406],"type":"Point"}
}