{
  "type": "Feature",
  "properties": {
    "addr:full":"309 Hidden Valley Pl NW Calgary AB T3A 5L7",
    "addr:housenumber":"309",
    "addr:postcode":"t3a 5l7",
    "addr:street":"Hidden Valley Pl Nw",
    "iso:country":"CA",
    "sg:address":"309 Hidden Valley Pl NW",
    "sg:city":"Calgary",
    "sg:classifiers":[
        {
            "category":"Building & Trades",
            "subcategory":"Construction",
            "type":"Services"
        }
    ],
    "sg:phone":"+1 403 730 8262",
    "sg:postcode":"T3A 5L7",
    "sg:province":"AB",
    "sg:tags":[
        "repairing",
        "remodeling",
        "contractor"
    ],
    "wof:name":"Regent Construction Svc",
    "wof:placetype":"venue"
},
  "geometry": {"coordinates":[-114.096153,51.145454],"type":"Point"}
}