{
  "type": "Feature",
  "properties": {
    "addr:full":"756 Yonge St Midland ON L4R 2E5",
    "addr:housenumber":"756",
    "addr:postcode":"l4r 2e5",
    "addr:street":"Yonge St",
    "iso:country":"CA",
    "sg:address":"756 Yonge St",
    "sg:city":"Midland",
    "sg:classifiers":[
        {
            "category":"Food & Beverages",
            "subcategory":"Candy",
            "type":"Retail Goods"
        }
    ],
    "sg:phone":"+1 705 528 0552",
    "sg:postcode":"L4R 2E5",
    "sg:province":"ON",
    "sg:tags":[
        "confectionery"
    ],
    "wof:name":"Googalee's",
    "wof:placetype":"venue"
},
  "geometry": {"coordinates":[-79.89347839360001,44.7425956726],"type":"Point"}
}