{
  "type": "Feature",
  "properties": {
    "iso:country":"CA",
    "sg:address":"301 Rue Bostonnais",
    "sg:city":"LA Tuque",
    "sg:classifiers":[
        {
            "category":"Food & Beverages",
            "subcategory":"Groceries & Convenience Stores",
            "type":"Retail Goods"
        }
    ],
    "sg:phone":"+1 819 523 4416",
    "sg:postcode":"G9X 2G4",
    "sg:province":"QC",
    "wof:name":"Depanneur Paul & Pauline Inc",
    "wof:placetype":"venue"
},
  "geometry": {"coordinates":[-72.775718689,47.4477462769],"type":"Point"}
}