{
  "type": "Feature",
  "properties": {
    "iso:country":"CA",
    "sg:address":"726 45th St W",
    "sg:city":"Saskatoon",
    "sg:classifiers":[
        {
            "category":"Manufacturing",
            "subcategory":"Apparel",
            "type":"Manufacturing & Wholesale Goods"
        }
    ],
    "sg:phone":"+1 306 665 5333",
    "sg:postcode":"S7L 5X1",
    "sg:province":"SK",
    "sg:tags":[
        "flag",
        "advertising"
    ],
    "wof:name":"Bazaar & Novelty Western",
    "wof:placetype":"venue"
},
  "geometry": {"coordinates":[-106.67844390899999,52.1640625],"type":"Point"}
}