{
  "type": "Feature",
  "properties": {
    "addr:full":"1410 Lonsdale Ave North Vancouver BC V7M 2J1",
    "addr:housenumber":"1410",
    "addr:postcode":"v7m 2j1",
    "addr:street":"Lonsdale Ave",
    "iso:country":"CA",
    "sg:address":"1410 Lonsdale Ave",
    "sg:city":"North Vancouver",
    "sg:classifiers":[
        {
            "category":"Travel",
            "subcategory":"Travel Agent",
            "type":"Entertainment"
        }
    ],
    "sg:phone":"+1 604 982 0909",
    "sg:postcode":"V7M 2J1",
    "sg:province":"BC",
    "sg:tags":[
        "agency",
        "bureau"
    ],
    "wof:name":"Pars Tours Inc",
    "wof:placetype":"venue"
},
  "geometry": {"coordinates":[-123.072143555,49.3212280273],"type":"Point"}
}