{
  "type": "Feature",
  "properties": {
    "addr:full":"5761 Av Caldwell Cote Saint-Luc QC H4W 1W1",
    "addr:housenumber":"5761",
    "addr:postcode":"h4w 1w1",
    "addr:street":"Av Caldwell Cote",
    "iso:country":"CA",
    "sg:address":"5761 Av Caldwell",
    "sg:city":"Cote Saint-Luc",
    "sg:classifiers":[
        {
            "category":"Retail",
            "subcategory":"Laundry & Dry Cleaning",
            "type":"Services"
        }
    ],
    "sg:phone":"+1 514 482 8844",
    "sg:postcode":"H4W 1W1",
    "sg:province":"QC",
    "sg:tags":[
        "cleaners"
    ],
    "wof:name":"Nettoyeur Caldwell",
    "wof:placetype":"venue"
},
  "geometry": {"coordinates":[-73.66815200000001,45.470966],"type":"Point"}
}