{
  "type": "Feature",
  "properties": {
    "addr:full":"169 Eastern Ave Toronto ON M5A 1H7",
    "addr:housenumber":"169",
    "addr:postcode":"m5a 1h7",
    "addr:street":"Eastern Ave",
    "iso:country":"CA",
    "sg:address":"169 Eastern Ave",
    "sg:city":"Toronto",
    "sg:classifiers":[
        {
            "category":"Shopping",
            "subcategory":"Computers & Home Electronics",
            "type":"Retail Goods"
        }
    ],
    "sg:phone":"+1 416 955 0171",
    "sg:postcode":"M5A 1H7",
    "sg:province":"ON",
    "sg:tags":[
        "equipment",
        "dealer"
    ],
    "wof:name":"Learning Support Council",
    "wof:placetype":"venue"
},
  "geometry": {"coordinates":[-79.355408,43.654568],"type":"Point"}
}