{
  "type": "Feature",
  "properties": {
    "addr:full":"99 North Port Rd Port Perry ON L9L 1B2",
    "addr:housenumber":"99",
    "addr:postcode":"l9l 1b2",
    "addr:street":"North Port Rd",
    "iso:country":"CA",
    "sg:address":"99 North Port Rd",
    "sg:city":"Port Perry",
    "sg:classifiers":[
        {
            "category":"Building & Trades",
            "subcategory":"Construction",
            "type":"Services"
        }
    ],
    "sg:phone":"+1 905 728 4887",
    "sg:postcode":"L9L 1B2",
    "sg:province":"ON",
    "sg:tags":[
        "product",
        "asphalt"
    ],
    "wof:name":"Matrex CO",
    "wof:placetype":"venue"
},
  "geometry": {"coordinates":[-78.976067,44.103203],"type":"Point"}
}