{
  "type": "Feature",
  "properties": {
    "addr:full":"Vancouver BC V6P 6G2",
    "addr:postcode":"v6p 6g2",
    "iso:country":"CA",
    "sg:city":"Vancouver",
    "sg:classifiers":[
        {
            "category":"Building & Trades",
            "subcategory":"Construction",
            "type":"Services"
        }
    ],
    "sg:phone":"+1 604 266 4700",
    "sg:postcode":"V6P 6G2",
    "sg:province":"BC",
    "sg:tags":[
        "maker",
        "cabinet"
    ],
    "wof:name":"Benson Industries Ltd",
    "wof:placetype":"venue"
},
  "geometry": {"coordinates":[-123.148026,49.206692],"type":"Point"}
}