{
  "type": "Feature",
  "properties": {
    "addr:full":"3904 Puntzi Lake Rd Chilanko Forks BC V0L 1H0",
    "addr:housenumber":"3904",
    "addr:postcode":"v0l 1h0",
    "addr:street":"Puntzi Lake Rd",
    "iso:country":"CA",
    "sg:address":"3904 Puntzi Lake Rd",
    "sg:city":"Chilanko Forks",
    "sg:classifiers":[
        {
            "category":"Travel",
            "subcategory":"Hotels & Motels",
            "type":"Entertainment"
        }
    ],
    "sg:phone":"+1 250 481 1130",
    "sg:postcode":"V0L 1H0",
    "sg:province":"BC",
    "sg:tags":[
        "resort"
    ],
    "wof:name":"Kokanee Bay Fishing Resort",
    "wof:placetype":"venue"
},
  "geometry": {"coordinates":[-124.066864,52.111736],"type":"Point"}
}