{
  "type": "Feature",
  "properties": {
    "addr:full":"Richmond BC V6V 1Z5",
    "addr:postcode":"v6v 1z5",
    "iso:country":"CA",
    "sg:city":"Richmond",
    "sg:classifiers":[
        {
            "category":"Professional",
            "subcategory":"Detective & Security Services",
            "type":"Services"
        }
    ],
    "sg:phone":"+1 604 303 9086",
    "sg:postcode":"V6V 1Z5",
    "sg:province":"BC",
    "sg:tags":[
        "system"
    ],
    "wof:name":"Ho King Renovation Ltd",
    "wof:placetype":"venue"
},
  "geometry": {"coordinates":[-123.08482360799999,49.1955108643],"type":"Point"}
}