{
  "type": "Feature",
  "properties": {
    "iso:country":"CA",
    "sg:city":"Edmonton",
    "sg:classifiers":[
        {
            "category":"Personal",
            "subcategory":"Beauty Salon",
            "type":"Services"
        }
    ],
    "sg:phone":"+1 780 454 9049",
    "sg:postcode":"T5M 3L7",
    "sg:province":"AB",
    "wof:name":"Passion Hair",
    "wof:placetype":"venue"
},
  "geometry": {"coordinates":[-113.490372,53.546219],"type":"Point"}
}