{
  "type": "Feature",
  "properties": {
    "addr:full":"2171 Ocean Westway Saint John NB E2M 5H6",
    "addr:housenumber":"2171",
    "addr:postcode":"e2m 5h6",
    "addr:street":"Ocean Westway",
    "iso:country":"CA",
    "sg:address":"2171 Ocean Westway",
    "sg:city":"Saint John",
    "sg:classifiers":[
        {
            "category":"Restaurant",
            "type":"Food & Drink"
        }
    ],
    "sg:phone":"+1 506 672 6090",
    "sg:postcode":"E2M 5H6",
    "sg:province":"NB",
    "wof:name":"Leo's Supper Club",
    "wof:placetype":"venue"
},
  "geometry": {"coordinates":[-66.1556625366,45.2304954529],"type":"Point"}
}