{
  "type": "Feature",
  "properties": {
    "addr:full":"194 Rue DE Martigny O Saint-Jerome QC J7Y 2G3",
    "addr:housenumber":"194",
    "addr:postcode":"j7y 2g3",
    "addr:street":"Rue De Martigny O Saint-Jerome",
    "iso:country":"CA",
    "sg:address":"194 Rue DE Martigny O",
    "sg:city":"Saint-Jerome",
    "sg:classifiers":[
        {
            "category":"Retail",
            "subcategory":"Veterinary Services",
            "type":"Services"
        }
    ],
    "sg:phone":"+1 450 438 6091",
    "sg:postcode":"J7Y 2G3",
    "sg:province":"QC",
    "sg:tags":[
        "veterinarian"
    ],
    "wof:name":"Cote, Marie F DVM",
    "wof:placetype":"venue"
},
  "geometry": {"coordinates":[-74.013588,45.779827],"type":"Point"}
}