{
  "type": "Feature",
  "properties": {
    "addr:full":"1881 Broad St Regina SK S4P 1X7",
    "addr:housenumber":"1881",
    "addr:postcode":"s4p 1x7",
    "addr:street":"Broad St",
    "iso:country":"CA",
    "sg:address":"1881 Broad St",
    "sg:city":"Regina",
    "sg:classifiers":[
        {
            "category":"Food & Beverages",
            "subcategory":"Liquor & Beverages",
            "type":"Retail Goods"
        }
    ],
    "sg:phone":"+1 306 787 4246",
    "sg:postcode":"S4P 1X7",
    "sg:province":"SK",
    "sg:tags":[
        "government"
    ],
    "wof:name":"Liquor Stores",
    "wof:placetype":"venue"
},
  "geometry": {"coordinates":[-104.606216,50.449219],"type":"Point"}
}