{
  "type": "Feature",
  "properties": {
    "iso:country":"CA",
    "sg:address":"657 Goderich St",
    "sg:city":"Port Elgin",
    "sg:classifiers":[
        {
            "category":"Restaurant",
            "type":"Food & Drink"
        }
    ],
    "sg:phone":"+1 519 389 2288",
    "sg:postcode":"N0H 2C0",
    "sg:province":"ON",
    "wof:name":"J C's Diner",
    "wof:placetype":"venue"
},
  "geometry": {"coordinates":[-81.3879852295,44.4370574951],"type":"Point"}
}