{
  "type": "Feature",
  "properties": {
    "addr:full":"567 Rue Iberville Beloeil QC J3G 2N7",
    "addr:housenumber":"567",
    "addr:postcode":"j3g 2n7",
    "addr:street":"Rue Iberville",
    "iso:country":"CA",
    "sg:address":"567 Rue Iberville",
    "sg:city":"Beloeil",
    "sg:classifiers":[
        {
            "category":"Organizations",
            "subcategory":"Religious Organization",
            "type":"Services"
        }
    ],
    "sg:phone":"+1 450 467 6831",
    "sg:postcode":"J3G 2N7",
    "sg:province":"QC",
    "sg:tags":[
        "church"
    ],
    "wof:name":"Groupe Biblique Du Richelieu",
    "wof:placetype":"venue"
},
  "geometry": {"coordinates":[-73.21159400000001,45.569656],"type":"Point"}
}