{
  "type": "Feature",
  "properties": {
    "addr:full":"1875 Rue Gutenberg Laval QC H7S 1A1",
    "addr:housenumber":"1875",
    "addr:postcode":"h7s 1a1",
    "addr:street":"Rue Gutenberg",
    "iso:country":"CA",
    "sg:address":"1875 Rue Gutenberg",
    "sg:city":"Laval",
    "sg:classifiers":[
        {
            "category":"Building & Trades",
            "subcategory":"Construction",
            "type":"Services"
        }
    ],
    "sg:phone":"+1 450 681 7000",
    "sg:postcode":"H7S 1A1",
    "sg:province":"QC",
    "sg:tags":[
        "general",
        "contractor"
    ],
    "wof:name":"Quadrax Construction Inc",
    "wof:placetype":"venue"
},
  "geometry": {"coordinates":[-73.745148,45.572739],"type":"Point"}
}