{
  "type": "Feature",
  "properties": {
    "iso:country":"CA",
    "sg:city":"Waterloo",
    "sg:classifiers":[
        {
            "category":"Retail",
            "subcategory":"Veterinary Services",
            "type":"Services"
        }
    ],
    "sg:phone":"+1 519 664 3707",
    "sg:postcode":"N2J 4G8",
    "sg:province":"ON",
    "sg:tags":[
        "veterinarian"
    ],
    "wof:name":"Conestoga Veterinary Clinic",
    "wof:placetype":"venue"
},
  "geometry": {"coordinates":[-80.520691,43.463139],"type":"Point"}
}