{
  "type": "Feature",
  "properties": {
    "addr:full":"411 6th Ave Midway BC V0H 1M0",
    "addr:housenumber":"411",
    "addr:postcode":"v0h 1m0",
    "addr:street":"6Th Ave",
    "iso:country":"CA",
    "sg:address":"411 6th Ave",
    "sg:city":"Midway",
    "sg:classifiers":[
        {
            "category":"Health Services",
            "subcategory":"Chiropractor",
            "type":"Services"
        }
    ],
    "sg:phone":"+1 250 449 2450",
    "sg:postcode":"V0H 1M0",
    "sg:province":"BC",
    "wof:name":"Kettle Valley Chiropractic",
    "wof:placetype":"venue"
},
  "geometry": {"coordinates":[-118.775268555,49.0066413879],"type":"Point"}
}