{
  "type": "Feature",
  "properties": {
    "iso:country":"CA",
    "sg:address":"3057 Pharmacy Ave",
    "sg:city":"Scarborough",
    "sg:classifiers":[
        {
            "category":"Retail",
            "subcategory":"Laundry & Dry Cleaning",
            "type":"Services"
        }
    ],
    "sg:phone":"+1 416 492 3848",
    "sg:postcode":"M1W 2H1",
    "sg:province":"ON",
    "sg:tags":[
        "cleaners"
    ],
    "wof:name":"London Cleaners",
    "wof:placetype":"venue"
},
  "geometry": {"coordinates":[-79.326546,43.795483],"type":"Point"}
}