{
  "type": "Feature",
  "properties": {
    "addr:full":"83 Captain Francis Dr Markham ON L3R 9E5",
    "addr:housenumber":"83",
    "addr:postcode":"l3r 9e5",
    "addr:street":"Captain Francis Dr",
    "iso:country":"CA",
    "sg:address":"83 Captain Francis Dr",
    "sg:city":"Markham",
    "sg:classifiers":[
        {
            "category":"Wholesale",
            "subcategory":"Office Equipment",
            "type":"Manufacturing & Wholesale Goods"
        }
    ],
    "sg:phone":"+1 905 940 7377",
    "sg:postcode":"L3R 9E5",
    "sg:province":"ON",
    "sg:tags":[
        "machine",
        "duplicating",
        "copying"
    ],
    "wof:name":"Just Right",
    "wof:placetype":"venue"
},
  "geometry": {"coordinates":[-79.3585357666,43.8673362732],"type":"Point"}
}