{
  "type": "Feature",
  "properties": {
    "addr:full":"4235 Breen Rd Putnam ON N0L 2B0",
    "addr:housenumber":"4235",
    "addr:postcode":"n0l 2b0",
    "addr:street":"Breen Rd",
    "iso:country":"CA",
    "sg:address":"4235 Breen Rd",
    "sg:city":"Putnam",
    "sg:classifiers":[
        {
            "category":"Freight",
            "type":"Transportation"
        }
    ],
    "sg:phone":"+1 519 485 3034",
    "sg:postcode":"N0L 2B0",
    "sg:province":"ON",
    "sg:tags":[
        "trucking"
    ],
    "wof:name":"Mike Nesbitt Trucking Inc",
    "wof:placetype":"venue"
},
  "geometry": {"coordinates":[-80.94869199999999,42.98222],"type":"Point"}
}