{
  "type": "Feature",
  "properties": {
    "addr:full":"600 Av DE LA Sorbonne Laval QC H7G 4R5",
    "addr:housenumber":"600",
    "addr:postcode":"qc h7g 4r5",
    "addr:street":"Av De La Sorbonne",
    "iso:country":"CA",
    "sg:address":"600 Av DE LA Sorbonne",
    "sg:city":"Laval",
    "sg:classifiers":[
        {
            "category":"Social Services",
            "type":"Services"
        }
    ],
    "sg:phone":"+1 450 663 1477",
    "sg:postcode":"H7G 4R5",
    "sg:province":"QC",
    "sg:tags":[
        "info",
        "drug",
        "abuse",
        "treatment",
        "welfare",
        "organization",
        "addiction"
    ],
    "wof:name":"Alliance Caat Desintox",
    "wof:placetype":"venue"
},
  "geometry": {"coordinates":[-73.687431,45.579559],"type":"Point"}
}