{
  "type": "Feature",
  "properties": {
    "addr:full":"4114 Macleod Trail SE Calgary AB T2G 2R7",
    "addr:housenumber":"4114",
    "addr:postcode":"t2g 2r7",
    "addr:street":"Macleod Trail Se",
    "iso:country":"CA",
    "sg:address":"4114 Macleod Trail SE",
    "sg:city":"Calgary",
    "sg:classifiers":[
        {
            "category":"Food & Beverages",
            "subcategory":"Liquor & Beverages",
            "type":"Retail Goods"
        }
    ],
    "sg:phone":"+1 403 214 0000",
    "sg:postcode":"T2G 2R7",
    "sg:province":"AB",
    "sg:tags":[
        "store"
    ],
    "wof:name":"O K Liquor Store",
    "wof:placetype":"venue"
},
  "geometry": {"coordinates":[-114.06306499999999,51.017624],"type":"Point"}
}