{
  "type": "Feature",
  "properties": {
    "addr:full":"479 Chilcotin Rd Kamloops BC V2H 1G4",
    "addr:housenumber":"479",
    "addr:postcode":"bc v2h 1g4",
    "addr:street":"Chilcotin Rd",
    "iso:country":"CA",
    "sg:address":"479 Chilcotin Rd",
    "sg:city":"Kamloops",
    "sg:classifiers":[
        {
            "category":"Recreation",
            "type":"Entertainment"
        }
    ],
    "sg:phone":"+1 250 314 9645",
    "sg:postcode":"V2H 1G4",
    "sg:province":"BC",
    "sg:tags":[
        "carnival",
        "government"
    ],
    "wof:name":"Kamloops Exhibition Assn",
    "wof:placetype":"venue"
},
  "geometry": {"coordinates":[-120.32933,50.69043],"type":"Point"}
}