{
  "type": "Feature",
  "properties": {
    "addr:full":"320 S Service Rd Swift Current SK S9H 3X6",
    "addr:housenumber":"320",
    "addr:postcode":"s9h 3x6",
    "addr:street":"S Service Rd",
    "iso:country":"CA",
    "sg:address":"320 S Service Rd",
    "sg:city":"Swift Current",
    "sg:classifiers":[
        {
            "category":"Restaurant",
            "type":"Food & Drink"
        }
    ],
    "sg:phone":"+1 306 773 6244",
    "sg:postcode":"S9H 3X6",
    "sg:province":"SK",
    "wof:name":"Wong's Kitchen",
    "wof:placetype":"venue"
},
  "geometry": {"coordinates":[-107.795394898,50.2978477478],"type":"Point"}
}