{
  "type": "Feature",
  "properties": {
    "addr:full":"491 Boul Perron Carleton QC G0C 1J0",
    "addr:housenumber":"491",
    "addr:postcode":"g0c 1j0",
    "addr:street":"Boul Perron",
    "iso:country":"CA",
    "sg:address":"491 Boul Perron",
    "sg:city":"Carleton",
    "sg:classifiers":[
        {
            "category":"Shopping",
            "subcategory":"Florist",
            "type":"Retail Goods"
        }
    ],
    "sg:phone":"+1 418 364 3202",
    "sg:postcode":"G0C 1J0",
    "sg:province":"QC",
    "sg:tags":[
        "shop",
        "gift"
    ],
    "wof:name":"Boutique Au Bon Secours Inc",
    "wof:placetype":"venue"
},
  "geometry": {"coordinates":[-66.133095,48.107552],"type":"Point"}
}