{
  "type": "Feature",
  "properties": {
    "iso:country":"CA",
    "sg:address":"1450 Lodestar Rd #12",
    "sg:city":"North York",
    "sg:classifiers":[
        {
            "category":"Professional",
            "subcategory":"Computer Services",
            "type":"Services"
        }
    ],
    "sg:phone":"+1 416 630 0998",
    "sg:postcode":"M3J 3C1",
    "sg:province":"ON",
    "sg:tags":[
        "consultant"
    ],
    "wof:name":"Protech Computer Systems",
    "wof:placetype":"venue"
},
  "geometry": {"coordinates":[-79.4678573608,43.7610931396],"type":"Point"}
}