{
  "type": "Feature",
  "properties": {
    "iso:country":"CA",
    "sg:address":"1501 Howard Ave",
    "sg:city":"Windsor",
    "sg:classifiers":[
        {
            "category":"Freight",
            "type":"Transportation"
        }
    ],
    "sg:phone":"+1 519 977 6319",
    "sg:postcode":"N8X 3T5",
    "sg:province":"ON",
    "sg:tags":[
        "trucking"
    ],
    "wof:name":"Rjr Transportation Svc",
    "wof:placetype":"venue"
},
  "geometry": {"coordinates":[-83.02038574220001,42.3028526306],"type":"Point"}
}