{
  "type": "Feature",
  "properties": {
    "addr:full":"985 Broadview Ave East York ON M4K 2R9",
    "addr:housenumber":"985",
    "addr:postcode":"m4k 2r9",
    "addr:street":"Broadview Ave",
    "iso:country":"CA",
    "sg:address":"985 Broadview Ave",
    "sg:city":"East York",
    "sg:classifiers":[
        {
            "category":"Professional",
            "subcategory":"Management & Consulting",
            "type":"Services"
        }
    ],
    "sg:phone":"+1 416 429 6545",
    "sg:postcode":"M4K 2R9",
    "sg:province":"ON",
    "sg:tags":[
        "marketing",
        "consultant"
    ],
    "wof:name":"Dhc Marketing Ltd",
    "wof:placetype":"venue"
},
  "geometry": {"coordinates":[-79.356827,43.683754],"type":"Point"}
}