{
  "type": "Feature",
  "properties": {
    "iso:country":"CA",
    "sg:address":"3725 Queens Line",
    "sg:city":"Tilbury",
    "sg:classifiers":[
        {
            "category":"Autos & Motor Vehicles",
            "subcategory":"Automobile Sales",
            "type":"Retail Goods"
        }
    ],
    "sg:phone":"+1 519 682 3333",
    "sg:postcode":"N0P 2L0",
    "sg:province":"ON",
    "sg:tags":[
        "truck"
    ],
    "wof:name":"Freeway Truck Sales",
    "wof:placetype":"venue"
},
  "geometry": {"coordinates":[-82.41380310060001,42.2669448853],"type":"Point"}
}