{
  "type": "Feature",
  "properties": {
    "addr:full":"455 Principale Saint-Felix-D'Otis QC G0V 1M0",
    "addr:housenumber":"455",
    "addr:postcode":"g0v 1m0",
    "addr:street":"Principale Saint-Felix-D'Otis",
    "iso:country":"CA",
    "sg:address":"455 Principale",
    "sg:city":"Saint-Felix-D'Otis",
    "sg:classifiers":[
        {
            "category":"Real Estate",
            "subcategory":"Real Estate Agent",
            "type":"Services"
        }
    ],
    "sg:phone":"+1 418 544 9122",
    "sg:postcode":"G0V 1M0",
    "sg:province":"QC",
    "sg:tags":[
        "authorities",
        "housing"
    ],
    "wof:name":"Office Municipal D'Habitation",
    "wof:placetype":"venue"
},
  "geometry": {"coordinates":[-68.857231,48.860443],"type":"Point"}
}