{
  "type": "Feature",
  "properties": {
    "addr:full":"200 Advance Blvd #9111 Brampton ON L6T 4V4",
    "addr:housenumber":"200",
    "addr:postcode":"l6t 4v4",
    "addr:street":"Advance Blvd # 9111",
    "iso:country":"CA",
    "sg:address":"200 Advance Blvd #9111",
    "sg:city":"Brampton",
    "sg:classifiers":[
        {
            "category":"Restaurant",
            "type":"Food & Drink"
        }
    ],
    "sg:phone":"+1 905 799 9777",
    "sg:postcode":"L6T 4V4",
    "sg:province":"ON",
    "wof:name":"Bombay Palace",
    "wof:placetype":"venue"
},
  "geometry": {"coordinates":[-79.695602417,43.6908798218],"type":"Point"}
}