{
  "type": "Feature",
  "properties": {
    "iso:country":"CA",
    "sg:city":"Montreal",
    "sg:classifiers":[
        {
            "category":"Shopping",
            "type":"Retail Goods"
        }
    ],
    "sg:phone":"+1 514 875 2596",
    "sg:postcode":"H3B 1H4",
    "sg:province":"QC",
    "sg:tags":[
        "for",
        "supply",
        "stamp",
        "coin",
        "collector",
        "dealer"
    ],
    "wof:name":"City Stamp",
    "wof:placetype":"venue"
},
  "geometry": {"coordinates":[-73.5565948486,45.5177078247],"type":"Point"}
}