{
  "type": "Feature",
  "properties": {
    "addr:full":"3598 Dufferin St North York ON M3K 1N7",
    "addr:housenumber":"3598",
    "addr:postcode":"m3k 1n7",
    "addr:street":"Dufferin St",
    "iso:country":"CA",
    "sg:address":"3598 Dufferin St",
    "sg:city":"North York",
    "sg:classifiers":[
        {
            "category":"Personal",
            "type":"Services"
        }
    ],
    "sg:phone":"+1 416 636 7323",
    "sg:postcode":"M3K 1N7",
    "sg:province":"ON",
    "sg:tags":[
        "therapist",
        "program",
        "massage",
        "fitness",
        "exercise",
        "physical"
    ],
    "wof:name":"Blue Pearl Health Spa Inc",
    "wof:placetype":"venue"
},
  "geometry": {"coordinates":[-79.458778,43.731022],"type":"Point"}
}