{
  "type": "Feature",
  "properties": {
    "addr:full":"418 Route 880 Lower Millstream NB E5P 3K4",
    "addr:housenumber":"418",
    "addr:postcode":"e5p 3k4",
    "addr:street":"Route 880",
    "iso:country":"CA",
    "sg:address":"418 Route 880",
    "sg:city":"Lower Millstream",
    "sg:classifiers":[
        {
            "category":"Health Services",
            "subcategory":"Nursing And Care Facility",
            "type":"Services"
        }
    ],
    "sg:phone":"+1 506 433 3401",
    "sg:postcode":"E5P 3K4",
    "sg:province":"NB",
    "sg:tags":[
        "home",
        "rest"
    ],
    "wof:name":"Primose Cottage Special Care",
    "wof:placetype":"venue"
},
  "geometry": {"coordinates":[-65.61404418950001,45.7361831665],"type":"Point"}
}