{
  "type": "Feature",
  "properties": {
    "addr:full":"Grand-Sault/Grand Falls NB E3Z 2K5",
    "addr:postcode":"e3z 2k5",
    "iso:country":"CA",
    "sg:city":"Grand-Sault/Grand Falls",
    "sg:classifiers":[
        {
            "category":"Insurance",
            "subcategory":"Insurance Agent",
            "type":"Services"
        }
    ],
    "sg:phone":"+1 506 473 2621",
    "sg:postcode":"E3Z 2K5",
    "sg:province":"NB",
    "wof:name":"L P Godbout Assurance Ltd",
    "wof:placetype":"venue"
},
  "geometry": {"coordinates":[-67.743492,47.04586],"type":"Point"}
}