{
  "type": "Feature",
  "properties": {
    "iso:country":"CA",
    "sg:address":"2208 Boul DE Maisonneuve O",
    "sg:city":"Montreal",
    "sg:classifiers":[
        {
            "category":"Building & Trades",
            "subcategory":"Plumbing",
            "type":"Services"
        }
    ],
    "sg:phone":"+1 514 935 6235",
    "sg:postcode":"H3H 1L1",
    "sg:province":"QC",
    "sg:tags":[
        "contractor"
    ],
    "wof:name":"James Griffin & Son Ltd",
    "wof:placetype":"venue"
},
  "geometry": {"coordinates":[-73.5501174927,45.526927948],"type":"Point"}
}