{
  "type": "Feature",
  "properties": {
    "addr:full":"438 Boul Des Ruisseaux Mont-Laurier QC J9L 3G6",
    "addr:housenumber":"438",
    "addr:postcode":"j9l 3g6",
    "addr:street":"Boul Des Ruisseaux",
    "iso:country":"CA",
    "sg:address":"438 Boul Des Ruisseaux",
    "sg:city":"Mont-Laurier",
    "sg:classifiers":[
        {
            "category":"Retail",
            "subcategory":"Auto Repair",
            "type":"Services"
        }
    ],
    "sg:phone":"+1 819 623 1252",
    "sg:postcode":"J9L 3G6",
    "sg:province":"QC",
    "sg:tags":[
        "recreational",
        "snowmobile"
    ],
    "wof:name":"Sports Michel Gauthier",
    "wof:placetype":"venue"
},
  "geometry": {"coordinates":[-75.53141021730001,46.5545387268],"type":"Point"}
}