{
  "type": "Feature",
  "properties": {
    "iso:country":"CA",
    "sg:address":"1260 Rue Des Cascades O",
    "sg:city":"Saint-Hyacinthe",
    "sg:classifiers":[
        {
            "category":"Shopping",
            "subcategory":"Clothing, Apparel, & Fashions",
            "type":"Retail Goods"
        }
    ],
    "sg:phone":"+1 450 261 8348",
    "sg:postcode":"J2S 3H1",
    "sg:province":"QC",
    "sg:tags":[
        "jean",
        "boutique"
    ],
    "wof:name":"Bo Jeans En Gros",
    "wof:placetype":"venue"
},
  "geometry": {"coordinates":[-72.9443511963,45.6257247925],"type":"Point"}
}