{
  "type": "Feature",
  "properties": {
    "iso:country":"CA",
    "sg:address":"240 Rue Manville O",
    "sg:city":"Asbestos",
    "sg:classifiers":[
        {
            "category":"Building & Trades",
            "subcategory":"Plumbing",
            "type":"Services"
        }
    ],
    "sg:phone":"+1 819 879 6777",
    "sg:postcode":"J1T 1G7",
    "sg:province":"QC",
    "sg:tags":[
        "mechanical",
        "contractor"
    ],
    "wof:name":"Mecanique Industrielle al",
    "wof:placetype":"venue"
},
  "geometry": {"coordinates":[-71.967414856,45.7767791748],"type":"Point"}
}