{
  "type": "Feature",
  "properties": {
    "addr:full":"250 Greenbank Rd Nepean ON K2H 8X4",
    "addr:housenumber":"250",
    "addr:postcode":"k2h 8x4",
    "addr:street":"Greenbank Rd",
    "iso:country":"CA",
    "sg:address":"250 Greenbank Rd",
    "sg:city":"Nepean",
    "sg:classifiers":[
        {
            "category":"Personal",
            "subcategory":"Beauty Salon",
            "type":"Services"
        }
    ],
    "sg:phone":"+1 613 596 0757",
    "sg:postcode":"K2H 8X4",
    "sg:province":"ON",
    "wof:name":"Bella's Glamour Studio",
    "wof:placetype":"venue"
},
  "geometry": {"coordinates":[-75.778587,45.324333],"type":"Point"}
}