{
  "type": "Feature",
  "properties": {
    "addr:full":"NW 9 1 2W Gretna MB R0G 0V0",
    "addr:housenumber":"1 2w",
    "addr:postcode":"r0g 0v0",
    "addr:street":"Nw 9",
    "iso:country":"CA",
    "sg:address":"NW 9 1 2W",
    "sg:city":"Gretna",
    "sg:classifiers":[
        {
            "category":"Farming",
            "subcategory":"Farm & Veterinary Services",
            "type":"Manufacturing & Wholesale Goods"
        }
    ],
    "sg:phone":"+1 204 327 5308",
    "sg:postcode":"R0G 0V0",
    "sg:province":"MB",
    "sg:tags":[
        "aerial",
        "applicator"
    ],
    "wof:name":"J & J Air",
    "wof:placetype":"venue"
},
  "geometry": {"coordinates":[-97.560997,49.007931],"type":"Point"}
}