{
  "type": "Feature",
  "properties": {
    "addr:full":"Kelowna BC V1Z 2W8",
    "addr:postcode":"v1z 2w8",
    "iso:country":"CA",
    "sg:city":"Kelowna",
    "sg:classifiers":[
        {
            "category":"Building & Trades",
            "subcategory":"Electrical",
            "type":"Services"
        }
    ],
    "sg:phone":"+1 250 769 5888",
    "sg:postcode":"V1Z 2W8",
    "sg:province":"BC",
    "sg:tags":[
        "electric",
        "contractor"
    ],
    "wof:name":"Bob Herron Electric Ltd",
    "wof:placetype":"venue"
},
  "geometry": {"coordinates":[-119.580474853,49.869468689],"type":"Point"}
}