{
  "type": "Feature",
  "properties": {
    "addr:full":"114 Ashgrove Blvd Brandon MB R7B 1E1",
    "addr:housenumber":"114",
    "addr:postcode":"r7b 1e1",
    "addr:street":"Ashgrove Blvd",
    "iso:country":"CA",
    "sg:address":"114 Ashgrove Blvd",
    "sg:city":"Brandon",
    "sg:classifiers":[
        {
            "category":"Organizations",
            "subcategory":"Religious Organization",
            "type":"Services"
        }
    ],
    "sg:phone":"+1 204 728 6206",
    "sg:postcode":"R7B 1E1",
    "sg:province":"MB",
    "sg:tags":[
        "church"
    ],
    "wof:name":"Lutheran Redeemer Church",
    "wof:placetype":"venue"
},
  "geometry": {"coordinates":[-99.9770736694,49.8302001953],"type":"Point"}
}