{
  "type": "Feature",
  "properties": {
    "iso:country":"CA",
    "sg:address":"206 Rue Jacques-Cartier S",
    "sg:city":"Farnham",
    "sg:classifiers":[
        {
            "category":"Retail",
            "subcategory":"Auto Repair",
            "type":"Services"
        }
    ],
    "sg:phone":"+1 450 293 5207",
    "sg:postcode":"J2N 1Y4",
    "sg:province":"QC",
    "sg:tags":[
        "repairing",
        "automobile",
        "body"
    ],
    "wof:name":"Debosselage Farnham Inc",
    "wof:placetype":"venue"
},
  "geometry": {"coordinates":[-72.98318481450001,45.2773361206],"type":"Point"}
}