{
  "type": "Feature",
  "properties": {
    "addr:full":"570 Clarke Rd #10 London ON N5V 3K5",
    "addr:housenumber":"570",
    "addr:postcode":"n5v 3k5",
    "addr:street":"Clarke Rd # 10",
    "iso:country":"CA",
    "sg:address":"570 Clarke Rd #10",
    "sg:city":"London",
    "sg:classifiers":[
        {
            "category":"Retail",
            "subcategory":"Car Wash",
            "type":"Services"
        }
    ],
    "sg:phone":"+1 519 455 6190",
    "sg:postcode":"N5V 3K5",
    "sg:province":"ON",
    "sg:tags":[
        "automobile",
        "detail",
        "sign"
    ],
    "wof:name":"Auto Trim Design",
    "wof:placetype":"venue"
},
  "geometry": {"coordinates":[-81.179535,43.012611],"type":"Point"}
}