{
  "type": "Feature",
  "properties": {
    "iso:country":"CA",
    "sg:address":"2465 St. Peter Ave",
    "sg:city":"Bathurst",
    "sg:classifiers":[
        {
            "category":"Shopping",
            "type":"Retail Goods"
        }
    ],
    "sg:phone":"+1 506 546 6286",
    "sg:postcode":"E2A 7K3",
    "sg:province":"NB",
    "sg:tags":[
        "physiotherapist",
        "orthopedic",
        "appliance"
    ],
    "wof:name":"Physio Max",
    "wof:placetype":"venue"
},
  "geometry": {"coordinates":[-65.6826171875,47.6608161926],"type":"Point"}
}