{
  "type": "Feature",
  "properties": {
    "addr:full":"710 3 Rang Lyster QC G0S 1V0",
    "addr:housenumber":"710 3",
    "addr:postcode":"g0s 1v0",
    "addr:street":"Rang Lyster",
    "iso:country":"CA",
    "sg:address":"710 3 Rang",
    "sg:city":"Lyster",
    "sg:classifiers":[
        {
            "category":"Farming",
            "subcategory":"Farm",
            "type":"Manufacturing & Wholesale Goods"
        }
    ],
    "sg:phone":"+1 819 389 5469",
    "sg:postcode":"G0S 1V0",
    "sg:province":"QC",
    "wof:name":"Ferme Mj Fillion Inc",
    "wof:placetype":"venue"
},
  "geometry": {"coordinates":[-71.62396200000001,46.392525],"type":"Point"}
}