{
  "type": "Feature",
  "properties": {
    "addr:full":"193 Commercial St Berwick NS B0P 1E0",
    "addr:housenumber":"193",
    "addr:postcode":"b0p 1e0",
    "addr:street":"Commercial St",
    "iso:country":"CA",
    "sg:address":"193 Commercial St",
    "sg:city":"Berwick",
    "sg:classifiers":[
        {
            "category":"Food & Beverages",
            "subcategory":"Bakery",
            "type":"Retail Goods"
        }
    ],
    "sg:phone":"+1 902 538 1104",
    "sg:postcode":"B0P 1E0",
    "sg:province":"NS",
    "sg:tags":[
        "doughnut"
    ],
    "wof:name":"Tim Hortons",
    "wof:placetype":"venue"
},
  "geometry": {"coordinates":[-64.735474,45.043045],"type":"Point"}
}