{
  "type": "Feature",
  "properties": {
    "addr:full":"415 Boul Fiset Sorel-Tracy QC J3P 3R7",
    "addr:housenumber":"415",
    "addr:postcode":"j3p 3r7",
    "addr:street":"Boul Fiset",
    "iso:country":"CA",
    "sg:address":"415 Boul Fiset",
    "sg:city":"Sorel-Tracy",
    "sg:classifiers":[
        {
            "category":"Building & Trades",
            "subcategory":"Landscaping Services",
            "type":"Services"
        }
    ],
    "sg:phone":"+1 450 743 4222",
    "sg:postcode":"J3P 3R7",
    "sg:province":"QC",
    "sg:tags":[
        "landscape",
        "contractor"
    ],
    "wof:name":"Jardins Plus",
    "wof:placetype":"venue"
},
  "geometry": {"coordinates":[-73.088753,46.032623],"type":"Point"}
}