{
  "type": "Feature",
  "properties": {
    "addr:full":"1442 Lawrence Ave W North York ON M6L 1B5",
    "addr:housenumber":"1442",
    "addr:postcode":"m6l 1b5",
    "addr:street":"Lawrence Ave W",
    "iso:country":"CA",
    "sg:address":"1442 Lawrence Ave W",
    "sg:city":"North York",
    "sg:classifiers":[
        {
            "category":"Food & Beverages",
            "subcategory":"Groceries & Convenience Stores",
            "type":"Retail Goods"
        }
    ],
    "sg:phone":"+1 416 247 9616",
    "sg:postcode":"M6L 1B5",
    "sg:province":"ON",
    "sg:tags":[
        "grocer"
    ],
    "wof:name":"Crown Grocery",
    "wof:placetype":"venue"
},
  "geometry": {"coordinates":[-79.478584,43.708626],"type":"Point"}
}