{
  "type": "Feature",
  "properties": {
    "addr:full":"11668 154 St NW Edmonton AB T5M 3N8",
    "addr:housenumber":"11668",
    "addr:postcode":"t5m 3n8",
    "addr:street":"154 St Nw",
    "iso:country":"CA",
    "sg:address":"11668 154 St NW",
    "sg:city":"Edmonton",
    "sg:classifiers":[
        {
            "category":"Wholesale",
            "subcategory":"Auto Parts",
            "type":"Manufacturing & Wholesale Goods"
        }
    ],
    "sg:phone":"+1 780 454 3399",
    "sg:postcode":"T5M 3N8",
    "sg:province":"AB",
    "sg:tags":[
        "body",
        "automobile",
        "shop"
    ],
    "wof:name":"Akzo Nobel Coatings",
    "wof:placetype":"venue"
},
  "geometry": {"coordinates":[-113.587463379,53.5688743591],"type":"Point"}
}