{
  "type": "Feature",
  "properties": {
    "addr:full":"Hay River NT X0E 1G2",
    "addr:postcode":"x0e 1g2",
    "iso:country":"CA",
    "sg:city":"Hay River",
    "sg:classifiers":[
        {
            "category":"Utilities",
            "subcategory":"Mobile Phone",
            "type":"Services"
        }
    ],
    "sg:phone":"+1 867 874 6688",
    "sg:postcode":"X0E 1G2",
    "sg:province":"NT",
    "sg:tags":[
        "television",
        "radio",
        "telephone",
        "cellular"
    ],
    "wof:name":"Superior Sound",
    "wof:placetype":"venue"
},
  "geometry": {"coordinates":[-115.787811,60.809364],"type":"Point"}
}