{
  "type": "Feature",
  "properties": {
    "iso:country":"CA",
    "sg:address":"39 Franklin St",
    "sg:city":"Churchill",
    "sg:classifiers":[
        {
            "category":"Ferry",
            "type":"Transportation"
        }
    ],
    "sg:phone":"+1 204 675 2195",
    "sg:postcode":"R0B 0E0",
    "sg:province":"MB",
    "sg:tags":[
        "whale",
        "watching"
    ],
    "wof:name":"Sea North Tours Ltd",
    "wof:placetype":"venue"
},
  "geometry": {"coordinates":[-94.1679534912,58.7691192627],"type":"Point"}
}