{
  "type": "Feature",
  "properties": {
    "iso:country":"CA",
    "sg:address":"2356 41st Ave W",
    "sg:city":"Vancouver",
    "sg:classifiers":[
        {
            "category":"Shopping",
            "type":"Retail Goods"
        }
    ],
    "sg:phone":"+1 604 263 2122",
    "sg:postcode":"V6M 2A4",
    "sg:province":"BC",
    "sg:tags":[
        "pottery",
        "art",
        "gallery",
        "dealer"
    ],
    "wof:name":"O H Brothers",
    "wof:placetype":"venue"
},
  "geometry": {"coordinates":[-123.160629273,49.2345085144],"type":"Point"}
}