{
  "type": "Feature",
  "properties": {
    "addr:full":"117 Rue J.-J.-Bertrand Cowansville QC J2K 3R5",
    "addr:housenumber":"117",
    "addr:postcode":"j2k 3r5",
    "addr:street":"Rue J.-J.-Bertrand",
    "iso:country":"CA",
    "sg:address":"117 Rue J.-J.-Bertrand",
    "sg:city":"Cowansville",
    "sg:classifiers":[
        {
            "category":"Professional",
            "subcategory":"Lawyer & Legal Services",
            "type":"Services"
        }
    ],
    "sg:phone":"+1 450 263 5807",
    "sg:postcode":"J2K 3R5",
    "sg:province":"QC",
    "sg:tags":[
        "attorney"
    ],
    "wof:name":"Bachand, Eugene",
    "wof:placetype":"venue"
},
  "geometry": {"coordinates":[-72.76680755620001,45.2094154358],"type":"Point"}
}