{
  "type": "Feature",
  "properties": {
    "addr:full":"345 Rue Isabey Saint-Laurent QC H4T 1Y2",
    "addr:housenumber":"345",
    "addr:postcode":"h4t 1y2",
    "addr:street":"Rue Isabey",
    "iso:country":"CA",
    "sg:address":"345 Rue Isabey",
    "sg:city":"Saint-Laurent",
    "sg:classifiers":[
        {
            "category":"Wholesale",
            "subcategory":"Electrical",
            "type":"Manufacturing & Wholesale Goods"
        }
    ],
    "sg:phone":"+1 514 342 6581",
    "sg:postcode":"H4T 1Y2",
    "sg:province":"QC",
    "sg:tags":[
        "equipment",
        "lighting",
        "system"
    ],
    "wof:name":"Pdm Produits Electriques",
    "wof:placetype":"venue"
},
  "geometry": {"coordinates":[-73.6835784912,45.4927253723],"type":"Point"}
}