{
  "type": "Feature",
  "properties": {
    "addr:full":"8552 Rue Saint-Denis Montreal QC H2P 2H2",
    "addr:housenumber":"8552",
    "addr:postcode":"h2p 2h2",
    "addr:street":"Rue Saint-Denis",
    "iso:country":"CA",
    "sg:address":"8552 Rue Saint-Denis",
    "sg:city":"Montreal",
    "sg:classifiers":[
        {
            "category":"Personal",
            "type":"Services"
        }
    ],
    "sg:phone":"+1 514 385 5889",
    "sg:postcode":"H2P 2H2",
    "sg:province":"QC",
    "sg:tags":[
        "bankruptcy",
        "trustee"
    ],
    "wof:name":"Centre D'Affaires St-Denis",
    "wof:placetype":"venue"
},
  "geometry": {"coordinates":[-73.63641357420001,45.5445556641],"type":"Point"}
}