{
  "type": "Feature",
  "properties": {
    "addr:full":"550 Lansdowne St W Peterborough ON K9J 8J8",
    "addr:housenumber":"550",
    "addr:postcode":"k9j 8j8",
    "addr:street":"Lansdowne St W",
    "iso:country":"CA",
    "sg:address":"550 Lansdowne St W",
    "sg:city":"Peterborough",
    "sg:classifiers":[
        {
            "category":"Wholesale",
            "subcategory":"Medical Equipment & Supplies",
            "type":"Manufacturing & Wholesale Goods"
        }
    ],
    "sg:phone":"+1 705 740 2650",
    "sg:postcode":"K9J 8J8",
    "sg:province":"ON",
    "sg:tags":[
        "wheel",
        "hospital",
        "scooter",
        "chair"
    ],
    "wof:name":"Medichair Trent",
    "wof:placetype":"venue"
},
  "geometry": {"coordinates":[-78.32813299999999,44.286457],"type":"Point"}
}