{
  "type": "Feature",
  "properties": {
    "addr:full":"237 Ch Du Lac Saint-Augustin-DE-Desmaures QC G3A 1W7",
    "addr:housenumber":"237",
    "addr:postcode":"g3a 1w7",
    "addr:street":"Ch Du Lac",
    "iso:country":"CA",
    "sg:address":"237 Ch Du Lac",
    "sg:city":"Saint-Augustin-DE-Desmaures",
    "sg:classifiers":[
        {
            "category":"Manufacturing",
            "subcategory":"Lumber",
            "type":"Manufacturing & Wholesale Goods"
        }
    ],
    "sg:phone":"+1 418 878 5085",
    "sg:postcode":"G3A 1W7",
    "sg:province":"QC",
    "sg:tags":[
        "syrup",
        "maple",
        "sugar"
    ],
    "wof:name":"Erabliere Le Chemin Du Roy Inc",
    "wof:placetype":"venue"
},
  "geometry": {"coordinates":[-71.412277,46.738434],"type":"Point"}
}