{
  "type": "Feature",
  "properties": {
    "iso:country":"CA",
    "sg:address":"1028 Clements Ave",
    "sg:city":"North Vancouver",
    "sg:classifiers":[
        {
            "category":"Professional",
            "subcategory":"Management & Consulting",
            "type":"Services"
        }
    ],
    "sg:phone":"+1 604 990 9680",
    "sg:postcode":"V7R 2L4",
    "sg:province":"BC",
    "sg:tags":[
        "consultant",
        "business"
    ],
    "wof:name":"Sommers Consulting Inc",
    "wof:placetype":"venue"
},
  "geometry": {"coordinates":[-123.10108184800001,49.3581771851],"type":"Point"}
}