{
  "type": "Feature",
  "properties": {
    "iso:country":"CA",
    "sg:address":"7 Rue Demers",
    "sg:city":"Bedford",
    "sg:classifiers":[
        {
            "category":"Personal",
            "type":"Services"
        }
    ],
    "sg:phone":"+1 450 248 2760",
    "sg:postcode":"J0J 1A0",
    "sg:province":"QC",
    "sg:tags":[
        "electrolysis"
    ],
    "wof:name":"Salon D'Esthetique Geisha",
    "wof:placetype":"venue"
},
  "geometry": {"coordinates":[-72.97825622560001,45.1223487854],"type":"Point"}
}