{
  "type": "Feature",
  "properties": {
    "addr:full":"7008 Rochdale Blvd Regina SK S4X 3E2",
    "addr:housenumber":"7008",
    "addr:postcode":"s4x 3e2",
    "addr:street":"Rochdale Blvd",
    "iso:country":"CA",
    "sg:address":"7008 Rochdale Blvd",
    "sg:city":"Regina",
    "sg:classifiers":[
        {
            "category":"Organizations",
            "subcategory":"Religious Organization",
            "type":"Services"
        }
    ],
    "sg:phone":"+1 306 949 6727",
    "sg:postcode":"S4X 3E2",
    "sg:province":"SK",
    "sg:tags":[
        "church"
    ],
    "wof:name":"Jehovah's Witnesses",
    "wof:placetype":"venue"
},
  "geometry": {"coordinates":[-104.681365967,50.4950561523],"type":"Point"}
}