{
  "type": "Feature",
  "properties": {
    "iso:country":"CA",
    "sg:city":"Beauport",
    "sg:classifiers":[
        {
            "category":"Organizations",
            "subcategory":"Religious Organization",
            "type":"Services"
        }
    ],
    "sg:phone":"+1 418 661 3148",
    "sg:postcode":"G1C 1A4",
    "sg:province":"QC",
    "sg:tags":[
        "home",
        "retirement",
        "community",
        "retreat",
        "house"
    ],
    "wof:name":"Residences DE Longpre Inc",
    "wof:placetype":"venue"
},
  "geometry": {"coordinates":[-71.1931381226,46.8592414856],"type":"Point"}
}