{
  "type": "Feature",
  "properties": {
    "addr:full":"168 George St Arthur ON N0G 1A0",
    "addr:housenumber":"168",
    "addr:postcode":"n0g 1a0",
    "addr:street":"George St",
    "iso:country":"CA",
    "sg:address":"168 George St",
    "sg:city":"Arthur",
    "sg:classifiers":[
        {
            "category":"Restaurant",
            "type":"Food & Drink"
        }
    ],
    "sg:phone":"+1 519 848 5454",
    "sg:postcode":"N0G 1A0",
    "sg:province":"ON",
    "sg:tags":[
        "pizza"
    ],
    "wof:name":"New Orleans Pizza",
    "wof:placetype":"venue"
},
  "geometry": {"coordinates":[-80.536423,43.83131],"type":"Point"}
}