{
  "type": "Feature",
  "properties": {
    "addr:full":"5343 Ch Queen-Mary Montreal QC H3X 1T9",
    "addr:postcode":"5343;h3x 1t9",
    "addr:street":"Ch Queen-Mary",
    "iso:country":"CA",
    "sg:address":"5343 Ch Queen-Mary",
    "sg:city":"Montreal",
    "sg:classifiers":[
        {
            "category":"Cinema",
            "subcategory":"Movie Rental",
            "type":"Entertainment"
        }
    ],
    "sg:phone":"+1 514 481 2344",
    "sg:postcode":"H3X 1T9",
    "sg:province":"QC",
    "sg:tags":[
        "leasing",
        "video",
        "disc",
        "tape"
    ],
    "wof:name":"Nickelodeon Video Boutique Ltd",
    "wof:placetype":"venue"
},
  "geometry": {"coordinates":[-73.63000488279999,45.4829559326],"type":"Point"}
}