{
  "type": "Feature",
  "properties": {
    "iso:country":"CA",
    "sg:address":"15 Lloyd St",
    "sg:city":"St Catharines",
    "sg:classifiers":[
        {
            "category":"Professional",
            "subcategory":"Accounting & Tax Preparation",
            "type":"Services"
        }
    ],
    "sg:phone":"+1 905 682 2629",
    "sg:postcode":"L2S 2N7",
    "sg:province":"ON",
    "sg:tags":[
        "accountant"
    ],
    "wof:name":"Rosetti & Bowley",
    "wof:placetype":"venue"
},
  "geometry": {"coordinates":[-79.2556381226,43.1447639465],"type":"Point"}
}