{
  "type": "Feature",
  "properties": {
    "addr:full":"510 Millstone Ave Nanaimo BC V9S 5A9",
    "addr:housenumber":"510",
    "addr:postcode":"v9s 5a9",
    "addr:street":"Millstone Ave",
    "iso:country":"CA",
    "sg:address":"510 Millstone Ave",
    "sg:city":"Nanaimo",
    "sg:classifiers":[
        {
            "category":"Education",
            "subcategory":"School",
            "type":"Public Place"
        }
    ],
    "sg:phone":"+1 250 754 7523",
    "sg:postcode":"V9S 5A9",
    "sg:province":"BC",
    "wof:name":"Brechin School",
    "wof:placetype":"venue"
},
  "geometry": {"coordinates":[-123.954887,49.177551],"type":"Point"}
}