{
  "type": "Feature",
  "properties": {
    "iso:country":"CA",
    "sg:address":"1150 Ellesmere Rd",
    "sg:city":"Scarborough",
    "sg:classifiers":[
        {
            "category":"Autos & Motor Vehicles",
            "subcategory":"Fuel & Gas Station",
            "type":"Retail Goods"
        }
    ],
    "sg:phone":"+1 416 298 8454",
    "sg:postcode":"M1P 2X4",
    "sg:province":"ON",
    "sg:tags":[
        "oil"
    ],
    "wof:name":"Sunoco",
    "wof:placetype":"venue"
},
  "geometry": {"coordinates":[-79.2706985474,43.768196106],"type":"Point"}
}