{
  "type": "Feature",
  "properties": {
    "iso:country":"CA",
    "sg:address":"8505 142 Ave NW",
    "sg:city":"Edmonton",
    "sg:classifiers":[
        {
            "category":"Organizations",
            "subcategory":"Religious Organization",
            "type":"Services"
        }
    ],
    "sg:phone":"+1 780 483 5366",
    "sg:postcode":"T5E 2G3",
    "sg:province":"AB",
    "sg:tags":[
        "church"
    ],
    "wof:name":"Laurier Heights Baptist Church",
    "wof:placetype":"venue"
},
  "geometry": {"coordinates":[-113.470542908,53.6039428711],"type":"Point"}
}