{
  "type": "Feature",
  "properties": {
    "addr:full":"4150 Rue Sherbrooke O Westmount QC H3Z 1C2",
    "addr:housenumber":"4150",
    "addr:postcode":"h3z 1c2",
    "addr:street":"Rue Sherbrooke O",
    "iso:country":"CA",
    "sg:address":"4150 Rue Sherbrooke O",
    "sg:city":"Westmount",
    "sg:classifiers":[
        {
            "category":"Health Services",
            "subcategory":"Health Practitioner",
            "type":"Services"
        }
    ],
    "sg:phone":"+1 514 747 9648",
    "sg:postcode":"H3Z 1C2",
    "sg:province":"QC",
    "sg:tags":[
        "psychologist"
    ],
    "wof:name":"Caplan, J",
    "wof:placetype":"venue"
},
  "geometry": {"coordinates":[-73.591042,45.488369],"type":"Point"}
}