{
  "type": "Feature",
  "properties": {
    "addr:full":"Red Lake ON P0V 2M0",
    "addr:postcode":"p0v 2m0",
    "iso:country":"CA",
    "sg:city":"Red Lake",
    "sg:classifiers":[
        {
            "category":"Professional",
            "subcategory":"Lawyer & Legal Services",
            "type":"Services"
        }
    ],
    "sg:phone":"+1 807 727 3200",
    "sg:postcode":"P0V 2M0",
    "sg:province":"ON",
    "sg:tags":[
        "attorney"
    ],
    "wof:name":"Smart, Russel S",
    "wof:placetype":"venue"
},
  "geometry": {"coordinates":[-93.823059,51.018261],"type":"Point"}
}