{
  "type": "Feature",
  "properties": {
    "iso:country":"CA",
    "sg:address":"5673 North St",
    "sg:city":"Niagara Falls",
    "sg:classifiers":[
        {
            "category":"Social Services",
            "type":"Services"
        }
    ],
    "sg:phone":"+1 905 356 7548",
    "sg:postcode":"L2G 1J4",
    "sg:province":"ON",
    "sg:tags":[
        "organization",
        "welfare"
    ],
    "wof:name":"Meals on Wheels Niagara Falls",
    "wof:placetype":"venue"
},
  "geometry": {"coordinates":[-79.089012146,43.093334198],"type":"Point"}
}