{
  "type": "Feature",
  "properties": {
    "iso:country":"CA",
    "sg:address":"10483 Islington Ave",
    "sg:city":"Kleinburg",
    "sg:classifiers":[
        {
            "category":"Shopping",
            "subcategory":"Jewelry",
            "type":"Retail Goods"
        }
    ],
    "sg:phone":"+1 905 893 1153",
    "sg:postcode":"L0J 1C0",
    "sg:province":"ON",
    "sg:tags":[
        "jeweler"
    ],
    "wof:name":"Jeremy Workshop",
    "wof:placetype":"venue"
},
  "geometry": {"coordinates":[-79.6274032593,43.8435897827],"type":"Point"}
}