{
  "type": "Feature",
  "properties": {
    "addr:full":"106 Kent St W Lindsay ON K9V 2Y4",
    "addr:housenumber":"106",
    "addr:postcode":"k9v 2y4",
    "addr:street":"Kent St W",
    "iso:country":"CA",
    "sg:address":"106 Kent St W",
    "sg:city":"Lindsay",
    "sg:classifiers":[
        {
            "category":"Restaurant",
            "type":"Food & Drink"
        }
    ],
    "sg:phone":"+1 705 328 1444",
    "sg:postcode":"K9V 2Y4",
    "sg:province":"ON",
    "wof:name":"Olympia Restaurant",
    "wof:placetype":"venue"
},
  "geometry": {"coordinates":[-78.7379226685,44.3549308777],"type":"Point"}
}