{
  "type": "Feature",
  "properties": {
    "iso:country":"CA",
    "sg:address":"9 Lanark Rd",
    "sg:city":"Perth",
    "sg:classifiers":[
        {
            "category":"Building & Trades",
            "subcategory":"Plumbing",
            "type":"Services"
        }
    ],
    "sg:phone":"+1 613 267 3236",
    "sg:postcode":"K7H 2R9",
    "sg:province":"ON",
    "sg:tags":[
        "air",
        "conditioning",
        "contractor",
        "system",
        "heating"
    ],
    "wof:name":"Kilpatrick Fuels Ltd",
    "wof:placetype":"venue"
},
  "geometry": {"coordinates":[-76.2483291626,44.8989448547],"type":"Point"}
}