{
  "type": "Feature",
  "properties": {
    "addr:full":"243 Water St Botwood NL A0H 1E0",
    "addr:housenumber":"243",
    "addr:postcode":"a0h 1e0",
    "addr:street":"Water St",
    "iso:country":"CA",
    "sg:address":"243 Water St",
    "sg:city":"Botwood",
    "sg:classifiers":[
        {
            "category":"Restaurant",
            "type":"Food & Drink"
        }
    ],
    "sg:phone":"+1 709 257 3179",
    "sg:postcode":"A0H 1E0",
    "sg:province":"NL",
    "wof:name":"Dockside Restaurant",
    "wof:placetype":"venue"
},
  "geometry": {"coordinates":[-55.359222,49.129429],"type":"Point"}
}