{
  "type": "Feature",
  "properties": {
    "addr:full":"Goodlow BC V0C 1S0",
    "addr:postcode":"bc v0c 1s0",
    "iso:country":"CA",
    "sg:city":"Goodlow",
    "sg:classifiers":[
        {
            "category":"Building & Trades",
            "subcategory":"Construction",
            "type":"Services"
        }
    ],
    "sg:phone":"+1 250 781 3598",
    "sg:postcode":"V0C 1S0",
    "sg:province":"BC",
    "sg:tags":[
        "excavating",
        "contractor"
    ],
    "wof:name":"Forrester Specialty Svc Ltd",
    "wof:placetype":"venue"
},
  "geometry": {"coordinates":[-120.18888855,56.3337211609],"type":"Point"}
}