{
  "type": "Feature",
  "properties": {
    "iso:country":"CA",
    "sg:address":"110 6th Ave",
    "sg:city":"Thorhild",
    "sg:classifiers":[
        {
            "category":"Health Services",
            "subcategory":"Doctor",
            "type":"Services"
        }
    ],
    "sg:phone":"+1 780 398 3533",
    "sg:postcode":"T0A 3J0",
    "sg:province":"AB",
    "sg:tags":[
        "physician",
        "surgeon"
    ],
    "wof:name":"Thorhild Medical Clinic",
    "wof:placetype":"venue"
},
  "geometry": {"coordinates":[-113.124427795,54.1586227417],"type":"Point"}
}