{
  "type": "Feature",
  "properties": {
    "addr:full":"Dunbow Rd DE Winton AB T0L 0X0",
    "addr:postcode":"t0l 0x0",
    "addr:street":"Dunbow Rd De Winton",
    "iso:country":"CA",
    "sg:address":"Dunbow Rd",
    "sg:city":"DE Winton",
    "sg:classifiers":[
        {
            "category":"Home & Garden",
            "subcategory":"Furniture",
            "type":"Retail Goods"
        }
    ],
    "sg:phone":"+1 403 254 9994",
    "sg:postcode":"T0L 0X0",
    "sg:province":"AB",
    "sg:tags":[
        "builder",
        "custom"
    ],
    "wof:name":"Furniture Maker",
    "wof:placetype":"venue"
},
  "geometry": {"coordinates":[-114.01475499999999,50.822979],"type":"Point"}
}