{
  "type": "Feature",
  "properties": {
    "addr:full":"450 Parliament St Toronto ON M5A 3A2",
    "addr:housenumber":"450",
    "addr:postcode":"m5a 3a2",
    "addr:street":"Parliament St",
    "iso:country":"CA",
    "sg:address":"450 Parliament St",
    "sg:city":"Toronto",
    "sg:classifiers":[
        {
            "category":"Restaurant",
            "type":"Food & Drink"
        }
    ],
    "sg:phone":"+1 416 515 7435",
    "sg:postcode":"M5A 3A2",
    "sg:province":"ON",
    "sg:tags":[
        "cafe"
    ],
    "wof:name":"M2M Muffins",
    "wof:placetype":"venue"
},
  "geometry": {"coordinates":[-79.3678512573,43.6635131836],"type":"Point"}
}