{
  "type": "Feature",
  "properties": {
    "addr:full":"29 Queen St # 2 Lakefield ON K0L 2H0",
    "addr:housenumber":"29",
    "addr:postcode":"k0l 2h0",
    "addr:street":"Queen St # 2 Lakefield",
    "iso:country":"CA",
    "sg:address":"29 Queen St # 2",
    "sg:city":"Lakefield",
    "sg:classifiers":[
        {
            "category":"Shopping",
            "subcategory":"Jewelry",
            "type":"Retail Goods"
        }
    ],
    "sg:phone":"+1 705 652 1099",
    "sg:postcode":"K0L 2H0",
    "sg:province":"ON",
    "sg:tags":[
        "jeweler"
    ],
    "wof:name":"Bill Garrett Jewellery",
    "wof:placetype":"venue"
},
  "geometry": {"coordinates":[-78.2720718384,44.4232177734],"type":"Point"}
}