{
  "type": "Feature",
  "properties": {
    "iso:country":"CA",
    "sg:address":"4714 50th St",
    "sg:city":"Two Hills",
    "sg:classifiers":[
        {
            "category":"Health Services",
            "subcategory":"Doctor",
            "type":"Services"
        }
    ],
    "sg:phone":"+1 780 657 3456",
    "sg:postcode":"T0B 4K0",
    "sg:province":"AB",
    "sg:tags":[
        "dentist"
    ],
    "wof:name":"C Lewandowski Professional",
    "wof:placetype":"venue"
},
  "geometry": {"coordinates":[-111.74420929,53.7093811035],"type":"Point"}
}