{
  "type": "Feature",
  "properties": {
    "addr:full":"2871 Main Rd Lower Wedgeport NS B0W 2B0",
    "addr:housenumber":"2871",
    "addr:postcode":"b0w 2b0",
    "addr:street":"Main Rd",
    "iso:country":"CA",
    "sg:address":"2871 Main Rd",
    "sg:city":"Lower Wedgeport",
    "sg:classifiers":[
        {
            "category":"Manufacturing",
            "subcategory":"Food",
            "type":"Manufacturing & Wholesale Goods"
        }
    ],
    "sg:phone":"+1 902 663 2503",
    "sg:postcode":"B0W 2B0",
    "sg:province":"NS",
    "sg:tags":[
        "packer",
        "fish"
    ],
    "wof:name":"R & K Murphy Enterprises Ltd",
    "wof:placetype":"venue"
},
  "geometry": {"coordinates":[-65.97927900000001,43.716103],"type":"Point"}
}