{
  "type": "Feature",
  "properties": {
    "addr:full":"Ottawa ON K1V 1J7",
    "addr:postcode":"k1v 1j7",
    "iso:country":"CA",
    "sg:city":"Ottawa",
    "sg:classifiers":[
        {
            "category":"Government",
            "subcategory":"Post Office",
            "type":"Public Place"
        }
    ],
    "sg:phone":"+1 416 979 8822",
    "sg:postcode":"K1V 1J7",
    "sg:province":"ON",
    "sg:tags":[
        "marketing",
        "program"
    ],
    "wof:name":"Canada Post Corp",
    "wof:placetype":"venue"
},
  "geometry": {"coordinates":[-75.6909790039,45.3754463196],"type":"Point"}
}