{
  "type": "Feature",
  "properties": {
    "addr:full":"Baie-Comeau QC G5C 1P4",
    "addr:postcode":"g5c 1p4",
    "iso:country":"CA",
    "sg:city":"Baie-Comeau",
    "sg:classifiers":[
        {
            "category":"Retail",
            "subcategory":"Repair Shop",
            "type":"Services"
        }
    ],
    "sg:phone":"+1 418 297 2923",
    "sg:postcode":"G5C 1P4",
    "sg:province":"QC",
    "sg:tags":[
        "lock",
        "locksmith"
    ],
    "wof:name":"Serrurier Lucypro Mobile",
    "wof:placetype":"venue"
},
  "geometry": {"coordinates":[-68.257423,49.190937],"type":"Point"}
}