{
  "type": "Feature",
  "properties": {
    "addr:full":"Brackendale BC V0N 1H0",
    "addr:postcode":"v0n 1h0",
    "iso:country":"CA",
    "sg:city":"Brackendale",
    "sg:classifiers":[
        {
            "category":"Shopping",
            "subcategory":"Computers & Home Electronics",
            "type":"Retail Goods"
        }
    ],
    "sg:phone":"+1 604 898 1589",
    "sg:postcode":"V0N 1H0",
    "sg:province":"BC",
    "sg:tags":[
        "equipment",
        "satellite",
        "system"
    ],
    "wof:name":"Satellite Services",
    "wof:placetype":"venue"
},
  "geometry": {"coordinates":[-123.137290955,49.765827179],"type":"Point"}
}