{
  "type": "Feature",
  "properties": {
    "addr:full":"13 24th Ave N Cranbrook BC V1C 3H9",
    "addr:housenumber":"13",
    "addr:postcode":"v1c 3h9",
    "addr:street":"24Th Ave N",
    "iso:country":"CA",
    "sg:address":"13 24th Ave N",
    "sg:city":"Cranbrook",
    "sg:classifiers":[
        {
            "category":"Health Services",
            "subcategory":"Clinic",
            "type":"Services"
        }
    ],
    "sg:phone":"+1 250 426 2065",
    "sg:postcode":"V1C 3H9",
    "sg:province":"BC",
    "sg:tags":[
        "hospital",
        "agency",
        "welfare"
    ],
    "wof:name":"Cranbrook Regional Hosp Axlry",
    "wof:placetype":"venue"
},
  "geometry": {"coordinates":[-115.748795,49.512016],"type":"Point"}
}