{
  "type": "Feature",
  "properties": {
    "addr:full":"2345 Av Watt Sainte-Foy QC G1P 3X2",
    "addr:housenumber":"2345",
    "addr:postcode":"g1p 3x2",
    "addr:street":"Av Watt",
    "iso:country":"CA",
    "sg:address":"2345 Av Watt",
    "sg:city":"Sainte-Foy",
    "sg:classifiers":[
        {
            "category":"Building & Trades",
            "subcategory":"Construction",
            "type":"Services"
        }
    ],
    "sg:phone":"+1 418 653 1299",
    "sg:postcode":"G1P 3X2",
    "sg:province":"QC",
    "sg:tags":[
        "contractor"
    ],
    "wof:name":"Pbi",
    "wof:placetype":"venue"
},
  "geometry": {"coordinates":[-71.291954,46.791458],"type":"Point"}
}