{
  "type": "Feature",
  "properties": {
    "addr:full":"8912 Boul Langelier Saint-Leonard QC H1P 3C8",
    "addr:housenumber":"8912",
    "addr:postcode":"h1p 3c8",
    "addr:street":"Boul Langelier",
    "iso:country":"CA",
    "sg:address":"8912 Boul Langelier",
    "sg:city":"Saint-Leonard",
    "sg:classifiers":[
        {
            "category":"Personal",
            "subcategory":"Beauty Salon",
            "type":"Services"
        }
    ],
    "sg:phone":"+1 514 328 4458",
    "sg:postcode":"H1P 3C8",
    "sg:province":"QC",
    "wof:name":"Salon DE Coiffure Caressa",
    "wof:placetype":"venue"
},
  "geometry": {"coordinates":[-73.59676399999999,45.60107],"type":"Point"}
}