{
  "type": "Feature",
  "properties": {
    "addr:full":"1990 Columbia Ave Castlegar BC V1N 2W7",
    "addr:housenumber":"1990",
    "addr:postcode":"v1n 2w7",
    "addr:street":"Columbia Ave",
    "iso:country":"CA",
    "sg:address":"1990 Columbia Ave",
    "sg:city":"Castlegar",
    "sg:classifiers":[
        {
            "category":"Banks & Credit Unions",
            "subcategory":"Bank",
            "type":"Services"
        }
    ],
    "sg:phone":"+1 250 365 6488",
    "sg:postcode":"V1N 2W7",
    "sg:province":"BC",
    "wof:name":"Bank of Montreal",
    "wof:placetype":"venue"
},
  "geometry": {"coordinates":[-117.653854,49.295338],"type":"Point"}
}