{
  "type": "Feature",
  "properties": {
    "addr:full":"71 Anne St S Barrie ON L4N 2E2",
    "addr:housenumber":"71",
    "addr:postcode":"l4n 2e2",
    "addr:street":"Anne St S",
    "iso:country":"CA",
    "sg:address":"71 Anne St S",
    "sg:city":"Barrie",
    "sg:classifiers":[
        {
            "category":"Autos & Motor Vehicles",
            "subcategory":"Fuel & Gas Station",
            "type":"Retail Goods"
        }
    ],
    "sg:phone":"+1 705 725 0717",
    "sg:postcode":"L4N 2E2",
    "sg:province":"ON",
    "sg:tags":[
        "oil"
    ],
    "wof:name":"Canadian Tire Gas Bar",
    "wof:placetype":"venue"
},
  "geometry": {"coordinates":[-79.70072937010001,44.3774833679],"type":"Point"}
}