{
  "type": "Feature",
  "properties": {
    "iso:country":"CA",
    "sg:address":"7790 Boul Arthur-Sauve",
    "sg:city":"Laval",
    "sg:classifiers":[
        {
            "category":"Building & Trades",
            "subcategory":"Plumbing",
            "type":"Services"
        }
    ],
    "sg:phone":"+1 450 627 2127",
    "sg:postcode":"H7R 3X9",
    "sg:province":"QC",
    "sg:tags":[
        "contractor"
    ],
    "wof:name":"Plomberie Normand Poirier Inc",
    "wof:placetype":"venue"
},
  "geometry": {"coordinates":[-73.8605880737,45.543674469],"type":"Point"}
}