{
  "type": "Feature",
  "properties": {
    "iso:country":"CA",
    "sg:city":"Sainte-Julie",
    "sg:classifiers":[
        {
            "category":"Retail",
            "subcategory":"Veterinary Services",
            "type":"Services"
        }
    ],
    "sg:phone":"+1 450 922 1203",
    "sg:postcode":"J3E 1W7",
    "sg:province":"QC",
    "sg:tags":[
        "veterinarian"
    ],
    "wof:name":"Clinique Veterinaire Ste-Julie",
    "wof:placetype":"venue"
},
  "geometry": {"coordinates":[-73.33930206300001,45.5937194824],"type":"Point"}
}