{
  "type": "Feature",
  "properties": {
    "addr:full":"511 Rue Ouimet Saint-Jerome QC J7Z 1P8",
    "addr:housenumber":"511",
    "addr:postcode":"j7z 1p8",
    "addr:street":"Rue Ouimet Saint-Jerome",
    "iso:country":"CA",
    "sg:address":"511 Rue Ouimet",
    "sg:city":"Saint-Jerome",
    "sg:classifiers":[
        {
            "category":"Food & Beverages",
            "subcategory":"Groceries & Convenience Stores",
            "type":"Retail Goods"
        }
    ],
    "sg:phone":"+1 450 436 8882",
    "sg:postcode":"J7Z 1P8",
    "sg:province":"QC",
    "wof:name":"Depanneur Boyer Ltee",
    "wof:placetype":"venue"
},
  "geometry": {"coordinates":[-73.992958,45.783821],"type":"Point"}
}