{
  "type": "Feature",
  "properties": {
    "addr:full":"850 Blanshard St Victoria BC V8W 2H2",
    "addr:housenumber":"850",
    "addr:postcode":"v8w 2h2",
    "addr:street":"Blanshard St",
    "iso:country":"CA",
    "sg:address":"850 Blanshard St",
    "sg:city":"Victoria",
    "sg:classifiers":[
        {
            "category":"Travel",
            "subcategory":"Hotels & Motels",
            "type":"Entertainment"
        }
    ],
    "sg:phone":"+1 250 385 6787",
    "sg:postcode":"V8W 2H2",
    "sg:province":"BC",
    "wof:name":"Quality Inn & Downtown",
    "wof:placetype":"venue"
},
  "geometry": {"coordinates":[-123.36316680900001,48.4223594666],"type":"Point"}
}