{
  "type": "Feature",
  "properties": {
    "addr:full":"24 Lindway Pl Lindsay ON K9V 6A2",
    "addr:housenumber":"24",
    "addr:postcode":"k9v 6a2",
    "addr:street":"Lindway Pl",
    "iso:country":"CA",
    "sg:address":"24 Lindway Pl",
    "sg:city":"Lindsay",
    "sg:classifiers":[
        {
            "category":"Real Estate",
            "subcategory":"Real Estate Agent",
            "type":"Services"
        }
    ],
    "sg:phone":"+1 705 324 2411",
    "sg:postcode":"K9V 6A2",
    "sg:province":"ON",
    "sg:tags":[
        "appraiser"
    ],
    "wof:name":"B L Hodgson & Assoc",
    "wof:placetype":"venue"
},
  "geometry": {"coordinates":[-78.748276,44.363567],"type":"Point"}
}