{
  "type": "Feature",
  "properties": {
    "addr:full":"275 Duke Ave Portage LA Prairie MB R1N 0S5",
    "addr:housenumber":"275",
    "addr:postcode":"r1n 0s5",
    "addr:street":"Duke Ave",
    "iso:country":"CA",
    "sg:address":"275 Duke Ave",
    "sg:city":"Portage LA Prairie",
    "sg:classifiers":[
        {
            "category":"Organizations",
            "subcategory":"Community Association",
            "type":"Services"
        }
    ],
    "sg:phone":"+1 204 857 5558",
    "sg:postcode":"R1N 0S5",
    "sg:province":"MB",
    "sg:tags":[
        "club"
    ],
    "wof:name":"Royal Canadian Legion",
    "wof:placetype":"venue"
},
  "geometry": {"coordinates":[-98.2868652344,49.9715080261],"type":"Point"}
}