{
  "type": "Feature",
  "properties": {
    "addr:full":"Quebec QC G1S 2P1",
    "addr:postcode":"g1s 2p1",
    "iso:country":"CA",
    "sg:city":"Quebec",
    "sg:classifiers":[
        {
            "category":"Professional",
            "subcategory":"Business Services",
            "type":"Services"
        }
    ],
    "sg:phone":"+1 418 681 8005",
    "sg:postcode":"G1S 2P1",
    "sg:province":"QC",
    "sg:tags":[
        "notary"
    ],
    "wof:name":"Michaud & Chouinard",
    "wof:placetype":"venue"
},
  "geometry": {"coordinates":[-71.25852966310001,46.7926902771],"type":"Point"}
}