{
  "type": "Feature",
  "properties": {
    "addr:full":"501 King St Welland ON L3B 3K4",
    "addr:housenumber":"501",
    "addr:postcode":"l3b 3k4",
    "addr:street":"King St",
    "iso:country":"CA",
    "sg:address":"501 King St",
    "sg:city":"Welland",
    "sg:classifiers":[
        {
            "category":"Recreation",
            "type":"Entertainment"
        }
    ],
    "sg:phone":"+1 905 788 2627",
    "sg:postcode":"L3B 3K4",
    "sg:province":"ON",
    "sg:tags":[
        "skating",
        "instruction"
    ],
    "wof:name":"Welland Figure Skating Club",
    "wof:placetype":"venue"
},
  "geometry": {"coordinates":[-79.2514419556,42.9803237915],"type":"Point"}
}