{
  "type": "Feature",
  "properties": {
    "addr:full":"1155 Bruce Road 12 Formosa ON N0G 1W0",
    "addr:housenumber":"1155",
    "addr:postcode":"n0g 1w0",
    "addr:street":"Bruce Road 12",
    "iso:country":"CA",
    "sg:address":"1155 Bruce Road 12",
    "sg:city":"Formosa",
    "sg:classifiers":[
        {
            "category":"Real Estate",
            "subcategory":"Real Estate Operator",
            "type":"Services"
        }
    ],
    "sg:phone":"+1 519 367 5499",
    "sg:postcode":"N0G 1W0",
    "sg:province":"ON",
    "sg:tags":[
        "apartment"
    ],
    "wof:name":"Valley View Terrace Seniors",
    "wof:placetype":"venue"
},
  "geometry": {"coordinates":[-81.2140960693,44.0670166016],"type":"Point"}
}