{
  "type": "Feature",
  "properties": {
    "iso:country":"CA",
    "sg:address":"6600 Rue Bombardier",
    "sg:city":"Saint-Leonard",
    "sg:classifiers":[
        {
            "category":"Retail",
            "subcategory":"Auto Repair",
            "type":"Services"
        }
    ],
    "sg:phone":"+1 514 598 0325",
    "sg:postcode":"H1P 1E4",
    "sg:province":"QC",
    "sg:tags":[
        "body",
        "automobile",
        "painting"
    ],
    "wof:name":"Placements Rite Inc",
    "wof:placetype":"venue"
},
  "geometry": {"coordinates":[-73.591988,45.601494],"type":"Point"}
}