{
  "type": "Feature",
  "properties": {
    "addr:full":"Surrey BC V3W 4E6",
    "addr:postcode":"v3w 4e6",
    "iso:country":"CA",
    "sg:city":"Surrey",
    "sg:classifiers":[
        {
            "category":"Building & Trades",
            "subcategory":"Construction",
            "type":"Services"
        }
    ],
    "sg:phone":"+1 604 597 0364",
    "sg:postcode":"V3W 4E6",
    "sg:province":"BC",
    "sg:tags":[
        "maker",
        "cabinet"
    ],
    "wof:name":"Sunrise Kitchens Ltd",
    "wof:placetype":"venue"
},
  "geometry": {"coordinates":[-122.868148804,49.1431770325],"type":"Point"}
}