{
  "type": "Feature",
  "properties": {
    "iso:country":"CA",
    "sg:address":"PO Box 336",
    "sg:city":"LA Crete",
    "sg:classifiers":[
        {
            "category":"Farming",
            "subcategory":"Farm & Veterinary Services",
            "type":"Manufacturing & Wholesale Goods"
        }
    ],
    "sg:phone":"+1 780 928 3042",
    "sg:postcode":"T0H 2H0",
    "sg:province":"AB",
    "sg:tags":[
        "seed",
        "grain",
        "cleaning"
    ],
    "wof:name":"Frontier Seed Cleaning CO-OP",
    "wof:placetype":"venue"
},
  "geometry": {"coordinates":[-116.397781,58.195358],"type":"Point"}
}