{
  "type": "Feature",
  "properties": {
    "iso:country":"CA",
    "sg:address":"7012 Rue Saint-Hubert",
    "sg:city":"Montreal",
    "sg:classifiers":[
        {
            "category":"Shopping",
            "subcategory":"Clothing, Apparel, & Fashions",
            "type":"Retail Goods"
        }
    ],
    "sg:phone":"+1 514 270 0806",
    "sg:postcode":"H2S 2M9",
    "sg:province":"QC",
    "wof:name":"Modes Kadoch",
    "wof:placetype":"venue"
},
  "geometry": {"coordinates":[-73.611191,45.539661],"type":"Point"}
}