{
  "type": "Feature",
  "properties": {
    "addr:full":"30 Rue Victoria Shediac NB E4P 2W7",
    "addr:housenumber":"30",
    "addr:postcode":"e4p 2w7",
    "addr:street":"Rue Victoria",
    "iso:country":"CA",
    "sg:address":"30 Rue Victoria",
    "sg:city":"Shediac",
    "sg:classifiers":[
        {
            "category":"Shopping",
            "subcategory":"Crafts & Fabrics",
            "type":"Retail Goods"
        }
    ],
    "sg:phone":"+1 506 532 5388",
    "sg:postcode":"E4P 2W7",
    "sg:province":"NB",
    "sg:tags":[
        "shop"
    ],
    "wof:name":"Turbide & Leger Ltee",
    "wof:placetype":"venue"
},
  "geometry": {"coordinates":[-64.54115299999999,46.218685],"type":"Point"}
}