{
  "type": "Feature",
  "properties": {
    "iso:country":"CA",
    "sg:city":"Mississauga",
    "sg:classifiers":[
        {
            "category":"Shopping",
            "subcategory":"Clothing, Apparel, & Fashions",
            "type":"Retail Goods"
        }
    ],
    "sg:phone":"+1 905 897 2010",
    "sg:postcode":"L4Y 4H5",
    "sg:province":"ON",
    "sg:tags":[
        "uniform"
    ],
    "wof:name":"Anthony's Uniform Shops",
    "wof:placetype":"venue"
},
  "geometry": {"coordinates":[-79.5937423706,43.6001243591],"type":"Point"}
}