{
  "type": "Feature",
  "properties": {
    "addr:full":"205 Frobisher Dr Waterloo ON N2V 2G4",
    "addr:housenumber":"205",
    "addr:postcode":"n2v 2g4",
    "addr:street":"Frobisher Dr",
    "iso:country":"CA",
    "sg:address":"205 Frobisher Dr",
    "sg:city":"Waterloo",
    "sg:classifiers":[
        {
            "category":"Wholesale",
            "subcategory":"Durable Goods & Equipment",
            "type":"Manufacturing & Wholesale Goods"
        }
    ],
    "sg:phone":"+1 519 886 5010",
    "sg:postcode":"N2V 2G4",
    "sg:province":"ON",
    "sg:tags":[
        "importer"
    ],
    "wof:name":"Donald Choi Canada Ltd",
    "wof:placetype":"venue"
},
  "geometry": {"coordinates":[-80.52467346189999,43.5095672607],"type":"Point"}
}