{
  "type": "Feature",
  "properties": {
    "iso:country":"CA",
    "sg:city":"London",
    "sg:classifiers":[
        {
            "category":"Health Services",
            "subcategory":"Clinic",
            "type":"Services"
        }
    ],
    "sg:phone":"+1 519 668 2997",
    "sg:postcode":"N6E 1N9",
    "sg:province":"ON",
    "sg:tags":[
        "home"
    ],
    "wof:name":"St Elizabeth Health Care",
    "wof:placetype":"venue"
},
  "geometry": {"coordinates":[-81.22035980219999,42.9335861206],"type":"Point"}
}