{
  "type": "Feature",
  "properties": {
    "addr:full":"10330 Ch DE LA Cote-DE-Liesse Lachine QC H8T 1A3",
    "addr:housenumber":"10330",
    "addr:postcode":"h8t 1a3",
    "addr:street":"Ch De La Cote-De-Liesse",
    "iso:country":"CA",
    "sg:address":"10330 Ch DE LA Cote-DE-Liesse",
    "sg:city":"Lachine",
    "sg:classifiers":[
        {
            "category":"Shopping",
            "subcategory":"Music",
            "type":"Retail Goods"
        }
    ],
    "sg:phone":"+1 514 631 9072",
    "sg:postcode":"H8T 1A3",
    "sg:province":"QC",
    "sg:tags":[
        "compact",
        "record",
        "disc",
        "tape"
    ],
    "wof:name":"Capitol Records-Emi of Canada",
    "wof:placetype":"venue"
},
  "geometry": {"coordinates":[-73.718147,45.46537],"type":"Point"}
}