{
  "type": "Feature",
  "properties": {
    "addr:full":"7200 Boul Jean-Xxiii Trois-Rivieres-Ouest QC G9A 5C9",
    "addr:housenumber":"7200",
    "addr:postcode":"g9a 5c9",
    "addr:street":"Boul Jean-Xxiii Trois-Rivieres-Ouest",
    "iso:country":"CA",
    "sg:address":"7200 Boul Jean-Xxiii",
    "sg:city":"Trois-Rivieres-Ouest",
    "sg:classifiers":[
        {
            "category":"Professional",
            "subcategory":"Detective & Security Services",
            "type":"Services"
        }
    ],
    "sg:phone":"+1 819 377 6272",
    "sg:postcode":"G9A 5C9",
    "sg:province":"QC",
    "sg:tags":[
        "burglary",
        "protective",
        "robbery"
    ],
    "wof:name":"Alarmes Mauriciennes",
    "wof:placetype":"venue"
},
  "geometry": {"coordinates":[-72.60217299999999,46.323009],"type":"Point"}
}