{
  "type": "Feature",
  "properties": {
    "addr:full":"134 Deer Park Cir London ON N6H 3B6",
    "addr:housenumber":"134",
    "addr:postcode":"n6h 3b6",
    "addr:street":"Deer Park Cir",
    "iso:country":"CA",
    "sg:address":"134 Deer Park Cir",
    "sg:city":"London",
    "sg:classifiers":[
        {
            "category":"Professional",
            "subcategory":"Accounting & Tax Preparation",
            "type":"Services"
        }
    ],
    "sg:phone":"+1 519 670 4731",
    "sg:postcode":"N6H 3B6",
    "sg:province":"ON",
    "sg:tags":[
        "bookkeeping",
        "general"
    ],
    "wof:name":"Complete Bookkeeping Svc",
    "wof:placetype":"venue"
},
  "geometry": {"coordinates":[-81.307068,42.97834],"type":"Point"}
}