{
  "type": "Feature",
  "properties": {
    "addr:full":"23B Bradley St Membertou NS B1S 3P5",
    "addr:housenumber":"23b",
    "addr:postcode":"b1s 3p5",
    "addr:street":"Bradley St",
    "iso:country":"CA",
    "sg:address":"23B Bradley St",
    "sg:city":"Membertou",
    "sg:classifiers":[
        {
            "category":"Recreation",
            "type":"Entertainment"
        }
    ],
    "sg:phone":"+1 902 564 3340",
    "sg:postcode":"B1S 3P5",
    "sg:province":"NS",
    "sg:tags":[
        "parlor",
        "billiard"
    ],
    "wof:name":"Membertou Billards",
    "wof:placetype":"venue"
},
  "geometry": {"coordinates":[-60.1896057129,46.1138038635],"type":"Point"}
}