{
  "type": "Feature",
  "properties": {
    "addr:full":"4926 50 St Killam AB T0B 2L0",
    "addr:housenumber":"4926",
    "addr:postcode":"t0b 2l0",
    "addr:street":"50 St",
    "iso:country":"CA",
    "sg:address":"4926 50 St",
    "sg:city":"Killam",
    "sg:classifiers":[
        {
            "category":"Wholesale",
            "subcategory":"Scrap",
            "type":"Manufacturing & Wholesale Goods"
        }
    ],
    "sg:phone":"+1 780 385 3036",
    "sg:postcode":"T0B 2L0",
    "sg:province":"AB",
    "sg:tags":[
        "recycling",
        "can",
        "bottle",
        "depot"
    ],
    "wof:name":"Killam Bottle Depot",
    "wof:placetype":"venue"
},
  "geometry": {"coordinates":[-111.85580400000001,52.790222],"type":"Point"}
}