{
  "type": "Feature",
  "properties": {
    "addr:full":"807 1st Ave W Meadow Lake SK S9X 1N2",
    "addr:housenumber":"807",
    "addr:postcode":"s9x 1n2",
    "addr:street":"1St Ave W Meadow",
    "iso:country":"CA",
    "sg:address":"807 1st Ave W",
    "sg:city":"Meadow Lake",
    "sg:classifiers":[
        {
            "category":"Autos & Motor Vehicles",
            "subcategory":"Auto Supplies",
            "type":"Retail Goods"
        }
    ],
    "sg:phone":"+1 306 236 4800",
    "sg:postcode":"S9X 1N2",
    "sg:province":"SK",
    "sg:tags":[
        "automobile",
        "parts"
    ],
    "wof:name":"Uap Napa Auto Parts",
    "wof:placetype":"venue"
},
  "geometry": {"coordinates":[-108.448807,54.133408],"type":"Point"}
}