{
  "type": "Feature",
  "properties": {
    "addr:full":"162 April Rd Port Moody BC V3H 3M6",
    "addr:housenumber":"162",
    "addr:postcode":"v3h 3m6",
    "addr:street":"April Rd",
    "iso:country":"CA",
    "sg:address":"162 April Rd",
    "sg:city":"Port Moody",
    "sg:classifiers":[
        {
            "category":"Social Services",
            "subcategory":"Job Training",
            "type":"Services"
        }
    ],
    "sg:phone":"+1 604 469 5444",
    "sg:postcode":"V3H 3M6",
    "sg:province":"BC",
    "sg:tags":[
        "rehabilitation"
    ],
    "wof:name":"Martin Disability Management",
    "wof:placetype":"venue"
},
  "geometry": {"coordinates":[-122.860374451,49.3003082275],"type":"Point"}
}