{
  "type": "Feature",
  "properties": {
    "addr:full":"Armagh QC G0R 1A0",
    "addr:postcode":"g0r 1a0",
    "iso:country":"CA",
    "sg:city":"Armagh",
    "sg:classifiers":[
        {
            "category":"Retail",
            "subcategory":"Auto Repair",
            "type":"Services"
        }
    ],
    "sg:phone":"+1 418 466 2244",
    "sg:postcode":"G0R 1A0",
    "sg:province":"QC",
    "sg:tags":[
        "repairing",
        "automobile"
    ],
    "wof:name":"Alignement Jean Fradet Enr",
    "wof:placetype":"venue"
},
  "geometry": {"coordinates":[-70.60865020750001,46.7427520752],"type":"Point"}
}