{
  "type": "Feature",
  "properties": {
    "addr:full":"Waterloo QC J0E 2N0",
    "addr:postcode":"j0e 2n0",
    "iso:country":"CA",
    "sg:city":"Waterloo",
    "sg:classifiers":[
        {
            "category":"Home & Garden",
            "subcategory":"Building Materials",
            "type":"Retail Goods"
        }
    ],
    "sg:phone":"+1 450 539 0595",
    "sg:postcode":"J0E 2N0",
    "sg:province":"QC",
    "sg:tags":[
        "door"
    ],
    "wof:name":"Menuiserie Bachand & Fils Inc",
    "wof:placetype":"venue"
},
  "geometry": {"coordinates":[-72.52372,45.343155],"type":"Point"}
}