{
  "type": "Feature",
  "properties": {
    "addr:full":"1795 Boul Wilfrid-Hamel Quebec QC G1N 3Y9",
    "addr:housenumber":"1795",
    "addr:postcode":"g1n 3y9",
    "addr:street":"Boul Wilfrid-Hamel",
    "iso:country":"CA",
    "sg:address":"1795 Boul Wilfrid-Hamel",
    "sg:city":"Quebec",
    "sg:classifiers":[
        {
            "category":"Personal",
            "subcategory":"Massage",
            "type":"Services"
        }
    ],
    "sg:phone":"+1 418 682 5418",
    "sg:postcode":"G1N 3Y9",
    "sg:province":"QC",
    "wof:name":"Centre Idem",
    "wof:placetype":"venue"
},
  "geometry": {"coordinates":[-71.281952,46.805607],"type":"Point"}
}