{
  "type": "Feature",
  "properties": {
    "addr:full":"820 North Talbot Rd Windsor ON N9G 1M7",
    "addr:housenumber":"820",
    "addr:postcode":"n9g 1m7",
    "addr:street":"North Talbot Rd",
    "iso:country":"CA",
    "sg:address":"820 North Talbot Rd",
    "sg:city":"Windsor",
    "sg:classifiers":[
        {
            "category":"Building & Trades",
            "subcategory":"Landscaping Services",
            "type":"Services"
        }
    ],
    "sg:phone":"+1 519 969 0570",
    "sg:postcode":"N9G 1M7",
    "sg:province":"ON",
    "sg:tags":[
        "center",
        "garden",
        "landscape",
        "contractor"
    ],
    "wof:name":"Orchard Farm Nursery Ltd",
    "wof:placetype":"venue"
},
  "geometry": {"coordinates":[-82.9869766235,42.2445755005],"type":"Point"}
}