{
  "type": "Feature",
  "properties": {
    "addr:full":"1407 Boul Des Laurentides Vimont QC H7M 2Y2",
    "addr:housenumber":"1407",
    "addr:postcode":"h7m 2y2",
    "addr:street":"Boul Des Laurentides",
    "iso:country":"CA",
    "sg:address":"1407 Boul Des Laurentides",
    "sg:city":"Vimont",
    "sg:classifiers":[
        {
            "category":"Bars & Pubs",
            "type":"Food & Drink"
        }
    ],
    "sg:phone":"+1 450 663 1390",
    "sg:postcode":"H7M 2Y2",
    "sg:province":"QC",
    "sg:tags":[
        "lounge",
        "cocktail"
    ],
    "wof:name":"Champion Bar",
    "wof:placetype":"venue"
},
  "geometry": {"coordinates":[-73.7119598389,45.5880470276],"type":"Point"}
}