{
  "type": "Feature",
  "properties": {
    "addr:full":"301 Ch Mailloux LA Malbaie QC G5A 1G3",
    "addr:housenumber":"301",
    "addr:postcode":"g5a 1g3",
    "addr:street":"Ch Mailloux",
    "iso:country":"CA",
    "sg:address":"301 Ch Mailloux",
    "sg:city":"LA Malbaie",
    "sg:classifiers":[
        {
            "category":"Shopping",
            "subcategory":"Clothing, Apparel, & Fashions",
            "type":"Retail Goods"
        }
    ],
    "sg:phone":"+1 418 665 7955",
    "sg:postcode":"G5A 1G3",
    "sg:province":"QC",
    "sg:tags":[
        "dressmaker",
        "infant"
    ],
    "wof:name":"Au Fil Des Fantaisies Re",
    "wof:placetype":"venue"
},
  "geometry": {"coordinates":[-70.19255800000001,47.646927],"type":"Point"}
}