{
  "type": "Feature",
  "properties": {
    "addr:full":"42 George St Brockville ON K6V 3V5",
    "addr:housenumber":"42",
    "addr:postcode":"k6v 3v5",
    "addr:street":"George St",
    "iso:country":"CA",
    "sg:address":"42 George St",
    "sg:city":"Brockville",
    "sg:classifiers":[
        {
            "category":"Social Services",
            "type":"Services"
        }
    ],
    "sg:phone":"+1 613 342 7040",
    "sg:postcode":"K6V 3V5",
    "sg:province":"ON",
    "sg:tags":[
        "organization",
        "welfare"
    ],
    "wof:name":"Volunteer Bureau",
    "wof:placetype":"venue"
},
  "geometry": {"coordinates":[-75.6874847412,44.5891418457],"type":"Point"}
}