{
  "type": "Feature",
  "properties": {
    "addr:full":"Belleville ON K8N 2Y9",
    "addr:postcode":"k8n 2y9",
    "iso:country":"CA",
    "sg:city":"Belleville",
    "sg:classifiers":[
        {
            "category":"Professional",
            "subcategory":"Lawyer & Legal Services",
            "type":"Services"
        }
    ],
    "sg:phone":"+1 613 966 3031",
    "sg:postcode":"K8N 2Y9",
    "sg:province":"ON",
    "sg:tags":[
        "attorney"
    ],
    "wof:name":"Leitch, Sharon A",
    "wof:placetype":"venue"
},
  "geometry": {"coordinates":[-77.38367462159999,44.1631774902],"type":"Point"}
}