{
  "type": "Feature",
  "properties": {
    "iso:country":"CA",
    "sg:address":"171 Bank St",
    "sg:city":"Ottawa",
    "sg:classifiers":[
        {
            "category":"Shopping",
            "subcategory":"Luggage & Leather Goods",
            "type":"Retail Goods"
        }
    ],
    "sg:phone":"+1 613 232 1662",
    "sg:postcode":"K2P 1W5",
    "sg:province":"ON",
    "wof:name":"Bentley Leather",
    "wof:placetype":"venue"
},
  "geometry": {"coordinates":[-75.69872283940001,45.4183654785],"type":"Point"}
}