{
  "type": "Feature",
  "properties": {
    "addr:full":"1906 Casey Rd Belleville ON K8N 4Z6",
    "addr:housenumber":"1906",
    "addr:postcode":"k8n 4z6",
    "addr:street":"Casey Rd",
    "iso:country":"CA",
    "sg:address":"1906 Casey Rd",
    "sg:city":"Belleville",
    "sg:classifiers":[
        {
            "category":"Retail",
            "subcategory":"Repair Shop",
            "type":"Services"
        }
    ],
    "sg:phone":"+1 613 966 5582",
    "sg:postcode":"K8N 4Z6",
    "sg:province":"ON",
    "sg:tags":[
        "welding"
    ],
    "wof:name":"Sherman Welding & Machine",
    "wof:placetype":"venue"
},
  "geometry": {"coordinates":[-77.280106,44.239792],"type":"Point"}
}