{
  "type": "Feature",
  "properties": {
    "addr:full":"12851 16 Ave Surrey BC V4A 1N5",
    "addr:housenumber":"12851",
    "addr:postcode":"v4a 1n5",
    "addr:street":"16 Ave",
    "iso:country":"CA",
    "sg:address":"12851 16 Ave",
    "sg:city":"Surrey",
    "sg:classifiers":[
        {
            "category":"Shopping",
            "subcategory":"Pharmacy",
            "type":"Retail Goods"
        }
    ],
    "sg:phone":"+1 604 536 7611",
    "sg:postcode":"V4A 1N5",
    "sg:province":"BC",
    "wof:name":"Pharmasave Drugs",
    "wof:placetype":"venue"
},
  "geometry": {"coordinates":[-122.865783691,49.0314865112],"type":"Point"}
}