{
  "type": "Feature",
  "properties": {
    "addr:full":"1167 Rue Principale E Sainte-Agathe-Des-Monts QC J8C 1L7",
    "addr:housenumber":"1167",
    "addr:postcode":"j8c 1l7",
    "addr:street":"Rue Principale E Sainte-Agathe-Des-Monts",
    "iso:country":"CA",
    "sg:address":"1167 Rue Principale E",
    "sg:city":"Sainte-Agathe-Des-Monts",
    "sg:classifiers":[
        {
            "category":"Retail",
            "subcategory":"Repair Shop",
            "type":"Services"
        }
    ],
    "sg:phone":"+1 819 324 0307",
    "sg:postcode":"J8C 1L7",
    "sg:province":"QC",
    "sg:tags":[
        "upholsterer"
    ],
    "wof:name":"Michel L'Artisan Rembourreur",
    "wof:placetype":"venue"
},
  "geometry": {"coordinates":[-74.262398,46.042648],"type":"Point"}
}