{
  "type": "Feature",
  "properties": {
    "addr:full":"176 Bobcaygeon Rd N Minden ON K0M 2K0",
    "addr:housenumber":"176",
    "addr:postcode":"k0m 2k0",
    "addr:street":"Bobcaygeon Rd N",
    "iso:country":"CA",
    "sg:address":"176 Bobcaygeon Rd N",
    "sg:city":"Minden",
    "sg:classifiers":[
        {
            "category":"Government",
            "subcategory":"Office",
            "type":"Public Place"
        }
    ],
    "sg:phone":"+1 705 286 3763",
    "sg:postcode":"K0M 2K0",
    "sg:province":"ON",
    "sg:tags":[
        "village"
    ],
    "wof:name":"Agnes Jamieson Gallery",
    "wof:placetype":"venue"
},
  "geometry": {"coordinates":[-78.72654,44.927696],"type":"Point"}
}