{
  "type": "Feature",
  "properties": {
    "addr:full":"22 Second St Elmira ON N3B 1H2",
    "addr:housenumber":"22",
    "addr:postcode":"n3b 1h2",
    "addr:street":"Second St",
    "iso:country":"CA",
    "sg:address":"22 Second St",
    "sg:city":"Elmira",
    "sg:classifiers":[
        {
            "category":"Building & Trades",
            "subcategory":"Construction",
            "type":"Services"
        }
    ],
    "sg:phone":"+1 519 669 1217",
    "sg:postcode":"N3B 1H2",
    "sg:province":"ON",
    "sg:tags":[
        "home",
        "improvement"
    ],
    "wof:name":"Rpm Construction",
    "wof:placetype":"venue"
},
  "geometry": {"coordinates":[-80.567108,43.593746],"type":"Point"}
}