{
  "type": "Feature",
  "properties": {
    "addr:full":"3535 Research Rd NW Calgary AB T2L 2K8",
    "addr:housenumber":"3535",
    "addr:postcode":"t2l 2k8",
    "addr:street":"Research Rd Nw",
    "iso:country":"CA",
    "sg:address":"3535 Research Rd NW",
    "sg:city":"Calgary",
    "sg:classifiers":[
        {
            "category":"Mining & Drilling",
            "type":"Manufacturing & Wholesale Goods"
        }
    ],
    "sg:phone":"+1 403 284 7400",
    "sg:postcode":"T2L 2K8",
    "sg:province":"AB",
    "sg:tags":[
        "company",
        "oil"
    ],
    "wof:name":"Imperial Oil Resources Ltd",
    "wof:placetype":"venue"
},
  "geometry": {"coordinates":[-114.135391235,51.0863685608],"type":"Point"}
}