{
  "type": "Feature",
  "properties": {
    "addr:full":"14700 Boul Becancour Becancour QC G9H 2L4",
    "addr:housenumber":"14700",
    "addr:postcode":"g9h 2l4",
    "addr:street":"Boul Becancour Becancour",
    "iso:country":"CA",
    "sg:address":"14700 Boul Becancour",
    "sg:city":"Becancour",
    "sg:classifiers":[
        {
            "category":"Education",
            "subcategory":"Library",
            "type":"Public Place"
        }
    ],
    "sg:phone":"+1 819 222 5735",
    "sg:postcode":"G9H 2L4",
    "sg:province":"QC",
    "wof:name":"Ste-Angele-DE-Laval Bibliotheq",
    "wof:placetype":"venue"
},
  "geometry": {"coordinates":[-72.512466,46.333111],"type":"Point"}
}