{
  "type": "Feature",
  "properties": {
    "addr:full":"7727 Edmonds St Burnaby BC V3N 1B9",
    "addr:housenumber":"7727",
    "addr:postcode":"v3n 1b9",
    "addr:street":"Edmonds St",
    "iso:country":"CA",
    "sg:address":"7727 Edmonds St",
    "sg:city":"Burnaby",
    "sg:classifiers":[
        {
            "category":"Health Services",
            "subcategory":"Medical Lab",
            "type":"Services"
        }
    ],
    "sg:phone":"+1 604 522 7337",
    "sg:postcode":"V3N 1B9",
    "sg:province":"BC",
    "sg:tags":[
        "laboratory"
    ],
    "wof:name":"Correct Dental Laboratory Ltd",
    "wof:placetype":"venue"
},
  "geometry": {"coordinates":[-122.940345764,49.2246208191],"type":"Point"}
}