{
  "type": "Feature",
  "properties": {
    "addr:full":"Hamilton ON L8W 2C6",
    "addr:postcode":"l8w 2c6",
    "iso:country":"CA",
    "sg:city":"Hamilton",
    "sg:classifiers":[
        {
            "category":"Food & Beverages",
            "subcategory":"Bakery",
            "type":"Retail Goods"
        }
    ],
    "sg:phone":"+1 905 383 8544",
    "sg:postcode":"L8W 2C6",
    "sg:province":"ON",
    "sg:tags":[
        "doughnut"
    ],
    "wof:name":"Donut Diner",
    "wof:placetype":"venue"
},
  "geometry": {"coordinates":[-79.833595,43.197701],"type":"Point"}
}