{
  "type": "Feature",
  "properties": {
    "addr:full":"1377 Pemberton Ave North Vancouver BC V7P 2R6",
    "addr:housenumber":"1377",
    "addr:postcode":"v7p 2r6",
    "addr:street":"Pemberton Ave",
    "iso:country":"CA",
    "sg:address":"1377 Pemberton Ave",
    "sg:city":"North Vancouver",
    "sg:classifiers":[
        {
            "category":"Professional",
            "subcategory":"Computer Services",
            "type":"Services"
        }
    ],
    "sg:phone":"+1 604 987 2242",
    "sg:postcode":"V7P 2R6",
    "sg:province":"BC",
    "wof:name":"Norocom",
    "wof:placetype":"venue"
},
  "geometry": {"coordinates":[-123.108002,49.320938],"type":"Point"}
}