{
  "type": "Feature",
  "properties": {
    "iso:country":"CA",
    "sg:city":"Caraquet",
    "sg:classifiers":[
        {
            "category":"Personal",
            "subcategory":"Beauty Salon",
            "type":"Services"
        }
    ],
    "sg:phone":"+1 506 727 2038",
    "sg:postcode":"E1W 1B3",
    "sg:province":"NB",
    "wof:name":"Salon Chez Pierrette",
    "wof:placetype":"venue"
},
  "geometry": {"coordinates":[-64.95227050779999,47.7910690308],"type":"Point"}
}