{
  "type": "Feature",
  "properties": {
    "addr:full":"Winnipeg MB R3C 4K5",
    "addr:postcode":"r3c 4k5",
    "iso:country":"CA",
    "sg:city":"Winnipeg",
    "sg:classifiers":[
        {
            "category":"Banks & Credit Unions",
            "subcategory":"Investment Brokerage",
            "type":"Services"
        }
    ],
    "sg:phone":"+1 204 946 0297",
    "sg:postcode":"R3C 4K5",
    "sg:province":"MB",
    "wof:name":"Bieber Securities Inc",
    "wof:placetype":"venue"
},
  "geometry": {"coordinates":[-97.148422,49.889053],"type":"Point"}
}