{
  "type": "Feature",
  "properties": {
    "addr:full":"Markham ON L3R 1C9",
    "addr:postcode":"l3r 1c9",
    "iso:country":"CA",
    "sg:city":"Markham",
    "sg:classifiers":[
        {
            "category":"Building & Trades",
            "subcategory":"Plumbing",
            "type":"Services"
        }
    ],
    "sg:phone":"+1 905 475 3000",
    "sg:postcode":"L3R 1C9",
    "sg:province":"ON",
    "sg:tags":[
        "air",
        "conditioning",
        "contractor",
        "system",
        "heating"
    ],
    "wof:name":"Sig Mechanical Svc Ltd",
    "wof:placetype":"venue"
},
  "geometry": {"coordinates":[-79.34569500000001,43.82692],"type":"Point"}
}