{
  "type": "Feature",
  "properties": {
    "addr:full":"Kingston ON K7M 8L9",
    "addr:postcode":"k7m 8l9",
    "iso:country":"CA",
    "sg:city":"Kingston",
    "sg:classifiers":[
        {
            "category":"Retail",
            "subcategory":"Funeral Services",
            "type":"Services"
        }
    ],
    "sg:phone":"+1 613 546 0335",
    "sg:postcode":"K7M 8L9",
    "sg:province":"ON",
    "sg:tags":[
        "director",
        "plan"
    ],
    "wof:name":"Frontenac Cremation Svc",
    "wof:placetype":"venue"
},
  "geometry": {"coordinates":[-76.557709,44.25148],"type":"Point"}
}