{
  "type": "Feature",
  "properties": {
    "addr:full":"41 Skyridge Ave Lower Sackville NS B4C 1P8",
    "addr:housenumber":"41",
    "addr:postcode":"b4c 1p8",
    "addr:street":"Skyridge Ave",
    "iso:country":"CA",
    "sg:address":"41 Skyridge Ave",
    "sg:city":"Lower Sackville",
    "sg:classifiers":[
        {
            "category":"Health Services",
            "subcategory":"Doctor",
            "type":"Services"
        }
    ],
    "sg:phone":"+1 902 865 0151",
    "sg:postcode":"B4C 1P8",
    "sg:province":"NS",
    "sg:tags":[
        "dentist"
    ],
    "wof:name":"Skyridge Dental Office",
    "wof:placetype":"venue"
},
  "geometry": {"coordinates":[-63.671131134,44.7618141174],"type":"Point"}
}