{
  "type": "Feature",
  "properties": {
    "addr:full":"1622 96th St North Battleford SK S9A 0H6",
    "addr:housenumber":"1622",
    "addr:postcode":"s9a 0h6",
    "addr:street":"96Th St",
    "iso:country":"CA",
    "sg:address":"1622 96th St",
    "sg:city":"North Battleford",
    "sg:classifiers":[
        {
            "category":"Education",
            "subcategory":"Dance Studio",
            "type":"Public Place"
        }
    ],
    "sg:phone":"+1 306 446 6226",
    "sg:postcode":"S9A 0H6",
    "sg:province":"SK",
    "sg:tags":[
        "instruction",
        "dancing"
    ],
    "wof:name":"Dance Connection",
    "wof:placetype":"venue"
},
  "geometry": {"coordinates":[-108.304695,52.781628],"type":"Point"}
}