{
  "type": "Feature",
  "properties": {
    "addr:full":"795 Balm Beach Rd E Midland ON L4R 4K4",
    "addr:housenumber":"795",
    "addr:postcode":"l4r 4k4",
    "addr:street":"Balm Beach Rd E",
    "iso:country":"CA",
    "sg:address":"795 Balm Beach Rd E",
    "sg:city":"Midland",
    "sg:classifiers":[
        {
            "category":"Food & Beverages",
            "subcategory":"Groceries & Convenience Stores",
            "type":"Retail Goods"
        }
    ],
    "sg:phone":"+1 705 527 4067",
    "sg:postcode":"L4R 4K4",
    "sg:province":"ON",
    "sg:tags":[
        "grocer"
    ],
    "wof:name":"Iga Midland",
    "wof:placetype":"venue"
},
  "geometry": {"coordinates":[-79.90683,44.735527],"type":"Point"}
}