{
  "type": "Feature",
  "properties": {
    "addr:full":"320 4 St S Lethbridge AB T1J 1Z8",
    "addr:housenumber":"320 4",
    "addr:postcode":"t1j 1z8",
    "addr:street":"St S",
    "iso:country":"CA",
    "sg:address":"320 4 St S",
    "sg:city":"Lethbridge",
    "sg:classifiers":[
        {
            "category":"Education",
            "subcategory":"Library",
            "type":"Public Place"
        }
    ],
    "sg:phone":"+1 403 381 5639",
    "sg:postcode":"T1J 1Z8",
    "sg:province":"AB",
    "sg:tags":[
        "government"
    ],
    "wof:name":"Alberta Law Society Library",
    "wof:placetype":"venue"
},
  "geometry": {"coordinates":[-112.84208700000001,49.695293],"type":"Point"}
}