{
  "type": "Feature",
  "properties": {
    "addr:full":"4 Rue Birchwood Sainte-Therese QC J7E 2R9",
    "addr:housenumber":"4",
    "addr:postcode":"j7e 2r9",
    "addr:street":"Rue Birchwood Sainte-Therese",
    "iso:country":"CA",
    "sg:address":"4 Rue Birchwood",
    "sg:city":"Sainte-Therese",
    "sg:classifiers":[
        {
            "category":"Building & Trades",
            "subcategory":"Construction",
            "type":"Services"
        }
    ],
    "sg:phone":"+1 450 434 3477",
    "sg:postcode":"J7E 2R9",
    "sg:province":"QC",
    "sg:tags":[
        "general",
        "contractor"
    ],
    "wof:name":"Couvrette & Assoc Inc",
    "wof:placetype":"venue"
},
  "geometry": {"coordinates":[-73.83631099999999,45.650848],"type":"Point"}
}