{
  "type": "Feature",
  "properties": {
    "addr:full":"Calgary AB T2T 0A3",
    "addr:postcode":"t2t 0a3",
    "iso:country":"CA",
    "sg:city":"Calgary",
    "sg:classifiers":[
        {
            "category":"Professional",
            "subcategory":"Business Services",
            "type":"Services"
        }
    ],
    "sg:phone":"+1 403 245 1703",
    "sg:postcode":"T2T 0A3",
    "sg:province":"AB",
    "wof:name":"Uptown 17 Business Rvtlztn",
    "wof:placetype":"venue"
},
  "geometry": {"coordinates":[-114.082207,51.037941],"type":"Point"}
}