{
  "type": "Feature",
  "properties": {
    "addr:full":"115 Nebo Rd Hamilton ON L8W 2E1",
    "addr:housenumber":"115",
    "addr:postcode":"l8w 2e1",
    "addr:street":"Nebo Rd",
    "iso:country":"CA",
    "sg:address":"115 Nebo Rd",
    "sg:city":"Hamilton",
    "sg:classifiers":[
        {
            "category":"Freight",
            "type":"Transportation"
        }
    ],
    "sg:phone":"+1 905 387 4294",
    "sg:postcode":"L8W 2E1",
    "sg:province":"ON",
    "sg:tags":[
        "mover"
    ],
    "wof:name":"Atw Overseas Moving Ltd",
    "wof:placetype":"venue"
},
  "geometry": {"coordinates":[-79.8362503052,43.1941108704],"type":"Point"}
}