{
  "type": "Feature",
  "properties": {
    "addr:full":"437 Main St N Russell MB R0J 1W0",
    "addr:housenumber":"437",
    "addr:postcode":"r0j 1w0",
    "addr:street":"Main St N",
    "iso:country":"CA",
    "sg:address":"437 Main St N",
    "sg:city":"Russell",
    "sg:classifiers":[
        {
            "category":"Retail",
            "subcategory":"Auto Repair",
            "type":"Services"
        }
    ],
    "sg:phone":"+1 204 773 3082",
    "sg:postcode":"R0J 1W0",
    "sg:province":"MB",
    "sg:tags":[
        "body",
        "automobile",
        "painting"
    ],
    "wof:name":"Clement Autobody",
    "wof:placetype":"venue"
},
  "geometry": {"coordinates":[-101.28801,50.782776],"type":"Point"}
}