{
  "type": "Feature",
  "properties": {
    "addr:full":"7219 104 St NW Edmonton AB T6E 4B8",
    "addr:housenumber":"7219",
    "addr:postcode":"t6e 4b8",
    "addr:street":"104 St Nw",
    "iso:country":"CA",
    "sg:address":"7219 104 St NW",
    "sg:city":"Edmonton",
    "sg:classifiers":[
        {
            "category":"Restaurant",
            "type":"Food & Drink"
        }
    ],
    "sg:phone":"+1 780 438 4646",
    "sg:postcode":"T6E 4B8",
    "sg:province":"AB",
    "wof:name":"Jewel of Kashmir",
    "wof:placetype":"venue"
},
  "geometry": {"coordinates":[-113.49751999999999,53.508705],"type":"Point"}
}