{
  "type": "Feature",
  "properties": {
    "addr:full":"2205 Rue Mousseau Montreal QC H1L 4V2",
    "addr:housenumber":"2205",
    "addr:postcode":"h1l 4v2",
    "addr:street":"Rue Mousseau",
    "iso:country":"CA",
    "sg:address":"2205 Rue Mousseau",
    "sg:city":"Montreal",
    "sg:classifiers":[
        {
            "category":"Education",
            "subcategory":"School",
            "type":"Public Place"
        }
    ],
    "sg:phone":"+1 514 596 5057",
    "sg:postcode":"H1L 4V2",
    "sg:province":"QC",
    "wof:name":"Caron Ecole",
    "wof:placetype":"venue"
},
  "geometry": {"coordinates":[-73.51605987550001,45.601360321],"type":"Point"}
}