{
  "type": "Feature",
  "properties": {
    "iso:country":"CA",
    "sg:address":"107 Walker Dr",
    "sg:city":"Brampton",
    "sg:classifiers":[
        {
            "category":"Wholesale",
            "subcategory":"Seafood",
            "type":"Manufacturing & Wholesale Goods"
        }
    ],
    "sg:phone":"+1 905 792 9700",
    "sg:postcode":"L6T 5K5",
    "sg:province":"ON",
    "wof:name":"Export Packers CO Ltd",
    "wof:placetype":"venue"
},
  "geometry": {"coordinates":[-79.68071,43.727783],"type":"Point"}
}