{
  "type": "Feature",
  "properties": {
    "addr:full":"42300 Yarrow Central Rd Chilliwack BC V2R 5E2",
    "addr:postcode":"42300;v2r 5e2",
    "addr:street":"Central Rd",
    "iso:country":"CA",
    "sg:address":"42300 Yarrow Central Rd",
    "sg:city":"Chilliwack",
    "sg:classifiers":[
        {
            "category":"Restaurant",
            "type":"Food & Drink"
        }
    ],
    "sg:phone":"+1 604 823 6375",
    "sg:postcode":"V2R 5E2",
    "sg:province":"BC",
    "sg:tags":[
        "delicatessen"
    ],
    "wof:name":"Yarrow Deli",
    "wof:placetype":"venue"
},
  "geometry": {"coordinates":[-122.053825378,49.0819511414],"type":"Point"}
}