{
  "type": "Feature",
  "properties": {
    "addr:full":"287 Main St Yarmouth NS B5A 1E3",
    "addr:housenumber":"287",
    "addr:postcode":"b5a 1e3",
    "addr:street":"Main St",
    "iso:country":"CA",
    "sg:address":"287 Main St",
    "sg:city":"Yarmouth",
    "sg:classifiers":[
        {
            "category":"Cinema",
            "subcategory":"Movie Rental",
            "type":"Entertainment"
        }
    ],
    "sg:phone":"+1 902 742 2535",
    "sg:postcode":"B5A 1E3",
    "sg:province":"NS",
    "sg:tags":[
        "leasing",
        "video",
        "disc",
        "tape"
    ],
    "wof:name":"10 To 10 Video Ltd",
    "wof:placetype":"venue"
},
  "geometry": {"coordinates":[-66.1199798584,43.8351707458],"type":"Point"}
}