{
  "type": "Feature",
  "properties": {
    "addr:full":"636 Boul St-Pierre O Caraquet NB E1W 1A2",
    "addr:housenumber":"636",
    "addr:postcode":"e1w 1a2",
    "addr:street":"Boul St-Pierre O",
    "iso:country":"CA",
    "sg:address":"636 Boul St-Pierre O",
    "sg:city":"Caraquet",
    "sg:classifiers":[
        {
            "category":"Wholesale",
            "subcategory":"Non-durable Goods",
            "type":"Manufacturing & Wholesale Goods"
        }
    ],
    "sg:phone":"+1 506 727 2323",
    "sg:postcode":"E1W 1A2",
    "sg:province":"NB",
    "sg:tags":[
        "advertising"
    ],
    "wof:name":"Promotions Blanchard",
    "wof:placetype":"venue"
},
  "geometry": {"coordinates":[-65.0201263428,47.772403717],"type":"Point"}
}