{
  "type": "Feature",
  "properties": {
    "addr:full":"Delta BC V4K 1W4",
    "addr:postcode":"v4k 1w4",
    "iso:country":"CA",
    "sg:city":"Delta",
    "sg:classifiers":[
        {
            "category":"Personal",
            "subcategory":"Beauty Salon",
            "type":"Services"
        }
    ],
    "sg:phone":"+1 604 940 9117",
    "sg:postcode":"V4K 1W4",
    "sg:province":"BC",
    "wof:name":"Great Clips For Hair",
    "wof:placetype":"venue"
},
  "geometry": {"coordinates":[-123.07691955599999,49.0903778076],"type":"Point"}
}