{
  "type": "Feature",
  "properties": {
    "addr:full":"34 Bristol Rd E Mississauga ON L4Z 3K8",
    "addr:housenumber":"34",
    "addr:postcode":"l4z 3k8",
    "addr:street":"Bristol Rd E",
    "iso:country":"CA",
    "sg:address":"34 Bristol Rd E",
    "sg:city":"Mississauga",
    "sg:classifiers":[
        {
            "category":"Food & Beverages",
            "subcategory":"Groceries & Convenience Stores",
            "type":"Retail Goods"
        }
    ],
    "sg:phone":"+1 905 507 6754",
    "sg:postcode":"L4Z 3K8",
    "sg:province":"ON",
    "wof:name":"Convenience K",
    "wof:placetype":"venue"
},
  "geometry": {"coordinates":[-79.66226959230001,43.6153640747],"type":"Point"}
}