{
  "type": "Feature",
  "properties": {
    "addr:full":"14 Boul DE Bromont Bromont QC J2L 2K2",
    "addr:housenumber":"14",
    "addr:postcode":"j2l 2k2",
    "addr:street":"Boul De Bromont",
    "iso:country":"CA",
    "sg:address":"14 Boul DE Bromont",
    "sg:city":"Bromont",
    "sg:classifiers":[
        {
            "category":"Food & Beverages",
            "subcategory":"Groceries & Convenience Stores",
            "type":"Retail Goods"
        }
    ],
    "sg:phone":"+1 450 534 1734",
    "sg:postcode":"J2L 2K2",
    "sg:province":"QC",
    "sg:tags":[
        "grocer"
    ],
    "wof:name":"Depanneur Petro-Canada",
    "wof:placetype":"venue"
},
  "geometry": {"coordinates":[-72.64902499999999,45.334522],"type":"Point"}
}