{
  "type": "Feature",
  "properties": {
    "iso:country":"CA",
    "sg:address":"31 Place Bourget N",
    "sg:city":"Joliette",
    "sg:classifiers":[
        {
            "category":"Shopping",
            "subcategory":"Gifts & Souvenirs",
            "type":"Retail Goods"
        }
    ],
    "sg:phone":"+1 450 752 2936",
    "sg:postcode":"J6E 5E3",
    "sg:province":"QC",
    "sg:tags":[
        "shop",
        "paint"
    ],
    "wof:name":"Belle Decoration",
    "wof:placetype":"venue"
},
  "geometry": {"coordinates":[-73.4409408569,46.0247116089],"type":"Point"}
}