{
  "type": "Feature",
  "properties": {
    "addr:full":"5111 Northland Dr NW # 511 Calgary AB T2L 2J8",
    "addr:housenumber":"5111",
    "addr:postcode":"t2l 2j8",
    "addr:street":"Northland Dr Nw # 511",
    "iso:country":"CA",
    "sg:address":"5111 Northland Dr NW # 511",
    "sg:city":"Calgary",
    "sg:classifiers":[
        {
            "category":"Shopping",
            "subcategory":"Department Store",
            "type":"Retail Goods"
        }
    ],
    "sg:phone":"+1 403 247 7884",
    "sg:postcode":"T2L 2J8",
    "sg:province":"AB",
    "wof:name":"Home Outfitters",
    "wof:placetype":"venue"
},
  "geometry": {"coordinates":[-114.14157104500001,51.0984344482],"type":"Point"}
}