{
  "type": "Feature",
  "properties": {
    "addr:full":"Trail BC V1R 2G9",
    "addr:postcode":"bc v1r 2g9",
    "addr:street":"Trail",
    "iso:country":"CA",
    "sg:city":"Trail",
    "sg:classifiers":[
        {
            "category":"Personal",
            "subcategory":"Beauty Salon",
            "type":"Services"
        }
    ],
    "sg:phone":"+1 250 368 3909",
    "sg:postcode":"V1R 2G9",
    "sg:province":"BC",
    "wof:name":"Styling Trends Family Hair",
    "wof:placetype":"venue"
},
  "geometry": {"coordinates":[-117.745087,49.095524],"type":"Point"}
}