{
  "type": "Feature",
  "properties": {
    "addr:full":"Mayerthorpe AB T0E 1N0",
    "addr:postcode":"t0e 1n0",
    "iso:country":"CA",
    "sg:city":"Mayerthorpe",
    "sg:classifiers":[
        {
            "category":"Retail",
            "subcategory":"Veterinary Services",
            "type":"Services"
        }
    ],
    "sg:phone":"+1 780 786 2000",
    "sg:postcode":"T0E 1N0",
    "sg:province":"AB",
    "sg:tags":[
        "veterinarian"
    ],
    "wof:name":"Mayerthorpe Vet Svc",
    "wof:placetype":"venue"
},
  "geometry": {"coordinates":[-115.142410278,53.9533233643],"type":"Point"}
}