{
  "type": "Feature",
  "properties": {
    "addr:full":"10315 34 Ave NW Edmonton AB T6J 6V1",
    "addr:housenumber":"10315",
    "addr:postcode":"t6j 6v1",
    "addr:street":"34 Ave Nw",
    "iso:country":"CA",
    "sg:address":"10315 34 Ave NW",
    "sg:city":"Edmonton",
    "sg:classifiers":[
        {
            "category":"Retail",
            "subcategory":"Auto Repair",
            "type":"Services"
        }
    ],
    "sg:phone":"+1 780 448 9599",
    "sg:postcode":"T6J 6V1",
    "sg:province":"AB",
    "sg:tags":[
        "automobile",
        "lubrication"
    ],
    "wof:name":"Mr Lube",
    "wof:placetype":"venue"
},
  "geometry": {"coordinates":[-113.49406399999999,53.467548],"type":"Point"}
}