{
  "type": "Feature",
  "properties": {
    "addr:full":"1187 Gordon Dr Kelowna BC V1Y 3E5",
    "addr:housenumber":"1187",
    "addr:postcode":"v1y 3e5",
    "addr:street":"Gordon Dr",
    "iso:country":"CA",
    "sg:address":"1187 Gordon Dr",
    "sg:city":"Kelowna",
    "sg:classifiers":[
        {
            "category":"Retail",
            "subcategory":"Repair Shop",
            "type":"Services"
        }
    ],
    "sg:phone":"+1 250 860 1151",
    "sg:postcode":"V1Y 3E5",
    "sg:province":"BC",
    "sg:tags":[
        "appliance"
    ],
    "wof:name":"Kelowna Refrigeration & Appl",
    "wof:placetype":"venue"
},
  "geometry": {"coordinates":[-119.47680699999999,49.893143],"type":"Point"}
}