{
  "type": "Feature",
  "properties": {
    "iso:country":"CA",
    "sg:address":"19 Rue Desjardins",
    "sg:city":"Mont-Carmel",
    "sg:classifiers":[
        {
            "category":"Building & Trades",
            "subcategory":"Construction",
            "type":"Services"
        }
    ],
    "sg:phone":"+1 418 498 3423",
    "sg:postcode":"G0L 1W0",
    "sg:province":"QC",
    "sg:tags":[
        "excavating",
        "contractor"
    ],
    "wof:name":"Jean-Luc Rivard & Fils Inc",
    "wof:placetype":"venue"
},
  "geometry": {"coordinates":[-69.854309082,47.4417877197],"type":"Point"}
}