{
  "type": "Feature",
  "properties": {
    "addr:full":"1366 Yonge St # 401 Toronto ON M4T 3A7",
    "addr:housenumber":"1366",
    "addr:postcode":"m4t 3a7",
    "addr:street":"Yonge St # 401",
    "iso:country":"CA",
    "sg:address":"1366 Yonge St # 401",
    "sg:city":"Toronto",
    "sg:classifiers":[
        {
            "category":"Health Services",
            "subcategory":"Chiropractor",
            "type":"Services"
        }
    ],
    "sg:phone":"+1 416 461 2200",
    "sg:postcode":"M4T 3A7",
    "sg:province":"ON",
    "wof:name":"Pringle, Jake J DC",
    "wof:placetype":"venue"
},
  "geometry": {"coordinates":[-79.3934020996,43.6859970093],"type":"Point"}
}