{
  "type": "Feature",
  "properties": {
    "addr:full":"526 Burrows St Grandview MB R0L 0Y0",
    "addr:housenumber":"526",
    "addr:postcode":"r0l 0y0",
    "addr:street":"Burrows St",
    "iso:country":"CA",
    "sg:address":"526 Burrows St",
    "sg:city":"Grandview",
    "sg:classifiers":[
        {
            "category":"Government",
            "subcategory":"Office",
            "type":"Public Place"
        }
    ],
    "sg:phone":"+1 204 546 5000",
    "sg:postcode":"R0L 0Y0",
    "sg:province":"MB",
    "wof:name":"Manitoba Conservation",
    "wof:placetype":"venue"
},
  "geometry": {"coordinates":[-100.6996,51.168411],"type":"Point"}
}