{
  "type": "Feature",
  "properties": {
    "addr:full":"264 Mcdermot Ave Winnipeg MB R3B 0S8",
    "addr:housenumber":"264",
    "addr:postcode":"r3b 0s8",
    "addr:street":"Mcdermot Ave",
    "iso:country":"CA",
    "sg:address":"264 Mcdermot Ave",
    "sg:city":"Winnipeg",
    "sg:classifiers":[
        {
            "category":"Professional",
            "subcategory":"Computer Services",
            "type":"Services"
        }
    ],
    "sg:phone":"+1 204 943 4646",
    "sg:postcode":"R3B 0S8",
    "sg:province":"MB",
    "sg:tags":[
        "internet"
    ],
    "wof:name":"Intrinsix Canada Inc",
    "wof:placetype":"venue"
},
  "geometry": {"coordinates":[-97.14102172849999,49.8972434998],"type":"Point"}
}