{
  "type": "Feature",
  "properties": {
    "addr:full":"8001 Goreway Dr Brampton ON L6T 3Y7",
    "addr:housenumber":"8001",
    "addr:postcode":"l6t 3y7",
    "addr:street":"Goreway Dr",
    "iso:country":"CA",
    "sg:address":"8001 Goreway Dr",
    "sg:city":"Brampton",
    "sg:classifiers":[
        {
            "category":"Freight",
            "type":"Transportation"
        }
    ],
    "sg:phone":"+1 905 793 0059",
    "sg:postcode":"L6T 3Y7",
    "sg:province":"ON",
    "sg:tags":[
        "trucking"
    ],
    "wof:name":"Chris Line Transportation Syst",
    "wof:placetype":"venue"
},
  "geometry": {"coordinates":[-79.65827941889999,43.7333831787],"type":"Point"}
}