{
  "type": "Feature",
  "properties": {
    "addr:full":"Sainte-Foy QC G1V 3V7",
    "addr:postcode":"g1v 3v7",
    "iso:country":"CA",
    "sg:city":"Sainte-Foy",
    "sg:classifiers":[
        {
            "category":"Health Services",
            "subcategory":"Health Practitioner",
            "type":"Services"
        }
    ],
    "sg:phone":"+1 418 657 3425",
    "sg:postcode":"G1V 3V7",
    "sg:province":"QC",
    "sg:tags":[
        "acupuncture"
    ],
    "wof:name":"Guimont, Claude",
    "wof:placetype":"venue"
},
  "geometry": {"coordinates":[-71.291763,46.769211],"type":"Point"}
}