{
  "type": "Feature",
  "properties": {
    "addr:full":"North York ON M9M 1M4",
    "addr:postcode":"m9m 1m4",
    "iso:country":"CA",
    "sg:city":"North York",
    "sg:classifiers":[
        {
            "category":"Retail",
            "subcategory":"Auto Repair",
            "type":"Services"
        }
    ],
    "sg:phone":"+1 416 745 4459",
    "sg:postcode":"M9M 1M4",
    "sg:province":"ON",
    "sg:tags":[
        "repairing",
        "automobile"
    ],
    "wof:name":"Custom Wheel Alignment & Auto",
    "wof:placetype":"venue"
},
  "geometry": {"coordinates":[-79.530357,43.738194],"type":"Point"}
}