{
  "type": "Feature",
  "properties": {
    "addr:full":"3350 32 St NE Calgary AB T1Y 6B9",
    "addr:housenumber":"3350",
    "addr:postcode":"t1y 6b9",
    "addr:street":"32 St Ne",
    "iso:country":"CA",
    "sg:address":"3350 32 St NE",
    "sg:city":"Calgary",
    "sg:classifiers":[
        {
            "category":"Retail",
            "subcategory":"Auto Repair",
            "type":"Services"
        }
    ],
    "sg:phone":"+1 403 265 6787",
    "sg:postcode":"T1Y 6B9",
    "sg:province":"AB",
    "sg:tags":[
        "repairing",
        "automobile"
    ],
    "wof:name":"Specs Automotive Repair & Svc",
    "wof:placetype":"venue"
},
  "geometry": {"coordinates":[-113.98839569099999,51.0821914673],"type":"Point"}
}