{
  "type": "Feature",
  "properties": {
    "addr:full":"Montreal QC H2Z 1X4",
    "addr:postcode":"h2z 1x4",
    "iso:country":"CA",
    "sg:city":"Montreal",
    "sg:classifiers":[
        {
            "category":"Shopping",
            "subcategory":"Optical Goods",
            "type":"Retail Goods"
        }
    ],
    "sg:phone":"+1 514 842 5274",
    "sg:postcode":"H2Z 1X4",
    "sg:province":"QC",
    "sg:tags":[
        "optician"
    ],
    "wof:name":"Marie-Jose Le Blanc Opticare",
    "wof:placetype":"venue"
},
  "geometry": {"coordinates":[-73.5597610474,45.5107154846],"type":"Point"}
}