{
  "type": "Feature",
  "properties": {
    "addr:full":"Winnipeg MB R3C 3X2",
    "addr:postcode":"r3c 3x2",
    "iso:country":"CA",
    "sg:city":"Winnipeg",
    "sg:classifiers":[
        {
            "category":"Professional",
            "subcategory":"Lawyer & Legal Services",
            "type":"Services"
        }
    ],
    "sg:phone":"+1 204 942 0161",
    "sg:postcode":"R3C 3X2",
    "sg:province":"MB",
    "sg:tags":[
        "attorney"
    ],
    "wof:name":"Adams, Alan A QC",
    "wof:placetype":"venue"
},
  "geometry": {"coordinates":[-97.138458,49.895248],"type":"Point"}
}