{
  "type": "Feature",
  "properties": {
    "addr:full":"Whistler BC V0N 1B1",
    "addr:postcode":"v0n 1b1",
    "iso:country":"CA",
    "sg:city":"Whistler",
    "sg:classifiers":[
        {
            "category":"Shopping",
            "subcategory":"Florist",
            "type":"Retail Goods"
        }
    ],
    "sg:phone":"+1 604 932 6376",
    "sg:postcode":"V0N 1B1",
    "sg:province":"BC",
    "sg:tags":[
        "garden",
        "center"
    ],
    "wof:name":"Whistler Garden Ctr",
    "wof:placetype":"venue"
},
  "geometry": {"coordinates":[-123.04239699999999,50.087246],"type":"Point"}
}