{
  "type": "Feature",
  "properties": {
    "addr:full":"1599 Second Ave Trail BC V1R 1M3",
    "addr:housenumber":"1599",
    "addr:postcode":"bc v1r 1m3",
    "addr:street":"Second Ave Trail",
    "iso:country":"CA",
    "sg:address":"1599 Second Ave",
    "sg:city":"Trail",
    "sg:classifiers":[
        {
            "category":"Food & Beverages",
            "subcategory":"Groceries & Convenience Stores",
            "type":"Retail Goods"
        }
    ],
    "sg:phone":"+1 250 368 6423",
    "sg:postcode":"V1R 1M3",
    "sg:province":"BC",
    "sg:tags":[
        "grocer"
    ],
    "wof:name":"Canada Safeway Ltd",
    "wof:placetype":"venue"
},
  "geometry": {"coordinates":[-117.70134,49.097694],"type":"Point"}
}