{
  "type": "Feature",
  "properties": {
    "addr:full":"393 Main Haileybury ON P0J 1K0",
    "addr:housenumber":"393",
    "addr:postcode":"p0j 1k0",
    "addr:street":"Main Haileybury",
    "iso:country":"CA",
    "sg:address":"393 Main",
    "sg:city":"Haileybury",
    "sg:classifiers":[
        {
            "category":"Government",
            "subcategory":"Office",
            "type":"Public Place"
        }
    ],
    "sg:phone":"+1 705 672 3321",
    "sg:postcode":"P0J 1K0",
    "sg:province":"ON",
    "wof:name":"Ontario Small Claims",
    "wof:placetype":"venue"
},
  "geometry": {"coordinates":[-79.634911,47.449131],"type":"Point"}
}