{
  "type": "Feature",
  "properties": {
    "iso:country":"CA",
    "sg:address":"1629 Mardell St",
    "sg:city":"London",
    "sg:classifiers":[
        {
            "category":"Home & Garden",
            "subcategory":"Carpets & Floor Coverings",
            "type":"Retail Goods"
        }
    ],
    "sg:phone":"+1 519 438 8757",
    "sg:postcode":"N5V 1X3",
    "sg:province":"ON",
    "sg:tags":[
        "material"
    ],
    "wof:name":"Peerless Flooring",
    "wof:placetype":"venue"
},
  "geometry": {"coordinates":[-81.1966247559,43.0092315674],"type":"Point"}
}