{
  "type": "Feature",
  "properties": {
    "addr:full":"North Vancouver BC V7H 1S1",
    "addr:postcode":"v7h 1s1",
    "iso:country":"CA",
    "sg:city":"North Vancouver",
    "sg:classifiers":[
        {
            "category":"Retail",
            "subcategory":"Auto Repair",
            "type":"Services"
        }
    ],
    "sg:phone":"+1 604 929 9401",
    "sg:postcode":"V7H 1S1",
    "sg:province":"BC",
    "sg:tags":[
        "repairing",
        "automobile"
    ],
    "wof:name":"Pika Pump & Compressor Svc",
    "wof:placetype":"venue"
},
  "geometry": {"coordinates":[-123.022033691,49.3036460876],"type":"Point"}
}