{
  "type": "Feature",
  "properties": {
    "addr:full":"810 Crowfoot Cres NW Calgary AB T3G 4S3",
    "addr:housenumber":"810",
    "addr:postcode":"t3g 4s3",
    "addr:street":"Crowfoot Cres Nw",
    "iso:country":"CA",
    "sg:address":"810 Crowfoot Cres NW",
    "sg:city":"Calgary",
    "sg:classifiers":[
        {
            "category":"Food & Beverages",
            "subcategory":"Meat & Fish",
            "type":"Retail Goods"
        }
    ],
    "sg:phone":"+1 403 208 2980",
    "sg:postcode":"T3G 4S3",
    "sg:province":"AB",
    "wof:name":"Crowfoot Cres Meat & Deli",
    "wof:placetype":"venue"
},
  "geometry": {"coordinates":[-114.206115723,51.126789093],"type":"Point"}
}