{
  "type": "Feature",
  "properties": {
    "addr:full":"100 East Beaver Creek Rd Richmond Hill ON L4B 1J6",
    "addr:housenumber":"100",
    "addr:postcode":"l4b 1j6",
    "addr:street":"East Beaver Creek Rd",
    "iso:country":"CA",
    "sg:address":"100 East Beaver Creek Rd",
    "sg:city":"Richmond Hill",
    "sg:classifiers":[
        {
            "category":"Wholesale",
            "subcategory":"Motor Vehicles",
            "type":"Manufacturing & Wholesale Goods"
        }
    ],
    "sg:phone":"+1 905 889 2600",
    "sg:postcode":"L4B 1J6",
    "sg:province":"ON",
    "sg:tags":[
        "automobile",
        "dealer"
    ],
    "wof:name":"Suzuki Canada Inc",
    "wof:placetype":"venue"
},
  "geometry": {"coordinates":[-79.378136,43.854366],"type":"Point"}
}