{
  "type": "Feature",
  "properties": {
    "addr:full":"North York ON M3A 3M5",
    "addr:postcode":"m3a 3m5",
    "iso:country":"CA",
    "sg:city":"North York",
    "sg:classifiers":[
        {
            "category":"Professional",
            "subcategory":"Business Services",
            "type":"Services"
        }
    ],
    "sg:phone":"+1 416 781 3000",
    "sg:postcode":"M3A 3M5",
    "sg:province":"ON",
    "sg:tags":[
        "inspection"
    ],
    "wof:name":"Rudolph Reusse Assoc",
    "wof:placetype":"venue"
},
  "geometry": {"coordinates":[-79.34477200000001,43.763638],"type":"Point"}
}