{
  "type": "Feature",
  "properties": {
    "addr:full":"425 Rue Leguerrier Aylmer QC J9H 6N8",
    "addr:housenumber":"425",
    "addr:postcode":"j9h 6n8",
    "addr:street":"Rue Leguerrier",
    "iso:country":"CA",
    "sg:address":"425 Rue Leguerrier",
    "sg:city":"Aylmer",
    "sg:classifiers":[
        {
            "category":"Health Services",
            "subcategory":"Hospital",
            "type":"Services"
        }
    ],
    "sg:phone":"+1 819 684 2251",
    "sg:postcode":"J9H 6N8",
    "sg:province":"QC",
    "sg:tags":[
        "organization",
        "social",
        "welfare"
    ],
    "wof:name":"Clsc Chsld Grande Riviere",
    "wof:placetype":"venue"
},
  "geometry": {"coordinates":[-75.83622699999999,45.39917],"type":"Point"}
}