{
  "type": "Feature",
  "properties": {
    "addr:full":"5335 Pulley Blank St Oldcastle ON N0R 1L0",
    "addr:housenumber":"5335",
    "addr:postcode":"n0r 1l0",
    "addr:street":"Pulley Blank St",
    "iso:country":"CA",
    "sg:address":"5335 Pulley Blank St",
    "sg:city":"Oldcastle",
    "sg:classifiers":[
        {
            "category":"Manufacturing",
            "subcategory":"Tools & Machinery",
            "type":"Manufacturing & Wholesale Goods"
        }
    ],
    "sg:phone":"+1 519 737 7825",
    "sg:postcode":"N0R 1L0",
    "sg:province":"ON",
    "sg:tags":[
        "machine"
    ],
    "wof:name":"Quality Carbide Grind Inc",
    "wof:placetype":"venue"
},
  "geometry": {"coordinates":[-82.969688,42.236477],"type":"Point"}
}