{
  "type": "Feature",
  "properties": {
    "addr:full":"341 Rue Saint-Joseph E Quebec QC G1K 3B3",
    "addr:housenumber":"341",
    "addr:postcode":"g1k 3b3",
    "addr:street":"Rue Saint-Joseph E",
    "iso:country":"CA",
    "sg:address":"341 Rue Saint-Joseph E",
    "sg:city":"Quebec",
    "sg:classifiers":[
        {
            "category":"Restaurant",
            "type":"Food & Drink"
        }
    ],
    "sg:phone":"+1 418 523 5600",
    "sg:postcode":"G1K 3B3",
    "sg:province":"QC",
    "wof:name":"Restaurant Valentine",
    "wof:placetype":"venue"
},
  "geometry": {"coordinates":[-71.22580000000001,46.81366],"type":"Point"}
}