{
  "type": "Feature",
  "properties": {
    "addr:full":"Smoky Lake AB T0A 3C0",
    "addr:postcode":"t0a 3c0",
    "iso:country":"CA",
    "sg:city":"Smoky Lake",
    "sg:classifiers":[
        {
            "category":"Autos & Motor Vehicles",
            "subcategory":"Fuel & Gas Station",
            "type":"Retail Goods"
        }
    ],
    "sg:phone":"+1 780 656 3738",
    "sg:postcode":"T0A 3C0",
    "sg:province":"AB",
    "sg:tags":[
        "oil"
    ],
    "wof:name":"Smoky Lake Esso",
    "wof:placetype":"venue"
},
  "geometry": {"coordinates":[-112.483887,54.112576],"type":"Point"}
}