{
  "type": "Feature",
  "properties": {
    "addr:full":"1350 Rue Principale Saint-Zotique QC J0P 1Z0",
    "addr:housenumber":"1350",
    "addr:postcode":"j0p 1z0",
    "addr:street":"Rue Principale",
    "iso:country":"CA",
    "sg:address":"1350 Rue Principale",
    "sg:city":"Saint-Zotique",
    "sg:classifiers":[
        {
            "category":"Sports & Exercise",
            "subcategory":"Golf",
            "type":"Entertainment"
        }
    ],
    "sg:phone":"+1 514 875 6666",
    "sg:postcode":"J0P 1Z0",
    "sg:province":"QC",
    "sg:tags":[
        "course"
    ],
    "wof:name":"Club DE Golf Banlieue Ouest",
    "wof:placetype":"venue"
},
  "geometry": {"coordinates":[-74.25312,45.239517],"type":"Point"}
}