{
  "type": "Feature",
  "properties": {
    "addr:full":"Orangeville ON L9W 2Z6",
    "addr:postcode":"l9w 2z6",
    "iso:country":"CA",
    "sg:city":"Orangeville",
    "sg:classifiers":[
        {
            "category":"Education",
            "subcategory":"School",
            "type":"Public Place"
        }
    ],
    "sg:phone":"+1 519 941 3381",
    "sg:postcode":"L9W 2Z6",
    "sg:province":"ON",
    "wof:name":"Orangeville Christian School",
    "wof:placetype":"venue"
},
  "geometry": {"coordinates":[-80.139915,43.91],"type":"Point"}
}