{
  "type": "Feature",
  "properties": {
    "addr:full":"Ottawa ON K2P 2H4",
    "addr:postcode":"k2p 2h4",
    "iso:country":"CA",
    "sg:city":"Ottawa",
    "sg:classifiers":[
        {
            "category":"Organizations",
            "subcategory":"Membership Organization",
            "type":"Services"
        }
    ],
    "sg:phone":"+1 613 232 9634",
    "sg:postcode":"K2P 2H4",
    "sg:province":"ON",
    "wof:name":"Catholic Immigration Ctr",
    "wof:placetype":"venue"
},
  "geometry": {"coordinates":[-75.69064331049999,45.4114189148],"type":"Point"}
}