{
  "type": "Feature",
  "properties": {
    "addr:full":"653 8E Av Saint-Zacharie QC G0M 2C0",
    "addr:housenumber":"653",
    "addr:postcode":"g0m 2c0",
    "addr:street":"8E Av Saint-Zacharie",
    "iso:country":"CA",
    "sg:address":"653 8E Av",
    "sg:city":"Saint-Zacharie",
    "sg:classifiers":[
        {
            "category":"Manufacturing",
            "subcategory":"Lumber",
            "type":"Manufacturing & Wholesale Goods"
        }
    ],
    "sg:phone":"+1 418 593 5164",
    "sg:postcode":"G0M 2C0",
    "sg:province":"QC",
    "sg:tags":[
        "syrup",
        "maple",
        "sugar"
    ],
    "wof:name":"Poirier Bascom Robert",
    "wof:placetype":"venue"
},
  "geometry": {"coordinates":[-70.36302947999999,46.1264381409],"type":"Point"}
}