{
  "type": "Feature",
  "properties": {
    "iso:country":"CA",
    "sg:city":"Vancouver",
    "sg:classifiers":[
        {
            "category":"Building & Trades",
            "subcategory":"Construction",
            "type":"Services"
        }
    ],
    "sg:phone":"+1 604 697 0227",
    "sg:postcode":"V6E 3X2",
    "sg:province":"BC",
    "sg:tags":[
        "contractor"
    ],
    "wof:name":"Quigg Group",
    "wof:placetype":"venue"
},
  "geometry": {"coordinates":[-123.118865967,49.2875595093],"type":"Point"}
}