{
  "type": "Feature",
  "properties": {
    "addr:full":"4261 Highway 7 Markham ON L3R 9W6",
    "addr:housenumber":"4261",
    "addr:postcode":"l3r 9w6",
    "addr:street":"Highway 7",
    "iso:country":"CA",
    "sg:address":"4261 Highway 7",
    "sg:city":"Markham",
    "sg:classifiers":[
        {
            "category":"Food & Beverages",
            "subcategory":"Meat & Fish",
            "type":"Retail Goods"
        }
    ],
    "sg:phone":"+1 905 474 1891",
    "sg:postcode":"L3R 9W6",
    "sg:province":"ON",
    "sg:tags":[
        "frozen"
    ],
    "wof:name":"M & M Meat Shops",
    "wof:placetype":"venue"
},
  "geometry": {"coordinates":[-79.33994300000001,43.856033],"type":"Point"}
}