{
  "type": "Feature",
  "properties": {
    "addr:full":"Sherbrooke NS B0J 3C0",
    "addr:postcode":"b0j 3c0",
    "iso:country":"CA",
    "sg:city":"Sherbrooke",
    "sg:classifiers":[
        {
            "category":"Government",
            "subcategory":"Office",
            "type":"Public Place"
        }
    ],
    "sg:phone":"+1 902 522 2212",
    "sg:postcode":"B0J 3C0",
    "sg:province":"NS",
    "wof:name":"Nova Scotia Public Health Svc",
    "wof:placetype":"venue"
},
  "geometry": {"coordinates":[-61.981689,45.143215],"type":"Point"}
}