{
  "type": "Feature",
  "properties": {
    "addr:full":"PO Box 219 Gladmar SK S0C 1A0",
    "addr:housenumber":"po",
    "addr:postcode":"s0c 1a0",
    "addr:street":"Box 219",
    "iso:country":"CA",
    "sg:address":"PO Box 219",
    "sg:city":"Gladmar",
    "sg:classifiers":[
        {
            "category":"Organizations",
            "subcategory":"Religious Organization",
            "type":"Services"
        }
    ],
    "sg:phone":"+1 306 447 2033",
    "sg:postcode":"S0C 1A0",
    "sg:province":"SK",
    "sg:tags":[
        "church"
    ],
    "wof:name":"Gladmar Lutheran Church",
    "wof:placetype":"venue"
},
  "geometry": {"coordinates":[-104.45459747300001,49.1638717651],"type":"Point"}
}