{
  "type": "Feature",
  "properties": {
    "addr:full":"145 Somerset Cir SW Calgary AB T2Y 3P7",
    "addr:housenumber":"145",
    "addr:postcode":"t2y 3p7",
    "addr:street":"Somerset Cir Sw",
    "iso:country":"CA",
    "sg:address":"145 Somerset Cir SW",
    "sg:city":"Calgary",
    "sg:classifiers":[
        {
            "category":"Food & Beverages",
            "subcategory":"Specialty",
            "type":"Retail Goods"
        }
    ],
    "sg:phone":"+1 403 201 0558",
    "sg:postcode":"T2Y 3P7",
    "sg:province":"AB",
    "sg:tags":[
        "basket",
        "gourmet",
        "gift",
        "parcel",
        "shop"
    ],
    "wof:name":"Baskets By Moonlight",
    "wof:placetype":"venue"
},
  "geometry": {"coordinates":[-114.079292,50.897511],"type":"Point"}
}