{
  "type": "Feature",
  "properties": {
    "addr:full":"Sudbury ON P3E 5P5",
    "addr:postcode":"p3e 5p5",
    "iso:country":"CA",
    "sg:city":"Sudbury",
    "sg:classifiers":[
        {
            "category":"Freight",
            "type":"Transportation"
        }
    ],
    "sg:phone":"+1 705 525 2744",
    "sg:postcode":"P3E 5P5",
    "sg:province":"ON",
    "sg:tags":[
        "mover"
    ],
    "wof:name":"Amj Campbell",
    "wof:placetype":"venue"
},
  "geometry": {"coordinates":[-81.0341339111,46.4678726196],"type":"Point"}
}