{
  "type": "Feature",
  "properties": {
    "addr:full":"90 Bessemer Rd London ON N6E 1R1",
    "addr:housenumber":"90",
    "addr:postcode":"n6e 1r1",
    "addr:street":"Bessemer Rd",
    "iso:country":"CA",
    "sg:address":"90 Bessemer Rd",
    "sg:city":"London",
    "sg:classifiers":[
        {
            "category":"Wholesale",
            "subcategory":"Electrical",
            "type":"Manufacturing & Wholesale Goods"
        }
    ],
    "sg:phone":"+1 519 681 1221",
    "sg:postcode":"N6E 1R1",
    "sg:province":"ON",
    "sg:tags":[
        "control"
    ],
    "wof:name":"Johnson Controls Ltd",
    "wof:placetype":"venue"
},
  "geometry": {"coordinates":[-81.2121124268,42.9306373596],"type":"Point"}
}