{
  "type": "Feature",
  "properties": {
    "iso:country":"CA",
    "sg:address":"55 Bradford St",
    "sg:city":"Barrie",
    "sg:classifiers":[
        {
            "category":"Autos & Motor Vehicles",
            "subcategory":"Automobile Sales",
            "type":"Retail Goods"
        }
    ],
    "sg:phone":"+1 705 726 1400",
    "sg:postcode":"L4N 3A7",
    "sg:province":"ON",
    "sg:tags":[
        "car",
        "dealer"
    ],
    "wof:name":"Network Auto Sales Barrie",
    "wof:placetype":"venue"
},
  "geometry": {"coordinates":[-79.693687,44.384727],"type":"Point"}
}