{
  "type": "Feature",
  "properties": {
    "iso:country":"CA",
    "sg:address":"102 Victoria St N",
    "sg:city":"Sarnia",
    "sg:classifiers":[
        {
            "category":"Retail",
            "subcategory":"Funeral Services",
            "type":"Services"
        }
    ],
    "sg:phone":"+1 519 336 6042",
    "sg:postcode":"N7T 5W9",
    "sg:province":"ON",
    "sg:tags":[
        "director"
    ],
    "wof:name":"D J Robb Funeral Home",
    "wof:placetype":"venue"
},
  "geometry": {"coordinates":[-82.405815,42.970776],"type":"Point"}
}