{
  "type": "Feature",
  "properties": {
    "addr:full":"550 Alden Rd Markham ON L3R 6A8",
    "addr:housenumber":"550",
    "addr:postcode":"l3r 6a8",
    "addr:street":"Alden Rd",
    "iso:country":"CA",
    "sg:address":"550 Alden Rd",
    "sg:city":"Markham",
    "sg:classifiers":[
        {
            "category":"Shopping",
            "type":"Retail Goods"
        }
    ],
    "sg:phone":"+1 905 479 9669",
    "sg:postcode":"L3R 6A8",
    "sg:province":"ON",
    "sg:tags":[
        "equipment",
        "answering",
        "telephone",
        "supply"
    ],
    "wof:name":"Voicegate Technologies",
    "wof:placetype":"venue"
},
  "geometry": {"coordinates":[-79.3320770264,43.836681366],"type":"Point"}
}