{
  "type": "Feature",
  "properties": {
    "iso:country":"CA",
    "sg:address":"290 Rue Saint-Joseph",
    "sg:city":"LA Tuque",
    "sg:classifiers":[
        {
            "category":"Government",
            "subcategory":"Office",
            "type":"Public Place"
        }
    ],
    "sg:phone":"+1 819 523 9533",
    "sg:postcode":"G9X 3Z8",
    "sg:province":"QC",
    "wof:name":"Quebec Palais DE Justice",
    "wof:placetype":"venue"
},
  "geometry": {"coordinates":[-72.7857513428,47.4410858154],"type":"Point"}
}