{
  "type": "Feature",
  "properties": {
    "addr:full":"257 Victoria St N Kitchener ON N2H 5C9",
    "addr:housenumber":"257",
    "addr:postcode":"n2h 5c9",
    "addr:street":"Victoria St N",
    "iso:country":"CA",
    "sg:address":"257 Victoria St N",
    "sg:city":"Kitchener",
    "sg:classifiers":[
        {
            "category":"Utilities",
            "subcategory":"Refuse",
            "type":"Services"
        }
    ],
    "sg:phone":"+1 519 743 9341",
    "sg:postcode":"N2H 5C9",
    "sg:province":"ON",
    "sg:tags":[
        "garbage",
        "collection"
    ],
    "wof:name":"Regional Waste Disposal",
    "wof:placetype":"venue"
},
  "geometry": {"coordinates":[-80.486656,43.457054],"type":"Point"}
}