{
  "type": "Feature",
  "properties": {
    "addr:full":"2707 North Service Rd W Swift Current SK S9H 5M1",
    "addr:housenumber":"2707",
    "addr:postcode":"s9h 5m1",
    "addr:street":"North Service Rd W",
    "iso:country":"CA",
    "sg:address":"2707 North Service Rd W",
    "sg:city":"Swift Current",
    "sg:classifiers":[
        {
            "category":"Retail",
            "subcategory":"Auto Repair",
            "type":"Services"
        }
    ],
    "sg:phone":"+1 306 773 2133",
    "sg:postcode":"S9H 5M1",
    "sg:province":"SK",
    "sg:tags":[
        "automobile",
        "wrecker",
        "wrecking"
    ],
    "wof:name":"First Choice Auto & Truck Prts",
    "wof:placetype":"venue"
},
  "geometry": {"coordinates":[-107.826416016,50.2874107361],"type":"Point"}
}