{
  "type": "Feature",
  "properties": {
    "addr:full":"Sillery QC G1T 1Z3",
    "addr:postcode":"g1t 1z3",
    "iso:country":"CA",
    "sg:city":"Sillery",
    "sg:classifiers":[
        {
            "category":"Wholesale",
            "subcategory":"Durable Goods & Equipment",
            "type":"Manufacturing & Wholesale Goods"
        }
    ],
    "sg:phone":"+1 418 683 2011",
    "sg:postcode":"G1T 1Z3",
    "sg:province":"QC",
    "sg:tags":[
        "exporter"
    ],
    "wof:name":"Gaspe Cured Enr",
    "wof:placetype":"venue"
},
  "geometry": {"coordinates":[-71.2515792847,46.7812461853],"type":"Point"}
}