{
  "type": "Feature",
  "properties": {
    "addr:full":"65 Church St S St Marys ON N4X 1B8",
    "addr:housenumber":"65",
    "addr:postcode":"n4x 1b8",
    "addr:street":"Church St S",
    "iso:country":"CA",
    "sg:address":"65 Church St S",
    "sg:city":"St Marys",
    "sg:classifiers":[
        {
            "category":"Organizations",
            "subcategory":"Religious Organization",
            "type":"Services"
        }
    ],
    "sg:phone":"+1 519 284 1147",
    "sg:postcode":"N4X 1B8",
    "sg:province":"ON",
    "sg:tags":[
        "church"
    ],
    "wof:name":"St James Anglican Church",
    "wof:placetype":"venue"
},
  "geometry": {"coordinates":[-81.140259,43.257999],"type":"Point"}
}