{
  "type": "Feature",
  "properties": {
    "iso:country":"CA",
    "sg:address":"15349 97 St NW",
    "sg:city":"Edmonton",
    "sg:classifiers":[
        {
            "category":"Personal",
            "subcategory":"Tanning Parlor",
            "type":"Services"
        }
    ],
    "sg:phone":"+1 780 944 1347",
    "sg:postcode":"T5X 5V3",
    "sg:province":"AB",
    "sg:tags":[
        "salon"
    ],
    "wof:name":"Fabutan Sun Tan Studios",
    "wof:placetype":"venue"
},
  "geometry": {"coordinates":[-113.491531,53.614876],"type":"Point"}
}