{
  "type": "Feature",
  "properties": {
    "addr:full":"855 Rue Principale # 3 Beresford NB E8K 1T3",
    "addr:housenumber":"855",
    "addr:postcode":"e8k 1t3",
    "addr:street":"Rue Principale # 3 Beresford",
    "iso:country":"CA",
    "sg:address":"855 Rue Principale # 3",
    "sg:city":"Beresford",
    "sg:classifiers":[
        {
            "category":"Education",
            "subcategory":"Library",
            "type":"Public Place"
        }
    ],
    "sg:phone":"+1 506 542 2704",
    "sg:postcode":"E8K 1T3",
    "sg:province":"NB",
    "wof:name":"Bibliotheque Publique Mgr",
    "wof:placetype":"venue"
},
  "geometry": {"coordinates":[-65.7036743164,47.7007446289],"type":"Point"}
}