{
  "type": "Feature",
  "properties": {
    "addr:full":"Hamilton ON L8P 3B6",
    "addr:postcode":"l8p 3b6",
    "iso:country":"CA",
    "sg:city":"Hamilton",
    "sg:classifiers":[
        {
            "category":"Health Services",
            "subcategory":"Doctor",
            "type":"Services"
        }
    ],
    "sg:phone":"+1 905 521 6040",
    "sg:postcode":"L8P 3B6",
    "sg:province":"ON",
    "sg:tags":[
        "physician",
        "surgeon"
    ],
    "wof:name":"Korzekwa, Marilyn MD",
    "wof:placetype":"venue"
},
  "geometry": {"coordinates":[-79.87286400000001,43.247856],"type":"Point"}
}