{
  "type": "Feature",
  "properties": {
    "addr:full":"802 Bernard Ave Kelowna BC V1Y 6P5",
    "addr:housenumber":"802",
    "addr:postcode":"v1y 6p5",
    "addr:street":"Bernard Ave",
    "iso:country":"CA",
    "sg:address":"802 Bernard Ave",
    "sg:city":"Kelowna",
    "sg:classifiers":[
        {
            "category":"Real Estate",
            "subcategory":"Real Estate Agent",
            "type":"Services"
        }
    ],
    "sg:phone":"+1 250 862 8100",
    "sg:postcode":"V1Y 6P5",
    "sg:province":"BC",
    "wof:name":"Syber Realty",
    "wof:placetype":"venue"
},
  "geometry": {"coordinates":[-119.485572815,49.886428833],"type":"Point"}
}