{
  "type": "Feature",
  "properties": {
    "addr:full":"Lethbridge AB T1H 5S1",
    "addr:postcode":"t1h 5s1",
    "iso:country":"CA",
    "sg:city":"Lethbridge",
    "sg:classifiers":[
        {
            "category":"Education",
            "subcategory":"School",
            "type":"Public Place"
        }
    ],
    "sg:phone":"+1 403 327 2160",
    "sg:postcode":"T1H 5S1",
    "sg:province":"AB",
    "wof:name":"Alberta Distance Learning Ctr",
    "wof:placetype":"venue"
},
  "geometry": {"coordinates":[-112.78769699999999,49.722439],"type":"Point"}
}