{
  "type": "Feature",
  "properties": {
    "addr:full":"6810 52 Ave Red Deer AB T4N 4L1",
    "addr:housenumber":"6810",
    "addr:postcode":"t4n 4l1",
    "addr:street":"52 Ave",
    "iso:country":"CA",
    "sg:address":"6810 52 Ave",
    "sg:city":"Red Deer",
    "sg:classifiers":[
        {
            "category":"Manufacturing",
            "subcategory":"Apparel",
            "type":"Manufacturing & Wholesale Goods"
        }
    ],
    "sg:phone":"+1 403 340 8211",
    "sg:postcode":"T4N 4L1",
    "sg:province":"AB",
    "sg:tags":[
        "hat"
    ],
    "wof:name":"Persimmon Patch & Embroidery",
    "wof:placetype":"venue"
},
  "geometry": {"coordinates":[-113.81710099999999,52.292961],"type":"Point"}
}