{
  "type": "Feature",
  "properties": {
    "addr:full":"10329 106 St NW Edmonton AB T5J 1H8",
    "addr:housenumber":"10329",
    "addr:postcode":"t5j 1h8",
    "addr:street":"106 St Nw",
    "iso:country":"CA",
    "sg:address":"10329 106 St NW",
    "sg:city":"Edmonton",
    "sg:classifiers":[
        {
            "category":"Banks & Credit Unions",
            "subcategory":"Investment Brokerage",
            "type":"Services"
        }
    ],
    "sg:phone":"+1 780 429 1217",
    "sg:postcode":"T5J 1H8",
    "sg:province":"AB",
    "sg:tags":[
        "consultant",
        "planning",
        "financial"
    ],
    "wof:name":"Hacking Financial Strategies",
    "wof:placetype":"venue"
},
  "geometry": {"coordinates":[-113.50266999999999,53.545155],"type":"Point"}
}