{
  "type": "Feature",
  "properties": {
    "iso:country":"CA",
    "sg:address":"24 Harrow Cir NW",
    "sg:city":"Edmonton",
    "sg:classifiers":[
        {
            "category":"Home & Garden",
            "subcategory":"Home Furnishings",
            "type":"Retail Goods"
        }
    ],
    "sg:phone":"+1 780 486 2776",
    "sg:postcode":"T5A 2S5",
    "sg:province":"AB",
    "sg:tags":[
        "curtain",
        "made",
        "drapery"
    ],
    "wof:name":"Chateau Draperies Ltd",
    "wof:placetype":"venue"
},
  "geometry": {"coordinates":[-113.404396057,53.5882225037],"type":"Point"}
}