{
  "type": "Feature",
  "properties": {
    "addr:full":"Fredericton NB E3B 2T8",
    "addr:postcode":"e3b 2t8",
    "iso:country":"CA",
    "sg:city":"Fredericton",
    "sg:classifiers":[
        {
            "category":"Personal",
            "type":"Services"
        }
    ],
    "sg:phone":"+1 506 457 1087",
    "sg:postcode":"E3B 2T8",
    "sg:province":"NB",
    "sg:tags":[
        "therapist",
        "massage"
    ],
    "wof:name":"Paulvic Massage Studio",
    "wof:placetype":"venue"
},
  "geometry": {"coordinates":[-66.6724243164,45.9435157776],"type":"Point"}
}