{
  "type": "Feature",
  "properties": {
    "addr:full":"310 Kent St W Lindsay ON K9V 4T7",
    "addr:housenumber":"310",
    "addr:postcode":"k9v 4t7",
    "addr:street":"Kent St W",
    "iso:country":"CA",
    "sg:address":"310 Kent St W",
    "sg:city":"Lindsay",
    "sg:classifiers":[
        {
            "category":"Health Services",
            "subcategory":"Doctor",
            "type":"Services"
        }
    ],
    "sg:phone":"+1 705 324 0290",
    "sg:postcode":"K9V 4T7",
    "sg:province":"ON",
    "sg:tags":[
        "dentist"
    ],
    "wof:name":"Brierley, Ronald DDS",
    "wof:placetype":"venue"
},
  "geometry": {"coordinates":[-78.752579,44.351837],"type":"Point"}
}