{
  "type": "Feature",
  "properties": {
    "addr:full":"370 Highland Rd W Kitchener ON N2M 5J9",
    "addr:housenumber":"370",
    "addr:postcode":"n2m 5j9",
    "addr:street":"Highland Rd W",
    "iso:country":"CA",
    "sg:address":"370 Highland Rd W",
    "sg:city":"Kitchener",
    "sg:classifiers":[
        {
            "category":"Restaurant",
            "type":"Food & Drink"
        }
    ],
    "sg:phone":"+1 519 581 1158",
    "sg:postcode":"N2M 5J9",
    "sg:province":"ON",
    "wof:name":"Angel's Diner",
    "wof:placetype":"venue"
},
  "geometry": {"coordinates":[-80.5120544434,43.4372329712],"type":"Point"}
}