{
  "type": "Feature",
  "properties": {
    "iso:country":"CA",
    "sg:address":"733 Boul DE LA Cote-Vertu",
    "sg:city":"Saint-Laurent",
    "sg:classifiers":[
        {
            "category":"Wholesale",
            "subcategory":"Meat",
            "type":"Manufacturing & Wholesale Goods"
        }
    ],
    "sg:phone":"+1 514 747 7754",
    "sg:postcode":"H4L 1Y3",
    "sg:province":"QC",
    "sg:tags":[
        "butchering"
    ],
    "wof:name":"Boucherie Abu Elias",
    "wof:placetype":"venue"
},
  "geometry": {"coordinates":[-73.6744384766,45.5209007263],"type":"Point"}
}