{
  "type": "Feature",
  "properties": {
    "iso:country":"CA",
    "sg:address":"25 Rue Morneault",
    "sg:city":"Edmundston",
    "sg:classifiers":[
        {
            "category":"Professional",
            "subcategory":"Business Services",
            "type":"Services"
        }
    ],
    "sg:phone":"+1 506 735 6435",
    "sg:postcode":"E3V 4J3",
    "sg:province":"NB",
    "sg:tags":[
        "appraiser"
    ],
    "wof:name":"Northwest Consultants Ltd",
    "wof:placetype":"venue"
},
  "geometry": {"coordinates":[-68.35116577150001,47.3998908997],"type":"Point"}
}