{
  "type": "Feature",
  "properties": {
    "addr:full":"582 Main St S Alexandria ON K0C 1A0",
    "addr:housenumber":"582",
    "addr:postcode":"k0c 1a0",
    "addr:street":"Main St S",
    "iso:country":"CA",
    "sg:address":"582 Main St S",
    "sg:city":"Alexandria",
    "sg:classifiers":[
        {
            "category":"Restaurant",
            "type":"Food & Drink"
        }
    ],
    "sg:phone":"+1 613 525 3351",
    "sg:postcode":"K0C 1A0",
    "sg:province":"ON",
    "sg:tags":[
        "parlor",
        "ice",
        "cream"
    ],
    "wof:name":"Dairy Queen",
    "wof:placetype":"venue"
},
  "geometry": {"coordinates":[-74.6261138916,45.2951698303],"type":"Point"}
}