{
  "type": "Feature",
  "properties": {
    "addr:full":"Montreal QC H3B 1A2",
    "addr:postcode":"h3b 1a2",
    "iso:country":"CA",
    "sg:city":"Montreal",
    "sg:classifiers":[
        {
            "category":"Professional",
            "subcategory":"Art Services",
            "type":"Services"
        }
    ],
    "sg:phone":"+1 514 395 2373",
    "sg:postcode":"H3B 1A2",
    "sg:province":"QC",
    "sg:tags":[
        "photographer"
    ],
    "wof:name":"Dumais, Stephane",
    "wof:placetype":"venue"
},
  "geometry": {"coordinates":[-73.56053199999999,45.513351],"type":"Point"}
}