{
  "type": "Feature",
  "properties": {
    "addr:full":"Scarborough ON M1P 3B2",
    "addr:postcode":"m1p 3b2",
    "iso:country":"CA",
    "sg:city":"Scarborough",
    "sg:classifiers":[
        {
            "category":"Manufacturing",
            "subcategory":"Tools & Machinery",
            "type":"Manufacturing & Wholesale Goods"
        }
    ],
    "sg:phone":"+1 416 285 0828",
    "sg:postcode":"M1P 3B2",
    "sg:province":"ON",
    "sg:tags":[
        "mold"
    ],
    "wof:name":"R B Precision Grinding Svc",
    "wof:placetype":"venue"
},
  "geometry": {"coordinates":[-79.26924099999999,43.75605],"type":"Point"}
}