{
  "type": "Feature",
  "properties": {
    "addr:full":"2337 Main St Vancouver BC V5T 3C9",
    "addr:housenumber":"2337",
    "addr:postcode":"v5t 3c9",
    "addr:street":"Main St",
    "iso:country":"CA",
    "sg:address":"2337 Main St",
    "sg:city":"Vancouver",
    "sg:classifiers":[
        {
            "category":"Manufacturing",
            "subcategory":"Furniture",
            "type":"Manufacturing & Wholesale Goods"
        }
    ],
    "sg:phone":"+1 604 879 3088",
    "sg:postcode":"V5T 3C9",
    "sg:province":"BC",
    "sg:tags":[
        "venetian",
        "blind"
    ],
    "wof:name":"Wang on Blinds Canada",
    "wof:placetype":"venue"
},
  "geometry": {"coordinates":[-123.101127624,49.2641601562],"type":"Point"}
}