{
  "type": "Feature",
  "properties": {
    "iso:country":"CA",
    "sg:address":"16732 113 Ave NW",
    "sg:city":"Edmonton",
    "sg:classifiers":[
        {
            "category":"Retail",
            "subcategory":"Auto Repair",
            "type":"Services"
        }
    ],
    "sg:phone":"+1 780 413 6004",
    "sg:postcode":"T5M 2X3",
    "sg:province":"AB",
    "sg:tags":[
        "repairing",
        "automobile"
    ],
    "wof:name":"Angel Automotive",
    "wof:placetype":"venue"
},
  "geometry": {"coordinates":[-113.609519959,53.5614814758],"type":"Point"}
}