{
  "type": "Feature",
  "properties": {
    "addr:full":"Calgary AB T2A 6K1",
    "addr:postcode":"t2a 6k1",
    "iso:country":"CA",
    "sg:city":"Calgary",
    "sg:classifiers":[
        {
            "category":"Wholesale",
            "subcategory":"Petroleum",
            "type":"Manufacturing & Wholesale Goods"
        }
    ],
    "sg:phone":"+1 403 248 3433",
    "sg:postcode":"T2A 6K1",
    "sg:province":"AB",
    "sg:tags":[
        "pipe",
        "line",
        "company",
        "contractor"
    ],
    "wof:name":"Eci Cancross Ltd",
    "wof:placetype":"venue"
},
  "geometry": {"coordinates":[-113.993125916,51.0597648621],"type":"Point"}
}