{
  "type": "Feature",
  "properties": {
    "addr:full":"206 Mcmaster Blvd W Lethbridge AB T1K 4R3",
    "addr:housenumber":"206",
    "addr:postcode":"t1k 4r3",
    "addr:street":"Mcmaster Blvd W",
    "iso:country":"CA",
    "sg:address":"206 Mcmaster Blvd W",
    "sg:city":"Lethbridge",
    "sg:classifiers":[
        {
            "category":"Education",
            "subcategory":"School",
            "type":"Public Place"
        }
    ],
    "sg:phone":"+1 403 381 8110",
    "sg:postcode":"T1K 4R3",
    "sg:province":"AB",
    "wof:name":"Children of St Martha",
    "wof:placetype":"venue"
},
  "geometry": {"coordinates":[-112.884727478,49.6735229492],"type":"Point"}
}