{
  "type": "Feature",
  "properties": {
    "addr:full":"2789 K.L.O. Rd Kelowna BC V1W 4A5",
    "addr:housenumber":"2789",
    "addr:postcode":"v1w 4a5",
    "addr:street":"K.L.O. Rd",
    "iso:country":"CA",
    "sg:address":"2789 K.L.O. Rd",
    "sg:city":"Kelowna",
    "sg:classifiers":[
        {
            "category":"Bars & Pubs",
            "type":"Food & Drink"
        }
    ],
    "sg:phone":"+1 250 762 8882",
    "sg:postcode":"V1W 4A5",
    "sg:province":"BC",
    "sg:tags":[
        "beer",
        "ale"
    ],
    "wof:name":"Mc Culloch Station Pub",
    "wof:placetype":"venue"
},
  "geometry": {"coordinates":[-119.49659699999999,49.886814],"type":"Point"}
}