{
  "type": "Feature",
  "properties": {
    "addr:full":"68 Rutherford Rd N Brampton ON L6V 2J1",
    "addr:housenumber":"68",
    "addr:postcode":"l6v 2j1",
    "addr:street":"Rutherford Rd N",
    "iso:country":"CA",
    "sg:address":"68 Rutherford Rd N",
    "sg:city":"Brampton",
    "sg:classifiers":[
        {
            "category":"Organizations",
            "subcategory":"Religious Organization",
            "type":"Services"
        }
    ],
    "sg:phone":"+1 905 451 5986",
    "sg:postcode":"L6V 2J1",
    "sg:province":"ON",
    "sg:tags":[
        "church"
    ],
    "wof:name":"Church of the Nazarene",
    "wof:placetype":"venue"
},
  "geometry": {"coordinates":[-79.7467575073,43.704120636],"type":"Point"}
}