{
  "type": "Feature",
  "properties": {
    "addr:full":"208 3rd Ave E Kyle SK S0L 1T0",
    "addr:housenumber":"208",
    "addr:postcode":"s0l 1t0",
    "addr:street":"3Rd Ave E",
    "iso:country":"CA",
    "sg:address":"208 3rd Ave E",
    "sg:city":"Kyle",
    "sg:classifiers":[
        {
            "category":"Shopping",
            "type":"Retail Goods"
        }
    ],
    "sg:phone":"+1 306 375 2400",
    "sg:postcode":"S0L 1T0",
    "sg:province":"SK",
    "sg:tags":[
        "equipment",
        "care",
        "health",
        "home"
    ],
    "wof:name":"Kyle Home Care",
    "wof:placetype":"venue"
},
  "geometry": {"coordinates":[-108.03958129900001,50.8342781067],"type":"Point"}
}