{
  "type": "Feature",
  "properties": {
    "addr:full":"611 Burrows Rd N Mccreary MB R0J 1B0",
    "addr:housenumber":"611",
    "addr:postcode":"r0j 1b0",
    "addr:street":"Burrows Rd N Mccreary",
    "iso:country":"CA",
    "sg:address":"611 Burrows Rd N",
    "sg:city":"Mccreary",
    "sg:classifiers":[
        {
            "category":"Food & Beverages",
            "subcategory":"Groceries & Convenience Stores",
            "type":"Retail Goods"
        }
    ],
    "sg:phone":"+1 204 835 2799",
    "sg:postcode":"R0J 1B0",
    "sg:province":"MB",
    "sg:tags":[
        "grocer"
    ],
    "wof:name":"T C's Town & Country",
    "wof:placetype":"venue"
},
  "geometry": {"coordinates":[-99.4940414429,50.7762947083],"type":"Point"}
}