{
  "type": "Feature",
  "properties": {
    "addr:full":"1129 17 Ave SW Calgary AB T2T 0B6",
    "addr:housenumber":"1129",
    "addr:postcode":"t2t 0b6",
    "addr:street":"17 Ave Sw",
    "iso:country":"CA",
    "sg:address":"1129 17 Ave SW",
    "sg:city":"Calgary",
    "sg:classifiers":[
        {
            "category":"Retail",
            "subcategory":"Laundry & Dry Cleaning",
            "type":"Services"
        }
    ],
    "sg:phone":"+1 403 229 1449",
    "sg:postcode":"T2T 0B6",
    "sg:province":"AB",
    "sg:tags":[
        "cleaners"
    ],
    "wof:name":"Randell's Fine Drycleaning Inc",
    "wof:placetype":"venue"
},
  "geometry": {"coordinates":[-114.08879899999999,51.037624],"type":"Point"}
}