{
  "type": "Feature",
  "properties": {
    "iso:country":"CA",
    "sg:city":"Bobcaygeon",
    "sg:classifiers":[
        {
            "category":"Shopping",
            "subcategory":"Florist",
            "type":"Retail Goods"
        }
    ],
    "sg:phone":"+1 705 738 4402",
    "sg:postcode":"K0M 1A0",
    "sg:province":"ON",
    "wof:name":"Village Florist",
    "wof:placetype":"venue"
},
  "geometry": {"coordinates":[-78.5441360474,44.5361747742],"type":"Point"}
}