{
  "type": "Feature",
  "properties": {
    "addr:full":"16 Heslop Dr Etobicoke ON M8W 4R1",
    "addr:housenumber":"16",
    "addr:postcode":"m8w 4r1",
    "addr:street":"Heslop Dr",
    "iso:country":"CA",
    "sg:address":"16 Heslop Dr",
    "sg:city":"Etobicoke",
    "sg:classifiers":[
        {
            "category":"Building & Trades",
            "subcategory":"Construction",
            "type":"Services"
        }
    ],
    "sg:phone":"+1 416 259 6791",
    "sg:postcode":"M8W 4R1",
    "sg:province":"ON",
    "sg:tags":[
        "concrete",
        "contractor"
    ],
    "wof:name":"Beam Construction",
    "wof:placetype":"venue"
},
  "geometry": {"coordinates":[-79.5506515503,43.6008262634],"type":"Point"}
}