{
  "type": "Feature",
  "properties": {
    "addr:full":"8 Borden St Brantford ON N3R 2G8",
    "addr:housenumber":"8",
    "addr:postcode":"n3r 2g8",
    "addr:street":"Borden St",
    "iso:country":"CA",
    "sg:address":"8 Borden St",
    "sg:city":"Brantford",
    "sg:classifiers":[
        {
            "category":"Health Services",
            "subcategory":"Clinic",
            "type":"Services"
        }
    ],
    "sg:phone":"+1 519 752 9307",
    "sg:postcode":"N3R 2G8",
    "sg:province":"ON",
    "sg:tags":[
        "equipment",
        "therapy",
        "oxygen"
    ],
    "wof:name":"Specialized Home Respiratory",
    "wof:placetype":"venue"
},
  "geometry": {"coordinates":[-80.2729644775,43.1613616943],"type":"Point"}
}