{
  "type": "Feature",
  "properties": {
    "addr:full":"108 Oak Park Ave East York ON M4C 4M3",
    "addr:housenumber":"108",
    "addr:postcode":"m4c 4m3",
    "addr:street":"Oak Park Ave",
    "iso:country":"CA",
    "sg:address":"108 Oak Park Ave",
    "sg:city":"East York",
    "sg:classifiers":[
        {
            "category":"Building & Trades",
            "subcategory":"Construction",
            "type":"Services"
        }
    ],
    "sg:phone":"+1 416 425 8309",
    "sg:postcode":"M4C 4M3",
    "sg:province":"ON",
    "sg:tags":[
        "resurfacing",
        "laying",
        "refinishing",
        "floor"
    ],
    "wof:name":"Face Lift Floors",
    "wof:placetype":"venue"
},
  "geometry": {"coordinates":[-79.3091049194,43.6905479431],"type":"Point"}
}