{
  "type": "Feature",
  "properties": {
    "addr:full":"301 Lansdowne Ave Toronto ON M6K 2W5",
    "addr:housenumber":"301",
    "addr:postcode":"m6k 2w5",
    "addr:street":"Lansdowne Ave",
    "iso:country":"CA",
    "sg:address":"301 Lansdowne Ave",
    "sg:city":"Toronto",
    "sg:classifiers":[
        {
            "category":"Food & Beverages",
            "subcategory":"Bakery",
            "type":"Retail Goods"
        }
    ],
    "sg:phone":"+1 416 537 1997",
    "sg:postcode":"M6K 2W5",
    "sg:province":"ON",
    "sg:tags":[
        "baker"
    ],
    "wof:name":"Vinh Bakery",
    "wof:placetype":"venue"
},
  "geometry": {"coordinates":[-79.439629,43.650345],"type":"Point"}
}