{
  "type": "Feature",
  "properties": {
    "iso:country":"CA",
    "sg:address":"11664 Hwy 43",
    "sg:city":"Mountain",
    "sg:classifiers":[
        {
            "category":"Health Services",
            "subcategory":"Nursing And Care Facility",
            "type":"Services"
        }
    ],
    "sg:phone":"+1 613 774 3391",
    "sg:postcode":"K0E 1S0",
    "sg:province":"ON",
    "sg:tags":[
        "home",
        "retirement",
        "community"
    ],
    "wof:name":"Hillcrest Haven Rest Home",
    "wof:placetype":"venue"
},
  "geometry": {"coordinates":[-75.535484314,45.0547180176],"type":"Point"}
}