{
  "type": "Feature",
  "properties": {
    "iso:country":"CA",
    "sg:address":"1755 Riverside Dr",
    "sg:city":"Ottawa",
    "sg:classifiers":[
        {
            "category":"Retail",
            "subcategory":"Repair Shop",
            "type":"Services"
        }
    ],
    "sg:phone":"+1 613 731 2001",
    "sg:postcode":"K1G 3T6",
    "sg:province":"ON",
    "sg:tags":[
        "lining",
        "coating",
        "tank"
    ],
    "wof:name":"Koch Engineering CO Ltd",
    "wof:placetype":"venue"
},
  "geometry": {"coordinates":[-75.66538238530001,45.4022026062],"type":"Point"}
}