{
  "type": "Feature",
  "properties": {
    "addr:full":"4932 Boul Des Sources Pierrefonds QC H8Y 3C9",
    "addr:housenumber":"4932",
    "addr:postcode":"h8y 3c9",
    "addr:street":"Boul Des Sources",
    "iso:country":"CA",
    "sg:address":"4932 Boul Des Sources",
    "sg:city":"Pierrefonds",
    "sg:classifiers":[
        {
            "category":"Food & Beverages",
            "subcategory":"Bakery",
            "type":"Retail Goods"
        }
    ],
    "sg:phone":"+1 514 685 0739",
    "sg:postcode":"H8Y 3C9",
    "sg:province":"QC",
    "sg:tags":[
        "doughnut"
    ],
    "wof:name":"Tim Hortons",
    "wof:placetype":"venue"
},
  "geometry": {"coordinates":[-73.847183,45.495155],"type":"Point"}
}