{
  "type": "Feature",
  "properties": {
    "addr:full":"Cumberland BC V0R 1S0",
    "addr:postcode":"v0r 1s0",
    "iso:country":"CA",
    "sg:city":"Cumberland",
    "sg:classifiers":[
        {
            "category":"Travel",
            "subcategory":"Hotels & Motels",
            "type":"Entertainment"
        }
    ],
    "sg:phone":"+1 250 336 8322",
    "sg:postcode":"V0R 1S0",
    "sg:province":"BC",
    "wof:name":"Waverley Hotel",
    "wof:placetype":"venue"
},
  "geometry": {"coordinates":[-125.03014400000001,49.619019],"type":"Point"}
}