{
  "type": "Feature",
  "properties": {
    "addr:full":"Saint-Patrice-DE-Beaurivage QC G0S 1B0",
    "addr:postcode":"g0s 1b0",
    "iso:country":"CA",
    "sg:city":"Saint-Patrice-DE-Beaurivage",
    "sg:classifiers":[
        {
            "category":"Retail",
            "subcategory":"Auto Repair",
            "type":"Services"
        }
    ],
    "sg:phone":"+1 418 596 2470",
    "sg:postcode":"G0S 1B0",
    "sg:province":"QC",
    "sg:tags":[
        "repairing",
        "automobile"
    ],
    "wof:name":"Sylvain Lionel Auto Ltee",
    "wof:placetype":"venue"
},
  "geometry": {"coordinates":[-71.2339706421,46.4113616943],"type":"Point"}
}