{
  "type": "Feature",
  "properties": {
    "addr:full":"14011 97 St Grande Prairie AB T8V 7B6",
    "addr:housenumber":"14011",
    "addr:postcode":"t8v 7b6",
    "addr:street":"97 St",
    "iso:country":"CA",
    "sg:address":"14011 97 St",
    "sg:city":"Grande Prairie",
    "sg:classifiers":[
        {
            "category":"Mining & Drilling",
            "type":"Manufacturing & Wholesale Goods"
        }
    ],
    "sg:phone":"+1 780 539 0703",
    "sg:postcode":"T8V 7B6",
    "sg:province":"AB",
    "sg:tags":[
        "field",
        "oil"
    ],
    "wof:name":"Opsco Industries Ltd",
    "wof:placetype":"venue"
},
  "geometry": {"coordinates":[-118.786277771,55.1997413635],"type":"Point"}
}