{
  "type": "Feature",
  "properties": {
    "addr:full":"155 Rue Craig Richmond QC J0B 2H0",
    "addr:housenumber":"155",
    "addr:postcode":"j0b 2h0",
    "addr:street":"Rue Craig",
    "iso:country":"CA",
    "sg:address":"155 Rue Craig",
    "sg:city":"Richmond",
    "sg:classifiers":[
        {
            "category":"Organizations",
            "subcategory":"Professional Association",
            "type":"Services"
        }
    ],
    "sg:phone":"+1 819 826 2428",
    "sg:postcode":"J0B 2H0",
    "sg:province":"QC",
    "sg:tags":[
        "club"
    ],
    "wof:name":"Club Lions Richmond Melbourne",
    "wof:placetype":"venue"
},
  "geometry": {"coordinates":[-72.139313,45.659405],"type":"Point"}
}