{
  "type": "Feature",
  "properties": {
    "addr:full":"3250 Bloor St W #600 Etobicoke ON M8X 2X9",
    "addr:housenumber":"3250",
    "addr:postcode":"m8x 2x9",
    "addr:street":"Bloor St W # 600",
    "iso:country":"CA",
    "sg:address":"3250 Bloor St W #600",
    "sg:city":"Etobicoke",
    "sg:classifiers":[
        {
            "category":"Government",
            "subcategory":"Office",
            "type":"Public Place"
        }
    ],
    "sg:phone":"+1 416 207 4800",
    "sg:postcode":"M8X 2X9",
    "sg:province":"ON",
    "sg:tags":[
        "real estate"
    ],
    "wof:name":"Real Estate Council of Ontario",
    "wof:placetype":"venue"
},
  "geometry": {"coordinates":[-79.520264,43.645485],"type":"Point"}
}