{
  "type": "Feature",
  "properties": {
    "iso:country":"CA",
    "sg:address":"PO Box 149",
    "sg:city":"Fort Severn",
    "sg:classifiers":[
        {
            "category":"Organizations",
            "subcategory":"Professional Association",
            "type":"Services"
        }
    ],
    "sg:phone":"+1 807 478 2572",
    "sg:postcode":"P0V 1W0",
    "sg:province":"ON",
    "sg:tags":[
        "government"
    ],
    "wof:name":"Fort Severn Band Council",
    "wof:placetype":"venue"
},
  "geometry": {"coordinates":[-79.7339706421,44.8052215576],"type":"Point"}
}