{
  "type": "Feature",
  "properties": {
    "addr:full":"1350 Shawson Dr Mississauga ON L4W 1C5",
    "addr:housenumber":"1350",
    "addr:postcode":"l4w 1c5",
    "addr:street":"Shawson Dr",
    "iso:country":"CA",
    "sg:address":"1350 Shawson Dr",
    "sg:city":"Mississauga",
    "sg:classifiers":[
        {
            "category":"Building & Trades",
            "subcategory":"Construction",
            "type":"Services"
        }
    ],
    "sg:phone":"+1 905 670 7898",
    "sg:postcode":"L4W 1C5",
    "sg:province":"ON",
    "sg:tags":[
        "maker",
        "cabinet"
    ],
    "wof:name":"Frendel Kitchens",
    "wof:placetype":"venue"
},
  "geometry": {"coordinates":[-79.64567599999999,43.650585],"type":"Point"}
}