{
  "type": "Feature",
  "properties": {
    "addr:full":"Edmonton AB T5Y 2G4",
    "addr:postcode":"t5y 2g4",
    "iso:country":"CA",
    "sg:city":"Edmonton",
    "sg:classifiers":[
        {
            "category":"Real Estate",
            "subcategory":"Real Estate Operator",
            "type":"Services"
        }
    ],
    "sg:phone":"+1 780 473 4741",
    "sg:postcode":"T5Y 2G4",
    "sg:province":"AB",
    "sg:tags":[
        "apartment"
    ],
    "wof:name":"Victoria Trail Apartments",
    "wof:placetype":"venue"
},
  "geometry": {"coordinates":[-113.379127502,53.6114044189],"type":"Point"}
}