{
  "type": "Feature",
  "properties": {
    "addr:full":"2317 Trim Rd Orleans ON K4A 3R3",
    "addr:housenumber":"2317",
    "addr:postcode":"k4a 3r3",
    "addr:street":"Trim Rd",
    "iso:country":"CA",
    "sg:address":"2317 Trim Rd",
    "sg:city":"Orleans",
    "sg:classifiers":[
        {
            "category":"Professional",
            "subcategory":"Business Services",
            "type":"Services"
        }
    ],
    "sg:phone":"+1 613 833 2811",
    "sg:postcode":"K4A 3R3",
    "sg:province":"ON",
    "sg:tags":[
        "recycling",
        "center"
    ],
    "wof:name":"Abp Recycling",
    "wof:placetype":"venue"
},
  "geometry": {"coordinates":[-75.45040130620001,45.4637298584],"type":"Point"}
}