{
  "type": "Feature",
  "properties": {
    "addr:full":"3200 Boul Laframboise # 1534 Saint-Hyacinthe QC J2S 4Z5",
    "addr:housenumber":"3200",
    "addr:postcode":"j2s 4z5",
    "addr:street":"Boul Laframboise # 1534",
    "iso:country":"CA",
    "sg:address":"3200 Boul Laframboise # 1534",
    "sg:city":"Saint-Hyacinthe",
    "sg:classifiers":[
        {
            "category":"Wholesale",
            "subcategory":"Groceries",
            "type":"Manufacturing & Wholesale Goods"
        }
    ],
    "sg:phone":"+1 450 774 0997",
    "sg:postcode":"J2S 4Z5",
    "sg:province":"QC",
    "sg:tags":[
        "cocoa",
        "shop",
        "gift",
        "chocolate"
    ],
    "wof:name":"Gourmandine",
    "wof:placetype":"venue"
},
  "geometry": {"coordinates":[-72.967308,45.636738],"type":"Point"}
}