{
  "type": "Feature",
  "properties": {
    "addr:full":"200 Rue Saint-Olivier Quebec QC G1R 1G3",
    "addr:housenumber":"200",
    "addr:postcode":"g1r 1g3",
    "addr:street":"Rue Saint-Olivier",
    "iso:country":"CA",
    "sg:address":"200 Rue Saint-Olivier",
    "sg:city":"Quebec",
    "sg:classifiers":[
        {
            "category":"Food & Beverages",
            "subcategory":"Groceries & Convenience Stores",
            "type":"Retail Goods"
        }
    ],
    "sg:phone":"+1 418 524 7838",
    "sg:postcode":"G1R 1G3",
    "sg:province":"QC",
    "sg:tags":[
        "grocer"
    ],
    "wof:name":"Epicerie St-Olivier",
    "wof:placetype":"venue"
},
  "geometry": {"coordinates":[-71.22605896,46.8090667725],"type":"Point"}
}