{
  "type": "Feature",
  "properties": {
    "addr:full":"315 Burnside Rd W Victoria BC V8Z 7L6",
    "addr:housenumber":"315",
    "addr:postcode":"v8z 7l6",
    "addr:street":"Burnside Rd W",
    "iso:country":"CA",
    "sg:address":"315 Burnside Rd W",
    "sg:city":"Victoria",
    "sg:classifiers":[
        {
            "category":"Restaurant",
            "type":"Food & Drink"
        }
    ],
    "sg:phone":"+1 250 978 9333",
    "sg:postcode":"V8Z 7L6",
    "sg:province":"BC",
    "sg:tags":[
        "caterer"
    ],
    "wof:name":"Montana's Cookhouse Saloon",
    "wof:placetype":"venue"
},
  "geometry": {"coordinates":[-123.381935,48.447948],"type":"Point"}
}