{
  "type": "Feature",
  "properties": {
    "addr:full":"215 Rue Principale Saint-Hilarion QC G0A 3V0",
    "addr:housenumber":"215",
    "addr:postcode":"g0a 3v0",
    "addr:street":"Rue Principale",
    "iso:country":"CA",
    "sg:address":"215 Rue Principale",
    "sg:city":"Saint-Hilarion",
    "sg:classifiers":[
        {
            "category":"Government",
            "subcategory":"Fire Station",
            "type":"Public Place"
        }
    ],
    "sg:phone":"+1 ",
    "sg:postcode":"G0A 3V0",
    "sg:province":"QC",
    "sg:tags":[
        "department"
    ],
    "wof:name":"St-Hilarion Pompiers-Appels",
    "wof:placetype":"venue"
},
  "geometry": {"coordinates":[-70.400757,47.573349],"type":"Point"}
}