{
  "type": "Feature",
  "properties": {
    "addr:full":"382 Canarctic Dr North York ON M3J 2V3",
    "addr:housenumber":"382",
    "addr:postcode":"m3j 2v3",
    "addr:street":"Canarctic Dr",
    "iso:country":"CA",
    "sg:address":"382 Canarctic Dr",
    "sg:city":"North York",
    "sg:classifiers":[
        {
            "category":"Wholesale",
            "subcategory":"Stationery",
            "type":"Manufacturing & Wholesale Goods"
        }
    ],
    "sg:phone":"+1 416 741 8716",
    "sg:postcode":"M3J 2V3",
    "sg:province":"ON",
    "sg:tags":[
        "box",
        "packaging"
    ],
    "wof:name":"Dennis Colt Packaging Ltd",
    "wof:placetype":"venue"
},
  "geometry": {"coordinates":[-79.487297,43.776779],"type":"Point"}
}