{
  "type": "Feature",
  "properties": {
    "addr:full":"737 Parkdale Ave Ottawa ON K1Y 1J8",
    "addr:housenumber":"737",
    "addr:postcode":"k1y 1j8",
    "addr:street":"Parkdale Ave",
    "iso:country":"CA",
    "sg:address":"737 Parkdale Ave",
    "sg:city":"Ottawa",
    "sg:classifiers":[
        {
            "category":"Health Services",
            "subcategory":"Doctor",
            "type":"Services"
        }
    ],
    "sg:phone":"+1 613 761 5177",
    "sg:postcode":"K1Y 1J8",
    "sg:province":"ON",
    "sg:tags":[
        "clinic"
    ],
    "wof:name":"Fertility Centre",
    "wof:placetype":"venue"
},
  "geometry": {"coordinates":[-75.723839,45.392353],"type":"Point"}
}