{
  "type": "Feature",
  "properties": {
    "addr:full":"580 Queen St Chatham ON N7M 2J8",
    "addr:housenumber":"580",
    "addr:postcode":"n7m 2j8",
    "addr:street":"Queen St",
    "iso:country":"CA",
    "sg:address":"580 Queen St",
    "sg:city":"Chatham",
    "sg:classifiers":[
        {
            "category":"Shopping",
            "subcategory":"Computers & Home Electronics",
            "type":"Retail Goods"
        }
    ],
    "sg:phone":"+1 519 436 1148",
    "sg:postcode":"N7M 2J8",
    "sg:province":"ON",
    "sg:tags":[
        "equipment",
        "dealer"
    ],
    "wof:name":"Canada Business Svc",
    "wof:placetype":"venue"
},
  "geometry": {"coordinates":[-82.173149,42.393158],"type":"Point"}
}