{
  "type": "Feature",
  "properties": {
    "addr:full":"99 Ninth St Etobicoke ON M8V 3E5",
    "addr:housenumber":"99",
    "addr:postcode":"m8v 3e5",
    "addr:street":"Ninth St",
    "iso:country":"CA",
    "sg:address":"99 Ninth St",
    "sg:city":"Etobicoke",
    "sg:classifiers":[
        {
            "category":"Social Services",
            "type":"Services"
        }
    ],
    "sg:phone":"+1 416 259 3376",
    "sg:postcode":"M8V 3E5",
    "sg:province":"ON",
    "sg:tags":[
        "youth",
        "organization",
        "center"
    ],
    "wof:name":"Etobicoke Girls Residence",
    "wof:placetype":"venue"
},
  "geometry": {"coordinates":[-79.50694300000001,43.599155],"type":"Point"}
}