{
  "type": "Feature",
  "properties": {
    "addr:full":"3702 Alberni Hwy Qualicum Beach BC V9K 1X7",
    "addr:housenumber":"3702",
    "addr:postcode":"v9k 1x7",
    "addr:street":"Alberni Hwy",
    "iso:country":"CA",
    "sg:address":"3702 Alberni Hwy",
    "sg:city":"Qualicum Beach",
    "sg:classifiers":[
        {
            "category":"Autos & Motor Vehicles",
            "subcategory":"Fuel & Gas Station",
            "type":"Retail Goods"
        }
    ],
    "sg:phone":"+1 250 752 9261",
    "sg:postcode":"V9K 1X7",
    "sg:province":"BC",
    "sg:tags":[
        "oil"
    ],
    "wof:name":"Whiskey Creek Store",
    "wof:placetype":"venue"
},
  "geometry": {"coordinates":[-124.441704,49.346706],"type":"Point"}
}