{
  "type": "Feature",
  "properties": {
    "addr:full":"Saint-Odilon QC G0S 3A0",
    "addr:postcode":"g0s 3a0",
    "addr:street":"Saint-Odilon",
    "iso:country":"CA",
    "sg:city":"Saint-Odilon",
    "sg:classifiers":[
        {
            "category":"Retail",
            "subcategory":"Auto Repair",
            "type":"Services"
        }
    ],
    "sg:phone":"+1 418 464 4691",
    "sg:postcode":"G0S 3A0",
    "sg:province":"QC",
    "sg:tags":[
        "repairing",
        "automobile"
    ],
    "wof:name":"Agence Mecanique Courtney Inc",
    "wof:placetype":"venue"
},
  "geometry": {"coordinates":[-70.6783370972,46.3567085266],"type":"Point"}
}