{
  "type": "Feature",
  "properties": {
    "addr:full":"99 4th St Hague SK S0K 1X0",
    "addr:housenumber":"99",
    "addr:postcode":"s0k 1x0",
    "addr:street":"4Th St",
    "iso:country":"CA",
    "sg:address":"99 4th St",
    "sg:city":"Hague",
    "sg:classifiers":[
        {
            "category":"Autos & Motor Vehicles",
            "subcategory":"Fuel & Gas Station",
            "type":"Retail Goods"
        }
    ],
    "sg:phone":"+1 306 225 4448",
    "sg:postcode":"S0K 1X0",
    "sg:province":"SK",
    "sg:tags":[
        "oil"
    ],
    "wof:name":"Shell & Confectionery",
    "wof:placetype":"venue"
},
  "geometry": {"coordinates":[-106.41457366900001,52.5097808838],"type":"Point"}
}