{
  "type": "Feature",
  "properties": {
    "addr:full":"Main St Channel-Port-Aux-Basques NL A0M 1C0",
    "addr:postcode":"a0m 1c0",
    "addr:street":"Main St",
    "iso:country":"CA",
    "sg:address":"Main St",
    "sg:city":"Channel-Port-Aux-Basques",
    "sg:classifiers":[
        {
            "category":"Government",
            "subcategory":"Office",
            "type":"Public Place"
        }
    ],
    "sg:phone":"+1 709 695 2835",
    "sg:postcode":"A0M 1C0",
    "sg:province":"NL",
    "wof:name":"Personal Care Homes Public",
    "wof:placetype":"venue"
},
  "geometry": {"coordinates":[-59.142372,47.573521],"type":"Point"}
}