{
  "type": "Feature",
  "properties": {
    "addr:full":"19 Bellerose Dr St Albert AB T8N 5E1",
    "addr:housenumber":"19",
    "addr:postcode":"t8n 5e1",
    "addr:street":"Bellerose Dr",
    "iso:country":"CA",
    "sg:address":"19 Bellerose Dr",
    "sg:city":"St Albert",
    "sg:classifiers":[
        {
            "category":"Cinema",
            "subcategory":"Movie Rental",
            "type":"Entertainment"
        }
    ],
    "sg:phone":"+1 780 458 3636",
    "sg:postcode":"T8N 5E1",
    "sg:province":"AB",
    "sg:tags":[
        "player",
        "recorder",
        "video",
        "leasing",
        "tape"
    ],
    "wof:name":"Rogers Video",
    "wof:placetype":"venue"
},
  "geometry": {"coordinates":[-113.622505,53.645943],"type":"Point"}
}