{
  "type": "Feature",
  "properties": {
    "addr:full":"Edmonton AB T5E 6A3",
    "addr:postcode":"t5e 6a3",
    "iso:country":"CA",
    "sg:city":"Edmonton",
    "sg:classifiers":[
        {
            "category":"Food & Beverages",
            "subcategory":"Bakery",
            "type":"Retail Goods"
        }
    ],
    "sg:phone":"+1 780 475 5996",
    "sg:postcode":"T5E 6A3",
    "sg:province":"AB",
    "sg:tags":[
        "baker"
    ],
    "wof:name":"Greek Bakery & Deli Ltd",
    "wof:placetype":"venue"
},
  "geometry": {"coordinates":[-113.482674,53.606121],"type":"Point"}
}