{
  "type": "Feature",
  "properties": {
    "iso:country":"CA",
    "sg:address":"60 Colonnade Rd",
    "sg:city":"Nepean",
    "sg:classifiers":[
        {
            "category":"Freight",
            "type":"Transportation"
        }
    ],
    "sg:phone":"+1 613 226 4944",
    "sg:postcode":"K2E 7J6",
    "sg:province":"ON",
    "sg:tags":[
        "delivery",
        "courier"
    ],
    "wof:name":"Dynamex",
    "wof:placetype":"venue"
},
  "geometry": {"coordinates":[-75.71347045900001,45.3455848694],"type":"Point"}
}