{
  "type": "Feature",
  "properties": {
    "addr:full":"4920 Ch Des Grands-Coteaux Saint-Mathieu-DE-Beloeil QC J3G 2C9",
    "addr:postcode":"4920;j3g 2c9",
    "addr:street":"Ch Des Grands-Coteaux",
    "iso:country":"CA",
    "sg:address":"4920 Ch Des Grands-Coteaux",
    "sg:city":"Saint-Mathieu-DE-Beloeil",
    "sg:classifiers":[
        {
            "category":"Cinema",
            "subcategory":"Movie Theater",
            "type":"Entertainment"
        }
    ],
    "sg:phone":"+1 450 446 2266",
    "sg:postcode":"J3G 2C9",
    "sg:province":"QC",
    "wof:name":"Theatre Des Hirondelles",
    "wof:placetype":"venue"
},
  "geometry": {"coordinates":[-73.27127838129999,45.6052246094],"type":"Point"}
}