{
  "type": "Feature",
  "properties": {
    "addr:full":"51 Park St # 49 Corner Brook NL A2H 2X1",
    "addr:housenumber":"51",
    "addr:postcode":"a2h 2x1",
    "addr:street":"Park St # 49",
    "iso:country":"CA",
    "sg:address":"51 Park St # 49",
    "sg:city":"Corner Brook",
    "sg:classifiers":[
        {
            "category":"Professional",
            "subcategory":"Computer Services",
            "type":"Services"
        }
    ],
    "sg:phone":"+1 709 634 4382",
    "sg:postcode":"A2H 2X1",
    "sg:province":"NL",
    "sg:tags":[
        "consultant",
        "accountant"
    ],
    "wof:name":"Grant Thornton Llp",
    "wof:placetype":"venue"
},
  "geometry": {"coordinates":[-57.941715,48.950687],"type":"Point"}
}