{
  "type": "Feature",
  "properties": {
    "iso:country":"CA",
    "sg:city":"Saint John",
    "sg:classifiers":[
        {
            "category":"Wholesale",
            "subcategory":"Hardware",
            "type":"Manufacturing & Wholesale Goods"
        }
    ],
    "sg:phone":"+1 506 658 0730",
    "sg:postcode":"E2L 4Z6",
    "sg:province":"NB",
    "sg:tags":[
        "steam",
        "specialty"
    ],
    "wof:name":"Preston Phipps Inc",
    "wof:placetype":"venue"
},
  "geometry": {"coordinates":[-66.0747680664,45.2612686157],"type":"Point"}
}