{
  "type": "Feature",
  "properties": {
    "addr:full":"1053 Boul Ducharme LA Tuque QC G9X 3C3",
    "addr:housenumber":"1053",
    "addr:postcode":"g9x 3c3",
    "addr:street":"Boul Ducharme",
    "iso:country":"CA",
    "sg:address":"1053 Boul Ducharme",
    "sg:city":"LA Tuque",
    "sg:classifiers":[
        {
            "category":"Wholesale",
            "subcategory":"Auto Parts",
            "type":"Manufacturing & Wholesale Goods"
        }
    ],
    "sg:phone":"+1 819 523 4465",
    "sg:postcode":"G9X 3C3",
    "sg:province":"QC",
    "sg:tags":[
        "equipment",
        "truck",
        "automobile",
        "supply"
    ],
    "wof:name":"Pieces Industrielles Rgr Inc",
    "wof:placetype":"venue"
},
  "geometry": {"coordinates":[-72.785263,47.423523],"type":"Point"}
}