{
  "type": "Feature",
  "properties": {
    "addr:full":"2350 Rue Guenette Saint-Laurent QC H4R 2H2",
    "addr:housenumber":"2350",
    "addr:postcode":"h4r 2h2",
    "addr:street":"Rue Guenette",
    "iso:country":"CA",
    "sg:address":"2350 Rue Guenette",
    "sg:city":"Saint-Laurent",
    "sg:classifiers":[
        {
            "category":"Manufacturing",
            "subcategory":"Tools & Machinery",
            "type":"Manufacturing & Wholesale Goods"
        }
    ],
    "sg:phone":"+1 514 337 5200",
    "sg:postcode":"H4R 2H2",
    "sg:province":"QC",
    "sg:tags":[
        "equipment",
        "hospital",
        "supply"
    ],
    "wof:name":"Trudell Medicale Ltee",
    "wof:placetype":"venue"
},
  "geometry": {"coordinates":[-73.7283782959,45.4998779297],"type":"Point"}
}