{
  "type": "Feature",
  "properties": {
    "addr:full":"569 Rue Laviolette Mont-Laurier QC J9L 2J2",
    "addr:housenumber":"569",
    "addr:postcode":"j9l 2j2",
    "addr:street":"Rue Laviolette",
    "iso:country":"CA",
    "sg:address":"569 Rue Laviolette",
    "sg:city":"Mont-Laurier",
    "sg:classifiers":[
        {
            "category":"Health Services",
            "subcategory":"Nursing And Care Facility",
            "type":"Services"
        }
    ],
    "sg:phone":"+1 819 623 5300",
    "sg:postcode":"J9L 2J2",
    "sg:province":"QC",
    "sg:tags":[
        "home",
        "retirement",
        "community"
    ],
    "wof:name":"Residences Des Violettes",
    "wof:placetype":"venue"
},
  "geometry": {"coordinates":[-75.5083694458,46.5506744385],"type":"Point"}
}