{
  "type": "Feature",
  "properties": {
    "addr:full":"1111 Oxford St E London ON N5Y 3L7",
    "addr:housenumber":"1111",
    "addr:postcode":"n5y 3l7",
    "addr:street":"Oxford St E",
    "iso:country":"CA",
    "sg:address":"1111 Oxford St E",
    "sg:city":"London",
    "sg:classifiers":[
        {
            "category":"Autos & Motor Vehicles",
            "subcategory":"Automobile Sales",
            "type":"Retail Goods"
        }
    ],
    "sg:phone":"+1 519 451 4560",
    "sg:postcode":"N5Y 3L7",
    "sg:province":"ON",
    "sg:tags":[
        "car",
        "dealer"
    ],
    "wof:name":"Dale Downie Pontiac Buick Gmc",
    "wof:placetype":"venue"
},
  "geometry": {"coordinates":[-81.216758728,43.0060005188],"type":"Point"}
}