{
  "type": "Feature",
  "properties": {
    "addr:full":"11725 93 St NW Edmonton AB T5G 1E2",
    "addr:housenumber":"11725",
    "addr:postcode":"t5g 1e2",
    "addr:street":"93 St Nw",
    "iso:country":"CA",
    "sg:address":"11725 93 St NW",
    "sg:city":"Edmonton",
    "sg:classifiers":[
        {
            "category":"Organizations",
            "subcategory":"Religious Organization",
            "type":"Services"
        }
    ],
    "sg:phone":"+1 780 477 5931",
    "sg:postcode":"T5G 1E2",
    "sg:province":"AB",
    "sg:tags":[
        "church"
    ],
    "wof:name":"St Faith's Anglican Church",
    "wof:placetype":"venue"
},
  "geometry": {"coordinates":[-113.483986,53.569336],"type":"Point"}
}