{
  "type": "Feature",
  "properties": {
    "addr:full":"542 7E Rang Saint-Dominique QC J0H 1L0",
    "addr:housenumber":"542",
    "addr:postcode":"j0h 1l0",
    "addr:street":"7E Rang Saint-Dominique",
    "iso:country":"CA",
    "sg:address":"542 7E Rang",
    "sg:city":"Saint-Dominique",
    "sg:classifiers":[
        {
            "category":"Manufacturing",
            "subcategory":"Furniture",
            "type":"Manufacturing & Wholesale Goods"
        }
    ],
    "sg:phone":"+1 450 774 2783",
    "sg:postcode":"J0H 1L0",
    "sg:province":"QC",
    "sg:tags":[
        "maker",
        "store",
        "cabinet"
    ],
    "wof:name":"Menui-Decor",
    "wof:placetype":"venue"
},
  "geometry": {"coordinates":[-72.84992200000001,45.579147],"type":"Point"}
}