{
  "type": "Feature",
  "properties": {
    "addr:full":"Mount Stewart PE C0A 1T0",
    "addr:postcode":"c0a 1t0",
    "iso:country":"CA",
    "sg:city":"Mount Stewart",
    "sg:classifiers":[
        {
            "category":"Organizations",
            "subcategory":"Religious Organization",
            "type":"Services"
        }
    ],
    "sg:phone":"+1 902 583 2095",
    "sg:postcode":"C0A 1T0",
    "sg:province":"PE",
    "sg:tags":[
        "church"
    ],
    "wof:name":"St Cuthbert's Parish House",
    "wof:placetype":"venue"
},
  "geometry": {"coordinates":[-62.8627433777,46.3645095825],"type":"Point"}
}