{
  "type": "Feature",
  "properties": {
    "addr:full":"1614 Lesperance Rd Windsor ON N8N 1Y3",
    "addr:housenumber":"1614",
    "addr:postcode":"n8n 1y3",
    "addr:street":"Lesperance Rd",
    "iso:country":"CA",
    "sg:address":"1614 Lesperance Rd",
    "sg:city":"Windsor",
    "sg:classifiers":[
        {
            "category":"Manufacturing",
            "subcategory":"Printing",
            "type":"Manufacturing & Wholesale Goods"
        }
    ],
    "sg:phone":"+1 519 735 2080",
    "sg:postcode":"N8N 1Y3",
    "sg:province":"ON",
    "sg:tags":[
        "newspaper"
    ],
    "wof:name":"Shoreline Week",
    "wof:placetype":"venue"
},
  "geometry": {"coordinates":[-83.0339126587,42.3178215027],"type":"Point"}
}