{
  "type": "Feature",
  "properties": {
    "iso:country":"CA",
    "sg:address":"1611 Britannia Rd E",
    "sg:city":"Mississauga",
    "sg:classifiers":[
        {
            "category":"Manufacturing",
            "subcategory":"Rubber & Plastics",
            "type":"Manufacturing & Wholesale Goods"
        }
    ],
    "sg:phone":"+1 905 670 7771",
    "sg:postcode":"L4W 1S5",
    "sg:province":"ON",
    "sg:tags":[
        "chemical",
        "container"
    ],
    "wof:name":"Contor Terminals",
    "wof:placetype":"venue"
},
  "geometry": {"coordinates":[-79.6447753906,43.6580848694],"type":"Point"}
}