{
  "type": "Feature",
  "properties": {
    "addr:full":"280 St George St E Fergus ON N1M 1K4",
    "addr:housenumber":"280",
    "addr:postcode":"n1m 1k4",
    "addr:street":"St George St E",
    "iso:country":"CA",
    "sg:address":"280 St George St E",
    "sg:city":"Fergus",
    "sg:classifiers":[
        {
            "category":"Professional",
            "subcategory":"Management & Consulting",
            "type":"Services"
        }
    ],
    "sg:phone":"+1 519 843 3977",
    "sg:postcode":"N1M 1K4",
    "sg:province":"ON",
    "sg:tags":[
        "employee",
        "consultant",
        "benefit"
    ],
    "wof:name":"Brooks Insurance & Financial",
    "wof:placetype":"venue"
},
  "geometry": {"coordinates":[-80.37696099999999,43.708992],"type":"Point"}
}