{
  "type": "Feature",
  "properties": {
    "iso:country":"CA",
    "sg:address":"6182 Eagle Dr",
    "sg:city":"Whistler",
    "sg:classifiers":[
        {
            "category":"Travel",
            "subcategory":"Hotels & Motels",
            "type":"Entertainment"
        }
    ],
    "sg:phone":"+1 604 938 3292",
    "sg:postcode":"V0N 1B6",
    "sg:province":"BC",
    "sg:tags":[
        "breakfast",
        "accommodation",
        "bed"
    ],
    "wof:name":"Chalet Bambi Bed & Breakfast",
    "wof:placetype":"venue"
},
  "geometry": {"coordinates":[-122.96220398,50.1203842163],"type":"Point"}
}