{
  "type": "Feature",
  "properties": {
    "addr:full":"6300 King Vaughan Rd Kleinburg ON L0J 1C0",
    "addr:housenumber":"6300",
    "addr:postcode":"l0j 1c0",
    "addr:street":"King Vaughan Rd",
    "iso:country":"CA",
    "sg:address":"6300 King Vaughan Rd",
    "sg:city":"Kleinburg",
    "sg:classifiers":[
        {
            "category":"Building & Trades",
            "subcategory":"Landscaping Services",
            "type":"Services"
        }
    ],
    "sg:phone":"+1 905 859 4555",
    "sg:postcode":"L0J 1C0",
    "sg:province":"ON",
    "sg:tags":[
        "landscape",
        "contractor"
    ],
    "wof:name":"Bruce Wilson Landscaping Ltd",
    "wof:placetype":"venue"
},
  "geometry": {"coordinates":[-79.65791299999999,43.882042],"type":"Point"}
}