{
  "type": "Feature",
  "properties": {
    "addr:full":"4557 Rue Saint-Denis Montreal QC H2J 2L4",
    "addr:housenumber":"4557",
    "addr:postcode":"h2j 2l4",
    "addr:street":"Rue Saint-Denis",
    "iso:country":"CA",
    "sg:address":"4557 Rue Saint-Denis",
    "sg:city":"Montreal",
    "sg:classifiers":[
        {
            "category":"Bars & Pubs",
            "type":"Food & Drink"
        }
    ],
    "sg:phone":"+1 514 849 5888",
    "sg:postcode":"H2J 2L4",
    "sg:province":"QC",
    "sg:tags":[
        "discotheque"
    ],
    "wof:name":"Au Diable Vert",
    "wof:placetype":"venue"
},
  "geometry": {"coordinates":[-73.583519,45.52441],"type":"Point"}
}