{
  "type": "Feature",
  "properties": {
    "addr:full":"56 Romeo Cres Woodbridge ON L4L 7A1",
    "addr:housenumber":"56",
    "addr:postcode":"l4l 7a1",
    "addr:street":"Romeo Cres",
    "iso:country":"CA",
    "sg:address":"56 Romeo Cres",
    "sg:city":"Woodbridge",
    "sg:classifiers":[
        {
            "category":"Building & Trades",
            "subcategory":"Construction",
            "type":"Services"
        }
    ],
    "sg:phone":"+1 416 630 7756",
    "sg:postcode":"L4L 7A1",
    "sg:province":"ON",
    "sg:tags":[
        "excavating",
        "contractor"
    ],
    "wof:name":"Weston Excavating & Grading",
    "wof:placetype":"venue"
},
  "geometry": {"coordinates":[-79.55798299999999,43.809502],"type":"Point"}
}