{
  "type": "Feature",
  "properties": {
    "iso:country":"CA",
    "sg:address":"128 Clark St",
    "sg:city":"Fredericton",
    "sg:classifiers":[
        {
            "category":"Manufacturing",
            "subcategory":"Tools & Machinery",
            "type":"Manufacturing & Wholesale Goods"
        }
    ],
    "sg:phone":"+1 506 458 9305",
    "sg:postcode":"E3A 2W7",
    "sg:province":"NB",
    "sg:tags":[
        "machine",
        "shop",
        "engine"
    ],
    "wof:name":"Engine Machine Shop",
    "wof:placetype":"venue"
},
  "geometry": {"coordinates":[-66.6285247803,45.9681663513],"type":"Point"}
}