{
  "type": "Feature",
  "properties": {
    "addr:full":"6550 Boul Maurice-Duplessis Montreal-Nord QC H1G 6K9",
    "addr:housenumber":"6550",
    "addr:postcode":"h1g 6k9",
    "addr:street":"Boul Maurice-Duplessis",
    "iso:country":"CA",
    "sg:address":"6550 Boul Maurice-Duplessis",
    "sg:city":"Montreal-Nord",
    "sg:classifiers":[
        {
            "category":"Social Services",
            "subcategory":"Child Care",
            "type":"Services"
        }
    ],
    "sg:phone":"+1 514 323 3079",
    "sg:postcode":"H1G 6K9",
    "sg:province":"QC",
    "wof:name":"Cpe Emmanuel",
    "wof:placetype":"venue"
},
  "geometry": {"coordinates":[-73.61412,45.617367],"type":"Point"}
}