{
  "type": "Feature",
  "properties": {
    "addr:full":"6911 Creditview Rd Mississauga ON L5N 8G1",
    "addr:housenumber":"6911",
    "addr:postcode":"l5n 8g1",
    "addr:street":"Creditview Rd",
    "iso:country":"CA",
    "sg:address":"6911 Creditview Rd",
    "sg:city":"Mississauga",
    "sg:classifiers":[
        {
            "category":"Wholesale",
            "subcategory":"Computers",
            "type":"Manufacturing & Wholesale Goods"
        }
    ],
    "sg:phone":"+1 905 286 6800",
    "sg:postcode":"L5N 8G1",
    "sg:province":"ON",
    "wof:name":"Tech Data Canada Inc",
    "wof:placetype":"venue"
},
  "geometry": {"coordinates":[-79.7406234741,43.6128120422],"type":"Point"}
}