{
  "type": "Feature",
  "properties": {
    "addr:full":"296 Richmond St W Toronto ON M5V 1X2",
    "addr:housenumber":"296",
    "addr:postcode":"m5v 1x2",
    "addr:street":"Richmond St W",
    "iso:country":"CA",
    "sg:address":"296 Richmond St W",
    "sg:city":"Toronto",
    "sg:classifiers":[
        {
            "category":"Freight",
            "type":"Transportation"
        }
    ],
    "sg:phone":"+1 416 598 3422",
    "sg:postcode":"M5V 1X2",
    "sg:province":"ON",
    "sg:tags":[
        "courier"
    ],
    "wof:name":"Datarush Courier Svc",
    "wof:placetype":"venue"
},
  "geometry": {"coordinates":[-79.3913803101,43.6491203308],"type":"Point"}
}