{
  "type": "Feature",
  "properties": {
    "addr:full":"2560 Rue Saint-Charles Saint-Laurent QC H4R 1B4",
    "addr:housenumber":"2560",
    "addr:postcode":"h4r 1b4",
    "addr:street":"Rue Saint-Charles",
    "iso:country":"CA",
    "sg:address":"2560 Rue Saint-Charles",
    "sg:city":"Saint-Laurent",
    "sg:classifiers":[
        {
            "category":"Manufacturing",
            "subcategory":"Metals",
            "type":"Manufacturing & Wholesale Goods"
        }
    ],
    "sg:phone":"+1 514 334 5412",
    "sg:postcode":"H4R 1B4",
    "sg:province":"QC",
    "sg:tags":[
        "coating"
    ],
    "wof:name":"Monitor-Simpsons Inc",
    "wof:placetype":"venue"
},
  "geometry": {"coordinates":[-73.71970399999999,45.515968],"type":"Point"}
}