{
  "type": "Feature",
  "properties": {
    "addr:full":"595 King St E Oshawa ON L1H 1G3",
    "addr:housenumber":"595",
    "addr:postcode":"l1h 1g3",
    "addr:street":"King St E",
    "iso:country":"CA",
    "sg:address":"595 King St E",
    "sg:city":"Oshawa",
    "sg:classifiers":[
        {
            "category":"Freight",
            "type":"Transportation"
        }
    ],
    "sg:phone":"+1 905 436 3370",
    "sg:postcode":"L1H 1G3",
    "sg:province":"ON",
    "sg:tags":[
        "courier"
    ],
    "wof:name":"Purolator Courier Ltd",
    "wof:placetype":"venue"
},
  "geometry": {"coordinates":[-78.8419265747,43.902469635],"type":"Point"}
}