{
  "type": "Feature",
  "properties": {
    "addr:full":"211 Main St Rosetown SK S0L 2V0",
    "addr:housenumber":"211",
    "addr:postcode":"s0l 2v0",
    "addr:street":"Main St",
    "iso:country":"CA",
    "sg:address":"211 Main St",
    "sg:city":"Rosetown",
    "sg:classifiers":[
        {
            "category":"Shopping",
            "subcategory":"Computers & Home Electronics",
            "type":"Retail Goods"
        }
    ],
    "sg:phone":"+1 306 882 4432",
    "sg:postcode":"S0L 2V0",
    "sg:province":"SK",
    "sg:tags":[
        "shop",
        "equipment",
        "fabric",
        "dealer"
    ],
    "wof:name":"Sew Special",
    "wof:placetype":"venue"
},
  "geometry": {"coordinates":[-107.99166099999999,51.551064],"type":"Point"}
}