{
  "type": "Feature",
  "properties": {
    "addr:full":"London ON N6E 3R6",
    "addr:postcode":"n6e 3r6",
    "iso:country":"CA",
    "sg:city":"London",
    "sg:classifiers":[
        {
            "category":"Arts & Performance",
            "subcategory":"Theater",
            "type":"Entertainment"
        }
    ],
    "sg:phone":"+1 519 649 2998",
    "sg:postcode":"N6E 3R6",
    "sg:province":"ON",
    "sg:tags":[
        "live",
        "music"
    ],
    "wof:name":"Black Tie Productions",
    "wof:placetype":"venue"
},
  "geometry": {"coordinates":[-81.24572000000001,42.933605],"type":"Point"}
}