{
  "type": "Feature",
  "properties": {
    "addr:full":"Prince George BC V2L 2Z3",
    "addr:postcode":"v2l 2z3",
    "iso:country":"CA",
    "sg:city":"Prince George",
    "sg:classifiers":[
        {
            "category":"Manufacturing",
            "subcategory":"Tools & Machinery",
            "type":"Manufacturing & Wholesale Goods"
        }
    ],
    "sg:phone":"+1 250 563 3312",
    "sg:postcode":"V2L 2Z3",
    "sg:province":"BC",
    "sg:tags":[
        "machine",
        "shop"
    ],
    "wof:name":"P G Machine Works",
    "wof:placetype":"venue"
},
  "geometry": {"coordinates":[-122.758674622,53.9228057861],"type":"Point"}
}