{
  "type": "Feature",
  "properties": {
    "iso:country":"CA",
    "sg:address":"1776 Strathcona Ave",
    "sg:city":"Prince George",
    "sg:classifiers":[
        {
            "category":"Food & Beverages",
            "subcategory":"Groceries & Convenience Stores",
            "type":"Retail Goods"
        }
    ],
    "sg:phone":"+1 250 562 9336",
    "sg:postcode":"V2L 4E8",
    "sg:province":"BC",
    "sg:tags":[
        "grocer"
    ],
    "wof:name":"Pgi Grocery Express",
    "wof:placetype":"venue"
},
  "geometry": {"coordinates":[-122.759788513,53.9024887085],"type":"Point"}
}