{
  "type": "Feature",
  "properties": {
    "addr:full":"2083 Rue Beaudry Montreal QC H2L 3G4",
    "addr:housenumber":"2083",
    "addr:postcode":"h2l 3g4",
    "addr:street":"Rue Beaudry",
    "iso:country":"CA",
    "sg:address":"2083 Rue Beaudry",
    "sg:city":"Montreal",
    "sg:classifiers":[
        {
            "category":"Real Estate",
            "subcategory":"Architect",
            "type":"Services"
        }
    ],
    "sg:phone":"+1 514 598 0265",
    "sg:postcode":"H2L 3G4",
    "sg:province":"QC",
    "wof:name":"Renee D'Amours Architects",
    "wof:placetype":"venue"
},
  "geometry": {"coordinates":[-73.563057,45.522152],"type":"Point"}
}