{
  "type": "Feature",
  "properties": {
    "addr:full":"206 Rue Jarry E Montreal QC H2P 1T5",
    "addr:housenumber":"206",
    "addr:postcode":"h2p 1t5",
    "addr:street":"Rue Jarry E",
    "iso:country":"CA",
    "sg:address":"206 Rue Jarry E",
    "sg:city":"Montreal",
    "sg:classifiers":[
        {
            "category":"Restaurant",
            "type":"Food & Drink"
        }
    ],
    "sg:phone":"+1 514 381 8176",
    "sg:postcode":"H2P 1T5",
    "sg:province":"QC",
    "wof:name":"Filoti Pizzeria",
    "wof:placetype":"venue"
},
  "geometry": {"coordinates":[-73.63014200000001,45.540783],"type":"Point"}
}