{
  "type": "Feature",
  "properties": {
    "addr:full":"153 Montreal Ave E Morris MB R0G 1K0",
    "addr:housenumber":"153",
    "addr:postcode":"r0g 1k0",
    "addr:street":"Montreal Ave E",
    "iso:country":"CA",
    "sg:address":"153 Montreal Ave E",
    "sg:city":"Morris",
    "sg:classifiers":[
        {
            "category":"Social Services",
            "subcategory":"Adult Care",
            "type":"Services"
        }
    ],
    "sg:phone":"+1 204 746 8836",
    "sg:postcode":"R0G 1K0",
    "sg:province":"MB",
    "sg:tags":[
        "organization",
        "senior",
        "citizen"
    ],
    "wof:name":"Davidson Memorial Ctr",
    "wof:placetype":"venue"
},
  "geometry": {"coordinates":[-97.35963439939999,49.3510437012],"type":"Point"}
}