{
  "type": "Feature",
  "properties": {
    "addr:full":"52 Keelegate Pl Winnipeg MB R2N 3V7",
    "addr:housenumber":"52",
    "addr:postcode":"r2n 3v7",
    "addr:street":"Keelegate Pl",
    "iso:country":"CA",
    "sg:address":"52 Keelegate Pl",
    "sg:city":"Winnipeg",
    "sg:classifiers":[
        {
            "category":"Retail",
            "subcategory":"Portrait Studio",
            "type":"Services"
        }
    ],
    "sg:phone":"+1 204 254 6813",
    "sg:postcode":"R2N 3V7",
    "sg:province":"MB",
    "sg:tags":[
        "photographer"
    ],
    "wof:name":"Rygiel Wedding Photography",
    "wof:placetype":"venue"
},
  "geometry": {"coordinates":[-97.0840148926,49.8072128296],"type":"Point"}
}