{
  "type": "Feature",
  "properties": {
    "addr:full":"217 Clandeboye Ave Selkirk MB R1A 0X2",
    "addr:housenumber":"217",
    "addr:postcode":"r1a 0x2",
    "addr:street":"Clandeboye Ave",
    "iso:country":"CA",
    "sg:address":"217 Clandeboye Ave",
    "sg:city":"Selkirk",
    "sg:classifiers":[
        {
            "category":"Manufacturing",
            "subcategory":"Printing",
            "type":"Manufacturing & Wholesale Goods"
        }
    ],
    "sg:phone":"+1 204 452 3752",
    "sg:postcode":"R1A 0X2",
    "sg:province":"MB",
    "sg:tags":[
        "printer"
    ],
    "wof:name":"Interlake Publishing",
    "wof:placetype":"venue"
},
  "geometry": {"coordinates":[-96.870667,50.143475],"type":"Point"}
}