{
  "type": "Feature",
  "properties": {
    "addr:full":"Montreal QC H2N 2B7",
    "addr:postcode":"h2n 2b7",
    "iso:country":"CA",
    "sg:city":"Montreal",
    "sg:classifiers":[
        {
            "category":"Manufacturing",
            "subcategory":"Apparel",
            "type":"Manufacturing & Wholesale Goods"
        }
    ],
    "sg:phone":"+1 514 383 1951",
    "sg:postcode":"H2N 2B7",
    "sg:province":"QC",
    "sg:tags":[
        "clothing"
    ],
    "wof:name":"Nouvelle Seamless",
    "wof:placetype":"venue"
},
  "geometry": {"coordinates":[-73.65850067140001,45.538394928],"type":"Point"}
}