{
  "type": "Feature",
  "properties": {
    "addr:full":"Hwy 17 Clearwater Bay ON P0X 1S0",
    "addr:postcode":"p0x 1s0",
    "addr:street":"Hwy 17",
    "iso:country":"CA",
    "sg:address":"Hwy 17",
    "sg:city":"Clearwater Bay",
    "sg:classifiers":[
        {
            "category":"Shopping",
            "subcategory":"Gifts & Souvenirs",
            "type":"Retail Goods"
        }
    ],
    "sg:phone":"+1 807 733 2366",
    "sg:postcode":"P0X 1S0",
    "sg:province":"ON",
    "sg:tags":[
        "shop"
    ],
    "wof:name":"Pinewood",
    "wof:placetype":"venue"
},
  "geometry": {"coordinates":[-94.75243377690001,49.7160797119],"type":"Point"}
}