{
  "type": "Feature",
  "properties": {
    "addr:full":"41 Mitchell Cres NW Medicine Hat AB T1A 6V2",
    "addr:housenumber":"41",
    "addr:postcode":"t1a 6v2",
    "addr:street":"Mitchell Cres Nw",
    "iso:country":"CA",
    "sg:address":"41 Mitchell Cres NW",
    "sg:city":"Medicine Hat",
    "sg:classifiers":[
        {
            "category":"Health Services",
            "subcategory":"Clinic",
            "type":"Services"
        }
    ],
    "sg:phone":"+1 403 526 9547",
    "sg:postcode":"T1A 6V2",
    "sg:province":"AB",
    "wof:name":"Nursing Care At Home Health",
    "wof:placetype":"venue"
},
  "geometry": {"coordinates":[-110.688095,50.050499],"type":"Point"}
}