{
  "type": "Feature",
  "properties": {
    "addr:full":"1118 Kingston Rd Scarborough ON M1N 1N4",
    "addr:housenumber":"1118",
    "addr:postcode":"m1n 1n4",
    "addr:street":"Kingston Rd",
    "iso:country":"CA",
    "sg:address":"1118 Kingston Rd",
    "sg:city":"Scarborough",
    "sg:classifiers":[
        {
            "category":"Personal",
            "subcategory":"Beauty Salon",
            "type":"Services"
        }
    ],
    "sg:phone":"+1 416 698 4091",
    "sg:postcode":"M1N 1N4",
    "sg:province":"ON",
    "wof:name":"Papillo Beauty Salon",
    "wof:placetype":"venue"
},
  "geometry": {"coordinates":[-79.28173099999999,43.681522],"type":"Point"}
}