{
  "type": "Feature",
  "properties": {
    "iso:country":"CA",
    "sg:city":"St-Peters Bay",
    "sg:classifiers":[
        {
            "category":"Social Services",
            "subcategory":"Child Care",
            "type":"Services"
        }
    ],
    "sg:phone":"+1 902 961 3234",
    "sg:postcode":"C0A 2A0",
    "sg:province":"PE",
    "wof:name":"Friends Forever Child Care Ctr",
    "wof:placetype":"venue"
},
  "geometry": {"coordinates":[-62.582660675,46.4184761047],"type":"Point"}
}