{
  "type": "Feature",
  "properties": {
    "addr:full":"555 Petrolia Rd North York ON M3J 2X8",
    "addr:housenumber":"555",
    "addr:postcode":"m3j 2x8",
    "addr:street":"Petrolia Rd",
    "iso:country":"CA",
    "sg:address":"555 Petrolia Rd",
    "sg:city":"North York",
    "sg:classifiers":[
        {
            "category":"Manufacturing",
            "subcategory":"Metals",
            "type":"Manufacturing & Wholesale Goods"
        }
    ],
    "sg:phone":"+1 416 663 5442",
    "sg:postcode":"M3J 2X8",
    "sg:province":"ON",
    "sg:tags":[
        "stamping"
    ],
    "wof:name":"Stampco Manufacturing Inc",
    "wof:placetype":"venue"
},
  "geometry": {"coordinates":[-79.48825836180001,43.7743034363],"type":"Point"}
}