{
  "type": "Feature",
  "properties": {
    "iso:country":"CA",
    "sg:address":"20451 Logan Ave",
    "sg:city":"Langley",
    "sg:classifiers":[
        {
            "category":"Freight",
            "type":"Transportation"
        }
    ],
    "sg:phone":"+1 604 534 0110",
    "sg:postcode":"V3A 4L8",
    "sg:province":"BC",
    "sg:tags":[
        "commercial",
        "storage"
    ],
    "wof:name":"Langley Mini Storage Park",
    "wof:placetype":"venue"
},
  "geometry": {"coordinates":[-122.6558,49.10722],"type":"Point"}
}