{
  "type": "Feature",
  "properties": {
    "iso:country":"CA",
    "sg:city":"Cap-DE-LA-Madeleine",
    "sg:classifiers":[
        {
            "category":"Shopping",
            "subcategory":"Clothing, Apparel, & Fashions",
            "type":"Retail Goods"
        }
    ],
    "sg:phone":"+1 819 372 9121",
    "sg:postcode":"G8T 6X5",
    "sg:province":"QC",
    "sg:tags":[
        "tailor"
    ],
    "wof:name":"Maison Colby Enr",
    "wof:placetype":"venue"
},
  "geometry": {"coordinates":[-72.5327987671,46.3663444519],"type":"Point"}
}