{
  "type": "Feature",
  "properties": {
    "addr:full":"65 Rue DE Castelnau O Montreal QC H2R 2W3",
    "addr:housenumber":"65",
    "addr:postcode":"h2r 2w3",
    "addr:street":"Rue De Castelnau O",
    "iso:country":"CA",
    "sg:address":"65 Rue DE Castelnau O",
    "sg:city":"Montreal",
    "sg:classifiers":[
        {
            "category":"Professional",
            "subcategory":"Business Services",
            "type":"Services"
        }
    ],
    "sg:phone":"+1 514 495 3058",
    "sg:postcode":"H2R 2W3",
    "sg:province":"QC",
    "sg:tags":[
        "interior",
        "consultant",
        "design",
        "decorator"
    ],
    "wof:name":"Senay, Marguerite",
    "wof:placetype":"venue"
},
  "geometry": {"coordinates":[-73.619339,45.536205],"type":"Point"}
}