{
  "type": "Feature",
  "properties": {
    "iso:country":"CA",
    "sg:address":"4854 Imperial St",
    "sg:city":"Burnaby",
    "sg:classifiers":[
        {
            "category":"Restaurant",
            "type":"Food & Drink"
        }
    ],
    "sg:phone":"+1 604 435 2277",
    "sg:postcode":"V5J 1C4",
    "sg:province":"BC",
    "wof:name":"Golden Wok Chinese Food Ltd",
    "wof:placetype":"venue"
},
  "geometry": {"coordinates":[-122.99485015899999,49.2217330933],"type":"Point"}
}