{
  "type": "Feature",
  "properties": {
    "addr:full":"Calgary AB T2K 4W6",
    "addr:postcode":"t2k 4w6",
    "iso:country":"CA",
    "sg:city":"Calgary",
    "sg:classifiers":[
        {
            "category":"Building & Trades",
            "subcategory":"Construction",
            "type":"Services"
        }
    ],
    "sg:phone":"+1 403 516 0668",
    "sg:postcode":"T2K 4W6",
    "sg:province":"AB",
    "sg:tags":[
        "woodworker"
    ],
    "wof:name":"Datum Millwork",
    "wof:placetype":"venue"
},
  "geometry": {"coordinates":[-114.04990386999999,51.1008300781],"type":"Point"}
}