{
  "type": "Feature",
  "properties": {
    "addr:full":"Aldergrove BC V4W 3V9",
    "addr:postcode":"v4w 3v9",
    "iso:country":"CA",
    "sg:city":"Aldergrove",
    "sg:classifiers":[
        {
            "category":"Retail",
            "subcategory":"Auto Repair",
            "type":"Services"
        }
    ],
    "sg:phone":"+1 604 856 8721",
    "sg:postcode":"V4W 3V9",
    "sg:province":"BC",
    "sg:tags":[
        "wrecker"
    ],
    "wof:name":"Quiring Towing & Heavy Duty",
    "wof:placetype":"venue"
},
  "geometry": {"coordinates":[-122.47229,49.056866],"type":"Point"}
}