{
  "type": "Feature",
  "properties": {
    "addr:full":"115 Boul Deguire Saint-Laurent QC H4N 1N7",
    "addr:housenumber":"115",
    "addr:postcode":"h4n 1n7",
    "addr:street":"Boul Deguire",
    "iso:country":"CA",
    "sg:address":"115 Boul Deguire",
    "sg:city":"Saint-Laurent",
    "sg:classifiers":[
        {
            "category":"Personal",
            "subcategory":"Beauty Salon",
            "type":"Services"
        }
    ],
    "sg:phone":"+1 514 331 8459",
    "sg:postcode":"H4N 1N7",
    "sg:province":"QC",
    "wof:name":"Salon Marie-Claude",
    "wof:placetype":"venue"
},
  "geometry": {"coordinates":[-73.67268371580001,45.531337738],"type":"Point"}
}