{
  "type": "Feature",
  "properties": {
    "iso:country":"CA",
    "sg:address":"207 Rue Principale",
    "sg:city":"Saint-Stanislas-DE-Champlain",
    "sg:classifiers":[
        {
            "category":"Personal",
            "subcategory":"Beauty Salon",
            "type":"Services"
        }
    ],
    "sg:phone":"+1 418 328 3158",
    "sg:postcode":"G0X 3E0",
    "sg:province":"QC",
    "wof:name":"Salon Louison",
    "wof:placetype":"venue"
},
  "geometry": {"coordinates":[-72.3848724365,46.6110038757],"type":"Point"}
}