{
  "type": "Feature",
  "properties": {
    "addr:full":"1500 Hopkins St Whitby ON L1N 2C3",
    "addr:housenumber":"1500",
    "addr:postcode":"l1n 2c3",
    "addr:street":"Hopkins St",
    "iso:country":"CA",
    "sg:address":"1500 Hopkins St",
    "sg:city":"Whitby",
    "sg:classifiers":[
        {
            "category":"Professional",
            "subcategory":"Computer Services",
            "type":"Services"
        }
    ],
    "sg:phone":"+1 905 665 7998",
    "sg:postcode":"L1N 2C3",
    "sg:province":"ON",
    "sg:tags":[
        "repair"
    ],
    "wof:name":"Genamation Repair Ctr",
    "wof:placetype":"venue"
},
  "geometry": {"coordinates":[-78.916634,43.870323],"type":"Point"}
}