{
  "type": "Feature",
  "properties": {
    "addr:full":"600 131 Rte Joliette QC J6E 7Y8",
    "addr:housenumber":"131",
    "addr:postcode":"j6e 7y8",
    "addr:street":"Rte Joliette",
    "iso:country":"CA",
    "sg:address":"600 131 Rte",
    "sg:city":"Joliette",
    "sg:classifiers":[
        {
            "category":"Food & Beverages",
            "subcategory":"Groceries & Convenience Stores",
            "type":"Retail Goods"
        }
    ],
    "sg:phone":"+1 450 759 8282",
    "sg:postcode":"J6E 7Y8",
    "sg:province":"QC",
    "wof:name":"Depanneur Provisions",
    "wof:placetype":"venue"
},
  "geometry": {"coordinates":[-73.4419555664,46.0235710144],"type":"Point"}
}