{
  "type": "Feature",
  "properties": {
    "addr:full":"4865 Rue Dagenais Montreal QC H4C 1L8",
    "addr:housenumber":"4865",
    "addr:postcode":"h4c 1l8",
    "addr:street":"Rue Dagenais",
    "iso:country":"CA",
    "sg:address":"4865 Rue Dagenais",
    "sg:city":"Montreal",
    "sg:classifiers":[
        {
            "category":"Professional",
            "subcategory":"Business Services",
            "type":"Services"
        }
    ],
    "sg:phone":"+1 514 332 0728",
    "sg:postcode":"H4C 1L8",
    "sg:province":"QC",
    "sg:tags":[
        "auctioneer"
    ],
    "wof:name":"Alex Davis & Assoc",
    "wof:placetype":"venue"
},
  "geometry": {"coordinates":[-73.59137,45.471558],"type":"Point"}
}