{
  "type": "Feature",
  "properties": {
    "addr:full":"217 Courtwright St Fort Erie ON L2A 2R9",
    "addr:housenumber":"217",
    "addr:postcode":"l2a 2r9",
    "addr:street":"Courtwright St",
    "iso:country":"CA",
    "sg:address":"217 Courtwright St",
    "sg:city":"Fort Erie",
    "sg:classifiers":[
        {
            "category":"Retail",
            "subcategory":"Repair Shop",
            "type":"Services"
        }
    ],
    "sg:phone":"+1 905 871 8293",
    "sg:postcode":"L2A 2R9",
    "sg:province":"ON",
    "sg:tags":[
        "refinishing",
        "furniture"
    ],
    "wof:name":"P J's",
    "wof:placetype":"venue"
},
  "geometry": {"coordinates":[-78.92094400000001,42.928616],"type":"Point"}
}