{
  "type": "Feature",
  "properties": {
    "iso:country":"CA",
    "sg:city":"Brampton",
    "sg:classifiers":[
        {
            "category":"Food & Beverages",
            "subcategory":"Meat & Fish",
            "type":"Retail Goods"
        }
    ],
    "sg:phone":"+1 905 454 3224",
    "sg:postcode":"L6X 2R6",
    "sg:province":"ON",
    "sg:tags":[
        "frozen",
        "freezer",
        "for"
    ],
    "wof:name":"M & M Meat Shops",
    "wof:placetype":"venue"
},
  "geometry": {"coordinates":[-79.7661437988,43.6818122864],"type":"Point"}
}