{
  "type": "Feature",
  "properties": {
    "addr:full":"Killam AB T0B 2L0",
    "addr:postcode":"t0b 2l0",
    "iso:country":"CA",
    "sg:city":"Killam",
    "sg:classifiers":[
        {
            "category":"Home & Garden",
            "subcategory":"Building Materials",
            "type":"Retail Goods"
        }
    ],
    "sg:phone":"+1 780 385 3821",
    "sg:postcode":"T0B 2L0",
    "sg:province":"AB",
    "sg:tags":[
        "mixed",
        "concrete"
    ],
    "wof:name":"Killam Transit Mix Ltd",
    "wof:placetype":"venue"
},
  "geometry": {"coordinates":[-111.84951,52.79184],"type":"Point"}
}