{
  "type": "Feature",
  "properties": {
    "addr:full":"Vanier QC G1M 1B4",
    "addr:postcode":"g1m 1b4",
    "iso:country":"CA",
    "sg:city":"Vanier",
    "sg:classifiers":[
        {
            "category":"Building & Trades",
            "subcategory":"Construction",
            "type":"Services"
        }
    ],
    "sg:phone":"+1 418 682 8338",
    "sg:postcode":"G1M 1B4",
    "sg:province":"QC",
    "sg:tags":[
        "general",
        "contractor"
    ],
    "wof:name":"Pepin Laureat Inc",
    "wof:placetype":"venue"
},
  "geometry": {"coordinates":[-71.2746810913,46.8214073181],"type":"Point"}
}