{
  "type": "Feature",
  "properties": {
    "iso:country":"CA",
    "sg:address":"50 Boul Graham",
    "sg:city":"Mont-Royal",
    "sg:classifiers":[
        {
            "category":"Organizations",
            "subcategory":"Religious Organization",
            "type":"Services"
        }
    ],
    "sg:phone":"+1 514 731 5732",
    "sg:postcode":"H3P 2C1",
    "sg:province":"QC",
    "sg:tags":[
        "church"
    ],
    "wof:name":"Hungarian United Church",
    "wof:placetype":"venue"
},
  "geometry": {"coordinates":[-73.626183,45.523335],"type":"Point"}
}