{
  "type": "Feature",
  "properties": {
    "addr:full":"49 309 Rte S Ferme-Neuve QC J0W 1C0",
    "addr:housenumber":"309",
    "addr:postcode":"j0w 1c0",
    "addr:street":"49;Rte S",
    "iso:country":"CA",
    "sg:address":"49 309 Rte S",
    "sg:city":"Ferme-Neuve",
    "sg:classifiers":[
        {
            "category":"Real Estate",
            "subcategory":"Real Estate Agent",
            "type":"Services"
        }
    ],
    "sg:phone":"+1 819 587 3332",
    "sg:postcode":"J0W 1C0",
    "sg:province":"QC",
    "sg:tags":[
        "agency",
        "rental"
    ],
    "wof:name":"Scies A Chaine Fn Ltee",
    "wof:placetype":"venue"
},
  "geometry": {"coordinates":[-75.456062,46.700245],"type":"Point"}
}