{
  "type": "Feature",
  "properties": {
    "addr:full":"Ripon QC J0V 1V0",
    "addr:postcode":"j0v 1v0",
    "iso:country":"CA",
    "sg:city":"Ripon",
    "sg:classifiers":[
        {
            "category":"Shopping",
            "subcategory":"Pharmacy",
            "type":"Retail Goods"
        }
    ],
    "sg:phone":"+1 819 983 4347",
    "sg:postcode":"J0V 1V0",
    "sg:province":"QC",
    "wof:name":"Pharmacie Yvon Gravel",
    "wof:placetype":"venue"
},
  "geometry": {"coordinates":[-75.0990066528,45.782951355],"type":"Point"}
}