{
  "type": "Feature",
  "properties": {
    "addr:full":"4053 Ogden Rd SE Calgary AB T2G 4P2",
    "addr:housenumber":"4053",
    "addr:postcode":"t2g 4p2",
    "addr:street":"Ogden Rd Se",
    "iso:country":"CA",
    "sg:address":"4053 Ogden Rd SE",
    "sg:city":"Calgary",
    "sg:classifiers":[
        {
            "category":"Building & Trades",
            "subcategory":"Electrical",
            "type":"Services"
        }
    ],
    "sg:phone":"+1 403 234 0086",
    "sg:postcode":"T2G 4P2",
    "sg:province":"AB",
    "sg:tags":[
        "electric",
        "contractor"
    ],
    "wof:name":"Seletech Electrical Ents Ltd",
    "wof:placetype":"venue"
},
  "geometry": {"coordinates":[-114.026955,51.018452],"type":"Point"}
}