{
  "type": "Feature",
  "properties": {
    "addr:full":"5023 52nd Ave Whitecourt AB T7S 1N8",
    "addr:housenumber":"5023",
    "addr:postcode":"t7s 1n8",
    "addr:street":"52Nd Ave",
    "iso:country":"CA",
    "sg:address":"5023 52nd Ave",
    "sg:city":"Whitecourt",
    "sg:classifiers":[
        {
            "category":"Shopping",
            "subcategory":"Department Store",
            "type":"Retail Goods"
        }
    ],
    "sg:phone":"+1 780 778 4228",
    "sg:postcode":"T7S 1N8",
    "sg:province":"AB",
    "wof:name":"Fields Stores",
    "wof:placetype":"venue"
},
  "geometry": {"coordinates":[-115.685348511,54.1422271729],"type":"Point"}
}