{
  "type": "Feature",
  "properties": {
    "addr:full":"330 Rue Bruce Cowansville QC J2K 3A9",
    "addr:housenumber":"330",
    "addr:postcode":"j2k 3a9",
    "addr:street":"Rue Bruce",
    "iso:country":"CA",
    "sg:address":"330 Rue Bruce",
    "sg:city":"Cowansville",
    "sg:classifiers":[
        {
            "category":"Organizations",
            "subcategory":"Religious Organization",
            "type":"Services"
        }
    ],
    "sg:phone":"+1 514 263 0741",
    "sg:postcode":"J2K 3A9",
    "sg:province":"QC",
    "sg:tags":[
        "church"
    ],
    "wof:name":"Christ's Church",
    "wof:placetype":"venue"
},
  "geometry": {"coordinates":[-72.7557296753,45.211681366],"type":"Point"}
}