{
  "type": "Feature",
  "properties": {
    "addr:full":"Scarborough ON M1B 5N1",
    "addr:postcode":"m1b 5n1",
    "iso:country":"CA",
    "sg:city":"Scarborough",
    "sg:classifiers":[
        {
            "category":"Retail",
            "subcategory":"Laundry & Dry Cleaning",
            "type":"Services"
        }
    ],
    "sg:phone":"+1 416 292 3558",
    "sg:postcode":"M1B 5N1",
    "sg:province":"ON",
    "sg:tags":[
        "cleaners"
    ],
    "wof:name":"City Cleaners",
    "wof:placetype":"venue"
},
  "geometry": {"coordinates":[-79.233597,43.790157],"type":"Point"}
}