{
  "type": "Feature",
  "properties": {
    "addr:full":"3506 Av Du Parc Montreal QC H2X 2H7",
    "addr:housenumber":"3506",
    "addr:postcode":"h2x 2h7",
    "addr:street":"Av Du Parc",
    "iso:country":"CA",
    "sg:address":"3506 Av Du Parc",
    "sg:city":"Montreal",
    "sg:classifiers":[
        {
            "category":"Professional",
            "subcategory":"Printing & Photocopies",
            "type":"Services"
        }
    ],
    "sg:phone":"+1 514 845 4515",
    "sg:postcode":"H2X 2H7",
    "sg:province":"QC",
    "sg:tags":[
        "duplicating",
        "copying"
    ],
    "wof:name":"Copie Smart",
    "wof:placetype":"venue"
},
  "geometry": {"coordinates":[-73.5741271973,45.5095367432],"type":"Point"}
}