{
  "type": "Feature",
  "properties": {
    "iso:country":"CA",
    "sg:address":"62 Hooper Rd",
    "sg:city":"Barrie",
    "sg:classifiers":[
        {
            "category":"Retail",
            "subcategory":"Veterinary Services",
            "type":"Services"
        }
    ],
    "sg:phone":"+1 705 722 4866",
    "sg:postcode":"L4N 8Z9",
    "sg:province":"ON",
    "sg:tags":[
        "veterinarian"
    ],
    "wof:name":"Essa Veterinary Svc",
    "wof:placetype":"venue"
},
  "geometry": {"coordinates":[-79.672653,44.336018],"type":"Point"}
}