{
  "type": "Feature",
  "properties": {
    "addr:full":"50th St & 48th Ave Sedgewick AB T0B 4C0",
    "addr:postcode":"t0b 4c0",
    "addr:street":"50Th St & 48Th Ave",
    "iso:country":"CA",
    "sg:address":"50th St & 48th Ave",
    "sg:city":"Sedgewick",
    "sg:classifiers":[
        {
            "category":"Autos & Motor Vehicles",
            "subcategory":"Auto Supplies",
            "type":"Retail Goods"
        }
    ],
    "sg:phone":"+1 780 384 3553",
    "sg:postcode":"T0B 4C0",
    "sg:province":"AB",
    "sg:tags":[
        "automobile",
        "parts"
    ],
    "wof:name":"Bumper To Bumper",
    "wof:placetype":"venue"
},
  "geometry": {"coordinates":[-111.697006,52.773941],"type":"Point"}
}