{
  "type": "Feature",
  "properties": {
    "addr:full":"984 Rang Sud Saint-Pierre-Montmagny QC G0R 4B0",
    "addr:housenumber":"984",
    "addr:postcode":"g0r 4b0",
    "addr:street":"Rang Sud",
    "iso:country":"CA",
    "sg:address":"984 Rang Sud",
    "sg:city":"Saint-Pierre-Montmagny",
    "sg:classifiers":[
        {
            "category":"Building & Trades",
            "subcategory":"Construction",
            "type":"Services"
        }
    ],
    "sg:phone":"+1 418 248 1265",
    "sg:postcode":"G0R 4B0",
    "sg:province":"QC",
    "sg:tags":[
        "water",
        "well",
        "drilling"
    ],
    "wof:name":"R Beaumont & Fils Inc",
    "wof:placetype":"venue"
},
  "geometry": {"coordinates":[-70.55378723139999,46.9849662781],"type":"Point"}
}