{
  "type": "Feature",
  "properties": {
    "addr:full":"Dartmouth NS B2Y 2T8",
    "addr:postcode":"b2y 2t8",
    "iso:country":"CA",
    "sg:city":"Dartmouth",
    "sg:classifiers":[
        {
            "category":"Manufacturing",
            "subcategory":"Printing",
            "type":"Manufacturing & Wholesale Goods"
        }
    ],
    "sg:phone":"+1 902 463 5055",
    "sg:postcode":"B2Y 2T8",
    "sg:province":"NS",
    "sg:tags":[
        "printer"
    ],
    "wof:name":"John Hilton Printing Svc",
    "wof:placetype":"venue"
},
  "geometry": {"coordinates":[-63.564636,44.666668],"type":"Point"}
}