{
  "type": "Feature",
  "properties": {
    "iso:country":"CA",
    "sg:address":"675 Belmont Ave W",
    "sg:city":"Kitchener",
    "sg:classifiers":[
        {
            "category":"Personal",
            "subcategory":"Beauty Salon",
            "type":"Services"
        }
    ],
    "sg:phone":"+1 519 578 8530",
    "sg:postcode":"N2M 1N8",
    "sg:province":"ON",
    "wof:name":"Mr Lee's Hair Fashions",
    "wof:placetype":"venue"
},
  "geometry": {"coordinates":[-80.517853,43.452976],"type":"Point"}
}