{
  "type": "Feature",
  "properties": {
    "iso:country":"CA",
    "sg:address":"130 Watford St",
    "sg:city":"Whitby",
    "sg:classifiers":[
        {
            "category":"Organizations",
            "subcategory":"Religious Organization",
            "type":"Services"
        }
    ],
    "sg:phone":"+1 905 655 3286",
    "sg:postcode":"L1M 1H2",
    "sg:province":"ON",
    "sg:tags":[
        "church"
    ],
    "wof:name":"St Leo's Catholic Church",
    "wof:placetype":"venue"
},
  "geometry": {"coordinates":[-78.9500961304,43.9647407532],"type":"Point"}
}