{
  "type": "Feature",
  "properties": {
    "addr:full":"3500 Boul Matte Brossard QC J4Y 2Z2",
    "addr:housenumber":"3500",
    "addr:postcode":"j4y 2z2",
    "addr:street":"Boul Matte",
    "iso:country":"CA",
    "sg:address":"3500 Boul Matte",
    "sg:city":"Brossard",
    "sg:classifiers":[
        {
            "category":"Home & Garden",
            "subcategory":"Building Materials",
            "type":"Retail Goods"
        }
    ],
    "sg:phone":"+1 450 444 0707",
    "sg:postcode":"J4Y 2Z2",
    "sg:province":"QC",
    "sg:tags":[
        "paint"
    ],
    "wof:name":"Sherwin-Williams CO",
    "wof:placetype":"venue"
},
  "geometry": {"coordinates":[-73.4668426514,45.4314498901],"type":"Point"}
}