{
  "type": "Feature",
  "properties": {
    "iso:country":"CA",
    "sg:address":"2144 Jetstream Rd",
    "sg:city":"London",
    "sg:classifiers":[
        {
            "category":"Manufacturing",
            "subcategory":"Metals",
            "type":"Manufacturing & Wholesale Goods"
        }
    ],
    "sg:phone":"+1 519 453 7240",
    "sg:postcode":"N5V 3P5",
    "sg:province":"ON",
    "sg:tags":[
        "treating",
        "heat"
    ],
    "wof:name":"Bayson Heat Treating Inc",
    "wof:placetype":"venue"
},
  "geometry": {"coordinates":[-81.16384887700001,43.0250244141],"type":"Point"}
}