{
  "type": "Feature",
  "properties": {
    "addr:full":"304 Victoria Ave N # 188 Hamilton ON L8L 5G4",
    "addr:housenumber":"304;188",
    "addr:postcode":"l8l 5g4",
    "addr:street":"Victoria Ave N #",
    "iso:country":"CA",
    "sg:address":"304 Victoria Ave N # 188",
    "sg:city":"Hamilton",
    "sg:classifiers":[
        {
            "category":"Social Services",
            "subcategory":"Job Training",
            "type":"Services"
        }
    ],
    "sg:phone":"+1 905 547 3926",
    "sg:postcode":"L8L 5G4",
    "sg:province":"ON",
    "sg:tags":[
        "rehabilitation"
    ],
    "wof:name":"Belmont Rehabilitation Ctr",
    "wof:placetype":"venue"
},
  "geometry": {"coordinates":[-79.8527374268,43.2619132996],"type":"Point"}
}