{
  "type": "Feature",
  "properties": {
    "iso:country":"CA",
    "sg:address":"758 Kingsway Garden Mall NW",
    "sg:city":"Edmonton",
    "sg:classifiers":[
        {
            "category":"Utilities",
            "subcategory":"Mobile Phone",
            "type":"Services"
        }
    ],
    "sg:phone":"+1 780 471 3807",
    "sg:postcode":"T5G 3E6",
    "sg:province":"AB",
    "sg:tags":[
        "telephone",
        "cellular"
    ],
    "wof:name":"Rogers At & T Store",
    "wof:placetype":"venue"
},
  "geometry": {"coordinates":[-113.490372,53.546219],"type":"Point"}
}