{
  "type": "Feature",
  "properties": {
    "addr:full":"235 Main St Doaktown NB E9C 1A9",
    "addr:housenumber":"235",
    "addr:postcode":"e9c 1a9",
    "addr:street":"Main St",
    "iso:country":"CA",
    "sg:address":"235 Main St",
    "sg:city":"Doaktown",
    "sg:classifiers":[
        {
            "category":"Restaurant",
            "type":"Food & Drink"
        }
    ],
    "sg:phone":"+1 506 365 4301",
    "sg:postcode":"E9C 1A9",
    "sg:province":"NB",
    "wof:name":"Village Family Restaurant",
    "wof:placetype":"venue"
},
  "geometry": {"coordinates":[-66.1276092529,46.5560951233],"type":"Point"}
}