{
  "type": "Feature",
  "properties": {
    "addr:full":"210 Chowsunket St Fraser Lake BC V0J 1S0",
    "addr:housenumber":"210",
    "addr:postcode":"v0j 1s0",
    "addr:street":"Chowsunket St",
    "iso:country":"CA",
    "sg:address":"210 Chowsunket St",
    "sg:city":"Fraser Lake",
    "sg:classifiers":[
        {
            "category":"Travel",
            "subcategory":"Hotels & Motels",
            "type":"Entertainment"
        }
    ],
    "sg:phone":"+1 250 699 6254",
    "sg:postcode":"V0J 1S0",
    "sg:province":"BC",
    "wof:name":"Cataline Motor Inn",
    "wof:placetype":"venue"
},
  "geometry": {"coordinates":[-124.849495,54.059425],"type":"Point"}
}