{
  "type": "Feature",
  "properties": {
    "addr:full":"200 Av Saint-Laurent Louiseville QC J5V 1J9",
    "addr:housenumber":"200",
    "addr:postcode":"j5v 1j9",
    "addr:street":"Av Saint-Laurent",
    "iso:country":"CA",
    "sg:address":"200 Av Saint-Laurent",
    "sg:city":"Louiseville",
    "sg:classifiers":[
        {
            "category":"Professional",
            "subcategory":"Lawyer & Legal Services",
            "type":"Services"
        }
    ],
    "sg:phone":"+1 819 228 9128",
    "sg:postcode":"J5V 1J9",
    "sg:province":"QC",
    "sg:tags":[
        "attorney"
    ],
    "wof:name":"Rioux, Francois",
    "wof:placetype":"venue"
},
  "geometry": {"coordinates":[-72.94422149659999,46.2558898926],"type":"Point"}
}