{
  "type": "Feature",
  "properties": {
    "addr:full":"950 Ch Hemming Saint-Charles-DE-Drummond QC J2B 7T5",
    "addr:housenumber":"950",
    "addr:postcode":"j2b 7t5",
    "addr:street":"Ch Hemming",
    "iso:country":"CA",
    "sg:address":"950 Ch Hemming",
    "sg:city":"Saint-Charles-DE-Drummond",
    "sg:classifiers":[
        {
            "category":"Social Services",
            "type":"Services"
        }
    ],
    "sg:phone":"+1 819 478 1201",
    "sg:postcode":"J2B 7T5",
    "sg:province":"QC",
    "sg:tags":[
        "organization",
        "outing",
        "welfare",
        "facility"
    ],
    "wof:name":"Centre Normand Leveille Inc",
    "wof:placetype":"venue"
},
  "geometry": {"coordinates":[-72.458786,45.867237],"type":"Point"}
}