{
  "type": "Feature",
  "properties": {
    "addr:full":"4611 48 St Rocky Mountain House AB T4T 1C8",
    "addr:housenumber":"4611",
    "addr:postcode":"t4t 1c8",
    "addr:street":"48 St Rocky",
    "iso:country":"CA",
    "sg:address":"4611 48 St",
    "sg:city":"Rocky Mountain House",
    "sg:classifiers":[
        {
            "category":"Social Services",
            "subcategory":"Job Training",
            "type":"Services"
        }
    ],
    "sg:phone":"+1 403 845 2922",
    "sg:postcode":"T4T 1C8",
    "sg:province":"AB",
    "sg:tags":[
        "rehabilitation"
    ],
    "wof:name":"Westward Goals Support Svc",
    "wof:placetype":"venue"
},
  "geometry": {"coordinates":[-114.916122,52.369843],"type":"Point"}
}