{
  "type": "Feature",
  "properties": {
    "iso:country":"CA",
    "sg:address":"1000 Rue Notre-Dame",
    "sg:city":"Saint-Sulpice",
    "sg:classifiers":[
        {
            "category":"Autos & Motor Vehicles",
            "subcategory":"Fuel & Gas Station",
            "type":"Retail Goods"
        }
    ],
    "sg:phone":"+1 450 589 4515",
    "sg:postcode":"J5W 3W3",
    "sg:province":"QC",
    "sg:tags":[
        "oil"
    ],
    "wof:name":"Station Service Leopold Roy",
    "wof:placetype":"venue"
},
  "geometry": {"coordinates":[-73.359055,45.825222],"type":"Point"}
}