{
  "type": "Feature",
  "properties": {
    "addr:full":"5051 Matchette Rd Windsor ON N9C 2A8",
    "addr:housenumber":"5051",
    "addr:postcode":"n9c 2a8",
    "addr:street":"Matchette Rd",
    "iso:country":"CA",
    "sg:address":"5051 Matchette Rd",
    "sg:city":"Windsor",
    "sg:classifiers":[
        {
            "category":"Manufacturing",
            "subcategory":"Furniture",
            "type":"Manufacturing & Wholesale Goods"
        }
    ],
    "sg:phone":"+1 519 250 6087",
    "sg:postcode":"N9C 2A8",
    "sg:province":"ON",
    "sg:tags":[
        "closet",
        "accessory"
    ],
    "wof:name":"Create A Space",
    "wof:placetype":"venue"
},
  "geometry": {"coordinates":[-83.07354736329999,42.2668647766],"type":"Point"}
}