{
  "type": "Feature",
  "properties": {
    "addr:full":"Houston BC V0J 1Z0",
    "addr:postcode":"v0j 1z0",
    "iso:country":"CA",
    "sg:city":"Houston",
    "sg:classifiers":[
        {
            "category":"Manufacturing",
            "subcategory":"Lumber",
            "type":"Manufacturing & Wholesale Goods"
        }
    ],
    "sg:phone":"+1 250 845 2361",
    "sg:postcode":"V0J 1Z0",
    "sg:province":"BC",
    "sg:tags":[
        "company",
        "logging"
    ],
    "wof:name":"Hladun Logging Ltd",
    "wof:placetype":"venue"
},
  "geometry": {"coordinates":[-126.647041,54.400635],"type":"Point"}
}