{
  "type": "Feature",
  "properties": {
    "addr:full":"3000 Rue Masson Montreal QC H1Y 1X6",
    "addr:housenumber":"3000",
    "addr:postcode":"h1y 1x6",
    "addr:street":"Rue Masson",
    "iso:country":"CA",
    "sg:address":"3000 Rue Masson",
    "sg:city":"Montreal",
    "sg:classifiers":[
        {
            "category":"Food & Beverages",
            "subcategory":"Groceries & Convenience Stores",
            "type":"Retail Goods"
        }
    ],
    "sg:phone":"+1 514 374 2158",
    "sg:postcode":"H1Y 1X6",
    "sg:province":"QC",
    "wof:name":"Couche-Tard",
    "wof:placetype":"venue"
},
  "geometry": {"coordinates":[-73.574417,45.548729],"type":"Point"}
}