{
  "type": "Feature",
  "properties": {
    "addr:full":"Hwy 5 E Saskatoon SK S7K 3J9",
    "addr:postcode":"s7k 3j9",
    "addr:street":"Hwy 5 E",
    "iso:country":"CA",
    "sg:address":"Hwy 5 E",
    "sg:city":"Saskatoon",
    "sg:classifiers":[
        {
            "category":"Manufacturing",
            "subcategory":"Chemicals & Compounds",
            "type":"Manufacturing & Wholesale Goods"
        }
    ],
    "sg:phone":"+1 306 653 7258",
    "sg:postcode":"S7K 3J9",
    "sg:province":"SK",
    "sg:tags":[
        "salt"
    ],
    "wof:name":"Ceres Industries",
    "wof:placetype":"venue"
},
  "geometry": {"coordinates":[-106.658340454,52.1329231262],"type":"Point"}
}