{
  "type": "Feature",
  "properties": {
    "addr:full":"50 Hopeton St Cambridge ON N1R 3T3",
    "addr:housenumber":"50",
    "addr:postcode":"n1r 3t3",
    "addr:street":"Hopeton St",
    "iso:country":"CA",
    "sg:address":"50 Hopeton St",
    "sg:city":"Cambridge",
    "sg:classifiers":[
        {
            "category":"Bars & Pubs",
            "type":"Food & Drink"
        }
    ],
    "sg:phone":"+1 519 622 2400",
    "sg:postcode":"N1R 3T3",
    "sg:province":"ON",
    "sg:tags":[
        "parlor",
        "billiard"
    ],
    "wof:name":"J D's Billiards",
    "wof:placetype":"venue"
},
  "geometry": {"coordinates":[-80.314491,43.369732],"type":"Point"}
}