{
  "type": "Feature",
  "properties": {
    "iso:country":"CA",
    "sg:address":"2017 Fisher Rd",
    "sg:city":"Kelowna",
    "sg:classifiers":[
        {
            "category":"Building & Trades",
            "subcategory":"Construction",
            "type":"Services"
        }
    ],
    "sg:phone":"+1 250 861 4822",
    "sg:postcode":"V1W 2H1",
    "sg:province":"BC",
    "sg:tags":[
        "paving",
        "contractor"
    ],
    "wof:name":"Security Paving CO Ltd",
    "wof:placetype":"venue"
},
  "geometry": {"coordinates":[-119.450409,49.862789],"type":"Point"}
}