{
  "type": "Feature",
  "properties": {
    "addr:full":"2017 Fisher Rd Kelowna BC V1W 2H1",
    "addr:housenumber":"2017",
    "addr:postcode":"v1w 2h1",
    "addr:street":"Fisher Rd",
    "iso:country":"CA",
    "sg:address":"2017 Fisher Rd",
    "sg:city":"Kelowna",
    "sg:classifiers":[
        {
            "category":"Building & Trades",
            "subcategory":"Construction",
            "type":"Services"
        }
    ],
    "sg:phone":"+1 250 861 4822",
    "sg:postcode":"V1W 2H1",
    "sg:province":"BC",
    "sg:tags":[
        "paving",
        "contractor"
    ],
    "wof:name":"Security Paving CO Ltd",
    "wof:placetype":"venue"
},
  "geometry": {"coordinates":[-119.45040899999999,49.862789],"type":"Point"}
}