{
  "type": "Feature",
  "properties": {
    "addr:full":"Vanier ON K1L 6C7",
    "addr:postcode":"k1l 6c7",
    "iso:country":"CA",
    "sg:city":"Vanier",
    "sg:classifiers":[
        {
            "category":"Professional",
            "subcategory":"Computer Services",
            "type":"Services"
        }
    ],
    "sg:phone":"+1 613 749 2935",
    "sg:postcode":"K1L 6C7",
    "sg:province":"ON",
    "sg:tags":[
        "consultant"
    ],
    "wof:name":"Bhi Computer Technologies",
    "wof:placetype":"venue"
},
  "geometry": {"coordinates":[-75.66226959230001,45.4359931946],"type":"Point"}
}