{
  "type": "Feature",
  "properties": {
    "addr:full":"103 Gore St W Thunder Bay ON P7E 3R3",
    "addr:housenumber":"103",
    "addr:postcode":"p7e 3r3",
    "addr:street":"Gore St W",
    "iso:country":"CA",
    "sg:address":"103 Gore St W",
    "sg:city":"Thunder Bay",
    "sg:classifiers":[
        {
            "category":"Retail",
            "subcategory":"Auto Repair",
            "type":"Services"
        }
    ],
    "sg:phone":"+1 807 577 6171",
    "sg:postcode":"P7E 3R3",
    "sg:province":"ON",
    "sg:tags":[
        "repairing",
        "automobile"
    ],
    "wof:name":"Pro Alignment & Repairs Ltd",
    "wof:placetype":"venue"
},
  "geometry": {"coordinates":[-89.2788696289,48.3641624451],"type":"Point"}
}