{
  "type": "Feature",
  "properties": {
    "addr:full":"11148 84 Ave NW Edmonton AB T6G 0V8",
    "addr:housenumber":"11148",
    "addr:postcode":"t6g 0v8",
    "addr:street":"84 Ave Nw",
    "iso:country":"CA",
    "sg:address":"11148 84 Ave NW",
    "sg:city":"Edmonton",
    "sg:classifiers":[
        {
            "category":"Organizations",
            "subcategory":"Religious Organization",
            "type":"Services"
        }
    ],
    "sg:phone":"+1 780 413 6159",
    "sg:postcode":"T6G 0V8",
    "sg:province":"AB",
    "sg:tags":[
        "church"
    ],
    "wof:name":"Edmonton Interfaith Ctr",
    "wof:placetype":"venue"
},
  "geometry": {"coordinates":[-113.519302368,53.520275116],"type":"Point"}
}