{
  "type": "Feature",
  "properties": {
    "iso:country":"CA",
    "sg:address":"1610 John Street Rd",
    "sg:city":"Thunder Bay",
    "sg:classifiers":[
        {
            "category":"Social Services",
            "subcategory":"Child Care",
            "type":"Services"
        }
    ],
    "sg:phone":"+1 807 768 2342",
    "sg:postcode":"P7G 1J9",
    "sg:province":"ON",
    "sg:tags":[
        "kindergarten",
        "academic",
        "school"
    ],
    "wof:name":"Thunder Bay Aboriginal Head",
    "wof:placetype":"venue"
},
  "geometry": {"coordinates":[-89.2921447754,48.4448204041],"type":"Point"}
}