{
  "type": "Feature",
  "properties": {
    "addr:full":"463 Bunting Dr North Bay ON P1A 4L4",
    "addr:housenumber":"463",
    "addr:postcode":"p1a 4l4",
    "addr:street":"Bunting Dr",
    "iso:country":"CA",
    "sg:address":"463 Bunting Dr",
    "sg:city":"North Bay",
    "sg:classifiers":[
        {
            "category":"Building & Trades",
            "subcategory":"Electrical",
            "type":"Services"
        }
    ],
    "sg:phone":"+1 705 474 0338",
    "sg:postcode":"P1A 4L4",
    "sg:province":"ON",
    "sg:tags":[
        "electric",
        "contractor"
    ],
    "wof:name":"Peter Lazarou Electrical",
    "wof:placetype":"venue"
},
  "geometry": {"coordinates":[-79.4280166626,46.2726516724],"type":"Point"}
}