{
  "type": "Feature",
  "properties": {
    "addr:full":"500 Main St Gravelbourg SK S0H 1X0",
    "addr:housenumber":"500",
    "addr:postcode":"s0h 1x0",
    "addr:street":"Main St",
    "iso:country":"CA",
    "sg:address":"500 Main St",
    "sg:city":"Gravelbourg",
    "sg:classifiers":[
        {
            "category":"Manufacturing",
            "subcategory":"Printing",
            "type":"Manufacturing & Wholesale Goods"
        }
    ],
    "sg:phone":"+1 306 648 3150",
    "sg:postcode":"S0H 1X0",
    "sg:province":"SK",
    "sg:tags":[
        "newspaper"
    ],
    "wof:name":"Wood River Free Press",
    "wof:placetype":"venue"
},
  "geometry": {"coordinates":[-106.557258606,49.8766403198],"type":"Point"}
}