{
  "type": "Feature",
  "properties": {
    "addr:full":"14305 128 Ave NW Edmonton AB T5L 3H3",
    "addr:housenumber":"14305",
    "addr:postcode":"t5l 3h3",
    "addr:street":"128 Ave Nw",
    "iso:country":"CA",
    "sg:address":"14305 128 Ave NW",
    "sg:city":"Edmonton",
    "sg:classifiers":[
        {
            "category":"Wholesale",
            "subcategory":"Construction Materials",
            "type":"Manufacturing & Wholesale Goods"
        }
    ],
    "sg:phone":"+1 780 451 1212",
    "sg:postcode":"T5L 3H3",
    "sg:province":"AB",
    "sg:tags":[
        "equipment",
        "concrete",
        "product",
        "supply"
    ],
    "wof:name":"National Concrete Accessories",
    "wof:placetype":"venue"
},
  "geometry": {"coordinates":[-113.56653595,53.5848197937],"type":"Point"}
}