{
  "type": "Feature",
  "properties": {
    "addr:full":"Hope BC V0X 1L4",
    "addr:postcode":"v0x 1l4",
    "iso:country":"CA",
    "sg:city":"Hope",
    "sg:classifiers":[
        {
            "category":"Health Services",
            "subcategory":"Nursing And Care Facility",
            "type":"Services"
        }
    ],
    "sg:phone":"+1 604 860 4700",
    "sg:postcode":"V0X 1L4",
    "sg:province":"BC",
    "sg:tags":[
        "home",
        "retirement",
        "convalescent",
        "community"
    ],
    "wof:name":"Riverside Manor",
    "wof:placetype":"venue"
},
  "geometry": {"coordinates":[-121.423957825,49.375328064],"type":"Point"}
}