{
  "type": "Feature",
  "properties": {
    "iso:country":"CA",
    "sg:address":"1430 George St",
    "sg:city":"Sydney",
    "sg:classifiers":[
        {
            "category":"Retail",
            "subcategory":"Auto Repair",
            "type":"Services"
        }
    ],
    "sg:phone":"+1 902 539 1791",
    "sg:postcode":"B1P 1P1",
    "sg:province":"NS",
    "sg:tags":[
        "repairing",
        "automobile"
    ],
    "wof:name":"Mira Road Svc Ctr Ltd",
    "wof:placetype":"venue"
},
  "geometry": {"coordinates":[-60.171546936,46.1179847717],"type":"Point"}
}