{
  "type": "Feature",
  "properties": {
    "addr:full":"Saint-Dominique QC J0H 1L0",
    "addr:postcode":"j0h 1l0",
    "iso:country":"CA",
    "sg:city":"Saint-Dominique",
    "sg:classifiers":[
        {
            "category":"Education",
            "subcategory":"Library",
            "type":"Public Place"
        }
    ],
    "sg:phone":"+1 450 771 0256",
    "sg:postcode":"J0H 1L0",
    "sg:province":"QC",
    "sg:tags":[
        "government"
    ],
    "wof:name":"St-Dominique Bibliotheque Mun",
    "wof:placetype":"venue"
},
  "geometry": {"coordinates":[-72.85092899999999,45.566055],"type":"Point"}
}