{
  "type": "Feature",
  "properties": {
    "addr:full":"60 Renfrew Dr # 248 Markham ON L3R 0E1",
    "addr:housenumber":"60",
    "addr:postcode":"l3r 0e1",
    "addr:street":"Renfrew Dr # 248",
    "iso:country":"CA",
    "sg:address":"60 Renfrew Dr # 248",
    "sg:city":"Markham",
    "sg:classifiers":[
        {
            "category":"Professional",
            "subcategory":"Accounting & Tax Preparation",
            "type":"Services"
        }
    ],
    "sg:phone":"+1 905 415 2228",
    "sg:postcode":"L3R 0E1",
    "sg:province":"ON",
    "sg:tags":[
        "accountant"
    ],
    "wof:name":"Chu, George CA",
    "wof:placetype":"venue"
},
  "geometry": {"coordinates":[-79.362236,43.857845],"type":"Point"}
}