{
  "type": "Feature",
  "properties": {
    "addr:full":"53 Power Rd Edmundston NB E3V 2X7",
    "addr:housenumber":"53",
    "addr:postcode":"e3v 2x7",
    "addr:street":"Power Rd",
    "iso:country":"CA",
    "sg:address":"53 Power Rd",
    "sg:city":"Edmundston",
    "sg:classifiers":[
        {
            "category":"Food & Beverages",
            "subcategory":"Groceries & Convenience Stores",
            "type":"Retail Goods"
        }
    ],
    "sg:phone":"+1 506 735 4403",
    "sg:postcode":"E3V 2X7",
    "sg:province":"NB",
    "sg:tags":[
        "grocer"
    ],
    "wof:name":"Depanneur Jack & Jill",
    "wof:placetype":"venue"
},
  "geometry": {"coordinates":[-68.325104,47.373714],"type":"Point"}
}