{
  "type": "Feature",
  "properties": {
    "iso:country":"CA",
    "sg:address":"362 Richmond Rd",
    "sg:city":"Ottawa",
    "sg:classifiers":[
        {
            "category":"Restaurant",
            "type":"Food & Drink"
        }
    ],
    "sg:phone":"+1 613 729 4401",
    "sg:postcode":"K2A 0E8",
    "sg:province":"ON",
    "sg:tags":[
        "shop",
        "coffee"
    ],
    "wof:name":"Bridgehead Coffeehouses",
    "wof:placetype":"venue"
},
  "geometry": {"coordinates":[-75.75495147709999,45.3914299011],"type":"Point"}
}