{
  "type": "Feature",
  "properties": {
    "addr:full":"Winnipeg MB R3K 0Y1",
    "addr:postcode":"r3k 0y1",
    "iso:country":"CA",
    "sg:city":"Winnipeg",
    "sg:classifiers":[
        {
            "category":"Health Services",
            "subcategory":"Doctor",
            "type":"Services"
        }
    ],
    "sg:phone":"+1 204 885 6442",
    "sg:postcode":"R3K 0Y1",
    "sg:province":"MB",
    "sg:tags":[
        "physician",
        "surgeon"
    ],
    "wof:name":"Bermack Weizman",
    "wof:placetype":"venue"
},
  "geometry": {"coordinates":[-97.281631,49.879784],"type":"Point"}
}