{
  "type": "Feature",
  "properties": {
    "addr:full":"119 Station St Belleville ON K8N 2S8",
    "addr:housenumber":"119",
    "addr:postcode":"k8n 2s8",
    "addr:street":"Station St",
    "iso:country":"CA",
    "sg:address":"119 Station St",
    "sg:city":"Belleville",
    "sg:classifiers":[
        {
            "category":"Organizations",
            "subcategory":"Professional Association",
            "type":"Services"
        }
    ],
    "sg:phone":"+1 613 962 6559",
    "sg:postcode":"K8N 2S8",
    "sg:province":"ON",
    "wof:name":"Belleville Lion's Club",
    "wof:placetype":"venue"
},
  "geometry": {"coordinates":[-77.3794174194,44.1739578247],"type":"Point"}
}