{
  "type": "Feature",
  "properties": {
    "addr:full":"929 Rue Principale Nord L'Annonciation QC J0T 1T0",
    "addr:housenumber":"929",
    "addr:postcode":"j0t 1t0",
    "addr:street":"Rue Principale Nord",
    "iso:country":"CA",
    "sg:address":"929 Rue Principale Nord",
    "sg:city":"L'Annonciation",
    "sg:classifiers":[
        {
            "category":"Social Services",
            "type":"Services"
        }
    ],
    "sg:phone":"+1 819 275 2060",
    "sg:postcode":"J0T 1T0",
    "sg:province":"QC",
    "sg:tags":[
        "organization",
        "welfare"
    ],
    "wof:name":"L'Arc En-Soi",
    "wof:placetype":"venue"
},
  "geometry": {"coordinates":[-74.869011,46.408436],"type":"Point"}
}