{
  "type": "Feature",
  "properties": {
    "addr:full":"22 Niagara St St Catharines ON L2R 4K7",
    "addr:housenumber":"22",
    "addr:postcode":"l2r 4k7",
    "addr:street":"Niagara St",
    "iso:country":"CA",
    "sg:address":"22 Niagara St",
    "sg:city":"St Catharines",
    "sg:classifiers":[
        {
            "category":"Personal",
            "subcategory":"Beauty Salon",
            "type":"Services"
        }
    ],
    "sg:phone":"+1 905 684 9431",
    "sg:postcode":"L2R 4K7",
    "sg:province":"ON",
    "wof:name":"Russell's Hairstyling",
    "wof:placetype":"venue"
},
  "geometry": {"coordinates":[-79.238899231,43.1631622314],"type":"Point"}
}