{
  "type": "Feature",
  "properties": {
    "addr:full":"4490 Farmers Dr Kelowna BC V1P 1A3",
    "addr:housenumber":"4490",
    "addr:postcode":"v1p 1a3",
    "addr:street":"Farmers Dr",
    "iso:country":"CA",
    "sg:address":"4490 Farmers Dr",
    "sg:city":"Kelowna",
    "sg:classifiers":[
        {
            "category":"Wholesale",
            "subcategory":"Machinery & Supplies",
            "type":"Manufacturing & Wholesale Goods"
        }
    ],
    "sg:phone":"+1 250 491 9644",
    "sg:postcode":"V1P 1A3",
    "sg:province":"BC",
    "sg:tags":[
        "compressor",
        "gas"
    ],
    "wof:name":"Atlas Copco Compressors",
    "wof:placetype":"venue"
},
  "geometry": {"coordinates":[-119.32390594500001,49.9503326416],"type":"Point"}
}