{
  "type": "Feature",
  "properties": {
    "addr:full":"11 Rang Saint-Edouard Amqui QC G5J 3N8",
    "addr:housenumber":"11",
    "addr:postcode":"g5j 3n8",
    "addr:street":"Rang Saint-Edouard",
    "iso:country":"CA",
    "sg:address":"11 Rang Saint-Edouard",
    "sg:city":"Amqui",
    "sg:classifiers":[
        {
            "category":"Manufacturing",
            "subcategory":"Lumber",
            "type":"Manufacturing & Wholesale Goods"
        }
    ],
    "sg:phone":"+1 418 629 5909",
    "sg:postcode":"G5J 3N8",
    "sg:province":"QC",
    "sg:tags":[
        "sawmill"
    ],
    "wof:name":"Felix Huard Inc Div Amqui",
    "wof:placetype":"venue"
},
  "geometry": {"coordinates":[-67.483147,48.498596],"type":"Point"}
}