{
  "type": "Feature",
  "properties": {
    "addr:full":"20 Robert St W Newcastle ON L1B 1C6",
    "addr:housenumber":"20",
    "addr:postcode":"l1b 1c6",
    "addr:street":"Robert St W",
    "iso:country":"CA",
    "sg:address":"20 Robert St W",
    "sg:city":"Newcastle",
    "sg:classifiers":[
        {
            "category":"Health Services",
            "subcategory":"Clinic",
            "type":"Services"
        }
    ],
    "sg:phone":"+1 905 987 3000",
    "sg:postcode":"L1B 1C6",
    "sg:province":"ON",
    "sg:tags":[
        "home"
    ],
    "wof:name":"Community Care Adult Day Prgrm",
    "wof:placetype":"venue"
},
  "geometry": {"coordinates":[-78.58729599999999,43.912258],"type":"Point"}
}