{
  "type": "Feature",
  "properties": {
    "addr:full":"397 Boul Grand L'Ile-Perrot QC J7V 4X3",
    "addr:housenumber":"397",
    "addr:postcode":"j7v 4x3",
    "addr:street":"Boul Grand L'Ile-Perrot",
    "iso:country":"CA",
    "sg:address":"397 Boul Grand",
    "sg:city":"L'Ile-Perrot",
    "sg:classifiers":[
        {
            "category":"Real Estate",
            "subcategory":"Real Estate Agent",
            "type":"Services"
        }
    ],
    "sg:phone":"+1 514 425 0101",
    "sg:postcode":"J7V 4X3",
    "sg:province":"QC",
    "wof:name":"Exit Immobilia Courtier Inc",
    "wof:placetype":"venue"
},
  "geometry": {"coordinates":[-73.9627,45.39016],"type":"Point"}
}