{
  "type": "Feature",
  "properties": {
    "addr:full":"9302 100 St Grande Prairie AB T8V 2K9",
    "addr:housenumber":"9302",
    "addr:postcode":"t8v 2k9",
    "addr:street":"100 St",
    "iso:country":"CA",
    "sg:address":"9302 100 St",
    "sg:city":"Grande Prairie",
    "sg:classifiers":[
        {
            "category":"Restaurant",
            "type":"Food & Drink"
        }
    ],
    "sg:phone":"+1 780 532 6969",
    "sg:postcode":"T8V 2K9",
    "sg:province":"AB",
    "wof:name":"Wally's Kitchen Ltd",
    "wof:placetype":"venue"
},
  "geometry": {"coordinates":[-118.79491400000001,55.164455],"type":"Point"}
}