{
  "type": "Feature",
  "properties": {
    "addr:full":"51 Av Sainte-Elizabeth Louiseville QC J5V 1L9",
    "addr:postcode":"j5v 1l9",
    "addr:street":"51 Av Sainte-Elizabeth",
    "iso:country":"CA",
    "sg:address":"51 Av Sainte-Elizabeth",
    "sg:city":"Louiseville",
    "sg:classifiers":[
        {
            "category":"Recreation",
            "type":"Entertainment"
        }
    ],
    "sg:phone":"+1 819 228 5517",
    "sg:postcode":"J5V 1L9",
    "sg:province":"QC",
    "sg:tags":[
        "parlor",
        "billiard"
    ],
    "wof:name":"Tapis Vert",
    "wof:placetype":"venue"
},
  "geometry": {"coordinates":[-72.94064299999999,46.254974],"type":"Point"}
}