{
  "type": "Feature",
  "properties": {
    "iso:country":"CA",
    "sg:city":"Calgary",
    "sg:classifiers":[
        {
            "category":"Manufacturing",
            "subcategory":"Tools & Machinery",
            "type":"Manufacturing & Wholesale Goods"
        }
    ],
    "sg:phone":"+1 403 253 6500",
    "sg:postcode":"T2H 1K4",
    "sg:province":"AB",
    "sg:tags":[
        "fire",
        "equipment",
        "protection"
    ],
    "wof:name":"Vipond Fire Protection Inc",
    "wof:placetype":"venue"
},
  "geometry": {"coordinates":[-114.056976318,50.9982872009],"type":"Point"}
}