{
  "type": "Feature",
  "properties": {
    "addr:full":"Assiniboia SK S0H 0B0",
    "addr:postcode":"s0h 0b0",
    "iso:country":"CA",
    "sg:city":"Assiniboia",
    "sg:classifiers":[
        {
            "category":"Organizations",
            "subcategory":"Religious Organization",
            "type":"Services"
        }
    ],
    "sg:phone":"+1 306 642 4747",
    "sg:postcode":"S0H 0B0",
    "sg:province":"SK",
    "sg:tags":[
        "church"
    ],
    "wof:name":"Kingdom Hall & Jehovah Witness",
    "wof:placetype":"venue"
},
  "geometry": {"coordinates":[-105.997643,49.631596],"type":"Point"}
}