{
  "type": "Feature",
  "properties": {
    "addr:full":"128 Rue Principale Saint-Adalbert QC G0R 2M0",
    "addr:housenumber":"128",
    "addr:postcode":"g0r 2m0",
    "addr:street":"Rue Principale",
    "iso:country":"CA",
    "sg:address":"128 Rue Principale",
    "sg:city":"Saint-Adalbert",
    "sg:classifiers":[
        {
            "category":"Food & Beverages",
            "subcategory":"Groceries & Convenience Stores",
            "type":"Retail Goods"
        }
    ],
    "sg:phone":"+1 418 356 3110",
    "sg:postcode":"G0R 2M0",
    "sg:province":"QC",
    "wof:name":"Accommodation Gm",
    "wof:placetype":"venue"
},
  "geometry": {"coordinates":[-69.9034729004,46.8599739075],"type":"Point"}
}