{
  "type": "Feature",
  "properties": {
    "addr:full":"2493 Finch Ave W North York ON M9M 2G1",
    "addr:housenumber":"2493",
    "addr:postcode":"m9m 2g1",
    "addr:street":"Finch Ave W",
    "iso:country":"CA",
    "sg:address":"2493 Finch Ave W",
    "sg:city":"North York",
    "sg:classifiers":[
        {
            "category":"Restaurant",
            "type":"Food & Drink"
        }
    ],
    "sg:phone":"+1 416 742 1771",
    "sg:postcode":"M9M 2G1",
    "sg:province":"ON",
    "wof:name":"Metro Pizza",
    "wof:placetype":"venue"
},
  "geometry": {"coordinates":[-79.554626,43.74931],"type":"Point"}
}