{
  "type": "Feature",
  "properties": {
    "iso:country":"CA",
    "sg:city":"Truro",
    "sg:classifiers":[
        {
            "category":"Food & Beverages",
            "subcategory":"Bakery",
            "type":"Retail Goods"
        }
    ],
    "sg:phone":"+1 902 895 3868",
    "sg:postcode":"B2N 4B4",
    "sg:province":"NS",
    "sg:tags":[
        "tea",
        "coffee",
        "doughnut"
    ],
    "wof:name":"Tim Hortons",
    "wof:placetype":"venue"
},
  "geometry": {"coordinates":[-63.2766036987,45.3642730713],"type":"Point"}
}