{
  "type": "Feature",
  "properties": {
    "addr:full":"21 Ch Du Roy O Saint-Jean-Port-Joli QC G0R 3G0",
    "addr:housenumber":"21",
    "addr:postcode":"g0r 3g0",
    "addr:street":"Ch Du Roy O",
    "iso:country":"CA",
    "sg:address":"21 Ch Du Roy O",
    "sg:city":"Saint-Jean-Port-Joli",
    "sg:classifiers":[
        {
            "category":"Personal",
            "subcategory":"Barber",
            "type":"Services"
        }
    ],
    "sg:phone":"+1 418 598 9483",
    "sg:postcode":"G0R 3G0",
    "sg:province":"QC",
    "wof:name":"Salon Capilus",
    "wof:placetype":"venue"
},
  "geometry": {"coordinates":[-70.2687,47.213898],"type":"Point"}
}