{
  "type": "Feature",
  "properties": {
    "addr:full":"269 John St N Hamilton ON L8L 4P6",
    "addr:housenumber":"269",
    "addr:postcode":"l8l 4p6",
    "addr:street":"John St N",
    "iso:country":"CA",
    "sg:address":"269 John St N",
    "sg:city":"Hamilton",
    "sg:classifiers":[
        {
            "category":"Restaurant",
            "type":"Food & Drink"
        }
    ],
    "sg:phone":"+1 905 529 4746",
    "sg:postcode":"L8L 4P6",
    "sg:province":"ON",
    "sg:tags":[
        "club",
        "banquet",
        "rooms"
    ],
    "wof:name":"Venetian Club",
    "wof:placetype":"venue"
},
  "geometry": {"coordinates":[-79.863197,43.263866],"type":"Point"}
}