{
  "type": "Feature",
  "properties": {
    "addr:full":"570 Yonge St Toronto ON M4Y 1Z3",
    "addr:housenumber":"570",
    "addr:postcode":"m4y 1z3",
    "addr:street":"Yonge St",
    "iso:country":"CA",
    "sg:address":"570 Yonge St",
    "sg:city":"Toronto",
    "sg:classifiers":[
        {
            "category":"Restaurant",
            "type":"Food & Drink"
        }
    ],
    "sg:phone":"+1 416 960 8898",
    "sg:postcode":"M4Y 1Z3",
    "sg:province":"ON",
    "wof:name":"Not Just Noodles",
    "wof:placetype":"venue"
},
  "geometry": {"coordinates":[-79.384727478,43.6650009155],"type":"Point"}
}