{
  "type": "Feature",
  "properties": {
    "addr:full":"81 Thorne Ave Saint John NB E2J 1W7",
    "addr:housenumber":"81",
    "addr:postcode":"e2j 1w7",
    "addr:street":"Thorne Ave",
    "iso:country":"CA",
    "sg:address":"81 Thorne Ave",
    "sg:city":"Saint John",
    "sg:classifiers":[
        {
            "category":"Retail",
            "subcategory":"Auto Repair",
            "type":"Services"
        }
    ],
    "sg:phone":"+1 506 634 7743",
    "sg:postcode":"E2J 1W7",
    "sg:province":"NB",
    "sg:tags":[
        "spring"
    ],
    "wof:name":"Saint John Spring Works Ltd",
    "wof:placetype":"venue"
},
  "geometry": {"coordinates":[-66.04716500000001,45.285774],"type":"Point"}
}