{
  "type": "Feature",
  "properties": {
    "addr:full":"5 Alberta Ave Sault Ste Marie ON P6B 2N6",
    "addr:housenumber":"5",
    "addr:postcode":"p6b 2n6",
    "addr:street":"Alberta Ave",
    "iso:country":"CA",
    "sg:address":"5 Alberta Ave",
    "sg:city":"Sault Ste Marie",
    "sg:classifiers":[
        {
            "category":"Freight",
            "type":"Transportation"
        }
    ],
    "sg:phone":"+1 705 254 3278",
    "sg:postcode":"P6B 2N6",
    "sg:province":"ON",
    "sg:tags":[
        "courier"
    ],
    "wof:name":"Tlc Courier Svc",
    "wof:placetype":"venue"
},
  "geometry": {"coordinates":[-84.326302,46.520115],"type":"Point"}
}