{
  "type": "Feature",
  "properties": {
    "iso:country":"CA",
    "sg:address":"22750 Lougheed Hwy",
    "sg:city":"Maple Ridge",
    "sg:classifiers":[
        {
            "category":"Retail",
            "subcategory":"Auto Repair",
            "type":"Services"
        }
    ],
    "sg:phone":"+1 604 463 7158",
    "sg:postcode":"V2X 2V6",
    "sg:province":"BC",
    "sg:tags":[
        "muffler",
        "exhaust",
        "brake"
    ],
    "wof:name":"Budget Brake & Muffler",
    "wof:placetype":"venue"
},
  "geometry": {"coordinates":[-122.592155456,49.2165031433],"type":"Point"}
}