{
  "type": "Feature",
  "properties": {
    "addr:full":"1 Valleybrook Dr # 101 North York ON M3B 2S7",
    "addr:housenumber":"1",
    "addr:postcode":"m3b 2s7",
    "addr:street":"Valleybrook Dr # 101",
    "iso:country":"CA",
    "sg:address":"1 Valleybrook Dr # 101",
    "sg:city":"North York",
    "sg:classifiers":[
        {
            "category":"Restaurant",
            "type":"Food & Drink"
        }
    ],
    "sg:phone":"+1 416 447 9462",
    "sg:postcode":"M3B 2S7",
    "sg:province":"ON",
    "sg:tags":[
        "out"
    ],
    "wof:name":"Chris Coffee Shop",
    "wof:placetype":"venue"
},
  "geometry": {"coordinates":[-79.35414886469999,43.7581748962],"type":"Point"}
}