{
  "type": "Feature",
  "properties": {
    "addr:full":"Edmonton AB T5K 2J1",
    "addr:postcode":"t5k 2j1",
    "iso:country":"CA",
    "sg:city":"Edmonton",
    "sg:classifiers":[
        {
            "category":"Organizations",
            "subcategory":"Professional Association",
            "type":"Services"
        }
    ],
    "sg:phone":"+1 780 451 5444",
    "sg:postcode":"T5K 2J1",
    "sg:province":"AB",
    "wof:name":"Construction Labour Relations",
    "wof:placetype":"venue"
},
  "geometry": {"coordinates":[-113.514168,53.539906],"type":"Point"}
}