{
  "type": "Feature",
  "properties": {
    "addr:full":"Surrey BC V3V 4G1",
    "addr:postcode":"v3v 4g1",
    "iso:country":"CA",
    "sg:city":"Surrey",
    "sg:classifiers":[
        {
            "category":"Autos & Motor Vehicles",
            "subcategory":"Recreational Vehicle Sales",
            "type":"Retail Goods"
        }
    ],
    "sg:phone":"+1 604 584 3722",
    "sg:postcode":"V3V 4G1",
    "sg:province":"BC",
    "sg:tags":[
        "canopy",
        "shell",
        "truck",
        "cap"
    ],
    "wof:name":"Westmount Canopies Plus",
    "wof:placetype":"venue"
},
  "geometry": {"coordinates":[-122.89010620099999,49.1899490356],"type":"Point"}
}