{
  "type": "Feature",
  "properties": {
    "addr:full":"Calgary AB T2P 3T5",
    "addr:postcode":"t2p 3t5",
    "iso:country":"CA",
    "sg:city":"Calgary",
    "sg:classifiers":[
        {
            "category":"Education",
            "subcategory":"College",
            "type":"Public Place"
        }
    ],
    "sg:phone":"+1 403 571 2550",
    "sg:postcode":"T2P 3T5",
    "sg:province":"AB",
    "sg:tags":[
        "academic",
        "church"
    ],
    "wof:name":"Nazarene University College",
    "wof:placetype":"venue"
},
  "geometry": {"coordinates":[-114.079421997,51.0496406555],"type":"Point"}
}