{
  "type": "Feature",
  "properties": {
    "addr:full":"Regina SK S4N 6M5",
    "addr:postcode":"s4n 6m5",
    "iso:country":"CA",
    "sg:city":"Regina",
    "sg:classifiers":[
        {
            "category":"Recreation",
            "type":"Entertainment"
        }
    ],
    "sg:phone":"+1 306 777 7000",
    "sg:postcode":"S4N 6M5",
    "sg:province":"SK",
    "sg:tags":[
        "skating",
        "rink"
    ],
    "wof:name":"Regina Skating Rinks",
    "wof:placetype":"venue"
},
  "geometry": {"coordinates":[-104.546722,50.447712],"type":"Point"}
}