{
  "type": "Feature",
  "properties": {
    "addr:full":"460 Rue Pomerleau Thetford Mines QC G6G 2H9",
    "addr:housenumber":"460",
    "addr:postcode":"g6g 2h9",
    "addr:street":"Rue Pomerleau",
    "iso:country":"CA",
    "sg:address":"460 Rue Pomerleau",
    "sg:city":"Thetford Mines",
    "sg:classifiers":[
        {
            "category":"Shopping",
            "type":"Retail Goods"
        }
    ],
    "sg:phone":"+1 418 338 6160",
    "sg:postcode":"G6G 2H9",
    "sg:province":"QC",
    "sg:tags":[
        "whirlpool",
        "equipment",
        "bath",
        "supply"
    ],
    "wof:name":"Bain Magique Thetford",
    "wof:placetype":"venue"
},
  "geometry": {"coordinates":[-71.29579200000001,46.098389],"type":"Point"}
}