{
  "type": "Feature",
  "properties": {
    "addr:full":"232 Oxford St Goderich ON N7A 1G3",
    "addr:housenumber":"232",
    "addr:postcode":"n7a 1g3",
    "addr:street":"Oxford St",
    "iso:country":"CA",
    "sg:address":"232 Oxford St",
    "sg:city":"Goderich",
    "sg:classifiers":[
        {
            "category":"Retail",
            "subcategory":"Auto Repair",
            "type":"Services"
        }
    ],
    "sg:phone":"+1 519 524 9538",
    "sg:postcode":"N7A 1G3",
    "sg:province":"ON",
    "sg:tags":[
        "repairing",
        "automobile"
    ],
    "wof:name":"Philip Breckles Automotive",
    "wof:placetype":"venue"
},
  "geometry": {"coordinates":[-81.69872283940001,43.7392044067],"type":"Point"}
}