{
  "type": "Feature",
  "properties": {
    "iso:country":"CA",
    "sg:address":"1771 Rose St",
    "sg:city":"Regina",
    "sg:classifiers":[
        {
            "category":"Social Services",
            "type":"Services"
        }
    ],
    "sg:phone":"+1 306 359 1862",
    "sg:postcode":"S4P 1Z4",
    "sg:province":"SK",
    "sg:tags":[
        "pregnancy",
        "information",
        "welfare",
        "counseling",
        "organization"
    ],
    "wof:name":"Birthright",
    "wof:placetype":"venue"
},
  "geometry": {"coordinates":[-104.60773467999999,50.4509811401],"type":"Point"}
}