{
  "type": "Feature",
  "properties": {
    "addr:full":"251 Rue Victoria Thurso QC J0X 3B0",
    "addr:housenumber":"251",
    "addr:postcode":"j0x 3b0",
    "addr:street":"Rue Victoria",
    "iso:country":"CA",
    "sg:address":"251 Rue Victoria",
    "sg:city":"Thurso",
    "sg:classifiers":[
        {
            "category":"Building & Trades",
            "subcategory":"Construction",
            "type":"Services"
        }
    ],
    "sg:phone":"+1 819 985 3501",
    "sg:postcode":"J0X 3B0",
    "sg:province":"QC",
    "sg:tags":[
        "equipment",
        "kitchen",
        "maker",
        "cabinet"
    ],
    "wof:name":"Boiseries Boileau Inc",
    "wof:placetype":"venue"
},
  "geometry": {"coordinates":[-75.23715199999999,45.597713],"type":"Point"}
}