{
  "type": "Feature",
  "properties": {
    "iso:country":"CA",
    "sg:address":"5150 Rue Paul-Pau",
    "sg:city":"Montreal",
    "sg:classifiers":[
        {
            "category":"Retail",
            "subcategory":"Auto Repair",
            "type":"Services"
        }
    ],
    "sg:phone":"+1 514 352 2850",
    "sg:postcode":"H1K 2M8",
    "sg:province":"QC",
    "sg:tags":[
        "lining",
        "brake"
    ],
    "wof:name":"Frein & Embrayage P & D Inc",
    "wof:placetype":"venue"
},
  "geometry": {"coordinates":[-73.532776,45.609444],"type":"Point"}
}