{
  "type": "Feature",
  "properties": {
    "addr:full":"Kash Rd Kashabowie ON P0T 1Y0",
    "addr:postcode":"p0t 1y0",
    "addr:street":"Kash Rd",
    "iso:country":"CA",
    "sg:address":"Kash Rd",
    "sg:city":"Kashabowie",
    "sg:classifiers":[
        {
            "category":"Travel",
            "subcategory":"Campground",
            "type":"Entertainment"
        }
    ],
    "sg:phone":"+1 807 926 2410",
    "sg:postcode":"P0T 1Y0",
    "sg:province":"ON",
    "sg:tags":[
        "camp",
        "fishing"
    ],
    "wof:name":"Lake Kashabowie Lodge & Camp",
    "wof:placetype":"venue"
},
  "geometry": {"coordinates":[-90.434029,48.649181],"type":"Point"}
}