{
  "type": "Feature",
  "properties": {
    "addr:full":"1841 Finch Ave W North York ON M3N 2V2",
    "addr:housenumber":"1841",
    "addr:postcode":"m3n 2v2",
    "addr:street":"Finch Ave W",
    "iso:country":"CA",
    "sg:address":"1841 Finch Ave W",
    "sg:city":"North York",
    "sg:classifiers":[
        {
            "category":"Restaurant",
            "type":"Food & Drink"
        }
    ],
    "sg:phone":"+1 416 638 6769",
    "sg:postcode":"M3N 2V2",
    "sg:province":"ON",
    "wof:name":"Di Salvo Panini Italian",
    "wof:placetype":"venue"
},
  "geometry": {"coordinates":[-79.513969,43.757771],"type":"Point"}
}