{
  "type": "Feature",
  "properties": {
    "addr:full":"59 Joseph St Markham ON L3P 2N4",
    "addr:housenumber":"59",
    "addr:postcode":"l3p 2n4",
    "addr:street":"Joseph St",
    "iso:country":"CA",
    "sg:address":"59 Joseph St",
    "sg:city":"Markham",
    "sg:classifiers":[
        {
            "category":"Organizations",
            "subcategory":"Non-profit Organization",
            "type":"Services"
        }
    ],
    "sg:phone":"+1 905 294 2838",
    "sg:postcode":"L3P 2N4",
    "sg:province":"ON",
    "sg:tags":[
        "consultant",
        "search",
        "executive",
        "screening",
        "background"
    ],
    "wof:name":"Just Checking Resources Inc",
    "wof:placetype":"venue"
},
  "geometry": {"coordinates":[-79.25606536870001,43.8785438538],"type":"Point"}
}