{
  "type": "Feature",
  "properties": {
    "iso:country":"CA",
    "sg:address":"1260 Old Innes Rd",
    "sg:city":"Ottawa",
    "sg:classifiers":[
        {
            "category":"Professional",
            "subcategory":"Engineering",
            "type":"Services"
        }
    ],
    "sg:phone":"+1 613 748 5500",
    "sg:postcode":"K1B 3V3",
    "sg:province":"ON",
    "sg:tags":[
        "engineer"
    ],
    "wof:name":"Davis Engineering Ltd",
    "wof:placetype":"venue"
},
  "geometry": {"coordinates":[-75.617477417,45.4103431702],"type":"Point"}
}