{
  "type": "Feature",
  "properties": {
    "iso:country":"CA",
    "sg:city":"Saint-Aubert",
    "sg:classifiers":[
        {
            "category":"Food & Beverages",
            "subcategory":"Groceries & Convenience Stores",
            "type":"Retail Goods"
        }
    ],
    "sg:phone":"+1 418 598 6022",
    "sg:postcode":"G0R 2R0",
    "sg:province":"QC",
    "wof:name":"Epicerie Hector Deschenes Enr",
    "wof:placetype":"venue"
},
  "geometry": {"coordinates":[-70.2129211426,47.185585022],"type":"Point"}
}