{
  "type": "Feature",
  "properties": {
    "iso:country":"CA",
    "sg:address":"360 Bay St",
    "sg:city":"Toronto",
    "sg:classifiers":[
        {
            "category":"Shopping",
            "subcategory":"Computers & Home Electronics",
            "type":"Retail Goods"
        }
    ],
    "sg:phone":"+1 416 367 3775",
    "sg:postcode":"M5H 2V6",
    "sg:province":"ON",
    "sg:tags":[
        "consultant",
        "software"
    ],
    "wof:name":"Electronic Software Products",
    "wof:placetype":"venue"
},
  "geometry": {"coordinates":[-79.381332,43.65073],"type":"Point"}
}