{
  "type": "Feature",
  "properties": {
    "iso:country":"CA",
    "sg:city":"Grande-Vallee",
    "sg:classifiers":[
        {
            "category":"Food & Beverages",
            "subcategory":"Bakery",
            "type":"Retail Goods"
        }
    ],
    "sg:phone":"+1 418 393 3088",
    "sg:postcode":"G0E 1K0",
    "sg:province":"QC",
    "sg:tags":[
        "baker"
    ],
    "wof:name":"Boulangerie Du Boulevard Enr",
    "wof:placetype":"venue"
},
  "geometry": {"coordinates":[-65.1322402954,49.2243804932],"type":"Point"}
}