{
  "type": "Feature",
  "properties": {
    "addr:full":"45809 Ferguson Line Belmont ON N0L 1B0",
    "addr:housenumber":"45809",
    "addr:postcode":"n0l 1b0",
    "addr:street":"Ferguson Line",
    "iso:country":"CA",
    "sg:address":"45809 Ferguson Line",
    "sg:city":"Belmont",
    "sg:classifiers":[
        {
            "category":"Sports & Exercise",
            "subcategory":"Golf",
            "type":"Entertainment"
        }
    ],
    "sg:phone":"+1 519 644 1370",
    "sg:postcode":"N0L 1B0",
    "sg:province":"ON",
    "sg:tags":[
        "club"
    ],
    "wof:name":"Belmont Golf Club",
    "wof:placetype":"venue"
},
  "geometry": {"coordinates":[-81.096146,42.834129],"type":"Point"}
}