{
  "type": "Feature",
  "properties": {
    "iso:country":"CA",
    "sg:address":"Hwy 2 S",
    "sg:city":"Bowden",
    "sg:classifiers":[
        {
            "category":"Sports & Exercise",
            "subcategory":"Golf",
            "type":"Entertainment"
        }
    ],
    "sg:phone":"+1 403 224 2121",
    "sg:postcode":"T0M 0K0",
    "sg:province":"AB",
    "sg:tags":[
        "course"
    ],
    "wof:name":"Bowden hi-Way Golf Assn",
    "wof:placetype":"venue"
},
  "geometry": {"coordinates":[-114.02546700000001,51.928654],"type":"Point"}
}