{
  "type": "Feature",
  "properties": {
    "addr:full":"313 Goldstream Ave Victoria BC V9B 2W4",
    "addr:housenumber":"313",
    "addr:postcode":"v9b 2w4",
    "addr:street":"Goldstream Ave",
    "iso:country":"CA",
    "sg:address":"313 Goldstream Ave",
    "sg:city":"Victoria",
    "sg:classifiers":[
        {
            "category":"Restaurant",
            "type":"Food & Drink"
        }
    ],
    "sg:phone":"+1 250 391 0803",
    "sg:postcode":"V9B 2W4",
    "sg:province":"BC",
    "wof:name":"Bill's Restaurant",
    "wof:placetype":"venue"
},
  "geometry": {"coordinates":[-123.364517212,48.428314209],"type":"Point"}
}