{
  "type": "Feature",
  "properties": {
    "addr:full":"1175 County Rd 20 Kingsville ON N9Y 2E6",
    "addr:housenumber":"1175",
    "addr:postcode":"n9y 2e6",
    "addr:street":"County Rd 20",
    "iso:country":"CA",
    "sg:address":"1175 County Rd 20",
    "sg:city":"Kingsville",
    "sg:classifiers":[
        {
            "category":"Building & Trades",
            "subcategory":"Landscaping Services",
            "type":"Services"
        }
    ],
    "sg:phone":"+1 519 733 2537",
    "sg:postcode":"N9Y 2E6",
    "sg:province":"ON",
    "sg:tags":[
        "tree"
    ],
    "wof:name":"County Wide Tree Svc",
    "wof:placetype":"venue"
},
  "geometry": {"coordinates":[-82.74031100000001,42.037884],"type":"Point"}
}