{
  "type": "Feature",
  "properties": {
    "addr:full":"1941 Eglinton Ave E Scarborough ON M1L 2M4",
    "addr:housenumber":"1941",
    "addr:postcode":"m1l 2m4",
    "addr:street":"Eglinton Ave E",
    "iso:country":"CA",
    "sg:address":"1941 Eglinton Ave E",
    "sg:city":"Scarborough",
    "sg:classifiers":[
        {
            "category":"Autos & Motor Vehicles",
            "subcategory":"Automobile Sales",
            "type":"Retail Goods"
        }
    ],
    "sg:phone":"+1 416 751 3511",
    "sg:postcode":"M1L 2M4",
    "sg:province":"ON",
    "sg:tags":[
        "car",
        "dealer"
    ],
    "wof:name":"Scarborough Nissan Ltd",
    "wof:placetype":"venue"
},
  "geometry": {"coordinates":[-79.28638458250001,43.7279701233],"type":"Point"}
}