{
  "type": "Feature",
  "properties": {
    "addr:full":"939 Main St Winnipeg MB R2W 3P2",
    "addr:housenumber":"939",
    "addr:postcode":"r2w 3p2",
    "addr:street":"Main St",
    "iso:country":"CA",
    "sg:address":"939 Main St",
    "sg:city":"Winnipeg",
    "sg:classifiers":[
        {
            "category":"Organizations",
            "subcategory":"Religious Organization",
            "type":"Services"
        }
    ],
    "sg:phone":"+1 204 942 3655",
    "sg:postcode":"R2W 3P2",
    "sg:province":"MB",
    "sg:tags":[
        "church"
    ],
    "wof:name":"St Ivan Suchavsky Ukrainian",
    "wof:placetype":"venue"
},
  "geometry": {"coordinates":[-97.132599,49.911137],"type":"Point"}
}