{
  "type": "Feature",
  "properties": {
    "addr:full":"Dartmouth NS B3A 1L8",
    "addr:postcode":"b3a 1l8",
    "iso:country":"CA",
    "sg:city":"Dartmouth",
    "sg:classifiers":[
        {
            "category":"Wholesale",
            "subcategory":"Chemicals & Plastics",
            "type":"Manufacturing & Wholesale Goods"
        }
    ],
    "sg:phone":"+1 902 464 9001",
    "sg:postcode":"B3A 1L8",
    "sg:province":"NS",
    "sg:tags":[
        "adhesive",
        "glue"
    ],
    "wof:name":"Hawk Industrial Sales",
    "wof:placetype":"venue"
},
  "geometry": {"coordinates":[-63.5848770142,44.6733703613],"type":"Point"}
}