{
  "type": "Feature",
  "properties": {
    "addr:full":"Bobcaygeon ON K0M 1A0",
    "addr:postcode":"k0m 1a0",
    "iso:country":"CA",
    "sg:city":"Bobcaygeon",
    "sg:classifiers":[
        {
            "category":"Retail",
            "subcategory":"Repair Shop",
            "type":"Services"
        }
    ],
    "sg:phone":"+1 705 738 3630",
    "sg:postcode":"K0M 1A0",
    "sg:province":"ON",
    "sg:tags":[
        "upholsterer"
    ],
    "wof:name":"Design Custom Upholstery",
    "wof:placetype":"venue"
},
  "geometry": {"coordinates":[-78.5469741821,44.5466651917],"type":"Point"}
}