{
  "type": "Feature",
  "properties": {
    "addr:full":"295 Main St Cardston AB T0K 0K0",
    "addr:housenumber":"295",
    "addr:postcode":"t0k 0k0",
    "addr:street":"Main St",
    "iso:country":"CA",
    "sg:address":"295 Main St",
    "sg:city":"Cardston",
    "sg:classifiers":[
        {
            "category":"Professional",
            "subcategory":"Business Services",
            "type":"Services"
        }
    ],
    "sg:phone":"+1 403 653 3006",
    "sg:postcode":"T0K 0K0",
    "sg:province":"AB",
    "sg:tags":[
        "license"
    ],
    "wof:name":"Chaparral Licensing & Registry",
    "wof:placetype":"venue"
},
  "geometry": {"coordinates":[-113.30197099999999,49.19902],"type":"Point"}
}