{
  "type": "Feature",
  "properties": {
    "iso:country":"CA",
    "sg:address":"251 Boul Fiset",
    "sg:city":"Sorel-Tracy",
    "sg:classifiers":[
        {
            "category":"Sports & Exercise",
            "subcategory":"Gym",
            "type":"Entertainment"
        }
    ],
    "sg:phone":"+1 450 746 1234",
    "sg:postcode":"J3P 3P9",
    "sg:province":"QC",
    "sg:tags":[
        "club",
        "health",
        "studio",
        "gymnasium"
    ],
    "wof:name":"Multi Forme Plus",
    "wof:placetype":"venue"
},
  "geometry": {"coordinates":[-73.0984344482,46.0397415161],"type":"Point"}
}