{
  "type": "Feature",
  "properties": {
    "iso:country":"CA",
    "sg:address":"304 Kinistino Ave",
    "sg:city":"Kinistino",
    "sg:classifiers":[
        {
            "category":"Retail",
            "subcategory":"Funeral Services",
            "type":"Services"
        }
    ],
    "sg:phone":"+1 306 864 3555",
    "sg:postcode":"S0J 1H0",
    "sg:province":"SK",
    "sg:tags":[
        "director"
    ],
    "wof:name":"Kinistino Funeral Home",
    "wof:placetype":"venue"
},
  "geometry": {"coordinates":[-105.034217834,52.9511146545],"type":"Point"}
}