{
  "type": "Feature",
  "properties": {
    "addr:full":"264 Westminster Ave W Penticton BC V2A 1J9",
    "addr:housenumber":"264",
    "addr:postcode":"v2a 1j9",
    "addr:street":"Westminster Ave W",
    "iso:country":"CA",
    "sg:address":"264 Westminster Ave W",
    "sg:city":"Penticton",
    "sg:classifiers":[
        {
            "category":"Professional",
            "subcategory":"Testing Lab",
            "type":"Services"
        }
    ],
    "sg:phone":"+1 250 492 9161",
    "sg:postcode":"V2A 1J9",
    "sg:province":"BC",
    "sg:tags":[
        "laboratory"
    ],
    "wof:name":"Okanagan Testing Svc",
    "wof:placetype":"venue"
},
  "geometry": {"coordinates":[-119.597054,49.499359],"type":"Point"}
}