{
  "type": "Feature",
  "properties": {
    "iso:country":"CA",
    "sg:address":"2 Lansing Sq",
    "sg:city":"North York",
    "sg:classifiers":[
        {
            "category":"Insurance",
            "subcategory":"Insurance Agent",
            "type":"Services"
        }
    ],
    "sg:phone":"+1 416 493 5586",
    "sg:postcode":"M2J 4P8",
    "sg:province":"ON",
    "wof:name":"Clewes & Assoc Life Insurance",
    "wof:placetype":"venue"
},
  "geometry": {"coordinates":[-79.325569,43.773476],"type":"Point"}
}