{
  "type": "Feature",
  "properties": {
    "addr:full":"109 Inverness Lane SE Calgary AB T2Z 2Y4",
    "addr:housenumber":"109",
    "addr:postcode":"t2z 2y4",
    "addr:street":"Inverness Lane Se",
    "iso:country":"CA",
    "sg:address":"109 Inverness Lane SE",
    "sg:city":"Calgary",
    "sg:classifiers":[
        {
            "category":"Building & Trades",
            "subcategory":"Construction",
            "type":"Services"
        }
    ],
    "sg:phone":"+1 403 257 2551",
    "sg:postcode":"T2Z 2Y4",
    "sg:province":"AB",
    "sg:tags":[
        "repairing",
        "remodeling",
        "door",
        "contractor"
    ],
    "wof:name":"Calgary Storm Doors",
    "wof:placetype":"venue"
},
  "geometry": {"coordinates":[-113.970512,50.912663],"type":"Point"}
}