{
  "type": "Feature",
  "properties": {
    "addr:full":"49 Rymal Rd E Hamilton ON L9B 1B9",
    "addr:housenumber":"49",
    "addr:postcode":"l9b 1b9",
    "addr:street":"Rymal Rd E",
    "iso:country":"CA",
    "sg:address":"49 Rymal Rd E",
    "sg:city":"Hamilton",
    "sg:classifiers":[
        {
            "category":"Autos & Motor Vehicles",
            "subcategory":"Automobile Sales",
            "type":"Retail Goods"
        }
    ],
    "sg:phone":"+1 905 388 6396",
    "sg:postcode":"L9B 1B9",
    "sg:province":"ON",
    "sg:tags":[
        "car",
        "dealer"
    ],
    "wof:name":"Airport Ford Lincoln Sales Ltd",
    "wof:placetype":"venue"
},
  "geometry": {"coordinates":[-79.89130400000001,43.202187],"type":"Point"}
}