{
  "type": "Feature",
  "properties": {
    "iso:country":"CA",
    "sg:address":"1906 Boul Bastien",
    "sg:city":"Quebec",
    "sg:classifiers":[
        {
            "category":"Restaurant",
            "type":"Food & Drink"
        }
    ],
    "sg:phone":"+1 418 843 4527",
    "sg:postcode":"G2B 1C1",
    "sg:province":"QC",
    "wof:name":"Restaurant Chez Le an",
    "wof:placetype":"venue"
},
  "geometry": {"coordinates":[-71.329689,46.85754],"type":"Point"}
}