{
  "type": "Feature",
  "properties": {
    "addr:full":"20 Wellington St S Drayton ON N0G 1P0",
    "addr:housenumber":"20",
    "addr:postcode":"n0g 1p0",
    "addr:street":"Wellington St S",
    "iso:country":"CA",
    "sg:address":"20 Wellington St S",
    "sg:city":"Drayton",
    "sg:classifiers":[
        {
            "category":"Personal",
            "subcategory":"Beauty Salon",
            "type":"Services"
        }
    ],
    "sg:phone":"+1 519 638 3025",
    "sg:postcode":"N0G 1P0",
    "sg:province":"ON",
    "wof:name":"Hair Daze",
    "wof:placetype":"venue"
},
  "geometry": {"coordinates":[-80.671898,43.754578],"type":"Point"}
}