{
  "type": "Feature",
  "properties": {
    "addr:full":"2635 Greenwood Rd RR 1 #A Nelson BC V1L 7A1",
    "addr:housenumber":"2635",
    "addr:postcode":"bc v1l 7a1",
    "addr:street":"Greenwood Rd;1 # A",
    "iso:country":"CA",
    "sg:address":"2635 Greenwood Rd RR 1 #A",
    "sg:city":"Nelson",
    "sg:classifiers":[
        {
            "category":"Food & Beverages",
            "subcategory":"Liquor & Beverages",
            "type":"Retail Goods"
        }
    ],
    "sg:phone":"+1 250 825 4645",
    "sg:postcode":"V1L 7A1",
    "sg:province":"BC",
    "sg:tags":[
        "resort"
    ],
    "wof:name":"Duhamel Store",
    "wof:placetype":"venue"
},
  "geometry": {"coordinates":[-117.231972,49.573357],"type":"Point"}
}