{
  "type": "Feature",
  "properties": {
    "addr:full":"54 Village Centre Pl Mississauga ON L4Z 1V9",
    "addr:housenumber":"54",
    "addr:postcode":"l4z 1v9",
    "addr:street":"Village Centre Pl",
    "iso:country":"CA",
    "sg:address":"54 Village Centre Pl",
    "sg:city":"Mississauga",
    "sg:classifiers":[
        {
            "category":"Professional",
            "subcategory":"Accounting & Tax Preparation",
            "type":"Services"
        }
    ],
    "sg:phone":"+1 905 277 9499",
    "sg:postcode":"L4Z 1V9",
    "sg:province":"ON",
    "sg:tags":[
        "accountant"
    ],
    "wof:name":"Jarvis Ryan Assoc",
    "wof:placetype":"venue"
},
  "geometry": {"coordinates":[-79.64091500000001,43.600555],"type":"Point"}
}