{
  "type": "Feature",
  "properties": {
    "iso:country":"CA",
    "sg:city":"Nanaimo",
    "sg:classifiers":[
        {
            "category":"Professional",
            "subcategory":"Accounting & Tax Preparation",
            "type":"Services"
        }
    ],
    "sg:phone":"+1 250 754 6396",
    "sg:postcode":"V9R 5H5",
    "sg:province":"BC",
    "sg:tags":[
        "consultant",
        "planning",
        "financial"
    ],
    "wof:name":"Church Pickard & CO",
    "wof:placetype":"venue"
},
  "geometry": {"coordinates":[-123.937141419,49.1672897339],"type":"Point"}
}