{
  "type": "Feature",
  "properties": {
    "addr:full":"120 Railway St Kingston ON K7K 2L9",
    "addr:housenumber":"120",
    "addr:postcode":"k7k 2l9",
    "addr:street":"Railway St",
    "iso:country":"CA",
    "sg:address":"120 Railway St",
    "sg:city":"Kingston",
    "sg:classifiers":[
        {
            "category":"Home & Garden",
            "subcategory":"Building Materials",
            "type":"Retail Goods"
        }
    ],
    "sg:phone":"+1 613 546 7220",
    "sg:postcode":"K7K 2L9",
    "sg:province":"ON",
    "sg:tags":[
        "glass",
        "window",
        "plate"
    ],
    "wof:name":"Afgd Glass Ctr",
    "wof:placetype":"venue"
},
  "geometry": {"coordinates":[-76.4924087524,44.2481536865],"type":"Point"}
}