{
  "type": "Feature",
  "properties": {
    "iso:country":"CA",
    "sg:city":"Carlyle",
    "sg:classifiers":[
        {
            "category":"Mining & Drilling",
            "type":"Manufacturing & Wholesale Goods"
        }
    ],
    "sg:phone":"+1 306 453 2545",
    "sg:postcode":"S0C 0R0",
    "sg:province":"SK",
    "sg:tags":[
        "company",
        "oil",
        "gas",
        "producer"
    ],
    "wof:name":"Talisman Energy Inc",
    "wof:placetype":"venue"
},
  "geometry": {"coordinates":[-102.276054382,49.6344985962],"type":"Point"}
}