{
  "type": "Feature",
  "properties": {
    "addr:full":"422 1st Ave SE Sturgis SK S0A 4A0",
    "addr:housenumber":"422",
    "addr:postcode":"s0a 4a0",
    "addr:street":"1St Ave Se",
    "iso:country":"CA",
    "sg:address":"422 1st Ave SE",
    "sg:city":"Sturgis",
    "sg:classifiers":[
        {
            "category":"Organizations",
            "subcategory":"Religious Organization",
            "type":"Services"
        }
    ],
    "sg:phone":"+1 306 548 2911",
    "sg:postcode":"S0A 4A0",
    "sg:province":"SK",
    "sg:tags":[
        "church"
    ],
    "wof:name":"Kingdom Hall of Jehovah's",
    "wof:placetype":"venue"
},
  "geometry": {"coordinates":[-102.540847778,51.9384918213],"type":"Point"}
}