{
  "type": "Feature",
  "properties": {
    "iso:country":"CA",
    "sg:address":"1955 Route 104",
    "sg:city":"Zealand",
    "sg:classifiers":[
        {
            "category":"Personal",
            "subcategory":"Beauty Salon",
            "type":"Services"
        }
    ],
    "sg:phone":"+1 506 363 3775",
    "sg:postcode":"E6L 2J2",
    "sg:province":"NB",
    "wof:name":"First Impression's Hairstyling",
    "wof:placetype":"venue"
},
  "geometry": {"coordinates":[-66.963508606,46.0671882629],"type":"Point"}
}