{
  "type": "Feature",
  "properties": {
    "addr:full":"4150 Lynn Valley Rd North Vancouver BC V7K 2T2",
    "addr:housenumber":"4150",
    "addr:postcode":"v7k 2t2",
    "addr:street":"Lynn Valley Rd",
    "iso:country":"CA",
    "sg:address":"4150 Lynn Valley Rd",
    "sg:city":"North Vancouver",
    "sg:classifiers":[
        {
            "category":"Professional",
            "subcategory":"Engineering",
            "type":"Services"
        }
    ],
    "sg:phone":"+1 604 987 4688",
    "sg:postcode":"V7K 2T2",
    "sg:province":"BC",
    "sg:tags":[
        "engineer"
    ],
    "wof:name":"Woodhead Consultants",
    "wof:placetype":"venue"
},
  "geometry": {"coordinates":[-123.022972107,49.3472290039],"type":"Point"}
}