{
  "type": "Feature",
  "properties": {
    "addr:full":"5 Nahanni Dr Yellowknife NT X1A 2P6",
    "addr:housenumber":"5",
    "addr:postcode":"x1a 2p6",
    "addr:street":"Nahanni Dr",
    "iso:country":"CA",
    "sg:address":"5 Nahanni Dr",
    "sg:city":"Yellowknife",
    "sg:classifiers":[
        {
            "category":"Retail",
            "subcategory":"Auto Repair",
            "type":"Services"
        }
    ],
    "sg:phone":"+1 867 873 5253",
    "sg:postcode":"X1A 2P6",
    "sg:province":"NT",
    "sg:tags":[
        "body",
        "automobile",
        "painting"
    ],
    "wof:name":"Superior Auto Body",
    "wof:placetype":"venue"
},
  "geometry": {"coordinates":[-114.425636,62.432438],"type":"Point"}
}