{
  "type": "Feature",
  "properties": {
    "addr:full":"1404 35 Ave Vernon BC V1T 2R6",
    "addr:housenumber":"1404",
    "addr:postcode":"v1t 2r6",
    "addr:street":"35 Ave",
    "iso:country":"CA",
    "sg:address":"1404 35 Ave",
    "sg:city":"Vernon",
    "sg:classifiers":[
        {
            "category":"Education",
            "subcategory":"School",
            "type":"Public Place"
        }
    ],
    "sg:phone":"+1 250 545 4409",
    "sg:postcode":"V1T 2R6",
    "sg:province":"BC",
    "wof:name":"Silver Star Elementary",
    "wof:placetype":"venue"
},
  "geometry": {"coordinates":[-119.248222,50.26733],"type":"Point"}
}