{
  "type": "Feature",
  "properties": {
    "iso:country":"CA",
    "sg:city":"Calgary",
    "sg:classifiers":[
        {
            "category":"Retail",
            "subcategory":"Auto Repair",
            "type":"Services"
        }
    ],
    "sg:phone":"+1 403 291 4869",
    "sg:postcode":"T2E 6L6",
    "sg:province":"AB",
    "sg:tags":[
        "repairing",
        "automobile"
    ],
    "wof:name":"Negenman Bros Auto Svc",
    "wof:placetype":"venue"
},
  "geometry": {"coordinates":[-114.03289,51.091892],"type":"Point"}
}