{
  "type": "Feature",
  "properties": {
    "addr:full":"2220 Midland Ave # 70Br Scarborough ON M1P 3E6",
    "addr:housenumber":"2220",
    "addr:postcode":"m1p 3e6",
    "addr:street":"Midland Ave # 70Br",
    "iso:country":"CA",
    "sg:address":"2220 Midland Ave # 70Br",
    "sg:city":"Scarborough",
    "sg:classifiers":[
        {
            "category":"Manufacturing",
            "subcategory":"Tools & Machinery",
            "type":"Manufacturing & Wholesale Goods"
        }
    ],
    "sg:phone":"+1 416 335 9877",
    "sg:postcode":"M1P 3E6",
    "sg:province":"ON",
    "sg:tags":[
        "equipment",
        "system",
        "automation"
    ],
    "wof:name":"Grohmann Automation",
    "wof:placetype":"venue"
},
  "geometry": {"coordinates":[-79.2736358643,43.7739944458],"type":"Point"}
}