{
  "type": "Feature",
  "properties": {
    "addr:full":"1250 Melton Dr Mississauga ON L4Y 1L5",
    "addr:housenumber":"1250",
    "addr:postcode":"l4y 1l5",
    "addr:street":"Melton Dr",
    "iso:country":"CA",
    "sg:address":"1250 Melton Dr",
    "sg:city":"Mississauga",
    "sg:classifiers":[
        {
            "category":"Education",
            "subcategory":"School",
            "type":"Public Place"
        }
    ],
    "sg:phone":"+1 905 277 8962",
    "sg:postcode":"L4Y 1L5",
    "sg:province":"ON",
    "wof:name":"St Edmund School",
    "wof:placetype":"venue"
},
  "geometry": {"coordinates":[-79.5773696899,43.5995025635],"type":"Point"}
}