{
  "type": "Feature",
  "properties": {
    "addr:full":"PO Box 619 STN Main Cochrane AB T4C 1A7",
    "addr:housenumber":"po",
    "addr:postcode":"t4c 1a7",
    "addr:street":"Box 619 Stn Main",
    "iso:country":"CA",
    "sg:address":"PO Box 619 STN Main",
    "sg:city":"Cochrane",
    "sg:classifiers":[
        {
            "category":"Health Services",
            "subcategory":"Health Practitioner",
            "type":"Services"
        }
    ],
    "sg:phone":"+1 403 932 5474",
    "sg:postcode":"T4C 1A7",
    "sg:province":"AB",
    "sg:tags":[
        "psychologist"
    ],
    "wof:name":"Taylor, Lance",
    "wof:placetype":"venue"
},
  "geometry": {"coordinates":[-114.468002,51.190826],"type":"Point"}
}