{
  "type": "Feature",
  "properties": {
    "addr:full":"Saint-Philippe QC J0L 2K0",
    "addr:postcode":"j0l 2k0",
    "iso:country":"CA",
    "sg:city":"Saint-Philippe",
    "sg:classifiers":[
        {
            "category":"Real Estate",
            "subcategory":"Developer",
            "type":"Services"
        }
    ],
    "sg:phone":"+1 450 444 7779",
    "sg:postcode":"J0L 2K0",
    "sg:province":"QC",
    "sg:tags":[
        "company",
        "land"
    ],
    "wof:name":"Villas DE Saint-Philippe",
    "wof:placetype":"venue"
},
  "geometry": {"coordinates":[-73.480377,45.355297],"type":"Point"}
}