{
  "type": "Feature",
  "properties": {
    "addr:full":"34 Rue Saint-Louis Saint-Cyrille-DE-Wendover QC J1Z 1S1",
    "addr:housenumber":"34",
    "addr:postcode":"j1z 1s1",
    "addr:street":"Rue Saint-Louis",
    "iso:country":"CA",
    "sg:address":"34 Rue Saint-Louis",
    "sg:city":"Saint-Cyrille-DE-Wendover",
    "sg:classifiers":[
        {
            "category":"Organizations",
            "subcategory":"Religious Organization",
            "type":"Services"
        }
    ],
    "sg:phone":"+1 819 397 2344",
    "sg:postcode":"J1Z 1S1",
    "sg:province":"QC",
    "sg:tags":[
        "church"
    ],
    "wof:name":"Presbytere St-Cyrille",
    "wof:placetype":"venue"
},
  "geometry": {"coordinates":[-72.4247741699,45.9331855774],"type":"Point"}
}