{
  "type": "Feature",
  "properties": {
    "addr:full":"133 Applewood Cres Concord ON L4K 4E4",
    "addr:housenumber":"133",
    "addr:postcode":"l4k 4e4",
    "addr:street":"Applewood Cres",
    "iso:country":"CA",
    "sg:address":"133 Applewood Cres",
    "sg:city":"Concord",
    "sg:classifiers":[
        {
            "category":"Building & Trades",
            "subcategory":"Construction",
            "type":"Services"
        }
    ],
    "sg:phone":"+1 905 761 8275",
    "sg:postcode":"L4K 4E4",
    "sg:province":"ON",
    "sg:tags":[
        "resurfacing",
        "laying",
        "refinishing",
        "floor"
    ],
    "wof:name":"Networx Flooring & Consulting",
    "wof:placetype":"venue"
},
  "geometry": {"coordinates":[-79.5325012207,43.8085823059],"type":"Point"}
}