{
  "type": "Feature",
  "properties": {
    "addr:full":"3333 Boul Rosemont Montreal QC H1X 1K4",
    "addr:housenumber":"3333",
    "addr:postcode":"h1x 1k4",
    "addr:street":"Boul Rosemont",
    "iso:country":"CA",
    "sg:address":"3333 Boul Rosemont",
    "sg:city":"Montreal",
    "sg:classifiers":[
        {
            "category":"Social Services",
            "subcategory":"Child Care",
            "type":"Services"
        }
    ],
    "sg:phone":"+1 514 727 5321",
    "sg:postcode":"H1X 1K4",
    "sg:province":"QC",
    "wof:name":"Garderie Beau Sourire Inc",
    "wof:placetype":"venue"
},
  "geometry": {"coordinates":[-73.57976499999999,45.554127],"type":"Point"}
}