{
  "type": "Feature",
  "properties": {
    "addr:full":"1306 56 St Delta BC V4L 2A4",
    "addr:housenumber":"1306",
    "addr:postcode":"v4l 2a4",
    "addr:street":"56 St",
    "iso:country":"CA",
    "sg:address":"1306 56 St",
    "sg:city":"Delta",
    "sg:classifiers":[
        {
            "category":"Food & Beverages",
            "subcategory":"Groceries & Convenience Stores",
            "type":"Retail Goods"
        }
    ],
    "sg:phone":"+1 604 943 2929",
    "sg:postcode":"V4L 2A4",
    "sg:province":"BC",
    "sg:tags":[
        "grocer"
    ],
    "wof:name":"Mac's Convenience Stores Ltd",
    "wof:placetype":"venue"
},
  "geometry": {"coordinates":[-123.06854199999999,49.026585],"type":"Point"}
}