{
  "type": "Feature",
  "properties": {
    "addr:full":"13412 Stony Plain Rd NW Edmonton AB T5N 3P5",
    "addr:housenumber":"13412",
    "addr:postcode":"t5n 3p5",
    "addr:street":"Stony Plain Rd Nw",
    "iso:country":"CA",
    "sg:address":"13412 Stony Plain Rd NW",
    "sg:city":"Edmonton",
    "sg:classifiers":[
        {
            "category":"Personal",
            "subcategory":"Beauty Salon",
            "type":"Services"
        }
    ],
    "sg:phone":"+1 780 452 4777",
    "sg:postcode":"T5N 3P5",
    "sg:province":"AB",
    "wof:name":"Phoenix hi-Touch Salon",
    "wof:placetype":"venue"
},
  "geometry": {"coordinates":[-113.55342102,53.5456542969],"type":"Point"}
}