{
  "type": "Feature",
  "properties": {
    "iso:country":"CA",
    "sg:address":"1289 Upper James St",
    "sg:city":"Hamilton",
    "sg:classifiers":[
        {
            "category":"Restaurant",
            "type":"Food & Drink"
        }
    ],
    "sg:phone":"+1 905 389 4113",
    "sg:postcode":"L9C 3B3",
    "sg:province":"ON",
    "sg:tags":[
        "basket",
        "parcel",
        "gift",
        "caterer"
    ],
    "wof:name":"Denninger Limited",
    "wof:placetype":"venue"
},
  "geometry": {"coordinates":[-79.888199,43.212875],"type":"Point"}
}