{
  "type": "Feature",
  "properties": {
    "addr:full":"4353 50 St NW Edmonton AB T6L 7E8",
    "addr:housenumber":"4353",
    "addr:postcode":"t6l 7e8",
    "addr:street":"50 St Nw",
    "iso:country":"CA",
    "sg:address":"4353 50 St NW",
    "sg:city":"Edmonton",
    "sg:classifiers":[
        {
            "category":"Food & Beverages",
            "subcategory":"Liquor & Beverages",
            "type":"Retail Goods"
        }
    ],
    "sg:phone":"+1 780 440 3521",
    "sg:postcode":"T6L 7E8",
    "sg:province":"AB",
    "sg:tags":[
        "store"
    ],
    "wof:name":"Liquor Barn",
    "wof:placetype":"venue"
},
  "geometry": {"coordinates":[-113.418549,53.480995],"type":"Point"}
}