{
  "type": "Feature",
  "properties": {
    "addr:full":"Calgary AB T3E 7J4",
    "addr:postcode":"t3e 7j4",
    "iso:country":"CA",
    "sg:city":"Calgary",
    "sg:classifiers":[
        {
            "category":"Communications",
            "subcategory":"Film & Video Production",
            "type":"Services"
        }
    ],
    "sg:phone":"+1 403 685 5357",
    "sg:postcode":"T3E 7J4",
    "sg:province":"AB",
    "sg:tags":[
        "taping"
    ],
    "wof:name":"Poindexter Productions Inc",
    "wof:placetype":"venue"
},
  "geometry": {"coordinates":[-114.122124,51.01741],"type":"Point"}
}