{
  "type": "Feature",
  "properties": {
    "iso:country":"CA",
    "sg:address":"13340 Mitchell Rd",
    "sg:city":"Richmond",
    "sg:classifiers":[
        {
            "category":"Building & Trades",
            "subcategory":"Construction",
            "type":"Services"
        }
    ],
    "sg:phone":"+1 604 324 3591",
    "sg:postcode":"V6V 1M8",
    "sg:province":"BC",
    "sg:tags":[
        "product",
        "paving",
        "asphalt",
        "contractor"
    ],
    "wof:name":"Columbia Bitulithic Ltd",
    "wof:placetype":"venue"
},
  "geometry": {"coordinates":[-123.07415,49.205544],"type":"Point"}
}