{
  "type": "Feature",
  "properties": {
    "iso:country":"CA",
    "sg:address":"1675 Rte Edouard-Vii",
    "sg:city":"Saint-Philippe",
    "sg:classifiers":[
        {
            "category":"Autos & Motor Vehicles",
            "subcategory":"Automobile Sales",
            "type":"Retail Goods"
        }
    ],
    "sg:phone":"+1 450 659 6666",
    "sg:postcode":"J0L 2K0",
    "sg:province":"QC",
    "sg:tags":[
        "car",
        "dealer"
    ],
    "wof:name":"Auto Jrl Inc",
    "wof:placetype":"venue"
},
  "geometry": {"coordinates":[-73.481407,45.375641],"type":"Point"}
}