{
  "type": "Feature",
  "properties": {
    "iso:country":"CA",
    "sg:city":"Montreal",
    "sg:classifiers":[
        {
            "category":"Manufacturing",
            "subcategory":"Jewelry",
            "type":"Manufacturing & Wholesale Goods"
        }
    ],
    "sg:phone":"+1 514 861 5771",
    "sg:postcode":"H3B 1M1",
    "sg:province":"QC",
    "wof:name":"Creations K",
    "wof:placetype":"venue"
},
  "geometry": {"coordinates":[-73.5683898926,45.5032424927],"type":"Point"}
}