{
  "type": "Feature",
  "properties": {
    "addr:full":"Nepean ON K2G 3J9",
    "addr:postcode":"k2g 3j9",
    "iso:country":"CA",
    "sg:city":"Nepean",
    "sg:classifiers":[
        {
            "category":"Building & Trades",
            "subcategory":"Cleaning & Sanitation",
            "type":"Services"
        }
    ],
    "sg:phone":"+1 613 860 1764",
    "sg:postcode":"K2G 3J9",
    "sg:province":"ON",
    "sg:tags":[
        "janitor"
    ],
    "wof:name":"Total Quality Cleaning",
    "wof:placetype":"venue"
},
  "geometry": {"coordinates":[-75.7345657349,45.3521842957],"type":"Point"}
}