{
  "type": "Feature",
  "properties": {
    "iso:country":"CA",
    "sg:address":"302 2nd Ave",
    "sg:city":"Irricana",
    "sg:classifiers":[
        {
            "category":"Education",
            "subcategory":"Library",
            "type":"Public Place"
        }
    ],
    "sg:phone":"+1 403 935 4818",
    "sg:postcode":"T0M 1B0",
    "sg:province":"AB",
    "wof:name":"Irricana & District Municipal",
    "wof:placetype":"venue"
},
  "geometry": {"coordinates":[-113.60597229,51.322227478],"type":"Point"}
}