{
  "type": "Feature",
  "properties": {
    "iso:country":"CA",
    "sg:city":"Mississauga",
    "sg:classifiers":[
        {
            "category":"Retail",
            "subcategory":"Veterinary Services",
            "type":"Services"
        }
    ],
    "sg:phone":"+1 905 821 9188",
    "sg:postcode":"L5M 5H1",
    "sg:province":"ON",
    "sg:tags":[
        "veterinarian"
    ],
    "wof:name":"Erin Center Veterinary Svc",
    "wof:placetype":"venue"
},
  "geometry": {"coordinates":[-79.7103347778,43.562335968],"type":"Point"}
}