{
  "type": "Feature",
  "properties": {
    "addr:full":"2403 2 Ave NW Calgary AB T2N 0H5",
    "addr:housenumber":"2403",
    "addr:postcode":"t2n 0h5",
    "addr:street":"2 Ave Nw",
    "iso:country":"CA",
    "sg:address":"2403 2 Ave NW",
    "sg:city":"Calgary",
    "sg:classifiers":[
        {
            "category":"Real Estate",
            "subcategory":"Real Estate Operator",
            "type":"Services"
        }
    ],
    "sg:phone":"+1 403 283 0985",
    "sg:postcode":"T2N 0H5",
    "sg:province":"AB",
    "sg:tags":[
        "apartment"
    ],
    "wof:name":"Kiwanis Senior Citizens Apts",
    "wof:placetype":"venue"
},
  "geometry": {"coordinates":[-114.115661621,51.0541648865],"type":"Point"}
}