{
  "type": "Feature",
  "properties": {
    "addr:full":"Nanaimo BC V9V 1R6",
    "addr:postcode":"v9v 1r6",
    "iso:country":"CA",
    "sg:city":"Nanaimo",
    "sg:classifiers":[
        {
            "category":"Personal",
            "subcategory":"Beauty Salon",
            "type":"Services"
        }
    ],
    "sg:phone":"+1 250 390 9082",
    "sg:postcode":"V9V 1R6",
    "sg:province":"BC",
    "sg:tags":[
        "tanning"
    ],
    "wof:name":"Hair Stylz",
    "wof:placetype":"venue"
},
  "geometry": {"coordinates":[-124.043838501,49.2395858765],"type":"Point"}
}