{
  "type": "Feature",
  "properties": {
    "addr:full":"724 King St Bridgewater NS B4V 1B4",
    "addr:housenumber":"724",
    "addr:postcode":"b4v 1b4",
    "addr:street":"King St",
    "iso:country":"CA",
    "sg:address":"724 King St",
    "sg:city":"Bridgewater",
    "sg:classifiers":[
        {
            "category":"Professional",
            "subcategory":"Accounting & Tax Preparation",
            "type":"Services"
        }
    ],
    "sg:phone":"+1 902 543 7361",
    "sg:postcode":"B4V 1B4",
    "sg:province":"NS",
    "sg:tags":[
        "return",
        "filing"
    ],
    "wof:name":"H & R Block Canada Inc",
    "wof:placetype":"venue"
},
  "geometry": {"coordinates":[-64.520782,44.37936],"type":"Point"}
}