{
  "type": "Feature",
  "properties": {
    "addr:full":"849 Upper Wentworth St # 406 Hamilton ON L9A 5H4",
    "addr:housenumber":"849;406",
    "addr:postcode":"l9a 5h4",
    "addr:street":"Upper Wentworth St #",
    "iso:country":"CA",
    "sg:address":"849 Upper Wentworth St # 406",
    "sg:city":"Hamilton",
    "sg:classifiers":[
        {
            "category":"Health Services",
            "subcategory":"Doctor",
            "type":"Services"
        }
    ],
    "sg:phone":"+1 905 575 9004",
    "sg:postcode":"L9A 5H4",
    "sg:province":"ON",
    "sg:tags":[
        "physician",
        "surgeon"
    ],
    "wof:name":"Zizzo, Richard A MD",
    "wof:placetype":"venue"
},
  "geometry": {"coordinates":[-79.862335,43.221664],"type":"Point"}
}