{
  "type": "Feature",
  "properties": {
    "iso:country":"CA",
    "sg:address":"160 Douglas St",
    "sg:city":"Sudbury",
    "sg:classifiers":[
        {
            "category":"Home & Garden",
            "subcategory":"Building Materials",
            "type":"Retail Goods"
        }
    ],
    "sg:phone":"+1 705 674 5747",
    "sg:postcode":"P3E 1G1",
    "sg:province":"ON",
    "sg:tags":[
        "siding"
    ],
    "wof:name":"M Champagne Siding Ltd",
    "wof:placetype":"venue"
},
  "geometry": {"coordinates":[-81.0019378662,46.4860343933],"type":"Point"}
}