{
  "type": "Feature",
  "properties": {
    "addr:full":"838 Glenforest St Oshawa ON L1J 5G1",
    "addr:housenumber":"838",
    "addr:postcode":"l1j 5g1",
    "addr:street":"Glenforest St",
    "iso:country":"CA",
    "sg:address":"838 Glenforest St",
    "sg:city":"Oshawa",
    "sg:classifiers":[
        {
            "category":"Building & Trades",
            "subcategory":"Plumbing",
            "type":"Services"
        }
    ],
    "sg:phone":"+1 905 433 8681",
    "sg:postcode":"L1J 5G1",
    "sg:province":"ON",
    "sg:tags":[
        "septic"
    ],
    "wof:name":"C A Coulter Waste Disposal Ltd",
    "wof:placetype":"venue"
},
  "geometry": {"coordinates":[-78.8898849487,43.9157028198],"type":"Point"}
}