{
  "type": "Feature",
  "properties": {
    "addr:full":"2806 27 Ave Vernon BC V1T 9K4",
    "addr:housenumber":"2806",
    "addr:postcode":"v1t 9k4",
    "addr:street":"27 Ave",
    "iso:country":"CA",
    "sg:address":"2806 27 Ave",
    "sg:city":"Vernon",
    "sg:classifiers":[
        {
            "category":"Railroad",
            "type":"Transportation"
        }
    ],
    "sg:phone":"+1 250 549 1473",
    "sg:postcode":"V1T 9K4",
    "sg:province":"BC",
    "wof:name":"Kelowna Pacific Railways Ltd",
    "wof:placetype":"venue"
},
  "geometry": {"coordinates":[-119.26907300000001,50.261509],"type":"Point"}
}