{
  "type": "Feature",
  "properties": {
    "addr:full":"54417 Range Road 222 Fort Saskatchewan AB T8L 3Z8",
    "addr:housenumber":"54417",
    "addr:postcode":"t8l 3z8",
    "addr:street":"Range Road 222",
    "iso:country":"CA",
    "sg:address":"54417 Range Road 222",
    "sg:city":"Fort Saskatchewan",
    "sg:classifiers":[
        {
            "category":"Recreation",
            "type":"Entertainment"
        }
    ],
    "sg:phone":"+1 780 998 2720",
    "sg:postcode":"T8L 3Z8",
    "sg:province":"AB",
    "sg:tags":[
        "stable"
    ],
    "wof:name":"Rocking Bar Ranch",
    "wof:placetype":"venue"
},
  "geometry": {"coordinates":[-113.214172,53.712887],"type":"Point"}
}