{
  "type": "Feature",
  "properties": {
    "addr:full":"Peterborough ON K9J 7S8",
    "addr:postcode":"k9j 7s8",
    "iso:country":"CA",
    "sg:city":"Peterborough",
    "sg:classifiers":[
        {
            "category":"Retail",
            "subcategory":"Car Wash",
            "type":"Services"
        }
    ],
    "sg:phone":"+1 705 741 6295",
    "sg:postcode":"K9J 7S8",
    "sg:province":"ON",
    "sg:tags":[
        "polishing",
        "automobile",
        "washing",
        "detail",
        "clean"
    ],
    "wof:name":"Pokey's Car Care",
    "wof:placetype":"venue"
},
  "geometry": {"coordinates":[-78.3342132568,44.2782897949],"type":"Point"}
}