{
  "type": "Feature",
  "properties": {
    "addr:full":"1145 Main St E Hamilton ON L8M 1P3",
    "addr:housenumber":"1145",
    "addr:postcode":"l8m 1p3",
    "addr:street":"Main St E",
    "iso:country":"CA",
    "sg:address":"1145 Main St E",
    "sg:city":"Hamilton",
    "sg:classifiers":[
        {
            "category":"Restaurant",
            "type":"Food & Drink"
        }
    ],
    "sg:phone":"+1 905 545 3924",
    "sg:postcode":"L8M 1P3",
    "sg:province":"ON",
    "wof:name":"Bright Spot Restaurant",
    "wof:placetype":"venue"
},
  "geometry": {"coordinates":[-79.82167099999999,43.243107],"type":"Point"}
}