{
  "type": "Feature",
  "properties": {
    "iso:country":"CA",
    "sg:address":"1145 Main St E",
    "sg:city":"Hamilton",
    "sg:classifiers":[
        {
            "category":"Restaurant",
            "type":"Food & Drink"
        }
    ],
    "sg:phone":"+1 905 545 3924",
    "sg:postcode":"L8M 1P3",
    "sg:province":"ON",
    "wof:name":"Bright Spot Restaurant",
    "wof:placetype":"venue"
},
  "geometry": {"coordinates":[-79.821671,43.243107],"type":"Point"}
}