{
  "type": "Feature",
  "properties": {
    "addr:full":"1950 Brigantine Dr Coquitlam BC V3K 7B5",
    "addr:housenumber":"1950",
    "addr:postcode":"v3k 7b5",
    "addr:street":"Brigantine Dr",
    "iso:country":"CA",
    "sg:address":"1950 Brigantine Dr",
    "sg:city":"Coquitlam",
    "sg:classifiers":[
        {
            "category":"Freight",
            "type":"Transportation"
        }
    ],
    "sg:phone":"+1 604 521 1714",
    "sg:postcode":"V3K 7B5",
    "sg:province":"BC",
    "sg:tags":[
        "booming",
        "log"
    ],
    "wof:name":"Pacific Custom Log Sorting Ltd",
    "wof:placetype":"venue"
},
  "geometry": {"coordinates":[-122.841300964,49.2244491577],"type":"Point"}
}