{
  "type": "Feature",
  "properties": {
    "addr:full":"2541 Victoria Ave Brandon MB R7B 0M6",
    "addr:housenumber":"2541",
    "addr:postcode":"r7b 0m6",
    "addr:street":"Victoria Ave",
    "iso:country":"CA",
    "sg:address":"2541 Victoria Ave",
    "sg:city":"Brandon",
    "sg:classifiers":[
        {
            "category":"Restaurant",
            "type":"Food & Drink"
        }
    ],
    "sg:phone":"+1 204 727 0647",
    "sg:postcode":"R7B 0M6",
    "sg:province":"MB",
    "wof:name":"Astoria Pizza & Pasta",
    "wof:placetype":"venue"
},
  "geometry": {"coordinates":[-99.9725494385,49.8425598145],"type":"Point"}
}