{
  "type": "Feature",
  "properties": {
    "addr:full":"27 Main St W Markdale ON N0C 1H0",
    "addr:housenumber":"27",
    "addr:postcode":"n0c 1h0",
    "addr:street":"Main St W",
    "iso:country":"CA",
    "sg:address":"27 Main St W",
    "sg:city":"Markdale",
    "sg:classifiers":[
        {
            "category":"Health Services",
            "subcategory":"Hospital",
            "type":"Services"
        }
    ],
    "sg:phone":"+1 519 986 3030",
    "sg:postcode":"N0C 1H0",
    "sg:province":"ON",
    "sg:tags":[
        "mental"
    ],
    "wof:name":"South Grey Comm Mental Health",
    "wof:placetype":"venue"
},
  "geometry": {"coordinates":[-80.6485214233,44.3180427551],"type":"Point"}
}