{
  "type": "Feature",
  "properties": {
    "addr:full":"5175 4E Av O Charlesbourg QC G1H 6W5",
    "addr:housenumber":"5175",
    "addr:postcode":"g1h 6w5",
    "addr:street":"4E Av O",
    "iso:country":"CA",
    "sg:address":"5175 4E Av O",
    "sg:city":"Charlesbourg",
    "sg:classifiers":[
        {
            "category":"Retail",
            "subcategory":"Auto Repair",
            "type":"Services"
        }
    ],
    "sg:phone":"+1 418 628 6468",
    "sg:postcode":"G1H 6W5",
    "sg:province":"QC",
    "sg:tags":[
        "repairing",
        "automobile"
    ],
    "wof:name":"Garage A & R Gagnon Inc",
    "wof:placetype":"venue"
},
  "geometry": {"coordinates":[-71.2493515015,46.8496818542],"type":"Point"}
}