{
  "type": "Feature",
  "properties": {
    "iso:country":"CA",
    "sg:address":"4458 10th Ave W",
    "sg:city":"Vancouver",
    "sg:classifiers":[
        {
            "category":"Home & Garden",
            "subcategory":"Home Furnishings",
            "type":"Retail Goods"
        }
    ],
    "sg:phone":"+1 604 222 1916",
    "sg:postcode":"V6R 2H9",
    "sg:province":"BC",
    "sg:tags":[
        "housewares"
    ],
    "wof:name":"Smarthouse Variety Store",
    "wof:placetype":"venue"
},
  "geometry": {"coordinates":[-123.20781707800001,49.2636795044],"type":"Point"}
}