{
  "type": "Feature",
  "properties": {
    "addr:full":"608 5th St Keremeos BC V0X 1N0",
    "addr:housenumber":"608",
    "addr:postcode":"v0x 1n0",
    "addr:street":"5Th St",
    "iso:country":"CA",
    "sg:address":"608 5th St",
    "sg:city":"Keremeos",
    "sg:classifiers":[
        {
            "category":"Organizations",
            "subcategory":"Religious Organization",
            "type":"Services"
        }
    ],
    "sg:phone":"+1 250 499 2036",
    "sg:postcode":"V0X 1N0",
    "sg:province":"BC",
    "sg:tags":[
        "church"
    ],
    "wof:name":"Catholic Church",
    "wof:placetype":"venue"
},
  "geometry": {"coordinates":[-119.827087402,49.2091255188],"type":"Point"}
}