{
  "type": "Feature",
  "properties": {
    "iso:country":"CA",
    "sg:city":"Notre-Dame-DE-LA-Paix",
    "sg:classifiers":[
        {
            "category":"Government",
            "subcategory":"Office",
            "type":"Public Place"
        }
    ],
    "sg:phone":"+1 819 522 6688",
    "sg:postcode":"J0V 1P0",
    "sg:province":"QC",
    "sg:tags":[
        "village"
    ],
    "wof:name":"Notre-Dame-DE LA-Paix Garage",
    "wof:placetype":"venue"
},
  "geometry": {"coordinates":[-74.9675750732,45.8087043762],"type":"Point"}
}