{
  "type": "Feature",
  "properties": {
    "addr:full":"St Albert AB T8N 1E4",
    "addr:postcode":"t8n 1e4",
    "iso:country":"CA",
    "sg:city":"St Albert",
    "sg:classifiers":[
        {
            "category":"Restaurant",
            "type":"Food & Drink"
        }
    ],
    "sg:phone":"+1 780 458 7575",
    "sg:postcode":"T8N 1E4",
    "sg:province":"AB",
    "wof:name":"Backstreet Cafe",
    "wof:placetype":"venue"
},
  "geometry": {"coordinates":[-113.625618,53.633808],"type":"Point"}
}