{
  "type": "Feature",
  "properties": {
    "addr:full":"2434 139 Ave NW Edmonton AB T5Y 2G9",
    "addr:housenumber":"2434",
    "addr:postcode":"t5y 2g9",
    "addr:street":"139 Ave Nw",
    "iso:country":"CA",
    "sg:address":"2434 139 Ave NW",
    "sg:city":"Edmonton",
    "sg:classifiers":[
        {
            "category":"Organizations",
            "subcategory":"Professional Association",
            "type":"Services"
        }
    ],
    "sg:phone":"+1 780 472 1193",
    "sg:postcode":"T5Y 2G9",
    "sg:province":"AB",
    "wof:name":"Bannerman Community Resource",
    "wof:placetype":"venue"
},
  "geometry": {"coordinates":[-113.38024900000001,53.602283],"type":"Point"}
}