{
  "type": "Feature",
  "properties": {
    "iso:country":"CA",
    "sg:city":"Edmonton",
    "sg:classifiers":[
        {
            "category":"Food & Beverages",
            "subcategory":"Specialty",
            "type":"Retail Goods"
        }
    ],
    "sg:phone":"+1 780 424 0456",
    "sg:postcode":"T5J 4A1",
    "sg:province":"AB",
    "sg:tags":[
        "tea",
        "coffee"
    ],
    "wof:name":"Bear Mountain",
    "wof:placetype":"venue"
},
  "geometry": {"coordinates":[-113.497901916,53.5431404114],"type":"Point"}
}