{
  "type": "Feature",
  "properties": {
    "addr:full":"266 Markham Rd Scarborough ON M1J 3C5",
    "addr:housenumber":"266",
    "addr:postcode":"m1j 3c5",
    "addr:street":"Markham Rd",
    "iso:country":"CA",
    "sg:address":"266 Markham Rd",
    "sg:city":"Scarborough",
    "sg:classifiers":[
        {
            "category":"Restaurant",
            "type":"Food & Drink"
        }
    ],
    "sg:phone":"+1 416 264 2564",
    "sg:postcode":"M1J 3C5",
    "sg:province":"ON",
    "wof:name":"Tim Choi Chinese Food",
    "wof:placetype":"venue"
},
  "geometry": {"coordinates":[-79.220146,43.745663],"type":"Point"}
}