{
  "type": "Feature",
  "properties": {
    "iso:country":"CA",
    "sg:address":"17 Northlawn Ave",
    "sg:city":"Waterdown",
    "sg:classifiers":[
        {
            "category":"Building & Trades",
            "subcategory":"Landscaping Services",
            "type":"Services"
        }
    ],
    "sg:phone":"+1 905 689 0554",
    "sg:postcode":"L0R 2H1",
    "sg:province":"ON",
    "sg:tags":[
        "designer",
        "landscape"
    ],
    "wof:name":"Reynolds & Assoc Landscape",
    "wof:placetype":"venue"
},
  "geometry": {"coordinates":[-79.906105,43.34119],"type":"Point"}
}