{
  "type": "Feature",
  "properties": {
    "addr:full":"Bancroft ON K0L 1C0",
    "addr:postcode":"k0l 1c0",
    "iso:country":"CA",
    "sg:city":"Bancroft",
    "sg:classifiers":[
        {
            "category":"Social Services",
            "type":"Services"
        }
    ],
    "sg:phone":"+1 613 332 4555",
    "sg:postcode":"K0L 1C0",
    "sg:province":"ON",
    "sg:tags":[
        "organization",
        "welfare"
    ],
    "wof:name":"Hastings & Prince Edward Count",
    "wof:placetype":"venue"
},
  "geometry": {"coordinates":[-77.862679,45.070599],"type":"Point"}
}