{
  "type": "Feature",
  "properties": {
    "addr:full":"2955 Boul Laurier Sainte-Foy QC G1V 2M2",
    "addr:housenumber":"2955",
    "addr:postcode":"g1v 2m2",
    "addr:street":"Boul Laurier",
    "iso:country":"CA",
    "sg:address":"2955 Boul Laurier",
    "sg:city":"Sainte-Foy",
    "sg:classifiers":[
        {
            "category":"Restaurant",
            "type":"Food & Drink"
        }
    ],
    "sg:phone":"+1 418 654 3644",
    "sg:postcode":"G1V 2M2",
    "sg:province":"QC",
    "wof:name":"Restaurant Rascal",
    "wof:placetype":"venue"
},
  "geometry": {"coordinates":[-71.2913818359,46.7653961182],"type":"Point"}
}