{
  "type": "Feature",
  "properties": {
    "addr:full":"162 Reach Industrial Park Rd Port Perry ON L9L 1B2",
    "addr:housenumber":"162",
    "addr:postcode":"l9l 1b2",
    "addr:street":"Reach Industrial Park Rd",
    "iso:country":"CA",
    "sg:address":"162 Reach Industrial Park Rd",
    "sg:city":"Port Perry",
    "sg:classifiers":[
        {
            "category":"Manufacturing",
            "subcategory":"Metals",
            "type":"Manufacturing & Wholesale Goods"
        }
    ],
    "sg:phone":"+1 905 982 1991",
    "sg:postcode":"L9L 1B2",
    "sg:province":"ON",
    "sg:tags":[
        "gates"
    ],
    "wof:name":"Alanjo Wrought Iron Works",
    "wof:placetype":"venue"
},
  "geometry": {"coordinates":[-78.98444366459999,44.1033248901],"type":"Point"}
}