{
  "type": "Feature",
  "properties": {
    "addr:full":"305 Rue Principale Saint-Modeste QC G0L 3W0",
    "addr:housenumber":"305",
    "addr:postcode":"g0l 3w0",
    "addr:street":"Rue Principale",
    "iso:country":"CA",
    "sg:address":"305 Rue Principale",
    "sg:city":"Saint-Modeste",
    "sg:classifiers":[
        {
            "category":"Personal",
            "subcategory":"Beauty Salon",
            "type":"Services"
        }
    ],
    "sg:phone":"+1 418 862 6469",
    "sg:postcode":"G0L 3W0",
    "sg:province":"QC",
    "wof:name":"Salon Louise Enr",
    "wof:placetype":"venue"
},
  "geometry": {"coordinates":[-69.406136,47.829178],"type":"Point"}
}