{
  "type": "Feature",
  "properties": {
    "addr:full":"6490 Rue Beaubien E Montreal QC H1M 1A9",
    "addr:housenumber":"6490",
    "addr:postcode":"h1m 1a9",
    "addr:street":"Rue Beaubien E",
    "iso:country":"CA",
    "sg:address":"6490 Rue Beaubien E",
    "sg:city":"Montreal",
    "sg:classifiers":[
        {
            "category":"Food & Beverages",
            "subcategory":"Liquor & Beverages",
            "type":"Retail Goods"
        }
    ],
    "sg:phone":"+1 514 259 2344",
    "sg:postcode":"H1M 1A9",
    "sg:province":"QC",
    "sg:tags":[
        "store"
    ],
    "wof:name":"Saq",
    "wof:placetype":"venue"
},
  "geometry": {"coordinates":[-73.5611114502,45.5870666504],"type":"Point"}
}