{
  "type": "Feature",
  "properties": {
    "addr:full":"12 Boul Laroche Warwick QC J0A 1M0",
    "addr:housenumber":"12",
    "addr:postcode":"j0a 1m0",
    "addr:street":"Boul Laroche",
    "iso:country":"CA",
    "sg:address":"12 Boul Laroche",
    "sg:city":"Warwick",
    "sg:classifiers":[
        {
            "category":"Recreation",
            "type":"Entertainment"
        }
    ],
    "sg:phone":"+1 819 358 2472",
    "sg:postcode":"J0A 1M0",
    "sg:province":"QC",
    "sg:tags":[
        "center"
    ],
    "wof:name":"Centre Recreatif Reg//Warwick",
    "wof:placetype":"venue"
},
  "geometry": {"coordinates":[-71.9915008545,45.9453811646],"type":"Point"}
}