{
  "type": "Feature",
  "properties": {
    "addr:full":"1201 Summit Dr Kamloops BC V2C 6C5",
    "addr:housenumber":"1201",
    "addr:postcode":"bc v2c 6c5",
    "addr:street":"Summit Dr",
    "iso:country":"CA",
    "sg:address":"1201 Summit Dr",
    "sg:city":"Kamloops",
    "sg:classifiers":[
        {
            "category":"Education",
            "subcategory":"Dance Studio",
            "type":"Public Place"
        }
    ],
    "sg:phone":"+1 250 314 9974",
    "sg:postcode":"V2C 6C5",
    "sg:province":"BC",
    "sg:tags":[
        "instruction",
        "dancing"
    ],
    "wof:name":"Academy of Dance",
    "wof:placetype":"venue"
},
  "geometry": {"coordinates":[-120.353989,50.667046],"type":"Point"}
}