{
  "type": "Feature",
  "properties": {
    "iso:country":"CA",
    "sg:address":"155 Clarke Rd",
    "sg:city":"London",
    "sg:classifiers":[
        {
            "category":"Food & Beverages",
            "subcategory":"Groceries & Convenience Stores",
            "type":"Retail Goods"
        }
    ],
    "sg:phone":"+1 519 455 5604",
    "sg:postcode":"N5W 5C9",
    "sg:province":"ON",
    "sg:tags":[
        "grocer"
    ],
    "wof:name":"A & P Food Stores Ltd",
    "wof:placetype":"venue"
},
  "geometry": {"coordinates":[-81.16966247560001,42.9916267395],"type":"Point"}
}