{
  "type": "Feature",
  "properties": {
    "addr:full":"Sudbury ON P3E 6C3",
    "addr:postcode":"p3e 6c3",
    "iso:country":"CA",
    "sg:city":"Sudbury",
    "sg:classifiers":[
        {
            "category":"Health Services",
            "subcategory":"Doctor",
            "type":"Services"
        }
    ],
    "sg:phone":"+1 705 523 4545",
    "sg:postcode":"P3E 6C3",
    "sg:province":"ON",
    "sg:tags":[
        "physician",
        "surgeon"
    ],
    "wof:name":"Kosar, S E MD",
    "wof:placetype":"venue"
},
  "geometry": {"coordinates":[-81.0034332275,46.4511795044],"type":"Point"}
}