{
  "type": "Feature",
  "properties": {
    "addr:full":"77 Brucewood Cres North York ON M6A 2G9",
    "addr:housenumber":"77",
    "addr:postcode":"m6a 2g9",
    "addr:street":"Brucewood Cres",
    "iso:country":"CA",
    "sg:address":"77 Brucewood Cres",
    "sg:city":"North York",
    "sg:classifiers":[
        {
            "category":"Wholesale",
            "subcategory":"Home Furnishings",
            "type":"Manufacturing & Wholesale Goods"
        }
    ],
    "sg:phone":"+1 416 256 7201",
    "sg:postcode":"M6A 2G9",
    "sg:province":"ON",
    "sg:tags":[
        "glassware",
        "chinaware"
    ],
    "wof:name":"Metro Smallwares Ltd",
    "wof:placetype":"venue"
},
  "geometry": {"coordinates":[-79.433144,43.723186],"type":"Point"}
}