{
  "type": "Feature",
  "properties": {
    "iso:country":"CA",
    "sg:address":"29 Commercial Crt",
    "sg:city":"Napanee",
    "sg:classifiers":[
        {
            "category":"Manufacturing",
            "subcategory":"Tools & Machinery",
            "type":"Manufacturing & Wholesale Goods"
        }
    ],
    "sg:phone":"+1 613 354 8467",
    "sg:postcode":"K7R 4A2",
    "sg:province":"ON",
    "sg:tags":[
        "truck"
    ],
    "wof:name":"Tim's Truck & Equipment Svc",
    "wof:placetype":"venue"
},
  "geometry": {"coordinates":[-76.960899353,44.2612228394],"type":"Point"}
}