{
  "type": "Feature",
  "properties": {
    "addr:full":"490 153 Rte E Grand-Mere QC G9T 3C1",
    "addr:housenumber":"153",
    "addr:postcode":"g9t 3c1",
    "addr:street":"Rte E Grand-Mere",
    "iso:country":"CA",
    "sg:address":"490 153 Rte E",
    "sg:city":"Grand-Mere",
    "sg:classifiers":[
        {
            "category":"Bars & Pubs",
            "type":"Food & Drink"
        }
    ],
    "sg:phone":"+1 819 538 8105",
    "sg:postcode":"G9T 3C1",
    "sg:province":"QC",
    "wof:name":"Bar Chez Bob",
    "wof:placetype":"venue"
},
  "geometry": {"coordinates":[-72.69319915769999,46.6209564209],"type":"Point"}
}