{
  "type": "Feature",
  "properties": {
    "addr:full":"Cote Saint-Luc QC H4W 3G7",
    "addr:postcode":"h4w 3g7",
    "addr:street":"Cote Saint-Luc",
    "iso:country":"CA",
    "sg:city":"Cote Saint-Luc",
    "sg:classifiers":[
        {
            "category":"Real Estate",
            "subcategory":"Real Estate Operator",
            "type":"Services"
        }
    ],
    "sg:phone":"+1 514 486 1660",
    "sg:postcode":"H4W 3G7",
    "sg:province":"QC",
    "sg:tags":[
        "condominium"
    ],
    "wof:name":"Rothchild Condominiums",
    "wof:placetype":"venue"
},
  "geometry": {"coordinates":[-73.66456604,45.4811706543],"type":"Point"}
}