{
  "type": "Feature",
  "properties": {
    "addr:full":"Laverlochere QC J0Z 2P0",
    "addr:postcode":"j0z 2p0",
    "iso:country":"CA",
    "sg:city":"Laverlochere",
    "sg:classifiers":[
        {
            "category":"Food & Beverages",
            "subcategory":"Groceries & Convenience Stores",
            "type":"Retail Goods"
        }
    ],
    "sg:phone":"+1 819 765 2121",
    "sg:postcode":"J0Z 2P0",
    "sg:province":"QC",
    "sg:tags":[
        "grocer"
    ],
    "wof:name":"Epicerie Bergeron Enrg",
    "wof:placetype":"venue"
},
  "geometry": {"coordinates":[-79.30717468260001,47.4264793396],"type":"Point"}
}