{
  "type": "Feature",
  "properties": {
    "addr:full":"RR 2 STN Main Tillsonburg ON N4G 4G7",
    "addr:postcode":"n4g 4g7",
    "addr:street":"Rr 2 Stn Main",
    "iso:country":"CA",
    "sg:address":"RR 2 STN Main",
    "sg:city":"Tillsonburg",
    "sg:classifiers":[
        {
            "category":"Building & Trades",
            "subcategory":"Construction",
            "type":"Services"
        }
    ],
    "sg:phone":"+1 519 842 6071",
    "sg:postcode":"N4G 4G7",
    "sg:province":"ON",
    "sg:tags":[
        "excavating",
        "contractor"
    ],
    "wof:name":"Trevor Hawley Trucking",
    "wof:placetype":"venue"
},
  "geometry": {"coordinates":[-80.7278671265,42.8606758118],"type":"Point"}
}