{
  "type": "Feature",
  "properties": {
    "addr:full":"15338 123 Ave NW Edmonton AB T5V 1K8",
    "addr:housenumber":"15338",
    "addr:postcode":"t5v 1k8",
    "addr:street":"123 Ave Nw",
    "iso:country":"CA",
    "sg:address":"15338 123 Ave NW",
    "sg:city":"Edmonton",
    "sg:classifiers":[
        {
            "category":"Building & Trades",
            "subcategory":"Construction",
            "type":"Services"
        }
    ],
    "sg:phone":"+1 780 452 9890",
    "sg:postcode":"T5V 1K8",
    "sg:province":"AB",
    "sg:tags":[
        "dry wall",
        "contractor"
    ],
    "wof:name":"Alpine Drywall & Plastering",
    "wof:placetype":"venue"
},
  "geometry": {"coordinates":[-113.585494995,53.5769042969],"type":"Point"}
}