{
  "type": "Feature",
  "properties": {
    "iso:country":"CA",
    "sg:address":"738 Ross Way",
    "sg:city":"Gabriola",
    "sg:classifiers":[
        {
            "category":"Building & Trades",
            "subcategory":"Construction",
            "type":"Services"
        }
    ],
    "sg:phone":"+1 250 755 6830",
    "sg:postcode":"V0R 1X0",
    "sg:province":"BC",
    "sg:tags":[
        "designer",
        "dealer",
        "pool",
        "swimming"
    ],
    "wof:name":"C-View Pools Ltd",
    "wof:placetype":"venue"
},
  "geometry": {"coordinates":[-123.84714508099999,49.1754226685],"type":"Point"}
}