{
  "type": "Feature",
  "properties": {
    "addr:full":"148 Bayshore Rd # 24 Brighton ON K0K 1H0",
    "addr:housenumber":"148",
    "addr:postcode":"k0k 1h0",
    "addr:street":"Bayshore Rd # 24",
    "iso:country":"CA",
    "sg:address":"148 Bayshore Rd # 24",
    "sg:city":"Brighton",
    "sg:classifiers":[
        {
            "category":"Manufacturing",
            "subcategory":"Printing",
            "type":"Manufacturing & Wholesale Goods"
        }
    ],
    "sg:phone":"+1 613 475 0335",
    "sg:postcode":"K0K 1H0",
    "sg:province":"ON",
    "sg:tags":[
        "printer"
    ],
    "wof:name":"Legend Products",
    "wof:placetype":"venue"
},
  "geometry": {"coordinates":[-77.68860599999999,44.002972],"type":"Point"}
}