{
  "type": "Feature",
  "properties": {
    "addr:full":"53 Estate Dr Scarborough ON M1H 2Z2",
    "addr:housenumber":"53",
    "addr:postcode":"m1h 2z2",
    "addr:street":"Estate Dr",
    "iso:country":"CA",
    "sg:address":"53 Estate Dr",
    "sg:city":"Scarborough",
    "sg:classifiers":[
        {
            "category":"Arts & Performance",
            "subcategory":"Theater",
            "type":"Entertainment"
        }
    ],
    "sg:phone":"+1 416 439 1104",
    "sg:postcode":"M1H 2Z2",
    "sg:province":"ON",
    "wof:name":"Scarborough Players",
    "wof:placetype":"venue"
},
  "geometry": {"coordinates":[-79.236862,43.782993],"type":"Point"}
}