{
  "type": "Feature",
  "properties": {
    "iso:country":"CA",
    "sg:address":"333 Ouellette Ave",
    "sg:city":"Windsor",
    "sg:classifiers":[
        {
            "category":"Bars & Pubs",
            "type":"Food & Drink"
        }
    ],
    "sg:phone":"+1 519 977 6102",
    "sg:postcode":"N9A 4J1",
    "sg:province":"ON",
    "sg:tags":[
        "lounge",
        "cocktail"
    ],
    "wof:name":"Vermouth",
    "wof:placetype":"venue"
},
  "geometry": {"coordinates":[-83.03894805909999,42.3170776367],"type":"Point"}
}