{
  "type": "Feature",
  "properties": {
    "addr:full":"57 Rue Saint-Charles-Borromee Joliette QC J6E 4R1",
    "addr:housenumber":"57",
    "addr:postcode":"j6e 4r1",
    "addr:street":"Rue Saint-Charles-Borromee",
    "iso:country":"CA",
    "sg:address":"57 Rue Saint-Charles-Borromee",
    "sg:city":"Joliette",
    "sg:classifiers":[
        {
            "category":"Manufacturing",
            "subcategory":"Printing",
            "type":"Manufacturing & Wholesale Goods"
        }
    ],
    "sg:phone":"+1 450 759 7575",
    "sg:postcode":"J6E 4R1",
    "sg:province":"QC",
    "sg:tags":[
        "designer",
        "graphic",
        "printer"
    ],
    "wof:name":"Imprimerie Pixell",
    "wof:placetype":"venue"
},
  "geometry": {"coordinates":[-73.43840026860001,46.0269088745],"type":"Point"}
}