{
  "type": "Feature",
  "properties": {
    "addr:full":"161 Orchard Heights Blvd Aurora ON L4G 3A3",
    "addr:housenumber":"161",
    "addr:postcode":"l4g 3a3",
    "addr:street":"Orchard Heights Blvd",
    "iso:country":"CA",
    "sg:address":"161 Orchard Heights Blvd",
    "sg:city":"Aurora",
    "sg:classifiers":[
        {
            "category":"Insurance",
            "subcategory":"Insurance Agent",
            "type":"Services"
        }
    ],
    "sg:phone":"+1 905 713 6563",
    "sg:postcode":"L4G 3A3",
    "sg:province":"ON",
    "wof:name":"Paul Laverty Insurance",
    "wof:placetype":"venue"
},
  "geometry": {"coordinates":[-79.48114776609999,44.0068664551],"type":"Point"}
}