{
  "type": "Feature",
  "properties": {
    "addr:full":"3015 120E Rue Saint-Georges-Est QC G5Y 5B9",
    "addr:housenumber":"3015",
    "addr:postcode":"g5y 5b9",
    "addr:street":"120E Rue Saint-Georges-Est",
    "iso:country":"CA",
    "sg:address":"3015 120E Rue",
    "sg:city":"Saint-Georges-Est",
    "sg:classifiers":[
        {
            "category":"Retail",
            "subcategory":"Auto Repair",
            "type":"Services"
        }
    ],
    "sg:phone":"+1 418 228 6266",
    "sg:postcode":"G5Y 5B9",
    "sg:province":"QC",
    "sg:tags":[
        "repairing",
        "automobile"
    ],
    "wof:name":"Garage Yvon Paquet",
    "wof:placetype":"venue"
},
  "geometry": {"coordinates":[-70.653069,46.132488],"type":"Point"}
}