{
  "type": "Feature",
  "properties": {
    "addr:full":"372 Rue Des Erables Saint-Lambert-DE-Lauzon QC G0S 2W0",
    "addr:housenumber":"372",
    "addr:postcode":"g0s 2w0",
    "addr:street":"Rue Des Erables",
    "iso:country":"CA",
    "sg:address":"372 Rue Des Erables",
    "sg:city":"Saint-Lambert-DE-Lauzon",
    "sg:classifiers":[
        {
            "category":"Autos & Motor Vehicles",
            "subcategory":"Fuel & Gas Station",
            "type":"Retail Goods"
        }
    ],
    "sg:phone":"+1 418 889 9956",
    "sg:postcode":"G0S 2W0",
    "sg:province":"QC",
    "sg:tags":[
        "oil"
    ],
    "wof:name":"Accommodation Vanier Inc",
    "wof:placetype":"venue"
},
  "geometry": {"coordinates":[-71.231323,46.635368],"type":"Point"}
}