{
  "type": "Feature",
  "properties": {
    "addr:full":"85 Kingston Rd E # 8 Ajax ON L1S 7J4",
    "addr:housenumber":"85",
    "addr:postcode":"l1s 7j4",
    "addr:street":"Kingston Rd E # 8",
    "iso:country":"CA",
    "sg:address":"85 Kingston Rd E # 8",
    "sg:city":"Ajax",
    "sg:classifiers":[
        {
            "category":"Personal",
            "subcategory":"Beauty Salon",
            "type":"Services"
        }
    ],
    "sg:phone":"+1 905 428 0220",
    "sg:postcode":"L1S 7J4",
    "sg:province":"ON",
    "sg:tags":[
        "manicuring"
    ],
    "wof:name":"Ajax Nails",
    "wof:placetype":"venue"
},
  "geometry": {"coordinates":[-79.021202,43.862049],"type":"Point"}
}