{
  "type": "Feature",
  "properties": {
    "addr:full":"18 Hughes Cres Perth ON K7H 3G3",
    "addr:housenumber":"18",
    "addr:postcode":"k7h 3g3",
    "addr:street":"Hughes Cres",
    "iso:country":"CA",
    "sg:address":"18 Hughes Cres",
    "sg:city":"Perth",
    "sg:classifiers":[
        {
            "category":"Professional",
            "type":"Services"
        }
    ],
    "sg:phone":"+1 613 264 2894",
    "sg:postcode":"K7H 3G3",
    "sg:province":"ON",
    "sg:tags":[
        "lumber",
        "establishment"
    ],
    "wof:name":"Rideau Home Building Ctr",
    "wof:placetype":"venue"
},
  "geometry": {"coordinates":[-76.2430114746,44.8894348145],"type":"Point"}
}