{
  "type": "Feature",
  "properties": {
    "addr:full":"544 Rockhill Cres Beaconsfield QC H9W 3G3",
    "addr:housenumber":"544",
    "addr:postcode":"h9w 3g3",
    "addr:street":"Rockhill Cres",
    "iso:country":"CA",
    "sg:address":"544 Rockhill Cres",
    "sg:city":"Beaconsfield",
    "sg:classifiers":[
        {
            "category":"Wholesale",
            "subcategory":"Machinery & Supplies",
            "type":"Manufacturing & Wholesale Goods"
        }
    ],
    "sg:phone":"+1 514 630 4227",
    "sg:postcode":"H9W 3G3",
    "sg:province":"QC",
    "sg:tags":[
        "equipment",
        "irrigation",
        "system"
    ],
    "wof:name":"Entreprises Irrigo Inc",
    "wof:placetype":"venue"
},
  "geometry": {"coordinates":[-73.8905410767,45.4239082336],"type":"Point"}
}