{
  "type": "Feature",
  "properties": {
    "iso:country":"CA",
    "sg:address":"PO Box 80",
    "sg:city":"Fort Good Hope",
    "sg:classifiers":[
        {
            "category":"Government",
            "subcategory":"Office",
            "type":"Public Place"
        }
    ],
    "sg:phone":"+1 867 598 2919",
    "sg:postcode":"X0E 0H0",
    "sg:province":"NT",
    "sg:tags":[
        "village"
    ],
    "wof:name":"Fort Good Hope Employment Ofc",
    "wof:placetype":"venue"
},
  "geometry": {"coordinates":[-128.60774230999999,66.2466201782],"type":"Point"}
}