{
  "type": "Feature",
  "properties": {
    "addr:full":"6182 North St Halifax NS B3K 1P5",
    "addr:housenumber":"6182",
    "addr:postcode":"b3k 1p5",
    "addr:street":"North St",
    "iso:country":"CA",
    "sg:address":"6182 North St",
    "sg:city":"Halifax",
    "sg:classifiers":[
        {
            "category":"Real Estate",
            "subcategory":"Real Estate Agent",
            "type":"Services"
        }
    ],
    "sg:phone":"+1 902 429 1811",
    "sg:postcode":"B3K 1P5",
    "sg:province":"NS",
    "wof:name":"Turner Drake & Partners Ltd",
    "wof:placetype":"venue"
},
  "geometry": {"coordinates":[-63.5978164673,44.6524162292],"type":"Point"}
}