{
  "type": "Feature",
  "properties": {
    "addr:full":"12827 96 Ave Surrey BC V3V 6V9",
    "addr:housenumber":"12827",
    "addr:postcode":"v3v 6v9",
    "addr:street":"96 Ave",
    "iso:country":"CA",
    "sg:address":"12827 96 Ave",
    "sg:city":"Surrey",
    "sg:classifiers":[
        {
            "category":"Retail",
            "subcategory":"Laundry & Dry Cleaning",
            "type":"Services"
        }
    ],
    "sg:phone":"+1 604 584 8828",
    "sg:postcode":"V3V 6V9",
    "sg:province":"BC",
    "wof:name":"Washette Coin Laundry",
    "wof:placetype":"venue"
},
  "geometry": {"coordinates":[-122.86702,49.177319],"type":"Point"}
}