{
  "type": "Feature",
  "properties": {
    "addr:full":"2250 Rue Saint-Philippe Trois-Rivieres QC G9A 4V7",
    "addr:housenumber":"2250",
    "addr:postcode":"g9a 4v7",
    "addr:street":"Rue Saint-Philippe",
    "iso:country":"CA",
    "sg:address":"2250 Rue Saint-Philippe",
    "sg:city":"Trois-Rivieres",
    "sg:classifiers":[
        {
            "category":"Retail",
            "subcategory":"Car Wash",
            "type":"Services"
        }
    ],
    "sg:phone":"+1 819 691 1986",
    "sg:postcode":"G9A 4V7",
    "sg:province":"QC",
    "sg:tags":[
        "polishing",
        "washing"
    ],
    "wof:name":"Lave Auto St-Philippe Reg'd",
    "wof:placetype":"venue"
},
  "geometry": {"coordinates":[-72.54737900000001,46.335464],"type":"Point"}
}