{
  "type": "Feature",
  "properties": {
    "iso:country":"CA",
    "sg:address":"1640 Av Dollard",
    "sg:city":"Lasalle",
    "sg:classifiers":[
        {
            "category":"Food & Beverages",
            "subcategory":"Groceries & Convenience Stores",
            "type":"Retail Goods"
        }
    ],
    "sg:phone":"+1 514 366 7413",
    "sg:postcode":"H8N 1T6",
    "sg:province":"QC",
    "wof:name":"Couche-Tard",
    "wof:placetype":"venue"
},
  "geometry": {"coordinates":[-73.62994384770001,45.4280357361],"type":"Point"}
}