{
  "type": "Feature",
  "properties": {
    "addr:full":"704 Wilson Ave North York ON M3K 1E1",
    "addr:housenumber":"704",
    "addr:postcode":"m3k 1e1",
    "addr:street":"Wilson Ave",
    "iso:country":"CA",
    "sg:address":"704 Wilson Ave",
    "sg:city":"North York",
    "sg:classifiers":[
        {
            "category":"Shopping",
            "subcategory":"Discount & Variety Stores",
            "type":"Retail Goods"
        }
    ],
    "sg:phone":"+1 416 638 5530",
    "sg:postcode":"M3K 1E1",
    "sg:province":"ON",
    "wof:name":"Bees Variety",
    "wof:placetype":"venue"
},
  "geometry": {"coordinates":[-79.462509,43.731747],"type":"Point"}
}