{
  "type": "Feature",
  "properties": {
    "addr:full":"160 Townsend Dr Melita MB R0M 1L0",
    "addr:housenumber":"160",
    "addr:postcode":"r0m 1l0",
    "addr:street":"Townsend Dr",
    "iso:country":"CA",
    "sg:address":"160 Townsend Dr",
    "sg:city":"Melita",
    "sg:classifiers":[
        {
            "category":"Recreation",
            "type":"Entertainment"
        }
    ],
    "sg:phone":"+1 204 522 8200",
    "sg:postcode":"R0M 1L0",
    "sg:province":"MB",
    "sg:tags":[
        "pool",
        "swimming"
    ],
    "wof:name":"Melita Swimming Pool",
    "wof:placetype":"venue"
},
  "geometry": {"coordinates":[-100.99518585200001,49.2677001953],"type":"Point"}
}