{
  "type": "Feature",
  "properties": {
    "addr:full":"Surrey BC V3T 5H6",
    "addr:postcode":"v3t 5h6",
    "iso:country":"CA",
    "sg:city":"Surrey",
    "sg:classifiers":[
        {
            "category":"Real Estate",
            "subcategory":"Real Estate Operator",
            "type":"Services"
        }
    ],
    "sg:phone":"+1 604 589 3930",
    "sg:postcode":"V3T 5H6",
    "sg:province":"BC",
    "sg:tags":[
        "apartment"
    ],
    "wof:name":"Surrey Village",
    "wof:placetype":"venue"
},
  "geometry": {"coordinates":[-122.84584,49.181149],"type":"Point"}
}