{
  "type": "Feature",
  "properties": {
    "addr:full":"11000 Ch DE LA Cote-DE-Liesse Lachine QC H8T 1A7",
    "addr:postcode":"11000;h8t 1a7",
    "addr:street":"Ch De La Cote-De-Liesse",
    "iso:country":"CA",
    "sg:address":"11000 Ch DE LA Cote-DE-Liesse",
    "sg:city":"Lachine",
    "sg:classifiers":[
        {
            "category":"Retail",
            "subcategory":"Auto Repair",
            "type":"Services"
        }
    ],
    "sg:phone":"+1 514 633 5446",
    "sg:postcode":"H8T 1A7",
    "sg:province":"QC",
    "sg:tags":[
        "repairing",
        "automobile"
    ],
    "wof:name":"Station Service Amy Inc",
    "wof:placetype":"venue"
},
  "geometry": {"coordinates":[-73.72393798829999,45.4612007141],"type":"Point"}
}