{
  "type": "Feature",
  "properties": {
    "addr:full":"1785 Boul Du Carmel Trois-Rivieres QC G8Z 3R8",
    "addr:housenumber":"1785",
    "addr:postcode":"g8z 3r8",
    "addr:street":"Boul Du Carmel Trois-Rivieres",
    "iso:country":"CA",
    "sg:address":"1785 Boul Du Carmel",
    "sg:city":"Trois-Rivieres",
    "sg:classifiers":[
        {
            "category":"Organizations",
            "subcategory":"Religious Organization",
            "type":"Services"
        }
    ],
    "sg:phone":"+1 819 374 5303",
    "sg:postcode":"G8Z 3R8",
    "sg:province":"QC",
    "wof:name":"Soeurs Carmelites",
    "wof:placetype":"venue"
},
  "geometry": {"coordinates":[-72.55851745610001,46.3516616821],"type":"Point"}
}