{
  "type": "Feature",
  "properties": {
    "addr:full":"1380 Mountain Rd Moncton NB E1C 2T8",
    "addr:housenumber":"1380",
    "addr:postcode":"e1c 2t8",
    "addr:street":"Mountain Rd",
    "iso:country":"CA",
    "sg:address":"1380 Mountain Rd",
    "sg:city":"Moncton",
    "sg:classifiers":[
        {
            "category":"Restaurant",
            "type":"Food & Drink"
        }
    ],
    "sg:phone":"+1 506 860 7777",
    "sg:postcode":"E1C 2T8",
    "sg:province":"NB",
    "wof:name":"Boston Pizza",
    "wof:placetype":"venue"
},
  "geometry": {"coordinates":[-64.8328552246,46.1110534668],"type":"Point"}
}