{
  "type": "Feature",
  "properties": {
    "addr:full":"London ON N6A 3N7",
    "addr:postcode":"n6a 3n7",
    "iso:country":"CA",
    "sg:city":"London",
    "sg:classifiers":[
        {
            "category":"Health Services",
            "subcategory":"Doctor",
            "type":"Services"
        }
    ],
    "sg:phone":"+1 519 439 2273",
    "sg:postcode":"N6A 3N7",
    "sg:province":"ON",
    "sg:tags":[
        "dentist"
    ],
    "wof:name":"Galleria Dental Ctr",
    "wof:placetype":"venue"
},
  "geometry": {"coordinates":[-81.244568,42.983196],"type":"Point"}
}