{
  "type": "Feature",
  "properties": {
    "addr:full":"North York ON M6A 3C6",
    "addr:postcode":"m6a 3c6",
    "iso:country":"CA",
    "sg:city":"North York",
    "sg:classifiers":[
        {
            "category":"Wholesale",
            "subcategory":"Furniture",
            "type":"Manufacturing & Wholesale Goods"
        }
    ],
    "sg:phone":"+1 416 787 1879",
    "sg:postcode":"M6A 3C6",
    "sg:province":"ON",
    "wof:name":"Ikor Integrated Facilities Inc",
    "wof:placetype":"venue"
},
  "geometry": {"coordinates":[-79.4521102905,43.7145576477],"type":"Point"}
}