{
  "type": "Feature",
  "properties": {
    "addr:full":"2198 Rue Thierry Lasalle QC H8N 1H7",
    "addr:housenumber":"2198",
    "addr:postcode":"h8n 1h7",
    "addr:street":"Rue Thierry",
    "iso:country":"CA",
    "sg:address":"2198 Rue Thierry",
    "sg:city":"Lasalle",
    "sg:classifiers":[
        {
            "category":"Building & Trades",
            "subcategory":"Electrical",
            "type":"Services"
        }
    ],
    "sg:phone":"+1 514 363 4274",
    "sg:postcode":"H8N 1H7",
    "sg:province":"QC",
    "sg:tags":[
        "contractor",
        "electric",
        "heating"
    ],
    "wof:name":"Bert Electrique Inc",
    "wof:placetype":"venue"
},
  "geometry": {"coordinates":[-73.6283569336,45.437664032],"type":"Point"}
}