{
  "type": "Feature",
  "properties": {
    "addr:full":"1215 117 Rte Saint-Faustin-Lac-Carre QC J0T 1J3",
    "addr:housenumber":"1215",
    "addr:postcode":"j0t 1j3",
    "addr:street":"117 Rte Saint-Faustin-Lac-Carre",
    "iso:country":"CA",
    "sg:address":"1215 117 Rte",
    "sg:city":"Saint-Faustin-Lac-Carre",
    "sg:classifiers":[
        {
            "category":"Travel",
            "subcategory":"Hotels & Motels",
            "type":"Entertainment"
        }
    ],
    "sg:phone":"+1 819 688 6226",
    "sg:postcode":"J0T 1J3",
    "sg:province":"QC",
    "wof:name":"Motel Le St Faustin",
    "wof:placetype":"venue"
},
  "geometry": {"coordinates":[-74.4815826416,46.1144943237],"type":"Point"}
}