{
  "type": "Feature",
  "properties": {
    "addr:full":"402 Albert St E Sault Ste Marie ON P6A 2J8",
    "addr:housenumber":"402",
    "addr:postcode":"p6a 2j8",
    "addr:street":"Albert St E",
    "iso:country":"CA",
    "sg:address":"402 Albert St E",
    "sg:city":"Sault Ste Marie",
    "sg:classifiers":[
        {
            "category":"Health Services",
            "subcategory":"Chiropractor",
            "type":"Services"
        }
    ],
    "sg:phone":"+1 705 946 3043",
    "sg:postcode":"P6A 2J8",
    "sg:province":"ON",
    "wof:name":"Alternative Health Care Clinic",
    "wof:placetype":"venue"
},
  "geometry": {"coordinates":[-84.33206199999999,46.512943],"type":"Point"}
}