{
  "type": "Feature",
  "properties": {
    "addr:full":"7 Wekusko Dr Snow Lake MB R0B 1M0",
    "addr:housenumber":"7",
    "addr:postcode":"r0b 1m0",
    "addr:street":"Wekusko Dr",
    "iso:country":"CA",
    "sg:address":"7 Wekusko Dr",
    "sg:city":"Snow Lake",
    "sg:classifiers":[
        {
            "category":"Organizations",
            "subcategory":"Professional Association",
            "type":"Services"
        }
    ],
    "sg:phone":"+1 204 358 2513",
    "sg:postcode":"R0B 1M0",
    "sg:province":"MB",
    "sg:tags":[
        "club"
    ],
    "wof:name":"Elks Lodge",
    "wof:placetype":"venue"
},
  "geometry": {"coordinates":[-100.015022,54.874523],"type":"Point"}
}