{
  "type": "Feature",
  "properties": {
    "addr:full":"557 Rue Charbonneau Mont-Tremblant QC J8E 3H4",
    "addr:housenumber":"557",
    "addr:postcode":"j8e 3h4",
    "addr:street":"Rue Charbonneau",
    "iso:country":"CA",
    "sg:address":"557 Rue Charbonneau",
    "sg:city":"Mont-Tremblant",
    "sg:classifiers":[
        {
            "category":"Professional",
            "subcategory":"Lawyer & Legal Services",
            "type":"Services"
        }
    ],
    "sg:phone":"+1 819 425 9838",
    "sg:postcode":"J8E 3H4",
    "sg:province":"QC",
    "sg:tags":[
        "attorney"
    ],
    "wof:name":"Dufour, Mario",
    "wof:placetype":"venue"
},
  "geometry": {"coordinates":[-74.59395599370001,46.1215896606],"type":"Point"}
}