{
  "type": "Feature",
  "properties": {
    "addr:full":"798 Boul Des Laurentides Laval QC H7G 2V9",
    "addr:housenumber":"798",
    "addr:postcode":"qc h7g 2v9",
    "addr:street":"Boul Des Laurentides",
    "iso:country":"CA",
    "sg:address":"798 Boul Des Laurentides",
    "sg:city":"Laval",
    "sg:classifiers":[
        {
            "category":"Personal",
            "subcategory":"Beauty Salon",
            "type":"Services"
        }
    ],
    "sg:phone":"+1 450 967 1309",
    "sg:postcode":"H7G 2V9",
    "sg:province":"QC",
    "sg:tags":[
        "manicuring"
    ],
    "wof:name":"Centre DE Beaute Pour L'Ongle",
    "wof:placetype":"venue"
},
  "geometry": {"coordinates":[-73.695511,45.573273],"type":"Point"}
}