{
  "type": "Feature",
  "properties": {
    "addr:full":"Calgary AB T1Y 5E4",
    "addr:postcode":"t1y 5e4",
    "iso:country":"CA",
    "sg:city":"Calgary",
    "sg:classifiers":[
        {
            "category":"Professional",
            "subcategory":"Computer Services",
            "type":"Services"
        }
    ],
    "sg:phone":"+1 403 777 4357",
    "sg:postcode":"T1Y 5E4",
    "sg:province":"AB",
    "sg:tags":[
        "internet"
    ],
    "wof:name":"Calgary on-Line Inc",
    "wof:placetype":"venue"
},
  "geometry": {"coordinates":[-113.99504899999999,51.082546],"type":"Point"}
}