{
  "type": "Feature",
  "properties": {
    "addr:full":"619 3rd Ave Prince George BC V2L 3C2",
    "addr:housenumber":"619",
    "addr:postcode":"v2l 3c2",
    "addr:street":"3Rd Ave",
    "iso:country":"CA",
    "sg:address":"619 3rd Ave",
    "sg:city":"Prince George",
    "sg:classifiers":[
        {
            "category":"Retail",
            "subcategory":"Auto Repair",
            "type":"Services"
        }
    ],
    "sg:phone":"+1 250 562 3533",
    "sg:postcode":"V2L 3C2",
    "sg:province":"BC",
    "sg:tags":[
        "repairing",
        "automobile"
    ],
    "wof:name":"Danroth Automotive",
    "wof:placetype":"venue"
},
  "geometry": {"coordinates":[-122.73535200000001,53.91383],"type":"Point"}
}