{
  "type": "Feature",
  "properties": {
    "iso:country":"CA",
    "sg:address":"619 3rd Ave",
    "sg:city":"Prince George",
    "sg:classifiers":[
        {
            "category":"Retail",
            "subcategory":"Auto Repair",
            "type":"Services"
        }
    ],
    "sg:phone":"+1 250 562 3533",
    "sg:postcode":"V2L 3C2",
    "sg:province":"BC",
    "sg:tags":[
        "repairing",
        "automobile"
    ],
    "wof:name":"Danroth Automotive",
    "wof:placetype":"venue"
},
  "geometry": {"coordinates":[-122.735352,53.91383],"type":"Point"}
}