{
  "type": "Feature",
  "properties": {
    "addr:full":"39 Orfus Rd North York ON M6A 1L7",
    "addr:housenumber":"39",
    "addr:postcode":"m6a 1l7",
    "addr:street":"Orfus Rd",
    "iso:country":"CA",
    "sg:address":"39 Orfus Rd",
    "sg:city":"North York",
    "sg:classifiers":[
        {
            "category":"Personal",
            "subcategory":"Beauty Salon",
            "type":"Services"
        }
    ],
    "sg:phone":"+1 416 785 9754",
    "sg:postcode":"M6A 1L7",
    "sg:province":"ON",
    "wof:name":"Gwen's Perm World",
    "wof:placetype":"venue"
},
  "geometry": {"coordinates":[-79.459518,43.719547],"type":"Point"}
}