{
  "type": "Feature",
  "properties": {
    "iso:country":"CA",
    "sg:city":"Coquitlam",
    "sg:classifiers":[
        {
            "category":"Retail",
            "subcategory":"Repair Shop",
            "type":"Services"
        }
    ],
    "sg:phone":"+1 604 936 9960",
    "sg:postcode":"V3J 1S9",
    "sg:province":"BC",
    "sg:tags":[
        "television",
        "radio"
    ],
    "wof:name":"A & G Electronics",
    "wof:placetype":"venue"
},
  "geometry": {"coordinates":[-122.859901428,49.24949646],"type":"Point"}
}