{
  "type": "Feature",
  "properties": {
    "addr:full":"101 Watts Ave Charlottetown PE C1E 2B7",
    "addr:housenumber":"101",
    "addr:postcode":"c1e 2b7",
    "addr:street":"Watts Ave",
    "iso:country":"CA",
    "sg:address":"101 Watts Ave",
    "sg:city":"Charlottetown",
    "sg:classifiers":[
        {
            "category":"Manufacturing",
            "subcategory":"Printing",
            "type":"Manufacturing & Wholesale Goods"
        }
    ],
    "sg:phone":"+1 902 566 2626",
    "sg:postcode":"C1E 2B7",
    "sg:province":"PE",
    "sg:tags":[
        "screen"
    ],
    "wof:name":"Cows Inc",
    "wof:placetype":"venue"
},
  "geometry": {"coordinates":[-63.1721839905,46.2673416138],"type":"Point"}
}