{
  "type": "Feature",
  "properties": {
    "addr:full":"6325 Montevideo Rd Mississauga ON L5N 4G7",
    "addr:housenumber":"6325",
    "addr:postcode":"l5n 4g7",
    "addr:street":"Montevideo Rd",
    "iso:country":"CA",
    "sg:address":"6325 Montevideo Rd",
    "sg:city":"Mississauga",
    "sg:classifiers":[
        {
            "category":"Education",
            "subcategory":"School",
            "type":"Public Place"
        }
    ],
    "sg:phone":"+1 905 858 3087",
    "sg:postcode":"L5N 4G7",
    "sg:province":"ON",
    "wof:name":"West Credit Secondary School",
    "wof:placetype":"venue"
},
  "geometry": {"coordinates":[-79.747597,43.585579],"type":"Point"}
}