{
  "type": "Feature",
  "properties": {
    "iso:country":"CA",
    "sg:address":"361 Queen St S",
    "sg:city":"Mississauga",
    "sg:classifiers":[
        {
            "category":"Social Services",
            "type":"Services"
        }
    ],
    "sg:phone":"+1 905 826 5846",
    "sg:postcode":"L5M 1M3",
    "sg:province":"ON",
    "sg:tags":[
        "organization",
        "welfare"
    ],
    "wof:name":"Cheshire House",
    "wof:placetype":"venue"
},
  "geometry": {"coordinates":[-79.6013336182,43.5419845581],"type":"Point"}
}