{
  "type": "Feature",
  "properties": {
    "iso:country":"CA",
    "sg:city":"Chateauguay",
    "sg:classifiers":[
        {
            "category":"Wholesale",
            "subcategory":"Machinery & Supplies",
            "type":"Manufacturing & Wholesale Goods"
        }
    ],
    "sg:phone":"+1 450 692 5219",
    "sg:postcode":"J6J 4Z2",
    "sg:province":"QC",
    "sg:tags":[
        "engraving",
        "equipment"
    ],
    "wof:name":"Stenlagraph Inc",
    "wof:placetype":"venue"
},
  "geometry": {"coordinates":[-73.697853,45.353542],"type":"Point"}
}