{
  "type": "Feature",
  "properties": {
    "addr:full":"10817 20 Ave NW Edmonton AB T6J 5W5",
    "addr:housenumber":"10817",
    "addr:postcode":"t6j 5w5",
    "addr:street":"20 Ave Nw",
    "iso:country":"CA",
    "sg:address":"10817 20 Ave NW",
    "sg:city":"Edmonton",
    "sg:classifiers":[
        {
            "category":"Building & Trades",
            "subcategory":"Construction",
            "type":"Services"
        }
    ],
    "sg:phone":"+1 780 469 1118",
    "sg:postcode":"T6J 5W5",
    "sg:province":"AB",
    "sg:tags":[
        "plastering",
        "stucco",
        "contractor"
    ],
    "wof:name":"Mark's Plastering & Stucco",
    "wof:placetype":"venue"
},
  "geometry": {"coordinates":[-113.50709500000001,53.45071],"type":"Point"}
}