{
  "type": "Feature",
  "properties": {
    "iso:country":"CA",
    "sg:address":"10817 20 Ave NW",
    "sg:city":"Edmonton",
    "sg:classifiers":[
        {
            "category":"Building & Trades",
            "subcategory":"Construction",
            "type":"Services"
        }
    ],
    "sg:phone":"+1 780 469 1118",
    "sg:postcode":"T6J 5W5",
    "sg:province":"AB",
    "sg:tags":[
        "plastering",
        "stucco",
        "contractor"
    ],
    "wof:name":"Mark's Plastering & Stucco",
    "wof:placetype":"venue"
},
  "geometry": {"coordinates":[-113.507095,53.45071],"type":"Point"}
}