{
  "type": "Feature",
  "properties": {
    "addr:full":"152 Rue Turgeon Sainte-Therese QC J7E 3J3",
    "addr:housenumber":"152",
    "addr:postcode":"j7e 3j3",
    "addr:street":"Rue Turgeon Sainte-Therese",
    "iso:country":"CA",
    "sg:address":"152 Rue Turgeon",
    "sg:city":"Sainte-Therese",
    "sg:classifiers":[
        {
            "category":"Home & Garden",
            "subcategory":"Carpets & Floor Coverings",
            "type":"Retail Goods"
        }
    ],
    "sg:phone":"+1 450 430 7660",
    "sg:postcode":"J7E 3J3",
    "sg:province":"QC",
    "sg:tags":[
        "dealer",
        "rug"
    ],
    "wof:name":"Couvre Planchers Ste Therese",
    "wof:placetype":"venue"
},
  "geometry": {"coordinates":[-73.8343429565,45.6339912415],"type":"Point"}
}