{
  "type": "Feature",
  "properties": {
    "addr:full":"2435 Schuyler St Saskatoon SK S7M 5H4",
    "addr:housenumber":"2435",
    "addr:postcode":"s7m 5h4",
    "addr:street":"Schuyler St",
    "iso:country":"CA",
    "sg:address":"2435 Schuyler St",
    "sg:city":"Saskatoon",
    "sg:classifiers":[
        {
            "category":"Wholesale",
            "subcategory":"Farm Supplies",
            "type":"Manufacturing & Wholesale Goods"
        }
    ],
    "sg:phone":"+1 306 384 2144",
    "sg:postcode":"S7M 5H4",
    "sg:province":"SK",
    "sg:tags":[
        "feed"
    ],
    "wof:name":"Feed-Rite Ltd",
    "wof:placetype":"venue"
},
  "geometry": {"coordinates":[-106.707748,52.111492],"type":"Point"}
}