{
  "type": "Feature",
  "properties": {
    "addr:full":"5401 Boul Des Galeries Quebec QC G2K 1N4",
    "addr:housenumber":"5401",
    "addr:postcode":"g2k 1n4",
    "addr:street":"Boul Des Galeries",
    "iso:country":"CA",
    "sg:address":"5401 Boul Des Galeries",
    "sg:city":"Quebec",
    "sg:classifiers":[
        {
            "category":"Shopping",
            "subcategory":"Gifts & Souvenirs",
            "type":"Retail Goods"
        }
    ],
    "sg:phone":"+1 418 628 8760",
    "sg:postcode":"G2K 1N4",
    "sg:province":"QC",
    "sg:tags":[
        "party",
        "supply",
        "drapery",
        "curtain"
    ],
    "wof:name":"Bou Clair Inc",
    "wof:placetype":"venue"
},
  "geometry": {"coordinates":[-71.2956771851,46.831237793],"type":"Point"}
}