{
  "type": "Feature",
  "properties": {
    "iso:country":"CA",
    "sg:address":"272 Industrial Ave E",
    "sg:city":"Penticton",
    "sg:classifiers":[
        {
            "category":"Retail",
            "subcategory":"Auto Repair",
            "type":"Services"
        }
    ],
    "sg:phone":"+1 250 492 9612",
    "sg:postcode":"V2A 3H8",
    "sg:province":"BC",
    "sg:tags":[
        "body",
        "automobile",
        "painting"
    ],
    "wof:name":"Ellis Creek Auto Body",
    "wof:placetype":"venue"
},
  "geometry": {"coordinates":[-119.57965850799999,49.4803733826],"type":"Point"}
}