{
  "type": "Feature",
  "properties": {
    "addr:full":"108 Rue Principale Saint-Gervais QC G0R 3C0",
    "addr:housenumber":"108",
    "addr:postcode":"g0r 3c0",
    "addr:street":"Rue Principale",
    "iso:country":"CA",
    "sg:address":"108 Rue Principale",
    "sg:city":"Saint-Gervais",
    "sg:classifiers":[
        {
            "category":"Wholesale",
            "subcategory":"Farm Supplies",
            "type":"Manufacturing & Wholesale Goods"
        }
    ],
    "sg:phone":"+1 418 887 3327",
    "sg:postcode":"G0R 3C0",
    "sg:province":"QC",
    "sg:tags":[
        "tractor"
    ],
    "wof:name":"Francois Goulet & Fils Inc",
    "wof:placetype":"venue"
},
  "geometry": {"coordinates":[-70.8967285156,46.7201118469],"type":"Point"}
}