{
  "type": "Feature",
  "properties": {
    "addr:full":"101 Rue Principale St-Sauveur-Des-Monts QC J0R 1R6",
    "addr:housenumber":"101",
    "addr:postcode":"j0r 1r6",
    "addr:street":"Rue Principale",
    "iso:country":"CA",
    "sg:address":"101 Rue Principale",
    "sg:city":"St-Sauveur-Des-Monts",
    "sg:classifiers":[
        {
            "category":"Health Services",
            "subcategory":"Nursing And Care Facility",
            "type":"Services"
        }
    ],
    "sg:phone":"+1 450 240 0040",
    "sg:postcode":"J0R 1R6",
    "sg:province":"QC",
    "sg:tags":[
        "home",
        "retirement",
        "community"
    ],
    "wof:name":"Gestion Des Manoirs Lp",
    "wof:placetype":"venue"
},
  "geometry": {"coordinates":[-74.149834,45.89835],"type":"Point"}
}