{
  "type": "Feature",
  "properties": {
    "addr:full":"Fort St John BC V1J 1Y8",
    "addr:postcode":"v1j 1y8",
    "iso:country":"CA",
    "sg:city":"Fort St John",
    "sg:classifiers":[
        {
            "category":"Organizations",
            "subcategory":"Community Association",
            "type":"Services"
        }
    ],
    "sg:phone":"+1 250 785 4900",
    "sg:postcode":"V1J 1Y8",
    "sg:province":"BC",
    "sg:tags":[
        "native"
    ],
    "wof:name":"Fort St John Native Housing",
    "wof:placetype":"venue"
},
  "geometry": {"coordinates":[-120.853172302,56.246219635],"type":"Point"}
}