{
  "type": "Feature",
  "properties": {
    "addr:full":"585 Montreal Rd Ottawa ON K1K 4K3",
    "addr:housenumber":"585",
    "addr:postcode":"k1k 4k3",
    "addr:street":"Montreal Rd",
    "iso:country":"CA",
    "sg:address":"585 Montreal Rd",
    "sg:city":"Ottawa",
    "sg:classifiers":[
        {
            "category":"Food & Beverages",
            "subcategory":"Groceries & Convenience Stores",
            "type":"Retail Goods"
        }
    ],
    "sg:phone":"+1 613 744 3463",
    "sg:postcode":"K1K 4K3",
    "sg:province":"ON",
    "sg:tags":[
        "grocer"
    ],
    "wof:name":"Farm Boy Fresh Market",
    "wof:placetype":"venue"
},
  "geometry": {"coordinates":[-75.64360000000001,45.442303],"type":"Point"}
}