{
  "type": "Feature",
  "properties": {
    "iso:country":"CA",
    "sg:address":"570 King St",
    "sg:city":"Welland",
    "sg:classifiers":[
        {
            "category":"Shopping",
            "subcategory":"Pharmacy",
            "type":"Retail Goods"
        }
    ],
    "sg:phone":"+1 905 714 9009",
    "sg:postcode":"L3B 3L2",
    "sg:province":"ON",
    "wof:name":"Welland Medical Pharmacy",
    "wof:placetype":"venue"
},
  "geometry": {"coordinates":[-79.2511138916,42.97838974],"type":"Point"}
}