{
  "type": "Feature",
  "properties": {
    "iso:country":"CA",
    "sg:city":"Guelph",
    "sg:classifiers":[
        {
            "category":"Retail",
            "subcategory":"Laundry & Dry Cleaning",
            "type":"Services"
        }
    ],
    "sg:phone":"+1 519 766 9682",
    "sg:postcode":"N1H 7G5",
    "sg:province":"ON",
    "sg:tags":[
        "cleaners"
    ],
    "wof:name":"K Cleaners",
    "wof:placetype":"venue"
},
  "geometry": {"coordinates":[-80.269173,43.558994],"type":"Point"}
}