{
  "type": "Feature",
  "properties": {
    "addr:full":"Camperville MB R0L 0J0",
    "addr:postcode":"r0l 0j0",
    "iso:country":"CA",
    "sg:city":"Camperville",
    "sg:classifiers":[
        {
            "category":"Building & Trades",
            "subcategory":"Construction",
            "type":"Services"
        }
    ],
    "sg:phone":"+1 204 524 2600",
    "sg:postcode":"R0L 0J0",
    "sg:province":"MB",
    "sg:tags":[
        "home",
        "builder"
    ],
    "wof:name":"Richard Construction",
    "wof:placetype":"venue"
},
  "geometry": {"coordinates":[-100.145202637,51.9859199524],"type":"Point"}
}