{
  "type": "Feature",
  "properties": {
    "iso:country":"CA",
    "sg:address":"220 Helmsdale Ave",
    "sg:city":"Winnipeg",
    "sg:classifiers":[
        {
            "category":"Organizations",
            "subcategory":"Religious Organization",
            "type":"Services"
        }
    ],
    "sg:phone":"+1 204 661 2432",
    "sg:postcode":"R2K 0V9",
    "sg:province":"MB",
    "sg:tags":[
        "church"
    ],
    "wof:name":"St Stephen's Anglican Church",
    "wof:placetype":"venue"
},
  "geometry": {"coordinates":[-97.102081,49.927895],"type":"Point"}
}