{
  "type": "Feature",
  "properties": {
    "addr:full":"232 Rue Saint-Charles Sainte-Therese QC J7E 2B4",
    "addr:housenumber":"232",
    "addr:postcode":"j7e 2b4",
    "addr:street":"Rue Saint-Charles",
    "iso:country":"CA",
    "sg:address":"232 Rue Saint-Charles",
    "sg:city":"Sainte-Therese",
    "sg:classifiers":[
        {
            "category":"Restaurant",
            "type":"Food & Drink"
        }
    ],
    "sg:phone":"+1 450 433 8966",
    "sg:postcode":"J7E 2B4",
    "sg:province":"QC",
    "wof:name":"Subway Sandwiches & Salads",
    "wof:placetype":"venue"
},
  "geometry": {"coordinates":[-73.861008,45.644333],"type":"Point"}
}