{
  "type": "Feature",
  "properties": {
    "addr:full":"223 Rue Doyon Saint-Victor QC G0M 2B0",
    "addr:housenumber":"223",
    "addr:postcode":"g0m 2b0",
    "addr:street":"Rue Doyon",
    "iso:country":"CA",
    "sg:address":"223 Rue Doyon",
    "sg:city":"Saint-Victor",
    "sg:classifiers":[
        {
            "category":"Building & Trades",
            "subcategory":"Construction",
            "type":"Services"
        }
    ],
    "sg:phone":"+1 418 588 6792",
    "sg:postcode":"G0M 2B0",
    "sg:province":"QC",
    "sg:tags":[
        "masonry",
        "contractor"
    ],
    "wof:name":"Maconnerie Gerard Fortin",
    "wof:placetype":"venue"
},
  "geometry": {"coordinates":[-70.9039154053,46.1398200989],"type":"Point"}
}