{
  "type": "Feature",
  "properties": {
    "addr:full":"Toronto ON M4V 3A9",
    "addr:postcode":"m4v 3a9",
    "iso:country":"CA",
    "sg:city":"Toronto",
    "sg:classifiers":[
        {
            "category":"Professional",
            "subcategory":"Advertising",
            "type":"Services"
        }
    ],
    "sg:phone":"+1 416 967 4660",
    "sg:postcode":"M4V 3A9",
    "sg:province":"ON",
    "sg:tags":[
        "counselor"
    ],
    "wof:name":"Seppi Marketing Comms Inc",
    "wof:placetype":"venue"
},
  "geometry": {"coordinates":[-79.3924255371,43.6821212769],"type":"Point"}
}