{
  "type": "Feature",
  "properties": {
    "addr:full":"9800 Boul Henri-Bourassa O Saint-Laurent QC H4S 1R5",
    "addr:housenumber":"9800",
    "addr:postcode":"h4s 1r5",
    "addr:street":"Boul Henri-Bourassa O",
    "iso:country":"CA",
    "sg:address":"9800 Boul Henri-Bourassa O",
    "sg:city":"Saint-Laurent",
    "sg:classifiers":[
        {
            "category":"Retail",
            "subcategory":"Auto Repair",
            "type":"Services"
        }
    ],
    "sg:phone":"+1 514 336 2045",
    "sg:postcode":"H4S 1R5",
    "sg:province":"QC",
    "sg:tags":[
        "repairing",
        "automobile"
    ],
    "wof:name":"Sam's Diesel Svc Ctr",
    "wof:placetype":"venue"
},
  "geometry": {"coordinates":[-73.75310500000001,45.495991],"type":"Point"}
}