{
  "type": "Feature",
  "properties": {
    "addr:full":"79 Villa St Drumheller AB T0J 0Y1",
    "addr:housenumber":"79",
    "addr:postcode":"t0j 0y1",
    "addr:street":"Villa St",
    "iso:country":"CA",
    "sg:address":"79 Villa St",
    "sg:city":"Drumheller",
    "sg:classifiers":[
        {
            "category":"Building & Trades",
            "subcategory":"Plumbing",
            "type":"Services"
        }
    ],
    "sg:phone":"+1 403 823 4822",
    "sg:postcode":"T0J 0Y1",
    "sg:province":"AB",
    "sg:tags":[
        "contractor"
    ],
    "wof:name":"Thom Mechanical Plumbing",
    "wof:placetype":"venue"
},
  "geometry": {"coordinates":[-112.715675354,51.4710121155],"type":"Point"}
}