{
  "type": "Feature",
  "properties": {
    "addr:full":"Happy Valley-Goose Bay NL A0P 1E0",
    "addr:postcode":"a0p 1e0",
    "iso:country":"CA",
    "sg:city":"Happy Valley-Goose Bay",
    "sg:classifiers":[
        {
            "category":"Shopping",
            "subcategory":"Bicycles & Sporting Goods",
            "type":"Retail Goods"
        }
    ],
    "sg:phone":"+1 709 896 5822",
    "sg:postcode":"A0P 1E0",
    "sg:province":"NL",
    "sg:tags":[
        "equipment",
        "outdoor",
        "outboard",
        "motor",
        "accessory"
    ],
    "wof:name":"Goose Bay Sports Ltd",
    "wof:placetype":"venue"
},
  "geometry": {"coordinates":[-60.374298,53.306454],"type":"Point"}
}