{
  "type": "Feature",
  "properties": {
    "addr:full":"2384 Hazen Rd Langton ON N0E 1G0",
    "addr:housenumber":"2384",
    "addr:postcode":"n0e 1g0",
    "addr:street":"Hazen Rd",
    "iso:country":"CA",
    "sg:address":"2384 Hazen Rd",
    "sg:city":"Langton",
    "sg:classifiers":[
        {
            "category":"Farming",
            "subcategory":"Nursery",
            "type":"Manufacturing & Wholesale Goods"
        }
    ],
    "sg:phone":"+1 519 875 4681",
    "sg:postcode":"N0E 1G0",
    "sg:province":"ON",
    "sg:tags":[
        "greenhouse"
    ],
    "wof:name":"Norfolk Greenhouses Inc",
    "wof:placetype":"venue"
},
  "geometry": {"coordinates":[-80.61685199999999,42.758602],"type":"Point"}
}