{
  "type": "Feature",
  "properties": {
    "addr:full":"4061 Butters Rd Scotch Creek BC V0E 3L0",
    "addr:housenumber":"4061",
    "addr:postcode":"bc v0e 3l0",
    "addr:street":"Butters Rd Scotch",
    "iso:country":"CA",
    "sg:address":"4061 Butters Rd",
    "sg:city":"Scotch Creek",
    "sg:classifiers":[
        {
            "category":"Manufacturing",
            "subcategory":"Food",
            "type":"Manufacturing & Wholesale Goods"
        }
    ],
    "sg:phone":"+1 250 955 2260",
    "sg:postcode":"V0E 3L0",
    "sg:province":"BC",
    "sg:tags":[
        "cocoa",
        "chocolate"
    ],
    "wof:name":"Ross Chocolates",
    "wof:placetype":"venue"
},
  "geometry": {"coordinates":[-119.44029235799999,50.9144935608],"type":"Point"}
}