{
  "type": "Feature",
  "properties": {
    "iso:country":"CA",
    "sg:city":"Vancouver",
    "sg:classifiers":[
        {
            "category":"Professional",
            "subcategory":"Accounting & Tax Preparation",
            "type":"Services"
        }
    ],
    "sg:phone":"+1 604 681 5922",
    "sg:postcode":"V6B 1T3",
    "sg:province":"BC",
    "sg:tags":[
        "accountant",
        "bookkeeping",
        "general"
    ],
    "wof:name":"Clearpoint Consulting Corp",
    "wof:placetype":"venue"
},
  "geometry": {"coordinates":[-123.110962,49.282333],"type":"Point"}
}