{
  "type": "Feature",
  "properties": {
    "addr:full":"Wiarton ON N0H 2T0",
    "addr:postcode":"n0h 2t0",
    "iso:country":"CA",
    "sg:city":"Wiarton",
    "sg:classifiers":[
        {
            "category":"Shopping",
            "subcategory":"Used Merchandise",
            "type":"Retail Goods"
        }
    ],
    "sg:phone":"+1 519 534 4460",
    "sg:postcode":"N0H 2T0",
    "sg:province":"ON",
    "sg:tags":[
        "antique"
    ],
    "wof:name":"Joanne's Back To Basics",
    "wof:placetype":"venue"
},
  "geometry": {"coordinates":[-81.1397857666,44.7401351929],"type":"Point"}
}