{
  "type": "Feature",
  "properties": {
    "iso:country":"CA",
    "sg:city":"Scarborough",
    "sg:classifiers":[
        {
            "category":"Shopping",
            "subcategory":"Clothing, Apparel, & Fashions",
            "type":"Retail Goods"
        }
    ],
    "sg:phone":"+1 416 292 0803",
    "sg:postcode":"M1S 4J5",
    "sg:province":"ON",
    "wof:name":"Ideal Fashion",
    "wof:placetype":"venue"
},
  "geometry": {"coordinates":[-79.2436904907,43.7979698181],"type":"Point"}
}