{
  "type": "Feature",
  "properties": {
    "addr:full":"135 Ormond St Brockville ON K6V 5Y2",
    "addr:housenumber":"135",
    "addr:postcode":"k6v 5y2",
    "addr:street":"Ormond St",
    "iso:country":"CA",
    "sg:address":"135 Ormond St",
    "sg:city":"Brockville",
    "sg:classifiers":[
        {
            "category":"Health Services",
            "subcategory":"Doctor",
            "type":"Services"
        }
    ],
    "sg:phone":"+1 613 342 5520",
    "sg:postcode":"K6V 5Y2",
    "sg:province":"ON",
    "sg:tags":[
        "physician",
        "surgeon"
    ],
    "wof:name":"Robertson, K D MD",
    "wof:placetype":"venue"
},
  "geometry": {"coordinates":[-75.68329620359999,44.597530365],"type":"Point"}
}