{
  "type": "Feature",
  "properties": {
    "addr:full":"3736 4th Line Ohsweken ON N0A 1M0",
    "addr:housenumber":"3736",
    "addr:postcode":"n0a 1m0",
    "addr:street":"4Th Line",
    "iso:country":"CA",
    "sg:address":"3736 4th Line",
    "sg:city":"Ohsweken",
    "sg:classifiers":[
        {
            "category":"Food & Beverages",
            "subcategory":"Specialty",
            "type":"Retail Goods"
        }
    ],
    "sg:phone":"+1 519 445 0392",
    "sg:postcode":"N0A 1M0",
    "sg:province":"ON",
    "sg:tags":[
        "water",
        "bulk",
        "company"
    ],
    "wof:name":"C & S Water Systems",
    "wof:placetype":"venue"
},
  "geometry": {"coordinates":[-80.090958,43.058739],"type":"Point"}
}