{
  "type": "Feature",
  "properties": {
    "addr:full":"85 Chimney Hill Dr Cambridge ON N1T 1H2",
    "addr:housenumber":"85",
    "addr:postcode":"n1t 1h2",
    "addr:street":"Chimney Hill Dr",
    "iso:country":"CA",
    "sg:address":"85 Chimney Hill Dr",
    "sg:city":"Cambridge",
    "sg:classifiers":[
        {
            "category":"Building & Trades",
            "subcategory":"Plumbing",
            "type":"Services"
        }
    ],
    "sg:phone":"+1 519 622 2764",
    "sg:postcode":"N1T 1H2",
    "sg:province":"ON",
    "sg:tags":[
        "heating",
        "contractor"
    ],
    "wof:name":"J C's Mechanical Systems",
    "wof:placetype":"venue"
},
  "geometry": {"coordinates":[-80.28656768800001,43.3832969666],"type":"Point"}
}