{
  "type": "Feature",
  "properties": {
    "addr:full":"625 Finch Ave W North York ON M2R 3W1",
    "addr:housenumber":"625",
    "addr:postcode":"m2r 3w1",
    "addr:street":"Finch Ave W",
    "iso:country":"CA",
    "sg:address":"625 Finch Ave W",
    "sg:city":"North York",
    "sg:classifiers":[
        {
            "category":"Shopping",
            "subcategory":"Discount & Variety Stores",
            "type":"Retail Goods"
        }
    ],
    "sg:phone":"+1 416 636 2680",
    "sg:postcode":"M2R 3W1",
    "sg:province":"ON",
    "wof:name":"Rich Sales",
    "wof:placetype":"venue"
},
  "geometry": {"coordinates":[-79.4525299072,43.7718467712],"type":"Point"}
}