{
  "type": "Feature",
  "properties": {
    "addr:full":"277 Evergreen Rd Campbell River BC V9W 5Y4",
    "addr:housenumber":"277",
    "addr:postcode":"v9w 5y4",
    "addr:street":"Evergreen Rd",
    "iso:country":"CA",
    "sg:address":"277 Evergreen Rd",
    "sg:city":"Campbell River",
    "sg:classifiers":[
        {
            "category":"Shopping",
            "subcategory":"Pharmacy",
            "type":"Retail Goods"
        }
    ],
    "sg:phone":"+1 250 287 3222",
    "sg:postcode":"V9W 5Y4",
    "sg:province":"BC",
    "wof:name":"Evergreen Pharmacy",
    "wof:placetype":"venue"
},
  "geometry": {"coordinates":[-125.241142,50.007301],"type":"Point"}
}