{
  "type": "Feature",
  "properties": {
    "addr:full":"105 Villa St Thunder Bay ON P7A 7W5",
    "addr:housenumber":"105",
    "addr:postcode":"p7a 7w5",
    "addr:street":"Villa St",
    "iso:country":"CA",
    "sg:address":"105 Villa St",
    "sg:city":"Thunder Bay",
    "sg:classifiers":[
        {
            "category":"Professional",
            "subcategory":"Management & Consulting",
            "type":"Services"
        }
    ],
    "sg:phone":"+1 807 344 4848",
    "sg:postcode":"P7A 7W5",
    "sg:province":"ON",
    "sg:tags":[
        "personnel",
        "consultant"
    ],
    "wof:name":"Mc Queen & Assoc Personnel",
    "wof:placetype":"venue"
},
  "geometry": {"coordinates":[-89.2151641846,48.4375228882],"type":"Point"}
}