{
  "type": "Feature",
  "properties": {
    "addr:full":"3075 Manning Rd Maidstone ON N0R 1K0",
    "addr:housenumber":"3075",
    "addr:postcode":"n0r 1k0",
    "addr:street":"Manning Rd",
    "iso:country":"CA",
    "sg:address":"3075 Manning Rd",
    "sg:city":"Maidstone",
    "sg:classifiers":[
        {
            "category":"Food & Beverages",
            "subcategory":"Bakery",
            "type":"Retail Goods"
        }
    ],
    "sg:phone":"+1 519 979 4129",
    "sg:postcode":"N0R 1K0",
    "sg:province":"ON",
    "sg:tags":[
        "tea",
        "coffee",
        "doughnut"
    ],
    "wof:name":"Tim Hortons",
    "wof:placetype":"venue"
},
  "geometry": {"coordinates":[-82.87481699999999,42.21941],"type":"Point"}
}