{
  "type": "Feature",
  "properties": {
    "iso:country":"CA",
    "sg:address":"156 Rue Principale",
    "sg:city":"Girardville",
    "sg:classifiers":[
        {
            "category":"Home & Garden",
            "subcategory":"Hardware",
            "type":"Retail Goods"
        }
    ],
    "sg:phone":"+1 418 258 3322",
    "sg:postcode":"G0W 1R0",
    "sg:province":"QC",
    "sg:tags":[
        "sporting"
    ],
    "wof:name":"Quincaillerie Perreault-Freres",
    "wof:placetype":"venue"
},
  "geometry": {"coordinates":[-72.5478363037,49.0035095215],"type":"Point"}
}