{
  "type": "Feature",
  "properties": {
    "addr:full":"Vanderhoof BC V0J 3A0",
    "addr:postcode":"v0j 3a0",
    "iso:country":"CA",
    "sg:city":"Vanderhoof",
    "sg:classifiers":[
        {
            "category":"Manufacturing",
            "subcategory":"Tools & Machinery",
            "type":"Manufacturing & Wholesale Goods"
        }
    ],
    "sg:phone":"+1 250 567 2364",
    "sg:postcode":"V0J 3A0",
    "sg:province":"BC",
    "sg:tags":[
        "machine",
        "shop",
        "welding"
    ],
    "wof:name":"Vanderhoof Machine Works Ltd",
    "wof:placetype":"venue"
},
  "geometry": {"coordinates":[-124.01409099999999,54.013081],"type":"Point"}
}