{
  "type": "Feature",
  "properties": {
    "addr:full":"4008 74 Ave NW Edmonton AB T6B 2P7",
    "addr:housenumber":"4008",
    "addr:postcode":"t6b 2p7",
    "addr:street":"74 Ave Nw",
    "iso:country":"CA",
    "sg:address":"4008 74 Ave NW",
    "sg:city":"Edmonton",
    "sg:classifiers":[
        {
            "category":"Manufacturing",
            "subcategory":"Metals",
            "type":"Manufacturing & Wholesale Goods"
        }
    ],
    "sg:phone":"+1 780 466 7766",
    "sg:postcode":"T6B 2P7",
    "sg:province":"AB",
    "sg:tags":[
        "steel"
    ],
    "wof:name":"Imperial Steel Fabricating Ltd",
    "wof:placetype":"venue"
},
  "geometry": {"coordinates":[-113.40325900000001,53.510479],"type":"Point"}
}