{
  "type": "Feature",
  "properties": {
    "addr:full":"North York ON M3J 3J6",
    "addr:postcode":"m3j 3j6",
    "iso:country":"CA",
    "sg:city":"North York",
    "sg:classifiers":[
        {
            "category":"Food & Beverages",
            "subcategory":"Bakery",
            "type":"Retail Goods"
        }
    ],
    "sg:phone":"+1 416 398 4533",
    "sg:postcode":"M3J 3J6",
    "sg:province":"ON",
    "sg:tags":[
        "baker"
    ],
    "wof:name":"Napolean Bakery",
    "wof:placetype":"venue"
},
  "geometry": {"coordinates":[-79.476654,43.766819],"type":"Point"}
}