{
  "type": "Feature",
  "properties": {
    "addr:full":"1842 117 Rte Mont-Tremblant QC J8E 2Y2",
    "addr:housenumber":"1842",
    "addr:postcode":"j8e 2y2",
    "addr:street":"117 Rte",
    "iso:country":"CA",
    "sg:address":"1842 117 Rte",
    "sg:city":"Mont-Tremblant",
    "sg:classifiers":[
        {
            "category":"Restaurant",
            "type":"Food & Drink"
        }
    ],
    "sg:phone":"+1 819 425 7113",
    "sg:postcode":"J8E 2Y2",
    "sg:province":"QC",
    "wof:name":"Table Enchantee",
    "wof:placetype":"venue"
},
  "geometry": {"coordinates":[-74.601685,46.11834],"type":"Point"}
}