{
  "type": "Feature",
  "properties": {
    "addr:full":"Toronto ON M5B 2H4",
    "addr:postcode":"m5b 2h4",
    "iso:country":"CA",
    "sg:city":"Toronto",
    "sg:classifiers":[
        {
            "category":"Home & Garden",
            "subcategory":"Furniture",
            "type":"Retail Goods"
        }
    ],
    "sg:phone":"+1 416 598 2184",
    "sg:postcode":"M5B 2H4",
    "sg:province":"ON",
    "sg:tags":[
        "bedding"
    ],
    "wof:name":"Down Under Linen & Bedding Ctr",
    "wof:placetype":"venue"
},
  "geometry": {"coordinates":[-79.383102417,43.6610298157],"type":"Point"}
}