{
  "type": "Feature",
  "properties": {
    "addr:full":"434 Rue Saint-Zotique E Montreal QC H2S 1L9",
    "addr:housenumber":"434",
    "addr:postcode":"h2s 1l9",
    "addr:street":"Rue Saint-Zotique E",
    "iso:country":"CA",
    "sg:address":"434 Rue Saint-Zotique E",
    "sg:city":"Montreal",
    "sg:classifiers":[
        {
            "category":"Professional",
            "subcategory":"Accounting & Tax Preparation",
            "type":"Services"
        }
    ],
    "sg:phone":"+1 514 279 6696",
    "sg:postcode":"H2S 1L9",
    "sg:province":"QC",
    "sg:tags":[
        "return",
        "filing"
    ],
    "wof:name":"Exa-Taxe Enrg",
    "wof:placetype":"venue"
},
  "geometry": {"coordinates":[-73.608017,45.535782],"type":"Point"}
}