{
  "type": "Feature",
  "properties": {
    "addr:full":"51 Cedar St Woodstock ON N4S 3P6",
    "addr:housenumber":"51",
    "addr:postcode":"n4s 3p6",
    "addr:street":"Cedar St",
    "iso:country":"CA",
    "sg:address":"51 Cedar St",
    "sg:city":"Woodstock",
    "sg:classifiers":[
        {
            "category":"Autos & Motor Vehicles",
            "subcategory":"Auto Supplies",
            "type":"Retail Goods"
        }
    ],
    "sg:phone":"+1 519 537 3421",
    "sg:postcode":"N4S 3P6",
    "sg:province":"ON",
    "sg:tags":[
        "automobile",
        "parts"
    ],
    "wof:name":"Auto Parts Plus",
    "wof:placetype":"venue"
},
  "geometry": {"coordinates":[-80.74321,43.125954],"type":"Point"}
}