{
  "type": "Feature",
  "properties": {
    "iso:country":"CA",
    "sg:address":"1703 Dublin Ave",
    "sg:city":"Winnipeg",
    "sg:classifiers":[
        {
            "category":"Manufacturing",
            "subcategory":"Tools & Machinery",
            "type":"Manufacturing & Wholesale Goods"
        }
    ],
    "sg:phone":"+1 204 237 4162",
    "sg:postcode":"R3H 0H2",
    "sg:province":"MB",
    "sg:tags":[
        "machine",
        "duplicating",
        "copying"
    ],
    "wof:name":"Laser Office Products",
    "wof:placetype":"venue"
},
  "geometry": {"coordinates":[-97.2041854858,49.9117965698],"type":"Point"}
}