{
  "type": "Feature",
  "properties": {
    "iso:country":"CA",
    "sg:address":"1930 Rue Principale",
    "sg:city":"Pohenegamook",
    "sg:classifiers":[
        {
            "category":"Food & Beverages",
            "subcategory":"Groceries & Convenience Stores",
            "type":"Retail Goods"
        }
    ],
    "sg:phone":"+1 418 859 2091",
    "sg:postcode":"G0L 1J0",
    "sg:province":"QC",
    "sg:tags":[
        "grocer"
    ],
    "wof:name":"Carl Belanger Epicerie Inc",
    "wof:placetype":"venue"
},
  "geometry": {"coordinates":[-69.2834396362,47.4888534546],"type":"Point"}
}