{
  "type": "Feature",
  "properties": {
    "addr:full":"430 DE L'Eglise Saint-Etienne-DE-Beauharnois QC J0S 1S0",
    "addr:housenumber":"430",
    "addr:postcode":"j0s 1s0",
    "addr:street":"De L'Eglise Saint-Etienne-De-Beauharnois",
    "iso:country":"CA",
    "sg:address":"430 DE L'Eglise",
    "sg:city":"Saint-Etienne-DE-Beauharnois",
    "sg:classifiers":[
        {
            "category":"Recreation",
            "type":"Entertainment"
        }
    ],
    "sg:phone":"+1 450 429 6384",
    "sg:postcode":"J0S 1S0",
    "sg:province":"QC",
    "sg:tags":[
        "government",
        "hall",
        "auditorium"
    ],
    "wof:name":"St-Etienne-Beauharnois Chalet",
    "wof:placetype":"venue"
},
  "geometry": {"coordinates":[-73.915314,45.24659],"type":"Point"}
}