{
  "type": "Feature",
  "properties": {
    "addr:full":"7000 Av Auteuil Brossard QC J4Z 3P2",
    "addr:housenumber":"7000",
    "addr:postcode":"j4z 3p2",
    "addr:street":"Av Auteuil",
    "iso:country":"CA",
    "sg:address":"7000 Av Auteuil",
    "sg:city":"Brossard",
    "sg:classifiers":[
        {
            "category":"Restaurant",
            "type":"Food & Drink"
        }
    ],
    "sg:phone":"+1 450 443 5999",
    "sg:postcode":"J4Z 3P2",
    "sg:province":"QC",
    "wof:name":"Restaurants D Lafleur Inc",
    "wof:placetype":"venue"
},
  "geometry": {"coordinates":[-73.46672058110001,45.4680557251],"type":"Point"}
}