{
  "type": "Feature",
  "properties": {
    "iso:country":"CA",
    "sg:address":"140 Haddon Rd SW",
    "sg:city":"Calgary",
    "sg:classifiers":[
        {
            "category":"Education",
            "subcategory":"School",
            "type":"Public Place"
        }
    ],
    "sg:phone":"+1 403 258 1312",
    "sg:postcode":"T2V 2Y3",
    "sg:province":"AB",
    "wof:name":"Akiva Academy",
    "wof:placetype":"venue"
},
  "geometry": {"coordinates":[-114.077789307,50.973690033],"type":"Point"}
}