{
  "type": "Feature",
  "properties": {
    "addr:full":"53 Tracey St Belleville ON K8P 2R7",
    "addr:housenumber":"53",
    "addr:postcode":"k8p 2r7",
    "addr:street":"Tracey St",
    "iso:country":"CA",
    "sg:address":"53 Tracey St",
    "sg:city":"Belleville",
    "sg:classifiers":[
        {
            "category":"Building & Trades",
            "subcategory":"Electrical",
            "type":"Services"
        }
    ],
    "sg:phone":"+1 613 962 5832",
    "sg:postcode":"K8P 2R7",
    "sg:province":"ON",
    "sg:tags":[
        "electric",
        "contractor"
    ],
    "wof:name":"D C Electric Ltd",
    "wof:placetype":"venue"
},
  "geometry": {"coordinates":[-77.40464,44.182449],"type":"Point"}
}