{
  "type": "Feature",
  "properties": {
    "addr:full":"693 St Clair Ave W Toronto ON M6C 1B2",
    "addr:housenumber":"693",
    "addr:postcode":"m6c 1b2",
    "addr:street":"St Clair Ave W",
    "iso:country":"CA",
    "sg:address":"693 St Clair Ave W",
    "sg:city":"Toronto",
    "sg:classifiers":[
        {
            "category":"Personal",
            "subcategory":"Beauty Salon",
            "type":"Services"
        }
    ],
    "sg:phone":"+1 416 654 7703",
    "sg:postcode":"M6C 1B2",
    "sg:province":"ON",
    "wof:name":"Silk Cut Hair Design",
    "wof:placetype":"venue"
},
  "geometry": {"coordinates":[-79.4260482788,43.6815681458],"type":"Point"}
}