{
  "type": "Feature",
  "properties": {
    "iso:country":"CA",
    "sg:address":"10740 Hollymount Dr",
    "sg:city":"Richmond",
    "sg:classifiers":[
        {
            "category":"Professional",
            "subcategory":"Detective & Security Services",
            "type":"Services"
        }
    ],
    "sg:phone":"+1 604 514 9686",
    "sg:postcode":"V7E 4Z2",
    "sg:province":"BC",
    "sg:tags":[
        "system"
    ],
    "wof:name":"Identitech",
    "wof:placetype":"venue"
},
  "geometry": {"coordinates":[-123.16655731199999,49.1347541809],"type":"Point"}
}