{
  "type": "Feature",
  "properties": {
    "addr:full":"1480 Danforth Ave Toronto ON M4J 1N4",
    "addr:housenumber":"1480",
    "addr:postcode":"m4j 1n4",
    "addr:street":"Danforth Ave",
    "iso:country":"CA",
    "sg:address":"1480 Danforth Ave",
    "sg:city":"Toronto",
    "sg:classifiers":[
        {
            "category":"Social Services",
            "type":"Services"
        }
    ],
    "sg:phone":"+1 416 466 7489",
    "sg:postcode":"M4J 1N4",
    "sg:province":"ON",
    "sg:tags":[
        "youth",
        "organization",
        "cafe",
        "center"
    ],
    "wof:name":"Gateway Cafe",
    "wof:placetype":"venue"
},
  "geometry": {"coordinates":[-79.3259048462,43.6829986572],"type":"Point"}
}