{
  "type": "Feature",
  "properties": {
    "addr:full":"Mississauga ON L5M 2P4",
    "addr:postcode":"l5m 2p4",
    "iso:country":"CA",
    "sg:city":"Mississauga",
    "sg:classifiers":[
        {
            "category":"Retail",
            "subcategory":"Veterinary Services",
            "type":"Services"
        }
    ],
    "sg:phone":"+1 905 567 0351",
    "sg:postcode":"L5M 2P4",
    "sg:province":"ON",
    "sg:tags":[
        "veterinarian"
    ],
    "wof:name":"Streetsville Animal Hospital",
    "wof:placetype":"venue"
},
  "geometry": {"coordinates":[-79.59796900000001,43.545517],"type":"Point"}
}