{
  "type": "Feature",
  "properties": {
    "addr:full":"Coquitlam BC V3K 6Y6",
    "addr:postcode":"v3k 6y6",
    "iso:country":"CA",
    "sg:city":"Coquitlam",
    "sg:classifiers":[
        {
            "category":"Home & Garden",
            "subcategory":"Furniture",
            "type":"Retail Goods"
        }
    ],
    "sg:phone":"+1 604 515 0888",
    "sg:postcode":"V3K 6Y6",
    "sg:province":"BC",
    "sg:tags":[
        "infant",
        "wear"
    ],
    "wof:name":"Baby's World",
    "wof:placetype":"venue"
},
  "geometry": {"coordinates":[-122.856148,49.232323],"type":"Point"}
}