{
  "type": "Feature",
  "properties": {
    "addr:full":"1987 Rue DE Champigny O Sainte-Foy QC G2G 1B1",
    "addr:housenumber":"1987",
    "addr:postcode":"g2g 1b1",
    "addr:street":"Rue De Champigny O",
    "iso:country":"CA",
    "sg:address":"1987 Rue DE Champigny O",
    "sg:city":"Sainte-Foy",
    "sg:classifiers":[
        {
            "category":"Building & Trades",
            "subcategory":"Landscaping Services",
            "type":"Services"
        }
    ],
    "sg:phone":"+1 418 872 6329",
    "sg:postcode":"G2G 1B1",
    "sg:province":"QC",
    "sg:tags":[
        "landscape",
        "contractor"
    ],
    "wof:name":"Jardin DE Dame Nature",
    "wof:placetype":"venue"
},
  "geometry": {"coordinates":[-71.378242,46.772083],"type":"Point"}
}