{
  "type": "Feature",
  "properties": {
    "addr:full":"2176 Government St Penticton BC V2A 8B5",
    "addr:housenumber":"2176",
    "addr:postcode":"v2a 8b5",
    "addr:street":"Government St",
    "iso:country":"CA",
    "sg:address":"2176 Government St",
    "sg:city":"Penticton",
    "sg:classifiers":[
        {
            "category":"Wholesale",
            "subcategory":"Metals & Minerals",
            "type":"Manufacturing & Wholesale Goods"
        }
    ],
    "sg:phone":"+1 250 492 8912",
    "sg:postcode":"V2A 8B5",
    "sg:province":"BC",
    "sg:tags":[
        "product",
        "laminated",
        "structural"
    ],
    "wof:name":"Structurlam Products Ltd",
    "wof:placetype":"venue"
},
  "geometry": {"coordinates":[-119.573807,49.475685],"type":"Point"}
}