{
  "type": "Feature",
  "properties": {
    "addr:full":"Calgary AB T3E 6V2",
    "addr:postcode":"t3e 6v2",
    "iso:country":"CA",
    "sg:city":"Calgary",
    "sg:classifiers":[
        {
            "category":"Health Services",
            "subcategory":"Health Practitioner",
            "type":"Services"
        }
    ],
    "sg:phone":"+1 403 242 1111",
    "sg:postcode":"T3E 6V2",
    "sg:province":"AB",
    "sg:tags":[
        "therapist",
        "physical"
    ],
    "wof:name":"Richmond Physiotherapy",
    "wof:placetype":"venue"
},
  "geometry": {"coordinates":[-114.16132399999999,51.021431],"type":"Point"}
}