{
  "type": "Feature",
  "properties": {
    "addr:full":"166 Parkdale Ave N Hamilton ON L8H 5X2",
    "addr:housenumber":"166",
    "addr:postcode":"l8h 5x2",
    "addr:street":"Parkdale Ave N",
    "iso:country":"CA",
    "sg:address":"166 Parkdale Ave N",
    "sg:city":"Hamilton",
    "sg:classifiers":[
        {
            "category":"Shopping",
            "subcategory":"Computers & Home Electronics",
            "type":"Retail Goods"
        }
    ],
    "sg:phone":"+1 905 547 8420",
    "sg:postcode":"L8H 5X2",
    "sg:province":"ON",
    "sg:tags":[
        "equipment",
        "electronic",
        "supply"
    ],
    "wof:name":"Nutech Electronics",
    "wof:placetype":"venue"
},
  "geometry": {"coordinates":[-79.789963,43.240837],"type":"Point"}
}