{
  "type": "Feature",
  "properties": {
    "addr:full":"35838 97th St Oliver BC V0H 1T0",
    "addr:housenumber":"35838",
    "addr:postcode":"bc v0h 1t0",
    "addr:street":"97Th St",
    "iso:country":"CA",
    "sg:address":"35838 97th St",
    "sg:city":"Oliver",
    "sg:classifiers":[
        {
            "category":"Shopping",
            "subcategory":"Florist",
            "type":"Retail Goods"
        }
    ],
    "sg:phone":"+1 250 498 4905",
    "sg:postcode":"V0H 1T0",
    "sg:province":"BC",
    "wof:name":"Tulips in Bloom Flowers-Gifts",
    "wof:placetype":"venue"
},
  "geometry": {"coordinates":[-119.550659,49.183632],"type":"Point"}
}