{
  "type": "Feature",
  "properties": {
    "iso:country":"CA",
    "sg:address":"15166 Fraser Hwy",
    "sg:city":"Surrey",
    "sg:classifiers":[
        {
            "category":"Restaurant",
            "type":"Food & Drink"
        }
    ],
    "sg:phone":"+1 604 583 0220",
    "sg:postcode":"V3R 3P1",
    "sg:province":"BC",
    "wof:name":"Kwality Sweets",
    "wof:placetype":"venue"
},
  "geometry": {"coordinates":[-122.80252075200001,49.1663742065],"type":"Point"}
}