{
  "type": "Feature",
  "properties": {
    "addr:full":"1349 Gainsborough Dr Oakville ON L6H 2H7",
    "addr:housenumber":"1349",
    "addr:postcode":"l6h 2h7",
    "addr:street":"Gainsborough Dr",
    "iso:country":"CA",
    "sg:address":"1349 Gainsborough Dr",
    "sg:city":"Oakville",
    "sg:classifiers":[
        {
            "category":"Recreation",
            "type":"Entertainment"
        }
    ],
    "sg:phone":"+1 905 844 4862",
    "sg:postcode":"L6H 2H7",
    "sg:province":"ON",
    "sg:tags":[
        "government",
        "swimming"
    ],
    "wof:name":"Falgarwood Pool",
    "wof:placetype":"venue"
},
  "geometry": {"coordinates":[-79.68538665769999,43.4779014587],"type":"Point"}
}