{
  "type": "Feature",
  "properties": {
    "addr:full":"Etobicoke ON M9W 6S2",
    "addr:postcode":"m9w 6s2",
    "iso:country":"CA",
    "sg:city":"Etobicoke",
    "sg:classifiers":[
        {
            "category":"Manufacturing",
            "subcategory":"Printing",
            "type":"Manufacturing & Wholesale Goods"
        }
    ],
    "sg:phone":"+1 416 213 0198",
    "sg:postcode":"M9W 6S2",
    "sg:province":"ON",
    "sg:tags":[
        "printer"
    ],
    "wof:name":"Formtel Printing Svc",
    "wof:placetype":"venue"
},
  "geometry": {"coordinates":[-79.617729,43.753166],"type":"Point"}
}