{
  "type": "Feature",
  "properties": {
    "iso:country":"CA",
    "sg:address":"55 Head St",
    "sg:city":"Dundas",
    "sg:classifiers":[
        {
            "category":"Freight",
            "type":"Transportation"
        }
    ],
    "sg:phone":"+1 905 628 6431",
    "sg:postcode":"L9H 3H8",
    "sg:province":"ON",
    "sg:tags":[
        "commercial",
        "storage"
    ],
    "wof:name":"Ormerod Brothers Ltd",
    "wof:placetype":"venue"
},
  "geometry": {"coordinates":[-79.9745635986,43.2679786682],"type":"Point"}
}