{
  "type": "Feature",
  "properties": {
    "addr:full":"66 Erie Ave Brantford ON N3S 2E8",
    "addr:housenumber":"66",
    "addr:postcode":"n3s 2e8",
    "addr:street":"Erie Ave",
    "iso:country":"CA",
    "sg:address":"66 Erie Ave",
    "sg:city":"Brantford",
    "sg:classifiers":[
        {
            "category":"Shopping",
            "subcategory":"Discount & Variety Stores",
            "type":"Retail Goods"
        }
    ],
    "sg:phone":"+1 519 756 3149",
    "sg:postcode":"N3S 2E8",
    "sg:province":"ON",
    "wof:name":"Sun Milk Convenience",
    "wof:placetype":"venue"
},
  "geometry": {"coordinates":[-80.259781,43.132683],"type":"Point"}
}