{
  "type": "Feature",
  "properties": {
    "addr:full":"18 Parkglen Dr Nepean ON K2G 3G9",
    "addr:housenumber":"18",
    "addr:postcode":"k2g 3g9",
    "addr:street":"Parkglen Dr",
    "iso:country":"CA",
    "sg:address":"18 Parkglen Dr",
    "sg:city":"Nepean",
    "sg:classifiers":[
        {
            "category":"Manufacturing",
            "subcategory":"Printing",
            "type":"Manufacturing & Wholesale Goods"
        }
    ],
    "sg:phone":"+1 613 224 9947",
    "sg:postcode":"K2G 3G9",
    "sg:province":"ON",
    "sg:tags":[
        "publisher"
    ],
    "wof:name":"Over the Road",
    "wof:placetype":"venue"
},
  "geometry": {"coordinates":[-75.75402800000001,45.346672],"type":"Point"}
}