{
  "type": "Feature",
  "properties": {
    "iso:country":"CA",
    "sg:address":"37 Main St N",
    "sg:city":"Markham",
    "sg:classifiers":[
        {
            "category":"Professional",
            "subcategory":"Computer Services",
            "type":"Services"
        }
    ],
    "sg:phone":"+1 905 294 6686",
    "sg:postcode":"L3P 1X4",
    "sg:province":"ON",
    "sg:tags":[
        "repair",
        "consultant"
    ],
    "wof:name":"Nerds 4 Hire",
    "wof:placetype":"venue"
},
  "geometry": {"coordinates":[-79.26001739500001,43.8753662109],"type":"Point"}
}