{
  "type": "Feature",
  "properties": {
    "addr:full":"20 Winterport Crt Richmond Hill ON L4C 9V6",
    "addr:housenumber":"20",
    "addr:postcode":"l4c 9v6",
    "addr:street":"Winterport Crt",
    "iso:country":"CA",
    "sg:address":"20 Winterport Crt",
    "sg:city":"Richmond Hill",
    "sg:classifiers":[
        {
            "category":"Building & Trades",
            "subcategory":"Construction",
            "type":"Services"
        }
    ],
    "sg:phone":"+1 905 764 3366",
    "sg:postcode":"L4C 9V6",
    "sg:province":"ON",
    "sg:tags":[
        "home",
        "improvement"
    ],
    "wof:name":"Solid Building Products CO",
    "wof:placetype":"venue"
},
  "geometry": {"coordinates":[-79.454773,43.84729],"type":"Point"}
}