{
  "type": "Feature",
  "properties": {
    "addr:full":"1047 Rue Dulcinee Havre-Saint-Pierre QC G0G 1P0",
    "addr:housenumber":"1047",
    "addr:postcode":"g0g 1p0",
    "addr:street":"Rue Dulcinee",
    "iso:country":"CA",
    "sg:address":"1047 Rue Dulcinee",
    "sg:city":"Havre-Saint-Pierre",
    "sg:classifiers":[
        {
            "category":"Professional",
            "subcategory":"Accounting & Tax Preparation",
            "type":"Services"
        }
    ],
    "sg:phone":"+1 418 538 2100",
    "sg:postcode":"G0G 1P0",
    "sg:province":"QC",
    "sg:tags":[
        "accountant",
        "management"
    ],
    "wof:name":"Groupe DE Gestion Richard",
    "wof:placetype":"venue"
},
  "geometry": {"coordinates":[-63.6038513184,50.2439880371],"type":"Point"}
}