{
  "type": "Feature",
  "properties": {
    "iso:country":"CA",
    "sg:address":"6995 Av Casgrain",
    "sg:city":"Montreal",
    "sg:classifiers":[
        {
            "category":"Restaurant",
            "type":"Food & Drink"
        }
    ],
    "sg:phone":"+1 514 274 6358",
    "sg:postcode":"H2S 2Z9",
    "sg:province":"QC",
    "sg:tags":[
        "butchering",
        "caterer"
    ],
    "wof:name":"Boucherie Joseph & Basile",
    "wof:placetype":"venue"
},
  "geometry": {"coordinates":[-73.614357,45.534733],"type":"Point"}
}