{
  "type": "Feature",
  "properties": {
    "iso:country":"CA",
    "sg:address":"192 Queen St",
    "sg:city":"Eganville",
    "sg:classifiers":[
        {
            "category":"Food & Beverages",
            "subcategory":"Groceries & Convenience Stores",
            "type":"Retail Goods"
        }
    ],
    "sg:phone":"+1 613 628 3785",
    "sg:postcode":"K0J 1T0",
    "sg:province":"ON",
    "sg:tags":[
        "grocer"
    ],
    "wof:name":"Village Discount & Variety",
    "wof:placetype":"venue"
},
  "geometry": {"coordinates":[-77.1000823975,45.5374908447],"type":"Point"}
}