{
  "type": "Feature",
  "properties": {
    "addr:full":"Belleterre QC J0Z 1L0",
    "addr:postcode":"j0z 1l0",
    "iso:country":"CA",
    "sg:city":"Belleterre",
    "sg:classifiers":[
        {
            "category":"Travel",
            "subcategory":"Campground",
            "type":"Entertainment"
        }
    ],
    "sg:phone":"+1 819 722 2424",
    "sg:postcode":"J0Z 1L0",
    "sg:province":"QC",
    "sg:tags":[
        "camp",
        "fishing"
    ],
    "wof:name":"Pourvoirie Lac LA Truite",
    "wof:placetype":"venue"
},
  "geometry": {"coordinates":[-78.69074999999999,47.380856],"type":"Point"}
}