{
  "type": "Feature",
  "properties": {
    "addr:full":"5224 50th St Mundare AB T0B 3H0",
    "addr:housenumber":"5224",
    "addr:postcode":"t0b 3h0",
    "addr:street":"50Th St",
    "iso:country":"CA",
    "sg:address":"5224 50th St",
    "sg:city":"Mundare",
    "sg:classifiers":[
        {
            "category":"Organizations",
            "subcategory":"Professional Association",
            "type":"Services"
        }
    ],
    "sg:phone":"+1 780 764 3959",
    "sg:postcode":"T0B 3H0",
    "sg:province":"AB",
    "sg:tags":[
        "club"
    ],
    "wof:name":"Mundare Senior Citizens Ctr",
    "wof:placetype":"venue"
},
  "geometry": {"coordinates":[-112.33883667000001,53.5944328308],"type":"Point"}
}