{
  "type": "Feature",
  "properties": {
    "iso:country":"CA",
    "sg:city":"Scarborough",
    "sg:classifiers":[
        {
            "category":"Shopping",
            "subcategory":"Clothing, Apparel, & Fashions",
            "type":"Retail Goods"
        }
    ],
    "sg:phone":"+1 416 299 8591",
    "sg:postcode":"M1B 4Y7",
    "sg:province":"ON",
    "sg:tags":[
        "jeweler"
    ],
    "wof:name":"Kiss",
    "wof:placetype":"venue"
},
  "geometry": {"coordinates":[-79.221336,43.805531],"type":"Point"}
}