{
  "type": "Feature",
  "properties": {
    "iso:country":"CA",
    "sg:address":"1 Rue DE L'Eglise",
    "sg:city":"Price",
    "sg:classifiers":[
        {
            "category":"Autos & Motor Vehicles",
            "subcategory":"Fuel & Gas Station",
            "type":"Retail Goods"
        }
    ],
    "sg:phone":"+1 418 775 8828",
    "sg:postcode":"G0J 1Z0",
    "sg:province":"QC",
    "sg:tags":[
        "oil"
    ],
    "wof:name":"Gaz Bar Dupont Enr",
    "wof:placetype":"venue"
},
  "geometry": {"coordinates":[-68.1248168945,48.6028518677],"type":"Point"}
}