{
  "type": "Feature",
  "properties": {
    "addr:full":"Vancouver BC V6A 4J6",
    "addr:postcode":"v6a 4j6",
    "iso:country":"CA",
    "sg:city":"Vancouver",
    "sg:classifiers":[
        {
            "category":"Wholesale",
            "subcategory":"Durable Goods & Equipment",
            "type":"Manufacturing & Wholesale Goods"
        }
    ],
    "sg:phone":"+1 604 683 3730",
    "sg:postcode":"V6A 4J6",
    "sg:province":"BC",
    "sg:tags":[
        "representative",
        "manufacturer"
    ],
    "wof:name":"Vera the Agency",
    "wof:placetype":"venue"
},
  "geometry": {"coordinates":[-123.081619,49.268921],"type":"Point"}
}