{
  "type": "Feature",
  "properties": {
    "addr:full":"10691 Shellbridge Way # 130 Richmond BC V6X 2W8",
    "addr:housenumber":"10691;130",
    "addr:postcode":"v6x 2w8",
    "addr:street":"Shellbridge Way #",
    "iso:country":"CA",
    "sg:address":"10691 Shellbridge Way # 130",
    "sg:city":"Richmond",
    "sg:classifiers":[
        {
            "category":"Wholesale",
            "subcategory":"Electrical",
            "type":"Manufacturing & Wholesale Goods"
        }
    ],
    "sg:phone":"+1 604 231 0711",
    "sg:postcode":"V6X 2W8",
    "sg:province":"BC",
    "sg:tags":[
        "instrument"
    ],
    "wof:name":"Thermo-Kinetics CO Ltd",
    "wof:placetype":"venue"
},
  "geometry": {"coordinates":[-123.10684999999999,49.187626],"type":"Point"}
}