{
  "type": "Feature",
  "properties": {
    "addr:full":"36 William St Mississauga ON L5M 1J3",
    "addr:housenumber":"36",
    "addr:postcode":"l5m 1j3",
    "addr:street":"William St",
    "iso:country":"CA",
    "sg:address":"36 William St",
    "sg:city":"Mississauga",
    "sg:classifiers":[
        {
            "category":"Retail",
            "subcategory":"Auto Repair",
            "type":"Services"
        }
    ],
    "sg:phone":"+1 905 826 2422",
    "sg:postcode":"L5M 1J3",
    "sg:province":"ON",
    "sg:tags":[
        "repairing",
        "automobile"
    ],
    "wof:name":"Johnny's Auto Ctr Inc",
    "wof:placetype":"venue"
},
  "geometry": {"coordinates":[-79.72113800050001,43.58568573],"type":"Point"}
}