{
  "type": "Feature",
  "properties": {
    "addr:full":"72 Albers Rd Lumby BC V0E 2G5",
    "addr:housenumber":"72",
    "addr:postcode":"v0e 2g5",
    "addr:street":"Albers Rd",
    "iso:country":"CA",
    "sg:address":"72 Albers Rd",
    "sg:city":"Lumby",
    "sg:classifiers":[
        {
            "category":"Manufacturing",
            "subcategory":"Lumber",
            "type":"Manufacturing & Wholesale Goods"
        }
    ],
    "sg:phone":"+1 250 547 6727",
    "sg:postcode":"V0E 2G5",
    "sg:province":"BC",
    "sg:tags":[
        "forester"
    ],
    "wof:name":"Bar-Ten Springs Enterprises",
    "wof:placetype":"venue"
},
  "geometry": {"coordinates":[-118.966888,50.247269],"type":"Point"}
}