{
  "type": "Feature",
  "properties": {
    "iso:country":"CA",
    "sg:address":"2341 Pooley St",
    "sg:city":"Wells",
    "sg:classifiers":[
        {
            "category":"Travel",
            "subcategory":"Hotels & Motels",
            "type":"Entertainment"
        }
    ],
    "sg:phone":"+1 250 994 3427",
    "sg:postcode":"V0K 2R0",
    "sg:province":"BC",
    "wof:name":"Wells Hotel",
    "wof:placetype":"venue"
},
  "geometry": {"coordinates":[-121.571647644,53.1039962769],"type":"Point"}
}