{
  "type": "Feature",
  "properties": {
    "addr:full":"Coquitlam BC V3K 4X8",
    "addr:postcode":"v3k 4x8",
    "iso:country":"CA",
    "sg:city":"Coquitlam",
    "sg:classifiers":[
        {
            "category":"Professional",
            "subcategory":"Art Services",
            "type":"Services"
        }
    ],
    "sg:phone":"+1 604 522 3500",
    "sg:postcode":"V3K 4X8",
    "sg:province":"BC",
    "sg:tags":[
        "graphic",
        "designer",
        "sign"
    ],
    "wof:name":"Neon Works",
    "wof:placetype":"venue"
},
  "geometry": {"coordinates":[-122.85231781,49.2336006165],"type":"Point"}
}