{
  "type": "Feature",
  "properties": {
    "addr:full":"4520 Ontario St Beamsville ON L0R 1B5",
    "addr:housenumber":"4520",
    "addr:postcode":"l0r 1b5",
    "addr:street":"Ontario St",
    "iso:country":"CA",
    "sg:address":"4520 Ontario St",
    "sg:city":"Beamsville",
    "sg:classifiers":[
        {
            "category":"Food & Beverages",
            "subcategory":"Groceries & Convenience Stores",
            "type":"Retail Goods"
        }
    ],
    "sg:phone":"+1 905 563 6131",
    "sg:postcode":"L0R 1B5",
    "sg:province":"ON",
    "wof:name":"Avondale Stores Ltd",
    "wof:placetype":"venue"
},
  "geometry": {"coordinates":[-79.477119,43.176899],"type":"Point"}
}