{
  "type": "Feature",
  "properties": {
    "addr:full":"1005 Boul Laure # B403 Sept-Iles QC G4R 4S6",
    "addr:housenumber":"1005;# b403",
    "addr:postcode":"g4r 4s6",
    "addr:street":"Boul Laure;Sept-Iles",
    "iso:country":"CA",
    "sg:address":"1005 Boul Laure # B403",
    "sg:city":"Sept-Iles",
    "sg:classifiers":[
        {
            "category":"Shopping",
            "subcategory":"Gifts & Souvenirs",
            "type":"Retail Goods"
        }
    ],
    "sg:phone":"+1 418 962 8681",
    "sg:postcode":"G4R 4S6",
    "sg:province":"QC",
    "sg:tags":[
        "shop"
    ],
    "wof:name":"Pot Pourri",
    "wof:placetype":"venue"
},
  "geometry": {"coordinates":[-66.39180755620001,50.2270050049],"type":"Point"}
}