{
  "type": "Feature",
  "properties": {
    "addr:full":"1935 Boul Hymus Dorval QC H9P 1J8",
    "addr:housenumber":"1935",
    "addr:postcode":"h9p 1j8",
    "addr:street":"Boul Hymus",
    "iso:country":"CA",
    "sg:address":"1935 Boul Hymus",
    "sg:city":"Dorval",
    "sg:classifiers":[
        {
            "category":"Manufacturing",
            "subcategory":"Printing",
            "type":"Manufacturing & Wholesale Goods"
        }
    ],
    "sg:phone":"+1 514 683 6161",
    "sg:postcode":"H9P 1J8",
    "sg:province":"QC",
    "sg:tags":[
        "lithographer",
        "printer"
    ],
    "wof:name":"Lithographie Internok Inc",
    "wof:placetype":"venue"
},
  "geometry": {"coordinates":[-73.78150939939999,45.4805183411],"type":"Point"}
}