{
  "type": "Feature",
  "properties": {
    "addr:full":"320 Lower Ganges Rd Salt Spring Island BC V8K 2V3",
    "addr:housenumber":"320",
    "addr:postcode":"v8k 2v3",
    "addr:street":"Lower Ganges Rd",
    "iso:country":"CA",
    "sg:address":"320 Lower Ganges Rd",
    "sg:city":"Salt Spring Island",
    "sg:classifiers":[
        {
            "category":"Health Services",
            "subcategory":"Doctor",
            "type":"Services"
        }
    ],
    "sg:phone":"+1 250 537 4141",
    "sg:postcode":"V8K 2V3",
    "sg:province":"BC",
    "sg:tags":[
        "dentist"
    ],
    "wof:name":"William E Lea Inc",
    "wof:placetype":"venue"
},
  "geometry": {"coordinates":[-123.508133,48.859432],"type":"Point"}
}