{
  "type": "Feature",
  "properties": {
    "iso:country":"CA",
    "sg:address":"85 Rue Principale",
    "sg:city":"Lachute",
    "sg:classifiers":[
        {
            "category":"Autos & Motor Vehicles",
            "subcategory":"Automobile Sales",
            "type":"Retail Goods"
        }
    ],
    "sg:phone":"+1 450 562 6165",
    "sg:postcode":"J8H 3A6",
    "sg:province":"QC",
    "sg:tags":[
        "repairing",
        "car"
    ],
    "wof:name":"Services Auto Ang Inc",
    "wof:placetype":"venue"
},
  "geometry": {"coordinates":[-74.3585968018,45.6533088684],"type":"Point"}
}