{
  "type": "Feature",
  "properties": {
    "addr:full":"9256 Commercial St # 1 New Minas NS B4N 4A9",
    "addr:housenumber":"9256",
    "addr:postcode":"b4n 4a9",
    "addr:street":"Commercial St # 1",
    "iso:country":"CA",
    "sg:address":"9256 Commercial St # 1",
    "sg:city":"New Minas",
    "sg:classifiers":[
        {
            "category":"Shopping",
            "subcategory":"Pharmacy",
            "type":"Retail Goods"
        }
    ],
    "sg:phone":"+1 902 681 1341",
    "sg:postcode":"B4N 4A9",
    "sg:province":"NS",
    "wof:name":"Zellers Pharmacy",
    "wof:placetype":"venue"
},
  "geometry": {"coordinates":[-64.4430770874,45.0682525635],"type":"Point"}
}