{
  "type": "Feature",
  "properties": {
    "iso:country":"CA",
    "sg:address":"5115 50 St",
    "sg:city":"Clive",
    "sg:classifiers":[
        {
            "category":"Education",
            "subcategory":"Library",
            "type":"Public Place"
        }
    ],
    "sg:phone":"+1 403 784 3131",
    "sg:postcode":"T0C 0Y0",
    "sg:province":"AB",
    "wof:name":"Clive Public Library",
    "wof:placetype":"venue"
},
  "geometry": {"coordinates":[-113.447265625,52.4783210754],"type":"Point"}
}