{
  "type": "Feature",
  "properties": {
    "addr:full":"6390 Rue Sherbrooke E Montreal QC H1N 3P6",
    "addr:housenumber":"6390",
    "addr:postcode":"h1n 3p6",
    "addr:street":"Rue Sherbrooke E",
    "iso:country":"CA",
    "sg:address":"6390 Rue Sherbrooke E",
    "sg:city":"Montreal",
    "sg:classifiers":[
        {
            "category":"Shopping",
            "type":"Retail Goods"
        }
    ],
    "sg:phone":"+1 514 251 2646",
    "sg:postcode":"H1N 3P6",
    "sg:province":"QC",
    "sg:tags":[
        "pet",
        "food",
        "shop",
        "supply"
    ],
    "wof:name":"J E Mondou Ltee",
    "wof:placetype":"venue"
},
  "geometry": {"coordinates":[-73.5440368652,45.5807533264],"type":"Point"}
}