{
  "type": "Feature",
  "properties": {
    "addr:full":"3243 Marentette Ave Windsor ON N8X 4G3",
    "addr:housenumber":"3243",
    "addr:postcode":"n8x 4g3",
    "addr:street":"Marentette Ave",
    "iso:country":"CA",
    "sg:address":"3243 Marentette Ave",
    "sg:city":"Windsor",
    "sg:classifiers":[
        {
            "category":"Manufacturing",
            "subcategory":"Glass & Minerals",
            "type":"Manufacturing & Wholesale Goods"
        }
    ],
    "sg:phone":"+1 519 966 6800",
    "sg:postcode":"N8X 4G3",
    "sg:province":"ON",
    "sg:tags":[
        "structural"
    ],
    "wof:name":"Bmw Glass Block Design",
    "wof:placetype":"venue"
},
  "geometry": {"coordinates":[-82.9975738525,42.2734222412],"type":"Point"}
}