{
  "type": "Feature",
  "properties": {
    "addr:full":"138 Sandiford Dr # 1 Stouffville ON L4A 7X5",
    "addr:housenumber":"138",
    "addr:postcode":"l4a 7x5",
    "addr:street":"Sandiford Dr # 1",
    "iso:country":"CA",
    "sg:address":"138 Sandiford Dr # 1",
    "sg:city":"Stouffville",
    "sg:classifiers":[
        {
            "category":"Retail",
            "subcategory":"Auto Repair",
            "type":"Services"
        }
    ],
    "sg:phone":"+1 905 640 3651",
    "sg:postcode":"L4A 7X5",
    "sg:province":"ON",
    "sg:tags":[
        "repairing",
        "automobile"
    ],
    "wof:name":"Firestone",
    "wof:placetype":"venue"
},
  "geometry": {"coordinates":[-79.2697067261,43.9639854431],"type":"Point"}
}