{
  "type": "Feature",
  "properties": {
    "addr:full":"260 Av Saint-Augustin Louiseville QC J5V 1B6",
    "addr:housenumber":"260",
    "addr:postcode":"j5v 1b6",
    "addr:street":"Av Saint-Augustin",
    "iso:country":"CA",
    "sg:address":"260 Av Saint-Augustin",
    "sg:city":"Louiseville",
    "sg:classifiers":[
        {
            "category":"Personal",
            "subcategory":"Beauty Salon",
            "type":"Services"
        }
    ],
    "sg:phone":"+1 819 228 1293",
    "sg:postcode":"J5V 1B6",
    "sg:province":"QC",
    "wof:name":"Salon DE Coiffure Ciseau",
    "wof:placetype":"venue"
},
  "geometry": {"coordinates":[-72.944992,46.258438],"type":"Point"}
}