{
  "type": "Feature",
  "properties": {
    "addr:full":"1622 Sydenham Rd Kingston ON K7L 4V4",
    "addr:housenumber":"1622",
    "addr:postcode":"k7l 4v4",
    "addr:street":"Sydenham Rd",
    "iso:country":"CA",
    "sg:address":"1622 Sydenham Rd",
    "sg:city":"Kingston",
    "sg:classifiers":[
        {
            "category":"Shopping",
            "subcategory":"Florist",
            "type":"Retail Goods"
        }
    ],
    "sg:phone":"+1 613 542 9929",
    "sg:postcode":"K7L 4V4",
    "sg:province":"ON",
    "wof:name":"Neil's Flowers Ltd",
    "wof:placetype":"venue"
},
  "geometry": {"coordinates":[-76.53941345210001,44.2891387939],"type":"Point"}
}