{
  "type": "Feature",
  "properties": {
    "addr:full":"8 Glen Watford Dr Scarborough ON M1S 2C1",
    "addr:housenumber":"8",
    "addr:postcode":"m1s 2c1",
    "addr:street":"Glen Watford Dr",
    "iso:country":"CA",
    "sg:address":"8 Glen Watford Dr",
    "sg:city":"Scarborough",
    "sg:classifiers":[
        {
            "category":"Shopping",
            "subcategory":"Gifts & Souvenirs",
            "type":"Retail Goods"
        }
    ],
    "sg:phone":"+1 416 754 3504",
    "sg:postcode":"M1S 2C1",
    "sg:province":"ON",
    "sg:tags":[
        "shop"
    ],
    "wof:name":"Eastgiant Corp",
    "wof:placetype":"venue"
},
  "geometry": {"coordinates":[-79.2761764526,43.7865715027],"type":"Point"}
}