{
  "type": "Feature",
  "properties": {
    "addr:full":"27024 Fraser Hwy Aldergrove BC V4W 3L6",
    "addr:housenumber":"27024",
    "addr:postcode":"v4w 3l6",
    "addr:street":"Fraser Hwy",
    "iso:country":"CA",
    "sg:address":"27024 Fraser Hwy",
    "sg:city":"Aldergrove",
    "sg:classifiers":[
        {
            "category":"Retail",
            "subcategory":"Photofinishing",
            "type":"Services"
        }
    ],
    "sg:phone":"+1 604 856 4835",
    "sg:postcode":"V4W 3L6",
    "sg:province":"BC",
    "sg:tags":[
        "photo",
        "finishing"
    ],
    "wof:name":"Altergrove Photo & Frames",
    "wof:placetype":"venue"
},
  "geometry": {"coordinates":[-122.475739,49.058117],"type":"Point"}
}