{
  "type": "Feature",
  "properties": {
    "addr:full":"642 Magnetic Dr North York ON M3J 2C4",
    "addr:housenumber":"642",
    "addr:postcode":"m3j 2c4",
    "addr:street":"Magnetic Dr",
    "iso:country":"CA",
    "sg:address":"642 Magnetic Dr",
    "sg:city":"North York",
    "sg:classifiers":[
        {
            "category":"Professional",
            "subcategory":"Business Services",
            "type":"Services"
        }
    ],
    "sg:phone":"+1 416 667 9967",
    "sg:postcode":"M3J 2C4",
    "sg:province":"ON",
    "sg:tags":[
        "broker"
    ],
    "wof:name":"Tradex Industry Group Inc",
    "wof:placetype":"venue"
},
  "geometry": {"coordinates":[-79.475692749,43.7837905884],"type":"Point"}
}