{
  "type": "Feature",
  "properties": {
    "iso:country":"CA",
    "sg:city":"Montreal",
    "sg:classifiers":[
        {
            "category":"Professional",
            "subcategory":"Computer Services",
            "type":"Services"
        }
    ],
    "sg:phone":"+1 514 875 7632",
    "sg:postcode":"H3G 1P9",
    "sg:province":"QC",
    "wof:name":"Danesh Electronique",
    "wof:placetype":"venue"
},
  "geometry": {"coordinates":[-73.5542297363,45.5203857422],"type":"Point"}
}