{
  "type": "Feature",
  "properties": {
    "addr:full":"3395 Fraser St Vancouver BC V5V 4C2",
    "addr:housenumber":"3395",
    "addr:postcode":"v5v 4c2",
    "addr:street":"Fraser St",
    "iso:country":"CA",
    "sg:address":"3395 Fraser St",
    "sg:city":"Vancouver",
    "sg:classifiers":[
        {
            "category":"Retail",
            "subcategory":"Laundry & Dry Cleaning",
            "type":"Services"
        }
    ],
    "sg:phone":"+1 604 874 2622",
    "sg:postcode":"V5V 4C2",
    "sg:province":"BC",
    "sg:tags":[
        "cleaners"
    ],
    "wof:name":"Busy Bee One Hour Cleaners",
    "wof:placetype":"venue"
},
  "geometry": {"coordinates":[-123.08994300000001,49.254772],"type":"Point"}
}