{
  "type": "Feature",
  "properties": {
    "addr:full":"30 Rue Beauchesne Warwick QC J0A 1M0",
    "addr:housenumber":"30",
    "addr:postcode":"j0a 1m0",
    "addr:street":"Rue Beauchesne",
    "iso:country":"CA",
    "sg:address":"30 Rue Beauchesne",
    "sg:city":"Warwick",
    "sg:classifiers":[
        {
            "category":"Manufacturing",
            "subcategory":"Apparel",
            "type":"Manufacturing & Wholesale Goods"
        }
    ],
    "sg:phone":"+1 819 358 2366",
    "sg:postcode":"J0A 1M0",
    "sg:province":"QC",
    "sg:tags":[
        "sewing",
        "contractor"
    ],
    "wof:name":"Nathalie Lussier Inc",
    "wof:placetype":"venue"
},
  "geometry": {"coordinates":[-71.99071499999999,45.95459],"type":"Point"}
}