{
  "type": "Feature",
  "properties": {
    "iso:country":"CA",
    "sg:city":"Montmagny",
    "sg:classifiers":[
        {
            "category":"Social Services",
            "subcategory":"Child Care",
            "type":"Services"
        }
    ],
    "sg:phone":"+1 418 248 8993",
    "sg:postcode":"G5V 3G7",
    "sg:province":"QC",
    "sg:tags":[
        "kindergarten",
        "academic",
        "school"
    ],
    "wof:name":"Atelier L'Envolee",
    "wof:placetype":"venue"
},
  "geometry": {"coordinates":[-70.56233978269999,46.9769439697],"type":"Point"}
}