{
  "type": "Feature",
  "properties": {
    "addr:full":"521 8th Ave W Vancouver BC V5Z 1C6",
    "addr:housenumber":"521",
    "addr:postcode":"v5z 1c6",
    "addr:street":"8Th Ave W",
    "iso:country":"CA",
    "sg:address":"521 8th Ave W",
    "sg:city":"Vancouver",
    "sg:classifiers":[
        {
            "category":"Wholesale",
            "subcategory":"Groceries",
            "type":"Manufacturing & Wholesale Goods"
        }
    ],
    "sg:phone":"+1 604 873 1393",
    "sg:postcode":"V5Z 1C6",
    "sg:province":"BC",
    "sg:tags":[
        "bakery",
        "prod"
    ],
    "wof:name":"Redpath Foods Inc",
    "wof:placetype":"venue"
},
  "geometry": {"coordinates":[-123.11548614500001,49.2642822266],"type":"Point"}
}