{
  "type": "Feature",
  "properties": {
    "iso:country":"CA",
    "sg:city":"Edson",
    "sg:classifiers":[
        {
            "category":"Personal",
            "subcategory":"Beauty Salon",
            "type":"Services"
        }
    ],
    "sg:phone":"+1 780 723 4979",
    "sg:postcode":"T7E 1T3",
    "sg:province":"AB",
    "wof:name":"Lee-Roy's Hairstyling",
    "wof:placetype":"venue"
},
  "geometry": {"coordinates":[-116.430656433,53.5838356018],"type":"Point"}
}