{
  "type": "Feature",
  "properties": {
    "addr:full":"2089 Maitland St Halifax NS B3K 2Z8",
    "addr:housenumber":"2089",
    "addr:postcode":"b3k 2z8",
    "addr:street":"Maitland St",
    "iso:country":"CA",
    "sg:address":"2089 Maitland St",
    "sg:city":"Halifax",
    "sg:classifiers":[
        {
            "category":"Communications",
            "subcategory":"Film & Video Production",
            "type":"Services"
        }
    ],
    "sg:phone":"+1 902 423 1989",
    "sg:postcode":"B3K 2Z8",
    "sg:province":"NS",
    "sg:tags":[
        "picture",
        "television",
        "producer",
        "motion",
        "program",
        "studio"
    ],
    "wof:name":"Creative Atlantic Comm Ltd",
    "wof:placetype":"venue"
},
  "geometry": {"coordinates":[-63.582157,44.652294],"type":"Point"}
}