{
  "type": "Feature",
  "properties": {
    "addr:full":"300 Holancin Rd Kettleby ON L0G 1J0",
    "addr:housenumber":"300",
    "addr:postcode":"l0g 1j0",
    "addr:street":"Holancin Rd",
    "iso:country":"CA",
    "sg:address":"300 Holancin Rd",
    "sg:city":"Kettleby",
    "sg:classifiers":[
        {
            "category":"Wholesale",
            "subcategory":"Fruits & Vegetables",
            "type":"Manufacturing & Wholesale Goods"
        }
    ],
    "sg:phone":"+1 905 775 2316",
    "sg:postcode":"L0G 1J0",
    "sg:province":"ON",
    "sg:tags":[
        "shipper"
    ],
    "wof:name":"Holancin's Farms",
    "wof:placetype":"venue"
},
  "geometry": {"coordinates":[-79.609573,44.032722],"type":"Point"}
}