{
  "type": "Feature",
  "properties": {
    "addr:full":"645 Bloor St W Oshawa ON L1J 5Y6",
    "addr:housenumber":"645",
    "addr:postcode":"l1j 5y6",
    "addr:street":"Bloor St W",
    "iso:country":"CA",
    "sg:address":"645 Bloor St W",
    "sg:city":"Oshawa",
    "sg:classifiers":[
        {
            "category":"Retail",
            "subcategory":"Auto Rental",
            "type":"Services"
        }
    ],
    "sg:phone":"+1 905 668 3101",
    "sg:postcode":"L1J 5Y6",
    "sg:province":"ON",
    "sg:tags":[
        "renting",
        "leasing",
        "trailer"
    ],
    "wof:name":"Jensen Trailer Sales & Svc",
    "wof:placetype":"venue"
},
  "geometry": {"coordinates":[-78.87854799999999,43.87487],"type":"Point"}
}