{
  "type": "Feature",
  "properties": {
    "iso:country":"CA",
    "sg:address":"565 Salway St",
    "sg:city":"London",
    "sg:classifiers":[
        {
            "category":"Building & Trades",
            "subcategory":"Construction",
            "type":"Services"
        }
    ],
    "sg:phone":"+1 519 471 1096",
    "sg:postcode":"N6H 3P9",
    "sg:province":"ON",
    "sg:tags":[
        "general",
        "contractor"
    ],
    "wof:name":"Condon Construction Ltd",
    "wof:placetype":"venue"
},
  "geometry": {"coordinates":[-81.31024169920001,42.9732093811],"type":"Point"}
}