{
  "type": "Feature",
  "properties": {
    "addr:full":"Saint-Bernard QC G0S 2G0",
    "addr:postcode":"g0s 2g0",
    "iso:country":"CA",
    "sg:city":"Saint-Bernard",
    "sg:classifiers":[
        {
            "category":"Manufacturing",
            "subcategory":"Signs",
            "type":"Manufacturing & Wholesale Goods"
        }
    ],
    "sg:phone":"+1 418 475 6678",
    "sg:postcode":"G0S 2G0",
    "sg:province":"QC",
    "wof:name":"Eclairages Fluo-Neon",
    "wof:placetype":"venue"
},
  "geometry": {"coordinates":[-71.11493682859999,46.511920929],"type":"Point"}
}