{
  "type": "Feature",
  "properties": {
    "iso:country":"CA",
    "sg:city":"London",
    "sg:classifiers":[
        {
            "category":"Personal",
            "subcategory":"Beauty Salon",
            "type":"Services"
        }
    ],
    "sg:phone":"+1 519 457 6870",
    "sg:postcode":"N5W 1V6",
    "sg:province":"ON",
    "wof:name":"New Hair Unisex",
    "wof:placetype":"venue"
},
  "geometry": {"coordinates":[-81.1919174194,42.9775161743],"type":"Point"}
}