{
  "type": "Feature",
  "properties": {
    "addr:full":"680 Rue Du Ruisseau Saint-Elzear QC G0S 2J0",
    "addr:housenumber":"680",
    "addr:postcode":"g0s 2j0",
    "addr:street":"Rue Du Ruisseau Saint-Elzear",
    "iso:country":"CA",
    "sg:address":"680 Rue Du Ruisseau",
    "sg:city":"Saint-Elzear",
    "sg:classifiers":[
        {
            "category":"Building & Trades",
            "subcategory":"Electrical",
            "type":"Services"
        }
    ],
    "sg:phone":"+1 418 387 7782",
    "sg:postcode":"G0S 2J0",
    "sg:province":"QC",
    "sg:tags":[
        "electric",
        "contractor"
    ],
    "wof:name":"Electricite Noel Berthiaume",
    "wof:placetype":"venue"
},
  "geometry": {"coordinates":[-71.06384300000001,46.405354],"type":"Point"}
}