{
  "type": "Feature",
  "properties": {
    "addr:full":"Winnipeg MB R2G 1P1",
    "addr:postcode":"r2g 1p1",
    "iso:country":"CA",
    "sg:city":"Winnipeg",
    "sg:classifiers":[
        {
            "category":"Professional",
            "subcategory":"Lawyer & Legal Services",
            "type":"Services"
        }
    ],
    "sg:phone":"+1 204 989 5540",
    "sg:postcode":"R2G 1P1",
    "sg:province":"MB",
    "sg:tags":[
        "attorney"
    ],
    "wof:name":"Dobrowolski, Alexander",
    "wof:placetype":"venue"
},
  "geometry": {"coordinates":[-97.07963562010001,49.9508705139],"type":"Point"}
}