{
  "type": "Feature",
  "properties": {
    "addr:full":"415 Rue St-Jean Riviere-Saint-Jean QC G0G 2N0",
    "addr:housenumber":"415",
    "addr:postcode":"g0g 2n0",
    "addr:street":"Rue St-Jean Riviere-Saint-Jean",
    "iso:country":"CA",
    "sg:address":"415 Rue St-Jean",
    "sg:city":"Riviere-Saint-Jean",
    "sg:classifiers":[
        {
            "category":"Autos & Motor Vehicles",
            "subcategory":"Fuel & Gas Station",
            "type":"Retail Goods"
        }
    ],
    "sg:phone":"+1 418 949 2429",
    "sg:postcode":"G0G 2N0",
    "sg:province":"QC",
    "sg:tags":[
        "oil",
        "extract",
        "flavoring"
    ],
    "wof:name":"Garage Ginette Boulay",
    "wof:placetype":"venue"
},
  "geometry": {"coordinates":[-64.35804,50.295448],"type":"Point"}
}