{
  "type": "Feature",
  "properties": {
    "addr:full":"6840 88 St NW Edmonton AB T6E 5H6",
    "addr:housenumber":"6840",
    "addr:postcode":"t6e 5h6",
    "addr:street":"88 St Nw",
    "iso:country":"CA",
    "sg:address":"6840 88 St NW",
    "sg:city":"Edmonton",
    "sg:classifiers":[
        {
            "category":"Organizations",
            "subcategory":"Professional Association",
            "type":"Services"
        }
    ],
    "sg:phone":"+1 780 461 7625",
    "sg:postcode":"T6E 5H6",
    "sg:province":"AB",
    "sg:tags":[
        "club"
    ],
    "wof:name":"Rockers Athletic",
    "wof:placetype":"venue"
},
  "geometry": {"coordinates":[-113.463500977,53.5048675537],"type":"Point"}
}