{
  "type": "Feature",
  "properties": {
    "addr:full":"9145 134B St Surrey BC V3V 5T8",
    "addr:housenumber":"9145",
    "addr:postcode":"v3v 5t8",
    "addr:street":"134B St",
    "iso:country":"CA",
    "sg:address":"9145 134B St",
    "sg:city":"Surrey",
    "sg:classifiers":[
        {
            "category":"Education",
            "subcategory":"Special Training",
            "type":"Public Place"
        }
    ],
    "sg:phone":"+1 604 502 8507",
    "sg:postcode":"V3V 5T8",
    "sg:province":"BC",
    "sg:tags":[
        "instruction",
        "driving"
    ],
    "wof:name":"Bhart Driving School",
    "wof:placetype":"venue"
},
  "geometry": {"coordinates":[-122.830215,49.105179],"type":"Point"}
}