{
  "type": "Feature",
  "properties": {
    "addr:full":"56 Harbour Dr Edwardsville NS B2A 4T6",
    "addr:housenumber":"56",
    "addr:postcode":"b2a 4t6",
    "addr:street":"Harbour Dr",
    "iso:country":"CA",
    "sg:address":"56 Harbour Dr",
    "sg:city":"Edwardsville",
    "sg:classifiers":[
        {
            "category":"Retail",
            "subcategory":"Auto Repair",
            "type":"Services"
        }
    ],
    "sg:phone":"+1 902 567 1030",
    "sg:postcode":"B2A 4T6",
    "sg:province":"NS",
    "sg:tags":[
        "truck"
    ],
    "wof:name":"Island Diesel & Marine",
    "wof:placetype":"venue"
},
  "geometry": {"coordinates":[-60.2295532227,46.1550712585],"type":"Point"}
}