{
  "type": "Feature",
  "properties": {
    "addr:full":"659 Bronson Ave Ottawa ON K1S 4E7",
    "addr:housenumber":"659",
    "addr:postcode":"k1s 4e7",
    "addr:street":"Bronson Ave",
    "iso:country":"CA",
    "sg:address":"659 Bronson Ave",
    "sg:city":"Ottawa",
    "sg:classifiers":[
        {
            "category":"Food & Beverages",
            "subcategory":"Groceries & Convenience Stores",
            "type":"Retail Goods"
        }
    ],
    "sg:phone":"+1 613 237 1553",
    "sg:postcode":"K1S 4E7",
    "sg:province":"ON",
    "wof:name":"Ainee's Convenience Store",
    "wof:placetype":"venue"
},
  "geometry": {"coordinates":[-75.70086669920001,45.4032363892],"type":"Point"}
}