{
  "type": "Feature",
  "properties": {
    "addr:full":"25 Winter St Sussex NB E4E 2H9",
    "addr:housenumber":"25",
    "addr:postcode":"e4e 2h9",
    "addr:street":"Winter St",
    "iso:country":"CA",
    "sg:address":"25 Winter St",
    "sg:city":"Sussex",
    "sg:classifiers":[
        {
            "category":"Government",
            "subcategory":"Office",
            "type":"Public Place"
        }
    ],
    "sg:phone":"+1 506 432 4587",
    "sg:postcode":"E4E 2H9",
    "sg:province":"NB",
    "sg:tags":[
        "member",
        "legislative",
        "assembly"
    ],
    "wof:name":"Cosman, Doug",
    "wof:placetype":"venue"
},
  "geometry": {"coordinates":[-65.507431,45.722466],"type":"Point"}
}