{
  "type": "Feature",
  "properties": {
    "addr:full":"204 Boteler St Ottawa ON K1N 5A7",
    "addr:housenumber":"204",
    "addr:postcode":"k1n 5a7",
    "addr:street":"Boteler St",
    "iso:country":"CA",
    "sg:address":"204 Boteler St",
    "sg:city":"Ottawa",
    "sg:classifiers":[
        {
            "category":"Organizations",
            "subcategory":"Membership Organization",
            "type":"Services"
        }
    ],
    "sg:phone":"+1 613 789 4338",
    "sg:postcode":"K1N 5A7",
    "sg:province":"ON",
    "wof:name":"Catholic Immigration Ctr",
    "wof:placetype":"venue"
},
  "geometry": {"coordinates":[-75.69326,45.435768],"type":"Point"}
}