{
  "type": "Feature",
  "properties": {
    "addr:full":"909 Boul LA Verendrye O Gatineau QC J8P 7H2",
    "addr:housenumber":"909",
    "addr:postcode":"j8p 7h2",
    "addr:street":"Boul La Verendrye O",
    "iso:country":"CA",
    "sg:address":"909 Boul LA Verendrye O",
    "sg:city":"Gatineau",
    "sg:classifiers":[
        {
            "category":"Organizations",
            "subcategory":"Labor Organization",
            "type":"Services"
        }
    ],
    "sg:phone":"+1 819 243 6318",
    "sg:postcode":"J8P 7H2",
    "sg:province":"QC",
    "wof:name":"Syndicat Des Infirmieres & Des",
    "wof:placetype":"venue"
},
  "geometry": {"coordinates":[-75.69090300000001,45.491871],"type":"Point"}
}