{
  "type": "Feature",
  "properties": {
    "addr:full":"377 Rue Mccaffrey Saint-Laurent QC H4T 1Z7",
    "addr:housenumber":"377",
    "addr:postcode":"h4t 1z7",
    "addr:street":"Rue Mccaffrey",
    "iso:country":"CA",
    "sg:address":"377 Rue Mccaffrey",
    "sg:city":"Saint-Laurent",
    "sg:classifiers":[
        {
            "category":"Manufacturing",
            "subcategory":"Metals",
            "type":"Manufacturing & Wholesale Goods"
        }
    ],
    "sg:phone":"+1 514 344 2729",
    "sg:postcode":"H4T 1Z7",
    "sg:province":"QC",
    "sg:tags":[
        "valve"
    ],
    "wof:name":"Bray Controls Canada",
    "wof:placetype":"venue"
},
  "geometry": {"coordinates":[-73.70393371580001,45.4835929871],"type":"Point"}
}