{
  "type": "Feature",
  "properties": {
    "iso:country":"CA",
    "sg:address":"43 Yongehurst Rd",
    "sg:city":"Richmond Hill",
    "sg:classifiers":[
        {
            "category":"Professional",
            "subcategory":"Management & Consulting",
            "type":"Services"
        }
    ],
    "sg:phone":"+1 905 780 9697",
    "sg:postcode":"L4C 3T3",
    "sg:province":"ON",
    "sg:tags":[
        "consultant",
        "business"
    ],
    "wof:name":"M J Bast Business Planning",
    "wof:placetype":"venue"
},
  "geometry": {"coordinates":[-79.438049,43.861961],"type":"Point"}
}