{
  "type": "Feature",
  "properties": {
    "addr:full":"43 Yongehurst Rd Richmond Hill ON L4C 3T3",
    "addr:housenumber":"43",
    "addr:postcode":"l4c 3t3",
    "addr:street":"Yongehurst Rd",
    "iso:country":"CA",
    "sg:address":"43 Yongehurst Rd",
    "sg:city":"Richmond Hill",
    "sg:classifiers":[
        {
            "category":"Professional",
            "subcategory":"Management & Consulting",
            "type":"Services"
        }
    ],
    "sg:phone":"+1 905 780 9697",
    "sg:postcode":"L4C 3T3",
    "sg:province":"ON",
    "sg:tags":[
        "consultant",
        "business"
    ],
    "wof:name":"M J Bast Business Planning",
    "wof:placetype":"venue"
},
  "geometry": {"coordinates":[-79.43804900000001,43.861961],"type":"Point"}
}