{
  "type": "Feature",
  "properties": {
    "addr:full":"412 Hwy 17 Nipigon ON P0T 2J0",
    "addr:housenumber":"412",
    "addr:postcode":"p0t 2j0",
    "addr:street":"Hwy 17",
    "iso:country":"CA",
    "sg:address":"412 Hwy 17",
    "sg:city":"Nipigon",
    "sg:classifiers":[
        {
            "category":"Travel",
            "subcategory":"Hotels & Motels",
            "type":"Entertainment"
        }
    ],
    "sg:phone":"+1 807 887 2914",
    "sg:postcode":"P0T 2J0",
    "sg:province":"ON",
    "wof:name":"Beaver Motel Hotel",
    "wof:placetype":"venue"
},
  "geometry": {"coordinates":[-88.28248600000001,49.020199],"type":"Point"}
}