{
  "type": "Feature",
  "properties": {
    "addr:full":"1 Rue Provost Lachine QC H8S 4H2",
    "addr:housenumber":"1",
    "addr:postcode":"h8s 4h2",
    "addr:street":"Rue Provost",
    "iso:country":"CA",
    "sg:address":"1 Rue Provost",
    "sg:city":"Lachine",
    "sg:classifiers":[
        {
            "category":"Freight",
            "type":"Transportation"
        }
    ],
    "sg:phone":"+1 514 634 1554",
    "sg:postcode":"H8S 4H2",
    "sg:province":"QC",
    "sg:tags":[
        "trucking"
    ],
    "wof:name":"International Cargo Trnsprtn",
    "wof:placetype":"venue"
},
  "geometry": {"coordinates":[-73.662361,45.441807],"type":"Point"}
}