{
  "type": "Feature",
  "properties": {
    "addr:full":"27 Hawkins St Blind River ON P0R 1B0",
    "addr:housenumber":"27",
    "addr:postcode":"p0r 1b0",
    "addr:street":"Hawkins St",
    "iso:country":"CA",
    "sg:address":"27 Hawkins St",
    "sg:city":"Blind River",
    "sg:classifiers":[
        {
            "category":"Social Services",
            "type":"Services"
        }
    ],
    "sg:phone":"+1 705 356 7471",
    "sg:postcode":"P0R 1B0",
    "sg:province":"ON",
    "sg:tags":[
        "organization",
        "welfare"
    ],
    "wof:name":"Royal Canadian Legion Branch",
    "wof:placetype":"venue"
},
  "geometry": {"coordinates":[-82.957443,46.187408],"type":"Point"}
}