{
  "type": "Feature",
  "properties": {
    "addr:full":"11575 Boul DE Pierrefonds Pierrefonds QC H8Y 3J2",
    "addr:housenumber":"11575",
    "addr:postcode":"h8y 3j2",
    "addr:street":"Boul De Pierrefonds",
    "iso:country":"CA",
    "sg:address":"11575 Boul DE Pierrefonds",
    "sg:city":"Pierrefonds",
    "sg:classifiers":[
        {
            "category":"Health Services",
            "subcategory":"Doctor",
            "type":"Services"
        }
    ],
    "sg:phone":"+1 514 421 1000",
    "sg:postcode":"H8Y 3J2",
    "sg:province":"QC",
    "sg:tags":[
        "clinic"
    ],
    "wof:name":"Medi-Centre DE Pierrefonds",
    "wof:placetype":"venue"
},
  "geometry": {"coordinates":[-73.81873299999999,45.507912],"type":"Point"}
}