{
  "type": "Feature",
  "properties": {
    "addr:full":"81 Tilley Rd Gagetown NB E5M 1B3",
    "addr:housenumber":"81",
    "addr:postcode":"e5m 1b3",
    "addr:street":"Tilley Rd",
    "iso:country":"CA",
    "sg:address":"81 Tilley Rd",
    "sg:city":"Gagetown",
    "sg:classifiers":[
        {
            "category":"Organizations",
            "subcategory":"Community Association",
            "type":"Services"
        }
    ],
    "sg:phone":"+1 506 488 2336",
    "sg:postcode":"E5M 1B3",
    "sg:province":"NB",
    "sg:tags":[
        "club"
    ],
    "wof:name":"Royal Can Legion 71",
    "wof:placetype":"venue"
},
  "geometry": {"coordinates":[-66.15239,45.778137],"type":"Point"}
}