{
  "type": "Feature",
  "properties": {
    "addr:full":"248 Edwards Ave The Pas MB R9A 1K2",
    "addr:housenumber":"248",
    "addr:postcode":"r9a 1k2",
    "addr:street":"Edwards Ave",
    "iso:country":"CA",
    "sg:address":"248 Edwards Ave",
    "sg:city":"The Pas",
    "sg:classifiers":[
        {
            "category":"Shopping",
            "subcategory":"Used Merchandise",
            "type":"Retail Goods"
        }
    ],
    "sg:phone":"+1 204 623 7882",
    "sg:postcode":"R9A 1K2",
    "sg:province":"MB",
    "sg:tags":[
        "pawnbroker"
    ],
    "wof:name":"Border Insta-Cash",
    "wof:placetype":"venue"
},
  "geometry": {"coordinates":[-101.251365662,53.8238716125],"type":"Point"}
}