{
  "type": "Feature",
  "properties": {
    "addr:full":"858 Rue Saint-Cyrille Normandin QC G8M 4H5",
    "addr:housenumber":"858",
    "addr:postcode":"g8m 4h5",
    "addr:street":"Rue Saint-Cyrille",
    "iso:country":"CA",
    "sg:address":"858 Rue Saint-Cyrille",
    "sg:city":"Normandin",
    "sg:classifiers":[
        {
            "category":"Home & Garden",
            "subcategory":"Furniture",
            "type":"Retail Goods"
        }
    ],
    "sg:phone":"+1 418 274 2022",
    "sg:postcode":"G8M 4H5",
    "sg:province":"QC",
    "wof:name":"R Doucet Meubles Ltee",
    "wof:placetype":"venue"
},
  "geometry": {"coordinates":[-72.5253601074,48.8333053589],"type":"Point"}
}