{
  "type": "Feature",
  "properties": {
    "iso:country":"CA",
    "sg:city":"Brampton",
    "sg:classifiers":[
        {
            "category":"Home & Garden",
            "subcategory":"Building Materials",
            "type":"Retail Goods"
        }
    ],
    "sg:phone":"+1 905 454 4454",
    "sg:postcode":"L6T 5E9",
    "sg:province":"ON",
    "sg:tags":[
        "glass",
        "window",
        "plate"
    ],
    "wof:name":"Admiral Glass Svc",
    "wof:placetype":"venue"
},
  "geometry": {"coordinates":[-79.68766021730001,43.7394866943],"type":"Point"}
}