{
  "type": "Feature",
  "properties": {
    "addr:full":"Richmond BC V6Y 3T8",
    "addr:postcode":"v6y 3t8",
    "iso:country":"CA",
    "sg:city":"Richmond",
    "sg:classifiers":[
        {
            "category":"Personal",
            "subcategory":"Beauty Salon",
            "type":"Services"
        }
    ],
    "sg:phone":"+1 604 278 8821",
    "sg:postcode":"V6Y 3T8",
    "sg:province":"BC",
    "sg:tags":[
        "consultant",
        "health"
    ],
    "wof:name":"D N & CO Hair Studio",
    "wof:placetype":"venue"
},
  "geometry": {"coordinates":[-123.134293,49.166672],"type":"Point"}
}