{
  "type": "Feature",
  "properties": {
    "addr:full":"881 Rue Main Ayer's Cliff QC J0B 1C0",
    "addr:housenumber":"881",
    "addr:postcode":"j0b 1c0",
    "addr:street":"Rue Main",
    "iso:country":"CA",
    "sg:address":"881 Rue Main",
    "sg:city":"Ayer's Cliff",
    "sg:classifiers":[
        {
            "category":"Professional",
            "subcategory":"Accounting & Tax Preparation",
            "type":"Services"
        }
    ],
    "sg:phone":"+1 819 838 4243",
    "sg:postcode":"J0B 1C0",
    "sg:province":"QC",
    "sg:tags":[
        "bookkeeping",
        "return",
        "system",
        "filing"
    ],
    "wof:name":"Benoit & Assoc",
    "wof:placetype":"venue"
},
  "geometry": {"coordinates":[-75.652252,45.507339],"type":"Point"}
}