{
  "type": "Feature",
  "properties": {
    "addr:full":"1740 Ontario Ave Saskatoon SK S7K 1T1",
    "addr:housenumber":"1740",
    "addr:postcode":"s7k 1t1",
    "addr:street":"Ontario Ave",
    "iso:country":"CA",
    "sg:address":"1740 Ontario Ave",
    "sg:city":"Saskatoon",
    "sg:classifiers":[
        {
            "category":"Shopping",
            "subcategory":"Bicycles & Sporting Goods",
            "type":"Retail Goods"
        }
    ],
    "sg:phone":"+1 306 242 1159",
    "sg:postcode":"S7K 1T1",
    "sg:province":"SK",
    "wof:name":"Larry's Sports Exchange",
    "wof:placetype":"venue"
},
  "geometry": {"coordinates":[-106.665932,52.152271],"type":"Point"}
}