{
  "type": "Feature",
  "properties": {
    "addr:full":"11 Rue Perusse Edmundston NB E3V 3K5",
    "addr:housenumber":"11",
    "addr:postcode":"e3v 3k5",
    "addr:street":"Rue Perusse",
    "iso:country":"CA",
    "sg:address":"11 Rue Perusse",
    "sg:city":"Edmundston",
    "sg:classifiers":[
        {
            "category":"Autos & Motor Vehicles",
            "subcategory":"Automobile Sales",
            "type":"Retail Goods"
        }
    ],
    "sg:phone":"+1 506 739 7713",
    "sg:postcode":"E3V 3K5",
    "sg:province":"NB",
    "sg:tags":[
        "car",
        "dealer"
    ],
    "wof:name":"G P Martin Mazda Autos Ltee",
    "wof:placetype":"venue"
},
  "geometry": {"coordinates":[-68.35126495359999,47.3937530518],"type":"Point"}
}