{
  "type": "Feature",
  "properties": {
    "iso:country":"CA",
    "sg:address":"1250 Lynn Valley Rd",
    "sg:city":"North Vancouver",
    "sg:classifiers":[
        {
            "category":"Food & Beverages",
            "subcategory":"Groceries & Convenience Stores",
            "type":"Retail Goods"
        }
    ],
    "sg:phone":"+1 604 985 6311",
    "sg:postcode":"V7J 2A3",
    "sg:province":"BC",
    "sg:tags":[
        "grocer"
    ],
    "wof:name":"Lynn Valley Produce",
    "wof:placetype":"venue"
},
  "geometry": {"coordinates":[-123.039245605,49.3366851807],"type":"Point"}
}