{
  "type": "Feature",
  "properties": {
    "addr:full":"21 Church St E Brampton ON L6V 1E8",
    "addr:housenumber":"21",
    "addr:postcode":"l6v 1e8",
    "addr:street":"Church St E",
    "iso:country":"CA",
    "sg:address":"21 Church St E",
    "sg:city":"Brampton",
    "sg:classifiers":[
        {
            "category":"Health Services",
            "subcategory":"Hospital",
            "type":"Services"
        }
    ],
    "sg:phone":"+1 905 450 0277",
    "sg:postcode":"L6V 1E8",
    "sg:province":"ON",
    "sg:tags":[
        "home",
        "convalescent",
        "mental",
        "nursing"
    ],
    "wof:name":"Genesis Lodge",
    "wof:placetype":"venue"
},
  "geometry": {"coordinates":[-79.76183319090001,43.6887626648],"type":"Point"}
}