{
  "type": "Feature",
  "properties": {
    "addr:full":"Saint-Pie QC J0H 1W0",
    "addr:postcode":"j0h 1w0",
    "iso:country":"CA",
    "sg:city":"Saint-Pie",
    "sg:classifiers":[
        {
            "category":"Government",
            "subcategory":"Office",
            "type":"Public Place"
        }
    ],
    "sg:phone":"+1 450 772 2200",
    "sg:postcode":"J0H 1W0",
    "sg:province":"QC",
    "sg:tags":[
        "village"
    ],
    "wof:name":"St-Pie Voirie & Aqueduc",
    "wof:placetype":"venue"
},
  "geometry": {"coordinates":[-72.8995056152,45.5014343262],"type":"Point"}
}