{
  "type": "Feature",
  "properties": {
    "addr:full":"721 Rue Saint-Joseph Saint-Raymond QC G3L 1M2",
    "addr:housenumber":"721",
    "addr:postcode":"g3l 1m2",
    "addr:street":"Rue Saint-Joseph",
    "iso:country":"CA",
    "sg:address":"721 Rue Saint-Joseph",
    "sg:city":"Saint-Raymond",
    "sg:classifiers":[
        {
            "category":"Restaurant",
            "type":"Food & Drink"
        }
    ],
    "sg:phone":"+1 418 337 7739",
    "sg:postcode":"G3L 1M2",
    "sg:province":"QC",
    "wof:name":"Restaurant Le St-Raymond 721",
    "wof:placetype":"venue"
},
  "geometry": {"coordinates":[-71.8228683472,46.8980865479],"type":"Point"}
}