{
  "type": "Feature",
  "properties": {
    "addr:full":"620 Hudson Dr Labrador City NL A2V 1M1",
    "addr:housenumber":"620",
    "addr:postcode":"a2v 1m1",
    "addr:street":"Hudson Dr",
    "iso:country":"CA",
    "sg:address":"620 Hudson Dr",
    "sg:city":"Labrador City",
    "sg:classifiers":[
        {
            "category":"Retail",
            "subcategory":"Funeral Services",
            "type":"Services"
        }
    ],
    "sg:phone":"+1 709 944 7790",
    "sg:postcode":"A2V 1M1",
    "sg:province":"NL",
    "sg:tags":[
        "director"
    ],
    "wof:name":"Penney's Funeral Home",
    "wof:placetype":"venue"
},
  "geometry": {"coordinates":[-66.91728999999999,52.942364],"type":"Point"}
}