{
  "type": "Feature",
  "properties": {
    "addr:full":"28 Rue Principale S LA Patrie QC J0B 1Y0",
    "addr:housenumber":"28",
    "addr:postcode":"j0b 1y0",
    "addr:street":"Rue Principale S La Patrie",
    "iso:country":"CA",
    "sg:address":"28 Rue Principale S",
    "sg:city":"LA Patrie",
    "sg:classifiers":[
        {
            "category":"Retail",
            "subcategory":"Auto Repair",
            "type":"Services"
        }
    ],
    "sg:phone":"+1 819 888 2495",
    "sg:postcode":"J0B 1Y0",
    "sg:province":"QC",
    "sg:tags":[
        "repairing",
        "automobile"
    ],
    "wof:name":"Auto LA Patrie Inc",
    "wof:placetype":"venue"
},
  "geometry": {"coordinates":[-71.248817,45.400772],"type":"Point"}
}