{
  "type": "Feature",
  "properties": {
    "addr:full":"199 Highway 28 Bailieboro ON K0L 1B0",
    "addr:housenumber":"199",
    "addr:postcode":"k0l 1b0",
    "addr:street":"Highway 28",
    "iso:country":"CA",
    "sg:address":"199 Highway 28",
    "sg:city":"Bailieboro",
    "sg:classifiers":[
        {
            "category":"Real Estate",
            "subcategory":"Real Estate Agent",
            "type":"Services"
        }
    ],
    "sg:phone":"+1 705 939 6111",
    "sg:postcode":"K0L 1B0",
    "sg:province":"ON",
    "wof:name":"Remax Eastern Realty Inc",
    "wof:placetype":"venue"
},
  "geometry": {"coordinates":[-78.35307299999999,44.132019],"type":"Point"}
}