{
  "type": "Feature",
  "properties": {
    "addr:full":"682 St Clair Ave W Toronto ON M6C 1B1",
    "addr:housenumber":"682",
    "addr:postcode":"m6c 1b1",
    "addr:street":"St Clair Ave W",
    "iso:country":"CA",
    "sg:address":"682 St Clair Ave W",
    "sg:city":"Toronto",
    "sg:classifiers":[
        {
            "category":"Restaurant",
            "type":"Food & Drink"
        }
    ],
    "sg:phone":"+1 416 651 3881",
    "sg:postcode":"M6C 1B1",
    "sg:province":"ON",
    "wof:name":"Honora Wise Guys Bar & Grill",
    "wof:placetype":"venue"
},
  "geometry": {"coordinates":[-79.425529,43.68187],"type":"Point"}
}