{
  "type": "Feature",
  "properties": {
    "addr:full":"8160 Dixie Rd Brampton ON L6T 5N9",
    "addr:housenumber":"8160",
    "addr:postcode":"l6t 5n9",
    "addr:street":"Dixie Rd",
    "iso:country":"CA",
    "sg:address":"8160 Dixie Rd",
    "sg:city":"Brampton",
    "sg:classifiers":[
        {
            "category":"Restaurant",
            "type":"Food & Drink"
        }
    ],
    "sg:phone":"+1 905 451 0680",
    "sg:postcode":"L6T 5N9",
    "sg:province":"ON",
    "wof:name":"Wendy's",
    "wof:placetype":"venue"
},
  "geometry": {"coordinates":[-79.711288,43.702084],"type":"Point"}
}