{
  "type": "Feature",
  "properties": {
    "addr:full":"Toronto ON M6J 1X3",
    "addr:postcode":"m6j 1x3",
    "iso:country":"CA",
    "sg:city":"Toronto",
    "sg:classifiers":[
        {
            "category":"Professional",
            "subcategory":"Accounting & Tax Preparation",
            "type":"Services"
        }
    ],
    "sg:phone":"+1 416 531 5770",
    "sg:postcode":"M6J 1X3",
    "sg:province":"ON",
    "sg:tags":[
        "accountant"
    ],
    "wof:name":"Gaspar, M",
    "wof:placetype":"venue"
},
  "geometry": {"coordinates":[-79.42306518549999,43.649269104],"type":"Point"}
}