{
  "type": "Feature",
  "properties": {
    "addr:full":"610 Niagara St Welland ON L3C 1L8",
    "addr:housenumber":"610",
    "addr:postcode":"l3c 1l8",
    "addr:street":"Niagara St",
    "iso:country":"CA",
    "sg:address":"610 Niagara St",
    "sg:city":"Welland",
    "sg:classifiers":[
        {
            "category":"Manufacturing",
            "subcategory":"Tools & Machinery",
            "type":"Manufacturing & Wholesale Goods"
        }
    ],
    "sg:phone":"+1 905 732 1307",
    "sg:postcode":"L3C 1L8",
    "sg:province":"ON",
    "sg:tags":[
        "equipment",
        "hospital",
        "supply"
    ],
    "wof:name":"Sandstrom Trade & Technology",
    "wof:placetype":"venue"
},
  "geometry": {"coordinates":[-79.250534,43.008076],"type":"Point"}
}