{
  "type": "Feature",
  "properties": {
    "addr:full":"Cote Saint-Luc QC H4W 2T5",
    "addr:postcode":"h4w 2t5",
    "addr:street":"Cote Saint-Luc",
    "iso:country":"CA",
    "sg:city":"Cote Saint-Luc",
    "sg:classifiers":[
        {
            "category":"Cinema",
            "subcategory":"Movie Rental",
            "type":"Entertainment"
        }
    ],
    "sg:phone":"+1 514 486 1278",
    "sg:postcode":"H4W 2T5",
    "sg:province":"QC",
    "sg:tags":[
        "leasing",
        "video",
        "disc",
        "tape"
    ],
    "wof:name":"Superclub Videotron",
    "wof:placetype":"venue"
},
  "geometry": {"coordinates":[-73.661644,45.475979],"type":"Point"}
}