{
  "type": "Feature",
  "properties": {
    "iso:country":"CA",
    "sg:address":"48 Ellen St",
    "sg:city":"Barrie",
    "sg:classifiers":[
        {
            "category":"Personal",
            "type":"Services"
        }
    ],
    "sg:phone":"+1 705 734 9161",
    "sg:postcode":"L4N 3A4",
    "sg:province":"ON",
    "sg:tags":[
        "therapist",
        "massage"
    ],
    "wof:name":"121 Massage Therapy & Bodywork",
    "wof:placetype":"venue"
},
  "geometry": {"coordinates":[-79.6923828125,44.3809738159],"type":"Point"}
}