{
  "type": "Feature",
  "properties": {
    "addr:full":"SW 21 2 3E Dominion City MB R0A 0H0",
    "addr:housenumber":"2 3e",
    "addr:postcode":"r0a 0h0",
    "addr:street":"Sw 21",
    "iso:country":"CA",
    "sg:address":"SW 21 2 3E",
    "sg:city":"Dominion City",
    "sg:classifiers":[
        {
            "category":"Government",
            "subcategory":"Office",
            "type":"Public Place"
        }
    ],
    "sg:phone":"+1 204 427 2610",
    "sg:postcode":"R0A 0H0",
    "sg:province":"MB",
    "wof:name":"Manitoba Maintenance Yard",
    "wof:placetype":"venue"
},
  "geometry": {"coordinates":[-97.1622467041,49.1334648132],"type":"Point"}
}