{
  "type": "Feature",
  "properties": {
    "addr:full":"73 Bay St Kingston ON K7K 1H7",
    "addr:housenumber":"73",
    "addr:postcode":"k7k 1h7",
    "addr:street":"Bay St",
    "iso:country":"CA",
    "sg:address":"73 Bay St",
    "sg:city":"Kingston",
    "sg:classifiers":[
        {
            "category":"Food & Beverages",
            "subcategory":"Groceries & Convenience Stores",
            "type":"Retail Goods"
        }
    ],
    "sg:phone":"+1 613 542 2254",
    "sg:postcode":"K7K 1H7",
    "sg:province":"ON",
    "sg:tags":[
        "grocer"
    ],
    "wof:name":"Cochrane's Grocery",
    "wof:placetype":"venue"
},
  "geometry": {"coordinates":[-76.4841,44.235931],"type":"Point"}
}