{
  "type": "Feature",
  "properties": {
    "addr:full":"1692 Flint St Quesnel BC V2J 4R8",
    "addr:housenumber":"1692",
    "addr:postcode":"v2j 4r8",
    "addr:street":"Flint St",
    "iso:country":"CA",
    "sg:address":"1692 Flint St",
    "sg:city":"Quesnel",
    "sg:classifiers":[
        {
            "category":"Recreation",
            "type":"Entertainment"
        }
    ],
    "sg:phone":"+1 250 747 1358",
    "sg:postcode":"V2J 4R8",
    "sg:province":"BC",
    "sg:tags":[
        "course",
        "golf"
    ],
    "wof:name":"Dragon Lake Golf Course Ltd",
    "wof:placetype":"venue"
},
  "geometry": {"coordinates":[-122.498245,52.978119],"type":"Point"}
}