{
  "type": "Feature",
  "properties": {
    "iso:country":"CA",
    "sg:address":"5235 Rue DE LA Savane",
    "sg:city":"Montreal",
    "sg:classifiers":[
        {
            "category":"Restaurant",
            "type":"Food & Drink"
        }
    ],
    "sg:phone":"+1 514 731 7979",
    "sg:postcode":"H4P 1V4",
    "sg:province":"QC",
    "wof:name":"Restaurant Randino",
    "wof:placetype":"venue"
},
  "geometry": {"coordinates":[-73.659386,45.499344],"type":"Point"}
}