{
  "type": "Feature",
  "properties": {
    "iso:country":"CA",
    "sg:address":"1530 Northmount Dr NW",
    "sg:city":"Calgary",
    "sg:classifiers":[
        {
            "category":"Education",
            "subcategory":"Library",
            "type":"Public Place"
        }
    ],
    "sg:phone":"+1 403 221 2029",
    "sg:postcode":"T2L 0G6",
    "sg:province":"AB",
    "wof:name":"Calgary Public Library",
    "wof:placetype":"venue"
},
  "geometry": {"coordinates":[-114.13906900000001,51.096245],"type":"Point"}
}