{
  "type": "Feature",
  "properties": {
    "addr:full":"586 Eglinton Ave E Toronto ON M4P 1P2",
    "addr:housenumber":"586",
    "addr:postcode":"m4p 1p2",
    "addr:street":"Eglinton Ave E",
    "iso:country":"CA",
    "sg:address":"586 Eglinton Ave E",
    "sg:city":"Toronto",
    "sg:classifiers":[
        {
            "category":"Real Estate",
            "subcategory":"Real Estate Agent",
            "type":"Services"
        }
    ],
    "sg:phone":"+1 416 483 1101",
    "sg:postcode":"M4P 1P2",
    "sg:province":"ON",
    "wof:name":"Intercon Realty Inc",
    "wof:placetype":"venue"
},
  "geometry": {"coordinates":[-79.379852,43.710613],"type":"Point"}
}