{
  "type": "Feature",
  "properties": {
    "addr:full":"1153 Lower Lions Club Rd Dundas ON L8S 4K7",
    "addr:housenumber":"1153",
    "addr:postcode":"l8s 4k7",
    "addr:street":"Lower Lions Club Rd",
    "iso:country":"CA",
    "sg:address":"1153 Lower Lions Club Rd",
    "sg:city":"Dundas",
    "sg:classifiers":[
        {
            "category":"Professional",
            "subcategory":"Art Services",
            "type":"Services"
        }
    ],
    "sg:phone":"+1 905 777 8880",
    "sg:postcode":"L8S 4K7",
    "sg:province":"ON",
    "sg:tags":[
        "graphic",
        "designer"
    ],
    "wof:name":"Newton & CO",
    "wof:placetype":"venue"
},
  "geometry": {"coordinates":[-79.952377,43.263779],"type":"Point"}
}