{
  "type": "Feature",
  "properties": {
    "addr:full":"682 Second Line E Sault Ste Marie ON P6B 4K3",
    "addr:housenumber":"682",
    "addr:postcode":"p6b 4k3",
    "addr:street":"Second Line E",
    "iso:country":"CA",
    "sg:address":"682 Second Line E",
    "sg:city":"Sault Ste Marie",
    "sg:classifiers":[
        {
            "category":"Home & Garden",
            "subcategory":"Furniture",
            "type":"Retail Goods"
        }
    ],
    "sg:phone":"+1 705 946 2510",
    "sg:postcode":"P6B 4K3",
    "sg:province":"ON",
    "wof:name":"Leon's Furniture Ltd",
    "wof:placetype":"venue"
},
  "geometry": {"coordinates":[-84.3182601929,46.5385398865],"type":"Point"}
}