{
  "type": "Feature",
  "properties": {
    "addr:full":"Hwy 21 Bayfield ON N0M 1G0",
    "addr:postcode":"n0m 1g0",
    "addr:street":"Hwy 21",
    "iso:country":"CA",
    "sg:address":"Hwy 21",
    "sg:city":"Bayfield",
    "sg:classifiers":[
        {
            "category":"Food & Beverages",
            "subcategory":"Groceries & Convenience Stores",
            "type":"Retail Goods"
        }
    ],
    "sg:phone":"+1 519 565 2727",
    "sg:postcode":"N0M 1G0",
    "sg:province":"ON",
    "sg:tags":[
        "grocer"
    ],
    "wof:name":"Bayfield Foodland",
    "wof:placetype":"venue"
},
  "geometry": {"coordinates":[-81.705376,43.575764],"type":"Point"}
}