{
  "type": "Feature",
  "properties": {
    "addr:full":"15584 Cabot Trail Hwy Cheticamp NS B0E 1H0",
    "addr:housenumber":"15584",
    "addr:postcode":"b0e 1h0",
    "addr:street":"Cabot Trail Hwy",
    "iso:country":"CA",
    "sg:address":"15584 Cabot Trail Hwy",
    "sg:city":"Cheticamp",
    "sg:classifiers":[
        {
            "category":"Travel",
            "subcategory":"Travel Agent",
            "type":"Entertainment"
        }
    ],
    "sg:phone":"+1 902 224 2642",
    "sg:postcode":"B0E 1H0",
    "sg:province":"NS",
    "sg:tags":[
        "information",
        "tourist"
    ],
    "wof:name":"Societe St Pierre Les Trois",
    "wof:placetype":"venue"
},
  "geometry": {"coordinates":[-61.002121,46.6423],"type":"Point"}
}