{
  "type": "Feature",
  "properties": {
    "addr:full":"15 Morenz Dr Stratford ON N5A 6W5",
    "addr:housenumber":"15",
    "addr:postcode":"n5a 6w5",
    "addr:street":"Morenz Dr",
    "iso:country":"CA",
    "sg:address":"15 Morenz Dr",
    "sg:city":"Stratford",
    "sg:classifiers":[
        {
            "category":"Arena",
            "subcategory":"Sports Club",
            "type":"Entertainment"
        }
    ],
    "sg:phone":"+1 519 271 2161",
    "sg:postcode":"N5A 6W5",
    "sg:province":"ON",
    "sg:tags":[
        "athletic",
        "fields",
        "stadium",
        "government"
    ],
    "wof:name":"William Allman Memorial Arena",
    "wof:placetype":"venue"
},
  "geometry": {"coordinates":[-80.976471,43.374088],"type":"Point"}
}