{
  "type": "Feature",
  "properties": {
    "addr:full":"2841 Dewdney Ave Victoria BC V8R 3M5",
    "addr:housenumber":"2841",
    "addr:postcode":"v8r 3m5",
    "addr:street":"Dewdney Ave",
    "iso:country":"CA",
    "sg:address":"2841 Dewdney Ave",
    "sg:city":"Victoria",
    "sg:classifiers":[
        {
            "category":"Social Services",
            "type":"Services"
        }
    ],
    "sg:phone":"+1 250 598 5889",
    "sg:postcode":"V8R 3M5",
    "sg:province":"BC",
    "sg:tags":[
        "counselor"
    ],
    "wof:name":"Ambery, Peter",
    "wof:placetype":"venue"
},
  "geometry": {"coordinates":[-123.364517212,48.428314209],"type":"Point"}
}