{
  "type": "Feature",
  "properties": {
    "addr:full":"Toronto ON M5R 2M8",
    "addr:postcode":"m5r 2m8",
    "iso:country":"CA",
    "sg:city":"Toronto",
    "sg:classifiers":[
        {
            "category":"Health Services",
            "subcategory":"Doctor",
            "type":"Services"
        }
    ],
    "sg:phone":"+1 416 922 5306",
    "sg:postcode":"M5R 2M8",
    "sg:province":"ON",
    "sg:tags":[
        "dentist"
    ],
    "wof:name":"Martin, Ronald F DDS",
    "wof:placetype":"venue"
},
  "geometry": {"coordinates":[-79.400093,43.66769],"type":"Point"}
}