{
  "type": "Feature",
  "properties": {
    "addr:full":"1598 Queen St E Toronto ON M4L 1G2",
    "addr:housenumber":"1598",
    "addr:postcode":"m4l 1g2",
    "addr:street":"Queen St E",
    "iso:country":"CA",
    "sg:address":"1598 Queen St E",
    "sg:city":"Toronto",
    "sg:classifiers":[
        {
            "category":"Wholesale",
            "subcategory":"Non-durable Goods",
            "type":"Manufacturing & Wholesale Goods"
        }
    ],
    "sg:phone":"+1 416 461 3391",
    "sg:postcode":"M4L 1G2",
    "sg:province":"ON",
    "sg:tags":[
        "leather",
        "clothing"
    ],
    "wof:name":"Ashbridges Leather Emporium",
    "wof:placetype":"venue"
},
  "geometry": {"coordinates":[-79.3173751831,43.6662864685],"type":"Point"}
}