{
  "type": "Feature",
  "properties": {
    "addr:full":"9775 Chemainus Rd Chemainus BC V0R 1K0",
    "addr:housenumber":"9775",
    "addr:postcode":"v0r 1k0",
    "addr:street":"Chemainus Rd",
    "iso:country":"CA",
    "sg:address":"9775 Chemainus Rd",
    "sg:city":"Chemainus",
    "sg:classifiers":[
        {
            "category":"Organizations",
            "subcategory":"Community Association",
            "type":"Services"
        }
    ],
    "sg:phone":"+1 250 246 4532",
    "sg:postcode":"V0R 1K0",
    "sg:province":"BC",
    "sg:tags":[
        "fraternal"
    ],
    "wof:name":"Royal Canadian Legion",
    "wof:placetype":"venue"
},
  "geometry": {"coordinates":[-123.719032,48.922379],"type":"Point"}
}