{
  "type": "Feature",
  "properties": {
    "addr:full":"1222 3 Ave S Lethbridge AB T1J 0J9",
    "addr:housenumber":"1222",
    "addr:postcode":"t1j 0j9",
    "addr:street":"3 Ave S",
    "iso:country":"CA",
    "sg:address":"1222 3 Ave S",
    "sg:city":"Lethbridge",
    "sg:classifiers":[
        {
            "category":"Professional",
            "subcategory":"Computer Services",
            "type":"Services"
        }
    ],
    "sg:phone":"+1 403 317 1969",
    "sg:postcode":"T1J 0J9",
    "sg:province":"AB",
    "sg:tags":[
        "website",
        "repair",
        "design"
    ],
    "wof:name":"Phoenix Rising Unlimited",
    "wof:placetype":"venue"
},
  "geometry": {"coordinates":[-112.827438,49.696259],"type":"Point"}
}