{
  "type": "Feature",
  "properties": {
    "addr:full":"Sainte-Adele QC J8B 1C9",
    "addr:postcode":"j8b 1c9",
    "iso:country":"CA",
    "sg:city":"Sainte-Adele",
    "sg:classifiers":[
        {
            "category":"Real Estate",
            "subcategory":"Real Estate Agent",
            "type":"Services"
        }
    ],
    "sg:phone":"+1 450 229 9942",
    "sg:postcode":"J8B 1C9",
    "sg:province":"QC",
    "sg:tags":[
        "development",
        "economic",
        "agency"
    ],
    "wof:name":"Corporation Du Parc D'Affaires",
    "wof:placetype":"venue"
},
  "geometry": {"coordinates":[-74.128136,45.935539],"type":"Point"}
}