{
  "type": "Feature",
  "properties": {
    "addr:full":"1840 Birchmount Rd Scarborough ON M1P 2H7",
    "addr:housenumber":"1840",
    "addr:postcode":"m1p 2h7",
    "addr:street":"Birchmount Rd",
    "iso:country":"CA",
    "sg:address":"1840 Birchmount Rd",
    "sg:city":"Scarborough",
    "sg:classifiers":[
        {
            "category":"Manufacturing",
            "subcategory":"Printing",
            "type":"Manufacturing & Wholesale Goods"
        }
    ],
    "sg:phone":"+1 416 321 2333",
    "sg:postcode":"M1P 2H7",
    "sg:province":"ON",
    "sg:tags":[
        "bookbinder"
    ],
    "wof:name":"Eastend Bindery Ltd",
    "wof:placetype":"venue"
},
  "geometry": {"coordinates":[-79.2921829224,43.7670478821],"type":"Point"}
}