{
  "type": "Feature",
  "properties": {
    "iso:country":"CA",
    "sg:address":"13 Rue Robert",
    "sg:city":"Repentigny",
    "sg:classifiers":[
        {
            "category":"Building & Trades",
            "subcategory":"Landscaping Services",
            "type":"Services"
        }
    ],
    "sg:phone":"+1 450 585 5845",
    "sg:postcode":"J6A 3E5",
    "sg:province":"QC",
    "sg:tags":[
        "tree",
        "landscape",
        "contractor"
    ],
    "wof:name":"G H Svc D'Arbres",
    "wof:placetype":"venue"
},
  "geometry": {"coordinates":[-73.4680557251,45.7170677185],"type":"Point"}
}