{
  "type": "Feature",
  "properties": {
    "addr:full":"25 Curity Ave East York ON M4B 3M2",
    "addr:housenumber":"25",
    "addr:postcode":"m4b 3m2",
    "addr:street":"Curity Ave",
    "iso:country":"CA",
    "sg:address":"25 Curity Ave",
    "sg:city":"East York",
    "sg:classifiers":[
        {
            "category":"Wholesale",
            "subcategory":"Durable Goods & Equipment",
            "type":"Manufacturing & Wholesale Goods"
        }
    ],
    "sg:phone":"+1 416 532 4233",
    "sg:postcode":"M4B 3M2",
    "sg:province":"ON",
    "sg:tags":[
        "importer"
    ],
    "wof:name":"Mandalay Box CO",
    "wof:placetype":"venue"
},
  "geometry": {"coordinates":[-79.31671142579999,43.7101211548],"type":"Point"}
}