{
  "type": "Feature",
  "properties": {
    "addr:full":"1355 Kingston Rd # 119A Pickering ON L1V 1B8",
    "addr:housenumber":"1355",
    "addr:postcode":"l1v 1b8",
    "addr:street":"Kingston Rd # 119A",
    "iso:country":"CA",
    "sg:address":"1355 Kingston Rd # 119A",
    "sg:city":"Pickering",
    "sg:classifiers":[
        {
            "category":"Travel",
            "subcategory":"Travel Agent",
            "type":"Entertainment"
        }
    ],
    "sg:phone":"+1 905 420 3233",
    "sg:postcode":"L1V 1B8",
    "sg:province":"ON",
    "sg:tags":[
        "agency",
        "bureau"
    ],
    "wof:name":"Goliger's Travel Plus",
    "wof:placetype":"venue"
},
  "geometry": {"coordinates":[-79.087242,43.837971],"type":"Point"}
}