{
  "type": "Feature",
  "properties": {
    "addr:full":"Evansburg AB T0E 0T0",
    "addr:postcode":"t0e 0t0",
    "iso:country":"CA",
    "sg:city":"Evansburg",
    "sg:classifiers":[
        {
            "category":"Professional",
            "subcategory":"Accounting & Tax Preparation",
            "type":"Services"
        }
    ],
    "sg:phone":"+1 780 727 3553",
    "sg:postcode":"T0E 0T0",
    "sg:province":"AB",
    "sg:tags":[
        "accountant"
    ],
    "wof:name":"Complete Accounting",
    "wof:placetype":"venue"
},
  "geometry": {"coordinates":[-115.01863899999999,53.601105],"type":"Point"}
}