{
  "type": "Feature",
  "properties": {
    "addr:full":"448 Rue Laurier Asbestos QC J1T 2H6",
    "addr:housenumber":"448",
    "addr:postcode":"j1t 2h6",
    "addr:street":"Rue Laurier",
    "iso:country":"CA",
    "sg:address":"448 Rue Laurier",
    "sg:city":"Asbestos",
    "sg:classifiers":[
        {
            "category":"Personal",
            "subcategory":"Beauty Salon",
            "type":"Services"
        }
    ],
    "sg:phone":"+1 819 879 2792",
    "sg:postcode":"J1T 2H6",
    "sg:province":"QC",
    "wof:name":"Esthetique Toi & Moi Enr",
    "wof:placetype":"venue"
},
  "geometry": {"coordinates":[-71.93402862550001,45.7671051025],"type":"Point"}
}