{
  "type": "Feature",
  "properties": {
    "addr:full":"Kelowna BC V1Z 3X4",
    "addr:postcode":"v1z 3x4",
    "iso:country":"CA",
    "sg:city":"Kelowna",
    "sg:classifiers":[
        {
            "category":"Home & Garden",
            "subcategory":"Home Furnishings",
            "type":"Retail Goods"
        }
    ],
    "sg:phone":"+1 250 769 2878",
    "sg:postcode":"V1Z 3X4",
    "sg:province":"BC",
    "sg:tags":[
        "venetian",
        "paint"
    ],
    "wof:name":"Color Your World",
    "wof:placetype":"venue"
},
  "geometry": {"coordinates":[-119.577629089,49.8623199463],"type":"Point"}
}