{
  "type": "Feature",
  "properties": {
    "addr:full":"91 Cornelia St W Smiths Falls ON K7A 5L3",
    "addr:housenumber":"91",
    "addr:postcode":"k7a 5l3",
    "addr:street":"Cornelia St W",
    "iso:country":"CA",
    "sg:address":"91 Cornelia St W",
    "sg:city":"Smiths Falls",
    "sg:classifiers":[
        {
            "category":"Health Services",
            "subcategory":"Doctor",
            "type":"Services"
        }
    ],
    "sg:phone":"+1 613 283 1142",
    "sg:postcode":"K7A 5L3",
    "sg:province":"ON",
    "sg:tags":[
        "physician",
        "surgeon"
    ],
    "wof:name":"Shew, Raphael E MD",
    "wof:placetype":"venue"
},
  "geometry": {"coordinates":[-76.02568817140001,44.9063873291],"type":"Point"}
}