{
  "type": "Feature",
  "properties": {
    "addr:full":"2791 St Patrick's Dr Windsor ON N9E 3G5",
    "addr:housenumber":"2791",
    "addr:postcode":"n9e 3g5",
    "addr:street":"St Patrick'S Dr",
    "iso:country":"CA",
    "sg:address":"2791 St Patrick's Dr",
    "sg:city":"Windsor",
    "sg:classifiers":[
        {
            "category":"Professional",
            "subcategory":"Accounting & Tax Preparation",
            "type":"Services"
        }
    ],
    "sg:phone":"+1 519 969 0975",
    "sg:postcode":"N9E 3G5",
    "sg:province":"ON",
    "sg:tags":[
        "bookkeeping",
        "general"
    ],
    "wof:name":"Adanac Bookkeeping Svc Ltd",
    "wof:placetype":"venue"
},
  "geometry": {"coordinates":[-83.069427,42.291786],"type":"Point"}
}