{
  "type": "Feature",
  "properties": {
    "addr:full":"1889 Rue Beaubien E Montreal QC H2G 1L8",
    "addr:housenumber":"1889",
    "addr:postcode":"h2g 1l8",
    "addr:street":"Rue Beaubien E",
    "iso:country":"CA",
    "sg:address":"1889 Rue Beaubien E",
    "sg:city":"Montreal",
    "sg:classifiers":[
        {
            "category":"Recreation",
            "type":"Entertainment"
        }
    ],
    "sg:phone":"+1 514 727 5376",
    "sg:postcode":"H2G 1L8",
    "sg:province":"QC",
    "sg:tags":[
        "martial",
        "arts",
        "instruction"
    ],
    "wof:name":"Academie Du Kenpo Yannick Gren",
    "wof:placetype":"venue"
},
  "geometry": {"coordinates":[-73.59600830079999,45.5441055298],"type":"Point"}
}