{
  "type": "Feature",
  "properties": {
    "iso:country":"CA",
    "sg:city":"Laval",
    "sg:classifiers":[
        {
            "category":"Professional",
            "subcategory":"Lawyer & Legal Services",
            "type":"Services"
        }
    ],
    "sg:phone":"+1 450 668 0888",
    "sg:postcode":"H7N 1A1",
    "sg:province":"QC",
    "sg:tags":[
        "attorney"
    ],
    "wof:name":"Cholette Savard",
    "wof:placetype":"venue"
},
  "geometry": {"coordinates":[-73.70517,45.581211],"type":"Point"}
}