{
  "type": "Feature",
  "properties": {
    "addr:full":"36 Knowles Cres Aurora ON L4G 1Z7",
    "addr:housenumber":"36",
    "addr:postcode":"l4g 1z7",
    "addr:street":"Knowles Cres",
    "iso:country":"CA",
    "sg:address":"36 Knowles Cres",
    "sg:city":"Aurora",
    "sg:classifiers":[
        {
            "category":"Building & Trades",
            "subcategory":"Construction",
            "type":"Services"
        }
    ],
    "sg:phone":"+1 905 727 6745",
    "sg:postcode":"L4G 1Z7",
    "sg:province":"ON",
    "sg:tags":[
        "painter"
    ],
    "wof:name":"Dave Taylor Painting & Decor",
    "wof:placetype":"venue"
},
  "geometry": {"coordinates":[-79.48086499999999,43.981167],"type":"Point"}
}