{
  "type": "Feature",
  "properties": {
    "addr:full":"RR 2 STN Main Renfrew ON K7V 3Z5",
    "addr:postcode":"k7v 3z5",
    "addr:street":"Rr 2 Stn Main",
    "iso:country":"CA",
    "sg:address":"RR 2 STN Main",
    "sg:city":"Renfrew",
    "sg:classifiers":[
        {
            "category":"Manufacturing",
            "subcategory":"Lumber",
            "type":"Manufacturing & Wholesale Goods"
        }
    ],
    "sg:phone":"+1 613 432 5209",
    "sg:postcode":"K7V 3Z5",
    "sg:province":"ON",
    "sg:tags":[
        "forester"
    ],
    "wof:name":"Opeongo Forestry Svc",
    "wof:placetype":"venue"
},
  "geometry": {"coordinates":[-76.68695099999999,45.474178],"type":"Point"}
}