{
  "type": "Feature",
  "properties": {
    "addr:full":"SE 17-3-5W Morden MB R6M 1B5",
    "addr:postcode":"r6m 1b5",
    "addr:street":"Se 17-3-5W",
    "iso:country":"CA",
    "sg:address":"SE 17-3-5W",
    "sg:city":"Morden",
    "sg:classifiers":[
        {
            "category":"Building & Trades",
            "subcategory":"Electrical",
            "type":"Services"
        }
    ],
    "sg:phone":"+1 204 822 5389",
    "sg:postcode":"R6M 1B5",
    "sg:province":"MB",
    "sg:tags":[
        "electric",
        "contractor"
    ],
    "wof:name":"Bergman Electric",
    "wof:placetype":"venue"
},
  "geometry": {"coordinates":[-98.113022,49.192284],"type":"Point"}
}