{
  "type": "Feature",
  "properties": {
    "addr:full":"230 Export Blvd Mississauga ON L5S 1Z1",
    "addr:housenumber":"230",
    "addr:postcode":"l5s 1z1",
    "addr:street":"Export Blvd",
    "iso:country":"CA",
    "sg:address":"230 Export Blvd",
    "sg:city":"Mississauga",
    "sg:classifiers":[
        {
            "category":"Wholesale",
            "subcategory":"Apparel",
            "type":"Manufacturing & Wholesale Goods"
        }
    ],
    "sg:phone":"+1 905 696 9950",
    "sg:postcode":"L5S 1Z1",
    "sg:province":"ON",
    "sg:tags":[
        "t"
    ],
    "wof:name":"Alstyle Apparel",
    "wof:placetype":"venue"
},
  "geometry": {"coordinates":[-79.703247,43.651299],"type":"Point"}
}