{
  "type": "Feature",
  "properties": {
    "iso:country":"CA",
    "sg:address":"2847 Lawrence Ave E",
    "sg:city":"Scarborough",
    "sg:classifiers":[
        {
            "category":"Restaurant",
            "type":"Food & Drink"
        }
    ],
    "sg:phone":"+1 416 264 2232",
    "sg:postcode":"M1P 2S8",
    "sg:province":"ON",
    "sg:tags":[
        "caterer"
    ],
    "wof:name":"Ahmuthasurabi",
    "wof:placetype":"venue"
},
  "geometry": {"coordinates":[-79.2549362183,43.7534484863],"type":"Point"}
}