{
  "type": "Feature",
  "properties": {
    "addr:full":"445 28 Ave NW Calgary AB T2M 2K7",
    "addr:postcode":"445;t2m 2k7",
    "addr:street":"28 Ave Nw",
    "iso:country":"CA",
    "sg:address":"445 28 Ave NW",
    "sg:city":"Calgary",
    "sg:classifiers":[
        {
            "category":"Professional",
            "subcategory":"Art Services",
            "type":"Services"
        }
    ],
    "sg:phone":"+1 403 277 0696",
    "sg:postcode":"T2M 2K7",
    "sg:province":"AB",
    "sg:tags":[
        "graphic",
        "designer"
    ],
    "wof:name":"Page Dynamics Graphic Design",
    "wof:placetype":"venue"
},
  "geometry": {"coordinates":[-114.069358826,51.0777015686],"type":"Point"}
}