{
  "type": "Feature",
  "properties": {
    "addr:full":"926 Queen St Kincardine ON N2Z 2Y2",
    "addr:housenumber":"926",
    "addr:postcode":"n2z 2y2",
    "addr:street":"Queen St",
    "iso:country":"CA",
    "sg:address":"926 Queen St",
    "sg:city":"Kincardine",
    "sg:classifiers":[
        {
            "category":"Insurance",
            "subcategory":"Insurance Agent",
            "type":"Services"
        }
    ],
    "sg:phone":"+1 519 396 3465",
    "sg:postcode":"N2Z 2Y2",
    "sg:province":"ON",
    "wof:name":"Miller Insurance Brokers Inc",
    "wof:placetype":"venue"
},
  "geometry": {"coordinates":[-81.6330795288,44.1801567078],"type":"Point"}
}