{
  "type": "Feature",
  "properties": {
    "addr:full":"6844 Rue Choisy Saint-Leonard QC H1T 2J5",
    "addr:housenumber":"6844",
    "addr:postcode":"h1t 2j5",
    "addr:street":"Rue Choisy",
    "iso:country":"CA",
    "sg:address":"6844 Rue Choisy",
    "sg:city":"Saint-Leonard",
    "sg:classifiers":[
        {
            "category":"Building & Trades",
            "subcategory":"Landscaping Services",
            "type":"Services"
        }
    ],
    "sg:phone":"+1 514 254 8896",
    "sg:postcode":"H1T 2J5",
    "sg:province":"QC",
    "sg:tags":[
        "landscape",
        "contractor"
    ],
    "wof:name":"Paysage Concorde Inc",
    "wof:placetype":"venue"
},
  "geometry": {"coordinates":[-73.569908,45.582623],"type":"Point"}
}