{
  "type": "Feature",
  "properties": {
    "addr:full":"39 1st Ave Clinton ON N0M 1L0",
    "addr:housenumber":"39",
    "addr:postcode":"n0m 1l0",
    "addr:street":"1St Ave",
    "iso:country":"CA",
    "sg:address":"39 1st Ave",
    "sg:city":"Clinton",
    "sg:classifiers":[
        {
            "category":"Organizations",
            "subcategory":"Professional Association",
            "type":"Services"
        }
    ],
    "sg:phone":"+1 519 482 3055",
    "sg:postcode":"N0M 1L0",
    "sg:province":"ON",
    "sg:tags":[
        "club"
    ],
    "wof:name":"Vanastra Curling Club",
    "wof:placetype":"venue"
},
  "geometry": {"coordinates":[-81.53969573969999,43.6176681519],"type":"Point"}
}