{
  "type": "Feature",
  "properties": {
    "addr:full":"Winnipeg MB R2X 3A6",
    "addr:postcode":"r2x 3a6",
    "iso:country":"CA",
    "sg:city":"Winnipeg",
    "sg:classifiers":[
        {
            "category":"Shopping",
            "type":"Retail Goods"
        }
    ],
    "sg:phone":"+1 204 334 8600",
    "sg:postcode":"R2X 3A6",
    "sg:province":"MB",
    "sg:tags":[
        "pet",
        "food",
        "supply"
    ],
    "wof:name":"Pet Valu",
    "wof:placetype":"venue"
},
  "geometry": {"coordinates":[-97.1590957642,49.9398765564],"type":"Point"}
}