{
  "type": "Feature",
  "properties": {
    "iso:country":"CA",
    "sg:address":"635 LA Verendrye Dr",
    "sg:city":"Gloucester",
    "sg:classifiers":[
        {
            "category":"Education",
            "subcategory":"School",
            "type":"Public Place"
        }
    ],
    "sg:phone":"+1 613 749 2251",
    "sg:postcode":"K1J 7C2",
    "sg:province":"ON",
    "wof:name":"Thomas D'Arcy Mc Gee Catholic",
    "wof:placetype":"venue"
},
  "geometry": {"coordinates":[-75.605461,45.454819],"type":"Point"}
}