{
  "type": "Feature",
  "properties": {
    "addr:full":"9023 72 St Fort St John BC V1J 4J2",
    "addr:housenumber":"9023",
    "addr:postcode":"v1j 4j2",
    "addr:street":"72 St",
    "iso:country":"CA",
    "sg:address":"9023 72 St",
    "sg:city":"Fort St John",
    "sg:phone":"+1 250 785 6758",
    "sg:postcode":"V1J 4J2",
    "sg:province":"BC",
    "sg:tags":[
        "company",
        "oil",
        "petroleum",
        "product"
    ],
    "wof:name":"Northern Peace Petroleums",
    "wof:placetype":"venue"
},
  "geometry": {"coordinates":[-120.847458,56.252464],"type":"Point"}
}