{
  "type": "Feature",
  "properties": {
    "addr:full":"1352 100th St North Battleford SK S9A 0V8",
    "addr:housenumber":"1352",
    "addr:postcode":"s9a 0v8",
    "addr:street":"100Th St",
    "iso:country":"CA",
    "sg:address":"1352 100th St",
    "sg:city":"North Battleford",
    "sg:classifiers":[
        {
            "category":"Organizations",
            "subcategory":"Community Association",
            "type":"Services"
        }
    ],
    "sg:phone":"+1 306 445 2173",
    "sg:postcode":"S9A 0V8",
    "sg:province":"SK",
    "sg:tags":[
        "club"
    ],
    "wof:name":"Royal Canadian Legion",
    "wof:placetype":"venue"
},
  "geometry": {"coordinates":[-108.298828125,52.7773323059],"type":"Point"}
}