{
  "type": "Feature",
  "properties": {
    "addr:full":"34 Potts Rd Simcoe ON N3Y 2S8",
    "addr:housenumber":"34",
    "addr:postcode":"n3y 2s8",
    "addr:street":"Potts Rd",
    "iso:country":"CA",
    "sg:address":"34 Potts Rd",
    "sg:city":"Simcoe",
    "sg:classifiers":[
        {
            "category":"Education",
            "subcategory":"School",
            "type":"Public Place"
        }
    ],
    "sg:phone":"+1 519 426 0820",
    "sg:postcode":"N3Y 2S8",
    "sg:province":"ON",
    "wof:name":"St Joseph's School",
    "wof:placetype":"venue"
},
  "geometry": {"coordinates":[-80.29462432859999,42.8332901001],"type":"Point"}
}