{
  "type": "Feature",
  "properties": {
    "addr:full":"Longueuil QC J4K 2V1",
    "addr:postcode":"j4k 2v1",
    "iso:country":"CA",
    "sg:city":"Longueuil",
    "sg:classifiers":[
        {
            "category":"Shopping",
            "subcategory":"Clothing, Apparel, & Fashions",
            "type":"Retail Goods"
        }
    ],
    "sg:phone":"+1 450 677 8943",
    "sg:postcode":"J4K 2V1",
    "sg:province":"QC",
    "sg:tags":[
        "machine",
        "dressmaker",
        "sewing"
    ],
    "wof:name":"Atelier DE Couture Tremblay",
    "wof:placetype":"venue"
},
  "geometry": {"coordinates":[-73.51357299999999,45.528343],"type":"Point"}
}