{
  "type": "Feature",
  "properties": {
    "iso:country":"CA",
    "sg:address":"312 Lillooet Ave",
    "sg:city":"Harrison Hot Springs",
    "sg:classifiers":[
        {
            "category":"Travel",
            "subcategory":"Hotels & Motels",
            "type":"Entertainment"
        }
    ],
    "sg:phone":"+1 604 796 9552",
    "sg:postcode":"V0M 1K0",
    "sg:province":"BC",
    "sg:tags":[
        "breakfast",
        "accommodation",
        "bed"
    ],
    "wof:name":"Harrison Hertiage House",
    "wof:placetype":"venue"
},
  "geometry": {"coordinates":[-121.782249451,49.3022422791],"type":"Point"}
}