{
  "type": "Feature",
  "properties": {
    "addr:full":"New Hazelton BC V0J 2J0",
    "addr:postcode":"v0j 2j0",
    "iso:country":"CA",
    "sg:city":"New Hazelton",
    "sg:classifiers":[
        {
            "category":"Retail",
            "subcategory":"Auto Repair",
            "type":"Services"
        }
    ],
    "sg:phone":"+1 250 847 9551",
    "sg:postcode":"V0J 2J0",
    "sg:province":"BC",
    "sg:tags":[
        "body",
        "automobile",
        "painting"
    ],
    "wof:name":"Bernie's Kustom Auto Body",
    "wof:placetype":"venue"
},
  "geometry": {"coordinates":[-127.643867493,55.2642593384],"type":"Point"}
}