{
  "type": "Feature",
  "properties": {
    "addr:full":"319 Ch Hormidas Bondu Notre-Dame-DE-Pontmain QC J0W 1S0",
    "addr:housenumber":"319",
    "addr:postcode":"j0w 1s0",
    "addr:street":"Ch Hormidas Bondu",
    "iso:country":"CA",
    "sg:address":"319 Ch Hormidas Bondu",
    "sg:city":"Notre-Dame-DE-Pontmain",
    "sg:classifiers":[
        {
            "category":"Manufacturing",
            "subcategory":"Lumber",
            "type":"Manufacturing & Wholesale Goods"
        }
    ],
    "sg:phone":"+1 819 597 2481",
    "sg:postcode":"J0W 1S0",
    "sg:province":"QC",
    "sg:tags":[
        "sawmill"
    ],
    "wof:name":"Scierie Bondu Inc",
    "wof:placetype":"venue"
},
  "geometry": {"coordinates":[-75.62951700000001,46.32975],"type":"Point"}
}