{
  "type": "Feature",
  "properties": {
    "addr:full":"6914 76 Ave NW Edmonton AB T6B 2R2",
    "addr:housenumber":"6914",
    "addr:postcode":"t6b 2r2",
    "addr:street":"76 Ave Nw",
    "iso:country":"CA",
    "sg:address":"6914 76 Ave NW",
    "sg:city":"Edmonton",
    "sg:classifiers":[
        {
            "category":"Manufacturing",
            "subcategory":"Furniture",
            "type":"Manufacturing & Wholesale Goods"
        }
    ],
    "sg:phone":"+1 780 944 6801",
    "sg:postcode":"T6B 2R2",
    "sg:province":"AB",
    "wof:name":"Oak Tables Plus Mfg Inc",
    "wof:placetype":"venue"
},
  "geometry": {"coordinates":[-113.433990478,53.512424469],"type":"Point"}
}