{
  "type": "Feature",
  "properties": {
    "iso:country":"CA",
    "sg:address":"1299 Rue Beaubien E",
    "sg:city":"Montreal",
    "sg:classifiers":[
        {
            "category":"Health Services",
            "subcategory":"Doctor",
            "type":"Services"
        }
    ],
    "sg:phone":"+1 514 279 3636",
    "sg:postcode":"H2S 1V1",
    "sg:province":"QC",
    "sg:tags":[
        "dentist"
    ],
    "wof:name":"Clinique Dentaire Raja Hanna",
    "wof:placetype":"venue"
},
  "geometry": {"coordinates":[-73.5997085571,45.5399398804],"type":"Point"}
}