{
  "type": "Feature",
  "properties": {
    "iso:country":"CA",
    "sg:address":"2328 Government St",
    "sg:city":"Victoria",
    "sg:classifiers":[
        {
            "category":"Freight",
            "type":"Transportation"
        }
    ],
    "sg:phone":"+1 250 384 3935",
    "sg:postcode":"V8T 5G5",
    "sg:province":"BC",
    "sg:tags":[
        "mover"
    ],
    "wof:name":"Allison Piano",
    "wof:placetype":"venue"
},
  "geometry": {"coordinates":[-123.36753845200001,48.4346656799],"type":"Point"}
}