{
  "type": "Feature",
  "properties": {
    "iso:country":"CA",
    "sg:address":"1489 Elgin Ave W",
    "sg:city":"Winnipeg",
    "sg:classifiers":[
        {
            "category":"Food & Beverages",
            "subcategory":"Groceries & Convenience Stores",
            "type":"Retail Goods"
        }
    ],
    "sg:phone":"+1 204 774 3328",
    "sg:postcode":"R3E 1B9",
    "sg:province":"MB",
    "sg:tags":[
        "grocer"
    ],
    "wof:name":"Kelly's Food Market",
    "wof:placetype":"venue"
},
  "geometry": {"coordinates":[-97.18836212159999,49.915977478],"type":"Point"}
}