{
  "type": "Feature",
  "properties": {
    "addr:full":"35 Rue Saint-Jacques Montreal QC H2Y 1K9",
    "addr:housenumber":"35",
    "addr:postcode":"h2y 1k9",
    "addr:street":"Rue Saint-Jacques",
    "iso:country":"CA",
    "sg:address":"35 Rue Saint-Jacques",
    "sg:city":"Montreal",
    "sg:classifiers":[
        {
            "category":"Freight",
            "type":"Transportation"
        }
    ],
    "sg:phone":"+1 514 285 7600",
    "sg:postcode":"H2Y 1K9",
    "sg:province":"QC",
    "sg:tags":[
        "broker",
        "customs"
    ],
    "wof:name":"Schenker Du Canada Ltee",
    "wof:placetype":"venue"
},
  "geometry": {"coordinates":[-73.55693817140001,45.5060577393],"type":"Point"}
}