{
  "type": "Feature",
  "properties": {
    "addr:full":"662 Argyle Sound Rd Pubnico NS B0W 2W0",
    "addr:housenumber":"662",
    "addr:postcode":"b0w 2w0",
    "addr:street":"Argyle Sound Rd",
    "iso:country":"CA",
    "sg:address":"662 Argyle Sound Rd",
    "sg:city":"Pubnico",
    "sg:classifiers":[
        {
            "category":"Manufacturing",
            "subcategory":"Watercraft",
            "type":"Manufacturing & Wholesale Goods"
        }
    ],
    "sg:phone":"+1 902 762 0247",
    "sg:postcode":"B0W 2W0",
    "sg:province":"NS",
    "sg:tags":[
        "boat"
    ],
    "wof:name":"Idle Oars Boatbuilders Ltd",
    "wof:placetype":"venue"
},
  "geometry": {"coordinates":[-65.782501,43.703033],"type":"Point"}
}