{
  "type": "Feature",
  "properties": {
    "iso:country":"CA",
    "sg:address":"7651 18th Ave",
    "sg:city":"Burnaby",
    "sg:classifiers":[
        {
            "category":"Education",
            "subcategory":"School",
            "type":"Public Place"
        }
    ],
    "sg:phone":"+1 604 664 8683",
    "sg:postcode":"V3N 1J1",
    "sg:province":"BC",
    "wof:name":"Edmonds Community School",
    "wof:placetype":"venue"
},
  "geometry": {"coordinates":[-122.94056701700001,49.2221832275],"type":"Point"}
}