{
  "type": "Feature",
  "properties": {
    "addr:full":"341 Rte DE LA Mer Sainte-Flavie QC G0J 2L0",
    "addr:housenumber":"341",
    "addr:postcode":"g0j 2l0",
    "addr:street":"Rte De La Mer",
    "iso:country":"CA",
    "sg:address":"341 Rte DE LA Mer",
    "sg:city":"Sainte-Flavie",
    "sg:classifiers":[
        {
            "category":"Building & Trades",
            "subcategory":"Construction",
            "type":"Services"
        }
    ],
    "sg:phone":"+1 418 775 8162",
    "sg:postcode":"G0J 2L0",
    "sg:province":"QC",
    "sg:tags":[
        "resurfacing",
        "laying",
        "refinishing",
        "floor"
    ],
    "wof:name":"Dany Castonguay Enr",
    "wof:placetype":"venue"
},
  "geometry": {"coordinates":[-68.253525,48.600658],"type":"Point"}
}