{
  "type": "Feature",
  "properties": {
    "addr:full":"Beauport QC G1C 3P9",
    "addr:postcode":"qc g1c 3p9",
    "iso:country":"CA",
    "sg:city":"Beauport",
    "sg:classifiers":[
        {
            "category":"Personal",
            "subcategory":"Beauty Salon",
            "type":"Services"
        }
    ],
    "sg:phone":"+1 418 666 4010",
    "sg:postcode":"G1C 3P9",
    "sg:province":"QC",
    "wof:name":"Haute Coiffure Lavoy Inc",
    "wof:placetype":"venue"
},
  "geometry": {"coordinates":[-71.202843,46.881535],"type":"Point"}
}