{
  "type": "Feature",
  "properties": {
    "addr:full":"1256 Rue Saint-Nicolas Laval QC H7E 4X3",
    "addr:housenumber":"1256",
    "addr:postcode":"h7e 4x3",
    "addr:street":"Rue Saint-Nicolas",
    "iso:country":"CA",
    "sg:address":"1256 Rue Saint-Nicolas",
    "sg:city":"Laval",
    "sg:classifiers":[
        {
            "category":"Wholesale",
            "subcategory":"Machinery & Supplies",
            "type":"Manufacturing & Wholesale Goods"
        }
    ],
    "sg:phone":"+1 450 661 1810",
    "sg:postcode":"H7E 4X3",
    "sg:province":"QC",
    "sg:tags":[
        "plate",
        "printing"
    ],
    "wof:name":"Plaques Express Rcm Inc",
    "wof:placetype":"venue"
},
  "geometry": {"coordinates":[-73.67038700000001,45.611282],"type":"Point"}
}