{
  "type": "Feature",
  "properties": {
    "addr:full":"705 Rue DE Vannes Lachenaie QC J6W 1Y5",
    "addr:housenumber":"705",
    "addr:postcode":"j6w 1y5",
    "addr:street":"Rue De Vannes",
    "iso:country":"CA",
    "sg:address":"705 Rue DE Vannes",
    "sg:city":"Lachenaie",
    "sg:classifiers":[
        {
            "category":"Building & Trades",
            "subcategory":"Electrical",
            "type":"Services"
        }
    ],
    "sg:phone":"+1 450 471 1416",
    "sg:postcode":"J6W 1Y5",
    "sg:province":"QC",
    "sg:tags":[
        "electric",
        "contractor"
    ],
    "wof:name":"A Levesque Electricien Inc",
    "wof:placetype":"venue"
},
  "geometry": {"coordinates":[-73.6379776001,45.7088775635],"type":"Point"}
}