{
  "type": "Feature",
  "properties": {
    "addr:full":"1261 Balmoral Rd Cambridge ON N1T 1C4",
    "addr:housenumber":"1261",
    "addr:postcode":"n1t 1c4",
    "addr:street":"Balmoral Rd",
    "iso:country":"CA",
    "sg:address":"1261 Balmoral Rd",
    "sg:city":"Cambridge",
    "sg:classifiers":[
        {
            "category":"Manufacturing",
            "subcategory":"Rubber & Plastics",
            "type":"Manufacturing & Wholesale Goods"
        }
    ],
    "sg:phone":"+1 519 622 0410",
    "sg:postcode":"N1T 1C4",
    "sg:province":"ON",
    "sg:tags":[
        "producer"
    ],
    "wof:name":"Pure Plast Inc",
    "wof:placetype":"venue"
},
  "geometry": {"coordinates":[-80.3013458252,43.4104576111],"type":"Point"}
}