{
  "type": "Feature",
  "properties": {
    "addr:full":"190 King St W Brockville ON K6V 3R5",
    "addr:housenumber":"190",
    "addr:postcode":"k6v 3r5",
    "addr:street":"King St W",
    "iso:country":"CA",
    "sg:address":"190 King St W",
    "sg:city":"Brockville",
    "sg:classifiers":[
        {
            "category":"Shopping",
            "subcategory":"Used Merchandise",
            "type":"Retail Goods"
        }
    ],
    "sg:phone":"+1 613 498 1566",
    "sg:postcode":"K6V 3R5",
    "sg:province":"ON",
    "sg:tags":[
        "second",
        "store",
        "hand"
    ],
    "wof:name":"Second Beginnings",
    "wof:placetype":"venue"
},
  "geometry": {"coordinates":[-75.68766784669999,44.5878372192],"type":"Point"}
}