{
  "type": "Feature",
  "properties": {
    "addr:full":"220 Dundas St W Mississauga ON L5B 1J2",
    "addr:housenumber":"220",
    "addr:postcode":"l5b 1j2",
    "addr:street":"Dundas St W",
    "iso:country":"CA",
    "sg:address":"220 Dundas St W",
    "sg:city":"Mississauga",
    "sg:classifiers":[
        {
            "category":"Retail",
            "subcategory":"Auto Repair",
            "type":"Services"
        }
    ],
    "sg:phone":"+1 905 275 7784",
    "sg:postcode":"L5B 1J2",
    "sg:province":"ON",
    "sg:tags":[
        "glass",
        "top",
        "upholstery",
        "automobile"
    ],
    "wof:name":"Standard Auto Glass",
    "wof:placetype":"venue"
},
  "geometry": {"coordinates":[-79.6216049194,43.5755271912],"type":"Point"}
}