{
  "type": "Feature",
  "properties": {
    "addr:full":"230 Montee DE LA Baie Pointe-Calumet QC J0N 1G2",
    "addr:housenumber":"230",
    "addr:postcode":"j0n 1g2",
    "addr:street":"Montee De La Baie",
    "iso:country":"CA",
    "sg:address":"230 Montee DE LA Baie",
    "sg:city":"Pointe-Calumet",
    "sg:classifiers":[
        {
            "category":"Food & Beverages",
            "subcategory":"Groceries & Convenience Stores",
            "type":"Retail Goods"
        }
    ],
    "sg:phone":"+1 450 491 5363",
    "sg:postcode":"J0N 1G2",
    "sg:province":"QC",
    "sg:tags":[
        "grocer"
    ],
    "wof:name":"Super Marche Robert Germain",
    "wof:placetype":"venue"
},
  "geometry": {"coordinates":[-73.97035200000001,45.499012],"type":"Point"}
}