{
  "type": "Feature",
  "properties": {
    "addr:full":"Mont-Saint-Gregoire QC J0J 1K0",
    "addr:postcode":"j0j 1k0",
    "iso:country":"CA",
    "sg:city":"Mont-Saint-Gregoire",
    "sg:classifiers":[
        {
            "category":"Wholesale",
            "subcategory":"Electrical",
            "type":"Manufacturing & Wholesale Goods"
        }
    ],
    "sg:phone":"+1 450 346 4687",
    "sg:postcode":"J0J 1K0",
    "sg:province":"QC",
    "sg:tags":[
        "electric",
        "motor"
    ],
    "wof:name":"G & T Moteur Elec & Pompes",
    "wof:placetype":"venue"
},
  "geometry": {"coordinates":[-73.15617399999999,45.33416],"type":"Point"}
}