{
  "type": "Feature",
  "properties": {
    "addr:full":"1232 Lawrence Ave E North York ON M3A 1B9",
    "addr:housenumber":"1232",
    "addr:postcode":"m3a 1b9",
    "addr:street":"Lawrence Ave E",
    "iso:country":"CA",
    "sg:address":"1232 Lawrence Ave E",
    "sg:city":"North York",
    "sg:classifiers":[
        {
            "category":"Health Services",
            "subcategory":"Doctor",
            "type":"Services"
        }
    ],
    "sg:phone":"+1 416 445 3872",
    "sg:postcode":"M3A 1B9",
    "sg:province":"ON",
    "sg:tags":[
        "dentist"
    ],
    "wof:name":"Chen & Mittelmann",
    "wof:placetype":"venue"
},
  "geometry": {"coordinates":[-79.32093811039999,43.7412147522],"type":"Point"}
}