{
  "type": "Feature",
  "properties": {
    "iso:country":"CA",
    "sg:address":"117 Rue Des Vieux Moulins",
    "sg:city":"Piopolis",
    "sg:classifiers":[
        {
            "category":"Building & Trades",
            "subcategory":"Construction",
            "type":"Services"
        }
    ],
    "sg:phone":"+1 819 583 3870",
    "sg:postcode":"G0Y 1H0",
    "sg:province":"QC",
    "sg:tags":[
        "excavating",
        "contractor"
    ],
    "wof:name":"Entreprises Francis Grenier",
    "wof:placetype":"venue"
},
  "geometry": {"coordinates":[-70.9029083252,45.4880828857],"type":"Point"}
}