{
  "type": "Feature",
  "properties": {
    "iso:country":"CA",
    "sg:city":"Ottawa",
    "sg:classifiers":[
        {
            "category":"Manufacturing",
            "subcategory":"Furniture",
            "type":"Manufacturing & Wholesale Goods"
        }
    ],
    "sg:phone":"+1 613 232 3700",
    "sg:postcode":"K2P 1C3",
    "sg:province":"ON",
    "sg:tags":[
        "designer",
        "exposition",
        "display",
        "producer"
    ],
    "wof:name":"Freres Proulx Brothers Inc",
    "wof:placetype":"venue"
},
  "geometry": {"coordinates":[-75.69055175779999,45.4102783203],"type":"Point"}
}