{
  "type": "Feature",
  "properties": {
    "addr:full":"Marine Dr Marystown NL A0E 2M0",
    "addr:postcode":"a0e 2m0",
    "addr:street":"Marine Dr",
    "iso:country":"CA",
    "sg:address":"Marine Dr",
    "sg:city":"Marystown",
    "sg:classifiers":[
        {
            "category":"Retail",
            "subcategory":"Animal Services",
            "type":"Services"
        }
    ],
    "sg:phone":"+1 709 279 2020",
    "sg:postcode":"A0E 2M0",
    "sg:province":"NL",
    "sg:tags":[
        "pet",
        "grooming",
        "washing"
    ],
    "wof:name":"Pet Paws Grooming",
    "wof:placetype":"venue"
},
  "geometry": {"coordinates":[-55.154091,47.158485],"type":"Point"}
}