{
  "type": "Feature",
  "properties": {
    "addr:full":"1 Court House Sq Goderich ON N7A 1M2",
    "addr:housenumber":"1",
    "addr:postcode":"n7a 1m2",
    "addr:street":"Court House Sq",
    "iso:country":"CA",
    "sg:address":"1 Court House Sq",
    "sg:city":"Goderich",
    "sg:classifiers":[
        {
            "category":"Government",
            "subcategory":"Office",
            "type":"Public Place"
        }
    ],
    "sg:phone":"+1 519 524 7962",
    "sg:postcode":"N7A 1M2",
    "sg:province":"ON",
    "wof:name":"Ontario Law Library",
    "wof:placetype":"venue"
},
  "geometry": {"coordinates":[-81.71135700000001,43.743668],"type":"Point"}
}