{
  "type": "Feature",
  "properties": {
    "addr:full":"1127 Main St E Hamilton ON L8M 1P2",
    "addr:housenumber":"1127",
    "addr:postcode":"l8m 1p2",
    "addr:street":"Main St E",
    "iso:country":"CA",
    "sg:address":"1127 Main St E",
    "sg:city":"Hamilton",
    "sg:classifiers":[
        {
            "category":"Personal",
            "subcategory":"Barber",
            "type":"Services"
        }
    ],
    "sg:phone":"+1 905 543 0906",
    "sg:postcode":"L8M 1P2",
    "sg:province":"ON",
    "wof:name":"J & D Barber Shop",
    "wof:placetype":"venue"
},
  "geometry": {"coordinates":[-79.822487,43.24334],"type":"Point"}
}