{
  "type": "Feature",
  "properties": {
    "addr:full":"4 Forest Hills Pky Dartmouth NS B2W 5G7",
    "addr:housenumber":"4",
    "addr:postcode":"b2w 5g7",
    "addr:street":"Forest Hills Pky",
    "iso:country":"CA",
    "sg:address":"4 Forest Hills Pky",
    "sg:city":"Dartmouth",
    "sg:classifiers":[
        {
            "category":"Cinema",
            "subcategory":"Movie Rental",
            "type":"Entertainment"
        }
    ],
    "sg:phone":"+1 902 435 5696",
    "sg:postcode":"B2W 5G7",
    "sg:province":"NS",
    "sg:tags":[
        "leasing",
        "video",
        "disc",
        "tape"
    ],
    "wof:name":"Rogers Video",
    "wof:placetype":"venue"
},
  "geometry": {"coordinates":[-63.4904212952,44.6722221375],"type":"Point"}
}