{
  "type": "Feature",
  "properties": {
    "addr:full":"Hornepayne ON P0M 1Z0",
    "addr:postcode":"p0m 1z0",
    "iso:country":"CA",
    "sg:city":"Hornepayne",
    "sg:classifiers":[
        {
            "category":"Travel",
            "subcategory":"Hotels & Motels",
            "type":"Entertainment"
        }
    ],
    "sg:phone":"+1 807 868 3150",
    "sg:postcode":"P0M 1Z0",
    "sg:province":"ON",
    "sg:tags":[
        "tourist",
        "accommodation"
    ],
    "wof:name":"Kirmick Lodge",
    "wof:placetype":"venue"
},
  "geometry": {"coordinates":[-84.77552,49.212616],"type":"Point"}
}