{
  "type": "Feature",
  "properties": {
    "addr:full":"366 Queen St Fredericton NB E3B 1B2",
    "addr:housenumber":"366",
    "addr:postcode":"e3b 1b2",
    "addr:street":"Queen St",
    "iso:country":"CA",
    "sg:address":"366 Queen St",
    "sg:city":"Fredericton",
    "sg:classifiers":[
        {
            "category":"Shopping",
            "subcategory":"Books",
            "type":"Retail Goods"
        }
    ],
    "sg:phone":"+1 506 450 3759",
    "sg:postcode":"E3B 1B2",
    "sg:province":"NB",
    "sg:tags":[
        "comic"
    ],
    "wof:name":"Strange Adventures",
    "wof:placetype":"venue"
},
  "geometry": {"coordinates":[-66.6440200806,45.9632492065],"type":"Point"}
}