{
  "type": "Feature",
  "properties": {
    "addr:full":"Markham ON L3P 1X7",
    "addr:postcode":"l3p 1x7",
    "iso:country":"CA",
    "sg:city":"Markham",
    "sg:classifiers":[
        {
            "category":"Health Services",
            "subcategory":"Doctor",
            "type":"Services"
        }
    ],
    "sg:phone":"+1 905 294 0761",
    "sg:postcode":"L3P 1X7",
    "sg:province":"ON",
    "sg:tags":[
        "dentist"
    ],
    "wof:name":"Lem, Morley M DDS",
    "wof:placetype":"venue"
},
  "geometry": {"coordinates":[-79.280525,43.963902],"type":"Point"}
}