{
  "type": "Feature",
  "properties": {
    "iso:country":"CA",
    "sg:address":"33406 South Fraser Way",
    "sg:city":"Abbotsford",
    "sg:classifiers":[
        {
            "category":"Retail",
            "subcategory":"Auto Repair",
            "type":"Services"
        }
    ],
    "sg:phone":"+1 604 853 5905",
    "sg:postcode":"V2S 2B5",
    "sg:province":"BC",
    "sg:tags":[
        "machine",
        "automobile",
        "shop"
    ],
    "wof:name":"Evans Engine Shop Ltd",
    "wof:placetype":"venue"
},
  "geometry": {"coordinates":[-122.298522949,49.0495605469],"type":"Point"}
}