{
  "type": "Feature",
  "properties": {
    "addr:full":"266 Mcfadden Line Trout Creek ON P0H 2L0",
    "addr:housenumber":"266",
    "addr:postcode":"p0h 2l0",
    "addr:street":"Mcfadden Line",
    "iso:country":"CA",
    "sg:address":"266 Mcfadden Line",
    "sg:city":"Trout Creek",
    "sg:classifiers":[
        {
            "category":"Food & Beverages",
            "subcategory":"Specialty",
            "type":"Retail Goods"
        }
    ],
    "sg:phone":"+1 705 723 5573",
    "sg:postcode":"P0H 2L0",
    "sg:province":"ON",
    "sg:tags":[
        "gourmet",
        "shop",
        "butchering"
    ],
    "wof:name":"Northern Meat Packers & Abbtr",
    "wof:placetype":"venue"
},
  "geometry": {"coordinates":[-79.359497,45.98822],"type":"Point"}
}