{
  "type": "Feature",
  "properties": {
    "addr:full":"12535 Rte Arthur-Sauve Mirabel QC J7N 2C2",
    "addr:housenumber":"12535",
    "addr:postcode":"j7n 2c2",
    "addr:street":"Rte Arthur-Sauve",
    "iso:country":"CA",
    "sg:address":"12535 Rte Arthur-Sauve",
    "sg:city":"Mirabel",
    "sg:classifiers":[
        {
            "category":"Manufacturing",
            "subcategory":"Tools & Machinery",
            "type":"Manufacturing & Wholesale Goods"
        }
    ],
    "sg:phone":"+1 514 332 1011",
    "sg:postcode":"J7N 2C2",
    "sg:province":"QC",
    "sg:tags":[
        "farm",
        "tractor"
    ],
    "wof:name":"Centre Agricole Jld Inc",
    "wof:placetype":"venue"
},
  "geometry": {"coordinates":[-74.027939,45.589947],"type":"Point"}
}