{
  "type": "Feature",
  "properties": {
    "addr:full":"650 DE Chambly Ch Longueuil QC J4H 3L8",
    "addr:housenumber":"650",
    "addr:postcode":"j4h 3l8",
    "addr:street":"De Chambly Ch",
    "iso:country":"CA",
    "sg:address":"650 DE Chambly Ch",
    "sg:city":"Longueuil",
    "sg:classifiers":[
        {
            "category":"Organizations",
            "subcategory":"Religious Organization",
            "type":"Services"
        }
    ],
    "sg:phone":"+1 450 651 6565",
    "sg:postcode":"J4H 3L8",
    "sg:province":"QC",
    "sg:tags":[
        "church"
    ],
    "wof:name":"Eglise Baptiste DE LA Rive Sud",
    "wof:placetype":"venue"
},
  "geometry": {"coordinates":[-73.50012207029999,45.536907196],"type":"Point"}
}