{
  "type": "Feature",
  "properties": {
    "iso:country":"CA",
    "sg:city":"Chilliwack",
    "sg:classifiers":[
        {
            "category":"Health Services",
            "subcategory":"Doctor",
            "type":"Services"
        }
    ],
    "sg:phone":"+1 604 792 2400",
    "sg:postcode":"V2P 6Z6",
    "sg:province":"BC",
    "sg:tags":[
        "dentist"
    ],
    "wof:name":"Meadowbrook Dental",
    "wof:placetype":"venue"
},
  "geometry": {"coordinates":[-121.958824158,49.1592178345],"type":"Point"}
}