{
  "type": "Feature",
  "properties": {
    "addr:full":"124 Rue Saint-Thomas Montmagny QC G5V 1M2",
    "addr:housenumber":"124",
    "addr:postcode":"g5v 1m2",
    "addr:street":"Rue Saint-Thomas",
    "iso:country":"CA",
    "sg:address":"124 Rue Saint-Thomas",
    "sg:city":"Montmagny",
    "sg:classifiers":[
        {
            "category":"Shopping",
            "subcategory":"Jewelry",
            "type":"Retail Goods"
        }
    ],
    "sg:phone":"+1 418 248 0539",
    "sg:postcode":"G5V 1M2",
    "sg:province":"QC",
    "sg:tags":[
        "jeweler"
    ],
    "wof:name":"Bijouterie Roy",
    "wof:placetype":"venue"
},
  "geometry": {"coordinates":[-70.5575637817,46.9805297852],"type":"Point"}
}