{
  "type": "Feature",
  "properties": {
    "addr:full":"2414 Boul Bastien Quebec QC G2B 1B4",
    "addr:housenumber":"2414",
    "addr:postcode":"g2b 1b4",
    "addr:street":"Boul Bastien",
    "iso:country":"CA",
    "sg:address":"2414 Boul Bastien",
    "sg:city":"Quebec",
    "sg:classifiers":[
        {
            "category":"Building & Trades",
            "subcategory":"Pest Control",
            "type":"Services"
        }
    ],
    "sg:phone":"+1 418 843 6403",
    "sg:postcode":"G2B 1B4",
    "sg:province":"QC",
    "wof:name":"Air-Neuf Extermination Quebec",
    "wof:placetype":"venue"
},
  "geometry": {"coordinates":[-71.34034699999999,46.857239],"type":"Point"}
}