{
  "type": "Feature",
  "properties": {
    "addr:full":"5317 43 St Olds AB T4H 1B6",
    "addr:housenumber":"5317",
    "addr:postcode":"t4h 1b6",
    "addr:street":"43 St",
    "iso:country":"CA",
    "sg:address":"5317 43 St",
    "sg:city":"Olds",
    "sg:classifiers":[
        {
            "category":"Professional",
            "subcategory":"Business Services",
            "type":"Services"
        }
    ],
    "sg:phone":"+1 403 556 7111",
    "sg:postcode":"T4H 1B6",
    "sg:province":"AB",
    "sg:tags":[
        "interior",
        "consultant",
        "design",
        "decorator"
    ],
    "wof:name":"Drapery Magic",
    "wof:placetype":"venue"
},
  "geometry": {"coordinates":[-114.111839,51.798126],"type":"Point"}
}