{
  "type": "Feature",
  "properties": {
    "addr:full":"1747 St Clair Ave W Toronto ON M6N 1J4",
    "addr:housenumber":"1747",
    "addr:postcode":"m6n 1j4",
    "addr:street":"St Clair Ave W",
    "iso:country":"CA",
    "sg:address":"1747 St Clair Ave W",
    "sg:city":"Toronto",
    "sg:classifiers":[
        {
            "category":"Health Services",
            "subcategory":"Doctor",
            "type":"Services"
        }
    ],
    "sg:phone":"+1 416 656 2264",
    "sg:postcode":"M6N 1J4",
    "sg:province":"ON",
    "sg:tags":[
        "dentist"
    ],
    "wof:name":"Lasko, David DDS",
    "wof:placetype":"venue"
},
  "geometry": {"coordinates":[-79.460228,43.674023],"type":"Point"}
}