{
  "type": "Feature",
  "properties": {
    "addr:full":"PO Box 460 Indian Head SK S0G 2K0",
    "addr:housenumber":"po;460",
    "addr:postcode":"s0g 2k0",
    "addr:street":"Box",
    "iso:country":"CA",
    "sg:address":"PO Box 460",
    "sg:city":"Indian Head",
    "sg:classifiers":[
        {
            "category":"Recreation",
            "type":"Entertainment"
        }
    ],
    "sg:phone":"+1 306 695 3466",
    "sg:postcode":"S0G 2K0",
    "sg:province":"SK",
    "sg:tags":[
        "center"
    ],
    "wof:name":"Indian Head Recreation Ctr",
    "wof:placetype":"venue"
},
  "geometry": {"coordinates":[-103.67880249,50.5317687988],"type":"Point"}
}