{
  "type": "Feature",
  "properties": {
    "addr:full":"6084 Shawson Dr Mississauga ON L5T 1E6",
    "addr:housenumber":"6084",
    "addr:postcode":"l5t 1e6",
    "addr:street":"Shawson Dr",
    "iso:country":"CA",
    "sg:address":"6084 Shawson Dr",
    "sg:city":"Mississauga",
    "sg:classifiers":[
        {
            "category":"Manufacturing",
            "subcategory":"Metals",
            "type":"Manufacturing & Wholesale Goods"
        }
    ],
    "sg:phone":"+1 905 670 4021",
    "sg:postcode":"L5T 1E6",
    "sg:province":"ON",
    "sg:tags":[
        "steel"
    ],
    "wof:name":"Relco Manufacturing",
    "wof:placetype":"venue"
},
  "geometry": {"coordinates":[-79.6579208374,43.6503791809],"type":"Point"}
}