{
  "type": "Feature",
  "properties": {
    "addr:full":"Calgary AB T2G 0X8",
    "addr:postcode":"t2g 0x8",
    "iso:country":"CA",
    "sg:city":"Calgary",
    "sg:classifiers":[
        {
            "category":"Professional",
            "subcategory":"Art Services",
            "type":"Services"
        }
    ],
    "sg:phone":"+1 403 266 6300",
    "sg:postcode":"T2G 0X8",
    "sg:province":"AB",
    "sg:tags":[
        "scanning"
    ],
    "wof:name":"Abl Imaging Inc",
    "wof:placetype":"venue"
},
  "geometry": {"coordinates":[-114.059776,51.042393],"type":"Point"}
}