{
  "type": "Feature",
  "properties": {
    "iso:country":"CA",
    "sg:city":"Sydney",
    "sg:classifiers":[
        {
            "category":"Social Services",
            "type":"Services"
        }
    ],
    "sg:phone":"+1 902 564 5437",
    "sg:postcode":"B1P 5E1",
    "sg:province":"NS",
    "sg:tags":[
        "youth",
        "charitable",
        "organization",
        "center",
        "institution"
    ],
    "wof:name":"Big Brothers & Big Sisters",
    "wof:placetype":"venue"
},
  "geometry": {"coordinates":[-60.1922569275,46.1346969604],"type":"Point"}
}