{
  "type": "Feature",
  "properties": {
    "addr:full":"SE 12 12 8W Portage LA Prairie MB R1N 3A4",
    "addr:housenumber":"12 12 8w",
    "addr:postcode":"r1n 3a4",
    "addr:street":"Se",
    "iso:country":"CA",
    "sg:address":"SE 12 12 8W",
    "sg:city":"Portage LA Prairie",
    "sg:classifiers":[
        {
            "category":"Farming",
            "subcategory":"Farm & Veterinary Services",
            "type":"Manufacturing & Wholesale Goods"
        }
    ],
    "sg:phone":"+1 204 274 2159",
    "sg:postcode":"R1N 3A4",
    "sg:province":"MB",
    "sg:tags":[
        "seed",
        "grain",
        "cleaning"
    ],
    "wof:name":"Faurschou Farms Ltd",
    "wof:placetype":"venue"
},
  "geometry": {"coordinates":[-98.290565,49.973083],"type":"Point"}
}