{
  "type": "Feature",
  "properties": {
    "addr:full":"847 Carnaby Cres Oshawa ON L1G 2Y7",
    "addr:housenumber":"847",
    "addr:postcode":"l1g 2y7",
    "addr:street":"Carnaby Cres",
    "iso:country":"CA",
    "sg:address":"847 Carnaby Cres",
    "sg:city":"Oshawa",
    "sg:classifiers":[
        {
            "category":"Insurance",
            "subcategory":"Insurance Agent",
            "type":"Services"
        }
    ],
    "sg:phone":"+1 905 571 3499",
    "sg:postcode":"L1G 2Y7",
    "sg:province":"ON",
    "wof:name":"C Fred Ball & Assoc",
    "wof:placetype":"venue"
},
  "geometry": {"coordinates":[-78.858994,43.923386],"type":"Point"}
}