{
  "type": "Feature",
  "properties": {
    "addr:full":"Shoal Lake MB R0J 1Z0",
    "addr:postcode":"r0j 1z0",
    "iso:country":"CA",
    "sg:city":"Shoal Lake",
    "sg:classifiers":[
        {
            "category":"Government",
            "subcategory":"Office",
            "type":"Public Place"
        }
    ],
    "sg:phone":"+1 204 759 4080",
    "sg:postcode":"R0J 1Z0",
    "sg:province":"MB",
    "wof:name":"Manitoba Conservation",
    "wof:placetype":"venue"
},
  "geometry": {"coordinates":[-100.590721,50.43692],"type":"Point"}
}