{
  "type": "Feature",
  "properties": {
    "addr:full":"6049 Centre St SW Calgary AB T2H 0C2",
    "addr:housenumber":"6049",
    "addr:postcode":"t2h 0c2",
    "addr:street":"Centre St Sw",
    "iso:country":"CA",
    "sg:address":"6049 Centre St SW",
    "sg:city":"Calgary",
    "sg:classifiers":[
        {
            "category":"Home & Garden",
            "subcategory":"Home Furnishings",
            "type":"Retail Goods"
        }
    ],
    "sg:phone":"+1 403 253 1688",
    "sg:postcode":"T2H 0C2",
    "sg:province":"AB",
    "sg:tags":[
        "curtain",
        "made",
        "drapery"
    ],
    "wof:name":"Sureway Window Fashions",
    "wof:placetype":"venue"
},
  "geometry": {"coordinates":[-114.064048767,50.9985694885],"type":"Point"}
}