{
  "type": "Feature",
  "properties": {
    "addr:full":"Delta BC V4G 1K5",
    "addr:postcode":"v4g 1k5",
    "iso:country":"CA",
    "sg:city":"Delta",
    "sg:classifiers":[
        {
            "category":"Manufacturing",
            "subcategory":"Metals",
            "type":"Manufacturing & Wholesale Goods"
        }
    ],
    "sg:phone":"+1 604 946 2824",
    "sg:postcode":"V4G 1K5",
    "sg:province":"BC",
    "sg:tags":[
        "anodizing"
    ],
    "wof:name":"Altech Anodizing Ltd",
    "wof:placetype":"venue"
},
  "geometry": {"coordinates":[-122.997787476,49.1451911926],"type":"Point"}
}