{
  "type": "Feature",
  "properties": {
    "addr:full":"490 Rue Notre-Dame Saint-Tite QC G0X 3H0",
    "addr:housenumber":"490",
    "addr:postcode":"g0x 3h0",
    "addr:street":"Rue Notre-Dame",
    "iso:country":"CA",
    "sg:address":"490 Rue Notre-Dame",
    "sg:city":"Saint-Tite",
    "sg:classifiers":[
        {
            "category":"Shopping",
            "subcategory":"Jewelry",
            "type":"Retail Goods"
        }
    ],
    "sg:phone":"+1 418 365 4289",
    "sg:postcode":"G0X 3H0",
    "sg:province":"QC",
    "sg:tags":[
        "clocks"
    ],
    "wof:name":"Ratelle, Yves",
    "wof:placetype":"venue"
},
  "geometry": {"coordinates":[-72.56550598139999,46.7282142639],"type":"Point"}
}