{
  "type": "Feature",
  "properties": {
    "iso:country":"CA",
    "sg:address":"2066 Lawrence Ave E",
    "sg:city":"Scarborough",
    "sg:classifiers":[
        {
            "category":"Retail",
            "subcategory":"Photofinishing",
            "type":"Services"
        }
    ],
    "sg:phone":"+1 416 757 1623",
    "sg:postcode":"M1R 2Z5",
    "sg:province":"ON",
    "sg:tags":[
        "photo",
        "finishing"
    ],
    "wof:name":"Photo Fast",
    "wof:placetype":"venue"
},
  "geometry": {"coordinates":[-79.293694,43.745739],"type":"Point"}
}