{
  "type": "Feature",
  "properties": {
    "addr:full":"12 Rue DE LA Cour Riviere-Du-Loup QC G5R 1J2",
    "addr:housenumber":"12",
    "addr:postcode":"g5r 1j2",
    "addr:street":"Rue De La Cour Riviere-Du-Loup",
    "iso:country":"CA",
    "sg:address":"12 Rue DE LA Cour",
    "sg:city":"Riviere-Du-Loup",
    "sg:classifiers":[
        {
            "category":"Professional",
            "subcategory":"Management & Consulting",
            "type":"Services"
        }
    ],
    "sg:phone":"+1 418 862 7831",
    "sg:postcode":"G5R 1J2",
    "sg:province":"QC",
    "sg:tags":[
        "consultant",
        "business"
    ],
    "wof:name":"Societe Gestion Primex Inc",
    "wof:placetype":"venue"
},
  "geometry": {"coordinates":[-69.53955841059999,47.8371086121],"type":"Point"}
}