{
  "type": "Feature",
  "properties": {
    "addr:full":"418 Lemay St Clarence Creek ON K0A 1N0",
    "addr:housenumber":"418",
    "addr:postcode":"k0a 1n0",
    "addr:street":"Lemay St",
    "iso:country":"CA",
    "sg:address":"418 Lemay St",
    "sg:city":"Clarence Creek",
    "sg:classifiers":[
        {
            "category":"Government",
            "subcategory":"Office",
            "type":"Public Place"
        }
    ],
    "sg:phone":"+1 613 488 2960",
    "sg:postcode":"K0A 1N0",
    "sg:province":"ON",
    "sg:tags":[
        "recreation",
        "center",
        "village"
    ],
    "wof:name":"Centre Recreatif DE Clarence",
    "wof:placetype":"venue"
},
  "geometry": {"coordinates":[-75.21589660639999,45.5085678101],"type":"Point"}
}