{
  "type": "Feature",
  "properties": {
    "addr:full":"Courtright ON N0N 1H0",
    "addr:postcode":"n0n 1h0",
    "iso:country":"CA",
    "sg:city":"Courtright",
    "sg:classifiers":[
        {
            "category":"Government",
            "subcategory":"Fire Station",
            "type":"Public Place"
        }
    ],
    "sg:phone":"+1 519 867 2110",
    "sg:postcode":"N0N 1H0",
    "sg:province":"ON",
    "sg:tags":[
        "department"
    ],
    "wof:name":"St Clair Fire Dept",
    "wof:placetype":"venue"
},
  "geometry": {"coordinates":[-82.4742279053,42.8188858032],"type":"Point"}
}