{
  "type": "Feature",
  "properties": {
    "iso:country":"CA",
    "sg:address":"85 Rue Saint-Jean-Baptiste",
    "sg:city":"Baie-Saint-Paul",
    "sg:classifiers":[
        {
            "category":"Social Services",
            "type":"Services"
        }
    ],
    "sg:phone":"+1 418 435 2503",
    "sg:postcode":"G3Z 1M5",
    "sg:province":"QC",
    "sg:tags":[
        "organization",
        "employment",
        "agency",
        "opportunity",
        "welfare"
    ],
    "wof:name":"Services DE Main D'Oeuvre Inc",
    "wof:placetype":"venue"
},
  "geometry": {"coordinates":[-70.508232,47.44355],"type":"Point"}
}