{
  "type": "Feature",
  "properties": {
    "addr:full":"19658 Centre St Mount Albert ON L0G 1M0",
    "addr:housenumber":"19658",
    "addr:postcode":"l0g 1m0",
    "addr:street":"Centre St",
    "iso:country":"CA",
    "sg:address":"19658 Centre St",
    "sg:city":"Mount Albert",
    "sg:classifiers":[
        {
            "category":"Building & Trades",
            "subcategory":"Landscaping Services",
            "type":"Services"
        }
    ],
    "sg:phone":"+1 905 473 2061",
    "sg:postcode":"L0G 1M0",
    "sg:province":"ON",
    "sg:tags":[
        "excavating",
        "landscape",
        "contractor"
    ],
    "wof:name":"Phil's Haulage & Excavtng Ltd",
    "wof:placetype":"venue"
},
  "geometry": {"coordinates":[-79.31172943120001,44.1485061646],"type":"Point"}
}