{
  "type": "Feature",
  "properties": {
    "addr:full":"3007 35 Ave Vernon BC V1T 2S9",
    "addr:housenumber":"3007",
    "addr:postcode":"v1t 2s9",
    "addr:street":"35 Ave",
    "iso:country":"CA",
    "sg:address":"3007 35 Ave",
    "sg:city":"Vernon",
    "sg:classifiers":[
        {
            "category":"Government",
            "subcategory":"Office",
            "type":"Public Place"
        }
    ],
    "sg:phone":"+1 250 549 5474",
    "sg:postcode":"V1T 2S9",
    "sg:province":"BC",
    "wof:name":"B C Income Support & Day Care",
    "wof:placetype":"venue"
},
  "geometry": {"coordinates":[-119.270966,50.267559],"type":"Point"}
}