{
  "type": "Feature",
  "properties": {
    "addr:full":"3400 Ch Des Quatre-Bourgeois Sainte-Foy QC G1W 2L3",
    "addr:postcode":"3400;g1w 2l3",
    "addr:street":"Ch Des Quatre-Bourgeois",
    "iso:country":"CA",
    "sg:address":"3400 Ch Des Quatre-Bourgeois",
    "sg:city":"Sainte-Foy",
    "sg:classifiers":[
        {
            "category":"Food & Beverages",
            "subcategory":"Liquor & Beverages",
            "type":"Retail Goods"
        }
    ],
    "sg:phone":"+1 418 656 0244",
    "sg:postcode":"G1W 2L3",
    "sg:province":"QC",
    "sg:tags":[
        "store"
    ],
    "wof:name":"Saq",
    "wof:placetype":"venue"
},
  "geometry": {"coordinates":[-71.31649,46.763435],"type":"Point"}
}