{
  "type": "Feature",
  "properties": {
    "addr:full":"4819 Macleod Trail SW Calgary AB T2G 0A7",
    "addr:housenumber":"4819",
    "addr:postcode":"t2g 0a7",
    "addr:street":"Macleod Trail Sw",
    "iso:country":"CA",
    "sg:address":"4819 Macleod Trail SW",
    "sg:city":"Calgary",
    "sg:classifiers":[
        {
            "category":"Shopping",
            "subcategory":"Shoes",
            "type":"Retail Goods"
        }
    ],
    "sg:phone":"+1 403 264 5833",
    "sg:postcode":"T2G 0A7",
    "sg:province":"AB",
    "wof:name":"Color Code Insoles Ltd",
    "wof:placetype":"venue"
},
  "geometry": {"coordinates":[-114.067222595,51.010597229],"type":"Point"}
}