{
  "type": "Feature",
  "properties": {
    "iso:country":"CA",
    "sg:city":"Prince George",
    "sg:classifiers":[
        {
            "category":"Manufacturing",
            "subcategory":"Metals",
            "type":"Manufacturing & Wholesale Goods"
        }
    ],
    "sg:phone":"+1 250 563 8871",
    "sg:postcode":"V2N 5S5",
    "sg:province":"BC",
    "sg:tags":[
        "rope",
        "wire"
    ],
    "wof:name":"Western Equipment Ltd",
    "wof:placetype":"venue"
},
  "geometry": {"coordinates":[-122.73374176,53.8698348999],"type":"Point"}
}