{
  "type": "Feature",
  "properties": {
    "addr:full":"Vaudreuil-Dorion QC J7V 8P2",
    "addr:postcode":"j7v 8p2",
    "iso:country":"CA",
    "sg:city":"Vaudreuil-Dorion",
    "sg:classifiers":[
        {
            "category":"Bars & Pubs",
            "type":"Food & Drink"
        }
    ],
    "sg:phone":"+1 450 455 6426",
    "sg:postcode":"J7V 8P2",
    "sg:province":"QC",
    "sg:tags":[
        "club",
        "night"
    ],
    "wof:name":"Miss Hill Top",
    "wof:placetype":"venue"
},
  "geometry": {"coordinates":[-74.0489654541,45.3750686646],"type":"Point"}
}