{
  "type": "Feature",
  "properties": {
    "addr:full":"2000 Rue Sainte-Catherine O Montreal QC H3H 2T2",
    "addr:housenumber":"2000",
    "addr:postcode":"h3h 2t2",
    "addr:street":"Rue Sainte-Catherine O",
    "iso:country":"CA",
    "sg:address":"2000 Rue Sainte-Catherine O",
    "sg:city":"Montreal",
    "sg:classifiers":[
        {
            "category":"Education",
            "subcategory":"College",
            "type":"Public Place"
        }
    ],
    "sg:phone":"+1 514 939 2006",
    "sg:postcode":"H3H 2T2",
    "sg:province":"QC",
    "sg:tags":[
        "academic",
        "school"
    ],
    "wof:name":"College LA Salle",
    "wof:placetype":"venue"
},
  "geometry": {"coordinates":[-73.55083500000001,45.524002],"type":"Point"}
}