{
  "type": "Feature",
  "properties": {
    "iso:country":"CA",
    "sg:address":"206 Lynden Rd",
    "sg:city":"Lynden",
    "sg:classifiers":[
        {
            "category":"Organizations",
            "subcategory":"Professional Association",
            "type":"Services"
        }
    ],
    "sg:phone":"+1 519 647 3403",
    "sg:postcode":"L0R 1T0",
    "sg:province":"ON",
    "wof:name":"Canadian Legion Hall",
    "wof:placetype":"venue"
},
  "geometry": {"coordinates":[-80.13916015620001,43.2138710022],"type":"Point"}
}