{
  "type": "Feature",
  "properties": {
    "addr:full":"1450 Whitehorse Rd North York ON M3J 3A7",
    "addr:housenumber":"1450",
    "addr:postcode":"m3j 3a7",
    "addr:street":"Whitehorse Rd",
    "iso:country":"CA",
    "sg:address":"1450 Whitehorse Rd",
    "sg:city":"North York",
    "sg:classifiers":[
        {
            "category":"Food & Beverages",
            "subcategory":"Bakery",
            "type":"Retail Goods"
        }
    ],
    "sg:phone":"+1 416 398 5538",
    "sg:postcode":"M3J 3A7",
    "sg:province":"ON",
    "sg:tags":[
        "baker"
    ],
    "wof:name":"Olde Fashioned Bagel Factory",
    "wof:placetype":"venue"
},
  "geometry": {"coordinates":[-79.4719009399,43.7578468323],"type":"Point"}
}