{
  "type": "Feature",
  "properties": {
    "addr:full":"411 Bayfield St Barrie ON L4M 3C5",
    "addr:housenumber":"411",
    "addr:postcode":"l4m 3c5",
    "addr:street":"Bayfield St",
    "iso:country":"CA",
    "sg:address":"411 Bayfield St",
    "sg:city":"Barrie",
    "sg:classifiers":[
        {
            "category":"Home & Garden",
            "subcategory":"Furniture",
            "type":"Retail Goods"
        }
    ],
    "sg:phone":"+1 705 721 0360",
    "sg:postcode":"L4M 3C5",
    "sg:province":"ON",
    "wof:name":"Sleep Country Canada",
    "wof:placetype":"venue"
},
  "geometry": {"coordinates":[-79.706627,44.408543],"type":"Point"}
}