{
  "type": "Feature",
  "properties": {
    "addr:full":"Edmonton AB T5S 1K6",
    "addr:postcode":"t5s 1k6",
    "iso:country":"CA",
    "sg:city":"Edmonton",
    "sg:classifiers":[
        {
            "category":"Professional",
            "subcategory":"Lawyer & Legal Services",
            "type":"Services"
        }
    ],
    "sg:phone":"+1 780 414 0222",
    "sg:postcode":"T5S 1K6",
    "sg:province":"AB",
    "sg:tags":[
        "attorney"
    ],
    "wof:name":"Kobewka, Sid J",
    "wof:placetype":"venue"
},
  "geometry": {"coordinates":[-113.620667,53.541882],"type":"Point"}
}