{
  "type": "Feature",
  "properties": {
    "addr:full":"Preeceville SK S0A 3B0",
    "addr:postcode":"s0a 3b0",
    "iso:country":"CA",
    "sg:city":"Preeceville",
    "sg:classifiers":[
        {
            "category":"Personal",
            "subcategory":"Beauty Salon",
            "type":"Services"
        }
    ],
    "sg:phone":"+1 306 547 5544",
    "sg:postcode":"S0A 3B0",
    "sg:province":"SK",
    "wof:name":"Molly's Beauty Salon",
    "wof:placetype":"venue"
},
  "geometry": {"coordinates":[-102.66686199999999,51.955147],"type":"Point"}
}