{
  "type": "Feature",
  "properties": {
    "iso:country":"CA",
    "sg:city":"Saint-Gedeon-DE-Beauce",
    "sg:classifiers":[
        {
            "category":"Shopping",
            "subcategory":"Florist",
            "type":"Retail Goods"
        }
    ],
    "sg:phone":"+1 418 582 3430",
    "sg:postcode":"G0M 1T0",
    "sg:province":"QC",
    "wof:name":"Chez Jannot Fleuriste",
    "wof:placetype":"venue"
},
  "geometry": {"coordinates":[-70.643196106,45.8503990173],"type":"Point"}
}