{
  "type": "Feature",
  "properties": {
    "addr:full":"Kerrobert SK S0L 1R0",
    "addr:postcode":"s0l 1r0",
    "addr:street":"Kerrobert",
    "iso:country":"CA",
    "sg:city":"Kerrobert",
    "sg:classifiers":[
        {
            "category":"Freight",
            "type":"Transportation"
        }
    ],
    "sg:phone":"+1 306 834 2829",
    "sg:postcode":"S0L 1R0",
    "sg:province":"SK",
    "sg:tags":[
        "trucking"
    ],
    "wof:name":"Plains Marketing Canada Lp",
    "wof:placetype":"venue"
},
  "geometry": {"coordinates":[-109.137908935,51.919960022],"type":"Point"}
}