{
  "type": "Feature",
  "properties": {
    "iso:country":"CA",
    "sg:city":"Mississauga",
    "sg:classifiers":[
        {
            "category":"Health Services",
            "subcategory":"Health Practitioner",
            "type":"Services"
        }
    ],
    "sg:phone":"+1 905 813 8338",
    "sg:postcode":"L5N 2Y1",
    "sg:province":"ON",
    "sg:tags":[
        "pathologist",
        "speech"
    ],
    "wof:name":"Manou, Marilee B",
    "wof:placetype":"venue"
},
  "geometry": {"coordinates":[-79.7586593628,43.5844497681],"type":"Point"}
}