{
  "type": "Feature",
  "properties": {
    "addr:full":"7600 Torbram Rd Mississauga ON L4T 3L8",
    "addr:housenumber":"7600",
    "addr:postcode":"l4t 3l8",
    "addr:street":"Torbram Rd",
    "iso:country":"CA",
    "sg:address":"7600 Torbram Rd",
    "sg:city":"Mississauga",
    "sg:classifiers":[
        {
            "category":"Manufacturing",
            "subcategory":"Lumber",
            "type":"Manufacturing & Wholesale Goods"
        }
    ],
    "sg:phone":"+1 905 677 9364",
    "sg:postcode":"L4T 3L8",
    "sg:province":"ON",
    "sg:tags":[
        "building",
        "material"
    ],
    "wof:name":"Weston Forest Corp",
    "wof:placetype":"venue"
},
  "geometry": {"coordinates":[-79.66975402830001,43.7066612244],"type":"Point"}
}