{
  "type": "Feature",
  "properties": {
    "iso:country":"CA",
    "sg:address":"1625 Rte Marie-Victorin",
    "sg:city":"Sorel-Tracy",
    "sg:classifiers":[
        {
            "category":"Railroad",
            "type":"Transportation"
        }
    ],
    "sg:phone":"+1 450 742 9277",
    "sg:postcode":"J3R 1M6",
    "sg:province":"QC",
    "wof:name":"Servirail",
    "wof:placetype":"venue"
},
  "geometry": {"coordinates":[-73.1455612183,46.0399093628],"type":"Point"}
}