{
  "type": "Feature",
  "properties": {
    "iso:country":"CA",
    "sg:address":"3027 Kingston Rd",
    "sg:city":"Scarborough",
    "sg:classifiers":[
        {
            "category":"Shopping",
            "subcategory":"Clothing, Apparel, & Fashions",
            "type":"Retail Goods"
        }
    ],
    "sg:phone":"+1 416 261 4484",
    "sg:postcode":"M1M 1P1",
    "sg:province":"ON",
    "wof:name":"Madlen's Fashion Wear",
    "wof:placetype":"venue"
},
  "geometry": {"coordinates":[-79.2310333252,43.7260971069],"type":"Point"}
}