{
  "type": "Feature",
  "properties": {
    "addr:full":"1727 Division Rd N Kingsville ON N9Y 2H1",
    "addr:housenumber":"1727",
    "addr:postcode":"n9y 2h1",
    "addr:street":"Division Rd N",
    "iso:country":"CA",
    "sg:address":"1727 Division Rd N",
    "sg:city":"Kingsville",
    "sg:classifiers":[
        {
            "category":"Retail",
            "subcategory":"Car Wash",
            "type":"Services"
        }
    ],
    "sg:phone":"+1 519 733 9901",
    "sg:postcode":"N9Y 2H1",
    "sg:province":"ON",
    "sg:tags":[
        "polishing",
        "washing"
    ],
    "wof:name":"Division Gas Station",
    "wof:placetype":"venue"
},
  "geometry": {"coordinates":[-82.7388305664,42.0501365662],"type":"Point"}
}