{
  "type": "Feature",
  "properties": {
    "addr:full":"265 Schoolhouse St Coquitlam BC V3K 4Y1",
    "addr:housenumber":"265",
    "addr:postcode":"v3k 4y1",
    "addr:street":"Schoolhouse St",
    "iso:country":"CA",
    "sg:address":"265 Schoolhouse St",
    "sg:city":"Coquitlam",
    "sg:classifiers":[
        {
            "category":"Manufacturing",
            "subcategory":"Metals",
            "type":"Manufacturing & Wholesale Goods"
        }
    ],
    "sg:phone":"+1 604 522 3310",
    "sg:postcode":"V3K 4Y1",
    "sg:province":"BC",
    "sg:tags":[
        "door"
    ],
    "wof:name":"National Door & Hardware Ltd",
    "wof:placetype":"venue"
},
  "geometry": {"coordinates":[-122.852287292,49.2385482788],"type":"Point"}
}