{
  "type": "Feature",
  "properties": {
    "addr:full":"9701 100th St LA Crete AB T0H 2H0",
    "addr:housenumber":"9701",
    "addr:postcode":"t0h 2h0",
    "addr:street":"100Th St",
    "iso:country":"CA",
    "sg:address":"9701 100th St",
    "sg:city":"LA Crete",
    "sg:classifiers":[
        {
            "category":"Building & Trades",
            "subcategory":"Construction",
            "type":"Services"
        }
    ],
    "sg:phone":"+1 780 928 3856",
    "sg:postcode":"T0H 2H0",
    "sg:province":"AB",
    "sg:tags":[
        "equipment",
        "kitchen",
        "maker",
        "cabinet"
    ],
    "wof:name":"Homestead Kitchens",
    "wof:placetype":"venue"
},
  "geometry": {"coordinates":[-116.404426575,58.1844406128],"type":"Point"}
}