{
  "type": "Feature",
  "properties": {
    "addr:full":"Toronto ON M5R 2S3",
    "addr:postcode":"m5r 2s3",
    "iso:country":"CA",
    "sg:city":"Toronto",
    "sg:classifiers":[
        {
            "category":"Arts & Performance",
            "subcategory":"Theater",
            "type":"Entertainment"
        }
    ],
    "sg:phone":"+1 416 968 0563",
    "sg:postcode":"M5R 2S3",
    "sg:province":"ON",
    "sg:tags":[
        "bureau"
    ],
    "wof:name":"Chandelle Productions",
    "wof:placetype":"venue"
},
  "geometry": {"coordinates":[-79.404296875,43.6714515686],"type":"Point"}
}