{
  "type": "Feature",
  "properties": {
    "addr:full":"50 Ann St Bolton ON L7E 1B9",
    "addr:housenumber":"50",
    "addr:postcode":"l7e 1b9",
    "addr:street":"Ann St",
    "iso:country":"CA",
    "sg:address":"50 Ann St",
    "sg:city":"Bolton",
    "sg:classifiers":[
        {
            "category":"Organizations",
            "subcategory":"Professional Association",
            "type":"Services"
        }
    ],
    "sg:phone":"+1 905 857 1874",
    "sg:postcode":"L7E 1B9",
    "sg:province":"ON",
    "wof:name":"Bolton Legion",
    "wof:placetype":"venue"
},
  "geometry": {"coordinates":[-79.740425,43.879776],"type":"Point"}
}