{
  "type": "Feature",
  "properties": {
    "addr:full":"333 Rothesay Ave Saint John NB E2J 2C3",
    "addr:housenumber":"333",
    "addr:postcode":"e2j 2c3",
    "addr:street":"Rothesay Ave",
    "iso:country":"CA",
    "sg:address":"333 Rothesay Ave",
    "sg:city":"Saint John",
    "sg:classifiers":[
        {
            "category":"Wholesale",
            "subcategory":"Machinery & Supplies",
            "type":"Manufacturing & Wholesale Goods"
        }
    ],
    "sg:phone":"+1 506 633 3010",
    "sg:postcode":"E2J 2C3",
    "sg:province":"NB",
    "sg:tags":[
        "seal"
    ],
    "wof:name":"Ceda Mechanical Svc",
    "wof:placetype":"venue"
},
  "geometry": {"coordinates":[-66.040367,45.296612],"type":"Point"}
}