{
  "type": "Feature",
  "properties": {
    "addr:full":"Calgary AB T2G 3C7",
    "addr:postcode":"t2g 3c7",
    "iso:country":"CA",
    "sg:city":"Calgary",
    "sg:classifiers":[
        {
            "category":"Wholesale",
            "subcategory":"Construction Materials",
            "type":"Manufacturing & Wholesale Goods"
        }
    ],
    "sg:phone":"+1 403 287 8453",
    "sg:postcode":"T2G 3C7",
    "sg:province":"AB",
    "sg:tags":[
        "tile"
    ],
    "wof:name":"Julian Ceramic Tile",
    "wof:placetype":"venue"
},
  "geometry": {"coordinates":[-114.040847778,51.0201225281],"type":"Point"}
}