{
  "type": "Feature",
  "properties": {
    "addr:full":"839 Spencer Lane Saskatoon SK S7K 7S6",
    "addr:housenumber":"839",
    "addr:postcode":"s7k 7s6",
    "addr:street":"Spencer Lane",
    "iso:country":"CA",
    "sg:address":"839 Spencer Lane",
    "sg:city":"Saskatoon",
    "sg:classifiers":[
        {
            "category":"Freight",
            "type":"Transportation"
        }
    ],
    "sg:phone":"+1 306 220 2715",
    "sg:postcode":"S7K 7S6",
    "sg:province":"SK",
    "sg:tags":[
        "consultant"
    ],
    "wof:name":"Northfork Enterprises",
    "wof:placetype":"venue"
},
  "geometry": {"coordinates":[-106.635445,52.186783],"type":"Point"}
}