{
  "type": "Feature",
  "properties": {
    "addr:full":"1920 Ottawa St Windsor ON N8Y 1R7",
    "addr:housenumber":"1920",
    "addr:postcode":"n8y 1r7",
    "addr:street":"Ottawa St",
    "iso:country":"CA",
    "sg:address":"1920 Ottawa St",
    "sg:city":"Windsor",
    "sg:classifiers":[
        {
            "category":"Food & Beverages",
            "subcategory":"Bakery",
            "type":"Retail Goods"
        }
    ],
    "sg:phone":"+1 519 258 5274",
    "sg:postcode":"N8Y 1R7",
    "sg:province":"ON",
    "sg:tags":[
        "tea",
        "coffee",
        "doughnut"
    ],
    "wof:name":"Tim Hortons",
    "wof:placetype":"venue"
},
  "geometry": {"coordinates":[-83.005959,42.312225],"type":"Point"}
}