{
  "type": "Feature",
  "properties": {
    "addr:full":"1285 Marine Dr North Vancouver BC V7P 1T3",
    "addr:housenumber":"1285",
    "addr:postcode":"v7p 1t3",
    "addr:street":"Marine Dr",
    "iso:country":"CA",
    "sg:address":"1285 Marine Dr",
    "sg:city":"North Vancouver",
    "sg:classifiers":[
        {
            "category":"Shopping",
            "subcategory":"Computers & Home Electronics",
            "type":"Retail Goods"
        }
    ],
    "sg:phone":"+1 604 987 3121",
    "sg:postcode":"V7P 1T3",
    "sg:province":"BC",
    "sg:tags":[
        "high",
        "television",
        "stereophonic",
        "radio",
        "fidelity"
    ],
    "wof:name":"Cgm Electronics Ltd",
    "wof:placetype":"venue"
},
  "geometry": {"coordinates":[-123.109909,49.323685],"type":"Point"}
}