{
  "type": "Feature",
  "properties": {
    "addr:full":"423 Union St Fredericton NB E3A 3M4",
    "addr:housenumber":"423",
    "addr:postcode":"e3a 3m4",
    "addr:street":"Union St",
    "iso:country":"CA",
    "sg:address":"423 Union St",
    "sg:city":"Fredericton",
    "sg:classifiers":[
        {
            "category":"Professional",
            "subcategory":"Business Services",
            "type":"Services"
        }
    ],
    "sg:phone":"+1 506 457 4559",
    "sg:postcode":"E3A 3M4",
    "sg:province":"NB",
    "wof:name":"Vaughn Barnett",
    "wof:placetype":"venue"
},
  "geometry": {"coordinates":[-66.6362686157,45.9720497131],"type":"Point"}
}