{
  "type": "Feature",
  "properties": {
    "addr:full":"1420 Lougar Ave Sarnia ON N7S 5N4",
    "addr:housenumber":"1420",
    "addr:postcode":"n7s 5n4",
    "addr:street":"Lougar Ave",
    "iso:country":"CA",
    "sg:address":"1420 Lougar Ave",
    "sg:city":"Sarnia",
    "sg:classifiers":[
        {
            "category":"Organizations",
            "subcategory":"Community Association",
            "type":"Services"
        }
    ],
    "sg:phone":"+1 519 344 0331",
    "sg:postcode":"N7S 5N4",
    "sg:province":"ON",
    "sg:tags":[
        "club"
    ],
    "wof:name":"Royal Canadian Naval Assn",
    "wof:placetype":"venue"
},
  "geometry": {"coordinates":[-82.3521652222,42.9578933716],"type":"Point"}
}