{
  "type": "Feature",
  "properties": {
    "addr:full":"349 Pleasant St Yarmouth NS B5A 2K9",
    "addr:housenumber":"349",
    "addr:postcode":"b5a 2k9",
    "addr:street":"Pleasant St",
    "iso:country":"CA",
    "sg:address":"349 Pleasant St",
    "sg:city":"Yarmouth",
    "sg:classifiers":[
        {
            "category":"Organizations",
            "subcategory":"Religious Organization",
            "type":"Services"
        }
    ],
    "sg:phone":"+1 902 742 3761",
    "sg:postcode":"B5A 2K9",
    "sg:province":"NS",
    "sg:tags":[
        "church"
    ],
    "wof:name":"Church of Jesus Christ-Lds",
    "wof:placetype":"venue"
},
  "geometry": {"coordinates":[-66.104752,43.850437],"type":"Point"}
}