{
  "type": "Feature",
  "properties": {
    "iso:country":"CA",
    "sg:address":"1230 Rue Tellier",
    "sg:city":"Laval",
    "sg:classifiers":[
        {
            "category":"Retail",
            "subcategory":"Auto Repair",
            "type":"Services"
        }
    ],
    "sg:phone":"+1 450 661 5747",
    "sg:postcode":"H7C 2H2",
    "sg:province":"QC",
    "sg:tags":[
        "body",
        "automobile",
        "painting"
    ],
    "wof:name":"A C Atelier DE Carrosserie",
    "wof:placetype":"venue"
},
  "geometry": {"coordinates":[-73.6585845947,45.6157722473],"type":"Point"}
}