{
  "type": "Feature",
  "properties": {
    "iso:country":"CA",
    "sg:address":"2474 Loon Lake Rd",
    "sg:city":"Cache Creek",
    "sg:classifiers":[
        {
            "category":"Recreation",
            "type":"Entertainment"
        }
    ],
    "sg:phone":"+1 250 459 2365",
    "sg:postcode":"V0K 1H0",
    "sg:province":"BC",
    "sg:tags":[
        "party",
        "fishing"
    ],
    "wof:name":"Wells Park Fishing Resort",
    "wof:placetype":"venue"
},
  "geometry": {"coordinates":[-121.326439,50.813385],"type":"Point"}
}