{
  "type": "Feature",
  "properties": {
    "addr:full":"1032 Grand Marais Rd E Windsor ON N8W 1W2",
    "addr:housenumber":"1032",
    "addr:postcode":"n8w 1w2",
    "addr:street":"Grand Marais Rd E",
    "iso:country":"CA",
    "sg:address":"1032 Grand Marais Rd E",
    "sg:city":"Windsor",
    "sg:classifiers":[
        {
            "category":"Building & Trades",
            "subcategory":"Construction",
            "type":"Services"
        }
    ],
    "sg:phone":"+1 519 966 8051",
    "sg:postcode":"N8W 1W2",
    "sg:province":"ON",
    "sg:tags":[
        "concrete",
        "contractor"
    ],
    "wof:name":"Fabbro Rinaldo & Son Concrete",
    "wof:placetype":"venue"
},
  "geometry": {"coordinates":[-82.99894714360001,42.2837562561],"type":"Point"}
}