{
  "type": "Feature",
  "properties": {
    "iso:country":"CA",
    "sg:address":"41 Adelaide St S",
    "sg:city":"London",
    "sg:classifiers":[
        {
            "category":"Retail",
            "subcategory":"Veterinary Services",
            "type":"Services"
        }
    ],
    "sg:phone":"+1 519 433 5490",
    "sg:postcode":"N5Z 3K1",
    "sg:province":"ON",
    "sg:tags":[
        "veterinarian"
    ],
    "wof:name":"Bouck, Gary DVM",
    "wof:placetype":"venue"
},
  "geometry": {"coordinates":[-81.224625,42.972309],"type":"Point"}
}