{
  "type": "Feature",
  "properties": {
    "addr:full":"410 Tranquille Rd Kamloops BC V2B 3G8",
    "addr:housenumber":"410",
    "addr:postcode":"bc v2b 3g8",
    "addr:street":"Tranquille Rd",
    "iso:country":"CA",
    "sg:address":"410 Tranquille Rd",
    "sg:city":"Kamloops",
    "sg:classifiers":[
        {
            "category":"Shopping",
            "subcategory":"Used Merchandise",
            "type":"Retail Goods"
        }
    ],
    "sg:phone":"+1 250 376 2284",
    "sg:postcode":"V2B 3G8",
    "sg:province":"BC",
    "sg:tags":[
        "antique"
    ],
    "wof:name":"Thrifty Things",
    "wof:placetype":"venue"
},
  "geometry": {"coordinates":[-120.35829200000001,50.69035],"type":"Point"}
}