{
  "type": "Feature",
  "properties": {
    "addr:full":"10133 34 Ave NW Edmonton AB T6E 6J8",
    "addr:housenumber":"10133",
    "addr:postcode":"t6e 6j8",
    "addr:street":"34 Ave Nw",
    "iso:country":"CA",
    "sg:address":"10133 34 Ave NW",
    "sg:city":"Edmonton",
    "sg:classifiers":[
        {
            "category":"Shopping",
            "subcategory":"Computers & Home Electronics",
            "type":"Retail Goods"
        }
    ],
    "sg:phone":"+1 780 438 6242",
    "sg:postcode":"T6E 6J8",
    "sg:province":"AB",
    "sg:tags":[
        "high",
        "fidelity",
        "stereophonic"
    ],
    "wof:name":"Visions the Best Name in Elec",
    "wof:placetype":"venue"
},
  "geometry": {"coordinates":[-113.490066528,53.4675216675],"type":"Point"}
}