{
  "type": "Feature",
  "properties": {
    "iso:country":"CA",
    "sg:address":"5107 50 St",
    "sg:city":"Rocky Mountain House",
    "sg:classifiers":[
        {
            "category":"Shopping",
            "subcategory":"Pharmacy",
            "type":"Retail Goods"
        }
    ],
    "sg:phone":"+1 403 845 3727",
    "sg:postcode":"T4T 1A1",
    "sg:province":"AB",
    "wof:name":"Alpine Value Drug Mart",
    "wof:placetype":"venue"
},
  "geometry": {"coordinates":[-114.91910553,52.3762245178],"type":"Point"}
}