{
  "type": "Feature",
  "properties": {
    "addr:full":"21 Spring Garden Ave North York ON M2N 3G1",
    "addr:housenumber":"21",
    "addr:postcode":"m2n 3g1",
    "addr:street":"Spring Garden Ave",
    "iso:country":"CA",
    "sg:address":"21 Spring Garden Ave",
    "sg:city":"North York",
    "sg:classifiers":[
        {
            "category":"Shopping",
            "subcategory":"Clothing, Apparel, & Fashions",
            "type":"Retail Goods"
        }
    ],
    "sg:phone":"+1 416 225 5881",
    "sg:postcode":"M2N 3G1",
    "sg:province":"ON",
    "sg:tags":[
        "accessory"
    ],
    "wof:name":"Olive & Brutus",
    "wof:placetype":"venue"
},
  "geometry": {"coordinates":[-79.410568,43.7644],"type":"Point"}
}