{
  "type": "Feature",
  "properties": {
    "iso:country":"CA",
    "sg:city":"Burlington",
    "sg:classifiers":[
        {
            "category":"Health Services",
            "subcategory":"Doctor",
            "type":"Services"
        }
    ],
    "sg:phone":"+1 905 632 3000",
    "sg:postcode":"L7N 3V2",
    "sg:province":"ON",
    "sg:tags":[
        "physician",
        "surgeon"
    ],
    "wof:name":"Powers, B N MD",
    "wof:placetype":"venue"
},
  "geometry": {"coordinates":[-79.796768,43.354084],"type":"Point"}
}