{
  "type": "Feature",
  "properties": {
    "addr:full":"RR 2 Dorchester ON N0L 1G5",
    "addr:postcode":"n0l 1g5",
    "addr:street":"Rr 2",
    "iso:country":"CA",
    "sg:address":"RR 2",
    "sg:city":"Dorchester",
    "sg:classifiers":[
        {
            "category":"Organizations",
            "subcategory":"Professional Association",
            "type":"Services"
        }
    ],
    "sg:phone":"+1 519 268 8531",
    "sg:postcode":"N0L 1G5",
    "sg:province":"ON",
    "wof:name":"Citizen Impact Canada",
    "wof:placetype":"venue"
},
  "geometry": {"coordinates":[-81.0499420166,42.986114502],"type":"Point"}
}