{
  "type": "Feature",
  "properties": {
    "iso:country":"CA",
    "sg:address":"11001 78 Ave",
    "sg:city":"Grande Prairie",
    "sg:classifiers":[
        {
            "category":"Building & Trades",
            "subcategory":"Construction",
            "type":"Services"
        }
    ],
    "sg:phone":"+1 780 539 0069",
    "sg:postcode":"T8W 2J7",
    "sg:province":"AB",
    "sg:tags":[
        "pipe",
        "field",
        "line",
        "oil",
        "contractor"
    ],
    "wof:name":"Flint Energy Svc Ltd",
    "wof:placetype":"venue"
},
  "geometry": {"coordinates":[-118.827438355,55.1510848999],"type":"Point"}
}