{
  "type": "Feature",
  "properties": {
    "addr:full":"Deer Lake ON P0V 1N0",
    "addr:postcode":"p0v 1n0",
    "iso:country":"CA",
    "sg:city":"Deer Lake",
    "sg:classifiers":[
        {
            "category":"Organizations",
            "subcategory":"Professional Association",
            "type":"Services"
        }
    ],
    "sg:phone":"+1 807 775 2226",
    "sg:postcode":"P0V 1N0",
    "sg:province":"ON",
    "wof:name":"Health Committee",
    "wof:placetype":"venue"
},
  "geometry": {"coordinates":[-79.713554,48.100452],"type":"Point"}
}