{
  "type": "Feature",
  "properties": {
    "addr:full":"Sherwood Park AB T8H 1X1",
    "addr:postcode":"t8h 1x1",
    "iso:country":"CA",
    "sg:city":"Sherwood Park",
    "sg:classifiers":[
        {
            "category":"Health Services",
            "subcategory":"Doctor",
            "type":"Services"
        }
    ],
    "sg:phone":"+1 780 467 7771",
    "sg:postcode":"T8H 1X1",
    "sg:province":"AB",
    "sg:tags":[
        "dentist"
    ],
    "wof:name":"Vanwieren, Stephan DDS",
    "wof:placetype":"venue"
},
  "geometry": {"coordinates":[-113.301086,53.541374],"type":"Point"}
}