{
  "type": "Feature",
  "properties": {
    "addr:full":"Saint-Hyacinthe QC J2S 4B6",
    "addr:postcode":"j2s 4b6",
    "iso:country":"CA",
    "sg:city":"Saint-Hyacinthe",
    "sg:classifiers":[
        {
            "category":"Health Services",
            "subcategory":"Doctor",
            "type":"Services"
        }
    ],
    "sg:phone":"+1 450 773 6946",
    "sg:postcode":"J2S 4B6",
    "sg:province":"QC",
    "sg:tags":[
        "physician",
        "surgeon"
    ],
    "wof:name":"Galarneau, Pierre MD",
    "wof:placetype":"venue"
},
  "geometry": {"coordinates":[-72.947472,45.634956],"type":"Point"}
}