{
  "type": "Feature",
  "properties": {
    "addr:full":"47 Washington Grand Ave Tillsonburg ON N4G 1Y8",
    "addr:housenumber":"47",
    "addr:postcode":"n4g 1y8",
    "addr:street":"Washington Grand Ave",
    "iso:country":"CA",
    "sg:address":"47 Washington Grand Ave",
    "sg:city":"Tillsonburg",
    "sg:classifiers":[
        {
            "category":"Social Services",
            "subcategory":"Child Care",
            "type":"Services"
        }
    ],
    "sg:phone":"+1 519 842 9311",
    "sg:postcode":"N4G 1Y8",
    "sg:province":"ON",
    "wof:name":"First Baptist Weekday Nursery",
    "wof:placetype":"venue"
},
  "geometry": {"coordinates":[-80.7314300537,42.8608131409],"type":"Point"}
}