{
  "type": "Feature",
  "properties": {
    "addr:full":"LA Pocatiere QC G0R 1Z0",
    "addr:postcode":"g0r 1z0",
    "iso:country":"CA",
    "sg:city":"LA Pocatiere",
    "sg:classifiers":[
        {
            "category":"Wholesale",
            "subcategory":"Farm Supplies",
            "type":"Manufacturing & Wholesale Goods"
        }
    ],
    "sg:phone":"+1 418 856 2323",
    "sg:postcode":"G0R 1Z0",
    "sg:province":"QC",
    "sg:tags":[
        "feed"
    ],
    "wof:name":"Services Agricoles Grondin",
    "wof:placetype":"venue"
},
  "geometry": {"coordinates":[-70.032059,47.377064],"type":"Point"}
}