{
  "type": "Feature",
  "properties": {
    "addr:full":"1175 Wilson St E Hamilton ON L8S 4K6",
    "addr:housenumber":"1175",
    "addr:postcode":"l8s 4k6",
    "addr:street":"Wilson St E",
    "iso:country":"CA",
    "sg:address":"1175 Wilson St E",
    "sg:city":"Hamilton",
    "sg:classifiers":[
        {
            "category":"Recreation",
            "type":"Entertainment"
        }
    ],
    "sg:phone":"+1 905 777 9663",
    "sg:postcode":"L8S 4K6",
    "sg:province":"ON",
    "sg:tags":[
        "martial",
        "arts",
        "instruction"
    ],
    "wof:name":"Wood's Martial Arts",
    "wof:placetype":"venue"
},
  "geometry": {"coordinates":[-79.94863100000001,43.245281],"type":"Point"}
}