{
  "type": "Feature",
  "properties": {
    "addr:full":"82 1E Av O Amos QC J9T 4B2",
    "addr:housenumber":"82",
    "addr:postcode":"j9t 4b2",
    "addr:street":"1E Av O Amos",
    "iso:country":"CA",
    "sg:address":"82 1E Av O",
    "sg:city":"Amos",
    "sg:classifiers":[
        {
            "category":"Shopping",
            "subcategory":"Music",
            "type":"Retail Goods"
        }
    ],
    "sg:phone":"+1 819 732 7918",
    "sg:postcode":"J9T 4B2",
    "sg:province":"QC",
    "sg:tags":[
        "compact",
        "record",
        "disc",
        "tape"
    ],
    "wof:name":"Mag Music Enr",
    "wof:placetype":"venue"
},
  "geometry": {"coordinates":[-78.11328899999999,48.571789],"type":"Point"}
}