{
  "type": "Feature",
  "properties": {
    "addr:full":"160 Springhurst Ave Toronto ON M6K 1C2",
    "addr:housenumber":"160",
    "addr:postcode":"m6k 1c2",
    "addr:street":"Springhurst Ave",
    "iso:country":"CA",
    "sg:address":"160 Springhurst Ave",
    "sg:city":"Toronto",
    "sg:classifiers":[
        {
            "category":"Restaurant",
            "type":"Food & Drink"
        }
    ],
    "sg:phone":"+1 416 532 2908",
    "sg:postcode":"M6K 1C2",
    "sg:province":"ON",
    "wof:name":"Harry's Char Broil & Dining",
    "wof:placetype":"venue"
},
  "geometry": {"coordinates":[-79.4365692139,43.6355400085],"type":"Point"}
}