{
  "type": "Feature",
  "properties": {
    "addr:full":"449 Sioux Rd Sherwood Park AB T8A 4H2",
    "addr:housenumber":"449",
    "addr:postcode":"t8a 4h2",
    "addr:street":"Sioux Rd",
    "iso:country":"CA",
    "sg:address":"449 Sioux Rd",
    "sg:city":"Sherwood Park",
    "sg:classifiers":[
        {
            "category":"Organizations",
            "subcategory":"Professional Association",
            "type":"Services"
        }
    ],
    "sg:phone":"+1 780 464 3788",
    "sg:postcode":"T8A 4H2",
    "sg:province":"AB",
    "sg:tags":[
        "club"
    ],
    "wof:name":"Step By Step School of Dance",
    "wof:placetype":"venue"
},
  "geometry": {"coordinates":[-113.332092285,53.5370330811],"type":"Point"}
}