{
  "type": "Feature",
  "properties": {
    "iso:country":"CA",
    "sg:city":"Montreal",
    "sg:classifiers":[
        {
            "category":"Health Services",
            "subcategory":"Optometrist",
            "type":"Services"
        }
    ],
    "sg:phone":"+1 514 844 8777",
    "sg:postcode":"H3A 1H3",
    "sg:province":"QC",
    "wof:name":"Optique Le Cartier",
    "wof:placetype":"venue"
},
  "geometry": {"coordinates":[-73.56575,45.521587],"type":"Point"}
}