{
  "type": "Feature",
  "properties": {
    "iso:country":"CA",
    "sg:address":"8945 Boul Industriel",
    "sg:city":"Chambly",
    "sg:classifiers":[
        {
            "category":"Building & Trades",
            "subcategory":"Construction",
            "type":"Services"
        }
    ],
    "sg:phone":"+1 450 447 9599",
    "sg:postcode":"J3L 5G8",
    "sg:province":"QC",
    "sg:tags":[
        "maker",
        "cabinet"
    ],
    "wof:name":"Ebenisterie Plm Design Enr",
    "wof:placetype":"venue"
},
  "geometry": {"coordinates":[-73.2817764282,45.4116821289],"type":"Point"}
}