{
  "type": "Feature",
  "properties": {
    "addr:full":"Langley BC V3A 4Y1",
    "addr:postcode":"v3a 4y1",
    "iso:country":"CA",
    "sg:city":"Langley",
    "sg:classifiers":[
        {
            "category":"Health Services",
            "subcategory":"Doctor",
            "type":"Services"
        }
    ],
    "sg:phone":"+1 604 514 9787",
    "sg:postcode":"V3A 4Y1",
    "sg:province":"BC",
    "sg:tags":[
        "physician",
        "surgeon",
        "rehabilitation"
    ],
    "wof:name":"Columbia Rehabilitation Ctr",
    "wof:placetype":"venue"
},
  "geometry": {"coordinates":[-122.672867,49.112835],"type":"Point"}
}