{
  "type": "Feature",
  "properties": {
    "addr:full":"547 St Mary's Rd Winnipeg MB R2M 3L4",
    "addr:housenumber":"547",
    "addr:postcode":"r2m 3l4",
    "addr:street":"St Mary'S Rd",
    "iso:country":"CA",
    "sg:address":"547 St Mary's Rd",
    "sg:city":"Winnipeg",
    "sg:classifiers":[
        {
            "category":"Personal",
            "type":"Services"
        }
    ],
    "sg:phone":"+1 204 233 3996",
    "sg:postcode":"R2M 3L4",
    "sg:province":"MB",
    "sg:tags":[
        "therapist",
        "massage"
    ],
    "wof:name":"Radiance Massage Therapy",
    "wof:placetype":"venue"
},
  "geometry": {"coordinates":[-97.1528167725,49.8892974854],"type":"Point"}
}