{
  "type": "Feature",
  "properties": {
    "addr:full":"St-Sauveur-Des-Monts QC J0R 1R7",
    "addr:postcode":"j0r 1r7",
    "iso:country":"CA",
    "sg:city":"St-Sauveur-Des-Monts",
    "sg:classifiers":[
        {
            "category":"Personal",
            "type":"Services"
        }
    ],
    "sg:phone":"+1 450 227 3950",
    "sg:postcode":"J0R 1R7",
    "sg:province":"QC",
    "sg:tags":[
        "electrolysis"
    ],
    "wof:name":"Esthetique Plus",
    "wof:placetype":"venue"
},
  "geometry": {"coordinates":[-74.165237,45.901672],"type":"Point"}
}