{
  "type": "Feature",
  "properties": {
    "iso:country":"CA",
    "sg:address":"875 Main St W",
    "sg:city":"Hamilton",
    "sg:classifiers":[
        {
            "category":"Professional",
            "subcategory":"Advertising",
            "type":"Services"
        }
    ],
    "sg:phone":"+1 905 522 6117",
    "sg:postcode":"L8S 4R1",
    "sg:province":"ON",
    "wof:name":"Hamilton Magazine",
    "wof:placetype":"venue"
},
  "geometry": {"coordinates":[-79.9016799927,43.2590789795],"type":"Point"}
}