{
  "type": "Feature",
  "properties": {
    "addr:full":"87 Elizabeth Ave St. John's NL A1B 1R6",
    "addr:housenumber":"87",
    "addr:postcode":"a1b 1r6",
    "addr:street":"Elizabeth Ave",
    "iso:country":"CA",
    "sg:address":"87 Elizabeth Ave",
    "sg:city":"St. John's",
    "sg:classifiers":[
        {
            "category":"Insurance",
            "subcategory":"Insurance Agent",
            "type":"Services"
        }
    ],
    "sg:phone":"+1 709 726 8627",
    "sg:postcode":"A1B 1R6",
    "sg:province":"NL",
    "wof:name":"Munn's Insurance Ltd",
    "wof:placetype":"venue"
},
  "geometry": {"coordinates":[-58.576335907,48.5545768738],"type":"Point"}
}