{
  "type": "Feature",
  "properties": {
    "iso:country":"CA",
    "sg:address":"135 Avalon Dr",
    "sg:city":"Labrador City",
    "sg:classifiers":[
        {
            "category":"Shopping",
            "subcategory":"Stationery & Office Supplies",
            "type":"Retail Goods"
        }
    ],
    "sg:phone":"+1 709 944 7535",
    "sg:postcode":"A2V 2Z2",
    "sg:province":"NL",
    "wof:name":"Officeworks Inc",
    "wof:placetype":"venue"
},
  "geometry": {"coordinates":[-66.9062042236,52.9435195923],"type":"Point"}
}