{
  "type": "Feature",
  "properties": {
    "iso:country":"CA",
    "sg:address":"269 James Bay Jct Rd",
    "sg:city":"Parry Sound",
    "sg:classifiers":[
        {
            "category":"Freight",
            "type":"Transportation"
        }
    ],
    "sg:phone":"+1 705 378 5430",
    "sg:postcode":"P2A 2W8",
    "sg:province":"ON",
    "sg:tags":[
        "commercial",
        "storage"
    ],
    "wof:name":"Beaver Public Storage",
    "wof:placetype":"venue"
},
  "geometry": {"coordinates":[-80.0363616943,45.3447685242],"type":"Point"}
}