{
  "type": "Feature",
  "properties": {
    "addr:full":"7355 Bayview Ave Thornhill ON L3T 5Z2",
    "addr:housenumber":"7355",
    "addr:postcode":"l3t 5z2",
    "addr:street":"Bayview Ave",
    "iso:country":"CA",
    "sg:address":"7355 Bayview Ave",
    "sg:city":"Thornhill",
    "sg:classifiers":[
        {
            "category":"Shopping",
            "subcategory":"Clothing, Apparel, & Fashions",
            "type":"Retail Goods"
        }
    ],
    "sg:phone":"+1 905 771 6039",
    "sg:postcode":"L3T 5Z2",
    "sg:province":"ON",
    "wof:name":"Xtc",
    "wof:placetype":"venue"
},
  "geometry": {"coordinates":[-79.399574,43.812817],"type":"Point"}
}