{
  "type": "Feature",
  "properties": {
    "addr:full":"Sainte-Monique-Lac-Saint-Jean QC G0W 2T0",
    "addr:postcode":"g0w 2t0",
    "iso:country":"CA",
    "sg:city":"Sainte-Monique-Lac-Saint-Jean",
    "sg:classifiers":[
        {
            "category":"Retail",
            "subcategory":"Auto Repair",
            "type":"Services"
        }
    ],
    "sg:phone":"+1 418 347 5024",
    "sg:postcode":"G0W 2T0",
    "sg:province":"QC",
    "sg:tags":[
        "repairing",
        "automobile"
    ],
    "wof:name":"Garage Claude Prescott",
    "wof:placetype":"venue"
},
  "geometry": {"coordinates":[-70.8897018433,46.9212303162],"type":"Point"}
}