{
  "type": "Feature",
  "properties": {
    "addr:full":"170 Main St Dutton ON N0L 1J0",
    "addr:housenumber":"170",
    "addr:postcode":"n0l 1j0",
    "addr:street":"Main St",
    "iso:country":"CA",
    "sg:address":"170 Main St",
    "sg:city":"Dutton",
    "sg:classifiers":[
        {
            "category":"Restaurant",
            "type":"Food & Drink"
        }
    ],
    "sg:phone":"+1 519 762 3560",
    "sg:postcode":"N0L 1J0",
    "sg:province":"ON",
    "wof:name":"Goal Post Sports Bar",
    "wof:placetype":"venue"
},
  "geometry": {"coordinates":[-81.5019073486,42.6628952026],"type":"Point"}
}