{
  "type": "Feature",
  "properties": {
    "addr:full":"337 Queen St Newmarket ON L3Y 2G5",
    "addr:housenumber":"337",
    "addr:postcode":"l3y 2g5",
    "addr:street":"Queen St",
    "iso:country":"CA",
    "sg:address":"337 Queen St",
    "sg:city":"Newmarket",
    "sg:classifiers":[
        {
            "category":"Organizations",
            "subcategory":"Religious Organization",
            "type":"Services"
        }
    ],
    "sg:phone":"+1 905 895 4268",
    "sg:postcode":"L3Y 2G5",
    "sg:province":"ON",
    "sg:tags":[
        "church"
    ],
    "wof:name":"New Hope Methodist Church",
    "wof:placetype":"venue"
},
  "geometry": {"coordinates":[-79.46444702150001,44.0550918579],"type":"Point"}
}