{
  "type": "Feature",
  "properties": {
    "iso:country":"CA",
    "sg:address":"2403 33 Ave SW",
    "sg:city":"Calgary",
    "sg:classifiers":[
        {
            "category":"Home & Garden",
            "subcategory":"Household Appliances",
            "type":"Retail Goods"
        }
    ],
    "sg:phone":"+1 403 241 2777",
    "sg:postcode":"T2T 2A2",
    "sg:province":"AB",
    "sg:tags":[
        "cleaners",
        "vacuum"
    ],
    "wof:name":"Central Vacuum Systems Ltd",
    "wof:placetype":"venue"
},
  "geometry": {"coordinates":[-114.114677429,51.0238685608],"type":"Point"}
}