{
  "type": "Feature",
  "properties": {
    "addr:full":"Lloydminster AB T9V 0P4",
    "addr:postcode":"t9v 0p4",
    "iso:country":"CA",
    "sg:city":"Lloydminster",
    "sg:classifiers":[
        {
            "category":"Personal",
            "subcategory":"Beauty Salon",
            "type":"Services"
        }
    ],
    "sg:phone":"+1 780 875 6867",
    "sg:postcode":"T9V 0P4",
    "sg:province":"AB",
    "sg:tags":[
        "electrolysis"
    ],
    "wof:name":"Electrolysis By Brenda",
    "wof:placetype":"venue"
},
  "geometry": {"coordinates":[-110.011032105,53.2845954895],"type":"Point"}
}