{
  "type": "Feature",
  "properties": {
    "addr:full":"5838 Rue Saint-Georges Levis QC G6V 4L4",
    "addr:housenumber":"5838",
    "addr:postcode":"g6v 4l4",
    "addr:street":"Rue Saint-Georges",
    "iso:country":"CA",
    "sg:address":"5838 Rue Saint-Georges",
    "sg:city":"Levis",
    "sg:classifiers":[
        {
            "category":"Personal",
            "subcategory":"Beauty Salon",
            "type":"Services"
        }
    ],
    "sg:phone":"+1 418 835 6776",
    "sg:postcode":"G6V 4L4",
    "sg:province":"QC",
    "wof:name":"Studio L'Entre-Deux Enr",
    "wof:placetype":"venue"
},
  "geometry": {"coordinates":[-71.180305,46.802963],"type":"Point"}
}