{
  "type": "Feature",
  "properties": {
    "iso:country":"CA",
    "sg:address":"462 4E Rue",
    "sg:city":"Shawinigan",
    "sg:classifiers":[
        {
            "category":"Personal",
            "subcategory":"Beauty Salon",
            "type":"Services"
        }
    ],
    "sg:phone":"+1 819 536 4188",
    "sg:postcode":"G9N 1G7",
    "sg:province":"QC",
    "wof:name":"Salon DE Coiffure Ctr-Ville",
    "wof:placetype":"venue"
},
  "geometry": {"coordinates":[-72.7476577759,46.5399971008],"type":"Point"}
}