{
  "type": "Feature",
  "properties": {
    "addr:full":"49 Main St St George NB E5C 3H9",
    "addr:housenumber":"49",
    "addr:postcode":"e5c 3h9",
    "addr:street":"Main St",
    "iso:country":"CA",
    "sg:address":"49 Main St",
    "sg:city":"St George",
    "sg:classifiers":[
        {
            "category":"Food & Beverages",
            "subcategory":"Liquor & Beverages",
            "type":"Retail Goods"
        }
    ],
    "sg:phone":"+1 506 755 7610",
    "sg:postcode":"E5C 3H9",
    "sg:province":"NB",
    "sg:tags":[
        "store"
    ],
    "wof:name":"N B Liquor Corp",
    "wof:placetype":"venue"
},
  "geometry": {"coordinates":[-66.8209762573,45.1315917969],"type":"Point"}
}