{
  "type": "Feature",
  "properties": {
    "addr:full":"Anzac AB T0P 1J0",
    "addr:postcode":"t0p 1j0",
    "iso:country":"CA",
    "sg:city":"Anzac",
    "sg:classifiers":[
        {
            "category":"Government",
            "subcategory":"Office",
            "type":"Public Place"
        }
    ],
    "sg:phone":"+1 780 334 2399",
    "sg:postcode":"T0P 1J0",
    "sg:province":"AB",
    "sg:tags":[
        "village"
    ],
    "wof:name":"Anzac Water Treatment Plant",
    "wof:placetype":"venue"
},
  "geometry": {"coordinates":[-111.058922,56.435654],"type":"Point"}
}