{
  "type": "Feature",
  "properties": {
    "addr:full":"Calgary AB T2N 1N4",
    "addr:postcode":"t2n 1n4",
    "iso:country":"CA",
    "sg:city":"Calgary",
    "sg:classifiers":[
        {
            "category":"Health Services",
            "subcategory":"Doctor",
            "type":"Services"
        }
    ],
    "sg:phone":"+1 403 220 5077",
    "sg:postcode":"T2N 1N4",
    "sg:province":"AB",
    "sg:tags":[
        "physician",
        "surgeon"
    ],
    "wof:name":"Bray, Robert C MD",
    "wof:placetype":"venue"
},
  "geometry": {"coordinates":[-114.136291504,51.0783882141],"type":"Point"}
}