{
  "type": "Feature",
  "properties": {
    "addr:full":"1010 Victoria Ave E Thunder Bay ON P7C 1B6",
    "addr:housenumber":"1010",
    "addr:postcode":"p7c 1b6",
    "addr:street":"Victoria Ave E",
    "iso:country":"CA",
    "sg:address":"1010 Victoria Ave E",
    "sg:city":"Thunder Bay",
    "sg:classifiers":[
        {
            "category":"Personal",
            "subcategory":"Beauty Salon",
            "type":"Services"
        }
    ],
    "sg:phone":"+1 807 623 0252",
    "sg:postcode":"P7C 1B6",
    "sg:province":"ON",
    "sg:tags":[
        "barber"
    ],
    "wof:name":"Eddies Stylists & Barbers",
    "wof:placetype":"venue"
},
  "geometry": {"coordinates":[-89.251396,48.383999],"type":"Point"}
}