{
  "type": "Feature",
  "properties": {
    "addr:full":"42 12E Av E Amos QC J9T 1J9",
    "addr:housenumber":"42",
    "addr:postcode":"j9t 1j9",
    "addr:street":"12E Av E Amos",
    "iso:country":"CA",
    "sg:address":"42 12E Av E",
    "sg:city":"Amos",
    "sg:classifiers":[
        {
            "category":"Building & Trades",
            "subcategory":"Construction",
            "type":"Services"
        }
    ],
    "sg:phone":"+1 819 732 3264",
    "sg:postcode":"J9T 1J9",
    "sg:province":"QC",
    "sg:tags":[
        "maker",
        "cabinet"
    ],
    "wof:name":"L Jeanson Cie Ltee",
    "wof:placetype":"venue"
},
  "geometry": {"coordinates":[-78.114853,48.567337],"type":"Point"}
}