{
  "type": "Feature",
  "properties": {
    "iso:country":"CA",
    "sg:address":"1268 Pine St",
    "sg:city":"Kamloops",
    "sg:classifiers":[
        {
            "category":"Farming",
            "subcategory":"Farm & Veterinary Services",
            "type":"Manufacturing & Wholesale Goods"
        }
    ],
    "sg:phone":"+1 250 828 8746",
    "sg:postcode":"V2C 3A9",
    "sg:province":"BC",
    "sg:tags":[
        "control",
        "tree",
        "weed"
    ],
    "wof:name":"Oscar's Spraying",
    "wof:placetype":"venue"
},
  "geometry": {"coordinates":[-120.310226,50.669792],"type":"Point"}
}