{
  "type": "Feature",
  "properties": {
    "addr:full":"Mont-Laurier QC J9L 1M7",
    "addr:postcode":"j9l 1m7",
    "iso:country":"CA",
    "sg:city":"Mont-Laurier",
    "sg:classifiers":[
        {
            "category":"Autos & Motor Vehicles",
            "subcategory":"Auto Supplies",
            "type":"Retail Goods"
        }
    ],
    "sg:phone":"+1 819 623 6636",
    "sg:postcode":"J9L 1M7",
    "sg:province":"QC",
    "sg:tags":[
        "automobile",
        "parts"
    ],
    "wof:name":"Carrefour Industriel Ldg Inc",
    "wof:placetype":"venue"
},
  "geometry": {"coordinates":[-75.473946,46.551926],"type":"Point"}
}