{
  "type": "Feature",
  "properties": {
    "addr:full":"Hull QC J8X 4E8",
    "addr:postcode":"j8x 4e8",
    "iso:country":"CA",
    "sg:city":"Hull",
    "sg:classifiers":[
        {
            "category":"Real Estate",
            "subcategory":"Real Estate Operator",
            "type":"Services"
        }
    ],
    "sg:phone":"+1 819 595 0337",
    "sg:postcode":"J8X 4E8",
    "sg:province":"QC",
    "sg:tags":[
        "apartment"
    ],
    "wof:name":"Terrasses DE Laval",
    "wof:placetype":"venue"
},
  "geometry": {"coordinates":[-75.7165527344,45.4285430908],"type":"Point"}
}