{
  "type": "Feature",
  "properties": {
    "iso:country":"CA",
    "sg:address":"506 Montee Cardinal",
    "sg:city":"Sainte-Justine-DE-Newton",
    "sg:classifiers":[
        {
            "category":"Freight",
            "type":"Transportation"
        }
    ],
    "sg:phone":"+1 450 764 1040",
    "sg:postcode":"J0P 1T0",
    "sg:province":"QC",
    "sg:tags":[
        "mover"
    ],
    "wof:name":"Affiliated Van Line Packers",
    "wof:placetype":"venue"
},
  "geometry": {"coordinates":[-74.42850494379999,45.405632019],"type":"Point"}
}