{
  "type": "Feature",
  "properties": {
    "addr:full":"2239 Mcallister Ave #E Port Coquitlam BC V3C 2A9",
    "addr:housenumber":"2239",
    "addr:postcode":"v3c 2a9",
    "addr:street":"Mcallister Ave # E",
    "iso:country":"CA",
    "sg:address":"2239 Mcallister Ave #E",
    "sg:city":"Port Coquitlam",
    "sg:classifiers":[
        {
            "category":"Restaurant",
            "type":"Food & Drink"
        }
    ],
    "sg:phone":"+1 604 468 8883",
    "sg:postcode":"V3C 2A9",
    "sg:province":"BC",
    "wof:name":"Wings Kitchen",
    "wof:placetype":"venue"
},
  "geometry": {"coordinates":[-122.77916,49.26215],"type":"Point"}
}