{
  "type": "Feature",
  "properties": {
    "iso:country":"CA",
    "sg:address":"901 Industrial Road No 2",
    "sg:city":"Cranbrook",
    "sg:classifiers":[
        {
            "category":"Professional",
            "subcategory":"Engineering",
            "type":"Services"
        }
    ],
    "sg:phone":"+1 250 489 4531",
    "sg:postcode":"V1C 4C9",
    "sg:province":"BC",
    "sg:tags":[
        "engineer"
    ],
    "wof:name":"Epec Consulting",
    "wof:placetype":"venue"
},
  "geometry": {"coordinates":[-115.76510620099999,49.5232887268],"type":"Point"}
}