{
  "type": "Feature",
  "properties": {
    "addr:full":"1188 Kimball Sideroad Sombra ON N0P 2H0",
    "addr:housenumber":"1188",
    "addr:postcode":"n0p 2h0",
    "addr:street":"Kimball Sideroad Sombra",
    "iso:country":"CA",
    "sg:address":"1188 Kimball Sideroad",
    "sg:city":"Sombra",
    "sg:classifiers":[
        {
            "category":"Professional",
            "subcategory":"Business Services",
            "type":"Services"
        }
    ],
    "sg:phone":"+1 519 864 1283",
    "sg:postcode":"N0P 2H0",
    "sg:province":"ON",
    "sg:tags":[
        "auctioneer"
    ],
    "wof:name":"Great West Auction CO",
    "wof:placetype":"venue"
},
  "geometry": {"coordinates":[-82.478416,42.714008],"type":"Point"}
}