{
  "type": "Feature",
  "properties": {
    "addr:full":"2740 343 Rte L'Assomption QC J5W 4R8",
    "addr:housenumber":"2740",
    "addr:postcode":"j5w 4r8",
    "addr:street":"343 Rte",
    "iso:country":"CA",
    "sg:address":"2740 343 Rte",
    "sg:city":"L'Assomption",
    "sg:classifiers":[
        {
            "category":"Organizations",
            "subcategory":"Professional Association",
            "type":"Services"
        }
    ],
    "sg:phone":"+1 450 588 7934",
    "sg:postcode":"J5W 4R8",
    "sg:province":"QC",
    "wof:name":"Societe St-Vincent DE Paul",
    "wof:placetype":"venue"
},
  "geometry": {"coordinates":[-73.431404,45.897568],"type":"Point"}
}