{
  "type": "Feature",
  "properties": {
    "addr:full":"2875 Rue Sigouin Drummondville QC J2C 6T4",
    "addr:housenumber":"2875",
    "addr:postcode":"j2c 6t4",
    "addr:street":"Rue Sigouin",
    "iso:country":"CA",
    "sg:address":"2875 Rue Sigouin",
    "sg:city":"Drummondville",
    "sg:classifiers":[
        {
            "category":"Building & Trades",
            "subcategory":"Plumbing",
            "type":"Services"
        }
    ],
    "sg:phone":"+1 819 475 1418",
    "sg:postcode":"J2C 6T4",
    "sg:province":"QC",
    "sg:tags":[
        "conditioning",
        "air",
        "system",
        "contractor"
    ],
    "wof:name":"Mecanair Ventilation Inc",
    "wof:placetype":"venue"
},
  "geometry": {"coordinates":[-72.52518499999999,45.8675],"type":"Point"}
}