{
  "type": "Feature",
  "properties": {
    "addr:full":"1195 Esquimalt Ave West Vancouver BC V7T 1K2",
    "addr:housenumber":"1195",
    "addr:postcode":"v7t 1k2",
    "addr:street":"Esquimalt Ave",
    "iso:country":"CA",
    "sg:address":"1195 Esquimalt Ave",
    "sg:city":"West Vancouver",
    "sg:classifiers":[
        {
            "category":"Professional",
            "subcategory":"Art Services",
            "type":"Services"
        }
    ],
    "sg:phone":"+1 604 922 2392",
    "sg:postcode":"V7T 1K2",
    "sg:province":"BC",
    "sg:tags":[
        "graphic",
        "designer"
    ],
    "wof:name":"All-Out Graphics",
    "wof:placetype":"venue"
},
  "geometry": {"coordinates":[-123.14827699999999,49.330566],"type":"Point"}
}