{
  "type": "Feature",
  "properties": {
    "addr:full":"5238 Lakeshore Rd Burlington ON L7L 1C2",
    "addr:housenumber":"5238",
    "addr:postcode":"l7l 1c2",
    "addr:street":"Lakeshore Rd",
    "iso:country":"CA",
    "sg:address":"5238 Lakeshore Rd",
    "sg:city":"Burlington",
    "sg:classifiers":[
        {
            "category":"Autos & Motor Vehicles",
            "subcategory":"Fuel & Gas Station",
            "type":"Retail Goods"
        }
    ],
    "sg:phone":"+1 905 633 8347",
    "sg:postcode":"L7L 1C2",
    "sg:province":"ON",
    "sg:tags":[
        "company",
        "oil"
    ],
    "wof:name":"Orfex Inc",
    "wof:placetype":"venue"
},
  "geometry": {"coordinates":[-79.73597717289999,43.3653259277],"type":"Point"}
}