{
  "type": "Feature",
  "properties": {
    "addr:full":"Invermere BC V0A 1K0",
    "addr:postcode":"v0a 1k0",
    "iso:country":"CA",
    "sg:city":"Invermere",
    "sg:classifiers":[
        {
            "category":"Real Estate",
            "subcategory":"Real Estate Agent",
            "type":"Services"
        }
    ],
    "sg:phone":"+1 250 342 6505",
    "sg:postcode":"V0A 1K0",
    "sg:province":"BC",
    "wof:name":"Re/Max Invermere",
    "wof:placetype":"venue"
},
  "geometry": {"coordinates":[-116.030349731,50.5091743469],"type":"Point"}
}