{
  "type": "Feature",
  "properties": {
    "addr:full":"1140 4 Ave SW Salmon Arm BC V1E 1T1",
    "addr:housenumber":"1140",
    "addr:postcode":"v1e 1t1",
    "addr:street":"4 Ave Sw",
    "iso:country":"CA",
    "sg:address":"1140 4 Ave SW",
    "sg:city":"Salmon Arm",
    "sg:classifiers":[
        {
            "category":"Wholesale",
            "subcategory":"Electrical",
            "type":"Manufacturing & Wholesale Goods"
        }
    ],
    "sg:phone":"+1 250 832 7790",
    "sg:postcode":"V1E 1T1",
    "sg:province":"BC",
    "sg:tags":[
        "equipment",
        "electric",
        "supply"
    ],
    "wof:name":"Torbram Electric Supply",
    "wof:placetype":"venue"
},
  "geometry": {"coordinates":[-119.298424,50.696766],"type":"Point"}
}