{
  "type": "Feature",
  "properties": {
    "addr:full":"14 Dennis Dr King City ON L7B 1C8",
    "addr:housenumber":"14",
    "addr:postcode":"l7b 1c8",
    "addr:street":"Dennis Dr",
    "iso:country":"CA",
    "sg:address":"14 Dennis Dr",
    "sg:city":"King City",
    "sg:classifiers":[
        {
            "category":"Retail",
            "subcategory":"Laundry & Dry Cleaning",
            "type":"Services"
        }
    ],
    "sg:phone":"+1 416 243 6489",
    "sg:postcode":"L7B 1C8",
    "sg:province":"ON",
    "sg:tags":[
        "repairing",
        "cleaners",
        "rug",
        "carpet"
    ],
    "wof:name":"Evans Carpet Cleaning Ltd",
    "wof:placetype":"venue"
},
  "geometry": {"coordinates":[-79.53542299999999,43.918762],"type":"Point"}
}