{
  "type": "Feature",
  "properties": {
    "iso:country":"CA",
    "sg:address":"1685 Notre Dame Ave",
    "sg:city":"Winnipeg",
    "sg:classifiers":[
        {
            "category":"Organizations",
            "subcategory":"Professional Association",
            "type":"Services"
        }
    ],
    "sg:phone":"+1 204 775 5257",
    "sg:postcode":"R3E 0R4",
    "sg:province":"MB",
    "sg:tags":[
        "club"
    ],
    "wof:name":"Club 373",
    "wof:placetype":"venue"
},
  "geometry": {"coordinates":[-97.1940612793,49.9157028198],"type":"Point"}
}