{
  "type": "Feature",
  "properties": {
    "addr:full":"30 Main St N Gilbert Plains MB R0L 0X0",
    "addr:housenumber":"30",
    "addr:postcode":"r0l 0x0",
    "addr:street":"Main St N Gilbert",
    "iso:country":"CA",
    "sg:address":"30 Main St N",
    "sg:city":"Gilbert Plains",
    "sg:classifiers":[
        {
            "category":"Insurance",
            "subcategory":"Insurance Agent",
            "type":"Services"
        }
    ],
    "sg:phone":"+1 204 548 2673",
    "sg:postcode":"R0L 0X0",
    "sg:province":"MB",
    "wof:name":"Duncan Insurance",
    "wof:placetype":"venue"
},
  "geometry": {"coordinates":[-100.485573,51.147266],"type":"Point"}
}