{
  "type": "Feature",
  "properties": {
    "addr:full":"3931 Brooklyn Cres NW Calgary AB T2L 1G9",
    "addr:housenumber":"3931",
    "addr:postcode":"t2l 1g9",
    "addr:street":"Brooklyn Cres Nw",
    "iso:country":"CA",
    "sg:address":"3931 Brooklyn Cres NW",
    "sg:city":"Calgary",
    "sg:classifiers":[
        {
            "category":"Retail",
            "subcategory":"Repair Shop",
            "type":"Services"
        }
    ],
    "sg:phone":"+1 403 282 9166",
    "sg:postcode":"T2L 1G9",
    "sg:province":"AB",
    "sg:tags":[
        "refinishing",
        "furniture"
    ],
    "wof:name":"Athlone Restorations Ltd",
    "wof:placetype":"venue"
},
  "geometry": {"coordinates":[-114.119972,51.089149],"type":"Point"}
}