{
  "type": "Feature",
  "properties": {
    "addr:full":"286 Broadway Orangeville ON L9W 1L1",
    "addr:housenumber":"286",
    "addr:postcode":"l9w 1l1",
    "addr:street":"Broadway",
    "iso:country":"CA",
    "sg:address":"286 Broadway",
    "sg:city":"Orangeville",
    "sg:classifiers":[
        {
            "category":"Food & Beverages",
            "subcategory":"Liquor & Beverages",
            "type":"Retail Goods"
        }
    ],
    "sg:phone":"+1 519 942 8304",
    "sg:postcode":"L9W 1L1",
    "sg:province":"ON",
    "sg:tags":[
        "store"
    ],
    "wof:name":"Wine Rack",
    "wof:placetype":"venue"
},
  "geometry": {"coordinates":[-80.107376,43.916912],"type":"Point"}
}