{
  "type": "Feature",
  "properties": {
    "addr:full":"33 Cairns Dr Markham ON L3P 7M8",
    "addr:housenumber":"33",
    "addr:postcode":"l3p 7m8",
    "addr:street":"Cairns Dr",
    "iso:country":"CA",
    "sg:address":"33 Cairns Dr",
    "sg:city":"Markham",
    "sg:classifiers":[
        {
            "category":"Education",
            "subcategory":"School",
            "type":"Public Place"
        }
    ],
    "sg:phone":"+1 905 471 1445",
    "sg:postcode":"L3P 7M8",
    "sg:province":"ON",
    "wof:name":"St Edward Catholic School",
    "wof:placetype":"venue"
},
  "geometry": {"coordinates":[-79.27906,43.881222],"type":"Point"}
}