{
  "type": "Feature",
  "properties": {
    "addr:full":"3440 Rue Fleury E Montreal-Nord QC H1H 2R8",
    "addr:housenumber":"3440",
    "addr:postcode":"h1h 2r8",
    "addr:street":"Rue Fleury E",
    "iso:country":"CA",
    "sg:address":"3440 Rue Fleury E",
    "sg:city":"Montreal-Nord",
    "sg:classifiers":[
        {
            "category":"Restaurant",
            "type":"Food & Drink"
        }
    ],
    "sg:phone":"+1 514 322 2222",
    "sg:postcode":"H1H 2R8",
    "sg:province":"QC",
    "wof:name":"O Pizza",
    "wof:placetype":"venue"
},
  "geometry": {"coordinates":[-73.641121,45.580948],"type":"Point"}
}