{
  "type": "Feature",
  "properties": {
    "addr:full":"41 Elmhurst Dr Etobicoke ON M9W 2J7",
    "addr:housenumber":"41",
    "addr:postcode":"m9w 2j7",
    "addr:street":"Elmhurst Dr",
    "iso:country":"CA",
    "sg:address":"41 Elmhurst Dr",
    "sg:city":"Etobicoke",
    "sg:classifiers":[
        {
            "category":"Organizations",
            "subcategory":"Religious Organization",
            "type":"Services"
        }
    ],
    "sg:phone":"+1 416 225 2442",
    "sg:postcode":"M9W 2J7",
    "sg:province":"ON",
    "wof:name":"Gospel Hall Lansing",
    "wof:placetype":"venue"
},
  "geometry": {"coordinates":[-79.55513000489999,43.7238426208],"type":"Point"}
}