{
  "type": "Feature",
  "properties": {
    "addr:full":"1300 Bath Rd Kingston ON K7M 4X4",
    "addr:housenumber":"1300",
    "addr:postcode":"k7m 4x4",
    "addr:street":"Bath Rd",
    "iso:country":"CA",
    "sg:address":"1300 Bath Rd",
    "sg:city":"Kingston",
    "sg:classifiers":[
        {
            "category":"Shopping",
            "subcategory":"Tobacco",
            "type":"Retail Goods"
        }
    ],
    "sg:phone":"+1 613 545 3829",
    "sg:postcode":"K7M 4X4",
    "sg:province":"ON",
    "sg:tags":[
        "cigarette",
        "cigar",
        "dealer"
    ],
    "wof:name":"Quality Smoke Shop",
    "wof:placetype":"venue"
},
  "geometry": {"coordinates":[-76.5247497559,44.2398223877],"type":"Point"}
}