{
  "type": "Feature",
  "properties": {
    "iso:country":"CA",
    "sg:address":"31 Eastwood Rd",
    "sg:city":"Toronto",
    "sg:classifiers":[
        {
            "category":"Organizations",
            "subcategory":"Religious Organization",
            "type":"Services"
        }
    ],
    "sg:phone":"+1 416 778 9615",
    "sg:postcode":"M4L 2C4",
    "sg:province":"ON",
    "sg:tags":[
        "church"
    ],
    "wof:name":"Toronto Formosan Presbyterian",
    "wof:placetype":"venue"
},
  "geometry": {"coordinates":[-79.31800842289999,43.6730613708],"type":"Point"}
}