{
  "type": "Feature",
  "properties": {
    "addr:full":"13800 Smallwood Pl Richmond BC V6V 2C2",
    "addr:housenumber":"13800",
    "addr:postcode":"v6v 2c2",
    "addr:street":"Smallwood Pl",
    "iso:country":"CA",
    "sg:address":"13800 Smallwood Pl",
    "sg:city":"Richmond",
    "sg:classifiers":[
        {
            "category":"Autos & Motor Vehicles",
            "subcategory":"Automobile Sales",
            "type":"Retail Goods"
        }
    ],
    "sg:phone":"+1 604 276 9177",
    "sg:postcode":"V6V 2C2",
    "sg:province":"BC",
    "sg:tags":[
        "car",
        "dealer"
    ],
    "wof:name":"Signature Mazda",
    "wof:placetype":"venue"
},
  "geometry": {"coordinates":[-123.079582214,49.1721382141],"type":"Point"}
}