{
  "type": "Feature",
  "properties": {
    "addr:full":"876 Montreal Rd # O Ottawa ON K1K 4L3",
    "addr:housenumber":"876",
    "addr:postcode":"k1k 4l3",
    "addr:street":"Montreal Rd # O",
    "iso:country":"CA",
    "sg:address":"876 Montreal Rd # O",
    "sg:city":"Ottawa",
    "sg:classifiers":[
        {
            "category":"Restaurant",
            "type":"Food & Drink"
        }
    ],
    "sg:phone":"+1 613 747 4000",
    "sg:postcode":"K1K 4L3",
    "sg:province":"ON",
    "sg:tags":[
        "pizza"
    ],
    "wof:name":"Milano Pizzeria",
    "wof:placetype":"venue"
},
  "geometry": {"coordinates":[-75.630569458,45.4462127686],"type":"Point"}
}