{
  "type": "Feature",
  "properties": {
    "iso:country":"CA",
    "sg:city":"Sandy Cove",
    "sg:classifiers":[
        {
            "category":"Manufacturing",
            "subcategory":"Watercraft",
            "type":"Manufacturing & Wholesale Goods"
        }
    ],
    "sg:phone":"+1 902 834 2340",
    "sg:postcode":"B0V 1E0",
    "sg:province":"NS",
    "sg:tags":[
        "boat"
    ],
    "wof:name":"Merritt's Fiberglass",
    "wof:placetype":"venue"
},
  "geometry": {"coordinates":[-66.09363555909999,44.4843864441],"type":"Point"}
}