{
  "type": "Feature",
  "properties": {
    "addr:full":"824 Fennell Ave E Hamilton ON L8V 1V6",
    "addr:housenumber":"824",
    "addr:postcode":"l8v 1v6",
    "addr:street":"Fennell Ave E",
    "iso:country":"CA",
    "sg:address":"824 Fennell Ave E",
    "sg:city":"Hamilton",
    "sg:classifiers":[
        {
            "category":"Retail",
            "subcategory":"Auto Repair",
            "type":"Services"
        }
    ],
    "sg:phone":"+1 905 387 1633",
    "sg:postcode":"L8V 1V6",
    "sg:province":"ON",
    "sg:tags":[
        "repairing",
        "automobile"
    ],
    "wof:name":"Speedy Auto Svc",
    "wof:placetype":"venue"
},
  "geometry": {"coordinates":[-79.847504,43.229801],"type":"Point"}
}