{
  "type": "Feature",
  "properties": {
    "addr:full":"179 Thompson Dr N Thompson MB R8N 1M9",
    "addr:housenumber":"179",
    "addr:postcode":"r8n 1m9",
    "addr:street":"Thompson Dr N",
    "iso:country":"CA",
    "sg:address":"179 Thompson Dr N",
    "sg:city":"Thompson",
    "sg:classifiers":[
        {
            "category":"Organizations",
            "subcategory":"Religious Organization",
            "type":"Services"
        }
    ],
    "sg:phone":"+1 204 677 4448",
    "sg:postcode":"R8N 1M9",
    "sg:province":"MB",
    "sg:tags":[
        "church"
    ],
    "wof:name":"Advent Lutheran Church",
    "wof:placetype":"venue"
},
  "geometry": {"coordinates":[-97.8601760864,55.7458572388],"type":"Point"}
}