{
  "type": "Feature",
  "properties": {
    "addr:full":"10235 50 St NW Edmonton AB T6A 2C2",
    "addr:housenumber":"10235",
    "addr:postcode":"t6a 2c2",
    "addr:street":"50 St Nw",
    "iso:country":"CA",
    "sg:address":"10235 50 St NW",
    "sg:city":"Edmonton",
    "sg:classifiers":[
        {
            "category":"Professional",
            "subcategory":"Engineering",
            "type":"Services"
        }
    ],
    "sg:phone":"+1 780 469 2077",
    "sg:postcode":"T6A 2C2",
    "sg:province":"AB",
    "sg:tags":[
        "fire",
        "equipment",
        "protection",
        "engineer"
    ],
    "wof:name":"Northern Fire Protection Ltd",
    "wof:placetype":"venue"
},
  "geometry": {"coordinates":[-113.418282,53.543392],"type":"Point"}
}