{
  "type": "Feature",
  "properties": {
    "addr:full":"430 Reid St Quesnel BC V2J 2M6",
    "addr:housenumber":"430",
    "addr:postcode":"v2j 2m6",
    "addr:street":"Reid St",
    "iso:country":"CA",
    "sg:address":"430 Reid St",
    "sg:city":"Quesnel",
    "sg:classifiers":[
        {
            "category":"Travel",
            "subcategory":"Travel Agent",
            "type":"Entertainment"
        }
    ],
    "sg:phone":"+1 250 992 7002",
    "sg:postcode":"V2J 2M6",
    "sg:province":"BC",
    "sg:tags":[
        "agency",
        "bureau"
    ],
    "wof:name":"Cariboo Travel Svc Quesnel",
    "wof:placetype":"venue"
},
  "geometry": {"coordinates":[-122.496795654,52.9797477722],"type":"Point"}
}