{
  "type": "Feature",
  "properties": {
    "addr:full":"452 Queen St W Toronto ON M5V 2A8",
    "addr:housenumber":"452",
    "addr:postcode":"m5v 2a8",
    "addr:street":"Queen St W",
    "iso:country":"CA",
    "sg:address":"452 Queen St W",
    "sg:city":"Toronto",
    "sg:classifiers":[
        {
            "category":"Personal",
            "subcategory":"Piercing",
            "type":"Services"
        }
    ],
    "sg:phone":"+1 416 504 8288",
    "sg:postcode":"M5V 2A8",
    "sg:province":"ON",
    "sg:tags":[
        "tattooing",
        "body"
    ],
    "wof:name":"Abstract Arts",
    "wof:placetype":"venue"
},
  "geometry": {"coordinates":[-79.39928399999999,43.648258],"type":"Point"}
}