{
  "type": "Feature",
  "properties": {
    "iso:country":"CA",
    "sg:address":"56 Rte 309 S",
    "sg:city":"Ferme-Neuve",
    "sg:classifiers":[
        {
            "category":"Wholesale",
            "subcategory":"Machinery & Supplies",
            "type":"Manufacturing & Wholesale Goods"
        }
    ],
    "sg:phone":"+1 819 587 4393",
    "sg:postcode":"J0W 1C0",
    "sg:province":"QC",
    "sg:tags":[
        "farm",
        "equipment"
    ],
    "wof:name":"Services Agricoles DE Ferme",
    "wof:placetype":"venue"
},
  "geometry": {"coordinates":[-75.467956543,46.6859054565],"type":"Point"}
}