{
  "type": "Feature",
  "properties": {
    "addr:full":"7300 Warden Ave Markham ON L3R 9Z6",
    "addr:housenumber":"7300",
    "addr:postcode":"l3r 9z6",
    "addr:street":"Warden Ave",
    "iso:country":"CA",
    "sg:address":"7300 Warden Ave",
    "sg:city":"Markham",
    "sg:classifiers":[
        {
            "category":"Wholesale",
            "subcategory":"Electrical",
            "type":"Manufacturing & Wholesale Goods"
        }
    ],
    "sg:phone":"+1 905 513 6222",
    "sg:postcode":"L3R 9Z6",
    "sg:province":"ON",
    "sg:tags":[
        "appliance"
    ],
    "wof:name":"Proctro Silex Canada Inc",
    "wof:placetype":"venue"
},
  "geometry": {"coordinates":[-79.3270568848,43.8286323547],"type":"Point"}
}