{
  "type": "Feature",
  "properties": {
    "iso:country":"CA",
    "sg:address":"103 Meeting House Rd",
    "sg:city":"Woodbridge",
    "sg:classifiers":[
        {
            "category":"Professional",
            "subcategory":"Management & Consulting",
            "type":"Services"
        }
    ],
    "sg:phone":"+1 905 850 1102",
    "sg:postcode":"L4L 1K9",
    "sg:province":"ON",
    "sg:tags":[
        "communications",
        "consultant"
    ],
    "wof:name":"Touchstone Consulting",
    "wof:placetype":"venue"
},
  "geometry": {"coordinates":[-79.5977935791,43.7895736694],"type":"Point"}
}