{
  "type": "Feature",
  "properties": {
    "addr:full":"1384 Ch Sainte-Foy Quebec QC G1S 2N6",
    "addr:postcode":"1384;g1s 2n6",
    "addr:street":"Ch Sainte-Foy",
    "iso:country":"CA",
    "sg:address":"1384 Ch Sainte-Foy",
    "sg:city":"Quebec",
    "sg:classifiers":[
        {
            "category":"Restaurant",
            "type":"Food & Drink"
        }
    ],
    "sg:phone":"+1 418 527 4141",
    "sg:postcode":"G1S 2N6",
    "sg:province":"QC",
    "wof:name":"Restaurant LA Girolle",
    "wof:placetype":"venue"
},
  "geometry": {"coordinates":[-71.2554473877,46.7943649292],"type":"Point"}
}