{
  "type": "Feature",
  "properties": {
    "addr:full":"5511 Cornwalis St Halifax NS B3K 3B4",
    "addr:housenumber":"5511",
    "addr:postcode":"b3k 3b4",
    "addr:street":"Cornwalis St",
    "iso:country":"CA",
    "sg:address":"5511 Cornwalis St",
    "sg:city":"Halifax",
    "sg:classifiers":[
        {
            "category":"Health Services",
            "subcategory":"Clinic",
            "type":"Services"
        }
    ],
    "sg:phone":"+1 902 423 9991",
    "sg:postcode":"B3K 3B4",
    "sg:province":"NS",
    "sg:tags":[
        "aids",
        "testing",
        "information"
    ],
    "wof:name":"Mainline Needle Exchange",
    "wof:placetype":"venue"
},
  "geometry": {"coordinates":[-63.5842323303,44.65234375],"type":"Point"}
}