{
  "type": "Feature",
  "properties": {
    "addr:full":"Bldg 34 Coral Harbour NU X0C 0C0",
    "addr:postcode":"x0c 0c0",
    "iso:country":"CA",
    "sg:address":"Bldg 34",
    "sg:city":"Coral Harbour",
    "sg:classifiers":[
        {
            "category":"Organizations",
            "subcategory":"Professional Association",
            "type":"Services"
        }
    ],
    "sg:phone":"+1 867 925 9927",
    "sg:postcode":"X0C 0C0",
    "sg:province":"NU",
    "wof:name":"Housing Association",
    "wof:placetype":"venue"
},
  "geometry": {"coordinates":[-83.1656036377,64.1372299194],"type":"Point"}
}