{
  "type": "Feature",
  "properties": {
    "addr:full":"8655 Rue Pascal-Gagnon Saint-Leonard QC H1P 1Y5",
    "addr:housenumber":"8655",
    "addr:postcode":"h1p 1y5",
    "addr:street":"Rue Pascal-Gagnon",
    "iso:country":"CA",
    "sg:address":"8655 Rue Pascal-Gagnon",
    "sg:city":"Saint-Leonard",
    "sg:classifiers":[
        {
            "category":"Freight",
            "type":"Transportation"
        }
    ],
    "sg:phone":"+1 514 322 1212",
    "sg:postcode":"H1P 1Y5",
    "sg:province":"QC",
    "sg:tags":[
        "trucking"
    ],
    "wof:name":"Eskimo Express Inc",
    "wof:placetype":"venue"
},
  "geometry": {"coordinates":[-73.5885467529,45.6025047302],"type":"Point"}
}