{
  "type": "Feature",
  "properties": {
    "addr:full":"1289 Hillcrest Rd Saint John NB E2N 2B8",
    "addr:housenumber":"1289",
    "addr:postcode":"e2n 2b8",
    "addr:street":"Hillcrest Rd",
    "iso:country":"CA",
    "sg:address":"1289 Hillcrest Rd",
    "sg:city":"Saint John",
    "sg:classifiers":[
        {
            "category":"Building & Trades",
            "subcategory":"Cleaning & Sanitation",
            "type":"Services"
        }
    ],
    "sg:phone":"+1 506 657 1842",
    "sg:postcode":"E2N 2B8",
    "sg:province":"NB",
    "sg:tags":[
        "cleaners",
        "janitor",
        "rug",
        "carpet"
    ],
    "wof:name":"Fabri-Zone Cleaning Systems",
    "wof:placetype":"venue"
},
  "geometry": {"coordinates":[-65.923874,45.332272],"type":"Point"}
}