{
  "type": "Feature",
  "properties": {
    "iso:country":"CA",
    "sg:city":"Vancouver",
    "sg:classifiers":[
        {
            "category":"Professional",
            "subcategory":"Management & Consulting",
            "type":"Services"
        }
    ],
    "sg:phone":"+1 604 732 8706",
    "sg:postcode":"V6J 2J3",
    "sg:province":"BC",
    "sg:tags":[
        "marketing",
        "consultant"
    ],
    "wof:name":"John Gordon & Assoc",
    "wof:placetype":"venue"
},
  "geometry": {"coordinates":[-123.143074036,49.2591438293],"type":"Point"}
}