{
  "type": "Feature",
  "properties": {
    "addr:full":"5780 Rue Pare Mont-Royal QC H4P 2M2",
    "addr:housenumber":"5780",
    "addr:postcode":"h4p 2m2",
    "addr:street":"Rue Pare",
    "iso:country":"CA",
    "sg:address":"5780 Rue Pare",
    "sg:city":"Mont-Royal",
    "sg:classifiers":[
        {
            "category":"Manufacturing",
            "subcategory":"Signs",
            "type":"Manufacturing & Wholesale Goods"
        }
    ],
    "sg:phone":"+1 514 736 7000",
    "sg:postcode":"H4P 2M2",
    "sg:province":"QC",
    "sg:tags":[
        "designer",
        "display",
        "producer"
    ],
    "wof:name":"Wexbro Flexi-Quins",
    "wof:placetype":"venue"
},
  "geometry": {"coordinates":[-73.66645812989999,45.4873085022],"type":"Point"}
}