{
  "type": "Feature",
  "properties": {
    "addr:full":"Quebec QC G1J 3C2",
    "addr:postcode":"g1j 3c2",
    "iso:country":"CA",
    "sg:city":"Quebec",
    "sg:classifiers":[
        {
            "category":"Retail",
            "subcategory":"Auto Repair",
            "type":"Services"
        }
    ],
    "sg:phone":"+1 418 522 1743",
    "sg:postcode":"G1J 3C2",
    "sg:province":"QC",
    "sg:tags":[
        "repairing",
        "automobile"
    ],
    "wof:name":"Garage J-M Lamarre Inc",
    "wof:placetype":"venue"
},
  "geometry": {"coordinates":[-71.23123168950001,46.8306655884],"type":"Point"}
}