{
  "type": "Feature",
  "properties": {
    "addr:full":"323 Connell St Woodstock NB E7M 5E7",
    "addr:housenumber":"323",
    "addr:postcode":"e7m 5e7",
    "addr:street":"Connell St",
    "iso:country":"CA",
    "sg:address":"323 Connell St",
    "sg:city":"Woodstock",
    "sg:classifiers":[
        {
            "category":"Autos & Motor Vehicles",
            "subcategory":"Automobile Sales",
            "type":"Retail Goods"
        }
    ],
    "sg:phone":"+1 506 328 9243",
    "sg:postcode":"E7M 5E7",
    "sg:province":"NB",
    "sg:tags":[
        "car",
        "dealer"
    ],
    "wof:name":"Connell Chrysler Ltd",
    "wof:placetype":"venue"
},
  "geometry": {"coordinates":[-67.595215,46.164585],"type":"Point"}
}