{
  "type": "Feature",
  "properties": {
    "addr:full":"2066 Dorchester Rd Ss 2 Dorchester ON N0L 1G2",
    "addr:housenumber":"2066",
    "addr:postcode":"n0l 1g2",
    "addr:street":"Dorchester Rd Ss 2",
    "iso:country":"CA",
    "sg:address":"2066 Dorchester Rd Ss 2",
    "sg:city":"Dorchester",
    "sg:classifiers":[
        {
            "category":"Social Services",
            "type":"Services"
        }
    ],
    "sg:phone":"+1 519 268 2025",
    "sg:postcode":"N0L 1G2",
    "sg:province":"ON",
    "sg:tags":[
        "senior",
        "government",
        "citizen"
    ],
    "wof:name":"Lion's Senior Ctr",
    "wof:placetype":"venue"
},
  "geometry": {"coordinates":[-81.0577011108,42.9862556458],"type":"Point"}
}