{
  "type": "Feature",
  "properties": {
    "addr:full":"125 Rue Tetreau Sorel-Tracy QC J3P 4S4",
    "addr:housenumber":"125",
    "addr:postcode":"j3p 4s4",
    "addr:street":"Rue Tetreau",
    "iso:country":"CA",
    "sg:address":"125 Rue Tetreau",
    "sg:city":"Sorel-Tracy",
    "sg:classifiers":[
        {
            "category":"Education",
            "subcategory":"School",
            "type":"Public Place"
        }
    ],
    "sg:phone":"+1 450 743 5193",
    "sg:postcode":"J3P 4S4",
    "sg:province":"QC",
    "wof:name":"Ecole Jean DE Brebeuf",
    "wof:placetype":"venue"
},
  "geometry": {"coordinates":[-73.10562899999999,46.034569],"type":"Point"}
}