{
  "type": "Feature",
  "properties": {
    "addr:full":"490 Steele St Port Colborne ON L3K 6A7",
    "addr:housenumber":"490",
    "addr:postcode":"l3k 6a7",
    "addr:street":"Steele St",
    "iso:country":"CA",
    "sg:address":"490 Steele St",
    "sg:city":"Port Colborne",
    "sg:classifiers":[
        {
            "category":"Personal",
            "subcategory":"Tanning Parlor",
            "type":"Services"
        }
    ],
    "sg:phone":"+1 905 834 8266",
    "sg:postcode":"L3K 6A7",
    "sg:province":"ON",
    "sg:tags":[
        "salon"
    ],
    "wof:name":"Tanning Tropix",
    "wof:placetype":"venue"
},
  "geometry": {"coordinates":[-79.26020812989999,42.8913726807],"type":"Point"}
}