{
  "type": "Feature",
  "properties": {
    "addr:full":"1 Main St S Shellbrook SK S0J 2E0",
    "addr:housenumber":"1",
    "addr:postcode":"s0j 2e0",
    "addr:street":"Main St S Shellbrook",
    "iso:country":"CA",
    "sg:address":"1 Main St S",
    "sg:city":"Shellbrook",
    "sg:classifiers":[
        {
            "category":"Professional",
            "subcategory":"Accounting & Tax Preparation",
            "type":"Services"
        }
    ],
    "sg:phone":"+1 306 747 2446",
    "sg:postcode":"S0J 2E0",
    "sg:province":"SK",
    "sg:tags":[
        "return",
        "filing"
    ],
    "wof:name":"Moore Income Tax Svc",
    "wof:placetype":"venue"
},
  "geometry": {"coordinates":[-106.38846599999999,53.218491],"type":"Point"}
}