{
  "type": "Feature",
  "properties": {
    "addr:full":"20 Lloyd St Woodbridge ON L4L 2B9",
    "addr:housenumber":"20",
    "addr:postcode":"l4l 2b9",
    "addr:street":"Lloyd St",
    "iso:country":"CA",
    "sg:address":"20 Lloyd St",
    "sg:city":"Woodbridge",
    "sg:classifiers":[
        {
            "category":"Organizations",
            "subcategory":"Professional Association",
            "type":"Services"
        }
    ],
    "sg:phone":"+1 416 746 6811",
    "sg:postcode":"L4L 2B9",
    "sg:province":"ON",
    "sg:tags":[
        "business",
        "trade"
    ],
    "wof:name":"Toronto Board of Trade Cc",
    "wof:placetype":"venue"
},
  "geometry": {"coordinates":[-79.58869900000001,43.791981],"type":"Point"}
}