{
  "type": "Feature",
  "properties": {
    "addr:full":"41 Water St N Cambridge ON N1R 3B3",
    "addr:housenumber":"41",
    "addr:postcode":"n1r 3b3",
    "addr:street":"Water St N",
    "iso:country":"CA",
    "sg:address":"41 Water St N",
    "sg:city":"Cambridge",
    "sg:classifiers":[
        {
            "category":"Personal",
            "subcategory":"Tattoo Parlor",
            "type":"Services"
        }
    ],
    "sg:phone":"+1 519 622 4845",
    "sg:postcode":"N1R 3B3",
    "sg:province":"ON",
    "sg:tags":[
        "tattooing"
    ],
    "wof:name":"Vivid Tattoo Studios",
    "wof:placetype":"venue"
},
  "geometry": {"coordinates":[-80.315163,43.360336],"type":"Point"}
}