{
  "type": "Feature",
  "properties": {
    "addr:full":"4531 47 St Delta BC V4K 2N5",
    "addr:housenumber":"4531",
    "addr:postcode":"v4k 2n5",
    "addr:street":"47 St",
    "iso:country":"CA",
    "sg:address":"4531 47 St",
    "sg:city":"Delta",
    "sg:classifiers":[
        {
            "category":"Freight",
            "type":"Transportation"
        }
    ],
    "sg:phone":"+1 604 940 0503",
    "sg:postcode":"V4K 2N5",
    "sg:province":"BC",
    "sg:tags":[
        "mover"
    ],
    "wof:name":"Tnt Dyn-O-Mite Moving",
    "wof:placetype":"venue"
},
  "geometry": {"coordinates":[-123.093032837,49.085483551],"type":"Point"}
}