{
  "type": "Feature",
  "properties": {
    "addr:full":"62 Ontario S St Marys ON N4X 1B7",
    "addr:housenumber":"62",
    "addr:postcode":"n4x 1b7",
    "addr:street":"Ontario S",
    "iso:country":"CA",
    "sg:address":"62 Ontario S",
    "sg:city":"St Marys",
    "sg:classifiers":[
        {
            "category":"Home & Garden",
            "subcategory":"Home Furnishings",
            "type":"Retail Goods"
        }
    ],
    "sg:phone":"+1 519 284 1688",
    "sg:postcode":"N4X 1B7",
    "sg:province":"ON",
    "sg:tags":[
        "curtain",
        "made",
        "drapery"
    ],
    "wof:name":"B A Home Scapes",
    "wof:placetype":"venue"
},
  "geometry": {"coordinates":[-81.14808654789999,43.2571144104],"type":"Point"}
}