{
  "type": "Feature",
  "properties": {
    "addr:full":"North Vancouver BC V7J 2C1",
    "addr:postcode":"v7j 2c1",
    "iso:country":"CA",
    "sg:city":"North Vancouver",
    "sg:classifiers":[
        {
            "category":"Wholesale",
            "subcategory":"Durable Goods & Equipment",
            "type":"Manufacturing & Wholesale Goods"
        }
    ],
    "sg:phone":"+1 604 988 2195",
    "sg:postcode":"V7J 2C1",
    "sg:province":"BC",
    "sg:tags":[
        "representative",
        "manufacturer"
    ],
    "wof:name":"Allan Crawford Assoc Ltd",
    "wof:placetype":"venue"
},
  "geometry": {"coordinates":[-123.04029800000001,49.307472],"type":"Point"}
}