{
  "type": "Feature",
  "properties": {
    "iso:country":"CA",
    "sg:address":"3780 Napier St",
    "sg:city":"Burnaby",
    "sg:classifiers":[
        {
            "category":"Professional",
            "subcategory":"Business Services",
            "type":"Services"
        }
    ],
    "sg:phone":"+1 604 257 3188",
    "sg:postcode":"V5C 3E5",
    "sg:province":"BC",
    "sg:tags":[
        "computer"
    ],
    "wof:name":"Access Computer Rentals Inc",
    "wof:placetype":"venue"
},
  "geometry": {"coordinates":[-123.021751404,49.2747116089],"type":"Point"}
}