{
  "type": "Feature",
  "properties": {
    "addr:full":"34 King William St Huntsville ON P1H 1G5",
    "addr:housenumber":"34",
    "addr:postcode":"p1h 1g5",
    "addr:street":"King William St",
    "iso:country":"CA",
    "sg:address":"34 King William St",
    "sg:city":"Huntsville",
    "sg:classifiers":[
        {
            "category":"Retail",
            "subcategory":"Photofinishing",
            "type":"Services"
        }
    ],
    "sg:phone":"+1 705 789 9603",
    "sg:postcode":"P1H 1G5",
    "sg:province":"ON",
    "sg:tags":[
        "picture",
        "frame",
        "photo"
    ],
    "wof:name":"Cavalcade Color Lab Inc",
    "wof:placetype":"venue"
},
  "geometry": {"coordinates":[-79.209442,45.331505],"type":"Point"}
}