{
  "type": "Feature",
  "properties": {
    "addr:full":"50 Elm Dr E Mississauga ON L5A 3X2",
    "addr:housenumber":"50",
    "addr:postcode":"l5a 3x2",
    "addr:street":"Elm Dr E",
    "iso:country":"CA",
    "sg:address":"50 Elm Dr E",
    "sg:city":"Mississauga",
    "sg:classifiers":[
        {
            "category":"Real Estate",
            "subcategory":"Real Estate Operator",
            "type":"Services"
        }
    ],
    "sg:phone":"+1 905 276 6137",
    "sg:postcode":"L5A 3X2",
    "sg:province":"ON",
    "sg:tags":[
        "condominium"
    ],
    "wof:name":"Peel Condominium Corp",
    "wof:placetype":"venue"
},
  "geometry": {"coordinates":[-79.630219,43.591343],"type":"Point"}
}