{
  "type": "Feature",
  "properties": {
    "iso:country":"CA",
    "sg:address":"1765 Boul Saint-Martin O",
    "sg:city":"Laval",
    "sg:classifiers":[
        {
            "category":"Personal",
            "subcategory":"Beauty Salon",
            "type":"Services"
        }
    ],
    "sg:phone":"+1 450 686 9070",
    "sg:postcode":"H7S 1N2",
    "sg:province":"QC",
    "wof:name":"Figaro Coiffure",
    "wof:placetype":"venue"
},
  "geometry": {"coordinates":[-73.7295379639,45.5672416687],"type":"Point"}
}