{
  "type": "Feature",
  "properties": {
    "addr:full":"33 Prince Arthur Ave Toronto ON M5R 1B2",
    "addr:housenumber":"33",
    "addr:postcode":"m5r 1b2",
    "addr:street":"Prince Arthur Ave",
    "iso:country":"CA",
    "sg:address":"33 Prince Arthur Ave",
    "sg:city":"Toronto",
    "sg:classifiers":[
        {
            "category":"Professional",
            "subcategory":"Lawyer & Legal Services",
            "type":"Services"
        }
    ],
    "sg:phone":"+1 416 964 9077",
    "sg:postcode":"M5R 1B2",
    "sg:province":"ON",
    "sg:tags":[
        "attorney"
    ],
    "wof:name":"Excalibur Capital Management",
    "wof:placetype":"venue"
},
  "geometry": {"coordinates":[-79.3966217041,43.6693611145],"type":"Point"}
}