{
  "type": "Feature",
  "properties": {
    "addr:full":"760 Arcola Ave Regina SK S4N 0S5",
    "addr:housenumber":"760",
    "addr:postcode":"s4n 0s5",
    "addr:street":"Arcola Ave",
    "iso:country":"CA",
    "sg:address":"760 Arcola Ave",
    "sg:city":"Regina",
    "sg:classifiers":[
        {
            "category":"Building & Trades",
            "subcategory":"Construction",
            "type":"Services"
        }
    ],
    "sg:phone":"+1 306 761 2001",
    "sg:postcode":"S4N 0S5",
    "sg:province":"SK",
    "sg:tags":[
        "general",
        "contractor"
    ],
    "wof:name":"By Design Homes",
    "wof:placetype":"venue"
},
  "geometry": {"coordinates":[-104.591476,50.450317],"type":"Point"}
}