{
  "type": "Feature",
  "properties": {
    "addr:full":"314 River Rd Gloucester ON K1V 1H2",
    "addr:housenumber":"314",
    "addr:postcode":"k1v 1h2",
    "addr:street":"River Rd",
    "iso:country":"CA",
    "sg:address":"314 River Rd",
    "sg:city":"Gloucester",
    "sg:classifiers":[
        {
            "category":"Retail",
            "subcategory":"Auto Repair",
            "type":"Services"
        }
    ],
    "sg:phone":"+1 613 731 1502",
    "sg:postcode":"K1V 1H2",
    "sg:province":"ON",
    "sg:tags":[
        "repairing",
        "automobile"
    ],
    "wof:name":"Bill Boivin Automotive Repair",
    "wof:placetype":"venue"
},
  "geometry": {"coordinates":[-75.6917800903,45.3179321289],"type":"Point"}
}