{
  "type": "Feature",
  "properties": {
    "addr:full":"31 MT Brewster Pl SE Calgary AB T2Z 2R7",
    "addr:housenumber":"31",
    "addr:postcode":"t2z 2r7",
    "addr:street":"Mt Brewster Pl Se",
    "iso:country":"CA",
    "sg:address":"31 MT Brewster Pl SE",
    "sg:city":"Calgary",
    "sg:classifiers":[
        {
            "category":"Real Estate",
            "subcategory":"Real Estate Agent",
            "type":"Services"
        }
    ],
    "sg:phone":"+1 403 860 5910",
    "sg:postcode":"T2Z 2R7",
    "sg:province":"AB",
    "sg:tags":[
        "appraiser"
    ],
    "wof:name":"Calgary Residential Appraisals",
    "wof:placetype":"venue"
},
  "geometry": {"coordinates":[-113.98545799999999,50.919346],"type":"Point"}
}