{
  "type": "Feature",
  "properties": {
    "addr:full":"Abbotsford BC V2T 6K8",
    "addr:postcode":"v2t 6k8",
    "iso:country":"CA",
    "sg:city":"Abbotsford",
    "sg:classifiers":[
        {
            "category":"Retail",
            "subcategory":"Funeral Services",
            "type":"Services"
        }
    ],
    "sg:phone":"+1 604 859 5885",
    "sg:postcode":"V2T 6K8",
    "sg:province":"BC",
    "sg:tags":[
        "director"
    ],
    "wof:name":"Wiebe & Jeske Burial & Cremat",
    "wof:placetype":"venue"
},
  "geometry": {"coordinates":[-122.356651,49.045715],"type":"Point"}
}