{
  "type": "Feature",
  "properties": {
    "addr:full":"2265 Boul Le Corbusier Laval QC H7S 1Z4",
    "addr:housenumber":"2265",
    "addr:postcode":"h7s 1z4",
    "addr:street":"Boul Le Corbusier",
    "iso:country":"CA",
    "sg:address":"2265 Boul Le Corbusier",
    "sg:city":"Laval",
    "sg:classifiers":[
        {
            "category":"Personal",
            "subcategory":"Tanning Parlor",
            "type":"Services"
        }
    ],
    "sg:phone":"+1 450 682 2255",
    "sg:postcode":"H7S 1Z4",
    "sg:province":"QC",
    "sg:tags":[
        "salon"
    ],
    "wof:name":"Salon DE Bronzage Soleil Plus",
    "wof:placetype":"venue"
},
  "geometry": {"coordinates":[-73.739929,45.571808],"type":"Point"}
}