{
  "type": "Feature",
  "properties": {
    "addr:full":"PO Box 1245 Fonthill ON L0S 1E0",
    "addr:housenumber":"po",
    "addr:postcode":"l0s 1e0",
    "addr:street":"Box 1245",
    "iso:country":"CA",
    "sg:address":"PO Box 1245",
    "sg:city":"Fonthill",
    "sg:classifiers":[
        {
            "category":"Building & Trades",
            "subcategory":"Landscaping Services",
            "type":"Services"
        }
    ],
    "sg:phone":"+1 905 892 5223",
    "sg:postcode":"L0S 1E0",
    "sg:province":"ON",
    "sg:tags":[
        "landscape",
        "contractor"
    ],
    "wof:name":"Timberline Landscape Contr",
    "wof:placetype":"venue"
},
  "geometry": {"coordinates":[-79.2818222046,43.0440979004],"type":"Point"}
}