{
  "type": "Feature",
  "properties": {
    "addr:full":"Smithers BC V0J 2N0",
    "addr:postcode":"v0j 2n0",
    "iso:country":"CA",
    "sg:city":"Smithers",
    "sg:classifiers":[
        {
            "category":"Government",
            "subcategory":"Office",
            "type":"Public Place"
        }
    ],
    "sg:phone":"+1 250 847 7319",
    "sg:postcode":"V0J 2N0",
    "sg:province":"BC",
    "wof:name":"BC Motor Vehicle",
    "wof:placetype":"venue"
},
  "geometry": {"coordinates":[-127.16812899999999,54.782803],"type":"Point"}
}