{
  "type": "Feature",
  "properties": {
    "addr:full":"55 Dufferin St Gladstone MB R0J 0T0",
    "addr:housenumber":"55",
    "addr:postcode":"r0j 0t0",
    "addr:street":"Dufferin St",
    "iso:country":"CA",
    "sg:address":"55 Dufferin St",
    "sg:city":"Gladstone",
    "sg:classifiers":[
        {
            "category":"Retail",
            "subcategory":"Repair Shop",
            "type":"Services"
        }
    ],
    "sg:phone":"+1 204 385 2828",
    "sg:postcode":"R0J 0T0",
    "sg:province":"MB",
    "sg:tags":[
        "television",
        "radio"
    ],
    "wof:name":"Joe's Tv & Radio Sales & Svc",
    "wof:placetype":"venue"
},
  "geometry": {"coordinates":[-98.9507522583,50.2254219055],"type":"Point"}
}