{
  "type": "Feature",
  "properties": {
    "addr:full":"Hull QC J9A 3G7",
    "addr:postcode":"j9a 3g7",
    "iso:country":"CA",
    "sg:city":"Hull",
    "sg:classifiers":[
        {
            "category":"Real Estate",
            "subcategory":"Real Estate Agent",
            "type":"Services"
        }
    ],
    "sg:phone":"+1 819 775 9666",
    "sg:postcode":"J9A 3G7",
    "sg:province":"QC",
    "wof:name":"Re/Max Vision Inc",
    "wof:placetype":"venue"
},
  "geometry": {"coordinates":[-75.7104873657,45.4278526306],"type":"Point"}
}