{
  "type": "Feature",
  "properties": {
    "iso:country":"CA",
    "sg:address":"333 Rue Chabanel O",
    "sg:city":"Montreal",
    "sg:classifiers":[
        {
            "category":"Wholesale",
            "subcategory":"Apparel",
            "type":"Manufacturing & Wholesale Goods"
        }
    ],
    "sg:phone":"+1 514 387 3721",
    "sg:postcode":"H2N 2E7",
    "sg:province":"QC",
    "sg:tags":[
        "clothing"
    ],
    "wof:name":"Leslie Belle Ltee",
    "wof:placetype":"venue"
},
  "geometry": {"coordinates":[-73.653968811,45.5399856567],"type":"Point"}
}