{
  "type": "Feature",
  "properties": {
    "addr:full":"328 Speedvale Ave E Guelph ON N1E 1N5",
    "addr:housenumber":"328",
    "addr:postcode":"n1e 1n5",
    "addr:street":"Speedvale Ave E",
    "iso:country":"CA",
    "sg:address":"328 Speedvale Ave E",
    "sg:city":"Guelph",
    "sg:classifiers":[
        {
            "category":"Restaurant",
            "type":"Food & Drink"
        }
    ],
    "sg:phone":"+1 519 763 8811",
    "sg:postcode":"N1E 1N5",
    "sg:province":"ON",
    "sg:tags":[
        "pizza"
    ],
    "wof:name":"Little Caesars Pizza",
    "wof:placetype":"venue"
},
  "geometry": {"coordinates":[-80.25769805909999,43.566280365],"type":"Point"}
}