{
  "type": "Feature",
  "properties": {
    "addr:full":"658 Boul Gouin E Montreal QC H2C 1A6",
    "addr:housenumber":"658",
    "addr:postcode":"h2c 1a6",
    "addr:street":"Boul Gouin E",
    "iso:country":"CA",
    "sg:address":"658 Boul Gouin E",
    "sg:city":"Montreal",
    "sg:classifiers":[
        {
            "category":"Personal",
            "subcategory":"Beauty Salon",
            "type":"Services"
        }
    ],
    "sg:phone":"+1 514 389 5981",
    "sg:postcode":"H2C 1A6",
    "sg:province":"QC",
    "wof:name":"Salon DE Coiffure Civa",
    "wof:placetype":"venue"
},
  "geometry": {"coordinates":[-73.66913599999999,45.55743],"type":"Point"}
}