{
  "type": "Feature",
  "properties": {
    "addr:full":"154 King St E Gananoque ON K7G 1G2",
    "addr:housenumber":"154",
    "addr:postcode":"k7g 1g2",
    "addr:street":"King St E",
    "iso:country":"CA",
    "sg:address":"154 King St E",
    "sg:city":"Gananoque",
    "sg:classifiers":[
        {
            "category":"Home & Garden",
            "subcategory":"Household Appliances",
            "type":"Retail Goods"
        }
    ],
    "sg:phone":"+1 613 382 2105",
    "sg:postcode":"K7G 1G2",
    "sg:province":"ON",
    "sg:tags":[
        "mail",
        "catalog",
        "shopping",
        "order"
    ],
    "wof:name":"Sears Canada Inc",
    "wof:placetype":"venue"
},
  "geometry": {"coordinates":[-76.161644,44.330341],"type":"Point"}
}