{
  "type": "Feature",
  "properties": {
    "addr:full":"Angus ON L0M 1B2",
    "addr:postcode":"l0m 1b2",
    "iso:country":"CA",
    "sg:city":"Angus",
    "sg:classifiers":[
        {
            "category":"Taxi",
            "type":"Transportation"
        }
    ],
    "sg:phone":"+1 705 424 4444",
    "sg:postcode":"L0M 1B2",
    "sg:province":"ON",
    "sg:tags":[
        "taxicab"
    ],
    "wof:name":"Angus Taxi",
    "wof:placetype":"venue"
},
  "geometry": {"coordinates":[-79.88839,44.324852],"type":"Point"}
}