{
  "type": "Feature",
  "properties": {
    "addr:full":"3639 Boul Harvey Jonquiere QC G7X 3B2",
    "addr:housenumber":"3639",
    "addr:postcode":"g7x 3b2",
    "addr:street":"Boul Harvey",
    "iso:country":"CA",
    "sg:address":"3639 Boul Harvey",
    "sg:city":"Jonquiere",
    "sg:classifiers":[
        {
            "category":"Professional",
            "subcategory":"Lawyer & Legal Services",
            "type":"Services"
        }
    ],
    "sg:phone":"+1 418 547 2644",
    "sg:postcode":"G7X 3B2",
    "sg:province":"QC",
    "sg:tags":[
        "attorney"
    ],
    "wof:name":"Aide Juridique",
    "wof:placetype":"venue"
},
  "geometry": {"coordinates":[-71.23539,48.411716],"type":"Point"}
}