{
  "type": "Feature",
  "properties": {
    "addr:full":"Thetford Mines QC G6G 6K2",
    "addr:postcode":"g6g 6k2",
    "iso:country":"CA",
    "sg:city":"Thetford Mines",
    "sg:classifiers":[
        {
            "category":"Restaurant",
            "type":"Food & Drink"
        }
    ],
    "sg:phone":"+1 418 338 2185",
    "sg:postcode":"G6G 6K2",
    "sg:province":"QC",
    "wof:name":"Mike's Restaurant",
    "wof:placetype":"venue"
},
  "geometry": {"coordinates":[-71.30748,46.088699],"type":"Point"}
}