{
  "type": "Feature",
  "properties": {
    "addr:full":"9415 Transcanadienne Rte Saint-Laurent QC H4S 1V3",
    "addr:postcode":"9415;h4s 1v3",
    "addr:street":"Transcanadienne Rte Saint-Laurent",
    "iso:country":"CA",
    "sg:address":"9415 Transcanadienne Rte",
    "sg:city":"Saint-Laurent",
    "sg:classifiers":[
        {
            "category":"Wholesale",
            "subcategory":"Machinery & Supplies",
            "type":"Manufacturing & Wholesale Goods"
        }
    ],
    "sg:phone":"+1 514 733 9595",
    "sg:postcode":"H4S 1V3",
    "sg:province":"QC",
    "sg:tags":[
        "equipment",
        "pneumatic",
        "component"
    ],
    "wof:name":"Smc Pneumatics Ltee",
    "wof:placetype":"venue"
},
  "geometry": {"coordinates":[-73.7454833984,45.4911727905],"type":"Point"}
}