{
  "type": "Feature",
  "properties": {
    "addr:full":"7935 Rue Nantes Brossard QC J4Y 2E3",
    "addr:housenumber":"7935",
    "addr:postcode":"j4y 2e3",
    "addr:street":"Rue Nantes",
    "iso:country":"CA",
    "sg:address":"7935 Rue Nantes",
    "sg:city":"Brossard",
    "sg:classifiers":[
        {
            "category":"Professional",
            "subcategory":"Management & Consulting",
            "type":"Services"
        }
    ],
    "sg:phone":"+1 450 462 8008",
    "sg:postcode":"J4Y 2E3",
    "sg:province":"QC",
    "sg:tags":[
        "consultant",
        "business"
    ],
    "wof:name":"Marcotte, Lise",
    "wof:placetype":"venue"
},
  "geometry": {"coordinates":[-73.459923,45.446953],"type":"Point"}
}