{
  "type": "Feature",
  "properties": {
    "iso:country":"CA",
    "sg:city":"Calgary",
    "sg:classifiers":[
        {
            "category":"Organizations",
            "subcategory":"Professional Association",
            "type":"Services"
        }
    ],
    "sg:phone":"+1 403 236 4616",
    "sg:postcode":"T2C 2B3",
    "sg:province":"AB",
    "wof:name":"Alberta Golf Assoc",
    "wof:placetype":"venue"
},
  "geometry": {"coordinates":[-113.97531890899999,50.9967460632],"type":"Point"}
}