{
  "type": "Feature",
  "properties": {
    "addr:full":"Elliot Lake ON P5A 2W9",
    "addr:postcode":"p5a 2w9",
    "iso:country":"CA",
    "sg:city":"Elliot Lake",
    "sg:classifiers":[
        {
            "category":"Professional",
            "subcategory":"Business Services",
            "type":"Services"
        }
    ],
    "sg:phone":"+1 705 848 1337",
    "sg:postcode":"P5A 2W9",
    "sg:province":"ON",
    "sg:tags":[
        "information",
        "referral"
    ],
    "wof:name":"Elliot Lake Volunteer Resource",
    "wof:placetype":"venue"
},
  "geometry": {"coordinates":[-82.670906,46.37809],"type":"Point"}
}