{
  "type": "Feature",
  "properties": {
    "addr:full":"Quadeville ON K0J 2G0",
    "addr:postcode":"k0j 2g0",
    "iso:country":"CA",
    "sg:city":"Quadeville",
    "sg:classifiers":[
        {
            "category":"Organizations",
            "subcategory":"Religious Organization",
            "type":"Services"
        }
    ],
    "sg:phone":"+1 613 758 2368",
    "sg:postcode":"K0J 2G0",
    "sg:province":"ON",
    "sg:tags":[
        "church"
    ],
    "wof:name":"Quadeville Pentecostal Church",
    "wof:placetype":"venue"
},
  "geometry": {"coordinates":[-77.375198,45.314655],"type":"Point"}
}