{
  "type": "Feature",
  "properties": {
    "addr:full":"9057 Route 3 Old Ridge NB E3L 4W6",
    "addr:housenumber":"9057",
    "addr:postcode":"e3l 4w6",
    "addr:street":"Route 3;Ridge",
    "iso:country":"CA",
    "sg:address":"9057 Route 3",
    "sg:city":"Old Ridge",
    "sg:classifiers":[
        {
            "category":"Health Services",
            "subcategory":"Nursing And Care Facility",
            "type":"Services"
        }
    ],
    "sg:phone":"+1 506 466 1868",
    "sg:postcode":"E3L 4W6",
    "sg:province":"NB",
    "sg:tags":[
        "home",
        "convalescent"
    ],
    "wof:name":"St Stephen Seniors Complex",
    "wof:placetype":"venue"
},
  "geometry": {"coordinates":[-67.29125999999999,45.262718],"type":"Point"}
}