{
  "type": "Feature",
  "properties": {
    "addr:full":"3199 Grant Ave Winnipeg MB R3R 1X2",
    "addr:housenumber":"3199",
    "addr:postcode":"r3r 1x2",
    "addr:street":"Grant Ave",
    "iso:country":"CA",
    "sg:address":"3199 Grant Ave",
    "sg:city":"Winnipeg",
    "sg:classifiers":[
        {
            "category":"Health Services",
            "subcategory":"Nursing And Care Facility",
            "type":"Services"
        }
    ],
    "sg:phone":"+1 204 889 3330",
    "sg:postcode":"R3R 1X2",
    "sg:province":"MB",
    "sg:tags":[
        "personal",
        "home"
    ],
    "wof:name":"West Park Manor Personal Cr Hm",
    "wof:placetype":"venue"
},
  "geometry": {"coordinates":[-97.253433,49.858932],"type":"Point"}
}