{
  "type": "Feature",
  "properties": {
    "addr:full":"1 West St Corner Brook NL A2H 2Y6",
    "addr:housenumber":"1",
    "addr:postcode":"a2h 2y6",
    "addr:street":"West St",
    "iso:country":"CA",
    "sg:address":"1 West St",
    "sg:city":"Corner Brook",
    "sg:classifiers":[
        {
            "category":"Banks & Credit Unions",
            "subcategory":"Bank",
            "type":"Services"
        }
    ],
    "sg:phone":"+1 709 637 6500",
    "sg:postcode":"A2H 2Y6",
    "sg:province":"NL",
    "wof:name":"Bank of Montreal",
    "wof:placetype":"venue"
},
  "geometry": {"coordinates":[-57.945137,48.953049],"type":"Point"}
}