{
  "type": "Feature",
  "properties": {
    "addr:full":"Surrey BC V3W 1L3",
    "addr:postcode":"v3w 1l3",
    "iso:country":"CA",
    "sg:city":"Surrey",
    "sg:classifiers":[
        {
            "category":"Shopping",
            "subcategory":"Bicycles & Sporting Goods",
            "type":"Retail Goods"
        }
    ],
    "sg:phone":"+1 604 594 0664",
    "sg:postcode":"V3W 1L3",
    "sg:province":"BC",
    "sg:tags":[
        "backpacking",
        "mountaineering"
    ],
    "wof:name":"Vertical Reality Climbing Gym",
    "wof:placetype":"venue"
},
  "geometry": {"coordinates":[-122.867744446,49.1434440613],"type":"Point"}
}