{
  "type": "Feature",
  "properties": {
    "addr:full":"2220 Ponderosa Ave Kamloops BC V2B 4V9",
    "addr:housenumber":"2220",
    "addr:postcode":"bc v2b 4v9",
    "addr:street":"Ponderosa Ave",
    "iso:country":"CA",
    "sg:address":"2220 Ponderosa Ave",
    "sg:city":"Kamloops",
    "sg:classifiers":[
        {
            "category":"Building & Trades",
            "subcategory":"Construction",
            "type":"Services"
        }
    ],
    "sg:phone":"+1 250 376 7567",
    "sg:postcode":"V2B 4V9",
    "sg:province":"BC",
    "sg:tags":[
        "excavating",
        "contractor"
    ],
    "wof:name":"Buholzer Construction Ltd",
    "wof:placetype":"venue"
},
  "geometry": {"coordinates":[-120.407478,50.706642],"type":"Point"}
}