{
  "type": "Feature",
  "properties": {
    "iso:country":"CA",
    "sg:city":"Richmond",
    "sg:classifiers":[
        {
            "category":"Travel",
            "subcategory":"Travel Agent",
            "type":"Entertainment"
        }
    ],
    "sg:phone":"+1 604 278 1600",
    "sg:postcode":"V6X 3K5",
    "sg:province":"BC",
    "sg:tags":[
        "agency",
        "bureau"
    ],
    "wof:name":"Cruiseshipcentres",
    "wof:placetype":"venue"
},
  "geometry": {"coordinates":[-123.133072,49.172173],"type":"Point"}
}