{
  "type": "Feature",
  "properties": {
    "addr:full":"9 Rue Saint-Charles N Granby QC J2G 5T7",
    "addr:housenumber":"9",
    "addr:postcode":"j2g 5t7",
    "addr:street":"Rue Saint-Charles N",
    "iso:country":"CA",
    "sg:address":"9 Rue Saint-Charles N",
    "sg:city":"Granby",
    "sg:classifiers":[
        {
            "category":"Personal",
            "subcategory":"Beauty Salon",
            "type":"Services"
        }
    ],
    "sg:phone":"+1 450 777 2577",
    "sg:postcode":"J2G 5T7",
    "sg:province":"QC",
    "wof:name":"Salon Hexagone",
    "wof:placetype":"venue"
},
  "geometry": {"coordinates":[-72.73370361329999,45.4036521912],"type":"Point"}
}