{
  "type": "Feature",
  "properties": {
    "addr:full":"2037 St. Peter Ave Bathurst NB E2A 7J5",
    "addr:housenumber":"2037",
    "addr:postcode":"e2a 7j5",
    "addr:street":"St. Peter Ave",
    "iso:country":"CA",
    "sg:address":"2037 St. Peter Ave",
    "sg:city":"Bathurst",
    "sg:classifiers":[
        {
            "category":"Retail",
            "subcategory":"Auto Rental",
            "type":"Services"
        }
    ],
    "sg:phone":"+1 506 546 3344",
    "sg:postcode":"E2A 7J5",
    "sg:province":"NB",
    "sg:tags":[
        "renting",
        "automobile"
    ],
    "wof:name":"Discount Car & Truck Rentals",
    "wof:placetype":"venue"
},
  "geometry": {"coordinates":[-65.67926,47.653027],"type":"Point"}
}