{
  "type": "Feature",
  "properties": {
    "iso:country":"CA",
    "sg:address":"104 Kingswood Dr",
    "sg:city":"Courtice",
    "sg:classifiers":[
        {
            "category":"Real Estate",
            "subcategory":"Real Estate Agent",
            "type":"Services"
        }
    ],
    "sg:phone":"+1 905 576 9700",
    "sg:postcode":"L1E 1G2",
    "sg:province":"ON",
    "sg:tags":[
        "appraiser"
    ],
    "wof:name":"Pineridge Appraisals Inc",
    "wof:placetype":"venue"
},
  "geometry": {"coordinates":[-78.8096694946,43.9014816284],"type":"Point"}
}