{
  "type": "Feature",
  "properties": {
    "iso:country":"CA",
    "sg:city":"Winnipeg",
    "sg:classifiers":[
        {
            "category":"Building & Trades",
            "subcategory":"Construction",
            "type":"Services"
        }
    ],
    "sg:phone":"+1 204 661 8464",
    "sg:postcode":"R2P 2E1",
    "sg:province":"MB",
    "sg:tags":[
        "home",
        "improvement"
    ],
    "wof:name":"Westar Construction & Stucco",
    "wof:placetype":"venue"
},
  "geometry": {"coordinates":[-97.1536865234,49.9523620605],"type":"Point"}
}