{
  "type": "Feature",
  "properties": {
    "addr:full":"7600 Boul Viau Saint-Leonard QC H1S 2P3",
    "addr:housenumber":"7600",
    "addr:postcode":"h1s 2p3",
    "addr:street":"Boul Viau",
    "iso:country":"CA",
    "sg:address":"7600 Boul Viau",
    "sg:city":"Saint-Leonard",
    "sg:classifiers":[
        {
            "category":"Personal",
            "subcategory":"Beauty Salon",
            "type":"Services"
        }
    ],
    "sg:phone":"+1 514 728 6500",
    "sg:postcode":"H1S 2P3",
    "sg:province":"QC",
    "wof:name":"Magic Cut",
    "wof:placetype":"venue"
},
  "geometry": {"coordinates":[-73.59075199999999,45.574825],"type":"Point"}
}