{
  "type": "Feature",
  "properties": {
    "addr:full":"Repentigny QC J6A 7N2",
    "addr:postcode":"j6a 7n2",
    "iso:country":"CA",
    "sg:city":"Repentigny",
    "sg:classifiers":[
        {
            "category":"Freight",
            "type":"Transportation"
        }
    ],
    "sg:phone":"+1 450 585 7771",
    "sg:postcode":"J6A 7N2",
    "sg:province":"QC",
    "sg:tags":[
        "trucking"
    ],
    "wof:name":"Transit Du-Roy",
    "wof:placetype":"venue"
},
  "geometry": {"coordinates":[-73.448868,45.7537],"type":"Point"}
}