{
  "type": "Feature",
  "properties": {
    "iso:country":"CA",
    "sg:address":"530 Otto Rd",
    "sg:city":"Mississauga",
    "sg:classifiers":[
        {
            "category":"Professional",
            "type":"Services"
        }
    ],
    "sg:phone":"+1 905 670 0468",
    "sg:postcode":"L5T 2L5",
    "sg:province":"ON",
    "sg:tags":[
        "establishment",
        "transportation",
        "consultant"
    ],
    "wof:name":"Road Authority",
    "wof:placetype":"venue"
},
  "geometry": {"coordinates":[-79.677414,43.643471],"type":"Point"}
}