{
  "type": "Feature",
  "properties": {
    "addr:full":"11302 89 Ave Grande Prairie AB T8V 5V8",
    "addr:housenumber":"11302",
    "addr:postcode":"t8v 5v8",
    "addr:street":"89 Ave",
    "iso:country":"CA",
    "sg:address":"11302 89 Ave",
    "sg:city":"Grande Prairie",
    "sg:classifiers":[
        {
            "category":"Wholesale",
            "subcategory":"Machinery & Supplies",
            "type":"Manufacturing & Wholesale Goods"
        }
    ],
    "sg:phone":"+1 780 539 2333",
    "sg:postcode":"T8V 5V8",
    "sg:province":"AB",
    "sg:tags":[
        "equipment",
        "oil",
        "well",
        "valve"
    ],
    "wof:name":"Cooper Cameron",
    "wof:placetype":"venue"
},
  "geometry": {"coordinates":[-118.838722229,55.1594314575],"type":"Point"}
}