{
  "type": "Feature",
  "properties": {
    "addr:full":"St-Paul QC J6E 3H3",
    "addr:postcode":"j6e 3h3",
    "iso:country":"CA",
    "sg:city":"St-Paul",
    "sg:classifiers":[
        {
            "category":"Manufacturing",
            "subcategory":"Metals",
            "type":"Manufacturing & Wholesale Goods"
        }
    ],
    "sg:phone":"+1 450 759 1313",
    "sg:postcode":"J6E 3H3",
    "sg:province":"QC",
    "sg:tags":[
        "plating",
        "finisher"
    ],
    "wof:name":"DDS Inc",
    "wof:placetype":"venue"
},
  "geometry": {"coordinates":[-73.47374725340001,45.998790741],"type":"Point"}
}