{
  "type": "Feature",
  "properties": {
    "iso:country":"CA",
    "sg:address":"7600 Tecumseh Rd E",
    "sg:city":"Windsor",
    "sg:classifiers":[
        {
            "category":"Shopping",
            "subcategory":"Optical Goods",
            "type":"Retail Goods"
        }
    ],
    "sg:phone":"+1 519 944 6474",
    "sg:postcode":"N8T 1E9",
    "sg:province":"ON",
    "sg:tags":[
        "sun",
        "goggles",
        "sunglasses"
    ],
    "wof:name":"Hakim Optical",
    "wof:placetype":"venue"
},
  "geometry": {"coordinates":[-82.9357223511,42.3136482239],"type":"Point"}
}