{
  "type": "Feature",
  "properties": {
    "iso:country":"CA",
    "sg:address":"12703 Kimberly Dr",
    "sg:city":"Windsor",
    "sg:classifiers":[
        {
            "category":"Retail",
            "subcategory":"Portrait Studio",
            "type":"Services"
        }
    ],
    "sg:phone":"+1 519 735 3319",
    "sg:postcode":"N8N 3M1",
    "sg:province":"ON",
    "sg:tags":[
        "photographer"
    ],
    "wof:name":"Seguin Studios",
    "wof:placetype":"venue"
},
  "geometry": {"coordinates":[-83.0339126587,42.3178215027],"type":"Point"}
}