{
  "type": "Feature",
  "properties": {
    "addr:full":"Farm Dodsland SK S0L 0V0",
    "addr:postcode":"s0l 0v0",
    "addr:street":"Dodsland",
    "iso:country":"CA",
    "sg:address":"Farm",
    "sg:city":"Dodsland",
    "sg:classifiers":[
        {
            "category":"Wholesale",
            "subcategory":"Machinery & Supplies",
            "type":"Manufacturing & Wholesale Goods"
        }
    ],
    "sg:phone":"+1 306 356 4550",
    "sg:postcode":"S0L 0V0",
    "sg:province":"SK",
    "sg:tags":[
        "agricultural",
        "implement"
    ],
    "wof:name":"Ron Brown Implements",
    "wof:placetype":"venue"
},
  "geometry": {"coordinates":[-108.83925600000001,51.799831],"type":"Point"}
}