{
  "type": "Feature",
  "properties": {
    "addr:full":"4010 76 Ave NW Edmonton AB T6B 2P1",
    "addr:housenumber":"4010",
    "addr:postcode":"t6b 2p1",
    "addr:street":"76 Ave Nw",
    "iso:country":"CA",
    "sg:address":"4010 76 Ave NW",
    "sg:city":"Edmonton",
    "sg:classifiers":[
        {
            "category":"Professional",
            "subcategory":"Engineering",
            "type":"Services"
        }
    ],
    "sg:phone":"+1 780 440 4411",
    "sg:postcode":"T6B 2P1",
    "sg:province":"AB",
    "sg:tags":[
        "engineer"
    ],
    "wof:name":"Al-Terra Engineering Ltd",
    "wof:placetype":"venue"
},
  "geometry": {"coordinates":[-113.403274536,53.512512207],"type":"Point"}
}