{
  "type": "Feature",
  "properties": {
    "addr:full":"5010 Glen Erin Dr Mississauga ON L5M 6J3",
    "addr:housenumber":"5010",
    "addr:postcode":"l5m 6j3",
    "addr:street":"Glen Erin Dr",
    "iso:country":"CA",
    "sg:address":"5010 Glen Erin Dr",
    "sg:city":"Mississauga",
    "sg:classifiers":[
        {
            "category":"Manufacturing",
            "subcategory":"Food",
            "type":"Manufacturing & Wholesale Goods"
        }
    ],
    "sg:phone":"+1 905 820 5552",
    "sg:postcode":"L5M 6J3",
    "sg:province":"ON",
    "sg:tags":[
        "liquor",
        "winery",
        "store"
    ],
    "wof:name":"Colio Estate Wines Inc",
    "wof:placetype":"venue"
},
  "geometry": {"coordinates":[-79.711983,43.55405],"type":"Point"}
}