{
  "type": "Feature",
  "properties": {
    "addr:full":"3901 Jane St North York ON M3N 2K1",
    "addr:housenumber":"3901",
    "addr:postcode":"m3n 2k1",
    "addr:street":"Jane St",
    "iso:country":"CA",
    "sg:address":"3901 Jane St",
    "sg:city":"North York",
    "sg:classifiers":[
        {
            "category":"Shopping",
            "subcategory":"Clothing, Apparel, & Fashions",
            "type":"Retail Goods"
        }
    ],
    "sg:phone":"+1 416 638 2124",
    "sg:postcode":"M3N 2K1",
    "sg:province":"ON",
    "sg:tags":[
        "tailor"
    ],
    "wof:name":"Tran's Sewing Ctr",
    "wof:placetype":"venue"
},
  "geometry": {"coordinates":[-79.51745605470001,43.7568511963],"type":"Point"}
}