{
  "type": "Feature",
  "properties": {
    "addr:full":"4612 53 St Camrose AB T4V 1Y6",
    "addr:housenumber":"4612",
    "addr:postcode":"t4v 1y6",
    "addr:street":"53 St",
    "iso:country":"CA",
    "sg:address":"4612 53 St",
    "sg:city":"Camrose",
    "sg:classifiers":[
        {
            "category":"Health Services",
            "subcategory":"Nursing And Care Facility",
            "type":"Services"
        }
    ],
    "sg:phone":"+1 780 679 3000",
    "sg:postcode":"T4V 1Y6",
    "sg:province":"AB",
    "sg:tags":[
        "home",
        "hospital",
        "convalescent"
    ],
    "wof:name":"Rosehaven Care Ctr",
    "wof:placetype":"venue"
},
  "geometry": {"coordinates":[-112.83137499999999,53.014725],"type":"Point"}
}