{
  "type": "Feature",
  "properties": {
    "addr:full":"21096 91A Ave Langley BC V1M 2C4",
    "addr:housenumber":"21096",
    "addr:postcode":"v1m 2c4",
    "addr:street":"91A Ave",
    "iso:country":"CA",
    "sg:address":"21096 91A Ave",
    "sg:city":"Langley",
    "sg:classifiers":[
        {
            "category":"Shopping",
            "subcategory":"Computers & Home Electronics",
            "type":"Retail Goods"
        }
    ],
    "sg:phone":"+1 604 882 8830",
    "sg:postcode":"V1M 2C4",
    "sg:province":"BC",
    "sg:tags":[
        "equipment",
        "dealer"
    ],
    "wof:name":"Blue Collar Computers",
    "wof:placetype":"venue"
},
  "geometry": {"coordinates":[-122.65657,49.104122],"type":"Point"}
}