{
  "type": "Feature",
  "properties": {
    "addr:full":"756 Hunter Dr Nacmine AB T0J 2E0",
    "addr:housenumber":"756",
    "addr:postcode":"t0j 2e0",
    "addr:street":"Hunter Dr",
    "iso:country":"CA",
    "sg:address":"756 Hunter Dr",
    "sg:city":"Nacmine",
    "sg:classifiers":[
        {
            "category":"Retail",
            "subcategory":"Car Wash",
            "type":"Services"
        }
    ],
    "sg:phone":"+1 403 823 3700",
    "sg:postcode":"T0J 2E0",
    "sg:province":"AB",
    "sg:tags":[
        "polishing",
        "washing"
    ],
    "wof:name":"Powder Buff Car Detail",
    "wof:placetype":"venue"
},
  "geometry": {"coordinates":[-112.77719116199999,51.4664611816],"type":"Point"}
}