{
  "type": "Feature",
  "properties": {
    "addr:full":"Kelowna BC V1Y 8Z5",
    "addr:postcode":"v1y 8z5",
    "iso:country":"CA",
    "sg:city":"Kelowna",
    "sg:classifiers":[
        {
            "category":"Health Services",
            "subcategory":"Clinic",
            "type":"Services"
        }
    ],
    "sg:phone":"+1 250 979 3937",
    "sg:postcode":"V1Y 8Z5",
    "sg:province":"BC",
    "sg:tags":[
        "laser",
        "treatment"
    ],
    "wof:name":"Kelowna Laser Vision Inc",
    "wof:placetype":"venue"
},
  "geometry": {"coordinates":[-119.489959717,49.864528656],"type":"Point"}
}