{
  "type": "Feature",
  "properties": {
    "addr:full":"201 Marsh St Clarksburg ON N0H 1J0",
    "addr:housenumber":"201",
    "addr:postcode":"n0h 1j0",
    "addr:street":"Marsh St",
    "iso:country":"CA",
    "sg:address":"201 Marsh St",
    "sg:city":"Clarksburg",
    "sg:classifiers":[
        {
            "category":"Shopping",
            "subcategory":"Used Merchandise",
            "type":"Retail Goods"
        }
    ],
    "sg:phone":"+1 519 599 6811",
    "sg:postcode":"N0H 1J0",
    "sg:province":"ON",
    "sg:tags":[
        "second",
        "store",
        "hand"
    ],
    "wof:name":"Clarksburgers",
    "wof:placetype":"venue"
},
  "geometry": {"coordinates":[-80.46165466310001,44.5469017029],"type":"Point"}
}