{
  "type": "Feature",
  "properties": {
    "addr:full":"601 Mowat Ave Fort Frances ON P9A 1Z2",
    "addr:housenumber":"601",
    "addr:postcode":"p9a 1z2",
    "addr:street":"Mowat Ave",
    "iso:country":"CA",
    "sg:address":"601 Mowat Ave",
    "sg:city":"Fort Frances",
    "sg:classifiers":[
        {
            "category":"Banks & Credit Unions",
            "subcategory":"Bank",
            "type":"Services"
        }
    ],
    "sg:phone":"+1 807 274 3217",
    "sg:postcode":"P9A 1Z2",
    "sg:province":"ON",
    "wof:name":"Northern Lights Credit Union",
    "wof:placetype":"venue"
},
  "geometry": {"coordinates":[-93.398735,48.611107],"type":"Point"}
}