{
  "type": "Feature",
  "properties": {
    "addr:full":"Saint-Hyacinthe QC J2S 3N5",
    "addr:postcode":"j2s 3n5",
    "iso:country":"CA",
    "sg:city":"Saint-Hyacinthe",
    "sg:classifiers":[
        {
            "category":"Wholesale",
            "subcategory":"Electrical",
            "type":"Manufacturing & Wholesale Goods"
        }
    ],
    "sg:phone":"+1 450 774 2308",
    "sg:postcode":"J2S 3N5",
    "sg:province":"QC",
    "sg:tags":[
        "protective",
        "fire",
        "alarm",
        "system",
        "robbery",
        "burglary"
    ],
    "wof:name":"Lussier Alarme Enr",
    "wof:placetype":"venue"
},
  "geometry": {"coordinates":[-72.94021600000001,45.624592],"type":"Point"}
}