{
  "type": "Feature",
  "properties": {
    "addr:full":"1615 Acadia Dr Saskatoon SK S7H 5K7",
    "addr:housenumber":"1615",
    "addr:postcode":"s7h 5k7",
    "addr:street":"Acadia Dr",
    "iso:country":"CA",
    "sg:address":"1615 Acadia Dr",
    "sg:city":"Saskatoon",
    "sg:classifiers":[
        {
            "category":"Arts & Performance",
            "subcategory":"Theater",
            "type":"Entertainment"
        }
    ],
    "sg:phone":"+1 306 222 6060",
    "sg:postcode":"S7H 5K7",
    "sg:province":"SK",
    "sg:tags":[
        "live",
        "music"
    ],
    "wof:name":"Sunset Music Productions",
    "wof:placetype":"venue"
},
  "geometry": {"coordinates":[-106.598663,52.106487],"type":"Point"}
}