{
  "type": "Feature",
  "properties": {
    "addr:full":"274 Raglan St S Renfrew ON K7V 1R4",
    "addr:housenumber":"274",
    "addr:postcode":"k7v 1r4",
    "addr:street":"Raglan St S",
    "iso:country":"CA",
    "sg:address":"274 Raglan St S",
    "sg:city":"Renfrew",
    "sg:classifiers":[
        {
            "category":"Insurance",
            "subcategory":"Insurance Agent",
            "type":"Services"
        }
    ],
    "sg:phone":"+1 613 432 5617",
    "sg:postcode":"K7V 1R4",
    "sg:province":"ON",
    "sg:tags":[
        "consultant",
        "planning",
        "financial"
    ],
    "wof:name":"Money Concepts",
    "wof:placetype":"venue"
},
  "geometry": {"coordinates":[-76.68273925779999,45.4706611633],"type":"Point"}
}