{
  "type": "Feature",
  "properties": {
    "addr:full":"11 Boul Labelle Sainte-Therese QC J7E 2X1",
    "addr:housenumber":"11",
    "addr:postcode":"j7e 2x1",
    "addr:street":"Boul Labelle Sainte-Therese",
    "iso:country":"CA",
    "sg:address":"11 Boul Labelle",
    "sg:city":"Sainte-Therese",
    "sg:classifiers":[
        {
            "category":"Manufacturing",
            "subcategory":"Printing",
            "type":"Manufacturing & Wholesale Goods"
        }
    ],
    "sg:phone":"+1 450 430 4740",
    "sg:postcode":"J7E 2X1",
    "sg:province":"QC",
    "sg:tags":[
        "printer"
    ],
    "wof:name":"Imprimerie Vaudry Inc",
    "wof:placetype":"venue"
},
  "geometry": {"coordinates":[-73.826469,45.638161],"type":"Point"}
}