{
  "type": "Feature",
  "properties": {
    "addr:full":"York ON M6M 1S7",
    "addr:postcode":"m6m 1s7",
    "iso:country":"CA",
    "sg:city":"York",
    "sg:classifiers":[
        {
            "category":"Health Services",
            "subcategory":"Doctor",
            "type":"Services"
        }
    ],
    "sg:phone":"+1 416 751 7760",
    "sg:postcode":"M6M 1S7",
    "sg:province":"ON",
    "sg:tags":[
        "dentist"
    ],
    "wof:name":"Zeit, Gerald DDS",
    "wof:placetype":"venue"
},
  "geometry": {"coordinates":[-79.464935,43.691921],"type":"Point"}
}