{
  "type": "Feature",
  "properties": {
    "addr:full":"432 Av Du Mont-Royal E Montreal QC H2J 1W1",
    "addr:postcode":"h2j 1w1",
    "addr:street":"432 Av Du Mont-Royal E",
    "iso:country":"CA",
    "sg:address":"432 Av Du Mont-Royal E",
    "sg:city":"Montreal",
    "sg:classifiers":[
        {
            "category":"Health Services",
            "subcategory":"Optometrist",
            "type":"Services"
        }
    ],
    "sg:phone":"+1 514 843 3711",
    "sg:postcode":"H2J 1W1",
    "sg:province":"QC",
    "wof:name":"Clinique D'Optique Metro",
    "wof:placetype":"venue"
},
  "geometry": {"coordinates":[-73.5824050903,45.5242614746],"type":"Point"}
}