{
  "type": "Feature",
  "properties": {
    "iso:country":"CA",
    "sg:city":"London",
    "sg:classifiers":[
        {
            "category":"Manufacturing",
            "subcategory":"Tools & Machinery",
            "type":"Manufacturing & Wholesale Goods"
        }
    ],
    "sg:phone":"+1 519 432 0909",
    "sg:postcode":"N6A 3G3",
    "sg:province":"ON",
    "sg:tags":[
        "optical",
        "optician"
    ],
    "wof:name":"Eyes on Richmond",
    "wof:placetype":"venue"
},
  "geometry": {"coordinates":[-81.251007,42.991005],"type":"Point"}
}