{
  "type": "Feature",
  "properties": {
    "addr:full":"85 Prince Edward St Saint John NB E2L 3S1",
    "addr:housenumber":"85",
    "addr:postcode":"nb e2l 3s1",
    "addr:street":"Prince Edward St",
    "iso:country":"CA",
    "sg:address":"85 Prince Edward St",
    "sg:city":"Saint John",
    "sg:classifiers":[
        {
            "category":"Professional",
            "subcategory":"Computer Services",
            "type":"Services"
        }
    ],
    "sg:phone":"+1 506 636 8574",
    "sg:postcode":"E2L 3S1",
    "sg:province":"NB",
    "sg:tags":[
        "cashing",
        "check",
        "internet"
    ],
    "wof:name":"Cash Now Ltd",
    "wof:placetype":"venue"
},
  "geometry": {"coordinates":[-66.05512237550001,45.2769126892],"type":"Point"}
}