{
  "type": "Feature",
  "properties": {
    "addr:full":"80 Mill St # 1109 Toronto ON M5A 4T3",
    "addr:housenumber":"80",
    "addr:postcode":"m5a 4t3",
    "addr:street":"Mill St # 1109",
    "iso:country":"CA",
    "sg:address":"80 Mill St # 1109",
    "sg:city":"Toronto",
    "sg:classifiers":[
        {
            "category":"Professional",
            "subcategory":"Management & Consulting",
            "type":"Services"
        }
    ],
    "sg:phone":"+1 416 961 0030",
    "sg:postcode":"M5A 4T3",
    "sg:province":"ON",
    "sg:tags":[
        "consultant",
        "business"
    ],
    "wof:name":"Harrows End Holdings",
    "wof:placetype":"venue"
},
  "geometry": {"coordinates":[-79.358582,43.651157],"type":"Point"}
}