{
  "type": "Feature",
  "properties": {
    "addr:full":"4230 Armadale Rd Pender Island BC V0N 2M1",
    "addr:postcode":"4230;v0n 2m1",
    "addr:street":"Armadale Rd",
    "iso:country":"CA",
    "sg:address":"4230 Armadale Rd",
    "sg:city":"Pender Island",
    "sg:classifiers":[
        {
            "category":"Travel",
            "subcategory":"Hotels & Motels",
            "type":"Entertainment"
        }
    ],
    "sg:phone":"+1 250 629 6691",
    "sg:postcode":"V0N 2M1",
    "sg:province":"BC",
    "sg:tags":[
        "breakfast",
        "accommodation",
        "bed"
    ],
    "wof:name":"Oceanside Inn",
    "wof:placetype":"venue"
},
  "geometry": {"coordinates":[-123.281525,48.810333],"type":"Point"}
}