{
  "type": "Feature",
  "properties": {
    "addr:full":"1900 Lauder Dr Ottawa ON K2A 1B1",
    "addr:housenumber":"1900",
    "addr:postcode":"k2a 1b1",
    "addr:street":"Lauder Dr",
    "iso:country":"CA",
    "sg:address":"1900 Lauder Dr",
    "sg:city":"Ottawa",
    "sg:classifiers":[
        {
            "category":"Organizations",
            "subcategory":"Religious Organization",
            "type":"Services"
        }
    ],
    "sg:phone":"+1 613 722 2834",
    "sg:postcode":"K2A 1B1",
    "sg:province":"ON",
    "sg:tags":[
        "church"
    ],
    "wof:name":"Bromley Road Baptist Church",
    "wof:placetype":"venue"
},
  "geometry": {"coordinates":[-75.761543,45.375816],"type":"Point"}
}