{
  "type": "Feature",
  "properties": {
    "addr:full":"32219 Dewdney Trunk Rd Mission BC V4S 1L7",
    "addr:housenumber":"32219",
    "addr:postcode":"v4s 1l7",
    "addr:street":"Dewdney Trunk Rd",
    "iso:country":"CA",
    "sg:address":"32219 Dewdney Trunk Rd",
    "sg:city":"Mission",
    "sg:classifiers":[
        {
            "category":"Building & Trades",
            "subcategory":"Construction",
            "type":"Services"
        }
    ],
    "sg:phone":"+1 604 820 8602",
    "sg:postcode":"V4S 1L7",
    "sg:province":"BC",
    "sg:tags":[
        "maker",
        "cabinet"
    ],
    "wof:name":"Morrison Creations",
    "wof:placetype":"venue"
},
  "geometry": {"coordinates":[-122.33572387700001,49.2286262512],"type":"Point"}
}