{
  "type": "Feature",
  "properties": {
    "addr:full":"Richmond BC V6X 2E3",
    "addr:postcode":"v6x 2e3",
    "iso:country":"CA",
    "sg:city":"Richmond",
    "sg:classifiers":[
        {
            "category":"Health Services",
            "subcategory":"Doctor",
            "type":"Services"
        }
    ],
    "sg:phone":"+1 604 278 8613",
    "sg:postcode":"V6X 2E3",
    "sg:province":"BC",
    "sg:tags":[
        "dentist"
    ],
    "wof:name":"Lau, C K Eric DDS",
    "wof:placetype":"venue"
},
  "geometry": {"coordinates":[-123.136680603,49.1707000732],"type":"Point"}
}