{
  "type": "Feature",
  "properties": {
    "addr:full":"Saint-Jean-Sur-Richelieu QC J3A 1M1",
    "addr:postcode":"j3a 1m1",
    "iso:country":"CA",
    "sg:city":"Saint-Jean-Sur-Richelieu",
    "sg:classifiers":[
        {
            "category":"Restaurant",
            "type":"Food & Drink"
        }
    ],
    "sg:phone":"+1 450 359 7427",
    "sg:postcode":"J3A 1M1",
    "sg:province":"QC",
    "wof:name":"Resto-Bar O'Ribs",
    "wof:placetype":"venue"
},
  "geometry": {"coordinates":[-73.2814788818,45.331577301],"type":"Point"}
}