{
  "type": "Feature",
  "properties": {
    "addr:full":"2154 Rue Moreau Montreal QC H1W 2M3",
    "addr:housenumber":"2154",
    "addr:postcode":"h1w 2m3",
    "addr:street":"Rue Moreau",
    "iso:country":"CA",
    "sg:address":"2154 Rue Moreau",
    "sg:city":"Montreal",
    "sg:classifiers":[
        {
            "category":"Professional",
            "subcategory":"Business Services",
            "type":"Services"
        }
    ],
    "sg:phone":"+1 514 527 1720",
    "sg:postcode":"H1W 2M3",
    "sg:province":"QC",
    "sg:tags":[
        "packaging"
    ],
    "wof:name":"Entreprises Denis Caisse Inc",
    "wof:placetype":"venue"
},
  "geometry": {"coordinates":[-73.55010986329999,45.5400238037],"type":"Point"}
}