{
  "type": "Feature",
  "properties": {
    "addr:full":"3121 1 Rang Doncaster Val-David QC J0T 2N0",
    "addr:housenumber":"3121 1",
    "addr:postcode":"j0t 2n0",
    "addr:street":"Rang Doncaster",
    "iso:country":"CA",
    "sg:address":"3121 1 Rang Doncaster",
    "sg:city":"Val-David",
    "sg:classifiers":[
        {
            "category":"Travel",
            "subcategory":"Campground",
            "type":"Entertainment"
        }
    ],
    "sg:phone":"+1 819 322 3207",
    "sg:postcode":"J0T 2N0",
    "sg:province":"QC",
    "wof:name":"Domaine LA Belle Etoile Inc",
    "wof:placetype":"venue"
},
  "geometry": {"coordinates":[-74.19619,46.046936],"type":"Point"}
}