{
  "type": "Feature",
  "properties": {
    "addr:full":"3 Beck Blvd Penetanguishene ON L9M 1B9",
    "addr:housenumber":"3",
    "addr:postcode":"l9m 1b9",
    "addr:street":"Beck Blvd",
    "iso:country":"CA",
    "sg:address":"3 Beck Blvd",
    "sg:city":"Penetanguishene",
    "sg:classifiers":[
        {
            "category":"Restaurant",
            "type":"Food & Drink"
        }
    ],
    "sg:phone":"+1 705 549 6262",
    "sg:postcode":"L9M 1B9",
    "sg:province":"ON",
    "wof:name":"Arthur's Fine Family Dining",
    "wof:placetype":"venue"
},
  "geometry": {"coordinates":[-79.9374923706,44.7733383179],"type":"Point"}
}