{
  "type": "Feature",
  "properties": {
    "addr:full":"70 Main St N Wadena SK S0A 4J0",
    "addr:housenumber":"70",
    "addr:postcode":"s0a 4j0",
    "addr:street":"Main St N",
    "iso:country":"CA",
    "sg:address":"70 Main St N",
    "sg:city":"Wadena",
    "sg:classifiers":[
        {
            "category":"Restaurant",
            "type":"Food & Drink"
        }
    ],
    "sg:phone":"+1 306 338 2212",
    "sg:postcode":"S0A 4J0",
    "sg:province":"SK",
    "sg:tags":[
        "baker"
    ],
    "wof:name":"Wadena Bakery Ltd",
    "wof:placetype":"venue"
},
  "geometry": {"coordinates":[-103.80140686,51.942943573],"type":"Point"}
}