{
  "type": "Feature",
  "properties": {
    "addr:full":"122 Grey St Winnipeg MB R2L 1V5",
    "addr:housenumber":"122",
    "addr:postcode":"r2l 1v5",
    "addr:street":"Grey St",
    "iso:country":"CA",
    "sg:address":"122 Grey St",
    "sg:city":"Winnipeg",
    "sg:classifiers":[
        {
            "category":"Personal",
            "subcategory":"Barber",
            "type":"Services"
        }
    ],
    "sg:phone":"+1 204 669 4389",
    "sg:postcode":"R2L 1V5",
    "sg:province":"MB",
    "wof:name":"Style Rite Hairstylists",
    "wof:placetype":"venue"
},
  "geometry": {"coordinates":[-97.0949020386,49.9051170349],"type":"Point"}
}