{
  "type": "Feature",
  "properties": {
    "iso:country":"CA",
    "sg:address":"1680 Boul Saint-Joseph",
    "sg:city":"Lachine",
    "sg:classifiers":[
        {
            "category":"Health Services",
            "subcategory":"Medical Lab",
            "type":"Services"
        }
    ],
    "sg:phone":"+1 514 637 5430",
    "sg:postcode":"H8S 2N1",
    "sg:province":"QC",
    "wof:name":"Clinic of Dentures",
    "wof:placetype":"venue"
},
  "geometry": {"coordinates":[-73.679489,45.432716],"type":"Point"}
}