{
  "type": "Feature",
  "properties": {
    "iso:country":"CA",
    "sg:address":"152 Perth St",
    "sg:city":"Brockville",
    "sg:classifiers":[
        {
            "category":"Manufacturing",
            "subcategory":"Tools & Machinery",
            "type":"Manufacturing & Wholesale Goods"
        }
    ],
    "sg:phone":"+1 613 342 4150",
    "sg:postcode":"K6V 5E5",
    "sg:province":"ON",
    "sg:tags":[
        "lighting",
        "fixture"
    ],
    "wof:name":"401 Electric Store",
    "wof:placetype":"venue"
},
  "geometry": {"coordinates":[-75.69375610349999,44.5921669006],"type":"Point"}
}