{
  "type": "Feature",
  "properties": {
    "iso:country":"CA",
    "sg:address":"10 Abbey Rd",
    "sg:city":"Brampton",
    "sg:classifiers":[
        {
            "category":"Wholesale",
            "subcategory":"Office Equipment",
            "type":"Manufacturing & Wholesale Goods"
        }
    ],
    "sg:phone":"+1 905 450 7927",
    "sg:postcode":"L6W 2T8",
    "sg:province":"ON",
    "sg:tags":[
        "register",
        "cash",
        "supply"
    ],
    "wof:name":"Metro Cash Register CO",
    "wof:placetype":"venue"
},
  "geometry": {"coordinates":[-79.7424316406,43.6810417175],"type":"Point"}
}