{
  "type": "Feature",
  "properties": {
    "addr:full":"58 Boul Hymus Pointe-Claire QC H9R 1C9",
    "addr:housenumber":"58",
    "addr:postcode":"h9r 1c9",
    "addr:street":"Boul Hymus",
    "iso:country":"CA",
    "sg:address":"58 Boul Hymus",
    "sg:city":"Pointe-Claire",
    "sg:classifiers":[
        {
            "category":"Manufacturing",
            "subcategory":"Printing",
            "type":"Manufacturing & Wholesale Goods"
        }
    ],
    "sg:phone":"+1 514 695 1314",
    "sg:postcode":"H9R 1C9",
    "sg:province":"QC",
    "sg:tags":[
        "printer"
    ],
    "wof:name":"Trans-Optique Inc",
    "wof:placetype":"venue"
},
  "geometry": {"coordinates":[-73.796181,45.473152],"type":"Point"}
}