{
  "type": "Feature",
  "properties": {
    "addr:full":"Quebec QC G2K 1N4",
    "addr:postcode":"g2k 1n4",
    "iso:country":"CA",
    "sg:city":"Quebec",
    "sg:classifiers":[
        {
            "category":"Shopping",
            "subcategory":"Clothing, Apparel, & Fashions",
            "type":"Retail Goods"
        }
    ],
    "sg:phone":"+1 418 628 0195",
    "sg:postcode":"G2K 1N4",
    "sg:province":"QC",
    "wof:name":"Boutique Claire France",
    "wof:placetype":"venue"
},
  "geometry": {"coordinates":[-71.2956771851,46.831237793],"type":"Point"}
}