{
  "type": "Feature",
  "properties": {
    "addr:full":"89 Water St Pugwash NS B0K 1L0",
    "addr:housenumber":"89",
    "addr:postcode":"b0k 1l0",
    "addr:street":"Water St",
    "iso:country":"CA",
    "sg:address":"89 Water St",
    "sg:city":"Pugwash",
    "sg:classifiers":[
        {
            "category":"Personal",
            "type":"Services"
        }
    ],
    "sg:phone":"+1 902 243 2080",
    "sg:postcode":"B0K 1L0",
    "sg:province":"NS",
    "sg:tags":[
        "program",
        "physical",
        "exercise",
        "fitness"
    ],
    "wof:name":"Seitl's Gym",
    "wof:placetype":"venue"
},
  "geometry": {"coordinates":[-63.661335,45.849506],"type":"Point"}
}