{
  "type": "Feature",
  "properties": {
    "iso:country":"CA",
    "sg:address":"90279 London Rd N",
    "sg:city":"Wingham",
    "sg:classifiers":[
        {
            "category":"Autos & Motor Vehicles",
            "subcategory":"Fuel & Gas Station",
            "type":"Retail Goods"
        }
    ],
    "sg:phone":"+1 519 357 4933",
    "sg:postcode":"N0G 2W0",
    "sg:province":"ON",
    "sg:tags":[
        "oil"
    ],
    "wof:name":"Royal T Gas Bar",
    "wof:placetype":"venue"
},
  "geometry": {"coordinates":[-81.3047866821,43.8965187073],"type":"Point"}
}