{
  "type": "Feature",
  "properties": {
    "addr:full":"2056 Bank St Ottawa ON K1V 7Z8",
    "addr:housenumber":"2056",
    "addr:postcode":"k1v 7z8",
    "addr:street":"Bank St",
    "iso:country":"CA",
    "sg:address":"2056 Bank St",
    "sg:city":"Ottawa",
    "sg:classifiers":[
        {
            "category":"Building & Trades",
            "subcategory":"Construction",
            "type":"Services"
        }
    ],
    "sg:phone":"+1 613 739 5306",
    "sg:postcode":"K1V 7Z8",
    "sg:province":"ON",
    "sg:tags":[
        "home",
        "rental",
        "improvement"
    ],
    "wof:name":"Home Depot Tool Rental",
    "wof:placetype":"venue"
},
  "geometry": {"coordinates":[-75.6572189331,45.361038208],"type":"Point"}
}