{
  "type": "Feature",
  "properties": {
    "addr:full":"1195 Wellington St W Ottawa ON K1Y 2Z6",
    "addr:housenumber":"1195",
    "addr:postcode":"k1y 2z6",
    "addr:street":"Wellington St W",
    "iso:country":"CA",
    "sg:address":"1195 Wellington St W",
    "sg:city":"Ottawa",
    "sg:classifiers":[
        {
            "category":"Personal",
            "subcategory":"Beauty Salon",
            "type":"Services"
        }
    ],
    "sg:phone":"+1 613 792 1000",
    "sg:postcode":"K1Y 2Z6",
    "sg:province":"ON",
    "wof:name":"Cutting Edge",
    "wof:placetype":"venue"
},
  "geometry": {"coordinates":[-75.730042,45.400539],"type":"Point"}
}