{
  "type": "Feature",
  "properties": {
    "addr:full":"8499 Rue Birnam Montreal QC H3N 2V2",
    "addr:housenumber":"8499",
    "addr:postcode":"h3n 2v2",
    "addr:street":"Rue Birnam",
    "iso:country":"CA",
    "sg:address":"8499 Rue Birnam",
    "sg:city":"Montreal",
    "sg:classifiers":[
        {
            "category":"Food & Beverages",
            "subcategory":"Groceries & Convenience Stores",
            "type":"Retail Goods"
        }
    ],
    "sg:phone":"+1 514 273 9146",
    "sg:postcode":"H3N 2V2",
    "sg:province":"QC",
    "sg:tags":[
        "grocer"
    ],
    "wof:name":"Marche Auset",
    "wof:placetype":"venue"
},
  "geometry": {"coordinates":[-73.643265,45.530067],"type":"Point"}
}