{
  "type": "Feature",
  "properties": {
    "addr:full":"Surrey BC V3S 8E5",
    "addr:postcode":"v3s 8e5",
    "iso:country":"CA",
    "sg:city":"Surrey",
    "sg:classifiers":[
        {
            "category":"Professional",
            "subcategory":"Art Services",
            "type":"Services"
        }
    ],
    "sg:phone":"+1 604 575 9016",
    "sg:postcode":"V3S 8E5",
    "sg:province":"BC",
    "sg:tags":[
        "graphic",
        "designer"
    ],
    "wof:name":"Canadian Multilink Graphics",
    "wof:placetype":"venue"
},
  "geometry": {"coordinates":[-122.691368,49.099617],"type":"Point"}
}