{
  "type": "Feature",
  "properties": {
    "addr:full":"142 Tilley Rd Gagetown NB E5M 1H6",
    "addr:housenumber":"142",
    "addr:postcode":"e5m 1h6",
    "addr:street":"Tilley Rd",
    "iso:country":"CA",
    "sg:address":"142 Tilley Rd",
    "sg:city":"Gagetown",
    "sg:classifiers":[
        {
            "category":"Health Services",
            "subcategory":"Nursing And Care Facility",
            "type":"Services"
        }
    ],
    "sg:phone":"+1 506 488 2620",
    "sg:postcode":"E5M 1H6",
    "sg:province":"NB",
    "sg:tags":[
        "home",
        "rest"
    ],
    "wof:name":"Gagetown Special Care Home",
    "wof:placetype":"venue"
},
  "geometry": {"coordinates":[-66.1523895264,45.778137207],"type":"Point"}
}