{
  "type": "Feature",
  "properties": {
    "addr:full":"150 Metcalfe St # 2100 Ottawa ON K2P 1P1",
    "addr:housenumber":"150",
    "addr:postcode":"k2p 1p1",
    "addr:street":"Metcalfe St # 2100",
    "iso:country":"CA",
    "sg:address":"150 Metcalfe St # 2100",
    "sg:city":"Ottawa",
    "sg:classifiers":[
        {
            "category":"Professional",
            "subcategory":"Research",
            "type":"Services"
        }
    ],
    "sg:phone":"+1 613 239 3817",
    "sg:postcode":"K2P 1P1",
    "sg:province":"ON",
    "sg:tags":[
        "development",
        "human",
        "factor"
    ],
    "wof:name":"Genome Canada",
    "wof:placetype":"venue"
},
  "geometry": {"coordinates":[-75.694962,45.419662],"type":"Point"}
}