{
  "type": "Feature",
  "properties": {
    "addr:full":"23 Fraxville Rd New Ross NS B0J 2M0",
    "addr:housenumber":"23",
    "addr:postcode":"b0j 2m0",
    "addr:street":"Fraxville Rd",
    "iso:country":"CA",
    "sg:address":"23 Fraxville Rd",
    "sg:city":"New Ross",
    "sg:classifiers":[
        {
            "category":"Manufacturing",
            "subcategory":"Lumber",
            "type":"Manufacturing & Wholesale Goods"
        }
    ],
    "sg:phone":"+1 902 689 2697",
    "sg:postcode":"B0J 2M0",
    "sg:province":"NS",
    "wof:name":"Murray A Reeves Forrestry Ltd",
    "wof:placetype":"venue"
},
  "geometry": {"coordinates":[-64.45358299999999,44.737045],"type":"Point"}
}