{
  "type": "Feature",
  "properties": {
    "iso:country":"CA",
    "sg:address":"10607 205 St NW",
    "sg:city":"Edmonton",
    "sg:classifiers":[
        {
            "category":"Wholesale",
            "subcategory":"Machinery & Supplies",
            "type":"Manufacturing & Wholesale Goods"
        }
    ],
    "sg:phone":"+1 780 447 3069",
    "sg:postcode":"T5S 2K3",
    "sg:province":"AB",
    "sg:tags":[
        "crane",
        "derrick"
    ],
    "wof:name":"Edmonton Crane Rentals Ltd",
    "wof:placetype":"venue"
},
  "geometry": {"coordinates":[-113.674285889,53.5496826172],"type":"Point"}
}