{
  "type": "Feature",
  "properties": {
    "addr:full":"373 Main St S Exeter ON N0M 1S0",
    "addr:housenumber":"373",
    "addr:postcode":"n0m 1s0",
    "addr:street":"Main St S",
    "iso:country":"CA",
    "sg:address":"373 Main St S",
    "sg:city":"Exeter",
    "sg:classifiers":[
        {
            "category":"Shopping",
            "subcategory":"Clothing, Apparel, & Fashions",
            "type":"Retail Goods"
        }
    ],
    "sg:phone":"+1 519 235 0442",
    "sg:postcode":"N0M 1S0",
    "sg:province":"ON",
    "sg:tags":[
        "furnishing"
    ],
    "wof:name":"Thomas H Fine Mens Wear",
    "wof:placetype":"venue"
},
  "geometry": {"coordinates":[-81.48060599999999,43.346443],"type":"Point"}
}