{
  "type": "Feature",
  "properties": {
    "addr:full":"236 Rue Notre-Dame E Victoriaville QC G6P 4A1",
    "addr:housenumber":"236",
    "addr:postcode":"g6p 4a1",
    "addr:street":"Rue Notre-Dame E",
    "iso:country":"CA",
    "sg:address":"236 Rue Notre-Dame E",
    "sg:city":"Victoriaville",
    "sg:classifiers":[
        {
            "category":"Shopping",
            "subcategory":"Bicycles & Sporting Goods",
            "type":"Retail Goods"
        }
    ],
    "sg:phone":"+1 819 752 6331",
    "sg:postcode":"G6P 4A1",
    "sg:province":"QC",
    "wof:name":"Reno Sport Inc",
    "wof:placetype":"venue"
},
  "geometry": {"coordinates":[-71.953186,46.057678],"type":"Point"}
}