{
  "type": "Feature",
  "properties": {
    "addr:full":"Surrey BC V3V 5Z4",
    "addr:postcode":"v3v 5z4",
    "iso:country":"CA",
    "sg:city":"Surrey",
    "sg:classifiers":[
        {
            "category":"Education",
            "subcategory":"School",
            "type":"Public Place"
        }
    ],
    "sg:phone":"+1 604 583 4040",
    "sg:postcode":"V3V 5Z4",
    "sg:province":"BC",
    "wof:name":"Adult & Continuing Education",
    "wof:placetype":"venue"
},
  "geometry": {"coordinates":[-122.834389,49.171471],"type":"Point"}
}