{
  "type": "Feature",
  "properties": {
    "addr:full":"79 Rue Du Zouave Salaberry-DE-Valleyfield QC J6T 2W4",
    "addr:housenumber":"79",
    "addr:postcode":"j6t 2w4",
    "addr:street":"Rue Du Zouave",
    "iso:country":"CA",
    "sg:address":"79 Rue Du Zouave",
    "sg:city":"Salaberry-DE-Valleyfield",
    "sg:classifiers":[
        {
            "category":"Social Services",
            "type":"Services"
        }
    ],
    "sg:phone":"+1 450 371 9617",
    "sg:postcode":"J6T 2W4",
    "sg:province":"QC",
    "sg:tags":[
        "organization",
        "welfare"
    ],
    "wof:name":"Maison D'Hebergement Depannage",
    "wof:placetype":"venue"
},
  "geometry": {"coordinates":[-74.13253,45.246265],"type":"Point"}
}