{
  "type": "Feature",
  "properties": {
    "addr:full":"20470 88 Ave Langley BC V1M 2Y6",
    "addr:housenumber":"20470",
    "addr:postcode":"v1m 2y6",
    "addr:street":"88 Ave",
    "iso:country":"CA",
    "sg:address":"20470 88 Ave",
    "sg:city":"Langley",
    "sg:classifiers":[
        {
            "category":"Travel",
            "subcategory":"Hotels & Motels",
            "type":"Entertainment"
        }
    ],
    "sg:phone":"+1 604 888 4891",
    "sg:postcode":"V1M 2Y6",
    "sg:province":"BC",
    "wof:name":"Langley Travelodge",
    "wof:placetype":"venue"
},
  "geometry": {"coordinates":[-122.65471599999999,49.162636],"type":"Point"}
}