{
  "type": "Feature",
  "properties": {
    "addr:full":"737 Schubert Dr Kamloops BC V2B 2G2",
    "addr:housenumber":"737",
    "addr:postcode":"bc v2b 2g2",
    "addr:street":"Schubert Dr",
    "iso:country":"CA",
    "sg:address":"737 Schubert Dr",
    "sg:city":"Kamloops",
    "sg:classifiers":[
        {
            "category":"Real Estate",
            "subcategory":"Architect",
            "type":"Services"
        }
    ],
    "sg:phone":"+1 250 554 9993",
    "sg:postcode":"V2B 2G2",
    "sg:province":"BC",
    "wof:name":"Nelson, Brian O",
    "wof:placetype":"venue"
},
  "geometry": {"coordinates":[-120.352486,50.697815],"type":"Point"}
}