{
  "type": "Feature",
  "properties": {
    "addr:full":"247 7E Rue O East Broughton Station QC G0N 1H0",
    "addr:housenumber":"247",
    "addr:postcode":"g0n 1h0",
    "addr:street":"7E Rue O",
    "iso:country":"CA",
    "sg:address":"247 7E Rue O",
    "sg:city":"East Broughton Station",
    "sg:classifiers":[
        {
            "category":"Restaurant",
            "type":"Food & Drink"
        }
    ],
    "sg:phone":"+1 418 427 2107",
    "sg:postcode":"G0N 1H0",
    "sg:province":"QC",
    "wof:name":"Cantine Dodier",
    "wof:placetype":"venue"
},
  "geometry": {"coordinates":[-71.081924,46.229713],"type":"Point"}
}