{
  "type": "Feature",
  "properties": {
    "addr:full":"Mississauga ON L4W 1N5",
    "addr:postcode":"l4w 1n5",
    "iso:country":"CA",
    "sg:city":"Mississauga",
    "sg:classifiers":[
        {
            "category":"Restaurant",
            "type":"Food & Drink"
        }
    ],
    "sg:phone":"+1 905 625 7775",
    "sg:postcode":"L4W 1N5",
    "sg:province":"ON",
    "wof:name":"Shandra's Roti Shop",
    "wof:placetype":"venue"
},
  "geometry": {"coordinates":[-79.62799099999999,43.630562],"type":"Point"}
}