{
  "type": "Feature",
  "properties": {
    "iso:country":"CA",
    "sg:address":"2065 Rue Bishop",
    "sg:city":"Montreal",
    "sg:classifiers":[
        {
            "category":"Food & Beverages",
            "subcategory":"Bakery",
            "type":"Retail Goods"
        }
    ],
    "sg:phone":"+1 514 285 5554",
    "sg:postcode":"H3G 2E8",
    "sg:province":"QC",
    "sg:tags":[
        "baker"
    ],
    "wof:name":"Uncle Guss Boulangerie Inc",
    "wof:placetype":"venue"
},
  "geometry": {"coordinates":[-73.578598,45.497845],"type":"Point"}
}