{
  "type": "Feature",
  "properties": {
    "addr:full":"2681 Hastings St E Vancouver BC V5K 1Z5",
    "addr:housenumber":"2681",
    "addr:postcode":"v5k 1z5",
    "addr:street":"Hastings St E",
    "iso:country":"CA",
    "sg:address":"2681 Hastings St E",
    "sg:city":"Vancouver",
    "sg:classifiers":[
        {
            "category":"Social Services",
            "type":"Services"
        }
    ],
    "sg:phone":"+1 604 255 3099",
    "sg:postcode":"V5K 1Z5",
    "sg:province":"BC",
    "sg:tags":[
        "organization",
        "association",
        "welfare"
    ],
    "wof:name":"Tenants Rights Coalition",
    "wof:placetype":"venue"
},
  "geometry": {"coordinates":[-123.049919,49.281273],"type":"Point"}
}