{
  "type": "Feature",
  "properties": {
    "addr:full":"452 30th St E Prince Albert SK S6V 5V4",
    "addr:housenumber":"452",
    "addr:postcode":"s6v 5v4",
    "addr:street":"30Th St",
    "iso:country":"CA",
    "sg:address":"452 30th St E",
    "sg:city":"Prince Albert",
    "sg:classifiers":[
        {
            "category":"Organizations",
            "subcategory":"Religious Organization",
            "type":"Services"
        }
    ],
    "sg:phone":"+1 306 763 7874",
    "sg:postcode":"S6V 5V4",
    "sg:province":"SK",
    "sg:tags":[
        "church"
    ],
    "wof:name":"Church of Jesus Christ of Lds",
    "wof:placetype":"venue"
},
  "geometry": {"coordinates":[-105.743156433,53.1859931946],"type":"Point"}
}