{
  "type": "Feature",
  "properties": {
    "addr:full":"780 Rue Notre-Dame Joliette QC J6E 3J6",
    "addr:housenumber":"780",
    "addr:postcode":"j6e 3j6",
    "addr:street":"Rue Notre-Dame",
    "iso:country":"CA",
    "sg:address":"780 Rue Notre-Dame",
    "sg:city":"Joliette",
    "sg:classifiers":[
        {
            "category":"Real Estate",
            "subcategory":"Architect",
            "type":"Services"
        }
    ],
    "sg:phone":"+1 450 759 0841",
    "sg:postcode":"J6E 3J6",
    "sg:province":"QC",
    "wof:name":"Roy Et Clavel Inc",
    "wof:placetype":"venue"
},
  "geometry": {"coordinates":[-73.444,46.020782],"type":"Point"}
}