{
  "type": "Feature",
  "properties": {
    "iso:country":"CA",
    "sg:address":"88 Setterington St",
    "sg:city":"Leamington",
    "sg:classifiers":[
        {
            "category":"Organizations",
            "subcategory":"Religious Organization",
            "type":"Services"
        }
    ],
    "sg:phone":"+1 519 326 4901",
    "sg:postcode":"N8H 1T6",
    "sg:province":"ON",
    "sg:tags":[
        "church"
    ],
    "wof:name":"Salvation Army",
    "wof:placetype":"venue"
},
  "geometry": {"coordinates":[-82.5916595459,42.0512084961],"type":"Point"}
}