{
  "type": "Feature",
  "properties": {
    "addr:full":"19 Montgomerie St Corner Brook NL A2H 2P8",
    "addr:housenumber":"19",
    "addr:postcode":"a2h 2p8",
    "addr:street":"Montgomerie St",
    "iso:country":"CA",
    "sg:address":"19 Montgomerie St",
    "sg:city":"Corner Brook",
    "sg:classifiers":[
        {
            "category":"Organizations",
            "subcategory":"Religious Organization",
            "type":"Services"
        }
    ],
    "sg:phone":"+1 709 634 9700",
    "sg:postcode":"A2H 2P8",
    "sg:province":"NL",
    "sg:tags":[
        "church"
    ],
    "wof:name":"Church of Jesus Christ-Lds",
    "wof:placetype":"venue"
},
  "geometry": {"coordinates":[-57.929813385,48.950881958],"type":"Point"}
}