{
  "type": "Feature",
  "properties": {
    "addr:full":"Schuler AB T0J 3B0",
    "addr:postcode":"t0j 3b0",
    "iso:country":"CA",
    "sg:city":"Schuler",
    "sg:classifiers":[
        {
            "category":"Food & Beverages",
            "subcategory":"Groceries & Convenience Stores",
            "type":"Retail Goods"
        }
    ],
    "sg:phone":"+1 403 839 2211",
    "sg:postcode":"T0J 3B0",
    "sg:province":"AB",
    "sg:tags":[
        "grocer"
    ],
    "wof:name":"Schuler Corner Store",
    "wof:placetype":"venue"
},
  "geometry": {"coordinates":[-110.094246,50.368176],"type":"Point"}
}