{
  "type": "Feature",
  "properties": {
    "addr:full":"Longueuil QC J4K 1W7",
    "addr:postcode":"j4k 1w7",
    "iso:country":"CA",
    "sg:city":"Longueuil",
    "sg:classifiers":[
        {
            "category":"Professional",
            "subcategory":"Accounting & Tax Preparation",
            "type":"Services"
        }
    ],
    "sg:phone":"+1 450 674 6203",
    "sg:postcode":"J4K 1W7",
    "sg:province":"QC",
    "sg:tags":[
        "accountant"
    ],
    "wof:name":"Senecal, Maurice",
    "wof:placetype":"venue"
},
  "geometry": {"coordinates":[-73.49748200000001,45.518784],"type":"Point"}
}