{
  "type": "Feature",
  "properties": {
    "iso:country":"CA",
    "sg:address":"RR 2 STN Lcd 1",
    "sg:city":"Hamilton",
    "sg:classifiers":[
        {
            "category":"Building & Trades",
            "subcategory":"Plumbing",
            "type":"Services"
        }
    ],
    "sg:phone":"+1 905 659 7415",
    "sg:postcode":"L8N 2Z7",
    "sg:province":"ON",
    "sg:tags":[
        "contractor"
    ],
    "wof:name":"Rick's Plumbing",
    "wof:placetype":"venue"
},
  "geometry": {"coordinates":[-79.888451,43.26099],"type":"Point"}
}