{
  "type": "Feature",
  "properties": {
    "addr:full":"Kelowna BC V1X 6A2",
    "addr:postcode":"v1x 6a2",
    "iso:country":"CA",
    "sg:city":"Kelowna",
    "sg:classifiers":[
        {
            "category":"Retail",
            "subcategory":"Auto Repair",
            "type":"Services"
        }
    ],
    "sg:phone":"+1 250 860 8370",
    "sg:postcode":"V1X 6A2",
    "sg:province":"BC",
    "sg:tags":[
        "repairing",
        "automobile"
    ],
    "wof:name":"Kelowna Auto Care",
    "wof:placetype":"venue"
},
  "geometry": {"coordinates":[-119.421531677,49.8838348389],"type":"Point"}
}