{
  "type": "Feature",
  "properties": {
    "addr:full":"43 Reid Ave Ottawa ON K1Y 1S5",
    "addr:housenumber":"43",
    "addr:postcode":"k1y 1s5",
    "addr:street":"Reid Ave",
    "iso:country":"CA",
    "sg:address":"43 Reid Ave",
    "sg:city":"Ottawa",
    "sg:classifiers":[
        {
            "category":"Wholesale",
            "subcategory":"Furniture",
            "type":"Manufacturing & Wholesale Goods"
        }
    ],
    "sg:phone":"+1 613 722 5343",
    "sg:postcode":"K1Y 1S5",
    "sg:province":"ON",
    "wof:name":"Jay Walsh Ltd",
    "wof:placetype":"venue"
},
  "geometry": {"coordinates":[-75.7222976685,45.3978233337],"type":"Point"}
}