{
  "type": "Feature",
  "properties": {
    "addr:full":"1975 Dundas St London ON N5V 4Y5",
    "addr:housenumber":"1975",
    "addr:postcode":"n5v 4y5",
    "addr:street":"Dundas St",
    "iso:country":"CA",
    "sg:address":"1975 Dundas St",
    "sg:city":"London",
    "sg:classifiers":[
        {
            "category":"Autos & Motor Vehicles",
            "subcategory":"Auto Supplies",
            "type":"Retail Goods"
        }
    ],
    "sg:phone":"+1 519 455 7272",
    "sg:postcode":"N5V 4Y5",
    "sg:province":"ON",
    "sg:tags":[
        "automobile",
        "parts"
    ],
    "wof:name":"Canadian Tire Gas Bar",
    "wof:placetype":"venue"
},
  "geometry": {"coordinates":[-81.17046356199999,43.0061035156],"type":"Point"}
}