{
  "type": "Feature",
  "properties": {
    "iso:country":"CA",
    "sg:city":"Matagami",
    "sg:classifiers":[
        {
            "category":"Manufacturing",
            "subcategory":"Lumber",
            "type":"Manufacturing & Wholesale Goods"
        }
    ],
    "sg:phone":"+1 819 739 4446",
    "sg:postcode":"J0Y 2A0",
    "sg:province":"QC",
    "sg:tags":[
        "forester"
    ],
    "wof:name":"Service Forestier Matagami Inc",
    "wof:placetype":"venue"
},
  "geometry": {"coordinates":[-77.6210403442,49.7586784363],"type":"Point"}
}