{
  "type": "Feature",
  "properties": {
    "addr:full":"Etobicoke ON M9B 6J8",
    "addr:postcode":"m9b 6j8",
    "iso:country":"CA",
    "sg:city":"Etobicoke",
    "sg:classifiers":[
        {
            "category":"Organizations",
            "subcategory":"Professional Association",
            "type":"Services"
        }
    ],
    "sg:phone":"+1 416 622 9771",
    "sg:postcode":"M9B 6J8",
    "sg:province":"ON",
    "wof:name":"Croplife Canada",
    "wof:placetype":"venue"
},
  "geometry": {"coordinates":[-79.5603637695,43.6477546692],"type":"Point"}
}