{
  "type": "Feature",
  "properties": {
    "iso:country":"CA",
    "sg:city":"Calgary",
    "sg:classifiers":[
        {
            "category":"Health Services",
            "subcategory":"Doctor",
            "type":"Services"
        }
    ],
    "sg:phone":"+1 403 777 3004",
    "sg:postcode":"T2W 4Y1",
    "sg:province":"AB",
    "sg:tags":[
        "physician",
        "surgeon"
    ],
    "wof:name":"Yacyshyn, Brian J MD",
    "wof:placetype":"venue"
},
  "geometry": {"coordinates":[-114.072632,50.958427],"type":"Point"}
}