{
  "type": "Feature",
  "properties": {
    "addr:full":"344 Bloor St W Toronto ON M5S 3A7",
    "addr:housenumber":"344",
    "addr:postcode":"m5s 3a7",
    "addr:street":"Bloor St W",
    "iso:country":"CA",
    "sg:address":"344 Bloor St W",
    "sg:city":"Toronto",
    "sg:classifiers":[
        {
            "category":"Health Services",
            "subcategory":"Clinic",
            "type":"Services"
        }
    ],
    "sg:phone":"+1 416 961 7812",
    "sg:postcode":"M5S 3A7",
    "sg:province":"ON",
    "sg:tags":[
        "information",
        "abortion"
    ],
    "wof:name":"Childbirth By Choice Trust",
    "wof:placetype":"venue"
},
  "geometry": {"coordinates":[-79.4043121338,43.6666755676],"type":"Point"}
}