{
  "type": "Feature",
  "properties": {
    "addr:full":"20416 Fraser Hwy Langley BC V3A 4G2",
    "addr:housenumber":"20416",
    "addr:postcode":"v3a 4g2",
    "addr:street":"Fraser Hwy",
    "iso:country":"CA",
    "sg:address":"20416 Fraser Hwy",
    "sg:city":"Langley",
    "sg:classifiers":[
        {
            "category":"Shopping",
            "subcategory":"Gifts & Souvenirs",
            "type":"Retail Goods"
        }
    ],
    "sg:phone":"+1 604 532 9720",
    "sg:postcode":"V3A 4G2",
    "sg:province":"BC",
    "sg:tags":[
        "shop"
    ],
    "wof:name":"Three Wishes Home Decor",
    "wof:placetype":"venue"
},
  "geometry": {"coordinates":[-122.655762,49.104412],"type":"Point"}
}