{
  "type": "Feature",
  "properties": {
    "addr:full":"58 Lincoln Rd Stoney Creek ON L8E 1Z3",
    "addr:housenumber":"58",
    "addr:postcode":"l8e 1z3",
    "addr:street":"Lincoln Rd",
    "iso:country":"CA",
    "sg:address":"58 Lincoln Rd",
    "sg:city":"Stoney Creek",
    "sg:classifiers":[
        {
            "category":"Professional",
            "subcategory":"Employment Agencies",
            "type":"Services"
        }
    ],
    "sg:phone":"+1 905 664 3303",
    "sg:postcode":"L8E 1Z3",
    "sg:province":"ON",
    "wof:name":"Fred's Bartending Svc",
    "wof:placetype":"venue"
},
  "geometry": {"coordinates":[-79.73483299999999,43.225529],"type":"Point"}
}