{
  "type": "Feature",
  "properties": {
    "addr:full":"Regina SK S4R 3C3",
    "addr:postcode":"s4r 3c3",
    "iso:country":"CA",
    "sg:city":"Regina",
    "sg:classifiers":[
        {
            "category":"Shopping",
            "subcategory":"Jewelry",
            "type":"Retail Goods"
        }
    ],
    "sg:phone":"+1 306 543 6671",
    "sg:postcode":"S4R 3C3",
    "sg:province":"SK",
    "sg:tags":[
        "jeweler"
    ],
    "wof:name":"Ben Moss Jewellers Ltd",
    "wof:placetype":"venue"
},
  "geometry": {"coordinates":[-104.617867,50.483841],"type":"Point"}
}