{
  "type": "Feature",
  "properties": {
    "iso:country":"CA",
    "sg:city":"Mississauga",
    "sg:classifiers":[
        {
            "category":"Building & Trades",
            "subcategory":"Cleaning & Sanitation",
            "type":"Services"
        }
    ],
    "sg:phone":"+1 905 821 7171",
    "sg:postcode":"L5N 2M2",
    "sg:province":"ON",
    "sg:tags":[
        "janitor"
    ],
    "wof:name":"Quinterra Property Maintenance",
    "wof:placetype":"venue"
},
  "geometry": {"coordinates":[-79.7456665039,43.5923118591],"type":"Point"}
}