{
  "type": "Feature",
  "properties": {
    "addr:full":"25 Main St Carrot River SK S0E 0L0",
    "addr:housenumber":"25",
    "addr:postcode":"s0e 0l0",
    "addr:street":"Main St",
    "iso:country":"CA",
    "sg:address":"25 Main St",
    "sg:city":"Carrot River",
    "sg:classifiers":[
        {
            "category":"Manufacturing",
            "subcategory":"Jewelry",
            "type":"Manufacturing & Wholesale Goods"
        }
    ],
    "sg:phone":"+1 306 768 3700",
    "sg:postcode":"S0E 0L0",
    "sg:province":"SK",
    "sg:tags":[
        "cutlery"
    ],
    "wof:name":"Schiller Knives",
    "wof:placetype":"venue"
},
  "geometry": {"coordinates":[-103.587532044,53.2833595276],"type":"Point"}
}