{
  "type": "Feature",
  "properties": {
    "addr:full":"2535 Rg 9 Wendover Bon-Conseil QC J0C 1A0",
    "addr:housenumber":"9",
    "addr:postcode":"2535;j0c 1a0",
    "addr:street":"Rg;Bon-Conseil",
    "iso:country":"CA",
    "sg:address":"2535 Rg 9 Wendover",
    "sg:city":"Bon-Conseil",
    "sg:classifiers":[
        {
            "category":"Mining & Drilling",
            "type":"Manufacturing & Wholesale Goods"
        }
    ],
    "sg:phone":"+1 819 336 5636",
    "sg:postcode":"J0C 1A0",
    "sg:province":"QC",
    "sg:tags":[
        "quarry"
    ],
    "wof:name":"Carrieres Pcm Ltee",
    "wof:placetype":"venue"
},
  "geometry": {"coordinates":[-72.34410095210001,46.0001907349],"type":"Point"}
}