{
  "type": "Feature",
  "properties": {
    "addr:full":"10006 101 St NW Edmonton AB T5J 0S1",
    "addr:housenumber":"10006",
    "addr:postcode":"t5j 0s1",
    "addr:street":"101 St Nw",
    "iso:country":"CA",
    "sg:address":"10006 101 St NW",
    "sg:city":"Edmonton",
    "sg:classifiers":[
        {
            "category":"Manufacturing",
            "subcategory":"Printing",
            "type":"Manufacturing & Wholesale Goods"
        }
    ],
    "sg:phone":"+1 780 917 7678",
    "sg:postcode":"T5J 0S1",
    "sg:province":"AB",
    "sg:tags":[
        "newspaper"
    ],
    "wof:name":"National Post",
    "wof:placetype":"venue"
},
  "geometry": {"coordinates":[-113.493942261,53.5397911072],"type":"Point"}
}