{
  "type": "Feature",
  "properties": {
    "addr:full":"1306 Lakeshore Rd E Oakville ON L6J 1L6",
    "addr:housenumber":"1306",
    "addr:postcode":"l6j 1l6",
    "addr:street":"Lakeshore Rd E",
    "iso:country":"CA",
    "sg:address":"1306 Lakeshore Rd E",
    "sg:city":"Oakville",
    "sg:classifiers":[
        {
            "category":"Shopping",
            "type":"Retail Goods"
        }
    ],
    "sg:phone":"+1 905 338 0117",
    "sg:postcode":"L6J 1L6",
    "sg:province":"ON",
    "sg:tags":[
        "art",
        "gallery",
        "dealer"
    ],
    "wof:name":"Art Rental & Sales Oakville",
    "wof:placetype":"venue"
},
  "geometry": {"coordinates":[-79.649635,43.462795],"type":"Point"}
}