{
  "type": "Feature",
  "properties": {
    "addr:full":"Baldur MB R0K 0B0",
    "addr:postcode":"r0k 0b0",
    "iso:country":"CA",
    "sg:city":"Baldur",
    "sg:classifiers":[
        {
            "category":"Retail",
            "subcategory":"Auto Repair",
            "type":"Services"
        }
    ],
    "sg:phone":"+1 204 535 2184",
    "sg:postcode":"R0K 0B0",
    "sg:province":"MB",
    "sg:tags":[
        "automobile",
        "customizing"
    ],
    "wof:name":"Lo-Boy's Rod & Custom",
    "wof:placetype":"venue"
},
  "geometry": {"coordinates":[-99.2448959351,49.3848953247],"type":"Point"}
}