{
  "type": "Feature",
  "properties": {
    "addr:full":"20 Bethridge Rd Etobicoke ON M9W 1N1",
    "addr:housenumber":"20",
    "addr:postcode":"m9w 1n1",
    "addr:street":"Bethridge Rd",
    "iso:country":"CA",
    "sg:address":"20 Bethridge Rd",
    "sg:city":"Etobicoke",
    "sg:classifiers":[
        {
            "category":"Manufacturing",
            "subcategory":"Tools & Machinery",
            "type":"Manufacturing & Wholesale Goods"
        }
    ],
    "sg:phone":"+1 416 743 9977",
    "sg:postcode":"M9W 1N1",
    "sg:province":"ON",
    "sg:tags":[
        "equipment",
        "electric",
        "heating"
    ],
    "wof:name":"Asb Heating Elements Ltd",
    "wof:placetype":"venue"
},
  "geometry": {"coordinates":[-79.568382,43.708645],"type":"Point"}
}