{
  "type": "Feature",
  "properties": {
    "addr:full":"701 Av Fortin S Alma QC G8B 2S8",
    "addr:housenumber":"701",
    "addr:postcode":"g8b 2s8",
    "addr:street":"Av Fortin S",
    "iso:country":"CA",
    "sg:address":"701 Av Fortin S",
    "sg:city":"Alma",
    "sg:classifiers":[
        {
            "category":"Wholesale",
            "subcategory":"Auto Parts",
            "type":"Manufacturing & Wholesale Goods"
        }
    ],
    "sg:phone":"+1 418 668 6113",
    "sg:postcode":"G8B 2S8",
    "sg:province":"QC",
    "sg:tags":[
        "body",
        "automobile",
        "shop",
        "supply"
    ],
    "wof:name":"Carquest Du Canada",
    "wof:placetype":"venue"
},
  "geometry": {"coordinates":[-71.64466899999999,48.540062],"type":"Point"}
}