{
  "type": "Feature",
  "properties": {
    "addr:full":"636 Wellington St London ON N6A 3R9",
    "addr:housenumber":"636",
    "addr:postcode":"n6a 3r9",
    "addr:street":"Wellington St",
    "iso:country":"CA",
    "sg:address":"636 Wellington St",
    "sg:city":"London",
    "sg:classifiers":[
        {
            "category":"Professional",
            "subcategory":"Management & Consulting",
            "type":"Services"
        }
    ],
    "sg:phone":"+1 519 433 0081",
    "sg:postcode":"N6A 3R9",
    "sg:province":"ON",
    "sg:tags":[
        "construction",
        "general",
        "contractor"
    ],
    "wof:name":"Ontario & King Ltd",
    "wof:placetype":"venue"
},
  "geometry": {"coordinates":[-81.248833,42.992264],"type":"Point"}
}