{
  "type": "Feature",
  "properties": {
    "addr:full":"303 Rue DE Puyjalon Baie-Comeau QC G5C 1M4",
    "addr:housenumber":"303",
    "addr:postcode":"g5c 1m4",
    "addr:street":"Rue De Puyjalon",
    "iso:country":"CA",
    "sg:address":"303 Rue DE Puyjalon",
    "sg:city":"Baie-Comeau",
    "sg:classifiers":[
        {
            "category":"Organizations",
            "subcategory":"Professional Association",
            "type":"Services"
        }
    ],
    "sg:phone":"+1 418 589 9824",
    "sg:postcode":"G5C 1M4",
    "sg:province":"QC",
    "wof:name":"Syndicat DE L'Enseignement",
    "wof:placetype":"venue"
},
  "geometry": {"coordinates":[-68.24730700000001,49.192924],"type":"Point"}
}