{
  "type": "Feature",
  "properties": {
    "addr:full":"7455 Rue Sherbrooke O Montreal QC H4B 1S3",
    "addr:housenumber":"7455",
    "addr:postcode":"h4b 1s3",
    "addr:street":"Rue Sherbrooke O",
    "iso:country":"CA",
    "sg:address":"7455 Rue Sherbrooke O",
    "sg:city":"Montreal",
    "sg:classifiers":[
        {
            "category":"Retail",
            "subcategory":"Repair Shop",
            "type":"Services"
        }
    ],
    "sg:phone":"+1 514 481 5736",
    "sg:postcode":"H4B 1S3",
    "sg:province":"QC",
    "sg:tags":[
        "repairing",
        "equipment",
        "electric"
    ],
    "wof:name":"Farmer Electric",
    "wof:placetype":"venue"
},
  "geometry": {"coordinates":[-73.538811,45.590672],"type":"Point"}
}