{
  "type": "Feature",
  "properties": {
    "addr:full":"6112 45 St # 1 Leduc AB T9E 7C2",
    "addr:housenumber":"6112",
    "addr:postcode":"t9e 7c2",
    "addr:street":"45 St # 1",
    "iso:country":"CA",
    "sg:address":"6112 45 St # 1",
    "sg:city":"Leduc",
    "sg:classifiers":[
        {
            "category":"Retail",
            "subcategory":"Auto Repair",
            "type":"Services"
        }
    ],
    "sg:phone":"+1 780 986 6628",
    "sg:postcode":"T9E 7C2",
    "sg:province":"AB",
    "sg:tags":[
        "repairing",
        "automobile",
        "brake"
    ],
    "wof:name":"Integra Automotive",
    "wof:placetype":"venue"
},
  "geometry": {"coordinates":[-113.542,53.274872],"type":"Point"}
}