{
  "type": "Feature",
  "properties": {
    "addr:full":"115 Boul Saint-Jean-Baptiste Chateauguay QC J6K 3B1",
    "addr:housenumber":"115",
    "addr:postcode":"j6k 3b1",
    "addr:street":"Boul Saint-Jean-Baptiste",
    "iso:country":"CA",
    "sg:address":"115 Boul Saint-Jean-Baptiste",
    "sg:city":"Chateauguay",
    "sg:classifiers":[
        {
            "category":"Building & Trades",
            "subcategory":"Construction",
            "type":"Services"
        }
    ],
    "sg:phone":"+1 450 698 2210",
    "sg:postcode":"J6K 3B1",
    "sg:province":"QC",
    "sg:tags":[
        "designer",
        "dealer",
        "pool",
        "swimming"
    ],
    "wof:name":"Piscines Trevi Inc",
    "wof:placetype":"venue"
},
  "geometry": {"coordinates":[-73.7164840698,45.3579673767],"type":"Point"}
}