{
  "type": "Feature",
  "properties": {
    "addr:full":"Terrace BC V8G 1S6",
    "addr:postcode":"v8g 1s6",
    "iso:country":"CA",
    "sg:city":"Terrace",
    "sg:classifiers":[
        {
            "category":"Professional",
            "subcategory":"Accounting & Tax Preparation",
            "type":"Services"
        }
    ],
    "sg:phone":"+1 250 635 4925",
    "sg:postcode":"V8G 1S6",
    "sg:province":"BC",
    "sg:tags":[
        "accountant"
    ],
    "wof:name":"Johnson, Michael CA",
    "wof:placetype":"venue"
},
  "geometry": {"coordinates":[-128.589676,54.517658],"type":"Point"}
}