{
  "type": "Feature",
  "properties": {
    "iso:country":"CA",
    "sg:address":"2107 110 St NW",
    "sg:city":"Edmonton",
    "sg:classifiers":[
        {
            "category":"Personal",
            "subcategory":"Beauty Salon",
            "type":"Services"
        }
    ],
    "sg:phone":"+1 780 469 8093",
    "sg:postcode":"T6J 6P6",
    "sg:province":"AB",
    "wof:name":"Mystique Hair Group",
    "wof:placetype":"venue"
},
  "geometry": {"coordinates":[-113.51292419400001,53.4528465271],"type":"Point"}
}