{
  "type": "Feature",
  "properties": {
    "iso:country":"CA",
    "sg:city":"Walkerton",
    "sg:classifiers":[
        {
            "category":"Building & Trades",
            "subcategory":"Construction",
            "type":"Services"
        }
    ],
    "sg:phone":"+1 519 881 3243",
    "sg:postcode":"N0G 2V0",
    "sg:province":"ON",
    "sg:tags":[
        "maker",
        "cabinet"
    ],
    "wof:name":"Johnson Woodworks",
    "wof:placetype":"venue"
},
  "geometry": {"coordinates":[-81.15069580079999,44.1245155334],"type":"Point"}
}