{
  "type": "Feature",
  "properties": {
    "iso:country":"CA",
    "sg:address":"2402 Priest Ave",
    "sg:city":"Merritt",
    "sg:classifiers":[
        {
            "category":"Manufacturing",
            "subcategory":"Motor Vehicles & Parts",
            "type":"Manufacturing & Wholesale Goods"
        }
    ],
    "sg:phone":"+1 250 378 4821",
    "sg:postcode":"V1K 1B8",
    "sg:province":"BC",
    "sg:tags":[
        "automobile",
        "wrecker"
    ],
    "wof:name":"Merritt Auto Wrecking",
    "wof:placetype":"venue"
},
  "geometry": {"coordinates":[-120.78314971899999,50.1037406921],"type":"Point"}
}