{
  "type": "Feature",
  "properties": {
    "addr:full":"71 Toombs St Moncton NB E1A 3A4",
    "addr:housenumber":"71",
    "addr:postcode":"e1a 3a4",
    "addr:street":"Toombs St",
    "iso:country":"CA",
    "sg:address":"71 Toombs St",
    "sg:city":"Moncton",
    "sg:classifiers":[
        {
            "category":"Arts & Performance",
            "subcategory":"Theater",
            "type":"Entertainment"
        }
    ],
    "sg:phone":"+1 506 853 8363",
    "sg:postcode":"E1A 3A4",
    "sg:province":"NB",
    "sg:tags":[
        "live",
        "music"
    ],
    "wof:name":"Dynamic Sounds D J's",
    "wof:placetype":"venue"
},
  "geometry": {"coordinates":[-64.7638626099,46.1126556396],"type":"Point"}
}