{
  "type": "Feature",
  "properties": {
    "addr:full":"148 Rue Saint-Gabriel Saint-Gabriel-DE-Brandon QC J0K 2N0",
    "addr:housenumber":"148",
    "addr:postcode":"j0k 2n0",
    "addr:street":"Rue Saint-Gabriel",
    "iso:country":"CA",
    "sg:address":"148 Rue Saint-Gabriel",
    "sg:city":"Saint-Gabriel-DE-Brandon",
    "sg:classifiers":[
        {
            "category":"Autos & Motor Vehicles",
            "subcategory":"Fuel & Gas Station",
            "type":"Retail Goods"
        }
    ],
    "sg:phone":"+1 450 835 2334",
    "sg:postcode":"J0K 2N0",
    "sg:province":"QC",
    "sg:tags":[
        "repairing",
        "automobile",
        "oil"
    ],
    "wof:name":"Garage Desrochers Esso",
    "wof:placetype":"venue"
},
  "geometry": {"coordinates":[-73.38155399999999,46.291168],"type":"Point"}
}