{
  "type": "Feature",
  "properties": {
    "addr:full":"Prescott ON K0E 1T0",
    "addr:postcode":"k0e 1t0",
    "iso:country":"CA",
    "sg:city":"Prescott",
    "sg:classifiers":[
        {
            "category":"Health Services",
            "subcategory":"Doctor",
            "type":"Services"
        }
    ],
    "sg:phone":"+1 613 925 3428",
    "sg:postcode":"K0E 1T0",
    "sg:province":"ON",
    "sg:tags":[
        "dentist"
    ],
    "wof:name":"Mc Intosh, Lance DDS",
    "wof:placetype":"venue"
},
  "geometry": {"coordinates":[-75.52075958250001,44.7049598694],"type":"Point"}
}