{
  "type": "Feature",
  "properties": {
    "addr:full":"2069 Dundas St Cardinal ON K0E 1E0",
    "addr:housenumber":"2069",
    "addr:postcode":"k0e 1e0",
    "addr:street":"Dundas St",
    "iso:country":"CA",
    "sg:address":"2069 Dundas St",
    "sg:city":"Cardinal",
    "sg:classifiers":[
        {
            "category":"Home & Garden",
            "subcategory":"Furniture",
            "type":"Retail Goods"
        }
    ],
    "sg:phone":"+1 613 657 3037",
    "sg:postcode":"K0E 1E0",
    "sg:province":"ON",
    "wof:name":"Madmacs Furniture & Appliances",
    "wof:placetype":"venue"
},
  "geometry": {"coordinates":[-75.380859,44.787094],"type":"Point"}
}