{
  "type": "Feature",
  "properties": {
    "addr:full":"Qualicum Beach BC V9K 2J3",
    "addr:postcode":"v9k 2j3",
    "iso:country":"CA",
    "sg:city":"Qualicum Beach",
    "sg:classifiers":[
        {
            "category":"Restaurant",
            "type":"Food & Drink"
        }
    ],
    "sg:phone":"+1 250 752 1376",
    "sg:postcode":"V9K 2J3",
    "sg:province":"BC",
    "wof:name":"Highgate Cafe & Tearoom",
    "wof:placetype":"venue"
},
  "geometry": {"coordinates":[-124.44742599999999,49.348133],"type":"Point"}
}