{
  "type": "Feature",
  "properties": {
    "addr:full":"228 Woolwich St Guelph ON N1H 3V7",
    "addr:housenumber":"228",
    "addr:postcode":"n1h 3v7",
    "addr:street":"Woolwich St",
    "iso:country":"CA",
    "sg:address":"228 Woolwich St",
    "sg:city":"Guelph",
    "sg:classifiers":[
        {
            "category":"Retail",
            "subcategory":"Auto Repair",
            "type":"Services"
        }
    ],
    "sg:phone":"+1 519 823 5360",
    "sg:postcode":"N1H 3V7",
    "sg:province":"ON",
    "sg:tags":[
        "repairing",
        "automobile",
        "muffler",
        "exhaust"
    ],
    "wof:name":"Speedy Auto Svc",
    "wof:placetype":"venue"
},
  "geometry": {"coordinates":[-80.2547988892,43.5484962463],"type":"Point"}
}