{
  "type": "Feature",
  "properties": {
    "addr:full":"Callander ON P0H 1H0",
    "addr:postcode":"p0h 1h0",
    "iso:country":"CA",
    "sg:city":"Callander",
    "sg:classifiers":[
        {
            "category":"Government",
            "subcategory":"Office",
            "type":"Public Place"
        }
    ],
    "sg:phone":"+1 705 752 1870",
    "sg:postcode":"P0H 1H0",
    "sg:province":"ON",
    "sg:tags":[
        "village"
    ],
    "wof:name":"East Ferris Public Works",
    "wof:placetype":"venue"
},
  "geometry": {"coordinates":[-79.3628768921,46.22315979],"type":"Point"}
}