{
  "type": "Feature",
  "properties": {
    "addr:full":"45 Brisbane Blvd Brantford ON N3S 4K9",
    "addr:housenumber":"45",
    "addr:postcode":"n3s 4k9",
    "addr:street":"Brisbane Blvd",
    "iso:country":"CA",
    "sg:address":"45 Brisbane Blvd",
    "sg:city":"Brantford",
    "sg:classifiers":[
        {
            "category":"Building & Trades",
            "subcategory":"Construction",
            "type":"Services"
        }
    ],
    "sg:phone":"+1 519 756 1478",
    "sg:postcode":"N3S 4K9",
    "sg:province":"ON",
    "sg:tags":[
        "concrete",
        "contractor"
    ],
    "wof:name":"Philip Del Signore Concrete",
    "wof:placetype":"venue"
},
  "geometry": {"coordinates":[-80.2132644653,43.1470565796],"type":"Point"}
}