{
  "type": "Feature",
  "properties": {
    "iso:country":"CA",
    "sg:address":"2985 Grant St",
    "sg:city":"Vancouver",
    "sg:classifiers":[
        {
            "category":"Manufacturing",
            "subcategory":"Printing",
            "type":"Manufacturing & Wholesale Goods"
        }
    ],
    "sg:phone":"+1 604 255 9579",
    "sg:postcode":"V5K 3H6",
    "sg:province":"BC",
    "sg:tags":[
        "foil",
        "metal",
        "label"
    ],
    "wof:name":"Avery Dennison",
    "wof:placetype":"venue"
},
  "geometry": {"coordinates":[-123.042030334,49.271522522],"type":"Point"}
}