{
  "type": "Feature",
  "properties": {
    "addr:full":"5820 Boul Bourque Rock Forest QC J1N 1H3",
    "addr:housenumber":"5820",
    "addr:postcode":"j1n 1h3",
    "addr:street":"Boul Bourque",
    "iso:country":"CA",
    "sg:address":"5820 Boul Bourque",
    "sg:city":"Rock Forest",
    "sg:phone":"+1 819 864 4111",
    "sg:postcode":"J1N 1H3",
    "sg:province":"QC",
    "sg:tags":[
        "equipment",
        "compound",
        "cleaning",
        "supply"
    ],
    "wof:name":"Laboratoire Qualiteck",
    "wof:placetype":"venue"
},
  "geometry": {"coordinates":[-72.00955200200001,45.3591308594],"type":"Point"}
}