{
  "type": "Feature",
  "properties": {
    "addr:full":"Vercheres QC J0L 2R0",
    "addr:postcode":"j0l 2r0",
    "iso:country":"CA",
    "sg:city":"Vercheres",
    "sg:classifiers":[
        {
            "category":"Recreation",
            "type":"Entertainment"
        }
    ],
    "sg:phone":"+1 450 583 2188",
    "sg:postcode":"J0L 2R0",
    "sg:province":"QC",
    "sg:tags":[
        "hall",
        "auditorium"
    ],
    "wof:name":"Centre Communautaire/Vercheres",
    "wof:placetype":"venue"
},
  "geometry": {"coordinates":[-73.351128,45.772263],"type":"Point"}
}