{
  "type": "Feature",
  "properties": {
    "iso:country":"CA",
    "sg:address":"5966 Rochdale Blvd",
    "sg:city":"Regina",
    "sg:classifiers":[
        {
            "category":"Banks & Credit Unions",
            "subcategory":"Bank",
            "type":"Services"
        }
    ],
    "sg:phone":"+1 306 569 5623",
    "sg:postcode":"S4X 4J7",
    "sg:province":"SK",
    "wof:name":"Bank of Montreal",
    "wof:placetype":"venue"
},
  "geometry": {"coordinates":[-104.665046692,50.4960136414],"type":"Point"}
}