{
  "type": "Feature",
  "properties": {
    "iso:country":"CA",
    "sg:address":"1202 Pender St E",
    "sg:city":"Vancouver",
    "sg:classifiers":[
        {
            "category":"Government",
            "subcategory":"Police Station",
            "type":"Public Place"
        }
    ],
    "sg:phone":"+1 604 717 2927",
    "sg:postcode":"V6A 1W8",
    "sg:province":"BC",
    "sg:tags":[
        "department"
    ],
    "wof:name":"Vancouver Community Police",
    "wof:placetype":"venue"
},
  "geometry": {"coordinates":[-123.078926,49.280231],"type":"Point"}
}