{
  "type": "Feature",
  "properties": {
    "addr:full":"Oshawa ON L1H 4N1",
    "addr:postcode":"l1h 4n1",
    "iso:country":"CA",
    "sg:city":"Oshawa",
    "sg:classifiers":[
        {
            "category":"Wholesale",
            "subcategory":"Machinery & Supplies",
            "type":"Manufacturing & Wholesale Goods"
        }
    ],
    "sg:phone":"+1 905 576 1670",
    "sg:postcode":"L1H 4N1",
    "sg:province":"ON",
    "sg:tags":[
        "instrument",
        "radioactivity"
    ],
    "wof:name":"Joe's Color Tv & Electronics",
    "wof:placetype":"venue"
},
  "geometry": {"coordinates":[-78.861633,43.896175],"type":"Point"}
}