{
  "type": "Feature",
  "properties": {
    "addr:full":"918 93rd Ave Tisdale SK S0E 1T0",
    "addr:housenumber":"918",
    "addr:postcode":"s0e 1t0",
    "addr:street":"93Rd Ave",
    "iso:country":"CA",
    "sg:address":"918 93rd Ave",
    "sg:city":"Tisdale",
    "sg:classifiers":[
        {
            "category":"Bars & Pubs",
            "type":"Food & Drink"
        }
    ],
    "sg:phone":"+1 306 873 5127",
    "sg:postcode":"S0E 1T0",
    "sg:province":"SK",
    "sg:tags":[
        "club",
        "night"
    ],
    "wof:name":"Little Willy's Sports Bar",
    "wof:placetype":"venue"
},
  "geometry": {"coordinates":[-104.05291748,52.8418045044],"type":"Point"}
}