{
  "type": "Feature",
  "properties": {
    "addr:full":"34831 Delair Rd Abbotsford BC V2S 2E1",
    "addr:housenumber":"34831",
    "addr:postcode":"v2s 2e1",
    "addr:street":"Delair Rd",
    "iso:country":"CA",
    "sg:address":"34831 Delair Rd",
    "sg:city":"Abbotsford",
    "sg:classifiers":[
        {
            "category":"Real Estate",
            "subcategory":"Real Estate Agent",
            "type":"Services"
        }
    ],
    "sg:phone":"+1 604 852 1180",
    "sg:postcode":"V2S 2E1",
    "sg:province":"BC",
    "wof:name":"B C Farm & Ranch Realty Corp",
    "wof:placetype":"venue"
},
  "geometry": {"coordinates":[-122.260566711,49.0337753296],"type":"Point"}
}