{
  "type": "Feature",
  "properties": {
    "addr:full":"3560 Wolfedale Rd Mississauga ON L5C 2V6",
    "addr:postcode":"3560;l5c 2v6",
    "addr:street":"Wolfedale Rd",
    "iso:country":"CA",
    "sg:address":"3560 Wolfedale Rd",
    "sg:city":"Mississauga",
    "sg:classifiers":[
        {
            "category":"Home & Garden",
            "subcategory":"Furniture",
            "type":"Retail Goods"
        }
    ],
    "sg:phone":"+1 905 848 4141",
    "sg:postcode":"L5C 2V6",
    "sg:province":"ON",
    "wof:name":"Royal Furniture Warehouse",
    "wof:placetype":"venue"
},
  "geometry": {"coordinates":[-79.6516113281,43.5735588074],"type":"Point"}
}