{
  "type": "Feature",
  "properties": {
    "addr:full":"12911 96 Ave Surrey BC V3V 7K6",
    "addr:housenumber":"12911",
    "addr:postcode":"v3v 7k6",
    "addr:street":"96 Ave",
    "iso:country":"CA",
    "sg:address":"12911 96 Ave",
    "sg:city":"Surrey",
    "sg:classifiers":[
        {
            "category":"Food & Beverages",
            "subcategory":"Liquor & Beverages",
            "type":"Retail Goods"
        }
    ],
    "sg:phone":"+1 604 588 5162",
    "sg:postcode":"V3V 7K6",
    "sg:province":"BC",
    "sg:tags":[
        "beer",
        "ale"
    ],
    "wof:name":"Wheelhouse Beer & Wine Store",
    "wof:placetype":"venue"
},
  "geometry": {"coordinates":[-122.86507400000001,49.177307],"type":"Point"}
}