{
  "type": "Feature",
  "properties": {
    "iso:country":"CA",
    "sg:address":"3572 Rue Masson",
    "sg:city":"Montreal",
    "sg:classifiers":[
        {
            "category":"Retail",
            "subcategory":"Auto Rental",
            "type":"Services"
        }
    ],
    "sg:phone":"+1 514 728 9205",
    "sg:postcode":"H1X 1S2",
    "sg:province":"QC",
    "sg:tags":[
        "renting",
        "automobile",
        "leasing"
    ],
    "wof:name":"Deragon Location",
    "wof:placetype":"venue"
},
  "geometry": {"coordinates":[-73.571312,45.554008],"type":"Point"}
}