{
  "type": "Feature",
  "properties": {
    "addr:full":"273 Tache Ave Winnipeg MB R2H 1Z8",
    "addr:housenumber":"273",
    "addr:postcode":"r2h 1z8",
    "addr:street":"Tache Ave",
    "iso:country":"CA",
    "sg:address":"273 Tache Ave",
    "sg:city":"Winnipeg",
    "sg:classifiers":[
        {
            "category":"Real Estate",
            "subcategory":"Real Estate Agent",
            "type":"Services"
        }
    ],
    "sg:phone":"+1 204 233 5454",
    "sg:postcode":"R2H 1Z8",
    "sg:province":"MB",
    "sg:tags":[
        "buyer",
        "broker"
    ],
    "wof:name":"Steck & Assoc Realty Ltd",
    "wof:placetype":"venue"
},
  "geometry": {"coordinates":[-97.12351200000001,49.880329],"type":"Point"}
}