{
  "type": "Feature",
  "properties": {
    "addr:full":"738 Rue Nicolas-Perrot Boucherville QC J4B 7V7",
    "addr:housenumber":"738",
    "addr:postcode":"j4b 7v7",
    "addr:street":"Rue Nicolas-Perrot",
    "iso:country":"CA",
    "sg:address":"738 Rue Nicolas-Perrot",
    "sg:city":"Boucherville",
    "sg:classifiers":[
        {
            "category":"Health Services",
            "subcategory":"Doctor",
            "type":"Services"
        }
    ],
    "sg:phone":"+1 450 655 3857",
    "sg:postcode":"J4B 7V7",
    "sg:province":"QC",
    "sg:tags":[
        "clinic"
    ],
    "wof:name":"Rousseau, Monique",
    "wof:placetype":"venue"
},
  "geometry": {"coordinates":[-73.4372329712,45.6094551086],"type":"Point"}
}