{
  "type": "Feature",
  "properties": {
    "addr:full":"13765 St. Gregory's Rd Windsor ON N8N 1K3",
    "addr:housenumber":"13765",
    "addr:postcode":"n8n 1k3",
    "addr:street":"St. Gregory'S Rd",
    "iso:country":"CA",
    "sg:address":"13765 St. Gregory's Rd",
    "sg:city":"Windsor",
    "sg:classifiers":[
        {
            "category":"Education",
            "subcategory":"School",
            "type":"Public Place"
        }
    ],
    "sg:phone":"+1 519 735 4583",
    "sg:postcode":"N8N 1K3",
    "sg:province":"ON",
    "wof:name":"St Gregory Elementary School",
    "wof:placetype":"venue"
},
  "geometry": {"coordinates":[-83.069427,42.291786],"type":"Point"}
}