{
  "type": "Feature",
  "properties": {
    "addr:full":"3094 Rue Charette Sainte-Adele QC J8B 1H3",
    "addr:housenumber":"3094",
    "addr:postcode":"j8b 1h3",
    "addr:street":"Rue Charette Sainte-Adele",
    "iso:country":"CA",
    "sg:address":"3094 Rue Charette",
    "sg:city":"Sainte-Adele",
    "sg:classifiers":[
        {
            "category":"Shopping",
            "subcategory":"Computers & Home Electronics",
            "type":"Retail Goods"
        }
    ],
    "sg:phone":"+1 450 229 5211",
    "sg:postcode":"J8B 1H3",
    "sg:province":"QC",
    "sg:tags":[
        "equipment",
        "television",
        "radio",
        "satellite"
    ],
    "wof:name":"Electronique Jean Parent Enr",
    "wof:placetype":"venue"
},
  "geometry": {"coordinates":[-74.1184768677,45.9401397705],"type":"Point"}
}