{
  "type": "Feature",
  "properties": {
    "iso:country":"CA",
    "sg:address":"207 Woolwich St",
    "sg:city":"Guelph",
    "sg:classifiers":[
        {
            "category":"Travel",
            "subcategory":"Travel Agent",
            "type":"Entertainment"
        }
    ],
    "sg:phone":"+1 519 823 1118",
    "sg:postcode":"N1H 3V4",
    "sg:province":"ON",
    "sg:tags":[
        "agency",
        "bureau"
    ],
    "wof:name":"Clare Newson Travel",
    "wof:placetype":"venue"
},
  "geometry": {"coordinates":[-80.25398254389999,43.5486297607],"type":"Point"}
}