{
  "type": "Feature",
  "properties": {
    "iso:country":"CA",
    "sg:address":"919 Pape Ave",
    "sg:city":"East York",
    "sg:classifiers":[
        {
            "category":"Restaurant",
            "type":"Food & Drink"
        }
    ],
    "sg:phone":"+1 416 469 2529",
    "sg:postcode":"M4K 3V3",
    "sg:province":"ON",
    "wof:name":"King's Park Souvlaki Place",
    "wof:placetype":"venue"
},
  "geometry": {"coordinates":[-79.3471374512,43.6855278015],"type":"Point"}
}