{
  "type": "Feature",
  "properties": {
    "addr:full":"2343 Barton St E Hamilton ON L8E 5V8",
    "addr:housenumber":"2343",
    "addr:postcode":"l8e 5v8",
    "addr:street":"Barton St E",
    "iso:country":"CA",
    "sg:address":"2343 Barton St E",
    "sg:city":"Hamilton",
    "sg:classifiers":[
        {
            "category":"Manufacturing",
            "subcategory":"Apparel",
            "type":"Manufacturing & Wholesale Goods"
        }
    ],
    "sg:phone":"+1 905 560 9230",
    "sg:postcode":"L8E 5V8",
    "sg:province":"ON",
    "sg:tags":[
        "canvas",
        "product",
        "related"
    ],
    "wof:name":"Fellfab Limited",
    "wof:placetype":"venue"
},
  "geometry": {"coordinates":[-79.767021,43.238537],"type":"Point"}
}