{
  "type": "Feature",
  "properties": {
    "addr:full":"1087 Harrietsville Dr Belmont ON N0L 1B0",
    "addr:housenumber":"1087",
    "addr:postcode":"n0l 1b0",
    "addr:street":"Harrietsville Dr",
    "iso:country":"CA",
    "sg:address":"1087 Harrietsville Dr",
    "sg:city":"Belmont",
    "sg:classifiers":[
        {
            "category":"Building & Trades",
            "subcategory":"Landscaping Services",
            "type":"Services"
        }
    ],
    "sg:phone":"+1 519 644 0934",
    "sg:postcode":"N0L 1B0",
    "sg:province":"ON",
    "sg:tags":[
        "topsoil"
    ],
    "wof:name":"Fisher Brothers Topsoil",
    "wof:placetype":"venue"
},
  "geometry": {"coordinates":[-81.08734893800001,42.8806381226],"type":"Point"}
}