{
  "type": "Feature",
  "properties": {
    "addr:full":"Vaudreuil-Dorion QC J7V 1Y2",
    "addr:postcode":"j7v 1y2",
    "iso:country":"CA",
    "sg:city":"Vaudreuil-Dorion",
    "sg:classifiers":[
        {
            "category":"Wholesale",
            "subcategory":"Groceries",
            "type":"Manufacturing & Wholesale Goods"
        }
    ],
    "sg:phone":"+1 450 424 4970",
    "sg:postcode":"J7V 1Y2",
    "sg:province":"QC",
    "sg:tags":[
        "product",
        "dairy"
    ],
    "wof:name":"St-Pierre & Gervais Inc",
    "wof:placetype":"venue"
},
  "geometry": {"coordinates":[-74.0126953125,45.3823394775],"type":"Point"}
}