{
  "type": "Feature",
  "properties": {
    "addr:full":"79 Durham St Madoc ON K0K 2K0",
    "addr:housenumber":"79",
    "addr:postcode":"k0k 2k0",
    "addr:street":"Durham St",
    "iso:country":"CA",
    "sg:address":"79 Durham St",
    "sg:city":"Madoc",
    "sg:classifiers":[
        {
            "category":"Cinema",
            "subcategory":"Movie Rental",
            "type":"Entertainment"
        }
    ],
    "sg:phone":"+1 613 473 5523",
    "sg:postcode":"K0K 2K0",
    "sg:province":"ON",
    "sg:tags":[
        "leasing",
        "video",
        "disc",
        "tape"
    ],
    "wof:name":"First Choice Video & Copy Ctr",
    "wof:placetype":"venue"
},
  "geometry": {"coordinates":[-77.47292299999999,44.506279],"type":"Point"}
}