{
  "type": "Feature",
  "properties": {
    "addr:full":"112 Rue DE LA Gauchetiere O Montreal QC H2Z 1C3",
    "addr:housenumber":"112",
    "addr:postcode":"h2z 1c3",
    "addr:street":"Rue De La Gauchetiere O",
    "iso:country":"CA",
    "sg:address":"112 Rue DE LA Gauchetiere O",
    "sg:city":"Montreal",
    "sg:classifiers":[
        {
            "category":"Food & Beverages",
            "subcategory":"Groceries & Convenience Stores",
            "type":"Retail Goods"
        }
    ],
    "sg:phone":"+1 514 393 8097",
    "sg:postcode":"H2Z 1C3",
    "sg:province":"QC",
    "sg:tags":[
        "grocer"
    ],
    "wof:name":"Epicerie Mow Fung",
    "wof:placetype":"venue"
},
  "geometry": {"coordinates":[-73.55877700000001,45.509541],"type":"Point"}
}