{
  "type": "Feature",
  "properties": {
    "addr:full":"204 Rue Du Village Les Eboulements QC G0A 2M0",
    "addr:housenumber":"204",
    "addr:postcode":"g0a 2m0",
    "addr:street":"Rue Du Village",
    "iso:country":"CA",
    "sg:address":"204 Rue Du Village",
    "sg:city":"Les Eboulements",
    "sg:classifiers":[
        {
            "category":"Building & Trades",
            "subcategory":"Construction",
            "type":"Services"
        }
    ],
    "sg:phone":"+1 418 635 2864",
    "sg:postcode":"G0A 2M0",
    "sg:province":"QC",
    "sg:tags":[
        "general",
        "contractor"
    ],
    "wof:name":"Entreprises Audet Tremblay Inc",
    "wof:placetype":"venue"
},
  "geometry": {"coordinates":[-70.321259,47.478741],"type":"Point"}
}