{
  "type": "Feature",
  "properties": {
    "iso:country":"CA",
    "sg:address":"428 Rue Lafontaine",
    "sg:city":"Riviere-Du-Loup",
    "sg:classifiers":[
        {
            "category":"Banks & Credit Unions",
            "subcategory":"Investment Brokerage",
            "type":"Services"
        }
    ],
    "sg:phone":"+1 418 863 6769",
    "sg:postcode":"G5R 3B8",
    "sg:province":"QC",
    "sg:tags":[
        "advisory",
        "financial"
    ],
    "wof:name":"Bmo Nesbitt Burns Inc",
    "wof:placetype":"venue"
},
  "geometry": {"coordinates":[-69.5322113037,47.8288383484],"type":"Point"}
}