{
  "type": "Feature",
  "properties": {
    "addr:full":"4511 97 St NW Edmonton AB T6E 5Y8",
    "addr:housenumber":"4511",
    "addr:postcode":"t6e 5y8",
    "addr:street":"97 St Nw",
    "iso:country":"CA",
    "sg:address":"4511 97 St NW",
    "sg:city":"Edmonton",
    "sg:classifiers":[
        {
            "category":"Restaurant",
            "type":"Food & Drink"
        }
    ],
    "sg:phone":"+1 780 435 2033",
    "sg:postcode":"T6E 5Y8",
    "sg:province":"AB",
    "wof:name":"Snack Shop",
    "wof:placetype":"venue"
},
  "geometry": {"coordinates":[-113.479225,53.483364],"type":"Point"}
}