{
  "type": "Feature",
  "properties": {
    "addr:full":"Huron & Barker Manitouwadge ON P0T 2C0",
    "addr:postcode":"p0t 2c0",
    "iso:country":"CA",
    "sg:address":"Huron & Barker",
    "sg:city":"Manitouwadge",
    "sg:classifiers":[
        {
            "category":"Banks & Credit Unions",
            "subcategory":"Bank",
            "type":"Services"
        }
    ],
    "sg:phone":"+1 807 826 3201",
    "sg:postcode":"P0T 2C0",
    "sg:province":"ON",
    "wof:name":"Cibc",
    "wof:placetype":"venue"
},
  "geometry": {"coordinates":[-85.828506,49.12682],"type":"Point"}
}