{
  "type": "Feature",
  "properties": {
    "addr:full":"20129 42 Ave Langley BC V3A 3A6",
    "addr:housenumber":"20129",
    "addr:postcode":"v3a 3a6",
    "addr:street":"42 Ave",
    "iso:country":"CA",
    "sg:address":"20129 42 Ave",
    "sg:city":"Langley",
    "sg:classifiers":[
        {
            "category":"Shopping",
            "type":"Retail Goods"
        }
    ],
    "sg:phone":"+1 604 530 5698",
    "sg:postcode":"V3A 3A6",
    "sg:province":"BC",
    "sg:tags":[
        "picture",
        "frame"
    ],
    "wof:name":"Designer Picture Framing",
    "wof:placetype":"venue"
},
  "geometry": {"coordinates":[-122.666023254,49.0785255432],"type":"Point"}
}