{
  "type": "Feature",
  "properties": {
    "addr:full":"2250 Heather St Vancouver BC V5Z 3H6",
    "addr:housenumber":"2250",
    "addr:postcode":"v5z 3h6",
    "addr:street":"Heather St",
    "iso:country":"CA",
    "sg:address":"2250 Heather St",
    "sg:city":"Vancouver",
    "sg:classifiers":[
        {
            "category":"Retail",
            "subcategory":"Auto Repair",
            "type":"Services"
        }
    ],
    "sg:phone":"+1 604 874 1555",
    "sg:postcode":"V5Z 3H6",
    "sg:province":"BC",
    "sg:tags":[
        "repairing",
        "automobile"
    ],
    "wof:name":"Fairview Automotive Ltd",
    "wof:placetype":"venue"
},
  "geometry": {"coordinates":[-123.11966700000001,49.265484],"type":"Point"}
}