{
  "type": "Feature",
  "properties": {
    "addr:full":"Toronto ON M6J 1G1",
    "addr:postcode":"m6j 1g1",
    "iso:country":"CA",
    "sg:city":"Toronto",
    "sg:classifiers":[
        {
            "category":"Organizations",
            "subcategory":"Non-profit Organization",
            "type":"Services"
        }
    ],
    "sg:phone":"+1 416 364 7373",
    "sg:postcode":"M6J 1G1",
    "sg:province":"ON",
    "sg:tags":[
        "addiction",
        "treatment",
        "center"
    ],
    "wof:name":"Breaking the Cycle",
    "wof:placetype":"venue"
},
  "geometry": {"coordinates":[-79.40785980219999,43.6462898254],"type":"Point"}
}