{
  "type": "Feature",
  "properties": {
    "addr:full":"3315 22nd Ave E Vancouver BC V5M 2Z2",
    "addr:housenumber":"3315",
    "addr:postcode":"v5m 2z2",
    "addr:street":"22Nd Ave E",
    "iso:country":"CA",
    "sg:address":"3315 22nd Ave E",
    "sg:city":"Vancouver",
    "sg:classifiers":[
        {
            "category":"Education",
            "subcategory":"School",
            "type":"Public Place"
        }
    ],
    "sg:phone":"+1 604 713 4851",
    "sg:postcode":"V5M 2Z2",
    "sg:province":"BC",
    "wof:name":"Renfrew Elementary School",
    "wof:placetype":"venue"
},
  "geometry": {"coordinates":[-123.033142,49.25074],"type":"Point"}
}