{
  "type": "Feature",
  "properties": {
    "addr:full":"7145 Market St Port Hardy BC V0N 2P0",
    "addr:housenumber":"7145",
    "addr:postcode":"v0n 2p0",
    "addr:street":"Market St",
    "iso:country":"CA",
    "sg:address":"7145 Market St",
    "sg:city":"Port Hardy",
    "sg:classifiers":[
        {
            "category":"Restaurant",
            "type":"Food & Drink"
        }
    ],
    "sg:phone":"+1 250 949 7133",
    "sg:postcode":"V0N 2P0",
    "sg:province":"BC",
    "wof:name":"Captain Hardy's",
    "wof:placetype":"venue"
},
  "geometry": {"coordinates":[-127.492111206,50.7214927673],"type":"Point"}
}