{
  "type": "Feature",
  "properties": {
    "addr:full":"Toronto ON M4M 2T4",
    "addr:postcode":"m4m 2t4",
    "iso:country":"CA",
    "sg:city":"Toronto",
    "sg:classifiers":[
        {
            "category":"Retail",
            "subcategory":"Auto Repair",
            "type":"Services"
        }
    ],
    "sg:phone":"+1 416 466 0700",
    "sg:postcode":"M4M 2T4",
    "sg:province":"ON",
    "sg:tags":[
        "repairing",
        "automobile"
    ],
    "wof:name":"Mobile Auto Svc Ctr",
    "wof:placetype":"venue"
},
  "geometry": {"coordinates":[-79.3421554565,43.6657028198],"type":"Point"}
}