{
  "type": "Feature",
  "properties": {
    "addr:full":"246 Main St Antigonish NS B2G 2C2",
    "addr:housenumber":"246",
    "addr:postcode":"b2g 2c2",
    "addr:street":"Main St",
    "iso:country":"CA",
    "sg:address":"246 Main St",
    "sg:city":"Antigonish",
    "sg:classifiers":[
        {
            "category":"Personal",
            "subcategory":"Beauty Salon",
            "type":"Services"
        }
    ],
    "sg:phone":"+1 902 863 2249",
    "sg:postcode":"B2G 2C2",
    "sg:province":"NS",
    "wof:name":"Marcos Hair Studio",
    "wof:placetype":"venue"
},
  "geometry": {"coordinates":[-61.990597,45.622608],"type":"Point"}
}