{
  "type": "Feature",
  "properties": {
    "iso:country":"CA",
    "sg:address":"8518 95 Ave",
    "sg:city":"Fort Saskatchewan",
    "sg:classifiers":[
        {
            "category":"Building & Trades",
            "subcategory":"Construction",
            "type":"Services"
        }
    ],
    "sg:phone":"+1 780 998 7799",
    "sg:postcode":"T8L 2V3",
    "sg:province":"AB",
    "sg:tags":[
        "painter"
    ],
    "wof:name":"D & L Painting",
    "wof:placetype":"venue"
},
  "geometry": {"coordinates":[-113.23896026600001,53.68983078],"type":"Point"}
}