{
  "type": "Feature",
  "properties": {
    "addr:full":"2615 Lancaster Rd Ottawa ON K1B 5N2",
    "addr:housenumber":"2615",
    "addr:postcode":"k1b 5n2",
    "addr:street":"Lancaster Rd",
    "iso:country":"CA",
    "sg:address":"2615 Lancaster Rd",
    "sg:city":"Ottawa",
    "sg:classifiers":[
        {
            "category":"Wholesale",
            "subcategory":"Office Equipment",
            "type":"Manufacturing & Wholesale Goods"
        }
    ],
    "sg:phone":"+1 613 248 1500",
    "sg:postcode":"K1B 5N2",
    "sg:province":"ON",
    "sg:tags":[
        "machine",
        "computer",
        "duplicating",
        "copying",
        "dealer"
    ],
    "wof:name":"4 Office Automation Ltd",
    "wof:placetype":"venue"
},
  "geometry": {"coordinates":[-75.6117935181,45.399433136],"type":"Point"}
}