{
  "type": "Feature",
  "properties": {
    "addr:full":"112 Rue Frontenac Repentigny QC J6A 4B3",
    "addr:housenumber":"112",
    "addr:postcode":"j6a 4b3",
    "addr:street":"Rue Frontenac",
    "iso:country":"CA",
    "sg:address":"112 Rue Frontenac",
    "sg:city":"Repentigny",
    "sg:classifiers":[
        {
            "category":"Retail",
            "subcategory":"Repair Shop",
            "type":"Services"
        }
    ],
    "sg:phone":"+1 450 654 4454",
    "sg:postcode":"J6A 4B3",
    "sg:province":"QC",
    "sg:tags":[
        "repairing",
        "piano",
        "refinishing"
    ],
    "wof:name":"Accordeur DE Pianos",
    "wof:placetype":"venue"
},
  "geometry": {"coordinates":[-73.460579,45.73439],"type":"Point"}
}