{
  "type": "Feature",
  "properties": {
    "iso:country":"CA",
    "sg:address":"825 Denison St # 7",
    "sg:city":"Markham",
    "sg:classifiers":[
        {
            "category":"Manufacturing",
            "subcategory":"Jewelry",
            "type":"Manufacturing & Wholesale Goods"
        }
    ],
    "sg:phone":"+1 905 513 7655",
    "sg:postcode":"L3R 5E4",
    "sg:province":"ON",
    "sg:tags":[
        "jeweler"
    ],
    "wof:name":"Hart Gem Enterprises Ltd",
    "wof:placetype":"venue"
},
  "geometry": {"coordinates":[-79.3339538574,43.8256034851],"type":"Point"}
}