{
  "type": "Feature",
  "properties": {
    "addr:full":"5885 Av Papineau Montreal QC H2G 2W5",
    "addr:housenumber":"5885",
    "addr:postcode":"h2g 2w5",
    "addr:street":"Av Papineau",
    "iso:country":"CA",
    "sg:address":"5885 Av Papineau",
    "sg:city":"Montreal",
    "sg:classifiers":[
        {
            "category":"Shopping",
            "subcategory":"Hobbies, Toys, & Games",
            "type":"Retail Goods"
        }
    ],
    "sg:phone":"+1 514 274 9090",
    "sg:postcode":"H2G 2W5",
    "sg:province":"QC",
    "sg:tags":[
        "box",
        "music"
    ],
    "wof:name":"Boite A Marius",
    "wof:placetype":"venue"
},
  "geometry": {"coordinates":[-73.5907745361,45.5405082703],"type":"Point"}
}