{
  "type": "Feature",
  "properties": {
    "addr:full":"459 Bernard Ave Kelowna BC V1Y 6N8",
    "addr:housenumber":"459",
    "addr:postcode":"v1y 6n8",
    "addr:street":"Bernard Ave",
    "iso:country":"CA",
    "sg:address":"459 Bernard Ave",
    "sg:city":"Kelowna",
    "sg:classifiers":[
        {
            "category":"Shopping",
            "subcategory":"Shoes",
            "type":"Retail Goods"
        }
    ],
    "sg:phone":"+1 250 762 2743",
    "sg:postcode":"V1Y 6N8",
    "sg:province":"BC",
    "wof:name":"Downtown Shoe Store",
    "wof:placetype":"venue"
},
  "geometry": {"coordinates":[-119.494202,49.886169],"type":"Point"}
}