{
  "type": "Feature",
  "properties": {
    "iso:country":"CA",
    "sg:address":"90 Rue Saint-Thomas",
    "sg:city":"Montmagny",
    "sg:classifiers":[
        {
            "category":"Personal",
            "subcategory":"Beauty Salon",
            "type":"Services"
        }
    ],
    "sg:phone":"+1 418 248 9516",
    "sg:postcode":"G5V 1L7",
    "sg:province":"QC",
    "wof:name":"Salon Signe Daniel Levesque",
    "wof:placetype":"venue"
},
  "geometry": {"coordinates":[-70.5586471558,46.979511261],"type":"Point"}
}