{
  "type": "Feature",
  "properties": {
    "iso:country":"CA",
    "sg:address":"367 Indian Meal Line",
    "sg:city":"Torbay",
    "sg:classifiers":[
        {
            "category":"Professional",
            "subcategory":"Accounting & Tax Preparation",
            "type":"Services"
        }
    ],
    "sg:phone":"+1 709 437 6007",
    "sg:postcode":"A1K 1G3",
    "sg:province":"NL",
    "sg:tags":[
        "return",
        "filing"
    ],
    "wof:name":"G W Tax Svc",
    "wof:placetype":"venue"
},
  "geometry": {"coordinates":[-52.7652854919,47.6476097107],"type":"Point"}
}