{
  "type": "Feature",
  "properties": {
    "addr:full":"Hwy 28 & Hwy 507 Lakefield ON K0L 2H0",
    "addr:postcode":"k0l 2h0",
    "addr:street":"Hwy 28 & Hwy 507 Lakefield",
    "iso:country":"CA",
    "sg:address":"Hwy 28 & Hwy 507",
    "sg:city":"Lakefield",
    "sg:classifiers":[
        {
            "category":"Shopping",
            "subcategory":"Jewelry",
            "type":"Retail Goods"
        }
    ],
    "sg:phone":"+1 705 652 7992",
    "sg:postcode":"K0L 2H0",
    "sg:province":"ON",
    "sg:tags":[
        "jeweler"
    ],
    "wof:name":"Jack & Jill Crafts",
    "wof:placetype":"venue"
},
  "geometry": {"coordinates":[-78.2727813721,44.4225082397],"type":"Point"}
}