{
  "type": "Feature",
  "properties": {
    "addr:full":"1395 Main St Winnipeg MB R2W 3V2",
    "addr:housenumber":"1395",
    "addr:postcode":"r2w 3v2",
    "addr:street":"Main St",
    "iso:country":"CA",
    "sg:address":"1395 Main St",
    "sg:city":"Winnipeg",
    "sg:classifiers":[
        {
            "category":"Building & Trades",
            "subcategory":"Electrical",
            "type":"Services"
        }
    ],
    "sg:phone":"+1 204 775 2800",
    "sg:postcode":"R2W 3V2",
    "sg:province":"MB",
    "sg:tags":[
        "air",
        "conditioning",
        "contractor",
        "system",
        "electric"
    ],
    "wof:name":"Mid-Canada Mechanical Elec",
    "wof:placetype":"venue"
},
  "geometry": {"coordinates":[-97.1253662109,49.9248695374],"type":"Point"}
}