{
  "type": "Feature",
  "properties": {
    "addr:full":"172 Jubilee Rd Bridgewater NS B4V 3K5",
    "addr:housenumber":"172",
    "addr:postcode":"b4v 3k5",
    "addr:street":"Jubilee Rd",
    "iso:country":"CA",
    "sg:address":"172 Jubilee Rd",
    "sg:city":"Bridgewater",
    "sg:classifiers":[
        {
            "category":"Health Services",
            "subcategory":"Doctor",
            "type":"Services"
        }
    ],
    "sg:phone":"+1 902 543 5314",
    "sg:postcode":"B4V 3K5",
    "sg:province":"NS",
    "sg:tags":[
        "physician",
        "surgeon"
    ],
    "wof:name":"Gandhi Medical Practice Inc",
    "wof:placetype":"venue"
},
  "geometry": {"coordinates":[-64.513474,44.367199],"type":"Point"}
}