{
  "type": "Feature",
  "properties": {
    "addr:full":"3859 Lake Shore Blvd W Etobicoke ON M8W 1R4",
    "addr:housenumber":"3859",
    "addr:postcode":"m8w 1r4",
    "addr:street":"Lake Shore Blvd W",
    "iso:country":"CA",
    "sg:address":"3859 Lake Shore Blvd W",
    "sg:city":"Etobicoke",
    "sg:classifiers":[
        {
            "category":"Restaurant",
            "type":"Food & Drink"
        }
    ],
    "sg:phone":"+1 416 251 8887",
    "sg:postcode":"M8W 1R4",
    "sg:province":"ON",
    "sg:tags":[
        "parlor",
        "ice",
        "cream"
    ],
    "wof:name":"Tasty Dairy Freeze",
    "wof:placetype":"venue"
},
  "geometry": {"coordinates":[-79.5451202393,43.5901374817],"type":"Point"}
}