{
  "type": "Feature",
  "properties": {
    "addr:full":"2128 Kensington Rd NW Calgary AB T2N 3R7",
    "addr:housenumber":"2128",
    "addr:postcode":"t2n 3r7",
    "addr:street":"Kensington Rd Nw",
    "iso:country":"CA",
    "sg:address":"2128 Kensington Rd NW",
    "sg:city":"Calgary",
    "sg:classifiers":[
        {
            "category":"Health Services",
            "subcategory":"Doctor",
            "type":"Services"
        }
    ],
    "sg:phone":"+1 403 270 8939",
    "sg:postcode":"T2N 3R7",
    "sg:province":"AB",
    "sg:tags":[
        "physician",
        "surgeon"
    ],
    "wof:name":"West Hillhurst Health Clinic",
    "wof:placetype":"venue"
},
  "geometry": {"coordinates":[-114.10881000000001,51.052628],"type":"Point"}
}