{
  "type": "Feature",
  "properties": {
    "addr:full":"4716 16 Ave NW Calgary AB T3B 0N1",
    "addr:housenumber":"4716",
    "addr:postcode":"t3b 0n1",
    "addr:street":"16 Ave Nw",
    "iso:country":"CA",
    "sg:address":"4716 16 Ave NW",
    "sg:city":"Calgary",
    "sg:classifiers":[
        {
            "category":"Shopping",
            "subcategory":"Bicycles & Sporting Goods",
            "type":"Retail Goods"
        }
    ],
    "sg:phone":"+1 403 247 0464",
    "sg:postcode":"T3B 0N1",
    "sg:province":"AB",
    "sg:tags":[
        "automobile",
        "skiing",
        "accessory"
    ],
    "wof:name":"Racks Unlimited",
    "wof:placetype":"venue"
},
  "geometry": {"coordinates":[-114.16298675500001,51.07188797],"type":"Point"}
}