{
  "type": "Feature",
  "properties": {
    "addr:full":"12285 Av Brunet Montreal-Nord QC H1G 5H1",
    "addr:postcode":"h1g 5h1",
    "addr:street":"Av Brunet",
    "iso:country":"CA",
    "sg:address":"12285 Av Brunet",
    "sg:city":"Montreal-Nord",
    "sg:classifiers":[
        {
            "category":"Building & Trades",
            "subcategory":"Construction",
            "type":"Services"
        }
    ],
    "sg:phone":"+1 514 324 9989",
    "sg:postcode":"H1G 5H1",
    "sg:province":"QC",
    "sg:tags":[
        "repairing",
        "remodeling",
        "landscape",
        "contractor"
    ],
    "wof:name":"Charette D Paysagiste Enr",
    "wof:placetype":"venue"
},
  "geometry": {"coordinates":[-73.636223,45.610413],"type":"Point"}
}