{
  "type": "Feature",
  "properties": {
    "addr:full":"316 Rue Saint-Jacques Granby QC J2G 3N2",
    "addr:housenumber":"316",
    "addr:postcode":"j2g 3n2",
    "addr:street":"Rue Saint-Jacques",
    "iso:country":"CA",
    "sg:address":"316 Rue Saint-Jacques",
    "sg:city":"Granby",
    "sg:classifiers":[
        {
            "category":"Home & Garden",
            "subcategory":"Home Furnishings",
            "type":"Retail Goods"
        }
    ],
    "sg:phone":"+1 450 375 1571",
    "sg:postcode":"J2G 3N2",
    "sg:province":"QC",
    "sg:tags":[
        "curtain",
        "made",
        "drapery"
    ],
    "wof:name":"Quintal Draperie",
    "wof:placetype":"venue"
},
  "geometry": {"coordinates":[-72.73246,45.398693],"type":"Point"}
}