{
  "type": "Feature",
  "properties": {
    "addr:full":"North York ON M3C 3L9",
    "addr:postcode":"m3c 3l9",
    "iso:country":"CA",
    "sg:city":"North York",
    "sg:classifiers":[
        {
            "category":"Insurance",
            "subcategory":"Insurance Agent",
            "type":"Services"
        }
    ],
    "sg:phone":"+1 416 446 7423",
    "sg:postcode":"M3C 3L9",
    "sg:province":"ON",
    "wof:name":"Consolidated Insurance Brokers",
    "wof:placetype":"venue"
},
  "geometry": {"coordinates":[-79.336617,43.724007],"type":"Point"}
}