{
  "type": "Feature",
  "properties": {
    "addr:full":"300 Rte 132 Port-Daniel QC G0C 2N0",
    "addr:housenumber":"300",
    "addr:postcode":"g0c 2n0",
    "addr:street":"Rte 132",
    "iso:country":"CA",
    "sg:address":"300 Rte 132",
    "sg:city":"Port-Daniel",
    "sg:classifiers":[
        {
            "category":"Retail",
            "subcategory":"Repair Shop",
            "type":"Services"
        }
    ],
    "sg:phone":"+1 418 396 3162",
    "sg:postcode":"G0C 2N0",
    "sg:province":"QC",
    "sg:tags":[
        "engine"
    ],
    "wof:name":"Norbert's Small Engines",
    "wof:placetype":"venue"
},
  "geometry": {"coordinates":[-64.99175262449999,48.1355819702],"type":"Point"}
}