{
  "type": "Feature",
  "properties": {
    "addr:full":"33 Chauncey Ave Etobicoke ON M8Z 2Z2",
    "addr:housenumber":"33",
    "addr:postcode":"m8z 2z2",
    "addr:street":"Chauncey Ave",
    "iso:country":"CA",
    "sg:address":"33 Chauncey Ave",
    "sg:city":"Etobicoke",
    "sg:classifiers":[
        {
            "category":"Building & Trades",
            "subcategory":"Plumbing",
            "type":"Services"
        }
    ],
    "sg:phone":"+1 416 237 9161",
    "sg:postcode":"M8Z 2Z2",
    "sg:province":"ON",
    "sg:tags":[
        "contractor"
    ],
    "wof:name":"Dan Mac Plumbing & Drain Svc",
    "wof:placetype":"venue"
},
  "geometry": {"coordinates":[-79.524254,43.63726],"type":"Point"}
}