{
  "type": "Feature",
  "properties": {
    "addr:full":"1860 Ellesmere Rd Scarborough ON M1H 2V5",
    "addr:housenumber":"1860",
    "addr:postcode":"m1h 2v5",
    "addr:street":"Ellesmere Rd",
    "iso:country":"CA",
    "sg:address":"1860 Ellesmere Rd",
    "sg:city":"Scarborough",
    "sg:classifiers":[
        {
            "category":"Retail",
            "subcategory":"Auto Repair",
            "type":"Services"
        }
    ],
    "sg:phone":"+1 416 439 9683",
    "sg:postcode":"M1H 2V5",
    "sg:province":"ON",
    "sg:tags":[
        "repairing",
        "automobile"
    ],
    "wof:name":"Stones Auto Svc",
    "wof:placetype":"venue"
},
  "geometry": {"coordinates":[-79.24226400000001,43.774403],"type":"Point"}
}