{
  "type": "Feature",
  "properties": {
    "addr:full":"4260 Rue DE Verdun Verdun QC H4G 1L5",
    "addr:housenumber":"4260",
    "addr:postcode":"h4g 1l5",
    "addr:street":"Rue De Verdun",
    "iso:country":"CA",
    "sg:address":"4260 Rue DE Verdun",
    "sg:city":"Verdun",
    "sg:classifiers":[
        {
            "category":"Personal",
            "subcategory":"Beauty Salon",
            "type":"Services"
        }
    ],
    "sg:phone":"+1 514 762 2394",
    "sg:postcode":"H4G 1L5",
    "sg:province":"QC",
    "wof:name":"Coiffure Sylvie Mode",
    "wof:placetype":"venue"
},
  "geometry": {"coordinates":[-73.57135009770001,45.4615364075],"type":"Point"}
}