{
  "type": "Feature",
  "properties": {
    "addr:full":"188 Ch Des Bois Grande-Riviere QC G0C 1V0",
    "addr:housenumber":"188",
    "addr:postcode":"g0c 1v0",
    "addr:street":"Ch Des Bois Grande-Riviere",
    "iso:country":"CA",
    "sg:address":"188 Ch Des Bois",
    "sg:city":"Grande-Riviere",
    "sg:classifiers":[
        {
            "category":"Personal",
            "subcategory":"Beauty Salon",
            "type":"Services"
        }
    ],
    "sg:phone":"+1 418 385 2684",
    "sg:postcode":"G0C 1V0",
    "sg:province":"QC",
    "wof:name":"Salon DE Coiffure Francine",
    "wof:placetype":"venue"
},
  "geometry": {"coordinates":[-64.478256,48.410255],"type":"Point"}
}