{
  "type": "Feature",
  "properties": {
    "addr:full":"10501 82 Ave NW Edmonton AB T6E 2A3",
    "addr:housenumber":"10501",
    "addr:postcode":"t6e 2a3",
    "addr:street":"82 Ave Nw",
    "iso:country":"CA",
    "sg:address":"10501 82 Ave NW",
    "sg:city":"Edmonton",
    "sg:classifiers":[
        {
            "category":"Restaurant",
            "type":"Food & Drink"
        }
    ],
    "sg:phone":"+1 780 439 9829",
    "sg:postcode":"T6E 2A3",
    "sg:province":"AB",
    "wof:name":"Chianti Cafe & Restaurant",
    "wof:placetype":"venue"
},
  "geometry": {"coordinates":[-113.50078600000001,53.517853],"type":"Point"}
}