{
  "type": "Feature",
  "properties": {
    "addr:full":"9720 Rue Sherbrooke E Montreal QC H1L 6N8",
    "addr:housenumber":"9720",
    "addr:postcode":"h1l 6n8",
    "addr:street":"Rue Sherbrooke E",
    "iso:country":"CA",
    "sg:address":"9720 Rue Sherbrooke E",
    "sg:city":"Montreal",
    "sg:classifiers":[
        {
            "category":"Professional",
            "subcategory":"Management & Consulting",
            "type":"Services"
        }
    ],
    "sg:phone":"+1 514 356 1774",
    "sg:postcode":"H1L 6N8",
    "sg:province":"QC",
    "sg:tags":[
        "consultant",
        "instructional"
    ],
    "wof:name":"Hexa Consultants & Frmtn",
    "wof:placetype":"venue"
},
  "geometry": {"coordinates":[-73.525589,45.61224],"type":"Point"}
}