{
  "type": "Feature",
  "properties": {
    "iso:country":"CA",
    "sg:address":"1289 Marlborough Crt",
    "sg:city":"Oakville",
    "sg:classifiers":[
        {
            "category":"Retail",
            "subcategory":"Laundry & Dry Cleaning",
            "type":"Services"
        }
    ],
    "sg:phone":"+1 905 337 3303",
    "sg:postcode":"L6H 2R9",
    "sg:province":"ON",
    "sg:tags":[
        "cleaners"
    ],
    "wof:name":"Tee Cleaners",
    "wof:placetype":"venue"
},
  "geometry": {"coordinates":[-79.6935501099,43.4695281982],"type":"Point"}
}