{
  "type": "Feature",
  "properties": {
    "addr:full":"7313 Woodbine Ave Markham ON L3R 3V7",
    "addr:housenumber":"7313",
    "addr:postcode":"l3r 3v7",
    "addr:street":"Woodbine Ave",
    "iso:country":"CA",
    "sg:address":"7313 Woodbine Ave",
    "sg:city":"Markham",
    "sg:classifiers":[
        {
            "category":"Personal",
            "subcategory":"Beauty Salon",
            "type":"Services"
        }
    ],
    "sg:phone":"+1 905 305 8002",
    "sg:postcode":"L3R 3V7",
    "sg:province":"ON",
    "wof:name":"Clipindale's Salon Inc",
    "wof:placetype":"venue"
},
  "geometry": {"coordinates":[-79.350449,43.821518],"type":"Point"}
}