{
  "type": "Feature",
  "properties": {
    "addr:full":"19 Flamboro St Waterdown ON L0R 2H0",
    "addr:housenumber":"19",
    "addr:postcode":"l0r 2h0",
    "addr:street":"Flamboro St",
    "iso:country":"CA",
    "sg:address":"19 Flamboro St",
    "sg:city":"Waterdown",
    "sg:classifiers":[
        {
            "category":"Retail",
            "subcategory":"Car Wash",
            "type":"Services"
        }
    ],
    "sg:phone":"+1 905 689 3372",
    "sg:postcode":"L0R 2H0",
    "sg:province":"ON",
    "sg:tags":[
        "polishing",
        "washing"
    ],
    "wof:name":"Midtown Car Wash",
    "wof:placetype":"venue"
},
  "geometry": {"coordinates":[-79.893005,43.332371],"type":"Point"}
}