{
  "type": "Feature",
  "properties": {
    "addr:full":"8 Dominic St Bishops Falls NL A0H 1C0",
    "addr:housenumber":"8",
    "addr:postcode":"a0h 1c0",
    "addr:street":"Dominic St",
    "iso:country":"CA",
    "sg:address":"8 Dominic St",
    "sg:city":"Bishops Falls",
    "sg:classifiers":[
        {
            "category":"Retail",
            "subcategory":"Auto Repair",
            "type":"Services"
        }
    ],
    "sg:phone":"+1 709 258 6462",
    "sg:postcode":"A0H 1C0",
    "sg:province":"NL",
    "sg:tags":[
        "body",
        "automobile",
        "painting"
    ],
    "wof:name":"Triple C Automotive Ltd",
    "wof:placetype":"venue"
},
  "geometry": {"coordinates":[-52.96508,47.519077],"type":"Point"}
}