{
  "type": "Feature",
  "properties": {
    "addr:full":"211 Passekeag Rd Passekeag NB E5N 7N8",
    "addr:housenumber":"211",
    "addr:postcode":"e5n 7n8",
    "addr:street":"Passekeag Rd",
    "iso:country":"CA",
    "sg:address":"211 Passekeag Rd",
    "sg:city":"Passekeag",
    "sg:classifiers":[
        {
            "category":"Professional",
            "subcategory":"Business Services",
            "type":"Services"
        }
    ],
    "sg:phone":"+1 506 832 4794",
    "sg:postcode":"E5N 7N8",
    "sg:province":"NB",
    "sg:tags":[
        "appraiser"
    ],
    "wof:name":"Abl Appraisal Svc Inc",
    "wof:placetype":"venue"
},
  "geometry": {"coordinates":[-65.76187896730001,45.5616912842],"type":"Point"}
}