{
  "type": "Feature",
  "properties": {
    "addr:full":"Stratford ON N5A 3G7",
    "addr:postcode":"n5a 3g7",
    "iso:country":"CA",
    "sg:city":"Stratford",
    "sg:classifiers":[
        {
            "category":"Professional",
            "subcategory":"Lawyer & Legal Services",
            "type":"Services"
        }
    ],
    "sg:phone":"+1 519 271 7330",
    "sg:postcode":"N5A 3G7",
    "sg:province":"ON",
    "sg:tags":[
        "attorney"
    ],
    "wof:name":"Dunphy, Charles G",
    "wof:placetype":"venue"
},
  "geometry": {"coordinates":[-80.98406982420001,43.3714523315],"type":"Point"}
}