{
  "type": "Feature",
  "properties": {
    "iso:country":"CA",
    "sg:address":"810 Eastern Ave",
    "sg:city":"Toronto",
    "sg:classifiers":[
        {
            "category":"Retail",
            "subcategory":"Auto Repair",
            "type":"Services"
        }
    ],
    "sg:phone":"+1 416 463 1774",
    "sg:postcode":"M4L 1A1",
    "sg:province":"ON",
    "sg:tags":[
        "repairing",
        "automobile"
    ],
    "wof:name":"S & S Motors Inc",
    "wof:placetype":"venue"
},
  "geometry": {"coordinates":[-79.3300704956,43.6613845825],"type":"Point"}
}