{
  "type": "Feature",
  "properties": {
    "addr:full":"420 Mackay St Ottawa ON K1M 2C4",
    "addr:housenumber":"420",
    "addr:postcode":"k1m 2c4",
    "addr:street":"Mackay St",
    "iso:country":"CA",
    "sg:address":"420 Mackay St",
    "sg:city":"Ottawa",
    "sg:classifiers":[
        {
            "category":"Health Services",
            "subcategory":"Nursing And Care Facility",
            "type":"Services"
        }
    ],
    "sg:phone":"+1 613 744 0901",
    "sg:postcode":"K1M 2C4",
    "sg:province":"ON",
    "sg:tags":[
        "home",
        "retirement",
        "community"
    ],
    "wof:name":"New Edinburgh Square",
    "wof:placetype":"venue"
},
  "geometry": {"coordinates":[-75.67803192140001,45.439704895],"type":"Point"}
}