{
  "type": "Feature",
  "properties": {
    "addr:full":"320 1st Ave Ladysmith BC V9G 1A3",
    "addr:housenumber":"320",
    "addr:postcode":"v9g 1a3",
    "addr:street":"1St Ave",
    "iso:country":"CA",
    "sg:address":"320 1st Ave",
    "sg:city":"Ladysmith",
    "sg:classifiers":[
        {
            "category":"Shopping",
            "subcategory":"Florist",
            "type":"Retail Goods"
        }
    ],
    "sg:phone":"+1 250 245 2131",
    "sg:postcode":"V9G 1A3",
    "sg:province":"BC",
    "wof:name":"Lait Bloomer Florist",
    "wof:placetype":"venue"
},
  "geometry": {"coordinates":[-123.818108,48.9939],"type":"Point"}
}