{
  "type": "Feature",
  "properties": {
    "iso:country":"CA",
    "sg:address":"10336 106 St",
    "sg:city":"Westlock",
    "sg:classifiers":[
        {
            "category":"Government",
            "subcategory":"Office",
            "type":"Public Place"
        }
    ],
    "sg:phone":"+1 780 349 3346",
    "sg:postcode":"T7P 2G1",
    "sg:province":"AB",
    "sg:tags":[
        "municipality"
    ],
    "wof:name":"Westlock County",
    "wof:placetype":"venue"
},
  "geometry": {"coordinates":[-113.852554321,54.1585121155],"type":"Point"}
}