{
  "type": "Feature",
  "properties": {
    "addr:full":"24 Bellevue St Mansonville QC J0E 1X0",
    "addr:housenumber":"24",
    "addr:postcode":"j0e 1x0",
    "addr:street":"Bellevue St",
    "iso:country":"CA",
    "sg:address":"24 Bellevue St",
    "sg:city":"Mansonville",
    "sg:classifiers":[
        {
            "category":"Manufacturing",
            "subcategory":"Chemicals & Compounds",
            "type":"Manufacturing & Wholesale Goods"
        }
    ],
    "sg:phone":"+1 450 292 3333",
    "sg:postcode":"J0E 1X0",
    "sg:province":"QC",
    "sg:tags":[
        "plastic"
    ],
    "wof:name":"Compagnie Chimique Huntsman",
    "wof:placetype":"venue"
},
  "geometry": {"coordinates":[-72.392197,45.04887],"type":"Point"}
}