{
  "type": "Feature",
  "properties": {
    "iso:country":"CA",
    "sg:address":"514 Fort St",
    "sg:city":"Victoria",
    "sg:classifiers":[
        {
            "category":"Real Estate",
            "subcategory":"Architect",
            "type":"Services"
        }
    ],
    "sg:phone":"+1 250 388 7371",
    "sg:postcode":"V8W 1E6",
    "sg:province":"BC",
    "wof:name":"Garyali Architects",
    "wof:placetype":"venue"
},
  "geometry": {"coordinates":[-123.369415,48.425056],"type":"Point"}
}