{
  "type": "Feature",
  "properties": {
    "addr:full":"1610 8 St # 4 Nisku AB T9E 7S6",
    "addr:housenumber":"1610 8;# 4",
    "addr:postcode":"t9e 7s6",
    "addr:street":"St",
    "iso:country":"CA",
    "sg:address":"1610 8 St # 4",
    "sg:city":"Nisku",
    "sg:classifiers":[
        {
            "category":"Wholesale",
            "subcategory":"Machinery & Supplies",
            "type":"Manufacturing & Wholesale Goods"
        }
    ],
    "sg:phone":"+1 780 955 8933",
    "sg:postcode":"T9E 7S6",
    "sg:province":"AB",
    "sg:tags":[
        "equipment",
        "welding"
    ],
    "wof:name":"Air Liquide Inc",
    "wof:placetype":"venue"
},
  "geometry": {"coordinates":[-113.516228,53.325756],"type":"Point"}
}