{
  "type": "Feature",
  "properties": {
    "addr:full":"Pohenegamook QC G0L 1J0",
    "addr:postcode":"g0l 1j0",
    "iso:country":"CA",
    "sg:city":"Pohenegamook",
    "sg:classifiers":[
        {
            "category":"Personal",
            "subcategory":"Beauty Salon",
            "type":"Services"
        }
    ],
    "sg:phone":"+1 418 859 2648",
    "sg:postcode":"G0L 1J0",
    "sg:province":"QC",
    "wof:name":"Coiffure Choc Enr",
    "wof:placetype":"venue"
},
  "geometry": {"coordinates":[-69.27977,47.486397],"type":"Point"}
}