{
  "type": "Feature",
  "properties": {
    "iso:country":"CA",
    "sg:address":"206 Woodworth Ave",
    "sg:city":"Kenton",
    "sg:classifiers":[
        {
            "category":"Autos & Motor Vehicles",
            "subcategory":"Automobile Sales",
            "type":"Retail Goods"
        }
    ],
    "sg:phone":"+1 204 838 2240",
    "sg:postcode":"R0M 0Z0",
    "sg:province":"MB",
    "sg:tags":[
        "car",
        "dealer"
    ],
    "wof:name":"Woodworth Dodge Chrysler Jeep",
    "wof:placetype":"venue"
},
  "geometry": {"coordinates":[-100.61486053500001,49.9876899719],"type":"Point"}
}