{
  "type": "Feature",
  "properties": {
    "addr:full":"39 Findley Rd Noel NS B0N 2C0",
    "addr:housenumber":"39",
    "addr:postcode":"b0n 2c0",
    "addr:street":"Findley Rd",
    "iso:country":"CA",
    "sg:address":"39 Findley Rd",
    "sg:city":"Noel",
    "sg:classifiers":[
        {
            "category":"Government",
            "subcategory":"Office",
            "type":"Public Place"
        }
    ],
    "sg:phone":"+1 902 369 2169",
    "sg:postcode":"B0N 2C0",
    "sg:province":"NS",
    "wof:name":"Nova Scotia Transportation Grg",
    "wof:placetype":"venue"
},
  "geometry": {"coordinates":[-63.744888,45.295807],"type":"Point"}
}