{
  "type": "Feature",
  "properties": {
    "addr:full":"43 Boyd Oxdrift ON P0V 2J0",
    "addr:housenumber":"43",
    "addr:postcode":"p0v 2j0",
    "addr:street":"Boyd Oxdrift",
    "iso:country":"CA",
    "sg:address":"43 Boyd",
    "sg:city":"Oxdrift",
    "sg:classifiers":[
        {
            "category":"Organizations",
            "subcategory":"Religious Organization",
            "type":"Services"
        }
    ],
    "sg:phone":"+1 807 937 6353",
    "sg:postcode":"P0V 2J0",
    "sg:province":"ON",
    "sg:tags":[
        "church"
    ],
    "wof:name":"Jehovah's Witnesses Kingdom",
    "wof:placetype":"venue"
},
  "geometry": {"coordinates":[-93.016396,49.80135],"type":"Point"}
}