{
  "type": "Feature",
  "properties": {
    "addr:full":"2 Ridgehill Dr Brampton ON L6Y 2C4",
    "addr:housenumber":"2",
    "addr:postcode":"l6y 2c4",
    "addr:street":"Ridgehill Dr",
    "iso:country":"CA",
    "sg:address":"2 Ridgehill Dr",
    "sg:city":"Brampton",
    "sg:classifiers":[
        {
            "category":"Wholesale",
            "subcategory":"Auto Parts",
            "type":"Manufacturing & Wholesale Goods"
        }
    ],
    "sg:phone":"+1 905 456 0607",
    "sg:postcode":"L6Y 2C4",
    "sg:province":"ON",
    "sg:tags":[
        "tire"
    ],
    "wof:name":"M & R Tire Products Inc",
    "wof:placetype":"venue"
},
  "geometry": {"coordinates":[-79.7520980835,43.6678161621],"type":"Point"}
}