{
  "type": "Feature",
  "properties": {
    "iso:country":"CA",
    "sg:address":"98 2nd Ave",
    "sg:city":"Burns Lake",
    "sg:classifiers":[
        {
            "category":"Health Services",
            "subcategory":"Doctor",
            "type":"Services"
        }
    ],
    "sg:phone":"+1 250 692 3103",
    "sg:postcode":"V0J 1E0",
    "sg:province":"BC",
    "sg:tags":[
        "dentist"
    ],
    "wof:name":"Burns Lake Dental Clinic",
    "wof:placetype":"venue"
},
  "geometry": {"coordinates":[-125.761260986,54.2292442322],"type":"Point"}
}