{
  "type": "Feature",
  "properties": {
    "addr:full":"4800 Boul Henri-Bourassa O Saint-Laurent QC H4L 1A8",
    "addr:housenumber":"4800",
    "addr:postcode":"h4l 1a8",
    "addr:street":"Boul Henri-Bourassa O",
    "iso:country":"CA",
    "sg:address":"4800 Boul Henri-Bourassa O",
    "sg:city":"Saint-Laurent",
    "sg:classifiers":[
        {
            "category":"Manufacturing",
            "subcategory":"Glass & Minerals",
            "type":"Manufacturing & Wholesale Goods"
        }
    ],
    "sg:phone":"+1 514 334 2850",
    "sg:postcode":"H4L 1A8",
    "sg:province":"QC",
    "sg:tags":[
        "tile"
    ],
    "wof:name":"Industries Ceramiques Maple",
    "wof:placetype":"venue"
},
  "geometry": {"coordinates":[-73.70510899999999,45.523132],"type":"Point"}
}