{
  "type": "Feature",
  "properties": {
    "addr:full":"Sainte-Cecile-DE-Masham QC J0X 2W0",
    "addr:postcode":"j0x 2w0",
    "iso:country":"CA",
    "sg:city":"Sainte-Cecile-DE-Masham",
    "sg:classifiers":[
        {
            "category":"Personal",
            "subcategory":"Barber",
            "type":"Services"
        }
    ],
    "sg:phone":"+1 819 456 2646",
    "sg:postcode":"J0X 2W0",
    "sg:province":"QC",
    "wof:name":"Thibeault, Jean Marie",
    "wof:placetype":"venue"
},
  "geometry": {"coordinates":[-76.030907,45.643124],"type":"Point"}
}