{
  "type": "Feature",
  "properties": {
    "addr:full":"1 Hwy 3 W Burdett AB T0K 0J0",
    "addr:postcode":"t0k 0j0",
    "addr:street":"1 Hwy 3 W",
    "iso:country":"CA",
    "sg:address":"1 Hwy 3 W",
    "sg:city":"Burdett",
    "sg:classifiers":[
        {
            "category":"Wholesale",
            "subcategory":"Machinery & Supplies",
            "type":"Manufacturing & Wholesale Goods"
        }
    ],
    "sg:phone":"+1 403 833 3811",
    "sg:postcode":"T0K 0J0",
    "sg:province":"AB",
    "sg:tags":[
        "farm",
        "equipment"
    ],
    "wof:name":"Green Power Ltd",
    "wof:placetype":"venue"
},
  "geometry": {"coordinates":[-111.506004334,49.8287582397],"type":"Point"}
}