{
  "type": "Feature",
  "properties": {
    "addr:full":"31 High School Rd Miscouche PE C0B 1T0",
    "addr:housenumber":"31",
    "addr:postcode":"c0b 1t0",
    "addr:street":"High School Rd",
    "iso:country":"CA",
    "sg:address":"31 High School Rd",
    "sg:city":"Miscouche",
    "sg:classifiers":[
        {
            "category":"Recreation",
            "type":"Entertainment"
        }
    ],
    "sg:phone":"+1 902 436 6171",
    "sg:postcode":"C0B 1T0",
    "sg:province":"PE",
    "sg:tags":[
        "center"
    ],
    "wof:name":"Miscouche Rec Ctr",
    "wof:placetype":"venue"
},
  "geometry": {"coordinates":[-63.8633651733,46.4330596924],"type":"Point"}
}