{
  "type": "Feature",
  "properties": {
    "addr:full":"London ON N6J 1Y5",
    "addr:postcode":"n6j 1y5",
    "iso:country":"CA",
    "sg:city":"London",
    "sg:classifiers":[
        {
            "category":"Shopping",
            "subcategory":"Shoes",
            "type":"Retail Goods"
        }
    ],
    "sg:phone":"+1 519 471 7556",
    "sg:postcode":"N6J 1Y5",
    "sg:province":"ON",
    "wof:name":"Ovation Shoes & Sports",
    "wof:placetype":"venue"
},
  "geometry": {"coordinates":[-81.2894287109,42.9545135498],"type":"Point"}
}