{
  "type": "Feature",
  "properties": {
    "iso:country":"CA",
    "sg:address":"31 Garnet Rd",
    "sg:city":"Brantford",
    "sg:classifiers":[
        {
            "category":"Autos & Motor Vehicles",
            "subcategory":"Auto Supplies",
            "type":"Retail Goods"
        }
    ],
    "sg:phone":"+1 519 754 1990",
    "sg:postcode":"N3T 5M1",
    "sg:province":"ON",
    "sg:tags":[
        "automobile",
        "parts",
        "truck"
    ],
    "wof:name":"Northway Ford Lincoln Ltd",
    "wof:placetype":"venue"
},
  "geometry": {"coordinates":[-80.26174163819999,43.1413612366],"type":"Point"}
}