{
  "type": "Feature",
  "properties": {
    "addr:full":"361 Main St N Moose Jaw SK S6H 0W2",
    "addr:housenumber":"361",
    "addr:postcode":"s6h 0w2",
    "addr:street":"Main St N",
    "iso:country":"CA",
    "sg:address":"361 Main St N",
    "sg:city":"Moose Jaw",
    "sg:classifiers":[
        {
            "category":"Retail",
            "subcategory":"Repair Shop",
            "type":"Services"
        }
    ],
    "sg:phone":"+1 306 694 5122",
    "sg:postcode":"S6H 0W2",
    "sg:province":"SK",
    "sg:tags":[
        "jewelry"
    ],
    "wof:name":"Stuart Bozyk Goldsmith",
    "wof:placetype":"venue"
},
  "geometry": {"coordinates":[-105.534385681,50.3931121826],"type":"Point"}
}