{
  "type": "Feature",
  "properties": {
    "addr:full":"3152 Avonhurst Dr Regina SK S4R 3J7",
    "addr:housenumber":"3152",
    "addr:postcode":"s4r 3j7",
    "addr:street":"Avonhurst Dr",
    "iso:country":"CA",
    "sg:address":"3152 Avonhurst Dr",
    "sg:city":"Regina",
    "sg:classifiers":[
        {
            "category":"Banks & Credit Unions",
            "subcategory":"Investment Brokerage",
            "type":"Services"
        }
    ],
    "sg:phone":"+1 306 546 5511",
    "sg:postcode":"S4R 3J7",
    "sg:province":"SK",
    "sg:tags":[
        "consultant",
        "planning",
        "financial"
    ],
    "wof:name":"Partners in Planning Financial",
    "wof:placetype":"venue"
},
  "geometry": {"coordinates":[-104.62611389200001,50.4720039368],"type":"Point"}
}