{
  "type": "Feature",
  "properties": {
    "addr:full":"5130 Boul Saint-Laurent Montreal QC H2T 1R8",
    "addr:housenumber":"5130",
    "addr:postcode":"h2t 1r8",
    "addr:street":"Boul Saint-Laurent",
    "iso:country":"CA",
    "sg:address":"5130 Boul Saint-Laurent",
    "sg:city":"Montreal",
    "sg:classifiers":[
        {
            "category":"Sports & Exercise",
            "subcategory":"Gym",
            "type":"Entertainment"
        }
    ],
    "sg:phone":"+1 514 274 3110",
    "sg:postcode":"H2T 1R8",
    "sg:province":"QC",
    "sg:tags":[
        "club",
        "health",
        "studio",
        "gymnasium"
    ],
    "wof:name":"Gymnastique Sur Table Tcp",
    "wof:placetype":"venue"
},
  "geometry": {"coordinates":[-73.593513,45.523224],"type":"Point"}
}