{
  "type": "Feature",
  "properties": {
    "iso:country":"CA",
    "sg:address":"835 Topsail Rd",
    "sg:city":"Mount Pearl",
    "sg:classifiers":[
        {
            "category":"Shopping",
            "subcategory":"Musical Instruments",
            "type":"Retail Goods"
        }
    ],
    "sg:phone":"+1 709 364 2233",
    "sg:postcode":"A1N 3J6",
    "sg:province":"NL",
    "wof:name":"Reid Music Ltd",
    "wof:placetype":"venue"
},
  "geometry": {"coordinates":[-52.7914466858,47.5240516663],"type":"Point"}
}