{
  "type": "Feature",
  "properties": {
    "addr:full":"1425 Rue Du Fort # 200 Montreal QC H3H 2C2",
    "addr:housenumber":"1425",
    "addr:postcode":"h3h 2c2",
    "addr:street":"Rue Du Fort # 200",
    "iso:country":"CA",
    "sg:address":"1425 Rue Du Fort # 200",
    "sg:city":"Montreal",
    "sg:classifiers":[
        {
            "category":"Manufacturing",
            "subcategory":"Printing",
            "type":"Manufacturing & Wholesale Goods"
        }
    ],
    "sg:phone":"+1 514 939 2800",
    "sg:postcode":"H3H 2C2",
    "sg:province":"QC",
    "sg:tags":[
        "publisher"
    ],
    "wof:name":"Ofc Publications Inc",
    "wof:placetype":"venue"
},
  "geometry": {"coordinates":[-73.5816268921,45.4921417236],"type":"Point"}
}