{
  "type": "Feature",
  "properties": {
    "iso:country":"CA",
    "sg:address":"11754 216 St",
    "sg:city":"Maple Ridge",
    "sg:classifiers":[
        {
            "category":"Wholesale",
            "subcategory":"Hardware",
            "type":"Manufacturing & Wholesale Goods"
        }
    ],
    "sg:phone":"+1 604 463 8706",
    "sg:postcode":"V2X 5H6",
    "sg:province":"BC",
    "sg:tags":[
        "plumbing",
        "fixture",
        "supply"
    ],
    "wof:name":"Mph Supply Ltd",
    "wof:placetype":"venue"
},
  "geometry": {"coordinates":[-122.622756958,49.2162666321],"type":"Point"}
}