{
  "type": "Feature",
  "properties": {
    "addr:full":"2251 Lynn-LA-Ran Dr Nanaimo BC V9R 6W1",
    "addr:housenumber":"2251",
    "addr:postcode":"v9r 6w1",
    "addr:street":"Lynn-La-Ran Dr",
    "iso:country":"CA",
    "sg:address":"2251 Lynn-LA-Ran Dr",
    "sg:city":"Nanaimo",
    "sg:classifiers":[
        {
            "category":"Building & Trades",
            "subcategory":"Construction",
            "type":"Services"
        }
    ],
    "sg:phone":"+1 250 716 9161",
    "sg:postcode":"V9R 6W1",
    "sg:province":"BC",
    "sg:tags":[
        "general",
        "contractor"
    ],
    "wof:name":"Inter Isle Construction Ltd",
    "wof:placetype":"venue"
},
  "geometry": {"coordinates":[-124.003189087,49.1760025024],"type":"Point"}
}