{
  "type": "Feature",
  "properties": {
    "addr:full":"1680 Av Morgan Montreal QC H1V 2P9",
    "addr:housenumber":"1680",
    "addr:postcode":"h1v 2p9",
    "addr:street":"Av Morgan",
    "iso:country":"CA",
    "sg:address":"1680 Av Morgan",
    "sg:city":"Montreal",
    "sg:classifiers":[
        {
            "category":"Education",
            "subcategory":"School",
            "type":"Public Place"
        }
    ],
    "sg:phone":"+1 514 596 5442",
    "sg:postcode":"H1V 2P9",
    "sg:province":"QC",
    "wof:name":"Maisonneuve Ecole",
    "wof:placetype":"venue"
},
  "geometry": {"coordinates":[-73.5361862183,45.5522041321],"type":"Point"}
}