{
  "type": "Feature",
  "properties": {
    "addr:full":"19 Pamille Pl North York ON M6M 3A9",
    "addr:housenumber":"19",
    "addr:postcode":"m6m 3a9",
    "addr:street":"Pamille Pl",
    "iso:country":"CA",
    "sg:address":"19 Pamille Pl",
    "sg:city":"North York",
    "sg:classifiers":[
        {
            "category":"Professional",
            "subcategory":"Computer Services",
            "type":"Services"
        }
    ],
    "sg:phone":"+1 416 248 6021",
    "sg:postcode":"M6M 3A9",
    "sg:province":"ON",
    "sg:tags":[
        "consultant"
    ],
    "wof:name":"Jdp Micro Solutions",
    "wof:placetype":"venue"
},
  "geometry": {"coordinates":[-79.501312,43.70068],"type":"Point"}
}