{
  "type": "Feature",
  "properties": {
    "addr:full":"1900 Rue Sherbrooke O Montreal QC H3H 1E6",
    "addr:housenumber":"1900",
    "addr:postcode":"h3h 1e6",
    "addr:street":"Rue Sherbrooke O",
    "iso:country":"CA",
    "sg:address":"1900 Rue Sherbrooke O",
    "sg:city":"Montreal",
    "sg:classifiers":[
        {
            "category":"Manufacturing",
            "subcategory":"Tools & Machinery",
            "type":"Manufacturing & Wholesale Goods"
        }
    ],
    "sg:phone":"+1 514 933 1198",
    "sg:postcode":"H3H 1E6",
    "sg:province":"QC",
    "sg:tags":[
        "transmission",
        "equipment",
        "plant",
        "power"
    ],
    "wof:name":"Enviromondial Inc",
    "wof:placetype":"venue"
},
  "geometry": {"coordinates":[-73.563393,45.529022],"type":"Point"}
}