{
  "type": "Feature",
  "properties": {
    "addr:full":"732 Rue Commerciale Saint-Jean-Chrysostome QC G6Z 2C5",
    "addr:housenumber":"732",
    "addr:postcode":"g6z 2c5",
    "addr:street":"Rue Commerciale Saint-Jean-Chrysostome",
    "iso:country":"CA",
    "sg:address":"732 Rue Commerciale",
    "sg:city":"Saint-Jean-Chrysostome",
    "sg:classifiers":[
        {
            "category":"Retail",
            "subcategory":"Auto Repair",
            "type":"Services"
        }
    ],
    "sg:phone":"+1 418 839 2282",
    "sg:postcode":"G6Z 2C5",
    "sg:province":"QC",
    "sg:tags":[
        "repairing",
        "automobile"
    ],
    "wof:name":"Garage Renaud Blais Enr",
    "wof:placetype":"venue"
},
  "geometry": {"coordinates":[-71.2100982666,46.7341880798],"type":"Point"}
}