{
  "type": "Feature",
  "properties": {
    "addr:full":"2883 Howard Ave Windsor ON N8X 3Y4",
    "addr:housenumber":"2883",
    "addr:postcode":"n8x 3y4",
    "addr:street":"Howard Ave",
    "iso:country":"CA",
    "sg:address":"2883 Howard Ave",
    "sg:city":"Windsor",
    "sg:classifiers":[
        {
            "category":"Travel",
            "subcategory":"Hotels & Motels",
            "type":"Entertainment"
        }
    ],
    "sg:phone":"+1 519 969 9120",
    "sg:postcode":"N8X 3Y4",
    "sg:province":"ON",
    "wof:name":"Towne & Country Motel",
    "wof:placetype":"venue"
},
  "geometry": {"coordinates":[-83.00890350340001,42.2797012329],"type":"Point"}
}