{
  "type": "Feature",
  "properties": {
    "addr:full":"3240 1E Av Quebec QC G1L 3P9",
    "addr:housenumber":"3240",
    "addr:postcode":"g1l 3p9",
    "addr:street":"1E Av",
    "iso:country":"CA",
    "sg:address":"3240 1E Av",
    "sg:city":"Quebec",
    "sg:classifiers":[
        {
            "category":"Food & Beverages",
            "subcategory":"Groceries & Convenience Stores",
            "type":"Retail Goods"
        }
    ],
    "sg:phone":"+1 418 623 3152",
    "sg:postcode":"G1L 3P9",
    "sg:province":"QC",
    "sg:tags":[
        "grocer"
    ],
    "wof:name":"Couche-Tard",
    "wof:placetype":"venue"
},
  "geometry": {"coordinates":[-71.24621582029999,46.8395614624],"type":"Point"}
}