{
  "type": "Feature",
  "properties": {
    "addr:full":"6145 Wasa School Rd Wasa BC V0B 2K0",
    "addr:housenumber":"6145",
    "addr:postcode":"bc v0b 2k0",
    "addr:street":"Wasa School Rd",
    "iso:country":"CA",
    "sg:address":"6145 Wasa School Rd",
    "sg:city":"Wasa",
    "sg:classifiers":[
        {
            "category":"Recreation",
            "type":"Entertainment"
        }
    ],
    "sg:phone":"+1 250 422 3607",
    "sg:postcode":"V0B 2K0",
    "sg:province":"BC",
    "sg:tags":[
        "hall",
        "auditorium"
    ],
    "wof:name":"Wasa Community Hall",
    "wof:placetype":"venue"
},
  "geometry": {"coordinates":[-115.744995,49.791794],"type":"Point"}
}