{
  "type": "Feature",
  "properties": {
    "addr:full":"5764 Tecumseh Rd E Windsor ON N8T 1C9",
    "addr:housenumber":"5764",
    "addr:postcode":"n8t 1c9",
    "addr:street":"Tecumseh Rd E",
    "iso:country":"CA",
    "sg:address":"5764 Tecumseh Rd E",
    "sg:city":"Windsor",
    "sg:classifiers":[
        {
            "category":"Retail",
            "subcategory":"Auto Repair",
            "type":"Services"
        }
    ],
    "sg:phone":"+1 519 974 9499",
    "sg:postcode":"N8T 1C9",
    "sg:province":"ON",
    "sg:tags":[
        "repairing",
        "automobile"
    ],
    "wof:name":"Mr Lube",
    "wof:placetype":"venue"
},
  "geometry": {"coordinates":[-82.95612300000001,42.309757],"type":"Point"}
}