{
  "type": "Feature",
  "properties": {
    "addr:full":"Richmond BC V6X 3A2",
    "addr:postcode":"v6x 3a2",
    "iso:country":"CA",
    "sg:city":"Richmond",
    "sg:classifiers":[
        {
            "category":"Retail",
            "subcategory":"Auto Repair",
            "type":"Services"
        }
    ],
    "sg:phone":"+1 604 270 3135",
    "sg:postcode":"V6X 3A2",
    "sg:province":"BC",
    "sg:tags":[
        "repairing",
        "automobile",
        "radiator"
    ],
    "wof:name":"Paul's Radiator Ltd",
    "wof:placetype":"venue"
},
  "geometry": {"coordinates":[-123.10172300000001,49.19215],"type":"Point"}
}