{
  "type": "Feature",
  "properties": {
    "addr:full":"Montreal QC H2A 2W9",
    "addr:postcode":"h2a 2w9",
    "iso:country":"CA",
    "sg:city":"Montreal",
    "sg:classifiers":[
        {
            "category":"Shopping",
            "subcategory":"Computers & Home Electronics",
            "type":"Retail Goods"
        }
    ],
    "sg:phone":"+1 514 722 2278",
    "sg:postcode":"H2A 2W9",
    "sg:province":"QC",
    "sg:tags":[
        "equipment",
        "satellite",
        "system"
    ],
    "wof:name":"V C Satellite",
    "wof:placetype":"venue"
},
  "geometry": {"coordinates":[-73.60410299999999,45.563988],"type":"Point"}
}