{
  "type": "Feature",
  "properties": {
    "addr:full":"10815 104 St Grande Prairie AB T8V 6R2",
    "addr:housenumber":"10815",
    "addr:postcode":"t8v 6r2",
    "addr:street":"104 St",
    "iso:country":"CA",
    "sg:address":"10815 104 St",
    "sg:city":"Grande Prairie",
    "sg:classifiers":[
        {
            "category":"Education",
            "subcategory":"School",
            "type":"Public Place"
        }
    ],
    "sg:phone":"+1 780 532 9276",
    "sg:postcode":"T8V 6R2",
    "sg:province":"AB",
    "wof:name":"Harry Balfour School",
    "wof:placetype":"venue"
},
  "geometry": {"coordinates":[-118.80748748800001,55.1781959534],"type":"Point"}
}