{
  "type": "Feature",
  "properties": {
    "addr:full":"963 Cates Walk Bowen Island BC V0N 1G0",
    "addr:housenumber":"963",
    "addr:postcode":"v0n 1g0",
    "addr:street":"Cates Walk",
    "iso:country":"CA",
    "sg:address":"963 Cates Walk",
    "sg:city":"Bowen Island",
    "sg:classifiers":[
        {
            "category":"Professional",
            "subcategory":"Management & Consulting",
            "type":"Services"
        }
    ],
    "sg:phone":"+1 604 947 2219",
    "sg:postcode":"V0N 1G0",
    "sg:province":"BC",
    "sg:tags":[
        "construction"
    ],
    "wof:name":"Dal-Tech Resources",
    "wof:placetype":"venue"
},
  "geometry": {"coordinates":[-123.33971405,49.3779678345],"type":"Point"}
}