{
  "type": "Feature",
  "properties": {
    "addr:full":"Saint-Cesaire QC J0L 1T0",
    "addr:postcode":"j0l 1t0",
    "iso:country":"CA",
    "sg:city":"Saint-Cesaire",
    "sg:classifiers":[
        {
            "category":"Sports & Exercise",
            "subcategory":"Bowling",
            "type":"Entertainment"
        }
    ],
    "sg:phone":"+1 450 469 2872",
    "sg:postcode":"J0L 1T0",
    "sg:province":"QC",
    "sg:tags":[
        "center"
    ],
    "wof:name":"Salon DE Quilles Tremblay",
    "wof:placetype":"venue"
},
  "geometry": {"coordinates":[-73.000984,45.411457],"type":"Point"}
}