{
  "type": "Feature",
  "properties": {
    "iso:country":"CA",
    "sg:city":"Delta",
    "sg:classifiers":[
        {
            "category":"Wholesale",
            "subcategory":"Electrical",
            "type":"Manufacturing & Wholesale Goods"
        }
    ],
    "sg:phone":"+1 604 523 0933",
    "sg:postcode":"V3M 6J8",
    "sg:province":"BC",
    "sg:tags":[
        "equipment",
        "electronic",
        "supply"
    ],
    "wof:name":"Omega Electronics",
    "wof:placetype":"venue"
},
  "geometry": {"coordinates":[-122.965584,49.165276],"type":"Point"}
}