{
  "type": "Feature",
  "properties": {
    "addr:full":"741 Mountain Rd Moncton NB E1C 2R1",
    "addr:housenumber":"741",
    "addr:postcode":"e1c 2r1",
    "addr:street":"Mountain Rd",
    "iso:country":"CA",
    "sg:address":"741 Mountain Rd",
    "sg:city":"Moncton",
    "sg:classifiers":[
        {
            "category":"Health Services",
            "subcategory":"Doctor",
            "type":"Services"
        }
    ],
    "sg:phone":"+1 506 859 4422",
    "sg:postcode":"E1C 2R1",
    "sg:province":"NB",
    "sg:tags":[
        "dentist"
    ],
    "wof:name":"Suzanne Drapeau Mc Nally Pro",
    "wof:placetype":"venue"
},
  "geometry": {"coordinates":[-64.8046875,46.0994606018],"type":"Point"}
}