{
  "type": "Feature",
  "properties": {
    "addr:full":"5736 Rue Tousignan Laval QC H7K 2W7",
    "addr:housenumber":"5736",
    "addr:postcode":"qc h7k 2w7",
    "addr:street":"Rue Tousignan",
    "iso:country":"CA",
    "sg:address":"5736 Rue Tousignan",
    "sg:city":"Laval",
    "sg:classifiers":[
        {
            "category":"Personal",
            "type":"Services"
        }
    ],
    "sg:phone":"+1 450 622 2846",
    "sg:postcode":"H7K 2W7",
    "sg:province":"QC",
    "sg:tags":[
        "electrolysis"
    ],
    "wof:name":"Esthetique Pierrette Voyer Enr",
    "wof:placetype":"venue"
},
  "geometry": {"coordinates":[-73.7580947876,45.627368927],"type":"Point"}
}