{
  "type": "Feature",
  "properties": {
    "addr:full":"99 Glidden Rd Brampton ON L6T 2H8",
    "addr:housenumber":"99",
    "addr:postcode":"l6t 2h8",
    "addr:street":"Glidden Rd",
    "iso:country":"CA",
    "sg:address":"99 Glidden Rd",
    "sg:city":"Brampton",
    "sg:classifiers":[
        {
            "category":"Professional",
            "subcategory":"Research",
            "type":"Services"
        }
    ],
    "sg:phone":"+1 905 457 5757",
    "sg:postcode":"L6T 2H8",
    "sg:province":"ON",
    "sg:tags":[
        "foundation",
        "philanthropic"
    ],
    "wof:name":"Sri Guru Nanak Sikh Ctr",
    "wof:placetype":"venue"
},
  "geometry": {"coordinates":[-79.71642300000001,43.69302],"type":"Point"}
}