{
  "type": "Feature",
  "properties": {
    "addr:full":"68 Princess St Hamilton ON L8L 3K9",
    "addr:housenumber":"68",
    "addr:postcode":"l8l 3k9",
    "addr:street":"Princess St",
    "iso:country":"CA",
    "sg:address":"68 Princess St",
    "sg:city":"Hamilton",
    "sg:classifiers":[
        {
            "category":"Professional",
            "type":"Services"
        }
    ],
    "sg:phone":"+1 905 545 8434",
    "sg:postcode":"L8L 3K9",
    "sg:province":"ON",
    "sg:tags":[
        "equipment",
        "hydroponics",
        "supply"
    ],
    "wof:name":"Happy Hydroponics",
    "wof:placetype":"venue"
},
  "geometry": {"coordinates":[-79.836868,43.258862],"type":"Point"}
}