{
  "type": "Feature",
  "properties": {
    "addr:full":"8 Elizabeth Dr Paradise NL A1L 1E4",
    "addr:housenumber":"8",
    "addr:postcode":"a1l 1e4",
    "addr:street":"Elizabeth Dr",
    "iso:country":"CA",
    "sg:address":"8 Elizabeth Dr",
    "sg:city":"Paradise",
    "sg:classifiers":[
        {
            "category":"Food & Beverages",
            "subcategory":"Groceries & Convenience Stores",
            "type":"Retail Goods"
        }
    ],
    "sg:phone":"+1 709 782 1312",
    "sg:postcode":"A1L 1E4",
    "sg:province":"NL",
    "wof:name":"Needs Store",
    "wof:placetype":"venue"
},
  "geometry": {"coordinates":[-52.8406906128,47.541973114],"type":"Point"}
}