{
  "type": "Feature",
  "properties": {
    "iso:country":"CA",
    "sg:address":"162 King St E",
    "sg:city":"Oshawa",
    "sg:classifiers":[
        {
            "category":"Retail",
            "subcategory":"Auto Repair",
            "type":"Services"
        }
    ],
    "sg:phone":"+1 905 720 2222",
    "sg:postcode":"L1H 1B6",
    "sg:province":"ON",
    "sg:tags":[
        "transmission"
    ],
    "wof:name":"Aamco Transmissions",
    "wof:placetype":"venue"
},
  "geometry": {"coordinates":[-78.857811,43.89909],"type":"Point"}
}