{
  "type": "Feature",
  "properties": {
    "addr:full":"2740 Merrittville Hwy Fonthill ON L0S 1E6",
    "addr:housenumber":"2740",
    "addr:postcode":"l0s 1e6",
    "addr:street":"Merrittville Hwy",
    "iso:country":"CA",
    "sg:address":"2740 Merrittville Hwy",
    "sg:city":"Fonthill",
    "sg:classifiers":[
        {
            "category":"Restaurant",
            "type":"Food & Drink"
        }
    ],
    "sg:phone":"+1 905 685 4418",
    "sg:postcode":"L0S 1E6",
    "sg:province":"ON",
    "wof:name":"Arizona's Taps & Grill",
    "wof:placetype":"venue"
},
  "geometry": {"coordinates":[-79.28182200000001,43.044098],"type":"Point"}
}