{
  "type": "Feature",
  "properties": {
    "addr:full":"35190 Delair Rd Abbotsford BC V3G 2E2",
    "addr:housenumber":"35190",
    "addr:postcode":"v3g 2e2",
    "addr:street":"Delair Rd",
    "iso:country":"CA",
    "sg:address":"35190 Delair Rd",
    "sg:city":"Abbotsford",
    "sg:classifiers":[
        {
            "category":"Organizations",
            "subcategory":"Religious Organization",
            "type":"Services"
        }
    ],
    "sg:phone":"+1 604 556 7000",
    "sg:postcode":"V3G 2E2",
    "sg:province":"BC",
    "sg:tags":[
        "church"
    ],
    "wof:name":"Cascade Community Church",
    "wof:placetype":"venue"
},
  "geometry": {"coordinates":[-122.25026699999999,49.034737],"type":"Point"}
}