{
  "type": "Feature",
  "properties": {
    "addr:full":"383 Main St Delhi ON N4B 2M9",
    "addr:housenumber":"383",
    "addr:postcode":"n4b 2m9",
    "addr:street":"Main St",
    "iso:country":"CA",
    "sg:address":"383 Main St",
    "sg:city":"Delhi",
    "sg:classifiers":[
        {
            "category":"Personal",
            "subcategory":"Beauty Salon",
            "type":"Services"
        }
    ],
    "sg:phone":"+1 519 582 1241",
    "sg:postcode":"N4B 2M9",
    "sg:province":"ON",
    "wof:name":"Second Appearance",
    "wof:placetype":"venue"
},
  "geometry": {"coordinates":[-80.501053,42.849766],"type":"Point"}
}