{
  "type": "Feature",
  "properties": {
    "iso:country":"CA",
    "sg:address":"2 Rue Surrey",
    "sg:city":"Dollard-Des-Ormeaux",
    "sg:classifiers":[
        {
            "category":"Wholesale",
            "subcategory":"Machinery & Supplies",
            "type":"Manufacturing & Wholesale Goods"
        }
    ],
    "sg:phone":"+1 514 685 1897",
    "sg:postcode":"H9B 2C3",
    "sg:province":"QC",
    "sg:tags":[
        "packer",
        "equipment",
        "meat"
    ],
    "wof:name":"Hand'Man Food Machinery Distr",
    "wof:placetype":"venue"
},
  "geometry": {"coordinates":[-73.7897720337,45.4912071228],"type":"Point"}
}