{
  "type": "Feature",
  "properties": {
    "addr:full":"15 Conner Hill Dr Morden MB R6M 1H7",
    "addr:housenumber":"15",
    "addr:postcode":"r6m 1h7",
    "addr:street":"Conner Hill Dr",
    "iso:country":"CA",
    "sg:address":"15 Conner Hill Dr",
    "sg:city":"Morden",
    "sg:classifiers":[
        {
            "category":"Organizations",
            "subcategory":"Religious Organization",
            "type":"Services"
        }
    ],
    "sg:phone":"+1 204 822 1166",
    "sg:postcode":"R6M 1H7",
    "sg:province":"MB",
    "sg:tags":[
        "church"
    ],
    "wof:name":"Hillside Community Church",
    "wof:placetype":"venue"
},
  "geometry": {"coordinates":[-98.124779,49.182987],"type":"Point"}
}