{
  "type": "Feature",
  "properties": {
    "addr:full":"13077 Highway 48 Stouffville ON L4A 7X3",
    "addr:housenumber":"13077",
    "addr:postcode":"l4a 7x3",
    "addr:street":"Highway 48",
    "iso:country":"CA",
    "sg:address":"13077 Highway 48",
    "sg:city":"Stouffville",
    "sg:classifiers":[
        {
            "category":"Recreation",
            "type":"Entertainment"
        }
    ],
    "sg:phone":"+1 905 640 2928",
    "sg:postcode":"L4A 7X3",
    "sg:province":"ON",
    "sg:tags":[
        "party",
        "fishing"
    ],
    "wof:name":"Burd's Trout Fishing",
    "wof:placetype":"venue"
},
  "geometry": {"coordinates":[-79.248024,43.971085],"type":"Point"}
}