{
  "type": "Feature",
  "properties": {
    "addr:full":"55 Midpark Rise SE Calgary AB T2X 1L7",
    "addr:housenumber":"55",
    "addr:postcode":"t2x 1l7",
    "addr:street":"Midpark Rise Se",
    "iso:country":"CA",
    "sg:address":"55 Midpark Rise SE",
    "sg:city":"Calgary",
    "sg:classifiers":[
        {
            "category":"Education",
            "subcategory":"School",
            "type":"Public Place"
        }
    ],
    "sg:phone":"+1 403 777 8680",
    "sg:postcode":"T2X 1L7",
    "sg:province":"AB",
    "wof:name":"Midnappore Elementary School",
    "wof:placetype":"venue"
},
  "geometry": {"coordinates":[-114.055565,50.915333],"type":"Point"}
}