{
  "type": "Feature",
  "properties": {
    "addr:full":"Swan River MB R0L 1Z0",
    "addr:postcode":"r0l 1z0",
    "iso:country":"CA",
    "sg:city":"Swan River",
    "sg:classifiers":[
        {
            "category":"Manufacturing",
            "subcategory":"Lumber",
            "type":"Manufacturing & Wholesale Goods"
        }
    ],
    "sg:phone":"+1 204 734 4222",
    "sg:postcode":"R0L 1Z0",
    "sg:province":"MB",
    "sg:tags":[
        "company",
        "logging"
    ],
    "wof:name":"Intermountain Logging",
    "wof:placetype":"venue"
},
  "geometry": {"coordinates":[-101.251449585,52.1071510315],"type":"Point"}
}