{
  "type": "Feature",
  "properties": {
    "addr:full":"130 Oxford St Ingersoll ON N5C 2V5",
    "addr:housenumber":"130",
    "addr:postcode":"n5c 2v5",
    "addr:street":"Oxford St",
    "iso:country":"CA",
    "sg:address":"130 Oxford St",
    "sg:city":"Ingersoll",
    "sg:classifiers":[
        {
            "category":"Education",
            "subcategory":"Library",
            "type":"Public Place"
        }
    ],
    "sg:phone":"+1 519 485 7394",
    "sg:postcode":"N5C 2V5",
    "sg:province":"ON",
    "wof:name":"Oxford County Library Hq",
    "wof:placetype":"venue"
},
  "geometry": {"coordinates":[-80.88402600000001,43.038074],"type":"Point"}
}