{
  "type": "Feature",
  "properties": {
    "addr:full":"9155 King George Hwy Surrey BC V3V 5W1",
    "addr:housenumber":"9155",
    "addr:postcode":"v3v 5w1",
    "addr:street":"King George Hwy",
    "iso:country":"CA",
    "sg:address":"9155 King George Hwy",
    "sg:city":"Surrey",
    "sg:classifiers":[
        {
            "category":"Travel",
            "subcategory":"Hotels & Motels",
            "type":"Entertainment"
        }
    ],
    "sg:phone":"+1 604 591 1900",
    "sg:postcode":"V3V 5W1",
    "sg:province":"BC",
    "wof:name":"Motel Hollywood Inc",
    "wof:placetype":"venue"
},
  "geometry": {"coordinates":[-122.846146,49.16917],"type":"Point"}
}