{
  "type": "Feature",
  "properties": {
    "addr:full":"269 Rue Saint-Paul Quebec QC G1K 3W6",
    "addr:housenumber":"269",
    "addr:postcode":"g1k 3w6",
    "addr:street":"Rue Saint-Paul",
    "iso:country":"CA",
    "sg:address":"269 Rue Saint-Paul",
    "sg:city":"Quebec",
    "sg:classifiers":[
        {
            "category":"Professional",
            "subcategory":"Lawyer & Legal Services",
            "type":"Services"
        }
    ],
    "sg:phone":"+1 418 692 3636",
    "sg:postcode":"G1K 3W6",
    "sg:province":"QC",
    "sg:tags":[
        "attorney"
    ],
    "wof:name":"Daignault & Assoc",
    "wof:placetype":"venue"
},
  "geometry": {"coordinates":[-71.210686,46.816952],"type":"Point"}
}