{
  "type": "Feature",
  "properties": {
    "addr:full":"9428 Boul Du Golf Anjou QC H1J 3A1",
    "addr:housenumber":"9428",
    "addr:postcode":"h1j 3a1",
    "addr:street":"Boul Du Golf",
    "iso:country":"CA",
    "sg:address":"9428 Boul Du Golf",
    "sg:city":"Anjou",
    "sg:classifiers":[
        {
            "category":"Manufacturing",
            "subcategory":"Tools & Machinery",
            "type":"Manufacturing & Wholesale Goods"
        }
    ],
    "sg:phone":"+1 514 341 5950",
    "sg:postcode":"H1J 3A1",
    "sg:province":"QC",
    "sg:tags":[
        "electric",
        "motor"
    ],
    "wof:name":"V J Pamensky Ltd",
    "wof:placetype":"venue"
},
  "geometry": {"coordinates":[-73.56215667719999,45.6235733032],"type":"Point"}
}