{
  "type": "Feature",
  "properties": {
    "iso:country":"CA",
    "sg:address":"495 Greenacre Blvd",
    "sg:city":"Winnipeg",
    "sg:classifiers":[
        {
            "category":"Building & Trades",
            "subcategory":"Construction",
            "type":"Services"
        }
    ],
    "sg:phone":"+1 204 888 7293",
    "sg:postcode":"R3K 1B6",
    "sg:province":"MB",
    "sg:tags":[
        "downspouts",
        "gutter"
    ],
    "wof:name":"Quality Eavestroughing Ltd",
    "wof:placetype":"venue"
},
  "geometry": {"coordinates":[-97.284157,49.878384],"type":"Point"}
}