{
  "type": "Feature",
  "properties": {
    "addr:full":"46000 Britton Ave Chilliwack BC V2R 2R8",
    "addr:postcode":"46000;v2r 2r8",
    "addr:street":"Britton Ave",
    "iso:country":"CA",
    "sg:address":"46000 Britton Ave",
    "sg:city":"Chilliwack",
    "sg:classifiers":[
        {
            "category":"Personal",
            "type":"Services"
        }
    ],
    "sg:phone":"+1 604 858 6802",
    "sg:postcode":"V2R 2R8",
    "sg:province":"BC",
    "sg:tags":[
        "therapist",
        "massage"
    ],
    "wof:name":"Krejan Massage Clinic",
    "wof:placetype":"venue"
},
  "geometry": {"coordinates":[-121.95135498,49.1315841675],"type":"Point"}
}