{
  "type": "Feature",
  "properties": {
    "iso:country":"CA",
    "sg:address":"4240 Rue Marcel-Lacasse",
    "sg:city":"Boisbriand",
    "sg:classifiers":[
        {
            "category":"Wholesale",
            "subcategory":"Construction Materials",
            "type":"Manufacturing & Wholesale Goods"
        }
    ],
    "sg:phone":"+1 450 435 8449",
    "sg:postcode":"J7H 1N3",
    "sg:province":"QC",
    "sg:tags":[
        "concrete",
        "form"
    ],
    "wof:name":"Construction Astra Inc",
    "wof:placetype":"venue"
},
  "geometry": {"coordinates":[-73.8738479614,45.6336631775],"type":"Point"}
}