{
  "type": "Feature",
  "properties": {
    "addr:full":"2535 Rue DE Salaberry Montreal QC H3M 1L1",
    "addr:housenumber":"2535",
    "addr:postcode":"h3m 1l1",
    "addr:street":"Rue De Salaberry",
    "iso:country":"CA",
    "sg:address":"2535 Rue DE Salaberry",
    "sg:city":"Montreal",
    "sg:classifiers":[
        {
            "category":"Retail",
            "subcategory":"Laundry & Dry Cleaning",
            "type":"Services"
        }
    ],
    "sg:phone":"+1 514 334 7830",
    "sg:postcode":"H3M 1L1",
    "sg:province":"QC",
    "sg:tags":[
        "cleaners"
    ],
    "wof:name":"Marie Claire Cleaners",
    "wof:placetype":"venue"
},
  "geometry": {"coordinates":[-73.698723,45.538593],"type":"Point"}
}