{
  "type": "Feature",
  "properties": {
    "iso:country":"CA",
    "sg:address":"230 Munger St W",
    "sg:city":"Harrow",
    "sg:classifiers":[
        {
            "category":"Building & Trades",
            "subcategory":"Construction",
            "type":"Services"
        }
    ],
    "sg:phone":"+1 519 738 9233",
    "sg:postcode":"N0R 1G0",
    "sg:province":"ON",
    "sg:tags":[
        "general",
        "contractor"
    ],
    "wof:name":"Bearing Construction",
    "wof:placetype":"venue"
},
  "geometry": {"coordinates":[-82.9232177734,42.0382156372],"type":"Point"}
}