{
  "type": "Feature",
  "properties": {
    "addr:full":"1767 Avenue Rd North York ON M5M 3Y8",
    "addr:housenumber":"1767",
    "addr:postcode":"m5m 3y8",
    "addr:street":"Avenue Rd",
    "iso:country":"CA",
    "sg:address":"1767 Avenue Rd",
    "sg:city":"North York",
    "sg:classifiers":[
        {
            "category":"Education",
            "subcategory":"School",
            "type":"Public Place"
        }
    ],
    "sg:phone":"+1 416 785 0962",
    "sg:postcode":"M5M 3Y8",
    "sg:province":"ON",
    "sg:tags":[
        "gemologists"
    ],
    "wof:name":"Canadian Gemmological Assn",
    "wof:placetype":"venue"
},
  "geometry": {"coordinates":[-79.4182815552,43.7293815613],"type":"Point"}
}