{
  "type": "Feature",
  "properties": {
    "addr:full":"1422 Main St Winnipeg MB R2W 3V4",
    "addr:housenumber":"1422",
    "addr:postcode":"r2w 3v4",
    "addr:street":"Main St",
    "iso:country":"CA",
    "sg:address":"1422 Main St",
    "sg:city":"Winnipeg",
    "sg:classifiers":[
        {
            "category":"Restaurant",
            "type":"Food & Drink"
        }
    ],
    "sg:phone":"+1 204 582 3874",
    "sg:postcode":"R2W 3V4",
    "sg:province":"MB",
    "wof:name":"Bo Bo Restaurant",
    "wof:placetype":"venue"
},
  "geometry": {"coordinates":[-97.12513,49.92606],"type":"Point"}
}