{
  "type": "Feature",
  "properties": {
    "iso:country":"CA",
    "sg:city":"Gatineau",
    "sg:classifiers":[
        {
            "category":"Retail",
            "subcategory":"Veterinary Services",
            "type":"Services"
        }
    ],
    "sg:phone":"+1 819 246 2428",
    "sg:postcode":"J8V 1A2",
    "sg:province":"QC",
    "sg:tags":[
        "veterinarian"
    ],
    "wof:name":"Prescott, Edith DVM",
    "wof:placetype":"venue"
},
  "geometry": {"coordinates":[-75.710487,45.427853],"type":"Point"}
}