{
  "type": "Feature",
  "properties": {
    "iso:country":"CA",
    "sg:address":"21463 Clarke Rd",
    "sg:city":"Arva",
    "sg:classifiers":[
        {
            "category":"Wholesale",
            "subcategory":"Scrap",
            "type":"Manufacturing & Wholesale Goods"
        }
    ],
    "sg:phone":"+1 519 457 1566",
    "sg:postcode":"N0M 1C0",
    "sg:province":"ON",
    "sg:tags":[
        "recycling",
        "center"
    ],
    "wof:name":"Try Recycling Inc",
    "wof:placetype":"venue"
},
  "geometry": {"coordinates":[-81.2952423096,43.0511703491],"type":"Point"}
}