{
  "type": "Feature",
  "properties": {
    "addr:full":"Richmond BC V6W 1H6",
    "addr:postcode":"v6w 1h6",
    "iso:country":"CA",
    "sg:city":"Richmond",
    "sg:classifiers":[
        {
            "category":"Freight",
            "type":"Transportation"
        }
    ],
    "sg:phone":"+1 604 451 1555",
    "sg:postcode":"V6W 1H6",
    "sg:province":"BC",
    "sg:tags":[
        "courier",
        "trucking"
    ],
    "wof:name":"K & H Dispatch Couriers",
    "wof:placetype":"venue"
},
  "geometry": {"coordinates":[-122.98955535899999,49.1686935425],"type":"Point"}
}