{
  "type": "Feature",
  "properties": {
    "addr:full":"675 Marine Dr West Vancouver BC V7T 1A4",
    "addr:housenumber":"675",
    "addr:postcode":"v7t 1a4",
    "addr:street":"Marine Dr",
    "iso:country":"CA",
    "sg:address":"675 Marine Dr",
    "sg:city":"West Vancouver",
    "sg:classifiers":[
        {
            "category":"Autos & Motor Vehicles",
            "subcategory":"Fuel & Gas Station",
            "type":"Retail Goods"
        }
    ],
    "sg:phone":"+1 604 921 3304",
    "sg:postcode":"V7T 1A4",
    "sg:province":"BC",
    "sg:tags":[
        "repairing",
        "automobile",
        "oil"
    ],
    "wof:name":"OK Tire Stores",
    "wof:placetype":"venue"
},
  "geometry": {"coordinates":[-123.133666992,49.3273696899],"type":"Point"}
}