{
  "type": "Feature",
  "properties": {
    "addr:full":"9831 107 St Westlock AB T7P 1R9",
    "addr:housenumber":"9831",
    "addr:postcode":"t7p 1r9",
    "addr:street":"107 St",
    "iso:country":"CA",
    "sg:address":"9831 107 St",
    "sg:city":"Westlock",
    "sg:classifiers":[
        {
            "category":"Professional",
            "subcategory":"Lawyer & Legal Services",
            "type":"Services"
        }
    ],
    "sg:phone":"+1 780 349 5366",
    "sg:postcode":"T7P 1R9",
    "sg:province":"AB",
    "sg:tags":[
        "attorney"
    ],
    "wof:name":"Mac Intyre, Michael",
    "wof:placetype":"venue"
},
  "geometry": {"coordinates":[-113.866432,54.153915],"type":"Point"}
}