{
  "type": "Feature",
  "properties": {
    "iso:country":"CA",
    "sg:city":"Surrey",
    "sg:classifiers":[
        {
            "category":"Banks & Credit Unions",
            "subcategory":"Financial Services",
            "type":"Services"
        }
    ],
    "sg:phone":"+1 604 581 2661",
    "sg:postcode":"V3R 8P7",
    "sg:province":"BC",
    "sg:tags":[
        "annuity",
        "insurance"
    ],
    "wof:name":"Metro Insurance Svc Ltd",
    "wof:placetype":"venue"
},
  "geometry": {"coordinates":[-122.80310821499999,49.1863288879],"type":"Point"}
}