{
  "type": "Feature",
  "properties": {
    "addr:full":"2093 Stanfield Rd Mississauga ON L4Y 1R4",
    "addr:housenumber":"2093",
    "addr:postcode":"l4y 1r4",
    "addr:street":"Stanfield Rd",
    "iso:country":"CA",
    "sg:address":"2093 Stanfield Rd",
    "sg:city":"Mississauga",
    "sg:classifiers":[
        {
            "category":"Freight",
            "type":"Transportation"
        }
    ],
    "sg:phone":"+1 905 276 8750",
    "sg:postcode":"L4Y 1R4",
    "sg:province":"ON",
    "sg:tags":[
        "trucking"
    ],
    "wof:name":"Forever Trucking Inc",
    "wof:placetype":"venue"
},
  "geometry": {"coordinates":[-79.5766448975,43.5939979553],"type":"Point"}
}