{
  "type": "Feature",
  "properties": {
    "iso:country":"CA",
    "sg:address":"PO Box 63 STN Main",
    "sg:city":"Okotoks",
    "sg:classifiers":[
        {
            "category":"Recreation",
            "type":"Entertainment"
        }
    ],
    "sg:phone":"+1 403 995 0649",
    "sg:postcode":"T1S 1A4",
    "sg:province":"AB",
    "sg:tags":[
        "center"
    ],
    "wof:name":"Airborne Tumbling & Trampoline",
    "wof:placetype":"venue"
},
  "geometry": {"coordinates":[-113.974937439,50.7258911133],"type":"Point"}
}