{
  "type": "Feature",
  "properties": {
    "iso:country":"CA",
    "sg:address":"1879 Notre Dame Ave",
    "sg:city":"Winnipeg",
    "sg:classifiers":[
        {
            "category":"Building & Trades",
            "subcategory":"Construction",
            "type":"Services"
        }
    ],
    "sg:phone":"+1 204 633 2425",
    "sg:postcode":"R3H 0J3",
    "sg:province":"MB",
    "sg:tags":[
        "home",
        "builder"
    ],
    "wof:name":"Central Homes",
    "wof:placetype":"venue"
},
  "geometry": {"coordinates":[-97.199928,49.916637],"type":"Point"}
}