{
  "type": "Feature",
  "properties": {
    "addr:full":"356 Simcoe St S Oshawa ON L1H 4J3",
    "addr:housenumber":"356",
    "addr:postcode":"l1h 4j3",
    "addr:street":"Simcoe St S",
    "iso:country":"CA",
    "sg:address":"356 Simcoe St S",
    "sg:city":"Oshawa",
    "sg:classifiers":[
        {
            "category":"Health Services",
            "subcategory":"Chiropractor",
            "type":"Services"
        }
    ],
    "sg:phone":"+1 905 725 4331",
    "sg:postcode":"L1H 4J3",
    "sg:province":"ON",
    "wof:name":"Oshawa South Chiropractic",
    "wof:placetype":"venue"
},
  "geometry": {"coordinates":[-78.8594284058,43.8881874084],"type":"Point"}
}