{
  "type": "Feature",
  "properties": {
    "addr:full":"57 Queen St Stephenville NL A2N 2M4",
    "addr:housenumber":"57",
    "addr:postcode":"a2n 2m4",
    "addr:street":"Queen St",
    "iso:country":"CA",
    "sg:address":"57 Queen St",
    "sg:city":"Stephenville",
    "sg:classifiers":[
        {
            "category":"Shopping",
            "type":"Retail Goods"
        }
    ],
    "sg:phone":"+1 709 643 3453",
    "sg:postcode":"A2N 2M4",
    "sg:province":"NL",
    "sg:tags":[
        "limb",
        "orthopedic",
        "appliance",
        "artificial"
    ],
    "wof:name":"Durnford Prosthetic & Orthotic",
    "wof:placetype":"venue"
},
  "geometry": {"coordinates":[-58.575314,48.546692],"type":"Point"}
}