{
  "type": "Feature",
  "properties": {
    "addr:full":"1493 Rue Roberval Saint-Bruno QC J3V 3P8",
    "addr:housenumber":"1493",
    "addr:postcode":"j3v 3p8",
    "addr:street":"Rue Roberval",
    "iso:country":"CA",
    "sg:address":"1493 Rue Roberval",
    "sg:city":"Saint-Bruno",
    "sg:classifiers":[
        {
            "category":"Retail",
            "subcategory":"Portrait Studio",
            "type":"Services"
        }
    ],
    "sg:phone":"+1 450 653 3121",
    "sg:postcode":"J3V 3P8",
    "sg:province":"QC",
    "sg:tags":[
        "photo",
        "finishing"
    ],
    "wof:name":"Ppm Photos",
    "wof:placetype":"venue"
},
  "geometry": {"coordinates":[-71.67552185060001,48.4717712402],"type":"Point"}
}