{
  "type": "Feature",
  "properties": {
    "iso:country":"CA",
    "sg:city":"Woodbridge",
    "sg:classifiers":[
        {
            "category":"Wholesale",
            "subcategory":"Home Furnishings",
            "type":"Manufacturing & Wholesale Goods"
        }
    ],
    "sg:phone":"+1 905 851 1274",
    "sg:postcode":"L4L 5Y5",
    "sg:province":"ON",
    "sg:tags":[
        "linen"
    ],
    "wof:name":"Mera International Ltd",
    "wof:placetype":"venue"
},
  "geometry": {"coordinates":[-79.565369,43.781445],"type":"Point"}
}