{
  "type": "Feature",
  "properties": {
    "addr:full":"Richmond Hill ON L4B 1M8",
    "addr:postcode":"l4b 1m8",
    "iso:country":"CA",
    "sg:city":"Richmond Hill",
    "sg:classifiers":[
        {
            "category":"Arts & Performance",
            "subcategory":"Theater",
            "type":"Entertainment"
        }
    ],
    "sg:phone":"+1 905 886 4000",
    "sg:postcode":"L4B 1M8",
    "sg:province":"ON",
    "sg:tags":[
        "live",
        "music"
    ],
    "wof:name":"Mandell Entertainment Grp Ltd",
    "wof:placetype":"venue"
},
  "geometry": {"coordinates":[-79.3889389038,43.8560523987],"type":"Point"}
}