{
  "type": "Feature",
  "properties": {
    "addr:full":"1657 Drouillard Rd Windsor ON N8Y 2S4",
    "addr:housenumber":"1657",
    "addr:postcode":"n8y 2s4",
    "addr:street":"Drouillard Rd",
    "iso:country":"CA",
    "sg:address":"1657 Drouillard Rd",
    "sg:city":"Windsor",
    "sg:classifiers":[
        {
            "category":"Building & Trades",
            "subcategory":"Plumbing",
            "type":"Services"
        }
    ],
    "sg:phone":"+1 519 948 2265",
    "sg:postcode":"N8Y 2S4",
    "sg:province":"ON",
    "sg:tags":[
        "contractor"
    ],
    "wof:name":"Faucet Shoppe",
    "wof:placetype":"venue"
},
  "geometry": {"coordinates":[-82.992195,42.308762],"type":"Point"}
}