{
  "type": "Feature",
  "properties": {
    "addr:full":"4584 Rte Marie-Victorin Contrecoeur QC J0L 1C0",
    "addr:housenumber":"4584",
    "addr:postcode":"j0l 1c0",
    "addr:street":"Rte Marie-Victorin",
    "iso:country":"CA",
    "sg:address":"4584 Rte Marie-Victorin",
    "sg:city":"Contrecoeur",
    "sg:classifiers":[
        {
            "category":"Restaurant",
            "type":"Food & Drink"
        }
    ],
    "sg:phone":"+1 450 587 2244",
    "sg:postcode":"J0L 1C0",
    "sg:province":"QC",
    "wof:name":"Restaurant Chez Gaby",
    "wof:placetype":"venue"
},
  "geometry": {"coordinates":[-73.24374389650001,45.8532905579],"type":"Point"}
}