{
  "type": "Feature",
  "properties": {
    "iso:country":"CA",
    "sg:address":"314 Duchess St",
    "sg:city":"Saskatoon",
    "sg:classifiers":[
        {
            "category":"Organizations",
            "subcategory":"Labor Organization",
            "type":"Services"
        }
    ],
    "sg:phone":"+1 306 652 1011",
    "sg:postcode":"S7K 0R1",
    "sg:province":"SK",
    "wof:name":"Service Employees Intl Union",
    "wof:placetype":"venue"
},
  "geometry": {"coordinates":[-106.657905579,52.1426620483],"type":"Point"}
}