{
  "type": "Feature",
  "properties": {
    "addr:full":"12 Upjohn Rd North York ON M3B 2V9",
    "addr:housenumber":"12",
    "addr:postcode":"m3b 2v9",
    "addr:street":"Upjohn Rd",
    "iso:country":"CA",
    "sg:address":"12 Upjohn Rd",
    "sg:city":"North York",
    "sg:classifiers":[
        {
            "category":"Shopping",
            "subcategory":"Computers & Home Electronics",
            "type":"Retail Goods"
        }
    ],
    "sg:phone":"+1 416 789 7100",
    "sg:postcode":"M3B 2V9",
    "sg:province":"ON",
    "sg:tags":[
        "equipment",
        "dealer",
        "software"
    ],
    "wof:name":"Steinberg Canada",
    "wof:placetype":"venue"
},
  "geometry": {"coordinates":[-79.35060900000001,43.753864],"type":"Point"}
}