{
  "type": "Feature",
  "properties": {
    "iso:country":"CA",
    "sg:address":"5115 17 Ave SE",
    "sg:city":"Calgary",
    "sg:classifiers":[
        {
            "category":"Shopping",
            "subcategory":"Pharmacy",
            "type":"Retail Goods"
        }
    ],
    "sg:phone":"+1 403 272 6977",
    "sg:postcode":"T2A 0V8",
    "sg:province":"AB",
    "wof:name":"Zellers Pharmacy",
    "wof:placetype":"venue"
},
  "geometry": {"coordinates":[-113.961013794,51.0377235413],"type":"Point"}
}