{
  "type": "Feature",
  "properties": {
    "addr:full":"6751 Graybar Rd # 140 Richmond BC V6W 1H3",
    "addr:housenumber":"6751;140",
    "addr:postcode":"v6w 1h3",
    "addr:street":"Graybar Rd #",
    "iso:country":"CA",
    "sg:address":"6751 Graybar Rd # 140",
    "sg:city":"Richmond",
    "sg:classifiers":[
        {
            "category":"Building & Trades",
            "subcategory":"Construction",
            "type":"Services"
        }
    ],
    "sg:phone":"+1 604 244 1986",
    "sg:postcode":"V6W 1H3",
    "sg:province":"BC",
    "sg:tags":[
        "contractor"
    ],
    "wof:name":"Wje Consultants Ltd",
    "wof:placetype":"venue"
},
  "geometry": {"coordinates":[-122.989952,49.165154],"type":"Point"}
}