{
  "type": "Feature",
  "properties": {
    "addr:full":"296 Patricia Ave Kitchener ON N2M 1K1",
    "addr:housenumber":"296",
    "addr:postcode":"n2m 1k1",
    "addr:street":"Patricia Ave",
    "iso:country":"CA",
    "sg:address":"296 Patricia Ave",
    "sg:city":"Kitchener",
    "sg:classifiers":[
        {
            "category":"Building & Trades",
            "subcategory":"Construction",
            "type":"Services"
        }
    ],
    "sg:phone":"+1 519 570 3509",
    "sg:postcode":"N2M 1K1",
    "sg:province":"ON",
    "sg:tags":[
        "designer",
        "dealer",
        "pool",
        "swimming"
    ],
    "wof:name":"Gdo Construction",
    "wof:placetype":"venue"
},
  "geometry": {"coordinates":[-80.5090713501,43.4445571899],"type":"Point"}
}