{
  "type": "Feature",
  "properties": {
    "iso:country":"CA",
    "sg:city":"North Rustico",
    "sg:classifiers":[
        {
            "category":"Food & Beverages",
            "subcategory":"Meat & Fish",
            "type":"Retail Goods"
        }
    ],
    "sg:phone":"+1 902 963 2442",
    "sg:postcode":"C0A 1X0",
    "sg:province":"PE",
    "sg:tags":[
        "seafood"
    ],
    "wof:name":"Doiron Fisheries",
    "wof:placetype":"venue"
},
  "geometry": {"coordinates":[-63.313205719,46.4581413269],"type":"Point"}
}