{
  "type": "Feature",
  "properties": {
    "addr:full":"405 Ch DE LA Grande-Cote Boisbriand QC J7G 1A9",
    "addr:housenumber":"405",
    "addr:postcode":"j7g 1a9",
    "addr:street":"Ch De La Grande-Cote",
    "iso:country":"CA",
    "sg:address":"405 Ch DE LA Grande-Cote",
    "sg:city":"Boisbriand",
    "sg:classifiers":[
        {
            "category":"Insurance",
            "subcategory":"Insurance Agent",
            "type":"Services"
        }
    ],
    "sg:phone":"+1 450 973 8222",
    "sg:postcode":"J7G 1A9",
    "sg:province":"QC",
    "wof:name":"Varennes, Bernard",
    "wof:placetype":"venue"
},
  "geometry": {"coordinates":[-73.835007,45.605904],"type":"Point"}
}