{
  "type": "Feature",
  "properties": {
    "iso:country":"CA",
    "sg:address":"769 St Clair Ave W",
    "sg:city":"Toronto",
    "sg:classifiers":[
        {
            "category":"Restaurant",
            "type":"Food & Drink"
        }
    ],
    "sg:phone":"+1 416 654 9119",
    "sg:postcode":"M6C 1B4",
    "sg:province":"ON",
    "sg:tags":[
        "cafe"
    ],
    "wof:name":"Ferro",
    "wof:placetype":"venue"
},
  "geometry": {"coordinates":[-79.42854309080001,43.6809959412],"type":"Point"}
}