{
  "type": "Feature",
  "properties": {
    "addr:full":"4537 1E Av Charlesbourg QC G1H 2S8",
    "addr:housenumber":"4537",
    "addr:postcode":"g1h 2s8",
    "addr:street":"1E Av",
    "iso:country":"CA",
    "sg:address":"4537 1E Av",
    "sg:city":"Charlesbourg",
    "sg:classifiers":[
        {
            "category":"Building & Trades",
            "subcategory":"Plumbing",
            "type":"Services"
        }
    ],
    "sg:phone":"+1 418 626 9260",
    "sg:postcode":"G1H 2S8",
    "sg:province":"QC",
    "sg:tags":[
        "ventilating",
        "establishment",
        "heating",
        "contractor"
    ],
    "wof:name":"Ventilation Alphonse Landry",
    "wof:placetype":"venue"
},
  "geometry": {"coordinates":[-71.2511978149,46.8442344666],"type":"Point"}
}