{
  "type": "Feature",
  "properties": {
    "iso:country":"CA",
    "sg:address":"335 Wharncliffe Rd N",
    "sg:city":"London",
    "sg:classifiers":[
        {
            "category":"Health Services",
            "subcategory":"Chiropractor",
            "type":"Services"
        }
    ],
    "sg:phone":"+1 519 438 5544",
    "sg:postcode":"N6G 1E4",
    "sg:province":"ON",
    "wof:name":"Tymoshenko, Walter DC",
    "wof:placetype":"venue"
},
  "geometry": {"coordinates":[-81.266472,42.995213],"type":"Point"}
}