{
  "type": "Feature",
  "properties": {
    "addr:full":"335 Wharncliffe Rd N London ON N6G 1E4",
    "addr:housenumber":"335",
    "addr:postcode":"n6g 1e4",
    "addr:street":"Wharncliffe Rd N",
    "iso:country":"CA",
    "sg:address":"335 Wharncliffe Rd N",
    "sg:city":"London",
    "sg:classifiers":[
        {
            "category":"Health Services",
            "subcategory":"Chiropractor",
            "type":"Services"
        }
    ],
    "sg:phone":"+1 519 438 5544",
    "sg:postcode":"N6G 1E4",
    "sg:province":"ON",
    "wof:name":"Tymoshenko, Walter DC",
    "wof:placetype":"venue"
},
  "geometry": {"coordinates":[-81.26647199999999,42.995213],"type":"Point"}
}