{
  "type": "Feature",
  "properties": {
    "addr:full":"4910 Hwy 1 Salmon River NS B0W 2Y0",
    "addr:housenumber":"4910",
    "addr:postcode":"b0w 2y0",
    "addr:street":"Hwy 1",
    "iso:country":"CA",
    "sg:address":"4910 Hwy 1",
    "sg:city":"Salmon River",
    "sg:classifiers":[
        {
            "category":"Food & Beverages",
            "subcategory":"Groceries & Convenience Stores",
            "type":"Retail Goods"
        }
    ],
    "sg:phone":"+1 902 649 2176",
    "sg:postcode":"B0W 2Y0",
    "sg:province":"NS",
    "wof:name":"D J Corner Store & Cafe",
    "wof:placetype":"venue"
},
  "geometry": {"coordinates":[-66.1632843018,44.0592079163],"type":"Point"}
}