{
  "type": "Feature",
  "properties": {
    "iso:country":"CA",
    "sg:address":"1137 Topsail Rd",
    "sg:city":"Mount Pearl",
    "sg:classifiers":[
        {
            "category":"Autos & Motor Vehicles",
            "subcategory":"Motorcycle Sales",
            "type":"Retail Goods"
        }
    ],
    "sg:phone":"+1 709 364 2325",
    "sg:postcode":"A1N 5G2",
    "sg:province":"NL",
    "sg:tags":[
        "recreational"
    ],
    "wof:name":"Honda One",
    "wof:placetype":"venue"
},
  "geometry": {"coordinates":[-52.8225669861,47.5273284912],"type":"Point"}
}