{
  "type": "Feature",
  "properties": {
    "addr:full":"SE 25 5 5E Grunthal MB R0A 0R0",
    "addr:housenumber":"25 5",
    "addr:postcode":"r0a 0r0",
    "addr:street":"Se",
    "iso:country":"CA",
    "sg:address":"SE 25 5 5E",
    "sg:city":"Grunthal",
    "sg:classifiers":[
        {
            "category":"Farming",
            "subcategory":"Farm",
            "type":"Manufacturing & Wholesale Goods"
        }
    ],
    "sg:phone":"+1 204 434 9107",
    "sg:postcode":"R0A 0R0",
    "sg:province":"MB",
    "wof:name":"Shelly's Hog Farm",
    "wof:placetype":"venue"
},
  "geometry": {"coordinates":[-96.851303,49.406689],"type":"Point"}
}