{
  "type": "Feature",
  "properties": {
    "addr:full":"Midland ON L4R 4L1",
    "addr:postcode":"l4r 4l1",
    "iso:country":"CA",
    "sg:city":"Midland",
    "sg:classifiers":[
        {
            "category":"Autos & Motor Vehicles",
            "subcategory":"Boat Sales",
            "type":"Retail Goods"
        }
    ],
    "sg:phone":"+1 705 526 4088",
    "sg:postcode":"L4R 4L1",
    "sg:province":"ON",
    "sg:tags":[
        "equipment",
        "supply"
    ],
    "wof:name":"Marine Supply Centre of Midlnd",
    "wof:placetype":"venue"
},
  "geometry": {"coordinates":[-79.869896,44.731575],"type":"Point"}
}