{
  "type": "Feature",
  "properties": {
    "iso:country":"CA",
    "sg:city":"Montreal",
    "sg:classifiers":[
        {
            "category":"Food & Beverages",
            "subcategory":"Groceries & Convenience Stores",
            "type":"Retail Goods"
        }
    ],
    "sg:phone":"+1 514 933 4370",
    "sg:postcode":"H3K 2V6",
    "sg:province":"QC",
    "wof:name":"Restaurant Jean-Guy",
    "wof:placetype":"venue"
},
  "geometry": {"coordinates":[-73.56517,45.480167],"type":"Point"}
}