{
  "type": "Feature",
  "properties": {
    "addr:full":"Saint-Donat-DE-Montcalm QC J0T 2C0",
    "addr:postcode":"j0t 2c0",
    "addr:street":"Saint-Donat-De-Montcalm",
    "iso:country":"CA",
    "sg:city":"Saint-Donat-DE-Montcalm",
    "sg:classifiers":[
        {
            "category":"Travel",
            "subcategory":"Hotels & Motels",
            "type":"Entertainment"
        }
    ],
    "sg:phone":"+1 819 424 2252",
    "sg:postcode":"J0T 2C0",
    "sg:province":"QC",
    "wof:name":"Auberge LA Cuillere A Pot",
    "wof:placetype":"venue"
},
  "geometry": {"coordinates":[-74.54745483400001,45.9447593689],"type":"Point"}
}