{
  "type": "Feature",
  "properties": {
    "addr:full":"45 Paget St N New Liskeard ON P0J 1P0",
    "addr:housenumber":"45",
    "addr:postcode":"p0j 1p0",
    "addr:street":"Paget St N New",
    "iso:country":"CA",
    "sg:address":"45 Paget St N",
    "sg:city":"New Liskeard",
    "sg:classifiers":[
        {
            "category":"Wholesale",
            "subcategory":"Office Equipment",
            "type":"Manufacturing & Wholesale Goods"
        }
    ],
    "sg:phone":"+1 705 647 3798",
    "sg:postcode":"P0J 1P0",
    "sg:province":"ON",
    "sg:tags":[
        "return",
        "tax",
        "system",
        "preparation",
        "accounting",
        "bookkeeping",
        "filing"
    ],
    "wof:name":"Mar's Accounting & Bookkeeping",
    "wof:placetype":"venue"
},
  "geometry": {"coordinates":[-79.67417907710001,47.5096282959],"type":"Point"}
}