{
  "type": "Feature",
  "properties": {
    "addr:full":"1003 33rd Ave W Vancouver BC V6M 1A1",
    "addr:housenumber":"1003",
    "addr:postcode":"v6m 1a1",
    "addr:street":"33Rd Ave W",
    "iso:country":"CA",
    "sg:address":"1003 33rd Ave W",
    "sg:city":"Vancouver",
    "sg:classifiers":[
        {
            "category":"Wholesale",
            "subcategory":"Vending Machines",
            "type":"Manufacturing & Wholesale Goods"
        }
    ],
    "sg:phone":"+1 604 734 4860",
    "sg:postcode":"V6M 1A1",
    "sg:province":"BC",
    "wof:name":"Kwik Kafe Ltd",
    "wof:placetype":"venue"
},
  "geometry": {"coordinates":[-123.12805938699999,49.2416305542],"type":"Point"}
}