{
  "type": "Feature",
  "properties": {
    "addr:full":"10188 Rue Berri Montreal QC H3L 2G6",
    "addr:housenumber":"10188",
    "addr:postcode":"h3l 2g6",
    "addr:street":"Rue Berri",
    "iso:country":"CA",
    "sg:address":"10188 Rue Berri",
    "sg:city":"Montreal",
    "sg:classifiers":[
        {
            "category":"Real Estate",
            "subcategory":"Real Estate Agent",
            "type":"Services"
        }
    ],
    "sg:phone":"+1 514 384 6024",
    "sg:postcode":"H3L 2G6",
    "sg:province":"QC",
    "wof:name":"Groupe Besner Inc",
    "wof:placetype":"venue"
},
  "geometry": {"coordinates":[-73.660751,45.552063],"type":"Point"}
}