{
  "type": "Feature",
  "properties": {
    "addr:full":"8509 Wagner Rd NW Edmonton AB T6E 5A7",
    "addr:housenumber":"8509",
    "addr:postcode":"t6e 5a7",
    "addr:street":"Wagner Rd Nw",
    "iso:country":"CA",
    "sg:address":"8509 Wagner Rd NW",
    "sg:city":"Edmonton",
    "sg:classifiers":[
        {
            "category":"Banks & Credit Unions",
            "subcategory":"Bank",
            "type":"Services"
        }
    ],
    "sg:phone":"+1 780 448 7880",
    "sg:postcode":"T6E 5A7",
    "sg:province":"AB",
    "wof:name":"Scotiabank",
    "wof:placetype":"venue"
},
  "geometry": {"coordinates":[-113.45417022700001,53.4969902039],"type":"Point"}
}