{
  "type": "Feature",
  "properties": {
    "addr:full":"7060 Kerr St Vancouver BC V5S 4W2",
    "addr:housenumber":"7060",
    "addr:postcode":"v5s 4w2",
    "addr:street":"Kerr St",
    "iso:country":"CA",
    "sg:address":"7060 Kerr St",
    "sg:city":"Vancouver",
    "sg:classifiers":[
        {
            "category":"Food & Beverages",
            "subcategory":"Fruits & Vegetables",
            "type":"Retail Goods"
        }
    ],
    "sg:phone":"+1 604 451 1329",
    "sg:postcode":"V5S 4W2",
    "sg:province":"BC",
    "sg:tags":[
        "produce"
    ],
    "wof:name":"Kin's Farm Market",
    "wof:placetype":"venue"
},
  "geometry": {"coordinates":[-123.041138,49.219627],"type":"Point"}
}