{
  "type": "Feature",
  "properties": {
    "addr:full":"5134 Cordova Bay Rd Victoria BC V8Y 2K5",
    "addr:housenumber":"5134",
    "addr:postcode":"v8y 2k5",
    "addr:street":"Cordova Bay Rd",
    "iso:country":"CA",
    "sg:address":"5134 Cordova Bay Rd",
    "sg:city":"Victoria",
    "sg:classifiers":[
        {
            "category":"Shopping",
            "subcategory":"Discount & Variety Stores",
            "type":"Retail Goods"
        }
    ],
    "sg:phone":"+1 250 658 5199",
    "sg:postcode":"V8Y 2K5",
    "sg:province":"BC",
    "sg:tags":[
        "post"
    ],
    "wof:name":"Cordova Bay Variety Store",
    "wof:placetype":"venue"
},
  "geometry": {"coordinates":[-123.364517212,48.428314209],"type":"Point"}
}