{
  "type": "Feature",
  "properties": {
    "iso:country":"CA",
    "sg:address":"28 Applewood Lane",
    "sg:city":"London",
    "sg:classifiers":[
        {
            "category":"Building & Trades",
            "subcategory":"Pest Control",
            "type":"Services"
        }
    ],
    "sg:phone":"+1 519 661 6832",
    "sg:postcode":"N6J 3P8",
    "sg:province":"ON",
    "wof:name":"AAA Pest Protection Svc",
    "wof:placetype":"venue"
},
  "geometry": {"coordinates":[-81.28834533689999,42.9588050842],"type":"Point"}
}