{
  "type": "Feature",
  "properties": {
    "addr:full":"Winnipeg MB R2K 2T8",
    "addr:postcode":"r2k 2t8",
    "iso:country":"CA",
    "sg:city":"Winnipeg",
    "sg:classifiers":[
        {
            "category":"Building & Trades",
            "subcategory":"Electrical",
            "type":"Services"
        }
    ],
    "sg:phone":"+1 204 661 3476",
    "sg:postcode":"R2K 2T8",
    "sg:province":"MB",
    "sg:tags":[
        "electric",
        "contractor"
    ],
    "wof:name":"Standard Electric Contractors",
    "wof:placetype":"venue"
},
  "geometry": {"coordinates":[-97.09487900000001,49.917805],"type":"Point"}
}