{
  "type": "Feature",
  "properties": {
    "iso:country":"CA",
    "sg:address":"196 King St E",
    "sg:city":"Bowmanville",
    "sg:classifiers":[
        {
            "category":"Cinema",
            "subcategory":"Movie Rental",
            "type":"Entertainment"
        }
    ],
    "sg:phone":"+1 905 623 9181",
    "sg:postcode":"L1C 1P1",
    "sg:province":"ON",
    "sg:tags":[
        "leasing",
        "video",
        "disc",
        "tape"
    ],
    "wof:name":"Blockbuster Video",
    "wof:placetype":"venue"
},
  "geometry": {"coordinates":[-78.67933654789999,43.9108734131],"type":"Point"}
}