{
  "type": "Feature",
  "properties": {
    "addr:full":"13884 Rue Denis Mirabel QC J7J 1C1",
    "addr:housenumber":"13884",
    "addr:postcode":"j7j 1c1",
    "addr:street":"Rue Denis",
    "iso:country":"CA",
    "sg:address":"13884 Rue Denis",
    "sg:city":"Mirabel",
    "sg:classifiers":[
        {
            "category":"Building & Trades",
            "subcategory":"Construction",
            "type":"Services"
        }
    ],
    "sg:phone":"+1 450 430 1285",
    "sg:postcode":"J7J 1C1",
    "sg:province":"QC",
    "sg:tags":[
        "resurfacing",
        "laying",
        "refinishing",
        "floor"
    ],
    "wof:name":"Planchers Jean Yves Ouellet",
    "wof:placetype":"venue"
},
  "geometry": {"coordinates":[-73.914902,45.706135],"type":"Point"}
}