{
  "type": "Feature",
  "properties": {
    "iso:country":"CA",
    "sg:address":"7009 Ch DE LA Cote-Saint-Luc",
    "sg:city":"Cote Saint-Luc",
    "sg:classifiers":[
        {
            "category":"Cinema",
            "subcategory":"Movie Rental",
            "type":"Entertainment"
        }
    ],
    "sg:phone":"+1 514 482 8227",
    "sg:postcode":"H4V 1J2",
    "sg:province":"QC",
    "sg:tags":[
        "leasing",
        "video",
        "disc",
        "tape"
    ],
    "wof:name":"Blockbuster Video",
    "wof:placetype":"venue"
},
  "geometry": {"coordinates":[-73.653625,45.465954],"type":"Point"}
}