{
  "type": "Feature",
  "properties": {
    "addr:full":"10427 100 Ave Westlock AB T7P 2J2",
    "addr:housenumber":"10427",
    "addr:postcode":"t7p 2j2",
    "addr:street":"100 Ave",
    "iso:country":"CA",
    "sg:address":"10427 100 Ave",
    "sg:city":"Westlock",
    "sg:classifiers":[
        {
            "category":"Banks & Credit Unions",
            "subcategory":"Bank",
            "type":"Services"
        }
    ],
    "sg:phone":"+1 780 349 3378",
    "sg:postcode":"T7P 2J2",
    "sg:province":"AB",
    "wof:name":"Royal Bank Financial Group",
    "wof:placetype":"venue"
},
  "geometry": {"coordinates":[-113.85962677000001,54.1536941528],"type":"Point"}
}