{
  "type": "Feature",
  "properties": {
    "iso:country":"CA",
    "sg:address":"7270 Woodbine Ave",
    "sg:city":"Markham",
    "sg:classifiers":[
        {
            "category":"Building & Trades",
            "subcategory":"Construction",
            "type":"Services"
        }
    ],
    "sg:phone":"+1 905 513 9700",
    "sg:postcode":"L3R 4B9",
    "sg:province":"ON",
    "sg:tags":[
        "general",
        "contractor"
    ],
    "wof:name":"Milne & Nicholls Ltd",
    "wof:placetype":"venue"
},
  "geometry": {"coordinates":[-79.350578,43.820572],"type":"Point"}
}