{
  "type": "Feature",
  "properties": {
    "addr:full":"5458 N Access Rd Chetwynd BC V0C 1J0",
    "addr:housenumber":"5458",
    "addr:postcode":"bc v0c 1j0",
    "addr:street":"N Access Rd",
    "iso:country":"CA",
    "sg:address":"5458 N Access Rd",
    "sg:city":"Chetwynd",
    "sg:classifiers":[
        {
            "category":"Social Services",
            "type":"Services"
        }
    ],
    "sg:phone":"+1 250 788 4889",
    "sg:postcode":"V0C 1J0",
    "sg:province":"BC",
    "sg:tags":[
        "organization",
        "welfare"
    ],
    "wof:name":"Chetwynd Society For Community",
    "wof:placetype":"venue"
},
  "geometry": {"coordinates":[-121.639847,55.695065],"type":"Point"}
}