{
  "type": "Feature",
  "properties": {
    "addr:full":"200 Glendale Ave N Hamilton ON L8L 7K3",
    "addr:housenumber":"200",
    "addr:postcode":"l8l 7k3",
    "addr:street":"Glendale Ave N",
    "iso:country":"CA",
    "sg:address":"200 Glendale Ave N",
    "sg:city":"Hamilton",
    "sg:classifiers":[
        {
            "category":"Manufacturing",
            "subcategory":"Textiles",
            "type":"Manufacturing & Wholesale Goods"
        }
    ],
    "sg:phone":"+1 905 544 3394",
    "sg:postcode":"L8L 7K3",
    "sg:province":"ON",
    "sg:tags":[
        "mills",
        "yarn"
    ],
    "wof:name":"Glendale Yarns Inc",
    "wof:placetype":"venue"
},
  "geometry": {"coordinates":[-79.8236160278,43.251033783],"type":"Point"}
}