{
  "type": "Feature",
  "properties": {
    "iso:country":"CA",
    "sg:city":"Central Butte",
    "sg:classifiers":[
        {
            "category":"Health Services",
            "subcategory":"Hospital",
            "type":"Services"
        }
    ],
    "sg:phone":"+1 306 796 2190",
    "sg:postcode":"S0H 0T0",
    "sg:province":"SK",
    "wof:name":"Central Butte Hospital",
    "wof:placetype":"venue"
},
  "geometry": {"coordinates":[-106.51249694800001,50.7961540222],"type":"Point"}
}