{
  "type": "Feature",
  "properties": {
    "iso:country":"CA",
    "sg:address":"12 International Dr",
    "sg:city":"Pembroke",
    "sg:classifiers":[
        {
            "category":"Professional",
            "subcategory":"Engineering",
            "type":"Services"
        }
    ],
    "sg:phone":"+1 613 735 2507",
    "sg:postcode":"K8A 6W5",
    "sg:province":"ON",
    "sg:tags":[
        "engineer"
    ],
    "wof:name":"Jp2G Consultants Inc",
    "wof:placetype":"venue"
},
  "geometry": {"coordinates":[-77.1175079346,45.8006401062],"type":"Point"}
}