{
  "type": "Feature",
  "properties": {
    "addr:full":"Tidnish Bridge Amherst NS B4H 3X9",
    "addr:postcode":"b4h 3x9",
    "iso:country":"CA",
    "sg:address":"Tidnish Bridge",
    "sg:city":"Amherst",
    "sg:classifiers":[
        {
            "category":"Travel",
            "subcategory":"Travel Agent",
            "type":"Entertainment"
        }
    ],
    "sg:phone":"+1 902 661 2703",
    "sg:postcode":"B4H 3X9",
    "sg:province":"NS",
    "sg:tags":[
        "information",
        "tourist"
    ],
    "wof:name":"Tidnish Tourist Bureau",
    "wof:placetype":"venue"
},
  "geometry": {"coordinates":[-64.20993,45.832039],"type":"Point"}
}