{
  "type": "Feature",
  "properties": {
    "addr:full":"2011 Daimler Dr Kelowna BC V1Z 3H6",
    "addr:housenumber":"2011",
    "addr:postcode":"v1z 3h6",
    "addr:street":"Daimler Dr",
    "iso:country":"CA",
    "sg:address":"2011 Daimler Dr",
    "sg:city":"Kelowna",
    "sg:classifiers":[
        {
            "category":"Organizations",
            "subcategory":"Religious Organization",
            "type":"Services"
        }
    ],
    "sg:phone":"+1 250 769 5481",
    "sg:postcode":"V1Z 3H6",
    "sg:province":"BC",
    "sg:tags":[
        "church"
    ],
    "wof:name":"Alliance Westside Church",
    "wof:placetype":"venue"
},
  "geometry": {"coordinates":[-119.5979,49.857117],"type":"Point"}
}