{
  "type": "Feature",
  "properties": {
    "addr:full":"442 Upper Horning Rd Hamilton ON L9C 7P6",
    "addr:housenumber":"442",
    "addr:postcode":"l9c 7p6",
    "addr:street":"Upper Horning Rd",
    "iso:country":"CA",
    "sg:address":"442 Upper Horning Rd",
    "sg:city":"Hamilton",
    "sg:classifiers":[
        {
            "category":"Building & Trades",
            "subcategory":"Construction",
            "type":"Services"
        }
    ],
    "sg:phone":"+1 905 525 4513",
    "sg:postcode":"L9C 7P6",
    "sg:province":"ON",
    "sg:tags":[
        "roofing",
        "contractor"
    ],
    "wof:name":"Jrp Roofing",
    "wof:placetype":"venue"
},
  "geometry": {"coordinates":[-79.92858886720001,43.2304382324],"type":"Point"}
}