{
  "type": "Feature",
  "properties": {
    "addr:full":"1125 Pembroke St Victoria BC V8T 1J3",
    "addr:housenumber":"1125",
    "addr:postcode":"v8t 1j3",
    "addr:street":"Pembroke St",
    "iso:country":"CA",
    "sg:address":"1125 Pembroke St",
    "sg:city":"Victoria",
    "sg:classifiers":[
        {
            "category":"Government",
            "subcategory":"Office",
            "type":"Public Place"
        }
    ],
    "sg:phone":"+1 250 387 1938",
    "sg:postcode":"V8T 1J3",
    "sg:province":"BC",
    "wof:name":"BC Youth Custody",
    "wof:placetype":"venue"
},
  "geometry": {"coordinates":[-123.351685,48.431728],"type":"Point"}
}