{
  "type": "Feature",
  "properties": {
    "addr:full":"353 Iroquois Shore Rd Oakville ON L6H 1M3",
    "addr:housenumber":"353",
    "addr:postcode":"l6h 1m3",
    "addr:street":"Iroquois Shore Rd",
    "iso:country":"CA",
    "sg:address":"353 Iroquois Shore Rd",
    "sg:city":"Oakville",
    "sg:classifiers":[
        {
            "category":"Manufacturing",
            "subcategory":"Electronics",
            "type":"Manufacturing & Wholesale Goods"
        }
    ],
    "sg:phone":"+1 905 844 2870",
    "sg:postcode":"L6H 1M3",
    "sg:province":"ON",
    "sg:tags":[
        "equipment",
        "recreational",
        "electronic",
        "vehicle"
    ],
    "wof:name":"Glendale International Corp",
    "wof:placetype":"venue"
},
  "geometry": {"coordinates":[-79.68590500000001,43.465195],"type":"Point"}
}