{
  "type": "Feature",
  "properties": {
    "iso:country":"CA",
    "sg:address":"506 18A St NW",
    "sg:city":"Calgary",
    "sg:classifiers":[
        {
            "category":"Professional",
            "subcategory":"Research",
            "type":"Services"
        }
    ],
    "sg:phone":"+1 403 283 8865",
    "sg:postcode":"T2N 2H2",
    "sg:province":"AB",
    "sg:tags":[
        "environmental",
        "ecological"
    ],
    "wof:name":"Fwr Freshwater Research Ltd",
    "wof:placetype":"venue"
},
  "geometry": {"coordinates":[-114.104133606,51.0567321777],"type":"Point"}
}