{
  "type": "Feature",
  "properties": {
    "iso:country":"CA",
    "sg:address":"3192 Logan Farm Dr",
    "sg:city":"Osgoode",
    "sg:classifiers":[
        {
            "category":"Health Services",
            "subcategory":"Doctor",
            "type":"Services"
        }
    ],
    "sg:phone":"+1 613 826 1638",
    "sg:postcode":"K0A 2W0",
    "sg:province":"ON",
    "sg:tags":[
        "dentist"
    ],
    "wof:name":"Osgoode Family Dental Ctr",
    "wof:placetype":"venue"
},
  "geometry": {"coordinates":[-75.60247039790001,45.1484718323],"type":"Point"}
}