{
  "type": "Feature",
  "properties": {
    "addr:full":"Jasper AB T0E 1E0",
    "addr:postcode":"t0e 1e0",
    "iso:country":"CA",
    "sg:city":"Jasper",
    "sg:classifiers":[
        {
            "category":"Travel",
            "subcategory":"Travel Agent",
            "type":"Entertainment"
        }
    ],
    "sg:phone":"+1 780 852 5247",
    "sg:postcode":"T0E 1E0",
    "sg:province":"AB",
    "sg:tags":[
        "information",
        "tourist"
    ],
    "wof:name":"Ski Jasper Consortium",
    "wof:placetype":"venue"
},
  "geometry": {"coordinates":[-118.080726623,52.87525177],"type":"Point"}
}