{
  "type": "Feature",
  "properties": {
    "addr:full":"316 Main St Rosetown SK S0L 2V0",
    "addr:housenumber":"316",
    "addr:postcode":"s0l 2v0",
    "addr:street":"Main St",
    "iso:country":"CA",
    "sg:address":"316 Main St",
    "sg:city":"Rosetown",
    "sg:classifiers":[
        {
            "category":"Food & Beverages",
            "subcategory":"Specialty",
            "type":"Retail Goods"
        }
    ],
    "sg:phone":"+1 306 882 2332",
    "sg:postcode":"S0L 2V0",
    "sg:province":"SK",
    "sg:tags":[
        "water",
        "bulk",
        "company"
    ],
    "wof:name":"Morning Mist Water Products",
    "wof:placetype":"venue"
},
  "geometry": {"coordinates":[-107.991539,51.551472],"type":"Point"}
}