{
  "type": "Feature",
  "properties": {
    "addr:full":"82 Cedar St Sudbury ON P3E 1A5",
    "addr:housenumber":"82",
    "addr:postcode":"p3e 1a5",
    "addr:street":"Cedar St",
    "iso:country":"CA",
    "sg:address":"82 Cedar St",
    "sg:city":"Sudbury",
    "sg:classifiers":[
        {
            "category":"Personal",
            "subcategory":"Beauty Salon",
            "type":"Services"
        }
    ],
    "sg:phone":"+1 705 674 8134",
    "sg:postcode":"P3E 1A5",
    "sg:province":"ON",
    "sg:tags":[
        "manicuring"
    ],
    "wof:name":"Roma Hair Styles",
    "wof:placetype":"venue"
},
  "geometry": {"coordinates":[-80.9936904907,46.4924354553],"type":"Point"}
}