{
  "type": "Feature",
  "properties": {
    "iso:country":"CA",
    "sg:address":"4034 Henderson Hwy",
    "sg:city":"East St Paul",
    "sg:classifiers":[
        {
            "category":"Building & Trades",
            "subcategory":"Electrical",
            "type":"Services"
        }
    ],
    "sg:phone":"+1 204 661 2391",
    "sg:postcode":"R2E 1B3",
    "sg:province":"MB",
    "sg:tags":[
        "electric",
        "contractor"
    ],
    "wof:name":"Schmidt Electric Ltd",
    "wof:placetype":"venue"
},
  "geometry": {"coordinates":[-97.0345001221,50.0190620422],"type":"Point"}
}