{
  "type": "Feature",
  "properties": {
    "iso:country":"CA",
    "sg:address":"6390 Tecumseh Rd E",
    "sg:city":"Windsor",
    "sg:classifiers":[
        {
            "category":"Manufacturing",
            "subcategory":"Tools & Machinery",
            "type":"Manufacturing & Wholesale Goods"
        }
    ],
    "sg:phone":"+1 519 798 3718",
    "sg:postcode":"N8T 1E6",
    "sg:province":"ON",
    "sg:tags":[
        "machine",
        "shop"
    ],
    "wof:name":"Innomation Technologies Inc",
    "wof:placetype":"venue"
},
  "geometry": {"coordinates":[-82.948928833,42.3111572266],"type":"Point"}
}