{
  "type": "Feature",
  "properties": {
    "addr:full":"4173 Rue Jarry E Montreal QC H1Z 2H5",
    "addr:housenumber":"4173",
    "addr:postcode":"h1z 2h5",
    "addr:street":"Rue Jarry E",
    "iso:country":"CA",
    "sg:address":"4173 Rue Jarry E",
    "sg:city":"Montreal",
    "sg:classifiers":[
        {
            "category":"Personal",
            "subcategory":"Beauty Salon",
            "type":"Services"
        }
    ],
    "sg:phone":"+1 514 729 5059",
    "sg:postcode":"H1Z 2H5",
    "sg:province":"QC",
    "wof:name":"Jarry Coiffure",
    "wof:placetype":"venue"
},
  "geometry": {"coordinates":[-73.60206604,45.5724182129],"type":"Point"}
}