{
  "type": "Feature",
  "properties": {
    "iso:country":"CA",
    "sg:address":"10346 University Ave NW",
    "sg:city":"Edmonton",
    "sg:classifiers":[
        {
            "category":"Restaurant",
            "type":"Food & Drink"
        }
    ],
    "sg:phone":"+1 780 433 3800",
    "sg:postcode":"T6E 4P4",
    "sg:province":"AB",
    "wof:name":"Spice Kitchen Restaurant",
    "wof:placetype":"venue"
},
  "geometry": {"coordinates":[-113.49581146200001,53.5114974976],"type":"Point"}
}