{
  "type": "Feature",
  "properties": {
    "addr:full":"60 Elm St St Thomas ON N5R 6G6",
    "addr:housenumber":"60",
    "addr:postcode":"n5r 6g6",
    "addr:street":"Elm St",
    "iso:country":"CA",
    "sg:address":"60 Elm St",
    "sg:city":"St Thomas",
    "sg:classifiers":[
        {
            "category":"Food & Beverages",
            "subcategory":"Bakery",
            "type":"Retail Goods"
        }
    ],
    "sg:phone":"+1 519 631 4575",
    "sg:postcode":"N5R 6G6",
    "sg:province":"ON",
    "sg:tags":[
        "tea",
        "coffee",
        "doughnut"
    ],
    "wof:name":"Tim Hortons",
    "wof:placetype":"venue"
},
  "geometry": {"coordinates":[-81.19261899999999,42.764706],"type":"Point"}
}