{
  "type": "Feature",
  "properties": {
    "addr:full":"10701 Boul Parkway Anjou QC H1J 1S1",
    "addr:housenumber":"10701",
    "addr:postcode":"h1j 1s1",
    "addr:street":"Boul Parkway",
    "iso:country":"CA",
    "sg:address":"10701 Boul Parkway",
    "sg:city":"Anjou",
    "sg:classifiers":[
        {
            "category":"Mining & Drilling",
            "type":"Manufacturing & Wholesale Goods"
        }
    ],
    "sg:phone":"+1 514 352 7490",
    "sg:postcode":"H1J 1S1",
    "sg:province":"QC",
    "sg:tags":[
        "company"
    ],
    "wof:name":"Mines Seleine Une",
    "wof:placetype":"venue"
},
  "geometry": {"coordinates":[-73.57910200000001,45.620518],"type":"Point"}
}