{
  "type": "Feature",
  "properties": {
    "addr:full":"5370 248 St Aldergrove BC V4W 1A7",
    "addr:housenumber":"5370",
    "addr:postcode":"v4w 1a7",
    "addr:street":"248 St",
    "iso:country":"CA",
    "sg:address":"5370 248 St",
    "sg:city":"Aldergrove",
    "sg:classifiers":[
        {
            "category":"Education",
            "subcategory":"School",
            "type":"Public Place"
        }
    ],
    "sg:phone":"+1 604 856 3355",
    "sg:postcode":"V4W 1A7",
    "sg:province":"BC",
    "wof:name":"North Otter Elementary School",
    "wof:placetype":"venue"
},
  "geometry": {"coordinates":[-122.472290039,49.0568656921],"type":"Point"}
}