{
  "type": "Feature",
  "properties": {
    "addr:full":"4205 Nahanni Dr Fort Nelson BC V0C 1R0",
    "addr:housenumber":"4205",
    "addr:postcode":"bc v0c 1r0",
    "addr:street":"Nahanni Dr",
    "iso:country":"CA",
    "sg:address":"4205 Nahanni Dr",
    "sg:city":"Fort Nelson",
    "sg:classifiers":[
        {
            "category":"Freight",
            "type":"Transportation"
        }
    ],
    "sg:phone":"+1 250 774 6659",
    "sg:postcode":"V0C 1R0",
    "sg:province":"BC",
    "sg:tags":[
        "trucking"
    ],
    "wof:name":"Cooper Barging Svc Ltd",
    "wof:placetype":"venue"
},
  "geometry": {"coordinates":[-122.67152404799999,58.7978248596],"type":"Point"}
}