{
  "type": "Feature",
  "properties": {
    "iso:country":"CA",
    "sg:address":"1116 Broadway W",
    "sg:city":"Vancouver",
    "sg:classifiers":[
        {
            "category":"Shopping",
            "type":"Retail Goods"
        }
    ],
    "sg:phone":"+1 604 738 0017",
    "sg:postcode":"V6H 1G5",
    "sg:province":"BC",
    "sg:tags":[
        "picture",
        "frame",
        "art",
        "gallery",
        "dealer"
    ],
    "wof:name":"Framagraphic",
    "wof:placetype":"venue"
},
  "geometry": {"coordinates":[-123.129562378,49.2633323669],"type":"Point"}
}