{
  "type": "Feature",
  "properties": {
    "addr:full":"3420 Trelawny Cir Mississauga ON L5N 6N6",
    "addr:housenumber":"3420",
    "addr:postcode":"l5n 6n6",
    "addr:street":"Trelawny Cir",
    "iso:country":"CA",
    "sg:address":"3420 Trelawny Cir",
    "sg:city":"Mississauga",
    "sg:classifiers":[
        {
            "category":"Education",
            "subcategory":"School",
            "type":"Public Place"
        }
    ],
    "sg:phone":"+1 905 824 0360",
    "sg:postcode":"L5N 6N6",
    "sg:province":"ON",
    "wof:name":"Trelawny Public School",
    "wof:placetype":"venue"
},
  "geometry": {"coordinates":[-79.76926400000001,43.571083],"type":"Point"}
}