{
  "type": "Feature",
  "properties": {
    "iso:country":"CA",
    "sg:address":"3420 Trelawny Cir",
    "sg:city":"Mississauga",
    "sg:classifiers":[
        {
            "category":"Education",
            "subcategory":"School",
            "type":"Public Place"
        }
    ],
    "sg:phone":"+1 905 824 0360",
    "sg:postcode":"L5N 6N6",
    "sg:province":"ON",
    "wof:name":"Trelawny Public School",
    "wof:placetype":"venue"
},
  "geometry": {"coordinates":[-79.769264,43.571083],"type":"Point"}
}