{
  "type": "Feature",
  "properties": {
    "addr:full":"31 Raddall Ave Dartmouth NS B3B 1L4",
    "addr:housenumber":"31",
    "addr:postcode":"b3b 1l4",
    "addr:street":"Raddall Ave",
    "iso:country":"CA",
    "sg:address":"31 Raddall Ave",
    "sg:city":"Dartmouth",
    "sg:classifiers":[
        {
            "category":"Retail",
            "subcategory":"Laundry & Dry Cleaning",
            "type":"Services"
        }
    ],
    "sg:phone":"+1 902 468 9119",
    "sg:postcode":"B3B 1L4",
    "sg:province":"NS",
    "sg:tags":[
        "cleaners",
        "rug",
        "carpet"
    ],
    "wof:name":"Chem-Dry of Halifax",
    "wof:placetype":"venue"
},
  "geometry": {"coordinates":[-63.5900726318,44.704246521],"type":"Point"}
}