{
  "type": "Feature",
  "properties": {
    "addr:full":"7 Mary St Parry Sound ON P2A 1C8",
    "addr:housenumber":"7",
    "addr:postcode":"p2a 1c8",
    "addr:street":"Mary St",
    "iso:country":"CA",
    "sg:address":"7 Mary St",
    "sg:city":"Parry Sound",
    "sg:classifiers":[
        {
            "category":"Organizations",
            "subcategory":"Professional Association",
            "type":"Services"
        }
    ],
    "sg:phone":"+1 705 746 3790",
    "sg:postcode":"P2A 1C8",
    "sg:province":"ON",
    "sg:tags":[
        "club",
        "hockey"
    ],
    "wof:name":"Parry Sound Hockey Club",
    "wof:placetype":"venue"
},
  "geometry": {"coordinates":[-80.031387,45.34568],"type":"Point"}
}