{
  "type": "Feature",
  "properties": {
    "iso:country":"CA",
    "sg:city":"Coquitlam",
    "sg:classifiers":[
        {
            "category":"Shopping",
            "subcategory":"Clothing, Apparel, & Fashions",
            "type":"Retail Goods"
        }
    ],
    "sg:phone":"+1 604 522 1575",
    "sg:postcode":"V3K 4X8",
    "sg:province":"BC",
    "wof:name":"Addition-Elle",
    "wof:placetype":"venue"
},
  "geometry": {"coordinates":[-122.852333069,49.2332038879],"type":"Point"}
}