{
  "type": "Feature",
  "properties": {
    "addr:full":"Edmonton AB T6K 4B2",
    "addr:postcode":"t6k 4b2",
    "iso:country":"CA",
    "sg:city":"Edmonton",
    "sg:classifiers":[
        {
            "category":"Health Services",
            "subcategory":"Health Practitioner",
            "type":"Services"
        }
    ],
    "sg:phone":"+1 780 450 0720",
    "sg:postcode":"T6K 4B2",
    "sg:province":"AB",
    "sg:tags":[
        "therapist",
        "physical"
    ],
    "wof:name":"Tawa Physical Therapy & Sports",
    "wof:placetype":"venue"
},
  "geometry": {"coordinates":[-113.433990478,53.4611358643],"type":"Point"}
}