{
  "type": "Feature",
  "properties": {
    "addr:full":"575 Bridge St Bathurst NB E2A 1W7",
    "addr:housenumber":"575",
    "addr:postcode":"e2a 1w7",
    "addr:street":"Bridge St",
    "iso:country":"CA",
    "sg:address":"575 Bridge St",
    "sg:city":"Bathurst",
    "sg:classifiers":[
        {
            "category":"Food & Beverages",
            "subcategory":"Bakery",
            "type":"Retail Goods"
        }
    ],
    "sg:phone":"+1 506 546 3040",
    "sg:postcode":"E2A 1W7",
    "sg:province":"NB",
    "sg:tags":[
        "tea",
        "coffee",
        "doughnut"
    ],
    "wof:name":"Tim Hortons",
    "wof:placetype":"venue"
},
  "geometry": {"coordinates":[-65.63539886469999,47.6127052307],"type":"Point"}
}