{
  "type": "Feature",
  "properties": {
    "addr:full":"648 Scott St Fort Frances ON P9A 1H6",
    "addr:housenumber":"648",
    "addr:postcode":"p9a 1h6",
    "addr:street":"Scott St",
    "iso:country":"CA",
    "sg:address":"648 Scott St",
    "sg:city":"Fort Frances",
    "sg:classifiers":[
        {
            "category":"Shopping",
            "subcategory":"Bicycles & Sporting Goods",
            "type":"Retail Goods"
        }
    ],
    "sg:phone":"+1 807 274 6180",
    "sg:postcode":"P9A 1H6",
    "sg:province":"ON",
    "wof:name":"Skates & Blades",
    "wof:placetype":"venue"
},
  "geometry": {"coordinates":[-93.38539900000001,48.610214],"type":"Point"}
}