{
  "type": "Feature",
  "properties": {
    "addr:full":"Vancouver BC V6S 1C5",
    "addr:postcode":"v6s 1c5",
    "iso:country":"CA",
    "sg:city":"Vancouver",
    "sg:classifiers":[
        {
            "category":"Health Services",
            "subcategory":"Doctor",
            "type":"Services"
        }
    ],
    "sg:phone":"+1 604 224 3115",
    "sg:postcode":"V6S 1C5",
    "sg:province":"BC",
    "sg:tags":[
        "dentist"
    ],
    "wof:name":"George A Porteous Inc",
    "wof:placetype":"venue"
},
  "geometry": {"coordinates":[-123.185562,49.255714],"type":"Point"}
}