{
  "type": "Feature",
  "properties": {
    "addr:full":"16275 Rue Notre-Dame E Pointe-Aux-Trembles QC H1A 3P7",
    "addr:housenumber":"16275",
    "addr:postcode":"h1a 3p7",
    "addr:street":"Rue Notre-Dame E Pointe-Aux-Trembles",
    "iso:country":"CA",
    "sg:address":"16275 Rue Notre-Dame E",
    "sg:city":"Pointe-Aux-Trembles",
    "sg:classifiers":[
        {
            "category":"Building & Trades",
            "subcategory":"Construction",
            "type":"Services"
        }
    ],
    "sg:phone":"+1 514 644 6464",
    "sg:postcode":"H1A 3P7",
    "sg:province":"QC",
    "sg:tags":[
        "asbestos",
        "removal"
    ],
    "wof:name":"Services Mcr Inc",
    "wof:placetype":"venue"
},
  "geometry": {"coordinates":[-73.48397827150001,45.6997871399],"type":"Point"}
}