{
  "type": "Feature",
  "properties": {
    "iso:country":"CA",
    "sg:address":"134 Rue Principale",
    "sg:city":"Saint-Andre-Avellin",
    "sg:classifiers":[
        {
            "category":"Organizations",
            "subcategory":"Professional Association",
            "type":"Services"
        }
    ],
    "sg:phone":"+1 819 983 1565",
    "sg:postcode":"J0V 1W0",
    "sg:province":"QC",
    "wof:name":"Comite Regional Du 3E Age",
    "wof:placetype":"venue"
},
  "geometry": {"coordinates":[-75.053352356,45.7259979248],"type":"Point"}
}