{
  "type": "Feature",
  "properties": {
    "addr:full":"224 Main St Courtland ON N0J 1E0",
    "addr:housenumber":"224",
    "addr:postcode":"n0j 1e0",
    "addr:street":"Main St",
    "iso:country":"CA",
    "sg:address":"224 Main St",
    "sg:city":"Courtland",
    "sg:classifiers":[
        {
            "category":"Bars & Pubs",
            "type":"Food & Drink"
        }
    ],
    "sg:phone":"+1 519 688 2416",
    "sg:postcode":"N0J 1E0",
    "sg:province":"ON",
    "wof:name":"Courtland Roadhouse Pub",
    "wof:placetype":"venue"
},
  "geometry": {"coordinates":[-80.6310119629,42.8439865112],"type":"Point"}
}