{
  "type": "Feature",
  "properties": {
    "addr:full":"5700 DE LA Cote-Des-Neiges Ch Montreal QC H3T 2A6",
    "addr:housenumber":"5700",
    "addr:postcode":"h3t 2a6",
    "addr:street":"De La Cote-Des-Neiges Ch",
    "iso:country":"CA",
    "sg:address":"5700 DE LA Cote-Des-Neiges Ch",
    "sg:city":"Montreal",
    "sg:classifiers":[
        {
            "category":"Professional",
            "subcategory":"Management & Consulting",
            "type":"Services"
        }
    ],
    "sg:phone":"+1 514 345 9427",
    "sg:postcode":"H3T 2A6",
    "sg:province":"QC",
    "sg:tags":[
        "consultant",
        "traffic",
        "parking"
    ],
    "wof:name":"Stationnement Mathola",
    "wof:placetype":"venue"
},
  "geometry": {"coordinates":[-73.55439,45.512287],"type":"Point"}
}