{
  "type": "Feature",
  "properties": {
    "addr:full":"1968 Boul DE Maisonneuve O Montreal QC H3H 1K5",
    "addr:housenumber":"1968",
    "addr:postcode":"h3h 1k5",
    "addr:street":"Boul De Maisonneuve O",
    "iso:country":"CA",
    "sg:address":"1968 Boul DE Maisonneuve O",
    "sg:city":"Montreal",
    "sg:classifiers":[
        {
            "category":"Professional",
            "subcategory":"Secretarial Services",
            "type":"Services"
        }
    ],
    "sg:phone":"+1 514 933 0798",
    "sg:postcode":"H3H 1K5",
    "sg:province":"QC",
    "sg:tags":[
        "reporting",
        "court"
    ],
    "wof:name":"Black Studies Ctr",
    "wof:placetype":"venue"
},
  "geometry": {"coordinates":[-73.55242200000001,45.524467],"type":"Point"}
}