{
  "type": "Feature",
  "properties": {
    "iso:country":"CA",
    "sg:address":"1968 Boul DE Maisonneuve O",
    "sg:city":"Montreal",
    "sg:classifiers":[
        {
            "category":"Professional",
            "subcategory":"Secretarial Services",
            "type":"Services"
        }
    ],
    "sg:phone":"+1 514 933 0798",
    "sg:postcode":"H3H 1K5",
    "sg:province":"QC",
    "sg:tags":[
        "reporting",
        "court"
    ],
    "wof:name":"Black Studies Ctr",
    "wof:placetype":"venue"
},
  "geometry": {"coordinates":[-73.552422,45.524467],"type":"Point"}
}