{
  "type": "Feature",
  "properties": {
    "addr:full":"Oakville ON L6J 3M5",
    "addr:postcode":"l6j 3m5",
    "iso:country":"CA",
    "sg:city":"Oakville",
    "sg:classifiers":[
        {
            "category":"Health Services",
            "subcategory":"Doctor",
            "type":"Services"
        }
    ],
    "sg:phone":"+1 905 842 8346",
    "sg:postcode":"L6J 3M5",
    "sg:province":"ON",
    "sg:tags":[
        "physician",
        "surgeon"
    ],
    "wof:name":"Knowlton, Robert MD",
    "wof:placetype":"venue"
},
  "geometry": {"coordinates":[-79.6779098511,43.4552268982],"type":"Point"}
}