{
  "type": "Feature",
  "properties": {
    "iso:country":"CA",
    "sg:address":"3 Prescott Dr",
    "sg:city":"Bolton",
    "sg:classifiers":[
        {
            "category":"Building & Trades",
            "subcategory":"Cleaning & Sanitation",
            "type":"Services"
        }
    ],
    "sg:phone":"+1 905 857 3183",
    "sg:postcode":"L7E 1P6",
    "sg:province":"ON",
    "sg:tags":[
        "janitor"
    ],
    "wof:name":"Ontario Floor Finishing Svc",
    "wof:placetype":"venue"
},
  "geometry": {"coordinates":[-79.7220535278,43.8728713989],"type":"Point"}
}