{
  "type": "Feature",
  "properties": {
    "iso:country":"CA",
    "sg:city":"Sherwood Park",
    "sg:classifiers":[
        {
            "category":"Autos & Motor Vehicles",
            "subcategory":"Fuel & Gas Station",
            "type":"Retail Goods"
        }
    ],
    "sg:phone":"+1 780 449 1636",
    "sg:postcode":"T8A 4W2",
    "sg:province":"AB",
    "sg:tags":[
        "oil"
    ],
    "wof:name":"CO-OP Gas Bar",
    "wof:placetype":"venue"
},
  "geometry": {"coordinates":[-113.290214539,53.528553009],"type":"Point"}
}