{
  "type": "Feature",
  "properties": {
    "addr:full":"159 Mary St Brantford ON N3S 3C1",
    "addr:housenumber":"159",
    "addr:postcode":"n3s 3c1",
    "addr:street":"Mary St",
    "iso:country":"CA",
    "sg:address":"159 Mary St",
    "sg:city":"Brantford",
    "sg:classifiers":[
        {
            "category":"Education",
            "subcategory":"School",
            "type":"Public Place"
        }
    ],
    "sg:phone":"+1 519 756 7100",
    "sg:postcode":"N3S 3C1",
    "sg:province":"ON",
    "wof:name":"St Jean DE Brebeuf",
    "wof:placetype":"venue"
},
  "geometry": {"coordinates":[-80.24395800000001,43.136078],"type":"Point"}
}