{
  "type": "Feature",
  "properties": {
    "addr:full":"Pickering ON L1W 2A1",
    "addr:postcode":"l1w 2a1",
    "iso:country":"CA",
    "sg:city":"Pickering",
    "sg:classifiers":[
        {
            "category":"Manufacturing",
            "subcategory":"Tools & Machinery",
            "type":"Manufacturing & Wholesale Goods"
        }
    ],
    "sg:phone":"+1 905 839 9463",
    "sg:postcode":"L1W 2A1",
    "sg:province":"ON",
    "sg:tags":[
        "filtering",
        "material",
        "supply"
    ],
    "wof:name":"Scott Laboratories Ltd",
    "wof:placetype":"venue"
},
  "geometry": {"coordinates":[-79.066261,43.830009],"type":"Point"}
}