{
  "type": "Feature",
  "properties": {
    "addr:full":"189 Applegrove St Sudbury ON P3C 1N4",
    "addr:housenumber":"189",
    "addr:postcode":"p3c 1n4",
    "addr:street":"Applegrove St",
    "iso:country":"CA",
    "sg:address":"189 Applegrove St",
    "sg:city":"Sudbury",
    "sg:classifiers":[
        {
            "category":"Social Services",
            "subcategory":"Child Care",
            "type":"Services"
        }
    ],
    "sg:phone":"+1 705 674 3334",
    "sg:postcode":"P3C 1N4",
    "sg:province":"ON",
    "wof:name":"Jubilee Heritage Family Rsrces",
    "wof:placetype":"venue"
},
  "geometry": {"coordinates":[-81.002869,46.491764],"type":"Point"}
}