{
  "type": "Feature",
  "properties": {
    "addr:full":"30 Shadow Rd Fernie BC V0B 1M5",
    "addr:housenumber":"30",
    "addr:postcode":"bc v0b 1m5",
    "addr:street":"Shadow Rd",
    "iso:country":"CA",
    "sg:address":"30 Shadow Rd",
    "sg:city":"Fernie",
    "sg:classifiers":[
        {
            "category":"Autos & Motor Vehicles",
            "subcategory":"Motorcycle Sales",
            "type":"Retail Goods"
        }
    ],
    "sg:phone":"+1 250 423 9251",
    "sg:postcode":"V0B 1M5",
    "sg:province":"BC",
    "sg:tags":[
        "snowmobile"
    ],
    "wof:name":"Ghost Rider Motor Sports",
    "wof:placetype":"venue"
},
  "geometry": {"coordinates":[-115.04866,49.527317],"type":"Point"}
}