{
  "type": "Feature",
  "properties": {
    "addr:full":"Richmond BC V7A 5C8",
    "addr:postcode":"v7a 5c8",
    "iso:country":"CA",
    "sg:city":"Richmond",
    "sg:classifiers":[
        {
            "category":"Manufacturing",
            "subcategory":"Metals",
            "type":"Manufacturing & Wholesale Goods"
        }
    ],
    "sg:phone":"+1 604 275 5225",
    "sg:postcode":"V7A 5C8",
    "sg:province":"BC",
    "sg:tags":[
        "housewares"
    ],
    "wof:name":"Jollen Home Creation Ltd",
    "wof:placetype":"venue"
},
  "geometry": {"coordinates":[-123.100319,49.128216],"type":"Point"}
}