{
  "type": "Feature",
  "properties": {
    "addr:full":"1127 Av Laurier O Outremont QC H2V 2L3",
    "addr:housenumber":"1127",
    "addr:postcode":"h2v 2l3",
    "addr:street":"Av Laurier O",
    "iso:country":"CA",
    "sg:address":"1127 Av Laurier O",
    "sg:city":"Outremont",
    "sg:classifiers":[
        {
            "category":"Shopping",
            "subcategory":"Clothing, Apparel, & Fashions",
            "type":"Retail Goods"
        }
    ],
    "sg:phone":"+1 514 274 2022",
    "sg:postcode":"H2V 2L3",
    "sg:province":"QC",
    "sg:tags":[
        "infant",
        "wear"
    ],
    "wof:name":"Jacadi Inc",
    "wof:placetype":"venue"
},
  "geometry": {"coordinates":[-73.59777832029999,45.5171356201],"type":"Point"}
}