{
  "type": "Feature",
  "properties": {
    "addr:full":"33 Rue Principale S LA Patrie QC J0B 1Y0",
    "addr:housenumber":"33",
    "addr:postcode":"j0b 1y0",
    "addr:street":"Rue Principale S La Patrie",
    "iso:country":"CA",
    "sg:address":"33 Rue Principale S",
    "sg:city":"LA Patrie",
    "sg:classifiers":[
        {
            "category":"Home & Garden",
            "subcategory":"Carpets & Floor Coverings",
            "type":"Retail Goods"
        }
    ],
    "sg:phone":"+1 819 888 2856",
    "sg:postcode":"J0B 1Y0",
    "sg:province":"QC",
    "sg:tags":[
        "material",
        "manufacturer"
    ],
    "wof:name":"Ditton Wood Industries Inc",
    "wof:placetype":"venue"
},
  "geometry": {"coordinates":[-71.249084,45.400524],"type":"Point"}
}