{
  "type": "Feature",
  "properties": {
    "addr:full":"Ottawa ON K2P 1P1",
    "addr:postcode":"k2p 1p1",
    "iso:country":"CA",
    "sg:city":"Ottawa",
    "sg:classifiers":[
        {
            "category":"Professional",
            "subcategory":"Lawyer & Legal Services",
            "type":"Services"
        }
    ],
    "sg:phone":"+1 613 238 8400",
    "sg:postcode":"K2P 1P1",
    "sg:province":"ON",
    "sg:tags":[
        "attorney"
    ],
    "wof:name":"Groulx, Rudolph W",
    "wof:placetype":"venue"
},
  "geometry": {"coordinates":[-75.694962,45.419662],"type":"Point"}
}