{
  "type": "Feature",
  "properties": {
    "addr:full":"411 Aberdeen St SE Medicine Hat AB T1A 0R4",
    "addr:housenumber":"411",
    "addr:postcode":"t1a 0r4",
    "addr:street":"Aberdeen St Se",
    "iso:country":"CA",
    "sg:address":"411 Aberdeen St SE",
    "sg:city":"Medicine Hat",
    "sg:classifiers":[
        {
            "category":"Professional",
            "subcategory":"Engineering",
            "type":"Services"
        }
    ],
    "sg:phone":"+1 403 527 5772",
    "sg:postcode":"T1A 0R4",
    "sg:province":"AB",
    "sg:tags":[
        "engineer"
    ],
    "wof:name":"P H Mc Nally Assoc Ltd",
    "wof:placetype":"venue"
},
  "geometry": {"coordinates":[-110.676933289,50.0359191895],"type":"Point"}
}