{
  "type": "Feature",
  "properties": {
    "addr:full":"320 Main St N Brampton ON L6V 4A3",
    "addr:housenumber":"320",
    "addr:postcode":"l6v 4a3",
    "addr:street":"Main St N",
    "iso:country":"CA",
    "sg:address":"320 Main St N",
    "sg:city":"Brampton",
    "sg:classifiers":[
        {
            "category":"Food & Beverages",
            "subcategory":"Groceries & Convenience Stores",
            "type":"Retail Goods"
        }
    ],
    "sg:phone":"+1 905 457 7100",
    "sg:postcode":"L6V 4A3",
    "sg:province":"ON",
    "wof:name":"City Convenience",
    "wof:placetype":"venue"
},
  "geometry": {"coordinates":[-79.7691116333,43.6929359436],"type":"Point"}
}