{
  "type": "Feature",
  "properties": {
    "addr:full":"3893 Bathurst St North York ON M3H 5V1",
    "addr:housenumber":"3893",
    "addr:postcode":"m3h 5v1",
    "addr:street":"Bathurst St",
    "iso:country":"CA",
    "sg:address":"3893 Bathurst St",
    "sg:city":"North York",
    "sg:classifiers":[
        {
            "category":"Shopping",
            "subcategory":"Computers & Home Electronics",
            "type":"Retail Goods"
        }
    ],
    "sg:phone":"+1 416 636 4822",
    "sg:postcode":"M3H 5V1",
    "sg:province":"ON",
    "sg:tags":[
        "television",
        "radio"
    ],
    "wof:name":"Howard Tv Stereo & Video Ctr",
    "wof:placetype":"venue"
},
  "geometry": {"coordinates":[-79.43501281739999,43.7422904968],"type":"Point"}
}