{
  "type": "Feature",
  "properties": {
    "addr:full":"1235 Montee Du Moulin Laval QC H7A 3V6",
    "addr:housenumber":"1235",
    "addr:postcode":"h7a 3v6",
    "addr:street":"Montee Du Moulin",
    "iso:country":"CA",
    "sg:address":"1235 Montee Du Moulin",
    "sg:city":"Laval",
    "sg:classifiers":[
        {
            "category":"Banks & Credit Unions",
            "subcategory":"Bank",
            "type":"Services"
        }
    ],
    "sg:phone":"+1 450 665 0692",
    "sg:postcode":"H7A 3V6",
    "sg:province":"QC",
    "wof:name":"Banque Nationale Du Canada",
    "wof:placetype":"venue"
},
  "geometry": {"coordinates":[-73.582275,45.676239],"type":"Point"}
}