{
  "type": "Feature",
  "properties": {
    "iso:country":"CA",
    "sg:address":"4924 51 Ave",
    "sg:city":"Whitecourt",
    "sg:classifiers":[
        {
            "category":"Food & Beverages",
            "subcategory":"Specialty",
            "type":"Retail Goods"
        }
    ],
    "sg:phone":"+1 780 778 8885",
    "sg:postcode":"T7S 1P1",
    "sg:province":"AB",
    "sg:tags":[
        "health",
        "diet"
    ],
    "wof:name":"Health & Herb House",
    "wof:placetype":"venue"
},
  "geometry": {"coordinates":[-115.682640076,54.1416015625],"type":"Point"}
}