{
  "type": "Feature",
  "properties": {
    "addr:full":"8331 125 Rte Chertsey QC J0K 3K0",
    "addr:housenumber":"8331",
    "addr:postcode":"j0k 3k0",
    "addr:street":"125 Rte",
    "iso:country":"CA",
    "sg:address":"8331 125 Rte",
    "sg:city":"Chertsey",
    "sg:classifiers":[
        {
            "category":"Retail",
            "subcategory":"Auto Repair",
            "type":"Services"
        }
    ],
    "sg:phone":"+1 450 882 2113",
    "sg:postcode":"J0K 3K0",
    "sg:province":"QC",
    "sg:tags":[
        "body",
        "automobile",
        "painting"
    ],
    "wof:name":"Garage Le Carrossier",
    "wof:placetype":"venue"
},
  "geometry": {"coordinates":[-73.89223480219999,46.0730743408],"type":"Point"}
}