{
  "type": "Feature",
  "properties": {
    "addr:full":"201 Government Rd Black Diamond AB T0L 0H0",
    "addr:housenumber":"201",
    "addr:postcode":"t0l 0h0",
    "addr:street":"Government Rd",
    "iso:country":"CA",
    "sg:address":"201 Government Rd",
    "sg:city":"Black Diamond",
    "sg:classifiers":[
        {
            "category":"Restaurant",
            "type":"Food & Drink"
        }
    ],
    "sg:phone":"+1 403 933 3333",
    "sg:postcode":"T0L 0H0",
    "sg:province":"AB",
    "wof:name":"Subway Sandwiches & Salads",
    "wof:placetype":"venue"
},
  "geometry": {"coordinates":[-114.232757568,50.6870651245],"type":"Point"}
}