{
  "type": "Feature",
  "properties": {
    "addr:full":"55 Vansco Rd Etobicoke ON M8Z 5Z8",
    "addr:housenumber":"55",
    "addr:postcode":"m8z 5z8",
    "addr:street":"Vansco Rd",
    "iso:country":"CA",
    "sg:address":"55 Vansco Rd",
    "sg:city":"Etobicoke",
    "sg:classifiers":[
        {
            "category":"Manufacturing",
            "subcategory":"Food",
            "type":"Manufacturing & Wholesale Goods"
        }
    ],
    "sg:phone":"+1 416 255 3474",
    "sg:postcode":"M8Z 5Z8",
    "sg:province":"ON",
    "sg:tags":[
        "product",
        "seafood",
        "fish",
        "prepared"
    ],
    "wof:name":"Allseas Fisheries Inc",
    "wof:placetype":"venue"
},
  "geometry": {"coordinates":[-79.534874,43.621841],"type":"Point"}
}