{
  "type": "Feature",
  "properties": {
    "addr:full":"430 Topsail Rd St. John's NL A1E 4N1",
    "addr:housenumber":"430",
    "addr:postcode":"a1e 4n1",
    "addr:street":"Topsail Rd",
    "iso:country":"CA",
    "sg:address":"430 Topsail Rd",
    "sg:city":"St. John's",
    "sg:classifiers":[
        {
            "category":"Professional",
            "subcategory":"Accounting & Tax Preparation",
            "type":"Services"
        }
    ],
    "sg:phone":"+1 709 364 7700",
    "sg:postcode":"A1E 4N1",
    "sg:province":"NL",
    "sg:tags":[
        "return",
        "filing"
    ],
    "wof:name":"H & R Block Canada Inc",
    "wof:placetype":"venue"
},
  "geometry": {"coordinates":[-52.751656,47.532768],"type":"Point"}
}