{
  "type": "Feature",
  "properties": {
    "addr:full":"Riviere-Mekinac QC G0X 2E0",
    "addr:postcode":"g0x 2e0",
    "iso:country":"CA",
    "sg:city":"Riviere-Mekinac",
    "sg:classifiers":[
        {
            "category":"Organizations",
            "subcategory":"Religious Organization",
            "type":"Services"
        }
    ],
    "sg:phone":"+1 819 646 1551",
    "sg:postcode":"G0X 2E0",
    "sg:province":"QC",
    "sg:tags":[
        "church"
    ],
    "wof:name":"Presbytere St-Roch-DE-Mekinac",
    "wof:placetype":"venue"
},
  "geometry": {"coordinates":[-72.769623,46.811031],"type":"Point"}
}