{
  "type": "Feature",
  "properties": {
    "addr:full":"3 Garfield St Charlottetown PE C1A 6A4",
    "addr:housenumber":"3",
    "addr:postcode":"c1a 6a4",
    "addr:street":"Garfield St",
    "iso:country":"CA",
    "sg:address":"3 Garfield St",
    "sg:city":"Charlottetown",
    "sg:classifiers":[
        {
            "category":"Food & Beverages",
            "subcategory":"Liquor & Beverages",
            "type":"Retail Goods"
        }
    ],
    "sg:phone":"+1 902 368 5710",
    "sg:postcode":"C1A 6A4",
    "sg:province":"PE",
    "sg:tags":[
        "government"
    ],
    "wof:name":"PE Liquor Control Commission",
    "wof:placetype":"venue"
},
  "geometry": {"coordinates":[-63.110657,46.25198],"type":"Point"}
}