{
  "type": "Feature",
  "properties": {
    "addr:full":"1500 Front St Hearst ON P0L 1N0",
    "addr:housenumber":"1500",
    "addr:postcode":"p0l 1n0",
    "addr:street":"Front St",
    "iso:country":"CA",
    "sg:address":"1500 Front St",
    "sg:city":"Hearst",
    "sg:classifiers":[
        {
            "category":"Freight",
            "type":"Transportation"
        }
    ],
    "sg:phone":"+1 705 362 4209",
    "sg:postcode":"P0L 1N0",
    "sg:province":"ON",
    "sg:tags":[
        "railroad",
        "courier"
    ],
    "wof:name":"Ontario Northland",
    "wof:placetype":"venue"
},
  "geometry": {"coordinates":[-83.681152,49.691059],"type":"Point"}
}