{
  "type": "Feature",
  "properties": {
    "addr:full":"177 Hachborn Rd Brantford ON N3S 7W7",
    "addr:housenumber":"177",
    "addr:postcode":"n3s 7w7",
    "addr:street":"Hachborn Rd",
    "iso:country":"CA",
    "sg:address":"177 Hachborn Rd",
    "sg:city":"Brantford",
    "sg:classifiers":[
        {
            "category":"Manufacturing",
            "subcategory":"Printing",
            "type":"Manufacturing & Wholesale Goods"
        }
    ],
    "sg:phone":"+1 519 759 5920",
    "sg:postcode":"N3S 7W7",
    "sg:province":"ON",
    "sg:tags":[
        "printer"
    ],
    "wof:name":"Fastprint Inc",
    "wof:placetype":"venue"
},
  "geometry": {"coordinates":[-80.219826,43.150692],"type":"Point"}
}