{
  "type": "Feature",
  "properties": {
    "addr:full":"1 Eva Rd Etobicoke ON M9C 4Z5",
    "addr:housenumber":"1",
    "addr:postcode":"m9c 4z5",
    "addr:street":"Eva Rd",
    "iso:country":"CA",
    "sg:address":"1 Eva Rd",
    "sg:city":"Etobicoke",
    "sg:classifiers":[
        {
            "category":"Banks & Credit Unions",
            "subcategory":"Investment Brokerage",
            "type":"Services"
        }
    ],
    "sg:phone":"+1 416 622 4441",
    "sg:postcode":"M9C 4Z5",
    "sg:province":"ON",
    "sg:tags":[
        "consultant",
        "planning",
        "financial"
    ],
    "wof:name":"Acquaint Financial",
    "wof:placetype":"venue"
},
  "geometry": {"coordinates":[-79.563278,43.639519],"type":"Point"}
}