{
  "type": "Feature",
  "properties": {
    "addr:full":"375 Plains Rd E Burlington ON L7T 2C7",
    "addr:housenumber":"375",
    "addr:postcode":"l7t 2c7",
    "addr:street":"Plains Rd E",
    "iso:country":"CA",
    "sg:address":"375 Plains Rd E",
    "sg:city":"Burlington",
    "sg:classifiers":[
        {
            "category":"Organizations",
            "subcategory":"Religious Organization",
            "type":"Services"
        }
    ],
    "sg:phone":"+1 905 634 5562",
    "sg:postcode":"L7T 2C7",
    "sg:province":"ON",
    "sg:tags":[
        "church"
    ],
    "wof:name":"East Plains United Church",
    "wof:placetype":"venue"
},
  "geometry": {"coordinates":[-79.840515,43.316185],"type":"Point"}
}