{
  "type": "Feature",
  "properties": {
    "addr:full":"Winnipeg MB R3R 2P9",
    "addr:postcode":"r3r 2p9",
    "iso:country":"CA",
    "sg:city":"Winnipeg",
    "sg:classifiers":[
        {
            "category":"Travel",
            "subcategory":"Travel Agent",
            "type":"Entertainment"
        }
    ],
    "sg:phone":"+1 204 953 2828",
    "sg:postcode":"R3R 2P9",
    "sg:province":"MB",
    "sg:tags":[
        "agency",
        "bureau"
    ],
    "wof:name":"Charleswood Travel",
    "wof:placetype":"venue"
},
  "geometry": {"coordinates":[-97.31526947019999,49.8633613586],"type":"Point"}
}