{
  "type": "Feature",
  "properties": {
    "addr:full":"225 Main St Chipman NB E4A 2H2",
    "addr:housenumber":"225",
    "addr:postcode":"e4a 2h2",
    "addr:street":"Main St",
    "iso:country":"CA",
    "sg:address":"225 Main St",
    "sg:city":"Chipman",
    "sg:classifiers":[
        {
            "category":"Organizations",
            "subcategory":"Religious Organization",
            "type":"Services"
        }
    ],
    "sg:phone":"+1 506 339 5466",
    "sg:postcode":"E4A 2H2",
    "sg:province":"NB",
    "sg:tags":[
        "church"
    ],
    "wof:name":"Second Chipman United Baptist",
    "wof:placetype":"venue"
},
  "geometry": {"coordinates":[-65.88166809080001,46.1752281189],"type":"Point"}
}