{
  "type": "Feature",
  "properties": {
    "addr:full":"445 Rte DE L'Eglise Saint-Jean-Port-Joli QC G0R 3G0",
    "addr:housenumber":"445",
    "addr:postcode":"g0r 3g0",
    "addr:street":"Rte De L'Eglise",
    "iso:country":"CA",
    "sg:address":"445 Rte DE L'Eglise",
    "sg:city":"Saint-Jean-Port-Joli",
    "sg:classifiers":[
        {
            "category":"Shopping",
            "subcategory":"Pharmacy",
            "type":"Retail Goods"
        }
    ],
    "sg:phone":"+1 418 598 3071",
    "sg:postcode":"G0R 3G0",
    "sg:province":"QC",
    "wof:name":"Pharmacie Brunet Maurice Nolin",
    "wof:placetype":"venue"
},
  "geometry": {"coordinates":[-70.26676940919999,47.2121009827],"type":"Point"}
}