{
  "type": "Feature",
  "properties": {
    "iso:country":"CA",
    "sg:address":"118 Raglan St S",
    "sg:city":"Renfrew",
    "sg:classifiers":[
        {
            "category":"Personal",
            "subcategory":"Beauty Salon",
            "type":"Services"
        }
    ],
    "sg:phone":"+1 613 433 8999",
    "sg:postcode":"K7V 1P9",
    "sg:province":"ON",
    "wof:name":"Tranquility Esthetics",
    "wof:placetype":"venue"
},
  "geometry": {"coordinates":[-76.68570709230001,45.4730072021],"type":"Point"}
}