{
  "type": "Feature",
  "properties": {
    "addr:full":"1421 117 Rte Val-David QC J0T 2N0",
    "addr:housenumber":"1421",
    "addr:postcode":"j0t 2n0",
    "addr:street":"117 Rte Val-David",
    "iso:country":"CA",
    "sg:address":"1421 117 Rte",
    "sg:city":"Val-David",
    "sg:classifiers":[
        {
            "category":"Food & Beverages",
            "subcategory":"Fruits & Vegetables",
            "type":"Retail Goods"
        }
    ],
    "sg:phone":"+1 819 322 6120",
    "sg:postcode":"J0T 2N0",
    "sg:province":"QC",
    "sg:tags":[
        "produce"
    ],
    "wof:name":"Fruits & Legumes Val-David",
    "wof:placetype":"venue"
},
  "geometry": {"coordinates":[-74.215874,46.027672],"type":"Point"}
}