{
  "type": "Feature",
  "properties": {
    "iso:country":"CA",
    "sg:address":"522 Boul DE LA Grande-Baie S",
    "sg:city":"LA Baie",
    "sg:classifiers":[
        {
            "category":"Shopping",
            "subcategory":"Pharmacy",
            "type":"Retail Goods"
        }
    ],
    "sg:phone":"+1 418 544 3333",
    "sg:postcode":"G7B 2C7",
    "sg:province":"QC",
    "wof:name":"Jean Coutu Pharmacy",
    "wof:placetype":"venue"
},
  "geometry": {"coordinates":[-70.88000488279999,48.3309783936],"type":"Point"}
}