{
  "type": "Feature",
  "properties": {
    "addr:full":"1211 Rue Principale Saint-Dominique QC J0H 1L0",
    "addr:housenumber":"1211",
    "addr:postcode":"j0h 1l0",
    "addr:street":"Rue Principale",
    "iso:country":"CA",
    "sg:address":"1211 Rue Principale",
    "sg:city":"Saint-Dominique",
    "sg:classifiers":[
        {
            "category":"Organizations",
            "subcategory":"Religious Organization",
            "type":"Services"
        }
    ],
    "sg:phone":"+1 450 773 0233",
    "sg:postcode":"J0H 1L0",
    "sg:province":"QC",
    "sg:tags":[
        "church"
    ],
    "wof:name":"Presbytere Ste-Dominique",
    "wof:placetype":"venue"
},
  "geometry": {"coordinates":[-72.85251599999999,45.564312],"type":"Point"}
}