{
  "type": "Feature",
  "properties": {
    "addr:full":"6854 Garner Rd Niagara Falls ON L2E 6S4",
    "addr:housenumber":"6854",
    "addr:postcode":"l2e 6s4",
    "addr:street":"Garner Rd",
    "iso:country":"CA",
    "sg:address":"6854 Garner Rd",
    "sg:city":"Niagara Falls",
    "sg:classifiers":[
        {
            "category":"Recreation",
            "type":"Entertainment"
        }
    ],
    "sg:phone":"+1 905 374 0224",
    "sg:postcode":"L2E 6S4",
    "sg:province":"ON",
    "sg:tags":[
        "hall",
        "auditorium"
    ],
    "wof:name":"German Village",
    "wof:placetype":"venue"
},
  "geometry": {"coordinates":[-79.1482543945,43.0751609802],"type":"Point"}
}