{
  "type": "Feature",
  "properties": {
    "addr:full":"Hwy 5A S Merritt BC V1K 1B8",
    "addr:postcode":"v1k 1b8",
    "addr:street":"Hwy 5A S",
    "iso:country":"CA",
    "sg:address":"Hwy 5A S",
    "sg:city":"Merritt",
    "sg:classifiers":[
        {
            "category":"Travel",
            "subcategory":"Hotels & Motels",
            "type":"Entertainment"
        }
    ],
    "sg:phone":"+1 250 378 4334",
    "sg:postcode":"V1K 1B8",
    "sg:province":"BC",
    "sg:tags":[
        "resort"
    ],
    "wof:name":"Corbett Lake Country Inn",
    "wof:placetype":"venue"
},
  "geometry": {"coordinates":[-120.760651,50.123386],"type":"Point"}
}