{
  "type": "Feature",
  "properties": {
    "iso:country":"CA",
    "sg:address":"47 Rue Nicholson",
    "sg:city":"Salaberry-DE-Valleyfield",
    "sg:classifiers":[
        {
            "category":"Government",
            "subcategory":"Fire Station",
            "type":"Public Place"
        }
    ],
    "sg:phone":"+1 ",
    "sg:postcode":"J6T 4M9",
    "sg:province":"QC",
    "sg:tags":[
        "department",
        "police"
    ],
    "wof:name":"Salaberry-Valleyfield Police",
    "wof:placetype":"venue"
},
  "geometry": {"coordinates":[-74.1308059692,45.2545623779],"type":"Point"}
}