{
  "type": "Feature",
  "properties": {
    "addr:full":"25 Pitt St E Windsor ON N9A 2V3",
    "addr:housenumber":"25",
    "addr:postcode":"n9a 2v3",
    "addr:street":"Pitt St E",
    "iso:country":"CA",
    "sg:address":"25 Pitt St E",
    "sg:city":"Windsor",
    "sg:classifiers":[
        {
            "category":"Restaurant",
            "type":"Food & Drink"
        }
    ],
    "sg:phone":"+1 519 977 5722",
    "sg:postcode":"N9A 2V3",
    "sg:province":"ON",
    "wof:name":"Patrick O Ryans",
    "wof:placetype":"venue"
},
  "geometry": {"coordinates":[-83.03927612299999,42.3188934326],"type":"Point"}
}