{
  "type": "Feature",
  "properties": {
    "iso:country":"CA",
    "sg:address":"Rte 279",
    "sg:city":"Saint-Lazare-DE-Bellechasse",
    "sg:classifiers":[
        {
            "category":"Shopping",
            "subcategory":"Used Merchandise",
            "type":"Retail Goods"
        }
    ],
    "sg:phone":"+1 418 883 2958",
    "sg:postcode":"G0R 3J0",
    "sg:province":"QC",
    "sg:tags":[
        "antique"
    ],
    "wof:name":"Plante Florian",
    "wof:placetype":"venue"
},
  "geometry": {"coordinates":[-70.8052139282,46.6543235779],"type":"Point"}
}