{
  "type": "Feature",
  "properties": {
    "addr:full":"3085 Boul Neuvialle Quebec QC G1P 3A7",
    "addr:housenumber":"3085",
    "addr:postcode":"g1p 3a7",
    "addr:street":"Boul Neuvialle",
    "iso:country":"CA",
    "sg:address":"3085 Boul Neuvialle",
    "sg:city":"Quebec",
    "sg:classifiers":[
        {
            "category":"Manufacturing",
            "subcategory":"Signs",
            "type":"Manufacturing & Wholesale Goods"
        }
    ],
    "sg:phone":"+1 418 527 3443",
    "sg:postcode":"G1P 3A7",
    "sg:province":"QC",
    "wof:name":"Star Graphique",
    "wof:placetype":"venue"
},
  "geometry": {"coordinates":[-71.3148651123,46.8136863708],"type":"Point"}
}