{
  "type": "Feature",
  "properties": {
    "iso:country":"CA",
    "sg:city":"Kelowna",
    "sg:classifiers":[
        {
            "category":"Real Estate",
            "subcategory":"Real Estate Agent",
            "type":"Services"
        }
    ],
    "sg:phone":"+1 250 860 7500",
    "sg:postcode":"V1Y 9K8",
    "sg:province":"BC",
    "wof:name":"Coldwell Banker Horizon Realty",
    "wof:placetype":"venue"
},
  "geometry": {"coordinates":[-119.467232,49.882118],"type":"Point"}
}