{
  "type": "Feature",
  "properties": {
    "addr:full":"5 Lansdowne Rd N Cambridge ON N1S 2S7",
    "addr:housenumber":"5",
    "addr:postcode":"n1s 2s7",
    "addr:street":"Lansdowne Rd N",
    "iso:country":"CA",
    "sg:address":"5 Lansdowne Rd N",
    "sg:city":"Cambridge",
    "sg:classifiers":[
        {
            "category":"Building & Trades",
            "subcategory":"Construction",
            "type":"Services"
        }
    ],
    "sg:phone":"+1 519 621 5537",
    "sg:postcode":"N1S 2S7",
    "sg:province":"ON",
    "sg:tags":[
        "ceiling"
    ],
    "wof:name":"Ceiling Doctor",
    "wof:placetype":"venue"
},
  "geometry": {"coordinates":[-80.32119,43.358673],"type":"Point"}
}