{
  "type": "Feature",
  "properties": {
    "iso:country":"CA",
    "sg:address":"3073 Boul DE Portland",
    "sg:city":"Sherbrooke",
    "sg:classifiers":[
        {
            "category":"Shopping",
            "subcategory":"Optical Goods",
            "type":"Retail Goods"
        }
    ],
    "sg:phone":"+1 819 346 4494",
    "sg:postcode":"J1L 2Y7",
    "sg:province":"QC",
    "sg:tags":[
        "optician"
    ],
    "wof:name":"Opticienne Marie-Sophia Dion",
    "wof:placetype":"venue"
},
  "geometry": {"coordinates":[-71.949944,45.403675],"type":"Point"}
}