{
  "type": "Feature",
  "properties": {
    "addr:full":"908 Ridge Rd Stoney Creek ON L8J 2Y9",
    "addr:housenumber":"908",
    "addr:postcode":"l8j 2y9",
    "addr:street":"Ridge Rd",
    "iso:country":"CA",
    "sg:address":"908 Ridge Rd",
    "sg:city":"Stoney Creek",
    "sg:classifiers":[
        {
            "category":"Building & Trades",
            "subcategory":"Construction",
            "type":"Services"
        }
    ],
    "sg:phone":"+1 905 643 3612",
    "sg:postcode":"L8J 2Y9",
    "sg:province":"ON",
    "sg:tags":[
        "excavating",
        "contractor"
    ],
    "wof:name":"Mountainview Excavating",
    "wof:placetype":"venue"
},
  "geometry": {"coordinates":[-79.6892166138,43.200050354],"type":"Point"}
}