{
  "type": "Feature",
  "properties": {
    "addr:full":"Calgary AB T3B 4N7",
    "addr:postcode":"t3b 4n7",
    "iso:country":"CA",
    "sg:city":"Calgary",
    "sg:classifiers":[
        {
            "category":"Food & Beverages",
            "subcategory":"Groceries & Convenience Stores",
            "type":"Retail Goods"
        }
    ],
    "sg:phone":"+1 403 288 2535",
    "sg:postcode":"T3B 4N7",
    "sg:province":"AB",
    "wof:name":"Mac's Convenience Stores Ltd",
    "wof:placetype":"venue"
},
  "geometry": {"coordinates":[-114.188896,51.103951],"type":"Point"}
}