{
  "type": "Feature",
  "properties": {
    "addr:full":"1105 13 St SW Calgary AB T3C 1B8",
    "addr:housenumber":"1105",
    "addr:postcode":"t3c 1b8",
    "addr:street":"13 St Sw",
    "iso:country":"CA",
    "sg:address":"1105 13 St SW",
    "sg:city":"Calgary",
    "sg:classifiers":[
        {
            "category":"Shopping",
            "subcategory":"Florist",
            "type":"Retail Goods"
        }
    ],
    "sg:phone":"+1 403 806 7673",
    "sg:postcode":"T3C 1B8",
    "sg:province":"AB",
    "wof:name":"Panda Flowers",
    "wof:placetype":"venue"
},
  "geometry": {"coordinates":[-114.093925,51.043102],"type":"Point"}
}