{
  "type": "Feature",
  "properties": {
    "iso:country":"CA",
    "sg:address":"1807 Drew Rd",
    "sg:city":"Mississauga",
    "sg:classifiers":[
        {
            "category":"Manufacturing",
            "subcategory":"Metals",
            "type":"Manufacturing & Wholesale Goods"
        }
    ],
    "sg:phone":"+1 905 673 1890",
    "sg:postcode":"L5S 1J5",
    "sg:province":"ON",
    "sg:tags":[
        "railing"
    ],
    "wof:name":"Expo Iron Works Ltd",
    "wof:placetype":"venue"
},
  "geometry": {"coordinates":[-79.6743011475,43.686378479],"type":"Point"}
}