{
  "type": "Feature",
  "properties": {
    "addr:full":"Turner Valley AB T0L 2A0",
    "addr:postcode":"t0l 2a0",
    "iso:country":"CA",
    "sg:city":"Turner Valley",
    "sg:classifiers":[
        {
            "category":"Home & Garden",
            "subcategory":"Home Furnishings",
            "type":"Retail Goods"
        }
    ],
    "sg:phone":"+1 403 933 5793",
    "sg:postcode":"T0L 2A0",
    "sg:province":"AB",
    "sg:tags":[
        "kitchen",
        "accessory"
    ],
    "wof:name":"Kitchen Stock",
    "wof:placetype":"venue"
},
  "geometry": {"coordinates":[-114.279083,50.674381],"type":"Point"}
}