{
  "type": "Feature",
  "properties": {
    "addr:full":"687 Griffith St London ON N6K 2S5",
    "addr:housenumber":"687",
    "addr:postcode":"n6k 2s5",
    "addr:street":"Griffith St",
    "iso:country":"CA",
    "sg:address":"687 Griffith St",
    "sg:city":"London",
    "sg:classifiers":[
        {
            "category":"Travel",
            "subcategory":"Hotels & Motels",
            "type":"Entertainment"
        }
    ],
    "sg:phone":"+1 519 657 2554",
    "sg:postcode":"N6K 2S5",
    "sg:province":"ON",
    "sg:tags":[
        "resort",
        "center",
        "skiing"
    ],
    "wof:name":"London Track 3 School",
    "wof:placetype":"venue"
},
  "geometry": {"coordinates":[-81.336754,42.946625],"type":"Point"}
}