{
  "type": "Feature",
  "properties": {
    "iso:country":"CA",
    "sg:city":"Regina",
    "sg:classifiers":[
        {
            "category":"Personal",
            "type":"Services"
        }
    ],
    "sg:phone":"+1 306 761 1048",
    "sg:postcode":"S4V 1C9",
    "sg:province":"SK",
    "sg:tags":[
        "bureau"
    ],
    "wof:name":"All-Ways Home Sitting Svc",
    "wof:placetype":"venue"
},
  "geometry": {"coordinates":[-104.53948211700001,50.4337234497],"type":"Point"}
}