{
  "type": "Feature",
  "properties": {
    "addr:full":"314 Queenston St Winnipeg MB R3N 0W8",
    "addr:housenumber":"314",
    "addr:postcode":"r3n 0w8",
    "addr:street":"Queenston St",
    "iso:country":"CA",
    "sg:address":"314 Queenston St",
    "sg:city":"Winnipeg",
    "sg:classifiers":[
        {
            "category":"Wholesale",
            "subcategory":"Durable Goods & Equipment",
            "type":"Manufacturing & Wholesale Goods"
        }
    ],
    "sg:phone":"+1 204 943 5523",
    "sg:postcode":"R3N 0W8",
    "sg:province":"MB",
    "sg:tags":[
        "representative",
        "manufacturer"
    ],
    "wof:name":"David Freedman Agencies Ltd",
    "wof:placetype":"venue"
},
  "geometry": {"coordinates":[-97.1865692139,49.8689117432],"type":"Point"}
}