{
  "type": "Feature",
  "properties": {
    "iso:country":"CA",
    "sg:city":"Newmarket",
    "sg:classifiers":[
        {
            "category":"Professional",
            "subcategory":"Business Services",
            "type":"Services"
        }
    ],
    "sg:phone":"+1 905 830 6835",
    "sg:postcode":"L3Y 8C6",
    "sg:province":"ON",
    "sg:tags":[
        "water",
        "treatment"
    ],
    "wof:name":"Peak Process Controls Inc",
    "wof:placetype":"venue"
},
  "geometry": {"coordinates":[-79.433617,44.073376],"type":"Point"}
}