{
  "type": "Feature",
  "properties": {
    "addr:full":"Chilliwack BC V2P 1S1",
    "addr:postcode":"v2p 1s1",
    "iso:country":"CA",
    "sg:city":"Chilliwack",
    "sg:classifiers":[
        {
            "category":"Health Services",
            "subcategory":"Doctor",
            "type":"Services"
        }
    ],
    "sg:phone":"+1 604 792 7291",
    "sg:postcode":"V2P 1S1",
    "sg:province":"BC",
    "sg:tags":[
        "physician",
        "surgeon"
    ],
    "wof:name":"Dr Tam Medical Clinic Inc",
    "wof:placetype":"venue"
},
  "geometry": {"coordinates":[-121.95824432400001,49.1686592102],"type":"Point"}
}