{
  "type": "Feature",
  "properties": {
    "addr:full":"1227 Barton St Stoney Creek ON L8E 5G9",
    "addr:housenumber":"1227",
    "addr:postcode":"l8e 5g9",
    "addr:street":"Barton St",
    "iso:country":"CA",
    "sg:address":"1227 Barton St",
    "sg:city":"Stoney Creek",
    "sg:classifiers":[
        {
            "category":"Restaurant",
            "type":"Food & Drink"
        }
    ],
    "sg:phone":"+1 905 545 2445",
    "sg:postcode":"L8E 5G9",
    "sg:province":"ON",
    "wof:name":"Daniel's Restaurant & Tavern",
    "wof:placetype":"venue"
},
  "geometry": {"coordinates":[-79.6533508301,43.2126998901],"type":"Point"}
}