{
  "type": "Feature",
  "properties": {
    "addr:full":"388 William St Cobourg ON K9A 3A2",
    "addr:housenumber":"388",
    "addr:postcode":"k9a 3a2",
    "addr:street":"William St",
    "iso:country":"CA",
    "sg:address":"388 William St",
    "sg:city":"Cobourg",
    "sg:classifiers":[
        {
            "category":"Organizations",
            "subcategory":"Religious Organization",
            "type":"Services"
        }
    ],
    "sg:phone":"+1 905 372 8110",
    "sg:postcode":"K9A 3A2",
    "sg:province":"ON",
    "sg:tags":[
        "church"
    ],
    "wof:name":"St Paul's Lutheran Church",
    "wof:placetype":"venue"
},
  "geometry": {"coordinates":[-78.178284,43.961201],"type":"Point"}
}