{
  "type": "Feature",
  "properties": {
    "addr:full":"1102 4th St Estevan SK S4A 0W7",
    "addr:housenumber":"1102",
    "addr:postcode":"s4a 0w7",
    "addr:street":"4Th St",
    "iso:country":"CA",
    "sg:address":"1102 4th St",
    "sg:city":"Estevan",
    "sg:classifiers":[
        {
            "category":"Government",
            "subcategory":"Office",
            "type":"Public Place"
        }
    ],
    "sg:phone":"+1 306 634 1800",
    "sg:postcode":"S4A 0W7",
    "sg:province":"SK",
    "sg:tags":[
        "village"
    ],
    "wof:name":"City of Estevan",
    "wof:placetype":"venue"
},
  "geometry": {"coordinates":[-102.993217,49.139641],"type":"Point"}
}