{
  "type": "Feature",
  "properties": {
    "addr:full":"108 East St S Sarnia ON N7T 3R1",
    "addr:housenumber":"108",
    "addr:postcode":"n7t 3r1",
    "addr:street":"East St S",
    "iso:country":"CA",
    "sg:address":"108 East St S",
    "sg:city":"Sarnia",
    "sg:classifiers":[
        {
            "category":"Personal",
            "subcategory":"Barber",
            "type":"Services"
        }
    ],
    "sg:phone":"+1 519 336 8566",
    "sg:postcode":"N7T 3R1",
    "sg:province":"ON",
    "wof:name":"Tom Jr's Barber Shop",
    "wof:placetype":"venue"
},
  "geometry": {"coordinates":[-82.386551,42.96973],"type":"Point"}
}