{
  "type": "Feature",
  "properties": {
    "addr:full":"Sparwood BC V0B 2G0",
    "addr:postcode":"bc v0b 2g0",
    "iso:country":"CA",
    "sg:city":"Sparwood",
    "sg:classifiers":[
        {
            "category":"Health Services",
            "subcategory":"Doctor",
            "type":"Services"
        }
    ],
    "sg:phone":"+1 250 425 7081",
    "sg:postcode":"V0B 2G0",
    "sg:province":"BC",
    "sg:tags":[
        "dentist"
    ],
    "wof:name":"Sparwood Dental Clinic",
    "wof:placetype":"venue"
},
  "geometry": {"coordinates":[-114.886696,49.732403],"type":"Point"}
}