{
  "type": "Feature",
  "properties": {
    "addr:full":"2200 Rue Leon-Harmel Quebec QC G1N 4L2",
    "addr:housenumber":"2200",
    "addr:postcode":"g1n 4l2",
    "addr:street":"Rue Leon-Harmel",
    "iso:country":"CA",
    "sg:address":"2200 Rue Leon-Harmel",
    "sg:city":"Quebec",
    "sg:classifiers":[
        {
            "category":"Manufacturing",
            "subcategory":"Paper Products",
            "type":"Manufacturing & Wholesale Goods"
        }
    ],
    "sg:phone":"+1 418 687 1001",
    "sg:postcode":"G1N 4L2",
    "sg:province":"QC",
    "sg:tags":[
        "envelope"
    ],
    "wof:name":"Enveloppes Demers Inc",
    "wof:placetype":"venue"
},
  "geometry": {"coordinates":[-71.2824478149,46.8000946045],"type":"Point"}
}