{
  "type": "Feature",
  "properties": {
    "addr:full":"477 Westwood Dr Winnipeg MB R3K 1G5",
    "addr:housenumber":"477",
    "addr:postcode":"r3k 1g5",
    "addr:street":"Westwood Dr",
    "iso:country":"CA",
    "sg:address":"477 Westwood Dr",
    "sg:city":"Winnipeg",
    "sg:classifiers":[
        {
            "category":"Travel",
            "subcategory":"Hotels & Motels",
            "type":"Entertainment"
        }
    ],
    "sg:phone":"+1 204 837 5871",
    "sg:postcode":"R3K 1G5",
    "sg:province":"MB",
    "wof:name":"Red Lion Inn",
    "wof:placetype":"venue"
},
  "geometry": {"coordinates":[-97.29299899999999,49.879921],"type":"Point"}
}