{
  "type": "Feature",
  "properties": {
    "addr:full":"40 York St London ON N6A 1A5",
    "addr:housenumber":"40",
    "addr:postcode":"n6a 1a5",
    "addr:street":"York St",
    "iso:country":"CA",
    "sg:address":"40 York St",
    "sg:city":"London",
    "sg:classifiers":[
        {
            "category":"Home & Garden",
            "subcategory":"Building Materials",
            "type":"Retail Goods"
        }
    ],
    "sg:phone":"+1 519 433 3501",
    "sg:postcode":"N6A 1A5",
    "sg:province":"ON",
    "sg:tags":[
        "glass",
        "window",
        "plate"
    ],
    "wof:name":"Provincial Glass & Mirror Ltd",
    "wof:placetype":"venue"
},
  "geometry": {"coordinates":[-81.25379180909999,42.9800071716],"type":"Point"}
}