{
  "type": "Feature",
  "properties": {
    "addr:full":"577 Catering Rd Sutton West ON L0E 1R0",
    "addr:housenumber":"577",
    "addr:postcode":"l0e 1r0",
    "addr:street":"Catering Rd",
    "iso:country":"CA",
    "sg:address":"577 Catering Rd",
    "sg:city":"Sutton West",
    "sg:classifiers":[
        {
            "category":"Social Services",
            "subcategory":"Child Care",
            "type":"Services"
        }
    ],
    "sg:phone":"+1 905 722 5818",
    "sg:postcode":"L0E 1R0",
    "sg:province":"ON",
    "wof:name":"Precious Jewels Child Care",
    "wof:placetype":"venue"
},
  "geometry": {"coordinates":[-79.3750457764,44.2851600647],"type":"Point"}
}