{
  "type": "Feature",
  "properties": {
    "iso:country":"CA",
    "sg:address":"441 Talbot St",
    "sg:city":"St Thomas",
    "sg:classifiers":[
        {
            "category":"Shopping",
            "subcategory":"Bicycles & Sporting Goods",
            "type":"Retail Goods"
        }
    ],
    "sg:phone":"+1 519 633 9596",
    "sg:postcode":"N5P 1C1",
    "sg:province":"ON",
    "wof:name":"Edge Sports",
    "wof:placetype":"venue"
},
  "geometry": {"coordinates":[-81.195908,42.779175],"type":"Point"}
}