{
  "type": "Feature",
  "properties": {
    "addr:full":"PO Box 758 STN Main Estevan SK S4A 2A6",
    "addr:housenumber":"po",
    "addr:postcode":"s4a 2a6",
    "addr:street":"Box 758 Stn Main",
    "iso:country":"CA",
    "sg:address":"PO Box 758 STN Main",
    "sg:city":"Estevan",
    "sg:classifiers":[
        {
            "category":"Building & Trades",
            "subcategory":"Plumbing",
            "type":"Services"
        }
    ],
    "sg:phone":"+1 306 634 3333",
    "sg:postcode":"S4A 2A6",
    "sg:province":"SK",
    "sg:tags":[
        "heating",
        "contractor"
    ],
    "wof:name":"Stan's Plumbing & Heating",
    "wof:placetype":"venue"
},
  "geometry": {"coordinates":[-102.993896484,49.1400489807],"type":"Point"}
}