{
  "type": "Feature",
  "properties": {
    "iso:country":"CA",
    "sg:address":"700 St. George Blvd",
    "sg:city":"Moncton",
    "sg:classifiers":[
        {
            "category":"Shopping",
            "subcategory":"Stationery & Office Supplies",
            "type":"Retail Goods"
        }
    ],
    "sg:phone":"+1 506 854 4952",
    "sg:postcode":"E1E 2C6",
    "sg:province":"NB",
    "sg:tags":[
        "educational",
        "material",
        "school"
    ],
    "wof:name":"Scholar's Choice/Moyer's",
    "wof:placetype":"venue"
},
  "geometry": {"coordinates":[-64.8091506958,46.0852928162],"type":"Point"}
}