{
  "type": "Feature",
  "properties": {
    "addr:full":"Drumheller AB T0J 0Y0",
    "addr:postcode":"t0j 0y0",
    "iso:country":"CA",
    "sg:city":"Drumheller",
    "sg:classifiers":[
        {
            "category":"Health Services",
            "subcategory":"Optometrist",
            "type":"Services"
        }
    ],
    "sg:phone":"+1 403 823 4999",
    "sg:postcode":"T0J 0Y0",
    "sg:province":"AB",
    "wof:name":"Erlandson, Robert OD",
    "wof:placetype":"venue"
},
  "geometry": {"coordinates":[-112.707123,51.463978],"type":"Point"}
}