{
  "type": "Feature",
  "properties": {
    "addr:full":"Dorval QC H9P 2V9",
    "addr:postcode":"h9p 2v9",
    "iso:country":"CA",
    "sg:city":"Dorval",
    "sg:classifiers":[
        {
            "category":"Health Services",
            "subcategory":"Doctor",
            "type":"Services"
        }
    ],
    "sg:phone":"+1 514 683 7877",
    "sg:postcode":"H9P 2V9",
    "sg:province":"QC",
    "sg:tags":[
        "clinic",
        "chiropractor"
    ],
    "wof:name":"Mediservice",
    "wof:placetype":"venue"
},
  "geometry": {"coordinates":[-73.7737121582,45.4892539978],"type":"Point"}
}