{
  "type": "Feature",
  "properties": {
    "iso:country":"CA",
    "sg:address":"2701 Eglinton Ave E",
    "sg:city":"Scarborough",
    "sg:classifiers":[
        {
            "category":"Shopping",
            "subcategory":"Discount & Variety Stores",
            "type":"Retail Goods"
        }
    ],
    "sg:phone":"+1 416 266 4001",
    "sg:postcode":"M1K 2S2",
    "sg:province":"ON",
    "wof:name":"Cap's Variety Store",
    "wof:placetype":"venue"
},
  "geometry": {"coordinates":[-79.2494506836,43.7362785339],"type":"Point"}
}