{
  "type": "Feature",
  "properties": {
    "addr:full":"2984 Boul Taschereau # 100 Greenfield Park QC J4V 2G9",
    "addr:housenumber":"2984",
    "addr:postcode":"j4v 2g9",
    "addr:street":"Boul Taschereau # 100;Park",
    "iso:country":"CA",
    "sg:address":"2984 Boul Taschereau # 100",
    "sg:city":"Greenfield Park",
    "sg:classifiers":[
        {
            "category":"Health Services",
            "subcategory":"Optometrist",
            "type":"Services"
        }
    ],
    "sg:phone":"+1 450 466 9978",
    "sg:postcode":"J4V 2G9",
    "sg:province":"QC",
    "wof:name":"Iris Optometristes-Opticiens",
    "wof:placetype":"venue"
},
  "geometry": {"coordinates":[-73.48667907710001,45.4988594055],"type":"Point"}
}