{
  "type": "Feature",
  "properties": {
    "iso:country":"CA",
    "sg:address":"2607 16th Ave W",
    "sg:city":"Vancouver",
    "sg:classifiers":[
        {
            "category":"Personal",
            "type":"Services"
        }
    ],
    "sg:phone":"+1 604 731 7883",
    "sg:postcode":"V6K 3C2",
    "sg:province":"BC",
    "sg:tags":[
        "therapist",
        "massage"
    ],
    "wof:name":"Soma Therapy Ctr",
    "wof:placetype":"venue"
},
  "geometry": {"coordinates":[-123.165092468,49.2578163147],"type":"Point"}
}