{
  "type": "Feature",
  "properties": {
    "addr:full":"438 Victoria Ave Regina SK S4N 0P6",
    "addr:housenumber":"438",
    "addr:postcode":"s4n 0p6",
    "addr:street":"Victoria Ave",
    "iso:country":"CA",
    "sg:address":"438 Victoria Ave",
    "sg:city":"Regina",
    "sg:classifiers":[
        {
            "category":"Shopping",
            "subcategory":"Jewelry",
            "type":"Retail Goods"
        }
    ],
    "sg:phone":"+1 306 546 5626",
    "sg:postcode":"S4N 0P6",
    "sg:province":"SK",
    "sg:tags":[
        "pawnbroker"
    ],
    "wof:name":"AAA Absolute Cash",
    "wof:placetype":"venue"
},
  "geometry": {"coordinates":[-104.587364197,50.4473495483],"type":"Point"}
}