{
  "type": "Feature",
  "properties": {
    "addr:full":"315 Rue Danis Salaberry-DE-Valleyfield QC J6S 1M1",
    "addr:housenumber":"315",
    "addr:postcode":"j6s 1m1",
    "addr:street":"Rue Danis",
    "iso:country":"CA",
    "sg:address":"315 Rue Danis",
    "sg:city":"Salaberry-DE-Valleyfield",
    "sg:classifiers":[
        {
            "category":"Retail",
            "subcategory":"Funeral Services",
            "type":"Services"
        }
    ],
    "sg:phone":"+1 450 373 3511",
    "sg:postcode":"J6S 1M1",
    "sg:province":"QC",
    "sg:tags":[
        "director"
    ],
    "wof:name":"Ernest Montpetit & Fils Inc",
    "wof:placetype":"venue"
},
  "geometry": {"coordinates":[-74.1376495361,45.2635192871],"type":"Point"}
}