{
  "type": "Feature",
  "properties": {
    "addr:full":"735 3E Av Shawinigan-Sud QC G9P 1G3",
    "addr:housenumber":"735",
    "addr:postcode":"g9p 1g3",
    "addr:street":"3E Av Shawinigan-Sud",
    "iso:country":"CA",
    "sg:address":"735 3E Av",
    "sg:city":"Shawinigan-Sud",
    "sg:classifiers":[
        {
            "category":"Food & Beverages",
            "subcategory":"Specialty",
            "type":"Retail Goods"
        }
    ],
    "sg:phone":"+1 819 536 7875",
    "sg:postcode":"G9P 1G3",
    "sg:province":"QC",
    "wof:name":"Shaklee",
    "wof:placetype":"venue"
},
  "geometry": {"coordinates":[-72.75266999999999,46.527149],"type":"Point"}
}