{
  "type": "Feature",
  "properties": {
    "addr:full":"Prescott ON K0E 1T0",
    "addr:postcode":"k0e 1t0",
    "iso:country":"CA",
    "sg:city":"Prescott",
    "sg:classifiers":[
        {
            "category":"Organizations",
            "subcategory":"Religious Organization",
            "type":"Services"
        }
    ],
    "sg:phone":"+1 613 925 5571",
    "sg:postcode":"K0E 1T0",
    "sg:province":"ON",
    "sg:tags":[
        "church"
    ],
    "wof:name":"Johnstown United Church",
    "wof:placetype":"venue"
},
  "geometry": {"coordinates":[-75.5184173584,44.7094192505],"type":"Point"}
}