{
  "type": "Feature",
  "properties": {
    "addr:full":"90 Rue Thibault S Abercorn QC J0E 1B0",
    "addr:housenumber":"90",
    "addr:postcode":"j0e 1b0",
    "addr:street":"Rue Thibault S Abercorn",
    "iso:country":"CA",
    "sg:address":"90 Rue Thibault S",
    "sg:city":"Abercorn",
    "sg:classifiers":[
        {
            "category":"Manufacturing",
            "subcategory":"Lumber",
            "type":"Manufacturing & Wholesale Goods"
        }
    ],
    "sg:phone":"+1 450 538 0126",
    "sg:postcode":"J0E 1B0",
    "sg:province":"QC",
    "sg:tags":[
        "sawmill"
    ],
    "wof:name":"Sciage Nadeau",
    "wof:placetype":"venue"
},
  "geometry": {"coordinates":[-72.662651,45.030277],"type":"Point"}
}