{
  "type": "Feature",
  "properties": {
    "addr:full":"Toronto ON M5H 4B2",
    "addr:postcode":"m5h 4b2",
    "iso:country":"CA",
    "sg:city":"Toronto",
    "sg:classifiers":[
        {
            "category":"Professional",
            "subcategory":"Management & Consulting",
            "type":"Services"
        }
    ],
    "sg:phone":"+1 416 777 1212",
    "sg:postcode":"M5H 4B2",
    "sg:province":"ON",
    "sg:tags":[
        "consultant",
        "computer",
        "business"
    ],
    "wof:name":"Sierra Systems Group Inc",
    "wof:placetype":"venue"
},
  "geometry": {"coordinates":[-79.381371,43.650829],"type":"Point"}
}