{
  "type": "Feature",
  "properties": {
    "iso:country":"CA",
    "sg:address":"11 Mclachlan Dr # A",
    "sg:city":"Etobicoke",
    "sg:classifiers":[
        {
            "category":"Retail",
            "subcategory":"Repair Shop",
            "type":"Services"
        }
    ],
    "sg:phone":"+1 416 675 3099",
    "sg:postcode":"M9W 1E3",
    "sg:province":"ON",
    "sg:tags":[
        "machinery"
    ],
    "wof:name":"Production Contracting Svc Ltd",
    "wof:placetype":"venue"
},
  "geometry": {"coordinates":[-79.585548,43.693661],"type":"Point"}
}