{
  "type": "Feature",
  "properties": {
    "addr:full":"536 Sonora Ave SW Calgary AB T3C 2J9",
    "addr:housenumber":"536",
    "addr:postcode":"t3c 2j9",
    "addr:street":"Sonora Ave Sw",
    "iso:country":"CA",
    "sg:address":"536 Sonora Ave SW",
    "sg:city":"Calgary",
    "sg:classifiers":[
        {
            "category":"Education",
            "subcategory":"School",
            "type":"Public Place"
        }
    ],
    "sg:phone":"+1 403 777 8590",
    "sg:postcode":"T3C 2J9",
    "sg:province":"AB",
    "wof:name":"Sunalta Elementary School",
    "wof:placetype":"venue"
},
  "geometry": {"coordinates":[-114.109459,51.040806],"type":"Point"}
}