{
  "type": "Feature",
  "properties": {
    "addr:full":"2189 Dufferin St York ON M6E 3R9",
    "addr:housenumber":"2189",
    "addr:postcode":"m6e 3r9",
    "addr:street":"Dufferin St",
    "iso:country":"CA",
    "sg:address":"2189 Dufferin St",
    "sg:city":"York",
    "sg:classifiers":[
        {
            "category":"Food & Beverages",
            "subcategory":"Bakery",
            "type":"Retail Goods"
        }
    ],
    "sg:phone":"+1 416 652 8666",
    "sg:postcode":"M6E 3R9",
    "sg:province":"ON",
    "sg:tags":[
        "baker"
    ],
    "wof:name":"Doce Minho Pastry & Bakery",
    "wof:placetype":"venue"
},
  "geometry": {"coordinates":[-79.44781500000001,43.690224],"type":"Point"}
}