{
  "type": "Feature",
  "properties": {
    "addr:full":"375 Glamorgan Cres SW Calgary AB T3E 5B7",
    "addr:housenumber":"375",
    "addr:postcode":"t3e 5b7",
    "addr:street":"Glamorgan Cres Sw",
    "iso:country":"CA",
    "sg:address":"375 Glamorgan Cres SW",
    "sg:city":"Calgary",
    "sg:classifiers":[
        {
            "category":"Building & Trades",
            "subcategory":"Electrical",
            "type":"Services"
        }
    ],
    "sg:phone":"+1 403 242 5527",
    "sg:postcode":"T3E 5B7",
    "sg:province":"AB",
    "sg:tags":[
        "electric",
        "contractor"
    ],
    "wof:name":"Viking Electric Ltd",
    "wof:placetype":"venue"
},
  "geometry": {"coordinates":[-114.15579200000001,51.01049],"type":"Point"}
}