{
  "type": "Feature",
  "properties": {
    "addr:full":"113 Silvercreek Pky N Guelph ON N1H 3T2",
    "addr:housenumber":"113",
    "addr:postcode":"n1h 3t2",
    "addr:street":"Silvercreek Pky N",
    "iso:country":"CA",
    "sg:address":"113 Silvercreek Pky N",
    "sg:city":"Guelph",
    "sg:classifiers":[
        {
            "category":"Food & Beverages",
            "subcategory":"Groceries & Convenience Stores",
            "type":"Retail Goods"
        }
    ],
    "sg:phone":"+1 519 837 1453",
    "sg:postcode":"N1H 3T2",
    "sg:province":"ON",
    "wof:name":"Little Short Stop Stores Ltd",
    "wof:placetype":"venue"
},
  "geometry": {"coordinates":[-80.279724,43.53965],"type":"Point"}
}