{
  "type": "Feature",
  "properties": {
    "iso:country":"CA",
    "sg:address":"675 Development Dr",
    "sg:city":"Kingston",
    "sg:classifiers":[
        {
            "category":"Wholesale",
            "subcategory":"Machinery & Supplies",
            "type":"Manufacturing & Wholesale Goods"
        }
    ],
    "sg:phone":"+1 613 389 4660",
    "sg:postcode":"K7M 4W6",
    "sg:province":"ON",
    "sg:tags":[
        "equipment",
        "railroad"
    ],
    "wof:name":"Knorr Brake Ltd",
    "wof:placetype":"venue"
},
  "geometry": {"coordinates":[-76.57015228269999,44.2415618896],"type":"Point"}
}