{
  "type": "Feature",
  "properties": {
    "addr:full":"146 Rte Du President-Kennedy Beauceville QC G5X 1P4",
    "addr:housenumber":"146",
    "addr:postcode":"g5x 1p4",
    "addr:street":"Rte Du President-Kennedy",
    "iso:country":"CA",
    "sg:address":"146 Rte Du President-Kennedy",
    "sg:city":"Beauceville",
    "sg:classifiers":[
        {
            "category":"Building & Trades",
            "subcategory":"Construction",
            "type":"Services"
        }
    ],
    "sg:phone":"+1 418 774 3873",
    "sg:postcode":"G5X 1P4",
    "sg:province":"QC",
    "sg:tags":[
        "general",
        "contractor"
    ],
    "wof:name":"Constructions Martin Jacques",
    "wof:placetype":"venue"
},
  "geometry": {"coordinates":[-70.818527,46.259579],"type":"Point"}
}