{
  "type": "Feature",
  "properties": {
    "addr:full":"8227 Silver Star Rd Vernon BC V1B 3M8",
    "addr:housenumber":"8227",
    "addr:postcode":"bc v1b 3m8",
    "addr:street":"Silver Star Rd",
    "iso:country":"CA",
    "sg:address":"8227 Silver Star Rd",
    "sg:city":"Vernon",
    "sg:classifiers":[
        {
            "category":"Professional",
            "subcategory":"Business Services",
            "type":"Services"
        }
    ],
    "sg:phone":"+1 250 542 4593",
    "sg:postcode":"V1B 3M8",
    "sg:province":"BC",
    "sg:tags":[
        "reservation",
        "motel",
        "hotel"
    ],
    "wof:name":"Okanagan High Country B & B",
    "wof:placetype":"venue"
},
  "geometry": {"coordinates":[-119.209351,50.308128],"type":"Point"}
}