{
  "type": "Feature",
  "properties": {
    "addr:full":"189 2nd St Winkler MB R6W 3N2",
    "addr:housenumber":"189",
    "addr:postcode":"r6w 3n2",
    "addr:street":"2Nd St",
    "iso:country":"CA",
    "sg:address":"189 2nd St",
    "sg:city":"Winkler",
    "sg:classifiers":[
        {
            "category":"Organizations",
            "subcategory":"Religious Organization",
            "type":"Services"
        }
    ],
    "sg:phone":"+1 204 325 7676",
    "sg:postcode":"R6W 3N2",
    "sg:province":"MB",
    "sg:tags":[
        "church"
    ],
    "wof:name":"Sommerfelder Church",
    "wof:placetype":"venue"
},
  "geometry": {"coordinates":[-97.93476099999999,49.179764],"type":"Point"}
}