{
  "type": "Feature",
  "properties": {
    "iso:country":"CA",
    "sg:city":"Laval",
    "sg:classifiers":[
        {
            "category":"Home & Garden",
            "subcategory":"Home Furnishings",
            "type":"Retail Goods"
        }
    ],
    "sg:phone":"+1 450 681 2228",
    "sg:postcode":"H7W 3Z9",
    "sg:province":"QC",
    "sg:tags":[
        "venetian",
        "curtain",
        "drapery"
    ],
    "wof:name":"Mont D'Or Draperies",
    "wof:placetype":"venue"
},
  "geometry": {"coordinates":[-73.764198,45.534634],"type":"Point"}
}