{
  "type": "Feature",
  "properties": {
    "iso:country":"CA",
    "sg:address":"1430 Youville Dr",
    "sg:city":"Orleans",
    "sg:classifiers":[
        {
            "category":"Retail",
            "subcategory":"Auto Rental",
            "type":"Services"
        }
    ],
    "sg:phone":"+1 613 837 9649",
    "sg:postcode":"K1C 2X8",
    "sg:province":"ON",
    "sg:tags":[
        "renting",
        "automobile",
        "storage"
    ],
    "wof:name":"Budget Car & Truck Rentals",
    "wof:placetype":"venue"
},
  "geometry": {"coordinates":[-75.55070495610001,45.4638977051],"type":"Point"}
}