{
  "type": "Feature",
  "properties": {
    "addr:full":"Toronto ON M5S 2T9",
    "addr:postcode":"m5s 2t9",
    "iso:country":"CA",
    "sg:city":"Toronto",
    "sg:classifiers":[
        {
            "category":"Health Services",
            "subcategory":"Doctor",
            "type":"Services"
        }
    ],
    "sg:phone":"+1 416 928 0920",
    "sg:postcode":"M5S 2T9",
    "sg:province":"ON",
    "sg:tags":[
        "physician",
        "surgeon"
    ],
    "wof:name":"Spadina Health Ctr",
    "wof:placetype":"venue"
},
  "geometry": {"coordinates":[-79.40329,43.665295],"type":"Point"}
}