{
  "type": "Feature",
  "properties": {
    "iso:country":"CA",
    "sg:address":"1145 Rue Du Marche",
    "sg:city":"Acton Vale",
    "sg:classifiers":[
        {
            "category":"Wholesale",
            "subcategory":"Meat",
            "type":"Manufacturing & Wholesale Goods"
        }
    ],
    "sg:phone":"+1 450 546 2759",
    "sg:postcode":"J0H 1A0",
    "sg:province":"QC",
    "sg:tags":[
        "grocer",
        "butchering"
    ],
    "wof:name":"Marche Guilmain Inc",
    "wof:placetype":"venue"
},
  "geometry": {"coordinates":[-72.5667877197,45.6502799988],"type":"Point"}
}