{
  "type": "Feature",
  "properties": {
    "addr:full":"87 Rue Saint-Jacques Saint-Jacques QC J0K 2R0",
    "addr:housenumber":"87",
    "addr:postcode":"j0k 2r0",
    "addr:street":"Rue Saint-Jacques",
    "iso:country":"CA",
    "sg:address":"87 Rue Saint-Jacques",
    "sg:city":"Saint-Jacques",
    "sg:classifiers":[
        {
            "category":"Restaurant",
            "type":"Food & Drink"
        }
    ],
    "sg:phone":"+1 450 839 3923",
    "sg:postcode":"J0K 2R0",
    "sg:province":"QC",
    "wof:name":"Restaurant LA Bonne Fourchette",
    "wof:placetype":"venue"
},
  "geometry": {"coordinates":[-73.57079299999999,45.948044],"type":"Point"}
}