{
  "type": "Feature",
  "properties": {
    "addr:full":"Qualicum Beach BC V9K 1S7",
    "addr:postcode":"v9k 1s7",
    "iso:country":"CA",
    "sg:city":"Qualicum Beach",
    "sg:classifiers":[
        {
            "category":"Personal",
            "subcategory":"Beauty Salon",
            "type":"Services"
        }
    ],
    "sg:phone":"+1 250 752 3551",
    "sg:postcode":"V9K 1S7",
    "sg:province":"BC",
    "wof:name":"Expressions Hair Salon",
    "wof:placetype":"venue"
},
  "geometry": {"coordinates":[-124.446266174,49.3473320007],"type":"Point"}
}