{
  "type": "Feature",
  "properties": {
    "addr:full":"35 Rue Saint-Louis Sainte-Agathe-Des-Monts QC J8C 2A2",
    "addr:housenumber":"35",
    "addr:postcode":"j8c 2a2",
    "addr:street":"Rue Saint-Louis",
    "iso:country":"CA",
    "sg:address":"35 Rue Saint-Louis",
    "sg:city":"Sainte-Agathe-Des-Monts",
    "sg:classifiers":[
        {
            "category":"Health Services",
            "subcategory":"Health Practitioner",
            "type":"Services"
        }
    ],
    "sg:phone":"+1 819 324 1174",
    "sg:postcode":"J8C 2A2",
    "sg:province":"QC",
    "sg:tags":[
        "psychologist"
    ],
    "wof:name":"Rochon, Jean-Pierre",
    "wof:placetype":"venue"
},
  "geometry": {"coordinates":[-74.289085,46.04805],"type":"Point"}
}