{
  "type": "Feature",
  "properties": {
    "addr:full":"980 Dufferin St Toronto ON M6H 4B4",
    "addr:housenumber":"980",
    "addr:postcode":"m6h 4b4",
    "addr:street":"Dufferin St",
    "iso:country":"CA",
    "sg:address":"980 Dufferin St",
    "sg:city":"Toronto",
    "sg:classifiers":[
        {
            "category":"Education",
            "subcategory":"School",
            "type":"Public Place"
        }
    ],
    "sg:phone":"+1 416 393 0400",
    "sg:postcode":"M6H 4B4",
    "sg:province":"ON",
    "wof:name":"Kent Sr Public School",
    "wof:placetype":"venue"
},
  "geometry": {"coordinates":[-79.43524169920001,43.6590995789],"type":"Point"}
}