{
  "type": "Feature",
  "properties": {
    "addr:full":"Quesnel BC V2J 6P3",
    "addr:postcode":"v2j 6p3",
    "iso:country":"CA",
    "sg:city":"Quesnel",
    "sg:classifiers":[
        {
            "category":"Manufacturing",
            "subcategory":"Printing",
            "type":"Manufacturing & Wholesale Goods"
        }
    ],
    "sg:phone":"+1 250 992 7292",
    "sg:postcode":"V2J 6P3",
    "sg:province":"BC",
    "sg:tags":[
        "screen"
    ],
    "wof:name":"Excel Specialties",
    "wof:placetype":"venue"
},
  "geometry": {"coordinates":[-122.516990662,52.9639129639],"type":"Point"}
}