{
  "type": "Feature",
  "properties": {
    "addr:full":"2565 Ch Acadie Cap-Pele NB E4N 1B8",
    "addr:housenumber":"2565",
    "addr:postcode":"e4n 1b8",
    "addr:street":"Ch Acadie",
    "iso:country":"CA",
    "sg:address":"2565 Ch Acadie",
    "sg:city":"Cap-Pele",
    "sg:classifiers":[
        {
            "category":"Wholesale",
            "subcategory":"Scrap",
            "type":"Manufacturing & Wholesale Goods"
        }
    ],
    "sg:phone":"+1 506 577 4698",
    "sg:postcode":"E4N 1B8",
    "sg:province":"NB",
    "sg:tags":[
        "recycling",
        "can",
        "bottle",
        "depot"
    ],
    "wof:name":"Al's Bottle Exchange",
    "wof:placetype":"venue"
},
  "geometry": {"coordinates":[-64.28270721440001,46.2163925171],"type":"Point"}
}