{
  "type": "Feature",
  "properties": {
    "addr:full":"Warwick QC J0A 1M0",
    "addr:postcode":"j0a 1m0",
    "iso:country":"CA",
    "sg:city":"Warwick",
    "sg:classifiers":[
        {
            "category":"Government",
            "subcategory":"Office",
            "type":"Public Place"
        }
    ],
    "sg:phone":"+1 819 358 4342",
    "sg:postcode":"J0A 1M0",
    "sg:province":"QC",
    "sg:tags":[
        "village"
    ],
    "wof:name":"Salle Du Canton Warwick",
    "wof:placetype":"venue"
},
  "geometry": {"coordinates":[-71.99253845210001,45.9353141785],"type":"Point"}
}