{
  "type": "Feature",
  "properties": {
    "addr:full":"1015 8th Ave W Vancouver BC V6H 1C3",
    "addr:housenumber":"1015",
    "addr:postcode":"v6h 1c3",
    "addr:street":"8Th Ave W",
    "iso:country":"CA",
    "sg:address":"1015 8th Ave W",
    "sg:city":"Vancouver",
    "sg:classifiers":[
        {
            "category":"Organizations",
            "subcategory":"Religious Organization",
            "type":"Services"
        }
    ],
    "sg:phone":"+1 604 731 2151",
    "sg:postcode":"V6H 1C3",
    "sg:province":"BC",
    "sg:tags":[
        "church"
    ],
    "wof:name":"Jehovah's Witnesses",
    "wof:placetype":"venue"
},
  "geometry": {"coordinates":[-123.12711299999999,49.264477],"type":"Point"}
}