{
  "type": "Feature",
  "properties": {
    "addr:full":"Winnipeg MB R3J 0K8",
    "addr:postcode":"r3j 0k8",
    "iso:country":"CA",
    "sg:city":"Winnipeg",
    "sg:classifiers":[
        {
            "category":"Professional",
            "subcategory":"Accounting & Tax Preparation",
            "type":"Services"
        }
    ],
    "sg:phone":"+1 204 832 2042",
    "sg:postcode":"R3J 0K8",
    "sg:province":"MB",
    "sg:tags":[
        "accountant"
    ],
    "wof:name":"H H Driedger & Assoc",
    "wof:placetype":"venue"
},
  "geometry": {"coordinates":[-97.2299423218,49.877696991],"type":"Point"}
}