{
  "type": "Feature",
  "properties": {
    "addr:full":"984 Cristina Crt Mississauga ON L5J 4S1",
    "addr:housenumber":"984",
    "addr:postcode":"l5j 4s1",
    "addr:street":"Cristina Crt",
    "iso:country":"CA",
    "sg:address":"984 Cristina Crt",
    "sg:city":"Mississauga",
    "sg:classifiers":[
        {
            "category":"Building & Trades",
            "subcategory":"Construction",
            "type":"Services"
        }
    ],
    "sg:phone":"+1 905 855 3700",
    "sg:postcode":"L5J 4S1",
    "sg:province":"ON",
    "sg:tags":[
        "contractor"
    ],
    "wof:name":"Easton Homes Inc",
    "wof:placetype":"venue"
},
  "geometry": {"coordinates":[-79.61511230470001,43.5226249695],"type":"Point"}
}