{
  "type": "Feature",
  "properties": {
    "addr:full":"112 Lakeshore Dr North Bay ON P1A 2A8",
    "addr:housenumber":"112",
    "addr:postcode":"p1a 2a8",
    "addr:street":"Lakeshore Dr",
    "iso:country":"CA",
    "sg:address":"112 Lakeshore Dr",
    "sg:city":"North Bay",
    "sg:classifiers":[
        {
            "category":"Health Services",
            "subcategory":"Optometrist",
            "type":"Services"
        }
    ],
    "sg:phone":"+1 705 495 2022",
    "sg:postcode":"P1A 2A8",
    "sg:province":"ON",
    "wof:name":"Cobean, Michael J OD",
    "wof:placetype":"venue"
},
  "geometry": {"coordinates":[-79.452545,46.2915],"type":"Point"}
}