{
  "type": "Feature",
  "properties": {
    "addr:full":"25 Kinnear Crt Richmond Hill ON L4B 1H9",
    "addr:housenumber":"25",
    "addr:postcode":"l4b 1h9",
    "addr:street":"Kinnear Crt",
    "iso:country":"CA",
    "sg:address":"25 Kinnear Crt",
    "sg:city":"Richmond Hill",
    "sg:classifiers":[
        {
            "category":"Building & Trades",
            "subcategory":"Construction",
            "type":"Services"
        }
    ],
    "sg:phone":"+1 905 889 0999",
    "sg:postcode":"L4B 1H9",
    "sg:province":"ON",
    "sg:tags":[
        "home",
        "general",
        "improvement",
        "contractor"
    ],
    "wof:name":"Hallmark Designer Basements",
    "wof:placetype":"venue"
},
  "geometry": {"coordinates":[-79.387046814,43.8532142639],"type":"Point"}
}