{
  "type": "Feature",
  "properties": {
    "addr:full":"711 Division St Cobourg ON K9A 3T1",
    "addr:housenumber":"711",
    "addr:postcode":"k9a 3t1",
    "addr:street":"Division St",
    "iso:country":"CA",
    "sg:address":"711 Division St",
    "sg:city":"Cobourg",
    "sg:classifiers":[
        {
            "category":"Personal",
            "subcategory":"Beauty Salon",
            "type":"Services"
        }
    ],
    "sg:phone":"+1 905 372 3025",
    "sg:postcode":"K9A 3T1",
    "sg:province":"ON",
    "wof:name":"Diane's Coiffures",
    "wof:placetype":"venue"
},
  "geometry": {"coordinates":[-78.17063903810001,43.9709510803],"type":"Point"}
}