{
  "type": "Feature",
  "properties": {
    "addr:full":"2 Church St Carbonear NL A1Y 1A9",
    "addr:housenumber":"2",
    "addr:postcode":"a1y 1a9",
    "addr:street":"Church St",
    "iso:country":"CA",
    "sg:address":"2 Church St",
    "sg:city":"Carbonear",
    "sg:classifiers":[
        {
            "category":"Organizations",
            "subcategory":"Religious Organization",
            "type":"Services"
        }
    ],
    "sg:phone":"+1 709 596 6754",
    "sg:postcode":"A1Y 1A9",
    "sg:province":"NL",
    "sg:tags":[
        "church"
    ],
    "wof:name":"Carbonear United Church",
    "wof:placetype":"venue"
},
  "geometry": {"coordinates":[-53.2294998169,47.7363815308],"type":"Point"}
}