{
  "type": "Feature",
  "properties": {
    "iso:country":"CA",
    "sg:address":"29 Park Ave",
    "sg:city":"Lac Du Bonnet",
    "sg:classifiers":[
        {
            "category":"Shopping",
            "subcategory":"Pharmacy",
            "type":"Retail Goods"
        }
    ],
    "sg:phone":"+1 204 345 2232",
    "sg:postcode":"R0E 1A0",
    "sg:province":"MB",
    "wof:name":"Ingham Pharmacy",
    "wof:placetype":"venue"
},
  "geometry": {"coordinates":[-96.05927276609999,50.2574615479],"type":"Point"}
}