{
  "type": "Feature",
  "properties": {
    "addr:full":"North York ON M2J 5B3",
    "addr:postcode":"m2j 5b3",
    "iso:country":"CA",
    "sg:city":"North York",
    "sg:classifiers":[
        {
            "category":"Professional",
            "subcategory":"Management & Consulting",
            "type":"Services"
        }
    ],
    "sg:phone":"+1 416 499 9506",
    "sg:postcode":"M2J 5B3",
    "sg:province":"ON",
    "sg:tags":[
        "consultant",
        "business"
    ],
    "wof:name":"International Business",
    "wof:placetype":"venue"
},
  "geometry": {"coordinates":[-79.330276,43.775124],"type":"Point"}
}