{
  "type": "Feature",
  "properties": {
    "addr:full":"43193 Hwy 8 Seaforth ON N0K 1W0",
    "addr:housenumber":"43193",
    "addr:postcode":"n0k 1w0",
    "addr:street":"Hwy 8",
    "iso:country":"CA",
    "sg:address":"43193 Hwy 8",
    "sg:city":"Seaforth",
    "sg:classifiers":[
        {
            "category":"Farming",
            "subcategory":"Farm",
            "type":"Manufacturing & Wholesale Goods"
        }
    ],
    "sg:phone":"+1 519 522 1795",
    "sg:postcode":"N0K 1W0",
    "sg:province":"ON",
    "wof:name":"Arts Farms Ltd",
    "wof:placetype":"venue"
},
  "geometry": {"coordinates":[-81.392807,43.553169],"type":"Point"}
}