{
  "type": "Feature",
  "properties": {
    "addr:full":"11801 100 St # 1 Grande Prairie AB T8V 3Y2",
    "addr:housenumber":"11801",
    "addr:postcode":"t8v 3y2",
    "addr:street":"100 St # 1",
    "iso:country":"CA",
    "sg:address":"11801 100 St # 1",
    "sg:city":"Grande Prairie",
    "sg:classifiers":[
        {
            "category":"Shopping",
            "subcategory":"Department Store",
            "type":"Retail Goods"
        }
    ],
    "sg:phone":"+1 780 532 0212",
    "sg:postcode":"T8V 3Y2",
    "sg:province":"AB",
    "wof:name":"Zellers",
    "wof:placetype":"venue"
},
  "geometry": {"coordinates":[-118.794456,55.186874],"type":"Point"}
}