{
  "type": "Feature",
  "properties": {
    "addr:full":"9117 82 Ave NW Edmonton AB T6C 0Z4",
    "addr:housenumber":"9117",
    "addr:postcode":"t6c 0z4",
    "addr:street":"82 Ave Nw",
    "iso:country":"CA",
    "sg:address":"9117 82 Ave NW",
    "sg:city":"Edmonton",
    "sg:classifiers":[
        {
            "category":"Health Services",
            "subcategory":"Doctor",
            "type":"Services"
        }
    ],
    "sg:phone":"+1 780 450 1200",
    "sg:postcode":"T6C 0Z4",
    "sg:province":"AB",
    "sg:tags":[
        "physician",
        "surgeon"
    ],
    "wof:name":"Popke, M MD",
    "wof:placetype":"venue"
},
  "geometry": {"coordinates":[-113.46787999999999,53.517803],"type":"Point"}
}