{
  "type": "Feature",
  "properties": {
    "addr:full":"PO Box 689 Hudson's Hope BC V0C 1V0",
    "addr:housenumber":"po",
    "addr:postcode":"bc v0c 1v0",
    "addr:street":"Box 689",
    "iso:country":"CA",
    "sg:address":"PO Box 689",
    "sg:city":"Hudson's Hope",
    "sg:classifiers":[
        {
            "category":"Building & Trades",
            "subcategory":"Construction",
            "type":"Services"
        }
    ],
    "sg:phone":"+1 250 783 5555",
    "sg:postcode":"V0C 1V0",
    "sg:province":"BC",
    "sg:tags":[
        "general",
        "contractor"
    ],
    "wof:name":"B Parson Rebar Placing",
    "wof:placetype":"venue"
},
  "geometry": {"coordinates":[-126.555511,54.485668],"type":"Point"}
}