{
  "type": "Feature",
  "properties": {
    "addr:full":"22 Fielding Ave Dartmouth NS B3B 1E2",
    "addr:housenumber":"22",
    "addr:postcode":"b3b 1e2",
    "addr:street":"Fielding Ave",
    "iso:country":"CA",
    "sg:address":"22 Fielding Ave",
    "sg:city":"Dartmouth",
    "sg:classifiers":[
        {
            "category":"Building & Trades",
            "subcategory":"Construction",
            "type":"Services"
        }
    ],
    "sg:phone":"+1 902 468 5000",
    "sg:postcode":"B3B 1E2",
    "sg:province":"NS",
    "sg:tags":[
        "general",
        "contractor"
    ],
    "wof:name":"J W Lindsay Enterprises Ltd",
    "wof:placetype":"venue"
},
  "geometry": {"coordinates":[-63.6014862061,44.7053375244],"type":"Point"}
}