{
  "type": "Feature",
  "properties": {
    "iso:country":"CA",
    "sg:address":"550 Barlow Ave",
    "sg:city":"Quesnel",
    "sg:classifiers":[
        {
            "category":"Recreation",
            "type":"Entertainment"
        }
    ],
    "sg:phone":"+1 250 992 5813",
    "sg:postcode":"V2J 2C4",
    "sg:province":"BC",
    "sg:tags":[
        "club",
        "curling"
    ],
    "wof:name":"Quesnel Curling Club",
    "wof:placetype":"venue"
},
  "geometry": {"coordinates":[-122.491333008,52.977519989],"type":"Point"}
}