{
  "type": "Feature",
  "properties": {
    "iso:country":"CA",
    "sg:city":"Oakville",
    "sg:classifiers":[
        {
            "category":"Insurance",
            "subcategory":"Insurance Agent",
            "type":"Services"
        }
    ],
    "sg:phone":"+1 905 829 5200",
    "sg:postcode":"L6J 7K1",
    "sg:province":"ON",
    "wof:name":"Hal Mayer Insurance Agcy",
    "wof:placetype":"venue"
},
  "geometry": {"coordinates":[-79.666435,43.504433],"type":"Point"}
}