{
  "type": "Feature",
  "properties": {
    "addr:full":"4831 49 St Innisfail AB T4G 1N2",
    "addr:housenumber":"4831",
    "addr:postcode":"t4g 1n2",
    "addr:street":"49 St",
    "iso:country":"CA",
    "sg:address":"4831 49 St",
    "sg:city":"Innisfail",
    "sg:classifiers":[
        {
            "category":"Professional",
            "subcategory":"Business Services",
            "type":"Services"
        }
    ],
    "sg:phone":"+1 403 227 1478",
    "sg:postcode":"T4G 1N2",
    "sg:province":"AB",
    "sg:tags":[
        "water",
        "treatment"
    ],
    "wof:name":"Pro-Water Conditioning",
    "wof:placetype":"venue"
},
  "geometry": {"coordinates":[-113.945564,52.026325],"type":"Point"}
}