{
  "type": "Feature",
  "properties": {
    "iso:country":"CA",
    "sg:address":"109 Queens Quay W",
    "sg:city":"Toronto",
    "sg:classifiers":[
        {
            "category":"Real Estate",
            "subcategory":"Real Estate Agent",
            "type":"Services"
        }
    ],
    "sg:phone":"+1 416 203 1920",
    "sg:postcode":"M5J 2T5",
    "sg:province":"ON",
    "wof:name":"Harbourside Realty Corp",
    "wof:placetype":"venue"
},
  "geometry": {"coordinates":[-79.37827301030001,43.6403808594],"type":"Point"}
}