{
  "type": "Feature",
  "properties": {
    "addr:full":"880 Notre Dame Ave Winnipeg MB R3E 0M7",
    "addr:housenumber":"880",
    "addr:postcode":"r3e 0m7",
    "addr:street":"Notre Dame Ave",
    "iso:country":"CA",
    "sg:address":"880 Notre Dame Ave",
    "sg:city":"Winnipeg",
    "sg:classifiers":[
        {
            "category":"Wholesale",
            "subcategory":"Machinery & Supplies",
            "type":"Manufacturing & Wholesale Goods"
        }
    ],
    "sg:phone":"+1 204 783 9996",
    "sg:postcode":"R3E 0M7",
    "sg:province":"MB",
    "sg:tags":[
        "salon",
        "beauty"
    ],
    "wof:name":"Aesthetic Products",
    "wof:placetype":"venue"
},
  "geometry": {"coordinates":[-97.16742706300001,49.9037666321],"type":"Point"}
}