{
  "type": "Feature",
  "properties": {
    "addr:full":"93 Arthur St St Catharines ON L2M 1H5",
    "addr:housenumber":"93",
    "addr:postcode":"l2m 1h5",
    "addr:street":"Arthur St",
    "iso:country":"CA",
    "sg:address":"93 Arthur St",
    "sg:city":"St Catharines",
    "sg:classifiers":[
        {
            "category":"Restaurant",
            "type":"Food & Drink"
        }
    ],
    "sg:phone":"+1 905 646 4000",
    "sg:postcode":"L2M 1H5",
    "sg:province":"ON",
    "wof:name":"Valley Restaurant & Tavern",
    "wof:placetype":"venue"
},
  "geometry": {"coordinates":[-79.22273254389999,43.2209014893],"type":"Point"}
}