{
  "type": "Feature",
  "properties": {
    "addr:full":"287 Gravely St Cobourg ON K9A 1H8",
    "addr:housenumber":"287",
    "addr:postcode":"k9a 1h8",
    "addr:street":"Gravely St",
    "iso:country":"CA",
    "sg:address":"287 Gravely St",
    "sg:city":"Cobourg",
    "sg:classifiers":[
        {
            "category":"Education",
            "subcategory":"School",
            "type":"Public Place"
        }
    ],
    "sg:phone":"+1 905 372 9752",
    "sg:postcode":"K9A 1H8",
    "sg:province":"ON",
    "wof:name":"C R Gummow Public School",
    "wof:placetype":"venue"
},
  "geometry": {"coordinates":[-78.1560745239,43.965385437],"type":"Point"}
}