{
  "type": "Feature",
  "properties": {
    "addr:full":"242 Pall Mall St London ON N6A 5P6",
    "addr:housenumber":"242",
    "addr:postcode":"n6a 5p6",
    "addr:street":"Pall Mall St",
    "iso:country":"CA",
    "sg:address":"242 Pall Mall St",
    "sg:city":"London",
    "sg:classifiers":[
        {
            "category":"Travel",
            "subcategory":"Hotels & Motels",
            "type":"Entertainment"
        }
    ],
    "sg:phone":"+1 519 642 4444",
    "sg:postcode":"N6A 5P6",
    "sg:province":"ON",
    "wof:name":"Station Park All Suite Hotel",
    "wof:placetype":"venue"
},
  "geometry": {"coordinates":[-81.2499923706,42.9930000305],"type":"Point"}
}