{
  "type": "Feature",
  "properties": {
    "iso:country":"CA",
    "sg:address":"49 Caster Ave",
    "sg:city":"Woodbridge",
    "sg:classifiers":[
        {
            "category":"Wholesale",
            "subcategory":"Non-durable Goods",
            "type":"Manufacturing & Wholesale Goods"
        }
    ],
    "sg:phone":"+1 905 856 6500",
    "sg:postcode":"L4L 5Z2",
    "sg:province":"ON",
    "sg:tags":[
        "plaster",
        "product"
    ],
    "wof:name":"Creative Ceiling Design Inc",
    "wof:placetype":"venue"
},
  "geometry": {"coordinates":[-79.557510376,43.7841720581],"type":"Point"}
}