{
  "type": "Feature",
  "properties": {
    "iso:country":"CA",
    "sg:city":"Calgary",
    "sg:classifiers":[
        {
            "category":"Mining & Drilling",
            "type":"Manufacturing & Wholesale Goods"
        }
    ],
    "sg:phone":"+1 403 266 0908",
    "sg:postcode":"T2P 3G2",
    "sg:province":"AB",
    "sg:tags":[
        "field",
        "oil"
    ],
    "wof:name":"Integrated Production Svc Inc",
    "wof:placetype":"venue"
},
  "geometry": {"coordinates":[-114.079772949,51.0471000671],"type":"Point"}
}