{
  "type": "Feature",
  "properties": {
    "addr:full":"1135 Keewatin St Winnipeg MB R2X 2Z3",
    "addr:housenumber":"1135",
    "addr:postcode":"r2x 2z3",
    "addr:street":"Keewatin St",
    "iso:country":"CA",
    "sg:address":"1135 Keewatin St",
    "sg:city":"Winnipeg",
    "sg:classifiers":[
        {
            "category":"Organizations",
            "subcategory":"Labor Organization",
            "type":"Services"
        }
    ],
    "sg:phone":"+1 204 987 9200",
    "sg:postcode":"R2X 2Z3",
    "sg:province":"MB",
    "wof:name":"International Brotherhood-Blr",
    "wof:placetype":"venue"
},
  "geometry": {"coordinates":[-97.194885,49.949604],"type":"Point"}
}