{
  "type": "Feature",
  "properties": {
    "iso:country":"CA",
    "sg:city":"Mississauga",
    "sg:classifiers":[
        {
            "category":"Shopping",
            "subcategory":"Optical Goods",
            "type":"Retail Goods"
        }
    ],
    "sg:phone":"+1 905 566 0514",
    "sg:postcode":"L4Y 4G6",
    "sg:province":"ON",
    "sg:tags":[
        "optician"
    ],
    "wof:name":"Advance Optical",
    "wof:placetype":"venue"
},
  "geometry": {"coordinates":[-79.59491,43.599037],"type":"Point"}
}