{
  "type": "Feature",
  "properties": {
    "iso:country":"CA",
    "sg:address":"1651 Lakeshore Rd W",
    "sg:city":"Mississauga",
    "sg:classifiers":[
        {
            "category":"Shopping",
            "subcategory":"Florist",
            "type":"Retail Goods"
        }
    ],
    "sg:phone":"+1 905 855 0677",
    "sg:postcode":"L5J 1J4",
    "sg:province":"ON",
    "wof:name":"Pandora's Box",
    "wof:placetype":"venue"
},
  "geometry": {"coordinates":[-79.620766,43.51968],"type":"Point"}
}