{
  "type": "Feature",
  "properties": {
    "addr:full":"101 Oven Head Rd Bethel NB E5C 1S3",
    "addr:housenumber":"101",
    "addr:postcode":"e5c 1s3",
    "addr:street":"Oven Head Rd",
    "iso:country":"CA",
    "sg:address":"101 Oven Head Rd",
    "sg:city":"Bethel",
    "sg:classifiers":[
        {
            "category":"Manufacturing",
            "subcategory":"Food",
            "type":"Manufacturing & Wholesale Goods"
        }
    ],
    "sg:phone":"+1 506 755 2507",
    "sg:postcode":"E5C 1S3",
    "sg:province":"NB",
    "sg:tags":[
        "seafood",
        "product",
        "fish",
        "prepared"
    ],
    "wof:name":"Oven Head Salmon Smokers",
    "wof:placetype":"venue"
},
  "geometry": {"coordinates":[-66.911537,45.157028],"type":"Point"}
}