{
  "type": "Feature",
  "properties": {
    "addr:full":"Marystown NL A0E 2M0",
    "addr:postcode":"a0e 2m0",
    "iso:country":"CA",
    "sg:city":"Marystown",
    "sg:classifiers":[
        {
            "category":"Freight",
            "type":"Transportation"
        }
    ],
    "sg:phone":"+1 709 279 6767",
    "sg:postcode":"A0E 2M0",
    "sg:province":"NL",
    "sg:tags":[
        "trucking"
    ],
    "wof:name":"Island Wide Construction-Trans",
    "wof:placetype":"venue"
},
  "geometry": {"coordinates":[-55.1570014954,47.1637496948],"type":"Point"}
}