{
  "type": "Feature",
  "properties": {
    "addr:full":"Nelson BC V1L 4C1",
    "addr:postcode":"bc v1l 4c1",
    "iso:country":"CA",
    "sg:city":"Nelson",
    "sg:classifiers":[
        {
            "category":"Manufacturing",
            "subcategory":"Tools & Machinery",
            "type":"Manufacturing & Wholesale Goods"
        }
    ],
    "sg:phone":"+1 250 352 2123",
    "sg:postcode":"V1L 4C1",
    "sg:province":"BC",
    "sg:tags":[
        "machine",
        "shop"
    ],
    "wof:name":"West Kootenay Machine Shop",
    "wof:placetype":"venue"
},
  "geometry": {"coordinates":[-117.29155731199999,49.496257782],"type":"Point"}
}