{
  "type": "Feature",
  "properties": {
    "addr:full":"3307 Pasqua St Regina SK S4S 7G8",
    "addr:housenumber":"3307",
    "addr:postcode":"s4s 7g8",
    "addr:street":"Pasqua St",
    "iso:country":"CA",
    "sg:address":"3307 Pasqua St",
    "sg:city":"Regina",
    "sg:classifiers":[
        {
            "category":"Organizations",
            "subcategory":"Religious Organization",
            "type":"Services"
        }
    ],
    "sg:phone":"+1 306 585 1466",
    "sg:postcode":"S4S 7G8",
    "sg:province":"SK",
    "sg:tags":[
        "church"
    ],
    "wof:name":"Hindu Samaj of Southern Sask",
    "wof:placetype":"venue"
},
  "geometry": {"coordinates":[-104.640739,50.426224],"type":"Point"}
}