{
  "type": "Feature",
  "properties": {
    "addr:full":"720 Ossington Ave Toronto ON M6G 3T7",
    "addr:housenumber":"720",
    "addr:postcode":"m6g 3t7",
    "addr:street":"Ossington Ave",
    "iso:country":"CA",
    "sg:address":"720 Ossington Ave",
    "sg:city":"Toronto",
    "sg:classifiers":[
        {
            "category":"Organizations",
            "subcategory":"Religious Organization",
            "type":"Services"
        }
    ],
    "sg:phone":"+1 416 533 5091",
    "sg:postcode":"M6G 3T7",
    "sg:province":"ON",
    "sg:tags":[
        "church"
    ],
    "wof:name":"Ossington Avenue Baptist Chr",
    "wof:placetype":"venue"
},
  "geometry": {"coordinates":[-79.4256057739,43.6613807678],"type":"Point"}
}