{
  "type": "Feature",
  "properties": {
    "addr:full":"265 Rue Saint-Felix Drummondville QC J2C 5M1",
    "addr:housenumber":"265",
    "addr:postcode":"j2c 5m1",
    "addr:street":"Rue Saint-Felix",
    "iso:country":"CA",
    "sg:address":"265 Rue Saint-Felix",
    "sg:city":"Drummondville",
    "sg:classifiers":[
        {
            "category":"Education",
            "subcategory":"School",
            "type":"Public Place"
        }
    ],
    "sg:phone":"+1 819 478 6600",
    "sg:postcode":"J2C 5M1",
    "sg:province":"QC",
    "wof:name":"Polyvalente Marie-Rivier",
    "wof:placetype":"venue"
},
  "geometry": {"coordinates":[-72.501808,45.898163],"type":"Point"}
}