{
  "type": "Feature",
  "properties": {
    "iso:country":"CA",
    "sg:address":"340 Route 173",
    "sg:city":"Saint-Theophile",
    "sg:classifiers":[
        {
            "category":"Manufacturing",
            "subcategory":"Lumber",
            "type":"Manufacturing & Wholesale Goods"
        }
    ],
    "sg:phone":"+1 418 597 3388",
    "sg:postcode":"G0M 2A0",
    "sg:province":"QC",
    "sg:tags":[
        "sawmill"
    ],
    "wof:name":"Industries Maibec Inc",
    "wof:placetype":"venue"
},
  "geometry": {"coordinates":[-70.3980636597,45.8067131042],"type":"Point"}
}