{
  "type": "Feature",
  "properties": {
    "addr:full":"RR 1 Carvel AB T0E 0H0",
    "addr:postcode":"t0e 0h0",
    "addr:street":"Rr 1",
    "iso:country":"CA",
    "sg:address":"RR 1",
    "sg:city":"Carvel",
    "sg:classifiers":[
        {
            "category":"Professional",
            "subcategory":"Management & Consulting",
            "type":"Services"
        }
    ],
    "sg:phone":"+1 780 892 3594",
    "sg:postcode":"T0E 0H0",
    "sg:province":"AB",
    "sg:tags":[
        "consultant",
        "energy",
        "conservation"
    ],
    "wof:name":"Information Technology Specs",
    "wof:placetype":"venue"
},
  "geometry": {"coordinates":[-114.128013611,53.5412406921],"type":"Point"}
}