{
  "type": "Feature",
  "properties": {
    "addr:full":"Nisku AB T9E 7Y8",
    "addr:postcode":"t9e 7y8",
    "iso:country":"CA",
    "sg:city":"Nisku",
    "sg:classifiers":[
        {
            "category":"Wholesale",
            "subcategory":"Hardware",
            "type":"Manufacturing & Wholesale Goods"
        }
    ],
    "sg:phone":"+1 780 955 2777",
    "sg:postcode":"T9E 7Y8",
    "sg:province":"AB",
    "sg:tags":[
        "nut",
        "bolt"
    ],
    "wof:name":"Nisku Nut & Bolt Ltd",
    "wof:placetype":"venue"
},
  "geometry": {"coordinates":[-113.516266,53.338017],"type":"Point"}
}