{
  "type": "Feature",
  "properties": {
    "addr:full":"5004 54 St Yellowknife NT X1A 2R6",
    "addr:housenumber":"5004",
    "addr:postcode":"x1a 2r6",
    "addr:street":"54 St",
    "iso:country":"CA",
    "sg:address":"5004 54 St",
    "sg:city":"Yellowknife",
    "sg:classifiers":[
        {
            "category":"Education",
            "subcategory":"College",
            "type":"Public Place"
        }
    ],
    "sg:phone":"+1 867 920 3030",
    "sg:postcode":"X1A 2R6",
    "sg:province":"NT",
    "sg:tags":[
        "academic",
        "school"
    ],
    "wof:name":"Aurora College Yellowknife",
    "wof:placetype":"venue"
},
  "geometry": {"coordinates":[-114.37603799999999,62.451397],"type":"Point"}
}