{
  "type": "Feature",
  "properties": {
    "addr:full":"Woodbridge ON L4L 9K9",
    "addr:postcode":"l4l 9k9",
    "iso:country":"CA",
    "sg:city":"Woodbridge",
    "sg:classifiers":[
        {
            "category":"Home & Garden",
            "subcategory":"Carpets & Floor Coverings",
            "type":"Retail Goods"
        }
    ],
    "sg:phone":"+1 905 264 0465",
    "sg:postcode":"L4L 9K9",
    "sg:province":"ON",
    "sg:tags":[
        "dealer",
        "rug"
    ],
    "wof:name":"Tami Persian Rug",
    "wof:placetype":"venue"
},
  "geometry": {"coordinates":[-79.59061431879999,43.7859077454],"type":"Point"}
}