{
  "type": "Feature",
  "properties": {
    "addr:full":"406 Mountain Ave Neepawa MB R0J 1H0",
    "addr:housenumber":"406",
    "addr:postcode":"r0j 1h0",
    "addr:street":"Mountain Ave",
    "iso:country":"CA",
    "sg:address":"406 Mountain Ave",
    "sg:city":"Neepawa",
    "sg:classifiers":[
        {
            "category":"Insurance",
            "subcategory":"Insurance Agent",
            "type":"Services"
        }
    ],
    "sg:phone":"+1 204 476 2345",
    "sg:postcode":"R0J 1H0",
    "sg:province":"MB",
    "wof:name":"Gill & Schmall Agencies",
    "wof:placetype":"venue"
},
  "geometry": {"coordinates":[-99.4665756226,50.2296714783],"type":"Point"}
}