{
  "type": "Feature",
  "properties": {
    "iso:country":"CA",
    "sg:address":"167 Boul Laurier # 3",
    "sg:city":"Laurier-Station",
    "sg:classifiers":[
        {
            "category":"Cinema",
            "subcategory":"Movie Rental",
            "type":"Entertainment"
        }
    ],
    "sg:phone":"+1 418 728 2454",
    "sg:postcode":"G0S 1N0",
    "sg:province":"QC",
    "sg:tags":[
        "leasing",
        "video",
        "disc",
        "tape"
    ],
    "wof:name":"M & M Dvd-Video",
    "wof:placetype":"venue"
},
  "geometry": {"coordinates":[-71.6286697388,46.5424766541],"type":"Point"}
}