{
  "type": "Feature",
  "properties": {
    "addr:full":"5 Ch Adelard Gracefield QC J0X 1W0",
    "addr:housenumber":"5",
    "addr:postcode":"j0x 1w0",
    "addr:street":"Ch Adelard",
    "iso:country":"CA",
    "sg:address":"5 Ch Adelard",
    "sg:city":"Gracefield",
    "sg:classifiers":[
        {
            "category":"Travel",
            "subcategory":"Campground",
            "type":"Entertainment"
        }
    ],
    "sg:phone":"+1 819 463 2629",
    "sg:postcode":"J0X 1W0",
    "sg:province":"QC",
    "sg:tags":[
        "camp",
        "fishing"
    ],
    "wof:name":"Pavillon Whitefish",
    "wof:placetype":"venue"
},
  "geometry": {"coordinates":[-75.91831970210001,46.0482940674],"type":"Point"}
}