{
  "type": "Feature",
  "properties": {
    "addr:full":"6 10th Ave S Cranbrook BC V1C 2M8",
    "addr:housenumber":"6",
    "addr:postcode":"bc v1c 2m8",
    "addr:street":"10Th Ave S",
    "iso:country":"CA",
    "sg:address":"6 10th Ave S",
    "sg:city":"Cranbrook",
    "sg:classifiers":[
        {
            "category":"Insurance",
            "subcategory":"Insurance Agent",
            "type":"Services"
        }
    ],
    "sg:phone":"+1 250 426 3561",
    "sg:postcode":"V1C 2M8",
    "sg:province":"BC",
    "wof:name":"Ed Vien Insurance",
    "wof:placetype":"venue"
},
  "geometry": {"coordinates":[-115.767357,49.511887],"type":"Point"}
}