{
  "type": "Feature",
  "properties": {
    "addr:full":"PO Box 6 Bawlf AB T0B 0J0",
    "addr:housenumber":"po;6",
    "addr:postcode":"t0b 0j0",
    "addr:street":"Box",
    "iso:country":"CA",
    "sg:address":"PO Box 6",
    "sg:city":"Bawlf",
    "sg:classifiers":[
        {
            "category":"Shopping",
            "subcategory":"Hobbies, Toys, & Games",
            "type":"Retail Goods"
        }
    ],
    "sg:phone":"+1 780 373 3953",
    "sg:postcode":"T0B 0J0",
    "sg:province":"AB",
    "sg:tags":[
        "model",
        "supply"
    ],
    "wof:name":"Alberta's Littlest Airport",
    "wof:placetype":"venue"
},
  "geometry": {"coordinates":[-112.46668243400001,52.9201011658],"type":"Point"}
}