{
  "type": "Feature",
  "properties": {
    "addr:full":"207 Milltown Blvd St Stephen NB E3L 1G7",
    "addr:housenumber":"207",
    "addr:postcode":"e3l 1g7",
    "addr:street":"Milltown Blvd",
    "iso:country":"CA",
    "sg:address":"207 Milltown Blvd",
    "sg:city":"St Stephen",
    "sg:classifiers":[
        {
            "category":"Shopping",
            "type":"Retail Goods"
        }
    ],
    "sg:phone":"+1 506 466 4088",
    "sg:postcode":"E3L 1G7",
    "sg:province":"NB",
    "sg:tags":[
        "miscellaneous",
        "store"
    ],
    "wof:name":"St Stephen Tax & Duty Free",
    "wof:placetype":"venue"
},
  "geometry": {"coordinates":[-67.2839050293,45.1927719116],"type":"Point"}
}