{
  "type": "Feature",
  "properties": {
    "iso:country":"CA",
    "sg:address":"475 Av Bloomfield",
    "sg:city":"Outremont",
    "sg:classifiers":[
        {
            "category":"Education",
            "subcategory":"School",
            "type":"Public Place"
        }
    ],
    "sg:phone":"+1 514 276 3746",
    "sg:postcode":"H2V 3R9",
    "sg:province":"QC",
    "wof:name":"Paul Gerin Lajoie Ecoles Scndr",
    "wof:placetype":"venue"
},
  "geometry": {"coordinates":[-73.6060791016,45.519695282],"type":"Point"}
}