{
  "type": "Feature",
  "properties": {
    "iso:country":"CA",
    "sg:city":"Nepean",
    "sg:classifiers":[
        {
            "category":"Manufacturing",
            "subcategory":"Chemicals & Compounds",
            "type":"Manufacturing & Wholesale Goods"
        }
    ],
    "sg:phone":"+1 613 727 7337",
    "sg:postcode":"K2E 7T8",
    "sg:province":"ON",
    "sg:tags":[
        "equipment",
        "cosmetic"
    ],
    "wof:name":"Natunola Health Inc",
    "wof:placetype":"venue"
},
  "geometry": {"coordinates":[-75.7080230713,45.3343658447],"type":"Point"}
}