{
  "type": "Feature",
  "properties": {
    "addr:full":"4 Whyte Ave Dryden ON P8N 1Y9",
    "addr:housenumber":"4",
    "addr:postcode":"p8n 1y9",
    "addr:street":"Whyte Ave",
    "iso:country":"CA",
    "sg:address":"4 Whyte Ave",
    "sg:city":"Dryden",
    "sg:classifiers":[
        {
            "category":"Professional",
            "subcategory":"Management & Consulting",
            "type":"Services"
        }
    ],
    "sg:phone":"+1 807 223 3464",
    "sg:postcode":"P8N 1Y9",
    "sg:province":"ON",
    "sg:tags":[
        "consultant",
        "business"
    ],
    "wof:name":"Thunder Management Inc",
    "wof:placetype":"venue"
},
  "geometry": {"coordinates":[-92.839050293,49.785068512],"type":"Point"}
}