{
  "type": "Feature",
  "properties": {
    "addr:full":"Prince George BC V2K 5B7",
    "addr:postcode":"v2k 5b7",
    "iso:country":"CA",
    "sg:city":"Prince George",
    "sg:classifiers":[
        {
            "category":"Building & Trades",
            "subcategory":"Construction",
            "type":"Services"
        }
    ],
    "sg:phone":"+1 250 962 0505",
    "sg:postcode":"V2K 5B7",
    "sg:province":"BC",
    "sg:tags":[
        "general",
        "contractor"
    ],
    "wof:name":"Sharp Construction Ltd",
    "wof:placetype":"venue"
},
  "geometry": {"coordinates":[-122.766548,53.972347],"type":"Point"}
}