{
  "type": "Feature",
  "properties": {
    "iso:country":"CA",
    "sg:address":"2255 Cabonga",
    "sg:city":"Grand-Remous",
    "sg:classifiers":[
        {
            "category":"Travel",
            "subcategory":"Campground",
            "type":"Entertainment"
        }
    ],
    "sg:phone":"+1 819 736 2255",
    "sg:postcode":"J0W 1E0",
    "sg:province":"QC",
    "sg:tags":[
        "camp",
        "fishing"
    ],
    "wof:name":"Deer Horn Lodge",
    "wof:placetype":"venue"
},
  "geometry": {"coordinates":[-75.8990859985,46.6039848328],"type":"Point"}
}