{
  "type": "Feature",
  "properties": {
    "addr:full":"10593 Yonge St Richmond Hill ON L4C 3C5",
    "addr:housenumber":"10593",
    "addr:postcode":"l4c 3c5",
    "addr:street":"Yonge St",
    "iso:country":"CA",
    "sg:address":"10593 Yonge St",
    "sg:city":"Richmond Hill",
    "sg:classifiers":[
        {
            "category":"Home & Garden",
            "subcategory":"Carpets & Floor Coverings",
            "type":"Retail Goods"
        }
    ],
    "sg:phone":"+1 905 770 7912",
    "sg:postcode":"L4C 3C5",
    "sg:province":"ON",
    "sg:tags":[
        "material",
        "rug"
    ],
    "wof:name":"Factory Flooring",
    "wof:placetype":"venue"
},
  "geometry": {"coordinates":[-79.440399,43.885635],"type":"Point"}
}