{
  "type": "Feature",
  "properties": {
    "iso:country":"CA",
    "sg:address":"630 Dunlop St W",
    "sg:city":"Barrie",
    "sg:classifiers":[
        {
            "category":"Wholesale",
            "subcategory":"Machinery & Supplies",
            "type":"Manufacturing & Wholesale Goods"
        }
    ],
    "sg:phone":"+1 705 722 8181",
    "sg:postcode":"L4N 9W5",
    "sg:province":"ON",
    "sg:tags":[
        "contractor"
    ],
    "wof:name":"United Rentals",
    "wof:placetype":"venue"
},
  "geometry": {"coordinates":[-79.729202,44.367359],"type":"Point"}
}