{
  "type": "Feature",
  "properties": {
    "addr:full":"7967 Fernbank Rd Ashton ON K0A 1B0",
    "addr:housenumber":"7967",
    "addr:postcode":"k0a 1b0",
    "addr:street":"Fernbank Rd",
    "iso:country":"CA",
    "sg:address":"7967 Fernbank Rd",
    "sg:city":"Ashton",
    "sg:classifiers":[
        {
            "category":"Recreation",
            "type":"Entertainment"
        }
    ],
    "sg:phone":"+1 613 257 5181",
    "sg:postcode":"K0A 1B0",
    "sg:province":"ON",
    "sg:tags":[
        "course",
        "golf"
    ],
    "wof:name":"Glen Mar Golf & Country Club",
    "wof:placetype":"venue"
},
  "geometry": {"coordinates":[-76.03224945069999,45.1571006775],"type":"Point"}
}