{
  "type": "Feature",
  "properties": {
    "addr:full":"97 Ch Du Bord-DE-L'Eau Laval QC H7X 1S5",
    "addr:housenumber":"97",
    "addr:postcode":"h7x 1s5",
    "addr:street":"Ch Du Bord-De-L'Eau",
    "iso:country":"CA",
    "sg:address":"97 Ch Du Bord-DE-L'Eau",
    "sg:city":"Laval",
    "sg:classifiers":[
        {
            "category":"Shopping",
            "subcategory":"Florist",
            "type":"Retail Goods"
        }
    ],
    "sg:phone":"+1 450 689 1597",
    "sg:postcode":"H7X 1S5",
    "sg:province":"QC",
    "sg:tags":[
        "garden",
        "center"
    ],
    "wof:name":"Michka Signe Charbonneau",
    "wof:placetype":"venue"
},
  "geometry": {"coordinates":[-73.77748099999999,45.52153],"type":"Point"}
}