{
  "type": "Feature",
  "properties": {
    "addr:full":"1780 Av Du Phare O Matane QC G4W 3M6",
    "addr:housenumber":"1780",
    "addr:postcode":"g4w 3m6",
    "addr:street":"Av Du Phare O",
    "iso:country":"CA",
    "sg:address":"1780 Av Du Phare O",
    "sg:city":"Matane",
    "sg:classifiers":[
        {
            "category":"Autos & Motor Vehicles",
            "subcategory":"Auto Supplies",
            "type":"Retail Goods"
        }
    ],
    "sg:phone":"+1 418 562 0245",
    "sg:postcode":"G4W 3M6",
    "sg:province":"QC",
    "sg:tags":[
        "automobile",
        "parts",
        "dealer"
    ],
    "wof:name":"Garage Marcel Villeneuve Inc",
    "wof:placetype":"venue"
},
  "geometry": {"coordinates":[-67.580872,48.82906],"type":"Point"}
}