{
  "type": "Feature",
  "properties": {
    "addr:full":"99 Merrymeeting Rd St. John's NL A1C 2W2",
    "addr:housenumber":"99",
    "addr:postcode":"a1c 2w2",
    "addr:street":"Merrymeeting Rd",
    "iso:country":"CA",
    "sg:address":"99 Merrymeeting Rd",
    "sg:city":"St. John's",
    "sg:classifiers":[
        {
            "category":"Retail",
            "subcategory":"Auto Repair",
            "type":"Services"
        }
    ],
    "sg:phone":"+1 709 579 6100",
    "sg:postcode":"A1C 2W2",
    "sg:province":"NL",
    "sg:tags":[
        "repairing",
        "automobile"
    ],
    "wof:name":"C & C Automotive",
    "wof:placetype":"venue"
},
  "geometry": {"coordinates":[-52.7203598022,47.5649795532],"type":"Point"}
}