{
  "type": "Feature",
  "properties": {
    "addr:full":"Main St Port Au Port NL A0N 1T0",
    "addr:postcode":"a0n 1t0",
    "addr:street":"Main St;Au Port",
    "iso:country":"CA",
    "sg:address":"Main St",
    "sg:city":"Port Au Port",
    "sg:classifiers":[
        {
            "category":"Bars & Pubs",
            "type":"Food & Drink"
        }
    ],
    "sg:phone":"+1 709 648 9225",
    "sg:postcode":"A0N 1T0",
    "sg:province":"NL",
    "sg:tags":[
        "lounge",
        "cocktail"
    ],
    "wof:name":"Bonnie's Lounge",
    "wof:placetype":"venue"
},
  "geometry": {"coordinates":[-58.710091,48.556732],"type":"Point"}
}