{
  "type": "Feature",
  "properties": {
    "addr:full":"1175 Tupper St Hawkesbury ON K6A 3T5",
    "addr:housenumber":"1175",
    "addr:postcode":"k6a 3t5",
    "addr:street":"Tupper St",
    "iso:country":"CA",
    "sg:address":"1175 Tupper St",
    "sg:city":"Hawkesbury",
    "sg:classifiers":[
        {
            "category":"Professional",
            "subcategory":"Research",
            "type":"Services"
        }
    ],
    "sg:phone":"+1 613 632 0933",
    "sg:postcode":"K6A 3T5",
    "sg:province":"ON",
    "sg:tags":[
        "development",
        "electronic"
    ],
    "wof:name":"Noreast Electronics CO Ltd",
    "wof:placetype":"venue"
},
  "geometry": {"coordinates":[-74.589157,45.59417],"type":"Point"}
}