{
  "type": "Feature",
  "properties": {
    "addr:full":"3293 Lawrence Ave E Scarborough ON M1H 1A5",
    "addr:housenumber":"3293",
    "addr:postcode":"m1h 1a5",
    "addr:street":"Lawrence Ave E",
    "iso:country":"CA",
    "sg:address":"3293 Lawrence Ave E",
    "sg:city":"Scarborough",
    "sg:classifiers":[
        {
            "category":"Retail",
            "subcategory":"Auto Repair",
            "type":"Services"
        }
    ],
    "sg:phone":"+1 416 439 5110",
    "sg:postcode":"M1H 1A5",
    "sg:province":"ON",
    "sg:tags":[
        "repairing",
        "automobile"
    ],
    "wof:name":"First Rate Auto",
    "wof:placetype":"venue"
},
  "geometry": {"coordinates":[-79.236092,43.757393],"type":"Point"}
}