{
  "type": "Feature",
  "properties": {
    "iso:country":"CA",
    "sg:city":"Vancouver",
    "sg:classifiers":[
        {
            "category":"Professional",
            "subcategory":"Management & Consulting",
            "type":"Services"
        }
    ],
    "sg:phone":"+1 604 801 5200",
    "sg:postcode":"V6Z 2M4",
    "sg:province":"BC",
    "sg:tags":[
        "consultant",
        "planning"
    ],
    "wof:name":"Sussex Consultants Ltd",
    "wof:placetype":"venue"
},
  "geometry": {"coordinates":[-123.122383118,49.2807159424],"type":"Point"}
}