{
  "type": "Feature",
  "properties": {
    "addr:full":"1st Ave Lucky Lake SK S0L 1Z0",
    "addr:postcode":"s0l 1z0",
    "addr:street":"1St Ave",
    "iso:country":"CA",
    "sg:address":"1st Ave",
    "sg:city":"Lucky Lake",
    "sg:classifiers":[
        {
            "category":"Education",
            "subcategory":"Library",
            "type":"Public Place"
        }
    ],
    "sg:phone":"+1 306 858 2246",
    "sg:postcode":"S0L 1Z0",
    "sg:province":"SK",
    "wof:name":"Library-Lucky Lake",
    "wof:placetype":"venue"
},
  "geometry": {"coordinates":[-107.135559,50.979946],"type":"Point"}
}