{
  "type": "Feature",
  "properties": {
    "addr:full":"123A Queen St # A Dryden ON P8N 1A6",
    "addr:housenumber":"123a",
    "addr:postcode":"p8n 1a6",
    "addr:street":"Queen St # A",
    "iso:country":"CA",
    "sg:address":"123A Queen St # A",
    "sg:city":"Dryden",
    "sg:classifiers":[
        {
            "category":"Government",
            "subcategory":"Office",
            "type":"Public Place"
        }
    ],
    "sg:phone":"+1 807 223 6456",
    "sg:postcode":"P8N 1A6",
    "sg:province":"ON",
    "sg:tags":[
        "organization",
        "political"
    ],
    "wof:name":"Hampton, Howard",
    "wof:placetype":"venue"
},
  "geometry": {"coordinates":[-92.8323440552,49.7853126526],"type":"Point"}
}