{
  "type": "Feature",
  "properties": {
    "addr:full":"204 Patillo Rd Tecumseh ON N8N 2L9",
    "addr:housenumber":"204",
    "addr:postcode":"n8n 2l9",
    "addr:street":"Patillo Rd",
    "iso:country":"CA",
    "sg:address":"204 Patillo Rd",
    "sg:city":"Tecumseh",
    "sg:classifiers":[
        {
            "category":"Autos & Motor Vehicles",
            "subcategory":"Recreational Vehicle Sales",
            "type":"Retail Goods"
        }
    ],
    "sg:phone":"+1 519 727 3400",
    "sg:postcode":"N8N 2L9",
    "sg:province":"ON",
    "wof:name":"Leisure Trailer Sales Ltd",
    "wof:placetype":"venue"
},
  "geometry": {"coordinates":[-82.88711547849999,42.315158844],"type":"Point"}
}