{
  "type": "Feature",
  "properties": {
    "iso:country":"CA",
    "sg:city":"Nepean",
    "sg:classifiers":[
        {
            "category":"Restaurant",
            "type":"Food & Drink"
        }
    ],
    "sg:phone":"+1 613 829 8951",
    "sg:postcode":"K2H 5Y9",
    "sg:province":"ON",
    "sg:tags":[
        "delicatessen"
    ],
    "wof:name":"Ziggy's",
    "wof:placetype":"venue"
},
  "geometry": {"coordinates":[-75.709023,45.314671],"type":"Point"}
}