{
  "type": "Feature",
  "properties": {
    "addr:full":"Riverton MB R0C 2R0",
    "addr:postcode":"r0c 2r0",
    "iso:country":"CA",
    "sg:city":"Riverton",
    "sg:classifiers":[
        {
            "category":"Building & Trades",
            "subcategory":"Construction",
            "type":"Services"
        }
    ],
    "sg:phone":"+1 204 378 2142",
    "sg:postcode":"R0C 2R0",
    "sg:province":"MB",
    "sg:tags":[
        "control",
        "erosion"
    ],
    "wof:name":"Erosion Control Blanket.com",
    "wof:placetype":"venue"
},
  "geometry": {"coordinates":[-96.9964523315,50.9984130859],"type":"Point"}
}