{
  "type": "Feature",
  "properties": {
    "addr:full":"42 Rue DE LA Dame-Neuve Lachute QC J8H 1A3",
    "addr:housenumber":"42",
    "addr:postcode":"j8h 1a3",
    "addr:street":"Rue De La Dame-Neuve",
    "iso:country":"CA",
    "sg:address":"42 Rue DE LA Dame-Neuve",
    "sg:city":"Lachute",
    "sg:classifiers":[
        {
            "category":"Building & Trades",
            "subcategory":"Construction",
            "type":"Services"
        }
    ],
    "sg:phone":"+1 450 562 8658",
    "sg:postcode":"J8H 1A3",
    "sg:province":"QC",
    "sg:tags":[
        "general",
        "contractor"
    ],
    "wof:name":"Construction & Pavage D'Argent",
    "wof:placetype":"venue"
},
  "geometry": {"coordinates":[-74.355186,45.634426],"type":"Point"}
}