{
  "type": "Feature",
  "properties": {
    "iso:country":"CA",
    "sg:city":"Grande Prairie",
    "sg:classifiers":[
        {
            "category":"Social Services",
            "type":"Services"
        }
    ],
    "sg:phone":"+1 780 539 4006",
    "sg:postcode":"T8V 0X9",
    "sg:province":"AB",
    "sg:tags":[
        "counseling"
    ],
    "wof:name":"Break Free Ministries",
    "wof:placetype":"venue"
},
  "geometry": {"coordinates":[-118.795219421,55.1714477539],"type":"Point"}
}