{
  "type": "Feature",
  "properties": {
    "addr:full":"1086 Labrosse St St Eugene ON K0B 1P0",
    "addr:housenumber":"1086",
    "addr:postcode":"k0b 1p0",
    "addr:street":"Labrosse St",
    "iso:country":"CA",
    "sg:address":"1086 Labrosse St",
    "sg:city":"St Eugene",
    "sg:classifiers":[
        {
            "category":"Health Services",
            "subcategory":"Doctor",
            "type":"Services"
        }
    ],
    "sg:phone":"+1 613 674 3264",
    "sg:postcode":"K0B 1P0",
    "sg:province":"ON",
    "sg:tags":[
        "physician",
        "surgeon"
    ],
    "wof:name":"Bender, Jacques MD",
    "wof:placetype":"venue"
},
  "geometry": {"coordinates":[-74.4645233154,45.4989776611],"type":"Point"}
}