{
  "type": "Feature",
  "properties": {
    "iso:country":"CA",
    "sg:address":"13 King St W",
    "sg:city":"Oshawa",
    "sg:classifiers":[
        {
            "category":"Personal",
            "subcategory":"Beauty Salon",
            "type":"Services"
        }
    ],
    "sg:phone":"+1 905 434 7171",
    "sg:postcode":"L1H 1A1",
    "sg:province":"ON",
    "wof:name":"Spartacus Hair Design",
    "wof:placetype":"venue"
},
  "geometry": {"coordinates":[-78.864159,43.897324],"type":"Point"}
}