{
  "type": "Feature",
  "properties": {
    "addr:full":"188 Bentworth Ave North York ON M6A 1P8",
    "addr:housenumber":"188",
    "addr:postcode":"m6a 1p8",
    "addr:street":"Bentworth Ave",
    "iso:country":"CA",
    "sg:address":"188 Bentworth Ave",
    "sg:city":"North York",
    "sg:classifiers":[
        {
            "category":"Manufacturing",
            "subcategory":"Apparel",
            "type":"Manufacturing & Wholesale Goods"
        }
    ],
    "sg:phone":"+1 416 783 0300",
    "sg:postcode":"M6A 1P8",
    "sg:province":"ON",
    "sg:tags":[
        "clothing"
    ],
    "wof:name":"Snugabye Factory Outlet",
    "wof:placetype":"venue"
},
  "geometry": {"coordinates":[-79.4689483643,43.7196121216],"type":"Point"}
}