{
  "type": "Feature",
  "properties": {
    "addr:full":"5118 Meadfeild Rd West Vancouver BC V7W 3G2",
    "addr:housenumber":"5118",
    "addr:postcode":"v7w 3g2",
    "addr:street":"Meadfeild Rd",
    "iso:country":"CA",
    "sg:address":"5118 Meadfeild Rd",
    "sg:city":"West Vancouver",
    "sg:classifiers":[
        {
            "category":"Manufacturing",
            "subcategory":"Printing",
            "type":"Manufacturing & Wholesale Goods"
        }
    ],
    "sg:phone":"+1 604 925 0266",
    "sg:postcode":"V7W 3G2",
    "sg:province":"BC",
    "sg:tags":[
        "publisher"
    ],
    "wof:name":"Ken Haycock & Assoc Inc",
    "wof:placetype":"venue"
},
  "geometry": {"coordinates":[-123.261123657,49.3487014771],"type":"Point"}
}