{
  "type": "Feature",
  "properties": {
    "addr:full":"31044 Hwy 48 Pefferlaw ON L0E 1N0",
    "addr:housenumber":"31044",
    "addr:postcode":"l0e 1n0",
    "addr:street":"Hwy 48 Pefferlaw",
    "iso:country":"CA",
    "sg:address":"31044 Hwy 48",
    "sg:city":"Pefferlaw",
    "sg:classifiers":[
        {
            "category":"Restaurant",
            "type":"Food & Drink"
        }
    ],
    "sg:phone":"+1 705 437 2634",
    "sg:postcode":"L0E 1N0",
    "sg:province":"ON",
    "wof:name":"Skipper's",
    "wof:placetype":"venue"
},
  "geometry": {"coordinates":[-79.21711000000001,44.330639],"type":"Point"}
}