{
  "type": "Feature",
  "properties": {
    "addr:full":"422 Murtle Rd Clearwater BC V0E 1N0",
    "addr:housenumber":"422",
    "addr:postcode":"v0e 1n0",
    "addr:street":"Murtle Rd",
    "iso:country":"CA",
    "sg:address":"422 Murtle Rd",
    "sg:city":"Clearwater",
    "sg:classifiers":[
        {
            "category":"Education",
            "subcategory":"Library",
            "type":"Public Place"
        }
    ],
    "sg:phone":"+1 250 674 2543",
    "sg:postcode":"V0E 1N0",
    "sg:province":"BC",
    "wof:name":"Clearwater Library",
    "wof:placetype":"venue"
},
  "geometry": {"coordinates":[-120.03830000000001,51.649601],"type":"Point"}
}