{
  "type": "Feature",
  "properties": {
    "addr:full":"550 Fisgard St Victoria BC V8W 1R4",
    "addr:housenumber":"550",
    "addr:postcode":"v8w 1r4",
    "addr:street":"Fisgard St",
    "iso:country":"CA",
    "sg:address":"550 Fisgard St",
    "sg:city":"Victoria",
    "sg:classifiers":[
        {
            "category":"Food & Beverages",
            "subcategory":"Groceries & Convenience Stores",
            "type":"Retail Goods"
        }
    ],
    "sg:phone":"+1 250 383 6969",
    "sg:postcode":"V8W 1R4",
    "sg:province":"BC",
    "sg:tags":[
        "grocer"
    ],
    "wof:name":"Fisgard Market Ltd",
    "wof:placetype":"venue"
},
  "geometry": {"coordinates":[-123.36813354500001,48.429473877],"type":"Point"}
}