{
  "type": "Feature",
  "properties": {
    "addr:full":"551 Northmount Dr NW Calgary AB T2K 3J3",
    "addr:housenumber":"551",
    "addr:postcode":"t2k 3j3",
    "addr:street":"Northmount Dr Nw",
    "iso:country":"CA",
    "sg:address":"551 Northmount Dr NW",
    "sg:city":"Calgary",
    "sg:classifiers":[
        {
            "category":"Retail",
            "subcategory":"Car Wash",
            "type":"Services"
        }
    ],
    "sg:phone":"+1 403 282 8863",
    "sg:postcode":"T2K 3J3",
    "sg:province":"AB",
    "sg:tags":[
        "polishing",
        "washing"
    ],
    "wof:name":"Western Pride Car Wash",
    "wof:placetype":"venue"
},
  "geometry": {"coordinates":[-114.085731506,51.0888252258],"type":"Point"}
}