{
  "type": "Feature",
  "properties": {
    "addr:full":"Terrace BC V8G 2N3",
    "addr:postcode":"v8g 2n3",
    "iso:country":"CA",
    "sg:city":"Terrace",
    "sg:classifiers":[
        {
            "category":"Shopping",
            "subcategory":"Crafts & Fabrics",
            "type":"Retail Goods"
        }
    ],
    "sg:phone":"+1 250 638 1335",
    "sg:postcode":"V8G 2N3",
    "sg:province":"BC",
    "sg:tags":[
        "shop"
    ],
    "wof:name":"Cotton Pick 'N' Quilt Patch",
    "wof:placetype":"venue"
},
  "geometry": {"coordinates":[-128.58677700000001,54.517441],"type":"Point"}
}