{
  "type": "Feature",
  "properties": {
    "iso:country":"CA",
    "sg:address":"1086 Frances St",
    "sg:city":"London",
    "sg:classifiers":[
        {
            "category":"Freight",
            "type":"Transportation"
        }
    ],
    "sg:phone":"+1 519 451 0592",
    "sg:postcode":"N5W 2L7",
    "sg:province":"ON",
    "sg:tags":[
        "mover"
    ],
    "wof:name":"Bev's Moving & Cartage",
    "wof:placetype":"venue"
},
  "geometry": {"coordinates":[-81.212852,42.989769],"type":"Point"}
}