{
  "type": "Feature",
  "properties": {
    "addr:full":"1086 Frances St London ON N5W 2L7",
    "addr:housenumber":"1086",
    "addr:postcode":"n5w 2l7",
    "addr:street":"Frances St",
    "iso:country":"CA",
    "sg:address":"1086 Frances St",
    "sg:city":"London",
    "sg:classifiers":[
        {
            "category":"Freight",
            "type":"Transportation"
        }
    ],
    "sg:phone":"+1 519 451 0592",
    "sg:postcode":"N5W 2L7",
    "sg:province":"ON",
    "sg:tags":[
        "mover"
    ],
    "wof:name":"Bev's Moving & Cartage",
    "wof:placetype":"venue"
},
  "geometry": {"coordinates":[-81.212852,42.989769],"type":"Point"}
}