{
  "type": "Feature",
  "properties": {
    "iso:country":"CA",
    "sg:city":"Saskatoon",
    "sg:classifiers":[
        {
            "category":"Banks & Credit Unions",
            "subcategory":"Investment Brokerage",
            "type":"Services"
        }
    ],
    "sg:phone":"+1 306 665 8111",
    "sg:postcode":"S7K 5T6",
    "sg:province":"SK",
    "sg:tags":[
        "consultant",
        "planning",
        "financial"
    ],
    "wof:name":"Arscott & Assoc",
    "wof:placetype":"venue"
},
  "geometry": {"coordinates":[-106.66004180900001,52.1282424927],"type":"Point"}
}