{
  "type": "Feature",
  "properties": {
    "iso:country":"CA",
    "sg:city":"Medicine Hat",
    "sg:classifiers":[
        {
            "category":"Building & Trades",
            "subcategory":"Landscaping Services",
            "type":"Services"
        }
    ],
    "sg:phone":"+1 403 526 3555",
    "sg:postcode":"T1B 3X9",
    "sg:province":"AB",
    "sg:tags":[
        "compost",
        "landscape",
        "contractor"
    ],
    "wof:name":"Earthworks Environmental Svc",
    "wof:placetype":"venue"
},
  "geometry": {"coordinates":[-110.639602661,50.0066452026],"type":"Point"}
}