{
  "type": "Feature",
  "properties": {
    "addr:full":"26 Collingwood Cres Yorkton SK S3N 2Z8",
    "addr:housenumber":"26",
    "addr:postcode":"s3n 2z8",
    "addr:street":"Collingwood Cres",
    "iso:country":"CA",
    "sg:address":"26 Collingwood Cres",
    "sg:city":"Yorkton",
    "sg:classifiers":[
        {
            "category":"Building & Trades",
            "subcategory":"Electrical",
            "type":"Services"
        }
    ],
    "sg:phone":"+1 306 782 9863",
    "sg:postcode":"S3N 2Z8",
    "sg:province":"SK",
    "sg:tags":[
        "electric",
        "contractor"
    ],
    "wof:name":"All-Stat Electric Ltd",
    "wof:placetype":"venue"
},
  "geometry": {"coordinates":[-102.495544,51.197289],"type":"Point"}
}