{
  "type": "Feature",
  "properties": {
    "addr:full":"Lac-Saint-Charles QC G3G 2Z4",
    "addr:postcode":"g3g 2z4",
    "addr:street":"Lac-Saint-Charles",
    "iso:country":"CA",
    "sg:city":"Lac-Saint-Charles",
    "sg:classifiers":[
        {
            "category":"Food & Beverages",
            "subcategory":"Groceries & Convenience Stores",
            "type":"Retail Goods"
        }
    ],
    "sg:phone":"+1 418 849 0889",
    "sg:postcode":"G3G 2Z4",
    "sg:province":"QC",
    "wof:name":"Super Depanneur Lac St-Charles",
    "wof:placetype":"venue"
},
  "geometry": {"coordinates":[-71.35443100000001,46.89077],"type":"Point"}
}