{
  "type": "Feature",
  "properties": {
    "addr:full":"Cranbrook BC V1C 2R7",
    "addr:postcode":"v1c 2r7",
    "iso:country":"CA",
    "sg:city":"Cranbrook",
    "sg:classifiers":[
        {
            "category":"Health Services",
            "subcategory":"Doctor",
            "type":"Services"
        }
    ],
    "sg:phone":"+1 250 426 5865",
    "sg:postcode":"V1C 2R7",
    "sg:province":"BC",
    "sg:tags":[
        "dentist"
    ],
    "wof:name":"Baker Hill Dental Clinic",
    "wof:placetype":"venue"
},
  "geometry": {"coordinates":[-115.764663696,49.5112953186],"type":"Point"}
}