{
  "type": "Feature",
  "properties": {
    "addr:full":"287 Rue Du Bon-Pasteur Matane QC G4W 3C8",
    "addr:housenumber":"287",
    "addr:postcode":"g4w 3c8",
    "addr:street":"Rue Du Bon-Pasteur",
    "iso:country":"CA",
    "sg:address":"287 Rue Du Bon-Pasteur",
    "sg:city":"Matane",
    "sg:classifiers":[
        {
            "category":"Insurance",
            "subcategory":"Insurance Agent",
            "type":"Services"
        }
    ],
    "sg:phone":"+1 418 562 0124",
    "sg:postcode":"G4W 3C8",
    "sg:province":"QC",
    "wof:name":"Assurances DE L'Est",
    "wof:placetype":"venue"
},
  "geometry": {"coordinates":[-67.53156300000001,48.846016],"type":"Point"}
}