{
  "type": "Feature",
  "properties": {
    "addr:full":"PO Box 99 Glenevis AB T0E 0X0",
    "addr:housenumber":"po box 99",
    "addr:postcode":"t0e 0x0",
    "addr:street":"Glenevis Ab",
    "iso:country":"CA",
    "sg:address":"PO Box 99",
    "sg:city":"Glenevis",
    "sg:classifiers":[
        {
            "category":"Recreation",
            "type":"Entertainment"
        }
    ],
    "sg:phone":"+1 780 785 3113",
    "sg:postcode":"T0E 0X0",
    "sg:province":"AB",
    "sg:tags":[
        "hall",
        "auditorium"
    ],
    "wof:name":"Glenevis Community Hall",
    "wof:placetype":"venue"
},
  "geometry": {"coordinates":[-114.533401,53.789665],"type":"Point"}
}