{
  "type": "Feature",
  "properties": {
    "addr:full":"Edson AB T7E 1V7",
    "addr:postcode":"t7e 1v7",
    "iso:country":"CA",
    "sg:city":"Edson",
    "sg:classifiers":[
        {
            "category":"Building & Trades",
            "subcategory":"Construction",
            "type":"Services"
        }
    ],
    "sg:phone":"+1 780 723 6490",
    "sg:postcode":"T7E 1V7",
    "sg:province":"AB",
    "sg:tags":[
        "general",
        "contractor"
    ],
    "wof:name":"Simms Road Maintenance Ltd",
    "wof:placetype":"venue"
},
  "geometry": {"coordinates":[-116.43409729,53.5821304321],"type":"Point"}
}