{
  "type": "Feature",
  "properties": {
    "addr:full":"295 Highview Dr Kitchener ON N2N 2K7",
    "addr:housenumber":"295",
    "addr:postcode":"n2n 2k7",
    "addr:street":"Highview Dr",
    "iso:country":"CA",
    "sg:address":"295 Highview Dr",
    "sg:city":"Kitchener",
    "sg:classifiers":[
        {
            "category":"Organizations",
            "subcategory":"Religious Organization",
            "type":"Services"
        }
    ],
    "sg:phone":"+1 519 745 1021",
    "sg:postcode":"N2N 2K7",
    "sg:province":"ON",
    "sg:tags":[
        "church"
    ],
    "wof:name":"Forestview Bible Church",
    "wof:placetype":"venue"
},
  "geometry": {"coordinates":[-80.552269,43.414734],"type":"Point"}
}