{
  "type": "Feature",
  "properties": {
    "addr:full":"843 Warren Ave Prince George BC V2M 3V8",
    "addr:housenumber":"843",
    "addr:postcode":"v2m 3v8",
    "addr:street":"Warren Ave",
    "iso:country":"CA",
    "sg:address":"843 Warren Ave",
    "sg:city":"Prince George",
    "sg:classifiers":[
        {
            "category":"Retail",
            "subcategory":"Repair Shop",
            "type":"Services"
        }
    ],
    "sg:phone":"+1 250 564 3030",
    "sg:postcode":"V2M 3V8",
    "sg:province":"BC",
    "sg:tags":[
        "plumbing",
        "drain",
        "cleaning",
        "sewer"
    ],
    "wof:name":"Roto-Rooter",
    "wof:placetype":"venue"
},
  "geometry": {"coordinates":[-122.78713999999999,53.917664],"type":"Point"}
}