{
  "type": "Feature",
  "properties": {
    "iso:country":"CA",
    "sg:address":"2780 King George Hwy",
    "sg:city":"Surrey",
    "sg:classifiers":[
        {
            "category":"Autos & Motor Vehicles",
            "subcategory":"Automobile Sales",
            "type":"Retail Goods"
        }
    ],
    "sg:phone":"+1 604 536 3644",
    "sg:postcode":"V4P 1A2",
    "sg:province":"BC",
    "sg:tags":[
        "car",
        "dealer"
    ],
    "wof:name":"King George Nissan",
    "wof:placetype":"venue"
},
  "geometry": {"coordinates":[-122.80219268800001,49.0527305603],"type":"Point"}
}