{
  "type": "Feature",
  "properties": {
    "addr:full":"529 2 Ave SE Airdrie AB T4B 2C2",
    "addr:housenumber":"529",
    "addr:postcode":"t4b 2c2",
    "addr:street":"2 Ave Se",
    "iso:country":"CA",
    "sg:address":"529 2 Ave SE",
    "sg:city":"Airdrie",
    "sg:classifiers":[
        {
            "category":"Autos & Motor Vehicles",
            "subcategory":"Fuel & Gas Station",
            "type":"Retail Goods"
        }
    ],
    "sg:phone":"+1 403 948 6285",
    "sg:postcode":"T4B 2C2",
    "sg:province":"AB",
    "sg:tags":[
        "oil"
    ],
    "wof:name":"Airdrie Shell",
    "wof:placetype":"venue"
},
  "geometry": {"coordinates":[-114.00316599999999,51.289852],"type":"Point"}
}