{
  "type": "Feature",
  "properties": {
    "addr:full":"639 Southdale Rd E London ON N6E 3M2",
    "addr:housenumber":"639",
    "addr:postcode":"n6e 3m2",
    "addr:street":"Southdale Rd E",
    "iso:country":"CA",
    "sg:address":"639 Southdale Rd E",
    "sg:city":"London",
    "sg:classifiers":[
        {
            "category":"Wholesale",
            "subcategory":"Meat",
            "type":"Manufacturing & Wholesale Goods"
        }
    ],
    "sg:phone":"+1 519 685 3625",
    "sg:postcode":"N6E 3M2",
    "sg:province":"ON",
    "sg:tags":[
        "butchering"
    ],
    "wof:name":"Laziz Meat & Deli",
    "wof:placetype":"venue"
},
  "geometry": {"coordinates":[-81.2298278809,42.9429855347],"type":"Point"}
}