{
  "type": "Feature",
  "properties": {
    "addr:full":"846 Ch Baisley Saint-Jacques NB E7B 1Z7",
    "addr:housenumber":"846",
    "addr:postcode":"e7b 1z7",
    "addr:street":"Ch Baisley",
    "iso:country":"CA",
    "sg:address":"846 Ch Baisley",
    "sg:city":"Saint-Jacques",
    "sg:classifiers":[
        {
            "category":"Manufacturing",
            "subcategory":"Tools & Machinery",
            "type":"Manufacturing & Wholesale Goods"
        }
    ],
    "sg:phone":"+1 506 735 5875",
    "sg:postcode":"E7B 1Z7",
    "sg:province":"NB",
    "sg:tags":[
        "machine",
        "shop"
    ],
    "wof:name":"F A Tool & Die Machine Shop",
    "wof:placetype":"venue"
},
  "geometry": {"coordinates":[-68.41851800000001,47.457977],"type":"Point"}
}