{
  "type": "Feature",
  "properties": {
    "addr:full":"2317 Skeena Dr Kamloops BC V2E 1Y2",
    "addr:housenumber":"2317",
    "addr:postcode":"bc v2e 1y2",
    "addr:street":"Skeena Dr",
    "iso:country":"CA",
    "sg:address":"2317 Skeena Dr",
    "sg:city":"Kamloops",
    "sg:classifiers":[
        {
            "category":"Retail",
            "subcategory":"Portrait Studio",
            "type":"Services"
        }
    ],
    "sg:phone":"+1 250 828 0006",
    "sg:postcode":"V2E 1Y2",
    "sg:province":"BC",
    "sg:tags":[
        "photographer"
    ],
    "wof:name":"Photos By Wendy",
    "wof:placetype":"venue"
},
  "geometry": {"coordinates":[-120.253654,50.659916],"type":"Point"}
}