{
  "type": "Feature",
  "properties": {
    "addr:full":"4 Drummond St Newboro ON K0G 1P0",
    "addr:housenumber":"4",
    "addr:postcode":"k0g 1p0",
    "addr:street":"Drummond St",
    "iso:country":"CA",
    "sg:address":"4 Drummond St",
    "sg:city":"Newboro",
    "sg:classifiers":[
        {
            "category":"Restaurant",
            "type":"Food & Drink"
        }
    ],
    "sg:phone":"+1 613 272 2900",
    "sg:postcode":"K0G 1P0",
    "sg:province":"ON",
    "sg:tags":[
        "motel",
        "hotel"
    ],
    "wof:name":"Stage Coach Inn",
    "wof:placetype":"venue"
},
  "geometry": {"coordinates":[-76.31927490229999,44.6504516602],"type":"Point"}
}