{
  "type": "Feature",
  "properties": {
    "addr:full":"Chateauguay QC J6K 5E4",
    "addr:postcode":"j6k 5e4",
    "iso:country":"CA",
    "sg:city":"Chateauguay",
    "sg:classifiers":[
        {
            "category":"Restaurant",
            "type":"Food & Drink"
        }
    ],
    "sg:phone":"+1 450 692 4219",
    "sg:postcode":"J6K 5E4",
    "sg:province":"QC",
    "wof:name":"Resto-Bar Amici",
    "wof:placetype":"venue"
},
  "geometry": {"coordinates":[-73.71369900000001,45.361176],"type":"Point"}
}