{
  "type": "Feature",
  "properties": {
    "addr:full":"Mohawak Beach Rd Kahnawake QC J0L 1B0",
    "addr:postcode":"j0l 1b0",
    "addr:street":"Beach Rd",
    "iso:country":"CA",
    "sg:address":"Mohawak Beach Rd",
    "sg:city":"Kahnawake",
    "sg:classifiers":[
        {
            "category":"Building & Trades",
            "subcategory":"Landscaping Services",
            "type":"Services"
        }
    ],
    "sg:phone":"+1 450 632 7506",
    "sg:postcode":"J0L 1B0",
    "sg:province":"QC",
    "sg:tags":[
        "tree"
    ],
    "wof:name":"Kirby Tree Experts",
    "wof:placetype":"venue"
},
  "geometry": {"coordinates":[-73.69050598139999,45.4080162048],"type":"Point"}
}