{
  "type": "Feature",
  "properties": {
    "iso:country":"CA",
    "sg:address":"3502 Manning Dr",
    "sg:city":"London",
    "sg:classifiers":[
        {
            "category":"Building & Trades",
            "subcategory":"Construction",
            "type":"Services"
        }
    ],
    "sg:phone":"+1 519 685 3717",
    "sg:postcode":"N6L 1K6",
    "sg:province":"ON",
    "sg:tags":[
        "excavating",
        "contractor"
    ],
    "wof:name":"Jcj Contracting",
    "wof:placetype":"venue"
},
  "geometry": {"coordinates":[-81.2185974121,42.8762207031],"type":"Point"}
}