{
  "type": "Feature",
  "properties": {
    "addr:full":"LA Presentation QC J0H 1B0",
    "addr:postcode":"j0h 1b0",
    "iso:country":"CA",
    "sg:city":"LA Presentation",
    "sg:classifiers":[
        {
            "category":"Manufacturing",
            "subcategory":"Tools & Machinery",
            "type":"Manufacturing & Wholesale Goods"
        }
    ],
    "sg:phone":"+1 450 796 5878",
    "sg:postcode":"J0H 1B0",
    "sg:province":"QC",
    "sg:tags":[
        "machine",
        "sewing",
        "system",
        "automation"
    ],
    "wof:name":"Technifil Machine A Coudre Inc",
    "wof:placetype":"venue"
},
  "geometry": {"coordinates":[-73.048714,45.663361],"type":"Point"}
}