{
  "type": "Feature",
  "properties": {
    "addr:full":"39267 Londesborough Rd Londesborough ON N0M 2H0",
    "addr:postcode":"39267;n0m 2h0",
    "addr:street":"Londesborough Rd",
    "iso:country":"CA",
    "sg:address":"39267 Londesborough Rd",
    "sg:city":"Londesborough",
    "sg:classifiers":[
        {
            "category":"Wholesale",
            "subcategory":"Machinery & Supplies",
            "type":"Manufacturing & Wholesale Goods"
        }
    ],
    "sg:phone":"+1 519 523 4922",
    "sg:postcode":"N0M 2H0",
    "sg:province":"ON",
    "sg:tags":[
        "equipment",
        "parts",
        "tractor"
    ],
    "wof:name":"Ontario Used Tractor Parts",
    "wof:placetype":"venue"
},
  "geometry": {"coordinates":[-81.47942399999999,43.699009],"type":"Point"}
}