{
  "type": "Feature",
  "properties": {
    "iso:country":"CA",
    "sg:address":"143 Dunlevy Ave",
    "sg:city":"Vancouver",
    "sg:classifiers":[
        {
            "category":"Real Estate",
            "subcategory":"Real Estate Operator",
            "type":"Services"
        }
    ],
    "sg:phone":"+1 604 681 1015",
    "sg:postcode":"V6A 3A4",
    "sg:province":"BC",
    "sg:tags":[
        "boarding",
        "house"
    ],
    "wof:name":"New Wings Hotel",
    "wof:placetype":"venue"
},
  "geometry": {"coordinates":[-123.095436,49.283642],"type":"Point"}
}