{
  "type": "Feature",
  "properties": {
    "addr:full":"Corunna ON N0N 1G0",
    "addr:postcode":"n0n 1g0",
    "iso:country":"CA",
    "sg:city":"Corunna",
    "sg:classifiers":[
        {
            "category":"Manufacturing",
            "subcategory":"Motor Vehicles & Parts",
            "type":"Manufacturing & Wholesale Goods"
        }
    ],
    "sg:phone":"+1 519 344 1130",
    "sg:postcode":"N0N 1G0",
    "sg:province":"ON",
    "sg:tags":[
        "locomotive"
    ],
    "wof:name":"Gatx Rail Canada",
    "wof:placetype":"venue"
},
  "geometry": {"coordinates":[-82.43420399999999,42.912193],"type":"Point"}
}