{
  "type": "Feature",
  "properties": {
    "addr:full":"7985 Rue Des Metis Quebec QC G2K 1V3",
    "addr:housenumber":"7985",
    "addr:postcode":"g2k 1v3",
    "addr:street":"Rue Des Metis",
    "iso:country":"CA",
    "sg:address":"7985 Rue Des Metis",
    "sg:city":"Quebec",
    "sg:classifiers":[
        {
            "category":"Autos & Motor Vehicles",
            "subcategory":"Automobile Sales",
            "type":"Retail Goods"
        }
    ],
    "sg:phone":"+1 418 628 9602",
    "sg:postcode":"G2K 1V3",
    "sg:province":"QC",
    "sg:tags":[
        "car",
        "dealer"
    ],
    "wof:name":"Automobiles C Marc Enr",
    "wof:placetype":"venue"
},
  "geometry": {"coordinates":[-71.28132629389999,46.8508415222],"type":"Point"}
}