{
  "type": "Feature",
  "properties": {
    "addr:full":"Montreal QC H1X 1K2",
    "addr:postcode":"h1x 1k2",
    "iso:country":"CA",
    "sg:city":"Montreal",
    "sg:classifiers":[
        {
            "category":"Wholesale",
            "subcategory":"Jewelry",
            "type":"Manufacturing & Wholesale Goods"
        }
    ],
    "sg:phone":"+1 514 722 0113",
    "sg:postcode":"H1X 1K2",
    "sg:province":"QC",
    "sg:tags":[
        "jeweler",
        "supply"
    ],
    "wof:name":"Distribution Klemco",
    "wof:placetype":"venue"
},
  "geometry": {"coordinates":[-73.5799255371,45.5536079407],"type":"Point"}
}