{
  "type": "Feature",
  "properties": {
    "addr:full":"4334 Kingston Rd Scarborough ON M1E 2M8",
    "addr:housenumber":"4334",
    "addr:postcode":"m1e 2m8",
    "addr:street":"Kingston Rd",
    "iso:country":"CA",
    "sg:address":"4334 Kingston Rd",
    "sg:city":"Scarborough",
    "sg:classifiers":[
        {
            "category":"Autos & Motor Vehicles",
            "subcategory":"Automobile Sales",
            "type":"Retail Goods"
        }
    ],
    "sg:phone":"+1 416 281 1234",
    "sg:postcode":"M1E 2M8",
    "sg:province":"ON",
    "sg:tags":[
        "car",
        "dealer"
    ],
    "wof:name":"Action Honda",
    "wof:placetype":"venue"
},
  "geometry": {"coordinates":[-79.192238,43.765121],"type":"Point"}
}