{
  "type": "Feature",
  "properties": {
    "addr:full":"51 Underhill Dr North York ON M3A 2J8",
    "addr:housenumber":"51",
    "addr:postcode":"m3a 2j8",
    "addr:street":"Underhill Dr",
    "iso:country":"CA",
    "sg:address":"51 Underhill Dr",
    "sg:city":"North York",
    "sg:classifiers":[
        {
            "category":"Shopping",
            "type":"Retail Goods"
        }
    ],
    "sg:phone":"+1 416 444 9463",
    "sg:postcode":"M3A 2J8",
    "sg:province":"ON",
    "sg:tags":[
        "equipment",
        "wine",
        "supply"
    ],
    "wof:name":"Wine Not",
    "wof:placetype":"venue"
},
  "geometry": {"coordinates":[-79.32588199999999,43.74469],"type":"Point"}
}