{
  "type": "Feature",
  "properties": {
    "iso:country":"CA",
    "sg:address":"51 Underhill Dr",
    "sg:city":"North York",
    "sg:classifiers":[
        {
            "category":"Shopping",
            "type":"Retail Goods"
        }
    ],
    "sg:phone":"+1 416 444 9463",
    "sg:postcode":"M3A 2J8",
    "sg:province":"ON",
    "sg:tags":[
        "equipment",
        "wine",
        "supply"
    ],
    "wof:name":"Wine Not",
    "wof:placetype":"venue"
},
  "geometry": {"coordinates":[-79.325882,43.74469],"type":"Point"}
}