{
  "type": "Feature",
  "properties": {
    "iso:country":"CA",
    "sg:address":"385 Mountain Ave",
    "sg:city":"Winkler",
    "sg:classifiers":[
        {
            "category":"Social Services",
            "type":"Services"
        }
    ],
    "sg:phone":"+1 204 331 3930",
    "sg:postcode":"R6W 4A6",
    "sg:province":"MB",
    "sg:tags":[
        "counselor",
        "marriage",
        "family"
    ],
    "wof:name":"Pembina Counselling Ctr",
    "wof:placetype":"venue"
},
  "geometry": {"coordinates":[-97.93882000000001,49.181877],"type":"Point"}
}