{
  "type": "Feature",
  "properties": {
    "addr:full":"4769 Hazel St # 128 Burnaby BC V5H 1S7",
    "addr:housenumber":"4769",
    "addr:postcode":"v5h 1s7",
    "addr:street":"Hazel St # 128",
    "iso:country":"CA",
    "sg:address":"4769 Hazel St # 128",
    "sg:city":"Burnaby",
    "sg:classifiers":[
        {
            "category":"Real Estate",
            "subcategory":"Real Estate Operator",
            "type":"Services"
        }
    ],
    "sg:phone":"+1 604 433 5321",
    "sg:postcode":"V5H 1S7",
    "sg:province":"BC",
    "sg:tags":[
        "apartment"
    ],
    "wof:name":"Parkview Towers I",
    "wof:placetype":"venue"
},
  "geometry": {"coordinates":[-122.99694100000001,49.228817],"type":"Point"}
}