{
  "type": "Feature",
  "properties": {
    "addr:full":"1400 Boul Des Recollets Trois-Rivieres QC G8Z 4L5",
    "addr:housenumber":"1400",
    "addr:postcode":"g8z 4l5",
    "addr:street":"Boul Des Recollets Trois-Rivieres",
    "iso:country":"CA",
    "sg:address":"1400 Boul Des Recollets",
    "sg:city":"Trois-Rivieres",
    "sg:classifiers":[
        {
            "category":"Shopping",
            "subcategory":"Bicycles & Sporting Goods",
            "type":"Retail Goods"
        }
    ],
    "sg:phone":"+1 819 373 2915",
    "sg:postcode":"G8Z 4L5",
    "sg:province":"QC",
    "wof:name":"Yeti",
    "wof:placetype":"venue"
},
  "geometry": {"coordinates":[-72.581322,46.350655],"type":"Point"}
}