{
  "type": "Feature",
  "properties": {
    "addr:full":"Mississauga ON L5B 1M5",
    "addr:postcode":"l5b 1m5",
    "iso:country":"CA",
    "sg:city":"Mississauga",
    "sg:classifiers":[
        {
            "category":"Real Estate",
            "subcategory":"Real Estate Agent",
            "type":"Services"
        }
    ],
    "sg:phone":"+1 905 275 9400",
    "sg:postcode":"L5B 1M5",
    "sg:province":"ON",
    "wof:name":"Royal Le Page Real Estate Svc",
    "wof:placetype":"venue"
},
  "geometry": {"coordinates":[-79.63859558110001,43.593120575],"type":"Point"}
}