{
  "type": "Feature",
  "properties": {
    "iso:country":"CA",
    "sg:address":"3655 Montee Gagnon",
    "sg:city":"Terrebonne",
    "sg:classifiers":[
        {
            "category":"Cinema",
            "subcategory":"Movie Rental",
            "type":"Entertainment"
        }
    ],
    "sg:phone":"+1 450 433 5111",
    "sg:postcode":"J6Y 1J4",
    "sg:province":"QC",
    "sg:tags":[
        "leasing",
        "video",
        "disc",
        "tape"
    ],
    "wof:name":"Club Video Premier Choix Enr",
    "wof:placetype":"venue"
},
  "geometry": {"coordinates":[-73.8109970093,45.6987457275],"type":"Point"}
}