{
  "type": "Feature",
  "properties": {
    "addr:full":"Scarborough ON M1L 4N2",
    "addr:postcode":"m1l 4n2",
    "iso:country":"CA",
    "sg:city":"Scarborough",
    "sg:classifiers":[
        {
            "category":"Shopping",
            "type":"Retail Goods"
        }
    ],
    "sg:phone":"+1 416 755 1985",
    "sg:postcode":"M1L 4N2",
    "sg:province":"ON",
    "sg:tags":[
        "picture",
        "frame"
    ],
    "wof:name":"Poster Seal",
    "wof:placetype":"venue"
},
  "geometry": {"coordinates":[-79.28019,43.72776],"type":"Point"}
}