{
  "type": "Feature",
  "properties": {
    "iso:country":"CA",
    "sg:address":"7168 Hamilton Rd",
    "sg:city":"Putnam",
    "sg:classifiers":[
        {
            "category":"Restaurant",
            "type":"Food & Drink"
        }
    ],
    "sg:phone":"+1 519 485 1391",
    "sg:postcode":"N0L 2B0",
    "sg:province":"ON",
    "wof:name":"Rustic Lunch",
    "wof:placetype":"venue"
},
  "geometry": {"coordinates":[-80.9771118164,42.9781608582],"type":"Point"}
}