{
  "type": "Feature",
  "properties": {
    "addr:full":"North York ON M2N 3B3",
    "addr:postcode":"m2n 3b3",
    "iso:country":"CA",
    "sg:city":"North York",
    "sg:classifiers":[
        {
            "category":"Health Services",
            "subcategory":"Doctor",
            "type":"Services"
        }
    ],
    "sg:phone":"+1 416 733 9100",
    "sg:postcode":"M2N 3B3",
    "sg:province":"ON",
    "sg:tags":[
        "dentist"
    ],
    "wof:name":"Kershen, Hal DDS",
    "wof:placetype":"venue"
},
  "geometry": {"coordinates":[-79.3923034668,43.7654953003],"type":"Point"}
}