{
  "type": "Feature",
  "properties": {
    "addr:full":"344 Av Rouleau Rimouski QC G5L 5V9",
    "addr:postcode":"g5l 5v9",
    "addr:street":"344 Av Rouleau",
    "iso:country":"CA",
    "sg:address":"344 Av Rouleau",
    "sg:city":"Rimouski",
    "sg:classifiers":[
        {
            "category":"Health Services",
            "subcategory":"Nursing And Care Facility",
            "type":"Services"
        }
    ],
    "sg:phone":"+1 418 722 6335",
    "sg:postcode":"G5L 5V9",
    "sg:province":"QC",
    "sg:tags":[
        "home",
        "rest"
    ],
    "wof:name":"Arbre DE Vie DE Rimouski",
    "wof:placetype":"venue"
},
  "geometry": {"coordinates":[-68.52330000000001,48.441311],"type":"Point"}
}