{
  "type": "Feature",
  "properties": {
    "addr:full":"6207 76 Ave NW Edmonton AB T6B 0A7",
    "addr:housenumber":"6207",
    "addr:postcode":"t6b 0a7",
    "addr:street":"76 Ave Nw",
    "iso:country":"CA",
    "sg:address":"6207 76 Ave NW",
    "sg:city":"Edmonton",
    "sg:classifiers":[
        {
            "category":"Professional",
            "type":"Services"
        }
    ],
    "sg:phone":"+1 780 435 0642",
    "sg:postcode":"T6B 0A7",
    "sg:province":"AB",
    "sg:tags":[
        "metal",
        "cleaning"
    ],
    "wof:name":"Rmc Industries Ltd",
    "wof:placetype":"venue"
},
  "geometry": {"coordinates":[-113.42578899999999,53.512302],"type":"Point"}
}