{
  "type": "Feature",
  "properties": {
    "iso:country":"CA",
    "sg:address":"861 Bloor St W",
    "sg:city":"Toronto",
    "sg:classifiers":[
        {
            "category":"Personal",
            "subcategory":"Barber",
            "type":"Services"
        }
    ],
    "sg:phone":"+1 416 531 0421",
    "sg:postcode":"M6G 1M4",
    "sg:province":"ON",
    "wof:name":"Crasher's Barber Shop & Salon",
    "wof:placetype":"venue"
},
  "geometry": {"coordinates":[-79.42445373539999,43.6621894836],"type":"Point"}
}