{
  "type": "Feature",
  "properties": {
    "iso:country":"CA",
    "sg:city":"Waterloo",
    "sg:classifiers":[
        {
            "category":"Shopping",
            "subcategory":"Computers & Home Electronics",
            "type":"Retail Goods"
        }
    ],
    "sg:phone":"+1 519 886 9750",
    "sg:postcode":"N2J 4R4",
    "sg:province":"ON",
    "sg:tags":[
        "software"
    ],
    "wof:name":"Softplan Technical Support",
    "wof:placetype":"venue"
},
  "geometry": {"coordinates":[-80.51535,43.489269],"type":"Point"}
}