{
  "type": "Feature",
  "properties": {
    "addr:full":"445 3rd St E Meota SK S0M 1X0",
    "addr:housenumber":"445",
    "addr:postcode":"s0m 1x0",
    "addr:street":"3Rd St;Meota",
    "iso:country":"CA",
    "sg:address":"445 3rd St E",
    "sg:city":"Meota",
    "sg:classifiers":[
        {
            "category":"Wholesale",
            "subcategory":"Groceries",
            "type":"Manufacturing & Wholesale Goods"
        }
    ],
    "sg:phone":"+1 306 892 2141",
    "sg:postcode":"S0M 1X0",
    "sg:province":"SK",
    "sg:tags":[
        "food",
        "product"
    ],
    "wof:name":"Watkins Quality Products",
    "wof:placetype":"venue"
},
  "geometry": {"coordinates":[-108.458656,53.033943],"type":"Point"}
}