{
  "type": "Feature",
  "properties": {
    "addr:full":"4 Locker Dr Ajax ON L1T 3K9",
    "addr:housenumber":"4",
    "addr:postcode":"l1t 3k9",
    "addr:street":"Locker Dr",
    "iso:country":"CA",
    "sg:address":"4 Locker Dr",
    "sg:city":"Ajax",
    "sg:classifiers":[
        {
            "category":"Professional",
            "subcategory":"Accounting & Tax Preparation",
            "type":"Services"
        }
    ],
    "sg:phone":"+1 905 686 8139",
    "sg:postcode":"L1T 3K9",
    "sg:province":"ON",
    "sg:tags":[
        "bookkeeping",
        "general"
    ],
    "wof:name":"Accounting Pro Bookkeeping Svc",
    "wof:placetype":"venue"
},
  "geometry": {"coordinates":[-79.03122711180001,43.8703384399],"type":"Point"}
}