{
  "type": "Feature",
  "properties": {
    "iso:country":"CA",
    "sg:address":"230 1st Ave E",
    "sg:city":"Central Butte",
    "sg:classifiers":[
        {
            "category":"Recreation",
            "type":"Entertainment"
        }
    ],
    "sg:phone":"+1 306 796 2185",
    "sg:postcode":"S0H 0T0",
    "sg:province":"SK",
    "sg:tags":[
        "skating",
        "rink"
    ],
    "wof:name":"Central Butte Arena",
    "wof:placetype":"venue"
},
  "geometry": {"coordinates":[-106.51249694800001,50.7961540222],"type":"Point"}
}