{
  "type": "Feature",
  "properties": {
    "addr:full":"4707 Rue Wellington Verdun QC H4G 1X2",
    "addr:housenumber":"4707",
    "addr:postcode":"h4g 1x2",
    "addr:street":"Rue Wellington",
    "iso:country":"CA",
    "sg:address":"4707 Rue Wellington",
    "sg:city":"Verdun",
    "sg:classifiers":[
        {
            "category":"Restaurant",
            "type":"Food & Drink"
        }
    ],
    "sg:phone":"+1 514 766 6205",
    "sg:postcode":"H4G 1X2",
    "sg:province":"QC",
    "wof:name":"Alexandre Terrasse Restaurant",
    "wof:placetype":"venue"
},
  "geometry": {"coordinates":[-73.5676116943,45.4577522278],"type":"Point"}
}