{
  "type": "Feature",
  "properties": {
    "addr:full":"36 Rue Saint-Jacques Saint-Jean-Sur-Richelieu QC J3B 2J7",
    "addr:housenumber":"36",
    "addr:postcode":"j3b 2j7",
    "addr:street":"Rue Saint-Jacques",
    "iso:country":"CA",
    "sg:address":"36 Rue Saint-Jacques",
    "sg:city":"Saint-Jean-Sur-Richelieu",
    "sg:classifiers":[
        {
            "category":"Personal",
            "subcategory":"Shoe Repair & Shine",
            "type":"Services"
        }
    ],
    "sg:phone":"+1 450 347 1489",
    "sg:postcode":"J3B 2J7",
    "sg:province":"QC",
    "sg:tags":[
        "repairing",
        "boot"
    ],
    "wof:name":"Cordonnerie Centrale",
    "wof:placetype":"venue"
},
  "geometry": {"coordinates":[-73.2516860962,45.3059196472],"type":"Point"}
}