{
  "type": "Feature",
  "properties": {
    "addr:full":"190 Rue Peel Montreal QC H3C 2G7",
    "addr:housenumber":"190",
    "addr:postcode":"h3c 2g7",
    "addr:street":"Rue Peel",
    "iso:country":"CA",
    "sg:address":"190 Rue Peel",
    "sg:city":"Montreal",
    "sg:classifiers":[
        {
            "category":"Shopping",
            "type":"Retail Goods"
        }
    ],
    "sg:phone":"+1 514 937 1689",
    "sg:postcode":"H3C 2G7",
    "sg:province":"QC",
    "sg:tags":[
        "picture",
        "frame"
    ],
    "wof:name":"Artifice Encadrement Sur",
    "wof:placetype":"venue"
},
  "geometry": {"coordinates":[-73.557999,45.493378],"type":"Point"}
}