{
  "type": "Feature",
  "properties": {
    "iso:country":"CA",
    "sg:address":"340 College St # 315",
    "sg:city":"Toronto",
    "sg:classifiers":[
        {
            "category":"Health Services",
            "subcategory":"Doctor",
            "type":"Services"
        }
    ],
    "sg:phone":"+1 416 929 5797",
    "sg:postcode":"M5T 3A9",
    "sg:province":"ON",
    "sg:tags":[
        "physician",
        "surgeon"
    ],
    "wof:name":"Conn, Garson S MD",
    "wof:placetype":"venue"
},
  "geometry": {"coordinates":[-79.40334320069999,43.6574478149],"type":"Point"}
}