{
  "type": "Feature",
  "properties": {
    "addr:full":"Thornhill ON L4J 8E1",
    "addr:postcode":"l4j 8e1",
    "iso:country":"CA",
    "sg:city":"Thornhill",
    "sg:classifiers":[
        {
            "category":"Professional",
            "subcategory":"Lawyer & Legal Services",
            "type":"Services"
        }
    ],
    "sg:phone":"+1 905 707 6677",
    "sg:postcode":"L4J 8E1",
    "sg:province":"ON",
    "sg:tags":[
        "attorney"
    ],
    "wof:name":"Breatross, Asher",
    "wof:placetype":"venue"
},
  "geometry": {"coordinates":[-79.44342803959999,43.8041267395],"type":"Point"}
}