{
  "type": "Feature",
  "properties": {
    "iso:country":"CA",
    "sg:address":"549 Hamilton Rd",
    "sg:city":"London",
    "sg:classifiers":[
        {
            "category":"Wholesale",
            "subcategory":"Groceries",
            "type":"Manufacturing & Wholesale Goods"
        }
    ],
    "sg:phone":"+1 519 433 5177",
    "sg:postcode":"N5Z 1S5",
    "sg:province":"ON",
    "sg:tags":[
        "baker"
    ],
    "wof:name":"London Bakery & Delicatessen",
    "wof:placetype":"venue"
},
  "geometry": {"coordinates":[-81.2145690918,42.980255127],"type":"Point"}
}