{
  "type": "Feature",
  "properties": {
    "addr:full":"790 Ch Canada Edmundston NB E3V 1W4",
    "addr:housenumber":"790",
    "addr:postcode":"e3v 1w4",
    "addr:street":"Ch",
    "iso:country":"CA",
    "sg:address":"790 Ch Canada",
    "sg:city":"Edmundston",
    "sg:classifiers":[
        {
            "category":"Manufacturing",
            "subcategory":"Tools & Machinery",
            "type":"Manufacturing & Wholesale Goods"
        }
    ],
    "sg:phone":"+1 506 739 6070",
    "sg:postcode":"E3V 1W4",
    "sg:province":"NB",
    "sg:tags":[
        "valve",
        "hydraulic"
    ],
    "wof:name":"Cdc Hydraulique Ltee",
    "wof:placetype":"venue"
},
  "geometry": {"coordinates":[-68.3524398804,47.3876914978],"type":"Point"}
}