{
  "type": "Feature",
  "properties": {
    "addr:full":"1200 4E Ave LA Pocatiere QC G0R 1Z0",
    "addr:housenumber":"1200",
    "addr:postcode":"g0r 1z0",
    "addr:street":"4E Ave",
    "iso:country":"CA",
    "sg:address":"1200 4E Ave",
    "sg:city":"LA Pocatiere",
    "sg:classifiers":[
        {
            "category":"Organizations",
            "subcategory":"Religious Organization",
            "type":"Services"
        }
    ],
    "sg:phone":"+1 418 856 1811",
    "sg:postcode":"G0R 1Z0",
    "sg:province":"QC",
    "sg:tags":[
        "church"
    ],
    "wof:name":"Eveche Ste Anne-LA Pocatiere",
    "wof:placetype":"venue"
},
  "geometry": {"coordinates":[-70.03224899999999,47.369015],"type":"Point"}
}