{
  "type": "Feature",
  "properties": {
    "addr:full":"888 Dundas St E Mississauga ON L4Y 4G6",
    "addr:housenumber":"888",
    "addr:postcode":"l4y 4g6",
    "addr:street":"Dundas St E",
    "iso:country":"CA",
    "sg:address":"888 Dundas St E",
    "sg:city":"Mississauga",
    "sg:classifiers":[
        {
            "category":"Food & Beverages",
            "subcategory":"Groceries & Convenience Stores",
            "type":"Retail Goods"
        }
    ],
    "sg:phone":"+1 905 803 9088",
    "sg:postcode":"L4Y 4G6",
    "sg:province":"ON",
    "sg:tags":[
        "grocer"
    ],
    "wof:name":"Oriental Food Ctr",
    "wof:placetype":"venue"
},
  "geometry": {"coordinates":[-79.59491,43.599052],"type":"Point"}
}