{
  "type": "Feature",
  "properties": {
    "addr:full":"125 1st St E North Vancouver BC V7L 1B2",
    "addr:housenumber":"125",
    "addr:postcode":"v7l 1b2",
    "addr:street":"1St St E",
    "iso:country":"CA",
    "sg:address":"125 1st St E",
    "sg:city":"North Vancouver",
    "sg:classifiers":[
        {
            "category":"Recreation",
            "type":"Entertainment"
        }
    ],
    "sg:phone":"+1 604 983 3799",
    "sg:postcode":"V7L 1B2",
    "sg:province":"BC",
    "sg:tags":[
        "martial",
        "arts",
        "instruction"
    ],
    "wof:name":"Champions Karate Academy",
    "wof:placetype":"venue"
},
  "geometry": {"coordinates":[-123.077805,49.311363],"type":"Point"}
}