{
  "type": "Feature",
  "properties": {
    "addr:full":"North York ON M3J 3H9",
    "addr:postcode":"m3j 3h9",
    "iso:country":"CA",
    "sg:city":"North York",
    "sg:classifiers":[
        {
            "category":"Restaurant",
            "type":"Food & Drink"
        }
    ],
    "sg:phone":"+1 416 665 1146",
    "sg:postcode":"M3J 3H9",
    "sg:province":"ON",
    "wof:name":"Magnetic Diner",
    "wof:placetype":"venue"
},
  "geometry": {"coordinates":[-79.4738082886,43.783203125],"type":"Point"}
}