{
  "type": "Feature",
  "properties": {
    "addr:full":"3650 Weston Rd North York ON M9L 1W2",
    "addr:housenumber":"3650",
    "addr:postcode":"m9l 1w2",
    "addr:street":"Weston Rd",
    "iso:country":"CA",
    "sg:address":"3650 Weston Rd",
    "sg:city":"North York",
    "sg:classifiers":[
        {
            "category":"Wholesale",
            "subcategory":"Office Equipment",
            "type":"Manufacturing & Wholesale Goods"
        }
    ],
    "sg:phone":"+1 416 740 2886",
    "sg:postcode":"M9L 1W2",
    "sg:province":"ON",
    "sg:tags":[
        "register",
        "cash",
        "supply"
    ],
    "wof:name":"Antique Cash Register CO",
    "wof:placetype":"venue"
},
  "geometry": {"coordinates":[-79.54444100000001,43.759811],"type":"Point"}
}