{
  "type": "Feature",
  "properties": {
    "iso:country":"CA",
    "sg:city":"Calgary",
    "sg:classifiers":[
        {
            "category":"Professional",
            "type":"Services"
        }
    ],
    "sg:phone":"+1 403 266 3885",
    "sg:postcode":"T2P 0L6",
    "sg:province":"AB",
    "sg:tags":[
        "geophysical"
    ],
    "wof:name":"Dove & Kay Exploration Ltd",
    "wof:placetype":"venue"
},
  "geometry": {"coordinates":[-114.070281982,51.0486335754],"type":"Point"}
}