{
  "type": "Feature",
  "properties": {
    "addr:full":"Brandon MB R7B 0S9",
    "addr:postcode":"r7b 0s9",
    "iso:country":"CA",
    "sg:city":"Brandon",
    "sg:classifiers":[
        {
            "category":"Shopping",
            "subcategory":"Clothing, Apparel, & Fashions",
            "type":"Retail Goods"
        }
    ],
    "sg:phone":"+1 204 725 4268",
    "sg:postcode":"R7B 0S9",
    "sg:province":"MB",
    "sg:tags":[
        "dressmaker"
    ],
    "wof:name":"Ann's Seamstress & Tailoring",
    "wof:placetype":"venue"
},
  "geometry": {"coordinates":[-99.97081,49.833107],"type":"Point"}
}