{
  "type": "Feature",
  "properties": {
    "addr:full":"Happy Valley-Goose Bay NL A0P 1C0",
    "addr:postcode":"a0p 1c0",
    "iso:country":"CA",
    "sg:city":"Happy Valley-Goose Bay",
    "sg:classifiers":[
        {
            "category":"Airport",
            "type":"Transportation"
        }
    ],
    "sg:phone":"+1 709 896 5445",
    "sg:postcode":"A0P 1C0",
    "sg:province":"NL",
    "wof:name":"Goose Bay Airport Corp",
    "wof:placetype":"venue"
},
  "geometry": {"coordinates":[-60.409203,53.308628],"type":"Point"}
}