{
  "type": "Feature",
  "properties": {
    "addr:full":"15909 92A Ave NW Edmonton AB T5R 5G2",
    "addr:housenumber":"15909",
    "addr:postcode":"t5r 5g2",
    "addr:street":"92A Ave Nw",
    "iso:country":"CA",
    "sg:address":"15909 92A Ave NW",
    "sg:city":"Edmonton",
    "sg:classifiers":[
        {
            "category":"Education",
            "subcategory":"Special Training",
            "type":"Public Place"
        }
    ],
    "sg:phone":"+1 780 489 7316",
    "sg:postcode":"T5R 5G2",
    "sg:province":"AB",
    "sg:tags":[
        "aid",
        "instruction",
        "first"
    ],
    "wof:name":"Life Works Consulting",
    "wof:placetype":"venue"
},
  "geometry": {"coordinates":[-113.594772339,53.5273132324],"type":"Point"}
}