{
  "type": "Feature",
  "properties": {
    "addr:full":"2365 13th Ave Regina SK S4P 0V8",
    "addr:housenumber":"2365",
    "addr:postcode":"s4p 0v8",
    "addr:street":"13Th Ave",
    "iso:country":"CA",
    "sg:address":"2365 13th Ave",
    "sg:city":"Regina",
    "sg:classifiers":[
        {
            "category":"Organizations",
            "subcategory":"Labor Organization",
            "type":"Services"
        }
    ],
    "sg:phone":"+1 306 777 0000",
    "sg:postcode":"S4P 0V8",
    "sg:province":"SK",
    "wof:name":"Communications Energy & Paper",
    "wof:placetype":"venue"
},
  "geometry": {"coordinates":[-104.614608765,50.4454078674],"type":"Point"}
}