{
  "type": "Feature",
  "properties": {
    "addr:full":"700 Broad St Regina SK S4R 8H7",
    "addr:housenumber":"700",
    "addr:postcode":"s4r 8h7",
    "addr:street":"Broad St",
    "iso:country":"CA",
    "sg:address":"700 Broad St",
    "sg:city":"Regina",
    "sg:classifiers":[
        {
            "category":"Autos & Motor Vehicles",
            "subcategory":"Automobile Sales",
            "type":"Retail Goods"
        }
    ],
    "sg:phone":"+1 306 522 2222",
    "sg:postcode":"S4R 8H7",
    "sg:province":"SK",
    "sg:tags":[
        "car",
        "dealer"
    ],
    "wof:name":"Triple Seven Chrysler",
    "wof:placetype":"venue"
},
  "geometry": {"coordinates":[-104.606628,50.468353],"type":"Point"}
}