{
  "type": "Feature",
  "properties": {
    "addr:full":"174 Charing Cross St Brantford ON N3R 2J4",
    "addr:housenumber":"174",
    "addr:postcode":"n3r 2j4",
    "addr:street":"Charing Cross St",
    "iso:country":"CA",
    "sg:address":"174 Charing Cross St",
    "sg:city":"Brantford",
    "sg:classifiers":[
        {
            "category":"Shopping",
            "type":"Retail Goods"
        }
    ],
    "sg:phone":"+1 519 753 3044",
    "sg:postcode":"N3R 2J4",
    "sg:province":"ON",
    "sg:tags":[
        "monument"
    ],
    "wof:name":"Brantford Monuments",
    "wof:placetype":"venue"
},
  "geometry": {"coordinates":[-80.260963,43.157734],"type":"Point"}
}