{
  "type": "Feature",
  "properties": {
    "addr:full":"4182 15th Ave Prince George BC V2M 1V8",
    "addr:housenumber":"4182",
    "addr:postcode":"v2m 1v8",
    "addr:street":"15Th Ave",
    "iso:country":"CA",
    "sg:address":"4182 15th Ave",
    "sg:city":"Prince George",
    "sg:classifiers":[
        {
            "category":"Bars & Pubs",
            "type":"Food & Drink"
        }
    ],
    "sg:phone":"+1 250 564 2160",
    "sg:postcode":"V2M 1V8",
    "sg:province":"BC",
    "wof:name":"Alfredo's Neighbourhood Pub",
    "wof:placetype":"venue"
},
  "geometry": {"coordinates":[-122.801033,53.910667],"type":"Point"}
}