{
  "type": "Feature",
  "properties": {
    "addr:full":"1613 Rue Saint-Denis Montreal QC H2X 3K3",
    "addr:housenumber":"1613",
    "addr:postcode":"h2x 3k3",
    "addr:street":"Rue Saint-Denis",
    "iso:country":"CA",
    "sg:address":"1613 Rue Saint-Denis",
    "sg:city":"Montreal",
    "sg:classifiers":[
        {
            "category":"Travel",
            "subcategory":"Travel Agent",
            "type":"Entertainment"
        }
    ],
    "sg:phone":"+1 514 843 8511",
    "sg:postcode":"H2X 3K3",
    "sg:province":"QC",
    "sg:tags":[
        "agency",
        "bureau"
    ],
    "wof:name":"Voyages Campus Swap",
    "wof:placetype":"venue"
},
  "geometry": {"coordinates":[-73.562675,45.514919],"type":"Point"}
}