{
  "type": "Feature",
  "properties": {
    "addr:full":"617 Mill St Port Elgin ON N0H 2C0",
    "addr:housenumber":"617",
    "addr:postcode":"n0h 2c0",
    "addr:street":"Mill St",
    "iso:country":"CA",
    "sg:address":"617 Mill St",
    "sg:city":"Port Elgin",
    "sg:classifiers":[
        {
            "category":"Personal",
            "subcategory":"Beauty Salon",
            "type":"Services"
        }
    ],
    "sg:phone":"+1 519 832 2527",
    "sg:postcode":"N0H 2C0",
    "sg:province":"ON",
    "wof:name":"Hair Unlimited",
    "wof:placetype":"venue"
},
  "geometry": {"coordinates":[-81.38709299999999,44.437386],"type":"Point"}
}