{
  "type": "Feature",
  "properties": {
    "addr:full":"Edmonton AB T6E 6N1",
    "addr:postcode":"t6e 6n1",
    "iso:country":"CA",
    "sg:city":"Edmonton",
    "sg:classifiers":[
        {
            "category":"Wholesale",
            "subcategory":"Machinery & Supplies",
            "type":"Manufacturing & Wholesale Goods"
        }
    ],
    "sg:phone":"+1 780 462 0075",
    "sg:postcode":"T6E 6N1",
    "sg:province":"AB",
    "sg:tags":[
        "janitor"
    ],
    "wof:name":"Busy-Bee Sanitary Supplies Inc",
    "wof:placetype":"venue"
},
  "geometry": {"coordinates":[-113.479652405,53.4753303528],"type":"Point"}
}