{
  "type": "Feature",
  "properties": {
    "addr:full":"3 Hazlett Close Red Deer AB T4N 5N3",
    "addr:housenumber":"3",
    "addr:postcode":"t4n 5n3",
    "addr:street":"Hazlett Close",
    "iso:country":"CA",
    "sg:address":"3 Hazlett Close",
    "sg:city":"Red Deer",
    "sg:classifiers":[
        {
            "category":"Home & Garden",
            "subcategory":"Home Furnishings",
            "type":"Retail Goods"
        }
    ],
    "sg:phone":"+1 403 343 3294",
    "sg:postcode":"T4N 5N3",
    "sg:province":"AB",
    "sg:tags":[
        "installation",
        "drapery"
    ],
    "wof:name":"Mardale Drapery Installation",
    "wof:placetype":"venue"
},
  "geometry": {"coordinates":[-113.835075378,52.2841377258],"type":"Point"}
}