{
  "type": "Feature",
  "properties": {
    "addr:full":"168 Brock St W Uxbridge ON L9P 1E8",
    "addr:housenumber":"168",
    "addr:postcode":"l9p 1e8",
    "addr:street":"Brock St W",
    "iso:country":"CA",
    "sg:address":"168 Brock St W",
    "sg:city":"Uxbridge",
    "sg:classifiers":[
        {
            "category":"Autos & Motor Vehicles",
            "subcategory":"Auto Supplies",
            "type":"Retail Goods"
        }
    ],
    "sg:phone":"+1 905 852 1902",
    "sg:postcode":"L9P 1E8",
    "sg:province":"ON",
    "sg:tags":[
        "tire"
    ],
    "wof:name":"Ontario Tire & Farm Equipment",
    "wof:placetype":"venue"
},
  "geometry": {"coordinates":[-79.128006,44.107502],"type":"Point"}
}