{
  "type": "Feature",
  "properties": {
    "addr:full":"285 Albert St Corunna ON N0N 1G0",
    "addr:housenumber":"285",
    "addr:postcode":"n0n 1g0",
    "addr:street":"Albert St",
    "iso:country":"CA",
    "sg:address":"285 Albert St",
    "sg:city":"Corunna",
    "sg:classifiers":[
        {
            "category":"Manufacturing",
            "subcategory":"Chemicals & Compounds",
            "type":"Manufacturing & Wholesale Goods"
        }
    ],
    "sg:phone":"+1 519 862 1445",
    "sg:postcode":"N0N 1G0",
    "sg:province":"ON",
    "sg:tags":[
        "plastic"
    ],
    "wof:name":"Nova Chemicals",
    "wof:placetype":"venue"
},
  "geometry": {"coordinates":[-82.437431,42.894798],"type":"Point"}
}