{
  "type": "Feature",
  "properties": {
    "addr:full":"166 Gainsborough Rd Hamilton ON L8E 1E5",
    "addr:housenumber":"166",
    "addr:postcode":"l8e 1e5",
    "addr:street":"Gainsborough Rd",
    "iso:country":"CA",
    "sg:address":"166 Gainsborough Rd",
    "sg:city":"Hamilton",
    "sg:classifiers":[
        {
            "category":"Personal",
            "subcategory":"Beauty Salon",
            "type":"Services"
        }
    ],
    "sg:phone":"+1 905 561 6029",
    "sg:postcode":"L8E 1E5",
    "sg:province":"ON",
    "wof:name":"Tiara Hair Fashion",
    "wof:placetype":"venue"
},
  "geometry": {"coordinates":[-79.762024,43.228874],"type":"Point"}
}