{
  "type": "Feature",
  "properties": {
    "addr:full":"3151 33E Rue Grand-Mere QC G9T 3N9",
    "addr:housenumber":"3151",
    "addr:postcode":"g9t 3n9",
    "addr:street":"33E Rue Grand-Mere",
    "iso:country":"CA",
    "sg:address":"3151 33E Rue",
    "sg:city":"Grand-Mere",
    "sg:classifiers":[
        {
            "category":"Health Services",
            "subcategory":"Nursing And Care Facility",
            "type":"Services"
        }
    ],
    "sg:phone":"+1 819 538 2626",
    "sg:postcode":"G9T 3N9",
    "sg:province":"QC",
    "sg:tags":[
        "home",
        "retirement",
        "community"
    ],
    "wof:name":"Maison Claire Daniel",
    "wof:placetype":"venue"
},
  "geometry": {"coordinates":[-72.7334060669,46.6140594482],"type":"Point"}
}