{
  "type": "Feature",
  "properties": {
    "addr:full":"Victoria BC V8R 1H8",
    "addr:postcode":"v8r 1h8",
    "iso:country":"CA",
    "sg:city":"Victoria",
    "sg:classifiers":[
        {
            "category":"Organizations",
            "subcategory":"Community Association",
            "type":"Services"
        }
    ],
    "sg:phone":"+1 250 598 3722",
    "sg:postcode":"V8R 1H8",
    "sg:province":"BC",
    "sg:tags":[
        "fraternal"
    ],
    "wof:name":"War Amputations of Canada",
    "wof:placetype":"venue"
},
  "geometry": {"coordinates":[-123.33573199999999,48.426888],"type":"Point"}
}