{
  "type": "Feature",
  "properties": {
    "addr:full":"264 Spadina Ave Toronto ON M5T 2E4",
    "addr:housenumber":"264",
    "addr:postcode":"m5t 2e4",
    "addr:street":"Spadina Ave",
    "iso:country":"CA",
    "sg:address":"264 Spadina Ave",
    "sg:city":"Toronto",
    "sg:classifiers":[
        {
            "category":"Shopping",
            "subcategory":"Shoes",
            "type":"Retail Goods"
        }
    ],
    "sg:phone":"+1 416 351 0315",
    "sg:postcode":"M5T 2E4",
    "sg:province":"ON",
    "wof:name":"In Shoes",
    "wof:placetype":"venue"
},
  "geometry": {"coordinates":[-79.39799499999999,43.652004],"type":"Point"}
}