{
  "type": "Feature",
  "properties": {
    "iso:country":"CA",
    "sg:address":"536 Rue Principale",
    "sg:city":"Beresford",
    "sg:classifiers":[
        {
            "category":"Building & Trades",
            "subcategory":"Landscaping Services",
            "type":"Services"
        }
    ],
    "sg:phone":"+1 506 542 9080",
    "sg:postcode":"E8K 2A6",
    "sg:province":"NB",
    "sg:tags":[
        "landscape",
        "contractor"
    ],
    "wof:name":"Pelouse Brunswick Lawn",
    "wof:placetype":"venue"
},
  "geometry": {"coordinates":[-65.7101593018,47.7286605835],"type":"Point"}
}