{
  "type": "Feature",
  "properties": {
    "addr:full":"Baie-Saint-Paul QC G3Z 1R7",
    "addr:postcode":"g3z 1r7",
    "iso:country":"CA",
    "sg:city":"Baie-Saint-Paul",
    "sg:classifiers":[
        {
            "category":"Wholesale",
            "subcategory":"Meat",
            "type":"Manufacturing & Wholesale Goods"
        }
    ],
    "sg:phone":"+1 418 240 2122",
    "sg:postcode":"G3Z 1R7",
    "sg:province":"QC",
    "wof:name":"Alimentation Le Boeuf Rouge",
    "wof:placetype":"venue"
},
  "geometry": {"coordinates":[-70.51750183110001,47.4475402832],"type":"Point"}
}