{
  "type": "Feature",
  "properties": {
    "iso:country":"CA",
    "sg:city":"Conche",
    "sg:classifiers":[
        {
            "category":"Government",
            "subcategory":"Office",
            "type":"Public Place"
        }
    ],
    "sg:phone":"+1 709 622 4531",
    "sg:postcode":"A0K 1Y0",
    "sg:province":"NL",
    "sg:tags":[
        "village"
    ],
    "wof:name":"Community Council",
    "wof:placetype":"venue"
},
  "geometry": {"coordinates":[-55.8949508667,50.896282196],"type":"Point"}
}