{
  "type": "Feature",
  "properties": {
    "addr:full":"North York ON M9M 2E3",
    "addr:postcode":"m9m 2e3",
    "iso:country":"CA",
    "sg:city":"North York",
    "sg:classifiers":[
        {
            "category":"Wholesale",
            "subcategory":"Scrap",
            "type":"Manufacturing & Wholesale Goods"
        }
    ],
    "sg:phone":"+1 416 744 8995",
    "sg:postcode":"M9M 2E3",
    "sg:province":"ON",
    "sg:tags":[
        "cloth",
        "wiping"
    ],
    "wof:name":"Ontario Wipers & Textiles",
    "wof:placetype":"venue"
},
  "geometry": {"coordinates":[-79.550552,43.750473],"type":"Point"}
}