{
  "type": "Feature",
  "properties": {
    "addr:full":"6580 Tamany Dr Victoria BC V8Z 6Y9",
    "addr:postcode":"6580;v8z 6y9",
    "addr:street":"Tamany Dr",
    "iso:country":"CA",
    "sg:address":"6580 Tamany Dr",
    "sg:city":"Victoria",
    "sg:classifiers":[
        {
            "category":"Building & Trades",
            "subcategory":"Cleaning & Sanitation",
            "type":"Services"
        }
    ],
    "sg:phone":"+1 250 652 6216",
    "sg:postcode":"V8Z 6Y9",
    "sg:province":"BC",
    "sg:tags":[
        "chemical"
    ],
    "wof:name":"Old Victoria Soap CO Ltd",
    "wof:placetype":"venue"
},
  "geometry": {"coordinates":[-123.364517212,48.428314209],"type":"Point"}
}