{
  "type": "Feature",
  "properties": {
    "addr:full":"Toronto ON M5T 3J1",
    "addr:postcode":"m5t 3j1",
    "iso:country":"CA",
    "sg:city":"Toronto",
    "sg:classifiers":[
        {
            "category":"Education",
            "subcategory":"College",
            "type":"Public Place"
        }
    ],
    "sg:phone":"+1 416 348 9710",
    "sg:postcode":"M5T 3J1",
    "sg:province":"ON",
    "sg:tags":[
        "academic",
        "school"
    ],
    "wof:name":"Fields Institute",
    "wof:placetype":"venue"
},
  "geometry": {"coordinates":[-79.39730072019999,43.6585350037],"type":"Point"}
}