{
  "type": "Feature",
  "properties": {
    "addr:full":"29 46E Av O Blainville QC J7C 1L3",
    "addr:housenumber":"29",
    "addr:postcode":"j7c 1l3",
    "addr:street":"46E Av O",
    "iso:country":"CA",
    "sg:address":"29 46E Av O",
    "sg:city":"Blainville",
    "sg:classifiers":[
        {
            "category":"Building & Trades",
            "subcategory":"Pest Control",
            "type":"Services"
        }
    ],
    "sg:phone":"+1 450 430 2385",
    "sg:postcode":"J7C 1L3",
    "sg:province":"QC",
    "wof:name":"Extermination Pare Enr",
    "wof:placetype":"venue"
},
  "geometry": {"coordinates":[-73.865189,45.666096],"type":"Point"}
}