{
  "type": "Feature",
  "properties": {
    "iso:country":"CA",
    "sg:address":"1300 Rue Sainte-Catherine O",
    "sg:city":"Montreal",
    "sg:classifiers":[
        {
            "category":"Manufacturing",
            "subcategory":"Apparel",
            "type":"Manufacturing & Wholesale Goods"
        }
    ],
    "sg:phone":"+1 514 398 9130",
    "sg:postcode":"H3G 1P6",
    "sg:province":"QC",
    "wof:name":"Bcbg",
    "wof:placetype":"venue"
},
  "geometry": {"coordinates":[-73.5552062988,45.5193367004],"type":"Point"}
}