{
  "type": "Feature",
  "properties": {
    "addr:full":"72 Rue Roy Ormstown QC J0S 1K0",
    "addr:housenumber":"72",
    "addr:postcode":"j0s 1k0",
    "addr:street":"Rue Roy",
    "iso:country":"CA",
    "sg:address":"72 Rue Roy",
    "sg:city":"Ormstown",
    "sg:classifiers":[
        {
            "category":"Social Services",
            "subcategory":"Job Training",
            "type":"Services"
        }
    ],
    "sg:phone":"+1 450 829 1106",
    "sg:postcode":"J0S 1K0",
    "sg:province":"QC",
    "sg:tags":[
        "rehabilitation"
    ],
    "wof:name":"Services DE Readaptation Du",
    "wof:placetype":"venue"
},
  "geometry": {"coordinates":[-73.991355896,45.1216812134],"type":"Point"}
}