{
  "type": "Feature",
  "properties": {
    "iso:country":"CA",
    "sg:address":"301 Balmoral Ave",
    "sg:city":"Cornwall",
    "sg:classifiers":[
        {
            "category":"Retail",
            "subcategory":"Auto Repair",
            "type":"Services"
        }
    ],
    "sg:phone":"+1 613 933 3370",
    "sg:postcode":"K6H 3G6",
    "sg:province":"ON",
    "sg:tags":[
        "repairing",
        "automobile"
    ],
    "wof:name":"Fern Leroux Svc Ctr Ltd",
    "wof:placetype":"venue"
},
  "geometry": {"coordinates":[-74.73834228520001,45.0405273438],"type":"Point"}
}