{
  "type": "Feature",
  "properties": {
    "iso:country":"CA",
    "sg:address":"346 Wyecroft Rd",
    "sg:city":"Oakville",
    "sg:classifiers":[
        {
            "category":"Manufacturing",
            "subcategory":"Tools & Machinery",
            "type":"Manufacturing & Wholesale Goods"
        }
    ],
    "sg:phone":"+1 905 337 0000",
    "sg:postcode":"L6K 2G7",
    "sg:province":"ON",
    "sg:tags":[
        "die",
        "maker"
    ],
    "wof:name":"Commercial Manufacturing",
    "wof:placetype":"venue"
},
  "geometry": {"coordinates":[-79.7016296387,43.441204071],"type":"Point"}
}