{
  "type": "Feature",
  "properties": {
    "addr:full":"1082 Cole Harbour Rd Dartmouth NS B2V 1E7",
    "addr:housenumber":"1082",
    "addr:postcode":"b2v 1e7",
    "addr:street":"Cole Harbour Rd",
    "iso:country":"CA",
    "sg:address":"1082 Cole Harbour Rd",
    "sg:city":"Dartmouth",
    "sg:classifiers":[
        {
            "category":"Wholesale",
            "subcategory":"Non-durable Goods",
            "type":"Manufacturing & Wholesale Goods"
        }
    ],
    "sg:phone":"+1 902 435 4078",
    "sg:postcode":"B2V 1E7",
    "sg:province":"NS",
    "sg:tags":[
        "trophy",
        "medal",
        "award"
    ],
    "wof:name":"Cole Harbour Trophies & Awards",
    "wof:placetype":"venue"
},
  "geometry": {"coordinates":[-63.48724,44.671856],"type":"Point"}
}