{
  "type": "Feature",
  "properties": {
    "iso:country":"CA",
    "sg:city":"Sherbrooke",
    "sg:classifiers":[
        {
            "category":"Health Services",
            "subcategory":"Health Practitioner",
            "type":"Services"
        }
    ],
    "sg:phone":"+1 819 822 2220",
    "sg:postcode":"J1H 4M2",
    "sg:province":"QC",
    "sg:tags":[
        "psychologist"
    ],
    "wof:name":"Lapointe, Luc",
    "wof:placetype":"venue"
},
  "geometry": {"coordinates":[-71.89408874510001,45.4051589966],"type":"Point"}
}