{
  "type": "Feature",
  "properties": {
    "addr:full":"Revelstoke BC V0E 2S0",
    "addr:postcode":"v0e 2s0",
    "iso:country":"CA",
    "sg:city":"Revelstoke",
    "sg:classifiers":[
        {
            "category":"Shopping",
            "type":"Retail Goods"
        }
    ],
    "sg:phone":"+1 250 837 5956",
    "sg:postcode":"V0E 2S0",
    "sg:province":"BC",
    "sg:tags":[
        "pet",
        "food",
        "supply"
    ],
    "wof:name":"Animal House",
    "wof:placetype":"venue"
},
  "geometry": {"coordinates":[-118.196899,50.999866],"type":"Point"}
}