{
  "type": "Feature",
  "properties": {
    "addr:full":"108 Rue Principale E Sainte-Henedine QC G0S 2R0",
    "addr:housenumber":"108",
    "addr:postcode":"g0s 2r0",
    "addr:street":"Rue Principale E Sainte-Henedine",
    "iso:country":"CA",
    "sg:address":"108 Rue Principale E",
    "sg:city":"Sainte-Henedine",
    "sg:classifiers":[
        {
            "category":"Wholesale",
            "subcategory":"Farm Supplies",
            "type":"Manufacturing & Wholesale Goods"
        }
    ],
    "sg:phone":"+1 418 935 3651",
    "sg:postcode":"G0S 2R0",
    "sg:province":"QC",
    "sg:tags":[
        "feed"
    ],
    "wof:name":"Unicoop Cooperative Agricole",
    "wof:placetype":"venue"
},
  "geometry": {"coordinates":[-70.985168,46.558182],"type":"Point"}
}