{
  "type": "Feature",
  "properties": {
    "addr:full":"1170 Rue DE Louvain O Montreal QC H4N 1G5",
    "addr:housenumber":"1170",
    "addr:postcode":"h4n 1g5",
    "addr:street":"Rue De Louvain O",
    "iso:country":"CA",
    "sg:address":"1170 Rue DE Louvain O",
    "sg:city":"Montreal",
    "sg:classifiers":[
        {
            "category":"Shopping",
            "subcategory":"Jewelry",
            "type":"Retail Goods"
        }
    ],
    "sg:phone":"+1 514 389 5029",
    "sg:postcode":"H4N 1G5",
    "sg:province":"QC",
    "sg:tags":[
        "jeweler"
    ],
    "wof:name":"Bourgeois Joailliers Inc",
    "wof:placetype":"venue"
},
  "geometry": {"coordinates":[-73.64563800000001,45.558792],"type":"Point"}
}