{
  "type": "Feature",
  "properties": {
    "iso:country":"CA",
    "sg:address":"119 Mckenzie Rd",
    "sg:city":"St Andrews",
    "sg:phone":"+1 204 482 1056",
    "sg:postcode":"R1A 4C1",
    "sg:province":"MB",
    "sg:tags":[
        "tanner",
        "taxidermist"
    ],
    "wof:name":"Muddywaters Taxidermy",
    "wof:placetype":"venue"
},
  "geometry": {"coordinates":[-96.9987106323,50.5033950806],"type":"Point"}
}