{
  "type": "Feature",
  "properties": {
    "addr:full":"North Bay ON P1B 7K8",
    "addr:postcode":"p1b 7k8",
    "iso:country":"CA",
    "sg:city":"North Bay",
    "sg:classifiers":[
        {
            "category":"Professional",
            "subcategory":"Lawyer & Legal Services",
            "type":"Services"
        }
    ],
    "sg:phone":"+1 705 476 6603",
    "sg:postcode":"P1B 7K8",
    "sg:province":"ON",
    "sg:tags":[
        "attorney"
    ],
    "wof:name":"Clinique Juridique Nipissing",
    "wof:placetype":"venue"
},
  "geometry": {"coordinates":[-79.465744,46.331573],"type":"Point"}
}