{
  "type": "Feature",
  "properties": {
    "iso:country":"CA",
    "sg:city":"Kirkland",
    "sg:classifiers":[
        {
            "category":"Wholesale",
            "subcategory":"Non-durable Goods",
            "type":"Manufacturing & Wholesale Goods"
        }
    ],
    "sg:phone":"+1 514 990 8347",
    "sg:postcode":"H9H 3C4",
    "sg:province":"QC",
    "sg:tags":[
        "advertising"
    ],
    "wof:name":"Grant Custom Ltee",
    "wof:placetype":"venue"
},
  "geometry": {"coordinates":[-73.86236572270001,45.4564743042],"type":"Point"}
}