{
  "type": "Feature",
  "properties": {
    "addr:full":"Carseland AB T0J 0M0",
    "addr:postcode":"t0j 0m0",
    "iso:country":"CA",
    "sg:city":"Carseland",
    "sg:classifiers":[
        {
            "category":"Manufacturing",
            "subcategory":"Tools & Machinery",
            "type":"Manufacturing & Wholesale Goods"
        }
    ],
    "sg:phone":"+1 403 901 2380",
    "sg:postcode":"T0J 0M0",
    "sg:province":"AB",
    "sg:tags":[
        "spraying",
        "equipment"
    ],
    "wof:name":"Spray-Air Technologies Ltd",
    "wof:placetype":"venue"
},
  "geometry": {"coordinates":[-113.46525573700001,50.8503494263],"type":"Point"}
}