{
  "type": "Feature",
  "properties": {
    "addr:full":"1644 75th Ave W Vancouver BC V6P 6G2",
    "addr:housenumber":"1644",
    "addr:postcode":"v6p 6g2",
    "addr:street":"75Th Ave W",
    "iso:country":"CA",
    "sg:address":"1644 75th Ave W",
    "sg:city":"Vancouver",
    "sg:classifiers":[
        {
            "category":"Communications",
            "subcategory":"Film & Video Production",
            "type":"Services"
        }
    ],
    "sg:phone":"+1 604 263 2551",
    "sg:postcode":"V6P 6G2",
    "sg:province":"BC",
    "sg:tags":[
        "motion",
        "picture"
    ],
    "wof:name":"Technicolor",
    "wof:placetype":"venue"
},
  "geometry": {"coordinates":[-123.14511108400001,49.2053108215],"type":"Point"}
}