{
  "type": "Feature",
  "properties": {
    "addr:full":"10 Rue Rocheleau Cap-DE-LA-Madeleine QC G8T 4Z7",
    "addr:housenumber":"10",
    "addr:postcode":"g8t 4z7",
    "addr:street":"Rue Rocheleau",
    "iso:country":"CA",
    "sg:address":"10 Rue Rocheleau",
    "sg:city":"Cap-DE-LA-Madeleine",
    "sg:classifiers":[
        {
            "category":"Wholesale",
            "subcategory":"Electrical",
            "type":"Manufacturing & Wholesale Goods"
        }
    ],
    "sg:phone":"+1 819 379 3999",
    "sg:postcode":"G8T 4Z7",
    "sg:province":"QC",
    "sg:tags":[
        "electric",
        "motor"
    ],
    "wof:name":"Sautess Enr",
    "wof:placetype":"venue"
},
  "geometry": {"coordinates":[-72.501564,46.365929],"type":"Point"}
}