{
  "type": "Feature",
  "properties": {
    "iso:country":"CA",
    "sg:address":"112 King St",
    "sg:city":"Rathwell",
    "sg:classifiers":[
        {
            "category":"Manufacturing",
            "subcategory":"Tools & Machinery",
            "type":"Manufacturing & Wholesale Goods"
        }
    ],
    "sg:phone":"+1 204 749 3000",
    "sg:postcode":"R0G 1S0",
    "sg:province":"MB",
    "sg:tags":[
        "farm",
        "equipment",
        "livestock",
        "supply"
    ],
    "wof:name":"Real Industries",
    "wof:placetype":"venue"
},
  "geometry": {"coordinates":[-98.5459518433,49.6471786499],"type":"Point"}
}