{
  "type": "Feature",
  "properties": {
    "addr:full":"2912 125 Rte Sainte-Julienne QC J0K 2T0",
    "addr:housenumber":"2912",
    "addr:postcode":"j0k 2t0",
    "addr:street":"125 Rte",
    "iso:country":"CA",
    "sg:address":"2912 125 Rte",
    "sg:city":"Sainte-Julienne",
    "sg:classifiers":[
        {
            "category":"Food & Beverages",
            "subcategory":"Groceries & Convenience Stores",
            "type":"Retail Goods"
        }
    ],
    "sg:phone":"+1 450 834 5375",
    "sg:postcode":"J0K 2T0",
    "sg:province":"QC",
    "sg:tags":[
        "grocer"
    ],
    "wof:name":"Depanneur LA Plaza Enr",
    "wof:placetype":"venue"
},
  "geometry": {"coordinates":[-73.72212219239999,46.0001792908],"type":"Point"}
}