{
  "type": "Feature",
  "properties": {
    "addr:full":"4280 6th Ave Port Alberni BC V9Y 4M9",
    "addr:housenumber":"4280",
    "addr:postcode":"v9y 4m9",
    "addr:street":"6Th Ave",
    "iso:country":"CA",
    "sg:address":"4280 6th Ave",
    "sg:city":"Port Alberni",
    "sg:classifiers":[
        {
            "category":"Manufacturing",
            "subcategory":"Apparel",
            "type":"Manufacturing & Wholesale Goods"
        }
    ],
    "sg:phone":"+1 250 723 5731",
    "sg:postcode":"V9Y 4M9",
    "sg:province":"BC",
    "sg:tags":[
        "flag",
        "banner"
    ],
    "wof:name":"Jal Designs & Graphics",
    "wof:placetype":"venue"
},
  "geometry": {"coordinates":[-124.803451538,49.2536773682],"type":"Point"}
}