{
  "type": "Feature",
  "properties": {
    "iso:country":"CA",
    "sg:address":"533 Rue Deslauriers",
    "sg:city":"Saint-Laurent",
    "sg:classifiers":[
        {
            "category":"Manufacturing",
            "subcategory":"Electronics",
            "type":"Manufacturing & Wholesale Goods"
        }
    ],
    "sg:phone":"+1 514 745 4464",
    "sg:postcode":"H4N 1W2",
    "sg:province":"QC",
    "sg:tags":[
        "printed",
        "circuit",
        "etched"
    ],
    "wof:name":"Circuits Labo Inc",
    "wof:placetype":"venue"
},
  "geometry": {"coordinates":[-73.665016,45.524494],"type":"Point"}
}