{
  "type": "Feature",
  "properties": {
    "addr:full":"Medicine Hat AB T1A 0H3",
    "addr:postcode":"t1a 0h3",
    "iso:country":"CA",
    "sg:city":"Medicine Hat",
    "sg:classifiers":[
        {
            "category":"Shopping",
            "subcategory":"Clothing, Apparel, & Fashions",
            "type":"Retail Goods"
        }
    ],
    "sg:phone":"+1 403 528 4332",
    "sg:postcode":"T1A 0H3",
    "sg:province":"AB",
    "wof:name":"Classic Plus Collections",
    "wof:placetype":"venue"
},
  "geometry": {"coordinates":[-110.677398682,50.0393486023],"type":"Point"}
}