{
  "type": "Feature",
  "properties": {
    "addr:full":"1928 Danforth Ave Toronto ON M4C 1J4",
    "addr:housenumber":"1928",
    "addr:postcode":"m4c 1j4",
    "addr:street":"Danforth Ave",
    "iso:country":"CA",
    "sg:address":"1928 Danforth Ave",
    "sg:city":"Toronto",
    "sg:classifiers":[
        {
            "category":"Restaurant",
            "type":"Food & Drink"
        }
    ],
    "sg:phone":"+1 416 425 9833",
    "sg:postcode":"M4C 1J4",
    "sg:province":"ON",
    "sg:tags":[
        "cafe"
    ],
    "wof:name":"Sam's Cafe",
    "wof:placetype":"venue"
},
  "geometry": {"coordinates":[-79.3159790039,43.6851272583],"type":"Point"}
}