{
  "type": "Feature",
  "properties": {
    "addr:full":"London ON N6B 1R8",
    "addr:postcode":"n6b 1r8",
    "iso:country":"CA",
    "sg:city":"London",
    "sg:classifiers":[
        {
            "category":"Health Services",
            "subcategory":"Health Practitioner",
            "type":"Services"
        }
    ],
    "sg:phone":"+1 519 850 8738",
    "sg:postcode":"N6B 1R8",
    "sg:province":"ON",
    "sg:tags":[
        "psychologist"
    ],
    "wof:name":"Freedman, Sid PhD",
    "wof:placetype":"venue"
},
  "geometry": {"coordinates":[-81.24395800000001,42.983772],"type":"Point"}
}