{
  "type": "Feature",
  "properties": {
    "iso:country":"CA",
    "sg:address":"12 Chipman Dr",
    "sg:city":"Kentville",
    "sg:classifiers":[
        {
            "category":"Wholesale",
            "subcategory":"Electrical",
            "type":"Manufacturing & Wholesale Goods"
        }
    ],
    "sg:phone":"+1 902 679 4237",
    "sg:postcode":"B4N 3V7",
    "sg:province":"NS",
    "sg:tags":[
        "equipment",
        "electric",
        "supply"
    ],
    "wof:name":"Westburne-Nedco Electrical",
    "wof:placetype":"venue"
},
  "geometry": {"coordinates":[-64.550323,45.068256],"type":"Point"}
}