{
  "type": "Feature",
  "properties": {
    "addr:full":"59 Albion St Belleville ON K8N 3R7",
    "addr:housenumber":"59",
    "addr:postcode":"k8n 3r7",
    "addr:street":"Albion St",
    "iso:country":"CA",
    "sg:address":"59 Albion St",
    "sg:city":"Belleville",
    "sg:classifiers":[
        {
            "category":"Shopping",
            "subcategory":"Clothing, Apparel, & Fashions",
            "type":"Retail Goods"
        }
    ],
    "sg:phone":"+1 613 969 7432",
    "sg:postcode":"K8N 3R7",
    "sg:province":"ON",
    "sg:tags":[
        "theatrical",
        "costume"
    ],
    "wof:name":"Costume Castle",
    "wof:placetype":"venue"
},
  "geometry": {"coordinates":[-77.3774261475,44.1756019592],"type":"Point"}
}