{
  "type": "Feature",
  "properties": {
    "addr:full":"2018 19th Ave Nanton AB T0L 1R0",
    "addr:housenumber":"2018",
    "addr:postcode":"t0l 1r0",
    "addr:street":"19Th Ave",
    "iso:country":"CA",
    "sg:address":"2018 19th Ave",
    "sg:city":"Nanton",
    "sg:classifiers":[
        {
            "category":"Retail",
            "subcategory":"Auto Repair",
            "type":"Services"
        }
    ],
    "sg:phone":"+1 403 646 3040",
    "sg:postcode":"T0L 1R0",
    "sg:province":"AB",
    "sg:tags":[
        "repairing",
        "automobile"
    ],
    "wof:name":"Hicklin Motors",
    "wof:placetype":"venue"
},
  "geometry": {"coordinates":[-113.769035339,50.3484802246],"type":"Point"}
}