{
  "type": "Feature",
  "properties": {
    "iso:country":"CA",
    "sg:address":"2018 19th Ave",
    "sg:city":"Nanton",
    "sg:classifiers":[
        {
            "category":"Retail",
            "subcategory":"Auto Repair",
            "type":"Services"
        }
    ],
    "sg:phone":"+1 403 646 3040",
    "sg:postcode":"T0L 1R0",
    "sg:province":"AB",
    "sg:tags":[
        "repairing",
        "automobile"
    ],
    "wof:name":"Hicklin Motors",
    "wof:placetype":"venue"
},
  "geometry": {"coordinates":[-113.769035339,50.3484802246],"type":"Point"}
}