{
  "type": "Feature",
  "properties": {
    "addr:full":"363 Queensdale Ave E Hamilton ON L9A 1L5",
    "addr:housenumber":"363",
    "addr:postcode":"l9a 1l5",
    "addr:street":"Queensdale Ave E",
    "iso:country":"CA",
    "sg:address":"363 Queensdale Ave E",
    "sg:city":"Hamilton",
    "sg:classifiers":[
        {
            "category":"Recreation",
            "type":"Entertainment"
        }
    ],
    "sg:phone":"+1 905 388 1227",
    "sg:postcode":"L9A 1L5",
    "sg:province":"ON",
    "sg:tags":[
        "boating",
        "instruction"
    ],
    "wof:name":"Hamilton Power & Sail Sqdrn",
    "wof:placetype":"venue"
},
  "geometry": {"coordinates":[-79.861046,43.237938],"type":"Point"}
}