{
  "type": "Feature",
  "properties": {
    "addr:full":"6576 21E Av Montreal QC H1X 2G7",
    "addr:housenumber":"6576",
    "addr:postcode":"h1x 2g7",
    "addr:street":"21E Av",
    "iso:country":"CA",
    "sg:address":"6576 21E Av",
    "sg:city":"Montreal",
    "sg:classifiers":[
        {
            "category":"Professional",
            "subcategory":"Business Services",
            "type":"Services"
        }
    ],
    "sg:phone":"+1 514 729 2872",
    "sg:postcode":"H1X 2G7",
    "sg:province":"QC",
    "sg:tags":[
        "translator",
        "interpreter"
    ],
    "wof:name":"Traductions Castel Inc",
    "wof:placetype":"venue"
},
  "geometry": {"coordinates":[-73.581924,45.562222],"type":"Point"}
}