{
  "type": "Feature",
  "properties": {
    "iso:country":"CA",
    "sg:address":"9683 Rue Clement",
    "sg:city":"Lasalle",
    "sg:classifiers":[
        {
            "category":"Manufacturing",
            "subcategory":"Printing",
            "type":"Manufacturing & Wholesale Goods"
        }
    ],
    "sg:phone":"+1 514 595 1414",
    "sg:postcode":"H8R 4B4",
    "sg:province":"QC",
    "sg:tags":[
        "broker"
    ],
    "wof:name":"Productions Klone Inc",
    "wof:placetype":"venue"
},
  "geometry": {"coordinates":[-73.6535186768,45.4349441528],"type":"Point"}
}