{
  "type": "Feature",
  "properties": {
    "addr:full":"1014 13 St SE High River AB T1V 1L4",
    "addr:housenumber":"1014",
    "addr:postcode":"t1v 1l4",
    "addr:street":"13 St Se",
    "iso:country":"CA",
    "sg:address":"1014 13 St SE",
    "sg:city":"High River",
    "sg:classifiers":[
        {
            "category":"Freight",
            "type":"Transportation"
        }
    ],
    "sg:phone":"+1 403 652 4775",
    "sg:postcode":"T1V 1L4",
    "sg:province":"AB",
    "sg:tags":[
        "delivery",
        "courier"
    ],
    "wof:name":"Highwood Courier Ltd",
    "wof:placetype":"venue"
},
  "geometry": {"coordinates":[-113.84815979,50.5753288269],"type":"Point"}
}