{
  "type": "Feature",
  "properties": {
    "addr:full":"Centreville NS B0P 1J0",
    "addr:postcode":"b0p 1j0",
    "iso:country":"CA",
    "sg:city":"Centreville",
    "sg:classifiers":[
        {
            "category":"Retail",
            "subcategory":"Auto Repair",
            "type":"Services"
        }
    ],
    "sg:phone":"+1 902 678 0942",
    "sg:postcode":"B0P 1J0",
    "sg:province":"NS",
    "sg:tags":[
        "body",
        "automobile",
        "painting"
    ],
    "wof:name":"Robert Sanford Autobody",
    "wof:placetype":"venue"
},
  "geometry": {"coordinates":[-64.52630600000001,45.130371],"type":"Point"}
}