{
  "type": "Feature",
  "properties": {
    "addr:full":"Surrey BC V4A 2H9",
    "addr:postcode":"v4a 2h9",
    "iso:country":"CA",
    "sg:city":"Surrey",
    "sg:classifiers":[
        {
            "category":"Insurance",
            "subcategory":"Insurance Agent",
            "type":"Services"
        }
    ],
    "sg:phone":"+1 604 535 5460",
    "sg:postcode":"V4A 2H9",
    "sg:province":"BC",
    "wof:name":"Insurance Services Dept",
    "wof:placetype":"venue"
},
  "geometry": {"coordinates":[-122.79742400000001,49.045792],"type":"Point"}
}