{
  "type": "Feature",
  "properties": {
    "addr:full":"Richmond BC V6X 4A5",
    "addr:postcode":"v6x 4a5",
    "iso:country":"CA",
    "sg:city":"Richmond",
    "sg:classifiers":[
        {
            "category":"Personal",
            "subcategory":"Beauty Salon",
            "type":"Services"
        }
    ],
    "sg:phone":"+1 604 232 9082",
    "sg:postcode":"V6X 4A5",
    "sg:province":"BC",
    "sg:tags":[
        "treatment",
        "skin"
    ],
    "wof:name":"Jennifer Beauty Ctr",
    "wof:placetype":"venue"
},
  "geometry": {"coordinates":[-123.126694,49.183514],"type":"Point"}
}