{
  "type": "Feature",
  "properties": {
    "addr:full":"Mississauga ON L5T 1J6",
    "addr:postcode":"l5t 1j6",
    "iso:country":"CA",
    "sg:city":"Mississauga",
    "sg:classifiers":[
        {
            "category":"Building & Trades",
            "subcategory":"Plumbing",
            "type":"Services"
        }
    ],
    "sg:phone":"+1 905 564 8700",
    "sg:postcode":"L5T 1J6",
    "sg:province":"ON",
    "sg:tags":[
        "contractor"
    ],
    "wof:name":"G O Tap Plus Inc",
    "wof:placetype":"venue"
},
  "geometry": {"coordinates":[-79.66464233400001,43.6511764526],"type":"Point"}
}