{
  "type": "Feature",
  "properties": {
    "addr:full":"162 Railroad Ave W Morris MB R0G 1K0",
    "addr:housenumber":"162",
    "addr:postcode":"r0g 1k0",
    "addr:street":"Railroad Ave W",
    "iso:country":"CA",
    "sg:address":"162 Railroad Ave W",
    "sg:city":"Morris",
    "sg:classifiers":[
        {
            "category":"Organizations",
            "subcategory":"Religious Organization",
            "type":"Services"
        }
    ],
    "sg:phone":"+1 204 746 8790",
    "sg:postcode":"R0G 1K0",
    "sg:province":"MB",
    "sg:tags":[
        "church"
    ],
    "wof:name":"Baptist Church Emmanuel",
    "wof:placetype":"venue"
},
  "geometry": {"coordinates":[-97.368675,49.35284],"type":"Point"}
}