{
  "type": "Feature",
  "properties": {
    "addr:full":"Calgary AB T2C 2G3",
    "addr:postcode":"t2c 2g3",
    "iso:country":"CA",
    "sg:city":"Calgary",
    "sg:classifiers":[
        {
            "category":"Home & Garden",
            "subcategory":"Building Materials",
            "type":"Retail Goods"
        }
    ],
    "sg:phone":"+1 403 236 8869",
    "sg:postcode":"T2C 2G3",
    "sg:province":"AB",
    "sg:tags":[
        "door"
    ],
    "wof:name":"K & A Custom Cabinets",
    "wof:placetype":"venue"
},
  "geometry": {"coordinates":[-113.98511499999999,51.000408],"type":"Point"}
}