{
  "type": "Feature",
  "properties": {
    "addr:full":"1250 Rudlin St Victoria BC V8V 3R7",
    "addr:housenumber":"1250",
    "addr:postcode":"v8v 3r7",
    "addr:street":"Rudlin St",
    "iso:country":"CA",
    "sg:address":"1250 Rudlin St",
    "sg:city":"Victoria",
    "sg:classifiers":[
        {
            "category":"Freight",
            "type":"Transportation"
        }
    ],
    "sg:phone":"+1 250 360 1560",
    "sg:postcode":"V8V 3R7",
    "sg:province":"BC",
    "sg:tags":[
        "consultant"
    ],
    "wof:name":"Victoria Transport Policy",
    "wof:placetype":"venue"
},
  "geometry": {"coordinates":[-123.348854,48.426407],"type":"Point"}
}