{
  "type": "Feature",
  "properties": {
    "addr:full":"108 Rue Guerrette Edmundston NB E3V 3S4",
    "addr:housenumber":"108",
    "addr:postcode":"e3v 3s4",
    "addr:street":"Rue Guerrette",
    "iso:country":"CA",
    "sg:address":"108 Rue Guerrette",
    "sg:city":"Edmundston",
    "sg:classifiers":[
        {
            "category":"Health Services",
            "subcategory":"Nursing And Care Facility",
            "type":"Services"
        }
    ],
    "sg:phone":"+1 506 739 8482",
    "sg:postcode":"E3V 3S4",
    "sg:province":"NB",
    "sg:tags":[
        "home",
        "convalescent"
    ],
    "wof:name":"Foyer Montfort",
    "wof:placetype":"venue"
},
  "geometry": {"coordinates":[-68.354843,47.360035],"type":"Point"}
}