{
  "type": "Feature",
  "properties": {
    "iso:country":"CA",
    "sg:city":"Parksville",
    "sg:classifiers":[
        {
            "category":"Professional",
            "subcategory":"Lawyer & Legal Services",
            "type":"Services"
        }
    ],
    "sg:phone":"+1 250 954 3554",
    "sg:postcode":"V9P 2H6",
    "sg:province":"BC",
    "sg:tags":[
        "attorney"
    ],
    "wof:name":"Thomas & CO",
    "wof:placetype":"venue"
},
  "geometry": {"coordinates":[-124.31552886999999,49.3204231262],"type":"Point"}
}