{
  "type": "Feature",
  "properties": {
    "addr:full":"4488 Boul Du Royaume Jonquiere QC G7X 7V5",
    "addr:housenumber":"4488",
    "addr:postcode":"g7x 7v5",
    "addr:street":"Boul Du Royaume",
    "iso:country":"CA",
    "sg:address":"4488 Boul Du Royaume",
    "sg:city":"Jonquiere",
    "sg:classifiers":[
        {
            "category":"Building & Trades",
            "subcategory":"Landscaping Services",
            "type":"Services"
        }
    ],
    "sg:phone":"+1 418 547 5248",
    "sg:postcode":"G7X 7V5",
    "sg:province":"QC",
    "sg:tags":[
        "landscape",
        "contractor"
    ],
    "wof:name":"Serre Boily Pepiniere Enr",
    "wof:placetype":"venue"
},
  "geometry": {"coordinates":[-71.27906,48.42131],"type":"Point"}
}