{
  "type": "Feature",
  "properties": {
    "addr:full":"112 Elm Ridge Dr Toronto ON M6B 1A9",
    "addr:housenumber":"112",
    "addr:postcode":"m6b 1a9",
    "addr:street":"Elm Ridge Dr",
    "iso:country":"CA",
    "sg:address":"112 Elm Ridge Dr",
    "sg:city":"Toronto",
    "sg:classifiers":[
        {
            "category":"Health Services",
            "subcategory":"Doctor",
            "type":"Services"
        }
    ],
    "sg:phone":"+1 416 487 5089",
    "sg:postcode":"M6B 1A9",
    "sg:province":"ON",
    "sg:tags":[
        "physician",
        "surgeon"
    ],
    "wof:name":"Brodziak, H MD",
    "wof:placetype":"venue"
},
  "geometry": {"coordinates":[-79.4359664917,43.7034759521],"type":"Point"}
}