{
  "type": "Feature",
  "properties": {
    "addr:full":"3 Rue Picotte Lanoraie QC J0K 1E0",
    "addr:housenumber":"3",
    "addr:postcode":"j0k 1e0",
    "addr:street":"Rue Picotte",
    "iso:country":"CA",
    "sg:address":"3 Rue Picotte",
    "sg:city":"Lanoraie",
    "sg:classifiers":[
        {
            "category":"Organizations",
            "subcategory":"Religious Organization",
            "type":"Services"
        }
    ],
    "sg:phone":"+1 450 887 2400",
    "sg:postcode":"J0K 1E0",
    "sg:province":"QC",
    "sg:tags":[
        "church"
    ],
    "wof:name":"Presbytere St-Joseph",
    "wof:placetype":"venue"
},
  "geometry": {"coordinates":[-73.221619,45.957691],"type":"Point"}
}