{
  "type": "Feature",
  "properties": {
    "addr:full":"185 Main St Bath ON K0H 1G0",
    "addr:housenumber":"185",
    "addr:postcode":"k0h 1g0",
    "addr:street":"Main St",
    "iso:country":"CA",
    "sg:address":"185 Main St",
    "sg:city":"Bath",
    "sg:classifiers":[
        {
            "category":"Recreation",
            "subcategory":"Marina",
            "type":"Entertainment"
        }
    ],
    "sg:phone":"+1 613 352 3478",
    "sg:postcode":"K0H 1G0",
    "sg:province":"ON",
    "wof:name":"Loyalist Cove Marina",
    "wof:placetype":"venue"
},
  "geometry": {"coordinates":[-76.76416778559999,44.1840209961],"type":"Point"}
}