{
  "type": "Feature",
  "properties": {
    "addr:full":"Lefroy ON L0L 1W0",
    "addr:postcode":"l0l 1w0",
    "iso:country":"CA",
    "sg:city":"Lefroy",
    "sg:classifiers":[
        {
            "category":"Home & Garden",
            "subcategory":"Garden Supply",
            "type":"Retail Goods"
        }
    ],
    "sg:phone":"+1 705 456 5822",
    "sg:postcode":"L0L 1W0",
    "sg:province":"ON",
    "sg:tags":[
        "center"
    ],
    "wof:name":"Lakeview Gardens",
    "wof:placetype":"venue"
},
  "geometry": {"coordinates":[-79.57693500000001,44.257263],"type":"Point"}
}