{
  "type": "Feature",
  "properties": {
    "iso:country":"CA",
    "sg:address":"Texas Creek Rd",
    "sg:city":"Lillooet",
    "sg:classifiers":[
        {
            "category":"Professional",
            "subcategory":"Management & Consulting",
            "type":"Services"
        }
    ],
    "sg:phone":"+1 250 256 4980",
    "sg:postcode":"V0K 1V0",
    "sg:province":"BC",
    "sg:tags":[
        "consultant",
        "educational",
        "speech",
        "pathologist"
    ],
    "wof:name":"Lillooet Professional Speech",
    "wof:placetype":"venue"
},
  "geometry": {"coordinates":[-121.936515808,50.6865348816],"type":"Point"}
}