{
  "type": "Feature",
  "properties": {
    "iso:country":"CA",
    "sg:address":"2676 Rue Acadie",
    "sg:city":"Cap-Pele",
    "sg:classifiers":[
        {
            "category":"Home & Garden",
            "subcategory":"Hardware",
            "type":"Retail Goods"
        }
    ],
    "sg:phone":"+1 506 577 2992",
    "sg:postcode":"E4N 1E5",
    "sg:province":"NB",
    "wof:name":"Landry Hardware Ltd",
    "wof:placetype":"venue"
},
  "geometry": {"coordinates":[-64.26792144780001,46.2148933411],"type":"Point"}
}