{
  "type": "Feature",
  "properties": {
    "addr:full":"10 Rue Sunnydale Dollard-Des-Ormeaux QC H9B 1E2",
    "addr:housenumber":"10",
    "addr:postcode":"h9b 1e2",
    "addr:street":"Rue Sunnydale",
    "iso:country":"CA",
    "sg:address":"10 Rue Sunnydale",
    "sg:city":"Dollard-Des-Ormeaux",
    "sg:classifiers":[
        {
            "category":"Government",
            "subcategory":"Fire Station",
            "type":"Public Place"
        }
    ],
    "sg:phone":"+1 ",
    "sg:postcode":"H9B 1E2",
    "sg:province":"QC",
    "sg:tags":[
        "department"
    ],
    "wof:name":"Dollard Des Ormeaux Prevention",
    "wof:placetype":"venue"
},
  "geometry": {"coordinates":[-73.80651855470001,45.4939689636],"type":"Point"}
}