{
  "type": "Feature",
  "properties": {
    "iso:country":"CA",
    "sg:address":"102 Dawes Rd",
    "sg:city":"East York",
    "sg:classifiers":[
        {
            "category":"Building & Trades",
            "subcategory":"Construction",
            "type":"Services"
        }
    ],
    "sg:phone":"+1 416 694 3377",
    "sg:postcode":"M4C 5B5",
    "sg:province":"ON",
    "sg:tags":[
        "roofing",
        "contractor"
    ],
    "wof:name":"Al's Roofing & Sheet Metal CO",
    "wof:placetype":"venue"
},
  "geometry": {"coordinates":[-79.297104,43.69199],"type":"Point"}
}