{
  "type": "Feature",
  "properties": {
    "addr:full":"86 Klages Rd Thunder Bay ON P7C 4V2",
    "addr:housenumber":"86",
    "addr:postcode":"p7c 4v2",
    "addr:street":"Klages Rd",
    "iso:country":"CA",
    "sg:address":"86 Klages Rd",
    "sg:city":"Thunder Bay",
    "sg:classifiers":[
        {
            "category":"Building & Trades",
            "subcategory":"Electrical",
            "type":"Services"
        }
    ],
    "sg:phone":"+1 807 475 6909",
    "sg:postcode":"P7C 4V2",
    "sg:province":"ON",
    "sg:tags":[
        "electric",
        "contractor"
    ],
    "wof:name":"Groom Electric",
    "wof:placetype":"venue"
},
  "geometry": {"coordinates":[-89.245476,48.381699],"type":"Point"}
}