{
  "type": "Feature",
  "properties": {
    "addr:full":"1506 Wyandotte St E Windsor ON N9A 3L2",
    "addr:housenumber":"1506",
    "addr:postcode":"n9a 3l2",
    "addr:street":"Wyandotte St E",
    "iso:country":"CA",
    "sg:address":"1506 Wyandotte St E",
    "sg:city":"Windsor",
    "sg:classifiers":[
        {
            "category":"Shopping",
            "type":"Retail Goods"
        }
    ],
    "sg:phone":"+1 519 253 5477",
    "sg:postcode":"N9A 3L2",
    "sg:province":"ON",
    "sg:tags":[
        "picture",
        "frame"
    ],
    "wof:name":"Posteroptics",
    "wof:placetype":"venue"
},
  "geometry": {"coordinates":[-83.0168457031,42.3214302063],"type":"Point"}
}