{
  "type": "Feature",
  "properties": {
    "addr:full":"Regina SK S4N 1A8",
    "addr:postcode":"s4n 1a8",
    "iso:country":"CA",
    "sg:city":"Regina",
    "sg:classifiers":[
        {
            "category":"Real Estate",
            "subcategory":"Real Estate Operator",
            "type":"Services"
        }
    ],
    "sg:phone":"+1 306 352 4993",
    "sg:postcode":"S4N 1A8",
    "sg:province":"SK",
    "sg:tags":[
        "apartment"
    ],
    "wof:name":"Tower Gardens",
    "wof:placetype":"venue"
},
  "geometry": {"coordinates":[-104.56751300000001,50.437244],"type":"Point"}
}