{
  "type": "Feature",
  "properties": {
    "addr:full":"100 Rue Fusey Cap-DE-LA-Madeleine QC G8T 9R2",
    "addr:housenumber":"100",
    "addr:postcode":"g8t 9r2",
    "addr:street":"Rue Fusey",
    "iso:country":"CA",
    "sg:address":"100 Rue Fusey",
    "sg:city":"Cap-DE-LA-Madeleine",
    "sg:classifiers":[
        {
            "category":"Retail",
            "subcategory":"Auto Repair",
            "type":"Services"
        }
    ],
    "sg:phone":"+1 819 375 3289",
    "sg:postcode":"G8T 9R2",
    "sg:province":"QC",
    "sg:tags":[
        "repairing",
        "automobile"
    ],
    "wof:name":"Garage Poirier & Fils Inc",
    "wof:placetype":"venue"
},
  "geometry": {"coordinates":[-72.526505,46.365826],"type":"Point"}
}