{
  "type": "Feature",
  "properties": {
    "addr:full":"5004 53 Ave High Prairie AB T0G 1E0",
    "addr:housenumber":"5004",
    "addr:postcode":"t0g 1e0",
    "addr:street":"53 Ave",
    "iso:country":"CA",
    "sg:address":"5004 53 Ave",
    "sg:city":"High Prairie",
    "sg:classifiers":[
        {
            "category":"Sports & Exercise",
            "subcategory":"Gym",
            "type":"Entertainment"
        }
    ],
    "sg:phone":"+1 780 523 4655",
    "sg:postcode":"T0G 1E0",
    "sg:province":"AB",
    "sg:tags":[
        "club",
        "health",
        "studio",
        "gymnasium"
    ],
    "wof:name":"Bodyshapers Gym",
    "wof:placetype":"venue"
},
  "geometry": {"coordinates":[-116.49556,55.432995],"type":"Point"}
}