{
  "type": "Feature",
  "properties": {
    "iso:country":"CA",
    "sg:address":"615 Twelfth St",
    "sg:city":"New Westminster",
    "sg:classifiers":[
        {
            "category":"Shopping",
            "subcategory":"Used Merchandise",
            "type":"Retail Goods"
        }
    ],
    "sg:phone":"+1 604 525 1180",
    "sg:postcode":"V3M 4J3",
    "sg:province":"BC",
    "sg:tags":[
        "antique"
    ],
    "wof:name":"Alleycats",
    "wof:placetype":"venue"
},
  "geometry": {"coordinates":[-122.931022644,49.2081184387],"type":"Point"}
}