{
  "type": "Feature",
  "properties": {
    "addr:full":"3639 26 St NE Calgary AB T1Y 5E1",
    "addr:housenumber":"3639",
    "addr:postcode":"t1y 5e1",
    "addr:street":"26 St Ne",
    "iso:country":"CA",
    "sg:address":"3639 26 St NE",
    "sg:city":"Calgary",
    "sg:classifiers":[
        {
            "category":"Building & Trades",
            "subcategory":"Construction",
            "type":"Services"
        }
    ],
    "sg:phone":"+1 403 266 7107",
    "sg:postcode":"T1Y 5E1",
    "sg:province":"AB",
    "sg:tags":[
        "general",
        "contractor"
    ],
    "wof:name":"Oasis Homes Ltd",
    "wof:placetype":"venue"
},
  "geometry": {"coordinates":[-113.997978,51.085293],"type":"Point"}
}