{
  "type": "Feature",
  "properties": {
    "addr:full":"Pangnirtung NU X0A 0R0",
    "addr:postcode":"x0a 0r0",
    "iso:country":"CA",
    "sg:city":"Pangnirtung",
    "sg:classifiers":[
        {
            "category":"Social Services",
            "subcategory":"Child Care",
            "type":"Services"
        }
    ],
    "sg:phone":"+1 867 473 8889",
    "sg:postcode":"X0A 0R0",
    "sg:province":"NU",
    "wof:name":"Precious Children's Daycare",
    "wof:placetype":"venue"
},
  "geometry": {"coordinates":[-65.69454193120001,66.1486816406],"type":"Point"}
}