{
  "type": "Feature",
  "properties": {
    "iso:country":"CA",
    "sg:city":"Etobicoke",
    "sg:classifiers":[
        {
            "category":"Food & Beverages",
            "subcategory":"Groceries & Convenience Stores",
            "type":"Retail Goods"
        }
    ],
    "sg:phone":"+1 416 741 9278",
    "sg:postcode":"M9V 4P2",
    "sg:province":"ON",
    "sg:tags":[
        "grocer"
    ],
    "wof:name":"Alli Basic Foods Inc",
    "wof:placetype":"venue"
},
  "geometry": {"coordinates":[-79.58861541749999,43.7564888],"type":"Point"}
}