{
  "type": "Feature",
  "properties": {
    "addr:full":"175 Queen St Charlottetown PE C1A 4B4",
    "addr:housenumber":"175",
    "addr:postcode":"c1a 4b4",
    "addr:street":"Queen St",
    "iso:country":"CA",
    "sg:address":"175 Queen St",
    "sg:city":"Charlottetown",
    "sg:classifiers":[
        {
            "category":"Shopping",
            "subcategory":"Shoes",
            "type":"Retail Goods"
        }
    ],
    "sg:phone":"+1 902 892 1500",
    "sg:postcode":"C1A 4B4",
    "sg:province":"PE",
    "wof:name":"Corney's Shoe Store",
    "wof:placetype":"venue"
},
  "geometry": {"coordinates":[-63.12878,46.234772],"type":"Point"}
}