{
  "type": "Feature",
  "properties": {
    "addr:full":"9000 Boul Lacroix Saint-Georges QC G5Y 5P4",
    "addr:housenumber":"9000",
    "addr:postcode":"g5y 5p4",
    "addr:street":"Boul Lacroix",
    "iso:country":"CA",
    "sg:address":"9000 Boul Lacroix",
    "sg:city":"Saint-Georges",
    "sg:classifiers":[
        {
            "category":"Home & Garden",
            "subcategory":"Home Furnishings",
            "type":"Retail Goods"
        }
    ],
    "sg:phone":"+1 418 228 0067",
    "sg:postcode":"G5Y 5P4",
    "sg:province":"QC",
    "sg:tags":[
        "window",
        "covering"
    ],
    "wof:name":"Marche Du Store",
    "wof:placetype":"venue"
},
  "geometry": {"coordinates":[-70.694344,46.130482],"type":"Point"}
}