{
  "type": "Feature",
  "properties": {
    "addr:full":"2240 Grant Ave Winnipeg MB R3P 0P7",
    "addr:housenumber":"2240",
    "addr:postcode":"r3p 0p7",
    "addr:street":"Grant Ave",
    "iso:country":"CA",
    "sg:address":"2240 Grant Ave",
    "sg:city":"Winnipeg",
    "sg:classifiers":[
        {
            "category":"Education",
            "subcategory":"School",
            "type":"Public Place"
        }
    ],
    "sg:phone":"+1 204 888 5898",
    "sg:postcode":"R3P 0P7",
    "sg:province":"MB",
    "wof:name":"Shaftesbury High School",
    "wof:placetype":"venue"
},
  "geometry": {"coordinates":[-97.228363,49.857651],"type":"Point"}
}