{
  "type": "Feature",
  "properties": {
    "addr:full":"1234 Lamar Dr Kamloops BC V2C 5C4",
    "addr:housenumber":"1234",
    "addr:postcode":"bc v2c 5c4",
    "addr:street":"Lamar Dr",
    "iso:country":"CA",
    "sg:address":"1234 Lamar Dr",
    "sg:city":"Kamloops",
    "sg:classifiers":[
        {
            "category":"Shopping",
            "type":"Retail Goods"
        }
    ],
    "sg:phone":"+1 250 573 3982",
    "sg:postcode":"V2C 5C4",
    "sg:province":"BC",
    "sg:tags":[
        "cosmetic",
        "perfume"
    ],
    "wof:name":"Mary Kay Cosmetics",
    "wof:placetype":"venue"
},
  "geometry": {"coordinates":[-120.17709350600001,50.6519584656],"type":"Point"}
}