{
  "type": "Feature",
  "properties": {
    "iso:country":"CA",
    "sg:address":"50 Hillside Dr N",
    "sg:city":"Elliot Lake",
    "sg:classifiers":[
        {
            "category":"Government",
            "subcategory":"Office",
            "type":"Public Place"
        }
    ],
    "sg:phone":"+1 705 848 0404",
    "sg:postcode":"P5A 1X4",
    "sg:province":"ON",
    "sg:tags":[
        "license"
    ],
    "wof:name":"Mavis License Bureau",
    "wof:placetype":"venue"
},
  "geometry": {"coordinates":[-82.652725,46.385242],"type":"Point"}
}