{
  "type": "Feature",
  "properties": {
    "addr:full":"450 120E Rue Shawinigan-Sud QC G9P 3J7",
    "addr:housenumber":"450",
    "addr:postcode":"g9p 3j7",
    "addr:street":"120E Rue Shawinigan-Sud",
    "iso:country":"CA",
    "sg:address":"450 120E Rue",
    "sg:city":"Shawinigan-Sud",
    "sg:classifiers":[
        {
            "category":"Health Services",
            "subcategory":"Doctor",
            "type":"Services"
        }
    ],
    "sg:phone":"+1 819 537 8816",
    "sg:postcode":"G9P 3J7",
    "sg:province":"QC",
    "sg:tags":[
        "clinic"
    ],
    "wof:name":"Clinique Dentaire Y Boisvert",
    "wof:placetype":"venue"
},
  "geometry": {"coordinates":[-72.746132,46.521175],"type":"Point"}
}