{
  "type": "Feature",
  "properties": {
    "addr:full":"2168 Rue Octave Jonquiere QC G7S 4A4",
    "addr:housenumber":"2168",
    "addr:postcode":"g7s 4a4",
    "addr:street":"Rue Octave",
    "iso:country":"CA",
    "sg:address":"2168 Rue Octave",
    "sg:city":"Jonquiere",
    "sg:classifiers":[
        {
            "category":"Building & Trades",
            "subcategory":"Construction",
            "type":"Services"
        }
    ],
    "sg:phone":"+1 418 548 7209",
    "sg:postcode":"G7S 4A4",
    "sg:province":"QC",
    "sg:tags":[
        "general",
        "contractor"
    ],
    "wof:name":"J B Lavoie Enr",
    "wof:placetype":"venue"
},
  "geometry": {"coordinates":[-71.1363296509,48.4344139099],"type":"Point"}
}