{
  "type": "Feature",
  "properties": {
    "addr:full":"400 Scurfield Blvd Winnipeg MB R3Y 1L3",
    "addr:housenumber":"400",
    "addr:postcode":"r3y 1l3",
    "addr:street":"Scurfield Blvd",
    "iso:country":"CA",
    "sg:address":"400 Scurfield Blvd",
    "sg:city":"Winnipeg",
    "sg:classifiers":[
        {
            "category":"Social Services",
            "subcategory":"Child Care",
            "type":"Services"
        }
    ],
    "sg:phone":"+1 204 488 3292",
    "sg:postcode":"R3Y 1L3",
    "sg:province":"MB",
    "wof:name":"Ymca-Ywca of Winnipeg",
    "wof:placetype":"venue"
},
  "geometry": {"coordinates":[-97.2054519653,49.8114013672],"type":"Point"}
}