{
  "type": "Feature",
  "properties": {
    "addr:full":"983 Wonderland Rd S London ON N6K 4L3",
    "addr:housenumber":"983",
    "addr:postcode":"n6k 4l3",
    "addr:street":"Wonderland Rd",
    "iso:country":"CA",
    "sg:address":"983 Wonderland Rd S",
    "sg:city":"London",
    "sg:classifiers":[
        {
            "category":"Banks & Credit Unions",
            "subcategory":"Bank",
            "type":"Services"
        }
    ],
    "sg:phone":"+1 519 649 0660",
    "sg:postcode":"N6K 4L3",
    "sg:province":"ON",
    "wof:name":"Cibc",
    "wof:placetype":"venue"
},
  "geometry": {"coordinates":[-81.284477,42.942482],"type":"Point"}
}