{
  "type": "Feature",
  "properties": {
    "addr:full":"5996 184 St Surrey BC V3S 4N4",
    "addr:housenumber":"5996",
    "addr:postcode":"v3s 4n4",
    "addr:street":"184 St",
    "iso:country":"CA",
    "sg:address":"5996 184 St",
    "sg:city":"Surrey",
    "sg:classifiers":[
        {
            "category":"Food & Beverages",
            "subcategory":"Groceries & Convenience Stores",
            "type":"Retail Goods"
        }
    ],
    "sg:phone":"+1 604 576 2215",
    "sg:postcode":"V3S 4N4",
    "sg:province":"BC",
    "sg:tags":[
        "grocer"
    ],
    "wof:name":"Cloverhill Market",
    "wof:placetype":"venue"
},
  "geometry": {"coordinates":[-122.71241000000001,49.111187],"type":"Point"}
}