{
  "type": "Feature",
  "properties": {
    "addr:full":"1515 Goth Ave Gloucester ON K1T 1E3",
    "addr:housenumber":"1515",
    "addr:postcode":"k1t 1e3",
    "addr:street":"Goth Ave",
    "iso:country":"CA",
    "sg:address":"1515 Goth Ave",
    "sg:city":"Gloucester",
    "sg:classifiers":[
        {
            "category":"Retail",
            "subcategory":"Repair Shop",
            "type":"Services"
        }
    ],
    "sg:phone":"+1 613 521 2167",
    "sg:postcode":"K1T 1E3",
    "sg:province":"ON",
    "sg:tags":[
        "upholsterer"
    ],
    "wof:name":"Leslie Morgan Furniture Ltd",
    "wof:placetype":"venue"
},
  "geometry": {"coordinates":[-75.633476,45.347561],"type":"Point"}
}