{
  "type": "Feature",
  "properties": {
    "iso:country":"CA",
    "sg:city":"Calgary",
    "sg:classifiers":[
        {
            "category":"Retail",
            "subcategory":"Auto Repair",
            "type":"Services"
        }
    ],
    "sg:phone":"+1 403 547 4932",
    "sg:postcode":"T3G 4B7",
    "sg:province":"AB",
    "sg:tags":[
        "body",
        "automobile",
        "painting"
    ],
    "wof:name":"Crowfoot Image Auto Body Ltd",
    "wof:placetype":"venue"
},
  "geometry": {"coordinates":[-114.207756042,51.1257400513],"type":"Point"}
}