{
  "type": "Feature",
  "properties": {
    "addr:full":"8054 Boul Saint-Michel Montreal QC H1Z 3E1",
    "addr:housenumber":"8054",
    "addr:postcode":"h1z 3e1",
    "addr:street":"Boul Saint-Michel",
    "iso:country":"CA",
    "sg:address":"8054 Boul Saint-Michel",
    "sg:city":"Montreal",
    "sg:classifiers":[
        {
            "category":"Shopping",
            "subcategory":"Department Store",
            "type":"Retail Goods"
        }
    ],
    "sg:phone":"+1 514 727 8859",
    "sg:postcode":"H1Z 3E1",
    "sg:province":"QC",
    "sg:tags":[
        "shop"
    ],
    "wof:name":"Aubaines Maximum",
    "wof:placetype":"venue"
},
  "geometry": {"coordinates":[-73.6090011597,45.5633277893],"type":"Point"}
}