{
  "type": "Feature",
  "properties": {
    "addr:full":"126 Richmond St Charlottetown PE C1A 1H9",
    "addr:housenumber":"126",
    "addr:postcode":"c1a 1h9",
    "addr:street":"Richmond St",
    "iso:country":"CA",
    "sg:address":"126 Richmond St",
    "sg:city":"Charlottetown",
    "sg:classifiers":[
        {
            "category":"Personal",
            "subcategory":"Beauty Salon",
            "type":"Services"
        }
    ],
    "sg:phone":"+1 902 894 5122",
    "sg:postcode":"C1A 1H9",
    "sg:province":"PE",
    "wof:name":"Magnolia's",
    "wof:placetype":"venue"
},
  "geometry": {"coordinates":[-63.126514,46.233841],"type":"Point"}
}