{
  "type": "Feature",
  "properties": {
    "addr:full":"23430 Tamarack Lane Maple Ridge BC V2W 1A8",
    "addr:housenumber":"23430",
    "addr:postcode":"v2w 1a8",
    "addr:street":"Tamarack Lane",
    "iso:country":"CA",
    "sg:address":"23430 Tamarack Lane",
    "sg:city":"Maple Ridge",
    "sg:classifiers":[
        {
            "category":"Building & Trades",
            "subcategory":"Cleaning & Sanitation",
            "type":"Services"
        }
    ],
    "sg:phone":"+1 604 466 1152",
    "sg:postcode":"V2W 1A8",
    "sg:province":"BC",
    "sg:tags":[
        "janitor"
    ],
    "wof:name":"Carol's Contract Cleaning",
    "wof:placetype":"venue"
},
  "geometry": {"coordinates":[-122.57209,49.20105],"type":"Point"}
}