{
  "type": "Feature",
  "properties": {
    "addr:full":"8000 Boul Henri-Bourassa O Saint-Laurent QC H4S 1P4",
    "addr:housenumber":"8000",
    "addr:postcode":"h4s 1p4",
    "addr:street":"Boul Henri-Bourassa O",
    "iso:country":"CA",
    "sg:address":"8000 Boul Henri-Bourassa O",
    "sg:city":"Saint-Laurent",
    "sg:classifiers":[
        {
            "category":"Freight",
            "type":"Transportation"
        }
    ],
    "sg:phone":"+1 514 333 7561",
    "sg:postcode":"H4S 1P4",
    "sg:province":"QC",
    "sg:tags":[
        "warehouse",
        "self",
        "storage"
    ],
    "wof:name":"Metro Canada Logistique Inc",
    "wof:placetype":"venue"
},
  "geometry": {"coordinates":[-73.743752,45.502754],"type":"Point"}
}