{
  "type": "Feature",
  "properties": {
    "iso:country":"CA",
    "sg:address":"4630 49 St",
    "sg:city":"Vegreville",
    "sg:classifiers":[
        {
            "category":"Organizations",
            "subcategory":"Professional Association",
            "type":"Services"
        }
    ],
    "sg:phone":"+1 780 632 2624",
    "sg:postcode":"T9C 1K7",
    "sg:province":"AB",
    "wof:name":"Senior Citizens Sunshine Club",
    "wof:placetype":"venue"
},
  "geometry": {"coordinates":[-112.052757263,53.4919090271],"type":"Point"}
}