{
  "type": "Feature",
  "properties": {
    "addr:full":"3532 Leicester Rd Amherst NS B4H 3Y1",
    "addr:housenumber":"3532",
    "addr:postcode":"b4h 3y1",
    "addr:street":"Leicester Rd",
    "iso:country":"CA",
    "sg:address":"3532 Leicester Rd",
    "sg:city":"Amherst",
    "sg:classifiers":[
        {
            "category":"Wholesale",
            "subcategory":"Meat",
            "type":"Manufacturing & Wholesale Goods"
        }
    ],
    "sg:phone":"+1 902 667 0454",
    "sg:postcode":"B4H 3Y1",
    "sg:province":"NS",
    "sg:tags":[
        "product",
        "butchering"
    ],
    "wof:name":"Dickie's Meats",
    "wof:placetype":"venue"
},
  "geometry": {"coordinates":[-64.2099304199,45.8320388794],"type":"Point"}
}