{
  "type": "Feature",
  "properties": {
    "iso:country":"CA",
    "sg:address":"2361 Boul Rosemont",
    "sg:city":"Montreal",
    "sg:classifiers":[
        {
            "category":"Building & Trades",
            "subcategory":"Cleaning & Sanitation",
            "type":"Services"
        }
    ],
    "sg:phone":"+1 514 728 4318",
    "sg:postcode":"H2G 1T9",
    "sg:province":"QC",
    "sg:tags":[
        "fireplace",
        "chimney"
    ],
    "wof:name":"Entreprises Normand Hamel",
    "wof:placetype":"venue"
},
  "geometry": {"coordinates":[-73.587402,45.545418],"type":"Point"}
}