{
  "type": "Feature",
  "properties": {
    "addr:full":"1303 Rte Becar Saint-Jean-Chrysostome QC G6Z 2L2",
    "addr:housenumber":"1303",
    "addr:postcode":"g6z 2l2",
    "addr:street":"Rte Becar Saint-Jean-Chrysostome",
    "iso:country":"CA",
    "sg:address":"1303 Rte Becar",
    "sg:city":"Saint-Jean-Chrysostome",
    "sg:classifiers":[
        {
            "category":"Manufacturing",
            "subcategory":"Tools & Machinery",
            "type":"Manufacturing & Wholesale Goods"
        }
    ],
    "sg:phone":"+1 418 839 9707",
    "sg:postcode":"G6Z 2L2",
    "sg:province":"QC",
    "sg:tags":[
        "equipment",
        "sawmill",
        "supply"
    ],
    "wof:name":"O M Ind Inc",
    "wof:placetype":"venue"
},
  "geometry": {"coordinates":[-71.1988067627,46.6980934143],"type":"Point"}
}