{
  "type": "Feature",
  "properties": {
    "addr:full":"510 Bow Valley Trail Canmore AB T1W 1N9",
    "addr:housenumber":"510",
    "addr:postcode":"t1w 1n9",
    "addr:street":"Bow Valley Trail",
    "iso:country":"CA",
    "sg:address":"510 Bow Valley Trail",
    "sg:city":"Canmore",
    "sg:classifiers":[
        {
            "category":"Autos & Motor Vehicles",
            "subcategory":"Fuel & Gas Station",
            "type":"Retail Goods"
        }
    ],
    "sg:phone":"+1 403 609 0034",
    "sg:postcode":"T1W 1N9",
    "sg:province":"AB",
    "sg:tags":[
        "oil"
    ],
    "wof:name":"Fas Gas",
    "wof:placetype":"venue"
},
  "geometry": {"coordinates":[-115.345985,51.086193],"type":"Point"}
}