{
  "type": "Feature",
  "properties": {
    "addr:full":"195 Country Hill Dr Kitchener ON N2E 2G7",
    "addr:housenumber":"195",
    "addr:postcode":"n2e 2g7",
    "addr:street":"Country Hill Dr",
    "iso:country":"CA",
    "sg:address":"195 Country Hill Dr",
    "sg:city":"Kitchener",
    "sg:classifiers":[
        {
            "category":"Education",
            "subcategory":"School",
            "type":"Public Place"
        }
    ],
    "sg:phone":"+1 519 743 6331",
    "sg:postcode":"N2E 2G7",
    "sg:province":"ON",
    "wof:name":"Country Hills Public School",
    "wof:placetype":"venue"
},
  "geometry": {"coordinates":[-80.47100830079999,43.4139633179],"type":"Point"}
}