{
  "type": "Feature",
  "properties": {
    "addr:full":"3050 41st Ave W Vancouver BC V6N 3C9",
    "addr:housenumber":"3050",
    "addr:postcode":"v6n 3c9",
    "addr:street":"41St Ave W",
    "iso:country":"CA",
    "sg:address":"3050 41st Ave W",
    "sg:city":"Vancouver",
    "sg:classifiers":[
        {
            "category":"Health Services",
            "subcategory":"Doctor",
            "type":"Services"
        }
    ],
    "sg:phone":"+1 604 222 0638",
    "sg:postcode":"V6N 3C9",
    "sg:province":"BC",
    "sg:tags":[
        "dentist"
    ],
    "wof:name":"Du, Patrick DDS",
    "wof:placetype":"venue"
},
  "geometry": {"coordinates":[-123.17379,49.234638],"type":"Point"}
}