{
  "type": "Feature",
  "properties": {
    "addr:full":"84 Waterloo Univ Campus Waterloo ON N2L 3G6",
    "addr:housenumber":"84",
    "addr:postcode":"n2l 3g6",
    "addr:street":"Waterloo",
    "iso:country":"CA",
    "sg:address":"84 Waterloo Univ Campus",
    "sg:city":"Waterloo",
    "sg:classifiers":[
        {
            "category":"Education",
            "subcategory":"College",
            "type":"Public Place"
        }
    ],
    "sg:phone":"+1 519 885 0014",
    "sg:postcode":"N2L 3G6",
    "sg:province":"ON",
    "sg:tags":[
        "academic",
        "school"
    ],
    "wof:name":"Conrad Grebel College",
    "wof:placetype":"venue"
},
  "geometry": {"coordinates":[-80.520690918,43.4631385803],"type":"Point"}
}