{
  "type": "Feature",
  "properties": {
    "iso:country":"CA",
    "sg:address":"556 Herald St #B1",
    "sg:city":"Victoria",
    "sg:classifiers":[
        {
            "category":"Retail",
            "subcategory":"Photofinishing",
            "type":"Services"
        }
    ],
    "sg:phone":"+1 250 383 8869",
    "sg:postcode":"V8W 1S6",
    "sg:province":"BC",
    "sg:tags":[
        "photo",
        "finishing"
    ],
    "wof:name":"Island Transparency Svc",
    "wof:placetype":"venue"
},
  "geometry": {"coordinates":[-123.36824,48.430328],"type":"Point"}
}