{
  "type": "Feature",
  "properties": {
    "addr:full":"291 Boul Lachapelle Saint-Jerome QC J7Z 7L2",
    "addr:housenumber":"291",
    "addr:postcode":"j7z 7l2",
    "addr:street":"Boul Lachapelle Saint-Jerome",
    "iso:country":"CA",
    "sg:address":"291 Boul Lachapelle",
    "sg:city":"Saint-Jerome",
    "sg:classifiers":[
        {
            "category":"Personal",
            "subcategory":"Beauty Salon",
            "type":"Services"
        }
    ],
    "sg:phone":"+1 450 660 6006",
    "sg:postcode":"J7Z 7L2",
    "sg:province":"QC",
    "wof:name":"Coiffure Picasso",
    "wof:placetype":"venue"
},
  "geometry": {"coordinates":[-73.9951705933,45.7579841614],"type":"Point"}
}