{
  "type": "Feature",
  "properties": {
    "iso:country":"CA",
    "sg:address":"18528 68 Ave NW",
    "sg:city":"Edmonton",
    "sg:classifiers":[
        {
            "category":"Building & Trades",
            "subcategory":"Cleaning & Sanitation",
            "type":"Services"
        }
    ],
    "sg:phone":"+1 780 481 4147",
    "sg:postcode":"T5T 2M7",
    "sg:province":"AB",
    "sg:tags":[
        "downspouts",
        "gutter",
        "fireplace",
        "chimney"
    ],
    "wof:name":"Chim-Chimney Ltd",
    "wof:placetype":"venue"
},
  "geometry": {"coordinates":[-113.64201355,53.5024108887],"type":"Point"}
}