{
  "type": "Feature",
  "properties": {
    "addr:full":"571 Ch Des Pionniers Cap-Saint-Ignace QC G0R 1H0",
    "addr:housenumber":"571",
    "addr:postcode":"g0r 1h0",
    "addr:street":"Ch Des Pionniers",
    "iso:country":"CA",
    "sg:address":"571 Ch Des Pionniers",
    "sg:city":"Cap-Saint-Ignace",
    "sg:classifiers":[
        {
            "category":"Bars & Pubs",
            "type":"Food & Drink"
        }
    ],
    "sg:phone":"+1 418 246 5531",
    "sg:postcode":"G0R 1H0",
    "sg:province":"QC",
    "sg:tags":[
        "lounge",
        "cocktail"
    ],
    "wof:name":"Bar L'Atmosphere",
    "wof:placetype":"venue"
},
  "geometry": {"coordinates":[-70.4520645142,47.0617866516],"type":"Point"}
}