{
  "type": "Feature",
  "properties": {
    "addr:full":"28 Killaloe Rd Concord ON L4K 2P2",
    "addr:housenumber":"28",
    "addr:postcode":"l4k 2p2",
    "addr:street":"Killaloe Rd",
    "iso:country":"CA",
    "sg:address":"28 Killaloe Rd",
    "sg:city":"Concord",
    "sg:classifiers":[
        {
            "category":"Building & Trades",
            "subcategory":"Equipment Rental",
            "type":"Services"
        }
    ],
    "sg:phone":"+1 905 738 6716",
    "sg:postcode":"L4K 2P2",
    "sg:province":"ON",
    "sg:tags":[
        "crane",
        "business"
    ],
    "wof:name":"Action Equipment Svc Ltd",
    "wof:placetype":"venue"
},
  "geometry": {"coordinates":[-79.51387800000001,43.794724],"type":"Point"}
}