{
  "type": "Feature",
  "properties": {
    "iso:country":"CA",
    "sg:city":"Winnipeg",
    "sg:classifiers":[
        {
            "category":"Personal",
            "subcategory":"Beauty Salon",
            "type":"Services"
        }
    ],
    "sg:phone":"+1 204 453 4247",
    "sg:postcode":"R3M 0Y2",
    "sg:province":"MB",
    "wof:name":"Hair & Skin By Victor",
    "wof:placetype":"venue"
},
  "geometry": {"coordinates":[-97.1567230225,49.8695487976],"type":"Point"}
}