{
  "type": "Feature",
  "properties": {
    "addr:full":"5020 50 Ave Red Deer AB T4N 4B1",
    "addr:housenumber":"5020",
    "addr:postcode":"t4n 4b1",
    "addr:street":"50 Ave",
    "iso:country":"CA",
    "sg:address":"5020 50 Ave",
    "sg:city":"Red Deer",
    "sg:classifiers":[
        {
            "category":"Home & Garden",
            "subcategory":"Home Furnishings",
            "type":"Retail Goods"
        }
    ],
    "sg:phone":"+1 403 346 5510",
    "sg:postcode":"T4N 4B1",
    "sg:province":"AB",
    "sg:tags":[
        "quilting"
    ],
    "wof:name":"Cotton Threads Quilt CO",
    "wof:placetype":"venue"
},
  "geometry": {"coordinates":[-113.81420135499999,52.2696304321],"type":"Point"}
}