{
  "type": "Feature",
  "properties": {
    "addr:full":"1200 Rue Tellier Laval QC H7C 2H2",
    "addr:housenumber":"1200",
    "addr:postcode":"h7c 2h2",
    "addr:street":"Rue Tellier",
    "iso:country":"CA",
    "sg:address":"1200 Rue Tellier",
    "sg:city":"Laval",
    "sg:classifiers":[
        {
            "category":"Retail",
            "subcategory":"Auto Repair",
            "type":"Services"
        }
    ],
    "sg:phone":"+1 450 661 2512",
    "sg:postcode":"H7C 2H2",
    "sg:province":"QC",
    "sg:tags":[
        "repairing",
        "automobile"
    ],
    "wof:name":"St Vincent DE Paul Auto Trans",
    "wof:placetype":"venue"
},
  "geometry": {"coordinates":[-73.65832519529999,45.6155319214],"type":"Point"}
}