{
  "type": "Feature",
  "properties": {
    "addr:full":"Calgary AB T2P 0Z1",
    "addr:postcode":"t2p 0z1",
    "iso:country":"CA",
    "sg:city":"Calgary",
    "sg:classifiers":[
        {
            "category":"Professional",
            "subcategory":"Business Services",
            "type":"Services"
        }
    ],
    "sg:phone":"+1 403 266 6999",
    "sg:postcode":"T2P 0Z1",
    "sg:province":"AB",
    "sg:tags":[
        "searcher",
        "paralegal",
        "record"
    ],
    "wof:name":"Package Paralegal Ltd",
    "wof:placetype":"venue"
},
  "geometry": {"coordinates":[-114.07661400000001,51.046997],"type":"Point"}
}