{
  "type": "Feature",
  "properties": {
    "addr:full":"Saint-Pie QC J0H 1W0",
    "addr:postcode":"j0h 1w0",
    "iso:country":"CA",
    "sg:city":"Saint-Pie",
    "sg:classifiers":[
        {
            "category":"Health Services",
            "subcategory":"Medical Lab",
            "type":"Services"
        }
    ],
    "sg:phone":"+1 450 772 2401",
    "sg:postcode":"J0H 1W0",
    "sg:province":"QC",
    "wof:name":"Landry, Jacques",
    "wof:placetype":"venue"
},
  "geometry": {"coordinates":[-72.90710449220001,45.5045318604],"type":"Point"}
}