{
  "type": "Feature",
  "properties": {
    "iso:country":"CA",
    "sg:address":"1025 2nd Ave W",
    "sg:city":"Owen Sound",
    "sg:classifiers":[
        {
            "category":"Social Services",
            "type":"Services"
        }
    ],
    "sg:phone":"+1 519 376 9439",
    "sg:postcode":"N4K 4N1",
    "sg:province":"ON",
    "sg:tags":[
        "counselor",
        "marriage",
        "family"
    ],
    "wof:name":"Fernstone",
    "wof:placetype":"venue"
},
  "geometry": {"coordinates":[-80.9460906982,44.5679588318],"type":"Point"}
}