{
  "type": "Feature",
  "properties": {
    "addr:full":"350 Evans Ave Etobicoke ON M8Z 1K5",
    "addr:housenumber":"350",
    "addr:postcode":"m8z 1k5",
    "addr:street":"Evans Ave",
    "iso:country":"CA",
    "sg:address":"350 Evans Ave",
    "sg:city":"Etobicoke",
    "sg:classifiers":[
        {
            "category":"Communications",
            "subcategory":"Film & Video Production",
            "type":"Services"
        }
    ],
    "sg:phone":"+1 416 364 4321",
    "sg:postcode":"M8Z 1K5",
    "sg:province":"ON",
    "sg:tags":[
        "motion",
        "picture",
        "laboratory"
    ],
    "wof:name":"Deluxe Laboratories",
    "wof:placetype":"venue"
},
  "geometry": {"coordinates":[-79.523376,43.616196],"type":"Point"}
}