{
  "type": "Feature",
  "properties": {
    "addr:full":"102 Main St S Newmarket ON L3Y 3Y7",
    "addr:housenumber":"102",
    "addr:postcode":"l3y 3y7",
    "addr:street":"Main St S",
    "iso:country":"CA",
    "sg:address":"102 Main St S",
    "sg:city":"Newmarket",
    "sg:classifiers":[
        {
            "category":"Social Services",
            "type":"Services"
        }
    ],
    "sg:phone":"+1 905 898 6455",
    "sg:postcode":"L3Y 3Y7",
    "sg:province":"ON",
    "sg:tags":[
        "organization",
        "welfare"
    ],
    "wof:name":"York Support Svc Network",
    "wof:placetype":"venue"
},
  "geometry": {"coordinates":[-79.4594116211,44.0556678772],"type":"Point"}
}