{
  "type": "Feature",
  "properties": {
    "addr:full":"2360 Rang Saint-Jacques Saint-Jacques QC J0K 2R0",
    "addr:housenumber":"2360",
    "addr:postcode":"j0k 2r0",
    "addr:street":"Rang Saint-Jacques",
    "iso:country":"CA",
    "sg:address":"2360 Rang Saint-Jacques",
    "sg:city":"Saint-Jacques",
    "sg:classifiers":[
        {
            "category":"Home & Garden",
            "subcategory":"Garden Supply",
            "type":"Retail Goods"
        }
    ],
    "sg:phone":"+1 450 839 6565",
    "sg:postcode":"J0K 2R0",
    "sg:province":"QC",
    "sg:tags":[
        "nurseryman"
    ],
    "wof:name":"Pepiniere Montcalm",
    "wof:placetype":"venue"
},
  "geometry": {"coordinates":[-73.592598,45.963551],"type":"Point"}
}