{
  "type": "Feature",
  "properties": {
    "addr:full":"160 Kinsac Rd Beaver Bank NS B4G 1C5",
    "addr:housenumber":"160",
    "addr:postcode":"b4g 1c5",
    "addr:street":"Kinsac Rd",
    "iso:country":"CA",
    "sg:address":"160 Kinsac Rd",
    "sg:city":"Beaver Bank",
    "sg:classifiers":[
        {
            "category":"Retail",
            "subcategory":"Car Wash",
            "type":"Services"
        }
    ],
    "sg:phone":"+1 902 865 7965",
    "sg:postcode":"B4G 1C5",
    "sg:province":"NS",
    "sg:tags":[
        "polishing",
        "washing",
        "cleaning"
    ],
    "wof:name":"Glow Clean Ltd",
    "wof:placetype":"venue"
},
  "geometry": {"coordinates":[-63.6891174316,44.7976379395],"type":"Point"}
}