{
  "type": "Feature",
  "properties": {
    "addr:full":"3711 Moncton St Richmond BC V7E 3A5",
    "addr:housenumber":"3711",
    "addr:postcode":"v7e 3a5",
    "addr:street":"Moncton St",
    "iso:country":"CA",
    "sg:address":"3711 Moncton St",
    "sg:city":"Richmond",
    "sg:classifiers":[
        {
            "category":"Restaurant",
            "type":"Food & Drink"
        }
    ],
    "sg:phone":"+1 604 272 1222",
    "sg:postcode":"V7E 3A5",
    "sg:province":"BC",
    "wof:name":"Steveston Cannery Cafe",
    "wof:placetype":"venue"
},
  "geometry": {"coordinates":[-123.183486938,49.1253242493],"type":"Point"}
}