{
  "type": "Feature",
  "properties": {
    "addr:full":"246 First Ave W North Bay ON P1B 3C1",
    "addr:housenumber":"246",
    "addr:postcode":"p1b 3c1",
    "addr:street":"First Ave W",
    "iso:country":"CA",
    "sg:address":"246 First Ave W",
    "sg:city":"North Bay",
    "sg:classifiers":[
        {
            "category":"Restaurant",
            "type":"Food & Drink"
        }
    ],
    "sg:phone":"+1 705 476 2666",
    "sg:postcode":"P1B 3C1",
    "sg:province":"ON",
    "wof:name":"100 George's",
    "wof:placetype":"venue"
},
  "geometry": {"coordinates":[-79.462631,46.314213],"type":"Point"}
}