{
  "type": "Feature",
  "properties": {
    "addr:full":"General Delivery Fort Liard NT X0G 0A0",
    "addr:postcode":"x0g 0a0",
    "addr:street":"Fort",
    "iso:country":"CA",
    "sg:address":"General Delivery",
    "sg:city":"Fort Liard",
    "sg:classifiers":[
        {
            "category":"Government",
            "subcategory":"Office",
            "type":"Public Place"
        }
    ],
    "sg:phone":"+1 867 770 3361",
    "sg:postcode":"X0G 0A0",
    "sg:province":"NT",
    "wof:name":"N T Transportation Dept Hwy",
    "wof:placetype":"venue"
},
  "geometry": {"coordinates":[-123.46453094500001,60.2437400818],"type":"Point"}
}