{
  "type": "Feature",
  "properties": {
    "iso:country":"CA",
    "sg:address":"275 First St",
    "sg:city":"Collingwood",
    "sg:classifiers":[
        {
            "category":"Shopping",
            "type":"Retail Goods"
        }
    ],
    "sg:phone":"+1 705 444 1930",
    "sg:postcode":"L9Y 1A8",
    "sg:province":"ON",
    "sg:tags":[
        "pet",
        "food",
        "shop",
        "supply"
    ],
    "wof:name":"Paulmac's Pet Food",
    "wof:placetype":"venue"
},
  "geometry": {"coordinates":[-80.2247848511,44.5022392273],"type":"Point"}
}