{
  "type": "Feature",
  "properties": {
    "addr:full":"20 Athlone Dr Etobicoke ON M8Y 2M4",
    "addr:housenumber":"20",
    "addr:postcode":"m8y 2m4",
    "addr:street":"Athlone Dr",
    "iso:country":"CA",
    "sg:address":"20 Athlone Dr",
    "sg:city":"Etobicoke",
    "sg:classifiers":[
        {
            "category":"Building & Trades",
            "subcategory":"Construction",
            "type":"Services"
        }
    ],
    "sg:phone":"+1 416 239 0770",
    "sg:postcode":"M8Y 2M4",
    "sg:province":"ON",
    "sg:tags":[
        "contractor"
    ],
    "wof:name":"Caldercor Limited Construction",
    "wof:placetype":"venue"
},
  "geometry": {"coordinates":[-79.5043640137,43.6443634033],"type":"Point"}
}