{
  "type": "Feature",
  "properties": {
    "addr:full":"Saskatoon SK S7K 3G8",
    "addr:postcode":"s7k 3g8",
    "iso:country":"CA",
    "sg:city":"Saskatoon",
    "sg:classifiers":[
        {
            "category":"Health Services",
            "subcategory":"Doctor",
            "type":"Services"
        }
    ],
    "sg:phone":"+1 306 665 1234",
    "sg:postcode":"S7K 3G8",
    "sg:province":"SK",
    "sg:tags":[
        "physician",
        "surgeon"
    ],
    "wof:name":"Stalder, Lisa MD",
    "wof:placetype":"venue"
},
  "geometry": {"coordinates":[-106.65921,52.126312],"type":"Point"}
}