{
  "type": "Feature",
  "properties": {
    "addr:full":"1108 55 Ave NE Calgary AB T2E 6Y4",
    "addr:housenumber":"1108",
    "addr:postcode":"t2e 6y4",
    "addr:street":"55 Ave Ne",
    "iso:country":"CA",
    "sg:address":"1108 55 Ave NE",
    "sg:city":"Calgary",
    "sg:classifiers":[
        {
            "category":"Manufacturing",
            "subcategory":"Metals",
            "type":"Manufacturing & Wholesale Goods"
        }
    ],
    "sg:phone":"+1 403 275 3544",
    "sg:postcode":"T2E 6Y4",
    "sg:province":"AB",
    "sg:tags":[
        "cable"
    ],
    "wof:name":"Sercel Canada Ltd",
    "wof:placetype":"venue"
},
  "geometry": {"coordinates":[-114.038681,51.102314],"type":"Point"}
}