{
  "type": "Feature",
  "properties": {
    "addr:full":"38 Arbour Estates Way NW Calgary AB T3G 3Z9",
    "addr:housenumber":"38",
    "addr:postcode":"t3g 3z9",
    "addr:street":"Arbour Estates Way Nw",
    "iso:country":"CA",
    "sg:address":"38 Arbour Estates Way NW",
    "sg:city":"Calgary",
    "sg:classifiers":[
        {
            "category":"Professional",
            "subcategory":"Business Services",
            "type":"Services"
        }
    ],
    "sg:phone":"+1 403 547 3128",
    "sg:postcode":"T3G 3Z9",
    "sg:province":"AB",
    "sg:tags":[
        "translator",
        "interpreter"
    ],
    "wof:name":"Chinese Language Svc",
    "wof:placetype":"venue"
},
  "geometry": {"coordinates":[-114.19778442400001,51.1313362122],"type":"Point"}
}