{
  "type": "Feature",
  "properties": {
    "iso:country":"CA",
    "sg:city":"North Bay",
    "sg:classifiers":[
        {
            "category":"Food & Beverages",
            "subcategory":"Specialty",
            "type":"Retail Goods"
        }
    ],
    "sg:phone":"+1 705 497 3234",
    "sg:postcode":"P1B 1B6",
    "sg:province":"ON",
    "sg:tags":[
        "health",
        "diet"
    ],
    "wof:name":"Nature's Harvest Health Food",
    "wof:placetype":"venue"
},
  "geometry": {"coordinates":[-79.4596939087,46.3053588867],"type":"Point"}
}