{
  "type": "Feature",
  "properties": {
    "iso:country":"CA",
    "sg:address":"1659 Victoria St N",
    "sg:city":"Kitchener",
    "sg:classifiers":[
        {
            "category":"Arts & Performance",
            "subcategory":"Theater",
            "type":"Entertainment"
        }
    ],
    "sg:phone":"+1 519 579 2212",
    "sg:postcode":"N2B 3E6",
    "sg:province":"ON",
    "sg:tags":[
        "entertainer",
        "amusement"
    ],
    "wof:name":"Kid's World",
    "wof:placetype":"venue"
},
  "geometry": {"coordinates":[-80.4331817627,43.4744262695],"type":"Point"}
}