{
  "type": "Feature",
  "properties": {
    "addr:full":"32 Rue Garneau Quebec QC G1R 3V5",
    "addr:housenumber":"32",
    "addr:postcode":"g1r 3v5",
    "addr:street":"Rue Garneau",
    "iso:country":"CA",
    "sg:address":"32 Rue Garneau",
    "sg:city":"Quebec",
    "sg:classifiers":[
        {
            "category":"Cinema",
            "subcategory":"Movie Rental",
            "type":"Entertainment"
        }
    ],
    "sg:phone":"+1 418 694 2471",
    "sg:postcode":"G1R 3V5",
    "sg:province":"QC",
    "sg:tags":[
        "leasing",
        "video",
        "disc",
        "tape"
    ],
    "wof:name":"Video Garneau",
    "wof:placetype":"venue"
},
  "geometry": {"coordinates":[-71.20811500000001,46.81469],"type":"Point"}
}