{
  "type": "Feature",
  "properties": {
    "addr:full":"Mont-Saint-Hilaire QC J3H 4X8",
    "addr:postcode":"j3h 4x8",
    "iso:country":"CA",
    "sg:city":"Mont-Saint-Hilaire",
    "sg:classifiers":[
        {
            "category":"Autos & Motor Vehicles",
            "subcategory":"Motorcycle Sales",
            "type":"Retail Goods"
        }
    ],
    "sg:phone":"+1 450 467 1521",
    "sg:postcode":"J3H 4X8",
    "sg:province":"QC",
    "sg:tags":[
        "scooter"
    ],
    "wof:name":"Super Moto St-Hilaire",
    "wof:placetype":"venue"
},
  "geometry": {"coordinates":[-73.179497,45.569729],"type":"Point"}
}