{
  "type": "Feature",
  "properties": {
    "iso:country":"CA",
    "sg:address":"1 Dock St",
    "sg:city":"Shelburne",
    "sg:classifiers":[
        {
            "category":"Restaurant",
            "type":"Food & Drink"
        }
    ],
    "sg:phone":"+1 902 875 1131",
    "sg:postcode":"B0T 1W0",
    "sg:province":"NS",
    "wof:name":"Sea Dog Saloon Ltd",
    "wof:placetype":"venue"
},
  "geometry": {"coordinates":[-65.31564331049999,43.7656593323],"type":"Point"}
}