{
  "type": "Feature",
  "properties": {
    "addr:full":"44 Lowell Ave St Catharines ON L2R 2E1",
    "addr:housenumber":"44",
    "addr:postcode":"l2r 2e1",
    "addr:street":"Lowell Ave",
    "iso:country":"CA",
    "sg:address":"44 Lowell Ave",
    "sg:city":"St Catharines",
    "sg:classifiers":[
        {
            "category":"Manufacturing",
            "subcategory":"Metals",
            "type":"Manufacturing & Wholesale Goods"
        }
    ],
    "sg:phone":"+1 905 684 7115",
    "sg:postcode":"L2R 2E1",
    "sg:province":"ON",
    "sg:tags":[
        "windows"
    ],
    "wof:name":"Maple Leaf Windows & Doors",
    "wof:placetype":"venue"
},
  "geometry": {"coordinates":[-79.2555007935,43.1647338867],"type":"Point"}
}