{
  "type": "Feature",
  "properties": {
    "addr:full":"5921 45 Street Cres Innisfail AB T4G 1L4",
    "addr:housenumber":"5921",
    "addr:postcode":"t4g 1l4",
    "addr:street":"45 Street Cres",
    "iso:country":"CA",
    "sg:address":"5921 45 Street Cres",
    "sg:city":"Innisfail",
    "sg:classifiers":[
        {
            "category":"Building & Trades",
            "subcategory":"Construction",
            "type":"Services"
        }
    ],
    "sg:phone":"+1 403 227 4784",
    "sg:postcode":"T4G 1L4",
    "sg:province":"AB",
    "sg:tags":[
        "general",
        "contractor"
    ],
    "wof:name":"G & R Builders Ltd",
    "wof:placetype":"venue"
},
  "geometry": {"coordinates":[-113.971153259,52.023979187],"type":"Point"}
}