{
  "type": "Feature",
  "properties": {
    "addr:full":"1590 Rue Barre Saint-Laurent QC H4L 4M6",
    "addr:housenumber":"1590",
    "addr:postcode":"h4l 4m6",
    "addr:street":"Rue Barre",
    "iso:country":"CA",
    "sg:address":"1590 Rue Barre",
    "sg:city":"Saint-Laurent",
    "sg:classifiers":[
        {
            "category":"Manufacturing",
            "subcategory":"Tobacco Products",
            "type":"Manufacturing & Wholesale Goods"
        }
    ],
    "sg:phone":"+1 514 744 9449",
    "sg:postcode":"H4L 4M6",
    "sg:province":"QC",
    "sg:tags":[
        "cigarette",
        "cigar",
        "dealer"
    ],
    "wof:name":"Aro Tabac",
    "wof:placetype":"venue"
},
  "geometry": {"coordinates":[-73.6834411621,45.5243263245],"type":"Point"}
}