{
  "type": "Feature",
  "properties": {
    "addr:full":"570 Mountainview Sq Kitimat BC V8C 2N2",
    "addr:housenumber":"570",
    "addr:postcode":"bc v8c 2n2",
    "addr:street":"Mountainview Sq",
    "iso:country":"CA",
    "sg:address":"570 Mountainview Sq",
    "sg:city":"Kitimat",
    "sg:classifiers":[
        {
            "category":"Health Services",
            "subcategory":"Doctor",
            "type":"Services"
        }
    ],
    "sg:phone":"+1 250 632 2118",
    "sg:postcode":"V8C 2N2",
    "sg:province":"BC",
    "sg:tags":[
        "physician",
        "surgeon"
    ],
    "wof:name":"Huang, Li MD",
    "wof:placetype":"venue"
},
  "geometry": {"coordinates":[-128.649078,54.051979],"type":"Point"}
}