{
  "type": "Feature",
  "properties": {
    "addr:full":"274 Ch Di Betta Grand-Remous QC J0W 1E0",
    "addr:housenumber":"274",
    "addr:postcode":"j0w 1e0",
    "addr:street":"Ch Di Betta",
    "iso:country":"CA",
    "sg:address":"274 Ch Di Betta",
    "sg:city":"Grand-Remous",
    "sg:classifiers":[
        {
            "category":"Travel",
            "subcategory":"Campground",
            "type":"Entertainment"
        }
    ],
    "sg:phone":"+1 819 438 2030",
    "sg:postcode":"J0W 1E0",
    "sg:province":"QC",
    "sg:tags":[
        "camp",
        "fishing"
    ],
    "wof:name":"Pavillon Baskatong Enr",
    "wof:placetype":"venue"
},
  "geometry": {"coordinates":[-75.84131622309999,46.7208862305],"type":"Point"}
}