{
  "type": "Feature",
  "properties": {
    "addr:full":"1215 Concession Rd 13 # C Cannington ON L0E 1E0",
    "addr:housenumber":"1215;13 # c",
    "addr:postcode":"l0e 1e0",
    "addr:street":"Concession Rd",
    "iso:country":"CA",
    "sg:address":"1215 Concession Rd 13 # C",
    "sg:city":"Cannington",
    "sg:classifiers":[
        {
            "category":"Building & Trades",
            "subcategory":"Construction",
            "type":"Services"
        }
    ],
    "sg:phone":"+1 705 432 8451",
    "sg:postcode":"L0E 1E0",
    "sg:province":"ON",
    "sg:tags":[
        "general",
        "contractor"
    ],
    "wof:name":"Town & Country Contracting",
    "wof:placetype":"venue"
},
  "geometry": {"coordinates":[-79.0378952026,44.3503684998],"type":"Point"}
}