{
  "type": "Feature",
  "properties": {
    "addr:full":"8225 Rue Mayrand Montreal QC H4P 2C7",
    "addr:housenumber":"8225",
    "addr:postcode":"h4p 2c7",
    "addr:street":"Rue Mayrand",
    "iso:country":"CA",
    "sg:address":"8225 Rue Mayrand",
    "sg:city":"Montreal",
    "sg:classifiers":[
        {
            "category":"Building & Trades",
            "subcategory":"Construction",
            "type":"Services"
        }
    ],
    "sg:phone":"+1 514 737 6541",
    "sg:postcode":"H4P 2C7",
    "sg:province":"QC",
    "sg:tags":[
        "foundation"
    ],
    "wof:name":"Fondations Micropiles Inc",
    "wof:placetype":"venue"
},
  "geometry": {"coordinates":[-73.65864562989999,45.4998588562],"type":"Point"}
}