{
  "type": "Feature",
  "properties": {
    "addr:full":"Stoney Creek ON L8E 5S2",
    "addr:postcode":"l8e 5s2",
    "iso:country":"CA",
    "sg:city":"Stoney Creek",
    "sg:classifiers":[
        {
            "category":"Autos & Motor Vehicles",
            "subcategory":"Auto Supplies",
            "type":"Retail Goods"
        }
    ],
    "sg:phone":"+1 905 643 6333",
    "sg:postcode":"L8E 5S2",
    "sg:province":"ON",
    "sg:tags":[
        "automobile",
        "parts"
    ],
    "wof:name":"Carquest Auto Parts",
    "wof:placetype":"venue"
},
  "geometry": {"coordinates":[-79.700249,43.222408],"type":"Point"}
}