{
  "type": "Feature",
  "properties": {
    "iso:country":"CA",
    "sg:address":"205 Second Ave SE",
    "sg:city":"Geraldton",
    "sg:classifiers":[
        {
            "category":"Travel",
            "subcategory":"Hotels & Motels",
            "type":"Entertainment"
        }
    ],
    "sg:phone":"+1 807 854 2048",
    "sg:postcode":"P0T 1M0",
    "sg:province":"ON",
    "sg:tags":[
        "breakfast",
        "accommodation",
        "bed"
    ],
    "wof:name":"Victoria Bed & Breakfast",
    "wof:placetype":"venue"
},
  "geometry": {"coordinates":[-86.9521942139,49.7256011963],"type":"Point"}
}