{
  "type": "Feature",
  "properties": {
    "addr:full":"1124 18 St S Lethbridge AB T1K 2A5",
    "addr:housenumber":"1124",
    "addr:postcode":"t1k 2a5",
    "addr:street":"18 St S",
    "iso:country":"CA",
    "sg:address":"1124 18 St S",
    "sg:city":"Lethbridge",
    "sg:classifiers":[
        {
            "category":"Professional",
            "subcategory":"Business Services",
            "type":"Services"
        }
    ],
    "sg:phone":"+1 403 320 7762",
    "sg:postcode":"T1K 2A5",
    "sg:province":"AB",
    "sg:tags":[
        "designer",
        "drafting"
    ],
    "wof:name":"Custom Concepts",
    "wof:placetype":"venue"
},
  "geometry": {"coordinates":[-112.815956,49.680573],"type":"Point"}
}