{
  "type": "Feature",
  "properties": {
    "addr:full":"Richmond Hill ON L4B 2P1",
    "addr:postcode":"l4b 2p1",
    "iso:country":"CA",
    "sg:city":"Richmond Hill",
    "sg:classifiers":[
        {
            "category":"Wholesale",
            "subcategory":"Home Furnishings",
            "type":"Manufacturing & Wholesale Goods"
        }
    ],
    "sg:phone":"+1 905 763 8528",
    "sg:postcode":"L4B 2P1",
    "sg:province":"ON",
    "sg:tags":[
        "microwave",
        "oven"
    ],
    "wof:name":"Galanz",
    "wof:placetype":"venue"
},
  "geometry": {"coordinates":[-79.3832015991,43.8541908264],"type":"Point"}
}