{
  "type": "Feature",
  "properties": {
    "iso:country":"CA",
    "sg:address":"1948 Dayton St",
    "sg:city":"Kelowna",
    "sg:classifiers":[
        {
            "category":"Wholesale",
            "subcategory":"Construction Materials",
            "type":"Manufacturing & Wholesale Goods"
        }
    ],
    "sg:phone":"+1 250 717 1616",
    "sg:postcode":"V1Y 7W6",
    "sg:province":"BC",
    "sg:tags":[
        "concrete",
        "form"
    ],
    "wof:name":"National Concrete Accessories",
    "wof:placetype":"venue"
},
  "geometry": {"coordinates":[-119.461181641,49.8780708313],"type":"Point"}
}