{
  "type": "Feature",
  "properties": {
    "iso:country":"CA",
    "sg:city":"Montreal",
    "sg:classifiers":[
        {
            "category":"Shopping",
            "type":"Retail Goods"
        }
    ],
    "sg:phone":"+1 514 524 1259",
    "sg:postcode":"H2K 4L5",
    "sg:province":"QC",
    "sg:tags":[
        "hearing",
        "equipment",
        "supply",
        "impaired"
    ],
    "wof:name":"Groupe Forget-Parent",
    "wof:placetype":"venue"
},
  "geometry": {"coordinates":[-73.563927,45.528576],"type":"Point"}
}