{
  "type": "Feature",
  "properties": {
    "addr:full":"11405 4E Av Montreal QC H1E 2Y8",
    "addr:housenumber":"11405",
    "addr:postcode":"h1e 2y8",
    "addr:street":"4E Av",
    "iso:country":"CA",
    "sg:address":"11405 4E Av",
    "sg:city":"Montreal",
    "sg:classifiers":[
        {
            "category":"Wholesale",
            "subcategory":"Durable Goods & Equipment",
            "type":"Manufacturing & Wholesale Goods"
        }
    ],
    "sg:phone":"+1 514 648 1244",
    "sg:postcode":"H1E 2Y8",
    "sg:province":"QC",
    "sg:tags":[
        "importer"
    ],
    "wof:name":"Verona Importing Ltd",
    "wof:placetype":"venue"
},
  "geometry": {"coordinates":[-73.597618,45.618534],"type":"Point"}
}