{
  "type": "Feature",
  "properties": {
    "addr:full":"4921 Bathurst St North York ON M2R 1X8",
    "addr:housenumber":"4921",
    "addr:postcode":"m2r 1x8",
    "addr:street":"Bathurst St",
    "iso:country":"CA",
    "sg:address":"4921 Bathurst St",
    "sg:city":"North York",
    "sg:classifiers":[
        {
            "category":"Retail",
            "subcategory":"Laundry & Dry Cleaning",
            "type":"Services"
        }
    ],
    "sg:phone":"+1 416 225 8952",
    "sg:postcode":"M2R 1X8",
    "sg:province":"ON",
    "sg:tags":[
        "cleaners"
    ],
    "wof:name":"Finch Cleaners & Launderers",
    "wof:placetype":"venue"
},
  "geometry": {"coordinates":[-79.442711,43.77356],"type":"Point"}
}