{
  "type": "Feature",
  "properties": {
    "iso:country":"CA",
    "sg:address":"212 Breithaupt St",
    "sg:city":"Kitchener",
    "sg:classifiers":[
        {
            "category":"Retail",
            "subcategory":"Auto Repair",
            "type":"Services"
        }
    ],
    "sg:phone":"+1 519 745 2034",
    "sg:postcode":"N2H 5H4",
    "sg:province":"ON",
    "sg:tags":[
        "transmission"
    ],
    "wof:name":"Jmw Automotive Inc",
    "wof:placetype":"venue"
},
  "geometry": {"coordinates":[-80.491065979,43.4573326111],"type":"Point"}
}