{
  "type": "Feature",
  "properties": {
    "addr:full":"589 Price Ch Dsl DE Drummond NB E3Y 2B2",
    "addr:housenumber":"589",
    "addr:postcode":"e3y 2b2",
    "addr:street":"De Drummond",
    "iso:country":"CA",
    "sg:address":"589 Price Ch",
    "sg:city":"Dsl DE Drummond",
    "sg:classifiers":[
        {
            "category":"Shopping",
            "type":"Retail Goods"
        }
    ],
    "sg:phone":"+1 506 473 3839",
    "sg:postcode":"E3Y 2B2",
    "sg:province":"NB",
    "sg:tags":[
        "trophy",
        "medal",
        "award"
    ],
    "wof:name":"Trophy & Plaque Ginette Moreau",
    "wof:placetype":"venue"
},
  "geometry": {"coordinates":[-67.685181,47.036789],"type":"Point"}
}