{
  "type": "Feature",
  "properties": {
    "addr:full":"Medicine Hat AB T1B 2H2",
    "addr:postcode":"t1b 2h2",
    "iso:country":"CA",
    "sg:city":"Medicine Hat",
    "sg:classifiers":[
        {
            "category":"Health Services",
            "subcategory":"Doctor",
            "type":"Services"
        }
    ],
    "sg:phone":"+1 403 529 6600",
    "sg:postcode":"T1B 2H2",
    "sg:province":"AB",
    "sg:tags":[
        "physician",
        "surgeon"
    ],
    "wof:name":"Saujani, V MD",
    "wof:placetype":"venue"
},
  "geometry": {"coordinates":[-110.647644043,50.0088615417],"type":"Point"}
}