{
  "type": "Feature",
  "properties": {
    "addr:full":"240 Mackay St Pembroke ON K8A 1C5",
    "addr:housenumber":"240",
    "addr:postcode":"k8a 1c5",
    "addr:street":"Mackay St",
    "iso:country":"CA",
    "sg:address":"240 Mackay St",
    "sg:city":"Pembroke",
    "sg:classifiers":[
        {
            "category":"Health Services",
            "subcategory":"Doctor",
            "type":"Services"
        }
    ],
    "sg:phone":"+1 613 732 2611",
    "sg:postcode":"K8A 1C5",
    "sg:province":"ON",
    "sg:tags":[
        "physician",
        "surgeon"
    ],
    "wof:name":"Hing, Roland MD",
    "wof:placetype":"venue"
},
  "geometry": {"coordinates":[-77.110733,45.825695],"type":"Point"}
}