{
  "type": "Feature",
  "properties": {
    "iso:country":"CA",
    "sg:address":"4370 Steeles Ave W",
    "sg:city":"Woodbridge",
    "sg:classifiers":[
        {
            "category":"Shopping",
            "subcategory":"Pharmacy",
            "type":"Retail Goods"
        }
    ],
    "sg:phone":"+1 905 856 3080",
    "sg:postcode":"L4L 4Y4",
    "sg:province":"ON",
    "sg:tags":[
        "aid",
        "first",
        "supply"
    ],
    "wof:name":"Mister Supplier Ltd",
    "wof:placetype":"venue"
},
  "geometry": {"coordinates":[-79.563477,43.766964],"type":"Point"}
}