{
  "type": "Feature",
  "properties": {
    "addr:full":"10051 Rue Mirabeau Anjou QC H1J 1T7",
    "addr:housenumber":"10051",
    "addr:postcode":"h1j 1t7",
    "addr:street":"Rue Mirabeau",
    "iso:country":"CA",
    "sg:address":"10051 Rue Mirabeau",
    "sg:city":"Anjou",
    "sg:classifiers":[
        {
            "category":"Wholesale",
            "subcategory":"Machinery & Supplies",
            "type":"Manufacturing & Wholesale Goods"
        }
    ],
    "sg:phone":"+1 514 723 0480",
    "sg:postcode":"H1J 1T7",
    "sg:province":"QC",
    "sg:tags":[
        "salon",
        "beauty"
    ],
    "wof:name":"Groupe Plateau Beaute",
    "wof:placetype":"venue"
},
  "geometry": {"coordinates":[-73.57888793950001,45.6152458191],"type":"Point"}
}