{
  "type": "Feature",
  "properties": {
    "addr:full":"3553 South Common Crt Mississauga ON L5L 2B3",
    "addr:housenumber":"3553",
    "addr:postcode":"l5l 2b3",
    "addr:street":"South Common Crt",
    "iso:country":"CA",
    "sg:address":"3553 South Common Crt",
    "sg:city":"Mississauga",
    "sg:classifiers":[
        {
            "category":"Education",
            "subcategory":"School",
            "type":"Public Place"
        }
    ],
    "sg:phone":"+1 905 569 7400",
    "sg:postcode":"L5L 2B3",
    "sg:province":"ON",
    "sg:tags":[
        "child",
        "care"
    ],
    "wof:name":"Rotherglen Private School",
    "wof:placetype":"venue"
},
  "geometry": {"coordinates":[-79.686684,43.54364],"type":"Point"}
}