{
  "type": "Feature",
  "properties": {
    "addr:full":"60 Weichel St Kitchener ON N2M 2A6",
    "addr:housenumber":"60",
    "addr:postcode":"n2m 2a6",
    "addr:street":"Weichel St",
    "iso:country":"CA",
    "sg:address":"60 Weichel St",
    "sg:city":"Kitchener",
    "sg:classifiers":[
        {
            "category":"Recreation",
            "type":"Entertainment"
        }
    ],
    "sg:phone":"+1 519 744 5249",
    "sg:postcode":"N2M 2A6",
    "sg:province":"ON",
    "sg:tags":[
        "provincial",
        "parks",
        "government"
    ],
    "wof:name":"Kitchener Ringette",
    "wof:placetype":"venue"
},
  "geometry": {"coordinates":[-80.517982,43.44141],"type":"Point"}
}