{
  "type": "Feature",
  "properties": {
    "addr:full":"1514 Rue Notre-Dame Centre Trois-Rivieres QC G9A 4X6",
    "addr:housenumber":"1514",
    "addr:postcode":"g9a 4x6",
    "addr:street":"Rue Notre-Dame Centre Trois-Rivieres",
    "iso:country":"CA",
    "sg:address":"1514 Rue Notre-Dame Centre",
    "sg:city":"Trois-Rivieres",
    "sg:classifiers":[
        {
            "category":"Professional",
            "subcategory":"Art Services",
            "type":"Services"
        }
    ],
    "sg:phone":"+1 819 374 6104",
    "sg:postcode":"G9A 4X6",
    "sg:province":"QC",
    "sg:tags":[
        "production",
        "video",
        "taping"
    ],
    "wof:name":"Studio Henrichon Inc",
    "wof:placetype":"venue"
},
  "geometry": {"coordinates":[-72.483749,46.382511],"type":"Point"}
}