{
  "type": "Feature",
  "properties": {
    "addr:full":"3473 Place Du Trianon Sainte-Foy QC G1X 2G1",
    "addr:housenumber":"3473",
    "addr:postcode":"g1x 2g1",
    "addr:street":"Place Du Trianon",
    "iso:country":"CA",
    "sg:address":"3473 Place Du Trianon",
    "sg:city":"Sainte-Foy",
    "sg:classifiers":[
        {
            "category":"Wholesale",
            "subcategory":"Electrical",
            "type":"Manufacturing & Wholesale Goods"
        }
    ],
    "sg:phone":"+1 418 656 1265",
    "sg:postcode":"G1X 2G1",
    "sg:province":"QC",
    "sg:tags":[
        "communication",
        "facsimile",
        "equipment"
    ],
    "wof:name":"Quefax Telecom Inc",
    "wof:placetype":"venue"
},
  "geometry": {"coordinates":[-71.329109,46.767696],"type":"Point"}
}