{
  "type": "Feature",
  "properties": {
    "addr:full":"Saskatoon SK S7L 6M8",
    "addr:postcode":"s7l 6m8",
    "iso:country":"CA",
    "sg:city":"Saskatoon",
    "sg:classifiers":[
        {
            "category":"Social Services",
            "type":"Services"
        }
    ],
    "sg:phone":"+1 306 651 3021",
    "sg:postcode":"S7L 6M8",
    "sg:province":"SK",
    "sg:tags":[
        "information",
        "organization",
        "treatment",
        "alcoholism",
        "welfare"
    ],
    "wof:name":"Metis Addictions Council",
    "wof:placetype":"venue"
},
  "geometry": {"coordinates":[-106.68397521999999,52.1574554443],"type":"Point"}
}