{
  "type": "Feature",
  "properties": {
    "iso:country":"CA",
    "sg:address":"5350 Rue J Armand Bonbardier",
    "sg:city":"Saint-Hubert",
    "sg:classifiers":[
        {
            "category":"Manufacturing",
            "subcategory":"Electronics",
            "type":"Manufacturing & Wholesale Goods"
        }
    ],
    "sg:phone":"+1 450 462 8651",
    "sg:postcode":"J3Z 1J1",
    "sg:province":"QC",
    "sg:tags":[
        "equipment",
        "electronic",
        "supply"
    ],
    "wof:name":"Specnor Tecnic Corp",
    "wof:placetype":"venue"
},
  "geometry": {"coordinates":[-73.4129486084,45.4595603943],"type":"Point"}
}