{
  "type": "Feature",
  "properties": {
    "iso:country":"CA",
    "sg:city":"Calgary",
    "sg:classifiers":[
        {
            "category":"Wholesale",
            "subcategory":"Machinery & Supplies",
            "type":"Manufacturing & Wholesale Goods"
        }
    ],
    "sg:phone":"+1 403 277 3010",
    "sg:postcode":"T2R 0J4",
    "sg:province":"AB",
    "sg:tags":[
        "equipment",
        "oil",
        "well"
    ],
    "wof:name":"Inter-Can Projects Ltd",
    "wof:placetype":"venue"
},
  "geometry": {"coordinates":[-114.082443,51.042095],"type":"Point"}
}