{
  "type": "Feature",
  "properties": {
    "iso:country":"CA",
    "sg:city":"Markham",
    "sg:classifiers":[
        {
            "category":"Real Estate",
            "subcategory":"Architect",
            "type":"Services"
        }
    ],
    "sg:phone":"+1 905 470 7200",
    "sg:postcode":"L3R 8H8",
    "sg:province":"ON",
    "wof:name":"Boigon Petroff Shepherd",
    "wof:placetype":"venue"
},
  "geometry": {"coordinates":[-79.3394241333,43.8585472107],"type":"Point"}
}