{
  "type": "Feature",
  "properties": {
    "addr:full":"12975 Rte Marie-Victorin Sorel-Tracy QC J3P 5N3",
    "addr:housenumber":"12975",
    "addr:postcode":"j3p 5n3",
    "addr:street":"Rte Marie-Victorin",
    "iso:country":"CA",
    "sg:address":"12975 Rte Marie-Victorin",
    "sg:city":"Sorel-Tracy",
    "sg:classifiers":[
        {
            "category":"Professional",
            "subcategory":"Business Services",
            "type":"Services"
        }
    ],
    "sg:phone":"+1 450 780 2393",
    "sg:postcode":"J3P 5N3",
    "sg:province":"QC",
    "sg:tags":[
        "notary"
    ],
    "wof:name":"Lavallee, Carmelle",
    "wof:placetype":"venue"
},
  "geometry": {"coordinates":[-73.176514,45.986259],"type":"Point"}
}