{
  "type": "Feature",
  "properties": {
    "addr:full":"2828 Rue DE Salaberry Montreal QC H3M 1L3",
    "addr:housenumber":"2828",
    "addr:postcode":"h3m 1l3",
    "addr:street":"Rue De Salaberry",
    "iso:country":"CA",
    "sg:address":"2828 Rue DE Salaberry",
    "sg:city":"Montreal",
    "sg:classifiers":[
        {
            "category":"Cinema",
            "subcategory":"Movie Rental",
            "type":"Entertainment"
        }
    ],
    "sg:phone":"+1 514 332 2345",
    "sg:postcode":"H3M 1L3",
    "sg:province":"QC",
    "sg:tags":[
        "leasing",
        "video",
        "disc",
        "tape"
    ],
    "wof:name":"Blockbuster Video",
    "wof:placetype":"venue"
},
  "geometry": {"coordinates":[-73.700058,45.537258],"type":"Point"}
}