{
  "type": "Feature",
  "properties": {
    "addr:full":"404 Boul Des Laurentides Laval QC H7G 2T8",
    "addr:housenumber":"404",
    "addr:postcode":"qc h7g 2t8",
    "addr:street":"Boul Des Laurentides",
    "iso:country":"CA",
    "sg:address":"404 Boul Des Laurentides",
    "sg:city":"Laval",
    "sg:classifiers":[
        {
            "category":"Shopping",
            "subcategory":"Used Merchandise",
            "type":"Retail Goods"
        }
    ],
    "sg:phone":"+1 450 967 2274",
    "sg:postcode":"H7G 2T8",
    "sg:province":"QC",
    "sg:tags":[
        "pawnbroker"
    ],
    "wof:name":"Banco Argent Comptant",
    "wof:placetype":"venue"
},
  "geometry": {"coordinates":[-73.689796,45.568111],"type":"Point"}
}