{
  "type": "Feature",
  "properties": {
    "addr:full":"120 Jackson St E Hamilton ON L8N 1L3",
    "addr:housenumber":"120",
    "addr:postcode":"l8n 1l3",
    "addr:street":"Jackson St E",
    "iso:country":"CA",
    "sg:address":"120 Jackson St E",
    "sg:city":"Hamilton",
    "sg:classifiers":[
        {
            "category":"Professional",
            "subcategory":"Lawyer & Legal Services",
            "type":"Services"
        }
    ],
    "sg:phone":"+1 905 777 1141",
    "sg:postcode":"L8N 1L3",
    "sg:province":"ON",
    "sg:tags":[
        "attorney"
    ],
    "wof:name":"Gee, Robert S",
    "wof:placetype":"venue"
},
  "geometry": {"coordinates":[-79.86537199999999,43.253136],"type":"Point"}
}