{
  "type": "Feature",
  "properties": {
    "iso:country":"CA",
    "sg:address":"120 Jackson St E",
    "sg:city":"Hamilton",
    "sg:classifiers":[
        {
            "category":"Professional",
            "subcategory":"Lawyer & Legal Services",
            "type":"Services"
        }
    ],
    "sg:phone":"+1 905 777 1141",
    "sg:postcode":"L8N 1L3",
    "sg:province":"ON",
    "sg:tags":[
        "attorney"
    ],
    "wof:name":"Gee, Robert S",
    "wof:placetype":"venue"
},
  "geometry": {"coordinates":[-79.865372,43.253136],"type":"Point"}
}