{
  "type": "Feature",
  "properties": {
    "iso:country":"CA",
    "sg:address":"2155 Av Chauveau",
    "sg:city":"Quebec",
    "sg:classifiers":[
        {
            "category":"Bars & Pubs",
            "type":"Food & Drink"
        }
    ],
    "sg:phone":"+1 418 843 0524",
    "sg:postcode":"G2C 1B2",
    "sg:province":"QC",
    "wof:name":"Brasserie Lionel Enr",
    "wof:placetype":"venue"
},
  "geometry": {"coordinates":[-71.3242263794,46.8441162109],"type":"Point"}
}