{
  "type": "Feature",
  "properties": {
    "addr:full":"2027 Commerce Park Dr Innisfil ON L9S 4A2",
    "addr:housenumber":"2027",
    "addr:postcode":"l9s 4a2",
    "addr:street":"Commerce Park Dr",
    "iso:country":"CA",
    "sg:address":"2027 Commerce Park Dr",
    "sg:city":"Innisfil",
    "sg:classifiers":[
        {
            "category":"Manufacturing",
            "subcategory":"Buildings",
            "type":"Manufacturing & Wholesale Goods"
        }
    ],
    "sg:phone":"+1 705 436 7507",
    "sg:postcode":"L9S 4A2",
    "sg:province":"ON",
    "sg:tags":[
        "cottage",
        "prefabricated"
    ],
    "wof:name":"Linwood Homes Ltd",
    "wof:placetype":"venue"
},
  "geometry": {"coordinates":[-79.6752624512,44.2831459045],"type":"Point"}
}