{
  "type": "Feature",
  "properties": {
    "addr:full":"Berthierville QC J0K 1A0",
    "addr:postcode":"j0k 1a0",
    "iso:country":"CA",
    "sg:city":"Berthierville",
    "sg:classifiers":[
        {
            "category":"Recreation",
            "subcategory":"Marina",
            "type":"Entertainment"
        }
    ],
    "sg:phone":"+1 450 836 7636",
    "sg:postcode":"J0K 1A0",
    "sg:province":"QC",
    "wof:name":"Marina Port DE Plaisance",
    "wof:placetype":"venue"
},
  "geometry": {"coordinates":[-73.17203521730001,46.0832901001],"type":"Point"}
}