{
  "type": "Feature",
  "properties": {
    "addr:full":"502 Princess St Port Lambton ON N0P 2B0",
    "addr:housenumber":"502",
    "addr:postcode":"n0p 2b0",
    "addr:street":"Princess St",
    "iso:country":"CA",
    "sg:address":"502 Princess St",
    "sg:city":"Port Lambton",
    "sg:classifiers":[
        {
            "category":"Retail",
            "subcategory":"Auto Repair",
            "type":"Services"
        }
    ],
    "sg:phone":"+1 519 677 4007",
    "sg:postcode":"N0P 2B0",
    "sg:province":"ON",
    "sg:tags":[
        "body",
        "automobile",
        "painting"
    ],
    "wof:name":"Port Lambton Auto Body-Towing",
    "wof:placetype":"venue"
},
  "geometry": {"coordinates":[-82.50547,42.659126],"type":"Point"}
}