{
  "type": "Feature",
  "properties": {
    "iso:country":"CA",
    "sg:address":"2477 Bloor St W",
    "sg:city":"Toronto",
    "sg:classifiers":[
        {
            "category":"Health Services",
            "subcategory":"Health Practitioner",
            "type":"Services"
        }
    ],
    "sg:phone":"+1 416 763 6649",
    "sg:postcode":"M6S 1P7",
    "sg:province":"ON",
    "sg:tags":[
        "therapist",
        "physical"
    ],
    "wof:name":"L & A Consultants",
    "wof:placetype":"venue"
},
  "geometry": {"coordinates":[-79.4847488403,43.6489906311],"type":"Point"}
}