{
  "type": "Feature",
  "properties": {
    "addr:full":"Saskatoon SK S7M 2Y1",
    "addr:postcode":"s7m 2y1",
    "iso:country":"CA",
    "sg:city":"Saskatoon",
    "sg:classifiers":[
        {
            "category":"Social Services",
            "type":"Services"
        }
    ],
    "sg:phone":"+1 306 653 3900",
    "sg:postcode":"S7M 2Y1",
    "sg:province":"SK",
    "sg:tags":[
        "counseling"
    ],
    "wof:name":"Family Healing Circle Lodge",
    "wof:placetype":"venue"
},
  "geometry": {"coordinates":[-106.695800781,52.1287651062],"type":"Point"}
}