{
  "type": "Feature",
  "properties": {
    "addr:full":"Parksville BC V9P 2B9",
    "addr:postcode":"v9p 2b9",
    "iso:country":"CA",
    "sg:city":"Parksville",
    "sg:classifiers":[
        {
            "category":"Retail",
            "subcategory":"Auto Repair",
            "type":"Services"
        }
    ],
    "sg:phone":"+1 250 954 3442",
    "sg:postcode":"V9P 2B9",
    "sg:province":"BC",
    "sg:tags":[
        "repairing",
        "automobile"
    ],
    "wof:name":"Erringtom Mechanical",
    "wof:placetype":"venue"
},
  "geometry": {"coordinates":[-124.324532,49.307011],"type":"Point"}
}