{
  "type": "Feature",
  "properties": {
    "iso:country":"CA",
    "sg:address":"317 St Lawrence St",
    "sg:city":"Merrickville",
    "sg:classifiers":[
        {
            "category":"Restaurant",
            "type":"Food & Drink"
        }
    ],
    "sg:phone":"+1 613 269 2094",
    "sg:postcode":"K0G 1N0",
    "sg:province":"ON",
    "sg:tags":[
        "pub"
    ],
    "wof:name":"Goose & Gridiron",
    "wof:placetype":"venue"
},
  "geometry": {"coordinates":[-75.8363647461,44.9145736694],"type":"Point"}
}