{
  "type": "Feature",
  "properties": {
    "iso:country":"CA",
    "sg:address":"5708 Rue Vanden-Abeele",
    "sg:city":"Saint-Laurent",
    "sg:classifiers":[
        {
            "category":"Manufacturing",
            "subcategory":"Tools & Machinery",
            "type":"Manufacturing & Wholesale Goods"
        }
    ],
    "sg:phone":"+1 514 745 2222",
    "sg:postcode":"H4S 1R9",
    "sg:province":"QC",
    "sg:tags":[
        "machine",
        "shop"
    ],
    "wof:name":"Mpm Atelier D'Usinage",
    "wof:placetype":"venue"
},
  "geometry": {"coordinates":[-73.74369,45.48695],"type":"Point"}
}