{
  "type": "Feature",
  "properties": {
    "addr:full":"1379 Rue Des Champs-Elysees Chicoutimi QC G7H 6J2",
    "addr:housenumber":"1379",
    "addr:postcode":"g7h 6j2",
    "addr:street":"Rue Des Champs-Elysees",
    "iso:country":"CA",
    "sg:address":"1379 Rue Des Champs-Elysees",
    "sg:city":"Chicoutimi",
    "sg:classifiers":[
        {
            "category":"Wholesale",
            "subcategory":"Furniture",
            "type":"Manufacturing & Wholesale Goods"
        }
    ],
    "sg:phone":"+1 418 545 9506",
    "sg:postcode":"G7H 6J2",
    "sg:province":"QC",
    "sg:tags":[
        "stationer"
    ],
    "wof:name":"A Et D Papeterie Inc",
    "wof:placetype":"venue"
},
  "geometry": {"coordinates":[-71.0517044067,48.4044189453],"type":"Point"}
}