{
  "type": "Feature",
  "properties": {
    "iso:country":"CA",
    "sg:address":"226 Rue Montcalm",
    "sg:city":"Hull",
    "sg:classifiers":[
        {
            "category":"Home & Garden",
            "subcategory":"Household Appliances",
            "type":"Retail Goods"
        }
    ],
    "sg:phone":"+1 819 776 0505",
    "sg:postcode":"J8Y 3B8",
    "sg:province":"QC",
    "wof:name":"Sos Electromenager",
    "wof:placetype":"venue"
},
  "geometry": {"coordinates":[-75.73192596440001,45.4312934875],"type":"Point"}
}