{
  "type": "Feature",
  "properties": {
    "iso:country":"CA",
    "sg:city":"Campbell River",
    "sg:classifiers":[
        {
            "category":"Retail",
            "subcategory":"Self-service Laundry",
            "type":"Services"
        }
    ],
    "sg:phone":"+1 250 830 1110",
    "sg:postcode":"V9W 2X5",
    "sg:province":"BC",
    "wof:name":"A J's Laundry Svc",
    "wof:placetype":"venue"
},
  "geometry": {"coordinates":[-125.247291565,50.0041999817],"type":"Point"}
}