{
  "type": "Feature",
  "properties": {
    "iso:country":"CA",
    "sg:address":"3539 Rue Ontario E",
    "sg:city":"Montreal",
    "sg:classifiers":[
        {
            "category":"Personal",
            "subcategory":"Beauty Salon",
            "type":"Services"
        }
    ],
    "sg:phone":"+1 514 257 5562",
    "sg:postcode":"H1W 1R6",
    "sg:province":"QC",
    "sg:tags":[
        "manicuring"
    ],
    "wof:name":"Ongles Populaires",
    "wof:placetype":"venue"
},
  "geometry": {"coordinates":[-73.545319,45.544643],"type":"Point"}
}