{
  "type": "Feature",
  "properties": {
    "addr:full":"51 Ontario Rd Mitchell ON N0K 1N0",
    "addr:housenumber":"51",
    "addr:postcode":"n0k 1n0",
    "addr:street":"Ontario Rd",
    "iso:country":"CA",
    "sg:address":"51 Ontario Rd",
    "sg:city":"Mitchell",
    "sg:classifiers":[
        {
            "category":"Farming",
            "subcategory":"Farm & Veterinary Services",
            "type":"Manufacturing & Wholesale Goods"
        }
    ],
    "sg:phone":"+1 519 348 4885",
    "sg:postcode":"N0K 1N0",
    "sg:province":"ON",
    "sg:tags":[
        "management"
    ],
    "wof:name":"Swine Management Svc",
    "wof:placetype":"venue"
},
  "geometry": {"coordinates":[-81.196884,43.46777],"type":"Point"}
}