{
  "type": "Feature",
  "properties": {
    "addr:full":"1516 Fairfield Rd # 6 Victoria BC V8S 1G1",
    "addr:housenumber":"1516",
    "addr:postcode":"v8s 1g1",
    "addr:street":"Fairfield Rd # 6",
    "iso:country":"CA",
    "sg:address":"1516 Fairfield Rd # 6",
    "sg:city":"Victoria",
    "sg:classifiers":[
        {
            "category":"Food & Beverages",
            "subcategory":"Specialty",
            "type":"Retail Goods"
        }
    ],
    "sg:phone":"+1 250 595 6690",
    "sg:postcode":"V8S 1G1",
    "sg:province":"BC",
    "sg:tags":[
        "health",
        "diet"
    ],
    "wof:name":"Logical Health Foods",
    "wof:placetype":"venue"
},
  "geometry": {"coordinates":[-123.339592,48.412479],"type":"Point"}
}