{
  "type": "Feature",
  "properties": {
    "addr:full":"2190 Av Du Mont-Royal E Montreal QC H2H 1K3",
    "addr:housenumber":"2190",
    "addr:postcode":"h2h 1k3",
    "addr:street":"Av Du Mont-Royal E",
    "iso:country":"CA",
    "sg:address":"2190 Av Du Mont-Royal E",
    "sg:city":"Montreal",
    "sg:classifiers":[
        {
            "category":"Professional",
            "subcategory":"Advertising",
            "type":"Services"
        }
    ],
    "sg:phone":"+1 514 525 1149",
    "sg:postcode":"H2H 1K3",
    "sg:province":"QC",
    "wof:name":"Memoriel Inc",
    "wof:placetype":"venue"
},
  "geometry": {"coordinates":[-73.571136,45.536434],"type":"Point"}
}