{
  "type": "Feature",
  "properties": {
    "addr:full":"1192 Vanier Dr Mississauga ON L5H 3X1",
    "addr:housenumber":"1192",
    "addr:postcode":"l5h 3x1",
    "addr:street":"Vanier Dr",
    "iso:country":"CA",
    "sg:address":"1192 Vanier Dr",
    "sg:city":"Mississauga",
    "sg:classifiers":[
        {
            "category":"Shopping",
            "subcategory":"Optical Goods",
            "type":"Retail Goods"
        }
    ],
    "sg:phone":"+1 905 271 2218",
    "sg:postcode":"L5H 3X1",
    "sg:province":"ON",
    "wof:name":"Partners in Optics Inc",
    "wof:placetype":"venue"
},
  "geometry": {"coordinates":[-79.62479400629999,43.5425262451],"type":"Point"}
}