{
  "type": "Feature",
  "properties": {
    "iso:country":"CA",
    "sg:address":"4917 50 Ave",
    "sg:city":"Clyde",
    "sg:classifiers":[
        {
            "category":"Food & Beverages",
            "subcategory":"Groceries & Convenience Stores",
            "type":"Retail Goods"
        }
    ],
    "sg:phone":"+1 780 348 5901",
    "sg:postcode":"T0G 0P0",
    "sg:province":"AB",
    "sg:tags":[
        "grocer"
    ],
    "wof:name":"Clyde Corner Store",
    "wof:placetype":"venue"
},
  "geometry": {"coordinates":[-113.634529114,54.1468696594],"type":"Point"}
}