{
  "type": "Feature",
  "properties": {
    "addr:full":"656 1/2 3 St SE Medicine Hat AB T1A 0H5",
    "addr:housenumber":"656 1 / 2 3",
    "addr:postcode":"t1a 0h5",
    "addr:street":"St Se",
    "iso:country":"CA",
    "sg:address":"656 1/2 3 St SE",
    "sg:city":"Medicine Hat",
    "sg:classifiers":[
        {
            "category":"Taxi",
            "type":"Transportation"
        }
    ],
    "sg:phone":"+1 403 526 3333",
    "sg:postcode":"T1A 0H5",
    "sg:province":"AB",
    "sg:tags":[
        "taxicab"
    ],
    "wof:name":"Deluxe Central Taxi",
    "wof:placetype":"venue"
},
  "geometry": {"coordinates":[-110.67457580599999,50.0403251648],"type":"Point"}
}