{
  "type": "Feature",
  "properties": {
    "iso:country":"CA",
    "sg:address":"1041 Lakeshore Rd E",
    "sg:city":"Mississauga",
    "sg:classifiers":[
        {
            "category":"Travel",
            "subcategory":"Hotels & Motels",
            "type":"Entertainment"
        }
    ],
    "sg:phone":"+1 905 278 3569",
    "sg:postcode":"L5E 1E7",
    "sg:province":"ON",
    "wof:name":"Willows Motel",
    "wof:placetype":"venue"
},
  "geometry": {"coordinates":[-79.558624,43.577229],"type":"Point"}
}