{
  "type": "Feature",
  "properties": {
    "addr:full":"1041 Lakeshore Rd E Mississauga ON L5E 1E7",
    "addr:housenumber":"1041",
    "addr:postcode":"l5e 1e7",
    "addr:street":"Lakeshore Rd E",
    "iso:country":"CA",
    "sg:address":"1041 Lakeshore Rd E",
    "sg:city":"Mississauga",
    "sg:classifiers":[
        {
            "category":"Travel",
            "subcategory":"Hotels & Motels",
            "type":"Entertainment"
        }
    ],
    "sg:phone":"+1 905 278 3569",
    "sg:postcode":"L5E 1E7",
    "sg:province":"ON",
    "wof:name":"Willows Motel",
    "wof:placetype":"venue"
},
  "geometry": {"coordinates":[-79.55862399999999,43.577229],"type":"Point"}
}