{
  "type": "Feature",
  "properties": {
    "addr:full":"880 Barton St E Hamilton ON L8L 3B7",
    "addr:housenumber":"880",
    "addr:postcode":"l8l 3b7",
    "addr:street":"Barton St E",
    "iso:country":"CA",
    "sg:address":"880 Barton St E",
    "sg:city":"Hamilton",
    "sg:classifiers":[
        {
            "category":"Organizations",
            "subcategory":"Religious Organization",
            "type":"Services"
        }
    ],
    "sg:phone":"+1 905 549 0470",
    "sg:postcode":"L8L 3B7",
    "sg:province":"ON",
    "sg:tags":[
        "church"
    ],
    "wof:name":"Holy Trinity Polish Church",
    "wof:placetype":"venue"
},
  "geometry": {"coordinates":[-79.8266372681,43.2538642883],"type":"Point"}
}