{
  "type": "Feature",
  "properties": {
    "addr:full":"4 Bolingbroke Rd North York ON M6B 3L6",
    "addr:housenumber":"4",
    "addr:postcode":"m6b 3l6",
    "addr:street":"Bolingbroke Rd",
    "iso:country":"CA",
    "sg:address":"4 Bolingbroke Rd",
    "sg:city":"North York",
    "sg:classifiers":[
        {
            "category":"Building & Trades",
            "subcategory":"Construction",
            "type":"Services"
        }
    ],
    "sg:phone":"+1 416 783 9698",
    "sg:postcode":"M6B 3L6",
    "sg:province":"ON",
    "sg:tags":[
        "contractor",
        "dry wall",
        "general"
    ],
    "wof:name":"LA Vitesse Dry Wall & Taping",
    "wof:placetype":"venue"
},
  "geometry": {"coordinates":[-79.448547,43.712551],"type":"Point"}
}