{
  "type": "Feature",
  "properties": {
    "iso:country":"CA",
    "sg:address":"75 London Rd",
    "sg:city":"Egmondville",
    "sg:classifiers":[
        {
            "category":"Personal",
            "subcategory":"Beauty Salon",
            "type":"Services"
        }
    ],
    "sg:phone":"+1 519 522 0900",
    "sg:postcode":"N0K 1G0",
    "sg:province":"ON",
    "wof:name":"Studio 75 Hair Care",
    "wof:placetype":"venue"
},
  "geometry": {"coordinates":[-81.40570099999999,43.538879],"type":"Point"}
}