{
  "type": "Feature",
  "properties": {
    "addr:full":"2202 Harbour Rd Sidney BC V8L 2P6",
    "addr:housenumber":"2202",
    "addr:postcode":"v8l 2p6",
    "addr:street":"Harbour Rd",
    "iso:country":"CA",
    "sg:address":"2202 Harbour Rd",
    "sg:city":"Sidney",
    "sg:classifiers":[
        {
            "category":"Recreation",
            "subcategory":"Marina",
            "type":"Entertainment"
        }
    ],
    "sg:phone":"+1 250 655 4543",
    "sg:postcode":"V8L 2P6",
    "sg:province":"BC",
    "sg:tags":[
        "repair",
        "marine"
    ],
    "wof:name":"Gartside Marine Engines Ltd",
    "wof:placetype":"venue"
},
  "geometry": {"coordinates":[-123.408661,48.665241],"type":"Point"}
}