{
  "type": "Feature",
  "properties": {
    "iso:country":"CA",
    "sg:city":"Gloucester",
    "sg:classifiers":[
        {
            "category":"Wholesale",
            "subcategory":"Machinery & Supplies",
            "type":"Manufacturing & Wholesale Goods"
        }
    ],
    "sg:phone":"+1 613 745 2939",
    "sg:postcode":"K1J 9C1",
    "sg:province":"ON",
    "sg:tags":[
        "fire",
        "equipment",
        "safety",
        "clothing",
        "extinguisher"
    ],
    "wof:name":"Blr Safety & First Aid",
    "wof:placetype":"venue"
},
  "geometry": {"coordinates":[-75.5854187012,45.4533348083],"type":"Point"}
}