{
  "type": "Feature",
  "properties": {
    "addr:full":"Scarborough ON M1X 1E9",
    "addr:postcode":"m1x 1e9",
    "iso:country":"CA",
    "sg:city":"Scarborough",
    "sg:classifiers":[
        {
            "category":"Manufacturing",
            "subcategory":"Rubber & Plastics",
            "type":"Manufacturing & Wholesale Goods"
        }
    ],
    "sg:phone":"+1 416 291 3934",
    "sg:postcode":"M1X 1E9",
    "sg:province":"ON",
    "sg:tags":[
        "equipment",
        "producer",
        "laminating",
        "supply"
    ],
    "wof:name":"South Asia Import & Export Ltd",
    "wof:placetype":"venue"
},
  "geometry": {"coordinates":[-79.24434661870001,43.8283157349],"type":"Point"}
}