{
  "type": "Feature",
  "properties": {
    "iso:country":"CA",
    "sg:address":"917 Industrial Road No 1",
    "sg:city":"Cranbrook",
    "sg:classifiers":[
        {
            "category":"Freight",
            "type":"Transportation"
        }
    ],
    "sg:phone":"+1 250 426 5918",
    "sg:postcode":"V1C 4C7",
    "sg:province":"BC",
    "sg:tags":[
        "broker",
        "customs"
    ],
    "wof:name":"Federated Customs Brokers Ltd",
    "wof:placetype":"venue"
},
  "geometry": {"coordinates":[-115.76184082,49.5226211548],"type":"Point"}
}