{
  "type": "Feature",
  "properties": {
    "addr:full":"4725 50 Ave Wetaskiwin AB T9A 0R9",
    "addr:housenumber":"4725",
    "addr:postcode":"t9a 0r9",
    "addr:street":"50 Ave",
    "iso:country":"CA",
    "sg:address":"4725 50 Ave",
    "sg:city":"Wetaskiwin",
    "sg:classifiers":[
        {
            "category":"Shopping",
            "type":"Retail Goods"
        }
    ],
    "sg:phone":"+1 780 352 0004",
    "sg:postcode":"T9A 0R9",
    "sg:province":"AB",
    "sg:tags":[
        "shop",
        "bridal",
        "wedding",
        "supply"
    ],
    "wof:name":"Krystals Bridal Salon-Balloon",
    "wof:placetype":"venue"
},
  "geometry": {"coordinates":[-113.368027,52.968884],"type":"Point"}
}