{
  "type": "Feature",
  "properties": {
    "addr:full":"494 Av Saint-Jerome Matane QC G4W 3B5",
    "addr:housenumber":"494",
    "addr:postcode":"g4w 3b5",
    "addr:street":"Av Saint-Jerome",
    "iso:country":"CA",
    "sg:address":"494 Av Saint-Jerome",
    "sg:city":"Matane",
    "sg:classifiers":[
        {
            "category":"Professional",
            "subcategory":"Lawyer & Legal Services",
            "type":"Services"
        }
    ],
    "sg:phone":"+1 418 562 0088",
    "sg:postcode":"G4W 3B5",
    "sg:province":"QC",
    "sg:tags":[
        "attorney"
    ],
    "wof:name":"Ouellet, Jean-Jacque",
    "wof:placetype":"venue"
},
  "geometry": {"coordinates":[-67.529624939,48.8479194641],"type":"Point"}
}