{
  "type": "Feature",
  "properties": {
    "iso:country":"CA",
    "sg:address":"297 Rue Parent",
    "sg:city":"Saint-Jerome",
    "sg:classifiers":[
        {
            "category":"Organizations",
            "subcategory":"Professional Association",
            "type":"Services"
        }
    ],
    "sg:phone":"+1 450 436 1576",
    "sg:postcode":"J7Z 1Z8",
    "sg:province":"QC",
    "wof:name":"Locateurs Avertis 1996",
    "wof:placetype":"venue"
},
  "geometry": {"coordinates":[-74.000831604,45.7774353027],"type":"Point"}
}