{
  "type": "Feature",
  "properties": {
    "addr:full":"1491 Creek Rd Niagara on the Lake ON L0S 1J0",
    "addr:housenumber":"1491",
    "addr:postcode":"l0s 1j0",
    "addr:street":"Creek Rd;On",
    "iso:country":"CA",
    "sg:address":"1491 Creek Rd",
    "sg:city":"Niagara on the Lake",
    "sg:classifiers":[
        {
            "category":"Building & Trades",
            "subcategory":"Construction",
            "type":"Services"
        }
    ],
    "sg:phone":"+1 905 684 3458",
    "sg:postcode":"L0S 1J0",
    "sg:province":"ON",
    "sg:tags":[
        "concrete",
        "contractor"
    ],
    "wof:name":"John Froese Construction Ltd",
    "wof:placetype":"venue"
},
  "geometry": {"coordinates":[-79.0721206665,43.2553939819],"type":"Point"}
}