{
  "type": "Feature",
  "properties": {
    "addr:full":"Calgary AB T2E 0A6",
    "addr:postcode":"t2e 0a6",
    "iso:country":"CA",
    "sg:city":"Calgary",
    "sg:classifiers":[
        {
            "category":"Real Estate",
            "subcategory":"Developer",
            "type":"Services"
        }
    ],
    "sg:phone":"+1 403 273 3434",
    "sg:postcode":"T2E 0A6",
    "sg:province":"AB",
    "sg:tags":[
        "company",
        "land"
    ],
    "wof:name":"Jec Enterprises Inc",
    "wof:placetype":"venue"
},
  "geometry": {"coordinates":[-114.01185599999999,51.052605],"type":"Point"}
}