{
  "type": "Feature",
  "properties": {
    "addr:full":"242 Rue Green Saint-Lambert QC J4P 1T1",
    "addr:housenumber":"242",
    "addr:postcode":"j4p 1t1",
    "addr:street":"Rue Green",
    "iso:country":"CA",
    "sg:address":"242 Rue Green",
    "sg:city":"Saint-Lambert",
    "sg:classifiers":[
        {
            "category":"Personal",
            "subcategory":"Beauty Salon",
            "type":"Services"
        }
    ],
    "sg:phone":"+1 450 671 0424",
    "sg:postcode":"J4P 1T1",
    "sg:province":"QC",
    "wof:name":"Salon Fournier",
    "wof:placetype":"venue"
},
  "geometry": {"coordinates":[-73.509109,45.504612],"type":"Point"}
}