{
  "type": "Feature",
  "properties": {
    "addr:full":"PO Box 119 Terrenceville NL A0E 2X0",
    "addr:housenumber":"po",
    "addr:postcode":"a0e 2x0",
    "addr:street":"Box 119",
    "iso:country":"CA",
    "sg:address":"PO Box 119",
    "sg:city":"Terrenceville",
    "sg:classifiers":[
        {
            "category":"Health Services",
            "subcategory":"Doctor",
            "type":"Services"
        }
    ],
    "sg:phone":"+1 709 662 2215",
    "sg:postcode":"A0E 2X0",
    "sg:province":"NL",
    "sg:tags":[
        "clinic"
    ],
    "wof:name":"Medical Clinics",
    "wof:placetype":"venue"
},
  "geometry": {"coordinates":[-54.720627,47.662567],"type":"Point"}
}