{
  "type": "Feature",
  "properties": {
    "iso:country":"CA",
    "sg:city":"Markham",
    "sg:classifiers":[
        {
            "category":"Wholesale",
            "subcategory":"Groceries",
            "type":"Manufacturing & Wholesale Goods"
        }
    ],
    "sg:phone":"+1 905 940 0889",
    "sg:postcode":"L3R 0E7",
    "sg:province":"ON",
    "sg:tags":[
        "food",
        "product"
    ],
    "wof:name":"Tfb & Assoc Ltd",
    "wof:placetype":"venue"
},
  "geometry": {"coordinates":[-79.331398,43.837227],"type":"Point"}
}