{
  "type": "Feature",
  "properties": {
    "iso:country":"CA",
    "sg:city":"Abbotsford",
    "sg:classifiers":[
        {
            "category":"Wholesale",
            "subcategory":"Machinery & Supplies",
            "type":"Manufacturing & Wholesale Goods"
        }
    ],
    "sg:phone":"+1 604 853 3053",
    "sg:postcode":"V2S 7T9",
    "sg:province":"BC",
    "sg:tags":[
        "equipment",
        "laundry"
    ],
    "wof:name":"Nicholson Mechanical Ltd",
    "wof:placetype":"venue"
},
  "geometry": {"coordinates":[-122.288146973,49.0635414124],"type":"Point"}
}