{
  "type": "Feature",
  "properties": {
    "addr:full":"2 Hunter's Point Dr Richmond Hill ON L4C 9Y4",
    "addr:housenumber":"2",
    "addr:postcode":"l4c 9y4",
    "addr:street":"Hunter'S Point Dr",
    "iso:country":"CA",
    "sg:address":"2 Hunter's Point Dr",
    "sg:city":"Richmond Hill",
    "sg:classifiers":[
        {
            "category":"Recreation",
            "type":"Entertainment"
        }
    ],
    "sg:phone":"+1 905 882 5907",
    "sg:postcode":"L4C 9Y4",
    "sg:province":"ON",
    "sg:tags":[
        "martial",
        "arts",
        "instruction"
    ],
    "wof:name":"Centre For Martial Arts",
    "wof:placetype":"venue"
},
  "geometry": {"coordinates":[-79.3784790039,43.8465499878],"type":"Point"}
}