{
  "type": "Feature",
  "properties": {
    "addr:full":"Hope BC V0X 1L1",
    "addr:postcode":"v0x 1l1",
    "iso:country":"CA",
    "sg:city":"Hope",
    "sg:classifiers":[
        {
            "category":"Government",
            "subcategory":"Office",
            "type":"Public Place"
        }
    ],
    "sg:phone":"+1 604 869 5661",
    "sg:postcode":"V0X 1L1",
    "sg:province":"BC",
    "wof:name":"BC Health Unit",
    "wof:placetype":"venue"
},
  "geometry": {"coordinates":[-121.44009399399999,49.3819046021],"type":"Point"}
}