{
  "type": "Feature",
  "properties": {
    "iso:country":"CA",
    "sg:address":"215 1st St",
    "sg:city":"Fox Creek",
    "sg:classifiers":[
        {
            "category":"Recreation",
            "type":"Entertainment"
        }
    ],
    "sg:phone":"+1 780 622 2332",
    "sg:postcode":"T0H 1P0",
    "sg:province":"AB",
    "sg:tags":[
        "club",
        "curling"
    ],
    "wof:name":"Fox Creek Curling Club",
    "wof:placetype":"venue"
},
  "geometry": {"coordinates":[-116.801613,54.40081],"type":"Point"}
}