{
  "type": "Feature",
  "properties": {
    "addr:full":"1154 Main St Sussex Corner NB E4E 2Z7",
    "addr:housenumber":"1154",
    "addr:postcode":"e4e 2z7",
    "addr:street":"Main St",
    "iso:country":"CA",
    "sg:address":"1154 Main St",
    "sg:city":"Sussex Corner",
    "sg:classifiers":[
        {
            "category":"Retail",
            "subcategory":"Auto Rental",
            "type":"Services"
        }
    ],
    "sg:phone":"+1 506 433 3595",
    "sg:postcode":"E4E 2Z7",
    "sg:province":"NB",
    "sg:tags":[
        "renting",
        "automobile",
        "leasing",
        "truck"
    ],
    "wof:name":"Discount Car & Truck Rental",
    "wof:placetype":"venue"
},
  "geometry": {"coordinates":[-65.48276519780001,45.7118492126],"type":"Point"}
}