{
  "type": "Feature",
  "properties": {
    "iso:country":"CA",
    "sg:address":"2471 Bank St",
    "sg:city":"Ottawa",
    "sg:classifiers":[
        {
            "category":"Retail",
            "subcategory":"Auto Repair",
            "type":"Services"
        }
    ],
    "sg:phone":"+1 613 733 7341",
    "sg:postcode":"K1V 8R9",
    "sg:province":"ON",
    "sg:tags":[
        "automobile",
        "lubrication"
    ],
    "wof:name":"Oil Changers",
    "wof:placetype":"venue"
},
  "geometry": {"coordinates":[-75.6455612183,45.3539581299],"type":"Point"}
}