{
  "type": "Feature",
  "properties": {
    "addr:full":"2819 Pandora St Vancouver BC V5K 1W3",
    "addr:housenumber":"2819",
    "addr:postcode":"v5k 1w3",
    "addr:street":"Pandora St",
    "iso:country":"CA",
    "sg:address":"2819 Pandora St",
    "sg:city":"Vancouver",
    "sg:classifiers":[
        {
            "category":"Wholesale",
            "subcategory":"Seafood",
            "type":"Manufacturing & Wholesale Goods"
        }
    ],
    "sg:phone":"+1 604 251 4964",
    "sg:postcode":"V5K 1W3",
    "sg:province":"BC",
    "sg:tags":[
        "importer"
    ],
    "wof:name":"Pui Kee Trading Corp",
    "wof:placetype":"venue"
},
  "geometry": {"coordinates":[-123.045975,49.2831],"type":"Point"}
}