{
  "type": "Feature",
  "properties": {
    "addr:full":"305 Rue Lawrence Greenfield Park QC J4V 2Z5",
    "addr:housenumber":"305",
    "addr:postcode":"j4v 2z5",
    "addr:street":"Rue Lawrence",
    "iso:country":"CA",
    "sg:address":"305 Rue Lawrence",
    "sg:city":"Greenfield Park",
    "sg:classifiers":[
        {
            "category":"Retail",
            "subcategory":"Animal Services",
            "type":"Services"
        }
    ],
    "sg:phone":"+1 450 672 0358",
    "sg:postcode":"J4V 2Z5",
    "sg:province":"QC",
    "sg:tags":[
        "pet",
        "training"
    ],
    "wof:name":"Centre Canin Intl",
    "wof:placetype":"venue"
},
  "geometry": {"coordinates":[-73.467758,45.483536],"type":"Point"}
}