{
  "type": "Feature",
  "properties": {
    "addr:full":"44 Garven Hts Winnipeg MB R2C 2Z2",
    "addr:housenumber":"44",
    "addr:postcode":"r2c 2z2",
    "addr:street":"Garven Hts",
    "iso:country":"CA",
    "sg:address":"44 Garven Hts",
    "sg:city":"Winnipeg",
    "sg:classifiers":[
        {
            "category":"Building & Trades",
            "subcategory":"Plumbing",
            "type":"Services"
        }
    ],
    "sg:phone":"+1 204 222 2937",
    "sg:postcode":"R2C 2Z2",
    "sg:province":"MB",
    "sg:tags":[
        "contractor"
    ],
    "wof:name":"G & G Plumbing & Heating",
    "wof:placetype":"venue"
},
  "geometry": {"coordinates":[-97.1175918579,49.8723983765],"type":"Point"}
}