{
  "type": "Feature",
  "properties": {
    "addr:full":"4692 Mountain Hwy North Vancouver BC V7K 2K8",
    "addr:housenumber":"4692",
    "addr:postcode":"v7k 2k8",
    "addr:street":"Mountain Hwy",
    "iso:country":"CA",
    "sg:address":"4692 Mountain Hwy",
    "sg:city":"North Vancouver",
    "sg:classifiers":[
        {
            "category":"Professional",
            "subcategory":"Business Services",
            "type":"Services"
        }
    ],
    "sg:phone":"+1 604 984 2044",
    "sg:postcode":"V7K 2K8",
    "sg:province":"BC",
    "sg:tags":[
        "drafting"
    ],
    "wof:name":"Technical Services & Design",
    "wof:placetype":"venue"
},
  "geometry": {"coordinates":[-123.037315369,49.3535690308],"type":"Point"}
}