{
  "type": "Feature",
  "properties": {
    "addr:full":"395 Rue Saint-Desire Black Lake QC G6H 1M3",
    "addr:housenumber":"395",
    "addr:postcode":"g6h 1m3",
    "addr:street":"Rue Saint-Desire Black Lake",
    "iso:country":"CA",
    "sg:address":"395 Rue Saint-Desire",
    "sg:city":"Black Lake",
    "sg:classifiers":[
        {
            "category":"Personal",
            "subcategory":"Beauty Salon",
            "type":"Services"
        }
    ],
    "sg:phone":"+1 418 423 2005",
    "sg:postcode":"G6H 1M3",
    "sg:province":"QC",
    "wof:name":"Salon Fanie",
    "wof:placetype":"venue"
},
  "geometry": {"coordinates":[-71.367851,46.047699],"type":"Point"}
}