{
  "type": "Feature",
  "properties": {
    "addr:full":"200 Jones Rd Stoney Creek ON L8E 5J5",
    "addr:housenumber":"200",
    "addr:postcode":"l8e 5j5",
    "addr:street":"Jones Rd",
    "iso:country":"CA",
    "sg:address":"200 Jones Rd",
    "sg:city":"Stoney Creek",
    "sg:classifiers":[
        {
            "category":"Education",
            "subcategory":"Special Training",
            "type":"Public Place"
        }
    ],
    "sg:phone":"+1 905 643 3513",
    "sg:postcode":"L8E 5J5",
    "sg:province":"ON",
    "sg:tags":[
        "school",
        "instruction",
        "art"
    ],
    "wof:name":"Stoney Creek School of Art",
    "wof:placetype":"venue"
},
  "geometry": {"coordinates":[-79.69150500000001,43.214935],"type":"Point"}
}