{
  "type": "Feature",
  "properties": {
    "addr:full":"130 Rue Principale Saint-Camille-DE-Bellechasse QC G0R 2S0",
    "addr:housenumber":"130",
    "addr:postcode":"g0r 2s0",
    "addr:street":"Rue Principale",
    "iso:country":"CA",
    "sg:address":"130 Rue Principale",
    "sg:city":"Saint-Camille-DE-Bellechasse",
    "sg:classifiers":[
        {
            "category":"Food & Beverages",
            "subcategory":"Groceries & Convenience Stores",
            "type":"Retail Goods"
        }
    ],
    "sg:phone":"+1 418 595 2171",
    "sg:postcode":"G0R 2S0",
    "sg:province":"QC",
    "wof:name":"Accommodation Anik",
    "wof:placetype":"venue"
},
  "geometry": {"coordinates":[-70.21159400000001,46.494968],"type":"Point"}
}