{
  "type": "Feature",
  "properties": {
    "addr:full":"64 Beasley Cres Cambridge ON N1T 1K1",
    "addr:housenumber":"64",
    "addr:postcode":"n1t 1k1",
    "addr:street":"Beasley Cres",
    "iso:country":"CA",
    "sg:address":"64 Beasley Cres",
    "sg:city":"Cambridge",
    "sg:classifiers":[
        {
            "category":"Personal",
            "subcategory":"Beauty Salon",
            "type":"Services"
        }
    ],
    "sg:phone":"+1 519 624 9948",
    "sg:postcode":"N1T 1K1",
    "sg:province":"ON",
    "wof:name":"Theresa's Salon",
    "wof:placetype":"venue"
},
  "geometry": {"coordinates":[-80.295654,43.37888],"type":"Point"}
}