{
  "type": "Feature",
  "properties": {
    "addr:full":"3875 Dougall Ave Windsor ON N9G 1X3",
    "addr:housenumber":"3875",
    "addr:postcode":"n9g 1x3",
    "addr:street":"Dougall Ave",
    "iso:country":"CA",
    "sg:address":"3875 Dougall Ave",
    "sg:city":"Windsor",
    "sg:classifiers":[
        {
            "category":"Shopping",
            "subcategory":"Gifts & Souvenirs",
            "type":"Retail Goods"
        }
    ],
    "sg:phone":"+1 519 250 4182",
    "sg:postcode":"N9G 1X3",
    "sg:province":"ON",
    "sg:tags":[
        "shop",
        "announcement",
        "invitation"
    ],
    "wof:name":"R Elizabeth Fine Stationery",
    "wof:placetype":"venue"
},
  "geometry": {"coordinates":[-83.00296,42.255699],"type":"Point"}
}