{
  "type": "Feature",
  "properties": {
    "addr:full":"1815 Middleton Ave Brandon MB R7C 1A7",
    "addr:housenumber":"1815",
    "addr:postcode":"r7c 1a7",
    "addr:street":"Middleton Ave",
    "iso:country":"CA",
    "sg:address":"1815 Middleton Ave",
    "sg:city":"Brandon",
    "sg:classifiers":[
        {
            "category":"Autos & Motor Vehicles",
            "subcategory":"Fuel & Gas Station",
            "type":"Retail Goods"
        }
    ],
    "sg:phone":"+1 204 725 0246",
    "sg:postcode":"R7C 1A7",
    "sg:province":"MB",
    "sg:tags":[
        "oil"
    ],
    "wof:name":"Hi-Way Esso",
    "wof:placetype":"venue"
},
  "geometry": {"coordinates":[-99.96199,49.887291],"type":"Point"}
}