{
  "type": "Feature",
  "properties": {
    "addr:full":"17 Rang Thiercent Saint-Louis QC J0G 1K0",
    "addr:housenumber":"17",
    "addr:postcode":"j0g 1k0",
    "addr:street":"Rang Thiercent",
    "iso:country":"CA",
    "sg:address":"17 Rang Thiercent",
    "sg:city":"Saint-Louis",
    "sg:classifiers":[
        {
            "category":"Bars & Pubs",
            "type":"Food & Drink"
        }
    ],
    "sg:phone":"+1 450 788 2828",
    "sg:postcode":"J0G 1K0",
    "sg:province":"QC",
    "sg:tags":[
        "lounge",
        "cocktail"
    ],
    "wof:name":"Au Bar LA Marraine Enr",
    "wof:placetype":"venue"
},
  "geometry": {"coordinates":[-72.9826202393,45.8326644897],"type":"Point"}
}