{
  "type": "Feature",
  "properties": {
    "addr:full":"General Delivery Chance Cove NL A0B 1K0",
    "addr:postcode":"a0b 1k0",
    "iso:country":"CA",
    "sg:address":"General Delivery",
    "sg:city":"Chance Cove",
    "sg:classifiers":[
        {
            "category":"Manufacturing",
            "subcategory":"Food",
            "type":"Manufacturing & Wholesale Goods"
        }
    ],
    "sg:phone":"+1 709 460 4356",
    "sg:postcode":"A0B 1K0",
    "sg:province":"NL",
    "sg:tags":[
        "seafood",
        "product",
        "fish",
        "prepared"
    ],
    "wof:name":"Smith's Seafoods",
    "wof:placetype":"venue"
},
  "geometry": {"coordinates":[-53.80064,47.650829],"type":"Point"}
}