{
  "type": "Feature",
  "properties": {
    "addr:full":"1803 1st Ave E Vancouver BC V5N 1B2",
    "addr:housenumber":"1803",
    "addr:postcode":"v5n 1b2",
    "addr:street":"1St Ave E",
    "iso:country":"CA",
    "sg:address":"1803 1st Ave E",
    "sg:city":"Vancouver",
    "sg:classifiers":[
        {
            "category":"Organizations",
            "subcategory":"Religious Organization",
            "type":"Services"
        }
    ],
    "sg:phone":"+1 604 255 1411",
    "sg:postcode":"V5N 1B2",
    "sg:province":"BC",
    "sg:tags":[
        "church"
    ],
    "wof:name":"Grandview Calvary Baptist Chr",
    "wof:placetype":"venue"
},
  "geometry": {"coordinates":[-123.06740600000001,49.269768],"type":"Point"}
}