{
  "type": "Feature",
  "properties": {
    "addr:full":"6437 Boul Gouin O Montreal QC H4K 1A9",
    "addr:housenumber":"6437",
    "addr:postcode":"h4k 1a9",
    "addr:street":"Boul Gouin O",
    "iso:country":"CA",
    "sg:address":"6437 Boul Gouin O",
    "sg:city":"Montreal",
    "sg:classifiers":[
        {
            "category":"Retail",
            "subcategory":"Laundry & Dry Cleaning",
            "type":"Services"
        }
    ],
    "sg:phone":"+1 514 745 3758",
    "sg:postcode":"H4K 1A9",
    "sg:province":"QC",
    "sg:tags":[
        "cleaners"
    ],
    "wof:name":"Astra II",
    "wof:placetype":"venue"
},
  "geometry": {"coordinates":[-73.724564,45.52919],"type":"Point"}
}