{
  "type": "Feature",
  "properties": {
    "addr:full":"253 Rue St Georges Grand Falls NB E3Y 1C4",
    "addr:housenumber":"253",
    "addr:postcode":"e3y 1c4",
    "addr:street":"Rue St Georges",
    "iso:country":"CA",
    "sg:address":"253 Rue St Georges",
    "sg:city":"Grand Falls",
    "sg:classifiers":[
        {
            "category":"Building & Trades",
            "subcategory":"Plumbing",
            "type":"Services"
        }
    ],
    "sg:phone":"+1 506 473 3293",
    "sg:postcode":"E3Y 1C4",
    "sg:province":"NB",
    "sg:tags":[
        "contractor"
    ],
    "wof:name":"Victor Ouellette Plumbing",
    "wof:placetype":"venue"
},
  "geometry": {"coordinates":[-67.73407745359999,47.052986145],"type":"Point"}
}