{
  "type": "Feature",
  "properties": {
    "addr:full":"85 Rue Prince Chateauguay QC J6K 3Z9",
    "addr:housenumber":"85",
    "addr:postcode":"j6k 3z9",
    "addr:street":"Rue Prince",
    "iso:country":"CA",
    "sg:address":"85 Rue Prince",
    "sg:city":"Chateauguay",
    "sg:classifiers":[
        {
            "category":"Education",
            "subcategory":"School",
            "type":"Public Place"
        }
    ],
    "sg:phone":"+1 450 698 5050",
    "sg:postcode":"J6K 3Z9",
    "sg:province":"QC",
    "wof:name":"Ecole Des Trois-Sources",
    "wof:placetype":"venue"
},
  "geometry": {"coordinates":[-73.730377,45.356052],"type":"Point"}
}