{
  "type": "Feature",
  "properties": {
    "iso:country":"CA",
    "sg:address":"878 Boul Maloney E",
    "sg:city":"Gatineau",
    "sg:classifiers":[
        {
            "category":"Home & Garden",
            "subcategory":"Hardware",
            "type":"Retail Goods"
        }
    ],
    "sg:phone":"+1 819 643 5331",
    "sg:postcode":"J8P 1H1",
    "sg:province":"QC",
    "wof:name":"Quincaillerie Des Boulevards",
    "wof:placetype":"venue"
},
  "geometry": {"coordinates":[-75.6033859253,45.4868392944],"type":"Point"}
}