{
  "type": "Feature",
  "properties": {
    "addr:full":"2206 22 Ave Coaldale AB T1M 1H7",
    "addr:housenumber":"2206",
    "addr:postcode":"t1m 1h7",
    "addr:street":"22 Ave",
    "iso:country":"CA",
    "sg:address":"2206 22 Ave",
    "sg:city":"Coaldale",
    "sg:classifiers":[
        {
            "category":"Freight",
            "type":"Transportation"
        }
    ],
    "sg:phone":"+1 403 345 7788",
    "sg:postcode":"T1M 1H7",
    "sg:province":"AB",
    "sg:tags":[
        "consultant"
    ],
    "wof:name":"Auto Drive Svc Consultants",
    "wof:placetype":"venue"
},
  "geometry": {"coordinates":[-112.628891,49.723282],"type":"Point"}
}