{
  "type": "Feature",
  "properties": {
    "addr:full":"45 West Side Dr Bowmanville ON L1C 4Y8",
    "addr:housenumber":"45",
    "addr:postcode":"l1c 4y8",
    "addr:street":"West Side Dr",
    "iso:country":"CA",
    "sg:address":"45 West Side Dr",
    "sg:city":"Bowmanville",
    "sg:classifiers":[
        {
            "category":"Education",
            "subcategory":"School",
            "type":"Public Place"
        }
    ],
    "sg:phone":"+1 905 623 3841",
    "sg:postcode":"L1C 4Y8",
    "sg:province":"ON",
    "wof:name":"Dr Ross Tilley Public School",
    "wof:placetype":"venue"
},
  "geometry": {"coordinates":[-78.7015304565,43.8982620239],"type":"Point"}
}