{
  "type": "Feature",
  "properties": {
    "addr:full":"380 Rue Pineault Mont-Saint-Hilaire QC J3H 3S4",
    "addr:housenumber":"380",
    "addr:postcode":"j3h 3s4",
    "addr:street":"Rue Pineault",
    "iso:country":"CA",
    "sg:address":"380 Rue Pineault",
    "sg:city":"Mont-Saint-Hilaire",
    "sg:classifiers":[
        {
            "category":"Banks & Credit Unions",
            "subcategory":"Investment Brokerage",
            "type":"Services"
        }
    ],
    "sg:phone":"+1 450 446 4822",
    "sg:postcode":"J3H 3S4",
    "sg:province":"QC",
    "sg:tags":[
        "consultant",
        "planning",
        "financial"
    ],
    "wof:name":"L'Optimum Planificateur",
    "wof:placetype":"venue"
},
  "geometry": {"coordinates":[-73.1849365234,45.5597953796],"type":"Point"}
}