{
  "type": "Feature",
  "properties": {
    "iso:country":"CA",
    "sg:city":"Bashaw",
    "sg:classifiers":[
        {
            "category":"Restaurant",
            "type":"Food & Drink"
        }
    ],
    "sg:phone":"+1 780 372 3777",
    "sg:postcode":"T0B 0H0",
    "sg:province":"AB",
    "wof:name":"Gollys",
    "wof:placetype":"venue"
},
  "geometry": {"coordinates":[-112.972290039,52.5830116272],"type":"Point"}
}