{
  "type": "Feature",
  "properties": {
    "addr:full":"102 Elora St Mildmay ON N0G 2J0",
    "addr:housenumber":"102",
    "addr:postcode":"n0g 2j0",
    "addr:street":"Elora St",
    "iso:country":"CA",
    "sg:address":"102 Elora St",
    "sg:city":"Mildmay",
    "sg:classifiers":[
        {
            "category":"Shopping",
            "subcategory":"Jewelry",
            "type":"Retail Goods"
        }
    ],
    "sg:phone":"+1 519 367 5357",
    "sg:postcode":"N0G 2J0",
    "sg:province":"ON",
    "sg:tags":[
        "jeweler"
    ],
    "wof:name":"Wendt's Jewellery Ltd",
    "wof:placetype":"venue"
},
  "geometry": {"coordinates":[-81.11925506590001,44.042640686],"type":"Point"}
}