{
  "type": "Feature",
  "properties": {
    "addr:full":"Edmonton AB T6A 0T7",
    "addr:postcode":"t6a 0t7",
    "iso:country":"CA",
    "sg:city":"Edmonton",
    "sg:classifiers":[
        {
            "category":"Education",
            "subcategory":"College",
            "type":"Public Place"
        }
    ],
    "sg:phone":"+1 780 988 8774",
    "sg:postcode":"T6A 0T7",
    "sg:province":"AB",
    "sg:tags":[
        "academic",
        "training",
        "computer"
    ],
    "wof:name":"Academy of Learning Strathcona",
    "wof:placetype":"venue"
},
  "geometry": {"coordinates":[-113.430030823,53.545085907],"type":"Point"}
}