{
  "type": "Feature",
  "properties": {
    "addr:full":"Vancouver BC V7Y 1E7",
    "addr:postcode":"v7y 1e7",
    "iso:country":"CA",
    "sg:city":"Vancouver",
    "sg:classifiers":[
        {
            "category":"Restaurant",
            "type":"Food & Drink"
        }
    ],
    "sg:phone":"+1 604 682 8016",
    "sg:postcode":"V7Y 1E7",
    "sg:province":"BC",
    "wof:name":"Vina Vietnamese Gourmet",
    "wof:placetype":"venue"
},
  "geometry": {"coordinates":[-123.116920471,49.2842025757],"type":"Point"}
}