{
  "type": "Feature",
  "properties": {
    "addr:full":"450 Albert St W Sault Ste Marie ON P6A 1C3",
    "addr:housenumber":"450",
    "addr:postcode":"p6a 1c3",
    "addr:street":"Albert St W",
    "iso:country":"CA",
    "sg:address":"450 Albert St W",
    "sg:city":"Sault Ste Marie",
    "sg:classifiers":[
        {
            "category":"Restaurant",
            "type":"Food & Drink"
        }
    ],
    "sg:phone":"+1 705 942 5556",
    "sg:postcode":"P6A 1C3",
    "sg:province":"ON",
    "sg:tags":[
        "banquet",
        "rooms"
    ],
    "wof:name":"Marconi Club",
    "wof:placetype":"venue"
},
  "geometry": {"coordinates":[-84.351631,46.520222],"type":"Point"}
}