{
  "type": "Feature",
  "properties": {
    "iso:country":"CA",
    "sg:address":"1020 St Laurent Blvd # 10",
    "sg:city":"Ottawa",
    "sg:classifiers":[
        {
            "category":"Food & Beverages",
            "subcategory":"Groceries & Convenience Stores",
            "type":"Retail Goods"
        }
    ],
    "sg:phone":"+1 613 742 4282",
    "sg:postcode":"K1K 4S2",
    "sg:province":"ON",
    "sg:tags":[
        "grocer"
    ],
    "wof:name":"Geeland",
    "wof:placetype":"venue"
},
  "geometry": {"coordinates":[-75.639839,45.428169],"type":"Point"}
}