{
  "type": "Feature",
  "properties": {
    "addr:full":"6655 178 St NW # 242 Edmonton AB T5T 4J5",
    "addr:housenumber":"6655",
    "addr:postcode":"t5t 4j5",
    "addr:street":"178 St Nw # 242",
    "iso:country":"CA",
    "sg:address":"6655 178 St NW # 242",
    "sg:city":"Edmonton",
    "sg:classifiers":[
        {
            "category":"Restaurant",
            "type":"Food & Drink"
        }
    ],
    "sg:phone":"+1 780 443 1336",
    "sg:postcode":"T5T 4J5",
    "sg:province":"AB",
    "wof:name":"Quizno's Subs",
    "wof:placetype":"venue"
},
  "geometry": {"coordinates":[-113.630409,53.501053],"type":"Point"}
}