{
  "type": "Feature",
  "properties": {
    "addr:full":"6 Wilson St E Perth ON K7H 1L2",
    "addr:housenumber":"6",
    "addr:postcode":"k7h 1l2",
    "addr:street":"Wilson St E",
    "iso:country":"CA",
    "sg:address":"6 Wilson St E",
    "sg:city":"Perth",
    "sg:classifiers":[
        {
            "category":"Health Services",
            "subcategory":"Doctor",
            "type":"Services"
        }
    ],
    "sg:phone":"+1 613 267 1402",
    "sg:postcode":"K7H 1L2",
    "sg:province":"ON",
    "sg:tags":[
        "physician",
        "surgeon"
    ],
    "wof:name":"Zabel, Ralph MD",
    "wof:placetype":"venue"
},
  "geometry": {"coordinates":[-76.25234985349999,44.9000358582],"type":"Point"}
}