{
  "type": "Feature",
  "properties": {
    "addr:full":"839 5th Ave NE Swift Current SK S9H 2L5",
    "addr:housenumber":"839",
    "addr:postcode":"s9h 2l5",
    "addr:street":"5Th Ave Ne",
    "iso:country":"CA",
    "sg:address":"839 5th Ave NE",
    "sg:city":"Swift Current",
    "sg:classifiers":[
        {
            "category":"Mining & Drilling",
            "type":"Manufacturing & Wholesale Goods"
        }
    ],
    "sg:phone":"+1 306 778 6252",
    "sg:postcode":"S9H 2L5",
    "sg:province":"SK",
    "sg:tags":[
        "oil",
        "well"
    ],
    "wof:name":"Abbey Holdings Ltd",
    "wof:placetype":"venue"
},
  "geometry": {"coordinates":[-107.793556,50.294495],"type":"Point"}
}