{
  "type": "Feature",
  "properties": {
    "iso:country":"CA",
    "sg:address":"555 Rue Lessard",
    "sg:city":"Sherbrooke",
    "sg:classifiers":[
        {
            "category":"Wholesale",
            "subcategory":"Chemicals & Plastics",
            "type":"Manufacturing & Wholesale Goods"
        }
    ],
    "sg:phone":"+1 819 562 5189",
    "sg:postcode":"J1E 2R4",
    "sg:province":"QC",
    "sg:tags":[
        "tile",
        "floor",
        "treatment",
        "compound"
    ],
    "wof:name":"Antiderapant DE L'Estrie",
    "wof:placetype":"venue"
},
  "geometry": {"coordinates":[-71.876022,45.416798],"type":"Point"}
}