{
  "type": "Feature",
  "properties": {
    "addr:full":"82 Boul Antonio-Barrette Notre-Dame-Des-Prairies QC J6E 1E4",
    "addr:housenumber":"82",
    "addr:postcode":"j6e 1e4",
    "addr:street":"Boul Antonio-Barrette",
    "iso:country":"CA",
    "sg:address":"82 Boul Antonio-Barrette",
    "sg:city":"Notre-Dame-Des-Prairies",
    "sg:classifiers":[
        {
            "category":"Building & Trades",
            "subcategory":"Construction",
            "type":"Services"
        }
    ],
    "sg:phone":"+1 450 759 6098",
    "sg:postcode":"J6E 1E4",
    "sg:province":"QC",
    "sg:tags":[
        "product",
        "asphalt"
    ],
    "wof:name":"Pros Lm Enr",
    "wof:placetype":"venue"
},
  "geometry": {"coordinates":[-73.436874,46.041443],"type":"Point"}
}