{
  "type": "Feature",
  "properties": {
    "iso:country":"CA",
    "sg:address":"470 Av Michel-Jasmin",
    "sg:city":"Dorval",
    "sg:classifiers":[
        {
            "category":"Professional",
            "type":"Services"
        }
    ],
    "sg:phone":"+1 514 633 4456",
    "sg:postcode":"H9P 1C3",
    "sg:province":"QC",
    "sg:tags":[
        "automobile",
        "parts",
        "establishment"
    ],
    "wof:name":"Dpt Rebuilders",
    "wof:placetype":"venue"
},
  "geometry": {"coordinates":[-73.735298,45.453274],"type":"Point"}
}