{
  "type": "Feature",
  "properties": {
    "addr:full":"Scarborough ON M1W 2S8",
    "addr:postcode":"m1w 2s8",
    "iso:country":"CA",
    "sg:city":"Scarborough",
    "sg:classifiers":[
        {
            "category":"Shopping",
            "subcategory":"Jewelry",
            "type":"Retail Goods"
        }
    ],
    "sg:phone":"+1 416 492 4486",
    "sg:postcode":"M1W 2S8",
    "sg:province":"ON",
    "sg:tags":[
        "jeweler"
    ],
    "wof:name":"Arain Jewellers",
    "wof:placetype":"venue"
},
  "geometry": {"coordinates":[-79.31596399999999,43.796898],"type":"Point"}
}