{
  "type": "Feature",
  "properties": {
    "addr:full":"434 Horner Ave Etobicoke ON M8W 2B3",
    "addr:housenumber":"434",
    "addr:postcode":"m8w 2b3",
    "addr:street":"Horner Ave",
    "iso:country":"CA",
    "sg:address":"434 Horner Ave",
    "sg:city":"Etobicoke",
    "sg:classifiers":[
        {
            "category":"Food & Beverages",
            "subcategory":"Groceries & Convenience Stores",
            "type":"Retail Goods"
        }
    ],
    "sg:phone":"+1 416 259 3005",
    "sg:postcode":"M8W 2B3",
    "sg:province":"ON",
    "wof:name":"Horner Mini Mart",
    "wof:placetype":"venue"
},
  "geometry": {"coordinates":[-79.538772583,43.6032676697],"type":"Point"}
}