{
  "type": "Feature",
  "properties": {
    "addr:full":"3775 Rue Sullivan Saint-Hubert QC J3Y 6L8",
    "addr:housenumber":"3775",
    "addr:postcode":"j3y 6l8",
    "addr:street":"Rue Sullivan",
    "iso:country":"CA",
    "sg:address":"3775 Rue Sullivan",
    "sg:city":"Saint-Hubert",
    "sg:classifiers":[
        {
            "category":"Professional",
            "subcategory":"Management & Consulting",
            "type":"Services"
        }
    ],
    "sg:phone":"+1 450 443 0006",
    "sg:postcode":"J3Y 6L8",
    "sg:province":"QC",
    "sg:tags":[
        "consultant",
        "resource",
        "human"
    ],
    "wof:name":"Convergence Rh Inc",
    "wof:placetype":"venue"
},
  "geometry": {"coordinates":[-73.41770935060001,45.4870986938],"type":"Point"}
}