{
  "type": "Feature",
  "properties": {
    "iso:country":"CA",
    "sg:city":"Richmond",
    "sg:classifiers":[
        {
            "category":"Building & Trades",
            "subcategory":"Construction",
            "type":"Services"
        }
    ],
    "sg:phone":"+1 604 276 0085",
    "sg:postcode":"V6V 1Y3",
    "sg:province":"BC",
    "sg:tags":[
        "painter"
    ],
    "wof:name":"City Wide Painters Ltd",
    "wof:placetype":"venue"
},
  "geometry": {"coordinates":[-123.06201934800001,49.2025680542],"type":"Point"}
}