{
  "type": "Feature",
  "properties": {
    "addr:full":"22 Wesley St Fillmore SK S0G 1N0",
    "addr:housenumber":"22",
    "addr:postcode":"s0g 1n0",
    "addr:street":"Wesley St",
    "iso:country":"CA",
    "sg:address":"22 Wesley St",
    "sg:city":"Fillmore",
    "sg:classifiers":[
        {
            "category":"Recreation",
            "type":"Entertainment"
        }
    ],
    "sg:phone":"+1 306 722 3833",
    "sg:postcode":"S0G 1N0",
    "sg:province":"SK",
    "sg:tags":[
        "hall",
        "auditorium"
    ],
    "wof:name":"Fillmore Community Memorial",
    "wof:placetype":"venue"
},
  "geometry": {"coordinates":[-103.43206000000001,49.882423],"type":"Point"}
}