{
  "type": "Feature",
  "properties": {
    "addr:full":"49 Kruger Rd Markham ON L3S 3Y8",
    "addr:housenumber":"49",
    "addr:postcode":"l3s 3y8",
    "addr:street":"Kruger Rd",
    "iso:country":"CA",
    "sg:address":"49 Kruger Rd",
    "sg:city":"Markham",
    "sg:classifiers":[
        {
            "category":"Building & Trades",
            "subcategory":"Cleaning & Sanitation",
            "type":"Services"
        }
    ],
    "sg:phone":"+1 905 472 2659",
    "sg:postcode":"L3S 3Y8",
    "sg:province":"ON",
    "sg:tags":[
        "janitor"
    ],
    "wof:name":"Seth Enterprises",
    "wof:placetype":"venue"
},
  "geometry": {"coordinates":[-79.261627,43.846786],"type":"Point"}
}