{
  "type": "Feature",
  "properties": {
    "addr:full":"Calgary AB T2M 1H5",
    "addr:postcode":"t2m 1h5",
    "iso:country":"CA",
    "sg:city":"Calgary",
    "sg:classifiers":[
        {
            "category":"Health Services",
            "subcategory":"Doctor",
            "type":"Services"
        }
    ],
    "sg:phone":"+1 403 284 9390",
    "sg:postcode":"T2M 1H5",
    "sg:province":"AB",
    "sg:tags":[
        "dentist"
    ],
    "wof:name":"Sabey, Craig DDS",
    "wof:placetype":"venue"
},
  "geometry": {"coordinates":[-114.105178833,51.0706939697],"type":"Point"}
}