{
  "type": "Feature",
  "properties": {
    "addr:full":"1994 Comox Ave Comox BC V9M 3M7",
    "addr:housenumber":"1994",
    "addr:postcode":"v9m 3m7",
    "addr:street":"Comox Ave",
    "iso:country":"CA",
    "sg:address":"1994 Comox Ave",
    "sg:city":"Comox",
    "sg:classifiers":[
        {
            "category":"Insurance",
            "subcategory":"Insurance Agent",
            "type":"Services"
        }
    ],
    "sg:phone":"+1 250 890 7580",
    "sg:postcode":"V9M 3M7",
    "sg:province":"BC",
    "wof:name":"Glacierview Financial Svc Ltd",
    "wof:placetype":"venue"
},
  "geometry": {"coordinates":[-124.93441799999999,49.675812],"type":"Point"}
}