{
  "type": "Feature",
  "properties": {
    "iso:country":"CA",
    "sg:address":"65 Brunswick St",
    "sg:city":"Fredericton",
    "sg:classifiers":[
        {
            "category":"Social Services",
            "type":"Services"
        }
    ],
    "sg:phone":"+1 506 457 1788",
    "sg:postcode":"E3B 1G5",
    "sg:province":"NB",
    "sg:tags":[
        "organization",
        "welfare"
    ],
    "wof:name":"Fredericton Community Kitchen",
    "wof:placetype":"venue"
},
  "geometry": {"coordinates":[-66.65180969239999,45.9642868042],"type":"Point"}
}