{
  "type": "Feature",
  "properties": {
    "addr:full":"8500 Ch Bourgeois Mirabel QC J7N 2K1",
    "addr:postcode":"8500;j7n 2k1",
    "addr:street":"Ch Bourgeois",
    "iso:country":"CA",
    "sg:address":"8500 Ch Bourgeois",
    "sg:city":"Mirabel",
    "sg:classifiers":[
        {
            "category":"Building & Trades",
            "subcategory":"Landscaping Services",
            "type":"Services"
        }
    ],
    "sg:phone":"+1 450 475 7725",
    "sg:postcode":"J7N 2K1",
    "sg:province":"QC",
    "sg:tags":[
        "topsoil"
    ],
    "wof:name":"Terres Noires G Belanger Inc",
    "wof:placetype":"venue"
},
  "geometry": {"coordinates":[-73.940826,45.631332],"type":"Point"}
}