{
  "type": "Feature",
  "properties": {
    "addr:full":"4829 Rue Wellington Verdun QC H4G 1X5",
    "addr:housenumber":"4829",
    "addr:postcode":"h4g 1x5",
    "addr:street":"Rue Wellington",
    "iso:country":"CA",
    "sg:address":"4829 Rue Wellington",
    "sg:city":"Verdun",
    "sg:classifiers":[
        {
            "category":"Shopping",
            "subcategory":"Shoes",
            "type":"Retail Goods"
        }
    ],
    "sg:phone":"+1 514 762 0139",
    "sg:postcode":"H4G 1X5",
    "sg:province":"QC",
    "wof:name":"Chaussures Super-Prix",
    "wof:placetype":"venue"
},
  "geometry": {"coordinates":[-73.567757,45.457085],"type":"Point"}
}