{
  "type": "Feature",
  "properties": {
    "addr:full":"1530 Midland Ave Scarborough ON M1P 3C2",
    "addr:housenumber":"1530",
    "addr:postcode":"m1p 3c2",
    "addr:street":"Midland Ave",
    "iso:country":"CA",
    "sg:address":"1530 Midland Ave",
    "sg:city":"Scarborough",
    "sg:classifiers":[
        {
            "category":"Home & Garden",
            "subcategory":"Building Materials",
            "type":"Retail Goods"
        }
    ],
    "sg:phone":"+1 416 285 8468",
    "sg:postcode":"M1P 3C2",
    "sg:province":"ON",
    "sg:tags":[
        "plate",
        "window",
        "coating",
        "tinting",
        "glass"
    ],
    "wof:name":"Tint King Autoworld Downtown",
    "wof:placetype":"venue"
},
  "geometry": {"coordinates":[-79.26615099999999,43.754105],"type":"Point"}
}