{
  "type": "Feature",
  "properties": {
    "addr:full":"760 Route 705 Wickham NB E5T 3R7",
    "addr:housenumber":"760",
    "addr:postcode":"e5t 3r7",
    "addr:street":"Route 705",
    "iso:country":"CA",
    "sg:address":"760 Route 705",
    "sg:city":"Wickham",
    "sg:classifiers":[
        {
            "category":"Building & Trades",
            "subcategory":"Construction",
            "type":"Services"
        }
    ],
    "sg:phone":"+1 506 485 5661",
    "sg:postcode":"E5T 3R7",
    "sg:province":"NB",
    "sg:tags":[
        "general",
        "contractor"
    ],
    "wof:name":"L & R Construction",
    "wof:placetype":"venue"
},
  "geometry": {"coordinates":[-66.058487,45.616531],"type":"Point"}
}