{
  "type": "Feature",
  "properties": {
    "addr:full":"Whycocomagh NS B0E 3M0",
    "addr:postcode":"b0e 3m0",
    "iso:country":"CA",
    "sg:city":"Whycocomagh",
    "sg:classifiers":[
        {
            "category":"Freight",
            "type":"Transportation"
        }
    ],
    "sg:phone":"+1 902 756 2050",
    "sg:postcode":"B0E 3M0",
    "sg:province":"NS",
    "sg:tags":[
        "trucking"
    ],
    "wof:name":"J P Mac Innis Trucking Ltd",
    "wof:placetype":"venue"
},
  "geometry": {"coordinates":[-61.1254920959,45.9750289917],"type":"Point"}
}