{
  "type": "Feature",
  "properties": {
    "addr:full":"2476 Shannon View Dr Westbank BC V4T 2T3",
    "addr:housenumber":"2476",
    "addr:postcode":"v4t 2t3",
    "addr:street":"Shannon View Dr",
    "iso:country":"CA",
    "sg:address":"2476 Shannon View Dr",
    "sg:city":"Westbank",
    "sg:classifiers":[
        {
            "category":"Building & Trades",
            "subcategory":"Construction",
            "type":"Services"
        }
    ],
    "sg:phone":"+1 250 707 0921",
    "sg:postcode":"V4T 2T3",
    "sg:province":"BC",
    "sg:tags":[
        "roofing",
        "contractor"
    ],
    "wof:name":"Wynn's Roofing",
    "wof:placetype":"venue"
},
  "geometry": {"coordinates":[-119.60346984900001,49.8658599854],"type":"Point"}
}