{
  "type": "Feature",
  "properties": {
    "addr:full":"Miscouche PE C0B 1T0",
    "addr:postcode":"c0b 1t0",
    "iso:country":"CA",
    "sg:city":"Miscouche",
    "sg:classifiers":[
        {
            "category":"Organizations",
            "subcategory":"Religious Organization",
            "type":"Services"
        }
    ],
    "sg:phone":"+1 902 436 3271",
    "sg:postcode":"C0B 1T0",
    "sg:province":"PE",
    "sg:tags":[
        "church"
    ],
    "wof:name":"St John the Baptist Parish",
    "wof:placetype":"venue"
},
  "geometry": {"coordinates":[-63.8620681763,46.4314651489],"type":"Point"}
}