{
  "type": "Feature",
  "properties": {
    "addr:full":"Calgary AB T2K 1A3",
    "addr:postcode":"t2k 1a3",
    "iso:country":"CA",
    "sg:city":"Calgary",
    "sg:classifiers":[
        {
            "category":"Restaurant",
            "type":"Food & Drink"
        }
    ],
    "sg:phone":"+1 403 284 4504",
    "sg:postcode":"T2K 1A3",
    "sg:province":"AB",
    "wof:name":"Stavro's Pizza & Sports Bar",
    "wof:placetype":"venue"
},
  "geometry": {"coordinates":[-114.071747,51.087742],"type":"Point"}
}