{
  "type": "Feature",
  "properties": {
    "addr:full":"Owen Sound ON N4K 3R3",
    "addr:postcode":"n4k 3r3",
    "iso:country":"CA",
    "sg:city":"Owen Sound",
    "sg:classifiers":[
        {
            "category":"Professional",
            "subcategory":"Engineering",
            "type":"Services"
        }
    ],
    "sg:phone":"+1 519 376 6281",
    "sg:postcode":"N4K 3R3",
    "sg:province":"ON",
    "sg:tags":[
        "engineer"
    ],
    "wof:name":"Craig Johnston Design Conslnt",
    "wof:placetype":"venue"
},
  "geometry": {"coordinates":[-80.94663238530001,44.5674705505],"type":"Point"}
}