{
  "type": "Feature",
  "properties": {
    "addr:full":"22386 119 Ave Maple Ridge BC V2X 2Z3",
    "addr:housenumber":"22386",
    "addr:postcode":"v2x 2z3",
    "addr:street":"119 Ave",
    "iso:country":"CA",
    "sg:address":"22386 119 Ave",
    "sg:city":"Maple Ridge",
    "sg:classifiers":[
        {
            "category":"Professional",
            "subcategory":"Accounting & Tax Preparation",
            "type":"Services"
        }
    ],
    "sg:phone":"+1 604 463 6171",
    "sg:postcode":"V2X 2Z3",
    "sg:province":"BC",
    "sg:tags":[
        "accountant",
        "bookkeeping",
        "general"
    ],
    "wof:name":"J & K Schafer & CO",
    "wof:placetype":"venue"
},
  "geometry": {"coordinates":[-122.602294922,49.2184066772],"type":"Point"}
}