{
  "type": "Feature",
  "properties": {
    "addr:full":"444 Rue Cantin # 112 Victoriaville QC G6P 7E6",
    "addr:housenumber":"444",
    "addr:postcode":"g6p 7e6",
    "addr:street":"Rue Cantin # 112",
    "iso:country":"CA",
    "sg:address":"444 Rue Cantin # 112",
    "sg:city":"Victoriaville",
    "sg:classifiers":[
        {
            "category":"Professional",
            "subcategory":"Management & Consulting",
            "type":"Services"
        }
    ],
    "sg:phone":"+1 819 758 8461",
    "sg:postcode":"G6P 7E6",
    "sg:province":"QC",
    "sg:tags":[
        "break",
        "tea",
        "coffee",
        "supply"
    ],
    "wof:name":"Cafe Vhm Enr",
    "wof:placetype":"venue"
},
  "geometry": {"coordinates":[-71.96434783940001,46.0687713623],"type":"Point"}
}