{
  "type": "Feature",
  "properties": {
    "iso:country":"CA",
    "sg:address":"165 Maghill St",
    "sg:city":"Lively",
    "sg:classifiers":[
        {
            "category":"Manufacturing",
            "subcategory":"Metals",
            "type":"Manufacturing & Wholesale Goods"
        }
    ],
    "sg:phone":"+1 705 692 0303",
    "sg:postcode":"P3Y 1K6",
    "sg:province":"ON",
    "sg:tags":[
        "fabricator",
        "aluminum"
    ],
    "wof:name":"Stainless Steel Technology",
    "wof:placetype":"venue"
},
  "geometry": {"coordinates":[-81.12037658689999,46.4385566711],"type":"Point"}
}