{
  "type": "Feature",
  "properties": {
    "addr:full":"560 Boul Charest E Quebec QC G1K 3J3",
    "addr:housenumber":"560",
    "addr:postcode":"g1k 3j3",
    "addr:street":"Boul Charest E",
    "iso:country":"CA",
    "sg:address":"560 Boul Charest E",
    "sg:city":"Quebec",
    "sg:classifiers":[
        {
            "category":"Government",
            "subcategory":"Office",
            "type":"Public Place"
        }
    ],
    "sg:phone":"+1 418 643 7667",
    "sg:postcode":"G1K 3J3",
    "sg:province":"QC",
    "wof:name":"Quebec Regie Des Permis Alcool",
    "wof:placetype":"venue"
},
  "geometry": {"coordinates":[-71.22217559809999,46.8143768311],"type":"Point"}
}