{
  "type": "Feature",
  "properties": {
    "addr:full":"1002 Route 530 Grande-Digue NB E4R 5K8",
    "addr:housenumber":"1002",
    "addr:postcode":"e4r 5k8",
    "addr:street":"Route 530",
    "iso:country":"CA",
    "sg:address":"1002 Route 530",
    "sg:city":"Grande-Digue",
    "sg:classifiers":[
        {
            "category":"Food & Beverages",
            "subcategory":"Meat & Fish",
            "type":"Retail Goods"
        }
    ],
    "sg:phone":"+1 506 576 1813",
    "sg:postcode":"E4R 5K8",
    "sg:province":"NB",
    "sg:tags":[
        "seafood"
    ],
    "wof:name":"Maurice Caissie Seafood",
    "wof:placetype":"venue"
},
  "geometry": {"coordinates":[-64.53061676030001,46.310710907],"type":"Point"}
}