{
  "type": "Feature",
  "properties": {
    "iso:country":"CA",
    "sg:address":"1645 Sydenham Rd",
    "sg:city":"Kingston",
    "sg:classifiers":[
        {
            "category":"Manufacturing",
            "subcategory":"Metals",
            "type":"Manufacturing & Wholesale Goods"
        }
    ],
    "sg:phone":"+1 613 546 6683",
    "sg:postcode":"K7L 4V4",
    "sg:province":"ON",
    "sg:tags":[
        "concrete",
        "product"
    ],
    "wof:name":"Anchor Concrete Products Ltd",
    "wof:placetype":"venue"
},
  "geometry": {"coordinates":[-76.53997039790001,44.2912788391],"type":"Point"}
}