{
  "type": "Feature",
  "properties": {
    "addr:full":"1249 River Rd Manotick ON K4M 1B4",
    "addr:housenumber":"1249",
    "addr:postcode":"k4m 1b4",
    "addr:street":"River Rd",
    "iso:country":"CA",
    "sg:address":"1249 River Rd",
    "sg:city":"Manotick",
    "sg:classifiers":[
        {
            "category":"Building & Trades",
            "subcategory":"Construction",
            "type":"Services"
        }
    ],
    "sg:phone":"+1 613 692 3979",
    "sg:postcode":"K4M 1B4",
    "sg:province":"ON",
    "sg:tags":[
        "concrete",
        "contractor"
    ],
    "wof:name":"Manotick Concrete Ltd",
    "wof:placetype":"venue"
},
  "geometry": {"coordinates":[-75.66748809809999,45.2253990173],"type":"Point"}
}