{
  "type": "Feature",
  "properties": {
    "addr:full":"1250 Chatsworth Rd Qualicum Beach BC V9K 1V6",
    "addr:housenumber":"1250",
    "addr:postcode":"v9k 1v6",
    "addr:street":"Chatsworth Rd",
    "iso:country":"CA",
    "sg:address":"1250 Chatsworth Rd",
    "sg:city":"Qualicum Beach",
    "sg:classifiers":[
        {
            "category":"Building & Trades",
            "subcategory":"Landscaping Services",
            "type":"Services"
        }
    ],
    "sg:phone":"+1 250 248 8140",
    "sg:postcode":"V9K 1V6",
    "sg:province":"BC",
    "sg:tags":[
        "landscape",
        "contractor"
    ],
    "wof:name":"R & D Enterprises",
    "wof:placetype":"venue"
},
  "geometry": {"coordinates":[-124.441703796,49.3467063904],"type":"Point"}
}