{
  "type": "Feature",
  "properties": {
    "iso:country":"CA",
    "sg:address":"6100 Boul DE LA Rive-Sud",
    "sg:city":"Levis",
    "sg:classifiers":[
        {
            "category":"Recreation",
            "type":"Entertainment"
        }
    ],
    "sg:phone":"+1 418 837 3618",
    "sg:postcode":"G6V 8Z7",
    "sg:province":"QC",
    "sg:tags":[
        "course",
        "golf"
    ],
    "wof:name":"Club DE Golf Levis Inc",
    "wof:placetype":"venue"
},
  "geometry": {"coordinates":[-71.16985321040001,46.8003158569],"type":"Point"}
}