{
  "type": "Feature",
  "properties": {
    "addr:full":"29 Plains Rd W Burlington ON L7T 1E8",
    "addr:housenumber":"29",
    "addr:postcode":"l7t 1e8",
    "addr:street":"Plains Rd W",
    "iso:country":"CA",
    "sg:address":"29 Plains Rd W",
    "sg:city":"Burlington",
    "sg:classifiers":[
        {
            "category":"Home & Garden",
            "subcategory":"Furniture",
            "type":"Retail Goods"
        }
    ],
    "sg:phone":"+1 905 681 3355",
    "sg:postcode":"L7T 1E8",
    "sg:province":"ON",
    "wof:name":"Hauser CO Stores",
    "wof:placetype":"venue"
},
  "geometry": {"coordinates":[-79.8539810181,43.3059463501],"type":"Point"}
}