{
  "type": "Feature",
  "properties": {
    "addr:full":"Richmond Hill ON L4B 1M5",
    "addr:postcode":"l4b 1m5",
    "iso:country":"CA",
    "sg:city":"Richmond Hill",
    "sg:classifiers":[
        {
            "category":"Manufacturing",
            "subcategory":"Printing",
            "type":"Manufacturing & Wholesale Goods"
        }
    ],
    "sg:phone":"+1 905 709 1310",
    "sg:postcode":"L4B 1M5",
    "sg:province":"ON",
    "sg:tags":[
        "printer"
    ],
    "wof:name":"Graphton Mackenzie Inc",
    "wof:placetype":"venue"
},
  "geometry": {"coordinates":[-79.38921356199999,43.8526725769],"type":"Point"}
}