{
  "type": "Feature",
  "properties": {
    "addr:full":"499 Notre Dame Ave Sudbury ON P3C 5L1",
    "addr:housenumber":"499",
    "addr:postcode":"p3c 5l1",
    "addr:street":"Notre Dame Ave",
    "iso:country":"CA",
    "sg:address":"499 Notre Dame Ave",
    "sg:city":"Sudbury",
    "sg:classifiers":[
        {
            "category":"Restaurant",
            "type":"Food & Drink"
        }
    ],
    "sg:phone":"+1 705 675 5090",
    "sg:postcode":"P3C 5L1",
    "sg:province":"ON",
    "wof:name":"Maria's Cosy Corner Restaurant",
    "wof:placetype":"venue"
},
  "geometry": {"coordinates":[-80.98695373539999,46.5043792725],"type":"Point"}
}