{
  "type": "Feature",
  "properties": {
    "addr:full":"3661 Dixie Rd Mississauga ON L4Y 2B3",
    "addr:housenumber":"3661",
    "addr:postcode":"l4y 2b3",
    "addr:street":"Dixie Rd",
    "iso:country":"CA",
    "sg:address":"3661 Dixie Rd",
    "sg:city":"Mississauga",
    "sg:classifiers":[
        {
            "category":"Restaurant",
            "type":"Food & Drink"
        }
    ],
    "sg:phone":"+1 905 624 1101",
    "sg:postcode":"L4Y 2B3",
    "sg:province":"ON",
    "sg:tags":[
        "delicatessen",
        "butchering"
    ],
    "wof:name":"Aurora Meat Cheese & Salami",
    "wof:placetype":"venue"
},
  "geometry": {"coordinates":[-79.599869,43.620663],"type":"Point"}
}