{
  "type": "Feature",
  "properties": {
    "addr:full":"3665 Kingsway #300 Vancouver BC V5R 5W2",
    "addr:housenumber":"3665;# 300",
    "addr:postcode":"v5r 5w2",
    "addr:street":"Kingsway",
    "iso:country":"CA",
    "sg:address":"3665 Kingsway #300",
    "sg:city":"Vancouver",
    "sg:classifiers":[
        {
            "category":"Professional",
            "subcategory":"Accounting & Tax Preparation",
            "type":"Services"
        }
    ],
    "sg:phone":"+1 604 639 4401",
    "sg:postcode":"V5R 5W2",
    "sg:province":"BC",
    "sg:tags":[
        "accountant"
    ],
    "wof:name":"Tipper, Brian",
    "wof:placetype":"venue"
},
  "geometry": {"coordinates":[-123.024384,49.232414],"type":"Point"}
}