{
  "type": "Feature",
  "properties": {
    "addr:full":"59 3rd St SW Chesley ON N0G 1L0",
    "addr:housenumber":"59",
    "addr:postcode":"n0g 1l0",
    "addr:street":"3Rd St Sw",
    "iso:country":"CA",
    "sg:address":"59 3rd St SW",
    "sg:city":"Chesley",
    "sg:classifiers":[
        {
            "category":"Organizations",
            "subcategory":"Religious Organization",
            "type":"Services"
        }
    ],
    "sg:phone":"+1 519 363 2282",
    "sg:postcode":"N0G 1L0",
    "sg:province":"ON",
    "sg:tags":[
        "church"
    ],
    "wof:name":"Geneva Presbyterian Church",
    "wof:placetype":"venue"
},
  "geometry": {"coordinates":[-81.09721399999999,44.297062],"type":"Point"}
}