{
  "type": "Feature",
  "properties": {
    "addr:full":"336 Sabrina Bay SW Calgary AB T2W 1Z2",
    "addr:housenumber":"336",
    "addr:postcode":"t2w 1z2",
    "addr:street":"Sabrina Bay Sw",
    "iso:country":"CA",
    "sg:address":"336 Sabrina Bay SW",
    "sg:city":"Calgary",
    "sg:classifiers":[
        {
            "category":"Arts & Performance",
            "subcategory":"Theater",
            "type":"Entertainment"
        }
    ],
    "sg:phone":"+1 403 252 5679",
    "sg:postcode":"T2W 1Z2",
    "sg:province":"AB",
    "sg:tags":[
        "bureau",
        "live",
        "music"
    ],
    "wof:name":"Disc Jockeys Unlimited",
    "wof:placetype":"venue"
},
  "geometry": {"coordinates":[-114.075478,50.953983],"type":"Point"}
}