{
  "type": "Feature",
  "properties": {
    "addr:full":"3750 Kingston Rd Scarborough ON M1J 3H5",
    "addr:housenumber":"3750",
    "addr:postcode":"m1j 3h5",
    "addr:street":"Kingston Rd",
    "iso:country":"CA",
    "sg:address":"3750 Kingston Rd",
    "sg:city":"Scarborough",
    "sg:classifiers":[
        {
            "category":"Restaurant",
            "type":"Food & Drink"
        }
    ],
    "sg:phone":"+1 416 265 7932",
    "sg:postcode":"M1J 3H5",
    "sg:province":"ON",
    "wof:name":"Olde Stone Cottage Pub & Patio",
    "wof:placetype":"venue"
},
  "geometry": {"coordinates":[-79.209137,43.746597],"type":"Point"}
}