{
  "type": "Feature",
  "properties": {
    "addr:full":"Centre St & 5 Ave Hanna AB T0J 1P0",
    "addr:postcode":"t0j 1p0",
    "addr:street":"Centre St & 5 Ave",
    "iso:country":"CA",
    "sg:address":"Centre St & 5 Ave",
    "sg:city":"Hanna",
    "sg:classifiers":[
        {
            "category":"Organizations",
            "subcategory":"Religious Organization",
            "type":"Services"
        }
    ],
    "sg:phone":"+1 403 854 4043",
    "sg:postcode":"T0J 1P0",
    "sg:province":"AB",
    "sg:tags":[
        "church"
    ],
    "wof:name":"Hanna Christian Church",
    "wof:placetype":"venue"
},
  "geometry": {"coordinates":[-111.942016602,51.639831543],"type":"Point"}
}