{
  "type": "Feature",
  "properties": {
    "addr:full":"Calgary AB T1Y 6Z8",
    "addr:postcode":"t1y 6z8",
    "iso:country":"CA",
    "sg:city":"Calgary",
    "sg:classifiers":[
        {
            "category":"Health Services",
            "subcategory":"Health Practitioner",
            "type":"Services"
        }
    ],
    "sg:phone":"+1 403 301 0260",
    "sg:postcode":"T1Y 6Z8",
    "sg:province":"AB",
    "sg:tags":[
        "nurse",
        "registry"
    ],
    "wof:name":"A Helping Hand",
    "wof:placetype":"venue"
},
  "geometry": {"coordinates":[-113.985603,51.087074],"type":"Point"}
}