{
  "type": "Feature",
  "properties": {
    "addr:full":"201 3E Av Quebec QC G1L 2V7",
    "addr:housenumber":"201",
    "addr:postcode":"g1l 2v7",
    "addr:street":"3E Av",
    "iso:country":"CA",
    "sg:address":"201 3E Av",
    "sg:city":"Quebec",
    "sg:classifiers":[
        {
            "category":"Manufacturing",
            "subcategory":"Textiles",
            "type":"Manufacturing & Wholesale Goods"
        }
    ],
    "sg:phone":"+1 418 529 0096",
    "sg:postcode":"G1L 2V7",
    "sg:province":"QC",
    "sg:tags":[
        "sail",
        "recondition"
    ],
    "wof:name":"Voiles Saintonge Inc",
    "wof:placetype":"venue"
},
  "geometry": {"coordinates":[-71.225227356,46.8212089539],"type":"Point"}
}