{
  "type": "Feature",
  "properties": {
    "addr:full":"1500 9th St S Golden BC V0A 1H0",
    "addr:housenumber":"1500",
    "addr:postcode":"v0a 1h0",
    "addr:street":"9Th St S",
    "iso:country":"CA",
    "sg:address":"1500 9th St S",
    "sg:city":"Golden",
    "sg:classifiers":[
        {
            "category":"Education",
            "subcategory":"School",
            "type":"Public Place"
        }
    ],
    "sg:phone":"+1 250 344 2201",
    "sg:postcode":"V0A 1H0",
    "sg:province":"BC",
    "wof:name":"Golden Secondary School",
    "wof:placetype":"venue"
},
  "geometry": {"coordinates":[-116.948768616,51.2976913452],"type":"Point"}
}