{
  "type": "Feature",
  "properties": {
    "addr:full":"11 Centre St W Strathroy ON N7G 1T5",
    "addr:housenumber":"11",
    "addr:postcode":"n7g 1t5",
    "addr:street":"Centre St W",
    "iso:country":"CA",
    "sg:address":"11 Centre St W",
    "sg:city":"Strathroy",
    "sg:classifiers":[
        {
            "category":"Health Services",
            "subcategory":"Optometrist",
            "type":"Services"
        }
    ],
    "sg:phone":"+1 519 245 1092",
    "sg:postcode":"N7G 1T5",
    "sg:province":"ON",
    "wof:name":"Johnston, J J OD",
    "wof:placetype":"venue"
},
  "geometry": {"coordinates":[-81.62394,42.9575],"type":"Point"}
}