{
  "type": "Feature",
  "properties": {
    "addr:full":"1547 Lori Ave Sarnia ON N7S 3N2",
    "addr:housenumber":"1547",
    "addr:postcode":"n7s 3n2",
    "addr:street":"Lori Ave",
    "iso:country":"CA",
    "sg:address":"1547 Lori Ave",
    "sg:city":"Sarnia",
    "sg:classifiers":[
        {
            "category":"Freight",
            "type":"Transportation"
        }
    ],
    "sg:phone":"+1 519 542 2673",
    "sg:postcode":"N7S 3N2",
    "sg:province":"ON",
    "sg:tags":[
        "trucking"
    ],
    "wof:name":"Clark Motor Express Canada",
    "wof:placetype":"venue"
},
  "geometry": {"coordinates":[-82.37357299999999,43.010117],"type":"Point"}
}