{
  "type": "Feature",
  "properties": {
    "addr:full":"Ottawa ON K1R 6H5",
    "addr:postcode":"k1r 6h5",
    "iso:country":"CA",
    "sg:city":"Ottawa",
    "sg:classifiers":[
        {
            "category":"Education",
            "subcategory":"Special Training",
            "type":"Public Place"
        }
    ],
    "sg:phone":"+1 613 233 3232",
    "sg:postcode":"K1R 6H5",
    "sg:province":"ON",
    "sg:tags":[
        "reading",
        "instruction",
        "improvement"
    ],
    "wof:name":"Abc Line",
    "wof:placetype":"venue"
},
  "geometry": {"coordinates":[-75.70672607420001,45.4133148193],"type":"Point"}
}