{
  "type": "Feature",
  "properties": {
    "iso:country":"CA",
    "sg:address":"16667 Boul Hymus",
    "sg:city":"Kirkland",
    "sg:classifiers":[
        {
            "category":"Wholesale",
            "subcategory":"Chemicals & Plastics",
            "type":"Manufacturing & Wholesale Goods"
        }
    ],
    "sg:phone":"+1 514 694 7050",
    "sg:postcode":"H9H 4R9",
    "sg:province":"QC",
    "wof:name":"Baralex Inc",
    "wof:placetype":"venue"
},
  "geometry": {"coordinates":[-73.8435516357,45.4501457214],"type":"Point"}
}