{
  "type": "Feature",
  "properties": {
    "addr:full":"208 Main St W Listowel ON N4W 1A1",
    "addr:housenumber":"208",
    "addr:postcode":"n4w 1a1",
    "addr:street":"Main St W",
    "iso:country":"CA",
    "sg:address":"208 Main St W",
    "sg:city":"Listowel",
    "sg:classifiers":[
        {
            "category":"Shopping",
            "subcategory":"Musical Instruments",
            "type":"Retail Goods"
        }
    ],
    "sg:phone":"+1 519 291 5566",
    "sg:postcode":"N4W 1A1",
    "sg:province":"ON",
    "wof:name":"Selinger's Music",
    "wof:placetype":"venue"
},
  "geometry": {"coordinates":[-80.95463599999999,43.732044],"type":"Point"}
}