{
  "type": "Feature",
  "properties": {
    "addr:full":"573 Rue Grondin Mcgregor ON N0R 1J0",
    "addr:housenumber":"573",
    "addr:postcode":"n0r 1j0",
    "addr:street":"Rue Grondin",
    "iso:country":"CA",
    "sg:address":"573 Rue Grondin",
    "sg:city":"Mcgregor",
    "sg:classifiers":[
        {
            "category":"Education",
            "subcategory":"School",
            "type":"Public Place"
        }
    ],
    "sg:phone":"+1 519 726 7246",
    "sg:postcode":"N0R 1J0",
    "sg:province":"ON",
    "wof:name":"Centre DE Ressources Pedagogig",
    "wof:placetype":"venue"
},
  "geometry": {"coordinates":[-82.96849060060001,42.1445159912],"type":"Point"}
}