{
  "type": "Feature",
  "properties": {
    "addr:full":"810 Main St Canmore AB T1W 2B7",
    "addr:housenumber":"810",
    "addr:postcode":"t1w 2b7",
    "addr:street":"Main St",
    "iso:country":"CA",
    "sg:address":"810 Main St",
    "sg:city":"Canmore",
    "sg:classifiers":[
        {
            "category":"Banks & Credit Unions",
            "subcategory":"Bank",
            "type":"Services"
        }
    ],
    "sg:phone":"+1 403 678 5549",
    "sg:postcode":"T1W 2B7",
    "sg:province":"AB",
    "wof:name":"Bow Valley Credit Union Ltd",
    "wof:placetype":"venue"
},
  "geometry": {"coordinates":[-115.361313,51.08931],"type":"Point"}
}