{
  "type": "Feature",
  "properties": {
    "addr:full":"Wynyard SK S0A 4T0",
    "addr:postcode":"s0a 4t0",
    "addr:street":"Wynyard",
    "iso:country":"CA",
    "sg:city":"Wynyard",
    "sg:classifiers":[
        {
            "category":"Health Services",
            "subcategory":"Doctor",
            "type":"Services"
        }
    ],
    "sg:phone":"+1 306 554 3363",
    "sg:postcode":"S0A 4T0",
    "sg:province":"SK",
    "sg:tags":[
        "physician",
        "surgeon"
    ],
    "wof:name":"Wynyard Community Health Ctr",
    "wof:placetype":"venue"
},
  "geometry": {"coordinates":[-104.185974,51.76886],"type":"Point"}
}