{
  "type": "Feature",
  "properties": {
    "addr:full":"30 St Catharine St St Thomas ON N5P 2V8",
    "addr:housenumber":"30",
    "addr:postcode":"n5p 2v8",
    "addr:street":"St Catharine St",
    "iso:country":"CA",
    "sg:address":"30 St Catharine St",
    "sg:city":"St Thomas",
    "sg:classifiers":[
        {
            "category":"Social Services",
            "type":"Services"
        }
    ],
    "sg:phone":"+1 519 631 8477",
    "sg:postcode":"N5P 2V8",
    "sg:province":"ON",
    "sg:tags":[
        "organization",
        "welfare"
    ],
    "wof:name":"Crime Stoppers St Thomas",
    "wof:placetype":"venue"
},
  "geometry": {"coordinates":[-81.19157409669999,42.7799491882],"type":"Point"}
}