{
  "type": "Feature",
  "properties": {
    "addr:full":"11575 4E Av Montreal QC H1E 2Y8",
    "addr:housenumber":"11575",
    "addr:postcode":"h1e 2y8",
    "addr:street":"4E Av",
    "iso:country":"CA",
    "sg:address":"11575 4E Av",
    "sg:city":"Montreal",
    "sg:classifiers":[
        {
            "category":"Retail",
            "subcategory":"Auto Repair",
            "type":"Services"
        }
    ],
    "sg:phone":"+1 514 648 9980",
    "sg:postcode":"H1E 2Y8",
    "sg:province":"QC",
    "sg:tags":[
        "muffler",
        "exhaust",
        "system"
    ],
    "wof:name":"Garage Valdombre",
    "wof:placetype":"venue"
},
  "geometry": {"coordinates":[-73.59922,45.620033],"type":"Point"}
}