{
  "type": "Feature",
  "properties": {
    "addr:full":"2229 Rue Guenette Saint-Laurent QC H4R 2E9",
    "addr:housenumber":"2229",
    "addr:postcode":"h4r 2e9",
    "addr:street":"Rue Guenette",
    "iso:country":"CA",
    "sg:address":"2229 Rue Guenette",
    "sg:city":"Saint-Laurent",
    "sg:classifiers":[
        {
            "category":"Manufacturing",
            "subcategory":"Electronics",
            "type":"Manufacturing & Wholesale Goods"
        }
    ],
    "sg:phone":"+1 514 339 9966",
    "sg:postcode":"H4R 2E9",
    "sg:province":"QC",
    "sg:tags":[
        "communication",
        "radio",
        "system"
    ],
    "wof:name":"Galim Wireless Inc",
    "wof:placetype":"venue"
},
  "geometry": {"coordinates":[-73.72528839109999,45.4983100891],"type":"Point"}
}