{
  "type": "Feature",
  "properties": {
    "addr:full":"Westmount QC H3Z 1N1",
    "addr:postcode":"h3z 1n1",
    "iso:country":"CA",
    "sg:city":"Westmount",
    "sg:classifiers":[
        {
            "category":"Health Services",
            "subcategory":"Health Practitioner",
            "type":"Services"
        }
    ],
    "sg:phone":"+1 514 481 5624",
    "sg:postcode":"H3Z 1N1",
    "sg:province":"QC",
    "sg:tags":[
        "psychologist"
    ],
    "wof:name":"Messmer, Denise PhD",
    "wof:placetype":"venue"
},
  "geometry": {"coordinates":[-73.60124999999999,45.476456],"type":"Point"}
}