{
  "type": "Feature",
  "properties": {
    "addr:full":"11804 Canfield Rd SW Calgary AB T2W 1V1",
    "addr:housenumber":"11804",
    "addr:postcode":"t2w 1v1",
    "addr:street":"Canfield Rd Sw",
    "iso:country":"CA",
    "sg:address":"11804 Canfield Rd SW",
    "sg:city":"Calgary",
    "sg:classifiers":[
        {
            "category":"Professional",
            "subcategory":"Management & Consulting",
            "type":"Services"
        }
    ],
    "sg:phone":"+1 403 281 7370",
    "sg:postcode":"T2W 1V1",
    "sg:province":"AB",
    "sg:tags":[
        "consultant",
        "construction"
    ],
    "wof:name":"Poleon Construction",
    "wof:placetype":"venue"
},
  "geometry": {"coordinates":[-114.073532105,50.9487380981],"type":"Point"}
}