{
  "type": "Feature",
  "properties": {
    "addr:full":"3333 Boul DE LA Concorde E Laval QC H7E 2C3",
    "addr:housenumber":"3333",
    "addr:postcode":"h7e 2c3",
    "addr:street":"Boul De La Concorde E",
    "iso:country":"CA",
    "sg:address":"3333 Boul DE LA Concorde E",
    "sg:city":"Laval",
    "sg:classifiers":[
        {
            "category":"Health Services",
            "subcategory":"Doctor",
            "type":"Services"
        }
    ],
    "sg:phone":"+1 450 661 2401",
    "sg:postcode":"H7E 2C3",
    "sg:province":"QC",
    "sg:tags":[
        "dentist"
    ],
    "wof:name":"Rompre, Denis DDS",
    "wof:placetype":"venue"
},
  "geometry": {"coordinates":[-73.664345,45.593651],"type":"Point"}
}