{
  "type": "Feature",
  "properties": {
    "iso:country":"CA",
    "sg:address":"26 Dominion Bay",
    "sg:city":"Thompson",
    "sg:classifiers":[
        {
            "category":"Building & Trades",
            "subcategory":"Equipment Rental",
            "type":"Services"
        }
    ],
    "sg:phone":"+1 204 677 5883",
    "sg:postcode":"R8N 1L3",
    "sg:province":"MB",
    "sg:tags":[
        "crane"
    ],
    "wof:name":"Thompson Crane Rental",
    "wof:placetype":"venue"
},
  "geometry": {"coordinates":[-97.8620300293,55.7341918945],"type":"Point"}
}