{
  "type": "Feature",
  "properties": {
    "addr:full":"Williams Lake BC V2G 1J1",
    "addr:postcode":"bc v2g 1j1",
    "iso:country":"CA",
    "sg:city":"Williams Lake",
    "sg:classifiers":[
        {
            "category":"Real Estate",
            "subcategory":"Real Estate Agent",
            "type":"Services"
        }
    ],
    "sg:phone":"+1 250 398 0066",
    "sg:postcode":"V2G 1J1",
    "sg:province":"BC",
    "wof:name":"Berger, Willy",
    "wof:placetype":"venue"
},
  "geometry": {"coordinates":[-122.142547607,52.1272315979],"type":"Point"}
}