{
  "type": "Feature",
  "properties": {
    "addr:full":"Gull Bay Indian Reserve Gull Bay ON P0T 1P0",
    "addr:postcode":"p0t 1p0",
    "iso:country":"CA",
    "sg:address":"Gull Bay Indian Reserve",
    "sg:city":"Gull Bay",
    "sg:classifiers":[
        {
            "category":"Government",
            "subcategory":"Office",
            "type":"Public Place"
        }
    ],
    "sg:phone":"+1 807 982 2104",
    "sg:postcode":"P0T 1P0",
    "sg:province":"ON",
    "wof:name":"Canada First Nations Health",
    "wof:placetype":"venue"
},
  "geometry": {"coordinates":[-89.15031399999999,49.786995],"type":"Point"}
}