{
  "type": "Feature",
  "properties": {
    "iso:country":"CA",
    "sg:address":"633 Rue Duvernay",
    "sg:city":"Vercheres",
    "sg:classifiers":[
        {
            "category":"Health Services",
            "subcategory":"Medical Lab",
            "type":"Services"
        }
    ],
    "sg:phone":"+1 450 583 5107",
    "sg:postcode":"J0L 2R0",
    "sg:province":"QC",
    "wof:name":"Au Centre Du Denturologiste",
    "wof:placetype":"venue"
},
  "geometry": {"coordinates":[-73.35168457029999,45.7739715576],"type":"Point"}
}