{
  "type": "Feature",
  "properties": {
    "iso:country":"CA",
    "sg:address":"4568 Rte 12",
    "sg:city":"New Ross",
    "sg:classifiers":[
        {
            "category":"Museum",
            "type":"Entertainment"
        }
    ],
    "sg:phone":"+1 902 689 2210",
    "sg:postcode":"B0J 2M0",
    "sg:province":"NS",
    "wof:name":"Ross Farm Museum",
    "wof:placetype":"venue"
},
  "geometry": {"coordinates":[-64.4564590454,44.7331085205],"type":"Point"}
}