{
  "type": "Feature",
  "properties": {
    "addr:full":"5142 Rue Beaubien E Montreal QC H1T 1V7",
    "addr:housenumber":"5142",
    "addr:postcode":"h1t 1v7",
    "addr:street":"Rue Beaubien E",
    "iso:country":"CA",
    "sg:address":"5142 Rue Beaubien E",
    "sg:city":"Montreal",
    "sg:classifiers":[
        {
            "category":"Bars & Pubs",
            "type":"Food & Drink"
        }
    ],
    "sg:phone":"+1 514 899 1450",
    "sg:postcode":"H1T 1V7",
    "sg:province":"QC",
    "sg:tags":[
        "lounge",
        "cocktail"
    ],
    "wof:name":"Cafe Navaro",
    "wof:placetype":"venue"
},
  "geometry": {"coordinates":[-73.5706253052,45.5728034973],"type":"Point"}
}