{
  "type": "Feature",
  "properties": {
    "addr:full":"420 Creek St Wallaceburg ON N8A 4C4",
    "addr:housenumber":"420",
    "addr:postcode":"n8a 4c4",
    "addr:street":"Creek St",
    "iso:country":"CA",
    "sg:address":"420 Creek St",
    "sg:city":"Wallaceburg",
    "sg:classifiers":[
        {
            "category":"Education",
            "subcategory":"School",
            "type":"Public Place"
        }
    ],
    "sg:phone":"+1 519 627 6762",
    "sg:postcode":"N8A 4C4",
    "sg:province":"ON",
    "wof:name":"St Clair Catholic District",
    "wof:placetype":"venue"
},
  "geometry": {"coordinates":[-82.3861999512,42.5966415405],"type":"Point"}
}