{
  "type": "Feature",
  "properties": {
    "addr:full":"Halifax NS B3M 4G2",
    "addr:postcode":"b3m 4g2",
    "iso:country":"CA",
    "sg:city":"Halifax",
    "sg:classifiers":[
        {
            "category":"Personal",
            "type":"Services"
        }
    ],
    "sg:phone":"+1 902 445 4429",
    "sg:postcode":"B3M 4G2",
    "sg:province":"NS",
    "sg:tags":[
        "therapist",
        "massage"
    ],
    "wof:name":"Natural Means Massage Therapy",
    "wof:placetype":"venue"
},
  "geometry": {"coordinates":[-63.654446,44.663197],"type":"Point"}
}