{
  "type": "Feature",
  "properties": {
    "iso:country":"CA",
    "sg:address":"499 John St",
    "sg:city":"Thunder Bay",
    "sg:classifiers":[
        {
            "category":"Wholesale",
            "subcategory":"Office Equipment",
            "type":"Manufacturing & Wholesale Goods"
        }
    ],
    "sg:phone":"+1 807 344 6691",
    "sg:postcode":"P7B 1Y2",
    "sg:province":"ON",
    "sg:tags":[
        "supply",
        "register",
        "cash",
        "duplicating",
        "machine",
        "copying"
    ],
    "wof:name":"Bbm Svc",
    "wof:placetype":"venue"
},
  "geometry": {"coordinates":[-89.24395,48.431011],"type":"Point"}
}