{
  "type": "Feature",
  "properties": {
    "iso:country":"CA",
    "sg:city":"Montreal",
    "sg:classifiers":[
        {
            "category":"Insurance",
            "subcategory":"Insurance Agent",
            "type":"Services"
        }
    ],
    "sg:phone":"+1 450 654 5000",
    "sg:postcode":"H2Y 2P5",
    "sg:province":"QC",
    "sg:tags":[
        "real estate"
    ],
    "wof:name":"M Goldin & Assoc",
    "wof:placetype":"venue"
},
  "geometry": {"coordinates":[-73.5560531616,45.5020523071],"type":"Point"}
}