{
  "type": "Feature",
  "properties": {
    "addr:full":"Dorval QC H9S 2C3",
    "addr:postcode":"h9s 2c3",
    "iso:country":"CA",
    "sg:city":"Dorval",
    "sg:classifiers":[
        {
            "category":"Real Estate",
            "subcategory":"Architect",
            "type":"Services"
        }
    ],
    "sg:phone":"+1 514 631 4220",
    "sg:postcode":"H9S 2C3",
    "sg:province":"QC",
    "wof:name":"Beauvais, Serge",
    "wof:placetype":"venue"
},
  "geometry": {"coordinates":[-73.738235,45.438793],"type":"Point"}
}