{
  "type": "Feature",
  "properties": {
    "addr:full":"Surrey BC V3R 1M7",
    "addr:postcode":"v3r 1m7",
    "iso:country":"CA",
    "sg:city":"Surrey",
    "sg:classifiers":[
        {
            "category":"Arts & Performance",
            "subcategory":"Theater",
            "type":"Entertainment"
        }
    ],
    "sg:phone":"+1 604 589 7559",
    "sg:postcode":"V3R 1M7",
    "sg:province":"BC",
    "sg:tags":[
        "talent",
        "agency",
        "casting"
    ],
    "wof:name":"Lloyd Talent",
    "wof:placetype":"venue"
},
  "geometry": {"coordinates":[-122.80872345,49.1913604736],"type":"Point"}
}