{
  "type": "Feature",
  "properties": {
    "iso:country":"CA",
    "sg:address":"111 Craig St",
    "sg:city":"Nanaimo",
    "sg:classifiers":[
        {
            "category":"Building & Trades",
            "subcategory":"Construction",
            "type":"Services"
        }
    ],
    "sg:phone":"+1 250 754 9635",
    "sg:postcode":"V9R 3V2",
    "sg:province":"BC",
    "sg:tags":[
        "general",
        "contractor"
    ],
    "wof:name":"Mc Cartan Contracting",
    "wof:placetype":"venue"
},
  "geometry": {"coordinates":[-123.953178,49.168167],"type":"Point"}
}