{
  "type": "Feature",
  "properties": {
    "addr:full":"Calgary AB T2Y 3S4",
    "addr:postcode":"t2y 3s4",
    "iso:country":"CA",
    "sg:city":"Calgary",
    "sg:classifiers":[
        {
            "category":"Food & Beverages",
            "subcategory":"Specialty",
            "type":"Retail Goods"
        }
    ],
    "sg:phone":"+1 403 201 3500",
    "sg:postcode":"T2Y 3S4",
    "sg:province":"AB",
    "sg:tags":[
        "health",
        "diet"
    ],
    "wof:name":"General Nutrition Ctr CO",
    "wof:placetype":"venue"
},
  "geometry": {"coordinates":[-114.06234741199999,50.8980865479],"type":"Point"}
}