{
  "type": "Feature",
  "properties": {
    "addr:full":"925 King St Bridgewater NS B4V 1B7",
    "addr:housenumber":"925",
    "addr:postcode":"b4v 1b7",
    "addr:street":"King St",
    "iso:country":"CA",
    "sg:address":"925 King St",
    "sg:city":"Bridgewater",
    "sg:classifiers":[
        {
            "category":"Professional",
            "subcategory":"Business Services",
            "type":"Services"
        }
    ],
    "sg:phone":"+1 902 543 2422",
    "sg:postcode":"B4V 1B7",
    "sg:province":"NS",
    "sg:tags":[
        "process",
        "server"
    ],
    "wof:name":"Nova Documents Svc",
    "wof:placetype":"venue"
},
  "geometry": {"coordinates":[-64.52551269529999,44.3837890625],"type":"Point"}
}