{
  "type": "Feature",
  "properties": {
    "addr:full":"2917 Early Dr Saskatoon SK S7H 3K5",
    "addr:housenumber":"2917",
    "addr:postcode":"s7h 3k5",
    "addr:street":"Early Dr",
    "iso:country":"CA",
    "sg:address":"2917 Early Dr",
    "sg:city":"Saskatoon",
    "sg:classifiers":[
        {
            "category":"Education",
            "subcategory":"Dance Studio",
            "type":"Public Place"
        }
    ],
    "sg:phone":"+1 306 955 0030",
    "sg:postcode":"S7H 3K5",
    "sg:province":"SK",
    "sg:tags":[
        "instruction",
        "dancing"
    ],
    "wof:name":"Jaspar Academy of Dance",
    "wof:placetype":"venue"
},
  "geometry": {"coordinates":[-106.61151099999999,52.108742],"type":"Point"}
}