{
  "type": "Feature",
  "properties": {
    "addr:full":"Etobicoke ON M8V 1J7",
    "addr:postcode":"m8v 1j7",
    "iso:country":"CA",
    "sg:city":"Etobicoke",
    "sg:classifiers":[
        {
            "category":"Insurance",
            "subcategory":"Insurance Agent",
            "type":"Services"
        }
    ],
    "sg:phone":"+1 416 255 3728",
    "sg:postcode":"M8V 1J7",
    "sg:province":"ON",
    "wof:name":"Marhen Insurance Brokers Ltd",
    "wof:placetype":"venue"
},
  "geometry": {"coordinates":[-79.506294,43.600708],"type":"Point"}
}