{
  "type": "Feature",
  "properties": {
    "addr:full":"1623 Braid Rd Delta BC V4L 1T5",
    "addr:housenumber":"1623",
    "addr:postcode":"v4l 1t5",
    "addr:street":"Braid Rd",
    "iso:country":"CA",
    "sg:address":"1623 Braid Rd",
    "sg:city":"Delta",
    "sg:classifiers":[
        {
            "category":"Shopping",
            "subcategory":"Jewelry",
            "type":"Retail Goods"
        }
    ],
    "sg:phone":"+1 604 943 7531",
    "sg:postcode":"V4L 1T5",
    "sg:province":"BC",
    "sg:tags":[
        "designer"
    ],
    "wof:name":"Stephen W Duffus Ltd",
    "wof:placetype":"venue"
},
  "geometry": {"coordinates":[-123.059181213,49.032535553],"type":"Point"}
}