{
  "type": "Feature",
  "properties": {
    "addr:full":"11125 Av L'Archeveque Montreal-Nord QC H1H 3A8",
    "addr:postcode":"h1h 3a8",
    "addr:street":"Av L'Archeveque",
    "iso:country":"CA",
    "sg:address":"11125 Av L'Archeveque",
    "sg:city":"Montreal-Nord",
    "sg:classifiers":[
        {
            "category":"Taxi",
            "type":"Transportation"
        }
    ],
    "sg:phone":"+1 514 322 2121",
    "sg:postcode":"H1H 3A8",
    "sg:province":"QC",
    "sg:tags":[
        "taxicab"
    ],
    "wof:name":"Taxi Moderne Inc",
    "wof:placetype":"venue"
},
  "geometry": {"coordinates":[-73.6303482056,45.597618103],"type":"Point"}
}