{
  "type": "Feature",
  "properties": {
    "iso:country":"CA",
    "sg:address":"930 Rue Notre-Dame",
    "sg:city":"Lachine",
    "sg:classifiers":[
        {
            "category":"Shopping",
            "subcategory":"Clothing, Apparel, & Fashions",
            "type":"Retail Goods"
        }
    ],
    "sg:phone":"+1 514 637 1211",
    "sg:postcode":"H8S 2B9",
    "sg:province":"QC",
    "wof:name":"Chez Marie Ladies Wear",
    "wof:placetype":"venue"
},
  "geometry": {"coordinates":[-73.672012,45.435047],"type":"Point"}
}