{
  "type": "Feature",
  "properties": {
    "addr:full":"1327 Loudoun Rd Winnipeg MB R3S 1A3",
    "addr:housenumber":"1327",
    "addr:postcode":"r3s 1a3",
    "addr:street":"Loudoun Rd",
    "iso:country":"CA",
    "sg:address":"1327 Loudoun Rd",
    "sg:city":"Winnipeg",
    "sg:classifiers":[
        {
            "category":"Retail",
            "subcategory":"Repair Shop",
            "type":"Services"
        }
    ],
    "sg:phone":"+1 204 896 5714",
    "sg:postcode":"R3S 1A3",
    "sg:province":"MB",
    "sg:tags":[
        "lock",
        "locksmith"
    ],
    "wof:name":"Rob's Door & Hardware Inslntn",
    "wof:placetype":"venue"
},
  "geometry": {"coordinates":[-97.25567599999999,49.838093],"type":"Point"}
}