{
  "type": "Feature",
  "properties": {
    "addr:full":"Evansburg AB T0E 0T0",
    "addr:postcode":"t0e 0t0",
    "iso:country":"CA",
    "sg:city":"Evansburg",
    "sg:classifiers":[
        {
            "category":"Organizations",
            "subcategory":"Religious Organization",
            "type":"Services"
        }
    ],
    "sg:phone":"+1 780 727 2245",
    "sg:postcode":"T0E 0T0",
    "sg:province":"AB",
    "sg:tags":[
        "church"
    ],
    "wof:name":"Evansburg Baptist Church",
    "wof:placetype":"venue"
},
  "geometry": {"coordinates":[-115.01438140899999,53.5998916626],"type":"Point"}
}