{
  "type": "Feature",
  "properties": {
    "addr:full":"Dalhousie NB E8C 2X3",
    "addr:postcode":"e8c 2x3",
    "iso:country":"CA",
    "sg:city":"Dalhousie",
    "sg:classifiers":[
        {
            "category":"Professional",
            "subcategory":"Lawyer & Legal Services",
            "type":"Services"
        }
    ],
    "sg:phone":"+1 506 684 5661",
    "sg:postcode":"E8C 2X3",
    "sg:province":"NB",
    "sg:tags":[
        "attorney"
    ],
    "wof:name":"Dube & Assoc",
    "wof:placetype":"venue"
},
  "geometry": {"coordinates":[-66.378288269,48.0667381287],"type":"Point"}
}