{
  "type": "Feature",
  "properties": {
    "addr:full":"27 Inglis Pl Truro NS B2N 4B5",
    "addr:housenumber":"27",
    "addr:postcode":"b2n 4b5",
    "addr:street":"Inglis Pl",
    "iso:country":"CA",
    "sg:address":"27 Inglis Pl",
    "sg:city":"Truro",
    "sg:classifiers":[
        {
            "category":"Personal",
            "subcategory":"Beauty Salon",
            "type":"Services"
        }
    ],
    "sg:phone":"+1 902 893 2558",
    "sg:postcode":"B2N 4B5",
    "sg:province":"NS",
    "wof:name":"Wendy's Shear Dimension",
    "wof:placetype":"venue"
},
  "geometry": {"coordinates":[-63.27618,45.364174],"type":"Point"}
}