{
  "type": "Feature",
  "properties": {
    "addr:full":"Vancouver BC V6G 1C9",
    "addr:postcode":"v6g 1c9",
    "iso:country":"CA",
    "sg:city":"Vancouver",
    "sg:classifiers":[
        {
            "category":"Restaurant",
            "type":"Food & Drink"
        }
    ],
    "sg:phone":"+1 604 684 7827",
    "sg:postcode":"V6G 1C9",
    "sg:province":"BC",
    "wof:name":"Subway Sandwiches & Salads",
    "wof:placetype":"venue"
},
  "geometry": {"coordinates":[-123.134254,49.290867],"type":"Point"}
}