{
  "type": "Feature",
  "properties": {
    "addr:full":"Picton ON K0K 2T0",
    "addr:postcode":"k0k 2t0",
    "iso:country":"CA",
    "sg:city":"Picton",
    "sg:classifiers":[
        {
            "category":"Manufacturing",
            "subcategory":"Tools & Machinery",
            "type":"Manufacturing & Wholesale Goods"
        }
    ],
    "sg:phone":"+1 613 476 1155",
    "sg:postcode":"K0K 2T0",
    "sg:province":"ON",
    "sg:tags":[
        "machine",
        "shop"
    ],
    "wof:name":"R T Connor Ltd",
    "wof:placetype":"venue"
},
  "geometry": {"coordinates":[-77.14505,44.019257],"type":"Point"}
}