{
  "type": "Feature",
  "properties": {
    "addr:full":"1449 Rue Cartier L'Ancienne-Lorette QC G2E 4N3",
    "addr:housenumber":"1449",
    "addr:postcode":"g2e 4n3",
    "addr:street":"Rue Cartier",
    "iso:country":"CA",
    "sg:address":"1449 Rue Cartier",
    "sg:city":"L'Ancienne-Lorette",
    "sg:classifiers":[
        {
            "category":"Building & Trades",
            "subcategory":"Construction",
            "type":"Services"
        }
    ],
    "sg:phone":"+1 418 872 9290",
    "sg:postcode":"G2E 4N3",
    "sg:province":"QC",
    "sg:tags":[
        "painter"
    ],
    "wof:name":"Jean-Paul Matte & Fils Inc",
    "wof:placetype":"venue"
},
  "geometry": {"coordinates":[-71.37249,46.807316],"type":"Point"}
}