{
  "type": "Feature",
  "properties": {
    "addr:full":"2061 Ch Gascon Lachenaie QC J6X 4H2",
    "addr:housenumber":"2061",
    "addr:postcode":"j6x 4h2",
    "addr:street":"Ch Gascon",
    "iso:country":"CA",
    "sg:address":"2061 Ch Gascon",
    "sg:city":"Lachenaie",
    "sg:classifiers":[
        {
            "category":"Home & Garden",
            "subcategory":"Household Appliances",
            "type":"Retail Goods"
        }
    ],
    "sg:phone":"+1 450 964 3777",
    "sg:postcode":"J6X 4H2",
    "sg:province":"QC",
    "sg:tags":[
        "machine",
        "sewing"
    ],
    "wof:name":"Machine A Coudre L'Attension",
    "wof:placetype":"venue"
},
  "geometry": {"coordinates":[-73.660866,45.721291],"type":"Point"}
}