{
  "type": "Feature",
  "properties": {
    "addr:full":"124 Boul Cure-Labelle Sainte-Rose QC H7L 2Z4",
    "addr:housenumber":"124",
    "addr:postcode":"h7l 2z4",
    "addr:street":"Boul Cure-Labelle",
    "iso:country":"CA",
    "sg:address":"124 Boul Cure-Labelle",
    "sg:city":"Sainte-Rose",
    "sg:classifiers":[
        {
            "category":"Building & Trades",
            "subcategory":"Construction",
            "type":"Services"
        }
    ],
    "sg:phone":"+1 450 628 6889",
    "sg:postcode":"H7L 2Z4",
    "sg:province":"QC",
    "sg:tags":[
        "general",
        "contractor"
    ],
    "wof:name":"Groupe Alto",
    "wof:placetype":"venue"
},
  "geometry": {"coordinates":[-73.79156500000001,45.609451],"type":"Point"}
}