{
  "type": "Feature",
  "properties": {
    "addr:full":"203 1st St W Wiseton SK S0L 3M0",
    "addr:housenumber":"203",
    "addr:postcode":"s0l 3m0",
    "addr:street":"1St St W Wiseton",
    "iso:country":"CA",
    "sg:address":"203 1st St W",
    "sg:city":"Wiseton",
    "sg:classifiers":[
        {
            "category":"Recreation",
            "type":"Entertainment"
        }
    ],
    "sg:phone":"+1 306 357 2083",
    "sg:postcode":"S0L 3M0",
    "sg:province":"SK",
    "sg:tags":[
        "club",
        "curling"
    ],
    "wof:name":"Wiseton Community Ctr",
    "wof:placetype":"venue"
},
  "geometry": {"coordinates":[-107.646828,51.315239],"type":"Point"}
}