{
  "type": "Feature",
  "properties": {
    "addr:full":"Ottawa ON K1B 4E4",
    "addr:postcode":"k1b 4e4",
    "iso:country":"CA",
    "sg:city":"Ottawa",
    "sg:classifiers":[
        {
            "category":"Retail",
            "subcategory":"Auto Repair",
            "type":"Services"
        }
    ],
    "sg:phone":"+1 613 746 1340",
    "sg:postcode":"K1B 4E4",
    "sg:province":"ON",
    "sg:tags":[
        "repairing",
        "automobile"
    ],
    "wof:name":"Zapper Motors",
    "wof:placetype":"venue"
},
  "geometry": {"coordinates":[-75.60889400000001,45.40406],"type":"Point"}
}