{
  "type": "Feature",
  "properties": {
    "addr:full":"195 14E Av S Sherbrooke QC J1G 2W5",
    "addr:housenumber":"195",
    "addr:postcode":"j1g 2w5",
    "addr:street":"14E Av S",
    "iso:country":"CA",
    "sg:address":"195 14E Av S",
    "sg:city":"Sherbrooke",
    "sg:classifiers":[
        {
            "category":"Building & Trades",
            "subcategory":"Construction",
            "type":"Services"
        }
    ],
    "sg:phone":"+1 819 346 4741",
    "sg:postcode":"J1G 2W5",
    "sg:province":"QC",
    "sg:tags":[
        "general",
        "contractor"
    ],
    "wof:name":"Demers, Alfred",
    "wof:placetype":"venue"
},
  "geometry": {"coordinates":[-71.868675,45.405384],"type":"Point"}
}