{
  "type": "Feature",
  "properties": {
    "addr:full":"1681 Highway Ave NE Redcliff AB T0J 2P0",
    "addr:housenumber":"1681",
    "addr:postcode":"t0j 2p0",
    "addr:street":"Highway Ave Ne",
    "iso:country":"CA",
    "sg:address":"1681 Highway Ave NE",
    "sg:city":"Redcliff",
    "sg:classifiers":[
        {
            "category":"Retail",
            "subcategory":"Auto Repair",
            "type":"Services"
        }
    ],
    "sg:phone":"+1 403 548 6257",
    "sg:postcode":"T0J 2P0",
    "sg:province":"AB",
    "sg:tags":[
        "repairing",
        "automobile"
    ],
    "wof:name":"Al's Auto Svc",
    "wof:placetype":"venue"
},
  "geometry": {"coordinates":[-110.76480100000001,50.07465],"type":"Point"}
}