{
  "type": "Feature",
  "properties": {
    "addr:full":"816 Twentieth St New Westminster BC V3M 4W6",
    "addr:housenumber":"816",
    "addr:postcode":"v3m 4w6",
    "addr:street":"Twentieth St",
    "iso:country":"CA",
    "sg:address":"816 Twentieth St",
    "sg:city":"New Westminster",
    "sg:classifiers":[
        {
            "category":"Food & Beverages",
            "subcategory":"Groceries & Convenience Stores",
            "type":"Retail Goods"
        }
    ],
    "sg:phone":"+1 604 521 8031",
    "sg:postcode":"V3M 4W6",
    "sg:province":"BC",
    "sg:tags":[
        "grocer"
    ],
    "wof:name":"Hi View Market",
    "wof:placetype":"venue"
},
  "geometry": {"coordinates":[-122.949195862,49.2033882141],"type":"Point"}
}