{
  "type": "Feature",
  "properties": {
    "iso:country":"CA",
    "sg:address":"1640 Johnston St",
    "sg:city":"Vancouver",
    "sg:classifiers":[
        {
            "category":"Shopping",
            "type":"Retail Goods"
        }
    ],
    "sg:phone":"+1 604 689 1650",
    "sg:postcode":"V6H 3S2",
    "sg:province":"BC",
    "sg:tags":[
        "art",
        "gallery",
        "dealer"
    ],
    "wof:name":"Dundarave Print Workshop",
    "wof:placetype":"venue"
},
  "geometry": {"coordinates":[-123.135445,49.272083],"type":"Point"}
}