{
  "type": "Feature",
  "properties": {
    "addr:full":"100 2nd Ave NE Moose Jaw SK S6H 1B8",
    "addr:housenumber":"100",
    "addr:postcode":"s6h 1b8",
    "addr:street":"2Nd Ave Ne",
    "iso:country":"CA",
    "sg:address":"100 2nd Ave NE",
    "sg:city":"Moose Jaw",
    "sg:classifiers":[
        {
            "category":"Personal",
            "subcategory":"Beauty Salon",
            "type":"Services"
        }
    ],
    "sg:phone":"+1 306 693 6991",
    "sg:postcode":"S6H 1B8",
    "sg:province":"SK",
    "sg:tags":[
        "electrolysis"
    ],
    "wof:name":"L A Electrolysis",
    "wof:placetype":"venue"
},
  "geometry": {"coordinates":[-105.529678,50.390739],"type":"Point"}
}