{
  "type": "Feature",
  "properties": {
    "addr:full":"3720 Parker St Burnaby BC V5C 3B1",
    "addr:housenumber":"3720",
    "addr:postcode":"v5c 3b1",
    "addr:street":"Parker St",
    "iso:country":"CA",
    "sg:address":"3720 Parker St",
    "sg:city":"Burnaby",
    "sg:classifiers":[
        {
            "category":"Retail",
            "subcategory":"Repair Shop",
            "type":"Services"
        }
    ],
    "sg:phone":"+1 604 294 1918",
    "sg:postcode":"V5C 3B1",
    "sg:province":"BC",
    "sg:tags":[
        "scooter",
        "motorcycle",
        "motor"
    ],
    "wof:name":"Hi-Way Choppers",
    "wof:placetype":"venue"
},
  "geometry": {"coordinates":[-123.02269699999999,49.275669],"type":"Point"}
}