{
  "type": "Feature",
  "properties": {
    "addr:full":"2 Ch DE LA Cote-Saint-Louis O Blainville QC J7C 1B5",
    "addr:housenumber":"2",
    "addr:postcode":"j7c 1b5",
    "addr:street":"Ch De La Cote-Saint-Louis O",
    "iso:country":"CA",
    "sg:address":"2 Ch DE LA Cote-Saint-Louis O",
    "sg:city":"Blainville",
    "sg:classifiers":[
        {
            "category":"Autos & Motor Vehicles",
            "subcategory":"Auto Supplies",
            "type":"Retail Goods"
        }
    ],
    "sg:phone":"+1 450 437 9771",
    "sg:postcode":"J7C 1B5",
    "sg:province":"QC",
    "sg:tags":[
        "tire"
    ],
    "wof:name":"Centre Du Pneu & Mags Haute",
    "wof:placetype":"venue"
},
  "geometry": {"coordinates":[-73.84612300000001,45.651756],"type":"Point"}
}