{
  "type": "Feature",
  "properties": {
    "addr:full":"670 Goyeau St Windsor ON N9A 1H4",
    "addr:housenumber":"670",
    "addr:postcode":"n9a 1h4",
    "addr:street":"Goyeau St",
    "iso:country":"CA",
    "sg:address":"670 Goyeau St",
    "sg:city":"Windsor",
    "sg:classifiers":[
        {
            "category":"Personal",
            "subcategory":"Beauty Salon",
            "type":"Services"
        }
    ],
    "sg:phone":"+1 519 973 9286",
    "sg:postcode":"N9A 1H4",
    "sg:province":"ON",
    "wof:name":"Majeda Complete Esthetics",
    "wof:placetype":"venue"
},
  "geometry": {"coordinates":[-83.034294,42.314011],"type":"Point"}
}