{
  "type": "Feature",
  "properties": {
    "iso:country":"CA",
    "sg:address":"12139 Rue Letellier",
    "sg:city":"Montreal",
    "sg:classifiers":[
        {
            "category":"Wholesale",
            "subcategory":"Vending Machines",
            "type":"Manufacturing & Wholesale Goods"
        }
    ],
    "sg:phone":"+1 514 274 2115",
    "sg:postcode":"H3M 2Z9",
    "sg:province":"QC",
    "sg:tags":[
        "operated",
        "phonograph"
    ],
    "wof:name":"Destounis Automatic Music Inc",
    "wof:placetype":"venue"
},
  "geometry": {"coordinates":[-73.697243,45.544922],"type":"Point"}
}