{
  "type": "Feature",
  "properties": {
    "iso:country":"CA",
    "sg:address":"2333 Clarke St",
    "sg:city":"Port Moody",
    "sg:classifiers":[
        {
            "category":"Retail",
            "subcategory":"Repair Shop",
            "type":"Services"
        }
    ],
    "sg:phone":"+1 604 931 3141",
    "sg:postcode":"V3H 1Y9",
    "sg:province":"BC",
    "sg:tags":[
        "upholsterer"
    ],
    "wof:name":"Choice Upholstery Fabrics",
    "wof:placetype":"venue"
},
  "geometry": {"coordinates":[-122.860626,49.277691],"type":"Point"}
}