{
  "type": "Feature",
  "properties": {
    "addr:full":"235 Mccallum St Miramichi NB E1V 2A4",
    "addr:housenumber":"235",
    "addr:postcode":"e1v 2a4",
    "addr:street":"Mccallum St",
    "iso:country":"CA",
    "sg:address":"235 Mccallum St",
    "sg:city":"Miramichi",
    "sg:classifiers":[
        {
            "category":"Social Services",
            "type":"Services"
        }
    ],
    "sg:phone":"+1 506 622 1256",
    "sg:postcode":"E1V 2A4",
    "sg:province":"NB",
    "sg:tags":[
        "senior",
        "citizen"
    ],
    "wof:name":"Newcastle Housing Corp",
    "wof:placetype":"venue"
},
  "geometry": {"coordinates":[-65.5657653809,46.9991149902],"type":"Point"}
}