{
  "type": "Feature",
  "properties": {
    "iso:country":"CA",
    "sg:address":"3461 Shenton Rd",
    "sg:city":"Nanaimo",
    "sg:classifiers":[
        {
            "category":"Retail",
            "subcategory":"Auto Repair",
            "type":"Services"
        }
    ],
    "sg:phone":"+1 250 729 4905",
    "sg:postcode":"V9T 2H1",
    "sg:province":"BC",
    "sg:tags":[
        "repairing",
        "automobile"
    ],
    "wof:name":"First Choice Auto Clinic",
    "wof:placetype":"venue"
},
  "geometry": {"coordinates":[-124.00765991199999,49.2036628723],"type":"Point"}
}