{
  "type": "Feature",
  "properties": {
    "addr:full":"21 Rue Forget St-Sauveur-Des-Monts QC J0R 1R0",
    "addr:housenumber":"21",
    "addr:postcode":"j0r 1r0",
    "addr:street":"Rue Forget St-Sauveur-Des-Monts",
    "iso:country":"CA",
    "sg:address":"21 Rue Forget",
    "sg:city":"St-Sauveur-Des-Monts",
    "sg:classifiers":[
        {
            "category":"Health Services",
            "subcategory":"Clinic",
            "type":"Services"
        }
    ],
    "sg:phone":"+1 450 227 6663",
    "sg:postcode":"J0R 1R0",
    "sg:province":"QC",
    "sg:tags":[
        "home"
    ],
    "wof:name":"Ressources Sante Lm Inc",
    "wof:placetype":"venue"
},
  "geometry": {"coordinates":[-74.157021,45.895332],"type":"Point"}
}