{
  "type": "Feature",
  "properties": {
    "addr:full":"843 Red River Rd Thunder Bay ON P7B 1K3",
    "addr:housenumber":"843",
    "addr:postcode":"p7b 1k3",
    "addr:street":"Red River Rd",
    "iso:country":"CA",
    "sg:address":"843 Red River Rd",
    "sg:city":"Thunder Bay",
    "sg:classifiers":[
        {
            "category":"Personal",
            "subcategory":"Tanning Parlor",
            "type":"Services"
        }
    ],
    "sg:phone":"+1 807 768 2828",
    "sg:postcode":"P7B 1K3",
    "sg:province":"ON",
    "sg:tags":[
        "salon"
    ],
    "wof:name":"Fabutan Sun Tan Studios",
    "wof:placetype":"venue"
},
  "geometry": {"coordinates":[-89.248344,48.445694],"type":"Point"}
}