{
  "type": "Feature",
  "properties": {
    "addr:full":"52 Du Pont St Bedford QC J0J 1A0",
    "addr:housenumber":"52",
    "addr:postcode":"j0j 1a0",
    "addr:street":"Du Pont St",
    "iso:country":"CA",
    "sg:address":"52 Du Pont St",
    "sg:city":"Bedford",
    "sg:classifiers":[
        {
            "category":"Organizations",
            "subcategory":"Professional Association",
            "type":"Services"
        }
    ],
    "sg:phone":"+1 450 248 2229",
    "sg:postcode":"J0J 1A0",
    "sg:province":"QC",
    "wof:name":"Roc Des Rivieres",
    "wof:placetype":"venue"
},
  "geometry": {"coordinates":[-72.988632,45.124226],"type":"Point"}
}