{
  "type": "Feature",
  "properties": {
    "addr:full":"Whitby ON L1M 1A2",
    "addr:postcode":"l1m 1a2",
    "iso:country":"CA",
    "sg:city":"Whitby",
    "sg:classifiers":[
        {
            "category":"Health Services",
            "subcategory":"Chiropractor",
            "type":"Services"
        }
    ],
    "sg:phone":"+1 905 655 8469",
    "sg:postcode":"L1M 1A2",
    "sg:province":"ON",
    "wof:name":"Du Quesnay, Katharine DC",
    "wof:placetype":"venue"
},
  "geometry": {"coordinates":[-78.9606704712,43.9568367004],"type":"Point"}
}