{
  "type": "Feature",
  "properties": {
    "iso:country":"CA",
    "sg:address":"930 Kamato Rd",
    "sg:city":"Mississauga",
    "sg:classifiers":[
        {
            "category":"Manufacturing",
            "subcategory":"Metals",
            "type":"Manufacturing & Wholesale Goods"
        }
    ],
    "sg:phone":"+1 905 625 9083",
    "sg:postcode":"L4W 2R6",
    "sg:province":"ON",
    "sg:tags":[
        "foundry"
    ],
    "wof:name":"Skara Metal Foundry Ltd",
    "wof:placetype":"venue"
},
  "geometry": {"coordinates":[-79.64762115480001,43.6354370117],"type":"Point"}
}