{
  "type": "Feature",
  "properties": {
    "addr:full":"Granby QC J2G 2J9",
    "addr:postcode":"j2g 2j9",
    "iso:country":"CA",
    "sg:city":"Granby",
    "sg:classifiers":[
        {
            "category":"Personal",
            "subcategory":"Beauty Salon",
            "type":"Services"
        }
    ],
    "sg:phone":"+1 450 372 7761",
    "sg:postcode":"J2G 2J9",
    "sg:province":"QC",
    "wof:name":"Salon Lyne",
    "wof:placetype":"venue"
},
  "geometry": {"coordinates":[-72.7243728638,45.4038734436],"type":"Point"}
}