{
  "type": "Feature",
  "properties": {
    "addr:full":"Ottawa ON K1B 4L2",
    "addr:postcode":"k1b 4l2",
    "iso:country":"CA",
    "sg:city":"Ottawa",
    "sg:classifiers":[
        {
            "category":"Retail",
            "subcategory":"Repair Shop",
            "type":"Services"
        }
    ],
    "sg:phone":"+1 613 744 0609",
    "sg:postcode":"K1B 4L2",
    "sg:province":"ON",
    "sg:tags":[
        "equipment"
    ],
    "wof:name":"Hrd Kitchen Svc Ltd",
    "wof:placetype":"venue"
},
  "geometry": {"coordinates":[-75.62329099999999,45.411194],"type":"Point"}
}