{
  "type": "Feature",
  "properties": {
    "addr:full":"Windsor ON N8X 4X9",
    "addr:postcode":"n8x 4x9",
    "iso:country":"CA",
    "sg:city":"Windsor",
    "sg:classifiers":[
        {
            "category":"Health Services",
            "subcategory":"Doctor",
            "type":"Services"
        }
    ],
    "sg:phone":"+1 519 254 2897",
    "sg:postcode":"N8X 4X9",
    "sg:province":"ON",
    "sg:tags":[
        "physician",
        "surgeon"
    ],
    "wof:name":"Windsor Vascular Laboratory",
    "wof:placetype":"venue"
},
  "geometry": {"coordinates":[-83.015586853,42.2984352112],"type":"Point"}
}