{
  "type": "Feature",
  "properties": {
    "iso:country":"CA",
    "sg:city":"Abbotsford",
    "sg:classifiers":[
        {
            "category":"Wholesale",
            "subcategory":"Machinery & Supplies",
            "type":"Manufacturing & Wholesale Goods"
        }
    ],
    "sg:phone":"+1 604 855 6086",
    "sg:postcode":"V2T 6B3",
    "sg:province":"BC",
    "sg:tags":[
        "farm",
        "equipment"
    ],
    "wof:name":"A & I Products Canada Inc",
    "wof:placetype":"venue"
},
  "geometry": {"coordinates":[-122.356773377,49.0426521301],"type":"Point"}
}