{
  "type": "Feature",
  "properties": {
    "addr:full":"5960 Dixie Rd Mississauga ON L4W 1E9",
    "addr:housenumber":"5960",
    "addr:postcode":"l4w 1e9",
    "addr:street":"Dixie Rd",
    "iso:country":"CA",
    "sg:address":"5960 Dixie Rd",
    "sg:city":"Mississauga",
    "sg:classifiers":[
        {
            "category":"Restaurant",
            "type":"Food & Drink"
        }
    ],
    "sg:phone":"+1 905 670 1919",
    "sg:postcode":"L4W 1E9",
    "sg:province":"ON",
    "wof:name":"Super Mack's Drive in Rstrnt",
    "wof:placetype":"venue"
},
  "geometry": {"coordinates":[-79.646439,43.654236],"type":"Point"}
}