{
  "type": "Feature",
  "properties": {
    "iso:country":"CA",
    "sg:address":"1195 Gainsborough Rd",
    "sg:city":"London",
    "sg:classifiers":[
        {
            "category":"Autos & Motor Vehicles",
            "subcategory":"Auto Supplies",
            "type":"Retail Goods"
        }
    ],
    "sg:phone":"+1 519 432 4171",
    "sg:postcode":"N6H 5L5",
    "sg:province":"ON",
    "sg:tags":[
        "tire"
    ],
    "wof:name":"Don Ashman's Central Tire Ltd",
    "wof:placetype":"venue"
},
  "geometry": {"coordinates":[-81.3405990601,42.9964485168],"type":"Point"}
}