{
  "type": "Feature",
  "properties": {
    "addr:full":"54 Whitmore St Grand Falls-Windsor NL A2B 1B9",
    "addr:housenumber":"54",
    "addr:postcode":"a2b 1b9",
    "addr:street":"Whitmore St",
    "iso:country":"CA",
    "sg:address":"54 Whitmore St",
    "sg:city":"Grand Falls-Windsor",
    "sg:classifiers":[
        {
            "category":"Wholesale",
            "subcategory":"Construction Materials",
            "type":"Manufacturing & Wholesale Goods"
        }
    ],
    "sg:phone":"+1 709 489 8492",
    "sg:postcode":"A2B 1B9",
    "sg:province":"NL",
    "sg:tags":[
        "sand",
        "gravel"
    ],
    "wof:name":"Kdj Enterprises",
    "wof:placetype":"venue"
},
  "geometry": {"coordinates":[-55.67564,48.952946],"type":"Point"}
}