{
  "type": "Feature",
  "properties": {
    "addr:full":"705 Ashburnham Dr Peterborough ON K9L 1P7",
    "addr:housenumber":"705",
    "addr:postcode":"k9l 1p7",
    "addr:street":"Ashburnham Dr",
    "iso:country":"CA",
    "sg:address":"705 Ashburnham Dr",
    "sg:city":"Peterborough",
    "sg:classifiers":[
        {
            "category":"Restaurant",
            "type":"Food & Drink"
        }
    ],
    "sg:phone":"+1 705 749 2835",
    "sg:postcode":"K9L 1P7",
    "sg:province":"ON",
    "wof:name":"Wendy's",
    "wof:placetype":"venue"
},
  "geometry": {"coordinates":[-78.296997,44.288803],"type":"Point"}
}