{
  "type": "Feature",
  "properties": {
    "addr:full":"8932 Boul Des Hetres Shawinigan QC G9N 4X8",
    "addr:housenumber":"8932",
    "addr:postcode":"g9n 4x8",
    "addr:street":"Boul Des Hetres",
    "iso:country":"CA",
    "sg:address":"8932 Boul Des Hetres",
    "sg:city":"Shawinigan",
    "sg:classifiers":[
        {
            "category":"Autos & Motor Vehicles",
            "subcategory":"Automobile Sales",
            "type":"Retail Goods"
        }
    ],
    "sg:phone":"+1 819 539 3939",
    "sg:postcode":"G9N 4X8",
    "sg:province":"QC",
    "sg:tags":[
        "car",
        "dealer"
    ],
    "wof:name":"R Rivard Automobiles",
    "wof:placetype":"venue"
},
  "geometry": {"coordinates":[-72.711533,46.589558],"type":"Point"}
}