{
  "type": "Feature",
  "properties": {
    "addr:full":"30 Main St Emerson MB R0A 0L0",
    "addr:housenumber":"30",
    "addr:postcode":"r0a 0l0",
    "addr:street":"Main St",
    "iso:country":"CA",
    "sg:address":"30 Main St",
    "sg:city":"Emerson",
    "sg:classifiers":[
        {
            "category":"Banks & Credit Unions",
            "subcategory":"Bank",
            "type":"Services"
        }
    ],
    "sg:phone":"+1 204 373 2536",
    "sg:postcode":"R0A 0L0",
    "sg:province":"MB",
    "wof:name":"Scotiabank",
    "wof:placetype":"venue"
},
  "geometry": {"coordinates":[-97.204758,49.008976],"type":"Point"}
}