{
  "type": "Feature",
  "properties": {
    "addr:full":"7153 West Saanich Rd Brentwood Bay BC V8M 1P7",
    "addr:housenumber":"7153",
    "addr:postcode":"v8m 1p7",
    "addr:street":"West Saanich Rd",
    "iso:country":"CA",
    "sg:address":"7153 West Saanich Rd",
    "sg:city":"Brentwood Bay",
    "sg:classifiers":[
        {
            "category":"Retail",
            "subcategory":"Veterinary Services",
            "type":"Services"
        }
    ],
    "sg:phone":"+1 250 652 3131",
    "sg:postcode":"V8M 1P7",
    "sg:province":"BC",
    "sg:tags":[
        "veterinarian"
    ],
    "wof:name":"Brentwood Bay Veterinary Hosp",
    "wof:placetype":"venue"
},
  "geometry": {"coordinates":[-123.447540283,48.5769424438],"type":"Point"}
}