{
  "type": "Feature",
  "properties": {
    "addr:full":"2260 Rue Fleury E Montreal QC H2B 1K6",
    "addr:housenumber":"2260",
    "addr:postcode":"h2b 1k6",
    "addr:street":"Rue Fleury E",
    "iso:country":"CA",
    "sg:address":"2260 Rue Fleury E",
    "sg:city":"Montreal",
    "sg:classifiers":[
        {
            "category":"Restaurant",
            "type":"Food & Drink"
        }
    ],
    "sg:phone":"+1 514 388 1550",
    "sg:postcode":"H2B 1K6",
    "sg:province":"QC",
    "wof:name":"Restaurant Au Petit Coq",
    "wof:placetype":"venue"
},
  "geometry": {"coordinates":[-73.64928399999999,45.573219],"type":"Point"}
}