{
  "type": "Feature",
  "properties": {
    "iso:country":"CA",
    "sg:city":"Sainte-Claire",
    "sg:classifiers":[
        {
            "category":"Freight",
            "type":"Transportation"
        }
    ],
    "sg:phone":"+1 418 883 3121",
    "sg:postcode":"G0R 2V0",
    "sg:province":"QC",
    "sg:tags":[
        "trucking"
    ],
    "wof:name":"M V Express Inc",
    "wof:placetype":"venue"
},
  "geometry": {"coordinates":[-70.83270263670001,46.5933876038],"type":"Point"}
}