{
  "type": "Feature",
  "properties": {
    "addr:full":"20 Rue Perreault Saint-Jerome QC J7Z 5R9",
    "addr:housenumber":"20",
    "addr:postcode":"j7z 5r9",
    "addr:street":"Rue Perreault Saint-Jerome",
    "iso:country":"CA",
    "sg:address":"20 Rue Perreault",
    "sg:city":"Saint-Jerome",
    "sg:classifiers":[
        {
            "category":"Building & Trades",
            "subcategory":"Cleaning & Sanitation",
            "type":"Services"
        }
    ],
    "sg:phone":"+1 450 569 6690",
    "sg:postcode":"J7Z 5R9",
    "sg:province":"QC",
    "sg:tags":[
        "venetian",
        "blind"
    ],
    "wof:name":"Lav-Store me Enr",
    "wof:placetype":"venue"
},
  "geometry": {"coordinates":[-74.004745,45.773514],"type":"Point"}
}