{
  "type": "Feature",
  "properties": {
    "addr:full":"17680 Hwy 7 Perth ON K7H 3C5",
    "addr:housenumber":"17680",
    "addr:postcode":"k7h 3c5",
    "addr:street":"Hwy 7",
    "iso:country":"CA",
    "sg:address":"17680 Hwy 7",
    "sg:city":"Perth",
    "sg:classifiers":[
        {
            "category":"Retail",
            "subcategory":"Auto Repair",
            "type":"Services"
        }
    ],
    "sg:phone":"+1 613 264 9179",
    "sg:postcode":"K7H 3C5",
    "sg:province":"ON",
    "sg:tags":[
        "repairing",
        "automobile"
    ],
    "wof:name":"K & M Automotive",
    "wof:placetype":"venue"
},
  "geometry": {"coordinates":[-76.25949900000001,44.912979],"type":"Point"}
}