{
  "type": "Feature",
  "properties": {
    "addr:full":"8960 Charles St Richmond BC V6X 1W1",
    "addr:housenumber":"8960",
    "addr:postcode":"v6x 1w1",
    "addr:street":"Charles St",
    "iso:country":"CA",
    "sg:address":"8960 Charles St",
    "sg:city":"Richmond",
    "sg:classifiers":[
        {
            "category":"Manufacturing",
            "subcategory":"Paper Products",
            "type":"Manufacturing & Wholesale Goods"
        }
    ],
    "sg:phone":"+1 604 276 9888",
    "sg:postcode":"V6X 1W1",
    "sg:province":"BC",
    "sg:tags":[
        "label"
    ],
    "wof:name":"Aries Label CO Ltd",
    "wof:placetype":"venue"
},
  "geometry": {"coordinates":[-123.12606,49.194485],"type":"Point"}
}