{
  "type": "Feature",
  "properties": {
    "addr:full":"Waterdown ON L0R 2H0",
    "addr:postcode":"l0r 2h0",
    "iso:country":"CA",
    "sg:city":"Waterdown",
    "sg:classifiers":[
        {
            "category":"Organizations",
            "subcategory":"Professional Association",
            "type":"Services"
        }
    ],
    "sg:phone":"+1 905 689 6112",
    "sg:postcode":"L0R 2H0",
    "sg:province":"ON",
    "sg:tags":[
        "club"
    ],
    "wof:name":"Royal Canadian Legion",
    "wof:placetype":"venue"
},
  "geometry": {"coordinates":[-79.899574,43.333645],"type":"Point"}
}