{
  "type": "Feature",
  "properties": {
    "addr:full":"516 Topsail Rd St. John's NL A1E 2C5",
    "addr:housenumber":"516",
    "addr:postcode":"a1e 2c5",
    "addr:street":"Topsail Rd",
    "iso:country":"CA",
    "sg:address":"516 Topsail Rd",
    "sg:city":"St. John's",
    "sg:classifiers":[
        {
            "category":"Education",
            "subcategory":"Special Training",
            "type":"Public Place"
        }
    ],
    "sg:phone":"+1 709 364 1679",
    "sg:postcode":"A1E 2C5",
    "sg:province":"NL",
    "sg:tags":[
        "instruction",
        "music"
    ],
    "wof:name":"Murphy Marilyn School of Music",
    "wof:placetype":"venue"
},
  "geometry": {"coordinates":[-52.757713,47.530491],"type":"Point"}
}