{
  "type": "Feature",
  "properties": {
    "addr:full":"Courtenay BC V9N 8M9",
    "addr:postcode":"v9n 8m9",
    "iso:country":"CA",
    "sg:city":"Courtenay",
    "sg:classifiers":[
        {
            "category":"Professional",
            "subcategory":"Testing Lab",
            "type":"Services"
        }
    ],
    "sg:phone":"+1 250 338 7786",
    "sg:postcode":"V9N 8M9",
    "sg:province":"BC",
    "sg:tags":[
        "laboratory"
    ],
    "wof:name":"North Island Laboratories",
    "wof:placetype":"venue"
},
  "geometry": {"coordinates":[-124.98683200000001,49.671535],"type":"Point"}
}