{
  "type": "Feature",
  "properties": {
    "addr:full":"1000 Waasis Rd Oromocto NB E2V 2P3",
    "addr:housenumber":"1000",
    "addr:postcode":"e2v 2p3",
    "addr:street":"Waasis Rd",
    "iso:country":"CA",
    "sg:address":"1000 Waasis Rd",
    "sg:city":"Oromocto",
    "sg:classifiers":[
        {
            "category":"Food & Beverages",
            "subcategory":"Groceries & Convenience Stores",
            "type":"Retail Goods"
        }
    ],
    "sg:phone":"+1 506 357 2777",
    "sg:postcode":"E2V 2P3",
    "sg:province":"NB",
    "wof:name":"Freeman's Convenience Store",
    "wof:placetype":"venue"
},
  "geometry": {"coordinates":[-66.519402,45.83276],"type":"Point"}
}