{
  "type": "Feature",
  "properties": {
    "addr:full":"795 University Ave W Windsor ON N9A 5R8",
    "addr:housenumber":"795",
    "addr:postcode":"n9a 5r8",
    "addr:street":"University Ave W",
    "iso:country":"CA",
    "sg:address":"795 University Ave W",
    "sg:city":"Windsor",
    "sg:classifiers":[
        {
            "category":"Wholesale",
            "subcategory":"Poultry",
            "type":"Manufacturing & Wholesale Goods"
        }
    ],
    "sg:phone":"+1 519 256 2341",
    "sg:postcode":"N9A 5R8",
    "sg:province":"ON",
    "sg:tags":[
        "eggs"
    ],
    "wof:name":"Thomson Produce",
    "wof:placetype":"venue"
},
  "geometry": {"coordinates":[-83.048164,42.315052],"type":"Point"}
}