{
  "type": "Feature",
  "properties": {
    "iso:country":"CA",
    "sg:address":"555 Rue Martin-Bouvard",
    "sg:city":"Chicoutimi",
    "sg:classifiers":[
        {
            "category":"Freight",
            "type":"Transportation"
        }
    ],
    "sg:phone":"+1 418 698 8722",
    "sg:postcode":"G7J 4N9",
    "sg:province":"QC",
    "sg:tags":[
        "trucking"
    ],
    "wof:name":"Transporteurs En Vrac DE",
    "wof:placetype":"venue"
},
  "geometry": {"coordinates":[-71.0884552002,48.4117698669],"type":"Point"}
}