{
  "type": "Feature",
  "properties": {
    "addr:full":"508 Front Ave Manitou MB R0G 1G0",
    "addr:housenumber":"508",
    "addr:postcode":"r0g 1g0",
    "addr:street":"Front Ave",
    "iso:country":"CA",
    "sg:address":"508 Front Ave",
    "sg:city":"Manitou",
    "sg:classifiers":[
        {
            "category":"Home & Garden",
            "subcategory":"Building Materials",
            "type":"Retail Goods"
        }
    ],
    "sg:phone":"+1 204 242 2538",
    "sg:postcode":"R0G 1G0",
    "sg:province":"MB",
    "sg:tags":[
        "lumber"
    ],
    "wof:name":"Manitou Building Ctr Ltd",
    "wof:placetype":"venue"
},
  "geometry": {"coordinates":[-98.53465271,49.2367210388],"type":"Point"}
}