{
  "type": "Feature",
  "properties": {
    "iso:country":"CA",
    "sg:address":"100 Av DE L'Eglise",
    "sg:city":"Dolbeau-Mistassini",
    "sg:classifiers":[
        {
            "category":"Shopping",
            "subcategory":"Jewelry",
            "type":"Retail Goods"
        }
    ],
    "sg:phone":"+1 418 276 2437",
    "sg:postcode":"G8L 4W4",
    "sg:province":"QC",
    "sg:tags":[
        "jeweler"
    ],
    "wof:name":"Bijouterie Norbert Sasseville",
    "wof:placetype":"venue"
},
  "geometry": {"coordinates":[-72.20044708250001,48.8933486938],"type":"Point"}
}