{
  "type": "Feature",
  "properties": {
    "addr:full":"166 John St S Hamilton ON L8N 2C4",
    "addr:housenumber":"166",
    "addr:postcode":"l8n 2c4",
    "addr:street":"John St S",
    "iso:country":"CA",
    "sg:address":"166 John St S",
    "sg:city":"Hamilton",
    "sg:classifiers":[
        {
            "category":"Real Estate",
            "subcategory":"Real Estate Agent",
            "type":"Services"
        }
    ],
    "sg:phone":"+1 905 528 9841",
    "sg:postcode":"L8N 2C4",
    "sg:province":"ON",
    "wof:name":"Cupido Realty Inc",
    "wof:placetype":"venue"
},
  "geometry": {"coordinates":[-79.86846160890001,43.2517356873],"type":"Point"}
}