{
  "type": "Feature",
  "properties": {
    "addr:full":"Calgary AB T2E 6V2",
    "addr:postcode":"t2e 6v2",
    "iso:country":"CA",
    "sg:city":"Calgary",
    "sg:classifiers":[
        {
            "category":"Shopping",
            "subcategory":"Computers & Home Electronics",
            "type":"Retail Goods"
        }
    ],
    "sg:phone":"+1 403 250 8127",
    "sg:postcode":"T2E 6V2",
    "sg:province":"AB",
    "sg:tags":[
        "equipment",
        "dealer"
    ],
    "wof:name":"Infinite Computers Corp",
    "wof:placetype":"venue"
},
  "geometry": {"coordinates":[-114.011475,51.084827],"type":"Point"}
}