{
  "type": "Feature",
  "properties": {
    "addr:full":"18 Rue Leroy Repentigny QC J6A 1P6",
    "addr:housenumber":"18",
    "addr:postcode":"j6a 1p6",
    "addr:street":"Rue Leroy",
    "iso:country":"CA",
    "sg:address":"18 Rue Leroy",
    "sg:city":"Repentigny",
    "sg:classifiers":[
        {
            "category":"Professional",
            "subcategory":"Computer Services",
            "type":"Services"
        }
    ],
    "sg:phone":"+1 450 654 1157",
    "sg:postcode":"J6A 1P6",
    "sg:province":"QC",
    "sg:tags":[
        "consultant"
    ],
    "wof:name":"Infologique Lc",
    "wof:placetype":"venue"
},
  "geometry": {"coordinates":[-73.4713439941,45.7272987366],"type":"Point"}
}