{
  "type": "Feature",
  "properties": {
    "addr:full":"806 Centre St NE Calgary AB T2E 8K1",
    "addr:housenumber":"806",
    "addr:postcode":"t2e 8k1",
    "addr:street":"Centre St Ne",
    "iso:country":"CA",
    "sg:address":"806 Centre St NE",
    "sg:city":"Calgary",
    "sg:classifiers":[
        {
            "category":"Restaurant",
            "type":"Food & Drink"
        }
    ],
    "sg:phone":"+1 403 276 3288",
    "sg:postcode":"T2E 8K1",
    "sg:province":"AB",
    "wof:name":"Happy Hill",
    "wof:placetype":"venue"
},
  "geometry": {"coordinates":[-114.04409,51.052567],"type":"Point"}
}