{
  "type": "Feature",
  "properties": {
    "iso:country":"CA",
    "sg:address":"51 Jardin Dr",
    "sg:city":"Concord",
    "sg:classifiers":[
        {
            "category":"Manufacturing",
            "subcategory":"Food",
            "type":"Manufacturing & Wholesale Goods"
        }
    ],
    "sg:phone":"+1 416 736 0585",
    "sg:postcode":"L4K 1X5",
    "sg:province":"ON",
    "sg:tags":[
        "product",
        "manufacturer"
    ],
    "wof:name":"Milano Foods & Biscuits Ltd",
    "wof:placetype":"venue"
},
  "geometry": {"coordinates":[-79.496277,43.795784],"type":"Point"}
}