{
  "type": "Feature",
  "properties": {
    "addr:full":"PO Box 5000 STN Main Waterville NS B0P 1V0",
    "addr:housenumber":"po",
    "addr:postcode":"b0p 1v0",
    "addr:street":"Box 5000 Stn Main",
    "iso:country":"CA",
    "sg:address":"PO Box 5000 STN Main",
    "sg:city":"Waterville",
    "sg:classifiers":[
        {
            "category":"Wholesale",
            "subcategory":"Auto Parts",
            "type":"Manufacturing & Wholesale Goods"
        }
    ],
    "sg:phone":"+1 902 538 8021",
    "sg:postcode":"B0P 1V0",
    "sg:province":"NS",
    "sg:tags":[
        "tire"
    ],
    "wof:name":"Michelin North America Inc",
    "wof:placetype":"venue"
},
  "geometry": {"coordinates":[-64.677437,45.048206],"type":"Point"}
}