{
  "type": "Feature",
  "properties": {
    "iso:country":"CA",
    "sg:address":"167 Rue Carrefour",
    "sg:city":"Fermont",
    "sg:classifiers":[
        {
            "category":"Wholesale",
            "subcategory":"Vending Machines",
            "type":"Manufacturing & Wholesale Goods"
        }
    ],
    "sg:phone":"+1 418 287 3311",
    "sg:postcode":"G0G 1J0",
    "sg:province":"QC",
    "wof:name":"Landry Amusement Inc",
    "wof:placetype":"venue"
},
  "geometry": {"coordinates":[-67.086929,52.795433],"type":"Point"}
}