{
  "type": "Feature",
  "properties": {
    "addr:full":"76 14E Rue Pl Laval QC H7N 1M1",
    "addr:housenumber":"76",
    "addr:postcode":"h7n 1m1",
    "addr:street":"14E Rue Pl",
    "iso:country":"CA",
    "sg:address":"76 14E Rue Pl",
    "sg:city":"Laval",
    "sg:classifiers":[
        {
            "category":"Building & Trades",
            "subcategory":"Landscaping Services",
            "type":"Services"
        }
    ],
    "sg:phone":"+1 450 663 0777",
    "sg:postcode":"H7N 1M1",
    "sg:province":"QC",
    "sg:tags":[
        "landscape",
        "contractor"
    ],
    "wof:name":"Entretien Paysage Darma",
    "wof:placetype":"venue"
},
  "geometry": {"coordinates":[-73.695465,45.56654],"type":"Point"}
}