{
  "type": "Feature",
  "properties": {
    "addr:full":"12432 87 St NW Edmonton AB T5B 3P3",
    "addr:housenumber":"12432",
    "addr:postcode":"t5b 3p3",
    "addr:street":"87 St Nw",
    "iso:country":"CA",
    "sg:address":"12432 87 St NW",
    "sg:city":"Edmonton",
    "sg:classifiers":[
        {
            "category":"Organizations",
            "subcategory":"Religious Organization",
            "type":"Services"
        }
    ],
    "sg:phone":"+1 780 471 2425",
    "sg:postcode":"T5B 3P3",
    "sg:province":"AB",
    "sg:tags":[
        "church"
    ],
    "wof:name":"Edmonton Living Word Assembly",
    "wof:placetype":"venue"
},
  "geometry": {"coordinates":[-113.474541,53.580284],"type":"Point"}
}