{
  "type": "Feature",
  "properties": {
    "addr:full":"Toronto ON M4V 1W6",
    "addr:postcode":"m4v 1w6",
    "iso:country":"CA",
    "sg:city":"Toronto",
    "sg:classifiers":[
        {
            "category":"Manufacturing",
            "subcategory":"Printing",
            "type":"Manufacturing & Wholesale Goods"
        }
    ],
    "sg:phone":"+1 416 545 0277",
    "sg:postcode":"M4V 1W6",
    "sg:province":"ON",
    "sg:tags":[
        "printer"
    ],
    "wof:name":"Ucc Press",
    "wof:placetype":"venue"
},
  "geometry": {"coordinates":[-79.403595,43.690807],"type":"Point"}
}