{
  "type": "Feature",
  "properties": {
    "addr:full":"30 Ch Du Golf O Saint-Charles-Borromee QC J6E 8X6",
    "addr:housenumber":"30",
    "addr:postcode":"j6e 8x6",
    "addr:street":"Ch Du Golf O Saint-Charles-Borromee",
    "iso:country":"CA",
    "sg:address":"30 Ch Du Golf O",
    "sg:city":"Saint-Charles-Borromee",
    "sg:classifiers":[
        {
            "category":"Health Services",
            "subcategory":"Health Practitioner",
            "type":"Services"
        }
    ],
    "sg:phone":"+1 450 752 2467",
    "sg:postcode":"J6E 8X6",
    "sg:province":"QC",
    "sg:tags":[
        "orthopedic",
        "appliance"
    ],
    "wof:name":"Laboratoires Bi-Op Inc",
    "wof:placetype":"venue"
},
  "geometry": {"coordinates":[-73.448402,46.043221],"type":"Point"}
}