{
  "type": "Feature",
  "properties": {
    "addr:full":"Yamachiche QC G0X 3L0",
    "addr:postcode":"g0x 3l0",
    "iso:country":"CA",
    "sg:city":"Yamachiche",
    "sg:classifiers":[
        {
            "category":"Restaurant",
            "type":"Food & Drink"
        }
    ],
    "sg:phone":"+1 819 228 9434",
    "sg:postcode":"G0X 3L0",
    "sg:province":"QC",
    "wof:name":"Porte DE LA Mauricie",
    "wof:placetype":"venue"
},
  "geometry": {"coordinates":[-72.769867,46.292706],"type":"Point"}
}